{
  "type": "Feature",
  "properties": {
    "addr:full":"74 Mayne St Murrurundi NSW 2338",
    "addr:housenumber":"74",
    "addr:postcode":"2338",
    "addr:street":"Mayne St",
    "iso:country":"AU",
    "sg:address":"74 Mayne St",
    "sg:city":"Murrurundi",
    "sg:classifiers":[
        {
            "category":"Education",
            "subcategory":"Kindergarten",
            "type":"Public Place"
        }
    ],
    "sg:phone":"+61 2 6546 6212",
    "sg:postcode":"2338",
    "sg:province":"NSW",
    "sg:tags":[
        "pre-schools"
    ],
    "wof:name":"Murrurundi Pre-School Kindergarten",
    "wof:placetype":"venue"
},
  "geometry": {"coordinates":[150.83074951200001,-31.7611713409],"type":"Point"}
}