{
  "type": "Feature",
  "properties": {
    "addr:full":"PO Box 1 Newstead VIC 3462",
    "addr:postcode":"3462",
    "iso:country":"AU",
    "sg:address":"PO Box 1",
    "sg:city":"Newstead",
    "sg:classifiers":[
        {
            "category":"Utilities",
            "subcategory":"Electric",
            "type":"Services"
        }
    ],
    "sg:phone":"+61 3 5476 2455",
    "sg:postcode":"3462",
    "sg:province":"VIC",
    "sg:tags":[
        "electrical",
        "contractor"
    ],
    "wof:name":"Rowland J.H.",
    "wof:placetype":"venue"
},
  "geometry": {"coordinates":[144.06175231899999,-37.106590271],"type":"Point"}
}