{
  "type": "Feature",
  "properties": {
    "addr:full":"2 Carrajung St Rosebud VIC 3939",
    "addr:housenumber":"2",
    "addr:postcode":"3939",
    "addr:street":"Carrajung St",
    "iso:country":"AU",
    "sg:address":"2 Carrajung St",
    "sg:city":"Rosebud",
    "sg:classifiers":[
        {
            "category":"Communications",
            "subcategory":"Film & Video Production",
            "type":"Services"
        }
    ],
    "sg:phone":"+61 3 5986 2071",
    "sg:postcode":"3939",
    "sg:province":"VIC",
    "sg:tags":[
        "yacht",
        "transport",
        "boat"
    ],
    "wof:name":"Ocean Reef Dive Services",
    "wof:placetype":"venue"
},
  "geometry": {"coordinates":[144.92611694300001,-38.3786125183],"type":"Point"}
}