{
  "type": "Feature",
  "properties": {
    "addr:full":"PO Box 2240 Kardinya WA 6163",
    "addr:postcode":"6163",
    "iso:country":"AU",
    "sg:address":"PO Box 2240",
    "sg:city":"Kardinya",
    "sg:classifiers":[
        {
            "category":"Arena",
            "subcategory":"Sports Club",
            "type":"Entertainment"
        }
    ],
    "sg:phone":"+61 8 9418 2227",
    "sg:postcode":"6163",
    "sg:province":"WA",
    "sg:tags":[
        "defence",
        "supply",
        "self",
        "instruction",
        "martial art"
    ],
    "wof:name":"Universal Tao Centre WA",
    "wof:placetype":"venue"
},
  "geometry": {"coordinates":[115.81944300000001,-32.067749],"type":"Point"}
}