{
  "type": "Feature",
  "properties": {
    "iso:country":"AU",
    "sg:address":"35A Cato St",
    "sg:city":"Prahran",
    "sg:classifiers":[
        {
            "category":"Personal",
            "subcategory":"Hair Removal",
            "type":"Services"
        }
    ],
    "sg:phone":"+61 3 9529 4559",
    "sg:postcode":"3181",
    "sg:province":"VIC",
    "wof:name":"Betty Ford Clinic",
    "wof:placetype":"venue"
},
  "geometry": {"coordinates":[144.99299621599999,-37.8473548889],"type":"Point"}
}