{
  "type": "Feature",
  "properties": {
    "addr:full":"Creamery Rd Tyntynder South VIC 3586",
    "addr:postcode":"3586",
    "addr:street":"Creamery Rd",
    "iso:country":"AU",
    "sg:address":"Creamery Rd",
    "sg:city":"Tyntynder South",
    "sg:classifiers":[
        {
            "category":"Manufacturing",
            "subcategory":"Motor Vehicles & Parts",
            "type":"Manufacturing & Wholesale Goods"
        }
    ],
    "sg:phone":"+61 3 5037 6405",
    "sg:postcode":"3586",
    "sg:province":"VIC",
    "sg:tags":[
        "engine",
        "equipment",
        "diesel"
    ],
    "wof:name":"Shoey Diesel",
    "wof:placetype":"venue"
},
  "geometry": {"coordinates":[143.517410278,-35.273979187],"type":"Point"}
}