{
  "type": "Feature",
  "properties": {
    "iso:country":"AU",
    "sg:address":"Unit 3, 9 Commerce Crt",
    "sg:city":"Noosaville",
    "sg:classifiers":[
        {
            "category":"Manufacturing",
            "subcategory":"Electronics",
            "type":"Manufacturing & Wholesale Goods"
        }
    ],
    "sg:phone":"+61 7 5447 1752",
    "sg:postcode":"4566",
    "sg:province":"QLD",
    "sg:tags":[
        "oven",
        "microwave"
    ],
    "wof:name":"Noosa T.V. & Video Repairs",
    "wof:placetype":"venue"
},
  "geometry": {"coordinates":[153.04600524899999,-26.4116668701],"type":"Point"}
}