{
  "type": "Feature",
  "properties": {
    "addr:full":"Shop3 b 710 Nicklin Way Currimundi QLD 4551",
    "addr:housenumber":"710",
    "addr:postcode":"4551",
    "addr:street":"Nicklin Way",
    "iso:country":"AU",
    "sg:address":"Shop3 b 710",
    "sg:city":"Nicklin Way Currimundi",
    "sg:classifiers":[
        {
            "category":"Personal",
            "subcategory":"Beauty Salon",
            "type":"Services"
        }
    ],
    "sg:phone":"+61 7 5437 6177",
    "sg:postcode":"4551",
    "sg:province":"QLD",
    "sg:tags":[
        "hairdresser"
    ],
    "wof:name":"Deanies Kids Cuts",
    "wof:placetype":"venue"
},
  "geometry": {"coordinates":[153.12203979500001,-26.7688465118],"type":"Point"}
}