{
  "type": "Feature",
  "properties": {
    "addr:full":"618 South Rd Angle Park SA 5010",
    "addr:housenumber":"618",
    "addr:postcode":"5010",
    "addr:street":"South Rd",
    "iso:country":"AU",
    "sg:address":"618 South Rd",
    "sg:city":"Angle Park",
    "sg:phone":"+61 8 8445 7822",
    "sg:postcode":"5010",
    "sg:province":"SA",
    "sg:website":"http://www.ri-industries.com.au",
    "wof:name":"Ri-Industries",
    "wof:placetype":"venue"
},
  "geometry": {"coordinates":[138.564743042,-34.854927063],"type":"Point"}
}