{
  "type": "Feature",
  "properties": {
    "addr:full":"7 Walter St Sale VIC 3850",
    "addr:housenumber":"7",
    "addr:postcode":"3850",
    "addr:street":"Walter St",
    "iso:country":"AU",
    "sg:address":"7 Walter St",
    "sg:city":"Sale",
    "sg:classifiers":[
        {
            "category":"Retail",
            "subcategory":"Auto Repair",
            "type":"Services"
        }
    ],
    "sg:phone":"+61 3 5143 0557",
    "sg:postcode":"3850",
    "sg:province":"VIC",
    "sg:tags":[
        "repairer",
        "motor",
        "engineer"
    ],
    "wof:name":"Quality Vehicle Maintenance & Repairs",
    "wof:placetype":"venue"
},
  "geometry": {"coordinates":[147.071044922,-38.1150932312],"type":"Point"}
}