{
  "type": "Feature",
  "properties": {
    "addr:full":"Ste 231/ 1 Katherine St Chatswood NSW 2067",
    "addr:housenumber":"/ 1",
    "addr:postcode":"2067",
    "addr:street":"Katherine St",
    "iso:country":"AU",
    "sg:address":"Ste 231/ 1 Katherine St",
    "sg:city":"Chatswood",
    "sg:classifiers":[
        {
            "category":"Health Services",
            "subcategory":"Health Practitioner",
            "type":"Services"
        }
    ],
    "sg:phone":"+61 414 913 653",
    "sg:postcode":"2067",
    "sg:province":"NSW",
    "sg:tags":[
        "psychologist"
    ],
    "wof:name":"Chatswood Counselling & Assessment Centre",
    "wof:placetype":"venue"
},
  "geometry": {"coordinates":[151.17962646500001,-33.7977561951],"type":"Point"}
}