{
  "type": "Feature",
  "properties": {
    "iso:country":"AU",
    "sg:address":"72 Harpenden St",
    "sg:city":"Huntingdale",
    "sg:classifiers":[
        {
            "category":"Government",
            "subcategory":"Department Of Motor Vehicles",
            "type":"Public Place"
        }
    ],
    "sg:phone":"+61 8 9490 2020",
    "sg:postcode":"6110",
    "sg:province":"WA",
    "sg:tags":[
        "wholesaler",
        "mfrs",
        "accessory"
    ],
    "wof:name":"Pozsteer Balljoint Reconditioners",
    "wof:placetype":"venue"
},
  "geometry": {"coordinates":[115.963653565,-32.0794754028],"type":"Point"}
}