{
  "type": "Feature",
  "properties": {
    "iso:country":"AU",
    "sg:address":"Unit 1609, 265 Exhibition St",
    "sg:city":"Melbourne",
    "sg:classifiers":[
        {
            "category":"Banks & Credit Unions",
            "subcategory":"Investment Brokerage",
            "type":"Services"
        }
    ],
    "sg:phone":"+61 3 9639 8539",
    "sg:postcode":"3000",
    "sg:province":"VIC",
    "wof:name":"Mirisklavos Nominess Pty Ltd",
    "wof:placetype":"venue"
},
  "geometry": {"coordinates":[144.96925354000001,-37.8095550537],"type":"Point"}
}