{
  "type": "Feature",
  "properties": {
    "addr:full":"180 Flinders St Adelaide SA 5000",
    "addr:housenumber":"180",
    "addr:postcode":"5000",
    "addr:street":"Flinders St",
    "iso:country":"AU",
    "sg:address":"180 Flinders St",
    "sg:city":"Adelaide",
    "sg:classifiers":[
        {
            "category":"Banks & Credit Unions",
            "subcategory":"Financial Services",
            "type":"Services"
        }
    ],
    "sg:phone":"+61 8 8232 0003",
    "sg:postcode":"5000",
    "sg:province":"SA",
    "sg:tags":[
        "registrar",
        "share"
    ],
    "wof:name":"National Shareholder Services Pty Ltd",
    "wof:placetype":"venue"
},
  "geometry": {"coordinates":[138.60731506400001,-34.9266471863],"type":"Point"}
}