{
  "type": "Feature",
  "properties": {
    "addr:full":"47 Annesley Ave Trinity Gardens SA 5068",
    "addr:housenumber":"47",
    "addr:postcode":"5068",
    "addr:street":"Annesley Ave Trinity Gardens",
    "iso:country":"AU",
    "sg:address":"47 Annesley Ave",
    "sg:city":"Trinity Gardens",
    "sg:classifiers":[
        {
            "category":"Utilities",
            "subcategory":"Refuse",
            "type":"Services"
        }
    ],
    "sg:phone":"+61 8 8364 1774",
    "sg:postcode":"5068",
    "sg:province":"SA",
    "sg:tags":[
        "remover",
        "rubbish"
    ],
    "wof:name":"Australian Littersack Corporation Pty Ltd",
    "wof:placetype":"venue"
},
  "geometry": {"coordinates":[138.642486572,-34.9103469849],"type":"Point"}
}