{
  "type": "Feature",
  "properties": {
    "addr:full":"10 Observation Drv Highbury SA 5089",
    "addr:housenumber":"10",
    "addr:postcode":"5089",
    "addr:street":"Observation Drv",
    "iso:country":"AU",
    "sg:address":"10 Observation Drv",
    "sg:city":"Highbury",
    "sg:classifiers":[
        {
            "category":"Building & Trades",
            "subcategory":"Construction",
            "type":"Services"
        }
    ],
    "sg:phone":"+61 410 725 826",
    "sg:postcode":"5089",
    "sg:province":"SA",
    "sg:tags":[
        "plasterboard",
        "plasterer",
        "fixer"
    ],
    "wof:name":"SA Renderman",
    "wof:placetype":"venue"
},
  "geometry": {"coordinates":[138.68838500999999,-34.8603134155],"type":"Point"}
}