{
  "type": "Feature",
  "properties": {
    "addr:full":"8/ 115 Ambleside Cct Warners Bay NSW 2282",
    "addr:housenumber":"/ 115",
    "addr:postcode":"2282",
    "addr:street":"Ambleside Cct",
    "iso:country":"AU",
    "sg:address":"8/ 115",
    "sg:city":"Ambleside Cct Warners Bay",
    "sg:classifiers":[
        {
            "category":"Banks & Credit Unions",
            "subcategory":"Bank",
            "type":"Services"
        }
    ],
    "sg:phone":"+61 2 4956 9909",
    "sg:postcode":"2282",
    "sg:province":"NSW",
    "sg:tags":[
        "broker",
        "mortgage"
    ],
    "wof:name":"Home Loan Connexion",
    "wof:placetype":"venue"
},
  "geometry": {"coordinates":[151.65034484899999,-32.9655227661],"type":"Point"}
}