{
  "type": "Feature",
  "properties": {
    "iso:country":"AU",
    "sg:address":"14 Edenmont Rd",
    "sg:city":"Clematis",
    "sg:classifiers":[
        {
            "category":"Building & Trades",
            "subcategory":"Plumbing",
            "type":"Services"
        }
    ],
    "sg:phone":"+61 428 542 806",
    "sg:postcode":"3782",
    "sg:province":"VIC",
    "sg:tags":[
        "plumber",
        "gasfitters"
    ],
    "wof:name":"Hiace Plumbing",
    "wof:placetype":"venue"
},
  "geometry": {"coordinates":[145.42804,-37.924122],"type":"Point"}
}