{
  "type": "Feature",
  "properties": {
    "addr:full":"PO Box 664 Carlton VIC 3053",
    "addr:postcode":"3053",
    "iso:country":"AU",
    "sg:address":"PO Box 664",
    "sg:city":"Carlton",
    "sg:classifiers":[
        {
            "category":"Professional",
            "subcategory":"Detective & Security Services",
            "type":"Services"
        }
    ],
    "sg:phone":"+61 3 9354 2982",
    "sg:postcode":"3053",
    "sg:province":"VIC",
    "sg:tags":[
        "consultant",
        "system"
    ],
    "wof:name":"Executive Assurance & Threat Management Pty Ltd",
    "wof:placetype":"venue"
},
  "geometry": {"coordinates":[144.967086792,-37.8000907898],"type":"Point"}
}