{
  "type": "Feature",
  "properties": {
    "addr:full":"997 Moorooduc Hwy Moorooduc VIC 3933",
    "addr:housenumber":"997",
    "addr:postcode":"3933",
    "addr:street":"Moorooduc Hwy",
    "iso:country":"AU",
    "sg:address":"997 Moorooduc Hwy",
    "sg:city":"Moorooduc",
    "sg:classifiers":[
        {
            "category":"Retail",
            "subcategory":"Auto Repair",
            "type":"Services"
        }
    ],
    "sg:phone":"+61 3 5978 8400",
    "sg:postcode":"3933",
    "sg:province":"VIC",
    "sg:tags":[
        "bus",
        "truck"
    ],
    "wof:name":"Peninsula Diesel Repairs",
    "wof:placetype":"venue"
},
  "geometry": {"coordinates":[145.07933044399999,-38.2544784546],"type":"Point"}
}