{
  "type": "Feature",
  "properties": {
    "iso:country":"AU",
    "sg:address":"2/ 35 Wellington St",
    "sg:city":"Cleveland",
    "sg:classifiers":[
        {
            "category":"Home & Garden",
            "subcategory":"Garden Supply",
            "type":"Retail Goods"
        }
    ],
    "sg:phone":"+61 7 3488 2855",
    "sg:postcode":"4163",
    "sg:province":"QLD",
    "sg:tags":[
        "equipment"
    ],
    "wof:name":"Outdoor Power Products Direct",
    "wof:placetype":"venue"
},
  "geometry": {"coordinates":[153.25567626899999,-27.5275287628],"type":"Point"}
}