{
  "type": "Feature",
  "properties": {
    "addr:full":"81 McIntyre Rd Nayook VIC 3821",
    "addr:housenumber":"81",
    "addr:postcode":"3821",
    "addr:street":"Mcintyre Rd",
    "iso:country":"AU",
    "sg:address":"81 McIntyre Rd",
    "sg:city":"Nayook",
    "sg:classifiers":[
        {
            "category":"Farming",
            "subcategory":"Berry Farm",
            "type":"Manufacturing & Wholesale Goods"
        }
    ],
    "sg:phone":"+61 3 5628 4337",
    "sg:postcode":"3821",
    "sg:province":"VIC",
    "sg:tags":[
        "fruit",
        "grower"
    ],
    "wof:name":"Nayook Fruit & Berry Farm",
    "wof:placetype":"venue"
},
  "geometry": {"coordinates":[146.06227100000001,-38.220596],"type":"Point"}
}