{
  "type": "Feature",
  "properties": {
    "addr:full":"12-14 Green St Thomastown VIC 3074",
    "addr:housenumber":"12-14",
    "addr:postcode":"3074",
    "addr:street":"Green St",
    "iso:country":"AU",
    "sg:address":"12-14 Green St",
    "sg:city":"Thomastown",
    "sg:classifiers":[
        {
            "category":"Manufacturing",
            "subcategory":"Building Materials",
            "type":"Manufacturing & Wholesale Goods"
        }
    ],
    "sg:phone":"+61 3 9465 0249",
    "sg:postcode":"3074",
    "sg:province":"VIC",
    "sg:tags":[
        "equipment",
        "handling"
    ],
    "sg:website":"http://www.annsir.com.au",
    "wof:name":"Annsir Engineering",
    "wof:placetype":"venue"
},
  "geometry": {"coordinates":[145.03826904300001,-37.6911430359],"type":"Point"}
}