{
  "type": "Feature",
  "properties": {
    "addr:full":"24 Norrie St Yennora NSW 2161",
    "addr:housenumber":"24",
    "addr:postcode":"2161",
    "addr:street":"Norrie St",
    "iso:country":"AU",
    "sg:address":"24 Norrie St",
    "sg:city":"Yennora",
    "sg:classifiers":[
        {
            "category":"Building & Trades",
            "subcategory":"Construction",
            "type":"Services"
        }
    ],
    "sg:phone":"+61 2 9632 3266",
    "sg:postcode":"2161",
    "sg:province":"NSW",
    "sg:tags":[
        "contractor"
    ],
    "wof:name":"M J S Constructions Pty Ltd",
    "wof:placetype":"venue"
},
  "geometry": {"coordinates":[150.969802856,-33.863910675],"type":"Point"}
}