{
  "type": "Feature",
  "properties": {
    "addr:full":"4 Coronation Ave Cardiff NSW 2285",
    "addr:housenumber":"4",
    "addr:postcode":"2285",
    "addr:street":"Coronation Ave",
    "iso:country":"AU",
    "sg:address":"4 Coronation Ave",
    "sg:city":"Cardiff",
    "sg:classifiers":[
        {
            "category":"Education",
            "subcategory":"Special Training",
            "type":"Public Place"
        }
    ],
    "sg:phone":"+61 2 4954 6494",
    "sg:postcode":"2285",
    "sg:province":"NSW",
    "sg:tags":[
        "school",
        "art"
    ],
    "wof:name":"Gina Ogrodnik",
    "wof:placetype":"venue"
},
  "geometry": {"coordinates":[151.669067383,-32.9476089478],"type":"Point"}
}