{
  "type": "Feature",
  "properties": {
    "addr:full":"Shop 2033 Westfield Liverpool NSW 2170",
    "addr:housenumber":"2033",
    "addr:postcode":"2170",
    "addr:street":"Westfield",
    "iso:country":"AU",
    "sg:address":"Shop 2033",
    "sg:city":"Westfield Liverpool",
    "sg:classifiers":[
        {
            "category":"Shopping",
            "subcategory":"Computers & Home Electronics",
            "type":"Retail Goods"
        }
    ],
    "sg:phone":"+61 2 9601 2774",
    "sg:postcode":"2170",
    "sg:province":"NSW",
    "sg:tags":[
        "hire",
        "video",
        "game"
    ],
    "wof:name":"Games Wizards The",
    "wof:placetype":"venue"
},
  "geometry": {"coordinates":[150.92414855999999,-33.9189300537],"type":"Point"}
}