{
  "type": "Feature",
  "properties": {
    "iso:country":"AU",
    "sg:address":"Unit 8, 42 Leighton Pl",
    "sg:city":"Hornsby",
    "sg:classifiers":[
        {
            "category":"Wholesale",
            "subcategory":"Electrical",
            "type":"Manufacturing & Wholesale Goods"
        }
    ],
    "sg:phone":"+61 2 9476 6966",
    "sg:postcode":"2077",
    "sg:province":"NSW",
    "sg:tags":[
        "wholesaler",
        "mfrs",
        "accessory"
    ],
    "wof:name":"Dasco Lighting",
    "wof:placetype":"venue"
},
  "geometry": {"coordinates":[151.11790466299999,-33.6945571899],"type":"Point"}
}