{
  "type": "Feature",
  "properties": {
    "addr:full":"PO Box 730 Gosford NSW 2250",
    "addr:postcode":"2250",
    "iso:country":"AU",
    "sg:address":"PO Box 730",
    "sg:city":"Gosford",
    "sg:classifiers":[
        {
            "category":"Arena",
            "subcategory":"Sports Club",
            "type":"Entertainment"
        }
    ],
    "sg:phone":"+61 418 277 051",
    "sg:postcode":"2250",
    "sg:province":"NSW",
    "sg:tags":[
        "australian",
        "football",
        "rule"
    ],
    "wof:name":"Black Diamond AFL Inc.",
    "wof:placetype":"venue"
},
  "geometry": {"coordinates":[151.34249877900001,-33.4237213135],"type":"Point"}
}