{
  "type": "Feature",
  "properties": {
    "addr:full":"PO Box 8 Leichhardt NSW 2040",
    "addr:postcode":"2040",
    "iso:country":"AU",
    "sg:address":"PO Box 8",
    "sg:city":"Leichhardt",
    "sg:classifiers":[
        {
            "category":"Social Services",
            "subcategory":"Retirement Home",
            "type":"Services"
        }
    ],
    "sg:phone":"+61 2 9564 5882",
    "sg:postcode":"2040",
    "sg:province":"NSW",
    "sg:tags":[
        "life",
        "coaching"
    ],
    "wof:name":"Jacqueline Hellyer",
    "wof:placetype":"venue"
},
  "geometry": {"coordinates":[151.158905,-33.883659],"type":"Point"}
}