{
  "type": "Feature",
  "properties": {
    "addr:full":"33 Marshall St Cobar NSW 2835",
    "addr:housenumber":"33",
    "addr:postcode":"2835",
    "addr:street":"Marshall St",
    "iso:country":"AU",
    "sg:address":"33 Marshall St",
    "sg:city":"Cobar",
    "sg:classifiers":[
        {
            "category":"Shopping",
            "subcategory":"Clothing, Apparel, & Fashions",
            "type":"Retail Goods"
        }
    ],
    "sg:phone":"+61 2 6836 1522",
    "sg:postcode":"2835",
    "sg:province":"NSW",
    "sg:tags":[
        "lady",
        "wear"
    ],
    "wof:name":"Ryec",
    "wof:placetype":"venue"
},
  "geometry": {"coordinates":[145.83938599999999,-31.497921],"type":"Point"}
}