{
  "type": "Feature",
  "properties": {
    "iso:country":"AU",
    "sg:address":"131 Main St",
    "sg:city":"Pakenham",
    "sg:classifiers":[
        {
            "category":"Communications",
            "subcategory":"Film & Video Production",
            "type":"Services"
        }
    ],
    "sg:phone":"+61 3 5941 1698",
    "sg:postcode":"3810",
    "sg:province":"VIC",
    "sg:tags":[
        "dvd",
        "library"
    ],
    "wof:name":"Video Busters",
    "wof:placetype":"venue"
},
  "geometry": {"coordinates":[145.48260500000001,-38.078587],"type":"Point"}
}