{
  "type": "Feature",
  "properties": {
    "iso:country":"AU",
    "sg:address":"4 Palari Rd",
    "sg:city":"Ocean Reef",
    "sg:classifiers":[
        {
            "category":"Building & Trades",
            "subcategory":"Plumbing",
            "type":"Services"
        }
    ],
    "sg:phone":"+61 8 9401 5864",
    "sg:postcode":"6027",
    "sg:province":"WA",
    "sg:tags":[
        "plumber",
        "gasfitters"
    ],
    "wof:name":"MG & T Palassis Plumbing & Gas",
    "wof:placetype":"venue"
},
  "geometry": {"coordinates":[115.743156433,-31.7671661377],"type":"Point"}
}