{
  "type": "Feature",
  "properties": {
    "addr:full":"124 Green Rd Regents Park QLD 4118",
    "addr:housenumber":"124",
    "addr:postcode":"4118",
    "addr:street":"Green Rd",
    "iso:country":"AU",
    "sg:address":"124 Green Rd",
    "sg:city":"Regents Park",
    "sg:classifiers":[
        {
            "category":"Manufacturing",
            "subcategory":"Building Materials",
            "type":"Manufacturing & Wholesale Goods"
        }
    ],
    "sg:phone":"+61 7 3809 4899",
    "sg:postcode":"4118",
    "sg:province":"QLD",
    "sg:tags":[
        "concrete",
        "product"
    ],
    "wof:name":"Casey John",
    "wof:placetype":"venue"
},
  "geometry": {"coordinates":[153.04879760700001,-27.6887168884],"type":"Point"}
}