{
  "type": "Feature",
  "properties": {
    "addr:full":"2289 Gold Coast Hwy Mermaid Beach QLD 4218",
    "addr:housenumber":"2289",
    "addr:postcode":"4218",
    "addr:street":"Gold Coast Hwy",
    "iso:country":"AU",
    "sg:address":"2289 Gold Coast Hwy",
    "sg:city":"Mermaid Beach",
    "sg:classifiers":[
        {
            "category":"Travel",
            "subcategory":"Hotels & Motels",
            "type":"Entertainment"
        }
    ],
    "sg:phone":"+61 7 5572 7733",
    "sg:postcode":"4218",
    "sg:province":"QLD",
    "wof:name":"Camelot Motel",
    "wof:placetype":"venue"
},
  "geometry": {"coordinates":[153.437774658,-28.0555286407],"type":"Point"}
}