{
  "type": "Feature",
  "properties": {
    "addr:full":"87- 89 Parramatta Rd Concord NSW 2137",
    "addr:housenumber":"89",
    "addr:postcode":"2137",
    "addr:street":"Parramatta Rd",
    "iso:country":"AU",
    "sg:address":"87- 89 Parramatta Rd",
    "sg:city":"Concord",
    "sg:classifiers":[
        {
            "category":"Retail",
            "subcategory":"Car Wash",
            "type":"Services"
        }
    ],
    "sg:phone":"+61 2 9744 6046",
    "sg:postcode":"2137",
    "sg:province":"NSW",
    "sg:tags":[
        "truck",
        "cleaning"
    ],
    "wof:name":"Caltex Complete Hand Car Wash",
    "wof:placetype":"venue"
},
  "geometry": {"coordinates":[151.099365234,-33.867980957],"type":"Point"}
}