{
  "type": "Feature",
  "properties": {
    "iso:country":"AU",
    "sg:address":"Suite 3.01 Platinum 4 Ilya Ave",
    "sg:city":"Erina",
    "sg:classifiers":[
        {
            "category":"Real Estate",
            "subcategory":"Developer",
            "type":"Services"
        }
    ],
    "sg:phone":"+61 2 4365 2700",
    "sg:postcode":"2250",
    "sg:province":"NSW",
    "sg:tags":[
        "development"
    ],
    "wof:name":"Phillip Brand Property Developer",
    "wof:placetype":"venue"
},
  "geometry": {"coordinates":[151.38421630900001,-33.4397659302],"type":"Point"}
}