{
  "type": "Feature",
  "properties": {
    "addr:full":"23 Ivy Ave Chain Valley Bay NSW 2259",
    "addr:housenumber":"23",
    "addr:postcode":"2259",
    "addr:street":"Ivy Ave",
    "iso:country":"AU",
    "sg:address":"23 Ivy Ave",
    "sg:city":"Chain Valley Bay",
    "sg:classifiers":[
        {
            "category":"Building & Trades",
            "subcategory":"Plumbing",
            "type":"Services"
        }
    ],
    "sg:phone":"+61 2 4358 8645",
    "sg:postcode":"2259",
    "sg:province":"NSW",
    "sg:tags":[
        "plumber",
        "gasfitters"
    ],
    "wof:name":"Boyd, Nat Plumbing",
    "wof:placetype":"venue"
},
  "geometry": {"coordinates":[151.560546875,-33.1757736206],"type":"Point"}
}