{
  "type": "Feature",
  "properties": {
    "iso:country":"AU",
    "sg:address":"36 Schapers Rd",
    "sg:city":"Glenella",
    "sg:classifiers":[
        {
            "category":"Home & Garden",
            "subcategory":"Carpets & Floor Coverings",
            "type":"Retail Goods"
        }
    ],
    "sg:phone":"+61 413 046 453",
    "sg:postcode":"4740",
    "sg:province":"QLD",
    "sg:tags":[
        "tile",
        "wall",
        "layer"
    ],
    "wof:name":"Noel Brecknell Tiling",
    "wof:placetype":"venue"
},
  "geometry": {"coordinates":[149.148712,-21.113167],"type":"Point"}
}