{
  "type": "Feature",
  "properties": {
    "iso:country":"AU",
    "sg:address":"4 Tooronga Rd",
    "sg:city":"Ringwood East",
    "sg:classifiers":[
        {
            "category":"Sports & Exercise",
            "subcategory":"Gym",
            "type":"Entertainment"
        }
    ],
    "sg:phone":"+61 412 097 102",
    "sg:postcode":"3135",
    "sg:province":"VIC",
    "sg:tags":[
        "health",
        "fitness"
    ],
    "wof:name":"Bushido International",
    "wof:placetype":"venue"
},
  "geometry": {"coordinates":[145.24356079099999,-37.8176803589],"type":"Point"}
}