{
  "type": "Feature",
  "properties": {
    "addr:full":"878 Toorak Rd Hawthorn East VIC 3123",
    "addr:housenumber":"878",
    "addr:postcode":"3123",
    "addr:street":"Toorak Rd",
    "iso:country":"AU",
    "sg:address":"878 Toorak Rd",
    "sg:city":"Hawthorn East",
    "sg:classifiers":[
        {
            "category":"Retail",
            "subcategory":"Auto Repair",
            "type":"Services"
        }
    ],
    "sg:phone":"+61 3 9822 8883",
    "sg:postcode":"3123",
    "sg:province":"VIC",
    "sg:tags":[
        "testing",
        "inspection",
        "motor",
        "vehicle"
    ],
    "wof:name":"Kurrle Motors",
    "wof:placetype":"venue"
},
  "geometry": {"coordinates":[145.053497314,-37.845741272],"type":"Point"}
}