{
  "type": "Feature",
  "properties": {
    "iso:country":"AU",
    "sg:address":"6 Harriet St",
    "sg:city":"Singleton",
    "sg:classifiers":[
        {
            "category":"Wholesale",
            "subcategory":"Machinery & Supplies",
            "type":"Manufacturing & Wholesale Goods"
        }
    ],
    "sg:phone":"+61 2 6572 3043",
    "sg:postcode":"2330",
    "sg:province":"NSW",
    "sg:tags":[
        "process",
        "instrument",
        "control"
    ],
    "wof:name":"MWB Controls Pty Ltd",
    "wof:placetype":"venue"
},
  "geometry": {"coordinates":[151.16520700000001,-32.569893],"type":"Point"}
}