{
  "type": "Feature",
  "properties": {
    "addr:full":"23 Minna St Albany WA 6330",
    "addr:housenumber":"23",
    "addr:postcode":"6330",
    "addr:street":"Minna St",
    "iso:country":"AU",
    "sg:address":"23 Minna St",
    "sg:city":"Albany",
    "sg:classifiers":[
        {
            "category":"Retail",
            "subcategory":"Auto Repair",
            "type":"Services"
        }
    ],
    "sg:phone":"+61 8 9841 3000",
    "sg:postcode":"6330",
    "sg:province":"WA",
    "sg:tags":[
        "beater",
        "painter",
        "panel"
    ],
    "wof:name":"Hitchcock Panel Beaters",
    "wof:placetype":"venue"
},
  "geometry": {"coordinates":[117.88168335,-35.0146064758],"type":"Point"}
}