{
  "type": "Feature",
  "properties": {
    "iso:country":"AU",
    "sg:address":"3/ 70 Attfield St",
    "sg:city":"Maddington",
    "sg:classifiers":[
        {
            "category":"Education",
            "subcategory":"Dance Studio",
            "type":"Public Place"
        }
    ],
    "sg:phone":"+61 417 998 037",
    "sg:postcode":"6109",
    "sg:province":"WA",
    "sg:tags":[
        "venue",
        "tuition"
    ],
    "wof:name":"Academie De La Classique",
    "wof:placetype":"venue"
},
  "geometry": {"coordinates":[115.980323791,-32.0523452759],"type":"Point"}
}