{
  "type": "Feature",
  "properties": {
    "addr:full":"25 Weir St Euroa VIC 3666",
    "addr:housenumber":"25",
    "addr:postcode":"3666",
    "addr:street":"Weir St",
    "iso:country":"AU",
    "sg:address":"25 Weir St",
    "sg:city":"Euroa",
    "sg:classifiers":[
        {
            "category":"Building & Trades",
            "subcategory":"Construction",
            "type":"Services"
        }
    ],
    "sg:phone":"+61 427 845 246",
    "sg:postcode":"3666",
    "sg:province":"VIC",
    "sg:tags":[
        "contractor"
    ],
    "wof:name":"Halsall D J & G D",
    "wof:placetype":"venue"
},
  "geometry": {"coordinates":[145.571075439,-36.7587356567],"type":"Point"}
}