{
  "type": "Feature",
  "properties": {
    "addr:full":"65c Salamander Rd Robinvale VIC 3549",
    "addr:housenumber":"65c",
    "addr:postcode":"3549",
    "addr:street":"Salamander Rd",
    "iso:country":"AU",
    "sg:address":"65c Salamander Rd",
    "sg:city":"Robinvale",
    "sg:classifiers":[
        {
            "category":"Farming",
            "subcategory":"Berry Farm",
            "type":"Manufacturing & Wholesale Goods"
        }
    ],
    "sg:phone":"+61 3 5026 4075",
    "sg:postcode":"3549",
    "sg:province":"VIC",
    "sg:tags":[
        "fruit",
        "grower"
    ],
    "wof:name":"Fotia L & M",
    "wof:placetype":"venue"
},
  "geometry": {"coordinates":[142.770065308,-34.5829200745],"type":"Point"}
}