{
  "type": "Feature",
  "properties": {
    "addr:full":"37 George St Morwell VIC 3840",
    "addr:housenumber":"37",
    "addr:postcode":"3840",
    "addr:street":"George St",
    "iso:country":"AU",
    "sg:address":"37 George St",
    "sg:city":"Morwell",
    "sg:classifiers":[
        {
            "category":"Cafe",
            "type":"Food & Drink"
        }
    ],
    "sg:phone":"+61 3 5134 1600",
    "sg:postcode":"3840",
    "sg:province":"VIC",
    "wof:name":"Claudia's Cafe",
    "wof:placetype":"venue"
},
  "geometry": {"coordinates":[146.39817810100001,-38.2384529114],"type":"Point"}
}