{
  "type": "Feature",
  "properties": {
    "addr:full":"Brisbane Club 241 Adelaide Brisbane QLD 4000",
    "addr:housenumber":"241",
    "addr:postcode":"4000",
    "addr:street":"Adelaide",
    "iso:country":"AU",
    "sg:address":"Brisbane Club 241 Adelaide",
    "sg:city":"Brisbane",
    "sg:classifiers":[
        {
            "category":"Health Services",
            "subcategory":"Dentist",
            "type":"Services"
        }
    ],
    "sg:phone":"+61 7 3221 7777",
    "sg:postcode":"4000",
    "sg:province":"QLD",
    "wof:name":"Tuffley Mark",
    "wof:placetype":"venue"
},
  "geometry": {"coordinates":[153.02781677199999,-27.4664211273],"type":"Point"}
}