{
  "type": "Feature",
  "properties": {
    "addr:full":"170 Lum Rd Wheelers Hill VIC 3150",
    "addr:housenumber":"170",
    "addr:postcode":"3150",
    "addr:street":"Lum Rd",
    "iso:country":"AU",
    "sg:address":"170 Lum Rd",
    "sg:city":"Wheelers Hill",
    "sg:classifiers":[
        {
            "category":"Manufacturing",
            "subcategory":"Food",
            "type":"Manufacturing & Wholesale Goods"
        }
    ],
    "sg:phone":"+61 3 9560 1587",
    "sg:postcode":"3150",
    "sg:province":"VIC",
    "sg:tags":[
        "function",
        "catering"
    ],
    "wof:name":"Churchills Victorian Ovens (Marketing) Pty Ltd",
    "wof:placetype":"venue"
},
  "geometry": {"coordinates":[145.180175781,-37.9042625427],"type":"Point"}
}