{
  "type": "Feature",
  "properties": {
    "addr:full":"6- 8 Harris Rd Griffith NSW 2680",
    "addr:housenumber":"8",
    "addr:postcode":"2680",
    "addr:street":"Harris Rd",
    "iso:country":"AU",
    "sg:address":"6- 8 Harris Rd",
    "sg:city":"Griffith",
    "sg:classifiers":[
        {
            "category":"Farming",
            "subcategory":"Crops",
            "type":"Manufacturing & Wholesale Goods"
        }
    ],
    "sg:phone":"+61 2 6964 5465",
    "sg:postcode":"2680",
    "sg:province":"NSW",
    "sg:tags":[
        "warehousing"
    ],
    "wof:name":"Griffith Self Storage",
    "wof:placetype":"venue"
},
  "geometry": {"coordinates":[146.05291700000001,-34.292072],"type":"Point"}
}