{
  "type": "Feature",
  "properties": {
    "iso:country":"AU",
    "sg:address":"222 Scarborough Beach Rd",
    "sg:city":"Mt Hawthorn",
    "sg:classifiers":[
        {
            "category":"Shopping",
            "subcategory":"Antiques",
            "type":"Retail Goods"
        }
    ],
    "sg:phone":"+61 8 9443 8244",
    "sg:postcode":"6016",
    "sg:province":"WA",
    "wof:name":"Timeless Treasures",
    "wof:placetype":"venue"
},
  "geometry": {"coordinates":[115.832832336,-31.9164772034],"type":"Point"}
}