{
  "type": "Feature",
  "properties": {
    "addr:full":"Unit 1 1 Wise St Joondalup WA 6027",
    "addr:housenumber":"1",
    "addr:postcode":"6027",
    "addr:street":"Wise St",
    "iso:country":"AU",
    "sg:address":"Unit 1 1 Wise St",
    "sg:city":"Joondalup",
    "sg:classifiers":[
        {
            "category":"Professional",
            "subcategory":"Business Services",
            "type":"Services"
        }
    ],
    "sg:phone":"+61 8 9301 0088",
    "sg:postcode":"6027",
    "sg:province":"WA",
    "sg:tags":[
        "fashion",
        "agent"
    ],
    "wof:name":"Naleh Pty Ltd",
    "wof:placetype":"venue"
},
  "geometry": {"coordinates":[115.766746521,-31.7465229034],"type":"Point"}
}