{
  "type": "Feature",
  "properties": {
    "iso:country":"AU",
    "sg:address":"U2/ 653 Portrush Rd",
    "sg:city":"Glen Osmond",
    "sg:classifiers":[
        {
            "category":"Health Services",
            "subcategory":"Health Practitioner",
            "type":"Services"
        }
    ],
    "sg:phone":"+61 8 8379 5074",
    "sg:postcode":"5064",
    "sg:province":"SA",
    "sg:tags":[
        "alternative"
    ],
    "wof:name":"Nurse At Work",
    "wof:placetype":"venue"
},
  "geometry": {"coordinates":[138.643997192,-34.9617538452],"type":"Point"}
}