{
  "type": "Feature",
  "properties": {
    "addr:full":"670 Canterbury Rd Surrey Hills VIC 3127",
    "addr:housenumber":"670",
    "addr:postcode":"3127",
    "addr:street":"Canterbury Rd",
    "iso:country":"AU",
    "sg:address":"670 Canterbury Rd",
    "sg:city":"Surrey Hills",
    "sg:classifiers":[
        {
            "category":"Shopping",
            "subcategory":"Pets & Pet Supplies",
            "type":"Retail Goods"
        }
    ],
    "sg:phone":"+61 3 9896 6222",
    "sg:postcode":"3127",
    "sg:province":"VIC",
    "sg:tags":[
        "food"
    ],
    "wof:name":"Uncle Ben's Australia",
    "wof:placetype":"venue"
},
  "geometry": {"coordinates":[145.1015625,-37.8265800476],"type":"Point"}
}