{
  "type": "Feature",
  "properties": {
    "addr:full":"Maccarone Health Clinic, 266 Appleby Rd Stafford Heights QLD 4053",
    "addr:housenumber":"266",
    "addr:postcode":"4053",
    "addr:street":"Appleby Rd",
    "iso:country":"AU",
    "sg:address":"Maccarone Health Clinic, 266 Appleby Rd",
    "sg:city":"Stafford Heights",
    "sg:classifiers":[
        {
            "category":"Health Services",
            "subcategory":"Health Practitioner",
            "type":"Services"
        }
    ],
    "sg:phone":"+61 7 3359 5318",
    "sg:postcode":"4053",
    "sg:province":"QLD",
    "sg:tags":[
        "dietitian"
    ],
    "wof:name":"Erica Maccarone",
    "wof:placetype":"venue"
},
  "geometry": {"coordinates":[153.010955811,-27.3929538727],"type":"Point"}
}