{
  "type": "Feature",
  "properties": {
    "addr:full":"35 Passmore St Richmond SA 5033",
    "addr:housenumber":"35",
    "addr:postcode":"5033",
    "addr:street":"Passmore St",
    "iso:country":"AU",
    "sg:address":"35 Passmore St",
    "sg:city":"Richmond",
    "sg:classifiers":[
        {
            "category":"Retail",
            "subcategory":"Auto Repair",
            "type":"Services"
        }
    ],
    "sg:phone":"+61 412 053 414",
    "sg:postcode":"5033",
    "sg:province":"SA",
    "sg:tags":[
        "electrical"
    ],
    "wof:name":"G. Batas Auto Electrics",
    "wof:placetype":"venue"
},
  "geometry": {"coordinates":[138.548339844,-34.9389419556],"type":"Point"}
}