{
  "type": "Feature",
  "properties": {
    "addr:full":"29 Daphne St Botany NSW 2019",
    "addr:housenumber":"29",
    "addr:postcode":"2019",
    "addr:street":"Daphne St",
    "iso:country":"AU",
    "sg:address":"29 Daphne St",
    "sg:city":"Botany",
    "sg:classifiers":[
        {
            "category":"Building & Trades",
            "subcategory":"Plumbing",
            "type":"Services"
        }
    ],
    "sg:phone":"+61 2 9666 5535",
    "sg:postcode":"2019",
    "sg:province":"NSW",
    "sg:tags":[
        "equipment",
        "valves"
    ],
    "wof:name":"Brian Connor Plumbing Pty Ltd",
    "wof:placetype":"venue"
},
  "geometry": {"coordinates":[151.19778442399999,-33.9419593811],"type":"Point"}
}