{
  "type": "Feature",
  "properties": {
    "addr:full":"2 Bangalo Ave Banora Point NSW 2486",
    "addr:housenumber":"2",
    "addr:postcode":"2486",
    "addr:street":"Bangalo Ave",
    "iso:country":"AU",
    "sg:address":"2 Bangalo Ave",
    "sg:city":"Banora Point",
    "sg:classifiers":[
        {
            "category":"Building & Trades",
            "subcategory":"Plumbing",
            "type":"Services"
        }
    ],
    "sg:phone":"+61 7 5523 9555",
    "sg:postcode":"2486",
    "sg:province":"NSW",
    "sg:tags":[
        "plumber",
        "gasfitters"
    ],
    "wof:name":"Bruem Mark",
    "wof:placetype":"venue"
},
  "geometry": {"coordinates":[153.55099487300001,-28.2118644714],"type":"Point"}
}