{
  "type": "Feature",
  "properties": {
    "iso:country":"AU",
    "sg:address":"124 Victoria Rd",
    "sg:city":"Drummoyne",
    "sg:classifiers":[
        {
            "category":"Manufacturing",
            "subcategory":"Watercraft",
            "type":"Manufacturing & Wholesale Goods"
        }
    ],
    "sg:phone":"+61 2 9819 6077",
    "sg:postcode":"2047",
    "sg:province":"NSW",
    "sg:tags":[
        "sail",
        "marine",
        "maker"
    ],
    "wof:name":"Jackson Sails",
    "wof:placetype":"venue"
},
  "geometry": {"coordinates":[151.156799,-33.853188],"type":"Point"}
}