{
  "type": "Feature",
  "properties": {
    "iso:country":"AU",
    "sg:address":"Frenchmans Rd",
    "sg:city":"Randwick",
    "sg:classifiers":[
        {
            "category":"Travel",
            "subcategory":"Hotels & Motels",
            "type":"Entertainment"
        }
    ],
    "sg:phone":"+61 2 9398 2682",
    "sg:postcode":"2031",
    "sg:province":"NSW",
    "sg:tags":[
        "pub"
    ],
    "wof:name":"Duke of Gloucester Hotel",
    "wof:placetype":"venue"
},
  "geometry": {"coordinates":[151.246536255,-33.9085502625],"type":"Point"}
}