{
  "type": "Feature",
  "properties": {
    "iso:country":"AU",
    "sg:address":"337 Whites Rd",
    "sg:city":"Paralowie",
    "sg:classifiers":[
        {
            "category":"Health Services",
            "subcategory":"Doctor",
            "type":"Services"
        }
    ],
    "sg:phone":"+61 8 8285 8888",
    "sg:postcode":"5108",
    "sg:province":"SA",
    "sg:tags":[
        "medical",
        "practitioner"
    ],
    "wof:name":"Health Matters Medical Centre Pty Ltd",
    "wof:placetype":"venue"
},
  "geometry": {"coordinates":[138.621704102,-34.7491874695],"type":"Point"}
}