{
  "type": "Feature",
  "properties": {
    "addr:full":"Shop 1 2 Sydney Rd Manly NSW 2095",
    "addr:housenumber":"shop;2",
    "addr:postcode":"2095",
    "addr:street":"Sydney Rd",
    "iso:country":"AU",
    "sg:address":"Shop 1 2 Sydney Rd",
    "sg:city":"Manly",
    "sg:classifiers":[
        {
            "category":"Cafe",
            "type":"Food & Drink"
        }
    ],
    "sg:phone":"+61 2 9977 0100",
    "sg:postcode":"2095",
    "sg:province":"NSW",
    "wof:name":"Ser/Bar Kebab & Pide House",
    "wof:placetype":"venue"
},
  "geometry": {"coordinates":[151.28733825699999,-33.7971115112],"type":"Point"}
}