{
  "type": "Feature",
  "properties": {
    "addr:full":"6 Siska Crt Mandurama NSW 2792",
    "addr:housenumber":"6",
    "addr:postcode":"2792",
    "addr:street":"Siska Crt",
    "iso:country":"AU",
    "sg:address":"6 Siska Crt",
    "sg:city":"Mandurama",
    "sg:classifiers":[
        {
            "category":"Health Services",
            "subcategory":"Chiropractor",
            "type":"Services"
        }
    ],
    "sg:phone":"+61 8 9535 6001",
    "sg:postcode":"2792",
    "sg:province":"NSW",
    "wof:name":"Rose Brennan",
    "wof:placetype":"venue"
},
  "geometry": {"coordinates":[148.98121643100001,-33.6480712891],"type":"Point"}
}