{
  "type": "Feature",
  "properties": {
    "addr:full":"1A Pitcairn St Urrbrae SA 5064",
    "addr:housenumber":"1a",
    "addr:postcode":"5064",
    "addr:street":"Pitcairn St",
    "iso:country":"AU",
    "sg:address":"1A Pitcairn St",
    "sg:city":"Urrbrae",
    "sg:classifiers":[
        {
            "category":"Health Services",
            "subcategory":"Health Practitioner",
            "type":"Services"
        }
    ],
    "sg:phone":"+61 428 306 956",
    "sg:postcode":"5064",
    "sg:province":"SA",
    "sg:tags":[
        "acupuncture"
    ],
    "wof:name":"Jezioranski Teresa",
    "wof:placetype":"venue"
},
  "geometry": {"coordinates":[138.63926696799999,-34.9642066956],"type":"Point"}
}