{
  "type": "Feature",
  "properties": {
    "addr:full":"10 Hamilton St Bayswater WA 6053",
    "addr:housenumber":"10",
    "addr:postcode":"6053",
    "addr:street":"Hamilton St",
    "iso:country":"AU",
    "sg:address":"10 Hamilton St",
    "sg:city":"Bayswater",
    "sg:classifiers":[
        {
            "category":"Shopping",
            "subcategory":"Musical Instruments",
            "type":"Retail Goods"
        }
    ],
    "sg:phone":"+61 8 9272 2118",
    "sg:postcode":"6053",
    "sg:province":"WA",
    "sg:tags":[
        "musician",
        "agent"
    ],
    "wof:name":"Erik Kowarski",
    "wof:placetype":"venue"
},
  "geometry": {"coordinates":[115.914352417,-31.9195613861],"type":"Point"}
}