{
  "type": "Feature",
  "properties": {
    "addr:full":"33a Chester St Oakleigh VIC 3166",
    "addr:housenumber":"33a",
    "addr:postcode":"3166",
    "addr:street":"Chester St",
    "iso:country":"AU",
    "sg:address":"33a Chester St",
    "sg:city":"Oakleigh",
    "sg:classifiers":[
        {
            "category":"Building & Trades",
            "subcategory":"Landscaping Services",
            "type":"Services"
        }
    ],
    "sg:phone":"+61 3 9568 4423",
    "sg:postcode":"3166",
    "sg:province":"VIC",
    "sg:tags":[
        "consultant"
    ],
    "wof:name":"Site Safety Audits",
    "wof:placetype":"venue"
},
  "geometry": {"coordinates":[145.09115600600001,-37.8994445801],"type":"Point"}
}