{
  "type": "Feature",
  "properties": {
    "addr:full":"11 Westside Drv Laverton North VIC 3026",
    "addr:housenumber":"11",
    "addr:postcode":"3026",
    "addr:street":"Westside Drv",
    "iso:country":"AU",
    "sg:address":"11 Westside Drv",
    "sg:city":"Laverton North",
    "sg:classifiers":[
        {
            "category":"Home & Garden",
            "subcategory":"Building Materials",
            "type":"Retail Goods"
        }
    ],
    "sg:phone":"+61 3 9314 1044",
    "sg:postcode":"3026",
    "sg:province":"VIC",
    "sg:tags":[
        "roofing"
    ],
    "wof:name":"JH Stephenson & Son P/L",
    "wof:placetype":"venue"
},
  "geometry": {"coordinates":[144.821686,-37.817558],"type":"Point"}
}