{
  "type": "Feature",
  "properties": {
    "addr:full":"10 Haslewood Crt Robina QLD 4226",
    "addr:housenumber":"10",
    "addr:postcode":"4226",
    "addr:street":"Haslewood Crt",
    "iso:country":"AU",
    "sg:address":"10 Haslewood Crt",
    "sg:city":"Robina",
    "sg:classifiers":[
        {
            "category":"Shopping",
            "subcategory":"Bicycles & Sporting Goods",
            "type":"Retail Goods"
        }
    ],
    "sg:phone":"+61 7 5575 5234",
    "sg:postcode":"4226",
    "sg:province":"QLD",
    "sg:tags":[
        "chemical",
        "equipment",
        "pool",
        "swimming"
    ],
    "wof:name":"Pool Blocks - Pool Drops Algicide",
    "wof:placetype":"venue"
},
  "geometry": {"coordinates":[153.41395568900001,-28.0475101471],"type":"Point"}
}