{
  "type": "Feature",
  "properties": {
    "addr:full":"15 Brittain St Como WA 6152",
    "addr:housenumber":"15",
    "addr:postcode":"6152",
    "addr:street":"Brittain St",
    "iso:country":"AU",
    "sg:address":"15 Brittain St",
    "sg:city":"Como",
    "sg:classifiers":[
        {
            "category":"Professional",
            "subcategory":"Art Services",
            "type":"Services"
        }
    ],
    "sg:phone":"+61 8 9313 1971",
    "sg:postcode":"6152",
    "sg:province":"WA",
    "sg:tags":[
        "decorator",
        "painter"
    ],
    "wof:name":"A Brush with Class Painting Service",
    "wof:placetype":"venue"
},
  "geometry": {"coordinates":[115.866867,-31.997461],"type":"Point"}
}