{
  "type": "Feature",
  "properties": {
    "addr:full":"Shp1/ 150 Merrylands Rd Merrylands NSW 2160",
    "addr:housenumber":"150",
    "addr:postcode":"2160",
    "addr:street":"Merrylands Rd",
    "iso:country":"AU",
    "sg:address":"Shp1/ 150 Merrylands Rd",
    "sg:city":"Merrylands",
    "sg:classifiers":[
        {
            "category":"Utilities",
            "subcategory":"Mobile Phone",
            "type":"Services"
        }
    ],
    "sg:phone":"+61 2 9637 9922",
    "sg:postcode":"2160",
    "sg:province":"NSW",
    "sg:tags":[
        "repair",
        "telephone"
    ],
    "wof:name":"Unifone.com",
    "wof:placetype":"venue"
},
  "geometry": {"coordinates":[150.99026489299999,-33.8366966248],"type":"Point"}
}