{
  "type": "Feature",
  "properties": {
    "addr:full":"13 Beaumaris St Enfield NSW 2136",
    "addr:housenumber":"13",
    "addr:postcode":"2136",
    "addr:street":"Beaumaris St",
    "iso:country":"AU",
    "sg:address":"13 Beaumaris St",
    "sg:city":"Enfield",
    "sg:classifiers":[
        {
            "category":"Sports & Exercise",
            "subcategory":"Gym",
            "type":"Entertainment"
        }
    ],
    "sg:phone":"+61 425 230 281",
    "sg:postcode":"2136",
    "sg:province":"NSW",
    "sg:tags":[
        "pilate",
        "method"
    ],
    "wof:name":"On the Mat Pilates",
    "wof:placetype":"venue"
},
  "geometry": {"coordinates":[151.09458923299999,-33.8864479065],"type":"Point"}
}