{
  "type": "Feature",
  "properties": {
    "iso:country":"AU",
    "sg:address":"56 Ashmore Rd",
    "sg:city":"Bundall",
    "sg:classifiers":[
        {
            "category":"Professional",
            "subcategory":"Art Services",
            "type":"Services"
        }
    ],
    "sg:phone":"+61 7 5538 8280",
    "sg:postcode":"4217",
    "sg:province":"QLD",
    "sg:tags":[
        "interior",
        "decorator"
    ],
    "wof:name":"Design Professionals",
    "wof:placetype":"venue"
},
  "geometry": {"coordinates":[153.406906128,-28.0106506348],"type":"Point"}
}