{
  "type": "Feature",
  "properties": {
    "addr:full":"Midland Hwy Stanhope VIC 3623",
    "addr:postcode":"3623",
    "addr:street":"Midland Hwy",
    "iso:country":"AU",
    "sg:address":"Midland Hwy",
    "sg:city":"Stanhope",
    "sg:classifiers":[
        {
            "category":"Manufacturing",
            "subcategory":"Retail Goods",
            "type":"Manufacturing & Wholesale Goods"
        }
    ],
    "sg:phone":"+61 3 5857 2466",
    "sg:postcode":"3623",
    "sg:province":"VIC",
    "sg:tags":[
        "merchant",
        "pump",
        "mfrs"
    ],
    "wof:name":"Midland Rural Engineering",
    "wof:placetype":"venue"
},
  "geometry": {"coordinates":[144.98629760700001,-36.4471855164],"type":"Point"}
}