{
  "type": "Feature",
  "properties": {
    "iso:country":"AU",
    "sg:address":"433a Centre Rd",
    "sg:city":"Bentleigh",
    "sg:classifiers":[
        {
            "category":"Health Services",
            "subcategory":"Optometrist",
            "type":"Services"
        }
    ],
    "sg:phone":"+61 3 9557 8319",
    "sg:postcode":"3204",
    "sg:province":"VIC",
    "wof:name":"Optical World",
    "wof:placetype":"venue"
},
  "geometry": {"coordinates":[145.039749,-37.918434],"type":"Point"}
}