{
  "type": "Feature",
  "properties": {
    "addr:full":"37-39 Kalimna Rd Nuriootpa SA 5355",
    "addr:housenumber":"37-39",
    "addr:postcode":"5355",
    "addr:street":"Kalimna Rd",
    "iso:country":"AU",
    "sg:address":"37-39 Kalimna Rd",
    "sg:city":"Nuriootpa",
    "sg:classifiers":[
        {
            "category":"Professional",
            "subcategory":"Printing & Photocopies",
            "type":"Services"
        }
    ],
    "sg:phone":"+61 8 8562 2796",
    "sg:postcode":"5355",
    "sg:province":"SA",
    "sg:tags":[
        "screen",
        "printer"
    ],
    "wof:name":"Valley Imprint",
    "wof:placetype":"venue"
},
  "geometry": {"coordinates":[139.00770568900001,-34.4599494934],"type":"Point"}
}