{
  "type": "Feature",
  "properties": {
    "addr:full":"24 Broad St Sarina QLD 4737",
    "addr:housenumber":"24",
    "addr:postcode":"4737",
    "addr:street":"Broad St",
    "iso:country":"AU",
    "sg:address":"24 Broad St",
    "sg:city":"Sarina",
    "sg:classifiers":[
        {
            "category":"Education",
            "subcategory":"Special Training",
            "type":"Public Place"
        }
    ],
    "sg:phone":"+61 7 4956 1428",
    "sg:postcode":"4737",
    "sg:province":"QLD",
    "sg:tags":[
        "development"
    ],
    "wof:name":"Skills Development Sarina",
    "wof:placetype":"venue"
},
  "geometry": {"coordinates":[149.21804800000001,-21.423786],"type":"Point"}
}