{
  "type": "Feature",
  "properties": {
    "iso:country":"AU",
    "sg:address":"40 Pearse St",
    "sg:city":"North Fremantle",
    "sg:classifiers":[
        {
            "category":"Professional",
            "subcategory":"Employment Agencies",
            "type":"Services"
        }
    ],
    "sg:phone":"+61 1300 132 331",
    "sg:postcode":"6159",
    "sg:province":"WA",
    "sg:tags":[
        "provider",
        "internet"
    ],
    "wof:name":"Norcom Internet Provider",
    "wof:placetype":"venue"
},
  "geometry": {"coordinates":[115.751953,-32.034027],"type":"Point"}
}