{
  "type": "Feature",
  "properties": {
    "addr:full":"116 Wahringah Rd Narraweena NSW 2099",
    "addr:housenumber":"116",
    "addr:postcode":"2099",
    "addr:street":"Wahringah Rd",
    "iso:country":"AU",
    "sg:address":"116 Wahringah Rd",
    "sg:city":"Narraweena",
    "sg:classifiers":[
        {
            "category":"Retail",
            "subcategory":"Auto Repair",
            "type":"Services"
        }
    ],
    "sg:phone":"+61 2 9971 5326",
    "sg:postcode":"2099",
    "sg:province":"NSW",
    "sg:tags":[
        "beater",
        "painter",
        "panel"
    ],
    "wof:name":"Ara's Unique Body Repairs",
    "wof:placetype":"venue"
},
  "geometry": {"coordinates":[151.270263672,-33.7545051575],"type":"Point"}
}