{
  "type": "Feature",
  "properties": {
    "iso:country":"AU",
    "sg:address":"24 Berry St",
    "sg:city":"Nowra",
    "sg:classifiers":[
        {
            "category":"Communications",
            "subcategory":"News Services",
            "type":"Services"
        }
    ],
    "sg:phone":"+61 2 4422 6277",
    "sg:postcode":"2541",
    "sg:province":"NSW",
    "sg:tags":[
        "information",
        "tourist",
        "attractions"
    ],
    "wof:name":"Tour Marvel",
    "wof:placetype":"venue"
},
  "geometry": {"coordinates":[150.59930419899999,-34.8814697266],"type":"Point"}
}