{
  "type": "Feature",
  "properties": {
    "addr:full":"4 Leslie St Belgrave VIC 3160",
    "addr:housenumber":"4",
    "addr:postcode":"3160",
    "addr:street":"Leslie St",
    "iso:country":"AU",
    "sg:address":"4 Leslie St",
    "sg:city":"Belgrave",
    "sg:classifiers":[
        {
            "category":"Retail",
            "subcategory":"Funeral Services",
            "type":"Services"
        }
    ],
    "sg:phone":"+61 3 9754 2722",
    "sg:postcode":"3160",
    "sg:province":"VIC",
    "sg:tags":[
        "supply"
    ],
    "wof:name":"Funeral Finery Pty Ltd",
    "wof:placetype":"venue"
},
  "geometry": {"coordinates":[145.35534668,-37.9044952393],"type":"Point"}
}