{
  "type": "Feature",
  "properties": {
    "iso:country":"AU",
    "sg:address":"74 Compton Rd",
    "sg:city":"Underwood",
    "sg:classifiers":[
        {
            "category":"Real Estate",
            "subcategory":"Real Estate Agent",
            "type":"Services"
        }
    ],
    "sg:phone":"+61 7 3209 3852",
    "sg:postcode":"4119",
    "sg:province":"QLD",
    "sg:tags":[
        "handyman's",
        "equipment",
        "hire",
        "builders",
        "contractor"
    ],
    "wof:name":"Logan Hire",
    "wof:placetype":"venue"
},
  "geometry": {"coordinates":[153.108444214,-27.6193618774],"type":"Point"}
}