{
  "type": "Feature",
  "properties": {
    "addr:full":"38 Stawell St Coburg VIC 3058",
    "addr:housenumber":"38",
    "addr:postcode":"3058",
    "addr:street":"Stawell St",
    "iso:country":"AU",
    "sg:address":"38 Stawell St",
    "sg:city":"Coburg",
    "sg:classifiers":[
        {
            "category":"Professional",
            "subcategory":"Business Services",
            "type":"Services"
        }
    ],
    "sg:phone":"+61 3 9350 1098",
    "sg:postcode":"3058",
    "sg:province":"VIC",
    "sg:tags":[
        "drafting"
    ],
    "wof:name":"Drawn To Scale",
    "wof:placetype":"venue"
},
  "geometry": {"coordinates":[144.952590942,-37.7397766113],"type":"Point"}
}