{
  "type": "Feature",
  "properties": {
    "addr:full":"6 Maiella Pl Yatala QLD 4207",
    "addr:housenumber":"6",
    "addr:postcode":"4207",
    "addr:street":"Maiella Pl",
    "iso:country":"AU",
    "sg:address":"6 Maiella Pl",
    "sg:city":"Yatala",
    "sg:classifiers":[
        {
            "category":"Freight",
            "type":"Transportation"
        }
    ],
    "sg:phone":"+61 1300 781 233",
    "sg:postcode":"4207",
    "sg:province":"QLD",
    "sg:tags":[
        "transport",
        "refrigerated"
    ],
    "sg:website":"http://www.coolcouriers.com",
    "wof:name":"Cool Couriers (Aust.) Pty Ltd",
    "wof:placetype":"venue"
},
  "geometry": {"coordinates":[153.233520508,-27.7369632721],"type":"Point"}
}