{
  "type": "Feature",
  "properties": {
    "addr:full":"328 Stirling Hwy Claremont WA 6010",
    "addr:housenumber":"328",
    "addr:postcode":"6010",
    "addr:street":"Stirling Hwy",
    "iso:country":"AU",
    "sg:address":"328 Stirling Hwy",
    "sg:city":"Claremont",
    "sg:classifiers":[
        {
            "category":"Health Services",
            "subcategory":"Medical Lab",
            "type":"Services"
        }
    ],
    "sg:phone":"+61 8 9385 1533",
    "sg:postcode":"6010",
    "sg:province":"WA",
    "sg:tags":[
        "laboratory",
        "pathology"
    ],
    "wof:name":"Pathwest",
    "wof:placetype":"venue"
},
  "geometry": {"coordinates":[115.778640747,-31.984172821],"type":"Point"}
}