{
  "type": "Feature",
  "properties": {
    "iso:country":"AU",
    "sg:address":"83 Glebe Point Rd",
    "sg:city":"Glebe",
    "sg:classifiers":[
        {
            "category":"Train Station",
            "subcategory":"Light Rail",
            "type":"Transportation"
        }
    ],
    "sg:phone":"+61 1300 138 483",
    "sg:postcode":"2037",
    "sg:province":"NSW",
    "sg:tags":[
        "equipment",
        "energy",
        "solar"
    ],
    "wof:name":"TODAE",
    "wof:placetype":"venue"
},
  "geometry": {"coordinates":[151.190551758,-33.8825187683],"type":"Point"}
}