{
  "type": "Feature",
  "properties": {
    "iso:country":"AU",
    "sg:address":"3/ 49 Ridley St",
    "sg:city":"Charlestown",
    "sg:classifiers":[
        {
            "category":"Real Estate",
            "subcategory":"Surveying",
            "type":"Services"
        }
    ],
    "sg:phone":"+61 2 4942 5441",
    "sg:postcode":"2290",
    "sg:province":"NSW",
    "sg:tags":[
        "surveyor",
        "land"
    ],
    "wof:name":"De Witt Consulting Pty Ltd",
    "wof:placetype":"venue"
},
  "geometry": {"coordinates":[151.69703674300001,-32.9622497559],"type":"Point"}
}