{
  "type": "Feature",
  "properties": {
    "addr:full":"14 Bean Ave North Rockhampton QLD 4701",
    "addr:housenumber":"14",
    "addr:postcode":"4701",
    "addr:street":"Bean Ave North",
    "iso:country":"AU",
    "sg:address":"14 Bean Ave",
    "sg:city":"North Rockhampton",
    "sg:classifiers":[
        {
            "category":"Professional",
            "subcategory":"Accounting & Tax Preparation",
            "type":"Services"
        }
    ],
    "sg:phone":"+61 7 4936 2152",
    "sg:postcode":"4701",
    "sg:province":"QLD",
    "sg:tags":[
        "consultant",
        "taxation"
    ],
    "wof:name":"APS Accounting & Taxation Services",
    "wof:placetype":"venue"
},
  "geometry": {"coordinates":[150.505783081,-23.354101181],"type":"Point"}
}