{
  "type": "Feature",
  "properties": {
    "addr:full":"G2 267 Murray St Perth WA 6000",
    "addr:housenumber":"267",
    "addr:postcode":"6000",
    "addr:street":"G2;Murray St",
    "iso:country":"AU",
    "sg:address":"G2 267 Murray St",
    "sg:city":"Perth",
    "sg:classifiers":[
        {
            "category":"Shopping",
            "subcategory":"Mobile Phones",
            "type":"Retail Goods"
        }
    ],
    "sg:phone":"+61 8 9231 1884",
    "sg:postcode":"6000",
    "sg:province":"WA",
    "sg:tags":[
        "telephone",
        "accessory"
    ],
    "wof:name":"Telstra Shop",
    "wof:placetype":"venue"
},
  "geometry": {"coordinates":[115.854179382,-31.9514904022],"type":"Point"}
}