{
  "type": "Feature",
  "properties": {
    "addr:full":"Shop 50 Settlement City Bay St Port Macquarie NSW 2444",
    "addr:housenumber":"shop 50",
    "addr:postcode":"2444",
    "addr:street":"Settlement City Bay St",
    "iso:country":"AU",
    "sg:address":"Shop 50 Settlement City Bay St",
    "sg:city":"Port Macquarie",
    "sg:classifiers":[
        {
            "category":"Personal",
            "subcategory":"Beauty Salon",
            "type":"Services"
        }
    ],
    "sg:phone":"+61 2 6583 2995",
    "sg:postcode":"2444",
    "sg:province":"NSW",
    "sg:tags":[
        "hairdresser"
    ],
    "wof:name":"Reflections Hair & Beauty Studio",
    "wof:placetype":"venue"
},
  "geometry": {"coordinates":[152.89505,-31.428562],"type":"Point"}
}