{
  "type": "Feature",
  "properties": {
    "addr:full":"Locked Bag 22 Homebush NSW 2140",
    "addr:postcode":"2140",
    "iso:country":"AU",
    "sg:address":"Locked Bag 22",
    "sg:city":"Homebush",
    "sg:classifiers":[
        {
            "category":"Farming",
            "subcategory":"Fish & Marine Products",
            "type":"Manufacturing & Wholesale Goods"
        }
    ],
    "sg:phone":"+61 2 9394 3222",
    "sg:postcode":"2140",
    "sg:province":"NSW",
    "sg:tags":[
        "chemical",
        "supplier"
    ],
    "wof:name":"Bronson & Jacobs Pty Ltd",
    "wof:placetype":"venue"
},
  "geometry": {"coordinates":[151.082397461,-33.8639793396],"type":"Point"}
}