{
  "type": "Feature",
  "properties": {
    "iso:country":"AU",
    "sg:address":"Farnborough Illawara Hwy",
    "sg:city":"Moss Vale",
    "sg:classifiers":[
        {
            "category":"Real Estate",
            "subcategory":"Developer",
            "type":"Services"
        }
    ],
    "sg:phone":"+61 2 4869 1604",
    "sg:postcode":"2577",
    "sg:province":"NSW",
    "sg:tags":[
        "development"
    ],
    "wof:name":"Winlord Pty Ltd",
    "wof:placetype":"venue"
},
  "geometry": {"coordinates":[150.39100647000001,-34.5528373718],"type":"Point"}
}