{
  "type": "Feature",
  "properties": {
    "addr:full":"136 Main Rd Lindenow VIC 3865",
    "addr:housenumber":"136",
    "addr:postcode":"3865",
    "addr:street":"Main Rd",
    "iso:country":"AU",
    "sg:address":"136 Main Rd",
    "sg:city":"Lindenow",
    "sg:classifiers":[
        {
            "category":"Building & Trades",
            "subcategory":"Plumbing",
            "type":"Services"
        }
    ],
    "sg:phone":"+61 3 5157 1387",
    "sg:postcode":"3865",
    "sg:province":"VIC",
    "sg:tags":[
        "plumber",
        "gasfitters"
    ],
    "wof:name":"St John Mark J",
    "wof:placetype":"venue"
},
  "geometry": {"coordinates":[147.470092773,-37.796661377],"type":"Point"}
}