{
  "type": "Feature",
  "properties": {
    "iso:country":"AU",
    "sg:address":"PO Box 253",
    "sg:city":"Yarraville",
    "sg:classifiers":[
        {
            "category":"Retail",
            "subcategory":"Event Space",
            "type":"Services"
        }
    ],
    "sg:phone":"+61 3 9362 0336",
    "sg:postcode":"3013",
    "sg:province":"VIC",
    "sg:tags":[
        "venue",
        "reception",
        "wedding"
    ],
    "wof:name":"MV Challenger",
    "wof:placetype":"venue"
},
  "geometry": {"coordinates":[144.882202148,-37.8180885315],"type":"Point"}
}