{
  "type": "Feature",
  "properties": {
    "addr:full":"Grantville Rd Almurta VIC 3979",
    "addr:postcode":"3979",
    "addr:street":"Grantville Rd",
    "iso:country":"AU",
    "sg:address":"Grantville Rd",
    "sg:city":"Almurta",
    "sg:classifiers":[
        {
            "category":"Building & Trades",
            "subcategory":"Landscaping Services",
            "type":"Services"
        }
    ],
    "sg:phone":"+61 3 5678 8345",
    "sg:postcode":"3979",
    "sg:province":"VIC",
    "sg:tags":[
        "grazier"
    ],
    "wof:name":"Paul A J",
    "wof:placetype":"venue"
},
  "geometry": {"coordinates":[145.598266602,-38.4593086243],"type":"Point"}
}