{
  "type": "Feature",
  "properties": {
    "iso:country":"AU",
    "sg:address":"585 Robinson Rd",
    "sg:city":"Aspley",
    "sg:classifiers":[
        {
            "category":"Personal",
            "subcategory":"Massage",
            "type":"Services"
        }
    ],
    "sg:phone":"+61 409 769 295",
    "sg:postcode":"4034",
    "sg:province":"QLD",
    "sg:tags":[
        "therapy"
    ],
    "wof:name":"Jennifer E Pryor - Mira",
    "wof:placetype":"venue"
},
  "geometry": {"coordinates":[153.02565,-27.364952],"type":"Point"}
}