{
  "type": "Feature",
  "properties": {
    "iso:country":"AU",
    "sg:address":"Lot 24 Richter Rd",
    "sg:city":"Bunbury",
    "sg:classifiers":[
        {
            "category":"Home & Garden",
            "subcategory":"Hardware",
            "type":"Retail Goods"
        }
    ],
    "sg:phone":"+61 8 9725 4433",
    "sg:postcode":"6230",
    "sg:province":"WA",
    "sg:tags":[
        "tarpaulin"
    ],
    "wof:name":"Del-Ray Canvas Australia",
    "wof:placetype":"venue"
},
  "geometry": {"coordinates":[115.663673,-33.356529],"type":"Point"}
}