{
  "type": "Feature",
  "properties": {
    "iso:country":"AU",
    "sg:address":"Shop 7/ 282 Princes Hwy",
    "sg:city":"Sylvania",
    "sg:classifiers":[
        {
            "category":"Health Services",
            "subcategory":"Chiropractor",
            "type":"Services"
        }
    ],
    "sg:phone":"+61 2 9544 8221",
    "sg:postcode":"2224",
    "sg:province":"NSW",
    "wof:name":"Graves Jane",
    "wof:placetype":"venue"
},
  "geometry": {"coordinates":[151.09446716299999,-34.0141868591],"type":"Point"}
}