{
  "type": "Feature",
  "properties": {
    "iso:country":"AU",
    "sg:address":"68 Wyndham St",
    "sg:city":"Shepparton",
    "sg:classifiers":[
        {
            "category":"Government",
            "subcategory":"Court House",
            "type":"Public Place"
        }
    ],
    "sg:phone":"+61 3 5831 4699",
    "sg:postcode":"3630",
    "sg:province":"VIC",
    "sg:tags":[
        "personal",
        "marriage",
        "family",
        "counselling"
    ],
    "wof:name":"Centacare",
    "wof:placetype":"venue"
},
  "geometry": {"coordinates":[145.409667969,-36.3916473389],"type":"Point"}
}