{
  "type": "Feature",
  "properties": {
    "addr:full":"Mawson Medical Center, Suite 16, 2 -4 Brown Street Campbelltown NSW 2560",
    "addr:housenumber":"2 -4",
    "addr:postcode":"2560",
    "addr:street":"Brown Street",
    "iso:country":"AU",
    "sg:address":"Mawson Medical Center, Suite 16, 2",
    "sg:city":"-4 Brown Street Campbelltown",
    "sg:classifiers":[
        {
            "category":"Health Services",
            "subcategory":"Doctor",
            "type":"Services"
        }
    ],
    "sg:phone":"+61 2 4627 2000",
    "sg:postcode":"2560",
    "sg:province":"NSW",
    "sg:tags":[
        "medical",
        "practitioner"
    ],
    "wof:name":"Dr George M. Calfas",
    "wof:placetype":"venue"
},
  "geometry": {"coordinates":[150.816574097,-34.064781189],"type":"Point"}
}