{
  "type": "Feature",
  "properties": {
    "iso:country":"AU",
    "sg:address":"1 Zeehan St",
    "sg:city":"Banksia Park",
    "sg:classifiers":[
        {
            "category":"Real Estate",
            "subcategory":"Architect",
            "type":"Services"
        }
    ],
    "sg:phone":"+61 8 8263 7250",
    "sg:postcode":"5091",
    "sg:province":"SA",
    "sg:tags":[
        "magnet",
        "magnetic",
        "material"
    ],
    "wof:name":"Alan Monks Advertising",
    "wof:placetype":"venue"
},
  "geometry": {"coordinates":[138.72354125999999,-34.8105621338],"type":"Point"}
}