{
  "type": "Feature",
  "properties": {
    "addr:full":"55 Maroondah Hwy Healesville VIC 3777",
    "addr:housenumber":"55",
    "addr:postcode":"3777",
    "addr:street":"Maroondah Hwy",
    "iso:country":"AU",
    "sg:address":"55 Maroondah Hwy",
    "sg:city":"Healesville",
    "sg:classifiers":[
        {
            "category":"Travel",
            "subcategory":"Hotels & Motels",
            "type":"Entertainment"
        }
    ],
    "sg:phone":"+61 3 5962 1323",
    "sg:postcode":"3777",
    "sg:province":"VIC",
    "wof:name":"Yarra Gables Motel",
    "wof:placetype":"venue"
},
  "geometry": {"coordinates":[145.51487700000001,-37.654137],"type":"Point"}
}