{
  "type": "Feature",
  "properties": {
    "addr:full":"42 Andrew Smith Drv Parafield Gardens SA 5107",
    "addr:housenumber":"42",
    "addr:postcode":"5107",
    "addr:street":"Andrew Smith Drv",
    "iso:country":"AU",
    "sg:address":"42 Andrew Smith Drv",
    "sg:city":"Parafield Gardens",
    "sg:classifiers":[
        {
            "category":"Education",
            "subcategory":"School",
            "type":"Public Place"
        }
    ],
    "sg:phone":"+61 8 8281 2199",
    "sg:postcode":"5107",
    "sg:province":"SA",
    "sg:tags":[
        "state",
        "except",
        "nsw"
    ],
    "wof:name":"The Pines Schools",
    "wof:placetype":"venue"
},
  "geometry": {"coordinates":[138.60777282699999,-34.7721557617],"type":"Point"}
}