{
  "type": "Feature",
  "properties": {
    "addr:full":"22 Bailey St Bairnsdale VIC 3875",
    "addr:housenumber":"22",
    "addr:postcode":"3875",
    "addr:street":"Bailey St",
    "iso:country":"AU",
    "sg:address":"22 Bailey St",
    "sg:city":"Bairnsdale",
    "sg:classifiers":[
        {
            "category":"Shopping",
            "subcategory":"Clothing, Apparel, & Fashions",
            "type":"Retail Goods"
        }
    ],
    "sg:phone":"+61 3 5152 5158",
    "sg:postcode":"3875",
    "sg:province":"VIC",
    "sg:tags":[
        "lady",
        "wear"
    ],
    "wof:name":"Miller's Fashion Club",
    "wof:placetype":"venue"
},
  "geometry": {"coordinates":[147.63157653799999,-37.825378418],"type":"Point"}
}