{
  "type": "Feature",
  "properties": {
    "iso:country":"AU",
    "sg:address":"27 Torino St",
    "sg:city":"Aspley",
    "sg:classifiers":[
        {
            "category":"Shopping",
            "subcategory":"Musical Instruments",
            "type":"Retail Goods"
        }
    ],
    "sg:phone":"+61 7 3263 4257",
    "sg:postcode":"4034",
    "sg:province":"QLD",
    "sg:tags":[
        "musician",
        "agent"
    ],
    "wof:name":"Purdie Rick",
    "wof:placetype":"venue"
},
  "geometry": {"coordinates":[153.029251,-27.359245],"type":"Point"}
}