{
  "type": "Feature",
  "properties": {
    "addr:full":"100 Barker Rd Harcourt North VIC 3453",
    "addr:housenumber":"100",
    "addr:postcode":"3453",
    "addr:street":"Barker Rd",
    "iso:country":"AU",
    "sg:address":"100 Barker Rd",
    "sg:city":"Harcourt North",
    "sg:classifiers":[
        {
            "category":"Building & Trades",
            "subcategory":"Plumbing",
            "type":"Services"
        }
    ],
    "sg:phone":"+61 3 5474 2367",
    "sg:postcode":"3453",
    "sg:province":"VIC",
    "sg:tags":[
        "plumber",
        "gasfitters"
    ],
    "wof:name":"Norris M G & L M",
    "wof:placetype":"venue"
},
  "geometry": {"coordinates":[144.29026794399999,-36.9446411133],"type":"Point"}
}