{
  "type": "Feature",
  "properties": {
    "iso:country":"AU",
    "sg:address":"77B Rundle Rd",
    "sg:city":"Salisbury South",
    "sg:classifiers":[
        {
            "category":"Building & Trades",
            "subcategory":"Cleaning & Sanitation",
            "type":"Services"
        }
    ],
    "sg:phone":"+61 8 8250 1647",
    "sg:postcode":"5106",
    "sg:province":"SA",
    "sg:tags":[
        "sweeping",
        "machine"
    ],
    "wof:name":"Dodge Sweepers & Scrubbers",
    "wof:placetype":"venue"
},
  "geometry": {"coordinates":[138.644638,-34.786163],"type":"Point"}
}