{
  "type": "Feature",
  "properties": {
    "iso:country":"AU",
    "sg:address":"30 Springdale St",
    "sg:city":"Wentworthville",
    "sg:classifiers":[
        {
            "category":"Professional",
            "subcategory":"Art Services",
            "type":"Services"
        }
    ],
    "sg:phone":"+61 2 9636 9409",
    "sg:postcode":"2145",
    "sg:province":"NSW",
    "sg:tags":[
        "decorator",
        "painter"
    ],
    "wof:name":"Hughes A C",
    "wof:placetype":"venue"
},
  "geometry": {"coordinates":[150.963180542,-33.8076705933],"type":"Point"}
}