{
  "type": "Feature",
  "properties": {
    "addr:full":"9 Brooklyn Ave Brighton VIC 3186",
    "addr:housenumber":"9",
    "addr:postcode":"3186",
    "addr:street":"Brooklyn Ave",
    "iso:country":"AU",
    "sg:address":"9 Brooklyn Ave",
    "sg:city":"Brighton",
    "sg:classifiers":[
        {
            "category":"Retail",
            "subcategory":"Repair Shop",
            "type":"Services"
        }
    ],
    "sg:phone":"+61 3 9587 4188",
    "sg:postcode":"3186",
    "sg:province":"VIC",
    "sg:tags":[
        "machine",
        "repairs",
        "part",
        "dryer",
        "washing"
    ],
    "wof:name":"P.T.R Appliances",
    "wof:placetype":"venue"
},
  "geometry": {"coordinates":[145.022338867,-37.894241333],"type":"Point"}
}