{
  "type": "Feature",
  "properties": {
    "addr:full":"Suite 3/ 307-317 Condamine St Manly Vale NSW 2093",
    "addr:housenumber":"/ 307-317",
    "addr:postcode":"2093",
    "addr:street":"Condamine St",
    "iso:country":"AU",
    "sg:address":"Suite 3/ 307-317 Condamine St",
    "sg:city":"Manly Vale",
    "sg:classifiers":[
        {
            "category":"Health Services",
            "subcategory":"Health Practitioner",
            "type":"Services"
        }
    ],
    "sg:phone":"+61 2 9949 5518",
    "sg:postcode":"2093",
    "sg:province":"NSW",
    "sg:tags":[
        "osteopath"
    ],
    "wof:name":"Barnes Stephen",
    "wof:placetype":"venue"
},
  "geometry": {"coordinates":[151.26705932600001,-33.7841796875],"type":"Point"}
}