{
  "type": "Feature",
  "properties": {
    "iso:country":"AU",
    "sg:address":"665a Darling St",
    "sg:city":"Rozelle",
    "sg:classifiers":[
        {
            "category":"Organizations",
            "subcategory":"Non-profit Organization",
            "type":"Services"
        }
    ],
    "sg:phone":"+61 2 9555 8988",
    "sg:postcode":"2039",
    "sg:province":"NSW",
    "sg:tags":[
        "support",
        "disability",
        "organisation"
    ],
    "wof:name":"Community Carers Team",
    "wof:placetype":"venue"
},
  "geometry": {"coordinates":[151.17025756800001,-33.8633232117],"type":"Point"}
}