{
  "type": "Feature",
  "properties": {
    "iso:country":"AU",
    "sg:address":"59 Beresford Rd",
    "sg:city":"Greystanes",
    "sg:classifiers":[
        {
            "category":"Building & Trades",
            "subcategory":"Construction",
            "type":"Services"
        }
    ],
    "sg:phone":"+61 2 8746 0510",
    "sg:postcode":"2145",
    "sg:province":"NSW",
    "sg:tags":[
        "plasterboard",
        "plasterer",
        "fixer"
    ],
    "wof:name":"Esterfall Pty Ltd",
    "wof:placetype":"venue"
},
  "geometry": {"coordinates":[150.941574097,-33.8133125305],"type":"Point"}
}