{
  "type": "Feature",
  "properties": {
    "addr:full":"Shop 5, 77 Oxford St Bulimba QLD 4171",
    "addr:housenumber":"shop;77",
    "addr:postcode":"4171",
    "addr:street":"Oxford St",
    "iso:country":"AU",
    "sg:address":"Shop 5, 77 Oxford St",
    "sg:city":"Bulimba",
    "sg:classifiers":[
        {
            "category":"Personal",
            "type":"Services"
        }
    ],
    "sg:phone":"+61 7 3899 3299",
    "sg:postcode":"4171",
    "sg:province":"QLD",
    "sg:tags":[
        "gift"
    ],
    "wof:name":"Baskets Of Balmoral",
    "wof:placetype":"venue"
},
  "geometry": {"coordinates":[153.05616760300001,-27.4510173798],"type":"Point"}
}