{
  "type": "Feature",
  "properties": {
    "iso:country":"AU",
    "sg:address":"4 Toorak Ave",
    "sg:city":"Bellevue Heights",
    "sg:classifiers":[
        {
            "category":"Building & Trades",
            "subcategory":"Landscaping Services",
            "type":"Services"
        }
    ],
    "sg:phone":"+61 8 8278 4405",
    "sg:postcode":"5050",
    "sg:province":"SA",
    "sg:tags":[
        "stump",
        "tree",
        "felling",
        "removal"
    ],
    "wof:name":"Bellevue Stump Cutters",
    "wof:placetype":"venue"
},
  "geometry": {"coordinates":[138.58595299999999,-35.032181],"type":"Point"}
}