{
  "type": "Feature",
  "properties": {
    "addr:full":"Shop 14, Grove Plaza Shopping Centre Cottesloe WA 6011",
    "addr:housenumber":"shop 14",
    "addr:postcode":"6011",
    "addr:street":"Grove",
    "iso:country":"AU",
    "sg:address":"Shop 14, Grove Plaza Shopping Centre",
    "sg:city":"Cottesloe",
    "sg:classifiers":[
        {
            "category":"Travel",
            "subcategory":"Travel Agent",
            "type":"Entertainment"
        }
    ],
    "sg:phone":"+61 8 9383 1622",
    "sg:postcode":"6011",
    "sg:province":"WA",
    "sg:tags":[
        "consultant"
    ],
    "wof:name":"Jetset",
    "wof:placetype":"venue"
},
  "geometry": {"coordinates":[115.757278442,-31.996049881],"type":"Point"}
}