{
  "type": "Feature",
  "properties": {
    "addr:full":"Lot 553 Valencia Rd Maddington WA 6109",
    "addr:postcode":"6109",
    "addr:street":"Valencia Rd",
    "iso:country":"AU",
    "sg:address":"Lot 553 Valencia Rd",
    "sg:city":"Maddington",
    "sg:classifiers":[
        {
            "category":"Building & Trades",
            "subcategory":"Construction",
            "type":"Services"
        }
    ],
    "sg:phone":"+61 8 9493 1900",
    "sg:postcode":"6109",
    "sg:province":"WA",
    "sg:tags":[
        "bitumen",
        "paving",
        "asphalt"
    ],
    "wof:name":"Premier Paving & Site Services",
    "wof:placetype":"venue"
},
  "geometry": {"coordinates":[115.995597839,-32.0352783203],"type":"Point"}
}