{
  "type": "Feature",
  "properties": {
    "iso:country":"AU",
    "sg:address":"36 Martingale Ave",
    "sg:city":"Henley Brook",
    "sg:classifiers":[
        {
            "category":"Health Services",
            "subcategory":"Health Practitioner",
            "type":"Services"
        }
    ],
    "sg:phone":"+61 411 184 934",
    "sg:postcode":"6055",
    "sg:province":"WA",
    "sg:tags":[
        "bowen",
        "therapy"
    ],
    "wof:name":"Melanie Locke",
    "wof:placetype":"venue"
},
  "geometry": {"coordinates":[115.974602,-31.800121],"type":"Point"}
}