{
  "type": "Feature",
  "properties": {
    "iso:country":"AU",
    "sg:address":"Shp 13, Victoria Crt",
    "sg:city":"Gosford East",
    "sg:classifiers":[
        {
            "category":"Personal",
            "subcategory":"Nail Salon",
            "type":"Services"
        }
    ],
    "sg:phone":"+61 2 4324 7009",
    "sg:postcode":"2250",
    "sg:province":"NSW",
    "sg:tags":[
        "artificial"
    ],
    "wof:name":"Beautique Beauty Spa",
    "wof:placetype":"venue"
},
  "geometry": {"coordinates":[151.35588073700001,-33.4397583008],"type":"Point"}
}