{
  "type": "Feature",
  "properties": {
    "iso:country":"AU",
    "sg:address":"195b Corio St",
    "sg:city":"Shepparton",
    "sg:classifiers":[
        {
            "category":"Retail",
            "subcategory":"Storage",
            "type":"Services"
        }
    ],
    "sg:phone":"+61 3 5822 2925",
    "sg:postcode":"3630",
    "sg:province":"VIC",
    "wof:name":"Printworks Document Scanning & Digital Archival",
    "wof:placetype":"venue"
},
  "geometry": {"coordinates":[145.40333557100001,-36.3825645447],"type":"Point"}
}