{
  "type": "Feature",
  "properties": {
    "addr:full":"76 Shore St Cleveland QLD 4163",
    "addr:housenumber":"76",
    "addr:postcode":"4163",
    "addr:street":"Shore St",
    "iso:country":"AU",
    "sg:address":"76 Shore St",
    "sg:city":"Cleveland",
    "sg:classifiers":[
        {
            "category":"Autos & Motor Vehicles",
            "subcategory":"Boat Sales",
            "type":"Retail Goods"
        }
    ],
    "sg:phone":"+61 7 3286 4137",
    "sg:postcode":"4163",
    "sg:province":"QLD",
    "sg:tags":[
        "yacht"
    ],
    "wof:name":"Cleveland Boating Services",
    "wof:placetype":"venue"
},
  "geometry": {"coordinates":[153.25833129899999,-27.5244274139],"type":"Point"}
}