{
  "type": "Feature",
  "properties": {
    "iso:country":"AU",
    "sg:address":"108 Pinetree Gully Rd",
    "sg:city":"Willetton",
    "sg:classifiers":[
        {
            "category":"Health Services",
            "subcategory":"Health Practitioner",
            "type":"Services"
        }
    ],
    "sg:phone":"+61 8 9332 2840",
    "sg:postcode":"6155",
    "sg:province":"WA",
    "sg:tags":[
        "pathologist",
        "speech"
    ],
    "wof:name":"Capricorn Speech Pathology",
    "wof:placetype":"venue"
},
  "geometry": {"coordinates":[115.88091300000001,-32.058735],"type":"Point"}
}