{
  "type": "Feature",
  "properties": {
    "iso:country":"AU",
    "sg:address":"5 Canterbury Rd",
    "sg:city":"Blackburn South",
    "sg:classifiers":[
        {
            "category":"Fast Food",
            "type":"Food & Drink"
        }
    ],
    "sg:phone":"+61 3 9890 9782",
    "sg:postcode":"3130",
    "sg:province":"VIC",
    "sg:tags":[
        "away",
        "take"
    ],
    "wof:name":"Kadai Curry Kitchen",
    "wof:placetype":"venue"
},
  "geometry": {"coordinates":[145.13638305699999,-37.8305854797],"type":"Point"}
}