{
  "type": "Feature",
  "properties": {
    "addr:full":"151 Esther St Belmont WA 6104",
    "addr:housenumber":"151",
    "addr:postcode":"6104",
    "addr:street":"Esther St",
    "iso:country":"AU",
    "sg:address":"151 Esther St",
    "sg:city":"Belmont",
    "sg:classifiers":[
        {
            "category":"Education",
            "subcategory":"School",
            "type":"Public Place"
        }
    ],
    "sg:phone":"+61 8 9478 7444",
    "sg:postcode":"6104",
    "sg:province":"WA",
    "sg:tags":[
        "supply"
    ],
    "wof:name":"Supply West",
    "wof:placetype":"venue"
},
  "geometry": {"coordinates":[115.92388153100001,-31.9612026215],"type":"Point"}
}