{
  "type": "Feature",
  "properties": {
    "iso:country":"AU",
    "sg:address":"3/ 129 Willard St",
    "sg:city":"Carina Heights",
    "sg:classifiers":[
        {
            "category":"Personal",
            "type":"Services"
        }
    ],
    "sg:phone":"+61 7 3324 8070",
    "sg:postcode":"4152",
    "sg:province":"QLD",
    "sg:tags":[
        "reducing",
        "treatment",
        "weight"
    ],
    "wof:name":"Herbalife Carina Heights",
    "wof:placetype":"venue"
},
  "geometry": {"coordinates":[153.09361267099999,-27.5051574707],"type":"Point"}
}