{
  "type": "Feature",
  "properties": {
    "addr:full":"31 Pascoe Ave Essendon North VIC 3041",
    "addr:housenumber":"31",
    "addr:postcode":"3041",
    "addr:street":"Pascoe Ave",
    "iso:country":"AU",
    "sg:address":"31 Pascoe Ave",
    "sg:city":"Essendon North",
    "sg:classifiers":[
        {
            "category":"Building & Trades",
            "subcategory":"Construction",
            "type":"Services"
        }
    ],
    "sg:phone":"+61 3 9379 1992",
    "sg:postcode":"3041",
    "sg:province":"VIC",
    "sg:tags":[
        "plasterboard",
        "plasterer",
        "fixer"
    ],
    "wof:name":"C.P. Plaster",
    "wof:placetype":"venue"
},
  "geometry": {"coordinates":[144.928466797,-37.7415618896],"type":"Point"}
}