{
  "type": "Feature",
  "properties": {
    "iso:country":"AU",
    "sg:address":"Factory 5 / 820 Princes Hwy",
    "sg:city":"Springvale",
    "sg:classifiers":[
        {
            "category":"Building & Trades",
            "subcategory":"Construction",
            "type":"Services"
        }
    ],
    "sg:phone":"+61 1300 764 354",
    "sg:postcode":"3171",
    "sg:province":"VIC",
    "sg:tags":[
        "pool",
        "swimming"
    ],
    "wof:name":"Structural Pools Aust",
    "wof:placetype":"venue"
},
  "geometry": {"coordinates":[145.16189575199999,-37.9441184998],"type":"Point"}
}