{
  "type": "Feature",
  "properties": {
    "addr:full":"Parkmore Shopping Centre Shop H09 Cheltenham Rd Keysborough VIC 3173",
    "addr:housenumber":"h09",
    "addr:postcode":"3173",
    "addr:street":"Cheltenham Rd",
    "iso:country":"AU",
    "sg:address":"Parkmore Shopping Centre Shop H09 Cheltenham Rd",
    "sg:city":"Keysborough",
    "sg:classifiers":[
        {
            "category":"Shopping",
            "subcategory":"Jewelry",
            "type":"Retail Goods"
        }
    ],
    "sg:phone":"+61 3 9769 0265",
    "sg:postcode":"3173",
    "sg:province":"VIC",
    "sg:tags":[
        "jeweller"
    ],
    "wof:name":"Prouds The Jewellers",
    "wof:placetype":"venue"
},
  "geometry": {"coordinates":[145.16888427699999,-37.99376297],"type":"Point"}
}