{
  "type": "Feature",
  "properties": {
    "addr:full":"10 Railway Pde Springwood NSW 2777",
    "addr:housenumber":"10",
    "addr:postcode":"2777",
    "addr:street":"Railway Pde",
    "iso:country":"AU",
    "sg:address":"10 Railway Pde",
    "sg:city":"Springwood",
    "sg:classifiers":[
        {
            "category":"Shopping",
            "subcategory":"Antiques",
            "type":"Retail Goods"
        }
    ],
    "sg:phone":"+61 2 4751 1424",
    "sg:postcode":"2777",
    "sg:province":"NSW",
    "sg:tags":[
        "restoration",
        "reproduction"
    ],
    "wof:name":"Bunda",
    "wof:placetype":"venue"
},
  "geometry": {"coordinates":[150.574951172,-33.7024726868],"type":"Point"}
}