{
  "type": "Feature",
  "properties": {
    "addr:full":"82 Levanswell Rd Moorabbin VIC 3189",
    "addr:housenumber":"82",
    "addr:postcode":"3189",
    "addr:street":"Levanswell Rd",
    "iso:country":"AU",
    "sg:address":"82 Levanswell Rd",
    "sg:city":"Moorabbin",
    "sg:classifiers":[
        {
            "category":"Utilities",
            "subcategory":"Recycling",
            "type":"Services"
        }
    ],
    "sg:phone":"+61 3 9555 5559",
    "sg:postcode":"3189",
    "sg:province":"VIC",
    "wof:name":"Olympic Polymers Pty Ltd",
    "wof:placetype":"venue"
},
  "geometry": {"coordinates":[145.07179260300001,-37.9457626343],"type":"Point"}
}