{
  "type": "Feature",
  "properties": {
    "iso:country":"AU",
    "sg:address":"Shop 2, Goolwa Shopping Ctr, Hutchinson St",
    "sg:city":"Goolwa",
    "sg:classifiers":[
        {
            "category":"Personal",
            "subcategory":"Beauty Salon",
            "type":"Services"
        }
    ],
    "sg:phone":"+61 8 8555 2220",
    "sg:postcode":"5214",
    "sg:province":"SA",
    "sg:tags":[
        "hairdresser"
    ],
    "wof:name":"Goolwa South Coast Hair Care",
    "wof:placetype":"venue"
},
  "geometry": {"coordinates":[138.77786254899999,-35.5047149658],"type":"Point"}
}