{
  "type": "Feature",
  "properties": {
    "addr:full":"Lot 14 Teran Cl Gateshead NSW 2290",
    "addr:postcode":"2290",
    "addr:street":"Teran Cl",
    "iso:country":"AU",
    "sg:address":"Lot 14 Teran Cl",
    "sg:city":"Gateshead",
    "sg:classifiers":[
        {
            "category":"Building & Trades",
            "subcategory":"Construction",
            "type":"Services"
        }
    ],
    "sg:phone":"+61 2 4942 5496",
    "sg:postcode":"2290",
    "sg:province":"NSW",
    "sg:tags":[
        "road",
        "contractor"
    ],
    "wof:name":"Ian Rich Asphalt Pty Ltd",
    "wof:placetype":"venue"
},
  "geometry": {"coordinates":[151.75787353499999,-32.911365509],"type":"Point"}
}