{
  "type": "Feature",
  "properties": {
    "addr:full":"69 Cooks Rd Peats Ridge NSW 2250",
    "addr:housenumber":"69",
    "addr:postcode":"2250",
    "addr:street":"Cooks Rd",
    "iso:country":"AU",
    "sg:address":"69 Cooks Rd",
    "sg:city":"Peats Ridge",
    "sg:classifiers":[
        {
            "category":"Travel",
            "subcategory":"Travel Agent",
            "type":"Entertainment"
        }
    ],
    "sg:phone":"+61 2 4375 1222",
    "sg:postcode":"2250",
    "sg:province":"NSW",
    "sg:tags":[
        "tour",
        "holiday",
        "adventure"
    ],
    "wof:name":"Glenworth Valley Horse Riding Pty Ltd",
    "wof:placetype":"venue"
},
  "geometry": {"coordinates":[151.20950317399999,-33.4015541077],"type":"Point"}
}