{
  "type": "Feature",
  "properties": {
    "iso:country":"AU",
    "sg:address":"570 Canterbury Rd",
    "sg:city":"Vermont",
    "sg:classifiers":[
        {
            "category":"Home & Garden",
            "subcategory":"Building Materials",
            "type":"Retail Goods"
        }
    ],
    "sg:phone":"+61 3 9873 8970",
    "sg:postcode":"3133",
    "sg:province":"VIC",
    "sg:tags":[
        "supply"
    ],
    "wof:name":"The Roof & Gutter Shop",
    "wof:placetype":"venue"
},
  "geometry": {"coordinates":[145.19288635300001,-37.8368644714],"type":"Point"}
}