{
  "type": "Feature",
  "properties": {
    "addr:full":"Carraboi St Wooli NSW 2462",
    "addr:postcode":"2462",
    "addr:street":"St",
    "iso:country":"AU",
    "sg:address":"Carraboi St",
    "sg:city":"Wooli",
    "sg:classifiers":[
        {
            "category":"Food & Beverages",
            "subcategory":"Groceries & Convenience Stores",
            "type":"Retail Goods"
        }
    ],
    "sg:phone":"+61 2 6649 7606",
    "sg:postcode":"2462",
    "sg:province":"NSW",
    "wof:name":"Wooli Kiosk",
    "wof:placetype":"venue"
},
  "geometry": {"coordinates":[153.26632690400001,-29.8638076782],"type":"Point"}
}