{
  "type": "Feature",
  "properties": {
    "iso:country":"AU",
    "sg:address":"6/ 88 Garden St",
    "sg:city":"Narrabeen",
    "sg:classifiers":[
        {
            "category":"Professional",
            "type":"Services"
        }
    ],
    "sg:phone":"+61 2 9913 3122",
    "sg:postcode":"2101",
    "sg:province":"NSW",
    "sg:tags":[
        "spray",
        "painting"
    ],
    "wof:name":"Lone Ranger Polyurethane",
    "wof:placetype":"venue"
},
  "geometry": {"coordinates":[151.294861,-33.700584],"type":"Point"}
}