{
  "type": "Feature",
  "properties": {
    "iso:country":"AU",
    "sg:address":"1 Farrell Pl",
    "sg:city":"Canberra City",
    "sg:classifiers":[
        {
            "category":"Professional",
            "subcategory":"Computer Services",
            "type":"Services"
        }
    ],
    "sg:phone":"+61 2 6257 6661",
    "sg:postcode":"2601",
    "sg:province":"ACT",
    "sg:tags":[
        "consultant",
        "system"
    ],
    "wof:name":"A.I.P.C.",
    "wof:placetype":"venue"
},
  "geometry": {"coordinates":[149.12474060100001,-35.2808189392],"type":"Point"}
}