{
  "type": "Feature",
  "properties": {
    "iso:country":"AU",
    "sg:address":"8- 26 Birtwell St",
    "sg:city":"Coolum Beach",
    "sg:classifiers":[
        {
            "category":"Health Services",
            "subcategory":"Doctor",
            "type":"Services"
        }
    ],
    "sg:phone":"+61 7 5471 6333",
    "sg:postcode":"4573",
    "sg:province":"QLD",
    "sg:tags":[
        "medical",
        "practitioner"
    ],
    "wof:name":"Coolum Beach 7 Day Doctors",
    "wof:placetype":"venue"
},
  "geometry": {"coordinates":[153.087494,-26.526644],"type":"Point"}
}