{
  "type": "Feature",
  "properties": {
    "addr:full":"36 Main St Pakenham VIC 3810",
    "addr:housenumber":"36",
    "addr:postcode":"3810",
    "addr:street":"Main St",
    "iso:country":"AU",
    "sg:address":"36 Main St",
    "sg:city":"Pakenham",
    "sg:classifiers":[
        {
            "category":"Health Services",
            "subcategory":"Health Practitioner",
            "type":"Services"
        }
    ],
    "sg:phone":"+61 3 5941 3688",
    "sg:postcode":"3810",
    "sg:province":"VIC",
    "sg:tags":[
        "physiotherapist"
    ],
    "wof:name":"Edwards Ross",
    "wof:placetype":"venue"
},
  "geometry": {"coordinates":[145.47860700000001,-38.074257],"type":"Point"}
}