{
  "type": "Feature",
  "properties": {
    "addr:full":"Shop 5 Canberra St St Johns Park NSW 2176",
    "addr:housenumber":"shop 5",
    "addr:postcode":"2176",
    "addr:street":"Canberra St St",
    "iso:country":"AU",
    "sg:address":"Shop 5 Canberra St",
    "sg:city":"St Johns Park",
    "sg:classifiers":[
        {
            "category":"Communications",
            "subcategory":"Film & Video Production",
            "type":"Services"
        }
    ],
    "sg:phone":"+61 2 9610 6128",
    "sg:postcode":"2176",
    "sg:province":"NSW",
    "sg:tags":[
        "dvd",
        "library"
    ],
    "wof:name":"St Johns Park Video",
    "wof:placetype":"venue"
},
  "geometry": {"coordinates":[150.90176391599999,-33.8794174194],"type":"Point"}
}