{
  "type": "Feature",
  "properties": {
    "iso:country":"AU",
    "sg:address":"81 Pirie St",
    "sg:city":"Adelaide",
    "sg:classifiers":[
        {
            "category":"Personal",
            "subcategory":"Beauty Salon",
            "type":"Services"
        }
    ],
    "sg:phone":"+61 8 8232 9299",
    "sg:postcode":"5000",
    "sg:province":"SA",
    "wof:name":"Diva Beauty",
    "wof:placetype":"venue"
},
  "geometry": {"coordinates":[138.60223388700001,-34.92578125],"type":"Point"}
}