{
  "type": "Feature",
  "properties": {
    "addr:full":"67 Alexander Ave Taren Point NSW 2229",
    "addr:housenumber":"67",
    "addr:postcode":"2229",
    "addr:street":"Alexander Ave",
    "iso:country":"AU",
    "sg:address":"67 Alexander Ave",
    "sg:city":"Taren Point",
    "sg:classifiers":[
        {
            "category":"Professional",
            "type":"Services"
        }
    ],
    "sg:phone":"+61 2 9525 2288",
    "sg:postcode":"2229",
    "sg:province":"NSW",
    "sg:tags":[
        "marine",
        "contractor"
    ],
    "wof:name":"Jenkins R Constructions Pty Ltd",
    "wof:placetype":"venue"
},
  "geometry": {"coordinates":[151.12374877900001,-34.0231018066],"type":"Point"}
}