{
  "type": "Feature",
  "properties": {
    "iso:country":"AU",
    "sg:address":"33 Lemore St",
    "sg:city":"Boondall",
    "sg:classifiers":[
        {
            "category":"Building & Trades",
            "subcategory":"Construction",
            "type":"Services"
        }
    ],
    "sg:phone":"+61 414 320 542",
    "sg:postcode":"4034",
    "sg:province":"QLD",
    "sg:tags":[
        "contractor"
    ],
    "wof:name":"Ironbark Constructions",
    "wof:placetype":"venue"
},
  "geometry": {"coordinates":[153.058365,-27.35047],"type":"Point"}
}