{
  "type": "Feature",
  "properties": {
    "iso:country":"AU",
    "sg:address":"Suite 1, 22- 26 Herbert St",
    "sg:city":"West Ryde",
    "sg:classifiers":[
        {
            "category":"Health Services",
            "subcategory":"Dentist",
            "type":"Services"
        }
    ],
    "sg:phone":"+61 2 9802 5832",
    "sg:postcode":"2114",
    "sg:province":"NSW",
    "sg:tags":[
        "dental",
        "prosthetist"
    ],
    "wof:name":"Crest Dental Laboratory",
    "wof:placetype":"venue"
},
  "geometry": {"coordinates":[151.09201049800001,-33.8073959351],"type":"Point"}
}