{
  "type": "Feature",
  "properties": {
    "addr:full":"Unit 20 / 84 Reserve Rd Artarmon NSW 2064",
    "addr:housenumber":"/ 84",
    "addr:postcode":"2064",
    "addr:street":"Reserve Rd",
    "iso:country":"AU",
    "sg:address":"Unit 20 / 84 Reserve Rd",
    "sg:city":"Artarmon",
    "sg:classifiers":[
        {
            "category":"Professional",
            "subcategory":"Printing & Photocopies",
            "type":"Services"
        }
    ],
    "sg:phone":"+61 2 9901 3666",
    "sg:postcode":"2064",
    "sg:province":"NSW",
    "sg:tags":[
        "photocopier"
    ],
    "sg:website":"http://www.austan.com.au",
    "wof:name":"Austan Rentals",
    "wof:placetype":"venue"
},
  "geometry": {"coordinates":[151.18760681099999,-33.8171081543],"type":"Point"}
}