{
  "type": "Feature",
  "properties": {
    "iso:country":"AU",
    "sg:address":"690 High St",
    "sg:city":"Thornbury",
    "sg:classifiers":[
        {
            "category":"Real Estate",
            "subcategory":"Real Estate Agent",
            "type":"Services"
        }
    ],
    "sg:phone":"+61 3 9480 6600",
    "sg:postcode":"3071",
    "sg:province":"VIC",
    "wof:name":"Thomas & Quixley Pty Ltd",
    "wof:placetype":"venue"
},
  "geometry": {"coordinates":[145.000823975,-37.7582893372],"type":"Point"}
}