{
  "type": "Feature",
  "properties": {
    "addr:full":"322 Unley Rd Hyde Park SA 5061",
    "addr:housenumber":"322",
    "addr:postcode":"5061",
    "addr:street":"Unley Rd",
    "iso:country":"AU",
    "sg:address":"322 Unley Rd",
    "sg:city":"Hyde Park",
    "sg:classifiers":[
        {
            "category":"Building & Trades",
            "subcategory":"Construction",
            "type":"Services"
        }
    ],
    "sg:phone":"+61 408 815 349",
    "sg:postcode":"5061",
    "sg:province":"SA",
    "sg:tags":[
        "renovation",
        "alterations",
        "extension",
        "contractor"
    ],
    "wof:name":"Tony Fachin Carpentry & Building",
    "wof:placetype":"venue"
},
  "geometry": {"coordinates":[138.60792541500001,-34.957824707],"type":"Point"}
}