{
  "type": "Feature",
  "properties": {
    "iso:country":"AU",
    "sg:address":"169a Jasper Rd",
    "sg:city":"Bentleigh",
    "sg:classifiers":[
        {
            "category":"Professional",
            "subcategory":"Accounting & Tax Preparation",
            "type":"Services"
        }
    ],
    "sg:phone":"+61 3 9563 9370",
    "sg:postcode":"3204",
    "sg:province":"VIC",
    "sg:tags":[
        "accountant",
        "auditor"
    ],
    "wof:name":"Shepperd & Co",
    "wof:placetype":"venue"
},
  "geometry": {"coordinates":[145.041519,-37.918678],"type":"Point"}
}