{
  "type": "Feature",
  "properties": {
    "addr:full":"5 Waratah St Scone NSW 2337",
    "addr:housenumber":"5",
    "addr:postcode":"2337",
    "addr:street":"Waratah St",
    "iso:country":"AU",
    "sg:address":"5 Waratah St",
    "sg:city":"Scone",
    "sg:classifiers":[
        {
            "category":"Building & Trades",
            "subcategory":"Construction",
            "type":"Services"
        }
    ],
    "sg:phone":"+61 411 120 129",
    "sg:postcode":"2337",
    "sg:province":"NSW",
    "sg:tags":[
        "earth",
        "excavating",
        "moving",
        "contractor"
    ],
    "wof:name":"Scone Dingo Service",
    "wof:placetype":"venue"
},
  "geometry": {"coordinates":[150.87767028799999,-32.0488204956],"type":"Point"}
}