{
  "type": "Feature",
  "properties": {
    "addr:full":"Shd1/ 14 Brian Rd Lonsdale SA 5160",
    "addr:housenumber":"14",
    "addr:postcode":"5160",
    "addr:street":"Brian Rd",
    "iso:country":"AU",
    "sg:address":"Shd1/ 14 Brian Rd",
    "sg:city":"Lonsdale",
    "sg:classifiers":[
        {
            "category":"Building & Trades",
            "subcategory":"Construction",
            "type":"Services"
        }
    ],
    "sg:phone":"+61 8 8322 1000",
    "sg:postcode":"5160",
    "sg:province":"SA",
    "sg:tags":[
        "window",
        "aluminium"
    ],
    "wof:name":"Cathedral Doors & Windows",
    "wof:placetype":"venue"
},
  "geometry": {"coordinates":[138.505935669,-35.1012115479],"type":"Point"}
}