{
  "type": "Feature",
  "properties": {
    "addr:full":"Cnr Bibby&#039;s & Edensor Rds Bonnyrigg NSW 2177",
    "addr:postcode":"2177",
    "addr:street":"Cnr",
    "iso:country":"AU",
    "sg:address":"Cnr Bibby&#039;s & Edensor Rds",
    "sg:city":"Bonnyrigg",
    "sg:classifiers":[
        {
            "category":"Food & Beverages",
            "subcategory":"Supermarket",
            "type":"Retail Goods"
        }
    ],
    "sg:phone":"+61 2 9823 4012",
    "sg:postcode":"2177",
    "sg:province":"NSW",
    "sg:tags":[
        "grocery",
        "store"
    ],
    "wof:name":"Quix Food Stores",
    "wof:placetype":"venue"
},
  "geometry": {"coordinates":[150.894897461,-33.8856468201],"type":"Point"}
}