{
  "type": "Feature",
  "properties": {
    "iso:country":"AU",
    "sg:address":"54 East Rd",
    "sg:city":"Pearsall",
    "sg:classifiers":[
        {
            "category":"Professional",
            "subcategory":"Art Services",
            "type":"Services"
        }
    ],
    "sg:phone":"+61 8 9405 6489",
    "sg:postcode":"6065",
    "sg:province":"WA",
    "sg:tags":[
        "decorator",
        "painter"
    ],
    "wof:name":"S & S Lamancusa Painters",
    "wof:placetype":"venue"
},
  "geometry": {"coordinates":[115.81414032000001,-31.7772445679],"type":"Point"}
}