{
  "type": "Feature",
  "properties": {
    "addr:full":"6 Williams St Largs NSW 2320",
    "addr:housenumber":"6",
    "addr:postcode":"2320",
    "addr:street":"Williams St",
    "iso:country":"AU",
    "sg:address":"6 Williams St",
    "sg:city":"Largs",
    "sg:classifiers":[
        {
            "category":"Mining & Drilling",
            "type":"Manufacturing & Wholesale Goods"
        }
    ],
    "sg:phone":"+61 418 685 670",
    "sg:postcode":"2320",
    "sg:province":"NSW",
    "sg:tags":[
        "boring",
        "contractor"
    ],
    "wof:name":"Alans Underroad Drilling Services",
    "wof:placetype":"venue"
},
  "geometry": {"coordinates":[151.60226440400001,-32.7039718628],"type":"Point"}
}