{
  "type": "Feature",
  "properties": {
    "iso:country":"AU",
    "sg:address":"18 Mead St",
    "sg:city":"Belair",
    "sg:classifiers":[
        {
            "category":"Health Services",
            "subcategory":"Doctor",
            "type":"Services"
        }
    ],
    "sg:phone":"+61 8 8278 3588",
    "sg:postcode":"5052",
    "sg:province":"SA",
    "sg:tags":[
        "occupational",
        "safety"
    ],
    "sg:website":"http://www.festraining.com.au",
    "wof:name":"F.E.S. Training",
    "wof:placetype":"venue"
},
  "geometry": {"coordinates":[138.603806,-35.007954],"type":"Point"}
}