{
  "type": "Feature",
  "properties": {
    "iso:country":"AU",
    "sg:address":"25 Arnett St",
    "sg:city":"Pendle Hill",
    "sg:classifiers":[
        {
            "category":"Professional",
            "subcategory":"Art Services",
            "type":"Services"
        }
    ],
    "sg:phone":"+61 2 9631 9093",
    "sg:postcode":"2145",
    "sg:province":"NSW",
    "sg:tags":[
        "decorator",
        "painter"
    ],
    "wof:name":"Jolly A E",
    "wof:placetype":"venue"
},
  "geometry": {"coordinates":[150.956497192,-33.8105354309],"type":"Point"}
}