{
  "type": "Feature",
  "properties": {
    "iso:country":"AU",
    "sg:address":"17 Rowntree St",
    "sg:city":"Balmain",
    "sg:classifiers":[
        {
            "category":"Personal",
            "subcategory":"Hair Removal",
            "type":"Services"
        }
    ],
    "sg:phone":"+61 1300 663 436",
    "sg:postcode":"2041",
    "sg:province":"NSW",
    "wof:name":"Splash Beauty Solutions",
    "wof:placetype":"venue"
},
  "geometry": {"coordinates":[151.178436,-33.855862],"type":"Point"}
}