{
  "type": "Feature",
  "properties": {
    "iso:country":"AU",
    "sg:address":"Suite 1, Level 1, 111 Henry St",
    "sg:city":"Penrith",
    "sg:classifiers":[
        {
            "category":"Professional",
            "subcategory":"Business Services",
            "type":"Services"
        }
    ],
    "sg:phone":"+61 1300 650 058",
    "sg:postcode":"2740",
    "sg:province":"NSW",
    "sg:tags":[
        "small",
        "advisory"
    ],
    "wof:name":"Greater Nepean Business Advisory Service",
    "wof:placetype":"venue"
},
  "geometry": {"coordinates":[150.699524,-33.752705],"type":"Point"}
}