{
  "type": "Feature",
  "properties": {
    "iso:country":"AU",
    "sg:address":"10a Williamson Rd",
    "sg:city":"Maribyrnong",
    "sg:classifiers":[
        {
            "category":"Wholesale",
            "subcategory":"Auto Parts",
            "type":"Manufacturing & Wholesale Goods"
        }
    ],
    "sg:phone":"+61 3 9318 1669",
    "sg:postcode":"3032",
    "sg:province":"VIC",
    "sg:tags":[
        "recyclers"
    ],
    "wof:name":"Peter's Radiator Service",
    "wof:placetype":"venue"
},
  "geometry": {"coordinates":[144.884109,-37.775181],"type":"Point"}
}