{
  "type": "Feature",
  "properties": {
    "addr:full":"326 Wanneroo Rd Nollamara WA 6061",
    "addr:housenumber":"326",
    "addr:postcode":"6061",
    "addr:street":"Wanneroo Rd",
    "iso:country":"AU",
    "sg:address":"326 Wanneroo Rd",
    "sg:city":"Nollamara",
    "sg:classifiers":[
        {
            "category":"Health Services",
            "subcategory":"Health Practitioner",
            "type":"Services"
        }
    ],
    "sg:phone":"+61 8 9344 6666",
    "sg:postcode":"6061",
    "sg:province":"WA",
    "sg:tags":[
        "naturopath"
    ],
    "wof:name":"Polly Clinic",
    "wof:placetype":"venue"
},
  "geometry": {"coordinates":[115.83399963399999,-31.8787155151],"type":"Point"}
}