{
  "type": "Feature",
  "properties": {
    "addr:full":"Shp62 / 62 Spring Sq Hallam VIC 3803",
    "addr:housenumber":"62",
    "addr:postcode":"3803",
    "addr:street":"Spring Sq",
    "iso:country":"AU",
    "sg:address":"Shp62",
    "sg:city":"/ 62 Spring Sq Hallam",
    "sg:classifiers":[
        {
            "category":"Food & Beverages",
            "subcategory":"Supermarket",
            "type":"Retail Goods"
        }
    ],
    "sg:phone":"+61 3 9702 4056",
    "sg:postcode":"3803",
    "sg:province":"VIC",
    "sg:tags":[
        "grocery",
        "store"
    ],
    "wof:name":"Nangahaar Supermarket",
    "wof:placetype":"venue"
},
  "geometry": {"coordinates":[145.26640319800001,-38.0038948059],"type":"Point"}
}