{
  "type": "Feature",
  "properties": {
    "iso:country":"AU",
    "sg:address":"25 Barrington Ave",
    "sg:city":"Kew",
    "sg:classifiers":[
        {
            "category":"Health Services",
            "subcategory":"Health Practitioner",
            "type":"Services"
        }
    ],
    "sg:phone":"+61 3 9817 3244",
    "sg:postcode":"3101",
    "sg:province":"VIC",
    "sg:tags":[
        "psychologist"
    ],
    "wof:name":"Kathy Deutsch & Associates",
    "wof:placetype":"venue"
},
  "geometry": {"coordinates":[145.04400634800001,-37.8063468933],"type":"Point"}
}