{
  "type": "Feature",
  "properties": {
    "addr:full":"9a Armstrong St Petrie QLD 4502",
    "addr:housenumber":"9a",
    "addr:postcode":"4502",
    "addr:street":"Armstrong St",
    "iso:country":"AU",
    "sg:address":"9a Armstrong St",
    "sg:city":"Petrie",
    "sg:classifiers":[
        {
            "category":"Education",
            "subcategory":"Kindergarten",
            "type":"Public Place"
        }
    ],
    "sg:phone":"+61 7 3285 4033",
    "sg:postcode":"4502",
    "sg:province":"QLD",
    "sg:tags":[
        "pre-schools"
    ],
    "wof:name":"Living Faith Early Learning Centre",
    "wof:placetype":"venue"
},
  "geometry": {"coordinates":[152.97836303700001,-27.2682647705],"type":"Point"}
}