{
  "type": "Feature",
  "properties": {
    "addr:full":"7 Harvest Rd Yandina QLD 4561",
    "addr:housenumber":"7",
    "addr:postcode":"4561",
    "addr:street":"Harvest Rd",
    "iso:country":"AU",
    "sg:address":"7 Harvest Rd",
    "sg:city":"Yandina",
    "sg:classifiers":[
        {
            "category":"Home & Garden",
            "subcategory":"Garden Supply",
            "type":"Retail Goods"
        }
    ],
    "sg:phone":"+61 7 5472 9900",
    "sg:postcode":"4561",
    "sg:province":"QLD",
    "sg:tags":[
        "fertilizer"
    ],
    "wof:name":"Nutri-Tech Solutions Pty Ltd",
    "wof:placetype":"venue"
},
  "geometry": {"coordinates":[152.96322631800001,-26.5550918579],"type":"Point"}
}