{
  "type": "Feature",
  "properties": {
    "addr:full":"16 Havilah St Chatswood NSW 2067",
    "addr:housenumber":"16",
    "addr:postcode":"2067",
    "addr:street":"Havilah St",
    "iso:country":"AU",
    "sg:address":"16 Havilah St",
    "sg:city":"Chatswood",
    "sg:classifiers":[
        {
            "category":"Professional",
            "subcategory":"Accounting & Tax Preparation",
            "type":"Services"
        }
    ],
    "sg:phone":"+61 2 9419 2363",
    "sg:postcode":"2067",
    "sg:province":"NSW",
    "sg:tags":[
        "accountant",
        "auditor"
    ],
    "wof:name":"O&#039;Neill Grant & Co",
    "wof:placetype":"venue"
},
  "geometry": {"coordinates":[151.18728637699999,-33.793636322],"type":"Point"}
}