{
  "type": "Feature",
  "properties": {
    "iso:country":"AU",
    "sg:address":"2 Carcoar St",
    "sg:city":"Blayney",
    "sg:classifiers":[
        {
            "category":"Retail",
            "subcategory":"Auto Repair",
            "type":"Services"
        }
    ],
    "sg:phone":"+61 2 6368 2021",
    "sg:postcode":"2799",
    "sg:province":"NSW",
    "sg:tags":[
        "repairer",
        "motor",
        "engineer"
    ],
    "wof:name":"Blayney Pit Stop Auto's",
    "wof:placetype":"venue"
},
  "geometry": {"coordinates":[149.247955,-33.53772],"type":"Point"}
}