{
  "type": "Feature",
  "properties": {
    "addr:full":"380 Church St Parramatta NSW 2150",
    "addr:housenumber":"380",
    "addr:postcode":"2150",
    "addr:street":"Church St",
    "iso:country":"AU",
    "sg:address":"380 Church St",
    "sg:city":"Parramatta",
    "sg:classifiers":[
        {
            "category":"Real Estate",
            "subcategory":"Real Estate Agent",
            "type":"Services"
        }
    ],
    "sg:phone":"+61 2 9683 5077",
    "sg:postcode":"2150",
    "sg:province":"NSW",
    "wof:name":"Riverside Real Estate (Parramatta)",
    "wof:placetype":"venue"
},
  "geometry": {"coordinates":[151.00544738799999,-33.8089904785],"type":"Point"}
}