{
  "type": "Feature",
  "properties": {
    "addr:full":"157 Canterbury Rd Heathmont VIC 3135",
    "addr:housenumber":"157",
    "addr:postcode":"3135",
    "addr:street":"Canterbury Rd",
    "iso:country":"AU",
    "sg:address":"157 Canterbury Rd",
    "sg:city":"Heathmont",
    "sg:classifiers":[
        {
            "category":"Fast Food",
            "type":"Food & Drink"
        }
    ],
    "sg:phone":"+61 3 9870 8158",
    "sg:postcode":"3135",
    "sg:province":"VIC",
    "sg:tags":[
        "away",
        "take"
    ],
    "wof:name":"Pizza Farina",
    "wof:placetype":"venue"
},
  "geometry": {"coordinates":[145.243743897,-37.8306465149],"type":"Point"}
}