{
  "type": "Feature",
  "properties": {
    "addr:full":"22 Bentley Ave Kellyville NSW 2155",
    "addr:housenumber":"22",
    "addr:postcode":"2155",
    "addr:street":"Bentley Ave",
    "iso:country":"AU",
    "sg:address":"22 Bentley Ave",
    "sg:city":"Kellyville",
    "sg:classifiers":[
        {
            "category":"Utilities",
            "subcategory":"Electric",
            "type":"Services"
        }
    ],
    "sg:phone":"+61 2 8824 9198",
    "sg:postcode":"2155",
    "sg:province":"NSW",
    "sg:tags":[
        "electrical",
        "contractor"
    ],
    "wof:name":"Real Electrical Services",
    "wof:placetype":"venue"
},
  "geometry": {"coordinates":[150.93296814000001,-33.6809997559],"type":"Point"}
}