{
  "type": "Feature",
  "properties": {
    "iso:country":"AU",
    "sg:address":"1 Nicholas St",
    "sg:city":"Lidcombe",
    "sg:classifiers":[
        {
            "category":"Shopping",
            "subcategory":"Computers & Home Electronics",
            "type":"Retail Goods"
        }
    ],
    "sg:phone":"+61 2 9649 6184",
    "sg:postcode":"2141",
    "sg:province":"NSW",
    "sg:tags":[
        "equipment",
        "supply"
    ],
    "wof:name":"Mwave",
    "wof:placetype":"venue"
},
  "geometry": {"coordinates":[151.04983520499999,-33.8560752869],"type":"Point"}
}