{
  "type": "Feature",
  "properties": {
    "iso:country":"AU",
    "sg:address":"11 Whyalla St",
    "sg:city":"Willetton",
    "sg:classifiers":[
        {
            "category":"Home & Garden",
            "subcategory":"Furniture",
            "type":"Retail Goods"
        }
    ],
    "sg:phone":"+61 8 9457 5877",
    "sg:postcode":"6155",
    "sg:province":"WA",
    "sg:tags":[
        "business"
    ],
    "wof:name":"Atelier Furniture & Interiors",
    "wof:placetype":"venue"
},
  "geometry": {"coordinates":[115.881851,-32.042343],"type":"Point"}
}