{
  "type": "Feature",
  "properties": {
    "addr:full":"61 Alderbury St Floreat WA 6014",
    "addr:housenumber":"61",
    "addr:postcode":"6014",
    "addr:street":"Alderbury St",
    "iso:country":"AU",
    "sg:address":"61 Alderbury St",
    "sg:city":"Floreat",
    "sg:classifiers":[
        {
            "category":"Utilities",
            "subcategory":"Water",
            "type":"Services"
        }
    ],
    "sg:phone":"+61 8 9285 8141",
    "sg:postcode":"6014",
    "sg:province":"WA",
    "sg:tags":[
        "hot",
        "system"
    ],
    "wof:name":"J & D Cain & Son",
    "wof:placetype":"venue"
},
  "geometry": {"coordinates":[115.797431946,-31.9443645477],"type":"Point"}
}