{
  "type": "Feature",
  "properties": {
    "iso:country":"AU",
    "sg:address":"Shp1&2/ 76 Station St",
    "sg:city":"Seymour",
    "sg:classifiers":[
        {
            "category":"Shopping",
            "subcategory":"Clothing, Apparel, & Fashions",
            "type":"Retail Goods"
        }
    ],
    "sg:phone":"+61 3 5792 4333",
    "sg:postcode":"3660",
    "sg:province":"VIC",
    "sg:tags":[
        "menswear"
    ],
    "wof:name":"C & J Kerris Menswear",
    "wof:placetype":"venue"
},
  "geometry": {"coordinates":[145.14465332,-37.0292663574],"type":"Point"}
}