{
  "type": "Feature",
  "properties": {
    "addr:full":"Unit 2/ 28 Bougainville St Manuka ACT 2603",
    "addr:housenumber":"28",
    "addr:postcode":"2603",
    "addr:street":"Bougainville St",
    "iso:country":"AU",
    "sg:address":"Unit 2/ 28 Bougainville St",
    "sg:city":"Manuka",
    "sg:classifiers":[
        {
            "category":"Banks & Credit Unions",
            "subcategory":"Investment Brokerage",
            "type":"Services"
        }
    ],
    "sg:phone":"+61 2 6295 6633",
    "sg:postcode":"2603",
    "sg:province":"ACT",
    "sg:tags":[
        "management",
        "property"
    ],
    "wof:name":"Manuka Real Estate",
    "wof:placetype":"venue"
},
  "geometry": {"coordinates":[149.13180542000001,-35.3207244873],"type":"Point"}
}