{
  "type": "Feature",
  "properties": {
    "iso:country":"AU",
    "sg:address":"9/ 10",
    "sg:city":"Stanford Way Malaga",
    "sg:classifiers":[
        {
            "category":"Shopping",
            "subcategory":"Party Supplies",
            "type":"Retail Goods"
        }
    ],
    "sg:phone":"+61 403 438 851",
    "sg:postcode":"6090",
    "sg:province":"WA",
    "wof:name":"Balls &#039;N&#039; All Amusements",
    "wof:placetype":"venue"
},
  "geometry": {"coordinates":[115.87940979,-31.8586444855],"type":"Point"}
}