{
  "type": "Feature",
  "properties": {
    "addr:full":"3/ 39 Hallstrom Pl Wetherill Park NSW 2164",
    "addr:housenumber":"/ 39",
    "addr:postcode":"2164",
    "addr:street":"Hallstrom Pl",
    "iso:country":"AU",
    "sg:address":"3/ 39 Hallstrom Pl",
    "sg:city":"Wetherill Park",
    "sg:classifiers":[
        {
            "category":"Manufacturing",
            "subcategory":"Tools & Machinery",
            "type":"Manufacturing & Wholesale Goods"
        }
    ],
    "sg:phone":"+61 2 9756 1631",
    "sg:postcode":"2164",
    "sg:province":"NSW",
    "sg:tags":[
        "toolmaker"
    ],
    "wof:name":"Avitron Pty Ltd",
    "wof:placetype":"venue"
},
  "geometry": {"coordinates":[150.88531494099999,-33.8451538086],"type":"Point"}
}