{
  "type": "Feature",
  "properties": {
    "addr:full":"7 Mildon Rd Tuggerah NSW 2259",
    "addr:housenumber":"7",
    "addr:postcode":"2259",
    "addr:street":"Mildon Rd",
    "iso:country":"AU",
    "sg:address":"7 Mildon Rd",
    "sg:city":"Tuggerah",
    "sg:classifiers":[
        {
            "category":"Home & Garden",
            "subcategory":"Building Materials",
            "type":"Retail Goods"
        }
    ],
    "sg:phone":"+61 2 4352 2626",
    "sg:postcode":"2259",
    "sg:province":"NSW",
    "sg:tags":[
        "laminate",
        "laminated",
        "panel"
    ],
    "wof:name":"Fineform Tops & Panels Pty Ltd",
    "wof:placetype":"venue"
},
  "geometry": {"coordinates":[151.4193573,-33.303276062],"type":"Point"}
}