{
  "type": "Feature",
  "properties": {
    "iso:country":"AU",
    "sg:address":"25-27 Brookman Ave",
    "sg:city":"Langford",
    "sg:classifiers":[
        {
            "category":"Communications",
            "subcategory":"Film & Video Production",
            "type":"Services"
        }
    ],
    "sg:phone":"+61 8 9358 6749",
    "sg:postcode":"6147",
    "sg:province":"WA",
    "sg:tags":[
        "society",
        "housing",
        "co-operative"
    ],
    "wof:name":"South City Housing Inc",
    "wof:placetype":"venue"
},
  "geometry": {"coordinates":[115.93615,-32.036293],"type":"Point"}
}