{
  "type": "Feature",
  "properties": {
    "addr:full":"321 Port Rd Hindmarsh SA 5007",
    "addr:housenumber":"321",
    "addr:postcode":"5007",
    "addr:street":"Port Rd",
    "iso:country":"AU",
    "sg:address":"321 Port Rd",
    "sg:city":"Hindmarsh",
    "sg:classifiers":[
        {
            "category":"Professional",
            "subcategory":"Business Services",
            "type":"Services"
        }
    ],
    "sg:phone":"+61 8 8340 1722",
    "sg:postcode":"5007",
    "sg:province":"SA",
    "sg:tags":[
        "small",
        "advisory"
    ],
    "wof:name":"State Retailers Association Of South Australia Inc",
    "wof:placetype":"venue"
},
  "geometry": {"coordinates":[138.56840515100001,-34.9024391174],"type":"Point"}
}