{
  "type": "Feature",
  "properties": {
    "iso:country":"AU",
    "sg:address":"4 Bronze St",
    "sg:city":"Sumner Park",
    "sg:classifiers":[
        {
            "category":"Professional",
            "subcategory":"Engineering",
            "type":"Services"
        }
    ],
    "sg:phone":"+61 7 3376 1277",
    "sg:postcode":"4074",
    "sg:province":"QLD",
    "sg:tags":[
        "engineer"
    ],
    "wof:name":"Associated Iron & Steel Pty Ltd",
    "wof:placetype":"venue"
},
  "geometry": {"coordinates":[152.93864440900001,-27.5624427795],"type":"Point"}
}