{
  "type": "Feature",
  "properties": {
    "addr:full":"Level 18, 120 Edward St Brisbane QLD 4000",
    "addr:housenumber":"120",
    "addr:postcode":"4000",
    "addr:street":"Edward St",
    "iso:country":"AU",
    "sg:address":"Level 18, 120 Edward St",
    "sg:city":"Brisbane",
    "sg:classifiers":[
        {
            "category":"Banks & Credit Unions",
            "subcategory":"Financial Services",
            "type":"Services"
        }
    ],
    "sg:phone":"+61 7 3112 3300",
    "sg:postcode":"4000",
    "sg:province":"QLD",
    "sg:tags":[
        "loan",
        "finance",
        "mortgage"
    ],
    "wof:name":"Wright Patton Shakespeare Financial Group",
    "wof:placetype":"venue"
},
  "geometry": {"coordinates":[153.02850341800001,-27.4700927734],"type":"Point"}
}