{
  "type": "Feature",
  "properties": {
    "iso:country":"AU",
    "sg:address":"Randwick Rd",
    "sg:city":"Lyneham",
    "sg:classifiers":[
        {
            "category":"Arena",
            "subcategory":"Sports Club",
            "type":"Entertainment"
        }
    ],
    "sg:phone":"+61 2 6241 3888",
    "sg:postcode":"2602",
    "sg:province":"ACT",
    "sg:tags":[
        "hunt",
        "racing"
    ],
    "wof:name":"Canberra Racing Club",
    "wof:placetype":"venue"
},
  "geometry": {"coordinates":[149.1302948,-35.2354888916],"type":"Point"}
}