{
  "type": "Feature",
  "properties": {
    "iso:country":"AU",
    "sg:address":"Mt Kooyong Rd",
    "sg:city":"Julatten",
    "sg:classifiers":[
        {
            "category":"Health Services",
            "subcategory":"Nursing And Care Facility",
            "type":"Services"
        }
    ],
    "sg:phone":"+61 7 4094 1279",
    "sg:postcode":"4871",
    "sg:province":"QLD",
    "sg:tags":[
        "home"
    ],
    "wof:name":"Mt Kooyong Nursing Home",
    "wof:placetype":"venue"
},
  "geometry": {"coordinates":[145.33909606899999,-16.5955028534],"type":"Point"}
}