{
  "type": "Feature",
  "properties": {
    "addr:full":"51 Adam St Wynnum QLD 4178",
    "addr:housenumber":"51",
    "addr:postcode":"4178",
    "addr:street":"Adam St",
    "iso:country":"AU",
    "sg:address":"51 Adam St",
    "sg:city":"Wynnum",
    "sg:classifiers":[
        {
            "category":"Real Estate",
            "subcategory":"Real Estate Operator",
            "type":"Services"
        }
    ],
    "sg:phone":"+61 417 720 710",
    "sg:postcode":"4178",
    "sg:province":"QLD",
    "sg:tags":[
        "concrete",
        "pumping"
    ],
    "wof:name":"Express Concrete Pumping",
    "wof:placetype":"venue"
},
  "geometry": {"coordinates":[153.16917419399999,-27.434047699],"type":"Point"}
}