{
  "type": "Feature",
  "properties": {
    "iso:country":"AU",
    "sg:address":"PO Box 503",
    "sg:city":"Rosanna",
    "sg:classifiers":[
        {
            "category":"Recreation",
            "subcategory":"Sailing Club",
            "type":"Entertainment"
        }
    ],
    "sg:phone":"+61 410 489 892",
    "sg:postcode":"8591",
    "sg:province":"VIC",
    "sg:tags":[
        "merchant",
        "diamond"
    ],
    "wof:name":"Australian Diamond Wholesale Brokers",
    "wof:placetype":"venue"
},
  "geometry": {"coordinates":[145.065308,-37.742722],"type":"Point"}
}