{
  "type": "Feature",
  "properties": {
    "addr:full":"275 Springvale Rd Springvale VIC 3171",
    "addr:housenumber":"275",
    "addr:postcode":"3171",
    "addr:street":"Springvale Rd",
    "iso:country":"AU",
    "sg:address":"275 Springvale Rd",
    "sg:city":"Springvale",
    "sg:classifiers":[
        {
            "category":"Health Services",
            "subcategory":"Doctor",
            "type":"Services"
        }
    ],
    "sg:phone":"+61 3 9547 2022",
    "sg:postcode":"3171",
    "sg:province":"VIC",
    "sg:tags":[
        "medical",
        "practitioner"
    ],
    "wof:name":"Extended Hours Medical Service",
    "wof:placetype":"venue"
},
  "geometry": {"coordinates":[145.153106689,-37.9485816956],"type":"Point"}
}