{
  "type": "Feature",
  "properties": {
    "addr:full":"217 Toombul Rd Northgate QLD 4013",
    "addr:housenumber":"217",
    "addr:postcode":"4013",
    "addr:street":"Toombul Rd",
    "iso:country":"AU",
    "sg:address":"217 Toombul Rd",
    "sg:city":"Northgate",
    "sg:classifiers":[
        {
            "category":"Retail",
            "subcategory":"Auto Repair",
            "type":"Services"
        }
    ],
    "sg:phone":"+61 7 3260 5416",
    "sg:postcode":"4013",
    "sg:province":"QLD",
    "sg:tags":[
        "beater",
        "painter",
        "panel"
    ],
    "wof:name":"Toombul Road Paint & Panel",
    "wof:placetype":"venue"
},
  "geometry": {"coordinates":[153.07304382300001,-27.3937892914],"type":"Point"}
}