{
  "type": "Feature",
  "properties": {
    "addr:full":"26 Rainbow Ave West Ballina NSW 2478",
    "addr:housenumber":"26",
    "addr:postcode":"2478",
    "addr:street":"Rainbow Ave",
    "iso:country":"AU",
    "sg:address":"26 Rainbow Ave",
    "sg:city":"West Ballina",
    "sg:classifiers":[
        {
            "category":"Manufacturing",
            "subcategory":"Tools & Machinery",
            "type":"Manufacturing & Wholesale Goods"
        }
    ],
    "sg:phone":"+61 2 6686 5232",
    "sg:postcode":"2478",
    "sg:province":"NSW",
    "sg:tags":[
        "earth",
        "excavating",
        "moving",
        "equipment"
    ],
    "wof:name":"Kellys Excavations",
    "wof:placetype":"venue"
},
  "geometry": {"coordinates":[153.53736877399999,-28.8646831512],"type":"Point"}
}