{
  "type": "Feature",
  "properties": {
    "iso:country":"AU",
    "sg:address":"23 Ireland Rd",
    "sg:city":"Blacktown",
    "sg:classifiers":[
        {
            "category":"Building & Trades",
            "subcategory":"Construction",
            "type":"Services"
        }
    ],
    "sg:phone":"+61 2 9676 3663",
    "sg:postcode":"2148",
    "sg:province":"NSW",
    "sg:tags":[
        "underpinning"
    ],
    "wof:name":"Pender & Sons Pty Ltd",
    "wof:placetype":"venue"
},
  "geometry": {"coordinates":[150.890228272,-33.7638931274],"type":"Point"}
}