{
  "type": "Feature",
  "properties": {
    "addr:full":"6 Lefroy St North Hobart TAS 7000",
    "addr:housenumber":"6",
    "addr:postcode":"7000",
    "addr:street":"Lefroy St",
    "iso:country":"AU",
    "sg:address":"6 Lefroy St",
    "sg:city":"North Hobart",
    "sg:classifiers":[
        {
            "category":"Organizations",
            "subcategory":"Labor Organization",
            "type":"Services"
        }
    ],
    "sg:phone":"+61 3 6234 6744",
    "sg:postcode":"7000",
    "sg:province":"TAS",
    "sg:tags":[
        "union"
    ],
    "wof:name":"Australian Workers Union (AWU)",
    "wof:placetype":"venue"
},
  "geometry": {"coordinates":[147.317230225,-42.8724975586],"type":"Point"}
}