{
  "type": "Feature",
  "properties": {
    "iso:country":"AU",
    "sg:address":"Units 1 & 2, 375 Roberts Rd",
    "sg:city":"Subiaco",
    "sg:classifiers":[
        {
            "category":"Communications",
            "subcategory":"Film & Video Production",
            "type":"Services"
        }
    ],
    "sg:phone":"+61 8 9388 1230",
    "sg:postcode":"6008",
    "sg:province":"WA",
    "sg:tags":[
        "dvd",
        "library"
    ],
    "wof:name":"Video Ezy",
    "wof:placetype":"venue"
},
  "geometry": {"coordinates":[115.824226379,-31.9454402924],"type":"Point"}
}