{
  "type": "Feature",
  "properties": {
    "addr:full":"26 Orchard St Toowong QLD 4066",
    "addr:housenumber":"26",
    "addr:postcode":"4066",
    "addr:street":"Orchard St",
    "iso:country":"AU",
    "sg:address":"26 Orchard St",
    "sg:city":"Toowong",
    "sg:classifiers":[
        {
            "category":"Professional",
            "subcategory":"Art Services",
            "type":"Services"
        }
    ],
    "sg:phone":"+61 7 3720 8499",
    "sg:postcode":"4066",
    "sg:province":"QLD",
    "sg:tags":[
        "picture",
        "frame",
        "framing"
    ],
    "wof:name":"Frame It Yourself Picture Framing",
    "wof:placetype":"venue"
},
  "geometry": {"coordinates":[152.97877502399999,-27.4848880768],"type":"Point"}
}