{
  "type": "Feature",
  "properties": {
    "iso:country":"AU",
    "sg:address":"13 Scott St",
    "sg:city":"Dandenong",
    "sg:classifiers":[
        {
            "category":"Professional",
            "subcategory":"Lawyer & Legal Services",
            "type":"Services"
        }
    ],
    "sg:phone":"+61 3 9791 4111",
    "sg:postcode":"3175",
    "sg:province":"VIC",
    "sg:tags":[
        "wills",
        "probate",
        "estate"
    ],
    "wof:name":"F.R. Monotti & Co",
    "wof:placetype":"venue"
},
  "geometry": {"coordinates":[145.21229553200001,-37.9863548279],"type":"Point"}
}