{
  "type": "Feature",
  "properties": {
    "addr:full":"46 Arthur St Forestville NSW 2087",
    "addr:housenumber":"46",
    "addr:postcode":"2087",
    "addr:street":"Arthur St",
    "iso:country":"AU",
    "sg:address":"46 Arthur St",
    "sg:city":"Forestville",
    "sg:classifiers":[
        {
            "category":"Retail",
            "subcategory":"Repair Shop",
            "type":"Services"
        }
    ],
    "sg:phone":"+61 2 9953 7576",
    "sg:postcode":"2087",
    "sg:province":"NSW",
    "sg:tags":[
        "upholsterer"
    ],
    "wof:name":"North Upholstery",
    "wof:placetype":"venue"
},
  "geometry": {"coordinates":[151.203857422,-33.7597160339],"type":"Point"}
}