{
  "type": "Feature",
  "properties": {
    "addr:full":"161 Castlereagh St Sydney NSW 2000",
    "addr:housenumber":"161",
    "addr:postcode":"2000",
    "addr:street":"Castlereagh St",
    "iso:country":"AU",
    "sg:address":"161 Castlereagh St",
    "sg:city":"Sydney",
    "sg:classifiers":[
        {
            "category":"Education",
            "subcategory":"Dance Studio",
            "type":"Public Place"
        }
    ],
    "sg:phone":"+61 2 9261 3137",
    "sg:postcode":"2000",
    "sg:province":"NSW",
    "sg:tags":[
        "venue",
        "tuition"
    ],
    "wof:name":"Studio Danse Orientale (Belly Dance)",
    "wof:placetype":"venue"
},
  "geometry": {"coordinates":[151.20913696299999,-33.8722496033],"type":"Point"}
}