{
  "type": "Feature",
  "properties": {
    "addr:full":"29 Gledden Drv Leinster WA 6437",
    "addr:housenumber":"29",
    "addr:postcode":"6437",
    "addr:street":"Gledden Drv",
    "iso:country":"AU",
    "sg:address":"29 Gledden Drv",
    "sg:city":"Leinster",
    "sg:classifiers":[
        {
            "category":"Social Services",
            "subcategory":"Child Care",
            "type":"Services"
        }
    ],
    "sg:phone":"+61 8 9037 9316",
    "sg:postcode":"6437",
    "sg:province":"WA",
    "sg:tags":[
        "support",
        "health"
    ],
    "wof:name":"Child Health Services",
    "wof:placetype":"venue"
},
  "geometry": {"coordinates":[120.69526672400001,-27.9378890991],"type":"Point"}
}