{
  "type": "Feature",
  "properties": {
    "addr:full":"Menangle St Picton NSW 2571",
    "addr:postcode":"2571",
    "addr:street":"Menangle St",
    "iso:country":"AU",
    "sg:address":"Menangle St",
    "sg:city":"Picton",
    "sg:classifiers":[
        {
            "category":"Restaurant",
            "type":"Food & Drink"
        }
    ],
    "sg:phone":"+61 2 4636 6218",
    "sg:postcode":"2571",
    "sg:province":"NSW",
    "sg:tags":[
        "theatre"
    ],
    "wof:name":"Picton Theatre Group Inc.",
    "wof:placetype":"venue"
},
  "geometry": {"coordinates":[150.611495972,-34.1690788269],"type":"Point"}
}