{
  "type": "Feature",
  "properties": {
    "addr:full":"Shop 17 Humpty Doo Plaza Freds Pass Humpty Doo NT 0836",
    "addr:housenumber":"shop 17",
    "addr:postcode":"nt 0836",
    "addr:street":"Humpty;Plaza;Pass",
    "iso:country":"AU",
    "sg:address":"Shop 17 Humpty Doo Plaza Freds Pass",
    "sg:city":"Humpty Doo",
    "sg:classifiers":[
        {
            "category":"Fast Food",
            "type":"Food & Drink"
        }
    ],
    "sg:phone":"+61 8 8988 1481",
    "sg:postcode":"0836",
    "sg:province":"NT",
    "sg:tags":[
        "away",
        "take"
    ],
    "wof:name":"Humpty Doo Seafoods",
    "wof:placetype":"venue"
},
  "geometry": {"coordinates":[131.10972599999999,-12.580288],"type":"Point"}
}