{
  "type": "Feature",
  "properties": {
    "addr:full":"17- 33 Milton Pde Malvern VIC 3144",
    "addr:housenumber":"33",
    "addr:postcode":"3144",
    "addr:street":"Milton Pde",
    "iso:country":"AU",
    "sg:address":"17- 33 Milton Pde",
    "sg:city":"Malvern",
    "sg:classifiers":[
        {
            "category":"Structure",
            "subcategory":"Office Building",
            "type":"Public Place"
        }
    ],
    "sg:phone":"+61 3 9832 0600",
    "sg:postcode":"3144",
    "sg:province":"VIC",
    "sg:tags":[
        "serviced"
    ],
    "wof:name":"Asian Pacific Business Centres",
    "wof:placetype":"venue"
},
  "geometry": {"coordinates":[145.039154053,-37.8464851379],"type":"Point"}
}