{
  "type": "Feature",
  "properties": {
    "addr:full":"U17/ 122 Hassall St Wetherill Park NSW 2164",
    "addr:housenumber":"122",
    "addr:postcode":"2164",
    "addr:street":"/;Hassall St",
    "iso:country":"AU",
    "sg:address":"U17/ 122 Hassall St",
    "sg:city":"Wetherill Park",
    "sg:classifiers":[
        {
            "category":"Professional",
            "type":"Services"
        }
    ],
    "sg:phone":"+61 2 9729 2993",
    "sg:postcode":"2164",
    "sg:province":"NSW",
    "sg:tags":[
        "shop",
        "fitting"
    ],
    "wof:name":"Life Time Joinery",
    "wof:placetype":"venue"
},
  "geometry": {"coordinates":[150.91290283199999,-33.8399734497],"type":"Point"}
}