{
  "type": "Feature",
  "properties": {
    "addr:full":"375 Jiggi Rd Goolmangar NSW 2480",
    "addr:housenumber":"375",
    "addr:postcode":"2480",
    "addr:street":"Jiggi Rd",
    "iso:country":"AU",
    "sg:address":"375 Jiggi Rd",
    "sg:city":"Goolmangar",
    "sg:classifiers":[
        {
            "category":"Building & Trades",
            "subcategory":"Plumbing",
            "type":"Services"
        }
    ],
    "sg:phone":"+61 2 6629 3286",
    "sg:postcode":"2480",
    "sg:province":"NSW",
    "sg:tags":[
        "plumber",
        "gasfitters"
    ],
    "wof:name":"Greg Scheibel Plumbing Pty Ltd",
    "wof:placetype":"venue"
},
  "geometry": {"coordinates":[153.19979858400001,-28.7309913635],"type":"Point"}
}