{
  "type": "Feature",
  "properties": {
    "addr:full":"42 Parnassus St Robertson QLD 4109",
    "addr:housenumber":"42",
    "addr:postcode":"4109",
    "addr:street":"Parnassus St",
    "iso:country":"AU",
    "sg:address":"42 Parnassus St",
    "sg:city":"Robertson",
    "sg:classifiers":[
        {
            "category":"Building & Trades",
            "subcategory":"Construction",
            "type":"Services"
        }
    ],
    "sg:phone":"+61 418 731 319",
    "sg:postcode":"4109",
    "sg:province":"QLD",
    "sg:tags":[
        "contractor"
    ],
    "wof:name":"Vedybuild Pty Ltd",
    "wof:placetype":"venue"
},
  "geometry": {"coordinates":[153.056243897,-27.5680847168],"type":"Point"}
}