{
  "type": "Feature",
  "properties": {
    "iso:country":"AU",
    "sg:address":"70 Macdonnell Rd",
    "sg:city":"Margate",
    "sg:classifiers":[
        {
            "category":"Professional",
            "subcategory":"Detective & Security Services",
            "type":"Services"
        }
    ],
    "sg:phone":"+61 7 3885 3965",
    "sg:postcode":"4019",
    "sg:province":"QLD",
    "sg:tags":[
        "equipment",
        "window",
        "doors"
    ],
    "wof:name":"Deborah's Doors",
    "wof:placetype":"venue"
},
  "geometry": {"coordinates":[153.09463500999999,-27.2354373932],"type":"Point"}
}