{
  "type": "Feature",
  "properties": {
    "iso:country":"AU",
    "sg:address":"458 Wattle St",
    "sg:city":"Ultimo",
    "sg:classifiers":[
        {
            "category":"Professional",
            "subcategory":"Art Services",
            "type":"Services"
        }
    ],
    "sg:phone":"+61 2 9211 1809",
    "sg:postcode":"2007",
    "sg:province":"NSW",
    "sg:tags":[
        "graphic",
        "designer"
    ],
    "wof:name":"3DC",
    "wof:placetype":"venue"
},
  "geometry": {"coordinates":[151.197021484,-33.8809700012],"type":"Point"}
}