{
  "type": "Feature",
  "properties": {
    "addr:full":"4 Wise St Elmhurst VIC 3469",
    "addr:housenumber":"4",
    "addr:postcode":"3469",
    "addr:street":"Wise St",
    "iso:country":"AU",
    "sg:address":"4 Wise St",
    "sg:city":"Elmhurst",
    "sg:classifiers":[
        {
            "category":"Arts & Performance",
            "subcategory":"Art Gallery",
            "type":"Entertainment"
        }
    ],
    "sg:phone":"+61 3 5354 8247",
    "sg:postcode":"3469",
    "sg:province":"VIC",
    "wof:name":"Oasis Crystal Studio Gallery",
    "wof:placetype":"venue"
},
  "geometry": {"coordinates":[143.25218200699999,-37.1782531738],"type":"Point"}
}