{
  "type": "Feature",
  "properties": {
    "iso:country":"AU",
    "sg:address":"1/ 703 The Horsley Drv",
    "sg:city":"Smithfield",
    "sg:classifiers":[
        {
            "category":"Retail",
            "subcategory":"Repair Shop",
            "type":"Services"
        }
    ],
    "sg:phone":"+61 2 9757 1157",
    "sg:postcode":"2164",
    "sg:province":"NSW",
    "sg:tags":[
        "windscreen"
    ],
    "wof:name":"Smithfield Autoglass",
    "wof:placetype":"venue"
},
  "geometry": {"coordinates":[150.93812560999999,-33.8529319763],"type":"Point"}
}