{
  "type": "Feature",
  "properties": {
    "iso:country":"AU",
    "sg:address":"3B/ 14-16 White St",
    "sg:city":"Oakleigh East",
    "sg:classifiers":[
        {
            "category":"Wholesale",
            "subcategory":"Machinery & Supplies",
            "type":"Manufacturing & Wholesale Goods"
        }
    ],
    "sg:phone":"+61 3 9543 5411",
    "sg:postcode":"3166",
    "sg:province":"VIC",
    "sg:tags":[
        "equipment",
        "hydraulic"
    ],
    "wof:name":"Stauff Corporation Pty Ltd",
    "wof:placetype":"venue"
},
  "geometry": {"coordinates":[145.12005615199999,-37.9118881226],"type":"Point"}
}