{
  "type": "Feature",
  "properties": {
    "addr:full":"6 Pinta Pl Cromer NSW 2099",
    "addr:housenumber":"6",
    "addr:postcode":"2099",
    "addr:street":"Pinta Pl",
    "iso:country":"AU",
    "sg:address":"6 Pinta Pl",
    "sg:city":"Cromer",
    "sg:classifiers":[
        {
            "category":"Building & Trades",
            "subcategory":"Construction",
            "type":"Services"
        }
    ],
    "sg:phone":"+61 2 9981 6509",
    "sg:postcode":"2099",
    "sg:province":"NSW",
    "sg:tags":[
        "management"
    ],
    "wof:name":"Harro Project Management Pty Ltd",
    "wof:placetype":"venue"
},
  "geometry": {"coordinates":[151.27247619600001,-33.7381477356],"type":"Point"}
}