{
  "type": "Feature",
  "properties": {
    "iso:country":"AU",
    "sg:address":"High St",
    "sg:city":"Marong",
    "sg:classifiers":[
        {
            "category":"Education",
            "subcategory":"Kindergarten",
            "type":"Public Place"
        }
    ],
    "sg:phone":"+61 3 5435 2394",
    "sg:postcode":"3515",
    "sg:province":"VIC",
    "sg:tags":[
        "pre-schools"
    ],
    "wof:name":"Marong Pre School",
    "wof:placetype":"venue"
},
  "geometry": {"coordinates":[144.13395700000001,-36.735931],"type":"Point"}
}