{
  "type": "Feature",
  "properties": {
    "addr:full":"Cnr Bruce Hwy & Private St Rockhampton QLD 4700",
    "addr:postcode":"4700",
    "addr:street":"Cnr Bruce Hwy & Private St",
    "iso:country":"AU",
    "sg:address":"Cnr Bruce Hwy & Private St",
    "sg:city":"Rockhampton",
    "sg:classifiers":[
        {
            "category":"Travel",
            "subcategory":"Hotels & Motels",
            "type":"Entertainment"
        }
    ],
    "sg:phone":"+61 7 4922 9200",
    "sg:postcode":"4700",
    "sg:province":"QLD",
    "wof:name":"Rocky Gardens Motor Inn",
    "wof:placetype":"venue"
},
  "geometry": {"coordinates":[150.50163269000001,-23.4042778015],"type":"Point"}
}