{
  "type": "Feature",
  "properties": {
    "addr:full":"108 Wakaden St Griffith NSW 2680",
    "addr:housenumber":"108",
    "addr:postcode":"2680",
    "addr:street":"Wakaden St",
    "iso:country":"AU",
    "sg:address":"108 Wakaden St",
    "sg:city":"Griffith",
    "sg:classifiers":[
        {
            "category":"Utilities",
            "subcategory":"Natural Gas",
            "type":"Services"
        }
    ],
    "sg:phone":"+61 13 21 80",
    "sg:postcode":"2680",
    "sg:province":"NSW",
    "sg:tags":[
        "supplier"
    ],
    "wof:name":"Kleenheat Gas",
    "wof:placetype":"venue"
},
  "geometry": {"coordinates":[146.052628,-34.286095],"type":"Point"}
}