{
  "type": "Feature",
  "properties": {
    "addr:full":"Unit C2, Hallmarc Business Park, 2A Westall Rd Springvale VIC 3171",
    "addr:housenumber":"2a",
    "addr:postcode":"3171",
    "addr:street":"Business Park;Westall Rd",
    "iso:country":"AU",
    "sg:address":"Unit C2, Hallmarc Business Park, 2A Westall Rd",
    "sg:city":"Springvale",
    "sg:classifiers":[
        {
            "category":"Government",
            "subcategory":"Fire Station",
            "type":"Public Place"
        }
    ],
    "sg:phone":"+61 3 9562 7577",
    "sg:postcode":"3171",
    "sg:province":"VIC",
    "sg:tags":[
        "equipment",
        "protection",
        "consultant"
    ],
    "wof:name":"Pertronic Industries Pty Ltd",
    "wof:placetype":"venue"
},
  "geometry": {"coordinates":[145.14227294899999,-37.9322090149],"type":"Point"}
}