{
  "type": "Feature",
  "properties": {
    "iso:country":"AU",
    "sg:address":"158 Guys Rd",
    "sg:city":"Cygnet",
    "sg:classifiers":[
        {
            "category":"Building & Trades",
            "subcategory":"Construction",
            "type":"Services"
        }
    ],
    "sg:phone":"+61 3 6295 0387",
    "sg:postcode":"7112",
    "sg:province":"TAS",
    "sg:tags":[
        "window",
        "aluminium"
    ],
    "wof:name":"Flexiscreens",
    "wof:placetype":"venue"
},
  "geometry": {"coordinates":[147.09251403799999,-43.1519088745],"type":"Point"}
}