{
  "type": "Feature",
  "properties": {
    "addr:full":"40 Coode St South Perth WA 6151",
    "addr:housenumber":"40",
    "addr:postcode":"6151",
    "addr:street":"Coode St South",
    "iso:country":"AU",
    "sg:address":"40 Coode St",
    "sg:city":"South Perth",
    "sg:classifiers":[
        {
            "category":"Education",
            "subcategory":"School",
            "type":"Public Place"
        }
    ],
    "sg:phone":"+61 8 9368 8000",
    "sg:postcode":"6151",
    "sg:province":"WA",
    "sg:tags":[
        "boy"
    ],
    "wof:name":"Wesley College",
    "wof:placetype":"venue"
},
  "geometry": {"coordinates":[115.864059,-31.979673],"type":"Point"}
}