{
  "type": "Feature",
  "properties": {
    "addr:full":"mandra Crt Voyager Point NSW 2171",
    "addr:postcode":"2171",
    "addr:street":"Mandra Crt",
    "iso:country":"AU",
    "sg:address":"mandra Crt",
    "sg:city":"Voyager Point",
    "sg:classifiers":[
        {
            "category":"Home & Garden",
            "subcategory":"Building Materials",
            "type":"Retail Goods"
        }
    ],
    "sg:phone":"+61 433 826 617",
    "sg:postcode":"2171",
    "sg:province":"NSW",
    "sg:tags":[
        "merchant",
        "glass",
        "glazier"
    ],
    "wof:name":"ARN Glass",
    "wof:placetype":"venue"
},
  "geometry": {"coordinates":[150.846237183,-33.9284286499],"type":"Point"}
}