{
  "type": "Feature",
  "properties": {
    "iso:country":"AU",
    "sg:address":"Karinie St",
    "sg:city":"Swan Hill",
    "sg:classifiers":[
        {
            "category":"Professional",
            "subcategory":"Art Services",
            "type":"Services"
        }
    ],
    "sg:phone":"+61 417 321 545",
    "sg:postcode":"3585",
    "sg:province":"NSW",
    "sg:tags":[
        "decorator",
        "painter"
    ],
    "wof:name":"Lindsay A S & V J",
    "wof:placetype":"venue"
},
  "geometry": {"coordinates":[143.55360400000001,-35.327419],"type":"Point"}
}