{
  "type": "Feature",
  "properties": {
    "addr:full":"9 Edge Pl Nicholls ACT 2913",
    "addr:housenumber":"9",
    "addr:postcode":"2913",
    "addr:street":"Edge Pl",
    "iso:country":"AU",
    "sg:address":"9 Edge Pl",
    "sg:city":"Nicholls",
    "sg:classifiers":[
        {
            "category":"Professional",
            "subcategory":"Art Services",
            "type":"Services"
        }
    ],
    "sg:phone":"+61 2 6262 2441",
    "sg:postcode":"2913",
    "sg:province":"ACT",
    "sg:tags":[
        "interior",
        "designer"
    ],
    "wof:name":"Eminence Kitchen Designs",
    "wof:placetype":"venue"
},
  "geometry": {"coordinates":[149.10748290999999,-35.1815490723],"type":"Point"}
}