{
  "type": "Feature",
  "properties": {
    "addr:full":"55 Ridgeway Ave Southport QLD 4215",
    "addr:housenumber":"55",
    "addr:postcode":"4215",
    "addr:street":"Ridgeway Ave",
    "iso:country":"AU",
    "sg:address":"55 Ridgeway Ave",
    "sg:city":"Southport",
    "sg:classifiers":[
        {
            "category":"Organizations",
            "subcategory":"Non-profit Organization",
            "type":"Services"
        }
    ],
    "sg:phone":"+61 7 5532 2088",
    "sg:postcode":"4215",
    "sg:province":"QLD",
    "sg:tags":[
        "support",
        "disability",
        "organisation"
    ],
    "wof:name":"Cerebral Palsy League Of QLD",
    "wof:placetype":"venue"
},
  "geometry": {"coordinates":[153.40357971200001,-27.9848861694],"type":"Point"}
}