{
  "type": "Feature",
  "properties": {
    "addr:full":"4 Danastas Ave Eimeo QLD 4740",
    "addr:housenumber":"4",
    "addr:postcode":"4740",
    "addr:street":"Danastas Ave",
    "iso:country":"AU",
    "sg:address":"4 Danastas Ave",
    "sg:city":"Eimeo",
    "sg:classifiers":[
        {
            "category":"Personal",
            "subcategory":"Nail Salon",
            "type":"Services"
        }
    ],
    "sg:phone":"+61 7 4954 9607",
    "sg:postcode":"4740",
    "sg:province":"QLD",
    "sg:tags":[
        "foil",
        "printing",
        "stamping"
    ],
    "wof:name":"Norside Foil Print",
    "wof:placetype":"venue"
},
  "geometry": {"coordinates":[149.17849699999999,-21.047398],"type":"Point"}
}