{
  "type": "Feature",
  "properties": {
    "addr:full":"165 MacLeod St Bairnsdale VIC 3875",
    "addr:housenumber":"165",
    "addr:postcode":"3875",
    "addr:street":"Macleod St",
    "iso:country":"AU",
    "sg:address":"165 MacLeod St",
    "sg:city":"Bairnsdale",
    "sg:classifiers":[
        {
            "category":"Home & Garden",
            "subcategory":"Furniture",
            "type":"Retail Goods"
        }
    ],
    "sg:phone":"+61 3 5153 1114",
    "sg:postcode":"3875",
    "sg:province":"VIC",
    "sg:tags":[
        "business"
    ],
    "wof:name":"Macleod House Office Furniture",
    "wof:placetype":"venue"
},
  "geometry": {"coordinates":[147.62124633799999,-37.8296546936],"type":"Point"}
}