{
  "type": "Feature",
  "properties": {
    "addr:full":"Ashley La Westmead NSW 2145",
    "addr:postcode":"2145",
    "addr:street":"Ashley",
    "iso:country":"AU",
    "sg:address":"Ashley La",
    "sg:city":"Westmead",
    "sg:classifiers":[
        {
            "category":"Health Services",
            "subcategory":"Doctor",
            "type":"Services"
        }
    ],
    "sg:phone":"+61 2 8833 3000",
    "sg:postcode":"2145",
    "sg:province":"NSW",
    "sg:tags":[
        "medical",
        "practitioner"
    ],
    "wof:name":"Paver Robert",
    "wof:placetype":"venue"
},
  "geometry": {"coordinates":[150.98887634299999,-33.807258606],"type":"Point"}
}