{
  "type": "Feature",
  "properties": {
    "addr:full":"77 MacQuarie St Dubbo NSW 2830",
    "addr:housenumber":"77",
    "addr:postcode":"2830",
    "addr:street":"Macquarie St",
    "iso:country":"AU",
    "sg:address":"77 MacQuarie St",
    "sg:city":"Dubbo",
    "sg:classifiers":[
        {
            "category":"Personal",
            "subcategory":"Beauty Salon",
            "type":"Services"
        }
    ],
    "sg:phone":"+61 2 6882 2066",
    "sg:postcode":"2830",
    "sg:province":"NSW",
    "sg:tags":[
        "hairdresser"
    ],
    "wof:name":"Hair Shananigans",
    "wof:placetype":"venue"
},
  "geometry": {"coordinates":[148.60125732399999,-32.246635437],"type":"Point"}
}