{
  "type": "Feature",
  "properties": {
    "iso:country":"AU",
    "sg:address":"Ling Siding Tasman Hwy",
    "sg:city":"Scottsdale",
    "sg:classifiers":[
        {
            "category":"Wholesale",
            "subcategory":"Machinery & Supplies",
            "type":"Manufacturing & Wholesale Goods"
        }
    ],
    "sg:phone":"+61 3 6352 4196",
    "sg:postcode":"7260",
    "sg:province":"TAS",
    "sg:tags":[
        "equipment",
        "hydraulic"
    ],
    "wof:name":"Enzed",
    "wof:placetype":"venue"
},
  "geometry": {"coordinates":[147.53024300000001,-41.170376],"type":"Point"}
}