{
  "type": "Feature",
  "properties": {
    "addr:full":"50 Cromwell St Sebastopol VIC 3356",
    "addr:housenumber":"50",
    "addr:postcode":"3356",
    "addr:street":"Cromwell St",
    "iso:country":"AU",
    "sg:address":"50 Cromwell St",
    "sg:city":"Sebastopol",
    "sg:classifiers":[
        {
            "category":"Retail",
            "subcategory":"Auto Repair",
            "type":"Services"
        }
    ],
    "sg:phone":"+61 3 5336 1105",
    "sg:postcode":"3356",
    "sg:province":"VIC",
    "sg:tags":[
        "clutch",
        "brake"
    ],
    "wof:name":"Latrobe Gas Fitting And Automotive Repairs",
    "wof:placetype":"venue"
},
  "geometry": {"coordinates":[143.830276,-37.585464],"type":"Point"}
}