{
  "type": "Feature",
  "properties": {
    "addr:full":"72- 74 Bathurst St Liverpool NSW 2170",
    "addr:housenumber":"74",
    "addr:postcode":"2170",
    "addr:street":"Bathurst St",
    "iso:country":"AU",
    "sg:address":"72- 74 Bathurst St",
    "sg:city":"Liverpool",
    "sg:classifiers":[
        {
            "category":"Professional",
            "subcategory":"Accounting & Tax Preparation",
            "type":"Services"
        }
    ],
    "sg:phone":"+61 2 9602 0200",
    "sg:postcode":"2170",
    "sg:province":"NSW",
    "sg:tags":[
        "accountant",
        "auditor"
    ],
    "wof:name":"Hancock & Associates",
    "wof:placetype":"venue"
},
  "geometry": {"coordinates":[150.921264648,-33.9233016968],"type":"Point"}
}