{
  "type": "Feature",
  "properties": {
    "addr:full":"3757 Arrarat - Halls Gap Rd Pomonal VIC 3381",
    "addr:housenumber":"3757",
    "addr:postcode":"3381",
    "addr:street":"Arrarat Halls Gap Rd",
    "iso:country":"AU",
    "sg:address":"3757 Arrarat - Halls Gap Rd",
    "sg:city":"Pomonal",
    "sg:classifiers":[
        {
            "category":"Personal",
            "subcategory":"Massage",
            "type":"Services"
        }
    ],
    "sg:phone":"+61 3 5356 6171",
    "sg:postcode":"3381",
    "sg:province":"VIC",
    "sg:tags":[
        "therapy"
    ],
    "wof:name":"Blaze Rock Retreat",
    "wof:placetype":"venue"
},
  "geometry": {"coordinates":[142.60894775400001,-37.1917114258],"type":"Point"}
}