{
  "type": "Feature",
  "properties": {
    "addr:full":"169- 173 Lord St Newtown NSW 2042",
    "addr:housenumber":"173",
    "addr:postcode":"2042",
    "addr:street":"Lord St",
    "iso:country":"AU",
    "sg:address":"169- 173 Lord St",
    "sg:city":"Newtown",
    "sg:classifiers":[
        {
            "category":"Retail",
            "subcategory":"Auto Repair",
            "type":"Services"
        }
    ],
    "sg:phone":"+61 2 9519 4332",
    "sg:postcode":"2042",
    "sg:province":"NSW",
    "sg:tags":[
        "repairer",
        "motor",
        "engineer"
    ],
    "wof:name":"Piccola Scuderia Ferrari Specialists",
    "wof:placetype":"venue"
},
  "geometry": {"coordinates":[151.17524700000001,-33.908195],"type":"Point"}
}