{
  "type": "Feature",
  "properties": {
    "addr:full":"6 Edna Pl Kings Langley NSW 2147",
    "addr:housenumber":"6",
    "addr:postcode":"2147",
    "addr:street":"Edna Pl",
    "iso:country":"AU",
    "sg:address":"6 Edna Pl",
    "sg:city":"Kings Langley",
    "sg:classifiers":[
        {
            "category":"Retail",
            "subcategory":"Laundry & Dry Cleaning",
            "type":"Services"
        }
    ],
    "sg:phone":"+61 2 9620 8847",
    "sg:postcode":"2147",
    "sg:province":"NSW",
    "sg:tags":[
        "cloth",
        "supply"
    ],
    "wof:name":"Samaritan Rag Supplies",
    "wof:placetype":"venue"
},
  "geometry": {"coordinates":[150.94128418,-33.7475357056],"type":"Point"}
}