{
  "type": "Feature",
  "properties": {
    "addr:full":"7/ 193 South Pine Rd Brendale QLD 4500",
    "addr:housenumber":"/ 193",
    "addr:postcode":"4500",
    "addr:street":"South Pine Rd",
    "iso:country":"AU",
    "sg:address":"7/ 193 South Pine Rd",
    "sg:city":"Brendale",
    "sg:classifiers":[
        {
            "category":"Health Services",
            "subcategory":"Health Practitioner",
            "type":"Services"
        }
    ],
    "sg:phone":"+61 7 3205 7019",
    "sg:postcode":"4500",
    "sg:province":"QLD",
    "sg:tags":[
        "physiotherapist"
    ],
    "wof:name":"Icefire Physiotherapy",
    "wof:placetype":"venue"
},
  "geometry": {"coordinates":[152.97962951700001,-27.3262500763],"type":"Point"}
}