{
  "type": "Feature",
  "properties": {
    "addr:full":"90 Rundle St Kent Town SA 5067",
    "addr:housenumber":"90",
    "addr:postcode":"5067",
    "addr:street":"Rundle St",
    "iso:country":"AU",
    "sg:address":"90 Rundle St",
    "sg:city":"Kent Town",
    "sg:classifiers":[
        {
            "category":"Banks & Credit Unions",
            "subcategory":"Investment Brokerage",
            "type":"Services"
        }
    ],
    "sg:phone":"+61 8 8363 1599",
    "sg:postcode":"5067",
    "sg:province":"SA",
    "sg:tags":[
        "finance",
        "broker"
    ],
    "wof:name":"Dynamic Loans",
    "wof:placetype":"venue"
},
  "geometry": {"coordinates":[138.61845398,-34.9203186035],"type":"Point"}
}