{
  "type": "Feature",
  "properties": {
    "iso:country":"AU",
    "sg:address":"8/ 53 Smith St",
    "sg:city":"Balmain",
    "sg:classifiers":[
        {
            "category":"Health Services",
            "subcategory":"Health Practitioner",
            "type":"Services"
        }
    ],
    "sg:phone":"+61 430 188 903",
    "sg:postcode":"2041",
    "sg:province":"NSW",
    "sg:tags":[
        "dietitian"
    ],
    "wof:name":"Instyle Health & Fitness",
    "wof:placetype":"venue"
},
  "geometry": {"coordinates":[151.178009,-33.862358],"type":"Point"}
}