{
  "type": "Feature",
  "properties": {
    "iso:country":"AU",
    "sg:address":"Windsor State School, Harris St",
    "sg:city":"Windsor",
    "sg:classifiers":[
        {
            "category":"Social Services",
            "subcategory":"Child Care",
            "type":"Services"
        }
    ],
    "sg:phone":"+61 7 3357 9848",
    "sg:postcode":"4030",
    "sg:province":"QLD",
    "wof:name":"Windsor School Age Care Centre Inc",
    "wof:placetype":"venue"
},
  "geometry": {"coordinates":[153.02946499999999,-27.430635],"type":"Point"}
}