{
  "type": "Feature",
  "properties": {
    "iso:country":"AU",
    "sg:address":"29 George St",
    "sg:city":"Marulan",
    "sg:classifiers":[
        {
            "category":"Social Services",
            "subcategory":"Child Care",
            "type":"Services"
        }
    ],
    "sg:phone":"+61 2 4841 1985",
    "sg:postcode":"2579",
    "sg:province":"NSW",
    "wof:name":"Marulan Childrens Centre - Little Treasures",
    "wof:placetype":"venue"
},
  "geometry": {"coordinates":[150.00877380399999,-34.7090835571],"type":"Point"}
}