{
  "type": "Feature",
  "properties": {
    "iso:country":"AU",
    "sg:address":"32 Bridges Rd",
    "sg:city":"New Lambton",
    "sg:classifiers":[
        {
            "category":"Professional",
            "subcategory":"Business Services",
            "type":"Services"
        }
    ],
    "sg:phone":"+61 403 308 278",
    "sg:postcode":"2305",
    "sg:province":"NSW",
    "sg:tags":[
        "management",
        "event"
    ],
    "wof:name":"Have A Dream Productions",
    "wof:placetype":"venue"
},
  "geometry": {"coordinates":[151.71965,-32.925117],"type":"Point"}
}