{
  "type": "Feature",
  "properties": {
    "addr:full":"33 Cumming Ave Birchip VIC 3483",
    "addr:housenumber":"33",
    "addr:postcode":"3483",
    "addr:street":"Cumming Ave",
    "iso:country":"AU",
    "sg:address":"33 Cumming Ave",
    "sg:city":"Birchip",
    "sg:classifiers":[
        {
            "category":"Shopping",
            "subcategory":"Clothing, Apparel, & Fashions",
            "type":"Retail Goods"
        }
    ],
    "sg:phone":"+61 3 5492 2415",
    "sg:postcode":"3483",
    "sg:province":"VIC",
    "sg:tags":[
        "lady",
        "wear"
    ],
    "wof:name":"Just You Casuals",
    "wof:placetype":"venue"
},
  "geometry": {"coordinates":[142.91653442399999,-35.9840202332],"type":"Point"}
}