{
  "type": "Feature",
  "properties": {
    "addr:full":"1939 Ourimbah Creek Rd Ourimbah NSW 2258",
    "addr:housenumber":"1939",
    "addr:postcode":"2258",
    "addr:street":"Ourimbah Creek Rd",
    "iso:country":"AU",
    "sg:address":"1939 Ourimbah Creek Rd",
    "sg:city":"Ourimbah",
    "sg:classifiers":[
        {
            "category":"Farming",
            "subcategory":"Livestock Farm",
            "type":"Manufacturing & Wholesale Goods"
        }
    ],
    "sg:phone":"+61 2 4362 1199",
    "sg:postcode":"2258",
    "sg:province":"NSW",
    "sg:tags":[
        "agistment"
    ],
    "wof:name":"Bellarimbah Horse Agistment.",
    "wof:placetype":"venue"
},
  "geometry": {"coordinates":[151.32359314000001,-33.3464355469],"type":"Point"}
}