{
  "type": "Feature",
  "properties": {
    "addr:full":"U6/ 12 Newspaper Pl Maroochydore QLD 4558",
    "addr:housenumber":"12",
    "addr:postcode":"4558",
    "addr:street":"U6 /;Pl",
    "iso:country":"AU",
    "sg:address":"U6/ 12 Newspaper Pl",
    "sg:city":"Maroochydore",
    "sg:classifiers":[
        {
            "category":"Arts & Performance",
            "subcategory":"Music",
            "type":"Entertainment"
        }
    ],
    "sg:phone":"+61 7 5451 0199",
    "sg:postcode":"4558",
    "sg:province":"QLD",
    "sg:tags":[
        "hi-fi",
        "equipment"
    ],
    "wof:name":"Home Entertainment Services",
    "wof:placetype":"venue"
},
  "geometry": {"coordinates":[153.09194946299999,-26.6676616669],"type":"Point"}
}