{
  "type": "Feature",
  "properties": {
    "addr:full":"22 Crossman Drv Croydon Hills VIC 3136",
    "addr:housenumber":"22",
    "addr:postcode":"3136",
    "addr:street":"Crossman Drv",
    "iso:country":"AU",
    "sg:address":"22 Crossman Drv",
    "sg:city":"Croydon Hills",
    "sg:classifiers":[
        {
            "category":"Education",
            "subcategory":"Special Training",
            "type":"Public Place"
        }
    ],
    "sg:phone":"+61 400 773 529",
    "sg:postcode":"3136",
    "sg:province":"VIC",
    "sg:tags":[
        "development"
    ],
    "wof:name":"C J Richards Pty Ltd",
    "wof:placetype":"venue"
},
  "geometry": {"coordinates":[145.2603302,-37.7798461914],"type":"Point"}
}