{
  "type": "Feature",
  "properties": {
    "iso:country":"AU",
    "sg:address":"146 Cochranes Rd",
    "sg:city":"Moorabbin",
    "sg:classifiers":[
        {
            "category":"Shopping",
            "subcategory":"Clothing, Apparel, & Fashions",
            "type":"Retail Goods"
        }
    ],
    "sg:phone":"+61 3 9532 0577",
    "sg:postcode":"3189",
    "sg:province":"VIC",
    "sg:tags":[
        "hire",
        "men's",
        "wear",
        "formal"
    ],
    "wof:name":"Ferrari Formal Hire",
    "wof:placetype":"venue"
},
  "geometry": {"coordinates":[145.07649230999999,-37.9444084167],"type":"Point"}
}