{
  "type": "Feature",
  "properties": {
    "addr:full":"1 John Holland Crt Blackburn VIC 3130",
    "addr:housenumber":"1",
    "addr:postcode":"3130",
    "addr:street":"John Holland Crt",
    "iso:country":"AU",
    "sg:address":"1 John Holland Crt",
    "sg:city":"Blackburn",
    "sg:classifiers":[
        {
            "category":"Retail",
            "subcategory":"Auto Repair",
            "type":"Services"
        }
    ],
    "sg:phone":"+61 3 9894 1492",
    "sg:postcode":"3130",
    "sg:province":"VIC",
    "sg:tags":[
        "sport",
        "motor"
    ],
    "wof:name":"Hand Made Machine",
    "wof:placetype":"venue"
},
  "geometry": {"coordinates":[145.15476989699999,-37.8108901978],"type":"Point"}
}