{
  "type": "Feature",
  "properties": {
    "addr:full":"41-43 Murchison St Marysville VIC 3779",
    "addr:housenumber":"41-43",
    "addr:postcode":"3779",
    "addr:street":"Murchison St",
    "iso:country":"AU",
    "sg:address":"41-43 Murchison St",
    "sg:city":"Marysville",
    "sg:classifiers":[
        {
            "category":"Sports & Exercise",
            "subcategory":"Ski Slope",
            "type":"Entertainment"
        }
    ],
    "sg:phone":"+61 3 5963 3322",
    "sg:postcode":"3779",
    "sg:province":"VIC",
    "sg:tags":[
        "equipment",
        "hire",
        "retail",
        "snow"
    ],
    "wof:name":"A Cross Country Ski Hire",
    "wof:placetype":"venue"
},
  "geometry": {"coordinates":[145.74589499999999,-37.510464],"type":"Point"}
}