{
  "type": "Feature",
  "properties": {
    "iso:country":"AU",
    "sg:address":"116 Artarmon Rd",
    "sg:city":"Artarmon",
    "sg:classifiers":[
        {
            "category":"Health Services",
            "subcategory":"Doctor",
            "type":"Services"
        }
    ],
    "sg:phone":"+61 2 9419 7999",
    "sg:postcode":"2064",
    "sg:province":"NSW",
    "sg:tags":[
        "medical",
        "practitioner"
    ],
    "wof:name":"Magoffin Annabel K. Dr",
    "wof:placetype":"venue"
},
  "geometry": {"coordinates":[151.18746948200001,-33.8074493408],"type":"Point"}
}