{
  "type": "Feature",
  "properties": {
    "addr:full":"12/ 93 Kew St Welshpool WA 6106",
    "addr:housenumber":"12 / 93",
    "addr:postcode":"6106",
    "addr:street":"Kew St",
    "iso:country":"AU",
    "sg:address":"12/ 93 Kew St",
    "sg:city":"Welshpool",
    "sg:classifiers":[
        {
            "category":"Shopping",
            "type":"Retail Goods"
        }
    ],
    "sg:phone":"+61 8 9470 5622",
    "sg:postcode":"6106",
    "sg:province":"WA",
    "sg:tags":[
        "equipment",
        "safety",
        "accessory"
    ],
    "wof:name":"All Welding Services Pty. Ltd.",
    "wof:placetype":"venue"
},
  "geometry": {"coordinates":[115.929916382,-31.9864025116],"type":"Point"}
}