{
  "type": "Feature",
  "properties": {
    "iso:country":"AU",
    "sg:address":"Sugarloaf Hill Rd",
    "sg:city":"Mt McKenzie",
    "sg:classifiers":[
        {
            "category":"Farming",
            "subcategory":"Berry Farm",
            "type":"Manufacturing & Wholesale Goods"
        }
    ],
    "sg:phone":"+61 8 8565 3297",
    "sg:postcode":"5353",
    "sg:province":"SA",
    "sg:tags":[
        "fruit",
        "grower"
    ],
    "wof:name":"Mount McKenzie Raspberry Farm",
    "wof:placetype":"venue"
},
  "geometry": {"coordinates":[139.084716797,-34.5648231506],"type":"Point"}
}