{
  "type": "Feature",
  "properties": {
    "iso:country":"AU",
    "sg:address":"Blockers La",
    "sg:city":"O B Flat",
    "sg:classifiers":[
        {
            "category":"Professional",
            "subcategory":"Engineering",
            "type":"Services"
        }
    ],
    "sg:phone":"+61 8 8726 8218",
    "sg:postcode":"5291",
    "sg:province":"SA",
    "sg:tags":[
        "engineer"
    ],
    "wof:name":"Kermond Engineering",
    "wof:placetype":"venue"
},
  "geometry": {"coordinates":[140.773438,-37.887856],"type":"Point"}
}