{
  "type": "Feature",
  "properties": {
    "addr:full":"107 Mercury St Narwee NSW 2209",
    "addr:housenumber":"107",
    "addr:postcode":"2209",
    "addr:street":"Mercury St",
    "iso:country":"AU",
    "sg:address":"107 Mercury St",
    "sg:city":"Narwee",
    "sg:classifiers":[
        {
            "category":"Building & Trades",
            "subcategory":"Construction",
            "type":"Services"
        }
    ],
    "sg:phone":"+61 2 9533 6696",
    "sg:postcode":"2209",
    "sg:province":"NSW",
    "sg:tags":[
        "home",
        "air conditioning"
    ],
    "wof:name":"J & K Action Air Installation",
    "wof:placetype":"venue"
},
  "geometry": {"coordinates":[151.07074,-33.948673],"type":"Point"}
}