{
  "type": "Feature",
  "properties": {
    "iso:country":"AU",
    "sg:address":"Unit 1, 1271 The Horsley Drv",
    "sg:city":"Wetherill Park",
    "sg:classifiers":[
        {
            "category":"Building & Trades",
            "subcategory":"Construction",
            "type":"Services"
        }
    ],
    "sg:phone":"+61 2 9756 5697",
    "sg:postcode":"2164",
    "sg:province":"NSW",
    "sg:tags":[
        "concrete",
        "contractor"
    ],
    "wof:name":"Colourtone Stencil Systems Pty. Ltd",
    "wof:placetype":"venue"
},
  "geometry": {"coordinates":[150.89094543499999,-33.8523101807],"type":"Point"}
}