{
  "type": "Feature",
  "properties": {
    "addr:full":"21 Pioneer Pl Castle Hill NSW 2154",
    "addr:housenumber":"21",
    "addr:postcode":"2154",
    "addr:street":"Pioneer Pl",
    "iso:country":"AU",
    "sg:address":"21 Pioneer Pl",
    "sg:city":"Castle Hill",
    "sg:classifiers":[
        {
            "category":"Banks & Credit Unions",
            "subcategory":"Bank",
            "type":"Services"
        }
    ],
    "sg:phone":"+61 2 8850 2982",
    "sg:postcode":"2154",
    "sg:province":"NSW",
    "sg:tags":[
        "broker",
        "mortgage"
    ],
    "wof:name":"Money Tree Loan Centre The",
    "wof:placetype":"venue"
},
  "geometry": {"coordinates":[151.01263427699999,-33.7282066345],"type":"Point"}
}