{
  "type": "Feature",
  "properties": {
    "addr:full":"18 Ranelagh Drv Mt Eliza VIC 3930",
    "addr:housenumber":"18",
    "addr:postcode":"3930",
    "addr:street":"Ranelagh Drv",
    "iso:country":"AU",
    "sg:address":"18 Ranelagh Drv",
    "sg:city":"Mt Eliza",
    "sg:classifiers":[
        {
            "category":"Personal",
            "subcategory":"Beauty Salon",
            "type":"Services"
        }
    ],
    "sg:phone":"+61 3 9787 2606",
    "sg:postcode":"3930",
    "sg:province":"VIC",
    "wof:name":"Mt Eliza Hairem",
    "wof:placetype":"venue"
},
  "geometry": {"coordinates":[145.08795165999999,-38.184425354],"type":"Point"}
}