{
  "type": "Feature",
  "properties": {
    "addr:full":"86 Lynch Rd Thomastown VIC 3074",
    "addr:housenumber":"86",
    "addr:postcode":"3074",
    "addr:street":"Lynch Rd",
    "iso:country":"AU",
    "sg:address":"86 Lynch Rd",
    "sg:city":"Thomastown",
    "sg:classifiers":[
        {
            "category":"Professional",
            "type":"Services"
        }
    ],
    "sg:phone":"+61 1300 552 521",
    "sg:postcode":"3074",
    "sg:province":"VIC",
    "sg:tags":[
        "transport"
    ],
    "wof:name":"Atlas Transport",
    "wof:placetype":"venue"
},
  "geometry": {"coordinates":[144.966033936,-37.7110595703],"type":"Point"}
}