{
  "type": "Feature",
  "properties": {
    "iso:country":"AU",
    "sg:address":"12a Renwick St",
    "sg:city":"Leichhardt",
    "sg:classifiers":[
        {
            "category":"Health Services",
            "subcategory":"Health Practitioner",
            "type":"Services"
        }
    ],
    "sg:phone":"+61 2 9564 6463",
    "sg:postcode":"2040",
    "sg:province":"NSW",
    "sg:tags":[
        "physiotherapist"
    ],
    "sg:website":"http://www.physiotherapy.asn.au",
    "wof:name":"Renwick Sports Physio & Orthopaedic Centre",
    "wof:placetype":"venue"
},
  "geometry": {"coordinates":[151.156586,-33.887768],"type":"Point"}
}