{
  "type": "Feature",
  "properties": {
    "addr:full":"352 Canterbury Rd Ringwood VIC 3134",
    "addr:housenumber":"352",
    "addr:postcode":"3134",
    "addr:street":"Canterbury Rd",
    "iso:country":"AU",
    "sg:address":"352 Canterbury Rd",
    "sg:city":"Ringwood",
    "sg:classifiers":[
        {
            "category":"Cafe",
            "type":"Food & Drink"
        }
    ],
    "sg:phone":"+61 3 9298 4500",
    "sg:postcode":"3134",
    "sg:province":"VIC",
    "wof:name":"Ringwood Golf Course",
    "wof:placetype":"venue"
},
  "geometry": {"coordinates":[145.226196289,-37.8325920105],"type":"Point"}
}