{
  "type": "Feature",
  "properties": {
    "iso:country":"AU",
    "sg:address":"17 Lumeah Ave",
    "sg:city":"Wamberal",
    "sg:classifiers":[
        {
            "category":"Building & Trades",
            "subcategory":"Construction",
            "type":"Services"
        }
    ],
    "sg:phone":"+61 2 4385 1200",
    "sg:postcode":"2260",
    "sg:province":"NSW",
    "sg:tags":[
        "contractor"
    ],
    "wof:name":"Malibu Constructions Pty Ltd",
    "wof:placetype":"venue"
},
  "geometry": {"coordinates":[151.443344,-33.431557],"type":"Point"}
}