{
  "type": "Feature",
  "properties": {
    "iso:country":"AU",
    "sg:address":"Stroud St",
    "sg:city":"Balwyn",
    "sg:classifiers":[
        {
            "category":"Education",
            "subcategory":"School",
            "type":"Public Place"
        }
    ],
    "sg:phone":"+61 3 9859 8762",
    "sg:postcode":"3103",
    "sg:province":"VIC",
    "sg:tags":[
        "state",
        "except",
        "nsw"
    ],
    "wof:name":"Belmore School (Special)",
    "wof:placetype":"venue"
},
  "geometry": {"coordinates":[145.08265685999999,-37.8045845032],"type":"Point"}
}