{
  "type": "Feature",
  "properties": {
    "addr:full":"565 Hay St Daglish WA 6008",
    "addr:housenumber":"565",
    "addr:postcode":"6008",
    "addr:street":"Hay St",
    "iso:country":"AU",
    "sg:address":"565 Hay St",
    "sg:city":"Daglish",
    "sg:classifiers":[
        {
            "category":"Professional",
            "subcategory":"Accounting & Tax Preparation",
            "type":"Services"
        }
    ],
    "sg:phone":"+61 8 9382 3244",
    "sg:postcode":"6008",
    "sg:province":"WA",
    "sg:tags":[
        "accountant",
        "auditor"
    ],
    "wof:name":"Marsden Partners",
    "wof:placetype":"venue"
},
  "geometry": {"coordinates":[115.816978455,-31.9473361969],"type":"Point"}
}