{
  "type": "Feature",
  "properties": {
    "iso:country":"AU",
    "sg:address":"Suite 5, 195 Thompsons Rd",
    "sg:city":"Bulleen",
    "sg:classifiers":[
        {
            "category":"Health Services",
            "subcategory":"Doctor",
            "type":"Services"
        }
    ],
    "sg:phone":"+61 3 9850 8998",
    "sg:postcode":"3105",
    "sg:province":"VIC",
    "sg:tags":[
        "medical",
        "practitioner"
    ],
    "wof:name":"Bulleen Medical Centre",
    "wof:placetype":"venue"
},
  "geometry": {"coordinates":[145.098510742,-37.7707595825],"type":"Point"}
}