{
  "type": "Feature",
  "properties": {
    "addr:full":"103 Dyson Rd Christies Beach SA 5165",
    "addr:housenumber":"103",
    "addr:postcode":"5165",
    "addr:street":"Dyson Rd",
    "iso:country":"AU",
    "sg:address":"103 Dyson Rd",
    "sg:city":"Christies Beach",
    "sg:classifiers":[
        {
            "category":"Autos & Motor Vehicles",
            "subcategory":"Auto Supplies",
            "type":"Retail Goods"
        }
    ],
    "sg:phone":"+61 8 8382 1422",
    "sg:postcode":"5165",
    "sg:province":"SA",
    "sg:tags":[
        "battery",
        "automotive"
    ],
    "wof:name":"Christies Auto Electrical",
    "wof:placetype":"venue"
},
  "geometry": {"coordinates":[138.48597717300001,-35.137134552],"type":"Point"}
}