{
  "type": "Feature",
  "properties": {
    "addr:full":"U2/ 5 Abundance Rd Medowie NSW 2318",
    "addr:housenumber":"5",
    "addr:postcode":"2318",
    "addr:street":"U2 /;Abundance Rd",
    "iso:country":"AU",
    "sg:address":"U2/ 5 Abundance Rd",
    "sg:city":"Medowie",
    "sg:classifiers":[
        {
            "category":"Shopping",
            "type":"Retail Goods"
        }
    ],
    "sg:phone":"+61 2 4981 7282",
    "sg:postcode":"2318",
    "sg:province":"NSW",
    "sg:tags":[
        "produce",
        "grain"
    ],
    "wof:name":"Medowie Pet & Produce",
    "wof:placetype":"venue"
},
  "geometry": {"coordinates":[151.856583,-32.740063],"type":"Point"}
}