{
  "type": "Feature",
  "properties": {
    "iso:country":"AU",
    "sg:address":"17 Catalano Rd",
    "sg:city":"Canning Vale",
    "sg:classifiers":[
        {
            "category":"Home & Garden",
            "subcategory":"Carpets & Floor Coverings",
            "type":"Retail Goods"
        }
    ],
    "sg:phone":"+61 8 9455 2228",
    "sg:postcode":"6155",
    "sg:province":"WA",
    "sg:tags":[
        "mat",
        "matting"
    ],
    "wof:name":"C.V.S. Trading Co",
    "wof:placetype":"venue"
},
  "geometry": {"coordinates":[115.903198,-32.060207],"type":"Point"}
}