{
  "type": "Feature",
  "properties": {
    "addr:full":"402 Glenferrie Rd Kooyong VIC 3144",
    "addr:housenumber":"402",
    "addr:postcode":"3144",
    "addr:street":"Glenferrie Rd",
    "iso:country":"AU",
    "sg:address":"402 Glenferrie Rd",
    "sg:city":"Kooyong",
    "sg:classifiers":[
        {
            "category":"Health Services",
            "subcategory":"Doctor",
            "type":"Services"
        }
    ],
    "sg:phone":"+61 3 9822 2006",
    "sg:postcode":"3144",
    "sg:province":"VIC",
    "sg:tags":[
        "medical",
        "practitioner"
    ],
    "wof:name":"Upjohn John W McK",
    "wof:placetype":"venue"
},
  "geometry": {"coordinates":[145.03182983400001,-37.8429870605],"type":"Point"}
}