{
  "type": "Feature",
  "properties": {
    "iso:country":"AU",
    "sg:address":"167 Sunshine Rd",
    "sg:city":"West Footscray",
    "sg:classifiers":[
        {
            "category":"Building & Trades",
            "subcategory":"Cleaning & Sanitation",
            "type":"Services"
        }
    ],
    "sg:phone":"+61 3 9325 1054",
    "sg:postcode":"3012",
    "sg:province":"VIC",
    "sg:tags":[
        "industrial",
        "commercial",
        "contractor"
    ],
    "wof:name":"Damas Cleaning Vic Pty Ltd",
    "wof:placetype":"venue"
},
  "geometry": {"coordinates":[144.863113403,-37.7997436523],"type":"Point"}
}