{
  "type": "Feature",
  "properties": {
    "iso:country":"AU",
    "sg:address":"330 Marion Rd",
    "sg:city":"Netley",
    "sg:classifiers":[
        {
            "category":"Wholesale",
            "subcategory":"Medical Equipment & Supplies",
            "type":"Manufacturing & Wholesale Goods"
        }
    ],
    "sg:phone":"+61 8 8193 1258",
    "sg:postcode":"5037",
    "sg:province":"SA",
    "sg:tags":[
        "aid",
        "care",
        "health",
        "home"
    ],
    "wof:name":"Domiciliary Equipment Service",
    "wof:placetype":"venue"
},
  "geometry": {"coordinates":[138.55389404300001,-34.9535865784],"type":"Point"}
}