{
  "type": "Feature",
  "properties": {
    "iso:country":"AU",
    "sg:address":"9 Blackbutt St",
    "sg:city":"Parklea",
    "sg:classifiers":[
        {
            "category":"Utilities",
            "subcategory":"Telephone",
            "type":"Services"
        }
    ],
    "sg:phone":"+61 1800 247 844",
    "sg:postcode":"2768",
    "sg:province":"NSW",
    "sg:tags":[
        "installation",
        "system",
        "maintenance"
    ],
    "wof:name":"Aqua Telecoms",
    "wof:placetype":"venue"
},
  "geometry": {"coordinates":[150.919495,-33.726303],"type":"Point"}
}