{
  "type": "Feature",
  "properties": {
    "iso:country":"AU",
    "sg:address":"U15/ 41 Sadgroves Crs",
    "sg:city":"Winnellie",
    "sg:classifiers":[
        {
            "category":"Education",
            "subcategory":"Music School",
            "type":"Public Place"
        }
    ],
    "sg:phone":"+61 8 8947 4993",
    "sg:postcode":"0820",
    "sg:province":"NT",
    "sg:tags":[
        "teacher"
    ],
    "wof:name":"Atomic School of Music",
    "wof:placetype":"venue"
},
  "geometry": {"coordinates":[130.89439392099999,-12.4263296127],"type":"Point"}
}