{
  "type": "Feature",
  "properties": {
    "iso:country":"AU",
    "sg:address":"22 Robertson Drv",
    "sg:city":"Mornington",
    "sg:classifiers":[
        {
            "category":"Personal",
            "subcategory":"Beauty Salon",
            "type":"Services"
        }
    ],
    "sg:phone":"+61 3 5975 7333",
    "sg:postcode":"3931",
    "sg:province":"VIC",
    "sg:tags":[
        "hairdresser"
    ],
    "wof:name":"Robertson Drive Hair Centre",
    "wof:placetype":"venue"
},
  "geometry": {"coordinates":[145.05563354500001,-38.2252502441],"type":"Point"}
}