{
  "type": "Feature",
  "properties": {
    "addr:full":"24- 26 Renown St Burwood VIC 3125",
    "addr:housenumber":"26",
    "addr:postcode":"3125",
    "addr:street":"Renown St",
    "iso:country":"AU",
    "sg:address":"24- 26 Renown St",
    "sg:city":"Burwood",
    "sg:classifiers":[
        {
            "category":"Shopping",
            "subcategory":"Stationery & Office Supplies",
            "type":"Retail Goods"
        }
    ],
    "sg:phone":"+61 3 9808 8661",
    "sg:postcode":"3125",
    "sg:province":"VIC",
    "sg:tags":[
        "packaging",
        "equipment",
        "sealing",
        "filling"
    ],
    "wof:name":"Smith & Searls Pty Ltd",
    "wof:placetype":"venue"
},
  "geometry": {"coordinates":[145.12205505399999,-37.8540496826],"type":"Point"}
}