{
  "type": "Feature",
  "properties": {
    "addr:full":"5b Milner St Quinns Rocks WA 6030",
    "addr:housenumber":"5b",
    "addr:postcode":"6030",
    "addr:street":"Milner St",
    "iso:country":"AU",
    "sg:address":"5b Milner St",
    "sg:city":"Quinns Rocks",
    "sg:classifiers":[
        {
            "category":"Food & Beverages",
            "subcategory":"Specialty",
            "type":"Retail Goods"
        }
    ],
    "sg:phone":"+61 8 9305 0121",
    "sg:postcode":"6030",
    "sg:province":"WA",
    "sg:tags":[
        "product",
        "health"
    ],
    "wof:name":"Herbalife Australasia Pty Ltd",
    "wof:placetype":"venue"
},
  "geometry": {"coordinates":[115.69387817400001,-31.6664295197],"type":"Point"}
}