{
  "type": "Feature",
  "properties": {
    "iso:country":"AU",
    "sg:address":"Cnr Bilsen Rd & Virginia St",
    "sg:city":"Virginia",
    "sg:classifiers":[
        {
            "category":"Retail",
            "subcategory":"Auto Repair",
            "type":"Services"
        }
    ],
    "sg:phone":"+61 7 3216 2975",
    "sg:postcode":"4014",
    "sg:province":"QLD",
    "sg:tags":[
        "transmission",
        "automotive",
        "car"
    ],
    "wof:name":"A Sure-Shift Automatics",
    "wof:placetype":"venue"
},
  "geometry": {"coordinates":[153.05744934099999,-27.3633537292],"type":"Point"}
}