{
  "type": "Feature",
  "properties": {
    "iso:country":"AU",
    "sg:address":"282 Clayton Rd",
    "sg:city":"Clayton",
    "sg:classifiers":[
        {
            "category":"Real Estate",
            "subcategory":"Real Estate Agent",
            "type":"Services"
        }
    ],
    "sg:phone":"+61 3 9544 9500",
    "sg:postcode":"3168",
    "sg:province":"VIC",
    "wof:name":"City Wide Real Estate",
    "wof:placetype":"venue"
},
  "geometry": {"coordinates":[145.119873047,-37.925151825],"type":"Point"}
}