{
  "type": "Feature",
  "properties": {
    "iso:country":"AU",
    "sg:address":"41 Keech Rd",
    "sg:city":"Castlereagh",
    "sg:classifiers":[
        {
            "category":"Personal",
            "subcategory":"Massage",
            "type":"Services"
        }
    ],
    "sg:phone":"+61 2 4777 5264",
    "sg:postcode":"2749",
    "sg:province":"NSW",
    "sg:tags":[
        "therapy"
    ],
    "wof:name":"Klein Andreas",
    "wof:placetype":"venue"
},
  "geometry": {"coordinates":[150.689163208,-33.6849975586],"type":"Point"}
}