{
  "type": "Feature",
  "properties": {
    "iso:country":"AU",
    "sg:address":"Unit 3, 116- 118 McCredie Rd",
    "sg:city":"Guildford",
    "sg:classifiers":[
        {
            "category":"Juice Bar",
            "subcategory":"None",
            "type":"Food & Drink"
        }
    ],
    "sg:phone":"+61 2 9681 4111",
    "sg:postcode":"2161",
    "sg:province":"NSW",
    "sg:tags":[
        "merchant",
        "fruit",
        "processor"
    ],
    "wof:name":"Juice World",
    "wof:placetype":"venue"
},
  "geometry": {"coordinates":[150.96029663100001,-33.8502845764],"type":"Point"}
}