{
  "type": "Feature",
  "properties": {
    "addr:full":"36 Mort St Braddon ACT 2612",
    "addr:housenumber":"36",
    "addr:postcode":"2612",
    "addr:street":"Mort St",
    "iso:country":"AU",
    "sg:address":"36 Mort St",
    "sg:city":"Braddon",
    "sg:classifiers":[
        {
            "category":"Autos & Motor Vehicles",
            "subcategory":"Automobile Sales",
            "type":"Retail Goods"
        }
    ],
    "sg:phone":"+61 2 6257 6999",
    "sg:postcode":"2612",
    "sg:province":"ACT",
    "sg:tags":[
        "car",
        "used"
    ],
    "wof:name":"Braddon Auto Mart",
    "wof:placetype":"venue"
},
  "geometry": {"coordinates":[149.131591797,-35.2735939026],"type":"Point"}
}