{
  "type": "Feature",
  "properties": {
    "addr:full":"1202 High St Armadale VIC 3143",
    "addr:housenumber":"1202",
    "addr:postcode":"3143",
    "addr:street":"High St",
    "iso:country":"AU",
    "sg:address":"1202 High St",
    "sg:city":"Armadale",
    "sg:classifiers":[
        {
            "category":"Manufacturing",
            "subcategory":"Furniture",
            "type":"Manufacturing & Wholesale Goods"
        }
    ],
    "sg:phone":"+61 3 9576 2729",
    "sg:postcode":"3143",
    "sg:province":"VIC",
    "sg:tags":[
        "builder",
        "designer",
        "custom"
    ],
    "wof:name":"Luna Blu Arte Moda",
    "wof:placetype":"venue"
},
  "geometry": {"coordinates":[145.027252197,-37.856464386],"type":"Point"}
}