{
  "type": "Feature",
  "properties": {
    "iso:country":"AU",
    "sg:address":"9 Pamela Rd",
    "sg:city":"Gympie",
    "sg:classifiers":[
        {
            "category":"Health Services",
            "subcategory":"Chiropractor",
            "type":"Services"
        }
    ],
    "sg:phone":"+61 7 5482 7111",
    "sg:postcode":"4570",
    "sg:province":"QLD",
    "wof:name":"Kulbys Gerry",
    "wof:placetype":"venue"
},
  "geometry": {"coordinates":[152.644363403,-26.1628246307],"type":"Point"}
}