{
  "type": "Feature",
  "properties": {
    "addr:full":"Apt81/ 78 Terrace Rd East Perth WA 6004",
    "addr:housenumber":"78",
    "addr:postcode":"6004",
    "addr:street":"Terrace Rd East",
    "iso:country":"AU",
    "sg:address":"Apt81/ 78 Terrace Rd",
    "sg:city":"East Perth",
    "sg:classifiers":[
        {
            "category":"Banks & Credit Unions",
            "subcategory":"Financial Services",
            "type":"Services"
        }
    ],
    "sg:phone":"+61 8 9221 1007",
    "sg:postcode":"6004",
    "sg:province":"WA",
    "sg:tags":[
        "loan",
        "finance",
        "mortgage"
    ],
    "wof:name":"Daimark Financial Services",
    "wof:placetype":"venue"
},
  "geometry": {"coordinates":[115.86995697,-31.9608879089],"type":"Point"}
}