{
  "type": "Feature",
  "properties": {
    "addr:full":"99 Princess Rd Balga WA 6061",
    "addr:housenumber":"99",
    "addr:postcode":"6061",
    "addr:street":"Princess Rd",
    "iso:country":"AU",
    "sg:address":"99 Princess Rd",
    "sg:city":"Balga",
    "sg:classifiers":[
        {
            "category":"Health Services",
            "subcategory":"Health Practitioner",
            "type":"Services"
        }
    ],
    "sg:phone":"+61 8 9349 0933",
    "sg:postcode":"6061",
    "sg:province":"WA",
    "sg:tags":[
        "physiotherapist"
    ],
    "wof:name":"Princess Road Physiotherapy",
    "wof:placetype":"venue"
},
  "geometry": {"coordinates":[115.836662292,-31.8564586639],"type":"Point"}
}