{
  "type": "Feature",
  "properties": {
    "addr:full":"85 Moreland St Footscray VIC 3011",
    "addr:housenumber":"85",
    "addr:postcode":"3011",
    "addr:street":"Moreland St",
    "iso:country":"AU",
    "sg:address":"85 Moreland St",
    "sg:city":"Footscray",
    "sg:classifiers":[
        {
            "category":"Train Station",
            "subcategory":"Rail",
            "type":"Transportation"
        }
    ],
    "sg:phone":"+61 3 9687 6622",
    "sg:postcode":"3011",
    "sg:province":"VIC",
    "sg:tags":[
        "marine",
        "engineer"
    ],
    "wof:name":"Marine Industrial Engineering",
    "wof:placetype":"venue"
},
  "geometry": {"coordinates":[144.90589904800001,-37.8045768738],"type":"Point"}
}