{
  "type": "Feature",
  "properties": {
    "addr:full":"72 Kingscliff St Kingscliff NSW 2487",
    "addr:housenumber":"72",
    "addr:postcode":"2487",
    "addr:street":"Kingscliff St",
    "iso:country":"AU",
    "sg:address":"72 Kingscliff St",
    "sg:city":"Kingscliff",
    "sg:classifiers":[
        {
            "category":"Taxi",
            "type":"Transportation"
        }
    ],
    "sg:phone":"+61 2 6674 1530",
    "sg:postcode":"2487",
    "sg:province":"NSW",
    "sg:tags":[
        "cab"
    ],
    "wof:name":"Tweeds Coast Taxis Kingscliff",
    "wof:placetype":"venue"
},
  "geometry": {"coordinates":[153.567504883,-28.2444667816],"type":"Point"}
}