{
  "type": "Feature",
  "properties": {
    "addr:full":"Unit 3/ 27 Collingwood St Osborne Park WA 6017",
    "addr:housenumber":"27",
    "addr:postcode":"6017",
    "addr:street":"Collingwood St",
    "iso:country":"AU",
    "sg:address":"Unit 3/ 27 Collingwood St",
    "sg:city":"Osborne Park",
    "sg:classifiers":[
        {
            "category":"Retail",
            "subcategory":"Auto Repair",
            "type":"Services"
        }
    ],
    "sg:phone":"+61 8 9446 8890",
    "sg:postcode":"6017",
    "sg:province":"WA",
    "sg:tags":[
        "repairer",
        "motor",
        "engineer"
    ],
    "wof:name":"Euromotive",
    "wof:placetype":"venue"
},
  "geometry": {"coordinates":[115.815872192,-31.9035167694],"type":"Point"}
}