{
  "type": "Feature",
  "properties": {
    "iso:country":"AU",
    "sg:address":"150 Mount Joy Pde",
    "sg:city":"Lorne",
    "sg:classifiers":[
        {
            "category":"Food & Beverages",
            "subcategory":"Groceries & Convenience Stores",
            "type":"Retail Goods"
        }
    ],
    "sg:phone":"+61 3 5289 2409",
    "sg:postcode":"3232",
    "sg:province":"VIC",
    "wof:name":"Cumberland Milkbar",
    "wof:placetype":"venue"
},
  "geometry": {"coordinates":[143.975327,-38.542042],"type":"Point"}
}