{
  "type": "Feature",
  "properties": {
    "iso:country":"AU",
    "sg:address":"87 Crocker Drv",
    "sg:city":"Malaga",
    "sg:classifiers":[
        {
            "category":"Banks & Credit Unions",
            "subcategory":"Investment Brokerage",
            "type":"Services"
        }
    ],
    "sg:phone":"+61 8 9249 6233",
    "sg:postcode":"6090",
    "sg:province":"WA",
    "sg:tags":[
        "water",
        "reticulation",
        "contractor"
    ],
    "wof:name":"Irrigation Management Services (WA)",
    "wof:placetype":"venue"
},
  "geometry": {"coordinates":[115.882011414,-31.8542633057],"type":"Point"}
}