{
  "type": "Feature",
  "properties": {
    "addr:full":"56 Cameron St Launceston TAS 7250",
    "addr:housenumber":"56",
    "addr:postcode":"7250",
    "addr:street":"Cameron St",
    "iso:country":"AU",
    "sg:address":"56 Cameron St",
    "sg:city":"Launceston",
    "sg:classifiers":[
        {
            "category":"Fast Food",
            "type":"Food & Drink"
        }
    ],
    "sg:phone":"+61 3 6334 4699",
    "sg:postcode":"7250",
    "sg:province":"TAS",
    "sg:tags":[
        "away",
        "take"
    ],
    "wof:name":"Cameron's Larder",
    "wof:placetype":"venue"
},
  "geometry": {"coordinates":[147.13822937,-41.4352302551],"type":"Point"}
}