{
  "type": "Feature",
  "properties": {
    "iso:country":"AU",
    "sg:address":"1650 Main Drain Rd",
    "sg:city":"Garfield",
    "sg:classifiers":[
        {
            "category":"Food & Beverages",
            "subcategory":"Fruits & Vegetables",
            "type":"Retail Goods"
        }
    ],
    "sg:phone":"+61 3 5629 1099",
    "sg:postcode":"3814",
    "sg:province":"VIC",
    "sg:tags":[
        "grower",
        "potato"
    ],
    "wof:name":"Rouse F & W",
    "wof:placetype":"venue"
},
  "geometry": {"coordinates":[145.64444,-38.13752],"type":"Point"}
}