{
  "type": "Feature",
  "properties": {
    "addr:full":"32 Ashley St Footscray West VIC 3012",
    "addr:housenumber":"32",
    "addr:postcode":"3012",
    "addr:street":"Ashley St",
    "iso:country":"AU",
    "sg:address":"32 Ashley St",
    "sg:city":"Footscray West",
    "sg:classifiers":[
        {
            "category":"Fast Food",
            "type":"Food & Drink"
        }
    ],
    "sg:phone":"+61 3 9689 6806",
    "sg:postcode":"3012",
    "sg:province":"VIC",
    "sg:tags":[
        "away",
        "take"
    ],
    "wof:name":"Sylvia & Frank's Takeaway",
    "wof:placetype":"venue"
},
  "geometry": {"coordinates":[144.86285400400001,-37.7961273193],"type":"Point"}
}