{
  "type": "Feature",
  "properties": {
    "iso:country":"AU",
    "sg:address":"Dominican Convent Marius St",
    "sg:city":"Tamworth",
    "sg:classifiers":[
        {
            "category":"Education",
            "subcategory":"Music School",
            "type":"Public Place"
        }
    ],
    "sg:phone":"+61 2 6766 6911",
    "sg:postcode":"2340",
    "sg:province":"NSW",
    "sg:tags":[
        "teacher"
    ],
    "wof:name":"Tamworth Regional Conservatorium Of Music",
    "wof:placetype":"venue"
},
  "geometry": {"coordinates":[150.93199157699999,-31.089630127],"type":"Point"}
}