{
  "type": "Feature",
  "properties": {
    "addr:full":"Shop 1/1a QVB Wlk Sydney NSW 2000",
    "addr:housenumber":"shop 1 / 1a",
    "addr:postcode":"2000",
    "addr:street":"Qvb Wlk",
    "iso:country":"AU",
    "sg:address":"Shop 1/1a QVB Wlk",
    "sg:city":"Sydney",
    "sg:classifiers":[
        {
            "category":"Shopping",
            "subcategory":"Clothing, Apparel, & Fashions",
            "type":"Retail Goods"
        }
    ],
    "sg:phone":"+61 2 9261 1431",
    "sg:postcode":"2000",
    "sg:province":"NSW",
    "sg:tags":[
        "sportswear"
    ],
    "wof:name":"Hot Tuna Retail Outlet",
    "wof:placetype":"venue"
},
  "geometry": {"coordinates":[151.210006714,-33.8695793152],"type":"Point"}
}