{
  "type": "Feature",
  "properties": {
    "addr:full":"Shop 84 Centro Lavington NSW 2641",
    "addr:housenumber":"shop 84",
    "addr:postcode":"2641",
    "iso:country":"AU",
    "sg:address":"Shop 84 Centro",
    "sg:city":"Lavington",
    "sg:classifiers":[
        {
            "category":"Farming",
            "subcategory":"Fish & Marine Products",
            "type":"Manufacturing & Wholesale Goods"
        }
    ],
    "sg:phone":"+61 2 6025 5311",
    "sg:postcode":"2641",
    "sg:province":"NSW",
    "sg:tags":[
        "organic"
    ],
    "wof:name":"The Health Store",
    "wof:placetype":"venue"
},
  "geometry": {"coordinates":[146.921585083,-36.0359420776],"type":"Point"}
}