{
  "type": "Feature",
  "properties": {
    "addr:full":"3a Charing Crs Marangaroo WA 6064",
    "addr:housenumber":"3a",
    "addr:postcode":"6064",
    "addr:street":"Charing Crs Marangaroo",
    "iso:country":"AU",
    "sg:address":"3a Charing Crs",
    "sg:city":"Marangaroo",
    "sg:classifiers":[
        {
            "category":"Building & Trades",
            "subcategory":"Landscaping Services",
            "type":"Services"
        }
    ],
    "sg:phone":"+61 8 9343 4903",
    "sg:postcode":"6064",
    "sg:province":"WA",
    "sg:tags":[
        "control",
        "weed"
    ],
    "wof:name":"Total Lawn Treatment",
    "wof:placetype":"venue"
},
  "geometry": {"coordinates":[115.826347351,-31.8316307068],"type":"Point"}
}