{
  "type": "Feature",
  "properties": {
    "addr:full":"5/ 4 Glyndebourne Ave Toorak VIC 3142",
    "addr:housenumber":"/ 4",
    "addr:postcode":"3142",
    "addr:street":"Glyndebourne Ave",
    "iso:country":"AU",
    "sg:address":"5/ 4 Glyndebourne Ave",
    "sg:city":"Toorak",
    "sg:classifiers":[
        {
            "category":"Professional",
            "subcategory":"Management & Consulting",
            "type":"Services"
        }
    ],
    "sg:phone":"+61 3 9822 8509",
    "sg:postcode":"3142",
    "sg:province":"VIC",
    "sg:tags":[
        "consultant"
    ],
    "wof:name":"Adhocracy Group The",
    "wof:placetype":"venue"
},
  "geometry": {"coordinates":[145.02442932100001,-37.8404655457],"type":"Point"}
}