{
  "type": "Feature",
  "properties": {
    "addr:full":"24 Mt Ida Ave Hawthorn East VIC 3123",
    "addr:housenumber":"24",
    "addr:postcode":"3123",
    "addr:street":"Mt Ida Ave",
    "iso:country":"AU",
    "sg:address":"24 Mt Ida Ave",
    "sg:city":"Hawthorn East",
    "sg:classifiers":[
        {
            "category":"Real Estate",
            "subcategory":"Surveying",
            "type":"Services"
        }
    ],
    "sg:phone":"+61 3 9882 2756",
    "sg:postcode":"3123",
    "sg:province":"VIC",
    "sg:tags":[
        "surveyor",
        "quantity"
    ],
    "wof:name":"Alsop Rodney",
    "wof:placetype":"venue"
},
  "geometry": {"coordinates":[145.048950195,-37.8381767273],"type":"Point"}
}