{
  "type": "Feature",
  "properties": {
    "iso:country":"AU",
    "sg:address":"467- 481 Woolcock St",
    "sg:city":"Garbutt",
    "sg:classifiers":[
        {
            "category":"Manufacturing",
            "subcategory":"Tools & Machinery",
            "type":"Manufacturing & Wholesale Goods"
        }
    ],
    "sg:phone":"+61 13 12 28",
    "sg:postcode":"4814",
    "sg:province":"QLD",
    "sg:tags":[
        "earth",
        "excavating",
        "moving",
        "equipment"
    ],
    "wof:name":"Hastings Deering",
    "wof:placetype":"venue"
},
  "geometry": {"coordinates":[146.75624099999999,-19.267601],"type":"Point"}
}