{
  "type": "Feature",
  "properties": {
    "addr:full":"14 Longstaff Rd Bayswater VIC 3153",
    "addr:housenumber":"14",
    "addr:postcode":"3153",
    "addr:street":"Longstaff Rd",
    "iso:country":"AU",
    "sg:address":"14 Longstaff Rd",
    "sg:city":"Bayswater",
    "sg:classifiers":[
        {
            "category":"Building & Trades",
            "subcategory":"Electrical",
            "type":"Services"
        }
    ],
    "sg:phone":"+61 1800 630 333",
    "sg:postcode":"3153",
    "sg:province":"VIC",
    "sg:tags":[
        "wholesaler",
        "equipment",
        "magnetic",
        "mfrs"
    ],
    "wof:name":"Steinert Sturton-Gill Magnetics Pty Ltd",
    "wof:placetype":"venue"
},
  "geometry": {"coordinates":[145.2862854,-37.835357666],"type":"Point"}
}