{
  "type": "Feature",
  "properties": {
    "iso:country":"AU",
    "sg:address":"Jimboomba Shopping Centre Mt Lindsay Hwy",
    "sg:city":"Jimboomba",
    "sg:classifiers":[
        {
            "category":"Fast Food",
            "type":"Food & Drink"
        }
    ],
    "sg:phone":"+61 7 5546 9585",
    "sg:postcode":"4280",
    "sg:province":"QLD",
    "sg:tags":[
        "away",
        "take"
    ],
    "wof:name":"Chicken Time",
    "wof:placetype":"venue"
},
  "geometry": {"coordinates":[153.02887000000001,-27.813459],"type":"Point"}
}