{
  "type": "Feature",
  "properties": {
    "addr:full":"267 St Georges Tce Perth WA 6000",
    "addr:housenumber":"267",
    "addr:postcode":"6000",
    "addr:street":"St Georges Tce",
    "iso:country":"AU",
    "sg:address":"267 St Georges Tce",
    "sg:city":"Perth",
    "sg:classifiers":[
        {
            "category":"Professional",
            "subcategory":"Computer Services",
            "type":"Services"
        }
    ],
    "sg:phone":"+61 8 9261 7770",
    "sg:postcode":"6000",
    "sg:province":"WA",
    "sg:tags":[
        "package",
        "software"
    ],
    "wof:name":"MDY Business Solutions",
    "wof:placetype":"venue"
},
  "geometry": {"coordinates":[115.849342346,-31.9524593353],"type":"Point"}
}