{
  "type": "Feature",
  "properties": {
    "iso:country":"AU",
    "sg:address":"56 Harrow Crt",
    "sg:city":"Caboolture",
    "sg:classifiers":[
        {
            "category":"Professional",
            "subcategory":"Art Services",
            "type":"Services"
        }
    ],
    "sg:phone":"+61 7 5498 3173",
    "sg:postcode":"4510",
    "sg:province":"QLD",
    "sg:tags":[
        "decorator",
        "painter"
    ],
    "wof:name":"Colin Van Kruining",
    "wof:placetype":"venue"
},
  "geometry": {"coordinates":[152.948929,-27.050812],"type":"Point"}
}