{
  "type": "Feature",
  "properties": {
    "addr:full":"4 Bunbury St Bridgetown WA 6255",
    "addr:housenumber":"4",
    "addr:postcode":"6255",
    "addr:street":"Bunbury St",
    "iso:country":"AU",
    "sg:address":"4 Bunbury St",
    "sg:city":"Bridgetown",
    "sg:classifiers":[
        {
            "category":"Retail",
            "subcategory":"Auto Repair",
            "type":"Services"
        }
    ],
    "sg:phone":"+61 8 9761 1174",
    "sg:postcode":"6255",
    "sg:province":"WA",
    "sg:tags":[
        "repairer",
        "motor",
        "engineer"
    ],
    "wof:name":"Bridgetown Engineering & Mechanical Repairs",
    "wof:placetype":"venue"
},
  "geometry": {"coordinates":[116.138023377,-33.9549598694],"type":"Point"}
}