{
  "type": "Feature",
  "properties": {
    "addr:full":"Great Eastern Hwy Cunderdin WA 6407",
    "addr:postcode":"6407",
    "addr:street":"Eastern Hwy",
    "iso:country":"AU",
    "sg:address":"Great Eastern Hwy",
    "sg:city":"Cunderdin",
    "sg:classifiers":[
        {
            "category":"Autos & Motor Vehicles",
            "subcategory":"Fuel & Gas Station",
            "type":"Retail Goods"
        }
    ],
    "sg:phone":"+61 8 9635 1151",
    "sg:postcode":"6407",
    "sg:province":"WA",
    "wof:name":"Peak Petroleum",
    "wof:placetype":"venue"
},
  "geometry": {"coordinates":[117.236450195,-31.6515865326],"type":"Point"}
}