{
  "type": "Feature",
  "properties": {
    "addr:full":"903 Main North Rd Pooraka SA 5095",
    "addr:housenumber":"903",
    "addr:postcode":"5095",
    "addr:street":"Main North Rd",
    "iso:country":"AU",
    "sg:address":"903 Main North Rd",
    "sg:city":"Pooraka",
    "sg:classifiers":[
        {
            "category":"Retail",
            "subcategory":"Auto Repair",
            "type":"Services"
        }
    ],
    "sg:phone":"+61 408 655 588",
    "sg:postcode":"5095",
    "sg:province":"SA",
    "sg:tags":[
        "electrical"
    ],
    "wof:name":"Darike Automatics",
    "wof:placetype":"venue"
},
  "geometry": {"coordinates":[138.619308472,-34.8222427368],"type":"Point"}
}