{
  "type": "Feature",
  "properties": {
    "addr:full":"133 Mary St Brisbane QLD 4000",
    "addr:housenumber":"133",
    "addr:postcode":"4000",
    "addr:street":"Mary St",
    "iso:country":"AU",
    "sg:address":"133 Mary St",
    "sg:city":"Brisbane",
    "sg:classifiers":[
        {
            "category":"Insurance",
            "subcategory":"Hazard Insurance",
            "type":"Services"
        }
    ],
    "sg:phone":"+61 13 37 23",
    "sg:postcode":"4000",
    "sg:province":"QLD",
    "sg:tags":[
        "motor",
        "vehicle"
    ],
    "wof:name":"Western QBE Insurance",
    "wof:placetype":"venue"
},
  "geometry": {"coordinates":[153.02867126500001,-27.4711551666],"type":"Point"}
}