{
  "type": "Feature",
  "properties": {
    "addr:full":"20 Currie Rd Forestville NSW 2087",
    "addr:housenumber":"20",
    "addr:postcode":"2087",
    "addr:street":"Currie Rd",
    "iso:country":"AU",
    "sg:address":"20 Currie Rd",
    "sg:city":"Forestville",
    "sg:classifiers":[
        {
            "category":"Shopping",
            "subcategory":"Computers & Home Electronics",
            "type":"Retail Goods"
        }
    ],
    "sg:phone":"+61 2 9451 6140",
    "sg:postcode":"2087",
    "sg:province":"NSW",
    "sg:tags":[
        "small",
        "equipment",
        "business"
    ],
    "wof:name":"Computer Awarness & Productivity Services",
    "wof:placetype":"venue"
},
  "geometry": {"coordinates":[151.22132873499999,-33.7594871521],"type":"Point"}
}