{
  "type": "Feature",
  "properties": {
    "iso:country":"AU",
    "sg:address":"2 Station St",
    "sg:city":"Ashfield",
    "sg:classifiers":[
        {
            "category":"Travel",
            "subcategory":"Travel Agent",
            "type":"Entertainment"
        }
    ],
    "sg:phone":"+61 2 9797 9922",
    "sg:postcode":"2131",
    "sg:province":"NSW",
    "sg:tags":[
        "consultant"
    ],
    "wof:name":"Daystar Travel & Tours Pty Ltd",
    "wof:placetype":"venue"
},
  "geometry": {"coordinates":[151.12559509299999,-33.887348175],"type":"Point"}
}