{
  "type": "Feature",
  "properties": {
    "addr:full":"7 Kialla Lakes Drv Kialla VIC 3631",
    "addr:housenumber":"7",
    "addr:postcode":"3631",
    "addr:street":"Kialla Lakes Drv",
    "iso:country":"AU",
    "sg:address":"7 Kialla Lakes Drv",
    "sg:city":"Kialla",
    "sg:classifiers":[
        {
            "category":"Manufacturing",
            "subcategory":"Paper Products",
            "type":"Manufacturing & Wholesale Goods"
        }
    ],
    "sg:phone":"+61 3 5823 2666",
    "sg:postcode":"3631",
    "sg:province":"VIC",
    "sg:tags":[
        "wholesaler",
        "mfrs"
    ],
    "wof:name":"Stockforms Australia",
    "wof:placetype":"venue"
},
  "geometry": {"coordinates":[145.39390564000001,-36.413646698],"type":"Point"}
}