{
  "type": "Feature",
  "properties": {
    "iso:country":"AU",
    "sg:address":"41- 43 Mooreville Rd",
    "sg:city":"Burnie",
    "sg:classifiers":[
        {
            "category":"Education",
            "subcategory":"University",
            "type":"Public Place"
        }
    ],
    "sg:phone":"+61 1300 655 307",
    "sg:postcode":"7320",
    "sg:province":"TAS",
    "sg:tags":[
        "college",
        "tertiary"
    ],
    "wof:name":"TAFE Tasmania",
    "wof:placetype":"venue"
},
  "geometry": {"coordinates":[145.88118,-41.060375],"type":"Point"}
}