{
  "type": "Feature",
  "properties": {
    "addr:full":"2/ 9 William St Fairfield NSW 2165",
    "addr:housenumber":"/ 9",
    "addr:postcode":"2165",
    "addr:street":"William St",
    "iso:country":"AU",
    "sg:address":"2/ 9 William St",
    "sg:city":"Fairfield",
    "sg:classifiers":[
        {
            "category":"Health Services",
            "subcategory":"Doctor",
            "type":"Services"
        }
    ],
    "sg:phone":"+61 2 9728 3260",
    "sg:postcode":"2165",
    "sg:province":"NSW",
    "sg:tags":[
        "medical",
        "practitioner"
    ],
    "wof:name":"Swid Gias Dr",
    "wof:placetype":"venue"
},
  "geometry": {"coordinates":[150.954223633,-33.8729934692],"type":"Point"}
}