{
  "type": "Feature",
  "properties": {
    "addr:full":"2 Gibson St Meandarra QLD 4422",
    "addr:housenumber":"2",
    "addr:postcode":"4422",
    "addr:street":"Gibson St",
    "iso:country":"AU",
    "sg:address":"2 Gibson St",
    "sg:city":"Meandarra",
    "sg:classifiers":[
        {
            "category":"Building & Trades",
            "subcategory":"Construction",
            "type":"Services"
        }
    ],
    "sg:phone":"+61 7 4665 6295",
    "sg:postcode":"4422",
    "sg:province":"QLD",
    "sg:tags":[
        "earth",
        "excavating",
        "moving",
        "contractor"
    ],
    "wof:name":"Max Kummerow",
    "wof:placetype":"venue"
},
  "geometry": {"coordinates":[149.88351440400001,-27.3269615173],"type":"Point"}
}