{
  "type": "Feature",
  "properties": {
    "iso:country":"AU",
    "sg:address":"14 Green St",
    "sg:city":"St Kilda East",
    "sg:classifiers":[
        {
            "category":"Professional",
            "subcategory":"Computer Services",
            "type":"Services"
        }
    ],
    "sg:phone":"+61 3 9527 2943",
    "sg:postcode":"3183",
    "sg:province":"VIC",
    "sg:tags":[
        "information"
    ],
    "wof:name":"AC Information Services",
    "wof:placetype":"venue"
},
  "geometry": {"coordinates":[145.00453185999999,-37.8726081848],"type":"Point"}
}