{
  "type": "Feature",
  "properties": {
    "iso:country":"AU",
    "sg:address":"43 Australia Crt",
    "sg:city":"Scarborough",
    "sg:classifiers":[
        {
            "category":"Professional",
            "subcategory":"Testing Lab",
            "type":"Services"
        }
    ],
    "sg:phone":"+61 7 3880 4199",
    "sg:postcode":"4020",
    "sg:province":"QLD",
    "sg:tags":[
        "inspection"
    ],
    "wof:name":"Martin R W & Associates Pty Ltd",
    "wof:placetype":"venue"
},
  "geometry": {"coordinates":[153.095337,-27.207514],"type":"Point"}
}