{
  "type": "Feature",
  "properties": {
    "addr:full":"18 Arthur St Bunbury WA 6230",
    "addr:housenumber":"18",
    "addr:postcode":"6230",
    "addr:street":"Arthur St",
    "iso:country":"AU",
    "sg:address":"18 Arthur St",
    "sg:city":"Bunbury",
    "sg:classifiers":[
        {
            "category":"Shopping",
            "subcategory":"Clothing, Apparel, & Fashions",
            "type":"Retail Goods"
        }
    ],
    "sg:phone":"+61 8 9792 5755",
    "sg:postcode":"6230",
    "sg:province":"WA",
    "sg:tags":[
        "menswear"
    ],
    "wof:name":"X-Treme T's",
    "wof:placetype":"venue"
},
  "geometry": {"coordinates":[115.63902299999999,-33.326801],"type":"Point"}
}