{
  "type": "Feature",
  "properties": {
    "addr:full":"Cnr Gold Coast Hwy & Palm Beach Ave Palm Beach QLD 4221",
    "addr:postcode":"4221",
    "addr:street":"Gold Coast Hwy & Palm;Ave",
    "iso:country":"AU",
    "sg:address":"Cnr Gold Coast Hwy & Palm Beach Ave",
    "sg:city":"Palm Beach",
    "sg:classifiers":[
        {
            "category":"Food & Beverages",
            "subcategory":"Groceries & Convenience Stores",
            "type":"Retail Goods"
        }
    ],
    "sg:phone":"+61 7 5598 1766",
    "sg:postcode":"4221",
    "sg:province":"QLD",
    "wof:name":"7-Eleven Stores Pty Ltd",
    "wof:placetype":"venue"
},
  "geometry": {"coordinates":[153.472824097,-28.1213474274],"type":"Point"}
}