{
  "type": "Feature",
  "properties": {
    "addr:full":"PO Box 3 Seaford SA 5169",
    "addr:postcode":"5169",
    "iso:country":"AU",
    "sg:address":"PO Box 3",
    "sg:city":"Seaford",
    "sg:classifiers":[
        {
            "category":"Professional",
            "subcategory":"Art Services",
            "type":"Services"
        }
    ],
    "sg:phone":"+61 8 8386 0726",
    "sg:postcode":"5169",
    "sg:province":"SA",
    "sg:tags":[
        "artist"
    ],
    "wof:name":"One & Only",
    "wof:placetype":"venue"
},
  "geometry": {"coordinates":[138.477050781,-35.1855392456],"type":"Point"}
}