{
  "type": "Feature",
  "properties": {
    "iso:country":"AU",
    "sg:address":"11 Mine St",
    "sg:city":"Redbank",
    "sg:classifiers":[
        {
            "category":"Manufacturing",
            "subcategory":"Pottery",
            "type":"Manufacturing & Wholesale Goods"
        }
    ],
    "sg:phone":"+61 7 3288 2091",
    "sg:postcode":"4301",
    "sg:province":"QLD",
    "wof:name":"Milner Porcelain Products",
    "wof:placetype":"venue"
},
  "geometry": {"coordinates":[152.86900329599999,-27.6022796631],"type":"Point"}
}