{
  "type": "Feature",
  "properties": {
    "addr:full":"125 Hackford Drv Kingston TAS 7050",
    "addr:housenumber":"125",
    "addr:postcode":"7050",
    "addr:street":"Hackford Drv",
    "iso:country":"AU",
    "sg:address":"125 Hackford Drv",
    "sg:city":"Kingston",
    "sg:classifiers":[
        {
            "category":"Utilities",
            "subcategory":"Electric",
            "type":"Services"
        }
    ],
    "sg:phone":"+61 3 6229 5994",
    "sg:postcode":"7050",
    "sg:province":"TAS",
    "sg:tags":[
        "electrical",
        "contractor"
    ],
    "wof:name":"Webb A.G. & J.A.",
    "wof:placetype":"venue"
},
  "geometry": {"coordinates":[147.263474,-42.961033],"type":"Point"}
}