{
  "type": "Feature",
  "properties": {
    "addr:full":"11 Helen St Caloundra QLD 4551",
    "addr:housenumber":"11",
    "addr:postcode":"4551",
    "addr:street":"Helen St",
    "iso:country":"AU",
    "sg:address":"11 Helen St",
    "sg:city":"Caloundra",
    "sg:classifiers":[
        {
            "category":"Freight",
            "type":"Transportation"
        }
    ],
    "sg:phone":"+61 7 5492 7788",
    "sg:postcode":"4551",
    "sg:province":"QLD",
    "sg:tags":[
        "transport",
        "refrigerated"
    ],
    "wof:name":"Wilmot Freeze Haul",
    "wof:placetype":"venue"
},
  "geometry": {"coordinates":[153.10775756800001,-26.791929245],"type":"Point"}
}