{
  "type": "Feature",
  "properties": {
    "iso:country":"AU",
    "sg:address":"398b Victoria Rd",
    "sg:city":"Malaga",
    "sg:classifiers":[
        {
            "category":"Shopping",
            "subcategory":"Bicycles & Sporting Goods",
            "type":"Retail Goods"
        }
    ],
    "sg:phone":"+61 8 9248 6866",
    "sg:postcode":"6090",
    "sg:province":"WA",
    "sg:tags":[
        "trampoline"
    ],
    "wof:name":"Jet Jol Trampolines",
    "wof:placetype":"venue"
},
  "geometry": {"coordinates":[115.900588989,-31.8616752625],"type":"Point"}
}