{
  "type": "Feature",
  "properties": {
    "iso:country":"AU",
    "sg:address":"Level 9/ 227 Collins St",
    "sg:city":"Melbourne",
    "sg:classifiers":[
        {
            "category":"Banks & Credit Unions",
            "subcategory":"Investment Brokerage",
            "type":"Services"
        }
    ],
    "sg:phone":"+61 1300 799 511",
    "sg:postcode":"3000",
    "sg:province":"VIC",
    "sg:tags":[
        "debt",
        "collection"
    ],
    "wof:name":"Debt Recoveries Australia",
    "wof:placetype":"venue"
},
  "geometry": {"coordinates":[144.96478271500001,-37.8181190491],"type":"Point"}
}