{
  "type": "Feature",
  "properties": {
    "iso:country":"AU",
    "sg:address":"138 Collins Ave",
    "sg:city":"Edge Hill",
    "sg:classifiers":[
        {
            "category":"Fast Food",
            "type":"Food & Drink"
        }
    ],
    "sg:phone":"+61 7 4053 4630",
    "sg:postcode":"4870",
    "sg:province":"QLD",
    "sg:tags":[
        "away",
        "take"
    ],
    "wof:name":"Flynns On Collins",
    "wof:placetype":"venue"
},
  "geometry": {"coordinates":[145.74220275900001,-16.9009437561],"type":"Point"}
}