{
  "type": "Feature",
  "properties": {
    "addr:full":"24 Church St Chatswood NSW 2067",
    "addr:housenumber":"24",
    "addr:postcode":"2067",
    "addr:street":"Church St",
    "iso:country":"AU",
    "sg:address":"24 Church St",
    "sg:city":"Chatswood",
    "sg:classifiers":[
        {
            "category":"Retail",
            "subcategory":"Car Wash",
            "type":"Services"
        }
    ],
    "sg:phone":"+61 2 9419 4999",
    "sg:postcode":"2067",
    "sg:province":"NSW",
    "sg:tags":[
        "truck",
        "cleaning"
    ],
    "wof:name":"Clean-A-Car",
    "wof:placetype":"venue"
},
  "geometry": {"coordinates":[151.19473266599999,-33.7957077026],"type":"Point"}
}