{
  "type": "Feature",
  "properties": {
    "iso:country":"AU",
    "sg:address":"Shop 11 Beaumaris City Constellation Drv",
    "sg:city":"Ocean Reef",
    "sg:classifiers":[
        {
            "category":"Fast Food",
            "type":"Food & Drink"
        }
    ],
    "sg:phone":"+61 8 9300 4828",
    "sg:postcode":"6027",
    "sg:province":"WA",
    "sg:tags":[
        "away",
        "take"
    ],
    "wof:name":"Beaumaris Fish & Chips",
    "wof:placetype":"venue"
},
  "geometry": {"coordinates":[115.732978821,-31.7506504059],"type":"Point"}
}