{
  "type": "Feature",
  "properties": {
    "addr:full":"21 Gladstone Rd Leura NSW 2780",
    "addr:housenumber":"21",
    "addr:postcode":"2780",
    "addr:street":"Gladstone Rd",
    "iso:country":"AU",
    "sg:address":"21 Gladstone Rd",
    "sg:city":"Leura",
    "sg:classifiers":[
        {
            "category":"Organizations",
            "subcategory":"Non-profit Organization",
            "type":"Services"
        }
    ],
    "sg:phone":"+61 2 4784 3345",
    "sg:postcode":"2780",
    "sg:province":"NSW",
    "sg:tags":[
        "support",
        "disability",
        "organisation"
    ],
    "wof:name":"Handicapped Childrens Centre Of NSW The",
    "wof:placetype":"venue"
},
  "geometry": {"coordinates":[150.34237670900001,-33.7126426697],"type":"Point"}
}