{
  "type": "Feature",
  "properties": {
    "iso:country":"AU",
    "sg:address":"2nd Floor Highway Arcade 47 Stuart Hwy",
    "sg:city":"Stuart Park",
    "sg:classifiers":[
        {
            "category":"Organizations",
            "subcategory":"Community Association",
            "type":"Services"
        }
    ],
    "sg:phone":"+61 8 8941 1752",
    "sg:postcode":"0820",
    "sg:province":"NT",
    "sg:tags":[
        "organisation",
        "family",
        "welfare"
    ],
    "wof:name":"Employee Assistance Service Australia",
    "wof:placetype":"venue"
},
  "geometry": {"coordinates":[130.84078979500001,-12.447936058],"type":"Point"}
}