{
  "type": "Feature",
  "properties": {
    "iso:country":"AU",
    "sg:address":"507 Nelson Rd",
    "sg:city":"Mt Nelson",
    "sg:classifiers":[
        {
            "category":"Shopping",
            "subcategory":"Computers & Home Electronics",
            "type":"Retail Goods"
        }
    ],
    "sg:phone":"+61 409 005 894",
    "sg:postcode":"7007",
    "sg:province":"TAS",
    "sg:tags":[
        "equipment",
        "multimedia"
    ],
    "wof:name":"Accent Design",
    "wof:placetype":"venue"
},
  "geometry": {"coordinates":[147.32550048799999,-42.9235229492],"type":"Point"}
}