{
  "type": "Feature",
  "properties": {
    "iso:country":"AU",
    "sg:address":"Lower Franklin Rd",
    "sg:city":"Foster",
    "sg:classifiers":[
        {
            "category":"Utilities",
            "subcategory":"Electric",
            "type":"Services"
        }
    ],
    "sg:phone":"+61 3 5682 2459",
    "sg:postcode":"3960",
    "sg:province":"VIC",
    "sg:tags":[
        "electrical",
        "contractor"
    ],
    "wof:name":"Williams W R",
    "wof:placetype":"venue"
},
  "geometry": {"coordinates":[146.21461486800001,-38.6612510681],"type":"Point"}
}