{
  "type": "Feature",
  "properties": {
    "iso:country":"AU",
    "sg:address":"4D/ 27 Ocean St",
    "sg:city":"Bondi",
    "sg:classifiers":[
        {
            "category":"Sports & Exercise",
            "subcategory":"Gym",
            "type":"Entertainment"
        }
    ],
    "sg:phone":"+61 2 9389 2538",
    "sg:postcode":"2026",
    "sg:province":"NSW",
    "sg:tags":[
        "personal",
        "trainer",
        "fitness"
    ],
    "wof:name":"Step into Life Rushcutters Bay",
    "wof:placetype":"venue"
},
  "geometry": {"coordinates":[151.26268005399999,-33.8917999268],"type":"Point"}
}