{
  "type": "Feature",
  "properties": {
    "addr:full":"\"Mallapunyah Springs\" PMB 13 Tennant Creek NT 0860",
    "addr:housenumber":"13",
    "addr:postcode":"nt 0860",
    "addr:street":"Pmb",
    "iso:country":"AU",
    "sg:address":"\"Mallapunyah Springs\" PMB 13",
    "sg:city":"Tennant Creek",
    "sg:classifiers":[
        {
            "category":"Building & Trades",
            "subcategory":"Landscaping Services",
            "type":"Services"
        }
    ],
    "sg:phone":"+61 8 8975 9912",
    "sg:postcode":"0860",
    "sg:province":"NT",
    "sg:tags":[
        "grazier"
    ],
    "wof:name":"Darcy Brothers",
    "wof:placetype":"venue"
},
  "geometry": {"coordinates":[134.178955,-19.64492],"type":"Point"}
}