{
  "type": "Feature",
  "properties": {
    "addr:full":"Bldg 40 The Avenue Mt Penang Parklands Pacific Hwy Kariong NSW 2250",
    "addr:housenumber":"40",
    "addr:postcode":"2250",
    "addr:street":"The Avenue;Penang Parklands Pacific Hwy",
    "iso:country":"AU",
    "sg:address":"Bldg 40 The Avenue Mt Penang Parklands Pacific Hwy",
    "sg:city":"Kariong",
    "sg:classifiers":[
        {
            "category":"Social Services",
            "subcategory":"Retirement Home",
            "type":"Services"
        }
    ],
    "sg:phone":"+61 2 4340 0677",
    "sg:postcode":"2250",
    "sg:province":"NSW",
    "sg:tags":[
        "environmental",
        "consultant",
        "pollution"
    ],
    "wof:name":"Travers John",
    "wof:placetype":"venue"
},
  "geometry": {"coordinates":[151.29852294899999,-33.436466217],"type":"Point"}
}