{
  "type": "Feature",
  "properties": {
    "addr:full":"93A Great North Rd Five Dock NSW 2046",
    "addr:housenumber":"93a",
    "addr:postcode":"2046",
    "addr:street":"Great North Rd",
    "iso:country":"AU",
    "sg:address":"93A Great North Rd",
    "sg:city":"Five Dock",
    "sg:classifiers":[
        {
            "category":"Health Services",
            "subcategory":"Health Practitioner",
            "type":"Services"
        }
    ],
    "sg:phone":"+61 2 9713 6423",
    "sg:postcode":"2046",
    "sg:province":"NSW",
    "sg:tags":[
        "naturopath"
    ],
    "wof:name":"Go-Vita Five Dock Health Nutrition & Natural Therapies Centr",
    "wof:placetype":"venue"
},
  "geometry": {"coordinates":[151.129166,-33.869957],"type":"Point"}
}