{
  "type": "Feature",
  "properties": {
    "addr:full":"Shop 1, 105 Regent St Redfern NSW 2016",
    "addr:housenumber":"shop 1 105",
    "addr:postcode":"2016",
    "addr:street":"Regent St",
    "iso:country":"AU",
    "sg:address":"Shop 1, 105 Regent St",
    "sg:city":"Redfern",
    "sg:classifiers":[
        {
            "category":"Professional",
            "subcategory":"Art Services",
            "type":"Services"
        }
    ],
    "sg:phone":"+61 411 728 647",
    "sg:postcode":"2016",
    "sg:province":"NSW",
    "sg:tags":[
        "interior",
        "decorator"
    ],
    "wof:name":"Distinctive Interiors Soft Furnishings",
    "wof:placetype":"venue"
},
  "geometry": {"coordinates":[151.200805664,-33.8919372559],"type":"Point"}
}