{
  "type": "Feature",
  "properties": {
    "addr:full":"28 Sulman Rd Wembley Downs WA 6019",
    "addr:housenumber":"28",
    "addr:postcode":"6019",
    "addr:street":"Sulman Rd",
    "iso:country":"AU",
    "sg:address":"28 Sulman Rd",
    "sg:city":"Wembley Downs",
    "sg:classifiers":[
        {
            "category":"Education",
            "subcategory":"Dance Studio",
            "type":"Public Place"
        }
    ],
    "sg:phone":"+61 8 9448 6519",
    "sg:postcode":"6019",
    "sg:province":"WA",
    "sg:tags":[
        "instruction",
        "language"
    ],
    "wof:name":"German Language Classes (WA)",
    "wof:placetype":"venue"
},
  "geometry": {"coordinates":[115.77487945599999,-31.912355423],"type":"Point"}
}