{
  "type": "Feature",
  "properties": {
    "iso:country":"AU",
    "sg:address":"344 Shepherds Hill Rd",
    "sg:city":"Blackwood",
    "sg:classifiers":[
        {
            "category":"Real Estate",
            "subcategory":"Real Estate Agent",
            "type":"Services"
        }
    ],
    "sg:phone":"+61 8 8278 1922",
    "sg:postcode":"5051",
    "sg:province":"SA",
    "wof:name":"Hawkins Cliff Pty Ltd",
    "wof:placetype":"venue"
},
  "geometry": {"coordinates":[138.615616,-35.021126],"type":"Point"}
}