{
  "type": "Feature",
  "properties": {
    "addr:full":"51-53 Lygon St Brunswick East VIC 3057",
    "addr:housenumber":"51-53",
    "addr:postcode":"3057",
    "addr:street":"Lygon St",
    "iso:country":"AU",
    "sg:address":"51-53 Lygon St",
    "sg:city":"Brunswick East",
    "sg:classifiers":[
        {
            "category":"Personal",
            "subcategory":"Beauty Salon",
            "type":"Services"
        }
    ],
    "sg:phone":"+61 3 9388 9366",
    "sg:postcode":"3057",
    "sg:province":"VIC",
    "sg:tags":[
        "hairdresser"
    ],
    "wof:name":"Out Of Africa Arts & Crafts",
    "wof:placetype":"venue"
},
  "geometry": {"coordinates":[144.97067260700001,-37.7774467468],"type":"Point"}
}