{
  "type": "Feature",
  "properties": {
    "addr:full":"PO Box 3144 Freemans Reach NSW 2756",
    "addr:postcode":"2756",
    "iso:country":"AU",
    "sg:address":"PO Box 3144",
    "sg:city":"Freemans Reach",
    "sg:classifiers":[
        {
            "category":"Building & Trades",
            "subcategory":"Equipment Rental",
            "type":"Services"
        }
    ],
    "sg:phone":"+61 413 584 425",
    "sg:postcode":"2756",
    "sg:province":"NSW",
    "sg:tags":[
        "demolition",
        "contractor"
    ],
    "wof:name":"Excel Demolition Pty Ltd",
    "wof:placetype":"venue"
},
  "geometry": {"coordinates":[150.79960632300001,-33.5579185486],"type":"Point"}
}