{
  "type": "Feature",
  "properties": {
    "addr:full":"7 Lockhart Drv Rosebud VIC 3939",
    "addr:housenumber":"7",
    "addr:postcode":"3939",
    "addr:street":"Lockhart Drv",
    "iso:country":"AU",
    "sg:address":"7 Lockhart Drv",
    "sg:city":"Rosebud",
    "sg:classifiers":[
        {
            "category":"Home & Garden",
            "subcategory":"Carpets & Floor Coverings",
            "type":"Retail Goods"
        }
    ],
    "sg:phone":"+61 3 5986 6386",
    "sg:postcode":"3939",
    "sg:province":"VIC",
    "sg:tags":[
        "tile",
        "wall",
        "layer"
    ],
    "wof:name":"Griffith B Wall Tiler",
    "wof:placetype":"venue"
},
  "geometry": {"coordinates":[144.896286011,-38.3758201599],"type":"Point"}
}