{
  "type": "Feature",
  "properties": {
    "addr:full":"8 Helen St Heidelberg Heights VIC 3081",
    "addr:housenumber":"8",
    "addr:postcode":"3081",
    "addr:street":"Helen St",
    "iso:country":"AU",
    "sg:address":"8 Helen St",
    "sg:city":"Heidelberg Heights",
    "sg:classifiers":[
        {
            "category":"Manufacturing",
            "subcategory":"Wood Products",
            "type":"Manufacturing & Wholesale Goods"
        }
    ],
    "sg:phone":"+61 3 9459 2112",
    "sg:postcode":"3081",
    "sg:province":"VIC",
    "sg:tags":[
        "polisher",
        "french"
    ],
    "wof:name":"Upholstery Restored",
    "wof:placetype":"venue"
},
  "geometry": {"coordinates":[145.052902222,-37.7344818115],"type":"Point"}
}