{
  "type": "Feature",
  "properties": {
    "iso:country":"AU",
    "sg:address":"50 Allingham St",
    "sg:city":"Condell Park",
    "sg:classifiers":[
        {
            "category":"Shopping",
            "subcategory":"Computers & Home Electronics",
            "type":"Retail Goods"
        }
    ],
    "sg:phone":"+61 2 9791 0277",
    "sg:postcode":"2200",
    "sg:province":"NSW",
    "sg:tags":[
        "wholesaler",
        "equipment",
        "electronic",
        "mfrs"
    ],
    "wof:name":"Traction Controls Pty Ltd",
    "wof:placetype":"venue"
},
  "geometry": {"coordinates":[151.000137,-33.919735],"type":"Point"}
}