{
  "type": "Feature",
  "properties": {
    "addr:full":"1695 Centre Rd Springvale VIC 3171",
    "addr:housenumber":"1695",
    "addr:postcode":"3171",
    "addr:street":"Centre Rd",
    "iso:country":"AU",
    "sg:address":"1695 Centre Rd",
    "sg:city":"Springvale",
    "sg:classifiers":[
        {
            "category":"Professional",
            "subcategory":"Printing & Photocopies",
            "type":"Services"
        }
    ],
    "sg:phone":"+61 3 9558 4938",
    "sg:postcode":"3171",
    "sg:province":"VIC",
    "sg:tags":[
        "embroidery"
    ],
    "wof:name":"Embroidery Australia",
    "wof:placetype":"venue"
},
  "geometry": {"coordinates":[145.152053833,-37.9324951172],"type":"Point"}
}