{
  "type": "Feature",
  "properties": {
    "addr:full":"6 / 21 Malcolm Rd Maddington WA 6109",
    "addr:housenumber":"/ 21",
    "addr:postcode":"6109",
    "addr:street":"Malcolm Rd",
    "iso:country":"AU",
    "sg:address":"6 / 21 Malcolm Rd",
    "sg:city":"Maddington",
    "sg:classifiers":[
        {
            "category":"Banks & Credit Unions",
            "subcategory":"Bureau De Change",
            "type":"Services"
        }
    ],
    "sg:phone":"+61 8 9493 2900",
    "sg:postcode":"6109",
    "sg:province":"WA",
    "sg:tags":[
        "equipment",
        "heat",
        "exchange"
    ],
    "wof:name":"Heat Exchangers WA",
    "wof:placetype":"venue"
},
  "geometry": {"coordinates":[115.984840393,-32.0416259766],"type":"Point"}
}