{
  "type": "Feature",
  "properties": {
    "iso:country":"AU",
    "sg:address":"19 Parkway Ave",
    "sg:city":"Walkley Heights",
    "sg:classifiers":[
        {
            "category":"Building & Trades",
            "subcategory":"Construction",
            "type":"Services"
        }
    ],
    "sg:phone":"+61 429 600 336",
    "sg:postcode":"5098",
    "sg:province":"SA",
    "sg:tags":[
        "polishing",
        "sanding",
        "floor"
    ],
    "wof:name":"Sandman Floorsanding & Polishing",
    "wof:placetype":"venue"
},
  "geometry": {"coordinates":[138.64479064899999,-34.8446502686],"type":"Point"}
}