{
  "type": "Feature",
  "properties": {
    "addr:full":"317 Pinjarra Rd Pinjarra Hills QLD 4069",
    "addr:housenumber":"317",
    "addr:postcode":"4069",
    "addr:street":"Pinjarra Rd",
    "iso:country":"AU",
    "sg:address":"317 Pinjarra Rd",
    "sg:city":"Pinjarra Hills",
    "sg:classifiers":[
        {
            "category":"Professional",
            "subcategory":"Art Services",
            "type":"Services"
        }
    ],
    "sg:phone":"+61 7 3202 9309",
    "sg:postcode":"4069",
    "sg:province":"QLD",
    "sg:tags":[
        "artist"
    ],
    "wof:name":"Scott Cathy",
    "wof:placetype":"venue"
},
  "geometry": {"coordinates":[152.89395141599999,-27.5469493866],"type":"Point"}
}