{
  "type": "Feature",
  "properties": {
    "iso:country":"AU",
    "sg:address":"11- 17 Anne St",
    "sg:city":"St Marys",
    "sg:classifiers":[
        {
            "category":"Professional",
            "subcategory":"Business Services",
            "type":"Services"
        }
    ],
    "sg:phone":"+61 2 9623 1965",
    "sg:postcode":"2760",
    "sg:province":"NSW",
    "sg:tags":[
        "drafting"
    ],
    "wof:name":"Prime Steel Detailers Pty Ltd",
    "wof:placetype":"venue"
},
  "geometry": {"coordinates":[150.77281189000001,-33.7509841919],"type":"Point"}
}