{
  "type": "Feature",
  "properties": {
    "iso:country":"AU",
    "sg:address":"332 Victoria St",
    "sg:city":"Darlinghurst",
    "sg:classifiers":[
        {
            "category":"Professional",
            "subcategory":"Employment Agencies",
            "type":"Services"
        }
    ],
    "sg:phone":"+61 2 9332 1911",
    "sg:postcode":"2010",
    "sg:province":"NSW",
    "sg:tags":[
        "entertainer",
        "agent"
    ],
    "wof:name":"Young Australia Workshop",
    "wof:placetype":"venue"
},
  "geometry": {"coordinates":[151.22177124000001,-33.8773078918],"type":"Point"}
}