{
  "type": "Feature",
  "properties": {
    "addr:full":"Glenquarie Town Centre Shop 66 Victoria Rd Macquarie Fields NSW 2564",
    "addr:housenumber":"shop 66",
    "addr:postcode":"2564",
    "addr:street":"Victoria Rd",
    "iso:country":"AU",
    "sg:address":"Glenquarie Town Centre Shop 66 Victoria Rd",
    "sg:city":"Macquarie Fields",
    "sg:classifiers":[
        {
            "category":"Fast Food",
            "type":"Food & Drink"
        }
    ],
    "sg:phone":"+61 2 9829 6679",
    "sg:postcode":"2564",
    "sg:province":"NSW",
    "sg:tags":[
        "away",
        "take"
    ],
    "wof:name":"Glenquarie Burger Express",
    "wof:placetype":"venue"
},
  "geometry": {"coordinates":[150.89471435600001,-33.9848747253],"type":"Point"}
}