{
  "type": "Feature",
  "properties": {
    "iso:country":"AU",
    "sg:address":"Suite 105/ 45 Kinghorne St",
    "sg:city":"Nowra",
    "sg:classifiers":[
        {
            "category":"Health Services",
            "subcategory":"Dentist",
            "type":"Services"
        }
    ],
    "sg:phone":"+61 2 4422 8957",
    "sg:postcode":"2541",
    "sg:province":"NSW",
    "sg:tags":[
        "dental",
        "prosthetist"
    ],
    "wof:name":"Barnier Denture Clinic",
    "wof:placetype":"venue"
},
  "geometry": {"coordinates":[150.60220336899999,-34.8778266907],"type":"Point"}
}