{
  "type": "Feature",
  "properties": {
    "iso:country":"AU",
    "sg:address":"PO Box 176",
    "sg:city":"Corrimal",
    "sg:classifiers":[
        {
            "category":"Building & Trades",
            "subcategory":"Landscaping Services",
            "type":"Services"
        }
    ],
    "sg:phone":"+61 413 598 576",
    "sg:postcode":"2518",
    "sg:province":"NSW",
    "sg:tags":[
        "designer",
        "landscape",
        "contractor"
    ],
    "wof:name":"Park View Landscaping Services",
    "wof:placetype":"venue"
},
  "geometry": {"coordinates":[150.896683,-34.374062],"type":"Point"}
}