{
  "type": "Feature",
  "properties": {
    "iso:country":"AU",
    "sg:address":"91 Darlington Drv",
    "sg:city":"Yatala",
    "sg:classifiers":[
        {
            "category":"Commercial Area",
            "type":"Public Place"
        }
    ],
    "sg:phone":"+61 7 3382 7526",
    "sg:postcode":"4207",
    "sg:province":"QLD",
    "sg:tags":[
        "heavy",
        "carrier"
    ],
    "wof:name":"Midway Freight",
    "wof:placetype":"venue"
},
  "geometry": {"coordinates":[153.2290802,-27.7523765564],"type":"Point"}
}