{
  "type": "Feature",
  "properties": {
    "iso:country":"AU",
    "sg:address":"260 Brunswick St",
    "sg:city":"Fitzroy",
    "sg:classifiers":[
        {
            "category":"Shopping",
            "subcategory":"Music",
            "type":"Retail Goods"
        }
    ],
    "sg:phone":"+61 3 9417 3576",
    "sg:postcode":"3065",
    "sg:province":"VIC",
    "sg:tags":[
        "store"
    ],
    "wof:name":"Sister Ray",
    "wof:placetype":"venue"
},
  "geometry": {"coordinates":[144.97840881400001,-37.7995758057],"type":"Point"}
}