{
  "type": "Feature",
  "properties": {
    "addr:full":"7 Dendy Pl Edens Landing QLD 4207",
    "addr:housenumber":"7",
    "addr:postcode":"4207",
    "addr:street":"Dendy Pl",
    "iso:country":"AU",
    "sg:address":"7 Dendy Pl",
    "sg:city":"Edens Landing",
    "sg:classifiers":[
        {
            "category":"Utilities",
            "subcategory":"Electric",
            "type":"Services"
        }
    ],
    "sg:phone":"+61 7 3807 0753",
    "sg:postcode":"4207",
    "sg:province":"QLD",
    "sg:tags":[
        "electrical",
        "contractor"
    ],
    "wof:name":"J And L Electricial",
    "wof:placetype":"venue"
},
  "geometry": {"coordinates":[153.17616272000001,-27.7052974701],"type":"Point"}
}