{
  "type": "Feature",
  "properties": {
    "addr:full":"392 High St Golden Square VIC 3555",
    "addr:housenumber":"392",
    "addr:postcode":"3555",
    "addr:street":"High St",
    "iso:country":"AU",
    "sg:address":"392 High St",
    "sg:city":"Golden Square",
    "sg:classifiers":[
        {
            "category":"Social Services",
            "subcategory":"Retirement Home",
            "type":"Services"
        }
    ],
    "sg:phone":"+61 3 5443 7999",
    "sg:postcode":"3555",
    "sg:province":"VIC",
    "sg:tags":[
        "village"
    ],
    "wof:name":"Alawara Retirement Village",
    "wof:placetype":"venue"
},
  "geometry": {"coordinates":[144.25448608400001,-36.7757835388],"type":"Point"}
}