{
  "type": "Feature",
  "properties": {
    "iso:country":"AU",
    "sg:address":"PO Box 338",
    "sg:city":"Ardrossan",
    "sg:classifiers":[
        {
            "category":"Professional",
            "subcategory":"Art Services",
            "type":"Services"
        }
    ],
    "sg:phone":"+61 407 970 460",
    "sg:postcode":"5571",
    "sg:province":"SA",
    "sg:tags":[
        "commercial",
        "artist"
    ],
    "wof:name":"Darren Lloyd Signs",
    "wof:placetype":"venue"
},
  "geometry": {"coordinates":[137.910430908,-34.422088623],"type":"Point"}
}