{
  "type": "Feature",
  "properties": {
    "addr:full":"52 Lachlan St Kempsey NSW 2440",
    "addr:housenumber":"52",
    "addr:postcode":"2440",
    "addr:street":"Lachlan St",
    "iso:country":"AU",
    "sg:address":"52 Lachlan St",
    "sg:city":"Kempsey",
    "sg:classifiers":[
        {
            "category":"Autos & Motor Vehicles",
            "subcategory":"Fuel & Gas Station",
            "type":"Retail Goods"
        }
    ],
    "sg:phone":"+61 2 6562 5673",
    "sg:postcode":"2440",
    "sg:province":"NSW",
    "wof:name":"Caltex Oil (Aust) Pty Ltd",
    "wof:placetype":"venue"
},
  "geometry": {"coordinates":[152.837219,-31.093693],"type":"Point"}
}