{
  "type": "Feature",
  "properties": {
    "addr:full":"Strathalbyn Rd Aldgate SA 5154",
    "addr:postcode":"5154",
    "addr:street":"Strathalbyn Rd",
    "iso:country":"AU",
    "sg:address":"Strathalbyn Rd",
    "sg:city":"Aldgate",
    "sg:classifiers":[
        {
            "category":"Retail",
            "subcategory":"Funeral Services",
            "type":"Services"
        }
    ],
    "sg:phone":"+61 8 8370 9721",
    "sg:postcode":"5154",
    "sg:province":"SA",
    "sg:tags":[
        "cemetery"
    ],
    "wof:name":"Stirling District Cemetery",
    "wof:placetype":"venue"
},
  "geometry": {"coordinates":[138.73716735799999,-35.015586853],"type":"Point"}
}