{
  "type": "Feature",
  "properties": {
    "iso:country":"AU",
    "sg:address":"1 Bramley Crt",
    "sg:city":"Corryong",
    "sg:classifiers":[
        {
            "category":"Social Services",
            "subcategory":"Child Care",
            "type":"Services"
        }
    ],
    "sg:phone":"+61 2 6076 2438",
    "sg:postcode":"3707",
    "sg:province":"VIC",
    "wof:name":"Peekaboo Child Care Centre",
    "wof:placetype":"venue"
},
  "geometry": {"coordinates":[147.89997863799999,-36.1952018738],"type":"Point"}
}