{
  "type": "Feature",
  "properties": {
    "addr:full":"24 Upton St Altona VIC 3018",
    "addr:housenumber":"24",
    "addr:postcode":"3018",
    "addr:street":"Upton St",
    "iso:country":"AU",
    "sg:address":"24 Upton St",
    "sg:city":"Altona",
    "sg:classifiers":[
        {
            "category":"Social Services",
            "subcategory":"Child Care",
            "type":"Services"
        }
    ],
    "sg:phone":"+61 3 9398 4634",
    "sg:postcode":"3018",
    "sg:province":"VIC",
    "wof:name":"Kids Campus",
    "wof:placetype":"venue"
},
  "geometry": {"coordinates":[144.82369995100001,-37.8673171997],"type":"Point"}
}