{
  "type": "Feature",
  "properties": {
    "addr:full":"232 Victoria Pde East Melbourne VIC 3002",
    "addr:housenumber":"232",
    "addr:postcode":"3002",
    "addr:street":"Victoria Pde",
    "iso:country":"AU",
    "sg:address":"232 Victoria Pde",
    "sg:city":"East Melbourne",
    "sg:classifiers":[
        {
            "category":"Communications",
            "type":"Services"
        }
    ],
    "sg:phone":"+61 3 9419 0265",
    "sg:postcode":"3002",
    "sg:province":"VIC",
    "sg:tags":[
        "translation"
    ],
    "wof:name":"Interpreting Services Bureau",
    "wof:placetype":"venue"
},
  "geometry": {"coordinates":[144.979858398,-37.8089332581],"type":"Point"}
}