{
  "type": "Feature",
  "properties": {
    "addr:full":"15 Sherreff St Stawell VIC 3380",
    "addr:housenumber":"15",
    "addr:postcode":"3380",
    "addr:street":"Sherreff St",
    "iso:country":"AU",
    "sg:address":"15 Sherreff St",
    "sg:city":"Stawell",
    "sg:classifiers":[
        {
            "category":"Professional",
            "subcategory":"Computer Services",
            "type":"Services"
        }
    ],
    "sg:phone":"+61 418 126 920",
    "sg:postcode":"3380",
    "sg:province":"VIC",
    "sg:tags":[
        "consultant",
        "system"
    ],
    "wof:name":"Dulkeith Computer Solutions",
    "wof:placetype":"venue"
},
  "geometry": {"coordinates":[142.77285766599999,-37.0611076355],"type":"Point"}
}