{
  "type": "Feature",
  "properties": {
    "iso:country":"AU",
    "sg:address":"62- 76 Cavanagh St",
    "sg:city":"Cheltenham",
    "sg:classifiers":[
        {
            "category":"Social Services",
            "subcategory":"Retirement Home",
            "type":"Services"
        }
    ],
    "sg:phone":"+61 3 9584 2500",
    "sg:postcode":"3192",
    "sg:province":"VIC",
    "sg:tags":[
        "accommodation",
        "special"
    ],
    "wof:name":"Kingston Green Lifestyle Serviced Apartments",
    "wof:placetype":"venue"
},
  "geometry": {"coordinates":[145.06622314399999,-37.9599113464],"type":"Point"}
}