{
  "type": "Feature",
  "properties": {
    "iso:country":"AU",
    "sg:address":"\"Kwobinyarn On Yass\" 138 Manton Rd",
    "sg:city":"Yass",
    "sg:classifiers":[
        {
            "category":"Retail",
            "subcategory":"Laundry & Dry Cleaning",
            "type":"Services"
        }
    ],
    "sg:phone":"+61 2 6227 1400",
    "sg:postcode":"2582",
    "sg:province":"NSW",
    "wof:name":"Animal Bedding & Rug Laundry",
    "wof:placetype":"venue"
},
  "geometry": {"coordinates":[149.009002686,-34.8691978455],"type":"Point"}
}