{
  "type": "Feature",
  "properties": {
    "addr:full":"211 Carp St Bega NSW 2550",
    "addr:housenumber":"211",
    "addr:postcode":"2550",
    "addr:street":"Carp St",
    "iso:country":"AU",
    "sg:address":"211 Carp St",
    "sg:city":"Bega",
    "sg:classifiers":[
        {
            "category":"Food & Beverages",
            "subcategory":"Specialty",
            "type":"Retail Goods"
        }
    ],
    "sg:phone":"+61 2 6492 1470",
    "sg:postcode":"2550",
    "sg:province":"NSW",
    "sg:tags":[
        "product",
        "health"
    ],
    "wof:name":"Bega Health Foods",
    "wof:placetype":"venue"
},
  "geometry": {"coordinates":[149.845214844,-36.6743507385],"type":"Point"}
}