{
  "type": "Feature",
  "properties": {
    "addr:full":"6/ 127 Cambridge St Collingwood VIC 3066",
    "addr:housenumber":"/ 127",
    "addr:postcode":"3066",
    "addr:street":"Cambridge St",
    "iso:country":"AU",
    "sg:address":"6/ 127 Cambridge St",
    "sg:city":"Collingwood",
    "sg:classifiers":[
        {
            "category":"Building & Trades",
            "subcategory":"Construction",
            "type":"Services"
        }
    ],
    "sg:phone":"+61 417 572 500",
    "sg:postcode":"3066",
    "sg:province":"VIC",
    "sg:tags":[
        "repair",
        "maintenance",
        "contractor"
    ],
    "wof:name":"The Renovator's Delight",
    "wof:placetype":"venue"
},
  "geometry": {"coordinates":[144.985595703,-37.8031578064],"type":"Point"}
}