{
  "type": "Feature",
  "properties": {
    "addr:full":"PO Box 211 Batemans Bay NSW 2536",
    "addr:postcode":"2536",
    "iso:country":"AU",
    "sg:address":"PO Box 211",
    "sg:city":"Batemans Bay",
    "sg:classifiers":[
        {
            "category":"Building & Trades",
            "subcategory":"Landscaping Services",
            "type":"Services"
        }
    ],
    "sg:phone":"+61 2 4478 1224",
    "sg:postcode":"2536",
    "sg:province":"NSW",
    "sg:tags":[
        "stump",
        "tree",
        "felling",
        "removal"
    ],
    "wof:name":"Tall Pauls Tree Service",
    "wof:placetype":"venue"
},
  "geometry": {"coordinates":[150.17732238799999,-35.7084007263],"type":"Point"}
}