{
  "type": "Feature",
  "properties": {
    "addr:full":"433 Hume Hwy Yagoona NSW 2199",
    "addr:housenumber":"433",
    "addr:postcode":"2199",
    "addr:street":"Hume Hwy",
    "iso:country":"AU",
    "sg:address":"433 Hume Hwy",
    "sg:city":"Yagoona",
    "sg:classifiers":[
        {
            "category":"Shopping",
            "subcategory":"Clothing, Apparel, & Fashions",
            "type":"Retail Goods"
        }
    ],
    "sg:phone":"+61 2 9793 1808",
    "sg:postcode":"2199",
    "sg:province":"NSW",
    "sg:tags":[
        "uniform"
    ],
    "wof:name":"Master Workwear",
    "wof:placetype":"venue"
},
  "geometry": {"coordinates":[151.02551299999999,-33.907749],"type":"Point"}
}