{
  "type": "Feature",
  "properties": {
    "addr:full":"285 Lord St Perth WA 6000",
    "addr:housenumber":"285",
    "addr:postcode":"6000",
    "addr:street":"Lord St",
    "iso:country":"AU",
    "sg:address":"285 Lord St",
    "sg:city":"Perth",
    "sg:classifiers":[
        {
            "category":"Professional",
            "subcategory":"Engineering",
            "type":"Services"
        }
    ],
    "sg:phone":"+61 8 9318 5888",
    "sg:postcode":"6000",
    "sg:province":"WA",
    "sg:tags":[
        "engineer",
        "structural"
    ],
    "wof:name":"Santillo Engineering Pty Ltd",
    "wof:placetype":"venue"
},
  "geometry": {"coordinates":[115.872802734,-31.9444446564],"type":"Point"}
}