{
  "type": "Feature",
  "properties": {
    "addr:full":"70 Railway Pde Midland WA 6056",
    "addr:housenumber":"70",
    "addr:postcode":"6056",
    "addr:street":"Railway Pde",
    "iso:country":"AU",
    "sg:address":"70 Railway Pde",
    "sg:city":"Midland",
    "sg:classifiers":[
        {
            "category":"Travel",
            "subcategory":"Hotels & Motels",
            "type":"Entertainment"
        }
    ],
    "sg:phone":"+61 8 9250 1824",
    "sg:postcode":"6056",
    "sg:province":"WA",
    "sg:tags":[
        "accommodation"
    ],
    "wof:name":"Commercial Tavern",
    "wof:placetype":"venue"
},
  "geometry": {"coordinates":[116.004760742,-31.89220047],"type":"Point"}
}