{
  "type": "Feature",
  "properties": {
    "iso:country":"AU",
    "sg:address":"1 Gardenia St",
    "sg:city":"Blackburn",
    "sg:classifiers":[
        {
            "category":"Organizations",
            "subcategory":"Non-profit Organization",
            "type":"Services"
        }
    ],
    "sg:phone":"+61 3 9877 9860",
    "sg:postcode":"3130",
    "sg:province":"VIC",
    "sg:tags":[
        "environmental",
        "organisation",
        "conservation"
    ],
    "wof:name":"Field Naturalists Club of Victoria",
    "wof:placetype":"venue"
},
  "geometry": {"coordinates":[145.15171814000001,-37.8206825256],"type":"Point"}
}