{
  "type": "Feature",
  "properties": {
    "addr:full":"39 Platt St Waratah NSW 2298",
    "addr:housenumber":"39",
    "addr:postcode":"2298",
    "addr:street":"Platt St",
    "iso:country":"AU",
    "sg:address":"39 Platt St",
    "sg:city":"Waratah",
    "sg:classifiers":[
        {
            "category":"Utilities",
            "subcategory":"Natural Gas",
            "type":"Services"
        }
    ],
    "sg:phone":"+61 2 4968 4901",
    "sg:postcode":"2298",
    "sg:province":"NSW",
    "sg:tags":[
        "consultant",
        "resource"
    ],
    "wof:name":"Ecotone Ecological",
    "wof:placetype":"venue"
},
  "geometry": {"coordinates":[151.72434997600001,-32.9004898071],"type":"Point"}
}