{
  "type": "Feature",
  "properties": {
    "addr:full":"874 Old Calder Hwy Keilor VIC 3036",
    "addr:housenumber":"874",
    "addr:postcode":"3036",
    "addr:street":"Old Calder Hwy",
    "iso:country":"AU",
    "sg:address":"874 Old Calder Hwy",
    "sg:city":"Keilor",
    "sg:classifiers":[
        {
            "category":"Autos & Motor Vehicles",
            "subcategory":"Boat Sales",
            "type":"Retail Goods"
        }
    ],
    "sg:phone":"+61 3 9390 7622",
    "sg:postcode":"3036",
    "sg:province":"VIC",
    "sg:tags":[
        "yacht"
    ],
    "wof:name":"Castoni Marine",
    "wof:placetype":"venue"
},
  "geometry": {"coordinates":[144.807693,-37.703125],"type":"Point"}
}