{
  "type": "Feature",
  "properties": {
    "addr:full":"1575 Burwood Hwy Tecoma VIC 3160",
    "addr:housenumber":"1575",
    "addr:postcode":"3160",
    "addr:street":"Burwood Hwy",
    "iso:country":"AU",
    "sg:address":"1575 Burwood Hwy",
    "sg:city":"Tecoma",
    "sg:classifiers":[
        {
            "category":"Health Services",
            "subcategory":"Doctor",
            "type":"Services"
        }
    ],
    "sg:phone":"+61 3 9757 8000",
    "sg:postcode":"3160",
    "sg:province":"VIC",
    "sg:tags":[
        "medical",
        "practitioner"
    ],
    "wof:name":"Barton Natalie Dr",
    "wof:placetype":"venue"
},
  "geometry": {"coordinates":[145.346923828,-37.9071121216],"type":"Point"}
}