{
  "type": "Feature",
  "properties": {
    "addr:full":"38 Niemur St Barham NSW 2732",
    "addr:housenumber":"38",
    "addr:postcode":"2732",
    "addr:street":"Niemur St",
    "iso:country":"AU",
    "sg:address":"38 Niemur St",
    "sg:city":"Barham",
    "sg:classifiers":[
        {
            "category":"Building & Trades",
            "subcategory":"Construction",
            "type":"Services"
        }
    ],
    "sg:phone":"+61 409 956 416",
    "sg:postcode":"2732",
    "sg:province":"NSW",
    "sg:tags":[
        "contractor"
    ],
    "wof:name":"Sambrooks Building",
    "wof:placetype":"venue"
},
  "geometry": {"coordinates":[144.130402,-35.626965],"type":"Point"}
}