{
  "type": "Feature",
  "properties": {
    "iso:country":"AU",
    "sg:address":"510 Elizabeth St",
    "sg:city":"Albury",
    "sg:classifiers":[
        {
            "category":"Personal",
            "subcategory":"Beauty Salon",
            "type":"Services"
        }
    ],
    "sg:phone":"+61 2 6021 6363",
    "sg:postcode":"2640",
    "sg:province":"NSW",
    "sg:tags":[
        "hairdresser"
    ],
    "wof:name":"Albury Hair Gallery",
    "wof:placetype":"venue"
},
  "geometry": {"coordinates":[146.91282653799999,-36.0795974731],"type":"Point"}
}