{
  "type": "Feature",
  "properties": {
    "addr:full":"87- 89 Rookwood Rd Yagoona NSW 2199",
    "addr:housenumber":"89",
    "addr:postcode":"2199",
    "addr:street":"Rookwood Rd",
    "iso:country":"AU",
    "sg:address":"87- 89 Rookwood Rd",
    "sg:city":"Yagoona",
    "sg:classifiers":[
        {
            "category":"Professional",
            "subcategory":"Detective & Security Services",
            "type":"Services"
        }
    ],
    "sg:phone":"+61 2 9790 7155",
    "sg:postcode":"2199",
    "sg:province":"NSW",
    "sg:tags":[
        "protective",
        "rustproofing"
    ],
    "wof:name":"Armaglaze",
    "wof:placetype":"venue"
},
  "geometry": {"coordinates":[151.03706399999999,-33.901623],"type":"Point"}
}