{
  "type": "Feature",
  "properties": {
    "iso:country":"AU",
    "sg:address":"Showroom 2, 9 Jennings Crt",
    "sg:city":"Rosebud",
    "sg:classifiers":[
        {
            "category":"Communications",
            "subcategory":"Film & Video Production",
            "type":"Services"
        }
    ],
    "sg:phone":"+61 3 5986 2822",
    "sg:postcode":"3939",
    "sg:province":"VIC",
    "sg:tags":[
        "television",
        "system",
        "circuit",
        "closed"
    ],
    "wof:name":"Security 24 7",
    "wof:placetype":"venue"
},
  "geometry": {"coordinates":[144.88340759299999,-38.3810997009],"type":"Point"}
}