{
  "type": "Feature",
  "properties": {
    "addr:full":"Unit 5/ 80 Webster Rd Stafford QLD 4053",
    "addr:housenumber":"80",
    "addr:postcode":"4053",
    "addr:street":"Webster Rd",
    "iso:country":"AU",
    "sg:address":"Unit 5/ 80 Webster Rd",
    "sg:city":"Stafford",
    "sg:classifiers":[
        {
            "category":"Retail",
            "subcategory":"Auto Repair",
            "type":"Services"
        }
    ],
    "sg:phone":"+61 7 3356 8499",
    "sg:postcode":"4053",
    "sg:province":"QLD",
    "sg:tags":[
        "transmission",
        "automotive",
        "car"
    ],
    "wof:name":"Motospecs",
    "wof:placetype":"venue"
},
  "geometry": {"coordinates":[153.01588439899999,-27.4149494171],"type":"Point"}
}