{
  "type": "Feature",
  "properties": {
    "iso:country":"AU",
    "sg:address":"North Rocks Rd",
    "sg:city":"North Rocks",
    "sg:classifiers":[
        {
            "category":"Real Estate",
            "subcategory":"Real Estate Agent",
            "type":"Services"
        }
    ],
    "sg:phone":"+61 2 9871 1700",
    "sg:postcode":"2151",
    "sg:province":"NSW",
    "wof:name":"Smith & Co First National Real Estate",
    "wof:placetype":"venue"
},
  "geometry": {"coordinates":[151.021316528,-33.77501297],"type":"Point"}
}