{
  "type": "Feature",
  "properties": {
    "iso:country":"AU",
    "sg:address":"6 Mackay Ave",
    "sg:city":"Glen Huntly",
    "sg:classifiers":[
        {
            "category":"Utilities",
            "subcategory":"Electric",
            "type":"Services"
        }
    ],
    "sg:phone":"+61 412 889 449",
    "sg:postcode":"3163",
    "sg:province":"VIC",
    "sg:tags":[
        "electrical",
        "contractor"
    ],
    "wof:name":"Comnet Electrical",
    "wof:placetype":"venue"
},
  "geometry": {"coordinates":[145.04200744600001,-37.8969650269],"type":"Point"}
}