{
  "type": "Feature",
  "properties": {
    "addr:full":"PO Box 44 Northam WA 6401",
    "addr:postcode":"6401",
    "iso:country":"AU",
    "sg:address":"PO Box 44",
    "sg:city":"Northam",
    "sg:classifiers":[
        {
            "category":"Farming",
            "subcategory":"Farm",
            "type":"Manufacturing & Wholesale Goods"
        }
    ],
    "sg:phone":"+61 8 9574 2251",
    "sg:postcode":"6401",
    "sg:province":"WA",
    "sg:tags":[
        "farmer"
    ],
    "wof:name":"Masters Jim R",
    "wof:placetype":"venue"
},
  "geometry": {"coordinates":[116.672973633,-31.6523208618],"type":"Point"}
}