{
  "type": "Feature",
  "properties": {
    "addr:full":"23 Station St Oakleigh VIC 3166",
    "addr:housenumber":"23",
    "addr:postcode":"3166",
    "addr:street":"Station St",
    "iso:country":"AU",
    "sg:address":"23 Station St",
    "sg:city":"Oakleigh",
    "sg:classifiers":[
        {
            "category":"Professional",
            "subcategory":"Art Services",
            "type":"Services"
        }
    ],
    "sg:phone":"+61 3 9530 9990",
    "sg:postcode":"3166",
    "sg:province":"VIC",
    "sg:tags":[
        "graphic",
        "designer"
    ],
    "wof:name":"Cameron Damon Media Pty Ltd",
    "wof:placetype":"venue"
},
  "geometry": {"coordinates":[145.08839416500001,-37.8995819092],"type":"Point"}
}