{
  "type": "Feature",
  "properties": {
    "addr:full":"Level 5 150 St Georges Tce Perth WA 6000",
    "addr:housenumber":"150",
    "addr:postcode":"6000",
    "addr:street":"St Georges Tce",
    "iso:country":"AU",
    "sg:address":"Level 5 150 St Georges Tce",
    "sg:city":"Perth",
    "sg:classifiers":[
        {
            "category":"Banks & Credit Unions",
            "subcategory":"Investment Brokerage",
            "type":"Services"
        }
    ],
    "sg:phone":"+61 8 9481 0888",
    "sg:postcode":"6000",
    "sg:province":"WA",
    "sg:tags":[
        "management",
        "property"
    ],
    "wof:name":"Portland Properties Ptd Ltd",
    "wof:placetype":"venue"
},
  "geometry": {"coordinates":[115.855712891,-31.954284668],"type":"Point"}
}