{
  "type": "Feature",
  "properties": {
    "addr:full":"31 William Ave Dandenong South VIC 3175",
    "addr:housenumber":"31",
    "addr:postcode":"3175",
    "addr:street":"William Ave",
    "iso:country":"AU",
    "sg:address":"31 William Ave",
    "sg:city":"Dandenong South",
    "sg:classifiers":[
        {
            "category":"Utilities",
            "subcategory":"Recycling",
            "type":"Services"
        }
    ],
    "sg:phone":"+61 3 9793 0110",
    "sg:postcode":"3175",
    "sg:province":"VIC",
    "wof:name":"AAD Recycled Paper",
    "wof:placetype":"venue"
},
  "geometry": {"coordinates":[145.21295165999999,-37.9962234497],"type":"Point"}
}