{
  "type": "Feature",
  "properties": {
    "addr:full":"Jones Rd Withcott QLD 4352",
    "addr:postcode":"4352",
    "addr:street":"Jones Rd",
    "iso:country":"AU",
    "sg:address":"Jones Rd",
    "sg:city":"Withcott",
    "sg:classifiers":[
        {
            "category":"Building & Trades",
            "subcategory":"Construction",
            "type":"Services"
        }
    ],
    "sg:phone":"+61 7 4630 3549",
    "sg:postcode":"4352",
    "sg:province":"QLD",
    "sg:tags":[
        "brick",
        "paving"
    ],
    "wof:name":"Dick Smith",
    "wof:placetype":"venue"
},
  "geometry": {"coordinates":[152.023956,-27.553064],"type":"Point"}
}