{
  "type": "Feature",
  "properties": {
    "iso:country":"AU",
    "sg:address":"65c Etwell St",
    "sg:city":"East Victoria Park",
    "sg:classifiers":[
        {
            "category":"Farming",
            "subcategory":"Fish & Marine Products",
            "type":"Manufacturing & Wholesale Goods"
        }
    ],
    "sg:phone":"+61 8 9470 1011",
    "sg:postcode":"6101",
    "sg:province":"WA",
    "sg:tags":[
        "organic"
    ],
    "wof:name":"Mimsbrook Farm Food Store",
    "wof:placetype":"venue"
},
  "geometry": {"coordinates":[115.89749145499999,-31.9952545166],"type":"Point"}
}