{
  "type": "Feature",
  "properties": {
    "iso:country":"AU",
    "sg:address":"8 Coghlans Rd",
    "sg:city":"Warrnambool",
    "sg:classifiers":[
        {
            "category":"Home & Garden",
            "subcategory":"Carpets & Floor Coverings",
            "type":"Retail Goods"
        }
    ],
    "sg:phone":"+61 418 518 693",
    "sg:postcode":"3280",
    "sg:province":"VIC",
    "sg:tags":[
        "layer",
        "planner"
    ],
    "wof:name":"Payne N W & G L",
    "wof:placetype":"venue"
},
  "geometry": {"coordinates":[142.46498107900001,-38.3522911072],"type":"Point"}
}