{
  "type": "Feature",
  "properties": {
    "addr:full":"PO Box 358 Doncaster VIC 8608",
    "addr:postcode":"8608",
    "iso:country":"AU",
    "sg:address":"PO Box 358",
    "sg:city":"Doncaster",
    "sg:classifiers":[
        {
            "category":"Utilities",
            "subcategory":"Natural Gas",
            "type":"Services"
        }
    ],
    "sg:phone":"+61 405 228 270",
    "sg:postcode":"8608",
    "sg:province":"VIC",
    "sg:tags":[
        "solid",
        "plasterer"
    ],
    "wof:name":"Impressive Rendering Pty Ltd",
    "wof:placetype":"venue"
},
  "geometry": {"coordinates":[145.13287399999999,-37.770561],"type":"Point"}
}