{
  "type": "Feature",
  "properties": {
    "addr:full":"12 Down St Longwood VIC 3665",
    "addr:housenumber":"12",
    "addr:postcode":"3665",
    "addr:street":"Down St",
    "iso:country":"AU",
    "sg:address":"12 Down St",
    "sg:city":"Longwood",
    "sg:classifiers":[
        {
            "category":"Government",
            "subcategory":"Post Office",
            "type":"Public Place"
        }
    ],
    "sg:phone":"+61 3 5798 5200",
    "sg:postcode":"3665",
    "sg:province":"VIC",
    "sg:tags":[
        "postal"
    ],
    "wof:name":"Australia Post",
    "wof:placetype":"venue"
},
  "geometry": {"coordinates":[145.42326355,-36.8028945923],"type":"Point"}
}