{
  "type": "Feature",
  "properties": {
    "addr:full":"Kellicar Road Macarthur Square Ambarvale NSW 2560",
    "addr:postcode":"2560",
    "addr:street":"Kellicar Road Macarthur Square",
    "iso:country":"AU",
    "sg:address":"Kellicar Road Macarthur Square",
    "sg:city":"Ambarvale",
    "sg:classifiers":[
        {
            "category":"Shopping",
            "subcategory":"Party Supplies",
            "type":"Retail Goods"
        }
    ],
    "sg:phone":"+61 2 4628 2677",
    "sg:postcode":"2560",
    "sg:province":"NSW",
    "sg:tags":[
        "children's"
    ],
    "wof:name":"AMF Macarthur Ten Pin Bowl",
    "wof:placetype":"venue"
},
  "geometry": {"coordinates":[150.79798889200001,-34.0741615295],"type":"Point"}
}