{
  "type": "Feature",
  "properties": {
    "addr:full":"25 Clarke St Port Noarlunga SA 5167",
    "addr:housenumber":"25",
    "addr:postcode":"5167",
    "addr:street":"Clarke St",
    "iso:country":"AU",
    "sg:address":"25 Clarke St",
    "sg:city":"Port Noarlunga",
    "sg:classifiers":[
        {
            "category":"Food & Beverages",
            "subcategory":"Bakery",
            "type":"Retail Goods"
        }
    ],
    "sg:phone":"+61 8 8186 1498",
    "sg:postcode":"5167",
    "sg:province":"SA",
    "sg:tags":[
        "baker"
    ],
    "wof:name":"Beck's Bakehouse",
    "wof:placetype":"venue"
},
  "geometry": {"coordinates":[138.471633911,-35.1494674683],"type":"Point"}
}