{
  "type": "Feature",
  "properties": {
    "iso:country":"AU",
    "sg:address":"7G 8 Chandler St",
    "sg:city":"Belconnen",
    "sg:classifiers":[
        {
            "category":"Health Services",
            "subcategory":"Doctor",
            "type":"Services"
        }
    ],
    "sg:phone":"+61 2 6253 3868",
    "sg:postcode":"2617",
    "sg:province":"ACT",
    "sg:tags":[
        "nurse",
        "nursing"
    ],
    "wof:name":"Care On Call",
    "wof:placetype":"venue"
},
  "geometry": {"coordinates":[149.061645508,-35.2385215759],"type":"Point"}
}