{
  "type": "Feature",
  "properties": {
    "iso:country":"AU",
    "sg:address":"10 Grand View Drv",
    "sg:city":"Seacombe Heights",
    "sg:classifiers":[
        {
            "category":"Retail",
            "subcategory":"Auto Rental",
            "type":"Services"
        }
    ],
    "sg:phone":"+61 8 8296 4006",
    "sg:postcode":"5047",
    "sg:province":"SA",
    "sg:tags":[
        "chauffeur",
        "car",
        "hire",
        "driven",
        "limousine"
    ],
    "wof:name":"Route 66 Tours",
    "wof:placetype":"venue"
},
  "geometry": {"coordinates":[138.543793,-35.033981],"type":"Point"}
}