{
  "type": "Feature",
  "properties": {
    "addr:full":"30- 34 May St St Peters NSW 2044",
    "addr:housenumber":"34",
    "addr:postcode":"2044",
    "addr:street":"May St",
    "iso:country":"AU",
    "sg:address":"30- 34 May St St",
    "sg:city":"Peters",
    "sg:classifiers":[
        {
            "category":"Wholesale",
            "subcategory":"Seafood",
            "type":"Manufacturing & Wholesale Goods"
        }
    ],
    "sg:phone":"+61 2 9314 7100",
    "sg:postcode":"2044",
    "sg:province":"NSW",
    "sg:tags":[
        "fish"
    ],
    "wof:name":"JOTO Fresh Fish",
    "wof:placetype":"venue"
},
  "geometry": {"coordinates":[151.179214,-33.909313],"type":"Point"}
}