{
  "type": "Feature",
  "properties": {
    "addr:full":"41 Johnston St Fitzroy VIC 3065",
    "addr:housenumber":"41",
    "addr:postcode":"3065",
    "addr:street":"Johnston St",
    "iso:country":"AU",
    "sg:address":"41 Johnston St",
    "sg:city":"Fitzroy",
    "sg:classifiers":[
        {
            "category":"Personal",
            "subcategory":"Beauty Salon",
            "type":"Services"
        }
    ],
    "sg:phone":"+61 3 9415 7848",
    "sg:postcode":"3065",
    "sg:province":"VIC",
    "wof:name":"Peak Body Therapy",
    "wof:placetype":"venue"
},
  "geometry": {"coordinates":[144.97642517099999,-37.797958374],"type":"Point"}
}