{
  "type": "Feature",
  "properties": {
    "addr:full":"Shop 6 35 Ferry St Kangaroo Point QLD 4169",
    "addr:housenumber":"shop;35",
    "addr:postcode":"4169",
    "addr:street":"Ferry St",
    "iso:country":"AU",
    "sg:address":"Shop 6 35 Ferry St",
    "sg:city":"Kangaroo Point",
    "sg:classifiers":[
        {
            "category":"Food & Beverages",
            "subcategory":"Liquor & Beverages",
            "type":"Retail Goods"
        }
    ],
    "sg:phone":"+61 7 3891 9499",
    "sg:postcode":"4169",
    "sg:province":"QLD",
    "sg:tags":[
        "store"
    ],
    "wof:name":"Drinx",
    "wof:placetype":"venue"
},
  "geometry": {"coordinates":[153.037017822,-27.4721469879],"type":"Point"}
}