{
  "type": "Feature",
  "properties": {
    "addr:full":"36 Richland Ave Coopers Plains QLD 4108",
    "addr:housenumber":"36",
    "addr:postcode":"4108",
    "addr:street":"Richland Ave",
    "iso:country":"AU",
    "sg:address":"36 Richland Ave",
    "sg:city":"Coopers Plains",
    "sg:classifiers":[
        {
            "category":"Wholesale",
            "subcategory":"Painting Supplies",
            "type":"Manufacturing & Wholesale Goods"
        }
    ],
    "sg:phone":"+61 7 3274 2593",
    "sg:postcode":"4108",
    "sg:province":"QLD",
    "sg:tags":[
        "product",
        "cleaning"
    ],
    "wof:name":"Eazygleam Products",
    "wof:placetype":"venue"
},
  "geometry": {"coordinates":[153.027542114,-27.5672836304],"type":"Point"}
}