{
  "type": "Feature",
  "properties": {
    "addr:full":"Shop 10/ 1 Archilles Drv Springwood QLD 4127",
    "addr:housenumber":"shop 10 / 1",
    "addr:postcode":"4127",
    "addr:street":"Archilles Drv",
    "iso:country":"AU",
    "sg:address":"Shop 10/ 1 Archilles Drv",
    "sg:city":"Springwood",
    "sg:classifiers":[
        {
            "category":"Shopping",
            "subcategory":"Pets & Pet Supplies",
            "type":"Retail Goods"
        }
    ],
    "sg:phone":"+61 7 3208 9586",
    "sg:postcode":"4127",
    "sg:province":"QLD",
    "sg:tags":[
        "dog"
    ],
    "wof:name":"Dog Essentials",
    "wof:placetype":"venue"
},
  "geometry": {"coordinates":[153.14065551799999,-27.6337509155],"type":"Point"}
}