{
  "type": "Feature",
  "properties": {
    "iso:country":"AU",
    "sg:address":"Shop 2003",
    "sg:city":", Westfield Shopping Centre Indooroopilly",
    "sg:classifiers":[
        {
            "category":"Retail",
            "subcategory":"Repair Shop",
            "type":"Services"
        }
    ],
    "sg:phone":"+61 7 3878 3944",
    "sg:postcode":"4068",
    "sg:province":"QLD",
    "sg:tags":[
        "handbag"
    ],
    "wof:name":"Oroton Pty Limited",
    "wof:placetype":"venue"
},
  "geometry": {"coordinates":[152.97575378400001,-27.4989395142],"type":"Point"}
}