{
  "type": "Feature",
  "properties": {
    "iso:country":"AU",
    "sg:address":"157 Remembrance Drv",
    "sg:city":"Tahmoor",
    "sg:classifiers":[
        {
            "category":"Food & Beverages",
            "subcategory":"Fruits & Vegetables",
            "type":"Retail Goods"
        }
    ],
    "sg:phone":"+61 2 4683 0044",
    "sg:postcode":"2573",
    "sg:province":"NSW",
    "sg:tags":[
        "wholesale"
    ],
    "wof:name":"Fresh For Life",
    "wof:placetype":"venue"
},
  "geometry": {"coordinates":[150.59182739299999,-34.2257804871],"type":"Point"}
}