{
  "type": "Feature",
  "properties": {
    "addr:full":"PO Box 5059 East Lismore NSW 2480",
    "addr:postcode":"2480",
    "iso:country":"AU",
    "sg:address":"PO Box 5059",
    "sg:city":"East Lismore",
    "sg:classifiers":[
        {
            "category":"Home & Garden",
            "subcategory":"Building Materials",
            "type":"Retail Goods"
        }
    ],
    "sg:phone":"+61 2 6624 2224",
    "sg:postcode":"2480",
    "sg:province":"NSW",
    "sg:tags":[
        "tile",
        "roofing"
    ],
    "wof:name":"Summerland Safe-T-Rail",
    "wof:placetype":"venue"
},
  "geometry": {"coordinates":[153.291381836,-28.8213405609],"type":"Point"}
}