{
  "type": "Feature",
  "properties": {
    "iso:country":"AU",
    "sg:address":"34- 38 Robert St",
    "sg:city":"Wickham",
    "sg:classifiers":[
        {
            "category":"Education",
            "subcategory":"Dance Studio",
            "type":"Public Place"
        }
    ],
    "sg:phone":"+61 2 4961 2425",
    "sg:postcode":"2293",
    "sg:province":"NSW",
    "sg:tags":[
        "training",
        "video",
        "film"
    ],
    "wof:name":"Digital Motion Studios",
    "wof:placetype":"venue"
},
  "geometry": {"coordinates":[151.75607299800001,-32.9171905518],"type":"Point"}
}