{
  "type": "Feature",
  "properties": {
    "addr:full":"6 Abbott Rd Seven Hills NSW 2147",
    "addr:housenumber":"6",
    "addr:postcode":"2147",
    "addr:street":"Abbott Rd",
    "iso:country":"AU",
    "sg:address":"6 Abbott Rd",
    "sg:city":"Seven Hills",
    "sg:classifiers":[
        {
            "category":"Retail",
            "subcategory":"Storage",
            "type":"Services"
        }
    ],
    "sg:phone":"+61 2 9624 6677",
    "sg:postcode":"2147",
    "sg:province":"NSW",
    "wof:name":"Rent A Space Self Storage",
    "wof:placetype":"venue"
},
  "geometry": {"coordinates":[150.94554138199999,-33.7679710388],"type":"Point"}
}