{
  "type": "Feature",
  "properties": {
    "iso:country":"AU",
    "sg:address":"6 Adina Crt",
    "sg:city":"Tullamarine",
    "sg:classifiers":[
        {
            "category":"Manufacturing",
            "subcategory":"Metals",
            "type":"Manufacturing & Wholesale Goods"
        }
    ],
    "sg:phone":"+61 3 9336 9300",
    "sg:postcode":"3043",
    "sg:province":"VIC",
    "sg:tags":[
        "steel",
        "fabricator",
        "mfrs"
    ],
    "wof:name":"Applied Manufacturing Pty Ltd",
    "wof:placetype":"venue"
},
  "geometry": {"coordinates":[144.87600707999999,-37.7110137939],"type":"Point"}
}