{
  "type": "Feature",
  "properties": {
    "addr:full":"Shop 3/ 71 Regent St New Lambton NSW 2305",
    "addr:housenumber":"shop 3 / 71",
    "addr:postcode":"2305",
    "addr:street":"Regent St",
    "iso:country":"AU",
    "sg:address":"Shop 3/ 71 Regent St",
    "sg:city":"New Lambton",
    "sg:classifiers":[
        {
            "category":"Real Estate",
            "subcategory":"Real Estate Services",
            "type":"Services"
        }
    ],
    "sg:phone":"+61 2 4957 6166",
    "sg:postcode":"2305",
    "sg:province":"NSW",
    "sg:tags":[
        "listing"
    ],
    "wof:name":"Robert Crawford Real Estate",
    "wof:placetype":"venue"
},
  "geometry": {"coordinates":[151.71331799999999,-32.924191],"type":"Point"}
}