{
  "type": "Feature",
  "properties": {
    "iso:country":"AU",
    "sg:address":"Shop 7, 14 Clyde St",
    "sg:city":"Kempsey",
    "sg:classifiers":[
        {
            "category":"Health Services",
            "subcategory":"Doctor",
            "type":"Services"
        }
    ],
    "sg:phone":"+61 2 6562 2688",
    "sg:postcode":"2440",
    "sg:province":"NSW",
    "sg:tags":[
        "medical",
        "practitioner"
    ],
    "wof:name":"East West Plaza Health Centre",
    "wof:placetype":"venue"
},
  "geometry": {"coordinates":[152.840485,-31.079716],"type":"Point"}
}