{
  "type": "Feature",
  "properties": {
    "iso:country":"AU",
    "sg:address":"Unit 1/ 543 Slater Pde",
    "sg:city":"Keilor East",
    "sg:classifiers":[
        {
            "category":"Professional",
            "type":"Services"
        }
    ],
    "sg:phone":"+61 13 16 10",
    "sg:postcode":"3033",
    "sg:province":"VIC",
    "sg:tags":[
        "courier"
    ],
    "wof:name":"Direct Couriers",
    "wof:placetype":"venue"
},
  "geometry": {"coordinates":[144.86222799999999,-37.729233],"type":"Point"}
}