{
  "type": "Feature",
  "properties": {
    "addr:full":"Unit 9/39- 41 Marigold St Revesby NSW 2212",
    "addr:housenumber":"41",
    "addr:postcode":"2212",
    "addr:street":"Marigold St",
    "iso:country":"AU",
    "sg:address":"Unit 9/39- 41 Marigold St",
    "sg:city":"Revesby",
    "sg:classifiers":[
        {
            "category":"Professional",
            "subcategory":"Engineering",
            "type":"Services"
        }
    ],
    "sg:phone":"+61 2 9773 8098",
    "sg:postcode":"2212",
    "sg:province":"NSW",
    "sg:tags":[
        "engineer"
    ],
    "wof:name":"Bortac Engineering Pty Ltd",
    "wof:placetype":"venue"
},
  "geometry": {"coordinates":[150.99951200000001,-33.937881],"type":"Point"}
}