{
  "type": "Feature",
  "properties": {
    "iso:country":"AU",
    "sg:address":"York Drv",
    "sg:city":"Flagstaff Hill",
    "sg:classifiers":[
        {
            "category":"Education",
            "subcategory":"Kindergarten",
            "type":"Public Place"
        }
    ],
    "sg:phone":"+61 8 8270 5135",
    "sg:postcode":"5159",
    "sg:province":"SA",
    "sg:tags":[
        "pre-schools"
    ],
    "wof:name":"Flagstaff Oval Kindergarten",
    "wof:placetype":"venue"
},
  "geometry": {"coordinates":[138.592285156,-35.051574707],"type":"Point"}
}