{
  "type": "Feature",
  "properties": {
    "addr:full":"132 Currans Rd Cooranbong NSW 2265",
    "addr:housenumber":"132",
    "addr:postcode":"2265",
    "addr:street":"Currans Rd",
    "iso:country":"AU",
    "sg:address":"132 Currans Rd",
    "sg:city":"Cooranbong",
    "sg:classifiers":[
        {
            "category":"Personal",
            "subcategory":"Massage",
            "type":"Services"
        }
    ],
    "sg:phone":"+61 2 4977 1082",
    "sg:postcode":"2265",
    "sg:province":"NSW",
    "sg:tags":[
        "therapy"
    ],
    "wof:name":"Alan Butt",
    "wof:placetype":"venue"
},
  "geometry": {"coordinates":[151.473206,-33.078751],"type":"Point"}
}