{
  "type": "Feature",
  "properties": {
    "addr:full":"38 Growse St Yarram VIC 3971",
    "addr:housenumber":"38",
    "addr:postcode":"3971",
    "addr:street":"Growse St",
    "iso:country":"AU",
    "sg:address":"38 Growse St",
    "sg:city":"Yarram",
    "sg:classifiers":[
        {
            "category":"Taxi",
            "type":"Transportation"
        }
    ],
    "sg:phone":"+61 3 5182 5986",
    "sg:postcode":"3971",
    "sg:province":"VIC",
    "sg:tags":[
        "cab"
    ],
    "wof:name":"Yarram Taxi Company",
    "wof:placetype":"venue"
},
  "geometry": {"coordinates":[146.6822052,-38.5689620972],"type":"Point"}
}