{
  "type": "Feature",
  "properties": {
    "addr:full":"10 Beaverdale Ave Windsor Gardens SA 5087",
    "addr:housenumber":"10",
    "addr:postcode":"5087",
    "addr:street":"Beaverdale Ave",
    "iso:country":"AU",
    "sg:address":"10 Beaverdale Ave",
    "sg:city":"Windsor Gardens",
    "sg:classifiers":[
        {
            "category":"Building & Trades",
            "subcategory":"Landscaping Services",
            "type":"Services"
        }
    ],
    "sg:phone":"+61 8 8367 8832",
    "sg:postcode":"5087",
    "sg:province":"SA",
    "sg:tags":[
        "stump",
        "tree",
        "felling",
        "removal"
    ],
    "wof:name":"Tree Monkey Services",
    "wof:placetype":"venue"
},
  "geometry": {"coordinates":[138.66308593799999,-34.8635673523],"type":"Point"}
}