{
  "type": "Feature",
  "properties": {
    "addr:full":"U1/ 74 Webster Rd Stafford QLD 4053",
    "addr:housenumber":"74",
    "addr:postcode":"4053",
    "addr:street":"U1 /;Webster Rd",
    "iso:country":"AU",
    "sg:address":"U1/ 74 Webster Rd",
    "sg:city":"Stafford",
    "sg:classifiers":[
        {
            "category":"Retail",
            "subcategory":"Auto Repair",
            "type":"Services"
        }
    ],
    "sg:phone":"+61 7 3856 2378",
    "sg:postcode":"4053",
    "sg:province":"QLD",
    "sg:tags":[
        "muffler",
        "exhaust",
        "system"
    ],
    "wof:name":"Gun Performance & Exhaust",
    "wof:placetype":"venue"
},
  "geometry": {"coordinates":[153.01583862300001,-27.4151973724],"type":"Point"}
}