{
  "type": "Feature",
  "properties": {
    "addr:full":"Unit 1/ 386 South St O'Connor WA 6163",
    "addr:housenumber":"/ 386",
    "addr:postcode":"6163",
    "addr:street":"South St",
    "iso:country":"AU",
    "sg:address":"Unit 1/ 386 South St",
    "sg:city":"O'Connor",
    "sg:classifiers":[
        {
            "category":"Health Services",
            "subcategory":"Health Practitioner",
            "type":"Services"
        }
    ],
    "sg:phone":"+61 8 9331 7531",
    "sg:postcode":"6163",
    "sg:province":"WA",
    "sg:tags":[
        "pathologist",
        "speech"
    ],
    "wof:name":"South Metro Speech Pathology",
    "wof:placetype":"venue"
},
  "geometry": {"coordinates":[115.79939299999999,-32.064816],"type":"Point"}
}