{
  "type": "Feature",
  "properties": {
    "iso:country":"AU",
    "sg:address":"18 Davey St",
    "sg:city":"Frankston",
    "sg:classifiers":[
        {
            "category":"Wholesale",
            "subcategory":"Medical Equipment & Supplies",
            "type":"Manufacturing & Wholesale Goods"
        }
    ],
    "sg:phone":"+61 3 9783 7677",
    "sg:postcode":"3199",
    "sg:province":"VIC",
    "sg:tags":[
        "aids",
        "hearing"
    ],
    "wof:name":"Frankston Hearing Aid Centre",
    "wof:placetype":"venue"
},
  "geometry": {"coordinates":[145.08804321299999,-37.9967842102],"type":"Point"}
}