{
  "type": "Feature",
  "properties": {
    "iso:country":"AU",
    "sg:address":"Monara Crs",
    "sg:city":"Red Hill",
    "sg:classifiers":[
        {
            "category":"Education",
            "subcategory":"School",
            "type":"Public Place"
        }
    ],
    "sg:phone":"+61 2 6260 9700",
    "sg:postcode":"2603",
    "sg:province":"ACT",
    "sg:tags":[
        "boy"
    ],
    "wof:name":"Canberra Grammar School",
    "wof:placetype":"venue"
},
  "geometry": {"coordinates":[149.12684631400001,-35.3397903442],"type":"Point"}
}