{
  "type": "Feature",
  "properties": {
    "addr:full":"Cnr Station St & Darebin Rd Fairfield VIC 3078",
    "addr:postcode":"3078",
    "addr:street":"Cnr Station St & Darebin Rd",
    "iso:country":"AU",
    "sg:address":"Cnr Station St & Darebin Rd",
    "sg:city":"Fairfield",
    "sg:classifiers":[
        {
            "category":"Food & Beverages",
            "subcategory":"Groceries & Convenience Stores",
            "type":"Retail Goods"
        }
    ],
    "sg:phone":"+61 3 9481 1719",
    "sg:postcode":"3078",
    "sg:province":"VIC",
    "wof:name":"7 Eleven",
    "wof:placetype":"venue"
},
  "geometry": {"coordinates":[145.019454956,-37.7709197998],"type":"Point"}
}