{
  "type": "Feature",
  "properties": {
    "iso:country":"AU",
    "sg:address":"70- 72 Church St",
    "sg:city":"Parramatta",
    "sg:classifiers":[
        {
            "category":"Shopping",
            "subcategory":"Computers & Home Electronics",
            "type":"Retail Goods"
        }
    ],
    "sg:phone":"+61 2 9633 5566",
    "sg:postcode":"2150",
    "sg:province":"NSW",
    "sg:tags":[
        "hardware",
        "equipment"
    ],
    "wof:name":"3C Importing Pty Ltd",
    "wof:placetype":"venue"
},
  "geometry": {"coordinates":[151.04385375999999,-33.862663269],"type":"Point"}
}