{
  "type": "Feature",
  "properties": {
    "addr:full":"2 Chaucer St Moorooka QLD 4105",
    "addr:housenumber":"2",
    "addr:postcode":"4105",
    "addr:street":"Chaucer St",
    "iso:country":"AU",
    "sg:address":"2 Chaucer St",
    "sg:city":"Moorooka",
    "sg:classifiers":[
        {
            "category":"Personal",
            "subcategory":"Barber",
            "type":"Services"
        }
    ],
    "sg:phone":"+61 7 3892 1949",
    "sg:postcode":"4105",
    "sg:province":"QLD",
    "wof:name":"Tung Chanh Hair Stylists",
    "wof:placetype":"venue"
},
  "geometry": {"coordinates":[153.01490783700001,-27.5351009369],"type":"Point"}
}