{
  "type": "Feature",
  "properties": {
    "addr:full":"14 Livingstone Rd Rockingham WA 6168",
    "addr:housenumber":"14",
    "addr:postcode":"6168",
    "addr:street":"Livingstone Rd",
    "iso:country":"AU",
    "sg:address":"14 Livingstone Rd",
    "sg:city":"Rockingham",
    "sg:classifiers":[
        {
            "category":"Professional",
            "subcategory":"Detective & Security Services",
            "type":"Services"
        }
    ],
    "sg:phone":"+61 8 9592 3722",
    "sg:postcode":"6168",
    "sg:province":"WA",
    "sg:tags":[
        "equipment",
        "window",
        "doors"
    ],
    "wof:name":"Quality Wardrobes",
    "wof:placetype":"venue"
},
  "geometry": {"coordinates":[115.741241,-32.286587],"type":"Point"}
}