{
  "type": "Feature",
  "properties": {
    "addr:full":"Lvl 11, Stockland House 175 Castlereagh St Sydney NSW 2000",
    "addr:housenumber":"11;175",
    "addr:postcode":"2000",
    "addr:street":"Castlereagh St",
    "iso:country":"AU",
    "sg:address":"Lvl 11, Stockland House 175 Castlereagh St",
    "sg:city":"Sydney",
    "sg:classifiers":[
        {
            "category":"Professional",
            "subcategory":"Accounting & Tax Preparation",
            "type":"Services"
        }
    ],
    "sg:phone":"+61 2 9261 8288",
    "sg:postcode":"2000",
    "sg:province":"NSW",
    "sg:tags":[
        "consultant",
        "taxation"
    ],
    "wof:name":"Copp Diment & Co",
    "wof:placetype":"venue"
},
  "geometry": {"coordinates":[151.20909118599999,-33.8726615906],"type":"Point"}
}