{
  "type": "Feature",
  "properties": {
    "iso:country":"AU",
    "sg:address":"75 Anderson Ave",
    "sg:city":"Panania",
    "sg:classifiers":[
        {
            "category":"Health Services",
            "subcategory":"Doctor",
            "type":"Services"
        }
    ],
    "sg:phone":"+61 2 9792 5555",
    "sg:postcode":"2213",
    "sg:province":"NSW",
    "sg:tags":[
        "medical",
        "practitioner"
    ],
    "wof:name":"Panania Family Clinic",
    "wof:placetype":"venue"
},
  "geometry": {"coordinates":[150.998611,-33.953815],"type":"Point"}
}