{
  "type": "Feature",
  "properties": {
    "addr:full":"Shop 5/ 63 Shore St Cleveland QLD 4163",
    "addr:housenumber":"shop 5 / 63",
    "addr:postcode":"4163",
    "addr:street":"Shore St",
    "iso:country":"AU",
    "sg:address":"Shop 5/ 63 Shore St",
    "sg:city":"Cleveland",
    "sg:classifiers":[
        {
            "category":"Autos & Motor Vehicles",
            "subcategory":"Auto Supplies",
            "type":"Retail Goods"
        }
    ],
    "sg:phone":"+61 7 3286 5055",
    "sg:postcode":"4163",
    "sg:province":"QLD",
    "sg:tags":[
        "part",
        "cycles",
        "accessory"
    ],
    "wof:name":"Rustys Bayside Custom Cycles",
    "wof:placetype":"venue"
},
  "geometry": {"coordinates":[153.25868225100001,-27.5244369507],"type":"Point"}
}