{
  "type": "Feature",
  "properties": {
    "addr:full":"36 Central Ave Sunshine VIC 3020",
    "addr:housenumber":"36",
    "addr:postcode":"3020",
    "addr:street":"Central Ave",
    "iso:country":"AU",
    "sg:address":"36 Central Ave",
    "sg:city":"Sunshine",
    "sg:classifiers":[
        {
            "category":"Retail",
            "subcategory":"Laundry & Dry Cleaning",
            "type":"Services"
        }
    ],
    "sg:phone":"+61 3 9311 1923",
    "sg:postcode":"3020",
    "sg:province":"VIC",
    "sg:tags":[
        "cloth",
        "supply"
    ],
    "wof:name":"Western Industrial Wipers Pty. Ltd.",
    "wof:placetype":"venue"
},
  "geometry": {"coordinates":[144.835556,-37.797421],"type":"Point"}
}