{
  "type": "Feature",
  "properties": {
    "addr:full":"101 Noble St Noble Park VIC 3174",
    "addr:housenumber":"101",
    "addr:postcode":"3174",
    "addr:street":"Noble St",
    "iso:country":"AU",
    "sg:address":"101 Noble St",
    "sg:city":"Noble Park",
    "sg:classifiers":[
        {
            "category":"Social Services",
            "subcategory":"Child Care",
            "type":"Services"
        }
    ],
    "sg:phone":"+61 3 9546 8812",
    "sg:postcode":"3174",
    "sg:province":"VIC",
    "sg:tags":[
        "support",
        "health"
    ],
    "wof:name":"Maternal & Child Health Centres",
    "wof:placetype":"venue"
},
  "geometry": {"coordinates":[145.16212463400001,-37.9670906067],"type":"Point"}
}