{
  "type": "Feature",
  "properties": {
    "addr:full":"Ste2/ 120 Prince Albert St Mosman NSW 2088",
    "addr:housenumber":"120",
    "addr:postcode":"2088",
    "addr:street":"Prince Albert St",
    "iso:country":"AU",
    "sg:address":"Ste2/ 120 Prince Albert St",
    "sg:city":"Mosman",
    "sg:classifiers":[
        {
            "category":"Retail",
            "subcategory":"Self-service Laundry",
            "type":"Services"
        }
    ],
    "sg:phone":"+61 2 9960 3831",
    "sg:postcode":"2088",
    "sg:province":"NSW",
    "wof:name":"Mosman Junction Laundrette",
    "wof:placetype":"venue"
},
  "geometry": {"coordinates":[151.243972778,-33.8318595886],"type":"Point"}
}