{
  "type": "Feature",
  "properties": {
    "addr:full":"533 Ross River Rd Cranbrook QLD 4814",
    "addr:housenumber":"533",
    "addr:postcode":"4814",
    "addr:street":"Ross River Rd",
    "iso:country":"AU",
    "sg:address":"533 Ross River Rd",
    "sg:city":"Cranbrook",
    "sg:classifiers":[
        {
            "category":"Health Services",
            "subcategory":"Medical Lab",
            "type":"Services"
        }
    ],
    "sg:phone":"+61 7 4723 9102",
    "sg:postcode":"4814",
    "sg:province":"QLD",
    "sg:tags":[
        "laboratory",
        "pathology"
    ],
    "wof:name":"Sullivan Nicolaides Pathology",
    "wof:placetype":"venue"
},
  "geometry": {"coordinates":[146.74659700000001,-19.311075],"type":"Point"}
}