{
  "type": "Feature",
  "properties": {
    "addr:full":"789 Sandgate Rd Clayfield QLD 4011",
    "addr:housenumber":"789",
    "addr:postcode":"4011",
    "addr:street":"Sandgate Rd",
    "iso:country":"AU",
    "sg:address":"789 Sandgate Rd",
    "sg:city":"Clayfield",
    "sg:classifiers":[
        {
            "category":"Health Services",
            "subcategory":"Health Practitioner",
            "type":"Services"
        }
    ],
    "sg:phone":"+61 7 3862 4544",
    "sg:postcode":"4011",
    "sg:province":"QLD",
    "sg:tags":[
        "physiotherapist"
    ],
    "wof:name":"Miller John",
    "wof:placetype":"venue"
},
  "geometry": {"coordinates":[153.05822800000001,-27.416729],"type":"Point"}
}