{
  "type": "Feature",
  "properties": {
    "addr:full":"13 Nairn St Fremantle WA 6160",
    "addr:housenumber":"13",
    "addr:postcode":"6160",
    "addr:street":"Nairn St",
    "iso:country":"AU",
    "sg:address":"13 Nairn St",
    "sg:city":"Fremantle",
    "sg:classifiers":[
        {
            "category":"Banks & Credit Unions",
            "subcategory":"Financial Services",
            "type":"Services"
        }
    ],
    "sg:phone":"+61 8 9430 5345",
    "sg:postcode":"6160",
    "sg:province":"WA",
    "sg:tags":[
        "financier"
    ],
    "wof:name":"Venture Capital Network Pty Ltd",
    "wof:placetype":"venue"
},
  "geometry": {"coordinates":[115.746567,-32.056168],"type":"Point"}
}