{
  "type": "Feature",
  "properties": {
    "addr:full":"2 Kalaroo Rd Redhead NSW 2290",
    "addr:housenumber":"2",
    "addr:postcode":"2290",
    "addr:street":"Kalaroo Rd",
    "iso:country":"AU",
    "sg:address":"2 Kalaroo Rd",
    "sg:city":"Redhead",
    "sg:classifiers":[
        {
            "category":"Manufacturing",
            "subcategory":"Metals",
            "type":"Manufacturing & Wholesale Goods"
        }
    ],
    "sg:phone":"+61 2 4944 8700",
    "sg:postcode":"2290",
    "sg:province":"NSW",
    "sg:tags":[
        "sheet",
        "worker"
    ],
    "wof:name":"Bryjo Design Engineering Manufacturing",
    "wof:placetype":"venue"
},
  "geometry": {"coordinates":[151.70599365199999,-33.0125961304],"type":"Point"}
}