{
  "type": "Feature",
  "properties": {
    "addr:full":"Lot 104 Sugarloaf Rd Chandlers Hill SA 5159",
    "addr:postcode":"5159",
    "addr:street":"Sugarloaf Rd",
    "iso:country":"AU",
    "sg:address":"Lot 104 Sugarloaf Rd",
    "sg:city":"Chandlers Hill",
    "sg:classifiers":[
        {
            "category":"Utilities",
            "subcategory":"Electric",
            "type":"Services"
        }
    ],
    "sg:phone":"+61 411 436 731",
    "sg:postcode":"5159",
    "sg:province":"SA",
    "sg:tags":[
        "electrical",
        "contractor"
    ],
    "wof:name":"Husky Electrical Contractors",
    "wof:placetype":"venue"
},
  "geometry": {"coordinates":[138.616333008,-35.0862503052],"type":"Point"}
}