{
  "type": "Feature",
  "properties": {
    "addr:full":"6 Marr St Edmonton QLD 4869",
    "addr:housenumber":"6",
    "addr:postcode":"4869",
    "addr:street":"Marr St",
    "iso:country":"AU",
    "sg:address":"6 Marr St",
    "sg:city":"Edmonton",
    "sg:classifiers":[
        {
            "category":"Shopping",
            "subcategory":"Musical Instruments",
            "type":"Retail Goods"
        }
    ],
    "sg:phone":"+61 7 4055 4086",
    "sg:postcode":"4869",
    "sg:province":"QLD",
    "sg:tags":[
        "musician",
        "agent"
    ],
    "wof:name":"Firth Peter",
    "wof:placetype":"venue"
},
  "geometry": {"coordinates":[145.73748779300001,-17.0248527527],"type":"Point"}
}