{
  "type": "Feature",
  "properties": {
    "addr:full":"Building J Vowels Crs Bruce ACT 2617",
    "addr:postcode":"2617",
    "addr:street":"Vowels Crs",
    "iso:country":"AU",
    "sg:address":"Building J Vowels Crs",
    "sg:city":"Bruce",
    "sg:classifiers":[
        {
            "category":"Education",
            "subcategory":"Special Training",
            "type":"Public Place"
        }
    ],
    "sg:phone":"+61 2 6207 4444",
    "sg:postcode":"2617",
    "sg:province":"ACT",
    "sg:tags":[
        "development"
    ],
    "wof:name":"Cit Solutions",
    "wof:placetype":"venue"
},
  "geometry": {"coordinates":[149.09266662600001,-35.2457618713],"type":"Point"}
}