{
  "type": "Feature",
  "properties": {
    "iso:country":"AU",
    "sg:address":"66 Glen Park Rd",
    "sg:city":"Eltham North",
    "sg:classifiers":[
        {
            "category":"Manufacturing",
            "subcategory":"Pottery",
            "type":"Manufacturing & Wholesale Goods"
        }
    ],
    "sg:phone":"+61 3 9431 0401",
    "sg:postcode":"3095",
    "sg:province":"VIC",
    "wof:name":"Chris & Mary Lou Pittard",
    "wof:placetype":"venue"
},
  "geometry": {"coordinates":[145.14683532699999,-37.6985206604],"type":"Point"}
}