{
  "type": "Feature",
  "properties": {
    "addr:full":"1228 Stanley St East Coorparoo QLD 4151",
    "addr:housenumber":"1228",
    "addr:postcode":"4151",
    "addr:street":"Stanley St East",
    "iso:country":"AU",
    "sg:address":"1228 Stanley St East",
    "sg:city":"Coorparoo",
    "sg:classifiers":[
        {
            "category":"Personal",
            "subcategory":"Beauty Salon",
            "type":"Services"
        }
    ],
    "sg:phone":"+61 7 3395 4755",
    "sg:postcode":"4151",
    "sg:province":"QLD",
    "sg:tags":[
        "hairdresser"
    ],
    "wof:name":"Coorparoo Cutz",
    "wof:placetype":"venue"
},
  "geometry": {"coordinates":[153.05918884299999,-27.4847164154],"type":"Point"}
}