{
  "type": "Feature",
  "properties": {
    "iso:country":"AU",
    "sg:address":"PO Box 5522",
    "sg:city":"Manly",
    "sg:classifiers":[
        {
            "category":"Landmark",
            "subcategory":"Scenic View",
            "type":"Public Place"
        }
    ],
    "sg:phone":"+61 7 3348 4571",
    "sg:postcode":"4179",
    "sg:province":"QLD",
    "sg:tags":[
        "staircase",
        "handrail"
    ],
    "wof:name":"Staircare Brisbane",
    "wof:placetype":"venue"
},
  "geometry": {"coordinates":[153.185821533,-27.4542293549],"type":"Point"}
}