{
  "type": "Feature",
  "properties": {
    "addr:full":"43a Foot St Frankston VIC 3199",
    "addr:postcode":"3199",
    "addr:street":"Foot St",
    "iso:country":"AU",
    "sg:address":"43a Foot St",
    "sg:city":"Frankston",
    "sg:classifiers":[
        {
            "category":"Retail",
            "subcategory":"Laundry & Dry Cleaning",
            "type":"Services"
        }
    ],
    "sg:phone":"+61 3 9783 2730",
    "sg:postcode":"3199",
    "sg:province":"VIC",
    "wof:name":"Foot Street Laundrette The",
    "wof:placetype":"venue"
},
  "geometry": {"coordinates":[145.130767822,-38.1576461792],"type":"Point"}
}