{
  "type": "Feature",
  "properties": {
    "addr:full":"7 Raglan St Turramurra NSW 2074",
    "addr:housenumber":"7",
    "addr:postcode":"2074",
    "addr:street":"Raglan St",
    "iso:country":"AU",
    "sg:address":"7 Raglan St",
    "sg:city":"Turramurra",
    "sg:classifiers":[
        {
            "category":"Professional",
            "subcategory":"Management & Consulting",
            "type":"Services"
        }
    ],
    "sg:phone":"+61 2 9449 1480",
    "sg:postcode":"2074",
    "sg:province":"NSW",
    "sg:tags":[
        "consultant"
    ],
    "wof:name":"Bryan J P Management Pty Limited",
    "wof:placetype":"venue"
},
  "geometry": {"coordinates":[151.144805908,-33.7293663025],"type":"Point"}
}