{
  "type": "Feature",
  "properties": {
    "iso:country":"AU",
    "sg:address":"PO Box 5161",
    "sg:city":"Central Queensland MC",
    "sg:classifiers":[
        {
            "category":"Professional",
            "subcategory":"Accounting & Tax Preparation",
            "type":"Services"
        }
    ],
    "sg:phone":"+61 7 4928 1555",
    "sg:postcode":"4702",
    "sg:province":"QLD",
    "sg:tags":[
        "accountant",
        "auditor"
    ],
    "wof:name":"ABA White Accountants",
    "wof:placetype":"venue"
},
  "geometry": {"coordinates":[147.65101623499999,-23.455619812],"type":"Point"}
}