{
  "type": "Feature",
  "properties": {
    "addr:full":"Coghill St Kapunda SA 5373",
    "addr:postcode":"5373",
    "addr:street":"Coghill St",
    "iso:country":"AU",
    "sg:address":"Coghill St",
    "sg:city":"Kapunda",
    "sg:classifiers":[
        {
            "category":"Autos & Motor Vehicles",
            "subcategory":"Fuel & Gas Station",
            "type":"Retail Goods"
        }
    ],
    "sg:phone":"+61 8 8566 2865",
    "sg:postcode":"5373",
    "sg:province":"SA",
    "wof:name":"BP Australia Limited",
    "wof:placetype":"venue"
},
  "geometry": {"coordinates":[138.91325378400001,-34.3425674438],"type":"Point"}
}