{
  "type": "Feature",
  "properties": {
    "addr:full":"60 Valley Drv Mollymook NSW 2539",
    "addr:housenumber":"60",
    "addr:postcode":"2539",
    "addr:street":"Valley Drv",
    "iso:country":"AU",
    "sg:address":"60 Valley Drv",
    "sg:city":"Mollymook",
    "sg:classifiers":[
        {
            "category":"Building & Trades",
            "subcategory":"Construction",
            "type":"Services"
        }
    ],
    "sg:phone":"+61 2 4454 5480",
    "sg:postcode":"2539",
    "sg:province":"NSW",
    "sg:tags":[
        "joiner",
        "carpenter"
    ],
    "wof:name":"Darryll Francis",
    "wof:placetype":"venue"
},
  "geometry": {"coordinates":[150.47218322800001,-35.3243408203],"type":"Point"}
}