{
  "type": "Feature",
  "properties": {
    "addr:full":"19 Della Torre Rd Moe VIC 3825",
    "addr:postcode":"3825",
    "addr:street":"19 Della Torre Rd",
    "iso:country":"AU",
    "sg:address":"19 Della Torre Rd",
    "sg:city":"Moe",
    "sg:classifiers":[
        {
            "category":"Manufacturing",
            "subcategory":"Metals",
            "type":"Manufacturing & Wholesale Goods"
        }
    ],
    "sg:phone":"+61 3 5126 1747",
    "sg:postcode":"3825",
    "sg:province":"VIC",
    "sg:tags":[
        "sheet",
        "worker"
    ],
    "wof:name":"Insulmet Pty Ltd",
    "wof:placetype":"venue"
},
  "geometry": {"coordinates":[146.258636,-38.167667],"type":"Point"}
}