{
  "type": "Feature",
  "properties": {
    "iso:country":"AU",
    "sg:address":"6 Currawong Crs",
    "sg:city":"Peregian Beach",
    "sg:classifiers":[
        {
            "category":"Utilities",
            "subcategory":"Electric",
            "type":"Services"
        }
    ],
    "sg:phone":"+61 7 5448 1080",
    "sg:postcode":"4573",
    "sg:province":"QLD",
    "sg:tags":[
        "electrical",
        "contractor"
    ],
    "wof:name":"Grant Airey Electrics",
    "wof:placetype":"venue"
},
  "geometry": {"coordinates":[153.095215,-26.47817],"type":"Point"}
}