{
  "type": "Feature",
  "properties": {
    "iso:country":"AU",
    "sg:address":"11 Teemer St",
    "sg:city":"Gladesville",
    "sg:classifiers":[
        {
            "category":"Building & Trades",
            "subcategory":"Landscaping Services",
            "type":"Services"
        }
    ],
    "sg:phone":"+61 2 9874 0919",
    "sg:postcode":"2111",
    "sg:province":"NSW",
    "sg:tags":[
        "designer",
        "landscape",
        "contractor"
    ],
    "wof:name":"Winter Landscape Services Pty Ltd",
    "wof:placetype":"venue"
},
  "geometry": {"coordinates":[151.11640930199999,-33.8295669556],"type":"Point"}
}