{
  "type": "Feature",
  "properties": {
    "iso:country":"AU",
    "sg:address":"Banksia St",
    "sg:city":"Tuart Hill",
    "sg:classifiers":[
        {
            "category":"Education",
            "subcategory":"School",
            "type":"Public Place"
        }
    ],
    "sg:phone":"+61 8 9349 1799",
    "sg:postcode":"6060",
    "sg:province":"WA",
    "sg:tags":[
        "state",
        "except",
        "nsw"
    ],
    "wof:name":"Tuart Hill Primary School",
    "wof:placetype":"venue"
},
  "geometry": {"coordinates":[115.839637756,-31.8972816467],"type":"Point"}
}