{
  "type": "Feature",
  "properties": {
    "iso:country":"AU",
    "sg:address":"4 Warwick St",
    "sg:city":"Stanmore",
    "sg:classifiers":[
        {
            "category":"Professional",
            "subcategory":"Management & Consulting",
            "type":"Services"
        }
    ],
    "sg:phone":"+61 411 193 120",
    "sg:postcode":"2048",
    "sg:province":"NSW",
    "sg:tags":[
        "consultant"
    ],
    "wof:name":"Sue Graham & Assoc.",
    "wof:placetype":"venue"
},
  "geometry": {"coordinates":[151.167419,-33.892754],"type":"Point"}
}