{
  "type": "Feature",
  "properties": {
    "iso:country":"AU",
    "sg:address":"12 Terrigal Rd",
    "sg:city":"Terrey Hills",
    "sg:classifiers":[
        {
            "category":"Home & Garden",
            "subcategory":"Building Materials",
            "type":"Retail Goods"
        }
    ],
    "sg:phone":"+61 2 9450 1175",
    "sg:postcode":"2084",
    "sg:province":"NSW",
    "sg:tags":[
        "lawn",
        "cutting",
        "maintenance"
    ],
    "wof:name":"Country Lawn & Garden Services",
    "wof:placetype":"venue"
},
  "geometry": {"coordinates":[151.22218322800001,-33.6841278076],"type":"Point"}
}