{
  "type": "Feature",
  "properties": {
    "iso:country":"AU",
    "sg:address":"323 Princes Hwy",
    "sg:city":"Rockdale",
    "sg:classifiers":[
        {
            "category":"Professional",
            "subcategory":"Accounting & Tax Preparation",
            "type":"Services"
        }
    ],
    "sg:phone":"+61 2 9597 6699",
    "sg:postcode":"2216",
    "sg:province":"NSW",
    "sg:tags":[
        "consultant",
        "taxation"
    ],
    "wof:name":"Bradfield Partners",
    "wof:placetype":"venue"
},
  "geometry": {"coordinates":[151.141357,-33.945366],"type":"Point"}
}