{
  "type": "Feature",
  "properties": {
    "addr:full":"Lot 103 Paperbark Pl Pinjarra WA 6208",
    "addr:postcode":"6208",
    "addr:street":"Paperbark Pl",
    "iso:country":"AU",
    "sg:address":"Lot 103 Paperbark Pl",
    "sg:city":"Pinjarra",
    "sg:classifiers":[
        {
            "category":"Building & Trades",
            "subcategory":"Construction",
            "type":"Services"
        }
    ],
    "sg:phone":"+61 413 733 874",
    "sg:postcode":"6208",
    "sg:province":"WA",
    "sg:tags":[
        "concrete",
        "contractor"
    ],
    "wof:name":"KCL Concrete",
    "wof:placetype":"venue"
},
  "geometry": {"coordinates":[115.838577,-32.620178],"type":"Point"}
}