{
  "type": "Feature",
  "properties": {
    "addr:full":"89 Edward St Langwarrin VIC 3910",
    "addr:housenumber":"89",
    "addr:postcode":"3910",
    "addr:street":"Edward St",
    "iso:country":"AU",
    "sg:address":"89 Edward St",
    "sg:city":"Langwarrin",
    "sg:classifiers":[
        {
            "category":"Building & Trades",
            "subcategory":"Construction",
            "type":"Services"
        }
    ],
    "sg:phone":"+61 3 9789 0666",
    "sg:postcode":"3910",
    "sg:province":"VIC",
    "sg:tags":[
        "concrete",
        "contractor"
    ],
    "wof:name":"P.& J. Guzzo",
    "wof:placetype":"venue"
},
  "geometry": {"coordinates":[145.181243897,-38.1536331177],"type":"Point"}
}