{
  "type": "Feature",
  "properties": {
    "iso:country":"AU",
    "sg:address":"44 Brian St",
    "sg:city":"Balgownie",
    "sg:classifiers":[
        {
            "category":"Professional",
            "subcategory":"Printing & Photocopies",
            "type":"Services"
        }
    ],
    "sg:phone":"+61 2 4284 6786",
    "sg:postcode":"2519",
    "sg:province":"NSW",
    "sg:tags":[
        "trophy"
    ],
    "wof:name":"Holt Trophies",
    "wof:placetype":"venue"
},
  "geometry": {"coordinates":[150.882446,-34.384052],"type":"Point"}
}