{
  "type": "Feature",
  "properties": {
    "addr:full":"13 Anzac Hwy Keswick SA 5035",
    "addr:housenumber":"13",
    "addr:postcode":"5035",
    "addr:street":"Anzac Hwy",
    "iso:country":"AU",
    "sg:address":"13 Anzac Hwy",
    "sg:city":"Keswick",
    "sg:classifiers":[
        {
            "category":"Home & Garden",
            "subcategory":"Carpets & Floor Coverings",
            "type":"Retail Goods"
        }
    ],
    "sg:phone":"+61 8 8293 3116",
    "sg:postcode":"5035",
    "sg:province":"SA",
    "sg:tags":[
        "mattress"
    ],
    "wof:name":"Rogers Rubber Products",
    "wof:placetype":"venue"
},
  "geometry": {"coordinates":[138.57850647000001,-34.9469795227],"type":"Point"}
}