{
  "type": "Feature",
  "properties": {
    "addr:full":"773 Warburton Hwy Seville East VIC 3139",
    "addr:housenumber":"773",
    "addr:postcode":"3139",
    "addr:street":"Warburton Hwy",
    "iso:country":"AU",
    "sg:address":"773 Warburton Hwy",
    "sg:city":"Seville East",
    "sg:classifiers":[
        {
            "category":"Farming",
            "subcategory":"Vineyard",
            "type":"Manufacturing & Wholesale Goods"
        }
    ],
    "sg:phone":"+61 3 5961 5877",
    "sg:postcode":"3139",
    "sg:province":"VIC",
    "sg:tags":[
        "winery"
    ],
    "wof:name":"Killara Park Estate",
    "wof:placetype":"venue"
},
  "geometry": {"coordinates":[145.49020385700001,-37.7757873535],"type":"Point"}
}