{
  "type": "Feature",
  "properties": {
    "iso:country":"AU",
    "sg:address":"Unit 2/ 13 Emplacement Crs",
    "sg:city":"Hamilton Hill",
    "sg:classifiers":[
        {
            "category":"Communications",
            "subcategory":"Television Station",
            "type":"Services"
        }
    ],
    "sg:phone":"+61 8 9335 1270",
    "sg:postcode":"6163",
    "sg:province":"WA",
    "sg:tags":[
        "mfrs",
        "tank",
        "installation",
        "septic"
    ],
    "wof:name":"Hi-Flow Systems Pty Ltd",
    "wof:placetype":"venue"
},
  "geometry": {"coordinates":[115.77831999999999,-32.080891],"type":"Point"}
}