{
  "type": "Feature",
  "properties": {
    "iso:country":"AU",
    "sg:address":"15 Little Buckingham St",
    "sg:city":"Surry Hills",
    "sg:classifiers":[
        {
            "category":"Government",
            "subcategory":"Post Office",
            "type":"Public Place"
        }
    ],
    "sg:phone":"+61 2 9319 1177",
    "sg:postcode":"2010",
    "sg:province":"NSW",
    "sg:tags":[
        "yoga"
    ],
    "wof:name":"Central Yoga School",
    "wof:placetype":"venue"
},
  "geometry": {"coordinates":[151.207519531,-33.8883476257],"type":"Point"}
}