{
  "type": "Feature",
  "properties": {
    "iso:country":"AU",
    "sg:address":"94 Clayton St",
    "sg:city":"Bellevue",
    "sg:classifiers":[
        {
            "category":"Health Services",
            "subcategory":"Health Practitioner",
            "type":"Services"
        }
    ],
    "sg:phone":"+61 8 9250 4203",
    "sg:postcode":"6056",
    "sg:province":"WA",
    "sg:tags":[
        "psychologist"
    ],
    "wof:name":"Heath Stephanie Dr",
    "wof:placetype":"venue"
},
  "geometry": {"coordinates":[116.01683807400001,-31.8979206085],"type":"Point"}
}