{
  "type": "Feature",
  "properties": {
    "addr:full":"70 Millewa Ave Malvern East VIC 3145",
    "addr:housenumber":"70",
    "addr:postcode":"3145",
    "addr:street":"Millewa Ave",
    "iso:country":"AU",
    "sg:address":"70 Millewa Ave",
    "sg:city":"Malvern East",
    "sg:classifiers":[
        {
            "category":"Professional",
            "subcategory":"Engineering",
            "type":"Services"
        }
    ],
    "sg:phone":"+61 3 9504 2086",
    "sg:postcode":"3145",
    "sg:province":"VIC",
    "sg:tags":[
        "engineer",
        "designing"
    ],
    "wof:name":"Meiller Consultants Pty Ltd",
    "wof:placetype":"venue"
},
  "geometry": {"coordinates":[145.07603454599999,-37.8802070618],"type":"Point"}
}