{
  "type": "Feature",
  "properties": {
    "addr:full":"1 Peterson Pl Wellington Point QLD 4160",
    "addr:housenumber":"1",
    "addr:postcode":"4160",
    "addr:street":"Peterson Pl",
    "iso:country":"AU",
    "sg:address":"1 Peterson Pl",
    "sg:city":"Wellington Point",
    "sg:classifiers":[
        {
            "category":"Health Services",
            "subcategory":"Doctor",
            "type":"Services"
        }
    ],
    "sg:phone":"+61 7 3822 4166",
    "sg:postcode":"4160",
    "sg:province":"QLD",
    "sg:tags":[
        "medical",
        "practitioner"
    ],
    "wof:name":"Houghton John",
    "wof:placetype":"venue"
},
  "geometry": {"coordinates":[153.23829650900001,-27.4874916077],"type":"Point"}
}