{
  "type": "Feature",
  "properties": {
    "iso:country":"AU",
    "sg:address":"107 A Pittwater Rd",
    "sg:city":"Hunters Hill",
    "sg:classifiers":[
        {
            "category":"Cafe",
            "type":"Food & Drink"
        }
    ],
    "sg:phone":"+61 2 9817 7000",
    "sg:postcode":"2110",
    "sg:province":"NSW",
    "wof:name":"Revive At 107",
    "wof:placetype":"venue"
},
  "geometry": {"coordinates":[151.13255310100001,-33.824508667],"type":"Point"}
}