{
  "type": "Feature",
  "properties": {
    "addr:full":"5 Murray Ave Red Cliffs VIC 3496",
    "addr:housenumber":"5",
    "addr:postcode":"3496",
    "addr:street":"Murray Ave",
    "iso:country":"AU",
    "sg:address":"5 Murray Ave",
    "sg:city":"Red Cliffs",
    "sg:classifiers":[
        {
            "category":"Farming",
            "subcategory":"Berry Farm",
            "type":"Manufacturing & Wholesale Goods"
        }
    ],
    "sg:phone":"+61 3 5024 3337",
    "sg:postcode":"3496",
    "sg:province":"VIC",
    "sg:tags":[
        "fruit",
        "grower"
    ],
    "wof:name":"Dichiera C & J",
    "wof:placetype":"venue"
},
  "geometry": {"coordinates":[142.18457031200001,-34.3123283386],"type":"Point"}
}