{
  "type": "Feature",
  "properties": {
    "addr:full":"68 Mooringe Ave North Plympton SA 5037",
    "addr:housenumber":"68",
    "addr:postcode":"5037",
    "addr:street":"Mooringe Ave North",
    "iso:country":"AU",
    "sg:address":"68 Mooringe Ave",
    "sg:city":"North Plympton",
    "sg:classifiers":[
        {
            "category":"Health Services",
            "subcategory":"Doctor",
            "type":"Services"
        }
    ],
    "sg:phone":"+61 8 8297 2399",
    "sg:postcode":"5037",
    "sg:province":"SA",
    "sg:tags":[
        "medical",
        "practitioner"
    ],
    "wof:name":"Jennings Ceciley J",
    "wof:placetype":"venue"
},
  "geometry": {"coordinates":[138.546417236,-34.9599990845],"type":"Point"}
}