{
  "type": "Feature",
  "properties": {
    "iso:country":"AU",
    "sg:address":"PO Box 85",
    "sg:city":"Sorell",
    "sg:classifiers":[
        {
            "category":"Professional",
            "subcategory":"Accounting & Tax Preparation",
            "type":"Services"
        }
    ],
    "sg:phone":"+61 3 6265 1317",
    "sg:postcode":"7172",
    "sg:province":"TAS",
    "sg:tags":[
        "bookkeeping"
    ],
    "wof:name":"Enterprise Accounts",
    "wof:placetype":"venue"
},
  "geometry": {"coordinates":[147.563598633,-42.7815818787],"type":"Point"}
}