{
  "type": "Feature",
  "properties": {
    "iso:country":"AU",
    "sg:address":"159 Church St",
    "sg:city":"Parramatta",
    "sg:classifiers":[
        {
            "category":"Shopping",
            "subcategory":"Computers & Home Electronics",
            "type":"Retail Goods"
        }
    ],
    "sg:phone":"+61 2 9687 8828",
    "sg:postcode":"2150",
    "sg:province":"NSW",
    "sg:tags":[
        "small",
        "equipment",
        "business"
    ],
    "wof:name":"Wireless 1 Parramatta",
    "wof:placetype":"venue"
},
  "geometry": {"coordinates":[151.11929321299999,-33.875289917],"type":"Point"}
}