{
  "type": "Feature",
  "properties": {
    "addr:full":"7a Robert St Atherton QLD 4883",
    "addr:housenumber":"7a",
    "addr:postcode":"4883",
    "addr:street":"Robert St",
    "iso:country":"AU",
    "sg:address":"7a Robert St",
    "sg:city":"Atherton",
    "sg:classifiers":[
        {
            "category":"Home & Garden",
            "subcategory":"Hardware",
            "type":"Retail Goods"
        }
    ],
    "sg:phone":"+61 7 4091 2200",
    "sg:postcode":"4883",
    "sg:province":"QLD",
    "sg:tags":[
        "generating",
        "set",
        "generator"
    ],
    "wof:name":"Tableland Parts Specialists",
    "wof:placetype":"venue"
},
  "geometry": {"coordinates":[145.47557067899999,-17.2686138153],"type":"Point"}
}