{
  "type": "Feature",
  "properties": {
    "addr:full":"Unit 5/ 20 Valente Cl Chermside QLD 4032",
    "addr:housenumber":"20",
    "addr:postcode":"qld 4032",
    "addr:street":"Valente Cl",
    "iso:country":"AU",
    "sg:address":"Unit 5/ 20 Valente Cl",
    "sg:city":"Chermside",
    "sg:classifiers":[
        {
            "category":"Utilities",
            "subcategory":"Electric",
            "type":"Services"
        }
    ],
    "sg:phone":"+61 7 3326 4444",
    "sg:postcode":"4032",
    "sg:province":"QLD",
    "sg:tags":[
        "electrical",
        "contractor"
    ],
    "sg:website":"http://www.nle.com.au",
    "wof:name":"NLE Group (AUST) Pty Ltd",
    "wof:placetype":"venue"
},
  "geometry": {"coordinates":[153.02555799999999,-27.39304],"type":"Point"}
}