{
  "type": "Feature",
  "properties": {
    "iso:country":"AU",
    "sg:address":"27 Twentieth Ave",
    "sg:city":"Brighton",
    "sg:classifiers":[
        {
            "category":"Building & Trades",
            "subcategory":"Construction",
            "type":"Services"
        }
    ],
    "sg:phone":"+61 7 3269 0621",
    "sg:postcode":"4017",
    "sg:province":"QLD",
    "sg:tags":[
        "earth",
        "excavating",
        "moving",
        "contractor"
    ],
    "wof:name":"Sta-Wil Plant Hire Constructions",
    "wof:placetype":"venue"
},
  "geometry": {"coordinates":[153.060546875,-27.2909030914],"type":"Point"}
}