{
  "type": "Feature",
  "properties": {
    "addr:full":"71 Lake St Cairns QLD 4870",
    "addr:housenumber":"71",
    "addr:postcode":"4870",
    "addr:street":"Lake St",
    "iso:country":"AU",
    "sg:address":"71 Lake St",
    "sg:city":"Cairns",
    "sg:classifiers":[
        {
            "category":"Travel",
            "subcategory":"Hotels & Motels",
            "type":"Entertainment"
        }
    ],
    "sg:phone":"+61 7 4041 2350",
    "sg:postcode":"4870",
    "sg:province":"QLD",
    "wof:name":"Inn Cairns Boutique Hotel/ Apartments",
    "wof:placetype":"venue"
},
  "geometry": {"coordinates":[145.77659606899999,-16.9232196808],"type":"Point"}
}