{
  "type": "Feature",
  "properties": {
    "addr:full":"87 Great Ocean Rd Anglesea VIC 3230",
    "addr:housenumber":"87",
    "addr:postcode":"3230",
    "addr:street":"Great Ocean Rd",
    "iso:country":"AU",
    "sg:address":"87 Great Ocean Rd",
    "sg:city":"Anglesea",
    "sg:classifiers":[
        {
            "category":"Shopping",
            "subcategory":"Clothing, Apparel, & Fashions",
            "type":"Retail Goods"
        }
    ],
    "sg:phone":"+61 3 5263 3001",
    "sg:postcode":"3230",
    "sg:province":"VIC",
    "sg:tags":[
        "lady",
        "wear"
    ],
    "wof:name":"Anglesea Beach Club",
    "wof:placetype":"venue"
},
  "geometry": {"coordinates":[144.18978899999999,-38.404709],"type":"Point"}
}