{
  "type": "Feature",
  "properties": {
    "addr:full":"555 Sunshine Ave Taylors Lakes VIC 3038",
    "addr:housenumber":"555",
    "addr:postcode":"3038",
    "addr:street":"Sunshine Ave",
    "iso:country":"AU",
    "sg:address":"555 Sunshine Ave",
    "sg:city":"Taylors Lakes",
    "sg:classifiers":[
        {
            "category":"Sports & Exercise",
            "subcategory":"Gym",
            "type":"Entertainment"
        }
    ],
    "sg:phone":"+61 3 9390 9099",
    "sg:postcode":"3038",
    "sg:province":"VIC",
    "sg:tags":[
        "health",
        "fitness"
    ],
    "wof:name":"Taylors Lakes Health & Fitness Centre",
    "wof:placetype":"venue"
},
  "geometry": {"coordinates":[144.801346,-37.703075],"type":"Point"}
}