{
  "type": "Feature",
  "properties": {
    "addr:full":"Lot 2839 Zimin Dve Katherine NT 0850",
    "addr:housenumber":"2839",
    "addr:postcode":"nt 0850",
    "addr:street":"Zimin Dve",
    "iso:country":"AU",
    "sg:address":"Lot 2839 Zimin Dve",
    "sg:city":"Katherine",
    "sg:classifiers":[
        {
            "category":"Retail",
            "subcategory":"Repair Shop",
            "type":"Services"
        }
    ],
    "sg:phone":"+61 8 8971 2133",
    "sg:postcode":"0850",
    "sg:province":"NT",
    "sg:tags":[
        "windscreen"
    ],
    "wof:name":"Novus Autoglass Repair & Replacement",
    "wof:placetype":"venue"
},
  "geometry": {"coordinates":[132.24676500000001,-14.453316],"type":"Point"}
}