{
  "type": "Feature",
  "properties": {
    "addr:full":"52 Murray Farm Rd Carlingford NSW 2118",
    "addr:housenumber":"52",
    "addr:postcode":"2118",
    "addr:street":"Murray Farm Rd",
    "iso:country":"AU",
    "sg:address":"52 Murray Farm Rd",
    "sg:city":"Carlingford",
    "sg:classifiers":[
        {
            "category":"Organizations",
            "subcategory":"Professional Association",
            "type":"Services"
        }
    ],
    "sg:phone":"+61 405 181 775",
    "sg:postcode":"2118",
    "sg:province":"NSW",
    "sg:tags":[
        "web",
        "internet"
    ],
    "wof:name":"Kramtek Computing",
    "wof:placetype":"venue"
},
  "geometry": {"coordinates":[151.041091919,-33.7638816833],"type":"Point"}
}