{
  "type": "Feature",
  "properties": {
    "addr:full":"43 Wimston Pde Abbotsford NSW 2046",
    "addr:housenumber":"43",
    "addr:postcode":"2046",
    "addr:street":"Wimston Pde",
    "iso:country":"AU",
    "sg:address":"43 Wimston Pde",
    "sg:city":"Abbotsford",
    "sg:classifiers":[
        {
            "category":"Utilities",
            "subcategory":"Electric",
            "type":"Services"
        }
    ],
    "sg:phone":"+61 2 9713 6162",
    "sg:postcode":"2046",
    "sg:province":"NSW",
    "sg:tags":[
        "electrical",
        "contractor"
    ],
    "wof:name":"Data & Electrical Services Pty Ltd",
    "wof:placetype":"venue"
},
  "geometry": {"coordinates":[151.12806699999999,-33.857132],"type":"Point"}
}