{
  "type": "Feature",
  "properties": {
    "addr:full":"118 Links Ave South Eagle Farm QLD 4009",
    "addr:housenumber":"118",
    "addr:postcode":"4009",
    "addr:street":"Links Ave South",
    "iso:country":"AU",
    "sg:address":"118 Links Ave South",
    "sg:city":"Eagle Farm",
    "sg:classifiers":[
        {
            "category":"Personal",
            "subcategory":"Skin Care",
            "type":"Services"
        }
    ],
    "sg:phone":"+61 7 3291 2244",
    "sg:postcode":"4009",
    "sg:province":"QLD",
    "sg:tags":[
        "hair",
        "product"
    ],
    "wof:name":"Sunday Australia Pty Ltd",
    "wof:placetype":"venue"
},
  "geometry": {"coordinates":[153.087524414,-27.4378204346],"type":"Point"}
}