{
  "type": "Feature",
  "properties": {
    "addr:full":"Lot 14 Owen Crt Narangba QLD 4504",
    "addr:postcode":"4504",
    "addr:street":"Owen Crt",
    "iso:country":"AU",
    "sg:address":"Lot 14 Owen Crt",
    "sg:city":"Narangba",
    "sg:classifiers":[
        {
            "category":"Building & Trades",
            "subcategory":"Construction",
            "type":"Services"
        }
    ],
    "sg:phone":"+61 7 3888 5575",
    "sg:postcode":"4504",
    "sg:province":"QLD",
    "sg:tags":[
        "plasterboard",
        "plasterer",
        "fixer"
    ],
    "wof:name":"Steve Heyward Plastering",
    "wof:placetype":"venue"
},
  "geometry": {"coordinates":[152.97621154800001,-27.201259613],"type":"Point"}
}