{
  "type": "Feature",
  "properties": {
    "addr:full":"5 Thomas St Mullewa WA 6630",
    "addr:housenumber":"5",
    "addr:postcode":"6630",
    "addr:street":"Thomas St",
    "iso:country":"AU",
    "sg:address":"5 Thomas St",
    "sg:city":"Mullewa",
    "sg:classifiers":[
        {
            "category":"Government",
            "subcategory":"Department Of Motor Vehicles",
            "type":"Public Place"
        }
    ],
    "sg:phone":"+61 8 9961 1007",
    "sg:postcode":"6630",
    "sg:province":"WA",
    "sg:tags":[
        "organisation",
        "local"
    ],
    "wof:name":"Mullewa Shire Of",
    "wof:placetype":"venue"
},
  "geometry": {"coordinates":[115.511016846,-28.5403614044],"type":"Point"}
}