{
  "type": "Feature",
  "properties": {
    "addr:full":"Tschampions Rd Macclesfield VIC 3782",
    "addr:postcode":"3782",
    "addr:street":"Tschampions Rd",
    "iso:country":"AU",
    "sg:address":"Tschampions Rd",
    "sg:city":"Macclesfield",
    "sg:classifiers":[
        {
            "category":"Train Station",
            "subcategory":"Rail",
            "type":"Transportation"
        }
    ],
    "sg:phone":"+61 3 5968 8963",
    "sg:postcode":"3782",
    "sg:province":"VIC",
    "sg:tags":[
        "goat",
        "farmer"
    ],
    "wof:name":"Melville G R",
    "wof:placetype":"venue"
},
  "geometry": {"coordinates":[145.47984299999999,-37.885506],"type":"Point"}
}