{
  "type": "Feature",
  "properties": {
    "iso:country":"AU",
    "sg:address":"2 Keft Ave",
    "sg:city":"Nowra",
    "sg:classifiers":[
        {
            "category":"Professional",
            "subcategory":"Accounting & Tax Preparation",
            "type":"Services"
        }
    ],
    "sg:phone":"+61 2 4421 8788",
    "sg:postcode":"2540",
    "sg:province":"NSW",
    "sg:tags":[
        "accountant",
        "auditor"
    ],
    "wof:name":"Solutions 4 Financial Services",
    "wof:placetype":"venue"
},
  "geometry": {"coordinates":[150.60032653799999,-34.8689498901],"type":"Point"}
}