{
  "type": "Feature",
  "properties": {
    "iso:country":"AU",
    "sg:address":"Channon St",
    "sg:city":"Gympie",
    "sg:classifiers":[
        {
            "category":"Travel",
            "subcategory":"Hotels & Motels",
            "type":"Entertainment"
        }
    ],
    "sg:phone":"+61 7 5482 2477",
    "sg:postcode":"4570",
    "sg:province":"QLD",
    "sg:tags":[
        "accommodation"
    ],
    "wof:name":"Northumberland Hotel-Motel",
    "wof:placetype":"venue"
},
  "geometry": {"coordinates":[152.65736389200001,-26.1891651154],"type":"Point"}
}