{
  "type": "Feature",
  "properties": {
    "addr:full":"Workshop 25, Level 1, Chifley Tower, (Hunter & Philip St) Sydney NSW 2000",
    "addr:housenumber":"25 level 1",
    "addr:postcode":"2000",
    "addr:street":"St",
    "iso:country":"AU",
    "sg:address":"Workshop 25, Level 1, Chifley Tower, (Hunter & Philip St)",
    "sg:city":"Sydney",
    "sg:classifiers":[
        {
            "category":"Building & Trades",
            "subcategory":"Locksmith",
            "type":"Services"
        }
    ],
    "sg:phone":"+61 2 9232 8839",
    "sg:postcode":"2000",
    "sg:province":"NSW",
    "sg:tags":[
        "lock"
    ],
    "wof:name":"CBD Master Locksmiths",
    "wof:placetype":"venue"
},
  "geometry": {"coordinates":[151.210006714,-33.8695793152],"type":"Point"}
}