{
  "type": "Feature",
  "properties": {
    "iso:country":"AU",
    "sg:address":"18 Canea Crs",
    "sg:city":"Allambie Heights",
    "sg:classifiers":[
        {
            "category":"Professional",
            "subcategory":"Accounting & Tax Preparation",
            "type":"Services"
        }
    ],
    "sg:phone":"+61 2 9451 5888",
    "sg:postcode":"2100",
    "sg:province":"NSW",
    "sg:tags":[
        "accountant",
        "auditor"
    ],
    "wof:name":"Peter Morris & Co. Pty Ltd",
    "wof:placetype":"venue"
},
  "geometry": {"coordinates":[151.251556397,-33.7655906677],"type":"Point"}
}