{
  "type": "Feature",
  "properties": {
    "addr:full":"Reddalls Rd Kembla Grange NSW 2526",
    "addr:postcode":"2526",
    "addr:street":"Reddalls Rd",
    "iso:country":"AU",
    "sg:address":"Reddalls Rd",
    "sg:city":"Kembla Grange",
    "sg:classifiers":[
        {
            "category":"Wholesale",
            "subcategory":"Construction Materials",
            "type":"Manufacturing & Wholesale Goods"
        }
    ],
    "sg:phone":"+61 2 4262 0700",
    "sg:postcode":"2526",
    "sg:province":"NSW",
    "sg:tags":[
        "protective",
        "coating"
    ],
    "wof:name":"APC Socotherm Pty Ltd",
    "wof:placetype":"venue"
},
  "geometry": {"coordinates":[150.796676636,-34.4650878906],"type":"Point"}
}