{
  "type": "Feature",
  "properties": {
    "addr:full":"2043 Sandgate Rd Virginia QLD 4014",
    "addr:housenumber":"2043",
    "addr:postcode":"4014",
    "addr:street":"Sandgate Rd",
    "iso:country":"AU",
    "sg:address":"2043 Sandgate Rd",
    "sg:city":"Virginia",
    "sg:classifiers":[
        {
            "category":"Home & Garden",
            "subcategory":"Furniture",
            "type":"Retail Goods"
        }
    ],
    "sg:phone":"+61 7 3265 2922",
    "sg:postcode":"4014",
    "sg:province":"QLD",
    "sg:tags":[
        "outdoor"
    ],
    "wof:name":"Saveways Furniture",
    "wof:placetype":"venue"
},
  "geometry": {"coordinates":[153.06239318900001,-27.3689823151],"type":"Point"}
}