{
  "type": "Feature",
  "properties": {
    "addr:full":"5 Notre Dame Crt Varsity Lakes QLD 4227",
    "addr:housenumber":"5",
    "addr:postcode":"4227",
    "addr:street":"Notre Dame Crt",
    "iso:country":"AU",
    "sg:address":"5 Notre Dame Crt",
    "sg:city":"Varsity Lakes",
    "sg:classifiers":[
        {
            "category":"Utilities",
            "subcategory":"Cable",
            "type":"Services"
        }
    ],
    "sg:phone":"+61 7 5576 0524",
    "sg:postcode":"4227",
    "sg:province":"QLD",
    "sg:tags":[
        "equipment",
        "meters"
    ],
    "wof:name":"Flowtech Water Meters",
    "wof:placetype":"venue"
},
  "geometry": {"coordinates":[153.42022705100001,-28.0826587677],"type":"Point"}
}