{
  "type": "Feature",
  "properties": {
    "addr:full":"612-614 Plenty Rd Preston VIC 3072",
    "addr:housenumber":"612-614",
    "addr:postcode":"3072",
    "addr:street":"Plenty Rd",
    "iso:country":"AU",
    "sg:address":"612-614 Plenty Rd",
    "sg:city":"Preston",
    "sg:classifiers":[
        {
            "category":"Autos & Motor Vehicles",
            "subcategory":"Boat Sales",
            "type":"Retail Goods"
        }
    ],
    "sg:phone":"+61 3 9478 1420",
    "sg:postcode":"3072",
    "sg:province":"VIC",
    "sg:tags":[
        "yacht"
    ],
    "wof:name":"Barry Lawrence Marine Pty Ltd",
    "wof:placetype":"venue"
},
  "geometry": {"coordinates":[145.004440308,-37.7413063049],"type":"Point"}
}