{
  "type": "Feature",
  "properties": {
    "iso:country":"AU",
    "sg:address":"62 Chadderton St",
    "sg:city":"Lansvale",
    "sg:classifiers":[
        {
            "category":"Wholesale",
            "subcategory":"Furniture",
            "type":"Manufacturing & Wholesale Goods"
        }
    ],
    "sg:phone":"+61 2 9726 6794",
    "sg:postcode":"2166",
    "sg:province":"NSW",
    "sg:tags":[
        "wholesaler",
        "mfrs"
    ],
    "wof:name":"Contempo Furniture Pty Ltd",
    "wof:placetype":"venue"
},
  "geometry": {"coordinates":[150.95625305199999,-33.8937149048],"type":"Point"}
}