{
  "type": "Feature",
  "properties": {
    "addr:full":"21 Jarrah St Minyama QLD 4575",
    "addr:housenumber":"21",
    "addr:postcode":"4575",
    "addr:street":"Jarrah St",
    "iso:country":"AU",
    "sg:address":"21 Jarrah St",
    "sg:city":"Minyama",
    "sg:classifiers":[
        {
            "category":"Health Services",
            "subcategory":"Dentist",
            "type":"Services"
        }
    ],
    "sg:phone":"+61 7 5478 2662",
    "sg:postcode":"4575",
    "sg:province":"QLD",
    "sg:tags":[
        "dental",
        "prosthetist"
    ],
    "wof:name":"Advance Oral",
    "wof:placetype":"venue"
},
  "geometry": {"coordinates":[153.122253,-26.697777],"type":"Point"}
}