{
  "type": "Feature",
  "properties": {
    "iso:country":"AU",
    "sg:address":"PO Box 872",
    "sg:city":"Dalby",
    "sg:classifiers":[
        {
            "category":"Autos & Motor Vehicles",
            "subcategory":"Automobile Sales",
            "type":"Retail Goods"
        }
    ],
    "sg:phone":"+61 7 4662 4253",
    "sg:postcode":"4405",
    "sg:province":"QLD",
    "sg:tags":[
        "equipment",
        "trailer"
    ],
    "wof:name":"Hillcrest Stock Crates & Equipment",
    "wof:placetype":"venue"
},
  "geometry": {"coordinates":[151.257415772,-27.1783504486],"type":"Point"}
}