{
  "type": "Feature",
  "properties": {
    "addr:full":"798a Burke Rd Camberwell VIC 3124",
    "addr:housenumber":"798a",
    "addr:postcode":"3124",
    "addr:street":"Burke Rd",
    "iso:country":"AU",
    "sg:address":"798a Burke Rd",
    "sg:city":"Camberwell",
    "sg:classifiers":[
        {
            "category":"Shopping",
            "subcategory":"Clothing, Apparel, & Fashions",
            "type":"Retail Goods"
        }
    ],
    "sg:phone":"+61 3 9882 0424",
    "sg:postcode":"3124",
    "sg:province":"VIC",
    "sg:tags":[
        "recycled",
        "clothing"
    ],
    "wof:name":"Carousel Recycle Boutique",
    "wof:placetype":"venue"
},
  "geometry": {"coordinates":[145.058319092,-37.8238143921],"type":"Point"}
}