{
  "type": "Feature",
  "properties": {
    "addr:full":"Shp3/ 19-21 Princes Hwy Fairy Meadow NSW 2519",
    "addr:housenumber":"19-21",
    "addr:postcode":"2519",
    "addr:street":"Princes Hwy",
    "iso:country":"AU",
    "sg:address":"Shp3/ 19-21 Princes Hwy",
    "sg:city":"Fairy Meadow",
    "sg:classifiers":[
        {
            "category":"Shopping",
            "subcategory":"Clothing, Apparel, & Fashions",
            "type":"Retail Goods"
        }
    ],
    "sg:phone":"+61 2 4283 5518",
    "sg:postcode":"2519",
    "sg:province":"NSW",
    "sg:tags":[
        "lady",
        "wear"
    ],
    "wof:name":"SixOneSIx",
    "wof:placetype":"venue"
},
  "geometry": {"coordinates":[150.89297500000001,-34.392563],"type":"Point"}
}