{
  "type": "Feature",
  "properties": {
    "addr:full":"171 Whitehorse Rd Blackburn VIC 3130",
    "addr:housenumber":"171",
    "addr:postcode":"3130",
    "addr:street":"Whitehorse Rd",
    "iso:country":"AU",
    "sg:address":"171 Whitehorse Rd",
    "sg:city":"Blackburn",
    "sg:classifiers":[
        {
            "category":"Shopping",
            "subcategory":"Music",
            "type":"Retail Goods"
        }
    ],
    "sg:phone":"+61 3 9878 8488",
    "sg:postcode":"3130",
    "sg:province":"VIC",
    "sg:tags":[
        "instrument",
        "musical"
    ],
    "wof:name":"Music Junction",
    "wof:placetype":"venue"
},
  "geometry": {"coordinates":[145.155487061,-37.8174629211],"type":"Point"}
}