{
  "type": "Feature",
  "properties": {
    "iso:country":"AU",
    "sg:address":"21 Fifth Ave",
    "sg:city":"Cheltenham",
    "sg:classifiers":[
        {
            "category":"Home & Garden",
            "subcategory":"Building Materials",
            "type":"Retail Goods"
        }
    ],
    "sg:phone":"+61 8 8341 1813",
    "sg:postcode":"5014",
    "sg:province":"SA",
    "sg:tags":[
        "lawn",
        "cutting",
        "maintenance"
    ],
    "wof:name":"Adelaide Lawn & Turf Care",
    "wof:placetype":"venue"
},
  "geometry": {"coordinates":[138.52134704599999,-34.8679618835],"type":"Point"}
}