{
  "type": "Feature",
  "properties": {
    "addr:full":"27 Mirrabooka Drv Clifton Springs VIC 3222",
    "addr:housenumber":"27",
    "addr:postcode":"3222",
    "addr:street":"Mirrabooka Drv",
    "iso:country":"AU",
    "sg:address":"27 Mirrabooka Drv",
    "sg:city":"Clifton Springs",
    "sg:classifiers":[
        {
            "category":"Health Services",
            "subcategory":"Health Practitioner",
            "type":"Services"
        }
    ],
    "sg:phone":"+61 3 5251 3242",
    "sg:postcode":"3222",
    "sg:province":"VIC",
    "sg:tags":[
        "naturopath"
    ],
    "wof:name":"Patrick Beck",
    "wof:placetype":"venue"
},
  "geometry": {"coordinates":[144.55604600000001,-38.160564],"type":"Point"}
}