{
  "type": "Feature",
  "properties": {
    "addr:full":"21 Kennedy St Liverpool NSW 2170",
    "addr:housenumber":"21",
    "addr:postcode":"2170",
    "addr:street":"Kennedy St",
    "iso:country":"AU",
    "sg:address":"21 Kennedy St",
    "sg:city":"Liverpool",
    "sg:classifiers":[
        {
            "category":"Mining & Drilling",
            "type":"Manufacturing & Wholesale Goods"
        }
    ],
    "sg:phone":"+61 2 9601 8319",
    "sg:postcode":"2170",
    "sg:province":"NSW",
    "sg:tags":[
        "boring",
        "contractor"
    ],
    "wof:name":"Techno Bore And Pump Servicing",
    "wof:placetype":"venue"
},
  "geometry": {"coordinates":[150.90658569300001,-33.9206581116],"type":"Point"}
}