{
  "type": "Feature",
  "properties": {
    "iso:country":"AU",
    "sg:address":"Lincoln Hwy",
    "sg:city":"Louth Bay",
    "sg:classifiers":[
        {
            "category":"Farming",
            "subcategory":"Farm",
            "type":"Manufacturing & Wholesale Goods"
        }
    ],
    "sg:phone":"+61 8 8684 6041",
    "sg:postcode":"5607",
    "sg:province":"SA",
    "sg:tags":[
        "farmer"
    ],
    "wof:name":"Branford B G & J F",
    "wof:placetype":"venue"
},
  "geometry": {"coordinates":[135.912674,-34.541309],"type":"Point"}
}