{
  "type": "Feature",
  "properties": {
    "addr:full":"Link Rd Leinster WA 6437",
    "addr:postcode":"6437",
    "addr:street":"Link Rd",
    "iso:country":"AU",
    "sg:address":"Link Rd",
    "sg:city":"Leinster",
    "sg:classifiers":[
        {
            "category":"Health Services",
            "subcategory":"Doctor",
            "type":"Services"
        }
    ],
    "sg:phone":"+61 8 9037 9025",
    "sg:postcode":"6437",
    "sg:province":"WA",
    "sg:tags":[
        "medical",
        "practitioner"
    ],
    "wof:name":"Leinster Medical Centre",
    "wof:placetype":"venue"
},
  "geometry": {"coordinates":[120.69526672400001,-27.9378890991],"type":"Point"}
}