{
  "type": "Feature",
  "properties": {
    "addr:full":"19 Dunn St Biloela QLD 4715",
    "addr:housenumber":"19",
    "addr:postcode":"4715",
    "addr:street":"Dunn St",
    "iso:country":"AU",
    "sg:address":"19 Dunn St",
    "sg:city":"Biloela",
    "sg:classifiers":[
        {
            "category":"Professional",
            "subcategory":"Employment Agencies",
            "type":"Services"
        }
    ],
    "sg:phone":"+61 7 4992 1999",
    "sg:postcode":"4715",
    "sg:province":"QLD",
    "sg:tags":[
        "hire",
        "labour",
        "contractor"
    ],
    "wof:name":"Austins Maintenance",
    "wof:placetype":"venue"
},
  "geometry": {"coordinates":[150.51252746599999,-24.4025592804],"type":"Point"}
}