{
  "type": "Feature",
  "properties": {
    "iso:country":"AU",
    "sg:address":"45 Wearden Rd",
    "sg:city":"Frenchs Forest",
    "sg:classifiers":[
        {
            "category":"Building & Trades",
            "subcategory":"Landscaping Services",
            "type":"Services"
        }
    ],
    "sg:phone":"+61 2 9452 5784",
    "sg:postcode":"2086",
    "sg:province":"NSW",
    "sg:tags":[
        "designer",
        "landscape",
        "contractor"
    ],
    "wof:name":"Ryco Agencies",
    "wof:placetype":"venue"
},
  "geometry": {"coordinates":[151.22706604000001,-33.7390861511],"type":"Point"}
}