{
  "type": "Feature",
  "properties": {
    "addr:full":"PO Box 563 Echunga SA 5153",
    "addr:postcode":"5153",
    "iso:country":"AU",
    "sg:address":"PO Box 563",
    "sg:city":"Echunga",
    "sg:classifiers":[
        {
            "category":"Professional",
            "subcategory":"Employment Agencies",
            "type":"Services"
        }
    ],
    "sg:phone":"+61 415 965 678",
    "sg:postcode":"5153",
    "sg:province":"SA",
    "wof:name":"Denstaff Temping Agency",
    "wof:placetype":"venue"
},
  "geometry": {"coordinates":[138.793426514,-35.1000900269],"type":"Point"}
}