{
  "type": "Feature",
  "properties": {
    "iso:country":"AU",
    "sg:address":"5/ 668 Burwood Rd",
    "sg:city":"Hawthorn East",
    "sg:classifiers":[
        {
            "category":"Professional",
            "subcategory":"Art Services",
            "type":"Services"
        }
    ],
    "sg:phone":"+61 3 9861 9777",
    "sg:postcode":"3123",
    "sg:province":"VIC",
    "sg:tags":[
        "graphic",
        "designer"
    ],
    "wof:name":"Rhodamine Design",
    "wof:placetype":"venue"
},
  "geometry": {"coordinates":[145.04779052699999,-37.824180603],"type":"Point"}
}