{
  "type": "Feature",
  "properties": {
    "addr:full":"340 George St Deniliquin NSW 2710",
    "addr:housenumber":"340",
    "addr:postcode":"2710",
    "addr:street":"George St",
    "iso:country":"AU",
    "sg:address":"340 George St",
    "sg:city":"Deniliquin",
    "sg:classifiers":[
        {
            "category":"Autos & Motor Vehicles",
            "subcategory":"Boat Sales",
            "type":"Retail Goods"
        }
    ],
    "sg:phone":"+61 3 5881 5255",
    "sg:postcode":"2710",
    "sg:province":"NSW",
    "sg:tags":[
        "yacht"
    ],
    "wof:name":"Deni Bike & Boats",
    "wof:placetype":"venue"
},
  "geometry": {"coordinates":[144.96363830600001,-35.5278892517],"type":"Point"}
}