{
  "type": "Feature",
  "properties": {
    "addr:full":"59A Pakington St St Kilda VIC 3182",
    "addr:housenumber":"59a",
    "addr:postcode":"3182",
    "addr:street":"Pakington St",
    "iso:country":"AU",
    "sg:address":"59A Pakington St St",
    "sg:city":"Kilda",
    "sg:classifiers":[
        {
            "category":"Social Services",
            "subcategory":"Retirement Home",
            "type":"Services"
        }
    ],
    "sg:phone":"+61 3 9534 3831",
    "sg:postcode":"3182",
    "sg:province":"VIC",
    "sg:tags":[
        "environmental",
        "consultant",
        "pollution"
    ],
    "wof:name":"Environment Link Pty Ltd",
    "wof:placetype":"venue"
},
  "geometry": {"coordinates":[144.989181519,-37.8662071228],"type":"Point"}
}