{
  "type": "Feature",
  "properties": {
    "iso:country":"AU",
    "sg:address":"58 Punari St",
    "sg:city":"Currajong",
    "sg:classifiers":[
        {
            "category":"Retail",
            "subcategory":"Auto Repair",
            "type":"Services"
        }
    ],
    "sg:phone":"+61 7 4775 5665",
    "sg:postcode":"4812",
    "sg:province":"QLD",
    "sg:tags":[
        "testing",
        "inspection",
        "motor",
        "vehicle"
    ],
    "wof:name":"Bradley Motors",
    "wof:placetype":"venue"
},
  "geometry": {"coordinates":[146.77868699999999,-19.273952],"type":"Point"}
}