{
  "type": "Feature",
  "properties": {
    "addr:full":"8 Stevenage St Yanchep WA 6035",
    "addr:housenumber":"8",
    "addr:postcode":"6035",
    "addr:street":"Stevenage St",
    "iso:country":"AU",
    "sg:address":"8 Stevenage St",
    "sg:city":"Yanchep",
    "sg:classifiers":[
        {
            "category":"Retail",
            "subcategory":"Auto Repair",
            "type":"Services"
        }
    ],
    "sg:phone":"+61 8 9561 1173",
    "sg:postcode":"6035",
    "sg:province":"WA",
    "sg:tags":[
        "repairer",
        "motor",
        "engineer"
    ],
    "wof:name":"Yanchep Towing & Mechanical Services",
    "wof:placetype":"venue"
},
  "geometry": {"coordinates":[115.641197205,-31.5459461212],"type":"Point"}
}