{
  "type": "Feature",
  "properties": {
    "iso:country":"AU",
    "sg:address":"29 - 31",
    "sg:city":"Market Lane Muswellbrook",
    "sg:classifiers":[
        {
            "category":"Building & Trades",
            "subcategory":"Locksmith",
            "type":"Services"
        }
    ],
    "sg:phone":"+61 2 6541 1913",
    "sg:postcode":"2333",
    "sg:province":"NSW",
    "sg:tags":[
        "strongroom",
        "safe",
        "door"
    ],
    "wof:name":"Elks Security Locksmiths & Alarm Services",
    "wof:placetype":"venue"
},
  "geometry": {"coordinates":[150.89222717300001,-32.2669677734],"type":"Point"}
}