{
  "type": "Feature",
  "properties": {
    "addr:full":"182 Bondi Rd Bondi NSW 2026",
    "addr:housenumber":"182",
    "addr:postcode":"2026",
    "addr:street":"Bondi Rd",
    "iso:country":"AU",
    "sg:address":"182 Bondi Rd",
    "sg:city":"Bondi",
    "sg:classifiers":[
        {
            "category":"Shopping",
            "subcategory":"Clothing, Apparel, & Fashions",
            "type":"Retail Goods"
        }
    ],
    "sg:phone":"+61 2 9387 4752",
    "sg:postcode":"2026",
    "sg:province":"NSW",
    "sg:tags":[
        "lady",
        "wear"
    ],
    "wof:name":"Bebe Collections",
    "wof:placetype":"venue"
},
  "geometry": {"coordinates":[151.26222229000001,-33.8935279846],"type":"Point"}
}