{
  "type": "Feature",
  "properties": {
    "iso:country":"AU",
    "sg:address":"4 Murray St",
    "sg:city":"Pittsworth",
    "sg:classifiers":[
        {
            "category":"Professional",
            "subcategory":"Detective & Security Services",
            "type":"Services"
        }
    ],
    "sg:phone":"+61 7 4693 1808",
    "sg:postcode":"4356",
    "sg:province":"QLD",
    "sg:tags":[
        "equipment",
        "window",
        "doors"
    ],
    "wof:name":"B & J Glass & Aluminium Pty Ltd",
    "wof:placetype":"venue"
},
  "geometry": {"coordinates":[151.637314,-27.715544],"type":"Point"}
}