{
  "type": "Feature",
  "properties": {
    "iso:country":"AU",
    "sg:address":"1 - 7 West St",
    "sg:city":"Petersham",
    "sg:classifiers":[
        {
            "category":"Health Services",
            "subcategory":"Health Practitioner",
            "type":"Services"
        }
    ],
    "sg:phone":"+61 2 9564 5938",
    "sg:postcode":"2049",
    "sg:province":"NSW",
    "sg:tags":[
        "herbalist"
    ],
    "wof:name":"Stephen Phillips",
    "wof:placetype":"venue"
},
  "geometry": {"coordinates":[151.150223,-33.892666],"type":"Point"}
}