{
  "type": "Feature",
  "properties": {
    "iso:country":"AU",
    "sg:address":"82 Wandeen Rd",
    "sg:city":"Clareville",
    "sg:classifiers":[
        {
            "category":"Farming",
            "subcategory":"Farm & Veterinary Services",
            "type":"Manufacturing & Wholesale Goods"
        }
    ],
    "sg:phone":"+61 2 9973 3442",
    "sg:postcode":"2107",
    "sg:province":"NSW",
    "sg:tags":[
        "worm"
    ],
    "wof:name":"Vermigold Products & Services",
    "wof:placetype":"venue"
},
  "geometry": {"coordinates":[151.313064575,-33.6387443542],"type":"Point"}
}