{
  "type": "Feature",
  "properties": {
    "addr:full":"PO Box 201 Mt Gravatt QLD 4122",
    "addr:postcode":"4122",
    "iso:country":"AU",
    "sg:address":"PO Box 201",
    "sg:city":"Mt Gravatt",
    "sg:classifiers":[
        {
            "category":"Utilities",
            "subcategory":"Electric",
            "type":"Services"
        }
    ],
    "sg:phone":"+61 407 584 300",
    "sg:postcode":"4122",
    "sg:province":"QLD",
    "sg:tags":[
        "electrical",
        "contractor"
    ],
    "wof:name":"Eltech Electrical Pty Ltd",
    "wof:placetype":"venue"
},
  "geometry": {"coordinates":[153.072723389,-27.5303192139],"type":"Point"}
}