{
  "type": "Feature",
  "properties": {
    "addr:full":"61 Meron St Southport QLD 4215",
    "addr:housenumber":"61",
    "addr:postcode":"4215",
    "addr:street":"Meron St",
    "iso:country":"AU",
    "sg:address":"61 Meron St",
    "sg:city":"Southport",
    "sg:classifiers":[
        {
            "category":"Real Estate",
            "subcategory":"Developer",
            "type":"Services"
        }
    ],
    "sg:phone":"+61 7 5531 2794",
    "sg:postcode":"4215",
    "sg:province":"QLD",
    "sg:tags":[
        "development"
    ],
    "wof:name":"Property Buyers Group",
    "wof:placetype":"venue"
},
  "geometry": {"coordinates":[153.41189575199999,-27.9748249054],"type":"Point"}
}