{
  "type": "Feature",
  "properties": {
    "iso:country":"AU",
    "sg:address":"32 Princess Rd",
    "sg:city":"Claremont",
    "sg:classifiers":[
        {
            "category":"Home & Garden",
            "subcategory":"Carpets & Floor Coverings",
            "type":"Retail Goods"
        }
    ],
    "sg:phone":"+61 8 9385 0504",
    "sg:postcode":"6010",
    "sg:province":"WA",
    "sg:tags":[
        "wood"
    ],
    "wof:name":"Fastwood Flooring",
    "wof:placetype":"venue"
},
  "geometry": {"coordinates":[115.784500122,-31.9865455627],"type":"Point"}
}