{
  "type": "Feature",
  "properties": {
    "addr:full":"15 Cranston St Port Lincoln SA 5606",
    "addr:housenumber":"15",
    "addr:postcode":"5606",
    "addr:street":"Cranston St",
    "iso:country":"AU",
    "sg:address":"15 Cranston St",
    "sg:city":"Port Lincoln",
    "sg:classifiers":[
        {
            "category":"Education",
            "subcategory":"Kindergarten",
            "type":"Public Place"
        }
    ],
    "sg:phone":"+61 8 8683 0479",
    "sg:postcode":"5606",
    "sg:province":"SA",
    "sg:tags":[
        "pre-schools"
    ],
    "wof:name":"Cranston Street Kindergarten",
    "wof:placetype":"venue"
},
  "geometry": {"coordinates":[135.85554500000001,-34.725109],"type":"Point"}
}