{
  "type": "Feature",
  "properties": {
    "addr:full":"1 Hunt St Old Erowal Bay NSW 2540",
    "addr:housenumber":"1",
    "addr:postcode":"2540",
    "addr:street":"Hunt St Old",
    "iso:country":"AU",
    "sg:address":"1 Hunt St",
    "sg:city":"Old Erowal Bay",
    "sg:classifiers":[
        {
            "category":"Building & Trades",
            "subcategory":"Construction",
            "type":"Services"
        }
    ],
    "sg:phone":"+61 2 4443 2270",
    "sg:postcode":"2540",
    "sg:province":"NSW",
    "sg:tags":[
        "contractor"
    ],
    "wof:name":"Illawarra Mastic Applicators",
    "wof:placetype":"venue"
},
  "geometry": {"coordinates":[150.647216797,-35.0878334045],"type":"Point"}
}