{
  "type": "Feature",
  "properties": {
    "addr:full":"108 Hale Rd Forrestfield WA 6058",
    "addr:housenumber":"108",
    "addr:postcode":"6058",
    "addr:street":"Hale Rd",
    "iso:country":"AU",
    "sg:address":"108 Hale Rd",
    "sg:city":"Forrestfield",
    "sg:classifiers":[
        {
            "category":"Professional",
            "subcategory":"Accounting & Tax Preparation",
            "type":"Services"
        }
    ],
    "sg:phone":"+61 8 9359 3007",
    "sg:postcode":"6058",
    "sg:province":"WA",
    "sg:tags":[
        "accountant",
        "auditor"
    ],
    "wof:name":"Peter J Richardson Accountants",
    "wof:placetype":"venue"
},
  "geometry": {"coordinates":[116.004806519,-31.9896392822],"type":"Point"}
}