{
  "type": "Feature",
  "properties": {
    "iso:country":"AU",
    "sg:address":"210 James St",
    "sg:city":"Toowoomba",
    "sg:classifiers":[
        {
            "category":"Travel",
            "subcategory":"Hotels & Motels",
            "type":"Entertainment"
        }
    ],
    "sg:phone":"+61 7 4639 8555",
    "sg:postcode":"4350",
    "sg:province":"QLD",
    "wof:name":"Apollo Lodge Units",
    "wof:placetype":"venue"
},
  "geometry": {"coordinates":[151.944626,-27.567833],"type":"Point"}
}