{
  "type": "Feature",
  "properties": {
    "iso:country":"AU",
    "sg:address":"29- 31 Melbourne St",
    "sg:city":"Riverstone",
    "sg:classifiers":[
        {
            "category":"Social Services",
            "subcategory":"Adult Care",
            "type":"Services"
        }
    ],
    "sg:phone":"+61 2 9838 1015",
    "sg:postcode":"2765",
    "sg:province":"NSW",
    "sg:tags":[
        "towing"
    ],
    "wof:name":"Quakers Hill Towing",
    "wof:placetype":"venue"
},
  "geometry": {"coordinates":[150.856765747,-33.6636734009],"type":"Point"}
}