{
  "type": "Feature",
  "properties": {
    "iso:country":"AU",
    "sg:address":"3a Wilmette Pl",
    "sg:city":"Mona Vale",
    "sg:classifiers":[
        {
            "category":"Home & Garden",
            "subcategory":"Building Materials",
            "type":"Retail Goods"
        }
    ],
    "sg:phone":"+61 2 9999 1525",
    "sg:postcode":"2103",
    "sg:province":"NSW",
    "sg:tags":[
        "merchant",
        "glass",
        "glazier"
    ],
    "wof:name":"Glasscraft Glass & Glazing Pty Ltd",
    "wof:placetype":"venue"
},
  "geometry": {"coordinates":[151.30523681599999,-33.6734352112],"type":"Point"}
}