{
  "type": "Feature",
  "properties": {
    "addr:full":"327 Brunswick Rd Brunswick VIC 3055",
    "addr:housenumber":"327",
    "addr:postcode":"3055",
    "addr:street":"Brunswick Rd",
    "iso:country":"AU",
    "sg:address":"327 Brunswick Rd",
    "sg:city":"Brunswick",
    "sg:classifiers":[
        {
            "category":"Health Services",
            "subcategory":"Health Practitioner",
            "type":"Services"
        }
    ],
    "sg:phone":"+61 3 9387 8279",
    "sg:postcode":"3055",
    "sg:province":"VIC",
    "sg:tags":[
        "psychologist"
    ],
    "wof:name":"Kelly Elaine",
    "wof:placetype":"venue"
},
  "geometry": {"coordinates":[144.951934814,-37.7761459351],"type":"Point"}
}