{
  "type": "Feature",
  "properties": {
    "iso:country":"AU",
    "sg:address":"57 Minnegang St",
    "sg:city":"Warrawong",
    "sg:classifiers":[
        {
            "category":"Professional",
            "subcategory":"Engineering",
            "type":"Services"
        }
    ],
    "sg:phone":"+61 2 4275 1999",
    "sg:postcode":"2502",
    "sg:province":"NSW",
    "sg:tags":[
        "engineer",
        "structural"
    ],
    "wof:name":"Pecorp Design",
    "wof:placetype":"venue"
},
  "geometry": {"coordinates":[150.875595,-34.487068],"type":"Point"}
}