{
  "type": "Feature",
  "properties": {
    "iso:country":"AU",
    "sg:address":"4 Teewah St",
    "sg:city":"Dicky Beach",
    "sg:classifiers":[
        {
            "category":"Building & Trades",
            "subcategory":"Construction",
            "type":"Services"
        }
    ],
    "sg:phone":"+61 438 773 861",
    "sg:postcode":"4551",
    "sg:province":"QLD",
    "sg:tags":[
        "earth",
        "excavating",
        "moving",
        "contractor"
    ],
    "wof:name":"Jimmy Browning Bobcat & Mini Excavators",
    "wof:placetype":"venue"
},
  "geometry": {"coordinates":[153.132156372,-26.7815494537],"type":"Point"}
}