{
  "type": "Feature",
  "properties": {
    "addr:full":"Unit 8/ 1296 Albany Hwy Cannington WA 6107",
    "addr:housenumber":"/ 1296",
    "addr:postcode":"6107",
    "addr:street":"Albany Hwy",
    "iso:country":"AU",
    "sg:address":"Unit 8/ 1296 Albany Hwy",
    "sg:city":"Cannington",
    "sg:classifiers":[
        {
            "category":"Shopping",
            "subcategory":"Music",
            "type":"Retail Goods"
        }
    ],
    "sg:phone":"+61 8 9258 4236",
    "sg:postcode":"6107",
    "sg:province":"WA",
    "sg:tags":[
        "instrument",
        "musical"
    ],
    "wof:name":"Kosmic Sound",
    "wof:placetype":"venue"
},
  "geometry": {"coordinates":[115.929412842,-32.0152282715],"type":"Point"}
}