{
  "type": "Feature",
  "properties": {
    "iso:country":"AU",
    "sg:address":"16/ 51 Old Barrenjoey Rd",
    "sg:city":"Avalon Beach",
    "sg:classifiers":[
        {
            "category":"Utilities",
            "subcategory":"Refuse",
            "type":"Services"
        }
    ],
    "sg:phone":"+61 2 9918 2483",
    "sg:postcode":"2107",
    "sg:province":"NSW",
    "sg:tags":[
        "disposal",
        "reduction",
        "waste"
    ],
    "wof:name":"Brown Brothers Skips",
    "wof:placetype":"venue"
},
  "geometry": {"coordinates":[151.32937622099999,-33.6360359192],"type":"Point"}
}