{
  "type": "Feature",
  "properties": {
    "addr:full":"Benaraby Rd (South) Gladstone QLD 4680",
    "addr:postcode":"4680",
    "addr:street":"Benaraby Rd South",
    "iso:country":"AU",
    "sg:address":"Benaraby Rd (South)",
    "sg:city":"Gladstone",
    "sg:classifiers":[
        {
            "category":"Building & Trades",
            "subcategory":"Equipment Rental",
            "type":"Services"
        }
    ],
    "sg:phone":"+61 7 4979 1444",
    "sg:postcode":"4680",
    "sg:province":"QLD",
    "sg:tags":[
        "crane",
        "hire"
    ],
    "wof:name":"Capacity Cranes",
    "wof:placetype":"venue"
},
  "geometry": {"coordinates":[151.25355529800001,-23.8438205719],"type":"Point"}
}