{
  "type": "Feature",
  "properties": {
    "iso:country":"AU",
    "sg:address":"2 Kirkpatrick Drv",
    "sg:city":"Delacombe",
    "sg:classifiers":[
        {
            "category":"Manufacturing",
            "subcategory":"Paper Products",
            "type":"Manufacturing & Wholesale Goods"
        }
    ],
    "sg:phone":"+61 3 5335 7430",
    "sg:postcode":"3356",
    "sg:province":"VIC",
    "sg:tags":[
        "box",
        "fibre",
        "carton",
        "cardboard"
    ],
    "wof:name":"L. & Y. Cole",
    "wof:placetype":"venue"
},
  "geometry": {"coordinates":[143.82135,-37.579807],"type":"Point"}
}