{
  "type": "Feature",
  "properties": {
    "addr:full":"131 Clovelly Rd Randwick NSW 2031",
    "addr:housenumber":"131",
    "addr:postcode":"2031",
    "addr:street":"Clovelly Rd",
    "iso:country":"AU",
    "sg:address":"131 Clovelly Rd",
    "sg:city":"Randwick",
    "sg:classifiers":[
        {
            "category":"Professional",
            "subcategory":"Art Services",
            "type":"Services"
        }
    ],
    "sg:phone":"+61 2 9398 4043",
    "sg:postcode":"2031",
    "sg:province":"NSW",
    "sg:tags":[
        "decorator",
        "painter"
    ],
    "wof:name":"Casson C J",
    "wof:placetype":"venue"
},
  "geometry": {"coordinates":[151.25108337399999,-33.9100227356],"type":"Point"}
}