{
  "type": "Feature",
  "properties": {
    "addr:full":"319 Mt Dandenong Rd Croydon VIC 3136",
    "addr:housenumber":"319",
    "addr:postcode":"3136",
    "addr:street":"Mt Dandenong Rd",
    "iso:country":"AU",
    "sg:address":"319 Mt Dandenong Rd",
    "sg:city":"Croydon",
    "sg:classifiers":[
        {
            "category":"Health Services",
            "subcategory":"Dentist",
            "type":"Services"
        }
    ],
    "sg:phone":"+61 3 9725 5611",
    "sg:postcode":"3136",
    "sg:province":"VIC",
    "wof:name":"Jayasekara Dom Dr",
    "wof:placetype":"venue"
},
  "geometry": {"coordinates":[145.29075622600001,-37.7995948792],"type":"Point"}
}