{
  "type": "Feature",
  "properties": {
    "addr:full":"77 Henderson St Inverell NSW 2360",
    "addr:housenumber":"77",
    "addr:postcode":"2360",
    "addr:street":"Henderson St",
    "iso:country":"AU",
    "sg:address":"77 Henderson St",
    "sg:city":"Inverell",
    "sg:classifiers":[
        {
            "category":"Building & Trades",
            "subcategory":"Construction",
            "type":"Services"
        }
    ],
    "sg:phone":"+61 408 869 264",
    "sg:postcode":"2360",
    "sg:province":"NSW",
    "sg:tags":[
        "renovation",
        "alterations",
        "extension",
        "contractor"
    ],
    "wof:name":"MacKay Geoff",
    "wof:placetype":"venue"
},
  "geometry": {"coordinates":[151.12196350100001,-29.7747268677],"type":"Point"}
}