{
  "type": "Feature",
  "properties": {
    "addr:full":"24 Queensland Ave Broadbeach QLD 4218",
    "addr:housenumber":"24",
    "addr:postcode":"4218",
    "addr:street":"Queensland Ave",
    "iso:country":"AU",
    "sg:address":"24 Queensland Ave",
    "sg:city":"Broadbeach",
    "sg:classifiers":[
        {
            "category":"Professional",
            "subcategory":"Employment Agencies",
            "type":"Services"
        }
    ],
    "sg:phone":"+61 7 5526 2566",
    "sg:postcode":"4218",
    "sg:province":"QLD",
    "sg:tags":[
        "model"
    ],
    "wof:name":"M.A.G.C Models Actors Gold Coast",
    "wof:placetype":"venue"
},
  "geometry": {"coordinates":[153.43168640100001,-28.0274410248],"type":"Point"}
}