{
  "type": "Feature",
  "properties": {
    "iso:country":"AU",
    "sg:address":"24 Lithgow St",
    "sg:city":"Fyshwick",
    "sg:classifiers":[
        {
            "category":"Building & Trades",
            "subcategory":"Cleaning & Sanitation",
            "type":"Services"
        }
    ],
    "sg:phone":"+61 2 6239 1399",
    "sg:postcode":"2609",
    "sg:province":"ACT",
    "sg:tags":[
        "commercial",
        "maintenance"
    ],
    "wof:name":"ABA Construction Managers Pty Ltd",
    "wof:placetype":"venue"
},
  "geometry": {"coordinates":[149.16828918499999,-35.3293914795],"type":"Point"}
}