{
  "type": "Feature",
  "properties": {
    "addr:full":"PO Box 751 Blackwood SA 5051",
    "addr:postcode":"5051",
    "iso:country":"AU",
    "sg:address":"PO Box 751",
    "sg:city":"Blackwood",
    "sg:classifiers":[
        {
            "category":"Building & Trades",
            "subcategory":"Construction",
            "type":"Services"
        }
    ],
    "sg:phone":"+61 418 422 488",
    "sg:postcode":"5051",
    "sg:province":"SA",
    "sg:tags":[
        "builder",
        "designer",
        "room",
        "cool"
    ],
    "wof:name":"S A Food Equipment",
    "wof:placetype":"venue"
},
  "geometry": {"coordinates":[138.611435,-35.020821],"type":"Point"}
}