{
  "type": "Feature",
  "properties": {
    "addr:full":"29 Loraine St Capalaba QLD 4157",
    "addr:housenumber":"29",
    "addr:postcode":"4157",
    "addr:street":"Loraine St",
    "iso:country":"AU",
    "sg:address":"29 Loraine St",
    "sg:city":"Capalaba",
    "sg:classifiers":[
        {
            "category":"Organizations",
            "subcategory":"Community Association",
            "type":"Services"
        }
    ],
    "sg:phone":"+61 7 3321 0237",
    "sg:postcode":"4157",
    "sg:province":"QLD",
    "sg:tags":[
        "organisation",
        "family",
        "welfare"
    ],
    "wof:name":"Mens Support Service Qld Inc.",
    "wof:placetype":"venue"
},
  "geometry": {"coordinates":[153.19244384800001,-27.5224971771],"type":"Point"}
}