{
  "type": "Feature",
  "properties": {
    "addr:full":"47 Whitbread Rd Clinton QLD 4680",
    "addr:housenumber":"47",
    "addr:postcode":"4680",
    "addr:street":"Whitbread Rd",
    "iso:country":"AU",
    "sg:address":"47 Whitbread Rd",
    "sg:city":"Clinton",
    "sg:classifiers":[
        {
            "category":"Home & Garden",
            "subcategory":"Hardware",
            "type":"Retail Goods"
        }
    ],
    "sg:phone":"+61 7 4978 4458",
    "sg:postcode":"4680",
    "sg:province":"QLD",
    "sg:tags":[
        "compressor",
        "air"
    ],
    "wof:name":"Gladstone Portable Air Systems",
    "wof:placetype":"venue"
},
  "geometry": {"coordinates":[151.20826721200001,-23.8730430603],"type":"Point"}
}