{
  "type": "Feature",
  "properties": {
    "addr:full":"O&#039;Neills Rd Tyabb VIC 3913",
    "addr:postcode":"3913",
    "addr:street":"Neills Rd",
    "iso:country":"AU",
    "sg:address":"O&#039;Neills Rd",
    "sg:city":"Tyabb",
    "sg:classifiers":[
        {
            "category":"Farming",
            "subcategory":"Nursery",
            "type":"Manufacturing & Wholesale Goods"
        }
    ],
    "sg:phone":"+61 3 5977 4888",
    "sg:postcode":"3913",
    "sg:province":"VIC",
    "wof:name":"Brunning & Sons John",
    "wof:placetype":"venue"
},
  "geometry": {"coordinates":[145.201904297,-38.2522697449],"type":"Point"}
}