{
  "type": "Feature",
  "properties": {
    "addr:full":"86 Haverfield St Echuca VIC 3564",
    "addr:housenumber":"86",
    "addr:postcode":"3564",
    "addr:street":"Haverfield St",
    "iso:country":"AU",
    "sg:address":"86 Haverfield St",
    "sg:city":"Echuca",
    "sg:classifiers":[
        {
            "category":"Travel",
            "subcategory":"Hostel",
            "type":"Entertainment"
        }
    ],
    "sg:phone":"+61 3 5480 6772",
    "sg:postcode":"3564",
    "sg:province":"VIC",
    "sg:tags":[
        "home"
    ],
    "wof:name":"Burke House",
    "wof:placetype":"venue"
},
  "geometry": {"coordinates":[144.745803833,-36.1363601685],"type":"Point"}
}