{
  "type": "Feature",
  "properties": {
    "addr:full":"Shop 40 Nowra Fair East St Nowra NSW 2540",
    "addr:housenumber":"shop 40",
    "addr:postcode":"2540",
    "addr:street":"St",
    "iso:country":"AU",
    "sg:address":"Shop 40 Nowra Fair East St",
    "sg:city":"Nowra",
    "sg:classifiers":[
        {
            "category":"Shopping",
            "subcategory":"Clothing, Apparel, & Fashions",
            "type":"Retail Goods"
        }
    ],
    "sg:phone":"+61 2 4421 2709",
    "sg:postcode":"2540",
    "sg:province":"NSW",
    "sg:tags":[
        "menswear"
    ],
    "wof:name":"Lowes",
    "wof:placetype":"venue"
},
  "geometry": {"coordinates":[150.81671142600001,-35.0161590576],"type":"Point"}
}