{
  "type": "Feature",
  "properties": {
    "addr:full":"32 Mitta St Box Hill North VIC 3129",
    "addr:housenumber":"32",
    "addr:postcode":"3129",
    "addr:street":"Mitta St",
    "iso:country":"AU",
    "sg:address":"32 Mitta St",
    "sg:city":"Box Hill North",
    "sg:classifiers":[
        {
            "category":"Building & Trades",
            "subcategory":"Construction",
            "type":"Services"
        }
    ],
    "sg:phone":"+61 3 9898 5024",
    "sg:postcode":"3129",
    "sg:province":"VIC",
    "sg:tags":[
        "contractor"
    ],
    "wof:name":"Wat's On Top Constructions",
    "wof:placetype":"venue"
},
  "geometry": {"coordinates":[145.12338256800001,-37.8031578064],"type":"Point"}
}