{
  "type": "Feature",
  "properties": {
    "addr:full":"Studio 5, The Walkway, 1269 Pacific Hwy Turramurra NSW 2074",
    "addr:housenumber":"1269",
    "addr:postcode":"2074",
    "addr:street":"The;Pacific Hwy",
    "iso:country":"AU",
    "sg:address":"Studio 5, The Walkway, 1269 Pacific Hwy",
    "sg:city":"Turramurra",
    "sg:classifiers":[
        {
            "category":"Professional",
            "subcategory":"Art Services",
            "type":"Services"
        }
    ],
    "sg:phone":"+61 2 9144 7161",
    "sg:postcode":"2074",
    "sg:province":"NSW",
    "sg:tags":[
        "picture",
        "frame",
        "framing"
    ],
    "wof:name":"My Framer",
    "wof:placetype":"venue"
},
  "geometry": {"coordinates":[151.130096436,-33.7330627441],"type":"Point"}
}