{
  "type": "Feature",
  "properties": {
    "addr:full":"68A Mullers Rd Greenacres SA 5086",
    "addr:housenumber":"68a",
    "addr:postcode":"5086",
    "addr:street":"Mullers Rd",
    "iso:country":"AU",
    "sg:address":"68A Mullers Rd",
    "sg:city":"Greenacres",
    "sg:classifiers":[
        {
            "category":"Real Estate",
            "subcategory":"Real Estate Agent",
            "type":"Services"
        }
    ],
    "sg:phone":"+61 8 8261 8333",
    "sg:postcode":"5086",
    "sg:province":"SA",
    "wof:name":"Professionals Northgate Oakden",
    "wof:placetype":"venue"
},
  "geometry": {"coordinates":[138.63412475600001,-34.8712882996],"type":"Point"}
}