{
  "type": "Feature",
  "properties": {
    "addr:full":"Sunflower Drv Claremont Meadows NSW 2747",
    "addr:postcode":"2747",
    "addr:street":"Sunflower Drv",
    "iso:country":"AU",
    "sg:address":"Sunflower Drv",
    "sg:city":"Claremont Meadows",
    "sg:classifiers":[
        {
            "category":"Education",
            "subcategory":"School",
            "type":"Public Place"
        }
    ],
    "sg:phone":"+61 2 9833 0711",
    "sg:postcode":"2747",
    "sg:province":"NSW",
    "wof:name":"Claremont Meadows Public School",
    "wof:placetype":"venue"
},
  "geometry": {"coordinates":[150.75221252399999,-33.7702255249],"type":"Point"}
}