{
  "type": "Feature",
  "properties": {
    "addr:full":"Shp 16/ 134 Mann St Gosford NSW 2250",
    "addr:housenumber":"16 / 134",
    "addr:postcode":"2250",
    "addr:street":"Mann St",
    "iso:country":"AU",
    "sg:address":"Shp 16/ 134 Mann St",
    "sg:city":"Gosford",
    "sg:classifiers":[
        {
            "category":"Shopping",
            "subcategory":"Clothing, Apparel, & Fashions",
            "type":"Retail Goods"
        }
    ],
    "sg:phone":"+61 2 4322 2887",
    "sg:postcode":"2250",
    "sg:province":"NSW",
    "sg:tags":[
        "recycled",
        "clothing"
    ],
    "wof:name":"Kelly Street Clothing",
    "wof:placetype":"venue"
},
  "geometry": {"coordinates":[151.34185790999999,-33.4261703491],"type":"Point"}
}