{
  "type": "Feature",
  "properties": {
    "iso:country":"AU",
    "sg:address":"4 Pascoe Ave",
    "sg:city":"Claremont",
    "sg:classifiers":[
        {
            "category":"Professional",
            "subcategory":"Accounting & Tax Preparation",
            "type":"Services"
        }
    ],
    "sg:phone":"+61 418 371 422",
    "sg:postcode":"7011",
    "sg:province":"TAS",
    "sg:tags":[
        "bookkeeping"
    ],
    "wof:name":"Just Bookkeeping",
    "wof:placetype":"venue"
},
  "geometry": {"coordinates":[147.25544738799999,-42.7941131592],"type":"Point"}
}