{
  "type": "Feature",
  "properties": {
    "iso:country":"AU",
    "sg:address":"111 Darley St",
    "sg:city":"Mona Vale",
    "sg:classifiers":[
        {
            "category":"Professional",
            "type":"Services"
        }
    ],
    "sg:phone":"+61 2 9979 7577",
    "sg:postcode":"2103",
    "sg:province":"NSW",
    "sg:tags":[
        "transport"
    ],
    "wof:name":"All Boat Transport Pty Ltd",
    "wof:placetype":"venue"
},
  "geometry": {"coordinates":[151.30351257300001,-33.6734390259],"type":"Point"}
}