{
  "type": "Feature",
  "properties": {
    "addr:full":"60 John St Northbridge WA 6003",
    "addr:housenumber":"60",
    "addr:postcode":"6003",
    "addr:street":"John St",
    "iso:country":"AU",
    "sg:address":"60 John St",
    "sg:city":"Northbridge",
    "sg:classifiers":[
        {
            "category":"Organizations",
            "subcategory":"Community Association",
            "type":"Services"
        }
    ],
    "sg:phone":"+61 8 9228 4525",
    "sg:postcode":"6003",
    "sg:province":"WA",
    "sg:tags":[
        "organisation",
        "family",
        "welfare"
    ],
    "wof:name":"WA Association of Toy Libraries (WAATL)",
    "wof:placetype":"venue"
},
  "geometry": {"coordinates":[115.854072571,-31.945230484],"type":"Point"}
}