{
  "type": "Feature",
  "properties": {
    "iso:country":"AU",
    "sg:address":"Rear of 46 Park Ave",
    "sg:city":"Adamstown",
    "sg:classifiers":[
        {
            "category":"Autos & Motor Vehicles",
            "subcategory":"Auto Supplies",
            "type":"Retail Goods"
        }
    ],
    "sg:phone":"+61 2 4952 1352",
    "sg:postcode":"2289",
    "sg:province":"NSW",
    "sg:tags":[
        "part",
        "cycles",
        "accessory"
    ],
    "wof:name":"Bikecare Motorcycle Dynotuning Centre",
    "wof:placetype":"venue"
},
  "geometry": {"coordinates":[151.71531677199999,-32.9388504028],"type":"Point"}
}