{
  "type": "Feature",
  "properties": {
    "iso:country":"AU",
    "sg:address":"Level 15/ 55 Clarence St",
    "sg:city":"Sydney",
    "sg:classifiers":[
        {
            "category":"Real Estate",
            "subcategory":"Real Estate Agent",
            "type":"Services"
        }
    ],
    "sg:phone":"+61 2 8823 6300",
    "sg:postcode":"2000",
    "sg:province":"NSW",
    "wof:name":"LandMark White (NSW) Pty Ltd",
    "wof:placetype":"venue"
},
  "geometry": {"coordinates":[151.205154419,-33.8663024902],"type":"Point"}
}