{
  "type": "Feature",
  "properties": {
    "iso:country":"AU",
    "sg:address":"Hart Rd",
    "sg:city":"Two Wells",
    "sg:classifiers":[
        {
            "category":"Food & Beverages",
            "subcategory":"Groceries & Convenience Stores",
            "type":"Retail Goods"
        }
    ],
    "sg:phone":"+61 8 8520 2001",
    "sg:postcode":"5501",
    "sg:province":"SA",
    "sg:tags":[
        "merchant",
        "egg"
    ],
    "wof:name":"Country Fresh Eggs",
    "wof:placetype":"venue"
},
  "geometry": {"coordinates":[138.476654,-34.562771],"type":"Point"}
}