{
  "type": "Feature",
  "properties": {
    "addr:full":"288 Kiewa St Albury NSW 2640",
    "addr:housenumber":"288",
    "addr:postcode":"2640",
    "addr:street":"Kiewa St",
    "iso:country":"AU",
    "sg:address":"288 Kiewa St",
    "sg:city":"Albury",
    "sg:classifiers":[
        {
            "category":"Retail",
            "subcategory":"Auto Repair",
            "type":"Services"
        }
    ],
    "sg:phone":"+61 2 6041 4733",
    "sg:postcode":"2640",
    "sg:province":"NSW",
    "sg:tags":[
        "clutch",
        "brake"
    ],
    "wof:name":"Albury Brake & Clutch Centre",
    "wof:placetype":"venue"
},
  "geometry": {"coordinates":[146.91595459000001,-36.0798721313],"type":"Point"}
}