{
  "type": "Feature",
  "properties": {
    "iso:country":"AU",
    "sg:address":"17 Rennison St",
    "sg:city":"Beaumaris",
    "sg:classifiers":[
        {
            "category":"Health Services",
            "subcategory":"Health Practitioner",
            "type":"Services"
        }
    ],
    "sg:phone":"+61 3 9589 3956",
    "sg:postcode":"3193",
    "sg:province":"VIC",
    "sg:tags":[
        "psychologist"
    ],
    "wof:name":"Andrew Jocelyn",
    "wof:placetype":"venue"
},
  "geometry": {"coordinates":[145.03814697300001,-37.9933929443],"type":"Point"}
}