{
  "type": "Feature",
  "properties": {
    "addr:full":"9 Clifford St Suffolk Park NSW 2481",
    "addr:housenumber":"9",
    "addr:postcode":"2481",
    "addr:street":"Clifford St",
    "iso:country":"AU",
    "sg:address":"9 Clifford St",
    "sg:city":"Suffolk Park",
    "sg:classifiers":[
        {
            "category":"Fast Food",
            "type":"Food & Drink"
        }
    ],
    "sg:phone":"+61 2 6685 3101",
    "sg:postcode":"2481",
    "sg:province":"NSW",
    "sg:tags":[
        "away",
        "take"
    ],
    "wof:name":"Earth &#039;n&#039;# Sea Pizza & Pasta",
    "wof:placetype":"venue"
},
  "geometry": {"coordinates":[153.60922241200001,-28.6895675659],"type":"Point"}
}