{
  "type": "Feature",
  "properties": {
    "addr:full":"65 Bulcock St Caloundra QLD 4551",
    "addr:housenumber":"65",
    "addr:postcode":"4551",
    "addr:street":"Bulcock St",
    "iso:country":"AU",
    "sg:address":"65 Bulcock St",
    "sg:city":"Caloundra",
    "sg:classifiers":[
        {
            "category":"Professional",
            "subcategory":"Accounting & Tax Preparation",
            "type":"Services"
        }
    ],
    "sg:phone":"+61 7 5491 2822",
    "sg:postcode":"4551",
    "sg:province":"QLD",
    "sg:tags":[
        "accountant",
        "auditor"
    ],
    "wof:name":"Focus Professional Group",
    "wof:placetype":"venue"
},
  "geometry": {"coordinates":[153.12911987300001,-26.8046302795],"type":"Point"}
}