{
  "type": "Feature",
  "properties": {
    "addr:full":"131 Macquarie St Sydney NSW 2000",
    "addr:housenumber":"131",
    "addr:postcode":"2000",
    "addr:street":"Macquarie St",
    "iso:country":"AU",
    "sg:address":"131 Macquarie St",
    "sg:city":"Sydney",
    "sg:classifiers":[
        {
            "category":"Manufacturing",
            "subcategory":"Metals",
            "type":"Manufacturing & Wholesale Goods"
        }
    ],
    "sg:phone":"+61 2 9235 5411",
    "sg:postcode":"2000",
    "sg:province":"NSW",
    "sg:tags":[
        "wholesaler",
        "aluminium",
        "mfrs"
    ],
    "wof:name":"Pechiney Pacific Pty Ltd",
    "wof:placetype":"venue"
},
  "geometry": {"coordinates":[151.212646484,-33.8641242981],"type":"Point"}
}