{
  "type": "Feature",
  "properties": {
    "addr:full":"Cnr Illawarra Crs South & Kookaburra Tce Ballajura WA 6066",
    "addr:postcode":"6066",
    "addr:street":"Cnr Illawarra Crs South & Kookaburra Tce",
    "iso:country":"AU",
    "sg:address":"Cnr Illawarra Crs South & Kookaburra Tce",
    "sg:city":"Ballajura",
    "sg:classifiers":[
        {
            "category":"Education",
            "subcategory":"School",
            "type":"Public Place"
        }
    ],
    "sg:phone":"+61 8 9249 3766",
    "sg:postcode":"6066",
    "sg:province":"WA",
    "sg:tags":[
        "state",
        "except",
        "nsw"
    ],
    "wof:name":"Ballajura Primary",
    "wof:placetype":"venue"
},
  "geometry": {"coordinates":[115.892547607,-31.834815979],"type":"Point"}
}