{
  "type": "Feature",
  "properties": {
    "iso:country":"AU",
    "sg:address":"Unit 1/ 49 Prime Drv",
    "sg:city":"Seven Hills",
    "sg:classifiers":[
        {
            "category":"Retail",
            "subcategory":"Auto Repair",
            "type":"Services"
        }
    ],
    "sg:phone":"+61 2 9620 9941",
    "sg:postcode":"2147",
    "sg:province":"NSW",
    "sg:tags":[
        "gas",
        "conversion",
        "natural",
        "lp",
        "vehicle"
    ],
    "wof:name":"Gas Man The",
    "wof:placetype":"venue"
},
  "geometry": {"coordinates":[150.953033447,-33.7723655701],"type":"Point"}
}