{
  "type": "Feature",
  "properties": {
    "iso:country":"AU",
    "sg:address":"PO Box 2079",
    "sg:city":"Windsor",
    "sg:classifiers":[
        {
            "category":"Home & Garden",
            "subcategory":"Building Materials",
            "type":"Retail Goods"
        }
    ],
    "sg:phone":"+61 7 3857 1660",
    "sg:postcode":"4030",
    "sg:province":"QLD",
    "sg:tags":[
        "lawn",
        "cutting",
        "maintenance"
    ],
    "wof:name":"Franks Lawnmowing Service",
    "wof:placetype":"venue"
},
  "geometry": {"coordinates":[153.028595,-27.437719],"type":"Point"}
}