{
  "type": "Feature",
  "properties": {
    "addr:full":"1 Davies Ave Hobart TAS 7000",
    "addr:housenumber":"1",
    "addr:postcode":"7000",
    "addr:street":"Davies Ave",
    "iso:country":"AU",
    "sg:address":"1 Davies Ave",
    "sg:city":"Hobart",
    "sg:classifiers":[
        {
            "category":"Sports & Exercise",
            "subcategory":"Gym",
            "type":"Entertainment"
        }
    ],
    "sg:phone":"+61 3 6222 6999",
    "sg:postcode":"7000",
    "sg:province":"TAS",
    "sg:tags":[
        "health",
        "fitness"
    ],
    "sg:website":"http://www.hobartcity.com.au/thac",
    "wof:name":"Tattersalls Hobart Aquatic Centre",
    "wof:placetype":"venue"
},
  "geometry": {"coordinates":[147.32814025900001,-42.8722763062],"type":"Point"}
}