{
  "type": "Feature",
  "properties": {
    "iso:country":"AU",
    "sg:address":"10 - 16 Waynote Pl",
    "sg:city":"Unanderra",
    "sg:classifiers":[
        {
            "category":"Utilities",
            "subcategory":"Refuse",
            "type":"Services"
        }
    ],
    "sg:phone":"+61 2 4272 7273",
    "sg:postcode":"2526",
    "sg:province":"NSW",
    "sg:tags":[
        "disposal",
        "reduction",
        "waste"
    ],
    "sg:website":"http://www.collex.com.au",
    "wof:name":"Collex Pty Ltd",
    "wof:placetype":"venue"
},
  "geometry": {"coordinates":[150.864013672,-34.4607391357],"type":"Point"}
}