{
  "type": "Feature",
  "properties": {
    "addr:full":"Birdcage 1. 1 Doody St Alexandria NSW 2015",
    "addr:housenumber":"1 1",
    "addr:postcode":"2015",
    "addr:street":"Birdcage;Doody St",
    "iso:country":"AU",
    "sg:address":"Birdcage 1. 1 Doody St",
    "sg:city":"Alexandria",
    "sg:classifiers":[
        {
            "category":"Professional",
            "subcategory":"Detective & Security Services",
            "type":"Services"
        }
    ],
    "sg:phone":"+61 2 8338 8546",
    "sg:postcode":"2015",
    "sg:province":"NSW",
    "sg:tags":[
        "consultant",
        "system"
    ],
    "wof:name":"Nsec",
    "wof:placetype":"venue"
},
  "geometry": {"coordinates":[151.19851684599999,-33.9172515869],"type":"Point"}
}