{
  "type": "Feature",
  "properties": {
    "addr:full":"22 Stow St Webberton WA 6530",
    "addr:housenumber":"22",
    "addr:postcode":"6530",
    "addr:street":"Stow St",
    "iso:country":"AU",
    "sg:address":"22 Stow St",
    "sg:city":"Webberton",
    "sg:classifiers":[
        {
            "category":"Building & Trades",
            "subcategory":"Plumbing",
            "type":"Services"
        }
    ],
    "sg:phone":"+61 8 9964 4171",
    "sg:postcode":"6530",
    "sg:province":"WA",
    "sg:tags":[
        "plumber",
        "gasfitters"
    ],
    "wof:name":"Herrings Coastal Plumbing & Gas Fitting Services",
    "wof:placetype":"venue"
},
  "geometry": {"coordinates":[114.639587402,-28.7572956085],"type":"Point"}
}