{
  "type": "Feature",
  "properties": {
    "iso:country":"AU",
    "sg:address":"Murray Valley Hwy",
    "sg:city":"Nyah",
    "sg:classifiers":[
        {
            "category":"Sports & Exercise",
            "subcategory":"Golf",
            "type":"Entertainment"
        }
    ],
    "sg:phone":"+61 3 5030 2396",
    "sg:postcode":"3594",
    "sg:province":"VIC",
    "sg:tags":[
        "club"
    ],
    "wof:name":"Nyah District Golf Club",
    "wof:placetype":"venue"
},
  "geometry": {"coordinates":[143.367843628,-35.1491088867],"type":"Point"}
}