{
  "type": "Feature",
  "properties": {
    "addr:full":"41 Wright St Wulguru QLD 4811",
    "addr:housenumber":"41",
    "addr:postcode":"4811",
    "addr:street":"Wright St",
    "iso:country":"AU",
    "sg:address":"41 Wright St",
    "sg:city":"Wulguru",
    "sg:classifiers":[
        {
            "category":"Building & Trades",
            "subcategory":"Construction",
            "type":"Services"
        }
    ],
    "sg:phone":"+61 7 4778 1971",
    "sg:postcode":"4811",
    "sg:province":"QLD",
    "sg:tags":[
        "earth",
        "excavating",
        "moving",
        "contractor"
    ],
    "wof:name":"Graham & Rosa Fielding",
    "wof:placetype":"venue"
},
  "geometry": {"coordinates":[146.815506,-19.327719],"type":"Point"}
}