{
  "type": "Feature",
  "properties": {
    "iso:country":"AU",
    "sg:address":"Shp 6 & 7, Westbourne Ave",
    "sg:city":"Thirlmere",
    "sg:classifiers":[
        {
            "category":"Communications",
            "subcategory":"Film & Video Production",
            "type":"Services"
        }
    ],
    "sg:phone":"+61 2 4683 3780",
    "sg:postcode":"2572",
    "sg:province":"NSW",
    "sg:tags":[
        "dvd",
        "library"
    ],
    "wof:name":"Legends Video",
    "wof:placetype":"venue"
},
  "geometry": {"coordinates":[150.57267761200001,-34.1947402954],"type":"Point"}
}