{
  "type": "Feature",
  "properties": {
    "iso:country":"AU",
    "sg:address":"966 Burwood Hwy",
    "sg:city":"Ferntree Gully",
    "sg:classifiers":[
        {
            "category":"Autos & Motor Vehicles",
            "subcategory":"Auto Supplies",
            "type":"Retail Goods"
        }
    ],
    "sg:phone":"+61 3 9758 8000",
    "sg:postcode":"3156",
    "sg:province":"VIC",
    "sg:tags":[
        "part",
        "cycles",
        "accessory"
    ],
    "wof:name":"City Motorbikes",
    "wof:placetype":"venue"
},
  "geometry": {"coordinates":[145.28514099099999,-37.8869628906],"type":"Point"}
}