{
  "type": "Feature",
  "properties": {
    "iso:country":"AU",
    "sg:address":"68 Yandilla St",
    "sg:city":"Pittsworth",
    "sg:classifiers":[
        {
            "category":"Food & Beverages",
            "subcategory":"Meat & Fish",
            "type":"Retail Goods"
        }
    ],
    "sg:phone":"+61 7 4693 1288",
    "sg:postcode":"4356",
    "sg:province":"QLD",
    "sg:tags":[
        "seafood"
    ],
    "wof:name":"Pittsworth Seafood & Gourmet Delicatessen",
    "wof:placetype":"venue"
},
  "geometry": {"coordinates":[151.634995,-27.715862],"type":"Point"}
}