{
  "type": "Feature",
  "properties": {
    "iso:country":"AU",
    "sg:address":"39 Park Ave",
    "sg:city":"Pennington",
    "sg:classifiers":[
        {
            "category":"Autos & Motor Vehicles",
            "subcategory":"Automobile Sales",
            "type":"Retail Goods"
        }
    ],
    "sg:phone":"+61 8 8243 2321",
    "sg:postcode":"5013",
    "sg:province":"SA",
    "sg:tags":[
        "bus",
        "used",
        "truck"
    ],
    "wof:name":"Fowles Auction Group",
    "wof:placetype":"venue"
},
  "geometry": {"coordinates":[138.537567139,-34.8597679138],"type":"Point"}
}