{
  "type": "Feature",
  "properties": {
    "addr:full":"Cnr Brisbane Rd & Tarcoola Ave Mooloolaba QLD 4557",
    "addr:postcode":"4557",
    "addr:street":"Cnr Brisbane Rd & Tarcoola Ave",
    "iso:country":"AU",
    "sg:address":"Cnr Brisbane Rd & Tarcoola Ave",
    "sg:city":"Mooloolaba",
    "sg:classifiers":[
        {
            "category":"Health Services",
            "subcategory":"Optometrist",
            "type":"Services"
        }
    ],
    "sg:phone":"+61 7 5452 5022",
    "sg:postcode":"4557",
    "sg:province":"QLD",
    "wof:name":"ProVision",
    "wof:placetype":"venue"
},
  "geometry": {"coordinates":[153.117797852,-26.6837902069],"type":"Point"}
}