{
  "type": "Feature",
  "properties": {
    "addr:full":"75- 87 Woodwood St Coolgardie WA 6429",
    "addr:housenumber":"87",
    "addr:postcode":"6429",
    "addr:street":"Woodwood St",
    "iso:country":"AU",
    "sg:address":"75- 87 Woodwood St",
    "sg:city":"Coolgardie",
    "sg:classifiers":[
        {
            "category":"Communications",
            "subcategory":"News Services",
            "type":"Services"
        }
    ],
    "sg:phone":"+61 8 9026 6388",
    "sg:postcode":"6429",
    "sg:province":"WA",
    "sg:tags":[
        "information",
        "tourist",
        "attractions"
    ],
    "wof:name":"Coolgardie Railway Station Museum",
    "wof:placetype":"venue"
},
  "geometry": {"coordinates":[121.18895000000001,-30.93961],"type":"Point"}
}