{
  "type": "Feature",
  "properties": {
    "addr:full":"109 Blackwall Rd Woy Woy NSW 2256",
    "addr:housenumber":"109",
    "addr:postcode":"2256",
    "addr:street":"Blackwall Rd",
    "iso:country":"AU",
    "sg:address":"109 Blackwall Rd",
    "sg:city":"Woy Woy",
    "sg:classifiers":[
        {
            "category":"Health Services",
            "subcategory":"Dentist",
            "type":"Services"
        }
    ],
    "sg:phone":"+61 2 4341 1751",
    "sg:postcode":"2256",
    "sg:province":"NSW",
    "wof:name":"Woy Woy Dental Care",
    "wof:placetype":"venue"
},
  "geometry": {"coordinates":[151.32562255900001,-33.488243103],"type":"Point"}
}