{
  "type": "Feature",
  "properties": {
    "addr:full":"22 Catherine St Myola NSW 2540",
    "addr:housenumber":"22",
    "addr:postcode":"2540",
    "addr:street":"Catherine St",
    "iso:country":"AU",
    "sg:address":"22 Catherine St",
    "sg:city":"Myola",
    "sg:classifiers":[
        {
            "category":"Home & Garden",
            "subcategory":"Building Materials",
            "type":"Retail Goods"
        }
    ],
    "sg:phone":"+61 2 4446 5472",
    "sg:postcode":"2540",
    "sg:province":"NSW",
    "sg:tags":[
        "lawn",
        "cutting",
        "maintenance"
    ],
    "wof:name":"Culburra Lawn Mowing",
    "wof:placetype":"venue"
},
  "geometry": {"coordinates":[150.672119141,-35.0231323242],"type":"Point"}
}