{
  "type": "Feature",
  "properties": {
    "iso:country":"AU",
    "sg:address":"Warrego Hwy",
    "sg:city":"Hatton Vale",
    "sg:classifiers":[
        {
            "category":"Utilities",
            "subcategory":"Fuel Oil & Lpg",
            "type":"Services"
        }
    ],
    "sg:phone":"+61 7 5465 6519",
    "sg:postcode":"4341",
    "sg:province":"QLD",
    "sg:tags":[
        "merchant"
    ],
    "wof:name":"Zischke Fuel Supplies",
    "wof:placetype":"venue"
},
  "geometry": {"coordinates":[152.467086792,-27.5652351379],"type":"Point"}
}