{
  "type": "Feature",
  "properties": {
    "addr:full":"42 Reilly St Ringwood VIC 3134",
    "addr:housenumber":"42",
    "addr:postcode":"3134",
    "addr:street":"Reilly St",
    "iso:country":"AU",
    "sg:address":"42 Reilly St",
    "sg:city":"Ringwood",
    "sg:classifiers":[
        {
            "category":"Personal",
            "type":"Services"
        }
    ],
    "sg:phone":"+61 417 148 380",
    "sg:postcode":"3134",
    "sg:province":"VIC",
    "sg:tags":[
        "career",
        "counselling"
    ],
    "wof:name":"Rainbow Lorikeet Services",
    "wof:placetype":"venue"
},
  "geometry": {"coordinates":[145.23434448200001,-37.8265037537],"type":"Point"}
}