{
  "type": "Feature",
  "properties": {
    "addr:full":"444 Kiewa St Albury NSW 2640",
    "addr:housenumber":"444",
    "addr:postcode":"2640",
    "addr:street":"Kiewa St",
    "iso:country":"AU",
    "sg:address":"444 Kiewa St",
    "sg:city":"Albury",
    "sg:classifiers":[
        {
            "category":"Education",
            "subcategory":"School",
            "type":"Public Place"
        }
    ],
    "sg:phone":"+61 2 6021 4464",
    "sg:postcode":"2640",
    "sg:province":"NSW",
    "wof:name":"St Patrick's Parish School",
    "wof:placetype":"venue"
},
  "geometry": {"coordinates":[146.91603088400001,-36.0795288086],"type":"Point"}
}