{
  "type": "Feature",
  "properties": {
    "addr:full":"Shop 4, Old Argyle Square 256 Argyle St Moss Vale NSW 2577",
    "addr:housenumber":"shop 4;256",
    "addr:postcode":"2577",
    "addr:street":"Old Argyle;Argyle St",
    "iso:country":"AU",
    "sg:address":"Shop 4, Old Argyle Square 256 Argyle St",
    "sg:city":"Moss Vale",
    "sg:classifiers":[
        {
            "category":"Health Services",
            "subcategory":"Optometrist",
            "type":"Services"
        }
    ],
    "sg:phone":"+61 2 4869 1648",
    "sg:postcode":"2577",
    "sg:province":"NSW",
    "wof:name":"Hircock, Gary",
    "wof:placetype":"venue"
},
  "geometry": {"coordinates":[150.374465942,-34.5469245911],"type":"Point"}
}