{
  "type": "Feature",
  "properties": {
    "addr:full":"13 Emily Ave Clapham SA 5062",
    "addr:housenumber":"13",
    "addr:postcode":"5062",
    "addr:street":"Emily Ave",
    "iso:country":"AU",
    "sg:address":"13 Emily Ave",
    "sg:city":"Clapham",
    "sg:classifiers":[
        {
            "category":"Education",
            "subcategory":"Music School",
            "type":"Public Place"
        }
    ],
    "sg:phone":"+61 8 8378 2972",
    "sg:postcode":"5062",
    "sg:province":"SA",
    "sg:tags":[
        "teacher"
    ],
    "wof:name":"Anna Essipoff Piano School",
    "wof:placetype":"venue"
},
  "geometry": {"coordinates":[138.605392456,-34.9867172241],"type":"Point"}
}