{
  "type": "Feature",
  "properties": {
    "iso:country":"AU",
    "sg:address":"Shop 1/ 125 Park Rd",
    "sg:city":"Rydalmere",
    "sg:classifiers":[
        {
            "category":"Professional",
            "subcategory":"Employment Agencies",
            "type":"Services"
        }
    ],
    "sg:phone":"+61 2 9638 5035",
    "sg:postcode":"2116",
    "sg:province":"NSW",
    "sg:tags":[
        "provider",
        "internet"
    ],
    "wof:name":"HCR Computer Services",
    "wof:placetype":"venue"
},
  "geometry": {"coordinates":[151.043060303,-33.8066482544],"type":"Point"}
}