{
  "type": "Feature",
  "properties": {
    "iso:country":"AU",
    "sg:address":"110 Ferndale St",
    "sg:city":"Annerley",
    "sg:classifiers":[
        {
            "category":"Health Services",
            "subcategory":"Health Practitioner",
            "type":"Services"
        }
    ],
    "sg:phone":"+61 7 3217 1865",
    "sg:postcode":"4103",
    "sg:province":"QLD",
    "sg:tags":[
        "physiotherapist"
    ],
    "wof:name":"T F P Group Pty Ltd",
    "wof:placetype":"venue"
},
  "geometry": {"coordinates":[153.03527832,-27.5177001953],"type":"Point"}
}