{
  "type": "Feature",
  "properties": {
    "iso:country":"AU",
    "sg:address":"Unit 1/ 21 Brendan Drv",
    "sg:city":"Nerang",
    "sg:classifiers":[
        {
            "category":"Home & Garden",
            "subcategory":"Building Materials",
            "type":"Retail Goods"
        }
    ],
    "sg:phone":"+61 7 5502 0744",
    "sg:postcode":"4211",
    "sg:province":"QLD",
    "sg:tags":[
        "merchant",
        "glass",
        "glazier"
    ],
    "wof:name":"In Glass Design",
    "wof:placetype":"venue"
},
  "geometry": {"coordinates":[153.34356689399999,-27.998626709],"type":"Point"}
}