{
  "type": "Feature",
  "properties": {
    "iso:country":"AU",
    "sg:address":"3/37 Township Drv",
    "sg:city":"West Burleigh",
    "sg:classifiers":[
        {
            "category":"Education",
            "subcategory":"Dance Studio",
            "type":"Public Place"
        }
    ],
    "sg:phone":"+61 439 749 871",
    "sg:postcode":"4219",
    "sg:province":"QLD",
    "sg:tags":[
        "venue",
        "tuition"
    ],
    "wof:name":"Streetbeat Dance School",
    "wof:placetype":"venue"
},
  "geometry": {"coordinates":[153.43466186500001,-28.1126823425],"type":"Point"}
}