{
  "type": "Feature",
  "properties": {
    "iso:country":"AU",
    "sg:address":"Suite 12 Weippin St",
    "sg:city":"Cleveland",
    "sg:classifiers":[
        {
            "category":"Health Services",
            "subcategory":"Doctor",
            "type":"Services"
        }
    ],
    "sg:phone":"+61 7 3344 5777",
    "sg:postcode":"4163",
    "sg:province":"QLD",
    "sg:tags":[
        "medical",
        "practitioner"
    ],
    "wof:name":"Seto Wei Dr",
    "wof:placetype":"venue"
},
  "geometry": {"coordinates":[153.25079345699999,-27.5413951874],"type":"Point"}
}