{
  "type": "Feature",
  "properties": {
    "iso:country":"AU",
    "sg:address":"11 Lakewood Drv",
    "sg:city":"Burpengary",
    "sg:classifiers":[
        {
            "category":"Home & Garden",
            "subcategory":"Building Materials",
            "type":"Retail Goods"
        }
    ],
    "sg:phone":"+61 7 3888 0748",
    "sg:postcode":"4505",
    "sg:province":"QLD",
    "sg:tags":[
        "lawn",
        "cutting",
        "maintenance"
    ],
    "wof:name":"R T Landscapes",
    "wof:placetype":"venue"
},
  "geometry": {"coordinates":[153.002563477,-27.1613082886],"type":"Point"}
}