{
  "type": "Feature",
  "properties": {
    "addr:full":"Frome Rd Adelaide SA 5000",
    "addr:postcode":"5000",
    "addr:street":"Frome Rd",
    "iso:country":"AU",
    "sg:address":"Frome Rd",
    "sg:city":"Adelaide",
    "sg:classifiers":[
        {
            "category":"Health Services",
            "subcategory":"Medical Lab",
            "type":"Services"
        }
    ],
    "sg:phone":"+61 8 8222 3000",
    "sg:postcode":"5000",
    "sg:province":"SA",
    "sg:tags":[
        "laboratory",
        "pathology"
    ],
    "sg:website":"http://www.imvs.sa.gov.au",
    "wof:name":"Institute Of Medical & Veterinary Science",
    "wof:placetype":"venue"
},
  "geometry": {"coordinates":[138.60780334500001,-34.9211273193],"type":"Point"}
}