{
  "type": "Feature",
  "properties": {
    "addr:full":"P.O.Box 518 Kippax Kippax ACT 2615",
    "addr:housenumber":"518",
    "addr:postcode":"2615",
    "addr:street":"P.O.Box",
    "iso:country":"AU",
    "sg:address":"P.O.Box 518 Kippax",
    "sg:city":"Kippax",
    "sg:classifiers":[
        {
            "category":"Education",
            "subcategory":"Music School",
            "type":"Public Place"
        }
    ],
    "sg:phone":"+61 2 6259 7171",
    "sg:postcode":"2615",
    "sg:province":"ACT",
    "sg:tags":[
        "choir",
        "bands",
        "orchestra"
    ],
    "wof:name":"Ginninderra Wind Orchestra",
    "wof:placetype":"venue"
},
  "geometry": {"coordinates":[149.02017211899999,-35.2236442566],"type":"Point"}
}