{
  "type": "Feature",
  "properties": {
    "addr:full":"211 Nicholls Rivulet Rd Oyster Cove TAS 7150",
    "addr:housenumber":"211",
    "addr:postcode":"7150",
    "addr:street":"Nicholls Rivulet Rd",
    "iso:country":"AU",
    "sg:address":"211 Nicholls Rivulet Rd",
    "sg:city":"Oyster Cove",
    "sg:classifiers":[
        {
            "category":"Retail",
            "subcategory":"Auto Repair",
            "type":"Services"
        }
    ],
    "sg:phone":"+61 407 873 127",
    "sg:postcode":"7150",
    "sg:province":"TAS",
    "sg:tags":[
        "camper-trailers",
        "caravan",
        "servicing"
    ],
    "wof:name":"Devine Upholstery & Foam",
    "wof:placetype":"venue"
},
  "geometry": {"coordinates":[147.22329711899999,-43.1042861938],"type":"Point"}
}