{
  "type": "Feature",
  "properties": {
    "addr:full":"Lot 56 Arthur Rd Walkaway WA 6528",
    "addr:housenumber":"56",
    "addr:postcode":"6528",
    "addr:street":"Arthur Rd",
    "iso:country":"AU",
    "sg:address":"Lot 56 Arthur Rd",
    "sg:city":"Walkaway",
    "sg:classifiers":[
        {
            "category":"Building & Trades",
            "subcategory":"Construction",
            "type":"Services"
        }
    ],
    "sg:phone":"+61 427 261 301",
    "sg:postcode":"6528",
    "sg:province":"WA",
    "sg:tags":[
        "fencing",
        "contractor"
    ],
    "wof:name":"Walkaway Fencing",
    "wof:placetype":"venue"
},
  "geometry": {"coordinates":[114.80547332800001,-28.9385795593],"type":"Point"}
}