{
  "type": "Feature",
  "properties": {
    "addr:full":"RMB 150 Red Cliffs VIC 3496",
    "addr:postcode":"3496",
    "iso:country":"AU",
    "sg:address":"RMB 150",
    "sg:city":"Red Cliffs",
    "sg:classifiers":[
        {
            "category":"Farming",
            "subcategory":"Vineyard",
            "type":"Manufacturing & Wholesale Goods"
        }
    ],
    "sg:phone":"+61 3 5024 1203",
    "sg:postcode":"3496",
    "sg:province":"VIC",
    "sg:tags":[
        "winery"
    ],
    "wof:name":"Thurla Farms",
    "wof:placetype":"venue"
},
  "geometry": {"coordinates":[142.18652343799999,-34.3077087402],"type":"Point"}
}