{
  "type": "Feature",
  "properties": {
    "iso:country":"AU",
    "sg:address":"1310 Plenty Rd",
    "sg:city":"Bundoora",
    "sg:classifiers":[
        {
            "category":"Manufacturing",
            "subcategory":"Food",
            "type":"Manufacturing & Wholesale Goods"
        }
    ],
    "sg:phone":"+61 3 9467 9399",
    "sg:postcode":"3083",
    "sg:province":"VIC",
    "sg:tags":[
        "function",
        "catering"
    ],
    "wof:name":"Feed A Crowd",
    "wof:placetype":"venue"
},
  "geometry": {"coordinates":[145.05874633799999,-37.6993331909],"type":"Point"}
}