{
  "type": "Feature",
  "properties": {
    "iso:country":"AU",
    "sg:address":"Tregarthen Rd",
    "sg:city":"Summertown",
    "sg:classifiers":[
        {
            "category":"Professional",
            "subcategory":"Accounting & Tax Preparation",
            "type":"Services"
        }
    ],
    "sg:phone":"+61 8 8390 1477",
    "sg:postcode":"5141",
    "sg:province":"SA",
    "sg:tags":[
        "bookkeeping"
    ],
    "wof:name":"Berwick Bookkeeping Service",
    "wof:placetype":"venue"
},
  "geometry": {"coordinates":[138.72781372099999,-34.9572944641],"type":"Point"}
}