{
  "type": "Feature",
  "properties": {
    "addr:full":"45- 55 Epsom Rd Rosebery NSW 2018",
    "addr:housenumber":"55",
    "addr:postcode":"2018",
    "addr:street":"Epsom Rd",
    "iso:country":"AU",
    "sg:address":"45- 55 Epsom Rd",
    "sg:city":"Rosebery",
    "sg:classifiers":[
        {
            "category":"Arts & Performance",
            "subcategory":"Theater",
            "type":"Entertainment"
        }
    ],
    "sg:phone":"+61 2 9663 5155",
    "sg:postcode":"2018",
    "sg:province":"NSW",
    "sg:tags":[
        "theatrical",
        "supply"
    ],
    "wof:name":"StageRig Pty Ltd",
    "wof:placetype":"venue"
},
  "geometry": {"coordinates":[151.20782470699999,-33.9110183716],"type":"Point"}
}