{
  "type": "Feature",
  "properties": {
    "iso:country":"AU",
    "sg:address":"Flame Crs",
    "sg:city":"Macquarie Fields",
    "sg:classifiers":[
        {
            "category":"Education",
            "subcategory":"Kindergarten",
            "type":"Public Place"
        }
    ],
    "sg:phone":"+61 2 9605 4679",
    "sg:postcode":"2564",
    "sg:province":"NSW",
    "sg:tags":[
        "pre-schools"
    ],
    "wof:name":"Ku Children's Services",
    "wof:placetype":"venue"
},
  "geometry": {"coordinates":[150.893707275,-33.985660553],"type":"Point"}
}