{
  "type": "Feature",
  "properties": {
    "addr:full":"171 Briens Rd Northmead NSW 2152",
    "addr:housenumber":"171",
    "addr:postcode":"2152",
    "addr:street":"Briens Rd",
    "iso:country":"AU",
    "sg:address":"171 Briens Rd",
    "sg:city":"Northmead",
    "sg:classifiers":[
        {
            "category":"Home & Garden",
            "subcategory":"Carpets & Floor Coverings",
            "type":"Retail Goods"
        }
    ],
    "sg:phone":"+61 2 8838 2500",
    "sg:postcode":"2152",
    "sg:province":"NSW",
    "wof:name":"Ontera Modular Carpets Pty Ltd",
    "wof:placetype":"venue"
},
  "geometry": {"coordinates":[150.983352661,-33.7983055115],"type":"Point"}
}