{
  "type": "Feature",
  "properties": {
    "addr:full":"53 Upper Regions St Dimboola VIC 3414",
    "addr:housenumber":"53",
    "addr:postcode":"3414",
    "addr:street":"Upper Regions St",
    "iso:country":"AU",
    "sg:address":"53 Upper Regions St",
    "sg:city":"Dimboola",
    "sg:classifiers":[
        {
            "category":"Professional",
            "subcategory":"Engineering",
            "type":"Services"
        }
    ],
    "sg:phone":"+61 3 5389 1025",
    "sg:postcode":"3414",
    "sg:province":"VIC",
    "sg:tags":[
        "engineer"
    ],
    "wof:name":"T F W Engineering Pty Ltd",
    "wof:placetype":"venue"
},
  "geometry": {"coordinates":[142.03431701700001,-36.4553337097],"type":"Point"}
}