{
  "type": "Feature",
  "properties": {
    "addr:full":"2/ 54 Turbo Drv Coorparoo QLD 4151",
    "addr:housenumber":"/ 54",
    "addr:postcode":"4151",
    "addr:street":"Turbo Drv",
    "iso:country":"AU",
    "sg:address":"2/ 54 Turbo Drv",
    "sg:city":"Coorparoo",
    "sg:classifiers":[
        {
            "category":"Utilities",
            "subcategory":"Refuse",
            "type":"Services"
        }
    ],
    "sg:phone":"+61 7 3392 4011",
    "sg:postcode":"4151",
    "sg:province":"QLD",
    "sg:tags":[
        "wholesale",
        "glassware",
        "china",
        "earthenware"
    ],
    "sg:website":"http://www.swannagencies.com.au",
    "wof:name":"Swann Agencies",
    "wof:placetype":"venue"
},
  "geometry": {"coordinates":[153.04914855999999,-27.492433548],"type":"Point"}
}