{
  "type": "Feature",
  "properties": {
    "iso:country":"AU",
    "sg:address":"312 - 314 Parramatta Rd",
    "sg:city":"Stanmore",
    "sg:classifiers":[
        {
            "category":"Professional",
            "type":"Services"
        }
    ],
    "sg:phone":"+61 2 9568 1633",
    "sg:postcode":"2048",
    "sg:province":"NSW",
    "sg:tags":[
        "shop",
        "fitting"
    ],
    "wof:name":"WU's International Development",
    "wof:placetype":"venue"
},
  "geometry": {"coordinates":[151.16369599999999,-33.888374],"type":"Point"}
}