{
  "type": "Feature",
  "properties": {
    "addr:full":"890 Bessie Creek Rd Nar Nar Goon VIC 3812",
    "addr:housenumber":"890",
    "addr:postcode":"3812",
    "addr:street":"Bessie Creek Rd",
    "iso:country":"AU",
    "sg:address":"890 Bessie Creek Rd",
    "sg:city":"Nar Nar Goon",
    "sg:classifiers":[
        {
            "category":"Retail",
            "subcategory":"Storage",
            "type":"Services"
        }
    ],
    "sg:phone":"+61 3 5941 5200",
    "sg:postcode":"3812",
    "sg:province":"VIC",
    "sg:tags":[
        "removal",
        "furniture"
    ],
    "wof:name":"Rainbow Moving & Storage",
    "wof:placetype":"venue"
},
  "geometry": {"coordinates":[145.54589799999999,-38.000961],"type":"Point"}
}