{
  "type": "Feature",
  "properties": {
    "iso:country":"AU",
    "sg:address":"291 Milperra Rd",
    "sg:city":"Revesby",
    "sg:classifiers":[
        {
            "category":"Manufacturing",
            "subcategory":"Tools & Machinery",
            "type":"Manufacturing & Wholesale Goods"
        }
    ],
    "sg:phone":"+61 2 9792 2733",
    "sg:postcode":"2212",
    "sg:province":"NSW",
    "sg:tags":[
        "abrasive"
    ],
    "wof:name":"Burwell Abrasive Equipment",
    "wof:placetype":"venue"
},
  "geometry": {"coordinates":[151.019073,-33.938255],"type":"Point"}
}