{
  "type": "Feature",
  "properties": {
    "iso:country":"AU",
    "sg:address":"26 Paterson St",
    "sg:city":"Parkes",
    "sg:classifiers":[
        {
            "category":"Personal",
            "type":"Services"
        }
    ],
    "sg:phone":"+61 2 6862 3829",
    "sg:postcode":"2870",
    "sg:province":"NSW",
    "sg:tags":[
        "dressmaker"
    ],
    "wof:name":"Lyn Townsend",
    "wof:placetype":"venue"
},
  "geometry": {"coordinates":[148.171494,-33.149052],"type":"Point"}
}