{
  "type": "Feature",
  "properties": {
    "addr:full":"70 First Ave Sawtell NSW 2452",
    "addr:housenumber":"70",
    "addr:postcode":"2452",
    "addr:street":"First Ave",
    "iso:country":"AU",
    "sg:address":"70 First Ave",
    "sg:city":"Sawtell",
    "sg:classifiers":[
        {
            "category":"Personal",
            "subcategory":"Beauty Salon",
            "type":"Services"
        }
    ],
    "sg:phone":"+61 2 6658 1022",
    "sg:postcode":"2452",
    "sg:province":"NSW",
    "sg:tags":[
        "hairdresser"
    ],
    "wof:name":"Surfside Salon",
    "wof:placetype":"venue"
},
  "geometry": {"coordinates":[153.10093699999999,-30.367668],"type":"Point"}
}