{
  "type": "Feature",
  "properties": {
    "addr:full":"43- 47 Edgecombe St Kyneton VIC 3444",
    "addr:housenumber":"47",
    "addr:postcode":"3444",
    "addr:street":"Edgecombe St",
    "iso:country":"AU",
    "sg:address":"43- 47 Edgecombe St",
    "sg:city":"Kyneton",
    "sg:classifiers":[
        {
            "category":"Education",
            "subcategory":"School",
            "type":"Public Place"
        }
    ],
    "sg:phone":"+61 3 5422 2056",
    "sg:postcode":"3444",
    "sg:province":"VIC",
    "wof:name":"Our Lady of The Rosary Parish Primary School",
    "wof:placetype":"venue"
},
  "geometry": {"coordinates":[144.46220398,-37.2511558533],"type":"Point"}
}