{
  "type": "Feature",
  "properties": {
    "iso:country":"AU",
    "sg:address":"720 Sandfly Rd",
    "sg:city":"Sandfly",
    "sg:classifiers":[
        {
            "category":"Autos & Motor Vehicles",
            "subcategory":"Fuel & Gas Station",
            "type":"Retail Goods"
        }
    ],
    "sg:phone":"+61 3 6239 6643",
    "sg:postcode":"7150",
    "sg:province":"TAS",
    "wof:name":"Caltex Sandfly",
    "wof:placetype":"venue"
},
  "geometry": {"coordinates":[147.19984435999999,-42.9925422668],"type":"Point"}
}