{
  "type": "Feature",
  "properties": {
    "iso:country":"AU",
    "sg:address":"Main St Arcade 85 Lake St",
    "sg:city":"Cairns",
    "sg:classifiers":[
        {
            "category":"Personal",
            "subcategory":"Day Spa",
            "type":"Services"
        }
    ],
    "sg:phone":"+61 7 4051 8344",
    "sg:postcode":"4870",
    "sg:province":"QLD",
    "sg:website":"http://www.refreshcitydayspa.com.au",
    "wof:name":"Refresh City Day Spa",
    "wof:placetype":"venue"
},
  "geometry": {"coordinates":[145.776412964,-16.9230213165],"type":"Point"}
}