{
  "type": "Feature",
  "properties": {
    "addr:full":"Cnr Barrenjoey Rd & Avalon Pde Avalon NSW 2107",
    "addr:postcode":"2107",
    "addr:street":"Cnr Barrenjoey Rd & Avalon Pde",
    "iso:country":"AU",
    "sg:address":"Cnr Barrenjoey Rd & Avalon Pde",
    "sg:city":"Avalon",
    "sg:classifiers":[
        {
            "category":"Autos & Motor Vehicles",
            "subcategory":"Fuel & Gas Station",
            "type":"Retail Goods"
        }
    ],
    "sg:phone":"+61 2 9918 3249",
    "sg:postcode":"2107",
    "sg:province":"NSW",
    "wof:name":"Shell Avalon Self Serve",
    "wof:placetype":"venue"
},
  "geometry": {"coordinates":[151.33172607399999,-33.6286430359],"type":"Point"}
}