{
  "type": "Feature",
  "properties": {
    "iso:country":"AU",
    "sg:address":"32 Norton Drv",
    "sg:city":"Shailer Park",
    "sg:classifiers":[
        {
            "category":"Insurance",
            "subcategory":"Insurance Agent",
            "type":"Services"
        }
    ],
    "sg:phone":"+61 7 3806 2244",
    "sg:postcode":"4128",
    "sg:province":"QLD",
    "sg:tags":[
        "broker"
    ],
    "wof:name":"Linq Insurance Brokers Pty Ltd",
    "wof:placetype":"venue"
},
  "geometry": {"coordinates":[153.16969299300001,-27.65284729],"type":"Point"}
}