{
  "type": "Feature",
  "properties": {
    "iso:country":"AU",
    "sg:address":"181 George St",
    "sg:city":"Bathurst",
    "sg:classifiers":[
        {
            "category":"Shopping",
            "subcategory":"Music",
            "type":"Retail Goods"
        }
    ],
    "sg:phone":"+61 2 6332 3322",
    "sg:postcode":"2795",
    "sg:province":"NSW",
    "sg:tags":[
        "instrument",
        "musical"
    ],
    "wof:name":"Day-Hakker Pianos",
    "wof:placetype":"venue"
},
  "geometry": {"coordinates":[149.57696533199999,-33.4176940918],"type":"Point"}
}