{
  "type": "Feature",
  "properties": {
    "addr:full":"194a Chandlers Hill Rd Happy Valley SA 5159",
    "addr:housenumber":"194a",
    "addr:postcode":"5159",
    "addr:street":"Chandlers Hill Rd",
    "iso:country":"AU",
    "sg:address":"194a Chandlers Hill Rd",
    "sg:city":"Happy Valley",
    "sg:classifiers":[
        {
            "category":"Health Services",
            "subcategory":"Doctor",
            "type":"Services"
        }
    ],
    "sg:phone":"+61 8 8381 2822",
    "sg:postcode":"5159",
    "sg:province":"SA",
    "sg:tags":[
        "medical",
        "practitioner"
    ],
    "wof:name":"Chen Rachel",
    "wof:placetype":"venue"
},
  "geometry": {"coordinates":[138.58744812,-35.0868606567],"type":"Point"}
}