{
  "type": "Feature",
  "properties": {
    "addr:full":"154 Hannell St Wickham NSW 2293",
    "addr:housenumber":"154",
    "addr:postcode":"2293",
    "addr:street":"Hannell St",
    "iso:country":"AU",
    "sg:address":"154 Hannell St",
    "sg:city":"Wickham",
    "sg:classifiers":[
        {
            "category":"Banks & Credit Unions",
            "subcategory":"Bureau De Change",
            "type":"Services"
        }
    ],
    "sg:phone":"+61 2 4962 2333",
    "sg:postcode":"2293",
    "sg:province":"NSW",
    "sg:tags":[
        "wheel",
        "industrial"
    ],
    "wof:name":"Flexello",
    "wof:placetype":"venue"
},
  "geometry": {"coordinates":[151.75787353499999,-32.9157180786],"type":"Point"}
}