{
  "type": "Feature",
  "properties": {
    "addr:full":"312 Spencer Rd Thornlie WA 6108",
    "addr:housenumber":"312",
    "addr:postcode":"6108",
    "addr:street":"Spencer Rd",
    "iso:country":"AU",
    "sg:address":"312 Spencer Rd",
    "sg:city":"Thornlie",
    "sg:classifiers":[
        {
            "category":"Health Services",
            "subcategory":"Chiropractor",
            "type":"Services"
        }
    ],
    "sg:phone":"+61 8 9452 3432",
    "sg:postcode":"6108",
    "sg:province":"WA",
    "wof:name":"Thornlie Huntingdale Chiropractic Centre",
    "wof:placetype":"venue"
},
  "geometry": {"coordinates":[115.96125793500001,-32.0549888611],"type":"Point"}
}