{
  "type": "Feature",
  "properties": {
    "addr:full":"60 Toolooa St Gladstone QLD 4680",
    "addr:housenumber":"60",
    "addr:postcode":"4680",
    "addr:street":"Toolooa St",
    "iso:country":"AU",
    "sg:address":"60 Toolooa St",
    "sg:city":"Gladstone",
    "sg:classifiers":[
        {
            "category":"Retail",
            "subcategory":"Repair Shop",
            "type":"Services"
        }
    ],
    "sg:phone":"+61 7 4972 3252",
    "sg:postcode":"4680",
    "sg:province":"QLD",
    "sg:tags":[
        "upholsterer"
    ],
    "wof:name":"Henden's Upholstery & Canvas",
    "wof:placetype":"venue"
},
  "geometry": {"coordinates":[151.266723633,-23.8517303467],"type":"Point"}
}