{
  "type": "Feature",
  "properties": {
    "iso:country":"AU",
    "sg:address":"PO Box 89",
    "sg:city":"Armadale PLB",
    "sg:classifiers":[
        {
            "category":"Home & Garden",
            "subcategory":"Building Materials",
            "type":"Retail Goods"
        }
    ],
    "sg:phone":"+61 8 9497 1200",
    "sg:postcode":"6992",
    "sg:province":"WA",
    "sg:tags":[
        "merchant",
        "glass",
        "glazier"
    ],
    "wof:name":"Metro Glassworks",
    "wof:placetype":"venue"
},
  "geometry": {"coordinates":[116.00827,-32.15239],"type":"Point"}
}