{
  "type": "Feature",
  "properties": {
    "iso:country":"AU",
    "sg:address":"Unit 1/1088 Heatherton Rd",
    "sg:city":"Noble Park",
    "sg:classifiers":[
        {
            "category":"Home & Garden",
            "subcategory":"Building Materials",
            "type":"Retail Goods"
        }
    ],
    "sg:phone":"+61 3 9548 4488",
    "sg:postcode":"3174",
    "sg:province":"VIC",
    "sg:tags":[
        "lawn",
        "cutting",
        "maintenance"
    ],
    "wof:name":"Renewitt Maintenance Services",
    "wof:placetype":"venue"
},
  "geometry": {"coordinates":[145.182006836,-37.9661178589],"type":"Point"}
}