{
  "type": "Feature",
  "properties": {
    "addr:full":"Suite 5 O'Connor Professional Chambers Sargood St O'Connor ACT 2602",
    "addr:postcode":"2602",
    "addr:street":"Sargood St",
    "iso:country":"AU",
    "sg:address":"Suite 5 O'Connor Professional Chambers Sargood St",
    "sg:city":"O'Connor",
    "sg:classifiers":[
        {
            "category":"Personal",
            "subcategory":"Massage",
            "type":"Services"
        }
    ],
    "sg:phone":"+61 2 6257 8373",
    "sg:postcode":"2602",
    "sg:province":"ACT",
    "sg:tags":[
        "therapy"
    ],
    "wof:name":"Inner North Massage",
    "wof:placetype":"venue"
},
  "geometry": {"coordinates":[149.12266540499999,-35.2641105652],"type":"Point"}
}