{
  "type": "Feature",
  "properties": {
    "iso:country":"AU",
    "sg:address":"Shop 1- 13 Inverloch Rd",
    "sg:city":"Wonthaggi",
    "sg:classifiers":[
        {
            "category":"Utilities",
            "type":"Services"
        }
    ],
    "sg:phone":"+61 3 5672 2426",
    "sg:postcode":"3995",
    "sg:province":"VIC",
    "sg:tags":[
        "refrigeration",
        "industrial",
        "commercial",
        "retail"
    ],
    "wof:name":"Bass Coast Refrigeration & Electrical",
    "wof:placetype":"venue"
},
  "geometry": {"coordinates":[145.603104,-38.606178],"type":"Point"}
}