{
  "type": "Feature",
  "properties": {
    "addr:full":"405 Victoria St Brunswick VIC 3055",
    "addr:housenumber":"405",
    "addr:postcode":"3055",
    "addr:street":"Victoria St",
    "iso:country":"AU",
    "sg:address":"405 Victoria St",
    "sg:city":"Brunswick",
    "sg:classifiers":[
        {
            "category":"Shopping",
            "type":"Retail Goods"
        }
    ],
    "sg:phone":"+61 3 9380 2133",
    "sg:postcode":"3055",
    "sg:province":"VIC",
    "sg:tags":[
        "product",
        "plastic"
    ],
    "wof:name":"Hongfa International Australia Pty Ltd",
    "wof:placetype":"venue"
},
  "geometry": {"coordinates":[144.954910278,-37.7660217285],"type":"Point"}
}