{
  "type": "Feature",
  "properties": {
    "iso:country":"AU",
    "sg:address":"602 Eureka St",
    "sg:city":"Ballarat East",
    "sg:classifiers":[
        {
            "category":"Restaurant",
            "type":"Food & Drink"
        }
    ],
    "sg:phone":"+61 3 5332 2122",
    "sg:postcode":"3350",
    "sg:province":"VIC",
    "wof:name":"Deeva Indian Restaurant",
    "wof:placetype":"venue"
},
  "geometry": {"coordinates":[143.88653600000001,-37.565769],"type":"Point"}
}