{
  "type": "Feature",
  "properties": {
    "addr:full":"Shop 3, 81 Gympie Rd Kedron QLD 4031",
    "addr:housenumber":"shop;81",
    "addr:postcode":"4031",
    "addr:street":"Gympie Rd",
    "iso:country":"AU",
    "sg:address":"Shop 3, 81 Gympie Rd",
    "sg:city":"Kedron",
    "sg:classifiers":[
        {
            "category":"Shopping",
            "subcategory":"Clothing, Apparel, & Fashions",
            "type":"Retail Goods"
        }
    ],
    "sg:phone":"+61 7 3357 5111",
    "sg:postcode":"4031",
    "sg:province":"QLD",
    "sg:tags":[
        "hire",
        "men's",
        "wear",
        "formal"
    ],
    "wof:name":"Calabro Formal Wear",
    "wof:placetype":"venue"
},
  "geometry": {"coordinates":[153.033905,-27.412779],"type":"Point"}
}