{
  "type": "Feature",
  "properties": {
    "addr:full":"8 Wunnunga Crs Coolum Beach QLD 4573",
    "addr:housenumber":"8",
    "addr:postcode":"4573",
    "addr:street":"Wunnunga Crs",
    "iso:country":"AU",
    "sg:address":"8 Wunnunga Crs",
    "sg:city":"Coolum Beach",
    "sg:classifiers":[
        {
            "category":"Building & Trades",
            "subcategory":"Construction",
            "type":"Services"
        }
    ],
    "sg:phone":"+61 7 5446 2642",
    "sg:postcode":"4573",
    "sg:province":"QLD",
    "sg:tags":[
        "contractor"
    ],
    "wof:name":"Hatfull Homes M & K Pty Ltd",
    "wof:placetype":"venue"
},
  "geometry": {"coordinates":[153.07545500000001,-26.53541],"type":"Point"}
}