{
  "type": "Feature",
  "properties": {
    "addr:full":"7 Dublin St Capalaba QLD 4157",
    "addr:housenumber":"7",
    "addr:postcode":"4157",
    "addr:street":"Dublin St",
    "iso:country":"AU",
    "sg:address":"7 Dublin St",
    "sg:city":"Capalaba",
    "sg:classifiers":[
        {
            "category":"Professional",
            "subcategory":"Computer Services",
            "type":"Services"
        }
    ],
    "sg:phone":"+61 7 3245 1029",
    "sg:postcode":"4157",
    "sg:province":"QLD",
    "sg:tags":[
        "training"
    ],
    "wof:name":"EDI Computers",
    "wof:placetype":"venue"
},
  "geometry": {"coordinates":[153.185424805,-27.5321235657],"type":"Point"}
}