{
  "type": "Feature",
  "properties": {
    "addr:full":"67 Frankston-Dandenong Rd Dandenong VIC 3175",
    "addr:housenumber":"67",
    "addr:postcode":"3175",
    "addr:street":"Frankston-Dandenong Rd",
    "iso:country":"AU",
    "sg:address":"67 Frankston-Dandenong Rd",
    "sg:city":"Dandenong",
    "sg:classifiers":[
        {
            "category":"Professional",
            "type":"Services"
        }
    ],
    "sg:phone":"+61 3 9706 7717",
    "sg:postcode":"3175",
    "sg:province":"VIC",
    "sg:tags":[
        "transport"
    ],
    "wof:name":"D T M Pty Ltd",
    "wof:placetype":"venue"
},
  "geometry": {"coordinates":[145.217453003,-38.0059204102],"type":"Point"}
}