{
  "type": "Feature",
  "properties": {
    "addr:full":"20 Danielle St Cleveland QLD 4163",
    "addr:housenumber":"20",
    "addr:postcode":"4163",
    "addr:street":"Danielle St",
    "iso:country":"AU",
    "sg:address":"20 Danielle St",
    "sg:city":"Cleveland",
    "sg:classifiers":[
        {
            "category":"Real Estate",
            "subcategory":"Real Estate Operator",
            "type":"Services"
        }
    ],
    "sg:phone":"+61 428 248 295",
    "sg:postcode":"4163",
    "sg:province":"QLD",
    "sg:tags":[
        "concrete",
        "pumping"
    ],
    "wof:name":"Geoff Langham Concrete Pumping",
    "wof:placetype":"venue"
},
  "geometry": {"coordinates":[153.26918029800001,-27.5355796814],"type":"Point"}
}