{
  "type": "Feature",
  "properties": {
    "iso:country":"AU",
    "sg:address":"Shop 1 42 Aerodrome Rd",
    "sg:city":"Caboolture",
    "sg:classifiers":[
        {
            "category":"Fast Food",
            "type":"Food & Drink"
        }
    ],
    "sg:phone":"+61 7 5495 7981",
    "sg:postcode":"4510",
    "sg:province":"QLD",
    "sg:tags":[
        "away",
        "take"
    ],
    "wof:name":"Tarmac Take Away",
    "wof:placetype":"venue"
},
  "geometry": {"coordinates":[152.981003,-27.081917],"type":"Point"}
}