{
  "type": "Feature",
  "properties": {
    "iso:country":"AU",
    "sg:address":"21 A Jackson St",
    "sg:city":"Forest Hill",
    "sg:classifiers":[
        {
            "category":"Travel",
            "subcategory":"Hotels & Motels",
            "type":"Entertainment"
        }
    ],
    "sg:phone":"+61 3 9877 4849",
    "sg:postcode":"3131",
    "sg:province":"VIC",
    "wof:name":"Chanleigh Corporate Accommodation",
    "wof:placetype":"venue"
},
  "geometry": {"coordinates":[145.160919189,-37.8384361267],"type":"Point"}
}