{
  "type": "Feature",
  "properties": {
    "addr:full":"409 Great North Rd Abbotsford NSW 2046",
    "addr:housenumber":"409",
    "addr:postcode":"2046",
    "addr:street":"Great North Rd",
    "iso:country":"AU",
    "sg:address":"409 Great North Rd",
    "sg:city":"Abbotsford",
    "sg:classifiers":[
        {
            "category":"Health Services",
            "subcategory":"Doctor",
            "type":"Services"
        }
    ],
    "sg:phone":"+61 2 9713 7988",
    "sg:postcode":"2046",
    "sg:province":"NSW",
    "sg:tags":[
        "medical",
        "practitioner"
    ],
    "wof:name":"Brettell Anthony Dr",
    "wof:placetype":"venue"
},
  "geometry": {"coordinates":[151.13031000000001,-33.855877],"type":"Point"}
}