{
  "type": "Feature",
  "properties": {
    "iso:country":"AU",
    "sg:address":"75 Mackie Rd",
    "sg:city":"Bentleigh East",
    "sg:classifiers":[
        {
            "category":"Food & Beverages",
            "subcategory":"Supermarket",
            "type":"Retail Goods"
        }
    ],
    "sg:phone":"+61 3 9570 2470",
    "sg:postcode":"3165",
    "sg:province":"VIC",
    "sg:tags":[
        "grocery",
        "store"
    ],
    "wof:name":"Foodtown",
    "wof:placetype":"venue"
},
  "geometry": {"coordinates":[145.07456970199999,-37.9154510498],"type":"Point"}
}