{
  "type": "Feature",
  "properties": {
    "iso:country":"AU",
    "sg:address":"Cnr Turner & Hughes Sts",
    "sg:city":"Leongatha",
    "sg:classifiers":[
        {
            "category":"Building & Trades",
            "subcategory":"Plumbing",
            "type":"Services"
        }
    ],
    "sg:phone":"+61 3 5662 2692",
    "sg:postcode":"3953",
    "sg:province":"VIC",
    "sg:tags":[
        "pump",
        "repairer"
    ],
    "wof:name":"Action Pumps And Irrigation",
    "wof:placetype":"venue"
},
  "geometry": {"coordinates":[145.982254028,-38.4433059692],"type":"Point"}
}