{
  "type": "Feature",
  "properties": {
    "addr:full":"26 Arcadia Drv Bundaberg QLD 4670",
    "addr:housenumber":"26",
    "addr:postcode":"4670",
    "addr:street":"Arcadia Drv",
    "iso:country":"AU",
    "sg:address":"26 Arcadia Drv",
    "sg:city":"Bundaberg",
    "sg:classifiers":[
        {
            "category":"Building & Trades",
            "subcategory":"Cleaning & Sanitation",
            "type":"Services"
        }
    ],
    "sg:phone":"+61 418 794 995",
    "sg:postcode":"4670",
    "sg:province":"QLD",
    "sg:tags":[
        "tank",
        "septic"
    ],
    "wof:name":"Keith Paap Plumbing & Cleansing Services",
    "wof:placetype":"venue"
},
  "geometry": {"coordinates":[152.287307739,-24.9100074768],"type":"Point"}
}