{
  "type": "Feature",
  "properties": {
    "addr:full":"PO Box 3038 Murray Bridge SA 5253",
    "addr:postcode":"5253",
    "iso:country":"AU",
    "sg:address":"PO Box 3038",
    "sg:city":"Murray Bridge",
    "sg:classifiers":[
        {
            "category":"Building & Trades",
            "subcategory":"Construction",
            "type":"Services"
        }
    ],
    "sg:phone":"+61 408 033 700",
    "sg:postcode":"5253",
    "sg:province":"SA",
    "sg:tags":[
        "plasterboard",
        "plasterer",
        "fixer"
    ],
    "wof:name":"Reed (Steven) Plasterboard",
    "wof:placetype":"venue"
},
  "geometry": {"coordinates":[139.282745361,-35.1072158813],"type":"Point"}
}