{
  "type": "Feature",
  "properties": {
    "iso:country":"AU",
    "sg:address":"98 Ayfield Rd",
    "sg:city":"Para Hills West",
    "sg:classifiers":[
        {
            "category":"Professional",
            "subcategory":"Accounting & Tax Preparation",
            "type":"Services"
        }
    ],
    "sg:phone":"+61 8 8258 7760",
    "sg:postcode":"5096",
    "sg:province":"SA",
    "sg:tags":[
        "consultant",
        "taxation"
    ],
    "wof:name":"Bailey E N",
    "wof:placetype":"venue"
},
  "geometry": {"coordinates":[138.64642334000001,-34.7950286865],"type":"Point"}
}