{
  "type": "Feature",
  "properties": {
    "addr:full":"28 Hillview Ave Toowoomba QLD 4350",
    "addr:housenumber":"28",
    "addr:postcode":"4350",
    "addr:street":"Hillview Ave",
    "iso:country":"AU",
    "sg:address":"28 Hillview Ave",
    "sg:city":"Toowoomba",
    "sg:classifiers":[
        {
            "category":"Organizations",
            "subcategory":"Professional Association",
            "type":"Services"
        }
    ],
    "sg:phone":"+61 415 332 799",
    "sg:postcode":"4350",
    "sg:province":"QLD",
    "sg:tags":[
        "web",
        "internet"
    ],
    "wof:name":"Interwarp Innovative Marketing",
    "wof:placetype":"venue"
},
  "geometry": {"coordinates":[151.943817,-27.549463],"type":"Point"}
}