{
  "type": "Feature",
  "properties": {
    "addr:full":"110 Goldie St Wynyard TAS 7325",
    "addr:housenumber":"110",
    "addr:postcode":"7325",
    "addr:street":"Goldie St",
    "iso:country":"AU",
    "sg:address":"110 Goldie St",
    "sg:city":"Wynyard",
    "sg:classifiers":[
        {
            "category":"Food & Beverages",
            "subcategory":"Supermarket",
            "type":"Retail Goods"
        }
    ],
    "sg:phone":"+61 3 6442 3023",
    "sg:postcode":"7325",
    "sg:province":"TAS",
    "sg:tags":[
        "grocery",
        "store"
    ],
    "wof:name":"Vos Supermarkets",
    "wof:placetype":"venue"
},
  "geometry": {"coordinates":[145.726562,-40.989677],"type":"Point"}
}