{
  "type": "Feature",
  "properties": {
    "iso:country":"AU",
    "sg:address":"Unit 8, 61 Frankston Gardens Drv",
    "sg:city":"Carrum Downs",
    "sg:classifiers":[
        {
            "category":"Wholesale",
            "subcategory":"Apparel",
            "type":"Manufacturing & Wholesale Goods"
        }
    ],
    "sg:phone":"+61 3 9770 8112",
    "sg:postcode":"3201",
    "sg:province":"VIC",
    "sg:tags":[
        "wholesaler",
        "mfrs",
        "uniform"
    ],
    "wof:name":"S.M Corporate & Workwear",
    "wof:placetype":"venue"
},
  "geometry": {"coordinates":[145.159546,-38.101322],"type":"Point"}
}