{
  "type": "Feature",
  "properties": {
    "iso:country":"AU",
    "sg:address":"62 Riviera Ave",
    "sg:city":"Terrigal",
    "sg:classifiers":[
        {
            "category":"Real Estate",
            "subcategory":"Developer",
            "type":"Services"
        }
    ],
    "sg:phone":"+61 2 4384 5066",
    "sg:postcode":"2260",
    "sg:province":"NSW",
    "sg:tags":[
        "development"
    ],
    "wof:name":"Wirth Henry P",
    "wof:placetype":"venue"
},
  "geometry": {"coordinates":[151.438995,-33.446186],"type":"Point"}
}