{
  "type": "Feature",
  "properties": {
    "iso:country":"AU",
    "sg:address":"61 Campbell St St",
    "sg:city":"Peters",
    "sg:classifiers":[
        {
            "category":"Arena",
            "subcategory":"Indoor Arena",
            "type":"Entertainment"
        }
    ],
    "sg:phone":"+61 2 9565 4518",
    "sg:postcode":"2044",
    "sg:province":"NSW",
    "sg:tags":[
        "modelmakers"
    ],
    "wof:name":"Acurate Models",
    "wof:placetype":"venue"
},
  "geometry": {"coordinates":[151.178543,-33.911674],"type":"Point"}
}