{
  "type": "Feature",
  "properties": {
    "iso:country":"AU",
    "sg:address":"30 Phillip St",
    "sg:city":"Parramatta",
    "sg:classifiers":[
        {
            "category":"Restaurant",
            "type":"Food & Drink"
        }
    ],
    "sg:phone":"+61 2 9685 0377",
    "sg:postcode":"2150",
    "sg:province":"NSW",
    "wof:name":"Elizabeth Restaurant",
    "wof:placetype":"venue"
},
  "geometry": {"coordinates":[151.02331543,-33.7961540222],"type":"Point"}
}