{
  "type": "Feature",
  "properties": {
    "addr:full":"Bldg 2, Lvl 1, 601 Doncaster Rd Doncaster VIC 3108",
    "addr:housenumber":"601",
    "addr:postcode":"3108",
    "addr:street":"Doncaster Rd",
    "iso:country":"AU",
    "sg:address":"Bldg 2, Lvl 1, 601 Doncaster Rd",
    "sg:city":"Doncaster",
    "sg:classifiers":[
        {
            "category":"Banks & Credit Unions",
            "subcategory":"Financial Services",
            "type":"Services"
        }
    ],
    "sg:phone":"+61 3 9848 6855",
    "sg:postcode":"3108",
    "sg:province":"VIC",
    "sg:tags":[
        "planning"
    ],
    "wof:name":"SAI Financial Services",
    "wof:placetype":"venue"
},
  "geometry": {"coordinates":[145.12310790999999,-37.7874488831],"type":"Point"}
}