{
  "type": "Feature",
  "properties": {
    "addr:full":"10 St Ives Drv Yanchep WA 6035",
    "addr:housenumber":"10",
    "addr:postcode":"6035",
    "addr:street":"St Ives Drv",
    "iso:country":"AU",
    "sg:address":"10 St Ives Drv",
    "sg:city":"Yanchep",
    "sg:classifiers":[
        {
            "category":"Building & Trades",
            "subcategory":"Construction",
            "type":"Services"
        }
    ],
    "sg:phone":"+61 8 9561 1153",
    "sg:postcode":"6035",
    "sg:province":"WA",
    "sg:tags":[
        "earth",
        "excavating",
        "moving",
        "contractor"
    ],
    "wof:name":"Sandgroper Truck & Bobcat Hire",
    "wof:placetype":"venue"
},
  "geometry": {"coordinates":[115.636322022,-31.5567703247],"type":"Point"}
}