{
  "type": "Feature",
  "properties": {
    "addr:full":"Shop 2 Main St Crafers SA 5152",
    "addr:housenumber":"shop 2",
    "addr:postcode":"5152",
    "addr:street":"Main St",
    "iso:country":"AU",
    "sg:address":"Shop 2 Main St",
    "sg:city":"Crafers",
    "sg:classifiers":[
        {
            "category":"Government",
            "subcategory":"Post Office",
            "type":"Public Place"
        }
    ],
    "sg:phone":"+61 8 8339 1635",
    "sg:postcode":"5152",
    "sg:province":"SA",
    "sg:tags":[
        "postal"
    ],
    "wof:name":"Australia Post",
    "wof:placetype":"venue"
},
  "geometry": {"coordinates":[138.70338439899999,-34.9971847534],"type":"Point"}
}