{
  "type": "Feature",
  "properties": {
    "addr:full":"Kiewa East Rd East Tangambalanga VIC 3691",
    "addr:postcode":"3691",
    "addr:street":"East Rd East",
    "iso:country":"AU",
    "sg:address":"Kiewa East Rd East",
    "sg:city":"Tangambalanga",
    "sg:classifiers":[
        {
            "category":"Building & Trades",
            "subcategory":"Construction",
            "type":"Services"
        }
    ],
    "sg:phone":"+61 2 6027 3129",
    "sg:postcode":"3691",
    "sg:province":"VIC",
    "sg:tags":[
        "earth",
        "excavating",
        "moving",
        "contractor"
    ],
    "wof:name":"Dove Brett & Louisa",
    "wof:placetype":"venue"
},
  "geometry": {"coordinates":[147.03739899999999,-36.25214],"type":"Point"}
}