{
  "type": "Feature",
  "properties": {
    "addr:full":"Shops 1 & 2 69 Dunmore St Wentworthville NSW 2145",
    "addr:housenumber":"shops 1 &;69",
    "addr:postcode":"2145",
    "addr:street":"2;Dunmore St",
    "iso:country":"AU",
    "sg:address":"Shops 1 & 2 69 Dunmore St",
    "sg:city":"Wentworthville",
    "sg:classifiers":[
        {
            "category":"Fast Food",
            "type":"Food & Drink"
        }
    ],
    "sg:phone":"+61 2 8855 2000",
    "sg:postcode":"2145",
    "sg:province":"NSW",
    "sg:tags":[
        "away",
        "take"
    ],
    "wof:name":"Domino's Pizza",
    "wof:placetype":"venue"
},
  "geometry": {"coordinates":[150.96992492699999,-33.8072624207],"type":"Point"}
}