{
  "type": "Feature",
  "properties": {
    "addr:full":"256 Beechworth Rd Wodonga VIC 3690",
    "addr:housenumber":"256",
    "addr:postcode":"3690",
    "addr:street":"Beechworth Rd",
    "iso:country":"AU",
    "sg:address":"256 Beechworth Rd",
    "sg:city":"Wodonga",
    "sg:classifiers":[
        {
            "category":"Retail",
            "subcategory":"Veterinary Services",
            "type":"Services"
        }
    ],
    "sg:phone":"+61 2 6056 4400",
    "sg:postcode":"3690",
    "sg:province":"VIC",
    "sg:tags":[
        "surgeon"
    ],
    "wof:name":"Clancy Justin",
    "wof:placetype":"venue"
},
  "geometry": {"coordinates":[146.88713073700001,-36.1309623718],"type":"Point"}
}