{
  "type": "Feature",
  "properties": {
    "iso:country":"AU",
    "sg:address":"Unit 18b/ 107 Miles Platting Rd",
    "sg:city":"Eight Mile Plains",
    "sg:classifiers":[
        {
            "category":"Farming",
            "subcategory":"Fish & Marine Products",
            "type":"Manufacturing & Wholesale Goods"
        }
    ],
    "sg:phone":"+61 7 3341 0488",
    "sg:postcode":"4113",
    "sg:province":"QLD",
    "sg:tags":[
        "chemical",
        "supplier"
    ],
    "wof:name":"Aotong International Pty Ltd",
    "wof:placetype":"venue"
},
  "geometry": {"coordinates":[153.098556519,-27.5768604279],"type":"Point"}
}