{
  "type": "Feature",
  "properties": {
    "iso:country":"AU",
    "sg:address":"Lowe St",
    "sg:city":"Nambour",
    "sg:classifiers":[
        {
            "category":"Building & Trades",
            "subcategory":"Construction",
            "type":"Services"
        }
    ],
    "sg:phone":"+61 7 5441 2777",
    "sg:postcode":"4560",
    "sg:province":"QLD",
    "sg:tags":[
        "home",
        "air conditioning"
    ],
    "wof:name":"Whelans Betta Electrical",
    "wof:placetype":"venue"
},
  "geometry": {"coordinates":[152.960403442,-26.6258125305],"type":"Point"}
}