{
  "type": "Feature",
  "properties": {
    "addr:full":"115 Boas Ave Joondalup WA 6027",
    "addr:housenumber":"115",
    "addr:postcode":"6027",
    "addr:street":"Boas Ave",
    "iso:country":"AU",
    "sg:address":"115 Boas Ave",
    "sg:city":"Joondalup",
    "sg:classifiers":[
        {
            "category":"Building & Trades",
            "subcategory":"Construction",
            "type":"Services"
        }
    ],
    "sg:phone":"+61 407 086 649",
    "sg:postcode":"6027",
    "sg:province":"WA",
    "sg:tags":[
        "ceiling"
    ],
    "wof:name":"E R Tutton",
    "wof:placetype":"venue"
},
  "geometry": {"coordinates":[115.77027130099999,-31.7429542542],"type":"Point"}
}