{
  "type": "Feature",
  "properties": {
    "addr:full":"Shop 7, 670 Maroondah Hwy Coldstream VIC 3770",
    "addr:housenumber":"shop 7 670",
    "addr:postcode":"3770",
    "addr:street":"Maroondah Hwy",
    "iso:country":"AU",
    "sg:address":"Shop 7, 670 Maroondah Hwy",
    "sg:city":"Coldstream",
    "sg:classifiers":[
        {
            "category":"Shopping",
            "subcategory":"Clothing, Apparel, & Fashions",
            "type":"Retail Goods"
        }
    ],
    "sg:phone":"+61 3 9739 0575",
    "sg:postcode":"3770",
    "sg:province":"VIC",
    "sg:tags":[
        "recycled",
        "clothing"
    ],
    "wof:name":"Bearly Used Children's Clothing",
    "wof:placetype":"venue"
},
  "geometry": {"coordinates":[145.37855500000001,-37.725597],"type":"Point"}
}