{
  "type": "Feature",
  "properties": {
    "addr:full":"Unit 9 20 Gibberd Rd Balcatta WA 6021",
    "addr:housenumber":"20",
    "addr:postcode":"6021",
    "addr:street":"Gibberd Rd",
    "iso:country":"AU",
    "sg:address":"Unit 9 20 Gibberd Rd",
    "sg:city":"Balcatta",
    "sg:classifiers":[
        {
            "category":"Government",
            "subcategory":"Court House",
            "type":"Public Place"
        }
    ],
    "sg:phone":"+61 427 989 165",
    "sg:postcode":"6021",
    "sg:province":"WA",
    "sg:tags":[
        "personal",
        "marriage",
        "family",
        "counselling"
    ],
    "wof:name":"Valerie Collocott",
    "wof:placetype":"venue"
},
  "geometry": {"coordinates":[115.812232971,-31.8647708893],"type":"Point"}
}