{
  "type": "Feature",
  "properties": {
    "iso:country":"AU",
    "sg:address":"Shed 6, 261 McCormack St",
    "sg:city":"Manunda",
    "sg:classifiers":[
        {
            "category":"Arena",
            "subcategory":"Sports Club",
            "type":"Entertainment"
        }
    ],
    "sg:phone":"+61 7 4053 4939",
    "sg:postcode":"4870",
    "sg:province":"QLD",
    "sg:tags":[
        "defence",
        "supply",
        "self",
        "instruction",
        "martial art"
    ],
    "wof:name":"Cairns Judo Club Incorporated",
    "wof:placetype":"venue"
},
  "geometry": {"coordinates":[145.74497985799999,-16.9150695801],"type":"Point"}
}