{
  "type": "Feature",
  "properties": {
    "iso:country":"AU",
    "sg:address":"20 Elliot St",
    "sg:city":"St Albans",
    "sg:classifiers":[
        {
            "category":"Building & Trades",
            "subcategory":"Construction",
            "type":"Services"
        }
    ],
    "sg:phone":"+61 409 432 449",
    "sg:postcode":"3021",
    "sg:province":"VIC",
    "sg:tags":[
        "concrete",
        "paving"
    ],
    "wof:name":"Superior Paving",
    "wof:placetype":"venue"
},
  "geometry": {"coordinates":[144.777756,-37.740349],"type":"Point"}
}