{
  "type": "Feature",
  "properties": {
    "iso:country":"AU",
    "sg:address":"20 Harlow Ave",
    "sg:city":"Hebersham",
    "sg:classifiers":[
        {
            "category":"Shopping",
            "subcategory":"Computers & Home Electronics",
            "type":"Retail Goods"
        }
    ],
    "sg:phone":"+61 2 9864 4805",
    "sg:postcode":"2770",
    "sg:province":"NSW",
    "sg:tags":[
        "small",
        "equipment",
        "business"
    ],
    "wof:name":"All Computer Equipment Supplies-Aces",
    "wof:placetype":"venue"
},
  "geometry": {"coordinates":[150.82426452600001,-33.7514648438],"type":"Point"}
}