{
  "type": "Feature",
  "properties": {
    "addr:full":"9 Marlow Pl Kellyville Ridge NSW 2155",
    "addr:housenumber":"9",
    "addr:postcode":"2155",
    "addr:street":"Marlow Pl",
    "iso:country":"AU",
    "sg:address":"9 Marlow Pl",
    "sg:city":"Kellyville Ridge",
    "sg:classifiers":[
        {
            "category":"Autos & Motor Vehicles",
            "subcategory":"Boat Sales",
            "type":"Retail Goods"
        }
    ],
    "sg:phone":"+61 407 069 562",
    "sg:postcode":"2155",
    "sg:province":"NSW",
    "sg:tags":[
        "equipment",
        "yacht"
    ],
    "wof:name":"Australian Subsea Electronics",
    "wof:placetype":"venue"
},
  "geometry": {"coordinates":[150.91822814899999,-33.7057037354],"type":"Point"}
}