{
  "type": "Feature",
  "properties": {
    "iso:country":"AU",
    "sg:address":"32 Ridgewood Drv",
    "sg:city":"Woombah",
    "sg:classifiers":[
        {
            "category":"Building & Trades",
            "subcategory":"Construction",
            "type":"Services"
        }
    ],
    "sg:phone":"+61 418 792 260",
    "sg:postcode":"2469",
    "sg:province":"NSW",
    "sg:tags":[
        "earth",
        "excavating",
        "moving",
        "contractor"
    ],
    "wof:name":"Scotts Bobcat & Excavator",
    "wof:placetype":"venue"
},
  "geometry": {"coordinates":[153.265548706,-29.3544254303],"type":"Point"}
}