{
  "type": "Feature",
  "properties": {
    "addr:full":"21 Dorcas St South Melbourne VIC 3205",
    "addr:housenumber":"21",
    "addr:postcode":"3205",
    "addr:street":"Dorcas St",
    "iso:country":"AU",
    "sg:address":"21 Dorcas St",
    "sg:city":"South Melbourne",
    "sg:classifiers":[
        {
            "category":"Health Services",
            "subcategory":"Doctor",
            "type":"Services"
        }
    ],
    "sg:phone":"+61 3 9699 2825",
    "sg:postcode":"3205",
    "sg:province":"VIC",
    "sg:tags":[
        "medical",
        "practitioner"
    ],
    "wof:name":"Wellness Clinic",
    "wof:placetype":"venue"
},
  "geometry": {"coordinates":[144.96994000000001,-37.830425],"type":"Point"}
}