{
  "type": "Feature",
  "properties": {
    "addr:full":"36 Robern Pde View Bank VIC 3084",
    "addr:housenumber":"36",
    "addr:postcode":"3084",
    "addr:street":"Robern Pde View Bank",
    "iso:country":"AU",
    "sg:address":"36 Robern Pde",
    "sg:city":"View Bank",
    "sg:classifiers":[
        {
            "category":"Health Services",
            "subcategory":"Health Practitioner",
            "type":"Services"
        }
    ],
    "sg:phone":"+61 3 9459 1168",
    "sg:postcode":"3084",
    "sg:province":"VIC",
    "sg:tags":[
        "psychologist"
    ],
    "wof:name":"Van De Meene, Bill",
    "wof:placetype":"venue"
},
  "geometry": {"coordinates":[145.087036133,-37.7381477356],"type":"Point"}
}