{
  "type": "Feature",
  "properties": {
    "addr:full":"Fcty1/ 6 Latham St Mornington VIC 3931",
    "addr:housenumber":"6",
    "addr:postcode":"3931",
    "addr:street":"Latham St",
    "iso:country":"AU",
    "sg:address":"Fcty1/ 6 Latham St",
    "sg:city":"Mornington",
    "sg:classifiers":[
        {
            "category":"Deli",
            "type":"Food & Drink"
        }
    ],
    "sg:phone":"+61 3 5976 4999",
    "sg:postcode":"3931",
    "sg:province":"VIC",
    "sg:tags":[
        "delicatessen"
    ],
    "wof:name":"Blue Bay Cheese",
    "wof:placetype":"venue"
},
  "geometry": {"coordinates":[145.05926513700001,-38.2341880798],"type":"Point"}
}