{
  "type": "Feature",
  "properties": {
    "addr:full":"ShdB/ 3 High St Kippa-Ring QLD 4021",
    "addr:housenumber":"3",
    "addr:postcode":"4021",
    "addr:street":"High St",
    "iso:country":"AU",
    "sg:address":"ShdB/ 3 High St",
    "sg:city":"Kippa-Ring",
    "sg:classifiers":[
        {
            "category":"Retail",
            "subcategory":"Auto Repair",
            "type":"Services"
        }
    ],
    "sg:phone":"+61 7 3284 1751",
    "sg:postcode":"4021",
    "sg:province":"QLD",
    "sg:tags":[
        "repairer",
        "motor",
        "engineer"
    ],
    "wof:name":"Assured Automotive Australia",
    "wof:placetype":"venue"
},
  "geometry": {"coordinates":[153.091263,-27.226074],"type":"Point"}
}