{
  "type": "Feature",
  "properties": {
    "iso:country":"AU",
    "sg:address":"Unit 6 Gladstone Crt 157 Gladstone St",
    "sg:city":"Fyshwick",
    "sg:classifiers":[
        {
            "category":"Shopping",
            "subcategory":"Beauty & Cosmetics",
            "type":"Retail Goods"
        }
    ],
    "sg:phone":"+61 2 6280 6622",
    "sg:postcode":"2609",
    "sg:province":"ACT",
    "sg:tags":[
        "equipment",
        "salon",
        "supply"
    ],
    "wof:name":"Geraghtys Hair & Beauty Supplies",
    "wof:placetype":"venue"
},
  "geometry": {"coordinates":[149.18328857399999,-35.3247833252],"type":"Point"}
}