{
  "type": "Feature",
  "properties": {
    "iso:country":"AU",
    "sg:address":"Sword St",
    "sg:city":"Muttaburra",
    "sg:classifiers":[
        {
            "category":"Education",
            "subcategory":"School",
            "type":"Public Place"
        }
    ],
    "sg:phone":"+61 7 4658 7289",
    "sg:postcode":"4732",
    "sg:province":"QLD",
    "sg:tags":[
        "state",
        "except",
        "nsw"
    ],
    "wof:name":"Muttaburra Primary School",
    "wof:placetype":"venue"
},
  "geometry": {"coordinates":[144.545593,-22.595284],"type":"Point"}
}