{
  "type": "Feature",
  "properties": {
    "iso:country":"AU",
    "sg:address":"16 Ballybunion Crs",
    "sg:city":"Connolly",
    "sg:classifiers":[
        {
            "category":"Utilities",
            "subcategory":"Electric",
            "type":"Services"
        }
    ],
    "sg:phone":"+61 8 9300 6123",
    "sg:postcode":"6027",
    "sg:province":"WA",
    "sg:tags":[
        "electrical",
        "contractor"
    ],
    "wof:name":"Harp Electrical",
    "wof:placetype":"venue"
},
  "geometry": {"coordinates":[115.7501297,-31.7527008057],"type":"Point"}
}