{
  "type": "Feature",
  "properties": {
    "addr:full":"Cnr Glenlee St & Dawson Pde Arana Hills QLD 4054",
    "addr:postcode":"4054",
    "addr:street":"Cnr Glenlee St & Dawson Pde",
    "iso:country":"AU",
    "sg:address":"Cnr Glenlee St & Dawson Pde",
    "sg:city":"Arana Hills",
    "sg:classifiers":[
        {
            "category":"Restaurant",
            "type":"Food & Drink"
        }
    ],
    "sg:phone":"+61 7 3851 0433",
    "sg:postcode":"4054",
    "sg:province":"QLD",
    "sg:tags":[
        "pizza"
    ],
    "wof:name":"Domino's Pizza",
    "wof:placetype":"venue"
},
  "geometry": {"coordinates":[152.95698547399999,-27.3931045532],"type":"Point"}
}