{
  "type": "Feature",
  "properties": {
    "addr:full":"11 Radford Pl Bairnsdale VIC 3875",
    "addr:housenumber":"11",
    "addr:postcode":"3875",
    "addr:street":"Radford Pl",
    "iso:country":"AU",
    "sg:address":"11 Radford Pl",
    "sg:city":"Bairnsdale",
    "sg:classifiers":[
        {
            "category":"Manufacturing",
            "subcategory":"Metals",
            "type":"Manufacturing & Wholesale Goods"
        }
    ],
    "sg:phone":"+61 3 5152 3233",
    "sg:postcode":"3875",
    "sg:province":"VIC",
    "sg:tags":[
        "sheet",
        "worker"
    ],
    "wof:name":"Bruce White Sheet Metal Pty Ltd",
    "wof:placetype":"venue"
},
  "geometry": {"coordinates":[147.60469055199999,-37.8367195129],"type":"Point"}
}