{
  "type": "Feature",
  "properties": {
    "iso:country":"AU",
    "sg:address":"50 - 52 Wingfield Rd",
    "sg:city":"Wingfield",
    "sg:classifiers":[
        {
            "category":"Manufacturing",
            "subcategory":"Rubber & Plastics",
            "type":"Manufacturing & Wholesale Goods"
        }
    ],
    "sg:phone":"+61 8 8445 6044",
    "sg:postcode":"5013",
    "sg:province":"SA",
    "sg:tags":[
        "moulders"
    ],
    "wof:name":"Joinit Plastics Pty Ltd",
    "wof:placetype":"venue"
},
  "geometry": {"coordinates":[138.551071167,-34.8442001343],"type":"Point"}
}