{
  "type": "Feature",
  "properties": {
    "iso:country":"AU",
    "sg:address":"1a Errol St",
    "sg:city":"Footscray",
    "sg:classifiers":[
        {
            "category":"Retail",
            "subcategory":"Storage",
            "type":"Services"
        }
    ],
    "sg:phone":"+61 423 633 566",
    "sg:postcode":"3011",
    "sg:province":"VIC",
    "sg:tags":[
        "removal",
        "furniture"
    ],
    "wof:name":"Furniture Removals & Storage",
    "wof:placetype":"venue"
},
  "geometry": {"coordinates":[144.89050293,-37.8016586304],"type":"Point"}
}