{
  "type": "Feature",
  "properties": {
    "addr:full":"3b Dennis Rd Campbellfield VIC 3061",
    "addr:housenumber":"3b",
    "addr:postcode":"3061",
    "addr:street":"Dennis Rd",
    "iso:country":"AU",
    "sg:address":"3b Dennis Rd",
    "sg:city":"Campbellfield",
    "sg:classifiers":[
        {
            "category":"Professional",
            "subcategory":"Detective & Security Services",
            "type":"Services"
        }
    ],
    "sg:phone":"+61 3 9303 9300",
    "sg:postcode":"3061",
    "sg:province":"VIC",
    "sg:tags":[
        "consultant",
        "system"
    ],
    "wof:name":"Mea Technologies",
    "wof:placetype":"venue"
},
  "geometry": {"coordinates":[144.940582275,-37.6473999023],"type":"Point"}
}