{
  "type": "Feature",
  "properties": {
    "iso:country":"AU",
    "sg:address":"119 Jetty Rd",
    "sg:city":"Glenelg",
    "sg:classifiers":[
        {
            "category":"Cinema",
            "subcategory":"Movie Theater",
            "type":"Entertainment"
        }
    ],
    "sg:phone":"+61 8 8294 3366",
    "sg:postcode":"5045",
    "sg:province":"SA",
    "wof:name":"Glenelg Cinema Centre",
    "wof:placetype":"venue"
},
  "geometry": {"coordinates":[138.519134522,-34.9799461365],"type":"Point"}
}