{
  "type": "Feature",
  "properties": {
    "addr:full":"2 Windham St Skipton VIC 3361",
    "addr:housenumber":"2",
    "addr:postcode":"3361",
    "addr:street":"Windham St",
    "iso:country":"AU",
    "sg:address":"2 Windham St",
    "sg:city":"Skipton",
    "sg:classifiers":[
        {
            "category":"Building & Trades",
            "subcategory":"Landscaping Services",
            "type":"Services"
        }
    ],
    "sg:phone":"+61 3 5340 2106",
    "sg:postcode":"3361",
    "sg:province":"VIC",
    "sg:tags":[
        "fertilizer",
        "spreading",
        "insecticide"
    ],
    "wof:name":"Nevills Skipton",
    "wof:placetype":"venue"
},
  "geometry": {"coordinates":[143.36148071299999,-37.6851234436],"type":"Point"}
}