{
  "type": "Feature",
  "properties": {
    "addr:full":"Shop 12, 25 South St Wodonga VIC 3690",
    "addr:housenumber":"shop 12 25",
    "addr:postcode":"3690",
    "addr:street":"South St",
    "iso:country":"AU",
    "sg:address":"Shop 12, 25 South St",
    "sg:city":"Wodonga",
    "sg:classifiers":[
        {
            "category":"Health Services",
            "subcategory":"Dentist",
            "type":"Services"
        }
    ],
    "sg:phone":"+61 2 6056 5877",
    "sg:postcode":"3690",
    "sg:province":"VIC",
    "sg:tags":[
        "dental",
        "prosthetist"
    ],
    "wof:name":"Albury & Wodonga Denture Clinic",
    "wof:placetype":"venue"
},
  "geometry": {"coordinates":[146.88694763199999,-36.1180076599],"type":"Point"}
}