{
  "type": "Feature",
  "properties": {
    "addr:full":"550 Warringah Rd Forestville NSW 2087",
    "addr:housenumber":"550",
    "addr:postcode":"2087",
    "addr:street":"Warringah Rd",
    "iso:country":"AU",
    "sg:address":"550 Warringah Rd",
    "sg:city":"Forestville",
    "sg:classifiers":[
        {
            "category":"Building & Trades",
            "subcategory":"Plumbing",
            "type":"Services"
        }
    ],
    "sg:phone":"+61 2 9962 9850",
    "sg:postcode":"2087",
    "sg:province":"NSW",
    "sg:tags":[
        "plumber",
        "gasfitters"
    ],
    "wof:name":"Perry Chris Plumbing",
    "wof:placetype":"venue"
},
  "geometry": {"coordinates":[151.22102355999999,-33.7554855347],"type":"Point"}
}