{
  "type": "Feature",
  "properties": {
    "iso:country":"AU",
    "sg:address":"34 Allied Drv",
    "sg:city":"Tullamarine",
    "sg:classifiers":[
        {
            "category":"Building & Trades",
            "subcategory":"Plumbing",
            "type":"Services"
        }
    ],
    "sg:phone":"+61 3 9330 3299",
    "sg:postcode":"3043",
    "sg:province":"VIC",
    "sg:tags":[
        "plumber",
        "gasfitters"
    ],
    "wof:name":"Tullamarine Plumbing & Drainage Pty Ltd",
    "wof:placetype":"venue"
},
  "geometry": {"coordinates":[144.873123169,-37.7106285095],"type":"Point"}
}