{
  "type": "Feature",
  "properties": {
    "addr:full":"24 George St Moonta SA 5558",
    "addr:housenumber":"24",
    "addr:postcode":"5558",
    "addr:street":"George St",
    "iso:country":"AU",
    "sg:address":"24 George St",
    "sg:city":"Moonta",
    "sg:classifiers":[
        {
            "category":"Personal",
            "subcategory":"Nail Salon",
            "type":"Services"
        }
    ],
    "sg:phone":"+61 8 8825 1655",
    "sg:postcode":"5558",
    "sg:province":"SA",
    "sg:tags":[
        "artificial"
    ],
    "wof:name":"Parisian Hair & Beaute",
    "wof:placetype":"venue"
},
  "geometry": {"coordinates":[137.59141540499999,-34.0684356689],"type":"Point"}
}