{
  "type": "Feature",
  "properties": {
    "addr:full":"1157 Old Northern Rd Dural NSW 2158",
    "addr:housenumber":"1157",
    "addr:postcode":"2158",
    "addr:street":"Old Northern Rd",
    "iso:country":"AU",
    "sg:address":"1157 Old Northern Rd",
    "sg:city":"Dural",
    "sg:classifiers":[
        {
            "category":"Personal",
            "type":"Services"
        }
    ],
    "sg:phone":"+61 2 9651 4832",
    "sg:postcode":"2158",
    "sg:province":"NSW",
    "sg:tags":[
        "dressmaker"
    ],
    "wof:name":"Nancy Resta Dressmaker",
    "wof:placetype":"venue"
},
  "geometry": {"coordinates":[151.02050781200001,-33.653842926],"type":"Point"}
}