{
  "type": "Feature",
  "properties": {
    "iso:country":"AU",
    "sg:address":"Moss Vale Rd",
    "sg:city":"Bowral",
    "sg:classifiers":[
        {
            "category":"Restaurant",
            "type":"Food & Drink"
        }
    ],
    "sg:phone":"+61 2 4868 3566",
    "sg:postcode":"2576",
    "sg:province":"NSW",
    "wof:name":"Briars Historic Inn & Bistro",
    "wof:placetype":"venue"
},
  "geometry": {"coordinates":[150.416503906,-34.4837188721],"type":"Point"}
}