{
  "type": "Feature",
  "properties": {
    "addr:full":"Suite 2/ 190 Main St Osborne Park WA 6017",
    "addr:housenumber":"/ 190",
    "addr:postcode":"6017",
    "addr:street":"Main St",
    "iso:country":"AU",
    "sg:address":"Suite 2/ 190 Main St",
    "sg:city":"Osborne Park",
    "sg:classifiers":[
        {
            "category":"Health Services",
            "subcategory":"Health Practitioner",
            "type":"Services"
        }
    ],
    "sg:phone":"+61 8 9345 4221",
    "sg:postcode":"6017",
    "sg:province":"WA",
    "sg:tags":[
        "physiotherapist"
    ],
    "wof:name":"Chromiak Fiona",
    "wof:placetype":"venue"
},
  "geometry": {"coordinates":[115.828422546,-31.8987541199],"type":"Point"}
}