{
  "type": "Feature",
  "properties": {
    "addr:full":"104 Targo St Bundaberg QLD 4670",
    "addr:housenumber":"104",
    "addr:postcode":"4670",
    "addr:street":"Targo St",
    "iso:country":"AU",
    "sg:address":"104 Targo St",
    "sg:city":"Bundaberg",
    "sg:classifiers":[
        {
            "category":"Education",
            "subcategory":"Special Training",
            "type":"Public Place"
        }
    ],
    "sg:phone":"+61 7 4153 3334",
    "sg:postcode":"4670",
    "sg:province":"QLD",
    "sg:tags":[
        "tuition-educational"
    ],
    "wof:name":"Kumon Education Centre",
    "wof:placetype":"venue"
},
  "geometry": {"coordinates":[152.35440063499999,-24.8754062653],"type":"Point"}
}