{
  "type": "Feature",
  "properties": {
    "addr:full":"1 Ryefield Crt Diamond Creek VIC 3089",
    "addr:housenumber":"1",
    "addr:postcode":"3089",
    "addr:street":"Ryefield Crt",
    "iso:country":"AU",
    "sg:address":"1 Ryefield Crt",
    "sg:city":"Diamond Creek",
    "sg:classifiers":[
        {
            "category":"Building & Trades",
            "subcategory":"Plumbing",
            "type":"Services"
        }
    ],
    "sg:phone":"+61 3 9433 6615",
    "sg:postcode":"3089",
    "sg:province":"VIC",
    "sg:tags":[
        "plumber",
        "gasfitters"
    ],
    "wof:name":"Dripping Tap",
    "wof:placetype":"venue"
},
  "geometry": {"coordinates":[145.16212463400001,-37.668598175],"type":"Point"}
}