{
  "type": "Feature",
  "properties": {
    "addr:full":"27 Tasma St North Hobart TAS 7000",
    "addr:housenumber":"27",
    "addr:postcode":"7000",
    "addr:street":"Tasma St",
    "iso:country":"AU",
    "sg:address":"27 Tasma St",
    "sg:city":"North Hobart",
    "sg:classifiers":[
        {
            "category":"Professional",
            "subcategory":"Art Services",
            "type":"Services"
        }
    ],
    "sg:phone":"+61 3 6231 0512",
    "sg:postcode":"7000",
    "sg:province":"TAS",
    "sg:tags":[
        "interior",
        "designer"
    ],
    "wof:name":"Designed Objects Tasmania Inc ( dot )",
    "wof:placetype":"venue"
},
  "geometry": {"coordinates":[147.32020568900001,-42.8746528625],"type":"Point"}
}