{
  "type": "Feature",
  "properties": {
    "iso:country":"AU",
    "sg:address":"78 Arncliffe St",
    "sg:city":"Arncliffe",
    "sg:classifiers":[
        {
            "category":"Retail",
            "subcategory":"Storage",
            "type":"Services"
        }
    ],
    "sg:phone":"+61 2 9599 2960",
    "sg:postcode":"2205",
    "sg:province":"NSW",
    "sg:tags":[
        "removal",
        "furniture"
    ],
    "wof:name":"BTT & British Taxi Trucks & Removals",
    "wof:placetype":"venue"
},
  "geometry": {"coordinates":[151.153244,-33.930901],"type":"Point"}
}