{
  "type": "Feature",
  "properties": {
    "iso:country":"AU",
    "sg:address":"1 Florence Ave North",
    "sg:city":"Ringwood",
    "sg:classifiers":[
        {
            "category":"Building & Trades",
            "subcategory":"Landscaping Services",
            "type":"Services"
        }
    ],
    "sg:phone":"+61 3 9878 7908",
    "sg:postcode":"3134",
    "sg:province":"VIC",
    "sg:tags":[
        "stump",
        "tree",
        "felling",
        "removal"
    ],
    "wof:name":"Ken Tregillis Tree Services",
    "wof:placetype":"venue"
},
  "geometry": {"coordinates":[145.231658936,-37.7945785522],"type":"Point"}
}