{
  "type": "Feature",
  "properties": {
    "addr:full":"160 Sussex St Sydney NSW 2000",
    "addr:housenumber":"160",
    "addr:postcode":"2000",
    "addr:street":"Sussex St",
    "iso:country":"AU",
    "sg:address":"160 Sussex St",
    "sg:city":"Sydney",
    "sg:classifiers":[
        {
            "category":"Transit Center",
            "subcategory":"Freight",
            "type":"Transportation"
        }
    ],
    "sg:phone":"+61 2 9364 8400",
    "sg:postcode":"2000",
    "sg:province":"NSW",
    "sg:tags":[
        "agent",
        "shipping"
    ],
    "wof:name":"P & O Australia Ltd",
    "wof:placetype":"venue"
},
  "geometry": {"coordinates":[151.203857422,-33.8695602417],"type":"Point"}
}