{
  "type": "Feature",
  "properties": {
    "addr:full":"12 Lowry St North Ipswich QLD 4305",
    "addr:housenumber":"12",
    "addr:postcode":"4305",
    "addr:street":"Lowry St",
    "iso:country":"AU",
    "sg:address":"12 Lowry St",
    "sg:city":"North Ipswich",
    "sg:classifiers":[
        {
            "category":"Transit Center",
            "subcategory":"Freight",
            "type":"Transportation"
        }
    ],
    "sg:phone":"+61 7 3812 1477",
    "sg:postcode":"4305",
    "sg:province":"QLD",
    "sg:tags":[
        "equipment",
        "transport",
        "road",
        "vehicle"
    ],
    "wof:name":"Ipswich Truck Parts Pty Ltd",
    "wof:placetype":"venue"
},
  "geometry": {"coordinates":[152.75907898,-27.6063842773],"type":"Point"}
}