{
  "type": "Feature",
  "properties": {
    "addr:full":"Lot 2 Upper Houghton Rd Giru QLD 4809",
    "addr:postcode":"4809",
    "addr:street":"Upper Houghton Rd",
    "iso:country":"AU",
    "sg:address":"Lot 2 Upper Houghton Rd",
    "sg:city":"Giru",
    "sg:classifiers":[
        {
            "category":"Farming",
            "subcategory":"Farm & Veterinary Services",
            "type":"Manufacturing & Wholesale Goods"
        }
    ],
    "sg:phone":"+61 7 4782 9393",
    "sg:postcode":"4809",
    "sg:province":"QLD",
    "sg:tags":[
        "contracting"
    ],
    "wof:name":"Stockham G K & M R",
    "wof:placetype":"venue"
},
  "geometry": {"coordinates":[147.10197448700001,-19.5531406403],"type":"Point"}
}