{
  "type": "Feature",
  "properties": {
    "addr:full":"Cnr 8th St & Lime Ave Mildura VIC 3500",
    "addr:postcode":"3500",
    "addr:street":"Cnr 8Th St & Lime Ave",
    "iso:country":"AU",
    "sg:address":"Cnr 8th St & Lime Ave",
    "sg:city":"Mildura",
    "sg:classifiers":[
        {
            "category":"Food & Beverages",
            "subcategory":"Bakery",
            "type":"Retail Goods"
        }
    ],
    "sg:phone":"+61 3 5021 2146",
    "sg:postcode":"3500",
    "sg:province":"VIC",
    "sg:tags":[
        "baker"
    ],
    "wof:name":"Bakers Delight Mildura City",
    "wof:placetype":"venue"
},
  "geometry": {"coordinates":[142.15609741200001,-34.1869926453],"type":"Point"}
}