{
  "type": "Feature",
  "properties": {
    "addr:full":"41 Rush St Woollahra NSW 2025",
    "addr:housenumber":"41",
    "addr:postcode":"2025",
    "addr:street":"Rush St",
    "iso:country":"AU",
    "sg:address":"41 Rush St",
    "sg:city":"Woollahra",
    "sg:classifiers":[
        {
            "category":"Real Estate",
            "subcategory":"Architect",
            "type":"Services"
        }
    ],
    "sg:phone":"+61 2 9363 4566",
    "sg:postcode":"2025",
    "sg:province":"NSW",
    "wof:name":"Reed Peter and Associates",
    "wof:placetype":"venue"
},
  "geometry": {"coordinates":[151.23675537099999,-33.8877830505],"type":"Point"}
}