{
  "type": "Feature",
  "properties": {
    "iso:country":"AU",
    "sg:address":"Lot 13, Sweny Drv",
    "sg:city":"Australind",
    "sg:classifiers":[
        {
            "category":"Building & Trades",
            "subcategory":"Construction",
            "type":"Services"
        }
    ],
    "sg:phone":"+61 8 9725 8787",
    "sg:postcode":"6233",
    "sg:province":"WA",
    "sg:tags":[
        "earth",
        "excavating",
        "moving",
        "contractor"
    ],
    "wof:name":"S & J Excavations",
    "wof:placetype":"venue"
},
  "geometry": {"coordinates":[115.746422,-33.276211],"type":"Point"}
}