{
  "type": "Feature",
  "properties": {
    "addr:full":"173 Blackwall Rd Woy Woy NSW 2256",
    "addr:housenumber":"173",
    "addr:postcode":"2256",
    "addr:street":"Blackwall Rd",
    "iso:country":"AU",
    "sg:address":"173 Blackwall Rd",
    "sg:city":"Woy Woy",
    "sg:phone":"+61 2 4344 2455",
    "sg:postcode":"2256",
    "sg:province":"NSW",
    "wof:name":"Terrigal Glass",
    "wof:placetype":"venue"
},
  "geometry": {"coordinates":[151.32733154300001,-33.4928283691],"type":"Point"}
}