{
  "type": "Feature",
  "properties": {
    "iso:country":"AU",
    "sg:address":"2/12 Cross St",
    "sg:city":"Double Bay",
    "sg:classifiers":[
        {
            "category":"Real Estate",
            "subcategory":"Real Estate Agent",
            "type":"Services"
        }
    ],
    "sg:phone":"+61 418 246 374",
    "sg:postcode":"2028",
    "sg:province":"NSW",
    "wof:name":"David Newgrosh Real Estate",
    "wof:placetype":"venue"
},
  "geometry": {"coordinates":[151.24314880399999,-33.8764038086],"type":"Point"}
}