{
  "type": "Feature",
  "properties": {
    "addr:full":"8 Oliver St Bellevue WA 6056",
    "addr:housenumber":"8",
    "addr:postcode":"6056",
    "addr:street":"Oliver St",
    "iso:country":"AU",
    "sg:address":"8 Oliver St",
    "sg:city":"Bellevue",
    "sg:classifiers":[
        {
            "category":"Manufacturing",
            "subcategory":"Tools & Machinery",
            "type":"Manufacturing & Wholesale Goods"
        }
    ],
    "sg:phone":"+61 8 9274 7820",
    "sg:postcode":"6056",
    "sg:province":"WA",
    "sg:tags":[
        "earth",
        "excavating",
        "moving",
        "equipment"
    ],
    "wof:name":"Plantman",
    "wof:placetype":"venue"
},
  "geometry": {"coordinates":[116.01725768999999,-31.9025421143],"type":"Point"}
}