{
  "type": "Feature",
  "properties": {
    "addr:full":"1st Floor, 119 The Crescent Fairfield NSW 2165",
    "addr:housenumber":"119",
    "addr:postcode":"2165",
    "addr:street":"The Crescent",
    "iso:country":"AU",
    "sg:address":"1st Floor, 119 The Crescent",
    "sg:city":"Fairfield",
    "sg:classifiers":[
        {
            "category":"Professional",
            "subcategory":"Employment Agencies",
            "type":"Services"
        }
    ],
    "sg:phone":"+61 2 9725 7577",
    "sg:postcode":"2165",
    "sg:province":"NSW",
    "wof:name":"Mission Employment",
    "wof:placetype":"venue"
},
  "geometry": {"coordinates":[150.957763672,-33.8709907532],"type":"Point"}
}