{
  "type": "Feature",
  "properties": {
    "addr:full":"3 Rankin Crt Bundaberg QLD 4670",
    "addr:housenumber":"3",
    "addr:postcode":"4670",
    "addr:street":"Rankin Crt",
    "iso:country":"AU",
    "sg:address":"3 Rankin Crt",
    "sg:city":"Bundaberg",
    "sg:classifiers":[
        {
            "category":"Professional",
            "subcategory":"Accounting & Tax Preparation",
            "type":"Services"
        }
    ],
    "sg:phone":"+61 7 4152 9369",
    "sg:postcode":"4670",
    "sg:province":"QLD",
    "sg:tags":[
        "accountant",
        "auditor"
    ],
    "wof:name":"Vikki Graham",
    "wof:placetype":"venue"
},
  "geometry": {"coordinates":[152.369873047,-24.8712615967],"type":"Point"}
}