{
  "type": "Feature",
  "properties": {
    "addr:full":"24 Murray St Camden NSW 2570",
    "addr:housenumber":"24",
    "addr:postcode":"2570",
    "addr:street":"Murray St",
    "iso:country":"AU",
    "sg:address":"24 Murray St",
    "sg:city":"Camden",
    "sg:classifiers":[
        {
            "category":"Personal",
            "subcategory":"Beauty Salon",
            "type":"Services"
        }
    ],
    "sg:phone":"+61 2 4655 9925",
    "sg:postcode":"2570",
    "sg:province":"NSW",
    "sg:tags":[
        "hairdresser"
    ],
    "wof:name":"Phillip Wayne Hairdressing",
    "wof:placetype":"venue"
},
  "geometry": {"coordinates":[150.69436645499999,-34.0566596985],"type":"Point"}
}