{
  "type": "Feature",
  "properties": {
    "addr:full":"86 Queen St Brisbane QLD 4000",
    "addr:housenumber":"86",
    "addr:postcode":"4000",
    "addr:street":"Queen St",
    "iso:country":"AU",
    "sg:address":"86 Queen St",
    "sg:city":"Brisbane",
    "sg:classifiers":[
        {
            "category":"Professional",
            "subcategory":"Management & Consulting",
            "type":"Services"
        }
    ],
    "sg:phone":"+61 1300 726 333",
    "sg:postcode":"4000",
    "sg:province":"QLD",
    "sg:tags":[
        "consultant"
    ],
    "wof:name":"International Business Network Pty Ltd",
    "wof:placetype":"venue"
},
  "geometry": {"coordinates":[153.024337769,-27.4701385498],"type":"Point"}
}