{
  "type": "Feature",
  "properties": {
    "addr:full":"2/ 154 Main Rd Moonah TAS 7009",
    "addr:housenumber":"/ 154",
    "addr:postcode":"7009",
    "addr:street":"Main Rd",
    "iso:country":"AU",
    "sg:address":"2/ 154 Main Rd",
    "sg:city":"Moonah",
    "sg:classifiers":[
        {
            "category":"Wholesale",
            "subcategory":"Construction Materials",
            "type":"Manufacturing & Wholesale Goods"
        }
    ],
    "sg:phone":"+61 3 6272 8533",
    "sg:postcode":"7009",
    "sg:province":"TAS",
    "sg:tags":[
        "protective",
        "coating"
    ],
    "wof:name":"Wattyl Industrial Coatings",
    "wof:placetype":"venue"
},
  "geometry": {"coordinates":[147.29258727999999,-42.8437767029],"type":"Point"}
}