{
  "type": "Feature",
  "properties": {
    "iso:country":"AU",
    "sg:address":"Shp G2/ 19 Gilbertson Rd",
    "sg:city":"Laverton North",
    "sg:classifiers":[
        {
            "category":"Professional",
            "type":"Services"
        }
    ],
    "sg:phone":"+61 3 8360 8661",
    "sg:postcode":"3026",
    "sg:province":"VIC",
    "sg:tags":[
        "transport"
    ],
    "wof:name":"Sidelink Transport Pty Ltd",
    "wof:placetype":"venue"
},
  "geometry": {"coordinates":[144.790497,-37.821716],"type":"Point"}
}