{
  "type": "Feature",
  "properties": {
    "iso:country":"AU",
    "sg:address":"3 Malcolm St",
    "sg:city":"West Croydon",
    "sg:classifiers":[
        {
            "category":"Home & Garden",
            "subcategory":"Hardware",
            "type":"Retail Goods"
        }
    ],
    "sg:phone":"+61 8 8346 8008",
    "sg:postcode":"5008",
    "sg:province":"SA",
    "sg:tags":[
        "battery",
        "dry",
        "rechargeable",
        "cell"
    ],
    "wof:name":"M.M.A Pty Ltd",
    "wof:placetype":"venue"
},
  "geometry": {"coordinates":[138.556793,-34.894295],"type":"Point"}
}