{
  "type": "Feature",
  "properties": {
    "iso:country":"AU",
    "sg:address":"81 Church St",
    "sg:city":"Dongara",
    "sg:classifiers":[
        {
            "category":"Travel",
            "subcategory":"Hotels & Motels",
            "type":"Entertainment"
        }
    ],
    "sg:phone":"+61 8 9927 2200",
    "sg:postcode":"6525",
    "sg:province":"WA",
    "wof:name":"Seaspray Beach Resort",
    "wof:placetype":"venue"
},
  "geometry": {"coordinates":[114.921669006,-29.2519931793],"type":"Point"}
}