{
  "type": "Feature",
  "properties": {
    "iso:country":"AU",
    "sg:address":"Suite 410/ 40 King St",
    "sg:city":"Waverton",
    "sg:classifiers":[
        {
            "category":"Professional",
            "subcategory":"Computer Services",
            "type":"Services"
        }
    ],
    "sg:phone":"+61 408 083 045",
    "sg:postcode":"2060",
    "sg:province":"NSW",
    "sg:tags":[
        "training"
    ],
    "wof:name":"Train 2000",
    "wof:placetype":"venue"
},
  "geometry": {"coordinates":[151.19781494099999,-33.8353805542],"type":"Point"}
}