{
  "type": "Feature",
  "properties": {
    "addr:full":"Ste2/ 1 Fitzwilliam St Parramatta NSW 2150",
    "addr:housenumber":"1",
    "addr:postcode":"2150",
    "addr:street":"Fitzwilliam St",
    "iso:country":"AU",
    "sg:address":"Ste2/ 1 Fitzwilliam St",
    "sg:city":"Parramatta",
    "sg:classifiers":[
        {
            "category":"Professional",
            "subcategory":"Employment Agencies",
            "type":"Services"
        }
    ],
    "sg:phone":"+61 2 9687 0746",
    "sg:postcode":"2150",
    "sg:province":"NSW",
    "wof:name":"Protech Personnel",
    "wof:placetype":"venue"
},
  "geometry": {"coordinates":[151.00506591800001,-33.8183555603],"type":"Point"}
}