{
  "type": "Feature",
  "properties": {
    "addr:full":"27 Hotham St Traralgon VIC 3844",
    "addr:housenumber":"27",
    "addr:postcode":"3844",
    "addr:street":"Hotham St",
    "iso:country":"AU",
    "sg:address":"27 Hotham St",
    "sg:city":"Traralgon",
    "sg:classifiers":[
        {
            "category":"Personal",
            "subcategory":"Hair Removal",
            "type":"Services"
        }
    ],
    "sg:phone":"+61 3 5174 1422",
    "sg:postcode":"3844",
    "sg:province":"VIC",
    "wof:name":"Skinsense Salon Spa",
    "wof:placetype":"venue"
},
  "geometry": {"coordinates":[146.53715515100001,-38.1974143982],"type":"Point"}
}