{
  "type": "Feature",
  "properties": {
    "addr:full":"Sackville St Ingleburn NSW 2565",
    "addr:postcode":"2565",
    "addr:street":"Sackville St",
    "iso:country":"AU",
    "sg:address":"Sackville St",
    "sg:city":"Ingleburn",
    "sg:classifiers":[
        {
            "category":"Education",
            "subcategory":"School",
            "type":"Public Place"
        }
    ],
    "sg:phone":"+61 2 9605 3073",
    "sg:postcode":"2565",
    "sg:province":"NSW",
    "sg:tags":[
        "state",
        "-",
        "nsw"
    ],
    "wof:name":"Sackville St Public School",
    "wof:placetype":"venue"
},
  "geometry": {"coordinates":[150.855957031,-34.0061759949],"type":"Point"}
}