{
  "type": "Feature",
  "properties": {
    "addr:full":"62-66 Woodlands Drv Braeside VIC 3195",
    "addr:housenumber":"62-66",
    "addr:postcode":"3195",
    "addr:street":"Woodlands Drv",
    "iso:country":"AU",
    "sg:address":"62-66 Woodlands Drv",
    "sg:city":"Braeside",
    "sg:classifiers":[
        {
            "category":"Manufacturing",
            "subcategory":"Metals",
            "type":"Manufacturing & Wholesale Goods"
        }
    ],
    "sg:phone":"+61 3 9580 5222",
    "sg:postcode":"3195",
    "sg:province":"VIC",
    "sg:tags":[
        "fabricator",
        "aluminium"
    ],
    "wof:name":"Durabar Fabrications Pty Ltd",
    "wof:placetype":"venue"
},
  "geometry": {"coordinates":[145.117355347,-37.9915084839],"type":"Point"}
}