{
  "type": "Feature",
  "properties": {
    "addr:full":"195 South Creek Rd Cromer NSW 2099",
    "addr:housenumber":"195",
    "addr:postcode":"2099",
    "addr:street":"South Creek Rd",
    "iso:country":"AU",
    "sg:address":"195 South Creek Rd",
    "sg:city":"Cromer",
    "sg:classifiers":[
        {
            "category":"Building & Trades",
            "subcategory":"Construction",
            "type":"Services"
        }
    ],
    "sg:phone":"+61 2 9982 3762",
    "sg:postcode":"2099",
    "sg:province":"NSW",
    "sg:tags":[
        "earth",
        "excavating",
        "moving",
        "contractor"
    ],
    "wof:name":"Neil Stewart Excavations",
    "wof:placetype":"venue"
},
  "geometry": {"coordinates":[151.279373169,-33.7343864441],"type":"Point"}
}