{
  "type": "Feature",
  "properties": {
    "addr:full":"Kingsley St Acton ACT 2601",
    "addr:postcode":"2601",
    "addr:street":"Kingsley St",
    "iso:country":"AU",
    "sg:address":"Kingsley St",
    "sg:city":"Acton",
    "sg:classifiers":[
        {
            "category":"Arts & Performance",
            "subcategory":"Art Gallery",
            "type":"Entertainment"
        }
    ],
    "sg:phone":"+61 2 6125 5832",
    "sg:postcode":"2601",
    "sg:province":"ACT",
    "wof:name":"Drill Hall Gallery",
    "wof:placetype":"venue"
},
  "geometry": {"coordinates":[149.12361145,-35.2769584656],"type":"Point"}
}