{
  "type": "Feature",
  "properties": {
    "iso:country":"AU",
    "sg:address":"405 High St",
    "sg:city":"Lalor",
    "sg:classifiers":[
        {
            "category":"Professional",
            "subcategory":"Engineering",
            "type":"Services"
        }
    ],
    "sg:phone":"+61 3 9466 1844",
    "sg:postcode":"3075",
    "sg:province":"VIC",
    "sg:tags":[
        "civil",
        "engineer"
    ],
    "wof:name":"Kozaris & Associates Pty Ltd",
    "wof:placetype":"venue"
},
  "geometry": {"coordinates":[145.00201415999999,-37.8528938293],"type":"Point"}
}