{
  "type": "Feature",
  "properties": {
    "addr:full":"Eugarie St Noosa Junction QLD 4567",
    "addr:postcode":"4567",
    "addr:street":"St",
    "iso:country":"AU",
    "sg:address":"Eugarie St",
    "sg:city":"Noosa Junction",
    "sg:classifiers":[
        {
            "category":"Health Services",
            "subcategory":"Doctor",
            "type":"Services"
        }
    ],
    "sg:phone":"+61 7 5455 4533",
    "sg:postcode":"4567",
    "sg:province":"QLD",
    "sg:tags":[
        "medical",
        "practitioner"
    ],
    "wof:name":"Cantor Chris Dr",
    "wof:placetype":"venue"
},
  "geometry": {"coordinates":[153.09304809599999,-26.3981742859],"type":"Point"}
}