{
  "type": "Feature",
  "properties": {
    "addr:full":"14 Mecklem St Strathpine QLD 4500",
    "addr:housenumber":"14",
    "addr:postcode":"4500",
    "addr:street":"Mecklem St",
    "iso:country":"AU",
    "sg:address":"14 Mecklem St",
    "sg:city":"Strathpine",
    "sg:classifiers":[
        {
            "category":"Professional",
            "subcategory":"Accounting & Tax Preparation",
            "type":"Services"
        }
    ],
    "sg:phone":"+61 7 3205 2881",
    "sg:postcode":"4500",
    "sg:province":"QLD",
    "sg:tags":[
        "accountant",
        "auditor"
    ],
    "wof:name":"Pine Rivers Consulting",
    "wof:placetype":"venue"
},
  "geometry": {"coordinates":[152.992797852,-27.3103275299],"type":"Point"}
}