{
  "type": "Feature",
  "properties": {
    "iso:country":"AU",
    "sg:address":"Melbourne Central, Shop G059, Lonsdale St",
    "sg:city":"Melbourne",
    "sg:classifiers":[
        {
            "category":"Shopping",
            "subcategory":"Clothing, Apparel, & Fashions",
            "type":"Retail Goods"
        }
    ],
    "sg:phone":"+61 3 9639 3585",
    "sg:postcode":"3000",
    "sg:province":"VIC",
    "sg:tags":[
        "sportswear"
    ],
    "wof:name":"Canterbury International",
    "wof:placetype":"venue"
},
  "geometry": {"coordinates":[144.96881103499999,-37.8132286072],"type":"Point"}
}