{
  "type": "Feature",
  "properties": {
    "addr:full":"3 Silvyn St Redcliffe QLD 4020",
    "addr:housenumber":"3",
    "addr:postcode":"4020",
    "addr:street":"Silvyn St",
    "iso:country":"AU",
    "sg:address":"3 Silvyn St",
    "sg:city":"Redcliffe",
    "sg:classifiers":[
        {
            "category":"Building & Trades",
            "subcategory":"Construction",
            "type":"Services"
        }
    ],
    "sg:phone":"+61 7 3889 3379",
    "sg:postcode":"4020",
    "sg:province":"QLD",
    "sg:tags":[
        "joiner",
        "carpenter"
    ],
    "wof:name":"All Purpose Carpentry & Cabinet Making",
    "wof:placetype":"venue"
},
  "geometry": {"coordinates":[153.10682700000001,-27.228199],"type":"Point"}
}