{
  "type": "Feature",
  "properties": {
    "addr:full":"4 Briggs St Palmwoods QLD 4555",
    "addr:housenumber":"4",
    "addr:postcode":"4555",
    "addr:street":"Briggs St",
    "iso:country":"AU",
    "sg:address":"4 Briggs St",
    "sg:city":"Palmwoods",
    "sg:classifiers":[
        {
            "category":"Retail",
            "subcategory":"Veterinary Services",
            "type":"Services"
        }
    ],
    "sg:phone":"+61 7 5445 9500",
    "sg:postcode":"4555",
    "sg:province":"QLD",
    "sg:tags":[
        "surgeon"
    ],
    "wof:name":"Stone Brett",
    "wof:placetype":"venue"
},
  "geometry": {"coordinates":[152.95904540999999,-26.6849842072],"type":"Point"}
}