{
  "type": "Feature",
  "properties": {
    "addr:full":"33 Fox Valley Rd Wahroonga NSW 2076",
    "addr:housenumber":"33",
    "addr:postcode":"2076",
    "addr:street":"Fox Valley Rd",
    "iso:country":"AU",
    "sg:address":"33 Fox Valley Rd",
    "sg:city":"Wahroonga",
    "sg:classifiers":[
        {
            "category":"Professional",
            "subcategory":"Accounting & Tax Preparation",
            "type":"Services"
        }
    ],
    "sg:phone":"+61 2 9489 5801",
    "sg:postcode":"2076",
    "sg:province":"NSW",
    "sg:tags":[
        "accountant",
        "auditor"
    ],
    "wof:name":"Brown David",
    "wof:placetype":"venue"
},
  "geometry": {"coordinates":[151.11647033700001,-33.7275047302],"type":"Point"}
}