{
  "type": "Feature",
  "properties": {
    "addr:full":"248 Bondi Rd Bondi NSW 2026",
    "addr:housenumber":"248",
    "addr:postcode":"2026",
    "addr:street":"Bondi Rd",
    "iso:country":"AU",
    "sg:address":"248 Bondi Rd",
    "sg:city":"Bondi",
    "sg:classifiers":[
        {
            "category":"Health Services",
            "subcategory":"Doctor",
            "type":"Services"
        }
    ],
    "sg:phone":"+61 2 9389 8000",
    "sg:postcode":"2026",
    "sg:province":"NSW",
    "sg:tags":[
        "medical",
        "practitioner"
    ],
    "wof:name":"Body Piercing Doctor Bondi Medical Centre",
    "wof:placetype":"venue"
},
  "geometry": {"coordinates":[151.26594543499999,-33.894115448],"type":"Point"}
}