{
  "type": "Feature",
  "properties": {
    "iso:country":"AU",
    "sg:address":"Shop 104, 87 Park",
    "sg:city":"Kotara",
    "sg:classifiers":[
        {
            "category":"Shopping",
            "subcategory":"Clothing, Apparel, & Fashions",
            "type":"Retail Goods"
        }
    ],
    "sg:phone":"+61 2 4957 7170",
    "sg:postcode":"2289",
    "sg:province":"NSW",
    "sg:tags":[
        "menswear"
    ],
    "wof:name":"Reuben F Scarf",
    "wof:placetype":"venue"
},
  "geometry": {"coordinates":[151.696777344,-32.9426994324],"type":"Point"}
}