{
  "type": "Feature",
  "properties": {
    "addr:full":"2 Hanlon Crt Wodonga VIC 3690",
    "addr:housenumber":"2",
    "addr:postcode":"3690",
    "addr:street":"Hanlon Crt",
    "iso:country":"AU",
    "sg:address":"2 Hanlon Crt",
    "sg:city":"Wodonga",
    "sg:classifiers":[
        {
            "category":"Social Services",
            "subcategory":"Retirement Home",
            "type":"Services"
        }
    ],
    "sg:phone":"+61 2 6059 8961",
    "sg:postcode":"3690",
    "sg:province":"VIC",
    "sg:tags":[
        "village"
    ],
    "wof:name":"Village Life Communities Wodonga",
    "wof:placetype":"venue"
},
  "geometry": {"coordinates":[146.892501831,-36.1128997803],"type":"Point"}
}