{
  "type": "Feature",
  "properties": {
    "addr:full":"Hume Hwy Bookham NSW 2582",
    "addr:postcode":"2582",
    "addr:street":"Hume Hwy",
    "iso:country":"AU",
    "sg:address":"Hume Hwy",
    "sg:city":"Bookham",
    "sg:classifiers":[
        {
            "category":"Wholesale",
            "subcategory":"Machinery & Supplies",
            "type":"Manufacturing & Wholesale Goods"
        }
    ],
    "sg:phone":"+61 2 6227 7227",
    "sg:postcode":"2582",
    "sg:province":"NSW",
    "sg:tags":[
        "agricultural"
    ],
    "wof:name":"Robinson's Of Bookham Pty Ltd",
    "wof:placetype":"venue"
},
  "geometry": {"coordinates":[148.629516602,-34.8083305359],"type":"Point"}
}