{
  "type": "Feature",
  "properties": {
    "addr:full":"9 Bloxham Crt Hoppers Crossing VIC 3029",
    "addr:housenumber":"9",
    "addr:postcode":"3029",
    "addr:street":"Bloxham Crt",
    "iso:country":"AU",
    "sg:address":"9 Bloxham Crt",
    "sg:city":"Hoppers Crossing",
    "sg:classifiers":[
        {
            "category":"Professional",
            "subcategory":"Computer Services",
            "type":"Services"
        }
    ],
    "sg:phone":"+61 417 584 168",
    "sg:postcode":"3029",
    "sg:province":"VIC",
    "sg:tags":[
        "equipment",
        "networking",
        "installation"
    ],
    "wof:name":"Aztec Computers Pty Ltd",
    "wof:placetype":"venue"
},
  "geometry": {"coordinates":[144.68066400000001,-37.871056],"type":"Point"}
}