{
  "type": "Feature",
  "properties": {
    "addr:full":"452 Pulteney St Adelaide SA 5000",
    "addr:housenumber":"452",
    "addr:postcode":"5000",
    "addr:street":"Pulteney St",
    "iso:country":"AU",
    "sg:address":"452 Pulteney St",
    "sg:city":"Adelaide",
    "sg:classifiers":[
        {
            "category":"Shopping",
            "subcategory":"Computers & Home Electronics",
            "type":"Retail Goods"
        }
    ],
    "sg:phone":"+61 8 8223 3800",
    "sg:postcode":"5000",
    "sg:province":"SA",
    "sg:tags":[
        "equipment",
        "multimedia"
    ],
    "wof:name":"Brave New Media",
    "wof:placetype":"venue"
},
  "geometry": {"coordinates":[138.60658264200001,-34.9343147278],"type":"Point"}
}