{
  "type": "Feature",
  "properties": {
    "addr:full":"Cnr Station & Ware Sts Fairfield NSW 2165",
    "addr:postcode":"2165",
    "addr:street":"Cnr",
    "iso:country":"AU",
    "sg:address":"Cnr Station & Ware Sts",
    "sg:city":"Fairfield",
    "sg:classifiers":[
        {
            "category":"Food & Beverages",
            "subcategory":"Liquor & Beverages",
            "type":"Retail Goods"
        }
    ],
    "sg:phone":"+61 2 9725 7551",
    "sg:postcode":"2165",
    "sg:province":"NSW",
    "sg:tags":[
        "store"
    ],
    "wof:name":"Liquorland",
    "wof:placetype":"venue"
},
  "geometry": {"coordinates":[150.948455811,-33.8654747009],"type":"Point"}
}