{
  "type": "Feature",
  "properties": {
    "addr:full":"141 Brunswick Rd Brunswick VIC 3056",
    "addr:housenumber":"141",
    "addr:postcode":"3056",
    "addr:street":"Brunswick Rd",
    "iso:country":"AU",
    "sg:address":"141 Brunswick Rd",
    "sg:city":"Brunswick",
    "sg:classifiers":[
        {
            "category":"Professional",
            "subcategory":"Employment Agencies",
            "type":"Services"
        }
    ],
    "sg:phone":"+61 3 9387 5670",
    "sg:postcode":"3056",
    "sg:province":"VIC",
    "sg:tags":[
        "hire",
        "labour",
        "contractor"
    ],
    "wof:name":"Advanced Australian Workplace Solutions Pty Ltd",
    "wof:placetype":"venue"
},
  "geometry": {"coordinates":[144.968017578,-37.7778015137],"type":"Point"}
}