{
  "type": "Feature",
  "properties": {
    "iso:country":"AU",
    "sg:address":"CityLink Customer Care, 67 Lorimer Street",
    "sg:city":"Southbank",
    "sg:classifiers":[
        {
            "category":"Organizations",
            "subcategory":"Labor Organization",
            "type":"Services"
        }
    ],
    "sg:phone":"+61 13 26 29",
    "sg:postcode":"3006",
    "sg:province":"VIC",
    "sg:tags":[
        "operator",
        "road",
        "toll"
    ],
    "sg:website":"http://www.citylink.com.au",
    "wof:name":"CityLink",
    "wof:placetype":"venue"
},
  "geometry": {"coordinates":[144.944824219,-37.8252182007],"type":"Point"}
}