{
  "type": "Feature",
  "properties": {
    "addr:full":"4/ 72 Gibbes St Chatswood NSW 2067",
    "addr:housenumber":"/ 72",
    "addr:postcode":"2067",
    "addr:street":"Gibbes St",
    "iso:country":"AU",
    "sg:address":"4/ 72 Gibbes St",
    "sg:city":"Chatswood",
    "sg:classifiers":[
        {
            "category":"Shopping",
            "subcategory":"Stationery & Office Supplies",
            "type":"Retail Goods"
        }
    ],
    "sg:phone":"+61 2 9545 1755",
    "sg:postcode":"2067",
    "sg:province":"NSW",
    "wof:name":"ATC Compact",
    "wof:placetype":"venue"
},
  "geometry": {"coordinates":[151.19854736299999,-33.7863922119],"type":"Point"}
}