{
  "type": "Feature",
  "properties": {
    "iso:country":"AU",
    "sg:address":"22 Enterprise St",
    "sg:city":"Caloundra",
    "sg:classifiers":[
        {
            "category":"Social Services",
            "type":"Services"
        }
    ],
    "sg:phone":"+61 7 5491 4829",
    "sg:postcode":"4551",
    "sg:province":"QLD",
    "sg:tags":[
        "disabled",
        "person",
        "equipment"
    ],
    "wof:name":"Accessible Transit Specialists",
    "wof:placetype":"venue"
},
  "geometry": {"coordinates":[153.11549377399999,-26.7956523895],"type":"Point"}
}