{
  "type": "Feature",
  "properties": {
    "iso:country":"AU",
    "sg:address":"18 Fisher St",
    "sg:city":"Silverwater",
    "sg:classifiers":[
        {
            "category":"Professional",
            "subcategory":"Printing & Photocopies",
            "type":"Services"
        }
    ],
    "sg:phone":"+61 2 9647 2822",
    "sg:postcode":"2128",
    "sg:province":"NSW",
    "sg:tags":[
        "screen",
        "printer"
    ],
    "wof:name":"Craftech Digital & Screen",
    "wof:placetype":"venue"
},
  "geometry": {"coordinates":[151.03791809099999,-33.8345603943],"type":"Point"}
}