{
  "type": "Feature",
  "properties": {
    "addr:full":"Shop 15 Langford Village Shopping Centre Langford WA 6147",
    "addr:housenumber":"shop 15",
    "addr:postcode":"6147",
    "addr:street":"Langford Village",
    "iso:country":"AU",
    "sg:address":"Shop 15 Langford Village Shopping Centre",
    "sg:city":"Langford",
    "sg:classifiers":[
        {
            "category":"Fast Food",
            "type":"Food & Drink"
        }
    ],
    "sg:phone":"+61 8 9451 6133",
    "sg:postcode":"6147",
    "sg:province":"WA",
    "sg:tags":[
        "away",
        "take"
    ],
    "wof:name":"Goodies Galore",
    "wof:placetype":"venue"
},
  "geometry": {"coordinates":[115.93647,-32.040379],"type":"Point"}
}