{
  "type": "Feature",
  "properties": {
    "addr:full":"10a Milson Pl O'Connor WA 6163",
    "addr:housenumber":"10a",
    "addr:postcode":"6163",
    "iso:country":"AU",
    "sg:address":"10a Milson Pl",
    "sg:city":"O'Connor",
    "sg:classifiers":[
        {
            "category":"Manufacturing",
            "subcategory":"Metals",
            "type":"Manufacturing & Wholesale Goods"
        }
    ],
    "sg:phone":"+61 8 9331 6131",
    "sg:postcode":"6163",
    "sg:province":"WA",
    "sg:tags":[
        "cutting"
    ],
    "wof:name":"Artcom Fabrication",
    "wof:placetype":"venue"
},
  "geometry": {"coordinates":[115.786621,-32.06028],"type":"Point"}
}