{
  "type": "Feature",
  "properties": {
    "addr:full":"Greenhill Rd Augusta WA 6290",
    "addr:postcode":"6290",
    "addr:street":"Greenhill Rd",
    "iso:country":"AU",
    "sg:address":"Greenhill Rd",
    "sg:city":"Augusta",
    "sg:classifiers":[
        {
            "category":"Utilities",
            "subcategory":"Electric",
            "type":"Services"
        }
    ],
    "sg:phone":"+61 8 9758 1733",
    "sg:postcode":"6290",
    "sg:province":"WA",
    "sg:tags":[
        "electrical",
        "contractor"
    ],
    "wof:name":"Haddon R & J",
    "wof:placetype":"venue"
},
  "geometry": {"coordinates":[115.13333129900001,-34.295124054],"type":"Point"}
}