{
  "type": "Feature",
  "properties": {
    "addr:full":"PO Box 783 Hamilton QLD 4007",
    "addr:postcode":"4007",
    "iso:country":"AU",
    "sg:address":"PO Box 783",
    "sg:city":"Hamilton",
    "sg:classifiers":[
        {
            "category":"Professional",
            "subcategory":"Accounting & Tax Preparation",
            "type":"Services"
        }
    ],
    "sg:phone":"+61 403 729 839",
    "sg:postcode":"4007",
    "sg:province":"QLD",
    "sg:tags":[
        "bookkeeping"
    ],
    "wof:name":"Conescu, Gabrielle",
    "wof:placetype":"venue"
},
  "geometry": {"coordinates":[153.064606,-27.4375],"type":"Point"}
}