{
  "type": "Feature",
  "properties": {
    "addr:full":"3 Rudd Crt Bridgewater SA 5155",
    "addr:housenumber":"3",
    "addr:postcode":"5155",
    "addr:street":"Rudd Crt",
    "iso:country":"AU",
    "sg:address":"3 Rudd Crt",
    "sg:city":"Bridgewater",
    "sg:classifiers":[
        {
            "category":"Manufacturing",
            "subcategory":"Apparel",
            "type":"Manufacturing & Wholesale Goods"
        }
    ],
    "sg:phone":"+61 8 8339 7872",
    "sg:postcode":"5155",
    "sg:province":"SA",
    "sg:tags":[
        "makers-up",
        "clothing"
    ],
    "wof:name":"Access Apparel",
    "wof:placetype":"venue"
},
  "geometry": {"coordinates":[138.75865173299999,-35.0045928955],"type":"Point"}
}