{
  "type": "Feature",
  "properties": {
    "addr:full":"Commercial Rd Murwillumbah NSW 2484",
    "addr:postcode":"2484",
    "addr:street":"Commercial Rd",
    "iso:country":"AU",
    "sg:address":"Commercial Rd",
    "sg:city":"Murwillumbah",
    "sg:classifiers":[
        {
            "category":"Travel",
            "subcategory":"Hotels & Motels",
            "type":"Entertainment"
        }
    ],
    "sg:phone":"+61 2 6672 4422",
    "sg:postcode":"2484",
    "sg:province":"NSW",
    "sg:tags":[
        "accommodation"
    ],
    "wof:name":"Australian Tavern",
    "wof:placetype":"venue"
},
  "geometry": {"coordinates":[153.39698791500001,-28.3319320679],"type":"Point"}
}