{
  "type": "Feature",
  "properties": {
    "addr:full":"PO Box 94 Ettalong Beach NSW 2257",
    "addr:postcode":"2257",
    "iso:country":"AU",
    "sg:address":"PO Box 94",
    "sg:city":"Ettalong Beach",
    "sg:classifiers":[
        {
            "category":"Landmark",
            "subcategory":"City Walls",
            "type":"Public Place"
        }
    ],
    "sg:phone":"+61 2 4381 0122",
    "sg:postcode":"2257",
    "sg:province":"NSW",
    "sg:tags":[
        "finish"
    ],
    "wof:name":"Ben Thain Painting",
    "wof:placetype":"venue"
},
  "geometry": {"coordinates":[151.334274292,-33.5093383789],"type":"Point"}
}