{
  "type": "Feature",
  "properties": {
    "addr:full":"204a High St Cranbourne VIC 3977",
    "addr:housenumber":"204a",
    "addr:postcode":"3977",
    "addr:street":"High St",
    "iso:country":"AU",
    "sg:address":"204a High St",
    "sg:city":"Cranbourne",
    "sg:classifiers":[
        {
            "category":"Autos & Motor Vehicles",
            "subcategory":"Auto Supplies",
            "type":"Retail Goods"
        }
    ],
    "sg:phone":"+61 3 5996 4988",
    "sg:postcode":"3977",
    "sg:province":"VIC",
    "sg:tags":[
        "tyre"
    ],
    "wof:name":"Cranbourne's Cheapest Tyres",
    "wof:placetype":"venue"
},
  "geometry": {"coordinates":[145.28248596200001,-38.1029701233],"type":"Point"}
}