{
  "type": "Feature",
  "properties": {
    "iso:country":"AU",
    "sg:address":"Ferry St",
    "sg:city":"Maryborough",
    "sg:classifiers":[
        {
            "category":"Travel",
            "subcategory":"Hotels & Motels",
            "type":"Entertainment"
        }
    ],
    "sg:phone":"+61 7 4122 2777",
    "sg:postcode":"4650",
    "sg:province":"QLD",
    "wof:name":"Comfort Inn Blue Shades Anderson Family",
    "wof:placetype":"venue"
},
  "geometry": {"coordinates":[152.693909,-25.537294],"type":"Point"}
}