{
  "type": "Feature",
  "properties": {
    "addr:full":"113 Oak St Barcaldine QLD 4725",
    "addr:housenumber":"113",
    "addr:postcode":"4725",
    "addr:street":"Oak St",
    "iso:country":"AU",
    "sg:address":"113 Oak St",
    "sg:city":"Barcaldine",
    "sg:classifiers":[
        {
            "category":"Shopping",
            "subcategory":"Crafts & Fabrics",
            "type":"Retail Goods"
        }
    ],
    "sg:phone":"+61 7 4651 1999",
    "sg:postcode":"4725",
    "sg:province":"QLD",
    "sg:tags":[
        "supply"
    ],
    "wof:name":"The Silver Thimble",
    "wof:placetype":"venue"
},
  "geometry": {"coordinates":[145.283051,-23.552086],"type":"Point"}
}