{
  "type": "Feature",
  "properties": {
    "addr:full":"108 Canal Rd Greystanes NSW 2145",
    "addr:housenumber":"108",
    "addr:postcode":"2145",
    "addr:street":"Canal Rd",
    "iso:country":"AU",
    "sg:address":"108 Canal Rd",
    "sg:city":"Greystanes",
    "sg:classifiers":[
        {
            "category":"Retail",
            "subcategory":"Repair Shop",
            "type":"Services"
        }
    ],
    "sg:phone":"+61 2 9636 2965",
    "sg:postcode":"2145",
    "sg:province":"NSW",
    "sg:tags":[
        "machine",
        "repairs",
        "part",
        "dryer",
        "washing"
    ],
    "wof:name":"ASCO Appliance Services",
    "wof:placetype":"venue"
},
  "geometry": {"coordinates":[150.956497192,-33.8361778259],"type":"Point"}
}