{
  "type": "Feature",
  "properties": {
    "addr:full":"PO Box 1551 Gladstone QLD 4680",
    "addr:postcode":"4680",
    "iso:country":"AU",
    "sg:address":"PO Box 1551",
    "sg:city":"Gladstone",
    "sg:classifiers":[
        {
            "category":"Professional",
            "subcategory":"Art Services",
            "type":"Services"
        }
    ],
    "sg:phone":"+61 427 756 364",
    "sg:postcode":"4680",
    "sg:province":"QLD",
    "sg:tags":[
        "decorator",
        "painter"
    ],
    "wof:name":"Master Painters & Decorators Gladstone",
    "wof:placetype":"venue"
},
  "geometry": {"coordinates":[151.21209716800001,-23.9871997833],"type":"Point"}
}