{
  "type": "Feature",
  "properties": {
    "addr:full":"99- 101 Maroondah Hwy Ringwood VIC 3134",
    "addr:housenumber":"101",
    "addr:postcode":"3134",
    "addr:street":"99;Maroondah Hwy",
    "iso:country":"AU",
    "sg:address":"99- 101 Maroondah Hwy",
    "sg:city":"Ringwood",
    "sg:classifiers":[
        {
            "category":"Sports & Exercise",
            "subcategory":"Ski Slope",
            "type":"Entertainment"
        }
    ],
    "sg:phone":"+61 3 9870 3111",
    "sg:postcode":"3134",
    "sg:province":"VIC",
    "sg:tags":[
        "equipment",
        "hire",
        "retail",
        "snow"
    ],
    "wof:name":"Rebel Sport",
    "wof:placetype":"venue"
},
  "geometry": {"coordinates":[145.22517395,-37.8163757324],"type":"Point"}
}