{
  "type": "Feature",
  "properties": {
    "addr:full":"6 Wilson Crt Shepparton VIC 3630",
    "addr:housenumber":"6",
    "addr:postcode":"3630",
    "addr:street":"Wilson Crt",
    "iso:country":"AU",
    "sg:address":"6 Wilson Crt",
    "sg:city":"Shepparton",
    "sg:classifiers":[
        {
            "category":"Home & Garden",
            "subcategory":"Building Materials",
            "type":"Retail Goods"
        }
    ],
    "sg:phone":"+61 3 5821 2412",
    "sg:postcode":"3630",
    "sg:province":"VIC",
    "sg:tags":[
        "tile",
        "roofing"
    ],
    "wof:name":"Rick Coates' Roof Restoration",
    "wof:placetype":"venue"
},
  "geometry": {"coordinates":[145.394775391,-36.3599357605],"type":"Point"}
}