{
  "type": "Feature",
  "properties": {
    "addr:full":"20 Eleanor St Narrabri NSW 2390",
    "addr:housenumber":"20",
    "addr:postcode":"2390",
    "addr:street":"Eleanor St",
    "iso:country":"AU",
    "sg:address":"20 Eleanor St",
    "sg:city":"Narrabri",
    "sg:classifiers":[
        {
            "category":"Wholesale",
            "subcategory":"Farm Supplies",
            "type":"Manufacturing & Wholesale Goods"
        }
    ],
    "sg:phone":"+61 2 6792 2352",
    "sg:postcode":"2390",
    "sg:province":"NSW",
    "sg:tags":[
        "feed",
        "supplement",
        "stock"
    ],
    "wof:name":"Narrabri Farm Centre",
    "wof:placetype":"venue"
},
  "geometry": {"coordinates":[149.79119873100001,-30.3270206451],"type":"Point"}
}