{
  "type": "Feature",
  "properties": {
    "iso:country":"AU",
    "sg:address":"1 Collins St",
    "sg:city":"Melbourne",
    "sg:classifiers":[
        {
            "category":"Real Estate",
            "subcategory":"Real Estate Agent",
            "type":"Services"
        }
    ],
    "sg:phone":"+61 3 9654 1111",
    "sg:postcode":"3000",
    "sg:province":"VIC",
    "wof:name":"MacEwan, O'Grady & Lockie",
    "wof:placetype":"venue"
},
  "geometry": {"coordinates":[144.97392273,-37.8134498596],"type":"Point"}
}