{
  "type": "Feature",
  "properties": {
    "addr:full":"PO Box 604 Mango Hill QLD 4509",
    "addr:postcode":"4509",
    "iso:country":"AU",
    "sg:address":"PO Box 604",
    "sg:city":"Mango Hill",
    "sg:classifiers":[
        {
            "category":"Government",
            "subcategory":"Customs House",
            "type":"Public Place"
        }
    ],
    "sg:phone":"+61 7 3491 3744",
    "sg:postcode":"4509",
    "sg:province":"QLD",
    "sg:tags":[
        "title",
        "management",
        "stratum"
    ],
    "wof:name":"Gold Key Management",
    "wof:placetype":"venue"
},
  "geometry": {"coordinates":[153.02011108400001,-27.2429904938],"type":"Point"}
}