{
  "type": "Feature",
  "properties": {
    "addr:full":"487- 489 Canterbury Rd Vermont VIC 3133",
    "addr:housenumber":"489",
    "addr:postcode":"3133",
    "addr:street":"Canterbury Rd",
    "iso:country":"AU",
    "sg:address":"487- 489 Canterbury Rd",
    "sg:city":"Vermont",
    "sg:classifiers":[
        {
            "category":"Social Services",
            "subcategory":"Child Care",
            "type":"Services"
        }
    ],
    "sg:phone":"+61 3 9874 2999",
    "sg:postcode":"3133",
    "sg:province":"VIC",
    "wof:name":"Vermont Child Care Pty Ltd",
    "wof:placetype":"venue"
},
  "geometry": {"coordinates":[145.19615173299999,-37.83568573],"type":"Point"}
}