{
  "type": "Feature",
  "properties": {
    "addr:full":"4 Mallana Crt Croydon VIC 3136",
    "addr:housenumber":"4",
    "addr:postcode":"3136",
    "addr:street":"Mallana Crt",
    "iso:country":"AU",
    "sg:address":"4 Mallana Crt",
    "sg:city":"Croydon",
    "sg:classifiers":[
        {
            "category":"Home & Garden",
            "subcategory":"Carpets & Floor Coverings",
            "type":"Retail Goods"
        }
    ],
    "sg:phone":"+61 3 9725 0155",
    "sg:postcode":"3136",
    "sg:province":"VIC",
    "sg:tags":[
        "layer",
        "planner"
    ],
    "wof:name":"P & K Tindal",
    "wof:placetype":"venue"
},
  "geometry": {"coordinates":[145.28622436500001,-37.8074226379],"type":"Point"}
}