{
  "type": "Feature",
  "properties": {
    "addr:full":"181 Darling St Dubbo NSW 2830",
    "addr:housenumber":"181",
    "addr:postcode":"2830",
    "addr:street":"Darling St",
    "iso:country":"AU",
    "sg:address":"181 Darling St",
    "sg:city":"Dubbo",
    "sg:classifiers":[
        {
            "category":"Education",
            "subcategory":"School",
            "type":"Public Place"
        }
    ],
    "sg:phone":"+61 2 6882 2399",
    "sg:postcode":"2830",
    "sg:province":"NSW",
    "sg:tags":[
        "state",
        "-",
        "nsw"
    ],
    "wof:name":"Dubbo Primary School",
    "wof:placetype":"venue"
},
  "geometry": {"coordinates":[148.60533142099999,-32.2563285828],"type":"Point"}
}