{
  "type": "Feature",
  "properties": {
    "iso:country":"AU",
    "sg:address":"2/ 48 Tenth St",
    "sg:city":"Mildura",
    "sg:classifiers":[
        {
            "category":"Professional",
            "subcategory":"Engineering",
            "type":"Services"
        }
    ],
    "sg:phone":"+61 3 5023 2870",
    "sg:postcode":"3500",
    "sg:province":"VIC",
    "sg:tags":[
        "consultant",
        "geotechnical",
        "engineer"
    ],
    "wof:name":"Civiltest Pty. Ltd.",
    "wof:placetype":"venue"
},
  "geometry": {"coordinates":[142.16812133799999,-34.1972122192],"type":"Point"}
}