{
  "type": "Feature",
  "properties": {
    "addr:full":"Lot 1 Sudlow Rd Spearwood WA 6163",
    "addr:postcode":"6163",
    "addr:street":"Sudlow Rd",
    "iso:country":"AU",
    "sg:address":"Lot 1 Sudlow Rd",
    "sg:city":"Spearwood",
    "sg:classifiers":[
        {
            "category":"Professional",
            "type":"Services"
        }
    ],
    "sg:phone":"+61 8 9434 2711",
    "sg:postcode":"6163",
    "sg:province":"WA",
    "sg:tags":[
        "transport"
    ],
    "wof:name":"Poole Lionel Transport",
    "wof:placetype":"venue"
},
  "geometry": {"coordinates":[115.80619,-32.104885],"type":"Point"}
}