{
  "type": "Feature",
  "properties": {
    "iso:country":"AU",
    "sg:address":"Kororoit Creek Rd",
    "sg:city":"Altona North",
    "sg:classifiers":[
        {
            "category":"Retail",
            "subcategory":"Driving School",
            "type":"Services"
        }
    ],
    "sg:phone":"+61 1300 659 340",
    "sg:postcode":"3025",
    "sg:province":"VIC",
    "wof:name":"Transport Industry Driver Education",
    "wof:placetype":"venue"
},
  "geometry": {"coordinates":[144.839294,-37.849167],"type":"Point"}
}