{
  "type": "Feature",
  "properties": {
    "addr:full":"8 Armstrong St Middle Park VIC 3206",
    "addr:housenumber":"8",
    "addr:postcode":"3206",
    "addr:street":"Armstrong St",
    "iso:country":"AU",
    "sg:address":"8 Armstrong St",
    "sg:city":"Middle Park",
    "sg:classifiers":[
        {
            "category":"Fast Food",
            "type":"Food & Drink"
        }
    ],
    "sg:phone":"+61 3 9682 0010",
    "sg:postcode":"3206",
    "sg:province":"VIC",
    "sg:tags":[
        "away",
        "take"
    ],
    "wof:name":"Urban Burger",
    "wof:placetype":"venue"
},
  "geometry": {"coordinates":[144.96464499999999,-37.849792],"type":"Point"}
}