{
  "type": "Feature",
  "properties": {
    "addr:full":"54 B William St Moffat Beach QLD 4551",
    "addr:housenumber":"54 b",
    "addr:postcode":"4551",
    "addr:street":"William St",
    "iso:country":"AU",
    "sg:address":"54 B William St",
    "sg:city":"Moffat Beach",
    "sg:classifiers":[
        {
            "category":"Social Services",
            "subcategory":"Adult Care",
            "type":"Services"
        }
    ],
    "sg:phone":"+61 7 5491 8896",
    "sg:postcode":"4551",
    "sg:province":"QLD",
    "sg:tags":[
        "aged"
    ],
    "wof:name":"Kabbarli Home & Community Care Assoc Inc (HACC)",
    "wof:placetype":"venue"
},
  "geometry": {"coordinates":[153.13798523,-26.793712616],"type":"Point"}
}