{
  "type": "Feature",
  "properties": {
    "iso:country":"AU",
    "sg:address":"Shop 39c Eastlakes Shopping Centre",
    "sg:city":"Eastlakes",
    "sg:classifiers":[
        {
            "category":"Shopping",
            "subcategory":"Baby Store",
            "type":"Retail Goods"
        }
    ],
    "sg:phone":"+61 2 9317 4126",
    "sg:postcode":"2018",
    "sg:province":"NSW",
    "sg:tags":[
        "children's",
        "wear"
    ],
    "wof:name":"Coco Kids Fashions",
    "wof:placetype":"venue"
},
  "geometry": {"coordinates":[151.21107482900001,-33.9239883423],"type":"Point"}
}