{
  "type": "Feature",
  "properties": {
    "addr:full":"90 Hannan St Kalgoorlie WA 6430",
    "addr:housenumber":"90",
    "addr:postcode":"6430",
    "addr:street":"Hannan St",
    "iso:country":"AU",
    "sg:address":"90 Hannan St",
    "sg:city":"Kalgoorlie",
    "sg:classifiers":[
        {
            "category":"Travel",
            "subcategory":"Hotels & Motels",
            "type":"Entertainment"
        }
    ],
    "sg:phone":"+61 8 9021 2353",
    "sg:postcode":"6430",
    "sg:province":"WA",
    "sg:tags":[
        "pub"
    ],
    "wof:name":"Grand Hotel Kalgoorlie The",
    "wof:placetype":"venue"
},
  "geometry": {"coordinates":[121.467788696,-30.7515583038],"type":"Point"}
}