{
  "type": "Feature",
  "properties": {
    "addr:full":"57 Humphries St Muswellbrook NSW 2333",
    "addr:housenumber":"57",
    "addr:postcode":"2333",
    "addr:street":"Humphries St",
    "iso:country":"AU",
    "sg:address":"57 Humphries St",
    "sg:city":"Muswellbrook",
    "sg:classifiers":[
        {
            "category":"Social Services",
            "subcategory":"Retirement Home",
            "type":"Services"
        }
    ],
    "sg:phone":"+61 422 175 039",
    "sg:postcode":"2333",
    "sg:province":"NSW",
    "sg:tags":[
        "environmental",
        "consultant",
        "pollution"
    ],
    "wof:name":"Yarrawalk",
    "wof:placetype":"venue"
},
  "geometry": {"coordinates":[150.89747619600001,-32.2527770996],"type":"Point"}
}