{
  "type": "Feature",
  "properties": {
    "iso:country":"AU",
    "sg:address":"Hender St",
    "sg:city":"Keith",
    "sg:classifiers":[
        {
            "category":"Government",
            "subcategory":"Post Office",
            "type":"Public Place"
        }
    ],
    "sg:phone":"+61 8 8755 1141",
    "sg:postcode":"5267",
    "sg:province":"SA",
    "sg:tags":[
        "postal"
    ],
    "wof:name":"Australia Post",
    "wof:placetype":"venue"
},
  "geometry": {"coordinates":[140.35369900000001,-36.098186],"type":"Point"}
}