{
  "type": "Feature",
  "properties": {
    "addr:full":"PO Box 60 Callala Beach NSW 2540",
    "addr:postcode":"2540",
    "iso:country":"AU",
    "sg:address":"PO Box 60",
    "sg:city":"Callala Beach",
    "sg:classifiers":[
        {
            "category":"Real Estate",
            "subcategory":"Architect",
            "type":"Services"
        }
    ],
    "sg:phone":"+61 2 4446 6677",
    "sg:postcode":"2540",
    "sg:province":"NSW",
    "wof:name":"David G Evans Architects",
    "wof:placetype":"venue"
},
  "geometry": {"coordinates":[150.82484435999999,-35.0159111023],"type":"Point"}
}