{
  "type": "Feature",
  "properties": {
    "addr:full":"Ground Floor 2 Mill St Perth WA 6000",
    "addr:housenumber":"2",
    "addr:postcode":"6000",
    "addr:street":"Mill St",
    "iso:country":"AU",
    "sg:address":"Ground Floor 2 Mill St",
    "sg:city":"Perth",
    "sg:classifiers":[
        {
            "category":"Real Estate",
            "subcategory":"Developer",
            "type":"Services"
        }
    ],
    "sg:phone":"+61 8 9322 1122",
    "sg:postcode":"6000",
    "sg:province":"WA",
    "sg:tags":[
        "development"
    ],
    "wof:name":"Godini Land Development Pty Ltd",
    "wof:placetype":"venue"
},
  "geometry": {"coordinates":[115.852630615,-31.954957962],"type":"Point"}
}