{
  "type": "Feature",
  "properties": {
    "addr:full":"PO Box 7081 Redland Bay QLD 4165",
    "addr:postcode":"4165",
    "iso:country":"AU",
    "sg:address":"PO Box 7081",
    "sg:city":"Redland Bay",
    "sg:classifiers":[
        {
            "category":"Building & Trades",
            "subcategory":"Landscaping Services",
            "type":"Services"
        }
    ],
    "sg:phone":"+61 7 3206 9216",
    "sg:postcode":"4165",
    "sg:province":"QLD",
    "sg:tags":[
        "designer",
        "landscape",
        "contractor"
    ],
    "wof:name":"Greenscene Landscape Design & Construction",
    "wof:placetype":"venue"
},
  "geometry": {"coordinates":[153.29371643100001,-27.6093597412],"type":"Point"}
}