{
  "type": "Feature",
  "properties": {
    "addr:full":"36 Cawley Rd Bellambi NSW 2518",
    "addr:housenumber":"36",
    "addr:postcode":"2518",
    "addr:street":"Cawley Rd",
    "iso:country":"AU",
    "sg:address":"36 Cawley Rd",
    "sg:city":"Bellambi",
    "sg:classifiers":[
        {
            "category":"Food & Beverages",
            "subcategory":"Groceries & Convenience Stores",
            "type":"Retail Goods"
        }
    ],
    "sg:phone":"+61 2 4284 5413",
    "sg:postcode":"2518",
    "sg:province":"NSW",
    "wof:name":"Mirandas Corner",
    "wof:placetype":"venue"
},
  "geometry": {"coordinates":[150.91636700000001,-34.367836],"type":"Point"}
}