{
  "type": "Feature",
  "properties": {
    "addr:full":"3/ 138 Carrington Rd Randwick NSW 2031",
    "addr:housenumber":"/ 138",
    "addr:postcode":"2031",
    "addr:street":"Carrington Rd",
    "iso:country":"AU",
    "sg:address":"3/ 138 Carrington Rd",
    "sg:city":"Randwick",
    "sg:classifiers":[
        {
            "category":"Health Services",
            "subcategory":"Health Practitioner",
            "type":"Services"
        }
    ],
    "sg:phone":"+61 2 9398 9301",
    "sg:postcode":"2031",
    "sg:province":"NSW",
    "sg:tags":[
        "psychologist"
    ],
    "wof:name":"England Mark",
    "wof:placetype":"venue"
},
  "geometry": {"coordinates":[151.251419067,-33.9098129272],"type":"Point"}
}