{
  "type": "Feature",
  "properties": {
    "addr:full":"Unit 1 & 2 / 7 - 9 Brough St Springvale VIC 3171",
    "addr:housenumber":"&;/ 7 9",
    "addr:postcode":"3171",
    "addr:street":"Brough St",
    "iso:country":"AU",
    "sg:address":"Unit 1 & 2 / 7 - 9 Brough St",
    "sg:city":"Springvale",
    "sg:classifiers":[
        {
            "category":"Education",
            "subcategory":"School",
            "type":"Public Place"
        }
    ],
    "sg:phone":"+61 3 9796 1177",
    "sg:postcode":"3171",
    "sg:province":"VIC",
    "sg:tags":[
        "teaching",
        "aid"
    ],
    "wof:name":"Objective Learning Materials",
    "wof:placetype":"venue"
},
  "geometry": {"coordinates":[145.170379639,-37.9420127869],"type":"Point"}
}