{
  "type": "Feature",
  "properties": {
    "iso:country":"AU",
    "sg:address":"6 Elsanlea Crt",
    "sg:city":"Langwarrin",
    "sg:classifiers":[
        {
            "category":"Utilities",
            "subcategory":"Refuse",
            "type":"Services"
        }
    ],
    "sg:phone":"+61 3 9786 4732",
    "sg:postcode":"3910",
    "sg:province":"VIC",
    "sg:tags":[
        "remover",
        "rubbish"
    ],
    "wof:name":"Freston M & C",
    "wof:placetype":"venue"
},
  "geometry": {"coordinates":[145.189086914,-38.1514091492],"type":"Point"}
}