{
  "type": "Feature",
  "properties": {
    "iso:country":"AU",
    "sg:address":"26 Coleman Rd",
    "sg:city":"Parkes",
    "sg:classifiers":[
        {
            "category":"Manufacturing",
            "subcategory":"Tools & Machinery",
            "type":"Manufacturing & Wholesale Goods"
        }
    ],
    "sg:phone":"+61 2 6862 2767",
    "sg:postcode":"2870",
    "sg:province":"NSW",
    "sg:tags":[
        "earth",
        "excavating",
        "moving",
        "equipment"
    ],
    "wof:name":"Brown J M & Sons Earthmoving Contractors Pty Ltd",
    "wof:placetype":"venue"
},
  "geometry": {"coordinates":[148.170975,-33.125645],"type":"Point"}
}