{
  "type": "Feature",
  "properties": {
    "addr:full":"Unit 1, 43 Myrtle St Glen Waverley VIC 3150",
    "addr:housenumber":"43",
    "addr:postcode":"3150",
    "addr:street":"Myrtle St",
    "iso:country":"AU",
    "sg:address":"Unit 1, 43 Myrtle St",
    "sg:city":"Glen Waverley",
    "sg:classifiers":[
        {
            "category":"Retail",
            "subcategory":"Auto Repair",
            "type":"Services"
        }
    ],
    "sg:phone":"+61 3 9562 5500",
    "sg:postcode":"3150",
    "sg:province":"VIC",
    "sg:tags":[
        "testing",
        "inspection",
        "motor",
        "vehicle"
    ],
    "wof:name":"Niss Serv",
    "wof:placetype":"venue"
},
  "geometry": {"coordinates":[145.15968322800001,-37.8856811523],"type":"Point"}
}