{
  "type": "Feature",
  "properties": {
    "addr:full":"12 Renmark Ave Renmark SA 5341",
    "addr:housenumber":"12",
    "addr:postcode":"5341",
    "addr:street":"Renmark Ave",
    "iso:country":"AU",
    "sg:address":"12 Renmark Ave",
    "sg:city":"Renmark",
    "sg:classifiers":[
        {
            "category":"Shopping",
            "subcategory":"Clothing, Apparel, & Fashions",
            "type":"Retail Goods"
        }
    ],
    "sg:phone":"+61 8 8586 5509",
    "sg:postcode":"5341",
    "sg:province":"SA",
    "sg:tags":[
        "lady",
        "wear"
    ],
    "wof:name":"Pol Fashions",
    "wof:placetype":"venue"
},
  "geometry": {"coordinates":[140.74206543,-34.1782951355],"type":"Point"}
}