{
  "type": "Feature",
  "properties": {
    "addr:full":"2 Crosby Hill Rd Buderim QLD 4556",
    "addr:housenumber":"2",
    "addr:postcode":"4556",
    "addr:street":"Crosby Hill Rd",
    "iso:country":"AU",
    "sg:address":"2 Crosby Hill Rd",
    "sg:city":"Buderim",
    "sg:classifiers":[
        {
            "category":"Education",
            "subcategory":"Special Training",
            "type":"Public Place"
        }
    ],
    "sg:phone":"+61 7 5445 4533",
    "sg:postcode":"4556",
    "sg:province":"QLD",
    "sg:tags":[
        "school",
        "art"
    ],
    "wof:name":"Paintbox Art School",
    "wof:placetype":"venue"
},
  "geometry": {"coordinates":[153.05128479000001,-26.6861343384],"type":"Point"}
}