{
  "type": "Feature",
  "properties": {
    "addr:full":"175 Bay St Brighton VIC 3186",
    "addr:housenumber":"175",
    "addr:postcode":"3186",
    "addr:street":"Bay St",
    "iso:country":"AU",
    "sg:address":"175 Bay St",
    "sg:city":"Brighton",
    "sg:classifiers":[
        {
            "category":"Health Services",
            "subcategory":"Health Practitioner",
            "type":"Services"
        }
    ],
    "sg:phone":"+61 3 9521 9511",
    "sg:postcode":"3186",
    "sg:province":"VIC",
    "sg:tags":[
        "hypnotherapy"
    ],
    "wof:name":"Alan R Farmer",
    "wof:placetype":"venue"
},
  "geometry": {"coordinates":[144.997756958,-37.9047393799],"type":"Point"}
}