{
  "type": "Feature",
  "properties": {
    "iso:country":"AU",
    "sg:address":"Suite 1, 25 Edgeworth David Ave",
    "sg:city":"Hornsby",
    "sg:classifiers":[
        {
            "category":"Education",
            "subcategory":"Special Training",
            "type":"Public Place"
        }
    ],
    "sg:phone":"+61 2 9412 3122",
    "sg:postcode":"2077",
    "sg:province":"NSW",
    "sg:tags":[
        "development"
    ],
    "wof:name":"Optons Enterprises",
    "wof:placetype":"venue"
},
  "geometry": {"coordinates":[151.10450744600001,-33.7062454224],"type":"Point"}
}