{
  "type": "Feature",
  "properties": {
    "iso:country":"AU",
    "sg:address":"49a Penshurst St",
    "sg:city":"Penshurst",
    "sg:classifiers":[
        {
            "category":"Restaurant",
            "type":"Food & Drink"
        }
    ],
    "sg:phone":"+61 2 9580 1963",
    "sg:postcode":"2222",
    "sg:province":"NSW",
    "wof:name":"Chun's Kitchen Penshurst Chinese",
    "wof:placetype":"venue"
},
  "geometry": {"coordinates":[151.087356567,-33.964302063],"type":"Point"}
}