{
  "type": "Feature",
  "properties": {
    "addr:full":"6 La Salle St Dudley Park SA 5008",
    "addr:housenumber":"6",
    "addr:postcode":"5008",
    "addr:street":"La Salle St",
    "iso:country":"AU",
    "sg:address":"6 La Salle St",
    "sg:city":"Dudley Park",
    "sg:classifiers":[
        {
            "category":"Home & Garden",
            "subcategory":"Hardware",
            "type":"Retail Goods"
        }
    ],
    "sg:phone":"+61 8 8269 7000",
    "sg:postcode":"5008",
    "sg:province":"SA",
    "sg:tags":[
        "generating",
        "set",
        "generator"
    ],
    "wof:name":"Genaust Power & Water Pty Ltd",
    "wof:placetype":"venue"
},
  "geometry": {"coordinates":[138.58122299999999,-34.88113],"type":"Point"}
}