{
  "type": "Feature",
  "properties": {
    "addr:full":"Unit 15, 1042 Grand Junction Rd Holden Hill SA 5088",
    "addr:housenumber":"1042",
    "addr:postcode":"5088",
    "addr:street":"Grand Junction Rd",
    "iso:country":"AU",
    "sg:address":"Unit 15, 1042 Grand Junction Rd",
    "sg:city":"Holden Hill",
    "sg:classifiers":[
        {
            "category":"Professional",
            "type":"Services"
        }
    ],
    "sg:phone":"+61 8 8264 2800",
    "sg:postcode":"5088",
    "sg:province":"SA",
    "sg:tags":[
        "coating",
        "powder"
    ],
    "wof:name":"Holden Hill Powder Coaters",
    "wof:placetype":"venue"
},
  "geometry": {"coordinates":[138.679290772,-34.8446731567],"type":"Point"}
}