{
  "type": "Feature",
  "properties": {
    "iso:country":"AU",
    "sg:address":"233 Crown St.",
    "sg:city":"Wollongong",
    "sg:classifiers":[
        {
            "category":"Wholesale",
            "subcategory":"Medical Equipment & Supplies",
            "type":"Manufacturing & Wholesale Goods"
        }
    ],
    "sg:phone":"+61 1800 040 995",
    "sg:postcode":"2500",
    "sg:province":"NSW",
    "sg:tags":[
        "aids",
        "hearing"
    ],
    "sg:website":"http://www.illawarrahearingcentre.com.au",
    "wof:name":"Illawarra Hearing Centre",
    "wof:placetype":"venue"
},
  "geometry": {"coordinates":[150.89212,-34.425159],"type":"Point"}
}