{
  "type": "Feature",
  "properties": {
    "addr:full":"158 Turpin Rd Labrador QLD 4215",
    "addr:housenumber":"158",
    "addr:postcode":"4215",
    "addr:street":"Turpin Rd",
    "iso:country":"AU",
    "sg:address":"158 Turpin Rd",
    "sg:city":"Labrador",
    "sg:classifiers":[
        {
            "category":"Professional",
            "subcategory":"Accounting & Tax Preparation",
            "type":"Services"
        }
    ],
    "sg:phone":"+61 7 5571 0030",
    "sg:postcode":"4215",
    "sg:province":"QLD",
    "sg:tags":[
        "accountant",
        "auditor"
    ],
    "wof:name":"Namro Services",
    "wof:placetype":"venue"
},
  "geometry": {"coordinates":[153.40267944300001,-27.9449806213],"type":"Point"}
}