{
  "type": "Feature",
  "properties": {
    "addr:full":"Forest St Tumut NSW 2720",
    "addr:postcode":"2720",
    "addr:street":"Forest St",
    "iso:country":"AU",
    "sg:address":"Forest St",
    "sg:city":"Tumut",
    "sg:classifiers":[
        {
            "category":"Education",
            "subcategory":"School",
            "type":"Public Place"
        }
    ],
    "sg:phone":"+61 2 6947 1533",
    "sg:postcode":"2720",
    "sg:province":"NSW",
    "sg:tags":[
        "state",
        "-",
        "nsw"
    ],
    "wof:name":"Franklin Public School",
    "wof:placetype":"venue"
},
  "geometry": {"coordinates":[148.230042,-35.314526],"type":"Point"}
}