{
  "type": "Feature",
  "properties": {
    "addr:full":"68 Albert St Preston VIC 3072",
    "addr:housenumber":"68",
    "addr:postcode":"3072",
    "addr:street":"Albert St",
    "iso:country":"AU",
    "sg:address":"68 Albert St",
    "sg:city":"Preston",
    "sg:classifiers":[
        {
            "category":"Manufacturing",
            "subcategory":"Motor Vehicles & Parts",
            "type":"Manufacturing & Wholesale Goods"
        }
    ],
    "sg:phone":"+61 3 9416 9455",
    "sg:postcode":"3072",
    "sg:province":"VIC",
    "sg:tags":[
        "replacement"
    ],
    "wof:name":"Makin & Luby Motors",
    "wof:placetype":"venue"
},
  "geometry": {"coordinates":[145.02235412600001,-37.7448158264],"type":"Point"}
}