{
  "type": "Feature",
  "properties": {
    "iso:country":"AU",
    "sg:address":"139 Kumbari Ave",
    "sg:city":"Labrador",
    "sg:classifiers":[
        {
            "category":"Professional",
            "subcategory":"Printing & Photocopies",
            "type":"Services"
        }
    ],
    "sg:phone":"+61 7 5591 1157",
    "sg:postcode":"4215",
    "sg:province":"QLD",
    "sg:tags":[
        "textile",
        "clothing"
    ],
    "wof:name":"MPS Promotional Gear",
    "wof:placetype":"venue"
},
  "geometry": {"coordinates":[153.39622497600001,-27.9502658844],"type":"Point"}
}