{
  "type": "Feature",
  "properties": {
    "addr:full":"Unit 2/ 64 Zillmere Rd Virginia QLD 4014",
    "addr:housenumber":"64",
    "addr:postcode":"4014",
    "addr:street":"Zillmere Rd",
    "iso:country":"AU",
    "sg:address":"Unit 2/ 64 Zillmere Rd",
    "sg:city":"Virginia",
    "sg:classifiers":[
        {
            "category":"Retail",
            "subcategory":"Auto Repair",
            "type":"Services"
        }
    ],
    "sg:phone":"+61 7 3265 1818",
    "sg:postcode":"4014",
    "sg:province":"QLD",
    "sg:tags":[
        "repairer",
        "motor",
        "engineer"
    ],
    "wof:name":"Platinum Automotive Solutions",
    "wof:placetype":"venue"
},
  "geometry": {"coordinates":[153.058425903,-27.3625411987],"type":"Point"}
}