{
  "type": "Feature",
  "properties": {
    "addr:full":"6 Johnson St Kotara NSW 2289",
    "addr:housenumber":"6",
    "addr:postcode":"2289",
    "addr:street":"Johnson St",
    "iso:country":"AU",
    "sg:address":"6 Johnson St",
    "sg:city":"Kotara",
    "sg:classifiers":[
        {
            "category":"Recreation",
            "subcategory":"Boat Charter",
            "type":"Entertainment"
        }
    ],
    "sg:phone":"+61 2 4942 1842",
    "sg:postcode":"2289",
    "sg:province":"NSW",
    "wof:name":"Tranquil Yacht Hire",
    "wof:placetype":"venue"
},
  "geometry": {"coordinates":[151.68690490700001,-32.9469718933],"type":"Point"}
}