{
  "type": "Feature",
  "properties": {
    "addr:full":"Barlee St Busselton WA 6280",
    "addr:postcode":"6280",
    "addr:street":"Barlee St",
    "iso:country":"AU",
    "sg:address":"Barlee St",
    "sg:city":"Busselton",
    "sg:classifiers":[
        {
            "category":"Retail",
            "subcategory":"Auto Repair",
            "type":"Services"
        }
    ],
    "sg:phone":"+61 8 9752 3244",
    "sg:postcode":"6280",
    "sg:province":"WA",
    "sg:tags":[
        "electrical"
    ],
    "wof:name":"Rod's Auto Electrics",
    "wof:placetype":"venue"
},
  "geometry": {"coordinates":[115.345497131,-33.6607627869],"type":"Point"}
}