{
  "type": "Feature",
  "properties": {
    "iso:country":"AU",
    "sg:address":"4335 South Gippsland Hwy",
    "sg:city":"Foster",
    "sg:classifiers":[
        {
            "category":"Building & Trades",
            "subcategory":"Construction",
            "type":"Services"
        }
    ],
    "sg:phone":"+61 3 5682 2117",
    "sg:postcode":"3960",
    "sg:province":"VIC",
    "sg:tags":[
        "welding"
    ],
    "wof:name":"Foster Welding & Fabrication",
    "wof:placetype":"venue"
},
  "geometry": {"coordinates":[146.244430542,-38.6446456909],"type":"Point"}
}