{
  "type": "Feature",
  "properties": {
    "iso:country":"AU",
    "sg:address":"Morses Creek Rd",
    "sg:city":"Wandiligong",
    "sg:classifiers":[
        {
            "category":"Recreation",
            "type":"Entertainment"
        }
    ],
    "sg:phone":"+61 3 5750 1480",
    "sg:postcode":"3744",
    "sg:province":"VIC",
    "sg:tags":[
        "hire",
        "tour",
        "motor",
        "cycle"
    ],
    "wof:name":"Budda's Dirt Bikes",
    "wof:placetype":"venue"
},
  "geometry": {"coordinates":[146.976685,-36.801693],"type":"Point"}
}