{
  "type": "Feature",
  "properties": {
    "addr:full":"Suite 1 , 82 Argyle St Camden NSW 2570",
    "addr:housenumber":"82",
    "addr:postcode":"2570",
    "addr:street":"Argyle St",
    "iso:country":"AU",
    "sg:address":"Suite 1 , 82 Argyle St",
    "sg:city":"Camden",
    "sg:classifiers":[
        {
            "category":"Health Services",
            "subcategory":"Health Practitioner",
            "type":"Services"
        }
    ],
    "sg:phone":"+61 2 4655 6449",
    "sg:postcode":"2570",
    "sg:province":"NSW",
    "sg:tags":[
        "naturopath"
    ],
    "wof:name":"Catherine Love",
    "wof:placetype":"venue"
},
  "geometry": {"coordinates":[150.696731567,-34.0543632507],"type":"Point"}
}