{
  "type": "Feature",
  "properties": {
    "addr:full":"3/ 14 Investigator St Nowra South NSW 2541",
    "addr:housenumber":"/ 14",
    "addr:postcode":"2541",
    "addr:street":"Investigator St",
    "iso:country":"AU",
    "sg:address":"3/ 14 Investigator St",
    "sg:city":"Nowra South",
    "sg:classifiers":[
        {
            "category":"Manufacturing",
            "subcategory":"Rubber & Plastics",
            "type":"Manufacturing & Wholesale Goods"
        }
    ],
    "sg:phone":"+61 2 4423 1215",
    "sg:postcode":"2541",
    "sg:province":"NSW",
    "sg:tags":[
        "wholesaler",
        "product",
        "mfrs"
    ],
    "wof:name":"Vision Plastics & Wholesale",
    "wof:placetype":"venue"
},
  "geometry": {"coordinates":[150.58203125,-34.909034729],"type":"Point"}
}