{
  "type": "Feature",
  "properties": {
    "addr:full":"127 St Barnabas Blv Quinns Rocks WA 6030",
    "addr:housenumber":"127",
    "addr:postcode":"6030",
    "addr:street":"St Barnabas Blv",
    "iso:country":"AU",
    "sg:address":"127 St",
    "sg:city":"Barnabas Blv Quinns Rocks",
    "sg:classifiers":[
        {
            "category":"Building & Trades",
            "subcategory":"Plumbing",
            "type":"Services"
        }
    ],
    "sg:phone":"+61 8 9562 1147",
    "sg:postcode":"6030",
    "sg:province":"WA",
    "sg:tags":[
        "plumber",
        "gasfitters"
    ],
    "wof:name":"Mates Rates",
    "wof:placetype":"venue"
},
  "geometry": {"coordinates":[115.698646545,-31.6612415314],"type":"Point"}
}