{
  "type": "Feature",
  "properties": {
    "addr:full":"91 Victoria Drv Thomastown VIC 3074",
    "addr:housenumber":"91",
    "addr:postcode":"3074",
    "addr:street":"Victoria Drv",
    "iso:country":"AU",
    "sg:address":"91 Victoria Drv",
    "sg:city":"Thomastown",
    "sg:classifiers":[
        {
            "category":"Food & Beverages",
            "subcategory":"Groceries & Convenience Stores",
            "type":"Retail Goods"
        }
    ],
    "sg:phone":"+61 3 9466 2706",
    "sg:postcode":"3074",
    "sg:province":"VIC",
    "wof:name":"Charlie's Milk Bar",
    "wof:placetype":"venue"
},
  "geometry": {"coordinates":[144.99046325699999,-37.6788673401],"type":"Point"}
}