{
  "type": "Feature",
  "properties": {
    "addr:full":"165 South Pine Rd Brendale QLD 4500",
    "addr:housenumber":"165",
    "addr:postcode":"4500",
    "addr:street":"South Pine Rd",
    "iso:country":"AU",
    "sg:address":"165 South Pine Rd",
    "sg:city":"Brendale",
    "sg:classifiers":[
        {
            "category":"Shopping",
            "subcategory":"Computers & Home Electronics",
            "type":"Retail Goods"
        }
    ],
    "sg:phone":"+61 7 3817 6900",
    "sg:postcode":"4500",
    "sg:province":"QLD",
    "sg:tags":[
        "wholesaler",
        "mfrs",
        "part",
        "electronic"
    ],
    "wof:name":"Crest Electronics",
    "wof:placetype":"venue"
},
  "geometry": {"coordinates":[152.98057556099999,-27.3263893127],"type":"Point"}
}