{
  "type": "Feature",
  "properties": {
    "iso:country":"AU",
    "sg:address":"Shp 2/ 246 Cabramatta Rd",
    "sg:city":"Cabramatta",
    "sg:classifiers":[
        {
            "category":"Wholesale",
            "subcategory":"Medical Equipment & Supplies",
            "type":"Manufacturing & Wholesale Goods"
        }
    ],
    "sg:phone":"+61 2 9755 7887",
    "sg:postcode":"2166",
    "sg:province":"NSW",
    "sg:tags":[
        "plastering"
    ],
    "wof:name":"Trade Plaster Supplies",
    "wof:placetype":"venue"
},
  "geometry": {"coordinates":[150.93479919399999,-33.8960266113],"type":"Point"}
}