{
  "type": "Feature",
  "properties": {
    "iso:country":"AU",
    "sg:address":"221 Camberwell Rd",
    "sg:city":"Hawthorn East",
    "sg:classifiers":[
        {
            "category":"Cafe",
            "type":"Food & Drink"
        }
    ],
    "sg:phone":"+61 3 9882 3422",
    "sg:postcode":"3123",
    "sg:province":"VIC",
    "wof:name":"Ta Prom Cafe",
    "wof:placetype":"venue"
},
  "geometry": {"coordinates":[145.056243897,-37.8306884766],"type":"Point"}
}