{
  "type": "Feature",
  "properties": {
    "addr:full":"6 Shaw Rd Ingleburn NSW 2565",
    "addr:housenumber":"6",
    "addr:postcode":"2565",
    "addr:street":"Shaw Rd",
    "iso:country":"AU",
    "sg:address":"6 Shaw Rd",
    "sg:city":"Ingleburn",
    "sg:classifiers":[
        {
            "category":"Wholesale",
            "subcategory":"Home Furnishings",
            "type":"Manufacturing & Wholesale Goods"
        }
    ],
    "sg:phone":"+61 2 9829 6199",
    "sg:postcode":"2565",
    "sg:province":"NSW",
    "sg:tags":[
        "wholesaler",
        "bedding",
        "mfrs",
        "bed"
    ],
    "wof:name":"Wool Products Australia Pty Ltd",
    "wof:placetype":"venue"
},
  "geometry": {"coordinates":[150.85670471200001,-34.0013084412],"type":"Point"}
}