{
  "type": "Feature",
  "properties": {
    "iso:country":"AU",
    "sg:address":"Shop 3- 61 Bridle Rd",
    "sg:city":"Morwell",
    "sg:classifiers":[
        {
            "category":"Personal",
            "subcategory":"Beauty Salon",
            "type":"Services"
        }
    ],
    "sg:phone":"+61 3 5133 3031",
    "sg:postcode":"3840",
    "sg:province":"VIC",
    "sg:tags":[
        "hairdresser"
    ],
    "wof:name":"Zaniti Hair Studio",
    "wof:placetype":"venue"
},
  "geometry": {"coordinates":[146.432403564,-38.2280006409],"type":"Point"}
}