{
  "type": "Feature",
  "properties": {
    "addr:full":"Westfield Shoppingtown 295 Gympie Rd Strathpine QLD 4500",
    "addr:housenumber":"295",
    "addr:postcode":"4500",
    "addr:street":"Gympie Rd",
    "iso:country":"AU",
    "sg:address":"Westfield Shoppingtown 295 Gympie Rd",
    "sg:city":"Strathpine",
    "sg:classifiers":[
        {
            "category":"Insurance",
            "subcategory":"Hazard Insurance",
            "type":"Services"
        }
    ],
    "sg:phone":"+61 13 11 75",
    "sg:postcode":"4500",
    "sg:province":"QLD",
    "sg:tags":[
        "motor",
        "vehicle"
    ],
    "wof:name":"Suncorp",
    "wof:placetype":"venue"
},
  "geometry": {"coordinates":[152.988845825,-27.3024139404],"type":"Point"}
}