{
  "type": "Feature",
  "properties": {
    "addr:full":"Unit 1/ 96 Grosvenor St St Kilda East VIC 3183",
    "addr:housenumber":"96",
    "addr:postcode":"3183",
    "addr:street":"Grosvenor St",
    "iso:country":"AU",
    "sg:address":"Unit 1/ 96 Grosvenor St St",
    "sg:city":"Kilda East",
    "sg:classifiers":[
        {
            "category":"Communications",
            "type":"Services"
        }
    ],
    "sg:phone":"+61 437 717 568",
    "sg:postcode":"3183",
    "sg:province":"VIC",
    "sg:tags":[
        "translation"
    ],
    "wof:name":"Salvatore Rendace",
    "wof:placetype":"venue"
},
  "geometry": {"coordinates":[144.99786376899999,-37.87342453],"type":"Point"}
}