{
  "type": "Feature",
  "properties": {
    "addr:full":"U17/ 46 Jedda Rd Prestons NSW 2170",
    "addr:postcode":"2170",
    "addr:street":"/ 46 Jedda Rd",
    "iso:country":"AU",
    "sg:address":"U17/ 46 Jedda Rd",
    "sg:city":"Prestons",
    "sg:classifiers":[
        {
            "category":"Building & Trades",
            "subcategory":"Construction",
            "type":"Services"
        }
    ],
    "sg:phone":"+61 2 9826 7300",
    "sg:postcode":"2170",
    "sg:province":"NSW",
    "sg:tags":[
        "contractor"
    ],
    "wof:name":"Dutch Harbour Group Pty Ltd",
    "wof:placetype":"venue"
},
  "geometry": {"coordinates":[150.88752746599999,-33.9348106384],"type":"Point"}
}