{
  "type": "Feature",
  "properties": {
    "addr:full":"Thompson Ave Mt Morgan QLD 4714",
    "addr:postcode":"4714",
    "addr:street":"Thompson Ave",
    "iso:country":"AU",
    "sg:address":"Thompson Ave",
    "sg:city":"Mt Morgan",
    "sg:classifiers":[
        {
            "category":"Social Services",
            "subcategory":"Child Care",
            "type":"Services"
        }
    ],
    "sg:phone":"+61 7 4938 1015",
    "sg:postcode":"4714",
    "sg:province":"QLD",
    "wof:name":"Anglicare Central Queensland Mt Morgan Child Care Centre",
    "wof:placetype":"venue"
},
  "geometry": {"coordinates":[150.38360595699999,-23.6435985565],"type":"Point"}
}