{
  "type": "Feature",
  "properties": {
    "iso:country":"AU",
    "sg:address":"Shop 112 Fordham Ave",
    "sg:city":"Camberwell",
    "sg:classifiers":[
        {
            "category":"Real Estate",
            "subcategory":"Architect",
            "type":"Services"
        }
    ],
    "sg:phone":"+61 3 9809 1100",
    "sg:postcode":"3124",
    "sg:province":"VIC",
    "sg:tags":[
        "magnet",
        "magnetic",
        "material"
    ],
    "wof:name":"Aussie Magnetic Energy Products",
    "wof:placetype":"venue"
},
  "geometry": {"coordinates":[145.07655334500001,-37.8440971375],"type":"Point"}
}