{
  "type": "Feature",
  "properties": {
    "addr:full":"34 Linden St Sutherland NSW 2232",
    "addr:housenumber":"34",
    "addr:postcode":"2232",
    "addr:street":"Linden St",
    "iso:country":"AU",
    "sg:address":"34 Linden St",
    "sg:city":"Sutherland",
    "sg:classifiers":[
        {
            "category":"Health Services",
            "subcategory":"Health Practitioner",
            "type":"Services"
        }
    ],
    "sg:phone":"+61 2 9521 2140",
    "sg:postcode":"2232",
    "sg:province":"NSW",
    "sg:tags":[
        "hypnotherapy"
    ],
    "wof:name":"Moxham Jeff Hypnotherapist",
    "wof:placetype":"venue"
},
  "geometry": {"coordinates":[151.055145264,-34.0302734375],"type":"Point"}
}