{
  "type": "Feature",
  "properties": {
    "iso:country":"AU",
    "sg:address":"8 McQuade Crt",
    "sg:city":"Noble Park North",
    "sg:classifiers":[
        {
            "category":"Education",
            "subcategory":"School",
            "type":"Public Place"
        }
    ],
    "sg:phone":"+61 3 9795 4065",
    "sg:postcode":"3174",
    "sg:province":"VIC",
    "wof:name":"Dresden Calisthenics College Inc",
    "wof:placetype":"venue"
},
  "geometry": {"coordinates":[145.19340515100001,-37.946395874],"type":"Point"}
}