{
  "type": "Feature",
  "properties": {
    "addr:full":"Lot 17 Anthony Rd Albany WA 6330",
    "addr:postcode":"6330",
    "addr:street":"Anthony Rd",
    "iso:country":"AU",
    "sg:address":"Lot 17 Anthony Rd",
    "sg:city":"Albany",
    "sg:classifiers":[
        {
            "category":"Wholesale",
            "subcategory":"Machinery & Supplies",
            "type":"Manufacturing & Wholesale Goods"
        }
    ],
    "sg:phone":"+61 8 9842 2676",
    "sg:postcode":"6330",
    "sg:province":"WA",
    "sg:tags":[
        "agricultural"
    ],
    "wof:name":"Farmers Centre (1978) Pty Ltd",
    "wof:placetype":"venue"
},
  "geometry": {"coordinates":[117.873268127,-34.9908485413],"type":"Point"}
}