{
  "type": "Feature",
  "properties": {
    "addr:full":"135 Prior St Tarragindi QLD 4121",
    "addr:housenumber":"135",
    "addr:postcode":"4121",
    "addr:street":"Prior St",
    "iso:country":"AU",
    "sg:address":"135 Prior St",
    "sg:city":"Tarragindi",
    "sg:classifiers":[
        {
            "category":"Retail",
            "subcategory":"Repair Shop",
            "type":"Services"
        }
    ],
    "sg:phone":"+61 7 3848 4345",
    "sg:postcode":"4121",
    "sg:province":"QLD",
    "sg:tags":[
        "upholsterer"
    ],
    "wof:name":"Wagner Ray Upholsterers",
    "wof:placetype":"venue"
},
  "geometry": {"coordinates":[153.03672790499999,-27.5301437378],"type":"Point"}
}