{
  "type": "Feature",
  "properties": {
    "addr:full":"1874 Goodwood Rd Goodwood QLD 4660",
    "addr:housenumber":"1874",
    "addr:postcode":"4660",
    "addr:street":"Goodwood Rd",
    "iso:country":"AU",
    "sg:address":"1874 Goodwood Rd",
    "sg:city":"Goodwood",
    "sg:classifiers":[
        {
            "category":"Farming",
            "subcategory":"Livestock Farm",
            "type":"Manufacturing & Wholesale Goods"
        }
    ],
    "sg:phone":"+61 7 4126 8338",
    "sg:postcode":"4660",
    "sg:province":"QLD",
    "sg:tags":[
        "breeder",
        "horse",
        "stud"
    ],
    "wof:name":"Circle S Miniature Horse Stud",
    "wof:placetype":"venue"
},
  "geometry": {"coordinates":[152.38621520999999,-25.1351222992],"type":"Point"}
}