{
  "type": "Feature",
  "properties": {
    "addr:full":"147 Centenary Drv Mill Park VIC 3082",
    "addr:housenumber":"147",
    "addr:postcode":"3082",
    "addr:street":"Centenary Drv",
    "iso:country":"AU",
    "sg:address":"147 Centenary Drv",
    "sg:city":"Mill Park",
    "sg:classifiers":[
        {
            "category":"Food & Beverages",
            "subcategory":"Groceries & Convenience Stores",
            "type":"Retail Goods"
        }
    ],
    "sg:phone":"+61 3 9436 7846",
    "sg:postcode":"3082",
    "sg:province":"VIC",
    "wof:name":"Centenary Drive Milk Bar",
    "wof:placetype":"venue"
},
  "geometry": {"coordinates":[145.075042725,-37.6572875977],"type":"Point"}
}