{
  "type": "Feature",
  "properties": {
    "addr:full":"19 Johnsons La Iluka NSW 2466",
    "addr:housenumber":"19",
    "addr:postcode":"2466",
    "addr:street":"Johnsons La Iluka",
    "iso:country":"AU",
    "sg:address":"19 Johnsons La",
    "sg:city":"Iluka",
    "sg:classifiers":[
        {
            "category":"Farming",
            "subcategory":"Fish & Marine Products",
            "type":"Manufacturing & Wholesale Goods"
        }
    ],
    "sg:phone":"+61 2 6646 5551",
    "sg:postcode":"2466",
    "sg:province":"NSW",
    "sg:tags":[
        "production",
        "seafood",
        "processing"
    ],
    "wof:name":"Fisherman's Freezer Pty Ltd",
    "wof:placetype":"venue"
},
  "geometry": {"coordinates":[153.35162353499999,-29.4068202972],"type":"Point"}
}