{
  "type": "Feature",
  "properties": {
    "iso:country":"AU",
    "sg:address":"13 Turill St",
    "sg:city":"Shailer Park",
    "sg:classifiers":[
        {
            "category":"Health Services",
            "subcategory":"Health Practitioner",
            "type":"Services"
        }
    ],
    "sg:phone":"+61 7 3801 5828",
    "sg:postcode":"4128",
    "sg:province":"QLD",
    "sg:tags":[
        "hypnotherapy"
    ],
    "wof:name":"Demosthonous Helene",
    "wof:placetype":"venue"
},
  "geometry": {"coordinates":[153.179244995,-27.6615104675],"type":"Point"}
}