{
  "type": "Feature",
  "properties": {
    "addr:full":"120 Batt St Penrith NSW 2750",
    "addr:housenumber":"120",
    "addr:postcode":"2750",
    "addr:street":"Batt St",
    "iso:country":"AU",
    "sg:address":"120 Batt St",
    "sg:city":"Penrith",
    "sg:classifiers":[
        {
            "category":"Shopping",
            "subcategory":"Computers & Home Electronics",
            "type":"Retail Goods"
        }
    ],
    "sg:phone":"+61 2 4722 8311",
    "sg:postcode":"2750",
    "sg:province":"NSW",
    "sg:tags":[
        "equipment",
        "supply"
    ],
    "wof:name":"AppleCentre Hills",
    "wof:placetype":"venue"
},
  "geometry": {"coordinates":[150.68168640100001,-33.7674713135],"type":"Point"}
}