{
  "type": "Feature",
  "properties": {
    "addr:full":"Cnr Kingsway & Dorcas Street, Level 1, 100 Dorcas Street Melbourne VIC 3004",
    "addr:housenumber":"100",
    "addr:postcode":"3004",
    "addr:street":"Cnr Kingsway & Dorcas Street;Dorcas Street",
    "iso:country":"AU",
    "sg:address":"Cnr Kingsway & Dorcas Street, Level 1, 100 Dorcas Street",
    "sg:city":"Melbourne",
    "sg:classifiers":[
        {
            "category":"Banks & Credit Unions",
            "subcategory":"Bank",
            "type":"Services"
        }
    ],
    "sg:phone":"+61 1300 842 346",
    "sg:postcode":"3004",
    "sg:province":"VIC",
    "sg:tags":[
        "broker",
        "mortgage"
    ],
    "wof:name":"Victoria Finance",
    "wof:placetype":"venue"
},
  "geometry": {"coordinates":[144.96600341800001,-37.8312988281],"type":"Point"}
}