{
  "type": "Feature",
  "properties": {
    "addr:full":"7503 Springfield Drv Hope Island QLD 4212",
    "addr:housenumber":"7503",
    "addr:postcode":"4212",
    "addr:street":"Springfield Drv",
    "iso:country":"AU",
    "sg:address":"7503 Springfield Drv",
    "sg:city":"Hope Island",
    "sg:classifiers":[
        {
            "category":"Travel",
            "subcategory":"Hotels & Motels",
            "type":"Entertainment"
        }
    ],
    "sg:phone":"+61 7 5514 0331",
    "sg:postcode":"4212",
    "sg:province":"QLD",
    "wof:name":"Town House Motor Inn The",
    "wof:placetype":"venue"
},
  "geometry": {"coordinates":[153.353240967,-27.8722038269],"type":"Point"}
}