{
  "type": "Feature",
  "properties": {
    "iso:country":"AU",
    "sg:address":"5 Stokes St",
    "sg:city":"Townsville",
    "sg:classifiers":[
        {
            "category":"Health Services",
            "subcategory":"Doctor",
            "type":"Services"
        }
    ],
    "sg:phone":"+61 7 4724 0026",
    "sg:postcode":"4810",
    "sg:province":"QLD",
    "sg:tags":[
        "medical",
        "practitioner"
    ],
    "wof:name":"Gillespie Dr Kerry M Medical Practice",
    "wof:placetype":"venue"
},
  "geometry": {"coordinates":[146.81454500000001,-19.25783],"type":"Point"}
}