{
  "type": "Feature",
  "properties": {
    "addr:full":"9 Sheridan St Cairns QLD 4870",
    "addr:housenumber":"9",
    "addr:postcode":"4870",
    "addr:street":"Sheridan St",
    "iso:country":"AU",
    "sg:address":"9 Sheridan St",
    "sg:city":"Cairns",
    "sg:classifiers":[
        {
            "category":"Utilities",
            "subcategory":"Mobile Phone",
            "type":"Services"
        }
    ],
    "sg:phone":"+61 7 4031 0220",
    "sg:postcode":"4870",
    "sg:province":"QLD",
    "sg:tags":[
        "repair",
        "telephone"
    ],
    "wof:name":"Cairns Battery Centre",
    "wof:placetype":"venue"
},
  "geometry": {"coordinates":[145.77772522000001,-16.9288806915],"type":"Point"}
}