{
  "type": "Feature",
  "properties": {
    "iso:country":"AU",
    "sg:address":"Shop 5",
    "sg:city":",Waratah Arcade,1067 OLd Princes Higway Engad",
    "sg:classifiers":[
        {
            "category":"Personal",
            "subcategory":"Beauty Salon",
            "type":"Services"
        }
    ],
    "sg:phone":"+61 2 9520 2862",
    "sg:postcode":"2233",
    "sg:province":"NSW",
    "sg:tags":[
        "hairdresser"
    ],
    "wof:name":"Salon De Paris",
    "wof:placetype":"venue"
},
  "geometry": {"coordinates":[151.01269531200001,-34.0654716492],"type":"Point"}
}