{
  "type": "Feature",
  "properties": {
    "iso:country":"AU",
    "sg:address":"16 Christie St St",
    "sg:city":"Leonards",
    "sg:classifiers":[
        {
            "category":"Professional",
            "subcategory":"Employment Agencies",
            "type":"Services"
        }
    ],
    "sg:phone":"+61 2 9437 4891",
    "sg:postcode":"2065",
    "sg:province":"NSW",
    "sg:tags":[
        "provider",
        "internet"
    ],
    "wof:name":"Ecommerce Suppliers Pty Ltd",
    "wof:placetype":"venue"
},
  "geometry": {"coordinates":[151.196807861,-33.8270492554],"type":"Point"}
}