{
  "type": "Feature",
  "properties": {
    "iso:country":"AU",
    "sg:address":"39 Delawney St",
    "sg:city":"Balcatta",
    "sg:classifiers":[
        {
            "category":"Government",
            "subcategory":"Department Of Motor Vehicles",
            "type":"Public Place"
        }
    ],
    "sg:phone":"+61 8 9240 5880",
    "sg:postcode":"6021",
    "sg:province":"WA",
    "sg:tags":[
        "disinfectant"
    ],
    "wof:name":"Peter Gs",
    "wof:placetype":"venue"
},
  "geometry": {"coordinates":[115.813468933,-31.8664054871],"type":"Point"}
}