{
  "type": "Feature",
  "properties": {
    "iso:country":"AU",
    "sg:address":"Woodstock St",
    "sg:city":"Newman",
    "sg:classifiers":[
        {
            "category":"Professional",
            "type":"Services"
        }
    ],
    "sg:phone":"+61 8 9175 0309",
    "sg:postcode":"6753",
    "sg:province":"WA",
    "sg:tags":[
        "transport"
    ],
    "wof:name":"Centurion",
    "wof:placetype":"venue"
},
  "geometry": {"coordinates":[119.73184967,-23.3686332703],"type":"Point"}
}