{
  "type": "Feature",
  "properties": {
    "addr:full":"710 Anzac Hwy Glenelg SA 5045",
    "addr:housenumber":"710",
    "addr:postcode":"5045",
    "addr:street":"Anzac Hwy",
    "iso:country":"AU",
    "sg:address":"710 Anzac Hwy",
    "sg:city":"Glenelg",
    "sg:classifiers":[
        {
            "category":"Health Services",
            "subcategory":"Health Practitioner",
            "type":"Services"
        }
    ],
    "sg:phone":"+61 8 8294 1411",
    "sg:postcode":"5045",
    "sg:province":"SA",
    "sg:tags":[
        "psychologist"
    ],
    "wof:name":"Litt Sandy Mr",
    "wof:placetype":"venue"
},
  "geometry": {"coordinates":[138.516693,-34.976669],"type":"Point"}
}