{
  "type": "Feature",
  "properties": {
    "addr:full":"U3/ 158 Wellington Rd Clayton VIC 3168",
    "addr:housenumber":"158",
    "addr:postcode":"3168",
    "addr:street":"U3 /;Wellington Rd",
    "iso:country":"AU",
    "sg:address":"U3/ 158 Wellington Rd",
    "sg:city":"Clayton",
    "sg:classifiers":[
        {
            "category":"Professional",
            "subcategory":"Accounting & Tax Preparation",
            "type":"Services"
        }
    ],
    "sg:phone":"+61 3 9561 5553",
    "sg:postcode":"3168",
    "sg:province":"VIC",
    "sg:tags":[
        "broom",
        "brush"
    ],
    "wof:name":"C.S.M Feather Duster Company",
    "wof:placetype":"venue"
},
  "geometry": {"coordinates":[145.14532470699999,-37.9171180725],"type":"Point"}
}