{
  "type": "Feature",
  "properties": {
    "addr:full":"252 South Creek Rd Dee Why NSW 2099",
    "addr:housenumber":"252",
    "addr:postcode":"2099",
    "addr:street":"South Creek Rd",
    "iso:country":"AU",
    "sg:address":"252 South Creek Rd",
    "sg:city":"Dee Why",
    "sg:classifiers":[
        {
            "category":"Building & Trades",
            "subcategory":"Construction",
            "type":"Services"
        }
    ],
    "sg:phone":"+61 424 311 182",
    "sg:postcode":"2099",
    "sg:province":"NSW",
    "sg:tags":[
        "earth",
        "excavating",
        "moving",
        "contractor"
    ],
    "wof:name":"Mini Digging Pty Ltd",
    "wof:placetype":"venue"
},
  "geometry": {"coordinates":[151.276809692,-33.7278556824],"type":"Point"}
}