{
  "type": "Feature",
  "properties": {
    "iso:country":"AU",
    "sg:address":"24 Fairfax Rd",
    "sg:city":"Woollamia",
    "sg:classifiers":[
        {
            "category":"Professional",
            "subcategory":"Art Services",
            "type":"Services"
        }
    ],
    "sg:phone":"+61 2 4447 8486",
    "sg:postcode":"2540",
    "sg:province":"NSW",
    "sg:tags":[
        "decorator",
        "painter"
    ],
    "wof:name":"Owen Robson",
    "wof:placetype":"venue"
},
  "geometry": {"coordinates":[150.62171935999999,-35.0092658997],"type":"Point"}
}