{
  "type": "Feature",
  "properties": {
    "iso:country":"AU",
    "sg:address":"45 Joe's Rd",
    "sg:city":"Caveside",
    "sg:classifiers":[
        {
            "category":"Farming",
            "subcategory":"Farm",
            "type":"Manufacturing & Wholesale Goods"
        }
    ],
    "sg:phone":"+61 3 6367 8162",
    "sg:postcode":"7304",
    "sg:province":"TAS",
    "sg:tags":[
        "farmer"
    ],
    "wof:name":"Parsons A R & D J",
    "wof:placetype":"venue"
},
  "geometry": {"coordinates":[146.453354,-41.5961],"type":"Point"}
}