{
  "type": "Feature",
  "properties": {
    "addr:full":"56 Talbragar St Dubbo NSW 2830",
    "addr:housenumber":"56",
    "addr:postcode":"2830",
    "addr:street":"Talbragar St",
    "iso:country":"AU",
    "sg:address":"56 Talbragar St",
    "sg:city":"Dubbo",
    "sg:classifiers":[
        {
            "category":"Real Estate",
            "subcategory":"Real Estate Services",
            "type":"Services"
        }
    ],
    "sg:phone":"+61 2 6882 6822",
    "sg:postcode":"2830",
    "sg:province":"NSW",
    "sg:tags":[
        "auctioneer"
    ],
    "wof:name":"Bob Berry Real Estate",
    "wof:placetype":"venue"
},
  "geometry": {"coordinates":[148.60336303700001,-32.2448883057],"type":"Point"}
}