{
  "type": "Feature",
  "properties": {
    "iso:country":"AU",
    "sg:address":"247 Freemans Drv",
    "sg:city":"Morisset",
    "sg:classifiers":[
        {
            "category":"Train Station",
            "subcategory":"Rail",
            "type":"Transportation"
        }
    ],
    "sg:phone":"+61 2 4977 3641",
    "sg:postcode":"2264",
    "sg:province":"NSW",
    "sg:tags":[
        "goat",
        "farmer"
    ],
    "wof:name":"Brindella Angora Goat Stud",
    "wof:placetype":"venue"
},
  "geometry": {"coordinates":[151.467072,-33.094051],"type":"Point"}
}