{
  "type": "Feature",
  "properties": {
    "addr:full":"45 Stott St Tweed Heads West NSW 2485",
    "addr:housenumber":"45",
    "addr:postcode":"2485",
    "addr:street":"Stott St",
    "iso:country":"AU",
    "sg:address":"45 Stott St",
    "sg:city":"Tweed Heads West",
    "sg:classifiers":[
        {
            "category":"Real Estate",
            "subcategory":"Real Estate Agent",
            "type":"Services"
        }
    ],
    "sg:phone":"+61 7 5599 8881",
    "sg:postcode":"2485",
    "sg:province":"NSW",
    "wof:name":"Tweed Highlands Estate",
    "wof:placetype":"venue"
},
  "geometry": {"coordinates":[153.49403381400001,-28.1924591064],"type":"Point"}
}