{
  "type": "Feature",
  "properties": {
    "addr:full":"31 Coora Rd Westleigh NSW 2120",
    "addr:housenumber":"31",
    "addr:postcode":"2120",
    "addr:street":"Coora Rd",
    "iso:country":"AU",
    "sg:address":"31 Coora Rd",
    "sg:city":"Westleigh",
    "sg:classifiers":[
        {
            "category":"Building & Trades",
            "subcategory":"Construction",
            "type":"Services"
        }
    ],
    "sg:phone":"+61 2 9875 4826",
    "sg:postcode":"2120",
    "sg:province":"NSW",
    "sg:tags":[
        "concrete",
        "contractor"
    ],
    "wof:name":"Danny Suplina",
    "wof:placetype":"venue"
},
  "geometry": {"coordinates":[151.07119750999999,-33.7069473267],"type":"Point"}
}