{
  "type": "Feature",
  "properties": {
    "addr:full":"125 Flockton St Everton Park QLD 4053",
    "addr:housenumber":"125",
    "addr:postcode":"4053",
    "addr:street":"Flockton St",
    "iso:country":"AU",
    "sg:address":"125 Flockton St",
    "sg:city":"Everton Park",
    "sg:classifiers":[
        {
            "category":"Health Services",
            "subcategory":"Doctor",
            "type":"Services"
        }
    ],
    "sg:phone":"+61 7 3353 0386",
    "sg:postcode":"4053",
    "sg:province":"QLD",
    "sg:tags":[
        "medical",
        "practitioner"
    ],
    "wof:name":"Pagliaro John A.",
    "wof:placetype":"venue"
},
  "geometry": {"coordinates":[152.99290466299999,-27.3945789337],"type":"Point"}
}