{
  "type": "Feature",
  "properties": {
    "iso:country":"AU",
    "sg:address":"661 Flinders St",
    "sg:city":"Townsville",
    "sg:classifiers":[
        {
            "category":"Banks & Credit Unions",
            "subcategory":"Investment Brokerage",
            "type":"Services"
        }
    ],
    "sg:phone":"+61 7 4724 4444",
    "sg:postcode":"4810",
    "sg:province":"QLD",
    "sg:tags":[
        "management",
        "property"
    ],
    "wof:name":"Lyn Anthony Real Estate",
    "wof:placetype":"venue"
},
  "geometry": {"coordinates":[146.809113,-19.267048],"type":"Point"}
}