{
  "type": "Feature",
  "properties": {
    "addr:full":"7 Brand Drv Thomastown VIC 3074",
    "addr:housenumber":"7",
    "addr:postcode":"3074",
    "addr:street":"Brand Drv",
    "iso:country":"AU",
    "sg:address":"7 Brand Drv",
    "sg:city":"Thomastown",
    "sg:classifiers":[
        {
            "category":"Professional",
            "subcategory":"Art Services",
            "type":"Services"
        }
    ],
    "sg:phone":"+61 3 9465 9522",
    "sg:postcode":"3074",
    "sg:province":"VIC",
    "sg:tags":[
        "graphic",
        "designer"
    ],
    "sg:website":"http://www.graphicsunlimited.com.au",
    "wof:name":"Graphics Unlimited (Vic) Pty Ltd",
    "wof:placetype":"venue"
},
  "geometry": {"coordinates":[145.03401184099999,-37.6923828125],"type":"Point"}
}