{
  "type": "Feature",
  "properties": {
    "addr:full":"26 Regent St Moama VIC 2731",
    "addr:housenumber":"26",
    "addr:postcode":"2731",
    "addr:street":"Regent St",
    "iso:country":"AU",
    "sg:address":"26 Regent St",
    "sg:city":"Moama",
    "sg:classifiers":[
        {
            "category":"Shopping",
            "subcategory":"Discount & Variety Stores",
            "type":"Retail Goods"
        }
    ],
    "sg:phone":"+61 3 5480 9909",
    "sg:postcode":"2731",
    "sg:province":"VIC",
    "sg:tags":[
        "register",
        "cash"
    ],
    "wof:name":"Rural Cash Registers & Point of Sale Systems",
    "wof:placetype":"venue"
},
  "geometry": {"coordinates":[144.77220199999999,-36.109035],"type":"Point"}
}