{
  "type": "Feature",
  "properties": {
    "addr:full":"\"Owen Park\" 201 Queen St Southport QLD 4215",
    "addr:housenumber":"201",
    "addr:postcode":"4215",
    "addr:street":"Queen St",
    "iso:country":"AU",
    "sg:address":"\"Owen Park\" 201 Queen St",
    "sg:city":"Southport",
    "sg:classifiers":[
        {
            "category":"Organizations",
            "subcategory":"Non-profit Organization",
            "type":"Services"
        }
    ],
    "sg:phone":"+61 7 5531 3312",
    "sg:postcode":"4215",
    "sg:province":"QLD",
    "sg:tags":[
        "support",
        "disability",
        "organisation"
    ],
    "wof:name":"Gold Coast Recreation & Sport Inc",
    "wof:placetype":"venue"
},
  "geometry": {"coordinates":[153.40032959000001,-27.9708309174],"type":"Point"}
}