{
  "type": "Feature",
  "properties": {
    "addr:full":"Suite 4, 40 - 42 Argyle St Camden NSW 2570",
    "addr:housenumber":"40 42",
    "addr:postcode":"2570",
    "addr:street":"Argyle St",
    "iso:country":"AU",
    "sg:address":"Suite 4, 40 - 42 Argyle St",
    "sg:city":"Camden",
    "sg:classifiers":[
        {
            "category":"Professional",
            "subcategory":"Engineering",
            "type":"Services"
        }
    ],
    "sg:phone":"+61 2 4655 5877",
    "sg:postcode":"2570",
    "sg:province":"NSW",
    "sg:tags":[
        "consulting",
        "engineer"
    ],
    "wof:name":"Siteplus",
    "wof:placetype":"venue"
},
  "geometry": {"coordinates":[150.69833374000001,-34.0536994934],"type":"Point"}
}