{
  "type": "Feature",
  "properties": {
    "addr:full":"Lot 61 First St Geraldton WA 6530",
    "addr:housenumber":"61",
    "addr:postcode":"6530",
    "addr:street":"First St",
    "iso:country":"AU",
    "sg:address":"Lot 61 First St",
    "sg:city":"Geraldton",
    "sg:classifiers":[
        {
            "category":"Fast Food",
            "type":"Food & Drink"
        }
    ],
    "sg:phone":"+61 8 9965 0666",
    "sg:postcode":"6530",
    "sg:province":"WA",
    "sg:tags":[
        "away",
        "take"
    ],
    "wof:name":"Domino's Pizza",
    "wof:placetype":"venue"
},
  "geometry": {"coordinates":[114.630058289,-28.7605800629],"type":"Point"}
}