{
  "type": "Feature",
  "properties": {
    "addr:full":"Unit 2/ 14 Mill St Mooroopna VIC 3629",
    "addr:housenumber":"14",
    "addr:postcode":"3629",
    "addr:street":"Mill St",
    "iso:country":"AU",
    "sg:address":"Unit 2/ 14 Mill St",
    "sg:city":"Mooroopna",
    "sg:classifiers":[
        {
            "category":"Health Services",
            "subcategory":"Dentist",
            "type":"Services"
        }
    ],
    "sg:phone":"+61 3 5825 2508",
    "sg:postcode":"3629",
    "sg:province":"VIC",
    "sg:tags":[
        "dental",
        "prosthetist"
    ],
    "wof:name":"Dyson Kenneth FJ",
    "wof:placetype":"venue"
},
  "geometry": {"coordinates":[145.36074829099999,-36.3927612305],"type":"Point"}
}