{
  "type": "Feature",
  "properties": {
    "addr:full":"2 Luke St Holt ACT 2615",
    "addr:housenumber":"2",
    "addr:postcode":"2615",
    "addr:street":"Luke St",
    "iso:country":"AU",
    "sg:address":"2 Luke St",
    "sg:city":"Holt",
    "sg:classifiers":[
        {
            "category":"Health Services",
            "subcategory":"Health Practitioner",
            "type":"Services"
        }
    ],
    "sg:phone":"+61 2 6254 9889",
    "sg:postcode":"2615",
    "sg:province":"ACT",
    "sg:tags":[
        "physiotherapist"
    ],
    "wof:name":"Springbett Lauren",
    "wof:placetype":"venue"
},
  "geometry": {"coordinates":[149.017852783,-35.2225456238],"type":"Point"}
}