{
  "type": "Feature",
  "properties": {
    "iso:country":"AU",
    "sg:address":"23 Wyong Rd",
    "sg:city":"Tumbi Umbi",
    "sg:classifiers":[
        {
            "category":"Fast Food",
            "type":"Food & Drink"
        }
    ],
    "sg:phone":"+61 2 4388 1619",
    "sg:postcode":"2261",
    "sg:province":"NSW",
    "sg:tags":[
        "away",
        "take"
    ],
    "wof:name":"Jolly Good Indian Restaurant",
    "wof:placetype":"venue"
},
  "geometry": {"coordinates":[151.447693,-33.362583],"type":"Point"}
}