{
  "type": "Feature",
  "properties": {
    "iso:country":"AU",
    "sg:address":"479A Keilor Rd",
    "sg:city":"Niddrie",
    "sg:classifiers":[
        {
            "category":"Shopping",
            "subcategory":"Jewelry",
            "type":"Retail Goods"
        }
    ],
    "sg:phone":"+61 3 9379 7249",
    "sg:postcode":"3042",
    "sg:province":"VIC",
    "sg:tags":[
        "jeweller"
    ],
    "wof:name":"Raymonds Jewellers",
    "wof:placetype":"venue"
},
  "geometry": {"coordinates":[144.88919067399999,-37.7361755371],"type":"Point"}
}