{
  "type": "Feature",
  "properties": {
    "addr:full":"36 Treatts Rd Lindfield NSW 2070",
    "addr:housenumber":"36",
    "addr:postcode":"2070",
    "addr:street":"Treatts Rd",
    "iso:country":"AU",
    "sg:address":"36 Treatts Rd",
    "sg:city":"Lindfield",
    "sg:classifiers":[
        {
            "category":"Building & Trades",
            "subcategory":"Pest Control",
            "type":"Services"
        }
    ],
    "sg:phone":"+61 2 9416 3347",
    "sg:postcode":"2070",
    "sg:province":"NSW",
    "sg:tags":[
        "wholesaler",
        "mfrs",
        "diary"
    ],
    "wof:name":"Agenda Diaries",
    "wof:placetype":"venue"
},
  "geometry": {"coordinates":[151.167144775,-33.7698059082],"type":"Point"}
}