{
  "type": "Feature",
  "properties": {
    "iso:country":"AU",
    "sg:address":"Shop 17a, Modbury Triangle Shopping Centre, 954 No",
    "sg:city":"Modbury",
    "sg:classifiers":[
        {
            "category":"Shopping",
            "subcategory":"Clothing, Apparel, & Fashions",
            "type":"Retail Goods"
        }
    ],
    "sg:phone":"+61 8 8395 2444",
    "sg:postcode":"5092",
    "sg:province":"SA",
    "sg:tags":[
        "jean"
    ],
    "wof:name":"The Jeans Factory",
    "wof:placetype":"venue"
},
  "geometry": {"coordinates":[138.684936523,-34.8319511414],"type":"Point"}
}