{
  "type": "Feature",
  "properties": {
    "addr:full":"Suite 2 Level 1 12 Mount St North Sydney NSW 2060",
    "addr:housenumber":"12",
    "addr:postcode":"2060",
    "addr:street":"Mount St",
    "iso:country":"AU",
    "sg:address":"Suite 2 Level 1 12 Mount St",
    "sg:city":"North Sydney",
    "sg:classifiers":[
        {
            "category":"Insurance",
            "subcategory":"Insurance Agent",
            "type":"Services"
        }
    ],
    "sg:phone":"+61 2 9955 3999",
    "sg:postcode":"2060",
    "sg:province":"NSW",
    "wof:name":"MMIA Pty Ltd",
    "wof:placetype":"venue"
},
  "geometry": {"coordinates":[151.20529174800001,-33.8384475708],"type":"Point"}
}