{
  "type": "Feature",
  "properties": {
    "addr:full":"44 Alexandra St Hunters Hill NSW 2110",
    "addr:housenumber":"44",
    "addr:postcode":"2110",
    "addr:street":"Alexandra St",
    "iso:country":"AU",
    "sg:address":"44 Alexandra St",
    "sg:city":"Hunters Hill",
    "sg:classifiers":[
        {
            "category":"Health Services",
            "subcategory":"Dentist",
            "type":"Services"
        }
    ],
    "sg:phone":"+61 2 9817 2005",
    "sg:postcode":"2110",
    "sg:province":"NSW",
    "wof:name":"Dalby Robert",
    "wof:placetype":"venue"
},
  "geometry": {"coordinates":[151.154907227,-33.8347740173],"type":"Point"}
}