{
  "type": "Feature",
  "properties": {
    "iso:country":"AU",
    "sg:address":"121 Langtree Ave",
    "sg:city":"Mildura",
    "sg:classifiers":[
        {
            "category":"Shopping",
            "subcategory":"Music",
            "type":"Retail Goods"
        }
    ],
    "sg:phone":"+61 3 5023 3662",
    "sg:postcode":"3500",
    "sg:province":"VIC",
    "sg:tags":[
        "instrument",
        "musical"
    ],
    "wof:name":"The Sound Trap",
    "wof:placetype":"venue"
},
  "geometry": {"coordinates":[142.15789794899999,-34.1869430542],"type":"Point"}
}