{
  "type": "Feature",
  "properties": {
    "addr:full":"U1/ 15 Stanley St St Ives NSW 2075",
    "addr:housenumber":"15",
    "addr:postcode":"2075",
    "addr:street":"U1 /;Stanley St",
    "iso:country":"AU",
    "sg:address":"U1/ 15 Stanley St",
    "sg:city":"St Ives",
    "sg:classifiers":[
        {
            "category":"Building & Trades",
            "subcategory":"Construction",
            "type":"Services"
        }
    ],
    "sg:phone":"+61 2 9988 4522",
    "sg:postcode":"2075",
    "sg:province":"NSW",
    "sg:tags":[
        "contractor"
    ],
    "wof:name":"Oppidan Homes Pty Ltd",
    "wof:placetype":"venue"
},
  "geometry": {"coordinates":[151.163330078,-33.7302627563],"type":"Point"}
}