{
  "type": "Feature",
  "properties": {
    "addr:full":"Suite 2, Rella House, 5 Durham Ave St Ives NSW 2075",
    "addr:housenumber":"5",
    "addr:postcode":"2075",
    "addr:street":"Durham Ave",
    "iso:country":"AU",
    "sg:address":"Suite 2, Rella House, 5 Durham Ave",
    "sg:city":"St Ives",
    "sg:classifiers":[
        {
            "category":"Shopping",
            "subcategory":"Computers & Home Electronics",
            "type":"Retail Goods"
        }
    ],
    "sg:phone":"+61 2 9838 8099",
    "sg:postcode":"2075",
    "sg:province":"NSW",
    "sg:tags":[
        "equipment",
        "supply"
    ],
    "wof:name":"Mintgold Computer Consumables",
    "wof:placetype":"venue"
},
  "geometry": {"coordinates":[151.160522461,-33.730014801],"type":"Point"}
}