{
  "type": "Feature",
  "properties": {
    "iso:country":"AU",
    "sg:address":"PO Box 1521",
    "sg:city":"Mountain Creek",
    "sg:classifiers":[
        {
            "category":"Banks & Credit Unions",
            "subcategory":"Financial Services",
            "type":"Services"
        }
    ],
    "sg:phone":"+61 7 5444 8577",
    "sg:postcode":"4557",
    "sg:province":"QLD",
    "sg:tags":[
        "loan",
        "finance",
        "mortgage"
    ],
    "wof:name":"Stallion Home Loans",
    "wof:placetype":"venue"
},
  "geometry": {"coordinates":[153.117797852,-26.6837902069],"type":"Point"}
}