{
  "type": "Feature",
  "properties": {
    "iso:country":"AU",
    "sg:address":"Suite 12 22 Fitzroy St St",
    "sg:city":"Kilda",
    "sg:classifiers":[
        {
            "category":"Professional",
            "subcategory":"Management & Consulting",
            "type":"Services"
        }
    ],
    "sg:phone":"+61 3 9536 3133",
    "sg:postcode":"3182",
    "sg:province":"VIC",
    "sg:tags":[
        "consultant"
    ],
    "wof:name":"FACT Team The",
    "wof:placetype":"venue"
},
  "geometry": {"coordinates":[144.974884033,-37.8610801697],"type":"Point"}
}