{
  "type": "Feature",
  "properties": {
    "addr:full":"4 Ash Rd Hoxton Park NSW 2171",
    "addr:housenumber":"4",
    "addr:postcode":"2171",
    "addr:street":"Ash Rd",
    "iso:country":"AU",
    "sg:address":"4 Ash Rd",
    "sg:city":"Hoxton Park",
    "sg:classifiers":[
        {
            "category":"Shopping Center",
            "type":"Public Place"
        }
    ],
    "sg:phone":"+61 1300 368 102",
    "sg:postcode":"2171",
    "sg:province":"NSW",
    "sg:tags":[
        "riveting",
        "equipment",
        "rivet"
    ],
    "wof:name":"Marson Rivets",
    "wof:placetype":"venue"
},
  "geometry": {"coordinates":[150.84803772000001,-33.9280090332],"type":"Point"}
}