{
  "type": "Feature",
  "properties": {
    "addr:full":"755 Albany Hwy East Victoria Park WA 6101",
    "addr:housenumber":"755",
    "addr:postcode":"6101",
    "addr:street":"Albany Hwy",
    "iso:country":"AU",
    "sg:address":"755 Albany Hwy",
    "sg:city":"East Victoria Park",
    "sg:classifiers":[
        {
            "category":"Professional",
            "type":"Services"
        }
    ],
    "sg:phone":"+61 8 9262 0409",
    "sg:postcode":"6101",
    "sg:province":"WA",
    "sg:tags":[
        "message",
        "answering",
        "telephone"
    ],
    "wof:name":"Centre Park Phone Answering Services",
    "wof:placetype":"venue"
},
  "geometry": {"coordinates":[115.901626587,-31.9826049805],"type":"Point"}
}