{
  "type": "Feature",
  "properties": {
    "iso:country":"AU",
    "sg:address":"Unit 1/ 1730 Hume Hwy",
    "sg:city":"Campbellfield",
    "sg:classifiers":[
        {
            "category":"Retail",
            "subcategory":"Auto Repair",
            "type":"Services"
        }
    ],
    "sg:phone":"+61 3 9357 1097",
    "sg:postcode":"3061",
    "sg:province":"VIC",
    "sg:tags":[
        "engine",
        "reconditioning"
    ],
    "wof:name":"BernieParts",
    "wof:placetype":"venue"
},
  "geometry": {"coordinates":[144.95596313499999,-37.6723709106],"type":"Point"}
}