{
  "type": "Feature",
  "properties": {
    "addr:full":"6 Moab Pl Figtree NSW 2525",
    "addr:housenumber":"6",
    "addr:postcode":"2525",
    "addr:street":"Pl",
    "iso:country":"AU",
    "sg:address":"6 Moab Pl",
    "sg:city":"Figtree",
    "sg:classifiers":[
        {
            "category":"Real Estate",
            "subcategory":"Developer",
            "type":"Services"
        }
    ],
    "sg:phone":"+61 2 4227 6444",
    "sg:postcode":"2525",
    "sg:province":"NSW",
    "sg:tags":[
        "development"
    ],
    "wof:name":"Mark Waldock Pty Ltd",
    "wof:placetype":"venue"
},
  "geometry": {"coordinates":[150.846435547,-34.420879364],"type":"Point"}
}