{
  "type": "Feature",
  "properties": {
    "addr:full":"Mt Dandenong-Tourist Rd Sassafras VIC 3787",
    "addr:postcode":"3787",
    "addr:street":"Dandenong-Tourist Rd",
    "iso:country":"AU",
    "sg:address":"Mt Dandenong-Tourist Rd",
    "sg:city":"Sassafras",
    "sg:classifiers":[
        {
            "category":"Restaurant",
            "type":"Food & Drink"
        }
    ],
    "sg:phone":"+61 3 9755 2081",
    "sg:postcode":"3787",
    "sg:province":"VIC",
    "wof:name":"Brother Jon's",
    "wof:placetype":"venue"
},
  "geometry": {"coordinates":[145.35304260300001,-37.8637390137],"type":"Point"}
}