{
  "type": "Feature",
  "properties": {
    "addr:full":"114 Goulburn St Crookwell NSW 2583",
    "addr:housenumber":"114",
    "addr:postcode":"2583",
    "addr:street":"Goulburn St",
    "iso:country":"AU",
    "sg:address":"114 Goulburn St",
    "sg:city":"Crookwell",
    "sg:classifiers":[
        {
            "category":"Retail",
            "subcategory":"Auto Repair",
            "type":"Services"
        }
    ],
    "sg:phone":"+61 2 4832 1433",
    "sg:postcode":"2583",
    "sg:province":"NSW",
    "sg:tags":[
        "repairer",
        "motor",
        "engineer"
    ],
    "wof:name":"Holden",
    "wof:placetype":"venue"
},
  "geometry": {"coordinates":[149.47312927199999,-34.4602584839],"type":"Point"}
}