{
  "type": "Feature",
  "properties": {
    "addr:full":"24 Ziems Ave Towradgi NSW 2518",
    "addr:housenumber":"24",
    "addr:postcode":"2518",
    "addr:street":"Ziems Ave",
    "iso:country":"AU",
    "sg:address":"24 Ziems Ave",
    "sg:city":"Towradgi",
    "sg:classifiers":[
        {
            "category":"Real Estate",
            "subcategory":"Architect",
            "type":"Services"
        }
    ],
    "sg:phone":"+61 403 293 298",
    "sg:postcode":"2518",
    "sg:province":"NSW",
    "sg:tags":[
        "building",
        "designer"
    ],
    "wof:name":"JHD Building Designs",
    "wof:placetype":"venue"
},
  "geometry": {"coordinates":[150.89721700000001,-34.381897],"type":"Point"}
}