{
  "type": "Feature",
  "properties": {
    "addr:full":"3 Grosvenor Rd Lindfield NSW 2070",
    "addr:housenumber":"3",
    "addr:postcode":"2070",
    "addr:street":"Grosvenor Rd",
    "iso:country":"AU",
    "sg:address":"3 Grosvenor Rd",
    "sg:city":"Lindfield",
    "sg:classifiers":[
        {
            "category":"Professional",
            "subcategory":"Management & Consulting",
            "type":"Services"
        }
    ],
    "sg:phone":"+61 2 9415 6314",
    "sg:postcode":"2070",
    "sg:province":"NSW",
    "sg:tags":[
        "consultant"
    ],
    "wof:name":"Webster Associates Pty Ltd",
    "wof:placetype":"venue"
},
  "geometry": {"coordinates":[151.169067383,-33.7815055847],"type":"Point"}
}