{
  "type": "Feature",
  "properties": {
    "iso:country":"AU",
    "sg:address":"Lot 112 Bago Rd",
    "sg:city":"Wauchope",
    "sg:classifiers":[
        {
            "category":"Building & Trades",
            "subcategory":"Construction",
            "type":"Services"
        }
    ],
    "sg:phone":"+61 409 856 113",
    "sg:postcode":"2446",
    "sg:province":"NSW",
    "sg:tags":[
        "welding"
    ],
    "wof:name":"Clarkes Fabrication & Welding Services",
    "wof:placetype":"venue"
},
  "geometry": {"coordinates":[152.729813,-31.488386],"type":"Point"}
}