{
  "type": "Feature",
  "properties": {
    "addr:full":"25 Graham St Surrey Hills VIC 3127",
    "addr:housenumber":"25",
    "addr:postcode":"3127",
    "addr:street":"Graham St",
    "iso:country":"AU",
    "sg:address":"25 Graham St",
    "sg:city":"Surrey Hills",
    "sg:classifiers":[
        {
            "category":"Banks & Credit Unions",
            "subcategory":"Financial Services",
            "type":"Services"
        }
    ],
    "sg:phone":"+61 3 9769 4153",
    "sg:postcode":"3127",
    "sg:province":"VIC",
    "sg:tags":[
        "loan",
        "finance",
        "mortgage"
    ],
    "wof:name":"Prompt Financial Services",
    "wof:placetype":"venue"
},
  "geometry": {"coordinates":[145.09753418,-37.833442688],"type":"Point"}
}