{
  "type": "Feature",
  "properties": {
    "iso:country":"AU",
    "sg:address":"51 Usher Ave",
    "sg:city":"Labrador",
    "sg:classifiers":[
        {
            "category":"Professional",
            "subcategory":"Accounting & Tax Preparation",
            "type":"Services"
        }
    ],
    "sg:phone":"+61 7 5532 6198",
    "sg:postcode":"4215",
    "sg:province":"QLD",
    "sg:tags":[
        "accountant",
        "auditor"
    ],
    "wof:name":"MPS Professional Accountants",
    "wof:placetype":"venue"
},
  "geometry": {"coordinates":[153.39158630399999,-27.9458427429],"type":"Point"}
}