{
  "type": "Feature",
  "properties": {
    "iso:country":"AU",
    "sg:address":"53 Carlton Pde",
    "sg:city":"Carlton",
    "sg:classifiers":[
        {
            "category":"Government",
            "subcategory":"Department Of Motor Vehicles",
            "type":"Public Place"
        }
    ],
    "sg:phone":"+61 2 9588 4216",
    "sg:postcode":"2218",
    "sg:province":"NSW",
    "sg:tags":[
        "machine",
        "knitting"
    ],
    "wof:name":"Singer Knitting Machine Centre",
    "wof:placetype":"venue"
},
  "geometry": {"coordinates":[151.123383,-33.968189],"type":"Point"}
}