{
  "type": "Feature",
  "properties": {
    "addr:full":"66 Allwood Pde Albany WA 6330",
    "addr:housenumber":"66",
    "addr:postcode":"6330",
    "addr:street":"Allwood Pde",
    "iso:country":"AU",
    "sg:address":"66 Allwood Pde",
    "sg:city":"Albany",
    "sg:classifiers":[
        {
            "category":"Manufacturing",
            "subcategory":"Food",
            "type":"Manufacturing & Wholesale Goods"
        }
    ],
    "sg:phone":"+61 8 9844 7996",
    "sg:postcode":"6330",
    "sg:province":"WA",
    "sg:tags":[
        "function",
        "catering"
    ],
    "wof:name":"Lisa Scanlons Catering Service",
    "wof:placetype":"venue"
},
  "geometry": {"coordinates":[117.943222046,-34.9775543213],"type":"Point"}
}