{
  "type": "Feature",
  "properties": {
    "addr:full":"624/ Blackshaw Ave Mortdale NSW 2223",
    "addr:housenumber":"624 / blackshaw",
    "addr:postcode":"2223",
    "addr:street":"Ave",
    "iso:country":"AU",
    "sg:address":"624/ Blackshaw Ave",
    "sg:city":"Mortdale",
    "sg:classifiers":[
        {
            "category":"Manufacturing",
            "subcategory":"Glass & Minerals",
            "type":"Manufacturing & Wholesale Goods"
        }
    ],
    "sg:phone":"+61 2 9586 2440",
    "sg:postcode":"2223",
    "sg:province":"NSW",
    "sg:tags":[
        "merchant",
        "granite",
        "marble"
    ],
    "wof:name":"M P Solid Surface Fabrication P/L",
    "wof:placetype":"venue"
},
  "geometry": {"coordinates":[151.07231140100001,-33.9694480896],"type":"Point"}
}