{
  "type": "Feature",
  "properties": {
    "addr:full":"19 Garfield St Wentworthville NSW 2145",
    "addr:housenumber":"19",
    "addr:postcode":"2145",
    "addr:street":"Garfield St",
    "iso:country":"AU",
    "sg:address":"19 Garfield St",
    "sg:city":"Wentworthville",
    "sg:classifiers":[
        {
            "category":"Shopping",
            "subcategory":"Party Supplies",
            "type":"Retail Goods"
        }
    ],
    "sg:phone":"+61 2 9896 1122",
    "sg:postcode":"2145",
    "sg:province":"NSW",
    "wof:name":"Wenty Party Hire",
    "wof:placetype":"venue"
},
  "geometry": {"coordinates":[150.969436645,-33.808681488],"type":"Point"}
}