{
  "type": "Feature",
  "properties": {
    "iso:country":"AU",
    "sg:address":"24 Aemilia Ave",
    "sg:city":"Norman Park",
    "sg:classifiers":[
        {
            "category":"Professional",
            "type":"Services"
        }
    ],
    "sg:phone":"+61 7 3399 5585",
    "sg:postcode":"4170",
    "sg:province":"QLD",
    "sg:tags":[
        "quality",
        "assurance"
    ],
    "wof:name":"Clarke Management Services Pty Ltd",
    "wof:placetype":"venue"
},
  "geometry": {"coordinates":[153.068756103,-27.4783592224],"type":"Point"}
}