{
  "type": "Feature",
  "properties": {
    "addr:full":"290 Timor St Warrnambool VIC 3280",
    "addr:housenumber":"290",
    "addr:postcode":"3280",
    "addr:street":"Timor St",
    "iso:country":"AU",
    "sg:address":"290 Timor St",
    "sg:city":"Warrnambool",
    "sg:classifiers":[
        {
            "category":"Health Services",
            "subcategory":"Health Practitioner",
            "type":"Services"
        }
    ],
    "sg:phone":"+61 3 5561 1435",
    "sg:postcode":"3280",
    "sg:province":"VIC",
    "sg:tags":[
        "physiotherapist"
    ],
    "wof:name":"Cooney John",
    "wof:placetype":"venue"
},
  "geometry": {"coordinates":[142.476028442,-38.3824462891],"type":"Point"}
}