{
  "type": "Feature",
  "properties": {
    "iso:country":"AU",
    "sg:address":"Shop 348 Centro",
    "sg:city":"Bankstown",
    "sg:classifiers":[
        {
            "category":"Shopping",
            "subcategory":"Jewelry",
            "type":"Retail Goods"
        }
    ],
    "sg:phone":"+61 2 4942 1661",
    "sg:postcode":"2200",
    "sg:province":"NSW",
    "sg:tags":[
        "jeweller"
    ],
    "wof:name":"Vivien's Jewellers",
    "wof:placetype":"venue"
},
  "geometry": {"coordinates":[151.034164,-33.914791],"type":"Point"}
}