{
  "type": "Feature",
  "properties": {
    "addr:full":"Shop 10 Plaza Arc Vulcan St Moruya NSW 2537",
    "addr:housenumber":"shop 10",
    "addr:postcode":"2537",
    "addr:street":"Plaza Arc Vulcan St",
    "iso:country":"AU",
    "sg:address":"Shop 10 Plaza Arc Vulcan St",
    "sg:city":"Moruya",
    "sg:classifiers":[
        {
            "category":"Shopping",
            "subcategory":"Beauty & Cosmetics",
            "type":"Retail Goods"
        }
    ],
    "sg:phone":"+61 2 4474 3595",
    "sg:postcode":"2537",
    "sg:province":"NSW",
    "wof:name":"Glamour Girl",
    "wof:placetype":"venue"
},
  "geometry": {"coordinates":[150.08018493599999,-35.9132499695],"type":"Point"}
}