{
  "type": "Feature",
  "properties": {
    "addr:full":"489 Middleborough Rd Box Hill North VIC 3129",
    "addr:housenumber":"489",
    "addr:postcode":"3129",
    "addr:street":"Middleborough Rd",
    "iso:country":"AU",
    "sg:address":"489 Middleborough Rd",
    "sg:city":"Box Hill North",
    "sg:classifiers":[
        {
            "category":"Building & Trades",
            "subcategory":"Cleaning & Sanitation",
            "type":"Services"
        }
    ],
    "sg:phone":"+61 3 9890 4730",
    "sg:postcode":"3129",
    "sg:province":"VIC",
    "sg:tags":[
        "cleaner",
        "repairer",
        "roof"
    ],
    "wof:name":"Rooftone Services Pty Ltd",
    "wof:placetype":"venue"
},
  "geometry": {"coordinates":[145.139968872,-37.8114967346],"type":"Point"}
}