{
  "type": "Feature",
  "properties": {
    "addr:full":"38 Sarton Rd Clayton VIC 3168",
    "addr:housenumber":"38",
    "addr:postcode":"3168",
    "addr:street":"Sarton Rd",
    "iso:country":"AU",
    "sg:address":"38 Sarton Rd",
    "sg:city":"Clayton",
    "sg:classifiers":[
        {
            "category":"Banks & Credit Unions",
            "subcategory":"Investment Brokerage",
            "type":"Services"
        }
    ],
    "sg:phone":"+61 3 9543 4277",
    "sg:postcode":"3168",
    "sg:province":"VIC",
    "sg:tags":[
        "directory",
        "notice",
        "board"
    ],
    "wof:name":"Consolidated Graphics Pty Ltd",
    "wof:placetype":"venue"
},
  "geometry": {"coordinates":[145.143875122,-37.9220809937],"type":"Point"}
}