{
  "type": "Feature",
  "properties": {
    "iso:country":"AU",
    "sg:address":"12 Stuart St",
    "sg:city":"North Ward",
    "sg:classifiers":[
        {
            "category":"Professional",
            "subcategory":"Testing Lab",
            "type":"Services"
        }
    ],
    "sg:phone":"+61 7 4721 4033",
    "sg:postcode":"4810",
    "sg:province":"QLD",
    "sg:tags":[
        "inspection"
    ],
    "wof:name":"Archicentre",
    "wof:placetype":"venue"
},
  "geometry": {"coordinates":[146.807343,-19.247898],"type":"Point"}
}