{
  "type": "Feature",
  "properties": {
    "iso:country":"AU",
    "sg:address":"30 Commercial St",
    "sg:city":"Willaura",
    "sg:classifiers":[
        {
            "category":"Professional",
            "subcategory":"Art Services",
            "type":"Services"
        }
    ],
    "sg:phone":"+61 417 165 584",
    "sg:postcode":"3379",
    "sg:province":"VIC",
    "sg:tags":[
        "decorator",
        "painter"
    ],
    "wof:name":"Sturt D & I",
    "wof:placetype":"venue"
},
  "geometry": {"coordinates":[142.739776611,-37.542930603],"type":"Point"}
}