{
  "type": "Feature",
  "properties": {
    "addr:full":"80 Cook Pde St Clair NSW 2759",
    "addr:housenumber":"80",
    "addr:postcode":"2759",
    "addr:street":"Cook Pde",
    "iso:country":"AU",
    "sg:address":"80 Cook Pde",
    "sg:city":"St Clair",
    "sg:classifiers":[
        {
            "category":"Health Services",
            "subcategory":"Doctor",
            "type":"Services"
        }
    ],
    "sg:phone":"+61 2 9670 5583",
    "sg:postcode":"2759",
    "sg:province":"NSW",
    "sg:tags":[
        "medical",
        "practitioner"
    ],
    "wof:name":"Torrance E",
    "wof:placetype":"venue"
},
  "geometry": {"coordinates":[150.77616882300001,-33.8048744202],"type":"Point"}
}