{
  "type": "Feature",
  "properties": {
    "iso:country":"AU",
    "sg:address":"70 Gladstone St",
    "sg:city":"South Melbourne",
    "sg:classifiers":[
        {
            "category":"Military Area",
            "subcategory":"Air Force Base",
            "type":"Public Place"
        }
    ],
    "sg:phone":"+61 3 9696 8999",
    "sg:postcode":"3205",
    "sg:province":"VIC",
    "sg:tags":[
        "fibre",
        "optic"
    ],
    "wof:name":"Computer Environment Services",
    "wof:placetype":"venue"
},
  "geometry": {"coordinates":[144.9505,-37.830265],"type":"Point"}
}