{
  "type": "Feature",
  "properties": {
    "addr:full":"Shop 21 Roxburgh Pk Roxburgh Park VIC 3064",
    "addr:housenumber":"shop 21",
    "addr:postcode":"3064",
    "addr:street":"Roxburgh Pk",
    "iso:country":"AU",
    "sg:address":"Shop 21 Roxburgh Pk",
    "sg:city":"Roxburgh Park",
    "sg:classifiers":[
        {
            "category":"Fast Food",
            "type":"Food & Drink"
        }
    ],
    "sg:phone":"+61 13 11 66",
    "sg:postcode":"3064",
    "sg:province":"VIC",
    "sg:tags":[
        "away",
        "take"
    ],
    "wof:name":"Pizza Hut Delivery",
    "wof:placetype":"venue"
},
  "geometry": {"coordinates":[144.92434692399999,-37.6232528687],"type":"Point"}
}