{
  "type": "Feature",
  "properties": {
    "iso:country":"AU",
    "sg:address":"43 Government Rd",
    "sg:city":"Weston",
    "sg:classifiers":[
        {
            "category":"Manufacturing",
            "subcategory":"Tools & Machinery",
            "type":"Manufacturing & Wholesale Goods"
        }
    ],
    "sg:phone":"+61 2 4938 9603",
    "sg:postcode":"2326",
    "sg:province":"NSW",
    "sg:tags":[
        "toolmaker"
    ],
    "wof:name":"Ausscot Engineering Pty Ltd",
    "wof:placetype":"venue"
},
  "geometry": {"coordinates":[151.46522522000001,-32.8104057312],"type":"Point"}
}