{
  "type": "Feature",
  "properties": {
    "iso:country":"AU",
    "sg:address":"7 Tumbi Creek Rd",
    "sg:city":"Berkeley Vale",
    "sg:classifiers":[
        {
            "category":"Wholesale",
            "subcategory":"Home Furnishings",
            "type":"Manufacturing & Wholesale Goods"
        }
    ],
    "sg:phone":"+61 2 4388 4044",
    "sg:postcode":"2261",
    "sg:province":"NSW",
    "sg:tags":[
        "wholesaler",
        "bedding",
        "mfrs",
        "bed"
    ],
    "wof:name":"Cot Wholesalers",
    "wof:placetype":"venue"
},
  "geometry": {"coordinates":[151.444672,-33.359768],"type":"Point"}
}