{
  "type": "Feature",
  "properties": {
    "iso:country":"AU",
    "sg:address":"140 Karne St",
    "sg:city":"Roselands",
    "sg:classifiers":[
        {
            "category":"Arts & Performance",
            "subcategory":"Dance",
            "type":"Entertainment"
        }
    ],
    "sg:phone":"+61 2 9153 9230",
    "sg:postcode":"2196",
    "sg:province":"NSW",
    "sg:tags":[
        "theatrical",
        "ballet",
        "tuition"
    ],
    "wof:name":"Komplete Dance Studio",
    "wof:placetype":"venue"
},
  "geometry": {"coordinates":[151.065887,-33.93708],"type":"Point"}
}