{
  "type": "Feature",
  "properties": {
    "iso:country":"AU",
    "sg:address":"Shop 6, Batehaven Shopping Mall",
    "sg:city":"Batehaven",
    "sg:classifiers":[
        {
            "category":"Personal",
            "subcategory":"Barber",
            "type":"Services"
        }
    ],
    "sg:phone":"+61 2 4472 3797",
    "sg:postcode":"2536",
    "sg:province":"NSW",
    "wof:name":"Anna's Cut Above",
    "wof:placetype":"venue"
},
  "geometry": {"coordinates":[150.205688477,-35.734790802],"type":"Point"}
}