{
  "type": "Feature",
  "properties": {
    "iso:country":"AU",
    "sg:address":"1301 Warrenheip St",
    "sg:city":"Buninyong",
    "sg:classifiers":[
        {
            "category":"Health Services",
            "subcategory":"Health Practitioner",
            "type":"Services"
        }
    ],
    "sg:phone":"+61 418 527 411",
    "sg:postcode":"3357",
    "sg:province":"VIC",
    "sg:tags":[
        "reiki"
    ],
    "wof:name":"Mary Bunting",
    "wof:placetype":"venue"
},
  "geometry": {"coordinates":[143.88107299999999,-37.659924],"type":"Point"}
}