{
  "type": "Feature",
  "properties": {
    "addr:full":"33 Killara Rd Campbellfield VIC 3061",
    "addr:housenumber":"33",
    "addr:postcode":"3061",
    "addr:street":"Killara Rd",
    "iso:country":"AU",
    "sg:address":"33 Killara Rd",
    "sg:city":"Campbellfield",
    "sg:classifiers":[
        {
            "category":"Retail",
            "subcategory":"Laundry & Dry Cleaning",
            "type":"Services"
        }
    ],
    "sg:phone":"+61 3 9357 7186",
    "sg:postcode":"3061",
    "sg:province":"VIC",
    "sg:tags":[
        "cloth",
        "supply"
    ],
    "wof:name":"A Grade Supplier Co.",
    "wof:placetype":"venue"
},
  "geometry": {"coordinates":[144.964187622,-37.6656608582],"type":"Point"}
}