{
  "type": "Feature",
  "properties": {
    "addr:full":"251 Blackburn Rd Doncaster East VIC 3109",
    "addr:housenumber":"251",
    "addr:postcode":"3109",
    "addr:street":"Blackburn Rd",
    "iso:country":"AU",
    "sg:address":"251 Blackburn Rd",
    "sg:city":"Doncaster East",
    "sg:classifiers":[
        {
            "category":"Real Estate",
            "subcategory":"Real Estate Agent",
            "type":"Services"
        }
    ],
    "sg:phone":"+61 3 9841 7666",
    "sg:postcode":"3109",
    "sg:province":"VIC",
    "wof:name":"Dawn Gordon Real Estate",
    "wof:placetype":"venue"
},
  "geometry": {"coordinates":[145.16317749000001,-37.7816047668],"type":"Point"}
}