{
  "type": "Feature",
  "properties": {
    "addr:full":"Osborne Ave Bundanoon NSW 2578",
    "addr:postcode":"2578",
    "addr:street":"Osborne Ave",
    "iso:country":"AU",
    "sg:address":"Osborne Ave",
    "sg:city":"Bundanoon",
    "sg:classifiers":[
        {
            "category":"Home & Garden",
            "subcategory":"Carpets & Floor Coverings",
            "type":"Retail Goods"
        }
    ],
    "sg:phone":"+61 2 4883 6454",
    "sg:postcode":"2578",
    "sg:province":"NSW",
    "sg:tags":[
        "tile",
        "wall",
        "layer"
    ],
    "wof:name":"Connolly P E & S J",
    "wof:placetype":"venue"
},
  "geometry": {"coordinates":[150.30209350600001,-34.6560401917],"type":"Point"}
}