{
  "type": "Feature",
  "properties": {
    "iso:country":"AU",
    "sg:address":"311 Manns Rd",
    "sg:city":"Gosford",
    "sg:classifiers":[
        {
            "category":"Building & Trades",
            "subcategory":"Equipment Rental",
            "type":"Services"
        }
    ],
    "sg:phone":"+61 2 4323 3844",
    "sg:postcode":"2250",
    "sg:province":"NSW",
    "sg:tags":[
        "builder",
        "contractor"
    ],
    "wof:name":"Ace Forklift Services",
    "wof:placetype":"venue"
},
  "geometry": {"coordinates":[151.32191467300001,-33.4177093506],"type":"Point"}
}