{
  "type": "Feature",
  "properties": {
    "iso:country":"AU",
    "sg:address":"98 Wentworth Ave",
    "sg:city":"Kingston",
    "sg:classifiers":[
        {
            "category":"Autos & Motor Vehicles",
            "subcategory":"Fuel & Gas Station",
            "type":"Retail Goods"
        }
    ],
    "sg:phone":"+61 2 6295 9464",
    "sg:postcode":"2604",
    "sg:province":"ACT",
    "wof:name":"Mobil Oil Australia Pty Ltd",
    "wof:placetype":"venue"
},
  "geometry": {"coordinates":[149.14820861800001,-35.3215332031],"type":"Point"}
}