{
  "type": "Feature",
  "properties": {
    "addr:full":"U22/ 3 Jackman St Southport QLD 4215",
    "addr:housenumber":"3",
    "addr:postcode":"4215",
    "addr:street":"/;Jackman St",
    "iso:country":"AU",
    "sg:address":"U22/ 3 Jackman St",
    "sg:city":"Southport",
    "sg:classifiers":[
        {
            "category":"Shopping",
            "type":"Retail Goods"
        }
    ],
    "sg:phone":"+61 7 5528 0698",
    "sg:postcode":"4215",
    "sg:province":"QLD",
    "sg:tags":[
        "clearance",
        "factory",
        "outlet"
    ],
    "wof:name":"Australian Factory Outlet",
    "wof:placetype":"venue"
},
  "geometry": {"coordinates":[153.403564453,-27.9676074982],"type":"Point"}
}