{
  "type": "Feature",
  "properties": {
    "addr:full":"277 Auburn Rd Hawthorn VIC 3122",
    "addr:housenumber":"277",
    "addr:postcode":"3122",
    "addr:street":"Auburn Rd",
    "iso:country":"AU",
    "sg:address":"277 Auburn Rd",
    "sg:city":"Hawthorn",
    "sg:classifiers":[
        {
            "category":"Travel",
            "subcategory":"Hotels & Motels",
            "type":"Entertainment"
        }
    ],
    "sg:phone":"+61 3 9882 3361",
    "sg:postcode":"3122",
    "sg:province":"VIC",
    "sg:tags":[
        "pub"
    ],
    "wof:name":"Riversdale Hotel",
    "wof:placetype":"venue"
},
  "geometry": {"coordinates":[145.04182434099999,-37.8390083313],"type":"Point"}
}