{
  "type": "Feature",
  "properties": {
    "addr:full":"14 Angle Rd Euroa VIC 3666",
    "addr:housenumber":"14",
    "addr:postcode":"3666",
    "addr:street":"Angle Rd",
    "iso:country":"AU",
    "sg:address":"14 Angle Rd",
    "sg:city":"Euroa",
    "sg:classifiers":[
        {
            "category":"Retail",
            "subcategory":"Veterinary Services",
            "type":"Services"
        }
    ],
    "sg:phone":"+61 3 5795 1333",
    "sg:postcode":"3666",
    "sg:province":"VIC",
    "sg:tags":[
        "surgeon"
    ],
    "wof:name":"Seven Creeks Equine Veterinary Clinic",
    "wof:placetype":"venue"
},
  "geometry": {"coordinates":[145.54031372099999,-36.7697219849],"type":"Point"}
}