{
  "type": "Feature",
  "properties": {
    "addr:full":"111a Pittwater Rd Hunters Hill NSW 2110",
    "addr:housenumber":"111a",
    "addr:postcode":"2110",
    "addr:street":"Pittwater Rd",
    "iso:country":"AU",
    "sg:address":"111a Pittwater Rd",
    "sg:city":"Hunters Hill",
    "sg:classifiers":[
        {
            "category":"Shopping",
            "subcategory":"Crafts & Fabrics",
            "type":"Retail Goods"
        }
    ],
    "sg:phone":"+61 2 9817 2733",
    "sg:postcode":"2110",
    "sg:province":"NSW",
    "sg:tags":[
        "supply"
    ],
    "wof:name":"Material Obsession",
    "wof:placetype":"venue"
},
  "geometry": {"coordinates":[151.13713073700001,-33.8192253113],"type":"Point"}
}