{
  "type": "Feature",
  "properties": {
    "addr:full":"Lot 2 Railway Pde Granville NSW 2142",
    "addr:housenumber":"2",
    "addr:postcode":"2142",
    "addr:street":"Railway Pde",
    "iso:country":"AU",
    "sg:address":"Lot 2 Railway Pde",
    "sg:city":"Granville",
    "sg:classifiers":[
        {
            "category":"Transit Center",
            "subcategory":"Freight",
            "type":"Transportation"
        }
    ],
    "sg:phone":"+61 411 691 471",
    "sg:postcode":"2142",
    "sg:province":"NSW",
    "sg:tags":[
        "forklift",
        "truck"
    ],
    "wof:name":"Active Forklift Repairs",
    "wof:placetype":"venue"
},
  "geometry": {"coordinates":[151.00971984899999,-33.8319091797],"type":"Point"}
}