{
  "type": "Feature",
  "properties": {
    "addr:full":"91 Main Rd Boolaroo NSW 2284",
    "addr:housenumber":"91",
    "addr:postcode":"2284",
    "addr:street":"Main Rd",
    "iso:country":"AU",
    "sg:address":"91 Main Rd",
    "sg:city":"Boolaroo",
    "sg:classifiers":[
        {
            "category":"Real Estate",
            "subcategory":"Real Estate Agent",
            "type":"Services"
        }
    ],
    "sg:phone":"+61 2 4958 8555",
    "sg:postcode":"2284",
    "sg:province":"NSW",
    "wof:name":"Love Realty.Com.Au",
    "wof:placetype":"venue"
},
  "geometry": {"coordinates":[151.62223815900001,-32.9551124573],"type":"Point"}
}