{
  "type": "Feature",
  "properties": {
    "addr:full":"220b Nicholson Rd Subiaco WA 6008",
    "addr:housenumber":"220b",
    "addr:postcode":"6008",
    "addr:street":"Nicholson Rd",
    "iso:country":"AU",
    "sg:address":"220b Nicholson Rd",
    "sg:city":"Subiaco",
    "sg:classifiers":[
        {
            "category":"Health Services",
            "subcategory":"Chiropractor",
            "type":"Services"
        }
    ],
    "sg:phone":"+61 8 9388 9188",
    "sg:postcode":"6008",
    "sg:province":"WA",
    "wof:name":"Zen Clinic",
    "wof:placetype":"venue"
},
  "geometry": {"coordinates":[115.81417083700001,-31.9561595917],"type":"Point"}
}