{
  "type": "Feature",
  "properties": {
    "addr:full":"Mitcham Square Shopping Centre 21\\\\ 119 Belair Road Torrens Park SA 5062",
    "addr:housenumber":"21 \\ \\ 119",
    "addr:postcode":"5062",
    "addr:street":"Mitcham;Belair Road",
    "iso:country":"AU",
    "sg:address":"Mitcham Square Shopping Centre 21\\\\ 119 Belair Road",
    "sg:city":"Torrens Park",
    "sg:classifiers":[
        {
            "category":"Health Services",
            "subcategory":"Dentist",
            "type":"Services"
        }
    ],
    "sg:phone":"+61 8 8272 2040",
    "sg:postcode":"5062",
    "sg:province":"SA",
    "wof:name":"Preventive Dentistry",
    "wof:placetype":"venue"
},
  "geometry": {"coordinates":[138.60960388199999,-34.9762954712],"type":"Point"}
}