{
  "type": "Feature",
  "properties": {
    "addr:full":"70 Boolcarrol Rd Wee Waa NSW 2388",
    "addr:housenumber":"70",
    "addr:postcode":"2388",
    "addr:street":"Boolcarrol Rd",
    "iso:country":"AU",
    "sg:address":"70 Boolcarrol Rd",
    "sg:city":"Wee Waa",
    "sg:classifiers":[
        {
            "category":"Manufacturing",
            "subcategory":"Chemicals & Compounds",
            "type":"Manufacturing & Wholesale Goods"
        }
    ],
    "sg:phone":"+61 2 6795 3210",
    "sg:postcode":"2388",
    "sg:province":"NSW",
    "sg:tags":[
        "agricultural"
    ],
    "wof:name":"Total Ag Services Pty Ltd",
    "wof:placetype":"venue"
},
  "geometry": {"coordinates":[149.437591553,-30.2241535187],"type":"Point"}
}