{
  "type": "Feature",
  "properties": {
    "addr:full":"44 Endevour St Sans Souci NSW 2219",
    "addr:housenumber":"44",
    "addr:postcode":"2219",
    "addr:street":"Endevour St",
    "iso:country":"AU",
    "sg:address":"44 Endevour St",
    "sg:city":"Sans Souci",
    "sg:classifiers":[
        {
            "category":"Recreation",
            "subcategory":"Boat Charter",
            "type":"Entertainment"
        }
    ],
    "sg:phone":"+61 417 065 728",
    "sg:postcode":"2219",
    "sg:province":"NSW",
    "sg:tags":[
        "hire",
        "drive"
    ],
    "wof:name":"Botany Bay Rent-A-Yacht",
    "wof:placetype":"venue"
},
  "geometry": {"coordinates":[151.12416099999999,-33.995659],"type":"Point"}
}