{
  "type": "Feature",
  "properties": {
    "iso:country":"AU",
    "sg:address":"Shop 37 Childs Rd",
    "sg:city":"Mill Park",
    "sg:classifiers":[
        {
            "category":"Personal",
            "subcategory":"Beauty Salon",
            "type":"Services"
        }
    ],
    "sg:phone":"+61 3 9404 3724",
    "sg:postcode":"3082",
    "sg:province":"VIC",
    "sg:tags":[
        "hairdresser"
    ],
    "wof:name":"Winning Post Unisex Hairdresser's The",
    "wof:placetype":"venue"
},
  "geometry": {"coordinates":[145.02525329599999,-37.66040802],"type":"Point"}
}