{
  "type": "Feature",
  "properties": {
    "addr:full":"PO Box 84 Tarlee SA 5411",
    "addr:postcode":"5411",
    "iso:country":"AU",
    "sg:address":"PO Box 84",
    "sg:city":"Tarlee",
    "sg:classifiers":[
        {
            "category":"Farming",
            "subcategory":"Farm",
            "type":"Manufacturing & Wholesale Goods"
        }
    ],
    "sg:phone":"+61 8 8528 2217",
    "sg:postcode":"5411",
    "sg:province":"SA",
    "sg:tags":[
        "farmer"
    ],
    "wof:name":"Horgan M J, L M & TG",
    "wof:placetype":"venue"
},
  "geometry": {"coordinates":[138.771026611,-34.2742004395],"type":"Point"}
}