{
  "type": "Feature",
  "properties": {
    "iso:country":"AU",
    "sg:address":"26b/ 28 Wyuna Crt",
    "sg:city":"Hemmant",
    "sg:classifiers":[
        {
            "category":"Autos & Motor Vehicles",
            "subcategory":"Boat Sales",
            "type":"Retail Goods"
        }
    ],
    "sg:phone":"+61 7 3893 1128",
    "sg:postcode":"4174",
    "sg:province":"QLD",
    "sg:tags":[
        "builder",
        "yacht",
        "repairer"
    ],
    "wof:name":"Marine Engineering Solutions",
    "wof:placetype":"venue"
},
  "geometry": {"coordinates":[153.13218689000001,-27.4342422485],"type":"Point"}
}