{
  "type": "Feature",
  "properties": {
    "addr:full":"Unit 2, 444- 446 South Gippsland Hwy Dandenong South VIC 3164",
    "addr:housenumber":"444 446",
    "addr:postcode":"3164",
    "addr:street":"South Gippsland Hwy",
    "iso:country":"AU",
    "sg:address":"Unit 2, 444- 446 South Gippsland Hwy",
    "sg:city":"Dandenong South",
    "sg:classifiers":[
        {
            "category":"Building & Trades",
            "subcategory":"Construction",
            "type":"Services"
        }
    ],
    "sg:phone":"+61 3 8795 2424",
    "sg:postcode":"3164",
    "sg:province":"VIC",
    "sg:tags":[
        "home",
        "air conditioning"
    ],
    "wof:name":"Celair",
    "wof:placetype":"venue"
},
  "geometry": {"coordinates":[145.24473571799999,-38.0341720581],"type":"Point"}
}