{
  "type": "Feature",
  "properties": {
    "addr:full":"15 Talus St Naremburn NSW 2065",
    "addr:housenumber":"15",
    "addr:postcode":"2065",
    "addr:street":"Talus St",
    "iso:country":"AU",
    "sg:address":"15 Talus St",
    "sg:city":"Naremburn",
    "sg:classifiers":[
        {
            "category":"Education",
            "subcategory":"Special Training",
            "type":"Public Place"
        }
    ],
    "sg:phone":"+61 2 9439 7999",
    "sg:postcode":"2065",
    "sg:province":"NSW",
    "sg:tags":[
        "development"
    ],
    "wof:name":"Trent Mind & Memory Development Pty Ltd",
    "wof:placetype":"venue"
},
  "geometry": {"coordinates":[151.195236206,-33.8182449341],"type":"Point"}
}