{
  "type": "Feature",
  "properties": {
    "addr:full":"36 Alfred St South Melbourne VIC 3205",
    "addr:housenumber":"36",
    "addr:postcode":"3205",
    "addr:street":"Alfred St",
    "iso:country":"AU",
    "sg:address":"36 Alfred St",
    "sg:city":"South Melbourne",
    "sg:classifiers":[
        {
            "category":"Wholesale",
            "subcategory":"Apparel",
            "type":"Manufacturing & Wholesale Goods"
        }
    ],
    "sg:phone":"+61 3 9686 2233",
    "sg:postcode":"3205",
    "sg:province":"VIC",
    "sg:tags":[
        "wholesaler",
        "mfrs",
        "sportswear",
        "women's"
    ],
    "wof:name":"Bella Bustiere",
    "wof:placetype":"venue"
},
  "geometry": {"coordinates":[144.94953899999999,-37.832016],"type":"Point"}
}