{
  "type": "Feature",
  "properties": {
    "addr:full":"38 Russell St Tumut NSW 2720",
    "addr:housenumber":"38",
    "addr:postcode":"2720",
    "addr:street":"Russell St",
    "iso:country":"AU",
    "sg:address":"38 Russell St",
    "sg:city":"Tumut",
    "sg:classifiers":[
        {
            "category":"Real Estate",
            "subcategory":"Real Estate Agent",
            "type":"Services"
        }
    ],
    "sg:phone":"+61 2 6947 1544",
    "sg:postcode":"2720",
    "sg:province":"NSW",
    "wof:name":"Elders Milton Archer Real Estate",
    "wof:placetype":"venue"
},
  "geometry": {"coordinates":[148.223724,-35.302921],"type":"Point"}
}