{
  "type": "Feature",
  "properties": {
    "addr:full":"5th Flr 380 Queen St Brisbane QLD 4000",
    "addr:housenumber":"380",
    "addr:postcode":"4000",
    "addr:street":"Queen St",
    "iso:country":"AU",
    "sg:address":"5th Flr 380 Queen St",
    "sg:city":"Brisbane",
    "sg:classifiers":[
        {
            "category":"Professional",
            "subcategory":"Computer Services",
            "type":"Services"
        }
    ],
    "sg:phone":"+61 7 3220 0422",
    "sg:postcode":"4000",
    "sg:province":"QLD",
    "sg:tags":[
        "consultant",
        "system"
    ],
    "wof:name":"Practitioner Technologies",
    "wof:placetype":"venue"
},
  "geometry": {"coordinates":[153.03007507300001,-27.4657096863],"type":"Point"}
}