{
  "type": "Feature",
  "properties": {
    "addr:full":"695-697 Rathdowne St Carlton North VIC 3054",
    "addr:housenumber":"695-697",
    "addr:postcode":"3054",
    "addr:street":"Rathdowne St",
    "iso:country":"AU",
    "sg:address":"695-697 Rathdowne St",
    "sg:city":"Carlton North",
    "sg:classifiers":[
        {
            "category":"Health Services",
            "subcategory":"Doctor",
            "type":"Services"
        }
    ],
    "sg:phone":"+61 3 9349 1116",
    "sg:postcode":"3054",
    "sg:province":"VIC",
    "sg:tags":[
        "medical",
        "practitioner"
    ],
    "wof:name":"Tan Dr. Christina",
    "wof:placetype":"venue"
},
  "geometry": {"coordinates":[144.97178649899999,-37.7886505127],"type":"Point"}
}