{
  "type": "Feature",
  "properties": {
    "addr:full":"91 Kew St Welshpool WA 6106",
    "addr:housenumber":"91",
    "addr:postcode":"6106",
    "addr:street":"Kew St",
    "iso:country":"AU",
    "sg:address":"91 Kew St",
    "sg:city":"Welshpool",
    "sg:classifiers":[
        {
            "category":"Professional",
            "subcategory":"Engineering",
            "type":"Services"
        }
    ],
    "sg:phone":"+61 8 9470 4844",
    "sg:postcode":"6106",
    "sg:province":"WA",
    "sg:tags":[
        "engineer"
    ],
    "wof:name":"Prime Precision Machining Services",
    "wof:placetype":"venue"
},
  "geometry": {"coordinates":[115.929656982,-31.9866256714],"type":"Point"}
}