{
  "type": "Feature",
  "properties": {
    "iso:country":"AU",
    "sg:address":"337 River St",
    "sg:city":"Kempsey",
    "sg:classifiers":[
        {
            "category":"Education",
            "subcategory":"Special Training",
            "type":"Public Place"
        }
    ],
    "sg:phone":"+61 2 6562 5556",
    "sg:postcode":"2440",
    "sg:province":"NSW",
    "sg:tags":[
        "development"
    ],
    "wof:name":"Booroongen College",
    "wof:placetype":"venue"
},
  "geometry": {"coordinates":[152.800293,-31.058666],"type":"Point"}
}