{
  "type": "Feature",
  "properties": {
    "addr:full":"337 River St Kempsey NSW 2440",
    "addr:housenumber":"337",
    "addr:postcode":"2440",
    "addr:street":"River St",
    "iso:country":"AU",
    "sg:address":"337 River St",
    "sg:city":"Kempsey",
    "sg:classifiers":[
        {
            "category":"Education",
            "subcategory":"Special Training",
            "type":"Public Place"
        }
    ],
    "sg:phone":"+61 2 6562 5556",
    "sg:postcode":"2440",
    "sg:province":"NSW",
    "sg:tags":[
        "development"
    ],
    "wof:name":"Booroongen College",
    "wof:placetype":"venue"
},
  "geometry": {"coordinates":[152.80029300000001,-31.058666],"type":"Point"}
}