{
  "type": "Feature",
  "properties": {
    "addr:full":"507 Norwest Central, 12 Century Cct Baulkham Hills NSW 2153",
    "addr:housenumber":"507;12",
    "addr:postcode":"2153",
    "addr:street":"Norwest Central;Century Cct",
    "iso:country":"AU",
    "sg:address":"507 Norwest Central, 12",
    "sg:city":"Century Cct Baulkham Hills",
    "sg:classifiers":[
        {
            "category":"Banks & Credit Unions",
            "subcategory":"Financial Services",
            "type":"Services"
        }
    ],
    "sg:phone":"+61 2 8853 2694",
    "sg:postcode":"2153",
    "sg:province":"NSW",
    "sg:tags":[
        "planning"
    ],
    "wof:name":"Count Wealth Accountants",
    "wof:placetype":"venue"
},
  "geometry": {"coordinates":[150.989624023,-33.7578811646],"type":"Point"}
}