{
  "type": "Feature",
  "properties": {
    "addr:full":"27 Central Ave Sunshine VIC 3020",
    "addr:housenumber":"27",
    "addr:postcode":"3020",
    "addr:street":"Central Ave",
    "iso:country":"AU",
    "sg:address":"27 Central Ave",
    "sg:city":"Sunshine",
    "sg:classifiers":[
        {
            "category":"Manufacturing",
            "subcategory":"Glass & Minerals",
            "type":"Manufacturing & Wholesale Goods"
        }
    ],
    "sg:phone":"+61 3 9310 2233",
    "sg:postcode":"3020",
    "sg:province":"VIC",
    "sg:tags":[
        "merchant",
        "granite",
        "marble"
    ],
    "wof:name":"3 Star Marble",
    "wof:placetype":"venue"
},
  "geometry": {"coordinates":[144.835114,-37.798008],"type":"Point"}
}