{
  "type": "Feature",
  "properties": {
    "addr:full":"Lv 1 18 Duke St Sunshine Beach QLD 4567",
    "addr:housenumber":"18",
    "addr:postcode":"4567",
    "addr:street":"Duke St",
    "iso:country":"AU",
    "sg:address":"Lv 1 18 Duke St",
    "sg:city":"Sunshine Beach",
    "sg:classifiers":[
        {
            "category":"Professional",
            "subcategory":"Accounting & Tax Preparation",
            "type":"Services"
        }
    ],
    "sg:phone":"+61 7 5455 4700",
    "sg:postcode":"4567",
    "sg:province":"QLD",
    "sg:tags":[
        "accountant",
        "auditor"
    ],
    "wof:name":"First Class Accounts",
    "wof:placetype":"venue"
},
  "geometry": {"coordinates":[153.109451294,-26.4057273865],"type":"Point"}
}