{
  "type": "Feature",
  "properties": {
    "iso:country":"AU",
    "sg:address":"155 Macquarie St",
    "sg:city":"Parramatta",
    "sg:classifiers":[
        {
            "category":"Real Estate",
            "subcategory":"Real Estate Agent",
            "type":"Services"
        }
    ],
    "sg:phone":"+61 2 9635 7500",
    "sg:postcode":"2150",
    "sg:province":"NSW",
    "wof:name":"Baillieu Knight Frank",
    "wof:placetype":"venue"
},
  "geometry": {"coordinates":[151.057174683,-33.9093017578],"type":"Point"}
}