{
  "type": "Feature",
  "properties": {
    "addr:full":"26 Young St Frankston VIC 3199",
    "addr:housenumber":"26",
    "addr:postcode":"3199",
    "addr:street":"Young St",
    "iso:country":"AU",
    "sg:address":"26 Young St",
    "sg:city":"Frankston",
    "sg:classifiers":[
        {
            "category":"Professional",
            "subcategory":"Accounting & Tax Preparation",
            "type":"Services"
        }
    ],
    "sg:phone":"+61 3 9783 2233",
    "sg:postcode":"3199",
    "sg:province":"VIC",
    "sg:tags":[
        "consultant",
        "taxation"
    ],
    "wof:name":"H&R Block",
    "wof:placetype":"venue"
},
  "geometry": {"coordinates":[145.095046997,-37.9101257324],"type":"Point"}
}