{
  "type": "Feature",
  "properties": {
    "iso:country":"AU",
    "sg:address":"38 William St",
    "sg:city":"Rockhampton",
    "sg:classifiers":[
        {
            "category":"Personal",
            "subcategory":"Beauty Salon",
            "type":"Services"
        }
    ],
    "sg:phone":"+61 7 4922 4255",
    "sg:postcode":"4700",
    "sg:province":"QLD",
    "sg:tags":[
        "hairdresser"
    ],
    "wof:name":"Total Hair Obsession",
    "wof:placetype":"venue"
},
  "geometry": {"coordinates":[150.50881957999999,-23.38347435],"type":"Point"}
}