{
  "type": "Feature",
  "properties": {
    "iso:country":"AU",
    "sg:address":"Suite C34/6 654 Pacific Hwy",
    "sg:city":"Kanwal",
    "sg:classifiers":[
        {
            "category":"Health Services",
            "subcategory":"Doctor",
            "type":"Services"
        }
    ],
    "sg:phone":"+61 2 4392 7733",
    "sg:postcode":"2259",
    "sg:province":"NSW",
    "sg:tags":[
        "medical",
        "practitioner"
    ],
    "wof:name":"Blackburn James Dr",
    "wof:placetype":"venue"
},
  "geometry": {"coordinates":[151.48776245100001,-33.2538909912],"type":"Point"}
}