{
  "type": "Feature",
  "properties": {
    "addr:full":"87 New England Hwy Branxton NSW 2335",
    "addr:housenumber":"87",
    "addr:postcode":"2335",
    "addr:street":"New England Hwy",
    "iso:country":"AU",
    "sg:address":"87 New England Hwy",
    "sg:city":"Branxton",
    "sg:classifiers":[
        {
            "category":"Autos & Motor Vehicles",
            "subcategory":"Auto Supplies",
            "type":"Retail Goods"
        }
    ],
    "sg:phone":"+61 2 4938 1633",
    "sg:postcode":"2335",
    "sg:province":"NSW",
    "sg:tags":[
        "tyre"
    ],
    "wof:name":"Branxton Mechanical & Tyres",
    "wof:placetype":"venue"
},
  "geometry": {"coordinates":[151.37942504899999,-32.6717300415],"type":"Point"}
}