{
  "type": "Feature",
  "properties": {
    "addr:full":"Main Rd Myrniong VIC 3341",
    "addr:postcode":"3341",
    "addr:street":"Main Rd",
    "iso:country":"AU",
    "sg:address":"Main Rd",
    "sg:city":"Myrniong",
    "sg:classifiers":[
        {
            "category":"Travel",
            "subcategory":"Hotels & Motels",
            "type":"Entertainment"
        }
    ],
    "sg:phone":"+61 3 5368 7243",
    "sg:postcode":"3341",
    "sg:province":"VIC",
    "sg:tags":[
        "accommodation"
    ],
    "wof:name":"Myrniong Hotel Motel",
    "wof:placetype":"venue"
},
  "geometry": {"coordinates":[144.34458923299999,-37.6191482544],"type":"Point"}
}