{
  "type": "Feature",
  "properties": {
    "addr:full":"7 Kokoda Ave Wahroonga NSW 2076",
    "addr:housenumber":"7",
    "addr:postcode":"2076",
    "addr:street":"Kokoda Ave",
    "iso:country":"AU",
    "sg:address":"7 Kokoda Ave",
    "sg:city":"Wahroonga",
    "sg:classifiers":[
        {
            "category":"Professional",
            "subcategory":"Management & Consulting",
            "type":"Services"
        }
    ],
    "sg:phone":"+61 2 9487 4880",
    "sg:postcode":"2076",
    "sg:province":"NSW",
    "sg:tags":[
        "consultant"
    ],
    "wof:name":"Sinclair Associates Pty Ltd",
    "wof:placetype":"venue"
},
  "geometry": {"coordinates":[151.14047241200001,-33.7162857056],"type":"Point"}
}