{
  "type": "Feature",
  "properties": {
    "addr:full":"123 Bouverie St Carlton VIC 3053",
    "addr:housenumber":"123",
    "addr:postcode":"3053",
    "addr:street":"Bouverie St",
    "iso:country":"AU",
    "sg:address":"123 Bouverie St",
    "sg:city":"Carlton",
    "sg:classifiers":[
        {
            "category":"Retail",
            "subcategory":"Auto Repair",
            "type":"Services"
        }
    ],
    "sg:phone":"+61 3 9349 2700",
    "sg:postcode":"3053",
    "sg:province":"VIC",
    "sg:tags":[
        "repairer",
        "motor",
        "engineer"
    ],
    "wof:name":"Mobile Car Care",
    "wof:placetype":"venue"
},
  "geometry": {"coordinates":[144.96174621599999,-37.8036499023],"type":"Point"}
}