{
  "type": "Feature",
  "properties": {
    "addr:full":"2/ 2 Shepherd St Darwin NT 0800",
    "addr:housenumber":"/ 2",
    "addr:postcode":"nt 0800",
    "addr:street":"Shepherd St",
    "iso:country":"AU",
    "sg:address":"2/ 2 Shepherd St",
    "sg:city":"Darwin",
    "sg:classifiers":[
        {
            "category":"Personal",
            "subcategory":"Tattoo Parlor",
            "type":"Services"
        }
    ],
    "sg:phone":"+61 8 8941 2344",
    "sg:postcode":"0800",
    "sg:province":"NT",
    "sg:tags":[
        "resume"
    ],
    "wof:name":"Darwin Human Resource & Computer Academy",
    "wof:placetype":"venue"
},
  "geometry": {"coordinates":[130.839477539,-12.458571434],"type":"Point"}
}