{
  "type": "Feature",
  "properties": {
    "addr:full":"58 Shepherd St Marrickville NSW 2204",
    "addr:housenumber":"58",
    "addr:postcode":"2204",
    "addr:street":"Shepherd St",
    "iso:country":"AU",
    "sg:address":"58 Shepherd St",
    "sg:city":"Marrickville",
    "sg:classifiers":[
        {
            "category":"Manufacturing",
            "subcategory":"Textiles",
            "type":"Manufacturing & Wholesale Goods"
        }
    ],
    "sg:phone":"+61 2 9550 9577",
    "sg:postcode":"2204",
    "sg:province":"NSW",
    "sg:tags":[
        "mill"
    ],
    "wof:name":"Bellinda Fabrics",
    "wof:placetype":"venue"
},
  "geometry": {"coordinates":[151.162735,-33.904766],"type":"Point"}
}