{
  "type": "Feature",
  "properties": {
    "addr:full":"13 Lemko Pl Penrith NSW 2740",
    "addr:housenumber":"13",
    "addr:postcode":"2740",
    "addr:street":"Lemko Pl",
    "iso:country":"AU",
    "sg:address":"13 Lemko Pl",
    "sg:city":"Penrith",
    "sg:classifiers":[
        {
            "category":"Retail",
            "subcategory":"Auto Rental",
            "type":"Services"
        }
    ],
    "sg:phone":"+61 2 4730 6999",
    "sg:postcode":"2740",
    "sg:province":"NSW",
    "sg:tags":[
        "bus",
        "truck"
    ],
    "wof:name":"Avis",
    "wof:placetype":"venue"
},
  "geometry": {"coordinates":[150.69233700000001,-33.736561],"type":"Point"}
}