{
  "type": "Feature",
  "properties": {
    "addr:full":"Neville Pl Griffith NSW 2680",
    "addr:postcode":"2680",
    "addr:street":"Neville Pl",
    "iso:country":"AU",
    "sg:address":"Neville Pl",
    "sg:city":"Griffith",
    "sg:classifiers":[
        {
            "category":"Education",
            "subcategory":"University",
            "type":"Public Place"
        }
    ],
    "sg:phone":"+61 2 6962 0444",
    "sg:postcode":"2680",
    "sg:province":"NSW",
    "sg:tags":[
        "college",
        "tertiary"
    ],
    "wof:name":"TAFE NSW Riverina Institute",
    "wof:placetype":"venue"
},
  "geometry": {"coordinates":[146.03684999999999,-34.286861],"type":"Point"}
}