{
  "type": "Feature",
  "properties": {
    "iso:country":"AU",
    "sg:address":"33 Princess St",
    "sg:city":"Seddon",
    "sg:classifiers":[
        {
            "category":"Professional",
            "subcategory":"Art Services",
            "type":"Services"
        }
    ],
    "sg:phone":"+61 3 9396 1981",
    "sg:postcode":"3011",
    "sg:province":"VIC",
    "sg:tags":[
        "graphic",
        "designer"
    ],
    "wof:name":"Lena Nappa Design",
    "wof:placetype":"venue"
},
  "geometry": {"coordinates":[144.89561462399999,-37.8105430603],"type":"Point"}
}