{
  "type": "Feature",
  "properties": {
    "iso:country":"AU",
    "sg:address":"337 Swan St",
    "sg:city":"Richmond",
    "sg:classifiers":[
        {
            "category":"Home & Garden",
            "subcategory":"Hardware",
            "type":"Retail Goods"
        }
    ],
    "sg:phone":"+61 3 9429 1211",
    "sg:postcode":"3121",
    "sg:province":"VIC",
    "sg:tags":[
        "plumber",
        "supply"
    ],
    "wof:name":"Elite Door & Tap Hardware Pty Ltd",
    "wof:placetype":"venue"
},
  "geometry": {"coordinates":[145.00453185999999,-37.8262481689],"type":"Point"}
}