{
  "type": "Feature",
  "properties": {
    "addr:full":"42 Keen Rd Ashmore QLD 4214",
    "addr:housenumber":"42",
    "addr:postcode":"4214",
    "addr:street":"Keen Rd",
    "iso:country":"AU",
    "sg:address":"42 Keen Rd",
    "sg:city":"Ashmore",
    "sg:classifiers":[
        {
            "category":"Building & Trades",
            "subcategory":"Cleaning & Sanitation",
            "type":"Services"
        }
    ],
    "sg:phone":"+61 1300 766 337",
    "sg:postcode":"4214",
    "sg:province":"QLD",
    "sg:tags":[
        "cleaner",
        "repairer",
        "roof"
    ],
    "wof:name":"Lifetime Roofing Solutions",
    "wof:placetype":"venue"
},
  "geometry": {"coordinates":[153.34788513199999,-27.966588974],"type":"Point"}
}