{
  "type": "Feature",
  "properties": {
    "addr:full":"29 Forbes St Trundle NSW 2875",
    "addr:housenumber":"29",
    "addr:postcode":"2875",
    "addr:street":"Forbes St",
    "iso:country":"AU",
    "sg:address":"29 Forbes St",
    "sg:city":"Trundle",
    "sg:classifiers":[
        {
            "category":"Government",
            "subcategory":"Post Office",
            "type":"Public Place"
        }
    ],
    "sg:phone":"+61 2 6892 1120",
    "sg:postcode":"2875",
    "sg:province":"NSW",
    "sg:tags":[
        "postal"
    ],
    "wof:name":"Australia Post",
    "wof:placetype":"venue"
},
  "geometry": {"coordinates":[147.70907600000001,-32.919266],"type":"Point"}
}