{
  "type": "Feature",
  "properties": {
    "addr:full":"U1/ 39 Shearwater Drv Taylors Beach NSW 2316",
    "addr:housenumber":"39",
    "addr:postcode":"2316",
    "addr:street":"U1 /;Shearwater Drv",
    "iso:country":"AU",
    "sg:address":"U1/ 39 Shearwater Drv",
    "sg:city":"Taylors Beach",
    "sg:classifiers":[
        {
            "category":"Real Estate",
            "subcategory":"Architect",
            "type":"Services"
        }
    ],
    "sg:phone":"+61 402 145 992",
    "sg:postcode":"2316",
    "sg:province":"NSW",
    "sg:tags":[
        "building",
        "designer"
    ],
    "wof:name":"Torren Bell",
    "wof:placetype":"venue"
},
  "geometry": {"coordinates":[152.07063299999999,-32.75272],"type":"Point"}
}