{
  "type": "Feature",
  "properties": {
    "addr:full":"Shop 9, Vermont South Shopping Centre, 495 Burwood Hwy Vermont South VIC 3133",
    "addr:housenumber":"shop 9;495",
    "addr:postcode":"3133",
    "addr:street":"Burwood Hwy",
    "iso:country":"AU",
    "sg:address":"Shop 9, Vermont South Shopping Centre, 495 Burwood Hwy",
    "sg:city":"Vermont South",
    "sg:classifiers":[
        {
            "category":"Food & Beverages",
            "subcategory":"Bakery",
            "type":"Retail Goods"
        }
    ],
    "sg:phone":"+61 3 9802 4590",
    "sg:postcode":"3133",
    "sg:province":"VIC",
    "sg:tags":[
        "baker"
    ],
    "wof:name":"Bakers Delight Ltd",
    "wof:placetype":"venue"
},
  "geometry": {"coordinates":[145.180541992,-37.8559684753],"type":"Point"}
}