{
  "type": "Feature",
  "properties": {
    "addr:full":"801b Ballarat Rd Deer Park VIC 3023",
    "addr:housenumber":"801b",
    "addr:postcode":"3023",
    "addr:street":"Ballarat Rd",
    "iso:country":"AU",
    "sg:address":"801b Ballarat Rd",
    "sg:city":"Deer Park",
    "sg:classifiers":[
        {
            "category":"Fast Food",
            "type":"Food & Drink"
        }
    ],
    "sg:phone":"+61 3 9360 5300",
    "sg:postcode":"3023",
    "sg:province":"VIC",
    "sg:tags":[
        "away",
        "take"
    ],
    "wof:name":"Deer Park Pizza",
    "wof:placetype":"venue"
},
  "geometry": {"coordinates":[144.77444499999999,-37.770512],"type":"Point"}
}