{
  "type": "Feature",
  "properties": {
    "iso:country":"AU",
    "sg:address":"306 Rouse St",
    "sg:city":"Tenterfield",
    "sg:classifiers":[
        {
            "category":"Autos & Motor Vehicles",
            "subcategory":"Auto Supplies",
            "type":"Retail Goods"
        }
    ],
    "sg:phone":"+61 2 6736 2171",
    "sg:postcode":"2372",
    "sg:province":"NSW",
    "sg:tags":[
        "tyre"
    ],
    "wof:name":"Willowtown Tyre Service",
    "wof:placetype":"venue"
},
  "geometry": {"coordinates":[152.019607544,-29.0518112183],"type":"Point"}
}