{
  "type": "Feature",
  "properties": {
    "iso:country":"AU",
    "sg:address":"Costello Rd",
    "sg:city":"Cabarlah",
    "sg:classifiers":[
        {
            "category":"Shopping",
            "subcategory":"Stationery & Office Supplies",
            "type":"Retail Goods"
        }
    ],
    "sg:phone":"+61 7 4696 9800",
    "sg:postcode":"4352",
    "sg:province":"QLD",
    "sg:tags":[
        "packaging",
        "material"
    ],
    "wof:name":"Range Plastics",
    "wof:placetype":"venue"
},
  "geometry": {"coordinates":[151.99595600000001,-27.428646],"type":"Point"}
}