{
  "type": "Feature",
  "properties": {
    "addr:full":"68-70 Mentmore Ave Rosebery NSW 2018",
    "addr:housenumber":"68-70",
    "addr:postcode":"2018",
    "addr:street":"Mentmore Ave",
    "iso:country":"AU",
    "sg:address":"68-70 Mentmore Ave",
    "sg:city":"Rosebery",
    "sg:classifiers":[
        {
            "category":"Shopping",
            "subcategory":"Clothing, Apparel, & Fashions",
            "type":"Retail Goods"
        }
    ],
    "sg:phone":"+61 2 8338 1785",
    "sg:postcode":"2018",
    "sg:province":"NSW",
    "sg:tags":[
        "lady",
        "wear"
    ],
    "wof:name":"Scandals",
    "wof:placetype":"venue"
},
  "geometry": {"coordinates":[151.20280456500001,-33.9185676575],"type":"Point"}
}