{
  "type": "Feature",
  "properties": {
    "addr:full":"U8/ 21-23 Tasman Way Byron Bay NSW 2481",
    "addr:housenumber":"21-23",
    "addr:postcode":"2481",
    "addr:street":"U8 /;Tasman Way",
    "iso:country":"AU",
    "sg:address":"U8/ 21-23 Tasman Way",
    "sg:city":"Byron Bay",
    "sg:classifiers":[
        {
            "category":"Manufacturing",
            "subcategory":"Apparel",
            "type":"Manufacturing & Wholesale Goods"
        }
    ],
    "sg:phone":"+61 2 6685 6050",
    "sg:postcode":"2481",
    "sg:province":"NSW",
    "sg:tags":[
        "makers-up",
        "clothing"
    ],
    "wof:name":"Red Sun Australia Pty Ltd",
    "wof:placetype":"venue"
},
  "geometry": {"coordinates":[153.57986450199999,-28.6349487305],"type":"Point"}
}