{
  "type": "Feature",
  "properties": {
    "addr:full":"110w Fitzroy St Walcha NSW 2354",
    "addr:housenumber":"110w",
    "addr:postcode":"2354",
    "addr:street":"Fitzroy St",
    "iso:country":"AU",
    "sg:address":"110w Fitzroy St",
    "sg:city":"Walcha",
    "sg:classifiers":[
        {
            "category":"Shopping",
            "type":"Retail Goods"
        }
    ],
    "sg:phone":"+61 2 6777 2099",
    "sg:postcode":"2354",
    "sg:province":"NSW",
    "sg:tags":[
        "agent",
        "stock"
    ],
    "wof:name":"Landmark Operations Limited",
    "wof:placetype":"venue"
},
  "geometry": {"coordinates":[151.58734130900001,-30.9841098785],"type":"Point"}
}