{
  "type": "Feature",
  "properties": {
    "addr:full":"Cnr Beattie Rd & Waterway Drv Coomera QLD 4209",
    "addr:postcode":"4209",
    "addr:street":"Cnr Beattie Rd & Waterway Drv",
    "iso:country":"AU",
    "sg:address":"Cnr Beattie Rd & Waterway Drv",
    "sg:city":"Coomera",
    "sg:classifiers":[
        {
            "category":"Autos & Motor Vehicles",
            "subcategory":"Boat Sales",
            "type":"Retail Goods"
        }
    ],
    "sg:phone":"+61 7 5529 9244",
    "sg:postcode":"4209",
    "sg:province":"QLD",
    "sg:tags":[
        "builder",
        "yacht",
        "repairer"
    ],
    "wof:name":"Porter's Outboard Services",
    "wof:placetype":"venue"
},
  "geometry": {"coordinates":[153.322097778,-27.8674850464],"type":"Point"}
}