{
  "type": "Feature",
  "properties": {
    "addr:full":"9 Cameron Pde Broadford VIC 3658",
    "addr:housenumber":"9",
    "addr:postcode":"3658",
    "addr:street":"Cameron Pde",
    "iso:country":"AU",
    "sg:address":"9 Cameron Pde",
    "sg:city":"Broadford",
    "sg:classifiers":[
        {
            "category":"Retail",
            "subcategory":"Storage",
            "type":"Services"
        }
    ],
    "sg:phone":"+61 408 374 248",
    "sg:postcode":"3658",
    "sg:province":"VIC",
    "wof:name":"Broadford Self Storage",
    "wof:placetype":"venue"
},
  "geometry": {"coordinates":[145.05931091299999,-37.209777832],"type":"Point"}
}