{
  "type": "Feature",
  "properties": {
    "iso:country":"AU",
    "sg:address":"Shop 68/69, Aspley Hypemarket, 59",
    "sg:city":"Albany Ck Aspley",
    "sg:classifiers":[
        {
            "category":"Shopping",
            "subcategory":"Computers & Home Electronics",
            "type":"Retail Goods"
        }
    ],
    "sg:phone":"+61 7 3263 8436",
    "sg:postcode":"4034",
    "sg:province":"QLD",
    "sg:tags":[
        "equipment",
        "part",
        "electronic"
    ],
    "wof:name":"Tandy",
    "wof:placetype":"venue"
},
  "geometry": {"coordinates":[153.012924,-27.363176],"type":"Point"}
}