{
  "type": "Feature",
  "properties": {
    "addr:full":"102 Bussell Hwy Margaret River WA 6285",
    "addr:housenumber":"102",
    "addr:postcode":"6285",
    "addr:street":"Bussell Hwy",
    "iso:country":"AU",
    "sg:address":"102 Bussell Hwy",
    "sg:city":"Margaret River",
    "sg:classifiers":[
        {
            "category":"Communications",
            "subcategory":"Film & Video Production",
            "type":"Services"
        }
    ],
    "sg:phone":"+61 8 9757 2121",
    "sg:postcode":"6285",
    "sg:province":"WA",
    "sg:tags":[
        "dvd",
        "library"
    ],
    "wof:name":"Civic Video Margaret River",
    "wof:placetype":"venue"
},
  "geometry": {"coordinates":[115.07408905,-33.9489593506],"type":"Point"}
}