{
  "type": "Feature",
  "properties": {
    "iso:country":"AU",
    "sg:address":"Level 8, 51 Pitt St",
    "sg:city":"Sydney",
    "sg:classifiers":[
        {
            "category":"Banks & Credit Unions",
            "subcategory":"Investment Brokerage",
            "type":"Services"
        }
    ],
    "sg:phone":"+61 2 9274 0300",
    "sg:postcode":"2000",
    "sg:province":"NSW",
    "wof:name":"Morningstar",
    "wof:placetype":"venue"
},
  "geometry": {"coordinates":[151.20887756400001,-33.8628616333],"type":"Point"}
}