{
  "type": "Feature",
  "properties": {
    "iso:country":"AU",
    "sg:address":"Cnr Federal Rd & Prospect Hwy",
    "sg:city":"Seven Hills",
    "sg:classifiers":[
        {
            "category":"Food & Beverages",
            "subcategory":"Liquor & Beverages",
            "type":"Retail Goods"
        }
    ],
    "sg:phone":"+61 2 9671 2999",
    "sg:postcode":"2147",
    "sg:province":"NSW",
    "sg:tags":[
        "store"
    ],
    "wof:name":"Macs Liquor",
    "wof:placetype":"venue"
},
  "geometry": {"coordinates":[150.93324279800001,-33.7767410278],"type":"Point"}
}