{
  "type": "Feature",
  "properties": {
    "iso:country":"AU",
    "sg:address":"Level 1 52- 57",
    "sg:city":"Esplanade Cairns",
    "sg:classifiers":[
        {
            "category":"Manufacturing",
            "subcategory":"Food",
            "type":"Manufacturing & Wholesale Goods"
        }
    ],
    "sg:phone":"+61 7 4046 4246",
    "sg:postcode":"4870",
    "sg:province":"QLD",
    "sg:tags":[
        "function",
        "catering"
    ],
    "wof:name":"Artistic Vue",
    "wof:placetype":"venue"
},
  "geometry": {"coordinates":[145.777786255,-16.9206085205],"type":"Point"}
}