{
  "type": "Feature",
  "properties": {
    "addr:full":"Shop 91 Sunnybank Plaza Sunnybank QLD 4109",
    "addr:housenumber":"shop 91",
    "addr:postcode":"4109",
    "addr:street":"Sunnybank Plaza",
    "iso:country":"AU",
    "sg:address":"Shop 91 Sunnybank Plaza",
    "sg:city":"Sunnybank",
    "sg:classifiers":[
        {
            "category":"Food & Beverages",
            "subcategory":"Supermarket",
            "type":"Retail Goods"
        }
    ],
    "sg:phone":"+61 7 3345 7688",
    "sg:postcode":"4109",
    "sg:province":"QLD",
    "sg:tags":[
        "grocery",
        "store"
    ],
    "wof:name":"Welcome Fresh Food",
    "wof:placetype":"venue"
},
  "geometry": {"coordinates":[153.066650391,-27.5968017578],"type":"Point"}
}