{
  "type": "Feature",
  "properties": {
    "iso:country":"AU",
    "sg:address":"59 Urquhart St",
    "sg:city":"Woodend",
    "sg:classifiers":[
        {
            "category":"Retail",
            "subcategory":"Auto Repair",
            "type":"Services"
        }
    ],
    "sg:phone":"+61 3 5427 3454",
    "sg:postcode":"3442",
    "sg:province":"VIC",
    "sg:tags":[
        "repairer",
        "motor",
        "engineer"
    ],
    "wof:name":"Woodend Motor Repairs",
    "wof:placetype":"venue"
},
  "geometry": {"coordinates":[144.533203125,-37.3585205078],"type":"Point"}
}