{
  "type": "Feature",
  "properties": {
    "addr:full":"346A Boronia Rd Boronia VIC 3155",
    "addr:housenumber":"346a",
    "addr:postcode":"3155",
    "addr:street":"Boronia Rd",
    "iso:country":"AU",
    "sg:address":"346A Boronia Rd",
    "sg:city":"Boronia",
    "sg:classifiers":[
        {
            "category":"Health Services",
            "subcategory":"Chiropractor",
            "type":"Services"
        }
    ],
    "sg:phone":"+61 3 9499 1800",
    "sg:postcode":"3155",
    "sg:province":"VIC",
    "wof:name":"Chiropractic Childrens Health Care",
    "wof:placetype":"venue"
},
  "geometry": {"coordinates":[145.25997924800001,-37.8584861755],"type":"Point"}
}