{
  "type": "Feature",
  "properties": {
    "addr:full":"Shop 7/ 41 Georgina Crs Yarrawonga NT 0830",
    "addr:housenumber":"shop 7 / 41",
    "addr:postcode":"nt 0830",
    "addr:street":"Georgina Crs",
    "iso:country":"AU",
    "sg:address":"Shop 7/ 41 Georgina Crs",
    "sg:city":"Yarrawonga",
    "sg:classifiers":[
        {
            "category":"Fast Food",
            "type":"Food & Drink"
        }
    ],
    "sg:phone":"+61 8 8931 0598",
    "sg:postcode":"0830",
    "sg:province":"NT",
    "sg:tags":[
        "away",
        "take"
    ],
    "wof:name":"Uncle Christos Yiros & Greek Food",
    "wof:placetype":"venue"
},
  "geometry": {"coordinates":[130.987076,-12.47033],"type":"Point"}
}