{
  "type": "Feature",
  "properties": {
    "addr:full":"Level 3, 468 George St Sydney NSW 2000",
    "addr:housenumber":"468",
    "addr:postcode":"2000",
    "addr:street":"George St",
    "iso:country":"AU",
    "sg:address":"Level 3, 468 George St",
    "sg:city":"Sydney",
    "sg:classifiers":[
        {
            "category":"Health Services",
            "subcategory":"Doctor",
            "type":"Services"
        }
    ],
    "sg:phone":"+61 2 9264 2155",
    "sg:postcode":"2000",
    "sg:province":"NSW",
    "sg:tags":[
        "medical",
        "practitioner"
    ],
    "wof:name":"Sydney Skin Cancer Clinic",
    "wof:placetype":"venue"
},
  "geometry": {"coordinates":[151.20715332,-33.871307373],"type":"Point"}
}