{
  "type": "Feature",
  "properties": {
    "addr:full":"Flat 6 44 Clarence St Elsternwick VIC 3185",
    "addr:housenumber":"44",
    "addr:postcode":"3185",
    "addr:street":"Clarence St",
    "iso:country":"AU",
    "sg:address":"Flat 6 44 Clarence St",
    "sg:city":"Elsternwick",
    "sg:classifiers":[
        {
            "category":"Banks & Credit Unions",
            "subcategory":"Atm",
            "type":"Services"
        }
    ],
    "sg:phone":"+61 3 9528 3049",
    "sg:postcode":"3185",
    "sg:province":"VIC",
    "sg:tags":[
        "wholesaler",
        "mfrs",
        "envelope"
    ],
    "wof:name":"Ed Bradley Envelopes",
    "wof:placetype":"venue"
},
  "geometry": {"coordinates":[145.012252808,-37.8921813965],"type":"Point"}
}