{
  "type": "Feature",
  "properties": {
    "addr:full":"14 Serica St Hallett Cove SA 5158",
    "addr:housenumber":"14",
    "addr:postcode":"5158",
    "addr:street":"Serica St",
    "iso:country":"AU",
    "sg:address":"14 Serica St",
    "sg:city":"Hallett Cove",
    "sg:classifiers":[
        {
            "category":"Professional",
            "subcategory":"Engineering",
            "type":"Services"
        }
    ],
    "sg:phone":"+61 412 004 622",
    "sg:postcode":"5158",
    "sg:province":"SA",
    "sg:tags":[
        "consulting",
        "engineer"
    ],
    "wof:name":"Drillassist",
    "wof:placetype":"venue"
},
  "geometry": {"coordinates":[138.505584717,-35.0765457153],"type":"Point"}
}