{
  "type": "Feature",
  "properties": {
    "addr:full":"Cnr Pascoe Vale Rd & Buckley St Moonee Ponds VIC 3039",
    "addr:postcode":"3039",
    "addr:street":"Pascoe Vale Rd & Buckley St",
    "iso:country":"AU",
    "sg:address":"Cnr Pascoe Vale Rd & Buckley St",
    "sg:city":"Moonee Ponds",
    "sg:classifiers":[
        {
            "category":"Autos & Motor Vehicles",
            "subcategory":"Fuel & Gas Station",
            "type":"Retail Goods"
        }
    ],
    "sg:phone":"+61 3 9375 3256",
    "sg:postcode":"3039",
    "sg:province":"VIC",
    "wof:name":"BP Australia Pty Ltd",
    "wof:placetype":"venue"
},
  "geometry": {"coordinates":[144.925095,-37.765987],"type":"Point"}
}