{
  "type": "Feature",
  "properties": {
    "addr:full":"PO Box 8002 Brighton East VIC 3187",
    "addr:postcode":"3187",
    "iso:country":"AU",
    "sg:address":"PO Box 8002",
    "sg:city":"Brighton East",
    "sg:classifiers":[
        {
            "category":"Shopping",
            "subcategory":"Computers & Home Electronics",
            "type":"Retail Goods"
        }
    ],
    "sg:phone":"+61 3 9568 6400",
    "sg:postcode":"3187",
    "sg:province":"VIC",
    "sg:tags":[
        "hardware",
        "equipment"
    ],
    "wof:name":"Southern Supplies",
    "wof:placetype":"venue"
},
  "geometry": {"coordinates":[145.01942443900001,-37.9164085388],"type":"Point"}
}