{
  "type": "Feature",
  "properties": {
    "addr:full":"80 Station St Fairfield VIC 3078",
    "addr:housenumber":"80",
    "addr:postcode":"3078",
    "addr:street":"Station St",
    "iso:country":"AU",
    "sg:address":"80 Station St",
    "sg:city":"Fairfield",
    "sg:classifiers":[
        {
            "category":"Shopping",
            "subcategory":"Party Supplies",
            "type":"Retail Goods"
        }
    ],
    "sg:phone":"+61 3 9482 2888",
    "sg:postcode":"3078",
    "sg:province":"VIC",
    "sg:tags":[
        "children's"
    ],
    "wof:name":"Fairyfields",
    "wof:placetype":"venue"
},
  "geometry": {"coordinates":[145.018035889,-37.7785682678],"type":"Point"}
}