{
  "type": "Feature",
  "properties": {
    "iso:country":"AU",
    "sg:address":"506 Eastpoint Twrs St",
    "sg:city":"Edgecliff",
    "sg:classifiers":[
        {
            "category":"Health Services",
            "subcategory":"Doctor",
            "type":"Services"
        }
    ],
    "sg:phone":"+61 2 9326 2385",
    "sg:postcode":"2027",
    "sg:province":"NSW",
    "sg:tags":[
        "medical",
        "practitioner"
    ],
    "wof:name":"Eden John A",
    "wof:placetype":"venue"
},
  "geometry": {"coordinates":[151.237792969,-33.8803787231],"type":"Point"}
}