{
  "type": "Feature",
  "properties": {
    "addr:full":"Ryrie Street Market 104 Ryrie St Geelong Geelong VIC 3220",
    "addr:housenumber":"104",
    "addr:postcode":"3220",
    "addr:street":"Ryrie;Ryrie St",
    "iso:country":"AU",
    "sg:address":"Ryrie Street Market 104 Ryrie St",
    "sg:city":"Geelong Geelong",
    "sg:classifiers":[
        {
            "category":"Wholesale",
            "subcategory":"Furniture",
            "type":"Manufacturing & Wholesale Goods"
        }
    ],
    "sg:phone":"+61 3 5224 1117",
    "sg:postcode":"3220",
    "sg:province":"VIC",
    "sg:tags":[
        "wholesaler",
        "mfrs"
    ],
    "wof:name":"Classic Handcrafted Furniture",
    "wof:placetype":"venue"
},
  "geometry": {"coordinates":[144.35772700000001,-38.148884],"type":"Point"}
}