{
  "type": "Feature",
  "properties": {
    "addr:full":"Unit 1, 100 Munibung Rd Cardiff NSW 2285",
    "addr:housenumber":"100",
    "addr:postcode":"2285",
    "addr:street":"Munibung Rd",
    "iso:country":"AU",
    "sg:address":"Unit 1, 100 Munibung Rd",
    "sg:city":"Cardiff",
    "sg:classifiers":[
        {
            "category":"Shopping",
            "subcategory":"Stationery & Office Supplies",
            "type":"Retail Goods"
        }
    ],
    "sg:phone":"+61 2 4953 7838",
    "sg:postcode":"2285",
    "sg:province":"NSW",
    "sg:tags":[
        "equipment",
        "facsimile"
    ],
    "wof:name":"Premier Copier Service",
    "wof:placetype":"venue"
},
  "geometry": {"coordinates":[151.63845825199999,-32.9418487549],"type":"Point"}
}