{
  "type": "Feature",
  "properties": {
    "addr:full":"103 Cleveland St Chippendale NSW 2008",
    "addr:housenumber":"103",
    "addr:postcode":"2008",
    "addr:street":"Cleveland St",
    "iso:country":"AU",
    "sg:address":"103 Cleveland St",
    "sg:city":"Chippendale",
    "sg:classifiers":[
        {
            "category":"Travel",
            "subcategory":"Hotels & Motels",
            "type":"Entertainment"
        }
    ],
    "sg:phone":"+61 2 9699 5315",
    "sg:postcode":"2008",
    "sg:province":"NSW",
    "sg:tags":[
        "accommodation"
    ],
    "wof:name":"Britannia Hotel",
    "wof:placetype":"venue"
},
  "geometry": {"coordinates":[151.196533203,-33.8884124756],"type":"Point"}
}