{
  "type": "Feature",
  "properties": {
    "iso:country":"AU",
    "sg:address":"78 King St",
    "sg:city":"Charters Towers",
    "sg:classifiers":[
        {
            "category":"Manufacturing",
            "subcategory":"Signs",
            "type":"Manufacturing & Wholesale Goods"
        }
    ],
    "sg:phone":"+61 7 4787 8707",
    "sg:postcode":"4820",
    "sg:province":"QLD",
    "sg:tags":[
        "traffic",
        "safety"
    ],
    "wof:name":"Chris Ives Signs",
    "wof:placetype":"venue"
},
  "geometry": {"coordinates":[146.25676,-20.072624],"type":"Point"}
}