{
  "type": "Feature",
  "properties": {
    "addr:full":"121 King St Melbourne VIC 3000",
    "addr:housenumber":"121",
    "addr:postcode":"3000",
    "addr:street":"King St",
    "iso:country":"AU",
    "sg:address":"121 King St",
    "sg:city":"Melbourne",
    "sg:classifiers":[
        {
            "category":"Professional",
            "subcategory":"Management & Consulting",
            "type":"Services"
        }
    ],
    "sg:phone":"+61 3 9614 5900",
    "sg:postcode":"3000",
    "sg:province":"VIC",
    "sg:tags":[
        "consultant",
        "energy"
    ],
    "wof:name":"Lincolne Scott Consulting Engineers",
    "wof:placetype":"venue"
},
  "geometry": {"coordinates":[144.955932617,-37.817150116],"type":"Point"}
}