{
  "type": "Feature",
  "properties": {
    "addr:full":"35 Glasstail Crs Narangba QLD 4504",
    "addr:housenumber":"35",
    "addr:postcode":"4504",
    "addr:street":"Glasstail Crs",
    "iso:country":"AU",
    "sg:address":"35 Glasstail Crs",
    "sg:city":"Narangba",
    "sg:classifiers":[
        {
            "category":"Health Services",
            "subcategory":"Health Practitioner",
            "type":"Services"
        }
    ],
    "sg:phone":"+61 421 703 408",
    "sg:postcode":"4504",
    "sg:province":"QLD",
    "sg:tags":[
        "naturopath"
    ],
    "wof:name":"Hodson Ann",
    "wof:placetype":"venue"
},
  "geometry": {"coordinates":[152.92854309099999,-27.1869602203],"type":"Point"}
}