{
  "type": "Feature",
  "properties": {
    "addr:full":"Haughton Rd Reserve Clayton VIC 3168",
    "addr:postcode":"3168",
    "addr:street":"Haughton Rd Reserve",
    "iso:country":"AU",
    "sg:address":"Haughton Rd Reserve",
    "sg:city":"Clayton",
    "sg:classifiers":[
        {
            "category":"Arena",
            "subcategory":"Sports Club",
            "type":"Entertainment"
        }
    ],
    "sg:phone":"+61 3 9543 4304",
    "sg:postcode":"3168",
    "sg:province":"VIC",
    "sg:tags":[
        "australian",
        "football",
        "rule"
    ],
    "wof:name":"Clayton Football Club Inc.",
    "wof:placetype":"venue"
},
  "geometry": {"coordinates":[145.11286926299999,-37.9191474915],"type":"Point"}
}