{
  "type": "Feature",
  "properties": {
    "addr:full":"Federal St Narrogin WA 6312",
    "addr:postcode":"6312",
    "addr:street":"Federal St",
    "iso:country":"AU",
    "sg:address":"Federal St",
    "sg:city":"Narrogin",
    "sg:classifiers":[
        {
            "category":"Fast Food",
            "type":"Food & Drink"
        }
    ],
    "sg:phone":"+61 8 9881 4144",
    "sg:postcode":"6312",
    "sg:province":"WA",
    "sg:tags":[
        "away",
        "take"
    ],
    "wof:name":"Chicken Treat",
    "wof:placetype":"venue"
},
  "geometry": {"coordinates":[117.178352356,-32.931388855],"type":"Point"}
}