{
  "type": "Feature",
  "properties": {
    "addr:full":"236 Darling St Balmain NSW 2041",
    "addr:housenumber":"236",
    "addr:postcode":"2041",
    "addr:street":"Darling St",
    "iso:country":"AU",
    "sg:address":"236 Darling St",
    "sg:city":"Balmain",
    "sg:classifiers":[
        {
            "category":"Health Services",
            "subcategory":"Health Practitioner",
            "type":"Services"
        }
    ],
    "sg:phone":"+61 2 9810 6100",
    "sg:postcode":"2041",
    "sg:province":"NSW",
    "sg:tags":[
        "alternative"
    ],
    "wof:name":"Eva Bodywork Therapy",
    "wof:placetype":"venue"
},
  "geometry": {"coordinates":[151.18450899999999,-33.85841],"type":"Point"}
}