{
  "type": "Feature",
  "properties": {
    "addr:full":"25 Shaws Road Bohle Townsville QLD 4810",
    "addr:housenumber":"25",
    "addr:postcode":"4810",
    "addr:street":"Shaws Road",
    "iso:country":"AU",
    "sg:address":"25 Shaws Road Bohle",
    "sg:city":"Townsville",
    "sg:classifiers":[
        {
            "category":"Home & Garden",
            "subcategory":"Building Materials",
            "type":"Retail Goods"
        }
    ],
    "sg:phone":"+61 7 4774 8055",
    "sg:postcode":"4810",
    "sg:province":"QLD",
    "sg:tags":[
        "decorative",
        "coating"
    ],
    "wof:name":"McElligotts Townsville",
    "wof:placetype":"venue"
},
  "geometry": {"coordinates":[146.70079000000001,-19.265482],"type":"Point"}
}