{
  "type": "Feature",
  "properties": {
    "addr:full":"Shop 5, 177 The Parade Norwood SA 5067",
    "addr:housenumber":"shop 5 177",
    "addr:postcode":"5067",
    "addr:street":"The Parade",
    "iso:country":"AU",
    "sg:address":"Shop 5, 177 The Parade",
    "sg:city":"Norwood",
    "sg:classifiers":[
        {
            "category":"Professional",
            "subcategory":"Computer Services",
            "type":"Services"
        }
    ],
    "sg:phone":"+61 8 8333 0922",
    "sg:postcode":"5067",
    "sg:province":"SA",
    "sg:tags":[
        "repairs",
        "upgrade",
        "equipment"
    ],
    "sg:website":"http://www.maccentrenorwood.com.au",
    "wof:name":"Mac Centre Norwood",
    "wof:placetype":"venue"
},
  "geometry": {"coordinates":[138.63276672399999,-34.92137146],"type":"Point"}
}