{
  "type": "Feature",
  "properties": {
    "addr:full":"31 Manoora St Greenacres SA 5086",
    "addr:housenumber":"31",
    "addr:postcode":"5086",
    "addr:street":"Manoora St",
    "iso:country":"AU",
    "sg:address":"31 Manoora St",
    "sg:city":"Greenacres",
    "sg:classifiers":[
        {
            "category":"Personal",
            "subcategory":"Beauty Salon",
            "type":"Services"
        }
    ],
    "sg:phone":"+61 8 8367 9099",
    "sg:postcode":"5086",
    "sg:province":"SA",
    "wof:name":"Amarin Hair & Beauty",
    "wof:placetype":"venue"
},
  "geometry": {"coordinates":[138.624343872,-34.8690223694],"type":"Point"}
}