{
  "type": "Feature",
  "properties": {
    "addr:full":"810 Punchbowl Rd Punchbowl NSW 2196",
    "addr:housenumber":"810",
    "addr:postcode":"2196",
    "addr:street":"Punchbowl Rd",
    "iso:country":"AU",
    "sg:address":"810 Punchbowl Rd",
    "sg:city":"Punchbowl",
    "sg:classifiers":[
        {
            "category":"Shopping",
            "subcategory":"Mobile Phones",
            "type":"Retail Goods"
        }
    ],
    "sg:phone":"+61 2 9708 0802",
    "sg:postcode":"2196",
    "sg:province":"NSW",
    "sg:tags":[
        "telephone",
        "accessory"
    ],
    "wof:name":"4 Star Communications",
    "wof:placetype":"venue"
},
  "geometry": {"coordinates":[151.05394000000001,-33.926193],"type":"Point"}
}