{
  "type": "Feature",
  "properties": {
    "addr:full":"PO Box 277 Uralla NSW 2358",
    "addr:postcode":"2358",
    "iso:country":"AU",
    "sg:address":"PO Box 277",
    "sg:city":"Uralla",
    "sg:classifiers":[
        {
            "category":"Building & Trades",
            "subcategory":"Pest Control",
            "type":"Services"
        }
    ],
    "sg:phone":"+61 427 662 115",
    "sg:postcode":"2358",
    "sg:province":"NSW",
    "wof:name":"Termi Mesh Northern Highland",
    "wof:placetype":"venue"
},
  "geometry": {"coordinates":[151.498214722,-30.642950058],"type":"Point"}
}