{
  "type": "Feature",
  "properties": {
    "addr:full":"1st Floor, 21 Watchorn St Hobart TAS 7000",
    "addr:housenumber":"21",
    "addr:postcode":"7000",
    "addr:street":"Watchorn St",
    "iso:country":"AU",
    "sg:address":"1st Floor, 21 Watchorn St",
    "sg:city":"Hobart",
    "sg:classifiers":[
        {
            "category":"Shopping",
            "subcategory":"Hobbies, Toys, & Games",
            "type":"Retail Goods"
        }
    ],
    "sg:phone":"+61 3 6234 4807",
    "sg:postcode":"7000",
    "sg:province":"TAS",
    "sg:tags":[
        "stamp"
    ],
    "wof:name":"Tasmanian Stamp Auctions",
    "wof:placetype":"venue"
},
  "geometry": {"coordinates":[147.32383727999999,-42.8825912476],"type":"Point"}
}