{
  "type": "Feature",
  "properties": {
    "addr:full":"101 Cumberland St Sunshine VIC 3020",
    "addr:housenumber":"101",
    "addr:postcode":"3020",
    "addr:street":"Cumberland St",
    "iso:country":"AU",
    "sg:address":"101 Cumberland St",
    "sg:city":"Sunshine",
    "sg:classifiers":[
        {
            "category":"Building & Trades",
            "subcategory":"Construction",
            "type":"Services"
        }
    ],
    "sg:phone":"+61 3 9311 5013",
    "sg:postcode":"3020",
    "sg:province":"VIC",
    "sg:tags":[
        "plasterboard",
        "plasterer",
        "fixer"
    ],
    "wof:name":"Vanhoof Plastering",
    "wof:placetype":"venue"
},
  "geometry": {"coordinates":[144.84471099999999,-37.766094],"type":"Point"}
}