{
  "type": "Feature",
  "properties": {
    "addr:full":"98 Carrington St Adelaide SA 5000",
    "addr:housenumber":"98",
    "addr:postcode":"5000",
    "addr:street":"Carrington St",
    "iso:country":"AU",
    "sg:address":"98 Carrington St",
    "sg:city":"Adelaide",
    "sg:classifiers":[
        {
            "category":"Personal",
            "subcategory":"Adult",
            "type":"Services"
        }
    ],
    "sg:phone":"+61 8 8232 4077",
    "sg:postcode":"5000",
    "sg:province":"SA",
    "sg:tags":[
        "vic",
        "except",
        "state",
        "escort",
        "social",
        "qld"
    ],
    "wof:name":"Dreams Of Perfection Escorts",
    "wof:placetype":"venue"
},
  "geometry": {"coordinates":[138.60386657699999,-34.9311981201],"type":"Point"}
}