{
  "type": "Feature",
  "properties": {
    "addr:full":"PO Box 362 Minto NSW 2566",
    "addr:postcode":"2566",
    "iso:country":"AU",
    "sg:address":"PO Box 362",
    "sg:city":"Minto",
    "sg:classifiers":[
        {
            "category":"Manufacturing",
            "subcategory":"Metals",
            "type":"Manufacturing & Wholesale Goods"
        }
    ],
    "sg:phone":"+61 2 9605 7050",
    "sg:postcode":"2566",
    "sg:province":"NSW",
    "sg:tags":[
        "fabricator",
        "aluminium"
    ],
    "wof:name":"Curtainwalls Glass & Aluminium Pty Ltd",
    "wof:placetype":"venue"
},
  "geometry": {"coordinates":[150.84469604500001,-34.0311889648],"type":"Point"}
}