{
  "type": "Feature",
  "properties": {
    "addr:full":"102 ascot St Ballarat VIC 3350",
    "addr:housenumber":"102",
    "addr:postcode":"3350",
    "addr:street":"Ascot St",
    "iso:country":"AU",
    "sg:address":"102 ascot St",
    "sg:city":"Ballarat",
    "sg:classifiers":[
        {
            "category":"Manufacturing",
            "subcategory":"Food",
            "type":"Manufacturing & Wholesale Goods"
        }
    ],
    "sg:phone":"+61 3 5320 3764",
    "sg:postcode":"3350",
    "sg:province":"VIC",
    "sg:tags":[
        "function",
        "catering"
    ],
    "wof:name":"BHS Catering",
    "wof:placetype":"venue"
},
  "geometry": {"coordinates":[143.84410099999999,-37.563293],"type":"Point"}
}