{
  "type": "Feature",
  "properties": {
    "iso:country":"AU",
    "sg:address":"1 Margate St",
    "sg:city":"Botany",
    "sg:classifiers":[
        {
            "category":"Retail",
            "subcategory":"Auto Repair",
            "type":"Services"
        }
    ],
    "sg:phone":"+61 2 9316 8337",
    "sg:postcode":"2019",
    "sg:province":"NSW",
    "sg:tags":[
        "repairer",
        "motor",
        "engineer"
    ],
    "wof:name":"Fineline Automotive Services",
    "wof:placetype":"venue"
},
  "geometry": {"coordinates":[151.199584961,-33.9499282837],"type":"Point"}
}