{
  "type": "Feature",
  "properties": {
    "iso:country":"AU",
    "sg:address":"Lakelands Shopng Cntr 31 Moorhen Drv",
    "sg:city":"Yangebup",
    "sg:classifiers":[
        {
            "category":"Health Services",
            "subcategory":"Doctor",
            "type":"Services"
        }
    ],
    "sg:phone":"+61 8 9417 7979",
    "sg:postcode":"6164",
    "sg:province":"WA",
    "sg:tags":[
        "medical",
        "practitioner"
    ],
    "wof:name":"Yangebup General Practice",
    "wof:placetype":"venue"
},
  "geometry": {"coordinates":[115.81783299999999,-32.119915],"type":"Point"}
}