{
  "type": "Feature",
  "properties": {
    "addr:full":"Crn of St Kilda Rd & Hanna St, Melbourne VIC 3000",
    "addr:postcode":"3000",
    "addr:street":"Crn;St Kilda Rd & Hanna St",
    "iso:country":"AU",
    "sg:address":"Crn of St Kilda Rd",
    "sg:city":"& Hanna St, Melbourne",
    "sg:classifiers":[
        {
            "category":"Personal",
            "subcategory":"Massage",
            "type":"Services"
        }
    ],
    "sg:phone":"+61 413 165 708",
    "sg:postcode":"3000",
    "sg:province":"VIC",
    "sg:tags":[
        "therapy"
    ],
    "wof:name":"Express De-Stress Massage - Remedial, Sports & Relaxation",
    "wof:placetype":"venue"
},
  "geometry": {"coordinates":[144.96751403799999,-37.8176269531],"type":"Point"}
}