{
  "type": "Feature",
  "properties": {
    "iso:country":"AU",
    "sg:address":"Shop 6, 262 Old Northern Rd",
    "sg:city":"Castle Hill",
    "sg:classifiers":[
        {
            "category":"Professional",
            "subcategory":"Computer Services",
            "type":"Services"
        }
    ],
    "sg:phone":"+61 2 9659 4172",
    "sg:postcode":"2154",
    "sg:province":"NSW",
    "sg:tags":[
        "repairs",
        "upgrade",
        "equipment"
    ],
    "wof:name":"PC Master",
    "wof:placetype":"venue"
},
  "geometry": {"coordinates":[151.003814697,-33.7339324951],"type":"Point"}
}