{
  "type": "Feature",
  "properties": {
    "addr:full":"Kenilworth Estate Kangaloon Rd Bowral NSW 2576",
    "addr:postcode":"2576",
    "addr:street":"Kangaloon Rd",
    "iso:country":"AU",
    "sg:address":"Kenilworth Estate Kangaloon Rd",
    "sg:city":"Bowral",
    "sg:classifiers":[
        {
            "category":"Building & Trades",
            "subcategory":"Landscaping Services",
            "type":"Services"
        }
    ],
    "sg:phone":"+61 2 4861 2755",
    "sg:postcode":"2576",
    "sg:province":"NSW",
    "sg:tags":[
        "grazier"
    ],
    "wof:name":"Whiskey Hill Cattle Co. Pty Ltd",
    "wof:placetype":"venue"
},
  "geometry": {"coordinates":[150.416015625,-34.4849662781],"type":"Point"}
}