{
  "type": "Feature",
  "properties": {
    "iso:country":"AU",
    "sg:address":"182 James St",
    "sg:city":"Toowoomba",
    "sg:classifiers":[
        {
            "category":"Retail",
            "subcategory":"Car Wash",
            "type":"Services"
        }
    ],
    "sg:phone":"+61 7 4632 5244",
    "sg:postcode":"4350",
    "sg:province":"QLD",
    "sg:tags":[
        "truck",
        "cleaning"
    ],
    "wof:name":"James Street Carwash",
    "wof:placetype":"venue"
},
  "geometry": {"coordinates":[151.949173,-27.568485],"type":"Point"}
}