{
  "type": "Feature",
  "properties": {
    "addr:full":"20 East St Lutwyche QLD 4030",
    "addr:housenumber":"20",
    "addr:postcode":"4030",
    "addr:street":"East St",
    "iso:country":"AU",
    "sg:address":"20 East St",
    "sg:city":"Lutwyche",
    "sg:classifiers":[
        {
            "category":"Home & Garden",
            "subcategory":"Building Materials",
            "type":"Retail Goods"
        }
    ],
    "sg:phone":"+61 7 3357 8386",
    "sg:postcode":"4030",
    "sg:province":"QLD",
    "sg:tags":[
        "lawn",
        "cutting",
        "maintenance"
    ],
    "wof:name":"Aussie Green Thumbs",
    "wof:placetype":"venue"
},
  "geometry": {"coordinates":[153.03465299999999,-27.423666],"type":"Point"}
}