{
  "type": "Feature",
  "properties": {
    "addr:full":"408 Milton Rd Auchenflower QLD 4066",
    "addr:housenumber":"408",
    "addr:postcode":"4066",
    "addr:street":"Milton Rd",
    "iso:country":"AU",
    "sg:address":"408 Milton Rd",
    "sg:city":"Auchenflower",
    "sg:classifiers":[
        {
            "category":"Travel",
            "subcategory":"Hotels & Motels",
            "type":"Entertainment"
        }
    ],
    "sg:phone":"+61 1800 655 805",
    "sg:postcode":"4066",
    "sg:province":"QLD",
    "wof:name":"Snooze Inn",
    "wof:placetype":"venue"
},
  "geometry": {"coordinates":[152.99551391599999,-27.4740505219],"type":"Point"}
}