{
  "type": "Feature",
  "properties": {
    "iso:country":"AU",
    "sg:address":"51 Jubilee St",
    "sg:city":"Beckenham",
    "sg:classifiers":[
        {
            "category":"Home & Garden",
            "subcategory":"Garden Supply",
            "type":"Retail Goods"
        }
    ],
    "sg:phone":"+61 8 9358 3355",
    "sg:postcode":"6107",
    "sg:province":"WA",
    "sg:tags":[
        "nursery"
    ],
    "wof:name":"Park Agencies",
    "wof:placetype":"venue"
},
  "geometry": {"coordinates":[115.96333313,-32.0135879517],"type":"Point"}
}