{
  "type": "Feature",
  "properties": {
    "addr:full":"46 Gladstone St Gladstone SA 5473",
    "addr:housenumber":"46",
    "addr:postcode":"5473",
    "addr:street":"Gladstone St",
    "iso:country":"AU",
    "sg:address":"46 Gladstone St",
    "sg:city":"Gladstone",
    "sg:classifiers":[
        {
            "category":"Food & Beverages",
            "subcategory":"Supermarket",
            "type":"Retail Goods"
        }
    ],
    "sg:phone":"+61 8 8662 2199",
    "sg:postcode":"5473",
    "sg:province":"SA",
    "sg:tags":[
        "grocery",
        "store"
    ],
    "wof:name":"I.G.A. Friendly Grocer-Gladstone",
    "wof:placetype":"venue"
},
  "geometry": {"coordinates":[138.356674,-33.270061],"type":"Point"}
}