{
  "type": "Feature",
  "properties": {
    "addr:full":"Kiosk 15 Broadmeadows Shopping Square Broadmeadows VIC 3047",
    "addr:postcode":"3047",
    "iso:country":"AU",
    "sg:address":"Kiosk 15 Broadmeadows Shopping Square",
    "sg:city":"Broadmeadows",
    "sg:classifiers":[
        {
            "category":"Fast Food",
            "type":"Food & Drink"
        }
    ],
    "sg:phone":"+61 3 9309 5481",
    "sg:postcode":"3047",
    "sg:province":"VIC",
    "sg:tags":[
        "away",
        "take"
    ],
    "wof:name":"Donut King",
    "wof:placetype":"venue"
},
  "geometry": {"coordinates":[144.926345825,-37.6860694885],"type":"Point"}
}