{
  "type": "Feature",
  "properties": {
    "iso:country":"AU",
    "sg:address":"146 Riseley St",
    "sg:city":"Booragoon",
    "sg:classifiers":[
        {
            "category":"Retail",
            "subcategory":"Veterinary Services",
            "type":"Services"
        }
    ],
    "sg:phone":"+61 8 9316 4499",
    "sg:postcode":"6154",
    "sg:province":"WA",
    "sg:tags":[
        "surgeon"
    ],
    "wof:name":"Garden Cities Vet Clinic",
    "wof:placetype":"venue"
},
  "geometry": {"coordinates":[115.83844000000001,-32.034267],"type":"Point"}
}