{
  "type": "Feature",
  "properties": {
    "addr:full":"3 Macrossan St South Townsville QLD 4810",
    "addr:housenumber":"3",
    "addr:postcode":"4810",
    "addr:street":"Macrossan St",
    "iso:country":"AU",
    "sg:address":"3 Macrossan St",
    "sg:city":"South Townsville",
    "sg:classifiers":[
        {
            "category":"Real Estate",
            "subcategory":"Real Estate Agent",
            "type":"Services"
        }
    ],
    "sg:phone":"+61 7 4721 3555",
    "sg:postcode":"4810",
    "sg:province":"QLD",
    "wof:name":"Ramlock Pty Ltd",
    "wof:placetype":"venue"
},
  "geometry": {"coordinates":[146.82621800000001,-19.265804],"type":"Point"}
}