{
  "type": "Feature",
  "properties": {
    "addr:full":"Cnr Newman & Cowra Drv Whaleback WA 6701",
    "addr:postcode":"6701",
    "addr:street":"Cnr",
    "iso:country":"AU",
    "sg:address":"Cnr Newman & Cowra Drv",
    "sg:city":"Whaleback",
    "sg:classifiers":[
        {
            "category":"Utilities",
            "subcategory":"Fuel Oil & Lpg",
            "type":"Services"
        }
    ],
    "sg:phone":"+61 8 9177 8023",
    "sg:postcode":"6701",
    "sg:province":"WA",
    "sg:tags":[
        "merchant"
    ],
    "wof:name":"Sovereign Petroleum",
    "wof:placetype":"venue"
},
  "geometry": {"coordinates":[113.654899597,-24.8776950836],"type":"Point"}
}