{
  "type": "Feature",
  "properties": {
    "iso:country":"AU",
    "sg:address":"346 Clarendon St",
    "sg:city":"South Melbourne",
    "sg:classifiers":[
        {
            "category":"Wholesale",
            "subcategory":"Painting Supplies",
            "type":"Manufacturing & Wholesale Goods"
        }
    ],
    "sg:phone":"+61 3 9686 5825",
    "sg:postcode":"3205",
    "sg:province":"VIC",
    "sg:tags":[
        "equipment",
        "drawing",
        "drafting"
    ],
    "wof:name":"Ray And Gilbert",
    "wof:placetype":"venue"
},
  "geometry": {"coordinates":[144.961243,-37.834824],"type":"Point"}
}