{
  "type": "Feature",
  "properties": {
    "addr:full":"4 Pickworth Crt Rosanna VIC 3084",
    "addr:housenumber":"4",
    "addr:postcode":"3084",
    "addr:street":"Pickworth Crt",
    "iso:country":"AU",
    "sg:address":"4 Pickworth Crt",
    "sg:city":"Rosanna",
    "sg:classifiers":[
        {
            "category":"Professional",
            "subcategory":"Secretarial Services",
            "type":"Services"
        }
    ],
    "sg:phone":"+61 3 9459 1132",
    "sg:postcode":"3084",
    "sg:province":"VIC",
    "sg:tags":[
        "typing"
    ],
    "wof:name":"R?sum? Action",
    "wof:placetype":"venue"
},
  "geometry": {"coordinates":[145.06932067899999,-37.7365989685],"type":"Point"}
}