{
  "type": "Feature",
  "properties": {
    "iso:country":"AU",
    "sg:address":"36 Main St",
    "sg:city":"Terowie",
    "sg:classifiers":[
        {
            "category":"Government",
            "subcategory":"Post Office",
            "type":"Public Place"
        }
    ],
    "sg:phone":"+61 8 8659 1002",
    "sg:postcode":"5421",
    "sg:province":"SA",
    "sg:tags":[
        "postal"
    ],
    "wof:name":"Australia Post",
    "wof:placetype":"venue"
},
  "geometry": {"coordinates":[138.9190979,-33.1506271362],"type":"Point"}
}