{
  "type": "Feature",
  "properties": {
    "addr:full":"77 Liebig St Warrnambool VIC 3280",
    "addr:housenumber":"77",
    "addr:postcode":"3280",
    "addr:street":"Liebig St",
    "iso:country":"AU",
    "sg:address":"77 Liebig St",
    "sg:city":"Warrnambool",
    "sg:classifiers":[
        {
            "category":"Manufacturing",
            "subcategory":"Food",
            "type":"Manufacturing & Wholesale Goods"
        }
    ],
    "sg:phone":"+61 408 622 432",
    "sg:postcode":"3280",
    "sg:province":"VIC",
    "sg:tags":[
        "function",
        "catering"
    ],
    "wof:name":"McLeods Catering Service",
    "wof:placetype":"venue"
},
  "geometry": {"coordinates":[142.482818603,-38.3845901489],"type":"Point"}
}