{
  "type": "Feature",
  "properties": {
    "addr:full":"77 Main South Rd Normanville SA 5204",
    "addr:housenumber":"77",
    "addr:postcode":"5204",
    "addr:street":"Main South Rd",
    "iso:country":"AU",
    "sg:address":"77 Main South Rd",
    "sg:city":"Normanville",
    "sg:classifiers":[
        {
            "category":"Real Estate",
            "subcategory":"Real Estate Agent",
            "type":"Services"
        }
    ],
    "sg:phone":"+61 8 8558 3833",
    "sg:postcode":"5204",
    "sg:province":"SA",
    "wof:name":"Brock Harcourts",
    "wof:placetype":"venue"
},
  "geometry": {"coordinates":[138.31913757300001,-35.4478263855],"type":"Point"}
}