{
  "type": "Feature",
  "properties": {
    "addr:full":"37 Dowe St Tamworth NSW 2340",
    "addr:housenumber":"37",
    "addr:postcode":"2340",
    "addr:street":"Dowe St",
    "iso:country":"AU",
    "sg:address":"37 Dowe St",
    "sg:city":"Tamworth",
    "sg:classifiers":[
        {
            "category":"Shopping",
            "subcategory":"Optical Goods",
            "type":"Retail Goods"
        }
    ],
    "sg:phone":"+61 2 6766 5656",
    "sg:postcode":"2340",
    "sg:province":"NSW",
    "sg:tags":[
        "supply"
    ],
    "wof:name":"Tri Star Optical",
    "wof:placetype":"venue"
},
  "geometry": {"coordinates":[150.929977417,-31.089427948],"type":"Point"}
}