{
  "type": "Feature",
  "properties": {
    "addr:full":"Young Rd Cowra NSW 2794",
    "addr:postcode":"2794",
    "addr:street":"Young Rd",
    "iso:country":"AU",
    "sg:address":"Young Rd",
    "sg:city":"Cowra",
    "sg:classifiers":[
        {
            "category":"Professional",
            "type":"Services"
        }
    ],
    "sg:phone":"+61 2 6341 1900",
    "sg:postcode":"2794",
    "sg:province":"NSW",
    "sg:tags":[
        "buyer",
        "merchant",
        "wool"
    ],
    "wof:name":"Beecher Wool Services",
    "wof:placetype":"venue"
},
  "geometry": {"coordinates":[148.69056701700001,-33.8345909119],"type":"Point"}
}