{
  "type": "Feature",
  "properties": {
    "addr:full":"1 Omega La Elermore Vale NSW 2287",
    "addr:housenumber":"1",
    "addr:postcode":"2287",
    "addr:street":"Omega La",
    "iso:country":"AU",
    "sg:address":"1 Omega La",
    "sg:city":"Elermore Vale",
    "sg:classifiers":[
        {
            "category":"Professional",
            "subcategory":"Printing & Photocopies",
            "type":"Services"
        }
    ],
    "sg:phone":"+61 411 304 470",
    "sg:postcode":"2287",
    "sg:province":"NSW",
    "sg:tags":[
        "trophy"
    ],
    "wof:name":"A&K Peterson",
    "wof:placetype":"venue"
},
  "geometry": {"coordinates":[151.65945434599999,-32.9163627625],"type":"Point"}
}