{
  "type": "Feature",
  "properties": {
    "addr:full":"5 Brisbane St Murwillumbah NSW 2484",
    "addr:housenumber":"5",
    "addr:postcode":"2484",
    "addr:street":"Brisbane St",
    "iso:country":"AU",
    "sg:address":"5 Brisbane St",
    "sg:city":"Murwillumbah",
    "sg:classifiers":[
        {
            "category":"Cinema",
            "subcategory":"Movie Theater",
            "type":"Entertainment"
        }
    ],
    "sg:phone":"+61 2 6672 8265",
    "sg:postcode":"2484",
    "sg:province":"NSW",
    "wof:name":"Murwillumbah Regent Cinema",
    "wof:placetype":"venue"
},
  "geometry": {"coordinates":[153.394989014,-28.3312988281],"type":"Point"}
}