{
  "type": "Feature",
  "properties": {
    "addr:full":"Anderson Drv Beresfield NSW 2322",
    "addr:postcode":"2322",
    "addr:street":"Anderson Drv",
    "iso:country":"AU",
    "sg:address":"Anderson Drv",
    "sg:city":"Beresfield",
    "sg:classifiers":[
        {
            "category":"Autos & Motor Vehicles",
            "subcategory":"Fuel & Gas Station",
            "type":"Retail Goods"
        }
    ],
    "sg:phone":"+61 2 4966 4610",
    "sg:postcode":"2322",
    "sg:province":"NSW",
    "wof:name":"Mobil Beresfield",
    "wof:placetype":"venue"
},
  "geometry": {"coordinates":[151.64698791500001,-32.800491333],"type":"Point"}
}