{
  "type": "Feature",
  "properties": {
    "iso:country":"AU",
    "sg:address":"13 Beryl Crt",
    "sg:city":"Skye",
    "sg:classifiers":[
        {
            "category":"Retail",
            "subcategory":"Storage",
            "type":"Services"
        }
    ],
    "sg:phone":"+61 414 618 750",
    "sg:postcode":"3977",
    "sg:province":"VIC",
    "sg:tags":[
        "removal",
        "furniture"
    ],
    "wof:name":"Stantrans Pty Ltd",
    "wof:placetype":"venue"
},
  "geometry": {"coordinates":[145.20217895499999,-38.0906295776],"type":"Point"}
}