{
  "type": "Feature",
  "properties": {
    "addr:full":"Tristana Drv Traralgon VIC 3844",
    "addr:postcode":"3844",
    "addr:street":"Tristana Drv",
    "iso:country":"AU",
    "sg:address":"Tristana Drv",
    "sg:city":"Traralgon",
    "sg:classifiers":[
        {
            "category":"Professional",
            "type":"Services"
        }
    ],
    "sg:phone":"+61 3 5174 3868",
    "sg:postcode":"3844",
    "sg:province":"VIC",
    "sg:tags":[
        "forwarding",
        "agent",
        "transport"
    ],
    "wof:name":"O&#039;Connor D & J",
    "wof:placetype":"venue"
},
  "geometry": {"coordinates":[146.57044982900001,-38.2015228271],"type":"Point"}
}