{
  "type": "Feature",
  "properties": {
    "addr:full":"1 Roche Crt Epping VIC 3076",
    "addr:housenumber":"1",
    "addr:postcode":"3076",
    "addr:street":"Roche Crt",
    "iso:country":"AU",
    "sg:address":"1 Roche Crt",
    "sg:city":"Epping",
    "sg:classifiers":[
        {
            "category":"Building & Trades",
            "subcategory":"Construction",
            "type":"Services"
        }
    ],
    "sg:phone":"+61 3 9401 2442",
    "sg:postcode":"3076",
    "sg:province":"VIC",
    "sg:tags":[
        "installation",
        "air conditioning"
    ],
    "wof:name":"A.C.H. Air Conditioning Services Pty Ltd",
    "wof:placetype":"venue"
},
  "geometry": {"coordinates":[145.039962769,-37.6470947266],"type":"Point"}
}