{
  "type": "Feature",
  "properties": {
    "iso:country":"AU",
    "sg:address":"Suite 25, Stirling Hwy",
    "sg:city":"Nedlands",
    "sg:classifiers":[
        {
            "category":"Communications",
            "type":"Services"
        }
    ],
    "sg:phone":"+61 8 9386 4546",
    "sg:postcode":"6009",
    "sg:province":"WA",
    "sg:tags":[
        "translation"
    ],
    "wof:name":"International Languages",
    "wof:placetype":"venue"
},
  "geometry": {"coordinates":[115.811348,-31.97765],"type":"Point"}
}