{
  "type": "Feature",
  "properties": {
    "iso:country":"AU",
    "sg:address":"Midland Central Clayton St",
    "sg:city":"Midland",
    "sg:classifiers":[
        {
            "category":"Home & Garden",
            "subcategory":"Furniture",
            "type":"Retail Goods"
        }
    ],
    "sg:phone":"+61 8 9274 1933",
    "sg:postcode":"6056",
    "sg:province":"WA",
    "sg:tags":[
        "outdoor"
    ],
    "wof:name":"The Outdoor Furniture Specialists",
    "wof:placetype":"venue"
},
  "geometry": {"coordinates":[116.009399414,-31.8956718445],"type":"Point"}
}