{
  "type": "Feature",
  "properties": {
    "addr:full":"77 Commercial Rd Port Augusta SA 5700",
    "addr:housenumber":"77",
    "addr:postcode":"5700",
    "addr:street":"Commercial Rd",
    "iso:country":"AU",
    "sg:address":"77 Commercial Rd",
    "sg:city":"Port Augusta",
    "sg:classifiers":[
        {
            "category":"Utilities",
            "subcategory":"Telephone",
            "type":"Services"
        }
    ],
    "sg:phone":"+61 8 8641 2727",
    "sg:postcode":"5700",
    "sg:province":"SA",
    "sg:tags":[
        "equipment",
        "system"
    ],
    "wof:name":"Arid Land Communications",
    "wof:placetype":"venue"
},
  "geometry": {"coordinates":[137.76312255900001,-32.4930114746],"type":"Point"}
}