{
  "type": "Feature",
  "properties": {
    "iso:country":"AU",
    "sg:address":"115 Watkins Rd",
    "sg:city":"Wangi Wangi",
    "sg:classifiers":[
        {
            "category":"Health Services",
            "subcategory":"Chiropractor",
            "type":"Services"
        }
    ],
    "sg:phone":"+61 2 4975 1532",
    "sg:postcode":"2267",
    "sg:province":"NSW",
    "wof:name":"Minors Ben",
    "wof:placetype":"venue"
},
  "geometry": {"coordinates":[151.600967,-33.071888],"type":"Point"}
}