{
  "type": "Feature",
  "properties": {
    "addr:full":"69 Marina St Ingham QLD 4850",
    "addr:housenumber":"69",
    "addr:postcode":"4850",
    "addr:street":"Marina St",
    "iso:country":"AU",
    "sg:address":"69 Marina St",
    "sg:city":"Ingham",
    "sg:classifiers":[
        {
            "category":"Arena",
            "subcategory":"Auto Racetrack",
            "type":"Entertainment"
        }
    ],
    "sg:phone":"+61 7 4776 2052",
    "sg:postcode":"4850",
    "sg:province":"QLD",
    "sg:tags":[
        "racecourse"
    ],
    "wof:name":"Herbert River Jockey Club",
    "wof:placetype":"venue"
},
  "geometry": {"coordinates":[146.16990661599999,-18.6531047821],"type":"Point"}
}