{
  "type": "Feature",
  "properties": {
    "iso:country":"AU",
    "sg:address":"Earlville Shopngtwn 517 Mulgrave Rd",
    "sg:city":"Earlville",
    "sg:classifiers":[
        {
            "category":"Banks & Credit Unions",
            "subcategory":"Bank",
            "type":"Services"
        }
    ],
    "sg:phone":"+61 13 20 32",
    "sg:postcode":"4870",
    "sg:province":"QLD",
    "wof:name":"Westpac",
    "wof:placetype":"venue"
},
  "geometry": {"coordinates":[145.74305725100001,-16.9396858215],"type":"Point"}
}