{
  "type": "Feature",
  "properties": {
    "addr:full":"5 Burgay Crt Osborne Park WA 6017",
    "addr:housenumber":"5",
    "addr:postcode":"6017",
    "addr:street":"Burgay Crt",
    "iso:country":"AU",
    "sg:address":"5 Burgay Crt",
    "sg:city":"Osborne Park",
    "sg:classifiers":[
        {
            "category":"Home & Garden",
            "subcategory":"Furniture",
            "type":"Retail Goods"
        }
    ],
    "sg:phone":"+61 8 9445 8087",
    "sg:postcode":"6017",
    "sg:province":"WA",
    "sg:tags":[
        "business"
    ],
    "wof:name":"Space Plan Solutions",
    "wof:placetype":"venue"
},
  "geometry": {"coordinates":[115.80268096899999,-31.9065132141],"type":"Point"}
}