{
  "type": "Feature",
  "properties": {
    "iso:country":"AU",
    "sg:address":"25 Stoneycreek Rd",
    "sg:city":"Bexley",
    "sg:classifiers":[
        {
            "category":"Organizations",
            "subcategory":"Professional Association",
            "type":"Services"
        }
    ],
    "sg:phone":"+61 2 9554 9399",
    "sg:postcode":"2207",
    "sg:province":"NSW",
    "sg:tags":[
        "organisation",
        "business"
    ],
    "wof:name":"Australian Licensed Aircraft Engineers Association",
    "wof:placetype":"venue"
},
  "geometry": {"coordinates":[151.107864,-33.948925],"type":"Point"}
}