{
  "type": "Feature",
  "properties": {
    "addr:full":"1 Andrews St Hamilton VIC 3300",
    "addr:housenumber":"1",
    "addr:postcode":"3300",
    "addr:street":"Andrews St",
    "iso:country":"AU",
    "sg:address":"1 Andrews St",
    "sg:city":"Hamilton",
    "sg:classifiers":[
        {
            "category":"Manufacturing",
            "subcategory":"Metals",
            "type":"Manufacturing & Wholesale Goods"
        }
    ],
    "sg:phone":"+61 3 5571 1888",
    "sg:postcode":"3300",
    "sg:province":"VIC",
    "sg:tags":[
        "steel",
        "fabricator",
        "mfrs"
    ],
    "wof:name":"Hamilton Steel",
    "wof:placetype":"venue"
},
  "geometry": {"coordinates":[141.99969482399999,-37.7272529602],"type":"Point"}
}