{
  "type": "Feature",
  "properties": {
    "iso:country":"AU",
    "sg:address":"Textile Ave",
    "sg:city":"Kawana Waters",
    "sg:classifiers":[
        {
            "category":"Personal",
            "subcategory":"Massage",
            "type":"Services"
        }
    ],
    "sg:phone":"+61 415 722 736",
    "sg:postcode":"4575",
    "sg:province":"QLD",
    "sg:tags":[
        "therapy"
    ],
    "wof:name":"Vital Balance Massage",
    "wof:placetype":"venue"
},
  "geometry": {"coordinates":[153.12423699999999,-26.730322],"type":"Point"}
}