{
  "type": "Feature",
  "properties": {
    "addr:full":"152 Junction Rd Nunawading VIC 3131",
    "addr:housenumber":"152",
    "addr:postcode":"3131",
    "addr:street":"Junction Rd",
    "iso:country":"AU",
    "sg:address":"152 Junction Rd",
    "sg:city":"Nunawading",
    "sg:classifiers":[
        {
            "category":"Health Services",
            "subcategory":"Health Practitioner",
            "type":"Services"
        }
    ],
    "sg:phone":"+61 3 9894 3700",
    "sg:postcode":"3131",
    "sg:province":"VIC",
    "sg:tags":[
        "naturopath"
    ],
    "wof:name":"Herb Doctor",
    "wof:placetype":"venue"
},
  "geometry": {"coordinates":[145.17483520499999,-37.8083763123],"type":"Point"}
}