{
  "type": "Feature",
  "properties": {
    "iso:country":"AU",
    "sg:address":"Shop 5 57 King St",
    "sg:city":"Sandy Bay",
    "sg:classifiers":[
        {
            "category":"Shopping",
            "subcategory":"Party Supplies",
            "type":"Retail Goods"
        }
    ],
    "sg:phone":"+61 3 6223 8726",
    "sg:postcode":"7005",
    "sg:province":"TAS",
    "sg:tags":[
        "children's"
    ],
    "wof:name":"Munchkins Child Friendly Cafe",
    "wof:placetype":"venue"
},
  "geometry": {"coordinates":[147.32650756800001,-42.8948822021],"type":"Point"}
}