{
  "type": "Feature",
  "properties": {
    "addr:full":"82 Bay St Port Melbourne VIC 3207",
    "addr:housenumber":"82",
    "addr:postcode":"3207",
    "addr:street":"Bay St",
    "iso:country":"AU",
    "sg:address":"82 Bay St",
    "sg:city":"Port Melbourne",
    "sg:classifiers":[
        {
            "category":"Health Services",
            "subcategory":"Doctor",
            "type":"Services"
        }
    ],
    "sg:phone":"+61 3 9681 7311",
    "sg:postcode":"3207",
    "sg:province":"VIC",
    "sg:tags":[
        "medical",
        "practitioner"
    ],
    "wof:name":"Endless Solutions - Health, Wellbeing, Longevity",
    "wof:placetype":"venue"
},
  "geometry": {"coordinates":[144.93954500000001,-37.841816],"type":"Point"}
}