{
  "type": "Feature",
  "properties": {
    "addr:full":"Lot 8, Moss Road Wingfield SA 5013",
    "addr:postcode":"5013",
    "addr:street":"Moss Road",
    "iso:country":"AU",
    "sg:address":"Lot 8, Moss Road",
    "sg:city":"Wingfield",
    "sg:classifiers":[
        {
            "category":"Professional",
            "type":"Services"
        }
    ],
    "sg:phone":"+61 8 8260 7288",
    "sg:postcode":"5013",
    "sg:province":"SA",
    "sg:tags":[
        "shop",
        "fitting"
    ],
    "wof:name":"New Age Joinery",
    "wof:placetype":"venue"
},
  "geometry": {"coordinates":[138.580810547,-34.840587616],"type":"Point"}
}