{
  "type": "Feature",
  "properties": {
    "addr:full":"257 Charters Towers Rd Townsville QLD 4810",
    "addr:housenumber":"257",
    "addr:postcode":"4810",
    "addr:street":"Charters Towers Rd",
    "iso:country":"AU",
    "sg:address":"257 Charters Towers Rd",
    "sg:city":"Townsville",
    "sg:classifiers":[
        {
            "category":"Manufacturing",
            "subcategory":"Furniture",
            "type":"Manufacturing & Wholesale Goods"
        }
    ],
    "sg:phone":"+61 7 4725 6300",
    "sg:postcode":"4810",
    "sg:province":"QLD",
    "sg:tags":[
        "equipment",
        "hire"
    ],
    "wof:name":"Digital Business Technology",
    "wof:placetype":"venue"
},
  "geometry": {"coordinates":[146.79646299999999,-19.288679],"type":"Point"}
}