{
  "type": "Feature",
  "properties": {
    "addr:full":"53 Nerang St Southport QLD 4215",
    "addr:housenumber":"53",
    "addr:postcode":"4215",
    "addr:street":"Nerang St",
    "iso:country":"AU",
    "sg:address":"53 Nerang St",
    "sg:city":"Southport",
    "sg:classifiers":[
        {
            "category":"Shopping",
            "subcategory":"Party Supplies",
            "type":"Retail Goods"
        }
    ],
    "sg:phone":"+61 7 5532 0008",
    "sg:postcode":"4215",
    "sg:province":"QLD",
    "sg:tags":[
        "hire",
        "costume"
    ],
    "wof:name":"Intanational Costumes",
    "wof:placetype":"venue"
},
  "geometry": {"coordinates":[153.412597656,-27.9681892395],"type":"Point"}
}