{
  "type": "Feature",
  "properties": {
    "addr:full":"Unit 2/ 50 Aruma Pl Cardiff NSW 2285",
    "addr:postcode":"2285",
    "addr:street":"50 Aruma Pl",
    "iso:country":"AU",
    "sg:address":"Unit 2/ 50 Aruma Pl",
    "sg:city":"Cardiff",
    "sg:classifiers":[
        {
            "category":"Autos & Motor Vehicles",
            "subcategory":"Boat Sales",
            "type":"Retail Goods"
        }
    ],
    "sg:phone":"+61 2 4954 7668",
    "sg:postcode":"2285",
    "sg:province":"NSW",
    "sg:tags":[
        "builder",
        "yacht",
        "repairer"
    ],
    "wof:name":"K.B. Fibreglass",
    "wof:placetype":"venue"
},
  "geometry": {"coordinates":[151.63897705100001,-32.9390258789],"type":"Point"}
}