{
  "type": "Feature",
  "properties": {
    "addr:full":"Unit 3, 91-93 Old Pittwater Rd Brookvale NSW 2100",
    "addr:housenumber":"91-93",
    "addr:postcode":"2100",
    "addr:street":"Old Pittwater Rd",
    "iso:country":"AU",
    "sg:address":"Unit 3, 91-93 Old Pittwater Rd",
    "sg:city":"Brookvale",
    "sg:classifiers":[
        {
            "category":"Building & Trades",
            "subcategory":"Equipment Rental",
            "type":"Services"
        }
    ],
    "sg:phone":"+61 2 9905 1300",
    "sg:postcode":"2100",
    "sg:province":"NSW",
    "sg:tags":[
        "fitness"
    ],
    "wof:name":"Fitness Generation Pty Ltd The",
    "wof:placetype":"venue"
},
  "geometry": {"coordinates":[151.262115478,-33.7676048279],"type":"Point"}
}