{
  "type": "Feature",
  "properties": {
    "addr:full":"16 Caulfield St Robina QLD 4226",
    "addr:housenumber":"16",
    "addr:postcode":"4226",
    "addr:street":"Caulfield St",
    "iso:country":"AU",
    "sg:address":"16 Caulfield St",
    "sg:city":"Robina",
    "sg:classifiers":[
        {
            "category":"Social Services",
            "subcategory":"Child Care",
            "type":"Services"
        }
    ],
    "sg:phone":"+61 7 5593 0362",
    "sg:postcode":"4226",
    "sg:province":"QLD",
    "wof:name":"Fuji International Kindergarten",
    "wof:placetype":"venue"
},
  "geometry": {"coordinates":[153.39700317399999,-28.0570297241],"type":"Point"}
}