{
  "type": "Feature",
  "properties": {
    "addr:full":"3 Highland Rd Thomastown VIC 3074",
    "addr:housenumber":"3",
    "addr:postcode":"3074",
    "addr:street":"Highland Rd",
    "iso:country":"AU",
    "sg:address":"3 Highland Rd",
    "sg:city":"Thomastown",
    "sg:classifiers":[
        {
            "category":"Health Services",
            "subcategory":"Health Practitioner",
            "type":"Services"
        }
    ],
    "sg:phone":"+61 3 9465 0282",
    "sg:postcode":"3074",
    "sg:province":"VIC",
    "sg:tags":[
        "physiotherapist"
    ],
    "wof:name":"Lalor Physiotherapy Centre",
    "wof:placetype":"venue"
},
  "geometry": {"coordinates":[145.013549805,-37.6792640686],"type":"Point"}
}