{
  "type": "Feature",
  "properties": {
    "iso:country":"AU",
    "sg:address":"50 Gloucester Rd",
    "sg:city":"Hurstville",
    "sg:classifiers":[
        {
            "category":"Health Services",
            "subcategory":"Doctor",
            "type":"Services"
        }
    ],
    "sg:phone":"+61 2 9586 3311",
    "sg:postcode":"2220",
    "sg:province":"NSW",
    "sg:tags":[
        "medical",
        "practitioner"
    ],
    "wof:name":"Fertility First",
    "wof:placetype":"venue"
},
  "geometry": {"coordinates":[151.09498596200001,-33.9608421326],"type":"Point"}
}