{
  "type": "Feature",
  "properties": {
    "iso:country":"AU",
    "sg:address":"771 Fifteenth St",
    "sg:city":"Mildura",
    "sg:classifiers":[
        {
            "category":"Retail",
            "subcategory":"Storage",
            "type":"Services"
        }
    ],
    "sg:phone":"+61 3 5023 4454",
    "sg:postcode":"3500",
    "sg:province":"VIC",
    "sg:tags":[
        "removal",
        "furniture"
    ],
    "wof:name":"Jati Imports",
    "wof:placetype":"venue"
},
  "geometry": {"coordinates":[142.14312744099999,-34.2119903564],"type":"Point"}
}