{
  "type": "Feature",
  "properties": {
    "iso:country":"AU",
    "sg:address":"49 Daisy St",
    "sg:city":"Grange",
    "sg:classifiers":[
        {
            "category":"Retail",
            "subcategory":"Laundry & Dry Cleaning",
            "type":"Services"
        }
    ],
    "sg:phone":"+61 403 302 965",
    "sg:postcode":"4051",
    "sg:province":"QLD",
    "sg:tags":[
        "ironing"
    ],
    "wof:name":"Daisy Fresh Washing & Ironing Service",
    "wof:placetype":"venue"
},
  "geometry": {"coordinates":[153.01130676299999,-27.4273071289],"type":"Point"}
}