{
  "type": "Feature",
  "properties": {
    "addr:full":"1/ 16 Griffin Drv Dunsborough WA 6281",
    "addr:housenumber":"/ 16",
    "addr:postcode":"6281",
    "addr:street":"Griffin Drv",
    "iso:country":"AU",
    "sg:address":"1/ 16 Griffin Drv",
    "sg:city":"Dunsborough",
    "sg:classifiers":[
        {
            "category":"Building & Trades",
            "subcategory":"Cleaning & Sanitation",
            "type":"Services"
        }
    ],
    "sg:phone":"+61 8 9755 3667",
    "sg:postcode":"6281",
    "sg:province":"WA",
    "sg:tags":[
        "industrial",
        "commercial",
        "contractor"
    ],
    "wof:name":"Blue Bay Property Services",
    "wof:placetype":"venue"
},
  "geometry": {"coordinates":[115.11472320599999,-33.6328010559],"type":"Point"}
}