{
  "type": "Feature",
  "properties": {
    "addr:full":"Cnr Monaro St & Princes Hwy Merimbula NSW 2548",
    "addr:postcode":"2548",
    "addr:street":"Cnr Monaro St & Princes Hwy",
    "iso:country":"AU",
    "sg:address":"Cnr Monaro St & Princes Hwy",
    "sg:city":"Merimbula",
    "sg:classifiers":[
        {
            "category":"School Buses",
            "type":"Transportation"
        }
    ],
    "sg:phone":"+61 2 6495 3044",
    "sg:postcode":"2548",
    "sg:province":"NSW",
    "sg:tags":[
        "brick"
    ],
    "wof:name":"Hayes Brick Centres",
    "wof:placetype":"venue"
},
  "geometry": {"coordinates":[149.90684509299999,-36.8909873962],"type":"Point"}
}