{
  "type": "Feature",
  "properties": {
    "addr:full":"20b Elliott St Midvale WA 6056",
    "addr:housenumber":"20b",
    "addr:postcode":"6056",
    "addr:street":"Elliott St",
    "iso:country":"AU",
    "sg:address":"20b Elliott St",
    "sg:city":"Midvale",
    "sg:classifiers":[
        {
            "category":"Wholesale",
            "subcategory":"Machinery & Supplies",
            "type":"Manufacturing & Wholesale Goods"
        }
    ],
    "sg:phone":"+61 8 9250 5055",
    "sg:postcode":"6056",
    "sg:province":"WA",
    "sg:tags":[
        "engine",
        "petrol"
    ],
    "wof:name":"Briggs Shop The",
    "wof:placetype":"venue"
},
  "geometry": {"coordinates":[116.03027343799999,-31.8938236237],"type":"Point"}
}