{
  "type": "Feature",
  "properties": {
    "addr:full":"28 Market St Brisbane QLD 4000",
    "addr:housenumber":"28",
    "addr:postcode":"4000",
    "addr:street":"Market St",
    "iso:country":"AU",
    "sg:address":"28 Market St",
    "sg:city":"Brisbane",
    "sg:classifiers":[
        {
            "category":"Professional",
            "subcategory":"Management & Consulting",
            "type":"Services"
        }
    ],
    "sg:phone":"+61 7 3230 8000",
    "sg:postcode":"4000",
    "sg:province":"QLD",
    "sg:tags":[
        "consultant"
    ],
    "wof:name":"Millhouse IAG (Investment & Advisory Group)",
    "wof:placetype":"venue"
},
  "geometry": {"coordinates":[153.03030395499999,-27.4660606384],"type":"Point"}
}