{
  "type": "Feature",
  "properties": {
    "addr:full":"319 Old Chum Creek Rd Healesville VIC 3777",
    "addr:housenumber":"319",
    "addr:postcode":"3777",
    "addr:street":"Old Chum Creek Rd",
    "iso:country":"AU",
    "sg:address":"319 Old Chum Creek Rd",
    "sg:city":"Healesville",
    "sg:classifiers":[
        {
            "category":"Farming",
            "subcategory":"Poultry Farm",
            "type":"Manufacturing & Wholesale Goods"
        }
    ],
    "sg:phone":"+61 3 5962 5394",
    "sg:postcode":"3777",
    "sg:province":"VIC",
    "sg:tags":[
        "farmer"
    ],
    "wof:name":"Chum Valley Eggs Farm",
    "wof:placetype":"venue"
},
  "geometry": {"coordinates":[145.479614,-37.57893],"type":"Point"}
}