{
  "type": "Feature",
  "properties": {
    "addr:full":"Wallcliffe Rd Margaret River WA 6285",
    "addr:postcode":"6285",
    "addr:street":"Wallcliffe Rd",
    "iso:country":"AU",
    "sg:address":"Wallcliffe Rd",
    "sg:city":"Margaret River",
    "sg:classifiers":[
        {
            "category":"Education",
            "subcategory":"School",
            "type":"Public Place"
        }
    ],
    "sg:phone":"+61 8 9757 3544",
    "sg:postcode":"6285",
    "sg:province":"WA",
    "wof:name":"St Thomas More Catholic Primary School",
    "wof:placetype":"venue"
},
  "geometry": {"coordinates":[115.07305145300001,-33.9536552429],"type":"Point"}
}