{
  "type": "Feature",
  "properties": {
    "iso:country":"AU",
    "sg:address":"McDonalds Drain Rd",
    "sg:city":"Pakenham South",
    "sg:classifiers":[
        {
            "category":"Farming",
            "subcategory":"Farm",
            "type":"Manufacturing & Wholesale Goods"
        }
    ],
    "sg:phone":"+61 3 5942 6202",
    "sg:postcode":"3810",
    "sg:province":"VIC",
    "sg:tags":[
        "farmer"
    ],
    "wof:name":"Ellett S B",
    "wof:placetype":"venue"
},
  "geometry": {"coordinates":[145.51040599999999,-38.109016],"type":"Point"}
}