{
  "type": "Feature",
  "properties": {
    "addr:full":"3/ 103 Beringarra Ave Malaga WA 6090",
    "addr:housenumber":"/ 103",
    "addr:postcode":"6090",
    "addr:street":"Beringarra Ave",
    "iso:country":"AU",
    "sg:address":"3/ 103 Beringarra Ave",
    "sg:city":"Malaga",
    "sg:classifiers":[
        {
            "category":"Home & Garden",
            "subcategory":"Carpets & Floor Coverings",
            "type":"Retail Goods"
        }
    ],
    "sg:phone":"+61 1300 304 082",
    "sg:postcode":"6090",
    "sg:province":"WA",
    "sg:tags":[
        "double",
        "window",
        "glazed"
    ],
    "sg:website":"http://www.magnetite.com.au",
    "wof:name":"Magnetite",
    "wof:placetype":"venue"
},
  "geometry": {"coordinates":[115.904067993,-31.8635864258],"type":"Point"}
}