{
  "type": "Feature",
  "properties": {
    "addr:full":"64 Young St Frankston VIC 3199",
    "addr:housenumber":"64",
    "addr:postcode":"3199",
    "addr:street":"Young St",
    "iso:country":"AU",
    "sg:address":"64 Young St",
    "sg:city":"Frankston",
    "sg:classifiers":[
        {
            "category":"Fast Food",
            "type":"Food & Drink"
        }
    ],
    "sg:phone":"+61 3 8774 0009",
    "sg:postcode":"3199",
    "sg:province":"VIC",
    "sg:tags":[
        "away",
        "take"
    ],
    "wof:name":"Daily Kebab",
    "wof:placetype":"venue"
},
  "geometry": {"coordinates":[144.978424072,-37.8062324524],"type":"Point"}
}