{
  "type": "Feature",
  "properties": {
    "addr:full":"Fcty 3/ 20 Enterprise Ave Berwick VIC 3806",
    "addr:housenumber":"/ 20",
    "addr:postcode":"3806",
    "addr:street":"Enterprise Ave",
    "iso:country":"AU",
    "sg:address":"Fcty 3/ 20 Enterprise Ave",
    "sg:city":"Berwick",
    "sg:classifiers":[
        {
            "category":"Professional",
            "subcategory":"Testing Lab",
            "type":"Services"
        }
    ],
    "sg:phone":"+61 3 9769 5799",
    "sg:postcode":"3806",
    "sg:province":"VIC",
    "sg:tags":[
        "soil",
        "investigation"
    ],
    "wof:name":"Terra Firma Laboratories",
    "wof:placetype":"venue"
},
  "geometry": {"coordinates":[145.34124755900001,-38.0373954773],"type":"Point"}
}