{
  "type": "Feature",
  "properties": {
    "addr:full":"61 High St Eaglehawk VIC 3556",
    "addr:housenumber":"61",
    "addr:postcode":"3556",
    "addr:street":"High St",
    "iso:country":"AU",
    "sg:address":"61 High St",
    "sg:city":"Eaglehawk",
    "sg:classifiers":[
        {
            "category":"Professional",
            "subcategory":"Accounting & Tax Preparation",
            "type":"Services"
        }
    ],
    "sg:phone":"+61 3 5442 8648",
    "sg:postcode":"3556",
    "sg:province":"VIC",
    "sg:tags":[
        "accountant",
        "auditor"
    ],
    "wof:name":"CAD Partners",
    "wof:placetype":"venue"
},
  "geometry": {"coordinates":[144.249633789,-36.7074394226],"type":"Point"}
}