{
  "type": "Feature",
  "properties": {
    "iso:country":"AU",
    "sg:address":"First Level/ 113 Oxford St",
    "sg:city":"Darlinghurst",
    "sg:classifiers":[
        {
            "category":"Shopping",
            "subcategory":"Clothing, Apparel, & Fashions",
            "type":"Retail Goods"
        }
    ],
    "sg:phone":"+61 2 9360 3311",
    "sg:postcode":"2010",
    "sg:province":"NSW",
    "sg:tags":[
        "lady",
        "wear"
    ],
    "wof:name":"Magnet Department Store DLC",
    "wof:placetype":"venue"
},
  "geometry": {"coordinates":[151.215042114,-33.8792114258],"type":"Point"}
}