{
  "type": "Feature",
  "properties": {
    "addr:full":"14 The Esplanade St Cowes VIC 3922",
    "addr:housenumber":"14",
    "addr:postcode":"3922",
    "addr:street":"The Esplanade St",
    "iso:country":"AU",
    "sg:address":"14 The Esplanade St",
    "sg:city":"Cowes",
    "sg:classifiers":[
        {
            "category":"Fast Food",
            "type":"Food & Drink"
        }
    ],
    "sg:phone":"+61 3 5952 3216",
    "sg:postcode":"3922",
    "sg:province":"VIC",
    "sg:tags":[
        "away",
        "take"
    ],
    "wof:name":"Fishbizz",
    "wof:placetype":"venue"
},
  "geometry": {"coordinates":[145.238677978,-38.4481925964],"type":"Point"}
}