{
  "type": "Feature",
  "properties": {
    "addr:full":"808 Warrenheip St Buninyong VIC 3357",
    "addr:housenumber":"808",
    "addr:postcode":"3357",
    "addr:street":"Warrenheip St",
    "iso:country":"AU",
    "sg:address":"808 Warrenheip St",
    "sg:city":"Buninyong",
    "sg:classifiers":[
        {
            "category":"Building & Trades",
            "subcategory":"Plumbing",
            "type":"Services"
        }
    ],
    "sg:phone":"+61 3 5341 8161",
    "sg:postcode":"3357",
    "sg:province":"VIC",
    "sg:tags":[
        "plumber",
        "gasfitters"
    ],
    "wof:name":"Gary Pond T/as Onshore Plumbing",
    "wof:placetype":"venue"
},
  "geometry": {"coordinates":[143.88269,-37.653553],"type":"Point"}
}