{
  "type": "Feature",
  "properties": {
    "iso:country":"AU",
    "sg:address":"190a Booran Rd",
    "sg:city":"Caulfield",
    "sg:classifiers":[
        {
            "category":"Personal",
            "subcategory":"Beauty Salon",
            "type":"Services"
        }
    ],
    "sg:phone":"+61 3 9578 4246",
    "sg:postcode":"3162",
    "sg:province":"VIC",
    "sg:tags":[
        "hairdresser"
    ],
    "wof:name":"Emphasis Hair",
    "wof:placetype":"venue"
},
  "geometry": {"coordinates":[145.03636169399999,-37.896484375],"type":"Point"}
}