{
  "type": "Feature",
  "properties": {
    "addr:full":"Unit 5/ 3 Cranbrook Rd Batemans Bay NSW 2536",
    "addr:housenumber":"3",
    "addr:postcode":"2536",
    "addr:street":"Cranbrook Rd",
    "iso:country":"AU",
    "sg:address":"Unit 5/ 3 Cranbrook Rd",
    "sg:city":"Batemans Bay",
    "sg:classifiers":[
        {
            "category":"Structure",
            "subcategory":"Building",
            "type":"Public Place"
        }
    ],
    "sg:phone":"+61 1300 888 509",
    "sg:postcode":"2536",
    "sg:province":"NSW",
    "sg:tags":[
        "sail",
        "shade"
    ],
    "wof:name":"3D Sails",
    "wof:placetype":"venue"
},
  "geometry": {"coordinates":[150.17526245100001,-35.7201271057],"type":"Point"}
}