{
  "type": "Feature",
  "properties": {
    "addr:full":"PO Box 220 Pottsville NSW 2489",
    "addr:postcode":"2489",
    "iso:country":"AU",
    "sg:address":"PO Box 220",
    "sg:city":"Pottsville",
    "sg:classifiers":[
        {
            "category":"Real Estate",
            "subcategory":"Real Estate Agent",
            "type":"Services"
        }
    ],
    "sg:phone":"+61 2 6676 3777",
    "sg:postcode":"2489",
    "sg:province":"NSW",
    "wof:name":"Laraine Whyte Real Estate",
    "wof:placetype":"venue"
},
  "geometry": {"coordinates":[153.564163208,-28.3891506195],"type":"Point"}
}