{
  "type": "Feature",
  "properties": {
    "addr:full":"Shop 7 314 Darling St Balmain NSW 2041",
    "addr:housenumber":"shop 7 314",
    "addr:postcode":"2041",
    "addr:street":"Darling St",
    "iso:country":"AU",
    "sg:address":"Shop 7 314 Darling St",
    "sg:city":"Balmain",
    "sg:classifiers":[
        {
            "category":"Arts & Performance",
            "subcategory":"Art Gallery",
            "type":"Entertainment"
        }
    ],
    "sg:phone":"+61 2 9555 9678",
    "sg:postcode":"2041",
    "sg:province":"NSW",
    "sg:tags":[
        "aboriginal",
        "craft"
    ],
    "wof:name":"Cando Classic Clothing",
    "wof:placetype":"venue"
},
  "geometry": {"coordinates":[151.179993,-33.857136],"type":"Point"}
}