{
  "type": "Feature",
  "properties": {
    "iso:country":"AU",
    "sg:address":"Shop 7, Oxley Circle Shopping Centre, 128 Lae Drv",
    "sg:city":"Runaway Bay",
    "sg:classifiers":[
        {
            "category":"Real Estate",
            "subcategory":"Real Estate Agent",
            "type":"Services"
        }
    ],
    "sg:phone":"+61 7 5529 0576",
    "sg:postcode":"4216",
    "sg:province":"QLD",
    "wof:name":"L.J. Hooker",
    "wof:placetype":"venue"
},
  "geometry": {"coordinates":[153.39768981899999,-27.9126338959],"type":"Point"}
}