{
  "type": "Feature",
  "properties": {
    "iso:country":"AU",
    "sg:address":"126 Victoria Rd",
    "sg:city":"Marrickville",
    "sg:classifiers":[
        {
            "category":"Professional",
            "subcategory":"Detective & Security Services",
            "type":"Services"
        }
    ],
    "sg:phone":"+61 2 9565 5912",
    "sg:postcode":"2204",
    "sg:province":"NSW",
    "sg:tags":[
        "equipment",
        "window",
        "doors"
    ],
    "sg:website":"http://www.acemetalwork.com.au",
    "wof:name":"Ace Metalwork",
    "wof:placetype":"venue"
},
  "geometry": {"coordinates":[151.165085,-33.906349],"type":"Point"}
}