{
  "type": "Feature",
  "properties": {
    "addr:full":"PO Box 377 Milsons Point NSW 1565",
    "addr:postcode":"1565",
    "iso:country":"AU",
    "sg:address":"PO Box 377",
    "sg:city":"Milsons Point",
    "sg:classifiers":[
        {
            "category":"Wholesale",
            "subcategory":"Chemicals & Plastics",
            "type":"Manufacturing & Wholesale Goods"
        }
    ],
    "sg:phone":"+61 2 9267 8422",
    "sg:postcode":"1565",
    "sg:province":"NSW",
    "sg:tags":[
        "bag"
    ],
    "wof:name":"Only Bags",
    "wof:placetype":"venue"
},
  "geometry": {"coordinates":[151.21270751899999,-33.8462715149],"type":"Point"}
}