{
  "type": "Feature",
  "properties": {
    "addr:full":"55 Links Ave (North) Eagle Farm QLD 4009",
    "addr:housenumber":"55",
    "addr:postcode":"4009",
    "addr:street":"Links Ave North",
    "iso:country":"AU",
    "sg:address":"55 Links Ave (North)",
    "sg:city":"Eagle Farm",
    "sg:classifiers":[
        {
            "category":"Shopping",
            "subcategory":"Computers & Home Electronics",
            "type":"Retail Goods"
        }
    ],
    "sg:phone":"+61 7 3268 1266",
    "sg:postcode":"4009",
    "sg:province":"QLD",
    "sg:tags":[
        "hardware",
        "equipment"
    ],
    "wof:name":"Aarqueanitech Pty Ltd",
    "wof:placetype":"venue"
},
  "geometry": {"coordinates":[153.09239196799999,-27.3970108032],"type":"Point"}
}