{
  "type": "Feature",
  "properties": {
    "addr:full":"Imperial Hotel Building 105 Faulkner St Armidale NSW 2350",
    "addr:housenumber":"105",
    "addr:postcode":"2350",
    "addr:street":"Faulkner St",
    "iso:country":"AU",
    "sg:address":"Imperial Hotel Building 105 Faulkner St",
    "sg:city":"Armidale",
    "sg:classifiers":[
        {
            "category":"Insurance",
            "subcategory":"Hazard Insurance",
            "type":"Services"
        }
    ],
    "sg:phone":"+61 2 6771 4400",
    "sg:postcode":"2350",
    "sg:province":"NSW",
    "sg:tags":[
        "motor",
        "vehicle"
    ],
    "wof:name":"James McDonald Insurance Agent Pty Ltd",
    "wof:placetype":"venue"
},
  "geometry": {"coordinates":[151.66690063499999,-30.5148124695],"type":"Point"}
}