{
  "type": "Feature",
  "properties": {
    "addr:full":"6 Ratcliffe St Eleebana NSW 2282",
    "addr:housenumber":"6",
    "addr:postcode":"2282",
    "addr:street":"Ratcliffe St",
    "iso:country":"AU",
    "sg:address":"6 Ratcliffe St",
    "sg:city":"Eleebana",
    "sg:classifiers":[
        {
            "category":"Utilities",
            "subcategory":"Electric",
            "type":"Services"
        }
    ],
    "sg:phone":"+61 2 4946 1545",
    "sg:postcode":"2282",
    "sg:province":"NSW",
    "sg:tags":[
        "electrical",
        "contractor"
    ],
    "wof:name":"NRL Electrical",
    "wof:placetype":"venue"
},
  "geometry": {"coordinates":[151.63981628400001,-32.9904785156],"type":"Point"}
}