{
  "type": "Feature",
  "properties": {
    "iso:country":"AU",
    "sg:address":"118 Bathurst St",
    "sg:city":"Launceston",
    "sg:classifiers":[
        {
            "category":"Retail",
            "subcategory":"Auto Repair",
            "type":"Services"
        }
    ],
    "sg:phone":"+61 3 6334 4067",
    "sg:postcode":"7250",
    "sg:province":"TAS",
    "sg:tags":[
        "clutch",
        "brake"
    ],
    "wof:name":"Bathurst Street Workshop",
    "wof:placetype":"venue"
},
  "geometry": {"coordinates":[147.13812255900001,-41.4451255798],"type":"Point"}
}