{
  "type": "Feature",
  "properties": {
    "addr:full":"Crawfords La Alstonville NSW 2477",
    "addr:postcode":"2477",
    "iso:country":"AU",
    "sg:address":"Crawfords La",
    "sg:city":"Alstonville",
    "sg:classifiers":[
        {
            "category":"Shopping",
            "subcategory":"Pets & Pet Supplies",
            "type":"Retail Goods"
        }
    ],
    "sg:phone":"+61 412 168 257",
    "sg:postcode":"2477",
    "sg:province":"NSW",
    "sg:tags":[
        "sheep",
        "equipment",
        "shearing"
    ],
    "wof:name":"Sheep Management & Shearing Services",
    "wof:placetype":"venue"
},
  "geometry": {"coordinates":[153.37738037099999,-28.8869991302],"type":"Point"}
}