{
  "type": "Feature",
  "properties": {
    "addr:full":"30a Prince St Busselton WA 6280",
    "addr:housenumber":"30a",
    "addr:postcode":"6280",
    "addr:street":"Prince St",
    "iso:country":"AU",
    "sg:address":"30a Prince St",
    "sg:city":"Busselton",
    "sg:classifiers":[
        {
            "category":"Personal",
            "subcategory":"Beauty Salon",
            "type":"Services"
        }
    ],
    "sg:phone":"+61 8 9754 3133",
    "sg:postcode":"6280",
    "sg:province":"WA",
    "wof:name":"Busselton Skin And Body Centre",
    "wof:placetype":"venue"
},
  "geometry": {"coordinates":[115.34416198700001,-33.6510543823],"type":"Point"}
}