{
  "type": "Feature",
  "properties": {
    "iso:country":"AU",
    "sg:address":"8 Peveril St",
    "sg:city":"Glen Waverley",
    "sg:classifiers":[
        {
            "category":"Building & Trades",
            "subcategory":"Construction",
            "type":"Services"
        }
    ],
    "sg:phone":"+61 3 9802 6611",
    "sg:postcode":"3150",
    "sg:province":"VIC",
    "sg:tags":[
        "insulation",
        "contractor"
    ],
    "wof:name":"Contract Insulations Pty Ltd",
    "wof:placetype":"venue"
},
  "geometry": {"coordinates":[145.15054321299999,-37.8900718689],"type":"Point"}
}