{
  "type": "Feature",
  "properties": {
    "addr:full":"Broadarrow Rd Beverly Hills NSW 2209",
    "addr:postcode":"2209",
    "addr:street":"Broadarrow Rd",
    "iso:country":"AU",
    "sg:address":"Broadarrow Rd",
    "sg:city":"Beverly Hills",
    "sg:classifiers":[
        {
            "category":"Education",
            "subcategory":"School",
            "type":"Public Place"
        }
    ],
    "sg:phone":"+61 2 9150 4280",
    "sg:postcode":"2209",
    "sg:province":"NSW",
    "sg:tags":[
        "state",
        "-",
        "nsw"
    ],
    "wof:name":"Beverly Hills Girls' High School",
    "wof:placetype":"venue"
},
  "geometry": {"coordinates":[151.07827800000001,-33.947193],"type":"Point"}
}