{
  "type": "Feature",
  "properties": {
    "addr:full":"14 Rangers Rd Neutral Bay NSW 2089",
    "addr:housenumber":"14",
    "addr:postcode":"2089",
    "addr:street":"Rangers Rd",
    "iso:country":"AU",
    "sg:address":"14 Rangers Rd",
    "sg:city":"Neutral Bay",
    "sg:classifiers":[
        {
            "category":"Professional",
            "subcategory":"Management & Consulting",
            "type":"Services"
        }
    ],
    "sg:phone":"+61 2 9953 4281",
    "sg:postcode":"2089",
    "sg:province":"NSW",
    "sg:tags":[
        "consultant"
    ],
    "wof:name":"Warwick Hamill & Associates Pty Ltd",
    "wof:placetype":"venue"
},
  "geometry": {"coordinates":[151.22434997600001,-33.8320388794],"type":"Point"}
}