{
  "type": "Feature",
  "properties": {
    "addr:full":"1603 Botany Rd Botany NSW 2019",
    "addr:housenumber":"1603",
    "addr:postcode":"2019",
    "addr:street":"Botany Rd",
    "iso:country":"AU",
    "sg:address":"1603 Botany Rd",
    "sg:city":"Botany",
    "sg:classifiers":[
        {
            "category":"Shopping",
            "subcategory":"Antiques",
            "type":"Retail Goods"
        }
    ],
    "sg:phone":"+61 2 9316 4445",
    "sg:postcode":"2019",
    "sg:province":"NSW",
    "sg:tags":[
        "restoration",
        "reproduction"
    ],
    "wof:name":"Eastern Suburbs Antique Restorations Pty Ltd",
    "wof:placetype":"venue"
},
  "geometry": {"coordinates":[151.20399475100001,-33.9488830566],"type":"Point"}
}