{
  "type": "Feature",
  "properties": {
    "addr:full":"119 Laidlaw St Boggabri NSW 2382",
    "addr:housenumber":"119",
    "addr:postcode":"2382",
    "addr:street":"Laidlaw St",
    "iso:country":"AU",
    "sg:address":"119 Laidlaw St",
    "sg:city":"Boggabri",
    "sg:classifiers":[
        {
            "category":"Social Services",
            "subcategory":"Child Care",
            "type":"Services"
        }
    ],
    "sg:phone":"+61 2 6743 4791",
    "sg:postcode":"2382",
    "sg:province":"NSW",
    "sg:tags":[
        "shearer"
    ],
    "wof:name":"Campbell Glenn",
    "wof:placetype":"venue"
},
  "geometry": {"coordinates":[150.046600342,-30.6991691589],"type":"Point"}
}