{
  "type": "Feature",
  "properties": {
    "addr:full":"PO Box 2374 Greenhills NSW 2323",
    "addr:postcode":"2323",
    "iso:country":"AU",
    "sg:address":"PO Box 2374",
    "sg:city":"Greenhills",
    "sg:classifiers":[
        {
            "category":"Arena",
            "subcategory":"Sports Club",
            "type":"Entertainment"
        }
    ],
    "sg:phone":"+61 2 4933 0771",
    "sg:postcode":"2323",
    "sg:province":"NSW",
    "sg:tags":[
        "defence",
        "supply",
        "self",
        "instruction",
        "martial art"
    ],
    "sg:website":"http://www.huntervalleykarate.com.au",
    "wof:name":"Hunter Valley Karate",
    "wof:placetype":"venue"
},
  "geometry": {"coordinates":[151.60096740700001,-32.7607192993],"type":"Point"}
}