{
  "type": "Feature",
  "properties": {
    "iso:country":"AU",
    "sg:address":"52b Joseph St",
    "sg:city":"Lidcombe",
    "sg:classifiers":[
        {
            "category":"Shopping",
            "subcategory":"Clothing, Apparel, & Fashions",
            "type":"Retail Goods"
        }
    ],
    "sg:phone":"+61 2 9649 8057",
    "sg:postcode":"2141",
    "sg:province":"NSW",
    "sg:tags":[
        "menswear"
    ],
    "wof:name":"Keighley's Mens and Ladies Wear",
    "wof:placetype":"venue"
},
  "geometry": {"coordinates":[151.043136597,-33.8665313721],"type":"Point"}
}