{
  "type": "Feature",
  "properties": {
    "addr:full":"10 Augustine St Hunters Hill NSW 2110",
    "addr:housenumber":"10",
    "addr:postcode":"2110",
    "addr:street":"Augustine St",
    "iso:country":"AU",
    "sg:address":"10 Augustine St",
    "sg:city":"Hunters Hill",
    "sg:classifiers":[
        {
            "category":"Shopping",
            "subcategory":"Optical Goods",
            "type":"Retail Goods"
        }
    ],
    "sg:phone":"+61 1300 644 872",
    "sg:postcode":"2110",
    "sg:province":"NSW",
    "sg:tags":[
        "supply"
    ],
    "wof:name":"Isupply Pty Ltd",
    "wof:placetype":"venue"
},
  "geometry": {"coordinates":[151.134475708,-33.8311538696],"type":"Point"}
}