{
  "type": "Feature",
  "properties": {
    "addr:full":"Unit 2/ 16 Lucy St Moorooka QLD 4105",
    "addr:housenumber":"16",
    "addr:postcode":"4105",
    "addr:street":"Lucy St",
    "iso:country":"AU",
    "sg:address":"Unit 2/ 16 Lucy St",
    "sg:city":"Moorooka",
    "sg:classifiers":[
        {
            "category":"Government",
            "subcategory":"Fire Station",
            "type":"Public Place"
        }
    ],
    "sg:phone":"+61 7 3892 6444",
    "sg:postcode":"4105",
    "sg:province":"QLD",
    "sg:tags":[
        "equipment",
        "protection",
        "consultant"
    ],
    "wof:name":"Notifier Inertia Fire Systems",
    "wof:placetype":"venue"
},
  "geometry": {"coordinates":[153.01817321799999,-27.5295391083],"type":"Point"}
}