{
  "type": "Feature",
  "properties": {
    "addr:full":"St Peters SA 5069",
    "addr:postcode":"5069",
    "iso:country":"AU",
    "sg:address":"St",
    "sg:city":"Peters",
    "sg:classifiers":[
        {
            "category":"Professional",
            "subcategory":"Business Services",
            "type":"Services"
        }
    ],
    "sg:phone":"+61 8 8362 1774",
    "sg:postcode":"5069",
    "sg:province":"SA",
    "sg:tags":[
        "consultant",
        "promoter",
        "entertainment"
    ],
    "wof:name":"Alan Holy-Comedy",
    "wof:placetype":"venue"
},
  "geometry": {"coordinates":[138.623504639,-34.9047203064],"type":"Point"}
}