{
  "type": "Feature",
  "properties": {
    "addr:full":"33 Bay Rd Sandringham VIC 3191",
    "addr:housenumber":"33",
    "addr:postcode":"3191",
    "addr:street":"Bay Rd",
    "iso:country":"AU",
    "sg:address":"33 Bay Rd",
    "sg:city":"Sandringham",
    "sg:classifiers":[
        {
            "category":"Health Services",
            "subcategory":"Nursing And Care Facility",
            "type":"Services"
        }
    ],
    "sg:phone":"+61 3 9598 5816",
    "sg:postcode":"3191",
    "sg:province":"VIC",
    "sg:tags":[
        "home"
    ],
    "wof:name":"St Leigh Private Nursing Home",
    "wof:placetype":"venue"
},
  "geometry": {"coordinates":[145.00564575199999,-37.9517593384],"type":"Point"}
}