{
  "type": "Feature",
  "properties": {
    "iso:country":"AU",
    "sg:address":"58 High St",
    "sg:city":"Wedderburn",
    "sg:classifiers":[
        {
            "category":"Professional",
            "subcategory":"Employment Agencies",
            "type":"Services"
        }
    ],
    "sg:phone":"+61 3 5494 1900",
    "sg:postcode":"3518",
    "sg:province":"VIC",
    "wof:name":"MAETS (JOBfutures)",
    "wof:placetype":"venue"
},
  "geometry": {"coordinates":[143.614349,-36.420658],"type":"Point"}
}