{
  "type": "Feature",
  "properties": {
    "iso:country":"AU",
    "sg:address":"612 Princes Hwy",
    "sg:city":"St Peters",
    "sg:classifiers":[
        {
            "category":"Autos & Motor Vehicles",
            "subcategory":"Automobile Sales",
            "type":"Retail Goods"
        }
    ],
    "sg:phone":"+61 2 9519 7777",
    "sg:postcode":"2044",
    "sg:province":"NSW",
    "sg:tags":[
        "car",
        "used"
    ],
    "wof:name":"Shaw Graham G Automotive Pty Ltd",
    "wof:placetype":"venue"
},
  "geometry": {"coordinates":[151.163773,-33.922047],"type":"Point"}
}