{
  "type": "Feature",
  "properties": {
    "addr:full":"110 Yorktown Rd Elizabeth Park SA 5113",
    "addr:housenumber":"110",
    "addr:postcode":"5113",
    "addr:street":"Yorktown Rd",
    "iso:country":"AU",
    "sg:address":"110 Yorktown Rd",
    "sg:city":"Elizabeth Park",
    "sg:classifiers":[
        {
            "category":"Health Services",
            "subcategory":"Dentist",
            "type":"Services"
        }
    ],
    "sg:phone":"+61 8 8287 0291",
    "sg:postcode":"5113",
    "sg:province":"SA",
    "sg:tags":[
        "technician",
        "dental"
    ],
    "wof:name":"Paulit Horry",
    "wof:placetype":"venue"
},
  "geometry": {"coordinates":[138.68211364699999,-34.7139778137],"type":"Point"}
}