{
  "type": "Feature",
  "properties": {
    "addr:full":"10 Grandview Drv Tea Tree Gully SA 5091",
    "addr:housenumber":"10",
    "addr:postcode":"5091",
    "addr:street":"Grandview Drv",
    "iso:country":"AU",
    "sg:address":"10 Grandview Drv",
    "sg:city":"Tea Tree Gully",
    "sg:classifiers":[
        {
            "category":"Professional",
            "subcategory":"Printing & Photocopies",
            "type":"Services"
        }
    ],
    "sg:phone":"+61 8 8265 1433",
    "sg:postcode":"5091",
    "sg:province":"SA",
    "sg:tags":[
        "laminating"
    ],
    "wof:name":"Clear All Plastic Laminating",
    "wof:placetype":"venue"
},
  "geometry": {"coordinates":[138.72190856899999,-34.8309783936],"type":"Point"}
}