{
  "type": "Feature",
  "properties": {
    "addr:full":"12 Coombes Drv Penrith NSW 2750",
    "addr:housenumber":"12",
    "addr:postcode":"2750",
    "addr:street":"Coombes Drv",
    "iso:country":"AU",
    "sg:address":"12 Coombes Drv",
    "sg:city":"Penrith",
    "sg:classifiers":[
        {
            "category":"Manufacturing",
            "subcategory":"Metals",
            "type":"Manufacturing & Wholesale Goods"
        }
    ],
    "sg:phone":"+61 2 4732 5011",
    "sg:postcode":"2750",
    "sg:province":"NSW",
    "sg:tags":[
        "sheet",
        "worker"
    ],
    "wof:name":"Sydney Fabrication Services",
    "wof:placetype":"venue"
},
  "geometry": {"coordinates":[150.697265625,-33.7429962158],"type":"Point"}
}