{
  "type": "Feature",
  "properties": {
    "addr:full":"17 Barkly St Mordialloc VIC 3195",
    "addr:housenumber":"17",
    "addr:postcode":"3195",
    "addr:street":"Barkly St",
    "iso:country":"AU",
    "sg:address":"17 Barkly St",
    "sg:city":"Mordialloc",
    "sg:classifiers":[
        {
            "category":"Professional",
            "subcategory":"Art Services",
            "type":"Services"
        }
    ],
    "sg:phone":"+61 3 9580 0112",
    "sg:postcode":"3195",
    "sg:province":"VIC",
    "sg:tags":[
        "graphic",
        "designer"
    ],
    "wof:name":"Mousetrap Graphics",
    "wof:placetype":"venue"
},
  "geometry": {"coordinates":[145.08734130900001,-38.0000915527],"type":"Point"}
}