{
  "type": "Feature",
  "properties": {
    "iso:country":"AU",
    "sg:address":"89 Forgan Rd",
    "sg:city":"Strathpine",
    "sg:classifiers":[
        {
            "category":"Wholesale",
            "subcategory":"Home Furnishings",
            "type":"Manufacturing & Wholesale Goods"
        }
    ],
    "sg:phone":"+61 421 119 166",
    "sg:postcode":"4500",
    "sg:province":"QLD",
    "sg:tags":[
        "terrazzo"
    ],
    "wof:name":"Barnaby May",
    "wof:placetype":"venue"
},
  "geometry": {"coordinates":[152.931106567,-27.279460907],"type":"Point"}
}