{
  "type": "Feature",
  "properties": {
    "iso:country":"AU",
    "sg:address":"46 Jilba St",
    "sg:city":"Indooroopilly",
    "sg:classifiers":[
        {
            "category":"Real Estate",
            "subcategory":"Surveying",
            "type":"Services"
        }
    ],
    "sg:phone":"+61 7 3378 0422",
    "sg:postcode":"4068",
    "sg:province":"QLD",
    "sg:tags":[
        "surveyor",
        "land"
    ],
    "wof:name":"Westside Surveys",
    "wof:placetype":"venue"
},
  "geometry": {"coordinates":[152.965209961,-27.5122680664],"type":"Point"}
}