{
  "type": "Feature",
  "properties": {
    "iso:country":"AU",
    "sg:address":"1 Austin St",
    "sg:city":"Trundle",
    "sg:classifiers":[
        {
            "category":"Education",
            "subcategory":"School",
            "type":"Public Place"
        }
    ],
    "sg:phone":"+61 2 6892 1073",
    "sg:postcode":"2875",
    "sg:province":"NSW",
    "wof:name":"St Patricks School",
    "wof:placetype":"venue"
},
  "geometry": {"coordinates":[147.708786,-32.923569],"type":"Point"}
}