{
  "type": "Feature",
  "properties": {
    "iso:country":"AU",
    "sg:address":"104 Fitzroy St",
    "sg:city":"Surry Hills",
    "sg:classifiers":[
        {
            "category":"Cafe",
            "type":"Food & Drink"
        }
    ],
    "sg:phone":"+61 2 9357 7104",
    "sg:postcode":"2010",
    "sg:province":"NSW",
    "wof:name":"Monkey's Coffee",
    "wof:placetype":"venue"
},
  "geometry": {"coordinates":[151.217071533,-33.885597229],"type":"Point"}
}