{
  "type": "Feature",
  "properties": {
    "iso:country":"AU",
    "sg:address":"120 Kewdale Rd",
    "sg:city":"Kewdale",
    "sg:classifiers":[
        {
            "category":"Banks & Credit Unions",
            "subcategory":"Bureau De Change",
            "type":"Services"
        }
    ],
    "sg:phone":"+61 8 9353 1399",
    "sg:postcode":"6105",
    "sg:province":"WA",
    "sg:tags":[
        "wheel",
        "industrial"
    ],
    "wof:name":"Richmond Wheel & Castor Co",
    "wof:placetype":"venue"
},
  "geometry": {"coordinates":[115.953460693,-31.9853096008],"type":"Point"}
}