{
  "type": "Feature",
  "properties": {
    "addr:full":"8816 Princes Hwy Panmure VIC 3265",
    "addr:housenumber":"8816",
    "addr:postcode":"3265",
    "addr:street":"Princes Hwy",
    "iso:country":"AU",
    "sg:address":"8816 Princes Hwy",
    "sg:city":"Panmure",
    "sg:classifiers":[
        {
            "category":"Building & Trades",
            "subcategory":"Construction",
            "type":"Services"
        }
    ],
    "sg:phone":"+61 3 5567 6003",
    "sg:postcode":"3265",
    "sg:province":"VIC",
    "sg:tags":[
        "welding"
    ],
    "wof:name":"K-7 Welding",
    "wof:placetype":"venue"
},
  "geometry": {"coordinates":[142.72976684599999,-38.3341751099],"type":"Point"}
}