{
  "type": "Feature",
  "properties": {
    "addr:full":"84 Lake St Cairns QLD 4870",
    "addr:housenumber":"84",
    "addr:postcode":"4870",
    "addr:street":"Lake St",
    "iso:country":"AU",
    "sg:address":"84 Lake St",
    "sg:city":"Cairns",
    "sg:classifiers":[
        {
            "category":"Shopping",
            "subcategory":"Music",
            "type":"Retail Goods"
        }
    ],
    "sg:phone":"+61 7 4041 1318",
    "sg:postcode":"4870",
    "sg:province":"QLD",
    "sg:tags":[
        "store"
    ],
    "wof:name":"Sanity",
    "wof:placetype":"venue"
},
  "geometry": {"coordinates":[145.776687622,-16.9229202271],"type":"Point"}
}