{
  "type": "Feature",
  "properties": {
    "addr:full":"1/ 20 Peninsula Blv Seaford VIC 3198",
    "addr:housenumber":"/ 20",
    "addr:postcode":"3198",
    "addr:street":"Peninsula Blv",
    "iso:country":"AU",
    "sg:address":"1/ 20",
    "sg:city":"Peninsula Blv Seaford",
    "sg:classifiers":[
        {
            "category":"Home & Garden",
            "subcategory":"Furniture",
            "type":"Retail Goods"
        }
    ],
    "sg:phone":"+61 1300 732 418",
    "sg:postcode":"3198",
    "sg:province":"VIC",
    "sg:tags":[
        "business"
    ],
    "wof:name":"FCI",
    "wof:placetype":"venue"
},
  "geometry": {"coordinates":[145.138916016,-38.1146583557],"type":"Point"}
}