{
  "type": "Feature",
  "properties": {
    "iso:country":"AU",
    "sg:address":"4 Janelle Crt",
    "sg:city":"Andergrove",
    "sg:classifiers":[
        {
            "category":"Shopping",
            "subcategory":"Clothing, Apparel, & Fashions",
            "type":"Retail Goods"
        }
    ],
    "sg:phone":"+61 7 4955 5971",
    "sg:postcode":"4740",
    "sg:province":"QLD",
    "sg:tags":[
        "uniform"
    ],
    "wof:name":"Glenlizzy Stockers Of Hospitality Uniforms",
    "wof:placetype":"venue"
},
  "geometry": {"coordinates":[149.185104,-21.086803],"type":"Point"}
}