{
  "type": "Feature",
  "properties": {
    "iso:country":"AU",
    "sg:address":"Shop 3/ 105 Tangerine St",
    "sg:city":"Fairfield East",
    "sg:classifiers":[
        {
            "category":"Food & Beverages",
            "subcategory":"Bakery",
            "type":"Retail Goods"
        }
    ],
    "sg:phone":"+61 2 9727 9437",
    "sg:postcode":"2165",
    "sg:province":"NSW",
    "sg:tags":[
        "cake",
        "shop",
        "pastry"
    ],
    "wof:name":"El Molino",
    "wof:placetype":"venue"
},
  "geometry": {"coordinates":[150.968994141,-33.8762969971],"type":"Point"}
}