{
  "type": "Feature",
  "properties": {
    "iso:country":"AU",
    "sg:address":"Unit 9 / The Auto Centre, Cnr Reed St South & Scollay St",
    "sg:city":"Greenway",
    "sg:classifiers":[
        {
            "category":"Shopping",
            "subcategory":"Bicycles & Sporting Goods",
            "type":"Retail Goods"
        }
    ],
    "sg:phone":"+61 2 6293 2077",
    "sg:postcode":"2900",
    "sg:province":"ACT",
    "sg:tags":[
        "dance",
        "accessory",
        "wear",
        "supply"
    ],
    "wof:name":"Showtime Costumes",
    "wof:placetype":"venue"
},
  "geometry": {"coordinates":[149.06744384800001,-35.4175262451],"type":"Point"}
}