{
  "type": "Feature",
  "properties": {
    "addr:full":"150 Queens Rd South Guildford WA 6055",
    "addr:housenumber":"150",
    "addr:postcode":"6055",
    "addr:street":"Queens Rd",
    "iso:country":"AU",
    "sg:address":"150 Queens Rd",
    "sg:city":"South Guildford",
    "sg:classifiers":[
        {
            "category":"Sports & Exercise",
            "subcategory":"Sports Center",
            "type":"Entertainment"
        }
    ],
    "sg:phone":"+61 8 9377 1677",
    "sg:postcode":"6055",
    "sg:province":"WA",
    "sg:tags":[
        "ground"
    ],
    "wof:name":"Guildford Indoor Sports",
    "wof:placetype":"venue"
},
  "geometry": {"coordinates":[115.96856699999999,-31.907681],"type":"Point"}
}