{
  "type": "Feature",
  "properties": {
    "addr:full":"Unit 9/130- 142 Forrester Rd St Marys NSW 2760",
    "addr:housenumber":"/ 130 142",
    "addr:postcode":"2760",
    "addr:street":"Forrester Rd",
    "iso:country":"AU",
    "sg:address":"Unit 9/130- 142 Forrester Rd",
    "sg:city":"St Marys",
    "sg:classifiers":[
        {
            "category":"Retail",
            "subcategory":"Auto Repair",
            "type":"Services"
        }
    ],
    "sg:phone":"+61 2 9623 1233",
    "sg:postcode":"2760",
    "sg:province":"NSW",
    "sg:tags":[
        "clutch",
        "brake"
    ],
    "wof:name":"Western Clutch Service Pty Ltd",
    "wof:placetype":"venue"
},
  "geometry": {"coordinates":[150.775787353,-33.7544784546],"type":"Point"}
}