{
  "type": "Feature",
  "properties": {
    "iso:country":"AU",
    "sg:address":"335 Parramatta Rd",
    "sg:city":"Leichhardt",
    "sg:classifiers":[
        {
            "category":"Professional",
            "subcategory":"Employment Agencies",
            "type":"Services"
        }
    ],
    "sg:phone":"+61 2 9518 0166",
    "sg:postcode":"2040",
    "sg:province":"NSW",
    "wof:name":"Job Futures",
    "wof:placetype":"venue"
},
  "geometry": {"coordinates":[151.159729,-33.887699],"type":"Point"}
}