{
  "type": "Feature",
  "properties": {
    "addr:full":"Fcty 3/ 407 Old Geelong Rd Hoppers Crossing VIC 3029",
    "addr:housenumber":"/ 407",
    "addr:postcode":"3029",
    "addr:street":"Old Geelong Rd",
    "iso:country":"AU",
    "sg:address":"Fcty 3/ 407 Old Geelong Rd",
    "sg:city":"Hoppers Crossing",
    "sg:classifiers":[
        {
            "category":"Retail",
            "subcategory":"Auto Repair",
            "type":"Services"
        }
    ],
    "sg:phone":"+61 3 9931 0322",
    "sg:postcode":"3029",
    "sg:province":"VIC",
    "sg:tags":[
        "automotive",
        "air conditioning"
    ],
    "wof:name":"I C Cold",
    "wof:placetype":"venue"
},
  "geometry": {"coordinates":[144.73001099999999,-37.869267],"type":"Point"}
}