{
  "type": "Feature",
  "properties": {
    "iso:country":"AU",
    "sg:address":"Cnr Hawtins St & Porter St",
    "sg:city":"Templestowe",
    "sg:classifiers":[
        {
            "category":"Sports & Exercise",
            "subcategory":"Sports Center",
            "type":"Entertainment"
        }
    ],
    "sg:phone":"+61 3 9824 4434",
    "sg:postcode":"3106",
    "sg:province":"VIC",
    "sg:tags":[
        "coach",
        "tennis"
    ],
    "wof:name":"Tennis Works",
    "wof:placetype":"venue"
},
  "geometry": {"coordinates":[145.14796447800001,-37.7539672852],"type":"Point"}
}