{
  "type": "Feature",
  "properties": {
    "iso:country":"AU",
    "sg:address":"241 Cumberland Rd",
    "sg:city":"Auburn",
    "sg:classifiers":[
        {
            "category":"Building & Trades",
            "subcategory":"Construction",
            "type":"Services"
        }
    ],
    "sg:phone":"+61 418 404 565",
    "sg:postcode":"2144",
    "sg:province":"NSW",
    "sg:tags":[
        "contractor"
    ],
    "wof:name":"B & T Tannous Constructions",
    "wof:placetype":"venue"
},
  "geometry": {"coordinates":[151.02565002399999,-33.8502197266],"type":"Point"}
}