{
  "type": "Feature",
  "properties": {
    "iso:country":"AU",
    "sg:address":"524 Old Llandilo Rd",
    "sg:city":"Llandilo",
    "sg:classifiers":[
        {
            "category":"Retail",
            "subcategory":"Storage",
            "type":"Services"
        }
    ],
    "sg:phone":"+61 2 4777 4941",
    "sg:postcode":"2747",
    "sg:province":"NSW",
    "sg:tags":[
        "shelving",
        "system"
    ],
    "wof:name":"Decorative Built-In Wardrobes",
    "wof:placetype":"venue"
},
  "geometry": {"coordinates":[150.76145935100001,-33.6956558228],"type":"Point"}
}