{
  "type": "Feature",
  "properties": {
    "addr:full":"26 Princess St Kew VIC 3101",
    "addr:housenumber":"26",
    "addr:postcode":"3101",
    "addr:street":"Princess St",
    "iso:country":"AU",
    "sg:address":"26 Princess St",
    "sg:city":"Kew",
    "sg:classifiers":[
        {
            "category":"Food & Beverages",
            "subcategory":"Supermarket",
            "type":"Retail Goods"
        }
    ],
    "sg:phone":"+61 3 9853 8314",
    "sg:postcode":"3101",
    "sg:province":"VIC",
    "sg:tags":[
        "grocery",
        "store"
    ],
    "wof:name":"Leo's Fine Food & Wine",
    "wof:placetype":"venue"
},
  "geometry": {"coordinates":[145.02911376899999,-37.8061943054],"type":"Point"}
}