{
  "type": "Feature",
  "properties": {
    "addr:full":"70 North St Glenroy VIC 3046",
    "addr:housenumber":"70",
    "addr:postcode":"3046",
    "addr:street":"North St",
    "iso:country":"AU",
    "sg:address":"70 North St",
    "sg:city":"Glenroy",
    "sg:classifiers":[
        {
            "category":"Fast Food",
            "type":"Food & Drink"
        }
    ],
    "sg:phone":"+61 3 9357 3599",
    "sg:postcode":"3046",
    "sg:province":"VIC",
    "sg:tags":[
        "away",
        "take"
    ],
    "wof:name":"Northside Pizza",
    "wof:placetype":"venue"
},
  "geometry": {"coordinates":[144.94407653799999,-37.704864502],"type":"Point"}
}