{
  "type": "Feature",
  "properties": {
    "iso:country":"AU",
    "sg:address":"1097 Greenhill Rd",
    "sg:city":"Summertown",
    "sg:classifiers":[
        {
            "category":"Real Estate",
            "subcategory":"Real Estate Agent",
            "type":"Services"
        }
    ],
    "sg:phone":"+61 8 8390 3303",
    "sg:postcode":"5141",
    "sg:province":"SA",
    "wof:name":"Jones H Douglas Real Estate",
    "wof:placetype":"venue"
},
  "geometry": {"coordinates":[138.73402404800001,-34.9597091675],"type":"Point"}
}