{
  "type": "Feature",
  "properties": {
    "iso:country":"AU",
    "sg:address":"PO Box 1261",
    "sg:city":"Bibra Lake",
    "sg:classifiers":[
        {
            "category":"Home & Garden",
            "subcategory":"Building Materials",
            "type":"Retail Goods"
        }
    ],
    "sg:phone":"+61 407 995 305",
    "sg:postcode":"6163",
    "sg:province":"WA",
    "sg:tags":[
        "lawn",
        "cutting",
        "maintenance"
    ],
    "wof:name":"G & W Lawnmowing Services",
    "wof:placetype":"venue"
},
  "geometry": {"coordinates":[115.81240099999999,-32.08992],"type":"Point"}
}