{
  "type": "Feature",
  "properties": {
    "iso:country":"AU",
    "sg:address":"31 Logie St",
    "sg:city":"Oakleigh",
    "sg:classifiers":[
        {
            "category":"Building & Trades",
            "subcategory":"Landscaping Services",
            "type":"Services"
        }
    ],
    "sg:phone":"+61 3 9569 6548",
    "sg:postcode":"3166",
    "sg:province":"VIC",
    "sg:tags":[
        "designer",
        "landscape",
        "contractor"
    ],
    "wof:name":"Chapman K H",
    "wof:placetype":"venue"
},
  "geometry": {"coordinates":[145.09260559099999,-37.8947067261],"type":"Point"}
}