{
  "type": "Feature",
  "properties": {
    "addr:full":"16 Marwarra St Ringwood East VIC 3135",
    "addr:housenumber":"16",
    "addr:postcode":"3135",
    "addr:street":"Marwarra St",
    "iso:country":"AU",
    "sg:address":"16 Marwarra St",
    "sg:city":"Ringwood East",
    "sg:classifiers":[
        {
            "category":"Building & Trades",
            "subcategory":"Landscaping Services",
            "type":"Services"
        }
    ],
    "sg:phone":"+61 412 369 054",
    "sg:postcode":"3135",
    "sg:province":"VIC",
    "sg:tags":[
        "gardener"
    ],
    "wof:name":"Grandiflora Gardens",
    "wof:placetype":"venue"
},
  "geometry": {"coordinates":[145.24252319300001,-37.8160476685],"type":"Point"}
}