{
  "type": "Feature",
  "properties": {
    "iso:country":"AU",
    "sg:address":"272 Raymond St",
    "sg:city":"Sale",
    "sg:classifiers":[
        {
            "category":"Shopping",
            "subcategory":"Clothing, Apparel, & Fashions",
            "type":"Retail Goods"
        }
    ],
    "sg:phone":"+61 3 5143 1230",
    "sg:postcode":"3850",
    "sg:province":"VIC",
    "sg:tags":[
        "maternity",
        "wear"
    ],
    "wof:name":"Sale Bridal Boutique",
    "wof:placetype":"venue"
},
  "geometry": {"coordinates":[147.065750122,-38.1069908142],"type":"Point"}
}