{
  "type": "Feature",
  "properties": {
    "addr:full":"53 Mountview Pde Croydon VIC 3136",
    "addr:housenumber":"53",
    "addr:postcode":"3136",
    "addr:street":"Mountview Pde",
    "iso:country":"AU",
    "sg:address":"53 Mountview Pde",
    "sg:city":"Croydon",
    "sg:classifiers":[
        {
            "category":"Professional",
            "subcategory":"Accounting & Tax Preparation",
            "type":"Services"
        }
    ],
    "sg:phone":"+61 3 9727 1202",
    "sg:postcode":"3136",
    "sg:province":"VIC",
    "sg:tags":[
        "jukebox"
    ],
    "wof:name":"Jukebox Hire C/O",
    "wof:placetype":"venue"
},
  "geometry": {"coordinates":[145.305084228,-37.7855644226],"type":"Point"}
}