{
  "type": "Feature",
  "properties": {
    "addr:full":"Unit 2/ 35 Irvine Drv Malaga WA 6090",
    "addr:postcode":"6090",
    "addr:street":"Irvine Drv",
    "iso:country":"AU",
    "sg:address":"Unit 2/ 35 Irvine Drv",
    "sg:city":"Malaga",
    "sg:classifiers":[
        {
            "category":"Retail",
            "subcategory":"Auto Repair",
            "type":"Services"
        }
    ],
    "sg:phone":"+61 8 9249 2838",
    "sg:postcode":"6090",
    "sg:province":"WA",
    "sg:tags":[
        "repairer",
        "motor",
        "engineer"
    ],
    "wof:name":"Swan City Mobile Mechanic",
    "wof:placetype":"venue"
},
  "geometry": {"coordinates":[115.885063171,-31.8559436798],"type":"Point"}
}