{
  "type": "Feature",
  "properties": {
    "iso:country":"AU",
    "sg:address":"344 Fitzgerald St",
    "sg:city":"North Perth",
    "sg:classifiers":[
        {
            "category":"Shopping",
            "subcategory":"Crafts & Fabrics",
            "type":"Retail Goods"
        }
    ],
    "sg:phone":"+61 8 9228 3001",
    "sg:postcode":"6006",
    "sg:province":"WA",
    "sg:tags":[
        "supply"
    ],
    "wof:name":"Starfish Lane",
    "wof:placetype":"venue"
},
  "geometry": {"coordinates":[115.858543396,-31.9348869324],"type":"Point"}
}