{
  "type": "Feature",
  "properties": {
    "addr:full":"Shop 5/ 18 Coldstream St Yamba NSW 2464",
    "addr:housenumber":"shop 5 / 18",
    "addr:postcode":"2464",
    "addr:street":"Coldstream St",
    "iso:country":"AU",
    "sg:address":"Shop 5/ 18 Coldstream St",
    "sg:city":"Yamba",
    "sg:classifiers":[
        {
            "category":"Internet Cafe",
            "subcategory":"None",
            "type":"Food & Drink"
        }
    ],
    "sg:phone":"+61 2 6646 2392",
    "sg:postcode":"2464",
    "sg:province":"NSW",
    "wof:name":"Jibber. Net",
    "wof:placetype":"venue"
},
  "geometry": {"coordinates":[153.360473633,-29.437046051],"type":"Point"}
}