{
  "type": "Feature",
  "properties": {
    "iso:country":"AU",
    "sg:address":"Shop 117 Brookside Shpng Cntr 159 Osborne Rd",
    "sg:city":"Mitchelton",
    "sg:classifiers":[
        {
            "category":"Banks & Credit Unions",
            "subcategory":"Bureau De Change",
            "type":"Services"
        }
    ],
    "sg:phone":"+61 1800 637 642",
    "sg:postcode":"4053",
    "sg:province":"QLD",
    "sg:tags":[
        "currency",
        "exchange",
        "foreign"
    ],
    "wof:name":"Travelex",
    "wof:placetype":"venue"
},
  "geometry": {"coordinates":[152.97825622600001,-27.4067153931],"type":"Point"}
}