{
  "type": "Feature",
  "properties": {
    "addr:full":"26 Reynolds St Blackalls Park NSW 2283",
    "addr:housenumber":"26",
    "addr:postcode":"2283",
    "addr:street":"Reynolds St",
    "iso:country":"AU",
    "sg:address":"26 Reynolds St",
    "sg:city":"Blackalls Park",
    "sg:classifiers":[
        {
            "category":"Organizations",
            "subcategory":"Professional Association",
            "type":"Services"
        }
    ],
    "sg:phone":"+61 2 4959 7741",
    "sg:postcode":"2283",
    "sg:province":"NSW",
    "sg:tags":[
        "web",
        "internet"
    ],
    "wof:name":"Platypus Websites Pty Ltd",
    "wof:placetype":"venue"
},
  "geometry": {"coordinates":[151.58102417000001,-32.9941329956],"type":"Point"}
}