{
  "type": "Feature",
  "properties": {
    "addr:full":"U3/ 8 Tombo St Capalaba QLD 4157",
    "addr:housenumber":"8",
    "addr:postcode":"4157",
    "addr:street":"U3 /;Tombo St",
    "iso:country":"AU",
    "sg:address":"U3/ 8 Tombo St",
    "sg:city":"Capalaba",
    "sg:classifiers":[
        {
            "category":"Home & Garden",
            "subcategory":"Carpets & Floor Coverings",
            "type":"Retail Goods"
        }
    ],
    "sg:phone":"+61 7 3823 3900",
    "sg:postcode":"4157",
    "sg:province":"QLD",
    "sg:tags":[
        "tile",
        "wall"
    ],
    "wof:name":"Designers Architects Building Supplies",
    "wof:placetype":"venue"
},
  "geometry": {"coordinates":[153.21090698200001,-27.5379695892],"type":"Point"}
}