{
  "type": "Feature",
  "properties": {
    "iso:country":"AU",
    "sg:address":"25 Hamilton St",
    "sg:city":"Subiaco",
    "sg:classifiers":[
        {
            "category":"Health Services",
            "subcategory":"Doctor",
            "type":"Services"
        }
    ],
    "sg:phone":"+61 8 9381 7965",
    "sg:postcode":"6008",
    "sg:province":"WA",
    "sg:tags":[
        "medical",
        "practitioner"
    ],
    "wof:name":"Vercoe Jack",
    "wof:placetype":"venue"
},
  "geometry": {"coordinates":[115.835571289,-31.9469509125],"type":"Point"}
}