{
  "type": "Feature",
  "properties": {
    "addr:full":"Chandler Hwy Kew VIC 3101",
    "addr:postcode":"3101",
    "addr:street":"Chandler Hwy",
    "iso:country":"AU",
    "sg:address":"Chandler Hwy",
    "sg:city":"Kew",
    "sg:classifiers":[
        {
            "category":"Social Services",
            "subcategory":"Adult Care",
            "type":"Services"
        }
    ],
    "sg:phone":"+61 3 9854 4444",
    "sg:postcode":"3101",
    "sg:province":"VIC",
    "sg:tags":[
        "disadvantaged",
        "aid",
        "organisation",
        "group"
    ],
    "wof:name":"Guide Dogs Victoria",
    "wof:placetype":"venue"
},
  "geometry": {"coordinates":[145.03089904800001,-37.7926521301],"type":"Point"}
}