{
  "type": "Feature",
  "properties": {
    "addr:full":"55 Brisbane St Drayton QLD 4350",
    "addr:housenumber":"55",
    "addr:postcode":"4350",
    "addr:street":"Brisbane St",
    "iso:country":"AU",
    "sg:address":"55 Brisbane St",
    "sg:city":"Drayton",
    "sg:classifiers":[
        {
            "category":"Education",
            "subcategory":"School",
            "type":"Public Place"
        }
    ],
    "sg:phone":"+61 7 4637 7444",
    "sg:postcode":"4350",
    "sg:province":"QLD",
    "sg:tags":[
        "state",
        "except",
        "nsw"
    ],
    "wof:name":"Drayton Primary",
    "wof:placetype":"venue"
},
  "geometry": {"coordinates":[151.912735,-27.602438],"type":"Point"}
}