{
  "type": "Feature",
  "properties": {
    "iso:country":"AU",
    "sg:address":"MP12 Market City 280 Bannister Rd",
    "sg:city":"Canning Vale",
    "sg:classifiers":[
        {
            "category":"Food & Beverages",
            "subcategory":"Fruits & Vegetables",
            "type":"Retail Goods"
        }
    ],
    "sg:phone":"+61 8 9455 2457",
    "sg:postcode":"6155",
    "sg:province":"WA",
    "sg:tags":[
        "wholesale"
    ],
    "wof:name":"Etherington",
    "wof:placetype":"venue"
},
  "geometry": {"coordinates":[115.895592,-32.070065],"type":"Point"}
}