{
  "type": "Feature",
  "properties": {
    "addr:full":"21 Newland St Alice Springs NT 0870",
    "addr:housenumber":"21",
    "addr:postcode":"nt 0870",
    "addr:street":"Newland St",
    "iso:country":"AU",
    "sg:address":"21 Newland St",
    "sg:city":"Alice Springs",
    "sg:classifiers":[
        {
            "category":"Personal",
            "type":"Services"
        }
    ],
    "sg:phone":"+61 8 8952 5899",
    "sg:postcode":"0870",
    "sg:province":"NT",
    "sg:tags":[
        "counselling",
        "alcohol",
        "drug"
    ],
    "wof:name":"Holyoake Alice Springs Inc.",
    "wof:placetype":"venue"
},
  "geometry": {"coordinates":[133.870727539,-23.708366394],"type":"Point"}
}