{
  "type": "Feature",
  "properties": {
    "addr:full":"23 Sargent St New Farm QLD 4005",
    "addr:housenumber":"23",
    "addr:postcode":"4005",
    "addr:street":"Sargent St",
    "iso:country":"AU",
    "sg:address":"23 Sargent St",
    "sg:city":"New Farm",
    "sg:classifiers":[
        {
            "category":"Professional",
            "subcategory":"Employment Agencies",
            "type":"Services"
        }
    ],
    "sg:phone":"+61 7 3254 2722",
    "sg:postcode":"4005",
    "sg:province":"QLD",
    "sg:tags":[
        "occupational",
        "therapist"
    ],
    "wof:name":"Mitchell Carmen",
    "wof:placetype":"venue"
},
  "geometry": {"coordinates":[153.04530334500001,-27.4737606049],"type":"Point"}
}