{
  "type": "Feature",
  "properties": {
    "iso:country":"AU",
    "sg:address":"Cnr Mt Gravatt/Capalaba Rd & Tryon St",
    "sg:city":"Upper Mt Gravatt",
    "sg:classifiers":[
        {
            "category":"Autos & Motor Vehicles",
            "subcategory":"Automobile Sales",
            "type":"Retail Goods"
        }
    ],
    "sg:phone":"+61 7 3347 9988",
    "sg:postcode":"4122",
    "sg:province":"QLD",
    "sg:tags":[
        "car",
        "used"
    ],
    "wof:name":"Bryan Byrt Used Cars",
    "wof:placetype":"venue"
},
  "geometry": {"coordinates":[153.09034729000001,-27.5556697845],"type":"Point"}
}