{
  "type": "Feature",
  "properties": {
    "iso:country":"AU",
    "sg:address":"PO Box 119",
    "sg:city":"Hove",
    "sg:classifiers":[
        {
            "category":"Professional",
            "subcategory":"Management & Consulting",
            "type":"Services"
        }
    ],
    "sg:phone":"+61 438 788 045",
    "sg:postcode":"5048",
    "sg:province":"SA",
    "sg:tags":[
        "consultant"
    ],
    "wof:name":"Zenith Consulting",
    "wof:placetype":"venue"
},
  "geometry": {"coordinates":[138.52238500000001,-35.00964],"type":"Point"}
}