{
  "type": "Feature",
  "properties": {
    "iso:country":"AU",
    "sg:address":"69 B Fitzgerald St",
    "sg:city":"Portland",
    "sg:classifiers":[
        {
            "category":"Sports & Exercise",
            "subcategory":"Playing Field",
            "type":"Entertainment"
        }
    ],
    "sg:phone":"+61 3 5523 6660",
    "sg:postcode":"3305",
    "sg:province":"VIC",
    "sg:tags":[
        "net",
        "fishing"
    ],
    "wof:name":"Network T.N.",
    "wof:placetype":"venue"
},
  "geometry": {"coordinates":[141.58982849099999,-38.3399734497],"type":"Point"}
}