{
  "type": "Feature",
  "properties": {
    "addr:full":"783 Military Rd Mosman NSW 2088",
    "addr:housenumber":"783",
    "addr:postcode":"2088",
    "addr:street":"Military Rd",
    "iso:country":"AU",
    "sg:address":"783 Military Rd",
    "sg:city":"Mosman",
    "sg:classifiers":[
        {
            "category":"Food & Beverages",
            "subcategory":"Bakery",
            "type":"Retail Goods"
        }
    ],
    "sg:phone":"+61 2 9969 2071",
    "sg:postcode":"2088",
    "sg:province":"NSW",
    "sg:tags":[
        "baker"
    ],
    "wof:name":"mmmm ! The Homestyle Bakery",
    "wof:placetype":"venue"
},
  "geometry": {"coordinates":[151.244049072,-33.8304634094],"type":"Point"}
}