{
  "type": "Feature",
  "properties": {
    "iso:country":"AU",
    "sg:address":"131 Crane St",
    "sg:city":"Longreach",
    "sg:classifiers":[
        {
            "category":"Retail",
            "subcategory":"Repair Shop",
            "type":"Services"
        }
    ],
    "sg:phone":"+61 7 4658 3553",
    "sg:postcode":"4730",
    "sg:province":"QLD",
    "sg:tags":[
        "upholsterer"
    ],
    "wof:name":"Tassies Upholstery",
    "wof:placetype":"venue"
},
  "geometry": {"coordinates":[144.249481,-23.446033],"type":"Point"}
}