{
  "type": "Feature",
  "properties": {
    "iso:country":"AU",
    "sg:address":"PO Box 370",
    "sg:city":"Fremantle",
    "sg:classifiers":[
        {
            "category":"Recreation",
            "subcategory":"Boat Charter",
            "type":"Entertainment"
        }
    ],
    "sg:phone":"+61 418 904 610",
    "sg:postcode":"6160",
    "sg:province":"WA",
    "wof:name":"MV Reel Thing Charters",
    "wof:placetype":"venue"
},
  "geometry": {"coordinates":[115.75592,-32.05257],"type":"Point"}
}