{
  "type": "Feature",
  "properties": {
    "addr:full":"Russell Rd Mt Thorley NSW 2330",
    "addr:postcode":"2330",
    "addr:street":"Russell Rd",
    "iso:country":"AU",
    "sg:address":"Russell Rd",
    "sg:city":"Mt Thorley",
    "sg:classifiers":[
        {
            "category":"Autos & Motor Vehicles",
            "subcategory":"Auto Supplies",
            "type":"Retail Goods"
        }
    ],
    "sg:phone":"+61 2 6574 6552",
    "sg:postcode":"2330",
    "sg:province":"NSW",
    "sg:tags":[
        "tyre"
    ],
    "wof:name":"Marathon Tyres",
    "wof:placetype":"venue"
},
  "geometry": {"coordinates":[151.103195,-32.62524],"type":"Point"}
}