{
  "type": "Feature",
  "properties": {
    "iso:country":"AU",
    "sg:address":"585 Grand Junction Rd",
    "sg:city":"Gepps Cross",
    "sg:classifiers":[
        {
            "category":"Manufacturing",
            "subcategory":"Paper Products",
            "type":"Manufacturing & Wholesale Goods"
        }
    ],
    "sg:phone":"+61 8 8349 4133",
    "sg:postcode":"5094",
    "sg:province":"SA",
    "sg:tags":[
        "metal",
        "non-ferrous",
        "foundry"
    ],
    "wof:name":"McKechnie Iron Foundry P/L",
    "wof:placetype":"venue"
},
  "geometry": {"coordinates":[138.59283447300001,-34.8482894897],"type":"Point"}
}