{
  "type": "Feature",
  "properties": {
    "addr:full":"17 Wellington St St Kilda VIC 3182",
    "addr:housenumber":"17",
    "addr:postcode":"3182",
    "addr:street":"Wellington St",
    "iso:country":"AU",
    "sg:address":"17 Wellington St St",
    "sg:city":"Kilda",
    "sg:classifiers":[
        {
            "category":"Shopping",
            "type":"Retail Goods"
        }
    ],
    "sg:phone":"+61 3 9510 9999",
    "sg:postcode":"3182",
    "sg:province":"VIC",
    "sg:tags":[
        "equipment",
        "safety",
        "accessory"
    ],
    "wof:name":"Pitstop Shop",
    "wof:placetype":"venue"
},
  "geometry": {"coordinates":[144.98402404800001,-37.8562164307],"type":"Point"}
}