{
  "type": "Feature",
  "properties": {
    "iso:country":"AU",
    "sg:address":"117 Drummond St",
    "sg:city":"Carlton",
    "sg:classifiers":[
        {
            "category":"Banks & Credit Unions",
            "subcategory":"Investment Brokerage",
            "type":"Services"
        }
    ],
    "sg:phone":"+61 3 9664 8383",
    "sg:postcode":"3053",
    "sg:province":"VIC",
    "wof:name":"Cinnabar Equities Pty Ltd",
    "wof:placetype":"venue"
},
  "geometry": {"coordinates":[144.96771240199999,-37.8039207458],"type":"Point"}
}