{
  "type": "Feature",
  "properties": {
    "iso:country":"AU",
    "sg:address":"1/ 144 Mann St",
    "sg:city":"Gosford",
    "sg:classifiers":[
        {
            "category":"Shopping",
            "subcategory":"Clothing, Apparel, & Fashions",
            "type":"Retail Goods"
        }
    ],
    "sg:phone":"+61 2 4323 2830",
    "sg:postcode":"2250",
    "sg:province":"NSW",
    "sg:tags":[
        "hire",
        "men's",
        "wear",
        "formal"
    ],
    "wof:name":"Diamond Weddings",
    "wof:placetype":"venue"
},
  "geometry": {"coordinates":[151.34193420400001,-33.4258270264],"type":"Point"}
}