{
  "type": "Feature",
  "properties": {
    "addr:full":"3 Dillon St Bendigo VIC 3550",
    "addr:housenumber":"3",
    "addr:postcode":"3550",
    "addr:street":"Dillon St",
    "iso:country":"AU",
    "sg:address":"3 Dillon St",
    "sg:city":"Bendigo",
    "sg:classifiers":[
        {
            "category":"Utilities",
            "type":"Services"
        }
    ],
    "sg:phone":"+61 3 5444 4205",
    "sg:postcode":"3550",
    "sg:province":"VIC",
    "sg:tags":[
        "refrigeration",
        "industrial",
        "commercial",
        "retail"
    ],
    "wof:name":"Des The Fridgeman",
    "wof:placetype":"venue"
},
  "geometry": {"coordinates":[144.26272582999999,-36.744972229],"type":"Point"}
}