{
  "type": "Feature",
  "properties": {
    "iso:country":"AU",
    "sg:address":"200 Mona Vale Rd St",
    "sg:city":"Ives",
    "sg:classifiers":[
        {
            "category":"Food & Beverages",
            "subcategory":"Liquor & Beverages",
            "type":"Retail Goods"
        }
    ],
    "sg:phone":"+61 2 9449 3566",
    "sg:postcode":"2075",
    "sg:province":"NSW",
    "sg:tags":[
        "store"
    ],
    "wof:name":"Liquorland",
    "wof:placetype":"venue"
},
  "geometry": {"coordinates":[151.16099548299999,-33.7298164368],"type":"Point"}
}