{
  "type": "Feature",
  "properties": {
    "addr:full":"Heron Cove Marina, End of Queens Pde (West) Newport NSW 2106",
    "addr:postcode":"2106",
    "addr:street":"Heron;Pde West",
    "iso:country":"AU",
    "sg:address":"Heron Cove Marina, End of Queens Pde (West)",
    "sg:city":"Newport",
    "sg:classifiers":[
        {
            "category":"Building & Trades",
            "subcategory":"Construction",
            "type":"Services"
        }
    ],
    "sg:phone":"+61 419 494 703",
    "sg:postcode":"2106",
    "sg:province":"NSW",
    "sg:tags":[
        "welding"
    ],
    "wof:name":"Revival Welding",
    "wof:placetype":"venue"
},
  "geometry": {"coordinates":[151.31622314399999,-33.6598625183],"type":"Point"}
}