{
  "type": "Feature",
  "properties": {
    "addr:full":"615 Nicholson St Carlton North VIC 3054",
    "addr:housenumber":"615",
    "addr:postcode":"3054",
    "addr:street":"Nicholson St",
    "iso:country":"AU",
    "sg:address":"615 Nicholson St",
    "sg:city":"Carlton North",
    "sg:classifiers":[
        {
            "category":"Communications",
            "subcategory":"Film & Video Production",
            "type":"Services"
        }
    ],
    "sg:phone":"+61 3 9388 1788",
    "sg:postcode":"3054",
    "sg:province":"VIC",
    "sg:tags":[
        "dvd",
        "library"
    ],
    "wof:name":"Video Ezy",
    "wof:placetype":"venue"
},
  "geometry": {"coordinates":[144.977005005,-37.7848434448],"type":"Point"}
}