{
  "type": "Feature",
  "properties": {
    "iso:country":"AU",
    "sg:address":"7 Torver Pl",
    "sg:city":"Wheeler Heights",
    "sg:classifiers":[
        {
            "category":"Professional",
            "subcategory":"Art Services",
            "type":"Services"
        }
    ],
    "sg:phone":"+61 2 9981 5380",
    "sg:postcode":"2097",
    "sg:province":"NSW",
    "sg:tags":[
        "artist"
    ],
    "wof:name":"Sykes Paul H",
    "wof:placetype":"venue"
},
  "geometry": {"coordinates":[151.27804565400001,-33.7270889282],"type":"Point"}
}