{
  "type": "Feature",
  "properties": {
    "iso:country":"AU",
    "sg:address":"205 Gosford Rd",
    "sg:city":"Adamstown",
    "sg:classifiers":[
        {
            "category":"Transit Center",
            "subcategory":"Freight",
            "type":"Transportation"
        }
    ],
    "sg:phone":"+61 2 4956 3020",
    "sg:postcode":"2289",
    "sg:province":"NSW",
    "sg:tags":[
        "agent",
        "shipping"
    ],
    "wof:name":"Schenker Australia Pty Ltd",
    "wof:placetype":"venue"
},
  "geometry": {"coordinates":[151.72743225100001,-32.9338417053],"type":"Point"}
}