{
  "type": "Feature",
  "properties": {
    "addr:full":"12 Lincoln St Largs Bay SA 5016",
    "addr:housenumber":"12",
    "addr:postcode":"5016",
    "addr:street":"Lincoln St",
    "iso:country":"AU",
    "sg:address":"12 Lincoln St",
    "sg:city":"Largs Bay",
    "sg:classifiers":[
        {
            "category":"Education",
            "subcategory":"Music School",
            "type":"Public Place"
        }
    ],
    "sg:phone":"+61 8 8449 9195",
    "sg:postcode":"5016",
    "sg:province":"SA",
    "sg:tags":[
        "choir",
        "bands",
        "orchestra"
    ],
    "wof:name":"Port Adelaide City Band Inc.",
    "wof:placetype":"venue"
},
  "geometry": {"coordinates":[138.494430542,-34.8258476257],"type":"Point"}
}