{
  "type": "Feature",
  "properties": {
    "addr:full":"208 Princes Hwy Arncliffe NSW 2205",
    "addr:housenumber":"208",
    "addr:postcode":"2205",
    "addr:street":"Princes Hwy",
    "iso:country":"AU",
    "sg:address":"208 Princes Hwy",
    "sg:city":"Arncliffe",
    "sg:classifiers":[
        {
            "category":"Home & Garden",
            "subcategory":"Carpets & Floor Coverings",
            "type":"Retail Goods"
        }
    ],
    "sg:phone":"+61 2 9597 2000",
    "sg:postcode":"2205",
    "sg:province":"NSW",
    "sg:tags":[
        "tile",
        "wall"
    ],
    "wof:name":"A1 Stone and Ceramics",
    "wof:placetype":"venue"
},
  "geometry": {"coordinates":[151.14503500000001,-33.941833],"type":"Point"}
}