{
  "type": "Feature",
  "properties": {
    "addr:full":"1 McArthurs Rd Altona North VIC 3025",
    "addr:housenumber":"1",
    "addr:postcode":"3025",
    "addr:street":"Mcarthurs Rd",
    "iso:country":"AU",
    "sg:address":"1 McArthurs Rd",
    "sg:city":"Altona North",
    "sg:classifiers":[
        {
            "category":"Education",
            "subcategory":"Dance Studio",
            "type":"Public Place"
        }
    ],
    "sg:phone":"+61 3 9689 1166",
    "sg:postcode":"3025",
    "sg:province":"VIC",
    "sg:tags":[
        "instruction",
        "language"
    ],
    "wof:name":"Victorian School of Languages",
    "wof:placetype":"venue"
},
  "geometry": {"coordinates":[144.84498600000001,-37.835659],"type":"Point"}
}