{
  "type": "Feature",
  "properties": {
    "addr:full":"Church St Bega NSW 2550",
    "addr:postcode":"2550",
    "addr:street":"Church St",
    "iso:country":"AU",
    "sg:address":"Church St",
    "sg:city":"Bega",
    "sg:classifiers":[
        {
            "category":"Health Services",
            "subcategory":"Health Practitioner",
            "type":"Services"
        }
    ],
    "sg:phone":"+61 2 6492 1239",
    "sg:postcode":"2550",
    "sg:province":"NSW",
    "sg:tags":[
        "osteopath"
    ],
    "wof:name":"Bega Osteopathic Clinic",
    "wof:placetype":"venue"
},
  "geometry": {"coordinates":[149.842071533,-36.6737632751],"type":"Point"}
}