{
  "type": "Feature",
  "properties": {
    "iso:country":"AU",
    "sg:address":"2/ 160 Anzac Pde",
    "sg:city":"Kensington",
    "sg:classifiers":[
        {
            "category":"Shopping",
            "subcategory":"Mobile Phones",
            "type":"Retail Goods"
        }
    ],
    "sg:phone":"+61 2 9662 7599",
    "sg:postcode":"2033",
    "sg:province":"NSW",
    "sg:tags":[
        "telephone",
        "accessory"
    ],
    "wof:name":"Mansour",
    "wof:placetype":"venue"
},
  "geometry": {"coordinates":[151.223694,-33.909046],"type":"Point"}
}