{
  "type": "Feature",
  "properties": {
    "iso:country":"AU",
    "sg:address":"210 Armstrong St",
    "sg:city":"(South) Ballarat",
    "sg:classifiers":[
        {
            "category":"Home & Garden",
            "subcategory":"Hardware",
            "type":"Retail Goods"
        }
    ],
    "sg:phone":"+61 3 5331 5811",
    "sg:postcode":"3350",
    "sg:province":"VIC",
    "sg:tags":[
        "repair",
        "tool",
        "power"
    ],
    "wof:name":"Des Elliott Pty Ltd",
    "wof:placetype":"venue"
},
  "geometry": {"coordinates":[143.855179,-37.566818],"type":"Point"}
}