{
  "type": "Feature",
  "properties": {
    "iso:country":"AU",
    "sg:address":"626 Greenwith Rd",
    "sg:city":"Golden Grove",
    "sg:classifiers":[
        {
            "category":"Retail",
            "subcategory":"Auto Repair",
            "type":"Services"
        }
    ],
    "sg:phone":"+61 8 8289 1053",
    "sg:postcode":"5125",
    "sg:province":"SA",
    "sg:tags":[
        "repairer",
        "motor",
        "engineer"
    ],
    "wof:name":"Grove Auto Repairs",
    "wof:placetype":"venue"
},
  "geometry": {"coordinates":[138.73272700000001,-34.791206],"type":"Point"}
}