{
  "type": "Feature",
  "properties": {
    "addr:full":"332 Relbia Rd Relbia TAS 7258",
    "addr:housenumber":"332",
    "addr:postcode":"7258",
    "addr:street":"Relbia Rd",
    "iso:country":"AU",
    "sg:address":"332 Relbia Rd",
    "sg:city":"Relbia",
    "sg:classifiers":[
        {
            "category":"Building & Trades",
            "subcategory":"Construction",
            "type":"Services"
        }
    ],
    "sg:phone":"+61 3 6344 8336",
    "sg:postcode":"7258",
    "sg:province":"TAS",
    "sg:tags":[
        "contractor"
    ],
    "wof:name":"Anderson G J & D",
    "wof:placetype":"venue"
},
  "geometry": {"coordinates":[147.20039367699999,-41.5043296814],"type":"Point"}
}