{
  "type": "Feature",
  "properties": {
    "iso:country":"AU",
    "sg:address":"94 Cranhaven Rd",
    "sg:city":"Langwarrin",
    "sg:classifiers":[
        {
            "category":"Utilities",
            "subcategory":"Water",
            "type":"Services"
        }
    ],
    "sg:phone":"+61 411 408 785",
    "sg:postcode":"3910",
    "sg:province":"VIC",
    "sg:tags":[
        "equipment",
        "treatment"
    ],
    "wof:name":"Tower Blaster Pty Ltd",
    "wof:placetype":"venue"
},
  "geometry": {"coordinates":[145.187988281,-38.1587333679],"type":"Point"}
}