{
  "type": "Feature",
  "properties": {
    "addr:full":"13 Nowill St Condell Park NSW 2200",
    "addr:housenumber":"13",
    "addr:postcode":"2200",
    "addr:street":"Nowill St",
    "iso:country":"AU",
    "sg:address":"13 Nowill St",
    "sg:city":"Condell Park",
    "sg:classifiers":[
        {
            "category":"Professional",
            "type":"Services"
        }
    ],
    "sg:phone":"+61 2 9793 9855",
    "sg:postcode":"2200",
    "sg:province":"NSW",
    "sg:tags":[
        "packaging",
        "filling",
        "assembling"
    ],
    "wof:name":"Micris Packaging",
    "wof:placetype":"venue"
},
  "geometry": {"coordinates":[151.01391599999999,-33.930218],"type":"Point"}
}