{
  "type": "Feature",
  "properties": {
    "iso:country":"AU",
    "sg:address":"406 Stuart Hwy",
    "sg:city":"Winnellie",
    "sg:classifiers":[
        {
            "category":"Communications",
            "type":"Services"
        }
    ],
    "sg:phone":"+61 8 8984 4490",
    "sg:postcode":"0820",
    "sg:province":"NT",
    "sg:tags":[
        "equipment",
        "satellite"
    ],
    "wof:name":"Homesat T.V. Australia",
    "wof:placetype":"venue"
},
  "geometry": {"coordinates":[130.87510681099999,-12.4254360199],"type":"Point"}
}