{
  "type": "Feature",
  "properties": {
    "iso:country":"AU",
    "sg:address":"208- 218 Williamson Rd",
    "sg:city":"Tamborine Village",
    "sg:classifiers":[
        {
            "category":"Manufacturing",
            "subcategory":"Pottery",
            "type":"Manufacturing & Wholesale Goods"
        }
    ],
    "sg:phone":"+61 7 5543 6161",
    "sg:postcode":"4270",
    "sg:province":"QLD",
    "wof:name":"Vaschalde J J & N",
    "wof:placetype":"venue"
},
  "geometry": {"coordinates":[153.09082031200001,-27.8377857208],"type":"Point"}
}