{
  "type": "Feature",
  "properties": {
    "iso:country":"AU",
    "sg:address":"2/ 39",
    "sg:city":"East Esp Manly",
    "sg:classifiers":[
        {
            "category":"Real Estate",
            "subcategory":"Real Estate Agent",
            "type":"Services"
        }
    ],
    "sg:phone":"+61 2 9976 3252",
    "sg:postcode":"2095",
    "sg:province":"NSW",
    "wof:name":"Hooker L J Manly Real Estate Agents & Auctioneers",
    "wof:placetype":"venue"
},
  "geometry": {"coordinates":[151.28582763700001,-33.799911499],"type":"Point"}
}