{
  "type": "Feature",
  "properties": {
    "iso:country":"AU",
    "sg:address":"63 Henderson St",
    "sg:city":"Turrella",
    "sg:classifiers":[
        {
            "category":"Professional",
            "subcategory":"Management & Consulting",
            "type":"Services"
        }
    ],
    "sg:phone":"+61 2 9599 4922",
    "sg:postcode":"2205",
    "sg:province":"NSW",
    "sg:tags":[
        "consultant"
    ],
    "wof:name":"Decision Makers Australia Pty Ltd",
    "wof:placetype":"venue"
},
  "geometry": {"coordinates":[151.142975,-33.928574],"type":"Point"}
}