{
  "type": "Feature",
  "properties": {
    "iso:country":"AU",
    "sg:address":"10 Winten St",
    "sg:city":"Glendenning",
    "sg:classifiers":[
        {
            "category":"Building & Trades",
            "subcategory":"Plumbing",
            "type":"Services"
        }
    ],
    "sg:phone":"+61 2 9677 0700",
    "sg:postcode":"2761",
    "sg:province":"NSW",
    "sg:tags":[
        "plumber",
        "gasfitters"
    ],
    "wof:name":"Bolwarra Plumbing Services",
    "wof:placetype":"venue"
},
  "geometry": {"coordinates":[150.854935,-33.74456],"type":"Point"}
}