{
  "type": "Feature",
  "properties": {
    "iso:country":"AU",
    "sg:address":"Unit 4, 481 Main Rd",
    "sg:city":"Montrose",
    "sg:classifiers":[
        {
            "category":"Communications",
            "subcategory":"News Services",
            "type":"Services"
        }
    ],
    "sg:phone":"+61 3 6274 1266",
    "sg:postcode":"7010",
    "sg:province":"TAS",
    "sg:tags":[
        "information",
        "tourist",
        "attractions"
    ],
    "wof:name":"Poster Impact",
    "wof:placetype":"venue"
},
  "geometry": {"coordinates":[147.2684021,-42.8285102844],"type":"Point"}
}