{
  "type": "Feature",
  "properties": {
    "addr:full":"5 O'Connor St Haberfield NSW 2045",
    "addr:housenumber":"5",
    "addr:postcode":"2045",
    "addr:street":"O'Connor St",
    "iso:country":"AU",
    "sg:address":"5 O'Connor St",
    "sg:city":"Haberfield",
    "sg:classifiers":[
        {
            "category":"Professional",
            "subcategory":"Computer Services",
            "type":"Services"
        }
    ],
    "sg:phone":"+61 2 9716 0011",
    "sg:postcode":"2045",
    "sg:province":"NSW",
    "sg:tags":[
        "consultant",
        "system"
    ],
    "wof:name":"Innovative Information Management",
    "wof:placetype":"venue"
},
  "geometry": {"coordinates":[151.14181500000001,-33.881653],"type":"Point"}
}