{
  "type": "Feature",
  "properties": {
    "addr:full":"30 William St Muswellbrook NSW 2333",
    "addr:housenumber":"30",
    "addr:postcode":"2333",
    "addr:street":"William St",
    "iso:country":"AU",
    "sg:address":"30 William St",
    "sg:city":"Muswellbrook",
    "sg:classifiers":[
        {
            "category":"Travel",
            "subcategory":"Hotels & Motels",
            "type":"Entertainment"
        }
    ],
    "sg:phone":"+61 2 6543 1613",
    "sg:postcode":"2333",
    "sg:province":"NSW",
    "sg:tags":[
        "accommodation"
    ],
    "wof:name":"Shamrock Hotel",
    "wof:placetype":"venue"
},
  "geometry": {"coordinates":[150.88984680199999,-32.265411377],"type":"Point"}
}