{
  "type": "Feature",
  "properties": {
    "addr:full":"75 Galoola Drv Nelson Bay NSW 2315",
    "addr:housenumber":"75",
    "addr:postcode":"2315",
    "addr:street":"Galoola Drv",
    "iso:country":"AU",
    "sg:address":"75 Galoola Drv",
    "sg:city":"Nelson Bay",
    "sg:classifiers":[
        {
            "category":"Professional",
            "subcategory":"Art Services",
            "type":"Services"
        }
    ],
    "sg:phone":"+61 2 4981 2723",
    "sg:postcode":"2315",
    "sg:province":"NSW",
    "sg:tags":[
        "decorator",
        "painter"
    ],
    "wof:name":"Tony Cooper",
    "wof:placetype":"venue"
},
  "geometry": {"coordinates":[152.13194300000001,-32.724983],"type":"Point"}
}