{
  "type": "Feature",
  "properties": {
    "iso:country":"AU",
    "sg:address":"PO Box 1139",
    "sg:city":"Atherton",
    "sg:classifiers":[
        {
            "category":"Health Services",
            "subcategory":"Health Practitioner",
            "type":"Services"
        }
    ],
    "sg:phone":"+61 7 4096 3181",
    "sg:postcode":"4883",
    "sg:province":"QLD",
    "sg:tags":[
        "homoeopath"
    ],
    "wof:name":"Beckert Henny",
    "wof:placetype":"venue"
},
  "geometry": {"coordinates":[145.474975586,-17.2683391571],"type":"Point"}
}