{
  "type": "Feature",
  "properties": {
    "addr:full":"Unit 34/ 41-49 Norcar Rd Nunawading VIC 3131",
    "addr:housenumber":"/ 41-49",
    "addr:postcode":"3131",
    "addr:street":"Norcar Rd",
    "iso:country":"AU",
    "sg:address":"Unit 34/ 41-49 Norcar Rd",
    "sg:city":"Nunawading",
    "sg:classifiers":[
        {
            "category":"Home & Garden",
            "subcategory":"Household Appliances",
            "type":"Retail Goods"
        }
    ],
    "sg:phone":"+61 3 9873 7920",
    "sg:postcode":"3131",
    "sg:province":"VIC",
    "sg:tags":[
        "range",
        "hood"
    ],
    "wof:name":"Pacific Range Hood Pty Ltd",
    "wof:placetype":"venue"
},
  "geometry": {"coordinates":[145.18138122600001,-37.8227958679],"type":"Point"}
}