{
  "type": "Feature",
  "properties": {
    "addr:full":"1 Watt Rd Mornington VIC 3931",
    "addr:housenumber":"1",
    "addr:postcode":"3931",
    "addr:street":"Watt Rd",
    "iso:country":"AU",
    "sg:address":"1 Watt Rd",
    "sg:city":"Mornington",
    "sg:classifiers":[
        {
            "category":"Recreation",
            "subcategory":"Amusement Park",
            "type":"Entertainment"
        }
    ],
    "sg:phone":"+61 3 5975 2080",
    "sg:postcode":"3931",
    "sg:province":"VIC",
    "wof:name":"Kids Ahoy",
    "wof:placetype":"venue"
},
  "geometry": {"coordinates":[145.06544494600001,-38.2344551086],"type":"Point"}
}