{
  "type": "Feature",
  "properties": {
    "addr:full":"U8/ 44 Buckingham Drv Wangara WA 6065",
    "addr:housenumber":"44",
    "addr:postcode":"6065",
    "addr:street":"U8 /;Buckingham Drv",
    "iso:country":"AU",
    "sg:address":"U8/ 44 Buckingham Drv",
    "sg:city":"Wangara",
    "sg:classifiers":[
        {
            "category":"Retail",
            "subcategory":"Auto Repair",
            "type":"Services"
        }
    ],
    "sg:phone":"+61 8 9309 6800",
    "sg:postcode":"6065",
    "sg:province":"WA",
    "sg:tags":[
        "repairer",
        "motor",
        "engineer"
    ],
    "wof:name":"K & D Car Care",
    "wof:placetype":"venue"
},
  "geometry": {"coordinates":[115.822158813,-31.7872047424],"type":"Point"}
}