{
  "type": "Feature",
  "properties": {
    "addr:full":"92- 94 Tennyson Rd Mortlake NSW 2137",
    "addr:housenumber":"94",
    "addr:postcode":"2137",
    "addr:street":"Tennyson Rd",
    "iso:country":"AU",
    "sg:address":"92- 94 Tennyson Rd",
    "sg:city":"Mortlake",
    "sg:classifiers":[
        {
            "category":"Wholesale",
            "subcategory":"Construction Materials",
            "type":"Manufacturing & Wholesale Goods"
        }
    ],
    "sg:phone":"+61 2 9743 6099",
    "sg:postcode":"2137",
    "sg:province":"NSW",
    "sg:tags":[
        "wholesaler",
        "lighting",
        "mfrs",
        "accessory"
    ],
    "wof:name":"Crosslite Pty Ltd",
    "wof:placetype":"venue"
},
  "geometry": {"coordinates":[151.10711669899999,-33.8407020569],"type":"Point"}
}