{
  "type": "Feature",
  "properties": {
    "iso:country":"AU",
    "sg:address":"1427 Main North Rd",
    "sg:city":"Para Hills West",
    "sg:classifiers":[
        {
            "category":"Building & Trades",
            "subcategory":"Plumbing",
            "type":"Services"
        }
    ],
    "sg:phone":"+61 8 8281 0609",
    "sg:postcode":"5096",
    "sg:province":"SA",
    "sg:tags":[
        "pipe",
        "line",
        "contractor"
    ],
    "wof:name":"Seychell Constructions",
    "wof:placetype":"venue"
},
  "geometry": {"coordinates":[138.64500427199999,-34.794593811],"type":"Point"}
}