{
  "type": "Feature",
  "properties": {
    "addr:full":"27 Upper Coonara Rd Olinda VIC 3788",
    "addr:housenumber":"27",
    "addr:postcode":"3788",
    "addr:street":"Upper Coonara Rd",
    "iso:country":"AU",
    "sg:address":"27 Upper Coonara Rd",
    "sg:city":"Olinda",
    "sg:classifiers":[
        {
            "category":"Real Estate",
            "subcategory":"Architect",
            "type":"Services"
        }
    ],
    "sg:phone":"+61 400 002 530",
    "sg:postcode":"3788",
    "sg:province":"VIC",
    "wof:name":"Cullen Architects Pty Ltd",
    "wof:placetype":"venue"
},
  "geometry": {"coordinates":[145.39189099999999,-37.874329],"type":"Point"}
}