{
  "type": "Feature",
  "properties": {
    "addr:full":"Staff House Rd St Lucia QLD 4067",
    "addr:housenumber":"staff",
    "addr:postcode":"4067",
    "addr:street":"House Rd St",
    "iso:country":"AU",
    "sg:address":"Staff House Rd",
    "sg:city":"St Lucia",
    "sg:classifiers":[
        {
            "category":"Cafe",
            "type":"Food & Drink"
        }
    ],
    "sg:phone":"+61 7 3365 2001",
    "sg:postcode":"4067",
    "sg:province":"QLD",
    "wof:name":"Wordsmiths Cafe",
    "wof:placetype":"venue"
},
  "geometry": {"coordinates":[153.01434326200001,-27.4990692139],"type":"Point"}
}