{
  "type": "Feature",
  "properties": {
    "addr:full":"6 Yetta Crt Keilor East VIC 3033",
    "addr:housenumber":"6",
    "addr:postcode":"3033",
    "addr:street":"Yetta Crt",
    "iso:country":"AU",
    "sg:address":"6 Yetta Crt",
    "sg:city":"Keilor East",
    "sg:classifiers":[
        {
            "category":"Building & Trades",
            "subcategory":"Pest Control",
            "type":"Services"
        }
    ],
    "sg:phone":"+61 1300 307 864",
    "sg:postcode":"3033",
    "sg:province":"VIC",
    "wof:name":"Neighbourhood Pest Control",
    "wof:placetype":"venue"
},
  "geometry": {"coordinates":[144.852203,-37.749359],"type":"Point"}
}