{
  "type": "Feature",
  "properties": {
    "iso:country":"AU",
    "sg:address":"105 - 153 Miller St",
    "sg:city":"North Sydney",
    "sg:classifiers":[
        {
            "category":"Banks & Credit Unions",
            "subcategory":"Investment Brokerage",
            "type":"Services"
        }
    ],
    "sg:phone":"+61 13 26 52",
    "sg:postcode":"2060",
    "sg:province":"NSW",
    "wof:name":"MLC Ltd",
    "wof:placetype":"venue"
},
  "geometry": {"coordinates":[151.207229614,-33.8378143311],"type":"Point"}
}