{
  "type": "Feature",
  "properties": {
    "iso:country":"AU",
    "sg:address":"107 Gheringhap St",
    "sg:city":"Geelong",
    "sg:classifiers":[
        {
            "category":"Real Estate",
            "subcategory":"Real Estate Agent",
            "type":"Services"
        }
    ],
    "sg:phone":"+61 3 5222 1333",
    "sg:postcode":"3220",
    "sg:province":"VIC",
    "wof:name":"Biggin & Scott",
    "wof:placetype":"venue"
},
  "geometry": {"coordinates":[144.355637,-38.152531],"type":"Point"}
}