{
  "type": "Feature",
  "properties": {
    "iso:country":"AU",
    "sg:address":"6 Robilliard St",
    "sg:city":"Mays Hill",
    "sg:classifiers":[
        {
            "category":"Building & Trades",
            "subcategory":"Construction",
            "type":"Services"
        }
    ],
    "sg:phone":"+61 2 9633 2313",
    "sg:postcode":"2145",
    "sg:province":"NSW",
    "sg:tags":[
        "renovation",
        "alterations",
        "extension",
        "contractor"
    ],
    "wof:name":"Knowdark Skylights",
    "wof:placetype":"venue"
},
  "geometry": {"coordinates":[150.98948669399999,-33.8198852539],"type":"Point"}
}