{
  "type": "Feature",
  "properties": {
    "addr:full":"Unit 6/ 16 Jijaws St Sumner Park QLD 4074",
    "addr:postcode":"4074",
    "addr:street":"16 Jijaws St",
    "iso:country":"AU",
    "sg:address":"Unit 6/ 16 Jijaws St",
    "sg:city":"Sumner Park",
    "sg:classifiers":[
        {
            "category":"Manufacturing",
            "subcategory":"Paper Products",
            "type":"Manufacturing & Wholesale Goods"
        }
    ],
    "sg:phone":"+61 7 3376 6900",
    "sg:postcode":"4074",
    "sg:province":"QLD",
    "sg:tags":[
        "disposable"
    ],
    "wof:name":"Food Pails International Pty Ltd",
    "wof:placetype":"venue"
},
  "geometry": {"coordinates":[152.940063477,-27.5647716522],"type":"Point"}
}