{
  "type": "Feature",
  "properties": {
    "iso:country":"AU",
    "sg:address":"5 Queen St",
    "sg:city":"Merredin",
    "sg:classifiers":[
        {
            "category":"Structure",
            "subcategory":"Tower",
            "type":"Public Place"
        }
    ],
    "sg:phone":"+61 8 9041 1141",
    "sg:postcode":"6415",
    "sg:province":"WA",
    "wof:name":"Burton Adrian & Co",
    "wof:placetype":"venue"
},
  "geometry": {"coordinates":[118.28146362299999,-31.481798172],"type":"Point"}
}