{
  "type": "Feature",
  "properties": {
    "iso:country":"AU",
    "sg:address":"202 Grant St",
    "sg:city":"Ballarat",
    "sg:classifiers":[
        {
            "category":"Building & Trades",
            "subcategory":"Landscaping Services",
            "type":"Services"
        }
    ],
    "sg:phone":"+61 3 5333 5942",
    "sg:postcode":"3350",
    "sg:province":"VIC",
    "sg:tags":[
        "designer",
        "landscape",
        "contractor"
    ],
    "wof:name":"THA Landscape Architects",
    "wof:placetype":"venue"
},
  "geometry": {"coordinates":[143.861069,-37.56863],"type":"Point"}
}