{
  "type": "Feature",
  "properties": {
    "addr:full":"2/ 16 Fremantle Rd Gosnells WA 6110",
    "addr:housenumber":"/ 16",
    "addr:postcode":"6110",
    "addr:street":"Fremantle Rd",
    "iso:country":"AU",
    "sg:address":"2/ 16 Fremantle Rd",
    "sg:city":"Gosnells",
    "sg:classifiers":[
        {
            "category":"Health Services",
            "subcategory":"Dentist",
            "type":"Services"
        }
    ],
    "sg:phone":"+61 8 9398 4786",
    "sg:postcode":"6110",
    "sg:province":"WA",
    "wof:name":"Owen Raymond C Dr",
    "wof:placetype":"venue"
},
  "geometry": {"coordinates":[115.996383667,-32.0686836243],"type":"Point"}
}