{
  "type": "Feature",
  "properties": {
    "addr:full":"39 Lynn St Trigg WA 6029",
    "addr:housenumber":"39",
    "addr:postcode":"6029",
    "addr:street":"Lynn St",
    "iso:country":"AU",
    "sg:address":"39 Lynn St",
    "sg:city":"Trigg",
    "sg:classifiers":[
        {
            "category":"Organizations",
            "subcategory":"Non-profit Organization",
            "type":"Services"
        }
    ],
    "sg:phone":"+61 8 9243 4567",
    "sg:postcode":"6029",
    "sg:province":"WA",
    "sg:tags":[
        "environmental",
        "organisation",
        "conservation"
    ],
    "wof:name":"Marine Information & Research Group Australia",
    "wof:placetype":"venue"
},
  "geometry": {"coordinates":[115.756187439,-31.8684368134],"type":"Point"}
}