{
  "type": "Feature",
  "properties": {
    "addr:full":"139A Cabramatta Rd Cabramatta NSW 2166",
    "addr:housenumber":"139a",
    "addr:postcode":"2166",
    "addr:street":"Cabramatta Rd",
    "iso:country":"AU",
    "sg:address":"139A Cabramatta Rd",
    "sg:city":"Cabramatta",
    "sg:classifiers":[
        {
            "category":"Health Services",
            "subcategory":"Doctor",
            "type":"Services"
        }
    ],
    "sg:phone":"+61 2 9724 2619",
    "sg:postcode":"2166",
    "sg:province":"NSW",
    "sg:tags":[
        "medical",
        "practitioner"
    ],
    "wof:name":"Chan V S P & Lau B C M",
    "wof:placetype":"venue"
},
  "geometry": {"coordinates":[150.937423706,-33.8951301575],"type":"Point"}
}