{
  "type": "Feature",
  "properties": {
    "addr:full":"PO Box 710 Manly NSW 1655",
    "addr:postcode":"1655",
    "iso:country":"AU",
    "sg:address":"PO Box 710",
    "sg:city":"Manly",
    "sg:classifiers":[
        {
            "category":"Building & Trades",
            "subcategory":"Construction",
            "type":"Services"
        }
    ],
    "sg:phone":"+61 412 998 436",
    "sg:postcode":"1655",
    "sg:province":"NSW",
    "sg:tags":[
        "contractor"
    ],
    "wof:name":"H & S Bricklaying Contractors Pty Ltd",
    "wof:placetype":"venue"
},
  "geometry": {"coordinates":[151.288040161,-33.7971382141],"type":"Point"}
}