{
  "type": "Feature",
  "properties": {
    "iso:country":"AU",
    "sg:address":"Unit 2 + 3 38- 42 White St",
    "sg:city":"South Melbourne",
    "sg:classifiers":[
        {
            "category":"Wholesale",
            "subcategory":"Electrical",
            "type":"Manufacturing & Wholesale Goods"
        }
    ],
    "sg:phone":"+61 3 9681 7022",
    "sg:postcode":"3205",
    "sg:province":"VIC",
    "sg:tags":[
        "wholesaler"
    ],
    "sg:website":"http://www.csdata.com.au",
    "wof:name":"Cetnaj Stronglink Pty Ltd",
    "wof:placetype":"venue"
},
  "geometry": {"coordinates":[144.94429,-37.826824],"type":"Point"}
}