{
  "type": "Feature",
  "properties": {
    "addr:full":"26 Yamba St Yamba NSW 2464",
    "addr:housenumber":"26",
    "addr:postcode":"2464",
    "addr:street":"Yamba St",
    "iso:country":"AU",
    "sg:address":"26 Yamba St",
    "sg:city":"Yamba",
    "sg:classifiers":[
        {
            "category":"Cafe",
            "type":"Food & Drink"
        }
    ],
    "sg:phone":"+61 2 6646 3791",
    "sg:postcode":"2464",
    "sg:province":"NSW",
    "wof:name":"Cafe 26",
    "wof:placetype":"venue"
},
  "geometry": {"coordinates":[153.36167907699999,-29.4370975494],"type":"Point"}
}