{
  "type": "Feature",
  "properties": {
    "iso:country":"AU",
    "sg:address":"23 Marino Drv",
    "sg:city":"Cranbourne",
    "sg:classifiers":[
        {
            "category":"Communications",
            "subcategory":"Film & Video Production",
            "type":"Services"
        }
    ],
    "sg:phone":"+61 3 5996 6134",
    "sg:postcode":"3977",
    "sg:province":"VIC",
    "sg:tags":[
        "cost",
        "estimator"
    ],
    "wof:name":"BWT Services",
    "wof:placetype":"venue"
},
  "geometry": {"coordinates":[145.18812560999999,-38.1204833984],"type":"Point"}
}