{
  "type": "Feature",
  "properties": {
    "addr:full":"6 Johnson St Oakleigh VIC 3166",
    "addr:housenumber":"6",
    "addr:postcode":"3166",
    "addr:street":"Johnson St",
    "iso:country":"AU",
    "sg:address":"6 Johnson St",
    "sg:city":"Oakleigh",
    "sg:classifiers":[
        {
            "category":"Personal",
            "subcategory":"Beauty Salon",
            "type":"Services"
        }
    ],
    "sg:phone":"+61 415 939 835",
    "sg:postcode":"3166",
    "sg:province":"VIC",
    "wof:name":"Aralea Beauty Centre",
    "wof:placetype":"venue"
},
  "geometry": {"coordinates":[145.087722778,-37.900390625],"type":"Point"}
}