{
  "type": "Feature",
  "properties": {
    "iso:country":"AU",
    "sg:address":"57 Plymouth Rd",
    "sg:city":"Wingfield",
    "sg:classifiers":[
        {
            "category":"Wholesale",
            "subcategory":"Furniture",
            "type":"Manufacturing & Wholesale Goods"
        }
    ],
    "sg:phone":"+61 8 8243 1150",
    "sg:postcode":"5013",
    "sg:province":"SA",
    "sg:tags":[
        "wholesaler",
        "mfrs"
    ],
    "wof:name":"Trans Furniture Manufacturing Pty Ltd",
    "wof:placetype":"venue"
},
  "geometry": {"coordinates":[138.552566528,-34.8434448242],"type":"Point"}
}