{
  "type": "Feature",
  "properties": {
    "iso:country":"AU",
    "sg:address":"22 Shadforth St",
    "sg:city":"Benalla",
    "sg:classifiers":[
        {
            "category":"Utilities",
            "subcategory":"Water",
            "type":"Services"
        }
    ],
    "sg:phone":"+61 3 5762 2885",
    "sg:postcode":"3672",
    "sg:province":"VIC",
    "sg:tags":[
        "hot",
        "system"
    ],
    "wof:name":"Baines P I & J Electrical Contractors",
    "wof:placetype":"venue"
},
  "geometry": {"coordinates":[145.971405,-36.547443],"type":"Point"}
}