{
  "type": "Feature",
  "properties": {
    "addr:full":"32 Valmadre Rd Lake Placid QLD 4878",
    "addr:housenumber":"32",
    "addr:postcode":"4878",
    "addr:street":"Valmadre Rd",
    "iso:country":"AU",
    "sg:address":"32 Valmadre Rd",
    "sg:city":"Lake Placid",
    "sg:classifiers":[
        {
            "category":"Building & Trades",
            "subcategory":"Pest Control",
            "type":"Services"
        }
    ],
    "sg:phone":"+61 418 738 041",
    "sg:postcode":"4878",
    "sg:province":"QLD",
    "wof:name":"Accredited Termite and Pest Management",
    "wof:placetype":"venue"
},
  "geometry": {"coordinates":[145.67872619600001,-16.8681545258],"type":"Point"}
}