{
  "type": "Feature",
  "properties": {
    "addr:full":"841 Hunter St Newcastle NSW 2300",
    "addr:housenumber":"841",
    "addr:postcode":"2300",
    "addr:street":"Hunter St",
    "iso:country":"AU",
    "sg:address":"841 Hunter St",
    "sg:city":"Newcastle",
    "sg:classifiers":[
        {
            "category":"Retail",
            "subcategory":"Event Space",
            "type":"Services"
        }
    ],
    "sg:phone":"+61 2 4961 0546",
    "sg:postcode":"2300",
    "sg:province":"NSW",
    "sg:tags":[
        "venue",
        "reception",
        "wedding"
    ],
    "wof:name":"Cathedral Catering & Function Centre",
    "wof:placetype":"venue"
},
  "geometry": {"coordinates":[151.75370799999999,-32.922531],"type":"Point"}
}