{
  "type": "Feature",
  "properties": {
    "addr:full":"30 Cobborah Rd Dubbo NSW 2830",
    "addr:housenumber":"30",
    "addr:postcode":"2830",
    "addr:street":"Cobborah Rd",
    "iso:country":"AU",
    "sg:address":"30 Cobborah Rd",
    "sg:city":"Dubbo",
    "sg:classifiers":[
        {
            "category":"Shopping",
            "subcategory":"Pets & Pet Supplies",
            "type":"Retail Goods"
        }
    ],
    "sg:phone":"+61 2 6882 6655",
    "sg:postcode":"2830",
    "sg:province":"NSW",
    "sg:tags":[
        "boring",
        "drilling",
        "equipment"
    ],
    "wof:name":"OneSteel Metaland",
    "wof:placetype":"venue"
},
  "geometry": {"coordinates":[148.617919922,-32.242931366],"type":"Point"}
}