{
  "type": "Feature",
  "properties": {
    "iso:country":"AU",
    "sg:address":"175 Youngs Road",
    "sg:city":"Hemmant",
    "sg:classifiers":[
        {
            "category":"Professional",
            "subcategory":"Accounting & Tax Preparation",
            "type":"Services"
        }
    ],
    "sg:phone":"+61 419 992 522",
    "sg:postcode":"4174",
    "sg:province":"QLD",
    "sg:tags":[
        "bookkeeping"
    ],
    "sg:website":"http://www.cindycampbell.com.au",
    "wof:name":"Cindy Campbell Business Consultants",
    "wof:placetype":"venue"
},
  "geometry": {"coordinates":[153.13368225100001,-27.4527416229],"type":"Point"}
}