{
  "type": "Feature",
  "properties": {
    "addr:full":"53 Matilda St Normanton QLD 4890",
    "addr:housenumber":"53",
    "addr:postcode":"4890",
    "addr:street":"Matilda St",
    "iso:country":"AU",
    "sg:address":"53 Matilda St",
    "sg:city":"Normanton",
    "sg:classifiers":[
        {
            "category":"Airport",
            "subcategory":"General Aviation",
            "type":"Transportation"
        }
    ],
    "sg:phone":"+61 7 4034 9420",
    "sg:postcode":"4890",
    "sg:province":"QLD",
    "sg:tags":[
        "helicopter"
    ],
    "wof:name":"Australian Helicopters",
    "wof:placetype":"venue"
},
  "geometry": {"coordinates":[141.076828003,-17.6768531799],"type":"Point"}
}