{
  "type": "Feature",
  "properties": {
    "addr:full":"12 Riverside Ave Bright VIC 3741",
    "addr:housenumber":"12",
    "addr:postcode":"3741",
    "addr:street":"Riverside Ave",
    "iso:country":"AU",
    "sg:address":"12 Riverside Ave",
    "sg:city":"Bright",
    "sg:classifiers":[
        {
            "category":"Building & Trades",
            "subcategory":"Plumbing",
            "type":"Services"
        }
    ],
    "sg:phone":"+61 3 5755 1907",
    "sg:postcode":"3741",
    "sg:province":"VIC",
    "sg:tags":[
        "plumber",
        "gasfitters"
    ],
    "wof:name":"O&#039;Shea J",
    "wof:placetype":"venue"
},
  "geometry": {"coordinates":[146.960846,-36.726448],"type":"Point"}
}