{
  "type": "Feature",
  "properties": {
    "addr:full":"82 Station St Quirindi NSW 2343",
    "addr:housenumber":"82",
    "addr:postcode":"2343",
    "addr:street":"Station St",
    "iso:country":"AU",
    "sg:address":"82 Station St",
    "sg:city":"Quirindi",
    "sg:classifiers":[
        {
            "category":"Travel",
            "subcategory":"Hotels & Motels",
            "type":"Entertainment"
        }
    ],
    "sg:phone":"+61 2 6746 2032",
    "sg:postcode":"2343",
    "sg:province":"NSW",
    "sg:tags":[
        "accommodation"
    ],
    "wof:name":"Royal Hotel",
    "wof:placetype":"venue"
},
  "geometry": {"coordinates":[150.68069457999999,-31.503118515],"type":"Point"}
}