{
  "type": "Feature",
  "properties": {
    "addr:full":"687 Orrong Rd Toorak VIC 3142",
    "addr:housenumber":"687",
    "addr:postcode":"3142",
    "addr:street":"Orrong Rd",
    "iso:country":"AU",
    "sg:address":"687 Orrong Rd",
    "sg:city":"Toorak",
    "sg:classifiers":[
        {
            "category":"Professional",
            "subcategory":"Accounting & Tax Preparation",
            "type":"Services"
        }
    ],
    "sg:phone":"+61 3 9827 2771",
    "sg:postcode":"3142",
    "sg:province":"VIC",
    "sg:tags":[
        "accountant",
        "auditor"
    ],
    "wof:name":"Bartlett L G",
    "wof:placetype":"venue"
},
  "geometry": {"coordinates":[145.013397217,-37.8430328369],"type":"Point"}
}