{
  "type": "Feature",
  "properties": {
    "addr:full":"1 Hastings St Noosa Heads QLD 4567",
    "addr:housenumber":"1",
    "addr:postcode":"4567",
    "addr:street":"Hastings St",
    "iso:country":"AU",
    "sg:address":"1 Hastings St",
    "sg:city":"Noosa Heads",
    "sg:classifiers":[
        {
            "category":"Restaurant",
            "type":"Food & Drink"
        }
    ],
    "sg:phone":"+61 7 5447 3880",
    "sg:postcode":"4567",
    "sg:province":"QLD",
    "wof:name":"Basserie One",
    "wof:placetype":"venue"
},
  "geometry": {"coordinates":[153.087356567,-26.3860435486],"type":"Point"}
}