{
  "type": "Feature",
  "properties": {
    "iso:country":"AU",
    "sg:address":"16 Castle St",
    "sg:city":"Molong",
    "sg:classifiers":[
        {
            "category":"Building & Trades",
            "subcategory":"Cleaning & Sanitation",
            "type":"Services"
        }
    ],
    "sg:phone":"+61 2 6366 8769",
    "sg:postcode":"2866",
    "sg:province":"NSW",
    "sg:tags":[
        "cleaner",
        "repairer",
        "roof"
    ],
    "wof:name":"Weekes Gus Plumbing",
    "wof:placetype":"venue"
},
  "geometry": {"coordinates":[148.860748,-33.084469],"type":"Point"}
}