{
  "type": "Feature",
  "properties": {
    "iso:country":"AU",
    "sg:address":"Shop 2019 Westfield Liverpool, Macquarie St",
    "sg:city":"Liverpool",
    "sg:classifiers":[
        {
            "category":"Insurance",
            "subcategory":"Hazard Insurance",
            "type":"Services"
        }
    ],
    "sg:phone":"+61 2 8778 5160",
    "sg:postcode":"2170",
    "sg:province":"NSW",
    "sg:tags":[
        "fire",
        "accident",
        "marine"
    ],
    "wof:name":"GIO General Limited",
    "wof:placetype":"venue"
},
  "geometry": {"coordinates":[150.91822814899999,-33.9286499023],"type":"Point"}
}