{
  "type": "Feature",
  "properties": {
    "addr:full":"230- 234 McIntyre Rd Sunshine North VIC 3020",
    "addr:housenumber":"230 234",
    "addr:postcode":"3020",
    "addr:street":"Mcintyre Rd",
    "iso:country":"AU",
    "sg:address":"230- 234 McIntyre Rd",
    "sg:city":"Sunshine North",
    "sg:classifiers":[
        {
            "category":"Home & Garden",
            "subcategory":"Carpets & Floor Coverings",
            "type":"Retail Goods"
        }
    ],
    "sg:phone":"+61 3 8312 0011",
    "sg:postcode":"3020",
    "sg:province":"VIC",
    "wof:name":"Western Distributors",
    "wof:placetype":"venue"
},
  "geometry": {"coordinates":[144.833054,-37.754147],"type":"Point"}
}