{
  "type": "Feature",
  "properties": {
    "iso:country":"AU",
    "sg:address":"32 Telopea St",
    "sg:city":"Redfern",
    "sg:classifiers":[
        {
            "category":"Building & Trades",
            "subcategory":"Plumbing",
            "type":"Services"
        }
    ],
    "sg:phone":"+61 2 9337 1009",
    "sg:postcode":"2016",
    "sg:province":"NSW",
    "sg:tags":[
        "drainers"
    ],
    "wof:name":"A AAAbound Emergency Draining Electric Eel Stormwater Pipe Re-Lining Locating CC",
    "wof:placetype":"venue"
},
  "geometry": {"coordinates":[151.212356567,-33.8942909241],"type":"Point"}
}