{
  "type": "Feature",
  "properties": {
    "addr:full":"1359 Albany Hwy Cannington WA 6107",
    "addr:housenumber":"1359",
    "addr:postcode":"6107",
    "addr:street":"Albany Hwy",
    "iso:country":"AU",
    "sg:address":"1359 Albany Hwy",
    "sg:city":"Cannington",
    "sg:classifiers":[
        {
            "category":"Education",
            "subcategory":"Special Training",
            "type":"Public Place"
        }
    ],
    "sg:phone":"+61 8 9356 2740",
    "sg:postcode":"6107",
    "sg:province":"WA",
    "sg:tags":[
        "development"
    ],
    "wof:name":"Silver Trowel Trade Training",
    "wof:placetype":"venue"
},
  "geometry": {"coordinates":[115.935310364,-32.0189552307],"type":"Point"}
}