{
  "type": "Feature",
  "properties": {
    "addr:full":"Grahams Rd Bundaberg QLD 4670",
    "addr:postcode":"4670",
    "addr:street":"Grahams Rd",
    "iso:country":"AU",
    "sg:address":"Grahams Rd",
    "sg:city":"Bundaberg",
    "sg:classifiers":[
        {
            "category":"Manufacturing",
            "subcategory":"Buildings",
            "type":"Manufacturing & Wholesale Goods"
        }
    ],
    "sg:phone":"+61 7 4151 8511",
    "sg:postcode":"4670",
    "sg:province":"QLD",
    "sg:tags":[
        "house",
        "gazebo",
        "shade"
    ],
    "wof:name":"Uneek Pine Products",
    "wof:placetype":"venue"
},
  "geometry": {"coordinates":[152.27613830600001,-24.8822975159],"type":"Point"}
}