{
  "type": "Feature",
  "properties": {
    "addr:full":"1/ 102 Point Cook Rd Seabrook VIC 3028",
    "addr:housenumber":"/ 102",
    "addr:postcode":"3028",
    "addr:street":"Point Cook Rd",
    "iso:country":"AU",
    "sg:address":"1/ 102 Point Cook Rd",
    "sg:city":"Seabrook",
    "sg:classifiers":[
        {
            "category":"Health Services",
            "subcategory":"Chiropractor",
            "type":"Services"
        }
    ],
    "sg:phone":"+61 3 9369 7987",
    "sg:postcode":"3028",
    "sg:province":"VIC",
    "wof:name":"Sanctuary Lakes Chiropractic",
    "wof:placetype":"venue"
},
  "geometry": {"coordinates":[144.757126,-37.879425],"type":"Point"}
}