{
  "type": "Feature",
  "properties": {
    "iso:country":"AU",
    "sg:address":"3 Bawden Ave",
    "sg:city":"Shoalhaven Heads",
    "sg:classifiers":[
        {
            "category":"Building & Trades",
            "subcategory":"Construction",
            "type":"Services"
        }
    ],
    "sg:phone":"+61 2 4448 5766",
    "sg:postcode":"2535",
    "sg:province":"NSW",
    "sg:tags":[
        "renovation",
        "alterations",
        "extension",
        "contractor"
    ],
    "wof:name":"GP & MJ Flanagan",
    "wof:placetype":"venue"
},
  "geometry": {"coordinates":[150.74455261200001,-34.8509788513],"type":"Point"}
}