{
  "type": "Feature",
  "properties": {
    "iso:country":"AU",
    "sg:address":"62 Poath Rd",
    "sg:city":"Hughesdale",
    "sg:classifiers":[
        {
            "category":"Shopping",
            "subcategory":"Clothing, Apparel, & Fashions",
            "type":"Retail Goods"
        }
    ],
    "sg:phone":"+61 3 9568 1407",
    "sg:postcode":"3166",
    "sg:province":"VIC",
    "sg:tags":[
        "recycled",
        "clothing"
    ],
    "wof:name":"Oakleigh Centre Opportunity Shop",
    "wof:placetype":"venue"
},
  "geometry": {"coordinates":[145.07714843799999,-37.8932571411],"type":"Point"}
}