{
  "type": "Feature",
  "properties": {
    "iso:country":"AU",
    "sg:address":"Shop 33 Chermside Shopping Centre Gympie Rd",
    "sg:city":"Chermside",
    "sg:classifiers":[
        {
            "category":"Shopping",
            "subcategory":"Clothing, Apparel, & Fashions",
            "type":"Retail Goods"
        }
    ],
    "sg:phone":"+61 7 3359 4297",
    "sg:postcode":"4032",
    "sg:province":"QLD",
    "sg:tags":[
        "lady",
        "wear"
    ],
    "wof:name":"Portmans",
    "wof:placetype":"venue"
},
  "geometry": {"coordinates":[153.031113,-27.386387],"type":"Point"}
}