{
  "type": "Feature",
  "properties": {
    "addr:full":"44 Waterloo St Queanbeyan ACT 2620",
    "addr:housenumber":"44",
    "addr:postcode":"2620",
    "addr:street":"Waterloo St",
    "iso:country":"AU",
    "sg:address":"44 Waterloo St",
    "sg:city":"Queanbeyan",
    "sg:classifiers":[
        {
            "category":"Social Services",
            "subcategory":"Adult Care",
            "type":"Services"
        }
    ],
    "sg:phone":"+61 2 6297 6339",
    "sg:postcode":"2620",
    "sg:province":"ACT",
    "sg:tags":[
        "towing"
    ],
    "wof:name":"Pronto Towing Service",
    "wof:placetype":"venue"
},
  "geometry": {"coordinates":[149.239303589,-35.3420028687],"type":"Point"}
}