{
  "type": "Feature",
  "properties": {
    "iso:country":"AU",
    "sg:address":"14 Duncan Crt",
    "sg:city":"Ottoway",
    "sg:classifiers":[
        {
            "category":"Manufacturing",
            "subcategory":"Metals",
            "type":"Manufacturing & Wholesale Goods"
        }
    ],
    "sg:phone":"+61 8 8447 1133",
    "sg:postcode":"5013",
    "sg:province":"SA",
    "sg:tags":[
        "merchant",
        "silver",
        "gold"
    ],
    "wof:name":"Peter W Beck Pty Ltd",
    "wof:placetype":"venue"
},
  "geometry": {"coordinates":[138.54371643100001,-34.8491249084],"type":"Point"}
}