{
  "type": "Feature",
  "properties": {
    "addr:full":"8 Leak St Bittern VIC 3918",
    "addr:housenumber":"8",
    "addr:postcode":"3918",
    "addr:street":"Leak St",
    "iso:country":"AU",
    "sg:address":"8 Leak St",
    "sg:city":"Bittern",
    "sg:classifiers":[
        {
            "category":"Building & Trades",
            "subcategory":"Construction",
            "type":"Services"
        }
    ],
    "sg:phone":"+61 3 5983 9332",
    "sg:postcode":"3918",
    "sg:province":"VIC",
    "sg:tags":[
        "earth",
        "excavating",
        "moving",
        "contractor"
    ],
    "wof:name":"Bittern By The Dingo",
    "wof:placetype":"venue"
},
  "geometry": {"coordinates":[145.18232727,-38.3397979736],"type":"Point"}
}