{
  "type": "Feature",
  "properties": {
    "addr:full":"Suite 23 166 Cabbage Tree Rd Grose Vale NSW 2753",
    "addr:housenumber":"166",
    "addr:postcode":"2753",
    "addr:street":"Cabbage Tree Rd",
    "iso:country":"AU",
    "sg:address":"Suite 23 166 Cabbage Tree Rd",
    "sg:city":"Grose Vale",
    "sg:classifiers":[
        {
            "category":"Social Services",
            "subcategory":"Retirement Home",
            "type":"Services"
        }
    ],
    "sg:phone":"+61 2 4572 2265",
    "sg:postcode":"2753",
    "sg:province":"NSW",
    "sg:tags":[
        "environmental",
        "consultant",
        "pollution"
    ],
    "wof:name":"C4ES Pty Ltd",
    "wof:placetype":"venue"
},
  "geometry": {"coordinates":[150.65176391599999,-33.5967636108],"type":"Point"}
}