{
  "type": "Feature",
  "properties": {
    "addr:full":"30 Koornang Rd Carnegie VIC 3163",
    "addr:housenumber":"30",
    "addr:postcode":"3163",
    "addr:street":"Koornang Rd",
    "iso:country":"AU",
    "sg:address":"30 Koornang Rd",
    "sg:city":"Carnegie",
    "sg:classifiers":[
        {
            "category":"Arena",
            "subcategory":"Sports Club",
            "type":"Entertainment"
        }
    ],
    "sg:phone":"+61 1800 736 734",
    "sg:postcode":"3163",
    "sg:province":"VIC",
    "sg:tags":[
        "defence",
        "supply",
        "self",
        "instruction",
        "martial art"
    ],
    "wof:name":"Karate School The",
    "wof:placetype":"venue"
},
  "geometry": {"coordinates":[145.05801391599999,-37.8848953247],"type":"Point"}
}