{
  "type": "Feature",
  "properties": {
    "iso:country":"AU",
    "sg:address":"6 Rochester St",
    "sg:city":"Homebush",
    "sg:classifiers":[
        {
            "category":"Health Services",
            "subcategory":"Doctor",
            "type":"Services"
        }
    ],
    "sg:phone":"+61 2 9746 8640",
    "sg:postcode":"2140",
    "sg:province":"NSW",
    "sg:tags":[
        "medical",
        "practitioner"
    ],
    "wof:name":"Bhar S",
    "wof:placetype":"venue"
},
  "geometry": {"coordinates":[151.08493042000001,-33.8671073914],"type":"Point"}
}