{
  "type": "Feature",
  "properties": {
    "addr:full":"44 Mawhera Ave Sandy Bay TAS 7005",
    "addr:housenumber":"44",
    "addr:postcode":"7005",
    "addr:street":"Mawhera Ave",
    "iso:country":"AU",
    "sg:address":"44 Mawhera Ave",
    "sg:city":"Sandy Bay",
    "sg:classifiers":[
        {
            "category":"Building & Trades",
            "subcategory":"Pest Control",
            "type":"Services"
        }
    ],
    "sg:phone":"+61 3 6225 0777",
    "sg:postcode":"7005",
    "sg:province":"TAS",
    "wof:name":"Australian Hygiene Services",
    "wof:placetype":"venue"
},
  "geometry": {"coordinates":[147.34048461899999,-42.9115943909],"type":"Point"}
}