{
  "type": "Feature",
  "properties": {
    "addr:full":"574 Tapleys Hill Rd Fulham SA 5024",
    "addr:housenumber":"574",
    "addr:postcode":"5024",
    "addr:street":"Tapleys Hill Rd",
    "iso:country":"AU",
    "sg:address":"574 Tapleys Hill Rd",
    "sg:city":"Fulham",
    "sg:classifiers":[
        {
            "category":"Health Services",
            "subcategory":"Dentist",
            "type":"Services"
        }
    ],
    "sg:phone":"+61 8 8356 5406",
    "sg:postcode":"5024",
    "sg:province":"SA",
    "wof:name":"Ozols I V",
    "wof:placetype":"venue"
},
  "geometry": {"coordinates":[138.51744079599999,-34.9266891479],"type":"Point"}
}