{
  "type": "Feature",
  "properties": {
    "addr:full":"13 Brookhollow Ave Baulkham Hills NSW 2153",
    "addr:housenumber":"13",
    "addr:postcode":"2153",
    "addr:street":"Brookhollow Ave",
    "iso:country":"AU",
    "sg:address":"13 Brookhollow Ave",
    "sg:city":"Baulkham Hills",
    "sg:classifiers":[
        {
            "category":"Building & Trades",
            "subcategory":"Plumbing",
            "type":"Services"
        }
    ],
    "sg:phone":"+61 2 9634 1722",
    "sg:postcode":"2153",
    "sg:province":"NSW",
    "sg:tags":[
        "plumber",
        "gasfitters"
    ],
    "wof:name":"Norwest Plumbing",
    "wof:placetype":"venue"
},
  "geometry": {"coordinates":[150.969848633,-33.7330856323],"type":"Point"}
}