{
  "type": "Feature",
  "properties": {
    "addr:full":"PO Box 69 Devonport TAS 7310",
    "addr:postcode":"7310",
    "iso:country":"AU",
    "sg:address":"PO Box 69",
    "sg:city":"Devonport",
    "sg:classifiers":[
        {
            "category":"Building & Trades",
            "subcategory":"Equipment Rental",
            "type":"Services"
        }
    ],
    "sg:phone":"+61 418 142 516",
    "sg:postcode":"7310",
    "sg:province":"TAS",
    "sg:tags":[
        "crane",
        "hire"
    ],
    "wof:name":"Coastal Crane And Haulage",
    "wof:placetype":"venue"
},
  "geometry": {"coordinates":[146.348587036,-41.1798591614],"type":"Point"}
}