{
  "type": "Feature",
  "properties": {
    "addr:full":"107 Grantham St Floreat Park WA 6014",
    "addr:housenumber":"107",
    "addr:postcode":"6014",
    "addr:street":"Grantham St Floreat Park",
    "iso:country":"AU",
    "sg:address":"107 Grantham St",
    "sg:city":"Floreat Park",
    "sg:classifiers":[
        {
            "category":"Retail",
            "subcategory":"Driving School",
            "type":"Services"
        }
    ],
    "sg:phone":"+61 405 845 802",
    "sg:postcode":"6014",
    "sg:province":"WA",
    "wof:name":"A.B International Driving School",
    "wof:placetype":"venue"
},
  "geometry": {"coordinates":[115.797149658,-31.9343490601],"type":"Point"}
}