{
  "type": "Feature",
  "properties": {
    "iso:country":"AU",
    "sg:address":"Bunbury Court House Ground Floor 65 Wittenoom",
    "sg:city":"Bunbury",
    "sg:classifiers":[
        {
            "category":"Government",
            "subcategory":"Court House",
            "type":"Public Place"
        }
    ],
    "sg:phone":"+61 8 9722 0494",
    "sg:postcode":"6230",
    "sg:province":"WA",
    "sg:tags":[
        "personal",
        "marriage",
        "family",
        "counselling"
    ],
    "wof:name":"Victim Support Service",
    "wof:placetype":"venue"
},
  "geometry": {"coordinates":[115.635429,-33.324169],"type":"Point"}
}