{
  "type": "Feature",
  "properties": {
    "iso:country":"AU",
    "sg:address":"Shop 3, 305 Thomas St",
    "sg:city":"Dandenong",
    "sg:classifiers":[
        {
            "category":"Cafe",
            "type":"Food & Drink"
        }
    ],
    "sg:phone":"+61 3 9792 5303",
    "sg:postcode":"3175",
    "sg:province":"VIC",
    "wof:name":"Mary's Courtyard Cafe",
    "wof:placetype":"venue"
},
  "geometry": {"coordinates":[145.212280273,-37.9855041504],"type":"Point"}
}