{
  "type": "Feature",
  "properties": {
    "addr:full":"Wellington Rd Wagerup WA 6215",
    "addr:postcode":"6215",
    "addr:street":"Wellington Rd",
    "iso:country":"AU",
    "sg:address":"Wellington Rd",
    "sg:city":"Wagerup",
    "sg:classifiers":[
        {
            "category":"Building & Trades",
            "subcategory":"Landscaping Services",
            "type":"Services"
        }
    ],
    "sg:phone":"+61 8 9733 5015",
    "sg:postcode":"6215",
    "sg:province":"WA",
    "sg:tags":[
        "grazier"
    ],
    "wof:name":"Blake Wayne",
    "wof:placetype":"venue"
},
  "geometry": {"coordinates":[115.887047,-32.928463],"type":"Point"}
}