{
  "type": "Feature",
  "properties": {
    "addr:full":"Knowles St Jingili NT 0810",
    "addr:postcode":"nt 0810",
    "addr:street":"Knowles St",
    "iso:country":"AU",
    "sg:address":"Knowles St",
    "sg:city":"Jingili",
    "sg:classifiers":[
        {
            "category":"Education",
            "subcategory":"School",
            "type":"Public Place"
        }
    ],
    "sg:phone":"+61 8 8985 1555",
    "sg:postcode":"0810",
    "sg:province":"NT",
    "sg:tags":[
        "state",
        "except",
        "nsw"
    ],
    "wof:name":"Jingili Primary School",
    "wof:placetype":"venue"
},
  "geometry": {"coordinates":[130.87583923299999,-12.3859081268],"type":"Point"}
}