{
  "type": "Feature",
  "properties": {
    "addr:full":"618 Church St Richmond VIC 3121",
    "addr:housenumber":"618",
    "addr:postcode":"3121",
    "addr:street":"Church St",
    "iso:country":"AU",
    "sg:address":"618 Church St",
    "sg:city":"Richmond",
    "sg:classifiers":[
        {
            "category":"Home & Garden",
            "subcategory":"Building Materials",
            "type":"Retail Goods"
        }
    ],
    "sg:phone":"+61 3 9429 9100",
    "sg:postcode":"3121",
    "sg:province":"VIC",
    "sg:tags":[
        "fitting",
        "door"
    ],
    "wof:name":"Access Studio",
    "wof:placetype":"venue"
},
  "geometry": {"coordinates":[144.99679565400001,-37.8310432434],"type":"Point"}
}