{
  "type": "Feature",
  "properties": {
    "addr:full":"Shp7/ 4 Waters Rd Neutral Bay NSW 2089",
    "addr:housenumber":"4",
    "addr:postcode":"2089",
    "addr:street":"Waters Rd",
    "iso:country":"AU",
    "sg:address":"Shp7/ 4 Waters Rd",
    "sg:city":"Neutral Bay",
    "sg:classifiers":[
        {
            "category":"Organizations",
            "subcategory":"Professional Association",
            "type":"Services"
        }
    ],
    "sg:phone":"+61 2 9904 4144",
    "sg:postcode":"2089",
    "sg:province":"NSW",
    "sg:tags":[
        "web",
        "internet"
    ],
    "wof:name":"Sidiem Sy",
    "wof:placetype":"venue"
},
  "geometry": {"coordinates":[151.223266602,-33.8312454224],"type":"Point"}
}