{
  "type": "Feature",
  "properties": {
    "addr:full":"Level 4/ 8 Crofts Ave Hurstville NSW 2220",
    "addr:housenumber":"/ 8",
    "addr:postcode":"2220",
    "addr:street":"Crofts Ave",
    "iso:country":"AU",
    "sg:address":"Level 4/ 8 Crofts Ave",
    "sg:city":"Hurstville",
    "sg:classifiers":[
        {
            "category":"Professional",
            "subcategory":"Engineering",
            "type":"Services"
        }
    ],
    "sg:phone":"+61 2 9580 5441",
    "sg:postcode":"2220",
    "sg:province":"NSW",
    "sg:tags":[
        "engineer",
        "structural"
    ],
    "wof:name":"Harrison J Engineering Consultancy Pty Ltd",
    "wof:placetype":"venue"
},
  "geometry": {"coordinates":[151.10308837900001,-33.9658966064],"type":"Point"}
}