{
  "type": "Feature",
  "properties": {
    "addr:full":"45 Ben Lexcen Drv Sunshine Beach QLD 4567",
    "addr:housenumber":"45",
    "addr:postcode":"4567",
    "addr:street":"Ben Lexcen Drv",
    "iso:country":"AU",
    "sg:address":"45 Ben Lexcen Drv",
    "sg:city":"Sunshine Beach",
    "sg:classifiers":[
        {
            "category":"Education",
            "subcategory":"School",
            "type":"Public Place"
        }
    ],
    "sg:phone":"+61 7 5440 4222",
    "sg:postcode":"4567",
    "sg:province":"QLD",
    "sg:tags":[
        "state",
        "except",
        "nsw"
    ],
    "wof:name":"Sunshine Beach High School",
    "wof:placetype":"venue"
},
  "geometry": {"coordinates":[153.10122680699999,-26.4093570709],"type":"Point"}
}