{
  "type": "Feature",
  "properties": {
    "addr:full":"120 Main Rd McLaren Vale SA 5171",
    "addr:housenumber":"120",
    "addr:postcode":"5171",
    "addr:street":"Main Rd",
    "iso:country":"AU",
    "sg:address":"120 Main Rd",
    "sg:city":"McLaren Vale",
    "sg:classifiers":[
        {
            "category":"Health Services",
            "subcategory":"Dentist",
            "type":"Services"
        }
    ],
    "sg:phone":"+61 8 8323 8457",
    "sg:postcode":"5171",
    "sg:province":"SA",
    "wof:name":"Fleurieu Dental",
    "wof:placetype":"venue"
},
  "geometry": {"coordinates":[138.53715515100001,-35.2149658203],"type":"Point"}
}