{
  "type": "Feature",
  "properties": {
    "addr:full":"175 Gap Creek Rd Kenmore Hills QLD 4069",
    "addr:housenumber":"175",
    "addr:postcode":"4069",
    "addr:street":"Gap Creek Rd",
    "iso:country":"AU",
    "sg:address":"175 Gap Creek Rd",
    "sg:city":"Kenmore Hills",
    "sg:classifiers":[
        {
            "category":"Sports & Exercise",
            "subcategory":"Gym",
            "type":"Entertainment"
        }
    ],
    "sg:phone":"+61 7 3374 3339",
    "sg:postcode":"4069",
    "sg:province":"QLD",
    "sg:tags":[
        "meditation"
    ],
    "wof:name":"Suma Ching Hai International Association",
    "wof:placetype":"venue"
},
  "geometry": {"coordinates":[152.926437378,-27.4871368408],"type":"Point"}
}