{
  "type": "Feature",
  "properties": {
    "iso:country":"AU",
    "sg:address":"19 Bute St",
    "sg:city":"Murrumbeena",
    "sg:classifiers":[
        {
            "category":"Health Services",
            "subcategory":"Health Practitioner",
            "type":"Services"
        }
    ],
    "sg:phone":"+61 3 9568 4561",
    "sg:postcode":"3163",
    "sg:province":"VIC",
    "sg:tags":[
        "psychologist"
    ],
    "wof:name":"Parker David J",
    "wof:placetype":"venue"
},
  "geometry": {"coordinates":[145.07083129899999,-37.8954048157],"type":"Point"}
}