{
  "type": "Feature",
  "properties": {
    "iso:country":"AU",
    "sg:address":"66 Murdoch Ave",
    "sg:city":"Narre Warren",
    "sg:classifiers":[
        {
            "category":"Building & Trades",
            "subcategory":"Cleaning & Sanitation",
            "type":"Services"
        }
    ],
    "sg:phone":"+61 3 9704 7162",
    "sg:postcode":"3805",
    "sg:province":"VIC",
    "sg:tags":[
        "industrial",
        "commercial",
        "contractor"
    ],
    "wof:name":"Lend-A-Hand",
    "wof:placetype":"venue"
},
  "geometry": {"coordinates":[145.315277,-38.002529],"type":"Point"}
}