{
  "type": "Feature",
  "properties": {
    "addr:full":"Meagher Drv Badgingarra WA 6521",
    "addr:postcode":"6521",
    "addr:street":"Meagher Drv",
    "iso:country":"AU",
    "sg:address":"Meagher Drv",
    "sg:city":"Badgingarra",
    "sg:classifiers":[
        {
            "category":"Restaurant",
            "type":"Food & Drink"
        }
    ],
    "sg:phone":"+61 8 9652 9051",
    "sg:postcode":"6521",
    "sg:province":"WA",
    "sg:tags":[
        "roadhouse"
    ],
    "wof:name":"Badgingarra Roadhouse",
    "wof:placetype":"venue"
},
  "geometry": {"coordinates":[115.501152039,-30.3894863129],"type":"Point"}
}