{
  "type": "Feature",
  "properties": {
    "addr:full":"Unit 5, Grnd Flr 77 Parramatta Rd Silverwater NSW 2128",
    "addr:postcode":"2128",
    "addr:street":"Grnd;Parramatta Rd",
    "iso:country":"AU",
    "sg:address":"Unit 5, Grnd Flr 77 Parramatta Rd",
    "sg:city":"Silverwater",
    "sg:classifiers":[
        {
            "category":"Health Services",
            "subcategory":"Health Practitioner",
            "type":"Services"
        }
    ],
    "sg:phone":"+61 2 8748 1555",
    "sg:postcode":"2128",
    "sg:province":"NSW",
    "sg:tags":[
        "physiotherapist"
    ],
    "wof:name":"Australian Physiotherapy Association (NSW Branch)",
    "wof:placetype":"venue"
},
  "geometry": {"coordinates":[151.04258727999999,-33.8451042175],"type":"Point"}
}