{
  "type": "Feature",
  "properties": {
    "addr:full":"18 Pentland Rd Salisbury South SA 5106",
    "addr:housenumber":"18",
    "addr:postcode":"5106",
    "addr:street":"Pentland Rd",
    "iso:country":"AU",
    "sg:address":"18 Pentland Rd",
    "sg:city":"Salisbury South",
    "sg:classifiers":[
        {
            "category":"Manufacturing",
            "subcategory":"Aerospace",
            "type":"Manufacturing & Wholesale Goods"
        }
    ],
    "sg:phone":"+61 8 8281 7175",
    "sg:postcode":"5106",
    "sg:province":"SA",
    "sg:tags":[
        "equipment",
        "aircraft",
        "maintenance"
    ],
    "wof:name":"Parafield Instrument Facilities Pty Ltd",
    "wof:placetype":"venue"
},
  "geometry": {"coordinates":[138.64295999999999,-34.783539],"type":"Point"}
}