{
  "type": "Feature",
  "properties": {
    "addr:full":"5/ 64 - 66 Oak Rd Kirrawee NSW 2232",
    "addr:housenumber":"/;66",
    "addr:postcode":"2232",
    "addr:street":"64;Oak Rd",
    "iso:country":"AU",
    "sg:address":"5/ 64 - 66 Oak Rd",
    "sg:city":"Kirrawee",
    "sg:classifiers":[
        {
            "category":"Retail",
            "subcategory":"Auto Repair",
            "type":"Services"
        }
    ],
    "sg:phone":"+61 2 9521 1052",
    "sg:postcode":"2232",
    "sg:province":"NSW",
    "sg:tags":[
        "repairer",
        "motor",
        "engineer"
    ],
    "wof:name":"Don Rangi Auto Repairers",
    "wof:placetype":"venue"
},
  "geometry": {"coordinates":[151.07276916500001,-34.0269737244],"type":"Point"}
}