{
  "type": "Feature",
  "properties": {
    "iso:country":"AU",
    "sg:address":"67 Hunter St",
    "sg:city":"Newcastle",
    "sg:classifiers":[
        {
            "category":"Cafe",
            "type":"Food & Drink"
        }
    ],
    "sg:phone":"+61 2 4900 5378",
    "sg:postcode":"2300",
    "sg:province":"NSW",
    "wof:name":"Juicy Beans Cafe",
    "wof:placetype":"venue"
},
  "geometry": {"coordinates":[151.78353899999999,-32.927738],"type":"Point"}
}