{
  "type": "Feature",
  "properties": {
    "iso:country":"AU",
    "sg:address":"38 Industry Drv",
    "sg:city":"Tweed Heads South",
    "sg:classifiers":[
        {
            "category":"Autos & Motor Vehicles",
            "subcategory":"Motorcycle Sales",
            "type":"Retail Goods"
        }
    ],
    "sg:phone":"+61 7 5524 8224",
    "sg:postcode":"2486",
    "sg:province":"NSW",
    "sg:tags":[
        "outboard"
    ],
    "wof:name":"A B Marine Parts",
    "wof:placetype":"venue"
},
  "geometry": {"coordinates":[153.542144775,-28.2017269135],"type":"Point"}
}