{
  "type": "Feature",
  "properties": {
    "addr:full":"Suite 3 / 1 Transvaal Ave Double Bay NSW 2028",
    "addr:postcode":"2028",
    "addr:street":"Transvaal Ave",
    "iso:country":"AU",
    "sg:address":"Suite 3 / 1 Transvaal Ave",
    "sg:city":"Double Bay",
    "sg:classifiers":[
        {
            "category":"Banks & Credit Unions",
            "subcategory":"Financial Services",
            "type":"Services"
        }
    ],
    "sg:phone":"+61 2 9363 5566",
    "sg:postcode":"2028",
    "sg:province":"NSW",
    "sg:tags":[
        "financier"
    ],
    "wof:name":"Chester Capital Pty Ltd",
    "wof:placetype":"venue"
},
  "geometry": {"coordinates":[151.243972778,-33.8765411377],"type":"Point"}
}