{
  "type": "Feature",
  "properties": {
    "addr:full":"Casuarina Square Shop GD 42 Trower Rd Casuarina NT 0810",
    "addr:housenumber":"42",
    "addr:postcode":"nt 0810",
    "addr:street":"Trower Rd",
    "iso:country":"AU",
    "sg:address":"Casuarina Square Shop GD 42 Trower Rd",
    "sg:city":"Casuarina",
    "sg:classifiers":[
        {
            "category":"Manufacturing",
            "subcategory":"Printing",
            "type":"Manufacturing & Wholesale Goods"
        }
    ],
    "sg:phone":"+61 8 8927 5411",
    "sg:postcode":"0810",
    "sg:province":"NT",
    "sg:tags":[
        "wholesaler",
        "mfrs",
        "greeting",
        "card"
    ],
    "wof:name":"Cardeaux Casuarina",
    "wof:placetype":"venue"
},
  "geometry": {"coordinates":[130.86155700699999,-12.3866100311],"type":"Point"}
}