{
  "type": "Feature",
  "properties": {
    "addr:full":"Shop 1, 72 Burnett St Buderim QLD 4556",
    "addr:housenumber":"shop;72",
    "addr:postcode":"4556",
    "addr:street":"Burnett St",
    "iso:country":"AU",
    "sg:address":"Shop 1, 72 Burnett St",
    "sg:city":"Buderim",
    "sg:classifiers":[
        {
            "category":"Communications",
            "subcategory":"Film & Video Production",
            "type":"Services"
        }
    ],
    "sg:phone":"+61 7 5445 5330",
    "sg:postcode":"4556",
    "sg:province":"QLD",
    "sg:tags":[
        "dvd",
        "library"
    ],
    "wof:name":"Blockbuster",
    "wof:placetype":"venue"
},
  "geometry": {"coordinates":[153.04908752399999,-26.6871871948],"type":"Point"}
}