{
  "type": "Feature",
  "properties": {
    "iso:country":"AU",
    "sg:address":"U13/ 489 South St",
    "sg:city":"Harristown",
    "sg:classifiers":[
        {
            "category":"Building & Trades",
            "subcategory":"Construction",
            "type":"Services"
        }
    ],
    "sg:phone":"+61 7 4633 1522",
    "sg:postcode":"4350",
    "sg:province":"QLD",
    "sg:tags":[
        "contractor"
    ],
    "wof:name":"Liebke Homes",
    "wof:placetype":"venue"
},
  "geometry": {"coordinates":[151.920929,-27.573702],"type":"Point"}
}