{
  "type": "Feature",
  "properties": {
    "addr:full":"Lot 2 Baradine Rd Coonabarabran NSW 2357",
    "addr:postcode":"2357",
    "addr:street":"Baradine Rd",
    "iso:country":"AU",
    "sg:address":"Lot 2 Baradine Rd",
    "sg:city":"Coonabarabran",
    "sg:classifiers":[
        {
            "category":"Farming",
            "subcategory":"Farm & Veterinary Services",
            "type":"Manufacturing & Wholesale Goods"
        }
    ],
    "sg:phone":"+61 500 885 545",
    "sg:postcode":"2357",
    "sg:province":"NSW",
    "sg:tags":[
        "drying",
        "seed",
        "cleaning",
        "grading"
    ],
    "wof:name":"Jones Chris Seed Grading",
    "wof:placetype":"venue"
},
  "geometry": {"coordinates":[149.27302551299999,-31.2671737671],"type":"Point"}
}