{
  "type": "Feature",
  "properties": {
    "addr:full":"8 Hartley Drv Thornton NSW 2322",
    "addr:housenumber":"8",
    "addr:postcode":"2322",
    "addr:street":"Hartley Drv",
    "iso:country":"AU",
    "sg:address":"8 Hartley Drv",
    "sg:city":"Thornton",
    "sg:classifiers":[
        {
            "category":"Mining & Drilling",
            "type":"Manufacturing & Wholesale Goods"
        }
    ],
    "sg:phone":"+61 2 4924 4000",
    "sg:postcode":"2322",
    "sg:province":"NSW",
    "sg:tags":[
        "equipment",
        "quarrying",
        "supply"
    ],
    "wof:name":"Mine Safety Technology Centre-NSW Department of Primary Industries",
    "wof:placetype":"venue"
},
  "geometry": {"coordinates":[151.6378479,-32.7901115417],"type":"Point"}
}