{
  "type": "Feature",
  "properties": {
    "iso:country":"AU",
    "sg:address":"Lot 1 South Western Hwy",
    "sg:city":"Mundijong",
    "sg:classifiers":[
        {
            "category":"Wholesale",
            "subcategory":"Farm Supplies",
            "type":"Manufacturing & Wholesale Goods"
        }
    ],
    "sg:phone":"+61 8 9525 5476",
    "sg:postcode":"6123",
    "sg:province":"WA",
    "sg:tags":[
        "equipment"
    ],
    "wof:name":"Mundijong Rural",
    "wof:placetype":"venue"
},
  "geometry": {"coordinates":[116.01091003400001,-32.2943916321],"type":"Point"}
}