{
  "type": "Feature",
  "properties": {
    "addr:full":"PO Box 202 Newstead TAS 7250",
    "addr:postcode":"7250",
    "iso:country":"AU",
    "sg:address":"PO Box 202",
    "sg:city":"Newstead",
    "sg:classifiers":[
        {
            "category":"Building & Trades",
            "subcategory":"Plumbing",
            "type":"Services"
        }
    ],
    "sg:phone":"+61 428 818 100",
    "sg:postcode":"7250",
    "sg:province":"TAS",
    "sg:tags":[
        "plumber",
        "gasfitters"
    ],
    "wof:name":"In House Home Solutions",
    "wof:placetype":"venue"
},
  "geometry": {"coordinates":[147.16065979000001,-41.4412384033],"type":"Point"}
}