{
  "type": "Feature",
  "properties": {
    "addr:full":"South St Boggabilla NSW 2409",
    "addr:postcode":"2409",
    "addr:street":"South St",
    "iso:country":"AU",
    "sg:address":"South St",
    "sg:city":"Boggabilla",
    "sg:classifiers":[
        {
            "category":"Education",
            "subcategory":"School",
            "type":"Public Place"
        }
    ],
    "sg:phone":"+61 7 4676 2104",
    "sg:postcode":"2409",
    "sg:province":"NSW",
    "sg:tags":[
        "state",
        "except",
        "nsw"
    ],
    "wof:name":"Boggabilla Central School",
    "wof:placetype":"venue"
},
  "geometry": {"coordinates":[150.359375,-28.6154537201],"type":"Point"}
}