{
  "type": "Feature",
  "properties": {
    "addr:full":"Suite 14, 110 Willoughby Rd Crows Nest NSW 2065",
    "addr:housenumber":"110",
    "addr:postcode":"2065",
    "addr:street":"Willoughby Rd",
    "iso:country":"AU",
    "sg:address":"Suite 14, 110 Willoughby Rd",
    "sg:city":"Crows Nest",
    "sg:classifiers":[
        {
            "category":"Utilities",
            "subcategory":"Water",
            "type":"Services"
        }
    ],
    "sg:phone":"+61 2 9439 2615",
    "sg:postcode":"2065",
    "sg:province":"NSW",
    "sg:tags":[
        "equipment",
        "treatment"
    ],
    "wof:name":"Aquarius Carwash Systems",
    "wof:placetype":"venue"
},
  "geometry": {"coordinates":[151.20074462900001,-33.824432373],"type":"Point"}
}