{
  "type": "Feature",
  "properties": {
    "addr:full":"Lvl 1/ 257 Coventry St South Melbourne VIC 3205",
    "addr:housenumber":"/ 257",
    "addr:postcode":"3205",
    "addr:street":"Coventry St",
    "iso:country":"AU",
    "sg:address":"Lvl 1/ 257 Coventry St",
    "sg:city":"South Melbourne",
    "sg:classifiers":[
        {
            "category":"Shopping",
            "subcategory":"Gifts & Souvenirs",
            "type":"Retail Goods"
        }
    ],
    "sg:phone":"+61 3 9686 4255",
    "sg:postcode":"3205",
    "sg:province":"VIC",
    "sg:tags":[
        "shop",
        "supply"
    ],
    "wof:name":"Christopher Vine Design Pty Ltd",
    "wof:placetype":"venue"
},
  "geometry": {"coordinates":[144.95931999999999,-37.832218],"type":"Point"}
}