{
  "type": "Feature",
  "properties": {
    "addr:full":"19B Strickland St Mt Claremont WA 6010",
    "addr:housenumber":"19b",
    "addr:postcode":"6010",
    "addr:street":"Strickland St",
    "iso:country":"AU",
    "sg:address":"19B Strickland St",
    "sg:city":"Mt Claremont",
    "sg:classifiers":[
        {
            "category":"Health Services",
            "subcategory":"Health Practitioner",
            "type":"Services"
        }
    ],
    "sg:phone":"+61 8 9384 7910",
    "sg:postcode":"6010",
    "sg:province":"WA",
    "sg:tags":[
        "homoeopath"
    ],
    "wof:name":"Joanne Sumpton-Wales",
    "wof:placetype":"venue"
},
  "geometry": {"coordinates":[115.775131226,-31.9651756287],"type":"Point"}
}