{
  "type": "Feature",
  "properties": {
    "addr:full":"86 Harrison St Box Hill North VIC 3129",
    "addr:housenumber":"86",
    "addr:postcode":"3129",
    "addr:street":"Harrison St",
    "iso:country":"AU",
    "sg:address":"86 Harrison St",
    "sg:city":"Box Hill North",
    "sg:classifiers":[
        {
            "category":"Utilities",
            "subcategory":"Electric",
            "type":"Services"
        }
    ],
    "sg:phone":"+61 3 9897 1188",
    "sg:postcode":"3129",
    "sg:province":"VIC",
    "sg:tags":[
        "electrical",
        "contractor"
    ],
    "wof:name":"Walsh E V & Co Pty Ltd",
    "wof:placetype":"venue"
},
  "geometry": {"coordinates":[145.133468628,-37.7991676331],"type":"Point"}
}