{
  "type": "Feature",
  "properties": {
    "addr:full":"61-65 Lane Cove Rd Ryde NSW 2112",
    "addr:housenumber":"61-65",
    "addr:postcode":"2112",
    "addr:street":"Lane Cove Rd",
    "iso:country":"AU",
    "sg:address":"61-65 Lane Cove Rd",
    "sg:city":"Ryde",
    "sg:classifiers":[
        {
            "category":"Education",
            "subcategory":"School",
            "type":"Public Place"
        }
    ],
    "sg:phone":"+61 2 9809 5252",
    "sg:postcode":"2112",
    "sg:province":"NSW",
    "sg:website":"http://www.northcross.nsw.edu.au",
    "wof:name":"Northcross Christian School",
    "wof:placetype":"venue"
},
  "geometry": {"coordinates":[151.10775756800001,-33.8088188171],"type":"Point"}
}