{
  "type": "Feature",
  "properties": {
    "iso:country":"AU",
    "sg:address":"Minorca Pl",
    "sg:city":"Toormina",
    "sg:classifiers":[
        {
            "category":"Professional",
            "subcategory":"Accounting & Tax Preparation",
            "type":"Services"
        }
    ],
    "sg:phone":"+61 2 6658 1655",
    "sg:postcode":"2452",
    "sg:province":"NSW",
    "sg:tags":[
        "accountant",
        "auditor"
    ],
    "wof:name":"Denis Jeff",
    "wof:placetype":"venue"
},
  "geometry": {"coordinates":[153.09098800000001,-30.352688],"type":"Point"}
}