{
  "type": "Feature",
  "properties": {
    "iso:country":"AU",
    "sg:address":"83a Bayview Rd",
    "sg:city":"Canada Bay",
    "sg:classifiers":[
        {
            "category":"Building & Trades",
            "subcategory":"Construction",
            "type":"Services"
        }
    ],
    "sg:phone":"+61 412 237 820",
    "sg:postcode":"2046",
    "sg:province":"NSW",
    "sg:tags":[
        "brick",
        "paving"
    ],
    "wof:name":"Ben Hall Enterprises",
    "wof:placetype":"venue"
},
  "geometry": {"coordinates":[151.114746,-33.863041],"type":"Point"}
}