{
  "type": "Feature",
  "properties": {
    "addr:full":"609 Dalton Rd Epping VIC 3076",
    "addr:housenumber":"609",
    "addr:postcode":"3076",
    "addr:street":"Dalton Rd",
    "iso:country":"AU",
    "sg:address":"609 Dalton Rd",
    "sg:city":"Epping",
    "sg:classifiers":[
        {
            "category":"Building & Trades",
            "subcategory":"Landscaping Services",
            "type":"Services"
        }
    ],
    "sg:phone":"+61 418 533 691",
    "sg:postcode":"3076",
    "sg:province":"VIC",
    "sg:tags":[
        "stump",
        "tree",
        "felling",
        "removal"
    ],
    "wof:name":"Marks Complete Tree Lopping Service",
    "wof:placetype":"venue"
},
  "geometry": {"coordinates":[145.030426025,-37.6439781189],"type":"Point"}
}