{
  "type": "Feature",
  "properties": {
    "addr:full":"48 Cambridge St Collingwood, Victoria 3066",
    "addr:housenumber":"48",
    "addr:postcode":"3066",
    "addr:street":"Cambridge St",
    "iso:country":"AU",
    "sg:address":"48 Cambridge St",
    "sg:city":"Collingwood, Victoria",
    "sg:classifiers":[
        {
            "category":"Professional",
            "subcategory":"Computer Services",
            "type":"Services"
        }
    ],
    "sg:postcode":"3066",
    "sg:website":"http://www.sitepoint.com",
    "wof:name":"SitePoint",
    "wof:placetype":"venue"
},
  "geometry": {"coordinates":[144.98526100000001,-37.807444],"type":"Point"}
}