{
  "type": "Feature",
  "properties": {
    "addr:full":"Suite 2/ Level 5/ 167- 169 Queen St Melbourne VIC 3000",
    "addr:housenumber":"/ 167 169",
    "addr:postcode":"3000",
    "addr:street":"Queen St",
    "iso:country":"AU",
    "sg:address":"Suite 2/ Level 5/ 167- 169 Queen St",
    "sg:city":"Melbourne",
    "sg:classifiers":[
        {
            "category":"Professional",
            "subcategory":"Management & Consulting",
            "type":"Services"
        }
    ],
    "sg:phone":"+61 3 9606 0118",
    "sg:postcode":"3000",
    "sg:province":"VIC",
    "sg:tags":[
        "consultant"
    ],
    "wof:name":"Precision Consultancy Pty Ltd",
    "wof:placetype":"venue"
},
  "geometry": {"coordinates":[144.96034240700001,-37.814540863],"type":"Point"}
}