{
  "type": "Feature",
  "properties": {
    "iso:country":"AU",
    "sg:address":"Level 1 354 Bay St",
    "sg:city":"Brighton-le-Sands",
    "sg:classifiers":[
        {
            "category":"Professional",
            "subcategory":"Accounting & Tax Preparation",
            "type":"Services"
        }
    ],
    "sg:phone":"+61 2 9597 1033",
    "sg:postcode":"2216",
    "sg:province":"NSW",
    "sg:tags":[
        "accountant",
        "auditor"
    ],
    "wof:name":"Mavrolefterou H",
    "wof:placetype":"venue"
},
  "geometry": {"coordinates":[151.154617,-33.960068],"type":"Point"}
}