{
  "type": "Feature",
  "properties": {
    "addr:full":"77 Burwood Rd Whitebridge NSW 2290",
    "addr:housenumber":"77",
    "addr:postcode":"2290",
    "addr:street":"Burwood Rd",
    "iso:country":"AU",
    "sg:address":"77 Burwood Rd",
    "sg:city":"Whitebridge",
    "sg:classifiers":[
        {
            "category":"Education",
            "subcategory":"School",
            "type":"Public Place"
        }
    ],
    "sg:phone":"+61 2 4942 6919",
    "sg:postcode":"2290",
    "sg:province":"NSW",
    "wof:name":"Under 3 Education Centre",
    "wof:placetype":"venue"
},
  "geometry": {"coordinates":[151.71893310600001,-32.9719619751],"type":"Point"}
}