{
  "type": "Feature",
  "properties": {
    "addr:full":"1 Young St Southport QLD 4215",
    "addr:housenumber":"1",
    "addr:postcode":"4215",
    "addr:street":"Young St",
    "iso:country":"AU",
    "sg:address":"1 Young St",
    "sg:city":"Southport",
    "sg:classifiers":[
        {
            "category":"Health Services",
            "subcategory":"Doctor",
            "type":"Services"
        }
    ],
    "sg:phone":"+61 7 5591 5644",
    "sg:postcode":"4215",
    "sg:province":"QLD",
    "sg:tags":[
        "reflexology"
    ],
    "wof:name":"Georgina Robinson",
    "wof:placetype":"venue"
},
  "geometry": {"coordinates":[153.41412353499999,-27.9686508179],"type":"Point"}
}