{
  "type": "Feature",
  "properties": {
    "addr:full":"P.O. Box 13191 Law Courts Melbourne VIC 3000",
    "addr:postcode":"3000",
    "iso:country":"AU",
    "sg:address":"P.O. Box 13191 Law Courts",
    "sg:city":"Melbourne",
    "sg:classifiers":[
        {
            "category":"Arts & Performance",
            "subcategory":"Music",
            "type":"Entertainment"
        }
    ],
    "sg:phone":"+61 3 9625 1284",
    "sg:postcode":"3000",
    "sg:province":"VIC",
    "sg:tags":[
        "mobile",
        "jockey",
        "disc"
    ],
    "wof:name":"Amazing Spin Doctors",
    "wof:placetype":"venue"
},
  "geometry": {"coordinates":[144.96881103499999,-37.8132286072],"type":"Point"}
}