{
  "type": "Feature",
  "properties": {
    "addr:full":"Suite 12 695 The Horsley Drv Smithfield NSW 2164",
    "addr:housenumber":"695",
    "addr:postcode":"2164",
    "addr:street":"The Horsley Drv",
    "iso:country":"AU",
    "sg:address":"Suite 12 695 The Horsley Drv",
    "sg:city":"Smithfield",
    "sg:classifiers":[
        {
            "category":"Banks & Credit Unions",
            "subcategory":"Financial Services",
            "type":"Services"
        }
    ],
    "sg:phone":"+61 2 9729 3177",
    "sg:postcode":"2164",
    "sg:province":"NSW",
    "sg:tags":[
        "planning"
    ],
    "wof:name":"Professional Investment Services",
    "wof:placetype":"venue"
},
  "geometry": {"coordinates":[150.938842773,-33.8530960083],"type":"Point"}
}