{
  "type": "Feature",
  "properties": {
    "addr:full":"Lvl1, 35 Norton St Leichhardt NSW 2040",
    "addr:housenumber":"35",
    "addr:postcode":"2040",
    "addr:street":"Norton St",
    "iso:country":"AU",
    "sg:address":"Lvl1, 35 Norton St",
    "sg:city":"Leichhardt",
    "sg:classifiers":[
        {
            "category":"Education",
            "subcategory":"Music School",
            "type":"Public Place"
        }
    ],
    "sg:phone":"+61 2 9560 2102",
    "sg:postcode":"2040",
    "sg:province":"NSW",
    "sg:tags":[
        "teacher"
    ],
    "wof:name":"International School Of Music",
    "wof:placetype":"venue"
},
  "geometry": {"coordinates":[151.15760800000001,-33.886574],"type":"Point"}
}