{
  "type": "Feature",
  "properties": {
    "addr:full":"Roxburgh Plaza Homemaker Cntr Unit 5 195 Somerton Rd Roxburgh Park VIC 3064",
    "addr:housenumber":"195",
    "addr:postcode":"3064",
    "addr:street":"Somerton Rd",
    "iso:country":"AU",
    "sg:address":"Roxburgh Plaza Homemaker Cntr Unit 5 195 Somerton Rd",
    "sg:city":"Roxburgh Park",
    "sg:classifiers":[
        {
            "category":"Building & Trades",
            "subcategory":"Construction",
            "type":"Services"
        }
    ],
    "sg:phone":"+61 3 9308 6455",
    "sg:postcode":"3064",
    "sg:province":"VIC",
    "sg:tags":[
        "pool",
        "swimming"
    ],
    "wof:name":"Clark Pools & Spas",
    "wof:placetype":"venue"
},
  "geometry": {"coordinates":[144.932830811,-37.6412391663],"type":"Point"}
}