{
  "type": "Feature",
  "properties": {
    "addr:full":"2 Rani Pl Kareela NSW 2232",
    "addr:housenumber":"2",
    "addr:postcode":"2232",
    "addr:street":"Rani Pl",
    "iso:country":"AU",
    "sg:address":"2 Rani Pl",
    "sg:city":"Kareela",
    "sg:classifiers":[
        {
            "category":"Shopping",
            "subcategory":"Computers & Home Electronics",
            "type":"Retail Goods"
        }
    ],
    "sg:phone":"+61 2 9528 3172",
    "sg:postcode":"2232",
    "sg:province":"NSW",
    "sg:tags":[
        "small",
        "equipment",
        "business"
    ],
    "wof:name":"Acrom Business Services Pty Ltd",
    "wof:placetype":"venue"
},
  "geometry": {"coordinates":[151.08320617699999,-34.0104522705],"type":"Point"}
}