{
  "type": "Feature",
  "properties": {
    "addr:full":"21 Rapallo Ave Isle Of Capri QLD 4217",
    "addr:housenumber":"21",
    "addr:postcode":"4217",
    "addr:street":"Rapallo Ave",
    "iso:country":"AU",
    "sg:address":"21 Rapallo Ave",
    "sg:city":"Isle Of Capri",
    "sg:classifiers":[
        {
            "category":"Building & Trades",
            "subcategory":"Construction",
            "type":"Services"
        }
    ],
    "sg:phone":"+61 403 052 973",
    "sg:postcode":"4217",
    "sg:province":"QLD",
    "sg:tags":[
        "builder",
        "designer",
        "room",
        "cool"
    ],
    "wof:name":"Rowland Industries Pty Ltd",
    "wof:placetype":"venue"
},
  "geometry": {"coordinates":[153.41664123499999,-28.0141868591],"type":"Point"}
}