{
  "type": "Feature",
  "properties": {
    "iso:country":"AU",
    "sg:address":"5 Jobson St",
    "sg:city":"Albion",
    "sg:classifiers":[
        {
            "category":"Building & Trades",
            "subcategory":"Construction",
            "type":"Services"
        }
    ],
    "sg:phone":"+61 7 3262 9044",
    "sg:postcode":"4010",
    "sg:province":"QLD",
    "sg:tags":[
        "welding"
    ],
    "wof:name":"Bushell Engineering",
    "wof:placetype":"venue"
},
  "geometry": {"coordinates":[153.04394531200001,-27.4382381439],"type":"Point"}
}