{
  "type": "Feature",
  "properties": {
    "iso:country":"AU",
    "sg:address":"3 Adams St",
    "sg:city":"O'Connor",
    "sg:classifiers":[
        {
            "category":"Home & Garden",
            "subcategory":"Hardware",
            "type":"Retail Goods"
        }
    ],
    "sg:phone":"+61 8 9331 5555",
    "sg:postcode":"6163",
    "sg:province":"WA",
    "sg:tags":[
        "part",
        "air conditioning"
    ],
    "wof:name":"AC Parts",
    "wof:placetype":"venue"
},
  "geometry": {"coordinates":[115.80165100000001,-32.062202],"type":"Point"}
}