{
  "type": "Feature",
  "properties": {
    "addr:full":"418 Elizabeth Ave Kippa-Ring QLD 4021",
    "addr:housenumber":"418",
    "addr:postcode":"4021",
    "addr:street":"Elizabeth Ave",
    "iso:country":"AU",
    "sg:address":"418 Elizabeth Ave",
    "sg:city":"Kippa-Ring",
    "sg:classifiers":[
        {
            "category":"Travel",
            "subcategory":"Hotels & Motels",
            "type":"Entertainment"
        }
    ],
    "sg:phone":"+61 7 3283 3933",
    "sg:postcode":"4021",
    "sg:province":"QLD",
    "wof:name":"Kippa Ring Village Motel",
    "wof:placetype":"venue"
},
  "geometry": {"coordinates":[153.08476300000001,-27.226622],"type":"Point"}
}