{
  "type": "Feature",
  "properties": {
    "addr:full":"1/ 251 High St Penrith NSW 2750",
    "addr:housenumber":"/ 251",
    "addr:postcode":"2750",
    "addr:street":"High St",
    "iso:country":"AU",
    "sg:address":"1/ 251 High St",
    "sg:city":"Penrith",
    "sg:classifiers":[
        {
            "category":"Food & Beverages",
            "subcategory":"Bakery",
            "type":"Retail Goods"
        }
    ],
    "sg:phone":"+61 2 4721 1404",
    "sg:postcode":"2750",
    "sg:province":"NSW",
    "sg:tags":[
        "cake",
        "shop",
        "pastry"
    ],
    "wof:name":"Cheesecake Shop The",
    "wof:placetype":"venue"
},
  "geometry": {"coordinates":[150.91560363799999,-33.8946762085],"type":"Point"}
}