{
  "type": "Feature",
  "properties": {
    "iso:country":"AU",
    "sg:address":"2 King William Rd",
    "sg:city":"North Adelaide",
    "sg:classifiers":[
        {
            "category":"Education",
            "subcategory":"Dance Studio",
            "type":"Public Place"
        }
    ],
    "sg:phone":"+61 8 8267 1177",
    "sg:postcode":"5006",
    "sg:province":"SA",
    "sg:tags":[
        "instruction",
        "language"
    ],
    "sg:website":"http://www.vllc.com.au",
    "wof:name":"Vocational Language Learning Centre",
    "wof:placetype":"venue"
},
  "geometry": {"coordinates":[138.59889221200001,-34.9132080078],"type":"Point"}
}