{
  "type": "Feature",
  "properties": {
    "addr:full":"3 Staughton St Melton South VIC 3338",
    "addr:housenumber":"3",
    "addr:postcode":"3338",
    "addr:street":"Staughton St",
    "iso:country":"AU",
    "sg:address":"3 Staughton St",
    "sg:city":"Melton South",
    "sg:classifiers":[
        {
            "category":"Professional",
            "subcategory":"Employment Agencies",
            "type":"Services"
        }
    ],
    "sg:phone":"+61 3 9743 7952",
    "sg:postcode":"3338",
    "sg:province":"VIC",
    "sg:tags":[
        "entertainer",
        "agent"
    ],
    "wof:name":"Colouris",
    "wof:placetype":"venue"
},
  "geometry": {"coordinates":[144.57449299999999,-37.704327],"type":"Point"}
}