{
  "type": "Feature",
  "properties": {
    "addr:full":"153 Roper Rd Gosford NSW 2250",
    "addr:housenumber":"153",
    "addr:postcode":"2250",
    "addr:street":"Roper Rd",
    "iso:country":"AU",
    "sg:address":"153 Roper Rd",
    "sg:city":"Gosford",
    "sg:classifiers":[
        {
            "category":"Building & Trades",
            "subcategory":"Plumbing",
            "type":"Services"
        }
    ],
    "sg:phone":"+61 418 430 024",
    "sg:postcode":"2250",
    "sg:province":"NSW",
    "sg:tags":[
        "plumber",
        "gasfitters"
    ],
    "wof:name":"Luke Shannon Plumbing Services",
    "wof:placetype":"venue"
},
  "geometry": {"coordinates":[151.34249877900001,-33.4237213135],"type":"Point"}
}