{
  "type": "Feature",
  "properties": {
    "iso:country":"AU",
    "sg:address":"Unit 1/37- 39 Green St",
    "sg:city":"Banksmeadow",
    "sg:classifiers":[
        {
            "category":"Professional",
            "subcategory":"Detective & Security Services",
            "type":"Services"
        }
    ],
    "sg:phone":"+61 2 9700 1911",
    "sg:postcode":"2019",
    "sg:province":"NSW",
    "sg:tags":[
        "consultant",
        "system"
    ],
    "wof:name":"H & T Security Pty Ltd",
    "wof:placetype":"venue"
},
  "geometry": {"coordinates":[151.21311950699999,-33.9440612793],"type":"Point"}
}