{
  "type": "Feature",
  "properties": {
    "iso:country":"AU",
    "sg:address":"12 Shepherds Bush Drv",
    "sg:city":"Kingsley",
    "sg:phone":"+61 8 9409 5650",
    "sg:postcode":"6026",
    "sg:province":"WA",
    "wof:name":"Filtration Industries",
    "wof:placetype":"venue"
},
  "geometry": {"coordinates":[115.794471741,-31.8060417175],"type":"Point"}
}