{
  "type": "Feature",
  "properties": {
    "addr:full":"33 Kent Rd Keswick SA 5035",
    "addr:housenumber":"33",
    "addr:postcode":"5035",
    "addr:street":"Kent Rd",
    "iso:country":"AU",
    "sg:address":"33 Kent Rd",
    "sg:city":"Keswick",
    "sg:classifiers":[
        {
            "category":"Professional",
            "type":"Services"
        }
    ],
    "sg:phone":"+61 8 8351 1133",
    "sg:postcode":"5035",
    "sg:province":"SA",
    "sg:tags":[
        "coating",
        "powder"
    ],
    "wof:name":"Central Powder Coaters",
    "wof:placetype":"venue"
},
  "geometry": {"coordinates":[138.57623290999999,-34.9449653625],"type":"Point"}
}