{
  "type": "Feature",
  "properties": {
    "addr:full":"Moffatt Rd Waterford West QLD 4133",
    "addr:postcode":"4133",
    "addr:street":"Moffatt Rd",
    "iso:country":"AU",
    "sg:address":"Moffatt Rd",
    "sg:city":"Waterford West",
    "sg:classifiers":[
        {
            "category":"Professional",
            "subcategory":"Employment Agencies",
            "type":"Services"
        }
    ],
    "sg:phone":"+61 7 3299 0777",
    "sg:postcode":"4133",
    "sg:province":"QLD",
    "wof:name":"Career Keys",
    "wof:placetype":"venue"
},
  "geometry": {"coordinates":[153.11268615700001,-27.6845664978],"type":"Point"}
}