{
  "type": "Feature",
  "properties": {
    "addr:full":"1 Boundry Rd Box Hill NSW 2765",
    "addr:housenumber":"1",
    "addr:postcode":"2765",
    "addr:street":"Boundry Rd",
    "iso:country":"AU",
    "sg:address":"1 Boundry Rd",
    "sg:city":"Box Hill",
    "sg:classifiers":[
        {
            "category":"Railroad",
            "type":"Transportation"
        }
    ],
    "sg:phone":"+61 2 4573 6800",
    "sg:postcode":"2765",
    "sg:province":"NSW",
    "sg:tags":[
        "equipment",
        "railway",
        "construction",
        "material"
    ],
    "wof:name":"Sheridan & Sons Pty Ltd",
    "wof:placetype":"venue"
},
  "geometry": {"coordinates":[150.906784058,-33.6005554199],"type":"Point"}
}