{
  "type": "Feature",
  "properties": {
    "iso:country":"AU",
    "sg:address":"Shp 3/ 336 Sandgate Rd",
    "sg:city":"Albion",
    "sg:classifiers":[
        {
            "category":"Cafe",
            "type":"Food & Drink"
        }
    ],
    "sg:phone":"+61 7 3256 1725",
    "sg:postcode":"4010",
    "sg:province":"QLD",
    "wof:name":"Darls",
    "wof:placetype":"venue"
},
  "geometry": {"coordinates":[153.04212951700001,-27.4292030334],"type":"Point"}
}