{
  "type": "Feature",
  "properties": {
    "iso:country":"AU",
    "sg:address":"42 Beach St",
    "sg:city":"Frankston",
    "sg:classifiers":[
        {
            "category":"Shopping",
            "subcategory":"Mobile Phones",
            "type":"Retail Goods"
        }
    ],
    "sg:phone":"+61 3 9783 7977",
    "sg:postcode":"3199",
    "sg:province":"VIC",
    "sg:tags":[
        "telephone",
        "accessory"
    ],
    "wof:name":"Frankston Retravision",
    "wof:placetype":"venue"
},
  "geometry": {"coordinates":[144.937744141,-37.8428726196],"type":"Point"}
}