{
  "type": "Feature",
  "properties": {
    "iso:country":"AU",
    "sg:address":"Phillipson St",
    "sg:city":"Wangaratta",
    "sg:classifiers":[
        {
            "category":"Autos & Motor Vehicles",
            "subcategory":"Fuel & Gas Station",
            "type":"Retail Goods"
        }
    ],
    "sg:phone":"+61 3 5722 2977",
    "sg:postcode":"3677",
    "sg:province":"VIC",
    "wof:name":"BP Australia Limited",
    "wof:placetype":"venue"
},
  "geometry": {"coordinates":[146.303833008,-36.3592987061],"type":"Point"}
}