{
  "type": "Feature",
  "properties": {
    "iso:country":"AU",
    "sg:address":"9 Bloomsbury St",
    "sg:city":"Newtown",
    "sg:classifiers":[
        {
            "category":"Building & Trades",
            "subcategory":"Plumbing",
            "type":"Services"
        }
    ],
    "sg:phone":"+61 418 520 316",
    "sg:postcode":"3220",
    "sg:province":"VIC",
    "sg:tags":[
        "plumber",
        "gasfitters"
    ],
    "wof:name":"Plumb Spec Plumbing Pty Ltd",
    "wof:placetype":"venue"
},
  "geometry": {"coordinates":[144.346115,-38.160244],"type":"Point"}
}