{
  "type": "Feature",
  "properties": {
    "addr:full":"54 Wellington St St Kilda VIC 3182",
    "addr:housenumber":"54",
    "addr:postcode":"3182",
    "addr:street":"Wellington St",
    "iso:country":"AU",
    "sg:address":"54 Wellington St",
    "sg:city":"St Kilda",
    "sg:classifiers":[
        {
            "category":"Professional",
            "subcategory":"Management & Consulting",
            "type":"Services"
        }
    ],
    "sg:phone":"+61 3 9529 6919",
    "sg:postcode":"3182",
    "sg:province":"VIC",
    "sg:tags":[
        "consultant"
    ],
    "wof:name":"R.A.D.A.C. Consultants Pty Ltd",
    "wof:placetype":"venue"
},
  "geometry": {"coordinates":[144.98629760700001,-37.8568649292],"type":"Point"}
}