{
  "type": "Feature",
  "properties": {
    "iso:country":"AU",
    "sg:address":"468 Fernbank Creek Rd",
    "sg:city":"Port Macquarie",
    "sg:classifiers":[
        {
            "category":"Professional",
            "subcategory":"Computer Services",
            "type":"Services"
        }
    ],
    "sg:phone":"+61 2 6583 9112",
    "sg:postcode":"2444",
    "sg:province":"NSW",
    "sg:tags":[
        "consultant",
        "system"
    ],
    "wof:name":"Express Accounting Solutions",
    "wof:placetype":"venue"
},
  "geometry": {"coordinates":[152.85871900000001,-31.407455],"type":"Point"}
}