{
  "type": "Feature",
  "properties": {
    "iso:country":"AU",
    "sg:address":"156 Langtree Ave",
    "sg:city":"Mildura",
    "sg:classifiers":[
        {
            "category":"Insurance",
            "subcategory":"Insurance Agent",
            "type":"Services"
        }
    ],
    "sg:phone":"+61 3 5023 7666",
    "sg:postcode":"3500",
    "sg:province":"VIC",
    "sg:tags":[
        "broker"
    ],
    "wof:name":"MGA Insurance Brokers Pty Ltd Tucker & Associates Inc.",
    "wof:placetype":"venue"
},
  "geometry": {"coordinates":[142.156784058,-34.1882553101],"type":"Point"}
}