{
  "type": "Feature",
  "properties": {
    "addr:full":"PO Box 498 Salisbury SA 5108",
    "addr:postcode":"5108",
    "iso:country":"AU",
    "sg:address":"PO Box 498",
    "sg:city":"Salisbury",
    "sg:classifiers":[
        {
            "category":"Shopping",
            "subcategory":"Crafts & Fabrics",
            "type":"Retail Goods"
        }
    ],
    "sg:phone":"+61 407 608 316",
    "sg:postcode":"5108",
    "sg:province":"SA",
    "sg:tags":[
        "supply"
    ],
    "wof:name":"Stamps & Stuff",
    "wof:placetype":"venue"
},
  "geometry": {"coordinates":[138.642120361,-34.7604484558],"type":"Point"}
}