{
  "type": "Feature",
  "properties": {
    "iso:country":"AU",
    "sg:address":"12 Trinity Pl",
    "sg:city":"Kirwan",
    "sg:classifiers":[
        {
            "category":"Professional",
            "subcategory":"Accounting & Tax Preparation",
            "type":"Services"
        }
    ],
    "sg:phone":"+61 7 4723 9922",
    "sg:postcode":"4817",
    "sg:province":"QLD",
    "sg:tags":[
        "bookkeeping"
    ],
    "wof:name":"ADMIN ALL WAYS",
    "wof:placetype":"venue"
},
  "geometry": {"coordinates":[146.720947,-19.315451],"type":"Point"}
}