{
  "type": "Feature",
  "properties": {
    "addr:full":"Shop 2, The Plaza, 23 - 25 Burns Bay Road Lane Cove NSW 2066",
    "addr:housenumber":"shop 2;23 25",
    "addr:postcode":"2066",
    "addr:street":"The Plaza;Burns Bay Road",
    "iso:country":"AU",
    "sg:address":"Shop 2, The Plaza, 23 - 25 Burns Bay Road",
    "sg:city":"Lane Cove",
    "sg:classifiers":[
        {
            "category":"Food & Beverages",
            "subcategory":"Bakery",
            "type":"Retail Goods"
        }
    ],
    "sg:phone":"+61 2 9418 3849",
    "sg:postcode":"2066",
    "sg:province":"NSW",
    "sg:tags":[
        "baker"
    ],
    "wof:name":"Bakers Delight Ltd",
    "wof:placetype":"venue"
},
  "geometry": {"coordinates":[151.16888427699999,-33.8144264221],"type":"Point"}
}