{
  "type": "Feature",
  "properties": {
    "addr:full":"130 Manning Rd Manning WA 6152",
    "addr:housenumber":"130",
    "addr:postcode":"6152",
    "addr:street":"Manning Rd",
    "iso:country":"AU",
    "sg:address":"130 Manning Rd",
    "sg:city":"Manning",
    "sg:classifiers":[
        {
            "category":"Health Services",
            "subcategory":"Doctor",
            "type":"Services"
        }
    ],
    "sg:phone":"+61 8 9313 1588",
    "sg:postcode":"6152",
    "sg:province":"WA",
    "sg:tags":[
        "medical",
        "practitioner"
    ],
    "wof:name":"Lee Dr. Marie",
    "wof:placetype":"venue"
},
  "geometry": {"coordinates":[115.87159699999999,-32.011417],"type":"Point"}
}