{
  "type": "Feature",
  "properties": {
    "iso:country":"AU",
    "sg:address":"10 Fuchsia Rd",
    "sg:city":"Wyoming",
    "sg:classifiers":[
        {
            "category":"Personal",
            "subcategory":"Beauty Salon",
            "type":"Services"
        }
    ],
    "sg:phone":"+61 2 4328 4461",
    "sg:postcode":"2250",
    "sg:province":"NSW",
    "sg:tags":[
        "hairdresser"
    ],
    "wof:name":"Marellas Hairdressing",
    "wof:placetype":"venue"
},
  "geometry": {"coordinates":[151.36175537099999,-33.4068412781],"type":"Point"}
}