{
  "type": "Feature",
  "properties": {
    "addr:full":"Midland Hwy Buninyong VIC 3357",
    "addr:postcode":"3357",
    "addr:street":"Midland Hwy",
    "iso:country":"AU",
    "sg:address":"Midland Hwy",
    "sg:city":"Buninyong",
    "sg:classifiers":[
        {
            "category":"Autos & Motor Vehicles",
            "subcategory":"Fuel & Gas Station",
            "type":"Retail Goods"
        }
    ],
    "sg:phone":"+61 3 5441 2154",
    "sg:postcode":"3357",
    "sg:province":"VIC",
    "wof:name":"BP Australia Limited",
    "wof:placetype":"venue"
},
  "geometry": {"coordinates":[143.88630699999999,-37.650757],"type":"Point"}
}