{
  "type": "Feature",
  "properties": {
    "addr:full":"The Deck 188-190 Tarleton St Devonport TAS 7310",
    "addr:housenumber":"188-190",
    "addr:postcode":"7310",
    "addr:street":"Tarleton St",
    "iso:country":"AU",
    "sg:address":"The Deck 188-190 Tarleton St",
    "sg:city":"Devonport",
    "sg:classifiers":[
        {
            "category":"Professional",
            "subcategory":"Accounting & Tax Preparation",
            "type":"Services"
        }
    ],
    "sg:phone":"+61 3 6423 2695",
    "sg:postcode":"7310",
    "sg:province":"TAS",
    "sg:tags":[
        "accountant",
        "auditor"
    ],
    "wof:name":"Badcocks Pty Ltd",
    "wof:placetype":"venue"
},
  "geometry": {"coordinates":[146.357513428,-41.1777153015],"type":"Point"}
}