{
  "type": "Feature",
  "properties": {
    "iso:country":"AU",
    "sg:address":"3/ 23 A'Beckett St",
    "sg:city":"Inverloch",
    "sg:classifiers":[
        {
            "category":"Retail",
            "subcategory":"Veterinary Services",
            "type":"Services"
        }
    ],
    "sg:phone":"+61 3 5674 3822",
    "sg:postcode":"3996",
    "sg:province":"VIC",
    "sg:tags":[
        "surgeon"
    ],
    "wof:name":"A'Beckett St Companion Animal Veterinary Clinic",
    "wof:placetype":"venue"
},
  "geometry": {"coordinates":[145.725281,-38.633709],"type":"Point"}
}