{
  "type": "Feature",
  "properties": {
    "iso:country":"AU",
    "sg:address":"Shop 16, Beerwah Market Place Peachester Rd",
    "sg:city":"Beerwah",
    "sg:classifiers":[
        {
            "category":"Banks & Credit Unions",
            "subcategory":"Bank",
            "type":"Services"
        }
    ],
    "sg:phone":"+61 7 5439 0622",
    "sg:postcode":"4519",
    "sg:province":"QLD",
    "wof:name":"Bank of Queensland",
    "wof:placetype":"venue"
},
  "geometry": {"coordinates":[152.957458,-26.857019],"type":"Point"}
}