{
  "type": "Feature",
  "properties": {
    "iso:country":"AU",
    "sg:address":"343 Cambridge St",
    "sg:city":"Wembley",
    "sg:classifiers":[
        {
            "category":"Health Services",
            "subcategory":"Doctor",
            "type":"Services"
        }
    ],
    "sg:phone":"+61 8 9383 9997",
    "sg:postcode":"6014",
    "sg:province":"WA",
    "sg:tags":[
        "medical",
        "practitioner"
    ],
    "wof:name":"Cullingford, Dr Jocelyn",
    "wof:placetype":"venue"
},
  "geometry": {"coordinates":[115.81118774399999,-31.9408855438],"type":"Point"}
}