{
  "type": "Feature",
  "properties": {
    "iso:country":"AU",
    "sg:address":"14 Carol Ave",
    "sg:city":"Springwood",
    "sg:classifiers":[
        {
            "category":"Travel",
            "subcategory":"Hotels & Motels",
            "type":"Entertainment"
        }
    ],
    "sg:phone":"+61 7 3387 6000",
    "sg:postcode":"4127",
    "sg:province":"QLD",
    "sg:tags":[
        "accommodation"
    ],
    "wof:name":"Hotel Gloria",
    "wof:placetype":"venue"
},
  "geometry": {"coordinates":[153.12669372600001,-27.6166305542],"type":"Point"}
}