{
  "type": "Feature",
  "properties": {
    "addr:full":"128 Lachlan St Forbes NSW 2871",
    "addr:housenumber":"128",
    "addr:postcode":"2871",
    "addr:street":"Lachlan St",
    "iso:country":"AU",
    "sg:address":"128 Lachlan St",
    "sg:city":"Forbes",
    "sg:classifiers":[
        {
            "category":"Organizations",
            "subcategory":"Community Association",
            "type":"Services"
        }
    ],
    "sg:phone":"+61 2 6852 3912",
    "sg:postcode":"2871",
    "sg:province":"NSW",
    "sg:tags":[
        "organisation",
        "family",
        "welfare"
    ],
    "wof:name":"Home Care Service Of NSW",
    "wof:placetype":"venue"
},
  "geometry": {"coordinates":[148.00709499999999,-33.385773],"type":"Point"}
}