{
  "type": "Feature",
  "properties": {
    "iso:country":"AU",
    "sg:address":"128 Lachlan St",
    "sg:city":"Forbes",
    "sg:classifiers":[
        {
            "category":"Organizations",
            "subcategory":"Community Association",
            "type":"Services"
        }
    ],
    "sg:phone":"+61 2 6852 3912",
    "sg:postcode":"2871",
    "sg:province":"NSW",
    "sg:tags":[
        "organisation",
        "family",
        "welfare"
    ],
    "wof:name":"Home Care Service Of NSW",
    "wof:placetype":"venue"
},
  "geometry": {"coordinates":[148.007095,-33.385773],"type":"Point"}
}