{
  "type": "Feature",
  "properties": {
    "addr:full":"17 Export Drv Molendinar QLD 4214",
    "addr:housenumber":"17",
    "addr:postcode":"4214",
    "addr:street":"Export Drv",
    "iso:country":"AU",
    "sg:address":"17 Export Drv",
    "sg:city":"Molendinar",
    "sg:classifiers":[
        {
            "category":"Communications",
            "subcategory":"Film & Video Production",
            "type":"Services"
        }
    ],
    "sg:phone":"+61 7 5563 3376",
    "sg:postcode":"4214",
    "sg:province":"QLD",
    "sg:tags":[
        "mirror"
    ],
    "wof:name":"Southport Glass & Aluminium",
    "wof:placetype":"venue"
},
  "geometry": {"coordinates":[153.359298706,-27.9680957794],"type":"Point"}
}