{
  "type": "Feature",
  "properties": {
    "iso:country":"AU",
    "sg:address":"13 Sunderland St",
    "sg:city":"Moonah",
    "sg:classifiers":[
        {
            "category":"Manufacturing",
            "subcategory":"Glass & Minerals",
            "type":"Manufacturing & Wholesale Goods"
        }
    ],
    "sg:phone":"+61 3 6273 9477",
    "sg:postcode":"7009",
    "sg:province":"TAS",
    "sg:tags":[
        "fabricator",
        "fibreglass"
    ],
    "wof:name":"Gee Ron Enterprises Pty Ltd",
    "wof:placetype":"venue"
},
  "geometry": {"coordinates":[147.295196533,-42.8422889709],"type":"Point"}
}