{
  "type": "Feature",
  "properties": {
    "addr:full":"210 Toorak Rd South Yarra VIC 3141",
    "addr:housenumber":"210",
    "addr:postcode":"3141",
    "addr:street":"Toorak Rd",
    "iso:country":"AU",
    "sg:address":"210 Toorak Rd",
    "sg:city":"South Yarra",
    "sg:classifiers":[
        {
            "category":"Retail",
            "subcategory":"Repair Shop",
            "type":"Services"
        }
    ],
    "sg:phone":"+61 3 9827 4080",
    "sg:postcode":"3141",
    "sg:province":"VIC",
    "sg:tags":[
        "mending",
        "clothing",
        "alteration"
    ],
    "wof:name":"House Of Services",
    "wof:placetype":"venue"
},
  "geometry": {"coordinates":[144.994064331,-37.8394126892],"type":"Point"}
}