{
  "type": "Feature",
  "properties": {
    "addr:full":"330 Loganlea Rd Meadowbrook QLD 4131",
    "addr:housenumber":"330",
    "addr:postcode":"4131",
    "addr:street":"Loganlea Rd",
    "iso:country":"AU",
    "sg:address":"330 Loganlea Rd",
    "sg:city":"Meadowbrook",
    "sg:classifiers":[
        {
            "category":"Building & Trades",
            "subcategory":"Construction",
            "type":"Services"
        }
    ],
    "sg:phone":"+61 7 3805 5528",
    "sg:postcode":"4131",
    "sg:province":"QLD",
    "sg:tags":[
        "contractor"
    ],
    "wof:name":"Coward Holdings Pty Ltd",
    "wof:placetype":"venue"
},
  "geometry": {"coordinates":[153.14021301299999,-27.6620693207],"type":"Point"}
}