{
  "type": "Feature",
  "properties": {
    "iso:country":"AU",
    "sg:address":"71 Mitchell St",
    "sg:city":"Bendigo",
    "sg:classifiers":[
        {
            "category":"Professional",
            "subcategory":"Accounting & Tax Preparation",
            "type":"Services"
        }
    ],
    "sg:phone":"+61 1300 660 800",
    "sg:postcode":"3539",
    "sg:province":"VIC",
    "sg:tags":[
        "consultant",
        "taxation"
    ],
    "wof:name":"The Tax Shop",
    "wof:placetype":"venue"
},
  "geometry": {"coordinates":[144.280807495,-36.7614936829],"type":"Point"}
}