{
  "type": "Feature",
  "properties": {
    "addr:full":"27 Claremont Ave Greenacre NSW 2190",
    "addr:housenumber":"27",
    "addr:postcode":"2190",
    "addr:street":"Claremont Ave",
    "iso:country":"AU",
    "sg:address":"27 Claremont Ave",
    "sg:city":"Greenacre",
    "sg:classifiers":[
        {
            "category":"Wholesale",
            "subcategory":"Auto Parts",
            "type":"Manufacturing & Wholesale Goods"
        }
    ],
    "sg:phone":"+61 2 9708 3312",
    "sg:postcode":"2190",
    "sg:province":"NSW",
    "sg:tags":[
        "recyclers"
    ],
    "wof:name":"Georges Wreckers",
    "wof:placetype":"venue"
},
  "geometry": {"coordinates":[151.03895600000001,-33.900532],"type":"Point"}
}