{
  "type": "Feature",
  "properties": {
    "iso:country":"AU",
    "sg:address":"114 Oberon St",
    "sg:city":"Oberon",
    "sg:classifiers":[
        {
            "category":"Professional",
            "subcategory":"Accounting & Tax Preparation",
            "type":"Services"
        }
    ],
    "sg:phone":"+61 2 6336 2033",
    "sg:postcode":"2787",
    "sg:province":"NSW",
    "sg:tags":[
        "accountant",
        "auditor"
    ],
    "wof:name":"Lowe H E & Company",
    "wof:placetype":"venue"
},
  "geometry": {"coordinates":[149.857666016,-33.7042388916],"type":"Point"}
}