{
  "type": "Feature",
  "properties": {
    "addr:full":"PO Box 431 Welshpool WA 6106",
    "addr:postcode":"6106",
    "iso:country":"AU",
    "sg:address":"PO Box 431",
    "sg:city":"Welshpool",
    "sg:classifiers":[
        {
            "category":"Wholesale",
            "subcategory":"Farm Supplies",
            "type":"Manufacturing & Wholesale Goods"
        }
    ],
    "sg:phone":"+61 8 9356 1722",
    "sg:postcode":"6106",
    "sg:province":"WA",
    "sg:tags":[
        "equipment"
    ],
    "wof:name":"Western Rural Traders.",
    "wof:placetype":"venue"
},
  "geometry": {"coordinates":[115.946907044,-31.9927997589],"type":"Point"}
}