{
  "type": "Feature",
  "properties": {
    "addr:full":"41 Saratoga Crs Keilor Downs VIC 3038",
    "addr:housenumber":"41",
    "addr:postcode":"3038",
    "addr:street":"Saratoga Crs",
    "iso:country":"AU",
    "sg:address":"41 Saratoga Crs",
    "sg:city":"Keilor Downs",
    "sg:classifiers":[
        {
            "category":"Utilities",
            "subcategory":"Electric",
            "type":"Services"
        }
    ],
    "sg:phone":"+61 3 9362 1235",
    "sg:postcode":"3038",
    "sg:province":"VIC",
    "sg:tags":[
        "electrical",
        "contractor"
    ],
    "wof:name":"No Shocks Electrics",
    "wof:placetype":"venue"
},
  "geometry": {"coordinates":[144.79104599999999,-37.716671],"type":"Point"}
}