{
  "type": "Feature",
  "properties": {
    "addr:full":"128 Alexander Ave Thomastown VIC 3074",
    "addr:housenumber":"128",
    "addr:postcode":"3074",
    "addr:street":"Alexander Ave",
    "iso:country":"AU",
    "sg:address":"128 Alexander Ave",
    "sg:city":"Thomastown",
    "sg:classifiers":[
        {
            "category":"Food & Beverages",
            "subcategory":"Groceries & Convenience Stores",
            "type":"Retail Goods"
        }
    ],
    "sg:phone":"+61 3 9465 2802",
    "sg:postcode":"3074",
    "sg:province":"VIC",
    "wof:name":"K & N Daghers Milkbar",
    "wof:placetype":"venue"
},
  "geometry": {"coordinates":[145.025466919,-37.6813774109],"type":"Point"}
}