{
  "type": "Feature",
  "properties": {
    "addr:full":"PO Box 667 Proserpine QLD 4800",
    "addr:postcode":"4800",
    "iso:country":"AU",
    "sg:address":"PO Box 667",
    "sg:city":"Proserpine",
    "sg:classifiers":[
        {
            "category":"Building & Trades",
            "subcategory":"Plumbing",
            "type":"Services"
        }
    ],
    "sg:phone":"+61 7 4947 1923",
    "sg:postcode":"4800",
    "sg:province":"QLD",
    "sg:tags":[
        "pipe",
        "line",
        "contractor"
    ],
    "wof:name":"McAllister Earth Moving Whitsunday",
    "wof:placetype":"venue"
},
  "geometry": {"coordinates":[148.593505859,-20.3528594971],"type":"Point"}
}