{
  "type": "Feature",
  "properties": {
    "addr:full":"PO Box 460 Seymour VIC 3661",
    "addr:postcode":"3661",
    "iso:country":"AU",
    "sg:address":"PO Box 460",
    "sg:city":"Seymour",
    "sg:classifiers":[
        {
            "category":"Communications",
            "type":"Services"
        }
    ],
    "sg:phone":"+61 439 036 281",
    "sg:postcode":"3661",
    "sg:province":"VIC",
    "sg:tags":[
        "data"
    ],
    "wof:name":"Shockwave Electrical",
    "wof:placetype":"venue"
},
  "geometry": {"coordinates":[145.134155273,-37.0253105164],"type":"Point"}
}