{
  "type": "Feature",
  "properties": {
    "iso:country":"AU",
    "sg:address":"8 Andell Pl",
    "sg:city":"Redcliffe",
    "sg:classifiers":[
        {
            "category":"Professional",
            "subcategory":"Computer Services",
            "type":"Services"
        }
    ],
    "sg:phone":"+61 8 9475 0090",
    "sg:postcode":"6104",
    "sg:province":"WA",
    "sg:tags":[
        "repairs",
        "upgrade",
        "equipment"
    ],
    "wof:name":"Frontline PC",
    "wof:placetype":"venue"
},
  "geometry": {"coordinates":[115.945602417,-31.9418296814],"type":"Point"}
}