{
  "type": "Feature",
  "properties": {
    "addr:full":"113- 115 Oxford St Darlinghurst NSW 2010",
    "addr:housenumber":"113 115",
    "addr:postcode":"2010",
    "addr:street":"Oxford St",
    "iso:country":"AU",
    "sg:address":"113- 115 Oxford St",
    "sg:city":"Darlinghurst",
    "sg:classifiers":[
        {
            "category":"Conference Center",
            "type":"Public Place"
        }
    ],
    "sg:phone":"+61 2 9331 1700",
    "sg:postcode":"2010",
    "sg:province":"NSW",
    "sg:tags":[
        "venue",
        "convention"
    ],
    "wof:name":"Conference Call (Aust) Pty Ltd",
    "wof:placetype":"venue"
},
  "geometry": {"coordinates":[151.21522522000001,-33.8793525696],"type":"Point"}
}