{
  "type": "Feature",
  "properties": {
    "iso:country":"AU",
    "sg:address":"203b Castlereagh St",
    "sg:city":"Sydney",
    "sg:classifiers":[
        {
            "category":"Shopping",
            "subcategory":"Stationery & Office Supplies",
            "type":"Retail Goods"
        }
    ],
    "sg:phone":"+61 1300 132 299",
    "sg:postcode":"2000",
    "sg:province":"NSW",
    "wof:name":"Surry Office National",
    "wof:placetype":"venue"
},
  "geometry": {"coordinates":[151.20892334000001,-33.8741645813],"type":"Point"}
}