{
  "type": "Feature",
  "properties": {
    "iso:country":"AU",
    "sg:address":"350 Auburn St",
    "sg:city":"Goulburn",
    "sg:classifiers":[
        {
            "category":"Personal",
            "subcategory":"Beauty Salon",
            "type":"Services"
        }
    ],
    "sg:phone":"+61 2 4821 4890",
    "sg:postcode":"2580",
    "sg:province":"NSW",
    "sg:tags":[
        "hairdresser"
    ],
    "wof:name":"Jason's Barber Shop & Beardry",
    "wof:placetype":"venue"
},
  "geometry": {"coordinates":[149.72093200699999,-34.7514076233],"type":"Point"}
}