{
  "type": "Feature",
  "properties": {
    "iso:country":"AU",
    "sg:address":"N3/ 94 Bundall Rd",
    "sg:city":"Bundall",
    "sg:classifiers":[
        {
            "category":"Shopping",
            "subcategory":"Jewelry",
            "type":"Retail Goods"
        }
    ],
    "sg:phone":"+61 7 5592 0099",
    "sg:postcode":"4217",
    "sg:province":"QLD",
    "sg:tags":[
        "merchant",
        "gem"
    ],
    "wof:name":"The Rock Shop (Gold Coast)",
    "wof:placetype":"venue"
},
  "geometry": {"coordinates":[153.41291809099999,-28.0056114197],"type":"Point"}
}