{
  "type": "Feature",
  "properties": {
    "addr:full":"240 Main Rd McLaren Vale SA 5171",
    "addr:housenumber":"240",
    "addr:postcode":"5171",
    "addr:street":"Main Rd",
    "iso:country":"AU",
    "sg:address":"240 Main Rd",
    "sg:city":"McLaren Vale",
    "sg:classifiers":[
        {
            "category":"Personal",
            "subcategory":"Shoe Repair & Shine",
            "type":"Services"
        }
    ],
    "sg:phone":"+61 8 8323 8220",
    "sg:postcode":"5171",
    "sg:province":"SA",
    "sg:tags":[
        "footwear"
    ],
    "wof:name":"Southern Deluxe Dry Cleaners",
    "wof:placetype":"venue"
},
  "geometry": {"coordinates":[138.53317260700001,-35.2116355896],"type":"Point"}
}