{
  "type": "Feature",
  "properties": {
    "addr:full":"10 Graystone St Tingalpa QLD 4173",
    "addr:housenumber":"10",
    "addr:postcode":"4173",
    "addr:street":"Graystone St",
    "iso:country":"AU",
    "sg:address":"10 Graystone St",
    "sg:city":"Tingalpa",
    "sg:classifiers":[
        {
            "category":"Autos & Motor Vehicles",
            "subcategory":"Boat Sales",
            "type":"Retail Goods"
        }
    ],
    "sg:phone":"+61 7 3240 3764",
    "sg:postcode":"4173",
    "sg:province":"QLD",
    "sg:tags":[
        "dictating",
        "machine"
    ],
    "wof:name":"Philips",
    "wof:placetype":"venue"
},
  "geometry": {"coordinates":[153.115036011,-27.4738311768],"type":"Point"}
}