{
  "type": "Feature",
  "properties": {
    "addr:full":"44 Lowe St Nambour QLD 4560",
    "addr:housenumber":"44",
    "addr:postcode":"4560",
    "addr:street":"Lowe St",
    "iso:country":"AU",
    "sg:address":"44 Lowe St",
    "sg:city":"Nambour",
    "sg:classifiers":[
        {
            "category":"Shopping",
            "subcategory":"Optical Goods",
            "type":"Retail Goods"
        }
    ],
    "sg:phone":"+61 7 5476 2333",
    "sg:postcode":"4560",
    "sg:province":"QLD",
    "sg:tags":[
        "supply"
    ],
    "wof:name":"D & S Eyewear",
    "wof:placetype":"venue"
},
  "geometry": {"coordinates":[152.960494995,-26.6259498596],"type":"Point"}
}