{
  "type": "Feature",
  "properties": {
    "iso:country":"AU",
    "sg:address":"12 Macpherson St",
    "sg:city":"Carnamah",
    "sg:classifiers":[
        {
            "category":"Food & Beverages",
            "subcategory":"Specialty",
            "type":"Retail Goods"
        }
    ],
    "sg:phone":"+61 8 9951 1133",
    "sg:postcode":"6517",
    "sg:province":"WA",
    "sg:tags":[
        "product",
        "health"
    ],
    "wof:name":"Bush Basket",
    "wof:placetype":"venue"
},
  "geometry": {"coordinates":[115.886711,-29.688452],"type":"Point"}
}