{
  "type": "Feature",
  "properties": {
    "addr:full":"4 Bungan St Mona Vale NSW 2103",
    "addr:housenumber":"4",
    "addr:postcode":"2103",
    "addr:street":"Bungan St",
    "iso:country":"AU",
    "sg:address":"4 Bungan St",
    "sg:city":"Mona Vale",
    "sg:classifiers":[
        {
            "category":"Fast Food",
            "type":"Food & Drink"
        }
    ],
    "sg:phone":"+61 2 9997 5961",
    "sg:postcode":"2103",
    "sg:province":"NSW",
    "sg:tags":[
        "away",
        "take"
    ],
    "wof:name":"Aces Charcoal Chicken",
    "wof:placetype":"venue"
},
  "geometry": {"coordinates":[151.302566528,-33.6770019531],"type":"Point"}
}