{
  "type": "Feature",
  "properties": {
    "addr:full":"49 Keona Rd McDowall QLD 4053",
    "addr:housenumber":"49",
    "addr:postcode":"4053",
    "addr:street":"Keona Rd",
    "iso:country":"AU",
    "sg:address":"49 Keona Rd",
    "sg:city":"McDowall",
    "sg:classifiers":[
        {
            "category":"Home & Garden",
            "subcategory":"Building Materials",
            "type":"Retail Goods"
        }
    ],
    "sg:phone":"+61 7 3353 4479",
    "sg:postcode":"4053",
    "sg:province":"QLD",
    "sg:tags":[
        "merchant",
        "glass",
        "glazier"
    ],
    "wof:name":"Brisbane Glazing & Property Maintenance",
    "wof:placetype":"venue"
},
  "geometry": {"coordinates":[152.98730468799999,-27.3731822968],"type":"Point"}
}