{
  "type": "Feature",
  "properties": {
    "iso:country":"AU",
    "sg:address":"143 Native Plains Rd",
    "sg:city":"Sassafras",
    "sg:classifiers":[
        {
            "category":"Farming",
            "subcategory":"Orchard",
            "type":"Manufacturing & Wholesale Goods"
        }
    ],
    "sg:phone":"+61 3 6426 7373",
    "sg:postcode":"7307",
    "sg:province":"TAS",
    "sg:tags":[
        "pear",
        "apple",
        "grower"
    ],
    "wof:name":"Sassafras Orchards",
    "wof:placetype":"venue"
},
  "geometry": {"coordinates":[146.468781,-41.270687],"type":"Point"}
}