{
  "type": "Feature",
  "properties": {
    "addr:full":"Benowa Gardens Shopping Centre, Cnr Ashmore & Benowa Rds Benowa QLD 4217",
    "addr:postcode":"4217",
    "addr:street":"Cnr",
    "iso:country":"AU",
    "sg:address":"Benowa Gardens Shopping Centre, Cnr Ashmore & Benowa Rds",
    "sg:city":"Benowa",
    "sg:classifiers":[
        {
            "category":"Ice Cream",
            "type":"Food & Drink"
        }
    ],
    "sg:phone":"+61 7 5597 0000",
    "sg:postcode":"4217",
    "sg:province":"QLD",
    "sg:tags":[
        "specialised",
        "fitting",
        "lady",
        "wear"
    ],
    "wof:name":"Liz Clift Boutique",
    "wof:placetype":"venue"
},
  "geometry": {"coordinates":[153.39222717300001,-28.0099372864],"type":"Point"}
}