{
  "type": "Feature",
  "properties": {
    "addr:full":"Lvl2/ 8 Eastern Rd South Melbourne VIC 3205",
    "addr:housenumber":"8",
    "addr:postcode":"3205",
    "addr:street":"Eastern Rd",
    "iso:country":"AU",
    "sg:address":"Lvl2/ 8 Eastern Rd",
    "sg:city":"South Melbourne",
    "sg:classifiers":[
        {
            "category":"Shopping",
            "subcategory":"Computers & Home Electronics",
            "type":"Retail Goods"
        }
    ],
    "sg:phone":"+61 3 9690 5537",
    "sg:postcode":"3205",
    "sg:province":"VIC",
    "sg:tags":[
        "equipment",
        "multimedia"
    ],
    "sg:website":"http://www.discready.com.au",
    "wof:name":"Disc Ready",
    "wof:placetype":"venue"
},
  "geometry": {"coordinates":[144.96388200000001,-37.830994],"type":"Point"}
}