{
  "type": "Feature",
  "properties": {
    "iso:country":"AU",
    "sg:address":"377 Edward St",
    "sg:city":"Wagga Wagga",
    "sg:classifiers":[
        {
            "category":"Wholesale",
            "subcategory":"Farm Supplies",
            "type":"Manufacturing & Wholesale Goods"
        }
    ],
    "sg:phone":"+61 2 6925 0395",
    "sg:postcode":"2650",
    "sg:province":"NSW",
    "sg:tags":[
        "feed",
        "supplement",
        "stock"
    ],
    "wof:name":"Hindys Stockfeeds",
    "wof:placetype":"venue"
},
  "geometry": {"coordinates":[147.34765625,-35.1157035828],"type":"Point"}
}