{
  "type": "Feature",
  "properties": {
    "addr:full":"153 Frederick St Toowong QLD 4066",
    "addr:housenumber":"153",
    "addr:postcode":"4066",
    "addr:street":"Frederick St",
    "iso:country":"AU",
    "sg:address":"153 Frederick St",
    "sg:city":"Toowong",
    "sg:classifiers":[
        {
            "category":"Professional",
            "subcategory":"Art Services",
            "type":"Services"
        }
    ],
    "sg:phone":"+61 411 885 840",
    "sg:postcode":"4066",
    "sg:province":"QLD",
    "sg:tags":[
        "decorator",
        "painter"
    ],
    "wof:name":"Hestehauge-Murphy",
    "wof:placetype":"venue"
},
  "geometry": {"coordinates":[152.98626709000001,-27.4721088409],"type":"Point"}
}