{
  "type": "Feature",
  "properties": {
    "addr:full":"12 Falkinder Ave Paradise Point QLD 4216",
    "addr:housenumber":"12",
    "addr:postcode":"4216",
    "addr:street":"Falkinder Ave",
    "iso:country":"AU",
    "sg:address":"12 Falkinder Ave",
    "sg:city":"Paradise Point",
    "sg:classifiers":[
        {
            "category":"Organizations",
            "subcategory":"Professional Association",
            "type":"Services"
        }
    ],
    "sg:phone":"+61 7 5537 9724",
    "sg:postcode":"4216",
    "sg:province":"QLD",
    "sg:tags":[
        "web",
        "internet"
    ],
    "wof:name":"Webco",
    "wof:placetype":"venue"
},
  "geometry": {"coordinates":[153.39494323700001,-27.8867473602],"type":"Point"}
}