{
  "type": "Feature",
  "properties": {
    "addr:full":"16- 20 Glen Innes Rd Inverell NSW 2360",
    "addr:housenumber":"20",
    "addr:postcode":"2360",
    "addr:street":"Glen Innes Rd",
    "iso:country":"AU",
    "sg:address":"16- 20 Glen Innes Rd",
    "sg:city":"Inverell",
    "sg:classifiers":[
        {
            "category":"Retail",
            "subcategory":"Storage",
            "type":"Services"
        }
    ],
    "sg:phone":"+61 2 6722 2202",
    "sg:postcode":"2360",
    "sg:province":"NSW",
    "wof:name":"Inverell Self Storage",
    "wof:placetype":"venue"
},
  "geometry": {"coordinates":[151.113555908,-29.776309967],"type":"Point"}
}