{
  "type": "Feature",
  "properties": {
    "iso:country":"AU",
    "sg:address":"88 Massingham St",
    "sg:city":"Kellerberrin",
    "sg:classifiers":[
        {
            "category":"Arts & Performance",
            "subcategory":"Art Gallery",
            "type":"Entertainment"
        }
    ],
    "sg:phone":"+61 8 9045 4739",
    "sg:postcode":"6410",
    "sg:province":"WA",
    "wof:name":"International Art Space Kellerberrin Australia",
    "wof:placetype":"venue"
},
  "geometry": {"coordinates":[117.723152161,-31.6334342957],"type":"Point"}
}