{
  "type": "Feature",
  "properties": {
    "iso:country":"AU",
    "sg:address":"Wilson St",
    "sg:city":"Collarenebri",
    "sg:classifiers":[
        {
            "category":"Professional",
            "type":"Services"
        }
    ],
    "sg:phone":"+61 2 6756 2263",
    "sg:postcode":"2833",
    "sg:province":"NSW",
    "sg:tags":[
        "transport"
    ],
    "wof:name":"Cutlers Freight",
    "wof:placetype":"venue"
},
  "geometry": {"coordinates":[148.576263428,-29.5447788239],"type":"Point"}
}