{
  "type": "Feature",
  "properties": {
    "iso:country":"AU",
    "sg:address":"7 Kenna St",
    "sg:city":"Orange",
    "sg:classifiers":[
        {
            "category":"Home & Garden",
            "subcategory":"Building Materials",
            "type":"Retail Goods"
        }
    ],
    "sg:phone":"+61 2 6361 9406",
    "sg:postcode":"2800",
    "sg:province":"NSW",
    "sg:tags":[
        "lawn",
        "cutting",
        "maintenance"
    ],
    "wof:name":"Garden Guru Orange",
    "wof:placetype":"venue"
},
  "geometry": {"coordinates":[149.08244323700001,-33.2904014587],"type":"Point"}
}