{
  "type": "Feature",
  "properties": {
    "addr:full":"37 Avonmore Ave Trinity Gardens SA 5068",
    "addr:housenumber":"37",
    "addr:postcode":"5068",
    "addr:street":"Avonmore Ave Trinity Gardens",
    "iso:country":"AU",
    "sg:address":"37 Avonmore Ave",
    "sg:city":"Trinity Gardens",
    "sg:classifiers":[
        {
            "category":"Home & Garden",
            "subcategory":"Building Materials",
            "type":"Retail Goods"
        }
    ],
    "sg:phone":"+61 419 826 420",
    "sg:postcode":"5068",
    "sg:province":"SA",
    "sg:tags":[
        "concrete",
        "gutter",
        "kerb"
    ],
    "wof:name":"D'Angelo Concrete Contractors Pty Ltd",
    "wof:placetype":"venue"
},
  "geometry": {"coordinates":[138.64474487300001,-34.9104347229],"type":"Point"}
}