{
  "type": "Feature",
  "properties": {
    "addr:full":"620 Kessels Rd MacGregor QLD 4109",
    "addr:housenumber":"620",
    "addr:postcode":"4109",
    "addr:street":"Kessels Rd",
    "iso:country":"AU",
    "sg:address":"620 Kessels Rd",
    "sg:city":"MacGregor",
    "sg:classifiers":[
        {
            "category":"Health Services",
            "subcategory":"Doctor",
            "type":"Services"
        }
    ],
    "sg:phone":"+61 7 3349 6444",
    "sg:postcode":"4109",
    "sg:province":"QLD",
    "sg:tags":[
        "medical",
        "practitioner"
    ],
    "wof:name":"Russell Terry Dr.",
    "wof:placetype":"venue"
},
  "geometry": {"coordinates":[153.07426452600001,-27.5616474152],"type":"Point"}
}