{
  "type": "Feature",
  "properties": {
    "addr:full":"Unit 5/ 45 Ardross St Applecross WA 6153",
    "addr:housenumber":"45",
    "addr:postcode":"6153",
    "addr:street":"Ardross St",
    "iso:country":"AU",
    "sg:address":"Unit 5/ 45 Ardross St",
    "sg:city":"Applecross",
    "sg:classifiers":[
        {
            "category":"Professional",
            "subcategory":"Accounting & Tax Preparation",
            "type":"Services"
        }
    ],
    "sg:phone":"+61 8 9316 4588",
    "sg:postcode":"6153",
    "sg:province":"WA",
    "sg:tags":[
        "accountant",
        "auditor"
    ],
    "wof:name":"GCM Group",
    "wof:placetype":"venue"
},
  "geometry": {"coordinates":[115.835098,-32.010941],"type":"Point"}
}