{
  "type": "Feature",
  "properties": {
    "addr:full":"Marshall St Fortitude Valley QLD 4006",
    "addr:postcode":"4006",
    "addr:street":"Marshall St",
    "iso:country":"AU",
    "sg:address":"Marshall St",
    "sg:city":"Fortitude Valley",
    "sg:classifiers":[
        {
            "category":"Food & Beverages",
            "subcategory":"Supermarket",
            "type":"Retail Goods"
        }
    ],
    "sg:phone":"+61 7 3852 1946",
    "sg:postcode":"4006",
    "sg:province":"QLD",
    "sg:tags":[
        "grocery",
        "store"
    ],
    "wof:name":"Garboro Asian Supermarket",
    "wof:placetype":"venue"
},
  "geometry": {"coordinates":[153.034622192,-27.4594764709],"type":"Point"}
}