{
  "type": "Feature",
  "properties": {
    "addr:full":"1 / 8 Granter St Brighton East VIC 3187",
    "addr:housenumber":"/ 8",
    "addr:postcode":"3187",
    "addr:street":"Granter St",
    "iso:country":"AU",
    "sg:address":"1 / 8 Granter St",
    "sg:city":"Brighton East",
    "sg:classifiers":[
        {
            "category":"Professional",
            "subcategory":"Computer Services",
            "type":"Services"
        }
    ],
    "sg:phone":"+61 3 9592 9993",
    "sg:postcode":"3187",
    "sg:province":"VIC",
    "sg:tags":[
        "technical",
        "support"
    ],
    "wof:name":"Computer Rehabilitation",
    "wof:placetype":"venue"
},
  "geometry": {"coordinates":[145.01675415,-37.9092178345],"type":"Point"}
}