{
  "type": "Feature",
  "properties": {
    "addr:full":"35 Foundary Rd Seven Hills NSW 2147",
    "addr:housenumber":"35",
    "addr:postcode":"2147",
    "addr:street":"Foundary Rd",
    "iso:country":"AU",
    "sg:address":"35 Foundary Rd",
    "sg:city":"Seven Hills",
    "sg:classifiers":[
        {
            "category":"Building & Trades",
            "subcategory":"Construction",
            "type":"Services"
        }
    ],
    "sg:phone":"+61 2 9674 8451",
    "sg:postcode":"2147",
    "sg:province":"NSW",
    "sg:tags":[
        "pool",
        "swimming"
    ],
    "wof:name":"Blue Sea Industries",
    "wof:placetype":"venue"
},
  "geometry": {"coordinates":[150.95512390100001,-33.7702865601],"type":"Point"}
}