{
  "type": "Feature",
  "properties": {
    "addr:full":"383 Pitt St Sydney NSW 2000",
    "addr:housenumber":"383",
    "addr:postcode":"2000",
    "addr:street":"Pitt St",
    "iso:country":"AU",
    "sg:address":"383 Pitt St",
    "sg:city":"Sydney",
    "sg:classifiers":[
        {
            "category":"Health Services",
            "subcategory":"Health Practitioner",
            "type":"Services"
        }
    ],
    "sg:phone":"+61 403 394 546",
    "sg:postcode":"2000",
    "sg:province":"NSW",
    "sg:tags":[
        "dietitian"
    ],
    "wof:name":"Sydney Nutrition",
    "wof:placetype":"venue"
},
  "geometry": {"coordinates":[151.20765685999999,-33.8765296936],"type":"Point"}
}