{
  "type": "Feature",
  "properties": {
    "addr:full":"310 Great Eastern Hwy Midland WA 6056",
    "addr:housenumber":"310",
    "addr:postcode":"6056",
    "addr:street":"Great Eastern Hwy",
    "iso:country":"AU",
    "sg:address":"310 Great Eastern Hwy",
    "sg:city":"Midland",
    "sg:classifiers":[
        {
            "category":"Professional",
            "subcategory":"Accounting & Tax Preparation",
            "type":"Services"
        }
    ],
    "sg:phone":"+61 8 9274 5575",
    "sg:postcode":"6056",
    "sg:province":"WA",
    "sg:tags":[
        "consultant",
        "taxation"
    ],
    "wof:name":"ITP The Income Tax Professionals",
    "wof:placetype":"venue"
},
  "geometry": {"coordinates":[116.01235961899999,-31.8918056488],"type":"Point"}
}