{
  "type": "Feature",
  "properties": {
    "iso:country":"AU",
    "sg:address":"Unit 2/ 30 Smith St",
    "sg:city":"Capalaba",
    "sg:classifiers":[
        {
            "category":"Building & Trades",
            "subcategory":"Construction",
            "type":"Services"
        }
    ],
    "sg:phone":"+61 7 3245 3715",
    "sg:postcode":"4157",
    "sg:province":"QLD",
    "sg:tags":[
        "fencing",
        "contractor"
    ],
    "wof:name":"River City Aluminium",
    "wof:placetype":"venue"
},
  "geometry": {"coordinates":[153.19932556099999,-27.5289649963],"type":"Point"}
}