{
  "type": "Feature",
  "properties": {
    "addr:full":"Pathology Suite, 297-299 Blaxcell Rd Granville NSW 1830",
    "addr:housenumber":"297-299",
    "addr:postcode":"1830",
    "addr:street":"Blaxcell Rd",
    "iso:country":"AU",
    "sg:address":"Pathology Suite, 297-299 Blaxcell Rd",
    "sg:city":"Granville",
    "sg:classifiers":[
        {
            "category":"Health Services",
            "subcategory":"Doctor",
            "type":"Services"
        }
    ],
    "sg:phone":"+61 2 9637 6384",
    "sg:postcode":"1830",
    "sg:province":"NSW",
    "sg:tags":[
        "medical",
        "practitioner"
    ],
    "wof:name":"SDS Pathology",
    "wof:placetype":"venue"
},
  "geometry": {"coordinates":[151.00816345199999,-33.8538780212],"type":"Point"}
}