{
  "type": "Feature",
  "properties": {
    "addr:full":"Warringah Rd Beacon Hill NSW 2100",
    "addr:postcode":"2100",
    "addr:street":"Warringah Rd",
    "iso:country":"AU",
    "sg:address":"Warringah Rd",
    "sg:city":"Beacon Hill",
    "sg:classifiers":[
        {
            "category":"Building & Trades",
            "subcategory":"Plumbing",
            "type":"Services"
        }
    ],
    "sg:phone":"+61 411 197 377",
    "sg:postcode":"2100",
    "sg:province":"NSW",
    "sg:tags":[
        "plumber",
        "gasfitters"
    ],
    "wof:name":"M.J.M. Plumbing (NSW) Pty Ltd",
    "wof:placetype":"venue"
},
  "geometry": {"coordinates":[151.25944519000001,-33.753578186],"type":"Point"}
}