{
  "type": "Feature",
  "properties": {
    "addr:full":"Cnr Elbow & Tozer Sts Kempsey NSW 2440",
    "addr:postcode":"2440",
    "addr:street":"Cnr;Sts",
    "iso:country":"AU",
    "sg:address":"Cnr Elbow & Tozer Sts",
    "sg:city":"Kempsey",
    "sg:classifiers":[
        {
            "category":"Wholesale",
            "subcategory":"Electrical",
            "type":"Manufacturing & Wholesale Goods"
        }
    ],
    "sg:phone":"+61 2 6562 6766",
    "sg:postcode":"2440",
    "sg:province":"NSW",
    "sg:tags":[
        "wholesaler",
        "mfrs",
        "accessory"
    ],
    "wof:name":"Cetnaj Pty Ltd",
    "wof:placetype":"venue"
},
  "geometry": {"coordinates":[152.83042900000001,-31.079786],"type":"Point"}
}