{
  "type": "Feature",
  "properties": {
    "addr:full":"18b Sherwood Rd Port Macquarie NSW 2444",
    "addr:housenumber":"18b",
    "addr:postcode":"2444",
    "addr:street":"Sherwood Rd",
    "iso:country":"AU",
    "sg:address":"18b Sherwood Rd",
    "sg:city":"Port Macquarie",
    "sg:classifiers":[
        {
            "category":"Professional",
            "subcategory":"Art Services",
            "type":"Services"
        }
    ],
    "sg:phone":"+61 2 6581 5051",
    "sg:postcode":"2444",
    "sg:province":"NSW",
    "sg:tags":[
        "decorator",
        "painter"
    ],
    "wof:name":"Hastings Valley Painters & Decorators",
    "wof:placetype":"venue"
},
  "geometry": {"coordinates":[152.87545800000001,-31.447716],"type":"Point"}
}