{
  "type": "Feature",
  "properties": {
    "iso:country":"AU",
    "sg:address":"18b Sherwood Rd",
    "sg:city":"Port Macquarie",
    "sg:classifiers":[
        {
            "category":"Professional",
            "subcategory":"Art Services",
            "type":"Services"
        }
    ],
    "sg:phone":"+61 2 6581 5051",
    "sg:postcode":"2444",
    "sg:province":"NSW",
    "sg:tags":[
        "decorator",
        "painter"
    ],
    "wof:name":"Hastings Valley Painters & Decorators",
    "wof:placetype":"venue"
},
  "geometry": {"coordinates":[152.875458,-31.447716],"type":"Point"}
}