{
  "type": "Feature",
  "properties": {
    "addr:full":"Lvl11/ 2 Bligh St Sydney NSW 2000",
    "addr:housenumber":"2",
    "addr:postcode":"2000",
    "addr:street":"Bligh St",
    "iso:country":"AU",
    "sg:address":"Lvl11/ 2 Bligh St",
    "sg:city":"Sydney",
    "sg:classifiers":[
        {
            "category":"Professional",
            "subcategory":"Accounting & Tax Preparation",
            "type":"Services"
        }
    ],
    "sg:phone":"+61 2 9232 8536",
    "sg:postcode":"2000",
    "sg:province":"NSW",
    "sg:tags":[
        "accountant",
        "auditor"
    ],
    "wof:name":"Universal Consolidated Group",
    "wof:placetype":"venue"
},
  "geometry": {"coordinates":[151.211135864,-33.8649597168],"type":"Point"}
}