{
  "type": "Feature",
  "properties": {
    "iso:country":"AU",
    "sg:address":"48 Tongarra Rd",
    "sg:city":"Albion Park Rail",
    "sg:classifiers":[
        {
            "category":"Building & Trades",
            "subcategory":"Construction",
            "type":"Services"
        }
    ],
    "sg:phone":"+61 2 4256 6360",
    "sg:postcode":"2527",
    "sg:province":"NSW",
    "sg:tags":[
        "decking",
        "contractor"
    ],
    "wof:name":"Joukador V G & A J",
    "wof:placetype":"venue"
},
  "geometry": {"coordinates":[150.79876709000001,-34.5685691833],"type":"Point"}
}