{
  "type": "Feature",
  "properties": {
    "iso:country":"AU",
    "sg:address":"105 Redcliffe Pde",
    "sg:city":"Redcliffe",
    "sg:classifiers":[
        {
            "category":"Shopping",
            "subcategory":"Shoes",
            "type":"Retail Goods"
        }
    ],
    "sg:phone":"+61 7 3284 8377",
    "sg:postcode":"4020",
    "sg:province":"QLD",
    "sg:tags":[
        "footwear"
    ],
    "wof:name":"Footwear & Clothing Crisis Liquidators",
    "wof:placetype":"venue"
},
  "geometry": {"coordinates":[153.11523399999999,-27.228085],"type":"Point"}
}