{
  "type": "Feature",
  "properties": {
    "addr:full":"260 Como (West) Pde Parkdale VIC 3195",
    "addr:housenumber":"260",
    "addr:postcode":"3195",
    "addr:street":"Como West Pde",
    "iso:country":"AU",
    "sg:address":"260 Como (West) Pde",
    "sg:city":"Parkdale",
    "sg:classifiers":[
        {
            "category":"Cafe",
            "type":"Food & Drink"
        }
    ],
    "sg:phone":"+61 3 9587 2733",
    "sg:postcode":"3195",
    "sg:province":"VIC",
    "wof:name":"Basic Black Cafe",
    "wof:placetype":"venue"
},
  "geometry": {"coordinates":[145.07623290999999,-37.9934692383],"type":"Point"}
}