{
  "type": "Feature",
  "properties": {
    "iso:country":"AU",
    "sg:address":"Sd 4/ 5 Toohey St",
    "sg:city":"Portsmith",
    "sg:classifiers":[
        {
            "category":"Building & Trades",
            "subcategory":"Construction",
            "type":"Services"
        }
    ],
    "sg:phone":"+61 438 453 054",
    "sg:postcode":"4870",
    "sg:province":"QLD",
    "sg:tags":[
        "window",
        "timber"
    ],
    "wof:name":"John Horner Design",
    "wof:placetype":"venue"
},
  "geometry": {"coordinates":[145.76167297399999,-16.9417266846],"type":"Point"}
}