{
  "type": "Feature",
  "properties": {
    "addr:full":"12 Endeavour Drv Port Adelaide SA 5015",
    "addr:housenumber":"12",
    "addr:postcode":"5015",
    "addr:street":"Endeavour Drv",
    "iso:country":"AU",
    "sg:address":"12 Endeavour Drv",
    "sg:city":"Port Adelaide",
    "sg:classifiers":[
        {
            "category":"Wholesale",
            "subcategory":"Furniture",
            "type":"Manufacturing & Wholesale Goods"
        }
    ],
    "sg:phone":"+61 8 8240 1111",
    "sg:postcode":"5015",
    "sg:province":"SA",
    "sg:tags":[
        "wholesaler",
        "mfrs"
    ],
    "wof:name":"Peacock Furniture Pty Ltd",
    "wof:placetype":"venue"
},
  "geometry": {"coordinates":[138.50474548299999,-34.852935791],"type":"Point"}
}