{
  "type": "Feature",
  "properties": {
    "iso:country":"AU",
    "sg:address":"Fcty 6/ 55 Wheelers La",
    "sg:city":"Dubbo",
    "sg:classifiers":[
        {
            "category":"Professional",
            "type":"Services"
        }
    ],
    "sg:phone":"+61 2 6884 4617",
    "sg:postcode":"2830",
    "sg:province":"NSW",
    "sg:tags":[
        "coating",
        "powder"
    ],
    "wof:name":"Dubbo Powder Coating & Sand Blasting",
    "wof:placetype":"venue"
},
  "geometry": {"coordinates":[148.63075256400001,-32.2478408813],"type":"Point"}
}