{
  "type": "Feature",
  "properties": {
    "iso:country":"AU",
    "sg:address":"1160 Nepean Hwy",
    "sg:city":"Cheltenham",
    "sg:classifiers":[
        {
            "category":"Health Services",
            "subcategory":"Health Practitioner",
            "type":"Services"
        }
    ],
    "sg:phone":"+61 1300 366 284",
    "sg:postcode":"3192",
    "sg:province":"VIC",
    "sg:tags":[
        "physiotherapist"
    ],
    "wof:name":"Backfocus Physiotherapy",
    "wof:placetype":"venue"
},
  "geometry": {"coordinates":[145.05299377399999,-37.9595375061],"type":"Point"}
}