{
  "type": "Feature",
  "properties": {
    "addr:full":"3752 Pt Nepean Rd Portsea VIC 3944",
    "addr:housenumber":"3752",
    "addr:postcode":"3944",
    "addr:street":"Pt Nepean Rd",
    "iso:country":"AU",
    "sg:address":"3752 Pt Nepean Rd",
    "sg:city":"Portsea",
    "sg:classifiers":[
        {
            "category":"Airport",
            "subcategory":"International",
            "type":"Transportation"
        }
    ],
    "sg:phone":"+61 3 5984 3155",
    "sg:postcode":"3944",
    "sg:province":"VIC",
    "sg:tags":[
        "diving",
        "commercial"
    ],
    "wof:name":"D I S Pty Ltd",
    "wof:placetype":"venue"
},
  "geometry": {"coordinates":[144.71453857399999,-38.3200531006],"type":"Point"}
}