{
  "type": "Feature",
  "properties": {
    "iso:country":"AU",
    "sg:address":"38 Thompson St",
    "sg:city":"Bowen Hills",
    "sg:classifiers":[
        {
            "category":"Building & Trades",
            "subcategory":"Construction",
            "type":"Services"
        }
    ],
    "sg:phone":"+61 7 3252 3949",
    "sg:postcode":"4006",
    "sg:province":"QLD",
    "sg:tags":[
        "contractor"
    ],
    "wof:name":"Bailey R N & Sons Pty Ltd",
    "wof:placetype":"venue"
},
  "geometry": {"coordinates":[153.04051208499999,-27.4402427673],"type":"Point"}
}