{
  "type": "Feature",
  "properties": {
    "iso:country":"AU",
    "sg:address":"17 Yawla St",
    "sg:city":"Bentleigh",
    "sg:classifiers":[
        {
            "category":"Building & Trades",
            "subcategory":"Construction",
            "type":"Services"
        }
    ],
    "sg:phone":"+61 3 9557 6347",
    "sg:postcode":"3204",
    "sg:province":"VIC",
    "sg:tags":[
        "contractor"
    ],
    "wof:name":"B.J. Brown Homes",
    "wof:placetype":"venue"
},
  "geometry": {"coordinates":[145.026291,-37.913345],"type":"Point"}
}