{
  "type": "Feature",
  "properties": {
    "iso:country":"AU",
    "sg:address":"190 Boundary Rd",
    "sg:city":"Bentleigh",
    "sg:classifiers":[
        {
            "category":"Sports & Exercise",
            "subcategory":"Gym",
            "type":"Entertainment"
        }
    ],
    "sg:phone":"+61 3 9570 7394",
    "sg:postcode":"3204",
    "sg:province":"VIC",
    "sg:tags":[
        "health",
        "fitness"
    ],
    "wof:name":"Bentleigh East Swim Centre",
    "wof:placetype":"venue"
},
  "geometry": {"coordinates":[145.026962,-37.91193],"type":"Point"}
}