{
  "type": "Feature",
  "properties": {
    "addr:full":"17 Stanley St Concord NSW 2137",
    "addr:housenumber":"17",
    "addr:postcode":"2137",
    "addr:street":"Stanley St",
    "iso:country":"AU",
    "sg:address":"17 Stanley St",
    "sg:city":"Concord",
    "sg:classifiers":[
        {
            "category":"Health Services",
            "subcategory":"Health Practitioner",
            "type":"Services"
        }
    ],
    "sg:phone":"+61 2 9744 5304",
    "sg:postcode":"2137",
    "sg:province":"NSW",
    "sg:tags":[
        "psychologist"
    ],
    "wof:name":"Sydney D & D",
    "wof:placetype":"venue"
},
  "geometry": {"coordinates":[151.106033325,-33.8633613586],"type":"Point"}
}