{
  "type": "Feature",
  "properties": {
    "addr:full":"32 - 42 Bradley St Goulburn NSW 2580",
    "addr:housenumber":"42",
    "addr:postcode":"2580",
    "addr:street":"Bradley St",
    "iso:country":"AU",
    "sg:address":"32 - 42 Bradley St",
    "sg:city":"Goulburn",
    "sg:classifiers":[
        {
            "category":"Autos & Motor Vehicles",
            "subcategory":"Automobile Sales",
            "type":"Retail Goods"
        }
    ],
    "sg:phone":"+61 2 4822 2010",
    "sg:postcode":"2580",
    "sg:province":"NSW",
    "sg:tags":[
        "car",
        "new"
    ],
    "wof:name":"Lilac City Cars",
    "wof:placetype":"venue"
},
  "geometry": {"coordinates":[149.723587036,-34.7502403259],"type":"Point"}
}