{
  "type": "Feature",
  "properties": {
    "iso:country":"AU",
    "sg:address":"71 Market St",
    "sg:city":"Mudgee",
    "sg:classifiers":[
        {
            "category":"Food & Beverages",
            "subcategory":"Fruits & Vegetables",
            "type":"Retail Goods"
        }
    ],
    "sg:phone":"+61 2 6372 1229",
    "sg:postcode":"2850",
    "sg:province":"NSW",
    "sg:tags":[
        "wholesale"
    ],
    "wof:name":"Bryant D G & J M",
    "wof:placetype":"venue"
},
  "geometry": {"coordinates":[149.57556199999999,-32.587852],"type":"Point"}
}