{
  "type": "Feature",
  "properties": {
    "addr:full":"Cnr Bedford St & Eastern Pde Gillman SA 5013",
    "addr:postcode":"5013",
    "addr:street":"Cnr Bedford St & Eastern Pde",
    "iso:country":"AU",
    "sg:address":"Cnr Bedford St & Eastern Pde",
    "sg:city":"Gillman",
    "sg:classifiers":[
        {
            "category":"Home & Garden",
            "subcategory":"Building Materials",
            "type":"Retail Goods"
        }
    ],
    "sg:phone":"+61 8 8447 9666",
    "sg:postcode":"5013",
    "sg:province":"SA",
    "sg:tags":[
        "roofing"
    ],
    "wof:name":"BHP Building Products",
    "wof:placetype":"venue"
},
  "geometry": {"coordinates":[138.530227661,-34.835559845],"type":"Point"}
}