{
  "type": "Feature",
  "properties": {
    "iso:country":"AU",
    "sg:address":"7 Rina Crt",
    "sg:city":"Stephens",
    "sg:classifiers":[
        {
            "category":"Food & Beverages",
            "subcategory":"Bakery",
            "type":"Retail Goods"
        }
    ],
    "sg:phone":"+61 7 5594 2850",
    "sg:postcode":"4227",
    "sg:province":"QLD",
    "sg:tags":[
        "baker"
    ],
    "wof:name":"Lorraine Bakery",
    "wof:placetype":"venue"
},
  "geometry": {"coordinates":[153.41113281200001,-28.1007480621],"type":"Point"}
}