{
  "type": "Feature",
  "properties": {
    "addr:full":"Level 5/ 131 MacQuarie St Sydney NSW 2000",
    "addr:housenumber":"/ 131",
    "addr:postcode":"2000",
    "addr:street":"Macquarie St",
    "iso:country":"AU",
    "sg:address":"Level 5/ 131 MacQuarie St",
    "sg:city":"Sydney",
    "sg:classifiers":[
        {
            "category":"Real Estate",
            "subcategory":"Developer",
            "type":"Services"
        }
    ],
    "sg:phone":"+61 2 9251 7100",
    "sg:postcode":"2000",
    "sg:province":"NSW",
    "sg:tags":[
        "development"
    ],
    "wof:name":"Ticor Developments Pty Ltd",
    "wof:placetype":"venue"
},
  "geometry": {"coordinates":[151.212646484,-33.8641242981],"type":"Point"}
}