{
  "type": "Feature",
  "properties": {
    "addr:full":"2 Cojo Pl Dandenong South VIC 3164",
    "addr:housenumber":"2",
    "addr:postcode":"3164",
    "addr:street":"Cojo Pl",
    "iso:country":"AU",
    "sg:address":"2 Cojo Pl",
    "sg:city":"Dandenong South",
    "sg:classifiers":[
        {
            "category":"Shopping",
            "subcategory":"Crafts & Fabrics",
            "type":"Retail Goods"
        }
    ],
    "sg:phone":"+61 3 8791 1000",
    "sg:postcode":"3164",
    "sg:province":"VIC",
    "sg:tags":[
        "perforating",
        "perforated",
        "material"
    ],
    "wof:name":"Locker Group Pty Ltd",
    "wof:placetype":"venue"
},
  "geometry": {"coordinates":[145.201705933,-38.0340309143],"type":"Point"}
}