{
  "type": "Feature",
  "properties": {
    "addr:full":"12 Dundee Pl St Andrews NSW 2566",
    "addr:housenumber":"12",
    "addr:postcode":"2566",
    "addr:street":"Dundee Pl",
    "iso:country":"AU",
    "sg:address":"12 Dundee Pl",
    "sg:city":"St Andrews",
    "sg:classifiers":[
        {
            "category":"Building & Trades",
            "subcategory":"Construction",
            "type":"Services"
        }
    ],
    "sg:phone":"+61 2 9603 7306",
    "sg:postcode":"2566",
    "sg:province":"NSW",
    "sg:tags":[
        "builder",
        "designer",
        "room",
        "cool"
    ],
    "wof:name":"Cool Room Building & Service",
    "wof:placetype":"venue"
},
  "geometry": {"coordinates":[150.82528686500001,-34.0291976929],"type":"Point"}
}