{
  "type": "Feature",
  "properties": {
    "iso:country":"AU",
    "sg:address":"197 Cormack Rd",
    "sg:city":"Wingfield",
    "sg:classifiers":[
        {
            "category":"Professional",
            "type":"Services"
        }
    ],
    "sg:phone":"+61 8 8262 8400",
    "sg:postcode":"5013",
    "sg:province":"SA",
    "sg:tags":[
        "spray",
        "painting"
    ],
    "wof:name":"J.V. Crash Repairs Pty Ltd",
    "wof:placetype":"venue"
},
  "geometry": {"coordinates":[138.56463623100001,-34.8406448364],"type":"Point"}
}