{
  "type": "Feature",
  "properties": {
    "iso:country":"AU",
    "sg:address":"50- 52 Meninya St",
    "sg:city":"Moama",
    "sg:classifiers":[
        {
            "category":"Farming",
            "subcategory":"Farm & Veterinary Services",
            "type":"Manufacturing & Wholesale Goods"
        }
    ],
    "sg:phone":"+61 3 5482 1862",
    "sg:postcode":"2731",
    "sg:province":"NSW",
    "sg:tags":[
        "irrigation",
        "reticulation",
        "system"
    ],
    "wof:name":"Wards Pumps & Irrigation",
    "wof:placetype":"venue"
},
  "geometry": {"coordinates":[144.75462300000001,-36.111275],"type":"Point"}
}