{
  "type": "Feature",
  "properties": {
    "iso:country":"AU",
    "sg:address":"Rusconis Rd",
    "sg:city":"Guildford",
    "sg:classifiers":[
        {
            "category":"Farming",
            "subcategory":"Farm & Veterinary Services",
            "type":"Manufacturing & Wholesale Goods"
        }
    ],
    "sg:phone":"+61 3 5473 4362",
    "sg:postcode":"3451",
    "sg:province":"VIC",
    "sg:tags":[
        "agricultural",
        "advisory"
    ],
    "wof:name":"Marold-Hof Environmental Design & Consultancy",
    "wof:placetype":"venue"
},
  "geometry": {"coordinates":[144.17703247099999,-37.1828575134],"type":"Point"}
}