{
  "type": "Feature",
  "properties": {
    "addr:full":"6/ 2281 Sandgate Rd Boondall QLD 4034",
    "addr:housenumber":"/ 2281",
    "addr:postcode":"4034",
    "addr:street":"Sandgate Rd",
    "iso:country":"AU",
    "sg:address":"6/ 2281 Sandgate Rd",
    "sg:city":"Boondall",
    "sg:classifiers":[
        {
            "category":"Health Services",
            "subcategory":"Doctor",
            "type":"Services"
        }
    ],
    "sg:phone":"+61 7 3265 7740",
    "sg:postcode":"4034",
    "sg:province":"QLD",
    "sg:tags":[
        "medical",
        "practitioner"
    ],
    "wof:name":"Boondall Family Practice",
    "wof:placetype":"venue"
},
  "geometry": {"coordinates":[153.06088299999999,-27.352222],"type":"Point"}
}