{
  "type": "Feature",
  "properties": {
    "addr:full":"James St Beenleigh QLD 4207",
    "addr:postcode":"4207",
    "addr:street":"James St",
    "iso:country":"AU",
    "sg:address":"James St",
    "sg:city":"Beenleigh",
    "sg:classifiers":[
        {
            "category":"Organizations",
            "subcategory":"Professional Association",
            "type":"Services"
        }
    ],
    "sg:phone":"+61 7 3807 1871",
    "sg:postcode":"4207",
    "sg:province":"QLD",
    "sg:tags":[
        "rural",
        "organisation",
        "production",
        "primary"
    ],
    "wof:name":"Beenleigh Show Society",
    "wof:placetype":"venue"
},
  "geometry": {"coordinates":[153.19520568900001,-27.7213096619],"type":"Point"}
}