{
  "type": "Feature",
  "properties": {
    "addr:full":"18 Neil St Toowoomba QLD 4350",
    "addr:housenumber":"18",
    "addr:postcode":"4350",
    "addr:street":"Neil St",
    "iso:country":"AU",
    "sg:address":"18 Neil St",
    "sg:city":"Toowoomba",
    "sg:classifiers":[
        {
            "category":"Professional",
            "subcategory":"Printing & Photocopies",
            "type":"Services"
        }
    ],
    "sg:phone":"+61 7 4638 5231",
    "sg:postcode":"4350",
    "sg:province":"QLD",
    "sg:tags":[
        "photocopying"
    ],
    "wof:name":"Snap Printing",
    "wof:placetype":"venue"
},
  "geometry": {"coordinates":[151.94760099999999,-27.56629],"type":"Point"}
}