{
  "type": "Feature",
  "properties": {
    "addr:full":"Shop 8, 16 Laurie St Laurieton NSW 2443",
    "addr:housenumber":"shop;16",
    "addr:postcode":"2443",
    "addr:street":"Laurie St",
    "iso:country":"AU",
    "sg:address":"Shop 8, 16 Laurie St",
    "sg:city":"Laurieton",
    "sg:classifiers":[
        {
            "category":"Health Services",
            "subcategory":"Optometrist",
            "type":"Services"
        }
    ],
    "sg:phone":"+61 2 6559 9007",
    "sg:postcode":"2443",
    "sg:province":"NSW",
    "wof:name":"Baker C J",
    "wof:placetype":"venue"
},
  "geometry": {"coordinates":[152.79553200000001,-31.652428],"type":"Point"}
}