{
  "type": "Feature",
  "properties": {
    "iso:country":"AU",
    "sg:address":"Shop 98A Macquarie Ctr Herring Rd",
    "sg:city":"Macquarie Centre",
    "sg:classifiers":[
        {
            "category":"Fast Food",
            "type":"Food & Drink"
        }
    ],
    "sg:phone":"+61 2 9805 0720",
    "sg:postcode":"2113",
    "sg:province":"NSW",
    "sg:tags":[
        "away",
        "take"
    ],
    "wof:name":"Pizza Hut",
    "wof:placetype":"venue"
},
  "geometry": {"coordinates":[151.11909484899999,-33.7765235901],"type":"Point"}
}