{
  "type": "Feature",
  "properties": {
    "addr:full":"Shop 3a/ 20 Karalta Rd Erina NSW 2250",
    "addr:housenumber":"shop 3a / 20",
    "addr:postcode":"2250",
    "addr:street":"Karalta Rd",
    "iso:country":"AU",
    "sg:address":"Shop 3a/ 20 Karalta Rd",
    "sg:city":"Erina",
    "sg:classifiers":[
        {
            "category":"Food & Beverages",
            "subcategory":"Bakery",
            "type":"Retail Goods"
        }
    ],
    "sg:phone":"+61 2 4365 6744",
    "sg:postcode":"2250",
    "sg:province":"NSW",
    "sg:tags":[
        "cake",
        "shop",
        "pastry"
    ],
    "wof:name":"Sarnellis Continental Cakes & Coffee Bar",
    "wof:placetype":"venue"
},
  "geometry": {"coordinates":[151.385375977,-33.4387931824],"type":"Point"}
}