{
  "type": "Feature",
  "properties": {
    "addr:full":"91-93 Youngman St Kingaroy QLD 4610",
    "addr:housenumber":"91-93",
    "addr:postcode":"4610",
    "addr:street":"Youngman St",
    "iso:country":"AU",
    "sg:address":"91-93 Youngman St",
    "sg:city":"Kingaroy",
    "sg:classifiers":[
        {
            "category":"Autos & Motor Vehicles",
            "subcategory":"Fuel & Gas Station",
            "type":"Retail Goods"
        }
    ],
    "sg:phone":"+61 7 4162 2911",
    "sg:postcode":"4610",
    "sg:province":"QLD",
    "wof:name":"Woolworths Plus Petrol",
    "wof:placetype":"venue"
},
  "geometry": {"coordinates":[151.83595275900001,-26.5411567688],"type":"Point"}
}