{
  "type": "Feature",
  "properties": {
    "addr:full":"23 Allworth Drv Frenchs Forest NSW 2086",
    "addr:housenumber":"23",
    "addr:postcode":"2086",
    "addr:street":"Allworth Drv",
    "iso:country":"AU",
    "sg:address":"23 Allworth Drv",
    "sg:city":"Frenchs Forest",
    "sg:classifiers":[
        {
            "category":"Building & Trades",
            "subcategory":"Plumbing",
            "type":"Services"
        }
    ],
    "sg:phone":"+61 409 466 884",
    "sg:postcode":"2086",
    "sg:province":"NSW",
    "sg:tags":[
        "plumber",
        "gasfitters"
    ],
    "wof:name":"Mission Impossible Plumbing",
    "wof:placetype":"venue"
},
  "geometry": {"coordinates":[151.19410705600001,-33.743183136],"type":"Point"}
}