{
  "type": "Feature",
  "properties": {
    "addr:full":"46 Veronica St Inverloch VIC 3996",
    "addr:housenumber":"46",
    "addr:postcode":"3996",
    "addr:street":"Veronica St",
    "iso:country":"AU",
    "sg:address":"46 Veronica St",
    "sg:city":"Inverloch",
    "sg:classifiers":[
        {
            "category":"Professional",
            "subcategory":"Secretarial Services",
            "type":"Services"
        }
    ],
    "sg:phone":"+61 3 5674 3422",
    "sg:postcode":"3996",
    "sg:province":"VIC",
    "sg:tags":[
        "typing"
    ],
    "wof:name":"Hawker Pat",
    "wof:placetype":"venue"
},
  "geometry": {"coordinates":[145.70678699999999,-38.642258],"type":"Point"}
}