{
  "type": "Feature",
  "properties": {
    "iso:country":"AU",
    "sg:address":"Suite 2, 1st Floor, 77 York St",
    "sg:city":"Sydney",
    "sg:classifiers":[
        {
            "category":"Personal",
            "subcategory":"Hair Removal",
            "type":"Services"
        }
    ],
    "sg:phone":"+61 1300 665 338",
    "sg:postcode":"2000",
    "sg:province":"NSW",
    "wof:name":"Hair Free Centre",
    "wof:placetype":"venue"
},
  "geometry": {"coordinates":[151.20591735799999,-33.8688011169],"type":"Point"}
}