{
  "type": "Feature",
  "properties": {
    "addr:full":"PO Box 61 Fortitude Valley QLD 4006",
    "addr:postcode":"4006",
    "iso:country":"AU",
    "sg:address":"PO Box 61",
    "sg:city":"Fortitude Valley",
    "sg:classifiers":[
        {
            "category":"Education",
            "subcategory":"Special Training",
            "type":"Public Place"
        }
    ],
    "sg:phone":"+61 7 3003 0363",
    "sg:postcode":"4006",
    "sg:province":"QLD",
    "sg:tags":[
        "development"
    ],
    "wof:name":"City Smart (Australia) Pty Ltd",
    "wof:placetype":"venue"
},
  "geometry": {"coordinates":[153.035324097,-27.4581394196],"type":"Point"}
}