{
  "type": "Feature",
  "properties": {
    "iso:country":"AU",
    "sg:address":"185 Conadilly St",
    "sg:city":"Gunnedah",
    "sg:classifiers":[
        {
            "category":"Food & Beverages",
            "subcategory":"Supermarket",
            "type":"Retail Goods"
        }
    ],
    "sg:phone":"+61 2 6742 0522",
    "sg:postcode":"2380",
    "sg:province":"NSW",
    "sg:tags":[
        "grocery",
        "store"
    ],
    "wof:name":"Bi-Lo Pty Ltd",
    "wof:placetype":"venue"
},
  "geometry": {"coordinates":[150.25245666500001,-30.9772987366],"type":"Point"}
}