{
  "type": "Feature",
  "properties": {
    "addr:full":"301 Aldersyde Rd Bickley WA 6076",
    "addr:housenumber":"301",
    "addr:postcode":"6076",
    "addr:street":"Aldersyde Rd",
    "iso:country":"AU",
    "sg:address":"301 Aldersyde Rd",
    "sg:city":"Bickley",
    "sg:classifiers":[
        {
            "category":"Building & Trades",
            "subcategory":"Construction",
            "type":"Services"
        }
    ],
    "sg:phone":"+61 412 425 607",
    "sg:postcode":"6076",
    "sg:province":"WA",
    "sg:tags":[
        "stonework",
        "stone",
        "mason"
    ],
    "wof:name":"Aesthetic Projects Pty Ltd",
    "wof:placetype":"venue"
},
  "geometry": {"coordinates":[116.09989166299999,-31.9933605194],"type":"Point"}
}