{
  "type": "Feature",
  "properties": {
    "iso:country":"AU",
    "sg:address":"52 Saxonwood Drv",
    "sg:city":"Narre Warren",
    "sg:classifiers":[
        {
            "category":"Building & Trades",
            "subcategory":"Landscaping Services",
            "type":"Services"
        }
    ],
    "sg:phone":"+61 418 180 482",
    "sg:postcode":"3805",
    "sg:province":"VIC",
    "sg:tags":[
        "designer",
        "landscape",
        "contractor"
    ],
    "wof:name":"SPR Excavations",
    "wof:placetype":"venue"
},
  "geometry": {"coordinates":[145.312073,-38.032188],"type":"Point"}
}