{
  "type": "Feature",
  "properties": {
    "iso:country":"AU",
    "sg:address":"171 Ravenswood Rd",
    "sg:city":"Ravenswood",
    "sg:classifiers":[
        {
            "category":"Manufacturing",
            "subcategory":"Paper Products",
            "type":"Manufacturing & Wholesale Goods"
        }
    ],
    "sg:phone":"+61 1800 804 970",
    "sg:postcode":"7250",
    "sg:province":"TAS",
    "sg:tags":[
        "metal",
        "non-ferrous",
        "foundry"
    ],
    "sg:website":"http://www.jacksonslocks.com.au",
    "wof:name":"Jacksons Foundry",
    "wof:placetype":"venue"
},
  "geometry": {"coordinates":[147.175323486,-41.4337997437],"type":"Point"}
}