{
  "type": "Feature",
  "properties": {
    "addr:full":"PO Box 516 Avalon NSW 2107",
    "addr:postcode":"2107",
    "iso:country":"AU",
    "sg:address":"PO Box 516",
    "sg:city":"Avalon",
    "sg:classifiers":[
        {
            "category":"Arena",
            "subcategory":"Sports Club",
            "type":"Entertainment"
        }
    ],
    "sg:phone":"+61 2 9918 5111",
    "sg:postcode":"2107",
    "sg:province":"NSW",
    "sg:tags":[
        "league",
        "rugby"
    ],
    "wof:name":"Avalon Junior Rugby League Club",
    "wof:placetype":"venue"
},
  "geometry": {"coordinates":[151.33171081500001,-33.6286201477],"type":"Point"}
}