{
  "type": "Feature",
  "properties": {
    "addr:full":"Woodlands Rd Taren Point NSW 2229",
    "addr:postcode":"2229",
    "addr:street":"Woodlands Rd",
    "iso:country":"AU",
    "sg:address":"Woodlands Rd",
    "sg:city":"Taren Point",
    "sg:classifiers":[
        {
            "category":"Education",
            "subcategory":"School",
            "type":"Public Place"
        }
    ],
    "sg:phone":"+61 2 9524 6379",
    "sg:postcode":"2229",
    "sg:province":"NSW",
    "sg:tags":[
        "state",
        "-",
        "nsw"
    ],
    "wof:name":"Taren Point Public School",
    "wof:placetype":"venue"
},
  "geometry": {"coordinates":[151.12336730999999,-34.0180549622],"type":"Point"}
}