{
  "type": "Feature",
  "properties": {
    "iso:country":"AU",
    "sg:address":"95 Glenora St",
    "sg:city":"Wynnum",
    "sg:classifiers":[
        {
            "category":"Education",
            "subcategory":"Kindergarten",
            "type":"Public Place"
        }
    ],
    "sg:phone":"+61 7 3396 8800",
    "sg:postcode":"4178",
    "sg:province":"QLD",
    "sg:tags":[
        "pre-schools"
    ],
    "wof:name":"Montessori Journey",
    "wof:placetype":"venue"
},
  "geometry": {"coordinates":[153.16773986800001,-27.4370346069],"type":"Point"}
}