{
  "type": "Feature",
  "properties": {
    "addr:full":"178 Sussex St Coburg VIC 3058",
    "addr:housenumber":"178",
    "addr:postcode":"3058",
    "addr:street":"Sussex St",
    "iso:country":"AU",
    "sg:address":"178 Sussex St",
    "sg:city":"Coburg",
    "sg:classifiers":[
        {
            "category":"Autos & Motor Vehicles",
            "subcategory":"Fuel & Gas Station",
            "type":"Retail Goods"
        }
    ],
    "sg:phone":"+61 3 9350 1677",
    "sg:postcode":"3058",
    "sg:province":"VIC",
    "wof:name":"Sussex Street Motors",
    "wof:placetype":"venue"
},
  "geometry": {"coordinates":[144.95048523,-37.7270431519],"type":"Point"}
}