{
  "type": "Feature",
  "properties": {
    "addr:full":"1- 19 Gowrie St Shepparton VIC 3630",
    "addr:housenumber":"19",
    "addr:postcode":"3630",
    "addr:street":"1;Gowrie St",
    "iso:country":"AU",
    "sg:address":"1- 19 Gowrie St",
    "sg:city":"Shepparton",
    "sg:classifiers":[
        {
            "category":"Education",
            "subcategory":"School",
            "type":"Public Place"
        }
    ],
    "sg:phone":"+61 3 5821 3100",
    "sg:postcode":"3630",
    "sg:province":"VIC",
    "sg:tags":[
        "state",
        "except",
        "nsw"
    ],
    "wof:name":"Gowrie Street Primary School",
    "wof:placetype":"venue"
},
  "geometry": {"coordinates":[145.396194458,-36.3675498962],"type":"Point"}
}