{
  "type": "Feature",
  "properties": {
    "addr:full":"20a Gregory St Yagoona NSW 2199",
    "addr:housenumber":"20a",
    "addr:postcode":"2199",
    "addr:street":"Gregory St",
    "iso:country":"AU",
    "sg:address":"20a Gregory St",
    "sg:city":"Yagoona",
    "sg:classifiers":[
        {
            "category":"Home & Garden",
            "subcategory":"Building Materials",
            "type":"Retail Goods"
        }
    ],
    "sg:phone":"+61 410 380 923",
    "sg:postcode":"2199",
    "sg:province":"NSW",
    "sg:tags":[
        "merchant",
        "glass",
        "glazier"
    ],
    "wof:name":"S&G A Touch Of Glass",
    "wof:placetype":"venue"
},
  "geometry": {"coordinates":[151.00741600000001,-33.906319],"type":"Point"}
}