{
  "type": "Feature",
  "properties": {
    "addr:full":"848 High St Thornbury VIC 3071",
    "addr:housenumber":"848",
    "addr:postcode":"3071",
    "addr:street":"High St",
    "iso:country":"AU",
    "sg:address":"848 High St",
    "sg:city":"Thornbury",
    "sg:classifiers":[
        {
            "category":"Banks & Credit Unions",
            "subcategory":"Bank",
            "type":"Services"
        }
    ],
    "sg:phone":"+61 3 9416 8133",
    "sg:postcode":"3071",
    "sg:province":"VIC",
    "wof:name":"ANZ Bank",
    "wof:placetype":"venue"
},
  "geometry": {"coordinates":[145.001785278,-37.7524833679],"type":"Point"}
}