{
  "type": "Feature",
  "properties": {
    "addr:full":"92 Robey St Maroubra NSW 2035",
    "addr:housenumber":"92",
    "addr:postcode":"2035",
    "addr:street":"Robey St",
    "iso:country":"AU",
    "sg:address":"92 Robey St",
    "sg:city":"Maroubra",
    "sg:classifiers":[
        {
            "category":"Real Estate",
            "subcategory":"Architect",
            "type":"Services"
        }
    ],
    "sg:phone":"+61 2 9315 5833",
    "sg:postcode":"2035",
    "sg:province":"NSW",
    "wof:name":"Edifice Design Pty Ltd",
    "wof:placetype":"venue"
},
  "geometry": {"coordinates":[151.23817443900001,-33.9457092285],"type":"Point"}
}