{
  "type": "Feature",
  "properties": {
    "iso:country":"AU",
    "sg:address":"123 Mostyn St",
    "sg:city":"Castlemaine",
    "sg:classifiers":[
        {
            "category":"Retail",
            "subcategory":"Funeral Services",
            "type":"Services"
        }
    ],
    "sg:phone":"+61 3 5472 2202",
    "sg:postcode":"3450",
    "sg:province":"VIC",
    "sg:tags":[
        "cremation"
    ],
    "wof:name":"Castlemaine & District Funeral Parlors",
    "wof:placetype":"venue"
},
  "geometry": {"coordinates":[144.22048950199999,-37.0658874512],"type":"Point"}
}