{
  "type": "Feature",
  "properties": {
    "iso:country":"AU",
    "sg:address":"239 King St",
    "sg:city":"Newcastle",
    "sg:classifiers":[
        {
            "category":"Professional",
            "subcategory":"Detective & Security Services",
            "type":"Services"
        }
    ],
    "sg:phone":"+61 2 4929 2608",
    "sg:postcode":"2300",
    "sg:province":"NSW",
    "sg:tags":[
        "guard",
        "patrol"
    ],
    "wof:name":"ASM Security Services",
    "wof:placetype":"venue"
},
  "geometry": {"coordinates":[151.770493,-32.928413],"type":"Point"}
}