{
  "type": "Feature",
  "properties": {
    "addr:full":"Ste 1, Lvl 3, Bldg A, 11 Talavera Rd Macquarie Park NSW 2113",
    "addr:postcode":"2113",
    "addr:street":"Talavera Rd",
    "iso:country":"AU",
    "sg:address":"Ste 1, Lvl 3, Bldg A, 11 Talavera Rd",
    "sg:city":"Macquarie Park",
    "sg:classifiers":[
        {
            "category":"Shopping",
            "subcategory":"Stationery & Office Supplies",
            "type":"Retail Goods"
        }
    ],
    "sg:phone":"+61 2 9887 4344",
    "sg:postcode":"2113",
    "sg:province":"NSW",
    "sg:tags":[
        "equipment",
        "facsimile"
    ],
    "wof:name":"Brother International (Aust) Pty Ltd",
    "wof:placetype":"venue"
},
  "geometry": {"coordinates":[151.12542724599999,-33.7778968811],"type":"Point"}
}