{
  "type": "Feature",
  "properties": {
    "addr:full":"1 Parade Crt Sunbury VIC 3429",
    "addr:housenumber":"1",
    "addr:postcode":"3429",
    "addr:street":"Parade Crt",
    "iso:country":"AU",
    "sg:address":"1 Parade Crt",
    "sg:city":"Sunbury",
    "sg:classifiers":[
        {
            "category":"Arts & Performance",
            "subcategory":"Dance",
            "type":"Entertainment"
        }
    ],
    "sg:phone":"+61 3 9744 3852",
    "sg:postcode":"3429",
    "sg:province":"VIC",
    "sg:tags":[
        "theatrical",
        "ballet",
        "tuition"
    ],
    "wof:name":"Black Swan Ballet Centre",
    "wof:placetype":"venue"
},
  "geometry": {"coordinates":[144.753082275,-37.5756530762],"type":"Point"}
}