{
  "type": "Feature",
  "properties": {
    "addr:full":"10A Ormond Rd East Geelong VIC 3219",
    "addr:housenumber":"10a",
    "addr:postcode":"3219",
    "addr:street":"Ormond Rd",
    "iso:country":"AU",
    "sg:address":"10A Ormond Rd",
    "sg:city":"East Geelong",
    "sg:classifiers":[
        {
            "category":"Personal",
            "subcategory":"Beauty Salon",
            "type":"Services"
        }
    ],
    "sg:phone":"+61 3 5229 4838",
    "sg:postcode":"3219",
    "sg:province":"VIC",
    "sg:tags":[
        "hairdresser"
    ],
    "wof:name":"Steve Connoley",
    "wof:placetype":"venue"
},
  "geometry": {"coordinates":[144.37179565400001,-38.1555213928],"type":"Point"}
}