{
  "type": "Feature",
  "properties": {
    "addr:full":"196 Christmas St Fairfield VIC 3078",
    "addr:housenumber":"196",
    "addr:postcode":"3078",
    "addr:street":"Christmas St",
    "iso:country":"AU",
    "sg:address":"196 Christmas St",
    "sg:city":"Fairfield",
    "sg:classifiers":[
        {
            "category":"Professional",
            "subcategory":"Engineering",
            "type":"Services"
        }
    ],
    "sg:phone":"+61 3 9499 8322",
    "sg:postcode":"3078",
    "sg:province":"VIC",
    "sg:tags":[
        "engineer"
    ],
    "wof:name":"L & B McKeon Engineering Pty Ltd",
    "wof:placetype":"venue"
},
  "geometry": {"coordinates":[145.02676391599999,-37.7682151794],"type":"Point"}
}