{
  "type": "Feature",
  "properties": {
    "addr:full":"3 William St Forth TAS 7310",
    "addr:housenumber":"3",
    "addr:postcode":"7310",
    "addr:street":"William St",
    "iso:country":"AU",
    "sg:address":"3 William St",
    "sg:city":"Forth",
    "sg:classifiers":[
        {
            "category":"Building & Trades",
            "subcategory":"Cleaning & Sanitation",
            "type":"Services"
        }
    ],
    "sg:phone":"+61 419 318 373",
    "sg:postcode":"7310",
    "sg:province":"TAS",
    "sg:tags":[
        "window"
    ],
    "wof:name":"Clear Horizon Window Cleaning",
    "wof:placetype":"venue"
},
  "geometry": {"coordinates":[146.25262451200001,-41.188999176],"type":"Point"}
}