{
  "type": "Feature",
  "properties": {
    "iso:country":"AU",
    "sg:address":"130 Yamba Rd",
    "sg:city":"Yamba",
    "sg:classifiers":[
        {
            "category":"Insurance",
            "subcategory":"Hazard Insurance",
            "type":"Services"
        }
    ],
    "sg:phone":"+61 2 6646 9771",
    "sg:postcode":"2464",
    "sg:province":"NSW",
    "sg:tags":[
        "loss",
        "adjuster",
        "assessor"
    ],
    "wof:name":"Mal Cocks Insurance Survey & Assessment",
    "wof:placetype":"venue"
},
  "geometry": {"coordinates":[153.32846069300001,-29.4297885895],"type":"Point"}
}