{
  "type": "Feature",
  "properties": {
    "addr:full":"199 Boundary Rd Rockhampton QLD 4700",
    "addr:housenumber":"199",
    "addr:postcode":"4700",
    "addr:street":"Boundary Rd",
    "iso:country":"AU",
    "sg:address":"199 Boundary Rd",
    "sg:city":"Rockhampton",
    "sg:classifiers":[
        {
            "category":"Commercial Area",
            "type":"Public Place"
        }
    ],
    "sg:phone":"+61 7 4936 4888",
    "sg:postcode":"4700",
    "sg:province":"QLD",
    "sg:tags":[
        "heavy",
        "carrier"
    ],
    "wof:name":"Bells Transport Pty Ltd",
    "wof:placetype":"venue"
},
  "geometry": {"coordinates":[150.50471496599999,-23.3157577515],"type":"Point"}
}