{
  "type": "Feature",
  "properties": {
    "iso:country":"AU",
    "sg:address":"59 Railway Ave",
    "sg:city":"Gunnedah",
    "sg:classifiers":[
        {
            "category":"Wholesale",
            "subcategory":"Electrical",
            "type":"Manufacturing & Wholesale Goods"
        }
    ],
    "sg:phone":"+61 2 6742 5600",
    "sg:postcode":"2380",
    "sg:province":"NSW",
    "sg:tags":[
        "wholesaler"
    ],
    "wof:name":"Lear & Smith Electrical Wholesalers Pty Ltd",
    "wof:placetype":"venue"
},
  "geometry": {"coordinates":[150.24908447300001,-30.9791927338],"type":"Point"}
}