{
  "type": "Feature",
  "properties": {
    "iso:country":"AU",
    "sg:address":"GPO Box 2370",
    "sg:city":"Sydney",
    "sg:classifiers":[
        {
            "category":"Professional",
            "subcategory":"Business Services",
            "type":"Services"
        }
    ],
    "sg:phone":"+61 1300 130 697",
    "sg:postcode":"2001",
    "sg:province":"NSW",
    "sg:tags":[
        "management",
        "event"
    ],
    "wof:name":"FLOP THE NUTS",
    "wof:placetype":"venue"
},
  "geometry": {"coordinates":[151.207107544,-33.8671417236],"type":"Point"}
}