{
  "type": "Feature",
  "properties": {
    "addr:full":"Unit 3, 39- 41 Olympic Cct Southport QLD 4215",
    "addr:housenumber":"39 41",
    "addr:postcode":"4215",
    "addr:street":"Olympic Cct",
    "iso:country":"AU",
    "sg:address":"Unit 3, 39- 41",
    "sg:city":"Olympic Cct Southport",
    "sg:classifiers":[
        {
            "category":"Building & Trades",
            "subcategory":"Plumbing",
            "type":"Services"
        }
    ],
    "sg:phone":"+61 7 5532 7200",
    "sg:postcode":"4215",
    "sg:province":"QLD",
    "sg:tags":[
        "equipment",
        "valves"
    ],
    "wof:name":"AHF Valves Australia Pty Ltd",
    "wof:placetype":"venue"
},
  "geometry": {"coordinates":[153.415557861,-27.9655303955],"type":"Point"}
}