{
  "type": "Feature",
  "properties": {
    "addr:full":"PO Box 268 Cotton Tree QLD 4558",
    "addr:postcode":"4558",
    "iso:country":"AU",
    "sg:address":"PO Box 268",
    "sg:city":"Cotton Tree",
    "sg:classifiers":[
        {
            "category":"Arts & Performance",
            "subcategory":"Art Gallery",
            "type":"Entertainment"
        }
    ],
    "sg:phone":"+61 7 5442 8691",
    "sg:postcode":"4558",
    "sg:province":"QLD",
    "sg:tags":[
        "aboriginal",
        "craft"
    ],
    "wof:name":"Murra Wolka Creations Aboriginal Artifacts",
    "wof:placetype":"venue"
},
  "geometry": {"coordinates":[153.098754883,-26.6551895142],"type":"Point"}
}