{
  "type": "Feature",
  "properties": {
    "addr:full":"Ferry Rd Kettering TAS 7155",
    "addr:postcode":"7155",
    "addr:street":"Ferry Rd",
    "iso:country":"AU",
    "sg:address":"Ferry Rd",
    "sg:city":"Kettering",
    "sg:classifiers":[
        {
            "category":"Wholesale",
            "subcategory":"Seafood",
            "type":"Manufacturing & Wholesale Goods"
        }
    ],
    "sg:phone":"+61 3 6267 4484",
    "sg:postcode":"7155",
    "sg:province":"TAS",
    "sg:tags":[
        "fish"
    ],
    "wof:name":"Great Bay Shellfish",
    "wof:placetype":"venue"
},
  "geometry": {"coordinates":[147.24688720699999,-43.1281814575],"type":"Point"}
}