{
  "type": "Feature",
  "properties": {
    "iso:country":"AU",
    "sg:address":"250 Brunswick St",
    "sg:city":"Fitzroy",
    "sg:classifiers":[
        {
            "category":"Shopping",
            "subcategory":"Clothing, Apparel, & Fashions",
            "type":"Retail Goods"
        }
    ],
    "sg:phone":"+61 3 9415 1477",
    "sg:postcode":"3065",
    "sg:province":"VIC",
    "sg:tags":[
        "lady",
        "wear"
    ],
    "wof:name":"Lush Clothing",
    "wof:placetype":"venue"
},
  "geometry": {"coordinates":[144.97833251899999,-37.7999992371],"type":"Point"}
}