{
  "type": "Feature",
  "properties": {
    "iso:country":"AU",
    "sg:address":"2 Princess St",
    "sg:city":"Brighton-le-Sands",
    "sg:classifiers":[
        {
            "category":"Fast Food",
            "type":"Food & Drink"
        }
    ],
    "sg:phone":"+61 2 9567 7788",
    "sg:postcode":"2216",
    "sg:province":"NSW",
    "sg:tags":[
        "away",
        "take"
    ],
    "wof:name":"Testarossa Pizza-Italian Food",
    "wof:placetype":"venue"
},
  "geometry": {"coordinates":[151.155991,-33.959877],"type":"Point"}
}