{
  "type": "Feature",
  "properties": {
    "iso:country":"AU",
    "sg:address":"13 Martin St",
    "sg:city":"South Melbourne",
    "sg:classifiers":[
        {
            "category":"Professional",
            "subcategory":"Management & Consulting",
            "type":"Services"
        }
    ],
    "sg:phone":"+61 3 9696 8684",
    "sg:postcode":"3205",
    "sg:province":"VIC",
    "sg:tags":[
        "project"
    ],
    "wof:name":"Mosaic Project Services Pty Ltd",
    "wof:placetype":"venue"
},
  "geometry": {"coordinates":[144.95863299999999,-37.837078],"type":"Point"}
}