{
  "type": "Feature",
  "properties": {
    "addr:full":"44 Lethbys Rd Eaglehawk VIC 3556",
    "addr:housenumber":"44",
    "addr:postcode":"3556",
    "addr:street":"Lethbys Rd",
    "iso:country":"AU",
    "sg:address":"44 Lethbys Rd",
    "sg:city":"Eaglehawk",
    "sg:classifiers":[
        {
            "category":"Professional",
            "subcategory":"Art Services",
            "type":"Services"
        }
    ],
    "sg:phone":"+61 419 370 218",
    "sg:postcode":"3556",
    "sg:province":"VIC",
    "sg:tags":[
        "decorator",
        "painter"
    ],
    "wof:name":"Expert Painting",
    "wof:placetype":"venue"
},
  "geometry": {"coordinates":[144.23150634800001,-36.7110900879],"type":"Point"}
}