{
  "type": "Feature",
  "properties": {
    "iso:country":"AU",
    "sg:address":"106 Northern Hwy",
    "sg:city":"Echuca",
    "sg:classifiers":[
        {
            "category":"Autos & Motor Vehicles",
            "subcategory":"Auto Supplies",
            "type":"Retail Goods"
        }
    ],
    "sg:phone":"+61 3 5480 6122",
    "sg:postcode":"3564",
    "sg:province":"VIC",
    "sg:tags":[
        "tyre"
    ],
    "wof:name":"A. Quick Fit Tyre Service",
    "wof:placetype":"venue"
},
  "geometry": {"coordinates":[144.730834961,-36.1499786377],"type":"Point"}
}