{
  "type": "Feature",
  "properties": {
    "addr:full":"U14/ 9 Ambitious Link Bibra Lake WA 6163",
    "addr:postcode":"6163",
    "addr:street":"/ 9 Ambitious Link",
    "iso:country":"AU",
    "sg:address":"U14/ 9 Ambitious Link",
    "sg:city":"Bibra Lake",
    "sg:classifiers":[
        {
            "category":"Retail",
            "subcategory":"Auto Repair",
            "type":"Services"
        }
    ],
    "sg:phone":"+61 8 9418 8454",
    "sg:postcode":"6163",
    "sg:province":"WA",
    "sg:tags":[
        "repairer",
        "motor",
        "engineer"
    ],
    "wof:name":"Ciccarone Autos Pty Ltd",
    "wof:placetype":"venue"
},
  "geometry": {"coordinates":[115.777496,-32.086662],"type":"Point"}
}