{
  "type": "Feature",
  "properties": {
    "addr:full":"143 Derwent Ave Lindisfarne TAS 7015",
    "addr:housenumber":"143",
    "addr:postcode":"7015",
    "addr:street":"Derwent Ave",
    "iso:country":"AU",
    "sg:address":"143 Derwent Ave",
    "sg:city":"Lindisfarne",
    "sg:classifiers":[
        {
            "category":"Organizations",
            "subcategory":"Membership Organization",
            "type":"Services"
        }
    ],
    "sg:phone":"+61 3 6244 6881",
    "sg:postcode":"7015",
    "sg:province":"TAS",
    "sg:tags":[
        "club",
        "car"
    ],
    "wof:name":"Hobart Radio Control Car Club",
    "wof:placetype":"venue"
},
  "geometry": {"coordinates":[147.343551636,-42.8474464417],"type":"Point"}
}