{
  "type": "Feature",
  "properties": {
    "addr:full":"390 Burwood Rd Hawthorn VIC 3122",
    "addr:housenumber":"390",
    "addr:postcode":"3122",
    "addr:street":"Burwood Rd",
    "iso:country":"AU",
    "sg:address":"390 Burwood Rd",
    "sg:city":"Hawthorn",
    "sg:classifiers":[
        {
            "category":"Health Services",
            "subcategory":"Dentist",
            "type":"Services"
        }
    ],
    "sg:phone":"+61 3 9818 2181",
    "sg:postcode":"3122",
    "sg:province":"VIC",
    "wof:name":"Barnes Victor Dr",
    "wof:placetype":"venue"
},
  "geometry": {"coordinates":[145.03741455100001,-37.8229446411],"type":"Point"}
}