{
  "type": "Feature",
  "properties": {
    "addr:full":"PO Box 167 Ballina NSW 2478",
    "addr:postcode":"2478",
    "iso:country":"AU",
    "sg:address":"PO Box 167",
    "sg:city":"Ballina",
    "sg:classifiers":[
        {
            "category":"Education",
            "subcategory":"Dance Studio",
            "type":"Public Place"
        }
    ],
    "sg:phone":"+61 2 6686 5827",
    "sg:postcode":"2478",
    "sg:province":"NSW",
    "sg:tags":[
        "venue",
        "tuition"
    ],
    "wof:name":"Ready to Rock",
    "wof:placetype":"venue"
},
  "geometry": {"coordinates":[153.554962158,-28.8678798676],"type":"Point"}
}