{
  "type": "Feature",
  "properties": {
    "iso:country":"AU",
    "sg:address":"Shop 234, Garden City, Cnr Park Ave & Northcott Drv",
    "sg:city":"Kotara",
    "sg:classifiers":[
        {
            "category":"Shopping",
            "subcategory":"Music",
            "type":"Retail Goods"
        }
    ],
    "sg:phone":"+61 2 4956 2151",
    "sg:postcode":"2289",
    "sg:province":"NSW",
    "sg:tags":[
        "store"
    ],
    "wof:name":"HMV Australia",
    "wof:placetype":"venue"
},
  "geometry": {"coordinates":[151.710693359,-32.9406433105],"type":"Point"}
}