{
  "type": "Feature",
  "properties": {
    "addr:full":"Hill St Kingston QLD 4114",
    "addr:postcode":"4114",
    "addr:street":"Hill St",
    "iso:country":"AU",
    "sg:address":"Hill St",
    "sg:city":"Kingston",
    "sg:classifiers":[
        {
            "category":"Building & Trades",
            "subcategory":"Construction",
            "type":"Services"
        }
    ],
    "sg:phone":"+61 7 3208 9966",
    "sg:postcode":"4114",
    "sg:province":"QLD",
    "sg:tags":[
        "plasterboard",
        "plasterer",
        "fixer"
    ],
    "wof:name":"Roots G & V Plasterers",
    "wof:placetype":"venue"
},
  "geometry": {"coordinates":[153.11695861800001,-27.6555118561],"type":"Point"}
}