{
  "type": "Feature",
  "properties": {
    "addr:full":"43 Cave Hill Rd Lilydale VIC 3140",
    "addr:housenumber":"43",
    "addr:postcode":"3140",
    "addr:street":"Cave Hill Rd",
    "iso:country":"AU",
    "sg:address":"43 Cave Hill Rd",
    "sg:city":"Lilydale",
    "sg:classifiers":[
        {
            "category":"Shopping",
            "subcategory":"Mobile Phones",
            "type":"Retail Goods"
        }
    ],
    "sg:phone":"+61 13 17 60",
    "sg:postcode":"3140",
    "sg:province":"VIC",
    "sg:tags":[
        "telephone",
        "accessory"
    ],
    "wof:name":"Battery World",
    "wof:placetype":"venue"
},
  "geometry": {"coordinates":[145.34283447300001,-37.7578964233],"type":"Point"}
}