{
  "type": "Feature",
  "properties": {
    "addr:full":"421 Clayton Rd Clayton VIC 3168",
    "addr:housenumber":"421",
    "addr:postcode":"3168",
    "addr:street":"Clayton Rd",
    "iso:country":"AU",
    "sg:address":"421 Clayton Rd",
    "sg:city":"Clayton",
    "sg:classifiers":[
        {
            "category":"Retail",
            "subcategory":"Auto Rental",
            "type":"Services"
        }
    ],
    "sg:phone":"+61 3 9544 5678",
    "sg:postcode":"3168",
    "sg:province":"VIC",
    "sg:tags":[
        "bus",
        "truck"
    ],
    "wof:name":"Atlantic Rent A Car",
    "wof:placetype":"venue"
},
  "geometry": {"coordinates":[145.11872863799999,-37.9291229248],"type":"Point"}
}