{
  "type": "Feature",
  "properties": {
    "addr:full":"494 Sheffield Rd Montrose VIC 3765",
    "addr:housenumber":"494",
    "addr:postcode":"3765",
    "addr:street":"Sheffield Rd",
    "iso:country":"AU",
    "sg:address":"494 Sheffield Rd",
    "sg:city":"Montrose",
    "sg:classifiers":[
        {
            "category":"Home & Garden",
            "subcategory":"Garden Supply",
            "type":"Retail Goods"
        }
    ],
    "sg:phone":"+61 3 9728 5961",
    "sg:postcode":"3765",
    "sg:province":"VIC",
    "sg:tags":[
        "equipment"
    ],
    "wof:name":"Work Smart Equipment (Vic)",
    "wof:placetype":"venue"
},
  "geometry": {"coordinates":[145.35850524899999,-37.8102302551],"type":"Point"}
}