{
  "type": "Feature",
  "properties": {
    "iso:country":"AU",
    "sg:address":"Ste 2/ 18 Skye Rd",
    "sg:city":"Frankston",
    "sg:classifiers":[
        {
            "category":"Shopping",
            "subcategory":"Bicycles & Sporting Goods",
            "type":"Retail Goods"
        }
    ],
    "sg:phone":"+61 3 9781 4044",
    "sg:postcode":"3199",
    "sg:province":"VIC",
    "sg:tags":[
        "water",
        "equipment",
        "skiing"
    ],
    "wof:name":"Strictly Marine Race Gear",
    "wof:placetype":"venue"
},
  "geometry": {"coordinates":[145.133102417,-38.1306228638],"type":"Point"}
}