{
  "type": "Feature",
  "properties": {
    "iso:country":"AU",
    "sg:address":"PO Box 194",
    "sg:city":"Calwell",
    "sg:classifiers":[
        {
            "category":"Transit Center",
            "subcategory":"Freight",
            "type":"Transportation"
        }
    ],
    "sg:phone":"+61 418 699 140",
    "sg:postcode":"2905",
    "sg:province":"ACT",
    "sg:tags":[
        "forklift",
        "truck"
    ],
    "wof:name":"Optimum Goods Handling",
    "wof:placetype":"venue"
},
  "geometry": {"coordinates":[149.10789489699999,-35.438369751],"type":"Point"}
}