{
  "type": "Feature",
  "properties": {
    "iso:country":"AU",
    "sg:address":"25- 27 Burdekin Ave",
    "sg:city":"Murray Bridge",
    "sg:classifiers":[
        {
            "category":"Education",
            "subcategory":"School",
            "type":"Public Place"
        }
    ],
    "sg:phone":"+61 8 8531 3090",
    "sg:postcode":"5253",
    "sg:province":"SA",
    "sg:tags":[
        "state",
        "except",
        "nsw"
    ],
    "wof:name":"Fraser Park Primary School",
    "wof:placetype":"venue"
},
  "geometry": {"coordinates":[139.28297424300001,-35.139503479],"type":"Point"}
}