{
  "type": "Feature",
  "properties": {
    "addr:full":"294 Elizabeth St Hobart TAS 7000",
    "addr:housenumber":"294",
    "addr:postcode":"7000",
    "addr:street":"Elizabeth St",
    "iso:country":"AU",
    "sg:address":"294 Elizabeth St",
    "sg:city":"Hobart",
    "sg:classifiers":[
        {
            "category":"Military Area",
            "subcategory":"Armory",
            "type":"Public Place"
        }
    ],
    "sg:phone":"+61 3 6234 3761",
    "sg:postcode":"7000",
    "sg:province":"TAS",
    "sg:tags":[
        "teleconferencing"
    ],
    "wof:name":"Canon Office Machines (Hobart)",
    "wof:placetype":"venue"
},
  "geometry": {"coordinates":[147.31829834000001,-42.8765563965],"type":"Point"}
}