{
  "type": "Feature",
  "properties": {
    "iso:country":"AU",
    "sg:address":"Brown St",
    "sg:city":"Yarraman",
    "sg:classifiers":[
        {
            "category":"Government",
            "subcategory":"City Hall",
            "type":"Public Place"
        }
    ],
    "sg:phone":"+61 7 4163 8400",
    "sg:postcode":"4614",
    "sg:province":"QLD",
    "wof:name":"The Yarraman Hall",
    "wof:placetype":"venue"
},
  "geometry": {"coordinates":[151.98275756800001,-26.8412799835],"type":"Point"}
}