{
  "type": "Feature",
  "properties": {
    "addr:full":"Lot 14 Paddys Drv Delacombe VIC 3356",
    "addr:postcode":"3356",
    "addr:street":"Paddys Drv",
    "iso:country":"AU",
    "sg:address":"Lot 14 Paddys Drv",
    "sg:city":"Delacombe",
    "sg:classifiers":[
        {
            "category":"Building & Trades",
            "subcategory":"Cleaning & Sanitation",
            "type":"Services"
        }
    ],
    "sg:phone":"+61 1800 777 034",
    "sg:postcode":"3356",
    "sg:province":"VIC",
    "sg:tags":[
        "asbestos",
        "treatment",
        "removal"
    ],
    "wof:name":"Western Sheetmetal Insulation & Asbestos Removal Pty Ltd",
    "wof:placetype":"venue"
},
  "geometry": {"coordinates":[143.80917400000001,-37.576317],"type":"Point"}
}