{
  "type": "Feature",
  "properties": {
    "addr:full":"26 High St Mansfield VIC 3722",
    "addr:housenumber":"26",
    "addr:postcode":"3722",
    "addr:street":"High St",
    "iso:country":"AU",
    "sg:address":"26 High St",
    "sg:city":"Mansfield",
    "sg:classifiers":[
        {
            "category":"Farming",
            "subcategory":"Vineyard",
            "type":"Manufacturing & Wholesale Goods"
        }
    ],
    "sg:phone":"+61 3 5775 2922",
    "sg:postcode":"3722",
    "sg:province":"VIC",
    "sg:tags":[
        "winery"
    ],
    "wof:name":"Delatite Winery",
    "wof:placetype":"venue"
},
  "geometry": {"coordinates":[146.13723754899999,-37.0812721252],"type":"Point"}
}