{
  "type": "Feature",
  "properties": {
    "iso:country":"AU",
    "sg:address":"23 High St",
    "sg:city":"Thomastown",
    "sg:classifiers":[
        {
            "category":"Utilities",
            "subcategory":"Fuel Oil & Lpg",
            "type":"Services"
        }
    ],
    "sg:phone":"+61 3 9466 4267",
    "sg:postcode":"3074",
    "sg:province":"VIC",
    "sg:tags":[
        "charcoal"
    ],
    "wof:name":"Ironbark Charcoal",
    "wof:placetype":"venue"
},
  "geometry": {"coordinates":[145.011886597,-37.6907310486],"type":"Point"}
}