{
  "type": "Feature",
  "properties": {
    "iso:country":"AU",
    "sg:address":"107 March St",
    "sg:city":"Orange",
    "sg:classifiers":[
        {
            "category":"Health Services",
            "subcategory":"Health Practitioner",
            "type":"Services"
        }
    ],
    "sg:phone":"+61 2 6361 2857",
    "sg:postcode":"2800",
    "sg:province":"NSW",
    "sg:tags":[
        "osteopath"
    ],
    "wof:name":"Christou G T",
    "wof:placetype":"venue"
},
  "geometry": {"coordinates":[149.096893311,-33.2787094116],"type":"Point"}
}