{
  "type": "Feature",
  "properties": {
    "iso:country":"AU",
    "sg:address":"53a Roberts Ave",
    "sg:city":"Horsham",
    "sg:classifiers":[
        {
            "category":"Shopping",
            "subcategory":"Clothing, Apparel, & Fashions",
            "type":"Retail Goods"
        }
    ],
    "sg:phone":"+61 3 5382 3605",
    "sg:postcode":"3400",
    "sg:province":"VIC",
    "sg:tags":[
        "lady",
        "wear"
    ],
    "wof:name":"Maria Da Ros Fashions",
    "wof:placetype":"venue"
},
  "geometry": {"coordinates":[142.197433472,-36.7144126892],"type":"Point"}
}