{
  "type": "Feature",
  "properties": {
    "iso:country":"AU",
    "sg:address":"528 City Rd",
    "sg:city":"South Melbourne",
    "sg:classifiers":[
        {
            "category":"Health Services",
            "subcategory":"Health Practitioner",
            "type":"Services"
        }
    ],
    "sg:phone":"+61 3 9696 2180",
    "sg:postcode":"3205",
    "sg:province":"VIC",
    "sg:tags":[
        "physiotherapist"
    ],
    "wof:name":"Walsh Greg",
    "wof:placetype":"venue"
},
  "geometry": {"coordinates":[144.951874,-37.832729],"type":"Point"}
}