{
  "type": "Feature",
  "properties": {
    "addr:full":"101 Old Bells Line Of Rd Kurrajong NSW 2758",
    "addr:housenumber":"101",
    "addr:postcode":"2758",
    "addr:street":"Old Bells Line Of Rd",
    "iso:country":"AU",
    "sg:address":"101 Old Bells Line Of Rd",
    "sg:city":"Kurrajong",
    "sg:classifiers":[
        {
            "category":"Farming",
            "subcategory":"Nursery",
            "type":"Manufacturing & Wholesale Goods"
        }
    ],
    "sg:phone":"+61 2 4573 2586",
    "sg:postcode":"2758",
    "sg:province":"NSW",
    "wof:name":"Hawkesbury Wholesale Nursery",
    "wof:placetype":"venue"
},
  "geometry": {"coordinates":[150.665817261,-33.5544433594],"type":"Point"}
}