{
  "type": "Feature",
  "properties": {
    "addr:full":"14 Karoom St Kariong NSW 2250",
    "addr:housenumber":"14",
    "addr:postcode":"2250",
    "addr:street":"Karoom St",
    "iso:country":"AU",
    "sg:address":"14 Karoom St",
    "sg:city":"Kariong",
    "sg:classifiers":[
        {
            "category":"Professional",
            "type":"Services"
        }
    ],
    "sg:phone":"+61 401 611 991",
    "sg:postcode":"2250",
    "sg:province":"NSW",
    "sg:tags":[
        "courier"
    ],
    "wof:name":"Dan's Carriers",
    "wof:placetype":"venue"
},
  "geometry": {"coordinates":[151.29826355,-33.4349746704],"type":"Point"}
}