{
  "type": "Feature",
  "properties": {
    "addr:full":"Werribee Plaza, Heaths Rd Hoppers Crossing VIC 3029",
    "addr:postcode":"3029",
    "addr:street":"Heaths Rd",
    "iso:country":"AU",
    "sg:address":"Werribee Plaza, Heaths Rd",
    "sg:city":"Hoppers Crossing",
    "sg:classifiers":[
        {
            "category":"Shopping",
            "subcategory":"Music",
            "type":"Retail Goods"
        }
    ],
    "sg:phone":"+61 3 9748 3533",
    "sg:postcode":"3029",
    "sg:province":"VIC",
    "sg:tags":[
        "store"
    ],
    "wof:name":"JB HI-FI",
    "wof:placetype":"venue"
},
  "geometry": {"coordinates":[144.70034799999999,-37.87923],"type":"Point"}
}