{
  "type": "Feature",
  "properties": {
    "addr:full":"54 Curtin St Westcourt QLD 4870",
    "addr:housenumber":"54",
    "addr:postcode":"4870",
    "addr:street":"Curtin St",
    "iso:country":"AU",
    "sg:address":"54 Curtin St",
    "sg:city":"Westcourt",
    "sg:classifiers":[
        {
            "category":"Donuts",
            "subcategory":"None",
            "type":"Food & Drink"
        }
    ],
    "sg:phone":"+61 7 4051 8446",
    "sg:postcode":"4870",
    "sg:province":"QLD",
    "sg:tags":[
        "die",
        "engraver",
        "sinker"
    ],
    "wof:name":"J.C. & D.L. Enterprises",
    "wof:placetype":"venue"
},
  "geometry": {"coordinates":[145.753616333,-16.9259243011],"type":"Point"}
}