{
  "type": "Feature",
  "properties": {
    "iso:country":"AU",
    "sg:address":"52a Trelawney St",
    "sg:city":"Eastwood",
    "sg:classifiers":[
        {
            "category":"Utilities",
            "subcategory":"Electric",
            "type":"Services"
        }
    ],
    "sg:phone":"+61 418 260 411",
    "sg:postcode":"2122",
    "sg:province":"NSW",
    "sg:tags":[
        "electrical",
        "contractor"
    ],
    "wof:name":"G A Eymael Pty Ltd",
    "wof:placetype":"venue"
},
  "geometry": {"coordinates":[151.079833984,-33.7971763611],"type":"Point"}
}