{
  "type": "Feature",
  "properties": {
    "addr:full":"Shp 131 Westfield Eastgardens Eastgardens NSW 2036",
    "addr:housenumber":"131",
    "addr:postcode":"2036",
    "addr:street":"Westfield Eastgardens",
    "iso:country":"AU",
    "sg:address":"Shp 131",
    "sg:city":"Westfield Eastgardens Eastgardens",
    "sg:classifiers":[
        {
            "category":"Health Services",
            "subcategory":"Health Practitioner",
            "type":"Services"
        }
    ],
    "sg:phone":"+61 2 8347 0521",
    "sg:postcode":"2036",
    "sg:province":"NSW",
    "sg:tags":[
        "physiotherapist"
    ],
    "wof:name":"Benchmark Physiotherapy - Eastgardens",
    "wof:placetype":"venue"
},
  "geometry": {"coordinates":[151.22244262699999,-33.9438705444],"type":"Point"}
}