{
  "type": "Feature",
  "properties": {
    "iso:country":"AU",
    "sg:address":"139 Gladstone Rd",
    "sg:city":"Rockhampton",
    "sg:classifiers":[
        {
            "category":"Travel",
            "subcategory":"Hotels & Motels",
            "type":"Entertainment"
        }
    ],
    "sg:phone":"+61 7 4927 7811",
    "sg:postcode":"4700",
    "sg:province":"QLD",
    "wof:name":"Cattle City Motor Inn",
    "wof:placetype":"venue"
},
  "geometry": {"coordinates":[150.50608825699999,-23.3955154419],"type":"Point"}
}