{
  "type": "Feature",
  "properties": {
    "addr:full":"cnr South Tce & Coode St South Perth WA 6151",
    "addr:postcode":"6151",
    "addr:street":"Cnr South Tce & Coode St South",
    "iso:country":"AU",
    "sg:address":"cnr South Tce & Coode St",
    "sg:city":"South Perth",
    "sg:classifiers":[
        {
            "category":"Restaurant",
            "type":"Food & Drink"
        }
    ],
    "sg:phone":"+61 8 9474 9000",
    "sg:postcode":"6151",
    "sg:province":"WA",
    "wof:name":"Dux Cafe Restaurant",
    "wof:placetype":"venue"
},
  "geometry": {"coordinates":[115.864166,-31.979849],"type":"Point"}
}