{
  "type": "Feature",
  "properties": {
    "addr:full":"246 Unley Rd Unley SA 5061",
    "addr:housenumber":"246",
    "addr:postcode":"5061",
    "addr:street":"Unley Rd",
    "iso:country":"AU",
    "sg:address":"246 Unley Rd",
    "sg:city":"Unley",
    "sg:classifiers":[
        {
            "category":"Professional",
            "subcategory":"Printing & Photocopies",
            "type":"Services"
        }
    ],
    "sg:phone":"+61 8 8271 7422",
    "sg:postcode":"5061",
    "sg:province":"SA",
    "sg:tags":[
        "photocopying"
    ],
    "wof:name":"Kwik Kopy Print & Design Centres",
    "wof:placetype":"venue"
},
  "geometry": {"coordinates":[138.607543945,-34.9533157349],"type":"Point"}
}