{
  "type": "Feature",
  "properties": {
    "addr:full":"56 Finch St Bingara NSW 2404",
    "addr:housenumber":"56",
    "addr:postcode":"2404",
    "addr:street":"Finch St",
    "iso:country":"AU",
    "sg:address":"56 Finch St",
    "sg:city":"Bingara",
    "sg:classifiers":[
        {
            "category":"Food & Beverages",
            "subcategory":"Groceries & Convenience Stores",
            "type":"Retail Goods"
        }
    ],
    "sg:phone":"+61 2 6724 1321",
    "sg:postcode":"2404",
    "sg:province":"NSW",
    "wof:name":"Bingara Corner Store & Fuel",
    "wof:placetype":"venue"
},
  "geometry": {"coordinates":[150.569091797,-29.8674755096],"type":"Point"}
}