{
  "type": "Feature",
  "properties": {
    "addr:full":"Unit 8 11 Alloa St Maddington WA 6109",
    "addr:housenumber":"11",
    "addr:postcode":"6109",
    "addr:street":"Alloa St",
    "iso:country":"AU",
    "sg:address":"Unit 8 11 Alloa St",
    "sg:city":"Maddington",
    "sg:classifiers":[
        {
            "category":"Building & Trades",
            "subcategory":"Plumbing",
            "type":"Services"
        }
    ],
    "sg:phone":"+61 8 9459 8533",
    "sg:postcode":"6109",
    "sg:province":"WA",
    "sg:tags":[
        "plumber",
        "gasfitters"
    ],
    "wof:name":"Allstate Plumbing Pty Ltd",
    "wof:placetype":"venue"
},
  "geometry": {"coordinates":[115.98445892300001,-32.044883728],"type":"Point"}
}