{
  "type": "Feature",
  "properties": {
    "iso:country":"AU",
    "sg:address":"Railway Pde",
    "sg:city":"Wingello",
    "sg:classifiers":[
        {
            "category":"Food & Beverages",
            "subcategory":"Groceries & Convenience Stores",
            "type":"Retail Goods"
        }
    ],
    "sg:phone":"+61 2 4884 4340",
    "sg:postcode":"2579",
    "sg:province":"NSW",
    "wof:name":"Wingello General Store",
    "wof:placetype":"venue"
},
  "geometry": {"coordinates":[150.15838623100001,-34.692363739],"type":"Point"}
}