{
  "type": "Feature",
  "properties": {
    "iso:country":"AU",
    "sg:address":"C11, Kanwal Medical Complex 654 Pacific Hwy",
    "sg:city":"Kanwal",
    "sg:classifiers":[
        {
            "category":"Personal",
            "subcategory":"Skin Care",
            "type":"Services"
        }
    ],
    "sg:phone":"+61 2 4392 8850",
    "sg:postcode":"2259",
    "sg:province":"NSW",
    "sg:tags":[
        "hair",
        "product"
    ],
    "wof:name":"Prue Kent Hair & Makeup",
    "wof:placetype":"venue"
},
  "geometry": {"coordinates":[151.48216247600001,-33.2626190186],"type":"Point"}
}