{
  "type": "Feature",
  "properties": {
    "addr:full":"33 Yuilles Road Mornington VIC 3931",
    "addr:housenumber":"33",
    "addr:postcode":"3931",
    "addr:street":"Yuilles Road",
    "iso:country":"AU",
    "sg:address":"33 Yuilles Road",
    "sg:city":"Mornington",
    "sg:classifiers":[
        {
            "category":"Shopping",
            "subcategory":"Bicycles & Sporting Goods",
            "type":"Retail Goods"
        }
    ],
    "sg:phone":"+61 3 5975 8466",
    "sg:postcode":"3931",
    "sg:province":"VIC",
    "sg:tags":[
        "chemical",
        "equipment",
        "pool",
        "swimming"
    ],
    "wof:name":"Mornington Pool & Spa Centre",
    "wof:placetype":"venue"
},
  "geometry": {"coordinates":[145.04570007300001,-38.2313537598],"type":"Point"}
}