{
  "type": "Feature",
  "properties": {
    "addr:full":"2/ 412 Logan River Rd Bethania QLD 4205",
    "addr:housenumber":"/ 412",
    "addr:postcode":"4205",
    "addr:street":"Logan River Rd",
    "iso:country":"AU",
    "sg:address":"2/ 412 Logan River Rd",
    "sg:city":"Bethania",
    "sg:classifiers":[
        {
            "category":"Autos & Motor Vehicles",
            "subcategory":"Motorcycle Sales",
            "type":"Retail Goods"
        }
    ],
    "sg:phone":"+61 7 3805 4611",
    "sg:postcode":"4205",
    "sg:province":"QLD",
    "sg:tags":[
        "outboard"
    ],
    "wof:name":"Hitide Marine",
    "wof:placetype":"venue"
},
  "geometry": {"coordinates":[153.158493042,-27.7013931274],"type":"Point"}
}