{
  "type": "Feature",
  "properties": {
    "iso:country":"AU",
    "sg:address":"Hickory St",
    "sg:city":"Marsden",
    "sg:classifiers":[
        {
            "category":"Education",
            "subcategory":"School",
            "type":"Public Place"
        }
    ],
    "sg:phone":"+61 7 3200 5122",
    "sg:postcode":"4132",
    "sg:province":"QLD",
    "sg:tags":[
        "state",
        "except",
        "nsw"
    ],
    "wof:name":"Marsden Primary",
    "wof:placetype":"venue"
},
  "geometry": {"coordinates":[153.09962463400001,-27.6825656891],"type":"Point"}
}