{
  "type": "Feature",
  "properties": {
    "addr:full":"Unit 2/49- 63 Victoria St Smithfield NSW 2164",
    "addr:housenumber":"63",
    "addr:postcode":"2164",
    "addr:street":"Victoria St",
    "iso:country":"AU",
    "sg:address":"Unit 2/49- 63 Victoria St",
    "sg:city":"Smithfield",
    "sg:classifiers":[
        {
            "category":"Autos & Motor Vehicles",
            "subcategory":"Auto Supplies",
            "type":"Retail Goods"
        }
    ],
    "sg:phone":"+61 2 9604 3777",
    "sg:postcode":"2164",
    "sg:province":"NSW",
    "sg:tags":[
        "wheel",
        "automotive",
        "rim"
    ],
    "wof:name":"Ace Tyres",
    "wof:placetype":"venue"
},
  "geometry": {"coordinates":[150.936599731,-33.8509216309],"type":"Point"}
}