{
  "type": "Feature",
  "properties": {
    "addr:full":"51 Leslie St Winmalee NSW 2777",
    "addr:housenumber":"51",
    "addr:postcode":"2777",
    "addr:street":"Leslie St",
    "iso:country":"AU",
    "sg:address":"51 Leslie St",
    "sg:city":"Winmalee",
    "sg:classifiers":[
        {
            "category":"Health Services",
            "subcategory":"Health Practitioner",
            "type":"Services"
        }
    ],
    "sg:phone":"+61 2 4754 1244",
    "sg:postcode":"2777",
    "sg:province":"NSW",
    "sg:tags":[
        "physiotherapist"
    ],
    "wof:name":"Schafer Enid A",
    "wof:placetype":"venue"
},
  "geometry": {"coordinates":[150.61408996599999,-33.6678962708],"type":"Point"}
}