{
  "type": "Feature",
  "properties": {
    "addr:full":"1 Hogan St Chambers Flat QLD 4133",
    "addr:housenumber":"1",
    "addr:postcode":"4133",
    "addr:street":"Hogan St",
    "iso:country":"AU",
    "sg:address":"1 Hogan St",
    "sg:city":"Chambers Flat",
    "sg:classifiers":[
        {
            "category":"Home & Garden",
            "subcategory":"Garden Supply",
            "type":"Retail Goods"
        }
    ],
    "sg:phone":"+61 7 3297 0986",
    "sg:postcode":"4133",
    "sg:province":"QLD",
    "sg:tags":[
        "turf",
        "lawn"
    ],
    "wof:name":"A Better Lawn",
    "wof:placetype":"venue"
},
  "geometry": {"coordinates":[153.04762268100001,-27.7633838654],"type":"Point"}
}