{
  "type": "Feature",
  "properties": {
    "addr:full":"146 Candlebark Rd Queanbeyan ACT 2620",
    "addr:housenumber":"146",
    "addr:postcode":"2620",
    "addr:street":"Candlebark Rd",
    "iso:country":"AU",
    "sg:address":"146 Candlebark Rd",
    "sg:city":"Queanbeyan",
    "sg:classifiers":[
        {
            "category":"Building & Trades",
            "subcategory":"Construction",
            "type":"Services"
        }
    ],
    "sg:phone":"+61 413 624 849",
    "sg:postcode":"2620",
    "sg:province":"ACT",
    "sg:tags":[
        "concrete",
        "contractor"
    ],
    "wof:name":"Sapphire Concreting",
    "wof:placetype":"venue"
},
  "geometry": {"coordinates":[149.231521606,-35.3769607544],"type":"Point"}
}