{
  "type": "Feature",
  "properties": {
    "addr:full":"165 Young Rd Torrumbarry VIC 3562",
    "addr:housenumber":"165",
    "addr:postcode":"3562",
    "addr:street":"Young Rd",
    "iso:country":"AU",
    "sg:address":"165 Young Rd",
    "sg:city":"Torrumbarry",
    "sg:classifiers":[
        {
            "category":"Retail",
            "subcategory":"Auto Rental",
            "type":"Services"
        }
    ],
    "sg:phone":"+61 3 5487 7259",
    "sg:postcode":"3562",
    "sg:province":"VIC",
    "sg:tags":[
        "car",
        "wedding"
    ],
    "wof:name":"Cobb & Co Horse Drawn Carriages",
    "wof:placetype":"venue"
},
  "geometry": {"coordinates":[144.55335998499999,-36.0334129333],"type":"Point"}
}