{
  "type": "Feature",
  "properties": {
    "addr:full":"141 Bundock St Belgian Gardens QLD 4810",
    "addr:housenumber":"141",
    "addr:postcode":"4810",
    "addr:street":"Bundock St",
    "iso:country":"AU",
    "sg:address":"141 Bundock St",
    "sg:city":"Belgian Gardens",
    "sg:classifiers":[
        {
            "category":"Professional",
            "subcategory":"Engineering",
            "type":"Services"
        }
    ],
    "sg:phone":"+61 7 4724 2541",
    "sg:postcode":"4810",
    "sg:province":"QLD",
    "sg:tags":[
        "electrical",
        "engineer"
    ],
    "wof:name":"Siemens Ltd",
    "wof:placetype":"venue"
},
  "geometry": {"coordinates":[146.78851299999999,-19.251703],"type":"Point"}
}