{
  "type": "Feature",
  "properties": {
    "addr:full":"102 Lagoon St Narrabeen NSW 2101",
    "addr:housenumber":"102",
    "addr:postcode":"2101",
    "addr:street":"Lagoon St",
    "iso:country":"AU",
    "sg:address":"102 Lagoon St",
    "sg:city":"Narrabeen",
    "sg:classifiers":[
        {
            "category":"Education",
            "subcategory":"Kindergarten",
            "type":"Public Place"
        }
    ],
    "sg:phone":"+61 2 9913 1064",
    "sg:postcode":"2101",
    "sg:province":"NSW",
    "sg:tags":[
        "pre-schools"
    ],
    "wof:name":"Our Little Friends Kindergarten",
    "wof:placetype":"venue"
},
  "geometry": {"coordinates":[151.30105599999999,-33.707485],"type":"Point"}
}