{
  "type": "Feature",
  "properties": {
    "addr:full":"Level 1 / 72 Main St Mornington VIC 3931",
    "addr:housenumber":"/ 72",
    "addr:postcode":"3931",
    "addr:street":"Main St",
    "iso:country":"AU",
    "sg:address":"Level 1 / 72 Main St",
    "sg:city":"Mornington",
    "sg:classifiers":[
        {
            "category":"Professional",
            "subcategory":"Management & Consulting",
            "type":"Services"
        }
    ],
    "sg:phone":"+61 3 5975 0312",
    "sg:postcode":"3931",
    "sg:province":"VIC",
    "sg:tags":[
        "consultant",
        "migration"
    ],
    "wof:name":"Obrien migration",
    "wof:placetype":"venue"
},
  "geometry": {"coordinates":[145.03808593799999,-38.2185974121],"type":"Point"}
}