{
  "type": "Feature",
  "properties": {
    "iso:country":"AU",
    "sg:address":"95 Belmont Rd",
    "sg:city":"Mosman",
    "sg:classifiers":[
        {
            "category":"Professional",
            "subcategory":"Art Services",
            "type":"Services"
        }
    ],
    "sg:phone":"+61 2 9969 1133",
    "sg:postcode":"2088",
    "sg:province":"NSW",
    "sg:tags":[
        "interior",
        "decorator"
    ],
    "wof:name":"Mosman Interiors",
    "wof:placetype":"venue"
},
  "geometry": {"coordinates":[151.23764038100001,-33.822063446],"type":"Point"}
}