{
  "type": "Feature",
  "properties": {
    "iso:country":"AU",
    "sg:address":"102 Wood St",
    "sg:city":"Gol Gol",
    "sg:classifiers":[
        {
            "category":"Building & Trades",
            "subcategory":"Construction",
            "type":"Services"
        }
    ],
    "sg:phone":"+61 3 5024 8684",
    "sg:postcode":"2738",
    "sg:province":"NSW",
    "sg:tags":[
        "earth",
        "excavating",
        "moving",
        "contractor"
    ],
    "wof:name":"City Bobcat Hire",
    "wof:placetype":"venue"
},
  "geometry": {"coordinates":[142.219757,-34.177044],"type":"Point"}
}