{
  "type": "Feature",
  "properties": {
    "addr:full":"196 Kinghorne St Nowra NSW 2541",
    "addr:housenumber":"196",
    "addr:postcode":"2541",
    "addr:street":"Kinghorne St",
    "iso:country":"AU",
    "sg:address":"196 Kinghorne St",
    "sg:city":"Nowra",
    "sg:classifiers":[
        {
            "category":"Health Services",
            "subcategory":"Dentist",
            "type":"Services"
        }
    ],
    "sg:phone":"+61 2 4423 3200",
    "sg:postcode":"2541",
    "sg:province":"NSW",
    "sg:tags":[
        "dental",
        "prosthetist"
    ],
    "wof:name":"Hancock Brett T.",
    "wof:placetype":"venue"
},
  "geometry": {"coordinates":[150.60122680699999,-34.8843460083],"type":"Point"}
}