{
  "type": "Feature",
  "properties": {
    "addr:full":"Alton St Cuballing WA 6311",
    "addr:postcode":"6311",
    "addr:street":"Alton St",
    "iso:country":"AU",
    "sg:address":"Alton St",
    "sg:city":"Cuballing",
    "sg:classifiers":[
        {
            "category":"Travel",
            "subcategory":"Hotels & Motels",
            "type":"Entertainment"
        }
    ],
    "sg:phone":"+61 8 9883 6032",
    "sg:postcode":"6311",
    "sg:province":"WA",
    "sg:tags":[
        "accommodation"
    ],
    "wof:name":"Cuballing Tavern",
    "wof:placetype":"venue"
},
  "geometry": {"coordinates":[117.17780304,-32.8169174194],"type":"Point"}
}