{
  "type": "Feature",
  "properties": {
    "addr:full":"47 Blackwood St Mitchelton QLD 4053",
    "addr:housenumber":"47",
    "addr:postcode":"4053",
    "addr:street":"Blackwood St",
    "iso:country":"AU",
    "sg:address":"47 Blackwood St",
    "sg:city":"Mitchelton",
    "sg:classifiers":[
        {
            "category":"Restaurant",
            "type":"Food & Drink"
        }
    ],
    "sg:phone":"+61 7 3355 9627",
    "sg:postcode":"4053",
    "sg:province":"QLD",
    "wof:name":"Des Alpes Swiss Restaurant",
    "wof:placetype":"venue"
},
  "geometry": {"coordinates":[152.974487305,-27.4118251801],"type":"Point"}
}