{
  "type": "Feature",
  "properties": {
    "iso:country":"AU",
    "sg:address":"485 Darling St",
    "sg:city":"Balmain",
    "sg:classifiers":[
        {
            "category":"Personal",
            "subcategory":"Beauty Salon",
            "type":"Services"
        }
    ],
    "sg:phone":"+61 2 9810 6375",
    "sg:postcode":"2041",
    "sg:province":"NSW",
    "sg:tags":[
        "hairdresser"
    ],
    "wof:name":"Boom (Hair & Health)",
    "wof:placetype":"venue"
},
  "geometry": {"coordinates":[151.17271400000001,-33.856426],"type":"Point"}
}