{
  "type": "Feature",
  "properties": {
    "iso:country":"AU",
    "sg:address":"56 Dunlop St",
    "sg:city":"Kelso",
    "sg:classifiers":[
        {
            "category":"Building & Trades",
            "subcategory":"Equipment Rental",
            "type":"Services"
        }
    ],
    "sg:phone":"+61 407 125 250",
    "sg:postcode":"4815",
    "sg:province":"QLD",
    "sg:tags":[
        "party",
        "hire"
    ],
    "wof:name":"Kool Kidz Car Hire",
    "wof:placetype":"venue"
},
  "geometry": {"coordinates":[146.72378499999999,-19.392527],"type":"Point"}
}