{
  "type": "Feature",
  "properties": {
    "iso:country":"AU",
    "sg:address":"Cnr Elder St & Old Dandenong Rd",
    "sg:city":"Heatherton",
    "sg:classifiers":[
        {
            "category":"Home & Garden",
            "subcategory":"Garden Supply",
            "type":"Retail Goods"
        }
    ],
    "sg:phone":"+61 3 9558 1077",
    "sg:postcode":"3202",
    "sg:province":"VIC",
    "sg:tags":[
        "nursery"
    ],
    "wof:name":"Heath Horticultural Transport",
    "wof:placetype":"venue"
},
  "geometry": {"coordinates":[145.09906005900001,-37.9485282898],"type":"Point"}
}