{
  "type": "Feature",
  "properties": {
    "iso:country":"AU",
    "sg:address":"529 Wanneroo Rd",
    "sg:city":"Woodvale",
    "sg:classifiers":[
        {
            "category":"Restaurant",
            "type":"Food & Drink"
        }
    ],
    "sg:phone":"+61 8 9409 1516",
    "sg:postcode":"6026",
    "sg:province":"WA",
    "wof:name":"Conti Restaurant",
    "wof:placetype":"venue"
},
  "geometry": {"coordinates":[115.81082916299999,-31.7884902954],"type":"Point"}
}