{
  "type": "Feature",
  "properties": {
    "addr:full":"191 Roslyn Rd Belmont VIC 3216",
    "addr:housenumber":"191",
    "addr:postcode":"3216",
    "addr:street":"Roslyn Rd",
    "iso:country":"AU",
    "sg:address":"191 Roslyn Rd",
    "sg:city":"Belmont",
    "sg:classifiers":[
        {
            "category":"Government",
            "subcategory":"Court House",
            "type":"Public Place"
        }
    ],
    "sg:phone":"+61 3 5243 9241",
    "sg:postcode":"3216",
    "sg:province":"VIC",
    "sg:tags":[
        "personal",
        "marriage",
        "family",
        "counselling"
    ],
    "wof:name":"Lorraine Newton",
    "wof:placetype":"venue"
},
  "geometry": {"coordinates":[144.32815551799999,-38.1737518311],"type":"Point"}
}