{
  "type": "Feature",
  "properties": {
    "addr:full":"143 Turrella St Turrella NSW 2205",
    "addr:housenumber":"143",
    "addr:postcode":"2205",
    "addr:street":"Turrella St",
    "iso:country":"AU",
    "sg:address":"143 Turrella St",
    "sg:city":"Turrella",
    "sg:classifiers":[
        {
            "category":"Retail",
            "subcategory":"Auto Repair",
            "type":"Services"
        }
    ],
    "sg:phone":"+61 2 9567 8168",
    "sg:postcode":"2205",
    "sg:province":"NSW",
    "sg:tags":[
        "repairer",
        "motor",
        "engineer"
    ],
    "wof:name":"Bill's Automotive Repairs & Services",
    "wof:placetype":"venue"
},
  "geometry": {"coordinates":[151.14262400000001,-33.929283],"type":"Point"}
}