{
  "type": "Feature",
  "properties": {
    "iso:country":"AU",
    "sg:address":"PO Box 70",
    "sg:city":"Ardrossan",
    "sg:classifiers":[
        {
            "category":"Farming",
            "subcategory":"Farm & Veterinary Services",
            "type":"Manufacturing & Wholesale Goods"
        }
    ],
    "sg:phone":"+61 8 8837 3993",
    "sg:postcode":"5571",
    "sg:province":"SA",
    "sg:tags":[
        "agricultural",
        "advisory"
    ],
    "wof:name":"Ag Consulting Co",
    "wof:placetype":"venue"
},
  "geometry": {"coordinates":[137.910430908,-34.422088623],"type":"Point"}
}