{
  "type": "Feature",
  "properties": {
    "addr:full":"26 Warrawong Drv Berwick VIC 3806",
    "addr:housenumber":"26",
    "addr:postcode":"3806",
    "addr:street":"Warrawong Drv",
    "iso:country":"AU",
    "sg:address":"26 Warrawong Drv",
    "sg:city":"Berwick",
    "sg:classifiers":[
        {
            "category":"Building & Trades",
            "subcategory":"Equipment Rental",
            "type":"Services"
        }
    ],
    "sg:phone":"+61 3 9704 0439",
    "sg:postcode":"3806",
    "sg:province":"VIC",
    "sg:tags":[
        "fitness"
    ],
    "wof:name":"Eclipse Sporting Surfaces",
    "wof:placetype":"venue"
},
  "geometry": {"coordinates":[145.32650756800001,-38.016784668],"type":"Point"}
}