{
  "type": "Feature",
  "properties": {
    "addr:full":"Shop 5/ 197 Days Rd Grange QLD 4051",
    "addr:housenumber":"shop 5 / 197",
    "addr:postcode":"4051",
    "addr:street":"Days Rd",
    "iso:country":"AU",
    "sg:address":"Shop 5/ 197 Days Rd",
    "sg:city":"Grange",
    "sg:classifiers":[
        {
            "category":"Health Services",
            "subcategory":"Doctor",
            "type":"Services"
        }
    ],
    "sg:phone":"+61 7 3356 7744",
    "sg:postcode":"4051",
    "sg:province":"QLD",
    "sg:tags":[
        "medical",
        "practitioner"
    ],
    "wof:name":"Ryan Helen Dr",
    "wof:placetype":"venue"
},
  "geometry": {"coordinates":[153.01451110799999,-27.4258174896],"type":"Point"}
}