{
  "type": "Feature",
  "properties": {
    "iso:country":"AU",
    "sg:address":"31 Goulburn St",
    "sg:city":"Nagambie",
    "sg:classifiers":[
        {
            "category":"Education",
            "subcategory":"School",
            "type":"Public Place"
        }
    ],
    "sg:phone":"+61 3 5794 2273",
    "sg:postcode":"3608",
    "sg:province":"VIC",
    "sg:tags":[
        "state",
        "except",
        "nsw"
    ],
    "wof:name":"Nagambie Primary School",
    "wof:placetype":"venue"
},
  "geometry": {"coordinates":[145.157302856,-36.7874565125],"type":"Point"}
}