{
  "type": "Feature",
  "properties": {
    "iso:country":"AU",
    "sg:address":"Unit 3 7 Bayswater Rd",
    "sg:city":"Hyde Park",
    "sg:classifiers":[
        {
            "category":"Health Services",
            "subcategory":"Doctor",
            "type":"Services"
        }
    ],
    "sg:phone":"+61 7 4721 4483",
    "sg:postcode":"4812",
    "sg:province":"QLD",
    "sg:tags":[
        "medical",
        "practitioner"
    ],
    "wof:name":"Low Bruce",
    "wof:placetype":"venue"
},
  "geometry": {"coordinates":[146.799866,-19.277185],"type":"Point"}
}