{
  "type": "Feature",
  "properties": {
    "addr:full":"10 Brunker Rd Chullora NSW 2190",
    "addr:housenumber":"10",
    "addr:postcode":"2190",
    "addr:street":"Brunker Rd",
    "iso:country":"AU",
    "sg:address":"10 Brunker Rd",
    "sg:city":"Chullora",
    "sg:classifiers":[
        {
            "category":"Professional",
            "type":"Services"
        }
    ],
    "sg:phone":"+61 2 9796 9992",
    "sg:postcode":"2190",
    "sg:province":"NSW",
    "sg:tags":[
        "transport"
    ],
    "wof:name":"Toll Fleet",
    "wof:placetype":"venue"
},
  "geometry": {"coordinates":[151.039627,-33.899185],"type":"Point"}
}