{
  "type": "Feature",
  "properties": {
    "addr:full":"27 Monaro St Queanbeyan ACT 2620",
    "addr:housenumber":"27",
    "addr:postcode":"2620",
    "addr:street":"Monaro St",
    "iso:country":"AU",
    "sg:address":"27 Monaro St",
    "sg:city":"Queanbeyan",
    "sg:classifiers":[
        {
            "category":"Real Estate",
            "subcategory":"Real Estate Agent",
            "type":"Services"
        }
    ],
    "sg:phone":"+61 2 6297 7799",
    "sg:postcode":"2620",
    "sg:province":"ACT",
    "wof:name":"Oz Property Services Pty Ltd",
    "wof:placetype":"venue"
},
  "geometry": {"coordinates":[149.23272705100001,-35.3539237976],"type":"Point"}
}