{
  "type": "Feature",
  "properties": {
    "addr:full":"57 Beeville Rd Petrie QLD 4502",
    "addr:housenumber":"57",
    "addr:postcode":"4502",
    "addr:street":"Beeville Rd",
    "iso:country":"AU",
    "sg:address":"57 Beeville Rd",
    "sg:city":"Petrie",
    "sg:classifiers":[
        {
            "category":"Wholesale",
            "subcategory":"Photographic Equipment",
            "type":"Manufacturing & Wholesale Goods"
        }
    ],
    "sg:phone":"+61 7 3285 5724",
    "sg:postcode":"4502",
    "sg:province":"QLD",
    "sg:tags":[
        "wholesaler",
        "mfrs",
        "supply"
    ],
    "wof:name":"Accurate Instrument Servicing Pty Ltd",
    "wof:placetype":"venue"
},
  "geometry": {"coordinates":[152.96522522000001,-27.2623634338],"type":"Point"}
}