{
  "type": "Feature",
  "properties": {
    "iso:country":"AU",
    "sg:address":"5 Dianella St",
    "sg:city":"Sunnybank",
    "sg:classifiers":[
        {
            "category":"Travel",
            "subcategory":"Travel Agent",
            "type":"Entertainment"
        }
    ],
    "sg:phone":"+61 7 3423 8900",
    "sg:postcode":"4109",
    "sg:province":"QLD",
    "sg:tags":[
        "consultant"
    ],
    "wof:name":"Princess Cruise Booking",
    "wof:placetype":"venue"
},
  "geometry": {"coordinates":[153.06967163100001,-27.5739173889],"type":"Point"}
}