{
  "type": "Feature",
  "properties": {
    "addr:full":"Old York Rd Light Industrial Area Northam WA 6401",
    "addr:postcode":"6401",
    "addr:street":"Old York Rd;Area",
    "iso:country":"AU",
    "sg:address":"Old York Rd Light Industrial Area",
    "sg:city":"Northam",
    "sg:classifiers":[
        {
            "category":"Professional",
            "subcategory":"Printing & Photocopies",
            "type":"Services"
        }
    ],
    "sg:phone":"+61 8 9622 3537",
    "sg:postcode":"6401",
    "sg:province":"WA",
    "sg:tags":[
        "screen",
        "printer"
    ],
    "wof:name":"Way Signs",
    "wof:placetype":"venue"
},
  "geometry": {"coordinates":[116.67897796600001,-31.6476097107],"type":"Point"}
}