{
  "type": "Feature",
  "properties": {
    "addr:full":"21 Merewyn St Burpengary QLD 4505",
    "addr:housenumber":"21",
    "addr:postcode":"4505",
    "addr:street":"Merewyn St",
    "iso:country":"AU",
    "sg:address":"21 Merewyn St",
    "sg:city":"Burpengary",
    "sg:classifiers":[
        {
            "category":"Building & Trades",
            "subcategory":"Construction",
            "type":"Services"
        }
    ],
    "sg:phone":"+61 418 725 377",
    "sg:postcode":"4505",
    "sg:province":"QLD",
    "sg:tags":[
        "joiner",
        "carpenter"
    ],
    "wof:name":"Cappiello T",
    "wof:placetype":"venue"
},
  "geometry": {"coordinates":[152.96060180699999,-27.1597976685],"type":"Point"}
}