{
  "type": "Feature",
  "properties": {
    "addr:full":"27 Nettlefold St Belconnen ACT 2616",
    "addr:housenumber":"27",
    "addr:postcode":"2616",
    "addr:street":"Nettlefold St",
    "iso:country":"AU",
    "sg:address":"27 Nettlefold St",
    "sg:city":"Belconnen",
    "sg:classifiers":[
        {
            "category":"Retail",
            "subcategory":"Auto Repair",
            "type":"Services"
        }
    ],
    "sg:phone":"+61 2 6251 6160",
    "sg:postcode":"2616",
    "sg:province":"ACT",
    "sg:tags":[
        "beater",
        "painter",
        "panel"
    ],
    "wof:name":"Belconnen Auto Refinishers",
    "wof:placetype":"venue"
},
  "geometry": {"coordinates":[149.05894470199999,-35.2406654358],"type":"Point"}
}