{
  "type": "Feature",
  "properties": {
    "iso:country":"AU",
    "sg:address":"1/ 449 Darling St",
    "sg:city":"Balmain",
    "sg:classifiers":[
        {
            "category":"Health Services",
            "subcategory":"Doctor",
            "type":"Services"
        }
    ],
    "sg:phone":"+61 2 9555 8816",
    "sg:postcode":"2041",
    "sg:province":"NSW",
    "sg:tags":[
        "medical",
        "practitioner"
    ],
    "wof:name":"Morris Catherine Dr",
    "wof:placetype":"venue"
},
  "geometry": {"coordinates":[151.173828,-33.855984],"type":"Point"}
}