{
  "type": "Feature",
  "properties": {
    "addr:full":"Shop 3, 5 Markwell St Kingaroy QLD 4610",
    "addr:housenumber":"shop;5",
    "addr:postcode":"4610",
    "addr:street":"Markwell St",
    "iso:country":"AU",
    "sg:address":"Shop 3, 5 Markwell St",
    "sg:city":"Kingaroy",
    "sg:classifiers":[
        {
            "category":"Retail",
            "subcategory":"Auto Repair",
            "type":"Services"
        }
    ],
    "sg:phone":"+61 7 4162 7844",
    "sg:postcode":"4610",
    "sg:province":"QLD",
    "sg:tags":[
        "body",
        "motor",
        "trimmer"
    ],
    "wof:name":"Kingaroy Motor Trimming & Upholstery",
    "wof:placetype":"venue"
},
  "geometry": {"coordinates":[151.840576172,-26.543050766],"type":"Point"}
}