{
  "type": "Feature",
  "properties": {
    "addr:full":"45 Rosedale Rd Gordon NSW 2072",
    "addr:housenumber":"45",
    "addr:postcode":"2072",
    "addr:street":"Rosedale Rd",
    "iso:country":"AU",
    "sg:address":"45 Rosedale Rd",
    "sg:city":"Gordon",
    "sg:classifiers":[
        {
            "category":"Personal",
            "subcategory":"Beauty Salon",
            "type":"Services"
        }
    ],
    "sg:phone":"+61 2 9499 2192",
    "sg:postcode":"2072",
    "sg:province":"NSW",
    "wof:name":"At Jayz",
    "wof:placetype":"venue"
},
  "geometry": {"coordinates":[151.15760803200001,-33.7474555969],"type":"Point"}
}