{
  "type": "Feature",
  "properties": {
    "iso:country":"AU",
    "sg:address":"62 Brighton St",
    "sg:city":"Harbord",
    "sg:classifiers":[
        {
            "category":"Retail",
            "subcategory":"Repair Shop",
            "type":"Services"
        }
    ],
    "sg:phone":"+61 2 9905 9181",
    "sg:postcode":"2096",
    "sg:province":"NSW",
    "sg:tags":[
        "maintenance",
        "pool",
        "swimming"
    ],
    "wof:name":"Northside Pool Pump Repairs",
    "wof:placetype":"venue"
},
  "geometry": {"coordinates":[151.28195190400001,-33.7697906494],"type":"Point"}
}