{
  "type": "Feature",
  "properties": {
    "addr:full":"31 Chifley St Smithfield NSW 2164",
    "addr:housenumber":"31",
    "addr:postcode":"2164",
    "addr:street":"Chifley St",
    "iso:country":"AU",
    "sg:address":"31 Chifley St",
    "sg:city":"Smithfield",
    "sg:classifiers":[
        {
            "category":"Professional",
            "subcategory":"Engineering",
            "type":"Services"
        }
    ],
    "sg:phone":"+61 2 9604 5863",
    "sg:postcode":"2164",
    "sg:province":"NSW",
    "sg:tags":[
        "engineer"
    ],
    "wof:name":"Newby Engineering Pty Ltd",
    "wof:placetype":"venue"
},
  "geometry": {"coordinates":[150.93458557100001,-33.8482933044],"type":"Point"}
}