{
  "type": "Feature",
  "properties": {
    "iso:country":"AU",
    "sg:address":"53 Rundle St",
    "sg:city":"Kent Town",
    "sg:classifiers":[
        {
            "category":"Professional",
            "subcategory":"Printing & Photocopies",
            "type":"Services"
        }
    ],
    "sg:phone":"+61 8 7421 2000",
    "sg:postcode":"5067",
    "sg:province":"SA",
    "sg:tags":[
        "photocopier"
    ],
    "wof:name":"Kyocera Mita Australia Pty Ltd",
    "wof:placetype":"venue"
},
  "geometry": {"coordinates":[138.617553711,-34.9207725525],"type":"Point"}
}