{
  "type": "Feature",
  "properties": {
    "addr:full":"94 Batman St West Melbourne VIC 3003",
    "addr:housenumber":"94",
    "addr:postcode":"3003",
    "addr:street":"Batman St",
    "iso:country":"AU",
    "sg:address":"94 Batman St",
    "sg:city":"West Melbourne",
    "sg:classifiers":[
        {
            "category":"Retail",
            "subcategory":"Car Wash",
            "type":"Services"
        }
    ],
    "sg:phone":"+61 3 9326 7797",
    "sg:postcode":"3003",
    "sg:province":"VIC",
    "sg:tags":[
        "truck",
        "cleaning"
    ],
    "wof:name":"Imac Car Wash & Detailing",
    "wof:placetype":"venue"
},
  "geometry": {"coordinates":[144.95002746599999,-37.8110237122],"type":"Point"}
}