{
  "type": "Feature",
  "properties": {
    "addr:full":"The Cabin 1a Liverpool St Bundeena NSW 2230",
    "addr:housenumber":"1a",
    "addr:postcode":"2230",
    "addr:street":"Liverpool St",
    "iso:country":"AU",
    "sg:address":"The Cabin 1a Liverpool St",
    "sg:city":"Bundeena",
    "sg:classifiers":[
        {
            "category":"Manufacturing",
            "subcategory":"Musical Instruments",
            "type":"Manufacturing & Wholesale Goods"
        }
    ],
    "sg:phone":"+61 2 9527 7975",
    "sg:postcode":"2230",
    "sg:province":"NSW",
    "sg:tags":[
        "therapist",
        "music"
    ],
    "wof:name":"Karen Cregan RMT",
    "wof:placetype":"venue"
},
  "geometry": {"coordinates":[151.14707946799999,-34.0831108093],"type":"Point"}
}