{
  "type": "Feature",
  "properties": {
    "iso:country":"AU",
    "sg:address":"1 / 29 Gibbs St",
    "sg:city":"Arundel",
    "sg:classifiers":[
        {
            "category":"Shopping",
            "subcategory":"Crafts & Fabrics",
            "type":"Retail Goods"
        }
    ],
    "sg:phone":"+61 7 5529 2767",
    "sg:postcode":"4214",
    "sg:province":"QLD",
    "sg:tags":[
        "supply"
    ],
    "wof:name":"Egg Decorating Supplies",
    "wof:placetype":"venue"
},
  "geometry": {"coordinates":[153.38278198200001,-27.9368877411],"type":"Point"}
}