{
  "type": "Feature",
  "properties": {
    "addr:full":"525 Lytton Rd Morningside QLD 4170",
    "addr:housenumber":"525",
    "addr:postcode":"4170",
    "addr:street":"Lytton Rd",
    "iso:country":"AU",
    "sg:address":"525 Lytton Rd",
    "sg:city":"Morningside",
    "sg:classifiers":[
        {
            "category":"Wholesale",
            "subcategory":"Construction Materials",
            "type":"Manufacturing & Wholesale Goods"
        }
    ],
    "sg:phone":"+61 7 3899 9877",
    "sg:postcode":"4170",
    "sg:province":"QLD",
    "sg:tags":[
        "protective",
        "coating"
    ],
    "wof:name":"Epirez",
    "wof:placetype":"venue"
},
  "geometry": {"coordinates":[153.098266602,-27.4569225311],"type":"Point"}
}