{
  "type": "Feature",
  "properties": {
    "addr:full":"Greenbah Rd Moree NSW 2400",
    "addr:postcode":"2400",
    "addr:street":"Greenbah Rd",
    "iso:country":"AU",
    "sg:address":"Greenbah Rd",
    "sg:city":"Moree",
    "sg:classifiers":[
        {
            "category":"Insurance",
            "subcategory":"Insurance Agent",
            "type":"Services"
        }
    ],
    "sg:phone":"+61 2 6759 1500",
    "sg:postcode":"2400",
    "sg:province":"NSW",
    "wof:name":"IAMA Insurance",
    "wof:placetype":"venue"
},
  "geometry": {"coordinates":[149.82818603499999,-29.4621391296],"type":"Point"}
}