{
  "type": "Feature",
  "properties": {
    "addr:full":"1/ 4a Hollylea Rd Leumeah NSW 2560",
    "addr:housenumber":"/ 4a",
    "addr:postcode":"2560",
    "addr:street":"Hollylea Rd",
    "iso:country":"AU",
    "sg:address":"1/ 4a Hollylea Rd",
    "sg:city":"Leumeah",
    "sg:classifiers":[
        {
            "category":"Manufacturing",
            "subcategory":"Tools & Machinery",
            "type":"Manufacturing & Wholesale Goods"
        }
    ],
    "sg:phone":"+61 2 4625 2111",
    "sg:postcode":"2560",
    "sg:province":"NSW",
    "wof:name":"Glenfords Tool Centre",
    "wof:placetype":"venue"
},
  "geometry": {"coordinates":[150.827926636,-34.0504722595],"type":"Point"}
}