{
  "type": "Feature",
  "properties": {
    "addr:full":"171 Balo St Moree NSW 2400",
    "addr:housenumber":"171",
    "addr:postcode":"2400",
    "addr:street":"Balo St",
    "iso:country":"AU",
    "sg:address":"171 Balo St",
    "sg:city":"Moree",
    "sg:classifiers":[
        {
            "category":"Fast Food",
            "type":"Food & Drink"
        }
    ],
    "sg:phone":"+61 2 6752 4979",
    "sg:postcode":"2400",
    "sg:province":"NSW",
    "sg:tags":[
        "away",
        "take"
    ],
    "wof:name":"Jack's Take Away",
    "wof:placetype":"venue"
},
  "geometry": {"coordinates":[149.84144592300001,-29.4651241302],"type":"Point"}
}