{
  "type": "Feature",
  "properties": {
    "iso:country":"AU",
    "sg:address":"110 Lemon Tree Passage Rd",
    "sg:city":"Salt Ash",
    "sg:classifiers":[
        {
            "category":"Farming",
            "subcategory":"Fish & Marine Products",
            "type":"Manufacturing & Wholesale Goods"
        }
    ],
    "sg:phone":"+61 2 4982 6249",
    "sg:postcode":"2318",
    "sg:province":"NSW",
    "sg:tags":[
        "supplier",
        "oyster",
        "farmer"
    ],
    "wof:name":"Kelly J W & B",
    "wof:placetype":"venue"
},
  "geometry": {"coordinates":[151.92889400000001,-32.778748],"type":"Point"}
}