{
  "type": "Feature",
  "properties": {
    "iso:country":"AU",
    "sg:address":"Shp2/ 1 Railway St",
    "sg:city":"Corrimal East",
    "sg:classifiers":[
        {
            "category":"Shopping",
            "subcategory":"Clothing, Apparel, & Fashions",
            "type":"Retail Goods"
        }
    ],
    "sg:phone":"+61 2 4283 1862",
    "sg:postcode":"2518",
    "sg:province":"NSW",
    "sg:tags":[
        "lady",
        "wear"
    ],
    "wof:name":"Total Fashion",
    "wof:placetype":"venue"
},
  "geometry": {"coordinates":[150.908768,-34.374809],"type":"Point"}
}