{
  "type": "Feature",
  "properties": {
    "addr:full":"Unit 2, 330 Curtin Ave (West) Eagle Farm QLD 4009",
    "addr:housenumber":"330",
    "addr:postcode":"4009",
    "addr:street":"Curtin Ave West",
    "iso:country":"AU",
    "sg:address":"Unit 2, 330 Curtin Ave (West)",
    "sg:city":"Eagle Farm",
    "sg:classifiers":[
        {
            "category":"Building & Trades",
            "subcategory":"Construction",
            "type":"Services"
        }
    ],
    "sg:phone":"+61 7 3868 4411",
    "sg:postcode":"4009",
    "sg:province":"QLD",
    "sg:tags":[
        "insulation",
        "contractor"
    ],
    "wof:name":"Industrial & Marine Insulation",
    "wof:placetype":"venue"
},
  "geometry": {"coordinates":[153.08851623499999,-27.4394054413],"type":"Point"}
}