{
  "type": "Feature",
  "properties": {
    "addr:full":"388 Barkly St Brunswick VIC 3056",
    "addr:housenumber":"388",
    "addr:postcode":"3056",
    "addr:street":"Barkly St",
    "iso:country":"AU",
    "sg:address":"388 Barkly St",
    "sg:city":"Brunswick",
    "sg:classifiers":[
        {
            "category":"Autos & Motor Vehicles",
            "subcategory":"Auto Supplies",
            "type":"Retail Goods"
        }
    ],
    "sg:phone":"+61 3 9380 6144",
    "sg:postcode":"3056",
    "sg:province":"VIC",
    "sg:tags":[
        "paint",
        "automotive"
    ],
    "wof:name":"Automotive Paint Supplies Pty Ltd",
    "wof:placetype":"venue"
},
  "geometry": {"coordinates":[144.956542969,-37.7756881714],"type":"Point"}
}