{
  "type": "Feature",
  "properties": {
    "iso:country":"AU",
    "sg:address":"49 Prince St",
    "sg:city":"Busselton",
    "sg:classifiers":[
        {
            "category":"Personal",
            "subcategory":"Beauty Salon",
            "type":"Services"
        }
    ],
    "sg:phone":"+61 8 9751 1811",
    "sg:postcode":"6280",
    "sg:province":"WA",
    "sg:tags":[
        "hairdresser"
    ],
    "wof:name":"Hair Bazaar",
    "wof:placetype":"venue"
},
  "geometry": {"coordinates":[115.345359802,-33.6508026123],"type":"Point"}
}