{
  "type": "Feature",
  "properties": {
    "addr:full":"Shp 5/ 5 Keats Ave Rockdale NSW 2216",
    "addr:housenumber":"/ 5",
    "addr:postcode":"2216",
    "addr:street":"Keats Ave",
    "iso:country":"AU",
    "sg:address":"Shp 5/ 5 Keats Ave",
    "sg:city":"Rockdale",
    "sg:classifiers":[
        {
            "category":"Travel",
            "subcategory":"Travel Agent",
            "type":"Entertainment"
        }
    ],
    "sg:phone":"+61 1300 884 737",
    "sg:postcode":"2216",
    "sg:province":"NSW",
    "sg:tags":[
        "consultant"
    ],
    "wof:name":"Kompas Travel",
    "wof:placetype":"venue"
},
  "geometry": {"coordinates":[151.13717700000001,-33.953133],"type":"Point"}
}