{
  "type": "Feature",
  "properties": {
    "iso:country":"AU",
    "sg:address":"Unit 3, Mcintosh Centre Mirrabooka Ave",
    "sg:city":"Moruya",
    "sg:classifiers":[
        {
            "category":"Personal",
            "subcategory":"Beauty Salon",
            "type":"Services"
        }
    ],
    "sg:phone":"+61 2 4474 2829",
    "sg:postcode":"2537",
    "sg:province":"NSW",
    "sg:tags":[
        "hairdresser"
    ],
    "wof:name":"Tanya's Hair Studio",
    "wof:placetype":"venue"
},
  "geometry": {"coordinates":[150.07939148,-35.9109954834],"type":"Point"}
}