{
  "type": "Feature",
  "properties": {
    "addr:full":"Suite 11/4 Ilya Ave Erina NSW 2250",
    "addr:housenumber":"11 / 4",
    "addr:postcode":"2250",
    "addr:street":"Ilya Ave",
    "iso:country":"AU",
    "sg:address":"Suite 11/4 Ilya Ave",
    "sg:city":"Erina",
    "sg:classifiers":[
        {
            "category":"Personal",
            "subcategory":"Tanning Parlor",
            "type":"Services"
        }
    ],
    "sg:phone":"+61 2 4365 0009",
    "sg:postcode":"2250",
    "sg:province":"NSW",
    "sg:tags":[
        "solarium"
    ],
    "wof:name":"Ergo Sun",
    "wof:placetype":"venue"
},
  "geometry": {"coordinates":[151.38421630900001,-33.4397659302],"type":"Point"}
}