{
  "type": "Feature",
  "properties": {
    "addr:full":"4/ 25 Industry Drv Tweed Heads South QLD 2486",
    "addr:housenumber":"/ 25",
    "addr:postcode":"2486",
    "addr:street":"Industry Drv",
    "iso:country":"AU",
    "sg:address":"4/ 25 Industry Drv",
    "sg:city":"Tweed Heads South",
    "sg:classifiers":[
        {
            "category":"Professional",
            "subcategory":"Art Services",
            "type":"Services"
        }
    ],
    "sg:phone":"+61 7 5523 4101",
    "sg:postcode":"2486",
    "sg:province":"QLD",
    "sg:tags":[
        "picture",
        "frame",
        "framing"
    ],
    "wof:name":"Coastal Framing & Design",
    "wof:placetype":"venue"
},
  "geometry": {"coordinates":[153.53924560600001,-28.2007675171],"type":"Point"}
}