{
  "type": "Feature",
  "properties": {
    "addr:full":"Unit 2, 46 Margaret Vella Drv Paget QLD 4740",
    "addr:housenumber":"46",
    "addr:postcode":"4740",
    "addr:street":"Margaret Vella Drv",
    "iso:country":"AU",
    "sg:address":"Unit 2, 46 Margaret Vella Drv",
    "sg:city":"Paget",
    "sg:classifiers":[
        {
            "category":"Autos & Motor Vehicles",
            "subcategory":"Auto Supplies",
            "type":"Retail Goods"
        }
    ],
    "sg:phone":"+61 7 4952 4900",
    "sg:postcode":"4740",
    "sg:province":"QLD",
    "sg:tags":[
        "equipment",
        "part",
        "truck"
    ],
    "wof:name":"Truckline Truck & Trailer Parts",
    "wof:placetype":"venue"
},
  "geometry": {"coordinates":[149.16098,-21.171959],"type":"Point"}
}