{
  "type": "Feature",
  "properties": {
    "iso:country":"AU",
    "sg:address":"276 Kent St",
    "sg:city":"Maryborough",
    "sg:classifiers":[
        {
            "category":"Professional",
            "subcategory":"Computer Services",
            "type":"Services"
        }
    ],
    "sg:phone":"+61 7 4123 6311",
    "sg:postcode":"4650",
    "sg:province":"QLD",
    "sg:tags":[
        "repairs",
        "upgrade",
        "equipment"
    ],
    "wof:name":"Axiom Computers",
    "wof:placetype":"venue"
},
  "geometry": {"coordinates":[152.698715,-25.535141],"type":"Point"}
}