{
  "type": "Feature",
  "properties": {
    "addr:full":"23 Avalon Pde Avalon NSW 2107",
    "addr:housenumber":"23",
    "addr:postcode":"2107",
    "addr:street":"Avalon Pde",
    "iso:country":"AU",
    "sg:address":"23 Avalon Pde",
    "sg:city":"Avalon",
    "sg:classifiers":[
        {
            "category":"Cafe",
            "type":"Food & Drink"
        }
    ],
    "sg:phone":"+61 2 9918 2077",
    "sg:postcode":"2107",
    "sg:province":"NSW",
    "wof:name":"Starfish Avalon",
    "wof:placetype":"venue"
},
  "geometry": {"coordinates":[151.329544067,-33.6366577148],"type":"Point"}
}