{
  "type": "Feature",
  "properties": {
    "addr:full":"Alto Centre, Cnr Compton & Ewing Rds Underwood QLD 4119",
    "addr:postcode":"4119",
    "addr:street":"Cnr Compton & Ewing Rds",
    "iso:country":"AU",
    "sg:address":"Alto Centre, Cnr Compton & Ewing Rds",
    "sg:city":"Underwood",
    "sg:classifiers":[
        {
            "category":"Professional",
            "subcategory":"Detective & Security Services",
            "type":"Services"
        }
    ],
    "sg:phone":"+61 7 3299 3900",
    "sg:postcode":"4119",
    "sg:province":"QLD",
    "sg:tags":[
        "equipment",
        "window",
        "doors"
    ],
    "wof:name":"Franklyn Blinds Awnings Security",
    "wof:placetype":"venue"
},
  "geometry": {"coordinates":[153.12074279800001,-27.6149673462],"type":"Point"}
}