{
  "type": "Feature",
  "properties": {
    "addr:full":"Shop 12, Capalaba Central S/C, Moreton Bay Rd Capalaba QLD 4157",
    "addr:housenumber":"shop 12",
    "addr:postcode":"4157",
    "addr:street":"Central;Moreton Bay Rd",
    "iso:country":"AU",
    "sg:address":"Shop 12, Capalaba Central S/C, Moreton Bay Rd",
    "sg:city":"Capalaba",
    "sg:classifiers":[
        {
            "category":"Food & Beverages",
            "subcategory":"Bakery",
            "type":"Retail Goods"
        }
    ],
    "sg:phone":"+61 7 3245 1102",
    "sg:postcode":"4157",
    "sg:province":"QLD",
    "sg:tags":[
        "baker"
    ],
    "wof:name":"Brumbys",
    "wof:placetype":"venue"
},
  "geometry": {"coordinates":[153.199981689,-27.5226707458],"type":"Point"}
}