{
  "type": "Feature",
  "properties": {
    "addr:full":"100 Argyle St Picton NSW 2571",
    "addr:housenumber":"100",
    "addr:postcode":"2571",
    "addr:street":"Argyle St",
    "iso:country":"AU",
    "sg:address":"100 Argyle St",
    "sg:city":"Picton",
    "sg:classifiers":[
        {
            "category":"Banks & Credit Unions",
            "subcategory":"Bank",
            "type":"Services"
        }
    ],
    "sg:phone":"+61 13 20 32",
    "sg:postcode":"2571",
    "sg:province":"NSW",
    "wof:name":"Westpac",
    "wof:placetype":"venue"
},
  "geometry": {"coordinates":[150.611602783,-34.1691513062],"type":"Point"}
}