{
  "type": "Feature",
  "properties": {
    "iso:country":"AU",
    "sg:address":"Shp1/ 256 Junction Rd",
    "sg:city":"Clayfield",
    "sg:classifiers":[
        {
            "category":"Sports & Exercise",
            "subcategory":"Gym",
            "type":"Entertainment"
        }
    ],
    "sg:phone":"+61 7 3857 2625",
    "sg:postcode":"4011",
    "sg:province":"QLD",
    "sg:tags":[
        "health",
        "fitness"
    ],
    "wof:name":"Fitshack",
    "wof:placetype":"venue"
},
  "geometry": {"coordinates":[153.051575,-27.415178],"type":"Point"}
}