{
  "type": "Feature",
  "properties": {
    "iso:country":"AU",
    "sg:address":"7 Hull St",
    "sg:city":"Glenorchy",
    "sg:classifiers":[
        {
            "category":"Social Services",
            "subcategory":"Retirement Home",
            "type":"Services"
        }
    ],
    "sg:phone":"+61 3 6273 5979",
    "sg:postcode":"7010",
    "sg:province":"TAS",
    "sg:tags":[
        "accommodation",
        "special"
    ],
    "wof:name":"Abbeyfield Society Inc",
    "wof:placetype":"venue"
},
  "geometry": {"coordinates":[147.26864624000001,-42.832485199],"type":"Point"}
}