{
  "type": "Feature",
  "properties": {
    "iso:country":"AU",
    "sg:address":"10 North St",
    "sg:city":"Harrisville",
    "sg:classifiers":[
        {
            "category":"Arts & Performance",
            "subcategory":"Music",
            "type":"Entertainment"
        }
    ],
    "sg:phone":"+61 407 659 399",
    "sg:postcode":"4307",
    "sg:province":"QLD",
    "sg:tags":[
        "mobile",
        "jockey",
        "disc"
    ],
    "wof:name":"Flashdance Mobile DJ",
    "wof:placetype":"venue"
},
  "geometry": {"coordinates":[152.67234802199999,-27.8110942841],"type":"Point"}
}