{
  "type": "Feature",
  "properties": {
    "addr:full":"Commonwealth Ave Yarralumla ACT 2600",
    "addr:postcode":"2600",
    "addr:street":"Commonwealth Ave",
    "iso:country":"AU",
    "sg:address":"Commonwealth Ave",
    "sg:city":"Yarralumla",
    "sg:classifiers":[
        {
            "category":"Retail",
            "subcategory":"Event Space",
            "type":"Services"
        }
    ],
    "sg:phone":"+61 2 6270 1234",
    "sg:postcode":"2600",
    "sg:province":"ACT",
    "sg:tags":[
        "venue",
        "reception",
        "wedding"
    ],
    "wof:name":"Hyatt Hotel Canberra.",
    "wof:placetype":"venue"
},
  "geometry": {"coordinates":[149.12495422399999,-35.3048324585],"type":"Point"}
}