{
  "type": "Feature",
  "properties": {
    "addr:full":"U18/ 21 Joondalup Drv Edgewater WA 6027",
    "addr:postcode":"6027",
    "addr:street":"/ 21 Joondalup Drv",
    "iso:country":"AU",
    "sg:address":"U18/ 21 Joondalup Drv",
    "sg:city":"Edgewater",
    "sg:classifiers":[
        {
            "category":"Home & Garden",
            "subcategory":"Carpets & Floor Coverings",
            "type":"Retail Goods"
        }
    ],
    "sg:phone":"+61 8 9300 0855",
    "sg:postcode":"6027",
    "sg:province":"WA",
    "sg:tags":[
        "wood"
    ],
    "wof:name":"DIY Flooring Centre",
    "wof:placetype":"venue"
},
  "geometry": {"coordinates":[115.78195953399999,-31.771982193],"type":"Point"}
}