{
  "type": "Feature",
  "properties": {
    "addr:full":"Lord St Brookstead QLD 4352",
    "addr:postcode":"4352",
    "addr:street":"Lord St",
    "iso:country":"AU",
    "sg:address":"Lord St",
    "sg:city":"Brookstead",
    "sg:classifiers":[
        {
            "category":"Wholesale",
            "subcategory":"Farm Supplies",
            "type":"Manufacturing & Wholesale Goods"
        }
    ],
    "sg:phone":"+61 7 4693 9299",
    "sg:postcode":"4352",
    "sg:province":"QLD",
    "sg:tags":[
        "equipment"
    ],
    "wof:name":"CRT- Combined Rural Traders",
    "wof:placetype":"venue"
},
  "geometry": {"coordinates":[151.44825700000001,-27.758516],"type":"Point"}
}