{
  "type": "Feature",
  "properties": {
    "addr:full":"20 Zephyr St Aspley QLD 4034",
    "addr:housenumber":"20",
    "addr:postcode":"4034",
    "addr:street":"Zephyr St",
    "iso:country":"AU",
    "sg:address":"20 Zephyr St",
    "sg:city":"Aspley",
    "sg:classifiers":[
        {
            "category":"Professional",
            "subcategory":"Business Services",
            "type":"Services"
        }
    ],
    "sg:phone":"+61 7 3263 8172",
    "sg:postcode":"4034",
    "sg:province":"QLD",
    "sg:tags":[
        "drafting"
    ],
    "wof:name":"Sintra Consulting Pty Ltd",
    "wof:placetype":"venue"
},
  "geometry": {"coordinates":[153.03169299999999,-27.369787],"type":"Point"}
}