{
  "type": "Feature",
  "properties": {
    "addr:full":"77 Thomas St Wallsend NSW 2287",
    "addr:housenumber":"77",
    "addr:postcode":"2287",
    "addr:street":"Thomas St",
    "iso:country":"AU",
    "sg:address":"77 Thomas St",
    "sg:city":"Wallsend",
    "sg:classifiers":[
        {
            "category":"Wholesale",
            "subcategory":"Furniture",
            "type":"Manufacturing & Wholesale Goods"
        }
    ],
    "sg:phone":"+61 2 4955 9548",
    "sg:postcode":"2287",
    "sg:province":"NSW",
    "sg:tags":[
        "wholesaler",
        "mfrs"
    ],
    "wof:name":"A R Metcalfe & Sons Pty Ltd",
    "wof:placetype":"venue"
},
  "geometry": {"coordinates":[151.676055908,-32.9039268494],"type":"Point"}
}