{
  "type": "Feature",
  "properties": {
    "addr:full":"464 Beckett Rd Bridgeman Downs QLD 4035",
    "addr:housenumber":"464",
    "addr:postcode":"4035",
    "addr:street":"Beckett Rd",
    "iso:country":"AU",
    "sg:address":"464 Beckett Rd",
    "sg:city":"Bridgeman Downs",
    "sg:classifiers":[
        {
            "category":"Home & Garden",
            "subcategory":"Garden Supply",
            "type":"Retail Goods"
        }
    ],
    "sg:phone":"+61 407 571 762",
    "sg:postcode":"4035",
    "sg:province":"QLD",
    "sg:tags":[
        "turf",
        "lawn"
    ],
    "wof:name":"Aspley Turf Supplies",
    "wof:placetype":"venue"
},
  "geometry": {"coordinates":[152.99295000000001,-27.356834],"type":"Point"}
}