{
  "type": "Feature",
  "properties": {
    "addr:full":"18 Smith St Kempsey NSW 2440",
    "addr:housenumber":"18",
    "addr:postcode":"2440",
    "addr:street":"Smith St",
    "iso:country":"AU",
    "sg:address":"18 Smith St",
    "sg:city":"Kempsey",
    "sg:classifiers":[
        {
            "category":"Shopping",
            "subcategory":"Jewelry",
            "type":"Retail Goods"
        }
    ],
    "sg:phone":"+61 2 6562 1307",
    "sg:postcode":"2440",
    "sg:province":"NSW",
    "sg:tags":[
        "jeweller"
    ],
    "wof:name":"IRVINES JEWELLERS",
    "wof:placetype":"venue"
},
  "geometry": {"coordinates":[152.84259,-31.077238],"type":"Point"}
}