{
  "type": "Feature",
  "properties": {
    "addr:full":"32 Pier St Altona VIC 3018",
    "addr:housenumber":"32",
    "addr:postcode":"3018",
    "addr:street":"Pier St",
    "iso:country":"AU",
    "sg:address":"32 Pier St",
    "sg:city":"Altona",
    "sg:classifiers":[
        {
            "category":"Personal",
            "subcategory":"Beauty Salon",
            "type":"Services"
        }
    ],
    "sg:phone":"+61 3 9398 3100",
    "sg:postcode":"3018",
    "sg:province":"VIC",
    "sg:tags":[
        "hairdresser"
    ],
    "wof:name":"Hair Rocks Hair & Beauty Studio",
    "wof:placetype":"venue"
},
  "geometry": {"coordinates":[144.83039855999999,-37.8697013855],"type":"Point"}
}