{
  "type": "Feature",
  "properties": {
    "addr:full":"Sinnamon Rd Jindalee QLD 4074",
    "addr:postcode":"4074",
    "addr:street":"Sinnamon Rd",
    "iso:country":"AU",
    "sg:address":"Sinnamon Rd",
    "sg:city":"Jindalee",
    "sg:classifiers":[
        {
            "category":"Retail",
            "subcategory":"Event Space",
            "type":"Services"
        }
    ],
    "sg:phone":"+61 7 3710 5825",
    "sg:postcode":"4074",
    "sg:province":"QLD",
    "sg:tags":[
        "venue",
        "reception",
        "wedding"
    ],
    "wof:name":"Jindalee Entertainment Venue",
    "wof:placetype":"venue"
},
  "geometry": {"coordinates":[152.94566345199999,-27.5344142914],"type":"Point"}
}