{
  "type": "Feature",
  "properties": {
    "addr:full":"Shop 8/ 401 Maroondah Hwy Croydon North VIC 3136",
    "addr:housenumber":"shop 8 / 401",
    "addr:postcode":"3136",
    "addr:street":"Maroondah Hwy",
    "iso:country":"AU",
    "sg:address":"Shop 8/ 401 Maroondah Hwy",
    "sg:city":"Croydon North",
    "sg:classifiers":[
        {
            "category":"Food & Beverages",
            "subcategory":"Bakery",
            "type":"Retail Goods"
        }
    ],
    "sg:phone":"+61 3 9727 0400",
    "sg:postcode":"3136",
    "sg:province":"VIC",
    "sg:tags":[
        "cake",
        "shop",
        "pastry"
    ],
    "wof:name":"Cheesecake Shop The",
    "wof:placetype":"venue"
},
  "geometry": {"coordinates":[145.29388427699999,-37.7716636658],"type":"Point"}
}