{
  "type": "Feature",
  "properties": {
    "iso:country":"AU",
    "sg:address":"53 Noble Ave",
    "sg:city":"Northgate",
    "sg:classifiers":[
        {
            "category":"Retail",
            "subcategory":"Storage",
            "type":"Services"
        }
    ],
    "sg:phone":"+61 7 5592 6124",
    "sg:postcode":"4013",
    "sg:province":"QLD",
    "sg:tags":[
        "removal",
        "furniture"
    ],
    "wof:name":"Overseas Shipping Services (Qld) Pty Ltd",
    "wof:placetype":"venue"
},
  "geometry": {"coordinates":[153.07460022000001,-27.3854293823],"type":"Point"}
}