{
  "type": "Feature",
  "properties": {
    "iso:country":"AU",
    "sg:address":"32 Kurrajong Ave",
    "sg:city":"Hollywell",
    "sg:classifiers":[
        {
            "category":"Social Services",
            "subcategory":"Job Training",
            "type":"Services"
        }
    ],
    "sg:phone":"+61 7 5564 1738",
    "sg:postcode":"4216",
    "sg:province":"QLD",
    "sg:tags":[
        "equipment",
        "clean",
        "installation",
        "room",
        "maintenance"
    ],
    "wof:name":"Critical Certification Qld",
    "wof:placetype":"venue"
},
  "geometry": {"coordinates":[153.39796447800001,-27.897649765],"type":"Point"}
}