{
  "type": "Feature",
  "properties": {
    "iso:country":"AU",
    "sg:address":"31 Reid St",
    "sg:city":"Wangaratta",
    "sg:classifiers":[
        {
            "category":"Shopping",
            "subcategory":"Shoes",
            "type":"Retail Goods"
        }
    ],
    "sg:phone":"+61 3 5721 8985",
    "sg:postcode":"3677",
    "sg:province":"VIC",
    "sg:tags":[
        "footwear"
    ],
    "wof:name":"Mario Solimo Footwear & Shoe Repairs",
    "wof:placetype":"venue"
},
  "geometry": {"coordinates":[146.326705933,-36.3556137085],"type":"Point"}
}