{
  "type": "Feature",
  "properties": {
    "addr:full":"2 / 40 Bundall Rd Bundall QLD 4217",
    "addr:housenumber":"/ 40",
    "addr:postcode":"4217",
    "addr:street":"Bundall Rd",
    "iso:country":"AU",
    "sg:address":"2 / 40 Bundall Rd",
    "sg:city":"Bundall",
    "sg:classifiers":[
        {
            "category":"Banks & Credit Unions",
            "subcategory":"Bank",
            "type":"Services"
        }
    ],
    "sg:phone":"+61 7 5584 0600",
    "sg:postcode":"4217",
    "sg:province":"QLD",
    "sg:tags":[
        "broker",
        "mortgage"
    ],
    "wof:name":"Aussie",
    "wof:placetype":"venue"
},
  "geometry": {"coordinates":[153.411834717,-28.0109348297],"type":"Point"}
}