{
  "type": "Feature",
  "properties": {
    "iso:country":"AU",
    "sg:address":"Cnr Lowry St & 399 Main Rd",
    "sg:city":"Glendale",
    "sg:classifiers":[
        {
            "category":"Retail",
            "subcategory":"Auto Repair",
            "type":"Services"
        }
    ],
    "sg:phone":"+61 2 4956 9826",
    "sg:postcode":"2285",
    "sg:province":"NSW",
    "sg:tags":[
        "gas",
        "conversion",
        "natural",
        "lp",
        "vehicle"
    ],
    "wof:name":"Gresham Mechanical",
    "wof:placetype":"venue"
},
  "geometry": {"coordinates":[151.64494323700001,-32.929233551],"type":"Point"}
}