{
  "type": "Feature",
  "properties": {
    "addr:full":"120 Stirling Hwy Toodyay WA 6566",
    "addr:housenumber":"120",
    "addr:postcode":"6566",
    "addr:street":"Stirling Hwy",
    "iso:country":"AU",
    "sg:address":"120 Stirling Hwy",
    "sg:city":"Toodyay",
    "sg:classifiers":[
        {
            "category":"Real Estate",
            "subcategory":"Real Estate Agent",
            "type":"Services"
        }
    ],
    "sg:phone":"+61 8 9574 2800",
    "sg:postcode":"6566",
    "sg:province":"WA",
    "wof:name":"RE/MAX Devenish",
    "wof:placetype":"venue"
},
  "geometry": {"coordinates":[116.46678199999999,-31.549957],"type":"Point"}
}