{
  "type": "Feature",
  "properties": {
    "addr:full":"15 Grimshaw St Greensborough VIC 3088",
    "addr:housenumber":"15",
    "addr:postcode":"3088",
    "addr:street":"Grimshaw St",
    "iso:country":"AU",
    "sg:address":"15 Grimshaw St",
    "sg:city":"Greensborough",
    "sg:classifiers":[
        {
            "category":"Health Services",
            "subcategory":"Dentist",
            "type":"Services"
        }
    ],
    "sg:phone":"+61 3 9654 4844",
    "sg:postcode":"3088",
    "sg:province":"VIC",
    "wof:name":"Heggie Andrew A C",
    "wof:placetype":"venue"
},
  "geometry": {"coordinates":[145.10763549800001,-37.7052612305],"type":"Point"}
}