{
  "type": "Feature",
  "properties": {
    "addr:full":"768 Brunswick St New Farm QLD 4005",
    "addr:housenumber":"768",
    "addr:postcode":"4005",
    "addr:street":"Brunswick St",
    "iso:country":"AU",
    "sg:address":"768 Brunswick St",
    "sg:city":"New Farm",
    "sg:classifiers":[
        {
            "category":"Professional",
            "subcategory":"Art Services",
            "type":"Services"
        }
    ],
    "sg:phone":"+61 7 3254 3000",
    "sg:postcode":"4005",
    "sg:province":"QLD",
    "sg:tags":[
        "interior",
        "designer"
    ],
    "wof:name":"Black John Interiors",
    "wof:placetype":"venue"
},
  "geometry": {"coordinates":[153.044067383,-27.4653911591],"type":"Point"}
}