{
  "type": "Feature",
  "properties": {
    "iso:country":"AU",
    "sg:address":"Factory 11, 350 Settlement Rd",
    "sg:city":"Thomastown",
    "sg:classifiers":[
        {
            "category":"Shopping",
            "subcategory":"Bicycles & Sporting Goods",
            "type":"Retail Goods"
        }
    ],
    "sg:phone":"+61 3 9464 6400",
    "sg:postcode":"3074",
    "sg:province":"VIC",
    "sg:tags":[
        "chemical",
        "equipment",
        "pool",
        "swimming"
    ],
    "wof:name":"Finsbury Pumps",
    "wof:placetype":"venue"
},
  "geometry": {"coordinates":[145.01809692399999,-37.6882858276],"type":"Point"}
}