{
  "type": "Feature",
  "properties": {
    "iso:country":"AU",
    "sg:address":"235 Port Rd",
    "sg:city":"Hindmarsh",
    "sg:classifiers":[
        {
            "category":"Manufacturing",
            "subcategory":"Glass & Minerals",
            "type":"Manufacturing & Wholesale Goods"
        }
    ],
    "sg:phone":"+61 8 8348 3500",
    "sg:postcode":"5007",
    "sg:province":"SA",
    "sg:tags":[
        "exploration"
    ],
    "wof:name":"Marathon Resources Ltd",
    "wof:placetype":"venue"
},
  "geometry": {"coordinates":[138.57043457,-34.9037628174],"type":"Point"}
}