{
  "type": "Feature",
  "properties": {
    "addr:full":"54 Downey St Alexandra VIC 3714",
    "addr:housenumber":"54",
    "addr:postcode":"3714",
    "addr:street":"Downey St",
    "iso:country":"AU",
    "sg:address":"54 Downey St",
    "sg:city":"Alexandra",
    "sg:classifiers":[
        {
            "category":"Health Services",
            "subcategory":"Doctor",
            "type":"Services"
        }
    ],
    "sg:phone":"+61 3 5772 1444",
    "sg:postcode":"3714",
    "sg:province":"VIC",
    "sg:tags":[
        "medical",
        "practitioner"
    ],
    "wof:name":"Alexandra Medical Centre",
    "wof:placetype":"venue"
},
  "geometry": {"coordinates":[145.70736694300001,-37.1922607422],"type":"Point"}
}