{
  "type": "Feature",
  "properties": {
    "iso:country":"AU",
    "sg:address":"Unit 3, 13 Berry St",
    "sg:city":"Clyde",
    "sg:classifiers":[
        {
            "category":"Home & Garden",
            "subcategory":"Garden Supply",
            "type":"Retail Goods"
        }
    ],
    "sg:phone":"+61 410 506 370",
    "sg:postcode":"2142",
    "sg:province":"NSW",
    "sg:tags":[
        "equipment"
    ],
    "wof:name":"Golden Crest Group",
    "wof:placetype":"venue"
},
  "geometry": {"coordinates":[151.017333984,-33.8353996277],"type":"Point"}
}