{
  "type": "Feature",
  "properties": {
    "addr:full":"Hedland Pl Karratha WA 6714",
    "addr:postcode":"6714",
    "addr:street":"Pl Karratha",
    "iso:country":"AU",
    "sg:address":"Hedland Pl",
    "sg:city":"Karratha",
    "sg:classifiers":[
        {
            "category":"Professional",
            "subcategory":"Testing Lab",
            "type":"Services"
        }
    ],
    "sg:phone":"+61 1300 765 725",
    "sg:postcode":"6714",
    "sg:province":"WA",
    "sg:tags":[
        "inspection"
    ],
    "wof:name":"SGS",
    "wof:placetype":"venue"
},
  "geometry": {"coordinates":[116.84790802000001,-20.7342777252],"type":"Point"}
}