{
  "type": "Feature",
  "properties": {
    "iso:country":"AU",
    "sg:address":"75 - 77 Westgate Drv",
    "sg:city":"Altona North",
    "sg:classifiers":[
        {
            "category":"Autos & Motor Vehicles",
            "subcategory":"Auto Supplies",
            "type":"Retail Goods"
        }
    ],
    "sg:phone":"+61 3 9646 6008",
    "sg:postcode":"3025",
    "sg:province":"VIC",
    "sg:tags":[
        "automotive",
        "stereo",
        "radio"
    ],
    "wof:name":"Fujitsu Ten (Australia) Pty Ltd",
    "wof:placetype":"venue"
},
  "geometry": {"coordinates":[144.819397,-37.832748],"type":"Point"}
}