{
  "type": "Feature",
  "properties": {
    "iso:country":"AU",
    "sg:address":"21 Claremont St",
    "sg:city":"Mt Eliza",
    "sg:classifiers":[
        {
            "category":"Professional",
            "subcategory":"Art Services",
            "type":"Services"
        }
    ],
    "sg:phone":"+61 412 175 774",
    "sg:postcode":"3930",
    "sg:province":"VIC",
    "sg:tags":[
        "decorator",
        "painter"
    ],
    "wof:name":"Uri's Quality Painting Service Pty Ltd",
    "wof:placetype":"venue"
},
  "geometry": {"coordinates":[145.10113525400001,-38.2105064392],"type":"Point"}
}