{
  "type": "Feature",
  "properties": {
    "addr:full":"11 Diligent Drv Bayswater VIC 3153",
    "addr:housenumber":"11",
    "addr:postcode":"3153",
    "addr:street":"Diligent Drv",
    "iso:country":"AU",
    "sg:address":"11 Diligent Drv",
    "sg:city":"Bayswater",
    "sg:classifiers":[
        {
            "category":"Building & Trades",
            "subcategory":"Construction",
            "type":"Services"
        }
    ],
    "sg:phone":"+61 3 9729 4088",
    "sg:postcode":"3153",
    "sg:province":"VIC",
    "sg:tags":[
        "window",
        "aluminium"
    ],
    "sg:website":"http://www.accent-aluminium-windows-australia.com.au",
    "wof:name":"Accent Aluminium Windows (Aus) Pty Ltd",
    "wof:placetype":"venue"
},
  "geometry": {"coordinates":[145.27984619099999,-37.826007843],"type":"Point"}
}