{
  "type": "Feature",
  "properties": {
    "addr:full":"Lvl 4, 4 Woodville St Hurstville NSW 2220",
    "addr:housenumber":"4",
    "addr:postcode":"2220",
    "addr:street":"Woodville St",
    "iso:country":"AU",
    "sg:address":"Lvl 4, 4 Woodville St",
    "sg:city":"Hurstville",
    "sg:classifiers":[
        {
            "category":"Banks & Credit Unions",
            "subcategory":"Financial Services",
            "type":"Services"
        }
    ],
    "sg:phone":"+61 2 9570 3222",
    "sg:postcode":"2220",
    "sg:province":"NSW",
    "sg:tags":[
        "advisory",
        "planning",
        "retirement"
    ],
    "wof:name":"Bridges Personal Investment Services",
    "wof:placetype":"venue"
},
  "geometry": {"coordinates":[151.10383605999999,-33.9647483826],"type":"Point"}
}