{
  "type": "Feature",
  "properties": {
    "addr:full":"7 Burke St Creswick VIC 3363",
    "addr:housenumber":"7",
    "addr:postcode":"3363",
    "addr:street":"Burke St",
    "iso:country":"AU",
    "sg:address":"7 Burke St",
    "sg:city":"Creswick",
    "sg:classifiers":[
        {
            "category":"Personal",
            "subcategory":"Beauty Salon",
            "type":"Services"
        }
    ],
    "sg:phone":"+61 3 5345 1558",
    "sg:postcode":"3363",
    "sg:province":"VIC",
    "sg:tags":[
        "hairdresser"
    ],
    "wof:name":"Two Cees Hair Galery",
    "wof:placetype":"venue"
},
  "geometry": {"coordinates":[143.89805602999999,-37.4159660339],"type":"Point"}
}