{
  "type": "Feature",
  "properties": {
    "addr:full":"Unit 4-5, 44 Bryants Rd Shailer Park QLD 4128",
    "addr:housenumber":"44",
    "addr:postcode":"4128",
    "addr:street":"Bryants Rd",
    "iso:country":"AU",
    "sg:address":"Unit 4-5, 44 Bryants Rd",
    "sg:city":"Shailer Park",
    "sg:classifiers":[
        {
            "category":"Real Estate",
            "subcategory":"Real Estate Agent",
            "type":"Services"
        }
    ],
    "sg:phone":"+61 7 3801 1888",
    "sg:postcode":"4128",
    "sg:province":"QLD",
    "wof:name":"PRDnationwide",
    "wof:placetype":"venue"
},
  "geometry": {"coordinates":[153.17515564000001,-27.6624259949],"type":"Point"}
}