{
  "type": "Feature",
  "properties": {
    "addr:full":"145 Dwyer St Kalgoorlie WA 6430",
    "addr:housenumber":"145",
    "addr:postcode":"6430",
    "addr:street":"Dwyer St",
    "iso:country":"AU",
    "sg:address":"145 Dwyer St",
    "sg:city":"Kalgoorlie",
    "sg:classifiers":[
        {
            "category":"Manufacturing",
            "subcategory":"Glass & Minerals",
            "type":"Manufacturing & Wholesale Goods"
        }
    ],
    "sg:phone":"+61 8 9093 3783",
    "sg:postcode":"6430",
    "sg:province":"WA",
    "sg:tags":[
        "exploration"
    ],
    "wof:name":"Westland Gold N L",
    "wof:placetype":"venue"
},
  "geometry": {"coordinates":[121.48342895499999,-30.7881546021],"type":"Point"}
}