{
  "type": "Feature",
  "properties": {
    "addr:full":"4 Alexandra Rd Ascot QLD 4007",
    "addr:housenumber":"4",
    "addr:postcode":"4007",
    "addr:street":"Alexandra Rd",
    "iso:country":"AU",
    "sg:address":"4 Alexandra Rd",
    "sg:city":"Ascot",
    "sg:classifiers":[
        {
            "category":"Real Estate",
            "subcategory":"Architect",
            "type":"Services"
        }
    ],
    "sg:phone":"+61 7 3862 2299",
    "sg:postcode":"4007",
    "sg:province":"QLD",
    "wof:name":"Villari Architects Pty Ltd",
    "wof:placetype":"venue"
},
  "geometry": {"coordinates":[153.057785,-27.430832],"type":"Point"}
}