{
  "type": "Feature",
  "properties": {
    "iso:country":"AU",
    "sg:address":"93 Brobenah Rd",
    "sg:city":"Leeton",
    "sg:classifiers":[
        {
            "category":"Building & Trades",
            "subcategory":"Cleaning & Sanitation",
            "type":"Services"
        }
    ],
    "sg:phone":"+61 427 394 483",
    "sg:postcode":"2705",
    "sg:province":"NSW",
    "sg:tags":[
        "chemical",
        "pressure",
        "steam",
        "contractor"
    ],
    "wof:name":"Denis White Mobile Pressure Cleaning Service",
    "wof:placetype":"venue"
},
  "geometry": {"coordinates":[146.40655517600001,-34.5430450439],"type":"Point"}
}