{
  "type": "Feature",
  "properties": {
    "iso:country":"AU",
    "sg:address":"9Mou Birch Pl",
    "sg:city":"Mt Druitt",
    "sg:classifiers":[
        {
            "category":"Shopping",
            "subcategory":"Clothing, Apparel, & Fashions",
            "type":"Retail Goods"
        }
    ],
    "sg:phone":"+61 2 9628 6229",
    "sg:postcode":"2770",
    "sg:province":"NSW",
    "sg:tags":[
        "maternity",
        "wear"
    ],
    "wof:name":"Glowing Mums Maternity Wear",
    "wof:placetype":"venue"
},
  "geometry": {"coordinates":[150.82049560600001,-33.7284660339],"type":"Point"}
}