{
  "type": "Feature",
  "properties": {
    "addr:full":"69 Oxford St Brahma Lodge SA 5109",
    "addr:housenumber":"69",
    "addr:postcode":"5109",
    "addr:street":"Oxford St",
    "iso:country":"AU",
    "sg:address":"69 Oxford St",
    "sg:city":"Brahma Lodge",
    "sg:classifiers":[
        {
            "category":"Health Services",
            "subcategory":"Doctor",
            "type":"Services"
        }
    ],
    "sg:phone":"+61 8 8258 1704",
    "sg:postcode":"5109",
    "sg:province":"SA",
    "sg:tags":[
        "medical",
        "practitioner"
    ],
    "wof:name":"Watson Colin N Dr",
    "wof:placetype":"venue"
},
  "geometry": {"coordinates":[138.654373169,-34.7774085999],"type":"Point"}
}