{
  "type": "Feature",
  "properties": {
    "addr:full":"Lvl1/ 6 Lowe St Ballarat VIC 3350",
    "addr:housenumber":"6",
    "addr:postcode":"3350",
    "addr:street":"Lowe St",
    "iso:country":"AU",
    "sg:address":"Lvl1/ 6 Lowe St",
    "sg:city":"Ballarat",
    "sg:classifiers":[
        {
            "category":"Insurance",
            "subcategory":"Insurance Agent",
            "type":"Services"
        }
    ],
    "sg:phone":"+61 3 5333 5076",
    "sg:postcode":"3350",
    "sg:province":"VIC",
    "wof:name":"Central Highland Insurance Group",
    "wof:placetype":"venue"
},
  "geometry": {"coordinates":[143.86334199999999,-37.561798],"type":"Point"}
}