{
  "type": "Feature",
  "properties": {
    "iso:country":"AU",
    "sg:address":"21 Bayfield Rd",
    "sg:city":"Arcadia",
    "sg:classifiers":[
        {
            "category":"Professional",
            "subcategory":"Advertising",
            "type":"Services"
        }
    ],
    "sg:phone":"+61 2 9653 1178",
    "sg:postcode":"2159",
    "sg:province":"NSW",
    "sg:tags":[
        "balloon",
        "novelty"
    ],
    "wof:name":"Point of Sale Inflatables",
    "wof:placetype":"venue"
},
  "geometry": {"coordinates":[151.04879760700001,-33.6322250366],"type":"Point"}
}