{
  "type": "Feature",
  "properties": {
    "addr:full":"201A Melrose Drv Tullamarine VIC 3043",
    "addr:housenumber":"201a",
    "addr:postcode":"3043",
    "addr:street":"Melrose Drv",
    "iso:country":"AU",
    "sg:address":"201A Melrose Drv",
    "sg:city":"Tullamarine",
    "sg:classifiers":[
        {
            "category":"Professional",
            "type":"Services"
        }
    ],
    "sg:phone":"+61 3 9338 0099",
    "sg:postcode":"3043",
    "sg:province":"VIC",
    "sg:tags":[
        "courier"
    ],
    "wof:name":"Pack & Send",
    "wof:placetype":"venue"
},
  "geometry": {"coordinates":[144.88017273,-37.7002258301],"type":"Point"}
}