{
  "type": "Feature",
  "properties": {
    "addr:full":"259a Auburn Rd Hawthorn VIC 3122",
    "addr:housenumber":"259a",
    "addr:postcode":"3122",
    "addr:street":"Auburn Rd",
    "iso:country":"AU",
    "sg:address":"259a Auburn Rd",
    "sg:city":"Hawthorn",
    "sg:classifiers":[
        {
            "category":"Communications",
            "subcategory":"Film & Video Production",
            "type":"Services"
        }
    ],
    "sg:phone":"+61 3 9813 4844",
    "sg:postcode":"3122",
    "sg:province":"VIC",
    "sg:tags":[
        "consultant",
        "material",
        "handling"
    ],
    "sg:website":"http://www.cortex.com.au",
    "wof:name":"Cortex Resources",
    "wof:placetype":"venue"
},
  "geometry": {"coordinates":[145.04182434099999,-37.8389854431],"type":"Point"}
}