{
  "type": "Feature",
  "properties": {
    "addr:full":"1329 Teven Rd Alstonville NSW 2477",
    "addr:housenumber":"1329",
    "addr:postcode":"2477",
    "addr:street":"Teven Rd",
    "iso:country":"AU",
    "sg:address":"1329 Teven Rd",
    "sg:city":"Alstonville",
    "sg:classifiers":[
        {
            "category":"Wholesale",
            "subcategory":"Medical Equipment & Supplies",
            "type":"Manufacturing & Wholesale Goods"
        }
    ],
    "sg:phone":"+61 2 6628 3866",
    "sg:postcode":"2477",
    "sg:province":"NSW",
    "sg:tags":[
        "dental"
    ],
    "wof:name":"TrollDental",
    "wof:placetype":"venue"
},
  "geometry": {"coordinates":[153.452636719,-28.83203125],"type":"Point"}
}