{
  "type": "Feature",
  "properties": {
    "addr:full":"113 Glebe Point Rd Glebe NSW 2037",
    "addr:housenumber":"113",
    "addr:postcode":"2037",
    "addr:street":"Glebe Point Rd",
    "iso:country":"AU",
    "sg:address":"113 Glebe Point Rd",
    "sg:city":"Glebe",
    "sg:classifiers":[
        {
            "category":"Retail",
            "subcategory":"Veterinary Services",
            "type":"Services"
        }
    ],
    "sg:phone":"+61 2 9660 1771",
    "sg:postcode":"2037",
    "sg:province":"NSW",
    "sg:tags":[
        "surgeon"
    ],
    "wof:name":"Glebe Veterinary Hospital",
    "wof:placetype":"venue"
},
  "geometry": {"coordinates":[151.189941406,-33.882106781],"type":"Point"}
}