{
  "type": "Feature",
  "properties": {
    "addr:full":"31 Derby St Collingwood VIC 3066",
    "addr:housenumber":"31",
    "addr:postcode":"3066",
    "addr:street":"Derby St",
    "iso:country":"AU",
    "sg:address":"31 Derby St",
    "sg:city":"Collingwood",
    "sg:classifiers":[
        {
            "category":"Banks & Credit Unions",
            "subcategory":"Financial Services",
            "type":"Services"
        }
    ],
    "sg:phone":"+61 3 9419 4511",
    "sg:postcode":"3066",
    "sg:province":"VIC",
    "sg:tags":[
        "planning"
    ],
    "wof:name":"Count Wealth Accountants",
    "wof:placetype":"venue"
},
  "geometry": {"coordinates":[144.984573364,-37.8070640564],"type":"Point"}
}