{
  "type": "Feature",
  "properties": {
    "addr:full":"Unit 3/ 31 Rene St Noosaville QLD 4566",
    "addr:housenumber":"31",
    "addr:postcode":"4566",
    "addr:street":"Rene St",
    "iso:country":"AU",
    "sg:address":"Unit 3/ 31 Rene St",
    "sg:city":"Noosaville",
    "sg:classifiers":[
        {
            "category":"Retail",
            "subcategory":"Auto Repair",
            "type":"Services"
        }
    ],
    "sg:phone":"+61 7 5447 1431",
    "sg:postcode":"4566",
    "sg:province":"QLD",
    "sg:tags":[
        "repairer",
        "motor",
        "engineer"
    ],
    "wof:name":"Tewantin Garage",
    "wof:placetype":"venue"
},
  "geometry": {"coordinates":[153.04229736299999,-26.415014267],"type":"Point"}
}