{
  "type": "Feature",
  "properties": {
    "addr:full":"91 Main St Lobethal SA 5241",
    "addr:housenumber":"91",
    "addr:postcode":"5241",
    "addr:street":"Main St",
    "iso:country":"AU",
    "sg:address":"91 Main St",
    "sg:city":"Lobethal",
    "sg:classifiers":[
        {
            "category":"Health Services",
            "subcategory":"Dentist",
            "type":"Services"
        }
    ],
    "sg:phone":"+61 8 8389 6871",
    "sg:postcode":"5241",
    "sg:province":"SA",
    "wof:name":"Moore G J & Bajada S B",
    "wof:placetype":"venue"
},
  "geometry": {"coordinates":[138.87504577600001,-34.9022026062],"type":"Point"}
}