{
  "type": "Feature",
  "properties": {
    "iso:country":"AU",
    "sg:address":"26 Baynes St",
    "sg:city":"Margate",
    "sg:classifiers":[
        {
            "category":"Fast Food",
            "type":"Food & Drink"
        }
    ],
    "sg:phone":"+61 7 3284 2280",
    "sg:postcode":"4019",
    "sg:province":"QLD",
    "sg:tags":[
        "away",
        "take"
    ],
    "wof:name":"Chicken Gourmet",
    "wof:placetype":"venue"
},
  "geometry": {"coordinates":[153.108154297,-27.243812561],"type":"Point"}
}