{
  "type": "Feature",
  "properties": {
    "addr:full":"99 Maribyrnong Rd Ascot Vale VIC 3032",
    "addr:housenumber":"99",
    "addr:postcode":"3032",
    "addr:street":"Maribyrnong Rd",
    "iso:country":"AU",
    "sg:address":"99 Maribyrnong Rd",
    "sg:city":"Ascot Vale",
    "sg:classifiers":[
        {
            "category":"Health Services",
            "subcategory":"Health Practitioner",
            "type":"Services"
        }
    ],
    "sg:phone":"+61 3 9375 3193",
    "sg:postcode":"3032",
    "sg:province":"VIC",
    "sg:tags":[
        "osteopath"
    ],
    "wof:name":"Rhodes Graeme",
    "wof:placetype":"venue"
},
  "geometry": {"coordinates":[144.91641200000001,-37.77187],"type":"Point"}
}