{
  "type": "Feature",
  "properties": {
    "addr:full":"Cnr Anson & Plain Sts Tamworth NSW 2340",
    "addr:postcode":"2340",
    "iso:country":"AU",
    "sg:address":"Cnr Anson & Plain Sts",
    "sg:city":"Tamworth",
    "sg:classifiers":[
        {
            "category":"Transit Center",
            "subcategory":"Freight",
            "type":"Transportation"
        }
    ],
    "sg:phone":"+61 2 6762 1411",
    "sg:postcode":"2340",
    "sg:province":"NSW",
    "sg:tags":[
        "forklift",
        "truck"
    ],
    "wof:name":"Tamworth Fork Lifts",
    "wof:placetype":"venue"
},
  "geometry": {"coordinates":[150.910644531,-31.0893974304],"type":"Point"}
}