{
  "type": "Feature",
  "properties": {
    "addr:full":"4 Leane St Hughes ACT 2605",
    "addr:housenumber":"4",
    "addr:postcode":"2605",
    "addr:street":"Leane St",
    "iso:country":"AU",
    "sg:address":"4 Leane St",
    "sg:city":"Hughes",
    "sg:classifiers":[
        {
            "category":"Professional",
            "subcategory":"Art Services",
            "type":"Services"
        }
    ],
    "sg:phone":"+61 2 6281 2807",
    "sg:postcode":"2605",
    "sg:province":"ACT",
    "sg:tags":[
        "interior",
        "designer"
    ],
    "wof:name":"David Boughton Architects",
    "wof:placetype":"venue"
},
  "geometry": {"coordinates":[149.10124206500001,-35.3334732056],"type":"Point"}
}