{
  "type": "Feature",
  "properties": {
    "addr:full":"Shop 1004 Westfield Kotara Cnr Park & Northcott Kotara NSW 2289",
    "addr:housenumber":"1004",
    "addr:postcode":"2289",
    "iso:country":"AU",
    "sg:address":"Shop 1004 Westfield Kotara Cnr Park & Northcott",
    "sg:city":"Kotara",
    "sg:classifiers":[
        {
            "category":"Shopping",
            "subcategory":"Clothing, Apparel, & Fashions",
            "type":"Retail Goods"
        }
    ],
    "sg:phone":"+61 2 4957 9144",
    "sg:postcode":"2289",
    "sg:province":"NSW",
    "sg:tags":[
        "menswear"
    ],
    "wof:name":"R.M. Williams",
    "wof:placetype":"venue"
},
  "geometry": {"coordinates":[151.71206665,-32.9396438599],"type":"Point"}
}