{
  "type": "Feature",
  "properties": {
    "iso:country":"AU",
    "sg:address":"20 Pottery Rd",
    "sg:city":"Lenah Valley",
    "sg:classifiers":[
        {
            "category":"Professional",
            "subcategory":"Business Services",
            "type":"Services"
        }
    ],
    "sg:phone":"+61 3 6228 9702",
    "sg:postcode":"7008",
    "sg:province":"TAS",
    "sg:tags":[
        "management",
        "event"
    ],
    "wof:name":"Mainstage Pty Ltd",
    "wof:placetype":"venue"
},
  "geometry": {"coordinates":[147.28895568900001,-42.8648109436],"type":"Point"}
}