{
  "type": "Feature",
  "properties": {
    "iso:country":"AU",
    "sg:address":"211 Portrush Rd",
    "sg:city":"Maylands",
    "sg:classifiers":[
        {
            "category":"Banks & Credit Unions",
            "subcategory":"Bank",
            "type":"Services"
        }
    ],
    "sg:phone":"+61 8 8333 3011",
    "sg:postcode":"5069",
    "sg:province":"SA",
    "sg:tags":[
        "broker",
        "mortgage"
    ],
    "wof:name":"Finance Opportunities",
    "wof:placetype":"venue"
},
  "geometry": {"coordinates":[138.640167236,-34.9136657715],"type":"Point"}
}