{
  "type": "Feature",
  "properties": {
    "iso:country":"AU",
    "sg:address":"PO Box 235",
    "sg:city":"Paddington",
    "sg:classifiers":[
        {
            "category":"Shopping",
            "subcategory":"Bridal",
            "type":"Retail Goods"
        }
    ],
    "sg:phone":"+61 2 9357 5950",
    "sg:postcode":"2021",
    "sg:province":"NSW",
    "sg:tags":[
        "hire",
        "wear"
    ],
    "wof:name":"Bridalboutique.com.au",
    "wof:placetype":"venue"
},
  "geometry": {"coordinates":[151.22581481899999,-33.8864593506],"type":"Point"}
}