{
  "type": "Feature",
  "properties": {
    "addr:full":"Shop 4 96 Main St Mornington VIC 3931",
    "addr:housenumber":"shop;96",
    "addr:postcode":"3931",
    "addr:street":"Main St",
    "iso:country":"AU",
    "sg:address":"Shop 4 96 Main St",
    "sg:city":"Mornington",
    "sg:classifiers":[
        {
            "category":"Banks & Credit Unions",
            "subcategory":"Bank",
            "type":"Services"
        }
    ],
    "sg:phone":"+61 3 5973 4011",
    "sg:postcode":"3931",
    "sg:province":"VIC",
    "sg:tags":[
        "broker",
        "mortgage"
    ],
    "wof:name":"Mortgage Choice",
    "wof:placetype":"venue"
},
  "geometry": {"coordinates":[145.038665772,-38.2194099426],"type":"Point"}
}