{
  "type": "Feature",
  "properties": {
    "addr:full":"9b Citrus St Braeside VIC 3195",
    "addr:housenumber":"9b",
    "addr:postcode":"3195",
    "addr:street":"Citrus St",
    "iso:country":"AU",
    "sg:address":"9b Citrus St",
    "sg:city":"Braeside",
    "sg:classifiers":[
        {
            "category":"Manufacturing",
            "subcategory":"Metals",
            "type":"Manufacturing & Wholesale Goods"
        }
    ],
    "sg:phone":"+61 3 9588 1044",
    "sg:postcode":"3195",
    "sg:province":"VIC",
    "sg:tags":[
        "steel",
        "fabricator",
        "mfrs"
    ],
    "wof:name":"Elite Metalcraft",
    "wof:placetype":"venue"
},
  "geometry": {"coordinates":[145.109207153,-37.9910011292],"type":"Point"}
}