{
  "type": "Feature",
  "properties": {
    "iso:country":"AU",
    "sg:address":"88a Partridge St",
    "sg:city":"Glenelg South",
    "sg:classifiers":[
        {
            "category":"Health Services",
            "subcategory":"Doctor",
            "type":"Services"
        }
    ],
    "sg:phone":"+61 8 8376 3844",
    "sg:postcode":"5045",
    "sg:province":"SA",
    "sg:tags":[
        "medical",
        "practitioner"
    ],
    "wof:name":"Seman Dr Elvis I",
    "wof:placetype":"venue"
},
  "geometry": {"coordinates":[138.518524,-34.987869],"type":"Point"}
}