{
  "type": "Feature",
  "properties": {
    "addr:full":"Greenbrook Shopping Centre Shop 8 53 McDonald Rd Epping VIC 3076",
    "addr:housenumber":"shop 8 53",
    "addr:postcode":"3076",
    "addr:street":"Mcdonald Rd",
    "iso:country":"AU",
    "sg:address":"Greenbrook Shopping Centre Shop 8 53 McDonald Rd",
    "sg:city":"Epping",
    "sg:classifiers":[
        {
            "category":"Personal",
            "subcategory":"Beauty Salon",
            "type":"Services"
        }
    ],
    "sg:phone":"+61 3 9401 3339",
    "sg:postcode":"3076",
    "sg:province":"VIC",
    "sg:tags":[
        "hairdresser"
    ],
    "wof:name":"Tootsie's Hair & Beauty",
    "wof:placetype":"venue"
},
  "geometry": {"coordinates":[144.84825134299999,-37.8092460632],"type":"Point"}
}