{
  "type": "Feature",
  "properties": {
    "addr:full":"Mann Rd Mt Eliza VIC 3930",
    "addr:postcode":"3930",
    "addr:street":"Mann Rd",
    "iso:country":"AU",
    "sg:address":"Mann Rd",
    "sg:city":"Mt Eliza",
    "sg:classifiers":[
        {
            "category":"Health Services",
            "subcategory":"Health Practitioner",
            "type":"Services"
        }
    ],
    "sg:phone":"+61 3 9787 1421",
    "sg:postcode":"3930",
    "sg:province":"VIC",
    "sg:tags":[
        "psychologist"
    ],
    "wof:name":"Vikki Argent",
    "wof:placetype":"venue"
},
  "geometry": {"coordinates":[145.102096558,-38.1709938049],"type":"Point"}
}