{
  "type": "Feature",
  "properties": {
    "iso:country":"AU",
    "sg:address":"Cnr Balaclava & Mulgrave Rds",
    "sg:city":"Earlville",
    "sg:classifiers":[
        {
            "category":"Shopping",
            "subcategory":"Party Supplies",
            "type":"Retail Goods"
        }
    ],
    "sg:phone":"+61 7 4054 6466",
    "sg:postcode":"4870",
    "sg:province":"QLD",
    "sg:tags":[
        "children's"
    ],
    "wof:name":"Balloons Etc",
    "wof:placetype":"venue"
},
  "geometry": {"coordinates":[145.73475647000001,-16.943857193],"type":"Point"}
}