{
  "type": "Feature",
  "properties": {
    "iso:country":"AU",
    "sg:address":"58 Aurora Drv",
    "sg:city":"Tregear",
    "sg:classifiers":[
        {
            "category":"Professional",
            "type":"Services"
        }
    ],
    "sg:phone":"+61 2 9628 8301",
    "sg:postcode":"2770",
    "sg:province":"NSW",
    "sg:tags":[
        "transport"
    ],
    "wof:name":"Trev-Trans Pty Ltd",
    "wof:placetype":"venue"
},
  "geometry": {"coordinates":[150.795318603,-33.7503929138],"type":"Point"}
}