{
  "type": "Feature",
  "properties": {
    "iso:country":"AU",
    "sg:address":"384 Lutwyche Rd",
    "sg:city":"Windsor",
    "sg:classifiers":[
        {
            "category":"Shopping",
            "subcategory":"Bicycles & Sporting Goods",
            "type":"Retail Goods"
        }
    ],
    "sg:phone":"+61 7 3856 1900",
    "sg:postcode":"4030",
    "sg:province":"QLD",
    "sg:tags":[
        "water",
        "equipment",
        "skiing"
    ],
    "wof:name":"Waterskiers Connection The",
    "wof:placetype":"venue"
},
  "geometry": {"coordinates":[153.032196,-27.426233],"type":"Point"}
}