{
  "type": "Feature",
  "properties": {
    "addr:full":"36 Avocet Crt Burpengary QLD 4505",
    "addr:housenumber":"36",
    "addr:postcode":"4505",
    "addr:street":"Avocet Crt",
    "iso:country":"AU",
    "sg:address":"36 Avocet Crt",
    "sg:city":"Burpengary",
    "sg:classifiers":[
        {
            "category":"Retail",
            "subcategory":"Auto Repair",
            "type":"Services"
        }
    ],
    "sg:phone":"+61 7 5498 5718",
    "sg:postcode":"4505",
    "sg:province":"QLD",
    "sg:tags":[
        "electrical"
    ],
    "wof:name":"Nicko's Auto & Marine Electrics",
    "wof:placetype":"venue"
},
  "geometry": {"coordinates":[152.94720459000001,-27.1461162567],"type":"Point"}
}