{
  "type": "Feature",
  "properties": {
    "addr:full":"Brisbane Technology Park, 2/ 77 Brandl St Eight Mile Plains QLD 4113",
    "addr:housenumber":"/ 77",
    "addr:postcode":"4113",
    "addr:street":"Brandl St",
    "iso:country":"AU",
    "sg:address":"Brisbane Technology Park, 2/ 77 Brandl St",
    "sg:city":"Eight Mile Plains",
    "sg:classifiers":[
        {
            "category":"Government",
            "subcategory":"Fire Station",
            "type":"Public Place"
        }
    ],
    "sg:phone":"+61 1300 133 473",
    "sg:postcode":"4113",
    "sg:province":"QLD",
    "sg:tags":[
        "equipment",
        "protection",
        "consultant"
    ],
    "sg:website":"http://www.spectrumfire.com.au",
    "wof:name":"Independent Fire Systems",
    "wof:placetype":"venue"
},
  "geometry": {"coordinates":[153.09909057600001,-27.5780353546],"type":"Point"}
}