{
  "type": "Feature",
  "properties": {
    "addr:full":"4/ 7 Price St Southport QLD 4215",
    "addr:housenumber":"/ 7",
    "addr:postcode":"4215",
    "addr:street":"Price St",
    "iso:country":"AU",
    "sg:address":"4/ 7 Price St",
    "sg:city":"Southport",
    "sg:classifiers":[
        {
            "category":"Manufacturing",
            "subcategory":"Motor Vehicles & Parts",
            "type":"Manufacturing & Wholesale Goods"
        }
    ],
    "sg:phone":"+61 7 5531 1931",
    "sg:postcode":"4215",
    "sg:province":"QLD",
    "sg:tags":[
        "replacement"
    ],
    "wof:name":"American Australian Autoparts",
    "wof:placetype":"venue"
},
  "geometry": {"coordinates":[153.404754639,-27.9660663605],"type":"Point"}
}