{
  "type": "Feature",
  "properties": {
    "iso:country":"AU",
    "sg:address":"Graham Rd",
    "sg:city":"Kyabram",
    "sg:classifiers":[
        {
            "category":"Building & Trades",
            "subcategory":"Construction",
            "type":"Services"
        }
    ],
    "sg:phone":"+61 3 5852 2158",
    "sg:postcode":"3620",
    "sg:province":"VIC",
    "sg:tags":[
        "contractor"
    ],
    "wof:name":"Paynter Don",
    "wof:placetype":"venue"
},
  "geometry": {"coordinates":[145.045043945,-36.2987976074],"type":"Point"}
}