{
  "type": "Feature",
  "properties": {
    "addr:full":"22 Drew St Greenacre NSW 2190",
    "addr:housenumber":"22",
    "addr:postcode":"2190",
    "addr:street":"Drew St",
    "iso:country":"AU",
    "sg:address":"22 Drew St",
    "sg:city":"Greenacre",
    "sg:classifiers":[
        {
            "category":"Personal",
            "subcategory":"Massage",
            "type":"Services"
        }
    ],
    "sg:phone":"+61 400 424 422",
    "sg:postcode":"2190",
    "sg:province":"NSW",
    "sg:tags":[
        "therapy"
    ],
    "wof:name":"Chichian Kevin-Softouch Therapeutic Services",
    "wof:placetype":"venue"
},
  "geometry": {"coordinates":[151.06712300000001,-33.907326],"type":"Point"}
}