{
  "type": "Feature",
  "properties": {
    "addr:full":"PO Box 376 Armadale WA 6992",
    "addr:postcode":"6992",
    "iso:country":"AU",
    "sg:address":"PO Box 376",
    "sg:city":"Armadale",
    "sg:classifiers":[
        {
            "category":"Professional",
            "type":"Services"
        }
    ],
    "sg:phone":"+61 8 9498 1838",
    "sg:postcode":"6992",
    "sg:province":"WA",
    "sg:tags":[
        "quality",
        "assurance"
    ],
    "wof:name":"Management & QA Systems",
    "wof:placetype":"venue"
},
  "geometry": {"coordinates":[116.00827,-32.15239],"type":"Point"}
}