{
  "type": "Feature",
  "properties": {
    "addr:full":"High St Hillston NSW 2675",
    "addr:postcode":"2675",
    "addr:street":"High St",
    "iso:country":"AU",
    "sg:address":"High St",
    "sg:city":"Hillston",
    "sg:classifiers":[
        {
            "category":"Autos & Motor Vehicles",
            "subcategory":"Fuel & Gas Station",
            "type":"Retail Goods"
        }
    ],
    "sg:phone":"+61 2 6967 2574",
    "sg:postcode":"2675",
    "sg:province":"NSW",
    "wof:name":"BP Australia Limited",
    "wof:placetype":"venue"
},
  "geometry": {"coordinates":[145.53733825699999,-33.4816551208],"type":"Point"}
}