{
  "type": "Feature",
  "properties": {
    "addr:full":"40 Manchester St Mile End SA 5031",
    "addr:housenumber":"40",
    "addr:postcode":"5031",
    "addr:street":"Manchester St",
    "iso:country":"AU",
    "sg:address":"40 Manchester St",
    "sg:city":"Mile End",
    "sg:classifiers":[
        {
            "category":"Ferry Terminal",
            "type":"Transportation"
        }
    ],
    "sg:phone":"+61 8 8443 6766",
    "sg:postcode":"5031",
    "sg:province":"SA",
    "sg:tags":[
        "mixing",
        "concrete",
        "vibrator",
        "equipment"
    ],
    "wof:name":"Marleston Pty Ltd",
    "wof:placetype":"venue"
},
  "geometry": {"coordinates":[138.57623290999999,-34.9391899109],"type":"Point"}
}