{
  "type": "Feature",
  "properties": {
    "addr:full":"Monash Rd Tarragindi QLD 4121",
    "addr:postcode":"4121",
    "addr:street":"Monash Rd",
    "iso:country":"AU",
    "sg:address":"Monash Rd",
    "sg:city":"Tarragindi",
    "sg:classifiers":[
        {
            "category":"Real Estate",
            "subcategory":"Real Estate Agent",
            "type":"Services"
        }
    ],
    "sg:phone":"+61 7 3848 9433",
    "sg:postcode":"4121",
    "sg:province":"QLD",
    "wof:name":"Reg Strow Real Estate",
    "wof:placetype":"venue"
},
  "geometry": {"coordinates":[153.044921875,-27.53266716],"type":"Point"}
}