{
  "type": "Feature",
  "properties": {
    "iso:country":"AU",
    "sg:address":"32 Highett St",
    "sg:city":"Richmond",
    "sg:classifiers":[
        {
            "category":"Health Services",
            "subcategory":"Doctor",
            "type":"Services"
        }
    ],
    "sg:phone":"+61 3 9421 6681",
    "sg:postcode":"3121",
    "sg:province":"VIC",
    "sg:tags":[
        "medical",
        "practitioner"
    ],
    "wof:name":"Entwisle Timothy Dr",
    "wof:placetype":"venue"
},
  "geometry": {"coordinates":[144.99220275900001,-37.8151435852],"type":"Point"}
}