{
  "type": "Feature",
  "properties": {
    "addr:full":"117 - 119 Evans St Sunbury VIC 3429",
    "addr:housenumber":"119",
    "addr:postcode":"3429",
    "addr:street":"Evans St",
    "iso:country":"AU",
    "sg:address":"117 - 119 Evans St",
    "sg:city":"Sunbury",
    "sg:classifiers":[
        {
            "category":"Retail",
            "subcategory":"Auto Repair",
            "type":"Services"
        }
    ],
    "sg:phone":"+61 3 9744 1200",
    "sg:postcode":"3429",
    "sg:province":"VIC",
    "sg:tags":[
        "beater",
        "painter",
        "panel"
    ],
    "wof:name":"Shepherd's Complete Car Care",
    "wof:placetype":"venue"
},
  "geometry": {"coordinates":[144.727905273,-37.5819587708],"type":"Point"}
}