{
  "type": "Feature",
  "properties": {
    "addr:full":"2 Princeton Ave Adamstown Heights NSW 2289",
    "addr:housenumber":"2",
    "addr:postcode":"2289",
    "addr:street":"Princeton Ave Adamstown",
    "iso:country":"AU",
    "sg:address":"2 Princeton Ave",
    "sg:city":"Adamstown Heights",
    "sg:classifiers":[
        {
            "category":"Real Estate",
            "subcategory":"Real Estate Agent",
            "type":"Services"
        }
    ],
    "sg:phone":"+61 412 867 777",
    "sg:postcode":"2289",
    "sg:province":"NSW",
    "wof:name":"Podmore David",
    "wof:placetype":"venue"
},
  "geometry": {"coordinates":[151.699615478,-32.9508361816],"type":"Point"}
}