{
  "type": "Feature",
  "properties": {
    "iso:country":"AU",
    "sg:address":"44 Kings Park Rd",
    "sg:city":"West Perth",
    "sg:classifiers":[
        {
            "category":"Professional",
            "subcategory":"Management & Consulting",
            "type":"Services"
        }
    ],
    "sg:phone":"+61 1300 302 783",
    "sg:postcode":"6005",
    "sg:province":"WA",
    "sg:tags":[
        "consultant"
    ],
    "wof:name":"Otto Bass",
    "wof:placetype":"venue"
},
  "geometry": {"coordinates":[115.837020874,-31.9514598846],"type":"Point"}
}