{
  "type": "Feature",
  "properties": {
    "addr:full":"18 Kurrajong St Sutherland NSW 2232",
    "addr:housenumber":"18",
    "addr:postcode":"2232",
    "addr:street":"Kurrajong St",
    "iso:country":"AU",
    "sg:address":"18 Kurrajong St",
    "sg:city":"Sutherland",
    "sg:classifiers":[
        {
            "category":"Banks & Credit Unions",
            "subcategory":"Financial Services",
            "type":"Services"
        }
    ],
    "sg:phone":"+61 2 9576 5730",
    "sg:postcode":"2232",
    "sg:province":"NSW",
    "sg:tags":[
        "planning"
    ],
    "wof:name":"Central & Southern Financial Group",
    "wof:placetype":"venue"
},
  "geometry": {"coordinates":[151.05946350100001,-34.0257797241],"type":"Point"}
}