{
  "type": "Feature",
  "properties": {
    "iso:country":"AU",
    "sg:address":"Shop 49 Wynnum Plaza, 2021 Wynnum Rd",
    "sg:city":"Wynnum",
    "sg:classifiers":[
        {
            "category":"Travel",
            "subcategory":"Travel Agent",
            "type":"Entertainment"
        }
    ],
    "sg:phone":"+61 13 18 66",
    "sg:postcode":"4178",
    "sg:province":"QLD",
    "sg:tags":[
        "consultant"
    ],
    "wof:name":"Flight Centre",
    "wof:placetype":"venue"
},
  "geometry": {"coordinates":[153.15676879899999,-27.4412631989],"type":"Point"}
}