{
  "type": "Feature",
  "properties": {
    "addr:full":"Suite 10/ 20 Young St Neutral Bay NSW 2089",
    "addr:housenumber":"10 / 20",
    "addr:postcode":"2089",
    "addr:street":"Young St",
    "iso:country":"AU",
    "sg:address":"Suite 10/ 20 Young St",
    "sg:city":"Neutral Bay",
    "sg:classifiers":[
        {
            "category":"Professional",
            "subcategory":"Engineering",
            "type":"Services"
        }
    ],
    "sg:phone":"+61 2 9908 2133",
    "sg:postcode":"2089",
    "sg:province":"NSW",
    "sg:tags":[
        "consulting",
        "engineer"
    ],
    "wof:name":"Paul Bekker Engineering Consultants Pty Ltd",
    "wof:placetype":"venue"
},
  "geometry": {"coordinates":[151.221359253,-33.8301811218],"type":"Point"}
}