{
  "type": "Feature",
  "properties": {
    "addr:full":"Finucane Rd Alexandra Hills QLD 4161",
    "addr:postcode":"4161",
    "addr:street":"Finucane Rd",
    "iso:country":"AU",
    "sg:address":"Finucane Rd",
    "sg:city":"Alexandra Hills",
    "sg:classifiers":[
        {
            "category":"Retail",
            "subcategory":"Event Space",
            "type":"Services"
        }
    ],
    "sg:phone":"+61 7 3824 4444",
    "sg:postcode":"4161",
    "sg:province":"QLD",
    "sg:tags":[
        "venue",
        "reception",
        "wedding"
    ],
    "wof:name":"Alexandra Hills Hotel/Motel",
    "wof:placetype":"venue"
},
  "geometry": {"coordinates":[153.22972106899999,-27.5240459442],"type":"Point"}
}