{
  "type": "Feature",
  "properties": {
    "addr:full":"Cnr Wilson & Ladbrook Sts Burnie TAS 7320",
    "addr:postcode":"7320",
    "addr:street":"Cnr",
    "iso:country":"AU",
    "sg:address":"Cnr Wilson & Ladbrook Sts",
    "sg:city":"Burnie",
    "sg:classifiers":[
        {
            "category":"Banks & Credit Unions",
            "subcategory":"Financial Services",
            "type":"Services"
        }
    ],
    "sg:phone":"+61 13 80 01",
    "sg:postcode":"7320",
    "sg:province":"TAS",
    "sg:tags":[
        "loan",
        "finance",
        "mortgage"
    ],
    "wof:name":"MyState Financial",
    "wof:placetype":"venue"
},
  "geometry": {"coordinates":[145.89825400000001,-41.075859],"type":"Point"}
}