{
  "type": "Feature",
  "properties": {
    "iso:country":"AU",
    "sg:address":"PO Box 2002",
    "sg:city":"Gladstone",
    "sg:classifiers":[
        {
            "category":"Banks & Credit Unions",
            "subcategory":"Atm",
            "type":"Services"
        }
    ],
    "sg:phone":"+61 1800 468 719",
    "sg:postcode":"4680",
    "sg:province":"QLD",
    "sg:tags":[
        "control",
        "soil",
        "erosion",
        "stabilisation"
    ],
    "wof:name":"Lanyonscapes",
    "wof:placetype":"venue"
},
  "geometry": {"coordinates":[151.25355529800001,-23.8438205719],"type":"Point"}
}