{
  "type": "Feature",
  "properties": {
    "iso:country":"AU",
    "sg:address":"17 McDonald St",
    "sg:city":"Murtoa",
    "sg:classifiers":[
        {
            "category":"Retail",
            "subcategory":"Funeral Services",
            "type":"Services"
        }
    ],
    "sg:phone":"+61 3 5385 2833",
    "sg:postcode":"3390",
    "sg:province":"VIC",
    "sg:tags":[
        "director"
    ],
    "wof:name":"Murtoa Funerals",
    "wof:placetype":"venue"
},
  "geometry": {"coordinates":[142.470703125,-36.6168327332],"type":"Point"}
}