{
  "type": "Feature",
  "properties": {
    "iso:country":"AU",
    "sg:address":"Lot989/ Industrial Rd",
    "sg:city":"Denmark",
    "sg:classifiers":[
        {
            "category":"Retail",
            "subcategory":"Auto Repair",
            "type":"Services"
        }
    ],
    "sg:phone":"+61 8 9848 3599",
    "sg:postcode":"6333",
    "sg:province":"WA",
    "sg:tags":[
        "beater",
        "painter",
        "panel"
    ],
    "wof:name":"Triple J Panel & Paint",
    "wof:placetype":"venue"
},
  "geometry": {"coordinates":[117.355636597,-34.9674606323],"type":"Point"}
}