{
  "type": "Feature",
  "properties": {
    "addr:full":"U1/ 9 Barnett Pl Molendinar QLD 4214",
    "addr:housenumber":"9",
    "addr:postcode":"4214",
    "addr:street":"U1 /;Pl",
    "iso:country":"AU",
    "sg:address":"U1/ 9 Barnett Pl",
    "sg:city":"Molendinar",
    "sg:classifiers":[
        {
            "category":"Real Estate",
            "subcategory":"Real Estate Agent",
            "type":"Services"
        }
    ],
    "sg:phone":"+61 7 5563 2617",
    "sg:postcode":"4214",
    "sg:province":"QLD",
    "wof:name":"P.T. Realty",
    "wof:placetype":"venue"
},
  "geometry": {"coordinates":[153.36015319800001,-27.9654884338],"type":"Point"}
}