{
  "type": "Feature",
  "properties": {
    "addr:full":"195 Nicholson St Brunswick East VIC 3057",
    "addr:housenumber":"195",
    "addr:postcode":"3057",
    "addr:street":"Nicholson St",
    "iso:country":"AU",
    "sg:address":"195 Nicholson St",
    "sg:city":"Brunswick East",
    "sg:classifiers":[
        {
            "category":"Food & Beverages",
            "subcategory":"Groceries & Convenience Stores",
            "type":"Retail Goods"
        }
    ],
    "sg:phone":"+61 3 9388 0387",
    "sg:postcode":"3057",
    "sg:province":"VIC",
    "wof:name":"LR Warehouse",
    "wof:placetype":"venue"
},
  "geometry": {"coordinates":[144.979736328,-37.7690124512],"type":"Point"}
}