{
  "type": "Feature",
  "properties": {
    "addr:full":"Cnr Quantum Cl & Gaine Rd Dandenong South VIC 3175",
    "addr:postcode":"3175",
    "addr:street":"Quantum Cl & Gaine Rd",
    "iso:country":"AU",
    "sg:address":"Cnr Quantum Cl & Gaine Rd",
    "sg:city":"Dandenong South",
    "sg:classifiers":[
        {
            "category":"Professional",
            "type":"Services"
        }
    ],
    "sg:phone":"+61 3 9799 5655",
    "sg:postcode":"3175",
    "sg:province":"VIC",
    "sg:tags":[
        "transport"
    ],
    "wof:name":"DTM Business Logistics",
    "wof:placetype":"venue"
},
  "geometry": {"coordinates":[145.240325928,-38.030582428],"type":"Point"}
}