{
  "type": "Feature",
  "properties": {
    "addr:full":"O'Briens Rd Cattai NSW 2756",
    "addr:postcode":"2756",
    "addr:street":"O'Briens Rd",
    "iso:country":"AU",
    "sg:address":"O'Briens Rd",
    "sg:city":"Cattai",
    "sg:classifiers":[
        {
            "category":"Building & Trades",
            "subcategory":"Construction",
            "type":"Services"
        }
    ],
    "sg:phone":"+61 414 975 490",
    "sg:postcode":"2756",
    "sg:province":"NSW",
    "sg:tags":[
        "spouting",
        "guttering"
    ],
    "wof:name":"Hahn Constructions Pty. Ltd.",
    "wof:placetype":"venue"
},
  "geometry": {"coordinates":[150.91680908199999,-33.5267829895],"type":"Point"}
}