{
  "type": "Feature",
  "properties": {
    "iso:country":"AU",
    "sg:address":"24 Realm St",
    "sg:city":"Auchenflower",
    "sg:classifiers":[
        {
            "category":"Communications",
            "type":"Services"
        }
    ],
    "sg:phone":"+61 7 3371 6827",
    "sg:postcode":"4066",
    "sg:province":"QLD",
    "sg:tags":[
        "translation"
    ],
    "wof:name":"Jehne C & M Language Services",
    "wof:placetype":"venue"
},
  "geometry": {"coordinates":[152.98965454099999,-27.4725570679],"type":"Point"}
}