{
  "type": "Feature",
  "properties": {
    "addr:full":"Suite 2, 19 Lang Pde Milton QLD 4064",
    "addr:housenumber":"19",
    "addr:postcode":"4064",
    "addr:street":"Lang Pde",
    "iso:country":"AU",
    "sg:address":"Suite 2, 19 Lang Pde",
    "sg:city":"Milton",
    "sg:classifiers":[
        {
            "category":"Health Services",
            "subcategory":"Health Practitioner",
            "type":"Services"
        }
    ],
    "sg:phone":"+61 7 3377 7899",
    "sg:postcode":"4064",
    "sg:province":"QLD",
    "sg:tags":[
        "physiotherapist"
    ],
    "wof:name":"Chong Len",
    "wof:placetype":"venue"
},
  "geometry": {"coordinates":[153.001754761,-27.4740123749],"type":"Point"}
}