{
  "type": "Feature",
  "properties": {
    "iso:country":"AU",
    "sg:address":"4 Hamilton St",
    "sg:city":"Cannington",
    "sg:classifiers":[
        {
            "category":"Restaurant",
            "type":"Food & Drink"
        }
    ],
    "sg:phone":"+61 8 9451 7570",
    "sg:postcode":"6107",
    "sg:province":"WA",
    "wof:name":"Ambassador Chinese Restaurant",
    "wof:placetype":"venue"
},
  "geometry": {"coordinates":[115.924453735,-32.0128211975],"type":"Point"}
}