{
  "type": "Feature",
  "properties": {
    "iso:country":"AU",
    "sg:address":"145 Flinders St",
    "sg:city":"Townsville City",
    "sg:classifiers":[
        {
            "category":"Restaurant",
            "type":"Food & Drink"
        }
    ],
    "sg:phone":"+61 7 4771 2173",
    "sg:postcode":"4810",
    "sg:province":"QLD",
    "wof:name":"Casa Lounge Bar & Restaurant",
    "wof:placetype":"venue"
},
  "geometry": {"coordinates":[146.810165,-19.266413],"type":"Point"}
}