{
  "type": "Feature",
  "properties": {
    "addr:full":"145 Flinders St Townsville City QLD 4810",
    "addr:housenumber":"145",
    "addr:postcode":"4810",
    "addr:street":"Flinders St",
    "iso:country":"AU",
    "sg:address":"145 Flinders St",
    "sg:city":"Townsville City",
    "sg:classifiers":[
        {
            "category":"Restaurant",
            "type":"Food & Drink"
        }
    ],
    "sg:phone":"+61 7 4771 2173",
    "sg:postcode":"4810",
    "sg:province":"QLD",
    "wof:name":"Casa Lounge Bar & Restaurant",
    "wof:placetype":"venue"
},
  "geometry": {"coordinates":[146.81016500000001,-19.266413],"type":"Point"}
}