{
  "type": "Feature",
  "properties": {
    "iso:country":"AU",
    "sg:address":"53 Merton Rd",
    "sg:city":"Woolloongabba",
    "sg:classifiers":[
        {
            "category":"Building & Trades",
            "subcategory":"Construction",
            "type":"Services"
        }
    ],
    "sg:phone":"+61 7 3391 1215",
    "sg:postcode":"4102",
    "sg:province":"QLD",
    "sg:tags":[
        "home",
        "air conditioning"
    ],
    "wof:name":"Allon Air",
    "wof:placetype":"venue"
},
  "geometry": {"coordinates":[153.02984619099999,-27.4898643494],"type":"Point"}
}