{
  "type": "Feature",
  "properties": {
    "addr:full":"Unit 2/ 66 Ashford Ave Milperra NSW 2214",
    "addr:housenumber":"66",
    "addr:postcode":"2214",
    "addr:street":"Ashford Ave",
    "iso:country":"AU",
    "sg:address":"Unit 2/ 66 Ashford Ave",
    "sg:city":"Milperra",
    "sg:classifiers":[
        {
            "category":"Manufacturing",
            "subcategory":"Chemicals & Compounds",
            "type":"Manufacturing & Wholesale Goods"
        }
    ],
    "sg:phone":"+61 2 9792 3341",
    "sg:postcode":"2214",
    "sg:province":"NSW",
    "sg:tags":[
        "agricultural"
    ],
    "wof:name":"Maxwell & Kemp Pty Ltd",
    "wof:placetype":"venue"
},
  "geometry": {"coordinates":[150.989532,-33.935692],"type":"Point"}
}