{
  "type": "Feature",
  "properties": {
    "iso:country":"AU",
    "sg:address":"4 Hospital Rd",
    "sg:city":"Emerald",
    "sg:classifiers":[
        {
            "category":"Food & Beverages",
            "subcategory":"Bakery",
            "type":"Retail Goods"
        }
    ],
    "sg:phone":"+61 7 4982 1485",
    "sg:postcode":"4720",
    "sg:province":"QLD",
    "sg:tags":[
        "baker"
    ],
    "wof:name":"Fairbairn Bakery",
    "wof:placetype":"venue"
},
  "geometry": {"coordinates":[148.15820299999999,-23.523741],"type":"Point"}
}