{
  "type": "Feature",
  "properties": {
    "iso:country":"AU",
    "sg:address":"1 Bell St",
    "sg:city":"Ipswich",
    "sg:classifiers":[
        {
            "category":"Shopping",
            "subcategory":"Music",
            "type":"Retail Goods"
        }
    ],
    "sg:phone":"+61 7 3812 2622",
    "sg:postcode":"4305",
    "sg:province":"QLD",
    "sg:tags":[
        "instrument",
        "musical"
    ],
    "wof:name":"Word Of Mouth",
    "wof:placetype":"venue"
},
  "geometry": {"coordinates":[152.760055542,-27.6142673492],"type":"Point"}
}