{
  "type": "Feature",
  "properties": {
    "iso:country":"AU",
    "sg:address":"5 Oronsay Crs",
    "sg:city":"Diamond Creek",
    "sg:classifiers":[
        {
            "category":"Building & Trades",
            "subcategory":"Plumbing",
            "type":"Services"
        }
    ],
    "sg:phone":"+61 3 9438 5334",
    "sg:postcode":"3089",
    "sg:province":"VIC",
    "sg:tags":[
        "plumber",
        "gasfitters"
    ],
    "wof:name":"MLH Plumbing",
    "wof:placetype":"venue"
},
  "geometry": {"coordinates":[145.15799,-37.674252],"type":"Point"}
}