{
  "type": "Feature",
  "properties": {
    "iso:country":"AU",
    "sg:address":"16 Laidlaw Drv",
    "sg:city":"Ballarat",
    "sg:classifiers":[
        {
            "category":"Building & Trades",
            "subcategory":"Construction",
            "type":"Services"
        }
    ],
    "sg:phone":"+61 3 5335 5058",
    "sg:postcode":"3353",
    "sg:province":"VIC",
    "sg:tags":[
        "contractor"
    ],
    "wof:name":"Fenlon Homes Pty Ltd",
    "wof:placetype":"venue"
},
  "geometry": {"coordinates":[143.824844,-37.577541],"type":"Point"}
}