{
  "type": "Feature",
  "properties": {
    "addr:full":"128 Scrub Hill Rd Hervey Bay QLD 4655",
    "addr:housenumber":"128",
    "addr:postcode":"4655",
    "addr:street":"Scrub Hill Rd",
    "iso:country":"AU",
    "sg:address":"128 Scrub Hill Rd",
    "sg:city":"Hervey Bay",
    "sg:classifiers":[
        {
            "category":"Home & Garden",
            "subcategory":"Garden Supply",
            "type":"Retail Goods"
        }
    ],
    "sg:phone":"+61 7 4124 4596",
    "sg:postcode":"4655",
    "sg:province":"QLD",
    "sg:tags":[
        "landscape"
    ],
    "wof:name":"Bay City Mini-Mix",
    "wof:placetype":"venue"
},
  "geometry": {"coordinates":[152.807434,-25.302099],"type":"Point"}
}