{
  "type": "Feature",
  "properties": {
    "iso:country":"AU",
    "sg:address":"10 Monger St",
    "sg:city":"Perth",
    "sg:classifiers":[
        {
            "category":"Building & Trades",
            "subcategory":"Construction",
            "type":"Services"
        }
    ],
    "sg:phone":"+61 8 9227 1822",
    "sg:postcode":"6000",
    "sg:province":"WA",
    "sg:tags":[
        "renovation",
        "alterations",
        "extension",
        "contractor"
    ],
    "wof:name":"Amerex Pty Ltd",
    "wof:placetype":"venue"
},
  "geometry": {"coordinates":[115.864097595,-31.9451370239],"type":"Point"}
}