{
  "type": "Feature",
  "properties": {
    "iso:country":"AU",
    "sg:address":"75 Esmond Rd",
    "sg:city":"Port Pirie",
    "sg:classifiers":[
        {
            "category":"Retail",
            "subcategory":"Auto Repair",
            "type":"Services"
        }
    ],
    "sg:phone":"+61 8 8632 3099",
    "sg:postcode":"5540",
    "sg:province":"SA",
    "sg:tags":[
        "electrical"
    ],
    "wof:name":"Coe's Auto Electrical",
    "wof:placetype":"venue"
},
  "geometry": {"coordinates":[138.00898742699999,-33.1935043335],"type":"Point"}
}