{
  "type": "Feature",
  "properties": {
    "addr:full":"26 Watt Rd Mornington VIC 3931",
    "addr:housenumber":"26",
    "addr:postcode":"3931",
    "addr:street":"Watt Rd",
    "iso:country":"AU",
    "sg:address":"26 Watt Rd",
    "sg:city":"Mornington",
    "sg:classifiers":[
        {
            "category":"Retail",
            "subcategory":"Auto Repair",
            "type":"Services"
        }
    ],
    "sg:phone":"+61 3 5975 7136",
    "sg:postcode":"3931",
    "sg:province":"VIC",
    "sg:tags":[
        "repairer",
        "motor",
        "engineer"
    ],
    "wof:name":"DP Euopean Car Services",
    "wof:placetype":"venue"
},
  "geometry": {"coordinates":[145.05125427199999,-38.2306938171],"type":"Point"}
}