{
  "type": "Feature",
  "properties": {
    "addr:full":"37 Arundel Rd Park Orchards VIC 3114",
    "addr:housenumber":"37",
    "addr:postcode":"3114",
    "addr:street":"Arundel Rd",
    "iso:country":"AU",
    "sg:address":"37 Arundel Rd",
    "sg:city":"Park Orchards",
    "sg:classifiers":[
        {
            "category":"Retail",
            "subcategory":"Car Wash",
            "type":"Services"
        }
    ],
    "sg:phone":"+61 3 9812 2544",
    "sg:postcode":"3114",
    "sg:province":"VIC",
    "sg:tags":[
        "merchant",
        "oil",
        "refiner"
    ],
    "wof:name":"Lubrication Engineers Pty Ltd",
    "wof:placetype":"venue"
},
  "geometry": {"coordinates":[145.21841430699999,-37.7775840759],"type":"Point"}
}