{
  "type": "Feature",
  "properties": {
    "iso:country":"AU",
    "sg:address":"20-22 Old Creswick Rd",
    "sg:city":"Ballarat",
    "sg:classifiers":[
        {
            "category":"Bars & Pubs",
            "subcategory":"Gay Bar",
            "type":"Food & Drink"
        }
    ],
    "sg:phone":"+61 3 5333 3008",
    "sg:postcode":"3350",
    "sg:province":"VIC",
    "sg:tags":[
        "plywood",
        "veneer"
    ],
    "wof:name":"Ballarat Joinery Supplies",
    "wof:placetype":"venue"
},
  "geometry": {"coordinates":[143.84930399999999,-37.525589],"type":"Point"}
}