{
  "type": "Feature",
  "properties": {
    "addr:full":"79 Ingham Rd Townsville QLD 4810",
    "addr:housenumber":"79",
    "addr:postcode":"4810",
    "addr:street":"Ingham Rd",
    "iso:country":"AU",
    "sg:address":"79 Ingham Rd",
    "sg:city":"Townsville",
    "sg:classifiers":[
        {
            "category":"Shopping",
            "subcategory":"Computers & Home Electronics",
            "type":"Retail Goods"
        }
    ],
    "sg:phone":"+61 7 4724 5056",
    "sg:postcode":"4810",
    "sg:province":"QLD",
    "sg:tags":[
        "hardware",
        "equipment"
    ],
    "wof:name":"J L C Computers",
    "wof:placetype":"venue"
},
  "geometry": {"coordinates":[146.799576,-19.268028],"type":"Point"}
}