{
  "type": "Feature",
  "properties": {
    "addr:full":"Unit 10, The Brickworks, Warehouse Road Southport QLD 4215",
    "addr:postcode":"4215",
    "addr:street":"Warehouse Road",
    "iso:country":"AU",
    "sg:address":"Unit 10, The Brickworks, Warehouse Road",
    "sg:city":"Southport",
    "sg:classifiers":[
        {
            "category":"Manufacturing",
            "subcategory":"Electronics",
            "type":"Manufacturing & Wholesale Goods"
        }
    ],
    "sg:phone":"+61 7 5591 6050",
    "sg:postcode":"4215",
    "sg:province":"QLD",
    "sg:tags":[
        "wholesaler",
        "equipment",
        "part",
        "mfrs",
        "refrigeration"
    ],
    "wof:name":"Actrol Parts",
    "wof:placetype":"venue"
},
  "geometry": {"coordinates":[153.408935547,-27.979801178],"type":"Point"}
}