{
  "type": "Feature",
  "properties": {
    "addr:full":"8 Rifle Range Rd Lismore NSW 2480",
    "addr:housenumber":"8",
    "addr:postcode":"2480",
    "addr:street":"Rifle Range Rd",
    "iso:country":"AU",
    "sg:address":"8 Rifle Range Rd",
    "sg:city":"Lismore",
    "sg:classifiers":[
        {
            "category":"Retail",
            "subcategory":"Repair Shop",
            "type":"Services"
        }
    ],
    "sg:phone":"+61 2 6621 7716",
    "sg:postcode":"2480",
    "sg:province":"NSW",
    "sg:tags":[
        "stove",
        "part",
        "range"
    ],
    "wof:name":"Bostock's Appliance Repairs",
    "wof:placetype":"venue"
},
  "geometry": {"coordinates":[153.302337647,-28.821811676],"type":"Point"}
}