{
  "type": "Feature",
  "properties": {
    "addr:full":"22- 30 Frome St Adelaide SA 5000",
    "addr:housenumber":"30",
    "addr:postcode":"5000",
    "addr:street":"Frome St",
    "iso:country":"AU",
    "sg:address":"22- 30 Frome St",
    "sg:city":"Adelaide",
    "sg:classifiers":[
        {
            "category":"Parking",
            "type":"Transportation"
        }
    ],
    "sg:phone":"+61 8 8203 7203",
    "sg:postcode":"5000",
    "sg:province":"SA",
    "wof:name":"U Park",
    "wof:placetype":"venue"
},
  "geometry": {"coordinates":[138.608032227,-34.9219284058],"type":"Point"}
}