{
  "type": "Feature",
  "properties": {
    "addr:full":"11 Boronia Crs Cockatoo VIC 3781",
    "addr:housenumber":"11",
    "addr:postcode":"3781",
    "addr:street":"Boronia Crs",
    "iso:country":"AU",
    "sg:address":"11 Boronia Crs",
    "sg:city":"Cockatoo",
    "sg:classifiers":[
        {
            "category":"Building & Trades",
            "subcategory":"Landscaping Services",
            "type":"Services"
        }
    ],
    "sg:phone":"+61 3 5968 8707",
    "sg:postcode":"3781",
    "sg:province":"VIC",
    "sg:tags":[
        "designer",
        "landscape",
        "contractor"
    ],
    "wof:name":"Arbor Landscapes",
    "wof:placetype":"venue"
},
  "geometry": {"coordinates":[145.49375900000001,-37.936218],"type":"Point"}
}