{
  "type": "Feature",
  "properties": {
    "iso:country":"AU",
    "sg:address":"Ste6/ 64 Thomas Drv",
    "sg:city":"Surfers Paradise",
    "sg:classifiers":[
        {
            "category":"Real Estate",
            "subcategory":"Developer",
            "type":"Services"
        }
    ],
    "sg:phone":"+61 7 5561 0888",
    "sg:postcode":"4217",
    "sg:province":"QLD",
    "sg:tags":[
        "development"
    ],
    "wof:name":"Australia Wealth Group Pty Ltd",
    "wof:placetype":"venue"
},
  "geometry": {"coordinates":[153.418502808,-27.9979763031],"type":"Point"}
}