{
  "type": "Feature",
  "properties": {
    "iso:country":"AU",
    "sg:address":"60 Tyndall Rd",
    "sg:city":"Bonnet Hill",
    "sg:classifiers":[
        {
            "category":"Professional",
            "subcategory":"Art Services",
            "type":"Services"
        }
    ],
    "sg:phone":"+61 416 175 798",
    "sg:postcode":"7053",
    "sg:province":"TAS",
    "sg:tags":[
        "decorator",
        "painter"
    ],
    "wof:name":"Southern Painting & Applicators",
    "wof:placetype":"venue"
},
  "geometry": {"coordinates":[147.330154,-42.974621],"type":"Point"}
}