{
  "type": "Feature",
  "properties": {
    "iso:country":"AU",
    "sg:address":"83- 85 Ebsworth St",
    "sg:city":"Tamworth",
    "sg:classifiers":[
        {
            "category":"Restaurant",
            "type":"Food & Drink"
        }
    ],
    "sg:phone":"+61 2 6762 0033",
    "sg:postcode":"2340",
    "sg:province":"NSW",
    "wof:name":"Ashby House Motor Inn & Restaurant",
    "wof:placetype":"venue"
},
  "geometry": {"coordinates":[150.923370361,-31.0937862396],"type":"Point"}
}