{
  "type": "Feature",
  "properties": {
    "iso:country":"AU",
    "sg:address":"49 Kiora Rd",
    "sg:city":"Miranda",
    "sg:classifiers":[
        {
            "category":"Insurance",
            "subcategory":"Hazard Insurance",
            "type":"Services"
        }
    ],
    "sg:phone":"+61 13 21 32",
    "sg:postcode":"2228",
    "sg:province":"NSW",
    "sg:tags":[
        "motor",
        "vehicle"
    ],
    "wof:name":"NRMA Insurance",
    "wof:placetype":"venue"
},
  "geometry": {"coordinates":[151.10194397000001,-34.0349388123],"type":"Point"}
}