{
  "type": "Feature",
  "properties": {
    "iso:country":"AU",
    "sg:address":"31 Kinkora Rd",
    "sg:city":"Hawthorn",
    "sg:classifiers":[
        {
            "category":"Home & Garden",
            "subcategory":"Kitchen Supply",
            "type":"Retail Goods"
        }
    ],
    "sg:phone":"+61 3 9818 4471",
    "sg:postcode":"3122",
    "sg:province":"VIC",
    "sg:tags":[
        "vegetable",
        "fruit",
        "grain",
        "exporter"
    ],
    "wof:name":"Vic Fresh Pty Ltd",
    "wof:placetype":"venue"
},
  "geometry": {"coordinates":[145.03221130399999,-37.8164978027],"type":"Point"}
}