{
  "type": "Feature",
  "properties": {
    "iso:country":"AU",
    "sg:address":"PO Box 265",
    "sg:city":"Concord",
    "sg:classifiers":[
        {
            "category":"Real Estate",
            "subcategory":"Real Estate Services",
            "type":"Services"
        }
    ],
    "sg:phone":"+61 417 297 041",
    "sg:postcode":"2137",
    "sg:province":"NSW",
    "sg:tags":[
        "auctioneer"
    ],
    "wof:name":"Phillip Virgona",
    "wof:placetype":"venue"
},
  "geometry": {"coordinates":[151.10325622600001,-33.8560791016],"type":"Point"}
}