{
  "type": "Feature",
  "properties": {
    "addr:full":"1/ 33 Rendle St Aitkenvale QLD 4814",
    "addr:housenumber":"/ 33",
    "addr:postcode":"4814",
    "addr:street":"Rendle St",
    "iso:country":"AU",
    "sg:address":"1/ 33 Rendle St",
    "sg:city":"Aitkenvale",
    "sg:classifiers":[
        {
            "category":"Education",
            "subcategory":"Special Training",
            "type":"Public Place"
        }
    ],
    "sg:phone":"+61 7 4779 9928",
    "sg:postcode":"4814",
    "sg:province":"QLD",
    "sg:tags":[
        "school",
        "art"
    ],
    "wof:name":"The Blue Art Shop",
    "wof:placetype":"venue"
},
  "geometry": {"coordinates":[146.77034,-19.291946],"type":"Point"}
}