{
  "type": "Feature",
  "properties": {
    "addr:full":"491 High St Prahran VIC 3181",
    "addr:housenumber":"491",
    "addr:postcode":"3181",
    "addr:street":"High St",
    "iso:country":"AU",
    "sg:address":"491 High St",
    "sg:city":"Prahran",
    "sg:classifiers":[
        {
            "category":"Shopping",
            "subcategory":"Antiques",
            "type":"Retail Goods"
        }
    ],
    "sg:phone":"+61 3 9510 8522",
    "sg:postcode":"3181",
    "sg:province":"VIC",
    "wof:name":"Leclerc Antiques & Art Decor",
    "wof:placetype":"venue"
},
  "geometry": {"coordinates":[145.004394531,-37.8531837463],"type":"Point"}
}