{
  "type": "Feature",
  "properties": {
    "iso:country":"AU",
    "sg:address":"Breffny Rd",
    "sg:city":"Romaine Heights",
    "sg:classifiers":[
        {
            "category":"Communications",
            "subcategory":"News Services",
            "type":"Services"
        }
    ],
    "sg:phone":"+61 3 6433 0478",
    "sg:postcode":"7320",
    "sg:province":"TAS",
    "sg:tags":[
        "information",
        "tourist",
        "attractions"
    ],
    "wof:name":"Emu Valley Rhododendron Garden Inc",
    "wof:placetype":"venue"
},
  "geometry": {"coordinates":[145.90063499999999,-41.09993],"type":"Point"}
}