{
  "type": "Feature",
  "properties": {
    "addr:full":"106 Hertford St Sebastopol VIC 3356",
    "addr:housenumber":"106",
    "addr:postcode":"3356",
    "addr:street":"Hertford St",
    "iso:country":"AU",
    "sg:address":"106 Hertford St",
    "sg:city":"Sebastopol",
    "sg:classifiers":[
        {
            "category":"Retail",
            "subcategory":"Auto Repair",
            "type":"Services"
        }
    ],
    "sg:phone":"+61 409 188 525",
    "sg:postcode":"3356",
    "sg:province":"VIC",
    "sg:tags":[
        "car",
        "restoration",
        "supply"
    ],
    "wof:name":"Rods &#039;N Restos",
    "wof:placetype":"venue"
},
  "geometry": {"coordinates":[143.82792699999999,-37.586903],"type":"Point"}
}