{
  "type": "Feature",
  "properties": {
    "iso:country":"AU",
    "sg:address":"2 Craine St",
    "sg:city":"South Melbourne",
    "sg:classifiers":[
        {
            "category":"Professional",
            "subcategory":"Accounting & Tax Preparation",
            "type":"Services"
        }
    ],
    "sg:phone":"+61 3 9645 5400",
    "sg:postcode":"3205",
    "sg:province":"VIC",
    "sg:tags":[
        "accountant",
        "auditor"
    ],
    "wof:name":"MI Accountants & Advisors",
    "wof:placetype":"venue"
},
  "geometry": {"coordinates":[144.960938,-37.830605],"type":"Point"}
}