{
  "type": "Feature",
  "properties": {
    "addr:full":"4 Shell Crt Beldon WA 6027",
    "addr:housenumber":"4",
    "addr:postcode":"6027",
    "addr:street":"Shell Crt",
    "iso:country":"AU",
    "sg:address":"4 Shell Crt",
    "sg:city":"Beldon",
    "sg:classifiers":[
        {
            "category":"Freight",
            "type":"Transportation"
        }
    ],
    "sg:phone":"+61 8 9401 7560",
    "sg:postcode":"6027",
    "sg:province":"WA",
    "sg:tags":[
        "light",
        "carrier"
    ],
    "wof:name":"Xtel Pty Ltd",
    "wof:placetype":"venue"
},
  "geometry": {"coordinates":[115.758827209,-31.7717933655],"type":"Point"}
}