{
  "type": "Feature",
  "properties": {
    "addr:full":"61 Cossington Smith Crs Lyneham ACT 2602",
    "addr:housenumber":"61",
    "addr:postcode":"2602",
    "addr:street":"Cossington Smith Crs",
    "iso:country":"AU",
    "sg:address":"61 Cossington Smith Crs",
    "sg:city":"Lyneham",
    "sg:classifiers":[
        {
            "category":"Home & Garden",
            "subcategory":"Carpets & Floor Coverings",
            "type":"Retail Goods"
        }
    ],
    "sg:phone":"+61 2 6257 5465",
    "sg:postcode":"2602",
    "sg:province":"ACT",
    "sg:tags":[
        "tile",
        "wall",
        "layer"
    ],
    "wof:name":"Binos Bathroom Renovations",
    "wof:placetype":"venue"
},
  "geometry": {"coordinates":[149.12710571299999,-35.2443618774],"type":"Point"}
}