{
  "type": "Feature",
  "properties": {
    "iso:country":"AU",
    "sg:address":"4 Moore St",
    "sg:city":"Rochester",
    "sg:classifiers":[
        {
            "category":"Wholesale",
            "subcategory":"Scrap",
            "type":"Manufacturing & Wholesale Goods"
        }
    ],
    "sg:phone":"+61 3 5484 2217",
    "sg:postcode":"3561",
    "sg:province":"VIC",
    "sg:tags":[
        "merchant",
        "metal"
    ],
    "wof:name":"Petes Collectables and Metal Recycling",
    "wof:placetype":"venue"
},
  "geometry": {"coordinates":[144.697265625,-36.3652915955],"type":"Point"}
}