{
  "type": "Feature",
  "properties": {
    "iso:country":"AU",
    "sg:address":"12 Leghorn St",
    "sg:city":"(Next to Cinema) Rockingham",
    "sg:classifiers":[
        {
            "category":"Health Services",
            "subcategory":"Dentist",
            "type":"Services"
        }
    ],
    "sg:phone":"+61 8 9527 8822",
    "sg:postcode":"6168",
    "sg:province":"WA",
    "wof:name":"George . T . Tan",
    "wof:placetype":"venue"
},
  "geometry": {"coordinates":[115.74149300000001,-32.285564],"type":"Point"}
}