{
  "type": "Feature",
  "properties": {
    "addr:full":"15 Elm St Colo Vale NSW 2575",
    "addr:housenumber":"15",
    "addr:postcode":"2575",
    "addr:street":"Elm St",
    "iso:country":"AU",
    "sg:address":"15 Elm St",
    "sg:city":"Colo Vale",
    "sg:classifiers":[
        {
            "category":"Utilities",
            "type":"Services"
        }
    ],
    "sg:phone":"+61 419 999 170",
    "sg:postcode":"2575",
    "sg:province":"NSW",
    "sg:tags":[
        "refrigeration",
        "industrial",
        "commercial",
        "retail"
    ],
    "wof:name":"Norm McDonald Refrigeration",
    "wof:placetype":"venue"
},
  "geometry": {"coordinates":[150.486984253,-34.4026527405],"type":"Point"}
}