{
  "type": "Feature",
  "properties": {
    "iso:country":"AU",
    "sg:address":"Jane St",
    "sg:city":"West Croydon",
    "sg:classifiers":[
        {
            "category":"Education",
            "subcategory":"School",
            "type":"Public Place"
        }
    ],
    "sg:phone":"+61 8 8345 4138",
    "sg:postcode":"5008",
    "sg:province":"SA",
    "sg:tags":[
        "state",
        "except",
        "nsw"
    ],
    "wof:name":"Kilkenny Primary",
    "wof:placetype":"venue"
},
  "geometry": {"coordinates":[138.554382,-34.890869],"type":"Point"}
}