{
  "type": "Feature",
  "properties": {
    "addr:full":"844 Grand Junction Rd Gilles Plains SA 5086",
    "addr:housenumber":"844",
    "addr:postcode":"5086",
    "addr:street":"Grand Junction Rd",
    "iso:country":"AU",
    "sg:address":"844 Grand Junction Rd",
    "sg:city":"Gilles Plains",
    "sg:classifiers":[
        {
            "category":"Building & Trades",
            "subcategory":"Equipment Rental",
            "type":"Services"
        }
    ],
    "sg:phone":"+61 8 8261 6747",
    "sg:postcode":"5086",
    "sg:province":"SA",
    "sg:tags":[
        "renting",
        "trailer"
    ],
    "wof:name":"Caltex Gilles Plains",
    "wof:placetype":"venue"
},
  "geometry": {"coordinates":[138.65997314399999,-34.845741272],"type":"Point"}
}