{
  "type": "Feature",
  "properties": {
    "addr:full":"PO Box 275 Wangaratta VIC 3676",
    "addr:postcode":"3676",
    "iso:country":"AU",
    "sg:address":"PO Box 275",
    "sg:city":"Wangaratta",
    "sg:classifiers":[
        {
            "category":"Building & Trades",
            "subcategory":"Construction",
            "type":"Services"
        }
    ],
    "sg:phone":"+61 3 5722 3230",
    "sg:postcode":"3676",
    "sg:province":"VIC",
    "sg:tags":[
        "earth",
        "excavating",
        "moving",
        "contractor"
    ],
    "wof:name":"N & A Excavations",
    "wof:placetype":"venue"
},
  "geometry": {"coordinates":[146.32493600000001,-36.35371],"type":"Point"}
}