{
  "type": "Feature",
  "properties": {
    "iso:country":"AU",
    "sg:address":"Ground Floor/ 405 Parramatta Rd",
    "sg:city":"Leichhardt",
    "sg:classifiers":[
        {
            "category":"Personal",
            "subcategory":"Beauty Salon",
            "type":"Services"
        }
    ],
    "sg:phone":"+61 2 9568 4333",
    "sg:postcode":"2040",
    "sg:province":"NSW",
    "wof:name":"Ambience Faith Body & Beauty",
    "wof:placetype":"venue"
},
  "geometry": {"coordinates":[151.157196,-33.888115],"type":"Point"}
}