{
  "type": "Feature",
  "properties": {
    "addr:full":"6 Emperor St Tin Can Bay QLD 4580",
    "addr:housenumber":"6",
    "addr:postcode":"4580",
    "addr:street":"Emperor St",
    "iso:country":"AU",
    "sg:address":"6 Emperor St",
    "sg:city":"Tin Can Bay",
    "sg:classifiers":[
        {
            "category":"Autos & Motor Vehicles",
            "subcategory":"Boat Sales",
            "type":"Retail Goods"
        }
    ],
    "sg:phone":"+61 7 5488 0960",
    "sg:postcode":"4580",
    "sg:province":"QLD",
    "sg:tags":[
        "yacht"
    ],
    "wof:name":"Tin Can Bay Boat Sales",
    "wof:placetype":"venue"
},
  "geometry": {"coordinates":[153.008865356,-25.9062900543],"type":"Point"}
}