{
  "type": "Feature",
  "properties": {
    "addr:full":"PO Box 4064 Milton Business Centre QLD 4064",
    "addr:postcode":"4064",
    "addr:street":"Milton",
    "iso:country":"AU",
    "sg:address":"PO Box 4064",
    "sg:city":"Milton Business Centre",
    "sg:classifiers":[
        {
            "category":"Professional",
            "subcategory":"Business Services",
            "type":"Services"
        }
    ],
    "sg:phone":"+61 414 646 653",
    "sg:postcode":"4064",
    "sg:province":"QLD",
    "sg:tags":[
        "drafting"
    ],
    "wof:name":"Facade Design & Drafting",
    "wof:placetype":"venue"
},
  "geometry": {"coordinates":[153.00137329099999,-27.4699516296],"type":"Point"}
}