{
  "type": "Feature",
  "properties": {
    "addr:full":"20 Albatoss Rd Batemans Bay NSW 2536",
    "addr:housenumber":"20",
    "addr:postcode":"2536",
    "addr:street":"Albatoss Rd",
    "iso:country":"AU",
    "sg:address":"20 Albatoss Rd",
    "sg:city":"Batemans Bay",
    "sg:classifiers":[
        {
            "category":"Building & Trades",
            "subcategory":"Construction",
            "type":"Services"
        }
    ],
    "sg:phone":"+61 423 460 189",
    "sg:postcode":"2536",
    "sg:province":"NSW",
    "sg:tags":[
        "rendering",
        "cement"
    ],
    "wof:name":"Luke Robinson",
    "wof:placetype":"venue"
},
  "geometry": {"coordinates":[150.17971801799999,-35.7254676819],"type":"Point"}
}