{
  "type": "Feature",
  "properties": {
    "iso:country":"AU",
    "sg:address":"14 Lorimer St",
    "sg:city":"Greensborough",
    "sg:classifiers":[
        {
            "category":"Health Services",
            "subcategory":"Health Practitioner",
            "type":"Services"
        }
    ],
    "sg:phone":"+61 3 9434 4122",
    "sg:postcode":"3088",
    "sg:province":"VIC",
    "sg:tags":[
        "acupuncture"
    ],
    "wof:name":"Dr David Piekarski, Medical Practice Greensborough",
    "wof:placetype":"venue"
},
  "geometry": {"coordinates":[145.10049438499999,-37.7025527954],"type":"Point"}
}