{
  "type": "Feature",
  "properties": {
    "addr:full":"10 Aberdeen St Geelong VIC 3220",
    "addr:housenumber":"10",
    "addr:postcode":"3220",
    "addr:street":"Aberdeen St",
    "iso:country":"AU",
    "sg:address":"10 Aberdeen St",
    "sg:city":"Geelong",
    "sg:classifiers":[
        {
            "category":"Insurance",
            "subcategory":"Insurance Agent",
            "type":"Services"
        }
    ],
    "sg:phone":"+61 3 5229 6008",
    "sg:postcode":"3220",
    "sg:province":"VIC",
    "wof:name":"Waterhouse Walsh Kirtley & Associates",
    "wof:placetype":"venue"
},
  "geometry": {"coordinates":[144.351303,-38.147102],"type":"Point"}
}