{
  "type": "Feature",
  "properties": {
    "addr:full":"62 Pacific Ave Sunshine Beach QLD 4567",
    "addr:housenumber":"62",
    "addr:postcode":"4567",
    "addr:street":"Pacific Ave Sunshine",
    "iso:country":"AU",
    "sg:address":"62 Pacific Ave",
    "sg:city":"Sunshine Beach",
    "sg:classifiers":[
        {
            "category":"Travel",
            "subcategory":"Travel Agent",
            "type":"Entertainment"
        }
    ],
    "sg:phone":"+61 7 5448 0017",
    "sg:postcode":"4567",
    "sg:province":"QLD",
    "sg:tags":[
        "tour",
        "holiday",
        "adventure"
    ],
    "wof:name":"Backpacker Tours Australia",
    "wof:placetype":"venue"
},
  "geometry": {"coordinates":[153.105392456,-26.4042263031],"type":"Point"}
}