{
  "type": "Feature",
  "properties": {
    "addr:full":"Shp4/ 120 Rawson Rd Greenacre NSW 2190",
    "addr:housenumber":"120",
    "addr:postcode":"2190",
    "addr:street":"Rawson Rd",
    "iso:country":"AU",
    "sg:address":"Shp4/ 120 Rawson Rd",
    "sg:city":"Greenacre",
    "sg:classifiers":[
        {
            "category":"Cafe",
            "type":"Food & Drink"
        }
    ],
    "sg:phone":"+61 2 9791 1508",
    "sg:postcode":"2190",
    "sg:province":"NSW",
    "wof:name":"Cafe Delisino & Takeaway",
    "wof:placetype":"venue"
},
  "geometry": {"coordinates":[151.05267334000001,-33.9019012451],"type":"Point"}
}