{
  "type": "Feature",
  "properties": {
    "addr:full":"64 Jolimont St Sherwood QLD 4075",
    "addr:housenumber":"64",
    "addr:postcode":"4075",
    "addr:street":"Jolimont St",
    "iso:country":"AU",
    "sg:address":"64 Jolimont St",
    "sg:city":"Sherwood",
    "sg:classifiers":[
        {
            "category":"Building & Trades",
            "subcategory":"Construction",
            "type":"Services"
        }
    ],
    "sg:phone":"+61 7 3379 8511",
    "sg:postcode":"4075",
    "sg:province":"QLD",
    "sg:tags":[
        "contractor"
    ],
    "wof:name":"Straight Edge Constructions Pty Ltd",
    "wof:placetype":"venue"
},
  "geometry": {"coordinates":[152.97547912600001,-27.5334644318],"type":"Point"}
}