{
  "type": "Feature",
  "properties": {
    "addr:full":"40 Barree St Narara NSW 2250",
    "addr:housenumber":"40",
    "addr:postcode":"2250",
    "addr:street":"Barree St",
    "iso:country":"AU",
    "sg:address":"40 Barree St",
    "sg:city":"Narara",
    "sg:classifiers":[
        {
            "category":"Building & Trades",
            "subcategory":"Construction",
            "type":"Services"
        }
    ],
    "sg:phone":"+61 2 4329 0497",
    "sg:postcode":"2250",
    "sg:province":"NSW",
    "sg:tags":[
        "joiner",
        "carpenter"
    ],
    "wof:name":"Ben Duncan Carpentry Services",
    "wof:placetype":"venue"
},
  "geometry": {"coordinates":[151.352493286,-33.3932571411],"type":"Point"}
}