{
  "type": "Feature",
  "properties": {
    "iso:country":"AU",
    "sg:address":"125 McKenzie St",
    "sg:city":"Dayboro",
    "sg:classifiers":[
        {
            "category":"Retail",
            "subcategory":"Veterinary Services",
            "type":"Services"
        }
    ],
    "sg:phone":"+61 7 3425 1544",
    "sg:postcode":"4521",
    "sg:province":"QLD",
    "sg:tags":[
        "surgeon"
    ],
    "wof:name":"Dayboro Veterinary Surgery",
    "wof:placetype":"venue"
},
  "geometry": {"coordinates":[152.812637,-27.190641],"type":"Point"}
}