{
  "type": "Feature",
  "properties": {
    "iso:country":"AU",
    "sg:address":"PO Box 1266",
    "sg:city":"Maroubra",
    "sg:classifiers":[
        {
            "category":"Building & Trades",
            "subcategory":"Landscaping Services",
            "type":"Services"
        }
    ],
    "sg:phone":"+61 404 858 839",
    "sg:postcode":"2035",
    "sg:province":"NSW",
    "sg:tags":[
        "designer",
        "landscape",
        "contractor"
    ],
    "wof:name":"Sydney Garden Landscapes",
    "wof:placetype":"venue"
},
  "geometry": {"coordinates":[151.23866272000001,-33.9415092468],"type":"Point"}
}