{
  "type": "Feature",
  "properties": {
    "iso:country":"AU",
    "sg:address":"469 Hommond Rd",
    "sg:city":"Dandenong",
    "sg:classifiers":[
        {
            "category":"Home & Garden",
            "subcategory":"Hardware",
            "type":"Retail Goods"
        }
    ],
    "sg:phone":"+61 3 9768 3555",
    "sg:postcode":"3175",
    "sg:province":"VIC",
    "sg:tags":[
        "nut",
        "bolt"
    ],
    "wof:name":"Hobson Engineering Co Pty Ltd",
    "wof:placetype":"venue"
},
  "geometry": {"coordinates":[145.202835083,-38.0290374756],"type":"Point"}
}