{
  "type": "Feature",
  "properties": {
    "iso:country":"AU",
    "sg:address":"Manilla Rd",
    "sg:city":"Boggabri",
    "sg:classifiers":[
        {
            "category":"Arena",
            "subcategory":"Sports Club",
            "type":"Entertainment"
        }
    ],
    "sg:phone":"+61 2 6743 4694",
    "sg:postcode":"2382",
    "sg:province":"NSW",
    "sg:tags":[
        "hunt",
        "racing"
    ],
    "wof:name":"Wean Amateur Picnic Race Club",
    "wof:placetype":"venue"
},
  "geometry": {"coordinates":[150.04176330600001,-30.7106208801],"type":"Point"}
}