{
  "type": "Feature",
  "properties": {
    "addr:full":"105 Hanson Rd Gladstone QLD 4680",
    "addr:housenumber":"105",
    "addr:postcode":"4680",
    "addr:street":"Hanson Rd",
    "iso:country":"AU",
    "sg:address":"105 Hanson Rd",
    "sg:city":"Gladstone",
    "sg:classifiers":[
        {
            "category":"Building & Trades",
            "subcategory":"Equipment Rental",
            "type":"Services"
        }
    ],
    "sg:phone":"+61 7 4972 2933",
    "sg:postcode":"4680",
    "sg:province":"QLD",
    "sg:tags":[
        "platform",
        "hire",
        "work",
        "elevating"
    ],
    "wof:name":"E. & B. Access Hire",
    "wof:placetype":"venue"
},
  "geometry": {"coordinates":[151.23973083499999,-23.8418388367],"type":"Point"}
}