{
  "type": "Feature",
  "properties": {
    "addr:full":"63 Police Rd Mulgrave VIC 3170",
    "addr:housenumber":"63",
    "addr:postcode":"3170",
    "addr:street":"Police Rd",
    "iso:country":"AU",
    "sg:address":"63 Police Rd",
    "sg:city":"Mulgrave",
    "sg:classifiers":[
        {
            "category":"Health Services",
            "subcategory":"Dentist",
            "type":"Services"
        }
    ],
    "sg:phone":"+61 3 9547 9456",
    "sg:postcode":"3170",
    "sg:province":"VIC",
    "wof:name":"Ong Dr J H & Ong Dr Daphne",
    "wof:placetype":"venue"
},
  "geometry": {"coordinates":[145.164154053,-37.9338684082],"type":"Point"}
}