{
  "type": "Feature",
  "properties": {
    "iso:country":"AU",
    "sg:address":"740 Heidelburg Rd",
    "sg:city":"Alphington",
    "sg:classifiers":[
        {
            "category":"Shopping",
            "subcategory":"Antiques",
            "type":"Retail Goods"
        }
    ],
    "sg:phone":"+61 418 552 553",
    "sg:postcode":"3078",
    "sg:province":"VIC",
    "wof:name":"Heidelberg Road Antiques and Collectables Centre",
    "wof:placetype":"venue"
},
  "geometry": {"coordinates":[145.03138732900001,-37.7808456421],"type":"Point"}
}