{
  "type": "Feature",
  "properties": {
    "addr:full":"Head Office: 728 - 734 Old Princes Hwy Sutherland NSW 2232",
    "addr:housenumber":"728 734",
    "addr:postcode":"2232",
    "addr:street":"Old Princes Hwy",
    "iso:country":"AU",
    "sg:address":"Head Office: 728 - 734 Old Princes Hwy",
    "sg:city":"Sutherland",
    "sg:classifiers":[
        {
            "category":"Banks & Credit Unions",
            "subcategory":"Financial Services",
            "type":"Services"
        }
    ],
    "sg:phone":"+61 1800 818 544",
    "sg:postcode":"2232",
    "sg:province":"NSW",
    "sg:tags":[
        "loan",
        "finance",
        "mortgage"
    ],
    "wof:name":"Better Choice Home Loans",
    "wof:placetype":"venue"
},
  "geometry": {"coordinates":[151.05857849099999,-34.0307312012],"type":"Point"}
}