{
  "type": "Feature",
  "properties": {
    "addr:full":"9 Lauderdale St East West Hoxton NSW 2171",
    "addr:housenumber":"9",
    "addr:postcode":"2171",
    "addr:street":"Lauderdale St East West",
    "iso:country":"AU",
    "sg:address":"9 Lauderdale St East",
    "sg:city":"West Hoxton",
    "sg:classifiers":[
        {
            "category":"Communications",
            "type":"Services"
        }
    ],
    "sg:phone":"+61 2 9826 6888",
    "sg:postcode":"2171",
    "sg:province":"NSW",
    "sg:tags":[
        "translation"
    ],
    "wof:name":"Interpreters Connection",
    "wof:placetype":"venue"
},
  "geometry": {"coordinates":[150.846633911,-33.9268913269],"type":"Point"}
}