{
  "type": "Feature",
  "properties": {
    "iso:country":"AU",
    "sg:address":"PO Box 112",
    "sg:city":"Ararat",
    "sg:classifiers":[
        {
            "category":"Organizations",
            "subcategory":"Non-profit Organization",
            "type":"Services"
        }
    ],
    "sg:phone":"+61 3 5352 2722",
    "sg:postcode":"3377",
    "sg:province":"VIC",
    "sg:tags":[
        "support",
        "disability",
        "organisation"
    ],
    "wof:name":"Grampians Disability Advocacy",
    "wof:placetype":"venue"
},
  "geometry": {"coordinates":[142.93130493199999,-37.2824211121],"type":"Point"}
}