{
  "type": "Feature",
  "properties": {
    "addr:full":"PO Box 3057 Rouse Hill NSW 2155",
    "addr:postcode":"2155",
    "iso:country":"AU",
    "sg:address":"PO Box 3057",
    "sg:city":"Rouse Hill",
    "sg:classifiers":[
        {
            "category":"Shopping",
            "subcategory":"Optical Goods",
            "type":"Retail Goods"
        }
    ],
    "sg:phone":"+61 2 9629 5216",
    "sg:postcode":"2155",
    "sg:province":"NSW",
    "sg:tags":[
        "supply"
    ],
    "wof:name":"Medmont Pty Ltd",
    "wof:placetype":"venue"
},
  "geometry": {"coordinates":[150.92202758799999,-33.6771697998],"type":"Point"}
}