{
  "type": "Feature",
  "properties": {
    "iso:country":"AU",
    "sg:address":"82 King Rd",
    "sg:city":"Bunbury",
    "sg:classifiers":[
        {
            "category":"Retail",
            "subcategory":"Auto Repair",
            "type":"Services"
        }
    ],
    "sg:phone":"+61 8 9721 3133",
    "sg:postcode":"6230",
    "sg:province":"WA",
    "sg:tags":[
        "repairer",
        "motor",
        "engineer"
    ],
    "wof:name":"Williams Shane Auto Repairs",
    "wof:placetype":"venue"
},
  "geometry": {"coordinates":[115.65435,-33.3382],"type":"Point"}
}