{
  "type": "Feature",
  "properties": {
    "addr:full":"Irish Mulga Rd Kambalda WA 6442",
    "addr:postcode":"6442",
    "addr:street":"Mulga Rd",
    "iso:country":"AU",
    "sg:address":"Irish Mulga Rd",
    "sg:city":"Kambalda",
    "sg:classifiers":[
        {
            "category":"Utilities",
            "subcategory":"Electric",
            "type":"Services"
        }
    ],
    "sg:phone":"+61 8 9027 1357",
    "sg:postcode":"6442",
    "sg:province":"WA",
    "sg:tags":[
        "electrical",
        "contractor"
    ],
    "wof:name":"C.T. Electrical Contractors (W.A.) Pty Ltd",
    "wof:placetype":"venue"
},
  "geometry": {"coordinates":[121.62213897700001,-31.2093429565],"type":"Point"}
}