{
  "type": "Feature",
  "properties": {
    "iso:country":"AU",
    "sg:address":"385- 393 Lower Dandenong Rd",
    "sg:city":"Dingley",
    "sg:classifiers":[
        {
            "category":"Banks & Credit Unions",
            "subcategory":"Financial Services",
            "type":"Services"
        }
    ],
    "sg:phone":"+61 3 9551 5566",
    "sg:postcode":"3172",
    "sg:province":"VIC",
    "sg:tags":[
        "wholesaler",
        "mfrs",
        "gear"
    ],
    "wof:name":"Hardman Bros. Pty Ltd",
    "wof:placetype":"venue"
},
  "geometry": {"coordinates":[145.11326599099999,-37.986656189],"type":"Point"}
}