{
  "type": "Feature",
  "properties": {
    "iso:country":"AU",
    "sg:address":"305 Bay St",
    "sg:city":"Brighton-le-Sands",
    "sg:classifiers":[
        {
            "category":"Health Services",
            "subcategory":"Optometrist",
            "type":"Services"
        }
    ],
    "sg:phone":"+61 2 9597 7030",
    "sg:postcode":"2216",
    "sg:province":"NSW",
    "wof:name":"Brighton Optometrist",
    "wof:placetype":"venue"
},
  "geometry": {"coordinates":[151.153976,-33.960056],"type":"Point"}
}