{
  "type": "Feature",
  "properties": {
    "addr:full":"105 George St Kalbar QLD 4309",
    "addr:housenumber":"105",
    "addr:postcode":"4309",
    "addr:street":"George St",
    "iso:country":"AU",
    "sg:address":"105 George St",
    "sg:city":"Kalbar",
    "sg:classifiers":[
        {
            "category":"Banks & Credit Unions",
            "subcategory":"Investment Brokerage",
            "type":"Services"
        }
    ],
    "sg:phone":"+61 7 5463 7555",
    "sg:postcode":"4309",
    "sg:province":"QLD",
    "sg:tags":[
        "management",
        "property"
    ],
    "wof:name":"Kalbar Real Estate",
    "wof:placetype":"venue"
},
  "geometry": {"coordinates":[152.62478637699999,-27.9344444275],"type":"Point"}
}