{
  "type": "Feature",
  "properties": {
    "addr:full":"PO Box 175 Cooma NSW 2630",
    "addr:postcode":"2630",
    "iso:country":"AU",
    "sg:address":"PO Box 175",
    "sg:city":"Cooma",
    "sg:classifiers":[
        {
            "category":"Health Services",
            "subcategory":"Doctor",
            "type":"Services"
        }
    ],
    "sg:phone":"+61 2 6456 7343",
    "sg:postcode":"2630",
    "sg:province":"NSW",
    "sg:tags":[
        "medical",
        "practitioner"
    ],
    "wof:name":"Tahmindjis Alex Dr",
    "wof:placetype":"venue"
},
  "geometry": {"coordinates":[149.13154602,-36.2323493958],"type":"Point"}
}