{
  "type": "Feature",
  "properties": {
    "iso:country":"AU",
    "sg:address":"10 Shuter Drv",
    "sg:city":"Moonee Ponds",
    "sg:classifiers":[
        {
            "category":"Health Services",
            "subcategory":"Doctor",
            "type":"Services"
        }
    ],
    "sg:phone":"+61 3 9370 7634",
    "sg:postcode":"3039",
    "sg:province":"VIC",
    "sg:tags":[
        "medical",
        "practitioner"
    ],
    "wof:name":"Poulier Hylton Dr",
    "wof:placetype":"venue"
},
  "geometry": {"coordinates":[144.920807,-37.767941],"type":"Point"}
}