{
  "type": "Feature",
  "properties": {
    "addr:full":"241 South St Marsden Park NSW 2765",
    "addr:housenumber":"241",
    "addr:postcode":"2765",
    "addr:street":"South St",
    "iso:country":"AU",
    "sg:address":"241 South St",
    "sg:city":"Marsden Park",
    "sg:classifiers":[
        {
            "category":"Building & Trades",
            "subcategory":"Landscaping Services",
            "type":"Services"
        }
    ],
    "sg:phone":"+61 2 9628 4448",
    "sg:postcode":"2765",
    "sg:province":"NSW",
    "sg:tags":[
        "horticultural",
        "consultant"
    ],
    "wof:name":"Sydney Wildflower Nursery West",
    "wof:placetype":"venue"
},
  "geometry": {"coordinates":[150.82406616200001,-33.7102050781],"type":"Point"}
}