{
  "type": "Feature",
  "properties": {
    "addr:full":"Shop 68 Munno Para Shopping City 600 Main North Rd Smithfield SA 5114",
    "addr:housenumber":"shop 68;600",
    "addr:postcode":"5114",
    "addr:street":"Main North Rd",
    "iso:country":"AU",
    "sg:address":"Shop 68 Munno Para Shopping City 600 Main North Rd",
    "sg:city":"Smithfield",
    "sg:classifiers":[
        {
            "category":"Shopping",
            "subcategory":"Pets & Pet Supplies",
            "type":"Retail Goods"
        }
    ],
    "sg:phone":"+61 8 8254 1123",
    "sg:postcode":"5114",
    "sg:province":"SA",
    "sg:tags":[
        "food"
    ],
    "wof:name":"Pops Pets",
    "wof:placetype":"venue"
},
  "geometry": {"coordinates":[138.67274475100001,-34.71641922],"type":"Point"}
}