{
  "type": "Feature",
  "properties": {
    "iso:country":"AU",
    "sg:address":"15 Queen St",
    "sg:city":"Perth",
    "sg:classifiers":[
        {
            "category":"Travel",
            "subcategory":"Travel Agent",
            "type":"Entertainment"
        }
    ],
    "sg:phone":"+61 8 9321 2288",
    "sg:postcode":"6000",
    "sg:province":"WA",
    "sg:tags":[
        "consultant"
    ],
    "wof:name":"Kings Tours & Travel",
    "wof:placetype":"venue"
},
  "geometry": {"coordinates":[115.856483459,-31.9516830444],"type":"Point"}
}