{
  "type": "Feature",
  "properties": {
    "addr:full":"Reef Marina Mackay Harbour QLD 4740",
    "addr:postcode":"4740",
    "iso:country":"AU",
    "sg:address":"Reef Marina",
    "sg:city":"Mackay Harbour",
    "sg:classifiers":[
        {
            "category":"Restaurant",
            "type":"Food & Drink"
        }
    ],
    "sg:phone":"+61 7 4955 5022",
    "sg:postcode":"4740",
    "sg:province":"QLD",
    "sg:website":"http://www.lighthousemarina.com.au",
    "wof:name":"Lighthouse Seafood Restaurant",
    "wof:placetype":"venue"
},
  "geometry": {"coordinates":[149.203857,-21.11508],"type":"Point"}
}