{
  "type": "Feature",
  "properties": {
    "addr:full":"18 Douglas Mcinnes Drv Laidley QLD 4341",
    "addr:housenumber":"18",
    "addr:postcode":"4341",
    "addr:street":"Douglas Mcinnes Drv",
    "iso:country":"AU",
    "sg:address":"18 Douglas Mcinnes Drv",
    "sg:city":"Laidley",
    "sg:classifiers":[
        {
            "category":"Retail",
            "subcategory":"Repair Shop",
            "type":"Services"
        }
    ],
    "sg:phone":"+61 7 5465 1610",
    "sg:postcode":"4341",
    "sg:province":"QLD",
    "sg:tags":[
        "stove",
        "part",
        "range"
    ],
    "wof:name":"Flanagan's Electrical",
    "wof:placetype":"venue"
},
  "geometry": {"coordinates":[152.40980529800001,-27.6406898499],"type":"Point"}
}