{
  "type": "Feature",
  "properties": {
    "addr:full":"119b New Canterbury Rd Petersham NSW 2049",
    "addr:housenumber":"119b",
    "addr:postcode":"2049",
    "addr:street":"New Canterbury Rd",
    "iso:country":"AU",
    "sg:address":"119b New Canterbury Rd",
    "sg:city":"Petersham",
    "sg:classifiers":[
        {
            "category":"Health Services",
            "subcategory":"Health Practitioner",
            "type":"Services"
        }
    ],
    "sg:phone":"+61 2 9572 8566",
    "sg:postcode":"2049",
    "sg:province":"NSW",
    "sg:tags":[
        "physiotherapist"
    ],
    "wof:name":"Petersham Physiotherapy",
    "wof:placetype":"venue"
},
  "geometry": {"coordinates":[151.15226699999999,-33.896812],"type":"Point"}
}