{
  "type": "Feature",
  "properties": {
    "addr:full":"Unit 12A / 1 Campbell Pde Manly Vale NSW 2093",
    "addr:housenumber":"unit 12a / 1",
    "addr:postcode":"2093",
    "addr:street":"Campbell Pde",
    "iso:country":"AU",
    "sg:address":"Unit 12A / 1 Campbell Pde",
    "sg:city":"Manly Vale",
    "sg:classifiers":[
        {
            "category":"Home & Garden",
            "subcategory":"Household Appliances",
            "type":"Retail Goods"
        }
    ],
    "sg:phone":"+61 2 9907 6155",
    "sg:postcode":"2093",
    "sg:province":"NSW",
    "sg:tags":[
        "heating",
        "system"
    ],
    "wof:name":"Total Climate Control",
    "wof:placetype":"venue"
},
  "geometry": {"coordinates":[151.27116394000001,-33.7813301086],"type":"Point"}
}