{
  "type": "Feature",
  "properties": {
    "addr:full":"1- 31 Murradoc Rd Drysdale VIC 3222",
    "addr:housenumber":"31",
    "addr:postcode":"3222",
    "addr:street":"1;Murradoc Rd",
    "iso:country":"AU",
    "sg:address":"1- 31 Murradoc Rd",
    "sg:city":"Drysdale",
    "sg:classifiers":[
        {
            "category":"Structure",
            "subcategory":"Bridge",
            "type":"Public Place"
        }
    ],
    "sg:phone":"+61 3 5253 1608",
    "sg:postcode":"3222",
    "sg:province":"VIC",
    "sg:tags":[
        "chainsaw",
        "brushcutters"
    ],
    "wof:name":"Drysdale Mowers",
    "wof:placetype":"venue"
},
  "geometry": {"coordinates":[144.573013,-38.173065],"type":"Point"}
}