{
  "type": "Feature",
  "properties": {
    "addr:full":"1- 9 Blundell Blv Tweed Heads South NSW 2486",
    "addr:housenumber":"9",
    "addr:postcode":"2486",
    "addr:street":"Blundell Blv",
    "iso:country":"AU",
    "sg:address":"1- 9",
    "sg:city":"Blundell Blv Tweed Heads South",
    "sg:classifiers":[
        {
            "category":"Social Services",
            "subcategory":"Retirement Home",
            "type":"Services"
        }
    ],
    "sg:phone":"+61 7 5524 4519",
    "sg:postcode":"2486",
    "sg:province":"NSW",
    "sg:tags":[
        "village"
    ],
    "wof:name":"Southern Cross St Josephs Villas",
    "wof:placetype":"venue"
},
  "geometry": {"coordinates":[153.54200744600001,-28.1995735168],"type":"Point"}
}