{
  "type": "Feature",
  "properties": {
    "iso:country":"AU",
    "sg:address":"Unit 4/ 25a Powers Rd",
    "sg:city":"Seven Hills",
    "sg:classifiers":[
        {
            "category":"Retail",
            "subcategory":"Auto Repair",
            "type":"Services"
        }
    ],
    "sg:phone":"+61 2 9674 3132",
    "sg:postcode":"2147",
    "sg:province":"NSW",
    "sg:tags":[
        "beater",
        "painter",
        "panel"
    ],
    "wof:name":"Asia Smash Repairs",
    "wof:placetype":"venue"
},
  "geometry": {"coordinates":[150.94493102999999,-33.7737884521],"type":"Point"}
}