{
  "type": "Feature",
  "properties": {
    "addr:full":"Unit 2/ 122- 134 Boundary Rd Braeside VIC 3195",
    "addr:housenumber":"/ 122 134",
    "addr:postcode":"3195",
    "addr:street":"Boundary Rd",
    "iso:country":"AU",
    "sg:address":"Unit 2/ 122- 134 Boundary Rd",
    "sg:city":"Braeside",
    "sg:classifiers":[
        {
            "category":"Building & Trades",
            "subcategory":"Construction",
            "type":"Services"
        }
    ],
    "sg:phone":"+61 3 9587 5800",
    "sg:postcode":"3195",
    "sg:province":"VIC",
    "sg:tags":[
        "roof"
    ],
    "wof:name":"Barden-Steeldeck Industries Pty Ltd",
    "wof:placetype":"venue"
},
  "geometry": {"coordinates":[145.10551452600001,-38.0009880066],"type":"Point"}
}