{
  "type": "Feature",
  "properties": {
    "addr:full":"14/31 Burnett St St Kilda VIC 3182",
    "addr:housenumber":"14 / 31",
    "addr:postcode":"3182",
    "addr:street":"Burnett St",
    "iso:country":"AU",
    "sg:address":"14/31 Burnett St St",
    "sg:city":"Kilda",
    "sg:classifiers":[
        {
            "category":"Professional",
            "subcategory":"Art Services",
            "type":"Services"
        }
    ],
    "sg:phone":"+61 414 555 659",
    "sg:postcode":"3182",
    "sg:province":"VIC",
    "sg:tags":[
        "interior",
        "decorator"
    ],
    "wof:name":"KRAKUSS Painting Service",
    "wof:placetype":"venue"
},
  "geometry": {"coordinates":[144.98184204099999,-37.8602790833],"type":"Point"}
}