{
  "type": "Feature",
  "properties": {
    "iso:country":"AU",
    "sg:address":"106 Frenchs Forest Rd",
    "sg:city":"Frenchs Forest",
    "sg:classifiers":[
        {
            "category":"Travel",
            "subcategory":"Travel Agent",
            "type":"Entertainment"
        }
    ],
    "sg:phone":"+61 2 9452 2344",
    "sg:postcode":"2086",
    "sg:province":"NSW",
    "sg:tags":[
        "consultant"
    ],
    "wof:name":"New Zealand Leisure Tours",
    "wof:placetype":"venue"
},
  "geometry": {"coordinates":[151.234375,-33.7496948242],"type":"Point"}
}