{
  "type": "Feature",
  "properties": {
    "addr:full":"98 George St Morwell VIC 3840",
    "addr:housenumber":"98",
    "addr:postcode":"3840",
    "addr:street":"George St",
    "iso:country":"AU",
    "sg:address":"98 George St",
    "sg:city":"Morwell",
    "sg:classifiers":[
        {
            "category":"Food & Beverages",
            "subcategory":"Liquor & Beverages",
            "type":"Retail Goods"
        }
    ],
    "sg:phone":"+61 3 5133 0544",
    "sg:postcode":"3840",
    "sg:province":"VIC",
    "sg:tags":[
        "store"
    ],
    "wof:name":"Liquorland Pty Ltd",
    "wof:placetype":"venue"
},
  "geometry": {"coordinates":[146.398193359,-38.2387161255],"type":"Point"}
}