{
  "type": "Feature",
  "properties": {
    "addr:full":"390 Pound Rd Narre Warren VIC 3805",
    "addr:housenumber":"390",
    "addr:postcode":"3805",
    "addr:street":"Pound Rd",
    "iso:country":"AU",
    "sg:address":"390 Pound Rd",
    "sg:city":"Narre Warren",
    "sg:classifiers":[
        {
            "category":"Manufacturing",
            "subcategory":"Motor Vehicles & Parts",
            "type":"Manufacturing & Wholesale Goods"
        }
    ],
    "sg:phone":"+61 3 8790 5942",
    "sg:postcode":"3805",
    "sg:province":"VIC",
    "sg:tags":[
        "replacement"
    ],
    "wof:name":"Chevrolet The Engine Centre",
    "wof:placetype":"venue"
},
  "geometry": {"coordinates":[145.287384,-38.036537],"type":"Point"}
}