{
  "type": "Feature",
  "properties": {
    "iso:country":"AU",
    "sg:address":"9 Crinoline St",
    "sg:city":"Orange",
    "sg:classifiers":[
        {
            "category":"Travel",
            "subcategory":"Hotels & Motels",
            "type":"Entertainment"
        }
    ],
    "sg:phone":"+61 2 6362 5729",
    "sg:postcode":"2800",
    "sg:province":"NSW",
    "wof:name":"Cleveland Bed & Breakfast",
    "wof:placetype":"venue"
},
  "geometry": {"coordinates":[149.10301208499999,-33.2662467957],"type":"Point"}
}