{
  "type": "Feature",
  "properties": {
    "addr:full":"GPO Box 2220 Canberra ACT 2601",
    "addr:postcode":"2601",
    "iso:country":"AU",
    "sg:address":"GPO Box 2220",
    "sg:city":"Canberra",
    "sg:classifiers":[
        {
            "category":"Personal",
            "type":"Services"
        }
    ],
    "sg:phone":"+61 2 6238 0836",
    "sg:postcode":"2601",
    "sg:province":"ACT",
    "sg:tags":[
        "career",
        "counselling"
    ],
    "wof:name":"Capital Coaching",
    "wof:placetype":"venue"
},
  "geometry": {"coordinates":[149.111816406,-35.2768592834],"type":"Point"}
}