{
  "type": "Feature",
  "properties": {
    "addr:full":"248 Seaford Rd Seaford VIC 3198",
    "addr:housenumber":"248",
    "addr:postcode":"3198",
    "addr:street":"Seaford Rd",
    "iso:country":"AU",
    "sg:address":"248 Seaford Rd",
    "sg:city":"Seaford",
    "sg:classifiers":[
        {
            "category":"Retail",
            "subcategory":"Veterinary Services",
            "type":"Services"
        }
    ],
    "sg:phone":"+61 3 9785 2611",
    "sg:postcode":"3198",
    "sg:province":"VIC",
    "sg:tags":[
        "surgeon"
    ],
    "wof:name":"Dr Paul Ross & Associates",
    "wof:placetype":"venue"
},
  "geometry": {"coordinates":[145.153442383,-38.1120376587],"type":"Point"}
}