{
  "type": "Feature",
  "properties": {
    "iso:country":"AU",
    "sg:address":"1/ 12 Baroona Rd",
    "sg:city":"Milton",
    "sg:classifiers":[
        {
            "category":"Food & Beverages",
            "subcategory":"Bakery",
            "type":"Retail Goods"
        }
    ],
    "sg:phone":"+61 7 3369 4528",
    "sg:postcode":"4064",
    "sg:province":"QLD",
    "sg:tags":[
        "baker"
    ],
    "wof:name":"BRED your bakery",
    "wof:placetype":"venue"
},
  "geometry": {"coordinates":[153.002883911,-27.4686489105],"type":"Point"}
}