{
  "type": "Feature",
  "properties": {
    "addr:full":"213 Barrington St Bibra Lake WA 6163",
    "addr:housenumber":"213",
    "addr:postcode":"6163",
    "addr:street":"Barrington St",
    "iso:country":"AU",
    "sg:address":"213 Barrington St",
    "sg:city":"Bibra Lake",
    "sg:classifiers":[
        {
            "category":"Wholesale",
            "subcategory":"Machinery & Supplies",
            "type":"Manufacturing & Wholesale Goods"
        }
    ],
    "sg:phone":"+61 8 9494 1004",
    "sg:postcode":"6163",
    "sg:province":"WA",
    "sg:tags":[
        "instrument"
    ],
    "wof:name":"Fusion Piping Systems",
    "wof:placetype":"venue"
},
  "geometry": {"coordinates":[115.81147799999999,-32.116741],"type":"Point"}
}