{
  "type": "Feature",
  "properties": {
    "iso:country":"AU",
    "sg:address":"Lvl 1, 385 Port Hacking Rd",
    "sg:city":"Caringbah",
    "sg:classifiers":[
        {
            "category":"Banks & Credit Unions",
            "subcategory":"Financial Services",
            "type":"Services"
        }
    ],
    "sg:phone":"+61 2 9531 2344",
    "sg:postcode":"2229",
    "sg:province":"NSW",
    "sg:tags":[
        "planning"
    ],
    "wof:name":"Count Wealth Accountants",
    "wof:placetype":"venue"
},
  "geometry": {"coordinates":[151.12306213400001,-34.0452804565],"type":"Point"}
}