{
  "type": "Feature",
  "properties": {
    "addr:full":"173 Parramatta Rd Annandale NSW 2038",
    "addr:housenumber":"173",
    "addr:postcode":"2038",
    "addr:street":"Parramatta Rd",
    "iso:country":"AU",
    "sg:address":"173 Parramatta Rd",
    "sg:city":"Annandale",
    "sg:classifiers":[
        {
            "category":"Personal",
            "type":"Services"
        }
    ],
    "sg:phone":"+61 2 9569 8101",
    "sg:postcode":"2038",
    "sg:province":"NSW",
    "sg:tags":[
        "gift"
    ],
    "wof:name":"Balloons.net.au",
    "wof:placetype":"venue"
},
  "geometry": {"coordinates":[151.165252686,-33.8879890442],"type":"Point"}
}