{
  "type": "Feature",
  "properties": {
    "iso:country":"AU",
    "sg:address":"330 Murray St",
    "sg:city":"Colac",
    "sg:classifiers":[
        {
            "category":"Retail",
            "subcategory":"Veterinary Services",
            "type":"Services"
        }
    ],
    "sg:phone":"+61 3 5231 3375",
    "sg:postcode":"3250",
    "sg:province":"VIC",
    "sg:tags":[
        "surgeon"
    ],
    "wof:name":"Murray Street Veterinary Clinic & Hospital",
    "wof:placetype":"venue"
},
  "geometry": {"coordinates":[143.586914,-38.339806],"type":"Point"}
}