{
  "type": "Feature",
  "properties": {
    "addr:full":"16 Reef St Gympie QLD 4570",
    "addr:housenumber":"16",
    "addr:postcode":"4570",
    "addr:street":"Reef St",
    "iso:country":"AU",
    "sg:address":"16 Reef St",
    "sg:city":"Gympie",
    "sg:classifiers":[
        {
            "category":"Home & Garden",
            "subcategory":"Carpets & Floor Coverings",
            "type":"Retail Goods"
        }
    ],
    "sg:phone":"+61 7 5483 9077",
    "sg:postcode":"4570",
    "sg:province":"QLD",
    "sg:tags":[
        "tile",
        "wall"
    ],
    "sg:website":"http://www.cooloolatiles.com.au",
    "wof:name":"Cooloola Tile Company",
    "wof:placetype":"venue"
},
  "geometry": {"coordinates":[152.659225464,-26.1896076202],"type":"Point"}
}