{
  "type": "Feature",
  "properties": {
    "addr:full":"156 Thompson Ave Cowes VIC 3922",
    "addr:housenumber":"156",
    "addr:postcode":"3922",
    "addr:street":"Thompson Ave",
    "iso:country":"AU",
    "sg:address":"156 Thompson Ave",
    "sg:city":"Cowes",
    "sg:classifiers":[
        {
            "category":"Building & Trades",
            "subcategory":"Construction",
            "type":"Services"
        }
    ],
    "sg:phone":"+61 3 5952 3966",
    "sg:postcode":"3922",
    "sg:province":"VIC",
    "sg:tags":[
        "contractor"
    ],
    "wof:name":"Leisure Style Builders",
    "wof:placetype":"venue"
},
  "geometry": {"coordinates":[145.238815308,-38.455821991],"type":"Point"}
}