{
  "type": "Feature",
  "properties": {
    "addr:full":"222 Learoyd Rd Acacia Ridge QLD 4110",
    "addr:housenumber":"222",
    "addr:postcode":"4110",
    "addr:street":"Learoyd Rd",
    "iso:country":"AU",
    "sg:address":"222 Learoyd Rd",
    "sg:city":"Acacia Ridge",
    "sg:classifiers":[
        {
            "category":"Building & Trades",
            "subcategory":"Cleaning & Sanitation",
            "type":"Services"
        }
    ],
    "sg:phone":"+61 7 3273 3417",
    "sg:postcode":"4110",
    "sg:province":"QLD",
    "sg:tags":[
        "asbestos",
        "treatment",
        "removal"
    ],
    "wof:name":"Asbestos We Can",
    "wof:placetype":"venue"
},
  "geometry": {"coordinates":[153.023269653,-27.5969867706],"type":"Point"}
}