{
  "type": "Feature",
  "properties": {
    "iso:country":"AU",
    "sg:address":"1st Floor, 141 Victoria Ave",
    "sg:city":"Albert Park",
    "sg:classifiers":[
        {
            "category":"Real Estate",
            "subcategory":"Architect",
            "type":"Services"
        }
    ],
    "sg:phone":"+61 3 9690 9661",
    "sg:postcode":"3206",
    "sg:province":"VIC",
    "sg:website":"http://www.metroworks.com.au",
    "wof:name":"Metroworks Architects Pty Ltd",
    "wof:placetype":"venue"
},
  "geometry": {"coordinates":[144.949905395,-37.8459663391],"type":"Point"}
}