{
  "type": "Feature",
  "properties": {
    "iso:country":"AU",
    "sg:address":"18 Captain Cook Drv",
    "sg:city":"Kurnell",
    "sg:classifiers":[
        {
            "category":"Personal",
            "subcategory":"Beauty Salon",
            "type":"Services"
        }
    ],
    "sg:phone":"+61 2 9668 9787",
    "sg:postcode":"2231",
    "sg:province":"NSW",
    "sg:tags":[
        "hairdresser"
    ],
    "wof:name":"Kurnell Topcuts",
    "wof:placetype":"venue"
},
  "geometry": {"coordinates":[151.21690368599999,-34.0090026855],"type":"Point"}
}