{
  "type": "Feature",
  "properties": {
    "iso:country":"AU",
    "sg:address":"Harbour St",
    "sg:city":"Wollongong",
    "sg:classifiers":[
        {
            "category":"Sports & Exercise",
            "subcategory":"Sports Center",
            "type":"Entertainment"
        }
    ],
    "sg:phone":"+61 2 4237 7496",
    "sg:postcode":"2500",
    "sg:province":"NSW",
    "sg:tags":[
        "coach",
        "tennis"
    ],
    "wof:name":"Parkers's Tennis Coaching",
    "wof:placetype":"venue"
},
  "geometry": {"coordinates":[150.902939,-34.423367],"type":"Point"}
}