{
  "type": "Feature",
  "properties": {
    "addr:full":"Cnr Florence & Abbott Sts Cairns QLD 4870",
    "addr:postcode":"4870",
    "addr:street":"Cnr",
    "iso:country":"AU",
    "sg:address":"Cnr Florence & Abbott Sts",
    "sg:city":"Cairns",
    "sg:classifiers":[
        {
            "category":"Retail",
            "subcategory":"Event Space",
            "type":"Services"
        }
    ],
    "sg:phone":"+61 7 4051 6188",
    "sg:postcode":"4870",
    "sg:province":"QLD",
    "sg:tags":[
        "venue",
        "reception",
        "wedding"
    ],
    "wof:name":"Country Comfort Outrigger Cairns",
    "wof:placetype":"venue"
},
  "geometry": {"coordinates":[145.76673889200001,-16.9236412048],"type":"Point"}
}