{
  "type": "Feature",
  "properties": {
    "iso:country":"AU",
    "sg:address":"138 Muir St",
    "sg:city":"Labrador",
    "sg:classifiers":[
        {
            "category":"Building & Trades",
            "subcategory":"Construction",
            "type":"Services"
        }
    ],
    "sg:phone":"+61 438 320 038",
    "sg:postcode":"4215",
    "sg:province":"QLD",
    "sg:tags":[
        "earth",
        "excavating",
        "moving",
        "contractor"
    ],
    "wof:name":"Limited Access",
    "wof:placetype":"venue"
},
  "geometry": {"coordinates":[153.40577697800001,-27.9464626312],"type":"Point"}
}