{
  "type": "Feature",
  "properties": {
    "addr:full":"77 Junction Rd Nunawading VIC 3131",
    "addr:housenumber":"77",
    "addr:postcode":"3131",
    "addr:street":"Junction Rd",
    "iso:country":"AU",
    "sg:address":"77 Junction Rd",
    "sg:city":"Nunawading",
    "sg:classifiers":[
        {
            "category":"Retail",
            "subcategory":"Veterinary Services",
            "type":"Services"
        }
    ],
    "sg:phone":"+61 3 9877 3527",
    "sg:postcode":"3131",
    "sg:province":"VIC",
    "sg:tags":[
        "surgeon"
    ],
    "wof:name":"Bob Bradley",
    "wof:placetype":"venue"
},
  "geometry": {"coordinates":[145.16848754899999,-37.8073692322],"type":"Point"}
}