{
  "type": "Feature",
  "properties": {
    "addr:full":"28 Bamfeild Rd Mt Evelyn VIC 3796",
    "addr:housenumber":"28",
    "addr:postcode":"3796",
    "addr:street":"Bamfeild Rd",
    "iso:country":"AU",
    "sg:address":"28 Bamfeild Rd",
    "sg:city":"Mt Evelyn",
    "sg:classifiers":[
        {
            "category":"Home & Garden",
            "subcategory":"Carpets & Floor Coverings",
            "type":"Retail Goods"
        }
    ],
    "sg:phone":"+61 3 9736 3535",
    "sg:postcode":"3796",
    "sg:province":"VIC",
    "sg:tags":[
        "tile",
        "wall",
        "layer"
    ],
    "wof:name":"Sherwood Slate & Tile Laying Services",
    "wof:placetype":"venue"
},
  "geometry": {"coordinates":[145.40834045400001,-37.7983818054],"type":"Point"}
}