{
  "type": "Feature",
  "properties": {
    "addr:full":"60 Marple Ave Villawood NSW 2163",
    "addr:housenumber":"60",
    "addr:postcode":"2163",
    "addr:street":"Marple Ave",
    "iso:country":"AU",
    "sg:address":"60 Marple Ave",
    "sg:city":"Villawood",
    "sg:classifiers":[
        {
            "category":"Retail",
            "subcategory":"Storage",
            "type":"Services"
        }
    ],
    "sg:phone":"+61 2 8717 1090",
    "sg:postcode":"2163",
    "sg:province":"NSW",
    "wof:name":"Amos",
    "wof:placetype":"venue"
},
  "geometry": {"coordinates":[150.98245239299999,-33.8850784302],"type":"Point"}
}