{
  "type": "Feature",
  "properties": {
    "addr:full":"26 Ewos Pde Cronulla NSW 2230",
    "addr:housenumber":"26",
    "addr:postcode":"2230",
    "addr:street":"Ewos Pde",
    "iso:country":"AU",
    "sg:address":"26 Ewos Pde",
    "sg:city":"Cronulla",
    "sg:classifiers":[
        {
            "category":"Personal",
            "subcategory":"Beauty Salon",
            "type":"Services"
        }
    ],
    "sg:phone":"+61 2 9523 8833",
    "sg:postcode":"2230",
    "sg:province":"NSW",
    "sg:tags":[
        "hairdresser"
    ],
    "wof:name":"Cronulla South Hairdressing & Beauty Centre",
    "wof:placetype":"venue"
},
  "geometry": {"coordinates":[151.15461730999999,-34.0602989197],"type":"Point"}
}