{
  "type": "Feature",
  "properties": {
    "addr:full":"180 High St Prahran VIC 3181",
    "addr:housenumber":"180",
    "addr:postcode":"3181",
    "addr:street":"High St",
    "iso:country":"AU",
    "sg:address":"180 High St",
    "sg:city":"Prahran",
    "sg:classifiers":[
        {
            "category":"Shopping",
            "subcategory":"Music",
            "type":"Retail Goods"
        }
    ],
    "sg:phone":"+61 3 9533 6635",
    "sg:postcode":"3181",
    "sg:province":"VIC",
    "sg:tags":[
        "store"
    ],
    "wof:name":"Capital D J Pty Ltd",
    "wof:placetype":"venue"
},
  "geometry": {"coordinates":[144.994262695,-37.8520736694],"type":"Point"}
}