{
  "type": "Feature",
  "properties": {
    "iso:country":"AU",
    "sg:address":"12/ 200 Canterbury Rd",
    "sg:city":"Bayswater",
    "sg:classifiers":[
        {
            "category":"Wholesale",
            "subcategory":"Machinery & Supplies",
            "type":"Manufacturing & Wholesale Goods"
        }
    ],
    "sg:phone":"+61 1300 134 861",
    "sg:postcode":"3153",
    "sg:province":"VIC",
    "sg:tags":[
        "equipment",
        "pneumatic"
    ],
    "wof:name":"Pneumax",
    "wof:placetype":"venue"
},
  "geometry": {"coordinates":[145.28724670400001,-37.8258934021],"type":"Point"}
}