{
  "type": "Feature",
  "properties": {
    "addr:full":"32 Wises Rd Maroochydore QLD 4558",
    "addr:housenumber":"32",
    "addr:postcode":"4558",
    "addr:street":"Wises Rd",
    "iso:country":"AU",
    "sg:address":"32 Wises Rd",
    "sg:city":"Maroochydore",
    "sg:classifiers":[
        {
            "category":"Home & Garden",
            "subcategory":"Furniture",
            "type":"Retail Goods"
        }
    ],
    "sg:phone":"+61 7 5452 7833",
    "sg:postcode":"4558",
    "sg:province":"QLD",
    "sg:tags":[
        "outdoor"
    ],
    "wof:name":"The Outdoor Furniture Specialists",
    "wof:placetype":"venue"
},
  "geometry": {"coordinates":[153.07867431599999,-26.6703243256],"type":"Point"}
}