{
  "type": "Feature",
  "properties": {
    "iso:country":"AU",
    "sg:address":"Unit 1/ 279 Camboon Rd",
    "sg:city":"Malaga",
    "sg:classifiers":[
        {
            "category":"Retail",
            "subcategory":"Auto Repair",
            "type":"Services"
        }
    ],
    "sg:phone":"+61 8 9248 8800",
    "sg:postcode":"6090",
    "sg:province":"WA",
    "sg:tags":[
        "electrical"
    ],
    "wof:name":"Malaga Diesel Electrics",
    "wof:placetype":"venue"
},
  "geometry": {"coordinates":[115.886909485,-31.8560886383],"type":"Point"}
}