{
  "type": "Feature",
  "properties": {
    "iso:country":"AU",
    "sg:address":"26 Erin St",
    "sg:city":"Richmond",
    "sg:classifiers":[
        {
            "category":"Health Services",
            "subcategory":"Doctor",
            "type":"Services"
        }
    ],
    "sg:phone":"+61 3 9427 9565",
    "sg:postcode":"3121",
    "sg:province":"VIC",
    "sg:tags":[
        "medical",
        "practitioner"
    ],
    "wof:name":"King Kevin F",
    "wof:placetype":"venue"
},
  "geometry": {"coordinates":[144.99945068400001,-37.8170204163],"type":"Point"}
}