{
  "type": "Feature",
  "properties": {
    "iso:country":"AU",
    "sg:address":"2/ 29 Wentworth St",
    "sg:city":"Greenacre",
    "sg:classifiers":[
        {
            "category":"Professional",
            "subcategory":"Management & Consulting",
            "type":"Services"
        }
    ],
    "sg:phone":"+61 2 9758 8411",
    "sg:postcode":"2190",
    "sg:province":"NSW",
    "sg:tags":[
        "consultant",
        "relocation"
    ],
    "wof:name":"P & C Bramley Transport",
    "wof:placetype":"venue"
},
  "geometry": {"coordinates":[151.069275,-33.899723],"type":"Point"}
}