{
  "type": "Feature",
  "properties": {
    "addr:full":"Cnr Bugden & South St Alstonville NSW 2477",
    "addr:postcode":"2477",
    "addr:street":"Cnr;St",
    "iso:country":"AU",
    "sg:address":"Cnr Bugden & South St",
    "sg:city":"Alstonville",
    "sg:classifiers":[
        {
            "category":"Building & Trades",
            "subcategory":"Landscaping Services",
            "type":"Services"
        }
    ],
    "sg:phone":"+61 2 6628 1122",
    "sg:postcode":"2477",
    "sg:province":"NSW",
    "sg:tags":[
        "horticultural",
        "consultant"
    ],
    "wof:name":"Fitzell Ross",
    "wof:placetype":"venue"
},
  "geometry": {"coordinates":[153.44125366200001,-28.8399486542],"type":"Point"}
}