{
  "type": "Feature",
  "properties": {
    "iso:country":"AU",
    "sg:address":"28 Montgomery St",
    "sg:city":"Kogarah",
    "sg:classifiers":[
        {
            "category":"Health Services",
            "subcategory":"Dentist",
            "type":"Services"
        }
    ],
    "sg:phone":"+61 2 9588 5855",
    "sg:postcode":"2217",
    "sg:province":"NSW",
    "wof:name":"Sydney Dental Care",
    "wof:placetype":"venue"
},
  "geometry": {"coordinates":[151.13447600000001,-33.963997],"type":"Point"}
}