{
  "type": "Feature",
  "properties": {
    "addr:full":"1 Burke St Appin NSW 2560",
    "addr:housenumber":"1",
    "addr:postcode":"2560",
    "addr:street":"Burke St",
    "iso:country":"AU",
    "sg:address":"1 Burke St",
    "sg:city":"Appin",
    "sg:classifiers":[
        {
            "category":"Landmark",
            "subcategory":"Scenic View",
            "type":"Public Place"
        }
    ],
    "sg:phone":"+61 2 4631 1268",
    "sg:postcode":"2560",
    "sg:province":"NSW",
    "sg:tags":[
        "staircase",
        "handrail"
    ],
    "wof:name":"Galaxy Staircases",
    "wof:placetype":"venue"
},
  "geometry": {"coordinates":[150.84381103499999,-34.0652885437],"type":"Point"}
}