{
  "type": "Feature",
  "properties": {
    "iso:country":"AU",
    "sg:address":"1 Howden Rd",
    "sg:city":"Margate",
    "sg:classifiers":[
        {
            "category":"Building & Trades",
            "subcategory":"Construction",
            "type":"Services"
        }
    ],
    "sg:phone":"+61 3 6267 1970",
    "sg:postcode":"7054",
    "sg:province":"TAS",
    "sg:tags":[
        "mural"
    ],
    "wof:name":"Murphy J",
    "wof:placetype":"venue"
},
  "geometry": {"coordinates":[147.273087,-43.007191],"type":"Point"}
}