{
  "type": "Feature",
  "properties": {
    "addr:full":"Main Drv Warana QLD 4575",
    "addr:postcode":"4575",
    "addr:street":"Main Drv",
    "iso:country":"AU",
    "sg:address":"Main Drv",
    "sg:city":"Warana",
    "sg:classifiers":[
        {
            "category":"Home & Garden",
            "subcategory":"Hardware",
            "type":"Retail Goods"
        }
    ],
    "sg:phone":"+61 7 5493 1511",
    "sg:postcode":"4575",
    "sg:province":"QLD",
    "sg:tags":[
        "repair",
        "tool",
        "power"
    ],
    "wof:name":"Stacks Timber And Hardware",
    "wof:placetype":"venue"
},
  "geometry": {"coordinates":[153.128525,-26.730846],"type":"Point"}
}