{
  "type": "Feature",
  "properties": {
    "addr:full":"18 Gleeson St Clare SA 5453",
    "addr:housenumber":"18",
    "addr:postcode":"5453",
    "addr:street":"Gleeson St",
    "iso:country":"AU",
    "sg:address":"18 Gleeson St",
    "sg:city":"Clare",
    "sg:classifiers":[
        {
            "category":"Health Services",
            "subcategory":"Health Practitioner",
            "type":"Services"
        }
    ],
    "sg:phone":"+61 8 8842 2729",
    "sg:postcode":"5453",
    "sg:province":"SA",
    "sg:tags":[
        "naturopath"
    ],
    "wof:name":"Dickmann D Dr",
    "wof:placetype":"venue"
},
  "geometry": {"coordinates":[138.61059599999999,-33.834866],"type":"Point"}
}