{
  "type": "Feature",
  "properties": {
    "addr:full":"Abel St Boyup Brook WA 6244",
    "addr:postcode":"6244",
    "addr:street":"Abel St",
    "iso:country":"AU",
    "sg:address":"Abel St",
    "sg:city":"Boyup Brook",
    "sg:classifiers":[
        {
            "category":"Autos & Motor Vehicles",
            "subcategory":"Fuel & Gas Station",
            "type":"Retail Goods"
        }
    ],
    "sg:phone":"+61 8 9765 1123",
    "sg:postcode":"6244",
    "sg:province":"WA",
    "wof:name":"BP Australia Limited",
    "wof:placetype":"venue"
},
  "geometry": {"coordinates":[116.389602661,-33.8336448669],"type":"Point"}
}