{
  "type": "Feature",
  "properties": {
    "addr:full":"143 Kildare Rd Blacktown NSW 2148",
    "addr:housenumber":"143",
    "addr:postcode":"2148",
    "addr:street":"Kildare Rd",
    "iso:country":"AU",
    "sg:address":"143 Kildare Rd",
    "sg:city":"Blacktown",
    "sg:classifiers":[
        {
            "category":"Retail",
            "subcategory":"Auto Repair",
            "type":"Services"
        }
    ],
    "sg:phone":"+61 2 9831 2625",
    "sg:postcode":"2148",
    "sg:province":"NSW",
    "sg:tags":[
        "repairer",
        "motor",
        "engineer"
    ],
    "wof:name":"A.M. Services",
    "wof:placetype":"venue"
},
  "geometry": {"coordinates":[150.89173889200001,-33.7686004639],"type":"Point"}
}