{
  "type": "Feature",
  "properties": {
    "iso:country":"AU",
    "sg:address":"Bournda Rd",
    "sg:city":"Tathra",
    "sg:classifiers":[
        {
            "category":"Building & Trades",
            "subcategory":"Construction",
            "type":"Services"
        }
    ],
    "sg:phone":"+61 2 6494 1391",
    "sg:postcode":"2550",
    "sg:province":"NSW",
    "sg:tags":[
        "earth",
        "excavating",
        "moving",
        "contractor"
    ],
    "wof:name":"Barker's Tathra Backhoe & Bobcat Hire",
    "wof:placetype":"venue"
},
  "geometry": {"coordinates":[149.915725708,-36.7860336304],"type":"Point"}
}