{
  "type": "Feature",
  "properties": {
    "iso:country":"AU",
    "sg:address":"144 Moray St",
    "sg:city":"South Melbourne",
    "sg:classifiers":[
        {
            "category":"Education",
            "subcategory":"Special Training",
            "type":"Public Place"
        }
    ],
    "sg:phone":"+61 3 9602 2300",
    "sg:postcode":"3205",
    "sg:province":"VIC",
    "sg:tags":[
        "development"
    ],
    "wof:name":"Australian Film Television & Radio School",
    "wof:placetype":"venue"
},
  "geometry": {"coordinates":[144.962112,-37.830585],"type":"Point"}
}