{
  "type": "Feature",
  "properties": {
    "iso:country":"AU",
    "sg:address":"21 Modillion St",
    "sg:city":"Trinder Park",
    "sg:classifiers":[
        {
            "category":"Building & Trades",
            "subcategory":"Construction",
            "type":"Services"
        }
    ],
    "sg:phone":"+61 414 738 370",
    "sg:postcode":"4114",
    "sg:province":"QLD",
    "sg:tags":[
        "concrete",
        "contractor"
    ],
    "wof:name":"Berry Ron Concrete Specialists",
    "wof:placetype":"venue"
},
  "geometry": {"coordinates":[153.098556519,-27.6258640289],"type":"Point"}
}