{
  "type": "Feature",
  "properties": {
    "addr:full":"Unit 4, 4- 10 Farrall Rd Midvale WA 6056",
    "addr:housenumber":"4 10",
    "addr:postcode":"6056",
    "addr:street":"Farrall Rd",
    "iso:country":"AU",
    "sg:address":"Unit 4, 4- 10 Farrall Rd",
    "sg:city":"Midvale",
    "sg:classifiers":[
        {
            "category":"Professional",
            "subcategory":"Accounting & Tax Preparation",
            "type":"Services"
        }
    ],
    "sg:phone":"+61 8 9250 2144",
    "sg:postcode":"6056",
    "sg:province":"WA",
    "sg:tags":[
        "accountant",
        "auditor"
    ],
    "wof:name":"Carter Woodgate",
    "wof:placetype":"venue"
},
  "geometry": {"coordinates":[116.033630371,-31.8840770721],"type":"Point"}
}