{
  "type": "Feature",
  "properties": {
    "addr:full":"4 / 289 Morayfield Rd Morayfield QLD 4506",
    "addr:housenumber":"/ 289",
    "addr:postcode":"4506",
    "addr:street":"Morayfield Rd",
    "iso:country":"AU",
    "sg:address":"4 / 289 Morayfield Rd",
    "sg:city":"Morayfield",
    "sg:classifiers":[
        {
            "category":"Building & Trades",
            "subcategory":"Construction",
            "type":"Services"
        }
    ],
    "sg:phone":"+61 7 5497 8136",
    "sg:postcode":"4506",
    "sg:province":"QLD",
    "sg:tags":[
        "window",
        "tinting"
    ],
    "wof:name":"Tint Mart Window Tinting",
    "wof:placetype":"venue"
},
  "geometry": {"coordinates":[152.95201110799999,-27.1137294769],"type":"Point"}
}