{
  "type": "Feature",
  "properties": {
    "addr:full":"Civic Centre 601 High St Penrith NSW 2750",
    "addr:housenumber":"601",
    "addr:postcode":"2750",
    "addr:street":"High St",
    "iso:country":"AU",
    "sg:address":"Civic Centre 601 High St",
    "sg:city":"Penrith",
    "sg:classifiers":[
        {
            "category":"Social Services",
            "subcategory":"Child Care",
            "type":"Services"
        }
    ],
    "sg:phone":"+61 2 4732 7828",
    "sg:postcode":"2750",
    "sg:province":"NSW",
    "wof:name":"Penrith City Council Child Care Centres",
    "wof:placetype":"venue"
},
  "geometry": {"coordinates":[150.915527344,-33.8951301575],"type":"Point"}
}