{
  "type": "Feature",
  "properties": {
    "iso:country":"AU",
    "sg:address":"19 McDonald St",
    "sg:city":"Osborne Park",
    "sg:classifiers":[
        {
            "category":"Building & Trades",
            "subcategory":"Plumbing",
            "type":"Services"
        }
    ],
    "sg:phone":"+61 8 9201 1177",
    "sg:postcode":"6017",
    "sg:province":"WA",
    "sg:tags":[
        "plumber",
        "gasfitters"
    ],
    "wof:name":"Boeing Plumbing",
    "wof:placetype":"venue"
},
  "geometry": {"coordinates":[115.820762634,-31.9060955048],"type":"Point"}
}