{
  "type": "Feature",
  "properties": {
    "addr:full":"196 Lord St Perth WA 6000",
    "addr:housenumber":"196",
    "addr:postcode":"6000",
    "addr:street":"Lord St",
    "iso:country":"AU",
    "sg:address":"196 Lord St",
    "sg:city":"Perth",
    "sg:classifiers":[
        {
            "category":"Organizations",
            "subcategory":"Labor Organization",
            "type":"Services"
        }
    ],
    "sg:phone":"+61 8 9227 9397",
    "sg:postcode":"6000",
    "sg:province":"WA",
    "sg:tags":[
        "union"
    ],
    "wof:name":"C.E.P.U. Communications Division",
    "wof:placetype":"venue"
},
  "geometry": {"coordinates":[115.870796204,-31.9476108551],"type":"Point"}
}