{
  "type": "Feature",
  "properties": {
    "addr:full":"246 Queen St Campbelltown NSW 2560",
    "addr:housenumber":"246",
    "addr:postcode":"2560",
    "addr:street":"Queen St",
    "iso:country":"AU",
    "sg:address":"246 Queen St",
    "sg:city":"Campbelltown",
    "sg:classifiers":[
        {
            "category":"Health Services",
            "subcategory":"Doctor",
            "type":"Services"
        }
    ],
    "sg:phone":"+61 2 4625 5255",
    "sg:postcode":"2560",
    "sg:province":"NSW",
    "sg:tags":[
        "medical",
        "practitioner"
    ],
    "wof:name":"Campbelltown Medical Practice",
    "wof:placetype":"venue"
},
  "geometry": {"coordinates":[150.81300354000001,-34.068271637],"type":"Point"}
}