{
  "type": "Feature",
  "properties": {
    "addr:full":"271 Grassdale Rd Gumdale QLD 4154",
    "addr:housenumber":"271",
    "addr:postcode":"4154",
    "addr:street":"Grassdale Rd",
    "iso:country":"AU",
    "sg:address":"271 Grassdale Rd",
    "sg:city":"Gumdale",
    "sg:classifiers":[
        {
            "category":"Building & Trades",
            "subcategory":"Construction",
            "type":"Services"
        }
    ],
    "sg:phone":"+61 418 152 207",
    "sg:postcode":"4154",
    "sg:province":"QLD",
    "sg:tags":[
        "renovation",
        "alterations",
        "extension",
        "contractor"
    ],
    "wof:name":"Ferguson Styling Pty Ltd",
    "wof:placetype":"venue"
},
  "geometry": {"coordinates":[153.14422607399999,-27.497095108],"type":"Point"}
}