{
  "type": "Feature",
  "properties": {
    "addr:full":"Unit 12, 8 Leighton Pl Hornsby NSW 2077",
    "addr:housenumber":"8",
    "addr:postcode":"2077",
    "addr:street":"Leighton Pl",
    "iso:country":"AU",
    "sg:address":"Unit 12, 8 Leighton Pl",
    "sg:city":"Hornsby",
    "sg:classifiers":[
        {
            "category":"Retail",
            "subcategory":"Auto Repair",
            "type":"Services"
        }
    ],
    "sg:phone":"+61 2 9476 4100",
    "sg:postcode":"2077",
    "sg:province":"NSW",
    "sg:tags":[
        "fuel",
        "petrol",
        "injection"
    ],
    "wof:name":"Recarb",
    "wof:placetype":"venue"
},
  "geometry": {"coordinates":[151.11230468799999,-33.6966781616],"type":"Point"}
}