{
  "type": "Feature",
  "properties": {
    "addr:full":"Cnr of Scarba & Murdock Sts Coffs Harbour NSW 2450",
    "addr:postcode":"2450",
    "iso:country":"AU",
    "sg:address":"Cnr of Scarba & Murdock Sts",
    "sg:city":"Coffs Harbour",
    "sg:classifiers":[
        {
            "category":"Retail",
            "subcategory":"Repair Shop",
            "type":"Services"
        }
    ],
    "sg:phone":"+61 2 6652 1863",
    "sg:postcode":"2450",
    "sg:province":"NSW",
    "sg:tags":[
        "machine",
        "sewing"
    ],
    "wof:name":"Creative Home Sewing Centre",
    "wof:placetype":"venue"
},
  "geometry": {"coordinates":[153.114136,-30.298374],"type":"Point"}
}