{
  "type": "Feature",
  "properties": {
    "addr:full":"548 Blaxlands Ridge Rd Kurrajong NSW 2758",
    "addr:housenumber":"548",
    "addr:postcode":"2758",
    "addr:street":"Blaxlands Ridge Rd",
    "iso:country":"AU",
    "sg:address":"548 Blaxlands Ridge Rd",
    "sg:city":"Kurrajong",
    "sg:classifiers":[
        {
            "category":"Professional",
            "type":"Services"
        }
    ],
    "sg:phone":"+61 2 4576 0343",
    "sg:postcode":"2758",
    "sg:province":"NSW",
    "sg:tags":[
        "transport"
    ],
    "wof:name":"McCormack Heavy Haulage",
    "wof:placetype":"venue"
},
  "geometry": {"coordinates":[150.76895141599999,-33.4920501709],"type":"Point"}
}