{
  "type": "Feature",
  "properties": {
    "addr:full":"Level1/ 85 Hutt St Adelaide SA 5000",
    "addr:housenumber":"85",
    "addr:postcode":"5000",
    "addr:street":"Hutt St",
    "iso:country":"AU",
    "sg:address":"Level1/ 85 Hutt St",
    "sg:city":"Adelaide",
    "sg:classifiers":[
        {
            "category":"Banks & Credit Unions",
            "subcategory":"Financial Services",
            "type":"Services"
        }
    ],
    "sg:phone":"+61 8 8232 9498",
    "sg:postcode":"5000",
    "sg:province":"SA",
    "sg:tags":[
        "planning"
    ],
    "wof:name":"Wallis-Smith Financial Planning",
    "wof:placetype":"venue"
},
  "geometry": {"coordinates":[138.61175537099999,-34.9283981323],"type":"Point"}
}