{
  "type": "Feature",
  "properties": {
    "iso:country":"AU",
    "sg:address":"182- 192 Callaghan Rd",
    "sg:city":"Narangba",
    "sg:classifiers":[
        {
            "category":"Shopping",
            "subcategory":"Antiques",
            "type":"Retail Goods"
        }
    ],
    "sg:phone":"+61 7 3888 0960",
    "sg:postcode":"4504",
    "sg:province":"QLD",
    "sg:tags":[
        "restoration",
        "reproduction"
    ],
    "wof:name":"East Coast Antique Restorations",
    "wof:placetype":"venue"
},
  "geometry": {"coordinates":[152.96710205100001,-27.189250946],"type":"Point"}
}