{
  "type": "Feature",
  "properties": {
    "addr:full":"Court St Tabulam NSW 2469",
    "addr:postcode":"2469",
    "addr:street":"Court St",
    "iso:country":"AU",
    "sg:address":"Court St",
    "sg:city":"Tabulam",
    "sg:classifiers":[
        {
            "category":"Food & Beverages",
            "subcategory":"Groceries & Convenience Stores",
            "type":"Retail Goods"
        }
    ],
    "sg:phone":"+61 2 6666 1484",
    "sg:postcode":"2469",
    "sg:province":"NSW",
    "wof:name":"Tabulam Cafe & Mini Mart",
    "wof:placetype":"venue"
},
  "geometry": {"coordinates":[152.5650177,-28.8903408051],"type":"Point"}
}