{
  "type": "Feature",
  "properties": {
    "iso:country":"AU",
    "sg:address":"816 Plenty Rd",
    "sg:city":"South Morang",
    "sg:classifiers":[
        {
            "category":"Home & Garden",
            "subcategory":"Household Appliances",
            "type":"Retail Goods"
        }
    ],
    "sg:phone":"+61 3 9437 6500",
    "sg:postcode":"3752",
    "sg:province":"VIC",
    "sg:tags":[
        "heating",
        "system"
    ],
    "wof:name":"Rosanna Ducted Heating & Air Conditioning",
    "wof:placetype":"venue"
},
  "geometry": {"coordinates":[145.09588600000001,-37.638],"type":"Point"}
}