{
  "type": "Feature",
  "properties": {
    "addr:full":"Kirin Centre, Level 5, 15 Ogilvie Rd Mt Pleasant WA 6153",
    "addr:housenumber":"15",
    "addr:postcode":"6153",
    "addr:street":"Ogilvie Rd",
    "iso:country":"AU",
    "sg:address":"Kirin Centre, Level 5, 15 Ogilvie Rd",
    "sg:city":"Mt Pleasant",
    "sg:classifiers":[
        {
            "category":"Banks & Credit Unions",
            "subcategory":"Financial Services",
            "type":"Services"
        }
    ],
    "sg:phone":"+61 8 9316 1666",
    "sg:postcode":"6153",
    "sg:province":"WA",
    "sg:tags":[
        "settlement",
        "nt",
        "agent",
        "wa"
    ],
    "wof:name":"Prudential Settlement Services",
    "wof:placetype":"venue"
},
  "geometry": {"coordinates":[115.835098,-32.010941],"type":"Point"}
}