{
  "type": "Feature",
  "properties": {
    "addr:full":"Whittless Rd Bridgetown WA 6255",
    "addr:postcode":"6255",
    "addr:street":"Whittless Rd",
    "iso:country":"AU",
    "sg:address":"Whittless Rd",
    "sg:city":"Bridgetown",
    "sg:classifiers":[
        {
            "category":"Building & Trades",
            "subcategory":"Construction",
            "type":"Services"
        }
    ],
    "sg:phone":"+61 8 9761 1061",
    "sg:postcode":"6255",
    "sg:province":"WA",
    "sg:tags":[
        "contractor"
    ],
    "wof:name":"Davies D",
    "wof:placetype":"venue"
},
  "geometry": {"coordinates":[116.14173126199999,-33.9431915283],"type":"Point"}
}