{
  "type": "Feature",
  "properties": {
    "addr:full":"2 Rob Pl Vineyard NSW 2765",
    "addr:housenumber":"2",
    "addr:postcode":"2765",
    "addr:street":"Rob Pl",
    "iso:country":"AU",
    "sg:address":"2 Rob Pl",
    "sg:city":"Vineyard",
    "sg:classifiers":[
        {
            "category":"Professional",
            "subcategory":"Engineering",
            "type":"Services"
        }
    ],
    "sg:phone":"+61 13 16 03",
    "sg:postcode":"2765",
    "sg:province":"NSW",
    "sg:tags":[
        "building",
        "prefabricated",
        "transportable",
        "industrial",
        "commercial"
    ],
    "wof:name":"Tri-Steel",
    "wof:placetype":"venue"
},
  "geometry": {"coordinates":[150.842407227,-33.6307792664],"type":"Point"}
}