{
  "type": "Feature",
  "properties": {
    "addr:full":"100 Waterloo Rd Greenacre NSW 2190",
    "addr:housenumber":"100",
    "addr:postcode":"2190",
    "addr:street":"Waterloo Rd",
    "iso:country":"AU",
    "sg:address":"100 Waterloo Rd",
    "sg:city":"Greenacre",
    "sg:classifiers":[
        {
            "category":"Food & Beverages",
            "subcategory":"Groceries & Convenience Stores",
            "type":"Retail Goods"
        }
    ],
    "sg:phone":"+61 2 9740 4425",
    "sg:postcode":"2190",
    "sg:province":"NSW",
    "wof:name":"Supreme Mixed Business",
    "wof:placetype":"venue"
},
  "geometry": {"coordinates":[151.05815100000001,-33.902248],"type":"Point"}
}