{
  "type": "Feature",
  "properties": {
    "addr:full":"8 Adecroft Crt Eltham VIC 3095",
    "addr:housenumber":"8",
    "addr:postcode":"3095",
    "addr:street":"Adecroft Crt",
    "iso:country":"AU",
    "sg:address":"8 Adecroft Crt",
    "sg:city":"Eltham",
    "sg:classifiers":[
        {
            "category":"Professional",
            "subcategory":"Engineering",
            "type":"Services"
        }
    ],
    "sg:phone":"+61 3 9439 3310",
    "sg:postcode":"3095",
    "sg:province":"VIC",
    "sg:tags":[
        "engineer"
    ],
    "wof:name":"SP Morgan Engineering Services",
    "wof:placetype":"venue"
},
  "geometry": {"coordinates":[145.160766602,-37.7153320312],"type":"Point"}
}