{
  "type": "Feature",
  "properties": {
    "addr:full":"18 Bundaroo St Bowral NSW 2576",
    "addr:housenumber":"18",
    "addr:postcode":"2576",
    "addr:street":"Bundaroo St",
    "iso:country":"AU",
    "sg:address":"18 Bundaroo St",
    "sg:city":"Bowral",
    "sg:classifiers":[
        {
            "category":"Real Estate",
            "subcategory":"Architect",
            "type":"Services"
        }
    ],
    "sg:phone":"+61 2 4861 6846",
    "sg:postcode":"2576",
    "sg:province":"NSW",
    "sg:tags":[
        "building",
        "designer"
    ],
    "wof:name":"Cold Climate Cottages Design Group",
    "wof:placetype":"venue"
},
  "geometry": {"coordinates":[150.420043945,-34.4766998291],"type":"Point"}
}