{
  "type": "Feature",
  "properties": {
    "addr:full":"106 Mt Peter Rd Edmonton QLD 4869",
    "addr:housenumber":"106",
    "addr:postcode":"4869",
    "addr:street":"Mt Peter Rd",
    "iso:country":"AU",
    "sg:address":"106 Mt Peter Rd",
    "sg:city":"Edmonton",
    "sg:classifiers":[
        {
            "category":"Building & Trades",
            "subcategory":"Construction",
            "type":"Services"
        }
    ],
    "sg:phone":"+61 7 4055 4608",
    "sg:postcode":"4869",
    "sg:province":"QLD",
    "sg:tags":[
        "earth",
        "excavating",
        "moving",
        "contractor"
    ],
    "wof:name":"Pedrola J & H",
    "wof:placetype":"venue"
},
  "geometry": {"coordinates":[145.734451294,-17.0301113129],"type":"Point"}
}