{
  "type": "Feature",
  "properties": {
    "iso:country":"AU",
    "sg:address":"7 Bromfield St",
    "sg:city":"Colac",
    "sg:classifiers":[
        {
            "category":"Insurance",
            "subcategory":"Insurance Agent",
            "type":"Services"
        }
    ],
    "sg:phone":"+61 3 5231 5411",
    "sg:postcode":"3250",
    "sg:province":"VIC",
    "wof:name":"Steve Millar",
    "wof:placetype":"venue"
},
  "geometry": {"coordinates":[143.585007,-38.340809],"type":"Point"}
}