{
  "type": "Feature",
  "properties": {
    "addr:full":"3 Bay St Port Broughton SA 5522",
    "addr:housenumber":"3",
    "addr:postcode":"5522",
    "addr:street":"Bay St",
    "iso:country":"AU",
    "sg:address":"3 Bay St",
    "sg:city":"Port Broughton",
    "sg:classifiers":[
        {
            "category":"Communications",
            "subcategory":"News Services",
            "type":"Services"
        }
    ],
    "sg:phone":"+61 8 8635 2261",
    "sg:postcode":"5522",
    "sg:province":"SA",
    "sg:tags":[
        "information",
        "tourist",
        "attractions"
    ],
    "wof:name":"Port Broughton Visitor Information Centre",
    "wof:placetype":"venue"
},
  "geometry": {"coordinates":[137.93328857399999,-33.6005477905],"type":"Point"}
}