{
  "type": "Feature",
  "properties": {
    "addr:full":"14 Belair Ave Port Willunga SA 5173",
    "addr:housenumber":"14",
    "addr:postcode":"5173",
    "addr:street":"Belair Ave",
    "iso:country":"AU",
    "sg:address":"14 Belair Ave",
    "sg:city":"Port Willunga",
    "sg:classifiers":[
        {
            "category":"Education",
            "subcategory":"Special Training",
            "type":"Public Place"
        }
    ],
    "sg:phone":"+61 8 8556 5316",
    "sg:postcode":"5173",
    "sg:province":"SA",
    "sg:tags":[
        "development"
    ],
    "wof:name":"Aussiehost Fleurieu",
    "wof:placetype":"venue"
},
  "geometry": {"coordinates":[138.45994567899999,-35.2666740417],"type":"Point"}
}