{
  "type": "Feature",
  "properties": {
    "addr:full":"19 Leda Drv Andrews QLD 4220",
    "addr:housenumber":"19",
    "addr:postcode":"4220",
    "addr:street":"Leda Drv",
    "iso:country":"AU",
    "sg:address":"19 Leda Drv",
    "sg:city":"Andrews",
    "sg:classifiers":[
        {
            "category":"Food & Beverages",
            "subcategory":"Fruits & Vegetables",
            "type":"Retail Goods"
        }
    ],
    "sg:phone":"+61 7 5520 6000",
    "sg:postcode":"4220",
    "sg:province":"QLD",
    "sg:tags":[
        "greengrocer",
        "fruiterer"
    ],
    "wof:name":"The Fresh Produce Company",
    "wof:placetype":"venue"
},
  "geometry": {"coordinates":[153.43020629899999,-28.1051998138],"type":"Point"}
}