{
  "type": "Feature",
  "properties": {
    "addr:full":"43b Norseman Rd Esperance WA 6450",
    "addr:housenumber":"43b",
    "addr:postcode":"6450",
    "addr:street":"Norseman Rd",
    "iso:country":"AU",
    "sg:address":"43b Norseman Rd",
    "sg:city":"Esperance",
    "sg:classifiers":[
        {
            "category":"Professional",
            "subcategory":"Detective & Security Services",
            "type":"Services"
        }
    ],
    "sg:phone":"+61 8 9071 7226",
    "sg:postcode":"6450",
    "sg:province":"WA",
    "sg:tags":[
        "guard",
        "patrol"
    ],
    "wof:name":"Storm Security Service",
    "wof:placetype":"venue"
},
  "geometry": {"coordinates":[121.90003967299999,-33.8441238403],"type":"Point"}
}