{
  "type": "Feature",
  "properties": {
    "addr:full":"560 High St Epping VIC 3076",
    "addr:housenumber":"560",
    "addr:postcode":"3076",
    "addr:street":"High St",
    "iso:country":"AU",
    "sg:address":"560 High St",
    "sg:city":"Epping",
    "sg:classifiers":[
        {
            "category":"Autos & Motor Vehicles",
            "subcategory":"Auto Supplies",
            "type":"Retail Goods"
        }
    ],
    "sg:phone":"+61 3 9408 3666",
    "sg:postcode":"3076",
    "sg:province":"VIC",
    "sg:tags":[
        "car",
        "alarm"
    ],
    "wof:name":"Autobarn",
    "wof:placetype":"venue"
},
  "geometry": {"coordinates":[145.00672912600001,-37.8537940979],"type":"Point"}
}