{
  "type": "Feature",
  "properties": {
    "addr:full":"Unit 1/ 12 Marchant Way Morley WA 6062",
    "addr:housenumber":"12",
    "addr:postcode":"6062",
    "addr:street":"Marchant Way",
    "iso:country":"AU",
    "sg:address":"Unit 1/ 12",
    "sg:city":"Marchant Way Morley",
    "sg:classifiers":[
        {
            "category":"Shopping",
            "subcategory":"Gifts & Souvenirs",
            "type":"Retail Goods"
        }
    ],
    "sg:phone":"+61 8 9375 9810",
    "sg:postcode":"6062",
    "sg:province":"WA",
    "sg:tags":[
        "shop",
        "supply"
    ],
    "wof:name":"Arts & Crafts Australia",
    "wof:placetype":"venue"
},
  "geometry": {"coordinates":[115.902778626,-31.9017410278],"type":"Point"}
}