{
  "type": "Feature",
  "properties": {
    "addr:full":"Shop 3, 417 Logan Road Stones Corner QLD 4120",
    "addr:housenumber":"shop 3 417",
    "addr:postcode":"4120",
    "addr:street":"Logan Road",
    "iso:country":"AU",
    "sg:address":"Shop 3, 417 Logan Road",
    "sg:city":"Stones Corner",
    "sg:classifiers":[
        {
            "category":"Shopping",
            "type":"Retail Goods"
        }
    ],
    "sg:phone":"+61 7 3397 3736",
    "sg:postcode":"4120",
    "sg:province":"QLD",
    "sg:tags":[
        "repair",
        "travel"
    ],
    "wof:name":"Strandbags Group",
    "wof:placetype":"venue"
},
  "geometry": {"coordinates":[153.045852661,-27.5009040833],"type":"Point"}
}