{
  "type": "Feature",
  "properties": {
    "addr:full":"21 Dakota Pl Raby NSW 2566",
    "addr:housenumber":"21",
    "addr:postcode":"2566",
    "addr:street":"Dakota Pl Raby",
    "iso:country":"AU",
    "sg:address":"21 Dakota Pl",
    "sg:city":"Raby",
    "sg:classifiers":[
        {
            "category":"Food & Beverages",
            "subcategory":"Specialty",
            "type":"Retail Goods"
        }
    ],
    "sg:phone":"+61 2 9820 7973",
    "sg:postcode":"2566",
    "sg:province":"NSW",
    "sg:tags":[
        "product",
        "health"
    ],
    "wof:name":"Herbalife Raby",
    "wof:placetype":"venue"
},
  "geometry": {"coordinates":[150.806884766,-34.0147094727],"type":"Point"}
}