{
  "type": "Feature",
  "properties": {
    "addr:full":"197 Young St Waterloo NSW 1440",
    "addr:housenumber":"197",
    "addr:postcode":"1440",
    "addr:street":"Young St",
    "iso:country":"AU",
    "sg:address":"197 Young St",
    "sg:city":"Waterloo",
    "sg:classifiers":[
        {
            "category":"Home & Garden",
            "subcategory":"Building Materials",
            "type":"Retail Goods"
        }
    ],
    "sg:phone":"+61 2 8332 6999",
    "sg:postcode":"1440",
    "sg:province":"NSW",
    "sg:tags":[
        "fitting",
        "door"
    ],
    "wof:name":"Mother Of Pearl & Sons",
    "wof:placetype":"venue"
},
  "geometry": {"coordinates":[151.209594727,-33.8970794678],"type":"Point"}
}