{
  "type": "Feature",
  "properties": {
    "addr:full":"Shp5/ 371 Belgravia St Cloverdale WA 6105",
    "addr:housenumber":"371",
    "addr:postcode":"6105",
    "addr:street":"Belgravia St",
    "iso:country":"AU",
    "sg:address":"Shp5/ 371 Belgravia St",
    "sg:city":"Cloverdale",
    "sg:classifiers":[
        {
            "category":"Retail",
            "subcategory":"Laundry & Dry Cleaning",
            "type":"Services"
        }
    ],
    "sg:phone":"+61 8 9478 1865",
    "sg:postcode":"6105",
    "sg:province":"WA",
    "sg:tags":[
        "ironing"
    ],
    "wof:name":"Lings Alterations & Ironing Services",
    "wof:placetype":"venue"
},
  "geometry": {"coordinates":[115.945037842,-31.9624538422],"type":"Point"}
}