{
  "type": "Feature",
  "properties": {
    "addr:full":"65 Redcliffe Pde Redcliffe QLD 4020",
    "addr:housenumber":"65",
    "addr:postcode":"4020",
    "addr:street":"Redcliffe Pde",
    "iso:country":"AU",
    "sg:address":"65 Redcliffe Pde",
    "sg:city":"Redcliffe",
    "sg:classifiers":[
        {
            "category":"Health Services",
            "subcategory":"Doctor",
            "type":"Services"
        }
    ],
    "sg:phone":"+61 7 3284 5739",
    "sg:postcode":"4020",
    "sg:province":"QLD",
    "sg:tags":[
        "medical",
        "practitioner"
    ],
    "wof:name":"Calas Imre",
    "wof:placetype":"venue"
},
  "geometry": {"coordinates":[153.115295,-27.228279],"type":"Point"}
}