{
  "type": "Feature",
  "properties": {
    "addr:full":"282a Dorcas St South Melbourne VIC 3205",
    "addr:housenumber":"282a",
    "addr:postcode":"3205",
    "addr:street":"Dorcas St",
    "iso:country":"AU",
    "sg:address":"282a Dorcas St",
    "sg:city":"South Melbourne",
    "sg:classifiers":[
        {
            "category":"Banks & Credit Unions",
            "subcategory":"Investment Brokerage",
            "type":"Services"
        }
    ],
    "sg:phone":"+61 3 9696 3811",
    "sg:postcode":"3205",
    "sg:province":"VIC",
    "sg:tags":[
        "debt",
        "collection"
    ],
    "wof:name":"Credit Management Services",
    "wof:placetype":"venue"
},
  "geometry": {"coordinates":[144.95704699999999,-37.833881],"type":"Point"}
}