{
  "type": "Feature",
  "properties": {
    "addr:full":"35 High St Rushworth VIC 3612",
    "addr:housenumber":"35",
    "addr:postcode":"3612",
    "addr:street":"High St",
    "iso:country":"AU",
    "sg:address":"35 High St",
    "sg:city":"Rushworth",
    "sg:classifiers":[
        {
            "category":"Personal",
            "subcategory":"Beauty Salon",
            "type":"Services"
        }
    ],
    "sg:phone":"+61 3 5856 1500",
    "sg:postcode":"3612",
    "sg:province":"VIC",
    "sg:tags":[
        "hairdresser"
    ],
    "wof:name":"Hairitage on High",
    "wof:placetype":"venue"
},
  "geometry": {"coordinates":[145.01573181099999,-36.5878181458],"type":"Point"}
}