{
  "type": "Feature",
  "properties": {
    "iso:country":"AU",
    "sg:address":"99 Ryedale Rd",
    "sg:city":"West Ryde",
    "sg:classifiers":[
        {
            "category":"Shopping",
            "subcategory":"Computers & Home Electronics",
            "type":"Retail Goods"
        }
    ],
    "sg:phone":"+61 2 9809 5754",
    "sg:postcode":"2114",
    "sg:province":"NSW",
    "sg:tags":[
        "plate",
        "name"
    ],
    "wof:name":"Godfrey Engraving & Signs",
    "wof:placetype":"venue"
},
  "geometry": {"coordinates":[151.091552734,-33.8060150146],"type":"Point"}
}