{
  "type": "Feature",
  "properties": {
    "addr:full":"Cold & Wet Rd Coonalpyn SA 5265",
    "addr:postcode":"5265",
    "addr:street":"Rd",
    "iso:country":"AU",
    "sg:address":"Cold & Wet Rd",
    "sg:city":"Coonalpyn",
    "sg:classifiers":[
        {
            "category":"Farming",
            "subcategory":"Farm",
            "type":"Manufacturing & Wholesale Goods"
        }
    ],
    "sg:phone":"+61 8 8571 1061",
    "sg:postcode":"5265",
    "sg:province":"SA",
    "sg:tags":[
        "farmer"
    ],
    "wof:name":"Lutze K M & D B",
    "wof:placetype":"venue"
},
  "geometry": {"coordinates":[139.851944,-35.697697],"type":"Point"}
}