{
  "type": "Feature",
  "properties": {
    "addr:full":"Lvl 4, Building B, 35 Saunders St Pyrmont NSW 2009",
    "addr:housenumber":"building;35",
    "addr:postcode":"2009",
    "addr:street":"Saunders St",
    "iso:country":"AU",
    "sg:address":"Lvl 4, Building B, 35 Saunders St",
    "sg:city":"Pyrmont",
    "sg:classifiers":[
        {
            "category":"Food & Beverages",
            "subcategory":"Liquor & Beverages",
            "type":"Retail Goods"
        }
    ],
    "sg:phone":"+61 2 9563 2500",
    "sg:postcode":"2009",
    "sg:province":"NSW",
    "sg:tags":[
        "merchant",
        "spirit",
        "wine"
    ],
    "wof:name":"Cockfighter's Ghost",
    "wof:placetype":"venue"
},
  "geometry": {"coordinates":[151.19056701700001,-33.869808197],"type":"Point"}
}