{
  "type": "Feature",
  "properties": {
    "addr:full":"218 Spence St Cairns QLD 4870",
    "addr:housenumber":"218",
    "addr:postcode":"4870",
    "addr:street":"Spence St",
    "iso:country":"AU",
    "sg:address":"218 Spence St",
    "sg:city":"Cairns",
    "sg:classifiers":[
        {
            "category":"Retail",
            "subcategory":"Storage",
            "type":"Services"
        }
    ],
    "sg:phone":"+61 1800 003 838",
    "sg:postcode":"4870",
    "sg:province":"QLD",
    "sg:tags":[
        "removal",
        "furniture"
    ],
    "wof:name":"M.E.M Removals & Storage",
    "wof:placetype":"venue"
},
  "geometry": {"coordinates":[145.754394531,-16.9413528442],"type":"Point"}
}