{
  "type": "Feature",
  "properties": {
    "iso:country":"AU",
    "sg:address":"PO Box 9617",
    "sg:city":"Deakin",
    "sg:classifiers":[
        {
            "category":"Building & Trades",
            "subcategory":"Construction",
            "type":"Services"
        }
    ],
    "sg:phone":"+61 409 788 769",
    "sg:postcode":"2600",
    "sg:province":"ACT",
    "sg:tags":[
        "contractor"
    ],
    "wof:name":"Exclaim ! Construction Pty Ltd",
    "wof:placetype":"venue"
},
  "geometry": {"coordinates":[149.10842895499999,-35.314781189],"type":"Point"}
}