{
  "type": "Feature",
  "properties": {
    "iso:country":"AU",
    "sg:address":"PO Box 2460",
    "sg:city":"Whyalla Norrie",
    "sg:classifiers":[
        {
            "category":"Building & Trades",
            "subcategory":"Landscaping Services",
            "type":"Services"
        }
    ],
    "sg:phone":"+61 8 8644 1401",
    "sg:postcode":"5608",
    "sg:province":"SA",
    "sg:tags":[
        "designer",
        "landscape",
        "contractor"
    ],
    "wof:name":"Samscapes-Landscape Designer/Consultant",
    "wof:placetype":"venue"
},
  "geometry": {"coordinates":[137.551117,-33.029064],"type":"Point"}
}