{
  "type": "Feature",
  "properties": {
    "addr:full":"26 Hyandra St Griffith NSW 2680",
    "addr:housenumber":"26",
    "addr:postcode":"2680",
    "addr:street":"Hyandra St",
    "iso:country":"AU",
    "sg:address":"26 Hyandra St",
    "sg:city":"Griffith",
    "sg:classifiers":[
        {
            "category":"Building & Trades",
            "subcategory":"Plumbing",
            "type":"Services"
        }
    ],
    "sg:phone":"+61 2 6964 3226",
    "sg:postcode":"2680",
    "sg:province":"NSW",
    "sg:tags":[
        "plumber",
        "gasfitters"
    ],
    "wof:name":"A.C.E.",
    "wof:placetype":"venue"
},
  "geometry": {"coordinates":[146.051804,-34.28318],"type":"Point"}
}