{
  "type": "Feature",
  "properties": {
    "addr:full":"85 Finsbury St Newmarket QLD 4051",
    "addr:housenumber":"85",
    "addr:postcode":"4051",
    "addr:street":"Finsbury St",
    "iso:country":"AU",
    "sg:address":"85 Finsbury St",
    "sg:city":"Newmarket",
    "sg:classifiers":[
        {
            "category":"Building & Trades",
            "subcategory":"Construction",
            "type":"Services"
        }
    ],
    "sg:phone":"+61 7 3352 4111",
    "sg:postcode":"4051",
    "sg:province":"QLD",
    "sg:tags":[
        "contractor"
    ],
    "wof:name":"A.M.S. Constructions",
    "wof:placetype":"venue"
},
  "geometry": {"coordinates":[153.013504028,-27.4399585724],"type":"Point"}
}