{
  "type": "Feature",
  "properties": {
    "addr:full":"79 Edward St Kalbar QLD 4309",
    "addr:housenumber":"79",
    "addr:postcode":"4309",
    "addr:street":"Edward St",
    "iso:country":"AU",
    "sg:address":"79 Edward St",
    "sg:city":"Kalbar",
    "sg:classifiers":[
        {
            "category":"Food & Beverages",
            "subcategory":"Groceries & Convenience Stores",
            "type":"Retail Goods"
        }
    ],
    "sg:phone":"+61 7 5463 7230",
    "sg:postcode":"4309",
    "sg:province":"QLD",
    "wof:name":"Kalbar Supermarket",
    "wof:placetype":"venue"
},
  "geometry": {"coordinates":[152.62411499000001,-27.938539505],"type":"Point"}
}