{
  "type": "Feature",
  "properties": {
    "addr:full":"18 Thompson St Mayne QLD 4006",
    "addr:housenumber":"18",
    "addr:postcode":"4006",
    "addr:street":"Thompson St",
    "iso:country":"AU",
    "sg:address":"18 Thompson St",
    "sg:city":"Mayne",
    "sg:classifiers":[
        {
            "category":"Professional",
            "type":"Services"
        }
    ],
    "sg:phone":"+61 7 3000 5011",
    "sg:postcode":"4006",
    "sg:province":"QLD",
    "sg:tags":[
        "courier"
    ],
    "wof:name":"A And CBD Couriers",
    "wof:placetype":"venue"
},
  "geometry": {"coordinates":[153.04031372099999,-27.4413852692],"type":"Point"}
}