{
  "type": "Feature",
  "properties": {
    "addr:full":"1355 Albany Hwy Cannington WA 6107",
    "addr:housenumber":"1355",
    "addr:postcode":"6107",
    "addr:street":"Albany Hwy",
    "iso:country":"AU",
    "sg:address":"1355 Albany Hwy",
    "sg:city":"Cannington",
    "sg:classifiers":[
        {
            "category":"Sports & Exercise",
            "subcategory":"Gym",
            "type":"Entertainment"
        }
    ],
    "sg:phone":"+61 8 9451 5155",
    "sg:postcode":"6107",
    "sg:province":"WA",
    "sg:tags":[
        "health",
        "fitness"
    ],
    "wof:name":"Fitness First",
    "wof:placetype":"venue"
},
  "geometry": {"coordinates":[115.935050964,-32.0186424255],"type":"Point"}
}