{
  "type": "Feature",
  "properties": {
    "addr:full":"12 London Pl Grose Wold NSW 2753",
    "addr:housenumber":"12",
    "addr:postcode":"2753",
    "addr:street":"London Pl Grose",
    "iso:country":"AU",
    "sg:address":"12 London Pl",
    "sg:city":"Grose Wold",
    "sg:classifiers":[
        {
            "category":"Building & Trades",
            "subcategory":"Construction",
            "type":"Services"
        }
    ],
    "sg:phone":"+61 2 4572 1641",
    "sg:postcode":"2753",
    "sg:province":"NSW",
    "sg:tags":[
        "brick",
        "paving"
    ],
    "wof:name":"Sully's Landscapes",
    "wof:placetype":"venue"
},
  "geometry": {"coordinates":[150.68327331500001,-33.5989685059],"type":"Point"}
}