{
  "type": "Feature",
  "properties": {
    "addr:full":"95 Aquarium Ave Hemmant QLD 4174",
    "addr:postcode":"4174",
    "addr:street":"Aquarium Ave",
    "iso:country":"AU",
    "sg:address":"95 Aquarium Ave",
    "sg:city":"Hemmant",
    "sg:classifiers":[
        {
            "category":"Autos & Motor Vehicles",
            "subcategory":"Boat Sales",
            "type":"Retail Goods"
        }
    ],
    "sg:phone":"+61 412 705 858",
    "sg:postcode":"4174",
    "sg:province":"QLD",
    "sg:tags":[
        "builder",
        "yacht",
        "repairer"
    ],
    "wof:name":"Michael Brown Shipwrights Pty Ltd",
    "wof:placetype":"venue"
},
  "geometry": {"coordinates":[153.12690734899999,-27.4405441284],"type":"Point"}
}