{
  "type": "Feature",
  "properties": {
    "iso:country":"AU",
    "sg:address":"171 Grattan St",
    "sg:city":"Carlton",
    "sg:classifiers":[
        {
            "category":"Travel",
            "subcategory":"Hotels & Motels",
            "type":"Entertainment"
        }
    ],
    "sg:phone":"+61 1300 559 244",
    "sg:postcode":"3053",
    "sg:province":"VIC",
    "sg:tags":[
        "accommodation"
    ],
    "wof:name":"Best Western Travel Inn",
    "wof:placetype":"venue"
},
  "geometry": {"coordinates":[144.967163086,-37.8007545471],"type":"Point"}
}