{
  "type": "Feature",
  "properties": {
    "addr:full":"PO Box 3423 Putney NSW 2112",
    "addr:postcode":"2112",
    "iso:country":"AU",
    "sg:address":"PO Box 3423",
    "sg:city":"Putney",
    "sg:classifiers":[
        {
            "category":"Wholesale",
            "subcategory":"Apparel",
            "type":"Manufacturing & Wholesale Goods"
        }
    ],
    "sg:phone":"+61 2 9816 5722",
    "sg:postcode":"2112",
    "sg:province":"NSW",
    "sg:tags":[
        "wholesaler",
        "mfrs",
        "uniform"
    ],
    "wof:name":"Elite Uniforms P/L",
    "wof:placetype":"venue"
},
  "geometry": {"coordinates":[151.10887145999999,-33.8238182068],"type":"Point"}
}