{
  "type": "Feature",
  "properties": {
    "iso:country":"AU",
    "sg:address":"Meatworks Ave",
    "sg:city":"Oxford Falls",
    "sg:classifiers":[
        {
            "category":"Transit Center",
            "subcategory":"Freight",
            "type":"Transportation"
        }
    ],
    "sg:phone":"+61 2 9452 4003",
    "sg:postcode":"2100",
    "sg:province":"NSW",
    "sg:tags":[
        "weighbridge"
    ],
    "wof:name":"Numeve Pty Ltd",
    "wof:placetype":"venue"
},
  "geometry": {"coordinates":[151.24647522000001,-33.7348556519],"type":"Point"}
}