{
  "type": "Feature",
  "properties": {
    "addr:full":"Suite 1, 19 Bishop St Jolimont WA 6014",
    "addr:housenumber":"19",
    "addr:postcode":"6014",
    "addr:street":"Bishop St",
    "iso:country":"AU",
    "sg:address":"Suite 1, 19 Bishop St",
    "sg:city":"Jolimont",
    "sg:classifiers":[
        {
            "category":"Wholesale",
            "subcategory":"Auto Parts",
            "type":"Manufacturing & Wholesale Goods"
        }
    ],
    "sg:phone":"+61 8 9478 9200",
    "sg:postcode":"6014",
    "sg:province":"WA",
    "sg:tags":[
        "tyre"
    ],
    "wof:name":"Goodyear Earthmover Pty Ltd",
    "wof:placetype":"venue"
},
  "geometry": {"coordinates":[115.812538147,-31.9453735352],"type":"Point"}
}