{
  "type": "Feature",
  "properties": {
    "iso:country":"AU",
    "sg:address":"Mars St",
    "sg:city":"Revesby",
    "sg:classifiers":[
        {
            "category":"Education",
            "subcategory":"School",
            "type":"Public Place"
        }
    ],
    "sg:phone":"+61 2 9773 8886",
    "sg:postcode":"2212",
    "sg:province":"NSW",
    "sg:tags":[
        "state",
        "-",
        "nsw"
    ],
    "wof:name":"Revesby South Public School",
    "wof:placetype":"venue"
},
  "geometry": {"coordinates":[151.017426,-33.959541],"type":"Point"}
}