{
  "type": "Feature",
  "properties": {
    "iso:country":"AU",
    "sg:address":"367 Moorabool St",
    "sg:city":"Geelong South",
    "sg:classifiers":[
        {
            "category":"Autos & Motor Vehicles",
            "subcategory":"Fuel & Gas Station",
            "type":"Retail Goods"
        }
    ],
    "sg:phone":"+61 3 5221 6103",
    "sg:postcode":"3220",
    "sg:province":"VIC",
    "wof:name":"Apco Easy Shops",
    "wof:placetype":"venue"
},
  "geometry": {"coordinates":[144.355774,-38.158356],"type":"Point"}
}