{
  "type": "Feature",
  "properties": {
    "iso:country":"AU",
    "sg:address":"757 GlenHuntly Rd",
    "sg:city":"Caulfield South",
    "sg:classifiers":[
        {
            "category":"Home & Garden",
            "subcategory":"Home Furnishings",
            "type":"Retail Goods"
        }
    ],
    "sg:phone":"+61 3 9532 4347",
    "sg:postcode":"3162",
    "sg:province":"VIC",
    "sg:tags":[
        "wholesaler",
        "wallpaper",
        "mfrs",
        "wallcoverings"
    ],
    "wof:name":"Staab Decor Pty Ltd",
    "wof:placetype":"venue"
},
  "geometry": {"coordinates":[145.020996094,-37.8866233826],"type":"Point"}
}