{
  "type": "Feature",
  "properties": {
    "addr:full":"14 Monte St Slacks Creek QLD 4127",
    "addr:housenumber":"14",
    "addr:postcode":"4127",
    "addr:street":"Monte St",
    "iso:country":"AU",
    "sg:address":"14 Monte St",
    "sg:city":"Slacks Creek",
    "sg:classifiers":[
        {
            "category":"Retail",
            "subcategory":"Auto Repair",
            "type":"Services"
        }
    ],
    "sg:phone":"+61 7 3804 1865",
    "sg:postcode":"4127",
    "sg:province":"QLD",
    "sg:tags":[
        "beater",
        "painter",
        "panel"
    ],
    "sg:website":"http://www.dentdoctor.com.au",
    "wof:name":"Dent-Doctor",
    "wof:placetype":"venue"
},
  "geometry": {"coordinates":[153.117630005,-27.6232395172],"type":"Point"}
}