{
  "type": "Feature",
  "properties": {
    "addr:full":"5 Village Ave Doncaster VIC 3108",
    "addr:housenumber":"5",
    "addr:postcode":"3108",
    "addr:street":"Village Ave",
    "iso:country":"AU",
    "sg:address":"5 Village Ave",
    "sg:city":"Doncaster",
    "sg:classifiers":[
        {
            "category":"Fast Food",
            "type":"Food & Drink"
        }
    ],
    "sg:phone":"+61 3 9857 5506",
    "sg:postcode":"3108",
    "sg:province":"VIC",
    "sg:tags":[
        "away",
        "take"
    ],
    "wof:name":"West Doncaster Fish Shop",
    "wof:placetype":"venue"
},
  "geometry": {"coordinates":[145.10980224599999,-37.7820167542],"type":"Point"}
}