{
  "type": "Feature",
  "properties": {
    "iso:country":"AU",
    "sg:address":"222 Target Hill Rd",
    "sg:city":"Greenwith",
    "sg:classifiers":[
        {
            "category":"Fast Food",
            "type":"Food & Drink"
        }
    ],
    "sg:phone":"+61 8 8289 7622",
    "sg:postcode":"5125",
    "sg:province":"SA",
    "sg:tags":[
        "away",
        "take"
    ],
    "wof:name":"Chicken Jim",
    "wof:placetype":"venue"
},
  "geometry": {"coordinates":[138.71286000000001,-34.772034],"type":"Point"}
}