{
  "type": "Feature",
  "properties": {
    "iso:country":"AU",
    "sg:address":"Oliver St",
    "sg:city":"Heathcote",
    "sg:classifiers":[
        {
            "category":"Education",
            "subcategory":"School",
            "type":"Public Place"
        }
    ],
    "sg:phone":"+61 2 9520 8759",
    "sg:postcode":"2233",
    "sg:province":"NSW",
    "sg:tags":[
        "state",
        "-",
        "nsw"
    ],
    "wof:name":"Heathcote Public School",
    "wof:placetype":"venue"
},
  "geometry": {"coordinates":[151.00465393100001,-34.0853691101],"type":"Point"}
}