{
  "type": "Feature",
  "properties": {
    "addr:full":"61 Saxenwood Drv Doncaster VIC 3108",
    "addr:housenumber":"61",
    "addr:postcode":"3108",
    "addr:street":"Saxenwood Drv",
    "iso:country":"AU",
    "sg:address":"61 Saxenwood Drv",
    "sg:city":"Doncaster",
    "sg:classifiers":[
        {
            "category":"Farming",
            "subcategory":"Vineyard",
            "type":"Manufacturing & Wholesale Goods"
        }
    ],
    "sg:phone":"+61 3 9842 4800",
    "sg:postcode":"3108",
    "sg:province":"VIC",
    "sg:tags":[
        "winery"
    ],
    "wof:name":"Whitehill Wine Company",
    "wof:placetype":"venue"
},
  "geometry": {"coordinates":[145.15614318900001,-37.7802848816],"type":"Point"}
}