{
  "type": "Feature",
  "properties": {
    "addr:full":"Melville House, 35 Melville St Hobart TAS 7000",
    "addr:housenumber":"35",
    "addr:postcode":"7000",
    "addr:street":"Melville St",
    "iso:country":"AU",
    "sg:address":"Melville House, 35 Melville St",
    "sg:city":"Hobart",
    "sg:classifiers":[
        {
            "category":"Professional",
            "subcategory":"Computer Services",
            "type":"Services"
        }
    ],
    "sg:phone":"+61 3 6231 5338",
    "sg:postcode":"7000",
    "sg:province":"TAS",
    "sg:tags":[
        "package",
        "software"
    ],
    "wof:name":"Technology One Ltd",
    "wof:placetype":"venue"
},
  "geometry": {"coordinates":[147.32545471200001,-42.879196167],"type":"Point"}
}