{
  "type": "Feature",
  "properties": {
    "iso:country":"AU",
    "sg:address":"4 Mc Quade St",
    "sg:city":"Morwell",
    "sg:classifiers":[
        {
            "category":"Building & Trades",
            "subcategory":"Construction",
            "type":"Services"
        }
    ],
    "sg:phone":"+61 3 5133 0301",
    "sg:postcode":"3840",
    "sg:province":"VIC",
    "sg:tags":[
        "contractor"
    ],
    "wof:name":"Vartel Developments",
    "wof:placetype":"venue"
},
  "geometry": {"coordinates":[146.44692993199999,-38.2349662781],"type":"Point"}
}