{
  "type": "Feature",
  "properties": {
    "addr:full":"1251 Anzac Ave Kallangur QLD 4503",
    "addr:housenumber":"1251",
    "addr:postcode":"4503",
    "addr:street":"Anzac Ave",
    "iso:country":"AU",
    "sg:address":"1251 Anzac Ave",
    "sg:city":"Kallangur",
    "sg:classifiers":[
        {
            "category":"Retail",
            "subcategory":"Veterinary Services",
            "type":"Services"
        }
    ],
    "sg:phone":"+61 7 3889 0899",
    "sg:postcode":"4503",
    "sg:province":"QLD",
    "sg:tags":[
        "surgeon"
    ],
    "wof:name":"Anzac Avenue Veterinary Surgery",
    "wof:placetype":"venue"
},
  "geometry": {"coordinates":[152.99732971200001,-27.2496070862],"type":"Point"}
}