{
  "type": "Feature",
  "properties": {
    "addr:full":"69 Byron St Inverell NSW 2360",
    "addr:housenumber":"69",
    "addr:postcode":"2360",
    "addr:street":"Byron St",
    "iso:country":"AU",
    "sg:address":"69 Byron St",
    "sg:city":"Inverell",
    "sg:classifiers":[
        {
            "category":"Fast Food",
            "type":"Food & Drink"
        }
    ],
    "sg:phone":"+61 2 6722 2256",
    "sg:postcode":"2360",
    "sg:province":"NSW",
    "sg:tags":[
        "away",
        "take"
    ],
    "wof:name":"Inverell Palace",
    "wof:placetype":"venue"
},
  "geometry": {"coordinates":[151.11294555699999,-29.7727184296],"type":"Point"}
}