{
  "type": "Feature",
  "properties": {
    "iso:country":"AU",
    "sg:address":"Cnr Tapping & Quinns Rds",
    "sg:city":"Quinns Rocks",
    "sg:classifiers":[
        {
            "category":"Food & Beverages",
            "subcategory":"Supermarket",
            "type":"Retail Goods"
        }
    ],
    "sg:phone":"+61 8 9305 1644",
    "sg:postcode":"6030",
    "sg:province":"WA",
    "sg:tags":[
        "grocery",
        "store"
    ],
    "wof:name":"IGA Supermarkets",
    "wof:placetype":"venue"
},
  "geometry": {"coordinates":[115.70870208700001,-31.6726989746],"type":"Point"}
}