{
  "type": "Feature",
  "properties": {
    "addr:full":"8/96 Camberwell Rd Hawthorn East VIC 3123",
    "addr:housenumber":"/ 96",
    "addr:postcode":"3123",
    "addr:street":"Camberwell Rd",
    "iso:country":"AU",
    "sg:address":"8/96 Camberwell Rd",
    "sg:city":"Hawthorn East",
    "sg:classifiers":[
        {
            "category":"Professional",
            "subcategory":"Accounting & Tax Preparation",
            "type":"Services"
        }
    ],
    "sg:phone":"+61 3 9882 7074",
    "sg:postcode":"3123",
    "sg:province":"VIC",
    "sg:tags":[
        "consultant",
        "taxation"
    ],
    "wof:name":"Morris Roger J & Co",
    "wof:placetype":"venue"
},
  "geometry": {"coordinates":[145.05174255399999,-37.8272094727],"type":"Point"}
}