{
  "type": "Feature",
  "properties": {
    "addr:full":"Cnr Lytton & Northcote Sts East Brisbane QLD 4169",
    "addr:postcode":"4169",
    "addr:street":"Cnr",
    "iso:country":"AU",
    "sg:address":"Cnr Lytton & Northcote Sts",
    "sg:city":"East Brisbane",
    "sg:classifiers":[
        {
            "category":"Food & Beverages",
            "subcategory":"Supermarket",
            "type":"Retail Goods"
        }
    ],
    "sg:phone":"+61 7 3217 4844",
    "sg:postcode":"4169",
    "sg:province":"QLD",
    "sg:tags":[
        "grocery",
        "store"
    ],
    "wof:name":"Foodworks",
    "wof:placetype":"venue"
},
  "geometry": {"coordinates":[153.04457092300001,-27.4793872833],"type":"Point"}
}