{
  "type": "Feature",
  "properties": {
    "addr:full":"Dee Why Pde Dee Why NSW 2099",
    "addr:postcode":"2099",
    "addr:street":"Dee Why Pde",
    "iso:country":"AU",
    "sg:address":"Dee Why Pde",
    "sg:city":"Dee Why",
    "sg:classifiers":[
        {
            "category":"Building & Trades",
            "subcategory":"Locksmith",
            "type":"Services"
        }
    ],
    "sg:phone":"+61 410 520 724",
    "sg:postcode":"2099",
    "sg:province":"NSW",
    "sg:tags":[
        "lock"
    ],
    "wof:name":"Peninsula Locksmiths & Security P/L",
    "wof:placetype":"venue"
},
  "geometry": {"coordinates":[151.28904724099999,-33.7517318726],"type":"Point"}
}