{
  "type": "Feature",
  "properties": {
    "addr:full":"26 Ridge St North Sydney NSW 2060",
    "addr:housenumber":"26",
    "addr:postcode":"2060",
    "addr:street":"Ridge St",
    "iso:country":"AU",
    "sg:address":"26 Ridge St",
    "sg:city":"North Sydney",
    "sg:classifiers":[
        {
            "category":"Professional",
            "subcategory":"Art Services",
            "type":"Services"
        }
    ],
    "sg:phone":"+61 2 9956 6821",
    "sg:postcode":"2060",
    "sg:province":"NSW",
    "sg:tags":[
        "graphic",
        "designer"
    ],
    "wof:name":"Quality St Pty Ltd",
    "wof:placetype":"venue"
},
  "geometry": {"coordinates":[151.206542969,-33.8324584961],"type":"Point"}
}