{
  "type": "Feature",
  "properties": {
    "addr:full":"Suite 1 19 Tania St Sunshine North VIC 3020",
    "addr:housenumber":"19",
    "addr:postcode":"3020",
    "addr:street":"Tania St",
    "iso:country":"AU",
    "sg:address":"Suite 1 19 Tania St",
    "sg:city":"Sunshine North",
    "sg:classifiers":[
        {
            "category":"Professional",
            "subcategory":"Detective & Security Services",
            "type":"Services"
        }
    ],
    "sg:phone":"+61 3 9364 4006",
    "sg:postcode":"3020",
    "sg:province":"VIC",
    "sg:tags":[
        "guard",
        "patrol"
    ],
    "wof:name":"Henderson Security Ltd",
    "wof:placetype":"venue"
},
  "geometry": {"coordinates":[144.82926900000001,-37.758591],"type":"Point"}
}