{
  "type": "Feature",
  "properties": {
    "addr:full":"20 Railway St Taree NSW 2430",
    "addr:housenumber":"20",
    "addr:postcode":"2430",
    "addr:street":"Railway St",
    "iso:country":"AU",
    "sg:address":"20 Railway St",
    "sg:city":"Taree",
    "sg:classifiers":[
        {
            "category":"Building & Trades",
            "subcategory":"Equipment Rental",
            "type":"Services"
        }
    ],
    "sg:phone":"+61 2 6552 5795",
    "sg:postcode":"2430",
    "sg:province":"NSW",
    "sg:tags":[
        "party",
        "hire"
    ],
    "wof:name":"Jumping Castles For hire",
    "wof:placetype":"venue"
},
  "geometry": {"coordinates":[152.465744,-31.905146],"type":"Point"}
}