{
  "type": "Feature",
  "properties": {
    "addr:full":"3 - 9 Lusher Rd Croydon VIC 3136",
    "addr:housenumber":"9",
    "addr:postcode":"3136",
    "addr:street":"Lusher Rd",
    "iso:country":"AU",
    "sg:address":"3 - 9 Lusher Rd",
    "sg:city":"Croydon",
    "sg:classifiers":[
        {
            "category":"Retail",
            "subcategory":"Storage",
            "type":"Services"
        }
    ],
    "sg:phone":"+61 3 9723 7700",
    "sg:postcode":"3136",
    "sg:province":"VIC",
    "wof:name":"Croydon Self Storage",
    "wof:placetype":"venue"
},
  "geometry": {"coordinates":[145.279174805,-37.8003082275],"type":"Point"}
}