{
  "type": "Feature",
  "properties": {
    "addr:full":"5A Joyce St Scarborough WA 6019",
    "addr:housenumber":"5a",
    "addr:postcode":"6019",
    "addr:street":"Joyce St",
    "iso:country":"AU",
    "sg:address":"5A Joyce St",
    "sg:city":"Scarborough",
    "sg:classifiers":[
        {
            "category":"Health Services",
            "subcategory":"Health Practitioner",
            "type":"Services"
        }
    ],
    "sg:phone":"+61 8 9245 3838",
    "sg:postcode":"6019",
    "sg:province":"WA",
    "sg:tags":[
        "psychologist"
    ],
    "wof:name":"Zyron Krupenia",
    "wof:placetype":"venue"
},
  "geometry": {"coordinates":[115.764007568,-31.8897151947],"type":"Point"}
}