{
  "type": "Feature",
  "properties": {
    "iso:country":"AU",
    "sg:address":"10 Matilda Pl",
    "sg:city":"Tamworth",
    "sg:classifiers":[
        {
            "category":"Professional",
            "subcategory":"Art Services",
            "type":"Services"
        }
    ],
    "sg:phone":"+61 408 667 643",
    "sg:postcode":"2340",
    "sg:province":"NSW",
    "sg:tags":[
        "decorator",
        "painter"
    ],
    "wof:name":"Alderton N B & M T",
    "wof:placetype":"venue"
},
  "geometry": {"coordinates":[150.918792725,-31.1257801056],"type":"Point"}
}