{
  "type": "Feature",
  "properties": {
    "iso:country":"AU",
    "sg:address":"1 Parsons St",
    "sg:city":"Alice Springs",
    "sg:classifiers":[
        {
            "category":"Fast Food",
            "type":"Food & Drink"
        }
    ],
    "sg:phone":"+61 8 8953 6033",
    "sg:postcode":"0870",
    "sg:province":"NT",
    "sg:tags":[
        "away",
        "take"
    ],
    "wof:name":"Big Al's Diner & Takeaway",
    "wof:placetype":"venue"
},
  "geometry": {"coordinates":[133.879516602,-23.6972293854],"type":"Point"}
}