{
  "type": "Feature",
  "properties": {
    "addr:full":"7 Harold St Forbes NSW 2871",
    "addr:housenumber":"7",
    "addr:postcode":"2871",
    "addr:street":"Harold St",
    "iso:country":"AU",
    "sg:address":"7 Harold St",
    "sg:city":"Forbes",
    "sg:classifiers":[
        {
            "category":"Social Services",
            "subcategory":"Adult Care",
            "type":"Services"
        }
    ],
    "sg:phone":"+61 2 6852 4388",
    "sg:postcode":"2871",
    "sg:province":"NSW",
    "sg:tags":[
        "disadvantaged",
        "aid",
        "organisation",
        "group"
    ],
    "wof:name":"Home & Community Care Program (HACC)",
    "wof:placetype":"venue"
},
  "geometry": {"coordinates":[148.00744599999999,-33.386436],"type":"Point"}
}