{
  "type": "Feature",
  "properties": {
    "iso:country":"AU",
    "sg:address":"18 Cronulla St",
    "sg:city":"Cronulla",
    "sg:classifiers":[
        {
            "category":"Shopping",
            "subcategory":"Clothing, Apparel, & Fashions",
            "type":"Retail Goods"
        }
    ],
    "sg:phone":"+61 2 9523 2468",
    "sg:postcode":"2230",
    "sg:province":"NSW",
    "sg:tags":[
        "lady",
        "wear"
    ],
    "wof:name":"Flirty",
    "wof:placetype":"venue"
},
  "geometry": {"coordinates":[151.153030395,-34.0522537231],"type":"Point"}
}