{
  "type": "Feature",
  "properties": {
    "addr:full":"101- 103 Maud St Maroochydore QLD 4558",
    "addr:housenumber":"103",
    "addr:postcode":"4558",
    "addr:street":"Maud St",
    "iso:country":"AU",
    "sg:address":"101- 103 Maud St",
    "sg:city":"Maroochydore",
    "sg:classifiers":[
        {
            "category":"Home & Garden",
            "subcategory":"Carpets & Floor Coverings",
            "type":"Retail Goods"
        }
    ],
    "sg:phone":"+61 7 5475 4110",
    "sg:postcode":"4558",
    "sg:province":"QLD",
    "sg:tags":[
        "wood"
    ],
    "sg:website":"http://www.queenslandtimberflooring.com",
    "wof:name":"Queensland Timber Flooring",
    "wof:placetype":"venue"
},
  "geometry": {"coordinates":[153.09242248499999,-26.6648769379],"type":"Point"}
}