{
  "type": "Feature",
  "properties": {
    "iso:country":"AU",
    "sg:address":"26 Seddon St",
    "sg:city":"Bankstown",
    "sg:classifiers":[
        {
            "category":"Manufacturing",
            "subcategory":"Glass & Minerals",
            "type":"Manufacturing & Wholesale Goods"
        }
    ],
    "sg:phone":"+61 2 9708 0322",
    "sg:postcode":"2200",
    "sg:province":"NSW",
    "sg:tags":[
        "merchant",
        "granite",
        "marble"
    ],
    "wof:name":"Casa Marble Pty Ltd",
    "wof:placetype":"venue"
},
  "geometry": {"coordinates":[151.03587300000001,-33.930061],"type":"Point"}
}