{
  "type": "Feature",
  "properties": {
    "addr:full":"Units 4 & 5, 65 Collingwood St Osborne Park WA 6017",
    "addr:housenumber":"units 4 &;65",
    "addr:postcode":"6017",
    "addr:street":"5;Collingwood St",
    "iso:country":"AU",
    "sg:address":"Units 4 & 5, 65 Collingwood St",
    "sg:city":"Osborne Park",
    "sg:classifiers":[
        {
            "category":"Wholesale",
            "subcategory":"Furniture",
            "type":"Manufacturing & Wholesale Goods"
        }
    ],
    "sg:phone":"+61 8 9204 5755",
    "sg:postcode":"6017",
    "sg:province":"WA",
    "sg:tags":[
        "wholesaler",
        "mfrs"
    ],
    "wof:name":"Pilgrim Furniture",
    "wof:placetype":"venue"
},
  "geometry": {"coordinates":[115.81754303,-31.9047374725],"type":"Point"}
}