{
  "type": "Feature",
  "properties": {
    "addr:full":"14 Jesmond Rd Croydon VIC 3136",
    "addr:housenumber":"14",
    "addr:postcode":"3136",
    "addr:street":"Jesmond Rd",
    "iso:country":"AU",
    "sg:address":"14 Jesmond Rd",
    "sg:city":"Croydon",
    "sg:classifiers":[
        {
            "category":"Manufacturing",
            "subcategory":"Retail Goods",
            "type":"Manufacturing & Wholesale Goods"
        }
    ],
    "sg:phone":"+61 3 9722 8888",
    "sg:postcode":"3136",
    "sg:province":"VIC",
    "sg:tags":[
        "merchant",
        "pump",
        "mfrs"
    ],
    "wof:name":"Pomona Pumps Pty Ltd",
    "wof:placetype":"venue"
},
  "geometry": {"coordinates":[145.28302001899999,-37.8061218262],"type":"Point"}
}