{
  "type": "Feature",
  "properties": {
    "addr:full":"5/ 17 Bellevue Park Rd Bellevue Hill NSW 2023",
    "addr:housenumber":"/ 17",
    "addr:postcode":"2023",
    "addr:street":"Bellevue Park Rd",
    "iso:country":"AU",
    "sg:address":"5/ 17 Bellevue Park Rd",
    "sg:city":"Bellevue Hill",
    "sg:classifiers":[
        {
            "category":"Home & Garden",
            "subcategory":"Carpets & Floor Coverings",
            "type":"Retail Goods"
        }
    ],
    "sg:phone":"+61 416 248 649",
    "sg:postcode":"2023",
    "sg:province":"NSW",
    "sg:tags":[
        "layer"
    ],
    "wof:name":"Him-a-Layer",
    "wof:placetype":"venue"
},
  "geometry": {"coordinates":[151.25982665999999,-33.8875579834],"type":"Point"}
}