{
  "type": "Feature",
  "properties": {
    "iso:country":"AU",
    "sg:address":"Isaac Smith St",
    "sg:city":"Kingsford",
    "sg:classifiers":[
        {
            "category":"Real Estate",
            "subcategory":"Surveying",
            "type":"Services"
        }
    ],
    "sg:phone":"+61 2 9663 1832",
    "sg:postcode":"2032",
    "sg:province":"NSW",
    "sg:tags":[
        "surveyor",
        "land"
    ],
    "wof:name":"Cochrane & Associates",
    "wof:placetype":"venue"
},
  "geometry": {"coordinates":[151.22154235799999,-33.9268417358],"type":"Point"}
}