{
  "type": "Feature",
  "properties": {
    "iso:country":"AU",
    "sg:address":"Lvl4/ 26 Wharf St",
    "sg:city":"Brisbane",
    "sg:classifiers":[
        {
            "category":"Real Estate",
            "subcategory":"Developer",
            "type":"Services"
        }
    ],
    "sg:phone":"+61 7 3831 0831",
    "sg:postcode":"4000",
    "sg:province":"QLD",
    "sg:tags":[
        "development"
    ],
    "wof:name":"Norris Corporation",
    "wof:placetype":"venue"
},
  "geometry": {"coordinates":[153.03010559099999,-27.4673233032],"type":"Point"}
}