{
  "type": "Feature",
  "properties": {
    "addr:full":"Bapaume Rd Moorebank NSW 2170",
    "addr:postcode":"2170",
    "addr:street":"Bapaume Rd",
    "iso:country":"AU",
    "sg:address":"Bapaume Rd",
    "sg:city":"Moorebank",
    "sg:classifiers":[
        {
            "category":"Manufacturing",
            "subcategory":"Electronics",
            "type":"Manufacturing & Wholesale Goods"
        }
    ],
    "sg:phone":"+61 2 9821 0111",
    "sg:postcode":"2170",
    "sg:province":"NSW",
    "sg:tags":[
        "industrial",
        "capacitor"
    ],
    "wof:name":"ABB",
    "wof:placetype":"venue"
},
  "geometry": {"coordinates":[150.92433166500001,-33.942779541],"type":"Point"}
}