{
  "type": "Feature",
  "properties": {
    "addr:full":"276 Pacific Hwy Hornsby NSW 2077",
    "addr:housenumber":"276",
    "addr:postcode":"2077",
    "addr:street":"Pacific Hwy",
    "iso:country":"AU",
    "sg:address":"276 Pacific Hwy",
    "sg:city":"Hornsby",
    "sg:classifiers":[
        {
            "category":"Fast Food",
            "type":"Food & Drink"
        }
    ],
    "sg:phone":"+61 2 9482 4994",
    "sg:postcode":"2077",
    "sg:province":"NSW",
    "sg:tags":[
        "away",
        "take"
    ],
    "wof:name":"Fish & Chips Hornsby",
    "wof:placetype":"venue"
},
  "geometry": {"coordinates":[151.09791564899999,-33.6975860596],"type":"Point"}
}