{
  "type": "Feature",
  "properties": {
    "iso:country":"AU",
    "sg:address":"Suite 151/ 149 Pyrmont St",
    "sg:city":"Darling Harbour",
    "sg:classifiers":[
        {
            "category":"School Buses",
            "type":"Transportation"
        }
    ],
    "sg:phone":"+61 2 9798 9373",
    "sg:postcode":"2000",
    "sg:province":"NSW",
    "sg:tags":[
        "nanny"
    ],
    "wof:name":"My Little Friend",
    "wof:placetype":"venue"
},
  "geometry": {"coordinates":[151.197067261,-33.8731307983],"type":"Point"}
}