{
  "type": "Feature",
  "properties": {
    "iso:country":"AU",
    "sg:address":"1 Du Rietz Crt",
    "sg:city":"Gympie",
    "sg:classifiers":[
        {
            "category":"Retail",
            "subcategory":"Auto Repair",
            "type":"Services"
        }
    ],
    "sg:phone":"+61 7 5482 7077",
    "sg:postcode":"4570",
    "sg:province":"QLD",
    "sg:tags":[
        "repairer",
        "motor",
        "engineer"
    ],
    "wof:name":"L C Automotive",
    "wof:placetype":"venue"
},
  "geometry": {"coordinates":[152.64216613799999,-26.2057189941],"type":"Point"}
}