{
  "type": "Feature",
  "properties": {
    "iso:country":"AU",
    "sg:address":"72 Kyabram St",
    "sg:city":"Coolaroo",
    "sg:classifiers":[
        {
            "category":"Retail",
            "subcategory":"Storage",
            "type":"Services"
        }
    ],
    "sg:phone":"+61 3 9302 3799",
    "sg:postcode":"3048",
    "sg:province":"VIC",
    "sg:tags":[
        "removal",
        "furniture"
    ],
    "wof:name":"Myers Self Storage",
    "wof:placetype":"venue"
},
  "geometry": {"coordinates":[144.936081,-37.658558],"type":"Point"}
}