{
  "type": "Feature",
  "properties": {
    "addr:full":"Lvl 8 / 621 Pacific Hwy St Leonards NSW 2065",
    "addr:housenumber":"/ 621",
    "addr:postcode":"2065",
    "addr:street":"Pacific Hwy",
    "iso:country":"AU",
    "sg:address":"Lvl 8 / 621 Pacific Hwy",
    "sg:city":"St Leonards",
    "sg:classifiers":[
        {
            "category":"Communications",
            "subcategory":"Film & Video Production",
            "type":"Services"
        }
    ],
    "sg:phone":"+61 2 9906 8818",
    "sg:postcode":"2065",
    "sg:province":"NSW",
    "sg:tags":[
        "consultant",
        "material",
        "handling"
    ],
    "sg:website":"http://www.hmide.com",
    "wof:name":"HM Industrial Design Engineers Pty Ltd",
    "wof:placetype":"venue"
},
  "geometry": {"coordinates":[151.19670105,-33.8233757019],"type":"Point"}
}