{
  "type": "Feature",
  "properties": {
    "addr:full":"646 Glenferrie Rd Hawthorn VIC 3122",
    "addr:housenumber":"646",
    "addr:postcode":"3122",
    "addr:street":"Glenferrie Rd",
    "iso:country":"AU",
    "sg:address":"646 Glenferrie Rd",
    "sg:city":"Hawthorn",
    "sg:classifiers":[
        {
            "category":"Shopping",
            "subcategory":"Clothing, Apparel, & Fashions",
            "type":"Retail Goods"
        }
    ],
    "sg:phone":"+61 3 9819 9646",
    "sg:postcode":"3122",
    "sg:province":"VIC",
    "sg:tags":[
        "lady",
        "wear"
    ],
    "wof:name":"Zilla",
    "wof:placetype":"venue"
},
  "geometry": {"coordinates":[145.035614014,-37.8220596313],"type":"Point"}
}