{
  "type": "Feature",
  "properties": {
    "addr:full":"90 Bell St Coburg VIC 3058",
    "addr:housenumber":"90",
    "addr:postcode":"3058",
    "addr:street":"Bell St",
    "iso:country":"AU",
    "sg:address":"90 Bell St",
    "sg:city":"Coburg",
    "sg:classifiers":[
        {
            "category":"Building & Trades",
            "subcategory":"Landscaping Services",
            "type":"Services"
        }
    ],
    "sg:phone":"+61 3 9240 2214",
    "sg:postcode":"3058",
    "sg:province":"VIC",
    "sg:tags":[
        "consultant"
    ],
    "wof:name":"Moreland Building Surveying",
    "wof:placetype":"venue"
},
  "geometry": {"coordinates":[144.96572875999999,-37.7413711548],"type":"Point"}
}