{
  "type": "Feature",
  "properties": {
    "addr:full":"RSD 17 Railton Rd Deloraine TAS 7304",
    "addr:housenumber":"17",
    "addr:postcode":"7304",
    "addr:street":"Railton Rd",
    "iso:country":"AU",
    "sg:address":"RSD 17 Railton Rd",
    "sg:city":"Deloraine",
    "sg:classifiers":[
        {
            "category":"Farming",
            "subcategory":"Dairy Farm",
            "type":"Manufacturing & Wholesale Goods"
        }
    ],
    "sg:phone":"+61 3 6368 1227",
    "sg:postcode":"7304",
    "sg:province":"TAS",
    "sg:tags":[
        "wholesaler",
        "product",
        "mfrs"
    ],
    "wof:name":"Elgaar Farm",
    "wof:placetype":"venue"
},
  "geometry": {"coordinates":[146.54246499999999,-41.463703],"type":"Point"}
}