{
  "type": "Feature",
  "properties": {
    "addr:full":"North St Georgetown QLD 4871",
    "addr:postcode":"4871",
    "addr:street":"North St",
    "iso:country":"AU",
    "sg:address":"North St",
    "sg:city":"Georgetown",
    "sg:classifiers":[
        {
            "category":"Government",
            "subcategory":"Department Of Motor Vehicles",
            "type":"Public Place"
        }
    ],
    "sg:phone":"+61 7 4062 1122",
    "sg:postcode":"4871",
    "sg:province":"QLD",
    "sg:tags":[
        "organisation",
        "local"
    ],
    "wof:name":"State Emergency Service",
    "wof:placetype":"venue"
},
  "geometry": {"coordinates":[143.54649352999999,-18.2898006439],"type":"Point"}
}