{
  "type": "Feature",
  "properties": {
    "addr:full":"PO Box 761 Stirling SA 5152",
    "addr:postcode":"5152",
    "iso:country":"AU",
    "sg:address":"PO Box 761",
    "sg:city":"Stirling",
    "sg:classifiers":[
        {
            "category":"Professional",
            "subcategory":"Art Services",
            "type":"Services"
        }
    ],
    "sg:phone":"+61 8 8339 6644",
    "sg:postcode":"5152",
    "sg:province":"SA",
    "sg:tags":[
        "interior",
        "decorator"
    ],
    "wof:name":"d.Lineate",
    "wof:placetype":"venue"
},
  "geometry": {"coordinates":[138.72253418,-35.0080490112],"type":"Point"}
}