{
  "type": "Feature",
  "properties": {
    "addr:full":"22 Frederick St Croydon VIC 3136",
    "addr:housenumber":"22",
    "addr:postcode":"3136",
    "addr:street":"Frederick St",
    "iso:country":"AU",
    "sg:address":"22 Frederick St",
    "sg:city":"Croydon",
    "sg:classifiers":[
        {
            "category":"Education",
            "subcategory":"Kindergarten",
            "type":"Public Place"
        }
    ],
    "sg:phone":"+61 3 9725 0498",
    "sg:postcode":"3136",
    "sg:province":"VIC",
    "sg:tags":[
        "pre-schools"
    ],
    "wof:name":"Croydon Gums Kindergarten Incorporated",
    "wof:placetype":"venue"
},
  "geometry": {"coordinates":[145.28541564899999,-37.8084831238],"type":"Point"}
}