{
  "type": "Feature",
  "properties": {
    "addr:full":"27 Quirk St Dee Why NSW 2099",
    "addr:housenumber":"27",
    "addr:postcode":"2099",
    "addr:street":"Quirk St",
    "iso:country":"AU",
    "sg:address":"27 Quirk St",
    "sg:city":"Dee Why",
    "sg:classifiers":[
        {
            "category":"Shopping",
            "subcategory":"Computers & Home Electronics",
            "type":"Retail Goods"
        }
    ],
    "sg:phone":"+61 2 9971 7177",
    "sg:postcode":"2099",
    "sg:province":"NSW",
    "sg:tags":[
        "detector",
        "electronic"
    ],
    "wof:name":"Aquatek",
    "wof:placetype":"venue"
},
  "geometry": {"coordinates":[151.28613281200001,-33.7590942383],"type":"Point"}
}