{
  "type": "Feature",
  "properties": {
    "addr:full":"29 Burgess Rd Bayswater North VIC 3153",
    "addr:housenumber":"29",
    "addr:postcode":"3153",
    "addr:street":"Burgess Rd",
    "iso:country":"AU",
    "sg:address":"29 Burgess Rd",
    "sg:city":"Bayswater North",
    "sg:classifiers":[
        {
            "category":"Retail",
            "subcategory":"Auto Repair",
            "type":"Services"
        }
    ],
    "sg:phone":"+61 3 9720 1008",
    "sg:postcode":"3153",
    "sg:province":"VIC",
    "sg:tags":[
        "beater",
        "painter",
        "panel"
    ],
    "wof:name":"Ron Hume Body Works",
    "wof:placetype":"venue"
},
  "geometry": {"coordinates":[145.28904724099999,-37.82188797],"type":"Point"}
}