{
  "type": "Feature",
  "properties": {
    "addr:full":"Shop 5/ 151 William St Devonport TAS 7310",
    "addr:housenumber":"shop 5 / 151",
    "addr:postcode":"7310",
    "addr:street":"William St",
    "iso:country":"AU",
    "sg:address":"Shop 5/ 151 William St",
    "sg:city":"Devonport",
    "sg:classifiers":[
        {
            "category":"Personal",
            "subcategory":"Beauty Salon",
            "type":"Services"
        }
    ],
    "sg:phone":"+61 3 6424 6232",
    "sg:postcode":"7310",
    "sg:province":"TAS",
    "sg:tags":[
        "hairdresser"
    ],
    "wof:name":"Hair Odyssey",
    "wof:placetype":"venue"
},
  "geometry": {"coordinates":[146.35096740700001,-41.1760978699],"type":"Point"}
}