{
  "type": "Feature",
  "properties": {
    "addr:full":"261- 265 Ballarat Rd Sunshine VIC 3020",
    "addr:housenumber":"265",
    "addr:postcode":"3020",
    "addr:street":"Ballarat Rd",
    "iso:country":"AU",
    "sg:address":"261- 265 Ballarat Rd",
    "sg:city":"Sunshine",
    "sg:classifiers":[
        {
            "category":"Autos & Motor Vehicles",
            "subcategory":"Auto Supplies",
            "type":"Retail Goods"
        }
    ],
    "sg:phone":"+61 3 9310 2020",
    "sg:postcode":"3020",
    "sg:province":"VIC",
    "sg:tags":[
        "battery",
        "automotive"
    ],
    "wof:name":"The Tyre Factory",
    "wof:placetype":"venue"
},
  "geometry": {"coordinates":[144.83471700000001,-37.777603],"type":"Point"}
}