{
  "type": "Feature",
  "properties": {
    "addr:full":"Shop 3 Terrace Arcade, Marine Terrace Geraldton WA 6530",
    "addr:housenumber":"shop 3",
    "addr:postcode":"6530",
    "addr:street":"Terrace Arcade Marine Terrace",
    "iso:country":"AU",
    "sg:address":"Shop 3 Terrace Arcade, Marine Terrace",
    "sg:city":"Geraldton",
    "sg:classifiers":[
        {
            "category":"Manufacturing",
            "subcategory":"Jewelry",
            "type":"Manufacturing & Wholesale Goods"
        }
    ],
    "sg:phone":"+61 8 9921 7007",
    "sg:postcode":"6530",
    "sg:province":"WA",
    "sg:tags":[
        "designer",
        "jewellery"
    ],
    "wof:name":"Verity Jewellers",
    "wof:placetype":"venue"
},
  "geometry": {"coordinates":[114.61161041299999,-28.7707767487],"type":"Point"}
}