{
  "type": "Feature",
  "properties": {
    "addr:full":"1 Simon St Underwood QLD 4119",
    "addr:housenumber":"1",
    "addr:postcode":"4119",
    "addr:street":"Simon St",
    "iso:country":"AU",
    "sg:address":"1 Simon St",
    "sg:city":"Underwood",
    "sg:classifiers":[
        {
            "category":"Professional",
            "subcategory":"Computer Services",
            "type":"Services"
        }
    ],
    "sg:phone":"+61 7 3341 5223",
    "sg:postcode":"4119",
    "sg:province":"QLD",
    "sg:tags":[
        "repairs",
        "upgrade",
        "equipment"
    ],
    "wof:name":"Computer Maintenance (DC)",
    "wof:placetype":"venue"
},
  "geometry": {"coordinates":[153.111083984,-27.5995922089],"type":"Point"}
}