{
  "type": "Feature",
  "properties": {
    "addr:full":"59 Sea Pde Port MacDonnell SA 5291",
    "addr:housenumber":"59",
    "addr:postcode":"5291",
    "addr:street":"Sea Pde",
    "iso:country":"AU",
    "sg:address":"59 Sea Pde",
    "sg:city":"Port MacDonnell",
    "sg:classifiers":[
        {
            "category":"Government",
            "subcategory":"Post Office",
            "type":"Public Place"
        }
    ],
    "sg:phone":"+61 8 8738 2085",
    "sg:postcode":"5291",
    "sg:province":"SA",
    "sg:tags":[
        "postal"
    ],
    "wof:name":"Australia Post",
    "wof:placetype":"venue"
},
  "geometry": {"coordinates":[140.69998200000001,-38.054302],"type":"Point"}
}