{
  "type": "Feature",
  "properties": {
    "addr:full":"87 Bishopsgate St Carlisle WA 6101",
    "addr:housenumber":"87",
    "addr:postcode":"6101",
    "addr:street":"Bishopsgate St",
    "iso:country":"AU",
    "sg:address":"87 Bishopsgate St",
    "sg:city":"Carlisle",
    "sg:classifiers":[
        {
            "category":"Health Services",
            "subcategory":"Health Practitioner",
            "type":"Services"
        }
    ],
    "sg:phone":"+61 8 9361 3477",
    "sg:postcode":"6101",
    "sg:province":"WA",
    "sg:tags":[
        "physiotherapist"
    ],
    "wof:name":"Archer St Physiotherapy Centre",
    "wof:placetype":"venue"
},
  "geometry": {"coordinates":[115.91216278100001,-31.9777889252],"type":"Point"}
}