{
  "type": "Feature",
  "properties": {
    "addr:full":"Spring St Mortlake VIC 3272",
    "addr:postcode":"3272",
    "addr:street":"Spring St",
    "iso:country":"AU",
    "sg:address":"Spring St",
    "sg:city":"Mortlake",
    "sg:classifiers":[
        {
            "category":"Commercial Area",
            "type":"Public Place"
        }
    ],
    "sg:phone":"+61 3 5599 2005",
    "sg:postcode":"3272",
    "sg:province":"VIC",
    "sg:tags":[
        "heavy",
        "carrier"
    ],
    "wof:name":"Cathcart Transport Industries",
    "wof:placetype":"venue"
},
  "geometry": {"coordinates":[142.80609130900001,-38.0834121704],"type":"Point"}
}