{
  "type": "Feature",
  "properties": {
    "iso:country":"AU",
    "sg:address":"Wellington Business Centre, Suite 17, 2",
    "sg:city":"Portrush Rd, Payneham",
    "sg:classifiers":[
        {
            "category":"Communications",
            "subcategory":"Film & Video Production",
            "type":"Services"
        }
    ],
    "sg:phone":"+61 8 8336 3544",
    "sg:postcode":"5070",
    "sg:province":"SA",
    "sg:tags":[
        "fan",
        "blower"
    ],
    "wof:name":"ZIEHL-ebm Australia Pty Ltd",
    "wof:placetype":"venue"
},
  "geometry": {"coordinates":[138.63929748499999,-34.8966178894],"type":"Point"}
}