{
  "type": "Feature",
  "properties": {
    "addr:full":"Sankeys Rd Skyrings Creek QLD 4568",
    "addr:postcode":"4568",
    "addr:street":"Sankeys Rd Skyrings",
    "iso:country":"AU",
    "sg:address":"Sankeys Rd",
    "sg:city":"Skyrings Creek",
    "sg:classifiers":[
        {
            "category":"Farming",
            "subcategory":"Farm",
            "type":"Manufacturing & Wholesale Goods"
        }
    ],
    "sg:phone":"+61 7 5485 1236",
    "sg:postcode":"4568",
    "sg:province":"QLD",
    "sg:tags":[
        "farmer"
    ],
    "wof:name":"Rose D R & A U",
    "wof:placetype":"venue"
},
  "geometry": {"coordinates":[152.813232422,-26.3769207001],"type":"Point"}
}