{
  "type": "Feature",
  "properties": {
    "addr:full":"Constitution Ave Reid ACT 2612",
    "addr:postcode":"2612",
    "addr:street":"Constitution Ave",
    "iso:country":"AU",
    "sg:address":"Constitution Ave",
    "sg:city":"Reid",
    "sg:classifiers":[
        {
            "category":"Cafe",
            "type":"Food & Drink"
        }
    ],
    "sg:phone":"+61 2 6207 3196",
    "sg:postcode":"2612",
    "sg:province":"ACT",
    "wof:name":"Cafe @ Cit",
    "wof:placetype":"venue"
},
  "geometry": {"coordinates":[149.13656616200001,-35.2864952087],"type":"Point"}
}