{
  "type": "Feature",
  "properties": {
    "addr:full":"243 Gladstone Rd Dutton Park QLD 4102",
    "addr:housenumber":"243",
    "addr:postcode":"4102",
    "addr:street":"Gladstone Rd",
    "iso:country":"AU",
    "sg:address":"243 Gladstone Rd",
    "sg:city":"Dutton Park",
    "sg:classifiers":[
        {
            "category":"Education",
            "subcategory":"School",
            "type":"Public Place"
        }
    ],
    "sg:phone":"+61 7 3033 7000",
    "sg:postcode":"4102",
    "sg:province":"QLD",
    "sg:tags":[
        "girl"
    ],
    "sg:website":"http://www.bne.catholic.edu.au",
    "wof:name":"Brisbane Catholic Education",
    "wof:placetype":"venue"
},
  "geometry": {"coordinates":[153.02218627900001,-27.493719101],"type":"Point"}
}