{
  "type": "Feature",
  "properties": {
    "addr:full":"11 Fennell St Parramatta NSW 2150",
    "addr:housenumber":"11",
    "addr:postcode":"2150",
    "addr:street":"Fennell St",
    "iso:country":"AU",
    "sg:address":"11 Fennell St",
    "sg:city":"Parramatta",
    "sg:classifiers":[
        {
            "category":"Banks & Credit Unions",
            "subcategory":"Financial Services",
            "type":"Services"
        }
    ],
    "sg:phone":"+61 1300 362 062",
    "sg:postcode":"2150",
    "sg:province":"NSW",
    "sg:tags":[
        "franchising"
    ],
    "wof:name":"Franchise Developments",
    "wof:placetype":"venue"
},
  "geometry": {"coordinates":[151.00814819300001,-33.8057899475],"type":"Point"}
}