{
  "type": "Feature",
  "properties": {
    "addr:full":"2502 Toodyay Rd Gidgegannup WA 6083",
    "addr:housenumber":"2502",
    "addr:postcode":"6083",
    "addr:street":"Toodyay Rd",
    "iso:country":"AU",
    "sg:address":"2502 Toodyay Rd",
    "sg:city":"Gidgegannup",
    "sg:classifiers":[
        {
            "category":"Building & Trades",
            "subcategory":"Landscaping Services",
            "type":"Services"
        }
    ],
    "sg:phone":"+61 8 9574 6114",
    "sg:postcode":"6083",
    "sg:province":"WA",
    "sg:tags":[
        "grazier"
    ],
    "wof:name":"Slater K Maxwell",
    "wof:placetype":"venue"
},
  "geometry": {"coordinates":[116.23548126199999,-31.7698440552],"type":"Point"}
}