{
  "type": "Feature",
  "properties": {
    "addr:full":"16 Galatea St Diamond Creek VIC 3089",
    "addr:housenumber":"16",
    "addr:postcode":"3089",
    "addr:street":"Galatea St",
    "iso:country":"AU",
    "sg:address":"16 Galatea St",
    "sg:city":"Diamond Creek",
    "sg:classifiers":[
        {
            "category":"Shopping",
            "subcategory":"Music",
            "type":"Retail Goods"
        }
    ],
    "sg:phone":"+61 3 9438 3760",
    "sg:postcode":"3089",
    "sg:province":"VIC",
    "sg:tags":[
        "instrument",
        "musical"
    ],
    "wof:name":"Diamond Valley Woodwind Centre",
    "wof:placetype":"venue"
},
  "geometry": {"coordinates":[145.14956699999999,-37.675285],"type":"Point"}
}