{
  "type": "Feature",
  "properties": {
    "addr:full":"Unit 16, 170 North Rd Woodridge QLD 4114",
    "addr:housenumber":"170",
    "addr:postcode":"4114",
    "addr:street":"North Rd",
    "iso:country":"AU",
    "sg:address":"Unit 16, 170 North Rd",
    "sg:city":"Woodridge",
    "sg:classifiers":[
        {
            "category":"Professional",
            "subcategory":"Accounting & Tax Preparation",
            "type":"Services"
        }
    ],
    "sg:phone":"+61 7 3209 1000",
    "sg:postcode":"4114",
    "sg:province":"QLD",
    "sg:tags":[
        "consultant",
        "taxation"
    ],
    "wof:name":"Integritax Accountants",
    "wof:placetype":"venue"
},
  "geometry": {"coordinates":[153.10479736299999,-27.620967865],"type":"Point"}
}