{
  "type": "Feature",
  "properties": {
    "addr:full":"100 Keelindi Rd Bellbird NSW 2325",
    "addr:housenumber":"100",
    "addr:postcode":"2325",
    "addr:street":"Keelindi Rd",
    "iso:country":"AU",
    "sg:address":"100 Keelindi Rd",
    "sg:city":"Bellbird",
    "sg:classifiers":[
        {
            "category":"Personal",
            "subcategory":"Beauty Salon",
            "type":"Services"
        }
    ],
    "sg:phone":"+61 409 907 261",
    "sg:postcode":"2325",
    "sg:province":"NSW",
    "sg:tags":[
        "supply",
        "artist",
        "make-up"
    ],
    "wof:name":"Make-Up (Professional) Julie Thompson",
    "wof:placetype":"venue"
},
  "geometry": {"coordinates":[151.331130981,-32.8498725891],"type":"Point"}
}