{
  "type": "Feature",
  "properties": {
    "iso:country":"AU",
    "sg:address":"1378 Pacific Hwy",
    "sg:city":"Bonville",
    "sg:classifiers":[
        {
            "category":"Home & Garden",
            "subcategory":"Garden Supply",
            "type":"Retail Goods"
        }
    ],
    "sg:phone":"+61 439 977 144",
    "sg:postcode":"2441",
    "sg:province":"NSW",
    "sg:tags":[
        "landscape"
    ],
    "wof:name":"The Sleeper King",
    "wof:placetype":"venue"
},
  "geometry": {"coordinates":[153.032455,-30.386751],"type":"Point"}
}