{
  "type": "Feature",
  "properties": {
    "iso:country":"AU",
    "sg:address":"337 Forest Rd",
    "sg:city":"Bexley",
    "sg:classifiers":[
        {
            "category":"Professional",
            "subcategory":"Accounting & Tax Preparation",
            "type":"Services"
        }
    ],
    "sg:phone":"+61 2 9597 7886",
    "sg:postcode":"2207",
    "sg:province":"NSW",
    "sg:tags":[
        "accountant",
        "auditor"
    ],
    "wof:name":"George Stivactas & Associates",
    "wof:placetype":"venue"
},
  "geometry": {"coordinates":[151.124542,-33.951626],"type":"Point"}
}