{
  "type": "Feature",
  "properties": {
    "iso:country":"AU",
    "sg:address":"Unit 1",
    "sg:city":"/ Fisherman&#039;s Wharf Darwin",
    "sg:classifiers":[
        {
            "category":"Professional",
            "subcategory":"Engineering",
            "type":"Services"
        }
    ],
    "sg:phone":"+61 8 8981 6566",
    "sg:postcode":"0800",
    "sg:province":"NT",
    "sg:tags":[
        "diesel",
        "engineer"
    ],
    "wof:name":"D.M.E.S",
    "wof:placetype":"venue"
},
  "geometry": {"coordinates":[130.84231567399999,-12.4620399475],"type":"Point"}
}