{
  "type": "Feature",
  "properties": {
    "iso:country":"AU",
    "sg:address":"Orthla Ave",
    "sg:city":"Heidelberg West",
    "sg:classifiers":[
        {
            "category":"Retail",
            "subcategory":"Auto Repair",
            "type":"Services"
        }
    ],
    "sg:phone":"+61 3 9459 9677",
    "sg:postcode":"3081",
    "sg:province":"VIC",
    "sg:tags":[
        "repairer",
        "motor",
        "engineer"
    ],
    "wof:name":"Bill Gordon Motors",
    "wof:placetype":"venue"
},
  "geometry": {"coordinates":[145.04527282699999,-37.7325820923],"type":"Point"}
}