{
  "type": "Feature",
  "properties": {
    "addr:full":"68 Maude St Shepparton VIC 3630",
    "addr:housenumber":"68",
    "addr:postcode":"3630",
    "addr:street":"Maude St",
    "iso:country":"AU",
    "sg:address":"68 Maude St",
    "sg:city":"Shepparton",
    "sg:classifiers":[
        {
            "category":"Health Services",
            "subcategory":"Doctor",
            "type":"Services"
        }
    ],
    "sg:phone":"+61 3 5821 7766",
    "sg:postcode":"3630",
    "sg:province":"VIC",
    "sg:tags":[
        "medical",
        "practitioner"
    ],
    "wof:name":"Brendan Pitts Dr",
    "wof:placetype":"venue"
},
  "geometry": {"coordinates":[145.402267456,-36.3730888367],"type":"Point"}
}