{
  "type": "Feature",
  "properties": {
    "iso:country":"AU",
    "sg:address":"61 Burns Pde",
    "sg:city":"Chapel Hill",
    "sg:classifiers":[
        {
            "category":"Retail",
            "subcategory":"Auto Rental",
            "type":"Services"
        }
    ],
    "sg:phone":"+61 407 144 041",
    "sg:postcode":"4069",
    "sg:province":"QLD",
    "sg:tags":[
        "chauffeur",
        "car",
        "hire",
        "driven",
        "limousine"
    ],
    "wof:name":"Acclaim Limousines",
    "wof:placetype":"venue"
},
  "geometry": {"coordinates":[152.952560425,-27.5129146576],"type":"Point"}
}