{
  "type": "Feature",
  "properties": {
    "addr:full":"Level 9 , 135 Wickham Tce Brisbane QLD 4000",
    "addr:housenumber":"135",
    "addr:postcode":"4000",
    "addr:street":"Wickham Tce",
    "iso:country":"AU",
    "sg:address":"Level 9 , 135 Wickham Tce",
    "sg:city":"Brisbane",
    "sg:classifiers":[
        {
            "category":"Health Services",
            "subcategory":"Health Practitioner",
            "type":"Services"
        }
    ],
    "sg:phone":"+61 7 3831 4452",
    "sg:postcode":"4000",
    "sg:province":"QLD",
    "sg:tags":[
        "psychologist"
    ],
    "sg:website":"http://www.brisbanecounsellingcentre.com.au",
    "wof:name":"Brisbane Counselling Centre",
    "wof:placetype":"venue"
},
  "geometry": {"coordinates":[153.02549743599999,-27.4646282196],"type":"Point"}
}