{
  "type": "Feature",
  "properties": {
    "iso:country":"AU",
    "sg:address":"81 Beresford Ave",
    "sg:city":"Greenacre",
    "sg:classifiers":[
        {
            "category":"Retail",
            "subcategory":"Auto Repair",
            "type":"Services"
        }
    ],
    "sg:phone":"+61 2 9790 5361",
    "sg:postcode":"2190",
    "sg:province":"NSW",
    "sg:tags":[
        "electrical"
    ],
    "wof:name":"Greenacre Auto Electrical",
    "wof:placetype":"venue"
},
  "geometry": {"coordinates":[151.039413,-33.904137],"type":"Point"}
}