{
  "type": "Feature",
  "properties": {
    "addr:full":"6/ 49 Palmerston Rd Hornsby NSW 2077",
    "addr:housenumber":"/ 49",
    "addr:postcode":"2077",
    "addr:street":"Palmerston Rd",
    "iso:country":"AU",
    "sg:address":"6/ 49 Palmerston Rd",
    "sg:city":"Hornsby",
    "sg:classifiers":[
        {
            "category":"Personal",
            "type":"Services"
        }
    ],
    "sg:phone":"+61 403 069 486",
    "sg:postcode":"2077",
    "sg:province":"NSW",
    "sg:tags":[
        "career",
        "counselling"
    ],
    "wof:name":"Wearne Karel",
    "wof:placetype":"venue"
},
  "geometry": {"coordinates":[151.111129761,-33.7027931213],"type":"Point"}
}