{
  "type": "Feature",
  "properties": {
    "addr:full":"221 Crown St Wollongong NSW 2500",
    "addr:housenumber":"221",
    "addr:postcode":"2500",
    "addr:street":"Crown St",
    "iso:country":"AU",
    "sg:address":"221 Crown St",
    "sg:city":"Wollongong",
    "sg:classifiers":[
        {
            "category":"Fast Food",
            "type":"Food & Drink"
        }
    ],
    "sg:phone":"+61 2 4229 7925",
    "sg:postcode":"2500",
    "sg:province":"NSW",
    "sg:tags":[
        "away",
        "take"
    ],
    "wof:name":"Subway Wollongong City",
    "wof:placetype":"venue"
},
  "geometry": {"coordinates":[150.892776,-34.425011],"type":"Point"}
}