{
  "type": "Feature",
  "properties": {
    "addr:full":"250 Anzac Hwy Plympton SA 5038",
    "addr:housenumber":"250",
    "addr:postcode":"5038",
    "addr:street":"Anzac Hwy",
    "iso:country":"AU",
    "sg:address":"250 Anzac Hwy",
    "sg:city":"Plympton",
    "sg:classifiers":[
        {
            "category":"Travel",
            "subcategory":"Travel Agent",
            "type":"Entertainment"
        }
    ],
    "sg:phone":"+61 8 8371 5540",
    "sg:postcode":"5038",
    "sg:province":"SA",
    "sg:tags":[
        "consultant"
    ],
    "wof:name":"Specialised Travel",
    "wof:placetype":"venue"
},
  "geometry": {"coordinates":[138.558303833,-34.9619407654],"type":"Point"}
}