{
  "type": "Feature",
  "properties": {
    "addr:full":"107 Norton St Leichhardt NSW 2040",
    "addr:housenumber":"107",
    "addr:postcode":"2040",
    "addr:street":"Norton St",
    "iso:country":"AU",
    "sg:address":"107 Norton St",
    "sg:city":"Leichhardt",
    "sg:classifiers":[
        {
            "category":"Government",
            "subcategory":"City Hall",
            "type":"Public Place"
        }
    ],
    "sg:phone":"+61 2 9367 9222",
    "sg:postcode":"2040",
    "sg:province":"NSW",
    "wof:name":"Leichhardt Town Hall",
    "wof:placetype":"venue"
},
  "geometry": {"coordinates":[151.15718100000001,-33.883518],"type":"Point"}
}