{
  "type": "Feature",
  "properties": {
    "addr:full":"87-97 Gunnedah Rd Tamworth NSW 2340",
    "addr:housenumber":"87-97",
    "addr:postcode":"2340",
    "addr:street":"Gunnedah Rd",
    "iso:country":"AU",
    "sg:address":"87-97 Gunnedah Rd",
    "sg:city":"Tamworth",
    "sg:classifiers":[
        {
            "category":"Autos & Motor Vehicles",
            "subcategory":"Automobile Sales",
            "type":"Retail Goods"
        }
    ],
    "sg:phone":"+61 2 6768 3111",
    "sg:postcode":"2340",
    "sg:province":"NSW",
    "sg:tags":[
        "car",
        "new"
    ],
    "wof:name":"Peel Valley Motors",
    "wof:placetype":"venue"
},
  "geometry": {"coordinates":[150.900314331,-31.0989017487],"type":"Point"}
}