{
  "type": "Feature",
  "properties": {
    "addr:full":"Lot 7/ 269 Warraba Rd The Branch NSW 2425",
    "addr:housenumber":"7 / 269",
    "addr:postcode":"2425",
    "addr:street":"Warraba Rd",
    "iso:country":"AU",
    "sg:address":"Lot 7/ 269 Warraba Rd",
    "sg:city":"The Branch",
    "sg:classifiers":[
        {
            "category":"Retail",
            "subcategory":"Laundry & Dry Cleaning",
            "type":"Services"
        }
    ],
    "sg:phone":"+61 2 4997 6776",
    "sg:postcode":"2425",
    "sg:province":"NSW",
    "sg:tags":[
        "breeder",
        "alpaca",
        "llama"
    ],
    "wof:name":"Carinya Park Alpaca Stud",
    "wof:placetype":"venue"
},
  "geometry": {"coordinates":[151.998947144,-32.5340385437],"type":"Point"}
}