{
  "type": "Feature",
  "properties": {
    "addr:full":"20 Parramatta Rd Lidcombe NSW 2141",
    "addr:housenumber":"20",
    "addr:postcode":"2141",
    "addr:street":"Parramatta Rd",
    "iso:country":"AU",
    "sg:address":"20 Parramatta Rd",
    "sg:city":"Lidcombe",
    "sg:classifiers":[
        {
            "category":"Utilities",
            "subcategory":"Telephone",
            "type":"Services"
        }
    ],
    "sg:phone":"+61 2 9647 3333",
    "sg:postcode":"2141",
    "sg:province":"NSW",
    "sg:tags":[
        "installation",
        "system",
        "maintenance"
    ],
    "wof:name":"ABC-NU Teck Communications",
    "wof:placetype":"venue"
},
  "geometry": {"coordinates":[151.05892944300001,-33.8536605835],"type":"Point"}
}