{
  "type": "Feature",
  "properties": {
    "addr:full":"14-16 Tasma St North Hobart TAS 7000",
    "addr:housenumber":"14-16",
    "addr:postcode":"7000",
    "addr:street":"Tasma St",
    "iso:country":"AU",
    "sg:address":"14-16 Tasma St",
    "sg:city":"North Hobart",
    "sg:classifiers":[
        {
            "category":"Home & Garden",
            "subcategory":"Furniture",
            "type":"Retail Goods"
        }
    ],
    "sg:phone":"+61 3 6231 3077",
    "sg:postcode":"7000",
    "sg:province":"TAS",
    "sg:tags":[
        "business"
    ],
    "wof:name":"Interlink Workspace",
    "wof:placetype":"venue"
},
  "geometry": {"coordinates":[147.32044982900001,-42.8748321533],"type":"Point"}
}