{
  "type": "Feature",
  "properties": {
    "addr:full":"295 Buckley St Essendon VIC 3040",
    "addr:housenumber":"295",
    "addr:postcode":"3040",
    "addr:street":"Buckley St",
    "iso:country":"AU",
    "sg:address":"295 Buckley St",
    "sg:city":"Essendon",
    "sg:classifiers":[
        {
            "category":"Personal",
            "subcategory":"Beauty Salon",
            "type":"Services"
        }
    ],
    "sg:phone":"+61 3 9337 7904",
    "sg:postcode":"3040",
    "sg:province":"VIC",
    "sg:tags":[
        "hairdresser"
    ],
    "wof:name":"Chai Hairdressing",
    "wof:placetype":"venue"
},
  "geometry": {"coordinates":[144.90159606899999,-37.7553977966],"type":"Point"}
}