{
  "type": "Feature",
  "properties": {
    "addr:full":"6 Pegasus Ave Eatons Hill QLD 4037",
    "addr:housenumber":"6",
    "addr:postcode":"4037",
    "addr:street":"Pegasus Ave",
    "iso:country":"AU",
    "sg:address":"6 Pegasus Ave",
    "sg:city":"Eatons Hill",
    "sg:classifiers":[
        {
            "category":"Building & Trades",
            "subcategory":"Cleaning & Sanitation",
            "type":"Services"
        }
    ],
    "sg:phone":"+61 7 3325 2266",
    "sg:postcode":"4037",
    "sg:province":"QLD",
    "sg:tags":[
        "industrial",
        "commercial",
        "contractor"
    ],
    "wof:name":"Bayet Cleaning Services",
    "wof:placetype":"venue"
},
  "geometry": {"coordinates":[152.952057,-27.339499],"type":"Point"}
}