{
  "type": "Feature",
  "properties": {
    "addr:full":"146a Daws Rd Melrose Park SA 5039",
    "addr:housenumber":"146a",
    "addr:postcode":"5039",
    "addr:street":"Daws Rd",
    "iso:country":"AU",
    "sg:address":"146a Daws Rd",
    "sg:city":"Melrose Park",
    "sg:classifiers":[
        {
            "category":"Manufacturing",
            "subcategory":"Metals",
            "type":"Manufacturing & Wholesale Goods"
        }
    ],
    "sg:phone":"+61 8 8277 1199",
    "sg:postcode":"5039",
    "sg:province":"SA",
    "sg:tags":[
        "fabricator",
        "aluminium"
    ],
    "wof:name":"Kingswood Aluminium Pty Ltd",
    "wof:placetype":"venue"
},
  "geometry": {"coordinates":[138.581207275,-34.9923286438],"type":"Point"}
}