{
  "type": "Feature",
  "properties": {
    "addr:full":"647 Waterdale Rd Heidelberg West VIC 3081",
    "addr:housenumber":"647",
    "addr:postcode":"3081",
    "addr:street":"Waterdale Rd",
    "iso:country":"AU",
    "sg:address":"647 Waterdale Rd",
    "sg:city":"Heidelberg West",
    "sg:classifiers":[
        {
            "category":"Retail",
            "subcategory":"Auto Repair",
            "type":"Services"
        }
    ],
    "sg:phone":"+61 3 9459 3222",
    "sg:postcode":"3081",
    "sg:province":"VIC",
    "sg:tags":[
        "clutch",
        "brake"
    ],
    "wof:name":"ABS",
    "wof:placetype":"venue"
},
  "geometry": {"coordinates":[145.04913330100001,-37.733505249],"type":"Point"}
}