{
  "type": "Feature",
  "properties": {
    "addr:full":"1 Lakeshore Ave Chain Valley Bay NSW 2259",
    "addr:housenumber":"1",
    "addr:postcode":"2259",
    "addr:street":"Lakeshore Ave",
    "iso:country":"AU",
    "sg:address":"1 Lakeshore Ave",
    "sg:city":"Chain Valley Bay",
    "sg:classifiers":[
        {
            "category":"Education",
            "subcategory":"Special Training",
            "type":"Public Place"
        }
    ],
    "sg:phone":"+61 2 9144 6080",
    "sg:postcode":"2259",
    "sg:province":"NSW",
    "sg:tags":[
        "development"
    ],
    "wof:name":"Bembridge Consulting Pty Ltd",
    "wof:placetype":"venue"
},
  "geometry": {"coordinates":[151.556518555,-33.1676025391],"type":"Point"}
}