{
  "type": "Feature",
  "properties": {
    "addr:full":"1a Cambridge Rd Bellerive TAS 7018",
    "addr:housenumber":"1a",
    "addr:postcode":"7018",
    "addr:street":"Cambridge Rd",
    "iso:country":"AU",
    "sg:address":"1a Cambridge Rd",
    "sg:city":"Bellerive",
    "sg:classifiers":[
        {
            "category":"Professional",
            "subcategory":"Accounting & Tax Preparation",
            "type":"Services"
        }
    ],
    "sg:phone":"+61 3 6244 3700",
    "sg:postcode":"7018",
    "sg:province":"TAS",
    "sg:tags":[
        "consultant",
        "taxation"
    ],
    "wof:name":"Scanlon Alastair",
    "wof:placetype":"venue"
},
  "geometry": {"coordinates":[147.365509033,-42.8744621277],"type":"Point"}
}