{
  "type": "Feature",
  "properties": {
    "addr:full":"56 Woolshed St Bordertown SA 5268",
    "addr:housenumber":"56",
    "addr:postcode":"5268",
    "addr:street":"Woolshed St",
    "iso:country":"AU",
    "sg:address":"56 Woolshed St",
    "sg:city":"Bordertown",
    "sg:classifiers":[
        {
            "category":"Shopping",
            "subcategory":"Clothing, Apparel, & Fashions",
            "type":"Retail Goods"
        }
    ],
    "sg:phone":"+61 8 8752 1110",
    "sg:postcode":"5268",
    "sg:province":"SA",
    "sg:tags":[
        "boutique"
    ],
    "wof:name":"Sharp Fashions",
    "wof:placetype":"venue"
},
  "geometry": {"coordinates":[140.77371199999999,-36.311115],"type":"Point"}
}