{
  "type": "Feature",
  "properties": {
    "addr:full":"10 Somerset Pl Prospect TAS 7250",
    "addr:housenumber":"10",
    "addr:postcode":"7250",
    "addr:street":"Somerset Pl Prospect",
    "iso:country":"AU",
    "sg:address":"10 Somerset Pl",
    "sg:city":"Prospect",
    "sg:classifiers":[
        {
            "category":"Utilities",
            "subcategory":"Electric",
            "type":"Services"
        }
    ],
    "sg:phone":"+61 3 6340 1059",
    "sg:postcode":"7250",
    "sg:province":"TAS",
    "sg:tags":[
        "electrical",
        "contractor"
    ],
    "wof:name":"Schipper J W & A J Electrical Contractors",
    "wof:placetype":"venue"
},
  "geometry": {"coordinates":[147.115478516,-41.4782714844],"type":"Point"}
}