{
  "type": "Feature",
  "properties": {
    "addr:full":"PO Box 103 Castlecrag NSW 2068",
    "addr:postcode":"2068",
    "iso:country":"AU",
    "sg:address":"PO Box 103",
    "sg:city":"Castlecrag",
    "sg:classifiers":[
        {
            "category":"Banks & Credit Unions",
            "subcategory":"Bank",
            "type":"Services"
        }
    ],
    "sg:phone":"+61 416 296 212",
    "sg:postcode":"2068",
    "sg:province":"NSW",
    "sg:tags":[
        "broker",
        "mortgage"
    ],
    "wof:name":"G J & Associates",
    "wof:placetype":"venue"
},
  "geometry": {"coordinates":[151.21209716800001,-33.8023986816],"type":"Point"}
}