{
  "type": "Feature",
  "properties": {
    "addr:full":"777 Priestdale Rd Priestdale QLD 4127",
    "addr:housenumber":"777",
    "addr:postcode":"4127",
    "addr:street":"Priestdale Rd",
    "iso:country":"AU",
    "sg:address":"777 Priestdale Rd",
    "sg:city":"Priestdale",
    "sg:classifiers":[
        {
            "category":"Building & Trades",
            "subcategory":"Construction",
            "type":"Services"
        }
    ],
    "sg:phone":"+61 7 3341 1278",
    "sg:postcode":"4127",
    "sg:province":"QLD",
    "sg:tags":[
        "contractor"
    ],
    "wof:name":"Timms R",
    "wof:placetype":"venue"
},
  "geometry": {"coordinates":[153.153640747,-27.5914707184],"type":"Point"}
}