{
  "type": "Feature",
  "properties": {
    "addr:full":"68 Neill St Beaufort VIC 3373",
    "addr:housenumber":"68",
    "addr:postcode":"3373",
    "addr:street":"Neill St",
    "iso:country":"AU",
    "sg:address":"68 Neill St",
    "sg:city":"Beaufort",
    "sg:classifiers":[
        {
            "category":"Shopping",
            "subcategory":"Jewelry",
            "type":"Retail Goods"
        }
    ],
    "sg:phone":"+61 3 5349 2533",
    "sg:postcode":"3373",
    "sg:province":"VIC",
    "sg:tags":[
        "jeweller"
    ],
    "wof:name":"Vintage Jewellers",
    "wof:placetype":"venue"
},
  "geometry": {"coordinates":[143.381881714,-37.4295043945],"type":"Point"}
}