{
  "type": "Feature",
  "properties": {
    "iso:country":"AU",
    "sg:address":"78 Albert St",
    "sg:city":"Taree",
    "sg:classifiers":[
        {
            "category":"Health Services",
            "subcategory":"Doctor",
            "type":"Services"
        }
    ],
    "sg:phone":"+61 2 6552 5533",
    "sg:postcode":"2430",
    "sg:province":"NSW",
    "sg:tags":[
        "medical",
        "practitioner"
    ],
    "wof:name":"Albert St Medical Centre",
    "wof:placetype":"venue"
},
  "geometry": {"coordinates":[152.461685,-31.910654],"type":"Point"}
}