{
  "type": "Feature",
  "properties": {
    "addr:full":"26 Howell Ave Matraville NSW 2036",
    "addr:housenumber":"26",
    "addr:postcode":"2036",
    "addr:street":"Howell Ave",
    "iso:country":"AU",
    "sg:address":"26 Howell Ave",
    "sg:city":"Matraville",
    "sg:classifiers":[
        {
            "category":"Home & Garden",
            "subcategory":"Carpets & Floor Coverings",
            "type":"Retail Goods"
        }
    ],
    "sg:phone":"+61 2 9311 0044",
    "sg:postcode":"2036",
    "sg:province":"NSW",
    "sg:tags":[
        "tile",
        "wall",
        "layer"
    ],
    "wof:name":"Astra Constructions Pty Ltd",
    "wof:placetype":"venue"
},
  "geometry": {"coordinates":[151.23565673799999,-33.955619812],"type":"Point"}
}