{
  "type": "Feature",
  "properties": {
    "addr:full":"41 Agnes Ave Queanbeyan ACT 2620",
    "addr:housenumber":"41",
    "addr:postcode":"2620",
    "addr:street":"Agnes Ave",
    "iso:country":"AU",
    "sg:address":"41 Agnes Ave",
    "sg:city":"Queanbeyan",
    "sg:classifiers":[
        {
            "category":"Retail",
            "subcategory":"Driving School",
            "type":"Services"
        }
    ],
    "sg:phone":"+61 401 242 595",
    "sg:postcode":"2620",
    "sg:province":"ACT",
    "wof:name":"Charlies Learn To Drive",
    "wof:placetype":"venue"
},
  "geometry": {"coordinates":[149.22247314399999,-35.351436615],"type":"Point"}
}