{
  "type": "Feature",
  "properties": {
    "iso:country":"AU",
    "sg:address":"2 Hogbin Drv",
    "sg:city":"Coffs Harbour",
    "sg:classifiers":[
        {
            "category":"Professional",
            "subcategory":"Management & Consulting",
            "type":"Services"
        }
    ],
    "sg:phone":"+61 2 6658 8199",
    "sg:postcode":"2450",
    "sg:province":"NSW",
    "sg:tags":[
        "consultant",
        "business"
    ],
    "wof:name":"Coffs Harbour Innovation Centre",
    "wof:placetype":"venue"
},
  "geometry": {"coordinates":[153.10369900000001,-30.321123],"type":"Point"}
}