{
  "type": "Feature",
  "properties": {
    "addr:full":"467 Pacific Hwy Belmont NSW 2280",
    "addr:housenumber":"467",
    "addr:postcode":"2280",
    "addr:street":"Pacific Hwy",
    "iso:country":"AU",
    "sg:address":"467 Pacific Hwy",
    "sg:city":"Belmont",
    "sg:classifiers":[
        {
            "category":"Autos & Motor Vehicles",
            "subcategory":"Fuel & Gas Station",
            "type":"Retail Goods"
        }
    ],
    "sg:phone":"+61 2 4945 8232",
    "sg:postcode":"2280",
    "sg:province":"NSW",
    "wof:name":"Caltex",
    "wof:placetype":"venue"
},
  "geometry": {"coordinates":[151.660598755,-33.0312614441],"type":"Point"}
}