{
  "type": "Feature",
  "properties": {
    "addr:full":"184 Dowling St Dungog NSW 2420",
    "addr:housenumber":"184",
    "addr:postcode":"2420",
    "addr:street":"Dowling St",
    "iso:country":"AU",
    "sg:address":"184 Dowling St",
    "sg:city":"Dungog",
    "sg:classifiers":[
        {
            "category":"Food & Beverages",
            "subcategory":"Supermarket",
            "type":"Retail Goods"
        }
    ],
    "sg:phone":"+61 2 4992 1988",
    "sg:postcode":"2420",
    "sg:province":"NSW",
    "sg:tags":[
        "grocery",
        "store"
    ],
    "wof:name":"Dungog IGA Everyday Supermarket",
    "wof:placetype":"venue"
},
  "geometry": {"coordinates":[151.75767500000001,-32.400814],"type":"Point"}
}