{
  "type": "Feature",
  "properties": {
    "addr:full":"174 Majura Ave Ainslie ACT 2602",
    "addr:housenumber":"174",
    "addr:postcode":"2602",
    "addr:street":"Majura Ave",
    "iso:country":"AU",
    "sg:address":"174 Majura Ave",
    "sg:city":"Ainslie",
    "sg:classifiers":[
        {
            "category":"Shopping",
            "type":"Retail Goods"
        }
    ],
    "sg:phone":"+61 2 6112 8614",
    "sg:postcode":"2602",
    "sg:province":"ACT",
    "sg:tags":[
        "equipment",
        "safety",
        "accessory"
    ],
    "wof:name":"Safe-T-Test",
    "wof:placetype":"venue"
},
  "geometry": {"coordinates":[149.15162658700001,-35.2522544861],"type":"Point"}
}