{
  "type": "Feature",
  "properties": {
    "addr:full":"2/ 216 Turner St Port Melbourne VIC 3207",
    "addr:housenumber":"/ 216",
    "addr:postcode":"3207",
    "addr:street":"Turner St",
    "iso:country":"AU",
    "sg:address":"2/ 216 Turner St",
    "sg:city":"Port Melbourne",
    "sg:classifiers":[
        {
            "category":"Wholesale",
            "subcategory":"Apparel",
            "type":"Manufacturing & Wholesale Goods"
        }
    ],
    "sg:phone":"+61 3 9676 2877",
    "sg:postcode":"3207",
    "sg:province":"VIC",
    "sg:tags":[
        "wholesaler",
        "mfrs",
        "uniform"
    ],
    "wof:name":"Dimension Corporate Pty Ltd",
    "wof:placetype":"venue"
},
  "geometry": {"coordinates":[144.933258,-37.8241],"type":"Point"}
}