{
  "type": "Feature",
  "properties": {
    "addr:full":"171 Murray St Tanunda SA 5352",
    "addr:housenumber":"171",
    "addr:postcode":"5352",
    "addr:street":"Murray St",
    "iso:country":"AU",
    "sg:address":"171 Murray St",
    "sg:city":"Tanunda",
    "sg:classifiers":[
        {
            "category":"Health Services",
            "subcategory":"Chiropractor",
            "type":"Services"
        }
    ],
    "sg:phone":"+61 8 8563 2216",
    "sg:postcode":"5352",
    "sg:province":"SA",
    "wof:name":"Nitschke Darryl",
    "wof:placetype":"venue"
},
  "geometry": {"coordinates":[138.969284058,-34.5170707703],"type":"Point"}
}