{
  "type": "Feature",
  "properties": {
    "iso:country":"AU",
    "sg:address":"PO Box 1093",
    "sg:city":"Bakery Hill",
    "sg:classifiers":[
        {
            "category":"Building & Trades",
            "subcategory":"Construction",
            "type":"Services"
        }
    ],
    "sg:phone":"+61 439 727 650",
    "sg:postcode":"3354",
    "sg:province":"VIC",
    "sg:tags":[
        "contractor"
    ],
    "wof:name":"D & T Building Contractors Pty Ltd",
    "wof:placetype":"venue"
},
  "geometry": {"coordinates":[143.863708,-37.56332],"type":"Point"}
}