{
  "type": "Feature",
  "properties": {
    "addr:full":"120 Norton St Leichhardt NSW 2040",
    "addr:housenumber":"120",
    "addr:postcode":"2040",
    "addr:street":"Norton St",
    "iso:country":"AU",
    "sg:address":"120 Norton St",
    "sg:city":"Leichhardt",
    "sg:classifiers":[
        {
            "category":"Real Estate",
            "subcategory":"Real Estate Agent",
            "type":"Services"
        }
    ],
    "sg:phone":"+61 2 9550 0400",
    "sg:postcode":"2040",
    "sg:province":"NSW",
    "wof:name":"Cammareri V Real Estate",
    "wof:placetype":"venue"
},
  "geometry": {"coordinates":[151.156937,-33.884041],"type":"Point"}
}