{
  "type": "Feature",
  "properties": {
    "addr:full":"22 Teton Crt Highett VIC 3190",
    "addr:housenumber":"22",
    "addr:postcode":"3190",
    "addr:street":"Teton Crt",
    "iso:country":"AU",
    "sg:address":"22 Teton Crt",
    "sg:city":"Highett",
    "sg:classifiers":[
        {
            "category":"Professional",
            "subcategory":"Art Services",
            "type":"Services"
        }
    ],
    "sg:phone":"+61 3 9555 9494",
    "sg:postcode":"3190",
    "sg:province":"VIC",
    "sg:tags":[
        "work",
        "metal"
    ],
    "wof:name":"Don Sheil Of Australia Pty Ltd",
    "wof:placetype":"venue"
},
  "geometry": {"coordinates":[145.05364990199999,-37.9478263855],"type":"Point"}
}