{
  "type": "Feature",
  "properties": {
    "iso:country":"AU",
    "sg:address":"5 Majtlis St",
    "sg:city":"Blackburn North",
    "sg:classifiers":[
        {
            "category":"Health Services",
            "subcategory":"Medical Lab",
            "type":"Services"
        }
    ],
    "sg:phone":"+61 3 9898 5241",
    "sg:postcode":"3130",
    "sg:province":"VIC",
    "sg:tags":[
        "laboratory",
        "dental"
    ],
    "wof:name":"Mackay Colin A Dental Laboratory",
    "wof:placetype":"venue"
},
  "geometry": {"coordinates":[145.14222717300001,-37.8064117432],"type":"Point"}
}