{
  "type": "Feature",
  "properties": {
    "iso:country":"AU",
    "sg:address":"Ipswich Mall Shp 242 Nicholas St",
    "sg:city":"Ipswich",
    "sg:classifiers":[
        {
            "category":"Manufacturing",
            "subcategory":"Jewelry",
            "type":"Manufacturing & Wholesale Goods"
        }
    ],
    "sg:phone":"+61 7 3281 6800",
    "sg:postcode":"4305",
    "sg:province":"QLD",
    "sg:tags":[
        "mfrg",
        "jeweller"
    ],
    "wof:name":"Brad Kearton Jewellers",
    "wof:placetype":"venue"
},
  "geometry": {"coordinates":[152.76020813,-27.6138000488],"type":"Point"}
}