{
  "type": "Feature",
  "properties": {
    "iso:country":"AU",
    "sg:address":"38 Hilltop Pl",
    "sg:city":"Kelmscott",
    "sg:classifiers":[
        {
            "category":"Professional",
            "subcategory":"Accounting & Tax Preparation",
            "type":"Services"
        }
    ],
    "sg:phone":"+61 8 9390 3600",
    "sg:postcode":"6111",
    "sg:province":"WA",
    "sg:tags":[
        "accountant",
        "auditor"
    ],
    "wof:name":"Pawlak Edward And Associates",
    "wof:placetype":"venue"
},
  "geometry": {"coordinates":[116.03553008999999,-32.1296768188],"type":"Point"}
}