{
  "type": "Feature",
  "properties": {
    "addr:full":"12 Mt Glorious Rd Samford QLD 4520",
    "addr:housenumber":"12",
    "addr:postcode":"4520",
    "addr:street":"Mt Glorious Rd",
    "iso:country":"AU",
    "sg:address":"12 Mt Glorious Rd",
    "sg:city":"Samford",
    "sg:classifiers":[
        {
            "category":"Autos & Motor Vehicles",
            "subcategory":"Automobile Sales",
            "type":"Retail Goods"
        }
    ],
    "sg:phone":"+61 7 3289 3339",
    "sg:postcode":"4520",
    "sg:province":"QLD",
    "sg:tags":[
        "car",
        "used"
    ],
    "wof:name":"Samford Auto Barn",
    "wof:placetype":"venue"
},
  "geometry": {"coordinates":[152.88653600000001,-27.373405],"type":"Point"}
}