{
  "type": "Feature",
  "properties": {
    "iso:country":"AU",
    "sg:address":"Unit 3/ 21-23 Princess Hwy",
    "sg:city":"Engadine",
    "sg:classifiers":[
        {
            "category":"Retail",
            "subcategory":"Auto Repair",
            "type":"Services"
        }
    ],
    "sg:phone":"+61 2 9520 0376",
    "sg:postcode":"2233",
    "sg:province":"NSW",
    "sg:tags":[
        "repairer",
        "motor",
        "engineer"
    ],
    "wof:name":"Ross Automotive & Performance Modifications",
    "wof:placetype":"venue"
},
  "geometry": {"coordinates":[150.99838256800001,-34.0964241028],"type":"Point"}
}