{
  "type": "Feature",
  "properties": {
    "addr:full":"9 Frederick St Red Hill VIC 3937",
    "addr:housenumber":"9",
    "addr:postcode":"3937",
    "addr:street":"Frederick St",
    "iso:country":"AU",
    "sg:address":"9 Frederick St",
    "sg:city":"Red Hill",
    "sg:classifiers":[
        {
            "category":"Professional",
            "subcategory":"Computer Services",
            "type":"Services"
        }
    ],
    "sg:phone":"+61 3 5989 2728",
    "sg:postcode":"3937",
    "sg:province":"VIC",
    "sg:tags":[
        "repairs",
        "upgrade",
        "equipment"
    ],
    "wof:name":"Top Of The Hill Computers",
    "wof:placetype":"venue"
},
  "geometry": {"coordinates":[145.01968383799999,-38.3843955994],"type":"Point"}
}