{
  "type": "Feature",
  "properties": {
    "iso:country":"AU",
    "sg:address":"8 Brangus St",
    "sg:city":"Harristown",
    "sg:classifiers":[
        {
            "category":"Retail",
            "subcategory":"Repair Shop",
            "type":"Services"
        }
    ],
    "sg:phone":"+61 7 4635 8123",
    "sg:postcode":"4350",
    "sg:province":"QLD",
    "sg:tags":[
        "mending",
        "clothing",
        "alteration"
    ],
    "wof:name":"Carol Elton",
    "wof:placetype":"venue"
},
  "geometry": {"coordinates":[151.926331,-27.585611],"type":"Point"}
}