{
  "type": "Feature",
  "properties": {
    "addr:full":"Newsom Rd Ascot Vale VIC 3032",
    "addr:postcode":"3032",
    "addr:street":"Newsom Rd",
    "iso:country":"AU",
    "sg:address":"Newsom Rd",
    "sg:city":"Ascot Vale",
    "sg:classifiers":[
        {
            "category":"Sports & Exercise",
            "subcategory":"Golf",
            "type":"Entertainment"
        }
    ],
    "sg:phone":"+61 3 9372 0188",
    "sg:postcode":"3032",
    "sg:province":"VIC",
    "sg:tags":[
        "club"
    ],
    "wof:name":"Riverside Golf Club (Essendon) Inc",
    "wof:placetype":"venue"
},
  "geometry": {"coordinates":[144.906586,-37.772751],"type":"Point"}
}