{
  "type": "Feature",
  "properties": {
    "addr:full":"12-22 Richmond Rd Keswick SA 5035",
    "addr:housenumber":"12-22",
    "addr:postcode":"5035",
    "addr:street":"Richmond Rd",
    "iso:country":"AU",
    "sg:address":"12-22 Richmond Rd",
    "sg:city":"Keswick",
    "sg:classifiers":[
        {
            "category":"Government",
            "subcategory":"Fire Station",
            "type":"Public Place"
        }
    ],
    "sg:phone":"+61 8 8538 5049",
    "sg:postcode":"5035",
    "sg:province":"SA",
    "sg:tags":[
        "equipment",
        "protection",
        "consultant"
    ],
    "wof:name":"Association of Wall & Ceiling Industries of S.A. (Inc)",
    "wof:placetype":"venue"
},
  "geometry": {"coordinates":[138.5806427,-34.9418144226],"type":"Point"}
}