{
  "type": "Feature",
  "properties": {
    "addr:full":"14 Barnes St Tamworth NSW 2340",
    "addr:housenumber":"14",
    "addr:postcode":"2340",
    "addr:street":"Barnes St",
    "iso:country":"AU",
    "sg:address":"14 Barnes St",
    "sg:city":"Tamworth",
    "sg:classifiers":[
        {
            "category":"Building & Trades",
            "subcategory":"Construction",
            "type":"Services"
        }
    ],
    "sg:phone":"+61 2 6765 8291",
    "sg:postcode":"2340",
    "sg:province":"NSW",
    "sg:tags":[
        "insulation",
        "contractor"
    ],
    "wof:name":"Tamworth Custom Lattice",
    "wof:placetype":"venue"
},
  "geometry": {"coordinates":[150.915817261,-31.089548111],"type":"Point"}
}