{
  "type": "Feature",
  "properties": {
    "addr:full":"Shop 65 Balmoral Walk Bayside Shopping Centre Frankston VIC 3199",
    "addr:housenumber":"shop 65",
    "addr:postcode":"3199",
    "addr:street":"Balmoral Walk;Shopping",
    "iso:country":"AU",
    "sg:address":"Shop 65 Balmoral Walk Bayside Shopping Centre",
    "sg:city":"Frankston",
    "sg:classifiers":[
        {
            "category":"Personal",
            "subcategory":"Beauty Salon",
            "type":"Services"
        }
    ],
    "sg:phone":"+61 3 9781 5066",
    "sg:postcode":"3199",
    "sg:province":"VIC",
    "sg:tags":[
        "hairdresser"
    ],
    "wof:name":"Hartfords Hairdressing",
    "wof:placetype":"venue"
},
  "geometry": {"coordinates":[145.12290954599999,-38.1423149109],"type":"Point"}
}