{
  "type": "Feature",
  "properties": {
    "addr:full":"Shp1/ 510 Sydney Rd Balgowlah NSW 2093",
    "addr:housenumber":"510",
    "addr:postcode":"2093",
    "addr:street":"Sydney Rd",
    "iso:country":"AU",
    "sg:address":"Shp1/ 510 Sydney Rd",
    "sg:city":"Balgowlah",
    "sg:classifiers":[
        {
            "category":"Professional",
            "subcategory":"Accounting & Tax Preparation",
            "type":"Services"
        }
    ],
    "sg:phone":"+61 2 9948 5521",
    "sg:postcode":"2093",
    "sg:province":"NSW",
    "sg:tags":[
        "accountant",
        "auditor"
    ],
    "wof:name":"Proactive Business Services Accountants",
    "wof:placetype":"venue"
},
  "geometry": {"coordinates":[151.2550354,-33.7952575684],"type":"Point"}
}