{
  "type": "Feature",
  "properties": {
    "iso:country":"AU",
    "sg:address":"209 The River Rd",
    "sg:city":"Revesby",
    "sg:classifiers":[
        {
            "category":"Building & Trades",
            "subcategory":"Plumbing",
            "type":"Services"
        }
    ],
    "sg:phone":"+61 414 841 554",
    "sg:postcode":"2212",
    "sg:province":"NSW",
    "sg:tags":[
        "plumber",
        "gasfitters"
    ],
    "wof:name":"Bill Barclay Plumbing",
    "wof:placetype":"venue"
},
  "geometry": {"coordinates":[151.016907,-33.957157],"type":"Point"}
}