{
  "type": "Feature",
  "properties": {
    "addr:full":"27 Emma St Bracknell TAS 7302",
    "addr:housenumber":"27",
    "addr:postcode":"7302",
    "addr:street":"Emma St",
    "iso:country":"AU",
    "sg:address":"27 Emma St",
    "sg:city":"Bracknell",
    "sg:classifiers":[
        {
            "category":"Communications",
            "subcategory":"Film & Video Production",
            "type":"Services"
        }
    ],
    "sg:phone":"+61 3 6397 3155",
    "sg:postcode":"7302",
    "sg:province":"TAS",
    "sg:tags":[
        "society",
        "housing",
        "co-operative"
    ],
    "wof:name":"Deloraine Country Housing Co-operative",
    "wof:placetype":"venue"
},
  "geometry": {"coordinates":[146.944580078,-41.6533355713],"type":"Point"}
}