{
  "type": "Feature",
  "properties": {
    "addr:full":"Lvl 1/ 34 Chandos St St Leonards NSW 2065",
    "addr:housenumber":"/ 34",
    "addr:postcode":"2065",
    "addr:street":"Chandos St",
    "iso:country":"AU",
    "sg:address":"Lvl 1/ 34 Chandos St St",
    "sg:city":"Leonards",
    "sg:classifiers":[
        {
            "category":"Professional",
            "subcategory":"Business Services",
            "type":"Services"
        }
    ],
    "sg:phone":"+61 2 9901 4120",
    "sg:postcode":"2065",
    "sg:province":"NSW",
    "sg:tags":[
        "consultant",
        "leasing"
    ],
    "wof:name":"National Rental Corporation Limited",
    "wof:placetype":"venue"
},
  "geometry": {"coordinates":[151.19662475600001,-33.8218841553],"type":"Point"}
}