{
  "type": "Feature",
  "properties": {
    "iso:country":"AU",
    "sg:address":"120 A Devonshire St",
    "sg:city":"Surry Hills",
    "sg:classifiers":[
        {
            "category":"Professional",
            "subcategory":"Art Services",
            "type":"Services"
        }
    ],
    "sg:phone":"+61 2 9310 5950",
    "sg:postcode":"2010",
    "sg:province":"NSW",
    "sg:tags":[
        "graphic",
        "designer"
    ],
    "wof:name":"Cheryl Collins Design",
    "wof:placetype":"venue"
},
  "geometry": {"coordinates":[151.207962036,-33.8862762451],"type":"Point"}
}