{
  "type": "Feature",
  "properties": {
    "addr:full":"Duffy's Rd Terrigal NSW 2260",
    "addr:postcode":"2260",
    "addr:street":"Duffy'S Rd",
    "iso:country":"AU",
    "sg:address":"Duffy's Rd",
    "sg:city":"Terrigal",
    "sg:classifiers":[
        {
            "category":"Sports & Exercise",
            "subcategory":"Sports Center",
            "type":"Entertainment"
        }
    ],
    "sg:phone":"+61 2 4385 3577",
    "sg:postcode":"2260",
    "sg:province":"NSW",
    "sg:tags":[
        "ground"
    ],
    "wof:name":"Gosford City Sports Stadium Inc",
    "wof:placetype":"venue"
},
  "geometry": {"coordinates":[151.42808500000001,-33.445423],"type":"Point"}
}