{
  "type": "Feature",
  "properties": {
    "addr:full":"29 Bridge St Benalla East VIC 3672",
    "addr:housenumber":"29",
    "addr:postcode":"3672",
    "addr:street":"Bridge St",
    "iso:country":"AU",
    "sg:address":"29 Bridge St",
    "sg:city":"Benalla East",
    "sg:classifiers":[
        {
            "category":"Social Services",
            "subcategory":"Child Care",
            "type":"Services"
        }
    ],
    "sg:phone":"+61 3 5762 7677",
    "sg:postcode":"3672",
    "sg:province":"VIC",
    "wof:name":"Benalla Kids Cottage",
    "wof:placetype":"venue"
},
  "geometry": {"coordinates":[145.983566,-36.551617],"type":"Point"}
}