{
  "type": "Feature",
  "properties": {
    "iso:country":"AU",
    "sg:address":"30 Gindurra Ave",
    "sg:city":"Castle Hill",
    "sg:classifiers":[
        {
            "category":"Building & Trades",
            "subcategory":"Landscaping Services",
            "type":"Services"
        }
    ],
    "sg:phone":"+61 412 213 213",
    "sg:postcode":"2154",
    "sg:province":"NSW",
    "sg:tags":[
        "designer",
        "landscape",
        "contractor"
    ],
    "wof:name":"Environ Property Services Pty Ltd",
    "wof:placetype":"venue"
},
  "geometry": {"coordinates":[150.98133850100001,-33.7178878784],"type":"Point"}
}