{
  "type": "Feature",
  "properties": {
    "addr:full":"70- 76 Princes Hwy Moruya NSW 2537",
    "addr:housenumber":"76",
    "addr:postcode":"2537",
    "addr:street":"Princes Hwy",
    "iso:country":"AU",
    "sg:address":"70- 76 Princes Hwy",
    "sg:city":"Moruya",
    "sg:classifiers":[
        {
            "category":"Autos & Motor Vehicles",
            "subcategory":"Automobile Sales",
            "type":"Retail Goods"
        }
    ],
    "sg:phone":"+61 2 4474 3444",
    "sg:postcode":"2537",
    "sg:province":"NSW",
    "sg:tags":[
        "car",
        "new"
    ],
    "wof:name":"Moruya Kia",
    "wof:placetype":"venue"
},
  "geometry": {"coordinates":[150.08424377399999,-35.9190101624],"type":"Point"}
}