{
  "type": "Feature",
  "properties": {
    "addr:full":"11 Cyrus Ave Wahroonga NSW 2076",
    "addr:housenumber":"11",
    "addr:postcode":"2076",
    "addr:street":"Cyrus Ave",
    "iso:country":"AU",
    "sg:address":"11 Cyrus Ave",
    "sg:city":"Wahroonga",
    "sg:classifiers":[
        {
            "category":"Banks & Credit Unions",
            "subcategory":"Financial Services",
            "type":"Services"
        }
    ],
    "sg:phone":"+61 2 9487 7907",
    "sg:postcode":"2076",
    "sg:province":"NSW",
    "sg:tags":[
        "loan",
        "finance",
        "mortgage"
    ],
    "wof:name":"Mortgage Control",
    "wof:placetype":"venue"
},
  "geometry": {"coordinates":[151.10716247600001,-33.7285308838],"type":"Point"}
}