{
  "type": "Feature",
  "properties": {
    "addr:full":"Ward Crt Laidley QLD 4341",
    "addr:postcode":"4341",
    "addr:street":"Ward",
    "iso:country":"AU",
    "sg:address":"Ward Crt",
    "sg:city":"Laidley",
    "sg:classifiers":[
        {
            "category":"Wholesale",
            "subcategory":"Machinery & Supplies",
            "type":"Manufacturing & Wholesale Goods"
        }
    ],
    "sg:phone":"+61 7 5465 3900",
    "sg:postcode":"4341",
    "sg:province":"QLD",
    "sg:tags":[
        "equipment",
        "welding"
    ],
    "wof:name":"Iwatani International Corporation Australia Pty Ltd",
    "wof:placetype":"venue"
},
  "geometry": {"coordinates":[152.40870666500001,-27.6393241882],"type":"Point"}
}