{
  "type": "Feature",
  "properties": {
    "addr:full":"2- 4 Begg St Leongatha VIC 3953",
    "addr:housenumber":"4",
    "addr:postcode":"3953",
    "addr:street":"Begg St",
    "iso:country":"AU",
    "sg:address":"2- 4 Begg St",
    "sg:city":"Leongatha",
    "sg:classifiers":[
        {
            "category":"Building & Trades",
            "subcategory":"Landscaping Services",
            "type":"Services"
        }
    ],
    "sg:phone":"+61 3 5662 5100",
    "sg:postcode":"3953",
    "sg:province":"VIC",
    "sg:tags":[
        "stump",
        "tree",
        "felling",
        "removal"
    ],
    "wof:name":"Steve Vagg",
    "wof:placetype":"venue"
},
  "geometry": {"coordinates":[145.937225342,-38.4826698303],"type":"Point"}
}