{
  "type": "Feature",
  "properties": {
    "addr:full":"Suite 3, 106 John St Singleton NSW 2330",
    "addr:housenumber":"106",
    "addr:postcode":"2330",
    "addr:street":"John St",
    "iso:country":"AU",
    "sg:address":"Suite 3, 106 John St",
    "sg:city":"Singleton",
    "sg:classifiers":[
        {
            "category":"Personal",
            "subcategory":"Massage",
            "type":"Services"
        }
    ],
    "sg:phone":"+61 407 006 061",
    "sg:postcode":"2330",
    "sg:province":"NSW",
    "sg:tags":[
        "therapy"
    ],
    "wof:name":"Pheonas Phancy Phingers",
    "wof:placetype":"venue"
},
  "geometry": {"coordinates":[151.16572600000001,-32.566921],"type":"Point"}
}