{
  "type": "Feature",
  "properties": {
    "addr:full":"Shp 1/ 45 Canton Beach Rd Toukley NSW 2263",
    "addr:housenumber":"/ 45",
    "addr:postcode":"2263",
    "addr:street":"Beach Rd",
    "iso:country":"AU",
    "sg:address":"Shp 1/ 45 Canton Beach Rd",
    "sg:city":"Toukley",
    "sg:classifiers":[
        {
            "category":"Personal",
            "subcategory":"Beauty Salon",
            "type":"Services"
        }
    ],
    "sg:phone":"+61 2 4396 1666",
    "sg:postcode":"2263",
    "sg:province":"NSW",
    "wof:name":"Deborah Green's Natural Beauty Therapy",
    "wof:placetype":"venue"
},
  "geometry": {"coordinates":[151.54072600000001,-33.264473],"type":"Point"}
}