{
  "type": "Feature",
  "properties": {
    "addr:full":"33 Shannon Ave Merrylands NSW 2160",
    "addr:housenumber":"33",
    "addr:postcode":"2160",
    "addr:street":"Shannon Ave",
    "iso:country":"AU",
    "sg:address":"33 Shannon Ave",
    "sg:city":"Merrylands",
    "sg:classifiers":[
        {
            "category":"Building & Trades",
            "subcategory":"Construction",
            "type":"Services"
        }
    ],
    "sg:phone":"+61 2 9682 5828",
    "sg:postcode":"2160",
    "sg:province":"NSW",
    "sg:tags":[
        "contractor"
    ],
    "wof:name":"Abco Engineering & Construction Services",
    "wof:placetype":"venue"
},
  "geometry": {"coordinates":[150.980667114,-33.8310966492],"type":"Point"}
}