{
  "type": "Feature",
  "properties": {
    "addr:full":"Hangar 149 Tom McDonald Drv Cairns QLD 4870",
    "addr:housenumber":"149",
    "addr:postcode":"4870",
    "addr:street":"Tom Mcdonald Drv",
    "iso:country":"AU",
    "sg:address":"Hangar 149 Tom McDonald Drv",
    "sg:city":"Cairns",
    "sg:classifiers":[
        {
            "category":"Manufacturing",
            "subcategory":"Aerospace",
            "type":"Manufacturing & Wholesale Goods"
        }
    ],
    "sg:phone":"+61 7 4030 1865",
    "sg:postcode":"4870",
    "sg:province":"QLD",
    "sg:tags":[
        "equipment",
        "aircraft",
        "maintenance"
    ],
    "sg:website":"http://www.australianavionics.com.au",
    "wof:name":"Australian Avionics",
    "wof:placetype":"venue"
},
  "geometry": {"coordinates":[145.747924805,-16.8842697144],"type":"Point"}
}