{
  "type": "Feature",
  "properties": {
    "iso:country":"AU",
    "sg:address":"4 Strathlora St",
    "sg:city":"Strathfield",
    "sg:classifiers":[
        {
            "category":"Utilities",
            "subcategory":"Electric",
            "type":"Services"
        }
    ],
    "sg:phone":"+61 2 9642 1361",
    "sg:postcode":"2135",
    "sg:province":"NSW",
    "sg:tags":[
        "electrical",
        "contractor"
    ],
    "wof:name":"Grahame True Electrician",
    "wof:placetype":"venue"
},
  "geometry": {"coordinates":[151.07975769000001,-33.8827362061],"type":"Point"}
}