{
  "type": "Feature",
  "properties": {
    "addr:full":"2a Garden Drv Tullamarine VIC 3043",
    "addr:housenumber":"2a",
    "addr:postcode":"3043",
    "addr:street":"Garden Drv",
    "iso:country":"AU",
    "sg:address":"2a Garden Drv",
    "sg:city":"Tullamarine",
    "sg:classifiers":[
        {
            "category":"Real Estate",
            "subcategory":"Real Estate Agent",
            "type":"Services"
        }
    ],
    "sg:phone":"+61 3 9335 2111",
    "sg:postcode":"3043",
    "sg:province":"VIC",
    "sg:tags":[
        "handyman's",
        "equipment",
        "hire",
        "builders",
        "contractor"
    ],
    "wof:name":"Total Tools Industrial",
    "wof:placetype":"venue"
},
  "geometry": {"coordinates":[144.880859375,-37.6922531128],"type":"Point"}
}