{
  "type": "Feature",
  "properties": {
    "iso:country":"AU",
    "sg:address":"377 Montague Rd",
    "sg:city":"West End (Brisbane)",
    "sg:classifiers":[
        {
            "category":"Professional",
            "subcategory":"Business Services",
            "type":"Services"
        }
    ],
    "sg:phone":"+61 7 3844 0446",
    "sg:postcode":"4101",
    "sg:province":"QLD",
    "sg:tags":[
        "fashion",
        "agent"
    ],
    "wof:name":"Mei Mei International Fashion",
    "wof:placetype":"venue"
},
  "geometry": {"coordinates":[153.00250244099999,-27.4842243195],"type":"Point"}
}