{
  "type": "Feature",
  "properties": {
    "addr:full":"GPO Box 1628 Hobart TAS 7001",
    "addr:postcode":"7001",
    "iso:country":"AU",
    "sg:address":"GPO Box 1628",
    "sg:city":"Hobart",
    "sg:classifiers":[
        {
            "category":"Home & Garden",
            "subcategory":"Hardware",
            "type":"Retail Goods"
        }
    ],
    "sg:phone":"+61 3 6243 5300",
    "sg:postcode":"7001",
    "sg:province":"TAS",
    "sg:tags":[
        "pumping",
        "contractor"
    ],
    "wof:name":"Noble Concrete Pumping",
    "wof:placetype":"venue"
},
  "geometry": {"coordinates":[147.51083374000001,-42.8352508545],"type":"Point"}
}