{
  "type": "Feature",
  "properties": {
    "iso:country":"AU",
    "sg:address":"84 Barkly St",
    "sg:city":"Ararat",
    "sg:classifiers":[
        {
            "category":"Travel",
            "subcategory":"Hotels & Motels",
            "type":"Entertainment"
        }
    ],
    "sg:phone":"+61 3 5352 1039",
    "sg:postcode":"3377",
    "sg:province":"VIC",
    "sg:tags":[
        "accommodation"
    ],
    "wof:name":"Bee-Jays Wine Bar",
    "wof:placetype":"venue"
},
  "geometry": {"coordinates":[142.92796325699999,-37.2844581604],"type":"Point"}
}