{
  "type": "Feature",
  "properties": {
    "addr:full":"29 Clifton Rd Taree NSW 2430",
    "addr:housenumber":"29",
    "addr:postcode":"2430",
    "addr:street":"Clifton Rd",
    "iso:country":"AU",
    "sg:address":"29 Clifton Rd",
    "sg:city":"Taree",
    "sg:classifiers":[
        {
            "category":"Professional",
            "subcategory":"Accounting & Tax Preparation",
            "type":"Services"
        }
    ],
    "sg:phone":"+61 2 6552 1449",
    "sg:postcode":"2430",
    "sg:province":"NSW",
    "sg:tags":[
        "accountant",
        "auditor"
    ],
    "wof:name":"Burgess P J",
    "wof:placetype":"venue"
},
  "geometry": {"coordinates":[152.419601,-31.873932],"type":"Point"}
}