{
  "type": "Feature",
  "properties": {
    "addr:full":"1/ 6 Bookham St Morley WA 6062",
    "addr:housenumber":"/ 6",
    "addr:postcode":"6062",
    "addr:street":"Bookham St",
    "iso:country":"AU",
    "sg:address":"1/ 6 Bookham St",
    "sg:city":"Morley",
    "sg:classifiers":[
        {
            "category":"Professional",
            "subcategory":"Computer Services",
            "type":"Services"
        }
    ],
    "sg:phone":"+61 8 9375 6544",
    "sg:postcode":"6062",
    "sg:province":"WA",
    "sg:tags":[
        "equipment",
        "networking",
        "installation"
    ],
    "wof:name":"Optel Enclosures",
    "wof:placetype":"venue"
},
  "geometry": {"coordinates":[115.896987915,-31.9003181458],"type":"Point"}
}