{
  "type": "Feature",
  "properties": {
    "addr:full":"Shp 1019 Knox City Shop Ctr Burwood Hwy Wantirna South VIC 3152",
    "addr:housenumber":"1019",
    "addr:postcode":"3152",
    "addr:street":"Knox;Burwood Hwy",
    "iso:country":"AU",
    "sg:address":"Shp 1019 Knox City Shop Ctr Burwood Hwy",
    "sg:city":"Wantirna South",
    "sg:classifiers":[
        {
            "category":"Communications",
            "subcategory":"Film & Video Production",
            "type":"Services"
        }
    ],
    "sg:phone":"+61 3 9887 1874",
    "sg:postcode":"3152",
    "sg:province":"VIC",
    "sg:tags":[
        "dvd",
        "library"
    ],
    "wof:name":"Network Video",
    "wof:placetype":"venue"
},
  "geometry": {"coordinates":[145.24488830600001,-37.8719444275],"type":"Point"}
}