{
  "type": "Feature",
  "properties": {
    "iso:country":"AU",
    "sg:address":"1 Tyres St",
    "sg:city":"Casterton",
    "sg:classifiers":[
        {
            "category":"Retail",
            "subcategory":"Auto Repair",
            "type":"Services"
        }
    ],
    "sg:phone":"+61 3 5581 1422",
    "sg:postcode":"3311",
    "sg:province":"VIC",
    "sg:tags":[
        "beater",
        "painter",
        "panel"
    ],
    "wof:name":"Casterton Panels",
    "wof:placetype":"venue"
},
  "geometry": {"coordinates":[141.407714844,-37.5826339722],"type":"Point"}
}