{
  "type": "Feature",
  "properties": {
    "addr:full":"18 Dylan Crt Mildura VIC 3500",
    "addr:housenumber":"18",
    "addr:postcode":"3500",
    "addr:street":"Dylan Crt",
    "iso:country":"AU",
    "sg:address":"18 Dylan Crt",
    "sg:city":"Mildura",
    "sg:classifiers":[
        {
            "category":"Manufacturing",
            "subcategory":"Rubber & Plastics",
            "type":"Manufacturing & Wholesale Goods"
        }
    ],
    "sg:phone":"+61 3 5023 4843",
    "sg:postcode":"3500",
    "sg:province":"VIC",
    "sg:tags":[
        "stamp",
        "equipment",
        "metal",
        "maker",
        "supply"
    ],
    "wof:name":"Goldfields Graphics",
    "wof:placetype":"venue"
},
  "geometry": {"coordinates":[142.13723754899999,-34.199672699],"type":"Point"}
}