{
  "type": "Feature",
  "properties": {
    "addr:full":"23 McCreddons Rd Marong VIC 3515",
    "addr:housenumber":"23",
    "addr:postcode":"3515",
    "addr:street":"Mccreddons Rd",
    "iso:country":"AU",
    "sg:address":"23 McCreddons Rd",
    "sg:city":"Marong",
    "sg:classifiers":[
        {
            "category":"Social Services",
            "subcategory":"Retirement Home",
            "type":"Services"
        }
    ],
    "sg:phone":"+61 3 5435 2313",
    "sg:postcode":"3515",
    "sg:province":"VIC",
    "sg:tags":[
        "life",
        "coaching"
    ],
    "wof:name":"Joel Stratford",
    "wof:placetype":"venue"
},
  "geometry": {"coordinates":[144.116333,-36.73893],"type":"Point"}
}