{
  "type": "Feature",
  "properties": {
    "addr:full":"Shop QG7 Prince Centre 8 Quay St Haymarket NSW 2000",
    "addr:housenumber":"qg7;8",
    "addr:postcode":"2000",
    "addr:street":"Prince Centre;Quay St",
    "iso:country":"AU",
    "sg:address":"Shop QG7 Prince Centre 8 Quay St",
    "sg:city":"Haymarket",
    "sg:classifiers":[
        {
            "category":"Travel",
            "subcategory":"Travel Agent",
            "type":"Entertainment"
        }
    ],
    "sg:phone":"+61 2 9211 6611",
    "sg:postcode":"2000",
    "sg:province":"NSW",
    "sg:tags":[
        "consultant"
    ],
    "wof:name":"Pan World Travel Pty Ltd",
    "wof:placetype":"venue"
},
  "geometry": {"coordinates":[151.202957153,-33.8806533813],"type":"Point"}
}