{
  "type": "Feature",
  "properties": {
    "iso:country":"AU",
    "sg:address":"29 Australia St",
    "sg:city":"Camperdown",
    "sg:classifiers":[
        {
            "category":"Banks & Credit Unions",
            "subcategory":"Bank",
            "type":"Services"
        }
    ],
    "sg:phone":"+61 1300 735 512",
    "sg:postcode":"2050",
    "sg:province":"NSW",
    "sg:tags":[
        "broker",
        "mortgage"
    ],
    "wof:name":"Wealthcheck Finance Pty Ltd",
    "wof:placetype":"venue"
},
  "geometry": {"coordinates":[151.17713900000001,-33.89415],"type":"Point"}
}