{
  "type": "Feature",
  "properties": {
    "addr:full":"3/ 51 Secam St Mansfield QLD 4122",
    "addr:housenumber":"/ 51",
    "addr:postcode":"4122",
    "addr:street":"Secam St",
    "iso:country":"AU",
    "sg:address":"3/ 51 Secam St",
    "sg:city":"Mansfield",
    "sg:classifiers":[
        {
            "category":"Building & Trades",
            "subcategory":"Equipment Rental",
            "type":"Services"
        }
    ],
    "sg:phone":"+61 7 3849 6228",
    "sg:postcode":"4122",
    "sg:province":"QLD",
    "sg:tags":[
        "hire",
        "catering"
    ],
    "wof:name":"Gold Medal Rents",
    "wof:placetype":"venue"
},
  "geometry": {"coordinates":[153.0987854,-27.5298709869],"type":"Point"}
}