{
  "type": "Feature",
  "properties": {
    "iso:country":"AU",
    "sg:address":"70 Petra St",
    "sg:city":"Palmyra",
    "sg:classifiers":[
        {
            "category":"Banks & Credit Unions",
            "subcategory":"Bank",
            "type":"Services"
        }
    ],
    "sg:phone":"+61 13 20 32",
    "sg:postcode":"6157",
    "sg:province":"WA",
    "wof:name":"Westpac",
    "wof:placetype":"venue"
},
  "geometry": {"coordinates":[115.776321,-32.039345],"type":"Point"}
}