{
  "type": "Feature",
  "properties": {
    "iso:country":"AU",
    "sg:address":"PO Box 70",
    "sg:city":"Giru",
    "sg:classifiers":[
        {
            "category":"Mining & Drilling",
            "type":"Manufacturing & Wholesale Goods"
        }
    ],
    "sg:phone":"+61 7 4782 9440",
    "sg:postcode":"4809",
    "sg:province":"QLD",
    "sg:tags":[
        "boring",
        "contractor"
    ],
    "wof:name":"Horizontal Directional Drillers",
    "wof:placetype":"venue"
},
  "geometry": {"coordinates":[147.10197448700001,-19.5531406403],"type":"Point"}
}