{
  "type": "Feature",
  "properties": {
    "iso:country":"AU",
    "sg:address":"Shop 2/John St Square 27 Harvey St",
    "sg:city":"Pyrmont",
    "sg:classifiers":[
        {
            "category":"Health Services",
            "subcategory":"Dentist",
            "type":"Services"
        }
    ],
    "sg:phone":"+61 2 9518 7832",
    "sg:postcode":"2009",
    "sg:province":"NSW",
    "wof:name":"Quach Linda Dr",
    "wof:placetype":"venue"
},
  "geometry": {"coordinates":[151.19247436500001,-33.8675003052],"type":"Point"}
}