{
  "type": "Feature",
  "properties": {
    "addr:full":"1340 Toodyay Rd Gidgegannup WA 6083",
    "addr:housenumber":"1340",
    "addr:postcode":"6083",
    "addr:street":"Toodyay Rd",
    "iso:country":"AU",
    "sg:address":"1340 Toodyay Rd",
    "sg:city":"Gidgegannup",
    "sg:classifiers":[
        {
            "category":"Utilities",
            "subcategory":"Recycling",
            "type":"Services"
        }
    ],
    "sg:phone":"+61 8 9574 6109",
    "sg:postcode":"6083",
    "sg:province":"WA",
    "wof:name":"CMR Pty Ltd",
    "wof:placetype":"venue"
},
  "geometry": {"coordinates":[116.179527283,-31.7997398376],"type":"Point"}
}