{
  "type": "Feature",
  "properties": {
    "iso:country":"AU",
    "sg:address":"Arthur St",
    "sg:city":"Tambo",
    "sg:classifiers":[
        {
            "category":"Travel",
            "subcategory":"Hotels & Motels",
            "type":"Entertainment"
        }
    ],
    "sg:phone":"+61 7 4654 6109",
    "sg:postcode":"4478",
    "sg:province":"QLD",
    "wof:name":"Club Hotel/Motel",
    "wof:placetype":"venue"
},
  "geometry": {"coordinates":[146.254592895,-24.8829174042],"type":"Point"}
}