{
  "type": "Feature",
  "properties": {
    "addr:full":"607- 608 Stockinbingal Rd Temora NSW 2666",
    "addr:housenumber":"608",
    "addr:postcode":"2666",
    "addr:street":"Stockinbingal Rd",
    "iso:country":"AU",
    "sg:address":"607- 608 Stockinbingal Rd",
    "sg:city":"Temora",
    "sg:classifiers":[
        {
            "category":"Retail",
            "subcategory":"Auto Repair",
            "type":"Services"
        }
    ],
    "sg:phone":"+61 2 6977 2255",
    "sg:postcode":"2666",
    "sg:province":"NSW",
    "sg:tags":[
        "repairer",
        "motor",
        "engineer"
    ],
    "wof:name":"Holden",
    "wof:placetype":"venue"
},
  "geometry": {"coordinates":[147.53408813499999,-34.4467506409],"type":"Point"}
}