{
  "type": "Feature",
  "properties": {
    "iso:country":"AU",
    "sg:address":"Unit 30 798 Marion Rd",
    "sg:city":"Marion",
    "sg:classifiers":[
        {
            "category":"Retail",
            "subcategory":"Auto Rental",
            "type":"Services"
        }
    ],
    "sg:phone":"+61 402 323 631",
    "sg:postcode":"5043",
    "sg:province":"SA",
    "sg:tags":[
        "car",
        "wedding"
    ],
    "wof:name":"Prestigious Jag Limousines",
    "wof:placetype":"venue"
},
  "geometry": {"coordinates":[138.558075,-35.00935],"type":"Point"}
}