{
  "type": "Feature",
  "properties": {
    "addr:full":"82 Dunlop St Mortlake VIC 3272",
    "addr:housenumber":"82",
    "addr:postcode":"3272",
    "addr:street":"Dunlop St",
    "iso:country":"AU",
    "sg:address":"82 Dunlop St",
    "sg:city":"Mortlake",
    "sg:classifiers":[
        {
            "category":"Shopping",
            "type":"Retail Goods"
        }
    ],
    "sg:phone":"+61 3 5599 2300",
    "sg:postcode":"3272",
    "sg:province":"VIC",
    "sg:tags":[
        "agent",
        "stock"
    ],
    "wof:name":"Elders Ltd",
    "wof:placetype":"venue"
},
  "geometry": {"coordinates":[142.805053711,-38.0805931091],"type":"Point"}
}