{
  "type": "Feature",
  "properties": {
    "addr:full":"17 Homestead Rd Berwick VIC 3806",
    "addr:housenumber":"17",
    "addr:postcode":"3806",
    "addr:street":"Homestead Rd",
    "iso:country":"AU",
    "sg:address":"17 Homestead Rd",
    "sg:city":"Berwick",
    "sg:classifiers":[
        {
            "category":"Home & Garden",
            "subcategory":"Building Materials",
            "type":"Retail Goods"
        }
    ],
    "sg:phone":"+61 3 9773 8884",
    "sg:postcode":"3806",
    "sg:province":"VIC",
    "sg:tags":[
        "lawn",
        "cutting",
        "maintenance"
    ],
    "wof:name":"Homestead Lawns & Gardens",
    "wof:placetype":"venue"
},
  "geometry": {"coordinates":[145.338012695,-38.0555305481],"type":"Point"}
}