{
  "type": "Feature",
  "properties": {
    "addr:full":"129 Rocky Point Rd Kirrawee NSW 2232",
    "addr:housenumber":"129",
    "addr:postcode":"2232",
    "addr:street":"Rocky Point Rd",
    "iso:country":"AU",
    "sg:address":"129 Rocky Point Rd",
    "sg:city":"Kirrawee",
    "sg:classifiers":[
        {
            "category":"Autos & Motor Vehicles",
            "subcategory":"Automobile Sales",
            "type":"Retail Goods"
        }
    ],
    "sg:phone":"+61 2 9545 8888",
    "sg:postcode":"2232",
    "sg:province":"NSW",
    "sg:tags":[
        "car",
        "new"
    ],
    "wof:name":"Mercedes-Benz Light Commercial Sales Tynan",
    "wof:placetype":"venue"
},
  "geometry": {"coordinates":[151.07110595699999,-34.0342292786],"type":"Point"}
}