{
  "type": "Feature",
  "properties": {
    "iso:country":"AU",
    "sg:address":"63 Remount Rd",
    "sg:city":"Mowbray",
    "sg:classifiers":[
        {
            "category":"Building & Trades",
            "subcategory":"Construction",
            "type":"Services"
        }
    ],
    "sg:phone":"+61 3 6326 8440",
    "sg:postcode":"7248",
    "sg:province":"TAS",
    "sg:tags":[
        "bitumen",
        "paving",
        "asphalt"
    ],
    "wof:name":"Venarchie Contracting Pty Ltd",
    "wof:placetype":"venue"
},
  "geometry": {"coordinates":[147.150268555,-41.4035987854],"type":"Point"}
}