{
  "type": "Feature",
  "properties": {
    "addr:full":"467 Upper Heidelberg Rd Heidelberg VIC 3084",
    "addr:housenumber":"467",
    "addr:postcode":"3084",
    "addr:street":"Upper Heidelberg Rd",
    "iso:country":"AU",
    "sg:address":"467 Upper Heidelberg Rd",
    "sg:city":"Heidelberg",
    "sg:classifiers":[
        {
            "category":"Health Services",
            "subcategory":"Dentist",
            "type":"Services"
        }
    ],
    "sg:phone":"+61 3 9458 2585",
    "sg:postcode":"3084",
    "sg:province":"VIC",
    "sg:tags":[
        "technician",
        "dental"
    ],
    "wof:name":"Randall Scott",
    "wof:placetype":"venue"
},
  "geometry": {"coordinates":[145.05653381400001,-37.7533111572],"type":"Point"}
}