{
  "type": "Feature",
  "properties": {
    "addr:full":"PO Box 4028 Knox City Centre VIC 3152",
    "addr:postcode":"3152",
    "iso:country":"AU",
    "sg:address":"PO Box 4028",
    "sg:city":"Knox City Centre",
    "sg:classifiers":[
        {
            "category":"Professional",
            "subcategory":"Computer Services",
            "type":"Services"
        }
    ],
    "sg:phone":"+61 3 9758 0898",
    "sg:postcode":"3152",
    "sg:province":"VIC",
    "sg:tags":[
        "training"
    ],
    "wof:name":"Warrabarr Accounting Solutions Pty Ltd",
    "wof:placetype":"venue"
},
  "geometry": {"coordinates":[145.24118042000001,-37.8691291809],"type":"Point"}
}