{
  "type": "Feature",
  "properties": {
    "addr:full":"8 Ninth St Snowtown SA 5520",
    "addr:housenumber":"8",
    "addr:postcode":"5520",
    "addr:street":"Ninth St",
    "iso:country":"AU",
    "sg:address":"8 Ninth St",
    "sg:city":"Snowtown",
    "sg:classifiers":[
        {
            "category":"Utilities",
            "subcategory":"Electric",
            "type":"Services"
        }
    ],
    "sg:phone":"+61 8 8865 2142",
    "sg:postcode":"5520",
    "sg:province":"SA",
    "sg:tags":[
        "electrical",
        "contractor"
    ],
    "wof:name":"Larges Electrical",
    "wof:placetype":"venue"
},
  "geometry": {"coordinates":[138.211669922,-33.7831306458],"type":"Point"}
}