{
  "type": "Feature",
  "properties": {
    "iso:country":"AU",
    "sg:address":"Suite 17/ 28 Garling Rd",
    "sg:city":"Kings Park",
    "sg:classifiers":[
        {
            "category":"Personal",
            "subcategory":"Skin Care",
            "type":"Services"
        }
    ],
    "sg:phone":"+61 2 9831 6900",
    "sg:postcode":"2148",
    "sg:province":"NSW",
    "sg:tags":[
        "hair",
        "product"
    ],
    "wof:name":"Keune Australia Pty Ltd",
    "wof:placetype":"venue"
},
  "geometry": {"coordinates":[150.90953064000001,-33.7438430786],"type":"Point"}
}