{
  "type": "Feature",
  "properties": {
    "addr:full":"134 West High St Coffs Harbour NSW 2450",
    "addr:housenumber":"134",
    "addr:postcode":"2450",
    "addr:street":"West High St",
    "iso:country":"AU",
    "sg:address":"134 West High St",
    "sg:city":"Coffs Harbour",
    "sg:classifiers":[
        {
            "category":"Professional",
            "subcategory":"Lawyer & Legal Services",
            "type":"Services"
        }
    ],
    "sg:phone":"+61 2 6650 7000",
    "sg:postcode":"2450",
    "sg:province":"NSW",
    "sg:tags":[
        "wills",
        "probate",
        "estate"
    ],
    "wof:name":"Fishburn Watson O'Brien Solicitors",
    "wof:placetype":"venue"
},
  "geometry": {"coordinates":[153.11247299999999,-30.295891],"type":"Point"}
}