{
  "type": "Feature",
  "properties": {
    "iso:country":"AU",
    "sg:address":"127 Goldsworthy Rd",
    "sg:city":"Corio",
    "sg:classifiers":[
        {
            "category":"Food & Beverages",
            "subcategory":"Groceries & Convenience Stores",
            "type":"Retail Goods"
        }
    ],
    "sg:phone":"+61 3 5275 1045",
    "sg:postcode":"3214",
    "sg:province":"VIC",
    "wof:name":"Abrahim Abir",
    "wof:placetype":"venue"
},
  "geometry": {"coordinates":[144.34315490700001,-38.076713562],"type":"Point"}
}