{
  "type": "Feature",
  "properties": {
    "iso:country":"AU",
    "sg:address":"Level 1, 25 Sturt St",
    "sg:city":"Townsville",
    "sg:classifiers":[
        {
            "category":"Banks & Credit Unions",
            "subcategory":"Financial Services",
            "type":"Services"
        }
    ],
    "sg:phone":"+61 7 4722 2702",
    "sg:postcode":"4810",
    "sg:province":"QLD",
    "sg:tags":[
        "loan",
        "finance",
        "mortgage"
    ],
    "wof:name":"Mortgage Managers Australia",
    "wof:placetype":"venue"
},
  "geometry": {"coordinates":[146.814682,-19.26083],"type":"Point"}
}