{
  "type": "Feature",
  "properties": {
    "iso:country":"AU",
    "sg:address":"Unit 1/ 106 Aldinga Beach Rd",
    "sg:city":"Aldinga Beach",
    "sg:classifiers":[
        {
            "category":"Home & Garden",
            "subcategory":"Building Materials",
            "type":"Retail Goods"
        }
    ],
    "sg:phone":"+61 8 8556 6878",
    "sg:postcode":"5173",
    "sg:province":"SA",
    "sg:tags":[
        "merchant",
        "glass",
        "glazier"
    ],
    "wof:name":"Coastal Glass & Window Maintenance",
    "wof:placetype":"venue"
},
  "geometry": {"coordinates":[138.45309448200001,-35.2786483765],"type":"Point"}
}