{
  "type": "Feature",
  "properties": {
    "addr:full":"169 High St Willoughby NSW 2068",
    "addr:housenumber":"169",
    "addr:postcode":"2068",
    "addr:street":"High St",
    "iso:country":"AU",
    "sg:address":"169 High St",
    "sg:city":"Willoughby",
    "sg:classifiers":[
        {
            "category":"Retail",
            "subcategory":"Auto Repair",
            "type":"Services"
        }
    ],
    "sg:phone":"+61 2 9967 2072",
    "sg:postcode":"2068",
    "sg:province":"NSW",
    "sg:tags":[
        "repairer",
        "motor",
        "engineer"
    ],
    "wof:name":"J V Mobile Mechanical Services",
    "wof:placetype":"venue"
},
  "geometry": {"coordinates":[151.20150756800001,-33.7976608276],"type":"Point"}
}