{
  "type": "Feature",
  "properties": {
    "addr:full":"Shp 3/ 672 Beaufort St Mt Lawley WA 6050",
    "addr:housenumber":"/ 672",
    "addr:postcode":"6050",
    "addr:street":"Beaufort St",
    "iso:country":"AU",
    "sg:address":"Shp 3/ 672 Beaufort St",
    "sg:city":"Mt Lawley",
    "sg:classifiers":[
        {
            "category":"Shopping",
            "subcategory":"Clothing, Apparel, & Fashions",
            "type":"Retail Goods"
        }
    ],
    "sg:phone":"+61 8 9371 7776",
    "sg:postcode":"6050",
    "sg:province":"WA",
    "sg:tags":[
        "lady",
        "wear"
    ],
    "wof:name":"Billie & Rose",
    "wof:placetype":"venue"
},
  "geometry": {"coordinates":[115.872848511,-31.9338207245],"type":"Point"}
}