{
  "type": "Feature",
  "properties": {
    "addr:full":"8 Spilsby Pl The Gap QLD 4061",
    "addr:housenumber":"8",
    "addr:postcode":"4061",
    "addr:street":"Spilsby Pl",
    "iso:country":"AU",
    "sg:address":"8 Spilsby Pl",
    "sg:city":"The Gap",
    "sg:classifiers":[
        {
            "category":"Real Estate",
            "subcategory":"Real Estate Agent",
            "type":"Services"
        }
    ],
    "sg:phone":"+61 7 3300 6699",
    "sg:postcode":"4061",
    "sg:province":"QLD",
    "wof:name":"Collins Brian J & Associates Pty Ltd",
    "wof:placetype":"venue"
},
  "geometry": {"coordinates":[152.93234252900001,-27.4433746338],"type":"Point"}
}