{
  "type": "Feature",
  "properties": {
    "addr:full":"134 Main St Bairnsdale VIC 3875",
    "addr:housenumber":"134",
    "addr:postcode":"3875",
    "addr:street":"Main St",
    "iso:country":"AU",
    "sg:address":"134 Main St",
    "sg:city":"Bairnsdale",
    "sg:classifiers":[
        {
            "category":"Banks & Credit Unions",
            "subcategory":"Financial Services",
            "type":"Services"
        }
    ],
    "sg:phone":"+61 3 5152 6887",
    "sg:postcode":"3875",
    "sg:province":"VIC",
    "sg:tags":[
        "loan",
        "finance",
        "mortgage"
    ],
    "wof:name":"ANZ",
    "wof:placetype":"venue"
},
  "geometry": {"coordinates":[147.827224731,-37.7086296082],"type":"Point"}
}