{
  "type": "Feature",
  "properties": {
    "iso:country":"AU",
    "sg:address":"26 Alinjarra Drv",
    "sg:city":"Tugun",
    "sg:classifiers":[
        {
            "category":"Retail",
            "subcategory":"Repair Shop",
            "type":"Services"
        }
    ],
    "sg:phone":"+61 416 189 032",
    "sg:postcode":"4224",
    "sg:province":"QLD",
    "sg:tags":[
        "maintenance",
        "pool",
        "swimming"
    ],
    "wof:name":"Ackerman Mark",
    "wof:placetype":"venue"
},
  "geometry": {"coordinates":[153.48313903799999,-28.151102066],"type":"Point"}
}