{
  "type": "Feature",
  "properties": {
    "addr:full":"21 Suffolk Pde Pottsville NSW 2489",
    "addr:housenumber":"21",
    "addr:postcode":"2489",
    "addr:street":"Suffolk Pde",
    "iso:country":"AU",
    "sg:address":"21 Suffolk Pde",
    "sg:city":"Pottsville",
    "sg:classifiers":[
        {
            "category":"Utilities",
            "subcategory":"Electric",
            "type":"Services"
        }
    ],
    "sg:phone":"+61 2 6676 2761",
    "sg:postcode":"2489",
    "sg:province":"NSW",
    "sg:tags":[
        "electrical",
        "contractor"
    ],
    "wof:name":"Mark The Spark Electrics",
    "wof:placetype":"venue"
},
  "geometry": {"coordinates":[153.56057739299999,-28.3860492706],"type":"Point"}
}