{
  "type": "Feature",
  "properties": {
    "iso:country":"AU",
    "sg:address":"10 Chaston St",
    "sg:city":"Wagga Wagga",
    "sg:classifiers":[
        {
            "category":"Manufacturing",
            "subcategory":"Electronics",
            "type":"Manufacturing & Wholesale Goods"
        }
    ],
    "sg:phone":"+61 2 6925 5155",
    "sg:postcode":"2650",
    "sg:province":"NSW",
    "sg:tags":[
        "oven",
        "microwave"
    ],
    "wof:name":"Millers Appliance Repairs & Sales",
    "wof:placetype":"venue"
},
  "geometry": {"coordinates":[147.35429382300001,-35.1217765808],"type":"Point"}
}