{
  "type": "Feature",
  "properties": {
    "addr:full":"16 Junction Rd Samford QLD 4520",
    "addr:housenumber":"16",
    "addr:postcode":"4520",
    "addr:street":"Junction Rd",
    "iso:country":"AU",
    "sg:address":"16 Junction Rd",
    "sg:city":"Samford",
    "sg:classifiers":[
        {
            "category":"Professional",
            "type":"Services"
        }
    ],
    "sg:phone":"+61 412 969 268",
    "sg:postcode":"4520",
    "sg:province":"QLD",
    "sg:tags":[
        "shop",
        "fitting"
    ],
    "wof:name":"RJR Developments",
    "wof:placetype":"venue"
},
  "geometry": {"coordinates":[152.88734400000001,-27.374016],"type":"Point"}
}