{
  "type": "Feature",
  "properties": {
    "addr:full":"104 Elgin St Carlton VIC 3053",
    "addr:housenumber":"104",
    "addr:postcode":"3053",
    "addr:street":"Elgin St",
    "iso:country":"AU",
    "sg:address":"104 Elgin St",
    "sg:city":"Carlton",
    "sg:classifiers":[
        {
            "category":"Manufacturing",
            "subcategory":"Food",
            "type":"Manufacturing & Wholesale Goods"
        }
    ],
    "sg:phone":"+61 3 9347 3971",
    "sg:postcode":"3053",
    "sg:province":"VIC",
    "sg:tags":[
        "function",
        "catering"
    ],
    "wof:name":"orange bean expresso",
    "wof:placetype":"venue"
},
  "geometry": {"coordinates":[144.971313477,-37.7974205017],"type":"Point"}
}