{
  "type": "Feature",
  "properties": {
    "iso:country":"AU",
    "sg:address":"Unit 4, 4 Nasmyth Rd",
    "sg:city":"Rockingham",
    "sg:classifiers":[
        {
            "category":"Building & Trades",
            "subcategory":"Plumbing",
            "type":"Services"
        }
    ],
    "sg:phone":"+61 8 9527 7267",
    "sg:postcode":"6168",
    "sg:province":"WA",
    "sg:tags":[
        "pump",
        "repairer"
    ],
    "wof:name":"Quality Rewinds",
    "wof:placetype":"venue"
},
  "geometry": {"coordinates":[115.76358,-32.276176],"type":"Point"}
}