{
  "type": "Feature",
  "properties": {
    "addr:full":"102 Owen Crs Regents Park QLD 4118",
    "addr:housenumber":"102",
    "addr:postcode":"4118",
    "addr:street":"Owen Crs",
    "iso:country":"AU",
    "sg:address":"102 Owen Crs",
    "sg:city":"Regents Park",
    "sg:classifiers":[
        {
            "category":"Home & Garden",
            "subcategory":"Building Materials",
            "type":"Retail Goods"
        }
    ],
    "sg:phone":"+61 403 345 487",
    "sg:postcode":"4118",
    "sg:province":"QLD",
    "sg:tags":[
        "shutter",
        "roller",
        "grille"
    ],
    "wof:name":"Milans Roller Shutters",
    "wof:placetype":"venue"
},
  "geometry": {"coordinates":[153.045318603,-27.6703491211],"type":"Point"}
}