{
  "type": "Feature",
  "properties": {
    "addr:full":"59 Gladstone Ave South Perth WA 6151",
    "addr:housenumber":"59",
    "addr:postcode":"6151",
    "addr:street":"Gladstone Ave South",
    "iso:country":"AU",
    "sg:address":"59 Gladstone Ave",
    "sg:city":"South Perth",
    "sg:classifiers":[
        {
            "category":"Real Estate",
            "subcategory":"Real Estate Agent",
            "type":"Services"
        }
    ],
    "sg:phone":"+61 8 9367 2434",
    "sg:postcode":"6151",
    "sg:province":"WA",
    "wof:name":"MacKenzie Andrew",
    "wof:placetype":"venue"
},
  "geometry": {"coordinates":[115.87394,-31.980143],"type":"Point"}
}