{
  "type": "Feature",
  "properties": {
    "iso:country":"AU",
    "sg:address":"164 Liebig St",
    "sg:city":"Warrnambool",
    "sg:classifiers":[
        {
            "category":"Professional",
            "subcategory":"Accounting & Tax Preparation",
            "type":"Services"
        }
    ],
    "sg:phone":"+61 3 5561 2992",
    "sg:postcode":"3280",
    "sg:province":"VIC",
    "sg:tags":[
        "consultant",
        "taxation"
    ],
    "wof:name":"Pola & Co",
    "wof:placetype":"venue"
},
  "geometry": {"coordinates":[142.47531127900001,-38.3766937256],"type":"Point"}
}