{
  "type": "Feature",
  "properties": {
    "addr:full":"9 Holbrook St Invermay TAS 7248",
    "addr:housenumber":"9",
    "addr:postcode":"7248",
    "addr:street":"Holbrook St",
    "iso:country":"AU",
    "sg:address":"9 Holbrook St",
    "sg:city":"Invermay",
    "sg:classifiers":[
        {
            "category":"Home & Garden",
            "subcategory":"Building Materials",
            "type":"Retail Goods"
        }
    ],
    "sg:phone":"+61 3 6334 3722",
    "sg:postcode":"7248",
    "sg:province":"TAS",
    "sg:tags":[
        "shutter",
        "roller",
        "grille"
    ],
    "wof:name":"Tom Moore & Son Launceston",
    "wof:placetype":"venue"
},
  "geometry": {"coordinates":[147.13577270499999,-41.4294319153],"type":"Point"}
}