{
  "type": "Feature",
  "properties": {
    "addr:full":"Shop 4 185- 211 Broadway St Ultimo NSW 2007",
    "addr:housenumber":"shop 4;211",
    "addr:postcode":"185;2007",
    "addr:street":"Broadway St",
    "iso:country":"AU",
    "sg:address":"Shop 4 185- 211 Broadway St",
    "sg:city":"Ultimo",
    "sg:classifiers":[
        {
            "category":"Travel",
            "subcategory":"Travel Agent",
            "type":"Entertainment"
        }
    ],
    "sg:phone":"+61 1300 762 410",
    "sg:postcode":"2007",
    "sg:province":"NSW",
    "sg:tags":[
        "consultant"
    ],
    "wof:name":"Student Flights",
    "wof:placetype":"venue"
},
  "geometry": {"coordinates":[151.19526672399999,-33.8842582703],"type":"Point"}
}