{
  "type": "Feature",
  "properties": {
    "addr:full":"33 Balmoral Rd Port Pirie SA 5540",
    "addr:housenumber":"33",
    "addr:postcode":"5540",
    "addr:street":"Balmoral Rd",
    "iso:country":"AU",
    "sg:address":"33 Balmoral Rd",
    "sg:city":"Port Pirie",
    "sg:classifiers":[
        {
            "category":"Social Services",
            "subcategory":"Retirement Home",
            "type":"Services"
        }
    ],
    "sg:phone":"+61 8 8633 1262",
    "sg:postcode":"5540",
    "sg:province":"SA",
    "sg:tags":[
        "accommodation",
        "special"
    ],
    "wof:name":"Orana Accommodation Centre",
    "wof:placetype":"venue"
},
  "geometry": {"coordinates":[138.010955811,-33.1988067627],"type":"Point"}
}