{
  "type": "Feature",
  "properties": {
    "addr:full":"9 Milly Crt Malaga WA 6090",
    "addr:housenumber":"9",
    "addr:postcode":"6090",
    "addr:street":"Milly Crt",
    "iso:country":"AU",
    "sg:address":"9 Milly Crt",
    "sg:city":"Malaga",
    "sg:classifiers":[
        {
            "category":"Manufacturing",
            "subcategory":"Metals",
            "type":"Manufacturing & Wholesale Goods"
        }
    ],
    "sg:phone":"+61 8 9248 1355",
    "sg:postcode":"6090",
    "sg:province":"WA",
    "sg:tags":[
        "sheet",
        "worker"
    ],
    "wof:name":"Wayne Vigar Sheetmetal",
    "wof:placetype":"venue"
},
  "geometry": {"coordinates":[115.914558411,-31.8603534698],"type":"Point"}
}