{
  "type": "Feature",
  "properties": {
    "addr:full":"74 Single St Werris Creek NSW 2341",
    "addr:housenumber":"74",
    "addr:postcode":"2341",
    "addr:street":"Single St",
    "iso:country":"AU",
    "sg:address":"74 Single St",
    "sg:city":"Werris Creek",
    "sg:classifiers":[
        {
            "category":"Personal",
            "subcategory":"Beauty Salon",
            "type":"Services"
        }
    ],
    "sg:phone":"+61 2 6768 7360",
    "sg:postcode":"2341",
    "sg:province":"NSW",
    "sg:tags":[
        "hairdresser"
    ],
    "wof:name":"A Cut Above",
    "wof:placetype":"venue"
},
  "geometry": {"coordinates":[150.64712524399999,-31.3515148163],"type":"Point"}
}