{
  "type": "Feature",
  "properties": {
    "iso:country":"AU",
    "sg:address":"4 Adelaide St",
    "sg:city":"Fremantle",
    "sg:classifiers":[
        {
            "category":"Banks & Credit Unions",
            "subcategory":"Bank",
            "type":"Services"
        }
    ],
    "sg:phone":"+61 13 20 32",
    "sg:postcode":"6160",
    "sg:province":"WA",
    "wof:name":"Westpac",
    "wof:placetype":"venue"
},
  "geometry": {"coordinates":[115.74743700000001,-32.053928],"type":"Point"}
}