{
  "type": "Feature",
  "properties": {
    "iso:country":"AU",
    "sg:address":"Johnson St",
    "sg:city":"Maffra",
    "sg:classifiers":[
        {
            "category":"Wholesale",
            "subcategory":"Fruits & Vegetables",
            "type":"Manufacturing & Wholesale Goods"
        }
    ],
    "sg:phone":"+61 3 5147 3100",
    "sg:postcode":"3860",
    "sg:province":"VIC",
    "sg:tags":[
        "produce",
        "grain"
    ],
    "wof:name":"Maffra Farm Supplies",
    "wof:placetype":"venue"
},
  "geometry": {"coordinates":[146.98312377900001,-37.9709205627],"type":"Point"}
}