{
  "type": "Feature",
  "properties": {
    "iso:country":"AU",
    "sg:address":"305 Tingira St",
    "sg:city":"Pinkenba",
    "sg:classifiers":[
        {
            "category":"Transit Center",
            "subcategory":"Freight",
            "type":"Transportation"
        }
    ],
    "sg:phone":"+61 13 21 80",
    "sg:postcode":"4008",
    "sg:province":"QLD",
    "sg:tags":[
        "forklift",
        "truck"
    ],
    "wof:name":"Kleenheat Gas",
    "wof:placetype":"venue"
},
  "geometry": {"coordinates":[153.13359069800001,-27.4180812836],"type":"Point"}
}