{
  "type": "Feature",
  "properties": {
    "addr:full":"66- 70 Mather St Mt Louisa QLD 4814",
    "addr:housenumber":"70",
    "addr:postcode":"4814",
    "addr:street":"Mather St Mt Louisa",
    "iso:country":"AU",
    "sg:address":"66- 70 Mather St",
    "sg:city":"Mt Louisa",
    "sg:classifiers":[
        {
            "category":"Building & Trades",
            "subcategory":"Construction",
            "type":"Services"
        }
    ],
    "sg:phone":"+61 7 4774 7533",
    "sg:postcode":"4814",
    "sg:province":"QLD",
    "sg:tags":[
        "earth",
        "excavating",
        "moving",
        "contractor"
    ],
    "wof:name":"Clarks Mini Excavations & Plant Hire Pty Ltd",
    "wof:placetype":"venue"
},
  "geometry": {"coordinates":[146.74856600000001,-19.269024],"type":"Point"}
}