{
  "type": "Feature",
  "properties": {
    "iso:country":"AU",
    "sg:address":"204 Lyons Rd",
    "sg:city":"Drummoyne",
    "sg:classifiers":[
        {
            "category":"Personal",
            "subcategory":"Beauty Salon",
            "type":"Services"
        }
    ],
    "sg:phone":"+61 2 9181 1988",
    "sg:postcode":"2047",
    "sg:province":"NSW",
    "wof:name":"Retreat Spa & Beauty",
    "wof:placetype":"venue"
},
  "geometry": {"coordinates":[151.14567600000001,-33.856743],"type":"Point"}
}