{
  "type": "Feature",
  "properties": {
    "iso:country":"AU",
    "sg:address":"20 Eva St",
    "sg:city":"Coorparoo",
    "sg:classifiers":[
        {
            "category":"Personal",
            "subcategory":"Beauty Salon",
            "type":"Services"
        }
    ],
    "sg:phone":"+61 7 3397 5274",
    "sg:postcode":"4151",
    "sg:province":"QLD",
    "sg:tags":[
        "hairdresser"
    ],
    "wof:name":"Communique Hair Design",
    "wof:placetype":"venue"
},
  "geometry": {"coordinates":[153.06874084500001,-27.5045814514],"type":"Point"}
}