{
  "type": "Feature",
  "properties": {
    "addr:full":"Marrar Rd Marrar NSW 2652",
    "addr:postcode":"2652",
    "addr:street":"Marrar Rd",
    "iso:country":"AU",
    "sg:address":"Marrar Rd",
    "sg:city":"Marrar",
    "sg:classifiers":[
        {
            "category":"Farming",
            "subcategory":"Farm",
            "type":"Manufacturing & Wholesale Goods"
        }
    ],
    "sg:phone":"+61 2 6927 4347",
    "sg:postcode":"2652",
    "sg:province":"NSW",
    "sg:tags":[
        "farmer"
    ],
    "wof:name":"Lowther J J & G M",
    "wof:placetype":"venue"
},
  "geometry": {"coordinates":[147.354644775,-34.8256187439],"type":"Point"}
}