{
  "type": "Feature",
  "properties": {
    "iso:country":"AU",
    "sg:address":"106 Herald St",
    "sg:city":"Cheltenham",
    "sg:classifiers":[
        {
            "category":"Banks & Credit Unions",
            "subcategory":"Bureau De Change",
            "type":"Services"
        }
    ],
    "sg:phone":"+61 3 9532 1980",
    "sg:postcode":"3192",
    "sg:province":"VIC",
    "sg:tags":[
        "gas",
        "natural",
        "lp",
        "equipment"
    ],
    "wof:name":"L G Motor Gas P/L",
    "wof:placetype":"venue"
},
  "geometry": {"coordinates":[145.07371520999999,-37.9525756836],"type":"Point"}
}