{
  "type": "Feature",
  "properties": {
    "addr:full":"Level 6, 85 Queen St Melbourne VIC 3000",
    "addr:housenumber":"85",
    "addr:postcode":"3000",
    "addr:street":"Queen St",
    "iso:country":"AU",
    "sg:address":"Level 6, 85 Queen St",
    "sg:city":"Melbourne",
    "sg:classifiers":[
        {
            "category":"Professional",
            "subcategory":"Computer Services",
            "type":"Services"
        }
    ],
    "sg:phone":"+61 3 9602 5077",
    "sg:postcode":"3000",
    "sg:province":"VIC",
    "sg:tags":[
        "training"
    ],
    "wof:name":"Training Choice Computer Training Rooms",
    "wof:placetype":"venue"
},
  "geometry": {"coordinates":[144.96124267600001,-37.816532135],"type":"Point"}
}