{
  "type": "Feature",
  "properties": {
    "addr:full":"Level 1 , 1 Southbank Blv Southbank VIC 3006",
    "addr:housenumber":"1",
    "addr:postcode":"3006",
    "addr:street":"Southbank Blv",
    "iso:country":"AU",
    "sg:address":"Level 1",
    "sg:city":", 1 Southbank Blv Southbank",
    "sg:classifiers":[
        {
            "category":"Professional",
            "subcategory":"Employment Agencies",
            "type":"Services"
        }
    ],
    "sg:phone":"+61 1300 553 776",
    "sg:postcode":"3006",
    "sg:province":"VIC",
    "sg:tags":[
        "provider",
        "internet"
    ],
    "wof:name":"Pacific Internet",
    "wof:placetype":"venue"
},
  "geometry": {"coordinates":[144.962799072,-37.8219337463],"type":"Point"}
}