{
  "type": "Feature",
  "properties": {
    "addr:full":"351 Tor St Wilsonton QLD 4350",
    "addr:postcode":"351;4350",
    "addr:street":"Tor St",
    "iso:country":"AU",
    "sg:address":"351 Tor St",
    "sg:city":"Wilsonton",
    "sg:classifiers":[
        {
            "category":"Health Services",
            "subcategory":"Dentist",
            "type":"Services"
        }
    ],
    "sg:phone":"+61 7 4634 1788",
    "sg:postcode":"4350",
    "sg:province":"QLD",
    "wof:name":"Christensen Neil",
    "wof:placetype":"venue"
},
  "geometry": {"coordinates":[151.92482000000001,-27.542891],"type":"Point"}
}