{
  "type": "Feature",
  "properties": {
    "iso:country":"AU",
    "sg:address":"Un 1/ 261 Marrickville Rd",
    "sg:city":"Marrickville",
    "sg:classifiers":[
        {
            "category":"Personal",
            "subcategory":"Beauty Salon",
            "type":"Services"
        }
    ],
    "sg:phone":"+61 2 9564 3393",
    "sg:postcode":"2204",
    "sg:province":"NSW",
    "wof:name":"Finest Nails & Beauty Salon",
    "wof:placetype":"venue"
},
  "geometry": {"coordinates":[151.155945,-33.910172],"type":"Point"}
}