{
  "type": "Feature",
  "properties": {
    "addr:full":"6 Rundle St Ulladulla NSW 2539",
    "addr:housenumber":"6",
    "addr:postcode":"2539",
    "addr:street":"Rundle St",
    "iso:country":"AU",
    "sg:address":"6 Rundle St",
    "sg:city":"Ulladulla",
    "sg:classifiers":[
        {
            "category":"Personal",
            "subcategory":"Beauty Salon",
            "type":"Services"
        }
    ],
    "sg:phone":"+61 2 4455 2364",
    "sg:postcode":"2539",
    "sg:province":"NSW",
    "sg:tags":[
        "hairdresser"
    ],
    "wof:name":"Anthony's Barber Shop",
    "wof:placetype":"venue"
},
  "geometry": {"coordinates":[150.468063355,-35.3566322327],"type":"Point"}
}