{
  "type": "Feature",
  "properties": {
    "addr:full":"534 Station St Carrum VIC 3197",
    "addr:housenumber":"534",
    "addr:postcode":"3197",
    "addr:street":"Station St",
    "iso:country":"AU",
    "sg:address":"534 Station St",
    "sg:city":"Carrum",
    "sg:classifiers":[
        {
            "category":"Professional",
            "subcategory":"Accounting & Tax Preparation",
            "type":"Services"
        }
    ],
    "sg:phone":"+61 3 9772 9364",
    "sg:postcode":"3197",
    "sg:province":"VIC",
    "sg:tags":[
        "consultant",
        "taxation"
    ],
    "wof:name":"Lobo J Pty Ltd",
    "wof:placetype":"venue"
},
  "geometry": {"coordinates":[145.12379455600001,-38.0781707764],"type":"Point"}
}