{
  "type": "Feature",
  "properties": {
    "addr:full":"127 James St Templestowe VIC 3106",
    "addr:housenumber":"127",
    "addr:postcode":"3106",
    "addr:street":"James St",
    "iso:country":"AU",
    "sg:address":"127 James St",
    "sg:city":"Templestowe",
    "sg:classifiers":[
        {
            "category":"Farming",
            "subcategory":"Fish & Marine Products",
            "type":"Manufacturing & Wholesale Goods"
        }
    ],
    "sg:phone":"+61 3 9846 5551",
    "sg:postcode":"3106",
    "sg:province":"VIC",
    "sg:tags":[
        "organic"
    ],
    "wof:name":"Organic Central",
    "wof:placetype":"venue"
},
  "geometry": {"coordinates":[145.129394531,-37.7567329407],"type":"Point"}
}