{
  "type": "Feature",
  "properties": {
    "addr:full":"Yackandandah Rd Myrtleford VIC 3737",
    "addr:postcode":"3737",
    "addr:street":"Yackandandah Rd",
    "iso:country":"AU",
    "sg:address":"Yackandandah Rd",
    "sg:city":"Myrtleford",
    "sg:classifiers":[
        {
            "category":"Sports & Exercise",
            "subcategory":"Golf",
            "type":"Entertainment"
        }
    ],
    "sg:phone":"+61 3 5752 2286",
    "sg:postcode":"3737",
    "sg:province":"VIC",
    "sg:tags":[
        "club"
    ],
    "wof:name":"Myrtleford Golf Club",
    "wof:placetype":"venue"
},
  "geometry": {"coordinates":[146.720870972,-36.5589904785],"type":"Point"}
}