{
  "type": "Feature",
  "properties": {
    "addr:full":"292 Kissing Point Rd Ermington NSW 2115",
    "addr:housenumber":"292",
    "addr:postcode":"2115",
    "addr:street":"Kissing Point Rd",
    "iso:country":"AU",
    "sg:address":"292 Kissing Point Rd",
    "sg:city":"Ermington",
    "sg:classifiers":[
        {
            "category":"Autos & Motor Vehicles",
            "subcategory":"Auto Supplies",
            "type":"Retail Goods"
        }
    ],
    "sg:phone":"+61 408 641 812",
    "sg:postcode":"2115",
    "sg:province":"NSW",
    "sg:tags":[
        "accessory"
    ],
    "wof:name":"Sam's Pinstripe Auto Accessories",
    "wof:placetype":"venue"
},
  "geometry": {"coordinates":[151.05763244600001,-33.801864624],"type":"Point"}
}