{
  "type": "Feature",
  "properties": {
    "iso:country":"AU",
    "sg:address":"Shop 1",
    "sg:city":"Dog Swamp Shopping Centre Joondanna",
    "sg:classifiers":[
        {
            "category":"Food & Beverages",
            "subcategory":"Fruits & Vegetables",
            "type":"Retail Goods"
        }
    ],
    "sg:phone":"+61 8 9242 1640",
    "sg:postcode":"6060",
    "sg:province":"WA",
    "sg:tags":[
        "greengrocer",
        "fruiterer"
    ],
    "wof:name":"Fresh Stop Market",
    "wof:placetype":"venue"
},
  "geometry": {"coordinates":[115.83831024200001,-31.9103908539],"type":"Point"}
}