{
  "type": "Feature",
  "properties": {
    "addr:full":"267 King St Newtown NSW 2042",
    "addr:housenumber":"267",
    "addr:postcode":"2042",
    "addr:street":"King St",
    "iso:country":"AU",
    "sg:address":"267 King St",
    "sg:city":"Newtown",
    "sg:classifiers":[
        {
            "category":"Shopping",
            "subcategory":"Jewelry",
            "type":"Retail Goods"
        }
    ],
    "sg:phone":"+61 2 9550 4559",
    "sg:postcode":"2042",
    "sg:province":"NSW",
    "sg:tags":[
        "jeweller"
    ],
    "wof:name":"Wood J H Jewellers",
    "wof:placetype":"venue"
},
  "geometry": {"coordinates":[151.18026699999999,-33.89616],"type":"Point"}
}