{
  "type": "Feature",
  "properties": {
    "addr:full":"39 Meenan St Garbutt QLD 4814",
    "addr:housenumber":"39",
    "addr:postcode":"4814",
    "addr:street":"Meenan St",
    "iso:country":"AU",
    "sg:address":"39 Meenan St",
    "sg:city":"Garbutt",
    "sg:classifiers":[
        {
            "category":"Fast Food",
            "type":"Food & Drink"
        }
    ],
    "sg:phone":"+61 7 4725 5205",
    "sg:postcode":"4814",
    "sg:province":"QLD",
    "sg:tags":[
        "away",
        "take"
    ],
    "wof:name":"Surf'N Sand Fish Bar",
    "wof:placetype":"venue"
},
  "geometry": {"coordinates":[146.77534499999999,-19.26005],"type":"Point"}
}