{
  "type": "Feature",
  "properties": {
    "addr:full":"16 Church St Ryde NSW 2112",
    "addr:housenumber":"16",
    "addr:postcode":"2112",
    "addr:street":"Church St",
    "iso:country":"AU",
    "sg:address":"16 Church St",
    "sg:city":"Ryde",
    "sg:classifiers":[
        {
            "category":"Restaurant",
            "type":"Food & Drink"
        }
    ],
    "sg:phone":"+61 2 9808 3220",
    "sg:postcode":"2112",
    "sg:province":"NSW",
    "wof:name":"Bivianos At Ryde",
    "wof:placetype":"venue"
},
  "geometry": {"coordinates":[151.10577392600001,-33.8139801025],"type":"Point"}
}