{
  "type": "Feature",
  "properties": {
    "addr:full":"Outlook Drv Figtree NSW 2525",
    "addr:postcode":"2525",
    "addr:street":"Outlook Drv",
    "iso:country":"AU",
    "sg:address":"Outlook Drv",
    "sg:city":"Figtree",
    "sg:classifiers":[
        {
            "category":"Retail",
            "subcategory":"Auto Repair",
            "type":"Services"
        }
    ],
    "sg:phone":"+61 408 425 650",
    "sg:postcode":"2525",
    "sg:province":"NSW",
    "sg:tags":[
        "repairer",
        "motor",
        "engineer"
    ],
    "wof:name":"Waldo's Mobile Automotive Services",
    "wof:placetype":"venue"
},
  "geometry": {"coordinates":[150.85731506400001,-34.4352493286],"type":"Point"}
}