{
  "type": "Feature",
  "properties": {
    "addr:full":"6 Gwynne St Watson ACT 2602",
    "addr:housenumber":"6",
    "addr:postcode":"2602",
    "addr:street":"Gwynne St",
    "iso:country":"AU",
    "sg:address":"6 Gwynne St",
    "sg:city":"Watson",
    "sg:classifiers":[
        {
            "category":"Education",
            "subcategory":"Kindergarten",
            "type":"Public Place"
        }
    ],
    "sg:phone":"+61 2 6241 1122",
    "sg:postcode":"2602",
    "sg:province":"ACT",
    "sg:tags":[
        "pre-schools"
    ],
    "wof:name":"Nipperville Early Learning Centre",
    "wof:placetype":"venue"
},
  "geometry": {"coordinates":[149.15246582,-35.2388267517],"type":"Point"}
}