{
  "type": "Feature",
  "properties": {
    "iso:country":"AU",
    "sg:address":"112 High St",
    "sg:city":"Fremantle",
    "sg:classifiers":[
        {
            "category":"Farming",
            "subcategory":"Fish & Marine Products",
            "type":"Manufacturing & Wholesale Goods"
        }
    ],
    "sg:phone":"+61 8 9430 7773",
    "sg:postcode":"6160",
    "sg:province":"WA",
    "sg:tags":[
        "fibre",
        "hemp",
        "oil"
    ],
    "wof:name":"Margaret River Hemp Co",
    "wof:placetype":"venue"
},
  "geometry": {"coordinates":[115.746719,-32.055458],"type":"Point"}
}