{
  "type": "Feature",
  "properties": {
    "addr:full":"Cnr Ben Boyd Rd & Ernest St Neutral Bay NSW 2089",
    "addr:postcode":"2089",
    "addr:street":"Cnr Ben Boyd Rd & Ernest St",
    "iso:country":"AU",
    "sg:address":"Cnr Ben Boyd Rd & Ernest St",
    "sg:city":"Neutral Bay",
    "sg:classifiers":[
        {
            "category":"Retail",
            "subcategory":"Auto Repair",
            "type":"Services"
        }
    ],
    "sg:phone":"+61 2 9953 1944",
    "sg:postcode":"2089",
    "sg:province":"NSW",
    "sg:tags":[
        "repairer",
        "motor",
        "engineer"
    ],
    "wof:name":"K - Mart Tyre & Auto Service",
    "wof:placetype":"venue"
},
  "geometry": {"coordinates":[151.21942138700001,-33.8306694031],"type":"Point"}
}