{
  "type": "Feature",
  "properties": {
    "addr:full":"116 Moray St South Melbourne VIC 3205",
    "addr:housenumber":"116",
    "addr:postcode":"3205",
    "addr:street":"Moray St",
    "iso:country":"AU",
    "sg:address":"116 Moray St",
    "sg:city":"South Melbourne",
    "sg:classifiers":[
        {
            "category":"Home & Garden",
            "subcategory":"Building Materials",
            "type":"Retail Goods"
        }
    ],
    "sg:phone":"+61 3 9699 7363",
    "sg:postcode":"3205",
    "sg:province":"VIC",
    "sg:tags":[
        "merchant",
        "glass",
        "glazier"
    ],
    "wof:name":"Gordon Glass (S/Melb) Pty Ltd",
    "wof:placetype":"venue"
},
  "geometry": {"coordinates":[144.96165500000001,-37.829605],"type":"Point"}
}