{
  "type": "Feature",
  "properties": {
    "addr:full":"48 Wingara Ave Keilor East VIC 3033",
    "addr:housenumber":"48",
    "addr:postcode":"3033",
    "addr:street":"Wingara Ave",
    "iso:country":"AU",
    "sg:address":"48 Wingara Ave",
    "sg:city":"Keilor East",
    "sg:classifiers":[
        {
            "category":"Personal",
            "subcategory":"Beauty Salon",
            "type":"Services"
        }
    ],
    "sg:phone":"+61 3 9331 6771",
    "sg:postcode":"3033",
    "sg:province":"VIC",
    "wof:name":"Variations",
    "wof:placetype":"venue"
},
  "geometry": {"coordinates":[144.867401,-37.733028],"type":"Point"}
}