{
  "type": "Feature",
  "properties": {
    "iso:country":"AU",
    "sg:address":"152 Cambridge St",
    "sg:city":"West Launceston",
    "sg:classifiers":[
        {
            "category":"Wholesale",
            "subcategory":"Non-durable Goods",
            "type":"Manufacturing & Wholesale Goods"
        }
    ],
    "sg:phone":"+61 3 6344 3890",
    "sg:postcode":"7250",
    "sg:province":"TAS",
    "sg:tags":[
        "wholesaler",
        "mfrs",
        "cosmetic"
    ],
    "wof:name":"Ali Hamylton Cosmetics",
    "wof:placetype":"venue"
},
  "geometry": {"coordinates":[147.13117980999999,-41.4613265991],"type":"Point"}
}