{
  "type": "Feature",
  "properties": {
    "iso:country":"AU",
    "sg:address":"131 Sutton St",
    "sg:city":"Redcliffe",
    "sg:classifiers":[
        {
            "category":"Professional",
            "subcategory":"Accounting & Tax Preparation",
            "type":"Services"
        }
    ],
    "sg:phone":"+61 7 3883 2433",
    "sg:postcode":"4020",
    "sg:province":"QLD",
    "sg:tags":[
        "consultant",
        "taxation"
    ],
    "wof:name":"TLA Business Services",
    "wof:placetype":"venue"
},
  "geometry": {"coordinates":[153.11479199999999,-27.229506],"type":"Point"}
}