{
  "type": "Feature",
  "properties": {
    "addr:full":"82 Albert St Preston VIC 3072",
    "addr:housenumber":"82",
    "addr:postcode":"3072",
    "addr:street":"Albert St",
    "iso:country":"AU",
    "sg:address":"82 Albert St",
    "sg:city":"Preston",
    "sg:classifiers":[
        {
            "category":"Communications",
            "subcategory":"Film & Video Production",
            "type":"Services"
        }
    ],
    "sg:phone":"+61 3 9470 2088",
    "sg:postcode":"3072",
    "sg:province":"VIC",
    "sg:tags":[
        "television",
        "system",
        "circuit",
        "closed"
    ],
    "wof:name":"Wiltech Electrical & Security P/L",
    "wof:placetype":"venue"
},
  "geometry": {"coordinates":[145.02264404300001,-37.7433891296],"type":"Point"}
}