{
  "type": "Feature",
  "properties": {
    "iso:country":"AU",
    "sg:address":"454 Hampton St",
    "sg:city":"Hampton",
    "sg:classifiers":[
        {
            "category":"Personal",
            "subcategory":"Beauty Salon",
            "type":"Services"
        }
    ],
    "sg:phone":"+61 3 9521 0695",
    "sg:postcode":"3188",
    "sg:province":"VIC",
    "sg:tags":[
        "hairdresser"
    ],
    "wof:name":"Sansal Hair",
    "wof:placetype":"venue"
},
  "geometry": {"coordinates":[145.00282287600001,-37.9366722107],"type":"Point"}
}