{
  "type": "Feature",
  "properties": {
    "addr:full":"Trouts Rd Everton Park QLD 4053",
    "addr:postcode":"4053",
    "addr:street":"Trouts Rd",
    "iso:country":"AU",
    "sg:address":"Trouts Rd",
    "sg:city":"Everton Park",
    "sg:classifiers":[
        {
            "category":"Personal",
            "subcategory":"Hair Removal",
            "type":"Services"
        }
    ],
    "sg:phone":"+61 7 3855 9731",
    "sg:postcode":"4053",
    "sg:province":"QLD",
    "wof:name":"Mias Beauty Room",
    "wof:placetype":"venue"
},
  "geometry": {"coordinates":[152.99737548799999,-27.4023952484],"type":"Point"}
}