{
  "type": "Feature",
  "properties": {
    "addr:full":"17 Hamilton Pl Mt Waverley VIC 3149",
    "addr:housenumber":"17",
    "addr:postcode":"3149",
    "addr:street":"Hamilton Pl Mt",
    "iso:country":"AU",
    "sg:address":"17 Hamilton Pl",
    "sg:city":"Mt Waverley",
    "sg:classifiers":[
        {
            "category":"Deli",
            "type":"Food & Drink"
        }
    ],
    "sg:phone":"+61 3 9807 6911",
    "sg:postcode":"3149",
    "sg:province":"VIC",
    "sg:tags":[
        "delicatessen"
    ],
    "wof:name":"Caputo International Foods",
    "wof:placetype":"venue"
},
  "geometry": {"coordinates":[145.12754821799999,-37.8761024475],"type":"Point"}
}