{
  "type": "Feature",
  "properties": {
    "iso:country":"AU",
    "sg:address":"5 Thomas St",
    "sg:city":"St Marys",
    "sg:classifiers":[
        {
            "category":"Building & Trades",
            "subcategory":"Plumbing",
            "type":"Services"
        }
    ],
    "sg:phone":"+61 2 9670 2526",
    "sg:postcode":"2760",
    "sg:province":"NSW",
    "sg:tags":[
        "plumber",
        "gasfitters"
    ],
    "wof:name":"Balloot Plumbing Contractors",
    "wof:placetype":"venue"
},
  "geometry": {"coordinates":[150.777511597,-33.781867981],"type":"Point"}
}