{
  "type": "Feature",
  "properties": {
    "addr:full":"9/10-12 Vulcan Rd Canning Vale WA 6155",
    "addr:housenumber":"/ 10-12",
    "addr:postcode":"6155",
    "addr:street":"Vulcan Rd",
    "iso:country":"AU",
    "sg:address":"9/10-12 Vulcan Rd",
    "sg:city":"Canning Vale",
    "sg:classifiers":[
        {
            "category":"Home & Garden",
            "subcategory":"Building Materials",
            "type":"Retail Goods"
        }
    ],
    "sg:phone":"+61 8 9455 6789",
    "sg:postcode":"6155",
    "sg:province":"WA",
    "sg:tags":[
        "balustrading"
    ],
    "wof:name":"Exclusive Wrought Iron",
    "wof:placetype":"venue"
},
  "geometry": {"coordinates":[115.92897000000001,-32.058323],"type":"Point"}
}