{
  "type": "Feature",
  "properties": {
    "addr:full":"28 Johnston St Collingwood VIC 3066",
    "addr:housenumber":"28",
    "addr:postcode":"3066",
    "addr:street":"Johnston St",
    "iso:country":"AU",
    "sg:address":"28 Johnston St",
    "sg:city":"Collingwood",
    "sg:classifiers":[
        {
            "category":"Retail",
            "subcategory":"Auto Repair",
            "type":"Services"
        }
    ],
    "sg:phone":"+61 3 9495 6608",
    "sg:postcode":"3066",
    "sg:province":"VIC",
    "sg:tags":[
        "repairer",
        "motor",
        "engineer"
    ],
    "wof:name":"Thinh Motor Repairs",
    "wof:placetype":"venue"
},
  "geometry": {"coordinates":[144.98574829099999,-37.79895401],"type":"Point"}
}