{
  "type": "Feature",
  "properties": {
    "addr:full":"Tondoon Botanical Gardens Glenlyon Rd Gladstone QLD 4680",
    "addr:postcode":"4680",
    "addr:street":"Glenlyon Rd",
    "iso:country":"AU",
    "sg:address":"Tondoon Botanical Gardens Glenlyon Rd",
    "sg:city":"Gladstone",
    "sg:classifiers":[
        {
            "category":"Cafe",
            "type":"Food & Drink"
        }
    ],
    "sg:phone":"+61 7 4979 3388",
    "sg:postcode":"4680",
    "sg:province":"QLD",
    "wof:name":"Tondoon Gardens Cafe",
    "wof:placetype":"venue"
},
  "geometry": {"coordinates":[151.260421753,-23.8574371338],"type":"Point"}
}