{
  "type": "Feature",
  "properties": {
    "iso:country":"AU",
    "sg:address":"29 New St St",
    "sg:city":"Frankston",
    "sg:classifiers":[
        {
            "category":"Retail",
            "subcategory":"Auto Repair",
            "type":"Services"
        }
    ],
    "sg:phone":"+61 3 9783 8322",
    "sg:postcode":"3199",
    "sg:province":"VIC",
    "sg:tags":[
        "repairer",
        "motor",
        "engineer"
    ],
    "wof:name":"Phil Hume Automotive",
    "wof:placetype":"venue"
},
  "geometry": {"coordinates":[145.12840270999999,-38.1306228638],"type":"Point"}
}