{
  "type": "Feature",
  "properties": {
    "addr:full":"195 Hastings River Drv Port Macquarie NSW 2444",
    "addr:housenumber":"195",
    "addr:postcode":"2444",
    "addr:street":"Hastings River Drv",
    "iso:country":"AU",
    "sg:address":"195 Hastings River Drv",
    "sg:city":"Port Macquarie",
    "sg:classifiers":[
        {
            "category":"Retail",
            "subcategory":"Auto Repair",
            "type":"Services"
        }
    ],
    "sg:phone":"+61 2 6583 1235",
    "sg:postcode":"2444",
    "sg:province":"NSW",
    "sg:tags":[
        "repairer",
        "motor",
        "engineer"
    ],
    "wof:name":"Maca's Mechanical Repairs",
    "wof:placetype":"venue"
},
  "geometry": {"coordinates":[152.88696300000001,-31.43071],"type":"Point"}
}