{
  "type": "Feature",
  "properties": {
    "iso:country":"AU",
    "sg:address":"13 Leslie St",
    "sg:city":"Dandenong",
    "sg:classifiers":[
        {
            "category":"Home & Garden",
            "subcategory":"Building Materials",
            "type":"Retail Goods"
        }
    ],
    "sg:phone":"+61 3 9792 2777",
    "sg:postcode":"3175",
    "sg:province":"VIC",
    "sg:tags":[
        "gate"
    ],
    "wof:name":"All Steel Security",
    "wof:placetype":"venue"
},
  "geometry": {"coordinates":[145.198974609,-37.9918785095],"type":"Point"}
}