{
  "type": "Feature",
  "properties": {
    "addr:full":"793 Park St Brunswick VIC 3056",
    "addr:housenumber":"793",
    "addr:postcode":"3056",
    "addr:street":"Park St",
    "iso:country":"AU",
    "sg:address":"793 Park St",
    "sg:city":"Brunswick",
    "sg:classifiers":[
        {
            "category":"Travel",
            "subcategory":"Hotels & Motels",
            "type":"Entertainment"
        }
    ],
    "sg:phone":"+61 3 9388 0055",
    "sg:postcode":"3056",
    "sg:province":"VIC",
    "wof:name":"Oxley Lodge",
    "wof:placetype":"venue"
},
  "geometry": {"coordinates":[144.950683594,-37.7767028809],"type":"Point"}
}