{
  "type": "Feature",
  "properties": {
    "addr:full":"Leeming Medical Centre 1 Westminster Ave Leeming WA 6149",
    "addr:housenumber":"1",
    "addr:postcode":"6149",
    "addr:street":"Westminster Ave",
    "iso:country":"AU",
    "sg:address":"Leeming Medical Centre 1 Westminster Ave",
    "sg:city":"Leeming",
    "sg:classifiers":[
        {
            "category":"Health Services",
            "subcategory":"Health Practitioner",
            "type":"Services"
        }
    ],
    "sg:phone":"+61 3 9332 9599",
    "sg:postcode":"6149",
    "sg:province":"WA",
    "sg:tags":[
        "pathologist",
        "speech"
    ],
    "wof:name":"Williams Sally",
    "wof:placetype":"venue"
},
  "geometry": {"coordinates":[115.85916899999999,-32.074306],"type":"Point"}
}