{
  "type": "Feature",
  "properties": {
    "addr:full":"23 Sentenial St Kuraby QLD 4112",
    "addr:housenumber":"23",
    "addr:postcode":"4112",
    "addr:street":"Sentenial St",
    "iso:country":"AU",
    "sg:address":"23 Sentenial St",
    "sg:city":"Kuraby",
    "sg:classifiers":[
        {
            "category":"Home & Garden",
            "subcategory":"Carpets & Floor Coverings",
            "type":"Retail Goods"
        }
    ],
    "sg:phone":"+61 414 284 288",
    "sg:postcode":"4112",
    "sg:province":"QLD",
    "sg:tags":[
        "tile",
        "wall",
        "layer"
    ],
    "wof:name":"Tilemasters Tiling Experts",
    "wof:placetype":"venue"
},
  "geometry": {"coordinates":[153.09248352,-27.6063804626],"type":"Point"}
}