{
  "type": "Feature",
  "properties": {
    "addr:full":"26 Cool St Reservoir VIC 3073",
    "addr:housenumber":"26",
    "addr:postcode":"3073",
    "addr:street":"Cool St",
    "iso:country":"AU",
    "sg:address":"26 Cool St",
    "sg:city":"Reservoir",
    "sg:classifiers":[
        {
            "category":"Professional",
            "subcategory":"Art Services",
            "type":"Services"
        }
    ],
    "sg:phone":"+61 3 9350 2375",
    "sg:postcode":"3073",
    "sg:province":"VIC",
    "sg:tags":[
        "graphic",
        "designer"
    ],
    "wof:name":"White Space Image Design",
    "wof:placetype":"venue"
},
  "geometry": {"coordinates":[144.985275269,-37.725933075],"type":"Point"}
}