{
  "type": "Feature",
  "properties": {
    "iso:country":"AU",
    "sg:address":"361 Darling St",
    "sg:city":"Balmain",
    "sg:classifiers":[
        {
            "category":"Fast Food",
            "type":"Food & Drink"
        }
    ],
    "sg:phone":"+61 2 9810 7652",
    "sg:postcode":"2041",
    "sg:province":"NSW",
    "sg:tags":[
        "away",
        "take"
    ],
    "wof:name":"Nicolaidis P",
    "wof:placetype":"venue"
},
  "geometry": {"coordinates":[151.178207,-33.856396],"type":"Point"}
}