{
  "type": "Feature",
  "properties": {
    "iso:country":"AU",
    "sg:address":"Cnr Quakers Rd & Allendale St",
    "sg:city":"Marayong",
    "sg:classifiers":[
        {
            "category":"Social Services",
            "subcategory":"Child Care",
            "type":"Services"
        }
    ],
    "sg:phone":"+61 2 9622 5396",
    "sg:postcode":"2148",
    "sg:province":"NSW",
    "sg:tags":[
        "support",
        "health"
    ],
    "wof:name":"Early Childhood Health Centres",
    "wof:placetype":"venue"
},
  "geometry": {"coordinates":[150.89976501500001,-33.746257782],"type":"Point"}
}