{
  "type": "Feature",
  "properties": {
    "addr:full":"Shop 13, Kiama Centro Terralong St Kiama NSW 2533",
    "addr:housenumber":"shop 13",
    "addr:postcode":"2533",
    "addr:street":"Kiama;St",
    "iso:country":"AU",
    "sg:address":"Shop 13, Kiama Centro Terralong St",
    "sg:city":"Kiama",
    "sg:classifiers":[
        {
            "category":"Health Services",
            "subcategory":"Optometrist",
            "type":"Services"
        }
    ],
    "sg:phone":"+61 2 4232 2610",
    "sg:postcode":"2533",
    "sg:province":"NSW",
    "wof:name":"Peter Rose Eyecare Plus",
    "wof:placetype":"venue"
},
  "geometry": {"coordinates":[150.84478759800001,-34.6896972656],"type":"Point"}
}