{
  "type": "Feature",
  "properties": {
    "addr:full":"17 Little Boundary Rd Laverton North VIC 3026",
    "addr:housenumber":"17",
    "addr:postcode":"3026",
    "addr:street":"Little Boundary Rd",
    "iso:country":"AU",
    "sg:address":"17 Little Boundary Rd",
    "sg:city":"Laverton North",
    "sg:classifiers":[
        {
            "category":"Shopping",
            "subcategory":"Pets & Pet Supplies",
            "type":"Retail Goods"
        }
    ],
    "sg:phone":"+61 3 9314 0844",
    "sg:postcode":"3026",
    "sg:province":"VIC",
    "sg:tags":[
        "equipment",
        "foundry"
    ],
    "wof:name":"SimsMetal",
    "wof:placetype":"venue"
},
  "geometry": {"coordinates":[144.82167100000001,-37.821568],"type":"Point"}
}