{
  "type": "Feature",
  "properties": {
    "addr:full":"453 New St Brighton VIC 3186",
    "addr:housenumber":"453",
    "addr:postcode":"3186",
    "addr:street":"New St",
    "iso:country":"AU",
    "sg:address":"453 New St",
    "sg:city":"Brighton",
    "sg:classifiers":[
        {
            "category":"Health Services",
            "subcategory":"Nursing And Care Facility",
            "type":"Services"
        }
    ],
    "sg:phone":"+61 3 9596 2914",
    "sg:postcode":"3186",
    "sg:province":"VIC",
    "sg:tags":[
        "home"
    ],
    "wof:name":"Girrawheen Nursing Home",
    "wof:placetype":"venue"
},
  "geometry": {"coordinates":[144.994796753,-37.8948669434],"type":"Point"}
}