{
  "type": "Feature",
  "properties": {
    "addr:full":"87 McLarty Ave Joondalup WA 6027",
    "addr:housenumber":"87",
    "addr:postcode":"6027",
    "addr:street":"Mclarty Ave",
    "iso:country":"AU",
    "sg:address":"87 McLarty Ave",
    "sg:city":"Joondalup",
    "sg:classifiers":[
        {
            "category":"Professional",
            "subcategory":"Employment Agencies",
            "type":"Services"
        }
    ],
    "sg:phone":"+61 8 9300 2144",
    "sg:postcode":"6027",
    "sg:province":"WA",
    "wof:name":"Bizlink",
    "wof:placetype":"venue"
},
  "geometry": {"coordinates":[115.76751709,-31.7400035858],"type":"Point"}
}