{
  "type": "Feature",
  "properties": {
    "addr:full":"8 Pandanus Crt Brunswick Heads NSW 2483",
    "addr:housenumber":"8",
    "addr:postcode":"2483",
    "addr:street":"Pandanus Crt",
    "iso:country":"AU",
    "sg:address":"8 Pandanus Crt",
    "sg:city":"Brunswick Heads",
    "sg:classifiers":[
        {
            "category":"Communications",
            "type":"Services"
        }
    ],
    "sg:phone":"+61 2 6685 1584",
    "sg:postcode":"2483",
    "sg:province":"NSW",
    "sg:tags":[
        "antenna"
    ],
    "wof:name":"Sheldon Thomson",
    "wof:placetype":"venue"
},
  "geometry": {"coordinates":[153.54684448200001,-28.537563324],"type":"Point"}
}