{
  "type": "Feature",
  "properties": {
    "iso:country":"AU",
    "sg:address":"16 Arbor Ave",
    "sg:city":"Selby",
    "sg:classifiers":[
        {
            "category":"Farming",
            "subcategory":"Fish & Marine Products",
            "type":"Manufacturing & Wholesale Goods"
        }
    ],
    "sg:phone":"+61 3 9752 5325",
    "sg:postcode":"3159",
    "sg:province":"VIC",
    "sg:tags":[
        "chemical",
        "supplier"
    ],
    "wof:name":"Advance Biologicals Pty Ltd",
    "wof:placetype":"venue"
},
  "geometry": {"coordinates":[145.36846923799999,-37.9170684814],"type":"Point"}
}