{
  "type": "Feature",
  "properties": {
    "iso:country":"AU",
    "sg:address":"Lvl 7, 55 Grafton St",
    "sg:city":"Woollahra",
    "sg:classifiers":[
        {
            "category":"Professional",
            "subcategory":"Accounting & Tax Preparation",
            "type":"Services"
        }
    ],
    "sg:phone":"+61 2 9389 1600",
    "sg:postcode":"2025",
    "sg:province":"NSW",
    "sg:tags":[
        "accountant",
        "auditor"
    ],
    "wof:name":"Baskin Clarke Pty Limited",
    "wof:placetype":"venue"
},
  "geometry": {"coordinates":[151.24577331500001,-33.8904838562],"type":"Point"}
}