{
  "type": "Feature",
  "properties": {
    "iso:country":"AU",
    "sg:address":"23 Catalina St",
    "sg:city":"Loganlea",
    "sg:classifiers":[
        {
            "category":"Building & Trades",
            "subcategory":"Construction",
            "type":"Services"
        }
    ],
    "sg:phone":"+61 415 749 494",
    "sg:postcode":"4131",
    "sg:province":"QLD",
    "sg:tags":[
        "earth",
        "excavating",
        "moving",
        "contractor"
    ],
    "wof:name":"Bob Butter Excavator Hire",
    "wof:placetype":"venue"
},
  "geometry": {"coordinates":[153.13475036599999,-27.672870636],"type":"Point"}
}