{
  "type": "Feature",
  "properties": {
    "addr:full":"46 Donaldson St Corryong NSW 3707",
    "addr:housenumber":"46",
    "addr:postcode":"3707",
    "addr:street":"Donaldson St",
    "iso:country":"AU",
    "sg:address":"46 Donaldson St",
    "sg:city":"Corryong",
    "sg:classifiers":[
        {
            "category":"Autos & Motor Vehicles",
            "subcategory":"Fuel & Gas Station",
            "type":"Retail Goods"
        }
    ],
    "sg:phone":"+61 2 6076 1119",
    "sg:postcode":"3707",
    "sg:province":"NSW",
    "wof:name":"Ampol Mid North Petroleum",
    "wof:placetype":"venue"
},
  "geometry": {"coordinates":[147.90719604500001,-36.1953964233],"type":"Point"}
}