{
  "type": "Feature",
  "properties": {
    "addr:full":"Shop 24 , Mt Ommaney Shopng Cntr Mt Ommaney QLD 4074",
    "addr:housenumber":"shop 24",
    "addr:postcode":"4074",
    "addr:street":"Mt Ommaney Shopng Cntr Mt Ommaney",
    "iso:country":"AU",
    "sg:address":"Shop 24",
    "sg:city":", Mt Ommaney Shopng Cntr Mt Ommaney",
    "sg:classifiers":[
        {
            "category":"Personal",
            "subcategory":"Skin Care",
            "type":"Services"
        }
    ],
    "sg:phone":"+61 7 3376 8018",
    "sg:postcode":"4074",
    "sg:province":"QLD",
    "sg:tags":[
        "hair",
        "product"
    ],
    "wof:name":"Price Attack",
    "wof:placetype":"venue"
},
  "geometry": {"coordinates":[152.93658447300001,-27.528755188],"type":"Point"}
}