{
  "type": "Feature",
  "properties": {
    "iso:country":"AU",
    "sg:address":"Shop 19, Wembley Road",
    "sg:city":"Woodridge",
    "sg:classifiers":[
        {
            "category":"Shopping",
            "subcategory":"Clothing, Apparel, & Fashions",
            "type":"Retail Goods"
        }
    ],
    "sg:phone":"+61 7 3209 4670",
    "sg:postcode":"4114",
    "sg:province":"QLD",
    "sg:tags":[
        "lady",
        "wear"
    ],
    "wof:name":"Silhouette",
    "wof:placetype":"venue"
},
  "geometry": {"coordinates":[153.11730957,-27.6420516968],"type":"Point"}
}