{
  "type": "Feature",
  "properties": {
    "iso:country":"AU",
    "sg:address":"124 Main Hurstbridge Rd",
    "sg:city":"Diamond Creek",
    "sg:classifiers":[
        {
            "category":"Social Services",
            "subcategory":"Retirement Home",
            "type":"Services"
        }
    ],
    "sg:phone":"+61 3 9438 5710",
    "sg:postcode":"3089",
    "sg:province":"VIC",
    "sg:tags":[
        "accommodation",
        "special"
    ],
    "wof:name":"Kilara Retirement Home",
    "wof:placetype":"venue"
},
  "geometry": {"coordinates":[145.16459699999999,-37.674938],"type":"Point"}
}