{
  "type": "Feature",
  "properties": {
    "iso:country":"AU",
    "sg:address":"Shop 1/ 5 Fitzroy St",
    "sg:city":"Sorell",
    "sg:classifiers":[
        {
            "category":"Building & Trades",
            "subcategory":"Locksmith",
            "type":"Services"
        }
    ],
    "sg:phone":"+61 3 6265 1883",
    "sg:postcode":"7172",
    "sg:province":"TAS",
    "sg:tags":[
        "lock"
    ],
    "wof:name":"Sorell Locksmiths",
    "wof:placetype":"venue"
},
  "geometry": {"coordinates":[147.562866211,-42.7830543518],"type":"Point"}
}