{
  "type": "Feature",
  "properties": {
    "iso:country":"AU",
    "sg:address":"376 Guildford Rd",
    "sg:city":"Guildford",
    "sg:classifiers":[
        {
            "category":"Health Services",
            "subcategory":"Health Practitioner",
            "type":"Services"
        }
    ],
    "sg:phone":"+61 2 9632 2009",
    "sg:postcode":"2161",
    "sg:province":"NSW",
    "sg:tags":[
        "bowen",
        "therapy"
    ],
    "wof:name":"Pitman Gladys",
    "wof:placetype":"venue"
},
  "geometry": {"coordinates":[150.985397339,-33.8540000916],"type":"Point"}
}