{
  "type": "Feature",
  "properties": {
    "addr:full":"Rhodes Rd Warragul VIC 3820",
    "addr:postcode":"3820",
    "addr:street":"Rhodes Rd",
    "iso:country":"AU",
    "sg:address":"Rhodes Rd",
    "sg:city":"Warragul",
    "sg:classifiers":[
        {
            "category":"Farming",
            "subcategory":"Farm",
            "type":"Manufacturing & Wholesale Goods"
        }
    ],
    "sg:phone":"+61 3 5627 8222",
    "sg:postcode":"3820",
    "sg:province":"VIC",
    "sg:tags":[
        "farmer"
    ],
    "wof:name":"Young R A & I M",
    "wof:placetype":"venue"
},
  "geometry": {"coordinates":[145.989395,-38.166649],"type":"Point"}
}