{
  "type": "Feature",
  "properties": {
    "iso:country":"AU",
    "sg:address":"3 collitt Crs",
    "sg:city":"Cranebrook",
    "sg:classifiers":[
        {
            "category":"Home & Garden",
            "subcategory":"Home Furnishings",
            "type":"Retail Goods"
        }
    ],
    "sg:phone":"+61 2 4729 3718",
    "sg:postcode":"2749",
    "sg:province":"NSW",
    "sg:tags":[
        "candle"
    ],
    "wof:name":"B W R Candles Ark",
    "wof:placetype":"venue"
},
  "geometry": {"coordinates":[150.710037231,-33.7194519043],"type":"Point"}
}