{
  "type": "Feature",
  "properties": {
    "addr:full":"Shop 12 Belmont Shopng Cntr Belmont WA 6104",
    "addr:housenumber":"shop 12",
    "addr:postcode":"6104",
    "addr:street":"Belmont Shopng Cntr",
    "iso:country":"AU",
    "sg:address":"Shop 12",
    "sg:city":"Belmont Shopng Cntr Belmont",
    "sg:classifiers":[
        {
            "category":"Real Estate",
            "subcategory":"Real Estate Agent",
            "type":"Services"
        }
    ],
    "sg:phone":"+61 8 9277 7099",
    "sg:postcode":"6104",
    "sg:province":"WA",
    "wof:name":"L.J. Hooker",
    "wof:placetype":"venue"
},
  "geometry": {"coordinates":[115.91844940199999,-31.9531135559],"type":"Point"}
}