{
  "type": "Feature",
  "properties": {
    "iso:country":"AU",
    "sg:address":"Unit 5, 23 Wadhurst Drv",
    "sg:city":"Boronia",
    "sg:classifiers":[
        {
            "category":"Autos & Motor Vehicles",
            "subcategory":"Boat Sales",
            "type":"Retail Goods"
        }
    ],
    "sg:phone":"+61 3 9887 5277",
    "sg:postcode":"3155",
    "sg:province":"VIC",
    "sg:tags":[
        "equipment",
        "yacht"
    ],
    "wof:name":"Float Pac",
    "wof:placetype":"venue"
},
  "geometry": {"coordinates":[145.25534057600001,-37.8663978577],"type":"Point"}
}