{
  "type": "Feature",
  "properties": {
    "iso:country":"AU",
    "sg:address":"143b Raglan St",
    "sg:city":"Mosman",
    "sg:classifiers":[
        {
            "category":"Professional",
            "subcategory":"Engineering",
            "type":"Services"
        }
    ],
    "sg:phone":"+61 2 8907 9000",
    "sg:postcode":"2088",
    "sg:province":"NSW",
    "sg:tags":[
        "consulting",
        "engineer"
    ],
    "wof:name":"Jeff Moulsdale & Associates Pty Limited",
    "wof:placetype":"venue"
},
  "geometry": {"coordinates":[151.244415283,-33.8310432434],"type":"Point"}
}