{
  "type": "Feature",
  "properties": {
    "addr:full":"541 St Kilda Rd St Kilda VIC 3182",
    "addr:housenumber":"541",
    "addr:postcode":"3182",
    "addr:street":"St Kilda Rd",
    "iso:country":"AU",
    "sg:address":"541 St Kilda Rd St",
    "sg:city":"Kilda",
    "sg:classifiers":[
        {
            "category":"Professional",
            "type":"Services"
        }
    ],
    "sg:phone":"+61 3 9593 6001",
    "sg:postcode":"3182",
    "sg:province":"VIC",
    "sg:tags":[
        "courier"
    ],
    "wof:name":"Pack & Send",
    "wof:placetype":"venue"
},
  "geometry": {"coordinates":[144.98277282699999,-37.8571586609],"type":"Point"}
}