{
  "type": "Feature",
  "properties": {
    "addr:full":"184 Scarborough St Southport QLD 4215",
    "addr:housenumber":"184",
    "addr:postcode":"4215",
    "addr:street":"Scarborough St",
    "iso:country":"AU",
    "sg:address":"184 Scarborough St",
    "sg:city":"Southport",
    "sg:classifiers":[
        {
            "category":"Professional",
            "subcategory":"Computer Services",
            "type":"Services"
        }
    ],
    "sg:phone":"+61 1300 652 132",
    "sg:postcode":"4215",
    "sg:province":"QLD",
    "sg:tags":[
        "package",
        "software"
    ],
    "wof:name":"Barclay's Business Systems",
    "wof:placetype":"venue"
},
  "geometry": {"coordinates":[153.41000366200001,-27.9618339539],"type":"Point"}
}