{
  "type": "Feature",
  "properties": {
    "addr:full":"PO Box 821 Banora Point NSW 2486",
    "addr:postcode":"2486",
    "iso:country":"AU",
    "sg:address":"PO Box 821",
    "sg:city":"Banora Point",
    "sg:classifiers":[
        {
            "category":"Retail",
            "subcategory":"Repair Shop",
            "type":"Services"
        }
    ],
    "sg:phone":"+61 418 600 276",
    "sg:postcode":"2486",
    "sg:province":"NSW",
    "sg:tags":[
        "maintenance",
        "pool",
        "swimming"
    ],
    "wof:name":"Adrians Pool Services",
    "wof:placetype":"venue"
},
  "geometry": {"coordinates":[153.54563903799999,-28.2131099701],"type":"Point"}
}