{
  "type": "Feature",
  "properties": {
    "addr:full":"140 Strawberry Rd Bonogin QLD 4213",
    "addr:housenumber":"140",
    "addr:postcode":"4213",
    "addr:street":"Strawberry Rd",
    "iso:country":"AU",
    "sg:address":"140 Strawberry Rd",
    "sg:city":"Bonogin",
    "sg:classifiers":[
        {
            "category":"Real Estate",
            "subcategory":"Real Estate Operator",
            "type":"Services"
        }
    ],
    "sg:phone":"+61 418 456 825",
    "sg:postcode":"4213",
    "sg:province":"QLD",
    "sg:tags":[
        "concrete",
        "pumping"
    ],
    "wof:name":"Alternative Concrete Pumping",
    "wof:placetype":"venue"
},
  "geometry": {"coordinates":[153.35462951700001,-28.1118335724],"type":"Point"}
}