{
  "type": "Feature",
  "properties": {
    "addr:full":"2 - 6 William St Beverley SA 5009",
    "addr:housenumber":"6",
    "addr:postcode":"5009",
    "addr:street":"William St",
    "iso:country":"AU",
    "sg:address":"2 - 6 William St",
    "sg:city":"Beverley",
    "sg:classifiers":[
        {
            "category":"Building & Trades",
            "subcategory":"Construction",
            "type":"Services"
        }
    ],
    "sg:phone":"+61 8 8243 4300",
    "sg:postcode":"5009",
    "sg:province":"SA",
    "sg:tags":[
        "fencing",
        "contractor"
    ],
    "wof:name":"Adelaide Fence Centre",
    "wof:placetype":"venue"
},
  "geometry": {"coordinates":[138.547332764,-34.9010505676],"type":"Point"}
}