{
  "type": "Feature",
  "properties": {
    "iso:country":"AU",
    "sg:address":"5 Amy St",
    "sg:city":"Camberwell",
    "sg:classifiers":[
        {
            "category":"Professional",
            "subcategory":"Engineering",
            "type":"Services"
        }
    ],
    "sg:phone":"+61 3 9889 2421",
    "sg:postcode":"3124",
    "sg:province":"VIC",
    "sg:tags":[
        "consulting",
        "engineer"
    ],
    "wof:name":"Halvale Pty Ltd",
    "wof:placetype":"venue"
},
  "geometry": {"coordinates":[145.083084106,-37.840221405],"type":"Point"}
}