{
  "type": "Feature",
  "properties": {
    "iso:country":"AU",
    "sg:address":"Level 7 19 Bolton St",
    "sg:city":"Newcastle",
    "sg:classifiers":[
        {
            "category":"Real Estate",
            "subcategory":"Real Estate Agent",
            "type":"Services"
        }
    ],
    "sg:phone":"+61 2 4926 3915",
    "sg:postcode":"2300",
    "sg:province":"NSW",
    "wof:name":"Rex Woods Golding & Associates",
    "wof:placetype":"venue"
},
  "geometry": {"coordinates":[151.78332499999999,-32.927685],"type":"Point"}
}