{
  "type": "Feature",
  "properties": {
    "addr:full":"694 Centre Rd Bentleigh East VIC 3165",
    "addr:housenumber":"694",
    "addr:postcode":"3165",
    "addr:street":"Centre Rd",
    "iso:country":"AU",
    "sg:address":"694 Centre Rd",
    "sg:city":"Bentleigh East",
    "sg:classifiers":[
        {
            "category":"Personal",
            "subcategory":"Tanning Parlor",
            "type":"Services"
        }
    ],
    "sg:phone":"+61 3 9570 9351",
    "sg:postcode":"3165",
    "sg:province":"VIC",
    "sg:tags":[
        "solarium"
    ],
    "wof:name":"Sunkissed Tanning & Beauty Studio",
    "wof:placetype":"venue"
},
  "geometry": {"coordinates":[145.057296753,-37.9210319519],"type":"Point"}
}