{
  "type": "Feature",
  "properties": {
    "iso:country":"AU",
    "sg:address":"Big B Arcade 21 Park Ave",
    "sg:city":"Burleigh Heads",
    "sg:classifiers":[
        {
            "category":"Health Services",
            "subcategory":"Doctor",
            "type":"Services"
        }
    ],
    "sg:phone":"+61 7 5576 5832",
    "sg:postcode":"4220",
    "sg:province":"QLD",
    "sg:tags":[
        "medical",
        "practitioner"
    ],
    "wof:name":"Spanner Mark",
    "wof:placetype":"venue"
},
  "geometry": {"coordinates":[153.45010375999999,-28.0899028778],"type":"Point"}
}