{
  "type": "Feature",
  "properties": {
    "addr:full":"21- 23 Princes Hwy Engadine NSW 2233",
    "addr:housenumber":"23",
    "addr:postcode":"2233",
    "addr:street":"Princes Hwy",
    "iso:country":"AU",
    "sg:address":"21- 23 Princes Hwy",
    "sg:city":"Engadine",
    "sg:classifiers":[
        {
            "category":"Autos & Motor Vehicles",
            "subcategory":"Auto Supplies",
            "type":"Retail Goods"
        }
    ],
    "sg:phone":"+61 2 9520 7222",
    "sg:postcode":"2233",
    "sg:province":"NSW",
    "sg:tags":[
        "tyre"
    ],
    "wof:name":"Duro",
    "wof:placetype":"venue"
},
  "geometry": {"coordinates":[150.99838256800001,-34.0964241028],"type":"Point"}
}