{
  "type": "Feature",
  "properties": {
    "addr:full":"18 Carlton St Granville NSW 2142",
    "addr:housenumber":"18",
    "addr:postcode":"2142",
    "addr:street":"Carlton St",
    "iso:country":"AU",
    "sg:address":"18 Carlton St",
    "sg:city":"Granville",
    "sg:classifiers":[
        {
            "category":"Health Services",
            "subcategory":"Dentist",
            "type":"Services"
        }
    ],
    "sg:phone":"+61 2 9637 1084",
    "sg:postcode":"2142",
    "sg:province":"NSW",
    "wof:name":"Dental Centre Granville",
    "wof:placetype":"venue"
},
  "geometry": {"coordinates":[151.009490967,-33.8329925537],"type":"Point"}
}