{
  "type": "Feature",
  "properties": {
    "addr:full":"PO Box 135 Korumburra VIC 3950",
    "addr:postcode":"3950",
    "iso:country":"AU",
    "sg:address":"PO Box 135",
    "sg:city":"Korumburra",
    "sg:classifiers":[
        {
            "category":"Professional",
            "subcategory":"Art Services",
            "type":"Services"
        }
    ],
    "sg:phone":"+61 427 572 433",
    "sg:postcode":"3950",
    "sg:province":"VIC",
    "sg:tags":[
        "interior",
        "decorator"
    ],
    "wof:name":"Rooms Revisited",
    "wof:placetype":"venue"
},
  "geometry": {"coordinates":[145.82281494099999,-38.4323501587],"type":"Point"}
}