{
  "type": "Feature",
  "properties": {
    "addr:full":"Cumberland View Whalley Drv Wheelers Hill VIC 3150",
    "addr:postcode":"3150",
    "addr:street":"Whalley Drv",
    "iso:country":"AU",
    "sg:address":"Cumberland View Whalley Drv",
    "sg:city":"Wheelers Hill",
    "sg:classifiers":[
        {
            "category":"Education",
            "subcategory":"University",
            "type":"Public Place"
        }
    ],
    "sg:phone":"+61 3 9701 0848",
    "sg:postcode":"3150",
    "sg:province":"VIC",
    "sg:tags":[
        "educational",
        "organisation",
        "cultural"
    ],
    "wof:name":"Universities Of The Third Age (U3A) - Victorian Network",
    "wof:placetype":"venue"
},
  "geometry": {"coordinates":[145.190383911,-37.9138755798],"type":"Point"}
}