{
  "type": "Feature",
  "properties": {
    "addr:full":"68 Smith St Kempsey NSW 2440",
    "addr:housenumber":"68",
    "addr:postcode":"2440",
    "addr:street":"Smith St",
    "iso:country":"AU",
    "sg:address":"68 Smith St",
    "sg:city":"Kempsey",
    "sg:classifiers":[
        {
            "category":"Retail",
            "subcategory":"Veterinary Services",
            "type":"Services"
        }
    ],
    "sg:phone":"+61 2 6562 4962",
    "sg:postcode":"2440",
    "sg:province":"NSW",
    "sg:tags":[
        "surgeon"
    ],
    "wof:name":"Lee M A",
    "wof:placetype":"venue"
},
  "geometry": {"coordinates":[152.842285,-31.07815],"type":"Point"}
}