{
  "type": "Feature",
  "properties": {
    "addr:full":"28 Howe St Balaklava SA 5461",
    "addr:housenumber":"28",
    "addr:postcode":"5461",
    "addr:street":"Howe St",
    "iso:country":"AU",
    "sg:address":"28 Howe St",
    "sg:city":"Balaklava",
    "sg:classifiers":[
        {
            "category":"Professional",
            "subcategory":"Printing & Photocopies",
            "type":"Services"
        }
    ],
    "sg:phone":"+61 8 8862 1696",
    "sg:postcode":"5461",
    "sg:province":"SA",
    "sg:tags":[
        "screen",
        "printer"
    ],
    "wof:name":"Grandeur Press",
    "wof:placetype":"venue"
},
  "geometry": {"coordinates":[138.41511499999999,-34.145641],"type":"Point"}
}