{
  "type": "Feature",
  "properties": {
    "addr:full":"20 Ely St Wangaratta VIC 3677",
    "addr:housenumber":"20",
    "addr:postcode":"3677",
    "addr:street":"Ely St",
    "iso:country":"AU",
    "sg:address":"20 Ely St",
    "sg:city":"Wangaratta",
    "sg:classifiers":[
        {
            "category":"Professional",
            "subcategory":"Employment Agencies",
            "type":"Services"
        }
    ],
    "sg:phone":"+61 3 5721 5959",
    "sg:postcode":"3677",
    "sg:province":"VIC",
    "wof:name":"Wills Im",
    "wof:placetype":"venue"
},
  "geometry": {"coordinates":[146.32655334500001,-36.3568305969],"type":"Point"}
}