{
  "type": "Feature",
  "properties": {
    "addr:full":"7 Talgarno Pl Mudgeeraba QLD 4213",
    "addr:housenumber":"7",
    "addr:postcode":"4213",
    "addr:street":"Talgarno Pl",
    "iso:country":"AU",
    "sg:address":"7 Talgarno Pl",
    "sg:city":"Mudgeeraba",
    "sg:classifiers":[
        {
            "category":"Building & Trades",
            "subcategory":"Plumbing",
            "type":"Services"
        }
    ],
    "sg:phone":"+61 7 5530 4914",
    "sg:postcode":"4213",
    "sg:province":"QLD",
    "sg:tags":[
        "plumber",
        "gasfitters"
    ],
    "wof:name":"S & J Maintenance",
    "wof:placetype":"venue"
},
  "geometry": {"coordinates":[153.34852600100001,-28.075258255],"type":"Point"}
}