{
  "type": "Feature",
  "properties": {
    "addr:full":"18 Colebard St West Archerfield QLD 4108",
    "addr:housenumber":"18",
    "addr:postcode":"4108",
    "addr:street":"Colebard St West",
    "iso:country":"AU",
    "sg:address":"18 Colebard St West",
    "sg:city":"Archerfield",
    "sg:classifiers":[
        {
            "category":"Professional",
            "subcategory":"Engineering",
            "type":"Services"
        }
    ],
    "sg:phone":"+61 7 3277 5822",
    "sg:postcode":"4108",
    "sg:province":"QLD",
    "sg:tags":[
        "engineer"
    ],
    "wof:name":"Walkers",
    "wof:placetype":"venue"
},
  "geometry": {"coordinates":[153.00422668499999,-27.5770645142],"type":"Point"}
}