{
  "type": "Feature",
  "properties": {
    "addr:full":"Cnr St Albans & Midway Lane Sunshine VIC 3020",
    "addr:postcode":"3020",
    "addr:street":"Cnr;Lane",
    "iso:country":"AU",
    "sg:address":"Cnr St",
    "sg:city":"Albans & Midway Lane Sunshine",
    "sg:classifiers":[
        {
            "category":"Banks & Credit Unions",
            "subcategory":"Bank",
            "type":"Services"
        }
    ],
    "sg:phone":"+61 3 9312 1356",
    "sg:postcode":"3020",
    "sg:province":"VIC",
    "sg:tags":[
        "concrete",
        "reinforcement"
    ],
    "wof:name":"Midway Mini-Mix Concrete Garden & Building Supplies",
    "wof:placetype":"venue"
},
  "geometry": {"coordinates":[144.82835399999999,-37.77681],"type":"Point"}
}