{
  "type": "Feature",
  "properties": {
    "addr:full":"Byron Bay Specialist Centre 6 Lawson St Byron Bay NSW 2481",
    "addr:housenumber":"6",
    "addr:postcode":"2481",
    "addr:street":"Lawson St",
    "iso:country":"AU",
    "sg:address":"Byron Bay Specialist Centre 6 Lawson St",
    "sg:city":"Byron Bay",
    "sg:classifiers":[
        {
            "category":"Health Services",
            "subcategory":"Health Practitioner",
            "type":"Services"
        }
    ],
    "sg:phone":"+61 2 6685 5662",
    "sg:postcode":"2481",
    "sg:province":"NSW",
    "sg:tags":[
        "psychologist"
    ],
    "wof:name":"Peter Stoker",
    "wof:placetype":"venue"
},
  "geometry": {"coordinates":[153.61297607399999,-28.642414093],"type":"Point"}
}