{
  "type": "Feature",
  "properties": {
    "addr:full":"16 Chandos St Gunnedah NSW 2380",
    "addr:housenumber":"16",
    "addr:postcode":"2380",
    "addr:street":"Chandos St",
    "iso:country":"AU",
    "sg:address":"16 Chandos St",
    "sg:city":"Gunnedah",
    "sg:classifiers":[
        {
            "category":"Travel",
            "subcategory":"Hotels & Motels",
            "type":"Entertainment"
        }
    ],
    "sg:phone":"+61 2 6742 0176",
    "sg:postcode":"2380",
    "sg:province":"NSW",
    "sg:tags":[
        "accommodation"
    ],
    "wof:name":"Imperial Hotel Gunnedah",
    "wof:placetype":"venue"
},
  "geometry": {"coordinates":[150.24995422399999,-30.9783058167],"type":"Point"}
}