{
  "type": "Feature",
  "properties": {
    "addr:full":"177 Malabar Rd South Coogee NSW 2034",
    "addr:housenumber":"177",
    "addr:postcode":"2034",
    "addr:street":"Malabar Rd",
    "iso:country":"AU",
    "sg:address":"177 Malabar Rd",
    "sg:city":"South Coogee",
    "sg:classifiers":[
        {
            "category":"Health Services",
            "subcategory":"Doctor",
            "type":"Services"
        }
    ],
    "sg:phone":"+61 2 9349 1998",
    "sg:postcode":"2034",
    "sg:province":"NSW",
    "sg:tags":[
        "medical",
        "practitioner"
    ],
    "wof:name":"Coogee Skin Cancer Clinic",
    "wof:placetype":"venue"
},
  "geometry": {"coordinates":[151.25747680699999,-33.9326286316],"type":"Point"}
}