{
  "type": "Feature",
  "properties": {
    "addr:full":"Unit 1/ 13 Enterprise Close, Gosford West NSW 2250",
    "addr:housenumber":"13",
    "addr:postcode":"2250",
    "addr:street":"Enterprise Close",
    "iso:country":"AU",
    "sg:address":"Unit 1/ 13",
    "sg:city":"Enterprise Close, Gosford West",
    "sg:classifiers":[
        {
            "category":"Shopping",
            "subcategory":"Computers & Home Electronics",
            "type":"Retail Goods"
        }
    ],
    "sg:phone":"+61 2 4325 0588",
    "sg:postcode":"2250",
    "sg:province":"NSW",
    "sg:tags":[
        "hardware",
        "equipment"
    ],
    "wof:name":"Sheather & Merrigan Business Equipment",
    "wof:placetype":"venue"
},
  "geometry": {"coordinates":[151.332565308,-33.412563324],"type":"Point"}
}