{
  "type": "Feature",
  "properties": {
    "addr:full":"20 Armstrong St Middle Park VIC 3206",
    "addr:housenumber":"20",
    "addr:postcode":"3206",
    "addr:street":"Armstrong St",
    "iso:country":"AU",
    "sg:address":"20 Armstrong St",
    "sg:city":"Middle Park",
    "sg:classifiers":[
        {
            "category":"Cafe",
            "type":"Food & Drink"
        }
    ],
    "sg:phone":"+61 3 9699 6082",
    "sg:postcode":"3206",
    "sg:province":"VIC",
    "wof:name":"Victorian Wine Centre",
    "wof:placetype":"venue"
},
  "geometry": {"coordinates":[144.964294,-37.850204],"type":"Point"}
}