{
  "type": "Feature",
  "properties": {
    "iso:country":"AU",
    "sg:address":"169 Maroondah Hwy",
    "sg:city":"Croydon",
    "sg:classifiers":[
        {
            "category":"Health Services",
            "subcategory":"Doctor",
            "type":"Services"
        }
    ],
    "sg:phone":"+61 3 9800 4988",
    "sg:postcode":"3136",
    "sg:province":"VIC",
    "sg:tags":[
        "medical",
        "practitioner"
    ],
    "wof:name":"Premier Medical Centres",
    "wof:placetype":"venue"
},
  "geometry": {"coordinates":[145.275512695,-37.7861938477],"type":"Point"}
}