{
  "type": "Feature",
  "properties": {
    "iso:country":"AU",
    "sg:address":"Lot 55 Nicholson Rd",
    "sg:city":"Canning Vale",
    "sg:classifiers":[
        {
            "category":"Retail",
            "subcategory":"Event Space",
            "type":"Services"
        }
    ],
    "sg:phone":"+61 8 9455 1187",
    "sg:postcode":"6155",
    "sg:province":"WA",
    "sg:tags":[
        "venue",
        "reception",
        "wedding"
    ],
    "sg:website":"http://www.willowpond.com.au",
    "wof:name":"Willow Pond Reception Centre",
    "wof:placetype":"venue"
},
  "geometry": {"coordinates":[115.92317199999999,-32.074661],"type":"Point"}
}