{
  "type": "Feature",
  "properties": {
    "addr:full":"Blackwood Ave Augusta WA 6290",
    "addr:postcode":"6290",
    "addr:street":"Blackwood Ave",
    "iso:country":"AU",
    "sg:address":"Blackwood Ave",
    "sg:city":"Augusta",
    "sg:classifiers":[
        {
            "category":"Travel",
            "subcategory":"Hostel",
            "type":"Entertainment"
        }
    ],
    "sg:phone":"+61 8 9758 1754",
    "sg:postcode":"6290",
    "sg:province":"WA",
    "sg:tags":[
        "home"
    ],
    "wof:name":"Leeuwin Frail Aged Lodge (Inc.)",
    "wof:placetype":"venue"
},
  "geometry": {"coordinates":[115.158638001,-34.3022537231],"type":"Point"}
}