{
  "type": "Feature",
  "properties": {
    "addr:full":"37 Pease St Manunda QLD 4870",
    "addr:housenumber":"37",
    "addr:postcode":"4870",
    "addr:street":"Pease St",
    "iso:country":"AU",
    "sg:address":"37 Pease St",
    "sg:city":"Manunda",
    "sg:classifiers":[
        {
            "category":"Professional",
            "subcategory":"Detective & Security Services",
            "type":"Services"
        }
    ],
    "sg:phone":"+61 7 4053 7424",
    "sg:postcode":"4870",
    "sg:province":"QLD",
    "sg:tags":[
        "investigator"
    ],
    "wof:name":"Cairns Security Services",
    "wof:placetype":"venue"
},
  "geometry": {"coordinates":[145.74989318900001,-16.9132595062],"type":"Point"}
}