{
  "type": "Feature",
  "properties": {
    "iso:country":"AU",
    "sg:address":"Unit 11/ 67 Gillam Drv",
    "sg:city":"Kelmscott",
    "sg:classifiers":[
        {
            "category":"Farming",
            "subcategory":"Farm & Veterinary Services",
            "type":"Manufacturing & Wholesale Goods"
        }
    ],
    "sg:phone":"+61 8 9495 4644",
    "sg:postcode":"6111",
    "sg:province":"WA",
    "sg:tags":[
        "irrigation",
        "reticulation",
        "system"
    ],
    "wof:name":"Total Eden Watering Systems",
    "wof:placetype":"venue"
},
  "geometry": {"coordinates":[116.00375366199999,-32.1270256042],"type":"Point"}
}