{
  "type": "Feature",
  "properties": {
    "addr:full":"Building 18, Headland Park, 1100a Middle Head Rd Mosman NSW 2088",
    "addr:housenumber":"18;1100a",
    "addr:postcode":"2088",
    "addr:street":"Park;Middle Head Rd",
    "iso:country":"AU",
    "sg:address":"Building 18, Headland Park, 1100a Middle Head Rd",
    "sg:city":"Mosman",
    "sg:classifiers":[
        {
            "category":"Professional",
            "subcategory":"Art Services",
            "type":"Services"
        }
    ],
    "sg:phone":"+61 2 9960 5557",
    "sg:postcode":"2088",
    "sg:province":"NSW",
    "sg:tags":[
        "conservation",
        "restoration"
    ],
    "wof:name":"Coburn Fine Art Conservation Pty Ltd",
    "wof:placetype":"venue"
},
  "geometry": {"coordinates":[151.258377075,-33.8307876587],"type":"Point"}
}