{
  "type": "Feature",
  "properties": {
    "addr:full":"126 Gurney Rd Chester Hill NSW 2162",
    "addr:housenumber":"126",
    "addr:postcode":"2162",
    "addr:street":"Gurney Rd",
    "iso:country":"AU",
    "sg:address":"126 Gurney Rd",
    "sg:city":"Chester Hill",
    "sg:classifiers":[
        {
            "category":"Retail",
            "subcategory":"Repair Shop",
            "type":"Services"
        }
    ],
    "sg:phone":"+61 2 9724 5531",
    "sg:postcode":"2162",
    "sg:province":"NSW",
    "sg:tags":[
        "maintenance",
        "pool",
        "swimming"
    ],
    "wof:name":"A 1 Hoffs Pools",
    "wof:placetype":"venue"
},
  "geometry": {"coordinates":[150.987915039,-33.8722343445],"type":"Point"}
}