{
  "type": "Feature",
  "properties": {
    "iso:country":"AU",
    "sg:address":"134 Wyong Rd",
    "sg:city":"Killarney Vale",
    "sg:classifiers":[
        {
            "category":"Real Estate",
            "subcategory":"Real Estate Agent",
            "type":"Services"
        }
    ],
    "sg:phone":"+61 2 4332 6800",
    "sg:postcode":"2261",
    "sg:province":"NSW",
    "wof:name":"Professionals Killarney Vale",
    "wof:placetype":"venue"
},
  "geometry": {"coordinates":[151.462296,-33.365906],"type":"Point"}
}