{
  "type": "Feature",
  "properties": {
    "addr:full":"23 Princes Hwy Figtree NSW 2525",
    "addr:housenumber":"23",
    "addr:postcode":"2525",
    "addr:street":"Princes Hwy",
    "iso:country":"AU",
    "sg:address":"23 Princes Hwy",
    "sg:city":"Figtree",
    "sg:classifiers":[
        {
            "category":"Banks & Credit Unions",
            "subcategory":"Financial Services",
            "type":"Services"
        }
    ],
    "sg:phone":"+61 2 4226 4089",
    "sg:postcode":"2525",
    "sg:province":"NSW",
    "sg:tags":[
        "loan",
        "finance",
        "mortgage"
    ],
    "wof:name":"CUA Figtree",
    "wof:placetype":"venue"
},
  "geometry": {"coordinates":[150.86190795900001,-34.4353485107],"type":"Point"}
}