{
  "type": "Feature",
  "properties": {
    "addr:full":"17a Regent St Kogarah NSW 2217",
    "addr:housenumber":"17a",
    "addr:postcode":"2217",
    "addr:street":"Regent St",
    "iso:country":"AU",
    "sg:address":"17a Regent St",
    "sg:city":"Kogarah",
    "sg:classifiers":[
        {
            "category":"Real Estate",
            "subcategory":"Real Estate Agent",
            "type":"Services"
        }
    ],
    "sg:phone":"+61 2 9588 2977",
    "sg:postcode":"2217",
    "sg:province":"NSW",
    "wof:name":"A Peppas",
    "wof:placetype":"venue"
},
  "geometry": {"coordinates":[151.133759,-33.962532],"type":"Point"}
}