{
  "type": "Feature",
  "properties": {
    "addr:full":"2 Halmore Pl Chapel Hill QLD 4069",
    "addr:housenumber":"2",
    "addr:postcode":"4069",
    "addr:street":"Halmore Pl",
    "iso:country":"AU",
    "sg:address":"2 Halmore Pl",
    "sg:city":"Chapel Hill",
    "sg:classifiers":[
        {
            "category":"Utilities",
            "subcategory":"Telephone",
            "type":"Services"
        }
    ],
    "sg:phone":"+61 7 3378 9163",
    "sg:postcode":"4069",
    "sg:province":"QLD",
    "sg:tags":[
        "installation",
        "system",
        "maintenance"
    ],
    "wof:name":"J K & L M Russell",
    "wof:placetype":"venue"
},
  "geometry": {"coordinates":[152.94140625,-27.4880561829],"type":"Point"}
}