{
  "type": "Feature",
  "properties": {
    "addr:full":"Level 1/ 1668 Centre Rd Springvale VIC 3171",
    "addr:housenumber":"/ 1668",
    "addr:postcode":"3171",
    "addr:street":"Centre Rd",
    "iso:country":"AU",
    "sg:address":"Level 1/ 1668 Centre Rd",
    "sg:city":"Springvale",
    "sg:classifiers":[
        {
            "category":"Professional",
            "subcategory":"Accounting & Tax Preparation",
            "type":"Services"
        }
    ],
    "sg:phone":"+61 3 9546 8699",
    "sg:postcode":"3171",
    "sg:province":"VIC",
    "sg:tags":[
        "accountant",
        "auditor"
    ],
    "wof:name":"Accounting First",
    "wof:placetype":"venue"
},
  "geometry": {"coordinates":[145.15240478499999,-37.9327964783],"type":"Point"}
}