{
  "type": "Feature",
  "properties": {
    "iso:country":"AU",
    "sg:address":"42 Rifle Range Rd",
    "sg:city":"Wollongbar",
    "sg:classifiers":[
        {
            "category":"Building & Trades",
            "subcategory":"Construction",
            "type":"Services"
        }
    ],
    "sg:phone":"+61 417 010 154",
    "sg:postcode":"2477",
    "sg:province":"NSW",
    "sg:tags":[
        "earth",
        "excavating",
        "moving",
        "contractor"
    ],
    "wof:name":"L.Keylock Services",
    "wof:placetype":"venue"
},
  "geometry": {"coordinates":[153.41923523,-28.822063446],"type":"Point"}
}