{
  "type": "Feature",
  "properties": {
    "iso:country":"AU",
    "sg:address":"Main St",
    "sg:city":"Bridport",
    "sg:classifiers":[
        {
            "category":"Health Services",
            "subcategory":"Doctor",
            "type":"Services"
        }
    ],
    "sg:phone":"+61 3 6356 1688",
    "sg:postcode":"7262",
    "sg:province":"TAS",
    "sg:tags":[
        "medical",
        "practitioner"
    ],
    "wof:name":"Bridport Medical Centre",
    "wof:placetype":"venue"
},
  "geometry": {"coordinates":[147.402939,-41.012047],"type":"Point"}
}