{
  "type": "Feature",
  "properties": {
    "iso:country":"AU",
    "sg:address":"14 Morgan St",
    "sg:city":"Rockingham",
    "sg:classifiers":[
        {
            "category":"Manufacturing",
            "subcategory":"Metals",
            "type":"Manufacturing & Wholesale Goods"
        }
    ],
    "sg:phone":"+61 8 9528 2300",
    "sg:postcode":"6168",
    "sg:province":"WA",
    "sg:tags":[
        "steel",
        "fabricator",
        "mfrs"
    ],
    "wof:name":"Lotus Engineering Pty Ltd",
    "wof:placetype":"venue"
},
  "geometry": {"coordinates":[115.752487,-32.275845],"type":"Point"}
}