{
  "type": "Feature",
  "properties": {
    "addr:full":"Shop 10 Homemaker Cntr 72 Maroochydore Rd Maroochydore QLD 4558",
    "addr:housenumber":"shop 10;72",
    "addr:postcode":"4558",
    "addr:street":"Homemaker Cntr;Maroochydore Rd",
    "iso:country":"AU",
    "sg:address":"Shop 10 Homemaker Cntr 72 Maroochydore Rd",
    "sg:city":"Maroochydore",
    "sg:classifiers":[
        {
            "category":"Food & Beverages",
            "subcategory":"Liquor & Beverages",
            "type":"Retail Goods"
        }
    ],
    "sg:phone":"+61 7 5451 0600",
    "sg:postcode":"4558",
    "sg:province":"QLD",
    "sg:tags":[
        "store"
    ],
    "wof:name":"BWS Liquor Stores",
    "wof:placetype":"venue"
},
  "geometry": {"coordinates":[153.06849670400001,-26.6588611603],"type":"Point"}
}