{
  "type": "Feature",
  "properties": {
    "iso:country":"AU",
    "sg:address":"258 Peel St",
    "sg:city":"Tamworth",
    "sg:classifiers":[
        {
            "category":"Real Estate",
            "subcategory":"Real Estate Services",
            "type":"Services"
        }
    ],
    "sg:phone":"+61 2 6762 1533",
    "sg:postcode":"2340",
    "sg:province":"NSW",
    "sg:tags":[
        "valuer"
    ],
    "wof:name":"BJ Cole & Co",
    "wof:placetype":"venue"
},
  "geometry": {"coordinates":[150.927902222,-31.0883102417],"type":"Point"}
}