{
  "type": "Feature",
  "properties": {
    "addr:full":"45 Homer St Narrogin WA 6312",
    "addr:housenumber":"45",
    "addr:postcode":"6312",
    "addr:street":"Homer St",
    "iso:country":"AU",
    "sg:address":"45 Homer St",
    "sg:city":"Narrogin",
    "sg:classifiers":[
        {
            "category":"Home & Garden",
            "subcategory":"Garden Supply",
            "type":"Retail Goods"
        }
    ],
    "sg:phone":"+61 8 9881 1725",
    "sg:postcode":"6312",
    "sg:province":"WA",
    "sg:tags":[
        "fertilizer"
    ],
    "wof:name":"C S P B & Farmers Ltd",
    "wof:placetype":"venue"
},
  "geometry": {"coordinates":[117.18939209,-32.9363555908],"type":"Point"}
}