{
  "type": "Feature",
  "properties": {
    "addr:full":"19 Tarzan St Bohle QLD 4818",
    "addr:housenumber":"19",
    "addr:postcode":"4818",
    "addr:street":"Tarzan St",
    "iso:country":"AU",
    "sg:address":"19 Tarzan St",
    "sg:city":"Bohle",
    "sg:classifiers":[
        {
            "category":"Manufacturing",
            "subcategory":"Buildings",
            "type":"Manufacturing & Wholesale Goods"
        }
    ],
    "sg:phone":"+61 7 4774 6474",
    "sg:postcode":"4818",
    "sg:province":"QLD",
    "sg:tags":[
        "transportable",
        "domestic",
        "relocatable"
    ],
    "wof:name":"North Queensland Steel Frames Pty Ltd",
    "wof:placetype":"venue"
},
  "geometry": {"coordinates":[146.730774,-19.258926],"type":"Point"}
}