{
  "type": "Feature",
  "properties": {
    "addr:full":"65A Millett St Hurstville NSW 2220",
    "addr:housenumber":"65a",
    "addr:postcode":"2220",
    "addr:street":"Millett St",
    "iso:country":"AU",
    "sg:address":"65A Millett St",
    "sg:city":"Hurstville",
    "sg:classifiers":[
        {
            "category":"Professional",
            "subcategory":"Engineering",
            "type":"Services"
        }
    ],
    "sg:phone":"+61 2 9570 1119",
    "sg:postcode":"2220",
    "sg:province":"NSW",
    "sg:tags":[
        "consulting",
        "engineer"
    ],
    "wof:name":"Soliman Hanna & Associates Pty Ltd",
    "wof:placetype":"venue"
},
  "geometry": {"coordinates":[151.09153747600001,-33.9585037231],"type":"Point"}
}