{
  "type": "Feature",
  "properties": {
    "iso:country":"AU",
    "sg:address":"60 Yarrabee Rd",
    "sg:city":"Greenhill",
    "sg:classifiers":[
        {
            "category":"Farming",
            "subcategory":"Farm & Veterinary Services",
            "type":"Manufacturing & Wholesale Goods"
        }
    ],
    "sg:phone":"+61 8 8390 1032",
    "sg:postcode":"5140",
    "sg:province":"SA",
    "sg:tags":[
        "irrigation",
        "reticulation",
        "system"
    ],
    "wof:name":"Bushfire Protection Solutions",
    "wof:placetype":"venue"
},
  "geometry": {"coordinates":[138.69778442399999,-34.9525260925],"type":"Point"}
}