{
  "type": "Feature",
  "properties": {
    "addr:full":"1 Rochester St Homebush NSW 2140",
    "addr:housenumber":"1",
    "addr:postcode":"2140",
    "addr:street":"Rochester St",
    "iso:country":"AU",
    "sg:address":"1 Rochester St",
    "sg:city":"Homebush",
    "sg:classifiers":[
        {
            "category":"Food & Beverages",
            "subcategory":"Bakery",
            "type":"Retail Goods"
        }
    ],
    "sg:phone":"+61 2 9746 1177",
    "sg:postcode":"2140",
    "sg:province":"NSW",
    "sg:tags":[
        "cake",
        "shop",
        "pastry"
    ],
    "wof:name":"Cheesecake Shop The",
    "wof:placetype":"venue"
},
  "geometry": {"coordinates":[151.084838867,-33.8666000366],"type":"Point"}
}