{
  "type": "Feature",
  "properties": {
    "addr:full":"5 Wapengo St Bermagui NSW 2546",
    "addr:housenumber":"5",
    "addr:postcode":"2546",
    "addr:street":"Wapengo St",
    "iso:country":"AU",
    "sg:address":"5 Wapengo St",
    "sg:city":"Bermagui",
    "sg:classifiers":[
        {
            "category":"Personal",
            "subcategory":"Beauty Salon",
            "type":"Services"
        }
    ],
    "sg:phone":"+61 2 6493 3955",
    "sg:postcode":"2546",
    "sg:province":"NSW",
    "wof:name":"Salon Blush",
    "wof:placetype":"venue"
},
  "geometry": {"coordinates":[150.065185547,-36.4224510193],"type":"Point"}
}