{
  "type": "Feature",
  "properties": {
    "addr:full":"Cnr Francis & Catherine Sts Cessnock NSW 2325",
    "addr:postcode":"2325",
    "addr:street":"Cnr",
    "iso:country":"AU",
    "sg:address":"Cnr Francis & Catherine Sts",
    "sg:city":"Cessnock",
    "sg:classifiers":[
        {
            "category":"Education",
            "subcategory":"Kindergarten",
            "type":"Public Place"
        }
    ],
    "sg:phone":"+61 2 4991 2802",
    "sg:postcode":"2325",
    "sg:province":"NSW",
    "sg:tags":[
        "pre-schools"
    ],
    "wof:name":"Natural Steps Pre-School",
    "wof:placetype":"venue"
},
  "geometry": {"coordinates":[151.354934692,-32.8325691223],"type":"Point"}
}