{
  "type": "Feature",
  "properties": {
    "addr:full":"PO Box 7212 West Lakes Shore SA 5020",
    "addr:postcode":"5020",
    "iso:country":"AU",
    "sg:address":"PO Box 7212",
    "sg:city":"West Lakes Shore",
    "sg:classifiers":[
        {
            "category":"Real Estate",
            "subcategory":"Real Estate Agent",
            "type":"Services"
        }
    ],
    "sg:phone":"+61 407 465 535",
    "sg:postcode":"5020",
    "sg:province":"SA",
    "wof:name":"Marion Bay Land Sales",
    "wof:placetype":"venue"
},
  "geometry": {"coordinates":[138.48747253400001,-34.8672485352],"type":"Point"}
}