{
  "type": "Feature",
  "properties": {
    "addr:full":"30 Willow Rd Warwick WA 6024",
    "addr:housenumber":"30",
    "addr:postcode":"6024",
    "addr:street":"Willow Rd",
    "iso:country":"AU",
    "sg:address":"30 Willow Rd",
    "sg:city":"Warwick",
    "sg:classifiers":[
        {
            "category":"Building & Trades",
            "subcategory":"Plumbing",
            "type":"Services"
        }
    ],
    "sg:phone":"+61 8 9246 1066",
    "sg:postcode":"6024",
    "sg:province":"WA",
    "sg:tags":[
        "equipment",
        "valves"
    ],
    "wof:name":"West Coast Valves",
    "wof:placetype":"venue"
},
  "geometry": {"coordinates":[115.80364227299999,-31.8423690796],"type":"Point"}
}