{
  "type": "Feature",
  "properties": {
    "addr:full":"Suite 6/ 67 Spit Rd Mosman NSW 2088",
    "addr:housenumber":"67",
    "addr:postcode":"2088",
    "addr:street":"Spit Rd",
    "iso:country":"AU",
    "sg:address":"Suite 6/ 67 Spit Rd",
    "sg:city":"Mosman",
    "sg:classifiers":[
        {
            "category":"Personal",
            "subcategory":"Massage",
            "type":"Services"
        }
    ],
    "sg:phone":"+61 2 9960 5895",
    "sg:postcode":"2088",
    "sg:province":"NSW",
    "sg:tags":[
        "therapy"
    ],
    "wof:name":"Sydney Health Massage",
    "wof:placetype":"venue"
},
  "geometry": {"coordinates":[151.243972778,-33.8217773438],"type":"Point"}
}