{
  "type": "Feature",
  "properties": {
    "addr:full":"5 Hayden St Bethania QLD 4205",
    "addr:housenumber":"5",
    "addr:postcode":"4205",
    "addr:street":"Hayden St",
    "iso:country":"AU",
    "sg:address":"5 Hayden St",
    "sg:city":"Bethania",
    "sg:classifiers":[
        {
            "category":"Building & Trades",
            "subcategory":"Cleaning & Sanitation",
            "type":"Services"
        }
    ],
    "sg:phone":"+61 416 126 058",
    "sg:postcode":"4205",
    "sg:province":"QLD",
    "sg:tags":[
        "industrial",
        "commercial",
        "contractor"
    ],
    "wof:name":"Texas Cleaning Services",
    "wof:placetype":"venue"
},
  "geometry": {"coordinates":[153.15313720699999,-27.6854934692],"type":"Point"}
}