{
  "type": "Feature",
  "properties": {
    "addr:full":"1020 Waterworks Rd The Gap QLD 4061",
    "addr:housenumber":"1020",
    "addr:postcode":"4061",
    "addr:street":"Waterworks Rd",
    "iso:country":"AU",
    "sg:address":"1020 Waterworks Rd",
    "sg:city":"The Gap",
    "sg:classifiers":[
        {
            "category":"Education",
            "subcategory":"School",
            "type":"Public Place"
        }
    ],
    "sg:phone":"+61 7 3511 3888",
    "sg:postcode":"4061",
    "sg:province":"QLD",
    "sg:tags":[
        "state",
        "except",
        "nsw"
    ],
    "wof:name":"The Gap State High School",
    "wof:placetype":"venue"
},
  "geometry": {"coordinates":[152.95199585,-27.445022583],"type":"Point"}
}