{
  "type": "Feature",
  "properties": {
    "iso:country":"AU",
    "sg:address":"69 Heatherdale Rd",
    "sg:city":"Ringwood",
    "sg:classifiers":[
        {
            "category":"Manufacturing",
            "subcategory":"Electronics",
            "type":"Manufacturing & Wholesale Goods"
        }
    ],
    "sg:phone":"+61 3 9873 3344",
    "sg:postcode":"3134",
    "sg:province":"VIC",
    "sg:tags":[
        "wholesaler",
        "equipment",
        "part",
        "mfrs",
        "refrigeration"
    ],
    "wof:name":"Refrigeration Parts (Vic) Pty Ltd",
    "wof:placetype":"venue"
},
  "geometry": {"coordinates":[145.213500977,-37.8236923218],"type":"Point"}
}