{
  "type": "Feature",
  "properties": {
    "iso:country":"AU",
    "sg:address":"Marion Kiosk 103A Westfield Shoppingtown Diagonal",
    "sg:city":"Oaklands Park",
    "sg:classifiers":[
        {
            "category":"Shopping",
            "subcategory":"Beauty & Cosmetics",
            "type":"Retail Goods"
        }
    ],
    "sg:phone":"+61 8 8298 8622",
    "sg:postcode":"5046",
    "sg:province":"SA",
    "wof:name":"Clinique Service Centres",
    "wof:placetype":"venue"
},
  "geometry": {"coordinates":[138.54437300000001,-35.013592],"type":"Point"}
}