{
  "type": "Feature",
  "properties": {
    "iso:country":"AU",
    "sg:address":"Unit 1, 21 Cook St",
    "sg:city":"Busselton",
    "sg:classifiers":[
        {
            "category":"Autos & Motor Vehicles",
            "subcategory":"Auto Supplies",
            "type":"Retail Goods"
        }
    ],
    "sg:phone":"+61 8 9752 1377",
    "sg:postcode":"6280",
    "sg:province":"WA",
    "sg:tags":[
        "car",
        "alarm"
    ],
    "wof:name":"Busselton Auto Electrics",
    "wof:placetype":"venue"
},
  "geometry": {"coordinates":[115.34403228799999,-33.6668815613],"type":"Point"}
}