{
  "type": "Feature",
  "properties": {
    "addr:full":"21 Bapauma Rd Holland Park QLD 4121",
    "addr:housenumber":"21",
    "addr:postcode":"4121",
    "addr:street":"Bapauma Rd",
    "iso:country":"AU",
    "sg:address":"21 Bapauma Rd",
    "sg:city":"Holland Park",
    "sg:classifiers":[
        {
            "category":"Autos & Motor Vehicles",
            "subcategory":"Fuel & Gas Station",
            "type":"Retail Goods"
        }
    ],
    "sg:phone":"+61 7 3397 4647",
    "sg:postcode":"4121",
    "sg:province":"QLD",
    "wof:name":"Shell",
    "wof:placetype":"venue"
},
  "geometry": {"coordinates":[153.05789184599999,-27.5290241241],"type":"Point"}
}