{
  "type": "Feature",
  "properties": {
    "addr:full":"56 Chard Rd Brookvale NSW 2100",
    "addr:housenumber":"56",
    "addr:postcode":"2100",
    "addr:street":"Chard Rd",
    "iso:country":"AU",
    "sg:address":"56 Chard Rd",
    "sg:city":"Brookvale",
    "sg:classifiers":[
        {
            "category":"Government",
            "subcategory":"Fire Station",
            "type":"Public Place"
        }
    ],
    "sg:phone":"+61 404 127 296",
    "sg:postcode":"2100",
    "sg:province":"NSW",
    "sg:tags":[
        "spring",
        "shock",
        "absorbers",
        "suspension"
    ],
    "sg:website":"http://www.airbaggit.com.au",
    "wof:name":"Air Ride Suspension Systems",
    "wof:placetype":"venue"
},
  "geometry": {"coordinates":[151.27537536599999,-33.7633399963],"type":"Point"}
}