{
  "type": "Feature",
  "properties": {
    "iso:country":"AU",
    "sg:address":"25 Woodland St",
    "sg:city":"Essendon",
    "sg:classifiers":[
        {
            "category":"Health Services",
            "subcategory":"Doctor",
            "type":"Services"
        }
    ],
    "sg:phone":"+61 3 9379 3120",
    "sg:postcode":"3040",
    "sg:province":"VIC",
    "sg:tags":[
        "medical",
        "practitioner"
    ],
    "wof:name":"Dr Willaton M",
    "wof:placetype":"venue"
},
  "geometry": {"coordinates":[144.925979614,-37.7433357239],"type":"Point"}
}