{
  "type": "Feature",
  "properties": {
    "addr:full":"PO Box 9065 Manly West QLD 4179",
    "addr:postcode":"4179",
    "iso:country":"AU",
    "sg:address":"PO Box 9065",
    "sg:city":"Manly West",
    "sg:classifiers":[
        {
            "category":"Arena",
            "subcategory":"Sports Club",
            "type":"Entertainment"
        }
    ],
    "sg:phone":"+61 7 3396 2183",
    "sg:postcode":"4179",
    "sg:province":"QLD",
    "sg:tags":[
        "defence",
        "supply",
        "self",
        "instruction",
        "martial art"
    ],
    "wof:name":"Progressive Martial Arts Academy",
    "wof:placetype":"venue"
},
  "geometry": {"coordinates":[153.164352417,-27.4578495026],"type":"Point"}
}