{
  "type": "Feature",
  "properties": {
    "addr:full":"Unit 1/ 8 Kembla Way Willetton WA 6155",
    "addr:postcode":"6155",
    "addr:street":"Kembla Way",
    "iso:country":"AU",
    "sg:address":"Unit 1/ 8 Kembla Way",
    "sg:city":"Willetton",
    "sg:classifiers":[
        {
            "category":"Wholesale",
            "subcategory":"Music Publishers",
            "type":"Manufacturing & Wholesale Goods"
        }
    ],
    "sg:phone":"+61 8 9457 1617",
    "sg:postcode":"6155",
    "sg:province":"WA",
    "sg:tags":[
        "wholesaler",
        "dvd",
        "mfrs",
        "cd"
    ],
    "wof:name":"BPS Video Services",
    "wof:placetype":"venue"
},
  "geometry": {"coordinates":[115.886391,-32.040218],"type":"Point"}
}