{
  "type": "Feature",
  "properties": {
    "addr:full":"42 Ben Bow St Yarraville VIC 3013",
    "addr:housenumber":"42",
    "addr:postcode":"3013",
    "addr:street":"Ben Bow St",
    "iso:country":"AU",
    "sg:address":"42 Ben Bow St",
    "sg:city":"Yarraville",
    "sg:classifiers":[
        {
            "category":"Building & Trades",
            "subcategory":"Construction",
            "type":"Services"
        }
    ],
    "sg:phone":"+61 416 112 122",
    "sg:postcode":"3013",
    "sg:province":"VIC",
    "sg:tags":[
        "spouting",
        "guttering"
    ],
    "wof:name":"A K Gutter & Roofing Maintenance",
    "wof:placetype":"venue"
},
  "geometry": {"coordinates":[144.87713623100001,-37.8222122192],"type":"Point"}
}