{
  "type": "Feature",
  "properties": {
    "iso:country":"AU",
    "sg:address":"7 Cousins St",
    "sg:city":"Winnellie",
    "sg:classifiers":[
        {
            "category":"Retail",
            "subcategory":"Car Wash",
            "type":"Services"
        }
    ],
    "sg:phone":"+61 431 452 673",
    "sg:postcode":"0820",
    "sg:province":"NT",
    "sg:tags":[
        "truck",
        "cleaning"
    ],
    "wof:name":"Rods Detailing",
    "wof:placetype":"venue"
},
  "geometry": {"coordinates":[130.87164306599999,-12.4277925491],"type":"Point"}
}