{
  "type": "Feature",
  "properties": {
    "iso:country":"AU",
    "sg:address":"Crn Evans Street & Swanbrood Rd",
    "sg:city":"Inverell",
    "sg:classifiers":[
        {
            "category":"Retail",
            "subcategory":"Auto Repair",
            "type":"Services"
        }
    ],
    "sg:phone":"+61 2 6722 5989",
    "sg:postcode":"2360",
    "sg:province":"NSW",
    "sg:tags":[
        "transmission",
        "automotive",
        "car"
    ],
    "wof:name":"Sapphire City Transmission",
    "wof:placetype":"venue"
},
  "geometry": {"coordinates":[151.12159729000001,-29.7680587769],"type":"Point"}
}