{
  "type": "Feature",
  "properties": {
    "addr:full":"Allora Drv Maroochydore QLD 4558",
    "addr:postcode":"4558",
    "addr:street":"Allora Drv",
    "iso:country":"AU",
    "sg:address":"Allora Drv",
    "sg:city":"Maroochydore",
    "sg:classifiers":[
        {
            "category":"Health Services",
            "subcategory":"Nursing And Care Facility",
            "type":"Services"
        }
    ],
    "sg:phone":"+61 7 5443 8488",
    "sg:postcode":"4558",
    "sg:province":"QLD",
    "sg:tags":[
        "home"
    ],
    "wof:name":"Regis Allora Lodge",
    "wof:placetype":"venue"
},
  "geometry": {"coordinates":[153.06776428200001,-26.6594276428],"type":"Point"}
}