{
  "type": "Feature",
  "properties": {
    "addr:full":"2552 Gold Coast Hwy Mermaid Beach QLD 4218",
    "addr:housenumber":"2552",
    "addr:postcode":"4218",
    "addr:street":"Gold Coast Hwy",
    "iso:country":"AU",
    "sg:address":"2552 Gold Coast Hwy",
    "sg:city":"Mermaid Beach",
    "sg:classifiers":[
        {
            "category":"Retail",
            "subcategory":"Auto Repair",
            "type":"Services"
        }
    ],
    "sg:phone":"+61 417 808 080",
    "sg:postcode":"4218",
    "sg:province":"QLD",
    "sg:tags":[
        "testing",
        "inspection",
        "motor",
        "vehicle"
    ],
    "wof:name":"East Coast Mobile Safety Certificates",
    "wof:placetype":"venue"
},
  "geometry": {"coordinates":[153.43348693900001,-28.0399436951],"type":"Point"}
}