{
  "type": "Feature",
  "properties": {
    "addr:full":"272 Hartley St Cairns QLD 4870",
    "addr:housenumber":"272",
    "addr:postcode":"4870",
    "addr:street":"Hartley St",
    "iso:country":"AU",
    "sg:address":"272 Hartley St",
    "sg:city":"Cairns",
    "sg:classifiers":[
        {
            "category":"Manufacturing",
            "subcategory":"Motor Vehicles & Parts",
            "type":"Manufacturing & Wholesale Goods"
        }
    ],
    "sg:phone":"+61 7 4030 8400",
    "sg:postcode":"4870",
    "sg:province":"QLD",
    "sg:tags":[
        "replacement"
    ],
    "wof:name":"NQ Crash & 4WD Spares",
    "wof:placetype":"venue"
},
  "geometry": {"coordinates":[145.75360107399999,-16.9455928802],"type":"Point"}
}