{
  "type": "Feature",
  "properties": {
    "addr:full":"169- 171 Curlewis St Swan Hill VIC 3585",
    "addr:housenumber":"171",
    "addr:postcode":"3585",
    "addr:street":"Curlewis St",
    "iso:country":"AU",
    "sg:address":"169- 171 Curlewis St",
    "sg:city":"Swan Hill",
    "sg:classifiers":[
        {
            "category":"Manufacturing",
            "subcategory":"Rubber & Plastics",
            "type":"Manufacturing & Wholesale Goods"
        }
    ],
    "sg:phone":"+61 3 5033 1124",
    "sg:postcode":"3585",
    "sg:province":"VIC",
    "sg:tags":[
        "stamp",
        "equipment",
        "metal",
        "maker",
        "supply"
    ],
    "wof:name":"Signs Plus",
    "wof:placetype":"venue"
},
  "geometry": {"coordinates":[143.56251499999999,-35.344967],"type":"Point"}
}