{
  "type": "Feature",
  "properties": {
    "iso:country":"AU",
    "sg:address":"149 Browns Rd",
    "sg:city":"Cranbourne South",
    "sg:classifiers":[
        {
            "category":"Mining & Drilling",
            "type":"Manufacturing & Wholesale Goods"
        }
    ],
    "sg:phone":"+61 3 9775 9955",
    "sg:postcode":"3977",
    "sg:province":"VIC",
    "sg:tags":[
        "boring",
        "contractor"
    ],
    "wof:name":"D & I Excavation",
    "wof:placetype":"venue"
},
  "geometry": {"coordinates":[145.239837647,-38.146987915],"type":"Point"}
}