{
  "type": "Feature",
  "properties": {
    "iso:country":"AU",
    "sg:address":"4 Tomaree St",
    "sg:city":"Nelson Bay",
    "sg:classifiers":[
        {
            "category":"Health Services",
            "subcategory":"Chiropractor",
            "type":"Services"
        }
    ],
    "sg:phone":"+61 2 4984 9255",
    "sg:postcode":"2315",
    "sg:province":"NSW",
    "sg:website":"http://www.chiropractors.asn.au",
    "wof:name":"Ivancic Chiropractic P/L",
    "wof:placetype":"venue"
},
  "geometry": {"coordinates":[152.14382900000001,-32.723595],"type":"Point"}
}