{
  "type": "Feature",
  "properties": {
    "iso:country":"AU",
    "sg:address":"6 Terry Rd",
    "sg:city":"Box Hill",
    "sg:classifiers":[
        {
            "category":"Building & Trades",
            "subcategory":"Construction",
            "type":"Services"
        }
    ],
    "sg:phone":"+61 2 9679 2429",
    "sg:postcode":"2765",
    "sg:province":"NSW",
    "sg:tags":[
        "renovation",
        "alterations",
        "extension",
        "contractor"
    ],
    "wof:name":"Aadbuild",
    "wof:placetype":"venue"
},
  "geometry": {"coordinates":[150.89588928200001,-33.6586227417],"type":"Point"}
}