{
  "type": "Feature",
  "properties": {
    "addr:full":"23 Colray Ave Osborne Park WA 6017",
    "addr:housenumber":"23",
    "addr:postcode":"6017",
    "addr:street":"Colray Ave",
    "iso:country":"AU",
    "sg:address":"23 Colray Ave",
    "sg:city":"Osborne Park",
    "sg:classifiers":[
        {
            "category":"Organizations",
            "subcategory":"Community Association",
            "type":"Services"
        }
    ],
    "sg:phone":"+61 8 9443 3838",
    "sg:postcode":"6017",
    "sg:province":"WA",
    "sg:tags":[
        "equipment",
        "system",
        "vacuum"
    ],
    "wof:name":"Magic Homecare Pty Ltd",
    "wof:placetype":"venue"
},
  "geometry": {"coordinates":[115.81884002699999,-31.9085578918],"type":"Point"}
}