{
  "type": "Feature",
  "properties": {
    "addr:full":"Lot 24 Hutchison St Coober Pedy SA 5723",
    "addr:postcode":"5723",
    "addr:street":"Hutchison St",
    "iso:country":"AU",
    "sg:address":"Lot 24 Hutchison St",
    "sg:city":"Coober Pedy",
    "sg:classifiers":[
        {
            "category":"Manufacturing",
            "subcategory":"Jewelry",
            "type":"Manufacturing & Wholesale Goods"
        }
    ],
    "sg:phone":"+61 8 8672 5717",
    "sg:postcode":"5723",
    "sg:province":"SA",
    "sg:tags":[
        "designer",
        "jewellery"
    ],
    "wof:name":"Jewellers Of Opal",
    "wof:placetype":"venue"
},
  "geometry": {"coordinates":[134.75541687,-29.0102005005],"type":"Point"}
}