{
  "type": "Feature",
  "properties": {
    "addr:full":"4 Park Rd Crawley WA 6009",
    "addr:housenumber":"4",
    "addr:postcode":"6009",
    "addr:street":"Park Rd",
    "iso:country":"AU",
    "sg:address":"4 Park Rd",
    "sg:city":"Crawley",
    "sg:classifiers":[
        {
            "category":"Shopping",
            "subcategory":"Clothing, Apparel, & Fashions",
            "type":"Retail Goods"
        }
    ],
    "sg:phone":"+61 8 9386 3570",
    "sg:postcode":"6009",
    "sg:province":"WA",
    "sg:tags":[
        "academic",
        "regalia",
        "wear"
    ],
    "wof:name":"Australian Federation Of University Women (WA) Inc",
    "wof:placetype":"venue"
},
  "geometry": {"coordinates":[115.815331,-31.974632],"type":"Point"}
}