{
  "type": "Feature",
  "properties": {
    "iso:country":"AU",
    "sg:address":"6 Power St",
    "sg:city":"North Rockhampton",
    "sg:classifiers":[
        {
            "category":"Shopping",
            "subcategory":"Pets & Pet Supplies",
            "type":"Retail Goods"
        }
    ],
    "sg:phone":"+61 7 4921 0577",
    "sg:postcode":"4701",
    "sg:province":"QLD",
    "sg:tags":[
        "boring",
        "drilling",
        "equipment"
    ],
    "wof:name":"D.T.H. Products Pty Ltd",
    "wof:placetype":"venue"
},
  "geometry": {"coordinates":[150.5050354,-23.3460388184],"type":"Point"}
}