{
  "type": "Feature",
  "properties": {
    "addr:full":"188 Liebig St Warrnambool VIC 3280",
    "addr:housenumber":"188",
    "addr:postcode":"3280",
    "addr:street":"Liebig St",
    "iso:country":"AU",
    "sg:address":"188 Liebig St",
    "sg:city":"Warrnambool",
    "sg:classifiers":[
        {
            "category":"Fast Food",
            "type":"Food & Drink"
        }
    ],
    "sg:phone":"+61 3 5562 4840",
    "sg:postcode":"3280",
    "sg:province":"VIC",
    "sg:tags":[
        "away",
        "take"
    ],
    "wof:name":"Warrnambool Fish Supply",
    "wof:placetype":"venue"
},
  "geometry": {"coordinates":[142.48562622099999,-38.3812255859],"type":"Point"}
}