{
  "type": "Feature",
  "properties": {
    "addr:full":"PO Box 272 Hillarys WA 6923",
    "addr:postcode":"6923",
    "iso:country":"AU",
    "sg:address":"PO Box 272",
    "sg:city":"Hillarys",
    "sg:classifiers":[
        {
            "category":"Personal",
            "type":"Services"
        }
    ],
    "sg:phone":"+61 1800 898 606",
    "sg:postcode":"6923",
    "sg:province":"WA",
    "sg:tags":[
        "gift"
    ],
    "wof:name":"The Brilliant Gift Box Company",
    "wof:placetype":"venue"
},
  "geometry": {"coordinates":[115.741539002,-31.809419632],"type":"Point"}
}