{
  "type": "Feature",
  "properties": {
    "iso:country":"AU",
    "sg:address":"PO Box 59",
    "sg:city":"Keith",
    "sg:classifiers":[
        {
            "category":"Shopping",
            "subcategory":"Florist",
            "type":"Retail Goods"
        }
    ],
    "sg:phone":"+61 8 8756 2768",
    "sg:postcode":"5267",
    "sg:province":"SA",
    "sg:tags":[
        "lucerne"
    ],
    "wof:name":"Flairdale Lucerne",
    "wof:placetype":"venue"
},
  "geometry": {"coordinates":[140.354874,-36.098148],"type":"Point"}
}