{
  "type": "Feature",
  "properties": {
    "addr:full":"109 Prince St Grafton NSW 2460",
    "addr:housenumber":"109",
    "addr:postcode":"2460",
    "addr:street":"Prince St",
    "iso:country":"AU",
    "sg:address":"109 Prince St",
    "sg:city":"Grafton",
    "sg:classifiers":[
        {
            "category":"Personal",
            "subcategory":"Beauty Salon",
            "type":"Services"
        }
    ],
    "sg:phone":"+61 2 6642 1791",
    "sg:postcode":"2460",
    "sg:province":"NSW",
    "sg:tags":[
        "hairdresser"
    ],
    "wof:name":"Peters Salon",
    "wof:placetype":"venue"
},
  "geometry": {"coordinates":[152.94218444800001,-29.6802501678],"type":"Point"}
}