{
  "type": "Feature",
  "properties": {
    "iso:country":"AU",
    "sg:address":"83 Proprietary St",
    "sg:city":"Tingalpa",
    "sg:classifiers":[
        {
            "category":"Professional",
            "subcategory":"Business Services",
            "type":"Services"
        }
    ],
    "sg:phone":"+61 7 3907 7500",
    "sg:postcode":"4173",
    "sg:province":"QLD",
    "sg:tags":[
        "fashion",
        "agent"
    ],
    "wof:name":"Nemuki Pty Ltd",
    "wof:placetype":"venue"
},
  "geometry": {"coordinates":[153.10978698700001,-27.4754333496],"type":"Point"}
}