{
  "type": "Feature",
  "properties": {
    "addr:full":"po box 1544, morley, 6943 Morley WA 6062",
    "addr:housenumber":"6943",
    "addr:postcode":"6062",
    "addr:street":"Morley",
    "iso:country":"AU",
    "sg:address":"po box 1544, morley, 6943",
    "sg:city":"Morley",
    "sg:classifiers":[
        {
            "category":"Government",
            "subcategory":"Post Office",
            "type":"Public Place"
        }
    ],
    "sg:phone":"+61 417 174 283",
    "sg:postcode":"6062",
    "sg:province":"WA",
    "sg:tags":[
        "yoga"
    ],
    "wof:name":"Energy Therapy Centre",
    "wof:placetype":"venue"
},
  "geometry": {"coordinates":[115.884628296,-31.8889198303],"type":"Point"}
}