{
  "type": "Feature",
  "properties": {
    "iso:country":"AU",
    "sg:address":"Shop 10, 477 Burwood Hwy",
    "sg:city":"Vermont South",
    "sg:classifiers":[
        {
            "category":"Real Estate",
            "subcategory":"Real Estate Agent",
            "type":"Services"
        }
    ],
    "sg:phone":"+61 3 9886 1588",
    "sg:postcode":"3133",
    "sg:province":"VIC",
    "wof:name":"Ray White (Victoria) Pty Ltd",
    "wof:placetype":"venue"
},
  "geometry": {"coordinates":[145.18011474599999,-37.855922699],"type":"Point"}
}