{
  "type": "Feature",
  "properties": {
    "addr:full":"22 Georgina Ave Keiraville NSW 2500",
    "addr:housenumber":"22",
    "addr:postcode":"2500",
    "addr:street":"Georgina Ave",
    "iso:country":"AU",
    "sg:address":"22 Georgina Ave",
    "sg:city":"Keiraville",
    "sg:classifiers":[
        {
            "category":"Building & Trades",
            "subcategory":"Construction",
            "type":"Services"
        }
    ],
    "sg:phone":"+61 407 211 207",
    "sg:postcode":"2500",
    "sg:province":"NSW",
    "sg:tags":[
        "brick",
        "paving"
    ],
    "wof:name":"Michael Lanyon Landscaping",
    "wof:placetype":"venue"
},
  "geometry": {"coordinates":[150.87039200000001,-34.408478],"type":"Point"}
}