{
  "type": "Feature",
  "properties": {
    "addr:full":"21 Palmer St South Townsville QLD 4810",
    "addr:housenumber":"21",
    "addr:postcode":"4810",
    "addr:street":"Palmer St",
    "iso:country":"AU",
    "sg:address":"21 Palmer St",
    "sg:city":"South Townsville",
    "sg:classifiers":[
        {
            "category":"Restaurant",
            "type":"Food & Drink"
        }
    ],
    "sg:phone":"+61 7 4721 1478",
    "sg:postcode":"4810",
    "sg:province":"QLD",
    "wof:name":"Cactus Jack's Bar & Grill",
    "wof:placetype":"venue"
},
  "geometry": {"coordinates":[146.820908,-19.26033],"type":"Point"}
}