{
  "type": "Feature",
  "properties": {
    "iso:country":"AU",
    "sg:address":"21 Palmer St",
    "sg:city":"South Townsville",
    "sg:classifiers":[
        {
            "category":"Restaurant",
            "type":"Food & Drink"
        }
    ],
    "sg:phone":"+61 7 4721 1478",
    "sg:postcode":"4810",
    "sg:province":"QLD",
    "wof:name":"Cactus Jack's Bar & Grill",
    "wof:placetype":"venue"
},
  "geometry": {"coordinates":[146.820908,-19.26033],"type":"Point"}
}