{
  "type": "Feature",
  "properties": {
    "iso:country":"AU",
    "sg:address":"37 Vernon St",
    "sg:city":"Woollahra",
    "sg:classifiers":[
        {
            "category":"Health Services",
            "subcategory":"Dentist",
            "type":"Services"
        }
    ],
    "sg:phone":"+61 1800 455 222",
    "sg:postcode":"2025",
    "sg:province":"NSW",
    "sg:website":"http://www.lifesmiles.com.au",
    "wof:name":"Arndt Philip D Dr",
    "wof:placetype":"venue"
},
  "geometry": {"coordinates":[151.247283936,-33.8901100159],"type":"Point"}
}