{
  "type": "Feature",
  "properties": {
    "addr:full":"93 High St East Maitland NSW 2323",
    "addr:housenumber":"93",
    "addr:postcode":"2323",
    "addr:street":"High St",
    "iso:country":"AU",
    "sg:address":"93 High St",
    "sg:city":"East Maitland",
    "sg:classifiers":[
        {
            "category":"Shopping",
            "subcategory":"Clothing, Apparel, & Fashions",
            "type":"Retail Goods"
        }
    ],
    "sg:phone":"+61 2 4933 3343",
    "sg:postcode":"2323",
    "sg:province":"NSW",
    "sg:tags":[
        "sample",
        "second",
        "clothing"
    ],
    "wof:name":"Redshield Family Store",
    "wof:placetype":"venue"
},
  "geometry": {"coordinates":[151.59007263199999,-32.7509040833],"type":"Point"}
}