{
  "type": "Feature",
  "properties": {
    "addr:full":"50 Hardy St Dover Heights NSW 2030",
    "addr:housenumber":"50",
    "addr:postcode":"2030",
    "addr:street":"Hardy St Dover",
    "iso:country":"AU",
    "sg:address":"50 Hardy St",
    "sg:city":"Dover Heights",
    "sg:classifiers":[
        {
            "category":"Professional",
            "subcategory":"Accounting & Tax Preparation",
            "type":"Services"
        }
    ],
    "sg:phone":"+61 2 9371 0576",
    "sg:postcode":"2030",
    "sg:province":"NSW",
    "sg:tags":[
        "accountant",
        "auditor"
    ],
    "wof:name":"Wikramanayake & Co",
    "wof:placetype":"venue"
},
  "geometry": {"coordinates":[151.277786255,-33.8761253357],"type":"Point"}
}