{
  "type": "Feature",
  "properties": {
    "addr:full":"27 Turner Pl Yarralumla ACT 2600",
    "addr:housenumber":"27",
    "addr:postcode":"2600",
    "addr:street":"Turner Pl",
    "iso:country":"AU",
    "sg:address":"27 Turner Pl",
    "sg:city":"Yarralumla",
    "sg:classifiers":[
        {
            "category":"Utilities",
            "subcategory":"Sewage",
            "type":"Services"
        }
    ],
    "sg:phone":"+61 409 822 416",
    "sg:postcode":"2600",
    "sg:province":"ACT",
    "sg:tags":[
        "arboriculturist"
    ],
    "wof:name":"Anthony Harris Tree Services",
    "wof:placetype":"venue"
},
  "geometry": {"coordinates":[149.09686279300001,-35.3021850586],"type":"Point"}
}