{
  "type": "Feature",
  "properties": {
    "iso:country":"AU",
    "sg:address":"PO Box 1004",
    "sg:city":"Cairns North",
    "sg:classifiers":[
        {
            "category":"Banks & Credit Unions",
            "subcategory":"Investment Brokerage",
            "type":"Services"
        }
    ],
    "sg:phone":"+61 7 4059 1992",
    "sg:postcode":"4870",
    "sg:province":"QLD",
    "sg:tags":[
        "shutter",
        "louvre"
    ],
    "wof:name":"Cairns Wholesale Blinds & Shutters",
    "wof:placetype":"venue"
},
  "geometry": {"coordinates":[145.759002686,-16.9041805267],"type":"Point"}
}