{
  "type": "Feature",
  "properties": {
    "addr:full":"46 Easey St Collingwood VIC 3066",
    "addr:housenumber":"46",
    "addr:postcode":"3066",
    "addr:street":"Easey St",
    "iso:country":"AU",
    "sg:address":"46 Easey St",
    "sg:city":"Collingwood",
    "sg:classifiers":[
        {
            "category":"Professional",
            "subcategory":"Art Services",
            "type":"Services"
        }
    ],
    "sg:phone":"+61 3 9415 6900",
    "sg:postcode":"3066",
    "sg:province":"VIC",
    "sg:tags":[
        "graphic",
        "designer"
    ],
    "wof:name":"Street Ink Pty Ltd",
    "wof:placetype":"venue"
},
  "geometry": {"coordinates":[144.98670959500001,-37.7975921631],"type":"Point"}
}