{
  "type": "Feature",
  "properties": {
    "addr:full":"Shop 3 20- 22 Hughes St Cabramatta NSW 2166",
    "addr:housenumber":"shop;20 22",
    "addr:postcode":"2166",
    "addr:street":"Hughes St",
    "iso:country":"AU",
    "sg:address":"Shop 3 20- 22 Hughes St",
    "sg:city":"Cabramatta",
    "sg:classifiers":[
        {
            "category":"Restaurant",
            "type":"Food & Drink"
        }
    ],
    "sg:phone":"+61 2 9724 0411",
    "sg:postcode":"2166",
    "sg:province":"NSW",
    "wof:name":"Duc Thanh Restaurant",
    "wof:placetype":"venue"
},
  "geometry": {"coordinates":[150.936203003,-33.8935585022],"type":"Point"}
}