{
  "type": "Feature",
  "properties": {
    "addr:full":"Patricks Rd Arana Hills QLD 4054",
    "addr:postcode":"4054",
    "addr:street":"Patricks Rd",
    "iso:country":"AU",
    "sg:address":"Patricks Rd",
    "sg:city":"Arana Hills",
    "sg:classifiers":[
        {
            "category":"Autos & Motor Vehicles",
            "subcategory":"Fuel & Gas Station",
            "type":"Retail Goods"
        }
    ],
    "sg:phone":"+61 7 3351 6511",
    "sg:postcode":"4054",
    "sg:province":"QLD",
    "wof:name":"Shell Arana Hills Self Serve",
    "wof:placetype":"venue"
},
  "geometry": {"coordinates":[152.960037231,-27.3975811005],"type":"Point"}
}