{
  "type": "Feature",
  "properties": {
    "addr:full":"101 Carp St Bega NSW 2550",
    "addr:housenumber":"101",
    "addr:postcode":"2550",
    "addr:street":"Carp St",
    "iso:country":"AU",
    "sg:address":"101 Carp St",
    "sg:city":"Bega",
    "sg:classifiers":[
        {
            "category":"Health Services",
            "subcategory":"Medical Lab",
            "type":"Services"
        }
    ],
    "sg:phone":"+61 2 6492 2049",
    "sg:postcode":"2550",
    "sg:province":"NSW",
    "sg:tags":[
        "laboratory",
        "pathology"
    ],
    "wof:name":"Capital Pathology",
    "wof:placetype":"venue"
},
  "geometry": {"coordinates":[149.84361267099999,-36.6741485596],"type":"Point"}
}