{
  "type": "Feature",
  "properties": {
    "addr:full":"Shop G53/ 3240 Surfers Paradise Blv Surfers Paradise QLD 4217",
    "addr:housenumber":"g53 / 3240",
    "addr:postcode":"4217",
    "addr:street":"Surfers Paradise Blv",
    "iso:country":"AU",
    "sg:address":"Shop G53/ 3240",
    "sg:city":"Surfers Paradise Blv Surfers Paradise",
    "sg:classifiers":[
        {
            "category":"Shopping",
            "subcategory":"Clothing, Apparel, & Fashions",
            "type":"Retail Goods"
        }
    ],
    "sg:phone":"+61 7 5526 8201",
    "sg:postcode":"4217",
    "sg:province":"QLD",
    "sg:tags":[
        "lady",
        "wear"
    ],
    "wof:name":"Golddigga Australia",
    "wof:placetype":"venue"
},
  "geometry": {"coordinates":[153.42901611299999,-27.9974365234],"type":"Point"}
}