{
  "type": "Feature",
  "properties": {
    "addr:full":"66 Sturgeon St Ormiston QLD 4160",
    "addr:housenumber":"66",
    "addr:postcode":"4160",
    "addr:street":"Sturgeon St",
    "iso:country":"AU",
    "sg:address":"66 Sturgeon St",
    "sg:city":"Ormiston",
    "sg:classifiers":[
        {
            "category":"Social Services",
            "subcategory":"Child Care",
            "type":"Services"
        }
    ],
    "sg:phone":"+61 7 3286 6333",
    "sg:postcode":"4160",
    "sg:province":"QLD",
    "wof:name":"Jumping Beans Chilcare",
    "wof:placetype":"venue"
},
  "geometry": {"coordinates":[153.25245666500001,-27.5119552612],"type":"Point"}
}