{
  "type": "Feature",
  "properties": {
    "iso:country":"AU",
    "sg:address":"33 Hobart St",
    "sg:city":"Riverstone",
    "sg:classifiers":[
        {
            "category":"Wholesale",
            "subcategory":"Metals & Minerals",
            "type":"Manufacturing & Wholesale Goods"
        }
    ],
    "sg:phone":"+61 1800 673 002",
    "sg:postcode":"2765",
    "sg:province":"NSW",
    "sg:tags":[
        "steel",
        "merchant"
    ],
    "wof:name":"All Steel N L &#039;Nick&#039; Dean",
    "wof:placetype":"venue"
},
  "geometry": {"coordinates":[150.859283447,-33.6683998108],"type":"Point"}
}