{
  "type": "Feature",
  "properties": {
    "iso:country":"AU",
    "sg:address":"30 Park Ave",
    "sg:city":"Woolgoolga",
    "sg:classifiers":[
        {
            "category":"Retail",
            "subcategory":"Auto Repair",
            "type":"Services"
        }
    ],
    "sg:phone":"+61 2 6654 7273",
    "sg:postcode":"2456",
    "sg:province":"NSW",
    "sg:tags":[
        "repairer",
        "motor",
        "engineer"
    ],
    "wof:name":"Mobytune",
    "wof:placetype":"venue"
},
  "geometry": {"coordinates":[153.173538,-30.119366],"type":"Point"}
}