{
  "type": "Feature",
  "properties": {
    "addr:full":"PO Box 907 South Perth WA 6151",
    "addr:postcode":"6151",
    "iso:country":"AU",
    "sg:address":"PO Box 907",
    "sg:city":"South Perth",
    "sg:classifiers":[
        {
            "category":"Building & Trades",
            "subcategory":"Plumbing",
            "type":"Services"
        }
    ],
    "sg:phone":"+61 8 9368 5005",
    "sg:postcode":"6151",
    "sg:province":"WA",
    "sg:tags":[
        "plumber",
        "gasfitters"
    ],
    "wof:name":"South Perth Water Plumbing Services",
    "wof:placetype":"venue"
},
  "geometry": {"coordinates":[115.870239,-31.98105],"type":"Point"}
}