{
  "type": "Feature",
  "properties": {
    "iso:country":"AU",
    "sg:address":"302 Macarthur St",
    "sg:city":"Ballarat",
    "sg:classifiers":[
        {
            "category":"Fast Food",
            "type":"Food & Drink"
        }
    ],
    "sg:phone":"+61 3 5332 1203",
    "sg:postcode":"3350",
    "sg:province":"VIC",
    "sg:tags":[
        "away",
        "take"
    ],
    "wof:name":"Fish Haul",
    "wof:placetype":"venue"
},
  "geometry": {"coordinates":[143.859375,-37.550938],"type":"Point"}
}