{
  "type": "Feature",
  "properties": {
    "iso:country":"AU",
    "sg:address":"PO Box 10",
    "sg:city":"Leppington",
    "sg:classifiers":[
        {
            "category":"Bars & Pubs",
            "subcategory":"Nightclub",
            "type":"Food & Drink"
        }
    ],
    "sg:phone":"+61 2 9606 4241",
    "sg:postcode":"2171",
    "sg:province":"NSW",
    "sg:tags":[
        "discotheque"
    ],
    "wof:name":"City Club Hopper",
    "wof:placetype":"venue"
},
  "geometry": {"coordinates":[150.846237183,-33.9284286499],"type":"Point"}
}