{
  "type": "Feature",
  "properties": {
    "addr:full":"Shp 6, 131 Bussell Hwy Margaret River WA 6285",
    "addr:housenumber":"131",
    "addr:postcode":"6285",
    "addr:street":"Bussell Hwy",
    "iso:country":"AU",
    "sg:address":"Shp 6, 131 Bussell Hwy",
    "sg:city":"Margaret River",
    "sg:classifiers":[
        {
            "category":"Shopping",
            "subcategory":"Clothing, Apparel, & Fashions",
            "type":"Retail Goods"
        }
    ],
    "sg:phone":"+61 8 9757 9260",
    "sg:postcode":"6285",
    "sg:province":"WA",
    "sg:tags":[
        "lingerie",
        "hosiery",
        "sleepwear"
    ],
    "wof:name":"Beautifully Bare Lingerie",
    "wof:placetype":"venue"
},
  "geometry": {"coordinates":[115.073829651,-33.9516983032],"type":"Point"}
}