{
  "type": "Feature",
  "properties": {
    "addr:full":"75 Natimuk Rd Horsham VIC 3400",
    "addr:housenumber":"75",
    "addr:postcode":"3400",
    "addr:street":"Natimuk Rd",
    "iso:country":"AU",
    "sg:address":"75 Natimuk Rd",
    "sg:city":"Horsham",
    "sg:classifiers":[
        {
            "category":"Utilities",
            "subcategory":"Electric",
            "type":"Services"
        }
    ],
    "sg:phone":"+61 3 5382 4552",
    "sg:postcode":"3400",
    "sg:province":"VIC",
    "sg:tags":[
        "electrical",
        "contractor"
    ],
    "wof:name":"David Chilver Electrician",
    "wof:placetype":"venue"
},
  "geometry": {"coordinates":[142.18365478499999,-36.7202301025],"type":"Point"}
}