{
  "type": "Feature",
  "properties": {
    "iso:country":"AU",
    "sg:address":"151 Point Nepean Rd",
    "sg:city":"Dromana",
    "sg:classifiers":[
        {
            "category":"Restaurant",
            "type":"Food & Drink"
        }
    ],
    "sg:phone":"+61 3 5987 1922",
    "sg:postcode":"3936",
    "sg:province":"VIC",
    "wof:name":"Dromana Hotel",
    "wof:placetype":"venue"
},
  "geometry": {"coordinates":[144.962814331,-38.3338241577],"type":"Point"}
}