{
  "type": "Feature",
  "properties": {
    "addr:full":"7 James St Yeppoon QLD 4703",
    "addr:housenumber":"7",
    "addr:postcode":"4703",
    "addr:street":"James St",
    "iso:country":"AU",
    "sg:address":"7 James St",
    "sg:city":"Yeppoon",
    "sg:classifiers":[
        {
            "category":"Arts & Performance",
            "subcategory":"Art Gallery",
            "type":"Entertainment"
        }
    ],
    "sg:phone":"+61 7 4938 3535",
    "sg:postcode":"4703",
    "sg:province":"QLD",
    "wof:name":"Paint Pot Gallery",
    "wof:placetype":"venue"
},
  "geometry": {"coordinates":[150.74650573700001,-23.1282958984],"type":"Point"}
}