{
  "type": "Feature",
  "properties": {
    "addr:full":"11 Woodlark St Lismore NSW 2480",
    "addr:housenumber":"11",
    "addr:postcode":"2480",
    "addr:street":"Woodlark St",
    "iso:country":"AU",
    "sg:address":"11 Woodlark St",
    "sg:city":"Lismore",
    "sg:classifiers":[
        {
            "category":"Shopping",
            "subcategory":"Beauty & Cosmetics",
            "type":"Retail Goods"
        }
    ],
    "sg:phone":"+61 2 6622 6464",
    "sg:postcode":"2480",
    "sg:province":"NSW",
    "wof:name":"Cosmetic Shop The",
    "wof:placetype":"venue"
},
  "geometry": {"coordinates":[153.27760314899999,-28.8069992065],"type":"Point"}
}