{
  "type": "Feature",
  "properties": {
    "addr:full":"64 Old York Rd Northam WA 6401",
    "addr:housenumber":"64",
    "addr:postcode":"6401",
    "addr:street":"Old York Rd",
    "iso:country":"AU",
    "sg:address":"64 Old York Rd",
    "sg:city":"Northam",
    "sg:classifiers":[
        {
            "category":"Wholesale",
            "subcategory":"Farm Supplies",
            "type":"Manufacturing & Wholesale Goods"
        }
    ],
    "sg:phone":"+61 8 9622 2888",
    "sg:postcode":"6401",
    "sg:province":"WA",
    "sg:tags":[
        "equipment"
    ],
    "wof:name":"Page Machinery Pty Ltd",
    "wof:placetype":"venue"
},
  "geometry": {"coordinates":[116.682098389,-31.6489849091],"type":"Point"}
}