{
  "type": "Feature",
  "properties": {
    "iso:country":"AU",
    "sg:address":"44 Commercial Rd",
    "sg:city":"Salisbury",
    "sg:classifiers":[
        {
            "category":"Professional",
            "subcategory":"Accounting & Tax Preparation",
            "type":"Services"
        }
    ],
    "sg:phone":"+61 8 8258 0421",
    "sg:postcode":"5108",
    "sg:province":"SA",
    "sg:tags":[
        "consultant",
        "taxation"
    ],
    "wof:name":"Hatcher & Vanson Pty Ltd",
    "wof:placetype":"venue"
},
  "geometry": {"coordinates":[138.649124145,-34.755355835],"type":"Point"}
}