{
  "type": "Feature",
  "properties": {
    "iso:country":"AU",
    "sg:address":"738 North Rd",
    "sg:city":"Ormond",
    "sg:classifiers":[
        {
            "category":"Building & Trades",
            "subcategory":"Construction",
            "type":"Services"
        }
    ],
    "sg:phone":"+61 403 383 330",
    "sg:postcode":"3204",
    "sg:province":"VIC",
    "sg:tags":[
        "renovation",
        "alterations",
        "extension",
        "contractor"
    ],
    "wof:name":"Pollak Constructions",
    "wof:placetype":"venue"
},
  "geometry": {"coordinates":[145.05221599999999,-37.905567],"type":"Point"}
}