{
  "type": "Feature",
  "properties": {
    "addr:full":"Shp2/ 50 Camp Rd Broadmeadows VIC 3047",
    "addr:postcode":"3047",
    "addr:street":"Camp Rd",
    "iso:country":"AU",
    "sg:address":"Shp2/ 50 Camp Rd",
    "sg:city":"Broadmeadows",
    "sg:classifiers":[
        {
            "category":"Home & Garden",
            "subcategory":"Hardware",
            "type":"Retail Goods"
        }
    ],
    "sg:phone":"+61 3 9357 1577",
    "sg:postcode":"3047",
    "sg:province":"VIC",
    "sg:tags":[
        "plumber",
        "supply"
    ],
    "wof:name":"Plumbcorp Bathroom & Kitchen Centre",
    "wof:placetype":"venue"
},
  "geometry": {"coordinates":[144.926605225,-37.6862106323],"type":"Point"}
}