{
  "type": "Feature",
  "properties": {
    "iso:country":"AU",
    "sg:address":"21 Sturt St",
    "sg:city":"Townsville",
    "sg:classifiers":[
        {
            "category":"Recreation",
            "subcategory":"Boat Charter",
            "type":"Entertainment"
        }
    ],
    "sg:phone":"+61 7 4774 7468",
    "sg:postcode":"4810",
    "sg:province":"QLD",
    "wof:name":"Luxury Charters NQ",
    "wof:placetype":"venue"
},
  "geometry": {"coordinates":[146.814697,-19.260807],"type":"Point"}
}