{
  "type": "Feature",
  "properties": {
    "addr:full":"2/ 483 Hammond Rd Dandenong VIC 3175",
    "addr:housenumber":"/ 483",
    "addr:postcode":"3175",
    "addr:street":"Hammond Rd",
    "iso:country":"AU",
    "sg:address":"2/ 483 Hammond Rd",
    "sg:city":"Dandenong",
    "sg:classifiers":[
        {
            "category":"Utilities",
            "subcategory":"Natural Gas",
            "type":"Services"
        }
    ],
    "sg:phone":"+61 3 9706 6788",
    "sg:postcode":"3175",
    "sg:province":"VIC",
    "sg:tags":[
        "hose",
        "reel",
        "cable"
    ],
    "wof:name":"Cavotec Australia Pty Ltd",
    "wof:placetype":"venue"
},
  "geometry": {"coordinates":[145.20249939000001,-38.030834198],"type":"Point"}
}