{
  "type": "Feature",
  "properties": {
    "addr:full":"Unit 1, 69 Hay St Subiaco WA 6008",
    "addr:housenumber":"69",
    "addr:postcode":"6008",
    "addr:street":"Hay St",
    "iso:country":"AU",
    "sg:address":"Unit 1, 69 Hay St",
    "sg:city":"Subiaco",
    "sg:classifiers":[
        {
            "category":"Shopping",
            "subcategory":"Computers & Home Electronics",
            "type":"Retail Goods"
        }
    ],
    "sg:phone":"+61 8 9388 2315",
    "sg:postcode":"6008",
    "sg:province":"WA",
    "sg:tags":[
        "hardware",
        "equipment"
    ],
    "wof:name":"X S I Technology Pty Ltd",
    "wof:placetype":"venue"
},
  "geometry": {"coordinates":[115.835449219,-31.9472026825],"type":"Point"}
}