{
  "type": "Feature",
  "properties": {
    "addr:full":"PO Box 16 Poowong VIC 3988",
    "addr:postcode":"3988",
    "iso:country":"AU",
    "sg:address":"PO Box 16",
    "sg:city":"Poowong",
    "sg:classifiers":[
        {
            "category":"Utilities",
            "subcategory":"Telephone",
            "type":"Services"
        }
    ],
    "sg:phone":"+61 409 867 733",
    "sg:postcode":"3988",
    "sg:province":"VIC",
    "sg:tags":[
        "installation",
        "system",
        "maintenance"
    ],
    "wof:name":"R.Selir Communications",
    "wof:placetype":"venue"
},
  "geometry": {"coordinates":[145.76388549800001,-38.3430290222],"type":"Point"}
}