{
  "type": "Feature",
  "properties": {
    "addr:full":"203 Malop St Geelong VIC 3220",
    "addr:housenumber":"203",
    "addr:postcode":"3220",
    "addr:street":"Malop St",
    "iso:country":"AU",
    "sg:address":"203 Malop St",
    "sg:city":"Geelong",
    "sg:classifiers":[
        {
            "category":"Professional",
            "subcategory":"Art Services",
            "type":"Services"
        }
    ],
    "sg:phone":"+61 3 5221 4408",
    "sg:postcode":"3220",
    "sg:province":"VIC",
    "sg:tags":[
        "graphic",
        "designer"
    ],
    "wof:name":"Ad-Cell Print Group Pty Ltd",
    "wof:placetype":"venue"
},
  "geometry": {"coordinates":[144.36613500000001,-38.148579],"type":"Point"}
}