{
  "type": "Feature",
  "properties": {
    "addr:full":"U2/ 7 Withington St East Brisbane QLD 4169",
    "addr:housenumber":"7",
    "addr:postcode":"4169",
    "addr:street":"U2 /;Withington St",
    "iso:country":"AU",
    "sg:address":"U2/ 7 Withington St",
    "sg:city":"East Brisbane",
    "sg:classifiers":[
        {
            "category":"Utilities",
            "subcategory":"Electric",
            "type":"Services"
        }
    ],
    "sg:phone":"+61 7 3891 3274",
    "sg:postcode":"4169",
    "sg:province":"QLD",
    "sg:tags":[
        "electrical",
        "contractor"
    ],
    "wof:name":"Urban Electrical",
    "wof:placetype":"venue"
},
  "geometry": {"coordinates":[153.04653930699999,-27.4867458344],"type":"Point"}
}