{
  "type": "Feature",
  "properties": {
    "addr:full":"124 Compton Rd Woodridge QLD 4114",
    "addr:housenumber":"124",
    "addr:postcode":"4114",
    "addr:street":"Compton Rd",
    "iso:country":"AU",
    "sg:address":"124 Compton Rd",
    "sg:city":"Woodridge",
    "sg:classifiers":[
        {
            "category":"Wholesale",
            "subcategory":"Metals & Minerals",
            "type":"Manufacturing & Wholesale Goods"
        }
    ],
    "sg:phone":"+61 7 3808 9988",
    "sg:postcode":"4114",
    "sg:province":"QLD",
    "sg:tags":[
        "steel",
        "merchant"
    ],
    "wof:name":"Coil Steels Plate & Long Products",
    "wof:placetype":"venue"
},
  "geometry": {"coordinates":[153.10168457,-27.6183795929],"type":"Point"}
}