{
  "type": "Feature",
  "properties": {
    "iso:country":"AU",
    "sg:address":"23 Yallambee Rd",
    "sg:city":"Berowra",
    "sg:classifiers":[
        {
            "category":"Professional",
            "subcategory":"Art Services",
            "type":"Services"
        }
    ],
    "sg:phone":"+61 2 9456 7670",
    "sg:postcode":"2081",
    "sg:province":"NSW",
    "sg:tags":[
        "decorator",
        "painter"
    ],
    "wof:name":"Peninsula Painting & Decorating",
    "wof:placetype":"venue"
},
  "geometry": {"coordinates":[151.14483642600001,-33.6288528442],"type":"Point"}
}