{
  "type": "Feature",
  "properties": {
    "iso:country":"AU",
    "sg:address":"U2/ 25 Industrial Rd",
    "sg:city":"Unanderra",
    "sg:classifiers":[
        {
            "category":"Building & Trades",
            "subcategory":"Construction",
            "type":"Services"
        }
    ],
    "sg:phone":"+61 2 4272 1744",
    "sg:postcode":"2526",
    "sg:province":"NSW",
    "sg:tags":[
        "contractor"
    ],
    "wof:name":"Hayes Russel",
    "wof:placetype":"venue"
},
  "geometry": {"coordinates":[150.85737609899999,-34.4643745422],"type":"Point"}
}