{
  "type": "Feature",
  "properties": {
    "iso:country":"AU",
    "sg:address":"17 Hindley St",
    "sg:city":"Adelaide",
    "sg:classifiers":[
        {
            "category":"Travel",
            "subcategory":"Hotels & Motels",
            "type":"Entertainment"
        }
    ],
    "sg:phone":"+61 8 8231 3225",
    "sg:postcode":"5000",
    "sg:province":"SA",
    "sg:tags":[
        "accommodation"
    ],
    "wof:name":"Tattersalls International Inner-City Backpackers",
    "wof:placetype":"venue"
},
  "geometry": {"coordinates":[138.598190308,-34.9231872559],"type":"Point"}
}