{
  "type": "Feature",
  "properties": {
    "addr:full":"127 Marin Pde San Remo VIC 3925",
    "addr:housenumber":"127",
    "addr:postcode":"3925",
    "addr:street":"Marin Pde",
    "iso:country":"AU",
    "sg:address":"127 Marin Pde",
    "sg:city":"San Remo",
    "sg:classifiers":[
        {
            "category":"Real Estate",
            "subcategory":"Real Estate Agent",
            "type":"Services"
        }
    ],
    "sg:phone":"+61 3 5678 5408",
    "sg:postcode":"3925",
    "sg:province":"VIC",
    "wof:name":"Homeland Estate Agency",
    "wof:placetype":"venue"
},
  "geometry": {"coordinates":[145.369140625,-38.5211029053],"type":"Point"}
}