{
  "type": "Feature",
  "properties": {
    "iso:country":"AU",
    "sg:address":"439 Gympie Rd",
    "sg:city":"Strathpine",
    "sg:classifiers":[
        {
            "category":"Professional",
            "subcategory":"Accounting & Tax Preparation",
            "type":"Services"
        }
    ],
    "sg:phone":"+61 7 3881 3397",
    "sg:postcode":"4500",
    "sg:province":"QLD",
    "sg:tags":[
        "consultant",
        "taxation"
    ],
    "wof:name":"Don Richards",
    "wof:placetype":"venue"
},
  "geometry": {"coordinates":[152.988845825,-27.3024024963],"type":"Point"}
}