{
  "type": "Feature",
  "properties": {
    "iso:country":"AU",
    "sg:address":"1975 Main Rd",
    "sg:city":"Lilydale",
    "sg:classifiers":[
        {
            "category":"Government",
            "subcategory":"Post Office",
            "type":"Public Place"
        }
    ],
    "sg:phone":"+61 3 6395 1177",
    "sg:postcode":"7268",
    "sg:province":"TAS",
    "sg:tags":[
        "postal"
    ],
    "wof:name":"Australia Post",
    "wof:placetype":"venue"
},
  "geometry": {"coordinates":[147.21772799999999,-41.249237],"type":"Point"}
}