{
  "type": "Feature",
  "properties": {
    "addr:full":"Shop 2, Moreton Town Shopping Centre, Wynnum Rd Tingalpa QLD 4173",
    "addr:housenumber":"shop 2",
    "addr:postcode":"4173",
    "addr:street":"Wynnum Rd",
    "iso:country":"AU",
    "sg:address":"Shop 2, Moreton Town Shopping Centre, Wynnum Rd",
    "sg:city":"Tingalpa",
    "sg:classifiers":[
        {
            "category":"Food & Beverages",
            "subcategory":"Liquor & Beverages",
            "type":"Retail Goods"
        }
    ],
    "sg:phone":"+61 7 3348 9856",
    "sg:postcode":"4173",
    "sg:province":"QLD",
    "sg:tags":[
        "store"
    ],
    "wof:name":"Moreton Town",
    "wof:placetype":"venue"
},
  "geometry": {"coordinates":[153.12892150900001,-27.4744300842],"type":"Point"}
}