{
  "type": "Feature",
  "properties": {
    "iso:country":"AU",
    "sg:address":"115 Lefroy Rd",
    "sg:city":"Hilton",
    "sg:classifiers":[
        {
            "category":"Communications",
            "subcategory":"Film & Video Production",
            "type":"Services"
        }
    ],
    "sg:phone":"+61 8 9337 7772",
    "sg:postcode":"6163",
    "sg:province":"WA",
    "sg:tags":[
        "dvd",
        "library"
    ],
    "wof:name":"Video City",
    "wof:placetype":"venue"
},
  "geometry": {"coordinates":[115.775192,-32.067242],"type":"Point"}
}