{
  "type": "Feature",
  "properties": {
    "addr:full":"Unit 2, Cnr Griffiths & Claude Sts Burswood WA 6100",
    "addr:housenumber":"cnr",
    "addr:postcode":"6100",
    "iso:country":"AU",
    "sg:address":"Unit 2, Cnr Griffiths & Claude Sts",
    "sg:city":"Burswood",
    "sg:classifiers":[
        {
            "category":"Shopping",
            "subcategory":"Gifts & Souvenirs",
            "type":"Retail Goods"
        }
    ],
    "sg:phone":"+61 8 9470 4995",
    "sg:postcode":"6100",
    "sg:province":"WA",
    "sg:tags":[
        "print",
        "poster",
        "pictures"
    ],
    "wof:name":"Daytone Printing Pty Ltd",
    "wof:placetype":"venue"
},
  "geometry": {"coordinates":[115.898841858,-31.9627990723],"type":"Point"}
}