{
  "type": "Feature",
  "properties": {
    "iso:country":"AU",
    "sg:address":"35 High St",
    "sg:city":"Hastings",
    "sg:classifiers":[
        {
            "category":"Real Estate",
            "subcategory":"Real Estate Agent",
            "type":"Services"
        }
    ],
    "sg:phone":"+61 3 5979 3000",
    "sg:postcode":"3915",
    "sg:province":"VIC",
    "wof:name":"Tallon First National Real Estate",
    "wof:placetype":"venue"
},
  "geometry": {"coordinates":[145.19198608400001,-38.3078422546],"type":"Point"}
}