{
  "type": "Feature",
  "properties": {
    "addr:full":"318 Hammond Rd Dandenong VIC 3175",
    "addr:housenumber":"318",
    "addr:postcode":"3175",
    "addr:street":"Hammond Rd",
    "iso:country":"AU",
    "sg:address":"318 Hammond Rd",
    "sg:city":"Dandenong",
    "sg:classifiers":[
        {
            "category":"Banks & Credit Unions",
            "subcategory":"Investment Brokerage",
            "type":"Services"
        }
    ],
    "sg:phone":"+61 3 9706 5577",
    "sg:postcode":"3175",
    "sg:province":"VIC",
    "sg:tags":[
        "heat",
        "metal",
        "treatment"
    ],
    "sg:website":"http://www.steelinc.com.au",
    "wof:name":"ADI Engineering Process & Heat Treatment",
    "wof:placetype":"venue"
},
  "geometry": {"coordinates":[145.20310974099999,-38.0259208679],"type":"Point"}
}