{
  "type": "Feature",
  "properties": {
    "addr:full":"2 Timor St Duncraig WA 6023",
    "addr:housenumber":"2",
    "addr:postcode":"6023",
    "addr:street":"Timor St",
    "iso:country":"AU",
    "sg:address":"2 Timor St",
    "sg:city":"Duncraig",
    "sg:classifiers":[
        {
            "category":"Professional",
            "subcategory":"Art Services",
            "type":"Services"
        }
    ],
    "sg:phone":"+61 8 9246 4408",
    "sg:postcode":"6023",
    "sg:province":"WA",
    "sg:tags":[
        "arranger",
        "music",
        "composer"
    ],
    "wof:name":"Bonsai Recording Studio",
    "wof:placetype":"venue"
},
  "geometry": {"coordinates":[115.789260864,-31.8368835449],"type":"Point"}
}