{
  "type": "Feature",
  "properties": {
    "addr:full":"46 Princes Hwy Doveton VIC 3177",
    "addr:housenumber":"46",
    "addr:postcode":"3177",
    "addr:street":"Princes Hwy",
    "iso:country":"AU",
    "sg:address":"46 Princes Hwy",
    "sg:city":"Doveton",
    "sg:classifiers":[
        {
            "category":"Autos & Motor Vehicles",
            "subcategory":"Auto Supplies",
            "type":"Retail Goods"
        }
    ],
    "sg:phone":"+61 3 9791 2215",
    "sg:postcode":"3177",
    "sg:province":"VIC",
    "sg:tags":[
        "tyre"
    ],
    "wof:name":"Bridgestone Australia Ltd",
    "wof:placetype":"venue"
},
  "geometry": {"coordinates":[145.238937378,-38.0016479492],"type":"Point"}
}