{
  "type": "Feature",
  "properties": {
    "iso:country":"AU",
    "sg:address":"55 Sandown Rd",
    "sg:city":"Norwood",
    "sg:classifiers":[
        {
            "category":"Recreation",
            "subcategory":"Fishing",
            "type":"Entertainment"
        }
    ],
    "sg:phone":"+61 3 6344 3691",
    "sg:postcode":"7250",
    "sg:province":"TAS",
    "sg:tags":[
        "trip"
    ],
    "wof:name":"Old Macs Farm & Fishery",
    "wof:placetype":"venue"
},
  "geometry": {"coordinates":[147.179290772,-41.4476318359],"type":"Point"}
}