{
  "type": "Feature",
  "properties": {
    "iso:country":"AU",
    "sg:address":"9 Cumberland Drv",
    "sg:city":"Seaford",
    "sg:classifiers":[
        {
            "category":"Professional",
            "subcategory":"Engineering",
            "type":"Services"
        }
    ],
    "sg:phone":"+61 3 9782 5158",
    "sg:postcode":"3198",
    "sg:province":"VIC",
    "sg:tags":[
        "engineer"
    ],
    "wof:name":"C & I Precision Engineering",
    "wof:placetype":"venue"
},
  "geometry": {"coordinates":[145.13981628400001,-38.1133880615],"type":"Point"}
}