{
  "type": "Feature",
  "properties": {
    "addr:full":"32 Watt St Gladstone QLD 4680",
    "addr:housenumber":"32",
    "addr:postcode":"4680",
    "addr:street":"Watt St",
    "iso:country":"AU",
    "sg:address":"32 Watt St",
    "sg:city":"Gladstone",
    "sg:classifiers":[
        {
            "category":"Freight",
            "type":"Transportation"
        }
    ],
    "sg:phone":"+61 414 729 429",
    "sg:postcode":"4680",
    "sg:province":"QLD",
    "sg:tags":[
        "light",
        "carrier"
    ],
    "wof:name":"Coleborn Transport Cranetruck Hire Service",
    "wof:placetype":"venue"
},
  "geometry": {"coordinates":[151.243286133,-23.8488273621],"type":"Point"}
}