{
  "type": "Feature",
  "properties": {
    "iso:country":"AU",
    "sg:address":"43a Egerton St",
    "sg:city":"Southport",
    "sg:classifiers":[
        {
            "category":"Manufacturing",
            "subcategory":"Motor Vehicles & Parts",
            "type":"Manufacturing & Wholesale Goods"
        }
    ],
    "sg:phone":"+61 7 5532 7914",
    "sg:postcode":"4215",
    "sg:province":"QLD",
    "sg:tags":[
        "replacement"
    ],
    "wof:name":"R M A Import Masters Pty Ltd",
    "wof:placetype":"venue"
},
  "geometry": {"coordinates":[153.41166687,-27.9783287048],"type":"Point"}
}