{
  "type": "Feature",
  "properties": {
    "addr:full":"341 Crown St Wollongong NSW 2500",
    "addr:housenumber":"341",
    "addr:postcode":"2500",
    "addr:street":"Crown St",
    "iso:country":"AU",
    "sg:address":"341 Crown St",
    "sg:city":"Wollongong",
    "sg:classifiers":[
        {
            "category":"Social Services",
            "subcategory":"Child Care",
            "type":"Services"
        }
    ],
    "sg:phone":"+61 2 4229 2755",
    "sg:postcode":"2500",
    "sg:province":"NSW",
    "sg:tags":[
        "support",
        "health"
    ],
    "wof:name":"Early Childhood Centres",
    "wof:placetype":"venue"
},
  "geometry": {"coordinates":[150.88816800000001,-34.425911],"type":"Point"}
}