{
  "type": "Feature",
  "properties": {
    "addr:full":"44 Audrey Ave Blair Athol SA 5084",
    "addr:housenumber":"44",
    "addr:postcode":"5084",
    "addr:street":"Audrey Ave",
    "iso:country":"AU",
    "sg:address":"44 Audrey Ave",
    "sg:city":"Blair Athol",
    "sg:classifiers":[
        {
            "category":"Education",
            "subcategory":"School",
            "type":"Public Place"
        }
    ],
    "sg:phone":"+61 8 8260 2655",
    "sg:postcode":"5084",
    "sg:province":"SA",
    "sg:tags":[
        "co-educational"
    ],
    "wof:name":"Lutheran Schools",
    "wof:placetype":"venue"
},
  "geometry": {"coordinates":[138.60025024399999,-34.8616752625],"type":"Point"}
}