{
  "type": "Feature",
  "properties": {
    "addr:full":"Gordon St Aramac QLD 4726",
    "addr:postcode":"4726",
    "addr:street":"Gordon St",
    "iso:country":"AU",
    "sg:address":"Gordon St",
    "sg:city":"Aramac",
    "sg:classifiers":[
        {
            "category":"Professional",
            "subcategory":"Business Services",
            "type":"Services"
        }
    ],
    "sg:phone":"+61 7 4651 3285",
    "sg:postcode":"4726",
    "sg:province":"QLD",
    "sg:tags":[
        "livestock",
        "transport"
    ],
    "wof:name":"Ken Walker Transport Pty Ltd",
    "wof:placetype":"venue"
},
  "geometry": {"coordinates":[145.246185303,-22.9719619751],"type":"Point"}
}