{
  "type": "Feature",
  "properties": {
    "addr:full":"114 Clarence St Sydney NSW 2000",
    "addr:housenumber":"114",
    "addr:postcode":"2000",
    "addr:street":"Clarence St",
    "iso:country":"AU",
    "sg:address":"114 Clarence St",
    "sg:city":"Sydney",
    "sg:classifiers":[
        {
            "category":"Banks & Credit Unions",
            "subcategory":"Bureau De Change",
            "type":"Services"
        }
    ],
    "sg:phone":"+61 2 9262 6788",
    "sg:postcode":"2000",
    "sg:province":"NSW",
    "sg:tags":[
        "reporting"
    ],
    "wof:name":"Faxsearch",
    "wof:placetype":"venue"
},
  "geometry": {"coordinates":[151.20541381800001,-33.8684082031],"type":"Point"}
}