{
  "type": "Feature",
  "properties": {
    "addr:full":"281 Place Rd Geraldton WA 6530",
    "addr:housenumber":"281",
    "addr:postcode":"6530",
    "addr:street":"Place Rd",
    "iso:country":"AU",
    "sg:address":"281 Place Rd",
    "sg:city":"Geraldton",
    "sg:classifiers":[
        {
            "category":"Retail",
            "subcategory":"Auto Repair",
            "type":"Services"
        }
    ],
    "sg:phone":"+61 8 9964 1355",
    "sg:postcode":"6530",
    "sg:province":"WA",
    "sg:tags":[
        "transmission",
        "automotive",
        "car"
    ],
    "wof:name":"Geraldton Transmissions & Diffs",
    "wof:placetype":"venue"
},
  "geometry": {"coordinates":[114.63407898,-28.7591743469],"type":"Point"}
}