{
  "type": "Feature",
  "properties": {
    "iso:country":"AU",
    "sg:address":"40 Lindsay St",
    "sg:city":"Burwood",
    "sg:classifiers":[
        {
            "category":"Health Services",
            "subcategory":"Doctor",
            "type":"Services"
        }
    ],
    "sg:phone":"+61 2 9747 4411",
    "sg:postcode":"2134",
    "sg:province":"NSW",
    "sg:tags":[
        "medical",
        "practitioner"
    ],
    "wof:name":"Weinman Darrel",
    "wof:placetype":"venue"
},
  "geometry": {"coordinates":[151.09765625,-33.8852233887],"type":"Point"}
}