{
  "type": "Feature",
  "properties": {
    "addr:full":"112 Burwood Rd Hawthorn VIC 3122",
    "addr:housenumber":"112",
    "addr:postcode":"3122",
    "addr:street":"Burwood Rd",
    "iso:country":"AU",
    "sg:address":"112 Burwood Rd",
    "sg:city":"Hawthorn",
    "sg:classifiers":[
        {
            "category":"Food & Beverages",
            "subcategory":"Bakery",
            "type":"Retail Goods"
        }
    ],
    "sg:phone":"+61 3 9818 4148",
    "sg:postcode":"3122",
    "sg:province":"VIC",
    "sg:tags":[
        "baker"
    ],
    "wof:name":"Hawthorn Hot Bread",
    "wof:placetype":"venue"
},
  "geometry": {"coordinates":[145.0259552,-37.8216171265],"type":"Point"}
}