{
  "type": "Feature",
  "properties": {
    "addr:full":"1 West St Lewisham NSW 2049",
    "addr:housenumber":"1",
    "addr:postcode":"2049",
    "addr:street":"West St",
    "iso:country":"AU",
    "sg:address":"1 West St",
    "sg:city":"Lewisham",
    "sg:classifiers":[
        {
            "category":"Health Services",
            "subcategory":"Health Practitioner",
            "type":"Services"
        }
    ],
    "sg:phone":"+61 2 9569 8399",
    "sg:postcode":"2049",
    "sg:province":"NSW",
    "sg:tags":[
        "physiotherapist"
    ],
    "wof:name":"Lewisham Sports Medicine Clinic-Physiotherapy",
    "wof:placetype":"venue"
},
  "geometry": {"coordinates":[151.15005500000001,-33.892433],"type":"Point"}
}