{
  "type": "Feature",
  "properties": {
    "addr:full":"2A Kane Rd Wodonga VIC 3690",
    "addr:housenumber":"2a",
    "addr:postcode":"3690",
    "addr:street":"Kane Rd",
    "iso:country":"AU",
    "sg:address":"2A Kane Rd",
    "sg:city":"Wodonga",
    "sg:classifiers":[
        {
            "category":"Wholesale",
            "subcategory":"Machinery & Supplies",
            "type":"Manufacturing & Wholesale Goods"
        }
    ],
    "sg:phone":"+61 418 324 887",
    "sg:postcode":"3690",
    "sg:province":"VIC",
    "sg:tags":[
        "equipment",
        "hydraulic"
    ],
    "wof:name":"Western Connections",
    "wof:placetype":"venue"
},
  "geometry": {"coordinates":[146.90097045900001,-36.1197509766],"type":"Point"}
}