{
  "type": "Feature",
  "properties": {
    "iso:country":"AU",
    "sg:address":"Shop 10/ 1 Brygon Creek Drv",
    "sg:city":"Upper Coomera",
    "sg:classifiers":[
        {
            "category":"Fast Food",
            "type":"Food & Drink"
        }
    ],
    "sg:phone":"+61 7 5519 9544",
    "sg:postcode":"4209",
    "sg:province":"QLD",
    "sg:tags":[
        "away",
        "take"
    ],
    "wof:name":"Brygon Take Aways",
    "wof:placetype":"venue"
},
  "geometry": {"coordinates":[153.29598999000001,-27.8698482513],"type":"Point"}
}