{
  "type": "Feature",
  "properties": {
    "addr:full":"Shop 156A Gladstone Park Shopping Centre Tullamarine VIC 3043",
    "addr:housenumber":"156a",
    "addr:postcode":"3043",
    "addr:street":"Gladstone",
    "iso:country":"AU",
    "sg:address":"Shop 156A Gladstone Park Shopping Centre",
    "sg:city":"Tullamarine",
    "sg:classifiers":[
        {
            "category":"Health Services",
            "subcategory":"Optometrist",
            "type":"Services"
        }
    ],
    "sg:phone":"+61 3 9338 2720",
    "sg:postcode":"3043",
    "sg:province":"VIC",
    "wof:name":"Andrew Fenwick",
    "wof:placetype":"venue"
},
  "geometry": {"coordinates":[144.86845398,-37.7137413025],"type":"Point"}
}