{
  "type": "Feature",
  "properties": {
    "addr:full":"58 Bulla Rd Bulla VIC 3428",
    "addr:postcode":"3428",
    "addr:street":"Bulla Rd",
    "iso:country":"AU",
    "sg:address":"58 Bulla Rd",
    "sg:city":"Bulla",
    "sg:classifiers":[
        {
            "category":"Building & Trades",
            "subcategory":"Construction",
            "type":"Services"
        }
    ],
    "sg:phone":"+61 3 9307 1482",
    "sg:postcode":"3428",
    "sg:province":"VIC",
    "sg:tags":[
        "fencing",
        "contractor"
    ],
    "wof:name":"B & B Fencing",
    "wof:placetype":"venue"
},
  "geometry": {"coordinates":[144.808395386,-37.6385765076],"type":"Point"}
}