{
  "type": "Feature",
  "properties": {
    "addr:full":"Kiosk 1 , Stocklands Shopping Centre, 1 Molly Morgan NSW 2323",
    "addr:housenumber":"1",
    "addr:postcode":"2323",
    "addr:street":"Molly Morgan",
    "iso:country":"AU",
    "sg:address":"Kiosk 1",
    "sg:city":", Stocklands Shopping Centre, 1 Molly Morgan",
    "sg:classifiers":[
        {
            "category":"Shopping",
            "subcategory":"Mobile Phones",
            "type":"Retail Goods"
        }
    ],
    "sg:phone":"+61 2 4933 0515",
    "sg:postcode":"2323",
    "sg:province":"NSW",
    "sg:tags":[
        "telephone",
        "accessory"
    ],
    "wof:name":"Allphones",
    "wof:placetype":"venue"
},
  "geometry": {"coordinates":[151.59274292000001,-32.7606735229],"type":"Point"}
}