{
  "type": "Feature",
  "properties": {
    "iso:country":"AU",
    "sg:address":"4 Brook St",
    "sg:city":"Kingsley",
    "sg:classifiers":[
        {
            "category":"Building & Trades",
            "subcategory":"Construction",
            "type":"Services"
        }
    ],
    "sg:phone":"+61 417 094 668",
    "sg:postcode":"6026",
    "sg:province":"WA",
    "sg:tags":[
        "installation",
        "air conditioning"
    ],
    "wof:name":"Aircond Installs WA",
    "wof:placetype":"venue"
},
  "geometry": {"coordinates":[115.80539703399999,-31.806388855],"type":"Point"}
}