{
  "type": "Feature",
  "properties": {
    "addr:full":"Cnr Station St & Thames Pde Chelsea VIC 3196",
    "addr:postcode":"3196",
    "addr:street":"Cnr Station St & Thames Pde",
    "iso:country":"AU",
    "sg:address":"Cnr Station St & Thames Pde",
    "sg:city":"Chelsea",
    "sg:classifiers":[
        {
            "category":"Social Services",
            "subcategory":"Child Care",
            "type":"Services"
        }
    ],
    "sg:phone":"+61 3 9772 1680",
    "sg:postcode":"3196",
    "sg:province":"VIC",
    "sg:tags":[
        "support",
        "health"
    ],
    "wof:name":"Maternal & Child Health Centres",
    "wof:placetype":"venue"
},
  "geometry": {"coordinates":[145.11451721200001,-38.0482597351],"type":"Point"}
}