{
  "type": "Feature",
  "properties": {
    "addr:full":"494 Brunswick St Fitzroy VIC 3065",
    "addr:housenumber":"494",
    "addr:postcode":"3065",
    "addr:street":"Brunswick St",
    "iso:country":"AU",
    "sg:address":"494 Brunswick St",
    "sg:city":"Fitzroy",
    "sg:classifiers":[
        {
            "category":"Education",
            "subcategory":"University",
            "type":"Public Place"
        }
    ],
    "sg:phone":"+61 3 9489 4344",
    "sg:postcode":"3065",
    "sg:province":"VIC",
    "sg:tags":[
        "educational",
        "organisation",
        "cultural"
    ],
    "wof:name":"Specific Learning Difficulties Association Of Victoria",
    "wof:placetype":"venue"
},
  "geometry": {"coordinates":[144.97677612300001,-37.8035812378],"type":"Point"}
}