{
  "type": "Feature",
  "properties": {
    "addr:full":"Ste G 08, Ground Floor, St Kilda Rd Melbourne VIC 3000",
    "addr:postcode":"3000",
    "addr:street":"St Kilda Rd",
    "iso:country":"AU",
    "sg:address":"Ste G 08, Ground Floor, St Kilda Rd",
    "sg:city":"Melbourne",
    "sg:classifiers":[
        {
            "category":"Travel",
            "subcategory":"Travel Agent",
            "type":"Entertainment"
        }
    ],
    "sg:phone":"+61 3 9510 1777",
    "sg:postcode":"3000",
    "sg:province":"VIC",
    "sg:tags":[
        "consultant"
    ],
    "wof:name":"Vision Tours",
    "wof:placetype":"venue"
},
  "geometry": {"coordinates":[144.96751403799999,-37.8176269531],"type":"Point"}
}