{
  "type": "Feature",
  "properties": {
    "addr:full":"123 Mitchell Rd Alexandria NSW 2015",
    "addr:housenumber":"123",
    "addr:postcode":"2015",
    "addr:street":"Mitchell Rd",
    "iso:country":"AU",
    "sg:address":"123 Mitchell Rd",
    "sg:city":"Alexandria",
    "sg:classifiers":[
        {
            "category":"Professional",
            "subcategory":"Art Services",
            "type":"Services"
        }
    ],
    "sg:phone":"+61 2 9550 4777",
    "sg:postcode":"2015",
    "sg:province":"NSW",
    "sg:tags":[
        "interior",
        "designer"
    ],
    "wof:name":"Positive Space Planning Pty Ltd",
    "wof:placetype":"venue"
},
  "geometry": {"coordinates":[151.192596436,-33.9013328552],"type":"Point"}
}