{
  "type": "Feature",
  "properties": {
    "addr:full":"6/ 188 Keilor Park Drv Tullamarine VIC 3043",
    "addr:housenumber":"/ 188",
    "addr:postcode":"3043",
    "addr:street":"Keilor Park Drv",
    "iso:country":"AU",
    "sg:address":"6/ 188 Keilor Park Drv",
    "sg:city":"Tullamarine",
    "sg:classifiers":[
        {
            "category":"Home & Garden",
            "subcategory":"Hardware",
            "type":"Retail Goods"
        }
    ],
    "sg:phone":"+61 3 9330 1007",
    "sg:postcode":"3043",
    "sg:province":"VIC",
    "sg:tags":[
        "nut",
        "bolt"
    ],
    "wof:name":"Exhausts-Motor Cycle",
    "wof:placetype":"venue"
},
  "geometry": {"coordinates":[144.86007690400001,-37.7080078125],"type":"Point"}
}