{
  "type": "Feature",
  "properties": {
    "addr:full":"23 Currawong Ave Lane Cove NSW 2066",
    "addr:housenumber":"23",
    "addr:postcode":"2066",
    "addr:street":"Currawong Ave",
    "iso:country":"AU",
    "sg:address":"23 Currawong Ave",
    "sg:city":"Lane Cove",
    "sg:classifiers":[
        {
            "category":"Professional",
            "subcategory":"Detective & Security Services",
            "type":"Services"
        }
    ],
    "sg:phone":"+61 405 395 195",
    "sg:postcode":"2066",
    "sg:province":"NSW",
    "sg:tags":[
        "seal"
    ],
    "wof:name":"Safepak",
    "wof:placetype":"venue"
},
  "geometry": {"coordinates":[151.15304565400001,-33.8133239746],"type":"Point"}
}