{
  "type": "Feature",
  "properties": {
    "addr:full":"87 Canterbury Rd Canterbury VIC 3126",
    "addr:housenumber":"87",
    "addr:postcode":"3126",
    "addr:street":"Canterbury Rd",
    "iso:country":"AU",
    "sg:address":"87 Canterbury Rd",
    "sg:city":"Canterbury",
    "sg:classifiers":[
        {
            "category":"Personal",
            "subcategory":"Beauty Salon",
            "type":"Services"
        }
    ],
    "sg:phone":"+61 3 9836 7760",
    "sg:postcode":"3126",
    "sg:province":"VIC",
    "wof:name":"Natskin Beauty Therapy",
    "wof:placetype":"venue"
},
  "geometry": {"coordinates":[145.070587158,-37.8226737976],"type":"Point"}
}