{
  "type": "Feature",
  "properties": {
    "addr:full":"Amaroo St Reid ACT 2612",
    "addr:postcode":"2612",
    "addr:street":"Amaroo St",
    "iso:country":"AU",
    "sg:address":"Amaroo St",
    "sg:city":"Reid",
    "sg:classifiers":[
        {
            "category":"Education",
            "subcategory":"Kindergarten",
            "type":"Public Place"
        }
    ],
    "sg:phone":"+61 2 6230 5660",
    "sg:postcode":"2612",
    "sg:province":"ACT",
    "sg:tags":[
        "pre-schools"
    ],
    "wof:name":"Reid Early Childhood Centre",
    "wof:placetype":"venue"
},
  "geometry": {"coordinates":[149.13656616200001,-35.2864952087],"type":"Point"}
}