{
  "type": "Feature",
  "properties": {
    "addr:full":"52 Old Forest Rd The Basin VIC 3154",
    "addr:housenumber":"52",
    "addr:postcode":"3154",
    "addr:street":"Old Forest Rd",
    "iso:country":"AU",
    "sg:address":"52 Old Forest Rd",
    "sg:city":"The Basin",
    "sg:classifiers":[
        {
            "category":"Building & Trades",
            "subcategory":"Construction",
            "type":"Services"
        }
    ],
    "sg:phone":"+61 3 9762 8439",
    "sg:postcode":"3154",
    "sg:province":"VIC",
    "sg:tags":[
        "earth",
        "excavating",
        "moving",
        "contractor"
    ],
    "wof:name":"Hillside Cartage And Bobcat Hire",
    "wof:placetype":"venue"
},
  "geometry": {"coordinates":[145.31655883799999,-37.8603858948],"type":"Point"}
}