{
  "type": "Feature",
  "properties": {
    "addr:full":"28 Whiteman Crt Bertram WA 6167",
    "addr:housenumber":"28",
    "addr:postcode":"6167",
    "addr:street":"Whiteman Crt",
    "iso:country":"AU",
    "sg:address":"28 Whiteman Crt",
    "sg:city":"Bertram",
    "sg:classifiers":[
        {
            "category":"Communications",
            "subcategory":"Film & Video Production",
            "type":"Services"
        }
    ],
    "sg:phone":"+61 8 9480 5266",
    "sg:postcode":"6167",
    "sg:province":"WA",
    "sg:tags":[
        "fan",
        "blower"
    ],
    "wof:name":"Choice One Electrical",
    "wof:placetype":"venue"
},
  "geometry": {"coordinates":[115.849571,-32.246292],"type":"Point"}
}