{
  "type": "Feature",
  "properties": {
    "iso:country":"AU",
    "sg:address":"54 Koola Drv",
    "sg:city":"Nerang",
    "sg:classifiers":[
        {
            "category":"Home & Garden",
            "subcategory":"Building Materials",
            "type":"Retail Goods"
        }
    ],
    "sg:phone":"+61 7 5596 3269",
    "sg:postcode":"4211",
    "sg:province":"QLD",
    "sg:tags":[
        "concrete",
        "gutter",
        "kerb"
    ],
    "wof:name":"Queensland Kerb & Channel Pty Ltd",
    "wof:placetype":"venue"
},
  "geometry": {"coordinates":[153.30934143100001,-27.9993572235],"type":"Point"}
}