{
  "type": "Feature",
  "properties": {
    "addr:full":"1158 Burwood Hwy Upper Ferntree Gully VIC 3156",
    "addr:housenumber":"1158",
    "addr:postcode":"3156",
    "addr:street":"Burwood Hwy",
    "iso:country":"AU",
    "sg:address":"1158 Burwood Hwy",
    "sg:city":"Upper Ferntree Gully",
    "sg:classifiers":[
        {
            "category":"Retail",
            "subcategory":"Auto Repair",
            "type":"Services"
        }
    ],
    "sg:phone":"+61 3 9758 9288",
    "sg:postcode":"3156",
    "sg:province":"VIC",
    "sg:tags":[
        "wheel",
        "balancing",
        "alignment"
    ],
    "wof:name":"Peter Puplett's Widetread Tyre Stores",
    "wof:placetype":"venue"
},
  "geometry": {"coordinates":[145.30307006800001,-37.8919677734],"type":"Point"}
}