{
  "type": "Feature",
  "properties": {
    "iso:country":"AU",
    "sg:address":"744 Canterbury Rd",
    "sg:city":"Belmore",
    "sg:classifiers":[
        {
            "category":"Retail",
            "subcategory":"Car Wash",
            "type":"Services"
        }
    ],
    "sg:phone":"+61 2 9740 5888",
    "sg:postcode":"2192",
    "sg:province":"NSW",
    "sg:tags":[
        "auction",
        "motor"
    ],
    "wof:name":"The Motor Auction Belmore",
    "wof:placetype":"venue"
},
  "geometry": {"coordinates":[151.089966,-33.924637],"type":"Point"}
}