{
  "type": "Feature",
  "properties": {
    "iso:country":"AU",
    "sg:address":"Midland Hwy",
    "sg:city":"Stanhope",
    "sg:classifiers":[
        {
            "category":"Education",
            "subcategory":"School",
            "type":"Public Place"
        }
    ],
    "sg:phone":"+61 3 5857 2514",
    "sg:postcode":"3623",
    "sg:province":"VIC",
    "sg:tags":[
        "state",
        "except",
        "nsw"
    ],
    "wof:name":"Stanhope Primary School",
    "wof:placetype":"venue"
},
  "geometry": {"coordinates":[144.98629760700001,-36.4471855164],"type":"Point"}
}