{
  "type": "Feature",
  "properties": {
    "addr:full":"17 Victoria Crs St Albans VIC 3021",
    "addr:housenumber":"17",
    "addr:postcode":"3021",
    "addr:street":"Victoria Crs",
    "iso:country":"AU",
    "sg:address":"17 Victoria Crs",
    "sg:city":"St Albans",
    "sg:classifiers":[
        {
            "category":"Health Services",
            "subcategory":"Doctor",
            "type":"Services"
        }
    ],
    "sg:phone":"+61 3 9364 2963",
    "sg:postcode":"3021",
    "sg:province":"VIC",
    "sg:tags":[
        "medical",
        "practitioner"
    ],
    "wof:name":"Sheriff A A Dr",
    "wof:placetype":"venue"
},
  "geometry": {"coordinates":[144.800217,-37.744259],"type":"Point"}
}