{
  "type": "Feature",
  "properties": {
    "addr:full":"98 Park Rd Kogarah Bay NSW 2217",
    "addr:housenumber":"98",
    "addr:postcode":"2217",
    "addr:street":"Park Rd",
    "iso:country":"AU",
    "sg:address":"98 Park Rd",
    "sg:city":"Kogarah Bay",
    "sg:classifiers":[
        {
            "category":"Home & Garden",
            "subcategory":"Furniture",
            "type":"Retail Goods"
        }
    ],
    "sg:phone":"+61 418 281 521",
    "sg:postcode":"2217",
    "sg:province":"NSW",
    "sg:tags":[
        "business"
    ],
    "wof:name":"Leather Care",
    "wof:placetype":"venue"
},
  "geometry": {"coordinates":[151.12582399999999,-33.981483],"type":"Point"}
}