{
  "type": "Feature",
  "properties": {
    "iso:country":"AU",
    "sg:address":"43 Gulfview Rd",
    "sg:city":"Christies Beach",
    "sg:classifiers":[
        {
            "category":"Sports & Exercise",
            "subcategory":"Gym",
            "type":"Entertainment"
        }
    ],
    "sg:phone":"+61 8 8384 7115",
    "sg:postcode":"5165",
    "sg:province":"SA",
    "sg:tags":[
        "health",
        "fitness"
    ],
    "wof:name":"Impact Health Club",
    "wof:placetype":"venue"
},
  "geometry": {"coordinates":[138.47615051299999,-35.1310501099],"type":"Point"}
}