{
  "type": "Feature",
  "properties": {
    "addr:full":"Suite 25 200 Terminus St Castle Hill NSW 2154",
    "addr:housenumber":"200",
    "addr:postcode":"2154",
    "addr:street":"Terminus St",
    "iso:country":"AU",
    "sg:address":"Suite 25 200 Terminus St",
    "sg:city":"Castle Hill",
    "sg:classifiers":[
        {
            "category":"Professional",
            "subcategory":"Computer Services",
            "type":"Services"
        }
    ],
    "sg:phone":"+61 2 8850 6655",
    "sg:postcode":"2154",
    "sg:province":"NSW",
    "sg:tags":[
        "repairs",
        "upgrade",
        "equipment"
    ],
    "wof:name":"Lightning I.T.",
    "wof:placetype":"venue"
},
  "geometry": {"coordinates":[151.005462647,-33.7345275879],"type":"Point"}
}