{
  "type": "Feature",
  "properties": {
    "iso:country":"AU",
    "sg:address":"21 Barry Drv",
    "sg:city":"Turner",
    "sg:classifiers":[
        {
            "category":"Professional",
            "subcategory":"Computer Services",
            "type":"Services"
        }
    ],
    "sg:phone":"+61 2 6248 9244",
    "sg:postcode":"2612",
    "sg:province":"ACT",
    "sg:tags":[
        "package",
        "software"
    ],
    "wof:name":"Data General Aust Pty Ltd",
    "wof:placetype":"venue"
},
  "geometry": {"coordinates":[149.12597656200001,-35.275138855],"type":"Point"}
}