{
  "type": "Feature",
  "properties": {
    "iso:country":"AU",
    "sg:address":"58 Prentis La",
    "sg:city":"Ebenezer",
    "sg:classifiers":[
        {
            "category":"Home & Garden",
            "subcategory":"Building Materials",
            "type":"Retail Goods"
        }
    ],
    "sg:phone":"+61 2 4579 9545",
    "sg:postcode":"2756",
    "sg:province":"NSW",
    "sg:tags":[
        "lawn",
        "cutting",
        "maintenance"
    ],
    "wof:name":"Thats One Property Maintenance",
    "wof:placetype":"venue"
},
  "geometry": {"coordinates":[150.88548278799999,-33.5227279663],"type":"Point"}
}