{
  "type": "Feature",
  "properties": {
    "addr:full":"1st Floor Market St Store, Market St Sydney NSW 2000",
    "addr:postcode":"2000",
    "addr:street":"St;Market St",
    "iso:country":"AU",
    "sg:address":"1st Floor Market St Store, Market St",
    "sg:city":"Sydney",
    "sg:classifiers":[
        {
            "category":"Personal",
            "subcategory":"Beauty Salon",
            "type":"Services"
        }
    ],
    "sg:phone":"+61 2 9266 5264",
    "sg:postcode":"2000",
    "sg:province":"NSW",
    "sg:tags":[
        "hairdresser"
    ],
    "wof:name":"David Jones Mens Hair Salon",
    "wof:placetype":"venue"
},
  "geometry": {"coordinates":[151.210113525,-33.870716095],"type":"Point"}
}