{
  "type": "Feature",
  "properties": {
    "addr:full":"Clinicare, 226 St George's Rd Fitzroy North VIC 3068",
    "addr:housenumber":"226",
    "addr:postcode":"3068",
    "addr:street":"Clinicare;St George'S Rd",
    "iso:country":"AU",
    "sg:address":"Clinicare, 226 St George's Rd",
    "sg:city":"Fitzroy North",
    "sg:classifiers":[
        {
            "category":"Health Services",
            "subcategory":"Health Practitioner",
            "type":"Services"
        }
    ],
    "sg:phone":"+61 3 9482 3344",
    "sg:postcode":"3068",
    "sg:province":"VIC",
    "sg:tags":[
        "naturopath"
    ],
    "wof:name":"Van Die Diana",
    "wof:placetype":"venue"
},
  "geometry": {"coordinates":[144.99270629899999,-37.7773857117],"type":"Point"}
}