{
  "type": "Feature",
  "properties": {
    "addr:full":"PO Box 4271 Hoppers Crossing VIC 3029",
    "addr:postcode":"3029",
    "iso:country":"AU",
    "sg:address":"PO Box 4271",
    "sg:city":"Hoppers Crossing",
    "sg:classifiers":[
        {
            "category":"Sports & Exercise",
            "subcategory":"Gym",
            "type":"Entertainment"
        }
    ],
    "sg:phone":"+61 414 966 749",
    "sg:postcode":"3029",
    "sg:province":"VIC",
    "sg:tags":[
        "personal",
        "trainer",
        "fitness"
    ],
    "wof:name":"Fit2Go",
    "wof:placetype":"venue"
},
  "geometry": {"coordinates":[144.703934,-37.864319],"type":"Point"}
}