{
  "type": "Feature",
  "properties": {
    "addr:full":"Cnr Anchorage Drv & Marmion Ave Mindarie WA 6030",
    "addr:postcode":"6030",
    "addr:street":"Cnr Anchorage Drv & Marmion Ave",
    "iso:country":"AU",
    "sg:address":"Cnr Anchorage Drv & Marmion Ave",
    "sg:city":"Mindarie",
    "sg:classifiers":[
        {
            "category":"Autos & Motor Vehicles",
            "subcategory":"Fuel & Gas Station",
            "type":"Retail Goods"
        }
    ],
    "sg:phone":"+61 8 9305 8995",
    "sg:postcode":"6030",
    "sg:province":"WA",
    "wof:name":"Quick Stop Fuel",
    "wof:placetype":"venue"
},
  "geometry": {"coordinates":[115.71449279799999,-31.6825084686],"type":"Point"}
}