{
  "type": "Feature",
  "properties": {
    "addr:full":"146 Bell St Preston VIC 3072",
    "addr:housenumber":"146",
    "addr:postcode":"3072",
    "addr:street":"Bell St",
    "iso:country":"AU",
    "sg:address":"146 Bell St",
    "sg:city":"Preston",
    "sg:classifiers":[
        {
            "category":"Home & Garden",
            "subcategory":"Furniture",
            "type":"Retail Goods"
        }
    ],
    "sg:phone":"+61 3 9416 9100",
    "sg:postcode":"3072",
    "sg:province":"VIC",
    "sg:tags":[
        "business"
    ],
    "wof:name":"Office Furniture Direct",
    "wof:placetype":"venue"
},
  "geometry": {"coordinates":[145.01939392099999,-37.7468109131],"type":"Point"}
}