{
  "type": "Feature",
  "properties": {
    "addr:full":"28 Saggart Field Rd Minto NSW 2566",
    "addr:housenumber":"28",
    "addr:postcode":"2566",
    "addr:street":"Saggart Field Rd",
    "iso:country":"AU",
    "sg:address":"28 Saggart Field Rd",
    "sg:city":"Minto",
    "sg:classifiers":[
        {
            "category":"Manufacturing",
            "subcategory":"Metals",
            "type":"Manufacturing & Wholesale Goods"
        }
    ],
    "sg:phone":"+61 2 9603 6486",
    "sg:postcode":"2566",
    "sg:province":"NSW",
    "sg:tags":[
        "wholesaler",
        "aluminium",
        "mfrs"
    ],
    "wof:name":"Calm Aluminium Pty Ltd",
    "wof:placetype":"venue"
},
  "geometry": {"coordinates":[150.84375,-34.0371437073],"type":"Point"}
}