{
  "type": "Feature",
  "properties": {
    "iso:country":"AU",
    "sg:address":"Unit 4C, 1-7 Unwins Bridge Rd St",
    "sg:city":"Peters",
    "sg:classifiers":[
        {
            "category":"Military Area",
            "subcategory":"Air Force Base",
            "type":"Public Place"
        }
    ],
    "sg:phone":"+61 2 9519 3325",
    "sg:postcode":"2044",
    "sg:province":"NSW",
    "sg:tags":[
        "equipment",
        "climbing",
        "venue",
        "rock"
    ],
    "wof:name":"Sydney Indoor Climbing Gym",
    "wof:placetype":"venue"
},
  "geometry": {"coordinates":[151.174927,-33.910362],"type":"Point"}
}