{
  "type": "Feature",
  "properties": {
    "addr:full":"26 Hall St Bondi Beach NSW 2026",
    "addr:housenumber":"26",
    "addr:postcode":"2026",
    "addr:street":"Hall St",
    "iso:country":"AU",
    "sg:address":"26 Hall St",
    "sg:city":"Bondi Beach",
    "sg:classifiers":[
        {
            "category":"Banks & Credit Unions",
            "subcategory":"Bank",
            "type":"Services"
        }
    ],
    "sg:phone":"+61 13 20 32",
    "sg:postcode":"2026",
    "sg:province":"NSW",
    "wof:name":"Westpac",
    "wof:placetype":"venue"
},
  "geometry": {"coordinates":[151.272705078,-33.8905830383],"type":"Point"}
}