{
  "type": "Feature",
  "properties": {
    "addr:full":"36 Fourth Rd Armadale WA 6112",
    "addr:housenumber":"36",
    "addr:postcode":"6112",
    "addr:street":"Fourth Rd",
    "iso:country":"AU",
    "sg:address":"36 Fourth Rd",
    "sg:city":"Armadale",
    "sg:classifiers":[
        {
            "category":"Personal",
            "subcategory":"Beauty Salon",
            "type":"Services"
        }
    ],
    "sg:phone":"+61 8 9399 4084",
    "sg:postcode":"6112",
    "sg:province":"WA",
    "sg:tags":[
        "hairdresser"
    ],
    "wof:name":"Hair By Us",
    "wof:placetype":"venue"
},
  "geometry": {"coordinates":[116.014976502,-32.1551933289],"type":"Point"}
}