{
  "type": "Feature",
  "properties": {
    "iso:country":"AU",
    "sg:address":"South Shore Piazza Shp4/ 85 Mends St",
    "sg:city":"South Perth",
    "sg:classifiers":[
        {
            "category":"Shopping",
            "subcategory":"Clothing, Apparel, & Fashions",
            "type":"Retail Goods"
        }
    ],
    "sg:phone":"+61 8 9368 2360",
    "sg:postcode":"6151",
    "sg:province":"WA",
    "sg:tags":[
        "menswear"
    ],
    "wof:name":"Men On Mends",
    "wof:placetype":"venue"
},
  "geometry": {"coordinates":[115.852623,-31.972372],"type":"Point"}
}