{
  "type": "Feature",
  "properties": {
    "addr:full":"69 Stansfield St Hughenden QLD 4821",
    "addr:housenumber":"69",
    "addr:postcode":"4821",
    "addr:street":"Stansfield St",
    "iso:country":"AU",
    "sg:address":"69 Stansfield St",
    "sg:city":"Hughenden",
    "sg:classifiers":[
        {
            "category":"Professional",
            "subcategory":"Art Services",
            "type":"Services"
        }
    ],
    "sg:phone":"+61 7 4741 0295",
    "sg:postcode":"4821",
    "sg:province":"QLD",
    "sg:tags":[
        "decorator",
        "painter"
    ],
    "wof:name":"Lance Millwood Painting",
    "wof:placetype":"venue"
},
  "geometry": {"coordinates":[144.19546508799999,-20.8427619934],"type":"Point"}
}