{
  "type": "Feature",
  "properties": {
    "iso:country":"AU",
    "sg:address":"24 Eastern Rd",
    "sg:city":"South Melbourne",
    "sg:classifiers":[
        {
            "category":"Organizations",
            "subcategory":"Professional Association",
            "type":"Services"
        }
    ],
    "sg:phone":"+61 3 9682 2388",
    "sg:postcode":"3205",
    "sg:province":"VIC",
    "sg:tags":[
        "web",
        "internet"
    ],
    "wof:name":"RUCC Pty Ltd",
    "wof:placetype":"venue"
},
  "geometry": {"coordinates":[144.96481299999999,-37.831905],"type":"Point"}
}