{
  "type": "Feature",
  "properties": {
    "addr:full":"Oakover Rd Preston VIC 3072",
    "addr:postcode":"3072",
    "addr:street":"Oakover Rd",
    "iso:country":"AU",
    "sg:address":"Oakover Rd",
    "sg:city":"Preston",
    "sg:classifiers":[
        {
            "category":"Education",
            "subcategory":"School",
            "type":"Public Place"
        }
    ],
    "sg:phone":"+61 3 9480 5622",
    "sg:postcode":"3072",
    "sg:province":"VIC",
    "sg:tags":[
        "state",
        "except",
        "nsw"
    ],
    "wof:name":"Bell Primary",
    "wof:placetype":"venue"
},
  "geometry": {"coordinates":[145.000900269,-37.7498245239],"type":"Point"}
}