{
  "type": "Feature",
  "properties": {
    "iso:country":"AU",
    "sg:address":"PO Box 5020",
    "sg:city":"Falcon",
    "sg:classifiers":[
        {
            "category":"Communications",
            "subcategory":"News Services",
            "type":"Services"
        }
    ],
    "sg:phone":"+61 8 9582 1570",
    "sg:postcode":"6210",
    "sg:province":"WA",
    "sg:tags":[
        "information",
        "tourist",
        "attractions"
    ],
    "wof:name":"Tagalong Australia",
    "wof:placetype":"venue"
},
  "geometry": {"coordinates":[115.662193,-32.581299],"type":"Point"}
}