{
  "type": "Feature",
  "properties": {
    "iso:country":"AU",
    "sg:address":"849 Glasshouse Rocks Rd",
    "sg:city":"Narooma",
    "sg:classifiers":[
        {
            "category":"Social Services",
            "subcategory":"Adult Care",
            "type":"Services"
        }
    ],
    "sg:phone":"+61 2 4476 4403",
    "sg:postcode":"2546",
    "sg:province":"NSW",
    "sg:tags":[
        "towing"
    ],
    "wof:name":"Garry Bennett Smash Repairs",
    "wof:placetype":"venue"
},
  "geometry": {"coordinates":[150.12571716299999,-36.2309379578],"type":"Point"}
}