{
  "type": "Feature",
  "properties": {
    "iso:country":"AU",
    "sg:address":"379 Birralee Rd",
    "sg:city":"Westbury",
    "sg:classifiers":[
        {
            "category":"Farming",
            "subcategory":"Livestock Farm",
            "type":"Manufacturing & Wholesale Goods"
        }
    ],
    "sg:phone":"+61 3 6393 1193",
    "sg:postcode":"7303",
    "sg:province":"TAS",
    "sg:tags":[
        "breeder",
        "horse",
        "stud"
    ],
    "wof:name":"Park Crest Thoroughbred Stud",
    "wof:placetype":"venue"
},
  "geometry": {"coordinates":[146.816666,-41.493736],"type":"Point"}
}