{
  "type": "Feature",
  "properties": {
    "iso:country":"AU",
    "sg:address":"34 Renee Crs",
    "sg:city":"Moruya Heads",
    "sg:classifiers":[
        {
            "category":"Building & Trades",
            "subcategory":"Construction",
            "type":"Services"
        }
    ],
    "sg:phone":"+61 414 389 478",
    "sg:postcode":"2537",
    "sg:province":"NSW",
    "sg:tags":[
        "joiner",
        "carpenter"
    ],
    "wof:name":"Andrew Badullovich",
    "wof:placetype":"venue"
},
  "geometry": {"coordinates":[150.15504455600001,-35.9125289917],"type":"Point"}
}