{
  "type": "Feature",
  "properties": {
    "iso:country":"AU",
    "sg:address":"31 North East Rd",
    "sg:city":"Collinswood",
    "sg:classifiers":[
        {
            "category":"Personal",
            "subcategory":"Beauty Salon",
            "type":"Services"
        }
    ],
    "sg:phone":"+61 8 8344 9733",
    "sg:postcode":"5081",
    "sg:province":"SA",
    "sg:tags":[
        "hairdresser"
    ],
    "wof:name":"Gentiles Hair & Beauty",
    "wof:placetype":"venue"
},
  "geometry": {"coordinates":[138.61541748100001,-34.8879241943],"type":"Point"}
}