{
  "type": "Feature",
  "properties": {
    "addr:full":"Suite 4, 5-7 Ross St Parramatta NSW 2151",
    "addr:housenumber":"5-7",
    "addr:postcode":"2151",
    "addr:street":"Ross St",
    "iso:country":"AU",
    "sg:address":"Suite 4, 5-7 Ross St",
    "sg:city":"Parramatta",
    "sg:classifiers":[
        {
            "category":"Health Services",
            "subcategory":"Dentist",
            "type":"Services"
        }
    ],
    "sg:phone":"+61 2 9630 1073",
    "sg:postcode":"2151",
    "sg:province":"NSW",
    "wof:name":"Dou ,Nancy Dentist",
    "wof:placetype":"venue"
},
  "geometry": {"coordinates":[151.00454711899999,-33.8076553345],"type":"Point"}
}