{
  "type": "Feature",
  "properties": {
    "iso:country":"AU",
    "sg:address":"PO Box 505",
    "sg:city":"X Leumeah",
    "sg:classifiers":[
        {
            "category":"Health Services",
            "subcategory":"Health Practitioner",
            "type":"Services"
        }
    ],
    "sg:phone":"+61 417 224 356",
    "sg:postcode":"2560",
    "sg:province":"NSW",
    "sg:tags":[
        "psychologist"
    ],
    "wof:name":"Solution Focused Psychological Services-Katarina Drazumeric",
    "wof:placetype":"venue"
},
  "geometry": {"coordinates":[150.83424377399999,-34.0516700745],"type":"Point"}
}