{
  "type": "Feature",
  "properties": {
    "addr:full":"10 Industrial Drv Somerville VIC 3912",
    "addr:housenumber":"10",
    "addr:postcode":"3912",
    "addr:street":"Industrial Drv",
    "iso:country":"AU",
    "sg:address":"10 Industrial Drv",
    "sg:city":"Somerville",
    "sg:classifiers":[
        {
            "category":"Wholesale",
            "subcategory":"Auto Parts",
            "type":"Manufacturing & Wholesale Goods"
        }
    ],
    "sg:phone":"+61 3 5977 7455",
    "sg:postcode":"3912",
    "sg:province":"VIC",
    "sg:tags":[
        "recyclers"
    ],
    "wof:name":"Somerville 4.W.D. Wreckers Pty Ltd",
    "wof:placetype":"venue"
},
  "geometry": {"coordinates":[145.180343628,-38.2197799683],"type":"Point"}
}