{
  "type": "Feature",
  "properties": {
    "addr:full":"203 Ingles St Port Melbourne VIC 3207",
    "addr:housenumber":"203",
    "addr:postcode":"3207",
    "addr:street":"Ingles St",
    "iso:country":"AU",
    "sg:address":"203 Ingles St",
    "sg:city":"Port Melbourne",
    "sg:classifiers":[
        {
            "category":"Autos & Motor Vehicles",
            "subcategory":"Automobile Sales",
            "type":"Retail Goods"
        }
    ],
    "sg:phone":"+61 3 9673 3399",
    "sg:postcode":"3207",
    "sg:province":"VIC",
    "sg:tags":[
        "car",
        "used"
    ],
    "wof:name":"First Auto Wholesalers",
    "wof:placetype":"venue"
},
  "geometry": {"coordinates":[144.94348099999999,-37.830711],"type":"Point"}
}