{
  "type": "Feature",
  "properties": {
    "addr:full":"129- 133 Military Rd Neutral Bay NSW 2089",
    "addr:housenumber":"133",
    "addr:postcode":"2089",
    "addr:street":"Military Rd",
    "iso:country":"AU",
    "sg:address":"129- 133 Military Rd",
    "sg:city":"Neutral Bay",
    "sg:classifiers":[
        {
            "category":"Communications",
            "subcategory":"Film & Video Production",
            "type":"Services"
        }
    ],
    "sg:phone":"+61 2 9953 2700",
    "sg:postcode":"2089",
    "sg:province":"NSW",
    "sg:tags":[
        "buyer",
        "refiner",
        "gold"
    ],
    "wof:name":"Happy Hockers",
    "wof:placetype":"venue"
},
  "geometry": {"coordinates":[151.22102355999999,-33.8311462402],"type":"Point"}
}