{
  "type": "Feature",
  "properties": {
    "iso:country":"AU",
    "sg:address":"Shop 3/ 11 Maine Rd",
    "sg:city":"Clontarf",
    "sg:classifiers":[
        {
            "category":"Personal",
            "subcategory":"Beauty Salon",
            "type":"Services"
        }
    ],
    "sg:phone":"+61 7 3284 4319",
    "sg:postcode":"4019",
    "sg:province":"QLD",
    "sg:tags":[
        "hairdresser"
    ],
    "wof:name":"Trimbles Hair & Beauty",
    "wof:placetype":"venue"
},
  "geometry": {"coordinates":[153.08906555199999,-27.2556419373],"type":"Point"}
}