{
  "type": "Feature",
  "properties": {
    "addr:full":"204 Great Eastern Hwy Midland WA 6056",
    "addr:housenumber":"204",
    "addr:postcode":"6056",
    "addr:street":"Great Eastern Hwy",
    "iso:country":"AU",
    "sg:address":"204 Great Eastern Hwy",
    "sg:city":"Midland",
    "sg:classifiers":[
        {
            "category":"Retail",
            "subcategory":"Auto Repair",
            "type":"Services"
        }
    ],
    "sg:phone":"+61 8 6274 0000",
    "sg:postcode":"6056",
    "sg:province":"WA",
    "sg:tags":[
        "repairer",
        "motor",
        "engineer"
    ],
    "wof:name":"Metro Mitsubishi",
    "wof:placetype":"venue"
},
  "geometry": {"coordinates":[116.00991821300001,-31.8910274506],"type":"Point"}
}