{
  "type": "Feature",
  "properties": {
    "addr:full":"35 Graceburn Ave Healesville VIC 3777",
    "addr:housenumber":"35",
    "addr:postcode":"3777",
    "addr:street":"Graceburn Ave",
    "iso:country":"AU",
    "sg:address":"35 Graceburn Ave",
    "sg:city":"Healesville",
    "sg:classifiers":[
        {
            "category":"Manufacturing",
            "subcategory":"Furniture",
            "type":"Manufacturing & Wholesale Goods"
        }
    ],
    "sg:phone":"+61 438 558 388",
    "sg:postcode":"3777",
    "sg:province":"VIC",
    "sg:tags":[
        "builder",
        "designer",
        "custom"
    ],
    "wof:name":"Nudibranch Design",
    "wof:placetype":"venue"
},
  "geometry": {"coordinates":[145.540436,-37.648964],"type":"Point"}
}