{
  "type": "Feature",
  "properties": {
    "iso:country":"AU",
    "sg:address":"339 High Rd",
    "sg:city":"Parkwood",
    "sg:classifiers":[
        {
            "category":"Food & Beverages",
            "subcategory":"Specialty",
            "type":"Retail Goods"
        }
    ],
    "sg:phone":"+61 8 9354 1969",
    "sg:postcode":"6147",
    "sg:province":"WA",
    "sg:tags":[
        "delicacy"
    ],
    "wof:name":"Eternal Victory",
    "wof:placetype":"venue"
},
  "geometry": {"coordinates":[115.90930899999999,-32.038666],"type":"Point"}
}