{
  "type": "Feature",
  "properties": {
    "iso:country":"AU",
    "sg:address":"1 Corrigin Crt",
    "sg:city":"Elanora",
    "sg:classifiers":[
        {
            "category":"Personal",
            "subcategory":"Tattoo Parlor",
            "type":"Services"
        }
    ],
    "sg:phone":"+61 413 273 278",
    "sg:postcode":"4221",
    "sg:province":"QLD",
    "sg:tags":[
        "resume"
    ],
    "wof:name":"Five Star Resume",
    "wof:placetype":"venue"
},
  "geometry": {"coordinates":[153.455810547,-28.1269187927],"type":"Point"}
}