{
  "type": "Feature",
  "properties": {
    "addr:full":"1 Masons Drv North Parramatta NSW 2151",
    "addr:housenumber":"1",
    "addr:postcode":"2151",
    "addr:street":"Masons Drv",
    "iso:country":"AU",
    "sg:address":"1 Masons Drv",
    "sg:city":"North Parramatta",
    "sg:classifiers":[
        {
            "category":"Social Services",
            "subcategory":"Child Care",
            "type":"Services"
        }
    ],
    "sg:phone":"+61 425 248 135",
    "sg:postcode":"2151",
    "sg:province":"NSW",
    "wof:name":"Burnside Before & After School Care",
    "wof:placetype":"venue"
},
  "geometry": {"coordinates":[151.01791381800001,-33.7939605713],"type":"Point"}
}