{
  "type": "Feature",
  "properties": {
    "iso:country":"AU",
    "sg:address":"18 Masuda St",
    "sg:city":"Annandale",
    "sg:classifiers":[
        {
            "category":"Education",
            "subcategory":"Music School",
            "type":"Public Place"
        }
    ],
    "sg:phone":"+61 7 4779 8093",
    "sg:postcode":"4814",
    "sg:province":"QLD",
    "sg:tags":[
        "choir",
        "bands",
        "orchestra"
    ],
    "wof:name":"Marathon Entertainment",
    "wof:placetype":"venue"
},
  "geometry": {"coordinates":[146.766998,-19.314878],"type":"Point"}
}