{
  "type": "Feature",
  "properties": {
    "addr:full":"Shop 4/ 222 Campbell Pde Bondi Beach NSW 2026",
    "addr:housenumber":"shop 4 / 222",
    "addr:postcode":"2026",
    "addr:street":"Campbell Pde",
    "iso:country":"AU",
    "sg:address":"Shop 4/ 222 Campbell Pde",
    "sg:city":"Bondi Beach",
    "sg:classifiers":[
        {
            "category":"Shopping",
            "subcategory":"Mobile Phones",
            "type":"Retail Goods"
        }
    ],
    "sg:phone":"+61 2 9365 3340",
    "sg:postcode":"2026",
    "sg:province":"NSW",
    "sg:tags":[
        "telephone",
        "accessory"
    ],
    "wof:name":"All Mobile Phone Pty Ltd",
    "wof:placetype":"venue"
},
  "geometry": {"coordinates":[151.279495239,-33.8891830444],"type":"Point"}
}