{
  "type": "Feature",
  "properties": {
    "addr:full":"6 Bushland Ave Tamworth NSW 2340",
    "addr:housenumber":"6",
    "addr:postcode":"2340",
    "addr:street":"Bushland Ave",
    "iso:country":"AU",
    "sg:address":"6 Bushland Ave",
    "sg:city":"Tamworth",
    "sg:classifiers":[
        {
            "category":"Organizations",
            "subcategory":"Community Association",
            "type":"Services"
        }
    ],
    "sg:phone":"+61 2 6766 1892",
    "sg:postcode":"2340",
    "sg:province":"NSW",
    "sg:tags":[
        "organisation",
        "family",
        "welfare"
    ],
    "wof:name":"Carol Dillon",
    "wof:placetype":"venue"
},
  "geometry": {"coordinates":[150.94737243599999,-31.09882164],"type":"Point"}
}