{
  "type": "Feature",
  "properties": {
    "iso:country":"AU",
    "sg:address":"1424 High St",
    "sg:city":"Malvern",
    "sg:classifiers":[
        {
            "category":"Retail",
            "subcategory":"Auto Repair",
            "type":"Services"
        }
    ],
    "sg:phone":"+61 3 9509 7082",
    "sg:postcode":"3144",
    "sg:province":"VIC",
    "sg:tags":[
        "repairer",
        "motor",
        "engineer"
    ],
    "wof:name":"Angle Service Centre",
    "wof:placetype":"venue"
},
  "geometry": {"coordinates":[145.040725708,-37.858215332],"type":"Point"}
}