{
  "type": "Feature",
  "properties": {
    "iso:country":"AU",
    "sg:address":"32 Commercial Rd",
    "sg:city":"Port Augusta",
    "sg:classifiers":[
        {
            "category":"Banks & Credit Unions",
            "subcategory":"Financial Services",
            "type":"Services"
        }
    ],
    "sg:phone":"+61 8 8642 2087",
    "sg:postcode":"5700",
    "sg:province":"SA",
    "sg:tags":[
        "financier"
    ],
    "wof:name":"CBFC Limited",
    "wof:placetype":"venue"
},
  "geometry": {"coordinates":[137.76182556099999,-32.4909286499],"type":"Point"}
}