{
  "type": "Feature",
  "properties": {
    "iso:country":"AU",
    "sg:address":"Shop 3/ 148 Windsor St",
    "sg:city":"Richmond",
    "sg:classifiers":[
        {
            "category":"Fast Food",
            "type":"Food & Drink"
        }
    ],
    "sg:phone":"+61 2 4588 5544",
    "sg:postcode":"2753",
    "sg:province":"NSW",
    "sg:tags":[
        "away",
        "take"
    ],
    "wof:name":"Richmond Star Kebab House",
    "wof:placetype":"venue"
},
  "geometry": {"coordinates":[150.753250122,-33.5980072021],"type":"Point"}
}