{
  "type": "Feature",
  "properties": {
    "addr:full":"14 Sheppard St Old Bar NSW 2430",
    "addr:housenumber":"14",
    "addr:postcode":"2430",
    "addr:street":"Sheppard St",
    "iso:country":"AU",
    "sg:address":"14 Sheppard St",
    "sg:city":"Old Bar",
    "sg:classifiers":[
        {
            "category":"Health Services",
            "subcategory":"Health Practitioner",
            "type":"Services"
        }
    ],
    "sg:phone":"+61 2 6553 7880",
    "sg:postcode":"2430",
    "sg:province":"NSW",
    "sg:tags":[
        "reiki"
    ],
    "wof:name":"Amos Wanda",
    "wof:placetype":"venue"
},
  "geometry": {"coordinates":[152.58448799999999,-31.967169],"type":"Point"}
}