{
  "type": "Feature",
  "properties": {
    "addr:full":"683 Plenty Rd Preston VIC 3072",
    "addr:housenumber":"683",
    "addr:postcode":"3072",
    "addr:street":"Plenty Rd",
    "iso:country":"AU",
    "sg:address":"683 Plenty Rd",
    "sg:city":"Preston",
    "sg:classifiers":[
        {
            "category":"Food & Beverages",
            "subcategory":"Bakery",
            "type":"Retail Goods"
        }
    ],
    "sg:phone":"+61 3 9478 4292",
    "sg:postcode":"3072",
    "sg:province":"VIC",
    "sg:tags":[
        "baker"
    ],
    "wof:name":"Plenty Rd Hot Bread Kitchen",
    "wof:placetype":"venue"
},
  "geometry": {"coordinates":[145.058135986,-37.7468109131],"type":"Point"}
}