{
  "type": "Feature",
  "properties": {
    "addr:full":"Unit 3, 105 Derby St Silverwater NSW 2128",
    "addr:housenumber":"105",
    "addr:postcode":"2128",
    "addr:street":"Derby St",
    "iso:country":"AU",
    "sg:address":"Unit 3, 105 Derby St",
    "sg:city":"Silverwater",
    "sg:classifiers":[
        {
            "category":"Building & Trades",
            "subcategory":"Cleaning & Sanitation",
            "type":"Services"
        }
    ],
    "sg:phone":"+61 2 9748 3288",
    "sg:postcode":"2128",
    "sg:province":"NSW",
    "sg:tags":[
        "commercial",
        "maintenance"
    ],
    "wof:name":"Maico Pty Ltd",
    "wof:placetype":"venue"
},
  "geometry": {"coordinates":[151.03973388700001,-33.8339881897],"type":"Point"}
}