{
  "type": "Feature",
  "properties": {
    "addr:full":"55 Paringa Rd Murarrie QLD 4172",
    "addr:housenumber":"55",
    "addr:postcode":"4172",
    "addr:street":"Paringa Rd",
    "iso:country":"AU",
    "sg:address":"55 Paringa Rd",
    "sg:city":"Murarrie",
    "sg:classifiers":[
        {
            "category":"Education",
            "subcategory":"Special Training",
            "type":"Public Place"
        }
    ],
    "sg:phone":"+61 7 3390 6649",
    "sg:postcode":"4172",
    "sg:province":"QLD",
    "sg:tags":[
        "development"
    ],
    "wof:name":"Lifting Skills Pty Ltd",
    "wof:placetype":"venue"
},
  "geometry": {"coordinates":[153.110275269,-27.4441413879],"type":"Point"}
}