{
  "type": "Feature",
  "properties": {
    "addr:full":"610- 612 Canterbury Rd Belmore NSW 2192",
    "addr:housenumber":"610 612",
    "addr:postcode":"2192",
    "addr:street":"Canterbury Rd",
    "iso:country":"AU",
    "sg:address":"610- 612 Canterbury Rd",
    "sg:city":"Belmore",
    "sg:classifiers":[
        {
            "category":"Shopping",
            "subcategory":"Music",
            "type":"Retail Goods"
        }
    ],
    "sg:phone":"+61 2 9787 4177",
    "sg:postcode":"2192",
    "sg:province":"NSW",
    "sg:tags":[
        "instrument",
        "musical"
    ],
    "wof:name":"Drummers Dream",
    "wof:placetype":"venue"
},
  "geometry": {"coordinates":[151.09520000000001,-33.922199],"type":"Point"}
}