{
  "type": "Feature",
  "properties": {
    "addr:full":"16 Macarthur St Parramatta NSW 2150",
    "addr:housenumber":"16",
    "addr:postcode":"2150",
    "addr:street":"Macarthur St",
    "iso:country":"AU",
    "sg:address":"16 Macarthur St",
    "sg:city":"Parramatta",
    "sg:classifiers":[
        {
            "category":"Building & Trades",
            "subcategory":"Landscaping Services",
            "type":"Services"
        }
    ],
    "sg:phone":"+61 2 9890 2288",
    "sg:postcode":"2150",
    "sg:province":"NSW",
    "sg:tags":[
        "consultant"
    ],
    "wof:name":"Kriton Pty Ltd",
    "wof:placetype":"venue"
},
  "geometry": {"coordinates":[151.062057495,-33.8113059998],"type":"Point"}
}