{
  "type": "Feature",
  "properties": {
    "iso:country":"AU",
    "sg:address":"31 Dwyer St",
    "sg:city":"Gymea",
    "sg:classifiers":[
        {
            "category":"Shopping",
            "subcategory":"Stationery & Office Supplies",
            "type":"Retail Goods"
        }
    ],
    "sg:phone":"+61 2 9525 9797",
    "sg:postcode":"2227",
    "sg:province":"NSW",
    "sg:tags":[
        "equipment",
        "badge",
        "making"
    ],
    "wof:name":"Accurate Badges",
    "wof:placetype":"venue"
},
  "geometry": {"coordinates":[151.09019470199999,-34.0308532715],"type":"Point"}
}