{
  "type": "Feature",
  "properties": {
    "addr:full":"23 Greenwood Crs Moil NT 0810",
    "addr:housenumber":"23",
    "addr:postcode":"nt 0810",
    "addr:street":"Greenwood Crs",
    "iso:country":"AU",
    "sg:address":"23 Greenwood Crs",
    "sg:city":"Moil",
    "sg:classifiers":[
        {
            "category":"Recreation",
            "subcategory":"Fishing",
            "type":"Entertainment"
        }
    ],
    "sg:phone":"+61 414 741 245",
    "sg:postcode":"0810",
    "sg:province":"NT",
    "sg:tags":[
        "trip"
    ],
    "wof:name":"King Kontis Fishing Charters",
    "wof:placetype":"venue"
},
  "geometry": {"coordinates":[130.876785278,-12.3831100464],"type":"Point"}
}