{
  "type": "Feature",
  "properties": {
    "iso:country":"AU",
    "sg:address":"107 Liebig St",
    "sg:city":"Warrnambool",
    "sg:classifiers":[
        {
            "category":"Shopping",
            "subcategory":"Clothing, Apparel, & Fashions",
            "type":"Retail Goods"
        }
    ],
    "sg:phone":"+61 3 5562 4660",
    "sg:postcode":"3280",
    "sg:province":"VIC",
    "sg:tags":[
        "lady",
        "wear"
    ],
    "wof:name":"Sussan Corporation (Aust) Pty Ltd",
    "wof:placetype":"venue"
},
  "geometry": {"coordinates":[142.48365783700001,-38.3834266663],"type":"Point"}
}