{
  "type": "Feature",
  "properties": {
    "iso:country":"AU",
    "sg:address":"PO Box W 270",
    "sg:city":"Warringah Mall",
    "sg:classifiers":[
        {
            "category":"Professional",
            "subcategory":"Accounting & Tax Preparation",
            "type":"Services"
        }
    ],
    "sg:phone":"+61 2 9981 1811",
    "sg:postcode":"2100",
    "sg:province":"NSW",
    "sg:tags":[
        "accountant",
        "auditor"
    ],
    "wof:name":"Seastar Business Solutions Pty Ltd",
    "wof:placetype":"venue"
},
  "geometry": {"coordinates":[151.250534058,-33.75233078],"type":"Point"}
}