{
  "type": "Feature",
  "properties": {
    "iso:country":"AU",
    "sg:address":"169 Cleveland St",
    "sg:city":"Chippendale",
    "sg:classifiers":[
        {
            "category":"Utilities",
            "subcategory":"Refuse",
            "type":"Services"
        }
    ],
    "sg:phone":"+61 2 9319 7544",
    "sg:postcode":"2008",
    "sg:province":"NSW",
    "sg:tags":[
        "leather",
        "retail",
        "clothing"
    ],
    "wof:name":"Kujo Leathers",
    "wof:placetype":"venue"
},
  "geometry": {"coordinates":[151.19886779800001,-33.8887252808],"type":"Point"}
}