{
  "type": "Feature",
  "properties": {
    "addr:full":"27 Linden Ave Orange NSW 2800",
    "addr:housenumber":"27",
    "addr:postcode":"2800",
    "addr:street":"Linden Ave",
    "iso:country":"AU",
    "sg:address":"27 Linden Ave",
    "sg:city":"Orange",
    "sg:classifiers":[
        {
            "category":"Building & Trades",
            "subcategory":"Construction",
            "type":"Services"
        }
    ],
    "sg:phone":"+61 2 6362 1979",
    "sg:postcode":"2800",
    "sg:province":"NSW",
    "sg:tags":[
        "contractor"
    ],
    "wof:name":"Wright K & R",
    "wof:placetype":"venue"
},
  "geometry": {"coordinates":[149.08190918,-33.2794113159],"type":"Point"}
}