{
  "type": "Feature",
  "properties": {
    "iso:country":"AU",
    "sg:address":"7 Parade St",
    "sg:city":"Pingelly",
    "sg:classifiers":[
        {
            "category":"Banks & Credit Unions",
            "subcategory":"Bank",
            "type":"Services"
        }
    ],
    "sg:phone":"+61 8 9887 0200",
    "sg:postcode":"6308",
    "sg:province":"WA",
    "wof:name":"Bendigo Community Bank",
    "wof:placetype":"venue"
},
  "geometry": {"coordinates":[117.08396911600001,-32.5335578918],"type":"Point"}
}