{
  "type": "Feature",
  "properties": {
    "addr:full":"17 Raleigh Ave Flinders Park SA 5025",
    "addr:housenumber":"17",
    "addr:postcode":"5025",
    "addr:street":"Raleigh Ave Flinders",
    "iso:country":"AU",
    "sg:address":"17 Raleigh Ave",
    "sg:city":"Flinders Park",
    "sg:classifiers":[
        {
            "category":"Health Services",
            "subcategory":"Health Practitioner",
            "type":"Services"
        }
    ],
    "sg:phone":"+61 8 8354 0562",
    "sg:postcode":"5025",
    "sg:province":"SA",
    "sg:tags":[
        "naturopath"
    ],
    "wof:name":"Bergineti Daniel",
    "wof:placetype":"venue"
},
  "geometry": {"coordinates":[138.54530334500001,-34.9063911438],"type":"Point"}
}