{
  "type": "Feature",
  "properties": {
    "addr:full":"5 Ballantyne Rd Kewdale WA 6105",
    "addr:housenumber":"5",
    "addr:postcode":"6105",
    "addr:street":"Ballantyne Rd",
    "iso:country":"AU",
    "sg:address":"5 Ballantyne Rd",
    "sg:city":"Kewdale",
    "sg:classifiers":[
        {
            "category":"Wholesale",
            "subcategory":"Home Furnishings",
            "type":"Manufacturing & Wholesale Goods"
        }
    ],
    "sg:phone":"+61 8 9353 4767",
    "sg:postcode":"6105",
    "sg:province":"WA",
    "sg:tags":[
        "wholesaler",
        "bedding",
        "mfrs",
        "bed"
    ],
    "wof:name":"Australian Commercial Bedding",
    "wof:placetype":"venue"
},
  "geometry": {"coordinates":[115.938499451,-31.9883346558],"type":"Point"}
}