{
  "type": "Feature",
  "properties": {
    "addr:full":"U11/ 85 John St Cabramatta NSW 2166",
    "addr:housenumber":"85",
    "addr:postcode":"2166",
    "addr:street":"/;John St",
    "iso:country":"AU",
    "sg:address":"U11/ 85 John St",
    "sg:city":"Cabramatta",
    "sg:classifiers":[
        {
            "category":"Food & Beverages",
            "subcategory":"Supermarket",
            "type":"Retail Goods"
        }
    ],
    "sg:phone":"+61 2 9723 0229",
    "sg:postcode":"2166",
    "sg:province":"NSW",
    "sg:tags":[
        "grocery",
        "store"
    ],
    "wof:name":"Van Phong Asian Grocery",
    "wof:placetype":"venue"
},
  "geometry": {"coordinates":[150.93576049800001,-33.8948860168],"type":"Point"}
}