{
  "type": "Feature",
  "properties": {
    "addr:full":"121 Lake Weyba Drv Noosaville QLD 4566",
    "addr:housenumber":"121",
    "addr:postcode":"4566",
    "addr:street":"Lake Weyba Drv",
    "iso:country":"AU",
    "sg:address":"121 Lake Weyba Drv",
    "sg:city":"Noosaville",
    "sg:classifiers":[
        {
            "category":"Real Estate",
            "subcategory":"Surveying",
            "type":"Services"
        }
    ],
    "sg:phone":"+61 7 5474 4266",
    "sg:postcode":"4566",
    "sg:province":"QLD",
    "sg:tags":[
        "surveyor",
        "quantity"
    ],
    "wof:name":"Snowden Phillip",
    "wof:placetype":"venue"
},
  "geometry": {"coordinates":[153.07188415499999,-26.4047107697],"type":"Point"}
}