{
  "type": "Feature",
  "properties": {
    "addr:full":"35 Amersham Drv Wantirna VIC 3152",
    "addr:housenumber":"35",
    "addr:postcode":"3152",
    "addr:street":"Amersham Drv",
    "iso:country":"AU",
    "sg:address":"35 Amersham Drv",
    "sg:city":"Wantirna",
    "sg:classifiers":[
        {
            "category":"Manufacturing",
            "subcategory":"Rubber & Plastics",
            "type":"Manufacturing & Wholesale Goods"
        }
    ],
    "sg:phone":"+61 3 9887 3252",
    "sg:postcode":"3152",
    "sg:province":"VIC",
    "sg:tags":[
        "consultant"
    ],
    "wof:name":"Delynda Pty Ltd",
    "wof:placetype":"venue"
},
  "geometry": {"coordinates":[145.22569274899999,-37.8585166931],"type":"Point"}
}