{
  "type": "Feature",
  "properties": {
    "iso:country":"AU",
    "sg:address":"11 Rohs Rd",
    "sg:city":"Bendigo",
    "sg:classifiers":[
        {
            "category":"Wholesale",
            "subcategory":"Durable Goods & Equipment",
            "type":"Manufacturing & Wholesale Goods"
        }
    ],
    "sg:phone":"+61 3 5442 3477",
    "sg:postcode":"3550",
    "sg:province":"VIC",
    "sg:tags":[
        "stockyard"
    ],
    "wof:name":"Kattle Gear Australia Pty Ltd",
    "wof:placetype":"venue"
},
  "geometry": {"coordinates":[144.31262207,-36.7451591492],"type":"Point"}
}