{
  "type": "Feature",
  "properties": {
    "addr:full":"101 Rickertt Rd Ransome QLD 4154",
    "addr:housenumber":"101",
    "addr:postcode":"4154",
    "addr:street":"Rickertt Rd",
    "iso:country":"AU",
    "sg:address":"101 Rickertt Rd",
    "sg:city":"Ransome",
    "sg:classifiers":[
        {
            "category":"Retail",
            "subcategory":"Driving School",
            "type":"Services"
        }
    ],
    "sg:phone":"+61 7 3245 1101",
    "sg:postcode":"4154",
    "sg:province":"QLD",
    "wof:name":"Cycle Right Motorcycle Training Academy",
    "wof:placetype":"venue"
},
  "geometry": {"coordinates":[153.16822814899999,-27.4851970673],"type":"Point"}
}