{
  "type": "Feature",
  "properties": {
    "addr:full":"Shop 18 (External Access), Waverley Gardens Shopping VIC 3170",
    "addr:housenumber":"shop 18",
    "addr:postcode":"3170",
    "addr:street":"External Access",
    "iso:country":"AU",
    "sg:address":"Shop 18",
    "sg:city":"(External Access), Waverley Gardens Shopping",
    "sg:classifiers":[
        {
            "category":"Personal",
            "subcategory":"Beauty Salon",
            "type":"Services"
        }
    ],
    "sg:phone":"+61 3 9562 4373",
    "sg:postcode":"3170",
    "sg:province":"VIC",
    "sg:tags":[
        "hairdresser"
    ],
    "wof:name":"Francois Ladies & Gents Hairdressing",
    "wof:placetype":"venue"
},
  "geometry": {"coordinates":[145.123947144,-37.8844184875],"type":"Point"}
}