{
  "type": "Feature",
  "properties": {
    "addr:full":"182 Gatton St Manunda QLD 4870",
    "addr:housenumber":"182",
    "addr:postcode":"4870",
    "addr:street":"Gatton St",
    "iso:country":"AU",
    "sg:address":"182 Gatton St",
    "sg:city":"Manunda",
    "sg:classifiers":[
        {
            "category":"Organizations",
            "subcategory":"Community Association",
            "type":"Services"
        }
    ],
    "sg:phone":"+61 1300 364 277",
    "sg:postcode":"4870",
    "sg:province":"QLD",
    "sg:tags":[
        "organisation",
        "family",
        "welfare"
    ],
    "wof:name":"Relationships Australia",
    "wof:placetype":"venue"
},
  "geometry": {"coordinates":[145.75538635300001,-16.9238872528],"type":"Point"}
}