{
  "type": "Feature",
  "properties": {
    "addr:full":"12 Trevatt Crt Lutana TAS 7009",
    "addr:housenumber":"12",
    "addr:postcode":"7009",
    "addr:street":"Trevatt Crt",
    "iso:country":"AU",
    "sg:address":"12 Trevatt Crt",
    "sg:city":"Lutana",
    "sg:classifiers":[
        {
            "category":"Building & Trades",
            "subcategory":"Landscaping Services",
            "type":"Services"
        }
    ],
    "sg:phone":"+61 429 198 008",
    "sg:postcode":"7009",
    "sg:province":"TAS",
    "sg:tags":[
        "gardener"
    ],
    "wof:name":"All Aspect Trees & Gardens",
    "wof:placetype":"venue"
},
  "geometry": {"coordinates":[147.312057495,-42.8386039734],"type":"Point"}
}