{
  "type": "Feature",
  "properties": {
    "addr:full":"22 Dandaloo St Narromine NSW 2821",
    "addr:housenumber":"22",
    "addr:postcode":"2821",
    "addr:street":"Dandaloo St",
    "iso:country":"AU",
    "sg:address":"22 Dandaloo St",
    "sg:city":"Narromine",
    "sg:classifiers":[
        {
            "category":"Health Services",
            "subcategory":"Health Practitioner",
            "type":"Services"
        }
    ],
    "sg:phone":"+61 2 6889 4932",
    "sg:postcode":"2821",
    "sg:province":"NSW",
    "sg:tags":[
        "psychologist"
    ],
    "wof:name":"Centacare- Family & Community Services",
    "wof:placetype":"venue"
},
  "geometry": {"coordinates":[148.23907470699999,-32.2356834412],"type":"Point"}
}