{
  "type": "Feature",
  "properties": {
    "addr:full":"87 Macleay St Potts Point NSW 2011",
    "addr:housenumber":"87",
    "addr:postcode":"2011",
    "addr:street":"Macleay St",
    "iso:country":"AU",
    "sg:address":"87 Macleay St",
    "sg:city":"Potts Point",
    "sg:classifiers":[
        {
            "category":"Bars & Pubs",
            "subcategory":"Dive Bar",
            "type":"Food & Drink"
        }
    ],
    "sg:phone":"+61 2 9358 4640",
    "sg:postcode":"2011",
    "sg:province":"NSW",
    "sg:tags":[
        "knitwear",
        "retail"
    ],
    "wof:name":"Coogi Knitwear At Sydneyscope",
    "wof:placetype":"venue"
},
  "geometry": {"coordinates":[151.225067139,-33.8712043762],"type":"Point"}
}