{
  "type": "Feature",
  "properties": {
    "addr:full":"Suite 12, 149 Colburn Ave Victoria Point QLD 4165",
    "addr:housenumber":"149",
    "addr:postcode":"4165",
    "addr:street":"Colburn Ave",
    "iso:country":"AU",
    "sg:address":"Suite 12, 149 Colburn Ave",
    "sg:city":"Victoria Point",
    "sg:classifiers":[
        {
            "category":"Health Services",
            "subcategory":"Doctor",
            "type":"Services"
        }
    ],
    "sg:phone":"+61 7 3207 8066",
    "sg:postcode":"4165",
    "sg:province":"QLD",
    "sg:tags":[
        "medical",
        "practitioner"
    ],
    "wof:name":"Zambelli Kim Dr",
    "wof:placetype":"venue"
},
  "geometry": {"coordinates":[153.30661010700001,-27.5865001678],"type":"Point"}
}