{
  "type": "Feature",
  "properties": {
    "iso:country":"AU",
    "sg:address":"83 Percival Rd",
    "sg:city":"Stanmore",
    "sg:classifiers":[
        {
            "category":"Cafe",
            "type":"Food & Drink"
        }
    ],
    "sg:phone":"+61 2 9568 3349",
    "sg:postcode":"2048",
    "sg:province":"NSW",
    "wof:name":"Poppies Cafe & Catering at Stanmore",
    "wof:placetype":"venue"
},
  "geometry": {"coordinates":[151.16407799999999,-33.893661],"type":"Point"}
}