{
  "type": "Feature",
  "properties": {
    "addr:full":"Unit 1 75 Addison Rd Pennington SA 5013",
    "addr:housenumber":"75",
    "addr:postcode":"5013",
    "addr:street":"Addison Rd",
    "iso:country":"AU",
    "sg:address":"Unit 1 75 Addison Rd",
    "sg:city":"Pennington",
    "sg:classifiers":[
        {
            "category":"Health Services",
            "subcategory":"Doctor",
            "type":"Services"
        }
    ],
    "sg:phone":"+61 8 8447 5592",
    "sg:postcode":"5013",
    "sg:province":"SA",
    "sg:tags":[
        "medical",
        "practitioner"
    ],
    "wof:name":"Nguyen T B Dr",
    "wof:placetype":"venue"
},
  "geometry": {"coordinates":[138.52897644000001,-34.8569145203],"type":"Point"}
}