{
  "type": "Feature",
  "properties": {
    "addr:full":"RMB 4135 Newry Rd Tinamba VIC 3859",
    "addr:postcode":"3859",
    "addr:street":"Newry Rd",
    "iso:country":"AU",
    "sg:address":"RMB 4135 Newry Rd",
    "sg:city":"Tinamba",
    "sg:classifiers":[
        {
            "category":"Mining & Drilling",
            "type":"Manufacturing & Wholesale Goods"
        }
    ],
    "sg:phone":"+61 409 022 044",
    "sg:postcode":"3859",
    "sg:province":"VIC",
    "sg:tags":[
        "boring",
        "contractor"
    ],
    "wof:name":"Gippsland Drilling",
    "wof:placetype":"venue"
},
  "geometry": {"coordinates":[146.88905334500001,-37.9285049438],"type":"Point"}
}