{
  "type": "Feature",
  "properties": {
    "addr:full":"4 Prestige Drv Clayton South VIC 3169",
    "addr:housenumber":"4",
    "addr:postcode":"3169",
    "addr:street":"Prestige Drv",
    "iso:country":"AU",
    "sg:address":"4 Prestige Drv",
    "sg:city":"Clayton South",
    "sg:classifiers":[
        {
            "category":"Retail",
            "subcategory":"Auto Repair",
            "type":"Services"
        }
    ],
    "sg:phone":"+61 3 9558 2688",
    "sg:postcode":"3169",
    "sg:province":"VIC",
    "sg:tags":[
        "repairer",
        "motor",
        "engineer"
    ],
    "wof:name":"AJ Carcare Service Centre",
    "wof:placetype":"venue"
},
  "geometry": {"coordinates":[145.12226867699999,-37.9414405823],"type":"Point"}
}