{
  "type": "Feature",
  "properties": {
    "addr:full":"206 Grahams Rd Lancefield VIC 3435",
    "addr:housenumber":"206",
    "addr:postcode":"3435",
    "addr:street":"Grahams Rd",
    "iso:country":"AU",
    "sg:address":"206 Grahams Rd",
    "sg:city":"Lancefield",
    "sg:classifiers":[
        {
            "category":"Farming",
            "subcategory":"Vineyard",
            "type":"Manufacturing & Wholesale Goods"
        }
    ],
    "sg:phone":"+61 3 5429 1964",
    "sg:postcode":"3435",
    "sg:province":"VIC",
    "sg:tags":[
        "winery"
    ],
    "wof:name":"Moonrise Wines",
    "wof:placetype":"venue"
},
  "geometry": {"coordinates":[144.76286315900001,-37.3006362915],"type":"Point"}
}