{
  "type": "Feature",
  "properties": {
    "addr:full":"18 Hastings St Noosa Heads QLD 4567",
    "addr:housenumber":"18",
    "addr:postcode":"4567",
    "addr:street":"Hastings St",
    "iso:country":"AU",
    "sg:address":"18 Hastings St",
    "sg:city":"Noosa Heads",
    "sg:classifiers":[
        {
            "category":"Shopping",
            "subcategory":"Jewelry",
            "type":"Retail Goods"
        }
    ],
    "sg:phone":"+61 7 5474 9500",
    "sg:postcode":"4567",
    "sg:province":"QLD",
    "sg:tags":[
        "jeweller"
    ],
    "wof:name":"Ixtlan",
    "wof:placetype":"venue"
},
  "geometry": {"coordinates":[153.088546753,-26.3864517212],"type":"Point"}
}