{
  "type": "Feature",
  "properties": {
    "addr:full":"840 Creek Rd Carina Heights QLD 4152",
    "addr:housenumber":"840",
    "addr:postcode":"4152",
    "addr:street":"Creek Rd",
    "iso:country":"AU",
    "sg:address":"840 Creek Rd",
    "sg:city":"Carina Heights",
    "sg:classifiers":[
        {
            "category":"Travel",
            "subcategory":"Hostel",
            "type":"Entertainment"
        }
    ],
    "sg:phone":"+61 7 3213 7222",
    "sg:postcode":"4152",
    "sg:province":"QLD",
    "sg:tags":[
        "home"
    ],
    "wof:name":"Salvin Park Complex",
    "wof:placetype":"venue"
},
  "geometry": {"coordinates":[153.09707641599999,-27.5173225403],"type":"Point"}
}