{
  "type": "Feature",
  "properties": {
    "iso:country":"AU",
    "sg:address":"48 Amaroo Drv",
    "sg:city":"Moree",
    "sg:classifiers":[
        {
            "category":"Social Services",
            "subcategory":"Child Care",
            "type":"Services"
        }
    ],
    "sg:phone":"+61 2 6752 7677",
    "sg:postcode":"2400",
    "sg:province":"NSW",
    "wof:name":"Aussie Kids of Moree Pre-School and Day Care Centre",
    "wof:placetype":"venue"
},
  "geometry": {"coordinates":[149.84324645999999,-29.4845218658],"type":"Point"}
}