{
  "type": "Feature",
  "properties": {
    "iso:country":"AU",
    "sg:address":"Suite 58",
    "sg:city":"Isle Of Capri Shopping Centre Isle Of Capri",
    "sg:classifiers":[
        {
            "category":"Health Services",
            "subcategory":"Clinic",
            "type":"Services"
        }
    ],
    "sg:phone":"+61 7 5538 7200",
    "sg:postcode":"4217",
    "sg:province":"QLD",
    "sg:tags":[
        "aid",
        "dental"
    ],
    "wof:name":"Slater Dental Studio",
    "wof:placetype":"venue"
},
  "geometry": {"coordinates":[153.41133117699999,-27.9702339172],"type":"Point"}
}