{
  "type": "Feature",
  "properties": {
    "addr:full":"233 Buckland Rd Nundah QLD 4012",
    "addr:housenumber":"233",
    "addr:postcode":"4012",
    "addr:street":"Buckland Rd",
    "iso:country":"AU",
    "sg:address":"233 Buckland Rd",
    "sg:city":"Nundah",
    "sg:classifiers":[
        {
            "category":"Building & Trades",
            "subcategory":"Construction",
            "type":"Services"
        }
    ],
    "sg:phone":"+61 7 3266 1306",
    "sg:postcode":"4012",
    "sg:province":"QLD",
    "sg:tags":[
        "concrete",
        "contractor"
    ],
    "wof:name":"A Bout Town Concrete Services Pty Ltd",
    "wof:placetype":"venue"
},
  "geometry": {"coordinates":[153.05130004899999,-27.4020080566],"type":"Point"}
}