{
  "type": "Feature",
  "properties": {
    "addr:full":"Bronzewing Drv Erina NSW 2250",
    "addr:postcode":"2250",
    "addr:street":"Bronzewing Drv",
    "iso:country":"AU",
    "sg:address":"Bronzewing Drv",
    "sg:city":"Erina",
    "sg:classifiers":[
        {
            "category":"Personal",
            "subcategory":"Massage",
            "type":"Services"
        }
    ],
    "sg:phone":"+61 2 4367 7813",
    "sg:postcode":"2250",
    "sg:province":"NSW",
    "sg:tags":[
        "therapy"
    ],
    "wof:name":"Leahy Jill",
    "wof:placetype":"venue"
},
  "geometry": {"coordinates":[151.390625,-33.4400787354],"type":"Point"}
}