{
  "type": "Feature",
  "properties": {
    "iso:country":"AU",
    "sg:address":"Cnr Newman Rd & Lauren St",
    "sg:city":"Geebung",
    "sg:classifiers":[
        {
            "category":"Autos & Motor Vehicles",
            "subcategory":"Fuel & Gas Station",
            "type":"Retail Goods"
        }
    ],
    "sg:phone":"+61 7 3265 6763",
    "sg:postcode":"4034",
    "sg:province":"QLD",
    "wof:name":"BP",
    "wof:placetype":"venue"
},
  "geometry": {"coordinates":[153.047867,-27.369242],"type":"Point"}
}