{
  "type": "Feature",
  "properties": {
    "iso:country":"AU",
    "sg:address":"6 Baker St",
    "sg:city":"Gosford",
    "sg:classifiers":[
        {
            "category":"Bars & Pubs",
            "subcategory":"Nightclub",
            "type":"Food & Drink"
        }
    ],
    "sg:phone":"+61 2 4322 0700",
    "sg:postcode":"2250",
    "sg:province":"NSW",
    "sg:tags":[
        "discotheque"
    ],
    "wof:name":"Level 1 Nightclub",
    "wof:placetype":"venue"
},
  "geometry": {"coordinates":[151.340744019,-33.4271469116],"type":"Point"}
}