{
  "type": "Feature",
  "properties": {
    "iso:country":"AU",
    "sg:address":"52 Belgrave St",
    "sg:city":"Balmoral",
    "sg:classifiers":[
        {
            "category":"Professional",
            "subcategory":"Management & Consulting",
            "type":"Services"
        }
    ],
    "sg:phone":"+61 7 3899 1490",
    "sg:postcode":"4171",
    "sg:province":"QLD",
    "sg:tags":[
        "consultant"
    ],
    "wof:name":"John Shepley & Associates",
    "wof:placetype":"venue"
},
  "geometry": {"coordinates":[153.066162109,-27.4628715515],"type":"Point"}
}