{
  "type": "Feature",
  "properties": {
    "addr:full":"20 Carrington Drv Sunshine VIC 3020",
    "addr:housenumber":"20",
    "addr:postcode":"3020",
    "addr:street":"Carrington Drv",
    "iso:country":"AU",
    "sg:address":"20 Carrington Drv",
    "sg:city":"Sunshine",
    "sg:classifiers":[
        {
            "category":"Retail",
            "subcategory":"Auto Repair",
            "type":"Services"
        }
    ],
    "sg:phone":"+61 3 9360 5005",
    "sg:postcode":"3020",
    "sg:province":"VIC",
    "sg:tags":[
        "hire",
        "go-kart"
    ],
    "sg:website":"http://www.acekarts.com.au",
    "wof:name":"Ace Karts",
    "wof:placetype":"venue"
},
  "geometry": {"coordinates":[144.80993699999999,-37.771275],"type":"Point"}
}