{
  "type": "Feature",
  "properties": {
    "iso:country":"AU",
    "sg:address":"Augustine Centre, 2 Minona St",
    "sg:city":"Hawthorn",
    "sg:classifiers":[
        {
            "category":"Health Services",
            "subcategory":"Health Practitioner",
            "type":"Services"
        }
    ],
    "sg:phone":"+61 3 9819 2844",
    "sg:postcode":"3122",
    "sg:province":"VIC",
    "sg:tags":[
        "psychologist"
    ],
    "wof:name":"Fay Oberklaid",
    "wof:placetype":"venue"
},
  "geometry": {"coordinates":[145.04197692899999,-37.8242111206],"type":"Point"}
}