{
  "type": "Feature",
  "properties": {
    "iso:country":"AU",
    "sg:address":"10a McInnes Rd",
    "sg:city":"Tynong North",
    "sg:classifiers":[
        {
            "category":"Building & Trades",
            "subcategory":"Construction",
            "type":"Services"
        }
    ],
    "sg:phone":"+61 409 232 236",
    "sg:postcode":"3813",
    "sg:province":"VIC",
    "sg:tags":[
        "earth",
        "excavating",
        "moving",
        "contractor"
    ],
    "wof:name":"Pakenham Dingo Hire",
    "wof:placetype":"venue"
},
  "geometry": {"coordinates":[145.613846,-38.053181],"type":"Point"}
}