{
  "type": "Feature",
  "properties": {
    "addr:full":"296 Spring Rd Dingley Village VIC 3172",
    "addr:housenumber":"296",
    "addr:postcode":"3172",
    "addr:street":"Spring Rd",
    "iso:country":"AU",
    "sg:address":"296 Spring Rd",
    "sg:city":"Dingley Village",
    "sg:classifiers":[
        {
            "category":"Education",
            "subcategory":"Dance Studio",
            "type":"Public Place"
        }
    ],
    "sg:phone":"+61 3 9551 7967",
    "sg:postcode":"3172",
    "sg:province":"VIC",
    "sg:tags":[
        "venue",
        "tuition"
    ],
    "wof:name":"Dingley Village Dance Centre",
    "wof:placetype":"venue"
},
  "geometry": {"coordinates":[145.138946533,-37.9820632935],"type":"Point"}
}