{
  "type": "Feature",
  "properties": {
    "addr:full":"65 Beach St Frankston VIC 3199",
    "addr:housenumber":"65",
    "addr:postcode":"3199",
    "addr:street":"Beach St",
    "iso:country":"AU",
    "sg:address":"65 Beach St",
    "sg:city":"Frankston",
    "sg:classifiers":[
        {
            "category":"Health Services",
            "subcategory":"Doctor",
            "type":"Services"
        }
    ],
    "sg:phone":"+61 3 9781 5255",
    "sg:postcode":"3199",
    "sg:province":"VIC",
    "sg:tags":[
        "medical",
        "practitioner"
    ],
    "wof:name":"Baker Geoffrey J",
    "wof:placetype":"venue"
},
  "geometry": {"coordinates":[144.936309814,-37.8420372009],"type":"Point"}
}