{
  "type": "Feature",
  "properties": {
    "addr:full":"238 Commercial Rd Port Adelaide SA 5015",
    "addr:housenumber":"238",
    "addr:postcode":"5015",
    "addr:street":"Commercial Rd",
    "iso:country":"AU",
    "sg:address":"238 Commercial Rd",
    "sg:city":"Port Adelaide",
    "sg:classifiers":[
        {
            "category":"Fast Food",
            "type":"Food & Drink"
        }
    ],
    "sg:phone":"+61 8 8447 3916",
    "sg:postcode":"5015",
    "sg:province":"SA",
    "sg:tags":[
        "away",
        "take"
    ],
    "wof:name":"Pizza Hut Delivery",
    "wof:placetype":"venue"
},
  "geometry": {"coordinates":[138.50782775900001,-34.848613739],"type":"Point"}
}