{
  "type": "Feature",
  "properties": {
    "iso:country":"AU",
    "sg:address":"Unit 18/ 8 Booth Pl",
    "sg:city":"Balcatta",
    "sg:classifiers":[
        {
            "category":"Home & Garden",
            "subcategory":"Home Furnishings",
            "type":"Retail Goods"
        }
    ],
    "sg:phone":"+61 8 9240 6688",
    "sg:postcode":"6021",
    "sg:province":"WA",
    "sg:tags":[
        "shower",
        "screen"
    ],
    "wof:name":"Freeway Screens-Aluminium-Glass",
    "wof:placetype":"venue"
},
  "geometry": {"coordinates":[115.803169251,-31.8662052155],"type":"Point"}
}