{
  "type": "Feature",
  "properties": {
    "addr:full":"Cnr Thuringowa Drv & Herveys Range Rd Willows QLD 4702",
    "addr:postcode":"4702",
    "addr:street":"Cnr Thuringowa Drv & Herveys Range Rd",
    "iso:country":"AU",
    "sg:address":"Cnr Thuringowa Drv & Herveys Range Rd",
    "sg:city":"Willows",
    "sg:classifiers":[
        {
            "category":"Fast Food",
            "type":"Food & Drink"
        }
    ],
    "sg:phone":"+61 7 4723 2544",
    "sg:postcode":"4702",
    "sg:province":"QLD",
    "sg:tags":[
        "away",
        "take"
    ],
    "wof:name":"McDonald's Family Restaurants",
    "wof:placetype":"venue"
},
  "geometry": {"coordinates":[151.729125977,-24.2227325439],"type":"Point"}
}