{
  "type": "Feature",
  "properties": {
    "iso:country":"AU",
    "sg:address":"99 Carrington St",
    "sg:city":"Adelaide",
    "sg:classifiers":[
        {
            "category":"Shopping",
            "subcategory":"Computers & Home Electronics",
            "type":"Retail Goods"
        }
    ],
    "sg:phone":"+61 8 8235 7900",
    "sg:postcode":"5000",
    "sg:province":"SA",
    "sg:tags":[
        "equipment",
        "multimedia"
    ],
    "wof:name":"Fusion",
    "wof:placetype":"venue"
},
  "geometry": {"coordinates":[138.603881836,-34.9314613342],"type":"Point"}
}