{
  "type": "Feature",
  "properties": {
    "iso:country":"AU",
    "sg:address":"Cnr Mount Alexander & Ormond Rds",
    "sg:city":"Ascot Vale",
    "sg:classifiers":[
        {
            "category":"Retail",
            "subcategory":"Repair Shop",
            "type":"Services"
        }
    ],
    "sg:phone":"+61 3 9370 8211",
    "sg:postcode":"3032",
    "sg:province":"VIC",
    "sg:tags":[
        "cleaner",
        "part",
        "vacuum"
    ],
    "wof:name":"Godfreys",
    "wof:placetype":"venue"
},
  "geometry": {"coordinates":[144.92695599999999,-37.772717],"type":"Point"}
}