{
  "type": "Feature",
  "properties": {
    "addr:full":"967 Creek Rd Carindale QLD 4152",
    "addr:housenumber":"967",
    "addr:postcode":"4152",
    "addr:street":"Creek Rd",
    "iso:country":"AU",
    "sg:address":"967 Creek Rd",
    "sg:city":"Carindale",
    "sg:classifiers":[
        {
            "category":"Health Services",
            "subcategory":"Health Practitioner",
            "type":"Services"
        }
    ],
    "sg:phone":"+61 7 3398 1977",
    "sg:postcode":"4152",
    "sg:province":"QLD",
    "sg:tags":[
        "naturopath"
    ],
    "wof:name":"Wright Maxine",
    "wof:placetype":"venue"
},
  "geometry": {"coordinates":[153.09906005900001,-27.509305954],"type":"Point"}
}