{
  "type": "Feature",
  "properties": {
    "addr:full":"2 Brisbane St Illawong NSW 2234",
    "addr:housenumber":"2",
    "addr:postcode":"2234",
    "addr:street":"Brisbane St",
    "iso:country":"AU",
    "sg:address":"2 Brisbane St",
    "sg:city":"Illawong",
    "sg:classifiers":[
        {
            "category":"Personal",
            "subcategory":"Beauty Salon",
            "type":"Services"
        }
    ],
    "sg:phone":"+61 2 9543 7573",
    "sg:postcode":"2234",
    "sg:province":"NSW",
    "sg:tags":[
        "hairdresser"
    ],
    "wof:name":"Shelly's Hair Studio",
    "wof:placetype":"venue"
},
  "geometry": {"coordinates":[151.041137695,-33.9993896484],"type":"Point"}
}