{
  "type": "Feature",
  "properties": {
    "addr:full":"Suite 33 Porter House 203 Castlereagh St Sydney NSW 2000",
    "addr:housenumber":"203",
    "addr:postcode":"2000",
    "addr:street":"Castlereagh St",
    "iso:country":"AU",
    "sg:address":"Suite 33 Porter House 203 Castlereagh St",
    "sg:city":"Sydney",
    "sg:classifiers":[
        {
            "category":"Health Services",
            "subcategory":"Dentist",
            "type":"Services"
        }
    ],
    "sg:phone":"+61 2 9267 3110",
    "sg:postcode":"2000",
    "sg:province":"NSW",
    "wof:name":"Rynberg A S",
    "wof:placetype":"venue"
},
  "geometry": {"coordinates":[151.20892334000001,-33.8741645813],"type":"Point"}
}