{
  "type": "Feature",
  "properties": {
    "addr:full":"240/ 15 Albert Ave Broadbeach QLD 4218",
    "addr:housenumber":"240 / 15",
    "addr:postcode":"4218",
    "addr:street":"Albert Ave",
    "iso:country":"AU",
    "sg:address":"240/ 15 Albert Ave",
    "sg:city":"Broadbeach",
    "sg:classifiers":[
        {
            "category":"Building & Trades",
            "subcategory":"Locksmith",
            "type":"Services"
        }
    ],
    "sg:phone":"+61 418 677 005",
    "sg:postcode":"4218",
    "sg:province":"QLD",
    "sg:tags":[
        "lock"
    ],
    "wof:name":"David May 24 Hour Mobile Locksmiths",
    "wof:placetype":"venue"
},
  "geometry": {"coordinates":[153.432174683,-28.0280647278],"type":"Point"}
}