{
  "type": "Feature",
  "properties": {
    "addr:full":"1 Reservoir St Gunnedah NSW 2380",
    "addr:housenumber":"1",
    "addr:postcode":"2380",
    "addr:street":"Reservoir St",
    "iso:country":"AU",
    "sg:address":"1 Reservoir St",
    "sg:city":"Gunnedah",
    "sg:classifiers":[
        {
            "category":"Education",
            "subcategory":"Kindergarten",
            "type":"Public Place"
        }
    ],
    "sg:phone":"+61 2 6742 1805",
    "sg:postcode":"2380",
    "sg:province":"NSW",
    "sg:tags":[
        "pre-schools"
    ],
    "wof:name":"Gunnedah Baptist Community Pre-School",
    "wof:placetype":"venue"
},
  "geometry": {"coordinates":[150.24995422399999,-30.9836368561],"type":"Point"}
}