{
  "type": "Feature",
  "properties": {
    "addr:full":"122 Glebe Rd Booval QLD 4304",
    "addr:housenumber":"122",
    "addr:postcode":"4304",
    "addr:street":"Glebe Rd",
    "iso:country":"AU",
    "sg:address":"122 Glebe Rd",
    "sg:city":"Booval",
    "sg:classifiers":[
        {
            "category":"Recreation",
            "type":"Entertainment"
        }
    ],
    "sg:phone":"+61 7 3281 0055",
    "sg:postcode":"4304",
    "sg:province":"QLD",
    "sg:tags":[
        "supply",
        "outdoor",
        "adventure",
        "activity"
    ],
    "wof:name":"Yellow Jersey Bike Shop",
    "wof:placetype":"venue"
},
  "geometry": {"coordinates":[152.788574219,-27.6174621582],"type":"Point"}
}