{
  "type": "Feature",
  "properties": {
    "addr:full":"140 States Rd Morphett Vale SA 5162",
    "addr:housenumber":"140",
    "addr:postcode":"5162",
    "addr:street":"States Rd",
    "iso:country":"AU",
    "sg:address":"140 States Rd",
    "sg:city":"Morphett Vale",
    "sg:classifiers":[
        {
            "category":"Education",
            "subcategory":"School",
            "type":"Public Place"
        }
    ],
    "sg:phone":"+61 8 8381 9877",
    "sg:postcode":"5162",
    "sg:province":"SA",
    "sg:tags":[
        "co-educational"
    ],
    "wof:name":"Southern Vales Christian College",
    "wof:placetype":"venue"
},
  "geometry": {"coordinates":[138.535400391,-35.1142921448],"type":"Point"}
}