{
  "type": "Feature",
  "properties": {
    "addr:full":"3 Curdie St Cobden VIC 3266",
    "addr:housenumber":"3",
    "addr:postcode":"3266",
    "addr:street":"Curdie St",
    "iso:country":"AU",
    "sg:address":"3 Curdie St",
    "sg:city":"Cobden",
    "sg:classifiers":[
        {
            "category":"Fast Food",
            "type":"Food & Drink"
        }
    ],
    "sg:phone":"+61 3 5595 1026",
    "sg:postcode":"3266",
    "sg:province":"VIC",
    "sg:tags":[
        "away",
        "take"
    ],
    "wof:name":"Cobden Fish & Chip Shop",
    "wof:placetype":"venue"
},
  "geometry": {"coordinates":[143.07945251500001,-38.3288764954],"type":"Point"}
}