{
  "type": "Feature",
  "properties": {
    "iso:country":"AU",
    "sg:address":"16 Beddome St",
    "sg:city":"Sandy Bay",
    "sg:classifiers":[
        {
            "category":"Retail",
            "subcategory":"Driving School",
            "type":"Services"
        }
    ],
    "sg:phone":"+61 3 6225 3577",
    "sg:postcode":"7005",
    "sg:province":"TAS",
    "wof:name":"Tricias Driving School",
    "wof:placetype":"venue"
},
  "geometry": {"coordinates":[147.33314514200001,-42.9114952087],"type":"Point"}
}