{
  "type": "Feature",
  "properties": {
    "addr:full":"Level 1 Southbank House Stanley St Plaza South Brisbane QLD 4101",
    "addr:postcode":"4101",
    "addr:street":"Stanley St Plaza",
    "iso:country":"AU",
    "sg:address":"Level 1 Southbank House Stanley St",
    "sg:city":"Plaza South Brisbane",
    "sg:classifiers":[
        {
            "category":"Banks & Credit Unions",
            "subcategory":"Financial Services",
            "type":"Services"
        }
    ],
    "sg:phone":"+61 7 3844 4378",
    "sg:postcode":"4101",
    "sg:province":"QLD",
    "sg:tags":[
        "planning"
    ],
    "wof:name":"Craig Boyd",
    "wof:placetype":"venue"
},
  "geometry": {"coordinates":[153.022247314,-27.4780635834],"type":"Point"}
}