{
  "type": "Feature",
  "properties": {
    "addr:full":"98 Dangar St Armidale NSW 2350",
    "addr:housenumber":"98",
    "addr:postcode":"2350",
    "addr:street":"Dangar St",
    "iso:country":"AU",
    "sg:address":"98 Dangar St",
    "sg:city":"Armidale",
    "sg:classifiers":[
        {
            "category":"Shopping",
            "subcategory":"Jewelry",
            "type":"Retail Goods"
        }
    ],
    "sg:phone":"+61 2 6772 3966",
    "sg:postcode":"2350",
    "sg:province":"NSW",
    "sg:tags":[
        "jeweller"
    ],
    "wof:name":"Courtneys Jewellers",
    "wof:placetype":"venue"
},
  "geometry": {"coordinates":[151.66545105,-30.5133991241],"type":"Point"}
}