{
  "type": "Feature",
  "properties": {
    "addr:full":"10 Fletcher Rd Cranbourne South VIC 3977",
    "addr:housenumber":"10",
    "addr:postcode":"3977",
    "addr:street":"Fletcher Rd",
    "iso:country":"AU",
    "sg:address":"10 Fletcher Rd",
    "sg:city":"Cranbourne South",
    "sg:classifiers":[
        {
            "category":"Building & Trades",
            "subcategory":"Landscaping Services",
            "type":"Services"
        }
    ],
    "sg:phone":"+61 3 5998 2524",
    "sg:postcode":"3977",
    "sg:province":"VIC",
    "sg:tags":[
        "designer",
        "landscape",
        "contractor"
    ],
    "wof:name":"ADSIM Excavations",
    "wof:placetype":"venue"
},
  "geometry": {"coordinates":[145.267654419,-38.1558876038],"type":"Point"}
}