{
  "type": "Feature",
  "properties": {
    "addr:full":"33 Tilshead Rd Elizabeth North SA 5113",
    "addr:housenumber":"33",
    "addr:postcode":"5113",
    "addr:street":"Tilshead Rd",
    "iso:country":"AU",
    "sg:address":"33 Tilshead Rd",
    "sg:city":"Elizabeth North",
    "sg:classifiers":[
        {
            "category":"Personal",
            "subcategory":"Beauty Salon",
            "type":"Services"
        }
    ],
    "sg:phone":"+61 8 8287 0874",
    "sg:postcode":"5113",
    "sg:province":"SA",
    "sg:tags":[
        "hairdresser"
    ],
    "wof:name":"Hair Obsessionz",
    "wof:placetype":"venue"
},
  "geometry": {"coordinates":[138.67245483400001,-34.7063369751],"type":"Point"}
}