{
  "type": "Feature",
  "properties": {
    "iso:country":"AU",
    "sg:address":"15 Annie St",
    "sg:city":"Landsborough",
    "sg:classifiers":[
        {
            "category":"Utilities",
            "subcategory":"Electric",
            "type":"Services"
        }
    ],
    "sg:phone":"+61 7 5494 1438",
    "sg:postcode":"4550",
    "sg:province":"QLD",
    "sg:tags":[
        "electrical",
        "contractor"
    ],
    "wof:name":"Roest Electrical",
    "wof:placetype":"venue"
},
  "geometry": {"coordinates":[152.95555114699999,-26.8019638062],"type":"Point"}
}