{
  "type": "Feature",
  "properties": {
    "addr:full":"Salleys Corner Rd Exeter NSW 2579",
    "addr:postcode":"2579",
    "addr:street":"Corner Rd",
    "iso:country":"AU",
    "sg:address":"Salleys Corner Rd",
    "sg:city":"Exeter",
    "sg:classifiers":[
        {
            "category":"Farming",
            "subcategory":"Farm",
            "type":"Manufacturing & Wholesale Goods"
        }
    ],
    "sg:phone":"+61 2 4883 4301",
    "sg:postcode":"2579",
    "sg:province":"NSW",
    "sg:tags":[
        "farmer"
    ],
    "wof:name":"Burns Fisher Pty Limited",
    "wof:placetype":"venue"
},
  "geometry": {"coordinates":[150.29583740199999,-34.6107063293],"type":"Point"}
}