{
  "type": "Feature",
  "properties": {
    "addr:full":"Cnr Corio Quay Rd & Langdon St Geelong North VIC 3215",
    "addr:postcode":"3215",
    "addr:street":"Corio Quay Rd & Langdon St",
    "iso:country":"AU",
    "sg:address":"Cnr Corio Quay Rd & Langdon St",
    "sg:city":"Geelong North",
    "sg:classifiers":[
        {
            "category":"Professional",
            "subcategory":"Business Services",
            "type":"Services"
        }
    ],
    "sg:phone":"+61 3 5272 2966",
    "sg:postcode":"3215",
    "sg:province":"VIC",
    "sg:tags":[
        "exporter"
    ],
    "wof:name":"SPE Management Pty Ltd",
    "wof:placetype":"venue"
},
  "geometry": {"coordinates":[144.354568481,-38.11328125],"type":"Point"}
}