{
  "type": "Feature",
  "properties": {
    "addr:full":"155 rowe St Eastwood NSW 2122",
    "addr:housenumber":"155",
    "addr:postcode":"2122",
    "addr:street":"Rowe St",
    "iso:country":"AU",
    "sg:address":"155 rowe St",
    "sg:city":"Eastwood",
    "sg:classifiers":[
        {
            "category":"Shopping",
            "subcategory":"Mobile Phones",
            "type":"Retail Goods"
        }
    ],
    "sg:phone":"+61 2 9804 8766",
    "sg:postcode":"2122",
    "sg:province":"NSW",
    "sg:tags":[
        "telephone",
        "accessory"
    ],
    "wof:name":"Newtech Mobile Phone Centre",
    "wof:placetype":"venue"
},
  "geometry": {"coordinates":[151.076080322,-33.7928657532],"type":"Point"}
}