{
  "type": "Feature",
  "properties": {
    "iso:country":"AU",
    "sg:address":"Werribee Plaza Shopping Centre, Derrimut Rd",
    "sg:city":"Werribee",
    "sg:classifiers":[
        {
            "category":"Recreation",
            "subcategory":"Fishing",
            "type":"Entertainment"
        }
    ],
    "sg:phone":"+61 3 9749 0555",
    "sg:postcode":"3030",
    "sg:province":"VIC",
    "sg:tags":[
        "tackle"
    ],
    "wof:name":"Reel Screamer Bait & Tackle",
    "wof:placetype":"venue"
},
  "geometry": {"coordinates":[144.68042,-37.893932],"type":"Point"}
}