{
  "type": "Feature",
  "properties": {
    "addr:full":"Corner of Gympie Rd & Dixon St Strathpine QLD 4500",
    "addr:postcode":"4500",
    "addr:street":"Corner;Gympie Rd & Dixon St",
    "iso:country":"AU",
    "sg:address":"Corner of Gympie Rd & Dixon St",
    "sg:city":"Strathpine",
    "sg:classifiers":[
        {
            "category":"Real Estate",
            "subcategory":"Real Estate Agent",
            "type":"Services"
        }
    ],
    "sg:phone":"+61 7 3817 6666",
    "sg:postcode":"4500",
    "sg:province":"QLD",
    "sg:website":"http://www.daviddeane.com.au",
    "wof:name":"David Deane Real Estate",
    "wof:placetype":"venue"
},
  "geometry": {"coordinates":[152.98843383799999,-27.3024482727],"type":"Point"}
}