{
  "type": "Feature",
  "properties": {
    "iso:country":"AU",
    "sg:address":"46 Thorn St",
    "sg:city":"Kangaroo Point",
    "sg:classifiers":[
        {
            "category":"Education",
            "subcategory":"Dance Studio",
            "type":"Public Place"
        }
    ],
    "sg:phone":"+61 7 3392 1400",
    "sg:postcode":"4169",
    "sg:province":"QLD",
    "sg:tags":[
        "instruction",
        "language"
    ],
    "wof:name":"Shafston International College",
    "wof:placetype":"venue"
},
  "geometry": {"coordinates":[153.042144775,-27.4777355194],"type":"Point"}
}