{
  "type": "Feature",
  "properties": {
    "addr:full":"3 Coscia Ave Salisbury North SA 5108",
    "addr:housenumber":"3",
    "addr:postcode":"5108",
    "addr:street":"Coscia Ave",
    "iso:country":"AU",
    "sg:address":"3 Coscia Ave",
    "sg:city":"Salisbury North",
    "sg:classifiers":[
        {
            "category":"Building & Trades",
            "subcategory":"Cleaning & Sanitation",
            "type":"Services"
        }
    ],
    "sg:phone":"+61 8 8283 0414",
    "sg:postcode":"5108",
    "sg:province":"SA",
    "sg:tags":[
        "industrial",
        "commercial",
        "contractor"
    ],
    "wof:name":"Oz Cleaning & Consultancy Service Pty Ltd",
    "wof:placetype":"venue"
},
  "geometry": {"coordinates":[138.61810302699999,-34.7381210327],"type":"Point"}
}