{
  "type": "Feature",
  "properties": {
    "addr:full":"38 Station Ave McKinnon VIC 3204",
    "addr:housenumber":"38",
    "addr:postcode":"3204",
    "addr:street":"Station Ave",
    "iso:country":"AU",
    "sg:address":"38 Station Ave",
    "sg:city":"McKinnon",
    "sg:classifiers":[
        {
            "category":"Utilities",
            "subcategory":"Refuse",
            "type":"Services"
        }
    ],
    "sg:phone":"+61 3 9578 6745",
    "sg:postcode":"3204",
    "sg:province":"VIC",
    "sg:tags":[
        "remover",
        "rubbish"
    ],
    "wof:name":"Allans Rubbish Removals",
    "wof:placetype":"venue"
},
  "geometry": {"coordinates":[145.039658,-37.90818],"type":"Point"}
}