{
  "type": "Feature",
  "properties": {
    "addr:full":"Cnr Robert & Railway Sts Mudgeeraba QLD 4213",
    "addr:postcode":"4213",
    "addr:street":"Cnr",
    "iso:country":"AU",
    "sg:address":"Cnr Robert & Railway Sts",
    "sg:city":"Mudgeeraba",
    "sg:classifiers":[
        {
            "category":"Retail",
            "subcategory":"Veterinary Services",
            "type":"Services"
        }
    ],
    "sg:phone":"+61 7 5530 2204",
    "sg:postcode":"4213",
    "sg:province":"QLD",
    "sg:tags":[
        "surgeon"
    ],
    "wof:name":"Vetcall",
    "wof:placetype":"venue"
},
  "geometry": {"coordinates":[153.36459350600001,-28.0756034851],"type":"Point"}
}