{
  "type": "Feature",
  "properties": {
    "addr:full":"209 Jacobs Drv Sussex Inlet NSW 2540",
    "addr:housenumber":"209",
    "addr:postcode":"2540",
    "addr:street":"Jacobs Drv",
    "iso:country":"AU",
    "sg:address":"209 Jacobs Drv",
    "sg:city":"Sussex Inlet",
    "sg:classifiers":[
        {
            "category":"Travel",
            "subcategory":"Hotels & Motels",
            "type":"Entertainment"
        }
    ],
    "sg:phone":"+61 2 4441 2076",
    "sg:postcode":"2540",
    "sg:province":"NSW",
    "wof:name":"Sussex Shores RSL Units",
    "wof:placetype":"venue"
},
  "geometry": {"coordinates":[150.59512329099999,-35.1571464539],"type":"Point"}
}