{
  "type": "Feature",
  "properties": {
    "iso:country":"AU",
    "sg:address":"83 Avenue Rd",
    "sg:city":"Mosman",
    "sg:classifiers":[
        {
            "category":"Fast Food",
            "type":"Food & Drink"
        }
    ],
    "sg:phone":"+61 2 9969 0425",
    "sg:postcode":"2088",
    "sg:province":"NSW",
    "sg:tags":[
        "away",
        "take"
    ],
    "wof:name":"Avenue Gourmet Pizza",
    "wof:placetype":"venue"
},
  "geometry": {"coordinates":[151.238555908,-33.8320159912],"type":"Point"}
}