{
  "type": "Feature",
  "properties": {
    "addr:full":"Suite: 2 190 George St St Parramatta NSW 2150",
    "addr:housenumber":"190",
    "addr:postcode":"2150",
    "addr:street":"George St St",
    "iso:country":"AU",
    "sg:address":"Suite: 2 190 George St St",
    "sg:city":"Parramatta",
    "sg:classifiers":[
        {
            "category":"Professional",
            "subcategory":"Employment Agencies",
            "type":"Services"
        }
    ],
    "sg:phone":"+61 1300 760 099",
    "sg:postcode":"2150",
    "sg:province":"NSW",
    "wof:name":"Workplace Connect",
    "wof:placetype":"venue"
},
  "geometry": {"coordinates":[151.083984375,-33.848991394],"type":"Point"}
}