{
  "type": "Feature",
  "properties": {
    "addr:full":"543- 549 Bridge St Richmond VIC 3121",
    "addr:housenumber":"549",
    "addr:postcode":"3121",
    "addr:street":"Bridge St",
    "iso:country":"AU",
    "sg:address":"543- 549 Bridge St",
    "sg:city":"Richmond",
    "sg:classifiers":[
        {
            "category":"Autos & Motor Vehicles",
            "subcategory":"Fuel & Gas Station",
            "type":"Retail Goods"
        }
    ],
    "sg:phone":"+61 3 9428 6518",
    "sg:postcode":"3121",
    "sg:province":"VIC",
    "wof:name":"BP Australia Pty Ltd",
    "wof:placetype":"venue"
},
  "geometry": {"coordinates":[145.00926208499999,-37.8194541931],"type":"Point"}
}