{
  "type": "Feature",
  "properties": {
    "iso:country":"AU",
    "sg:address":"28 Binshaw Ave",
    "sg:city":"Byford",
    "sg:classifiers":[
        {
            "category":"Shopping",
            "subcategory":"Gifts & Souvenirs",
            "type":"Retail Goods"
        }
    ],
    "sg:phone":"+61 8 9525 4111",
    "sg:postcode":"6122",
    "sg:province":"WA",
    "sg:tags":[
        "print",
        "poster",
        "pictures"
    ],
    "wof:name":"Horseprints",
    "wof:placetype":"venue"
},
  "geometry": {"coordinates":[115.99299621599999,-32.2150382996],"type":"Point"}
}