{
  "type": "Feature",
  "properties": {
    "addr:full":"244 Anzac Ave Redcliffe QLD 4020",
    "addr:housenumber":"244",
    "addr:postcode":"4020",
    "addr:street":"Anzac Ave",
    "iso:country":"AU",
    "sg:address":"244 Anzac Ave",
    "sg:city":"Redcliffe",
    "sg:classifiers":[
        {
            "category":"Fast Food",
            "type":"Food & Drink"
        }
    ],
    "sg:phone":"+61 7 3284 4050",
    "sg:postcode":"4020",
    "sg:province":"QLD",
    "sg:tags":[
        "away",
        "take"
    ],
    "wof:name":"Eagle Boys Pizza",
    "wof:placetype":"venue"
},
  "geometry": {"coordinates":[153.08891299999999,-27.226831],"type":"Point"}
}