{
  "type": "Feature",
  "properties": {
    "addr:full":"4 Bulga Rd Dover Heights NSW 2030",
    "addr:housenumber":"4",
    "addr:postcode":"2030",
    "addr:street":"Bulga Rd",
    "iso:country":"AU",
    "sg:address":"4 Bulga Rd",
    "sg:city":"Dover Heights",
    "sg:classifiers":[
        {
            "category":"Travel",
            "subcategory":"Travel Agent",
            "type":"Entertainment"
        }
    ],
    "sg:phone":"+61 2 9371 7293",
    "sg:postcode":"2030",
    "sg:province":"NSW",
    "sg:tags":[
        "consultant"
    ],
    "wof:name":"Zipp Travel",
    "wof:placetype":"venue"
},
  "geometry": {"coordinates":[151.28205871599999,-33.8663291931],"type":"Point"}
}