{
  "type": "Feature",
  "properties": {
    "addr:full":"150 Sandy Bay Rd Sandy Bay TAS 7005",
    "addr:housenumber":"150",
    "addr:postcode":"7005",
    "addr:street":"Sandy Bay Rd",
    "iso:country":"AU",
    "sg:address":"150 Sandy Bay Rd",
    "sg:city":"Sandy Bay",
    "sg:classifiers":[
        {
            "category":"Fast Food",
            "type":"Food & Drink"
        }
    ],
    "sg:phone":"+61 3 6223 5410",
    "sg:postcode":"7005",
    "sg:province":"TAS",
    "sg:tags":[
        "away",
        "take"
    ],
    "wof:name":"Oriental Restaurant",
    "wof:placetype":"venue"
},
  "geometry": {"coordinates":[147.32621765100001,-42.8941612244],"type":"Point"}
}