{
  "type": "Feature",
  "properties": {
    "addr:full":"18 Mary St Gympie QLD 4570",
    "addr:housenumber":"18",
    "addr:postcode":"4570",
    "addr:street":"Mary St",
    "iso:country":"AU",
    "sg:address":"18 Mary St",
    "sg:city":"Gympie",
    "sg:classifiers":[
        {
            "category":"Shopping",
            "subcategory":"Music",
            "type":"Retail Goods"
        }
    ],
    "sg:phone":"+61 7 5482 7572",
    "sg:postcode":"4570",
    "sg:province":"QLD",
    "sg:tags":[
        "store"
    ],
    "wof:name":"Tommyrockers",
    "wof:placetype":"venue"
},
  "geometry": {"coordinates":[152.664916992,-26.1903305054],"type":"Point"}
}