{
  "type": "Feature",
  "properties": {
    "addr:full":"254 Boulder Rd Malaga WA 6090",
    "addr:housenumber":"254",
    "addr:postcode":"6090",
    "addr:street":"Boulder Rd",
    "iso:country":"AU",
    "sg:address":"254 Boulder Rd",
    "sg:city":"Malaga",
    "sg:classifiers":[
        {
            "category":"Building & Trades",
            "subcategory":"Construction",
            "type":"Services"
        }
    ],
    "sg:phone":"+61 8 9248 7993",
    "sg:postcode":"6090",
    "sg:province":"WA",
    "sg:tags":[
        "concrete",
        "paving"
    ],
    "wof:name":"GWC Agencies",
    "wof:placetype":"venue"
},
  "geometry": {"coordinates":[115.89994812,-31.8649234772],"type":"Point"}
}