{
  "type": "Feature",
  "properties": {
    "addr:full":"1/44 Buckingham St Surry Hills NSW 2010",
    "addr:housenumber":"/ 44",
    "addr:postcode":"2010",
    "addr:street":"Buckingham St",
    "iso:country":"AU",
    "sg:address":"1/44 Buckingham St",
    "sg:city":"Surry Hills",
    "sg:classifiers":[
        {
            "category":"Home & Garden",
            "subcategory":"Building Materials",
            "type":"Retail Goods"
        }
    ],
    "sg:phone":"+61 2 9699 3330",
    "sg:postcode":"2010",
    "sg:province":"NSW",
    "sg:tags":[
        "fitting",
        "door"
    ],
    "wof:name":"Halliday & Baillie Pty Ltd",
    "wof:placetype":"venue"
},
  "geometry": {"coordinates":[151.20762634299999,-33.8874511719],"type":"Point"}
}