{
  "type": "Feature",
  "properties": {
    "addr:full":"264 Wardell Rd Dulwich Hill NSW 2203",
    "addr:housenumber":"264",
    "addr:postcode":"2203",
    "addr:street":"Wardell Rd",
    "iso:country":"AU",
    "sg:address":"264 Wardell Rd",
    "sg:city":"Dulwich Hill",
    "sg:classifiers":[
        {
            "category":"Communications",
            "subcategory":"Film & Video Production",
            "type":"Services"
        }
    ],
    "sg:phone":"+61 2 9554 7013",
    "sg:postcode":"2203",
    "sg:province":"NSW",
    "sg:tags":[
        "dvd",
        "library"
    ],
    "wof:name":"Civic Video Pty Ltd",
    "wof:placetype":"venue"
},
  "geometry": {"coordinates":[151.144958,-33.907116],"type":"Point"}
}