{
  "type": "Feature",
  "properties": {
    "addr:full":"Presgrave Building, Little Collins St Melbourne VIC 3000",
    "addr:postcode":"3000",
    "addr:street":"Little Collins St",
    "iso:country":"AU",
    "sg:address":"Presgrave Building, Little Collins St",
    "sg:city":"Melbourne",
    "sg:classifiers":[
        {
            "category":"Shopping",
            "subcategory":"Clothing, Apparel, & Fashions",
            "type":"Retail Goods"
        }
    ],
    "sg:phone":"+61 3 9654 2018",
    "sg:postcode":"3000",
    "sg:province":"VIC",
    "sg:tags":[
        "accessory"
    ],
    "wof:name":"Oroton Pty Limited",
    "wof:placetype":"venue"
},
  "geometry": {"coordinates":[144.969604492,-37.8134613037],"type":"Point"}
}