{
  "type": "Feature",
  "properties": {
    "addr:full":"249 Brunswick St Fortitude Valley QLD 4006",
    "addr:housenumber":"249",
    "addr:postcode":"4006",
    "addr:street":"Brunswick St",
    "iso:country":"AU",
    "sg:address":"249 Brunswick St",
    "sg:city":"Fortitude Valley",
    "sg:classifiers":[
        {
            "category":"Personal",
            "subcategory":"Adult",
            "type":"Services"
        }
    ],
    "sg:phone":"+61 7 3252 5413",
    "sg:postcode":"4006",
    "sg:province":"QLD",
    "sg:tags":[
        "product"
    ],
    "wof:name":"Lush International",
    "wof:placetype":"venue"
},
  "geometry": {"coordinates":[153.03306579599999,-27.4571018219],"type":"Point"}
}