{
  "type": "Feature",
  "properties": {
    "addr:full":"Unit 3 115 Tinning St Brunswick VIC 3056",
    "addr:housenumber":"115",
    "addr:postcode":"3056",
    "addr:street":"Tinning St",
    "iso:country":"AU",
    "sg:address":"Unit 3 115 Tinning St",
    "sg:city":"Brunswick",
    "sg:classifiers":[
        {
            "category":"Shopping",
            "subcategory":"Musical Instruments",
            "type":"Retail Goods"
        }
    ],
    "sg:phone":"+61 412 148 906",
    "sg:postcode":"3056",
    "sg:province":"VIC",
    "sg:tags":[
        "musician",
        "agent"
    ],
    "wof:name":"Carroll Phil",
    "wof:placetype":"venue"
},
  "geometry": {"coordinates":[144.95588684099999,-37.7588233948],"type":"Point"}
}