{
  "type": "Feature",
  "properties": {
    "iso:country":"AU",
    "sg:address":"32 Birdwood St",
    "sg:city":"Mitcham",
    "sg:classifiers":[
        {
            "category":"Utilities",
            "subcategory":"Electric",
            "type":"Services"
        }
    ],
    "sg:phone":"+61 8 8271 5732",
    "sg:postcode":"5062",
    "sg:province":"SA",
    "sg:tags":[
        "electrical",
        "contractor"
    ],
    "wof:name":"Andrew Lawson Electrical",
    "wof:placetype":"venue"
},
  "geometry": {"coordinates":[138.622802734,-34.9748458862],"type":"Point"}
}