{
  "type": "Feature",
  "properties": {
    "iso:country":"AU",
    "sg:address":"33 Paling St",
    "sg:city":"Thornleigh",
    "sg:classifiers":[
        {
            "category":"Utilities",
            "subcategory":"Electric",
            "type":"Services"
        }
    ],
    "sg:phone":"+61 2 9980 8879",
    "sg:postcode":"2120",
    "sg:province":"NSW",
    "sg:tags":[
        "electrical",
        "contractor"
    ],
    "wof:name":"Beyond 2001 Electrics",
    "wof:placetype":"venue"
},
  "geometry": {"coordinates":[151.08059692399999,-33.7342567444],"type":"Point"}
}