{
  "type": "Feature",
  "properties": {
    "iso:country":"AU",
    "sg:address":"47 Dobell Drv",
    "sg:city":"Wangi Wangi",
    "sg:classifiers":[
        {
            "category":"Museum",
            "type":"Entertainment"
        }
    ],
    "sg:phone":"+61 2 4975 4115",
    "sg:postcode":"2267",
    "sg:province":"NSW",
    "wof:name":"Dobell House",
    "wof:placetype":"venue"
},
  "geometry": {"coordinates":[151.57914700000001,-33.071362],"type":"Point"}
}