{
  "type": "Feature",
  "properties": {
    "addr:full":"St James Hall Grey St Traralgon VIC 3844",
    "addr:postcode":"3844",
    "addr:street":"Grey St",
    "iso:country":"AU",
    "sg:address":"St James Hall Grey St",
    "sg:city":"Traralgon",
    "sg:classifiers":[
        {
            "category":"Recreation",
            "type":"Entertainment"
        }
    ],
    "sg:phone":"+61 3 5174 4632",
    "sg:postcode":"3844",
    "sg:province":"VIC",
    "sg:tags":[
        "children's",
        "play",
        "programme"
    ],
    "wof:name":"Gymbaroo",
    "wof:placetype":"venue"
},
  "geometry": {"coordinates":[146.53977966299999,-38.1934165955],"type":"Point"}
}