{
  "type": "Feature",
  "properties": {
    "addr:full":"572 Box Rd Jannali NSW 2226",
    "addr:housenumber":"572",
    "addr:postcode":"2226",
    "addr:street":"Box Rd",
    "iso:country":"AU",
    "sg:address":"572 Box Rd",
    "sg:city":"Jannali",
    "sg:classifiers":[
        {
            "category":"Travel",
            "subcategory":"Travel Agent",
            "type":"Entertainment"
        }
    ],
    "sg:phone":"+61 2 9528 3111",
    "sg:postcode":"2226",
    "sg:province":"NSW",
    "sg:tags":[
        "consultant"
    ],
    "wof:name":"Harvey World Travel",
    "wof:placetype":"venue"
},
  "geometry": {"coordinates":[151.06562805199999,-34.0163421631],"type":"Point"}
}