{
  "type": "Feature",
  "properties": {
    "addr:full":"Wiltshire House 25 Wiltshire St Salisbury SA 5108",
    "addr:housenumber":"25",
    "addr:postcode":"5108",
    "addr:street":"Wiltshire St",
    "iso:country":"AU",
    "sg:address":"Wiltshire House 25 Wiltshire St",
    "sg:city":"Salisbury",
    "sg:classifiers":[
        {
            "category":"Health Services",
            "subcategory":"Doctor",
            "type":"Services"
        }
    ],
    "sg:phone":"+61 8 8250 3732",
    "sg:postcode":"5108",
    "sg:province":"SA",
    "sg:tags":[
        "podiatrist"
    ],
    "wof:name":"Halliday Kaye",
    "wof:placetype":"venue"
},
  "geometry": {"coordinates":[138.64564514200001,-34.7633934021],"type":"Point"}
}