{
  "type": "Feature",
  "properties": {
    "addr:full":"390 The Entrance Rd Erina Heights NSW 2260",
    "addr:housenumber":"390",
    "addr:postcode":"2260",
    "addr:street":"The Entrance Rd",
    "iso:country":"AU",
    "sg:address":"390 The Entrance Rd",
    "sg:city":"Erina Heights",
    "sg:classifiers":[
        {
            "category":"Professional",
            "subcategory":"Art Services",
            "type":"Services"
        }
    ],
    "sg:phone":"+61 2 4367 5977",
    "sg:postcode":"2260",
    "sg:province":"NSW",
    "sg:tags":[
        "graphic",
        "designer"
    ],
    "wof:name":"Amazing Productions",
    "wof:placetype":"venue"
},
  "geometry": {"coordinates":[151.401657,-33.42564],"type":"Point"}
}