{
  "type": "Feature",
  "properties": {
    "iso:country":"AU",
    "sg:address":"Unit 6 37 Nicholson St",
    "sg:city":"Balmain East",
    "sg:classifiers":[
        {
            "category":"Organizations",
            "subcategory":"Professional Association",
            "type":"Services"
        }
    ],
    "sg:phone":"+61 2 9555 8060",
    "sg:postcode":"2041",
    "sg:province":"NSW",
    "sg:tags":[
        "web",
        "internet"
    ],
    "wof:name":"Egloo Technologies Pty Ltd",
    "wof:placetype":"venue"
},
  "geometry": {"coordinates":[151.192337,-33.8554],"type":"Point"}
}