{
  "type": "Feature",
  "properties": {
    "addr:full":"Lot 12 Galah Crs Singleton NSW 2330",
    "addr:postcode":"2330",
    "addr:street":"Galah Crs",
    "iso:country":"AU",
    "sg:address":"Lot 12 Galah Crs",
    "sg:city":"Singleton",
    "sg:classifiers":[
        {
            "category":"Wholesale",
            "subcategory":"Durable Goods & Equipment",
            "type":"Manufacturing & Wholesale Goods"
        }
    ],
    "sg:phone":"+61 2 6571 2313",
    "sg:postcode":"2330",
    "sg:province":"NSW",
    "sg:tags":[
        "abrasive",
        "blasting"
    ],
    "wof:name":"All Blast Mine Maintenance Pty Ltd",
    "wof:placetype":"venue"
},
  "geometry": {"coordinates":[151.14106799999999,-32.546879],"type":"Point"}
}