{
  "type": "Feature",
  "properties": {
    "addr:full":"15 Station St Roma QLD 4455",
    "addr:housenumber":"15",
    "addr:postcode":"4455",
    "addr:street":"Station St",
    "iso:country":"AU",
    "sg:address":"15 Station St",
    "sg:city":"Roma",
    "sg:classifiers":[
        {
            "category":"Building & Trades",
            "subcategory":"Construction",
            "type":"Services"
        }
    ],
    "sg:phone":"+61 7 4622 5139",
    "sg:postcode":"4455",
    "sg:province":"QLD",
    "sg:tags":[
        "contractor"
    ],
    "wof:name":"Ide Iseppi",
    "wof:placetype":"venue"
},
  "geometry": {"coordinates":[148.79124450699999,-26.5754871368],"type":"Point"}
}