{
  "type": "Feature",
  "properties": {
    "iso:country":"AU",
    "sg:address":"2450 Point Nepean Rd",
    "sg:city":"Rye",
    "sg:classifiers":[
        {
            "category":"Recreation",
            "subcategory":"Boat Charter",
            "type":"Entertainment"
        }
    ],
    "sg:phone":"+61 417 516 406",
    "sg:postcode":"3941",
    "sg:province":"VIC",
    "sg:tags":[
        "hire",
        "drive"
    ],
    "wof:name":"Rye Boat Hire",
    "wof:placetype":"venue"
},
  "geometry": {"coordinates":[144.81951904300001,-38.3700942993],"type":"Point"}
}