{
  "type": "Feature",
  "properties": {
    "iso:country":"AU",
    "sg:address":"40 smith Drv",
    "sg:city":"Ballina",
    "sg:classifiers":[
        {
            "category":"Wholesale",
            "subcategory":"Electrical",
            "type":"Manufacturing & Wholesale Goods"
        }
    ],
    "sg:phone":"+61 402 943 117",
    "sg:postcode":"2478",
    "sg:province":"NSW",
    "sg:tags":[
        "equipment",
        "testing",
        "electronic",
        "electric"
    ],
    "wof:name":"Dial a Hubby",
    "wof:placetype":"venue"
},
  "geometry": {"coordinates":[153.51600647000001,-28.8649654388],"type":"Point"}
}