{
  "type": "Feature",
  "properties": {
    "addr:full":"167 Arden St Coogee NSW 2034",
    "addr:housenumber":"167",
    "addr:postcode":"2034",
    "addr:street":"Arden St",
    "iso:country":"AU",
    "sg:address":"167 Arden St",
    "sg:city":"Coogee",
    "sg:classifiers":[
        {
            "category":"Retail",
            "subcategory":"Laundry & Dry Cleaning",
            "type":"Services"
        }
    ],
    "sg:phone":"+61 2 9398 2558",
    "sg:postcode":"2034",
    "sg:province":"NSW",
    "sg:tags":[
        "ironing"
    ],
    "wof:name":"Eastern Suburbs Ironing Service",
    "wof:placetype":"venue"
},
  "geometry": {"coordinates":[151.257522583,-33.9179916382],"type":"Point"}
}