{
  "type": "Feature",
  "properties": {
    "iso:country":"AU",
    "sg:address":"29 Collier St",
    "sg:city":"Griffith",
    "sg:classifiers":[
        {
            "category":"Retail",
            "subcategory":"Auto Repair",
            "type":"Services"
        }
    ],
    "sg:phone":"+61 2 6962 6162",
    "sg:postcode":"2680",
    "sg:province":"NSW",
    "sg:tags":[
        "electrical"
    ],
    "wof:name":"David Gras Auto Electrics Pty Ltd",
    "wof:placetype":"venue"
},
  "geometry": {"coordinates":[146.070374,-34.290684],"type":"Point"}
}