{
  "type": "Feature",
  "properties": {
    "iso:country":"AU",
    "sg:address":"Unit 6/111- 113 William Angliss Drv",
    "sg:city":"Laverton North",
    "sg:classifiers":[
        {
            "category":"Professional",
            "subcategory":"Employment Agencies",
            "type":"Services"
        }
    ],
    "sg:phone":"+61 1300 936 723",
    "sg:postcode":"3026",
    "sg:province":"VIC",
    "sg:tags":[
        "hire",
        "labour",
        "contractor"
    ],
    "wof:name":"Workforce International Pty. Ltd.",
    "wof:placetype":"venue"
},
  "geometry": {"coordinates":[144.781158,-37.816753],"type":"Point"}
}