{
  "type": "Feature",
  "properties": {
    "addr:full":"Level 2 75- 79 Watton St Werribee VIC 3030",
    "addr:housenumber":"75 79",
    "addr:postcode":"3030",
    "addr:street":"Watton St",
    "iso:country":"AU",
    "sg:address":"Level 2 75- 79 Watton St",
    "sg:city":"Werribee",
    "sg:classifiers":[
        {
            "category":"Personal",
            "subcategory":"Beauty Salon",
            "type":"Services"
        }
    ],
    "sg:phone":"+61 1800 444 333",
    "sg:postcode":"3030",
    "sg:province":"VIC",
    "wof:name":"Lanzer Daniel Dr",
    "wof:placetype":"venue"
},
  "geometry": {"coordinates":[144.66111799999999,-37.901573],"type":"Point"}
}