{
  "type": "Feature",
  "properties": {
    "iso:country":"AU",
    "sg:address":"2 Bridge Rd",
    "sg:city":"Launceston",
    "sg:classifiers":[
        {
            "category":"Personal",
            "subcategory":"Beauty Salon",
            "type":"Services"
        }
    ],
    "sg:phone":"+61 3 6334 5070",
    "sg:postcode":"7250",
    "sg:province":"TAS",
    "sg:tags":[
        "hairdresser"
    ],
    "wof:name":"Enigma Hair Design",
    "wof:placetype":"venue"
},
  "geometry": {"coordinates":[147.12872314399999,-41.4404029846],"type":"Point"}
}