{
  "type": "Feature",
  "properties": {
    "iso:country":"AU",
    "sg:address":"82-84 Mataram Rd",
    "sg:city":"Woongarrah",
    "sg:classifiers":[
        {
            "category":"Education",
            "subcategory":"Kindergarten",
            "type":"Public Place"
        }
    ],
    "sg:phone":"+61 2 4392 4770",
    "sg:postcode":"2259",
    "sg:province":"NSW",
    "sg:tags":[
        "pre-schools"
    ],
    "wof:name":"Kids Academy Warnervale",
    "wof:placetype":"venue"
},
  "geometry": {"coordinates":[151.485397339,-33.242767334],"type":"Point"}
}