{
  "type": "Feature",
  "properties": {
    "addr:full":"253 Wattleup Rd Wattleup WA 6166",
    "addr:housenumber":"253",
    "addr:postcode":"6166",
    "addr:street":"Wattleup Rd",
    "iso:country":"AU",
    "sg:address":"253 Wattleup Rd",
    "sg:city":"Wattleup",
    "sg:classifiers":[
        {
            "category":"Professional",
            "subcategory":"Testing Lab",
            "type":"Services"
        }
    ],
    "sg:phone":"+61 8 9437 1637",
    "sg:postcode":"6166",
    "sg:province":"WA",
    "sg:tags":[
        "soil",
        "investigation"
    ],
    "wof:name":"J & S Drilling",
    "wof:placetype":"venue"
},
  "geometry": {"coordinates":[115.820671,-32.177399],"type":"Point"}
}