{
  "type": "Feature",
  "properties": {
    "addr:full":"L 5/ 221-229 Crown St Wollongong NSW 2500",
    "addr:housenumber":"/ 221-229",
    "addr:postcode":"2500",
    "addr:street":"Crown St",
    "iso:country":"AU",
    "sg:address":"L 5/ 221-229 Crown St",
    "sg:city":"Wollongong",
    "sg:classifiers":[
        {
            "category":"Banks & Credit Unions",
            "subcategory":"Financial Services",
            "type":"Services"
        }
    ],
    "sg:phone":"+61 2 4225 0777",
    "sg:postcode":"2500",
    "sg:province":"NSW",
    "sg:tags":[
        "annuity",
        "rollover",
        "superannuation",
        "consultant"
    ],
    "wof:name":"Charter Financial Planning",
    "wof:placetype":"venue"
},
  "geometry": {"coordinates":[150.89239499999999,-34.425083],"type":"Point"}
}