{
  "type": "Feature",
  "properties": {
    "iso:country":"AU",
    "sg:address":"219 Railway Pde",
    "sg:city":"Maylands",
    "sg:classifiers":[
        {
            "category":"Professional",
            "subcategory":"Employment Agencies",
            "type":"Services"
        }
    ],
    "sg:phone":"+61 1300 855 627",
    "sg:postcode":"6051",
    "sg:province":"WA",
    "wof:name":"Westnet Employment Services Inc",
    "wof:placetype":"venue"
},
  "geometry": {"coordinates":[115.88745900000001,-31.93084],"type":"Point"}
}