{
  "type": "Feature",
  "properties": {
    "addr:full":"424 Blackburn Rd Glen Waverley VIC 3150",
    "addr:housenumber":"424",
    "addr:postcode":"3150",
    "addr:street":"Blackburn Rd",
    "iso:country":"AU",
    "sg:address":"424 Blackburn Rd",
    "sg:city":"Glen Waverley",
    "sg:classifiers":[
        {
            "category":"Health Services",
            "subcategory":"Chiropractor",
            "type":"Services"
        }
    ],
    "sg:phone":"+61 3 9803 7520",
    "sg:postcode":"3150",
    "sg:province":"VIC",
    "wof:name":"Pinewood Chiropractic Clinic",
    "wof:placetype":"venue"
},
  "geometry": {"coordinates":[145.1456604,-37.8878631592],"type":"Point"}
}