{
  "type": "Feature",
  "properties": {
    "addr:full":"PO Box 202 Burnside SA 5066",
    "addr:postcode":"5066",
    "iso:country":"AU",
    "sg:address":"PO Box 202",
    "sg:city":"Burnside",
    "sg:classifiers":[
        {
            "category":"Food & Beverages",
            "subcategory":"Fruits & Vegetables",
            "type":"Retail Goods"
        }
    ],
    "sg:phone":"+61 419 820 206",
    "sg:postcode":"5066",
    "sg:province":"SA",
    "sg:tags":[
        "consultant",
        "catering"
    ],
    "wof:name":"Kate Swaffer's Katering",
    "wof:placetype":"venue"
},
  "geometry": {"coordinates":[138.65997314399999,-34.9359016418],"type":"Point"}
}