{
  "type": "Feature",
  "properties": {
    "addr:full":"1046 High St Armadale VIC 3143",
    "addr:housenumber":"1046",
    "addr:postcode":"3143",
    "addr:street":"High St",
    "iso:country":"AU",
    "sg:address":"1046 High St",
    "sg:city":"Armadale",
    "sg:classifiers":[
        {
            "category":"Arts & Performance",
            "subcategory":"Art Gallery",
            "type":"Entertainment"
        }
    ],
    "sg:phone":"+61 3 9509 8292",
    "sg:postcode":"3143",
    "sg:province":"VIC",
    "wof:name":"Libby Edwards Galleries",
    "wof:placetype":"venue"
},
  "geometry": {"coordinates":[145.02220153799999,-37.8558044434],"type":"Point"}
}