{
  "type": "Feature",
  "properties": {
    "addr:full":"Canterbury Rd Bankstown NSW 2200",
    "addr:postcode":"2200",
    "addr:street":"Canterbury Rd",
    "iso:country":"AU",
    "sg:address":"Canterbury Rd",
    "sg:city":"Bankstown",
    "sg:classifiers":[
        {
            "category":"Wholesale",
            "subcategory":"Photographic Equipment",
            "type":"Manufacturing & Wholesale Goods"
        }
    ],
    "sg:phone":"+61 2 9790 5777",
    "sg:postcode":"2200",
    "sg:province":"NSW",
    "sg:tags":[
        "machinery",
        "plastic"
    ],
    "wof:name":"Wittmann Battenfeld Australia Pty Ltd",
    "wof:placetype":"venue"
},
  "geometry": {"coordinates":[151.02623,-33.934055],"type":"Point"}
}