{
  "type": "Feature",
  "properties": {
    "addr:full":"198 Pitt St Sydney NSW 2000",
    "addr:housenumber":"198",
    "addr:postcode":"2000",
    "addr:street":"Pitt St",
    "iso:country":"AU",
    "sg:address":"198 Pitt St",
    "sg:city":"Sydney",
    "sg:classifiers":[
        {
            "category":"Health Services",
            "subcategory":"Doctor",
            "type":"Services"
        }
    ],
    "sg:phone":"+61 2 9267 9421",
    "sg:postcode":"2000",
    "sg:province":"NSW",
    "sg:tags":[
        "medical",
        "practitioner"
    ],
    "wof:name":"Campion F J",
    "wof:placetype":"venue"
},
  "geometry": {"coordinates":[151.20835876500001,-33.8710708618],"type":"Point"}
}