{
  "type": "Feature",
  "properties": {
    "iso:country":"AU",
    "sg:address":"2 Union St",
    "sg:city":"Kilmore",
    "sg:classifiers":[
        {
            "category":"Professional",
            "subcategory":"Business Services",
            "type":"Services"
        }
    ],
    "sg:phone":"+61 3 5782 0596",
    "sg:postcode":"3764",
    "sg:province":"VIC",
    "sg:tags":[
        "management",
        "event"
    ],
    "wof:name":"Cygnet Productions (Melbourne) Pty Ltd",
    "wof:placetype":"venue"
},
  "geometry": {"coordinates":[144.94639587399999,-37.2922096252],"type":"Point"}
}