{
  "type": "Feature",
  "properties": {
    "iso:country":"AU",
    "sg:address":"Seal Rocks Rd",
    "sg:city":"Bungwahl",
    "sg:classifiers":[
        {
            "category":"Wholesale",
            "subcategory":"Seafood",
            "type":"Manufacturing & Wholesale Goods"
        }
    ],
    "sg:phone":"+61 2 4997 6117",
    "sg:postcode":"2423",
    "sg:province":"NSW",
    "sg:tags":[
        "fish"
    ],
    "wof:name":"Commercial Fishermen's Co-Operative Ltd",
    "wof:placetype":"venue"
},
  "geometry": {"coordinates":[152.44703699999999,-32.388142],"type":"Point"}
}