{
  "type": "Feature",
  "properties": {
    "addr:full":"Shop 2/ 558B Pennant Hills Rd West Pennant Hills NSW 2125",
    "addr:housenumber":"shop 2 / 558b",
    "addr:postcode":"2125",
    "addr:street":"Pennant Hills Rd",
    "iso:country":"AU",
    "sg:address":"Shop 2/ 558B Pennant Hills Rd",
    "sg:city":"West Pennant Hills",
    "sg:classifiers":[
        {
            "category":"Personal",
            "subcategory":"Beauty Salon",
            "type":"Services"
        }
    ],
    "sg:phone":"+61 2 9875 3232",
    "sg:postcode":"2125",
    "sg:province":"NSW",
    "sg:tags":[
        "hairdresser"
    ],
    "wof:name":"Foiled Again Hair Design",
    "wof:placetype":"venue"
},
  "geometry": {"coordinates":[151.04745483400001,-33.7538948059],"type":"Point"}
}