{
  "type": "Feature",
  "properties": {
    "addr:full":"253 Sturt St Adelaide SA 5000",
    "addr:housenumber":"253",
    "addr:postcode":"5000",
    "addr:street":"Sturt St",
    "iso:country":"AU",
    "sg:address":"253 Sturt St",
    "sg:city":"Adelaide",
    "sg:classifiers":[
        {
            "category":"Professional",
            "subcategory":"Accounting & Tax Preparation",
            "type":"Services"
        }
    ],
    "sg:phone":"+61 8 8211 7000",
    "sg:postcode":"5000",
    "sg:province":"SA",
    "sg:tags":[
        "accountant",
        "auditor"
    ],
    "wof:name":"Sturt Street Accountants Pty Ltd",
    "wof:placetype":"venue"
},
  "geometry": {"coordinates":[138.588912964,-34.9336166382],"type":"Point"}
}