{
  "type": "Feature",
  "properties": {
    "iso:country":"AU",
    "sg:address":"PO Box 224",
    "sg:city":"Wurtulla",
    "sg:classifiers":[
        {
            "category":"Professional",
            "subcategory":"Business Services",
            "type":"Services"
        }
    ],
    "sg:phone":"+61 7 5493 5033",
    "sg:postcode":"4575",
    "sg:province":"QLD",
    "sg:tags":[
        "management",
        "event"
    ],
    "wof:name":"Dynamique Events",
    "wof:placetype":"venue"
},
  "geometry": {"coordinates":[153.124146,-26.760639],"type":"Point"}
}