{
  "type": "Feature",
  "properties": {
    "addr:full":"0 0 St Victoria Park WA 6100",
    "addr:housenumber":"0",
    "addr:postcode":"6100",
    "addr:street":"St",
    "iso:country":"AU",
    "sg:address":"0 0 St",
    "sg:city":"Victoria Park",
    "sg:classifiers":[
        {
            "category":"Home & Garden",
            "subcategory":"Building Materials",
            "type":"Retail Goods"
        }
    ],
    "sg:phone":"+61 407 878 279",
    "sg:postcode":"6100",
    "sg:province":"WA",
    "sg:tags":[
        "lawn",
        "cutting",
        "maintenance"
    ],
    "wof:name":"Same Day Mowing",
    "wof:placetype":"venue"
},
  "geometry": {"coordinates":[115.89881133999999,-31.9802436829],"type":"Point"}
}