{
  "type": "Feature",
  "properties": {
    "iso:country":"AU",
    "sg:address":"89 John St",
    "sg:city":"Salisbury",
    "sg:classifiers":[
        {
            "category":"Banks & Credit Unions",
            "subcategory":"Financial Services",
            "type":"Services"
        }
    ],
    "sg:phone":"+61 1300 555 888",
    "sg:postcode":"5108",
    "sg:province":"SA",
    "sg:tags":[
        "loan",
        "finance",
        "mortgage"
    ],
    "wof:name":"AAA Mortgage Solutions",
    "wof:placetype":"venue"
},
  "geometry": {"coordinates":[138.64772033700001,-34.7616920471],"type":"Point"}
}