{
  "type": "Feature",
  "properties": {
    "iso:country":"AU",
    "sg:address":"Jack Parr St",
    "sg:city":"Mundubbera",
    "sg:classifiers":[
        {
            "category":"Juice Bar",
            "subcategory":"None",
            "type":"Food & Drink"
        }
    ],
    "sg:phone":"+61 7 4165 4722",
    "sg:postcode":"4626",
    "sg:province":"QLD",
    "sg:tags":[
        "merchant",
        "fruit",
        "processor"
    ],
    "wof:name":"Central Burnett Fruit Processors Co-Op Association Ltd",
    "wof:placetype":"venue"
},
  "geometry": {"coordinates":[151.313782,-25.594742],"type":"Point"}
}