{
  "type": "Feature",
  "properties": {
    "addr:full":"46 Clendon Rd Toorak VIC 3142",
    "addr:housenumber":"46",
    "addr:postcode":"3142",
    "addr:street":"Clendon Rd",
    "iso:country":"AU",
    "sg:address":"46 Clendon Rd",
    "sg:city":"Toorak",
    "sg:classifiers":[
        {
            "category":"Health Services",
            "subcategory":"Chiropractor",
            "type":"Services"
        }
    ],
    "sg:phone":"+61 3 9826 9099",
    "sg:postcode":"3142",
    "sg:province":"VIC",
    "wof:name":"The Oaks Chiropractic Clinic",
    "wof:placetype":"venue"
},
  "geometry": {"coordinates":[145.01617431599999,-37.8469619751],"type":"Point"}
}