{
  "type": "Feature",
  "properties": {
    "addr:full":"45 Three Chain Rd South Lismore NSW 2480",
    "addr:housenumber":"45",
    "addr:postcode":"2480",
    "addr:street":"Three Chain Rd South",
    "iso:country":"AU",
    "sg:address":"45 Three Chain Rd",
    "sg:city":"South Lismore",
    "sg:classifiers":[
        {
            "category":"Professional",
            "type":"Services"
        }
    ],
    "sg:phone":"+61 2 6621 3334",
    "sg:postcode":"2480",
    "sg:province":"NSW",
    "sg:tags":[
        "coating",
        "powder"
    ],
    "wof:name":"Lismore House Spraying",
    "wof:placetype":"venue"
},
  "geometry": {"coordinates":[153.26214599599999,-28.8207263947],"type":"Point"}
}