{
  "type": "Feature",
  "properties": {
    "addr:full":"318 Learmonth St Buninyong VIC 3357",
    "addr:housenumber":"318",
    "addr:postcode":"3357",
    "addr:street":"Learmonth St",
    "iso:country":"AU",
    "sg:address":"318 Learmonth St",
    "sg:city":"Buninyong",
    "sg:classifiers":[
        {
            "category":"Food & Beverages",
            "subcategory":"Bakery",
            "type":"Retail Goods"
        }
    ],
    "sg:phone":"+61 3 5341 2199",
    "sg:postcode":"3357",
    "sg:province":"VIC",
    "sg:tags":[
        "cake",
        "shop",
        "pastry"
    ],
    "wof:name":"Buninyong Bakehouse",
    "wof:placetype":"venue"
},
  "geometry": {"coordinates":[143.884964,-37.650154],"type":"Point"}
}