{
  "type": "Feature",
  "properties": {
    "iso:country":"AU",
    "sg:address":"73 Gulfview Rd",
    "sg:city":"Blackwood",
    "sg:classifiers":[
        {
            "category":"Utilities",
            "subcategory":"Electric",
            "type":"Services"
        }
    ],
    "sg:phone":"+61 8 8278 2084",
    "sg:postcode":"5051",
    "sg:province":"SA",
    "sg:tags":[
        "electrical",
        "contractor"
    ],
    "wof:name":"Instalect Pty Ltd",
    "wof:placetype":"venue"
},
  "geometry": {"coordinates":[138.610336,-35.015171],"type":"Point"}
}