{
  "type": "Feature",
  "properties": {
    "addr:full":"Suite 4/ 82 Reserve St Wembley WA 6014",
    "addr:housenumber":"82",
    "addr:postcode":"6014",
    "addr:street":"Reserve St",
    "iso:country":"AU",
    "sg:address":"Suite 4/ 82 Reserve St",
    "sg:city":"Wembley",
    "sg:classifiers":[
        {
            "category":"Health Services",
            "subcategory":"Health Practitioner",
            "type":"Services"
        }
    ],
    "sg:phone":"+61 1300 558 682",
    "sg:postcode":"6014",
    "sg:province":"WA",
    "sg:tags":[
        "psychologist"
    ],
    "wof:name":"Carol Smith",
    "wof:placetype":"venue"
},
  "geometry": {"coordinates":[115.806739807,-31.931432724],"type":"Point"}
}