{
  "type": "Feature",
  "properties": {
    "addr:full":"24 Nungamoora St Hallett Cove SA 5158",
    "addr:housenumber":"24",
    "addr:postcode":"5158",
    "addr:street":"Nungamoora St",
    "iso:country":"AU",
    "sg:address":"24 Nungamoora St",
    "sg:city":"Hallett Cove",
    "sg:classifiers":[
        {
            "category":"Health Services",
            "subcategory":"Health Practitioner",
            "type":"Services"
        }
    ],
    "sg:phone":"+61 414 566 618",
    "sg:postcode":"5158",
    "sg:province":"SA",
    "sg:tags":[
        "reiki"
    ],
    "wof:name":"Ms J Rose",
    "wof:placetype":"venue"
},
  "geometry": {"coordinates":[138.50555419899999,-35.0610237122],"type":"Point"}
}