{
  "type": "Feature",
  "properties": {
    "iso:country":"AU",
    "sg:address":"174 Bridport St",
    "sg:city":"Albert Park",
    "sg:classifiers":[
        {
            "category":"Shopping",
            "subcategory":"Clothing, Apparel, & Fashions",
            "type":"Retail Goods"
        }
    ],
    "sg:phone":"+61 3 9699 4240",
    "sg:postcode":"3206",
    "sg:province":"VIC",
    "sg:tags":[
        "boutique"
    ],
    "wof:name":"Essence Boutique",
    "wof:placetype":"venue"
},
  "geometry": {"coordinates":[144.95469700000001,-37.840836],"type":"Point"}
}