{
  "type": "Feature",
  "properties": {
    "addr:full":"159 Villa St Yeronga QLD 4104",
    "addr:housenumber":"159",
    "addr:postcode":"4104",
    "addr:street":"Villa St",
    "iso:country":"AU",
    "sg:address":"159 Villa St",
    "sg:city":"Yeronga",
    "sg:classifiers":[
        {
            "category":"Education",
            "subcategory":"School",
            "type":"Public Place"
        }
    ],
    "sg:phone":"+61 7 3249 1400",
    "sg:postcode":"4104",
    "sg:province":"QLD",
    "sg:tags":[
        "state",
        "except",
        "nsw"
    ],
    "wof:name":"Yeronga High",
    "wof:placetype":"venue"
},
  "geometry": {"coordinates":[153.022872925,-27.5173931122],"type":"Point"}
}