{
  "type": "Feature",
  "properties": {
    "addr:full":"29 Eurong St Wahroonga NSW 2076",
    "addr:housenumber":"29",
    "addr:postcode":"2076",
    "addr:street":"Eurong St",
    "iso:country":"AU",
    "sg:address":"29 Eurong St",
    "sg:city":"Wahroonga",
    "sg:classifiers":[
        {
            "category":"Professional",
            "subcategory":"Accounting & Tax Preparation",
            "type":"Services"
        }
    ],
    "sg:phone":"+61 2 9487 5305",
    "sg:postcode":"2076",
    "sg:province":"NSW",
    "sg:tags":[
        "consultant",
        "taxation"
    ],
    "wof:name":"Lofay Les B.Bus Asa",
    "wof:placetype":"venue"
},
  "geometry": {"coordinates":[151.102615356,-33.7403144836],"type":"Point"}
}