{
  "type": "Feature",
  "properties": {
    "addr:full":"PO Box 3027 Shelley WA 6148",
    "addr:postcode":"6148",
    "iso:country":"AU",
    "sg:address":"PO Box 3027",
    "sg:city":"Shelley",
    "sg:classifiers":[
        {
            "category":"Mining & Drilling",
            "type":"Manufacturing & Wholesale Goods"
        }
    ],
    "sg:phone":"+61 8 9457 0257",
    "sg:postcode":"6148",
    "sg:province":"WA",
    "sg:tags":[
        "concrete",
        "breaking",
        "grinding",
        "sawing"
    ],
    "wof:name":"Cutting Concrete",
    "wof:placetype":"venue"
},
  "geometry": {"coordinates":[115.881927,-32.034382],"type":"Point"}
}