{
  "type": "Feature",
  "properties": {
    "iso:country":"AU",
    "sg:address":"38 South St",
    "sg:city":"Manilla",
    "sg:classifiers":[
        {
            "category":"Autos & Motor Vehicles",
            "subcategory":"Boat Sales",
            "type":"Retail Goods"
        }
    ],
    "sg:phone":"+61 1800 001 185",
    "sg:postcode":"2346",
    "sg:province":"NSW",
    "sg:tags":[
        "yacht"
    ],
    "wof:name":"Magnum Boats",
    "wof:placetype":"venue"
},
  "geometry": {"coordinates":[150.727020264,-30.7569065094],"type":"Point"}
}