{
  "type": "Feature",
  "properties": {
    "iso:country":"AU",
    "sg:address":"Ste 304 Platinum Bldg, Ilya Ave",
    "sg:city":"Erina",
    "sg:classifiers":[
        {
            "category":"Banks & Credit Unions",
            "subcategory":"Financial Services",
            "type":"Services"
        }
    ],
    "sg:phone":"+61 2 4365 3666",
    "sg:postcode":"2250",
    "sg:province":"NSW",
    "sg:tags":[
        "planning"
    ],
    "wof:name":"CCFM Financial Group",
    "wof:placetype":"venue"
},
  "geometry": {"coordinates":[151.38435363799999,-33.4397850037],"type":"Point"}
}