{
  "type": "Feature",
  "properties": {
    "addr:full":"Level 16/ 251 Adelaide Tce Perth WA 6000",
    "addr:housenumber":"/ 251",
    "addr:postcode":"6000",
    "addr:street":"Adelaide Tce",
    "iso:country":"AU",
    "sg:address":"Level 16/ 251 Adelaide Tce",
    "sg:city":"Perth",
    "sg:classifiers":[
        {
            "category":"Health Services",
            "subcategory":"Health Practitioner",
            "type":"Services"
        }
    ],
    "sg:phone":"+61 8 9225 4522",
    "sg:postcode":"6000",
    "sg:province":"WA",
    "sg:tags":[
        "psychologist"
    ],
    "wof:name":"OSA Group",
    "wof:placetype":"venue"
},
  "geometry": {"coordinates":[115.86605835,-31.958026886],"type":"Point"}
}