{
  "type": "Feature",
  "properties": {
    "iso:country":"AU",
    "sg:address":"22/ 465 Glebe Point Rd",
    "sg:city":"Glebe",
    "sg:classifiers":[
        {
            "category":"Manufacturing",
            "subcategory":"Furniture",
            "type":"Manufacturing & Wholesale Goods"
        }
    ],
    "sg:phone":"+61 2 9518 7952",
    "sg:postcode":"2037",
    "sg:province":"NSW",
    "sg:tags":[
        "builder",
        "designer",
        "custom"
    ],
    "wof:name":"Aximo",
    "wof:placetype":"venue"
},
  "geometry": {"coordinates":[151.181396484,-33.8724975586],"type":"Point"}
}