{
  "type": "Feature",
  "properties": {
    "addr:full":"24 Hillside Rd Newport NSW 2106",
    "addr:housenumber":"24",
    "addr:postcode":"2106",
    "addr:street":"Hillside Rd",
    "iso:country":"AU",
    "sg:address":"24 Hillside Rd",
    "sg:city":"Newport",
    "sg:classifiers":[
        {
            "category":"Building & Trades",
            "subcategory":"Construction",
            "type":"Services"
        }
    ],
    "sg:phone":"+61 410 459 677",
    "sg:postcode":"2106",
    "sg:province":"NSW",
    "sg:tags":[
        "joiner",
        "carpenter"
    ],
    "wof:name":"Schommy Brothers Projects",
    "wof:placetype":"venue"
},
  "geometry": {"coordinates":[151.31997680699999,-33.6497306824],"type":"Point"}
}