{
  "type": "Feature",
  "properties": {
    "addr:full":"2 Yale St Wendouree VIC 3355",
    "addr:housenumber":"2",
    "addr:postcode":"3355",
    "addr:street":"Yale St",
    "iso:country":"AU",
    "sg:address":"2 Yale St",
    "sg:city":"Wendouree",
    "sg:classifiers":[
        {
            "category":"Professional",
            "subcategory":"Art Services",
            "type":"Services"
        }
    ],
    "sg:phone":"+61 3 5339 6130",
    "sg:postcode":"3355",
    "sg:province":"VIC",
    "sg:tags":[
        "artist"
    ],
    "wof:name":"Ken McCully",
    "wof:placetype":"venue"
},
  "geometry": {"coordinates":[143.83764600000001,-37.529434],"type":"Point"}
}