{
  "type": "Feature",
  "properties": {
    "iso:country":"AU",
    "sg:address":"21 St Edmonds Rd",
    "sg:city":"Prahran",
    "sg:classifiers":[
        {
            "category":"Food & Beverages",
            "subcategory":"Bakery",
            "type":"Retail Goods"
        }
    ],
    "sg:phone":"+61 3 9510 6805",
    "sg:postcode":"3181",
    "sg:province":"VIC",
    "sg:tags":[
        "baker"
    ],
    "wof:name":"Egg Unlimited",
    "wof:placetype":"venue"
},
  "geometry": {"coordinates":[144.99159240700001,-37.8504257202],"type":"Point"}
}