{
  "type": "Feature",
  "properties": {
    "iso:country":"AU",
    "sg:address":"41- 43 Mooreville Rd",
    "sg:city":"Burnie",
    "sg:classifiers":[
        {
            "category":"Education",
            "subcategory":"School",
            "type":"Public Place"
        }
    ],
    "sg:phone":"+61 3 6433 3611",
    "sg:postcode":"7320",
    "sg:province":"TAS",
    "sg:tags":[
        "co-educational"
    ],
    "wof:name":"Hellyer College",
    "wof:placetype":"venue"
},
  "geometry": {"coordinates":[145.88118,-41.060375],"type":"Point"}
}