{
  "type": "Feature",
  "properties": {
    "iso:country":"AU",
    "sg:address":"146 Crockford Street",
    "sg:city":"Northgate",
    "sg:classifiers":[
        {
            "category":"Wholesale",
            "subcategory":"Machinery & Supplies",
            "type":"Manufacturing & Wholesale Goods"
        }
    ],
    "sg:phone":"+61 7 3266 1555",
    "sg:postcode":"4013",
    "sg:province":"QLD",
    "sg:tags":[
        "equipment",
        "system",
        "elevating",
        "conveying"
    ],
    "sg:website":"http://www.maxworthyfabrication.com.au",
    "wof:name":"Maxworthy Fabrication (QLD) Pty Ltd",
    "wof:placetype":"venue"
},
  "geometry": {"coordinates":[153.07472229000001,-27.3864765167],"type":"Point"}
}