{
  "type": "Feature",
  "properties": {
    "iso:country":"AU",
    "sg:address":"350 Princes St",
    "sg:city":"Port Melbourne",
    "sg:classifiers":[
        {
            "category":"Professional",
            "subcategory":"Management & Consulting",
            "type":"Services"
        }
    ],
    "sg:phone":"+61 3 9645 3416",
    "sg:postcode":"3207",
    "sg:province":"VIC",
    "sg:tags":[
        "consultant"
    ],
    "wof:name":"Lexington Consulting Group",
    "wof:placetype":"venue"
},
  "geometry": {"coordinates":[144.94305399999999,-37.83493],"type":"Point"}
}