{
  "type": "Feature",
  "properties": {
    "iso:country":"AU",
    "sg:address":"11 Thornycroft St",
    "sg:city":"Campbellfield",
    "sg:classifiers":[
        {
            "category":"Professional",
            "type":"Services"
        }
    ],
    "sg:phone":"+61 418 351 302",
    "sg:postcode":"3061",
    "sg:province":"VIC",
    "sg:tags":[
        "transport"
    ],
    "wof:name":"Target Transport Pty Ltd",
    "wof:placetype":"venue"
},
  "geometry": {"coordinates":[144.94224548299999,-37.6465377808],"type":"Point"}
}