{
  "type": "Feature",
  "properties": {
    "addr:full":"Cnr Sydney & Victoria Sts Mackay QLD 4740",
    "addr:postcode":"4740",
    "iso:country":"AU",
    "sg:address":"Cnr Sydney & Victoria Sts",
    "sg:city":"Mackay",
    "sg:classifiers":[
        {
            "category":"Banks & Credit Unions",
            "subcategory":"Investment Brokerage",
            "type":"Services"
        }
    ],
    "sg:phone":"+61 7 4957 3033",
    "sg:postcode":"4740",
    "sg:province":"QLD",
    "sg:tags":[
        "share",
        "broker",
        "stock"
    ],
    "wof:name":"ABN.Amro Morgans",
    "wof:placetype":"venue"
},
  "geometry": {"coordinates":[149.185608,-21.1514],"type":"Point"}
}