{
  "type": "Feature",
  "properties": {
    "addr:full":"70a Chapel St St Kilda VIC 3182",
    "addr:housenumber":"70a",
    "addr:postcode":"3182",
    "addr:street":"Chapel St",
    "iso:country":"AU",
    "sg:address":"70a Chapel St St",
    "sg:city":"Kilda",
    "sg:classifiers":[
        {
            "category":"Health Services",
            "subcategory":"Health Practitioner",
            "type":"Services"
        }
    ],
    "sg:phone":"+61 3 9534 6660",
    "sg:postcode":"3182",
    "sg:province":"VIC",
    "sg:tags":[
        "naturopath"
    ],
    "wof:name":"Aqua Natural Health & Colonic Hydrotherapy",
    "wof:placetype":"venue"
},
  "geometry": {"coordinates":[144.992874145,-37.8553199768],"type":"Point"}
}