{
  "type": "Feature",
  "properties": {
    "iso:country":"AU",
    "sg:address":"Carmichael Crt",
    "sg:city":"D&#039;Aguilar",
    "sg:classifiers":[
        {
            "category":"Utilities",
            "subcategory":"Electric",
            "type":"Services"
        }
    ],
    "sg:phone":"+61 7 5496 4749",
    "sg:postcode":"4514",
    "sg:province":"QLD",
    "sg:tags":[
        "electrical",
        "contractor"
    ],
    "wof:name":"O&#039;Connell Ron",
    "wof:placetype":"venue"
},
  "geometry": {"coordinates":[152.800247,-26.984455],"type":"Point"}
}