{
  "type": "Feature",
  "properties": {
    "addr:full":"601 Stanley St Albury NSW 2640",
    "addr:housenumber":"601",
    "addr:postcode":"2640",
    "addr:street":"Stanley St",
    "iso:country":"AU",
    "sg:address":"601 Stanley St",
    "sg:city":"Albury",
    "sg:classifiers":[
        {
            "category":"Professional",
            "subcategory":"Accounting & Tax Preparation",
            "type":"Services"
        }
    ],
    "sg:phone":"+61 2 6041 3044",
    "sg:postcode":"2640",
    "sg:province":"NSW",
    "sg:tags":[
        "accountant",
        "auditor"
    ],
    "wof:name":"O&#039;Callaghans Business Advisers",
    "wof:placetype":"venue"
},
  "geometry": {"coordinates":[146.912185669,-36.0786056519],"type":"Point"}
}