{
  "type": "Feature",
  "properties": {
    "addr:full":"Shop 7- 8 Target Cntr 236 Bourke St Melbourne VIC 3000",
    "addr:housenumber":"shop;8;236",
    "addr:postcode":"3000",
    "addr:street":"Target Cntr;Bourke St",
    "iso:country":"AU",
    "sg:address":"Shop 7- 8 Target Cntr 236 Bourke St",
    "sg:city":"Melbourne",
    "sg:classifiers":[
        {
            "category":"Cafe",
            "type":"Food & Drink"
        }
    ],
    "sg:phone":"+61 3 9662 1377",
    "sg:postcode":"3000",
    "sg:province":"VIC",
    "wof:name":"Gloria Jean's Coffees",
    "wof:placetype":"venue"
},
  "geometry": {"coordinates":[144.966064453,-37.8132553101],"type":"Point"}
}