{
  "type": "Feature",
  "properties": {
    "addr:full":"Unit 3, 4- 10 Farrall Rd Midvale WA 6056",
    "addr:housenumber":"4 10",
    "addr:postcode":"6056",
    "addr:street":"Farrall Rd",
    "iso:country":"AU",
    "sg:address":"Unit 3, 4- 10 Farrall Rd",
    "sg:city":"Midvale",
    "sg:classifiers":[
        {
            "category":"Professional",
            "subcategory":"Accounting & Tax Preparation",
            "type":"Services"
        }
    ],
    "sg:phone":"+61 1300 656 942",
    "sg:postcode":"6056",
    "sg:province":"WA",
    "sg:tags":[
        "consultant",
        "taxation"
    ],
    "wof:name":"Vogue Business & Bookkeeping Consultancy",
    "wof:placetype":"venue"
},
  "geometry": {"coordinates":[116.033630371,-31.8840770721],"type":"Point"}
}