{
  "type": "Feature",
  "properties": {
    "addr:full":"Howard Smith Drv Fisherman Islands QLD 4178",
    "addr:postcode":"4178",
    "addr:street":"Smith Drv Fisherman",
    "iso:country":"AU",
    "sg:address":"Howard Smith Drv",
    "sg:city":"Fisherman Islands",
    "sg:classifiers":[
        {
            "category":"Building & Trades",
            "subcategory":"Equipment Rental",
            "type":"Services"
        }
    ],
    "sg:phone":"+61 7 3895 1466",
    "sg:postcode":"4178",
    "sg:province":"QLD",
    "sg:tags":[
        "mfrs",
        "dredging",
        "contractor"
    ],
    "wof:name":"Dredeco Pty Ltd",
    "wof:placetype":"venue"
},
  "geometry": {"coordinates":[153.15907287600001,-27.4034061432],"type":"Point"}
}