{
  "type": "Feature",
  "properties": {
    "iso:country":"AU",
    "sg:address":"68 Bulcock St",
    "sg:city":"Caloundra",
    "sg:classifiers":[
        {
            "category":"Shopping",
            "subcategory":"Clothing, Apparel, & Fashions",
            "type":"Retail Goods"
        }
    ],
    "sg:phone":"+61 7 5491 4531",
    "sg:postcode":"4551",
    "sg:province":"QLD",
    "sg:tags":[
        "recycled",
        "clothing"
    ],
    "wof:name":"Lifeline T/A Encore Boutique",
    "wof:placetype":"venue"
},
  "geometry": {"coordinates":[153.129074097,-26.8046283722],"type":"Point"}
}