{
  "type": "Feature",
  "properties": {
    "iso:country":"AU",
    "sg:address":"868 Old Calder Hwy",
    "sg:city":"Keilor",
    "sg:classifiers":[
        {
            "category":"Social Services",
            "subcategory":"Retirement Home",
            "type":"Services"
        }
    ],
    "sg:phone":"+61 3 9390 8855",
    "sg:postcode":"3036",
    "sg:province":"VIC",
    "sg:tags":[
        "village"
    ],
    "wof:name":"Keilor Village",
    "wof:placetype":"venue"
},
  "geometry": {"coordinates":[144.809326,-37.703506],"type":"Point"}
}