{
  "type": "Feature",
  "properties": {
    "addr:full":"4 Macao Rd High Wycombe WA 6057",
    "addr:housenumber":"4",
    "addr:postcode":"6057",
    "addr:street":"Macao Rd",
    "iso:country":"AU",
    "sg:address":"4 Macao Rd",
    "sg:city":"High Wycombe",
    "sg:classifiers":[
        {
            "category":"Utilities",
            "subcategory":"Electric",
            "type":"Services"
        }
    ],
    "sg:phone":"+61 8 9454 5998",
    "sg:postcode":"6057",
    "sg:province":"WA",
    "sg:tags":[
        "electrical",
        "contractor"
    ],
    "wof:name":"Rabadan A. & J.N.",
    "wof:placetype":"venue"
},
  "geometry": {"coordinates":[116.00051116900001,-31.9405612946],"type":"Point"}
}