{
  "type": "Feature",
  "properties": {
    "addr:full":"18 Chambers Rd Woodford QLD 4514",
    "addr:housenumber":"18",
    "addr:postcode":"4514",
    "addr:street":"Chambers Rd",
    "iso:country":"AU",
    "sg:address":"18 Chambers Rd",
    "sg:city":"Woodford",
    "sg:classifiers":[
        {
            "category":"Utilities",
            "subcategory":"Electric",
            "type":"Services"
        }
    ],
    "sg:phone":"+61 7 5422 9933",
    "sg:postcode":"4514",
    "sg:province":"QLD",
    "sg:tags":[
        "transformer"
    ],
    "wof:name":"Seaford Transformers Pty Ltd",
    "wof:placetype":"venue"
},
  "geometry": {"coordinates":[152.78857400000001,-26.971485],"type":"Point"}
}