{
  "type": "Feature",
  "properties": {
    "iso:country":"AU",
    "sg:address":"Cnr Wheelers La & Myall St",
    "sg:city":"Dubbo",
    "sg:classifiers":[
        {
            "category":"Travel",
            "subcategory":"Hotels & Motels",
            "type":"Entertainment"
        }
    ],
    "sg:phone":"+61 2 6882 6500",
    "sg:postcode":"2830",
    "sg:province":"NSW",
    "wof:name":"Forest Lodge Motor Inn",
    "wof:placetype":"venue"
},
  "geometry": {"coordinates":[148.63017273,-32.2425689697],"type":"Point"}
}