{
  "type": "Feature",
  "properties": {
    "iso:country":"AU",
    "sg:address":"John St",
    "sg:city":"Coonabarabran",
    "sg:classifiers":[
        {
            "category":"Education",
            "subcategory":"School",
            "type":"Public Place"
        }
    ],
    "sg:phone":"+61 2 6842 1771",
    "sg:postcode":"2357",
    "sg:province":"NSW",
    "sg:tags":[
        "state",
        "-",
        "nsw"
    ],
    "wof:name":"Coonabarabran Public School",
    "wof:placetype":"venue"
},
  "geometry": {"coordinates":[149.27748107900001,-31.273979187],"type":"Point"}
}