{
  "type": "Feature",
  "properties": {
    "addr:full":"PO Box 271 Goodna QLD 4300",
    "addr:postcode":"4300",
    "iso:country":"AU",
    "sg:address":"PO Box 271",
    "sg:city":"Goodna",
    "sg:classifiers":[
        {
            "category":"Home & Garden",
            "subcategory":"Building Materials",
            "type":"Retail Goods"
        }
    ],
    "sg:phone":"+61 7 3818 2205",
    "sg:postcode":"4300",
    "sg:province":"QLD",
    "sg:tags":[
        "laminate",
        "laminated",
        "panel"
    ],
    "wof:name":"Kirkbuild Systems Pty Ltd",
    "wof:placetype":"venue"
},
  "geometry": {"coordinates":[152.89840698200001,-27.6107692719],"type":"Point"}
}