{
  "type": "Feature",
  "properties": {
    "addr:full":"68 Goman St Sunnybank Hills QLD 4109",
    "addr:housenumber":"68",
    "addr:postcode":"4109",
    "addr:street":"Goman St",
    "iso:country":"AU",
    "sg:address":"68 Goman St",
    "sg:city":"Sunnybank Hills",
    "sg:classifiers":[
        {
            "category":"Shopping",
            "subcategory":"Mobile Phones",
            "type":"Retail Goods"
        }
    ],
    "sg:phone":"+61 7 3345 8398",
    "sg:postcode":"4109",
    "sg:province":"QLD",
    "sg:tags":[
        "telephone",
        "accessory"
    ],
    "wof:name":"All You Need Mobile Phone Accessories",
    "wof:placetype":"venue"
},
  "geometry": {"coordinates":[153.0418396,-27.5814704895],"type":"Point"}
}