{
  "type": "Feature",
  "properties": {
    "addr:full":"Cnr Owen & Bunya Sts Dalby QLD 4405",
    "addr:postcode":"4405",
    "addr:street":"Cnr",
    "iso:country":"AU",
    "sg:address":"Cnr Owen & Bunya Sts",
    "sg:city":"Dalby",
    "sg:classifiers":[
        {
            "category":"Education",
            "subcategory":"School",
            "type":"Public Place"
        }
    ],
    "sg:phone":"+61 7 4672 3833",
    "sg:postcode":"4405",
    "sg:province":"QLD",
    "sg:tags":[
        "state",
        "except",
        "nsw"
    ],
    "wof:name":"Dalby South Preschool",
    "wof:placetype":"venue"
},
  "geometry": {"coordinates":[151.25590515100001,-27.1789798737],"type":"Point"}
}