{
  "type": "Feature",
  "properties": {
    "addr:full":"21 Gundibri St Busby NSW 2168",
    "addr:housenumber":"21",
    "addr:postcode":"2168",
    "addr:street":"Gundibri St",
    "iso:country":"AU",
    "sg:address":"21 Gundibri St",
    "sg:city":"Busby",
    "sg:classifiers":[
        {
            "category":"Social Services",
            "subcategory":"Adult Care",
            "type":"Services"
        }
    ],
    "sg:phone":"+61 407 274 594",
    "sg:postcode":"2168",
    "sg:province":"NSW",
    "sg:tags":[
        "towing"
    ],
    "wof:name":"AA & PA Cook Pty Ltd",
    "wof:placetype":"venue"
},
  "geometry": {"coordinates":[150.88119506800001,-33.9104232788],"type":"Point"}
}