{
  "type": "Feature",
  "properties": {
    "addr:full":"Oliver St Inverell NSW 2360",
    "addr:postcode":"2360",
    "addr:street":"Oliver St",
    "iso:country":"AU",
    "sg:address":"Oliver St",
    "sg:city":"Inverell",
    "sg:classifiers":[
        {
            "category":"Autos & Motor Vehicles",
            "subcategory":"Fuel & Gas Station",
            "type":"Retail Goods"
        }
    ],
    "sg:phone":"+61 2 6722 2366",
    "sg:postcode":"2360",
    "sg:province":"NSW",
    "wof:name":"Gaukroger F Sales Pty Ltd",
    "wof:placetype":"venue"
},
  "geometry": {"coordinates":[151.11416625999999,-29.7733078003],"type":"Point"}
}