{
  "type": "Feature",
  "properties": {
    "iso:country":"AU",
    "sg:address":"Unit 7/ 130 Forrester Rd",
    "sg:city":"St Marys",
    "sg:classifiers":[
        {
            "category":"Travel",
            "subcategory":"Travel Agent",
            "type":"Entertainment"
        }
    ],
    "sg:phone":"+61 2 9623 6001",
    "sg:postcode":"2760",
    "sg:province":"NSW",
    "sg:tags":[
        "tour",
        "holiday",
        "adventure"
    ],
    "wof:name":"Australian Weekend Adventures",
    "wof:placetype":"venue"
},
  "geometry": {"coordinates":[150.775787353,-33.7544784546],"type":"Point"}
}