{
  "type": "Feature",
  "properties": {
    "iso:country":"AU",
    "sg:address":"136 New South Head Rd",
    "sg:city":"Edgecliff",
    "sg:classifiers":[
        {
            "category":"Health Services",
            "subcategory":"Health Practitioner",
            "type":"Services"
        }
    ],
    "sg:phone":"+61 425 255 320",
    "sg:postcode":"2027",
    "sg:province":"NSW",
    "sg:tags":[
        "naturopath"
    ],
    "wof:name":"Jankelson Jeff",
    "wof:placetype":"venue"
},
  "geometry": {"coordinates":[151.23373413100001,-33.8774414062],"type":"Point"}
}