{
  "type": "Feature",
  "properties": {
    "iso:country":"AU",
    "sg:address":"19 Zander Ave",
    "sg:city":"Nunawading",
    "sg:classifiers":[
        {
            "category":"Building & Trades",
            "subcategory":"Construction",
            "type":"Services"
        }
    ],
    "sg:phone":"+61 3 9894 4711",
    "sg:postcode":"3131",
    "sg:province":"VIC",
    "sg:tags":[
        "renovation",
        "alterations",
        "extension",
        "contractor"
    ],
    "wof:name":"Chris McArdle Reblocking",
    "wof:placetype":"venue"
},
  "geometry": {"coordinates":[145.16860961899999,-37.810333252],"type":"Point"}
}