{
  "type": "Feature",
  "properties": {
    "iso:country":"AU",
    "sg:address":"14 Hinkler Rd",
    "sg:city":"Taminda",
    "sg:classifiers":[
        {
            "category":"Manufacturing",
            "subcategory":"Motor Vehicles & Parts",
            "type":"Manufacturing & Wholesale Goods"
        }
    ],
    "sg:phone":"+61 2 6763 2100",
    "sg:postcode":"2340",
    "sg:province":"NSW",
    "sg:tags":[
        "replacement"
    ],
    "wof:name":"Stallion Wholesale Auto Parts",
    "wof:placetype":"venue"
},
  "geometry": {"coordinates":[150.898834228,-31.0957107544],"type":"Point"}
}