{
  "type": "Feature",
  "properties": {
    "addr:full":"87 Glenferrie Rd Malvern VIC 3144",
    "addr:housenumber":"87",
    "addr:postcode":"3144",
    "addr:street":"Glenferrie Rd",
    "iso:country":"AU",
    "sg:address":"87 Glenferrie Rd",
    "sg:city":"Malvern",
    "sg:classifiers":[
        {
            "category":"Shopping",
            "subcategory":"Clothing, Apparel, & Fashions",
            "type":"Retail Goods"
        }
    ],
    "sg:phone":"+61 3 9500 9170",
    "sg:postcode":"3144",
    "sg:province":"VIC",
    "sg:tags":[
        "lady",
        "wear"
    ],
    "wof:name":"Clothes Plus Boutique",
    "wof:placetype":"venue"
},
  "geometry": {"coordinates":[145.028106689,-37.8627815247],"type":"Point"}
}