{
  "type": "Feature",
  "properties": {
    "iso:country":"AU",
    "sg:address":"82 Vulture St",
    "sg:city":"West End",
    "sg:classifiers":[
        {
            "category":"Education",
            "subcategory":"University",
            "type":"Public Place"
        }
    ],
    "sg:phone":"+61 7 3846 4358",
    "sg:postcode":"4101",
    "sg:province":"QLD",
    "sg:tags":[
        "educational",
        "organisation",
        "cultural"
    ],
    "wof:name":"The West End Street Festival",
    "wof:placetype":"venue"
},
  "geometry": {"coordinates":[153.01185607900001,-27.4807910919],"type":"Point"}
}