{
  "type": "Feature",
  "properties": {
    "addr:full":"Unit 2, 9 Maurice St Bayswater WA 6053",
    "addr:housenumber":"9",
    "addr:postcode":"6053",
    "addr:street":"Maurice St",
    "iso:country":"AU",
    "sg:address":"Unit 2, 9 Maurice St",
    "sg:city":"Bayswater",
    "sg:classifiers":[
        {
            "category":"Retail",
            "subcategory":"Auto Repair",
            "type":"Services"
        }
    ],
    "sg:phone":"+61 8 9371 5116",
    "sg:postcode":"6053",
    "sg:province":"WA",
    "sg:tags":[
        "repairer",
        "motor",
        "engineer"
    ],
    "wof:name":"For Serv",
    "wof:placetype":"venue"
},
  "geometry": {"coordinates":[115.912666321,-31.9082336426],"type":"Point"}
}