{
  "type": "Feature",
  "properties": {
    "addr:full":"61 Commercial St East Mt Gambier SA 5290",
    "addr:housenumber":"61",
    "addr:postcode":"5290",
    "addr:street":"Commercial St East Mt",
    "iso:country":"AU",
    "sg:address":"61 Commercial St",
    "sg:city":"East Mt Gambier",
    "sg:classifiers":[
        {
            "category":"Insurance",
            "subcategory":"Insurance Agent",
            "type":"Services"
        }
    ],
    "sg:phone":"+61 8 8723 1466",
    "sg:postcode":"5290",
    "sg:province":"SA",
    "sg:tags":[
        "broker"
    ],
    "wof:name":"Fallas Kenseley Insurance Brokers Pty Ltd",
    "wof:placetype":"venue"
},
  "geometry": {"coordinates":[140.78303500000001,-37.829029],"type":"Point"}
}