{
  "type": "Feature",
  "properties": {
    "addr:full":"Egret St Kooragang Island NSW 2304",
    "addr:postcode":"2304",
    "addr:street":"Egret St",
    "iso:country":"AU",
    "sg:address":"Egret St",
    "sg:city":"Kooragang Island",
    "sg:classifiers":[
        {
            "category":"Transit Center",
            "subcategory":"Freight",
            "type":"Transportation"
        }
    ],
    "sg:phone":"+61 13 24 62",
    "sg:postcode":"2304",
    "sg:province":"NSW",
    "sg:tags":[
        "forklift",
        "truck"
    ],
    "wof:name":"Origin Energy",
    "wof:placetype":"venue"
},
  "geometry": {"coordinates":[151.764068603,-32.8818664551],"type":"Point"}
}