{
  "type": "Feature",
  "properties": {
    "addr:full":"Flinders Hwy Torrens Creek QLD 4816",
    "addr:postcode":"4816",
    "addr:street":"Flinders Hwy",
    "iso:country":"AU",
    "sg:address":"Flinders Hwy",
    "sg:city":"Torrens Creek",
    "sg:classifiers":[
        {
            "category":"Travel",
            "subcategory":"Hotels & Motels",
            "type":"Entertainment"
        }
    ],
    "sg:phone":"+61 7 4741 7342",
    "sg:postcode":"4816",
    "sg:province":"QLD",
    "sg:tags":[
        "accommodation"
    ],
    "wof:name":"Exchange Hotel Torrens Creek",
    "wof:placetype":"venue"
},
  "geometry": {"coordinates":[145.02153000000001,-20.769547],"type":"Point"}
}