{
  "type": "Feature",
  "properties": {
    "addr:full":"2C Denham Pl Toorak VIC 3142",
    "addr:housenumber":"2c",
    "addr:postcode":"3142",
    "addr:street":"Denham Pl",
    "iso:country":"AU",
    "sg:address":"2C Denham Pl",
    "sg:city":"Toorak",
    "sg:classifiers":[
        {
            "category":"Health Services",
            "subcategory":"Health Practitioner",
            "type":"Services"
        }
    ],
    "sg:phone":"+61 3 9824 8142",
    "sg:postcode":"3142",
    "sg:province":"VIC",
    "sg:tags":[
        "psychologist"
    ],
    "wof:name":"Brideson Marilyn (Em)",
    "wof:placetype":"venue"
},
  "geometry": {"coordinates":[145.025634766,-37.8508415222],"type":"Point"}
}