{
  "type": "Feature",
  "properties": {
    "iso:country":"AU",
    "sg:address":"PO Box 1064",
    "sg:city":"Leichhardt",
    "sg:classifiers":[
        {
            "category":"Personal",
            "subcategory":"Beauty Salon",
            "type":"Services"
        }
    ],
    "sg:phone":"+61 417 212 974",
    "sg:postcode":"2040",
    "sg:province":"NSW",
    "sg:tags":[
        "supply",
        "artist",
        "make-up"
    ],
    "wof:name":"Accredited Mobile Make-Up Artist",
    "wof:placetype":"venue"
},
  "geometry": {"coordinates":[151.158905,-33.883659],"type":"Point"}
}