{
  "type": "Feature",
  "properties": {
    "addr:full":"241 Church Rd Taigum QLD 4018",
    "addr:housenumber":"241",
    "addr:postcode":"4018",
    "addr:street":"Church Rd",
    "iso:country":"AU",
    "sg:address":"241 Church Rd",
    "sg:city":"Taigum",
    "sg:classifiers":[
        {
            "category":"Social Services",
            "subcategory":"Adult Care",
            "type":"Services"
        }
    ],
    "sg:phone":"+61 7 3865 3279",
    "sg:postcode":"4018",
    "sg:province":"QLD",
    "sg:tags":[
        "aged"
    ],
    "wof:name":"Greek Respite Centre",
    "wof:placetype":"venue"
},
  "geometry": {"coordinates":[153.04690600000001,-27.348015],"type":"Point"}
}