{
  "type": "Feature",
  "properties": {
    "addr:full":"Shop 6,2- 10 Pittwater Rd Manly NSW 2095",
    "addr:housenumber":"6,2 10",
    "addr:postcode":"2095",
    "addr:street":"Pittwater Rd",
    "iso:country":"AU",
    "sg:address":"Shop 6,2- 10 Pittwater Rd",
    "sg:city":"Manly",
    "sg:classifiers":[
        {
            "category":"Health Services",
            "subcategory":"Dentist",
            "type":"Services"
        }
    ],
    "sg:phone":"+61 2 9977 3374",
    "sg:postcode":"2095",
    "sg:province":"NSW",
    "wof:name":"Prashanth Kanakamedala Dr",
    "wof:placetype":"venue"
},
  "geometry": {"coordinates":[151.28529357900001,-33.7952308655],"type":"Point"}
}