{
  "type": "Feature",
  "properties": {
    "iso:country":"AU",
    "sg:address":"195 Commercial St",
    "sg:city":"West Mt Gambier",
    "sg:classifiers":[
        {
            "category":"Autos & Motor Vehicles",
            "subcategory":"Fuel & Gas Station",
            "type":"Retail Goods"
        }
    ],
    "sg:phone":"+61 8 8723 2033",
    "sg:postcode":"5290",
    "sg:province":"SA",
    "wof:name":"Mobil Oil Australia Pty Ltd",
    "wof:placetype":"venue"
},
  "geometry": {"coordinates":[140.767319,-37.824245],"type":"Point"}
}