{
  "type": "Feature",
  "properties": {
    "addr:full":"22 Beatty Ave Armadale VIC 3143",
    "addr:housenumber":"22",
    "addr:postcode":"3143",
    "addr:street":"Beatty Ave",
    "iso:country":"AU",
    "sg:address":"22 Beatty Ave",
    "sg:city":"Armadale",
    "sg:classifiers":[
        {
            "category":"Restaurant",
            "type":"Food & Drink"
        }
    ],
    "sg:phone":"+61 3 9824 8022",
    "sg:postcode":"3143",
    "sg:province":"VIC",
    "wof:name":"Chez Bob Restaurant",
    "wof:placetype":"venue"
},
  "geometry": {"coordinates":[145.014038086,-37.8503494263],"type":"Point"}
}