{
  "type": "Feature",
  "properties": {
    "iso:country":"AU",
    "sg:address":"10 Muller St",
    "sg:city":"North Beach",
    "sg:classifiers":[
        {
            "category":"Professional",
            "subcategory":"Engineering",
            "type":"Services"
        }
    ],
    "sg:phone":"+61 8 9447 8932",
    "sg:postcode":"6020",
    "sg:province":"WA",
    "sg:tags":[
        "consulting",
        "engineer"
    ],
    "wof:name":"Jayrise Pty Ltd",
    "wof:placetype":"venue"
},
  "geometry": {"coordinates":[115.753562927,-31.8680648804],"type":"Point"}
}