{
  "type": "Feature",
  "properties": {
    "iso:country":"AU",
    "sg:address":"8 Mason Crt",
    "sg:city":"Shepparton East",
    "sg:classifiers":[
        {
            "category":"Building & Trades",
            "subcategory":"Cleaning & Sanitation",
            "type":"Services"
        }
    ],
    "sg:phone":"+61 418 335 740",
    "sg:postcode":"3631",
    "sg:province":"VIC",
    "sg:tags":[
        "industrial",
        "commercial",
        "contractor"
    ],
    "wof:name":"Cambos Cleaning Service",
    "wof:placetype":"venue"
},
  "geometry": {"coordinates":[145.45501709000001,-36.3921966553],"type":"Point"}
}