{
  "type": "Feature",
  "properties": {
    "addr:full":"PO Box 176 Applecross Private Boxes WA 6953",
    "addr:postcode":"6953",
    "iso:country":"AU",
    "sg:address":"PO Box 176",
    "sg:city":"Applecross Private Boxes",
    "sg:classifiers":[
        {
            "category":"Recreation",
            "subcategory":"Fishing",
            "type":"Entertainment"
        }
    ],
    "sg:phone":"+61 8 9339 2432",
    "sg:postcode":"6953",
    "sg:province":"WA",
    "sg:tags":[
        "trip"
    ],
    "wof:name":"Apache Charters",
    "wof:placetype":"venue"
},
  "geometry": {"coordinates":[115.833221435,-32.0194015503],"type":"Point"}
}