{
  "type": "Feature",
  "properties": {
    "addr:full":"192 Koroit St Warrnambool VIC 3280",
    "addr:housenumber":"192",
    "addr:postcode":"3280",
    "addr:street":"Koroit St",
    "iso:country":"AU",
    "sg:address":"192 Koroit St",
    "sg:city":"Warrnambool",
    "sg:classifiers":[
        {
            "category":"Real Estate",
            "subcategory":"Surveying",
            "type":"Services"
        }
    ],
    "sg:phone":"+61 3 5561 1500",
    "sg:postcode":"3280",
    "sg:province":"VIC",
    "sg:tags":[
        "surveyor",
        "land"
    ],
    "wof:name":"Crowe Paul",
    "wof:placetype":"venue"
},
  "geometry": {"coordinates":[142.47958374000001,-38.3816223145],"type":"Point"}
}