{
  "type": "Feature",
  "properties": {
    "addr:full":"Shp1/ 140 Wilsons Rd Whittington VIC 3219",
    "addr:housenumber":"140",
    "addr:postcode":"3219",
    "addr:street":"Wilsons Rd",
    "iso:country":"AU",
    "sg:address":"Shp1/ 140 Wilsons Rd",
    "sg:city":"Whittington",
    "sg:classifiers":[
        {
            "category":"Fast Food",
            "type":"Food & Drink"
        }
    ],
    "sg:phone":"+61 3 5248 3899",
    "sg:postcode":"3219",
    "sg:province":"VIC",
    "sg:tags":[
        "away",
        "take"
    ],
    "wof:name":"Wilsons Road Fish Shop",
    "wof:placetype":"venue"
},
  "geometry": {"coordinates":[144.390899658,-38.1724815369],"type":"Point"}
}