{
  "type": "Feature",
  "properties": {
    "addr:full":"254 Wingrove St Fairfield VIC 3078",
    "addr:housenumber":"254",
    "addr:postcode":"3078",
    "addr:street":"Wingrove St",
    "iso:country":"AU",
    "sg:address":"254 Wingrove St",
    "sg:city":"Fairfield",
    "sg:classifiers":[
        {
            "category":"Wholesale",
            "subcategory":"Home Furnishings",
            "type":"Manufacturing & Wholesale Goods"
        }
    ],
    "sg:phone":"+61 3 9486 1572",
    "sg:postcode":"3078",
    "sg:province":"VIC",
    "sg:tags":[
        "wholesaler",
        "mfrs",
        "kitchenware"
    ],
    "wof:name":"Lygon Imports",
    "wof:placetype":"venue"
},
  "geometry": {"coordinates":[145.01800537099999,-37.7787780762],"type":"Point"}
}