{
  "type": "Feature",
  "properties": {
    "addr:full":"Fcty1/ 82 Bayfield Rd Bayswater VIC 3153",
    "addr:housenumber":"82",
    "addr:postcode":"3153",
    "addr:street":"Bayfield Rd",
    "iso:country":"AU",
    "sg:address":"Fcty1/ 82 Bayfield Rd",
    "sg:city":"Bayswater",
    "sg:classifiers":[
        {
            "category":"Manufacturing",
            "subcategory":"Metals",
            "type":"Manufacturing & Wholesale Goods"
        }
    ],
    "sg:phone":"+61 3 9729 4806",
    "sg:postcode":"3153",
    "sg:province":"VIC",
    "sg:tags":[
        "steel",
        "fabricator",
        "mfrs"
    ],
    "wof:name":"Innovative Metal Fabrication",
    "wof:placetype":"venue"
},
  "geometry": {"coordinates":[145.27731323200001,-37.8241653442],"type":"Point"}
}