{
  "type": "Feature",
  "properties": {
    "addr:full":"110 Harris St Welshpool WA 6106",
    "addr:housenumber":"110",
    "addr:postcode":"6106",
    "addr:street":"Harris St",
    "iso:country":"AU",
    "sg:address":"110 Harris St",
    "sg:city":"Welshpool",
    "sg:classifiers":[
        {
            "category":"Retail",
            "subcategory":"Auto Repair",
            "type":"Services"
        }
    ],
    "sg:phone":"+61 8 9361 8202",
    "sg:postcode":"6106",
    "sg:province":"WA",
    "sg:tags":[
        "beater",
        "painter",
        "panel"
    ],
    "wof:name":"Swan Smash Repairs",
    "wof:placetype":"venue"
},
  "geometry": {"coordinates":[115.927833557,-31.986038208],"type":"Point"}
}