{
  "type": "Feature",
  "properties": {
    "iso:country":"AU",
    "sg:address":"1 Maleny Rd",
    "sg:city":"Landsborough",
    "sg:classifiers":[
        {
            "category":"Fast Food",
            "type":"Food & Drink"
        }
    ],
    "sg:phone":"+61 7 5494 1210",
    "sg:postcode":"4550",
    "sg:province":"QLD",
    "sg:tags":[
        "away",
        "take"
    ],
    "wof:name":"Landsborough Country Kitchen Eat In Or Takeaway",
    "wof:placetype":"venue"
},
  "geometry": {"coordinates":[152.96551513700001,-26.8091011047],"type":"Point"}
}