{
  "type": "Feature",
  "properties": {
    "addr:full":"259 Pittwater Rd Manly NSW 2095",
    "addr:housenumber":"259",
    "addr:postcode":"2095",
    "addr:street":"Pittwater Rd",
    "iso:country":"AU",
    "sg:address":"259 Pittwater Rd",
    "sg:city":"Manly",
    "sg:classifiers":[
        {
            "category":"Autos & Motor Vehicles",
            "subcategory":"Automobile Sales",
            "type":"Retail Goods"
        }
    ],
    "sg:phone":"+61 2 9977 3255",
    "sg:postcode":"2095",
    "sg:province":"NSW",
    "sg:tags":[
        "car",
        "new"
    ],
    "wof:name":"Titan Daewoo",
    "wof:placetype":"venue"
},
  "geometry": {"coordinates":[151.28121948200001,-33.7868003845],"type":"Point"}
}