{
  "type": "Feature",
  "properties": {
    "addr:full":"338 South Rd Hampton East VIC 3188",
    "addr:housenumber":"338",
    "addr:postcode":"3188",
    "addr:street":"South Rd",
    "iso:country":"AU",
    "sg:address":"338 South Rd",
    "sg:city":"Hampton East",
    "sg:classifiers":[
        {
            "category":"Shopping",
            "subcategory":"Beauty & Cosmetics",
            "type":"Retail Goods"
        }
    ],
    "sg:phone":"+61 1300 725 661",
    "sg:postcode":"3188",
    "sg:province":"VIC",
    "sg:tags":[
        "equipment",
        "salon",
        "supply"
    ],
    "wof:name":"Salon First",
    "wof:placetype":"venue"
},
  "geometry": {"coordinates":[145.032470703,-37.9329872131],"type":"Point"}
}