{
  "type": "Feature",
  "properties": {
    "iso:country":"AU",
    "sg:address":"Lvl 1/ 151 Burwood Rd",
    "sg:city":"Burwood",
    "sg:classifiers":[
        {
            "category":"Professional",
            "subcategory":"Management & Consulting",
            "type":"Services"
        }
    ],
    "sg:phone":"+61 2 9715 2334",
    "sg:postcode":"2134",
    "sg:province":"NSW",
    "sg:tags":[
        "consultant",
        "educational"
    ],
    "wof:name":"Australia English Drama Education Centre",
    "wof:placetype":"venue"
},
  "geometry": {"coordinates":[151.103683472,-33.8766021729],"type":"Point"}
}