{
  "type": "Feature",
  "properties": {
    "addr:full":"465 High St Preston VIC 3072",
    "addr:housenumber":"465",
    "addr:postcode":"3072",
    "addr:street":"High St",
    "iso:country":"AU",
    "sg:address":"465 High St",
    "sg:city":"Preston",
    "sg:classifiers":[
        {
            "category":"Food & Beverages",
            "subcategory":"Bakery",
            "type":"Retail Goods"
        }
    ],
    "sg:phone":"+61 3 9478 4443",
    "sg:postcode":"3072",
    "sg:province":"VIC",
    "sg:tags":[
        "baker"
    ],
    "wof:name":"La Panella Bakery",
    "wof:placetype":"venue"
},
  "geometry": {"coordinates":[145.00376892099999,-37.7382354736],"type":"Point"}
}