{
  "type": "Feature",
  "properties": {
    "addr:full":"250 Glen Osmond Rd Fullarton SA 5063",
    "addr:housenumber":"250",
    "addr:postcode":"5063",
    "addr:street":"Glen Osmond Rd",
    "iso:country":"AU",
    "sg:address":"250 Glen Osmond Rd",
    "sg:city":"Fullarton",
    "sg:classifiers":[
        {
            "category":"Health Services",
            "subcategory":"Doctor",
            "type":"Services"
        }
    ],
    "sg:phone":"+61 8 8338 1000",
    "sg:postcode":"5063",
    "sg:province":"SA",
    "sg:tags":[
        "nurse",
        "nursing"
    ],
    "wof:name":"Nursing Agency of SA",
    "wof:placetype":"venue"
},
  "geometry": {"coordinates":[138.63340759299999,-34.95129776],"type":"Point"}
}