{
  "type": "Feature",
  "properties": {
    "iso:country":"AU",
    "sg:address":"156 Inala Ave",
    "sg:city":"Inala",
    "sg:classifiers":[
        {
            "category":"Shopping",
            "subcategory":"Clothing, Apparel, & Fashions",
            "type":"Retail Goods"
        }
    ],
    "sg:phone":"+61 7 3879 7444",
    "sg:postcode":"4077",
    "sg:province":"QLD",
    "sg:tags":[
        "lady",
        "wear"
    ],
    "wof:name":"Central Lane",
    "wof:placetype":"venue"
},
  "geometry": {"coordinates":[152.98414611800001,-27.5972423553],"type":"Point"}
}