{
  "type": "Feature",
  "properties": {
    "addr:full":"34 King St Bendigo VIC 3550",
    "addr:housenumber":"34",
    "addr:postcode":"3550",
    "addr:street":"King St",
    "iso:country":"AU",
    "sg:address":"34 King St",
    "sg:city":"Bendigo",
    "sg:classifiers":[
        {
            "category":"Personal",
            "subcategory":"Beauty Salon",
            "type":"Services"
        }
    ],
    "sg:phone":"+61 3 5444 1223",
    "sg:postcode":"3550",
    "sg:province":"VIC",
    "sg:tags":[
        "hairdresser"
    ],
    "wof:name":"Shyne Hair Studio",
    "wof:placetype":"venue"
},
  "geometry": {"coordinates":[144.279373169,-36.7627639771],"type":"Point"}
}