{
  "type": "Feature",
  "properties": {
    "addr:full":"257 Magill Rd Magill SA 5072",
    "addr:housenumber":"257",
    "addr:postcode":"5072",
    "addr:street":"Magill Rd",
    "iso:country":"AU",
    "sg:address":"257 Magill Rd",
    "sg:city":"Magill",
    "sg:classifiers":[
        {
            "category":"Food & Beverages",
            "subcategory":"Groceries & Convenience Stores",
            "type":"Retail Goods"
        }
    ],
    "sg:phone":"+61 8 8431 1066",
    "sg:postcode":"5072",
    "sg:province":"SA",
    "wof:name":"BP Express",
    "wof:placetype":"venue"
},
  "geometry": {"coordinates":[138.66781616200001,-34.9134407043],"type":"Point"}
}