{
  "type": "Feature",
  "properties": {
    "iso:country":"AU",
    "sg:address":"30 - 32 Kilkenny Crt",
    "sg:city":"Dandenong",
    "sg:classifiers":[
        {
            "category":"Shopping",
            "subcategory":"Stationery & Office Supplies",
            "type":"Retail Goods"
        }
    ],
    "sg:phone":"+61 3 9793 7100",
    "sg:postcode":"3175",
    "sg:province":"VIC",
    "sg:tags":[
        "screen",
        "printing"
    ],
    "wof:name":"DIC International Australia Pty Ltd",
    "wof:placetype":"venue"
},
  "geometry": {"coordinates":[145.201370239,-38.0195770264],"type":"Point"}
}