{
  "type": "Feature",
  "properties": {
    "addr:full":"264 Upper Dawson Rd Rockhampton QLD 4700",
    "addr:housenumber":"264",
    "addr:postcode":"4700",
    "addr:street":"Upper Dawson Rd",
    "iso:country":"AU",
    "sg:address":"264 Upper Dawson Rd",
    "sg:city":"Rockhampton",
    "sg:classifiers":[
        {
            "category":"Food & Beverages",
            "subcategory":"Groceries & Convenience Stores",
            "type":"Retail Goods"
        }
    ],
    "sg:phone":"+61 7 4927 3647",
    "sg:postcode":"4700",
    "sg:province":"QLD",
    "wof:name":"Whiting's General Store",
    "wof:placetype":"venue"
},
  "geometry": {"coordinates":[150.50018310600001,-23.4042358398],"type":"Point"}
}