{
  "type": "Feature",
  "properties": {
    "addr:full":"110 Andromeda Drv Cranebrook NSW 2749",
    "addr:housenumber":"110",
    "addr:postcode":"2749",
    "addr:street":"Andromeda Drv",
    "iso:country":"AU",
    "sg:address":"110 Andromeda Drv",
    "sg:city":"Cranebrook",
    "sg:classifiers":[
        {
            "category":"Transit Center",
            "subcategory":"Freight",
            "type":"Transportation"
        }
    ],
    "sg:phone":"+61 412 076 346",
    "sg:postcode":"2749",
    "sg:province":"NSW",
    "sg:tags":[
        "forklift",
        "truck"
    ],
    "wof:name":"KR Lift Truck Services",
    "wof:placetype":"venue"
},
  "geometry": {"coordinates":[150.71836852999999,-33.7131576538],"type":"Point"}
}