{
  "type": "Feature",
  "properties": {
    "iso:country":"AU",
    "sg:address":"38a Eyre St",
    "sg:city":"Seaview Downs",
    "sg:classifiers":[
        {
            "category":"Health Services",
            "subcategory":"Health Practitioner",
            "type":"Services"
        }
    ],
    "sg:phone":"+61 8 8296 6589",
    "sg:postcode":"5049",
    "sg:province":"SA",
    "sg:tags":[
        "pathologist",
        "speech"
    ],
    "wof:name":"Coralie Hayley",
    "wof:placetype":"venue"
},
  "geometry": {"coordinates":[138.53608700000001,-35.034634],"type":"Point"}
}