{
  "type": "Feature",
  "properties": {
    "addr:full":"7 Tudor St Hamilton NSW 2303",
    "addr:housenumber":"7",
    "addr:postcode":"2303",
    "addr:street":"Tudor St",
    "iso:country":"AU",
    "sg:address":"7 Tudor St",
    "sg:city":"Hamilton",
    "sg:classifiers":[
        {
            "category":"Shopping",
            "subcategory":"Shoes",
            "type":"Retail Goods"
        }
    ],
    "sg:phone":"+61 2 4961 3313",
    "sg:postcode":"2303",
    "sg:province":"NSW",
    "sg:tags":[
        "footwear"
    ],
    "wof:name":"Footwear Barn",
    "wof:placetype":"venue"
},
  "geometry": {"coordinates":[151.747894,-32.92437],"type":"Point"}
}