{
  "type": "Feature",
  "properties": {
    "addr:full":"88 Mair St East Bakery Hill VIC 3354",
    "addr:housenumber":"88",
    "addr:postcode":"3354",
    "addr:street":"Mair St East",
    "iso:country":"AU",
    "sg:address":"88 Mair St",
    "sg:city":"East Bakery Hill",
    "sg:classifiers":[
        {
            "category":"Banks & Credit Unions",
            "subcategory":"Financial Services",
            "type":"Services"
        }
    ],
    "sg:phone":"+61 3 5333 1576",
    "sg:postcode":"3354",
    "sg:province":"VIC",
    "sg:tags":[
        "annuity",
        "rollover",
        "superannuation",
        "consultant"
    ],
    "wof:name":"WHK Prescott",
    "wof:placetype":"venue"
},
  "geometry": {"coordinates":[143.86755400000001,-37.560986],"type":"Point"}
}