{
  "type": "Feature",
  "properties": {
    "iso:country":"AU",
    "sg:address":"PO Box 6833",
    "sg:city":"Tweed Heads South",
    "sg:classifiers":[
        {
            "category":"Utilities",
            "subcategory":"Electric",
            "type":"Services"
        }
    ],
    "sg:phone":"+61 412 197 327",
    "sg:postcode":"2486",
    "sg:province":"NSW",
    "sg:tags":[
        "electrical",
        "contractor"
    ],
    "wof:name":"David Ross Electrical & Air Conditioning",
    "wof:placetype":"venue"
},
  "geometry": {"coordinates":[153.54444885300001,-28.2044506073],"type":"Point"}
}