{
  "type": "Feature",
  "properties": {
    "addr:full":"\"Annangrove Park\" Cargo Rd Orange NSW 2800",
    "addr:postcode":"2800",
    "addr:street":"Cargo Rd",
    "iso:country":"AU",
    "sg:address":"\"Annangrove Park\" Cargo Rd",
    "sg:city":"Orange",
    "sg:classifiers":[
        {
            "category":"Farming",
            "subcategory":"Vineyard",
            "type":"Manufacturing & Wholesale Goods"
        }
    ],
    "sg:phone":"+61 2 6364 3118",
    "sg:postcode":"2800",
    "sg:province":"NSW",
    "sg:tags":[
        "winery"
    ],
    "wof:name":"Jarretts Wines",
    "wof:placetype":"venue"
},
  "geometry": {"coordinates":[149.063323975,-33.2846984863],"type":"Point"}
}