{
  "type": "Feature",
  "properties": {
    "iso:country":"AU",
    "sg:address":"Unit 3 / 33- 35 William Angliss Drv",
    "sg:city":"Laverton North",
    "sg:classifiers":[
        {
            "category":"Retail",
            "subcategory":"Auto Repair",
            "type":"Services"
        }
    ],
    "sg:phone":"+61 3 9931 0698",
    "sg:postcode":"3026",
    "sg:province":"VIC",
    "sg:tags":[
        "electrical"
    ],
    "wof:name":"AMS Auto Electrics",
    "wof:placetype":"venue"
},
  "geometry": {"coordinates":[144.778381,-37.823196],"type":"Point"}
}