{
  "type": "Feature",
  "properties": {
    "addr:full":"13 Narwee Ave Narwee NSW 2209",
    "addr:housenumber":"13",
    "addr:postcode":"2209",
    "addr:street":"Narwee Ave",
    "iso:country":"AU",
    "sg:address":"13 Narwee Ave",
    "sg:city":"Narwee",
    "sg:classifiers":[
        {
            "category":"Personal",
            "subcategory":"Beauty Salon",
            "type":"Services"
        }
    ],
    "sg:phone":"+61 2 9533 6403",
    "sg:postcode":"2209",
    "sg:province":"NSW",
    "sg:tags":[
        "supply",
        "artist",
        "make-up"
    ],
    "wof:name":"Flair Mobile Make-up Artists",
    "wof:placetype":"venue"
},
  "geometry": {"coordinates":[151.067047,-33.947803],"type":"Point"}
}