{
  "type": "Feature",
  "properties": {
    "iso:country":"AU",
    "sg:address":"456 Great Western Hwy",
    "sg:city":"Faulconbridge",
    "sg:classifiers":[
        {
            "category":"Food & Beverages",
            "subcategory":"Liquor & Beverages",
            "type":"Retail Goods"
        }
    ],
    "sg:phone":"+61 2 4751 3029",
    "sg:postcode":"2776",
    "sg:province":"NSW",
    "sg:tags":[
        "store"
    ],
    "wof:name":"Faulconbridge Cellars",
    "wof:placetype":"venue"
},
  "geometry": {"coordinates":[150.546951294,-33.6933021545],"type":"Point"}
}