{
  "type": "Feature",
  "properties": {
    "addr:full":"11 Stark St Ashgrove QLD 4060",
    "addr:housenumber":"11",
    "addr:postcode":"4060",
    "addr:street":"Stark St",
    "iso:country":"AU",
    "sg:address":"11 Stark St",
    "sg:city":"Ashgrove",
    "sg:classifiers":[
        {
            "category":"Personal",
            "type":"Services"
        }
    ],
    "sg:phone":"+61 7 3366 1966",
    "sg:postcode":"4060",
    "sg:province":"QLD",
    "sg:tags":[
        "dressmaker"
    ],
    "wof:name":"Justine Hope School Formals",
    "wof:placetype":"venue"
},
  "geometry": {"coordinates":[152.988967895,-27.4350547791],"type":"Point"}
}