{
  "type": "Feature",
  "properties": {
    "addr:full":"U 2/ 38 First St Katherine NT 0850",
    "addr:housenumber":"38",
    "addr:postcode":"nt 0850",
    "addr:street":"First St",
    "iso:country":"AU",
    "sg:address":"U 2/ 38 First St",
    "sg:city":"Katherine",
    "sg:classifiers":[
        {
            "category":"Education",
            "subcategory":"Special Training",
            "type":"Public Place"
        }
    ],
    "sg:phone":"+61 8 8971 2177",
    "sg:postcode":"0850",
    "sg:province":"NT",
    "sg:tags":[
        "development"
    ],
    "wof:name":"Little Fish",
    "wof:placetype":"venue"
},
  "geometry": {"coordinates":[132.261078,-14.462021],"type":"Point"}
}