{
  "type": "Feature",
  "properties": {
    "iso:country":"AU",
    "sg:address":"Byron St",
    "sg:city":"Lennox Head",
    "sg:classifiers":[
        {
            "category":"Education",
            "subcategory":"Kindergarten",
            "type":"Public Place"
        }
    ],
    "sg:phone":"+61 2 6687 7105",
    "sg:postcode":"2478",
    "sg:province":"NSW",
    "sg:tags":[
        "pre-schools"
    ],
    "wof:name":"Lennox Head Community Preschool",
    "wof:placetype":"venue"
},
  "geometry": {"coordinates":[153.59364318900001,-28.793598175],"type":"Point"}
}