{
  "type": "Feature",
  "properties": {
    "addr:full":"1130 Padman Drv Albury NSW 2640",
    "addr:housenumber":"1130",
    "addr:postcode":"2640",
    "addr:street":"Padman Drv",
    "iso:country":"AU",
    "sg:address":"1130 Padman Drv",
    "sg:city":"Albury",
    "sg:classifiers":[
        {
            "category":"Health Services",
            "subcategory":"Doctor",
            "type":"Services"
        }
    ],
    "sg:phone":"+61 2 6021 3336",
    "sg:postcode":"2640",
    "sg:province":"NSW",
    "sg:tags":[
        "podiatrist"
    ],
    "wof:name":"Byrnes Louise",
    "wof:placetype":"venue"
},
  "geometry": {"coordinates":[146.750274658,-36.0170402527],"type":"Point"}
}