{
  "type": "Feature",
  "properties": {
    "addr:full":"4 Maddick La Burpengary QLD 4505",
    "addr:housenumber":"4",
    "addr:postcode":"4505",
    "addr:street":"Maddick La",
    "iso:country":"AU",
    "sg:address":"4 Maddick La",
    "sg:city":"Burpengary",
    "sg:classifiers":[
        {
            "category":"Building & Trades",
            "subcategory":"Construction",
            "type":"Services"
        }
    ],
    "sg:phone":"+61 7 5498 5617",
    "sg:postcode":"4505",
    "sg:province":"QLD",
    "sg:tags":[
        "contractor"
    ],
    "wof:name":"Roberts Home Improvements Pty Ltd",
    "wof:placetype":"venue"
},
  "geometry": {"coordinates":[152.961669922,-27.1311035156],"type":"Point"}
}