{
  "type": "Feature",
  "properties": {
    "addr:full":"228 Malvern Rd Prahran VIC 3181",
    "addr:housenumber":"228",
    "addr:postcode":"3181",
    "addr:street":"Malvern Rd",
    "iso:country":"AU",
    "sg:address":"228 Malvern Rd",
    "sg:city":"Prahran",
    "sg:classifiers":[
        {
            "category":"Health Services",
            "subcategory":"Dentist",
            "type":"Services"
        }
    ],
    "sg:phone":"+61 3 9510 2313",
    "sg:postcode":"3181",
    "sg:province":"VIC",
    "wof:name":"Prahran Dental Group",
    "wof:placetype":"venue"
},
  "geometry": {"coordinates":[144.99482727,-37.847076416],"type":"Point"}
}