{
  "type": "Feature",
  "properties": {
    "iso:country":"AU",
    "sg:address":"145 High St",
    "sg:city":"Maryborough",
    "sg:classifiers":[
        {
            "category":"Arts & Performance",
            "subcategory":"Music",
            "type":"Entertainment"
        }
    ],
    "sg:phone":"+61 3 5461 1054",
    "sg:postcode":"3465",
    "sg:province":"VIC",
    "sg:tags":[
        "mobile",
        "jockey",
        "disc"
    ],
    "wof:name":"Top Band Wild Thing",
    "wof:placetype":"venue"
},
  "geometry": {"coordinates":[143.73829650900001,-37.0462684631],"type":"Point"}
}