{
  "type": "Feature",
  "properties": {
    "iso:country":"AU",
    "sg:address":"46 Alma Rd",
    "sg:city":"St Kilda",
    "sg:classifiers":[
        {
            "category":"Professional",
            "subcategory":"Research",
            "type":"Services"
        }
    ],
    "sg:phone":"+61 3 9534 2625",
    "sg:postcode":"3182",
    "sg:province":"VIC",
    "sg:tags":[
        "market"
    ],
    "wof:name":"Tremayne Consulting Group",
    "wof:placetype":"venue"
},
  "geometry": {"coordinates":[144.98696899399999,-37.8606796265],"type":"Point"}
}