{
  "type": "Feature",
  "properties": {
    "addr:full":"Shp 1112, Carousel Westfield, 1382 Albany Hwy Cannington WA 6107",
    "addr:housenumber":"1112;1382",
    "addr:postcode":"6107",
    "addr:street":"Carousel Westfield;Albany Hwy",
    "iso:country":"AU",
    "sg:address":"Shp 1112, Carousel Westfield, 1382 Albany Hwy",
    "sg:city":"Cannington",
    "sg:classifiers":[
        {
            "category":"Shopping",
            "subcategory":"Clothing, Apparel, & Fashions",
            "type":"Retail Goods"
        }
    ],
    "sg:phone":"+61 8 9358 1399",
    "sg:postcode":"6107",
    "sg:province":"WA",
    "sg:tags":[
        "lady",
        "wear"
    ],
    "wof:name":"Buss",
    "wof:placetype":"venue"
},
  "geometry": {"coordinates":[115.948387146,-32.0278816223],"type":"Point"}
}