{
  "type": "Feature",
  "properties": {
    "addr:full":"109 Oxley Ave Woody Point QLD 4019",
    "addr:housenumber":"109",
    "addr:postcode":"4019",
    "addr:street":"Oxley Ave",
    "iso:country":"AU",
    "sg:address":"109 Oxley Ave",
    "sg:city":"Woody Point",
    "sg:classifiers":[
        {
            "category":"Education",
            "subcategory":"Special Training",
            "type":"Public Place"
        }
    ],
    "sg:phone":"+61 7 3889 4527",
    "sg:postcode":"4019",
    "sg:province":"QLD",
    "sg:tags":[
        "drama",
        "tuition"
    ],
    "wof:name":"Basil Grumble Drama School",
    "wof:placetype":"venue"
},
  "geometry": {"coordinates":[153.10423278799999,-27.2570743561],"type":"Point"}
}