{
  "type": "Feature",
  "properties": {
    "iso:country":"AU",
    "sg:address":"9 Quilan Crt",
    "sg:city":"Caroline Springs",
    "sg:classifiers":[
        {
            "category":"Professional",
            "subcategory":"Accounting & Tax Preparation",
            "type":"Services"
        }
    ],
    "sg:phone":"+61 1300 723 483",
    "sg:postcode":"3023",
    "sg:province":"VIC",
    "sg:tags":[
        "jukebox"
    ],
    "wof:name":"Adams Juke Box Karaoke Hire",
    "wof:placetype":"venue"
},
  "geometry": {"coordinates":[144.740555,-37.74432],"type":"Point"}
}