{
  "type": "Feature",
  "properties": {
    "iso:country":"AU",
    "sg:address":"29 Woodland St",
    "sg:city":"Strathmore",
    "sg:classifiers":[
        {
            "category":"Health Services",
            "subcategory":"Health Practitioner",
            "type":"Services"
        }
    ],
    "sg:phone":"+61 3 9374 2664",
    "sg:postcode":"3041",
    "sg:province":"VIC",
    "sg:tags":[
        "naturopath"
    ],
    "wof:name":"Renee Loricchiecca",
    "wof:placetype":"venue"
},
  "geometry": {"coordinates":[144.92584228499999,-37.7433242798],"type":"Point"}
}