{
  "type": "Feature",
  "properties": {
    "addr:full":"13 Keerock Ave Seaford VIC 3198",
    "addr:housenumber":"13",
    "addr:postcode":"3198",
    "addr:street":"Keerock Ave",
    "iso:country":"AU",
    "sg:address":"13 Keerock Ave",
    "sg:city":"Seaford",
    "sg:classifiers":[
        {
            "category":"Utilities",
            "subcategory":"Refuse",
            "type":"Services"
        }
    ],
    "sg:phone":"+61 418 310 304",
    "sg:postcode":"3198",
    "sg:province":"VIC",
    "sg:tags":[
        "remover",
        "rubbish"
    ],
    "wof:name":"Bayline & Frankston Cheapest Skips",
    "wof:placetype":"venue"
},
  "geometry": {"coordinates":[145.14837646500001,-38.1085319519],"type":"Point"}
}