{
  "type": "Feature",
  "properties": {
    "addr:full":"18/ 621 Toorak Rd Toorak VIC 3142",
    "addr:housenumber":"18 / 621",
    "addr:postcode":"3142",
    "addr:street":"Toorak Rd",
    "iso:country":"AU",
    "sg:address":"18/ 621 Toorak Rd",
    "sg:city":"Toorak",
    "sg:classifiers":[
        {
            "category":"Education",
            "subcategory":"Special Training",
            "type":"Public Place"
        }
    ],
    "sg:phone":"+61 3 9822 0692",
    "sg:postcode":"3142",
    "sg:province":"VIC",
    "sg:tags":[
        "drama",
        "speech",
        "speaking",
        "tuition"
    ],
    "wof:name":"Benness Enterprises",
    "wof:placetype":"venue"
},
  "geometry": {"coordinates":[145.023803711,-37.8426933289],"type":"Point"}
}