{
  "type": "Feature",
  "properties": {
    "addr:full":"456 Magill Rd Kensington Gardens SA 5068",
    "addr:housenumber":"456",
    "addr:postcode":"5068",
    "addr:street":"Magill Rd",
    "iso:country":"AU",
    "sg:address":"456 Magill Rd",
    "sg:city":"Kensington Gardens",
    "sg:classifiers":[
        {
            "category":"Professional",
            "subcategory":"Computer Services",
            "type":"Services"
        }
    ],
    "sg:phone":"+61 8 8361 2961",
    "sg:postcode":"5068",
    "sg:province":"SA",
    "sg:tags":[
        "package",
        "software"
    ],
    "wof:name":"Bob Packenham Computing",
    "wof:placetype":"venue"
},
  "geometry": {"coordinates":[138.66410827600001,-34.9137535095],"type":"Point"}
}