{
  "type": "Feature",
  "properties": {
    "iso:country":"AU",
    "sg:address":"17 New Beith Rd",
    "sg:city":"Greenbank",
    "sg:classifiers":[
        {
            "category":"Building & Trades",
            "subcategory":"Construction",
            "type":"Services"
        }
    ],
    "sg:phone":"+61 7 3200 0281",
    "sg:postcode":"4124",
    "sg:province":"QLD",
    "sg:tags":[
        "concrete",
        "contractor"
    ],
    "wof:name":"Petersen L.J.& R.",
    "wof:placetype":"venue"
},
  "geometry": {"coordinates":[152.97698974599999,-27.7140426636],"type":"Point"}
}