{
  "type": "Feature",
  "properties": {
    "iso:country":"AU",
    "sg:address":"PO Box 461",
    "sg:city":"Moss Vale",
    "sg:classifiers":[
        {
            "category":"Home & Garden",
            "subcategory":"Building Materials",
            "type":"Retail Goods"
        }
    ],
    "sg:phone":"+61 2 4869 1805",
    "sg:postcode":"2577",
    "sg:province":"NSW",
    "sg:tags":[
        "ventilating",
        "equipment",
        "system"
    ],
    "wof:name":"Aversatile Pest Control",
    "wof:placetype":"venue"
},
  "geometry": {"coordinates":[150.371170044,-34.5501289368],"type":"Point"}
}