{
  "type": "Feature",
  "properties": {
    "iso:country":"AU",
    "sg:address":"Suite 6 331 Barrenjoey Rd",
    "sg:city":"Newport Beach",
    "sg:classifiers":[
        {
            "category":"Health Services",
            "subcategory":"Dentist",
            "type":"Services"
        }
    ],
    "sg:phone":"+61 2 9997 5848",
    "sg:postcode":"2106",
    "sg:province":"NSW",
    "wof:name":"Newport Gentle Dental Care",
    "wof:placetype":"venue"
},
  "geometry": {"coordinates":[151.31927490199999,-33.6557235718],"type":"Point"}
}