{
  "type": "Feature",
  "properties": {
    "addr:full":"227 Princess Hwy Ulladulla NSW 2539",
    "addr:housenumber":"227",
    "addr:postcode":"2539",
    "addr:street":"Princess Hwy",
    "iso:country":"AU",
    "sg:address":"227 Princess Hwy",
    "sg:city":"Ulladulla",
    "sg:classifiers":[
        {
            "category":"Shopping",
            "subcategory":"Antiques",
            "type":"Retail Goods"
        }
    ],
    "sg:phone":"+61 2 4455 7007",
    "sg:postcode":"2539",
    "sg:province":"NSW",
    "sg:tags":[
        "restoration",
        "reproduction"
    ],
    "wof:name":"Zaman Dulu Asian emporium",
    "wof:placetype":"venue"
},
  "geometry": {"coordinates":[150.47038269000001,-35.3674736023],"type":"Point"}
}