{
  "type": "Feature",
  "properties": {
    "addr:full":"WestBeach Outlet Shop 41 Tetley Hill Rd West Beach SA 5024",
    "addr:housenumber":"41",
    "addr:postcode":"5024",
    "addr:street":"Tetley Hill Rd",
    "iso:country":"AU",
    "sg:address":"WestBeach Outlet Shop 41 Tetley Hill Rd",
    "sg:city":"West Beach",
    "sg:classifiers":[
        {
            "category":"Shopping",
            "subcategory":"Clothing, Apparel, & Fashions",
            "type":"Retail Goods"
        }
    ],
    "sg:phone":"+61 8 8355 0577",
    "sg:postcode":"5024",
    "sg:province":"SA",
    "sg:tags":[
        "menswear"
    ],
    "wof:name":"Ed Harry Menswear",
    "wof:placetype":"venue"
},
  "geometry": {"coordinates":[138.51683044399999,-34.9363937378],"type":"Point"}
}