{
  "type": "Feature",
  "properties": {
    "addr:full":"115 Grange Rd Allenby Gardens SA 5009",
    "addr:housenumber":"115",
    "addr:postcode":"5009",
    "addr:street":"Grange Rd",
    "iso:country":"AU",
    "sg:address":"115 Grange Rd",
    "sg:city":"Allenby Gardens",
    "sg:classifiers":[
        {
            "category":"Health Services",
            "subcategory":"Dentist",
            "type":"Services"
        }
    ],
    "sg:phone":"+61 8 8340 1555",
    "sg:postcode":"5009",
    "sg:province":"SA",
    "wof:name":"Gatoudis A J",
    "wof:placetype":"venue"
},
  "geometry": {"coordinates":[138.553024292,-34.9042854309],"type":"Point"}
}