{
  "type": "Feature",
  "properties": {
    "addr:full":"Greystanes Rd Greystanes NSW 2145",
    "addr:postcode":"2145",
    "addr:street":"Greystanes Rd",
    "iso:country":"AU",
    "sg:address":"Greystanes Rd",
    "sg:city":"Greystanes",
    "sg:classifiers":[
        {
            "category":"Professional",
            "type":"Services"
        }
    ],
    "sg:phone":"+61 2 9688 9839",
    "sg:postcode":"2145",
    "sg:province":"NSW",
    "sg:tags":[
        "transport"
    ],
    "wof:name":"Boral Transport",
    "wof:placetype":"venue"
},
  "geometry": {"coordinates":[150.934356689,-33.8159675598],"type":"Point"}
}