{
  "type": "Feature",
  "properties": {
    "iso:country":"AU",
    "sg:address":"509 Princes Hwy",
    "sg:city":"Narre Warren",
    "sg:classifiers":[
        {
            "category":"Health Services",
            "subcategory":"Chiropractor",
            "type":"Services"
        }
    ],
    "sg:phone":"+61 3 9704 6478",
    "sg:postcode":"3805",
    "sg:province":"VIC",
    "wof:name":"Narre Warren Chiropractic Centre",
    "wof:placetype":"venue"
},
  "geometry": {"coordinates":[145.310135,-38.027233],"type":"Point"}
}