{
  "type": "Feature",
  "properties": {
    "addr:full":"18 Mirrool St Ardlethan NSW 2665",
    "addr:housenumber":"18",
    "addr:postcode":"2665",
    "addr:street":"Mirrool St",
    "iso:country":"AU",
    "sg:address":"18 Mirrool St",
    "sg:city":"Ardlethan",
    "sg:classifiers":[
        {
            "category":"Professional",
            "subcategory":"Engineering",
            "type":"Services"
        }
    ],
    "sg:phone":"+61 2 6978 2025",
    "sg:postcode":"2665",
    "sg:province":"NSW",
    "sg:tags":[
        "engineer",
        "mechanical"
    ],
    "wof:name":"Haldens Auto Repairs",
    "wof:placetype":"venue"
},
  "geometry": {"coordinates":[146.897415161,-34.3570022583],"type":"Point"}
}