{
  "type": "Feature",
  "properties": {
    "iso:country":"AU",
    "sg:address":"Factory 10/ 19-23 Japaddy St",
    "sg:city":"Mordialloc",
    "sg:classifiers":[
        {
            "category":"Manufacturing",
            "subcategory":"Rubber & Plastics",
            "type":"Manufacturing & Wholesale Goods"
        }
    ],
    "sg:phone":"+61 3 9587 3833",
    "sg:postcode":"3195",
    "sg:province":"VIC",
    "sg:tags":[
        "wholesaler",
        "product",
        "mfrs"
    ],
    "wof:name":"Compco Pty Ltd",
    "wof:placetype":"venue"
},
  "geometry": {"coordinates":[145.105545044,-37.989151001],"type":"Point"}
}