{
  "type": "Feature",
  "properties": {
    "addr:full":"PO Box 41 Narooma NSW 2546",
    "addr:postcode":"2546",
    "iso:country":"AU",
    "sg:address":"PO Box 41",
    "sg:city":"Narooma",
    "sg:classifiers":[
        {
            "category":"Shopping",
            "subcategory":"Musical Instruments",
            "type":"Retail Goods"
        }
    ],
    "sg:phone":"+61 408 037 934",
    "sg:postcode":"2546",
    "sg:province":"NSW",
    "sg:tags":[
        "musician",
        "agent"
    ],
    "wof:name":"Clive Doreian",
    "wof:placetype":"venue"
},
  "geometry": {"coordinates":[150.132324219,-36.2188415527],"type":"Point"}
}