{
  "type": "Feature",
  "properties": {
    "addr:full":"33 Vivian St Boulder WA 6432",
    "addr:housenumber":"33",
    "addr:postcode":"6432",
    "addr:street":"Vivian St",
    "iso:country":"AU",
    "sg:address":"33 Vivian St",
    "sg:city":"Boulder",
    "sg:classifiers":[
        {
            "category":"Building & Trades",
            "subcategory":"Construction",
            "type":"Services"
        }
    ],
    "sg:phone":"+61 8 9093 2523",
    "sg:postcode":"6432",
    "sg:province":"WA",
    "sg:tags":[
        "fencing",
        "contractor"
    ],
    "wof:name":"Outback Industries",
    "wof:placetype":"venue"
},
  "geometry": {"coordinates":[121.495368958,-30.7902851105],"type":"Point"}
}