{
  "type": "Feature",
  "properties": {
    "addr:full":"PO Box 266 Rosny TAS 7018",
    "addr:postcode":"7018",
    "iso:country":"AU",
    "sg:address":"PO Box 266",
    "sg:city":"Rosny",
    "sg:classifiers":[
        {
            "category":"Social Services",
            "subcategory":"Retirement Home",
            "type":"Services"
        }
    ],
    "sg:phone":"+61 3 6244 6957",
    "sg:postcode":"7018",
    "sg:province":"TAS",
    "sg:tags":[
        "t-shirt",
        "supplier"
    ],
    "wof:name":"Print &#039;N&#039; Tell",
    "wof:placetype":"venue"
},
  "geometry": {"coordinates":[147.355545044,-42.8691101074],"type":"Point"}
}