{
  "type": "Feature",
  "properties": {
    "iso:country":"AU",
    "sg:address":"Hinkley Rd",
    "sg:city":"Gnowangerup",
    "sg:classifiers":[
        {
            "category":"Sports & Exercise",
            "subcategory":"Golf",
            "type":"Entertainment"
        }
    ],
    "sg:phone":"+61 8 9827 1222",
    "sg:postcode":"6335",
    "sg:province":"WA",
    "sg:tags":[
        "club"
    ],
    "wof:name":"Gnowangerup Golf Club (Inc)",
    "wof:placetype":"venue"
},
  "geometry": {"coordinates":[118.03401184099999,-33.9324111938],"type":"Point"}
}