{
  "type": "Feature",
  "properties": {
    "iso:country":"AU",
    "sg:address":"252 Hammond Ave",
    "sg:city":"Wagga Wagga",
    "sg:classifiers":[
        {
            "category":"Wholesale",
            "subcategory":"Machinery & Supplies",
            "type":"Manufacturing & Wholesale Goods"
        }
    ],
    "sg:phone":"+61 2 6921 2148",
    "sg:postcode":"2650",
    "sg:province":"NSW",
    "sg:tags":[
        "agricultural"
    ],
    "wof:name":"Great Southern Motors Pty Ltd",
    "wof:placetype":"venue"
},
  "geometry": {"coordinates":[147.40834045400001,-35.1251525879],"type":"Point"}
}