{
  "type": "Feature",
  "properties": {
    "iso:country":"AU",
    "sg:address":"Level 6, 67 Castlereagh St",
    "sg:city":"Sydney",
    "sg:classifiers":[
        {
            "category":"Autos & Motor Vehicles",
            "subcategory":"Boat Sales",
            "type":"Retail Goods"
        }
    ],
    "sg:phone":"+61 2 9231 5161",
    "sg:postcode":"2000",
    "sg:province":"NSW",
    "sg:tags":[
        "dictating",
        "machine"
    ],
    "sg:website":"http://www.pcdictation.com.au",
    "wof:name":"Administrative Aid Pty Ltd",
    "wof:placetype":"venue"
},
  "geometry": {"coordinates":[151.20950317399999,-33.8692016602],"type":"Point"}
}