{
  "type": "Feature",
  "properties": {
    "iso:country":"AU",
    "sg:address":"Suite 11-13, 890 Canning Hwy",
    "sg:city":"Applecross",
    "sg:classifiers":[
        {
            "category":"Banks & Credit Unions",
            "subcategory":"Financial Services",
            "type":"Services"
        }
    ],
    "sg:phone":"+61 8 9364 2000",
    "sg:postcode":"6153",
    "sg:province":"WA",
    "sg:tags":[
        "annuity",
        "rollover",
        "superannuation",
        "consultant"
    ],
    "wof:name":"Framework Financial Planning",
    "wof:placetype":"venue"
},
  "geometry": {"coordinates":[115.847542,-32.013287],"type":"Point"}
}