{
  "type": "Feature",
  "properties": {
    "addr:full":"45 Wynyard Ave Rossmore NSW 2171",
    "addr:housenumber":"45",
    "addr:postcode":"2171",
    "addr:street":"Wynyard Ave",
    "iso:country":"AU",
    "sg:address":"45 Wynyard Ave",
    "sg:city":"Rossmore",
    "sg:classifiers":[
        {
            "category":"Farming",
            "subcategory":"Nursery",
            "type":"Manufacturing & Wholesale Goods"
        }
    ],
    "sg:phone":"+61 2 9606 4086",
    "sg:postcode":"2171",
    "sg:province":"NSW",
    "wof:name":"De Vries Wholesale Nurseries",
    "wof:placetype":"venue"
},
  "geometry": {"coordinates":[150.99270629899999,-33.8980293274],"type":"Point"}
}