{
  "type": "Feature",
  "properties": {
    "iso:country":"AU",
    "sg:address":"245 Campbell St",
    "sg:city":"Swan Hill",
    "sg:classifiers":[
        {
            "category":"Professional",
            "subcategory":"Printing & Photocopies",
            "type":"Services"
        }
    ],
    "sg:phone":"+61 3 5033 2177",
    "sg:postcode":"3585",
    "sg:province":"VIC",
    "sg:tags":[
        "photocopying"
    ],
    "wof:name":"Swan Hill Copy Centre",
    "wof:placetype":"venue"
},
  "geometry": {"coordinates":[143.560455,-35.341381],"type":"Point"}
}