{
  "type": "Feature",
  "properties": {
    "addr:full":"144 New Town Rd New Town TAS 7008",
    "addr:housenumber":"144",
    "addr:postcode":"7008",
    "addr:street":"New Town Rd",
    "iso:country":"AU",
    "sg:address":"144 New Town Rd",
    "sg:city":"New Town",
    "sg:classifiers":[
        {
            "category":"Autos & Motor Vehicles",
            "subcategory":"Automobile Sales",
            "type":"Retail Goods"
        }
    ],
    "sg:phone":"+61 3 6278 9000",
    "sg:postcode":"7008",
    "sg:province":"TAS",
    "sg:tags":[
        "car",
        "used"
    ],
    "wof:name":"Kruse Motor Company",
    "wof:placetype":"venue"
},
  "geometry": {"coordinates":[147.30633544899999,-42.8599357605],"type":"Point"}
}