{
  "type": "Feature",
  "properties": {
    "iso:country":"AU",
    "sg:address":"17 Pickwick St",
    "sg:city":"Cannon Hill",
    "sg:classifiers":[
        {
            "category":"Utilities",
            "subcategory":"Water",
            "type":"Services"
        }
    ],
    "sg:phone":"+61 7 3399 5333",
    "sg:postcode":"4170",
    "sg:province":"QLD",
    "sg:tags":[
        "equipment",
        "treatment"
    ],
    "wof:name":"Aquacorp P/L",
    "wof:placetype":"venue"
},
  "geometry": {"coordinates":[153.094146728,-27.4707508087],"type":"Point"}
}