{
  "type": "Feature",
  "properties": {
    "addr:full":"Cnr Wellington & Outram Sts West Perth WA 6005",
    "addr:postcode":"6005",
    "addr:street":"Cnr Wellington & Outram Sts",
    "iso:country":"AU",
    "sg:address":"Cnr Wellington & Outram Sts",
    "sg:city":"West Perth",
    "sg:classifiers":[
        {
            "category":"Shopping",
            "subcategory":"Computers & Home Electronics",
            "type":"Retail Goods"
        }
    ],
    "sg:phone":"+61 8 9226 1500",
    "sg:postcode":"6005",
    "sg:province":"WA",
    "sg:tags":[
        "hardware",
        "equipment"
    ],
    "wof:name":"Arrow Computers",
    "wof:placetype":"venue"
},
  "geometry": {"coordinates":[115.845932007,-31.9471607208],"type":"Point"}
}