{
  "type": "Feature",
  "properties": {
    "addr:full":"Scenic Drv Narooma NSW 2546",
    "addr:postcode":"2546",
    "addr:street":"Scenic Drv",
    "iso:country":"AU",
    "sg:address":"Scenic Drv",
    "sg:city":"Narooma",
    "sg:classifiers":[
        {
            "category":"Health Services",
            "subcategory":"Health Practitioner",
            "type":"Services"
        }
    ],
    "sg:phone":"+61 2 4476 4009",
    "sg:postcode":"2546",
    "sg:province":"NSW",
    "sg:tags":[
        "psychologist"
    ],
    "wof:name":"Willis Adrian",
    "wof:placetype":"venue"
},
  "geometry": {"coordinates":[150.054122925,-36.4059562683],"type":"Point"}
}