{
  "type": "Feature",
  "properties": {
    "addr:full":"199 Waverley Rd Malvern East VIC 3145",
    "addr:housenumber":"199",
    "addr:postcode":"3145",
    "addr:street":"Waverley Rd",
    "iso:country":"AU",
    "sg:address":"199 Waverley Rd",
    "sg:city":"Malvern East",
    "sg:classifiers":[
        {
            "category":"Health Services",
            "subcategory":"Health Practitioner",
            "type":"Services"
        }
    ],
    "sg:phone":"+61 3 9571 5843",
    "sg:postcode":"3145",
    "sg:province":"VIC",
    "sg:tags":[
        "pathologist",
        "speech"
    ],
    "wof:name":"Brenda Carey",
    "wof:placetype":"venue"
},
  "geometry": {"coordinates":[145.05177307100001,-37.8762245178],"type":"Point"}
}