{
  "type": "Feature",
  "properties": {
    "addr:full":"234 Pimpala Rd Woodcroft SA 5162",
    "addr:housenumber":"234",
    "addr:postcode":"5162",
    "addr:street":"Pimpala Rd",
    "iso:country":"AU",
    "sg:address":"234 Pimpala Rd",
    "sg:city":"Woodcroft",
    "sg:classifiers":[
        {
            "category":"Social Services",
            "subcategory":"Child Care",
            "type":"Services"
        }
    ],
    "sg:phone":"+61 8 8387 4533",
    "sg:postcode":"5162",
    "sg:province":"SA",
    "wof:name":"Green Vale Child Care Centre.",
    "wof:placetype":"venue"
},
  "geometry": {"coordinates":[138.55528259299999,-35.103767395],"type":"Point"}
}