{
  "type": "Feature",
  "properties": {
    "iso:country":"AU",
    "sg:address":"30- 32 Powers Rd",
    "sg:city":"Seven Hills",
    "sg:classifiers":[
        {
            "category":"Banks & Credit Unions",
            "subcategory":"Atm",
            "type":"Services"
        }
    ],
    "sg:phone":"+61 2 9624 6455",
    "sg:postcode":"2147",
    "sg:province":"NSW",
    "sg:tags":[
        "reconditioners",
        "drum",
        "manufacturers"
    ],
    "wof:name":"Drum Reconditioners (N.S.W.) Pty Ltd",
    "wof:placetype":"venue"
},
  "geometry": {"coordinates":[150.945800781,-33.7738761902],"type":"Point"}
}