{
  "type": "Feature",
  "properties": {
    "iso:country":"AU",
    "sg:address":"206 Main Rd",
    "sg:city":"Blackwood",
    "sg:classifiers":[
        {
            "category":"Fast Food",
            "type":"Food & Drink"
        }
    ],
    "sg:phone":"+61 8 8278 2444",
    "sg:postcode":"5051",
    "sg:province":"SA",
    "sg:tags":[
        "away",
        "take"
    ],
    "wof:name":"Sturt Dial-A-Pizza",
    "wof:placetype":"venue"
},
  "geometry": {"coordinates":[138.61644,-35.017185],"type":"Point"}
}