{
  "type": "Feature",
  "properties": {
    "iso:country":"AU",
    "sg:address":"51 Pymble Ave",
    "sg:city":"Inverloch",
    "sg:classifiers":[
        {
            "category":"Building & Trades",
            "subcategory":"Plumbing",
            "type":"Services"
        }
    ],
    "sg:phone":"+61 3 5674 1969",
    "sg:postcode":"3996",
    "sg:province":"VIC",
    "sg:tags":[
        "plumber",
        "gasfitters"
    ],
    "wof:name":"Catt Bros Pty Ltd",
    "wof:placetype":"venue"
},
  "geometry": {"coordinates":[145.73674,-38.628647],"type":"Point"}
}