{
  "type": "Feature",
  "properties": {
    "addr:full":"20 Leyland Ave Deception Bay QLD 4508",
    "addr:housenumber":"20",
    "addr:postcode":"4508",
    "addr:street":"Leyland Ave",
    "iso:country":"AU",
    "sg:address":"20 Leyland Ave",
    "sg:city":"Deception Bay",
    "sg:classifiers":[
        {
            "category":"Home & Garden",
            "subcategory":"Garden Supply",
            "type":"Retail Goods"
        }
    ],
    "sg:phone":"+61 7 3204 7446",
    "sg:postcode":"4508",
    "sg:province":"QLD",
    "sg:tags":[
        "equipment"
    ],
    "wof:name":"Mushroom Compost",
    "wof:placetype":"venue"
},
  "geometry": {"coordinates":[153.01872253400001,-27.1935214996],"type":"Point"}
}