{
  "type": "Feature",
  "properties": {
    "addr:full":"Shop 5B, Coonan St Indooroopilly QLD 4068",
    "addr:housenumber":"shop 5b",
    "addr:postcode":"4068",
    "addr:street":"Coonan St",
    "iso:country":"AU",
    "sg:address":"Shop 5B, Coonan St",
    "sg:city":"Indooroopilly",
    "sg:classifiers":[
        {
            "category":"Home & Garden",
            "subcategory":"Carpets & Floor Coverings",
            "type":"Retail Goods"
        }
    ],
    "sg:phone":"+61 7 3378 6200",
    "sg:postcode":"4068",
    "sg:province":"QLD",
    "sg:tags":[
        "tile",
        "wall"
    ],
    "wof:name":"Andersens Ceramics",
    "wof:placetype":"venue"
},
  "geometry": {"coordinates":[152.971359253,-27.4979820251],"type":"Point"}
}