{
  "type": "Feature",
  "properties": {
    "addr:full":"Unit 6 Homemaker Village East, 356 Bagot Rd Millner NT 0810",
    "addr:postcode":"nt 0810",
    "addr:street":"East 356 Bagot Rd",
    "iso:country":"AU",
    "sg:address":"Unit 6 Homemaker Village East, 356 Bagot Rd",
    "sg:city":"Millner",
    "sg:classifiers":[
        {
            "category":"Sports & Exercise",
            "subcategory":"Gym",
            "type":"Entertainment"
        }
    ],
    "sg:phone":"+61 8 8923 1133",
    "sg:postcode":"0810",
    "sg:province":"NT",
    "sg:tags":[
        "health",
        "fitness"
    ],
    "wof:name":"Fernwood Women's Health Clubs",
    "wof:placetype":"venue"
},
  "geometry": {"coordinates":[130.85624694800001,-12.3921422958],"type":"Point"}
}