{
  "type": "Feature",
  "properties": {
    "iso:country":"AU",
    "sg:address":"33 New City Rd",
    "sg:city":"Mullumbimby",
    "sg:classifiers":[
        {
            "category":"Health Services",
            "subcategory":"Health Practitioner",
            "type":"Services"
        }
    ],
    "sg:phone":"+61 411 170 468",
    "sg:postcode":"2482",
    "sg:province":"NSW",
    "sg:tags":[
        "osteopath"
    ],
    "wof:name":"Amelia Lemon",
    "wof:placetype":"venue"
},
  "geometry": {"coordinates":[153.506881714,-28.5553264618],"type":"Point"}
}