{
  "type": "Feature",
  "properties": {
    "addr:full":"31 Mansfield Ave Caringbah NSW 2229",
    "addr:housenumber":"31",
    "addr:postcode":"2229",
    "addr:street":"Mansfield Ave",
    "iso:country":"AU",
    "sg:address":"31 Mansfield Ave",
    "sg:city":"Caringbah",
    "sg:classifiers":[
        {
            "category":"Fast Food",
            "type":"Food & Drink"
        }
    ],
    "sg:phone":"+61 2 9525 4555",
    "sg:postcode":"2229",
    "sg:province":"NSW",
    "sg:tags":[
        "away",
        "take"
    ],
    "wof:name":"Gourmet Inn Chinese Take-Away",
    "wof:placetype":"venue"
},
  "geometry": {"coordinates":[151.12379455600001,-34.0440139771],"type":"Point"}
}