{
  "type": "Feature",
  "properties": {
    "iso:country":"AU",
    "sg:address":"343- 345 Old Geelong Rd",
    "sg:city":"Hoppers Crossing",
    "sg:classifiers":[
        {
            "category":"Banks & Credit Unions",
            "subcategory":"Financial Services",
            "type":"Services"
        }
    ],
    "sg:phone":"+61 3 9360 0200",
    "sg:postcode":"3029",
    "sg:province":"VIC",
    "sg:tags":[
        "hire",
        "uniform"
    ],
    "wof:name":"Hudsons Uniform Service",
    "wof:placetype":"venue"
},
  "geometry": {"coordinates":[144.722534,-37.872932],"type":"Point"}
}