{
  "type": "Feature",
  "properties": {
    "addr:full":"40 Cumner Rd Gatton QLD 4343",
    "addr:housenumber":"40",
    "addr:postcode":"4343",
    "addr:street":"Cumner Rd",
    "iso:country":"AU",
    "sg:address":"40 Cumner Rd",
    "sg:city":"Gatton",
    "sg:classifiers":[
        {
            "category":"Home & Garden",
            "subcategory":"Garden Supply",
            "type":"Retail Goods"
        }
    ],
    "sg:phone":"+61 7 5462 5100",
    "sg:postcode":"4343",
    "sg:province":"QLD",
    "sg:tags":[
        "equipment"
    ],
    "wof:name":"D & D Hardwood Supplies",
    "wof:placetype":"venue"
},
  "geometry": {"coordinates":[152.28770446799999,-27.5503902435],"type":"Point"}
}