{
  "type": "Feature",
  "properties": {
    "iso:country":"AU",
    "sg:address":"Coles Complex Shop 2 Urana Rd",
    "sg:city":"Lavington",
    "sg:classifiers":[
        {
            "category":"Manufacturing",
            "subcategory":"Food",
            "type":"Manufacturing & Wholesale Goods"
        }
    ],
    "sg:phone":"+61 2 6025 1448",
    "sg:postcode":"2641",
    "sg:province":"NSW",
    "sg:tags":[
        "function",
        "catering"
    ],
    "wof:name":"Tony Harts Quality Meats",
    "wof:placetype":"venue"
},
  "geometry": {"coordinates":[146.90838623100001,-36.0213737488],"type":"Point"}
}