{
  "type": "Feature",
  "properties": {
    "addr:full":"4/ 8 Young St East Maitland NSW 2323",
    "addr:housenumber":"/ 8",
    "addr:postcode":"2323",
    "addr:street":"Young St",
    "iso:country":"AU",
    "sg:address":"4/ 8 Young St",
    "sg:city":"East Maitland",
    "sg:classifiers":[
        {
            "category":"Communications",
            "subcategory":"Television Station",
            "type":"Services"
        }
    ],
    "sg:phone":"+61 2 4933 3148",
    "sg:postcode":"2323",
    "sg:province":"NSW",
    "sg:tags":[
        "screening",
        "machinery",
        "grading"
    ],
    "wof:name":"AA Symphony Piano Harp Screens",
    "wof:placetype":"venue"
},
  "geometry": {"coordinates":[151.59896850600001,-32.7532157898],"type":"Point"}
}