{
  "type": "Feature",
  "properties": {
    "addr:full":"Lot 11 3 Hereford St Berkeley Vale NSW 2261",
    "addr:housenumber":"3",
    "addr:postcode":"2261",
    "addr:street":"Hereford St",
    "iso:country":"AU",
    "sg:address":"Lot 11 3 Hereford St",
    "sg:city":"Berkeley Vale",
    "sg:classifiers":[
        {
            "category":"Industrial Area",
            "type":"Public Place"
        }
    ],
    "sg:phone":"+61 2 4389 1434",
    "sg:postcode":"2261",
    "sg:province":"NSW",
    "sg:tags":[
        "protective",
        "clothing"
    ],
    "wof:name":"Lawrence & Hanson",
    "wof:placetype":"venue"
},
  "geometry": {"coordinates":[151.42529300000001,-33.328648],"type":"Point"}
}