{
  "type": "Feature",
  "properties": {
    "iso:country":"AU",
    "sg:address":"Walpole St",
    "sg:city":"Millmerran",
    "sg:classifiers":[
        {
            "category":"Government",
            "subcategory":"Post Office",
            "type":"Public Place"
        }
    ],
    "sg:phone":"+61 7 4695 1147",
    "sg:postcode":"4357",
    "sg:province":"QLD",
    "sg:tags":[
        "postal"
    ],
    "wof:name":"Australia Post",
    "wof:placetype":"venue"
},
  "geometry": {"coordinates":[151.27053799999999,-27.87389],"type":"Point"}
}