{
  "type": "Feature",
  "properties": {
    "iso:country":"AU",
    "sg:address":"65 Leyland St",
    "sg:city":"Townsville",
    "sg:classifiers":[
        {
            "category":"Manufacturing",
            "subcategory":"Retail Goods",
            "type":"Manufacturing & Wholesale Goods"
        }
    ],
    "sg:phone":"+61 7 4725 1588",
    "sg:postcode":"4810",
    "sg:province":"QLD",
    "sg:tags":[
        "merchant",
        "pump",
        "mfrs"
    ],
    "wof:name":"Onga Pty Ltd",
    "wof:placetype":"venue"
},
  "geometry": {"coordinates":[146.761017,-19.27157],"type":"Point"}
}