{
  "type": "Feature",
  "properties": {
    "addr:full":"Kalamunda Hotel, 43 Railway Rd Kalamunda WA 6076",
    "addr:housenumber":"43",
    "addr:postcode":"6076",
    "addr:street":"Railway Rd",
    "iso:country":"AU",
    "sg:address":"Kalamunda Hotel, 43 Railway Rd",
    "sg:city":"Kalamunda",
    "sg:classifiers":[
        {
            "category":"Food & Beverages",
            "subcategory":"Liquor & Beverages",
            "type":"Retail Goods"
        }
    ],
    "sg:phone":"+61 8 9257 1084",
    "sg:postcode":"6076",
    "sg:province":"WA",
    "sg:tags":[
        "store"
    ],
    "wof:name":"Sip'n Save Kalamunda",
    "wof:placetype":"venue"
},
  "geometry": {"coordinates":[116.059928894,-31.9721469879],"type":"Point"}
}