{
  "type": "Feature",
  "properties": {
    "addr:full":"Round Tower Rd Dandenong VIC 3175",
    "addr:postcode":"3175",
    "addr:street":"Tower Rd",
    "iso:country":"AU",
    "sg:address":"Round Tower Rd",
    "sg:city":"Dandenong",
    "sg:classifiers":[
        {
            "category":"Military Area",
            "subcategory":"Air Force Base",
            "type":"Public Place"
        }
    ],
    "sg:phone":"+61 3 9794 7777",
    "sg:postcode":"3175",
    "sg:province":"VIC",
    "sg:tags":[
        "wholesaler",
        "bag",
        "mfrs",
        "sack"
    ],
    "wof:name":"Australian Multiwall Bag Co Pty Ltd",
    "wof:placetype":"venue"
},
  "geometry": {"coordinates":[145.235565186,-38.0072174072],"type":"Point"}
}