{
  "type": "Feature",
  "properties": {
    "addr:full":"17 Meredith St Banyo QLD 4014",
    "addr:housenumber":"17",
    "addr:postcode":"4014",
    "addr:street":"Meredith St",
    "iso:country":"AU",
    "sg:address":"17 Meredith St",
    "sg:city":"Banyo",
    "sg:classifiers":[
        {
            "category":"Home & Garden",
            "subcategory":"Hardware",
            "type":"Retail Goods"
        }
    ],
    "sg:phone":"+61 7 3267 0510",
    "sg:postcode":"4014",
    "sg:province":"QLD",
    "sg:tags":[
        "printed",
        "circuit"
    ],
    "wof:name":"Ian Capps Electronics",
    "wof:placetype":"venue"
},
  "geometry": {"coordinates":[153.07943725600001,-27.3747425079],"type":"Point"}
}