{
  "type": "Feature",
  "properties": {
    "addr:full":"Auburn Rd Chinchilla QLD 4413",
    "addr:postcode":"4413",
    "addr:street":"Auburn Rd",
    "iso:country":"AU",
    "sg:address":"Auburn Rd",
    "sg:city":"Chinchilla",
    "sg:classifiers":[
        {
            "category":"Utilities",
            "subcategory":"Electric",
            "type":"Services"
        }
    ],
    "sg:phone":"+61 7 4662 7954",
    "sg:postcode":"4413",
    "sg:province":"QLD",
    "sg:tags":[
        "electrical",
        "contractor"
    ],
    "wof:name":"Bell G R & C L",
    "wof:placetype":"venue"
},
  "geometry": {"coordinates":[150.61219787600001,-26.7200813293],"type":"Point"}
}