{
  "type": "Feature",
  "properties": {
    "addr:full":"54- 58 Lipton Drv Thomastown VIC 3074",
    "addr:housenumber":"58",
    "addr:postcode":"3074",
    "addr:street":"Lipton Drv",
    "iso:country":"AU",
    "sg:address":"54- 58 Lipton Drv",
    "sg:city":"Thomastown",
    "sg:classifiers":[
        {
            "category":"Utilities",
            "subcategory":"Electric",
            "type":"Services"
        }
    ],
    "sg:phone":"+61 3 9462 0600",
    "sg:postcode":"3074",
    "sg:province":"VIC",
    "sg:tags":[
        "electrical",
        "contractor"
    ],
    "wof:name":"Lenmic Pty Ltd",
    "wof:placetype":"venue"
},
  "geometry": {"coordinates":[144.99508667000001,-37.6891555786],"type":"Point"}
}