{
  "type": "Feature",
  "properties": {
    "addr:full":"7 Longstaff St Shepparton VIC 3630",
    "addr:housenumber":"7",
    "addr:postcode":"3630",
    "addr:street":"Longstaff St",
    "iso:country":"AU",
    "sg:address":"7 Longstaff St",
    "sg:city":"Shepparton",
    "sg:classifiers":[
        {
            "category":"Utilities",
            "subcategory":"Electric",
            "type":"Services"
        }
    ],
    "sg:phone":"+61 3 5822 2380",
    "sg:postcode":"3630",
    "sg:province":"VIC",
    "sg:tags":[
        "electrical",
        "contractor"
    ],
    "wof:name":"Munro T P",
    "wof:placetype":"venue"
},
  "geometry": {"coordinates":[145.391967773,-36.3957977295],"type":"Point"}
}