{
  "type": "Feature",
  "properties": {
    "addr:full":"430 Sheridan St North Cairns QLD 4870",
    "addr:housenumber":"430",
    "addr:postcode":"4870",
    "addr:street":"Sheridan St North",
    "iso:country":"AU",
    "sg:address":"430 Sheridan St",
    "sg:city":"North Cairns",
    "sg:classifiers":[
        {
            "category":"Home & Garden",
            "subcategory":"Building Materials",
            "type":"Retail Goods"
        }
    ],
    "sg:phone":"+61 7 4053 4188",
    "sg:postcode":"4870",
    "sg:province":"QLD",
    "sg:tags":[
        "merchant",
        "glass",
        "glazier"
    ],
    "wof:name":"O&#039;Brien",
    "wof:placetype":"venue"
},
  "geometry": {"coordinates":[145.75477600100001,-16.8958377838],"type":"Point"}
}