{
  "type": "Feature",
  "properties": {
    "addr:full":"9 Newcomen St Newcastle NSW 2300",
    "addr:housenumber":"9",
    "addr:postcode":"2300",
    "addr:street":"Newcomen St",
    "iso:country":"AU",
    "sg:address":"9 Newcomen St",
    "sg:city":"Newcastle",
    "sg:classifiers":[
        {
            "category":"Personal",
            "subcategory":"Beauty Salon",
            "type":"Services"
        }
    ],
    "sg:phone":"+61 2 4929 2816",
    "sg:postcode":"2300",
    "sg:province":"NSW",
    "sg:tags":[
        "hairdresser"
    ],
    "wof:name":"Harbourside Trimmers",
    "wof:placetype":"venue"
},
  "geometry": {"coordinates":[151.78227200000001,-32.927048],"type":"Point"}
}