{
  "type": "Feature",
  "properties": {
    "iso:country":"AU",
    "sg:address":"Lot 100 Estuary Drv",
    "sg:city":"Bunbury",
    "sg:classifiers":[
        {
            "category":"Building & Trades",
            "subcategory":"Cleaning & Sanitation",
            "type":"Services"
        }
    ],
    "sg:phone":"+61 417 975 825",
    "sg:postcode":"6230",
    "sg:province":"WA",
    "sg:tags":[
        "abrasive",
        "blasting"
    ],
    "wof:name":"South West Sandblasting Services",
    "wof:placetype":"venue"
},
  "geometry": {"coordinates":[115.689369,-33.318916],"type":"Point"}
}