{
  "type": "Feature",
  "properties": {
    "addr:full":"16 Cobbler Pl Mirrabooka WA 6061",
    "addr:housenumber":"16",
    "addr:postcode":"6061",
    "addr:street":"Cobbler Pl",
    "iso:country":"AU",
    "sg:address":"16 Cobbler Pl",
    "sg:city":"Mirrabooka",
    "sg:classifiers":[
        {
            "category":"Manufacturing",
            "subcategory":"Musical Instruments",
            "type":"Manufacturing & Wholesale Goods"
        }
    ],
    "sg:phone":"+61 8 9344 4080",
    "sg:postcode":"6061",
    "sg:province":"WA",
    "sg:tags":[
        "repair",
        "maker"
    ],
    "wof:name":"PKs Music",
    "wof:placetype":"venue"
},
  "geometry": {"coordinates":[115.86286926299999,-31.8738765717],"type":"Point"}
}