{
  "type": "Feature",
  "properties": {
    "addr:full":"23 Julia St Portland VIC 3305",
    "addr:housenumber":"23",
    "addr:postcode":"3305",
    "addr:street":"Julia St",
    "iso:country":"AU",
    "sg:address":"23 Julia St",
    "sg:city":"Portland",
    "sg:classifiers":[
        {
            "category":"Personal",
            "subcategory":"Beauty Salon",
            "type":"Services"
        }
    ],
    "sg:phone":"+61 3 5521 7410",
    "sg:postcode":"3305",
    "sg:province":"VIC",
    "wof:name":"Vivid Beauty",
    "wof:placetype":"venue"
},
  "geometry": {"coordinates":[141.604705811,-38.348526001],"type":"Point"}
}