{
  "type": "Feature",
  "properties": {
    "addr:full":"35 Cobden St North Melbourne VIC 3051",
    "addr:housenumber":"35",
    "addr:postcode":"3051",
    "addr:street":"Cobden St",
    "iso:country":"AU",
    "sg:address":"35 Cobden St",
    "sg:city":"North Melbourne",
    "sg:classifiers":[
        {
            "category":"Food & Beverages",
            "subcategory":"Liquor & Beverages",
            "type":"Retail Goods"
        }
    ],
    "sg:phone":"+61 3 9915 0640",
    "sg:postcode":"3051",
    "sg:province":"VIC",
    "sg:tags":[
        "store"
    ],
    "wof:name":"Inn-Keeper Bottleshops",
    "wof:placetype":"venue"
},
  "geometry": {"coordinates":[144.95721435600001,-37.8045196533],"type":"Point"}
}