{
  "type": "Feature",
  "properties": {
    "addr:full":"10 Clyde St St Kilda VIC 3182",
    "addr:housenumber":"10",
    "addr:postcode":"3182",
    "addr:street":"Clyde St",
    "iso:country":"AU",
    "sg:address":"10 Clyde St",
    "sg:city":"St Kilda",
    "sg:classifiers":[
        {
            "category":"Professional",
            "subcategory":"Management & Consulting",
            "type":"Services"
        }
    ],
    "sg:phone":"+61 3 9537 7633",
    "sg:postcode":"3182",
    "sg:province":"VIC",
    "sg:tags":[
        "consultant",
        "industrial",
        "relation"
    ],
    "wof:name":"Magellan Consulting Pty Ltd",
    "wof:placetype":"venue"
},
  "geometry": {"coordinates":[144.97753906200001,-37.8659706116],"type":"Point"}
}