{
  "type": "Feature",
  "properties": {
    "addr:full":"16a Bolton St Newcastle NSW 2300",
    "addr:housenumber":"16a",
    "addr:postcode":"2300",
    "addr:street":"Bolton St",
    "iso:country":"AU",
    "sg:address":"16a Bolton St",
    "sg:city":"Newcastle",
    "sg:classifiers":[
        {
            "category":"Organizations",
            "subcategory":"Professional Association",
            "type":"Services"
        }
    ],
    "sg:phone":"+61 2 4929 7899",
    "sg:postcode":"2300",
    "sg:province":"NSW",
    "sg:tags":[
        "organisation",
        "business"
    ],
    "wof:name":"Australian Industry Group",
    "wof:placetype":"venue"
},
  "geometry": {"coordinates":[151.78312700000001,-32.927361],"type":"Point"}
}