{
  "type": "Feature",
  "properties": {
    "addr:full":"5 Kurrajong Pde Mildura VIC 3500",
    "addr:housenumber":"5",
    "addr:postcode":"3500",
    "addr:street":"Kurrajong Pde",
    "iso:country":"AU",
    "sg:address":"5 Kurrajong Pde",
    "sg:city":"Mildura",
    "sg:classifiers":[
        {
            "category":"Sports & Exercise",
            "subcategory":"Gym",
            "type":"Entertainment"
        }
    ],
    "sg:phone":"+61 422 193 056",
    "sg:postcode":"3500",
    "sg:province":"VIC",
    "sg:tags":[
        "personal",
        "trainer",
        "fitness"
    ],
    "wof:name":"SB Life Personal Training",
    "wof:placetype":"venue"
},
  "geometry": {"coordinates":[142.151901245,-34.1888237],"type":"Point"}
}