{
  "type": "Feature",
  "properties": {
    "iso:country":"AU",
    "sg:address":"272 Campbell St",
    "sg:city":"Swan Hill",
    "sg:classifiers":[
        {
            "category":"Shopping",
            "subcategory":"Clothing, Apparel, & Fashions",
            "type":"Retail Goods"
        }
    ],
    "sg:phone":"+61 3 5032 4241",
    "sg:postcode":"3585",
    "sg:province":"VIC",
    "sg:tags":[
        "lady",
        "wear"
    ],
    "wof:name":"Pat & Velias Boutique",
    "wof:placetype":"venue"
},
  "geometry": {"coordinates":[143.56004300000001,-35.341797],"type":"Point"}
}