{
  "type": "Feature",
  "properties": {
    "addr:full":"GPO Box 38 Mt Hawthorn WA 6016",
    "addr:postcode":"6016",
    "addr:street":"Mt",
    "iso:country":"AU",
    "sg:address":"GPO Box 38",
    "sg:city":"Mt Hawthorn",
    "sg:classifiers":[
        {
            "category":"Building & Trades",
            "subcategory":"Plumbing",
            "type":"Services"
        }
    ],
    "sg:phone":"+61 413 777 700",
    "sg:postcode":"6016",
    "sg:province":"WA",
    "sg:tags":[
        "plumber",
        "gasfitters"
    ],
    "wof:name":"Abrahams Plumbing Pty Ltd",
    "wof:placetype":"venue"
},
  "geometry": {"coordinates":[115.837333679,-31.9206905365],"type":"Point"}
}