{
  "type": "Feature",
  "properties": {
    "addr:full":"95 Toombul Rd Northgate QLD 4013",
    "addr:housenumber":"95",
    "addr:postcode":"4013",
    "addr:street":"Toombul Rd",
    "iso:country":"AU",
    "sg:address":"95 Toombul Rd",
    "sg:city":"Northgate",
    "sg:classifiers":[
        {
            "category":"Government",
            "subcategory":"Court House",
            "type":"Public Place"
        }
    ],
    "sg:phone":"+61 7 3260 7713",
    "sg:postcode":"4013",
    "sg:province":"QLD",
    "sg:tags":[
        "personal",
        "marriage",
        "family",
        "counselling"
    ],
    "wof:name":"Youth Hotline",
    "wof:placetype":"venue"
},
  "geometry": {"coordinates":[153.06758117699999,-27.3872375488],"type":"Point"}
}