{
  "type": "Feature",
  "properties": {
    "addr:full":"54 Yarralea St Alphington VIC 3078",
    "addr:housenumber":"54",
    "addr:postcode":"3078",
    "addr:street":"Yarralea St",
    "iso:country":"AU",
    "sg:address":"54 Yarralea St",
    "sg:city":"Alphington",
    "sg:classifiers":[
        {
            "category":"Education",
            "subcategory":"Kindergarten",
            "type":"Public Place"
        }
    ],
    "sg:phone":"+61 3 9499 2251",
    "sg:postcode":"3078",
    "sg:province":"VIC",
    "sg:tags":[
        "pre-schools"
    ],
    "wof:name":"Yarralea Childrens Centre Inc",
    "wof:placetype":"venue"
},
  "geometry": {"coordinates":[145.03219604500001,-37.7818107605],"type":"Point"}
}