{
  "type": "Feature",
  "properties": {
    "addr:full":"9 Leons Rd Springvale South VIC 3172",
    "addr:housenumber":"9",
    "addr:postcode":"3172",
    "addr:street":"Leons Rd",
    "iso:country":"AU",
    "sg:address":"9 Leons Rd",
    "sg:city":"Springvale South",
    "sg:classifiers":[
        {
            "category":"Retail",
            "subcategory":"Laundry & Dry Cleaning",
            "type":"Services"
        }
    ],
    "sg:phone":"+61 3 9558 4334",
    "sg:postcode":"3172",
    "sg:province":"VIC",
    "sg:tags":[
        "cloth",
        "supply"
    ],
    "wof:name":"All Wiper Cloth Recyclers Pty Ltd",
    "wof:placetype":"venue"
},
  "geometry": {"coordinates":[145.15142822300001,-37.9777412415],"type":"Point"}
}