{
  "type": "Feature",
  "properties": {
    "iso:country":"AU",
    "sg:address":"69- 73 Chloe Drv",
    "sg:city":"Munruben",
    "sg:classifiers":[
        {
            "category":"Farming",
            "subcategory":"Farm & Veterinary Services",
            "type":"Manufacturing & Wholesale Goods"
        }
    ],
    "sg:phone":"+61 7 3833 4153",
    "sg:postcode":"4125",
    "sg:province":"QLD",
    "sg:tags":[
        "irrigation",
        "reticulation",
        "system"
    ],
    "wof:name":"Able Sprinkler Systems",
    "wof:placetype":"venue"
},
  "geometry": {"coordinates":[153.036575317,-27.7436504364],"type":"Point"}
}