{
  "type": "Feature",
  "properties": {
    "addr:full":"28 Montague St Balmain NSW 2041",
    "addr:housenumber":"28",
    "addr:postcode":"2041",
    "addr:street":"Montague St",
    "iso:country":"AU",
    "sg:address":"28 Montague St",
    "sg:city":"Balmain",
    "sg:classifiers":[
        {
            "category":"Professional",
            "subcategory":"Business Services",
            "type":"Services"
        }
    ],
    "sg:phone":"+61 2 9555 9308",
    "sg:postcode":"2041",
    "sg:province":"NSW",
    "sg:tags":[
        "management",
        "event"
    ],
    "wof:name":"Australian Business Theatre (ABT)",
    "wof:placetype":"venue"
},
  "geometry": {"coordinates":[151.17781099999999,-33.858013],"type":"Point"}
}