{
  "type": "Feature",
  "properties": {
    "iso:country":"AU",
    "sg:address":"35 Bentley St",
    "sg:city":"Wetherill Park",
    "sg:classifiers":[
        {
            "category":"Wholesale",
            "subcategory":"Electrical",
            "type":"Manufacturing & Wholesale Goods"
        }
    ],
    "sg:phone":"+61 2 9756 3833",
    "sg:postcode":"2164",
    "sg:province":"NSW",
    "sg:tags":[
        "wholesaler"
    ],
    "wof:name":"Gemcell",
    "wof:placetype":"venue"
},
  "geometry": {"coordinates":[150.883743286,-33.8449630737],"type":"Point"}
}