{
  "type": "Feature",
  "properties": {
    "addr:full":"214 Junction Rd Ruse NSW 2560",
    "addr:housenumber":"214",
    "addr:postcode":"2560",
    "addr:street":"Junction Rd",
    "iso:country":"AU",
    "sg:address":"214 Junction Rd",
    "sg:city":"Ruse",
    "sg:classifiers":[
        {
            "category":"Manufacturing",
            "subcategory":"Tools & Machinery",
            "type":"Manufacturing & Wholesale Goods"
        }
    ],
    "sg:phone":"+61 2 4626 8209",
    "sg:postcode":"2560",
    "sg:province":"NSW",
    "sg:tags":[
        "earth",
        "excavating",
        "moving",
        "equipment"
    ],
    "wof:name":"A & E Bobocat & Tipper Hire",
    "wof:placetype":"venue"
},
  "geometry": {"coordinates":[150.84083557100001,-34.075504303],"type":"Point"}
}