{
  "type": "Feature",
  "properties": {
    "iso:country":"AU",
    "sg:address":"Suite 6, 354 Pennant Hills Rd",
    "sg:city":"Pennant Hills",
    "sg:classifiers":[
        {
            "category":"Health Services",
            "subcategory":"Chiropractor",
            "type":"Services"
        }
    ],
    "sg:phone":"+61 2 9980 9000",
    "sg:postcode":"2120",
    "sg:province":"NSW",
    "wof:name":"Hazel Jenkins",
    "wof:placetype":"venue"
},
  "geometry": {"coordinates":[151.07034301799999,-33.7390632629],"type":"Point"}
}