{
  "type": "Feature",
  "properties": {
    "iso:country":"AU",
    "sg:address":"63 Lindsay St",
    "sg:city":"Hamilton",
    "sg:classifiers":[
        {
            "category":"Professional",
            "subcategory":"Accounting & Tax Preparation",
            "type":"Services"
        }
    ],
    "sg:phone":"+61 2 4940 6100",
    "sg:postcode":"2303",
    "sg:province":"NSW",
    "sg:tags":[
        "accountant",
        "auditor"
    ],
    "wof:name":"McArtney Richard",
    "wof:placetype":"venue"
},
  "geometry": {"coordinates":[151.747162,-32.921951],"type":"Point"}
}