{
  "type": "Feature",
  "properties": {
    "iso:country":"AU",
    "sg:address":"26 Lyttleton St",
    "sg:city":"East Launceston",
    "sg:classifiers":[
        {
            "category":"Health Services",
            "subcategory":"Doctor",
            "type":"Services"
        }
    ],
    "sg:phone":"+61 3 6334 2242",
    "sg:postcode":"7250",
    "sg:province":"TAS",
    "sg:tags":[
        "medical",
        "practitioner"
    ],
    "wof:name":"Campbell Joanne Dr",
    "wof:placetype":"venue"
},
  "geometry": {"coordinates":[147.14984130900001,-41.4344100952],"type":"Point"}
}