{
  "type": "Feature",
  "properties": {
    "iso:country":"AU",
    "sg:address":"Lot 5437 Emungalan Rd",
    "sg:city":"Katherine",
    "sg:classifiers":[
        {
            "category":"Building & Trades",
            "subcategory":"Construction",
            "type":"Services"
        }
    ],
    "sg:phone":"+61 8 8971 0070",
    "sg:postcode":"0850",
    "sg:province":"NT",
    "sg:tags":[
        "road",
        "contractor"
    ],
    "wof:name":"Allan King & Sons Constructions",
    "wof:placetype":"venue"
},
  "geometry": {"coordinates":[132.25799599999999,-14.437285],"type":"Point"}
}