{
  "type": "Feature",
  "properties": {
    "iso:country":"AU",
    "sg:address":"Oxley Secondary College Performing Arts Centre, 53 Seventeen Mile Rocks Rd",
    "sg:city":"Oxley",
    "sg:classifiers":[
        {
            "category":"Arts & Performance",
            "subcategory":"Dance",
            "type":"Entertainment"
        }
    ],
    "sg:phone":"+61 7 3378 3436",
    "sg:postcode":"4075",
    "sg:province":"QLD",
    "sg:tags":[
        "theatrical",
        "ballet",
        "tuition"
    ],
    "wof:name":"Centenary Dance Academy",
    "wof:placetype":"venue"
},
  "geometry": {"coordinates":[152.96955871599999,-27.5533046722],"type":"Point"}
}