{
  "type": "Feature",
  "properties": {
    "addr:full":"Shp15/ 345 Peel St Tamworth NSW 2340",
    "addr:housenumber":"345",
    "addr:postcode":"2340",
    "addr:street":"Peel St",
    "iso:country":"AU",
    "sg:address":"Shp15/ 345 Peel St",
    "sg:city":"Tamworth",
    "sg:classifiers":[
        {
            "category":"Personal",
            "subcategory":"Beauty Salon",
            "type":"Services"
        }
    ],
    "sg:phone":"+61 2 6761 2144",
    "sg:postcode":"2340",
    "sg:province":"NSW",
    "wof:name":"VIP Nail Artistry & Beauty",
    "wof:placetype":"venue"
},
  "geometry": {"coordinates":[150.92979431099999,-31.0907363892],"type":"Point"}
}