{
  "type": "Feature",
  "properties": {
    "iso:country":"AU",
    "sg:address":"50 Woodbridge Hill Rd",
    "sg:city":"Woodbridge",
    "sg:classifiers":[
        {
            "category":"Professional",
            "subcategory":"Computer Services",
            "type":"Services"
        }
    ],
    "sg:phone":"+61 3 6267 4658",
    "sg:postcode":"7162",
    "sg:province":"TAS",
    "sg:tags":[
        "repairs",
        "upgrade",
        "equipment"
    ],
    "wof:name":"Channel PC Repairs",
    "wof:placetype":"venue"
},
  "geometry": {"coordinates":[147.23330688499999,-43.160785675],"type":"Point"}
}