{
  "type": "Feature",
  "properties": {
    "iso:country":"AU",
    "sg:address":"59 Morrice St",
    "sg:city":"Lane Cove",
    "sg:classifiers":[
        {
            "category":"Communications",
            "type":"Services"
        }
    ],
    "sg:phone":"+61 2 9428 3353",
    "sg:postcode":"2066",
    "sg:province":"NSW",
    "sg:tags":[
        "translation"
    ],
    "wof:name":"Sydney Language Centre (Mike Nasir & Associates)",
    "wof:placetype":"venue"
},
  "geometry": {"coordinates":[151.16673278799999,-33.8180503845],"type":"Point"}
}