{
  "type": "Feature",
  "properties": {
    "addr:full":"31 Dolphin Crs Noosa Sound Noosaville QLD 4566",
    "addr:housenumber":"31",
    "addr:postcode":"4566",
    "addr:street":"Dolphin Crs Noosa",
    "iso:country":"AU",
    "sg:address":"31 Dolphin Crs Noosa Sound",
    "sg:city":"Noosaville",
    "sg:classifiers":[
        {
            "category":"Building & Trades",
            "subcategory":"Plumbing",
            "type":"Services"
        }
    ],
    "sg:phone":"+61 7 5449 8707",
    "sg:postcode":"4566",
    "sg:province":"QLD",
    "sg:tags":[
        "drainers"
    ],
    "wof:name":"Murray Bones R J Plumbing",
    "wof:placetype":"venue"
},
  "geometry": {"coordinates":[153.08274841299999,-26.4040546417],"type":"Point"}
}