{
  "type": "Feature",
  "properties": {
    "iso:country":"AU",
    "sg:address":"PO Box 7169",
    "sg:city":"Spearwood",
    "sg:classifiers":[
        {
            "category":"Utilities",
            "subcategory":"Electric",
            "type":"Services"
        }
    ],
    "sg:phone":"+61 404 216 333",
    "sg:postcode":"6163",
    "sg:province":"WA",
    "sg:tags":[
        "electrical",
        "contractor"
    ],
    "wof:name":"SafetySwitch Electrical Services",
    "wof:placetype":"venue"
},
  "geometry": {"coordinates":[115.79158,-32.105766],"type":"Point"}
}