{
  "type": "Feature",
  "properties": {
    "iso:country":"AU",
    "sg:address":"236 Main North Rd",
    "sg:city":"Prospect",
    "sg:classifiers":[
        {
            "category":"Banks & Credit Unions",
            "subcategory":"Investment Brokerage",
            "type":"Services"
        }
    ],
    "sg:phone":"+61 8 8342 5590",
    "sg:postcode":"5082",
    "sg:province":"SA",
    "sg:tags":[
        "radiator",
        "motor"
    ],
    "wof:name":"Prospect Radiators",
    "wof:placetype":"venue"
},
  "geometry": {"coordinates":[138.60240173299999,-34.8826370239],"type":"Point"}
}