{
  "type": "Feature",
  "properties": {
    "iso:country":"AU",
    "sg:address":"88 Hallam Valley Rd",
    "sg:city":"Dandenong South",
    "sg:classifiers":[
        {
            "category":"Professional",
            "type":"Services"
        }
    ],
    "sg:phone":"+61 418 104 103",
    "sg:postcode":"3175",
    "sg:province":"VIC",
    "sg:tags":[
        "transport"
    ],
    "wof:name":"All State Heavy Haulage",
    "wof:placetype":"venue"
},
  "geometry": {"coordinates":[145.23274230999999,-38.0128097534],"type":"Point"}
}