{
  "type": "Feature",
  "properties": {
    "iso:country":"AU",
    "sg:address":"2/ 5 Tooronga Ave",
    "sg:city":"Edwardstown",
    "sg:classifiers":[
        {
            "category":"Professional",
            "subcategory":"Art Services",
            "type":"Services"
        }
    ],
    "sg:phone":"+61 8 8374 2703",
    "sg:postcode":"5039",
    "sg:province":"SA",
    "sg:tags":[
        "graphic",
        "designer"
    ],
    "wof:name":"Stellar Graphics",
    "wof:placetype":"venue"
},
  "geometry": {"coordinates":[138.571533203,-34.9922447205],"type":"Point"}
}