{
  "type": "Feature",
  "properties": {
    "iso:country":"AU",
    "sg:address":"1 Virginia Crt",
    "sg:city":"Delacombe",
    "sg:classifiers":[
        {
            "category":"Health Services",
            "subcategory":"Health Practitioner",
            "type":"Services"
        }
    ],
    "sg:phone":"+61 409 362 349",
    "sg:postcode":"3356",
    "sg:province":"VIC",
    "sg:tags":[
        "reiki"
    ],
    "wof:name":"Uni-Dove",
    "wof:placetype":"venue"
},
  "geometry": {"coordinates":[143.812454,-37.583252],"type":"Point"}
}