{
  "type": "Feature",
  "properties": {
    "addr:full":"PO Box 563 Campbelltown SA 5074",
    "addr:postcode":"5074",
    "iso:country":"AU",
    "sg:address":"PO Box 563",
    "sg:city":"Campbelltown",
    "sg:classifiers":[
        {
            "category":"Manufacturing",
            "subcategory":"Food",
            "type":"Manufacturing & Wholesale Goods"
        }
    ],
    "sg:phone":"+61 403 837 095",
    "sg:postcode":"5074",
    "sg:province":"SA",
    "sg:tags":[
        "function",
        "catering"
    ],
    "wof:name":"Tailor Made Catering",
    "wof:placetype":"venue"
},
  "geometry": {"coordinates":[138.66169738799999,-34.8811988831],"type":"Point"}
}