{
  "type": "Feature",
  "properties": {
    "addr:full":"PO Box 42771 Casuarina NT 0811",
    "addr:postcode":"nt 0811",
    "iso:country":"AU",
    "sg:address":"PO Box 42771",
    "sg:city":"Casuarina",
    "sg:classifiers":[
        {
            "category":"Arena",
            "subcategory":"Sports Club",
            "type":"Entertainment"
        }
    ],
    "sg:phone":"+61 8 8945 0447",
    "sg:postcode":"0811",
    "sg:province":"NT",
    "sg:tags":[
        "life",
        "surfing",
        "saving"
    ],
    "wof:name":"Darwin Surf Life Saving Club",
    "wof:placetype":"venue"
},
  "geometry": {"coordinates":[130.858886719,-12.3764762878],"type":"Point"}
}