{
  "type": "Feature",
  "properties": {
    "addr:full":"17 Garnett Ave Blackwood SA 5051",
    "addr:housenumber":"17",
    "addr:postcode":"5051",
    "addr:street":"Garnett Ave",
    "iso:country":"AU",
    "sg:address":"17 Garnett Ave",
    "sg:city":"Blackwood",
    "sg:classifiers":[
        {
            "category":"Real Estate",
            "subcategory":"Architect",
            "type":"Services"
        }
    ],
    "sg:phone":"+61 417 829 956",
    "sg:postcode":"5051",
    "sg:province":"SA",
    "sg:tags":[
        "building",
        "designer"
    ],
    "wof:name":"Athenree Pty Ltd",
    "wof:placetype":"venue"
},
  "geometry": {"coordinates":[138.61779799999999,-35.030216],"type":"Point"}
}