{
  "type": "Feature",
  "properties": {
    "addr:full":"7 Nursery Pl Belrose NSW 2085",
    "addr:housenumber":"7",
    "addr:postcode":"2085",
    "addr:street":"Nursery Pl",
    "iso:country":"AU",
    "sg:address":"7 Nursery Pl",
    "sg:city":"Belrose",
    "sg:classifiers":[
        {
            "category":"Building & Trades",
            "subcategory":"Construction",
            "type":"Services"
        }
    ],
    "sg:phone":"+61 2 9452 1473",
    "sg:postcode":"2085",
    "sg:province":"NSW",
    "sg:tags":[
        "concrete",
        "contractor"
    ],
    "wof:name":"Ocean Concrete Pty Ltd",
    "wof:placetype":"venue"
},
  "geometry": {"coordinates":[151.216033936,-33.7265510559],"type":"Point"}
}