{
  "type": "Feature",
  "properties": {
    "iso:country":"AU",
    "sg:address":"4 Pashol St",
    "sg:city":"Bentleigh",
    "sg:classifiers":[
        {
            "category":"Home & Garden",
            "subcategory":"Carpets & Floor Coverings",
            "type":"Retail Goods"
        }
    ],
    "sg:phone":"+61 413 901 277",
    "sg:postcode":"3204",
    "sg:province":"VIC",
    "sg:tags":[
        "tile",
        "wall",
        "layer"
    ],
    "wof:name":"Offord Paving & Tiling",
    "wof:placetype":"venue"
},
  "geometry": {"coordinates":[145.044724,-37.929646],"type":"Point"}
}