{
  "type": "Feature",
  "properties": {
    "iso:country":"AU",
    "sg:address":"118 Dawd St",
    "sg:city":"Welshpool",
    "sg:classifiers":[
        {
            "category":"Wholesale",
            "subcategory":"Metals & Minerals",
            "type":"Manufacturing & Wholesale Goods"
        }
    ],
    "sg:phone":"+61 8 6253 6400",
    "sg:postcode":"6106",
    "sg:province":"WA",
    "sg:tags":[
        "steel",
        "merchant"
    ],
    "wof:name":"CMC Coil Steels",
    "wof:placetype":"venue"
},
  "geometry": {"coordinates":[115.95393371599999,-31.9889202118],"type":"Point"}
}