{
  "type": "Feature",
  "properties": {
    "addr:full":"Lot 194 Old Tarcoola Rd Port Augusta SA 5700",
    "addr:postcode":"5700",
    "addr:street":"Old Tarcoola Rd",
    "iso:country":"AU",
    "sg:address":"Lot 194 Old Tarcoola Rd",
    "sg:city":"Port Augusta",
    "sg:classifiers":[
        {
            "category":"Utilities",
            "subcategory":"Natural Gas",
            "type":"Services"
        }
    ],
    "sg:phone":"+61 13 21 80",
    "sg:postcode":"5700",
    "sg:province":"SA",
    "sg:tags":[
        "supplier"
    ],
    "wof:name":"Kleenheat Gas",
    "wof:placetype":"venue"
},
  "geometry": {"coordinates":[137.743530273,-32.4729423523],"type":"Point"}
}