{
  "type": "Feature",
  "properties": {
    "addr:full":"Shop 7 23 Callister St Shepparton VIC 3630",
    "addr:housenumber":"shop;23",
    "addr:postcode":"3630",
    "addr:street":"Callister St",
    "iso:country":"AU",
    "sg:address":"Shop 7 23 Callister St",
    "sg:city":"Shepparton",
    "sg:classifiers":[
        {
            "category":"Shopping",
            "subcategory":"Crafts & Fabrics",
            "type":"Retail Goods"
        }
    ],
    "sg:phone":"+61 3 5821 0646",
    "sg:postcode":"3630",
    "sg:province":"VIC",
    "sg:tags":[
        "synthetic",
        "canvas",
        "product"
    ],
    "wof:name":"Spot On Canvas Centre",
    "wof:placetype":"venue"
},
  "geometry": {"coordinates":[145.41542053200001,-36.3861694336],"type":"Point"}
}