{
  "type": "Feature",
  "properties": {
    "iso:country":"AU",
    "sg:address":"2318 Albany Hwy",
    "sg:city":"Gosnells",
    "sg:classifiers":[
        {
            "category":"Wholesale",
            "subcategory":"Painting Supplies",
            "type":"Manufacturing & Wholesale Goods"
        }
    ],
    "sg:phone":"+61 8 9398 6636",
    "sg:postcode":"6110",
    "sg:province":"WA",
    "sg:tags":[
        "painter"
    ],
    "wof:name":"Southern River Paints",
    "wof:placetype":"venue"
},
  "geometry": {"coordinates":[116.00478363000001,-32.0736923218],"type":"Point"}
}