{
  "type": "Feature",
  "properties": {
    "iso:country":"AU",
    "sg:address":"41 Harvester Ave",
    "sg:city":"Sunshine",
    "sg:classifiers":[
        {
            "category":"Professional",
            "type":"Services"
        }
    ],
    "sg:phone":"+61 417 300 075",
    "sg:postcode":"3020",
    "sg:province":"VIC",
    "sg:tags":[
        "transport"
    ],
    "wof:name":"Grimac Transport & Storage",
    "wof:placetype":"venue"
},
  "geometry": {"coordinates":[144.837723,-37.760536],"type":"Point"}
}