{
  "type": "Feature",
  "properties": {
    "addr:full":"Unit 4/ 7- 11 Gurney St Garbutt QLD 4814",
    "addr:housenumber":"11",
    "addr:postcode":"4814",
    "addr:street":"Gurney St",
    "iso:country":"AU",
    "sg:address":"Unit 4/ 7- 11 Gurney St",
    "sg:city":"Garbutt",
    "sg:classifiers":[
        {
            "category":"Communications",
            "type":"Services"
        }
    ],
    "sg:phone":"+61 7 4775 3966",
    "sg:postcode":"4814",
    "sg:province":"QLD",
    "sg:tags":[
        "equipment",
        "satellite"
    ],
    "wof:name":"Matchmaster TV Reception Systems",
    "wof:placetype":"venue"
},
  "geometry": {"coordinates":[146.76632699999999,-19.265348],"type":"Point"}
}