{
  "type": "Feature",
  "properties": {
    "addr:full":"9775 Murray River Rd Walwa NSW 3709",
    "addr:housenumber":"9775",
    "addr:postcode":"3709",
    "addr:street":"Murray River Rd",
    "iso:country":"AU",
    "sg:address":"9775 Murray River Rd",
    "sg:city":"Walwa",
    "sg:classifiers":[
        {
            "category":"Arena",
            "subcategory":"Sports Club",
            "type":"Entertainment"
        }
    ],
    "sg:phone":"+61 2 6037 1233",
    "sg:postcode":"3709",
    "sg:province":"NSW",
    "sg:tags":[
        "defence",
        "supply",
        "self",
        "instruction",
        "martial art"
    ],
    "wof:name":"Hi Chi Mizu Martial Arts",
    "wof:placetype":"venue"
},
  "geometry": {"coordinates":[147.736038208,-35.963886261],"type":"Point"}
}