{
  "type": "Feature",
  "properties": {
    "iso:country":"AU",
    "sg:address":"9 East St",
    "sg:city":"Parkes",
    "sg:classifiers":[
        {
            "category":"Building & Trades",
            "subcategory":"Construction",
            "type":"Services"
        }
    ],
    "sg:phone":"+61 2 6862 3850",
    "sg:postcode":"2870",
    "sg:province":"NSW",
    "sg:tags":[
        "contractor"
    ],
    "wof:name":"DC & RL Knights Pty Ltd",
    "wof:placetype":"venue"
},
  "geometry": {"coordinates":[148.18275499999999,-33.141674],"type":"Point"}
}