{
  "type": "Feature",
  "properties": {
    "addr:full":"Shop 3, Raymond Terrace Marketplace, 35-39 William St Raymond Terrace NSW 2324",
    "addr:housenumber":"shop 3;35-39",
    "addr:postcode":"2324",
    "addr:street":"Raymond Terrace;William St",
    "iso:country":"AU",
    "sg:address":"Shop 3, Raymond Terrace Marketplace, 35-39 William St",
    "sg:city":"Raymond Terrace",
    "sg:classifiers":[
        {
            "category":"Insurance",
            "subcategory":"Health Insurance",
            "type":"Services"
        }
    ],
    "sg:phone":"+61 2 4987 3174",
    "sg:postcode":"2324",
    "sg:province":"NSW",
    "wof:name":"NIB Health Funds",
    "wof:placetype":"venue"
},
  "geometry": {"coordinates":[151.74574279800001,-32.7644882202],"type":"Point"}
}