{
  "type": "Feature",
  "properties": {
    "addr:full":"32 Bundabah Ave St Ives NSW 2075",
    "addr:housenumber":"32",
    "addr:postcode":"2075",
    "addr:street":"Bundabah Ave",
    "iso:country":"AU",
    "sg:address":"32 Bundabah Ave",
    "sg:city":"St Ives",
    "sg:classifiers":[
        {
            "category":"Professional",
            "subcategory":"Employment Agencies",
            "type":"Services"
        }
    ],
    "sg:phone":"+61 2 9988 3989",
    "sg:postcode":"2075",
    "sg:province":"NSW",
    "sg:tags":[
        "entertainer",
        "agent"
    ],
    "wof:name":"Slim Dusty Enterprises Pty Ltd",
    "wof:placetype":"venue"
},
  "geometry": {"coordinates":[151.16604614299999,-33.7232322693],"type":"Point"}
}