{
  "type": "Feature",
  "properties": {
    "iso:country":"AU",
    "sg:address":"156 Brisbane Rd",
    "sg:city":"Mooloolaba",
    "sg:classifiers":[
        {
            "category":"Shopping",
            "subcategory":"Clothing, Apparel, & Fashions",
            "type":"Retail Goods"
        }
    ],
    "sg:phone":"+61 7 5477 5613",
    "sg:postcode":"4557",
    "sg:province":"QLD",
    "sg:tags":[
        "sportswear"
    ],
    "wof:name":"Skateside",
    "wof:placetype":"venue"
},
  "geometry": {"coordinates":[153.11491394000001,-26.6899223328],"type":"Point"}
}