{
  "type": "Feature",
  "properties": {
    "addr:full":"154 Station St Fairfield VIC 3078",
    "addr:housenumber":"154",
    "addr:postcode":"3078",
    "addr:street":"Station St",
    "iso:country":"AU",
    "sg:address":"154 Station St",
    "sg:city":"Fairfield",
    "sg:classifiers":[
        {
            "category":"Health Services",
            "subcategory":"Health Practitioner",
            "type":"Services"
        }
    ],
    "sg:phone":"+61 3 9499 6901",
    "sg:postcode":"3078",
    "sg:province":"VIC",
    "sg:tags":[
        "psychologist"
    ],
    "wof:name":"Ray Vera",
    "wof:placetype":"venue"
},
  "geometry": {"coordinates":[145.029693603,-37.776676178],"type":"Point"}
}