{
  "type": "Feature",
  "properties": {
    "iso:country":"AU",
    "sg:address":"26-28 Albany Hwy",
    "sg:city":"Albany",
    "sg:classifiers":[
        {
            "category":"Health Services",
            "subcategory":"Dentist",
            "type":"Services"
        }
    ],
    "sg:phone":"+61 8 9841 1238",
    "sg:postcode":"6330",
    "sg:province":"WA",
    "wof:name":"Albany Dental Centre",
    "wof:placetype":"venue"
},
  "geometry": {"coordinates":[117.881309509,-35.0198974609],"type":"Point"}
}