{
  "type": "Feature",
  "properties": {
    "addr:full":"Simmsville Rd Stroud NSW 2425",
    "addr:postcode":"2425",
    "addr:street":"Simmsville Rd",
    "iso:country":"AU",
    "sg:address":"Simmsville Rd",
    "sg:city":"Stroud",
    "sg:classifiers":[
        {
            "category":"Utilities",
            "subcategory":"Refuse",
            "type":"Services"
        }
    ],
    "sg:phone":"+61 2 4994 5699",
    "sg:postcode":"2425",
    "sg:province":"NSW",
    "sg:tags":[
        "disposal",
        "reduction",
        "waste"
    ],
    "wof:name":"Great Lakes Council",
    "wof:placetype":"venue"
},
  "geometry": {"coordinates":[151.96998596200001,-32.4113464355],"type":"Point"}
}