{
  "type": "Feature",
  "properties": {
    "addr:full":"153 High St Wodonga VIC 3690",
    "addr:housenumber":"153",
    "addr:postcode":"3690",
    "addr:street":"High St",
    "iso:country":"AU",
    "sg:address":"153 High St",
    "sg:city":"Wodonga",
    "sg:classifiers":[
        {
            "category":"Travel",
            "subcategory":"Travel Agent",
            "type":"Entertainment"
        }
    ],
    "sg:phone":"+61 2 6024 1344",
    "sg:postcode":"3690",
    "sg:province":"VIC",
    "sg:tags":[
        "consultant"
    ],
    "wof:name":"Mylon Travel Pty Ltd",
    "wof:placetype":"venue"
},
  "geometry": {"coordinates":[146.88796997099999,-36.1237297058],"type":"Point"}
}