{
  "type": "Feature",
  "properties": {
    "addr:full":"25 Glendale Crs Mulgrave VIC 3170",
    "addr:housenumber":"25",
    "addr:postcode":"3170",
    "addr:street":"Glendale Crs",
    "iso:country":"AU",
    "sg:address":"25 Glendale Crs",
    "sg:city":"Mulgrave",
    "sg:classifiers":[
        {
            "category":"Shopping",
            "subcategory":"Stationery & Office Supplies",
            "type":"Retail Goods"
        }
    ],
    "sg:phone":"+61 3 9561 9188",
    "sg:postcode":"3170",
    "sg:province":"VIC",
    "sg:tags":[
        "partition"
    ],
    "wof:name":"STI Commercial Interiors",
    "wof:placetype":"venue"
},
  "geometry": {"coordinates":[145.150100708,-37.9374427795],"type":"Point"}
}