{
  "type": "Feature",
  "properties": {
    "iso:country":"AU",
    "sg:address":"71 Navigators Rd",
    "sg:city":"Warrenheip",
    "sg:classifiers":[
        {
            "category":"Utilities",
            "subcategory":"Electric",
            "type":"Services"
        }
    ],
    "sg:phone":"+61 3 5334 7595",
    "sg:postcode":"3352",
    "sg:province":"VIC",
    "sg:tags":[
        "electrical",
        "contractor"
    ],
    "wof:name":"Taylor John",
    "wof:placetype":"venue"
},
  "geometry": {"coordinates":[143.91494800000001,-37.579922],"type":"Point"}
}