{
  "type": "Feature",
  "properties": {
    "iso:country":"AU",
    "sg:address":"2/ 39 Tuloa Ave",
    "sg:city":"Hawks Nest",
    "sg:classifiers":[
        {
            "category":"Professional",
            "subcategory":"Detective & Security Services",
            "type":"Services"
        }
    ],
    "sg:phone":"+61 2 4997 1554",
    "sg:postcode":"2324",
    "sg:province":"NSW",
    "sg:tags":[
        "equipment",
        "window",
        "doors"
    ],
    "wof:name":"Advantage Home Improvements of Australia Pty Ltd",
    "wof:placetype":"venue"
},
  "geometry": {"coordinates":[152.176681519,-32.6765785217],"type":"Point"}
}