{
  "type": "Feature",
  "properties": {
    "iso:country":"AU",
    "sg:address":"Middleton Tavern Cnr of Goolwa Rd & Mindacowie Ave",
    "sg:city":"Middleton",
    "sg:classifiers":[
        {
            "category":"Food & Beverages",
            "subcategory":"Liquor & Beverages",
            "type":"Retail Goods"
        }
    ],
    "sg:phone":"+61 8 8554 3010",
    "sg:postcode":"5213",
    "sg:province":"SA",
    "sg:tags":[
        "store"
    ],
    "wof:name":"Liquorwise",
    "wof:placetype":"venue"
},
  "geometry": {"coordinates":[138.705276489,-35.5109291077],"type":"Point"}
}