{
  "type": "Feature",
  "properties": {
    "addr:full":"Ryall St Canowindra NSW 2804",
    "addr:postcode":"2804",
    "addr:street":"Ryall St",
    "iso:country":"AU",
    "sg:address":"Ryall St",
    "sg:city":"Canowindra",
    "sg:classifiers":[
        {
            "category":"Restaurant",
            "type":"Food & Drink"
        }
    ],
    "sg:phone":"+61 2 6344 1026",
    "sg:postcode":"2804",
    "sg:province":"NSW",
    "wof:name":"Canowindra Bowling Club Chinese Restaurant",
    "wof:placetype":"venue"
},
  "geometry": {"coordinates":[148.66207885700001,-33.5617904663],"type":"Point"}
}