{
  "type": "Feature",
  "properties": {
    "iso:country":"AU",
    "sg:address":"Shop 4, Lloyd Place Arcade, 1790",
    "sg:city":"David Low Way Coolum Beach",
    "sg:classifiers":[
        {
            "category":"Retail",
            "subcategory":"Self-service Laundry",
            "type":"Services"
        }
    ],
    "sg:phone":"+61 411 105 072",
    "sg:postcode":"4573",
    "sg:province":"QLD",
    "wof:name":"Coolum Beach Laundromat",
    "wof:placetype":"venue"
},
  "geometry": {"coordinates":[153.091354,-26.530399],"type":"Point"}
}