{
  "type": "Feature",
  "properties": {
    "iso:country":"AU",
    "sg:address":"Shop 7-8 Raglan Sq Shoppin Centre 918-920 Military Rd",
    "sg:city":"Mosman",
    "sg:classifiers":[
        {
            "category":"Shopping",
            "subcategory":"Clothing, Apparel, & Fashions",
            "type":"Retail Goods"
        }
    ],
    "sg:phone":"+61 2 9969 1253",
    "sg:postcode":"2088",
    "sg:province":"NSW",
    "sg:tags":[
        "lady",
        "wear"
    ],
    "wof:name":"Portmans",
    "wof:placetype":"venue"
},
  "geometry": {"coordinates":[151.24440002399999,-33.8308448792],"type":"Point"}
}