{
  "type": "Feature",
  "properties": {
    "iso:country":"AU",
    "sg:address":"9 James St",
    "sg:city":"Toronto",
    "sg:classifiers":[
        {
            "category":"Retail",
            "subcategory":"Event Space",
            "type":"Services"
        }
    ],
    "sg:phone":"+61 2 4959 2011",
    "sg:postcode":"2283",
    "sg:province":"NSW",
    "sg:tags":[
        "venue",
        "reception",
        "wedding"
    ],
    "wof:name":"Toronto Workers Club",
    "wof:placetype":"venue"
},
  "geometry": {"coordinates":[151.59080505399999,-33.0105133057],"type":"Point"}
}