{
  "type": "Feature",
  "properties": {
    "addr:full":"33 Court Rd Nambour QLD 4560",
    "addr:housenumber":"33",
    "addr:postcode":"4560",
    "addr:street":"Court Rd",
    "iso:country":"AU",
    "sg:address":"33 Court Rd",
    "sg:city":"Nambour",
    "sg:classifiers":[
        {
            "category":"Retail",
            "subcategory":"Auto Repair",
            "type":"Services"
        }
    ],
    "sg:phone":"+61 400 887 783",
    "sg:postcode":"4560",
    "sg:province":"QLD",
    "sg:tags":[
        "electrical"
    ],
    "wof:name":"Petrol Injector Services",
    "wof:placetype":"venue"
},
  "geometry": {"coordinates":[152.963378906,-26.6297912598],"type":"Point"}
}