{
  "type": "Feature",
  "properties": {
    "addr:full":"10 Koorana Rd Picton NSW 2571",
    "addr:housenumber":"10",
    "addr:postcode":"2571",
    "addr:street":"Koorana Rd",
    "iso:country":"AU",
    "sg:address":"10 Koorana Rd",
    "sg:city":"Picton",
    "sg:classifiers":[
        {
            "category":"Real Estate",
            "subcategory":"Real Estate Operator",
            "type":"Services"
        }
    ],
    "sg:phone":"+61 2 4683 2212",
    "sg:postcode":"2571",
    "sg:province":"NSW",
    "sg:tags":[
        "concrete",
        "pumping"
    ],
    "wof:name":"J & D Concrete Pumping Services",
    "wof:placetype":"venue"
},
  "geometry": {"coordinates":[150.60885620100001,-34.212348938],"type":"Point"}
}