{
  "type": "Feature",
  "properties": {
    "iso:country":"AU",
    "sg:address":"150 Cronulla St",
    "sg:city":"Cronulla",
    "sg:classifiers":[
        {
            "category":"Personal",
            "subcategory":"Beauty Salon",
            "type":"Services"
        }
    ],
    "sg:phone":"+61 2 9523 5001",
    "sg:postcode":"2230",
    "sg:province":"NSW",
    "wof:name":"Backstage Day Spa",
    "wof:placetype":"venue"
},
  "geometry": {"coordinates":[151.151977539,-34.0549812317],"type":"Point"}
}