{
  "type": "Feature",
  "properties": {
    "addr:full":"2nd Floor 169 Swanston Wlk Melbourne VIC 3000",
    "addr:housenumber":"169",
    "addr:postcode":"3000",
    "addr:street":"Swanston Wlk",
    "iso:country":"AU",
    "sg:address":"2nd Floor 169 Swanston Wlk",
    "sg:city":"Melbourne",
    "sg:classifiers":[
        {
            "category":"Organizations",
            "subcategory":"Community Association",
            "type":"Services"
        }
    ],
    "sg:phone":"+61 3 9654 7690",
    "sg:postcode":"3000",
    "sg:province":"VIC",
    "sg:tags":[
        "organisation",
        "family",
        "welfare"
    ],
    "wof:name":"Travellers' Aid Disability Access Service",
    "wof:placetype":"venue"
},
  "geometry": {"coordinates":[144.96562194800001,-37.8138275146],"type":"Point"}
}