{
  "type": "Feature",
  "properties": {
    "addr:full":"4/41- 45 Railway Ave Werribee VIC 3030",
    "addr:housenumber":"/;45",
    "addr:postcode":"3030",
    "addr:street":"41;Railway Ave",
    "iso:country":"AU",
    "sg:address":"4/41- 45 Railway Ave",
    "sg:city":"Werribee",
    "sg:classifiers":[
        {
            "category":"Retail",
            "subcategory":"Repair Shop",
            "type":"Services"
        }
    ],
    "sg:phone":"+61 3 9742 2260",
    "sg:postcode":"3030",
    "sg:province":"VIC",
    "sg:tags":[
        "handbag"
    ],
    "wof:name":"Rosalino's Food Manufacturing Pty Ltd",
    "wof:placetype":"venue"
},
  "geometry": {"coordinates":[144.676086,-37.893028],"type":"Point"}
}