{
  "type": "Feature",
  "properties": {
    "addr:full":"Level 1, Cnr First Ave & Gold Coast Hwy Burleigh Heads QLD 4220",
    "addr:postcode":"4220",
    "addr:street":"First Ave & Gold Coast Hwy",
    "iso:country":"AU",
    "sg:address":"Level 1, Cnr First Ave & Gold Coast Hwy",
    "sg:city":"Burleigh Heads",
    "sg:classifiers":[
        {
            "category":"Personal",
            "subcategory":"Massage",
            "type":"Services"
        }
    ],
    "sg:phone":"+61 7 5520 0644",
    "sg:postcode":"4220",
    "sg:province":"QLD",
    "sg:tags":[
        "therapy"
    ],
    "wof:name":"John Garfield",
    "wof:placetype":"venue"
},
  "geometry": {"coordinates":[153.45013427699999,-28.0863265991],"type":"Point"}
}