{
  "type": "Feature",
  "properties": {
    "addr:full":"Unit 6/ 17 Wellard St Bibra Lake WA 6163",
    "addr:postcode":"6163",
    "addr:street":"17 Wellard St",
    "iso:country":"AU",
    "sg:address":"Unit 6/ 17 Wellard St",
    "sg:city":"Bibra Lake",
    "sg:classifiers":[
        {
            "category":"Manufacturing",
            "subcategory":"Glass & Minerals",
            "type":"Manufacturing & Wholesale Goods"
        }
    ],
    "sg:phone":"+61 8 9494 1610",
    "sg:postcode":"6163",
    "sg:province":"WA",
    "sg:tags":[
        "merchant",
        "granite",
        "marble"
    ],
    "wof:name":"Refined Marble & Granite",
    "wof:placetype":"venue"
},
  "geometry": {"coordinates":[115.801727,-32.105927],"type":"Point"}
}