{
  "type": "Feature",
  "properties": {
    "addr:full":"154 Young St Carrington NSW 2294",
    "addr:housenumber":"154",
    "addr:postcode":"2294",
    "addr:street":"Young St",
    "iso:country":"AU",
    "sg:address":"154 Young St",
    "sg:city":"Carrington",
    "sg:classifiers":[
        {
            "category":"Home & Garden",
            "subcategory":"Hardware",
            "type":"Retail Goods"
        }
    ],
    "sg:phone":"+61 2 4961 6414",
    "sg:postcode":"2294",
    "sg:province":"NSW",
    "sg:tags":[
        "generating",
        "set",
        "generator"
    ],
    "wof:name":"Generator Rentals Pty Ltd",
    "wof:placetype":"venue"
},
  "geometry": {"coordinates":[151.76632690400001,-32.9169273376],"type":"Point"}
}