{
  "type": "Feature",
  "properties": {
    "addr:full":"118a Margaret St Launceston TAS 7250",
    "addr:housenumber":"118a",
    "addr:postcode":"7250",
    "addr:street":"Margaret St",
    "iso:country":"AU",
    "sg:address":"118a Margaret St",
    "sg:city":"Launceston",
    "sg:classifiers":[
        {
            "category":"Education",
            "subcategory":"Music School",
            "type":"Public Place"
        }
    ],
    "sg:phone":"+61 3 6331 8996",
    "sg:postcode":"7250",
    "sg:province":"TAS",
    "sg:tags":[
        "teacher"
    ],
    "wof:name":"Clark Glenn W",
    "wof:placetype":"venue"
},
  "geometry": {"coordinates":[147.13726806599999,-41.4465522766],"type":"Point"}
}