{
  "type": "Feature",
  "properties": {
    "iso:country":"AU",
    "sg:address":"25 Towong St",
    "sg:city":"Tallangatta",
    "sg:classifiers":[
        {
            "category":"Food & Beverages",
            "subcategory":"Supermarket",
            "type":"Retail Goods"
        }
    ],
    "sg:phone":"+61 2 6071 2201",
    "sg:postcode":"3700",
    "sg:province":"VIC",
    "sg:tags":[
        "grocery",
        "store"
    ],
    "wof:name":"Tallangatta Super Store",
    "wof:placetype":"venue"
},
  "geometry": {"coordinates":[147.17955017099999,-36.2158241272],"type":"Point"}
}