{
  "type": "Feature",
  "properties": {
    "addr:full":"The Village Mall George St Beenleigh QLD 4207",
    "addr:postcode":"4207",
    "addr:street":"George St",
    "iso:country":"AU",
    "sg:address":"The Village Mall George St",
    "sg:city":"Beenleigh",
    "sg:classifiers":[
        {
            "category":"Food & Beverages",
            "subcategory":"Supermarket",
            "type":"Retail Goods"
        }
    ],
    "sg:phone":"+61 7 3287 4109",
    "sg:postcode":"4207",
    "sg:province":"QLD",
    "sg:tags":[
        "grocery",
        "store"
    ],
    "wof:name":"Franklins",
    "wof:placetype":"venue"
},
  "geometry": {"coordinates":[153.19346618599999,-27.7148361206],"type":"Point"}
}