{
  "type": "Feature",
  "properties": {
    "addr:full":"PO Box 94 Yinnar VIC 3869",
    "addr:postcode":"3869",
    "iso:country":"AU",
    "sg:address":"PO Box 94",
    "sg:city":"Yinnar",
    "sg:classifiers":[
        {
            "category":"Building & Trades",
            "subcategory":"Landscaping Services",
            "type":"Services"
        }
    ],
    "sg:phone":"+61 427 631 627",
    "sg:postcode":"3869",
    "sg:province":"VIC",
    "sg:tags":[
        "control",
        "weed"
    ],
    "wof:name":"Allan Wyhoon Enterprises",
    "wof:placetype":"venue"
},
  "geometry": {"coordinates":[146.32502746599999,-38.3253288269],"type":"Point"}
}