{
  "type": "Feature",
  "properties": {
    "addr:full":"140 Overett Ave Kemps Creek NSW 2171",
    "addr:housenumber":"140",
    "addr:postcode":"2171",
    "addr:street":"Overett Ave",
    "iso:country":"AU",
    "sg:address":"140 Overett Ave",
    "sg:city":"Kemps Creek",
    "sg:classifiers":[
        {
            "category":"Manufacturing",
            "subcategory":"Tools & Machinery",
            "type":"Manufacturing & Wholesale Goods"
        }
    ],
    "sg:phone":"+61 2 9826 1283",
    "sg:postcode":"2171",
    "sg:province":"NSW",
    "sg:tags":[
        "earth",
        "excavating",
        "moving",
        "equipment"
    ],
    "wof:name":"G P S Plant Hire",
    "wof:placetype":"venue"
},
  "geometry": {"coordinates":[150.770385742,-33.8795623779],"type":"Point"}
}