{
  "type": "Feature",
  "properties": {
    "iso:country":"AU",
    "sg:address":"4 / 40 George St",
    "sg:city":"Granville",
    "sg:classifiers":[
        {
            "category":"Professional",
            "type":"Services"
        }
    ],
    "sg:phone":"+61 2 9682 1222",
    "sg:postcode":"2142",
    "sg:province":"NSW",
    "sg:tags":[
        "courier"
    ],
    "wof:name":"Snap Courier Services Pty Ltd",
    "wof:placetype":"venue"
},
  "geometry": {"coordinates":[151.018035889,-33.8324890137],"type":"Point"}
}