{
  "type": "Feature",
  "properties": {
    "addr:full":"73 Waratah St Seacliff SA 5049",
    "addr:housenumber":"73",
    "addr:postcode":"5049",
    "addr:street":"Waratah St",
    "iso:country":"AU",
    "sg:address":"73 Waratah St",
    "sg:city":"Seacliff",
    "sg:classifiers":[
        {
            "category":"Professional",
            "subcategory":"Computer Services",
            "type":"Services"
        }
    ],
    "sg:phone":"+61 8 8377 2366",
    "sg:postcode":"5049",
    "sg:province":"SA",
    "sg:tags":[
        "repairs",
        "upgrade",
        "equipment"
    ],
    "wof:name":"Network Solutions",
    "wof:placetype":"venue"
},
  "geometry": {"coordinates":[138.520782,-35.03344],"type":"Point"}
}