{
  "type": "Feature",
  "properties": {
    "addr:full":"2 abercairn Crt Deer Park VIC 3023",
    "addr:housenumber":"2",
    "addr:postcode":"3023",
    "addr:street":"Abercairn Crt",
    "iso:country":"AU",
    "sg:address":"2 abercairn Crt",
    "sg:city":"Deer Park",
    "sg:classifiers":[
        {
            "category":"Building & Trades",
            "subcategory":"Construction",
            "type":"Services"
        }
    ],
    "sg:phone":"+61 412 800 830",
    "sg:postcode":"3023",
    "sg:province":"VIC",
    "sg:tags":[
        "window",
        "tinting"
    ],
    "wof:name":"The Tint Guy",
    "wof:placetype":"venue"
},
  "geometry": {"coordinates":[144.75822400000001,-37.758526],"type":"Point"}
}