{
  "type": "Feature",
  "properties": {
    "iso:country":"AU",
    "sg:address":"2/ 368 Griffith Rd",
    "sg:city":"Lavington",
    "sg:classifiers":[
        {
            "category":"Autos & Motor Vehicles",
            "subcategory":"Auto Supplies",
            "type":"Retail Goods"
        }
    ],
    "sg:phone":"+61 2 6025 9516",
    "sg:postcode":"2641",
    "sg:province":"NSW",
    "sg:tags":[
        "tyre"
    ],
    "wof:name":"Mates Rates Tyre & Wheel Centre",
    "wof:placetype":"venue"
},
  "geometry": {"coordinates":[146.94198608400001,-36.0445518494],"type":"Point"}
}