{
  "type": "Feature",
  "properties": {
    "addr:full":"107 Beresford Rd Lilydale VIC 3140",
    "addr:housenumber":"107",
    "addr:postcode":"3140",
    "addr:street":"Beresford Rd",
    "iso:country":"AU",
    "sg:address":"107 Beresford Rd",
    "sg:city":"Lilydale",
    "sg:classifiers":[
        {
            "category":"Retail",
            "subcategory":"Auto Repair",
            "type":"Services"
        }
    ],
    "sg:phone":"+61 3 9739 6588",
    "sg:postcode":"3140",
    "sg:province":"VIC",
    "sg:tags":[
        "beater",
        "painter",
        "panel"
    ],
    "wof:name":"A.R.P. Smash Repairs",
    "wof:placetype":"venue"
},
  "geometry": {"coordinates":[145.3487854,-37.7509880066],"type":"Point"}
}