{
  "type": "Feature",
  "properties": {
    "addr:full":"163 Park Rd Yeerongpilly QLD 4105",
    "addr:housenumber":"163",
    "addr:postcode":"4105",
    "addr:street":"Park Rd",
    "iso:country":"AU",
    "sg:address":"163 Park Rd",
    "sg:city":"Yeerongpilly",
    "sg:classifiers":[
        {
            "category":"Professional",
            "subcategory":"Printing & Photocopies",
            "type":"Services"
        }
    ],
    "sg:phone":"+61 7 3848 0547",
    "sg:postcode":"4105",
    "sg:province":"QLD",
    "sg:tags":[
        "embroidery"
    ],
    "wof:name":"Busy Bobbin",
    "wof:placetype":"venue"
},
  "geometry": {"coordinates":[153.018630981,-27.5232524872],"type":"Point"}
}