{
  "type": "Feature",
  "properties": {
    "addr:full":"12 Gallipoli St Condell Park NSW 2200",
    "addr:housenumber":"12",
    "addr:postcode":"2200",
    "addr:street":"Gallipoli St",
    "iso:country":"AU",
    "sg:address":"12 Gallipoli St",
    "sg:city":"Condell Park",
    "sg:classifiers":[
        {
            "category":"Food & Beverages",
            "subcategory":"Specialty",
            "type":"Retail Goods"
        }
    ],
    "sg:phone":"+61 2 9786 1854",
    "sg:postcode":"2200",
    "sg:province":"NSW",
    "sg:tags":[
        "product",
        "health"
    ],
    "wof:name":"Herbalife Australasia Pty Ltd",
    "wof:placetype":"venue"
},
  "geometry": {"coordinates":[151.02110300000001,-33.926903],"type":"Point"}
}