{
  "type": "Feature",
  "properties": {
    "addr:full":"Redbank Plaza S/C 1 Collingwood Drv Redbank QLD 4301",
    "addr:housenumber":"1",
    "addr:postcode":"4301",
    "addr:street":"Collingwood Drv",
    "iso:country":"AU",
    "sg:address":"Redbank Plaza S/C 1 Collingwood Drv",
    "sg:city":"Redbank",
    "sg:classifiers":[
        {
            "category":"Shopping",
            "subcategory":"Jewelry",
            "type":"Retail Goods"
        }
    ],
    "sg:phone":"+61 7 3818 2911",
    "sg:postcode":"4301",
    "sg:province":"QLD",
    "sg:tags":[
        "jeweller"
    ],
    "wof:name":"Prouds The Jewellers",
    "wof:placetype":"venue"
},
  "geometry": {"coordinates":[152.86949157699999,-27.6062335968],"type":"Point"}
}