{
  "type": "Feature",
  "properties": {
    "iso:country":"AU",
    "sg:address":"Lot161/ Jubilee Ave",
    "sg:city":"Beverley Park",
    "sg:classifiers":[
        {
            "category":"Sports & Exercise",
            "subcategory":"Golf",
            "type":"Entertainment"
        }
    ],
    "sg:phone":"+61 2 9588 5828",
    "sg:postcode":"2217",
    "sg:province":"NSW",
    "sg:tags":[
        "club"
    ],
    "wof:name":"Beverley Park Golf Club Ltd",
    "wof:placetype":"venue"
},
  "geometry": {"coordinates":[151.13218699999999,-33.975597],"type":"Point"}
}