{
  "type": "Feature",
  "properties": {
    "addr:full":"5/ 22-28 Best St Fitzroy North VIC 3068",
    "addr:housenumber":"/ 22-28",
    "addr:postcode":"3068",
    "addr:street":"Best St",
    "iso:country":"AU",
    "sg:address":"5/ 22-28 Best St",
    "sg:city":"Fitzroy North",
    "sg:classifiers":[
        {
            "category":"Real Estate",
            "subcategory":"Architect",
            "type":"Services"
        }
    ],
    "sg:phone":"+61 3 9481 7002",
    "sg:postcode":"3068",
    "sg:province":"VIC",
    "sg:tags":[
        "building",
        "designer"
    ],
    "wof:name":"Busselmann & Associates",
    "wof:placetype":"venue"
},
  "geometry": {"coordinates":[144.98326110799999,-37.784286499],"type":"Point"}
}