{
  "type": "Feature",
  "properties": {
    "addr:full":"86 Golf Links Rd Lakes Entrance VIC 3909",
    "addr:housenumber":"86",
    "addr:postcode":"3909",
    "addr:street":"Golf Links Rd Lakes",
    "iso:country":"AU",
    "sg:address":"86 Golf Links Rd",
    "sg:city":"Lakes Entrance",
    "sg:classifiers":[
        {
            "category":"Social Services",
            "subcategory":"Retirement Home",
            "type":"Services"
        }
    ],
    "sg:phone":"+61 419 553 647",
    "sg:postcode":"3909",
    "sg:province":"VIC",
    "sg:tags":[
        "village"
    ],
    "wof:name":"Lakes Entrance Re-Locatable Home Village",
    "wof:placetype":"venue"
},
  "geometry": {"coordinates":[148.015060425,-37.871131897],"type":"Point"}
}