{
  "type": "Feature",
  "properties": {
    "addr:full":"38 Parkhurst Drv Knoxfield VIC 3180",
    "addr:housenumber":"38",
    "addr:postcode":"3180",
    "addr:street":"Parkhurst Drv",
    "iso:country":"AU",
    "sg:address":"38 Parkhurst Drv",
    "sg:city":"Knoxfield",
    "sg:classifiers":[
        {
            "category":"Banks & Credit Unions",
            "subcategory":"Bureau De Change",
            "type":"Services"
        }
    ],
    "sg:phone":"+61 3 9887 4998",
    "sg:postcode":"3180",
    "sg:province":"VIC",
    "sg:tags":[
        "equipment",
        "heat",
        "exchange"
    ],
    "wof:name":"Allied Heat Transfer",
    "wof:placetype":"venue"
},
  "geometry": {"coordinates":[145.252197266,-37.8722686768],"type":"Point"}
}