{
  "type": "Feature",
  "properties": {
    "addr:full":"222 Welshpool Rd Welshpool WA 6106",
    "addr:housenumber":"222",
    "addr:postcode":"6106",
    "addr:street":"Welshpool Rd",
    "iso:country":"AU",
    "sg:address":"222 Welshpool Rd",
    "sg:city":"Welshpool",
    "sg:classifiers":[
        {
            "category":"Shopping",
            "subcategory":"Pets & Pet Supplies",
            "type":"Retail Goods"
        }
    ],
    "sg:phone":"+61 8 9451 6682",
    "sg:postcode":"6106",
    "sg:province":"WA",
    "sg:tags":[
        "boring",
        "drilling",
        "equipment"
    ],
    "wof:name":"Secoroc Australia Pty Limited",
    "wof:placetype":"venue"
},
  "geometry": {"coordinates":[115.97386169400001,-32.0032348633],"type":"Point"}
}