{
  "type": "Feature",
  "properties": {
    "addr:full":"12 Moore St Austinmer NSW 2515",
    "addr:housenumber":"12",
    "addr:postcode":"2515",
    "addr:street":"Moore St",
    "iso:country":"AU",
    "sg:address":"12 Moore St",
    "sg:city":"Austinmer",
    "sg:classifiers":[
        {
            "category":"Professional",
            "subcategory":"Art Services",
            "type":"Services"
        }
    ],
    "sg:phone":"+61 2 4268 6232",
    "sg:postcode":"2515",
    "sg:province":"NSW",
    "sg:tags":[
        "graphic",
        "designer"
    ],
    "wof:name":"CarriE Graphic Design Services",
    "wof:placetype":"venue"
},
  "geometry": {"coordinates":[150.93298300000001,-34.3074],"type":"Point"}
}