{
  "type": "Feature",
  "properties": {
    "addr:full":"13 Ku-Ring Gai Crt Maroochydore QLD 4558",
    "addr:housenumber":"13",
    "addr:postcode":"4558",
    "addr:street":"Ku-Ring Gai Crt",
    "iso:country":"AU",
    "sg:address":"13 Ku-Ring Gai Crt",
    "sg:city":"Maroochydore",
    "sg:classifiers":[
        {
            "category":"Retail",
            "subcategory":"Repair Shop",
            "type":"Services"
        }
    ],
    "sg:phone":"+61 7 5476 5508",
    "sg:postcode":"4558",
    "sg:province":"QLD",
    "sg:tags":[
        "mending",
        "clothing",
        "alteration"
    ],
    "wof:name":"Dickinson-Fox J",
    "wof:placetype":"venue"
},
  "geometry": {"coordinates":[153.06077575699999,-26.6624221802],"type":"Point"}
}