{
  "type": "Feature",
  "properties": {
    "addr:full":"156 Barwarre Rd Grovedale VIC 3216",
    "addr:housenumber":"156",
    "addr:postcode":"3216",
    "addr:street":"Barwarre Rd",
    "iso:country":"AU",
    "sg:address":"156 Barwarre Rd",
    "sg:city":"Grovedale",
    "sg:classifiers":[
        {
            "category":"Manufacturing",
            "subcategory":"Tools & Machinery",
            "type":"Manufacturing & Wholesale Goods"
        }
    ],
    "sg:phone":"+61 418 599 427",
    "sg:postcode":"3216",
    "sg:province":"VIC",
    "sg:tags":[
        "earth",
        "excavating",
        "moving",
        "equipment"
    ],
    "wof:name":"Shane O'Neill Excavations",
    "wof:placetype":"venue"
},
  "geometry": {"coordinates":[144.371170044,-38.1988792419],"type":"Point"}
}