{
  "type": "Feature",
  "properties": {
    "addr:full":"Level 4, Suite 4005, 376 Bay St Brighton-le-Sands NSW 2216",
    "addr:housenumber":"376",
    "addr:postcode":"2216",
    "addr:street":"Bay St",
    "iso:country":"AU",
    "sg:address":"Level 4, Suite 4005, 376 Bay St",
    "sg:city":"Brighton-le-Sands",
    "sg:classifiers":[
        {
            "category":"Banks & Credit Unions",
            "subcategory":"Financial Services",
            "type":"Services"
        }
    ],
    "sg:phone":"+61 2 9599 3133",
    "sg:postcode":"2216",
    "sg:province":"NSW",
    "sg:tags":[
        "planning"
    ],
    "wof:name":"Materials Cost Management Pty Ltd",
    "wof:placetype":"venue"
},
  "geometry": {"coordinates":[151.156128,-33.960987],"type":"Point"}
}