{
  "type": "Feature",
  "properties": {
    "iso:country":"AU",
    "sg:address":"116 Harold St",
    "sg:city":"Middle Park",
    "sg:classifiers":[
        {
            "category":"Home & Garden",
            "subcategory":"Furniture",
            "type":"Retail Goods"
        }
    ],
    "sg:phone":"+61 3 9696 9462",
    "sg:postcode":"3206",
    "sg:province":"VIC",
    "sg:tags":[
        "outdoor"
    ],
    "wof:name":"Leblon Outdoor Design",
    "wof:placetype":"venue"
},
  "geometry": {"coordinates":[144.958054,-37.852177],"type":"Point"}
}