{
  "type": "Feature",
  "properties": {
    "addr:full":"Level 4 ,Sunnybank Hills Shoppingtown Sunnybank Hills QLD 4109",
    "addr:postcode":"4109",
    "iso:country":"AU",
    "sg:address":"Level 4",
    "sg:city":",Sunnybank Hills Shoppingtown Sunnybank Hills",
    "sg:classifiers":[
        {
            "category":"Personal",
            "subcategory":"Beauty Salon",
            "type":"Services"
        }
    ],
    "sg:phone":"+61 7 3847 7227",
    "sg:postcode":"4109",
    "sg:province":"QLD",
    "wof:name":"Cherise For Nails",
    "wof:placetype":"venue"
},
  "geometry": {"coordinates":[153.06637573200001,-27.5965461731],"type":"Point"}
}