{
  "type": "Feature",
  "properties": {
    "addr:full":"35 Kylie Crs Batemans Bay NSW 2536",
    "addr:housenumber":"35",
    "addr:postcode":"2536",
    "addr:street":"Kylie Crs",
    "iso:country":"AU",
    "sg:address":"35 Kylie Crs",
    "sg:city":"Batemans Bay",
    "sg:classifiers":[
        {
            "category":"Wholesale",
            "subcategory":"Metals & Minerals",
            "type":"Manufacturing & Wholesale Goods"
        }
    ],
    "sg:phone":"+61 2 4472 5004",
    "sg:postcode":"2536",
    "sg:province":"NSW",
    "sg:tags":[
        "steel",
        "stainless",
        "product",
        "equipment"
    ],
    "wof:name":"Eurobodalla Refrigeration & Coffee Equipment Pty Ltd",
    "wof:placetype":"venue"
},
  "geometry": {"coordinates":[150.17732238799999,-35.7084007263],"type":"Point"}
}