{
  "type": "Feature",
  "properties": {
    "iso:country":"AU",
    "sg:address":"Florina Rd",
    "sg:city":"Katherine",
    "sg:classifiers":[
        {
            "category":"Professional",
            "type":"Services"
        }
    ],
    "sg:phone":"+61 8 8975 0525",
    "sg:postcode":"0850",
    "sg:province":"NT",
    "sg:tags":[
        "transport"
    ],
    "wof:name":"Barton House Shift",
    "wof:placetype":"venue"
},
  "geometry": {"coordinates":[132.23130800000001,-14.467741],"type":"Point"}
}