{
  "type": "Feature",
  "properties": {
    "iso:country":"AU",
    "sg:address":"64 Caledonian Ave",
    "sg:city":"Maylands",
    "sg:classifiers":[
        {
            "category":"Social Services",
            "subcategory":"Job Training",
            "type":"Services"
        }
    ],
    "sg:phone":"+61 8 9271 6725",
    "sg:postcode":"6051",
    "sg:province":"WA",
    "sg:tags":[
        "goldsmith",
        "silversmith"
    ],
    "wof:name":"Linton Silver",
    "wof:placetype":"venue"
},
  "geometry": {"coordinates":[115.901756,-31.932425],"type":"Point"}
}