{
  "type": "Feature",
  "properties": {
    "addr:full":"10-16 Syme St Brunswick VIC 3056",
    "addr:housenumber":"10-16",
    "addr:postcode":"3056",
    "addr:street":"Syme St",
    "iso:country":"AU",
    "sg:address":"10-16 Syme St",
    "sg:city":"Brunswick",
    "sg:classifiers":[
        {
            "category":"Wholesale",
            "subcategory":"Machinery & Supplies",
            "type":"Manufacturing & Wholesale Goods"
        }
    ],
    "sg:phone":"+61 3 9388 0588",
    "sg:postcode":"3056",
    "sg:province":"VIC",
    "sg:tags":[
        "equipment",
        "welding"
    ],
    "wof:name":"Talarc Welding Products",
    "wof:placetype":"venue"
},
  "geometry": {"coordinates":[144.95460510300001,-37.7691459656],"type":"Point"}
}