{
  "type": "Feature",
  "properties": {
    "addr:full":"Darlinghurst Public School, Cnr Liverpool St & Barcom Ave Sydney NSW 2000",
    "addr:postcode":"2000",
    "addr:street":"Cnr Liverpool St & Barcom Ave",
    "iso:country":"AU",
    "sg:address":"Darlinghurst Public School, Cnr Liverpool St & Barcom Ave",
    "sg:city":"Sydney",
    "sg:classifiers":[
        {
            "category":"Organizations",
            "subcategory":"Professional Association",
            "type":"Services"
        }
    ],
    "sg:phone":"+61 2 9331 6920",
    "sg:postcode":"2000",
    "sg:province":"NSW",
    "sg:tags":[
        "organisation",
        "business"
    ],
    "wof:name":"Institute Of Electrical & Electronics Engineers Inc The",
    "wof:placetype":"venue"
},
  "geometry": {"coordinates":[151.20828247099999,-33.8766899109],"type":"Point"}
}