{
  "type": "Feature",
  "properties": {
    "addr:full":"27 Melbourne St Geelong VIC 3220",
    "addr:housenumber":"27",
    "addr:postcode":"3220",
    "addr:street":"Melbourne St",
    "iso:country":"AU",
    "sg:address":"27 Melbourne St",
    "sg:city":"Geelong",
    "sg:classifiers":[
        {
            "category":"Home & Garden",
            "subcategory":"Carpets & Floor Coverings",
            "type":"Retail Goods"
        }
    ],
    "sg:phone":"+61 3 5277 2779",
    "sg:postcode":"3220",
    "sg:province":"VIC",
    "sg:tags":[
        "laying",
        "supply"
    ],
    "wof:name":"Stewart Wholesalers",
    "wof:placetype":"venue"
},
  "geometry": {"coordinates":[144.34605400000001,-38.157108],"type":"Point"}
}