{
  "type": "Feature",
  "properties": {
    "iso:country":"AU",
    "sg:address":"Mid Western Hwy",
    "sg:city":"Goolgowi",
    "sg:classifiers":[
        {
            "category":"Autos & Motor Vehicles",
            "subcategory":"Fuel & Gas Station",
            "type":"Retail Goods"
        }
    ],
    "sg:phone":"+61 2 6965 1200",
    "sg:postcode":"2652",
    "sg:province":"NSW",
    "wof:name":"Goolgowi Truck & Tucker",
    "wof:placetype":"venue"
},
  "geometry": {"coordinates":[145.715087891,-33.9777412415],"type":"Point"}
}