{
  "type": "Feature",
  "properties": {
    "iso:country":"AU",
    "sg:address":"Shop 6/ 120 Dempster St",
    "sg:city":"Esperance",
    "sg:classifiers":[
        {
            "category":"Shopping",
            "subcategory":"Crafts & Fabrics",
            "type":"Retail Goods"
        }
    ],
    "sg:phone":"+61 8 9072 1760",
    "sg:postcode":"6450",
    "sg:province":"WA",
    "sg:tags":[
        "supply"
    ],
    "wof:name":"Patches &#039;N&#039; Things",
    "wof:placetype":"venue"
},
  "geometry": {"coordinates":[121.893066406,-33.8596382141],"type":"Point"}
}