{
  "type": "Feature",
  "properties": {
    "addr:full":"93/ 24 Buchanan St Balmain NSW 2041",
    "addr:housenumber":"93 / 24",
    "addr:postcode":"2041",
    "addr:street":"Buchanan St",
    "iso:country":"AU",
    "sg:address":"93/ 24 Buchanan St",
    "sg:city":"Balmain",
    "sg:classifiers":[
        {
            "category":"Banks & Credit Unions",
            "subcategory":"Bank",
            "type":"Services"
        }
    ],
    "sg:phone":"+61 1300 765 765",
    "sg:postcode":"2041",
    "sg:province":"NSW",
    "wof:name":"Aussie Financial Services",
    "wof:placetype":"venue"
},
  "geometry": {"coordinates":[151.180206,-33.863392],"type":"Point"}
}