{
  "type": "Feature",
  "properties": {
    "addr:full":"Shop 263 Ipswich City Mall, Nicholas Street Nicholas St Ipswich QLD 4305",
    "addr:housenumber":"263",
    "addr:postcode":"4305",
    "addr:street":"Nicholas Street Nicholas St",
    "iso:country":"AU",
    "sg:address":"Shop 263 Ipswich City Mall, Nicholas Street Nicholas St",
    "sg:city":"Ipswich",
    "sg:classifiers":[
        {
            "category":"Wholesale",
            "subcategory":"Medical Equipment & Supplies",
            "type":"Manufacturing & Wholesale Goods"
        }
    ],
    "sg:phone":"+61 7 3812 5133",
    "sg:postcode":"4305",
    "sg:province":"QLD",
    "sg:tags":[
        "aids",
        "hearing"
    ],
    "wof:name":"Hearing Life",
    "wof:placetype":"venue"
},
  "geometry": {"coordinates":[152.76527404800001,-27.6164894104],"type":"Point"}
}