{
  "type": "Feature",
  "properties": {
    "addr:full":"Shop 3848 Westfield Shopngtwn North Rocks NSW 2151",
    "addr:housenumber":"3848",
    "addr:postcode":"2151",
    "addr:street":"Westfield Shopngtwn",
    "iso:country":"AU",
    "sg:address":"Shop 3848 Westfield Shopngtwn",
    "sg:city":"North Rocks",
    "sg:classifiers":[
        {
            "category":"Shopping",
            "subcategory":"Clothing, Apparel, & Fashions",
            "type":"Retail Goods"
        }
    ],
    "sg:phone":"+61 2 9873 3744",
    "sg:postcode":"2151",
    "sg:province":"NSW",
    "sg:tags":[
        "lady",
        "wear"
    ],
    "wof:name":"Fashion Warehouse Pty Ltd",
    "wof:placetype":"venue"
},
  "geometry": {"coordinates":[151.021286011,-33.7750396729],"type":"Point"}
}