{
  "type": "Feature",
  "properties": {
    "iso:country":"AU",
    "sg:address":"Unit 3 46 Violet St",
    "sg:city":"Gympie",
    "sg:classifiers":[
        {
            "category":"Building & Trades",
            "subcategory":"Construction",
            "type":"Services"
        }
    ],
    "sg:phone":"+61 7 5482 8626",
    "sg:postcode":"4570",
    "sg:province":"QLD",
    "sg:tags":[
        "joinery"
    ],
    "wof:name":"Gympie Joinery",
    "wof:placetype":"venue"
},
  "geometry": {"coordinates":[152.652175903,-26.1828575134],"type":"Point"}
}