{
  "type": "Feature",
  "properties": {
    "addr:full":"PO Box 9 Broome WA 6725",
    "addr:postcode":"6725",
    "iso:country":"AU",
    "sg:address":"PO Box 9",
    "sg:city":"Broome",
    "sg:classifiers":[
        {
            "category":"Professional",
            "subcategory":"Business Services",
            "type":"Services"
        }
    ],
    "sg:phone":"+61 418 936 614",
    "sg:postcode":"6725",
    "sg:province":"WA",
    "sg:tags":[
        "drafting"
    ],
    "wof:name":"Concept Building Design & Drafting",
    "wof:placetype":"venue"
},
  "geometry": {"coordinates":[122.677589416,-18.2141704559],"type":"Point"}
}