{
  "type": "Feature",
  "properties": {
    "iso:country":"AU",
    "sg:address":"4 Kergo Pl",
    "sg:city":"Wantirna South",
    "sg:classifiers":[
        {
            "category":"Home & Garden",
            "subcategory":"Building Materials",
            "type":"Retail Goods"
        }
    ],
    "sg:phone":"+61 3 9887 1890",
    "sg:postcode":"3152",
    "sg:province":"VIC",
    "sg:tags":[
        "merchant",
        "glass",
        "glazier"
    ],
    "wof:name":"Brooks Glass",
    "wof:placetype":"venue"
},
  "geometry": {"coordinates":[145.24293518100001,-37.8812561035],"type":"Point"}
}