{
  "type": "Feature",
  "properties": {
    "iso:country":"AU",
    "sg:address":"Shop 5, 99 Elizabeth St",
    "sg:city":"Brisbane",
    "sg:classifiers":[
        {
            "category":"Personal",
            "subcategory":"Beauty Salon",
            "type":"Services"
        }
    ],
    "sg:phone":"+61 7 3003 0533",
    "sg:postcode":"4000",
    "sg:province":"QLD",
    "sg:tags":[
        "supply",
        "artist",
        "make-up"
    ],
    "wof:name":"Napoleon Makeup Emporium.",
    "wof:placetype":"venue"
},
  "geometry": {"coordinates":[153.025558472,-27.4709091187],"type":"Point"}
}