{
  "type": "Feature",
  "properties": {
    "addr:full":"6 Mullum Drv Donvale VIC 3111",
    "addr:housenumber":"6",
    "addr:postcode":"3111",
    "addr:street":"Mullum Drv",
    "iso:country":"AU",
    "sg:address":"6 Mullum Drv",
    "sg:city":"Donvale",
    "sg:classifiers":[
        {
            "category":"Utilities",
            "subcategory":"Electric",
            "type":"Services"
        }
    ],
    "sg:phone":"+61 3 9842 6993",
    "sg:postcode":"3111",
    "sg:province":"VIC",
    "sg:tags":[
        "electrical",
        "contractor"
    ],
    "wof:name":"Dennis Electrics",
    "wof:placetype":"venue"
},
  "geometry": {"coordinates":[145.18592834500001,-37.7801208496],"type":"Point"}
}