{
  "type": "Feature",
  "properties": {
    "addr:full":"Unit 2 324 Bayswater Rd Garbutt QLD 4814",
    "addr:housenumber":"324",
    "addr:postcode":"4814",
    "addr:street":"Bayswater Rd",
    "iso:country":"AU",
    "sg:address":"Unit 2 324 Bayswater Rd",
    "sg:city":"Garbutt",
    "sg:classifiers":[
        {
            "category":"Building & Trades",
            "subcategory":"Construction",
            "type":"Services"
        }
    ],
    "sg:phone":"+61 407 730 999",
    "sg:postcode":"4814",
    "sg:province":"QLD",
    "sg:tags":[
        "scaffolding"
    ],
    "wof:name":"A1 Scaffolding-Zip Zap",
    "wof:placetype":"venue"
},
  "geometry": {"coordinates":[146.76507599999999,-19.273603],"type":"Point"}
}