{
  "type": "Feature",
  "properties": {
    "iso:country":"AU",
    "sg:address":"PO Box 175",
    "sg:city":"Jannali",
    "sg:classifiers":[
        {
            "category":"Professional",
            "subcategory":"Employment Agencies",
            "type":"Services"
        }
    ],
    "sg:phone":"+61 2 9521 5223",
    "sg:postcode":"2226",
    "sg:province":"NSW",
    "sg:tags":[
        "entertainer",
        "agent"
    ],
    "wof:name":"Still Crazy Management",
    "wof:placetype":"venue"
},
  "geometry": {"coordinates":[151.06605529800001,-34.0162887573],"type":"Point"}
}