{
  "type": "Feature",
  "properties": {
    "addr:full":"42 Amy St Regents Park NSW 2143",
    "addr:housenumber":"42",
    "addr:postcode":"2143",
    "addr:street":"Amy St",
    "iso:country":"AU",
    "sg:address":"42 Amy St",
    "sg:city":"Regents Park",
    "sg:classifiers":[
        {
            "category":"Professional",
            "subcategory":"Detective & Security Services",
            "type":"Services"
        }
    ],
    "sg:phone":"+61 2 9645 5049",
    "sg:postcode":"2143",
    "sg:province":"NSW",
    "sg:tags":[
        "alarm",
        "protection",
        "system",
        "machinery"
    ],
    "wof:name":"Apex Alarms Electronics & Communications",
    "wof:placetype":"venue"
},
  "geometry": {"coordinates":[151.02687072800001,-33.8840904236],"type":"Point"}
}