{
  "type": "Feature",
  "properties": {
    "addr:full":"2958 Wean Rd Gunnedah NSW 2380",
    "addr:housenumber":"2958",
    "addr:postcode":"2380",
    "addr:street":"Wean Rd",
    "iso:country":"AU",
    "sg:address":"2958 Wean Rd",
    "sg:city":"Gunnedah",
    "sg:classifiers":[
        {
            "category":"Farming",
            "subcategory":"Farm",
            "type":"Manufacturing & Wholesale Goods"
        }
    ],
    "sg:phone":"+61 2 6743 2565",
    "sg:postcode":"2380",
    "sg:province":"NSW",
    "sg:tags":[
        "farmer"
    ],
    "wof:name":"Castlebar White Dorpers",
    "wof:placetype":"venue"
},
  "geometry": {"coordinates":[150.25680542000001,-30.9613647461],"type":"Point"}
}