{
  "type": "Feature",
  "properties": {
    "iso:country":"AU",
    "sg:address":"44 Sullivan Rd",
    "sg:city":"Kennedy",
    "sg:classifiers":[
        {
            "category":"Recreation",
            "subcategory":"Fishing",
            "type":"Entertainment"
        }
    ],
    "sg:phone":"+61 7 4066 0032",
    "sg:postcode":"4816",
    "sg:province":"QLD",
    "sg:tags":[
        "trip"
    ],
    "wof:name":"Un-Reel Sports Fishing Adventures",
    "wof:placetype":"venue"
},
  "geometry": {"coordinates":[145.92511,-18.241899],"type":"Point"}
}