{
  "type": "Feature",
  "properties": {
    "iso:country":"AU",
    "sg:address":"PO Box 6262",
    "sg:city":"Cairns",
    "sg:classifiers":[
        {
            "category":"Building & Trades",
            "subcategory":"Construction",
            "type":"Services"
        }
    ],
    "sg:phone":"+61 7 4034 2827",
    "sg:postcode":"4870",
    "sg:province":"QLD",
    "sg:tags":[
        "earth",
        "excavating",
        "moving",
        "contractor"
    ],
    "wof:name":"Cairns Mini Loaders & Tippers",
    "wof:placetype":"venue"
},
  "geometry": {"coordinates":[145.66958618199999,-17.0185699463],"type":"Point"}
}