{
  "type": "Feature",
  "properties": {
    "iso:country":"AU",
    "sg:address":"PO Box 503 Nedlands 6909",
    "sg:city":"Nedlands",
    "sg:classifiers":[
        {
            "category":"Organizations",
            "subcategory":"Membership Organization",
            "type":"Services"
        }
    ],
    "sg:phone":"+61 421 994 293",
    "sg:postcode":"6009",
    "sg:province":"WA",
    "sg:tags":[
        "club",
        "bridge"
    ],
    "wof:name":"BAWA",
    "wof:placetype":"venue"
},
  "geometry": {"coordinates":[115.807823,-31.984711],"type":"Point"}
}