{
  "type": "Feature",
  "properties": {
    "addr:full":"Shp 10A, Pelican Plaza Shopng Cntr, 1007 North Eas Modbury SA 5092",
    "addr:housenumber":"10a;1007",
    "addr:postcode":"5092",
    "addr:street":"Pelican Plaza Shopng Cntr;North Eas",
    "iso:country":"AU",
    "sg:address":"Shp 10A, Pelican Plaza Shopng Cntr, 1007 North Eas",
    "sg:city":"Modbury",
    "sg:classifiers":[
        {
            "category":"Banks & Credit Unions",
            "subcategory":"Financial Services",
            "type":"Services"
        }
    ],
    "sg:phone":"+61 8 8395 4888",
    "sg:postcode":"5092",
    "sg:province":"SA",
    "sg:tags":[
        "loan",
        "finance",
        "mortgage"
    ],
    "wof:name":"Wizard",
    "wof:placetype":"venue"
},
  "geometry": {"coordinates":[138.69456481899999,-34.827671051],"type":"Point"}
}