{
  "type": "Feature",
  "properties": {
    "iso:country":"AU",
    "sg:address":"1096 Doncaster Rd",
    "sg:city":"Doncaster East",
    "sg:classifiers":[
        {
            "category":"Insurance",
            "subcategory":"Insurance Agent",
            "type":"Services"
        }
    ],
    "sg:phone":"+61 3 9842 9333",
    "sg:postcode":"3109",
    "sg:province":"VIC",
    "sg:tags":[
        "broker"
    ],
    "wof:name":"Paramount Insurance Brokers Pty Ltd",
    "wof:placetype":"venue"
},
  "geometry": {"coordinates":[145.169754028,-37.790222168],"type":"Point"}
}