{
  "type": "Feature",
  "properties": {
    "iso:country":"AU",
    "sg:address":"5 Ray St",
    "sg:city":"Gympie",
    "sg:classifiers":[
        {
            "category":"Retail",
            "subcategory":"Storage",
            "type":"Services"
        }
    ],
    "sg:phone":"+61 408 826 755",
    "sg:postcode":"4570",
    "sg:province":"QLD",
    "wof:name":"Seer's Self Storage Facilities",
    "wof:placetype":"venue"
},
  "geometry": {"coordinates":[152.670532227,-26.1851196289],"type":"Point"}
}