{
  "type": "Feature",
  "properties": {
    "addr:full":"Hackett Pl Hackett ACT 2602",
    "addr:postcode":"2602",
    "addr:street":"Pl",
    "iso:country":"AU",
    "sg:address":"Hackett Pl",
    "sg:city":"Hackett",
    "sg:classifiers":[
        {
            "category":"Food & Beverages",
            "subcategory":"Supermarket",
            "type":"Retail Goods"
        }
    ],
    "sg:phone":"+61 2 6249 7303",
    "sg:postcode":"2602",
    "sg:province":"ACT",
    "sg:tags":[
        "grocery",
        "store"
    ],
    "wof:name":"Festival IGA Supermarkets",
    "wof:placetype":"venue"
},
  "geometry": {"coordinates":[149.162841797,-35.2485809326],"type":"Point"}
}