{
  "type": "Feature",
  "properties": {
    "addr:full":"PO Box 7275 Geelong West VIC 3218",
    "addr:postcode":"3218",
    "iso:country":"AU",
    "sg:address":"PO Box 7275",
    "sg:city":"Geelong West",
    "sg:classifiers":[
        {
            "category":"Industrial Area",
            "type":"Public Place"
        }
    ],
    "sg:phone":"+61 448 297 321",
    "sg:postcode":"3218",
    "sg:province":"VIC",
    "sg:tags":[
        "protective",
        "clothing"
    ],
    "wof:name":"Just Safety",
    "wof:placetype":"venue"
},
  "geometry": {"coordinates":[144.34837341299999,-38.1403617859],"type":"Point"}
}