{
  "type": "Feature",
  "properties": {
    "addr:full":"43 John St Singleton NSW 2330",
    "addr:housenumber":"43",
    "addr:postcode":"2330",
    "addr:street":"John St",
    "iso:country":"AU",
    "sg:address":"43 John St",
    "sg:city":"Singleton",
    "sg:classifiers":[
        {
            "category":"Retail",
            "subcategory":"Auto Repair",
            "type":"Services"
        }
    ],
    "sg:phone":"+61 2 6572 3755",
    "sg:postcode":"2330",
    "sg:province":"NSW",
    "sg:tags":[
        "repairer",
        "motor",
        "engineer"
    ],
    "wof:name":"Singleton Toyota",
    "wof:placetype":"venue"
},
  "geometry": {"coordinates":[151.16480999999999,-32.568256],"type":"Point"}
}