{
  "type": "Feature",
  "properties": {
    "addr:full":"12 Bunyarra Crt Greensborough VIC 3088",
    "addr:housenumber":"12",
    "addr:postcode":"3088",
    "addr:street":"Bunyarra Crt",
    "iso:country":"AU",
    "sg:address":"12 Bunyarra Crt",
    "sg:city":"Greensborough",
    "sg:classifiers":[
        {
            "category":"Real Estate",
            "subcategory":"Surveying",
            "type":"Services"
        }
    ],
    "sg:phone":"+61 3 9434 1895",
    "sg:postcode":"3088",
    "sg:province":"VIC",
    "sg:tags":[
        "surveyor",
        "land"
    ],
    "wof:name":"Loy M J",
    "wof:placetype":"venue"
},
  "geometry": {"coordinates":[145.10978698700001,-37.6922149658],"type":"Point"}
}