{
  "type": "Feature",
  "properties": {
    "iso:country":"AU",
    "sg:address":"PO Box 285",
    "sg:city":"Nedlands",
    "sg:classifiers":[
        {
            "category":"Recreation",
            "type":"Entertainment"
        }
    ],
    "sg:phone":"+61 8 9487 2548",
    "sg:postcode":"6009",
    "sg:province":"WA",
    "sg:tags":[
        "supply",
        "outdoor",
        "adventure",
        "activity"
    ],
    "wof:name":"Action Outdoors Association",
    "wof:placetype":"venue"
},
  "geometry": {"coordinates":[115.803146,-31.9792],"type":"Point"}
}