{
  "type": "Feature",
  "properties": {
    "addr:full":"222 Flinders St (East) Townsville QLD 4810",
    "addr:housenumber":"222",
    "addr:postcode":"4810",
    "addr:street":"Flinders St East",
    "iso:country":"AU",
    "sg:address":"222 Flinders St",
    "sg:city":"(East) Townsville",
    "sg:classifiers":[
        {
            "category":"Personal",
            "subcategory":"Beauty Salon",
            "type":"Services"
        }
    ],
    "sg:phone":"+61 7 4771 6659",
    "sg:postcode":"4810",
    "sg:province":"QLD",
    "wof:name":"Bellanova Skin & Make Up Studio",
    "wof:placetype":"venue"
},
  "geometry": {"coordinates":[146.81002799999999,-19.266493],"type":"Point"}
}