{
  "type": "Feature",
  "properties": {
    "iso:country":"AU",
    "sg:address":"National Water Sports Centre Riverend Rd",
    "sg:city":"Bangholme",
    "sg:classifiers":[
        {
            "category":"Farming",
            "subcategory":"Crops",
            "type":"Manufacturing & Wholesale Goods"
        }
    ],
    "sg:phone":"+61 3 9776 0413",
    "sg:postcode":"3175",
    "sg:province":"VIC",
    "sg:tags":[
        "club",
        "rowing"
    ],
    "wof:name":"Carrum Rowing Club",
    "wof:placetype":"venue"
},
  "geometry": {"coordinates":[145.14349365199999,-38.0377235413],"type":"Point"}
}