{
  "type": "Feature",
  "properties": {
    "iso:country":"AU",
    "sg:address":"Hewlett Rd",
    "sg:city":"Lenswood",
    "sg:classifiers":[
        {
            "category":"Farming",
            "subcategory":"Orchard",
            "type":"Manufacturing & Wholesale Goods"
        }
    ],
    "sg:phone":"+61 8 8389 8238",
    "sg:postcode":"5240",
    "sg:province":"SA",
    "sg:tags":[
        "pear",
        "apple",
        "grower"
    ],
    "wof:name":"Plummer I L & K L",
    "wof:placetype":"venue"
},
  "geometry": {"coordinates":[138.808197022,-34.9158973694],"type":"Point"}
}