{
  "type": "Feature",
  "properties": {
    "addr:full":"PO Box 101 Wodonga VIC 3689",
    "addr:postcode":"3689",
    "iso:country":"AU",
    "sg:address":"PO Box 101",
    "sg:city":"Wodonga",
    "sg:classifiers":[
        {
            "category":"Building & Trades",
            "subcategory":"Construction",
            "type":"Services"
        }
    ],
    "sg:phone":"+61 437 199 477",
    "sg:postcode":"3689",
    "sg:province":"VIC",
    "sg:tags":[
        "sun",
        "product",
        "protection"
    ],
    "wof:name":"Performance Tinting Services",
    "wof:placetype":"venue"
},
  "geometry": {"coordinates":[146.894363,-36.1138],"type":"Point"}
}