{
  "type": "Feature",
  "properties": {
    "addr:full":"303b Grey St Glen Innes NSW 2370",
    "addr:housenumber":"303b",
    "addr:postcode":"2370",
    "addr:street":"Grey St",
    "iso:country":"AU",
    "sg:address":"303b Grey St",
    "sg:city":"Glen Innes",
    "sg:classifiers":[
        {
            "category":"Retail",
            "subcategory":"Repair Shop",
            "type":"Services"
        }
    ],
    "sg:phone":"+61 2 6732 2172",
    "sg:postcode":"2370",
    "sg:province":"NSW",
    "sg:tags":[
        "upholsterer"
    ],
    "wof:name":"MJT Upholstery",
    "wof:placetype":"venue"
},
  "geometry": {"coordinates":[151.73617553700001,-29.7358264923],"type":"Point"}
}