{
  "type": "Feature",
  "properties": {
    "addr:full":"Shop 202 Greensborough Plaza Greensborough VIC 3088",
    "addr:housenumber":"202",
    "addr:postcode":"3088",
    "addr:street":"Greensborough Plaza",
    "iso:country":"AU",
    "sg:address":"Shop 202 Greensborough Plaza",
    "sg:city":"Greensborough",
    "sg:classifiers":[
        {
            "category":"Shopping",
            "subcategory":"Crafts & Fabrics",
            "type":"Retail Goods"
        }
    ],
    "sg:phone":"+61 3 9432 0655",
    "sg:postcode":"3088",
    "sg:province":"VIC",
    "sg:tags":[
        "supply"
    ],
    "wof:name":"Riot, Art & Craft",
    "wof:placetype":"venue"
},
  "geometry": {"coordinates":[145.10263061500001,-37.7043380737],"type":"Point"}
}