{
  "type": "Feature",
  "properties": {
    "iso:country":"AU",
    "sg:address":"62 High St",
    "sg:city":"Terang",
    "sg:classifiers":[
        {
            "category":"Fast Food",
            "type":"Food & Drink"
        }
    ],
    "sg:phone":"+61 3 5592 1226",
    "sg:postcode":"3264",
    "sg:province":"VIC",
    "sg:tags":[
        "away",
        "take"
    ],
    "wof:name":"Terang Court Cafe",
    "wof:placetype":"venue"
},
  "geometry": {"coordinates":[142.91741943400001,-38.2408752441],"type":"Point"}
}