{
  "type": "Feature",
  "properties": {
    "addr:full":"1953 Logan Rd Upper Mt Gravatt QLD 4122",
    "addr:housenumber":"1953",
    "addr:postcode":"4122",
    "addr:street":"Logan Rd Upper",
    "iso:country":"AU",
    "sg:address":"1953 Logan Rd",
    "sg:city":"Upper Mt Gravatt",
    "sg:classifiers":[
        {
            "category":"Banks & Credit Unions",
            "subcategory":"Financial Services",
            "type":"Services"
        }
    ],
    "sg:phone":"+61 7 3343 1411",
    "sg:postcode":"4122",
    "sg:province":"QLD",
    "sg:tags":[
        "financier"
    ],
    "wof:name":"GE Finance And Insurance",
    "wof:placetype":"venue"
},
  "geometry": {"coordinates":[153.080169678,-27.5582313538],"type":"Point"}
}