{
  "type": "Feature",
  "properties": {
    "addr:full":"Jersey Rd Emerton NSW 2770",
    "addr:postcode":"2770",
    "addr:street":"Jersey Rd",
    "iso:country":"AU",
    "sg:address":"Jersey Rd",
    "sg:city":"Emerton",
    "sg:classifiers":[
        {
            "category":"Personal",
            "subcategory":"Beauty Salon",
            "type":"Services"
        }
    ],
    "sg:phone":"+61 2 9628 0668",
    "sg:postcode":"2770",
    "sg:province":"NSW",
    "wof:name":"Mary K Beauty Salon",
    "wof:placetype":"venue"
},
  "geometry": {"coordinates":[150.80612182600001,-33.7428092957],"type":"Point"}
}