{
  "type": "Feature",
  "properties": {
    "addr:full":"Lot 14 Woomma Rd Virginia SA 5120",
    "addr:postcode":"5120",
    "addr:street":"Woomma Rd",
    "iso:country":"AU",
    "sg:address":"Lot 14 Woomma Rd",
    "sg:city":"Virginia",
    "sg:classifiers":[
        {
            "category":"Food & Beverages",
            "subcategory":"Fruits & Vegetables",
            "type":"Retail Goods"
        }
    ],
    "sg:phone":"+61 416 301 435",
    "sg:postcode":"5120",
    "sg:province":"SA",
    "sg:tags":[
        "wholesale"
    ],
    "wof:name":"Laftsis Fresh Produce",
    "wof:placetype":"venue"
},
  "geometry": {"coordinates":[138.560745239,-34.6561775208],"type":"Point"}
}