{
  "type": "Feature",
  "properties": {
    "iso:country":"AU",
    "sg:address":"49 Leyland St",
    "sg:city":"Garbutt",
    "sg:classifiers":[
        {
            "category":"Home & Garden",
            "subcategory":"Household Appliances",
            "type":"Retail Goods"
        }
    ],
    "sg:phone":"+61 7 4725 4733",
    "sg:postcode":"4814",
    "sg:province":"QLD",
    "sg:tags":[
        "chemical",
        "equipment",
        "steam",
        "cleaning",
        "pressure"
    ],
    "wof:name":"Pressure Cleaner & Small Engine Sales & Services Pty Ltd",
    "wof:placetype":"venue"
},
  "geometry": {"coordinates":[146.762817,-19.272137],"type":"Point"}
}