{
  "type": "Feature",
  "properties": {
    "addr:full":"45 Burnett St New Norfolk TAS 7140",
    "addr:housenumber":"45",
    "addr:postcode":"7140",
    "addr:street":"Burnett St",
    "iso:country":"AU",
    "sg:address":"45 Burnett St",
    "sg:city":"New Norfolk",
    "sg:classifiers":[
        {
            "category":"Shopping",
            "subcategory":"Antiques",
            "type":"Retail Goods"
        }
    ],
    "sg:phone":"+61 3 6261 5416",
    "sg:postcode":"7140",
    "sg:province":"TAS",
    "wof:name":"Old Maypole Collectables & Antiques",
    "wof:placetype":"venue"
},
  "geometry": {"coordinates":[147.062454,-42.78175],"type":"Point"}
}