{
  "type": "Feature",
  "properties": {
    "iso:country":"AU",
    "sg:address":"13 Allpike Rd",
    "sg:city":"Darlington",
    "sg:classifiers":[
        {
            "category":"Shopping",
            "subcategory":"Musical Instruments",
            "type":"Retail Goods"
        }
    ],
    "sg:phone":"+61 8 9299 6817",
    "sg:postcode":"6070",
    "sg:province":"WA",
    "sg:tags":[
        "musician",
        "agent"
    ],
    "wof:name":"Classical Barz",
    "wof:placetype":"venue"
},
  "geometry": {"coordinates":[116.085510254,-31.9274101257],"type":"Point"}
}