{
  "type": "Feature",
  "properties": {
    "addr:full":"1717 Beaudesert Rd Acacia Ridge QLD 4110",
    "addr:postcode":"1717;4110",
    "addr:street":"Beaudesert Rd",
    "iso:country":"AU",
    "sg:address":"1717 Beaudesert Rd",
    "sg:city":"Acacia Ridge",
    "sg:classifiers":[
        {
            "category":"Retail",
            "subcategory":"Storage",
            "type":"Services"
        }
    ],
    "sg:phone":"+61 7 3272 2333",
    "sg:postcode":"4110",
    "sg:province":"QLD",
    "wof:name":"Acacia Self Storage",
    "wof:placetype":"venue"
},
  "geometry": {"coordinates":[153.03814697300001,-27.5975494385],"type":"Point"}
}