{
  "type": "Feature",
  "properties": {
    "addr:full":"16 Marriott St Oakleigh VIC 3166",
    "addr:housenumber":"16",
    "addr:postcode":"3166",
    "addr:street":"Marriott St",
    "iso:country":"AU",
    "sg:address":"16 Marriott St",
    "sg:city":"Oakleigh",
    "sg:classifiers":[
        {
            "category":"Autos & Motor Vehicles",
            "subcategory":"Auto Supplies",
            "type":"Retail Goods"
        }
    ],
    "sg:phone":"+61 3 9568 7455",
    "sg:postcode":"3166",
    "sg:province":"VIC",
    "sg:tags":[
        "tyre"
    ],
    "wof:name":"Cobbas Tyres & Servicing",
    "wof:placetype":"venue"
},
  "geometry": {"coordinates":[145.09715270999999,-37.8945846558],"type":"Point"}
}