{
  "type": "Feature",
  "properties": {
    "iso:country":"AU",
    "sg:address":"28 Howards Rd",
    "sg:city":"Baranduda",
    "sg:classifiers":[
        {
            "category":"Freight",
            "type":"Transportation"
        }
    ],
    "sg:phone":"+61 2 6020 8481",
    "sg:postcode":"3691",
    "sg:province":"VIC",
    "sg:tags":[
        "car",
        "carrier",
        "transporting"
    ],
    "wof:name":"Albury Wodonga Car Carriers",
    "wof:placetype":"venue"
},
  "geometry": {"coordinates":[146.943604,-36.185905],"type":"Point"}
}