{
  "type": "Feature",
  "properties": {
    "addr:full":"2036 Logan Rd Upper Mt Gravatt QLD 4122",
    "addr:housenumber":"2036",
    "addr:postcode":"4122",
    "addr:street":"Logan Rd Upper",
    "iso:country":"AU",
    "sg:address":"2036 Logan Rd",
    "sg:city":"Upper Mt Gravatt",
    "sg:classifiers":[
        {
            "category":"Insurance",
            "subcategory":"Insurance Agent",
            "type":"Services"
        }
    ],
    "sg:phone":"+61 7 3849 5588",
    "sg:postcode":"4122",
    "sg:province":"QLD",
    "wof:name":"Carter Financial Group",
    "wof:placetype":"venue"
},
  "geometry": {"coordinates":[153.08108520499999,-27.5592918396],"type":"Point"}
}