{
  "type": "Feature",
  "properties": {
    "addr:full":"63 George St Launceston TAS 7250",
    "addr:housenumber":"63",
    "addr:postcode":"7250",
    "addr:street":"George St",
    "iso:country":"AU",
    "sg:address":"63 George St",
    "sg:city":"Launceston",
    "sg:classifiers":[
        {
            "category":"Restaurant",
            "type":"Food & Drink"
        }
    ],
    "sg:phone":"+61 3 6331 6244",
    "sg:postcode":"7250",
    "sg:province":"TAS",
    "wof:name":"La Cantina Restaurant",
    "wof:placetype":"venue"
},
  "geometry": {"coordinates":[147.13999939000001,-41.4354553223],"type":"Point"}
}