{
  "type": "Feature",
  "properties": {
    "iso:country":"AU",
    "sg:address":"Shop 4, Parkway Medical Centr 100 Cheltenham Drv",
    "sg:city":"Robina",
    "sg:classifiers":[
        {
            "category":"Health Services",
            "subcategory":"Doctor",
            "type":"Services"
        }
    ],
    "sg:phone":"+61 7 5526 1090",
    "sg:postcode":"4226",
    "sg:province":"QLD",
    "sg:tags":[
        "medical",
        "practitioner"
    ],
    "wof:name":"The Clinic Of Medical Skin Technology",
    "wof:placetype":"venue"
},
  "geometry": {"coordinates":[153.39471435600001,-28.0681438446],"type":"Point"}
}