{
  "type": "Feature",
  "properties": {
    "iso:country":"AU",
    "sg:address":"71a Lofven St",
    "sg:city":"Nerrina",
    "sg:classifiers":[
        {
            "category":"Building & Trades",
            "subcategory":"Cleaning & Sanitation",
            "type":"Services"
        }
    ],
    "sg:phone":"+61 3 5331 2577",
    "sg:postcode":"3350",
    "sg:province":"VIC",
    "sg:tags":[
        "window"
    ],
    "wof:name":"Steffen P.& C.",
    "wof:placetype":"venue"
},
  "geometry": {"coordinates":[143.88838200000001,-37.545921],"type":"Point"}
}