{
  "type": "Feature",
  "properties": {
    "addr:full":"Suite 7 904 Stanley St East Brisbane QLD 4169",
    "addr:housenumber":"904",
    "addr:postcode":"4169",
    "addr:street":"Stanley St",
    "iso:country":"AU",
    "sg:address":"Suite 7 904 Stanley St",
    "sg:city":"East Brisbane",
    "sg:classifiers":[
        {
            "category":"Professional",
            "subcategory":"Employment Agencies",
            "type":"Services"
        }
    ],
    "sg:phone":"+61 7 3391 2599",
    "sg:postcode":"4169",
    "sg:province":"QLD",
    "wof:name":"Chefs On The Run Australia Pty Ltd",
    "wof:placetype":"venue"
},
  "geometry": {"coordinates":[153.04202270499999,-27.4875679016],"type":"Point"}
}