{
  "type": "Feature",
  "properties": {
    "addr:full":"186 Glynburn Rd Tranmere SA 5073",
    "addr:housenumber":"186",
    "addr:postcode":"5073",
    "addr:street":"Glynburn Rd",
    "iso:country":"AU",
    "sg:address":"186 Glynburn Rd",
    "sg:city":"Tranmere",
    "sg:classifiers":[
        {
            "category":"Health Services",
            "subcategory":"Health Practitioner",
            "type":"Services"
        }
    ],
    "sg:phone":"+61 8 8364 5088",
    "sg:postcode":"5073",
    "sg:province":"SA",
    "sg:tags":[
        "physiotherapist"
    ],
    "wof:name":"Custance Karen",
    "wof:placetype":"venue"
},
  "geometry": {"coordinates":[138.65769958499999,-34.9032669067],"type":"Point"}
}