{
  "type": "Feature",
  "properties": {
    "addr:full":"4/274 - 276 Hoxton Park Rd Prestons NSW 2170",
    "addr:housenumber":"/ 274 276",
    "addr:postcode":"2170",
    "addr:street":"Hoxton Park Rd",
    "iso:country":"AU",
    "sg:address":"4/274 - 276 Hoxton Park Rd",
    "sg:city":"Prestons",
    "sg:classifiers":[
        {
            "category":"Utilities",
            "subcategory":"Recycling",
            "type":"Services"
        }
    ],
    "sg:phone":"+61 2 9825 0876",
    "sg:postcode":"2170",
    "sg:province":"NSW",
    "sg:website":"http://www.aprecycling.com",
    "wof:name":"All Product Recycling",
    "wof:placetype":"venue"
},
  "geometry": {"coordinates":[150.88473510700001,-33.9279289246],"type":"Point"}
}