{
  "type": "Feature",
  "properties": {
    "addr:full":"13 Matlock St Preston VIC 3072",
    "addr:housenumber":"13",
    "addr:postcode":"3072",
    "addr:street":"Matlock St",
    "iso:country":"AU",
    "sg:address":"13 Matlock St",
    "sg:city":"Preston",
    "sg:classifiers":[
        {
            "category":"Professional",
            "subcategory":"Art Services",
            "type":"Services"
        }
    ],
    "sg:phone":"+61 418 518 673",
    "sg:postcode":"3072",
    "sg:province":"VIC",
    "sg:tags":[
        "decorator",
        "painter"
    ],
    "wof:name":"A.J. Brennan & Son",
    "wof:placetype":"venue"
},
  "geometry": {"coordinates":[144.986602783,-37.745262146],"type":"Point"}
}