{
  "type": "Feature",
  "properties": {
    "addr:full":"Suite 4/ Level 1/ 111 Phillip St Parramatta NSW 2150",
    "addr:housenumber":"/ 111",
    "addr:postcode":"2150",
    "addr:street":"Phillip St",
    "iso:country":"AU",
    "sg:address":"Suite 4/ Level 1/ 111 Phillip St",
    "sg:city":"Parramatta",
    "sg:classifiers":[
        {
            "category":"Professional",
            "subcategory":"Computer Services",
            "type":"Services"
        }
    ],
    "sg:phone":"+61 2 9891 6346",
    "sg:postcode":"2150",
    "sg:province":"NSW",
    "sg:tags":[
        "package",
        "software"
    ],
    "wof:name":"Mobtec",
    "wof:placetype":"venue"
},
  "geometry": {"coordinates":[151.02232360799999,-33.8353843689],"type":"Point"}
}