{
  "type": "Feature",
  "properties": {
    "addr:full":"8/ 158 High St Fremantle WA 6160",
    "addr:housenumber":"/ 158",
    "addr:postcode":"6160",
    "addr:street":"High St",
    "iso:country":"AU",
    "sg:address":"8/ 158 High St",
    "sg:city":"Fremantle",
    "sg:classifiers":[
        {
            "category":"Health Services",
            "subcategory":"Health Practitioner",
            "type":"Services"
        }
    ],
    "sg:phone":"+61 8 9335 3111",
    "sg:postcode":"6160",
    "sg:province":"WA",
    "sg:tags":[
        "naturopath"
    ],
    "wof:name":"Chinawest",
    "wof:placetype":"venue"
},
  "geometry": {"coordinates":[115.75264,-32.05241],"type":"Point"}
}