{
  "type": "Feature",
  "properties": {
    "iso:country":"AU",
    "sg:address":"137 William St (Cnr William & Wellington Sts)",
    "sg:city":"Perth",
    "sg:classifiers":[
        {
            "category":"Personal",
            "subcategory":"Beauty Salon",
            "type":"Services"
        }
    ],
    "sg:phone":"+61 8 9321 7797",
    "sg:postcode":"6000",
    "sg:province":"WA",
    "sg:tags":[
        "hairdresser"
    ],
    "wof:name":"Hall & Jones Hair Shop",
    "wof:placetype":"venue"
},
  "geometry": {"coordinates":[115.856811523,-31.9536781311],"type":"Point"}
}