{
  "type": "Feature",
  "properties": {
    "iso:country":"AU",
    "sg:address":"54 Francis Rd",
    "sg:city":"Wingfield",
    "sg:classifiers":[
        {
            "category":"Professional",
            "type":"Services"
        }
    ],
    "sg:phone":"+61 8 8268 2688",
    "sg:postcode":"5013",
    "sg:province":"SA",
    "sg:tags":[
        "coating",
        "powder"
    ],
    "wof:name":"Controlled Powder Coating",
    "wof:placetype":"venue"
},
  "geometry": {"coordinates":[138.546707153,-34.8458442688],"type":"Point"}
}