{
  "type": "Feature",
  "properties": {
    "iso:country":"AU",
    "sg:address":"12 Station St",
    "sg:city":"Nunawading",
    "sg:classifiers":[
        {
            "category":"Professional",
            "subcategory":"Accounting & Tax Preparation",
            "type":"Services"
        }
    ],
    "sg:phone":"+61 3 9878 2400",
    "sg:postcode":"3131",
    "sg:province":"VIC",
    "sg:tags":[
        "accountant",
        "auditor"
    ],
    "wof:name":"De Sensi & Associates",
    "wof:placetype":"venue"
},
  "geometry": {"coordinates":[145.17601013199999,-37.8207397461],"type":"Point"}
}