{
  "type": "Feature",
  "properties": {
    "iso:country":"AU",
    "sg:address":"63 Wilgarning St",
    "sg:city":"Stafford Heights",
    "sg:classifiers":[
        {
            "category":"Personal",
            "subcategory":"Beauty Salon",
            "type":"Services"
        }
    ],
    "sg:phone":"+61 7 3350 6596",
    "sg:postcode":"4053",
    "sg:province":"QLD",
    "sg:tags":[
        "hairdresser"
    ],
    "wof:name":"MOHR hairmakeupbeauty",
    "wof:placetype":"venue"
},
  "geometry": {"coordinates":[153.01521301299999,-27.4018306732],"type":"Point"}
}