{
  "type": "Feature",
  "properties": {
    "iso:country":"AU",
    "sg:address":"3 Keel Crt",
    "sg:city":"Caboolture",
    "sg:classifiers":[
        {
            "category":"Shopping",
            "subcategory":"Mobile Phones",
            "type":"Retail Goods"
        }
    ],
    "sg:phone":"+61 7 5495 5754",
    "sg:postcode":"4510",
    "sg:province":"QLD",
    "sg:tags":[
        "telephone",
        "accessory"
    ],
    "wof:name":"Walkabout Communications Pty Ltd",
    "wof:placetype":"venue"
},
  "geometry": {"coordinates":[152.935928,-27.09042],"type":"Point"}
}