{
  "type": "Feature",
  "properties": {
    "addr:full":"23 Hardy St Dover Heights NSW 2030",
    "addr:housenumber":"23",
    "addr:postcode":"2030",
    "addr:street":"Hardy St Dover",
    "iso:country":"AU",
    "sg:address":"23 Hardy St",
    "sg:city":"Dover Heights",
    "sg:classifiers":[
        {
            "category":"Travel",
            "subcategory":"Travel Agent",
            "type":"Entertainment"
        }
    ],
    "sg:phone":"+61 2 9388 1471",
    "sg:postcode":"2030",
    "sg:province":"NSW",
    "sg:tags":[
        "consultant"
    ],
    "wof:name":"V. Olian Travel",
    "wof:placetype":"venue"
},
  "geometry": {"coordinates":[151.27746582,-33.879699707],"type":"Point"}
}