{
  "type": "Feature",
  "properties": {
    "iso:country":"AU",
    "sg:address":"Shp 9/ 190 William St",
    "sg:city":"Beckenham",
    "sg:classifiers":[
        {
            "category":"Food & Beverages",
            "subcategory":"Meat & Fish",
            "type":"Retail Goods"
        }
    ],
    "sg:phone":"+61 8 9451 4003",
    "sg:postcode":"6107",
    "sg:province":"WA",
    "sg:tags":[
        "seafood"
    ],
    "wof:name":"Beckenham Fish & Chips",
    "wof:placetype":"venue"
},
  "geometry": {"coordinates":[115.96499633800001,-32.0140609741],"type":"Point"}
}