{
  "type": "Feature",
  "properties": {
    "addr:full":"8 Melville St Parramatta NSW 2150",
    "addr:housenumber":"8",
    "addr:postcode":"2150",
    "addr:street":"Melville St",
    "iso:country":"AU",
    "sg:address":"8 Melville St",
    "sg:city":"Parramatta",
    "sg:classifiers":[
        {
            "category":"Professional",
            "type":"Services"
        }
    ],
    "sg:phone":"+61 2 9683 5144",
    "sg:postcode":"2150",
    "sg:province":"NSW",
    "sg:tags":[
        "message",
        "answering",
        "telephone"
    ],
    "wof:name":"Macarthur House",
    "wof:placetype":"venue"
},
  "geometry": {"coordinates":[151.09898376500001,-33.8074378967],"type":"Point"}
}