{
  "type": "Feature",
  "properties": {
    "addr:full":"3 McEvoy St Kew VIC 3101",
    "addr:housenumber":"3",
    "addr:postcode":"3101",
    "addr:street":"Mcevoy St",
    "iso:country":"AU",
    "sg:address":"3 McEvoy St",
    "sg:city":"Kew",
    "sg:classifiers":[
        {
            "category":"Professional",
            "subcategory":"Accounting & Tax Preparation",
            "type":"Services"
        }
    ],
    "sg:phone":"+61 3 9853 4248",
    "sg:postcode":"3101",
    "sg:province":"VIC",
    "sg:tags":[
        "bookkeeping"
    ],
    "wof:name":"Business Management Solutions",
    "wof:placetype":"venue"
},
  "geometry": {"coordinates":[145.011276245,-37.8064689636],"type":"Point"}
}