{
  "type": "Feature",
  "properties": {
    "iso:country":"AU",
    "sg:address":"26 Tallean Rd",
    "sg:city":"Nelson Bay",
    "sg:classifiers":[
        {
            "category":"Real Estate",
            "subcategory":"Real Estate Agent",
            "type":"Services"
        }
    ],
    "sg:phone":"+61 412 235 398",
    "sg:postcode":"2315",
    "sg:province":"NSW",
    "wof:name":"Hunter Lloyd",
    "wof:placetype":"venue"
},
  "geometry": {"coordinates":[152.14027400000001,-32.726414],"type":"Point"}
}