{
  "type": "Feature",
  "properties": {
    "iso:country":"AU",
    "sg:address":"Unit 5/ 41 Boyland Ave",
    "sg:city":"Coopers Plains",
    "sg:classifiers":[
        {
            "category":"Shopping",
            "subcategory":"Crafts & Fabrics",
            "type":"Retail Goods"
        }
    ],
    "sg:phone":"+61 7 3274 5577",
    "sg:postcode":"4108",
    "sg:province":"QLD",
    "sg:tags":[
        "florist",
        "supply"
    ],
    "wof:name":"Apack Pty Ltd",
    "wof:placetype":"venue"
},
  "geometry": {"coordinates":[153.02772522000001,-27.5678787231],"type":"Point"}
}