{
  "type": "Feature",
  "properties": {
    "addr:full":"202 Carlisle St Balaclava VIC 3183",
    "addr:housenumber":"202",
    "addr:postcode":"3183",
    "addr:street":"Carlisle St",
    "iso:country":"AU",
    "sg:address":"202 Carlisle St",
    "sg:city":"Balaclava",
    "sg:classifiers":[
        {
            "category":"Health Services",
            "subcategory":"Dentist",
            "type":"Services"
        }
    ],
    "sg:phone":"+61 3 9534 6414",
    "sg:postcode":"3183",
    "sg:province":"VIC",
    "wof:name":"Kokorev Alexander Dr",
    "wof:placetype":"venue"
},
  "geometry": {"coordinates":[144.99087524399999,-37.868270874],"type":"Point"}
}