{
  "type": "Feature",
  "properties": {
    "addr:full":"627 Riversdale Rd Camberwell VIC 3124",
    "addr:housenumber":"627",
    "addr:postcode":"3124",
    "addr:street":"Riversdale Rd",
    "iso:country":"AU",
    "sg:address":"627 Riversdale Rd",
    "sg:city":"Camberwell",
    "sg:classifiers":[
        {
            "category":"Professional",
            "subcategory":"Management & Consulting",
            "type":"Services"
        }
    ],
    "sg:phone":"+61 3 9882 0875",
    "sg:postcode":"3124",
    "sg:province":"VIC",
    "sg:tags":[
        "consultant"
    ],
    "wof:name":"Garside Consulting",
    "wof:placetype":"venue"
},
  "geometry": {"coordinates":[145.06687927199999,-37.8323554993],"type":"Point"}
}