{
  "type": "Feature",
  "properties": {
    "iso:country":"AU",
    "sg:address":"5 Lookover Rd",
    "sg:city":"Donvale",
    "sg:classifiers":[
        {
            "category":"Home & Garden",
            "subcategory":"Carpets & Floor Coverings",
            "type":"Retail Goods"
        }
    ],
    "sg:phone":"+61 419 326 076",
    "sg:postcode":"3111",
    "sg:province":"VIC",
    "sg:tags":[
        "tile",
        "wall",
        "layer"
    ],
    "wof:name":"R.J.A. Ceramics",
    "wof:placetype":"venue"
},
  "geometry": {"coordinates":[145.208816528,-37.7950820923],"type":"Point"}
}