{
  "type": "Feature",
  "properties": {
    "addr:full":"Suite 7, 230 Church St Richmond VIC 3121",
    "addr:housenumber":"230",
    "addr:postcode":"3121",
    "addr:street":"Church St",
    "iso:country":"AU",
    "sg:address":"Suite 7, 230 Church St",
    "sg:city":"Richmond",
    "sg:classifiers":[
        {
            "category":"Professional",
            "subcategory":"Management & Consulting",
            "type":"Services"
        }
    ],
    "sg:phone":"+61 3 9428 1198",
    "sg:postcode":"3121",
    "sg:province":"VIC",
    "sg:tags":[
        "consultant",
        "migration"
    ],
    "wof:name":"Aussie World Information Services",
    "wof:placetype":"venue"
},
  "geometry": {"coordinates":[144.99908447300001,-37.8181152344],"type":"Point"}
}