{
  "type": "Feature",
  "properties": {
    "addr:full":"231 Bourke St Melbourne VIC 3000",
    "addr:housenumber":"231",
    "addr:postcode":"3000",
    "addr:street":"Bourke St",
    "iso:country":"AU",
    "sg:address":"231 Bourke St",
    "sg:city":"Melbourne",
    "sg:classifiers":[
        {
            "category":"Shopping",
            "subcategory":"Clothing, Apparel, & Fashions",
            "type":"Retail Goods"
        }
    ],
    "sg:phone":"+61 3 9650 3183",
    "sg:postcode":"3000",
    "sg:province":"VIC",
    "sg:tags":[
        "menswear"
    ],
    "wof:name":"Anthony Thomas Menswear",
    "wof:placetype":"venue"
},
  "geometry": {"coordinates":[144.96678161599999,-37.8133125305],"type":"Point"}
}