{
  "type": "Feature",
  "properties": {
    "addr:full":"9 Gregory St Granville NSW 2142",
    "addr:housenumber":"9",
    "addr:postcode":"2142",
    "addr:street":"Gregory St",
    "iso:country":"AU",
    "sg:address":"9 Gregory St",
    "sg:city":"Granville",
    "sg:classifiers":[
        {
            "category":"Professional",
            "subcategory":"Employment Agencies",
            "type":"Services"
        }
    ],
    "sg:phone":"+61 2 9897 0597",
    "sg:postcode":"2142",
    "sg:province":"NSW",
    "sg:tags":[
        "hire",
        "labour",
        "contractor"
    ],
    "wof:name":"Vee Dee Associates Private Pty Ltd",
    "wof:placetype":"venue"
},
  "geometry": {"coordinates":[151.008468628,-33.8429527283],"type":"Point"}
}