{
  "type": "Feature",
  "properties": {
    "iso:country":"AU",
    "sg:address":"26 Beveridge St",
    "sg:city":"Swan Hill",
    "sg:classifiers":[
        {
            "category":"Professional",
            "subcategory":"Engineering",
            "type":"Services"
        }
    ],
    "sg:phone":"+61 3 5032 9147",
    "sg:postcode":"3585",
    "sg:province":"VIC",
    "sg:tags":[
        "engineer",
        "structural"
    ],
    "wof:name":"F.C.H. Consulting Pty Ltd",
    "wof:placetype":"venue"
},
  "geometry": {"coordinates":[143.55722,-35.336494],"type":"Point"}
}