{
  "type": "Feature",
  "properties": {
    "addr:full":"116 Military Rd Neutral Bay NSW 2089",
    "addr:housenumber":"116",
    "addr:postcode":"2089",
    "addr:street":"Military Rd",
    "iso:country":"AU",
    "sg:address":"116 Military Rd",
    "sg:city":"Neutral Bay",
    "sg:classifiers":[
        {
            "category":"Banks & Credit Unions",
            "subcategory":"Investment Brokerage",
            "type":"Services"
        }
    ],
    "sg:phone":"+61 2 9968 5850",
    "sg:postcode":"2089",
    "sg:province":"NSW",
    "wof:name":"InvestmentLink Ltd",
    "wof:placetype":"venue"
},
  "geometry": {"coordinates":[151.219314575,-33.830242157],"type":"Point"}
}