{
  "type": "Feature",
  "properties": {
    "addr:full":"U3/ 10 Immo St Essendon VIC 3040",
    "addr:postcode":"3040",
    "addr:street":"U3 /;Immo St",
    "iso:country":"AU",
    "sg:address":"U3/ 10 Immo St",
    "sg:city":"Essendon",
    "sg:classifiers":[
        {
            "category":"Building & Trades",
            "subcategory":"Landscaping Services",
            "type":"Services"
        }
    ],
    "sg:phone":"+61 414 364 194",
    "sg:postcode":"3040",
    "sg:province":"VIC",
    "sg:tags":[
        "gardener"
    ],
    "wof:name":"Adam Beck's Landscaping & Lawn Care",
    "wof:placetype":"venue"
},
  "geometry": {"coordinates":[144.89550781200001,-37.7537536621],"type":"Point"}
}