{
  "type": "Feature",
  "properties": {
    "iso:country":"AU",
    "sg:address":"20 Rooke St",
    "sg:city":"Devonport",
    "sg:classifiers":[
        {
            "category":"Banks & Credit Unions",
            "subcategory":"Financial Services",
            "type":"Services"
        }
    ],
    "sg:phone":"+61 3 6424 1172",
    "sg:postcode":"7310",
    "sg:province":"TAS",
    "sg:tags":[
        "planning"
    ],
    "wof:name":"Alan Pattison",
    "wof:placetype":"venue"
},
  "geometry": {"coordinates":[146.360595703,-41.1806716919],"type":"Point"}
}