{
  "type": "Feature",
  "properties": {
    "addr:full":"6 Dygal St Mona Vale NSW 2103",
    "addr:housenumber":"6",
    "addr:postcode":"2103",
    "addr:street":"Dygal St",
    "iso:country":"AU",
    "sg:address":"6 Dygal St",
    "sg:city":"Mona Vale",
    "sg:classifiers":[
        {
            "category":"Building & Trades",
            "subcategory":"Equipment Rental",
            "type":"Services"
        }
    ],
    "sg:phone":"+61 2 9997 5193",
    "sg:postcode":"2103",
    "sg:province":"NSW",
    "sg:tags":[
        "demolition",
        "contractor"
    ],
    "wof:name":"Harrys Earthmoving",
    "wof:placetype":"venue"
},
  "geometry": {"coordinates":[151.30052185100001,-33.6748962402],"type":"Point"}
}