{
  "type": "Feature",
  "properties": {
    "iso:country":"AU",
    "sg:address":"59 Train St",
    "sg:city":"Broulee",
    "sg:classifiers":[
        {
            "category":"Education",
            "subcategory":"Kindergarten",
            "type":"Public Place"
        }
    ],
    "sg:phone":"+61 2 4471 5133",
    "sg:postcode":"2537",
    "sg:province":"NSW",
    "sg:tags":[
        "pre-schools"
    ],
    "wof:name":"Broulee Long Day Care Centre",
    "wof:placetype":"venue"
},
  "geometry": {"coordinates":[150.16830444300001,-35.8436126709],"type":"Point"}
}