{
  "type": "Feature",
  "properties": {
    "addr:full":"68 Megalong St Katoomba NSW 2780",
    "addr:housenumber":"68",
    "addr:postcode":"2780",
    "addr:street":"Megalong St",
    "iso:country":"AU",
    "sg:address":"68 Megalong St",
    "sg:city":"Katoomba",
    "sg:classifiers":[
        {
            "category":"Travel",
            "subcategory":"Travel Agent",
            "type":"Entertainment"
        }
    ],
    "sg:phone":"+61 2 4782 3333",
    "sg:postcode":"2780",
    "sg:province":"NSW",
    "sg:tags":[
        "tour",
        "holiday",
        "adventure"
    ],
    "wof:name":"Blue Mountains Trolley Tours",
    "wof:placetype":"venue"
},
  "geometry": {"coordinates":[150.32229614299999,-33.7129745483],"type":"Point"}
}