{
  "type": "Feature",
  "properties": {
    "addr:full":"Cedars St Mossman QLD 4873",
    "addr:postcode":"4873",
    "addr:street":"Cedars St",
    "iso:country":"AU",
    "sg:address":"Cedars St",
    "sg:city":"Mossman",
    "sg:classifiers":[
        {
            "category":"Farming",
            "subcategory":"Farm",
            "type":"Manufacturing & Wholesale Goods"
        }
    ],
    "sg:phone":"+61 7 4098 1155",
    "sg:postcode":"4873",
    "sg:province":"QLD",
    "sg:tags":[
        "farmer"
    ],
    "wof:name":"Raldini A A & A",
    "wof:placetype":"venue"
},
  "geometry": {"coordinates":[145.447357178,-16.2271156311],"type":"Point"}
}