{
  "type": "Feature",
  "properties": {
    "iso:country":"AU",
    "sg:address":"Tapping Crs",
    "sg:city":"North Haven",
    "sg:classifiers":[
        {
            "category":"Education",
            "subcategory":"School",
            "type":"Public Place"
        }
    ],
    "sg:phone":"+61 8 8248 3011",
    "sg:postcode":"5018",
    "sg:province":"SA",
    "sg:tags":[
        "state",
        "except",
        "nsw"
    ],
    "wof:name":"North Haven Schools",
    "wof:placetype":"venue"
},
  "geometry": {"coordinates":[138.49134826700001,-34.7935714722],"type":"Point"}
}