{
  "type": "Feature",
  "properties": {
    "addr:full":"3/ 130 Imlay St Eden NSW 2551",
    "addr:housenumber":"/ 130",
    "addr:postcode":"2551",
    "addr:street":"Imlay St",
    "iso:country":"AU",
    "sg:address":"3/ 130 Imlay St",
    "sg:city":"Eden",
    "sg:classifiers":[
        {
            "category":"Health Services",
            "subcategory":"Dentist",
            "type":"Services"
        }
    ],
    "sg:phone":"+61 2 6496 4222",
    "sg:postcode":"2551",
    "sg:province":"NSW",
    "wof:name":"Maratheftis Gabriel Dr",
    "wof:placetype":"venue"
},
  "geometry": {"coordinates":[149.91131591800001,-37.0728340149],"type":"Point"}
}