{
  "type": "Feature",
  "properties": {
    "iso:country":"AU",
    "sg:address":"10 William St",
    "sg:city":"Adamstown",
    "sg:classifiers":[
        {
            "category":"Professional",
            "type":"Services"
        }
    ],
    "sg:phone":"+61 2 4957 2732",
    "sg:postcode":"2289",
    "sg:province":"NSW",
    "sg:tags":[
        "transport"
    ],
    "wof:name":"United Transport Services",
    "wof:placetype":"venue"
},
  "geometry": {"coordinates":[151.71861267099999,-32.9394645691],"type":"Point"}
}