{
  "type": "Feature",
  "properties": {
    "addr:full":"7 Main St Beenleigh QLD 4207",
    "addr:housenumber":"7",
    "addr:postcode":"4207",
    "addr:street":"Main St",
    "iso:country":"AU",
    "sg:address":"7 Main St",
    "sg:city":"Beenleigh",
    "sg:classifiers":[
        {
            "category":"Personal",
            "subcategory":"Beauty Salon",
            "type":"Services"
        }
    ],
    "sg:phone":"+61 7 3287 4655",
    "sg:postcode":"4207",
    "sg:province":"QLD",
    "sg:tags":[
        "hairdresser"
    ],
    "wof:name":"Spectrum New Image Hair & Beauty Studio",
    "wof:placetype":"venue"
},
  "geometry": {"coordinates":[153.20245361299999,-27.716501236],"type":"Point"}
}