{
  "type": "Feature",
  "properties": {
    "addr:full":"Shp4/ 3 Clifford St Suffolk Park NSW 2481",
    "addr:housenumber":"3",
    "addr:postcode":"2481",
    "addr:street":"Clifford St",
    "iso:country":"AU",
    "sg:address":"Shp4/ 3 Clifford St",
    "sg:city":"Suffolk Park",
    "sg:classifiers":[
        {
            "category":"Food & Beverages",
            "subcategory":"Supermarket",
            "type":"Retail Goods"
        }
    ],
    "sg:phone":"+61 2 6685 9604",
    "sg:postcode":"2481",
    "sg:province":"NSW",
    "sg:tags":[
        "grocery",
        "store"
    ],
    "wof:name":"5 Star Handi Market",
    "wof:placetype":"venue"
},
  "geometry": {"coordinates":[153.61167907699999,-28.6901683807],"type":"Point"}
}