{
  "type": "Feature",
  "properties": {
    "addr:full":"1 Blaxland Crs Vincent QLD 4814",
    "addr:housenumber":"1",
    "addr:postcode":"4814",
    "addr:street":"Blaxland Crs Vincent",
    "iso:country":"AU",
    "sg:address":"1 Blaxland Crs",
    "sg:city":"Vincent",
    "sg:classifiers":[
        {
            "category":"Shopping",
            "subcategory":"Computers & Home Electronics",
            "type":"Retail Goods"
        }
    ],
    "sg:phone":"+61 414 882 459",
    "sg:postcode":"4814",
    "sg:province":"QLD",
    "sg:tags":[
        "cleaning"
    ],
    "wof:name":"Complete Computer Repairs",
    "wof:placetype":"venue"
},
  "geometry": {"coordinates":[146.76797500000001,-19.28476],"type":"Point"}
}