{
  "type": "Feature",
  "properties": {
    "iso:country":"AU",
    "sg:address":"Corbett Ave",
    "sg:city":"Buronga",
    "sg:classifiers":[
        {
            "category":"Industrial Area",
            "type":"Public Place"
        }
    ],
    "sg:phone":"+61 3 5021 3536",
    "sg:postcode":"2739",
    "sg:province":"VIC",
    "sg:tags":[
        "rural",
        "shed"
    ],
    "wof:name":"APK Engineering Pty Ltd",
    "wof:placetype":"venue"
},
  "geometry": {"coordinates":[142.186188,-34.160191],"type":"Point"}
}