{
  "type": "Feature",
  "properties": {
    "addr:full":"Shop 93 Midland Gate Shopping Centre Midland WA 6056",
    "addr:housenumber":"shop 93",
    "addr:postcode":"6056",
    "addr:street":"Midland Gate",
    "iso:country":"AU",
    "sg:address":"Shop 93 Midland Gate Shopping Centre",
    "sg:city":"Midland",
    "sg:classifiers":[
        {
            "category":"Shopping",
            "subcategory":"Clothing, Apparel, & Fashions",
            "type":"Retail Goods"
        }
    ],
    "sg:phone":"+61 8 9274 8282",
    "sg:postcode":"6056",
    "sg:province":"WA",
    "sg:tags":[
        "lady",
        "wear"
    ],
    "wof:name":"Chantique Fashion & Accessories",
    "wof:placetype":"venue"
},
  "geometry": {"coordinates":[116.009643555,-31.8911304474],"type":"Point"}
}