{
  "type": "Feature",
  "properties": {
    "addr:full":"10 Vaughan St Paynesville VIC 3880",
    "addr:housenumber":"10",
    "addr:postcode":"3880",
    "addr:street":"Vaughan St",
    "iso:country":"AU",
    "sg:address":"10 Vaughan St",
    "sg:city":"Paynesville",
    "sg:classifiers":[
        {
            "category":"Building & Trades",
            "subcategory":"Construction",
            "type":"Services"
        }
    ],
    "sg:phone":"+61 428 516 275",
    "sg:postcode":"3880",
    "sg:province":"VIC",
    "sg:tags":[
        "polishing",
        "sanding",
        "floor"
    ],
    "wof:name":"Greggs Floor Sanding",
    "wof:placetype":"venue"
},
  "geometry": {"coordinates":[147.71737670900001,-37.911239624],"type":"Point"}
}