{
  "type": "Feature",
  "properties": {
    "iso:country":"AU",
    "sg:address":"2 Sydenham Rd",
    "sg:city":"Brookvale",
    "sg:classifiers":[
        {
            "category":"Building & Trades",
            "subcategory":"Construction",
            "type":"Services"
        }
    ],
    "sg:phone":"+61 2 9907 1267",
    "sg:postcode":"2100",
    "sg:province":"NSW",
    "sg:tags":[
        "sun",
        "product",
        "protection"
    ],
    "wof:name":"Seasportz Australia",
    "wof:placetype":"venue"
},
  "geometry": {"coordinates":[151.272094727,-33.7643013],"type":"Point"}
}