{
  "type": "Feature",
  "properties": {
    "iso:country":"AU",
    "sg:address":"93 Waverley Rd",
    "sg:city":"Malvern East",
    "sg:classifiers":[
        {
            "category":"Professional",
            "subcategory":"Art Services",
            "type":"Services"
        }
    ],
    "sg:phone":"+61 3 9569 3880",
    "sg:postcode":"3145",
    "sg:province":"VIC",
    "sg:tags":[
        "picture",
        "frame",
        "framing"
    ],
    "wof:name":"Icon Frames",
    "wof:placetype":"venue"
},
  "geometry": {"coordinates":[145.04759216299999,-37.8757476807],"type":"Point"}
}