{
  "type": "Feature",
  "properties": {
    "iso:country":"AU",
    "sg:address":"Level 4, Suite 404/ 74 Pitt St",
    "sg:city":"Sydney",
    "sg:classifiers":[
        {
            "category":"Personal",
            "subcategory":"Beauty Salon",
            "type":"Services"
        }
    ],
    "sg:phone":"+61 1300 365 273",
    "sg:postcode":"2000",
    "sg:province":"NSW",
    "wof:name":"Australian Laser Clinic",
    "wof:placetype":"venue"
},
  "geometry": {"coordinates":[151.20875549300001,-33.8661460876],"type":"Point"}
}