{
  "type": "Feature",
  "properties": {
    "iso:country":"AU",
    "sg:address":"Ste1/ 72 Mann St",
    "sg:city":"Gosford",
    "sg:classifiers":[
        {
            "category":"Professional",
            "subcategory":"Art Services",
            "type":"Services"
        }
    ],
    "sg:phone":"+61 2 4322 2919",
    "sg:postcode":"2250",
    "sg:province":"NSW",
    "sg:tags":[
        "graphic",
        "designer"
    ],
    "wof:name":"Cad Training & Support",
    "wof:placetype":"venue"
},
  "geometry": {"coordinates":[151.341506958,-33.4277915955],"type":"Point"}
}