{
  "type": "Feature",
  "properties": {
    "iso:country":"AU",
    "sg:address":"9 James St",
    "sg:city":"Beenleigh",
    "sg:classifiers":[
        {
            "category":"Health Services",
            "subcategory":"Doctor",
            "type":"Services"
        }
    ],
    "sg:phone":"+61 7 3804 7560",
    "sg:postcode":"4207",
    "sg:province":"QLD",
    "sg:tags":[
        "medical",
        "practitioner"
    ],
    "wof:name":"Australian Radiological Imaging",
    "wof:placetype":"venue"
},
  "geometry": {"coordinates":[153.199462891,-27.7178020477],"type":"Point"}
}