{
  "type": "Feature",
  "properties": {
    "addr:full":"Unit 15/ 10 Playfair Rd Mt Colah NSW 2079",
    "addr:housenumber":"/ 10",
    "addr:postcode":"2079",
    "addr:street":"Playfair Rd;Colah",
    "iso:country":"AU",
    "sg:address":"Unit 15/ 10 Playfair Rd",
    "sg:city":"Mt Colah",
    "sg:classifiers":[
        {
            "category":"Professional",
            "subcategory":"Business Services",
            "type":"Services"
        }
    ],
    "sg:phone":"+61 2 9476 3683",
    "sg:postcode":"2079",
    "sg:province":"NSW",
    "sg:tags":[
        "drafting"
    ],
    "wof:name":"Rob Crump Design",
    "wof:placetype":"venue"
},
  "geometry": {"coordinates":[151.11671447800001,-33.668296814],"type":"Point"}
}