{
  "type": "Feature",
  "properties": {
    "iso:country":"AU",
    "sg:address":"25 Waterfall Rd",
    "sg:city":"Forrestfield",
    "sg:classifiers":[
        {
            "category":"Building & Trades",
            "subcategory":"Construction",
            "type":"Services"
        }
    ],
    "sg:phone":"+61 8 9359 1200",
    "sg:postcode":"6058",
    "sg:province":"WA",
    "sg:tags":[
        "brick",
        "paving"
    ],
    "wof:name":"Coppens L P & S L Brickpaving & Landscaping",
    "wof:placetype":"venue"
},
  "geometry": {"coordinates":[116.019073486,-31.9999294281],"type":"Point"}
}