{
  "type": "Feature",
  "properties": {
    "addr:full":"10 Westleigh Drv Westleigh NSW 2120",
    "addr:housenumber":"10",
    "addr:postcode":"2120",
    "addr:street":"Westleigh Drv",
    "iso:country":"AU",
    "sg:address":"10 Westleigh Drv",
    "sg:city":"Westleigh",
    "sg:classifiers":[
        {
            "category":"Organizations",
            "subcategory":"Professional Association",
            "type":"Services"
        }
    ],
    "sg:phone":"+61 2 9418 0493",
    "sg:postcode":"2120",
    "sg:province":"NSW",
    "sg:tags":[
        "web",
        "internet"
    ],
    "wof:name":"Tim Osity Web Sire Design",
    "wof:placetype":"venue"
},
  "geometry": {"coordinates":[151.06507873499999,-33.7158927917],"type":"Point"}
}