{
  "type": "Feature",
  "properties": {
    "addr:full":"15 Bathurst St Condobolin NSW 2877",
    "addr:housenumber":"15",
    "addr:postcode":"2877",
    "addr:street":"Bathurst St",
    "iso:country":"AU",
    "sg:address":"15 Bathurst St",
    "sg:city":"Condobolin",
    "sg:classifiers":[
        {
            "category":"Professional",
            "subcategory":"Engineering",
            "type":"Services"
        }
    ],
    "sg:phone":"+61 2 6895 2775",
    "sg:postcode":"2877",
    "sg:province":"NSW",
    "sg:tags":[
        "precision",
        "engineer"
    ],
    "wof:name":"Kiss J & E M General & Precision Engineering",
    "wof:placetype":"venue"
},
  "geometry": {"coordinates":[147.14712499999999,-33.088306],"type":"Point"}
}