{
  "type": "Feature",
  "properties": {
    "iso:country":"AU",
    "sg:address":"Suite 1 161 Wickham St",
    "sg:city":"Fortitude Valley",
    "sg:classifiers":[
        {
            "category":"Shopping",
            "subcategory":"News",
            "type":"Retail Goods"
        }
    ],
    "sg:phone":"+61 7 3257 1008",
    "sg:postcode":"4006",
    "sg:province":"QLD",
    "sg:tags":[
        "magazine",
        "periodical"
    ],
    "wof:name":"Adskyland Weekly",
    "wof:placetype":"venue"
},
  "geometry": {"coordinates":[153.03289794899999,-27.4584236145],"type":"Point"}
}