{
  "type": "Feature",
  "properties": {
    "addr:full":"338 Separation St Northcote VIC 3070",
    "addr:housenumber":"338",
    "addr:postcode":"3070",
    "addr:street":"Separation St",
    "iso:country":"AU",
    "sg:address":"338 Separation St",
    "sg:city":"Northcote",
    "sg:classifiers":[
        {
            "category":"Wholesale",
            "subcategory":"Home Furnishings",
            "type":"Manufacturing & Wholesale Goods"
        }
    ],
    "sg:phone":"+61 3 9482 6477",
    "sg:postcode":"3070",
    "sg:province":"VIC",
    "sg:tags":[
        "wholesaler",
        "mfrs",
        "clock"
    ],
    "wof:name":"AAA Tower Clock Service",
    "wof:placetype":"venue"
},
  "geometry": {"coordinates":[145.013046,-37.771118],"type":"Point"}
}