{
  "type": "Feature",
  "properties": {
    "iso:country":"AU",
    "sg:address":"150 Douglas Ave",
    "sg:city":"South Perth",
    "sg:classifiers":[
        {
            "category":"Health Services",
            "subcategory":"Dentist",
            "type":"Services"
        }
    ],
    "sg:phone":"+61 8 9474 5083",
    "sg:postcode":"6151",
    "sg:province":"WA",
    "wof:name":"Delaney Rosemary",
    "wof:placetype":"venue"
},
  "geometry": {"coordinates":[115.866982,-31.976118],"type":"Point"}
}