{
  "type": "Feature",
  "properties": {
    "addr:full":"730 Logan Rd Greenslopes QLD 4120",
    "addr:housenumber":"730",
    "addr:postcode":"4120",
    "addr:street":"Logan Rd",
    "iso:country":"AU",
    "sg:address":"730 Logan Rd",
    "sg:city":"Greenslopes",
    "sg:classifiers":[
        {
            "category":"Building & Trades",
            "subcategory":"Equipment Rental",
            "type":"Services"
        }
    ],
    "sg:phone":"+61 7 3397 1922",
    "sg:postcode":"4120",
    "sg:province":"QLD",
    "sg:tags":[
        "fitness"
    ],
    "wof:name":"Advanced Fitness",
    "wof:placetype":"venue"
},
  "geometry": {"coordinates":[153.05364990199999,-27.5126495361],"type":"Point"}
}