{
  "type": "Feature",
  "properties": {
    "addr:full":"Shop 9/ 611 Wynnum Rd Morningside QLD 4170",
    "addr:housenumber":"shop 9 / 611",
    "addr:postcode":"4170",
    "addr:street":"Wynnum Rd",
    "iso:country":"AU",
    "sg:address":"Shop 9/ 611 Wynnum Rd",
    "sg:city":"Morningside",
    "sg:classifiers":[
        {
            "category":"Personal",
            "subcategory":"Beauty Salon",
            "type":"Services"
        }
    ],
    "sg:phone":"+61 7 3399 6017",
    "sg:postcode":"4170",
    "sg:province":"QLD",
    "sg:tags":[
        "hairdresser"
    ],
    "wof:name":"K R Hairdressers",
    "wof:placetype":"venue"
},
  "geometry": {"coordinates":[153.07183837900001,-27.4684658051],"type":"Point"}
}