{
  "type": "Feature",
  "properties": {
    "iso:country":"AU",
    "sg:address":"18 McCullogh St",
    "sg:city":"Elizabeth Downs",
    "sg:classifiers":[
        {
            "category":"Education",
            "subcategory":"Music School",
            "type":"Public Place"
        }
    ],
    "sg:phone":"+61 8 8287 4010",
    "sg:postcode":"5113",
    "sg:province":"SA",
    "sg:tags":[
        "teacher"
    ],
    "wof:name":"DY Music",
    "wof:placetype":"venue"
},
  "geometry": {"coordinates":[138.70382690400001,-34.6985359192],"type":"Point"}
}