{
  "type": "Feature",
  "properties": {
    "addr:full":"39 Clovelly Rd Randwick NSW 2031",
    "addr:housenumber":"39",
    "addr:postcode":"2031",
    "addr:street":"Clovelly Rd",
    "iso:country":"AU",
    "sg:address":"39 Clovelly Rd",
    "sg:city":"Randwick",
    "sg:classifiers":[
        {
            "category":"Sports & Exercise",
            "subcategory":"Gym",
            "type":"Entertainment"
        }
    ],
    "sg:phone":"+61 413 044 410",
    "sg:postcode":"2031",
    "sg:province":"NSW",
    "sg:tags":[
        "personal",
        "trainer",
        "fitness"
    ],
    "wof:name":"Marich Anthony",
    "wof:placetype":"venue"
},
  "geometry": {"coordinates":[151.24989318900001,-33.9098777771],"type":"Point"}
}