{
  "type": "Feature",
  "properties": {
    "iso:country":"AU",
    "sg:address":"Suite 2002/ 114- 120 Old Pittwater Rd",
    "sg:city":"Brookvale",
    "sg:classifiers":[
        {
            "category":"Shopping",
            "subcategory":"Stationery & Office Supplies",
            "type":"Retail Goods"
        }
    ],
    "sg:phone":"+61 2 9905 7777",
    "sg:postcode":"2100",
    "sg:province":"NSW",
    "sg:tags":[
        "partition"
    ],
    "wof:name":"Sheldon Commercial Interiors Pty Ltd",
    "wof:placetype":"venue"
},
  "geometry": {"coordinates":[151.26185607900001,-33.7669143677],"type":"Point"}
}