{
  "type": "Feature",
  "properties": {
    "addr:full":"384 Swann Rd St Lucia QLD 4067",
    "addr:housenumber":"384",
    "addr:postcode":"4067",
    "addr:street":"Swann Rd",
    "iso:country":"AU",
    "sg:address":"384 Swann Rd",
    "sg:city":"St Lucia",
    "sg:classifiers":[
        {
            "category":"Social Services",
            "subcategory":"Child Care",
            "type":"Services"
        }
    ],
    "sg:phone":"+61 7 3371 6947",
    "sg:postcode":"4067",
    "sg:province":"QLD",
    "wof:name":"Campus Kindergarten After School Care",
    "wof:placetype":"venue"
},
  "geometry": {"coordinates":[152.99557495100001,-27.5012359619],"type":"Point"}
}