{
  "type": "Feature",
  "properties": {
    "iso:country":"AU",
    "sg:address":"66 Cross Rd",
    "sg:city":"Myrtle Bank",
    "sg:classifiers":[
        {
            "category":"Retail",
            "subcategory":"Repair Shop",
            "type":"Services"
        }
    ],
    "sg:phone":"+61 8 8379 7644",
    "sg:postcode":"5064",
    "sg:province":"SA",
    "sg:tags":[
        "upholsterer"
    ],
    "wof:name":"David Gunner",
    "wof:placetype":"venue"
},
  "geometry": {"coordinates":[138.63064575199999,-34.9641952515],"type":"Point"}
}