{
  "type": "Feature",
  "properties": {
    "addr:full":"225 Bamford La Kirwan QLD 4817",
    "addr:housenumber":"225",
    "addr:postcode":"4817",
    "addr:street":"Bamford La Kirwan",
    "iso:country":"AU",
    "sg:address":"225 Bamford La",
    "sg:city":"Kirwan",
    "sg:classifiers":[
        {
            "category":"Social Services",
            "subcategory":"Child Care",
            "type":"Services"
        }
    ],
    "sg:phone":"+61 7 4773 5474",
    "sg:postcode":"4817",
    "sg:province":"QLD",
    "wof:name":"Riverview Play Centre",
    "wof:placetype":"venue"
},
  "geometry": {"coordinates":[146.7397,-19.313169],"type":"Point"}
}