{
  "type": "Feature",
  "properties": {
    "iso:country":"AU",
    "sg:address":"7 Born Rd",
    "sg:city":"Casuarina",
    "sg:classifiers":[
        {
            "category":"Retail",
            "subcategory":"Auto Repair",
            "type":"Services"
        }
    ],
    "sg:phone":"+61 8 9419 3120",
    "sg:postcode":"6167",
    "sg:province":"WA",
    "sg:tags":[
        "beater",
        "painter",
        "panel"
    ],
    "wof:name":"Michel Smash Repairs Pty Ltd",
    "wof:placetype":"venue"
},
  "geometry": {"coordinates":[115.873062,-32.255047],"type":"Point"}
}