{
  "type": "Feature",
  "properties": {
    "iso:country":"AU",
    "sg:address":"95 Kubis Drv",
    "sg:city":"Ringwood",
    "sg:classifiers":[
        {
            "category":"Wholesale",
            "subcategory":"Medical Equipment & Supplies",
            "type":"Manufacturing & Wholesale Goods"
        }
    ],
    "sg:phone":"+61 3 9876 4431",
    "sg:postcode":"3134",
    "sg:province":"VIC",
    "sg:tags":[
        "buffing"
    ],
    "wof:name":"Calico Buffs & Mops",
    "wof:placetype":"venue"
},
  "geometry": {"coordinates":[145.224075317,-37.7928848267],"type":"Point"}
}