{
  "type": "Feature",
  "properties": {
    "iso:country":"AU",
    "sg:address":"Factory 5/ 1156 Burwood Hwy",
    "sg:city":"Boronia",
    "sg:classifiers":[
        {
            "category":"Building & Trades",
            "subcategory":"Construction",
            "type":"Services"
        }
    ],
    "sg:phone":"+61 3 9758 2511",
    "sg:postcode":"3155",
    "sg:province":"VIC",
    "sg:tags":[
        "industrial",
        "commercial",
        "air conditioning"
    ],
    "wof:name":"Chatfield Airconditioning & Electrical Services Pty Ltd",
    "wof:placetype":"venue"
},
  "geometry": {"coordinates":[145.30258178700001,-37.8918075562],"type":"Point"}
}