{
  "type": "Feature",
  "properties": {
    "iso:country":"AU",
    "sg:address":"PO Box 1010",
    "sg:city":"Buddina",
    "sg:classifiers":[
        {
            "category":"Sports & Exercise",
            "subcategory":"Gym",
            "type":"Entertainment"
        }
    ],
    "sg:phone":"+61 405 101 069",
    "sg:postcode":"4575",
    "sg:province":"QLD",
    "sg:tags":[
        "personal",
        "trainer",
        "fitness"
    ],
    "wof:name":"Kooz U Kan Personal Development",
    "wof:placetype":"venue"
},
  "geometry": {"coordinates":[153.129639,-26.700609],"type":"Point"}
}