{
  "type": "Feature",
  "properties": {
    "addr:full":"60 Ocean View Drv Valla Beach NSW 2448",
    "addr:housenumber":"60",
    "addr:postcode":"2448",
    "addr:street":"Ocean View Drv",
    "iso:country":"AU",
    "sg:address":"60 Ocean View Drv",
    "sg:city":"Valla Beach",
    "sg:classifiers":[
        {
            "category":"Building & Trades",
            "subcategory":"Plumbing",
            "type":"Services"
        }
    ],
    "sg:phone":"+61 2 6569 5330",
    "sg:postcode":"2448",
    "sg:province":"NSW",
    "sg:tags":[
        "plumber",
        "gasfitters"
    ],
    "wof:name":"Young R C",
    "wof:placetype":"venue"
},
  "geometry": {"coordinates":[153.00559999999999,-30.596973],"type":"Point"}
}