{
  "type": "Feature",
  "properties": {
    "addr:full":"Shop 1/ 115 Blackwall Rd Woy Woy NSW 2256",
    "addr:housenumber":"shop 1 / 115",
    "addr:postcode":"2256",
    "addr:street":"Blackwall Rd",
    "iso:country":"AU",
    "sg:address":"Shop 1/ 115 Blackwall Rd",
    "sg:city":"Woy Woy",
    "sg:classifiers":[
        {
            "category":"Fast Food",
            "type":"Food & Drink"
        }
    ],
    "sg:phone":"+61 2 4341 0441",
    "sg:postcode":"2256",
    "sg:province":"NSW",
    "sg:tags":[
        "away",
        "take"
    ],
    "wof:name":"K B Thai Takeaway",
    "wof:placetype":"venue"
},
  "geometry": {"coordinates":[151.325714111,-33.488483429],"type":"Point"}
}