{
  "type": "Feature",
  "properties": {
    "iso:country":"AU",
    "sg:address":"PO Box 9460",
    "sg:city":"Mt Gambier West",
    "sg:classifiers":[
        {
            "category":"Professional",
            "subcategory":"Computer Services",
            "type":"Services"
        }
    ],
    "sg:phone":"+61 427 901 801",
    "sg:postcode":"5291",
    "sg:province":"SA",
    "sg:tags":[
        "repairs",
        "upgrade",
        "equipment"
    ],
    "wof:name":"Tact Se",
    "wof:placetype":"venue"
},
  "geometry": {"coordinates":[140.762589,-37.822639],"type":"Point"}
}