{
  "type": "Feature",
  "properties": {
    "addr:full":"21 Carr St Coogee NSW 2034",
    "addr:housenumber":"21",
    "addr:postcode":"2034",
    "addr:street":"Carr St",
    "iso:country":"AU",
    "sg:address":"21 Carr St",
    "sg:city":"Coogee",
    "sg:classifiers":[
        {
            "category":"Health Services",
            "subcategory":"Doctor",
            "type":"Services"
        }
    ],
    "sg:phone":"+61 2 9665 4344",
    "sg:postcode":"2034",
    "sg:province":"NSW",
    "sg:tags":[
        "medical",
        "practitioner"
    ],
    "wof:name":"Baker Martyn,Jacobs Naomi,Blainey Chris, Ho Carol",
    "wof:placetype":"venue"
},
  "geometry": {"coordinates":[151.25140380900001,-33.9218978882],"type":"Point"}
}