{
  "type": "Feature",
  "properties": {
    "addr:full":"57 Cumberland St Cessnock NSW 2325",
    "addr:housenumber":"57",
    "addr:postcode":"2325",
    "addr:street":"Cumberland St",
    "iso:country":"AU",
    "sg:address":"57 Cumberland St",
    "sg:city":"Cessnock",
    "sg:classifiers":[
        {
            "category":"Banks & Credit Unions",
            "subcategory":"Investment Brokerage",
            "type":"Services"
        }
    ],
    "sg:phone":"+61 2 4991 1911",
    "sg:postcode":"2325",
    "sg:province":"NSW",
    "sg:tags":[
        "finance",
        "broker"
    ],
    "wof:name":"Spinks Consulting",
    "wof:placetype":"venue"
},
  "geometry": {"coordinates":[151.35690307600001,-32.8366088867],"type":"Point"}
}