{
  "type": "Feature",
  "properties": {
    "addr:full":"54 Stradbroke Drv St Albans VIC 3021",
    "addr:housenumber":"54",
    "addr:postcode":"3021",
    "addr:street":"Stradbroke Drv",
    "iso:country":"AU",
    "sg:address":"54 Stradbroke Drv",
    "sg:city":"St Albans",
    "sg:classifiers":[
        {
            "category":"Fast Food",
            "type":"Food & Drink"
        }
    ],
    "sg:phone":"+61 3 9367 7222",
    "sg:postcode":"3021",
    "sg:province":"VIC",
    "sg:tags":[
        "away",
        "take"
    ],
    "wof:name":"Frankies Pizza",
    "wof:placetype":"venue"
},
  "geometry": {"coordinates":[144.80934099999999,-37.747593],"type":"Point"}
}