{
  "type": "Feature",
  "properties": {
    "iso:country":"AU",
    "sg:address":"15385 Bass Hwy",
    "sg:city":"Somerset",
    "sg:classifiers":[
        {
            "category":"Home & Garden",
            "subcategory":"Garden Supply",
            "type":"Retail Goods"
        }
    ],
    "sg:phone":"+61 3 6435 1391",
    "sg:postcode":"7322",
    "sg:province":"TAS",
    "sg:tags":[
        "landscape"
    ],
    "wof:name":"Cloverlea Plants Plus",
    "wof:placetype":"venue"
},
  "geometry": {"coordinates":[145.805756,-41.028355],"type":"Point"}
}