{
  "type": "Feature",
  "properties": {
    "iso:country":"AU",
    "sg:address":"211 Wheeles Hill Rd",
    "sg:city":"Musk",
    "sg:classifiers":[
        {
            "category":"Wholesale",
            "subcategory":"Machinery & Supplies",
            "type":"Manufacturing & Wholesale Goods"
        }
    ],
    "sg:phone":"+61 3 5348 2669",
    "sg:postcode":"3461",
    "sg:province":"VIC",
    "sg:tags":[
        "agricultural"
    ],
    "wof:name":"Fix Engineering",
    "wof:placetype":"venue"
},
  "geometry": {"coordinates":[144.18423461899999,-37.3870048523],"type":"Point"}
}