{
  "type": "Feature",
  "properties": {
    "addr:full":"Suite 7, 5 Innovation Park Way Birtinya QLD 4575",
    "addr:housenumber":"5",
    "addr:postcode":"4575",
    "addr:street":"Innovation Park Way",
    "iso:country":"AU",
    "sg:address":"Suite 7, 5 Innovation Park Way",
    "sg:city":"Birtinya",
    "sg:classifiers":[
        {
            "category":"Health Services",
            "subcategory":"Doctor",
            "type":"Services"
        }
    ],
    "sg:phone":"+61 7 5493 3800",
    "sg:postcode":"4575",
    "sg:province":"QLD",
    "sg:tags":[
        "medical",
        "practitioner"
    ],
    "wof:name":"Lake Kawana General Practice",
    "wof:placetype":"venue"
},
  "geometry": {"coordinates":[153.12170399999999,-26.731689],"type":"Point"}
}