{
  "type": "Feature",
  "properties": {
    "addr:full":"Shop 23 The Galleria Morley Collier Rd Morley WA 6062",
    "addr:housenumber":"shop 23",
    "addr:postcode":"6062",
    "addr:street":"The;Collier Rd",
    "iso:country":"AU",
    "sg:address":"Shop 23 The Galleria Morley Collier Rd",
    "sg:city":"Morley",
    "sg:classifiers":[
        {
            "category":"Personal",
            "subcategory":"Beauty Salon",
            "type":"Services"
        }
    ],
    "sg:phone":"+61 8 9275 5558",
    "sg:postcode":"6062",
    "sg:province":"WA",
    "sg:tags":[
        "hairdresser"
    ],
    "wof:name":"Ali Barber Mens Hair Stylist",
    "wof:placetype":"venue"
},
  "geometry": {"coordinates":[115.90247345,-31.894908905],"type":"Point"}
}