{
  "type": "Feature",
  "properties": {
    "addr:full":"3/ 255 Military Rd West Lakes Shore SA 5020",
    "addr:housenumber":"/ 255",
    "addr:postcode":"5020",
    "addr:street":"Military Rd",
    "iso:country":"AU",
    "sg:address":"3/ 255 Military Rd",
    "sg:city":"West Lakes Shore",
    "sg:classifiers":[
        {
            "category":"Banks & Credit Unions",
            "subcategory":"Bank",
            "type":"Services"
        }
    ],
    "sg:phone":"+61 410 607 447",
    "sg:postcode":"5020",
    "sg:province":"SA",
    "sg:tags":[
        "broker",
        "mortgage"
    ],
    "wof:name":"DG Professional Financal Services Pty Ltd",
    "wof:placetype":"venue"
},
  "geometry": {"coordinates":[138.47962951700001,-34.8656768799],"type":"Point"}
}