{
  "type": "Feature",
  "properties": {
    "addr:full":"PO Box 58 Hallam VIC 3803",
    "addr:postcode":"3803",
    "iso:country":"AU",
    "sg:address":"PO Box 58",
    "sg:city":"Hallam",
    "sg:classifiers":[
        {
            "category":"Utilities",
            "subcategory":"Refuse",
            "type":"Services"
        }
    ],
    "sg:phone":"+61 418 365 918",
    "sg:postcode":"3803",
    "sg:province":"VIC",
    "sg:tags":[
        "remover",
        "rubbish"
    ],
    "wof:name":"The Bin Man",
    "wof:placetype":"venue"
},
  "geometry": {"coordinates":[145.269256592,-38.0042991638],"type":"Point"}
}