{
  "type": "Feature",
  "properties": {
    "addr:full":"Shp12/ 347 Kingsway St Caringbah NSW 2229",
    "addr:housenumber":"347",
    "addr:postcode":"2229",
    "addr:street":"Kingsway St",
    "iso:country":"AU",
    "sg:address":"Shp12/ 347 Kingsway St",
    "sg:city":"Caringbah",
    "sg:classifiers":[
        {
            "category":"Fast Food",
            "type":"Food & Drink"
        }
    ],
    "sg:phone":"+61 2 9525 0294",
    "sg:postcode":"2229",
    "sg:province":"NSW",
    "sg:tags":[
        "away",
        "take"
    ],
    "wof:name":"Caringbah Charcoal Chicken",
    "wof:placetype":"venue"
},
  "geometry": {"coordinates":[151.12168884299999,-34.0412979126],"type":"Point"}
}