{
  "type": "Feature",
  "properties": {
    "iso:country":"AU",
    "sg:address":"521 Great North Rd",
    "sg:city":"Abbotsford",
    "sg:classifiers":[
        {
            "category":"Health Services",
            "subcategory":"Health Practitioner",
            "type":"Services"
        }
    ],
    "sg:phone":"+61 2 9712 2298",
    "sg:postcode":"2046",
    "sg:province":"NSW",
    "sg:tags":[
        "pathologist",
        "speech"
    ],
    "wof:name":"Gillian Fong Speech Pathology Services",
    "wof:placetype":"venue"
},
  "geometry": {"coordinates":[151.128006,-33.849579],"type":"Point"}
}