{
  "type": "Feature",
  "properties": {
    "iso:country":"AU",
    "sg:address":"4/ 97 Beach Rd",
    "sg:city":"Christies Beach",
    "sg:classifiers":[
        {
            "category":"Food & Beverages",
            "subcategory":"Specialty",
            "type":"Retail Goods"
        }
    ],
    "sg:phone":"+61 8 8382 1125",
    "sg:postcode":"5165",
    "sg:province":"SA",
    "sg:tags":[
        "product",
        "health"
    ],
    "wof:name":"Christies Beach Health Food Barn",
    "wof:placetype":"venue"
},
  "geometry": {"coordinates":[138.480667114,-35.1388092041],"type":"Point"}
}