{
  "type": "Feature",
  "properties": {
    "addr:full":"28 Kennedy St Bendigo VIC 3550",
    "addr:housenumber":"28",
    "addr:postcode":"3550",
    "addr:street":"Kennedy St",
    "iso:country":"AU",
    "sg:address":"28 Kennedy St",
    "sg:city":"Bendigo",
    "sg:classifiers":[
        {
            "category":"Banks & Credit Unions",
            "subcategory":"Bureau De Change",
            "type":"Services"
        }
    ],
    "sg:phone":"+61 3 5441 2348",
    "sg:postcode":"3550",
    "sg:province":"VIC",
    "sg:tags":[
        "control",
        "consultant",
        "vibration"
    ],
    "wof:name":"Computerised Bearing Analysis",
    "wof:placetype":"venue"
},
  "geometry": {"coordinates":[144.292572022,-36.7546920776],"type":"Point"}
}