{
  "type": "Feature",
  "properties": {
    "iso:country":"AU",
    "sg:address":"Druids House, Lvl 1 407-409 Swanston St",
    "sg:city":"Melbourne",
    "sg:classifiers":[
        {
            "category":"Personal",
            "subcategory":"Massage",
            "type":"Services"
        }
    ],
    "sg:phone":"+61 413 610 683",
    "sg:postcode":"3000",
    "sg:province":"VIC",
    "sg:tags":[
        "therapy"
    ],
    "wof:name":"Wendy Farrelly Holistic Healing And Massage",
    "wof:placetype":"venue"
},
  "geometry": {"coordinates":[144.96330261200001,-37.8088302612],"type":"Point"}
}