{
  "type": "Feature",
  "properties": {
    "addr:full":"9 Flynn St Churchlands WA 6018",
    "addr:housenumber":"9",
    "addr:postcode":"6018",
    "addr:street":"Flynn St",
    "iso:country":"AU",
    "sg:address":"9 Flynn St",
    "sg:city":"Churchlands",
    "sg:classifiers":[
        {
            "category":"Food & Beverages",
            "subcategory":"Bakery",
            "type":"Retail Goods"
        }
    ],
    "sg:phone":"+61 8 9284 0909",
    "sg:postcode":"6018",
    "sg:province":"WA",
    "sg:tags":[
        "baker"
    ],
    "wof:name":"Brumbys WA & NT",
    "wof:placetype":"venue"
},
  "geometry": {"coordinates":[115.802009583,-31.931219101],"type":"Point"}
}