{
  "type": "Feature",
  "properties": {
    "iso:country":"AU",
    "sg:address":"164 Greenhill Rd",
    "sg:city":"Parkside",
    "sg:classifiers":[
        {
            "category":"Real Estate",
            "subcategory":"Architect",
            "type":"Services"
        }
    ],
    "sg:phone":"+61 8 8272 2600",
    "sg:postcode":"5063",
    "sg:province":"SA",
    "wof:name":"David Walker Architects",
    "wof:placetype":"venue"
},
  "geometry": {"coordinates":[138.61036682100001,-34.9409446716],"type":"Point"}
}