{
  "type": "Feature",
  "properties": {
    "iso:country":"AU",
    "sg:address":"87 Canadian Bay Rd",
    "sg:city":"Mt Eliza",
    "sg:classifiers":[
        {
            "category":"Health Services",
            "subcategory":"Dentist",
            "type":"Services"
        }
    ],
    "sg:phone":"+61 3 9787 3355",
    "sg:postcode":"3930",
    "sg:province":"VIC",
    "wof:name":"Mt Eliza Dental Centre",
    "wof:placetype":"venue"
},
  "geometry": {"coordinates":[145.09085082999999,-38.1854705811],"type":"Point"}
}