{
  "type": "Feature",
  "properties": {
    "addr:full":"Building 6 Parrott St Ipswich QLD 4305",
    "addr:postcode":"4305",
    "addr:street":"Parrott St",
    "iso:country":"AU",
    "sg:address":"Building 6 Parrott St",
    "sg:city":"Ipswich",
    "sg:classifiers":[
        {
            "category":"Retail",
            "subcategory":"Repair Shop",
            "type":"Services"
        }
    ],
    "sg:phone":"+61 7 3381 7777",
    "sg:postcode":"4305",
    "sg:province":"QLD",
    "sg:tags":[
        "machine",
        "repairs",
        "part",
        "dryer",
        "washing"
    ],
    "wof:name":"R.T. Edwards",
    "wof:placetype":"venue"
},
  "geometry": {"coordinates":[152.76182556099999,-27.6341724396],"type":"Point"}
}