{
  "type": "Feature",
  "properties": {
    "addr:full":"Shop 8 Northcote Central Northcote VIC 3070",
    "addr:housenumber":"shop 8",
    "addr:postcode":"3070",
    "iso:country":"AU",
    "sg:address":"Shop 8",
    "sg:city":"Northcote Central Northcote",
    "sg:classifiers":[
        {
            "category":"Health Services",
            "subcategory":"Optometrist",
            "type":"Services"
        }
    ],
    "sg:phone":"+61 3 9481 7900",
    "sg:postcode":"3070",
    "sg:province":"VIC",
    "wof:name":"Merringtons",
    "wof:placetype":"venue"
},
  "geometry": {"coordinates":[145.008026,-37.774433],"type":"Point"}
}