{
  "type": "Feature",
  "properties": {
    "iso:country":"AU",
    "sg:address":"Unit 3/ 18 Vinnicombe Drv",
    "sg:city":"Canning Vale",
    "sg:classifiers":[
        {
            "category":"Home & Garden",
            "subcategory":"Building Materials",
            "type":"Retail Goods"
        }
    ],
    "sg:phone":"+61 8 9455 1880",
    "sg:postcode":"6155",
    "sg:province":"WA",
    "sg:tags":[
        "skylight"
    ],
    "wof:name":"Homestead Skylights",
    "wof:placetype":"venue"
},
  "geometry": {"coordinates":[115.91626,-32.058891],"type":"Point"}
}