{
  "type": "Feature",
  "properties": {
    "addr:full":"218 Bellbridge Drv Hoppers Crossing VIC 3029",
    "addr:housenumber":"218",
    "addr:postcode":"3029",
    "addr:street":"Bellbridge Drv",
    "iso:country":"AU",
    "sg:address":"218 Bellbridge Drv",
    "sg:city":"Hoppers Crossing",
    "sg:classifiers":[
        {
            "category":"Utilities",
            "subcategory":"Water",
            "type":"Services"
        }
    ],
    "sg:phone":"+61 3 9748 4047",
    "sg:postcode":"3029",
    "sg:province":"VIC",
    "sg:tags":[
        "equipment",
        "treatment"
    ],
    "wof:name":"HomePure Healthy Water Systems",
    "wof:placetype":"venue"
},
  "geometry": {"coordinates":[144.70683299999999,-37.861046],"type":"Point"}
}