{
  "type": "Feature",
  "properties": {
    "iso:country":"AU",
    "sg:address":"38 Graylands Rd",
    "sg:city":"Claremont",
    "sg:classifiers":[
        {
            "category":"Arts & Performance",
            "subcategory":"Dance",
            "type":"Entertainment"
        }
    ],
    "sg:phone":"+61 8 9385 2989",
    "sg:postcode":"6010",
    "sg:province":"WA",
    "sg:tags":[
        "theatrical",
        "ballet",
        "tuition"
    ],
    "wof:name":"John & Bernadette Taylor Ballet School",
    "wof:placetype":"venue"
},
  "geometry": {"coordinates":[115.782981873,-31.9744625092],"type":"Point"}
}