{
  "type": "Feature",
  "properties": {
    "iso:country":"AU",
    "sg:address":"Lot 28",
    "sg:city":"Napier Tce Broome",
    "sg:classifiers":[
        {
            "category":"Retail",
            "subcategory":"Auto Repair",
            "type":"Services"
        }
    ],
    "sg:phone":"+61 13 23 81",
    "sg:postcode":"6725",
    "sg:province":"WA",
    "sg:tags":[
        "wheel",
        "balancing",
        "alignment"
    ],
    "wof:name":"Beaurepaires",
    "wof:placetype":"venue"
},
  "geometry": {"coordinates":[122.240531921,-17.9550647736],"type":"Point"}
}