{
  "type": "Feature",
  "properties": {
    "iso:country":"AU",
    "sg:address":"782 Heidelberg Rd",
    "sg:city":"Alphington",
    "sg:classifiers":[
        {
            "category":"Wholesale",
            "subcategory":"Machinery & Supplies",
            "type":"Manufacturing & Wholesale Goods"
        }
    ],
    "sg:phone":"+61 3 9497 3633",
    "sg:postcode":"3078",
    "sg:province":"VIC",
    "wof:name":"Machinery Forum Pty Ltd",
    "wof:placetype":"venue"
},
  "geometry": {"coordinates":[145.032836914,-37.7805786133],"type":"Point"}
}