{
  "type": "Feature",
  "properties": {
    "addr:full":"28 Brook St Sunbury VIC 3429",
    "addr:housenumber":"28",
    "addr:postcode":"3429",
    "addr:street":"Brook St",
    "iso:country":"AU",
    "sg:address":"28 Brook St",
    "sg:city":"Sunbury",
    "sg:classifiers":[
        {
            "category":"Communications",
            "subcategory":"Film & Video Production",
            "type":"Services"
        }
    ],
    "sg:phone":"+61 3 9744 6844",
    "sg:postcode":"3429",
    "sg:province":"VIC",
    "sg:tags":[
        "dvd",
        "library"
    ],
    "wof:name":"Movies Plus",
    "wof:placetype":"venue"
},
  "geometry": {"coordinates":[144.73162841800001,-37.5808830261],"type":"Point"}
}