{
  "type": "Feature",
  "properties": {
    "addr:full":"39 Margaret St Mayfield East NSW 2304",
    "addr:housenumber":"39",
    "addr:postcode":"2304",
    "addr:street":"Margaret St",
    "iso:country":"AU",
    "sg:address":"39 Margaret St",
    "sg:city":"Mayfield East",
    "sg:classifiers":[
        {
            "category":"Autos & Motor Vehicles",
            "subcategory":"Fuel & Gas Station",
            "type":"Retail Goods"
        }
    ],
    "sg:phone":"+61 2 4960 0512",
    "sg:postcode":"2304",
    "sg:province":"NSW",
    "sg:tags":[
        "injection",
        "diesel"
    ],
    "wof:name":"Dieselcraft Australasia",
    "wof:placetype":"venue"
},
  "geometry": {"coordinates":[151.74903869600001,-32.900604248],"type":"Point"}
}