{
  "type": "Feature",
  "properties": {
    "addr:full":"55 Thomas St Ringwood VIC 3134",
    "addr:housenumber":"55",
    "addr:postcode":"3134",
    "addr:street":"Thomas St",
    "iso:country":"AU",
    "sg:address":"55 Thomas St",
    "sg:city":"Ringwood",
    "sg:classifiers":[
        {
            "category":"Retail",
            "subcategory":"Storage",
            "type":"Services"
        }
    ],
    "sg:phone":"+61 3 9879 3461",
    "sg:postcode":"3134",
    "sg:province":"VIC",
    "sg:tags":[
        "removal",
        "furniture"
    ],
    "wof:name":"L J Removals",
    "wof:placetype":"venue"
},
  "geometry": {"coordinates":[145.234375,-37.8216667175],"type":"Point"}
}