{
  "type": "Feature",
  "properties": {
    "iso:country":"AU",
    "sg:address":"32 Mangrove Rd",
    "sg:city":"Narara",
    "sg:classifiers":[
        {
            "category":"Banks & Credit Unions",
            "subcategory":"Financial Services",
            "type":"Services"
        }
    ],
    "sg:phone":"+61 2 4329 2144",
    "sg:postcode":"2250",
    "sg:province":"NSW",
    "sg:tags":[
        "loan",
        "finance",
        "mortgage"
    ],
    "wof:name":"Murray Stan",
    "wof:placetype":"venue"
},
  "geometry": {"coordinates":[151.34381103499999,-33.385799408],"type":"Point"}
}