{
  "type": "Feature",
  "properties": {
    "addr:full":"Shop 6 Air Raid Arcade, 35 Cavenagh St, Darwin NT 0800",
    "addr:housenumber":"shop 6;35",
    "addr:postcode":"nt 0800",
    "addr:street":"Air Raid Arcade;Cavenagh St",
    "iso:country":"AU",
    "sg:address":"Shop 6 Air Raid Arcade, 35",
    "sg:city":"Cavenagh St, Darwin",
    "sg:classifiers":[
        {
            "category":"Communications",
            "subcategory":"News Services",
            "type":"Services"
        }
    ],
    "sg:phone":"+61 8 8941 3593",
    "sg:postcode":"0800",
    "sg:province":"NT",
    "sg:tags":[
        "information",
        "tourist",
        "attractions"
    ],
    "wof:name":"Tiwi Art Network - Art Tours",
    "wof:placetype":"venue"
},
  "geometry": {"coordinates":[130.84201049800001,-12.4616527557],"type":"Point"}
}