{
  "type": "Feature",
  "properties": {
    "addr:full":"124 Fitzgerald St Northam WA 6401",
    "addr:housenumber":"124",
    "addr:postcode":"6401",
    "addr:street":"Fitzgerald St",
    "iso:country":"AU",
    "sg:address":"124 Fitzgerald St",
    "sg:city":"Northam",
    "sg:classifiers":[
        {
            "category":"Health Services",
            "subcategory":"Health Practitioner",
            "type":"Services"
        }
    ],
    "sg:phone":"+61 8 9622 5040",
    "sg:postcode":"6401",
    "sg:province":"WA",
    "sg:tags":[
        "physiotherapist"
    ],
    "wof:name":"Northam Physiotherapy",
    "wof:placetype":"venue"
},
  "geometry": {"coordinates":[116.67301178,-31.652097702],"type":"Point"}
}