{
  "type": "Feature",
  "properties": {
    "iso:country":"AU",
    "sg:address":"30 Doctors Gully Rd",
    "sg:city":"Doreen",
    "sg:classifiers":[
        {
            "category":"Autos & Motor Vehicles",
            "subcategory":"Automobile Sales",
            "type":"Retail Goods"
        }
    ],
    "sg:phone":"+61 3 9717 3085",
    "sg:postcode":"3754",
    "sg:province":"VIC",
    "sg:tags":[
        "equipment",
        "trailer"
    ],
    "wof:name":"Ranger Stock Floats Pty Ltd",
    "wof:placetype":"venue"
},
  "geometry": {"coordinates":[145.13949600000001,-37.605721],"type":"Point"}
}