{
  "type": "Feature",
  "properties": {
    "addr:full":"116 Gympie Rd Strathpine QLD 4500",
    "addr:housenumber":"116",
    "addr:postcode":"4500",
    "addr:street":"Gympie Rd",
    "iso:country":"AU",
    "sg:address":"116 Gympie Rd",
    "sg:city":"Strathpine",
    "sg:classifiers":[
        {
            "category":"Autos & Motor Vehicles",
            "subcategory":"Fuel & Gas Station",
            "type":"Retail Goods"
        }
    ],
    "sg:phone":"+61 7 3205 2481",
    "sg:postcode":"4500",
    "sg:province":"QLD",
    "wof:name":"Matilda Strathpine",
    "wof:placetype":"venue"
},
  "geometry": {"coordinates":[152.98826599099999,-27.3018779755],"type":"Point"}
}