{
  "type": "Feature",
  "properties": {
    "addr:full":"38 McIntosh St Airport West VIC 3042",
    "addr:housenumber":"38",
    "addr:postcode":"3042",
    "addr:street":"Mcintosh St",
    "iso:country":"AU",
    "sg:address":"38 McIntosh St",
    "sg:city":"Airport West",
    "sg:classifiers":[
        {
            "category":"Manufacturing",
            "subcategory":"Furniture",
            "type":"Manufacturing & Wholesale Goods"
        }
    ],
    "sg:phone":"+61 3 9330 2512",
    "sg:postcode":"3042",
    "sg:province":"VIC",
    "sg:tags":[
        "builder",
        "designer",
        "custom"
    ],
    "wof:name":"Emerald Built In Robes",
    "wof:placetype":"venue"
},
  "geometry": {"coordinates":[144.88751220699999,-37.7209854126],"type":"Point"}
}