{
  "type": "Feature",
  "properties": {
    "addr:full":"555 Pittwater Rd Brookvale NSW 2100",
    "addr:housenumber":"555",
    "addr:postcode":"2100",
    "addr:street":"Pittwater Rd",
    "iso:country":"AU",
    "sg:address":"555 Pittwater Rd",
    "sg:city":"Brookvale",
    "sg:classifiers":[
        {
            "category":"Building & Trades",
            "subcategory":"Landscaping Services",
            "type":"Services"
        }
    ],
    "sg:phone":"+61 2 9905 0069",
    "sg:postcode":"2100",
    "sg:province":"NSW",
    "sg:tags":[
        "designer",
        "landscape",
        "contractor"
    ],
    "wof:name":"No Limit Design & Construction",
    "wof:placetype":"venue"
},
  "geometry": {"coordinates":[151.27662658700001,-33.760974884],"type":"Point"}
}