{
  "type": "Feature",
  "properties": {
    "addr:full":"80 Buttaba Ave Belmont North NSW 2280",
    "addr:housenumber":"80",
    "addr:postcode":"2280",
    "addr:street":"Buttaba Ave",
    "iso:country":"AU",
    "sg:address":"80 Buttaba Ave",
    "sg:city":"Belmont North",
    "sg:classifiers":[
        {
            "category":"Building & Trades",
            "subcategory":"Construction",
            "type":"Services"
        }
    ],
    "sg:phone":"+61 2 4945 4257",
    "sg:postcode":"2280",
    "sg:province":"NSW",
    "sg:tags":[
        "contractor"
    ],
    "wof:name":"Aiello's Building & Construction Pty Ltd",
    "wof:placetype":"venue"
},
  "geometry": {"coordinates":[151.67222595199999,-33.0212173462],"type":"Point"}
}