{
  "type": "Feature",
  "properties": {
    "iso:country":"AU",
    "sg:address":"54- 56 Sackville St",
    "sg:city":"Collingwood",
    "sg:classifiers":[
        {
            "category":"Professional",
            "subcategory":"Printing & Photocopies",
            "type":"Services"
        }
    ],
    "sg:phone":"+61 3 9417 6838",
    "sg:postcode":"3066",
    "sg:province":"VIC",
    "sg:tags":[
        "embroidery"
    ],
    "wof:name":"Winston Hi-Tech Computerised Embroidery Punching Pty Ltd",
    "wof:placetype":"venue"
},
  "geometry": {"coordinates":[144.986984253,-37.7983360291],"type":"Point"}
}