{
  "type": "Feature",
  "properties": {
    "iso:country":"AU",
    "sg:address":"Shop 37 Nathan plaza 310 Ross River Rd",
    "sg:city":"Aitkenvale",
    "sg:classifiers":[
        {
            "category":"Shopping",
            "subcategory":"Clothing, Apparel, & Fashions",
            "type":"Retail Goods"
        }
    ],
    "sg:phone":"+61 7 4725 3062",
    "sg:postcode":"4814",
    "sg:province":"QLD",
    "sg:tags":[
        "jean"
    ],
    "wof:name":"Westco Jeans (Aust) Pty Ltd",
    "wof:placetype":"venue"
},
  "geometry": {"coordinates":[146.764191,-19.297947],"type":"Point"}
}