{
  "type": "Feature",
  "properties": {
    "iso:country":"AU",
    "sg:address":"PO Box 80",
    "sg:city":"Arno Bay",
    "sg:classifiers":[
        {
            "category":"Food & Beverages",
            "subcategory":"Meat & Fish",
            "type":"Retail Goods"
        }
    ],
    "sg:phone":"+61 8 8628 0220",
    "sg:postcode":"5603",
    "sg:province":"SA",
    "sg:tags":[
        "aquaculture"
    ],
    "wof:name":"Clean Sea's Aquaculture",
    "wof:placetype":"venue"
},
  "geometry": {"coordinates":[136.565506,-33.905499],"type":"Point"}
}