{
  "type": "Feature",
  "properties": {
    "addr:full":"110a Hoddle St Abbotsford VIC 3067",
    "addr:housenumber":"110a",
    "addr:postcode":"3067",
    "addr:street":"Hoddle St",
    "iso:country":"AU",
    "sg:address":"110a Hoddle St",
    "sg:city":"Abbotsford",
    "sg:classifiers":[
        {
            "category":"Fast Food",
            "type":"Food & Drink"
        }
    ],
    "sg:phone":"+61 3 9419 9470",
    "sg:postcode":"3067",
    "sg:province":"VIC",
    "sg:tags":[
        "away",
        "take"
    ],
    "wof:name":"Encore Pizza & Pasta",
    "wof:placetype":"venue"
},
  "geometry": {"coordinates":[144.992385864,-37.8051261902],"type":"Point"}
}