{
  "type": "Feature",
  "properties": {
    "addr:full":"21 Yeatman St Hyde Park QLD 4812",
    "addr:housenumber":"21",
    "addr:postcode":"4812",
    "addr:street":"Yeatman St",
    "iso:country":"AU",
    "sg:address":"21 Yeatman St",
    "sg:city":"Hyde Park",
    "sg:classifiers":[
        {
            "category":"Home & Garden",
            "subcategory":"Furniture",
            "type":"Retail Goods"
        }
    ],
    "sg:phone":"+61 7 4722 0322",
    "sg:postcode":"4812",
    "sg:province":"QLD",
    "sg:tags":[
        "business"
    ],
    "wof:name":"Townsville Office Furniture Pty Ltd",
    "wof:placetype":"venue"
},
  "geometry": {"coordinates":[146.80098000000001,-19.272451],"type":"Point"}
}