{
  "type": "Feature",
  "properties": {
    "addr:full":"126 Lisbon St Fairfield NSW 2165",
    "addr:housenumber":"126",
    "addr:postcode":"2165",
    "addr:street":"Lisbon St",
    "iso:country":"AU",
    "sg:address":"126 Lisbon St",
    "sg:city":"Fairfield",
    "sg:classifiers":[
        {
            "category":"Professional",
            "subcategory":"Detective & Security Services",
            "type":"Services"
        }
    ],
    "sg:phone":"+61 1300 736 683",
    "sg:postcode":"2165",
    "sg:province":"NSW",
    "sg:tags":[
        "shuttering"
    ],
    "wof:name":"A. Allshutters 24 Hour Emergency Service",
    "wof:placetype":"venue"
},
  "geometry": {"coordinates":[150.97486877399999,-33.8708839417],"type":"Point"}
}