{
  "type": "Feature",
  "properties": {
    "iso:country":"AU",
    "sg:address":"Suite 3/ 15 Moss St",
    "sg:city":"Nowra",
    "sg:classifiers":[
        {
            "category":"Organizations",
            "subcategory":"Non-profit Organization",
            "type":"Services"
        }
    ],
    "sg:phone":"+61 2 4423 3180",
    "sg:postcode":"2541",
    "sg:province":"NSW",
    "sg:tags":[
        "support",
        "disability",
        "organisation"
    ],
    "wof:name":"House With No Steps Southern Region Accommodation Support",
    "wof:placetype":"venue"
},
  "geometry": {"coordinates":[150.604415894,-34.8722381592],"type":"Point"}
}