{
  "type": "Feature",
  "properties": {
    "iso:country":"AU",
    "sg:address":"128 Brunswick St",
    "sg:city":"Lismore",
    "sg:classifiers":[
        {
            "category":"Building & Trades",
            "subcategory":"Construction",
            "type":"Services"
        }
    ],
    "sg:phone":"+61 2 6621 2982",
    "sg:postcode":"2480",
    "sg:province":"NSW",
    "sg:tags":[
        "roof"
    ],
    "wof:name":"Aarox Plumbing",
    "wof:placetype":"venue"
},
  "geometry": {"coordinates":[153.293212891,-28.7982273102],"type":"Point"}
}