{
  "type": "Feature",
  "properties": {
    "addr:full":"23 Sudbury St Darra QLD 4076",
    "addr:housenumber":"23",
    "addr:postcode":"4076",
    "addr:street":"Sudbury St",
    "iso:country":"AU",
    "sg:address":"23 Sudbury St",
    "sg:city":"Darra",
    "sg:classifiers":[
        {
            "category":"Bars & Pubs",
            "subcategory":"Gay Bar",
            "type":"Food & Drink"
        }
    ],
    "sg:phone":"+61 7 3279 7111",
    "sg:postcode":"4076",
    "sg:province":"QLD",
    "sg:tags":[
        "plywood",
        "veneer"
    ],
    "wof:name":"Plywood & Panel Supplies Pty Ltd",
    "wof:placetype":"venue"
},
  "geometry": {"coordinates":[152.945404053,-27.5620174408],"type":"Point"}
}