{
  "type": "Feature",
  "properties": {
    "addr:full":"457 Upper Edward St Brisbane QLD 4000",
    "addr:housenumber":"457",
    "addr:postcode":"4000",
    "addr:street":"Upper Edward St",
    "iso:country":"AU",
    "sg:address":"457 Upper Edward St",
    "sg:city":"Brisbane",
    "sg:classifiers":[
        {
            "category":"Professional",
            "subcategory":"Accounting & Tax Preparation",
            "type":"Services"
        }
    ],
    "sg:phone":"+61 7 3839 4299",
    "sg:postcode":"4000",
    "sg:province":"QLD",
    "sg:tags":[
        "accountant",
        "auditor"
    ],
    "wof:name":"Harg & Company",
    "wof:placetype":"venue"
},
  "geometry": {"coordinates":[153.024490356,-27.4638061523],"type":"Point"}
}