{
  "type": "Feature",
  "properties": {
    "iso:country":"AU",
    "sg:address":"7 Railway Pl",
    "sg:city":"Bendigo",
    "sg:classifiers":[
        {
            "category":"Communications",
            "subcategory":"News Services",
            "type":"Services"
        }
    ],
    "sg:phone":"+61 3 5444 4400",
    "sg:postcode":"3550",
    "sg:province":"VIC",
    "sg:tags":[
        "information",
        "tourist",
        "attractions"
    ],
    "wof:name":"Discovery Science & Technology Centre",
    "wof:placetype":"venue"
},
  "geometry": {"coordinates":[144.280426025,-36.7670021057],"type":"Point"}
}