{
  "type": "Feature",
  "properties": {
    "iso:country":"AU",
    "sg:address":"22 Barter St",
    "sg:city":"Gympie",
    "sg:classifiers":[
        {
            "category":"Professional",
            "subcategory":"Employment Agencies",
            "type":"Services"
        }
    ],
    "sg:phone":"+61 7 5482 2328",
    "sg:postcode":"4570",
    "sg:province":"QLD",
    "wof:name":"Red Cross Employment Agency",
    "wof:placetype":"venue"
},
  "geometry": {"coordinates":[152.65739440900001,-26.1900482178],"type":"Point"}
}