{
  "type": "Feature",
  "properties": {
    "addr:full":"Unit 3/ 111 Freight Drv Somerton VIC 3062",
    "addr:housenumber":"/ 111",
    "addr:postcode":"3062",
    "addr:street":"Freight Drv",
    "iso:country":"AU",
    "sg:address":"Unit 3/ 111 Freight Drv",
    "sg:city":"Somerton",
    "sg:classifiers":[
        {
            "category":"Retail",
            "subcategory":"Auto Repair",
            "type":"Services"
        }
    ],
    "sg:phone":"+61 3 9305 3393",
    "sg:postcode":"3062",
    "sg:province":"VIC",
    "sg:tags":[
        "bus",
        "truck"
    ],
    "wof:name":"Online Transport Repairs P/L",
    "wof:placetype":"venue"
},
  "geometry": {"coordinates":[144.957473755,-37.6373329163],"type":"Point"}
}