{
  "type": "Feature",
  "properties": {
    "iso:country":"AU",
    "sg:address":"56 Therese Ave",
    "sg:city":"Mt Waverley",
    "sg:classifiers":[
        {
            "category":"Building & Trades",
            "subcategory":"Landscaping Services",
            "type":"Services"
        }
    ],
    "sg:phone":"+61 411 754 096",
    "sg:postcode":"3149",
    "sg:province":"VIC",
    "sg:tags":[
        "designer",
        "landscape",
        "contractor"
    ],
    "wof:name":"Bright Landscape",
    "wof:placetype":"venue"
},
  "geometry": {"coordinates":[145.12307739299999,-37.8929023743],"type":"Point"}
}