{
  "type": "Feature",
  "properties": {
    "addr:full":"108 Edenholme Rd Five Dock NSW 2046",
    "addr:housenumber":"108",
    "addr:postcode":"2046",
    "addr:street":"Edenholme Rd",
    "iso:country":"AU",
    "sg:address":"108 Edenholme Rd",
    "sg:city":"Five Dock",
    "sg:classifiers":[
        {
            "category":"Real Estate",
            "subcategory":"Architect",
            "type":"Services"
        }
    ],
    "sg:phone":"+61 2 9520 7750",
    "sg:postcode":"2046",
    "sg:province":"NSW",
    "sg:tags":[
        "building",
        "designer"
    ],
    "wof:name":"A P B Design Services",
    "wof:placetype":"venue"
},
  "geometry": {"coordinates":[151.133759,-33.856186],"type":"Point"}
}