{
  "type": "Feature",
  "properties": {
    "iso:country":"AU",
    "sg:address":"205- 207 Lonsdale St",
    "sg:city":"Melbourne",
    "sg:classifiers":[
        {
            "category":"Restaurant",
            "type":"Food & Drink"
        }
    ],
    "sg:phone":"+61 3 9650 4050",
    "sg:postcode":"3000",
    "sg:province":"VIC",
    "wof:name":"Dion Greek Restaurant & Bar",
    "wof:placetype":"venue"
},
  "geometry": {"coordinates":[144.966308594,-37.8112297058],"type":"Point"}
}