{
  "type": "Feature",
  "properties": {
    "iso:country":"AU",
    "sg:address":"1547 North Rd",
    "sg:city":"Ormond",
    "sg:classifiers":[
        {
            "category":"Home & Garden",
            "subcategory":"Carpets & Floor Coverings",
            "type":"Retail Goods"
        }
    ],
    "sg:phone":"+61 412 998 042",
    "sg:postcode":"3163",
    "sg:province":"VIC",
    "sg:tags":[
        "tile",
        "wall",
        "layer"
    ],
    "wof:name":"Offord Tiling",
    "wof:placetype":"venue"
},
  "geometry": {"coordinates":[145.05453491200001,-37.9057502747],"type":"Point"}
}