{
  "type": "Feature",
  "properties": {
    "addr:full":"Factory 3 Enterprise Way Bayswater North VIC 3153",
    "addr:housenumber":"3",
    "addr:postcode":"3153",
    "addr:street":"Enterprise Way",
    "iso:country":"AU",
    "sg:address":"Factory 3",
    "sg:city":"Enterprise Way Bayswater North",
    "sg:classifiers":[
        {
            "category":"Autos & Motor Vehicles",
            "subcategory":"Auto Supplies",
            "type":"Retail Goods"
        }
    ],
    "sg:phone":"+61 3 9738 1877",
    "sg:postcode":"3153",
    "sg:province":"VIC",
    "sg:tags":[
        "camper-trailers",
        "caravan",
        "equipment"
    ],
    "wof:name":"Canterbury Trailers",
    "wof:placetype":"venue"
},
  "geometry": {"coordinates":[145.279571533,-37.8257255554],"type":"Point"}
}