{
  "type": "Feature",
  "properties": {
    "addr:full":"136 Wee Waa St Boggabri NSW 2382",
    "addr:housenumber":"136",
    "addr:postcode":"2382",
    "addr:street":"Wee Waa St",
    "iso:country":"AU",
    "sg:address":"136 Wee Waa St",
    "sg:city":"Boggabri",
    "sg:classifiers":[
        {
            "category":"Autos & Motor Vehicles",
            "subcategory":"Auto Supplies",
            "type":"Retail Goods"
        }
    ],
    "sg:phone":"+61 2 6743 4383",
    "sg:postcode":"2382",
    "sg:province":"NSW",
    "sg:tags":[
        "oil",
        "spirit"
    ],
    "wof:name":"Shell Co Of Aust Distributors",
    "wof:placetype":"venue"
},
  "geometry": {"coordinates":[150.04122924800001,-30.7116012573],"type":"Point"}
}