{
  "type": "Feature",
  "properties": {
    "iso:country":"AU",
    "sg:address":"7/ 11 Forest View La",
    "sg:city":"Upper Ferntree Gully",
    "sg:classifiers":[
        {
            "category":"Education",
            "subcategory":"Music School",
            "type":"Public Place"
        }
    ],
    "sg:phone":"+61 3 9753 6569",
    "sg:postcode":"3156",
    "sg:province":"VIC",
    "sg:tags":[
        "teacher"
    ],
    "wof:name":"Donnelly K",
    "wof:placetype":"venue"
},
  "geometry": {"coordinates":[145.31486511200001,-37.9012374878],"type":"Point"}
}