{
  "type": "Feature",
  "properties": {
    "iso:country":"AU",
    "sg:address":"U5/ 6",
    "sg:city":"Tasman Way Byron Bay",
    "sg:classifiers":[
        {
            "category":"Organizations",
            "subcategory":"Professional Association",
            "type":"Services"
        }
    ],
    "sg:phone":"+61 2 6680 8174",
    "sg:postcode":"2481",
    "sg:province":"NSW",
    "sg:tags":[
        "web",
        "internet"
    ],
    "wof:name":"Webko Pty Ltd",
    "wof:placetype":"venue"
},
  "geometry": {"coordinates":[153.57992553700001,-28.6362438202],"type":"Point"}
}