{
  "type": "Feature",
  "properties": {
    "iso:country":"AU",
    "sg:address":"550 North Rd",
    "sg:city":"Ormond",
    "sg:classifiers":[
        {
            "category":"Home & Garden",
            "subcategory":"Furniture",
            "type":"Retail Goods"
        }
    ],
    "sg:phone":"+61 3 9578 8863",
    "sg:postcode":"3204",
    "sg:province":"VIC",
    "sg:tags":[
        "outdoor"
    ],
    "wof:name":"Early Settler",
    "wof:placetype":"venue"
},
  "geometry": {"coordinates":[145.039185,-37.903957],"type":"Point"}
}