{
  "type": "Feature",
  "properties": {
    "addr:full":"55 Cape St Heidelberg VIC 3084",
    "addr:housenumber":"55",
    "addr:postcode":"3084",
    "addr:street":"Cape St",
    "iso:country":"AU",
    "sg:address":"55 Cape St",
    "sg:city":"Heidelberg",
    "sg:classifiers":[
        {
            "category":"Education",
            "subcategory":"School",
            "type":"Public Place"
        }
    ],
    "sg:phone":"+61 3 9459 2963",
    "sg:postcode":"3084",
    "sg:province":"VIC",
    "sg:tags":[
        "co-educational"
    ],
    "wof:name":"St John's Primary",
    "wof:placetype":"venue"
},
  "geometry": {"coordinates":[145.06672668499999,-37.757522583],"type":"Point"}
}