{
  "type": "Feature",
  "properties": {
    "iso:country":"AU",
    "sg:address":"106 Marine Pde",
    "sg:city":"Kingscliff",
    "sg:classifiers":[
        {
            "category":"Food & Beverages",
            "subcategory":"Bakery",
            "type":"Retail Goods"
        }
    ],
    "sg:phone":"+61 2 6674 1959",
    "sg:postcode":"2487",
    "sg:province":"NSW",
    "sg:tags":[
        "baker"
    ],
    "wof:name":"Bazza's Bakery",
    "wof:placetype":"venue"
},
  "geometry": {"coordinates":[153.575683594,-28.2549495697],"type":"Point"}
}