{
  "type": "Feature",
  "properties": {
    "addr:full":"Shop 4/Gowan Plaza, 210 Kameruka Street Calamvale QLD 4116",
    "addr:housenumber":"shop 4 / gowan;210",
    "addr:postcode":"4116",
    "addr:street":"Kameruka Street",
    "iso:country":"AU",
    "sg:address":"Shop 4/Gowan Plaza, 210 Kameruka Street",
    "sg:city":"Calamvale",
    "sg:classifiers":[
        {
            "category":"Professional",
            "subcategory":"Computer Services",
            "type":"Services"
        }
    ],
    "sg:phone":"+61 7 3272 4897",
    "sg:postcode":"4116",
    "sg:province":"QLD",
    "sg:tags":[
        "equipment",
        "networking",
        "installation"
    ],
    "wof:name":"TechNet Services Australia Pty Ltd",
    "wof:placetype":"venue"
},
  "geometry": {"coordinates":[153.06198120100001,-27.6256217957],"type":"Point"}
}