{
  "type": "Feature",
  "properties": {
    "iso:country":"AU",
    "sg:address":"6 Andrew Crt",
    "sg:city":"Gawler West",
    "sg:classifiers":[
        {
            "category":"Professional",
            "subcategory":"Detective & Security Services",
            "type":"Services"
        }
    ],
    "sg:phone":"+61 8 8523 3606",
    "sg:postcode":"5118",
    "sg:province":"SA",
    "sg:tags":[
        "consultant",
        "system"
    ],
    "wof:name":"Prosys Australia",
    "wof:placetype":"venue"
},
  "geometry": {"coordinates":[138.73024000000001,-34.595623],"type":"Point"}
}