{
  "type": "Feature",
  "properties": {
    "addr:full":"39 Mentmore Ave Rosebery NSW 2018",
    "addr:housenumber":"39",
    "addr:postcode":"2018",
    "addr:street":"Mentmore Ave",
    "iso:country":"AU",
    "sg:address":"39 Mentmore Ave",
    "sg:city":"Rosebery",
    "sg:classifiers":[
        {
            "category":"Professional",
            "subcategory":"Detective & Security Services",
            "type":"Services"
        }
    ],
    "sg:phone":"+61 2 9698 9698",
    "sg:postcode":"2018",
    "sg:province":"NSW",
    "sg:tags":[
        "consultant",
        "system"
    ],
    "wof:name":"Direct Alarm Supplies",
    "wof:placetype":"venue"
},
  "geometry": {"coordinates":[151.20408630399999,-33.913848877],"type":"Point"}
}