{
  "type": "Feature",
  "properties": {
    "addr:full":"51 Railway Rd Mt Evelyn VIC 3796",
    "addr:housenumber":"51",
    "addr:postcode":"3796",
    "addr:street":"Railway Rd",
    "iso:country":"AU",
    "sg:address":"51 Railway Rd",
    "sg:city":"Mt Evelyn",
    "sg:classifiers":[
        {
            "category":"Building & Trades",
            "subcategory":"Construction",
            "type":"Services"
        }
    ],
    "sg:phone":"+61 3 9736 1875",
    "sg:postcode":"3796",
    "sg:province":"VIC",
    "sg:tags":[
        "mural"
    ],
    "wof:name":"Monks David",
    "wof:placetype":"venue"
},
  "geometry": {"coordinates":[145.37094116200001,-37.7929916382],"type":"Point"}
}