{
  "type": "Feature",
  "properties": {
    "addr:full":"7 Aspinall Pl Mulgrave NSW 2756",
    "addr:housenumber":"7",
    "addr:postcode":"2756",
    "addr:street":"Aspinall Pl",
    "iso:country":"AU",
    "sg:address":"7 Aspinall Pl",
    "sg:city":"Mulgrave",
    "sg:classifiers":[
        {
            "category":"Industrial Area",
            "type":"Public Place"
        }
    ],
    "sg:phone":"+61 2 4577 7259",
    "sg:postcode":"2756",
    "sg:province":"NSW",
    "sg:tags":[
        "rural",
        "shed"
    ],
    "wof:name":"Tri Steel",
    "wof:placetype":"venue"
},
  "geometry": {"coordinates":[150.834259033,-33.6243667603],"type":"Point"}
}