{
  "type": "Feature",
  "properties": {
    "iso:country":"AU",
    "sg:address":"724 A Glenhuntly Rd",
    "sg:city":"Caulfield South",
    "sg:classifiers":[
        {
            "category":"Education",
            "subcategory":"Kindergarten",
            "type":"Public Place"
        }
    ],
    "sg:phone":"+61 3 9523 1473",
    "sg:postcode":"3162",
    "sg:province":"VIC",
    "sg:tags":[
        "pre-schools"
    ],
    "wof:name":"Caulfield Primary Kindergarten",
    "wof:placetype":"venue"
},
  "geometry": {"coordinates":[144.99261474599999,-37.8833045959],"type":"Point"}
}