{
  "type": "Feature",
  "properties": {
    "addr:full":"15 Kamholtz Crt Ashmore QLD 4214",
    "addr:housenumber":"15",
    "addr:postcode":"4214",
    "addr:street":"Kamholtz Crt",
    "iso:country":"AU",
    "sg:address":"15 Kamholtz Crt",
    "sg:city":"Ashmore",
    "sg:classifiers":[
        {
            "category":"Retail",
            "subcategory":"Auto Repair",
            "type":"Services"
        }
    ],
    "sg:phone":"+61 7 5539 2039",
    "sg:postcode":"4214",
    "sg:province":"QLD",
    "sg:tags":[
        "wheel",
        "balancing",
        "alignment"
    ],
    "wof:name":"Truck-Trailer Laser Alignment",
    "wof:placetype":"venue"
},
  "geometry": {"coordinates":[153.358688355,-27.9863491058],"type":"Point"}
}