{
  "type": "Feature",
  "properties": {
    "addr:full":"337 Springvale Rd Springvale VIC 3171",
    "addr:housenumber":"337",
    "addr:postcode":"3171",
    "addr:street":"Springvale Rd",
    "iso:country":"AU",
    "sg:address":"337 Springvale Rd",
    "sg:city":"Springvale",
    "sg:classifiers":[
        {
            "category":"Banks & Credit Unions",
            "subcategory":"Financial Services",
            "type":"Services"
        }
    ],
    "sg:phone":"+61 3 9546 4777",
    "sg:postcode":"3171",
    "sg:province":"VIC",
    "sg:tags":[
        "financier"
    ],
    "wof:name":"Avco Financial Services Ltd",
    "wof:placetype":"venue"
},
  "geometry": {"coordinates":[145.15264892600001,-37.9513206482],"type":"Point"}
}