{
  "type": "Feature",
  "properties": {
    "iso:country":"AU",
    "sg:address":"71-73 Dandenong St",
    "sg:city":"Dandenong",
    "sg:classifiers":[
        {
            "category":"Professional",
            "type":"Services"
        }
    ],
    "sg:phone":"+61 3 9793 4811",
    "sg:postcode":"3175",
    "sg:province":"VIC",
    "sg:tags":[
        "shop",
        "fitting"
    ],
    "wof:name":"Impact Shopfitting Pty Ltd",
    "wof:placetype":"venue"
},
  "geometry": {"coordinates":[145.19731140100001,-37.9952316284],"type":"Point"}
}