{
  "type": "Feature",
  "properties": {
    "addr:full":"150 Bainbridge St Ormiston QLD 4160",
    "addr:housenumber":"150",
    "addr:postcode":"4160",
    "addr:street":"Bainbridge St",
    "iso:country":"AU",
    "sg:address":"150 Bainbridge St",
    "sg:city":"Ormiston",
    "sg:classifiers":[
        {
            "category":"Manufacturing",
            "subcategory":"Printing",
            "type":"Manufacturing & Wholesale Goods"
        }
    ],
    "sg:phone":"+61 7 3821 3692",
    "sg:postcode":"4160",
    "sg:province":"QLD",
    "sg:tags":[
        "wholesaler",
        "mfrs",
        "greeting",
        "card"
    ],
    "wof:name":"Sydney G. Hughes (Agents) P/L",
    "wof:placetype":"venue"
},
  "geometry": {"coordinates":[153.246826172,-27.5195331573],"type":"Point"}
}