{
  "type": "Feature",
  "properties": {
    "iso:country":"AU",
    "sg:address":"21 / 218 Padstow Rd",
    "sg:city":"Eight Mile Plains",
    "sg:classifiers":[
        {
            "category":"Retail",
            "subcategory":"Veterinary Services",
            "type":"Services"
        }
    ],
    "sg:phone":"+61 7 3841 2733",
    "sg:postcode":"4113",
    "sg:province":"QLD",
    "sg:tags":[
        "surgeon"
    ],
    "wof:name":"Eight Mile Plains Vet Surgery",
    "wof:placetype":"venue"
},
  "geometry": {"coordinates":[153.08709716800001,-27.574930191],"type":"Point"}
}