{
  "type": "Feature",
  "properties": {
    "addr:full":"51 Station St Engadine NSW 2233",
    "addr:housenumber":"51",
    "addr:postcode":"2233",
    "addr:street":"Station St",
    "iso:country":"AU",
    "sg:address":"51 Station St",
    "sg:city":"Engadine",
    "sg:classifiers":[
        {
            "category":"Professional",
            "type":"Services"
        }
    ],
    "sg:phone":"+61 2 9520 0628",
    "sg:postcode":"2233",
    "sg:province":"NSW",
    "sg:tags":[
        "overlocking",
        "rug",
        "carpet"
    ],
    "wof:name":"Engadine Carpet Centre",
    "wof:placetype":"venue"
},
  "geometry": {"coordinates":[151.013473511,-34.0660476685],"type":"Point"}
}