{
  "type": "Feature",
  "properties": {
    "iso:country":"AU",
    "sg:address":"The Performing Arts Centre 50 Little Malop St",
    "sg:city":"Geelong",
    "sg:classifiers":[
        {
            "category":"Arts & Performance",
            "subcategory":"Dance",
            "type":"Entertainment"
        }
    ],
    "sg:phone":"+61 3 9699 6761",
    "sg:postcode":"3220",
    "sg:province":"VIC",
    "sg:tags":[
        "theatrical",
        "ballet",
        "tuition"
    ],
    "wof:name":"Anne Carrick School Of Dance",
    "wof:placetype":"venue"
},
  "geometry": {"coordinates":[144.35656700000001,-38.14735],"type":"Point"}
}