{
  "type": "Feature",
  "properties": {
    "addr:full":"9 Belinda Crt Dandenong North VIC 3175",
    "addr:housenumber":"9",
    "addr:postcode":"3175",
    "addr:street":"Belinda Crt",
    "iso:country":"AU",
    "sg:address":"9 Belinda Crt",
    "sg:city":"Dandenong North",
    "sg:classifiers":[
        {
            "category":"Building & Trades",
            "subcategory":"Cleaning & Sanitation",
            "type":"Services"
        }
    ],
    "sg:phone":"+61 3 8707 2990",
    "sg:postcode":"3175",
    "sg:province":"VIC",
    "sg:tags":[
        "industrial",
        "commercial",
        "contractor"
    ],
    "wof:name":"NABS Cleaning Services",
    "wof:placetype":"venue"
},
  "geometry": {"coordinates":[145.21585082999999,-37.9562110901],"type":"Point"}
}