{
  "type": "Feature",
  "properties": {
    "addr:full":"44a Semaphore Rd Semaphore SA 5019",
    "addr:housenumber":"44a",
    "addr:postcode":"5019",
    "addr:street":"Semaphore Rd",
    "iso:country":"AU",
    "sg:address":"44a Semaphore Rd",
    "sg:city":"Semaphore",
    "sg:classifiers":[
        {
            "category":"Health Services",
            "subcategory":"Dentist",
            "type":"Services"
        }
    ],
    "sg:phone":"+61 8 8242 2458",
    "sg:postcode":"5019",
    "sg:province":"SA",
    "wof:name":"Dr Dustin Tien Pham",
    "wof:placetype":"venue"
},
  "geometry": {"coordinates":[138.48422241200001,-34.8391647339],"type":"Point"}
}