{
  "type": "Feature",
  "properties": {
    "iso:country":"AU",
    "sg:address":"Shop 2/ 203 Victoria Rd",
    "sg:city":"Gladesville",
    "sg:classifiers":[
        {
            "category":"Personal",
            "subcategory":"Beauty Salon",
            "type":"Services"
        }
    ],
    "sg:phone":"+61 2 9817 3144",
    "sg:postcode":"2111",
    "sg:province":"NSW",
    "wof:name":"Beau Visage Clinique De Beaute",
    "wof:placetype":"venue"
},
  "geometry": {"coordinates":[151.12713623100001,-33.8327598572],"type":"Point"}
}