{
  "type": "Feature",
  "properties": {
    "addr:full":"242- 244 Main St Bacchus Marsh VIC 3340",
    "addr:housenumber":"244",
    "addr:postcode":"3340",
    "addr:street":"Main St",
    "iso:country":"AU",
    "sg:address":"242- 244 Main St",
    "sg:city":"Bacchus Marsh",
    "sg:classifiers":[
        {
            "category":"Home & Garden",
            "subcategory":"Hardware",
            "type":"Retail Goods"
        }
    ],
    "sg:phone":"+61 3 5367 2277",
    "sg:postcode":"3340",
    "sg:province":"VIC",
    "sg:tags":[
        "plumber",
        "supply"
    ],
    "wof:name":"McCanns Plumbing Plus",
    "wof:placetype":"venue"
},
  "geometry": {"coordinates":[144.44494599999999,-37.676613],"type":"Point"}
}