{
  "type": "Feature",
  "properties": {
    "addr:full":"93- 97 Merrindale Drv Croydon VIC 3136",
    "addr:housenumber":"97",
    "addr:postcode":"3136",
    "addr:street":"Merrindale Drv",
    "iso:country":"AU",
    "sg:address":"93- 97 Merrindale Drv",
    "sg:city":"Croydon",
    "sg:classifiers":[
        {
            "category":"Military Area",
            "subcategory":"Air Force Base",
            "type":"Public Place"
        }
    ],
    "sg:phone":"+61 1300 232 476",
    "sg:postcode":"3136",
    "sg:province":"VIC",
    "sg:tags":[
        "fibre",
        "optic"
    ],
    "wof:name":"AFC Group Pty Ltd",
    "wof:placetype":"venue"
},
  "geometry": {"coordinates":[145.2890625,-37.8132667542],"type":"Point"}
}