{
  "type": "Feature",
  "properties": {
    "addr:full":"81 Benalla Rd Shepparton VIC 3630",
    "addr:housenumber":"81",
    "addr:postcode":"3630",
    "addr:street":"Benalla Rd",
    "iso:country":"AU",
    "sg:address":"81 Benalla Rd",
    "sg:city":"Shepparton",
    "sg:classifiers":[
        {
            "category":"Building & Trades",
            "subcategory":"Construction",
            "type":"Services"
        }
    ],
    "sg:phone":"+61 3 5831 6759",
    "sg:postcode":"3630",
    "sg:province":"VIC",
    "sg:tags":[
        "repairing",
        "window"
    ],
    "wof:name":"Stegbar",
    "wof:placetype":"venue"
},
  "geometry": {"coordinates":[145.42115783700001,-36.385055542],"type":"Point"}
}