{
  "type": "Feature",
  "properties": {
    "addr:full":"PO Box 19 Clifton Hill VIC 3068",
    "addr:postcode":"3068",
    "addr:street":"Hill",
    "iso:country":"AU",
    "sg:address":"PO Box 19",
    "sg:city":"Clifton Hill",
    "sg:classifiers":[
        {
            "category":"Professional",
            "subcategory":"Accounting & Tax Preparation",
            "type":"Services"
        }
    ],
    "sg:phone":"+61 417 389 739",
    "sg:postcode":"3068",
    "sg:province":"VIC",
    "sg:tags":[
        "accountant",
        "auditor"
    ],
    "wof:name":"BusinessMinders Consulting Pty Ltd",
    "wof:placetype":"venue"
},
  "geometry": {"coordinates":[144.994598389,-37.7913017273],"type":"Point"}
}