{
  "type": "Feature",
  "properties": {
    "addr:full":"11- 13 Sandilands St Bonalbo NSW 2469",
    "addr:housenumber":"13",
    "addr:postcode":"2469",
    "addr:street":"Sandilands St",
    "iso:country":"AU",
    "sg:address":"11- 13 Sandilands St",
    "sg:city":"Bonalbo",
    "sg:classifiers":[
        {
            "category":"Health Services",
            "subcategory":"Doctor",
            "type":"Services"
        }
    ],
    "sg:phone":"+61 2 6665 1216",
    "sg:postcode":"2469",
    "sg:province":"NSW",
    "sg:tags":[
        "medical",
        "practitioner"
    ],
    "wof:name":"Tierney T J",
    "wof:placetype":"venue"
},
  "geometry": {"coordinates":[152.61825561500001,-28.7343711853],"type":"Point"}
}