{
  "type": "Feature",
  "properties": {
    "addr:full":"4170 Pacific Hwy Loganholme QLD 4129",
    "addr:housenumber":"4170",
    "addr:postcode":"4129",
    "addr:street":"Pacific Hwy",
    "iso:country":"AU",
    "sg:address":"4170 Pacific Hwy",
    "sg:city":"Loganholme",
    "sg:classifiers":[
        {
            "category":"Travel",
            "subcategory":"Hotels & Motels",
            "type":"Entertainment"
        }
    ],
    "sg:phone":"+61 7 3209 8830",
    "sg:postcode":"4129",
    "sg:province":"QLD",
    "wof:name":"McNevins Logan Park Motel",
    "wof:placetype":"venue"
},
  "geometry": {"coordinates":[153.17984008799999,-27.6705970764],"type":"Point"}
}