{
  "type": "Feature",
  "properties": {
    "iso:country":"AU",
    "sg:address":"4 Prospect St",
    "sg:city":"Mackay",
    "sg:classifiers":[
        {
            "category":"Retail",
            "subcategory":"Auto Repair",
            "type":"Services"
        }
    ],
    "sg:phone":"+61 7 4957 3900",
    "sg:postcode":"4740",
    "sg:province":"QLD",
    "sg:tags":[
        "beater",
        "painter",
        "panel"
    ],
    "wof:name":"A & L Smash Repairs",
    "wof:placetype":"venue"
},
  "geometry": {"coordinates":[149.189774,-21.148241],"type":"Point"}
}