{
  "type": "Feature",
  "properties": {
    "addr:full":"140 Invermay Rd Launceston TAS 7250",
    "addr:housenumber":"140",
    "addr:postcode":"7250",
    "addr:street":"Invermay Rd",
    "iso:country":"AU",
    "sg:address":"140 Invermay Rd",
    "sg:city":"Launceston",
    "sg:classifiers":[
        {
            "category":"Autos & Motor Vehicles",
            "subcategory":"Auto Supplies",
            "type":"Retail Goods"
        }
    ],
    "sg:phone":"+61 3 6326 2900",
    "sg:postcode":"7250",
    "sg:province":"TAS",
    "sg:tags":[
        "battery",
        "automotive"
    ],
    "wof:name":"Exide Batteries",
    "wof:placetype":"venue"
},
  "geometry": {"coordinates":[147.13345336899999,-41.4139404297],"type":"Point"}
}