{
  "type": "Feature",
  "properties": {
    "iso:country":"AU",
    "sg:address":"69 Martins La",
    "sg:city":"View Bank",
    "sg:classifiers":[
        {
            "category":"Fast Food",
            "type":"Food & Drink"
        }
    ],
    "sg:phone":"+61 3 9455 1123",
    "sg:postcode":"3084",
    "sg:province":"VIC",
    "sg:tags":[
        "away",
        "take"
    ],
    "wof:name":"Viewbank Pizza",
    "wof:placetype":"venue"
},
  "geometry": {"coordinates":[145.09083557100001,-37.7326889038],"type":"Point"}
}