{
  "type": "Feature",
  "properties": {
    "addr:full":"5 Green Plateau Rd Springfield NSW 2250",
    "addr:housenumber":"5",
    "addr:postcode":"2250",
    "addr:street":"Green Plateau Rd",
    "iso:country":"AU",
    "sg:address":"5 Green Plateau Rd",
    "sg:city":"Springfield",
    "sg:classifiers":[
        {
            "category":"Social Services",
            "subcategory":"Adult Care",
            "type":"Services"
        }
    ],
    "sg:phone":"+61 2 4323 2344",
    "sg:postcode":"2250",
    "sg:province":"NSW",
    "sg:tags":[
        "towing"
    ],
    "wof:name":"Terrigal Motors",
    "wof:placetype":"venue"
},
  "geometry": {"coordinates":[151.36106872600001,-33.430015564],"type":"Point"}
}