{
  "type": "Feature",
  "properties": {
    "addr:full":"141 Charleston Rd Bendigo VIC 3550",
    "addr:housenumber":"141",
    "addr:postcode":"3550",
    "addr:street":"Charleston Rd",
    "iso:country":"AU",
    "sg:address":"141 Charleston Rd",
    "sg:city":"Bendigo",
    "sg:classifiers":[
        {
            "category":"Transit Center",
            "subcategory":"Freight",
            "type":"Transportation"
        }
    ],
    "sg:phone":"+61 3 5441 7666",
    "sg:postcode":"3550",
    "sg:province":"VIC",
    "sg:tags":[
        "equipment",
        "transport",
        "road",
        "vehicle"
    ],
    "wof:name":"Colrain Bendigo",
    "wof:placetype":"venue"
},
  "geometry": {"coordinates":[144.294830322,-36.7515716553],"type":"Point"}
}