{
  "type": "Feature",
  "properties": {
    "addr:full":"67 Dawson Pde Grovely QLD 4054",
    "addr:housenumber":"67",
    "addr:postcode":"4054",
    "addr:street":"Dawson Pde",
    "iso:country":"AU",
    "sg:address":"67 Dawson Pde",
    "sg:city":"Grovely",
    "sg:classifiers":[
        {
            "category":"Social Services",
            "subcategory":"Child Care",
            "type":"Services"
        }
    ],
    "sg:phone":"+61 7 3354 3904",
    "sg:postcode":"4054",
    "sg:province":"QLD",
    "wof:name":"St William Outside School Hours Care Program",
    "wof:placetype":"venue"
},
  "geometry": {"coordinates":[152.96241760300001,-27.4080638885],"type":"Point"}
}