{
  "type": "Feature",
  "properties": {
    "iso:country":"AU",
    "sg:address":"4/ 57 Harvey St North",
    "sg:city":"Eagle Farm",
    "sg:classifiers":[
        {
            "category":"Professional",
            "type":"Services"
        }
    ],
    "sg:phone":"+61 7 3268 1845",
    "sg:postcode":"4009",
    "sg:province":"QLD",
    "sg:tags":[
        "coating",
        "powder"
    ],
    "wof:name":"Mulholland Powder Coating Services Pty Ltd",
    "wof:placetype":"venue"
},
  "geometry": {"coordinates":[153.09217834500001,-27.4337673187],"type":"Point"}
}