{
  "type": "Feature",
  "properties": {
    "addr:full":"Unit 2/ 2 North Rocks Rd North Parramatta NSW 2151",
    "addr:postcode":"2151",
    "addr:street":"North Rocks Rd",
    "iso:country":"AU",
    "sg:address":"Unit 2/ 2 North Rocks Rd",
    "sg:city":"North Parramatta",
    "sg:classifiers":[
        {
            "category":"Building & Trades",
            "subcategory":"Construction",
            "type":"Services"
        }
    ],
    "sg:phone":"+61 2 9890 3577",
    "sg:postcode":"2151",
    "sg:province":"NSW",
    "sg:tags":[
        "window",
        "tinting"
    ],
    "wof:name":"Australian Tint Wizard",
    "wof:placetype":"venue"
},
  "geometry": {"coordinates":[151.000366211,-33.7933692932],"type":"Point"}
}