{
  "type": "Feature",
  "properties": {
    "iso:country":"AU",
    "sg:address":"Shed 2/ 13 Toohey St",
    "sg:city":"Portsmith",
    "sg:classifiers":[
        {
            "category":"Building & Trades",
            "subcategory":"Construction",
            "type":"Services"
        }
    ],
    "sg:phone":"+61 7 4035 5226",
    "sg:postcode":"4870",
    "sg:province":"QLD",
    "sg:tags":[
        "contractor"
    ],
    "wof:name":"M V Design & Construction",
    "wof:placetype":"venue"
},
  "geometry": {"coordinates":[145.761474609,-16.9410953522],"type":"Point"}
}