{
  "type": "Feature",
  "properties": {
    "iso:country":"AU",
    "sg:address":"301 Somerville Rd",
    "sg:city":"Footscray West",
    "sg:classifiers":[
        {
            "category":"Retail",
            "subcategory":"Auto Repair",
            "type":"Services"
        }
    ],
    "sg:phone":"+61 3 9314 5840",
    "sg:postcode":"3012",
    "sg:province":"VIC",
    "sg:tags":[
        "testing",
        "inspection",
        "motor",
        "vehicle"
    ],
    "wof:name":"Grant Hall Motors",
    "wof:placetype":"venue"
},
  "geometry": {"coordinates":[144.872955322,-37.8117256165],"type":"Point"}
}