{
  "type": "Feature",
  "properties": {
    "addr:full":"10 Railway Pde Eastwood NSW 2122",
    "addr:housenumber":"10",
    "addr:postcode":"2122",
    "addr:street":"Railway Pde",
    "iso:country":"AU",
    "sg:address":"10 Railway Pde",
    "sg:city":"Eastwood",
    "sg:classifiers":[
        {
            "category":"Personal",
            "subcategory":"Beauty Salon",
            "type":"Services"
        }
    ],
    "sg:phone":"+61 2 9804 7083",
    "sg:postcode":"2122",
    "sg:province":"NSW",
    "sg:tags":[
        "hairdresser"
    ],
    "wof:name":"Silk Flowery Hair Salon",
    "wof:placetype":"venue"
},
  "geometry": {"coordinates":[151.082595825,-33.7905693054],"type":"Point"}
}