{
  "type": "Feature",
  "properties": {
    "addr:full":"47 London St Port Lincoln SA 5606",
    "addr:housenumber":"47",
    "addr:postcode":"5606",
    "addr:street":"London St",
    "iso:country":"AU",
    "sg:address":"47 London St",
    "sg:city":"Port Lincoln",
    "sg:classifiers":[
        {
            "category":"Professional",
            "subcategory":"Art Services",
            "type":"Services"
        }
    ],
    "sg:phone":"+61 8 8682 1527",
    "sg:postcode":"5606",
    "sg:province":"SA",
    "sg:tags":[
        "picture",
        "frame",
        "framing"
    ],
    "wof:name":"Lincoln Custom Framing",
    "wof:placetype":"venue"
},
  "geometry": {"coordinates":[135.871994,-34.725101],"type":"Point"}
}