{
  "type": "Feature",
  "properties": {
    "iso:country":"AU",
    "sg:address":"PO Box 34",
    "sg:city":"Nar Nar Goon",
    "sg:classifiers":[
        {
            "category":"Farming",
            "subcategory":"Farm",
            "type":"Manufacturing & Wholesale Goods"
        }
    ],
    "sg:phone":"+61 3 5942 5226",
    "sg:postcode":"3812",
    "sg:province":"VIC",
    "sg:tags":[
        "farmer"
    ],
    "wof:name":"Houlihans Mail Order",
    "wof:placetype":"venue"
},
  "geometry": {"coordinates":[145.543762,-38.066029],"type":"Point"}
}