{
  "type": "Feature",
  "properties": {
    "addr:full":"2 Cowper St Footscray VIC 3011",
    "addr:housenumber":"2",
    "addr:postcode":"3011",
    "addr:street":"Cowper St",
    "iso:country":"AU",
    "sg:address":"2 Cowper St",
    "sg:city":"Footscray",
    "sg:classifiers":[
        {
            "category":"Building & Trades",
            "subcategory":"Landscaping Services",
            "type":"Services"
        }
    ],
    "sg:phone":"+61 3 9689 2235",
    "sg:postcode":"3011",
    "sg:province":"VIC",
    "sg:tags":[
        "gardener"
    ],
    "wof:name":"Green Angel Garden Care",
    "wof:placetype":"venue"
},
  "geometry": {"coordinates":[144.90516662600001,-37.7978897095],"type":"Point"}
}