{
  "type": "Feature",
  "properties": {
    "addr:full":"4 Diane Crt Somerville VIC 3912",
    "addr:housenumber":"4",
    "addr:postcode":"3912",
    "addr:street":"Diane Crt",
    "iso:country":"AU",
    "sg:address":"4 Diane Crt",
    "sg:city":"Somerville",
    "sg:classifiers":[
        {
            "category":"Building & Trades",
            "subcategory":"Construction",
            "type":"Services"
        }
    ],
    "sg:phone":"+61 418 544 082",
    "sg:postcode":"3912",
    "sg:province":"VIC",
    "sg:tags":[
        "earth",
        "excavating",
        "moving",
        "contractor"
    ],
    "wof:name":"Scott's Excavations Plus Pty Ltd",
    "wof:placetype":"venue"
},
  "geometry": {"coordinates":[145.16368102999999,-38.223526001],"type":"Point"}
}