{
  "type": "Feature",
  "properties": {
    "addr:full":"Konkerberry Drv Kununurra WA 6743",
    "addr:postcode":"6743",
    "addr:street":"Konkerberry Drv",
    "iso:country":"AU",
    "sg:address":"Konkerberry Drv",
    "sg:city":"Kununurra",
    "sg:classifiers":[
        {
            "category":"Communications",
            "subcategory":"Film & Video Production",
            "type":"Services"
        }
    ],
    "sg:phone":"+61 8 9168 2619",
    "sg:postcode":"6743",
    "sg:province":"WA",
    "sg:tags":[
        "dvd",
        "library"
    ],
    "wof:name":"Video 2000",
    "wof:placetype":"venue"
},
  "geometry": {"coordinates":[128.740631103,-15.772851944],"type":"Point"}
}