{
  "type": "Feature",
  "properties": {
    "addr:full":"36 Quambone St Worongary QLD 4213",
    "addr:housenumber":"36",
    "addr:postcode":"4213",
    "addr:street":"Quambone St",
    "iso:country":"AU",
    "sg:address":"36 Quambone St",
    "sg:city":"Worongary",
    "sg:classifiers":[
        {
            "category":"Building & Trades",
            "subcategory":"Plumbing",
            "type":"Services"
        }
    ],
    "sg:phone":"+61 7 5530 2912",
    "sg:postcode":"4213",
    "sg:province":"QLD",
    "sg:tags":[
        "plumber",
        "gasfitters"
    ],
    "wof:name":"Citylink Plumbing Services",
    "wof:placetype":"venue"
},
  "geometry": {"coordinates":[153.34535217300001,-28.0415096283],"type":"Point"}
}