{
  "type": "Feature",
  "properties": {
    "addr:full":"52 Pioneer Drv Maiden Gully VIC 3551",
    "addr:housenumber":"52",
    "addr:postcode":"3551",
    "addr:street":"Pioneer Drv",
    "iso:country":"AU",
    "sg:address":"52 Pioneer Drv",
    "sg:city":"Maiden Gully",
    "sg:classifiers":[
        {
            "category":"Professional",
            "subcategory":"Accounting & Tax Preparation",
            "type":"Services"
        }
    ],
    "sg:phone":"+61 3 5449 7087",
    "sg:postcode":"3551",
    "sg:province":"VIC",
    "sg:tags":[
        "accountant",
        "auditor"
    ],
    "wof:name":"Dean Primmer Accounting",
    "wof:placetype":"venue"
},
  "geometry": {"coordinates":[144.222579956,-36.7519569397],"type":"Point"}
}