{
  "type": "Feature",
  "properties": {
    "iso:country":"AU",
    "sg:address":"Cnr Duckworth & Hill St",
    "sg:city":"Garbutt",
    "sg:classifiers":[
        {
            "category":"Home & Garden",
            "subcategory":"Building Materials",
            "type":"Retail Goods"
        }
    ],
    "sg:phone":"+61 7 4725 2200",
    "sg:postcode":"4814",
    "sg:province":"QLD",
    "sg:tags":[
        "plaster",
        "plasterboard",
        "supply"
    ],
    "wof:name":"CSR Gyprock",
    "wof:placetype":"venue"
},
  "geometry": {"coordinates":[146.76091,-19.263388],"type":"Point"}
}