{
  "type": "Feature",
  "properties": {
    "iso:country":"AU",
    "sg:address":"Gowings Bld, 45 Market St, 7th Floor, Suite 707",
    "sg:city":"Sydney",
    "sg:classifiers":[
        {
            "category":"Personal",
            "subcategory":"Beauty Salon",
            "type":"Services"
        }
    ],
    "sg:phone":"+61 2 9261 1885",
    "sg:postcode":"2000",
    "sg:province":"NSW",
    "wof:name":"Miki's Beauty Salon",
    "wof:placetype":"venue"
},
  "geometry": {"coordinates":[151.20484924300001,-33.8805923462],"type":"Point"}
}