{
  "type": "Feature",
  "properties": {
    "addr:full":"218 Camberwell Rd Hawthorn East VIC 3123",
    "addr:housenumber":"218",
    "addr:postcode":"3123",
    "addr:street":"Camberwell Rd",
    "iso:country":"AU",
    "sg:address":"218 Camberwell Rd",
    "sg:city":"Hawthorn East",
    "sg:classifiers":[
        {
            "category":"Health Services",
            "subcategory":"Optometrist",
            "type":"Services"
        }
    ],
    "sg:phone":"+61 3 9882 1140",
    "sg:postcode":"3123",
    "sg:province":"VIC",
    "wof:name":"Anthony K.N. Smith",
    "wof:placetype":"venue"
},
  "geometry": {"coordinates":[145.05633544899999,-37.8311424255],"type":"Point"}
}