{
  "type": "Feature",
  "properties": {
    "addr:full":"533 Princes Drv Morwell VIC 3840",
    "addr:housenumber":"533",
    "addr:postcode":"3840",
    "addr:street":"Princes Drv",
    "iso:country":"AU",
    "sg:address":"533 Princes Drv",
    "sg:city":"Morwell",
    "sg:classifiers":[
        {
            "category":"Manufacturing",
            "subcategory":"Retail Goods",
            "type":"Manufacturing & Wholesale Goods"
        }
    ],
    "sg:phone":"+61 3 5134 8899",
    "sg:postcode":"3840",
    "sg:province":"VIC",
    "sg:tags":[
        "merchant",
        "pump",
        "mfrs"
    ],
    "wof:name":"Central Gippsland Mowers & Chainsaws Pty Ltd",
    "wof:placetype":"venue"
},
  "geometry": {"coordinates":[146.43443298299999,-38.2346191406],"type":"Point"}
}