{
  "type": "Feature",
  "properties": {
    "addr:full":"Cnr The River & Uranus Rds Revesby NSW 2212",
    "addr:postcode":"2212",
    "addr:street":"Cnr The",
    "iso:country":"AU",
    "sg:address":"Cnr The River & Uranus Rds",
    "sg:city":"Revesby",
    "sg:classifiers":[
        {
            "category":"Social Services",
            "subcategory":"Adult Care",
            "type":"Services"
        }
    ],
    "sg:phone":"+61 2 9771 2335",
    "sg:postcode":"2212",
    "sg:province":"NSW",
    "sg:tags":[
        "towing"
    ],
    "wof:name":"McQ Smash Repairs & Towing",
    "wof:placetype":"venue"
},
  "geometry": {"coordinates":[151.01676900000001,-33.956932],"type":"Point"}
}