{
  "type": "Feature",
  "properties": {
    "addr:full":"Shop 1122A Westfield Helensvale Town Centre Drv Helensvale QLD 4212",
    "addr:housenumber":"1122a",
    "addr:postcode":"4212",
    "addr:street":"Westfield Helensvale Town Centre Drv",
    "iso:country":"AU",
    "sg:address":"Shop 1122A Westfield Helensvale Town Centre Drv",
    "sg:city":"Helensvale",
    "sg:classifiers":[
        {
            "category":"Fast Food",
            "type":"Food & Drink"
        }
    ],
    "sg:phone":"+61 7 5519 3133",
    "sg:postcode":"4212",
    "sg:province":"QLD",
    "sg:tags":[
        "away",
        "take"
    ],
    "wof:name":"Domino's Pizza",
    "wof:placetype":"venue"
},
  "geometry": {"coordinates":[153.338256836,-27.9241104126],"type":"Point"}
}