{
  "type": "Feature",
  "properties": {
    "addr:full":"4 Collins St Belmont VIC 3216",
    "addr:housenumber":"4",
    "addr:postcode":"3216",
    "addr:street":"Collins St",
    "iso:country":"AU",
    "sg:address":"4 Collins St",
    "sg:city":"Belmont",
    "sg:classifiers":[
        {
            "category":"Retail",
            "subcategory":"Laundry & Dry Cleaning",
            "type":"Services"
        }
    ],
    "sg:phone":"+61 448 344 005",
    "sg:postcode":"3216",
    "sg:province":"VIC",
    "wof:name":"C T Melville Laundry Service",
    "wof:placetype":"venue"
},
  "geometry": {"coordinates":[144.34315490700001,-38.1698646545],"type":"Point"}
}