{
  "type": "Feature",
  "properties": {
    "iso:country":"AU",
    "sg:address":"2 Gillies St",
    "sg:city":"Mitcham",
    "sg:classifiers":[
        {
            "category":"Building & Trades",
            "subcategory":"Landscaping Services",
            "type":"Services"
        }
    ],
    "sg:phone":"+61 423 689 577",
    "sg:postcode":"3132",
    "sg:province":"VIC",
    "sg:tags":[
        "designer",
        "landscape",
        "contractor"
    ],
    "wof:name":"Super Synthetic Grass",
    "wof:placetype":"venue"
},
  "geometry": {"coordinates":[145.18902587900001,-37.8141784668],"type":"Point"}
}