{
  "type": "Feature",
  "properties": {
    "iso:country":"AU",
    "sg:address":"PO Box 639",
    "sg:city":"Sutherland Private Box",
    "sg:classifiers":[
        {
            "category":"Banks & Credit Unions",
            "subcategory":"Financial Services",
            "type":"Services"
        }
    ],
    "sg:phone":"+61 2 9521 6699",
    "sg:postcode":"1499",
    "sg:province":"NSW",
    "sg:tags":[
        "system",
        "alerting"
    ],
    "wof:name":"Allamber Alarms",
    "wof:placetype":"venue"
},
  "geometry": {"coordinates":[151.057953,-34.031429],"type":"Point"}
}