{
  "type": "Feature",
  "properties": {
    "addr:full":"Level 1 12 Howard Ave Dee Why NSW 2099",
    "addr:housenumber":"12",
    "addr:postcode":"2099",
    "addr:street":"Howard Ave",
    "iso:country":"AU",
    "sg:address":"Level 1 12 Howard Ave",
    "sg:city":"Dee Why",
    "sg:classifiers":[
        {
            "category":"Professional",
            "subcategory":"Accounting & Tax Preparation",
            "type":"Services"
        }
    ],
    "sg:phone":"+61 2 9971 9632",
    "sg:postcode":"2099",
    "sg:province":"NSW",
    "sg:tags":[
        "accountant",
        "auditor"
    ],
    "wof:name":"Isaacs Page & Co",
    "wof:placetype":"venue"
},
  "geometry": {"coordinates":[151.28788757300001,-33.7525100708],"type":"Point"}
}