{
  "type": "Feature",
  "properties": {
    "addr:full":"434 Montague Rd Modbury North SA 5092",
    "addr:housenumber":"434",
    "addr:postcode":"5092",
    "addr:street":"Montague Rd",
    "iso:country":"AU",
    "sg:address":"434 Montague Rd",
    "sg:city":"Modbury North",
    "sg:classifiers":[
        {
            "category":"Banks & Credit Unions",
            "subcategory":"Investment Brokerage",
            "type":"Services"
        }
    ],
    "sg:phone":"+61 8 8395 3928",
    "sg:postcode":"5092",
    "sg:province":"SA",
    "wof:name":"Commonwealth Financial Planning",
    "wof:placetype":"venue"
},
  "geometry": {"coordinates":[138.672607422,-34.8287582397],"type":"Point"}
}