{
  "type": "Feature",
  "properties": {
    "addr:full":"81 Glenrock Drv Rasmussen QLD 4815",
    "addr:housenumber":"81",
    "addr:postcode":"4815",
    "addr:street":"Glenrock Drv",
    "iso:country":"AU",
    "sg:address":"81 Glenrock Drv",
    "sg:city":"Rasmussen",
    "sg:classifiers":[
        {
            "category":"Utilities",
            "subcategory":"Electric",
            "type":"Services"
        }
    ],
    "sg:phone":"+61 7 4723 1539",
    "sg:postcode":"4815",
    "sg:province":"QLD",
    "sg:tags":[
        "electrical",
        "contractor"
    ],
    "wof:name":"Trilectric",
    "wof:placetype":"venue"
},
  "geometry": {"coordinates":[146.71847500000001,-19.345842],"type":"Point"}
}