{
  "type": "Feature",
  "properties": {
    "addr:full":"12 Ricketts Rd Mt Waverley VIC 3149",
    "addr:housenumber":"12",
    "addr:postcode":"3149",
    "addr:street":"Ricketts Rd",
    "iso:country":"AU",
    "sg:address":"12 Ricketts Rd",
    "sg:city":"Mt Waverley",
    "sg:classifiers":[
        {
            "category":"Cafe",
            "type":"Food & Drink"
        }
    ],
    "sg:phone":"+61 3 9558 6407",
    "sg:postcode":"3149",
    "sg:province":"VIC",
    "wof:name":"Feeder Cafe Bar",
    "wof:placetype":"venue"
},
  "geometry": {"coordinates":[145.136276245,-37.894985199],"type":"Point"}
}