{
  "type": "Feature",
  "properties": {
    "iso:country":"AU",
    "sg:address":"2130 Heidelberg-Kinglake Rd",
    "sg:city":"St Andrews",
    "sg:classifiers":[
        {
            "category":"Farming",
            "subcategory":"Vineyard",
            "type":"Manufacturing & Wholesale Goods"
        }
    ],
    "sg:phone":"+61 3 9710 1155",
    "sg:postcode":"3761",
    "sg:province":"VIC",
    "sg:tags":[
        "winery"
    ],
    "wof:name":"Lance Family Wines Pty Ltd",
    "wof:placetype":"venue"
},
  "geometry": {"coordinates":[145.28790283199999,-37.5792198181],"type":"Point"}
}