{
  "type": "Feature",
  "properties": {
    "addr:full":"Sampsons Rd Polkemmet VIC 3401",
    "addr:postcode":"3401",
    "addr:street":"Sampsons Rd",
    "iso:country":"AU",
    "sg:address":"Sampsons Rd",
    "sg:city":"Polkemmet",
    "sg:classifiers":[
        {
            "category":"Farming",
            "subcategory":"Farm",
            "type":"Manufacturing & Wholesale Goods"
        }
    ],
    "sg:phone":"+61 3 5384 2274",
    "sg:postcode":"3401",
    "sg:province":"VIC",
    "sg:tags":[
        "farmer"
    ],
    "wof:name":"Sampson C E & B H",
    "wof:placetype":"venue"
},
  "geometry": {"coordinates":[142.018966675,-36.6198768616],"type":"Point"}
}