{
  "type": "Feature",
  "properties": {
    "iso:country":"AU",
    "sg:address":"Attwell St",
    "sg:city":"Landsdale",
    "sg:classifiers":[
        {
            "category":"Fast Food",
            "type":"Food & Drink"
        }
    ],
    "sg:phone":"+61 8 9309 2347",
    "sg:postcode":"6065",
    "sg:province":"WA",
    "sg:tags":[
        "away",
        "take"
    ],
    "wof:name":"Attwells Lunch Bar",
    "wof:placetype":"venue"
},
  "geometry": {"coordinates":[115.84764099100001,-31.8035907745],"type":"Point"}
}