{
  "type": "Feature",
  "properties": {
    "addr:full":"1081 Victoria Rd West Ryde NSW 2114",
    "addr:housenumber":"1081",
    "addr:postcode":"2114",
    "addr:street":"Victoria Rd",
    "iso:country":"AU",
    "sg:address":"1081 Victoria Rd",
    "sg:city":"West Ryde",
    "sg:classifiers":[
        {
            "category":"Recreation",
            "subcategory":"Fishing",
            "type":"Entertainment"
        }
    ],
    "sg:phone":"+61 2 9874 4299",
    "sg:postcode":"2114",
    "sg:province":"NSW",
    "sg:tags":[
        "bait"
    ],
    "wof:name":"Sydney Fishing Tackle",
    "wof:placetype":"venue"
},
  "geometry": {"coordinates":[151.08450317399999,-33.8069725037],"type":"Point"}
}