{
  "type": "Feature",
  "properties": {
    "addr:full":"733 Ann St Fortitude Valley QLD 4006",
    "addr:housenumber":"733",
    "addr:postcode":"4006",
    "addr:street":"Ann St",
    "iso:country":"AU",
    "sg:address":"733 Ann St",
    "sg:city":"Fortitude Valley",
    "sg:classifiers":[
        {
            "category":"Autos & Motor Vehicles",
            "subcategory":"Automobile Sales",
            "type":"Retail Goods"
        }
    ],
    "sg:phone":"+61 7 3248 9489",
    "sg:postcode":"4006",
    "sg:province":"QLD",
    "sg:tags":[
        "car",
        "new"
    ],
    "wof:name":"Austral Volvo",
    "wof:placetype":"venue"
},
  "geometry": {"coordinates":[153.03648376500001,-27.4571800232],"type":"Point"}
}