{
  "type": "Feature",
  "properties": {
    "iso:country":"AU",
    "sg:address":"4 Draper St",
    "sg:city":"Kadina",
    "sg:classifiers":[
        {
            "category":"Banks & Credit Unions",
            "subcategory":"Bank",
            "type":"Services"
        }
    ],
    "sg:phone":"+61 8 8821 3077",
    "sg:postcode":"5554",
    "sg:province":"SA",
    "sg:tags":[
        "broker",
        "mortgage"
    ],
    "wof:name":"Matrix Finance",
    "wof:placetype":"venue"
},
  "geometry": {"coordinates":[137.711791992,-33.9634017944],"type":"Point"}
}