{
  "type": "Feature",
  "properties": {
    "iso:country":"AU",
    "sg:address":"94 Princes St",
    "sg:city":"Cundletown",
    "sg:classifiers":[
        {
            "category":"Education",
            "subcategory":"School",
            "type":"Public Place"
        }
    ],
    "sg:phone":"+61 2 6553 8844",
    "sg:postcode":"2430",
    "sg:province":"NSW",
    "wof:name":"Manning Valley Anglican College",
    "wof:placetype":"venue"
},
  "geometry": {"coordinates":[152.523529,-31.902323],"type":"Point"}
}