{
  "type": "Feature",
  "properties": {
    "addr:full":"7 Manchester St Victoria Park WA 6100",
    "addr:housenumber":"7",
    "addr:postcode":"6100",
    "addr:street":"Manchester St",
    "iso:country":"AU",
    "sg:address":"7 Manchester St",
    "sg:city":"Victoria Park",
    "sg:classifiers":[
        {
            "category":"Health Services",
            "subcategory":"Doctor",
            "type":"Services"
        }
    ],
    "sg:phone":"+61 8 9362 6011",
    "sg:postcode":"6100",
    "sg:province":"WA",
    "sg:tags":[
        "podiatrist"
    ],
    "wof:name":"Just For Feet Podiatry",
    "wof:placetype":"venue"
},
  "geometry": {"coordinates":[115.897521973,-31.9781188965],"type":"Point"}
}