{
  "type": "Feature",
  "properties": {
    "addr:full":"63 Swan St Richmond VIC 3121",
    "addr:housenumber":"63",
    "addr:postcode":"3121",
    "addr:street":"Swan St",
    "iso:country":"AU",
    "sg:address":"63 Swan St",
    "sg:city":"Richmond",
    "sg:classifiers":[
        {
            "category":"Fast Food",
            "type":"Food & Drink"
        }
    ],
    "sg:phone":"+61 3 9428 9581",
    "sg:postcode":"3121",
    "sg:province":"VIC",
    "sg:tags":[
        "away",
        "take"
    ],
    "wof:name":"Samanthas Pizza Heaven",
    "wof:placetype":"venue"
},
  "geometry": {"coordinates":[144.993011475,-37.8249931335],"type":"Point"}
}