{
  "type": "Feature",
  "properties": {
    "addr:full":"6 Delisle Ave Shepparton VIC 3630",
    "addr:housenumber":"6",
    "addr:postcode":"3630",
    "addr:street":"Delisle Ave",
    "iso:country":"AU",
    "sg:address":"6 Delisle Ave",
    "sg:city":"Shepparton",
    "sg:classifiers":[
        {
            "category":"Building & Trades",
            "subcategory":"Pest Control",
            "type":"Services"
        }
    ],
    "sg:phone":"+61 3 5821 7225",
    "sg:postcode":"3630",
    "sg:province":"VIC",
    "wof:name":"Total Pest Control",
    "wof:placetype":"venue"
},
  "geometry": {"coordinates":[145.37875366200001,-36.3604812622],"type":"Point"}
}