{
  "type": "Feature",
  "properties": {
    "addr:full":"Suite 1, 74-76 Wyndham St Alexandria NSW 2015",
    "addr:housenumber":"74-76",
    "addr:postcode":"2015",
    "addr:street":"Wyndham St",
    "iso:country":"AU",
    "sg:address":"Suite 1, 74-76 Wyndham St",
    "sg:city":"Alexandria",
    "sg:classifiers":[
        {
            "category":"Recreation",
            "subcategory":"Boat Charter",
            "type":"Entertainment"
        }
    ],
    "sg:phone":"+61 1300 550 903",
    "sg:postcode":"2015",
    "sg:province":"NSW",
    "wof:name":"Affordable Harbour Cruises",
    "wof:placetype":"venue"
},
  "geometry": {"coordinates":[151.198730469,-33.8976478577],"type":"Point"}
}