{
  "type": "Feature",
  "properties": {
    "addr:full":"PO Box 187 + Victor Harbor SA 5211",
    "addr:postcode":"5211",
    "iso:country":"AU",
    "sg:address":"PO Box 187",
    "sg:city":"+ Victor Harbor",
    "sg:classifiers":[
        {
            "category":"Building & Trades",
            "subcategory":"Landscaping Services",
            "type":"Services"
        }
    ],
    "sg:phone":"+61 403 089 521",
    "sg:postcode":"5211",
    "sg:province":"SA",
    "sg:tags":[
        "gardener"
    ],
    "wof:name":"Great Southern Garden Care",
    "wof:placetype":"venue"
},
  "geometry": {"coordinates":[138.624435425,-35.5497398376],"type":"Point"}
}