{
  "type": "Feature",
  "properties": {
    "iso:country":"AU",
    "sg:address":"20 Tinderbox Rd",
    "sg:city":"Bangalow",
    "sg:classifiers":[
        {
            "category":"Farming",
            "subcategory":"Farm & Veterinary Services",
            "type":"Manufacturing & Wholesale Goods"
        }
    ],
    "sg:phone":"+61 2 6687 2011",
    "sg:postcode":"2479",
    "sg:province":"NSW",
    "sg:tags":[
        "irrigation",
        "reticulation",
        "system"
    ],
    "wof:name":"Northern Rivers Irrigaton Services",
    "wof:placetype":"venue"
},
  "geometry": {"coordinates":[153.54725647000001,-28.6752605438],"type":"Point"}
}