{
  "type": "Feature",
  "properties": {
    "addr:full":"8 Gordon St Newstead QLD 4006",
    "addr:housenumber":"8",
    "addr:postcode":"4006",
    "addr:street":"Gordon St",
    "iso:country":"AU",
    "sg:address":"8 Gordon St",
    "sg:city":"Newstead",
    "sg:classifiers":[
        {
            "category":"Retail",
            "subcategory":"Laundry & Dry Cleaning",
            "type":"Services"
        }
    ],
    "sg:phone":"+61 7 3252 5549",
    "sg:postcode":"4006",
    "sg:province":"QLD",
    "sg:tags":[
        "equipment",
        "supply"
    ],
    "wof:name":"Ewex Australia Pty Ltd",
    "wof:placetype":"venue"
},
  "geometry": {"coordinates":[153.04454040499999,-27.4476146698],"type":"Point"}
}