{
  "type": "Feature",
  "properties": {
    "addr:full":"117 North Rd Denistone East NSW 2112",
    "addr:housenumber":"117",
    "addr:postcode":"2112",
    "addr:street":"North Rd",
    "iso:country":"AU",
    "sg:address":"117 North Rd",
    "sg:city":"Denistone East",
    "sg:classifiers":[
        {
            "category":"Health Services",
            "subcategory":"Doctor",
            "type":"Services"
        }
    ],
    "sg:phone":"+61 2 9878 6988",
    "sg:postcode":"2112",
    "sg:province":"NSW",
    "sg:tags":[
        "podiatrist"
    ],
    "wof:name":"Aghajanian Rima",
    "wof:placetype":"venue"
},
  "geometry": {"coordinates":[151.10253906200001,-33.7954139709],"type":"Point"}
}