{
  "type": "Feature",
  "properties": {
    "addr:full":"Albert St Creswick VIC 3363",
    "addr:postcode":"3363",
    "addr:street":"Albert St",
    "iso:country":"AU",
    "sg:address":"Albert St",
    "sg:city":"Creswick",
    "sg:classifiers":[
        {
            "category":"Farming",
            "subcategory":"Dairy Farm",
            "type":"Manufacturing & Wholesale Goods"
        }
    ],
    "sg:phone":"+61 3 5345 2523",
    "sg:postcode":"3363",
    "sg:province":"VIC",
    "wof:name":"Wrigley C N & E L",
    "wof:placetype":"venue"
},
  "geometry": {"coordinates":[143.894897461,-37.4234199524],"type":"Point"}
}