{
  "type": "Feature",
  "properties": {
    "addr:full":"94 Childers St North Adelaide SA 5006",
    "addr:housenumber":"94",
    "addr:postcode":"5006",
    "addr:street":"Childers St",
    "iso:country":"AU",
    "sg:address":"94 Childers St",
    "sg:city":"North Adelaide",
    "sg:classifiers":[
        {
            "category":"Professional",
            "subcategory":"Business Services",
            "type":"Services"
        }
    ],
    "sg:phone":"+61 8 8267 5572",
    "sg:postcode":"5006",
    "sg:province":"SA",
    "sg:tags":[
        "exporter"
    ],
    "wof:name":"Sundowners Trading Company Pty Ltd",
    "wof:placetype":"venue"
},
  "geometry": {"coordinates":[138.59161376899999,-34.9039344788],"type":"Point"}
}