{
  "type": "Feature",
  "properties": {
    "addr:full":"Scottville Rd Collinsville QLD 4804",
    "addr:postcode":"4804",
    "addr:street":"Scottville Rd",
    "iso:country":"AU",
    "sg:address":"Scottville Rd",
    "sg:city":"Collinsville",
    "sg:classifiers":[
        {
            "category":"Professional",
            "subcategory":"Business Services",
            "type":"Services"
        }
    ],
    "sg:phone":"+61 7 4785 5733",
    "sg:postcode":"4804",
    "sg:province":"QLD",
    "sg:tags":[
        "livestock",
        "transport"
    ],
    "wof:name":"Pattels Collinsville",
    "wof:placetype":"venue"
},
  "geometry": {"coordinates":[147.84407043499999,-20.5566978455],"type":"Point"}
}