{
  "type": "Feature",
  "properties": {
    "addr:full":"Rear 443 Scarborough Beach Rd Osborne Park WA 6017",
    "addr:housenumber":"443",
    "addr:postcode":"6017",
    "addr:street":"Scarborough Beach Rd",
    "iso:country":"AU",
    "sg:address":"Rear 443 Scarborough Beach Rd",
    "sg:city":"Osborne Park",
    "sg:classifiers":[
        {
            "category":"Building & Trades",
            "subcategory":"Equipment Rental",
            "type":"Services"
        }
    ],
    "sg:phone":"+61 1300 557 773",
    "sg:postcode":"6017",
    "sg:province":"WA",
    "sg:tags":[
        "fitness"
    ],
    "sg:website":"http://www.familyfitness.com.au",
    "wof:name":"Royel Fitness",
    "wof:placetype":"venue"
},
  "geometry": {"coordinates":[115.809791565,-31.906545639],"type":"Point"}
}