{
  "type": "Feature",
  "properties": {
    "addr:full":"Suite 411 188 Chalmers St Surry Hills NSW 2010",
    "addr:housenumber":"188",
    "addr:postcode":"2010",
    "addr:street":"Chalmers St",
    "iso:country":"AU",
    "sg:address":"Suite 411 188 Chalmers St",
    "sg:city":"Surry Hills",
    "sg:classifiers":[
        {
            "category":"Professional",
            "subcategory":"Employment Agencies",
            "type":"Services"
        }
    ],
    "sg:phone":"+61 412 852 423",
    "sg:postcode":"2010",
    "sg:province":"NSW",
    "sg:tags":[
        "provider",
        "internet"
    ],
    "wof:name":"Keilo Visual Design",
    "wof:placetype":"venue"
},
  "geometry": {"coordinates":[151.20640564000001,-33.8888702393],"type":"Point"}
}