{
  "type": "Feature",
  "properties": {
    "iso:country":"AU",
    "sg:address":"1780 Albany. Hwy",
    "sg:city":"Kenwick",
    "sg:classifiers":[
        {
            "category":"Home & Garden",
            "subcategory":"Carpets & Floor Coverings",
            "type":"Retail Goods"
        }
    ],
    "sg:phone":"+61 8 9459 1244",
    "sg:postcode":"6107",
    "sg:province":"WA",
    "sg:tags":[
        "tile",
        "wall"
    ],
    "wof:name":"Crosby Tiles",
    "wof:placetype":"venue"
},
  "geometry": {"coordinates":[115.972129822,-32.0415306091],"type":"Point"}
}