{
  "type": "Feature",
  "properties": {
    "addr:full":"7 Mantova Drv Wheelers Hill VIC 3150",
    "addr:housenumber":"7",
    "addr:postcode":"3150",
    "addr:street":"Mantova Drv",
    "iso:country":"AU",
    "sg:address":"7 Mantova Drv",
    "sg:city":"Wheelers Hill",
    "sg:classifiers":[
        {
            "category":"Communications",
            "type":"Services"
        }
    ],
    "sg:phone":"+61 3 9574 9994",
    "sg:postcode":"3150",
    "sg:province":"VIC",
    "sg:tags":[
        "equipment",
        "radio"
    ],
    "wof:name":"Advanced Radio Communications Pty Ltd",
    "wof:placetype":"venue"
},
  "geometry": {"coordinates":[145.179885864,-37.9145736694],"type":"Point"}
}