{
  "type": "Feature",
  "properties": {
    "addr:full":"169 Hay St East Perth WA 6004",
    "addr:housenumber":"169",
    "addr:postcode":"6004",
    "addr:street":"Hay St East",
    "iso:country":"AU",
    "sg:address":"169 Hay St",
    "sg:city":"East Perth",
    "sg:classifiers":[
        {
            "category":"Professional",
            "subcategory":"Engineering",
            "type":"Services"
        }
    ],
    "sg:phone":"+61 8 9268 1000",
    "sg:postcode":"6004",
    "sg:province":"WA",
    "sg:tags":[
        "consulting",
        "engineer"
    ],
    "wof:name":"Toussaint & Richardson Pty Ltd",
    "wof:placetype":"venue"
},
  "geometry": {"coordinates":[115.87432098399999,-31.9593086243],"type":"Point"}
}