{
  "type": "Feature",
  "properties": {
    "iso:country":"AU",
    "sg:address":"4 Duggan Ave",
    "sg:city":"Glengowrie",
    "sg:classifiers":[
        {
            "category":"Food & Beverages",
            "subcategory":"Specialty",
            "type":"Retail Goods"
        }
    ],
    "sg:phone":"+61 8 8376 0789",
    "sg:postcode":"5044",
    "sg:province":"SA",
    "sg:tags":[
        "product",
        "health"
    ],
    "wof:name":"Reliv Independent Distributor",
    "wof:placetype":"venue"
},
  "geometry": {"coordinates":[138.536407,-34.977661],"type":"Point"}
}