{
  "type": "Feature",
  "properties": {
    "addr:full":"1 Kosciuszko St Traralgon VIC 3844",
    "addr:housenumber":"1",
    "addr:postcode":"3844",
    "addr:street":"Kosciuszko St",
    "iso:country":"AU",
    "sg:address":"1 Kosciuszko St",
    "sg:city":"Traralgon",
    "sg:classifiers":[
        {
            "category":"Building & Trades",
            "subcategory":"Construction",
            "type":"Services"
        }
    ],
    "sg:phone":"+61 1300 553 938",
    "sg:postcode":"3844",
    "sg:province":"VIC",
    "sg:tags":[
        "renovation",
        "alterations",
        "extension",
        "contractor"
    ],
    "wof:name":"Spanline Home Additions",
    "wof:placetype":"venue"
},
  "geometry": {"coordinates":[146.51437377900001,-38.2040176392],"type":"Point"}
}