{
  "type": "Feature",
  "properties": {
    "addr:full":"27 Holberg St Moonee Ponds VIC 3039",
    "addr:housenumber":"27",
    "addr:postcode":"3039",
    "addr:street":"Holberg St",
    "iso:country":"AU",
    "sg:address":"27 Holberg St",
    "sg:city":"Moonee Ponds",
    "sg:classifiers":[
        {
            "category":"Health Services",
            "subcategory":"Medical Lab",
            "type":"Services"
        }
    ],
    "sg:phone":"+61 3 9375 2047",
    "sg:postcode":"3039",
    "sg:province":"VIC",
    "sg:tags":[
        "laboratory",
        "dental"
    ],
    "wof:name":"Dentech Ceramic Laboratory",
    "wof:placetype":"venue"
},
  "geometry": {"coordinates":[144.933334,-37.77087],"type":"Point"}
}