{
  "type": "Feature",
  "properties": {
    "addr:full":"33 Mount St Wentworthville NSW 2145",
    "addr:housenumber":"33",
    "addr:postcode":"2145",
    "addr:street":"Mount St",
    "iso:country":"AU",
    "sg:address":"33 Mount St",
    "sg:city":"Wentworthville",
    "sg:classifiers":[
        {
            "category":"Building & Trades",
            "subcategory":"Construction",
            "type":"Services"
        }
    ],
    "sg:phone":"+61 2 9631 6055",
    "sg:postcode":"2145",
    "sg:province":"NSW",
    "sg:tags":[
        "concrete",
        "contractor"
    ],
    "wof:name":"Lazanas E",
    "wof:placetype":"venue"
},
  "geometry": {"coordinates":[150.97177124000001,-33.7956695557],"type":"Point"}
}