{
  "type": "Feature",
  "properties": {
    "addr:full":"G14 Wheelers Hill Business Centre, 202 Jells Rd Wheelers Hill VIC 3150",
    "addr:housenumber":"g14;202",
    "addr:postcode":"3150",
    "addr:street":"Jells Rd",
    "iso:country":"AU",
    "sg:address":"G14 Wheelers Hill Business Centre, 202 Jells Rd",
    "sg:city":"Wheelers Hill",
    "sg:classifiers":[
        {
            "category":"Health Services",
            "subcategory":"Optometrist",
            "type":"Services"
        }
    ],
    "sg:phone":"+61 3 9562 1505",
    "sg:postcode":"3150",
    "sg:province":"VIC",
    "wof:name":"Alfred Nott Optometrists",
    "wof:placetype":"venue"
},
  "geometry": {"coordinates":[145.18846130399999,-37.9090690613],"type":"Point"}
}