{
  "type": "Feature",
  "properties": {
    "addr:full":"3 Cavanagh Crt Moranbah QLD 4744",
    "addr:housenumber":"3",
    "addr:postcode":"4744",
    "addr:street":"Cavanagh Crt",
    "iso:country":"AU",
    "sg:address":"3 Cavanagh Crt",
    "sg:city":"Moranbah",
    "sg:classifiers":[
        {
            "category":"Building & Trades",
            "subcategory":"Plumbing",
            "type":"Services"
        }
    ],
    "sg:phone":"+61 7 4941 9099",
    "sg:postcode":"4744",
    "sg:province":"QLD",
    "sg:tags":[
        "fitting",
        "hose",
        "supply"
    ],
    "wof:name":"Enzed",
    "wof:placetype":"venue"
},
  "geometry": {"coordinates":[148.09439086899999,-22.1004600525],"type":"Point"}
}