{
  "type": "Feature",
  "properties": {
    "addr:full":"20 Raine Ave Liverpool NSW 2170",
    "addr:housenumber":"20",
    "addr:postcode":"2170",
    "addr:street":"Raine Ave",
    "iso:country":"AU",
    "sg:address":"20 Raine Ave",
    "sg:city":"Liverpool",
    "sg:classifiers":[
        {
            "category":"Building & Trades",
            "subcategory":"Plumbing",
            "type":"Services"
        }
    ],
    "sg:phone":"+61 414 622 588",
    "sg:postcode":"2170",
    "sg:province":"NSW",
    "sg:tags":[
        "plumber",
        "gasfitters"
    ],
    "wof:name":"Drainaway Plumbing Pty Ltd",
    "wof:placetype":"venue"
},
  "geometry": {"coordinates":[150.90785217300001,-33.9323768616],"type":"Point"}
}