{
  "type": "Feature",
  "properties": {
    "addr:full":"Hilltop Crs Ivanhoe VIC 3079",
    "addr:postcode":"3079",
    "addr:street":"Hilltop Crs",
    "iso:country":"AU",
    "sg:address":"Hilltop Crs",
    "sg:city":"Ivanhoe",
    "sg:classifiers":[
        {
            "category":"Building & Trades",
            "subcategory":"Plumbing",
            "type":"Services"
        }
    ],
    "sg:phone":"+61 412 542 862",
    "sg:postcode":"3079",
    "sg:province":"VIC",
    "sg:tags":[
        "plumber",
        "gasfitters"
    ],
    "wof:name":"Ivanhoe Plumbing Services",
    "wof:placetype":"venue"
},
  "geometry": {"coordinates":[145.045196533,-37.7665290833],"type":"Point"}
}