{
  "type": "Feature",
  "properties": {
    "iso:country":"AU",
    "sg:address":"2 Carmen St",
    "sg:city":"Dandenong",
    "sg:classifiers":[
        {
            "category":"Building & Trades",
            "subcategory":"Plumbing",
            "type":"Services"
        }
    ],
    "sg:phone":"+61 3 9793 2744",
    "sg:postcode":"3175",
    "sg:province":"VIC",
    "sg:tags":[
        "pump",
        "repairer"
    ],
    "wof:name":"Fluid Sealing Pty Ltd",
    "wof:placetype":"venue"
},
  "geometry": {"coordinates":[145.19688415499999,-37.9707336426],"type":"Point"}
}