{
  "type": "Feature",
  "properties": {
    "addr:full":"Sylvan St Malua Bay NSW 2536",
    "addr:postcode":"2536",
    "addr:street":"Sylvan St",
    "iso:country":"AU",
    "sg:address":"Sylvan St",
    "sg:city":"Malua Bay",
    "sg:classifiers":[
        {
            "category":"Restaurant",
            "type":"Food & Drink"
        }
    ],
    "sg:phone":"+61 2 4471 2248",
    "sg:postcode":"2536",
    "sg:province":"NSW",
    "wof:name":"Malua Bay Bowling & Recreation Club (Sea Change at Malua Bay)",
    "wof:placetype":"venue"
},
  "geometry": {"coordinates":[150.228683472,-35.7925262451],"type":"Point"}
}