{
  "type": "Feature",
  "properties": {
    "addr:full":"5 Ellenbrae Pl Marangaroo WA 6064",
    "addr:housenumber":"5",
    "addr:postcode":"6064",
    "addr:street":"Ellenbrae Pl Marangaroo",
    "iso:country":"AU",
    "sg:address":"5 Ellenbrae Pl",
    "sg:city":"Marangaroo",
    "sg:classifiers":[
        {
            "category":"Retail",
            "subcategory":"Storage",
            "type":"Services"
        }
    ],
    "sg:phone":"+61 8 9247 3232",
    "sg:postcode":"6064",
    "sg:province":"WA",
    "sg:tags":[
        "removal",
        "furniture"
    ],
    "wof:name":"Phillips Clive",
    "wof:placetype":"venue"
},
  "geometry": {"coordinates":[115.84101867699999,-31.8245677948],"type":"Point"}
}