{
  "type": "Feature",
  "properties": {
    "addr:full":"47 Stephen Rd Dandenong VIC 3175",
    "addr:housenumber":"47",
    "addr:postcode":"3175",
    "addr:street":"Stephen Rd",
    "iso:country":"AU",
    "sg:address":"47 Stephen Rd",
    "sg:city":"Dandenong",
    "sg:classifiers":[
        {
            "category":"Food & Beverages",
            "subcategory":"Bakery",
            "type":"Retail Goods"
        }
    ],
    "sg:phone":"+61 3 9769 2218",
    "sg:postcode":"3175",
    "sg:province":"VIC",
    "sg:tags":[
        "baker"
    ],
    "wof:name":"Tangold Pastry (Aust) Pty Ltd",
    "wof:placetype":"venue"
},
  "geometry": {"coordinates":[145.21304321299999,-38.0072784424],"type":"Point"}
}