{
  "type": "Feature",
  "properties": {
    "addr:full":"Level 5, 10- 14 Waterloo St Surry Hills NSW 2010",
    "addr:housenumber":"10 14",
    "addr:postcode":"2010",
    "addr:street":"Waterloo St",
    "iso:country":"AU",
    "sg:address":"Level 5, 10- 14 Waterloo St",
    "sg:city":"Surry Hills",
    "sg:classifiers":[
        {
            "category":"Shopping",
            "subcategory":"Clothing, Apparel, & Fashions",
            "type":"Retail Goods"
        }
    ],
    "sg:phone":"+61 414 974 674",
    "sg:postcode":"2010",
    "sg:province":"NSW",
    "sg:tags":[
        "sportswear"
    ],
    "wof:name":"Tasman Australia",
    "wof:placetype":"venue"
},
  "geometry": {"coordinates":[151.2109375,-33.8857650757],"type":"Point"}
}