{
  "type": "Feature",
  "properties": {
    "iso:country":"AU",
    "sg:address":"61 Boyd St",
    "sg:city":"Kelso",
    "sg:classifiers":[
        {
            "category":"Health Services",
            "subcategory":"Nursing And Care Facility",
            "type":"Services"
        }
    ],
    "sg:phone":"+61 2 6331 7599",
    "sg:postcode":"2795",
    "sg:province":"NSW",
    "sg:tags":[
        "home"
    ],
    "wof:name":"Bathurst Nursing Home",
    "wof:placetype":"venue"
},
  "geometry": {"coordinates":[149.61102294899999,-33.4144554138],"type":"Point"}
}