{
  "type": "Feature",
  "properties": {
    "addr:full":"55 Betula Ave Vermont VIC 3133",
    "addr:housenumber":"55",
    "addr:postcode":"3133",
    "addr:street":"Betula Ave",
    "iso:country":"AU",
    "sg:address":"55 Betula Ave",
    "sg:city":"Vermont",
    "sg:classifiers":[
        {
            "category":"Building & Trades",
            "subcategory":"Cleaning & Sanitation",
            "type":"Services"
        }
    ],
    "sg:phone":"+61 432 749 499",
    "sg:postcode":"3133",
    "sg:province":"VIC",
    "sg:tags":[
        "chemical",
        "pressure",
        "steam",
        "contractor"
    ],
    "wof:name":"Dr Driveway",
    "wof:placetype":"venue"
},
  "geometry": {"coordinates":[145.18495178200001,-37.8323707581],"type":"Point"}
}