{
  "type": "Feature",
  "properties": {
    "addr:full":"Fy 6a/ 6 Dunlop Ave Hoppers Crossing VIC 3029",
    "addr:housenumber":"6a / 6",
    "addr:postcode":"3029",
    "addr:street":"Fy;Dunlop Ave",
    "iso:country":"AU",
    "sg:address":"Fy 6a/ 6 Dunlop Ave",
    "sg:city":"Hoppers Crossing",
    "sg:classifiers":[
        {
            "category":"Food & Beverages",
            "subcategory":"Groceries & Convenience Stores",
            "type":"Retail Goods"
        }
    ],
    "sg:phone":"+61 3 8368 2677",
    "sg:postcode":"3029",
    "sg:province":"VIC",
    "wof:name":"Sustain Ability International",
    "wof:placetype":"venue"
},
  "geometry": {"coordinates":[144.72482299999999,-37.871044],"type":"Point"}
}