{
  "type": "Feature",
  "properties": {
    "addr:full":"Shop 4/49 Cnr Palm Beach Ave & Phillipine Pde Palm Beach QLD 4221",
    "addr:housenumber":"shop 4 / 49",
    "addr:postcode":"4221",
    "addr:street":"Cnr Palm Beach Ave & Phillipine Pde",
    "iso:country":"AU",
    "sg:address":"Shop 4/49 Cnr Palm Beach Ave & Phillipine Pde",
    "sg:city":"Palm Beach",
    "sg:classifiers":[
        {
            "category":"Retail",
            "subcategory":"Auto Repair",
            "type":"Services"
        }
    ],
    "sg:phone":"+61 7 5534 1048",
    "sg:postcode":"4221",
    "sg:province":"QLD",
    "sg:tags":[
        "electrical"
    ],
    "wof:name":"Palm Beach Auto Electrics",
    "wof:placetype":"venue"
},
  "geometry": {"coordinates":[153.471893311,-28.1212558746],"type":"Point"}
}