{
  "type": "Feature",
  "properties": {
    "iso:country":"AU",
    "sg:address":"97 Main Rd",
    "sg:city":"Moonah",
    "sg:classifiers":[
        {
            "category":"Personal",
            "subcategory":"Barber",
            "type":"Services"
        }
    ],
    "sg:phone":"+61 3 6228 5298",
    "sg:postcode":"7009",
    "sg:province":"TAS",
    "wof:name":"Theo's Hair Salon",
    "wof:placetype":"venue"
},
  "geometry": {"coordinates":[147.29510498100001,-42.8466491699],"type":"Point"}
}