{
  "type": "Feature",
  "properties": {
    "addr:full":"10 Main St Osborne Park WA 6017",
    "addr:housenumber":"10",
    "addr:postcode":"6017",
    "addr:street":"Main St",
    "iso:country":"AU",
    "sg:address":"10 Main St",
    "sg:city":"Osborne Park",
    "sg:classifiers":[
        {
            "category":"Professional",
            "subcategory":"Printing & Photocopies",
            "type":"Services"
        }
    ],
    "sg:phone":"+61 8 9201 1777",
    "sg:postcode":"6017",
    "sg:province":"WA",
    "sg:tags":[
        "rubber",
        "stamp",
        "metal"
    ],
    "wof:name":"Allstamps",
    "wof:placetype":"venue"
},
  "geometry": {"coordinates":[115.82840728799999,-31.9134197235],"type":"Point"}
}