{
  "type": "Feature",
  "properties": {
    "iso:country":"AU",
    "sg:address":"30 Minchinton St",
    "sg:city":"Caloundra",
    "sg:classifiers":[
        {
            "category":"Banks & Credit Unions",
            "subcategory":"Bank",
            "type":"Services"
        }
    ],
    "sg:phone":"+61 7 5438 1311",
    "sg:postcode":"4551",
    "sg:province":"QLD",
    "sg:tags":[
        "broker",
        "mortgage"
    ],
    "wof:name":"Queensland Property Finance",
    "wof:placetype":"venue"
},
  "geometry": {"coordinates":[153.13238525400001,-26.8050079346],"type":"Point"}
}