{
  "type": "Feature",
  "properties": {
    "addr:full":"29 Pearson St Wagga Wagga NSW 2650",
    "addr:housenumber":"29",
    "addr:postcode":"2650",
    "addr:street":"Pearson St",
    "iso:country":"AU",
    "sg:address":"29 Pearson St",
    "sg:city":"Wagga Wagga",
    "sg:classifiers":[
        {
            "category":"Home & Garden",
            "subcategory":"Building Materials",
            "type":"Retail Goods"
        }
    ],
    "sg:phone":"+61 2 6925 0836",
    "sg:postcode":"2650",
    "sg:province":"NSW",
    "sg:tags":[
        "merchant",
        "glass",
        "glazier"
    ],
    "wof:name":"Regency",
    "wof:placetype":"venue"
},
  "geometry": {"coordinates":[147.34486389200001,-35.1191711426],"type":"Point"}
}