{
  "type": "Feature",
  "properties": {
    "iso:country":"AU",
    "sg:address":"Lot 66 Sandridge Rd",
    "sg:city":"Bunbury",
    "sg:classifiers":[
        {
            "category":"Fast Food",
            "type":"Food & Drink"
        }
    ],
    "sg:phone":"+61 8 9721 7533",
    "sg:postcode":"6230",
    "sg:province":"WA",
    "sg:tags":[
        "away",
        "take"
    ],
    "wof:name":"Red Rooster",
    "wof:placetype":"venue"
},
  "geometry": {"coordinates":[115.664322,-33.336433],"type":"Point"}
}