{
  "type": "Feature",
  "properties": {
    "addr:full":"73 Cricket Rd Regency Downs QLD 4341",
    "addr:housenumber":"73",
    "addr:postcode":"4341",
    "addr:street":"Cricket Rd",
    "iso:country":"AU",
    "sg:address":"73 Cricket Rd",
    "sg:city":"Regency Downs",
    "sg:classifiers":[
        {
            "category":"Building & Trades",
            "subcategory":"Construction",
            "type":"Services"
        }
    ],
    "sg:phone":"+61 7 3216 8999",
    "sg:postcode":"4341",
    "sg:province":"QLD",
    "sg:tags":[
        "home",
        "air conditioning"
    ],
    "wof:name":"Air Necessities",
    "wof:placetype":"venue"
},
  "geometry": {"coordinates":[152.45033264200001,-27.5175647736],"type":"Point"}
}