{
  "type": "Feature",
  "properties": {
    "iso:country":"AU",
    "sg:address":"9 King St",
    "sg:city":"Burnie",
    "sg:classifiers":[
        {
            "category":"Professional",
            "subcategory":"Accounting & Tax Preparation",
            "type":"Services"
        }
    ],
    "sg:phone":"+61 3 6431 9435",
    "sg:postcode":"7320",
    "sg:province":"TAS",
    "sg:tags":[
        "consultant",
        "taxation"
    ],
    "wof:name":"Active Accountants",
    "wof:placetype":"venue"
},
  "geometry": {"coordinates":[145.90249600000001,-41.05035],"type":"Point"}
}