{
  "type": "Feature",
  "properties": {
    "addr:full":"Cleveland Rd Dapto NSW 2530",
    "addr:postcode":"2530",
    "addr:street":"Cleveland Rd",
    "iso:country":"AU",
    "sg:address":"Cleveland Rd",
    "sg:city":"Dapto",
    "sg:classifiers":[
        {
            "category":"Education",
            "subcategory":"School",
            "type":"Public Place"
        }
    ],
    "sg:phone":"+61 2 4261 1416",
    "sg:postcode":"2530",
    "sg:province":"NSW",
    "sg:tags":[
        "state",
        "-",
        "nsw"
    ],
    "wof:name":"Dapto High School",
    "wof:placetype":"venue"
},
  "geometry": {"coordinates":[150.78843689000001,-34.5021858215],"type":"Point"}
}