{
  "type": "Feature",
  "properties": {
    "addr:full":"Suite 14, 31 Dunn Bay Rd Dunsborough WA 6281",
    "addr:housenumber":"31",
    "addr:postcode":"6281",
    "addr:street":"Dunn Bay Rd",
    "iso:country":"AU",
    "sg:address":"Suite 14, 31 Dunn Bay Rd",
    "sg:city":"Dunsborough",
    "sg:classifiers":[
        {
            "category":"Farming",
            "subcategory":"Vineyard",
            "type":"Manufacturing & Wholesale Goods"
        }
    ],
    "sg:phone":"+61 8 9756 8011",
    "sg:postcode":"6281",
    "sg:province":"WA",
    "sg:tags":[
        "winery"
    ],
    "wof:name":"AHA Viticulture",
    "wof:placetype":"venue"
},
  "geometry": {"coordinates":[115.107513428,-33.6152877808],"type":"Point"}
}