{
  "type": "Feature",
  "properties": {
    "addr:full":"Prince St Busselton WA 6280",
    "addr:postcode":"6280",
    "addr:street":"Prince St",
    "iso:country":"AU",
    "sg:address":"Prince St",
    "sg:city":"Busselton",
    "sg:classifiers":[
        {
            "category":"Health Services",
            "subcategory":"Optometrist",
            "type":"Services"
        }
    ],
    "sg:phone":"+61 8 9754 1441",
    "sg:postcode":"6280",
    "sg:province":"WA",
    "wof:name":"Mr B The Optometrist",
    "wof:placetype":"venue"
},
  "geometry": {"coordinates":[115.343193054,-33.6513786316],"type":"Point"}
}