{
  "type": "Feature",
  "properties": {
    "iso:country":"AU",
    "sg:address":"1/ 27 Philip St",
    "sg:city":"Fannie Bay",
    "sg:classifiers":[
        {
            "category":"Personal",
            "subcategory":"Massage",
            "type":"Services"
        }
    ],
    "sg:phone":"+61 400 286 631",
    "sg:postcode":"0820",
    "sg:province":"NT",
    "sg:tags":[
        "therapy"
    ],
    "wof:name":"Right Touch Massage",
    "wof:placetype":"venue"
},
  "geometry": {"coordinates":[130.836669922,-12.4202671051],"type":"Point"}
}