{
  "type": "Feature",
  "properties": {
    "iso:country":"AU",
    "sg:address":"17 Mary St",
    "sg:city":"Pakenham",
    "sg:classifiers":[
        {
            "category":"Retail",
            "subcategory":"Storage",
            "type":"Services"
        }
    ],
    "sg:phone":"+61 3 5941 1255",
    "sg:postcode":"3810",
    "sg:province":"VIC",
    "wof:name":"Paken-Store/Self Storage",
    "wof:placetype":"venue"
},
  "geometry": {"coordinates":[145.45983899999999,-38.060459],"type":"Point"}
}