{
  "type": "Feature",
  "properties": {
    "iso:country":"AU",
    "sg:address":"617 Toohey Rd",
    "sg:city":"Salisbury",
    "sg:classifiers":[
        {
            "category":"Structure",
            "subcategory":"Building",
            "type":"Public Place"
        }
    ],
    "sg:phone":"+61 7 3276 7095",
    "sg:postcode":"4107",
    "sg:province":"QLD",
    "sg:tags":[
        "sail",
        "shade"
    ],
    "sg:website":"http://www.sailmaker.com.au",
    "wof:name":"Sailmaker Shade Sail Designs.",
    "wof:placetype":"venue"
},
  "geometry": {"coordinates":[153.039352417,-27.5433330536],"type":"Point"}
}