{
  "type": "Feature",
  "properties": {
    "iso:country":"AU",
    "sg:address":"27 - 29 Worrell St",
    "sg:city":"Nunawading",
    "sg:classifiers":[
        {
            "category":"Professional",
            "subcategory":"Computer Services",
            "type":"Services"
        }
    ],
    "sg:phone":"+61 3 9878 7407",
    "sg:postcode":"3131",
    "sg:province":"VIC",
    "sg:tags":[
        "scanning",
        "document"
    ],
    "wof:name":"Micro Image",
    "wof:placetype":"venue"
},
  "geometry": {"coordinates":[145.18096923799999,-37.8050842285],"type":"Point"}
}