{
  "type": "Feature",
  "properties": {
    "iso:country":"AU",
    "sg:address":"31 Stratton Ave",
    "sg:city":"Lenah Valley",
    "sg:classifiers":[
        {
            "category":"Retail",
            "subcategory":"Repair Shop",
            "type":"Services"
        }
    ],
    "sg:phone":"+61 3 6228 2350",
    "sg:postcode":"7008",
    "sg:province":"TAS",
    "sg:tags":[
        "upholsterer"
    ],
    "wof:name":"Turner & Robertson",
    "wof:placetype":"venue"
},
  "geometry": {"coordinates":[147.278076172,-42.8597717285],"type":"Point"}
}