{
  "type": "Feature",
  "properties": {
    "iso:country":"AU",
    "sg:address":"590 Marion Rd",
    "sg:city":"Plympton Park",
    "sg:classifiers":[
        {
            "category":"Health Services",
            "subcategory":"Health Practitioner",
            "type":"Services"
        }
    ],
    "sg:phone":"+61 8 8276 8122",
    "sg:postcode":"5038",
    "sg:province":"SA",
    "sg:tags":[
        "naturopath"
    ],
    "wof:name":"Adelaide Natural Medicine Clinic",
    "wof:placetype":"venue"
},
  "geometry": {"coordinates":[138.556030273,-34.9821014404],"type":"Point"}
}