{
  "type": "Feature",
  "properties": {
    "addr:full":"684 Frankston-Dandenong Rd Carrum Downs VIC 3201",
    "addr:housenumber":"684",
    "addr:postcode":"3201",
    "addr:street":"Frankston-Dandenong Rd",
    "iso:country":"AU",
    "sg:address":"684 Frankston-Dandenong Rd",
    "sg:city":"Carrum Downs",
    "sg:classifiers":[
        {
            "category":"Food & Beverages",
            "subcategory":"Groceries & Convenience Stores",
            "type":"Retail Goods"
        }
    ],
    "sg:phone":"+61 3 9782 8611",
    "sg:postcode":"3201",
    "sg:province":"VIC",
    "wof:name":"Vel Spices",
    "wof:placetype":"venue"
},
  "geometry": {"coordinates":[145.181839,-38.087303],"type":"Point"}
}