{
  "type": "Feature",
  "properties": {
    "addr:full":"48 Cave Hill Rd Lilydale VIC 3140",
    "addr:housenumber":"48",
    "addr:postcode":"3140",
    "addr:street":"Cave Hill Rd",
    "iso:country":"AU",
    "sg:address":"48 Cave Hill Rd",
    "sg:city":"Lilydale",
    "sg:classifiers":[
        {
            "category":"Retail",
            "subcategory":"Auto Repair",
            "type":"Services"
        }
    ],
    "sg:phone":"+61 3 9739 5367",
    "sg:postcode":"3140",
    "sg:province":"VIC",
    "sg:tags":[
        "repairer",
        "motor",
        "engineer"
    ],
    "wof:name":"Estate Automotive Services",
    "wof:placetype":"venue"
},
  "geometry": {"coordinates":[145.34283447300001,-37.7578964233],"type":"Point"}
}