{
  "type": "Feature",
  "properties": {
    "addr:full":"4 Sunbeam Rd Croydon Park SA 5008",
    "addr:housenumber":"4",
    "addr:postcode":"5008",
    "addr:street":"Sunbeam Rd",
    "iso:country":"AU",
    "sg:address":"4 Sunbeam Rd",
    "sg:city":"Croydon Park",
    "sg:classifiers":[
        {
            "category":"Professional",
            "subcategory":"Engineering",
            "type":"Services"
        }
    ],
    "sg:phone":"+61 8 8346 2981",
    "sg:postcode":"5008",
    "sg:province":"SA",
    "sg:tags":[
        "engineer"
    ],
    "wof:name":"I & A Engineers",
    "wof:placetype":"venue"
},
  "geometry": {"coordinates":[138.57235700000001,-34.885021],"type":"Point"}
}