{
  "type": "Feature",
  "properties": {
    "iso:country":"AU",
    "sg:address":"22 Nedland Crs",
    "sg:city":"Port Noarlunga South",
    "sg:classifiers":[
        {
            "category":"Building & Trades",
            "subcategory":"Construction",
            "type":"Services"
        }
    ],
    "sg:phone":"+61 8 8386 3537",
    "sg:postcode":"5167",
    "sg:province":"SA",
    "sg:tags":[
        "plasterboard",
        "plasterer",
        "fixer"
    ],
    "wof:name":"W & M F Osoinik Solid Plastering",
    "wof:placetype":"venue"
},
  "geometry": {"coordinates":[138.49444580100001,-35.1869773865],"type":"Point"}
}