{
  "type": "Feature",
  "properties": {
    "addr:full":"244 Pitt St Merrylands NSW 2160",
    "addr:housenumber":"244",
    "addr:postcode":"2160",
    "addr:street":"Pitt St",
    "iso:country":"AU",
    "sg:address":"244 Pitt St",
    "sg:city":"Merrylands",
    "sg:classifiers":[
        {
            "category":"Health Services",
            "subcategory":"Health Practitioner",
            "type":"Services"
        }
    ],
    "sg:phone":"+61 2 9897 3788",
    "sg:postcode":"2160",
    "sg:province":"NSW",
    "sg:tags":[
        "physiotherapist"
    ],
    "wof:name":"Medclinic Physiotherapy",
    "wof:placetype":"venue"
},
  "geometry": {"coordinates":[150.99168395999999,-33.8360023499],"type":"Point"}
}