{
  "type": "Feature",
  "properties": {
    "addr:full":"Cnr Simmie St & Glengala Rd Sunshine VIC 3020",
    "addr:postcode":"3020",
    "addr:street":"Cnr Simmie St & Glengala Rd",
    "iso:country":"AU",
    "sg:address":"Cnr Simmie St & Glengala Rd",
    "sg:city":"Sunshine",
    "sg:classifiers":[
        {
            "category":"Government",
            "subcategory":"City Hall",
            "type":"Public Place"
        }
    ],
    "sg:phone":"+61 3 9364 5322",
    "sg:postcode":"3020",
    "sg:province":"VIC",
    "wof:name":"Glengala Community Centre",
    "wof:placetype":"venue"
},
  "geometry": {"coordinates":[144.81689499999999,-37.789776],"type":"Point"}
}