{
  "type": "Feature",
  "properties": {
    "iso:country":"AU",
    "sg:address":"213 Queen St",
    "sg:city":"Campbelltown",
    "sg:classifiers":[
        {
            "category":"Banks & Credit Unions",
            "subcategory":"Bank",
            "type":"Services"
        }
    ],
    "sg:phone":"+61 13 20 32",
    "sg:postcode":"2560",
    "sg:province":"NSW",
    "wof:name":"Westpac",
    "wof:placetype":"venue"
},
  "geometry": {"coordinates":[150.813262939,-34.0675697327],"type":"Point"}
}