{
  "type": "Feature",
  "properties": {
    "addr:full":"Riverview Drv Berri SA 5343",
    "addr:postcode":"5343",
    "addr:street":"Riverview Drv",
    "iso:country":"AU",
    "sg:address":"Riverview Drv",
    "sg:city":"Berri",
    "sg:classifiers":[
        {
            "category":"Travel",
            "subcategory":"Hotels & Motels",
            "type":"Entertainment"
        }
    ],
    "sg:phone":"+61 1800 088 226",
    "sg:postcode":"5343",
    "sg:province":"SA",
    "wof:name":"Berri Resort Hotel",
    "wof:placetype":"venue"
},
  "geometry": {"coordinates":[140.601654053,-34.2879714966],"type":"Point"}
}