{
  "type": "Feature",
  "properties": {
    "addr:full":"Kyeamba St Rosewood NSW 2652",
    "addr:postcode":"2652",
    "addr:street":"Kyeamba St",
    "iso:country":"AU",
    "sg:address":"Kyeamba St",
    "sg:city":"Rosewood",
    "sg:classifiers":[
        {
            "category":"Food & Beverages",
            "subcategory":"Groceries & Convenience Stores",
            "type":"Retail Goods"
        }
    ],
    "sg:phone":"+61 2 6948 8248",
    "sg:postcode":"2652",
    "sg:province":"NSW",
    "wof:name":"Rosewood Store",
    "wof:placetype":"venue"
},
  "geometry": {"coordinates":[147.864303589,-35.6709938049],"type":"Point"}
}