{
  "type": "Feature",
  "properties": {
    "iso:country":"AU",
    "sg:address":"Shop 2/ 21 Elliott Crt",
    "sg:city":"Hillcrest",
    "sg:classifiers":[
        {
            "category":"Professional",
            "subcategory":"Engineering",
            "type":"Services"
        }
    ],
    "sg:phone":"+61 7 3809 0157",
    "sg:postcode":"4118",
    "sg:province":"QLD",
    "sg:tags":[
        "installation",
        "maintenance",
        "engineer"
    ],
    "wof:name":"KRM Maintenance Engineering Pty Ltd",
    "wof:placetype":"venue"
},
  "geometry": {"coordinates":[153.032302856,-27.6612472534],"type":"Point"}
}