{
  "type": "Feature",
  "properties": {
    "addr:full":"59 Beane St Gosford NSW 2250",
    "addr:housenumber":"59",
    "addr:postcode":"2250",
    "addr:street":"Beane St",
    "iso:country":"AU",
    "sg:address":"59 Beane St",
    "sg:city":"Gosford",
    "sg:classifiers":[
        {
            "category":"Health Services",
            "subcategory":"Health Practitioner",
            "type":"Services"
        }
    ],
    "sg:phone":"+61 2 4365 3385",
    "sg:postcode":"2250",
    "sg:province":"NSW",
    "sg:tags":[
        "pathologist",
        "speech"
    ],
    "wof:name":"Woodward Susan E",
    "wof:placetype":"venue"
},
  "geometry": {"coordinates":[151.34523010300001,-33.421421051],"type":"Point"}
}