{
  "type": "Feature",
  "properties": {
    "addr:full":"45 Laurie St Yarrambat VIC 3091",
    "addr:housenumber":"45",
    "addr:postcode":"3091",
    "addr:street":"Laurie St",
    "iso:country":"AU",
    "sg:address":"45 Laurie St",
    "sg:city":"Yarrambat",
    "sg:classifiers":[
        {
            "category":"Farming",
            "subcategory":"Vineyard",
            "type":"Manufacturing & Wholesale Goods"
        }
    ],
    "sg:phone":"+61 3 9717 3710",
    "sg:postcode":"3091",
    "sg:province":"VIC",
    "sg:tags":[
        "winery"
    ],
    "wof:name":"Yarrambat Estate",
    "wof:placetype":"venue"
},
  "geometry": {"coordinates":[145.140014648,-37.6222686768],"type":"Point"}
}