{
  "type": "Feature",
  "properties": {
    "iso:country":"AU",
    "sg:address":"7a Embrey Crt",
    "sg:city":"Pakenham",
    "sg:classifiers":[
        {
            "category":"Education",
            "subcategory":"Dance Studio",
            "type":"Public Place"
        }
    ],
    "sg:phone":"+61 3 5940 3380",
    "sg:postcode":"3810",
    "sg:province":"VIC",
    "sg:tags":[
        "venue",
        "tuition"
    ],
    "wof:name":"Marshere Pakenham",
    "wof:placetype":"venue"
},
  "geometry": {"coordinates":[145.49839800000001,-38.085037],"type":"Point"}
}