{
  "type": "Feature",
  "properties": {
    "addr:full":"Pullenvale Rd Pullenvale QLD 4069",
    "addr:postcode":"4069",
    "addr:street":"Pullenvale Rd",
    "iso:country":"AU",
    "sg:address":"Pullenvale Rd",
    "sg:city":"Pullenvale",
    "sg:classifiers":[
        {
            "category":"Professional",
            "subcategory":"Management & Consulting",
            "type":"Services"
        }
    ],
    "sg:phone":"+61 7 3374 2801",
    "sg:postcode":"4069",
    "sg:province":"QLD",
    "sg:tags":[
        "consultant"
    ],
    "wof:name":"Siggins Miller Consultants Pty Ltd",
    "wof:placetype":"venue"
},
  "geometry": {"coordinates":[152.887573242,-27.5234260559],"type":"Point"}
}