{
  "type": "Feature",
  "properties": {
    "addr:full":"75 Taunton St Annerley QLD 4103",
    "addr:housenumber":"75",
    "addr:postcode":"4103",
    "addr:street":"Taunton St",
    "iso:country":"AU",
    "sg:address":"75 Taunton St",
    "sg:city":"Annerley",
    "sg:classifiers":[
        {
            "category":"Real Estate",
            "subcategory":"Architect",
            "type":"Services"
        }
    ],
    "sg:phone":"+61 7 3392 9255",
    "sg:postcode":"4103",
    "sg:province":"QLD",
    "sg:tags":[
        "naval"
    ],
    "wof:name":"J Q Stephen Pty Ltd",
    "wof:placetype":"venue"
},
  "geometry": {"coordinates":[153.02572631800001,-27.5155849457],"type":"Point"}
}