{
  "type": "Feature",
  "properties": {
    "addr:full":"54 Gilbert St Latrobe TAS 7307",
    "addr:housenumber":"54",
    "addr:postcode":"7307",
    "addr:street":"Gilbert St",
    "iso:country":"AU",
    "sg:address":"54 Gilbert St",
    "sg:city":"Latrobe",
    "sg:classifiers":[
        {
            "category":"Shopping",
            "subcategory":"Crafts & Fabrics",
            "type":"Retail Goods"
        }
    ],
    "sg:phone":"+61 3 6426 2270",
    "sg:postcode":"7307",
    "sg:province":"TAS",
    "sg:tags":[
        "supply"
    ],
    "wof:name":"Picture Patchwork",
    "wof:placetype":"venue"
},
  "geometry": {"coordinates":[146.40846300000001,-41.235229],"type":"Point"}
}