{
  "type": "Feature",
  "properties": {
    "addr:full":"16 Britton St Smithfield NSW 2164",
    "addr:housenumber":"16",
    "addr:postcode":"2164",
    "addr:street":"Britton St",
    "iso:country":"AU",
    "sg:address":"16 Britton St",
    "sg:city":"Smithfield",
    "sg:classifiers":[
        {
            "category":"Professional",
            "type":"Services"
        }
    ],
    "sg:phone":"+61 2 9757 1244",
    "sg:postcode":"2164",
    "sg:province":"NSW",
    "sg:tags":[
        "transport"
    ],
    "wof:name":"Hi-Speed Transport Pty Ltd",
    "wof:placetype":"venue"
},
  "geometry": {"coordinates":[150.945236206,-33.8443336487],"type":"Point"}
}