{
  "type": "Feature",
  "properties": {
    "addr:full":"Cnr Roselea & Lyndale Sts Shailer Park QLD 4128",
    "addr:postcode":"4128",
    "addr:street":"Cnr",
    "iso:country":"AU",
    "sg:address":"Cnr Roselea & Lyndale Sts",
    "sg:city":"Shailer Park",
    "sg:classifiers":[
        {
            "category":"Food & Beverages",
            "subcategory":"Supermarket",
            "type":"Retail Goods"
        }
    ],
    "sg:phone":"+61 7 3801 2003",
    "sg:postcode":"4128",
    "sg:province":"QLD",
    "sg:tags":[
        "grocery",
        "store"
    ],
    "wof:name":"Kimberley Park Convenience Store",
    "wof:placetype":"venue"
},
  "geometry": {"coordinates":[153.17282104500001,-27.6514759064],"type":"Point"}
}