{
  "type": "Feature",
  "properties": {
    "iso:country":"AU",
    "sg:address":"3/ 75 Bronte Rd",
    "sg:city":"Bondi Junction",
    "sg:classifiers":[
        {
            "category":"Personal",
            "subcategory":"Beauty Salon",
            "type":"Services"
        }
    ],
    "sg:phone":"+61 2 9369 4020",
    "sg:postcode":"2022",
    "sg:province":"NSW",
    "sg:tags":[
        "hairdresser"
    ],
    "wof:name":"Funch Hair",
    "wof:placetype":"venue"
},
  "geometry": {"coordinates":[151.24995422399999,-33.8945884705],"type":"Point"}
}