{
  "type": "Feature",
  "properties": {
    "addr:full":"172 Liebig St Warrnambool VIC 3280",
    "addr:housenumber":"172",
    "addr:postcode":"3280",
    "addr:street":"Liebig St",
    "iso:country":"AU",
    "sg:address":"172 Liebig St",
    "sg:city":"Warrnambool",
    "sg:classifiers":[
        {
            "category":"Food & Beverages",
            "subcategory":"Specialty",
            "type":"Retail Goods"
        }
    ],
    "sg:phone":"+61 3 5562 9937",
    "sg:postcode":"3280",
    "sg:province":"VIC",
    "sg:tags":[
        "product",
        "health"
    ],
    "wof:name":"Healthy Alternatives",
    "wof:placetype":"venue"
},
  "geometry": {"coordinates":[142.48533630399999,-38.3816184998],"type":"Point"}
}