{
  "type": "Feature",
  "properties": {
    "addr:full":"1 Willow Rd Bowral NSW 2576",
    "addr:housenumber":"1",
    "addr:postcode":"2576",
    "addr:street":"Willow Rd",
    "iso:country":"AU",
    "sg:address":"1 Willow Rd",
    "sg:city":"Bowral",
    "sg:classifiers":[
        {
            "category":"Retail",
            "subcategory":"Repair Shop",
            "type":"Services"
        }
    ],
    "sg:phone":"+61 13 16 16",
    "sg:postcode":"2576",
    "sg:province":"NSW",
    "sg:tags":[
        "windscreen"
    ],
    "wof:name":"O&#039;Brien",
    "wof:placetype":"venue"
},
  "geometry": {"coordinates":[150.414916992,-34.4791564941],"type":"Point"}
}