{
  "type": "Feature",
  "properties": {
    "addr:full":"27 South St Granville NSW 2142",
    "addr:housenumber":"27",
    "addr:postcode":"2142",
    "addr:street":"South St",
    "iso:country":"AU",
    "sg:address":"27 South St",
    "sg:city":"Granville",
    "sg:classifiers":[
        {
            "category":"Banks & Credit Unions",
            "subcategory":"Bank",
            "type":"Services"
        }
    ],
    "sg:phone":"+61 13 20 32",
    "sg:postcode":"2142",
    "sg:province":"NSW",
    "wof:name":"Westpac",
    "wof:placetype":"venue"
},
  "geometry": {"coordinates":[151.011260986,-33.8335342407],"type":"Point"}
}