{
  "type": "Feature",
  "properties": {
    "addr:full":"5/ 7 Tumbi Creek Rd Berkeley Vale NSW 2261",
    "addr:housenumber":"/ 7",
    "addr:postcode":"2261",
    "addr:street":"Tumbi Creek Rd",
    "iso:country":"AU",
    "sg:address":"5/ 7 Tumbi Creek Rd",
    "sg:city":"Berkeley Vale",
    "sg:classifiers":[
        {
            "category":"Home & Garden",
            "subcategory":"Hardware",
            "type":"Retail Goods"
        }
    ],
    "sg:phone":"+61 2 4388 4033",
    "sg:postcode":"2261",
    "sg:province":"NSW",
    "sg:tags":[
        "printed",
        "circuit"
    ],
    "wof:name":"Screen Process Circuits",
    "wof:placetype":"venue"
},
  "geometry": {"coordinates":[151.444672,-33.359768],"type":"Point"}
}