{
  "type": "Feature",
  "properties": {
    "addr:full":"402 South Rd Moorabbin VIC 3189",
    "addr:housenumber":"402",
    "addr:postcode":"3189",
    "addr:street":"South Rd",
    "iso:country":"AU",
    "sg:address":"402 South Rd",
    "sg:city":"Moorabbin",
    "sg:classifiers":[
        {
            "category":"Utilities",
            "subcategory":"Water",
            "type":"Services"
        }
    ],
    "sg:phone":"+61 3 9553 4022",
    "sg:postcode":"3189",
    "sg:province":"VIC",
    "sg:tags":[
        "hot",
        "system"
    ],
    "wof:name":"Active Hot Water Services",
    "wof:placetype":"venue"
},
  "geometry": {"coordinates":[145.03977966299999,-37.9338760376],"type":"Point"}
}