{
  "type": "Feature",
  "properties": {
    "addr:full":"133 Rooke St Devonport TAS 7310",
    "addr:housenumber":"133",
    "addr:postcode":"7310",
    "addr:street":"Rooke St",
    "iso:country":"AU",
    "sg:address":"133 Rooke St",
    "sg:city":"Devonport",
    "sg:classifiers":[
        {
            "category":"Real Estate",
            "subcategory":"Real Estate Services",
            "type":"Services"
        }
    ],
    "sg:phone":"+61 3 6424 4888",
    "sg:postcode":"7310",
    "sg:province":"TAS",
    "sg:tags":[
        "listing"
    ],
    "wof:name":"John Ackroyd & Associates Real Estate Pty Ltd",
    "wof:placetype":"venue"
},
  "geometry": {"coordinates":[146.36082458499999,-41.1778831482],"type":"Point"}
}