{
  "type": "Feature",
  "properties": {
    "addr:full":"46- 52 Ferndell St Granville NSW 2142",
    "addr:housenumber":"52",
    "addr:postcode":"2142",
    "addr:street":"Ferndell St",
    "iso:country":"AU",
    "sg:address":"46- 52 Ferndell St",
    "sg:city":"Granville",
    "sg:classifiers":[
        {
            "category":"Bars & Pubs",
            "subcategory":"Gay Bar",
            "type":"Food & Drink"
        }
    ],
    "sg:phone":"+61 2 9645 1000",
    "sg:postcode":"2142",
    "sg:province":"NSW",
    "sg:tags":[
        "plywood",
        "veneer"
    ],
    "wof:name":"Processed Forest Products",
    "wof:placetype":"venue"
},
  "geometry": {"coordinates":[151.008056641,-33.8682250977],"type":"Point"}
}