{
  "type": "Feature",
  "properties": {
    "addr:full":"1 Mephan St Maribyrnong VIC 3032",
    "addr:housenumber":"1",
    "addr:postcode":"3032",
    "addr:street":"Mephan St",
    "iso:country":"AU",
    "sg:address":"1 Mephan St",
    "sg:city":"Maribyrnong",
    "sg:classifiers":[
        {
            "category":"Recreation",
            "type":"Entertainment"
        }
    ],
    "sg:phone":"+61 3 9318 1110",
    "sg:postcode":"3032",
    "sg:province":"VIC",
    "sg:tags":[
        "children's",
        "play",
        "programme"
    ],
    "wof:name":"Dizzys Castle Indoor Play Centre",
    "wof:placetype":"venue"
},
  "geometry": {"coordinates":[144.889984,-37.787109],"type":"Point"}
}