{
  "type": "Feature",
  "properties": {
    "iso:country":"AU",
    "sg:address":"60 James Rd",
    "sg:city":"Medowie",
    "sg:classifiers":[
        {
            "category":"Utilities",
            "subcategory":"Electric",
            "type":"Services"
        }
    ],
    "sg:phone":"+61 428 490 236",
    "sg:postcode":"2318",
    "sg:province":"NSW",
    "sg:tags":[
        "electrical",
        "contractor"
    ],
    "wof:name":"Bambach D G Pty Ltd",
    "wof:placetype":"venue"
},
  "geometry": {"coordinates":[151.882645,-32.746452],"type":"Point"}
}