{
  "type": "Feature",
  "properties": {
    "addr:full":"24 Depot Rd Dubbo NSW 2830",
    "addr:housenumber":"24",
    "addr:postcode":"2830",
    "addr:street":"Depot Rd",
    "iso:country":"AU",
    "sg:address":"24 Depot Rd",
    "sg:city":"Dubbo",
    "sg:classifiers":[
        {
            "category":"Retail",
            "subcategory":"Auto Repair",
            "type":"Services"
        }
    ],
    "sg:phone":"+61 2 6884 0155",
    "sg:postcode":"2830",
    "sg:province":"NSW",
    "sg:tags":[
        "electrical"
    ],
    "wof:name":"Century Batteries",
    "wof:placetype":"venue"
},
  "geometry": {"coordinates":[148.583740234,-32.2445983887],"type":"Point"}
}