{
  "type": "Feature",
  "properties": {
    "addr:full":"PO Box 7064 Dubbo NSW 2830",
    "addr:postcode":"2830",
    "iso:country":"AU",
    "sg:address":"PO Box 7064",
    "sg:city":"Dubbo",
    "sg:classifiers":[
        {
            "category":"Building & Trades",
            "subcategory":"Construction",
            "type":"Services"
        }
    ],
    "sg:phone":"+61 412 192 525",
    "sg:postcode":"2830",
    "sg:province":"NSW",
    "sg:tags":[
        "earth",
        "excavating",
        "moving",
        "contractor"
    ],
    "wof:name":"RA Riley Excavations",
    "wof:placetype":"venue"
},
  "geometry": {"coordinates":[148.60118102999999,-32.2478713989],"type":"Point"}
}