{
  "type": "Feature",
  "properties": {
    "addr:full":"10 Howard Ave Green Point NSW 2251",
    "addr:housenumber":"10",
    "addr:postcode":"2251",
    "addr:street":"Howard Ave",
    "iso:country":"AU",
    "sg:address":"10 Howard Ave",
    "sg:city":"Green Point",
    "sg:classifiers":[
        {
            "category":"Building & Trades",
            "subcategory":"Construction",
            "type":"Services"
        }
    ],
    "sg:phone":"+61 2 4365 2303",
    "sg:postcode":"2251",
    "sg:province":"NSW",
    "sg:tags":[
        "brick",
        "paving"
    ],
    "wof:name":"Landscape Business The",
    "wof:placetype":"venue"
},
  "geometry": {"coordinates":[151.38070678700001,-33.4433708191],"type":"Point"}
}