{
  "type": "Feature",
  "properties": {
    "iso:country":"AU",
    "sg:address":"34 Victoria Pde",
    "sg:city":"Thursday Island",
    "sg:classifiers":[
        {
            "category":"Food & Beverages",
            "subcategory":"Bakery",
            "type":"Retail Goods"
        }
    ],
    "sg:phone":"+61 7 4069 2090",
    "sg:postcode":"4875",
    "sg:province":"QLD",
    "sg:tags":[
        "baker"
    ],
    "wof:name":"Aunt Marys Bakery",
    "wof:placetype":"venue"
},
  "geometry": {"coordinates":[142.216995239,-10.5847272873],"type":"Point"}
}