{
  "type": "Feature",
  "properties": {
    "iso:country":"AU",
    "sg:address":"1380 Bailey Rd",
    "sg:city":"Glen Forrest",
    "sg:classifiers":[
        {
            "category":"Professional",
            "subcategory":"Art Services",
            "type":"Services"
        }
    ],
    "sg:phone":"+61 8 9298 8253",
    "sg:postcode":"6071",
    "sg:province":"WA",
    "sg:tags":[
        "artist"
    ],
    "wof:name":"Goddard Inta",
    "wof:placetype":"venue"
},
  "geometry": {"coordinates":[116.11538696300001,-31.9137992859],"type":"Point"}
}