{
  "type": "Feature",
  "properties": {
    "iso:country":"AU",
    "sg:address":"758 Centre Rd",
    "sg:city":"Bentleigh East",
    "sg:classifiers":[
        {
            "category":"Health Services",
            "subcategory":"Doctor",
            "type":"Services"
        }
    ],
    "sg:phone":"+61 3 9579 2400",
    "sg:postcode":"3165",
    "sg:province":"VIC",
    "sg:tags":[
        "medical",
        "practitioner"
    ],
    "wof:name":"MIA Victoria",
    "wof:placetype":"venue"
},
  "geometry": {"coordinates":[145.063232422,-37.9218025208],"type":"Point"}
}