{
  "type": "Feature",
  "properties": {
    "addr:full":"2a Alexander Ave Dandenong VIC 3175",
    "addr:housenumber":"2a",
    "addr:postcode":"3175",
    "addr:street":"Alexander Ave",
    "iso:country":"AU",
    "sg:address":"2a Alexander Ave",
    "sg:city":"Dandenong",
    "sg:classifiers":[
        {
            "category":"Building & Trades",
            "subcategory":"Equipment Rental",
            "type":"Services"
        }
    ],
    "sg:phone":"+61 3 9706 7522",
    "sg:postcode":"3175",
    "sg:province":"VIC",
    "sg:tags":[
        "party",
        "hire"
    ],
    "wof:name":"Turners Hire Service",
    "wof:placetype":"venue"
},
  "geometry": {"coordinates":[145.19671630900001,-37.9703521729],"type":"Point"}
}