{
  "type": "Feature",
  "properties": {
    "addr:full":"Dragon St Warwick QLD 4370",
    "addr:postcode":"4370",
    "addr:street":"Dragon St",
    "iso:country":"AU",
    "sg:address":"Dragon St",
    "sg:city":"Warwick",
    "sg:classifiers":[
        {
            "category":"Education",
            "subcategory":"University",
            "type":"Public Place"
        }
    ],
    "sg:phone":"+61 7 4661 5804",
    "sg:postcode":"4370",
    "sg:province":"QLD",
    "sg:tags":[
        "college",
        "tertiary"
    ],
    "wof:name":"Open Learning Centre",
    "wof:placetype":"venue"
},
  "geometry": {"coordinates":[152.02775573700001,-28.2165336609],"type":"Point"}
}