{
  "type": "Feature",
  "properties": {
    "addr:full":"Cnr Whip Crt & Craig St Long Gully VIC 3550",
    "addr:postcode":"3550",
    "addr:street":"Cnr Whip Crt & Craig St Long",
    "iso:country":"AU",
    "sg:address":"Cnr Whip Crt & Craig St",
    "sg:city":"Long Gully",
    "sg:classifiers":[
        {
            "category":"Retail",
            "subcategory":"Auto Repair",
            "type":"Services"
        }
    ],
    "sg:phone":"+61 3 5441 2710",
    "sg:postcode":"3550",
    "sg:province":"VIC",
    "sg:tags":[
        "fuel",
        "petrol",
        "injection"
    ],
    "wof:name":"Bendigo Carburettors",
    "wof:placetype":"venue"
},
  "geometry": {"coordinates":[144.263275147,-36.7417869568],"type":"Point"}
}