{
  "type": "Feature",
  "properties": {
    "iso:country":"AU",
    "sg:address":"Clifton St",
    "sg:city":"Euroa",
    "sg:classifiers":[
        {
            "category":"Retail",
            "subcategory":"Auto Repair",
            "type":"Services"
        }
    ],
    "sg:phone":"+61 3 8795 2702",
    "sg:postcode":"3666",
    "sg:province":"VIC",
    "sg:tags":[
        "repairer",
        "motor",
        "engineer"
    ],
    "wof:name":"Parker Bros Auto Co.",
    "wof:placetype":"venue"
},
  "geometry": {"coordinates":[145.57501220699999,-36.7535057068],"type":"Point"}
}