{
  "type": "Feature",
  "properties": {
    "addr:full":"35 Mill Ave Forest Hill VIC 3131",
    "addr:housenumber":"35",
    "addr:postcode":"3131",
    "addr:street":"Mill Ave",
    "iso:country":"AU",
    "sg:address":"35 Mill Ave",
    "sg:city":"Forest Hill",
    "sg:classifiers":[
        {
            "category":"Home & Garden",
            "subcategory":"Household Appliances",
            "type":"Retail Goods"
        }
    ],
    "sg:phone":"+61 3 9878 4295",
    "sg:postcode":"3131",
    "sg:province":"VIC",
    "sg:tags":[
        "heating",
        "system"
    ],
    "wof:name":"Frantec",
    "wof:placetype":"venue"
},
  "geometry": {"coordinates":[145.168823242,-37.8384780884],"type":"Point"}
}