{
  "type": "Feature",
  "properties": {
    "addr:full":"21 Kamholtz Crt Molendinar QLD 4214",
    "addr:housenumber":"21",
    "addr:postcode":"4214",
    "addr:street":"Kamholtz Crt",
    "iso:country":"AU",
    "sg:address":"21 Kamholtz Crt",
    "sg:city":"Molendinar",
    "sg:classifiers":[
        {
            "category":"Manufacturing",
            "subcategory":"Metals",
            "type":"Manufacturing & Wholesale Goods"
        }
    ],
    "sg:phone":"+61 7 5597 1622",
    "sg:postcode":"4214",
    "sg:province":"QLD",
    "sg:tags":[
        "steel",
        "fabricator",
        "mfrs"
    ],
    "wof:name":"Zacklee Fabrications",
    "wof:placetype":"venue"
},
  "geometry": {"coordinates":[153.35809326200001,-27.9865589142],"type":"Point"}
}