{
  "type": "Feature",
  "properties": {
    "addr:full":"Shop 12, &#039;The Boulevard&#039; 70 River St Ballina NSW 2478",
    "addr:housenumber":"shop 12 & # 039;70",
    "addr:postcode":"2478",
    "addr:street":"The Boulevard &;River St",
    "iso:country":"AU",
    "sg:address":"Shop 12, &#039;The Boulevard&#039; 70 River St",
    "sg:city":"Ballina",
    "sg:classifiers":[
        {
            "category":"Wholesale",
            "subcategory":"Medical Equipment & Supplies",
            "type":"Manufacturing & Wholesale Goods"
        }
    ],
    "sg:phone":"+61 2 6686 9886",
    "sg:postcode":"2478",
    "sg:province":"NSW",
    "sg:tags":[
        "scooter",
        "mobility"
    ],
    "wof:name":"Ballina Scooters",
    "wof:placetype":"venue"
},
  "geometry": {"coordinates":[153.562103272,-28.8712882996],"type":"Point"}
}