{
  "type": "Feature",
  "properties": {
    "iso:country":"AU",
    "sg:address":"Wilson St",
    "sg:city":"Collarenebri",
    "sg:classifiers":[
        {
            "category":"Cafe",
            "type":"Food & Drink"
        }
    ],
    "sg:phone":"+61 2 6756 2100",
    "sg:postcode":"2833",
    "sg:province":"NSW",
    "wof:name":"New Excelsior Cafe",
    "wof:placetype":"venue"
},
  "geometry": {"coordinates":[148.576263428,-29.5447788239],"type":"Point"}
}