{
  "type": "Feature",
  "properties": {
    "addr:full":"123 Kurnall Rd Welshpool WA 6106",
    "addr:housenumber":"123",
    "addr:postcode":"6106",
    "addr:street":"Kurnall Rd",
    "iso:country":"AU",
    "sg:address":"123 Kurnall Rd",
    "sg:city":"Welshpool",
    "sg:classifiers":[
        {
            "category":"Professional",
            "type":"Services"
        }
    ],
    "sg:phone":"+61 8 9458 2455",
    "sg:postcode":"6106",
    "sg:province":"WA",
    "sg:tags":[
        "transport"
    ],
    "wof:name":"Linfox",
    "wof:placetype":"venue"
},
  "geometry": {"coordinates":[115.960678101,-31.9910926819],"type":"Point"}
}