{
  "type": "Feature",
  "properties": {
    "addr:full":"Colquhoun Rd Lakes Entrance VIC 3909",
    "addr:postcode":"3909",
    "addr:street":"Colquhoun Rd Lakes",
    "iso:country":"AU",
    "sg:address":"Colquhoun Rd",
    "sg:city":"Lakes Entrance",
    "sg:classifiers":[
        {
            "category":"Building & Trades",
            "subcategory":"Construction",
            "type":"Services"
        }
    ],
    "sg:phone":"+61 3 5155 1490",
    "sg:postcode":"3909",
    "sg:province":"VIC",
    "sg:tags":[
        "contractor"
    ],
    "wof:name":"Bolding A.A. & G.R.",
    "wof:placetype":"venue"
},
  "geometry": {"coordinates":[148.00587463400001,-37.8661422729],"type":"Point"}
}