{
  "type": "Feature",
  "properties": {
    "addr:full":"Rialto North Tower, Lvl 24, 525 Collins St Melbourne VIC 3000",
    "addr:housenumber":"525",
    "addr:postcode":"3000",
    "addr:street":"Collins St",
    "iso:country":"AU",
    "sg:address":"Rialto North Tower, Lvl 24, 525 Collins St",
    "sg:city":"Melbourne",
    "sg:classifiers":[
        {
            "category":"Professional",
            "subcategory":"Research",
            "type":"Services"
        }
    ],
    "sg:phone":"+61 1800 627 253",
    "sg:postcode":"3000",
    "sg:province":"VIC",
    "sg:tags":[
        "market"
    ],
    "wof:name":"BIS Shrapnel",
    "wof:placetype":"venue"
},
  "geometry": {"coordinates":[144.95716857900001,-37.8183326721],"type":"Point"}
}