{
  "type": "Feature",
  "properties": {
    "addr:full":"92 East St Narrandera NSW 2700",
    "addr:housenumber":"92",
    "addr:postcode":"2700",
    "addr:street":"East St",
    "iso:country":"AU",
    "sg:address":"92 East St",
    "sg:city":"Narrandera",
    "sg:classifiers":[
        {
            "category":"Banks & Credit Unions",
            "subcategory":"Bank",
            "type":"Services"
        }
    ],
    "sg:phone":"+61 2 6959 9766",
    "sg:postcode":"2700",
    "sg:province":"NSW",
    "wof:name":"Bendigo Community Bank",
    "wof:placetype":"venue"
},
  "geometry": {"coordinates":[146.55328369099999,-34.7450027466],"type":"Point"}
}