{
  "type": "Feature",
  "properties": {
    "addr:full":"Lvl 3, 2 Help St West Chatswood NSW 2067",
    "addr:housenumber":"2",
    "addr:postcode":"2067",
    "addr:street":"Help St West",
    "iso:country":"AU",
    "sg:address":"Lvl 3, 2 Help St",
    "sg:city":"West Chatswood",
    "sg:classifiers":[
        {
            "category":"Banks & Credit Unions",
            "subcategory":"Financial Services",
            "type":"Services"
        }
    ],
    "sg:phone":"+61 2 9411 8855",
    "sg:postcode":"2067",
    "sg:province":"NSW",
    "sg:tags":[
        "loan",
        "finance",
        "mortgage"
    ],
    "wof:name":"Global Mortgages Pty Ltd",
    "wof:placetype":"venue"
},
  "geometry": {"coordinates":[151.18011474599999,-33.7957496643],"type":"Point"}
}