{
  "type": "Feature",
  "properties": {
    "iso:country":"AU",
    "sg:address":"9 Steptoe St",
    "sg:city":"Bundaberg",
    "sg:classifiers":[
        {
            "category":"Retail",
            "subcategory":"Auto Repair",
            "type":"Services"
        }
    ],
    "sg:phone":"+61 7 4152 8922",
    "sg:postcode":"4670",
    "sg:province":"QLD",
    "sg:tags":[
        "body",
        "builder",
        "motor"
    ],
    "wof:name":"A W D Engineering",
    "wof:placetype":"venue"
},
  "geometry": {"coordinates":[152.37422180199999,-24.8648147583],"type":"Point"}
}