{
  "type": "Feature",
  "properties": {
    "addr:full":"2 Maranui Ave Dee Why NSW 2099",
    "addr:housenumber":"2",
    "addr:postcode":"2099",
    "addr:street":"Maranui Ave",
    "iso:country":"AU",
    "sg:address":"2 Maranui Ave",
    "sg:city":"Dee Why",
    "sg:classifiers":[
        {
            "category":"Building & Trades",
            "subcategory":"Cleaning & Sanitation",
            "type":"Services"
        }
    ],
    "sg:phone":"+61 2 9971 4079",
    "sg:postcode":"2099",
    "sg:province":"NSW",
    "sg:tags":[
        "commercial",
        "maintenance"
    ],
    "wof:name":"R C M Building Maintenance",
    "wof:placetype":"venue"
},
  "geometry": {"coordinates":[151.28416442899999,-33.750038147],"type":"Point"}
}