{
  "type": "Feature",
  "properties": {
    "addr:full":"44 Fifth Ave South Townsville QLD 4810",
    "addr:housenumber":"44",
    "addr:postcode":"4810",
    "addr:street":"Fifth Ave",
    "iso:country":"AU",
    "sg:address":"44 Fifth Ave",
    "sg:city":"South Townsville",
    "sg:classifiers":[
        {
            "category":"Train Station",
            "subcategory":"Rail",
            "type":"Transportation"
        }
    ],
    "sg:phone":"+61 7 4772 6392",
    "sg:postcode":"4810",
    "sg:province":"QLD",
    "sg:tags":[
        "marine",
        "engineer"
    ],
    "wof:name":"Rosshaven Marine Pty Ltd",
    "wof:placetype":"venue"
},
  "geometry": {"coordinates":[146.82797199999999,-19.269014],"type":"Point"}
}