{
  "type": "Feature",
  "properties": {
    "iso:country":"AU",
    "sg:address":"8 Baldwin St",
    "sg:city":"Caloundra",
    "sg:classifiers":[
        {
            "category":"Autos & Motor Vehicles",
            "subcategory":"Boat Sales",
            "type":"Retail Goods"
        }
    ],
    "sg:phone":"+61 7 5491 1944",
    "sg:postcode":"4551",
    "sg:province":"QLD",
    "sg:tags":[
        "yacht"
    ],
    "sg:website":"http://www.ccpb.com",
    "wof:name":"Sunshine Coast Marine Centre",
    "wof:placetype":"venue"
},
  "geometry": {"coordinates":[153.11984252900001,-26.8044528961],"type":"Point"}
}