{
  "type": "Feature",
  "properties": {
    "iso:country":"AU",
    "sg:address":"127 Murlong St",
    "sg:city":"Swan Hill",
    "sg:classifiers":[
        {
            "category":"Building & Trades",
            "subcategory":"Construction",
            "type":"Services"
        }
    ],
    "sg:phone":"+61 3 5032 4323",
    "sg:postcode":"3585",
    "sg:province":"VIC",
    "sg:tags":[
        "earth",
        "excavating",
        "moving",
        "contractor"
    ],
    "wof:name":"Rowe G L",
    "wof:placetype":"venue"
},
  "geometry": {"coordinates":[143.54461699999999,-35.33828],"type":"Point"}
}