{
  "type": "Feature",
  "properties": {
    "addr:full":"227B Annangrove Rd Annangrove NSW 2156",
    "addr:housenumber":"227b",
    "addr:postcode":"2156",
    "addr:street":"Annangrove Rd",
    "iso:country":"AU",
    "sg:address":"227B Annangrove Rd",
    "sg:city":"Annangrove",
    "sg:classifiers":[
        {
            "category":"Landmark",
            "subcategory":"Unesco World Heritage Site",
            "type":"Public Place"
        }
    ],
    "sg:phone":"+61 1300 555 711",
    "sg:postcode":"2156",
    "sg:province":"NSW",
    "sg:tags":[
        "balloon",
        "hot",
        "air"
    ],
    "wof:name":"Cloud 9 Balloon Flights",
    "wof:placetype":"venue"
},
  "geometry": {"coordinates":[150.94659423799999,-33.6621131897],"type":"Point"}
}