{
  "type": "Feature",
  "properties": {
    "iso:country":"AU",
    "sg:address":"1/ 15 Henry Wilson Drv",
    "sg:city":"Rosebud",
    "sg:classifiers":[
        {
            "category":"Home & Garden",
            "subcategory":"Home Furnishings",
            "type":"Retail Goods"
        }
    ],
    "sg:phone":"+61 3 5986 2313",
    "sg:postcode":"3939",
    "sg:province":"VIC",
    "sg:tags":[
        "shower",
        "screen"
    ],
    "wof:name":"A. Peninsula Screens",
    "wof:placetype":"venue"
},
  "geometry": {"coordinates":[144.88490295400001,-38.3831253052],"type":"Point"}
}