{
  "type": "Feature",
  "properties": {
    "addr:full":"Botany St Randwick NSW 2031",
    "addr:postcode":"2031",
    "addr:street":"Botany St",
    "iso:country":"AU",
    "sg:address":"Botany St",
    "sg:city":"Randwick",
    "sg:classifiers":[
        {
            "category":"Education",
            "subcategory":"University",
            "type":"Public Place"
        }
    ],
    "sg:phone":"+61 2 9931 9490",
    "sg:postcode":"2031",
    "sg:province":"NSW",
    "sg:tags":[
        "college",
        "tertiary"
    ],
    "wof:name":"Australian Graduate School of Management",
    "wof:placetype":"venue"
},
  "geometry": {"coordinates":[151.23748779300001,-33.9129524231],"type":"Point"}
}