{
  "type": "Feature",
  "properties": {
    "addr:full":"Cnr Coventry & Athol Rds Evanston Gardens SA 5116",
    "addr:postcode":"5116",
    "addr:street":"Cnr",
    "iso:country":"AU",
    "sg:address":"Cnr Coventry & Athol Rds",
    "sg:city":"Evanston Gardens",
    "sg:classifiers":[
        {
            "category":"Food & Beverages",
            "subcategory":"Fruits & Vegetables",
            "type":"Retail Goods"
        }
    ],
    "sg:phone":"+61 8 8522 6804",
    "sg:postcode":"5116",
    "sg:province":"SA",
    "sg:tags":[
        "grower"
    ],
    "wof:name":"Prokopiou Nominees",
    "wof:placetype":"venue"
},
  "geometry": {"coordinates":[138.71778869600001,-34.6292724609],"type":"Point"}
}