{
  "type": "Feature",
  "properties": {
    "iso:country":"AU",
    "sg:address":"6 Capo D&#039;Orlando Drv",
    "sg:city":"Fremantle",
    "sg:classifiers":[
        {
            "category":"Autos & Motor Vehicles",
            "subcategory":"Boat Sales",
            "type":"Retail Goods"
        }
    ],
    "sg:phone":"+61 8 9335 4800",
    "sg:postcode":"6160",
    "sg:province":"WA",
    "sg:tags":[
        "equipment",
        "yacht"
    ],
    "sg:website":"http://www.coastalmarine.com.au",
    "wof:name":"Coastal Marine Electronics",
    "wof:placetype":"venue"
},
  "geometry": {"coordinates":[115.75592,-32.05257],"type":"Point"}
}