{
  "type": "Feature",
  "properties": {
    "iso:country":"AU",
    "sg:address":"18- 24 Argyle St",
    "sg:city":"The Rocks",
    "sg:classifiers":[
        {
            "category":"Shopping",
            "subcategory":"Department Store",
            "type":"Retail Goods"
        }
    ],
    "sg:phone":"+61 2 9251 4800",
    "sg:postcode":"2000",
    "sg:province":"NSW",
    "wof:name":"Argyle Stores",
    "wof:placetype":"venue"
},
  "geometry": {"coordinates":[151.20831298799999,-33.8590278625],"type":"Point"}
}