{
  "type": "Feature",
  "properties": {
    "addr:full":"496 Golden Four Drv Tugun QLD 4224",
    "addr:housenumber":"496",
    "addr:postcode":"4224",
    "addr:street":"Golden Four Drv",
    "iso:country":"AU",
    "sg:address":"496 Golden Four Drv",
    "sg:city":"Tugun",
    "sg:classifiers":[
        {
            "category":"Food & Beverages",
            "subcategory":"Bakery",
            "type":"Retail Goods"
        }
    ],
    "sg:phone":"+61 7 5534 3288",
    "sg:postcode":"4224",
    "sg:province":"QLD",
    "sg:tags":[
        "cake",
        "shop",
        "pastry"
    ],
    "wof:name":"Sticky Buns",
    "wof:placetype":"venue"
},
  "geometry": {"coordinates":[153.492385864,-28.1412029266],"type":"Point"}
}