{
  "type": "Feature",
  "properties": {
    "iso:country":"AU",
    "sg:address":"11 Websters Rd",
    "sg:city":"Templestowe",
    "sg:classifiers":[
        {
            "category":"Manufacturing",
            "subcategory":"Paper Products",
            "type":"Manufacturing & Wholesale Goods"
        }
    ],
    "sg:phone":"+61 3 9846 8009",
    "sg:postcode":"3106",
    "sg:province":"VIC",
    "sg:tags":[
        "disposable"
    ],
    "wof:name":"Star Packaging",
    "wof:placetype":"venue"
},
  "geometry": {"coordinates":[145.16726684599999,-37.7489814758],"type":"Point"}
}