{
  "type": "Feature",
  "properties": {
    "iso:country":"AU",
    "sg:address":"3 Cheney Pl",
    "sg:city":"Mitchell",
    "sg:classifiers":[
        {
            "category":"Commercial Area",
            "type":"Public Place"
        }
    ],
    "sg:phone":"+61 2 6123 0200",
    "sg:postcode":"2911",
    "sg:province":"ACT",
    "sg:tags":[
        "heavy",
        "carrier"
    ],
    "wof:name":"Canberra Carways Pty Ltd",
    "wof:placetype":"venue"
},
  "geometry": {"coordinates":[149.141067505,-35.2123832703],"type":"Point"}
}