{
  "type": "Feature",
  "properties": {
    "iso:country":"AU",
    "sg:address":"460 Beaufort St",
    "sg:city":"Highgate",
    "sg:classifiers":[
        {
            "category":"Retail",
            "subcategory":"Veterinary Services",
            "type":"Services"
        }
    ],
    "sg:phone":"+61 8 9328 7966",
    "sg:postcode":"6003",
    "sg:province":"WA",
    "sg:tags":[
        "surgeon"
    ],
    "wof:name":"Beaufort Veterinary Clinic",
    "wof:placetype":"venue"
},
  "geometry": {"coordinates":[115.869132996,-31.9395008087],"type":"Point"}
}