{
  "type": "Feature",
  "properties": {
    "iso:country":"AU",
    "sg:address":"540 Lane St",
    "sg:city":"Broken Hill",
    "sg:classifiers":[
        {
            "category":"Insurance",
            "subcategory":"Insurance Agent",
            "type":"Services"
        }
    ],
    "sg:phone":"+61 8 8087 5619",
    "sg:postcode":"2880",
    "sg:province":"NSW",
    "wof:name":"Blake Geoff & Susanne",
    "wof:placetype":"venue"
},
  "geometry": {"coordinates":[141.469573975,-31.9471721649],"type":"Point"}
}