{
  "type": "Feature",
  "properties": {
    "iso:country":"AU",
    "sg:address":"Burwood Hwy",
    "sg:city":"Broadmeadows",
    "sg:classifiers":[
        {
            "category":"Fast Food",
            "type":"Food & Drink"
        }
    ],
    "sg:phone":"+61 3 9302 1871",
    "sg:postcode":"3047",
    "sg:province":"VIC",
    "sg:tags":[
        "away",
        "take"
    ],
    "wof:name":"Sushi Sushi",
    "wof:placetype":"venue"
},
  "geometry": {"coordinates":[144.87864685100001,-37.7081642151],"type":"Point"}
}