{
  "type": "Feature",
  "properties": {
    "iso:country":"AU",
    "sg:address":"9 Toxteth Ave",
    "sg:city":"Austinmer",
    "sg:classifiers":[
        {
            "category":"Building & Trades",
            "subcategory":"Construction",
            "type":"Services"
        }
    ],
    "sg:phone":"+61 2 4268 2855",
    "sg:postcode":"2515",
    "sg:province":"NSW",
    "sg:tags":[
        "contractor"
    ],
    "wof:name":"Gray Malcolm Pty. Ltd.",
    "wof:placetype":"venue"
},
  "geometry": {"coordinates":[150.93606600000001,-34.304508],"type":"Point"}
}