{
  "type": "Feature",
  "properties": {
    "addr:full":"2/ 291 Morayfield Rd Morayfield QLD 4506",
    "addr:housenumber":"/ 291",
    "addr:postcode":"4506",
    "addr:street":"Morayfield Rd",
    "iso:country":"AU",
    "sg:address":"2/ 291 Morayfield Rd",
    "sg:city":"Morayfield",
    "sg:classifiers":[
        {
            "category":"Retail",
            "subcategory":"Auto Repair",
            "type":"Services"
        }
    ],
    "sg:phone":"+61 7 5497 8899",
    "sg:postcode":"4506",
    "sg:province":"QLD",
    "sg:tags":[
        "wheel",
        "balancing",
        "alignment"
    ],
    "wof:name":"Tyres Galore",
    "wof:placetype":"venue"
},
  "geometry": {"coordinates":[152.95208740199999,-27.1139163971],"type":"Point"}
}