{
  "type": "Feature",
  "properties": {
    "addr:full":"Heaths Rd North Mackay QLD 4740",
    "addr:postcode":"4740",
    "addr:street":"Heaths Rd",
    "iso:country":"AU",
    "sg:address":"Heaths Rd",
    "sg:city":"North Mackay",
    "sg:classifiers":[
        {
            "category":"Home & Garden",
            "subcategory":"Furniture",
            "type":"Retail Goods"
        }
    ],
    "sg:phone":"+61 7 4942 1133",
    "sg:postcode":"4740",
    "sg:province":"QLD",
    "sg:tags":[
        "outdoor"
    ],
    "wof:name":"Mackay Leisuretime Outdoor Furniture Specialist",
    "wof:placetype":"venue"
},
  "geometry": {"coordinates":[149.16304,-21.129229],"type":"Point"}
}