{
  "type": "Feature",
  "properties": {
    "addr:full":"459A Torrens Rd Woodville Park SA 5011",
    "addr:housenumber":"459a",
    "addr:postcode":"5011",
    "addr:street":"Torrens Rd",
    "iso:country":"AU",
    "sg:address":"459A Torrens Rd",
    "sg:city":"Woodville Park",
    "sg:classifiers":[
        {
            "category":"Professional",
            "subcategory":"Accounting & Tax Preparation",
            "type":"Services"
        }
    ],
    "sg:phone":"+61 8 8345 4774",
    "sg:postcode":"5011",
    "sg:province":"SA",
    "sg:tags":[
        "accountant",
        "auditor"
    ],
    "wof:name":"H&R Block",
    "wof:placetype":"venue"
},
  "geometry": {"coordinates":[138.54896545400001,-34.8756217957],"type":"Point"}
}