{
  "type": "Feature",
  "properties": {
    "addr:full":"529 Burke Rd Camberwell VIC 3124",
    "addr:housenumber":"529",
    "addr:postcode":"3124",
    "addr:street":"Burke Rd",
    "iso:country":"AU",
    "sg:address":"529 Burke Rd",
    "sg:city":"Camberwell",
    "sg:classifiers":[
        {
            "category":"Retail",
            "subcategory":"Veterinary Services",
            "type":"Services"
        }
    ],
    "sg:phone":"+61 3 9822 3268",
    "sg:postcode":"3124",
    "sg:province":"VIC",
    "sg:tags":[
        "surgeon"
    ],
    "wof:name":"Jennings Cathy Dr",
    "wof:placetype":"venue"
},
  "geometry": {"coordinates":[145.054153442,-37.8439559937],"type":"Point"}
}