{
  "type": "Feature",
  "properties": {
    "iso:country":"AU",
    "sg:address":"89 Empire Day Drv",
    "sg:city":"Daleys Point",
    "sg:classifiers":[
        {
            "category":"Coffee & Tea",
            "type":"Food & Drink"
        }
    ],
    "sg:phone":"+61 2 4341 2866",
    "sg:postcode":"2257",
    "sg:province":"NSW",
    "sg:tags":[
        "kayak",
        "canoe"
    ],
    "wof:name":"C-Kayak Australia",
    "wof:placetype":"venue"
},
  "geometry": {"coordinates":[151.35392761200001,-33.497215271],"type":"Point"}
}