{
  "type": "Feature",
  "properties": {
    "addr:full":"Hollis Rd Compton SA 5290",
    "addr:postcode":"5290",
    "addr:street":"Hollis Rd",
    "iso:country":"AU",
    "sg:address":"Hollis Rd",
    "sg:city":"Compton",
    "sg:classifiers":[
        {
            "category":"Manufacturing",
            "subcategory":"Musical Instruments",
            "type":"Manufacturing & Wholesale Goods"
        }
    ],
    "sg:phone":"+61 8 8725 0963",
    "sg:postcode":"5290",
    "sg:province":"SA",
    "sg:tags":[
        "logging",
        "timber"
    ],
    "wof:name":"G & R Logging Pty Ltd",
    "wof:placetype":"venue"
},
  "geometry": {"coordinates":[140.78360000000001,-37.830528],"type":"Point"}
}