{
  "type": "Feature",
  "properties": {
    "addr:full":"46 Blinzinger Rd Banyo QLD 4014",
    "addr:housenumber":"46",
    "addr:postcode":"4014",
    "addr:street":"Blinzinger Rd",
    "iso:country":"AU",
    "sg:address":"46 Blinzinger Rd",
    "sg:city":"Banyo",
    "sg:classifiers":[
        {
            "category":"Professional",
            "subcategory":"Testing Lab",
            "type":"Services"
        }
    ],
    "sg:phone":"+61 7 3407 4979",
    "sg:postcode":"4014",
    "sg:province":"QLD",
    "sg:tags":[
        "equipment"
    ],
    "wof:name":"Energex",
    "wof:placetype":"venue"
},
  "geometry": {"coordinates":[153.06967163100001,-27.3768959045],"type":"Point"}
}