{
  "type": "Feature",
  "properties": {
    "addr:full":"PO Box 123 Officer VIC 3809",
    "addr:postcode":"3809",
    "iso:country":"AU",
    "sg:address":"PO Box 123",
    "sg:city":"Officer",
    "sg:classifiers":[
        {
            "category":"Wholesale",
            "subcategory":"Scrap",
            "type":"Manufacturing & Wholesale Goods"
        }
    ],
    "sg:phone":"+61 411 556 746",
    "sg:postcode":"3809",
    "sg:province":"VIC",
    "sg:tags":[
        "merchant",
        "metal"
    ],
    "wof:name":"B & H Scrap Removals",
    "wof:placetype":"venue"
},
  "geometry": {"coordinates":[145.406036,-38.05938],"type":"Point"}
}