{
  "type": "Feature",
  "properties": {
    "addr:full":"25 Andrew St Esperance WA 6450",
    "addr:housenumber":"25",
    "addr:postcode":"6450",
    "addr:street":"Andrew St",
    "iso:country":"AU",
    "sg:address":"25 Andrew St",
    "sg:city":"Esperance",
    "sg:classifiers":[
        {
            "category":"Autos & Motor Vehicles",
            "subcategory":"Fuel & Gas Station",
            "type":"Retail Goods"
        }
    ],
    "sg:phone":"+61 8 9071 2403",
    "sg:postcode":"6450",
    "sg:province":"WA",
    "wof:name":"Shell Co Of Australia Ltd The",
    "wof:placetype":"venue"
},
  "geometry": {"coordinates":[121.891616821,-33.8612365723],"type":"Point"}
}