{
  "type": "Feature",
  "properties": {
    "iso:country":"AU",
    "sg:address":"281 Port Rd",
    "sg:city":"Hindmarsh",
    "sg:classifiers":[
        {
            "category":"Health Services",
            "subcategory":"Dentist",
            "type":"Services"
        }
    ],
    "sg:phone":"+61 8 8346 3940",
    "sg:postcode":"5007",
    "sg:province":"SA",
    "wof:name":"Harms Andrew",
    "wof:placetype":"venue"
},
  "geometry": {"coordinates":[138.56932067899999,-34.9030265808],"type":"Point"}
}