{
  "type": "Feature",
  "properties": {
    "addr:full":"22 Watt St Gosford NSW 2250",
    "addr:housenumber":"22",
    "addr:postcode":"2250",
    "addr:street":"Watt St",
    "iso:country":"AU",
    "sg:address":"22 Watt St",
    "sg:city":"Gosford",
    "sg:classifiers":[
        {
            "category":"Health Services",
            "subcategory":"Doctor",
            "type":"Services"
        }
    ],
    "sg:phone":"+61 2 4324 1444",
    "sg:postcode":"2250",
    "sg:province":"NSW",
    "sg:tags":[
        "medical",
        "practitioner"
    ],
    "wof:name":"Cooper A J",
    "wof:placetype":"venue"
},
  "geometry": {"coordinates":[151.34361267099999,-33.4234199524],"type":"Point"}
}