{
  "type": "Feature",
  "properties": {
    "iso:country":"AU",
    "sg:address":"Unit 5, 1 Cnr Hill & Burroway Rd",
    "sg:city":"Homebush Bay",
    "sg:classifiers":[
        {
            "category":"Shopping",
            "subcategory":"Party Supplies",
            "type":"Retail Goods"
        }
    ],
    "sg:phone":"+61 2 9647 2151",
    "sg:postcode":"2127",
    "sg:province":"NSW",
    "wof:name":"Discount Party Warehouse",
    "wof:placetype":"venue"
},
  "geometry": {"coordinates":[151.07966613799999,-33.8240890503],"type":"Point"}
}