{
  "type": "Feature",
  "properties": {
    "addr:full":"276 Norton St Leichhardt NSW 2040",
    "addr:housenumber":"276",
    "addr:postcode":"2040",
    "addr:street":"Norton St",
    "iso:country":"AU",
    "sg:address":"276 Norton St",
    "sg:city":"Leichhardt",
    "sg:classifiers":[
        {
            "category":"Building & Trades",
            "subcategory":"Landscaping Services",
            "type":"Services"
        }
    ],
    "sg:phone":"+61 2 9558 8622",
    "sg:postcode":"2040",
    "sg:province":"NSW",
    "sg:tags":[
        "fertilizer",
        "spreading",
        "insecticide"
    ],
    "wof:name":"A1 White Ant Termite Specialist Pty Ltd",
    "wof:placetype":"venue"
},
  "geometry": {"coordinates":[151.15617399999999,-33.877758],"type":"Point"}
}