{
  "type": "Feature",
  "properties": {
    "addr:full":"19 Kingswood Ave Onkaparinga Hills SA 5163",
    "addr:housenumber":"19",
    "addr:postcode":"5163",
    "addr:street":"Kingswood Ave",
    "iso:country":"AU",
    "sg:address":"19 Kingswood Ave",
    "sg:city":"Onkaparinga Hills",
    "sg:classifiers":[
        {
            "category":"Building & Trades",
            "subcategory":"Cleaning & Sanitation",
            "type":"Services"
        }
    ],
    "sg:phone":"+61 417 003 285",
    "sg:postcode":"5163",
    "sg:province":"SA",
    "sg:tags":[
        "window"
    ],
    "wof:name":"Mark C Lahiff Window Cleaning Services",
    "wof:placetype":"venue"
},
  "geometry": {"coordinates":[138.53883361800001,-35.1431503296],"type":"Point"}
}