{
  "type": "Feature",
  "properties": {
    "addr:full":"Shop CG29A Canberra Centre, City Walk, Civic Square Canberra ACT 2601",
    "addr:postcode":"2601",
    "iso:country":"AU",
    "sg:address":"Shop CG29A Canberra Centre, City Walk, Civic Square",
    "sg:city":"Canberra",
    "sg:classifiers":[
        {
            "category":"Shopping",
            "subcategory":"Mobile Phones",
            "type":"Retail Goods"
        }
    ],
    "sg:phone":"+61 2 6257 9600",
    "sg:postcode":"2601",
    "sg:province":"ACT",
    "sg:tags":[
        "telephone",
        "accessory"
    ],
    "wof:name":"Optus World",
    "wof:placetype":"venue"
},
  "geometry": {"coordinates":[149.130249023,-35.2772827148],"type":"Point"}
}