{
  "type": "Feature",
  "properties": {
    "iso:country":"AU",
    "sg:address":"542 Goodwood Rd",
    "sg:city":"Daw Park",
    "sg:classifiers":[
        {
            "category":"Food & Beverages",
            "subcategory":"Fruits & Vegetables",
            "type":"Retail Goods"
        }
    ],
    "sg:phone":"+61 8 8276 9955",
    "sg:postcode":"5041",
    "sg:province":"SA",
    "sg:tags":[
        "greengrocer",
        "fruiterer"
    ],
    "wof:name":"Bridgewater Greengrocer",
    "wof:placetype":"venue"
},
  "geometry": {"coordinates":[138.591766,-34.979816],"type":"Point"}
}