{
  "type": "Feature",
  "properties": {
    "addr:full":"17 Koel Crt Carrum Downs VIC 3201",
    "addr:housenumber":"17",
    "addr:postcode":"3201",
    "addr:street":"Koel Crt",
    "iso:country":"AU",
    "sg:address":"17 Koel Crt",
    "sg:city":"Carrum Downs",
    "sg:classifiers":[
        {
            "category":"Insurance",
            "subcategory":"Life Insurance",
            "type":"Services"
        }
    ],
    "sg:phone":"+61 3 9776 4110",
    "sg:postcode":"3201",
    "sg:province":"VIC",
    "wof:name":"AAA Financial Group",
    "wof:placetype":"venue"
},
  "geometry": {"coordinates":[145.173416,-38.107113],"type":"Point"}
}