{
  "type": "Feature",
  "properties": {
    "iso:country":"AU",
    "sg:address":"36 Dampier St",
    "sg:city":"Tamworth",
    "sg:classifiers":[
        {
            "category":"Autos & Motor Vehicles",
            "subcategory":"Automobile Sales",
            "type":"Retail Goods"
        }
    ],
    "sg:phone":"+61 2 6762 0101",
    "sg:postcode":"2340",
    "sg:province":"NSW",
    "sg:tags":[
        "car",
        "used"
    ],
    "wof:name":"Westside Autos",
    "wof:placetype":"venue"
},
  "geometry": {"coordinates":[150.89784240700001,-31.0954036713],"type":"Point"}
}