{
  "type": "Feature",
  "properties": {
    "iso:country":"AU",
    "sg:address":"41 Wason St",
    "sg:city":"Milton",
    "sg:classifiers":[
        {
            "category":"Shopping",
            "subcategory":"Antiques",
            "type":"Retail Goods"
        }
    ],
    "sg:phone":"+61 2 4454 4538",
    "sg:postcode":"2538",
    "sg:province":"NSW",
    "sg:tags":[
        "restoration",
        "reproduction"
    ],
    "wof:name":"Milton Restoration Supplies",
    "wof:placetype":"venue"
},
  "geometry": {"coordinates":[150.435745239,-35.3164596558],"type":"Point"}
}