{
  "type": "Feature",
  "properties": {
    "iso:country":"AU",
    "sg:address":"19 Yennora Ave",
    "sg:city":"Yennora",
    "sg:classifiers":[
        {
            "category":"Professional",
            "type":"Services"
        }
    ],
    "sg:phone":"+61 2 9892 3551",
    "sg:postcode":"2161",
    "sg:province":"NSW",
    "sg:tags":[
        "courier"
    ],
    "wof:name":"JTC Transport",
    "wof:placetype":"venue"
},
  "geometry": {"coordinates":[150.97137451200001,-33.8618278503],"type":"Point"}
}