{
  "type": "Feature",
  "properties": {
    "addr:full":"Shop 52, Salamander Shopping Centre 2 Town Cntr Circuit Salamander Bay NSW 2317",
    "addr:housenumber":"shop 52;2",
    "addr:postcode":"2317",
    "addr:street":"Salamander Shopping;Town Cntr Circuit Salamander",
    "iso:country":"AU",
    "sg:address":"Shop 52, Salamander Shopping Centre 2 Town Cntr Circuit",
    "sg:city":"Salamander Bay",
    "sg:classifiers":[
        {
            "category":"Personal",
            "subcategory":"Beauty Salon",
            "type":"Services"
        }
    ],
    "sg:phone":"+61 2 4982 0953",
    "sg:postcode":"2317",
    "sg:province":"NSW",
    "sg:tags":[
        "hairdresser"
    ],
    "wof:name":"Just Cuts",
    "wof:placetype":"venue"
},
  "geometry": {"coordinates":[152.08209199999999,-32.731091],"type":"Point"}
}