{
  "type": "Feature",
  "properties": {
    "iso:country":"AU",
    "sg:address":"158 Witt St",
    "sg:city":"Benalla",
    "sg:classifiers":[
        {
            "category":"Building & Trades",
            "subcategory":"Construction",
            "type":"Services"
        }
    ],
    "sg:phone":"+61 408 530 643",
    "sg:postcode":"3672",
    "sg:province":"VIC",
    "sg:tags":[
        "earth",
        "excavating",
        "moving",
        "contractor"
    ],
    "wof:name":"Brad Biddle",
    "wof:placetype":"venue"
},
  "geometry": {"coordinates":[146.000565,-36.534126],"type":"Point"}
}