{
  "type": "Feature",
  "properties": {
    "iso:country":"AU",
    "sg:address":"Level 1/ 38 Misterton St",
    "sg:city":"Fortitude Valley",
    "sg:classifiers":[
        {
            "category":"Health Services",
            "subcategory":"Doctor",
            "type":"Services"
        }
    ],
    "sg:phone":"+61 7 3852 6800",
    "sg:postcode":"4006",
    "sg:province":"QLD",
    "sg:tags":[
        "medical",
        "practitioner"
    ],
    "wof:name":"Belt Paul J Dr",
    "wof:placetype":"venue"
},
  "geometry": {"coordinates":[153.03225707999999,-27.4535427094],"type":"Point"}
}