{
  "type": "Feature",
  "properties": {
    "iso:country":"AU",
    "sg:address":"22 Rushton Drv",
    "sg:city":"Kanahooka",
    "sg:classifiers":[
        {
            "category":"Building & Trades",
            "subcategory":"Construction",
            "type":"Services"
        }
    ],
    "sg:phone":"+61 2 4261 7022",
    "sg:postcode":"2530",
    "sg:province":"NSW",
    "sg:tags":[
        "contractor"
    ],
    "wof:name":"N & T Buildings Pty Ltd",
    "wof:placetype":"venue"
},
  "geometry": {"coordinates":[150.79861450199999,-34.496547699],"type":"Point"}
}