{
  "type": "Feature",
  "properties": {
    "addr:full":"91 Grafton St Cairns QLD 4870",
    "addr:housenumber":"91",
    "addr:postcode":"4870",
    "addr:street":"Grafton St",
    "iso:country":"AU",
    "sg:address":"91 Grafton St",
    "sg:city":"Cairns",
    "sg:classifiers":[
        {
            "category":"Health Services",
            "subcategory":"Health Practitioner",
            "type":"Services"
        }
    ],
    "sg:phone":"+61 407 456 515",
    "sg:postcode":"4870",
    "sg:province":"QLD",
    "sg:tags":[
        "hypnotherapy"
    ],
    "wof:name":"Harding Pete",
    "wof:placetype":"venue"
},
  "geometry": {"coordinates":[145.775100708,-16.9234237671],"type":"Point"}
}