{
  "type": "Feature",
  "properties": {
    "iso:country":"AU",
    "sg:address":"19 Cornwall St",
    "sg:city":"Rose Bay",
    "sg:classifiers":[
        {
            "category":"Professional",
            "subcategory":"Art Services",
            "type":"Services"
        }
    ],
    "sg:phone":"+61 3 6243 8302",
    "sg:postcode":"7015",
    "sg:province":"TAS",
    "sg:tags":[
        "decorator",
        "painter"
    ],
    "wof:name":"Cobden Painting & Maintenance Service",
    "wof:placetype":"venue"
},
  "geometry": {"coordinates":[147.35877990700001,-42.8589553833],"type":"Point"}
}