{
  "type": "Feature",
  "properties": {
    "iso:country":"AU",
    "sg:address":"175a Alison Rd",
    "sg:city":"Randwick",
    "sg:classifiers":[
        {
            "category":"Government",
            "subcategory":"Customs House",
            "type":"Public Place"
        }
    ],
    "sg:phone":"+61 2 9399 7799",
    "sg:postcode":"2031",
    "sg:province":"NSW",
    "sg:tags":[
        "title",
        "management",
        "stratum"
    ],
    "wof:name":"KSL Strata Management",
    "wof:placetype":"venue"
},
  "geometry": {"coordinates":[151.23997497600001,-33.9129676819],"type":"Point"}
}