{
  "type": "Feature",
  "properties": {
    "addr:full":"PO Box 1578 Chatswood NSW 2057",
    "addr:postcode":"2057",
    "iso:country":"AU",
    "sg:address":"PO Box 1578",
    "sg:city":"Chatswood",
    "sg:classifiers":[
        {
            "category":"Shopping",
            "subcategory":"Clothing, Apparel, & Fashions",
            "type":"Retail Goods"
        }
    ],
    "sg:phone":"+61 2 9411 5386",
    "sg:postcode":"2057",
    "sg:province":"NSW",
    "sg:tags":[
        "maternity",
        "wear"
    ],
    "wof:name":"Queen Bee Maternity",
    "wof:placetype":"venue"
},
  "geometry": {"coordinates":[151.19012499999999,-33.792439],"type":"Point"}
}