{
  "type": "Feature",
  "properties": {
    "addr:full":"62 Cliftlands Rd Scone NSW 2337",
    "addr:housenumber":"62",
    "addr:postcode":"2337",
    "addr:street":"Cliftlands Rd",
    "iso:country":"AU",
    "sg:address":"62 Cliftlands Rd",
    "sg:city":"Scone",
    "sg:classifiers":[
        {
            "category":"Wholesale",
            "subcategory":"Farm Supplies",
            "type":"Manufacturing & Wholesale Goods"
        }
    ],
    "sg:phone":"+61 418 262 411",
    "sg:postcode":"2337",
    "sg:province":"NSW",
    "sg:tags":[
        "feed",
        "supplement",
        "stock"
    ],
    "wof:name":"Hunter Valley Stock Feeds",
    "wof:placetype":"venue"
},
  "geometry": {"coordinates":[150.83987426799999,-32.0573043823],"type":"Point"}
}