{
  "type": "Feature",
  "properties": {
    "addr:full":"645 Forest Rd Peakhurst NSW 2210",
    "addr:housenumber":"645",
    "addr:postcode":"2210",
    "addr:street":"Forest Rd",
    "iso:country":"AU",
    "sg:address":"645 Forest Rd",
    "sg:city":"Peakhurst",
    "sg:classifiers":[
        {
            "category":"Building & Trades",
            "subcategory":"Construction",
            "type":"Services"
        }
    ],
    "sg:phone":"+61 419 293 495",
    "sg:postcode":"2210",
    "sg:province":"NSW",
    "sg:tags":[
        "contractor"
    ],
    "wof:name":"Jim Firmstone Building Services",
    "wof:placetype":"venue"
},
  "geometry": {"coordinates":[151.04843099999999,-33.971199],"type":"Point"}
}