{
  "type": "Feature",
  "properties": {
    "iso:country":"AU",
    "sg:address":"Shop 14 Hometown, Cnr Lexington & Logan Rds",
    "sg:city":"Underwood",
    "sg:classifiers":[
        {
            "category":"Retail",
            "subcategory":"Veterinary Services",
            "type":"Services"
        }
    ],
    "sg:phone":"+61 7 3841 7011",
    "sg:postcode":"4119",
    "sg:province":"QLD",
    "sg:tags":[
        "surgeon"
    ],
    "wof:name":"Veterinary Specialist Services",
    "wof:placetype":"venue"
},
  "geometry": {"coordinates":[153.12213134800001,-27.6128444672],"type":"Point"}
}