{
  "type": "Feature",
  "properties": {
    "addr:full":"401 Chapel St South Yarra VIC 3141",
    "addr:housenumber":"401",
    "addr:postcode":"3141",
    "addr:street":"Chapel St",
    "iso:country":"AU",
    "sg:address":"401 Chapel St",
    "sg:city":"South Yarra",
    "sg:classifiers":[
        {
            "category":"Shopping",
            "subcategory":"Clothing, Apparel, & Fashions",
            "type":"Retail Goods"
        }
    ],
    "sg:phone":"+61 3 9694 1270",
    "sg:postcode":"3141",
    "sg:province":"VIC",
    "sg:tags":[
        "boutique"
    ],
    "wof:name":"Ed Hardy Store",
    "wof:placetype":"venue"
},
  "geometry": {"coordinates":[144.994262695,-37.8453369141],"type":"Point"}
}