{
  "type": "Feature",
  "properties": {
    "addr:full":"4 Grace Ave Warrnambool VIC 3280",
    "addr:housenumber":"4",
    "addr:postcode":"3280",
    "addr:street":"Grace Ave",
    "iso:country":"AU",
    "sg:address":"4 Grace Ave",
    "sg:city":"Warrnambool",
    "sg:classifiers":[
        {
            "category":"Retail",
            "subcategory":"Auto Repair",
            "type":"Services"
        }
    ],
    "sg:phone":"+61 3 5562 0118",
    "sg:postcode":"3280",
    "sg:province":"VIC",
    "sg:tags":[
        "electrical"
    ],
    "wof:name":"Peter Molans Auto Electrical",
    "wof:placetype":"venue"
},
  "geometry": {"coordinates":[142.48088073700001,-38.3821678162],"type":"Point"}
}