{
  "type": "Feature",
  "properties": {
    "addr:full":"Shop 3, 1331 North East Rd Tea Tree Gully SA 5091",
    "addr:housenumber":"shop 3 1331",
    "addr:postcode":"5091",
    "addr:street":"North East Rd Tea Tree",
    "iso:country":"AU",
    "sg:address":"Shop 3, 1331 North East Rd",
    "sg:city":"Tea Tree Gully",
    "sg:classifiers":[
        {
            "category":"Personal",
            "subcategory":"Massage",
            "type":"Services"
        }
    ],
    "sg:phone":"+61 8 8396 7677",
    "sg:postcode":"5091",
    "sg:province":"SA",
    "sg:tags":[
        "therapy"
    ],
    "wof:name":"Spirit Health Care Studio",
    "wof:placetype":"venue"
},
  "geometry": {"coordinates":[138.728912353,-34.8207778931],"type":"Point"}
}