{
  "type": "Feature",
  "properties": {
    "addr:full":"Horn Rd Aspley QLD 4034",
    "addr:postcode":"4034",
    "addr:street":"Horn Rd",
    "iso:country":"AU",
    "sg:address":"Horn Rd",
    "sg:city":"Aspley",
    "sg:classifiers":[
        {
            "category":"Social Services",
            "subcategory":"Child Care",
            "type":"Services"
        }
    ],
    "sg:phone":"+61 7 3263 4366",
    "sg:postcode":"4034",
    "sg:province":"QLD",
    "wof:name":"YMCA Outside School Hours Care",
    "wof:placetype":"venue"
},
  "geometry": {"coordinates":[153.01417499999999,-27.369909],"type":"Point"}
}