{
  "type": "Feature",
  "properties": {
    "addr:full":"PO Box 647 Tewantin QLD 4565",
    "addr:postcode":"4565",
    "iso:country":"AU",
    "sg:address":"PO Box 647",
    "sg:city":"Tewantin",
    "sg:classifiers":[
        {
            "category":"Professional",
            "subcategory":"Accounting & Tax Preparation",
            "type":"Services"
        }
    ],
    "sg:phone":"+61 1300 651 219",
    "sg:postcode":"4565",
    "sg:province":"QLD",
    "sg:tags":[
        "accountant",
        "auditor"
    ],
    "wof:name":"MBX Financial Services",
    "wof:placetype":"venue"
},
  "geometry": {"coordinates":[153.02789306599999,-26.3908996582],"type":"Point"}
}