{
  "type": "Feature",
  "properties": {
    "iso:country":"AU",
    "sg:address":"U3/ 37 Pine St",
    "sg:city":"Hawthorn",
    "sg:classifiers":[
        {
            "category":"Professional",
            "subcategory":"Art Services",
            "type":"Services"
        }
    ],
    "sg:phone":"+61 3 9853 0700",
    "sg:postcode":"3122",
    "sg:province":"VIC",
    "sg:tags":[
        "graphic",
        "designer"
    ],
    "wof:name":"Go To Wo Consulting",
    "wof:placetype":"venue"
},
  "geometry": {"coordinates":[145.022506714,-37.8138504028],"type":"Point"}
}