{
  "type": "Feature",
  "properties": {
    "addr:full":"65 Averys Rd Eaglehawk VIC 3556",
    "addr:housenumber":"65",
    "addr:postcode":"3556",
    "addr:street":"Averys Rd",
    "iso:country":"AU",
    "sg:address":"65 Averys Rd",
    "sg:city":"Eaglehawk",
    "sg:classifiers":[
        {
            "category":"Building & Trades",
            "subcategory":"Construction",
            "type":"Services"
        }
    ],
    "sg:phone":"+61 418 140 964",
    "sg:postcode":"3556",
    "sg:province":"VIC",
    "sg:tags":[
        "earth",
        "excavating",
        "moving",
        "contractor"
    ],
    "wof:name":"J.J.'s Bobcat & Truck Hire",
    "wof:placetype":"venue"
},
  "geometry": {"coordinates":[144.27676391599999,-36.7195549011],"type":"Point"}
}