{
  "type": "Feature",
  "properties": {
    "addr:full":"Lwr Hermitage Rd Houghton SA 5131",
    "addr:postcode":"5131",
    "addr:street":"Lwr Hermitage Rd",
    "iso:country":"AU",
    "sg:address":"Lwr Hermitage Rd",
    "sg:city":"Houghton",
    "sg:classifiers":[
        {
            "category":"Retail",
            "subcategory":"Laundry & Dry Cleaning",
            "type":"Services"
        }
    ],
    "sg:phone":"+61 8 8380 5454",
    "sg:postcode":"5131",
    "sg:province":"SA",
    "sg:tags":[
        "breeder",
        "alpaca",
        "llama"
    ],
    "wof:name":"The Hermitage Alpacas",
    "wof:placetype":"venue"
},
  "geometry": {"coordinates":[138.75813293499999,-34.8173370361],"type":"Point"}
}