{
  "type": "Feature",
  "properties": {
    "iso:country":"AU",
    "sg:address":"5 Bambra Rd",
    "sg:city":"Caulfield North",
    "sg:classifiers":[
        {
            "category":"Health Services",
            "subcategory":"Nursing And Care Facility",
            "type":"Services"
        }
    ],
    "sg:phone":"+61 3 9528 5550",
    "sg:postcode":"3161",
    "sg:province":"VIC",
    "sg:tags":[
        "home"
    ],
    "wof:name":"Bambra House Nursing Home",
    "wof:placetype":"venue"
},
  "geometry": {"coordinates":[145.03111267099999,-37.8741111755],"type":"Point"}
}