{
  "type": "Feature",
  "properties": {
    "addr:full":"735 Portarlington Rd Leopold VIC 3224",
    "addr:housenumber":"735",
    "addr:postcode":"3224",
    "addr:street":"Portarlington Rd",
    "iso:country":"AU",
    "sg:address":"735 Portarlington Rd",
    "sg:city":"Leopold",
    "sg:classifiers":[
        {
            "category":"Farming",
            "subcategory":"Nursery",
            "type":"Manufacturing & Wholesale Goods"
        }
    ],
    "sg:phone":"+61 3 5250 2058",
    "sg:postcode":"3224",
    "sg:province":"VIC",
    "wof:name":"Pioneer Orchid Farm",
    "wof:placetype":"venue"
},
  "geometry": {"coordinates":[144.46253999999999,-38.196381],"type":"Point"}
}