{
  "type": "Feature",
  "properties": {
    "iso:country":"AU",
    "sg:address":"Main St",
    "sg:city":"Hivesville",
    "sg:classifiers":[
        {
            "category":"Travel",
            "subcategory":"Hotels & Motels",
            "type":"Entertainment"
        }
    ],
    "sg:phone":"+61 7 4168 9876",
    "sg:postcode":"4612",
    "sg:province":"QLD",
    "sg:tags":[
        "accommodation"
    ],
    "wof:name":"Hivesville Hotel",
    "wof:placetype":"venue"
},
  "geometry": {"coordinates":[151.69099426299999,-26.1766662598],"type":"Point"}
}