{
  "type": "Feature",
  "properties": {
    "addr:full":"Avery St Rutherford NSW 2320",
    "addr:postcode":"2320",
    "addr:street":"Avery St",
    "iso:country":"AU",
    "sg:address":"Avery St",
    "sg:city":"Rutherford",
    "sg:classifiers":[
        {
            "category":"Education",
            "subcategory":"School",
            "type":"Public Place"
        }
    ],
    "sg:phone":"+61 2 4932 5999",
    "sg:postcode":"2320",
    "sg:province":"NSW",
    "sg:tags":[
        "state",
        "-",
        "nsw"
    ],
    "wof:name":"Rutherford High School",
    "wof:placetype":"venue"
},
  "geometry": {"coordinates":[151.53166198700001,-32.7142181396],"type":"Point"}
}