{
  "type": "Feature",
  "properties": {
    "iso:country":"AU",
    "sg:address":"295 Bagot Rd",
    "sg:city":"Subiaco",
    "sg:classifiers":[
        {
            "category":"Social Services",
            "subcategory":"Child Care",
            "type":"Services"
        }
    ],
    "sg:phone":"+61 8 9382 4607",
    "sg:postcode":"6008",
    "sg:province":"WA",
    "wof:name":"Subicare Child Care Centre",
    "wof:placetype":"venue"
},
  "geometry": {"coordinates":[115.821968079,-31.9504985809],"type":"Point"}
}