{
  "type": "Feature",
  "properties": {
    "iso:country":"AU",
    "sg:address":"9 Merindah Ave",
    "sg:city":"Manilla",
    "sg:classifiers":[
        {
            "category":"Autos & Motor Vehicles",
            "subcategory":"Auto Supplies",
            "type":"Retail Goods"
        }
    ],
    "sg:phone":"+61 408 659 078",
    "sg:postcode":"2346",
    "sg:province":"NSW",
    "sg:tags":[
        "battery",
        "automotive"
    ],
    "wof:name":"Supercharge Batteries",
    "wof:placetype":"venue"
},
  "geometry": {"coordinates":[150.73164367699999,-30.7492046356],"type":"Point"}
}