{
  "type": "Feature",
  "properties": {
    "addr:full":"36 Mirbelia St Everton Hills QLD 4053",
    "addr:housenumber":"36",
    "addr:postcode":"4053",
    "addr:street":"Mirbelia St",
    "iso:country":"AU",
    "sg:address":"36 Mirbelia St",
    "sg:city":"Everton Hills",
    "sg:classifiers":[
        {
            "category":"Professional",
            "subcategory":"Testing Lab",
            "type":"Services"
        }
    ],
    "sg:phone":"+61 7 3367 2181",
    "sg:postcode":"4053",
    "sg:province":"QLD",
    "sg:tags":[
        "soil",
        "investigation"
    ],
    "wof:name":"Geotech Drilling Services Pty Ltd",
    "wof:placetype":"venue"
},
  "geometry": {"coordinates":[152.967895508,-27.3959827423],"type":"Point"}
}