{
  "type": "Feature",
  "properties": {
    "addr:full":"Shop 17 Albert St Harbord NSW 2096",
    "addr:housenumber":"shop 17",
    "addr:postcode":"2096",
    "addr:street":"Albert St",
    "iso:country":"AU",
    "sg:address":"Shop 17 Albert St",
    "sg:city":"Harbord",
    "sg:classifiers":[
        {
            "category":"Retail",
            "subcategory":"Repair Shop",
            "type":"Services"
        }
    ],
    "sg:phone":"+61 2 9905 2680",
    "sg:postcode":"2096",
    "sg:province":"NSW",
    "sg:tags":[
        "machine",
        "repairs",
        "part",
        "dryer",
        "washing"
    ],
    "wof:name":"Harbord Traders Appliance Services Pty Ltd",
    "wof:placetype":"venue"
},
  "geometry": {"coordinates":[151.28619384800001,-33.7784957886],"type":"Point"}
}