{
  "type": "Feature",
  "properties": {
    "addr:full":"Shop 7 The Walk Shopping Cntr Maroondah Hwy Healesville VIC 3777",
    "addr:housenumber":"shop 7",
    "addr:postcode":"3777",
    "addr:street":"The Walk Shopping Cntr Maroondah Hwy",
    "iso:country":"AU",
    "sg:address":"Shop 7 The Walk Shopping Cntr Maroondah Hwy",
    "sg:city":"Healesville",
    "sg:classifiers":[
        {
            "category":"Communications",
            "subcategory":"Film & Video Production",
            "type":"Services"
        }
    ],
    "sg:phone":"+61 3 5962 3100",
    "sg:postcode":"3777",
    "sg:province":"VIC",
    "sg:tags":[
        "dvd",
        "library"
    ],
    "wof:name":"Video Ezy",
    "wof:placetype":"venue"
},
  "geometry": {"coordinates":[145.52145400000001,-37.65192],"type":"Point"}
}