{
  "type": "Feature",
  "properties": {
    "addr:full":"54 Hill Rd Lurnea NSW 2170",
    "addr:housenumber":"54",
    "addr:postcode":"2170",
    "addr:street":"Hill Rd",
    "iso:country":"AU",
    "sg:address":"54 Hill Rd",
    "sg:city":"Lurnea",
    "sg:classifiers":[
        {
            "category":"Food & Beverages",
            "subcategory":"Groceries & Convenience Stores",
            "type":"Retail Goods"
        }
    ],
    "sg:phone":"+61 2 9607 4859",
    "sg:postcode":"2170",
    "sg:province":"NSW",
    "wof:name":"Clancy's Food Stores Pty Ltd",
    "wof:placetype":"venue"
},
  "geometry": {"coordinates":[150.89671325699999,-33.9308204651],"type":"Point"}
}