{
  "type": "Feature",
  "properties": {
    "iso:country":"AU",
    "sg:address":"12 Wycombe St",
    "sg:city":"Queanbeyan",
    "sg:classifiers":[
        {
            "category":"Professional",
            "subcategory":"Engineering",
            "type":"Services"
        }
    ],
    "sg:phone":"+61 2 6299 6433",
    "sg:postcode":"2620",
    "sg:province":"ACT",
    "sg:tags":[
        "diesel",
        "engineer"
    ],
    "wof:name":"Southern Truck Centre",
    "wof:placetype":"venue"
},
  "geometry": {"coordinates":[149.246368408,-35.3362159729],"type":"Point"}
}