{
  "type": "Feature",
  "properties": {
    "iso:country":"AU",
    "sg:address":"Cnr Murray Valley Hwy & Irrigation Rd",
    "sg:city":"Numurkah",
    "sg:classifiers":[
        {
            "category":"Home & Garden",
            "subcategory":"Hardware",
            "type":"Retail Goods"
        }
    ],
    "sg:phone":"+61 3 5821 4214",
    "sg:postcode":"3636",
    "sg:province":"VIC",
    "sg:tags":[
        "plumber",
        "supply"
    ],
    "wof:name":"Shepparton Vibrated Concrete Products",
    "wof:placetype":"venue"
},
  "geometry": {"coordinates":[145.42938232399999,-36.0948448181],"type":"Point"}
}