{
  "type": "Feature",
  "properties": {
    "addr:full":"6 James St Yeppoon QLD 4703",
    "addr:housenumber":"6",
    "addr:postcode":"4703",
    "addr:street":"James St",
    "iso:country":"AU",
    "sg:address":"6 James St",
    "sg:city":"Yeppoon",
    "sg:classifiers":[
        {
            "category":"Professional",
            "subcategory":"Accounting & Tax Preparation",
            "type":"Services"
        }
    ],
    "sg:phone":"+61 7 4939 1200",
    "sg:postcode":"4703",
    "sg:province":"QLD",
    "sg:tags":[
        "consultant",
        "taxation"
    ],
    "wof:name":"Ward Accounting Group",
    "wof:placetype":"venue"
},
  "geometry": {"coordinates":[150.74508667000001,-23.1284828186],"type":"Point"}
}