{
  "type": "Feature",
  "properties": {
    "iso:country":"AU",
    "sg:address":"14 Newcastle Drv",
    "sg:city":"Sawtell",
    "sg:classifiers":[
        {
            "category":"Building & Trades",
            "subcategory":"Cleaning & Sanitation",
            "type":"Services"
        }
    ],
    "sg:phone":"+61 2 6658 5611",
    "sg:postcode":"2452",
    "sg:province":"NSW",
    "sg:tags":[
        "sweeping",
        "machine"
    ],
    "wof:name":"Keith Dowling Engineering",
    "wof:placetype":"venue"
},
  "geometry": {"coordinates":[153.09161399999999,-30.362297],"type":"Point"}
}