{
  "type": "Feature",
  "properties": {
    "iso:country":"AU",
    "sg:address":"Suite 3.11 / 4 Llya Ave",
    "sg:city":"Erina",
    "sg:classifiers":[
        {
            "category":"Structure",
            "subcategory":"Office Building",
            "type":"Public Place"
        }
    ],
    "sg:phone":"+61 2 4365 7500",
    "sg:postcode":"2250",
    "sg:province":"NSW",
    "sg:tags":[
        "serviced"
    ],
    "wof:name":"Platinum - Serviced & Virtual Offices",
    "wof:placetype":"venue"
},
  "geometry": {"coordinates":[151.341720581,-33.4248847961],"type":"Point"}
}