{
  "type": "Feature",
  "properties": {
    "iso:country":"AU",
    "sg:address":"7/ 1 Cook Drv",
    "sg:city":"Coffs Harbour",
    "sg:classifiers":[
        {
            "category":"Home & Garden",
            "subcategory":"Furniture",
            "type":"Retail Goods"
        }
    ],
    "sg:phone":"+61 2 6652 7133",
    "sg:postcode":"2450",
    "sg:province":"NSW",
    "sg:tags":[
        "repair",
        "restoration"
    ],
    "wof:name":"Polish Shoppe The",
    "wof:placetype":"venue"
},
  "geometry": {"coordinates":[153.096725,-30.313881],"type":"Point"}
}