{
  "type": "Feature",
  "properties": {
    "iso:country":"AU",
    "sg:address":"3 Browning Drv",
    "sg:city":"Templestowe",
    "sg:classifiers":[
        {
            "category":"Manufacturing",
            "subcategory":"Glass & Minerals",
            "type":"Manufacturing & Wholesale Goods"
        }
    ],
    "sg:phone":"+61 3 9842 7694",
    "sg:postcode":"3106",
    "sg:province":"VIC",
    "sg:tags":[
        "exploration"
    ],
    "wof:name":"Graham Robertson Tenement Consultant",
    "wof:placetype":"venue"
},
  "geometry": {"coordinates":[145.162200928,-37.7679710388],"type":"Point"}
}