{
  "type": "Feature",
  "properties": {
    "addr:full":"The Loft, 63 Johnston St Annandale NSW 2038",
    "addr:housenumber":"63",
    "addr:postcode":"2038",
    "addr:street":"Johnston St",
    "iso:country":"AU",
    "sg:address":"The Loft, 63 Johnston St",
    "sg:city":"Annandale",
    "sg:classifiers":[
        {
            "category":"Professional",
            "subcategory":"Business Services",
            "type":"Services"
        }
    ],
    "sg:phone":"+61 2 9518 3055",
    "sg:postcode":"2038",
    "sg:province":"NSW",
    "sg:tags":[
        "management",
        "event"
    ],
    "wof:name":"Podium- The Event Producer",
    "wof:placetype":"venue"
},
  "geometry": {"coordinates":[151.16995239299999,-33.8832511902],"type":"Point"}
}