{
  "type": "Feature",
  "properties": {
    "iso:country":"AU",
    "sg:address":"25 Stanley St",
    "sg:city":"Rockhampton",
    "sg:classifiers":[
        {
            "category":"Manufacturing",
            "subcategory":"Retail Goods",
            "type":"Manufacturing & Wholesale Goods"
        }
    ],
    "sg:phone":"+61 7 4927 1022",
    "sg:postcode":"4700",
    "sg:province":"QLD",
    "sg:tags":[
        "merchant",
        "pump",
        "mfrs"
    ],
    "wof:name":"T & I Pumps & Irrigation",
    "wof:placetype":"venue"
},
  "geometry": {"coordinates":[150.507324219,-23.3897666931],"type":"Point"}
}