{
  "type": "Feature",
  "properties": {
    "addr:full":"160 Newtown Rd Hobart TAS 7000",
    "addr:housenumber":"160",
    "addr:postcode":"7000",
    "addr:street":"Newtown Rd",
    "iso:country":"AU",
    "sg:address":"160 Newtown Rd",
    "sg:city":"Hobart",
    "sg:classifiers":[
        {
            "category":"Shopping",
            "subcategory":"Computers & Home Electronics",
            "type":"Retail Goods"
        }
    ],
    "sg:phone":"+61 3 6228 0077",
    "sg:postcode":"7000",
    "sg:province":"TAS",
    "sg:tags":[
        "hardware",
        "equipment"
    ],
    "wof:name":"Micro-Tech",
    "wof:placetype":"venue"
},
  "geometry": {"coordinates":[147.30480957,-42.8590507507],"type":"Point"}
}