{
  "type": "Feature",
  "properties": {
    "iso:country":"AU",
    "sg:address":"30 Marsden St",
    "sg:city":"Clayfield",
    "sg:classifiers":[
        {
            "category":"Building & Trades",
            "subcategory":"Construction",
            "type":"Services"
        }
    ],
    "sg:phone":"+61 7 3862 1141",
    "sg:postcode":"4011",
    "sg:province":"QLD",
    "sg:tags":[
        "contractor"
    ],
    "wof:name":"Cottee Constructions",
    "wof:placetype":"venue"
},
  "geometry": {"coordinates":[153.047607,-27.426697],"type":"Point"}
}