{
  "type": "Feature",
  "properties": {
    "addr:full":"80 Chinderah Bay Drv Chinderah NSW 2487",
    "addr:housenumber":"80",
    "addr:postcode":"2487",
    "addr:street":"Chinderah Bay Drv",
    "iso:country":"AU",
    "sg:address":"80 Chinderah Bay Drv",
    "sg:city":"Chinderah",
    "sg:classifiers":[
        {
            "category":"Wholesale",
            "subcategory":"Seafood",
            "type":"Manufacturing & Wholesale Goods"
        }
    ],
    "sg:phone":"+61 2 6674 1363",
    "sg:postcode":"2487",
    "sg:province":"NSW",
    "sg:tags":[
        "fish"
    ],
    "wof:name":"Warren Markwell Seafoods",
    "wof:placetype":"venue"
},
  "geometry": {"coordinates":[153.54818725600001,-28.2406177521],"type":"Point"}
}