{
  "type": "Feature",
  "properties": {
    "addr:full":"PO Box 68 Belmont WA 6104",
    "addr:postcode":"6104",
    "iso:country":"AU",
    "sg:address":"PO Box 68",
    "sg:city":"Belmont",
    "sg:classifiers":[
        {
            "category":"Autos & Motor Vehicles",
            "subcategory":"Auto Supplies",
            "type":"Retail Goods"
        }
    ],
    "sg:phone":"+61 13 21 91",
    "sg:postcode":"6104",
    "sg:province":"WA",
    "sg:tags":[
        "tyre"
    ],
    "wof:name":"Tyrepower",
    "wof:placetype":"venue"
},
  "geometry": {"coordinates":[115.933372498,-31.941619873],"type":"Point"}
}