{
  "type": "Feature",
  "properties": {
    "addr:full":"811 Stanley St Woolloongabba QLD 4102",
    "addr:housenumber":"811",
    "addr:postcode":"4102",
    "addr:street":"Stanley St",
    "iso:country":"AU",
    "sg:address":"811 Stanley St",
    "sg:city":"Woolloongabba",
    "sg:classifiers":[
        {
            "category":"Shopping",
            "subcategory":"Computers & Home Electronics",
            "type":"Retail Goods"
        }
    ],
    "sg:phone":"+61 7 3891 6989",
    "sg:postcode":"4102",
    "sg:province":"QLD",
    "sg:tags":[
        "equipment",
        "multimedia"
    ],
    "wof:name":"Amorphous Interactive",
    "wof:placetype":"venue"
},
  "geometry": {"coordinates":[153.03541564899999,-27.4866447449],"type":"Point"}
}