{
  "type": "Feature",
  "properties": {
    "addr:full":"2/ 20- 24 Manufacturer Drv Ernest QLD 4214",
    "addr:housenumber":"/;24",
    "addr:postcode":"4214",
    "addr:street":"20;Manufacturer Drv Ernest",
    "iso:country":"AU",
    "sg:address":"2/ 20- 24 Manufacturer Drv",
    "sg:city":"Ernest",
    "sg:classifiers":[
        {
            "category":"Home & Garden",
            "subcategory":"Building Materials",
            "type":"Retail Goods"
        }
    ],
    "sg:phone":"+61 404 775 008",
    "sg:postcode":"4214",
    "sg:province":"QLD",
    "sg:tags":[
        "balustrading"
    ],
    "wof:name":"Grand Wrought Iron",
    "wof:placetype":"venue"
},
  "geometry": {"coordinates":[153.36309814399999,-27.9653778076],"type":"Point"}
}