{
  "type": "Feature",
  "properties": {
    "iso:country":"AU",
    "sg:address":"37 Skye St",
    "sg:city":"Morisset",
    "sg:classifiers":[
        {
            "category":"Farming",
            "subcategory":"Livestock Farm",
            "type":"Manufacturing & Wholesale Goods"
        }
    ],
    "sg:phone":"+61 2 4973 1783",
    "sg:postcode":"2264",
    "sg:province":"NSW",
    "sg:tags":[
        "breeder",
        "horse",
        "stud"
    ],
    "wof:name":"Kentucky Thoroughbreds",
    "wof:placetype":"venue"
},
  "geometry": {"coordinates":[151.49194299999999,-33.105747],"type":"Point"}
}