{
  "type": "Feature",
  "properties": {
    "addr:full":"Factory 24/ 283 Rex Rd Campbellfield VIC 3061",
    "addr:housenumber":"24 / 283",
    "addr:postcode":"3061",
    "addr:street":"Rex Rd",
    "iso:country":"AU",
    "sg:address":"Factory 24/ 283 Rex Rd",
    "sg:city":"Campbellfield",
    "sg:classifiers":[
        {
            "category":"Building & Trades",
            "subcategory":"Locksmith",
            "type":"Services"
        }
    ],
    "sg:phone":"+61 3 9303 9929",
    "sg:postcode":"3061",
    "sg:province":"VIC",
    "sg:tags":[
        "lock"
    ],
    "wof:name":"All Associated Security Pty Ltd",
    "wof:placetype":"venue"
},
  "geometry": {"coordinates":[144.96290588400001,-37.6467971802],"type":"Point"}
}