{
  "type": "Feature",
  "properties": {
    "addr:full":"59 Aberdare St Kurri Kurri NSW 2327",
    "addr:housenumber":"59",
    "addr:postcode":"2327",
    "addr:street":"Aberdare St",
    "iso:country":"AU",
    "sg:address":"59 Aberdare St",
    "sg:city":"Kurri Kurri",
    "sg:classifiers":[
        {
            "category":"Retail",
            "subcategory":"Driving School",
            "type":"Services"
        }
    ],
    "sg:phone":"+61 2 4937 4161",
    "sg:postcode":"2327",
    "sg:province":"NSW",
    "wof:name":"Baileys Driver Training",
    "wof:placetype":"venue"
},
  "geometry": {"coordinates":[151.484375,-32.8139343262],"type":"Point"}
}