{
  "type": "Feature",
  "properties": {
    "iso:country":"AU",
    "sg:address":"54 Eyre St",
    "sg:city":"Echuca",
    "sg:classifiers":[
        {
            "category":"Retail",
            "subcategory":"Driving School",
            "type":"Services"
        }
    ],
    "sg:phone":"+61 3 5482 3111",
    "sg:postcode":"3564",
    "sg:province":"VIC",
    "wof:name":"Echuca Driving School",
    "wof:placetype":"venue"
},
  "geometry": {"coordinates":[144.75811767600001,-36.1336288452],"type":"Point"}
}