{
  "type": "Feature",
  "properties": {
    "addr:full":"37 Enterprise St Mackay QLD 4740",
    "addr:housenumber":"37",
    "addr:postcode":"4740",
    "addr:street":"Enterprise St",
    "iso:country":"AU",
    "sg:address":"37 Enterprise St",
    "sg:city":"Mackay",
    "sg:classifiers":[
        {
            "category":"Building & Trades",
            "subcategory":"Plumbing",
            "type":"Services"
        }
    ],
    "sg:phone":"+61 7 4952 4890",
    "sg:postcode":"4740",
    "sg:province":"QLD",
    "sg:tags":[
        "fitting",
        "hose",
        "supply"
    ],
    "wof:name":"Parker Hannifin",
    "wof:placetype":"venue"
},
  "geometry": {"coordinates":[149.16081199999999,-21.184498],"type":"Point"}
}