{
  "type": "Feature",
  "properties": {
    "iso:country":"AU",
    "sg:address":"49 Bundock St",
    "sg:city":"Belgian Gardens",
    "sg:classifiers":[
        {
            "category":"Personal",
            "subcategory":"Beauty Salon",
            "type":"Services"
        }
    ],
    "sg:phone":"+61 405 336 381",
    "sg:postcode":"4810",
    "sg:province":"QLD",
    "wof:name":"A1 Nail Design",
    "wof:placetype":"venue"
},
  "geometry": {"coordinates":[146.755463,-19.2351],"type":"Point"}
}