{
  "type": "Feature",
  "properties": {
    "iso:country":"AU",
    "sg:address":"78 Albany Ave",
    "sg:city":"Port Noarlunga South",
    "sg:classifiers":[
        {
            "category":"Building & Trades",
            "subcategory":"Landscaping Services",
            "type":"Services"
        }
    ],
    "sg:phone":"+61 408 423 250",
    "sg:postcode":"5167",
    "sg:province":"SA",
    "sg:tags":[
        "designer",
        "landscape",
        "contractor"
    ],
    "wof:name":"Botha Landscapes & Irrigation",
    "wof:placetype":"venue"
},
  "geometry": {"coordinates":[138.46832275400001,-35.1695556641],"type":"Point"}
}