{
  "type": "Feature",
  "properties": {
    "addr:full":"1B Dynes St Ringwood East VIC 3135",
    "addr:housenumber":"1b",
    "addr:postcode":"3135",
    "addr:street":"Dynes St",
    "iso:country":"AU",
    "sg:address":"1B Dynes St",
    "sg:city":"Ringwood East",
    "sg:classifiers":[
        {
            "category":"Building & Trades",
            "subcategory":"Construction",
            "type":"Services"
        }
    ],
    "sg:phone":"+61 3 9879 5460",
    "sg:postcode":"3135",
    "sg:province":"VIC",
    "sg:tags":[
        "contractor"
    ],
    "wof:name":"Acetech Homes",
    "wof:placetype":"venue"
},
  "geometry": {"coordinates":[145.255493164,-37.8011360168],"type":"Point"}
}