{
  "type": "Feature",
  "properties": {
    "iso:country":"AU",
    "sg:address":"200 Rosamond Rd",
    "sg:city":"Maribyrnong",
    "sg:classifiers":[
        {
            "category":"Insurance",
            "subcategory":"Health Insurance",
            "type":"Services"
        }
    ],
    "sg:phone":"+61 13 23 31",
    "sg:postcode":"3032",
    "sg:province":"VIC",
    "wof:name":"Medibank Private",
    "wof:placetype":"venue"
},
  "geometry": {"coordinates":[144.886414,-37.771812],"type":"Point"}
}