{
  "type": "Feature",
  "properties": {
    "addr:full":"PO Box 193 Kingsgrove 1480 Kingsgrove NSW 2208",
    "addr:postcode":"1480;2208",
    "addr:street":"Kingsgrove",
    "iso:country":"AU",
    "sg:address":"PO Box 193 Kingsgrove 1480",
    "sg:city":"Kingsgrove",
    "sg:classifiers":[
        {
            "category":"Shopping",
            "type":"Retail Goods"
        }
    ],
    "sg:phone":"+61 2 9592 1204",
    "sg:postcode":"2208",
    "sg:province":"NSW",
    "sg:tags":[
        "product",
        "plastic"
    ],
    "wof:name":"Budget Packaging",
    "wof:placetype":"venue"
},
  "geometry": {"coordinates":[151.098938,-33.93948],"type":"Point"}
}