{
  "type": "Feature",
  "properties": {
    "addr:full":"77 McLennan St Mooroopna VIC 3629",
    "addr:housenumber":"77",
    "addr:postcode":"3629",
    "addr:street":"Mclennan St",
    "iso:country":"AU",
    "sg:address":"77 McLennan St",
    "sg:city":"Mooroopna",
    "sg:classifiers":[
        {
            "category":"Fast Food",
            "type":"Food & Drink"
        }
    ],
    "sg:phone":"+61 3 5825 1001",
    "sg:postcode":"3629",
    "sg:province":"VIC",
    "sg:tags":[
        "away",
        "take"
    ],
    "wof:name":"Luen Sing Chinese Restaurant",
    "wof:placetype":"venue"
},
  "geometry": {"coordinates":[145.359817505,-36.3949394226],"type":"Point"}
}