{
  "type": "Feature",
  "properties": {
    "iso:country":"AU",
    "sg:address":"8 Bay St",
    "sg:city":"Southport",
    "sg:classifiers":[
        {
            "category":"Building & Trades",
            "subcategory":"Construction",
            "type":"Services"
        }
    ],
    "sg:phone":"+61 7 5591 4527",
    "sg:postcode":"4215",
    "sg:province":"QLD",
    "sg:tags":[
        "contractor"
    ],
    "wof:name":"Ashmore Constructions Pty Ltd",
    "wof:placetype":"venue"
},
  "geometry": {"coordinates":[153.411743164,-27.9672336578],"type":"Point"}
}