{
  "type": "Feature",
  "properties": {
    "addr:full":"Cnr Frederick Rd & Lochside Drv West Lakes SA 5021",
    "addr:postcode":"5021",
    "addr:street":"Cnr Frederick Rd & Lochside Drv",
    "iso:country":"AU",
    "sg:address":"Cnr Frederick Rd & Lochside Drv",
    "sg:city":"West Lakes",
    "sg:classifiers":[
        {
            "category":"Personal",
            "subcategory":"Massage",
            "type":"Services"
        }
    ],
    "sg:phone":"+61 8 8345 4589",
    "sg:postcode":"5021",
    "sg:province":"SA",
    "sg:tags":[
        "therapy"
    ],
    "wof:name":"West Lakes Remedial Massage Clinic",
    "wof:placetype":"venue"
},
  "geometry": {"coordinates":[138.503372192,-34.8721008301],"type":"Point"}
}