{
  "type": "Feature",
  "properties": {
    "addr:full":"24 Charles Rd Beverley SA 5009",
    "addr:housenumber":"24",
    "addr:postcode":"5009",
    "addr:street":"Charles Rd",
    "iso:country":"AU",
    "sg:address":"24 Charles Rd",
    "sg:city":"Beverley",
    "sg:classifiers":[
        {
            "category":"Utilities",
            "subcategory":"Recycling",
            "type":"Services"
        }
    ],
    "sg:phone":"+61 8 8243 0321",
    "sg:postcode":"5009",
    "sg:province":"SA",
    "wof:name":"That's Not Garbage",
    "wof:placetype":"venue"
},
  "geometry": {"coordinates":[138.54635620100001,-34.8949966431],"type":"Point"}
}