{
  "type": "Feature",
  "properties": {
    "addr:full":"23 Riverside Drv Nambucca Heads NSW 2448",
    "addr:housenumber":"23",
    "addr:postcode":"2448",
    "addr:street":"Riverside Drv",
    "iso:country":"AU",
    "sg:address":"23 Riverside Drv",
    "sg:city":"Nambucca Heads",
    "sg:classifiers":[
        {
            "category":"Food & Beverages",
            "subcategory":"Meat & Fish",
            "type":"Retail Goods"
        }
    ],
    "sg:phone":"+61 2 6568 6624",
    "sg:postcode":"2448",
    "sg:province":"NSW",
    "sg:tags":[
        "seafood"
    ],
    "wof:name":"Davis Seafoods",
    "wof:placetype":"venue"
},
  "geometry": {"coordinates":[152.99801600000001,-30.64864],"type":"Point"}
}