{
  "type": "Feature",
  "properties": {
    "addr:full":"50b King Edward Rd Osborne Park WA 6017",
    "addr:housenumber":"50b",
    "addr:postcode":"6017",
    "addr:street":"King Edward Rd",
    "iso:country":"AU",
    "sg:address":"50b King Edward Rd",
    "sg:city":"Osborne Park",
    "sg:classifiers":[
        {
            "category":"Building & Trades",
            "subcategory":"Construction",
            "type":"Services"
        }
    ],
    "sg:phone":"+61 8 9445 8333",
    "sg:postcode":"6017",
    "sg:province":"WA",
    "sg:tags":[
        "concrete",
        "contractor"
    ],
    "wof:name":"Limescapes",
    "wof:placetype":"venue"
},
  "geometry": {"coordinates":[115.811668396,-31.8986415863],"type":"Point"}
}