{
  "type": "Feature",
  "properties": {
    "addr:full":"396 Bromide St Broken Hill NSW 2880",
    "addr:housenumber":"396",
    "addr:postcode":"2880",
    "addr:street":"Bromide St",
    "iso:country":"AU",
    "sg:address":"396 Bromide St",
    "sg:city":"Broken Hill",
    "sg:classifiers":[
        {
            "category":"Building & Trades",
            "subcategory":"Construction",
            "type":"Services"
        }
    ],
    "sg:phone":"+61 8 8087 4669",
    "sg:postcode":"2880",
    "sg:province":"NSW",
    "sg:tags":[
        "contractor"
    ],
    "wof:name":"Steer Contractors Pty Ltd",
    "wof:placetype":"venue"
},
  "geometry": {"coordinates":[141.4480896,-31.9440441132],"type":"Point"}
}