{
  "type": "Feature",
  "properties": {
    "iso:country":"AU",
    "sg:address":"83-85 Longview Rd",
    "sg:city":"Croydon South",
    "sg:classifiers":[
        {
            "category":"Building & Trades",
            "subcategory":"Construction",
            "type":"Services"
        }
    ],
    "sg:phone":"+61 418 101 266",
    "sg:postcode":"3136",
    "sg:province":"VIC",
    "sg:tags":[
        "joiner",
        "carpenter"
    ],
    "wof:name":"GMR Carpentry Services",
    "wof:placetype":"venue"
},
  "geometry": {"coordinates":[145.26335144000001,-37.8116645813],"type":"Point"}
}