{
  "type": "Feature",
  "properties": {
    "addr:full":"13 Raymond St Moorabbin VIC 3189",
    "addr:housenumber":"13",
    "addr:postcode":"3189",
    "addr:street":"Raymond St",
    "iso:country":"AU",
    "sg:address":"13 Raymond St",
    "sg:city":"Moorabbin",
    "sg:classifiers":[
        {
            "category":"Professional",
            "subcategory":"Art Services",
            "type":"Services"
        }
    ],
    "sg:phone":"+61 3 9555 2126",
    "sg:postcode":"3189",
    "sg:province":"VIC",
    "sg:tags":[
        "decorator",
        "painter"
    ],
    "wof:name":"True Colour Painting",
    "wof:placetype":"venue"
},
  "geometry": {"coordinates":[145.050415039,-37.9739494324],"type":"Point"}
}