{
  "type": "Feature",
  "properties": {
    "addr:full":"2 Withers St Arncliffe NSW 2205",
    "addr:housenumber":"2",
    "addr:postcode":"2205",
    "addr:street":"Withers St",
    "iso:country":"AU",
    "sg:address":"2 Withers St",
    "sg:city":"Arncliffe",
    "sg:classifiers":[
        {
            "category":"Professional",
            "subcategory":"Computer Services",
            "type":"Services"
        }
    ],
    "sg:phone":"+61 412 169 971",
    "sg:postcode":"2205",
    "sg:province":"NSW",
    "sg:tags":[
        "consultant",
        "system"
    ],
    "wof:name":"Carl Hill Business Solution Pty Ltd",
    "wof:placetype":"venue"
},
  "geometry": {"coordinates":[151.14047199999999,-33.941563],"type":"Point"}
}