{
  "type": "Feature",
  "properties": {
    "addr:full":"1322 Pacific Hwy Turramurra NSW 2074",
    "addr:housenumber":"1322",
    "addr:postcode":"2074",
    "addr:street":"Pacific Hwy",
    "iso:country":"AU",
    "sg:address":"1322 Pacific Hwy",
    "sg:city":"Turramurra",
    "sg:classifiers":[
        {
            "category":"Travel",
            "subcategory":"Hostel",
            "type":"Entertainment"
        }
    ],
    "sg:phone":"+61 2 9449 5644",
    "sg:postcode":"2074",
    "sg:province":"NSW",
    "sg:tags":[
        "home"
    ],
    "wof:name":"Northaven Retirement Village",
    "wof:placetype":"venue"
},
  "geometry": {"coordinates":[151.130935669,-33.7334365845],"type":"Point"}
}