{
  "type": "Feature",
  "properties": {
    "iso:country":"AU",
    "sg:address":"1119 Latrobe St",
    "sg:city":"Ballarat",
    "sg:classifiers":[
        {
            "category":"Manufacturing",
            "subcategory":"Petroleum Products",
            "type":"Manufacturing & Wholesale Goods"
        }
    ],
    "sg:phone":"+61 3 5336 1999",
    "sg:postcode":"3350",
    "sg:province":"VIC",
    "sg:tags":[
        "lubricant"
    ],
    "wof:name":"Ampol/Caltex",
    "wof:placetype":"venue"
},
  "geometry": {"coordinates":[143.81532300000001,-37.570423],"type":"Point"}
}