{
  "type": "Feature",
  "properties": {
    "addr:full":"Wondall Road Shopping Centre Wynnum West QLD 4178",
    "addr:postcode":"4178",
    "addr:street":"Wondall",
    "iso:country":"AU",
    "sg:address":"Wondall Road Shopping Centre",
    "sg:city":"Wynnum West",
    "sg:classifiers":[
        {
            "category":"Health Services",
            "subcategory":"Health Practitioner",
            "type":"Services"
        }
    ],
    "sg:phone":"+61 7 3396 5886",
    "sg:postcode":"4178",
    "sg:province":"QLD",
    "sg:tags":[
        "physiotherapist"
    ],
    "wof:name":"Richard J. Lumley Pty Ltd",
    "wof:placetype":"venue"
},
  "geometry": {"coordinates":[153.163040161,-27.4594936371],"type":"Point"}
}