{
  "type": "Feature",
  "properties": {
    "addr:full":"30 Hayfield Rd Mt Waverley VIC 3149",
    "addr:housenumber":"30",
    "addr:postcode":"3149",
    "addr:street":"Hayfield Rd",
    "iso:country":"AU",
    "sg:address":"30 Hayfield Rd",
    "sg:city":"Mt Waverley",
    "sg:classifiers":[
        {
            "category":"Utilities",
            "subcategory":"Electric",
            "type":"Services"
        }
    ],
    "sg:phone":"+61 418 581 575",
    "sg:postcode":"3149",
    "sg:province":"VIC",
    "sg:tags":[
        "electrical",
        "contractor"
    ],
    "wof:name":"Powerphase Electrics",
    "wof:placetype":"venue"
},
  "geometry": {"coordinates":[145.13381957999999,-37.8607139587],"type":"Point"}
}