{
  "type": "Feature",
  "properties": {
    "iso:country":"AU",
    "sg:address":"18 Shannon St",
    "sg:city":"Wentworth",
    "sg:classifiers":[
        {
            "category":"Communications",
            "subcategory":"News Services",
            "type":"Services"
        }
    ],
    "sg:phone":"+61 1800 611 268",
    "sg:postcode":"2648",
    "sg:province":"VIC",
    "sg:tags":[
        "information",
        "tourist",
        "attractions"
    ],
    "wof:name":"Paddleboat Coonawarra",
    "wof:placetype":"venue"
},
  "geometry": {"coordinates":[141.924881,-34.101841],"type":"Point"}
}