{
  "type": "Feature",
  "properties": {
    "addr:full":"28 Raworth Ave Raworth NSW 2321",
    "addr:housenumber":"28",
    "addr:postcode":"2321",
    "addr:street":"Raworth Ave",
    "iso:country":"AU",
    "sg:address":"28 Raworth Ave",
    "sg:city":"Raworth",
    "sg:classifiers":[
        {
            "category":"Sports & Exercise",
            "subcategory":"Sports Center",
            "type":"Entertainment"
        }
    ],
    "sg:phone":"+61 2 4933 3750",
    "sg:postcode":"2321",
    "sg:province":"NSW",
    "sg:tags":[
        "coach",
        "tennis"
    ],
    "wof:name":"Hunter Tennis Resort",
    "wof:placetype":"venue"
},
  "geometry": {"coordinates":[151.614044189,-32.7300376892],"type":"Point"}
}