{
  "type": "Feature",
  "properties": {
    "addr:full":"Hotham St Casino NSW 2470",
    "addr:postcode":"2470",
    "addr:street":"Hotham St",
    "iso:country":"AU",
    "sg:address":"Hotham St",
    "sg:city":"Casino",
    "sg:classifiers":[
        {
            "category":"Education",
            "subcategory":"School",
            "type":"Public Place"
        }
    ],
    "sg:phone":"+61 2 6662 1916",
    "sg:postcode":"2470",
    "sg:province":"NSW",
    "sg:tags":[
        "state",
        "-",
        "nsw"
    ],
    "wof:name":"Casino West Public School",
    "wof:placetype":"venue"
},
  "geometry": {"coordinates":[153.03758239699999,-28.8569126129],"type":"Point"}
}