{
  "type": "Feature",
  "properties": {
    "iso:country":"AU",
    "sg:address":"15 Maitland Rd",
    "sg:city":"Mayfield East",
    "sg:classifiers":[
        {
            "category":"Industrial Area",
            "type":"Public Place"
        }
    ],
    "sg:phone":"+61 2 4968 0890",
    "sg:postcode":"2304",
    "sg:province":"NSW",
    "sg:tags":[
        "rural",
        "shed"
    ],
    "wof:name":"Armourshed",
    "wof:placetype":"venue"
},
  "geometry": {"coordinates":[151.74650573700001,-32.9051475525],"type":"Point"}
}