{
  "type": "Feature",
  "properties": {
    "addr:full":"83 High St Mansfield VIC 3722",
    "addr:housenumber":"83",
    "addr:postcode":"3722",
    "addr:street":"High St",
    "iso:country":"AU",
    "sg:address":"83 High St",
    "sg:city":"Mansfield",
    "sg:classifiers":[
        {
            "category":"Travel",
            "subcategory":"Hotels & Motels",
            "type":"Entertainment"
        }
    ],
    "sg:phone":"+61 3 5775 2046",
    "sg:postcode":"3722",
    "sg:province":"VIC",
    "sg:tags":[
        "accommodation"
    ],
    "wof:name":"Commercial Hotel-Accommodation",
    "wof:placetype":"venue"
},
  "geometry": {"coordinates":[146.08877563499999,-37.0520324707],"type":"Point"}
}