{
  "type": "Feature",
  "properties": {
    "addr:full":"Un 8/ 53 Gladesville Rd Hunters Hill NSW 2110",
    "addr:housenumber":"53",
    "addr:postcode":"2110",
    "addr:street":"Gladesville Rd",
    "iso:country":"AU",
    "sg:address":"Un 8/ 53 Gladesville Rd",
    "sg:city":"Hunters Hill",
    "sg:classifiers":[
        {
            "category":"Health Services",
            "subcategory":"Doctor",
            "type":"Services"
        }
    ],
    "sg:phone":"+61 2 9879 5824",
    "sg:postcode":"2110",
    "sg:province":"NSW",
    "sg:tags":[
        "podiatrist"
    ],
    "wof:name":"Hunters Hill Podiatry",
    "wof:placetype":"venue"
},
  "geometry": {"coordinates":[151.14421081500001,-33.8336143494],"type":"Point"}
}