{
  "type": "Feature",
  "properties": {
    "addr:full":"27a Victoria Ave Concord West NSW 2138",
    "addr:housenumber":"27a",
    "addr:postcode":"2138",
    "addr:street":"Victoria Ave",
    "iso:country":"AU",
    "sg:address":"27a Victoria Ave",
    "sg:city":"Concord West",
    "sg:classifiers":[
        {
            "category":"Personal",
            "subcategory":"Beauty Salon",
            "type":"Services"
        }
    ],
    "sg:phone":"+61 2 9743 2440",
    "sg:postcode":"2138",
    "sg:province":"NSW",
    "sg:tags":[
        "hairdresser"
    ],
    "wof:name":"Hair Techniques",
    "wof:placetype":"venue"
},
  "geometry": {"coordinates":[151.08677673299999,-33.8478546143],"type":"Point"}
}