{
  "type": "Feature",
  "properties": {
    "iso:country":"AU",
    "sg:address":"10 Annie St",
    "sg:city":"Caboolture",
    "sg:classifiers":[
        {
            "category":"Health Services",
            "subcategory":"Doctor",
            "type":"Services"
        }
    ],
    "sg:phone":"+61 7 5498 9344",
    "sg:postcode":"4510",
    "sg:province":"QLD",
    "sg:tags":[
        "medical",
        "practitioner"
    ],
    "wof:name":"Ter Dr Swee",
    "wof:placetype":"venue"
},
  "geometry": {"coordinates":[152.94996599999999,-27.082138],"type":"Point"}
}