{
  "type": "Feature",
  "properties": {
    "iso:country":"AU",
    "sg:address":"Cnr Keira St & Champion Drive",
    "sg:city":"Kelmscott",
    "sg:classifiers":[
        {
            "category":"Building & Trades",
            "subcategory":"Equipment Rental",
            "type":"Services"
        }
    ],
    "sg:phone":"+61 8 9497 3998",
    "sg:postcode":"6111",
    "sg:province":"WA",
    "sg:tags":[
        "renting",
        "trailer"
    ],
    "wof:name":"Shift Yourself Trailers",
    "wof:placetype":"venue"
},
  "geometry": {"coordinates":[116.003631592,-32.1315498352],"type":"Point"}
}