{
  "type": "Feature",
  "properties": {
    "iso:country":"AU",
    "sg:address":"314 Jells Rd",
    "sg:city":"Wheelers Hill",
    "sg:classifiers":[
        {
            "category":"Health Services",
            "subcategory":"Health Practitioner",
            "type":"Services"
        }
    ],
    "sg:phone":"+61 3 9560 7551",
    "sg:postcode":"3150",
    "sg:province":"VIC",
    "sg:tags":[
        "hypnotherapy"
    ],
    "wof:name":"Berger Harry",
    "wof:placetype":"venue"
},
  "geometry": {"coordinates":[145.187133789,-37.9187774658],"type":"Point"}
}