{
  "type": "Feature",
  "properties": {
    "addr:full":"11 Bindook Crs Terrey Hills NSW 2084",
    "addr:housenumber":"11",
    "addr:postcode":"2084",
    "addr:street":"Bindook Crs",
    "iso:country":"AU",
    "sg:address":"11 Bindook Crs",
    "sg:city":"Terrey Hills",
    "sg:classifiers":[
        {
            "category":"Social Services",
            "subcategory":"Child Care",
            "type":"Services"
        }
    ],
    "sg:phone":"+61 2 9486 3868",
    "sg:postcode":"2084",
    "sg:province":"NSW",
    "wof:name":"Bindook Cottage",
    "wof:placetype":"venue"
},
  "geometry": {"coordinates":[151.229705811,-33.6837692261],"type":"Point"}
}