{
  "type": "Feature",
  "properties": {
    "addr:full":"5 Overall Crt St Agnes SA 5097",
    "addr:housenumber":"5",
    "addr:postcode":"5097",
    "addr:street":"Overall Crt",
    "iso:country":"AU",
    "sg:address":"5 Overall Crt",
    "sg:city":"St Agnes",
    "sg:classifiers":[
        {
            "category":"Real Estate",
            "subcategory":"Architect",
            "type":"Services"
        }
    ],
    "sg:phone":"+61 8 8396 1996",
    "sg:postcode":"5097",
    "sg:province":"SA",
    "sg:tags":[
        "building",
        "designer"
    ],
    "wof:name":"Mario Civitarese Building Design",
    "wof:placetype":"venue"
},
  "geometry": {"coordinates":[138.706573486,-34.8357772827],"type":"Point"}
}