{
  "type": "Feature",
  "properties": {
    "addr:full":"PO Box 172 Cherrybrook NSW 2126",
    "addr:postcode":"2126",
    "iso:country":"AU",
    "sg:address":"PO Box 172",
    "sg:city":"Cherrybrook",
    "sg:classifiers":[
        {
            "category":"Government",
            "subcategory":"Post Office",
            "type":"Public Place"
        }
    ],
    "sg:phone":"+61 2 4625 3083",
    "sg:postcode":"2126",
    "sg:province":"NSW",
    "sg:tags":[
        "house",
        "doll"
    ],
    "wof:name":"Australian Miniature Enthusiasts Association",
    "wof:placetype":"venue"
},
  "geometry": {"coordinates":[151.04136657699999,-33.7210006714],"type":"Point"}
}