{
  "type": "Feature",
  "properties": {
    "addr:full":"144 John St Lidcombe NSW 2141",
    "addr:housenumber":"144",
    "addr:postcode":"2141",
    "addr:street":"John St",
    "iso:country":"AU",
    "sg:address":"144 John St",
    "sg:city":"Lidcombe",
    "sg:classifiers":[
        {
            "category":"Fast Food",
            "type":"Food & Drink"
        }
    ],
    "sg:phone":"+61 2 9649 9835",
    "sg:postcode":"2141",
    "sg:province":"NSW",
    "sg:tags":[
        "away",
        "take"
    ],
    "wof:name":"Con's Takeaway",
    "wof:placetype":"venue"
},
  "geometry": {"coordinates":[151.04737854000001,-33.8539962769],"type":"Point"}
}