{
  "type": "Feature",
  "properties": {
    "addr:full":"344- 346 South Rd Croydon Park SA 5008",
    "addr:housenumber":"346",
    "addr:postcode":"5008",
    "addr:street":"South Rd",
    "iso:country":"AU",
    "sg:address":"344- 346 South Rd",
    "sg:city":"Croydon Park",
    "sg:classifiers":[
        {
            "category":"Home & Garden",
            "subcategory":"Carpets & Floor Coverings",
            "type":"Retail Goods"
        }
    ],
    "sg:phone":"+61 8 8346 2588",
    "sg:postcode":"5008",
    "sg:province":"SA",
    "sg:tags":[
        "wood"
    ],
    "sg:website":"http://www.discountcitycarpets.com.au",
    "wof:name":"Discount City Carpets",
    "wof:placetype":"venue"
},
  "geometry": {"coordinates":[138.57148699999999,-34.875294],"type":"Point"}
}