{
  "type": "Feature",
  "properties": {
    "addr:full":"Taylors Rd West Aberfoyle Park SA 5159",
    "addr:postcode":"5159",
    "addr:street":"Taylors Rd West",
    "iso:country":"AU",
    "sg:address":"Taylors Rd West",
    "sg:city":"Aberfoyle Park",
    "sg:classifiers":[
        {
            "category":"Organizations",
            "subcategory":"Community Association",
            "type":"Services"
        }
    ],
    "sg:phone":"+61 8 8270 5162",
    "sg:postcode":"5159",
    "sg:province":"SA",
    "sg:tags":[
        "club",
        "senior",
        "citizen"
    ],
    "wof:name":"Happy Valley Senior Citizens Club Incorporated",
    "wof:placetype":"venue"
},
  "geometry": {"coordinates":[138.591140747,-35.0733375549],"type":"Point"}
}