{
  "type": "Feature",
  "properties": {
    "addr:full":"93c Unley Rd Unley SA 5061",
    "addr:housenumber":"93c",
    "addr:postcode":"5061",
    "addr:street":"Unley Rd",
    "iso:country":"AU",
    "sg:address":"93c Unley Rd",
    "sg:city":"Unley",
    "sg:classifiers":[
        {
            "category":"Insurance",
            "subcategory":"Life Insurance",
            "type":"Services"
        }
    ],
    "sg:phone":"+61 8 8299 9601",
    "sg:postcode":"5061",
    "sg:province":"SA",
    "wof:name":"Purdie Financial Services",
    "wof:placetype":"venue"
},
  "geometry": {"coordinates":[138.607345581,-34.9471817017],"type":"Point"}
}