{
  "type": "Feature",
  "properties": {
    "addr:full":"Shop 2/18 Eaton Mall Oakleigh VIC 3166",
    "addr:housenumber":"shop 2 / 18",
    "addr:postcode":"3166",
    "addr:street":"Eaton Mall",
    "iso:country":"AU",
    "sg:address":"Shop 2/18 Eaton Mall",
    "sg:city":"Oakleigh",
    "sg:classifiers":[
        {
            "category":"Shopping",
            "subcategory":"Clothing, Apparel, & Fashions",
            "type":"Retail Goods"
        }
    ],
    "sg:phone":"+61 3 9563 2447",
    "sg:postcode":"3166",
    "sg:province":"VIC",
    "sg:tags":[
        "lady",
        "wear"
    ],
    "wof:name":"Isabella Fashions",
    "wof:placetype":"venue"
},
  "geometry": {"coordinates":[145.090942383,-37.9002609253],"type":"Point"}
}