{
  "type": "Feature",
  "properties": {
    "addr:full":"Lot 52 Stott St Tweed Heads West NSW 2485",
    "addr:postcode":"2485",
    "addr:street":"Stott St",
    "iso:country":"AU",
    "sg:address":"Lot 52 Stott St",
    "sg:city":"Tweed Heads West",
    "sg:classifiers":[
        {
            "category":"Building & Trades",
            "subcategory":"Construction",
            "type":"Services"
        }
    ],
    "sg:phone":"+61 414 941 586",
    "sg:postcode":"2485",
    "sg:province":"NSW",
    "sg:tags":[
        "contractor"
    ],
    "wof:name":"Seascape Design & Construction",
    "wof:placetype":"venue"
},
  "geometry": {"coordinates":[153.49313354500001,-28.1911144257],"type":"Point"}
}