{
  "type": "Feature",
  "properties": {
    "iso:country":"AU",
    "sg:address":"Mc Ivor Hwy",
    "sg:city":"Junortoun",
    "sg:classifiers":[
        {
            "category":"Travel",
            "subcategory":"Hotels & Motels",
            "type":"Entertainment"
        }
    ],
    "sg:phone":"+61 3 5449 3201",
    "sg:postcode":"3551",
    "sg:province":"VIC",
    "sg:tags":[
        "accommodation"
    ],
    "wof:name":"Farmers Arms Hotel",
    "wof:placetype":"venue"
},
  "geometry": {"coordinates":[144.22103881800001,-36.9059715271],"type":"Point"}
}