{
  "type": "Feature",
  "properties": {
    "addr:full":"451 Sherwood Rd Sherwood QLD 4075",
    "addr:housenumber":"451",
    "addr:postcode":"4075",
    "addr:street":"Sherwood Rd",
    "iso:country":"AU",
    "sg:address":"451 Sherwood Rd",
    "sg:city":"Sherwood",
    "sg:classifiers":[
        {
            "category":"Building & Trades",
            "subcategory":"Cleaning & Sanitation",
            "type":"Services"
        }
    ],
    "sg:phone":"+61 7 3848 3433",
    "sg:postcode":"4075",
    "sg:province":"QLD",
    "sg:tags":[
        "abrasive",
        "blasting"
    ],
    "wof:name":"Brisbane Abrasive Blasting",
    "wof:placetype":"venue"
},
  "geometry": {"coordinates":[152.991333008,-27.5335006714],"type":"Point"}
}