{
  "type": "Feature",
  "properties": {
    "addr:full":"23- 27 Hood St Airport West VIC 3042",
    "addr:housenumber":"27",
    "addr:postcode":"3042",
    "addr:street":"Hood St",
    "iso:country":"AU",
    "sg:address":"23- 27 Hood St",
    "sg:city":"Airport West",
    "sg:classifiers":[
        {
            "category":"Food & Beverages",
            "subcategory":"Liquor & Beverages",
            "type":"Retail Goods"
        }
    ],
    "sg:phone":"+61 3 9338 2778",
    "sg:postcode":"3042",
    "sg:province":"VIC",
    "sg:tags":[
        "merchant",
        "spirit",
        "wine"
    ],
    "wof:name":"Wine Justice",
    "wof:placetype":"venue"
},
  "geometry": {"coordinates":[144.88841247600001,-37.7255134583],"type":"Point"}
}