{
  "type": "Feature",
  "properties": {
    "addr:full":"PO Box 324 Lakes Entrance VIC 3909",
    "addr:postcode":"3909",
    "iso:country":"AU",
    "sg:address":"PO Box 324",
    "sg:city":"Lakes Entrance",
    "sg:classifiers":[
        {
            "category":"Building & Trades",
            "subcategory":"Equipment Rental",
            "type":"Services"
        }
    ],
    "sg:phone":"+61 3 5155 4332",
    "sg:postcode":"3909",
    "sg:province":"VIC",
    "sg:tags":[
        "builder",
        "contractor"
    ],
    "wof:name":"Tony Moore Builders",
    "wof:placetype":"venue"
},
  "geometry": {"coordinates":[148.00227355999999,-37.8771514893],"type":"Point"}
}