{
  "type": "Feature",
  "properties": {
    "addr:full":"190- 192 Hoddle St Abbotsford VIC 3067",
    "addr:housenumber":"192",
    "addr:postcode":"3067",
    "addr:street":"Hoddle St",
    "iso:country":"AU",
    "sg:address":"190- 192 Hoddle St",
    "sg:city":"Abbotsford",
    "sg:classifiers":[
        {
            "category":"Professional",
            "subcategory":"Printing & Photocopies",
            "type":"Services"
        }
    ],
    "sg:phone":"+61 1300 782 162",
    "sg:postcode":"3067",
    "sg:province":"VIC",
    "sg:tags":[
        "photocopier"
    ],
    "wof:name":"Niche Technology",
    "wof:placetype":"venue"
},
  "geometry": {"coordinates":[144.99298095699999,-37.8013954163],"type":"Point"}
}