{
  "type": "Feature",
  "properties": {
    "addr:full":"unt 2 249 Boundary Rd Mordialloc VIC 3195",
    "addr:housenumber":"249",
    "addr:postcode":"3195",
    "addr:street":"Boundary Rd",
    "iso:country":"AU",
    "sg:address":"unt 2 249 Boundary Rd",
    "sg:city":"Mordialloc",
    "sg:classifiers":[
        {
            "category":"Shopping",
            "subcategory":"Pets & Pet Supplies",
            "type":"Retail Goods"
        }
    ],
    "sg:phone":"+61 3 9587 2885",
    "sg:postcode":"3195",
    "sg:province":"VIC",
    "sg:tags":[
        "shop",
        "supplier"
    ],
    "wof:name":"Aussie Pet Comfort Pty Ltd",
    "wof:placetype":"venue"
},
  "geometry": {"coordinates":[145.10621643100001,-37.9941062927],"type":"Point"}
}