{
  "type": "Feature",
  "properties": {
    "iso:country":"AU",
    "sg:address":"Lot 1, Cleveland Rd",
    "sg:city":"Dapto",
    "sg:classifiers":[
        {
            "category":"Military Area",
            "subcategory":"Army Base",
            "type":"Public Place"
        }
    ],
    "sg:phone":"+61 2 4261 6591",
    "sg:postcode":"2530",
    "sg:province":"NSW",
    "sg:tags":[
        "concrete",
        "slab",
        "floor"
    ],
    "wof:name":"Universal Concrete Pty Ltd",
    "wof:placetype":"venue"
},
  "geometry": {"coordinates":[150.78521728499999,-34.501537323],"type":"Point"}
}