{
  "type": "Feature",
  "properties": {
    "iso:country":"AU",
    "sg:address":"shop 4 100-124 Terminus St",
    "sg:city":"Liverpool",
    "sg:classifiers":[
        {
            "category":"Banks & Credit Unions",
            "subcategory":"Financial Services",
            "type":"Services"
        }
    ],
    "sg:phone":"+61 2 9786 1009",
    "sg:postcode":"2170",
    "sg:province":"NSW",
    "sg:tags":[
        "financier"
    ],
    "wof:name":"VIP Home Loans",
    "wof:placetype":"venue"
},
  "geometry": {"coordinates":[150.921630859,-33.9268302917],"type":"Point"}
}