{
  "type": "Feature",
  "properties": {
    "addr:full":"300 Graves Rd Mansfield VIC 3722",
    "addr:housenumber":"300",
    "addr:postcode":"3722",
    "addr:street":"Graves Rd",
    "iso:country":"AU",
    "sg:address":"300 Graves Rd",
    "sg:city":"Mansfield",
    "sg:classifiers":[
        {
            "category":"Building & Trades",
            "subcategory":"Landscaping Services",
            "type":"Services"
        }
    ],
    "sg:phone":"+61 409 404 559",
    "sg:postcode":"3722",
    "sg:province":"VIC",
    "sg:tags":[
        "grazier"
    ],
    "wof:name":"Mahoney D J",
    "wof:placetype":"venue"
},
  "geometry": {"coordinates":[146.15138244600001,-37.0460090637],"type":"Point"}
}