{
  "type": "Feature",
  "properties": {
    "iso:country":"AU",
    "sg:address":"5 Carlo Crt",
    "sg:city":"Greensborough",
    "sg:classifiers":[
        {
            "category":"Professional",
            "subcategory":"Accounting & Tax Preparation",
            "type":"Services"
        }
    ],
    "sg:phone":"+61 3 9435 0489",
    "sg:postcode":"3088",
    "sg:province":"VIC",
    "sg:tags":[
        "consultant",
        "taxation"
    ],
    "wof:name":"Varalla L",
    "wof:placetype":"venue"
},
  "geometry": {"coordinates":[145.126464844,-37.6842842102],"type":"Point"}
}