{
  "type": "Feature",
  "properties": {
    "iso:country":"AU",
    "sg:address":"1 Rose St",
    "sg:city":"Hurstville",
    "sg:classifiers":[
        {
            "category":"Banks & Credit Unions",
            "subcategory":"Financial Services",
            "type":"Services"
        }
    ],
    "sg:phone":"+61 2 9580 6663",
    "sg:postcode":"2220",
    "sg:province":"NSW",
    "sg:tags":[
        "finance",
        "factoring"
    ],
    "wof:name":"MAP FACTORS PTY LIMITED",
    "wof:placetype":"venue"
},
  "geometry": {"coordinates":[151.105010986,-33.9669723511],"type":"Point"}
}