{
  "type": "Feature",
  "properties": {
    "addr:full":"70 High St North Rockhampton QLD 4701",
    "addr:housenumber":"70",
    "addr:postcode":"4701",
    "addr:street":"High St North",
    "iso:country":"AU",
    "sg:address":"70 High St",
    "sg:city":"North Rockhampton",
    "sg:classifiers":[
        {
            "category":"Recreation",
            "subcategory":"Boat Charter",
            "type":"Entertainment"
        }
    ],
    "sg:phone":"+61 7 4928 3166",
    "sg:postcode":"4701",
    "sg:province":"QLD",
    "wof:name":"Rum Rambler Cruises",
    "wof:placetype":"venue"
},
  "geometry": {"coordinates":[150.53138732900001,-23.3593273163],"type":"Point"}
}