{
  "type": "Feature",
  "properties": {
    "iso:country":"AU",
    "sg:address":"10 College Rd",
    "sg:city":"Karana Downs",
    "sg:classifiers":[
        {
            "category":"Health Services",
            "subcategory":"Health Practitioner",
            "type":"Services"
        }
    ],
    "sg:phone":"+61 7 3822 6454",
    "sg:postcode":"4306",
    "sg:province":"QLD",
    "sg:tags":[
        "dietitian"
    ],
    "wof:name":"Kelli Hale",
    "wof:placetype":"venue"
},
  "geometry": {"coordinates":[152.807662964,-27.5526065826],"type":"Point"}
}