{
  "type": "Feature",
  "properties": {
    "addr:full":"78 Wellington St Kerang VIC 3579",
    "addr:housenumber":"78",
    "addr:postcode":"3579",
    "addr:street":"Wellington St",
    "iso:country":"AU",
    "sg:address":"78 Wellington St",
    "sg:city":"Kerang",
    "sg:classifiers":[
        {
            "category":"Travel",
            "subcategory":"Hotels & Motels",
            "type":"Entertainment"
        }
    ],
    "sg:phone":"+61 3 5452 1177",
    "sg:postcode":"3579",
    "sg:province":"VIC",
    "sg:tags":[
        "accommodation"
    ],
    "wof:name":"Gilbert Club Hotel",
    "wof:placetype":"venue"
},
  "geometry": {"coordinates":[143.91792297399999,-35.7366409302],"type":"Point"}
}