{
  "type": "Feature",
  "properties": {
    "addr:full":"29 Hinkler Rd Mordialloc VIC 3195",
    "addr:housenumber":"29",
    "addr:postcode":"3195",
    "addr:street":"Hinkler Rd",
    "iso:country":"AU",
    "sg:address":"29 Hinkler Rd",
    "sg:city":"Mordialloc",
    "sg:classifiers":[
        {
            "category":"Landmark",
            "subcategory":"Scenic View",
            "type":"Public Place"
        }
    ],
    "sg:phone":"+61 3 9580 8785",
    "sg:postcode":"3195",
    "sg:province":"VIC",
    "sg:tags":[
        "staircase",
        "handrail"
    ],
    "wof:name":"Swift Maintenance & Installations Pty Ltd",
    "wof:placetype":"venue"
},
  "geometry": {"coordinates":[145.09872436500001,-37.9893836975],"type":"Point"}
}