{
  "type": "Feature",
  "properties": {
    "iso:country":"AU",
    "sg:address":"55 Bay St",
    "sg:city":"Double Bay",
    "sg:classifiers":[
        {
            "category":"Shopping",
            "subcategory":"Clothing, Apparel, & Fashions",
            "type":"Retail Goods"
        }
    ],
    "sg:phone":"+61 2 9363 2619",
    "sg:postcode":"2028",
    "sg:province":"NSW",
    "sg:tags":[
        "lady",
        "wear"
    ],
    "wof:name":"Maria Finlay",
    "wof:placetype":"venue"
},
  "geometry": {"coordinates":[151.24205017099999,-33.8760032654],"type":"Point"}
}