{
  "type": "Feature",
  "properties": {
    "addr:full":"11 Dover Crs Wembley Downs WA 6019",
    "addr:housenumber":"11",
    "addr:postcode":"6019",
    "addr:street":"Dover Crs Wembley Downs",
    "iso:country":"AU",
    "sg:address":"11 Dover Crs",
    "sg:city":"Wembley Downs",
    "sg:classifiers":[
        {
            "category":"Shopping",
            "subcategory":"Beauty & Cosmetics",
            "type":"Retail Goods"
        }
    ],
    "sg:phone":"+61 8 9245 5229",
    "sg:postcode":"6019",
    "sg:province":"WA",
    "sg:tags":[
        "equipment",
        "salon",
        "supply"
    ],
    "wof:name":"Firm.n.Fold",
    "wof:placetype":"venue"
},
  "geometry": {"coordinates":[115.76550293,-31.8995304108],"type":"Point"}
}