{
  "type": "Feature",
  "properties": {
    "addr:full":"66 Bungarra Crs Chipping Norton NSW 2170",
    "addr:housenumber":"66",
    "addr:postcode":"2170",
    "addr:street":"Bungarra Crs",
    "iso:country":"AU",
    "sg:address":"66 Bungarra Crs",
    "sg:city":"Chipping Norton",
    "sg:classifiers":[
        {
            "category":"Building & Trades",
            "subcategory":"Pest Control",
            "type":"Services"
        }
    ],
    "sg:phone":"+61 408 274 548",
    "sg:postcode":"2170",
    "sg:province":"NSW",
    "wof:name":"Turners Pest Control",
    "wof:placetype":"venue"
},
  "geometry": {"coordinates":[150.96173095699999,-33.9171600342],"type":"Point"}
}