{
  "type": "Feature",
  "properties": {
    "iso:country":"AU",
    "sg:address":"85 Brewer Drv",
    "sg:city":"Wodonga",
    "sg:classifiers":[
        {
            "category":"Building & Trades",
            "subcategory":"Construction",
            "type":"Services"
        }
    ],
    "sg:phone":"+61 412 691 235",
    "sg:postcode":"3690",
    "sg:province":"VIC",
    "sg:tags":[
        "contractor"
    ],
    "wof:name":"Konig Wolfgang",
    "wof:placetype":"venue"
},
  "geometry": {"coordinates":[146.83497619600001,-36.1202316284],"type":"Point"}
}