{
  "type": "Feature",
  "properties": {
    "iso:country":"AU",
    "sg:address":"14 Cavell Ave",
    "sg:city":"Rhodes",
    "sg:classifiers":[
        {
            "category":"Government",
            "subcategory":"Department Of Motor Vehicles",
            "type":"Public Place"
        }
    ],
    "sg:phone":"+61 2 9743 6822",
    "sg:postcode":"2138",
    "sg:province":"NSW",
    "sg:tags":[
        "car",
        "conversion",
        "seat"
    ],
    "wof:name":"Roman Autotek Australia Pty Ltd",
    "wof:placetype":"venue"
},
  "geometry": {"coordinates":[151.089752197,-33.8251342773],"type":"Point"}
}