{
  "type": "Feature",
  "properties": {
    "addr:full":"Shp 32/ 43 Park Rd Cabramatta NSW 2166",
    "addr:housenumber":"32 / 43",
    "addr:postcode":"2166",
    "addr:street":"Park Rd",
    "iso:country":"AU",
    "sg:address":"Shp 32/ 43 Park Rd",
    "sg:city":"Cabramatta",
    "sg:classifiers":[
        {
            "category":"Shopping",
            "subcategory":"Clothing, Apparel, & Fashions",
            "type":"Retail Goods"
        }
    ],
    "sg:phone":"+61 2 9723 3877",
    "sg:postcode":"2166",
    "sg:province":"NSW",
    "sg:tags":[
        "lady",
        "wear"
    ],
    "wof:name":"New Smiley Fashion",
    "wof:placetype":"venue"
},
  "geometry": {"coordinates":[150.93765258799999,-33.890209198],"type":"Point"}
}