{
  "type": "Feature",
  "properties": {
    "addr:full":"17 Willmett Rd Goolwa SA 5214",
    "addr:housenumber":"17",
    "addr:postcode":"5214",
    "addr:street":"Willmett Rd",
    "iso:country":"AU",
    "sg:address":"17 Willmett Rd",
    "sg:city":"Goolwa",
    "sg:classifiers":[
        {
            "category":"Social Services",
            "subcategory":"Retirement Home",
            "type":"Services"
        }
    ],
    "sg:phone":"+61 8 8555 0044",
    "sg:postcode":"5214",
    "sg:province":"SA",
    "sg:tags":[
        "village"
    ],
    "wof:name":"Thornbury Park",
    "wof:placetype":"venue"
},
  "geometry": {"coordinates":[138.771194458,-35.5069389343],"type":"Point"}
}