{
  "type": "Feature",
  "properties": {
    "addr:full":"1 Ryan Pl Moruya NSW 2537",
    "addr:housenumber":"1",
    "addr:postcode":"2537",
    "addr:street":"Ryan Pl",
    "iso:country":"AU",
    "sg:address":"1 Ryan Pl",
    "sg:city":"Moruya",
    "sg:classifiers":[
        {
            "category":"Professional",
            "subcategory":"Business Services",
            "type":"Services"
        }
    ],
    "sg:phone":"+61 2 4474 4046",
    "sg:postcode":"2537",
    "sg:province":"NSW",
    "sg:tags":[
        "drafting"
    ],
    "wof:name":"Hallahan & Associates",
    "wof:placetype":"venue"
},
  "geometry": {"coordinates":[150.07366943400001,-35.9124717712],"type":"Point"}
}