{
  "type": "Feature",
  "properties": {
    "addr:full":"26- 28 Aumuller St Portsmith QLD 4870",
    "addr:housenumber":"28",
    "addr:postcode":"4870",
    "addr:street":"Aumuller St Portsmith",
    "iso:country":"AU",
    "sg:address":"26- 28 Aumuller St",
    "sg:city":"Portsmith",
    "sg:classifiers":[
        {
            "category":"Farming",
            "subcategory":"Crops",
            "type":"Manufacturing & Wholesale Goods"
        }
    ],
    "sg:phone":"+61 7 4035 5200",
    "sg:postcode":"4870",
    "sg:province":"QLD",
    "sg:tags":[
        "warehousing"
    ],
    "wof:name":"Cairns Self Storage",
    "wof:placetype":"venue"
},
  "geometry": {"coordinates":[145.771194458,-16.9438419342],"type":"Point"}
}