{
  "type": "Feature",
  "properties": {
    "addr:full":"29 Hilton St Clifton Hill VIC 3068",
    "addr:housenumber":"29",
    "addr:postcode":"3068",
    "addr:street":"Hilton St",
    "iso:country":"AU",
    "sg:address":"29 Hilton St",
    "sg:city":"Clifton Hill",
    "sg:classifiers":[
        {
            "category":"Health Services",
            "subcategory":"Health Practitioner",
            "type":"Services"
        }
    ],
    "sg:phone":"+61 3 9481 4907",
    "sg:postcode":"3068",
    "sg:province":"VIC",
    "sg:tags":[
        "alternative"
    ],
    "wof:name":"Alexander Technique Australian Society Of Teachers Of The (Austat)",
    "wof:placetype":"venue"
},
  "geometry": {"coordinates":[144.98724365199999,-37.7916412354],"type":"Point"}
}