{
  "type": "Feature",
  "properties": {
    "iso:country":"AU",
    "sg:address":"6, 15 Delawney St",
    "sg:city":"Balcatta",
    "sg:classifiers":[
        {
            "category":"Professional",
            "subcategory":"Detective & Security Services",
            "type":"Services"
        }
    ],
    "sg:phone":"+61 8 9240 2733",
    "sg:postcode":"6021",
    "sg:province":"WA",
    "sg:tags":[
        "investigator"
    ],
    "wof:name":"Adept",
    "wof:placetype":"venue"
},
  "geometry": {"coordinates":[115.80950164799999,-31.8664302826],"type":"Point"}
}