{
  "type": "Feature",
  "properties": {
    "addr:full":"417 Russel Rd Munster WA 6166",
    "addr:housenumber":"417",
    "addr:postcode":"6166",
    "addr:street":"Russel Rd",
    "iso:country":"AU",
    "sg:address":"417 Russel Rd",
    "sg:city":"Munster",
    "sg:classifiers":[
        {
            "category":"Retail",
            "subcategory":"Laundry & Dry Cleaning",
            "type":"Services"
        }
    ],
    "sg:phone":"+61 409 921 092",
    "sg:postcode":"6166",
    "sg:province":"WA",
    "sg:tags":[
        "cloth",
        "supply"
    ],
    "wof:name":"Cotton Waste Supply",
    "wof:placetype":"venue"
},
  "geometry": {"coordinates":[115.789101,-32.14558],"type":"Point"}
}