{
  "type": "Feature",
  "properties": {
    "addr:full":"25 Coldstream St Yamba NSW 2464",
    "addr:housenumber":"25",
    "addr:postcode":"2464",
    "addr:street":"Coldstream St",
    "iso:country":"AU",
    "sg:address":"25 Coldstream St",
    "sg:city":"Yamba",
    "sg:classifiers":[
        {
            "category":"Education",
            "subcategory":"Special Training",
            "type":"Public Place"
        }
    ],
    "sg:phone":"+61 2 6646 1999",
    "sg:postcode":"2464",
    "sg:province":"NSW",
    "sg:tags":[
        "school",
        "art"
    ],
    "wof:name":"Arthouse Australia",
    "wof:placetype":"venue"
},
  "geometry": {"coordinates":[153.36009216299999,-29.4369735718],"type":"Point"}
}