{
  "type": "Feature",
  "properties": {
    "iso:country":"AU",
    "sg:address":"Shop9 Corsair Ave",
    "sg:city":"Inala",
    "sg:classifiers":[
        {
            "category":"Health Services",
            "subcategory":"Doctor",
            "type":"Services"
        }
    ],
    "sg:phone":"+61 7 3372 1277",
    "sg:postcode":"4077",
    "sg:province":"QLD",
    "sg:tags":[
        "medical",
        "practitioner"
    ],
    "wof:name":"TRan A L V DR",
    "wof:placetype":"venue"
},
  "geometry": {"coordinates":[152.97567749000001,-27.5976905823],"type":"Point"}
}