{
  "type": "Feature",
  "properties": {
    "addr:full":"156 Richmond Rd Bowen QLD 4805",
    "addr:housenumber":"156",
    "addr:postcode":"4805",
    "addr:street":"Richmond Rd",
    "iso:country":"AU",
    "sg:address":"156 Richmond Rd",
    "sg:city":"Bowen",
    "sg:classifiers":[
        {
            "category":"Retail",
            "subcategory":"Veterinary Services",
            "type":"Services"
        }
    ],
    "sg:phone":"+61 7 4786 4864",
    "sg:postcode":"4805",
    "sg:province":"QLD",
    "sg:tags":[
        "surgeon"
    ],
    "wof:name":"Bowen Veterinary Clinic",
    "wof:placetype":"venue"
},
  "geometry": {"coordinates":[148.23564148,-20.0006713867],"type":"Point"}
}