{
  "type": "Feature",
  "properties": {
    "iso:country":"AU",
    "sg:address":"945 Beaufort St",
    "sg:city":"Inglewood",
    "sg:classifiers":[
        {
            "category":"Shopping",
            "subcategory":"Baby Store",
            "type":"Retail Goods"
        }
    ],
    "sg:phone":"+61 8 9471 1011",
    "sg:postcode":"6052",
    "sg:province":"WA",
    "sg:tags":[
        "wear"
    ],
    "wof:name":"Baby Goose Nursery Manchester & Clothing",
    "wof:placetype":"venue"
},
  "geometry": {"coordinates":[115.886642456,-31.9209842682],"type":"Point"}
}