{
  "type": "Feature",
  "properties": {
    "addr:full":"31 View Rd Vermont VIC 3133",
    "addr:housenumber":"31",
    "addr:postcode":"3133",
    "addr:street":"View Rd",
    "iso:country":"AU",
    "sg:address":"31 View Rd",
    "sg:city":"Vermont",
    "sg:classifiers":[
        {
            "category":"Building & Trades",
            "subcategory":"Cleaning & Sanitation",
            "type":"Services"
        }
    ],
    "sg:phone":"+61 3 9874 6787",
    "sg:postcode":"3133",
    "sg:province":"VIC",
    "sg:tags":[
        "cleaner",
        "repairer",
        "roof"
    ],
    "wof:name":"Select Metal Roofing",
    "wof:placetype":"venue"
},
  "geometry": {"coordinates":[145.20274352999999,-37.8377075195],"type":"Point"}
}