{
  "type": "Feature",
  "properties": {
    "iso:country":"AU",
    "sg:address":"80 Chandos St",
    "sg:city":"St Leonards",
    "sg:classifiers":[
        {
            "category":"Manufacturing",
            "subcategory":"Glass & Minerals",
            "type":"Manufacturing & Wholesale Goods"
        }
    ],
    "sg:phone":"+61 2 9906 5220",
    "sg:postcode":"2065",
    "sg:province":"NSW",
    "sg:tags":[
        "exploration"
    ],
    "wof:name":"PlatSearch NL",
    "wof:placetype":"venue"
},
  "geometry": {"coordinates":[151.19923400900001,-33.8218917847],"type":"Point"}
}