{
  "type": "Feature",
  "properties": {
    "iso:country":"AU",
    "sg:address":"62a Tenth Ave",
    "sg:city":"Budgewoi",
    "sg:classifiers":[
        {
            "category":"Education",
            "subcategory":"University",
            "type":"Public Place"
        }
    ],
    "sg:phone":"+61 2 4390 8121",
    "sg:postcode":"2262",
    "sg:province":"NSW",
    "sg:tags":[
        "sewing",
        "dressmaking",
        "tuition"
    ],
    "wof:name":"Charm Cottage Quilts & Collectables",
    "wof:placetype":"venue"
},
  "geometry": {"coordinates":[151.55526699999999,-33.233601],"type":"Point"}
}