{
  "type": "Feature",
  "properties": {
    "addr:full":"Cnr Somerville Rd & Williamstown Rd Yarraville VIC 3013",
    "addr:postcode":"3013",
    "addr:street":"Cnr Somerville Rd & Williamstown Rd",
    "iso:country":"AU",
    "sg:address":"Cnr Somerville Rd & Williamstown Rd",
    "sg:city":"Yarraville",
    "sg:classifiers":[
        {
            "category":"Health Services",
            "subcategory":"Health Practitioner",
            "type":"Services"
        }
    ],
    "sg:phone":"+61 3 9314 7557",
    "sg:postcode":"3013",
    "sg:province":"VIC",
    "sg:tags":[
        "naturopath"
    ],
    "wof:name":"Carnovale Pharmacy - Yarraville",
    "wof:placetype":"venue"
},
  "geometry": {"coordinates":[144.88348388700001,-37.8127937317],"type":"Point"}
}