{
  "type": "Feature",
  "properties": {
    "addr:full":"253 Hemmant-Tingalpa Rd Hemmant QLD 4174",
    "addr:housenumber":"253",
    "addr:postcode":"4174",
    "addr:street":"Hemmant-Tingalpa Rd",
    "iso:country":"AU",
    "sg:address":"253 Hemmant-Tingalpa Rd",
    "sg:city":"Hemmant",
    "sg:classifiers":[
        {
            "category":"Utilities",
            "subcategory":"Electric",
            "type":"Services"
        }
    ],
    "sg:phone":"+61 422 345 522",
    "sg:postcode":"4174",
    "sg:province":"QLD",
    "sg:tags":[
        "electrical",
        "contractor"
    ],
    "wof:name":"Cadillac Electrical Services",
    "wof:placetype":"venue"
},
  "geometry": {"coordinates":[153.16294860799999,-27.4504547119],"type":"Point"}
}