{
  "type": "Feature",
  "properties": {
    "addr:full":"105 Adams Rd Mariginiup WA 6065",
    "addr:housenumber":"105",
    "addr:postcode":"6065",
    "addr:street":"Adams Rd",
    "iso:country":"AU",
    "sg:address":"105 Adams Rd",
    "sg:city":"Mariginiup",
    "sg:classifiers":[
        {
            "category":"Building & Trades",
            "subcategory":"Plumbing",
            "type":"Services"
        }
    ],
    "sg:phone":"+61 8 9405 4200",
    "sg:postcode":"6065",
    "sg:province":"WA",
    "sg:tags":[
        "plumber",
        "gasfitters"
    ],
    "wof:name":"Triple T Contracting Pty Ltd",
    "wof:placetype":"venue"
},
  "geometry": {"coordinates":[115.826828003,-31.7066287994],"type":"Point"}
}