{
  "type": "Feature",
  "properties": {
    "iso:country":"AU",
    "sg:address":"274 Main Rd East St",
    "sg:city":"Albans",
    "sg:classifiers":[
        {
            "category":"Health Services",
            "subcategory":"Dentist",
            "type":"Services"
        }
    ],
    "sg:phone":"+61 3 9822 1761",
    "sg:postcode":"3021",
    "sg:province":"VIC",
    "wof:name":"Cernavin I",
    "wof:placetype":"venue"
},
  "geometry": {"coordinates":[144.804092,-37.744568],"type":"Point"}
}