{
  "type": "Feature",
  "properties": {
    "iso:country":"AU",
    "sg:address":"485 Whitehorse Rd",
    "sg:city":"Mitcham",
    "sg:classifiers":[
        {
            "category":"Banks & Credit Unions",
            "subcategory":"Financial Services",
            "type":"Services"
        }
    ],
    "sg:phone":"+61 3 8873 1600",
    "sg:postcode":"3132",
    "sg:province":"VIC",
    "sg:tags":[
        "loan",
        "finance",
        "mortgage"
    ],
    "wof:name":"Melbourne Credit Union",
    "wof:placetype":"venue"
},
  "geometry": {"coordinates":[145.19236755399999,-37.8162384033],"type":"Point"}
}