{
  "type": "Feature",
  "properties": {
    "iso:country":"AU",
    "sg:address":"17 Hollingworth St",
    "sg:city":"Port Macquarie",
    "sg:classifiers":[
        {
            "category":"Health Services",
            "subcategory":"Doctor",
            "type":"Services"
        }
    ],
    "sg:phone":"+61 2 6586 6180",
    "sg:postcode":"2444",
    "sg:province":"NSW",
    "sg:tags":[
        "medical",
        "practitioner"
    ],
    "wof:name":"Ngu Slc",
    "wof:placetype":"venue"
},
  "geometry": {"coordinates":[152.904831,-31.433212],"type":"Point"}
}