{
  "type": "Feature",
  "properties": {
    "iso:country":"AU",
    "sg:address":"12- 14 Bay St",
    "sg:city":"Port Broughton",
    "sg:classifiers":[
        {
            "category":"Autos & Motor Vehicles",
            "subcategory":"Boat Sales",
            "type":"Retail Goods"
        }
    ],
    "sg:phone":"+61 8 8635 2889",
    "sg:postcode":"5522",
    "sg:province":"SA",
    "sg:tags":[
        "yacht"
    ],
    "wof:name":"Broughton Marine & Outdoor",
    "wof:placetype":"venue"
},
  "geometry": {"coordinates":[137.93325805699999,-33.6005477905],"type":"Point"}
}