{
  "type": "Feature",
  "properties": {
    "addr:full":"29 Irvine St Bayswater WA 6053",
    "addr:housenumber":"29",
    "addr:postcode":"6053",
    "addr:street":"Irvine St",
    "iso:country":"AU",
    "sg:address":"29 Irvine St",
    "sg:city":"Bayswater",
    "sg:classifiers":[
        {
            "category":"Professional",
            "type":"Services"
        }
    ],
    "sg:phone":"+61 8 9272 7560",
    "sg:postcode":"6053",
    "sg:province":"WA",
    "sg:tags":[
        "spray",
        "painting"
    ],
    "wof:name":"A.B. Smash Repairs",
    "wof:placetype":"venue"
},
  "geometry": {"coordinates":[115.919692993,-31.9108753204],"type":"Point"}
}