{
  "type": "Feature",
  "properties": {
    "addr:full":"9 Sydney Rd Brunswick VIC 3056",
    "addr:housenumber":"9",
    "addr:postcode":"3056",
    "addr:street":"Sydney Rd",
    "iso:country":"AU",
    "sg:address":"9 Sydney Rd",
    "sg:city":"Brunswick",
    "sg:classifiers":[
        {
            "category":"Utilities",
            "subcategory":"Natural Gas",
            "type":"Services"
        }
    ],
    "sg:phone":"+61 412 558 100",
    "sg:postcode":"3056",
    "sg:province":"VIC",
    "sg:tags":[
        "solid",
        "plasterer"
    ],
    "wof:name":"Carlton Plaster Co",
    "wof:placetype":"venue"
},
  "geometry": {"coordinates":[144.96400451700001,-37.755153656],"type":"Point"}
}