{
  "type": "Feature",
  "properties": {
    "addr:full":"90 Avebury Drv Berwick VIC 3806",
    "addr:housenumber":"90",
    "addr:postcode":"3806",
    "addr:street":"Avebury Drv",
    "iso:country":"AU",
    "sg:address":"90 Avebury Drv",
    "sg:city":"Berwick",
    "sg:classifiers":[
        {
            "category":"Health Services",
            "subcategory":"Health Practitioner",
            "type":"Services"
        }
    ],
    "sg:phone":"+61 3 9796 1088",
    "sg:postcode":"3806",
    "sg:province":"VIC",
    "sg:tags":[
        "bowen",
        "therapy"
    ],
    "wof:name":"Pam Bolger",
    "wof:placetype":"venue"
},
  "geometry": {"coordinates":[145.331863403,-38.0243339539],"type":"Point"}
}