{
  "type": "Feature",
  "properties": {
    "addr:full":"7 Elfran Ave Pottsville Beach NSW 2489",
    "addr:housenumber":"7",
    "addr:postcode":"2489",
    "addr:street":"Elfran Ave",
    "iso:country":"AU",
    "sg:address":"7 Elfran Ave",
    "sg:city":"Pottsville Beach",
    "sg:classifiers":[
        {
            "category":"Utilities",
            "type":"Services"
        }
    ],
    "sg:phone":"+61 2 6676 1010",
    "sg:postcode":"2489",
    "sg:province":"NSW",
    "sg:tags":[
        "refrigeration",
        "industrial",
        "commercial",
        "retail"
    ],
    "wof:name":"Elfran Refrigeration",
    "wof:placetype":"venue"
},
  "geometry": {"coordinates":[153.570037842,-28.3791656494],"type":"Point"}
}