{
  "type": "Feature",
  "properties": {
    "iso:country":"AU",
    "sg:address":"Unit 1 / 19 Fisher St",
    "sg:city":"Salisbury",
    "sg:classifiers":[
        {
            "category":"Building & Trades",
            "subcategory":"Electrical",
            "type":"Services"
        }
    ],
    "sg:phone":"+61 8 8281 6367",
    "sg:postcode":"5108",
    "sg:province":"SA",
    "sg:tags":[
        "repair",
        "generator",
        "electric",
        "motor"
    ],
    "wof:name":"R.M.E",
    "wof:placetype":"venue"
},
  "geometry": {"coordinates":[138.645141602,-34.7535934448],"type":"Point"}
}