{
  "type": "Feature",
  "properties": {
    "addr:full":"16 Walker St South Windsor NSW 2756",
    "addr:housenumber":"16",
    "addr:postcode":"2756",
    "addr:street":"Walker St",
    "iso:country":"AU",
    "sg:address":"16 Walker St",
    "sg:city":"South Windsor",
    "sg:classifiers":[
        {
            "category":"Manufacturing",
            "subcategory":"Metals",
            "type":"Manufacturing & Wholesale Goods"
        }
    ],
    "sg:phone":"+61 2 4577 5652",
    "sg:postcode":"2756",
    "sg:province":"NSW",
    "sg:tags":[
        "merchant"
    ],
    "wof:name":"KRE Metaland",
    "wof:placetype":"venue"
},
  "geometry": {"coordinates":[150.80987548799999,-33.6232223511],"type":"Point"}
}