{
  "type": "Feature",
  "properties": {
    "iso:country":"AU",
    "sg:address":"66 Canterbury Rd",
    "sg:city":"Bayswater",
    "sg:classifiers":[
        {
            "category":"Farming",
            "subcategory":"Fish & Marine Products",
            "type":"Manufacturing & Wholesale Goods"
        }
    ],
    "sg:phone":"+61 3 8720 1966",
    "sg:postcode":"3153",
    "sg:province":"VIC",
    "sg:tags":[
        "foil"
    ],
    "wof:name":"Confoil Containers",
    "wof:placetype":"venue"
},
  "geometry": {"coordinates":[145.29669189399999,-37.8234138489],"type":"Point"}
}