{
  "type": "Feature",
  "properties": {
    "addr:full":"73 Henley St Henley Brook WA 6055",
    "addr:housenumber":"73",
    "addr:postcode":"6055",
    "addr:street":"Henley St Henley",
    "iso:country":"AU",
    "sg:address":"73 Henley St",
    "sg:city":"Henley Brook",
    "sg:classifiers":[
        {
            "category":"Building & Trades",
            "subcategory":"Construction",
            "type":"Services"
        }
    ],
    "sg:phone":"+61 8 9296 4785",
    "sg:postcode":"6055",
    "sg:province":"WA",
    "sg:tags":[
        "fencing",
        "contractor"
    ],
    "wof:name":"Reliable Fencing",
    "wof:placetype":"venue"
},
  "geometry": {"coordinates":[115.996239,-31.807676],"type":"Point"}
}