{
  "type": "Feature",
  "properties": {
    "iso:country":"AU",
    "sg:address":"Shop 14 The Pines K P McGrath Drv",
    "sg:city":"Elanora",
    "sg:classifiers":[
        {
            "category":"Retail",
            "subcategory":"Repair Shop",
            "type":"Services"
        }
    ],
    "sg:phone":"+61 7 5534 4822",
    "sg:postcode":"4221",
    "sg:province":"QLD",
    "sg:tags":[
        "handbag"
    ],
    "wof:name":"Kay's Bag Stores (NSW) Pty Ltd",
    "wof:placetype":"venue"
},
  "geometry": {"coordinates":[153.46051025400001,-28.1234436035],"type":"Point"}
}