{
  "type": "Feature",
  "properties": {
    "addr:full":"34 Debenham Ave Leumeah Heights NSW 2560",
    "addr:housenumber":"34",
    "addr:postcode":"2560",
    "addr:street":"Debenham Ave",
    "iso:country":"AU",
    "sg:address":"34 Debenham Ave",
    "sg:city":"Leumeah Heights",
    "sg:classifiers":[
        {
            "category":"Structure",
            "subcategory":"Office Building",
            "type":"Public Place"
        }
    ],
    "sg:phone":"+61 2 4628 8834",
    "sg:postcode":"2560",
    "sg:province":"NSW",
    "sg:tags":[
        "slater",
        "tiler",
        "roof"
    ],
    "wof:name":"MacLeod Shaun L",
    "wof:placetype":"venue"
},
  "geometry": {"coordinates":[150.84999084500001,-34.0488967896],"type":"Point"}
}