{
  "type": "Feature",
  "properties": {
    "addr:full":"PO Box 224 Ascot Vale VIC 3032",
    "addr:postcode":"3032",
    "iso:country":"AU",
    "sg:address":"PO Box 224",
    "sg:city":"Ascot Vale",
    "sg:classifiers":[
        {
            "category":"Professional",
            "subcategory":"Employment Agencies",
            "type":"Services"
        }
    ],
    "sg:phone":"+61 3 9352 0655",
    "sg:postcode":"3032",
    "sg:province":"VIC",
    "sg:tags":[
        "entertainer",
        "agent"
    ],
    "wof:name":"Tina Louise Entertainment Group",
    "wof:placetype":"venue"
},
  "geometry": {"coordinates":[144.91554300000001,-37.7756],"type":"Point"}
}