{
  "type": "Feature",
  "properties": {
    "addr:full":"240 Mona Vale Rd St Ives NSW 2075",
    "addr:housenumber":"240",
    "addr:postcode":"2075",
    "addr:street":"Mona Vale Rd",
    "iso:country":"AU",
    "sg:address":"240 Mona Vale Rd",
    "sg:city":"St Ives",
    "sg:classifiers":[
        {
            "category":"Home & Garden",
            "subcategory":"Garden Supply",
            "type":"Retail Goods"
        }
    ],
    "sg:phone":"+61 2 9144 6969",
    "sg:postcode":"2075",
    "sg:province":"NSW",
    "sg:tags":[
        "equipment"
    ],
    "wof:name":"Flower Power Garden Centres",
    "wof:placetype":"venue"
},
  "geometry": {"coordinates":[151.164886475,-33.7274475098],"type":"Point"}
}