{
  "type": "Feature",
  "properties": {
    "addr:full":"5- 7 College St North Lakes QLD 4509",
    "addr:housenumber":"7",
    "addr:postcode":"4509",
    "addr:street":"College St",
    "iso:country":"AU",
    "sg:address":"5- 7 College St",
    "sg:city":"North Lakes",
    "sg:classifiers":[
        {
            "category":"Social Services",
            "subcategory":"Child Care",
            "type":"Services"
        }
    ],
    "sg:phone":"+61 7 3886 5455",
    "sg:postcode":"4509",
    "sg:province":"QLD",
    "wof:name":"ABC Learning Centres",
    "wof:placetype":"venue"
},
  "geometry": {"coordinates":[153.02272033700001,-27.2326087952],"type":"Point"}
}