{
  "type": "Feature",
  "properties": {
    "addr:full":"126 Sydney Rd Fairlight NSW 2094",
    "addr:housenumber":"126",
    "addr:postcode":"2094",
    "addr:street":"Sydney Rd",
    "iso:country":"AU",
    "sg:address":"126 Sydney Rd",
    "sg:city":"Fairlight",
    "sg:classifiers":[
        {
            "category":"Autos & Motor Vehicles",
            "subcategory":"Fuel & Gas Station",
            "type":"Retail Goods"
        }
    ],
    "sg:phone":"+61 2 9949 2474",
    "sg:postcode":"2094",
    "sg:province":"NSW",
    "wof:name":"Avos Auto Repairs",
    "wof:placetype":"venue"
},
  "geometry": {"coordinates":[151.27760314899999,-33.7958335876],"type":"Point"}
}