{
  "type": "Feature",
  "properties": {
    "iso:country":"AU",
    "sg:address":"Gladstone Rd",
    "sg:city":"Dandenong North",
    "sg:classifiers":[
        {
            "category":"Education",
            "subcategory":"Dance Studio",
            "type":"Public Place"
        }
    ],
    "sg:phone":"+61 3 9791 4781",
    "sg:postcode":"3175",
    "sg:province":"VIC",
    "sg:tags":[
        "instruction",
        "language"
    ],
    "wof:name":"Standard Chinese Language School",
    "wof:placetype":"venue"
},
  "geometry": {"coordinates":[145.20782470699999,-37.9539031982],"type":"Point"}
}