{
  "type": "Feature",
  "properties": {
    "addr:full":"136 Victoria Rd Balmain NSW 2041",
    "addr:housenumber":"136",
    "addr:postcode":"2041",
    "addr:street":"Victoria Rd",
    "iso:country":"AU",
    "sg:address":"136 Victoria Rd",
    "sg:city":"Balmain",
    "sg:classifiers":[
        {
            "category":"Education",
            "subcategory":"Dance Studio",
            "type":"Public Place"
        }
    ],
    "sg:phone":"+61 2 9557 7751",
    "sg:postcode":"2041",
    "sg:province":"NSW",
    "sg:tags":[
        "venue",
        "tuition"
    ],
    "wof:name":"Latin Motion Dance Academy",
    "wof:placetype":"venue"
},
  "geometry": {"coordinates":[151.169861,-33.86396],"type":"Point"}
}