{
  "type": "Feature",
  "properties": {
    "addr:full":"29 Lowndes St Salisbury QLD 4107",
    "addr:housenumber":"29",
    "addr:postcode":"4107",
    "addr:street":"Lowndes St",
    "iso:country":"AU",
    "sg:address":"29 Lowndes St",
    "sg:city":"Salisbury",
    "sg:classifiers":[
        {
            "category":"Home & Garden",
            "subcategory":"Carpets & Floor Coverings",
            "type":"Retail Goods"
        }
    ],
    "sg:phone":"+61 418 725 760",
    "sg:postcode":"4107",
    "sg:province":"QLD",
    "sg:tags":[
        "tile",
        "wall",
        "layer"
    ],
    "wof:name":"Valzacchi D J",
    "wof:placetype":"venue"
},
  "geometry": {"coordinates":[153.044555664,-27.5551376343],"type":"Point"}
}