{
  "type": "Feature",
  "properties": {
    "addr:full":"275- 290 Victoria St Darlinghurst NSW 2010",
    "addr:housenumber":"290",
    "addr:postcode":"2010",
    "addr:street":"Victoria St",
    "iso:country":"AU",
    "sg:address":"275- 290 Victoria St",
    "sg:city":"Darlinghurst",
    "sg:classifiers":[
        {
            "category":"Fast Food",
            "type":"Food & Drink"
        }
    ],
    "sg:phone":"+61 2 9357 1600",
    "sg:postcode":"2010",
    "sg:province":"NSW",
    "sg:tags":[
        "away",
        "take"
    ],
    "wof:name":"Oporto Darlinghurst",
    "wof:placetype":"venue"
},
  "geometry": {"coordinates":[151.22103881800001,-33.8791770935],"type":"Point"}
}