{
  "type": "Feature",
  "properties": {
    "addr:full":"3 Kaleski St Moorebank NSW 2170",
    "addr:housenumber":"3",
    "addr:postcode":"2170",
    "addr:street":"Kaleski St",
    "iso:country":"AU",
    "sg:address":"3 Kaleski St",
    "sg:city":"Moorebank",
    "sg:classifiers":[
        {
            "category":"Farming",
            "subcategory":"Orchard",
            "type":"Manufacturing & Wholesale Goods"
        }
    ],
    "sg:phone":"+61 2 9821 4249",
    "sg:postcode":"2170",
    "sg:province":"NSW",
    "sg:tags":[
        "wholesaler",
        "jean",
        "mfrs"
    ],
    "wof:name":"Stereo Clothing Pty Ltd",
    "wof:placetype":"venue"
},
  "geometry": {"coordinates":[150.93066406200001,-33.9367408752],"type":"Point"}
}