{
  "type": "Feature",
  "properties": {
    "addr:full":"Kitchener Pde Bankstown NSW 2200",
    "addr:postcode":"2200",
    "addr:street":"Kitchener",
    "iso:country":"AU",
    "sg:address":"Kitchener Pde",
    "sg:city":"Bankstown",
    "sg:classifiers":[
        {
            "category":"Banks & Credit Unions",
            "subcategory":"Financial Services",
            "type":"Services"
        }
    ],
    "sg:phone":"+61 2 9708 5900",
    "sg:postcode":"2200",
    "sg:province":"NSW",
    "sg:tags":[
        "financier"
    ],
    "wof:name":"St.George Bank Limited",
    "wof:placetype":"venue"
},
  "geometry": {"coordinates":[151.032883,-33.916775],"type":"Point"}
}