{
  "type": "Feature",
  "properties": {
    "iso:country":"AU",
    "sg:address":"4/ 27 Lawrence Drv",
    "sg:city":"Nerang",
    "sg:classifiers":[
        {
            "category":"Landmark",
            "subcategory":"City Walls",
            "type":"Public Place"
        }
    ],
    "sg:phone":"+61 7 5596 4426",
    "sg:postcode":"4211",
    "sg:province":"QLD",
    "sg:tags":[
        "board",
        "particle"
    ],
    "wof:name":"Gold Coast Woodmachining",
    "wof:placetype":"venue"
},
  "geometry": {"coordinates":[153.34695434599999,-27.9969100952],"type":"Point"}
}