{
  "type": "Feature",
  "properties": {
    "iso:country":"AU",
    "sg:address":"305 Stephenson Rd",
    "sg:city":"Mt Waverley",
    "sg:classifiers":[
        {
            "category":"Fast Food",
            "type":"Food & Drink"
        }
    ],
    "sg:phone":"+61 3 9830 8182",
    "sg:postcode":"3149",
    "sg:province":"VIC",
    "sg:tags":[
        "away",
        "take"
    ],
    "wof:name":"Starfish Fish & Chippery",
    "wof:placetype":"venue"
},
  "geometry": {"coordinates":[145.12872314399999,-37.8765907288],"type":"Point"}
}