{
  "type": "Feature",
  "properties": {
    "addr:full":"55 Barry Ave Mortdale NSW 2223",
    "addr:housenumber":"55",
    "addr:postcode":"2223",
    "addr:street":"Barry Ave",
    "iso:country":"AU",
    "sg:address":"55 Barry Ave",
    "sg:city":"Mortdale",
    "sg:classifiers":[
        {
            "category":"Manufacturing",
            "subcategory":"Chemicals & Compounds",
            "type":"Manufacturing & Wholesale Goods"
        }
    ],
    "sg:phone":"+61 2 9533 2333",
    "sg:postcode":"2223",
    "sg:province":"NSW",
    "sg:tags":[
        "electroplating"
    ],
    "wof:name":"Anodizers & Electroplaters Pty Ltd",
    "wof:placetype":"venue"
},
  "geometry": {"coordinates":[151.06752014200001,-33.966632843],"type":"Point"}
}