{
  "type": "Feature",
  "properties": {
    "addr:full":"42 Jonson St Byron Bay NSW 2481",
    "addr:housenumber":"42",
    "addr:postcode":"2481",
    "addr:street":"Jonson St",
    "iso:country":"AU",
    "sg:address":"42 Jonson St",
    "sg:city":"Byron Bay",
    "sg:classifiers":[
        {
            "category":"Retail",
            "subcategory":"Laundry & Dry Cleaning",
            "type":"Services"
        }
    ],
    "sg:phone":"+61 2 6685 6599",
    "sg:postcode":"2481",
    "sg:province":"NSW",
    "wof:name":"Byron Dry Cleaners & Laundry Service",
    "wof:placetype":"venue"
},
  "geometry": {"coordinates":[153.612838745,-28.6479206085],"type":"Point"}
}