{
  "type": "Feature",
  "properties": {
    "addr:full":"3 Chaucer Ave Malvern East VIC 3145",
    "addr:housenumber":"3",
    "addr:postcode":"3145",
    "addr:street":"Chaucer Ave",
    "iso:country":"AU",
    "sg:address":"3 Chaucer Ave",
    "sg:city":"Malvern East",
    "sg:classifiers":[
        {
            "category":"Manufacturing",
            "subcategory":"Tools & Machinery",
            "type":"Manufacturing & Wholesale Goods"
        }
    ],
    "sg:phone":"+61 3 9571 3907",
    "sg:postcode":"3145",
    "sg:province":"VIC",
    "sg:tags":[
        "equipment",
        "scale",
        "weighing"
    ],
    "wof:name":"Libra Scale Service",
    "wof:placetype":"venue"
},
  "geometry": {"coordinates":[145.060012817,-37.8789634705],"type":"Point"}
}