{
  "type": "Feature",
  "properties": {
    "iso:country":"AU",
    "sg:address":"78 Park La",
    "sg:city":"Traralgon",
    "sg:classifiers":[
        {
            "category":"Building & Trades",
            "subcategory":"Construction",
            "type":"Services"
        }
    ],
    "sg:phone":"+61 412 505 738",
    "sg:postcode":"3844",
    "sg:province":"VIC",
    "sg:tags":[
        "contractor"
    ],
    "wof:name":"Geoff Fletcher Builders",
    "wof:placetype":"venue"
},
  "geometry": {"coordinates":[146.560714722,-38.1884346008],"type":"Point"}
}