{
  "type": "Feature",
  "properties": {
    "addr:full":"34-38 Manning St Taree NSW 2430",
    "addr:housenumber":"34-38",
    "addr:postcode":"2430",
    "addr:street":"Manning St",
    "iso:country":"AU",
    "sg:address":"34-38 Manning St",
    "sg:city":"Taree",
    "sg:classifiers":[
        {
            "category":"Building & Trades",
            "subcategory":"Construction",
            "type":"Services"
        }
    ],
    "sg:phone":"+61 2 6552 3288",
    "sg:postcode":"2430",
    "sg:province":"NSW",
    "sg:tags":[
        "pool",
        "swimming"
    ],
    "wof:name":"Mitre 10 Solutions Taree",
    "wof:placetype":"venue"
},
  "geometry": {"coordinates":[152.460815,-31.911863],"type":"Point"}
}