{
  "type": "Feature",
  "properties": {
    "addr:full":"144 Rowe St Eastwood NSW 2122",
    "addr:housenumber":"144",
    "addr:postcode":"2122",
    "addr:street":"Rowe St",
    "iso:country":"AU",
    "sg:address":"144 Rowe St",
    "sg:city":"Eastwood",
    "sg:classifiers":[
        {
            "category":"Banks & Credit Unions",
            "subcategory":"Bank",
            "type":"Services"
        }
    ],
    "sg:phone":"+61 13 20 32",
    "sg:postcode":"2122",
    "sg:province":"NSW",
    "wof:name":"Westpac",
    "wof:placetype":"venue"
},
  "geometry": {"coordinates":[151.08181762699999,-33.7915649414],"type":"Point"}
}