{
  "type": "Feature",
  "properties": {
    "addr:full":"PO Box 1900 Bathurst NSW 2795",
    "addr:postcode":"2795",
    "iso:country":"AU",
    "sg:address":"PO Box 1900",
    "sg:city":"Bathurst",
    "sg:classifiers":[
        {
            "category":"Commercial Area",
            "type":"Public Place"
        }
    ],
    "sg:phone":"+61 2 6332 1600",
    "sg:postcode":"2795",
    "sg:province":"NSW",
    "sg:tags":[
        "heavy",
        "carrier"
    ],
    "wof:name":"Balmana Earthmoving & Transport",
    "wof:placetype":"venue"
},
  "geometry": {"coordinates":[149.61332702600001,-33.4233894348],"type":"Point"}
}