{
  "type": "Feature",
  "properties": {
    "addr:full":"PO Box 539 North Perth WA 6006",
    "addr:postcode":"6006",
    "iso:country":"AU",
    "sg:address":"PO Box 539",
    "sg:city":"North Perth",
    "sg:classifiers":[
        {
            "category":"Retail",
            "subcategory":"Car Wash",
            "type":"Services"
        }
    ],
    "sg:phone":"+61 422 395 000",
    "sg:postcode":"6006",
    "sg:province":"WA",
    "sg:tags":[
        "truck",
        "cleaning"
    ],
    "wof:name":"Gleam Wheels Automotive Detailing",
    "wof:placetype":"venue"
},
  "geometry": {"coordinates":[115.854103088,-31.9246997833],"type":"Point"}
}