{
  "type": "Feature",
  "properties": {
    "addr:full":"97 Flemington Rd North Melbourne VIC 3051",
    "addr:housenumber":"97",
    "addr:postcode":"3051",
    "addr:street":"Flemington Rd",
    "iso:country":"AU",
    "sg:address":"97 Flemington Rd",
    "sg:city":"North Melbourne",
    "sg:classifiers":[
        {
            "category":"Industrial Area",
            "type":"Public Place"
        }
    ],
    "sg:phone":"+61 3 9220 1177",
    "sg:postcode":"3051",
    "sg:province":"VIC",
    "sg:tags":[
        "protective",
        "clothing"
    ],
    "wof:name":"KingGee",
    "wof:placetype":"venue"
},
  "geometry": {"coordinates":[144.952835083,-37.7983131409],"type":"Point"}
}