{
  "type": "Feature",
  "properties": {
    "iso:country":"AU",
    "sg:address":"161 Pinjarra Rd",
    "sg:city":"Mandurah",
    "sg:classifiers":[
        {
            "category":"Autos & Motor Vehicles",
            "subcategory":"Automobile Sales",
            "type":"Retail Goods"
        }
    ],
    "sg:phone":"+61 8 9583 1333",
    "sg:postcode":"6210",
    "sg:province":"WA",
    "sg:tags":[
        "car",
        "new"
    ],
    "sg:website":"http://www.mandurahtoyota.com.au/",
    "wof:name":"Mandurah Toyota",
    "wof:placetype":"venue"
},
  "geometry": {"coordinates":[115.773201,-32.547264],"type":"Point"}
}