{
  "type": "Feature",
  "properties": {
    "addr:full":"Cnr Mitchell & Queen Sts Bendigo VIC 3550",
    "addr:postcode":"3550",
    "addr:street":"Cnr",
    "iso:country":"AU",
    "sg:address":"Cnr Mitchell & Queen Sts",
    "sg:city":"Bendigo",
    "sg:classifiers":[
        {
            "category":"Banks & Credit Unions",
            "subcategory":"Investment Brokerage",
            "type":"Services"
        }
    ],
    "sg:phone":"+61 3 5443 7966",
    "sg:postcode":"3550",
    "sg:province":"VIC",
    "sg:tags":[
        "share",
        "broker",
        "stock"
    ],
    "wof:name":"Dungey Robert K",
    "wof:placetype":"venue"
},
  "geometry": {"coordinates":[144.283935547,-36.7645721436],"type":"Point"}
}