{
  "type": "Feature",
  "properties": {
    "iso:country":"AU",
    "sg:address":"1/ 3 Resolution Drv",
    "sg:city":"Caringbah",
    "sg:classifiers":[
        {
            "category":"Retail",
            "subcategory":"Auto Repair",
            "type":"Services"
        }
    ],
    "sg:phone":"+61 2 9526 7311",
    "sg:postcode":"1495",
    "sg:province":"NSW",
    "sg:tags":[
        "aluminium"
    ],
    "wof:name":"Smart Aluminium",
    "wof:placetype":"venue"
},
  "geometry": {"coordinates":[151.13334699999999,-34.034431],"type":"Point"}
}