{
  "type": "Feature",
  "properties": {
    "iso:country":"AU",
    "sg:address":"Cnr St Kilda & Commercial Rds",
    "sg:city":"Melbourne",
    "sg:classifiers":[
        {
            "category":"Health Services",
            "subcategory":"Doctor",
            "type":"Services"
        }
    ],
    "sg:phone":"+61 3 9820 3255",
    "sg:postcode":"3004",
    "sg:province":"VIC",
    "sg:tags":[
        "medical",
        "practitioner"
    ],
    "wof:name":"St Kilda Rd Medi 7",
    "wof:placetype":"venue"
},
  "geometry": {"coordinates":[144.97633361800001,-37.8373184204],"type":"Point"}
}