{
  "type": "Feature",
  "properties": {
    "addr:full":"70- 72 Orange Ave Mildura VIC 3500",
    "addr:housenumber":"72",
    "addr:postcode":"3500",
    "addr:street":"Orange Ave",
    "iso:country":"AU",
    "sg:address":"70- 72 Orange Ave",
    "sg:city":"Mildura",
    "sg:classifiers":[
        {
            "category":"Manufacturing",
            "subcategory":"Motor Vehicles & Parts",
            "type":"Manufacturing & Wholesale Goods"
        }
    ],
    "sg:phone":"+61 3 5023 7633",
    "sg:postcode":"3500",
    "sg:province":"VIC",
    "sg:tags":[
        "replacement"
    ],
    "wof:name":"Burson Automotive Pty Ltd",
    "wof:placetype":"venue"
},
  "geometry": {"coordinates":[142.163787842,-34.1879005432],"type":"Point"}
}