{
  "type": "Feature",
  "properties": {
    "addr:full":"Spectrum House 1 Elegans Ave St Ives NSW 2075",
    "addr:housenumber":"1",
    "addr:postcode":"2075",
    "addr:street":"Elegans Ave",
    "iso:country":"AU",
    "sg:address":"Spectrum House 1 Elegans Ave",
    "sg:city":"St Ives",
    "sg:classifiers":[
        {
            "category":"Social Services",
            "subcategory":"Job Training",
            "type":"Services"
        }
    ],
    "sg:phone":"+61 2 9449 6499",
    "sg:postcode":"2075",
    "sg:province":"NSW",
    "sg:tags":[
        "control",
        "equipment",
        "noise"
    ],
    "wof:name":"Noise & Sound Services",
    "wof:placetype":"venue"
},
  "geometry": {"coordinates":[151.17193603499999,-33.7356109619],"type":"Point"}
}