{
  "type": "Feature",
  "properties": {
    "addr:full":"Shop 1/ 55 Queen St Campbelltown NSW 2560",
    "addr:housenumber":"shop 1 / 55",
    "addr:postcode":"2560",
    "addr:street":"Queen St",
    "iso:country":"AU",
    "sg:address":"Shop 1/ 55 Queen St",
    "sg:city":"Campbelltown",
    "sg:classifiers":[
        {
            "category":"Autos & Motor Vehicles",
            "subcategory":"Auto Supplies",
            "type":"Retail Goods"
        }
    ],
    "sg:phone":"+61 2 4620 5777",
    "sg:postcode":"2560",
    "sg:province":"NSW",
    "sg:tags":[
        "part",
        "cycles",
        "accessory"
    ],
    "wof:name":"The Motor Cycle Cafe Pty Ltd",
    "wof:placetype":"venue"
},
  "geometry": {"coordinates":[150.818115234,-34.0621871948],"type":"Point"}
}