{
  "type": "Feature",
  "properties": {
    "iso:country":"AU",
    "sg:address":"Level 3, 87 Wickham Tce",
    "sg:city":"Brisbane",
    "sg:classifiers":[
        {
            "category":"Professional",
            "subcategory":"Engineering",
            "type":"Services"
        }
    ],
    "sg:phone":"+61 419 662 242",
    "sg:postcode":"4001",
    "sg:province":"QLD",
    "sg:tags":[
        "engineer"
    ],
    "wof:name":"Flagstaff Consulting Group",
    "wof:placetype":"venue"
},
  "geometry": {"coordinates":[153.047561645,-27.3007793427],"type":"Point"}
}