{
  "type": "Feature",
  "properties": {
    "addr:full":"10 Parkvalley Dr Chirnside Park VIC 3116",
    "addr:housenumber":"10",
    "addr:postcode":"3116",
    "addr:street":"Parkvalley Dr",
    "iso:country":"AU",
    "sg:address":"10 Parkvalley Dr",
    "sg:city":"Chirnside Park",
    "sg:classifiers":[
        {
            "category":"Professional",
            "subcategory":"Management & Consulting",
            "type":"Services"
        }
    ],
    "sg:phone":"+61 3 9777 0213",
    "sg:postcode":"3116",
    "sg:province":"VIC",
    "sg:tags":[
        "consultant",
        "business"
    ],
    "wof:name":"J Barnetts Business Systems",
    "wof:placetype":"venue"
},
  "geometry": {"coordinates":[145.32817077600001,-37.7565078735],"type":"Point"}
}