{
  "type": "Feature",
  "properties": {
    "addr:full":"Level 1, 19 Essex St Fremantle WA 6160",
    "addr:housenumber":"19",
    "addr:postcode":"6160",
    "addr:street":"Essex St",
    "iso:country":"AU",
    "sg:address":"Level 1, 19 Essex St",
    "sg:city":"Fremantle",
    "sg:classifiers":[
        {
            "category":"Recreation",
            "subcategory":"Amusement Park",
            "type":"Entertainment"
        }
    ],
    "sg:phone":"+61 8 9431 7760",
    "sg:postcode":"6160",
    "sg:province":"WA",
    "wof:name":"The Poolroom Essex Street",
    "wof:placetype":"venue"
},
  "geometry": {"coordinates":[115.74803900000001,-32.056774],"type":"Point"}
}