{
  "type": "Feature",
  "properties": {
    "addr:full":"485 Latrobe St Melbourne VIC 3000",
    "addr:housenumber":"485",
    "addr:postcode":"3000",
    "addr:street":"Latrobe St",
    "iso:country":"AU",
    "sg:address":"485 Latrobe St",
    "sg:city":"Melbourne",
    "sg:classifiers":[
        {
            "category":"Insurance",
            "subcategory":"Hazard Insurance",
            "type":"Services"
        }
    ],
    "sg:phone":"+61 3 9601 8755",
    "sg:postcode":"3000",
    "sg:province":"VIC",
    "sg:tags":[
        "fire",
        "accident",
        "marine"
    ],
    "wof:name":"Commercial Union Lenders Mortgage Insurance Ltd",
    "wof:placetype":"venue"
},
  "geometry": {"coordinates":[144.954681397,-37.812374115],"type":"Point"}
}