{
  "type": "Feature",
  "properties": {
    "addr:full":"20/ 215 Betula Ave Mill Park VIC 3082",
    "addr:housenumber":"20 / 215",
    "addr:postcode":"3082",
    "addr:street":"Betula Ave",
    "iso:country":"AU",
    "sg:address":"20/ 215 Betula Ave",
    "sg:city":"Mill Park",
    "sg:classifiers":[
        {
            "category":"Professional",
            "subcategory":"Detective & Security Services",
            "type":"Services"
        }
    ],
    "sg:phone":"+61 3 9775 6000",
    "sg:postcode":"3082",
    "sg:province":"VIC",
    "sg:tags":[
        "consultant",
        "system"
    ],
    "wof:name":"Telstar Security",
    "wof:placetype":"venue"
},
  "geometry": {"coordinates":[145.05809020999999,-37.6773414612],"type":"Point"}
}