{
  "type": "Feature",
  "properties": {
    "addr:full":"29 Sorrensen St Tinana QLD 4650",
    "addr:housenumber":"29",
    "addr:postcode":"4650",
    "addr:street":"Sorrensen St",
    "iso:country":"AU",
    "sg:address":"29 Sorrensen St",
    "sg:city":"Tinana",
    "sg:classifiers":[
        {
            "category":"Building & Trades",
            "subcategory":"Construction",
            "type":"Services"
        }
    ],
    "sg:phone":"+61 7 4121 5599",
    "sg:postcode":"4650",
    "sg:province":"QLD",
    "sg:tags":[
        "welding"
    ],
    "wof:name":"D Francis Welding",
    "wof:placetype":"venue"
},
  "geometry": {"coordinates":[152.674713,-25.558598],"type":"Point"}
}