{
  "type": "Feature",
  "properties": {
    "addr:full":"117 Mcintyre Rd Sunshine North VIC 3020",
    "addr:housenumber":"117",
    "addr:postcode":"3020",
    "addr:street":"Mcintyre Rd",
    "iso:country":"AU",
    "sg:address":"117 Mcintyre Rd",
    "sg:city":"Sunshine North",
    "sg:classifiers":[
        {
            "category":"Retail",
            "subcategory":"Auto Repair",
            "type":"Services"
        }
    ],
    "sg:phone":"+61 3 9312 2484",
    "sg:postcode":"3020",
    "sg:province":"VIC",
    "sg:tags":[
        "gas",
        "conversion",
        "natural",
        "lp",
        "vehicle"
    ],
    "wof:name":"Autoteck Pty Ltd",
    "wof:placetype":"venue"
},
  "geometry": {"coordinates":[144.83038300000001,-37.767193],"type":"Point"}
}