{
  "type": "Feature",
  "properties": {
    "addr:full":"Shp 1/ 489 Peel St Tamworth NSW 2340",
    "addr:housenumber":"/ 489",
    "addr:postcode":"2340",
    "addr:street":"Peel St",
    "iso:country":"AU",
    "sg:address":"Shp 1/ 489 Peel St",
    "sg:city":"Tamworth",
    "sg:classifiers":[
        {
            "category":"Personal",
            "subcategory":"Beauty Salon",
            "type":"Services"
        }
    ],
    "sg:phone":"+61 2 6766 5113",
    "sg:postcode":"2340",
    "sg:province":"NSW",
    "sg:tags":[
        "hairdresser"
    ],
    "wof:name":"Wavelengths 489",
    "wof:placetype":"venue"
},
  "geometry": {"coordinates":[150.93295288100001,-31.0942459106],"type":"Point"}
}