{
  "type": "Feature",
  "properties": {
    "iso:country":"AU",
    "sg:address":"1 Plumkett Ave",
    "sg:city":"Ormond",
    "sg:classifiers":[
        {
            "category":"Building & Trades",
            "subcategory":"Locksmith",
            "type":"Services"
        }
    ],
    "sg:phone":"+61 417 113 237",
    "sg:postcode":"3204",
    "sg:province":"VIC",
    "sg:tags":[
        "lock"
    ],
    "wof:name":"Aussie Rab",
    "wof:placetype":"venue"
},
  "geometry": {"coordinates":[145.04620399999999,-37.900433],"type":"Point"}
}