{
  "type": "Feature",
  "properties": {
    "addr:full":"Level 13 15 Bent St Sydney NSW 2000",
    "addr:housenumber":"15",
    "addr:postcode":"2000",
    "addr:street":"Bent St",
    "iso:country":"AU",
    "sg:address":"Level 13 15 Bent St",
    "sg:city":"Sydney",
    "sg:classifiers":[
        {
            "category":"Banks & Credit Unions",
            "subcategory":"Investment Brokerage",
            "type":"Services"
        }
    ],
    "sg:phone":"+61 2 9221 1777",
    "sg:postcode":"2000",
    "sg:province":"NSW",
    "wof:name":"Lewis Securities Ltd",
    "wof:placetype":"venue"
},
  "geometry": {"coordinates":[151.21090698200001,-33.8647537231],"type":"Point"}
}