{
  "type": "Feature",
  "properties": {
    "addr:full":"2 Karrakatta St Black Rock VIC 3193",
    "addr:housenumber":"2",
    "addr:postcode":"3193",
    "addr:street":"Karrakatta St",
    "iso:country":"AU",
    "sg:address":"2 Karrakatta St",
    "sg:city":"Black Rock",
    "sg:classifiers":[
        {
            "category":"Organizations",
            "subcategory":"Community Association",
            "type":"Services"
        }
    ],
    "sg:phone":"+61 3 9589 4424",
    "sg:postcode":"3193",
    "sg:province":"VIC",
    "sg:tags":[
        "club",
        "senior",
        "citizen"
    ],
    "wof:name":"Black Rock Activity Centre",
    "wof:placetype":"venue"
},
  "geometry": {"coordinates":[145.016647339,-37.9743919373],"type":"Point"}
}