{
  "type": "Feature",
  "properties": {
    "addr:full":"Barramul St Simpson VIC 3266",
    "addr:postcode":"3266",
    "addr:street":"St",
    "iso:country":"AU",
    "sg:address":"Barramul St",
    "sg:city":"Simpson",
    "sg:classifiers":[
        {
            "category":"Food & Beverages",
            "subcategory":"Supermarket",
            "type":"Retail Goods"
        }
    ],
    "sg:phone":"+61 3 5594 3340",
    "sg:postcode":"3266",
    "sg:province":"VIC",
    "sg:tags":[
        "grocery",
        "store"
    ],
    "wof:name":"Settlement Supermarket",
    "wof:placetype":"venue"
},
  "geometry": {"coordinates":[143.209274292,-38.4959716797],"type":"Point"}
}