{
  "type": "Feature",
  "properties": {
    "iso:country":"AU",
    "sg:address":"2 Byre Ave",
    "sg:city":"Somerton Park",
    "sg:classifiers":[
        {
            "category":"Retail",
            "subcategory":"Auto Repair",
            "type":"Services"
        }
    ],
    "sg:phone":"+61 8 8376 6288",
    "sg:postcode":"5044",
    "sg:province":"SA",
    "sg:tags":[
        "repairer",
        "motor",
        "engineer"
    ],
    "wof:name":"I T S Auto Care",
    "wof:placetype":"venue"
},
  "geometry": {"coordinates":[138.52177399999999,-34.998016],"type":"Point"}
}