{
  "type": "Feature",
  "properties": {
    "iso:country":"AU",
    "sg:address":"24 Sowden St",
    "sg:city":"Toowoomba",
    "sg:classifiers":[
        {
            "category":"Mining & Drilling",
            "type":"Manufacturing & Wholesale Goods"
        }
    ],
    "sg:phone":"+61 7 4630 1276",
    "sg:postcode":"4350",
    "sg:province":"QLD",
    "sg:tags":[
        "boring",
        "contractor"
    ],
    "wof:name":"O&#039;Hara Bros Qld Pty Ltd",
    "wof:placetype":"venue"
},
  "geometry": {"coordinates":[151.91957099999999,-27.59096],"type":"Point"}
}