{
  "type": "Feature",
  "properties": {
    "iso:country":"AU",
    "sg:address":"195 Hector St",
    "sg:city":"Sefton",
    "sg:classifiers":[
        {
            "category":"Food & Beverages",
            "subcategory":"Groceries & Convenience Stores",
            "type":"Retail Goods"
        }
    ],
    "sg:phone":"+61 2 9743 8711",
    "sg:postcode":"2162",
    "sg:province":"NSW",
    "wof:name":"Amin Mixed Business",
    "wof:placetype":"venue"
},
  "geometry": {"coordinates":[151.00550842300001,-33.8910522461],"type":"Point"}
}