{
  "type": "Feature",
  "properties": {
    "addr:full":"PO Box 4187 Manuka ACT 2603",
    "addr:postcode":"2603",
    "iso:country":"AU",
    "sg:address":"PO Box 4187",
    "sg:city":"Manuka",
    "sg:classifiers":[
        {
            "category":"Education",
            "subcategory":"Special Training",
            "type":"Public Place"
        }
    ],
    "sg:phone":"+61 2 6239 5766",
    "sg:postcode":"2603",
    "sg:province":"ACT",
    "sg:tags":[
        "development"
    ],
    "wof:name":"PALM Consulting Group",
    "wof:placetype":"venue"
},
  "geometry": {"coordinates":[149.13372802699999,-35.3202018738],"type":"Point"}
}