{
  "type": "Feature",
  "properties": {
    "addr:full":"48 Longueville Rd Lane Cove NSW 2066",
    "addr:housenumber":"48",
    "addr:postcode":"2066",
    "addr:street":"Longueville Rd",
    "iso:country":"AU",
    "sg:address":"48 Longueville Rd",
    "sg:city":"Lane Cove",
    "sg:classifiers":[
        {
            "category":"Government",
            "subcategory":"Department Of Motor Vehicles",
            "type":"Public Place"
        }
    ],
    "sg:phone":"+61 2 9911 3555",
    "sg:postcode":"2066",
    "sg:province":"NSW",
    "sg:tags":[
        "organisation",
        "local"
    ],
    "wof:name":"Lane Cove Council",
    "wof:placetype":"venue"
},
  "geometry": {"coordinates":[151.17022705100001,-33.8137817383],"type":"Point"}
}