{
  "type": "Feature",
  "properties": {
    "addr:full":"55 Anderson St Manunda QLD 4870",
    "addr:housenumber":"55",
    "addr:postcode":"4870",
    "addr:street":"Anderson St",
    "iso:country":"AU",
    "sg:address":"55 Anderson St",
    "sg:city":"Manunda",
    "sg:classifiers":[
        {
            "category":"Manufacturing",
            "subcategory":"Motor Vehicles & Parts",
            "type":"Manufacturing & Wholesale Goods"
        }
    ],
    "sg:phone":"+61 7 4051 2511",
    "sg:postcode":"4870",
    "sg:province":"QLD",
    "sg:tags":[
        "replacement"
    ],
    "wof:name":"Auto Parts",
    "wof:placetype":"venue"
},
  "geometry": {"coordinates":[145.750091553,-16.9146270752],"type":"Point"}
}