{
  "type": "Feature",
  "properties": {
    "iso:country":"AU",
    "sg:address":"20 Bundy St",
    "sg:city":"Gilgandra",
    "sg:classifiers":[
        {
            "category":"Building & Trades",
            "subcategory":"Pest Control",
            "type":"Services"
        }
    ],
    "sg:phone":"+61 2 6847 2772",
    "sg:postcode":"2827",
    "sg:province":"NSW",
    "wof:name":"B J's Pest Control",
    "wof:placetype":"venue"
},
  "geometry": {"coordinates":[148.65618896500001,-31.7120113373],"type":"Point"}
}