{
  "type": "Feature",
  "properties": {
    "addr:full":"172 Liberty Pde Heidelberg West VIC 3081",
    "addr:housenumber":"172",
    "addr:postcode":"3081",
    "addr:street":"Liberty Pde",
    "iso:country":"AU",
    "sg:address":"172 Liberty Pde",
    "sg:city":"Heidelberg West",
    "sg:classifiers":[
        {
            "category":"Health Services",
            "subcategory":"Doctor",
            "type":"Services"
        }
    ],
    "sg:phone":"+61 411 147 547",
    "sg:postcode":"3081",
    "sg:province":"VIC",
    "sg:tags":[
        "nurse",
        "nursing"
    ],
    "wof:name":"Harmony Health Nursing Agency",
    "wof:placetype":"venue"
},
  "geometry": {"coordinates":[145.037307739,-37.7471237183],"type":"Point"}
}