{
  "type": "Feature",
  "properties": {
    "iso:country":"AU",
    "sg:address":"627 Burwood Rd",
    "sg:city":"Hawthorn East",
    "sg:classifiers":[
        {
            "category":"Retail",
            "subcategory":"Repair Shop",
            "type":"Services"
        }
    ],
    "sg:phone":"+61 3 9813 1199",
    "sg:postcode":"3123",
    "sg:province":"VIC",
    "sg:tags":[
        "mending",
        "clothing",
        "alteration"
    ],
    "wof:name":"Snippity Snip",
    "wof:placetype":"venue"
},
  "geometry": {"coordinates":[145.04502868599999,-37.8235778809],"type":"Point"}
}