{
  "type": "Feature",
  "properties": {
    "addr:full":"107 Philip St Parramatta NSW 2150",
    "addr:housenumber":"107",
    "addr:postcode":"2150",
    "addr:street":"Philip St",
    "iso:country":"AU",
    "sg:address":"107 Philip St",
    "sg:city":"Parramatta",
    "sg:classifiers":[
        {
            "category":"Home & Garden",
            "subcategory":"Building Materials",
            "type":"Retail Goods"
        }
    ],
    "sg:phone":"+61 2 9849 7400",
    "sg:postcode":"2150",
    "sg:province":"NSW",
    "sg:tags":[
        "pre-mixed",
        "concrete"
    ],
    "wof:name":"Metromix Concrete",
    "wof:placetype":"venue"
},
  "geometry": {"coordinates":[151.097167969,-33.8707962036],"type":"Point"}
}