{
  "type": "Feature",
  "properties": {
    "addr:full":"9 Beauty Point Rd Mosman NSW 2088",
    "addr:postcode":"2088",
    "addr:street":"Rd",
    "iso:country":"AU",
    "sg:address":"9 Beauty Point Rd",
    "sg:city":"Mosman",
    "sg:classifiers":[
        {
            "category":"Education",
            "subcategory":"School",
            "type":"Public Place"
        }
    ],
    "sg:phone":"+61 2 9969 9205",
    "sg:postcode":"2088",
    "sg:province":"NSW",
    "sg:tags":[
        "correspondence"
    ],
    "wof:name":"Kodomo Japanese Language School",
    "wof:placetype":"venue"
},
  "geometry": {"coordinates":[151.240524292,-33.8096084595],"type":"Point"}
}