{
  "type": "Feature",
  "properties": {
    "addr:full":"106 Churchill St Childers QLD 4660",
    "addr:housenumber":"106",
    "addr:postcode":"4660",
    "addr:street":"Churchill St",
    "iso:country":"AU",
    "sg:address":"106 Churchill St",
    "sg:city":"Childers",
    "sg:classifiers":[
        {
            "category":"Food & Beverages",
            "subcategory":"Specialty",
            "type":"Retail Goods"
        }
    ],
    "sg:phone":"+61 7 4126 1000",
    "sg:postcode":"4660",
    "sg:province":"QLD",
    "sg:tags":[
        "product",
        "health"
    ],
    "wof:name":"Live Now Health Foods",
    "wof:placetype":"venue"
},
  "geometry": {"coordinates":[152.27760314899999,-25.2366142273],"type":"Point"}
}