{
  "type": "Feature",
  "properties": {
    "addr:full":"52 Fourth Rd Armadale WA 6112",
    "addr:housenumber":"52",
    "addr:postcode":"6112",
    "addr:street":"Fourth Rd",
    "iso:country":"AU",
    "sg:address":"52 Fourth Rd",
    "sg:city":"Armadale",
    "sg:classifiers":[
        {
            "category":"Health Services",
            "subcategory":"Health Practitioner",
            "type":"Services"
        }
    ],
    "sg:phone":"+61 8 9399 5709",
    "sg:postcode":"6112",
    "sg:province":"WA",
    "sg:tags":[
        "naturopath"
    ],
    "wof:name":"Mariappan Indira",
    "wof:placetype":"venue"
},
  "geometry": {"coordinates":[116.01361846899999,-32.154132843],"type":"Point"}
}