{
  "type": "Feature",
  "properties": {
    "addr:full":"21 Coldstream St Leederville WA 6007",
    "addr:housenumber":"21",
    "addr:postcode":"6007",
    "addr:street":"Coldstream St",
    "iso:country":"AU",
    "sg:address":"21 Coldstream St",
    "sg:city":"Leederville",
    "sg:classifiers":[
        {
            "category":"Organizations",
            "subcategory":"Membership Organization",
            "type":"Services"
        }
    ],
    "sg:phone":"+61 8 9381 5270",
    "sg:postcode":"6007",
    "sg:province":"WA",
    "sg:tags":[
        "club",
        "bridge"
    ],
    "wof:name":"Smith Peter R",
    "wof:placetype":"venue"
},
  "geometry": {"coordinates":[115.836921692,-31.9377365112],"type":"Point"}
}