{
  "type": "Feature",
  "properties": {
    "addr:full":"41 Latimer Rd Logan Village QLD 4207",
    "addr:housenumber":"41",
    "addr:postcode":"4207",
    "addr:street":"Latimer Rd",
    "iso:country":"AU",
    "sg:address":"41 Latimer Rd",
    "sg:city":"Logan Village",
    "sg:classifiers":[
        {
            "category":"Home & Garden",
            "subcategory":"Garden Supply",
            "type":"Retail Goods"
        }
    ],
    "sg:phone":"+61 414 359 267",
    "sg:postcode":"4207",
    "sg:province":"QLD",
    "sg:tags":[
        "turf",
        "lawn"
    ],
    "wof:name":"Apollo Turf",
    "wof:placetype":"venue"
},
  "geometry": {"coordinates":[153.13583374000001,-27.7799835205],"type":"Point"}
}