{
  "type": "Feature",
  "properties": {
    "addr:full":"PO Box 1068 Noosa Heads QLD 4567",
    "addr:postcode":"4567",
    "iso:country":"AU",
    "sg:address":"PO Box 1068",
    "sg:city":"Noosa Heads",
    "sg:classifiers":[
        {
            "category":"Professional",
            "subcategory":"Art Services",
            "type":"Services"
        }
    ],
    "sg:phone":"+61 412 071 918",
    "sg:postcode":"4567",
    "sg:province":"QLD",
    "sg:tags":[
        "decorator",
        "painter"
    ],
    "wof:name":"Anderson Painting & Decorating",
    "wof:placetype":"venue"
},
  "geometry": {"coordinates":[153.086105347,-26.3990192413],"type":"Point"}
}