{
  "type": "Feature",
  "properties": {
    "addr:full":"19B Pascoe Street Karrinyup WA 6018",
    "addr:housenumber":"19b",
    "addr:postcode":"6018",
    "addr:street":"Pascoe Street",
    "iso:country":"AU",
    "sg:address":"19B Pascoe Street",
    "sg:city":"Karrinyup",
    "sg:classifiers":[
        {
            "category":"Professional",
            "subcategory":"Computer Services",
            "type":"Services"
        }
    ],
    "sg:phone":"+61 8 9245 5716",
    "sg:postcode":"6018",
    "sg:province":"WA",
    "sg:tags":[
        "repairs",
        "upgrade",
        "equipment"
    ],
    "wof:name":"PC Advice",
    "wof:placetype":"venue"
},
  "geometry": {"coordinates":[115.773277283,-31.8717956543],"type":"Point"}
}