{
  "type": "Feature",
  "properties": {
    "iso:country":"AU",
    "sg:address":"111 Junction Rd",
    "sg:city":"Nunawading",
    "sg:classifiers":[
        {
            "category":"Real Estate",
            "subcategory":"Surveying",
            "type":"Services"
        }
    ],
    "sg:phone":"+61 428 312 408",
    "sg:postcode":"3131",
    "sg:province":"VIC",
    "sg:tags":[
        "surveyor",
        "land"
    ],
    "wof:name":"G & C Sadlier Design Pty Ltd",
    "wof:placetype":"venue"
},
  "geometry": {"coordinates":[145.17036438,-37.8075637817],"type":"Point"}
}