{
  "type": "Feature",
  "properties": {
    "iso:country":"AU",
    "sg:address":"3 Laurel St",
    "sg:city":"Pennington",
    "sg:classifiers":[
        {
            "category":"Professional",
            "subcategory":"Accounting & Tax Preparation",
            "type":"Services"
        }
    ],
    "sg:phone":"+61 437 799 713",
    "sg:postcode":"5013",
    "sg:province":"SA",
    "sg:tags":[
        "bookkeeping"
    ],
    "wof:name":"Ready Bookkeeping",
    "wof:placetype":"venue"
},
  "geometry": {"coordinates":[138.52955627399999,-34.8531112671],"type":"Point"}
}