{
  "type": "Feature",
  "properties": {
    "iso:country":"AU",
    "sg:address":"Unit 3/ 2 Pullman Pl",
    "sg:city":"Emu Plains",
    "sg:classifiers":[
        {
            "category":"Professional",
            "subcategory":"Engineering",
            "type":"Services"
        }
    ],
    "sg:phone":"+61 2 4735 3657",
    "sg:postcode":"2750",
    "sg:province":"NSW",
    "sg:tags":[
        "consultant",
        "geotechnical",
        "engineer"
    ],
    "wof:name":"Earth, Air, Water Consulting & Monitoring Pty Ltd",
    "wof:placetype":"venue"
},
  "geometry": {"coordinates":[150.65480041500001,-33.7460517883],"type":"Point"}
}