{
  "type": "Feature",
  "properties": {
    "addr:full":"7 Cairns Ave Palm Beach QLD 4221",
    "addr:housenumber":"7",
    "addr:postcode":"4221",
    "addr:street":"Cairns Ave",
    "iso:country":"AU",
    "sg:address":"7 Cairns Ave",
    "sg:city":"Palm Beach",
    "sg:classifiers":[
        {
            "category":"Building & Trades",
            "subcategory":"Construction",
            "type":"Services"
        }
    ],
    "sg:phone":"+61 7 5598 3383",
    "sg:postcode":"4221",
    "sg:province":"QLD",
    "sg:tags":[
        "concrete",
        "contractor"
    ],
    "wof:name":"UXL International",
    "wof:placetype":"venue"
},
  "geometry": {"coordinates":[153.47108459500001,-28.1310768127],"type":"Point"}
}