{
  "type": "Feature",
  "properties": {
    "addr:full":"10 Snowdon St Wodonga VIC 3689",
    "addr:housenumber":"10",
    "addr:postcode":"3689",
    "addr:street":"Snowdon St",
    "iso:country":"AU",
    "sg:address":"10 Snowdon St",
    "sg:city":"Wodonga",
    "sg:classifiers":[
        {
            "category":"Personal",
            "subcategory":"Massage",
            "type":"Services"
        }
    ],
    "sg:phone":"+61 424 062 162",
    "sg:postcode":"3689",
    "sg:province":"VIC",
    "sg:tags":[
        "therapy"
    ],
    "wof:name":"Ken Wilson",
    "wof:placetype":"venue"
},
  "geometry": {"coordinates":[146.87896699999999,-36.124161],"type":"Point"}
}