{
  "type": "Feature",
  "properties": {
    "iso:country":"AU",
    "sg:address":"6 Great Western Plains Rd",
    "sg:city":"Stirling North",
    "sg:classifiers":[
        {
            "category":"Retail",
            "subcategory":"Repair Shop",
            "type":"Services"
        }
    ],
    "sg:phone":"+61 419 038 596",
    "sg:postcode":"5710",
    "sg:province":"SA",
    "sg:tags":[
        "stove",
        "part",
        "range"
    ],
    "wof:name":"PKB Electrical Services",
    "wof:placetype":"venue"
},
  "geometry": {"coordinates":[137.84220886200001,-32.5129356384],"type":"Point"}
}