{
  "type": "Feature",
  "properties": {
    "addr:full":"8 Glastonbury Ave Unanderra NSW 2526",
    "addr:housenumber":"8",
    "addr:postcode":"2526",
    "addr:street":"Glastonbury Ave",
    "iso:country":"AU",
    "sg:address":"8 Glastonbury Ave",
    "sg:city":"Unanderra",
    "sg:classifiers":[
        {
            "category":"Wholesale",
            "subcategory":"Machinery & Supplies",
            "type":"Manufacturing & Wholesale Goods"
        }
    ],
    "sg:phone":"+61 2 4260 5877",
    "sg:postcode":"2526",
    "sg:province":"NSW",
    "sg:tags":[
        "distributor",
        "crane",
        "mfrs"
    ],
    "wof:name":"South Coast Hiab Services",
    "wof:placetype":"venue"
},
  "geometry": {"coordinates":[150.857543945,-34.4570121765],"type":"Point"}
}