{
  "type": "Feature",
  "properties": {
    "addr:full":"170 Francis Rd Lawnton QLD 4501",
    "addr:housenumber":"170",
    "addr:postcode":"4501",
    "addr:street":"Francis Rd",
    "iso:country":"AU",
    "sg:address":"170 Francis Rd",
    "sg:city":"Lawnton",
    "sg:classifiers":[
        {
            "category":"Organizations",
            "subcategory":"Membership Organization",
            "type":"Services"
        }
    ],
    "sg:phone":"+61 7 3205 5141",
    "sg:postcode":"4501",
    "sg:province":"QLD",
    "sg:tags":[
        "club",
        "car"
    ],
    "wof:name":"Queensland Chevrolet Club",
    "wof:placetype":"venue"
},
  "geometry": {"coordinates":[152.963653564,-27.284828186],"type":"Point"}
}