{
  "type": "Feature",
  "properties": {
    "iso:country":"AU",
    "sg:address":"15 George St",
    "sg:city":"Wallsend",
    "sg:classifiers":[
        {
            "category":"Professional",
            "subcategory":"Art Services",
            "type":"Services"
        }
    ],
    "sg:phone":"+61 2 4951 4862",
    "sg:postcode":"2287",
    "sg:province":"NSW",
    "sg:tags":[
        "decorator",
        "painter"
    ],
    "wof:name":"Brockwell F H",
    "wof:placetype":"venue"
},
  "geometry": {"coordinates":[151.67466735799999,-32.9017982483],"type":"Point"}
}