{
  "type": "Feature",
  "properties": {
    "addr:full":"266 Oxford St Bondi Junction NSW 2022",
    "addr:housenumber":"266",
    "addr:postcode":"2022",
    "addr:street":"Oxford St",
    "iso:country":"AU",
    "sg:address":"266 Oxford St",
    "sg:city":"Bondi Junction",
    "sg:classifiers":[
        {
            "category":"Home & Garden",
            "subcategory":"Carpets & Floor Coverings",
            "type":"Retail Goods"
        }
    ],
    "sg:phone":"+61 2 9387 4500",
    "sg:postcode":"2022",
    "sg:province":"NSW",
    "sg:tags":[
        "tile",
        "wall"
    ],
    "wof:name":"Pazotti",
    "wof:placetype":"venue"
},
  "geometry": {"coordinates":[151.244232178,-33.8907241821],"type":"Point"}
}