{
  "type": "Feature",
  "properties": {
    "addr:full":"158 McFarlane Drv Minchinbury NSW 2770",
    "addr:housenumber":"158",
    "addr:postcode":"2770",
    "addr:street":"Mcfarlane Drv",
    "iso:country":"AU",
    "sg:address":"158 McFarlane Drv",
    "sg:city":"Minchinbury",
    "sg:classifiers":[
        {
            "category":"Professional",
            "subcategory":"Accounting & Tax Preparation",
            "type":"Services"
        }
    ],
    "sg:phone":"+61 422 347 719",
    "sg:postcode":"2770",
    "sg:province":"NSW",
    "sg:tags":[
        "consultant",
        "taxation"
    ],
    "wof:name":"Excel Accounting",
    "wof:placetype":"venue"
},
  "geometry": {"coordinates":[150.83197021500001,-33.787361145],"type":"Point"}
}