{
  "type": "Feature",
  "properties": {
    "iso:country":"AU",
    "sg:address":"4/ 4 Shelley Crt",
    "sg:city":"Kilsyth",
    "sg:classifiers":[
        {
            "category":"Manufacturing",
            "subcategory":"Metals",
            "type":"Manufacturing & Wholesale Goods"
        }
    ],
    "sg:phone":"+61 405 613 521",
    "sg:postcode":"3137",
    "sg:province":"VIC",
    "sg:tags":[
        "steel",
        "fabricator",
        "mfrs"
    ],
    "wof:name":"Last Stand Fabrications",
    "wof:placetype":"venue"
},
  "geometry": {"coordinates":[145.303955078,-37.8038673401],"type":"Point"}
}