{
  "type": "Feature",
  "properties": {
    "iso:country":"AU",
    "sg:address":"21 Brennan Rd",
    "sg:city":"Scarborough",
    "sg:classifiers":[
        {
            "category":"Building & Trades",
            "subcategory":"Construction",
            "type":"Services"
        }
    ],
    "sg:phone":"+61 7 3203 5075",
    "sg:postcode":"4020",
    "sg:province":"QLD",
    "sg:tags":[
        "contractor"
    ],
    "wof:name":"Turnbull Constructions Pty Ltd",
    "wof:placetype":"venue"
},
  "geometry": {"coordinates":[153.10411099999999,-27.201387],"type":"Point"}
}