{
  "type": "Feature",
  "properties": {
    "addr:full":"7 Rodney Rd North Geelong VIC 3215",
    "addr:housenumber":"7",
    "addr:postcode":"3215",
    "addr:street":"Rodney Rd",
    "iso:country":"AU",
    "sg:address":"7 Rodney Rd",
    "sg:city":"North Geelong",
    "sg:classifiers":[
        {
            "category":"Home & Garden",
            "subcategory":"Building Materials",
            "type":"Retail Goods"
        }
    ],
    "sg:phone":"+61 3 5277 9933",
    "sg:postcode":"3215",
    "sg:province":"VIC",
    "sg:tags":[
        "fitting",
        "door"
    ],
    "wof:name":"Doors Leadlight & More",
    "wof:placetype":"venue"
},
  "geometry": {"coordinates":[144.346603394,-38.0988197327],"type":"Point"}
}