{
  "type": "Feature",
  "properties": {
    "addr:full":"1 / 1 Holder Way Malaga WA 6090",
    "addr:housenumber":"/ 1",
    "addr:postcode":"6090",
    "addr:street":"Holder Way",
    "iso:country":"AU",
    "sg:address":"1 / 1 Holder Way",
    "sg:city":"Malaga",
    "sg:classifiers":[
        {
            "category":"Building & Trades",
            "subcategory":"Construction",
            "type":"Services"
        }
    ],
    "sg:phone":"+61 1300 661 771",
    "sg:postcode":"6090",
    "sg:province":"WA",
    "sg:tags":[
        "home",
        "air conditioning"
    ],
    "wof:name":"Mr Split Airconditioning",
    "wof:placetype":"venue"
},
  "geometry": {"coordinates":[115.89114379900001,-31.8564338684],"type":"Point"}
}