{
  "type": "Feature",
  "properties": {
    "addr:full":"2 Fairview Rd Crafers SA 5152",
    "addr:housenumber":"2",
    "addr:postcode":"5152",
    "addr:street":"Fairview Rd",
    "iso:country":"AU",
    "sg:address":"2 Fairview Rd",
    "sg:city":"Crafers",
    "sg:classifiers":[
        {
            "category":"Social Services",
            "type":"Services"
        }
    ],
    "sg:phone":"+61 8 8370 9015",
    "sg:postcode":"5152",
    "sg:province":"SA",
    "sg:tags":[
        "disabled",
        "person",
        "equipment"
    ],
    "wof:name":"Anelco Mobility",
    "wof:placetype":"venue"
},
  "geometry": {"coordinates":[138.708892822,-34.995929718],"type":"Point"}
}