{
  "type": "Feature",
  "properties": {
    "addr:full":"Unit 3/ 210 Amelia St Balcatta WA 6021",
    "addr:housenumber":"/ 210",
    "addr:postcode":"6021",
    "addr:street":"Amelia St",
    "iso:country":"AU",
    "sg:address":"Unit 3/ 210 Amelia St",
    "sg:city":"Balcatta",
    "sg:classifiers":[
        {
            "category":"Health Services",
            "subcategory":"Chiropractor",
            "type":"Services"
        }
    ],
    "sg:phone":"+61 8 9344 6400",
    "sg:postcode":"6021",
    "sg:province":"WA",
    "wof:name":"Balcatta Chiropractic",
    "wof:placetype":"venue"
},
  "geometry": {"coordinates":[115.830116272,-31.87383461],"type":"Point"}
}