{
  "type": "Feature",
  "properties": {
    "iso:country":"AU",
    "sg:address":"Derry Ave",
    "sg:city":"Mt Nasura",
    "sg:classifiers":[
        {
            "category":"Building & Trades",
            "subcategory":"Plumbing",
            "type":"Services"
        }
    ],
    "sg:phone":"+61 8 9497 1703",
    "sg:postcode":"6112",
    "sg:province":"WA",
    "sg:tags":[
        "plumber",
        "gasfitters"
    ],
    "wof:name":"Armadale Gas Services",
    "wof:placetype":"venue"
},
  "geometry": {"coordinates":[116.018928528,-32.1375617981],"type":"Point"}
}