{
  "type": "Feature",
  "properties": {
    "addr:full":"17 Bonaparte Pl Rowville VIC 3178",
    "addr:housenumber":"17",
    "addr:postcode":"3178",
    "addr:street":"Bonaparte Pl",
    "iso:country":"AU",
    "sg:address":"17 Bonaparte Pl",
    "sg:city":"Rowville",
    "sg:classifiers":[
        {
            "category":"Building & Trades",
            "subcategory":"Construction",
            "type":"Services"
        }
    ],
    "sg:phone":"+61 409 326 803",
    "sg:postcode":"3178",
    "sg:province":"VIC",
    "sg:tags":[
        "concrete",
        "contractor"
    ],
    "wof:name":"Lakesfield Paving",
    "wof:placetype":"venue"
},
  "geometry": {"coordinates":[145.27406310999999,-37.9062652588],"type":"Point"}
}