{
  "type": "Feature",
  "properties": {
    "iso:country":"AU",
    "sg:address":"219 Newton Rd",
    "sg:city":"Wetherill Park",
    "sg:classifiers":[
        {
            "category":"Transit Center",
            "subcategory":"Freight",
            "type":"Transportation"
        }
    ],
    "sg:phone":"+61 2 8788 1777",
    "sg:postcode":"2164",
    "sg:province":"NSW",
    "sg:tags":[
        "forklift",
        "truck"
    ],
    "sg:website":"http://www.adapt-a-lift.com.au",
    "wof:name":"Adapt-A-Lift Forklift Rentals & Sales",
    "wof:placetype":"venue"
},
  "geometry": {"coordinates":[150.89213562,-33.8390312195],"type":"Point"}
}