{
  "type": "Feature",
  "properties": {
    "addr:full":"PO Box 1550 Mt Gambier SA 5290",
    "addr:postcode":"5290",
    "iso:country":"AU",
    "sg:address":"PO Box 1550",
    "sg:city":"Mt Gambier",
    "sg:classifiers":[
        {
            "category":"Professional",
            "subcategory":"Art Services",
            "type":"Services"
        }
    ],
    "sg:phone":"+61 419 858 829",
    "sg:postcode":"5290",
    "sg:province":"SA",
    "sg:tags":[
        "interior",
        "decorator"
    ],
    "wof:name":"Kanmantoo Painters & Decorators",
    "wof:placetype":"venue"
},
  "geometry": {"coordinates":[140.78329500000001,-37.826321],"type":"Point"}
}