{
  "type": "Feature",
  "properties": {
    "iso:country":"AU",
    "sg:address":"46a Alexander Ave",
    "sg:city":"Taren Point",
    "sg:classifiers":[
        {
            "category":"Autos & Motor Vehicles",
            "subcategory":"Boat Sales",
            "type":"Retail Goods"
        }
    ],
    "sg:phone":"+61 2 9525 7904",
    "sg:postcode":"2229",
    "sg:province":"NSW",
    "sg:tags":[
        "builder",
        "yacht",
        "repairer"
    ],
    "wof:name":"G.K.M. Fibreglassing",
    "wof:placetype":"venue"
},
  "geometry": {"coordinates":[151.12411499000001,-34.0212554932],"type":"Point"}
}