{
  "type": "Feature",
  "properties": {
    "iso:country":"AU",
    "sg:address":"45 Cathedral Ave",
    "sg:city":"Geraldton",
    "sg:classifiers":[
        {
            "category":"Insurance",
            "subcategory":"Hazard Insurance",
            "type":"Services"
        }
    ],
    "sg:phone":"+61 13 32 33",
    "sg:postcode":"6530",
    "sg:province":"WA",
    "sg:tags":[
        "fire",
        "accident",
        "marine"
    ],
    "wof:name":"SGIO",
    "wof:placetype":"venue"
},
  "geometry": {"coordinates":[114.610092163,-28.7750778198],"type":"Point"}
}