{
  "type": "Feature",
  "properties": {
    "addr:full":"221- 229 Sydney Park Rd Erskineville NSW 2043",
    "addr:housenumber":"221 229",
    "addr:postcode":"2043",
    "addr:street":"Sydney Park Rd",
    "iso:country":"AU",
    "sg:address":"221- 229 Sydney Park Rd",
    "sg:city":"Erskineville",
    "sg:classifiers":[
        {
            "category":"Home & Garden",
            "subcategory":"Carpets & Floor Coverings",
            "type":"Retail Goods"
        }
    ],
    "sg:phone":"+61 2 9565 1811",
    "sg:postcode":"2043",
    "sg:province":"NSW",
    "sg:tags":[
        "wholesaler",
        "tie",
        "mfrs",
        "scarf"
    ],
    "wof:name":"Sydney Neckwear Co Pty Ltd",
    "wof:placetype":"venue"
},
  "geometry": {"coordinates":[151.183594,-33.906925],"type":"Point"}
}