{
  "type": "Feature",
  "properties": {
    "addr:full":"33 Powell St Wulguru QLD 4811",
    "addr:housenumber":"33",
    "addr:postcode":"4811",
    "addr:street":"Powell St",
    "iso:country":"AU",
    "sg:address":"33 Powell St",
    "sg:city":"Wulguru",
    "sg:classifiers":[
        {
            "category":"Professional",
            "subcategory":"Accounting & Tax Preparation",
            "type":"Services"
        }
    ],
    "sg:phone":"+61 7 4778 3244",
    "sg:postcode":"4811",
    "sg:province":"QLD",
    "sg:tags":[
        "accountant",
        "auditor"
    ],
    "wof:name":"Gray Margaret",
    "wof:placetype":"venue"
},
  "geometry": {"coordinates":[146.819321,-19.329168],"type":"Point"}
}