{
  "type": "Feature",
  "properties": {
    "addr:full":"Rear 53 Church St Mudgee NSW 2850",
    "addr:housenumber":"53",
    "addr:postcode":"2850",
    "addr:street":"Church St",
    "iso:country":"AU",
    "sg:address":"Rear 53 Church St",
    "sg:city":"Mudgee",
    "sg:classifiers":[
        {
            "category":"Building & Trades",
            "subcategory":"Construction",
            "type":"Services"
        }
    ],
    "sg:phone":"+61 2 6372 3440",
    "sg:postcode":"2850",
    "sg:province":"NSW",
    "sg:tags":[
        "monumental",
        "mason"
    ],
    "wof:name":"Macquarie Valley Monuments",
    "wof:placetype":"venue"
},
  "geometry": {"coordinates":[149.585342,-32.60659],"type":"Point"}
}