{
  "type": "Feature",
  "properties": {
    "addr:full":"PO Box 47 Castlemaine VIC 3450",
    "addr:postcode":"3450",
    "iso:country":"AU",
    "sg:address":"PO Box 47",
    "sg:city":"Castlemaine",
    "sg:classifiers":[
        {
            "category":"Building & Trades",
            "subcategory":"Plumbing",
            "type":"Services"
        }
    ],
    "sg:phone":"+61 407 723 634",
    "sg:postcode":"3450",
    "sg:province":"VIC",
    "sg:tags":[
        "plumber",
        "gasfitters"
    ],
    "wof:name":"David Ross",
    "wof:placetype":"venue"
},
  "geometry": {"coordinates":[144.216552734,-37.0669288635],"type":"Point"}
}