{
  "type": "Feature",
  "properties": {
    "iso:country":"AU",
    "sg:address":"Shop 43",
    "sg:city":"-44 Sorrento Quay Broadwalk Hillarys Boat Har",
    "sg:classifiers":[
        {
            "category":"Fast Food",
            "type":"Food & Drink"
        }
    ],
    "sg:phone":"+61 8 9203 6299",
    "sg:postcode":"6025",
    "sg:province":"WA",
    "sg:tags":[
        "away",
        "take"
    ],
    "wof:name":"Wokinabox",
    "wof:placetype":"venue"
},
  "geometry": {"coordinates":[115.744338989,-31.8261623383],"type":"Point"}
}