{
  "type": "Feature",
  "properties": {
    "addr:full":"U12/ 108 Welshpool Rd Welshpool WA 6106",
    "addr:postcode":"6106",
    "addr:street":"/ 108 Welshpool Rd",
    "iso:country":"AU",
    "sg:address":"U12/ 108 Welshpool Rd",
    "sg:city":"Welshpool",
    "sg:classifiers":[
        {
            "category":"Autos & Motor Vehicles",
            "subcategory":"Auto Supplies",
            "type":"Retail Goods"
        }
    ],
    "sg:phone":"+61 8 9358 4969",
    "sg:postcode":"6106",
    "sg:province":"WA",
    "sg:tags":[
        "accessory"
    ],
    "wof:name":"Jshop",
    "wof:placetype":"venue"
},
  "geometry": {"coordinates":[115.927978516,-31.994020462],"type":"Point"}
}