{
  "type": "Feature",
  "properties": {
    "iso:country":"AU",
    "sg:address":"Lot6/ Atkins St",
    "sg:city":"Bendigo North",
    "sg:classifiers":[
        {
            "category":"Arena",
            "subcategory":"Sports Club",
            "type":"Entertainment"
        }
    ],
    "sg:phone":"+61 3 5441 4494",
    "sg:postcode":"3550",
    "sg:province":"VIC",
    "sg:tags":[
        "australian",
        "football",
        "rule"
    ],
    "wof:name":"North Bendigo Football Club",
    "wof:placetype":"venue"
},
  "geometry": {"coordinates":[144.273895264,-36.7475509644],"type":"Point"}
}