{
  "type": "Feature",
  "properties": {
    "addr:full":"24 Earle St Windsor QLD 4030",
    "addr:housenumber":"24",
    "addr:postcode":"4030",
    "addr:street":"Earle St",
    "iso:country":"AU",
    "sg:address":"24 Earle St",
    "sg:city":"Windsor",
    "sg:classifiers":[
        {
            "category":"Banks & Credit Unions",
            "subcategory":"Investment Brokerage",
            "type":"Services"
        }
    ],
    "sg:phone":"+61 7 3357 6266",
    "sg:postcode":"4030",
    "sg:province":"QLD",
    "sg:tags":[
        "radiator",
        "motor"
    ],
    "wof:name":"Smaus Radiator House",
    "wof:placetype":"venue"
},
  "geometry": {"coordinates":[153.03121899999999,-27.442215],"type":"Point"}
}