{
  "type": "Feature",
  "properties": {
    "iso:country":"AU",
    "sg:address":"Unit 5/ 5 Pavilion Pl",
    "sg:city":"Cardiff",
    "sg:classifiers":[
        {
            "category":"Manufacturing",
            "subcategory":"Building Materials",
            "type":"Manufacturing & Wholesale Goods"
        }
    ],
    "sg:phone":"+61 2 4979 1500",
    "sg:postcode":"2285",
    "sg:province":"NSW",
    "sg:tags":[
        "equipment",
        "handling"
    ],
    "wof:name":"Demag Cranes & Components Pty Ltd",
    "wof:placetype":"venue"
},
  "geometry": {"coordinates":[151.64474487300001,-32.9401664734],"type":"Point"}
}