{
  "type": "Feature",
  "properties": {
    "addr:full":"32 Randolph St Rocklea QLD 4106",
    "addr:housenumber":"32",
    "addr:postcode":"4106",
    "addr:street":"Randolph St",
    "iso:country":"AU",
    "sg:address":"32 Randolph St",
    "sg:city":"Rocklea",
    "sg:classifiers":[
        {
            "category":"Professional",
            "type":"Services"
        }
    ],
    "sg:phone":"+61 7 3277 4999",
    "sg:postcode":"4106",
    "sg:province":"QLD",
    "sg:tags":[
        "transport"
    ],
    "wof:name":"McClintock's Transport",
    "wof:placetype":"venue"
},
  "geometry": {"coordinates":[152.99919128400001,-27.5626945496],"type":"Point"}
}