{
  "type": "Feature",
  "properties": {
    "addr:full":"7/ 8 Baretta Rd Wangara WA 6065",
    "addr:housenumber":"/ 8",
    "addr:postcode":"6065",
    "addr:street":"Baretta Rd",
    "iso:country":"AU",
    "sg:address":"7/ 8 Baretta Rd",
    "sg:city":"Wangara",
    "sg:classifiers":[
        {
            "category":"Professional",
            "subcategory":"Engineering",
            "type":"Services"
        }
    ],
    "sg:phone":"+61 8 9408 1622",
    "sg:postcode":"6065",
    "sg:province":"WA",
    "sg:tags":[
        "refrigeration",
        "engineer"
    ],
    "wof:name":"Air Torque Refrigeration & Air Conditioning",
    "wof:placetype":"venue"
},
  "geometry": {"coordinates":[115.81764984100001,-31.7922401428],"type":"Point"}
}