{
  "type": "Feature",
  "properties": {
    "addr:full":"119 Toolooa St Gladstone QLD 4680",
    "addr:housenumber":"119",
    "addr:postcode":"4680",
    "addr:street":"Toolooa St",
    "iso:country":"AU",
    "sg:address":"119 Toolooa St",
    "sg:city":"Gladstone",
    "sg:classifiers":[
        {
            "category":"Health Services",
            "subcategory":"Doctor",
            "type":"Services"
        }
    ],
    "sg:phone":"+61 7 4972 9688",
    "sg:postcode":"4680",
    "sg:province":"QLD",
    "sg:tags":[
        "medical",
        "practitioner"
    ],
    "wof:name":"Toolooa Family Practice",
    "wof:placetype":"venue"
},
  "geometry": {"coordinates":[151.26942443900001,-23.8570823669],"type":"Point"}
}