{
  "type": "Feature",
  "properties": {
    "iso:country":"AU",
    "sg:address":"42- 48 John St",
    "sg:city":"Leichhardt",
    "sg:classifiers":[
        {
            "category":"Professional",
            "type":"Services"
        }
    ],
    "sg:phone":"+61 2 9552 1899",
    "sg:postcode":"2040",
    "sg:province":"NSW",
    "sg:tags":[
        "valuer"
    ],
    "wof:name":"Raffan Kelaher & Thomas Pty Ltd",
    "wof:placetype":"venue"
},
  "geometry": {"coordinates":[151.16568,-33.881142],"type":"Point"}
}