{
  "type": "Feature",
  "properties": {
    "iso:country":"AU",
    "sg:address":"Orange Rd",
    "sg:city":"Ourimbah",
    "sg:classifiers":[
        {
            "category":"Real Estate",
            "subcategory":"Real Estate Agent",
            "type":"Services"
        }
    ],
    "sg:phone":"+61 2 4362 2533",
    "sg:postcode":"2258",
    "sg:province":"NSW",
    "wof:name":"Homeseekers Real Estate Pty Ltd",
    "wof:placetype":"venue"
},
  "geometry": {"coordinates":[151.39039611800001,-33.3502883911],"type":"Point"}
}