{
  "type": "Feature",
  "properties": {
    "iso:country":"AU",
    "sg:address":"Shop 2 36 Simpson St",
    "sg:city":"Beerwah",
    "sg:classifiers":[
        {
            "category":"Shopping",
            "subcategory":"Clothing, Apparel, & Fashions",
            "type":"Retail Goods"
        }
    ],
    "sg:phone":"+61 7 5494 0532",
    "sg:postcode":"4519",
    "sg:province":"QLD",
    "sg:tags":[
        "lady",
        "wear"
    ],
    "wof:name":"Chic Effects",
    "wof:placetype":"venue"
},
  "geometry": {"coordinates":[152.957764,-26.858517],"type":"Point"}
}