{
  "type": "Feature",
  "properties": {
    "iso:country":"AU",
    "sg:address":"170 White Rd",
    "sg:city":"Wonthaggi",
    "sg:classifiers":[
        {
            "category":"Shopping",
            "subcategory":"Stationery & Office Supplies",
            "type":"Retail Goods"
        }
    ],
    "sg:phone":"+61 418 595 463",
    "sg:postcode":"3995",
    "sg:province":"VIC",
    "sg:tags":[
        "equipment",
        "dairy"
    ],
    "wof:name":"Phillips R A",
    "wof:placetype":"venue"
},
  "geometry": {"coordinates":[145.590927,-38.593391],"type":"Point"}
}