{
  "type": "Feature",
  "properties": {
    "addr:full":"37 Paradise Ave Miami QLD 4220",
    "addr:housenumber":"37",
    "addr:postcode":"4220",
    "addr:street":"Paradise Ave",
    "iso:country":"AU",
    "sg:address":"37 Paradise Ave",
    "sg:city":"Miami",
    "sg:classifiers":[
        {
            "category":"Retail",
            "subcategory":"Repair Shop",
            "type":"Services"
        }
    ],
    "sg:phone":"+61 7 5572 1337",
    "sg:postcode":"4220",
    "sg:province":"QLD",
    "sg:tags":[
        "upholsterer"
    ],
    "wof:name":"Sew Biz",
    "wof:placetype":"venue"
},
  "geometry": {"coordinates":[153.43551635700001,-28.0648670197],"type":"Point"}
}