{
  "type": "Feature",
  "properties": {
    "addr:full":"6 Kuna Ave Inverell NSW 2360",
    "addr:housenumber":"6",
    "addr:postcode":"2360",
    "addr:street":"Kuna Ave",
    "iso:country":"AU",
    "sg:address":"6 Kuna Ave",
    "sg:city":"Inverell",
    "sg:classifiers":[
        {
            "category":"Communications",
            "type":"Services"
        }
    ],
    "sg:phone":"+61 2 6721 0010",
    "sg:postcode":"2360",
    "sg:province":"NSW",
    "sg:tags":[
        "equipment",
        "satellite"
    ],
    "wof:name":"Lyn Willing Electronics",
    "wof:placetype":"venue"
},
  "geometry": {"coordinates":[151.11578369099999,-29.7668857574],"type":"Point"}
}