{
  "type": "Feature",
  "properties": {
    "addr:full":"149 Lonsdale St Melbourne VIC 3000",
    "addr:housenumber":"149",
    "addr:postcode":"3000",
    "addr:street":"Lonsdale St",
    "iso:country":"AU",
    "sg:address":"149 Lonsdale St",
    "sg:city":"Melbourne",
    "sg:classifiers":[
        {
            "category":"Restaurant",
            "type":"Food & Drink"
        }
    ],
    "sg:phone":"+61 3 9639 0888",
    "sg:postcode":"3000",
    "sg:province":"VIC",
    "wof:name":"Dragon Boat Restaurants",
    "wof:placetype":"venue"
},
  "geometry": {"coordinates":[144.967926025,-37.810760498],"type":"Point"}
}