{
  "type": "Feature",
  "properties": {
    "iso:country":"AU",
    "sg:address":"26 Merriman St",
    "sg:city":"Kyle Bay",
    "sg:classifiers":[
        {
            "category":"Professional",
            "subcategory":"Engineering",
            "type":"Services"
        }
    ],
    "sg:phone":"+61 412 414 678",
    "sg:postcode":"2221",
    "sg:province":"NSW",
    "sg:tags":[
        "consulting",
        "engineer"
    ],
    "wof:name":"CompDes Civil & Structural",
    "wof:placetype":"venue"
},
  "geometry": {"coordinates":[151.10429382300001,-33.9884986877],"type":"Point"}
}