{
  "type": "Feature",
  "properties": {
    "addr:full":"\"Burwood\" Clifton Rd Pittsworth QLD 4356",
    "addr:postcode":"4356",
    "addr:street":"Clifton Rd",
    "iso:country":"AU",
    "sg:address":"\"Burwood\" Clifton Rd",
    "sg:city":"Pittsworth",
    "sg:classifiers":[
        {
            "category":"Farming",
            "subcategory":"Farm",
            "type":"Manufacturing & Wholesale Goods"
        }
    ],
    "sg:phone":"+61 7 4693 1309",
    "sg:postcode":"4356",
    "sg:province":"QLD",
    "sg:tags":[
        "farmer"
    ],
    "wof:name":"Denning N T & C E",
    "wof:placetype":"venue"
},
  "geometry": {"coordinates":[151.627396,-27.718729],"type":"Point"}
}