{
  "type": "Feature",
  "properties": {
    "iso:country":"AU",
    "sg:address":"14/ 93 Chewings St",
    "sg:city":"Scullin",
    "sg:classifiers":[
        {
            "category":"Health Services",
            "subcategory":"Health Practitioner",
            "type":"Services"
        }
    ],
    "sg:phone":"+61 2 6254 3096",
    "sg:postcode":"2614",
    "sg:province":"ACT",
    "sg:tags":[
        "psychologist"
    ],
    "wof:name":"Baker Helen",
    "wof:placetype":"venue"
},
  "geometry": {"coordinates":[149.04783630399999,-35.2325210571],"type":"Point"}
}