{
  "type": "Feature",
  "properties": {
    "addr:full":"PO Box 373 Orbost VIC 3888",
    "addr:postcode":"3888",
    "iso:country":"AU",
    "sg:address":"PO Box 373",
    "sg:city":"Orbost",
    "sg:classifiers":[
        {
            "category":"Building & Trades",
            "subcategory":"Landscaping Services",
            "type":"Services"
        }
    ],
    "sg:phone":"+61 427 557 236",
    "sg:postcode":"3888",
    "sg:province":"VIC",
    "sg:tags":[
        "stump",
        "tree",
        "felling",
        "removal"
    ],
    "wof:name":"Re Arbor Tree Services",
    "wof:placetype":"venue"
},
  "geometry": {"coordinates":[148.46343994099999,-37.7093696594],"type":"Point"}
}