{
  "type": "Feature",
  "properties": {
    "iso:country":"AU",
    "sg:address":"120 James St",
    "sg:city":"Templestowe",
    "sg:classifiers":[
        {
            "category":"Manufacturing",
            "subcategory":"Electronics",
            "type":"Manufacturing & Wholesale Goods"
        }
    ],
    "sg:phone":"+61 3 9846 2466",
    "sg:postcode":"3106",
    "sg:province":"VIC",
    "sg:tags":[
        "oven",
        "microwave"
    ],
    "wof:name":"Diamond Valley TV & Video Repairs",
    "wof:placetype":"venue"
},
  "geometry": {"coordinates":[145.12901306099999,-37.7569580078],"type":"Point"}
}