{
  "type": "Feature",
  "properties": {
    "addr:full":"Shop 50 Mountain Gate Shopng Cntr Ferntree Gully VIC 3156",
    "addr:housenumber":"shop 50",
    "addr:postcode":"3156",
    "addr:street":"Mountain Gate Shopng",
    "iso:country":"AU",
    "sg:address":"Shop 50",
    "sg:city":"Mountain Gate Shopng Cntr Ferntree Gully",
    "sg:classifiers":[
        {
            "category":"Shopping",
            "subcategory":"Party Supplies",
            "type":"Retail Goods"
        }
    ],
    "sg:phone":"+61 3 9758 5505",
    "sg:postcode":"3156",
    "sg:province":"VIC",
    "wof:name":"Balloonsparty.com",
    "wof:placetype":"venue"
},
  "geometry": {"coordinates":[145.274291992,-37.8894615173],"type":"Point"}
}