{
  "type": "Feature",
  "properties": {
    "addr:full":"260 Nicholson St Fitzroy VIC 3065",
    "addr:housenumber":"260",
    "addr:postcode":"3065",
    "addr:street":"Nicholson St",
    "iso:country":"AU",
    "sg:address":"260 Nicholson St",
    "sg:city":"Fitzroy",
    "sg:classifiers":[
        {
            "category":"Shopping",
            "type":"Retail Goods"
        }
    ],
    "sg:phone":"+61 3 9486 0390",
    "sg:postcode":"3065",
    "sg:province":"VIC",
    "sg:tags":[
        "clearance",
        "factory",
        "outlet"
    ],
    "wof:name":"Fila Factory Outlet",
    "wof:placetype":"venue"
},
  "geometry": {"coordinates":[144.97520446799999,-37.7972984314],"type":"Point"}
}