{
  "type": "Feature",
  "properties": {
    "addr:full":"105 Capes Rd Lakes Entrance VIC 3909",
    "addr:housenumber":"105",
    "addr:postcode":"3909",
    "addr:street":"Capes Rd Lakes",
    "iso:country":"AU",
    "sg:address":"105 Capes Rd",
    "sg:city":"Lakes Entrance",
    "sg:classifiers":[
        {
            "category":"Home & Garden",
            "subcategory":"Building Materials",
            "type":"Retail Goods"
        }
    ],
    "sg:phone":"+61 3 5155 3604",
    "sg:postcode":"3909",
    "sg:province":"VIC",
    "sg:tags":[
        "lawn",
        "cutting",
        "maintenance"
    ],
    "wof:name":"Cams Cuts",
    "wof:placetype":"venue"
},
  "geometry": {"coordinates":[147.982147217,-37.8640937805],"type":"Point"}
}