{
  "type": "Feature",
  "properties": {
    "iso:country":"AU",
    "sg:address":"142 Wilson St",
    "sg:city":"Cheltenham",
    "sg:classifiers":[
        {
            "category":"Professional",
            "subcategory":"Detective & Security Services",
            "type":"Services"
        }
    ],
    "sg:phone":"+61 3 9502 3529",
    "sg:postcode":"3192",
    "sg:province":"VIC",
    "sg:tags":[
        "consultant",
        "laser"
    ],
    "wof:name":"Genius Laser Technology",
    "wof:placetype":"venue"
},
  "geometry": {"coordinates":[145.06124877900001,-37.9534492493],"type":"Point"}
}