{
  "type": "Feature",
  "properties": {
    "addr:full":"11 Montreal Rd Woodbridge WA 6056",
    "addr:housenumber":"11",
    "addr:postcode":"6056",
    "addr:street":"Montreal Rd",
    "iso:country":"AU",
    "sg:address":"11 Montreal Rd",
    "sg:city":"Woodbridge",
    "sg:classifiers":[
        {
            "category":"Shopping",
            "subcategory":"Stationery & Office Supplies",
            "type":"Retail Goods"
        }
    ],
    "sg:phone":"+61 8 9274 5170",
    "sg:postcode":"6056",
    "sg:province":"WA",
    "sg:tags":[
        "partition"
    ],
    "wof:name":"Sound Partitions",
    "wof:placetype":"venue"
},
  "geometry": {"coordinates":[115.994407654,-31.8939552307],"type":"Point"}
}