{
  "type": "Feature",
  "properties": {
    "iso:country":"AU",
    "sg:address":"Unit 3/ 25 Granite St",
    "sg:city":"Geebung",
    "sg:classifiers":[
        {
            "category":"Professional",
            "subcategory":"Detective & Security Services",
            "type":"Services"
        }
    ],
    "sg:phone":"+61 1800 333 590",
    "sg:postcode":"4034",
    "sg:province":"QLD",
    "sg:tags":[
        "equipment",
        "window",
        "doors"
    ],
    "wof:name":"Screen Alert Australia",
    "wof:placetype":"venue"
},
  "geometry": {"coordinates":[153.049835,-27.364883],"type":"Point"}
}