{
  "type": "Feature",
  "properties": {
    "addr:full":"4/ 85 Bardia Ave Seaford VIC 3198",
    "addr:housenumber":"/ 85",
    "addr:postcode":"3198",
    "addr:street":"Bardia Ave",
    "iso:country":"AU",
    "sg:address":"4/ 85 Bardia Ave",
    "sg:city":"Seaford",
    "sg:classifiers":[
        {
            "category":"Building & Trades",
            "subcategory":"Construction",
            "type":"Services"
        }
    ],
    "sg:phone":"+61 3 9786 6600",
    "sg:postcode":"3198",
    "sg:province":"VIC",
    "sg:tags":[
        "industrial",
        "commercial",
        "air conditioning"
    ],
    "wof:name":"Aircon Service Management VIC",
    "wof:placetype":"venue"
},
  "geometry": {"coordinates":[145.13534545900001,-38.11901474],"type":"Point"}
}