{
  "type": "Feature",
  "properties": {
    "iso:country":"AU",
    "sg:address":"U2/ 12a Moorefield Park Rd",
    "sg:city":"Wodonga West",
    "sg:classifiers":[
        {
            "category":"Fast Food",
            "type":"Food & Drink"
        }
    ],
    "sg:phone":"+61 2 6056 2556",
    "sg:postcode":"3690",
    "sg:province":"VIC",
    "sg:tags":[
        "away",
        "take"
    ],
    "wof:name":"Rumbles Sandwich Bar",
    "wof:placetype":"venue"
},
  "geometry": {"coordinates":[146.85971069300001,-36.1134643555],"type":"Point"}
}