{
  "type": "Feature",
  "properties": {
    "addr:full":"Hutton Rd The Entrance North NSW 2261",
    "addr:postcode":"2261",
    "addr:street":"Hutton Rd",
    "iso:country":"AU",
    "sg:address":"Hutton Rd",
    "sg:city":"The Entrance North",
    "sg:classifiers":[
        {
            "category":"Education",
            "subcategory":"School",
            "type":"Public Place"
        }
    ],
    "sg:phone":"+61 2 4334 3600",
    "sg:postcode":"2261",
    "sg:province":"NSW",
    "sg:tags":[
        "state",
        "-",
        "nsw"
    ],
    "wof:name":"The Entrance North",
    "wof:placetype":"venue"
},
  "geometry": {"coordinates":[151.50520299999999,-33.329369],"type":"Point"}
}