{
  "type": "Feature",
  "properties": {
    "addr:full":"95- 97 Sheridan St Gundagai NSW 2722",
    "addr:housenumber":"97",
    "addr:postcode":"2722",
    "addr:street":"Sheridan St",
    "iso:country":"AU",
    "sg:address":"95- 97 Sheridan St",
    "sg:city":"Gundagai",
    "sg:classifiers":[
        {
            "category":"Professional",
            "subcategory":"Accounting & Tax Preparation",
            "type":"Services"
        }
    ],
    "sg:phone":"+61 1800 188 088",
    "sg:postcode":"2722",
    "sg:province":"NSW",
    "sg:tags":[
        "accountant",
        "auditor"
    ],
    "wof:name":"Quality Practice Accreditation Pty Ltd",
    "wof:placetype":"venue"
},
  "geometry": {"coordinates":[148.100067,-35.062332],"type":"Point"}
}