{
  "type": "Feature",
  "properties": {
    "iso:country":"AU",
    "sg:address":"136 Victoria Rd",
    "sg:city":"Marrickville",
    "sg:classifiers":[
        {
            "category":"Autos & Motor Vehicles",
            "subcategory":"Auto Supplies",
            "type":"Retail Goods"
        }
    ],
    "sg:phone":"+61 2 9724 9499",
    "sg:postcode":"2204",
    "sg:province":"NSW",
    "sg:tags":[
        "accessory"
    ],
    "wof:name":"Inland Australia Pty Ltd",
    "wof:placetype":"venue"
},
  "geometry": {"coordinates":[151.164825,-33.906685],"type":"Point"}
}