{
  "type": "Feature",
  "properties": {
    "addr:full":"48A Whittle Ave Milperra NSW 2214",
    "addr:housenumber":"48a",
    "addr:postcode":"2214",
    "addr:street":"Whittle Ave",
    "iso:country":"AU",
    "sg:address":"48A Whittle Ave",
    "sg:city":"Milperra",
    "sg:classifiers":[
        {
            "category":"Professional",
            "subcategory":"Employment Agencies",
            "type":"Services"
        }
    ],
    "sg:phone":"+61 418 113 931",
    "sg:postcode":"2214",
    "sg:province":"NSW",
    "sg:tags":[
        "hire",
        "labour",
        "contractor"
    ],
    "wof:name":"D & R Contractors NSW Pty Ltd",
    "wof:placetype":"venue"
},
  "geometry": {"coordinates":[150.98127700000001,-33.935562],"type":"Point"}
}