{
  "type": "Feature",
  "properties": {
    "iso:country":"AU",
    "sg:address":"3 Jones Crt",
    "sg:city":"Laverton",
    "sg:classifiers":[
        {
            "category":"Personal",
            "subcategory":"Beauty Salon",
            "type":"Services"
        }
    ],
    "sg:phone":"+61 3 9360 9797",
    "sg:postcode":"3028",
    "sg:province":"VIC",
    "sg:tags":[
        "supply",
        "artist",
        "make-up"
    ],
    "wof:name":"Juliet Bradford",
    "wof:placetype":"venue"
},
  "geometry": {"coordinates":[144.775787,-37.851139],"type":"Point"}
}