{
  "type": "Feature",
  "properties": {
    "addr:full":"Main Rd Hagley TAS 7292",
    "addr:postcode":"7292",
    "addr:street":"Main Rd",
    "iso:country":"AU",
    "sg:address":"Main Rd",
    "sg:city":"Hagley",
    "sg:classifiers":[
        {
            "category":"Utilities",
            "subcategory":"Electric",
            "type":"Services"
        }
    ],
    "sg:phone":"+61 418 130 640",
    "sg:postcode":"7292",
    "sg:province":"TAS",
    "sg:tags":[
        "electrical",
        "contractor"
    ],
    "wof:name":"Freeman Richard",
    "wof:placetype":"venue"
},
  "geometry": {"coordinates":[147.05892944300001,-41.5096855164],"type":"Point"}
}