{
  "type": "Feature",
  "properties": {
    "addr:full":"55 Mundy St Bendigo VIC 3550",
    "addr:housenumber":"55",
    "addr:postcode":"3550",
    "addr:street":"Mundy St",
    "iso:country":"AU",
    "sg:address":"55 Mundy St",
    "sg:city":"Bendigo",
    "sg:classifiers":[
        {
            "category":"Health Services",
            "subcategory":"Dentist",
            "type":"Services"
        }
    ],
    "sg:phone":"+61 3 5443 4561",
    "sg:postcode":"3550",
    "sg:province":"VIC",
    "sg:tags":[
        "technician",
        "dental"
    ],
    "wof:name":"Hughes Anne",
    "wof:placetype":"venue"
},
  "geometry": {"coordinates":[144.28594970699999,-36.7599449158],"type":"Point"}
}