{
  "type": "Feature",
  "properties": {
    "iso:country":"AU",
    "sg:address":"18 Single St",
    "sg:city":"Werris Creek",
    "sg:classifiers":[
        {
            "category":"Retail",
            "subcategory":"Auto Repair",
            "type":"Services"
        }
    ],
    "sg:phone":"+61 2 6768 7108",
    "sg:postcode":"2341",
    "sg:province":"NSW",
    "sg:tags":[
        "beater",
        "painter",
        "panel"
    ],
    "wof:name":"Patterson's Car Repairs",
    "wof:placetype":"venue"
},
  "geometry": {"coordinates":[150.646972656,-31.3527584076],"type":"Point"}
}