{
  "type": "Feature",
  "properties": {
    "addr:full":"1 Demand Ave Arundel QLD 4214",
    "addr:housenumber":"1",
    "addr:postcode":"4214",
    "addr:street":"Demand Ave",
    "iso:country":"AU",
    "sg:address":"1 Demand Ave",
    "sg:city":"Arundel",
    "sg:classifiers":[
        {
            "category":"Professional",
            "type":"Services"
        }
    ],
    "sg:phone":"+61 7 5571 6970",
    "sg:postcode":"4214",
    "sg:province":"QLD",
    "sg:tags":[
        "shop",
        "fitting"
    ],
    "wof:name":"Advanced Polyurethane",
    "wof:placetype":"venue"
},
  "geometry": {"coordinates":[153.37359619099999,-27.9421386719],"type":"Point"}
}