{
  "type": "Feature",
  "properties": {
    "iso:country":"AU",
    "sg:address":"25 Clarendon St",
    "sg:city":"Hyde Park",
    "sg:classifiers":[
        {
            "category":"Professional",
            "subcategory":"Art Services",
            "type":"Services"
        }
    ],
    "sg:phone":"+61 7 4721 5112",
    "sg:postcode":"4812",
    "sg:province":"QLD",
    "sg:tags":[
        "interior",
        "designer"
    ],
    "wof:name":"Sally Logan Interiors",
    "wof:placetype":"venue"
},
  "geometry": {"coordinates":[146.79911799999999,-19.272945],"type":"Point"}
}