{
  "type": "Feature",
  "properties": {
    "addr:full":"137 George St Beenleigh QLD 4207",
    "addr:housenumber":"137",
    "addr:postcode":"4207",
    "addr:street":"George St",
    "iso:country":"AU",
    "sg:address":"137 George St",
    "sg:city":"Beenleigh",
    "sg:classifiers":[
        {
            "category":"Shopping",
            "subcategory":"Bicycles & Sporting Goods",
            "type":"Retail Goods"
        }
    ],
    "sg:phone":"+61 7 3382 7733",
    "sg:postcode":"4207",
    "sg:province":"QLD",
    "sg:tags":[
        "chemical",
        "equipment",
        "pool",
        "swimming"
    ],
    "wof:name":"Clark Pools & Spas",
    "wof:placetype":"venue"
},
  "geometry": {"coordinates":[153.204345703,-27.7162628174],"type":"Point"}
}