{
  "type": "Feature",
  "properties": {
    "addr:full":"1028 Albany Hwy East Victoria Park WA 6101",
    "addr:housenumber":"1028",
    "addr:postcode":"6101",
    "addr:street":"Albany Hwy",
    "iso:country":"AU",
    "sg:address":"1028 Albany Hwy",
    "sg:city":"East Victoria Park",
    "sg:classifiers":[
        {
            "category":"Autos & Motor Vehicles",
            "subcategory":"Auto Supplies",
            "type":"Retail Goods"
        }
    ],
    "sg:phone":"+61 8 9472 3030",
    "sg:postcode":"6101",
    "sg:province":"WA",
    "sg:tags":[
        "part",
        "cycles",
        "accessory"
    ],
    "wof:name":"Total Tyres",
    "wof:placetype":"venue"
},
  "geometry": {"coordinates":[115.91239166299999,-31.993347168],"type":"Point"}
}