{
  "type": "Feature",
  "properties": {
    "addr:full":"21 King St Sandy Bay TAS 7005",
    "addr:housenumber":"21",
    "addr:postcode":"7005",
    "addr:street":"King St",
    "iso:country":"AU",
    "sg:address":"21 King St",
    "sg:city":"Sandy Bay",
    "sg:classifiers":[
        {
            "category":"Real Estate",
            "subcategory":"Real Estate Agent",
            "type":"Services"
        }
    ],
    "sg:phone":"+61 413 518 888",
    "sg:postcode":"7005",
    "sg:province":"TAS",
    "wof:name":"Anthony (Will) Ballard",
    "wof:placetype":"venue"
},
  "geometry": {"coordinates":[147.330245972,-42.8953208923],"type":"Point"}
}