{
  "type": "Feature",
  "properties": {
    "addr:full":"8 Apollo Ave Slacks Creek QLD 4127",
    "addr:housenumber":"8",
    "addr:postcode":"4127",
    "addr:street":"Apollo Ave",
    "iso:country":"AU",
    "sg:address":"8 Apollo Ave",
    "sg:city":"Slacks Creek",
    "sg:classifiers":[
        {
            "category":"Wholesale",
            "subcategory":"Machinery & Supplies",
            "type":"Manufacturing & Wholesale Goods"
        }
    ],
    "sg:phone":"+61 7 3299 1739",
    "sg:postcode":"4127",
    "sg:province":"QLD",
    "sg:tags":[
        "agricultural"
    ],
    "wof:name":"Commodore Mobile Tractor services",
    "wof:placetype":"venue"
},
  "geometry": {"coordinates":[153.12290954599999,-27.6439189911],"type":"Point"}
}