{
  "type": "Feature",
  "properties": {
    "addr:full":"18 Florida St Sylvania NSW 2224",
    "addr:housenumber":"18",
    "addr:postcode":"2224",
    "addr:street":"Florida St",
    "iso:country":"AU",
    "sg:address":"18 Florida St",
    "sg:city":"Sylvania",
    "sg:classifiers":[
        {
            "category":"Building & Trades",
            "subcategory":"Pest Control",
            "type":"Services"
        }
    ],
    "sg:phone":"+61 2 9522 6060",
    "sg:postcode":"2224",
    "sg:province":"NSW",
    "wof:name":"Bills Pest Services",
    "wof:placetype":"venue"
},
  "geometry": {"coordinates":[151.107223511,-34.0085754395],"type":"Point"}
}