{
  "type": "Feature",
  "properties": {
    "iso:country":"AU",
    "sg:address":"445- 449 Ruthven St",
    "sg:city":"Toowoomba",
    "sg:classifiers":[
        {
            "category":"Insurance",
            "subcategory":"Hazard Insurance",
            "type":"Services"
        }
    ],
    "sg:phone":"+61 7 4632 4299",
    "sg:postcode":"4350",
    "sg:province":"QLD",
    "sg:tags":[
        "fire",
        "accident",
        "marine"
    ],
    "wof:name":"Royal & Sun Alliance Insurance Australia Ltd",
    "wof:placetype":"venue"
},
  "geometry": {"coordinates":[151.95228599999999,-27.568207],"type":"Point"}
}