{
  "type": "Feature",
  "properties": {
    "addr:full":"27 Gunyah St Windsor QLD 4030",
    "addr:housenumber":"27",
    "addr:postcode":"4030",
    "addr:street":"Gunyah St",
    "iso:country":"AU",
    "sg:address":"27 Gunyah St",
    "sg:city":"Windsor",
    "sg:classifiers":[
        {
            "category":"Shopping",
            "subcategory":"Baby Store",
            "type":"Retail Goods"
        }
    ],
    "sg:phone":"+61 7 3857 7760",
    "sg:postcode":"4030",
    "sg:province":"QLD",
    "sg:tags":[
        "children's",
        "wear"
    ],
    "wof:name":"R Divine",
    "wof:placetype":"venue"
},
  "geometry": {"coordinates":[153.027557,-27.423637],"type":"Point"}
}