{
  "type": "Feature",
  "properties": {
    "addr:full":"151 Osbourne Ave Clayton South VIC 3169",
    "addr:housenumber":"151",
    "addr:postcode":"3169",
    "addr:street":"Osbourne Ave",
    "iso:country":"AU",
    "sg:address":"151 Osbourne Ave",
    "sg:city":"Clayton South",
    "sg:classifiers":[
        {
            "category":"Professional",
            "subcategory":"Business Services",
            "type":"Services"
        }
    ],
    "sg:phone":"+61 419 997 010",
    "sg:postcode":"3169",
    "sg:province":"VIC",
    "sg:tags":[
        "management",
        "event"
    ],
    "wof:name":"Tucker Geoff",
    "wof:placetype":"venue"
},
  "geometry": {"coordinates":[145.13116455100001,-37.9446716309],"type":"Point"}
}