{
  "type": "Feature",
  "properties": {
    "iso:country":"AU",
    "sg:address":"79 Haldon St",
    "sg:city":"Lakemba",
    "sg:classifiers":[
        {
            "category":"Education",
            "subcategory":"University",
            "type":"Public Place"
        }
    ],
    "sg:phone":"+61 2 9740 9276",
    "sg:postcode":"2195",
    "sg:province":"NSW",
    "sg:tags":[
        "educational",
        "organisation",
        "cultural"
    ],
    "wof:name":"Somali Islamic & Cultural Centre Inc",
    "wof:placetype":"venue"
},
  "geometry": {"coordinates":[151.07751500000001,-33.920345],"type":"Point"}
}