{
  "type": "Feature",
  "properties": {
    "addr:full":"3 Dividend St Mansfield QLD 4122",
    "addr:housenumber":"3",
    "addr:postcode":"4122",
    "addr:street":"Dividend St",
    "iso:country":"AU",
    "sg:address":"3 Dividend St",
    "sg:city":"Mansfield",
    "sg:classifiers":[
        {
            "category":"Shopping",
            "subcategory":"Computers & Home Electronics",
            "type":"Retail Goods"
        }
    ],
    "sg:phone":"+61 7 3849 6793",
    "sg:postcode":"4122",
    "sg:province":"QLD",
    "sg:tags":[
        "ergonomics"
    ],
    "wof:name":"Botanic Niche Pty Ltd",
    "wof:placetype":"venue"
},
  "geometry": {"coordinates":[153.10385131800001,-27.5335903168],"type":"Point"}
}