{
  "type": "Feature",
  "properties": {
    "iso:country":"AU",
    "sg:address":"11- 21 Berrima St",
    "sg:city":"Oakleigh East",
    "sg:classifiers":[
        {
            "category":"Manufacturing",
            "subcategory":"Paper Products",
            "type":"Manufacturing & Wholesale Goods"
        }
    ],
    "sg:phone":"+61 1800 000 398",
    "sg:postcode":"3166",
    "sg:province":"VIC",
    "sg:tags":[
        "disposable"
    ],
    "wof:name":"Coverall",
    "wof:placetype":"venue"
},
  "geometry": {"coordinates":[145.123046875,-37.9006690979],"type":"Point"}
}