{
  "type": "Feature",
  "properties": {
    "addr:full":"24 Commercial St Kaniva VIC 3419",
    "addr:housenumber":"24",
    "addr:postcode":"3419",
    "addr:street":"Commercial St",
    "iso:country":"AU",
    "sg:address":"24 Commercial St",
    "sg:city":"Kaniva",
    "sg:classifiers":[
        {
            "category":"Professional",
            "subcategory":"Accounting & Tax Preparation",
            "type":"Services"
        }
    ],
    "sg:phone":"+61 3 5392 2361",
    "sg:postcode":"3419",
    "sg:province":"VIC",
    "sg:tags":[
        "consultant",
        "taxation"
    ],
    "wof:name":"Murray Nankivell",
    "wof:placetype":"venue"
},
  "geometry": {"coordinates":[141.23849487300001,-36.3788375854],"type":"Point"}
}