{
  "type": "Feature",
  "properties": {
    "addr:full":"53 Tamar Ave Ballina NSW 2478",
    "addr:housenumber":"53",
    "addr:postcode":"2478",
    "addr:street":"Tamar Ave",
    "iso:country":"AU",
    "sg:address":"53 Tamar Ave",
    "sg:city":"Ballina",
    "sg:classifiers":[
        {
            "category":"Organizations",
            "subcategory":"Non-profit Organization",
            "type":"Services"
        }
    ],
    "sg:phone":"+61 2 6681 6069",
    "sg:postcode":"2478",
    "sg:province":"NSW",
    "sg:tags":[
        "environmental",
        "organisation",
        "conservation"
    ],
    "wof:name":"Wetland Care Australia",
    "wof:placetype":"venue"
},
  "geometry": {"coordinates":[153.56239318900001,-28.8699817657],"type":"Point"}
}