{
  "type": "Feature",
  "properties": {
    "addr:full":"339 Dandelion Drv Rowville VIC 3178",
    "addr:housenumber":"339",
    "addr:postcode":"3178",
    "addr:street":"Dandelion Drv",
    "iso:country":"AU",
    "sg:address":"339 Dandelion Drv",
    "sg:city":"Rowville",
    "sg:classifiers":[
        {
            "category":"Insurance",
            "subcategory":"Hazard Insurance",
            "type":"Services"
        }
    ],
    "sg:phone":"+61 3 9759 7415",
    "sg:postcode":"3178",
    "sg:province":"VIC",
    "sg:tags":[
        "loss",
        "adjuster",
        "assessor"
    ],
    "wof:name":"BGS Machinery Loss Assessor",
    "wof:placetype":"venue"
},
  "geometry": {"coordinates":[145.265869141,-37.92578125],"type":"Point"}
}