{
  "type": "Feature",
  "properties": {
    "addr:full":"39 Woongarra St Bundaberg QLD 4670",
    "addr:housenumber":"39",
    "addr:postcode":"4670",
    "addr:street":"Woongarra St",
    "iso:country":"AU",
    "sg:address":"39 Woongarra St",
    "sg:city":"Bundaberg",
    "sg:classifiers":[
        {
            "category":"Organizations",
            "subcategory":"Non-profit Organization",
            "type":"Services"
        }
    ],
    "sg:phone":"+61 7 4153 2670",
    "sg:postcode":"4670",
    "sg:province":"QLD",
    "sg:tags":[
        "support",
        "disability",
        "organisation"
    ],
    "wof:name":"Guide Dogs Queensland",
    "wof:placetype":"venue"
},
  "geometry": {"coordinates":[152.35072326700001,-24.8667602539],"type":"Point"}
}