{
  "type": "Feature",
  "properties": {
    "addr:full":"757 Logan Rd Greenslopes QLD 4120",
    "addr:housenumber":"757",
    "addr:postcode":"4120",
    "addr:street":"Logan Rd",
    "iso:country":"AU",
    "sg:address":"757 Logan Rd",
    "sg:city":"Greenslopes",
    "sg:classifiers":[
        {
            "category":"Professional",
            "subcategory":"Detective & Security Services",
            "type":"Services"
        }
    ],
    "sg:phone":"+61 7 3397 7944",
    "sg:postcode":"4120",
    "sg:province":"QLD",
    "sg:tags":[
        "equipment",
        "window",
        "doors"
    ],
    "wof:name":"Regency Security Doors & Windows",
    "wof:placetype":"venue"
},
  "geometry": {"coordinates":[153.053787231,-27.5134334564],"type":"Point"}
}