{
  "type": "Feature",
  "properties": {
    "addr:full":"1/ 89 Norma Rd Myaree WA 6154",
    "addr:housenumber":"/ 89",
    "addr:postcode":"6154",
    "addr:street":"Norma Rd",
    "iso:country":"AU",
    "sg:address":"1/ 89 Norma Rd",
    "sg:city":"Myaree",
    "sg:classifiers":[
        {
            "category":"Building & Trades",
            "subcategory":"Locksmith",
            "type":"Services"
        }
    ],
    "sg:phone":"+61 8 9528 2650",
    "sg:postcode":"6154",
    "sg:province":"WA",
    "sg:tags":[
        "lock"
    ],
    "wof:name":"Coastal Lock Service",
    "wof:placetype":"venue"
},
  "geometry": {"coordinates":[115.82215100000001,-32.042011],"type":"Point"}
}