{
  "type": "Feature",
  "properties": {
    "iso:country":"AU",
    "sg:address":"Unit 8/ 890 Bourke St",
    "sg:city":"Waterloo",
    "sg:classifiers":[
        {
            "category":"Wholesale",
            "subcategory":"Medical Equipment & Supplies",
            "type":"Manufacturing & Wholesale Goods"
        }
    ],
    "sg:phone":"+61 2 9699 4655",
    "sg:postcode":"2017",
    "sg:province":"NSW",
    "sg:tags":[
        "alternative",
        "health"
    ],
    "wof:name":"Traditional Medicine Supplies Pty Ltd",
    "wof:placetype":"venue"
},
  "geometry": {"coordinates":[151.20716857900001,-33.9033088684],"type":"Point"}
}