{
  "type": "Feature",
  "properties": {
    "addr:full":"6 Babel Rd Welshpool WA 6106",
    "addr:housenumber":"6",
    "addr:postcode":"6106",
    "addr:street":"Babel Rd",
    "iso:country":"AU",
    "sg:address":"6 Babel Rd",
    "sg:city":"Welshpool",
    "sg:classifiers":[
        {
            "category":"Home & Garden",
            "subcategory":"Building Materials",
            "type":"Retail Goods"
        }
    ],
    "sg:phone":"+61 8 9351 8555",
    "sg:postcode":"6106",
    "sg:province":"WA",
    "sg:tags":[
        "balustrading"
    ],
    "wof:name":"Tubelok Metals Australia Pty Ltd",
    "wof:placetype":"venue"
},
  "geometry": {"coordinates":[115.932502747,-31.9930400848],"type":"Point"}
}