{
  "type": "Feature",
  "properties": {
    "addr:full":"202/ 40 Refinery Drv Pyrmont NSW 2009",
    "addr:housenumber":"202 / 40",
    "addr:postcode":"2009",
    "addr:street":"Refinery Drv",
    "iso:country":"AU",
    "sg:address":"202/ 40 Refinery Drv",
    "sg:city":"Pyrmont",
    "sg:classifiers":[
        {
            "category":"Real Estate",
            "subcategory":"Architect",
            "type":"Services"
        }
    ],
    "sg:phone":"+61 412 002 122",
    "sg:postcode":"2009",
    "sg:province":"NSW",
    "wof:name":"Twibill Architects Pty Ltd",
    "wof:placetype":"venue"
},
  "geometry": {"coordinates":[151.19029235799999,-33.8664207458],"type":"Point"}
}