{
  "type": "Feature",
  "properties": {
    "addr:full":"1/ 132 Oxford St Cambridge Park NSW 2747",
    "addr:housenumber":"/ 132",
    "addr:postcode":"2747",
    "addr:street":"Oxford St",
    "iso:country":"AU",
    "sg:address":"1/ 132 Oxford St",
    "sg:city":"Cambridge Park",
    "sg:classifiers":[
        {
            "category":"Restaurant",
            "type":"Food & Drink"
        }
    ],
    "sg:phone":"+61 2 4731 8236",
    "sg:postcode":"2747",
    "sg:province":"NSW",
    "wof:name":"Caminn Chineses Restaurant",
    "wof:placetype":"venue"
},
  "geometry": {"coordinates":[150.720779419,-33.7476806641],"type":"Point"}
}