{
  "type": "Feature",
  "properties": {
    "iso:country":"AU",
    "sg:address":"PMB 63 via",
    "sg:city":"Katherine",
    "sg:classifiers":[
        {
            "category":"Education",
            "subcategory":"School",
            "type":"Public Place"
        }
    ],
    "sg:phone":"+61 8 8975 0946",
    "sg:postcode":"0852",
    "sg:province":"NT",
    "sg:tags":[
        "state",
        "except",
        "nsw"
    ],
    "wof:name":"Lajamanu Community Education Centre",
    "wof:placetype":"venue"
},
  "geometry": {"coordinates":[133.373886,-16.30308],"type":"Point"}
}