{
  "type": "Feature",
  "properties": {
    "iso:country":"AU",
    "sg:address":"Gardner St",
    "sg:city":"Goolwa",
    "sg:classifiers":[
        {
            "category":"Education",
            "subcategory":"School",
            "type":"Public Place"
        }
    ],
    "sg:phone":"+61 8 8555 2261",
    "sg:postcode":"5214",
    "sg:province":"SA",
    "sg:tags":[
        "state",
        "except",
        "nsw"
    ],
    "wof:name":"Goolwa Primary School",
    "wof:placetype":"venue"
},
  "geometry": {"coordinates":[138.775512695,-35.5013046265],"type":"Point"}
}