{
  "type": "Feature",
  "properties": {
    "iso:country":"AU",
    "sg:address":"Suite 3/ 255-259 Pacific Hwy",
    "sg:city":"North Sydney",
    "sg:classifiers":[
        {
            "category":"Health Services",
            "subcategory":"Health Practitioner",
            "type":"Services"
        }
    ],
    "sg:phone":"+61 2 9957 3200",
    "sg:postcode":"2060",
    "sg:province":"NSW",
    "sg:tags":[
        "psychologist"
    ],
    "wof:name":"FMA Rehabilation Services",
    "wof:placetype":"venue"
},
  "geometry": {"coordinates":[151.20504760700001,-33.834072113],"type":"Point"}
}