{
  "type": "Feature",
  "properties": {
    "iso:country":"AU",
    "sg:address":"Anderson St",
    "sg:city":"Lilydale",
    "sg:classifiers":[
        {
            "category":"Health Services",
            "subcategory":"Nursing And Care Facility",
            "type":"Services"
        }
    ],
    "sg:phone":"+61 3 9739 5711",
    "sg:postcode":"3140",
    "sg:province":"VIC",
    "sg:tags":[
        "home"
    ],
    "wof:name":"Summerwood Hostel",
    "wof:placetype":"venue"
},
  "geometry": {"coordinates":[145.35551452600001,-37.7617683411],"type":"Point"}
}