{
  "type": "Feature",
  "properties": {
    "addr:full":"205 King St Hamilton VIC 3300",
    "addr:housenumber":"205",
    "addr:postcode":"3300",
    "addr:street":"King St",
    "iso:country":"AU",
    "sg:address":"205 King St",
    "sg:city":"Hamilton",
    "sg:classifiers":[
        {
            "category":"Food & Beverages",
            "subcategory":"Specialty",
            "type":"Retail Goods"
        }
    ],
    "sg:phone":"+61 3 5572 3098",
    "sg:postcode":"3300",
    "sg:province":"VIC",
    "sg:tags":[
        "product",
        "health"
    ],
    "wof:name":"Herbal Life Distributor",
    "wof:placetype":"venue"
},
  "geometry": {"coordinates":[142.02737426799999,-37.7323074341],"type":"Point"}
}