{
  "type": "Feature",
  "properties": {
    "iso:country":"AU",
    "sg:address":"Adsto House 401 New Canterbury Rd",
    "sg:city":"Dulwich Hill",
    "sg:classifiers":[
        {
            "category":"Professional",
            "subcategory":"Business Services",
            "type":"Services"
        }
    ],
    "sg:phone":"+61 2 9560 1110",
    "sg:postcode":"2203",
    "sg:province":"NSW",
    "sg:tags":[
        "small",
        "advisory"
    ],
    "wof:name":"Adsto International Pty Ltd",
    "wof:placetype":"venue"
},
  "geometry": {"coordinates":[151.13656599999999,-33.905685],"type":"Point"}
}