{
  "type": "Feature",
  "properties": {
    "iso:country":"AU",
    "sg:address":"135 Macquarie St",
    "sg:city":"Sydney",
    "sg:classifiers":[
        {
            "category":"Wholesale",
            "subcategory":"Medical Equipment & Supplies",
            "type":"Manufacturing & Wholesale Goods"
        }
    ],
    "sg:phone":"+61 2 9810 1466",
    "sg:postcode":"2000",
    "sg:province":"NSW",
    "sg:tags":[
        "aids",
        "hearing"
    ],
    "wof:name":"Pauka Hearing Aids Pty Ltd",
    "wof:placetype":"venue"
},
  "geometry": {"coordinates":[151.21263122600001,-33.8643074036],"type":"Point"}
}