{
  "type": "Feature",
  "properties": {
    "addr:full":"41 Clarendon Rd Peakhurst NSW 2210",
    "addr:housenumber":"41",
    "addr:postcode":"2210",
    "addr:street":"Clarendon Rd",
    "iso:country":"AU",
    "sg:address":"41 Clarendon Rd",
    "sg:city":"Peakhurst",
    "sg:classifiers":[
        {
            "category":"Home & Garden",
            "subcategory":"Building Materials",
            "type":"Retail Goods"
        }
    ],
    "sg:phone":"+61 402 462 036",
    "sg:postcode":"2210",
    "sg:province":"NSW",
    "sg:tags":[
        "concrete",
        "gutter",
        "kerb"
    ],
    "wof:name":"Tom Wang",
    "wof:placetype":"venue"
},
  "geometry": {"coordinates":[151.044342,-33.956966],"type":"Point"}
}