{
  "type": "Feature",
  "properties": {
    "iso:country":"AU",
    "sg:address":"6 Thomas St",
    "sg:city":"Hampton",
    "sg:classifiers":[
        {
            "category":"Retail",
            "subcategory":"Veterinary Services",
            "type":"Services"
        }
    ],
    "sg:phone":"+61 3 9521 0211",
    "sg:postcode":"3188",
    "sg:province":"VIC",
    "sg:tags":[
        "surgeon"
    ],
    "wof:name":"Hampton Vet Hospital",
    "wof:placetype":"venue"
},
  "geometry": {"coordinates":[145.003372192,-37.9385643005],"type":"Point"}
}