{
  "type": "Feature",
  "properties": {
    "addr:full":"46 Old Barrenjoey Rd Avalon NSW 2107",
    "addr:housenumber":"46",
    "addr:postcode":"2107",
    "addr:street":"Old Barrenjoey Rd",
    "iso:country":"AU",
    "sg:address":"46 Old Barrenjoey Rd",
    "sg:city":"Avalon",
    "sg:classifiers":[
        {
            "category":"Health Services",
            "subcategory":"Health Practitioner",
            "type":"Services"
        }
    ],
    "sg:phone":"+61 2 9973 1676",
    "sg:postcode":"2107",
    "sg:province":"NSW",
    "sg:tags":[
        "psychotherapist"
    ],
    "wof:name":"Peninsula Counselling-Avalon",
    "wof:placetype":"venue"
},
  "geometry": {"coordinates":[151.328613281,-33.637840271],"type":"Point"}
}