{
  "type": "Feature",
  "properties": {
    "iso:country":"AU",
    "sg:address":"20 Pangee St",
    "sg:city":"Kingsgrove",
    "sg:classifiers":[
        {
            "category":"Professional",
            "type":"Services"
        }
    ],
    "sg:phone":"+61 412 254 880",
    "sg:postcode":"2208",
    "sg:province":"NSW",
    "sg:tags":[
        "courier"
    ],
    "wof:name":"C J K Couriers",
    "wof:placetype":"venue"
},
  "geometry": {"coordinates":[151.103668,-33.935253],"type":"Point"}
}