{
  "type": "Feature",
  "properties": {
    "addr:full":"Cnr Bruce Hwy & Oak St Gympie QLD 4570",
    "addr:postcode":"4570",
    "addr:street":"Cnr Bruce Hwy & Oak St",
    "iso:country":"AU",
    "sg:address":"Cnr Bruce Hwy & Oak St",
    "sg:city":"Gympie",
    "sg:classifiers":[
        {
            "category":"Autos & Motor Vehicles",
            "subcategory":"Auto Supplies",
            "type":"Retail Goods"
        }
    ],
    "sg:phone":"+61 7 5482 8597",
    "sg:postcode":"4570",
    "sg:province":"QLD",
    "sg:tags":[
        "camper-trailers",
        "caravan",
        "equipment"
    ],
    "wof:name":"Sunshine Coast RVs",
    "wof:placetype":"venue"
},
  "geometry": {"coordinates":[152.65594482399999,-26.190279007],"type":"Point"}
}