{
  "type": "Feature",
  "properties": {
    "iso:country":"AU",
    "sg:address":"Unit 3a/ 57 Oxford St",
    "sg:city":"Bulimba",
    "sg:classifiers":[
        {
            "category":"Real Estate",
            "subcategory":"Architect",
            "type":"Services"
        }
    ],
    "sg:phone":"+61 7 3399 7797",
    "sg:postcode":"4171",
    "sg:province":"QLD",
    "wof:name":"Arco Eco",
    "wof:placetype":"venue"
},
  "geometry": {"coordinates":[153.05502319300001,-27.4508533478],"type":"Point"}
}