{
  "type": "Feature",
  "properties": {
    "addr:full":"11 McElligott Crt Canning Vale WA 6155",
    "addr:housenumber":"11",
    "addr:postcode":"6155",
    "addr:street":"Mcelligott Crt",
    "iso:country":"AU",
    "sg:address":"11 McElligott Crt",
    "sg:city":"Canning Vale",
    "sg:classifiers":[
        {
            "category":"Communications",
            "type":"Services"
        }
    ],
    "sg:phone":"+61 8 9455 4288",
    "sg:postcode":"6155",
    "sg:province":"WA",
    "sg:tags":[
        "equipment",
        "radio"
    ],
    "wof:name":"Terlin Outbacker",
    "wof:placetype":"venue"
},
  "geometry": {"coordinates":[115.920563,-32.061897],"type":"Point"}
}