{
  "type": "Feature",
  "properties": {
    "iso:country":"AU",
    "sg:address":"4 Snow Street (Australian Air Express)",
    "sg:city":"Lismore",
    "sg:classifiers":[
        {
            "category":"Retail",
            "subcategory":"Auto Rental",
            "type":"Services"
        }
    ],
    "sg:phone":"+61 2 6621 9022",
    "sg:postcode":"2480",
    "sg:province":"NSW",
    "sg:tags":[
        "bus",
        "truck"
    ],
    "wof:name":"Avis",
    "wof:placetype":"venue"
},
  "geometry": {"coordinates":[153.26510620100001,-28.8194561005],"type":"Point"}
}