{
  "type": "Feature",
  "properties": {
    "addr:full":"57 Erin St Richmond VIC 3121",
    "addr:housenumber":"57",
    "addr:postcode":"3121",
    "addr:street":"Erin St",
    "iso:country":"AU",
    "sg:address":"57 Erin St",
    "sg:city":"Richmond",
    "sg:classifiers":[
        {
            "category":"Health Services",
            "subcategory":"Doctor",
            "type":"Services"
        }
    ],
    "sg:phone":"+61 3 9429 6547",
    "sg:postcode":"3121",
    "sg:province":"VIC",
    "sg:tags":[
        "medical",
        "practitioner"
    ],
    "wof:name":"Manolas E G Dr",
    "wof:placetype":"venue"
},
  "geometry": {"coordinates":[144.99339294399999,-37.8165016174],"type":"Point"}
}