{
  "type": "Feature",
  "properties": {
    "iso:country":"AU",
    "sg:address":"Cnr Rockingham Rd & Barrett St",
    "sg:city":"Spearwood",
    "sg:classifiers":[
        {
            "category":"Wholesale",
            "subcategory":"Medical Equipment & Supplies",
            "type":"Manufacturing & Wholesale Goods"
        }
    ],
    "sg:phone":"+61 8 9434 1118",
    "sg:postcode":"6163",
    "sg:province":"WA",
    "sg:tags":[
        "aid",
        "care",
        "health",
        "home"
    ],
    "wof:name":"Spearwood 7 Day Pharmacy",
    "wof:placetype":"venue"
},
  "geometry": {"coordinates":[115.780907,-32.10252],"type":"Point"}
}