{
  "type": "Feature",
  "properties": {
    "addr:full":"106 Dilkera Ave Valentine NSW 2280",
    "addr:housenumber":"106",
    "addr:postcode":"2280",
    "addr:street":"Dilkera Ave",
    "iso:country":"AU",
    "sg:address":"106 Dilkera Ave",
    "sg:city":"Valentine",
    "sg:classifiers":[
        {
            "category":"Professional",
            "subcategory":"Computer Services",
            "type":"Services"
        }
    ],
    "sg:phone":"+61 418 820 440",
    "sg:postcode":"2280",
    "sg:province":"NSW",
    "sg:tags":[
        "consultant",
        "system"
    ],
    "wof:name":"Iterations Pty Ltd",
    "wof:placetype":"venue"
},
  "geometry": {"coordinates":[151.629562378,-33.0112609863],"type":"Point"}
}