{
  "type": "Feature",
  "properties": {
    "iso:country":"AU",
    "sg:address":"298 Hursley Rd",
    "sg:city":"Toowoomba",
    "sg:classifiers":[
        {
            "category":"Building & Trades",
            "subcategory":"Landscaping Services",
            "type":"Services"
        }
    ],
    "sg:phone":"+61 7 4630 4055",
    "sg:postcode":"4350",
    "sg:province":"QLD",
    "sg:tags":[
        "stump",
        "tree",
        "felling",
        "removal"
    ],
    "wof:name":"Falknau Professional Tree Lopping Service",
    "wof:placetype":"venue"
},
  "geometry": {"coordinates":[151.890411,-27.555111],"type":"Point"}
}