{
  "type": "Feature",
  "properties": {
    "addr:full":"26 Narrows Rd The Narrows NT 0820",
    "addr:housenumber":"26",
    "addr:postcode":"nt 0820",
    "addr:street":"Narrows Rd",
    "iso:country":"AU",
    "sg:address":"26 Narrows Rd",
    "sg:city":"The Narrows",
    "sg:classifiers":[
        {
            "category":"Professional",
            "subcategory":"Accounting & Tax Preparation",
            "type":"Services"
        }
    ],
    "sg:phone":"+61 419 729 867",
    "sg:postcode":"0820",
    "sg:province":"NT",
    "sg:tags":[
        "jukebox"
    ],
    "sg:website":"http://www.rebmoc.com",
    "wof:name":"Darwin Digital Jukebox Hire",
    "wof:placetype":"venue"
},
  "geometry": {"coordinates":[130.86026000999999,-12.4252471924],"type":"Point"}
}