{
  "type": "Feature",
  "properties": {
    "addr:full":"Shop 59 The Palm Centre Coffs Harbour NSW 2450",
    "addr:housenumber":"shop 59",
    "addr:postcode":"2450",
    "addr:street":"The",
    "iso:country":"AU",
    "sg:address":"Shop 59",
    "sg:city":"The Palm Centre Coffs Harbour",
    "sg:classifiers":[
        {
            "category":"Shopping",
            "subcategory":"Clothing, Apparel, & Fashions",
            "type":"Retail Goods"
        }
    ],
    "sg:phone":"+61 2 6652 9556",
    "sg:postcode":"2450",
    "sg:province":"NSW",
    "sg:tags":[
        "lady",
        "wear"
    ],
    "wof:name":"Queens Emporium",
    "wof:placetype":"venue"
},
  "geometry": {"coordinates":[153.11515800000001,-30.29701],"type":"Point"}
}