{
  "type": "Feature",
  "properties": {
    "addr:full":"5A Ray St Invermay TAS 7248",
    "addr:housenumber":"5a",
    "addr:postcode":"7248",
    "addr:street":"Ray St",
    "iso:country":"AU",
    "sg:address":"5A Ray St",
    "sg:city":"Invermay",
    "sg:classifiers":[
        {
            "category":"Building & Trades",
            "subcategory":"Construction",
            "type":"Services"
        }
    ],
    "sg:phone":"+61 408 133 175",
    "sg:postcode":"7248",
    "sg:province":"TAS",
    "sg:tags":[
        "bitumen",
        "paving",
        "asphalt"
    ],
    "wof:name":"Northseal Pty Ltd",
    "wof:placetype":"venue"
},
  "geometry": {"coordinates":[147.13836669899999,-41.4227867126],"type":"Point"}
}