{
  "type": "Feature",
  "properties": {
    "addr:full":"32 Josephine Ave Mt Waverley VIC 3149",
    "addr:housenumber":"32",
    "addr:postcode":"3149",
    "addr:street":"Josephine Ave Mt",
    "iso:country":"AU",
    "sg:address":"32 Josephine Ave",
    "sg:city":"Mt Waverley",
    "sg:classifiers":[
        {
            "category":"Professional",
            "subcategory":"Accounting & Tax Preparation",
            "type":"Services"
        }
    ],
    "sg:phone":"+61 3 9802 3302",
    "sg:postcode":"3149",
    "sg:province":"VIC",
    "sg:tags":[
        "accountant",
        "auditor"
    ],
    "wof:name":"Fowler R J & Associates",
    "wof:placetype":"venue"
},
  "geometry": {"coordinates":[145.14047241200001,-37.8683509827],"type":"Point"}
}