{
  "type": "Feature",
  "properties": {
    "iso:country":"AU",
    "sg:address":"16 Oak Ave",
    "sg:city":"Elsternwick",
    "sg:classifiers":[
        {
            "category":"Home & Garden",
            "subcategory":"Building Materials",
            "type":"Retail Goods"
        }
    ],
    "sg:phone":"+61 412 747 799",
    "sg:postcode":"3185",
    "sg:province":"VIC",
    "sg:tags":[
        "restoration",
        "supply"
    ],
    "wof:name":"Insight Building & Design",
    "wof:placetype":"venue"
},
  "geometry": {"coordinates":[145.00323486299999,-37.8900527954],"type":"Point"}
}