{
  "type": "Feature",
  "properties": {
    "iso:country":"AU",
    "sg:address":"Suite 104, 554 Church St",
    "sg:city":"Richmond",
    "sg:classifiers":[
        {
            "category":"Professional",
            "subcategory":"Art Services",
            "type":"Services"
        }
    ],
    "sg:phone":"+61 3 9421 1555",
    "sg:postcode":"3121",
    "sg:province":"VIC",
    "sg:tags":[
        "graphic",
        "designer"
    ],
    "wof:name":"White Marketing Design",
    "wof:placetype":"venue"
},
  "geometry": {"coordinates":[144.99717712399999,-37.8289146423],"type":"Point"}
}