{
  "type": "Feature",
  "properties": {
    "addr:full":"338 New South Head Rd Double Bay NSW 2028",
    "addr:housenumber":"338",
    "addr:postcode":"2028",
    "addr:street":"New South Head Rd",
    "iso:country":"AU",
    "sg:address":"338 New South Head Rd",
    "sg:city":"Double Bay",
    "sg:classifiers":[
        {
            "category":"Fast Food",
            "type":"Food & Drink"
        }
    ],
    "sg:phone":"+61 2 9327 7755",
    "sg:postcode":"2028",
    "sg:province":"NSW",
    "sg:tags":[
        "away",
        "take"
    ],
    "wof:name":"Oporto Double Bay",
    "wof:placetype":"venue"
},
  "geometry": {"coordinates":[151.24244689899999,-33.8779067993],"type":"Point"}
}