{
  "type": "Feature",
  "properties": {
    "iso:country":"AU",
    "sg:address":"Shp 3, South Street (Cnr Stock Road)",
    "sg:city":"O'Connor",
    "sg:classifiers":[
        {
            "category":"Manufacturing",
            "subcategory":"Furniture",
            "type":"Manufacturing & Wholesale Goods"
        }
    ],
    "sg:phone":"+61 8 9314 1377",
    "sg:postcode":"6163",
    "sg:province":"WA",
    "sg:tags":[
        "builder",
        "designer",
        "custom"
    ],
    "sg:website":"http://www.colonyfurniture.com.au",
    "wof:name":"Colony Furniture",
    "wof:placetype":"venue"
},
  "geometry": {"coordinates":[115.815697,-32.068451],"type":"Point"}
}