{
  "type": "Feature",
  "properties": {
    "iso:country":"AU",
    "sg:address":"Shp 1 / 27 Orlando St",
    "sg:city":"Coffs Harbour",
    "sg:classifiers":[
        {
            "category":"Wholesale",
            "subcategory":"Medical Equipment & Supplies",
            "type":"Manufacturing & Wholesale Goods"
        }
    ],
    "sg:phone":"+61 2 6650 0454",
    "sg:postcode":"2450",
    "sg:province":"NSW",
    "sg:tags":[
        "aids",
        "hearing"
    ],
    "wof:name":"Coffs Coastal Hearing Service",
    "wof:placetype":"venue"
},
  "geometry": {"coordinates":[153.136597,-30.297129],"type":"Point"}
}