{
  "type": "Feature",
  "properties": {
    "addr:full":"Unit 2, 61 Norman St Peakhurst NSW 2210",
    "addr:housenumber":"61",
    "addr:postcode":"2210",
    "addr:street":"Norman St",
    "iso:country":"AU",
    "sg:address":"Unit 2, 61 Norman St",
    "sg:city":"Peakhurst",
    "sg:classifiers":[
        {
            "category":"Shopping",
            "subcategory":"Music",
            "type":"Retail Goods"
        }
    ],
    "sg:phone":"+61 2 9533 7703",
    "sg:postcode":"2210",
    "sg:province":"NSW",
    "sg:tags":[
        "instrument",
        "musical"
    ],
    "wof:name":"Music Studio 101",
    "wof:placetype":"venue"
},
  "geometry": {"coordinates":[151.062195,-33.965141],"type":"Point"}
}