{
  "type": "Feature",
  "properties": {
    "addr:full":"Unit 2 6 Carroll St Mt Louisa QLD 4814",
    "addr:housenumber":"6",
    "addr:postcode":"4814",
    "addr:street":"Carroll St Mt Louisa",
    "iso:country":"AU",
    "sg:address":"Unit 2 6 Carroll St",
    "sg:city":"Mt Louisa",
    "sg:classifiers":[
        {
            "category":"Building & Trades",
            "subcategory":"Pest Control",
            "type":"Services"
        }
    ],
    "sg:phone":"+61 7 4774 7600",
    "sg:postcode":"4814",
    "sg:province":"QLD",
    "sg:tags":[
        "herbicide",
        "insecticides",
        "fungicide"
    ],
    "wof:name":"Macspred Pty Ltd",
    "wof:placetype":"venue"
},
  "geometry": {"coordinates":[146.748245,-19.265366],"type":"Point"}
}