{
  "type": "Feature",
  "properties": {
    "addr:full":"568 Ingham Rd Mt Louisa QLD 4814",
    "addr:housenumber":"568",
    "addr:postcode":"4814",
    "addr:street":"Ingham Rd",
    "iso:country":"AU",
    "sg:address":"568 Ingham Rd",
    "sg:city":"Mt Louisa",
    "sg:classifiers":[
        {
            "category":"Home & Garden",
            "subcategory":"Garden Supply",
            "type":"Retail Goods"
        }
    ],
    "sg:phone":"+61 7 4774 5155",
    "sg:postcode":"4814",
    "sg:province":"QLD",
    "sg:tags":[
        "landscape"
    ],
    "wof:name":"Hanson Masonry",
    "wof:placetype":"venue"
},
  "geometry": {"coordinates":[146.74648999999999,-19.262794],"type":"Point"}
}