{
  "type": "Feature",
  "properties": {
    "iso:country":"AU",
    "sg:address":"Gandel Campus 245 Burwood Hwy",
    "sg:city":"Burwood",
    "sg:classifiers":[
        {
            "category":"Education",
            "subcategory":"School",
            "type":"Public Place"
        }
    ],
    "sg:phone":"+61 3 9834 0000",
    "sg:postcode":"3125",
    "sg:province":"VIC",
    "sg:tags":[
        "co-educational"
    ],
    "wof:name":"Mount Scopus Memorial College",
    "wof:placetype":"venue"
},
  "geometry": {"coordinates":[145.11782836899999,-37.8500823975],"type":"Point"}
}