{
  "type": "Feature",
  "properties": {
    "addr:full":"199 Heidelberg Rd Northcote VIC 3070",
    "addr:housenumber":"199",
    "addr:postcode":"3070",
    "addr:street":"Heidelberg Rd",
    "iso:country":"AU",
    "sg:address":"199 Heidelberg Rd",
    "sg:city":"Northcote",
    "sg:classifiers":[
        {
            "category":"Military Area",
            "subcategory":"Armory",
            "type":"Public Place"
        }
    ],
    "sg:phone":"+61 3 9488 1599",
    "sg:postcode":"3070",
    "sg:province":"VIC",
    "sg:tags":[
        "teleconferencing"
    ],
    "wof:name":"Rutledge Engineering",
    "wof:placetype":"venue"
},
  "geometry": {"coordinates":[145.01095599999999,-37.783962],"type":"Point"}
}