{
  "type": "Feature",
  "properties": {
    "addr:full":"99 Nepean Hwy Elsternwick VIC 3185",
    "addr:housenumber":"99",
    "addr:postcode":"3185",
    "addr:street":"Nepean Hwy",
    "iso:country":"AU",
    "sg:address":"99 Nepean Hwy",
    "sg:city":"Elsternwick",
    "sg:classifiers":[
        {
            "category":"Autos & Motor Vehicles",
            "subcategory":"Automobile Sales",
            "type":"Retail Goods"
        }
    ],
    "sg:phone":"+61 3 9524 2079",
    "sg:postcode":"3185",
    "sg:province":"VIC",
    "sg:tags":[
        "car",
        "used"
    ],
    "sg:website":"http://www.lexusofbrighton.com.au",
    "wof:name":"Lexus Of Brighton",
    "wof:placetype":"venue"
},
  "geometry": {"coordinates":[145.00386047399999,-37.8934173584],"type":"Point"}
}