{
  "type": "Feature",
  "properties": {
    "addr:full":"Janine St B11 Scoresby Ind Pk Scoresby VIC 3179",
    "addr:postcode":"b11 scoresby;3179",
    "addr:street":"Janine St",
    "iso:country":"AU",
    "sg:address":"Janine St B11 Scoresby Ind Pk",
    "sg:city":"Scoresby",
    "sg:classifiers":[
        {
            "category":"Autos & Motor Vehicles",
            "subcategory":"Auto Supplies",
            "type":"Retail Goods"
        }
    ],
    "sg:phone":"+61 3 9763 6701",
    "sg:postcode":"3179",
    "sg:province":"VIC",
    "sg:tags":[
        "transmission",
        "equipment",
        "power"
    ],
    "wof:name":"Challenge Power Transmission",
    "wof:placetype":"venue"
},
  "geometry": {"coordinates":[145.230300903,-37.9011497498],"type":"Point"}
}