{
  "type": "Feature",
  "properties": {
    "iso:country":"AU",
    "sg:address":"337 Bell St",
    "sg:city":"Heidelberg West",
    "sg:classifiers":[
        {
            "category":"Health Services",
            "subcategory":"Doctor",
            "type":"Services"
        }
    ],
    "sg:phone":"+61 3 9459 8139",
    "sg:postcode":"3081",
    "sg:province":"VIC",
    "sg:tags":[
        "medical",
        "practitioner"
    ],
    "wof:name":"Bellfield Medical Centre",
    "wof:placetype":"venue"
},
  "geometry": {"coordinates":[145.039825439,-37.7497711182],"type":"Point"}
}