{
  "type": "Feature",
  "properties": {
    "addr:full":"53 Francis St Clarence Park SA 5034",
    "addr:housenumber":"53",
    "addr:postcode":"5034",
    "addr:street":"Francis St",
    "iso:country":"AU",
    "sg:address":"53 Francis St",
    "sg:city":"Clarence Park",
    "sg:classifiers":[
        {
            "category":"Home & Garden",
            "subcategory":"Building Materials",
            "type":"Retail Goods"
        }
    ],
    "sg:phone":"+61 423 194 916",
    "sg:postcode":"5034",
    "sg:province":"SA",
    "sg:tags":[
        "lawn",
        "cutting",
        "maintenance"
    ],
    "wof:name":"Inside out Home and Garden Maintenance",
    "wof:placetype":"venue"
},
  "geometry": {"coordinates":[138.584884644,-34.9631996155],"type":"Point"}
}