{
  "type": "Feature",
  "properties": {
    "addr:full":"3/ 8 Otranto Ave Caloundra QLD 4551",
    "addr:housenumber":"/ 8",
    "addr:postcode":"4551",
    "addr:street":"Otranto Ave",
    "iso:country":"AU",
    "sg:address":"3/ 8 Otranto Ave",
    "sg:city":"Caloundra",
    "sg:classifiers":[
        {
            "category":"Professional",
            "subcategory":"Accounting & Tax Preparation",
            "type":"Services"
        }
    ],
    "sg:phone":"+61 7 5491 5968",
    "sg:postcode":"4551",
    "sg:province":"QLD",
    "sg:tags":[
        "bookkeeping"
    ],
    "wof:name":"ITP Bookkeeping",
    "wof:placetype":"venue"
},
  "geometry": {"coordinates":[153.130249023,-26.8043403625],"type":"Point"}
}