{
  "type": "Feature",
  "properties": {
    "iso:country":"AU",
    "sg:address":"Shop 4/ 217 Unley Rd",
    "sg:city":"Malvern",
    "sg:classifiers":[
        {
            "category":"Shopping",
            "subcategory":"Clothing, Apparel, & Fashions",
            "type":"Retail Goods"
        }
    ],
    "sg:phone":"+61 8 8373 6689",
    "sg:postcode":"5061",
    "sg:province":"SA",
    "sg:tags":[
        "boutique"
    ],
    "wof:name":"Paola Calo",
    "wof:placetype":"venue"
},
  "geometry": {"coordinates":[138.608154297,-34.9565887451],"type":"Point"}
}