{
  "type": "Feature",
  "properties": {
    "iso:country":"AU",
    "sg:address":"76 Aldinga Drv",
    "sg:city":"Wamberal",
    "sg:classifiers":[
        {
            "category":"Personal",
            "subcategory":"Beauty Salon",
            "type":"Services"
        }
    ],
    "sg:phone":"+61 2 4385 3537",
    "sg:postcode":"2260",
    "sg:province":"NSW",
    "wof:name":"Beauty Obsession",
    "wof:placetype":"venue"
},
  "geometry": {"coordinates":[151.444351,-33.417316],"type":"Point"}
}