{
  "type": "Feature",
  "properties": {
    "iso:country":"AU",
    "sg:address":"5 Calvert St",
    "sg:city":"Marrickville",
    "sg:classifiers":[
        {
            "category":"Food & Beverages",
            "subcategory":"Fruits & Vegetables",
            "type":"Retail Goods"
        }
    ],
    "sg:phone":"+61 2 9558 5949",
    "sg:postcode":"2204",
    "sg:province":"NSW",
    "sg:tags":[
        "consultant",
        "catering"
    ],
    "wof:name":"Sloan's Range of Gourmet Goodys",
    "wof:placetype":"venue"
},
  "geometry": {"coordinates":[151.158447,-33.913216],"type":"Point"}
}