{
  "type": "Feature",
  "properties": {
    "addr:full":"101 Challis Rd Armadale WA 6112",
    "addr:housenumber":"101",
    "addr:postcode":"6112",
    "addr:street":"Challis Rd",
    "iso:country":"AU",
    "sg:address":"101 Challis Rd",
    "sg:city":"Armadale",
    "sg:classifiers":[
        {
            "category":"Social Services",
            "subcategory":"Child Care",
            "type":"Services"
        }
    ],
    "sg:phone":"+61 8 9497 3091",
    "sg:postcode":"6112",
    "sg:province":"WA",
    "wof:name":"Mundarda Child Care Centre",
    "wof:placetype":"venue"
},
  "geometry": {"coordinates":[115.999900818,-32.1311302185],"type":"Point"}
}