{
  "type": "Feature",
  "properties": {
    "addr:full":"Unit 4/110- 112 Ballandella Rd Pendle Hill NSW 2145",
    "addr:housenumber":"/ 110 112",
    "addr:postcode":"2145",
    "addr:street":"Ballandella Rd",
    "iso:country":"AU",
    "sg:address":"Unit 4/110- 112 Ballandella Rd",
    "sg:city":"Pendle Hill",
    "sg:classifiers":[
        {
            "category":"Professional",
            "subcategory":"Engineering",
            "type":"Services"
        }
    ],
    "sg:phone":"+61 1800 800 181",
    "sg:postcode":"2145",
    "sg:province":"NSW",
    "sg:tags":[
        "refrigeration",
        "engineer"
    ],
    "wof:name":"New Systems Industries Pty Ltd",
    "wof:placetype":"venue"
},
  "geometry": {"coordinates":[150.955276489,-33.7970695496],"type":"Point"}
}