{
  "type": "Feature",
  "properties": {
    "addr:full":"39 Doyle Ave Unanderra NSW 2526",
    "addr:housenumber":"39",
    "addr:postcode":"2526",
    "addr:street":"Doyle Ave",
    "iso:country":"AU",
    "sg:address":"39 Doyle Ave",
    "sg:city":"Unanderra",
    "sg:classifiers":[
        {
            "category":"Manufacturing",
            "subcategory":"Tools & Machinery",
            "type":"Manufacturing & Wholesale Goods"
        }
    ],
    "sg:phone":"+61 2 4272 2599",
    "sg:postcode":"2526",
    "sg:province":"NSW",
    "sg:tags":[
        "earth",
        "excavating",
        "moving",
        "equipment"
    ],
    "wof:name":"Komatsu",
    "wof:placetype":"venue"
},
  "geometry": {"coordinates":[150.83598327600001,-34.4682998657],"type":"Point"}
}