{
  "type": "Feature",
  "properties": {
    "addr:full":"Mid City Centre, 197 Pitt Street Mall Sydney NSW 2000",
    "addr:housenumber":"197",
    "addr:postcode":"2000",
    "addr:street":"Pitt Street Mall",
    "iso:country":"AU",
    "sg:address":"Mid City Centre, 197",
    "sg:city":"Pitt Street Mall Sydney",
    "sg:classifiers":[
        {
            "category":"Transit Center",
            "subcategory":"Passenger",
            "type":"Transportation"
        }
    ],
    "sg:phone":"+61 2 9230 0677",
    "sg:postcode":"2000",
    "sg:province":"NSW",
    "sg:tags":[
        "retail",
        "toiletry",
        "perfume"
    ],
    "wof:name":"The Perfume Connection",
    "wof:placetype":"venue"
},
  "geometry": {"coordinates":[151.208084106,-33.869758606],"type":"Point"}
}