{
  "type": "Feature",
  "properties": {
    "iso:country":"AU",
    "sg:address":"414 Botany Rd",
    "sg:city":"Alexandria",
    "sg:classifiers":[
        {
            "category":"Cafe",
            "type":"Food & Drink"
        }
    ],
    "sg:phone":"+61 2 9319 2653",
    "sg:postcode":"2015",
    "sg:province":"NSW",
    "wof:name":"Big George's Cafe",
    "wof:placetype":"venue"
},
  "geometry": {"coordinates":[151.20187377900001,-33.9111671448],"type":"Point"}
}