{
  "type": "Feature",
  "properties": {
    "addr:full":"74a Liverpool St Hobart TAS 7000",
    "addr:housenumber":"74a",
    "addr:postcode":"7000",
    "addr:street":"Liverpool St",
    "iso:country":"AU",
    "sg:address":"74a Liverpool St",
    "sg:city":"Hobart",
    "sg:classifiers":[
        {
            "category":"Travel",
            "subcategory":"Travel Agent",
            "type":"Entertainment"
        }
    ],
    "sg:phone":"+61 3 6234 3711",
    "sg:postcode":"7000",
    "sg:province":"TAS",
    "sg:tags":[
        "consultant"
    ],
    "wof:name":"American Express Travel Services",
    "wof:placetype":"venue"
},
  "geometry": {"coordinates":[147.32754516599999,-42.8811531067],"type":"Point"}
}