{
  "type": "Feature",
  "properties": {
    "addr:full":"Unit 2B/ 1 High Rd Bethania QLD 4205",
    "addr:housenumber":"unit 2b / 1",
    "addr:postcode":"4205",
    "addr:street":"High Rd",
    "iso:country":"AU",
    "sg:address":"Unit 2B/ 1 High Rd",
    "sg:city":"Bethania",
    "sg:classifiers":[
        {
            "category":"Utilities",
            "subcategory":"Electric",
            "type":"Services"
        }
    ],
    "sg:phone":"+61 7 3805 7801",
    "sg:postcode":"4205",
    "sg:province":"QLD",
    "sg:tags":[
        "electrical",
        "contractor"
    ],
    "wof:name":"JAJ Systems",
    "wof:placetype":"venue"
},
  "geometry": {"coordinates":[153.155685425,-27.6962337494],"type":"Point"}
}