{
  "type": "Feature",
  "properties": {
    "iso:country":"AU",
    "sg:address":"133 King William Rd",
    "sg:city":"Hyde Park",
    "sg:classifiers":[
        {
            "category":"Education",
            "subcategory":"Junior College",
            "type":"Public Place"
        }
    ],
    "sg:phone":"+61 8 8357 9066",
    "sg:postcode":"5061",
    "sg:province":"SA",
    "sg:tags":[
        "wholesaler",
        "school",
        "mfrs",
        "uniform"
    ],
    "wof:name":"Sandy Nelson Teamwear",
    "wof:placetype":"venue"
},
  "geometry": {"coordinates":[138.600341797,-34.9561080933],"type":"Point"}
}