{
  "type": "Feature",
  "properties": {
    "iso:country":"AU",
    "sg:address":"435 Barkly St",
    "sg:city":"Footscray",
    "sg:classifiers":[
        {
            "category":"Autos & Motor Vehicles",
            "subcategory":"Automobile Sales",
            "type":"Retail Goods"
        }
    ],
    "sg:phone":"+61 3 9687 4222",
    "sg:postcode":"3011",
    "sg:province":"VIC",
    "sg:tags":[
        "car",
        "new"
    ],
    "wof:name":"HSV",
    "wof:placetype":"venue"
},
  "geometry": {"coordinates":[144.88461303700001,-37.7983055115],"type":"Point"}
}