{
  "type": "Feature",
  "properties": {
    "addr:full":"2 Menton Crt Avondale Heights VIC 3034",
    "addr:housenumber":"2",
    "addr:postcode":"3034",
    "addr:street":"Menton Crt",
    "iso:country":"AU",
    "sg:address":"2 Menton Crt",
    "sg:city":"Avondale Heights",
    "sg:classifiers":[
        {
            "category":"Utilities",
            "subcategory":"Electric",
            "type":"Services"
        }
    ],
    "sg:phone":"+61 3 9337 2187",
    "sg:postcode":"3034",
    "sg:province":"VIC",
    "sg:tags":[
        "electrical",
        "contractor"
    ],
    "wof:name":"Artt Electrics",
    "wof:placetype":"venue"
},
  "geometry": {"coordinates":[144.86862199999999,-37.755833],"type":"Point"}
}