{
  "type": "Feature",
  "properties": {
    "iso:country":"AU",
    "sg:address":"201 Fulham Rd",
    "sg:city":"Fairfield",
    "sg:classifiers":[
        {
            "category":"Wholesale",
            "subcategory":"Toys & Hobbies",
            "type":"Manufacturing & Wholesale Goods"
        }
    ],
    "sg:phone":"+61 3 9499 6000",
    "sg:postcode":"3078",
    "sg:province":"VIC",
    "wof:name":"Metro Kids",
    "wof:placetype":"venue"
},
  "geometry": {"coordinates":[145.028076172,-37.7680702209],"type":"Point"}
}