{
  "type": "Feature",
  "properties": {
    "addr:full":"1 Seabeach Pde North Shore VIC 3214",
    "addr:housenumber":"1",
    "addr:postcode":"3214",
    "addr:street":"Seabeach Pde",
    "iso:country":"AU",
    "sg:address":"1 Seabeach Pde",
    "sg:city":"North Shore",
    "sg:classifiers":[
        {
            "category":"Fast Food",
            "type":"Food & Drink"
        }
    ],
    "sg:phone":"+61 3 5278 3149",
    "sg:postcode":"3214",
    "sg:province":"VIC",
    "sg:tags":[
        "away",
        "take"
    ],
    "wof:name":"Seabeach Sandwich Bar",
    "wof:placetype":"venue"
},
  "geometry": {"coordinates":[144.371551514,-38.1001739502],"type":"Point"}
}