{
  "type": "Feature",
  "properties": {
    "addr:full":"Cnr Maitland Rd & Valencia St Mayfield NSW 2304",
    "addr:postcode":"2304",
    "addr:street":"Cnr Maitland Rd & Valencia St",
    "iso:country":"AU",
    "sg:address":"Cnr Maitland Rd & Valencia St",
    "sg:city":"Mayfield",
    "sg:classifiers":[
        {
            "category":"Food & Beverages",
            "subcategory":"Supermarket",
            "type":"Retail Goods"
        }
    ],
    "sg:phone":"+61 2 4967 6400",
    "sg:postcode":"2304",
    "sg:province":"NSW",
    "sg:tags":[
        "grocery",
        "store"
    ],
    "wof:name":"Woolworths Ltd",
    "wof:placetype":"venue"
},
  "geometry": {"coordinates":[151.73826599099999,-32.8985939026],"type":"Point"}
}