{
  "type": "Feature",
  "properties": {
    "addr:full":"6 Dunoon Crt Mulgrave VIC 3170",
    "addr:housenumber":"6",
    "addr:postcode":"3170",
    "addr:street":"Dunoon Crt",
    "iso:country":"AU",
    "sg:address":"6 Dunoon Crt",
    "sg:city":"Mulgrave",
    "sg:classifiers":[
        {
            "category":"Manufacturing",
            "subcategory":"Jewelry",
            "type":"Manufacturing & Wholesale Goods"
        }
    ],
    "sg:phone":"+61 3 9547 5333",
    "sg:postcode":"3170",
    "sg:province":"VIC",
    "sg:tags":[
        "mfrg",
        "jeweller"
    ],
    "wof:name":"Brandon Jewellery Manufacturers",
    "wof:placetype":"venue"
},
  "geometry": {"coordinates":[145.16111755399999,-37.9328269958],"type":"Point"}
}