{
  "type": "Feature",
  "properties": {
    "addr:full":"Shop 7 Dee Why Square 26 Oaks Ave Dee Why NSW 2099",
    "addr:housenumber":"shop 7;26",
    "addr:postcode":"2099",
    "addr:street":"Dee Why Square;Oaks Ave",
    "iso:country":"AU",
    "sg:address":"Shop 7 Dee Why Square 26 Oaks Ave",
    "sg:city":"Dee Why",
    "sg:classifiers":[
        {
            "category":"Food & Beverages",
            "subcategory":"Bakery",
            "type":"Retail Goods"
        }
    ],
    "sg:phone":"+61 2 9981 2250",
    "sg:postcode":"2099",
    "sg:province":"NSW",
    "sg:tags":[
        "baker"
    ],
    "wof:name":"Empanadas & Pies",
    "wof:placetype":"venue"
},
  "geometry": {"coordinates":[151.288375855,-33.7536239624],"type":"Point"}
}