{
  "type": "Feature",
  "properties": {
    "addr:full":"26 Redden St Cairns QLD 4870",
    "addr:housenumber":"26",
    "addr:postcode":"4870",
    "addr:street":"Redden St",
    "iso:country":"AU",
    "sg:address":"26 Redden St",
    "sg:city":"Cairns",
    "sg:classifiers":[
        {
            "category":"Communications",
            "subcategory":"News Services",
            "type":"Services"
        }
    ],
    "sg:phone":"+61 7 4035 5566",
    "sg:postcode":"4870",
    "sg:province":"QLD",
    "sg:tags":[
        "information",
        "tourist",
        "attractions"
    ],
    "wof:name":"Down Under Tours Australia",
    "wof:placetype":"venue"
},
  "geometry": {"coordinates":[145.766555786,-16.9459667206],"type":"Point"}
}