{
  "type": "Feature",
  "properties": {
    "addr:full":"108 Wentworth St Port Kembla NSW 2505",
    "addr:housenumber":"108",
    "addr:postcode":"2505",
    "addr:street":"Wentworth St",
    "iso:country":"AU",
    "sg:address":"108 Wentworth St",
    "sg:city":"Port Kembla",
    "sg:classifiers":[
        {
            "category":"Wholesale",
            "subcategory":"Machinery & Supplies",
            "type":"Manufacturing & Wholesale Goods"
        }
    ],
    "sg:phone":"+61 2 4274 3001",
    "sg:postcode":"2505",
    "sg:province":"NSW",
    "sg:tags":[
        "equipment",
        "welding"
    ],
    "wof:name":"Ryan P J Engineering",
    "wof:placetype":"venue"
},
  "geometry": {"coordinates":[150.90316799999999,-34.482281],"type":"Point"}
}