{
  "type": "Feature",
  "properties": {
    "addr:full":"Unit 4, 14 Bent St St Marys NSW 2760",
    "addr:housenumber":"14",
    "addr:postcode":"2760",
    "addr:street":"Bent St",
    "iso:country":"AU",
    "sg:address":"Unit 4, 14 Bent St",
    "sg:city":"St Marys",
    "sg:phone":"+61 2 4739 8859",
    "sg:postcode":"2760",
    "sg:province":"NSW",
    "wof:name":"Gutter Tailors Pty Ltd",
    "wof:placetype":"venue"
},
  "geometry": {"coordinates":[150.77543640100001,-33.749004364],"type":"Point"}
}