{
  "type": "Feature",
  "properties": {
    "addr:full":"34 Takalvan St Bundaberg QLD 4670",
    "addr:housenumber":"34",
    "addr:postcode":"4670",
    "addr:street":"Takalvan St",
    "iso:country":"AU",
    "sg:address":"34 Takalvan St",
    "sg:city":"Bundaberg",
    "sg:classifiers":[
        {
            "category":"Transit Center",
            "subcategory":"Freight",
            "type":"Transportation"
        }
    ],
    "sg:phone":"+61 7 4151 6251",
    "sg:postcode":"4670",
    "sg:province":"QLD",
    "sg:tags":[
        "forklift",
        "truck"
    ],
    "wof:name":"Landoway Pty Ltd",
    "wof:placetype":"venue"
},
  "geometry": {"coordinates":[152.32974243199999,-24.8780422211],"type":"Point"}
}