{
  "type": "Feature",
  "properties": {
    "addr:full":"16 Glenelg St Raymond Terrace NSW 2324",
    "addr:housenumber":"16",
    "addr:postcode":"2324",
    "addr:street":"Glenelg St",
    "iso:country":"AU",
    "sg:address":"16 Glenelg St",
    "sg:city":"Raymond Terrace",
    "sg:classifiers":[
        {
            "category":"Health Services",
            "subcategory":"Dentist",
            "type":"Services"
        }
    ],
    "sg:phone":"+61 2 4987 3410",
    "sg:postcode":"2324",
    "sg:province":"NSW",
    "wof:name":"Wattbright Amanda",
    "wof:placetype":"venue"
},
  "geometry": {"coordinates":[151.74354553200001,-32.7656974792],"type":"Point"}
}