{
  "type": "Feature",
  "properties": {
    "iso:country":"AU",
    "sg:address":"Thornton Pl",
    "sg:city":"Gooseberry Hill",
    "sg:classifiers":[
        {
            "category":"Insurance",
            "subcategory":"Life Insurance",
            "type":"Services"
        }
    ],
    "sg:phone":"+61 418 923 050",
    "sg:postcode":"6076",
    "sg:province":"WA",
    "wof:name":"Tomazin Tony & Associates",
    "wof:placetype":"venue"
},
  "geometry": {"coordinates":[116.05091095,-31.9615936279],"type":"Point"}
}