{
  "type": "Feature",
  "properties": {
    "iso:country":"AU",
    "sg:address":"76 First Rd",
    "sg:city":"Berkshire Park",
    "sg:classifiers":[
        {
            "category":"Building & Trades",
            "subcategory":"Construction",
            "type":"Services"
        }
    ],
    "sg:phone":"+61 2 4572 5261",
    "sg:postcode":"2765",
    "sg:province":"NSW",
    "sg:tags":[
        "earth",
        "excavating",
        "moving",
        "contractor"
    ],
    "wof:name":"Wormleaton K R Grader Hire",
    "wof:placetype":"venue"
},
  "geometry": {"coordinates":[150.79739379899999,-33.6671257019],"type":"Point"}
}