{
  "type": "Feature",
  "properties": {
    "iso:country":"AU",
    "sg:address":"201 Newton Rd",
    "sg:city":"Wetherill Park",
    "sg:classifiers":[
        {
            "category":"Utilities",
            "subcategory":"Refuse",
            "type":"Services"
        }
    ],
    "sg:phone":"+61 2 9756 1575",
    "sg:postcode":"2164",
    "sg:province":"NSW",
    "sg:tags":[
        "remover",
        "rubbish"
    ],
    "wof:name":"Builders Bins",
    "wof:placetype":"venue"
},
  "geometry": {"coordinates":[150.89189148,-33.8389968872],"type":"Point"}
}