{
  "type": "Feature",
  "properties": {
    "addr:full":"75 Willow St Malvern VIC 3144",
    "addr:housenumber":"75",
    "addr:postcode":"3144",
    "addr:street":"Willow St",
    "iso:country":"AU",
    "sg:address":"75 Willow St",
    "sg:city":"Malvern",
    "sg:classifiers":[
        {
            "category":"Utilities",
            "subcategory":"Electric",
            "type":"Services"
        }
    ],
    "sg:phone":"+61 3 9822 5307",
    "sg:postcode":"3144",
    "sg:province":"VIC",
    "sg:tags":[
        "electrical",
        "contractor"
    ],
    "wof:name":"A. AAABA Home Phone Cabeling",
    "wof:placetype":"venue"
},
  "geometry": {"coordinates":[145.03811645499999,-37.8494949341],"type":"Point"}
}