{
  "type": "Feature",
  "properties": {
    "addr:full":"44 Mews Rd Fremantle WA 6160",
    "addr:housenumber":"44",
    "addr:postcode":"6160",
    "addr:street":"Mews Rd",
    "iso:country":"AU",
    "sg:address":"44 Mews Rd",
    "sg:city":"Fremantle",
    "sg:classifiers":[
        {
            "category":"Restaurant",
            "type":"Food & Drink"
        }
    ],
    "sg:phone":"+61 8 9430 5005",
    "sg:postcode":"6160",
    "sg:province":"WA",
    "wof:name":"Char Char Bull",
    "wof:placetype":"venue"
},
  "geometry": {"coordinates":[115.74793200000001,-32.060345],"type":"Point"}
}