{
  "type": "Feature",
  "properties": {
    "addr:full":"U4/ 2 Victoria Crs Mt Barker SA 5251",
    "addr:housenumber":"2",
    "addr:postcode":"5251",
    "addr:street":"U4 /;Victoria Crs Mt",
    "iso:country":"AU",
    "sg:address":"U4/ 2 Victoria Crs",
    "sg:city":"Mt Barker",
    "sg:classifiers":[
        {
            "category":"Ice Cream",
            "type":"Food & Drink"
        }
    ],
    "sg:phone":"+61 8 8391 4370",
    "sg:postcode":"5251",
    "sg:province":"SA",
    "sg:tags":[
        "specialised",
        "fitting",
        "lady",
        "wear"
    ],
    "wof:name":"Dressing Station",
    "wof:placetype":"venue"
},
  "geometry": {"coordinates":[138.867645264,-35.0770454407],"type":"Point"}
}