{
  "type": "Feature",
  "properties": {
    "addr:full":"180 Warrigal Rd Camberwell VIC 3124",
    "addr:housenumber":"180",
    "addr:postcode":"3124",
    "addr:street":"Warrigal Rd",
    "iso:country":"AU",
    "sg:address":"180 Warrigal Rd",
    "sg:city":"Camberwell",
    "sg:classifiers":[
        {
            "category":"Health Services",
            "subcategory":"Doctor",
            "type":"Services"
        }
    ],
    "sg:phone":"+61 3 9808 0041",
    "sg:postcode":"3124",
    "sg:province":"VIC",
    "sg:tags":[
        "medical",
        "practitioner"
    ],
    "wof:name":"Baxter C M Dr",
    "wof:placetype":"venue"
},
  "geometry": {"coordinates":[145.09666442899999,-37.843837738],"type":"Point"}
}