{
  "type": "Feature",
  "properties": {
    "addr:full":"310 Skye Point Rd Coal Point NSW 2283",
    "addr:housenumber":"310",
    "addr:postcode":"2283",
    "addr:street":"Skye Point Rd",
    "iso:country":"AU",
    "sg:address":"310 Skye Point Rd",
    "sg:city":"Coal Point",
    "sg:classifiers":[
        {
            "category":"Utilities",
            "subcategory":"Electric",
            "type":"Services"
        }
    ],
    "sg:phone":"+61 414 254 556",
    "sg:postcode":"2283",
    "sg:province":"NSW",
    "sg:tags":[
        "electrical",
        "contractor"
    ],
    "wof:name":"Anything Electrical Newcastle",
    "wof:placetype":"venue"
},
  "geometry": {"coordinates":[151.615631103,-33.0452613831],"type":"Point"}
}