{
  "type": "Feature",
  "properties": {
    "addr:full":"143 King St Buderim QLD 4556",
    "addr:housenumber":"143",
    "addr:postcode":"4556",
    "addr:street":"King St",
    "iso:country":"AU",
    "sg:address":"143 King St",
    "sg:city":"Buderim",
    "sg:classifiers":[
        {
            "category":"Retail",
            "subcategory":"Auto Repair",
            "type":"Services"
        }
    ],
    "sg:phone":"+61 7 5445 8127",
    "sg:postcode":"4556",
    "sg:province":"QLD",
    "sg:tags":[
        "repairer",
        "motor",
        "engineer"
    ],
    "wof:name":"Buderim Garage",
    "wof:placetype":"venue"
},
  "geometry": {"coordinates":[153.07148742699999,-26.6841335297],"type":"Point"}
}