{
  "type": "Feature",
  "properties": {
    "addr:full":"26 Franklin St Brooklyn TAS 7320",
    "addr:housenumber":"26",
    "addr:postcode":"7320",
    "addr:street":"Franklin St",
    "iso:country":"AU",
    "sg:address":"26 Franklin St",
    "sg:city":"Brooklyn",
    "sg:classifiers":[
        {
            "category":"Arena",
            "subcategory":"Sports Club",
            "type":"Entertainment"
        }
    ],
    "sg:phone":"+61 3 6431 6018",
    "sg:postcode":"7320",
    "sg:province":"TAS",
    "sg:tags":[
        "defence",
        "supply",
        "self",
        "instruction",
        "martial art"
    ],
    "wof:name":"Tasmanian Martial Arts Council",
    "wof:placetype":"venue"
},
  "geometry": {"coordinates":[145.90609699999999,-41.072662],"type":"Point"}
}