{
  "type": "Feature",
  "properties": {
    "addr:full":"42 Dundas Rd Inglewood WA 6052",
    "addr:housenumber":"42",
    "addr:postcode":"6052",
    "addr:street":"Dundas Rd",
    "iso:country":"AU",
    "sg:address":"42 Dundas Rd",
    "sg:city":"Inglewood",
    "sg:classifiers":[
        {
            "category":"Health Services",
            "subcategory":"Health Practitioner",
            "type":"Services"
        }
    ],
    "sg:phone":"+61 8 9272 2850",
    "sg:postcode":"6052",
    "sg:province":"WA",
    "sg:tags":[
        "naturopath"
    ],
    "wof:name":"Carruthers Gordon R",
    "wof:placetype":"venue"
},
  "geometry": {"coordinates":[115.884689331,-31.9181194305],"type":"Point"}
}