{
  "type": "Feature",
  "properties": {
    "addr:full":"71 Shirley St Byron Bay NSW 2481",
    "addr:housenumber":"71",
    "addr:postcode":"2481",
    "addr:street":"Shirley St",
    "iso:country":"AU",
    "sg:address":"71 Shirley St",
    "sg:city":"Byron Bay",
    "sg:classifiers":[
        {
            "category":"Health Services",
            "subcategory":"Health Practitioner",
            "type":"Services"
        }
    ],
    "sg:phone":"+61 2 6685 8538",
    "sg:postcode":"2481",
    "sg:province":"NSW",
    "sg:tags":[
        "naturopath"
    ],
    "wof:name":"House Of Wellbeing",
    "wof:placetype":"venue"
},
  "geometry": {"coordinates":[153.60386657699999,-28.6395645142],"type":"Point"}
}