{
  "type": "Feature",
  "properties": {
    "iso:country":"AU",
    "sg:address":"Bosworth St",
    "sg:city":"Bairnsdale",
    "sg:classifiers":[
        {
            "category":"Home & Garden",
            "subcategory":"Building Materials",
            "type":"Retail Goods"
        }
    ],
    "sg:phone":"+61 3 5152 4333",
    "sg:postcode":"3875",
    "sg:province":"VIC",
    "sg:tags":[
        "pre-mixed",
        "concrete"
    ],
    "wof:name":"Pioneer Concrete",
    "wof:placetype":"venue"
},
  "geometry": {"coordinates":[147.61273193400001,-37.839012146],"type":"Point"}
}