{
  "type": "Feature",
  "properties": {
    "addr:full":"Hoyts Highpoint, Highpoint Shopng Cntr Rosamond Rd Maribyrnong VIC 3032",
    "addr:postcode":"3032",
    "addr:street":"Rosamond Rd",
    "iso:country":"AU",
    "sg:address":"Hoyts Highpoint, Highpoint Shopng Cntr Rosamond Rd",
    "sg:city":"Maribyrnong",
    "sg:classifiers":[
        {
            "category":"Cinema",
            "subcategory":"Movie Theater",
            "type":"Entertainment"
        }
    ],
    "sg:phone":"+61 3 9318 6800",
    "sg:postcode":"3032",
    "sg:province":"VIC",
    "wof:name":"Hoyts",
    "wof:placetype":"venue"
},
  "geometry": {"coordinates":[144.88632200000001,-37.771435],"type":"Point"}
}