{
  "type": "Feature",
  "properties": {
    "addr:full":"201 Ramsay St Haberfield NSW 2045",
    "addr:housenumber":"201",
    "addr:postcode":"2045",
    "addr:street":"Ramsay St",
    "iso:country":"AU",
    "sg:address":"201 Ramsay St",
    "sg:city":"Haberfield",
    "sg:classifiers":[
        {
            "category":"Professional",
            "subcategory":"Accounting & Tax Preparation",
            "type":"Services"
        }
    ],
    "sg:phone":"+61 2 9798 4837",
    "sg:postcode":"2045",
    "sg:province":"NSW",
    "sg:tags":[
        "accountant",
        "auditor"
    ],
    "wof:name":"Tax Management Consultants Pty Ltd",
    "wof:placetype":"venue"
},
  "geometry": {"coordinates":[151.136673,-33.877541],"type":"Point"}
}