{
  "type": "Feature",
  "properties": {
    "addr:full":"33 Cambria Rd Keysborough VIC 3173",
    "addr:housenumber":"33",
    "addr:postcode":"3173",
    "addr:street":"Cambria Rd",
    "iso:country":"AU",
    "sg:address":"33 Cambria Rd",
    "sg:city":"Keysborough",
    "sg:classifiers":[
        {
            "category":"Wholesale",
            "subcategory":"Auto Parts",
            "type":"Manufacturing & Wholesale Goods"
        }
    ],
    "sg:phone":"+61 3 9798 3333",
    "sg:postcode":"3173",
    "sg:province":"VIC",
    "sg:tags":[
        "recyclers"
    ],
    "wof:name":"Volvsaab",
    "wof:placetype":"venue"
},
  "geometry": {"coordinates":[145.189697266,-37.9896507263],"type":"Point"}
}