{
  "type": "Feature",
  "properties": {
    "addr:full":"205 Pitt Town Rd Kenthurst NSW 2156",
    "addr:housenumber":"205",
    "addr:postcode":"2156",
    "addr:street":"Pitt Town Rd",
    "iso:country":"AU",
    "sg:address":"205 Pitt Town Rd",
    "sg:city":"Kenthurst",
    "sg:classifiers":[
        {
            "category":"Food & Beverages",
            "subcategory":"Fruits & Vegetables",
            "type":"Retail Goods"
        }
    ],
    "sg:phone":"+61 412 409 300",
    "sg:postcode":"2156",
    "sg:province":"NSW",
    "sg:tags":[
        "grower"
    ],
    "wof:name":"Hydro King",
    "wof:placetype":"venue"
},
  "geometry": {"coordinates":[150.95214843799999,-33.6274414062],"type":"Point"}
}