{
  "type": "Feature",
  "properties": {
    "addr:full":"369 Bahrs Scrub Rd Beenleigh QLD 4207",
    "addr:housenumber":"369",
    "addr:postcode":"4207",
    "addr:street":"Bahrs Scrub Rd",
    "iso:country":"AU",
    "sg:address":"369 Bahrs Scrub Rd",
    "sg:city":"Beenleigh",
    "sg:classifiers":[
        {
            "category":"Mining & Drilling",
            "type":"Manufacturing & Wholesale Goods"
        }
    ],
    "sg:phone":"+61 7 3804 0081",
    "sg:postcode":"4207",
    "sg:province":"QLD",
    "sg:tags":[
        "boring",
        "contractor"
    ],
    "wof:name":"Rosentreter Wayne & Wendy",
    "wof:placetype":"venue"
},
  "geometry": {"coordinates":[153.18052673299999,-27.74077034],"type":"Point"}
}