{
  "type": "Feature",
  "properties": {
    "iso:country":"AU",
    "sg:address":"26 Action St",
    "sg:city":"Noosaville",
    "sg:classifiers":[
        {
            "category":"Autos & Motor Vehicles",
            "subcategory":"Boat Sales",
            "type":"Retail Goods"
        }
    ],
    "sg:phone":"+61 7 5440 5222",
    "sg:postcode":"4566",
    "sg:province":"QLD",
    "sg:tags":[
        "yacht"
    ],
    "wof:name":"Noosa Boatique",
    "wof:placetype":"venue"
},
  "geometry": {"coordinates":[153.04476928700001,-26.4097480774],"type":"Point"}
}