{
  "type": "Feature",
  "properties": {
    "iso:country":"AU",
    "sg:address":"12 Hillcrest Ave",
    "sg:city":"Ashfield",
    "sg:classifiers":[
        {
            "category":"Building & Trades",
            "subcategory":"Construction",
            "type":"Services"
        }
    ],
    "sg:phone":"+61 2 9550 0693",
    "sg:postcode":"2131",
    "sg:province":"NSW",
    "sg:tags":[
        "contractor"
    ],
    "wof:name":"Maintenance Trades",
    "wof:placetype":"venue"
},
  "geometry": {"coordinates":[151.12625122099999,-33.8983039856],"type":"Point"}
}