{
  "type": "Feature",
  "properties": {
    "iso:country":"AU",
    "sg:address":"24 Marsden St",
    "sg:city":"Boorowa",
    "sg:classifiers":[
        {
            "category":"Shopping",
            "type":"Retail Goods"
        }
    ],
    "sg:phone":"+61 2 6385 3666",
    "sg:postcode":"2586",
    "sg:province":"NSW",
    "sg:tags":[
        "agent",
        "stock"
    ],
    "wof:name":"Landmark Operations Limited",
    "wof:placetype":"venue"
},
  "geometry": {"coordinates":[148.71638488799999,-34.4373283386],"type":"Point"}
}