{
  "type": "Feature",
  "properties": {
    "iso:country":"AU",
    "sg:address":"99 Mulgowie Rd",
    "sg:city":"Buaraba",
    "sg:classifiers":[
        {
            "category":"Wholesale",
            "subcategory":"Scrap",
            "type":"Manufacturing & Wholesale Goods"
        }
    ],
    "sg:phone":"+61 7 5426 4769",
    "sg:postcode":"4311",
    "sg:province":"QLD",
    "sg:tags":[
        "merchant",
        "metal"
    ],
    "wof:name":"Shift-eze",
    "wof:placetype":"venue"
},
  "geometry": {"coordinates":[152.377227783,-27.3661403656],"type":"Point"}
}