{
  "type": "Feature",
  "properties": {
    "addr:full":"935 Gembrook Rd Hoddles Creek VIC 3139",
    "addr:housenumber":"935",
    "addr:postcode":"3139",
    "addr:street":"Gembrook Rd",
    "iso:country":"AU",
    "sg:address":"935 Gembrook Rd",
    "sg:city":"Hoddles Creek",
    "sg:classifiers":[
        {
            "category":"Utilities",
            "type":"Services"
        }
    ],
    "sg:phone":"+61 3 5967 4245",
    "sg:postcode":"3139",
    "sg:province":"VIC",
    "sg:tags":[
        "refrigeration",
        "industrial",
        "commercial",
        "retail"
    ],
    "wof:name":"D K Turner Refrigeration",
    "wof:placetype":"venue"
},
  "geometry": {"coordinates":[145.68496704099999,-37.7555580139],"type":"Point"}
}