{
  "type": "Feature",
  "properties": {
    "addr:full":"16 Dunsford St Lancefield VIC 3435",
    "addr:housenumber":"16",
    "addr:postcode":"3435",
    "addr:street":"Dunsford St",
    "iso:country":"AU",
    "sg:address":"16 Dunsford St",
    "sg:city":"Lancefield",
    "sg:classifiers":[
        {
            "category":"Education",
            "subcategory":"Kindergarten",
            "type":"Public Place"
        }
    ],
    "sg:phone":"+61 3 5429 1388",
    "sg:postcode":"3435",
    "sg:province":"VIC",
    "sg:tags":[
        "pre-schools"
    ],
    "wof:name":"Lancefield Kindergarten",
    "wof:placetype":"venue"
},
  "geometry": {"coordinates":[144.73324585,-37.2780532837],"type":"Point"}
}