{
  "type": "Feature",
  "properties": {
    "addr:full":"22 Cedar St Cooroy QLD 4563",
    "addr:housenumber":"22",
    "addr:postcode":"4563",
    "addr:street":"Cedar St",
    "iso:country":"AU",
    "sg:address":"22 Cedar St",
    "sg:city":"Cooroy",
    "sg:classifiers":[
        {
            "category":"Professional",
            "subcategory":"Accounting & Tax Preparation",
            "type":"Services"
        }
    ],
    "sg:phone":"+61 7 5442 6228",
    "sg:postcode":"4563",
    "sg:province":"QLD",
    "sg:tags":[
        "accountant",
        "auditor"
    ],
    "wof:name":"Billinghurst Martin Pty Ltd",
    "wof:placetype":"venue"
},
  "geometry": {"coordinates":[152.912033081,-26.4190444946],"type":"Point"}
}