{
  "type": "Feature",
  "properties": {
    "addr:full":"Hopetoun Rd Ravensthorpe WA 6346",
    "addr:postcode":"6346",
    "addr:street":"Hopetoun Rd",
    "iso:country":"AU",
    "sg:address":"Hopetoun Rd",
    "sg:city":"Ravensthorpe",
    "sg:classifiers":[
        {
            "category":"Home & Garden",
            "subcategory":"Garden Supply",
            "type":"Retail Goods"
        }
    ],
    "sg:phone":"+61 8 9872 0025",
    "sg:postcode":"6346",
    "sg:province":"WA",
    "sg:tags":[
        "fertilizer"
    ],
    "wof:name":"Matrix Minerals Ltd",
    "wof:placetype":"venue"
},
  "geometry": {"coordinates":[120.045776,-33.58176],"type":"Point"}
}