{
  "type": "Feature",
  "properties": {
    "iso:country":"AU",
    "sg:address":"Lot 1 Main North Rd",
    "sg:city":"Evanston South",
    "sg:classifiers":[
        {
            "category":"Building & Trades",
            "subcategory":"Construction",
            "type":"Services"
        }
    ],
    "sg:phone":"+61 8 8523 1490",
    "sg:postcode":"5116",
    "sg:province":"SA",
    "sg:tags":[
        "pool",
        "swimming"
    ],
    "wof:name":"All Class Pools & Spas",
    "wof:placetype":"venue"
},
  "geometry": {"coordinates":[138.71238708499999,-34.6535301208],"type":"Point"}
}