{
  "type": "Feature",
  "properties": {
    "addr:full":"Shop 2 28 Blackburn Rd Blackburn VIC 3130",
    "addr:housenumber":"shop;28",
    "addr:postcode":"3130",
    "addr:street":"Blackburn Rd",
    "iso:country":"AU",
    "sg:address":"Shop 2 28 Blackburn Rd",
    "sg:city":"Blackburn",
    "sg:classifiers":[
        {
            "category":"Cafe",
            "type":"Food & Drink"
        }
    ],
    "sg:phone":"+61 3 9894 7652",
    "sg:postcode":"3130",
    "sg:province":"VIC",
    "wof:name":"The Jacaranda Tree",
    "wof:placetype":"venue"
},
  "geometry": {"coordinates":[145.15252685600001,-37.8215751648],"type":"Point"}
}