{
  "type": "Feature",
  "properties": {
    "addr:full":"41 Sunhill Rd Mt Waverley VIC 3149",
    "addr:housenumber":"41",
    "addr:postcode":"3149",
    "addr:street":"Sunhill Rd",
    "iso:country":"AU",
    "sg:address":"41 Sunhill Rd",
    "sg:city":"Mt Waverley",
    "sg:classifiers":[
        {
            "category":"Food & Beverages",
            "subcategory":"Groceries & Convenience Stores",
            "type":"Retail Goods"
        }
    ],
    "sg:phone":"+61 3 9807 1156",
    "sg:postcode":"3149",
    "sg:province":"VIC",
    "wof:name":"Morel Imports",
    "wof:placetype":"venue"
},
  "geometry": {"coordinates":[145.12792968799999,-37.8666801453],"type":"Point"}
}