{
  "type": "Feature",
  "properties": {
    "addr:full":"1 Grace St Lake Cargelligo NSW 2672",
    "addr:housenumber":"1",
    "addr:postcode":"2672",
    "addr:street":"Grace St",
    "iso:country":"AU",
    "sg:address":"1 Grace St",
    "sg:city":"Lake Cargelligo",
    "sg:classifiers":[
        {
            "category":"Professional",
            "subcategory":"Detective & Security Services",
            "type":"Services"
        }
    ],
    "sg:phone":"+61 2 6898 2088",
    "sg:postcode":"2672",
    "sg:province":"NSW",
    "sg:tags":[
        "domestic",
        "alarm",
        "commercial",
        "burglar"
    ],
    "wof:name":"Regal Electro",
    "wof:placetype":"venue"
},
  "geometry": {"coordinates":[146.370803833,-33.305847168],"type":"Point"}
}