{
  "type": "Feature",
  "properties": {
    "addr:full":"Shop 3 Park Ave Coffs Harbour NSW 2450",
    "addr:housenumber":"shop 3",
    "addr:postcode":"2450",
    "addr:street":"Park Ave",
    "iso:country":"AU",
    "sg:address":"Shop 3 Park Ave",
    "sg:city":"Coffs Harbour",
    "sg:classifiers":[
        {
            "category":"Wholesale",
            "subcategory":"Apparel",
            "type":"Manufacturing & Wholesale Goods"
        }
    ],
    "sg:phone":"+61 2 6651 6965",
    "sg:postcode":"2450",
    "sg:province":"NSW",
    "sg:tags":[
        "wholesaler",
        "mfrs",
        "sportswear",
        "women's"
    ],
    "wof:name":"Cheeki Sportswear",
    "wof:placetype":"venue"
},
  "geometry": {"coordinates":[153.11364699999999,-30.297699],"type":"Point"}
}