{
  "type": "Feature",
  "properties": {
    "addr:full":"93 Prince Edward St Malabar NSW 2036",
    "addr:housenumber":"93",
    "addr:postcode":"2036",
    "addr:street":"Prince Edward St",
    "iso:country":"AU",
    "sg:address":"93 Prince Edward St",
    "sg:city":"Malabar",
    "sg:classifiers":[
        {
            "category":"Professional",
            "subcategory":"Computer Services",
            "type":"Services"
        }
    ],
    "sg:phone":"+61 418 465 353",
    "sg:postcode":"2036",
    "sg:province":"NSW",
    "sg:tags":[
        "package",
        "software"
    ],
    "wof:name":"Logistics Information Systems",
    "wof:placetype":"venue"
},
  "geometry": {"coordinates":[151.250686645,-33.9672012329],"type":"Point"}
}