{
  "type": "Feature",
  "properties": {
    "addr:full":"Unit 1 35-37 Glossop St St Marys NSW 2760",
    "addr:housenumber":"35-37",
    "addr:postcode":"2760",
    "addr:street":"Glossop St",
    "iso:country":"AU",
    "sg:address":"Unit 1 35-37 Glossop St St",
    "sg:city":"Marys",
    "sg:classifiers":[
        {
            "category":"Wholesale",
            "subcategory":"Painting Supplies",
            "type":"Manufacturing & Wholesale Goods"
        }
    ],
    "sg:phone":"+61 2 9833 9655",
    "sg:postcode":"2760",
    "sg:province":"NSW",
    "sg:tags":[
        "equipment",
        "spraying"
    ],
    "wof:name":"JD Spray",
    "wof:placetype":"venue"
},
  "geometry": {"coordinates":[150.77932739299999,-33.757434845],"type":"Point"}
}