{
  "type": "Feature",
  "properties": {
    "addr:full":"24 Peel St Collingwood VIC 3066",
    "addr:housenumber":"24",
    "addr:postcode":"3066",
    "addr:street":"Peel St",
    "iso:country":"AU",
    "sg:address":"24 Peel St",
    "sg:city":"Collingwood",
    "sg:classifiers":[
        {
            "category":"Professional",
            "subcategory":"Accounting & Tax Preparation",
            "type":"Services"
        }
    ],
    "sg:phone":"+61 3 9417 2775",
    "sg:postcode":"3066",
    "sg:province":"VIC",
    "sg:tags":[
        "accountant",
        "auditor"
    ],
    "wof:name":"Mc Cready & Co",
    "wof:placetype":"venue"
},
  "geometry": {"coordinates":[144.984909058,-37.8050193787],"type":"Point"}
}