{
  "type": "Feature",
  "properties": {
    "addr:full":"Cnr Hopetoun & Victoria Sts Kurri Kurri NSW 2327",
    "addr:postcode":"2327",
    "addr:street":"Cnr",
    "iso:country":"AU",
    "sg:address":"Cnr Hopetoun & Victoria Sts",
    "sg:city":"Kurri Kurri",
    "sg:classifiers":[
        {
            "category":"Retail",
            "subcategory":"Veterinary Services",
            "type":"Services"
        }
    ],
    "sg:phone":"+61 2 4937 3799",
    "sg:postcode":"2327",
    "sg:province":"NSW",
    "sg:tags":[
        "surgeon"
    ],
    "wof:name":"Kurri Kurri Veterinary Clinic",
    "wof:placetype":"venue"
},
  "geometry": {"coordinates":[151.48350524899999,-32.8211669922],"type":"Point"}
}