{
  "type": "Feature",
  "properties": {
    "iso:country":"AU",
    "sg:address":"Rose Lane Centre, Sandridge Rd",
    "sg:city":"Bunbury",
    "sg:classifiers":[
        {
            "category":"Utilities",
            "subcategory":"Electric",
            "type":"Services"
        }
    ],
    "sg:phone":"+61 8 9721 3418",
    "sg:postcode":"6230",
    "sg:province":"WA",
    "sg:tags":[
        "tube",
        "lamps",
        "globe"
    ],
    "wof:name":"McCormick's City Lighting",
    "wof:placetype":"venue"
},
  "geometry": {"coordinates":[115.650146,-33.341118],"type":"Point"}
}