{
  "type": "Feature",
  "properties": {
    "iso:country":"AU",
    "sg:address":"7a Yallourn St",
    "sg:city":"Fyshwick",
    "sg:classifiers":[
        {
            "category":"Manufacturing",
            "subcategory":"Furniture",
            "type":"Manufacturing & Wholesale Goods"
        }
    ],
    "sg:phone":"+61 2 6239 1013",
    "sg:postcode":"2609",
    "sg:province":"ACT",
    "sg:tags":[
        "builder",
        "designer",
        "custom"
    ],
    "wof:name":"Trout Design",
    "wof:placetype":"venue"
},
  "geometry": {"coordinates":[149.16995239299999,-35.3331108093],"type":"Point"}
}