{
  "type": "Feature",
  "properties": {
    "iso:country":"AU",
    "sg:address":"PO Box 3214 Broadway",
    "sg:city":"Nedlands",
    "sg:classifiers":[
        {
            "category":"Building & Trades",
            "subcategory":"Construction",
            "type":"Services"
        }
    ],
    "sg:phone":"+61 417 915 997",
    "sg:postcode":"6009",
    "sg:province":"WA",
    "sg:tags":[
        "road",
        "contractor"
    ],
    "wof:name":"Statewide Line Marking",
    "wof:placetype":"venue"
},
  "geometry": {"coordinates":[115.803047,-31.97897],"type":"Point"}
}