{
  "type": "Feature",
  "properties": {
    "iso:country":"AU",
    "sg:address":"11A South Gippsland Hwy",
    "sg:city":"Leongatha",
    "sg:classifiers":[
        {
            "category":"Home & Garden",
            "subcategory":"Building Materials",
            "type":"Retail Goods"
        }
    ],
    "sg:phone":"+61 3 5662 5553",
    "sg:postcode":"3953",
    "sg:province":"VIC",
    "sg:tags":[
        "tile",
        "roofing"
    ],
    "wof:name":"Shield Master Roofing",
    "wof:placetype":"venue"
},
  "geometry": {"coordinates":[145.938552856,-38.4686660767],"type":"Point"}
}