{
  "type": "Feature",
  "properties": {
    "iso:country":"AU",
    "sg:address":"60 Spence Rd",
    "sg:city":"Wavell Heights",
    "sg:classifiers":[
        {
            "category":"Real Estate",
            "subcategory":"Real Estate Agent",
            "type":"Services"
        }
    ],
    "sg:phone":"+61 7 3260 6156",
    "sg:postcode":"4012",
    "sg:province":"QLD",
    "wof:name":"Lewis Rod Real Estate",
    "wof:placetype":"venue"
},
  "geometry": {"coordinates":[153.046264648,-27.3927726746],"type":"Point"}
}