{
  "type": "Feature",
  "properties": {
    "iso:country":"AU",
    "sg:address":"Shops 1 & 2",
    "sg:city":"The Galleria Darwin Mall Darwin",
    "sg:classifiers":[
        {
            "category":"Transit Center",
            "subcategory":"Passenger",
            "type":"Transportation"
        }
    ],
    "sg:phone":"+61 8 8981 2333",
    "sg:postcode":"0800",
    "sg:province":"NT",
    "sg:tags":[
        "wholesaler",
        "mfrs",
        "toiletry",
        "perfume"
    ],
    "wof:name":"Bardens Pharmacy Pty Ltd",
    "wof:placetype":"venue"
},
  "geometry": {"coordinates":[130.84251403799999,-12.4638319016],"type":"Point"}
}