{
  "type": "Feature",
  "properties": {
    "addr:full":"Lvl5/ 203 New South Head Rd Edgecliff NSW 2027",
    "addr:housenumber":"203",
    "addr:postcode":"2027",
    "addr:street":"New South Head Rd",
    "iso:country":"AU",
    "sg:address":"Lvl5/ 203 New South Head Rd",
    "sg:city":"Edgecliff",
    "sg:classifiers":[
        {
            "category":"Professional",
            "subcategory":"Management & Consulting",
            "type":"Services"
        }
    ],
    "sg:phone":"+61 417 437 121",
    "sg:postcode":"2027",
    "sg:province":"NSW",
    "sg:tags":[
        "consultant",
        "migration"
    ],
    "wof:name":"A.M.E.C.",
    "wof:placetype":"venue"
},
  "geometry": {"coordinates":[151.23535156200001,-33.8787155151],"type":"Point"}
}