{
  "type": "Feature",
  "properties": {
    "addr:full":"Cnr The Esplanade & Spence Street Cairns QLD 4870",
    "addr:postcode":"4870",
    "addr:street":"Cnr The Esplanade & Spence Street",
    "iso:country":"AU",
    "sg:address":"Cnr The Esplanade & Spence Street",
    "sg:city":"Cairns",
    "sg:classifiers":[
        {
            "category":"Manufacturing",
            "subcategory":"Food",
            "type":"Manufacturing & Wholesale Goods"
        }
    ],
    "sg:phone":"+61 7 4051 7888",
    "sg:postcode":"4870",
    "sg:province":"QLD",
    "sg:tags":[
        "function",
        "catering"
    ],
    "sg:website":"http://www.pacifichotelcairns.com",
    "wof:name":"Pacific International",
    "wof:placetype":"venue"
},
  "geometry": {"coordinates":[145.75108337399999,-16.9450416565],"type":"Point"}
}