{
  "type": "Feature",
  "properties": {
    "addr:full":"1130 Burke Rd Balwyn North VIC 3104",
    "addr:housenumber":"1130",
    "addr:postcode":"3104",
    "addr:street":"Burke Rd",
    "iso:country":"AU",
    "sg:address":"1130 Burke Rd",
    "sg:city":"Balwyn North",
    "sg:classifiers":[
        {
            "category":"Professional",
            "subcategory":"Engineering",
            "type":"Services"
        }
    ],
    "sg:phone":"+61 3 9859 0444",
    "sg:postcode":"3104",
    "sg:province":"VIC",
    "sg:tags":[
        "consulting",
        "engineer"
    ],
    "wof:name":"Kyrgios John & Associates Pty Ltd",
    "wof:placetype":"venue"
},
  "geometry": {"coordinates":[145.06398010300001,-37.7941436768],"type":"Point"}
}