{
  "type": "Feature",
  "properties": {
    "addr:full":"11 Bellingham St Narellan NSW 2567",
    "addr:housenumber":"11",
    "addr:postcode":"2567",
    "addr:street":"Bellingham St",
    "iso:country":"AU",
    "sg:address":"11 Bellingham St",
    "sg:city":"Narellan",
    "sg:classifiers":[
        {
            "category":"Professional",
            "subcategory":"Engineering",
            "type":"Services"
        }
    ],
    "sg:phone":"+61 2 4647 1328",
    "sg:postcode":"2567",
    "sg:province":"NSW",
    "sg:tags":[
        "diesel",
        "engineer"
    ],
    "wof:name":"J C Diesel",
    "wof:placetype":"venue"
},
  "geometry": {"coordinates":[150.73150634800001,-34.0370063782],"type":"Point"}
}