{
  "type": "Feature",
  "properties": {
    "iso:country":"AU",
    "sg:address":"9 Turley St",
    "sg:city":"Raceview",
    "sg:classifiers":[
        {
            "category":"Retail",
            "subcategory":"Auto Repair",
            "type":"Services"
        }
    ],
    "sg:phone":"+61 7 3281 9474",
    "sg:postcode":"4305",
    "sg:province":"QLD",
    "sg:tags":[
        "beater",
        "painter",
        "panel"
    ],
    "wof:name":"Westside Panel & Paint",
    "wof:placetype":"venue"
},
  "geometry": {"coordinates":[152.758712769,-27.6342487335],"type":"Point"}
}