{
  "type": "Feature",
  "properties": {
    "addr:full":"Units 2- 3, 1 Gesham Way Bomaderry NSW 2541",
    "addr:housenumber":"units 2 3 1",
    "addr:postcode":"2541",
    "addr:street":"Gesham Way",
    "iso:country":"AU",
    "sg:address":"Units 2- 3, 1 Gesham Way",
    "sg:city":"Bomaderry",
    "sg:classifiers":[
        {
            "category":"Manufacturing",
            "subcategory":"Furniture",
            "type":"Manufacturing & Wholesale Goods"
        }
    ],
    "sg:phone":"+61 2 4422 4600",
    "sg:postcode":"2541",
    "sg:province":"NSW",
    "sg:tags":[
        "builder",
        "designer",
        "custom"
    ],
    "wof:name":"Rybrook Joinery",
    "wof:placetype":"venue"
},
  "geometry": {"coordinates":[150.61137390100001,-34.8450202942],"type":"Point"}
}