{
  "type": "Feature",
  "properties": {
    "addr:full":"Lvl 3/ 1c Grand Ave Rosehill NSW 2142",
    "addr:housenumber":"/ 1c",
    "addr:postcode":"2142",
    "addr:street":"Grand Ave",
    "iso:country":"AU",
    "sg:address":"Lvl 3/ 1c Grand Ave",
    "sg:city":"Rosehill",
    "sg:classifiers":[
        {
            "category":"Professional",
            "subcategory":"Engineering",
            "type":"Services"
        }
    ],
    "sg:phone":"+61 2 9684 4488",
    "sg:postcode":"2142",
    "sg:province":"NSW",
    "sg:tags":[
        "consulting",
        "engineer"
    ],
    "wof:name":"Plantweave Technologies",
    "wof:placetype":"venue"
},
  "geometry": {"coordinates":[151.02606201200001,-33.8203201294],"type":"Point"}
}