{
  "type": "Feature",
  "properties": {
    "addr:full":"Fcty 3/ 18 Power Rd Doveton VIC 3177",
    "addr:housenumber":"/ 18",
    "addr:postcode":"3177",
    "addr:street":"Power Rd",
    "iso:country":"AU",
    "sg:address":"Fcty 3/ 18 Power Rd",
    "sg:city":"Doveton",
    "sg:classifiers":[
        {
            "category":"Autos & Motor Vehicles",
            "subcategory":"Fuel & Gas Station",
            "type":"Retail Goods"
        }
    ],
    "sg:phone":"+61 3 9793 2551",
    "sg:postcode":"3177",
    "sg:province":"VIC",
    "wof:name":"Olds-Kool Automotive Service & Repairs",
    "wof:placetype":"venue"
},
  "geometry": {"coordinates":[145.23628234899999,-37.9988098145],"type":"Point"}
}