{
  "type": "Feature",
  "properties": {
    "addr:full":"Suite 1 175 Ferry Rd Southport QLD 4215",
    "addr:housenumber":"175",
    "addr:postcode":"4215",
    "addr:street":"Ferry Rd",
    "iso:country":"AU",
    "sg:address":"Suite 1 175 Ferry Rd",
    "sg:city":"Southport",
    "sg:classifiers":[
        {
            "category":"Banks & Credit Unions",
            "subcategory":"Bank",
            "type":"Services"
        }
    ],
    "sg:phone":"+61 7 5503 1558",
    "sg:postcode":"4215",
    "sg:province":"QLD",
    "sg:tags":[
        "broker",
        "mortgage"
    ],
    "wof:name":"Icon Financial Services Pty Ltd",
    "wof:placetype":"venue"
},
  "geometry": {"coordinates":[153.41172790499999,-27.9863414764],"type":"Point"}
}