{
  "type": "Feature",
  "properties": {
    "addr:full":"Unit 2f 13 Forrester St Kingsgrove NSW 2208",
    "addr:housenumber":"13",
    "addr:postcode":"2208",
    "addr:street":"Forrester St",
    "iso:country":"AU",
    "sg:address":"Unit 2f 13 Forrester St",
    "sg:city":"Kingsgrove",
    "sg:classifiers":[
        {
            "category":"Cafe",
            "type":"Food & Drink"
        }
    ],
    "sg:phone":"+61 2 9554 9925",
    "sg:postcode":"2208",
    "sg:province":"NSW",
    "wof:name":"The Grove Courtyard Cafe",
    "wof:placetype":"venue"
},
  "geometry": {"coordinates":[151.09747300000001,-33.937878],"type":"Point"}
}