{
  "type": "Feature",
  "properties": {
    "iso:country":"AU",
    "sg:address":"12 Sawtell St",
    "sg:city":"Kingaroy",
    "sg:classifiers":[
        {
            "category":"Retail",
            "subcategory":"Repair Shop",
            "type":"Services"
        }
    ],
    "sg:phone":"+61 7 4162 7580",
    "sg:postcode":"4610",
    "sg:province":"QLD",
    "sg:tags":[
        "mending",
        "clothing",
        "alteration"
    ],
    "wof:name":"Stitches On Embroidery Clothing & Alterations",
    "wof:placetype":"venue"
},
  "geometry": {"coordinates":[151.83442688,-26.5375709534],"type":"Point"}
}