{
  "type": "Feature",
  "properties": {
    "iso:country":"AU",
    "sg:address":"61 Carramar Drv",
    "sg:city":"Gol Gol",
    "sg:classifiers":[
        {
            "category":"Farming",
            "subcategory":"Fish & Marine Products",
            "type":"Manufacturing & Wholesale Goods"
        }
    ],
    "sg:phone":"+61 3 5024 8580",
    "sg:postcode":"2738",
    "sg:province":"NSW",
    "sg:tags":[
        "chemical",
        "supplier"
    ],
    "wof:name":"Vival Chemicals",
    "wof:placetype":"venue"
},
  "geometry": {"coordinates":[142.248016,-34.22324],"type":"Point"}
}