{
  "type": "Feature",
  "properties": {
    "addr:full":"38 Park St Bayview Heights QLD 4868",
    "addr:housenumber":"38",
    "addr:postcode":"4868",
    "addr:street":"Park St",
    "iso:country":"AU",
    "sg:address":"38 Park St",
    "sg:city":"Bayview Heights",
    "sg:classifiers":[
        {
            "category":"Professional",
            "subcategory":"Art Services",
            "type":"Services"
        }
    ],
    "sg:phone":"+61 7 4054 2382",
    "sg:postcode":"4868",
    "sg:province":"QLD",
    "sg:tags":[
        "decorator",
        "painter"
    ],
    "wof:name":"Sadler B N & L E",
    "wof:placetype":"venue"
},
  "geometry": {"coordinates":[145.72567749000001,-16.9546394348],"type":"Point"}
}