{
  "type": "Feature",
  "properties": {
    "addr:full":"4 Clarence St Malvern East VIC 3145",
    "addr:housenumber":"4",
    "addr:postcode":"3145",
    "addr:street":"Clarence St",
    "iso:country":"AU",
    "sg:address":"4 Clarence St",
    "sg:city":"Malvern East",
    "sg:classifiers":[
        {
            "category":"Arts & Performance",
            "subcategory":"Dance",
            "type":"Entertainment"
        }
    ],
    "sg:phone":"+61 3 9569 3009",
    "sg:postcode":"3145",
    "sg:province":"VIC",
    "sg:tags":[
        "theatrical",
        "ballet",
        "tuition"
    ],
    "wof:name":"Fox Julia",
    "wof:placetype":"venue"
},
  "geometry": {"coordinates":[145.041625977,-37.8749198914],"type":"Point"}
}