{
  "type": "Feature",
  "properties": {
    "iso:country":"AU",
    "sg:address":"Shp 5/ 73 The Tce",
    "sg:city":"Ocean Grove",
    "sg:classifiers":[
        {
            "category":"Personal",
            "subcategory":"Tattoo Parlor",
            "type":"Services"
        }
    ],
    "sg:phone":"+61 3 5255 5550",
    "sg:postcode":"3226",
    "sg:province":"VIC",
    "sg:tags":[
        "tattooing"
    ],
    "wof:name":"Coastline Tattoo",
    "wof:placetype":"venue"
},
  "geometry": {"coordinates":[144.53233299999999,-38.265778],"type":"Point"}
}