{
  "type": "Feature",
  "properties": {
    "addr:full":"159- 161 Broadwater Tce Redland Bay QLD 4165",
    "addr:housenumber":"161",
    "addr:postcode":"4165",
    "addr:street":"Broadwater Tce",
    "iso:country":"AU",
    "sg:address":"159- 161 Broadwater Tce",
    "sg:city":"Redland Bay",
    "sg:classifiers":[
        {
            "category":"Real Estate",
            "subcategory":"Real Estate Agent",
            "type":"Services"
        }
    ],
    "sg:phone":"+61 7 3206 7666",
    "sg:postcode":"4165",
    "sg:province":"QLD",
    "wof:name":"Noel Maher Realty Redland Bay",
    "wof:placetype":"venue"
},
  "geometry": {"coordinates":[153.30317688,-27.6123504639],"type":"Point"}
}