{
  "type": "Feature",
  "properties": {
    "addr:full":"126 Bank St South Melbourne VIC 3205",
    "addr:housenumber":"126",
    "addr:postcode":"3205",
    "addr:street":"Bank St",
    "iso:country":"AU",
    "sg:address":"126 Bank St",
    "sg:city":"South Melbourne",
    "sg:classifiers":[
        {
            "category":"Organizations",
            "subcategory":"Non-profit Organization",
            "type":"Services"
        }
    ],
    "sg:phone":"+61 3 9682 6828",
    "sg:postcode":"3205",
    "sg:province":"VIC",
    "sg:tags":[
        "environmental",
        "organisation",
        "conservation"
    ],
    "wof:name":"Earthwatch",
    "wof:placetype":"venue"
},
  "geometry": {"coordinates":[144.964584,-37.832962],"type":"Point"}
}