{
  "type": "Feature",
  "properties": {
    "addr:full":"&#034;Domain Park&#034; 202 Dunnes Rd Winslow VIC 3281",
    "addr:housenumber":"202",
    "addr:postcode":"3281",
    "addr:street":"Dunnes Rd",
    "iso:country":"AU",
    "sg:address":"&#034;Domain Park&#034; 202 Dunnes Rd",
    "sg:city":"Winslow",
    "sg:classifiers":[
        {
            "category":"Farming",
            "subcategory":"Farm",
            "type":"Manufacturing & Wholesale Goods"
        }
    ],
    "sg:phone":"+61 3 5569 2416",
    "sg:postcode":"3281",
    "sg:province":"VIC",
    "sg:tags":[
        "farmer"
    ],
    "wof:name":"O&#039;Keefe C J & B M",
    "wof:placetype":"venue"
},
  "geometry": {"coordinates":[142.4609375,-38.2306938171],"type":"Point"}
}