{
  "type": "Feature",
  "properties": {
    "addr:full":"Shp 6/ 582 Chapman Rd Geraldton WA 6530",
    "addr:housenumber":"/ 582",
    "addr:postcode":"6530",
    "addr:street":"Chapman Rd",
    "iso:country":"AU",
    "sg:address":"Shp 6/ 582 Chapman Rd",
    "sg:city":"Geraldton",
    "sg:classifiers":[
        {
            "category":"Fast Food",
            "type":"Food & Drink"
        }
    ],
    "sg:phone":"+61 8 9938 2009",
    "sg:postcode":"6530",
    "sg:province":"WA",
    "sg:tags":[
        "away",
        "take"
    ],
    "wof:name":"Coffee Days",
    "wof:placetype":"venue"
},
  "geometry": {"coordinates":[114.636810303,-28.719959259],"type":"Point"}
}