{
  "type": "Feature",
  "properties": {
    "addr:full":"Davos St Main Ridge VIC 3928",
    "addr:postcode":"3928",
    "addr:street":"St",
    "iso:country":"AU",
    "sg:address":"Davos St",
    "sg:city":"Main Ridge",
    "sg:classifiers":[
        {
            "category":"Real Estate",
            "subcategory":"Architect",
            "type":"Services"
        }
    ],
    "sg:phone":"+61 3 5989 6041",
    "sg:postcode":"3928",
    "sg:province":"VIC",
    "wof:name":"Corner J",
    "wof:placetype":"venue"
},
  "geometry": {"coordinates":[144.955932617,-38.3860702515],"type":"Point"}
}