{
  "type": "Feature",
  "properties": {
    "iso:country":"AU",
    "sg:address":"Shop 3/5 Smart St Mall",
    "sg:city":"Mandurah",
    "sg:classifiers":[
        {
            "category":"Personal",
            "subcategory":"Piercing",
            "type":"Services"
        }
    ],
    "sg:phone":"+61 8 9581 4500",
    "sg:postcode":"6210",
    "sg:province":"WA",
    "sg:tags":[
        "body",
        "ear"
    ],
    "wof:name":"Avellion Body Piercing Studio",
    "wof:placetype":"venue"
},
  "geometry": {"coordinates":[115.719398,-32.533474],"type":"Point"}
}