{
  "type": "Feature",
  "properties": {
    "addr:full":"Shp2/ 945 Botany Rd Mascot NSW 2020",
    "addr:housenumber":"945",
    "addr:postcode":"2020",
    "addr:street":"Botany Rd",
    "iso:country":"AU",
    "sg:address":"Shp2/ 945 Botany Rd",
    "sg:city":"Mascot",
    "sg:classifiers":[
        {
            "category":"Retail",
            "subcategory":"Self-service Laundry",
            "type":"Services"
        }
    ],
    "sg:phone":"+61 2 9693 1108",
    "sg:postcode":"2020",
    "sg:province":"NSW",
    "wof:name":"Steven's Laundry",
    "wof:placetype":"venue"
},
  "geometry": {"coordinates":[151.19432067899999,-33.9355049133],"type":"Point"}
}