{
  "type": "Feature",
  "properties": {
    "addr:full":"10 Felicia St Mt Gambier SA 5290",
    "addr:housenumber":"10",
    "addr:postcode":"5290",
    "addr:street":"Felicia St",
    "iso:country":"AU",
    "sg:address":"10 Felicia St",
    "sg:city":"Mt Gambier",
    "sg:classifiers":[
        {
            "category":"Shopping",
            "subcategory":"Pets & Pet Supplies",
            "type":"Retail Goods"
        }
    ],
    "sg:phone":"+61 8 8725 9615",
    "sg:postcode":"5290",
    "sg:province":"SA",
    "sg:tags":[
        "dog"
    ],
    "wof:name":"Stockman Dog Products",
    "wof:placetype":"venue"
},
  "geometry": {"coordinates":[140.76902799999999,-37.812981],"type":"Point"}
}