{
  "type": "Feature",
  "properties": {
    "addr:full":"228 Victoria Rd Chatswood NSW 2067",
    "addr:housenumber":"228",
    "addr:postcode":"2067",
    "addr:street":"Victoria Rd",
    "iso:country":"AU",
    "sg:address":"228 Victoria Rd",
    "sg:city":"Chatswood",
    "sg:classifiers":[
        {
            "category":"Fast Food",
            "type":"Food & Drink"
        }
    ],
    "sg:phone":"+61 2 9411 4575",
    "sg:postcode":"2067",
    "sg:province":"NSW",
    "sg:tags":[
        "away",
        "take"
    ],
    "wof:name":"Chookas Chargrilled Chicken",
    "wof:placetype":"venue"
},
  "geometry": {"coordinates":[151.189453125,-33.7944602966],"type":"Point"}
}