{
  "type": "Feature",
  "properties": {
    "addr:full":"Lewis Rd Waikerie SA 5330",
    "addr:postcode":"5330",
    "addr:street":"Lewis Rd",
    "iso:country":"AU",
    "sg:address":"Lewis Rd",
    "sg:city":"Waikerie",
    "sg:classifiers":[
        {
            "category":"Farming",
            "subcategory":"Orchard",
            "type":"Manufacturing & Wholesale Goods"
        }
    ],
    "sg:phone":"+61 8 8541 2470",
    "sg:postcode":"5330",
    "sg:province":"SA",
    "sg:tags":[
        "citrus",
        "fruit",
        "grower"
    ],
    "wof:name":"L & R citus Pty Ltd",
    "wof:placetype":"venue"
},
  "geometry": {"coordinates":[139.91122436500001,-34.1747169495],"type":"Point"}
}