{
  "type": "Feature",
  "properties": {
    "iso:country":"AU",
    "sg:address":"55 Logan St",
    "sg:city":"Eglinton",
    "sg:classifiers":[
        {
            "category":"Building & Trades",
            "subcategory":"Construction",
            "type":"Services"
        }
    ],
    "sg:phone":"+61 428 637 356",
    "sg:postcode":"2795",
    "sg:province":"NSW",
    "sg:tags":[
        "contractor"
    ],
    "wof:name":"D&M Board Building Contractors",
    "wof:placetype":"venue"
},
  "geometry": {"coordinates":[149.54440307600001,-33.3813247681],"type":"Point"}
}