{
  "type": "Feature",
  "properties": {
    "addr:full":"18 Glenferrie Rd Malvern VIC 3144",
    "addr:housenumber":"18",
    "addr:postcode":"3144",
    "addr:street":"Glenferrie Rd",
    "iso:country":"AU",
    "sg:address":"18 Glenferrie Rd",
    "sg:city":"Malvern",
    "sg:classifiers":[
        {
            "category":"Restaurant",
            "type":"Food & Drink"
        }
    ],
    "sg:phone":"+61 3 9509 9624",
    "sg:postcode":"3144",
    "sg:province":"VIC",
    "wof:name":"Chun Po Chinese Restaurant",
    "wof:placetype":"venue"
},
  "geometry": {"coordinates":[145.02815246599999,-37.8644523621],"type":"Point"}
}