{
  "type": "Feature",
  "properties": {
    "iso:country":"AU",
    "sg:address":"16 Caledonia St",
    "sg:city":"Parkes",
    "sg:classifiers":[
        {
            "category":"Mining & Drilling",
            "type":"Manufacturing & Wholesale Goods"
        }
    ],
    "sg:phone":"+61 2 6862 1355",
    "sg:postcode":"2870",
    "sg:province":"NSW",
    "sg:tags":[
        "boring",
        "contractor"
    ],
    "wof:name":"G C McCabe & Co Parkes Pty Ltd",
    "wof:placetype":"venue"
},
  "geometry": {"coordinates":[148.17503400000001,-33.141106],"type":"Point"}
}