{
  "type": "Feature",
  "properties": {
    "addr:full":"83 Comur St Yass ACT 2582",
    "addr:housenumber":"83",
    "addr:postcode":"2582",
    "addr:street":"Comur St",
    "iso:country":"AU",
    "sg:address":"83 Comur St",
    "sg:city":"Yass",
    "sg:classifiers":[
        {
            "category":"Personal",
            "subcategory":"Beauty Salon",
            "type":"Services"
        }
    ],
    "sg:phone":"+61 2 6226 6044",
    "sg:postcode":"2582",
    "sg:province":"ACT",
    "sg:tags":[
        "hairdresser"
    ],
    "wof:name":"Phillip's Hair Studio",
    "wof:placetype":"venue"
},
  "geometry": {"coordinates":[148.912033081,-34.8427963257],"type":"Point"}
}