{
  "type": "Feature",
  "properties": {
    "iso:country":"AU",
    "sg:address":"29 Finchley St",
    "sg:city":"Milton",
    "sg:classifiers":[
        {
            "category":"Manufacturing",
            "subcategory":"Retail Goods",
            "type":"Manufacturing & Wholesale Goods"
        }
    ],
    "sg:phone":"+61 7 3369 3599",
    "sg:postcode":"4064",
    "sg:province":"QLD",
    "sg:tags":[
        "merchant",
        "pump",
        "mfrs"
    ],
    "wof:name":"Applied Vacuum Solutions",
    "wof:placetype":"venue"
},
  "geometry": {"coordinates":[153.00559997600001,-27.4657821655],"type":"Point"}
}