{
  "type": "Feature",
  "properties": {
    "addr:full":"204 Learmonth St Alfredton VIC 3350",
    "addr:housenumber":"204",
    "addr:postcode":"3350",
    "addr:street":"Learmonth St",
    "iso:country":"AU",
    "sg:address":"204 Learmonth St",
    "sg:city":"Alfredton",
    "sg:classifiers":[
        {
            "category":"Home & Garden",
            "subcategory":"Hardware",
            "type":"Retail Goods"
        }
    ],
    "sg:phone":"+61 3 5335 1777",
    "sg:postcode":"3350",
    "sg:province":"VIC",
    "sg:tags":[
        "nut",
        "bolt"
    ],
    "wof:name":"Thomas Warburton Pty Ltd",
    "wof:placetype":"venue"
},
  "geometry": {"coordinates":[143.810486,-37.568798],"type":"Point"}
}