{
  "type": "Feature",
  "properties": {
    "addr:full":"59 Bourbong St Chapel Hill QLD 4069",
    "addr:housenumber":"59",
    "addr:postcode":"4069",
    "addr:street":"Bourbong St",
    "iso:country":"AU",
    "sg:address":"59 Bourbong St",
    "sg:city":"Chapel Hill",
    "sg:classifiers":[
        {
            "category":"Personal",
            "subcategory":"Beauty Salon",
            "type":"Services"
        }
    ],
    "sg:phone":"+61 413 824 184",
    "sg:postcode":"4069",
    "sg:province":"QLD",
    "sg:tags":[
        "supply",
        "artist",
        "make-up"
    ],
    "wof:name":"Tegan Richardson Make-up Artist",
    "wof:placetype":"venue"
},
  "geometry": {"coordinates":[152.95924377399999,-27.5021076202],"type":"Point"}
}