{
  "type": "Feature",
  "properties": {
    "iso:country":"AU",
    "sg:address":"7 Russell Ave",
    "sg:city":"Lindfield",
    "sg:classifiers":[
        {
            "category":"Health Services",
            "subcategory":"Dentist",
            "type":"Services"
        }
    ],
    "sg:phone":"+61 2 9416 2767",
    "sg:postcode":"2070",
    "sg:province":"NSW",
    "wof:name":"Chang J",
    "wof:placetype":"venue"
},
  "geometry": {"coordinates":[151.17074585,-33.7764434814],"type":"Point"}
}