{
  "type": "Feature",
  "properties": {
    "addr:full":"Suite 17/ 336 Churchill Ave Subiaco WA 6008",
    "addr:housenumber":"17 / 336",
    "addr:postcode":"6008",
    "addr:street":"Churchill Ave",
    "iso:country":"AU",
    "sg:address":"Suite 17/ 336 Churchill Ave",
    "sg:city":"Subiaco",
    "sg:classifiers":[
        {
            "category":"Professional",
            "subcategory":"Art Services",
            "type":"Services"
        }
    ],
    "sg:phone":"+61 8 9382 1155",
    "sg:postcode":"6008",
    "sg:province":"WA",
    "sg:tags":[
        "graphic",
        "designer"
    ],
    "sg:website":"http://www.bonserdesign.com.au",
    "wof:name":"Bonser Design",
    "wof:placetype":"venue"
},
  "geometry": {"coordinates":[115.824150085,-31.9477558136],"type":"Point"}
}