{
  "type": "Feature",
  "properties": {
    "addr:full":"7 Belcaro St Mt Gravatt QLD 4122",
    "addr:housenumber":"7",
    "addr:postcode":"4122",
    "addr:street":"Belcaro St",
    "iso:country":"AU",
    "sg:address":"7 Belcaro St",
    "sg:city":"Mt Gravatt",
    "sg:classifiers":[
        {
            "category":"Building & Trades",
            "subcategory":"Landscaping Services",
            "type":"Services"
        }
    ],
    "sg:phone":"+61 413 333 330",
    "sg:postcode":"4122",
    "sg:province":"QLD",
    "sg:tags":[
        "stump",
        "tree",
        "felling",
        "removal"
    ],
    "wof:name":"The Easy Gardener",
    "wof:placetype":"venue"
},
  "geometry": {"coordinates":[153.08746337900001,-27.5545768738],"type":"Point"}
}