{
  "type": "Feature",
  "properties": {
    "addr:full":"58 McBride Ave Wonthaggi VIC 3995",
    "addr:housenumber":"58",
    "addr:postcode":"3995",
    "addr:street":"Mcbride Ave",
    "iso:country":"AU",
    "sg:address":"58 McBride Ave",
    "sg:city":"Wonthaggi",
    "sg:classifiers":[
        {
            "category":"Shopping",
            "subcategory":"Mobile Phones",
            "type":"Retail Goods"
        }
    ],
    "sg:phone":"+61 3 5672 4080",
    "sg:postcode":"3995",
    "sg:province":"VIC",
    "sg:tags":[
        "telephone",
        "accessory"
    ],
    "wof:name":"Leading Edge Computers",
    "wof:placetype":"venue"
},
  "geometry": {"coordinates":[145.591095,-38.606792],"type":"Point"}
}