{
  "type": "Feature",
  "properties": {
    "addr:full":"651 New South Head Rd Rose Bay NSW 2029",
    "addr:housenumber":"651",
    "addr:postcode":"2029",
    "addr:street":"New South Head Rd",
    "iso:country":"AU",
    "sg:address":"651 New South Head Rd",
    "sg:city":"Rose Bay",
    "sg:classifiers":[
        {
            "category":"Retail",
            "subcategory":"Self-service Laundry",
            "type":"Services"
        }
    ],
    "sg:phone":"+61 2 9371 5877",
    "sg:postcode":"2029",
    "sg:province":"NSW",
    "wof:name":"Hangout Laundry Drycleaning",
    "wof:placetype":"venue"
},
  "geometry": {"coordinates":[151.259643555,-33.8725967407],"type":"Point"}
}