{
  "type": "Feature",
  "properties": {
    "iso:country":"AU",
    "sg:address":"178 Jubilee Hwy",
    "sg:city":"West Mt Gambier",
    "sg:classifiers":[
        {
            "category":"Travel",
            "subcategory":"Hotels & Motels",
            "type":"Entertainment"
        }
    ],
    "sg:phone":"+61 8 8723 1200",
    "sg:postcode":"5290",
    "sg:province":"SA",
    "sg:tags":[
        "accommodation"
    ],
    "wof:name":"Charlies Diner",
    "wof:placetype":"venue"
},
  "geometry": {"coordinates":[140.75950599999999,-37.816105],"type":"Point"}
}