{
  "type": "Feature",
  "properties": {
    "addr:full":"Shp 40 Forestway Shopng Cntr Russell St Frenchs Forest NSW 2086",
    "addr:housenumber":"40",
    "addr:postcode":"2086",
    "addr:street":"Forestway Shopng Cntr Russell St",
    "iso:country":"AU",
    "sg:address":"Shp 40 Forestway Shopng Cntr Russell St",
    "sg:city":"Frenchs Forest",
    "sg:classifiers":[
        {
            "category":"Banks & Credit Unions",
            "subcategory":"Investment Brokerage",
            "type":"Services"
        }
    ],
    "sg:phone":"+61 2 9451 0188",
    "sg:postcode":"2086",
    "sg:province":"NSW",
    "wof:name":"Commonwealth Financial Planning",
    "wof:placetype":"venue"
},
  "geometry": {"coordinates":[151.23475647000001,-33.7508201599],"type":"Point"}
}