{
  "type": "Feature",
  "properties": {
    "addr:full":"Northpark Shopping Centre 264 Main North Rd Prospect SA 5082",
    "addr:housenumber":"264",
    "addr:postcode":"5082",
    "addr:street":"Main North Rd",
    "iso:country":"AU",
    "sg:address":"Northpark Shopping Centre 264 Main North Rd",
    "sg:city":"Prospect",
    "sg:classifiers":[
        {
            "category":"Travel",
            "subcategory":"Travel Agent",
            "type":"Entertainment"
        }
    ],
    "sg:phone":"+61 13 18 66",
    "sg:postcode":"5082",
    "sg:province":"SA",
    "sg:tags":[
        "consultant"
    ],
    "wof:name":"Flight Centre",
    "wof:placetype":"venue"
},
  "geometry": {"coordinates":[138.602386475,-34.8823623657],"type":"Point"}
}