{
  "type": "Feature",
  "properties": {
    "iso:country":"AU",
    "sg:address":"2431 Gold Coast Hwy",
    "sg:city":"Mermaid Beach",
    "sg:classifiers":[
        {
            "category":"Health Services",
            "subcategory":"Doctor",
            "type":"Services"
        }
    ],
    "sg:phone":"+61 7 5575 2444",
    "sg:postcode":"4218",
    "sg:province":"QLD",
    "sg:tags":[
        "medical",
        "practitioner"
    ],
    "wof:name":"Benjamin Lil Dr",
    "wof:placetype":"venue"
},
  "geometry": {"coordinates":[153.43557739299999,-28.0465373993],"type":"Point"}
}