{
  "type": "Feature",
  "properties": {
    "iso:country":"AU",
    "sg:address":"55 Muldoon St",
    "sg:city":"Taree",
    "sg:classifiers":[
        {
            "category":"Recreation",
            "subcategory":"Amusement Park",
            "type":"Entertainment"
        }
    ],
    "sg:phone":"+61 2 6552 4733",
    "sg:postcode":"2430",
    "sg:province":"NSW",
    "wof:name":"Taree TenPin Bowl",
    "wof:placetype":"venue"
},
  "geometry": {"coordinates":[152.45871,-31.89879],"type":"Point"}
}