{
  "type": "Feature",
  "properties": {
    "addr:full":"Ste 30/ 12 Railway Pde Burwood NSW 2134",
    "addr:housenumber":"/ 12",
    "addr:postcode":"2134",
    "addr:street":"Railway Pde",
    "iso:country":"AU",
    "sg:address":"Ste 30/ 12 Railway Pde",
    "sg:city":"Burwood",
    "sg:classifiers":[
        {
            "category":"Health Services",
            "subcategory":"Health Practitioner",
            "type":"Services"
        }
    ],
    "sg:phone":"+61 2 9745 1243",
    "sg:postcode":"2134",
    "sg:province":"NSW",
    "sg:tags":[
        "dietitian"
    ],
    "wof:name":"Chin Emily",
    "wof:placetype":"venue"
},
  "geometry": {"coordinates":[151.10604858400001,-33.8779602051],"type":"Point"}
}