{
  "type": "Feature",
  "properties": {
    "iso:country":"AU",
    "sg:address":"Farm 1212",
    "sg:city":"Corbie Hill",
    "sg:classifiers":[
        {
            "category":"Farming",
            "subcategory":"Farm",
            "type":"Manufacturing & Wholesale Goods"
        }
    ],
    "sg:phone":"+61 2 6955 6252",
    "sg:postcode":"2705",
    "sg:province":"NSW",
    "sg:tags":[
        "farmer"
    ],
    "wof:name":"Ciccia A & C",
    "wof:placetype":"venue"
},
  "geometry": {"coordinates":[146.482055664,-34.5597000122],"type":"Point"}
}