{
  "type": "Feature",
  "properties": {
    "iso:country":"AU",
    "sg:address":"1542 Mt Dandenong Tourist Rd",
    "sg:city":"Olinda",
    "sg:classifiers":[
        {
            "category":"Health Services",
            "subcategory":"Health Practitioner",
            "type":"Services"
        }
    ],
    "sg:phone":"+61 3 9751 0400",
    "sg:postcode":"3788",
    "sg:province":"VIC",
    "sg:tags":[
        "physiotherapist"
    ],
    "wof:name":"Dandenong Ranges Physiotherapy",
    "wof:placetype":"venue"
},
  "geometry": {"coordinates":[145.361237,-37.848225],"type":"Point"}
}