{
  "type": "Feature",
  "properties": {
    "addr:full":"227 Union St Brunswick VIC 3056",
    "addr:housenumber":"227",
    "addr:postcode":"3056",
    "addr:street":"Union St",
    "iso:country":"AU",
    "sg:address":"227 Union St",
    "sg:city":"Brunswick",
    "sg:classifiers":[
        {
            "category":"Home & Garden",
            "subcategory":"Carpets & Floor Coverings",
            "type":"Retail Goods"
        }
    ],
    "sg:phone":"+61 408 366 660",
    "sg:postcode":"3056",
    "sg:province":"VIC",
    "sg:tags":[
        "tile",
        "wall"
    ],
    "wof:name":"Sam's Tiling Service",
    "wof:placetype":"venue"
},
  "geometry": {"coordinates":[144.94291687,-37.7721824646],"type":"Point"}
}