{
  "type": "Feature",
  "properties": {
    "addr:full":"PO Box 135 Main Beach QLD 4217",
    "addr:postcode":"4217",
    "iso:country":"AU",
    "sg:address":"PO Box 135",
    "sg:city":"Main Beach",
    "sg:classifiers":[
        {
            "category":"Conference Center",
            "type":"Public Place"
        }
    ],
    "sg:phone":"+61 411 711 274",
    "sg:postcode":"4217",
    "sg:province":"QLD",
    "sg:tags":[
        "venue",
        "convention"
    ],
    "wof:name":"Gold Coast Ferries Pty Ltd",
    "wof:placetype":"venue"
},
  "geometry": {"coordinates":[153.429153442,-27.982339859],"type":"Point"}
}