{
  "type": "Feature",
  "properties": {
    "iso:country":"AU",
    "sg:address":"337 Ruthven St",
    "sg:city":"Toowoomba City",
    "sg:classifiers":[
        {
            "category":"Arena",
            "subcategory":"Sports Club",
            "type":"Entertainment"
        }
    ],
    "sg:phone":"+61 7 4632 2994",
    "sg:postcode":"4350",
    "sg:province":"QLD",
    "sg:tags":[
        "australian",
        "football",
        "rule"
    ],
    "wof:name":"AFL Queensland Ltd",
    "wof:placetype":"venue"
},
  "geometry": {"coordinates":[151.952271,-27.568323],"type":"Point"}
}