{
  "type": "Feature",
  "properties": {
    "addr:full":"136 Bussell Hwy Margaret River WA 6285",
    "addr:housenumber":"136",
    "addr:postcode":"6285",
    "addr:street":"Bussell Hwy",
    "iso:country":"AU",
    "sg:address":"136 Bussell Hwy",
    "sg:city":"Margaret River",
    "sg:classifiers":[
        {
            "category":"Autos & Motor Vehicles",
            "subcategory":"Fuel & Gas Station",
            "type":"Retail Goods"
        }
    ],
    "sg:phone":"+61 8 9757 2240",
    "sg:postcode":"6285",
    "sg:province":"WA",
    "wof:name":"BP Aust Ltd",
    "wof:placetype":"venue"
},
  "geometry": {"coordinates":[115.073486328,-33.951789856],"type":"Point"}
}