{
  "type": "Feature",
  "properties": {
    "addr:full":"U3/ 20 Avalon Pde Miami QLD 4220",
    "addr:housenumber":"20",
    "addr:postcode":"4220",
    "addr:street":"U3 /;Avalon Pde",
    "iso:country":"AU",
    "sg:address":"U3/ 20 Avalon Pde",
    "sg:city":"Miami",
    "sg:classifiers":[
        {
            "category":"Retail",
            "subcategory":"Laundry & Dry Cleaning",
            "type":"Services"
        }
    ],
    "sg:phone":"+61 7 5575 5050",
    "sg:postcode":"4220",
    "sg:province":"QLD",
    "wof:name":"Lord Linen Service",
    "wof:placetype":"venue"
},
  "geometry": {"coordinates":[153.435150147,-28.0634860992],"type":"Point"}
}