{
  "type": "Feature",
  "properties": {
    "iso:country":"AU",
    "sg:address":"Shp7, 115- 121 Longueville Rd",
    "sg:city":"Lane Cove",
    "sg:classifiers":[
        {
            "category":"Shopping",
            "subcategory":"Baby Store",
            "type":"Retail Goods"
        }
    ],
    "sg:phone":"+61 2 9427 3230",
    "sg:postcode":"2066",
    "sg:province":"NSW",
    "sg:tags":[
        "wear"
    ],
    "wof:name":"Charlie's Lane Cove",
    "wof:placetype":"venue"
},
  "geometry": {"coordinates":[151.17005920400001,-33.8143501282],"type":"Point"}
}