{
  "type": "Feature",
  "properties": {
    "addr:full":"32 Withers St Sunshine VIC 3020",
    "addr:housenumber":"32",
    "addr:postcode":"3020",
    "addr:street":"Withers St",
    "iso:country":"AU",
    "sg:address":"32 Withers St",
    "sg:city":"Sunshine",
    "sg:classifiers":[
        {
            "category":"Organizations",
            "subcategory":"Community Association",
            "type":"Services"
        }
    ],
    "sg:phone":"+61 3 9311 5900",
    "sg:postcode":"3020",
    "sg:province":"VIC",
    "sg:tags":[
        "organisation",
        "family",
        "welfare"
    ],
    "wof:name":"Uniting Care-Sunshine Mission",
    "wof:placetype":"venue"
},
  "geometry": {"coordinates":[144.83415199999999,-37.785271],"type":"Point"}
}