{
  "type": "Feature",
  "properties": {
    "addr:full":"317 Handford Rd Taigum QLD 4018",
    "addr:housenumber":"317",
    "addr:postcode":"4018",
    "addr:street":"Handford Rd",
    "iso:country":"AU",
    "sg:address":"317 Handford Rd",
    "sg:city":"Taigum",
    "sg:classifiers":[
        {
            "category":"Social Services",
            "subcategory":"Retirement Home",
            "type":"Services"
        }
    ],
    "sg:phone":"+61 7 3865 6666",
    "sg:postcode":"4018",
    "sg:province":"QLD",
    "sg:tags":[
        "environmental",
        "consultant",
        "pollution"
    ],
    "wof:name":"Environmental & Earth Sciences",
    "wof:placetype":"venue"
},
  "geometry": {"coordinates":[153.040863,-27.345982],"type":"Point"}
}