{
  "type": "Feature",
  "properties": {
    "addr:full":"Unit 6, 2 Canning Hwy South Perth WA 6151",
    "addr:housenumber":"2",
    "addr:postcode":"6151",
    "addr:street":"Canning Hwy South",
    "iso:country":"AU",
    "sg:address":"Unit 6, 2 Canning Hwy",
    "sg:city":"South Perth",
    "sg:classifiers":[
        {
            "category":"Professional",
            "subcategory":"Accounting & Tax Preparation",
            "type":"Services"
        }
    ],
    "sg:phone":"+61 8 9474 4899",
    "sg:postcode":"6151",
    "sg:province":"WA",
    "sg:tags":[
        "accountant",
        "auditor"
    ],
    "wof:name":"H & R Block",
    "wof:placetype":"venue"
},
  "geometry": {"coordinates":[115.871132,-31.988543],"type":"Point"}
}