{
  "type": "Feature",
  "properties": {
    "addr:full":"55 Belford St Broadmeadow NSW 2292",
    "addr:housenumber":"55",
    "addr:postcode":"2292",
    "addr:street":"Belford St",
    "iso:country":"AU",
    "sg:address":"55 Belford St",
    "sg:city":"Broadmeadow",
    "sg:classifiers":[
        {
            "category":"Health Services",
            "subcategory":"Health Practitioner",
            "type":"Services"
        }
    ],
    "sg:phone":"+61 2 4965 3511",
    "sg:postcode":"2292",
    "sg:province":"NSW",
    "sg:tags":[
        "physiotherapist"
    ],
    "wof:name":"Hunter Physio",
    "wof:placetype":"venue"
},
  "geometry": {"coordinates":[151.73747253400001,-32.9243392944],"type":"Point"}
}