{
  "type": "Feature",
  "properties": {
    "addr:full":"1/34 Eaglehawk Rd Bendigo VIC 3550",
    "addr:housenumber":"/ 34",
    "addr:postcode":"3550",
    "addr:street":"Eaglehawk Rd",
    "iso:country":"AU",
    "sg:address":"1/34 Eaglehawk Rd",
    "sg:city":"Bendigo",
    "sg:classifiers":[
        {
            "category":"Professional",
            "subcategory":"Management & Consulting",
            "type":"Services"
        }
    ],
    "sg:phone":"+61 3 5443 0576",
    "sg:postcode":"3550",
    "sg:province":"VIC",
    "sg:tags":[
        "consultant",
        "business"
    ],
    "wof:name":"Successus",
    "wof:placetype":"venue"
},
  "geometry": {"coordinates":[144.266647339,-36.7559394836],"type":"Point"}
}