{
  "type": "Feature",
  "properties": {
    "iso:country":"AU",
    "sg:address":"240 Norris Rd",
    "sg:city":"Bracken Ridge",
    "sg:classifiers":[
        {
            "category":"Food & Beverages",
            "subcategory":"Fruits & Vegetables",
            "type":"Retail Goods"
        }
    ],
    "sg:phone":"+61 7 3261 6200",
    "sg:postcode":"4017",
    "sg:province":"QLD",
    "sg:tags":[
        "greengrocer",
        "fruiterer"
    ],
    "wof:name":"Ace Fruit Mart",
    "wof:placetype":"venue"
},
  "geometry": {"coordinates":[153.02572631800001,-27.3276615143],"type":"Point"}
}