{
  "type": "Feature",
  "properties": {
    "iso:country":"AU",
    "sg:address":"71 Atchison St",
    "sg:city":"Crows Nest",
    "sg:classifiers":[
        {
            "category":"Building & Trades",
            "subcategory":"Construction",
            "type":"Services"
        }
    ],
    "sg:phone":"+61 2 9437 6545",
    "sg:postcode":"2065",
    "sg:province":"NSW",
    "sg:tags":[
        "joiner",
        "carpenter"
    ],
    "wof:name":"Djurasevich S",
    "wof:placetype":"venue"
},
  "geometry": {"coordinates":[151.20196533199999,-33.823223114],"type":"Point"}
}