{
  "type": "Feature",
  "properties": {
    "addr:full":"85a Argyle St Hobart TAS 7000",
    "addr:housenumber":"85a",
    "addr:postcode":"7000",
    "addr:street":"Argyle St",
    "iso:country":"AU",
    "sg:address":"85a Argyle St",
    "sg:city":"Hobart",
    "sg:classifiers":[
        {
            "category":"Health Services",
            "subcategory":"Hospital",
            "type":"Services"
        }
    ],
    "sg:phone":"+61 3 6230 8581",
    "sg:postcode":"7000",
    "sg:province":"TAS",
    "sg:tags":[
        "ambulance"
    ],
    "wof:name":"Ambulance",
    "wof:placetype":"venue"
},
  "geometry": {"coordinates":[147.32591247600001,-42.8781356812],"type":"Point"}
}