{
  "type": "Feature",
  "properties": {
    "addr:full":"162 Cameron Pde Watsonia VIC 3087",
    "addr:housenumber":"162",
    "addr:postcode":"3087",
    "addr:street":"Cameron Pde",
    "iso:country":"AU",
    "sg:address":"162 Cameron Pde",
    "sg:city":"Watsonia",
    "sg:classifiers":[
        {
            "category":"Food & Beverages",
            "subcategory":"Groceries & Convenience Stores",
            "type":"Retail Goods"
        }
    ],
    "sg:phone":"+61 3 9434 2886",
    "sg:postcode":"3087",
    "sg:province":"VIC",
    "wof:name":"Cameron Parade Milkbar",
    "wof:placetype":"venue"
},
  "geometry": {"coordinates":[145.08201599099999,-37.6993560791],"type":"Point"}
}