{
  "type": "Feature",
  "properties": {
    "addr:full":"178 Sladen St Cranbourne VIC 3977",
    "addr:housenumber":"178",
    "addr:postcode":"3977",
    "addr:street":"Sladen St",
    "iso:country":"AU",
    "sg:address":"178 Sladen St",
    "sg:city":"Cranbourne",
    "sg:classifiers":[
        {
            "category":"Professional",
            "subcategory":"Management & Consulting",
            "type":"Services"
        }
    ],
    "sg:phone":"+61 3 5996 7700",
    "sg:postcode":"3977",
    "sg:province":"VIC",
    "sg:tags":[
        "consultant",
        "migration"
    ],
    "wof:name":"McCarthy Hoey",
    "wof:placetype":"venue"
},
  "geometry": {"coordinates":[145.284469605,-38.113319397],"type":"Point"}
}