{
  "type": "Feature",
  "properties": {
    "addr:full":"13/ 81 Bishop St Kelvin Grove QLD 4059",
    "addr:housenumber":"13 / 81",
    "addr:postcode":"4059",
    "addr:street":"Bishop St",
    "iso:country":"AU",
    "sg:address":"13/ 81 Bishop St",
    "sg:city":"Kelvin Grove",
    "sg:classifiers":[
        {
            "category":"Home & Garden",
            "subcategory":"Building Materials",
            "type":"Retail Goods"
        }
    ],
    "sg:phone":"+61 7 3856 6660",
    "sg:postcode":"4059",
    "sg:province":"QLD",
    "sg:tags":[
        "fitting",
        "door"
    ],
    "wof:name":"Door Seals of Australia",
    "wof:placetype":"venue"
},
  "geometry": {"coordinates":[153.01100158700001,-27.4410247803],"type":"Point"}
}