{
  "type": "Feature",
  "properties": {
    "iso:country":"AU",
    "sg:address":"Cnr Morphett & Hindley Sts",
    "sg:city":"Adelaide",
    "sg:classifiers":[
        {
            "category":"Restaurant",
            "type":"Food & Drink"
        }
    ],
    "sg:phone":"+61 1800 755 332",
    "sg:postcode":"5000",
    "sg:province":"SA",
    "wof:name":"Blue Seaford & Chargrill",
    "wof:placetype":"venue"
},
  "geometry": {"coordinates":[138.59375,-34.9266891479],"type":"Point"}
}