{
  "type": "Feature",
  "properties": {
    "addr:full":"30 Kawanna St Mudjimba QLD 4564",
    "addr:housenumber":"30",
    "addr:postcode":"4564",
    "addr:street":"Kawanna St",
    "iso:country":"AU",
    "sg:address":"30 Kawanna St",
    "sg:city":"Mudjimba",
    "sg:classifiers":[
        {
            "category":"Utilities",
            "subcategory":"Electric",
            "type":"Services"
        }
    ],
    "sg:phone":"+61 7 5448 8499",
    "sg:postcode":"4564",
    "sg:province":"QLD",
    "sg:tags":[
        "electrical",
        "contractor"
    ],
    "wof:name":"Peter McLaren Electrical Contractor",
    "wof:placetype":"venue"
},
  "geometry": {"coordinates":[153.09954834000001,-26.6137580872],"type":"Point"}
}