{
  "type": "Feature",
  "properties": {
    "addr:full":"Factory 2/ 8 Sherwood Crt Wantirna VIC 3152",
    "addr:housenumber":"/ 8",
    "addr:postcode":"3152",
    "addr:street":"Sherwood Crt",
    "iso:country":"AU",
    "sg:address":"Factory 2/ 8 Sherwood Crt",
    "sg:city":"Wantirna",
    "sg:classifiers":[
        {
            "category":"Building & Trades",
            "subcategory":"Construction",
            "type":"Services"
        }
    ],
    "sg:phone":"+61 3 9887 4344",
    "sg:postcode":"3152",
    "sg:province":"VIC",
    "sg:tags":[
        "plasterboard",
        "plasterer",
        "fixer"
    ],
    "wof:name":"Countrywide Plastering Pty Ltd",
    "wof:placetype":"venue"
},
  "geometry": {"coordinates":[145.24888610799999,-37.8685455322],"type":"Point"}
}