{
  "type": "Feature",
  "properties": {
    "iso:country":"AU",
    "sg:address":"181 Argyle St",
    "sg:city":"Moss Vale",
    "sg:classifiers":[
        {
            "category":"Shopping",
            "type":"Retail Goods"
        }
    ],
    "sg:phone":"+61 2 4868 1661",
    "sg:postcode":"2577",
    "sg:province":"NSW",
    "sg:tags":[
        "agent",
        "stock"
    ],
    "wof:name":"Wallis Keith",
    "wof:placetype":"venue"
},
  "geometry": {"coordinates":[150.371185303,-34.5501174927],"type":"Point"}
}