{
  "type": "Feature",
  "properties": {
    "addr:full":"59 Augusta Rd Lenah Valley TAS 7008",
    "addr:postcode":"7008",
    "addr:street":"59 Augusta Rd",
    "iso:country":"AU",
    "sg:address":"59 Augusta Rd",
    "sg:city":"Lenah Valley",
    "sg:classifiers":[
        {
            "category":"Health Services",
            "subcategory":"Doctor",
            "type":"Services"
        }
    ],
    "sg:phone":"+61 3 6228 5777",
    "sg:postcode":"7008",
    "sg:province":"TAS",
    "sg:tags":[
        "medical",
        "practitioner"
    ],
    "wof:name":"Turner Lisa",
    "wof:placetype":"venue"
},
  "geometry": {"coordinates":[147.30296325699999,-42.8665962219],"type":"Point"}
}