{
  "type": "Feature",
  "properties": {
    "iso:country":"AU",
    "sg:address":"Suite 5/ 1016 Doncaster Rd",
    "sg:city":"Doncaster East",
    "sg:classifiers":[
        {
            "category":"Professional",
            "subcategory":"Accounting & Tax Preparation",
            "type":"Services"
        }
    ],
    "sg:phone":"+61 3 9841 5833",
    "sg:postcode":"3109",
    "sg:province":"VIC",
    "sg:tags":[
        "accountant",
        "auditor"
    ],
    "wof:name":"Pride Steve & Associates",
    "wof:placetype":"venue"
},
  "geometry": {"coordinates":[145.160842895,-37.7890586853],"type":"Point"}
}