{
  "type": "Feature",
  "properties": {
    "addr:full":"PO Box 117 Jindabyne NSW 2627",
    "addr:postcode":"2627",
    "iso:country":"AU",
    "sg:address":"PO Box 117",
    "sg:city":"Jindabyne",
    "sg:classifiers":[
        {
            "category":"Manufacturing",
            "subcategory":"Food",
            "type":"Manufacturing & Wholesale Goods"
        }
    ],
    "sg:phone":"+61 2 6456 2618",
    "sg:postcode":"2627",
    "sg:province":"NSW",
    "sg:tags":[
        "function",
        "catering"
    ],
    "wof:name":"Kim Neville Catering",
    "wof:placetype":"venue"
},
  "geometry": {"coordinates":[148.60859680199999,-36.4327316284],"type":"Point"}
}