{
  "type": "Feature",
  "properties": {
    "iso:country":"AU",
    "sg:address":"Ste21/ 328 Albany Hwy",
    "sg:city":"Victoria Park",
    "sg:classifiers":[
        {
            "category":"Banks & Credit Unions",
            "subcategory":"Bank",
            "type":"Services"
        }
    ],
    "sg:phone":"+61 8 9361 0600",
    "sg:postcode":"6100",
    "sg:province":"WA",
    "sg:tags":[
        "broker",
        "mortgage"
    ],
    "wof:name":"Amity Mortgage Solutions",
    "wof:placetype":"venue"
},
  "geometry": {"coordinates":[115.896186829,-31.9726905823],"type":"Point"}
}