{
  "type": "Feature",
  "properties": {
    "addr:full":"278 Stephensons Rd Mt Waverley VIC 3149",
    "addr:housenumber":"278",
    "addr:postcode":"3149",
    "addr:street":"Stephensons Rd",
    "iso:country":"AU",
    "sg:address":"278 Stephensons Rd",
    "sg:city":"Mt Waverley",
    "sg:classifiers":[
        {
            "category":"Travel",
            "subcategory":"Travel Agent",
            "type":"Entertainment"
        }
    ],
    "sg:phone":"+61 3 9807 0322",
    "sg:postcode":"3149",
    "sg:province":"VIC",
    "sg:tags":[
        "consultant"
    ],
    "wof:name":"Waverley Travel",
    "wof:placetype":"venue"
},
  "geometry": {"coordinates":[145.12890625,-37.8772659302],"type":"Point"}
}