{
  "type": "Feature",
  "properties": {
    "addr:full":"16-16 Thorn St Ryde NSW 2112",
    "addr:housenumber":"16-16",
    "addr:postcode":"2112",
    "addr:street":"Thorn St",
    "iso:country":"AU",
    "sg:address":"16-16 Thorn St",
    "sg:city":"Ryde",
    "sg:classifiers":[
        {
            "category":"Professional",
            "subcategory":"Art Services",
            "type":"Services"
        }
    ],
    "sg:phone":"+61 438 621 528",
    "sg:postcode":"2112",
    "sg:province":"NSW",
    "sg:tags":[
        "decorator",
        "painter"
    ],
    "wof:name":"K H Fish & Son",
    "wof:placetype":"venue"
},
  "geometry": {"coordinates":[151.09568786599999,-33.816493988],"type":"Point"}
}