{
  "type": "Feature",
  "properties": {
    "addr:full":"PO Box 266 Corio VIC 3214",
    "addr:postcode":"3214",
    "iso:country":"AU",
    "sg:address":"PO Box 266",
    "sg:city":"Corio",
    "sg:classifiers":[
        {
            "category":"Manufacturing",
            "subcategory":"Aerospace",
            "type":"Manufacturing & Wholesale Goods"
        }
    ],
    "sg:phone":"+61 419 371 856",
    "sg:postcode":"3214",
    "sg:province":"VIC",
    "sg:tags":[
        "equipment",
        "aircraft",
        "maintenance"
    ],
    "wof:name":"Southern Aero Engineering",
    "wof:placetype":"venue"
},
  "geometry": {"coordinates":[144.35643005399999,-38.0738601685],"type":"Point"}
}