{
  "type": "Feature",
  "properties": {
    "addr:full":"60 Railway St Mudgeeraba QLD 4213",
    "addr:housenumber":"60",
    "addr:postcode":"4213",
    "addr:street":"Railway St",
    "iso:country":"AU",
    "sg:address":"60 Railway St",
    "sg:city":"Mudgeeraba",
    "sg:classifiers":[
        {
            "category":"Real Estate",
            "subcategory":"Real Estate Agent",
            "type":"Services"
        }
    ],
    "sg:phone":"+61 7 5530 2000",
    "sg:postcode":"4213",
    "sg:province":"QLD",
    "wof:name":"Tallai Property World",
    "wof:placetype":"venue"
},
  "geometry": {"coordinates":[153.36526489299999,-28.0786247253],"type":"Point"}
}