{
  "type": "Feature",
  "properties": {
    "addr:full":"34 Derwent Park Rd Derwent Park TAS 7009",
    "addr:housenumber":"34",
    "addr:postcode":"7009",
    "addr:street":"Derwent Park Rd",
    "iso:country":"AU",
    "sg:address":"34 Derwent Park Rd",
    "sg:city":"Derwent Park",
    "sg:classifiers":[
        {
            "category":"Communications",
            "subcategory":"Film & Video Production",
            "type":"Services"
        }
    ],
    "sg:phone":"+61 1800 337 324",
    "sg:postcode":"7009",
    "sg:province":"TAS",
    "sg:tags":[
        "colour",
        "pigment"
    ],
    "wof:name":"Ability Building Chemicals Co",
    "wof:placetype":"venue"
},
  "geometry": {"coordinates":[147.29487609899999,-42.8387451172],"type":"Point"}
}