{
  "type": "Feature",
  "properties": {
    "iso:country":"AU",
    "sg:address":"40 Smith St",
    "sg:city":"Capalaba",
    "sg:classifiers":[
        {
            "category":"Building & Trades",
            "subcategory":"Construction",
            "type":"Services"
        }
    ],
    "sg:phone":"+61 7 3823 1762",
    "sg:postcode":"4157",
    "sg:province":"QLD",
    "sg:tags":[
        "fencing",
        "contractor"
    ],
    "wof:name":"C Safe Glass Fencing Systems",
    "wof:placetype":"venue"
},
  "geometry": {"coordinates":[153.20083618199999,-27.5291957855],"type":"Point"}
}