{
  "type": "Feature",
  "properties": {
    "addr:full":"77- 79 Hallam Rd Hampton Park VIC 3976",
    "addr:housenumber":"79",
    "addr:postcode":"3976",
    "addr:street":"Hallam Rd",
    "iso:country":"AU",
    "sg:address":"77- 79 Hallam Rd",
    "sg:city":"Hampton Park",
    "sg:classifiers":[
        {
            "category":"Health Services",
            "subcategory":"Chiropractor",
            "type":"Services"
        }
    ],
    "sg:phone":"+61 3 9702 8444",
    "sg:postcode":"3976",
    "sg:province":"VIC",
    "wof:name":"Teshome T. Dr.",
    "wof:placetype":"venue"
},
  "geometry": {"coordinates":[145.26707458499999,-38.0350723267],"type":"Point"}
}