{
  "type": "Feature",
  "properties": {
    "iso:country":"AU",
    "sg:address":"Cnr Mountain View & Rattray Rds",
    "sg:city":"Montmorency",
    "sg:classifiers":[
        {
            "category":"Education",
            "subcategory":"Kindergarten",
            "type":"Public Place"
        }
    ],
    "sg:phone":"+61 3 9435 6946",
    "sg:postcode":"3094",
    "sg:province":"VIC",
    "sg:tags":[
        "pre-schools"
    ],
    "wof:name":"St Andrews Uniting Church Kindergarten",
    "wof:placetype":"venue"
},
  "geometry": {"coordinates":[145.123413086,-37.7176132202],"type":"Point"}
}