{
  "type": "Feature",
  "properties": {
    "addr:full":"Unit G 5A Dickson Chambers Dickson Pl Dickson ACT 2602",
    "addr:housenumber":"5a",
    "addr:postcode":"2602",
    "addr:street":"Dickson Chambers",
    "iso:country":"AU",
    "sg:address":"Unit G 5A Dickson Chambers Dickson Pl",
    "sg:city":"Dickson",
    "sg:classifiers":[
        {
            "category":"Travel",
            "subcategory":"Travel Agent",
            "type":"Entertainment"
        }
    ],
    "sg:phone":"+61 2 6262 9110",
    "sg:postcode":"2602",
    "sg:province":"ACT",
    "sg:tags":[
        "consultant"
    ],
    "wof:name":"Harvey World Travel",
    "wof:placetype":"venue"
},
  "geometry": {"coordinates":[149.138015747,-35.2501411438],"type":"Point"}
}