{
  "type": "Feature",
  "properties": {
    "iso:country":"AU",
    "sg:address":"198 Anson St",
    "sg:city":"Orange",
    "sg:classifiers":[
        {
            "category":"Insurance",
            "subcategory":"Hazard Insurance",
            "type":"Services"
        }
    ],
    "sg:phone":"+61 2 5310 1722",
    "sg:postcode":"2800",
    "sg:province":"NSW",
    "sg:tags":[
        "fire",
        "accident",
        "marine"
    ],
    "wof:name":"CGU",
    "wof:placetype":"venue"
},
  "geometry": {"coordinates":[149.09877014200001,-33.2838935852],"type":"Point"}
}