{
  "type": "Feature",
  "properties": {
    "iso:country":"AU",
    "sg:address":"128 James St",
    "sg:city":"Templestowe",
    "sg:classifiers":[
        {
            "category":"Personal",
            "subcategory":"Beauty Salon",
            "type":"Services"
        }
    ],
    "sg:phone":"+61 3 9846 8866",
    "sg:postcode":"3106",
    "sg:province":"VIC",
    "wof:name":"PCI Concept Salons",
    "wof:placetype":"venue"
},
  "geometry": {"coordinates":[145.12945556599999,-37.7570037842],"type":"Point"}
}