{
  "type": "Feature",
  "properties": {
    "addr:full":"5/ 1 Fortitude Crs Burleigh Heads QLD 4220",
    "addr:housenumber":"/ 1",
    "addr:postcode":"4220",
    "addr:street":"Fortitude Crs",
    "iso:country":"AU",
    "sg:address":"5/ 1 Fortitude Crs",
    "sg:city":"Burleigh Heads",
    "sg:classifiers":[
        {
            "category":"Retail",
            "subcategory":"Repair Shop",
            "type":"Services"
        }
    ],
    "sg:phone":"+61 7 5520 1466",
    "sg:postcode":"4220",
    "sg:province":"QLD",
    "sg:tags":[
        "restorer",
        "repairer",
        "carpet"
    ],
    "wof:name":"A Abate Carpet Cleaning",
    "wof:placetype":"venue"
},
  "geometry": {"coordinates":[153.449752808,-28.0879096985],"type":"Point"}
}