{
  "type": "Feature",
  "properties": {
    "iso:country":"AU",
    "sg:address":"8 Mc Crea St",
    "sg:city":"Prospect",
    "sg:classifiers":[
        {
            "category":"Military Area",
            "subcategory":"Air Force Base",
            "type":"Public Place"
        }
    ],
    "sg:phone":"+61 427 187 203",
    "sg:postcode":"5082",
    "sg:province":"SA",
    "sg:tags":[
        "merchant",
        "eftpos",
        "facility"
    ],
    "wof:name":"Access Cash ATMs",
    "wof:placetype":"venue"
},
  "geometry": {"coordinates":[138.59971618599999,-34.8811836243],"type":"Point"}
}