{
  "type": "Feature",
  "properties": {
    "iso:country":"AU",
    "sg:address":"96 Victoria St",
    "sg:city":"Richmond North",
    "sg:classifiers":[
        {
            "category":"Health Services",
            "subcategory":"Health Practitioner",
            "type":"Services"
        }
    ],
    "sg:phone":"+61 3 9428 9982",
    "sg:postcode":"3121",
    "sg:province":"VIC",
    "sg:tags":[
        "acupuncture"
    ],
    "wof:name":"Bessie Bi Qian Wang",
    "wof:placetype":"venue"
},
  "geometry": {"coordinates":[144.99478149399999,-37.8100662231],"type":"Point"}
}