{
  "type": "Feature",
  "properties": {
    "addr:full":"Unit 7 \"Axis On Main\" 55 Main St Pialba QLD 4655",
    "addr:housenumber":"55",
    "addr:postcode":"4655",
    "addr:street":"Main St",
    "iso:country":"AU",
    "sg:address":"Unit 7 \"Axis On Main\" 55 Main St",
    "sg:city":"Pialba",
    "sg:classifiers":[
        {
            "category":"Professional",
            "subcategory":"Engineering",
            "type":"Services"
        }
    ],
    "sg:phone":"+61 7 4124 5455",
    "sg:postcode":"4655",
    "sg:province":"QLD",
    "sg:tags":[
        "consulting",
        "engineer"
    ],
    "wof:name":"Cardno",
    "wof:placetype":"venue"
},
  "geometry": {"coordinates":[152.83843999999999,-25.285608],"type":"Point"}
}