{
  "type": "Feature",
  "properties": {
    "addr:full":"27 Cameron St Brunswick VIC 3056",
    "addr:housenumber":"27",
    "addr:postcode":"3056",
    "addr:street":"Cameron St",
    "iso:country":"AU",
    "sg:address":"27 Cameron St",
    "sg:city":"Brunswick",
    "sg:classifiers":[
        {
            "category":"Wholesale",
            "subcategory":"Durable Goods & Equipment",
            "type":"Manufacturing & Wholesale Goods"
        }
    ],
    "sg:phone":"+61 3 9386 7122",
    "sg:postcode":"3056",
    "sg:province":"VIC",
    "sg:tags":[
        "logging",
        "sawmilling"
    ],
    "wof:name":"Camco Cutting Tools Pty Ltd",
    "wof:placetype":"venue"
},
  "geometry": {"coordinates":[144.96188354500001,-37.7576255798],"type":"Point"}
}