{
  "type": "Feature",
  "properties": {
    "addr:full":"Cnr Shute Harbour Rd & The Esplanade Airlie Beach QLD 4802",
    "addr:postcode":"4802",
    "addr:street":"Cnr Shute Harbour Rd & The Esplanade",
    "iso:country":"AU",
    "sg:address":"Cnr Shute Harbour Rd",
    "sg:city":"& The Esplanade Airlie Beach",
    "sg:classifiers":[
        {
            "category":"Travel",
            "subcategory":"Travel Agent",
            "type":"Entertainment"
        }
    ],
    "sg:phone":"+61 7 4946 6255",
    "sg:postcode":"4802",
    "sg:province":"QLD",
    "sg:tags":[
        "consultant"
    ],
    "wof:name":"Travelscene Whitsunday",
    "wof:placetype":"venue"
},
  "geometry": {"coordinates":[148.71969604500001,-20.2692375183],"type":"Point"}
}