{
  "type": "Feature",
  "properties": {
    "addr:full":"117 Kilkenny Rd Somersby NSW 2250",
    "addr:housenumber":"117",
    "addr:postcode":"2250",
    "addr:street":"Kilkenny Rd",
    "iso:country":"AU",
    "sg:address":"117 Kilkenny Rd",
    "sg:city":"Somersby",
    "sg:classifiers":[
        {
            "category":"Home & Garden",
            "subcategory":"Garden Supply",
            "type":"Retail Goods"
        }
    ],
    "sg:phone":"+61 2 4372 2008",
    "sg:postcode":"2250",
    "sg:province":"NSW",
    "sg:tags":[
        "turf",
        "lawn"
    ],
    "wof:name":"Sawtell Turf",
    "wof:placetype":"venue"
},
  "geometry": {"coordinates":[151.29292297399999,-33.3394813538],"type":"Point"}
}