{
  "type": "Feature",
  "properties": {
    "iso:country":"AU",
    "sg:address":"120 Hoddle St",
    "sg:city":"Abbotsford",
    "sg:classifiers":[
        {
            "category":"Banks & Credit Unions",
            "subcategory":"Bank",
            "type":"Services"
        }
    ],
    "sg:phone":"+61 3 8415 0011",
    "sg:postcode":"3067",
    "sg:province":"VIC",
    "sg:tags":[
        "equipment",
        "sale",
        "point"
    ],
    "wof:name":"Lotus Cash Register",
    "wof:placetype":"venue"
},
  "geometry": {"coordinates":[144.992462158,-37.8046607971],"type":"Point"}
}