{
  "type": "Feature",
  "properties": {
    "addr:full":"649 Springvale Rd Mulgrave VIC 3170",
    "addr:housenumber":"649",
    "addr:postcode":"3170",
    "addr:street":"Springvale Rd",
    "iso:country":"AU",
    "sg:address":"649 Springvale Rd",
    "sg:city":"Mulgrave",
    "sg:classifiers":[
        {
            "category":"Utilities",
            "subcategory":"Telephone",
            "type":"Services"
        }
    ],
    "sg:phone":"+61 13 16 32",
    "sg:postcode":"3170",
    "sg:province":"VIC",
    "sg:tags":[
        "installation",
        "system",
        "maintenance"
    ],
    "wof:name":"NEC Business Solutions",
    "wof:placetype":"venue"
},
  "geometry": {"coordinates":[145.159301758,-37.9125938416],"type":"Point"}
}