{
  "type": "Feature",
  "properties": {
    "addr:full":"188 Bridge Rd Richmond VIC 3121",
    "addr:housenumber":"188",
    "addr:postcode":"3121",
    "addr:street":"Bridge Rd",
    "iso:country":"AU",
    "sg:address":"188 Bridge Rd",
    "sg:city":"Richmond",
    "sg:classifiers":[
        {
            "category":"Shopping",
            "subcategory":"Shoes",
            "type":"Retail Goods"
        }
    ],
    "sg:phone":"+61 3 9427 0820",
    "sg:postcode":"3121",
    "sg:province":"VIC",
    "sg:tags":[
        "footwear"
    ],
    "wof:name":"Aboh Enterprizes Pty Ltd",
    "wof:placetype":"venue"
},
  "geometry": {"coordinates":[144.99659729000001,-37.8184051514],"type":"Point"}
}