{
  "type": "Feature",
  "properties": {
    "addr:full":"19 Emerson St Toowong QLD 4066",
    "addr:housenumber":"19",
    "addr:postcode":"4066",
    "addr:street":"Emerson St",
    "iso:country":"AU",
    "sg:address":"19 Emerson St",
    "sg:city":"Toowong",
    "sg:classifiers":[
        {
            "category":"Real Estate",
            "subcategory":"Architect",
            "type":"Services"
        }
    ],
    "sg:phone":"+61 7 3870 9612",
    "sg:postcode":"4066",
    "sg:province":"QLD",
    "wof:name":"Cyber ARTS",
    "wof:placetype":"venue"
},
  "geometry": {"coordinates":[152.976104736,-27.4828262329],"type":"Point"}
}