{
  "type": "Feature",
  "properties": {
    "addr:full":"68- 70 Albion St Kyabram VIC 3620",
    "addr:housenumber":"70",
    "addr:postcode":"3620",
    "addr:street":"Albion St",
    "iso:country":"AU",
    "sg:address":"68- 70 Albion St",
    "sg:city":"Kyabram",
    "sg:classifiers":[
        {
            "category":"Retail",
            "subcategory":"Auto Repair",
            "type":"Services"
        }
    ],
    "sg:phone":"+61 3 5852 2329",
    "sg:postcode":"3620",
    "sg:province":"VIC",
    "sg:tags":[
        "recapping",
        "repairing",
        "retreading",
        "tyre"
    ],
    "wof:name":"D & S Tyre Service",
    "wof:placetype":"venue"
},
  "geometry": {"coordinates":[145.049728394,-36.3097076416],"type":"Point"}
}