{
  "type": "Feature",
  "properties": {
    "addr:full":"60 Export Drv Molendinar QLD 4214",
    "addr:housenumber":"60",
    "addr:postcode":"4214",
    "addr:street":"Export Drv",
    "iso:country":"AU",
    "sg:address":"60 Export Drv",
    "sg:city":"Molendinar",
    "sg:classifiers":[
        {
            "category":"Professional",
            "subcategory":"Business Services",
            "type":"Services"
        }
    ],
    "sg:phone":"+61 7 5574 4888",
    "sg:postcode":"4214",
    "sg:province":"QLD",
    "sg:tags":[
        "drafting"
    ],
    "wof:name":"Active Engineering & Design",
    "wof:placetype":"venue"
},
  "geometry": {"coordinates":[153.360305786,-27.9674873352],"type":"Point"}
}