{
  "type": "Feature",
  "properties": {
    "iso:country":"AU",
    "sg:address":"5 Norah Ave",
    "sg:city":"Wodonga",
    "sg:classifiers":[
        {
            "category":"Building & Trades",
            "subcategory":"Construction",
            "type":"Services"
        }
    ],
    "sg:phone":"+61 2 6056 8411",
    "sg:postcode":"3689",
    "sg:province":"VIC",
    "sg:tags":[
        "earth",
        "excavating",
        "moving",
        "contractor"
    ],
    "wof:name":"Lefoe P",
    "wof:placetype":"venue"
},
  "geometry": {"coordinates":[146.876938,-36.123783],"type":"Point"}
}