{
  "type": "Feature",
  "properties": {
    "addr:full":"1076 Sydney Rd Fawkner VIC 3060",
    "addr:housenumber":"1076",
    "addr:postcode":"3060",
    "addr:street":"Sydney Rd",
    "iso:country":"AU",
    "sg:address":"1076 Sydney Rd",
    "sg:city":"Fawkner",
    "sg:classifiers":[
        {
            "category":"Retail",
            "subcategory":"Auto Repair",
            "type":"Services"
        }
    ],
    "sg:phone":"+61 3 9359 1496",
    "sg:postcode":"3060",
    "sg:province":"VIC",
    "sg:tags":[
        "transmission",
        "automotive",
        "car"
    ],
    "wof:name":"A.C.T.S Automatic Cars Transmission Specialists",
    "wof:placetype":"venue"
},
  "geometry": {"coordinates":[144.96299743599999,-37.7177696228],"type":"Point"}
}