{
  "type": "Feature",
  "properties": {
    "addr:full":"Unit 5/ 60 Fairford Rd Padstow NSW 2211",
    "addr:housenumber":"60",
    "addr:postcode":"2211",
    "addr:street":"Fairford Rd",
    "iso:country":"AU",
    "sg:address":"Unit 5/ 60 Fairford Rd",
    "sg:city":"Padstow",
    "sg:classifiers":[
        {
            "category":"Building & Trades",
            "subcategory":"Plumbing",
            "type":"Services"
        }
    ],
    "sg:phone":"+61 2 9790 8479",
    "sg:postcode":"2211",
    "sg:province":"NSW",
    "sg:tags":[
        "plumber",
        "gasfitters"
    ],
    "wof:name":"Inform Energy Pty Ltd",
    "wof:placetype":"venue"
},
  "geometry": {"coordinates":[151.03627,-33.938194],"type":"Point"}
}