{
  "type": "Feature",
  "properties": {
    "addr:full":"37 Henderson Rd Clayton VIC 3168",
    "addr:housenumber":"37",
    "addr:postcode":"3168",
    "addr:street":"Henderson Rd",
    "iso:country":"AU",
    "sg:address":"37 Henderson Rd",
    "sg:city":"Clayton",
    "sg:classifiers":[
        {
            "category":"Manufacturing",
            "subcategory":"Metals",
            "type":"Manufacturing & Wholesale Goods"
        }
    ],
    "sg:phone":"+61 3 9545 1662",
    "sg:postcode":"3168",
    "sg:province":"VIC",
    "sg:tags":[
        "sheet",
        "worker"
    ],
    "wof:name":"Flashco",
    "wof:placetype":"venue"
},
  "geometry": {"coordinates":[145.14523315400001,-37.91355896],"type":"Point"}
}