{
  "type": "Feature",
  "properties": {
    "addr:full":"161 Gilbert St Latrobe TAS 7307",
    "addr:housenumber":"161",
    "addr:postcode":"7307",
    "addr:street":"Gilbert St",
    "iso:country":"AU",
    "sg:address":"161 Gilbert St",
    "sg:city":"Latrobe",
    "sg:classifiers":[
        {
            "category":"Travel",
            "subcategory":"Hotels & Motels",
            "type":"Entertainment"
        }
    ],
    "sg:phone":"+61 3 6426 1142",
    "sg:postcode":"7307",
    "sg:province":"TAS",
    "sg:tags":[
        "accommodation"
    ],
    "wof:name":"Mackey's Royal Hotel",
    "wof:placetype":"venue"
},
  "geometry": {"coordinates":[146.414703,-41.235836],"type":"Point"}
}