{
  "type": "Feature",
  "properties": {
    "iso:country":"AU",
    "sg:address":"Buccaneer Drv",
    "sg:city":"Urangan",
    "sg:classifiers":[
        {
            "category":"Conference Center",
            "type":"Public Place"
        }
    ],
    "sg:phone":"+61 7 4197 8200",
    "sg:postcode":"4655",
    "sg:province":"QLD",
    "sg:tags":[
        "venue",
        "convention"
    ],
    "wof:name":"Outrigger Hervey Bay",
    "wof:placetype":"venue"
},
  "geometry": {"coordinates":[152.908646,-25.293362],"type":"Point"}
}