{
  "type": "Feature",
  "properties": {
    "addr:full":"Shop 101 Westfield Shoppingtown Warrawong NSW 2502",
    "addr:housenumber":"101",
    "addr:postcode":"2502",
    "addr:street":"Westfield Shoppingtown",
    "iso:country":"AU",
    "sg:address":"Shop 101",
    "sg:city":"Westfield Shoppingtown Warrawong",
    "sg:classifiers":[
        {
            "category":"Health Services",
            "subcategory":"Doctor",
            "type":"Services"
        }
    ],
    "sg:phone":"+61 2 4274 6855",
    "sg:postcode":"2502",
    "sg:province":"NSW",
    "sg:tags":[
        "medical",
        "practitioner"
    ],
    "wof:name":"Pauline G J Radiolgst",
    "wof:placetype":"venue"
},
  "geometry": {"coordinates":[150.88922099999999,-34.486359],"type":"Point"}
}