{
  "type": "Feature",
  "properties": {
    "iso:country":"AU",
    "sg:address":"Shop 13, One Park Rd",
    "sg:city":"Milton",
    "sg:classifiers":[
        {
            "category":"Shopping",
            "subcategory":"Clothing, Apparel, & Fashions",
            "type":"Retail Goods"
        }
    ],
    "sg:phone":"+61 7 3511 4222",
    "sg:postcode":"4064",
    "sg:province":"QLD",
    "sg:tags":[
        "lingerie",
        "hosiery",
        "sleepwear"
    ],
    "wof:name":"Spirit Of Life Boutique",
    "wof:placetype":"venue"
},
  "geometry": {"coordinates":[153.00378418,-27.4693546295],"type":"Point"}
}