{
  "type": "Feature",
  "properties": {
    "addr:full":"Unit 2, 16- 18 Barry Rd Chipping Norton NSW 2170",
    "addr:housenumber":"16 18",
    "addr:postcode":"2170",
    "addr:street":"Barry Rd",
    "iso:country":"AU",
    "sg:address":"Unit 2, 16- 18 Barry Rd",
    "sg:city":"Chipping Norton",
    "sg:classifiers":[
        {
            "category":"Wholesale",
            "subcategory":"Painting Supplies",
            "type":"Manufacturing & Wholesale Goods"
        }
    ],
    "sg:phone":"+61 2 9755 2125",
    "sg:postcode":"2170",
    "sg:province":"NSW",
    "sg:tags":[
        "product",
        "cleaning"
    ],
    "wof:name":"Nu-Line Resources",
    "wof:placetype":"venue"
},
  "geometry": {"coordinates":[150.96420288100001,-33.9152374268],"type":"Point"}
}