{
  "type": "Feature",
  "properties": {
    "addr:full":"Shop 2 & 3, 26 River Esp Mooloolaba QLD 4557",
    "addr:housenumber":"shop 2 &;26",
    "addr:postcode":"4557",
    "addr:street":"3",
    "iso:country":"AU",
    "sg:address":"Shop 2 & 3, 26",
    "sg:city":"River Esp Mooloolaba",
    "sg:classifiers":[
        {
            "category":"Retail",
            "subcategory":"Laundry & Dry Cleaning",
            "type":"Services"
        }
    ],
    "sg:phone":"+61 7 5444 6233",
    "sg:postcode":"4557",
    "sg:province":"QLD",
    "sg:tags":[
        "manicurist"
    ],
    "wof:name":"Hoi Polloi Beauty Centre",
    "wof:placetype":"venue"
},
  "geometry": {"coordinates":[153.12054443400001,-26.6822242737],"type":"Point"}
}