{
  "type": "Feature",
  "properties": {
    "addr:full":"Denna St Maroochydore QLD 4558",
    "addr:postcode":"4558",
    "addr:street":"Denna St",
    "iso:country":"AU",
    "sg:address":"Denna St",
    "sg:city":"Maroochydore",
    "sg:classifiers":[
        {
            "category":"Food & Beverages",
            "subcategory":"Groceries & Convenience Stores",
            "type":"Retail Goods"
        }
    ],
    "sg:phone":"+61 7 5479 3732",
    "sg:postcode":"4558",
    "sg:province":"QLD",
    "wof:name":"Maroochy Waters Five Star",
    "wof:placetype":"venue"
},
  "geometry": {"coordinates":[153.068634033,-26.6447734833],"type":"Point"}
}