{
  "type": "Feature",
  "properties": {
    "iso:country":"AU",
    "sg:address":"Careel Bay Wharf, 94 George St",
    "sg:city":"Avalon",
    "sg:classifiers":[
        {
            "category":"Recreation",
            "subcategory":"Fishing",
            "type":"Entertainment"
        }
    ],
    "sg:phone":"+61 2 9918 3914",
    "sg:postcode":"2107",
    "sg:province":"NSW",
    "sg:tags":[
        "trip"
    ],
    "sg:website":"http://www.avfish.com",
    "wof:name":"A Avfish Charters",
    "wof:placetype":"venue"
},
  "geometry": {"coordinates":[151.32220459000001,-33.6210784912],"type":"Point"}
}