{
  "type": "Feature",
  "properties": {
    "addr:full":"15 Dickson Ave Artarmon NSW 2064",
    "addr:housenumber":"15",
    "addr:postcode":"2064",
    "addr:street":"Dickson Ave",
    "iso:country":"AU",
    "sg:address":"15 Dickson Ave",
    "sg:city":"Artarmon",
    "sg:classifiers":[
        {
            "category":"Retail",
            "subcategory":"Auto Repair",
            "type":"Services"
        }
    ],
    "sg:phone":"+61 2 9438 3830",
    "sg:postcode":"2064",
    "sg:province":"NSW",
    "sg:tags":[
        "repairer",
        "motor",
        "engineer"
    ],
    "sg:website":"http://www.reliableauto.com.au",
    "wof:name":"Reliable Automotive Services",
    "wof:placetype":"venue"
},
  "geometry": {"coordinates":[151.185256958,-33.8152503967],"type":"Point"}
}