{
  "type": "Feature",
  "properties": {
    "addr:full":"150 Belair Rd Hawthorn SA 5062",
    "addr:housenumber":"150",
    "addr:postcode":"5062",
    "addr:street":"Belair Rd",
    "iso:country":"AU",
    "sg:address":"150 Belair Rd",
    "sg:city":"Hawthorn",
    "sg:classifiers":[
        {
            "category":"Education",
            "subcategory":"Kindergarten",
            "type":"Public Place"
        }
    ],
    "sg:phone":"+61 8 8271 2042",
    "sg:postcode":"5062",
    "sg:province":"SA",
    "sg:tags":[
        "pre-schools"
    ],
    "wof:name":"Mitcham Pre-School Centre",
    "wof:placetype":"venue"
},
  "geometry": {"coordinates":[138.608932495,-34.9717025757],"type":"Point"}
}