{
  "type": "Feature",
  "properties": {
    "addr:full":"Maronghi Creek Rd Harlin QLD 4306",
    "addr:postcode":"4306",
    "addr:street":"Creek Rd",
    "iso:country":"AU",
    "sg:address":"Maronghi Creek Rd",
    "sg:city":"Harlin",
    "sg:classifiers":[
        {
            "category":"Farming",
            "subcategory":"Farm",
            "type":"Manufacturing & Wholesale Goods"
        }
    ],
    "sg:phone":"+61 7 5423 5135",
    "sg:postcode":"4306",
    "sg:province":"QLD",
    "sg:tags":[
        "farmer"
    ],
    "wof:name":"Humphreys P E & J D",
    "wof:placetype":"venue"
},
  "geometry": {"coordinates":[152.32437133799999,-26.9852275848],"type":"Point"}
}