{
  "type": "Feature",
  "properties": {
    "addr:full":"Shop 7b Bi-Lo Old Town Mall 211 Old South Rd Old Reynella SA 5161",
    "addr:housenumber":"shop 7b bi-lo;211",
    "addr:postcode":"5161",
    "addr:street":"Old South Rd",
    "iso:country":"AU",
    "sg:address":"Shop 7b Bi-Lo Old Town Mall 211 Old South Rd",
    "sg:city":"Old Reynella",
    "sg:classifiers":[
        {
            "category":"Health Services",
            "subcategory":"Chiropractor",
            "type":"Services"
        }
    ],
    "sg:phone":"+61 8 8387 8033",
    "sg:postcode":"5161",
    "sg:province":"SA",
    "wof:name":"Wingfield Ben Dr",
    "wof:placetype":"venue"
},
  "geometry": {"coordinates":[138.541625977,-35.0886993408],"type":"Point"}
}