{
  "type": "Feature",
  "properties": {
    "addr:full":"35 Coate Ave Alphington VIC 3078",
    "addr:housenumber":"35",
    "addr:postcode":"3078",
    "addr:street":"Coate Ave",
    "iso:country":"AU",
    "sg:address":"35 Coate Ave",
    "sg:city":"Alphington",
    "sg:classifiers":[
        {
            "category":"Travel",
            "subcategory":"Hotels & Motels",
            "type":"Entertainment"
        }
    ],
    "sg:phone":"+61 3 9488 1188",
    "sg:postcode":"3078",
    "sg:province":"VIC",
    "wof:name":"Alphington Quest Apartments",
    "wof:placetype":"venue"
},
  "geometry": {"coordinates":[145.02430725100001,-37.7821998596],"type":"Point"}
}