{
  "type": "Feature",
  "properties": {
    "addr:full":"Cnr Nicholson and Drayton Sts Dalby QLD 4405",
    "addr:postcode":"4405",
    "addr:street":"Cnr Nicholson",
    "iso:country":"AU",
    "sg:address":"Cnr Nicholson and Drayton Sts",
    "sg:city":"Dalby",
    "sg:classifiers":[
        {
            "category":"Autos & Motor Vehicles",
            "subcategory":"Automobile Sales",
            "type":"Retail Goods"
        }
    ],
    "sg:phone":"+61 7 4669 9616",
    "sg:postcode":"4405",
    "sg:province":"QLD",
    "sg:tags":[
        "car",
        "used"
    ],
    "wof:name":"Western 4X4 Cars & Commercials",
    "wof:placetype":"venue"
},
  "geometry": {"coordinates":[151.25869750999999,-27.1788253784],"type":"Point"}
}