{
  "type": "Feature",
  "properties": {
    "addr:full":"2- 6 Cumberland Ave Smithfield (Cairns) QLD 4878",
    "addr:housenumber":"6",
    "addr:postcode":"4878",
    "addr:street":"Cumberland Ave",
    "iso:country":"AU",
    "sg:address":"2- 6 Cumberland Ave",
    "sg:city":"Smithfield (Cairns)",
    "sg:classifiers":[
        {
            "category":"Personal",
            "type":"Services"
        }
    ],
    "sg:phone":"+61 7 4038 2944",
    "sg:postcode":"4878",
    "sg:province":"QLD",
    "sg:tags":[
        "career",
        "counselling"
    ],
    "wof:name":"Neato Employment Services",
    "wof:placetype":"venue"
},
  "geometry": {"coordinates":[145.689208984,-16.8383102417],"type":"Point"}
}