{
  "type": "Feature",
  "properties": {
    "addr:full":"Level 1, 700 Nicholson St Fitzroy North VIC 3068",
    "addr:housenumber":"700",
    "addr:postcode":"3068",
    "addr:street":"Nicholson St",
    "iso:country":"AU",
    "sg:address":"Level 1, 700 Nicholson St",
    "sg:city":"Fitzroy North",
    "sg:classifiers":[
        {
            "category":"Organizations",
            "subcategory":"Professional Association",
            "type":"Services"
        }
    ],
    "sg:phone":"+61 1300 853 820",
    "sg:postcode":"3068",
    "sg:province":"VIC",
    "sg:tags":[
        "web",
        "internet"
    ],
    "wof:name":"Super Sites (supersites)",
    "wof:placetype":"venue"
},
  "geometry": {"coordinates":[144.97784423799999,-37.7831001282],"type":"Point"}
}