{
  "type": "Feature",
  "properties": {
    "iso:country":"AU",
    "sg:address":"97 Wallgrove Rd",
    "sg:city":"Cecil Park",
    "sg:classifiers":[
        {
            "category":"Building & Trades",
            "subcategory":"Construction",
            "type":"Services"
        }
    ],
    "sg:phone":"+61 410 318 609",
    "sg:postcode":"2171",
    "sg:province":"NSW",
    "sg:tags":[
        "spouting",
        "guttering"
    ],
    "wof:name":"Hadley Fascia & Guttering Pty Ltd",
    "wof:placetype":"venue"
},
  "geometry": {"coordinates":[150.85174560600001,-33.819606781],"type":"Point"}
}