{
  "type": "Feature",
  "properties": {
    "addr:full":"302a Darling St Balmain NSW 2041",
    "addr:housenumber":"302a",
    "addr:postcode":"2041",
    "addr:street":"Darling St",
    "iso:country":"AU",
    "sg:address":"302a Darling St",
    "sg:city":"Balmain",
    "sg:classifiers":[
        {
            "category":"Personal",
            "subcategory":"Beauty Salon",
            "type":"Services"
        }
    ],
    "sg:phone":"+61 2 9818 2908",
    "sg:postcode":"2041",
    "sg:province":"NSW",
    "wof:name":"Powder Puff Face & Body Care",
    "wof:placetype":"venue"
},
  "geometry": {"coordinates":[151.180466,-33.857426],"type":"Point"}
}