{
  "type": "Feature",
  "properties": {
    "addr:full":"212 Richardson Rd North Rockhampton QLD 4701",
    "addr:housenumber":"212",
    "addr:postcode":"4701",
    "addr:street":"Richardson Rd North",
    "iso:country":"AU",
    "sg:address":"212 Richardson Rd",
    "sg:city":"North Rockhampton",
    "sg:classifiers":[
        {
            "category":"Utilities",
            "type":"Services"
        }
    ],
    "sg:phone":"+61 7 4931 4099",
    "sg:postcode":"4701",
    "sg:province":"QLD",
    "sg:tags":[
        "refrigeration",
        "industrial",
        "commercial",
        "retail"
    ],
    "wof:name":"BPM Cowlrick",
    "wof:placetype":"venue"
},
  "geometry": {"coordinates":[150.52348327600001,-23.3396911621],"type":"Point"}
}