{
  "type": "Feature",
  "properties": {
    "iso:country":"AU",
    "sg:address":"50 Meeks St",
    "sg:city":"Kingsford",
    "sg:classifiers":[
        {
            "category":"Social Services",
            "subcategory":"Retirement Home",
            "type":"Services"
        }
    ],
    "sg:phone":"+61 2 9399 6630",
    "sg:postcode":"2032",
    "sg:province":"NSW",
    "sg:tags":[
        "environmental",
        "consultant",
        "pollution"
    ],
    "wof:name":"Wasteplan Consultancy",
    "wof:placetype":"venue"
},
  "geometry": {"coordinates":[151.233032227,-33.9230728149],"type":"Point"}
}