{
  "type": "Feature",
  "properties": {
    "addr:full":"Unit 22, 8 Riverland Dr Loganholme QLD 4129",
    "addr:housenumber":"8",
    "addr:postcode":"4129",
    "addr:street":"Riverland Dr",
    "iso:country":"AU",
    "sg:address":"Unit 22, 8 Riverland Dr",
    "sg:city":"Loganholme",
    "sg:classifiers":[
        {
            "category":"Manufacturing",
            "subcategory":"Apparel",
            "type":"Manufacturing & Wholesale Goods"
        }
    ],
    "sg:phone":"+61 7 3806 3444",
    "sg:postcode":"4129",
    "sg:province":"QLD",
    "sg:tags":[
        "wholesaler",
        "mfrs",
        "footwear"
    ],
    "wof:name":"Terry Marks Agencies",
    "wof:placetype":"venue"
},
  "geometry": {"coordinates":[153.191696167,-27.6838436127],"type":"Point"}
}