{
  "type": "Feature",
  "properties": {
    "iso:country":"AU",
    "sg:address":"Ryley St",
    "sg:city":"Wangaratta",
    "sg:classifiers":[
        {
            "category":"Travel",
            "subcategory":"Hotels & Motels",
            "type":"Entertainment"
        }
    ],
    "sg:phone":"+61 1800 032 475",
    "sg:postcode":"3677",
    "sg:province":"VIC",
    "wof:name":"Parkview Motor Inn",
    "wof:placetype":"venue"
},
  "geometry": {"coordinates":[146.31637573200001,-36.3591995239],"type":"Point"}
}