{
  "type": "Feature",
  "properties": {
    "addr:full":"1st Flr, 84 Kiora Rd (Cnr Urunga Pde) Miranda NSW 2228",
    "addr:housenumber":"84",
    "addr:postcode":"2228",
    "addr:street":"Kiora Rd Cnr Urunga Pde Miranda",
    "iso:country":"AU",
    "sg:address":"1st Flr, 84 Kiora Rd (Cnr Urunga Pde)",
    "sg:city":"Miranda",
    "sg:classifiers":[
        {
            "category":"Professional",
            "subcategory":"Accounting & Tax Preparation",
            "type":"Services"
        }
    ],
    "sg:phone":"+61 2 9526 2410",
    "sg:postcode":"2228",
    "sg:province":"NSW",
    "sg:tags":[
        "consultant",
        "taxation"
    ],
    "wof:name":"H&R Block",
    "wof:placetype":"venue"
},
  "geometry": {"coordinates":[151.10293579099999,-34.0357589722],"type":"Point"}
}