{
  "type": "Feature",
  "properties": {
    "iso:country":"AU",
    "sg:address":"292 Beardy St",
    "sg:city":"Armidale",
    "sg:classifiers":[
        {
            "category":"Organizations",
            "subcategory":"Non-profit Organization",
            "type":"Services"
        }
    ],
    "sg:phone":"+61 2 6772 9060",
    "sg:postcode":"2350",
    "sg:province":"NSW",
    "sg:tags":[
        "support",
        "disability",
        "organisation"
    ],
    "wof:name":"Post School Options",
    "wof:placetype":"venue"
},
  "geometry": {"coordinates":[151.653762817,-30.5100078583],"type":"Point"}
}