{
  "type": "Feature",
  "properties": {
    "addr:full":"21/613 Hampton St Brighton VIC 3186",
    "addr:housenumber":"21 / 613",
    "addr:postcode":"3186",
    "addr:street":"Hampton St",
    "iso:country":"AU",
    "sg:address":"21/613 Hampton St",
    "sg:city":"Brighton",
    "sg:classifiers":[
        {
            "category":"Building & Trades",
            "subcategory":"Plumbing",
            "type":"Services"
        }
    ],
    "sg:phone":"+61 438 835 205",
    "sg:postcode":"3186",
    "sg:province":"VIC",
    "sg:tags":[
        "plumber",
        "gasfitters"
    ],
    "wof:name":"Miller Plumbing & Gas Fitting",
    "wof:placetype":"venue"
},
  "geometry": {"coordinates":[145.00395202600001,-37.9288406372],"type":"Point"}
}