{
  "type": "Feature",
  "properties": {
    "addr:full":"Merindah Rd Baulkham Hills NSW 2153",
    "addr:postcode":"2153",
    "addr:street":"Merindah Rd",
    "iso:country":"AU",
    "sg:address":"Merindah Rd",
    "sg:city":"Baulkham Hills",
    "sg:classifiers":[
        {
            "category":"Retail",
            "subcategory":"Auto Repair",
            "type":"Services"
        }
    ],
    "sg:phone":"+61 2 9624 4793",
    "sg:postcode":"2153",
    "sg:province":"NSW",
    "sg:tags":[
        "repairer",
        "motor",
        "engineer"
    ],
    "wof:name":"Merindah Service Centre",
    "wof:placetype":"venue"
},
  "geometry": {"coordinates":[150.963012695,-33.7555809021],"type":"Point"}
}