{
  "type": "Feature",
  "properties": {
    "addr:full":"6 Clark St Horsham VIC 3400",
    "addr:housenumber":"6",
    "addr:postcode":"3400",
    "addr:street":"Clark St",
    "iso:country":"AU",
    "sg:address":"6 Clark St",
    "sg:city":"Horsham",
    "sg:classifiers":[
        {
            "category":"Retail",
            "subcategory":"Repair Shop",
            "type":"Services"
        }
    ],
    "sg:phone":"+61 3 5382 0650",
    "sg:postcode":"3400",
    "sg:province":"VIC",
    "sg:tags":[
        "machine",
        "repairs",
        "part",
        "dryer",
        "washing"
    ],
    "wof:name":"Horsham Appliance Repairs",
    "wof:placetype":"venue"
},
  "geometry": {"coordinates":[142.20347595199999,-36.718208313],"type":"Point"}
}