{
  "type": "Feature",
  "properties": {
    "iso:country":"AU",
    "sg:address":"24 Belmore St",
    "sg:city":"Maitland",
    "sg:classifiers":[
        {
            "category":"Autos & Motor Vehicles",
            "subcategory":"Auto Supplies",
            "type":"Retail Goods"
        }
    ],
    "sg:phone":"+61 2 4933 6799",
    "sg:postcode":"2320",
    "sg:province":"NSW",
    "sg:tags":[
        "tyre"
    ],
    "wof:name":"Beaurepaires",
    "wof:placetype":"venue"
},
  "geometry": {"coordinates":[151.55986023,-32.7271080017],"type":"Point"}
}