{
  "type": "Feature",
  "properties": {
    "addr:full":"144 Cabramatta Rd (East) Cabramatta NSW 2166",
    "addr:housenumber":"144",
    "addr:postcode":"2166",
    "addr:street":"Cabramatta Rd East",
    "iso:country":"AU",
    "sg:address":"144 Cabramatta Rd (East)",
    "sg:city":"Cabramatta",
    "sg:classifiers":[
        {
            "category":"Health Services",
            "subcategory":"Doctor",
            "type":"Services"
        }
    ],
    "sg:phone":"+61 2 9724 5678",
    "sg:postcode":"2166",
    "sg:province":"NSW",
    "sg:tags":[
        "medical",
        "practitioner"
    ],
    "wof:name":"Ultrasound- Nuclear Medicine",
    "wof:placetype":"venue"
},
  "geometry": {"coordinates":[150.90351867699999,-33.8947181702],"type":"Point"}
}