{
  "type": "Feature",
  "properties": {
    "iso:country":"AU",
    "sg:address":"134 Wakaden St",
    "sg:city":"Griffith",
    "sg:classifiers":[
        {
            "category":"School Buses",
            "type":"Transportation"
        }
    ],
    "sg:phone":"+61 2 6964 1699",
    "sg:postcode":"2680",
    "sg:province":"NSW",
    "sg:tags":[
        "brick"
    ],
    "wof:name":"Midcity Brick & Tile",
    "wof:placetype":"venue"
},
  "geometry": {"coordinates":[146.052246,-34.286057],"type":"Point"}
}