{
  "type": "Feature",
  "properties": {
    "addr:full":"860 Albany Hwy Victoria Park WA 6100",
    "addr:housenumber":"860",
    "addr:postcode":"6100",
    "addr:street":"Albany Hwy Victoria",
    "iso:country":"AU",
    "sg:address":"860 Albany Hwy",
    "sg:city":"Victoria Park",
    "sg:classifiers":[
        {
            "category":"Communications",
            "subcategory":"Film & Video Production",
            "type":"Services"
        }
    ],
    "sg:phone":"+61 8 9472 5220",
    "sg:postcode":"6100",
    "sg:province":"WA",
    "sg:tags":[
        "dvd",
        "library"
    ],
    "wof:name":"Video Ezy",
    "wof:placetype":"venue"
},
  "geometry": {"coordinates":[115.897911072,-31.9751224518],"type":"Point"}
}