{
  "type": "Feature",
  "properties": {
    "iso:country":"AU",
    "sg:address":"81- 89 Garrick St",
    "sg:city":"Collinsville",
    "sg:classifiers":[
        {
            "category":"Health Services",
            "subcategory":"Doctor",
            "type":"Services"
        }
    ],
    "sg:phone":"+61 7 4785 5344",
    "sg:postcode":"4804",
    "sg:province":"QLD",
    "sg:tags":[
        "medical",
        "practitioner"
    ],
    "wof:name":"Singh Manjit Dr",
    "wof:placetype":"venue"
},
  "geometry": {"coordinates":[147.83847045900001,-20.5456924438],"type":"Point"}
}