{
  "type": "Feature",
  "properties": {
    "addr:full":"Lvl 3/ 770 George St Sydney NSW 2000",
    "addr:housenumber":"/ 770",
    "addr:postcode":"2000",
    "addr:street":"George St",
    "iso:country":"AU",
    "sg:address":"Lvl 3/ 770 George St",
    "sg:city":"Sydney",
    "sg:classifiers":[
        {
            "category":"Education",
            "subcategory":"University",
            "type":"Public Place"
        }
    ],
    "sg:phone":"+61 2 9211 4577",
    "sg:postcode":"2000",
    "sg:province":"NSW",
    "sg:tags":[
        "college",
        "tertiary"
    ],
    "wof:name":"Sterling College",
    "wof:placetype":"venue"
},
  "geometry": {"coordinates":[151.20512390100001,-33.8806800842],"type":"Point"}
}