{
  "type": "Feature",
  "properties": {
    "addr:full":"221a Darlinghurst Rd Darlinghurst NSW 2010",
    "addr:housenumber":"221a",
    "addr:postcode":"2010",
    "addr:street":"Darlinghurst Rd",
    "iso:country":"AU",
    "sg:address":"221a Darlinghurst Rd",
    "sg:city":"Darlinghurst",
    "sg:classifiers":[
        {
            "category":"Professional",
            "subcategory":"Secretarial Services",
            "type":"Services"
        }
    ],
    "sg:phone":"+61 2 9360 5156",
    "sg:postcode":"2010",
    "sg:province":"NSW",
    "sg:tags":[
        "typing"
    ],
    "wof:name":"Resume Assistance - Darlinghurst",
    "wof:placetype":"venue"
},
  "geometry": {"coordinates":[151.220413208,-33.8777999878],"type":"Point"}
}