{
  "type": "Feature",
  "properties": {
    "addr:full":"Argyle St Moss Vale NSW 2577",
    "addr:postcode":"2577",
    "addr:street":"Argyle St",
    "iso:country":"AU",
    "sg:address":"Argyle St",
    "sg:city":"Moss Vale",
    "sg:classifiers":[
        {
            "category":"Real Estate",
            "subcategory":"Real Estate Services",
            "type":"Services"
        }
    ],
    "sg:phone":"+61 418 483 300",
    "sg:postcode":"2577",
    "sg:province":"NSW",
    "sg:tags":[
        "valuer"
    ],
    "wof:name":"Avery Jim V. (Lic) Moss Vale",
    "wof:placetype":"venue"
},
  "geometry": {"coordinates":[150.371185303,-34.5501174927],"type":"Point"}
}