{
  "type": "Feature",
  "properties": {
    "addr:full":"Lytton St Warra QLD 4411",
    "addr:postcode":"4411",
    "addr:street":"Lytton St",
    "iso:country":"AU",
    "sg:address":"Lytton St",
    "sg:city":"Warra",
    "sg:classifiers":[
        {
            "category":"Commercial Area",
            "type":"Public Place"
        }
    ],
    "sg:phone":"+61 7 4668 1106",
    "sg:postcode":"4411",
    "sg:province":"QLD",
    "sg:tags":[
        "heavy",
        "carrier"
    ],
    "wof:name":"Henderson R W",
    "wof:placetype":"venue"
},
  "geometry": {"coordinates":[150.91891479500001,-26.9305992126],"type":"Point"}
}