{
  "type": "Feature",
  "properties": {
    "iso:country":"AU",
    "sg:address":"Lvl 1/ 893 Stanley St",
    "sg:city":"Woolloongabba",
    "sg:classifiers":[
        {
            "category":"Real Estate",
            "subcategory":"Real Estate Operator",
            "type":"Services"
        }
    ],
    "sg:phone":"+61 7 3217 3700",
    "sg:postcode":"4102",
    "sg:province":"QLD",
    "sg:tags":[
        "building",
        "consultant",
        "management"
    ],
    "wof:name":"Hannan- Eagle Project Management",
    "wof:placetype":"venue"
},
  "geometry": {"coordinates":[153.040924072,-27.4874000549],"type":"Point"}
}