{
  "type": "Feature",
  "properties": {
    "addr:full":"218 McCaffrey Drv Rankin Park NSW 2287",
    "addr:housenumber":"218",
    "addr:postcode":"2287",
    "addr:street":"Mccaffrey Drv Rankin",
    "iso:country":"AU",
    "sg:address":"218 McCaffrey Drv",
    "sg:city":"Rankin Park",
    "sg:classifiers":[
        {
            "category":"Building & Trades",
            "subcategory":"Construction",
            "type":"Services"
        }
    ],
    "sg:phone":"+61 2 4965 5074",
    "sg:postcode":"2287",
    "sg:province":"NSW",
    "sg:tags":[
        "fencing",
        "contractor"
    ],
    "wof:name":"Hutchings Aluminium",
    "wof:placetype":"venue"
},
  "geometry": {"coordinates":[151.67848205600001,-32.9212493896],"type":"Point"}
}