{
  "type": "Feature",
  "properties": {
    "addr:full":"33 Irrigation Rd Merrylands West NSW 2160",
    "addr:housenumber":"33",
    "addr:postcode":"2160",
    "addr:street":"Irrigation Rd",
    "iso:country":"AU",
    "sg:address":"33 Irrigation Rd",
    "sg:city":"Merrylands West",
    "sg:classifiers":[
        {
            "category":"Food & Beverages",
            "subcategory":"Bakery",
            "type":"Retail Goods"
        }
    ],
    "sg:phone":"+61 2 9631 1660",
    "sg:postcode":"2160",
    "sg:province":"NSW",
    "sg:tags":[
        "cake",
        "shop",
        "pastry"
    ],
    "wof:name":"Meno's Pastizzi",
    "wof:placetype":"venue"
},
  "geometry": {"coordinates":[150.96571350100001,-33.828578949],"type":"Point"}
}