{
  "type": "Feature",
  "properties": {
    "iso:country":"AU",
    "sg:address":"78 High St",
    "sg:city":"Wodonga",
    "sg:classifiers":[
        {
            "category":"Home & Garden",
            "subcategory":"Carpets & Floor Coverings",
            "type":"Retail Goods"
        }
    ],
    "sg:phone":"+61 2 6024 7388",
    "sg:postcode":"3690",
    "sg:province":"VIC",
    "sg:tags":[
        "layer",
        "planner"
    ],
    "wof:name":"Middleton's Carpets",
    "wof:placetype":"venue"
},
  "geometry": {"coordinates":[146.88987731899999,-36.1181869507],"type":"Point"}
}