{
  "type": "Feature",
  "properties": {
    "addr:full":"27 Carey St Bunbury WA 6230",
    "addr:housenumber":"27",
    "addr:postcode":"6230",
    "addr:street":"Carey St",
    "iso:country":"AU",
    "sg:address":"27 Carey St",
    "sg:city":"Bunbury",
    "sg:classifiers":[
        {
            "category":"Banks & Credit Unions",
            "subcategory":"Financial Services",
            "type":"Services"
        }
    ],
    "sg:phone":"+61 8 9721 5444",
    "sg:postcode":"6230",
    "sg:province":"WA",
    "sg:tags":[
        "planning"
    ],
    "wof:name":"Prophet Financial Advice Pty Ltd",
    "wof:placetype":"venue"
},
  "geometry": {"coordinates":[115.63758900000001,-33.319843],"type":"Point"}
}