{
  "type": "Feature",
  "properties": {
    "iso:country":"AU",
    "sg:address":"38 Akonna St",
    "sg:city":"Wynnum",
    "sg:classifiers":[
        {
            "category":"Real Estate",
            "subcategory":"Architect",
            "type":"Services"
        }
    ],
    "sg:phone":"+61 7 3893 0028",
    "sg:postcode":"4178",
    "sg:province":"QLD",
    "wof:name":"Arctech Studios",
    "wof:placetype":"venue"
},
  "geometry": {"coordinates":[153.17738342300001,-27.4463844299],"type":"Point"}
}