{
  "type": "Feature",
  "properties": {
    "iso:country":"AU",
    "sg:address":"6 Rola Pl",
    "sg:city":"Burnie",
    "sg:classifiers":[
        {
            "category":"Building & Trades",
            "subcategory":"Construction",
            "type":"Services"
        }
    ],
    "sg:phone":"+61 3 6432 4404",
    "sg:postcode":"7320",
    "sg:province":"TAS",
    "sg:tags":[
        "roof"
    ],
    "wof:name":"Butlers Roofing Services",
    "wof:placetype":"venue"
},
  "geometry": {"coordinates":[145.897293,-41.067406],"type":"Point"}
}