{
  "type": "Feature",
  "properties": {
    "iso:country":"AU",
    "sg:address":"Trentham Rd",
    "sg:city":"Musk",
    "sg:classifiers":[
        {
            "category":"Farming",
            "subcategory":"Farm",
            "type":"Manufacturing & Wholesale Goods"
        }
    ],
    "sg:phone":"+61 3 5348 5527",
    "sg:postcode":"3461",
    "sg:province":"VIC",
    "sg:tags":[
        "farmer"
    ],
    "wof:name":"Gruer B R",
    "wof:placetype":"venue"
},
  "geometry": {"coordinates":[144.313034058,-37.3705558777],"type":"Point"}
}