{
  "type": "Feature",
  "properties": {
    "iso:country":"AU",
    "sg:address":"Suite 700/701a Diagonal Rd",
    "sg:city":"Westfield Marion Oaklands Park",
    "sg:classifiers":[
        {
            "category":"Professional",
            "subcategory":"Employment Agencies",
            "type":"Services"
        }
    ],
    "sg:phone":"+61 8 8306 3333",
    "sg:postcode":"5046",
    "sg:province":"SA",
    "wof:name":"Campbell Page",
    "wof:placetype":"venue"
},
  "geometry": {"coordinates":[138.54364,-35.013016],"type":"Point"}
}