{
  "type": "Feature",
  "properties": {
    "addr:full":"18 Wollongong St Fyshwick ACT 2609",
    "addr:housenumber":"18",
    "addr:postcode":"2609",
    "addr:street":"Wollongong St",
    "iso:country":"AU",
    "sg:address":"18 Wollongong St",
    "sg:city":"Fyshwick",
    "sg:classifiers":[
        {
            "category":"Home & Garden",
            "subcategory":"Carpets & Floor Coverings",
            "type":"Retail Goods"
        }
    ],
    "sg:phone":"+61 2 6280 0550",
    "sg:postcode":"2609",
    "sg:province":"ACT",
    "sg:tags":[
        "mattress"
    ],
    "wof:name":"Futons Express",
    "wof:placetype":"venue"
},
  "geometry": {"coordinates":[149.17817688,-35.3271141052],"type":"Point"}
}