{
  "type": "Feature",
  "properties": {
    "addr:full":"58 Barry St Bayswater VIC 3153",
    "addr:housenumber":"58",
    "addr:postcode":"3153",
    "addr:street":"Barry St",
    "iso:country":"AU",
    "sg:address":"58 Barry St",
    "sg:city":"Bayswater",
    "sg:classifiers":[
        {
            "category":"Retail",
            "subcategory":"Auto Repair",
            "type":"Services"
        }
    ],
    "sg:phone":"+61 3 9761 0166",
    "sg:postcode":"3153",
    "sg:province":"VIC",
    "sg:tags":[
        "electrical"
    ],
    "wof:name":"All Power Auto Electrics",
    "wof:placetype":"venue"
},
  "geometry": {"coordinates":[145.28248596200001,-37.8479804993],"type":"Point"}
}