{
  "type": "Feature",
  "properties": {
    "addr:full":"14 Sunnyside Ave Dandenong VIC 3175",
    "addr:housenumber":"14",
    "addr:postcode":"3175",
    "addr:street":"Sunnyside Ave",
    "iso:country":"AU",
    "sg:address":"14 Sunnyside Ave",
    "sg:city":"Dandenong",
    "sg:classifiers":[
        {
            "category":"Personal",
            "subcategory":"Massage",
            "type":"Services"
        }
    ],
    "sg:phone":"+61 405 184 792",
    "sg:postcode":"3175",
    "sg:province":"VIC",
    "sg:tags":[
        "therapy"
    ],
    "wof:name":"Marys Massage Therapy",
    "wof:placetype":"venue"
},
  "geometry": {"coordinates":[145.22299194300001,-37.9821510315],"type":"Point"}
}