{
  "type": "Feature",
  "properties": {
    "addr:full":"PO Box 101 Boolaroo NSW 2284",
    "addr:postcode":"2284",
    "iso:country":"AU",
    "sg:address":"PO Box 101",
    "sg:city":"Boolaroo",
    "sg:classifiers":[
        {
            "category":"Building & Trades",
            "subcategory":"Construction",
            "type":"Services"
        }
    ],
    "sg:phone":"+61 2 4958 7024",
    "sg:postcode":"2284",
    "sg:province":"NSW",
    "sg:tags":[
        "brick",
        "paving"
    ],
    "wof:name":"Barretts Landscaping Services",
    "wof:placetype":"venue"
},
  "geometry": {"coordinates":[151.61907959000001,-32.9506492615],"type":"Point"}
}