{
  "type": "Feature",
  "properties": {
    "addr:full":"452 Swift St Albury NSW 2640",
    "addr:housenumber":"452",
    "addr:postcode":"2640",
    "addr:street":"Swift St",
    "iso:country":"AU",
    "sg:address":"452 Swift St",
    "sg:city":"Albury",
    "sg:classifiers":[
        {
            "category":"Government",
            "subcategory":"Court House",
            "type":"Public Place"
        }
    ],
    "sg:phone":"+61 2 6021 0012",
    "sg:postcode":"2640",
    "sg:province":"NSW",
    "sg:tags":[
        "personal",
        "marriage",
        "family",
        "counselling"
    ],
    "wof:name":"Sowden Lanning Dr",
    "wof:placetype":"venue"
},
  "geometry": {"coordinates":[146.91635131800001,-36.0787887573],"type":"Point"}
}