{
  "type": "Feature",
  "properties": {
    "addr:full":"17 Cunningham St Dalby QLD 4405",
    "addr:housenumber":"17",
    "addr:postcode":"4405",
    "addr:street":"Cunningham St",
    "iso:country":"AU",
    "sg:address":"17 Cunningham St",
    "sg:city":"Dalby",
    "sg:classifiers":[
        {
            "category":"Shopping",
            "subcategory":"Clothing, Apparel, & Fashions",
            "type":"Retail Goods"
        }
    ],
    "sg:phone":"+61 7 4669 8030",
    "sg:postcode":"4405",
    "sg:province":"QLD",
    "sg:tags":[
        "lady",
        "wear"
    ],
    "wof:name":"Lills Liberty Lane",
    "wof:placetype":"venue"
},
  "geometry": {"coordinates":[151.26716613799999,-27.1807975769],"type":"Point"}
}