{
  "type": "Feature",
  "properties": {
    "addr:full":"18 Scott St Beaumaris VIC 3193",
    "addr:housenumber":"18",
    "addr:postcode":"3193",
    "addr:street":"Scott St",
    "iso:country":"AU",
    "sg:address":"18 Scott St",
    "sg:city":"Beaumaris",
    "sg:classifiers":[
        {
            "category":"Retail",
            "subcategory":"Repair Shop",
            "type":"Services"
        }
    ],
    "sg:phone":"+61 3 9589 3096",
    "sg:postcode":"3193",
    "sg:province":"VIC",
    "sg:tags":[
        "repairing",
        "piano",
        "tuning"
    ],
    "wof:name":"Allan W Hill Piano Services",
    "wof:placetype":"venue"
},
  "geometry": {"coordinates":[145.03953552199999,-37.9891777039],"type":"Point"}
}