{
  "type": "Feature",
  "properties": {
    "iso:country":"AU",
    "sg:address":"61 Denison St",
    "sg:city":"Bondi Junction",
    "sg:classifiers":[
        {
            "category":"Banks & Credit Unions",
            "subcategory":"Investment Brokerage",
            "type":"Services"
        }
    ],
    "sg:phone":"+61 2 9387 4911",
    "sg:postcode":"2022",
    "sg:province":"NSW",
    "sg:tags":[
        "management",
        "property"
    ],
    "wof:name":"Century 21 Tony Moses",
    "wof:placetype":"venue"
},
  "geometry": {"coordinates":[151.24464416500001,-33.892780304],"type":"Point"}
}