{
  "type": "Feature",
  "properties": {
    "addr:full":"Newton Plaza 297 Montacute Rd Newton SA 5074",
    "addr:housenumber":"297",
    "addr:postcode":"5074",
    "addr:street":"Montacute Rd",
    "iso:country":"AU",
    "sg:address":"Newton Plaza 297 Montacute Rd",
    "sg:city":"Newton",
    "sg:classifiers":[
        {
            "category":"Government",
            "subcategory":"Post Office",
            "type":"Public Place"
        }
    ],
    "sg:phone":"+61 8 8337 2557",
    "sg:postcode":"5074",
    "sg:province":"SA",
    "sg:tags":[
        "postal"
    ],
    "wof:name":"Australia Post",
    "wof:placetype":"venue"
},
  "geometry": {"coordinates":[138.69015502900001,-34.8867454529],"type":"Point"}
}