{
  "type": "Feature",
  "properties": {
    "addr:full":"Shop 4 48 Newcastle St Morisset NSW 2264",
    "addr:housenumber":"shop;48",
    "addr:postcode":"2264",
    "addr:street":"Newcastle St",
    "iso:country":"AU",
    "sg:address":"Shop 4 48 Newcastle St",
    "sg:city":"Morisset",
    "sg:classifiers":[
        {
            "category":"Real Estate",
            "subcategory":"Developer",
            "type":"Services"
        }
    ],
    "sg:phone":"+61 2 4973 2745",
    "sg:postcode":"2264",
    "sg:province":"NSW",
    "sg:tags":[
        "development"
    ],
    "wof:name":"Evans & Smith Consulting Surveyors Pty Ltd",
    "wof:placetype":"venue"
},
  "geometry": {"coordinates":[151.487076,-33.106697],"type":"Point"}
}