{
  "type": "Feature",
  "properties": {
    "addr:full":"PO Box 53 Claremont WA 6910",
    "addr:postcode":"6910",
    "iso:country":"AU",
    "sg:address":"PO Box 53",
    "sg:city":"Claremont",
    "sg:classifiers":[
        {
            "category":"Retail",
            "subcategory":"Funeral Services",
            "type":"Services"
        }
    ],
    "sg:phone":"+61 8 9383 5200",
    "sg:postcode":"6910",
    "sg:province":"WA",
    "sg:tags":[
        "cemetery"
    ],
    "wof:name":"Metropolitan Cemeteries Board",
    "wof:placetype":"venue"
},
  "geometry": {"coordinates":[115.77961731000001,-31.9812297821],"type":"Point"}
}