{
  "type": "Feature",
  "properties": {
    "iso:country":"AU",
    "sg:address":"27 Alfreda St",
    "sg:city":"Coogee",
    "sg:classifiers":[
        {
            "category":"Banks & Credit Unions",
            "subcategory":"Bureau De Change",
            "type":"Services"
        }
    ],
    "sg:phone":"+61 2 9664 2901",
    "sg:postcode":"2034",
    "sg:province":"NSW",
    "sg:tags":[
        "control",
        "equipment",
        "compressed",
        "air"
    ],
    "wof:name":"Pro-Diving Services Pty Ltd",
    "wof:placetype":"venue"
},
  "geometry": {"coordinates":[151.25636291500001,-33.9201545715],"type":"Point"}
}