{
  "type": "Feature",
  "properties": {
    "addr:full":"14/ 417 Warrigal Rd Cheltenham VIC 3192",
    "addr:housenumber":"14 / 417",
    "addr:postcode":"3192",
    "addr:street":"Warrigal Rd",
    "iso:country":"AU",
    "sg:address":"14/ 417 Warrigal Rd",
    "sg:city":"Cheltenham",
    "sg:classifiers":[
        {
            "category":"Professional",
            "subcategory":"Computer Services",
            "type":"Services"
        }
    ],
    "sg:phone":"+61 3 9532 3003",
    "sg:postcode":"3192",
    "sg:province":"VIC",
    "sg:tags":[
        "repairs",
        "upgrade",
        "equipment"
    ],
    "wof:name":"Anything Technical",
    "wof:placetype":"venue"
},
  "geometry": {"coordinates":[145.077102661,-37.9501686096],"type":"Point"}
}