{
  "type": "Feature",
  "properties": {
    "iso:country":"AU",
    "sg:address":"97 Springvale Rd",
    "sg:city":"Springvale",
    "sg:classifiers":[
        {
            "category":"Fast Food",
            "type":"Food & Drink"
        }
    ],
    "sg:phone":"+61 3 9546 6700",
    "sg:postcode":"3171",
    "sg:province":"VIC",
    "sg:tags":[
        "away",
        "take"
    ],
    "wof:name":"Pizza Malibu",
    "wof:placetype":"venue"
},
  "geometry": {"coordinates":[145.15443420400001,-37.9416351318],"type":"Point"}
}