{
  "type": "Feature",
  "properties": {
    "iso:country":"AU",
    "sg:address":"21 Chullwyne Mews",
    "sg:city":"High Wycombe",
    "sg:classifiers":[
        {
            "category":"Education",
            "subcategory":"School",
            "type":"Public Place"
        }
    ],
    "sg:phone":"+61 8 9352 8852",
    "sg:postcode":"6057",
    "sg:province":"WA",
    "sg:tags":[
        "teaching",
        "aid"
    ],
    "wof:name":"Praxis Productions",
    "wof:placetype":"venue"
},
  "geometry": {"coordinates":[115.99819946300001,-31.9336929321],"type":"Point"}
}