{
  "type": "Feature",
  "properties": {
    "addr:full":"Glengala Rd Sunshine VIC 3020",
    "addr:postcode":"3020",
    "addr:street":"Glengala Rd",
    "iso:country":"AU",
    "sg:address":"Glengala Rd",
    "sg:city":"Sunshine",
    "sg:classifiers":[
        {
            "category":"Travel",
            "subcategory":"Hotels & Motels",
            "type":"Entertainment"
        }
    ],
    "sg:phone":"+61 3 9361 1007",
    "sg:postcode":"3020",
    "sg:province":"VIC",
    "sg:tags":[
        "pub"
    ],
    "wof:name":"Glengala Hotel",
    "wof:placetype":"venue"
},
  "geometry": {"coordinates":[144.80261200000001,-37.787453],"type":"Point"}
}