{
  "type": "Feature",
  "properties": {
    "addr:full":"Ground Floor 8 Thomas St Chatswood NSW 2067",
    "addr:housenumber":"8",
    "addr:postcode":"2067",
    "addr:street":"Thomas St",
    "iso:country":"AU",
    "sg:address":"Ground Floor 8 Thomas St",
    "sg:city":"Chatswood",
    "sg:classifiers":[
        {
            "category":"Banks & Credit Unions",
            "subcategory":"Investment Brokerage",
            "type":"Services"
        }
    ],
    "sg:phone":"+61 2 9411 8988",
    "sg:postcode":"2067",
    "sg:province":"NSW",
    "sg:tags":[
        "share",
        "broker",
        "stock"
    ],
    "wof:name":"ABN AMRO Morgans",
    "wof:placetype":"venue"
},
  "geometry": {"coordinates":[151.180130005,-33.7981834412],"type":"Point"}
}