{
  "type": "Feature",
  "properties": {
    "addr:full":"8-12 Mavis Rd Morayfield QLD 4506",
    "addr:housenumber":"8-12",
    "addr:postcode":"4506",
    "addr:street":"Mavis Rd",
    "iso:country":"AU",
    "sg:address":"8-12 Mavis Rd",
    "sg:city":"Morayfield",
    "sg:classifiers":[
        {
            "category":"Personal",
            "subcategory":"Massage",
            "type":"Services"
        }
    ],
    "sg:phone":"+61 7 5433 0123",
    "sg:postcode":"4506",
    "sg:province":"QLD",
    "sg:tags":[
        "therapy"
    ],
    "wof:name":"Morayfield Bowen Therapy",
    "wof:placetype":"venue"
},
  "geometry": {"coordinates":[152.94456481899999,-27.1380748749],"type":"Point"}
}