{
  "type": "Feature",
  "properties": {
    "addr:full":"1A Wattle Drv Frankston VIC 3199",
    "addr:housenumber":"1a",
    "addr:postcode":"3199",
    "addr:street":"Wattle Drv",
    "iso:country":"AU",
    "sg:address":"1A Wattle Drv",
    "sg:city":"Frankston",
    "sg:classifiers":[
        {
            "category":"Building & Trades",
            "subcategory":"Plumbing",
            "type":"Services"
        }
    ],
    "sg:phone":"+61 3 9789 1761",
    "sg:postcode":"3199",
    "sg:province":"VIC",
    "sg:tags":[
        "plumber",
        "gasfitters"
    ],
    "wof:name":"Bayside Roof Plumbing",
    "wof:placetype":"venue"
},
  "geometry": {"coordinates":[145.237060547,-37.9982757568],"type":"Point"}
}