{
  "type": "Feature",
  "properties": {
    "addr:full":"PO Box 320 Kilkenny SA 5009",
    "addr:postcode":"5009",
    "iso:country":"AU",
    "sg:address":"PO Box 320",
    "sg:city":"Kilkenny",
    "sg:classifiers":[
        {
            "category":"Building & Trades",
            "subcategory":"Locksmith",
            "type":"Services"
        }
    ],
    "sg:phone":"+61 417 838 503",
    "sg:postcode":"5009",
    "sg:province":"SA",
    "sg:tags":[
        "lock"
    ],
    "wof:name":"A Arndale Locksmiths",
    "wof:placetype":"venue"
},
  "geometry": {"coordinates":[138.54966735799999,-34.8821411133],"type":"Point"}
}