{
  "type": "Feature",
  "properties": {
    "addr:full":"Factory 1 5- 7 Adrian Rd Campbellfield VIC 3061",
    "addr:housenumber":"5 7",
    "addr:postcode":"3061",
    "addr:street":"Adrian Rd",
    "iso:country":"AU",
    "sg:address":"Factory 1 5- 7 Adrian Rd",
    "sg:city":"Campbellfield",
    "sg:classifiers":[
        {
            "category":"Building & Trades",
            "subcategory":"Construction",
            "type":"Services"
        }
    ],
    "sg:phone":"+61 3 9357 8155",
    "sg:postcode":"3061",
    "sg:province":"VIC",
    "sg:tags":[
        "contractor"
    ],
    "wof:name":"Mallia Builders (Vic) Pty Ltd",
    "wof:placetype":"venue"
},
  "geometry": {"coordinates":[144.960250855,-37.6631584167],"type":"Point"}
}