{
  "type": "Feature",
  "properties": {
    "addr:full":"8/ 42 Mann St Gosford NSW 2250",
    "addr:housenumber":"/ 42",
    "addr:postcode":"2250",
    "addr:street":"Mann St",
    "iso:country":"AU",
    "sg:address":"8/ 42 Mann St",
    "sg:city":"Gosford",
    "sg:classifiers":[
        {
            "category":"Real Estate",
            "subcategory":"Developer",
            "type":"Services"
        }
    ],
    "sg:phone":"+61 2 4323 1255",
    "sg:postcode":"2250",
    "sg:province":"NSW",
    "sg:tags":[
        "development"
    ],
    "wof:name":"Stephen Thorne & Associates Pty Ltd",
    "wof:placetype":"venue"
},
  "geometry": {"coordinates":[151.341308594,-33.4287071228],"type":"Point"}
}