{
  "type": "Feature",
  "properties": {
    "addr:full":"Unit 3/ 348 Manns Rd Gosford West NSW 2250",
    "addr:housenumber":"/ 348",
    "addr:postcode":"2250",
    "addr:street":"Manns Rd",
    "iso:country":"AU",
    "sg:address":"Unit 3/ 348 Manns Rd",
    "sg:city":"Gosford West",
    "sg:classifiers":[
        {
            "category":"Building & Trades",
            "subcategory":"Construction",
            "type":"Services"
        }
    ],
    "sg:phone":"+61 2 4324 8055",
    "sg:postcode":"2250",
    "sg:province":"NSW",
    "sg:tags":[
        "window",
        "timber"
    ],
    "wof:name":"Town & Country Conservatories Pty Ltd",
    "wof:placetype":"venue"
},
  "geometry": {"coordinates":[151.31935119600001,-33.4246940613],"type":"Point"}
}