{
  "type": "Feature",
  "properties": {
    "iso:country":"AU",
    "sg:address":"Muchow Rd",
    "sg:city":"Waterford West",
    "sg:classifiers":[
        {
            "category":"Education",
            "subcategory":"School",
            "type":"Public Place"
        }
    ],
    "sg:phone":"+61 7 3299 0555",
    "sg:postcode":"4133",
    "sg:province":"QLD",
    "sg:tags":[
        "state",
        "except",
        "nsw"
    ],
    "wof:name":"Marsden High",
    "wof:placetype":"venue"
},
  "geometry": {"coordinates":[153.12106323200001,-27.6861076355],"type":"Point"}
}