{
  "type": "Feature",
  "properties": {
    "iso:country":"AU",
    "sg:address":"38 Janay Rd",
    "sg:city":"Kabra",
    "sg:classifiers":[
        {
            "category":"Building & Trades",
            "subcategory":"Plumbing",
            "type":"Services"
        }
    ],
    "sg:phone":"+61 7 4933 3074",
    "sg:postcode":"4702",
    "sg:province":"QLD",
    "sg:tags":[
        "pump",
        "repairer"
    ],
    "wof:name":"McLeod R S & C G",
    "wof:placetype":"venue"
},
  "geometry": {"coordinates":[150.40657043499999,-23.4887313843],"type":"Point"}
}