{
  "type": "Feature",
  "properties": {
    "iso:country":"AU",
    "sg:address":"17 Robsart St",
    "sg:city":"Parkside",
    "sg:classifiers":[
        {
            "category":"Health Services",
            "subcategory":"Nursing And Care Facility",
            "type":"Services"
        }
    ],
    "sg:phone":"+61 8 8271 5679",
    "sg:postcode":"5063",
    "sg:province":"SA",
    "sg:tags":[
        "home"
    ],
    "wof:name":"Burnleigh Private Residential Care",
    "wof:placetype":"venue"
},
  "geometry": {"coordinates":[138.61900329599999,-34.9451179504],"type":"Point"}
}