{
  "type": "Feature",
  "properties": {
    "addr:full":"2 Tathra Rd Lambton NSW 2299",
    "addr:housenumber":"2",
    "addr:postcode":"2299",
    "addr:street":"Tathra Rd",
    "iso:country":"AU",
    "sg:address":"2 Tathra Rd",
    "sg:city":"Lambton",
    "sg:classifiers":[
        {
            "category":"Taxi",
            "type":"Transportation"
        }
    ],
    "sg:phone":"+61 407 004 525",
    "sg:postcode":"2299",
    "sg:province":"NSW",
    "sg:tags":[
        "truck"
    ],
    "wof:name":"ASAP Direct Pty Ltd",
    "wof:placetype":"venue"
},
  "geometry": {"coordinates":[151.71286010700001,-32.9130020142],"type":"Point"}
}