{
  "type": "Feature",
  "properties": {
    "iso:country":"AU",
    "sg:address":"16 Mahogany Pl",
    "sg:city":"Medowie",
    "sg:classifiers":[
        {
            "category":"Professional",
            "subcategory":"Art Services",
            "type":"Services"
        }
    ],
    "sg:phone":"+61 2 4981 7620",
    "sg:postcode":"2318",
    "sg:province":"NSW",
    "sg:tags":[
        "decorator",
        "painter"
    ],
    "wof:name":"Butora A",
    "wof:placetype":"venue"
},
  "geometry": {"coordinates":[151.84678600000001,-32.732742],"type":"Point"}
}