{
  "type": "Feature",
  "properties": {
    "iso:country":"AU",
    "sg:address":"30 Century Rd",
    "sg:city":"Malaga",
    "sg:classifiers":[
        {
            "category":"Building & Trades",
            "subcategory":"Locksmith",
            "type":"Services"
        }
    ],
    "sg:phone":"+61 8 9249 7717",
    "sg:postcode":"6090",
    "sg:province":"WA",
    "sg:tags":[
        "strongroom",
        "safe",
        "door"
    ],
    "sg:website":"http://www.ssw.net.au",
    "wof:name":"Safe & Security Wholesalers",
    "wof:placetype":"venue"
},
  "geometry": {"coordinates":[115.896850586,-31.8569145203],"type":"Point"}
}