{
  "type": "Feature",
  "properties": {
    "iso:country":"AU",
    "sg:address":"1/ 80 Adelong Rd",
    "sg:city":"Tumut",
    "sg:classifiers":[
        {
            "category":"Building & Trades",
            "subcategory":"Construction",
            "type":"Services"
        }
    ],
    "sg:phone":"+61 2 6947 6677",
    "sg:postcode":"2720",
    "sg:province":"NSW",
    "sg:tags":[
        "window",
        "tinting"
    ],
    "wof:name":"Power Tint & Installs",
    "wof:placetype":"venue"
},
  "geometry": {"coordinates":[148.212097,-35.295879],"type":"Point"}
}