{
  "type": "Feature",
  "properties": {
    "addr:full":"45 Blessington St St Kilda VIC 3182",
    "addr:housenumber":"45",
    "addr:postcode":"3182",
    "addr:street":"Blessington St",
    "iso:country":"AU",
    "sg:address":"45 Blessington St",
    "sg:city":"St Kilda",
    "sg:classifiers":[
        {
            "category":"Fast Food",
            "type":"Food & Drink"
        }
    ],
    "sg:phone":"+61 3 9525 3310",
    "sg:postcode":"3182",
    "sg:province":"VIC",
    "sg:tags":[
        "away",
        "take"
    ],
    "wof:name":"St Kilda Pizza House",
    "wof:placetype":"venue"
},
  "geometry": {"coordinates":[144.981323242,-37.8703041077],"type":"Point"}
}