{
  "type": "Feature",
  "properties": {
    "iso:country":"AU",
    "sg:address":"35 Main Rd",
    "sg:city":"Wivenhoe",
    "sg:classifiers":[
        {
            "category":"Professional",
            "subcategory":"Computer Services",
            "type":"Services"
        }
    ],
    "sg:phone":"+61 3 6431 4128",
    "sg:postcode":"7320",
    "sg:province":"TAS",
    "sg:tags":[
        "repairs",
        "upgrade",
        "equipment"
    ],
    "wof:name":"Robbies Teletrician Pty Ltd",
    "wof:placetype":"venue"
},
  "geometry": {"coordinates":[145.93512,-41.068008],"type":"Point"}
}