{
  "type": "Feature",
  "properties": {
    "iso:country":"AU",
    "sg:address":"Lvl 2/ 9 Underwood Ave",
    "sg:city":"Botany",
    "sg:classifiers":[
        {
            "category":"Professional",
            "subcategory":"Employment Agencies",
            "type":"Services"
        }
    ],
    "sg:phone":"+61 2 9666 6317",
    "sg:postcode":"2019",
    "sg:province":"NSW",
    "wof:name":"Drive Recruit Pty Ltd",
    "wof:placetype":"venue"
},
  "geometry": {"coordinates":[151.19493102999999,-33.9452018738],"type":"Point"}
}