{
  "type": "Feature",
  "properties": {
    "iso:country":"AU",
    "sg:address":"507 Highett Rd",
    "sg:city":"Highett",
    "sg:classifiers":[
        {
            "category":"Personal",
            "subcategory":"Beauty Salon",
            "type":"Services"
        }
    ],
    "sg:phone":"+61 3 9553 2429",
    "sg:postcode":"3190",
    "sg:province":"VIC",
    "sg:tags":[
        "hairdresser"
    ],
    "wof:name":"Grey Flamingo Hairdressing",
    "wof:placetype":"venue"
},
  "geometry": {"coordinates":[145.042678833,-37.9486961365],"type":"Point"}
}