{
  "type": "Feature",
  "properties": {
    "iso:country":"AU",
    "sg:address":"172 Southpine Rd",
    "sg:city":"Strathpine",
    "sg:classifiers":[
        {
            "category":"Professional",
            "subcategory":"Art Services",
            "type":"Services"
        }
    ],
    "sg:phone":"+61 7 3881 3133",
    "sg:postcode":"4500",
    "sg:province":"QLD",
    "sg:tags":[
        "graphic",
        "designer"
    ],
    "wof:name":"Kwik Kopy Printing",
    "wof:placetype":"venue"
},
  "geometry": {"coordinates":[153.004394531,-27.3167686462],"type":"Point"}
}