{
  "type": "Feature",
  "properties": {
    "iso:country":"AU",
    "sg:address":"622 Lutwyche Rd",
    "sg:city":"Lutwyche",
    "sg:classifiers":[
        {
            "category":"Health Services",
            "subcategory":"Doctor",
            "type":"Services"
        }
    ],
    "sg:phone":"+61 7 3357 6744",
    "sg:postcode":"4030",
    "sg:province":"QLD",
    "sg:tags":[
        "medical",
        "practitioner"
    ],
    "wof:name":"Ryan Barry",
    "wof:placetype":"venue"
},
  "geometry": {"coordinates":[153.034714,-27.419235],"type":"Point"}
}