{
  "type": "Feature",
  "properties": {
    "addr:full":"138 Thunderbolt Drv Raby NSW 2566",
    "addr:housenumber":"138",
    "addr:postcode":"2566",
    "addr:street":"Thunderbolt Drv",
    "iso:country":"AU",
    "sg:address":"138 Thunderbolt Drv",
    "sg:city":"Raby",
    "sg:classifiers":[
        {
            "category":"Health Services",
            "subcategory":"Doctor",
            "type":"Services"
        }
    ],
    "sg:phone":"+61 2 9820 8000",
    "sg:postcode":"2566",
    "sg:province":"NSW",
    "sg:tags":[
        "medical",
        "practitioner"
    ],
    "wof:name":"C & P Law",
    "wof:placetype":"venue"
},
  "geometry": {"coordinates":[150.81707763700001,-34.015007019],"type":"Point"}
}