{
  "type": "Feature",
  "properties": {
    "iso:country":"AU",
    "sg:address":"10/ 17 Avondale Rd",
    "sg:city":"New Lambton",
    "sg:classifiers":[
        {
            "category":"Building & Trades",
            "subcategory":"Construction",
            "type":"Services"
        }
    ],
    "sg:phone":"+61 418 274 882",
    "sg:postcode":"2305",
    "sg:province":"NSW",
    "sg:tags":[
        "welding"
    ],
    "wof:name":"Jaslie Pty Ltd",
    "wof:placetype":"venue"
},
  "geometry": {"coordinates":[151.711273,-32.920193],"type":"Point"}
}