{
  "type": "Feature",
  "properties": {
    "iso:country":"AU",
    "sg:address":"55 Bonds Rd",
    "sg:city":"Peakhurst",
    "sg:classifiers":[
        {
            "category":"Building & Trades",
            "subcategory":"Cleaning & Sanitation",
            "type":"Services"
        }
    ],
    "sg:phone":"+61 418 207 437",
    "sg:postcode":"2210",
    "sg:province":"NSW",
    "sg:tags":[
        "chemical",
        "pressure",
        "steam",
        "contractor"
    ],
    "wof:name":"Jag Cleaning",
    "wof:placetype":"venue"
},
  "geometry": {"coordinates":[151.060135,-33.954441],"type":"Point"}
}