{
  "type": "Feature",
  "properties": {
    "addr:full":"203a Ryde Rd West Pymble NSW 2073",
    "addr:housenumber":"203a",
    "addr:postcode":"2073",
    "addr:street":"Ryde Rd",
    "iso:country":"AU",
    "sg:address":"203a Ryde Rd",
    "sg:city":"West Pymble",
    "sg:classifiers":[
        {
            "category":"Real Estate",
            "subcategory":"Architect",
            "type":"Services"
        }
    ],
    "sg:phone":"+61 2 9498 7479",
    "sg:postcode":"2073",
    "sg:province":"NSW",
    "wof:name":"Pichler Albert",
    "wof:placetype":"venue"
},
  "geometry": {"coordinates":[151.136550903,-33.7675514221],"type":"Point"}
}