{
  "type": "Feature",
  "properties": {
    "addr:full":"1 Lord St Roseville NSW 2069",
    "addr:housenumber":"1",
    "addr:postcode":"2069",
    "addr:street":"Lord St",
    "iso:country":"AU",
    "sg:address":"1 Lord St",
    "sg:city":"Roseville",
    "sg:classifiers":[
        {
            "category":"Personal",
            "subcategory":"Beauty Salon",
            "type":"Services"
        }
    ],
    "sg:phone":"+61 2 9415 8982",
    "sg:postcode":"2069",
    "sg:province":"NSW",
    "sg:tags":[
        "hairdresser"
    ],
    "wof:name":"Art Success Salon",
    "wof:placetype":"venue"
},
  "geometry": {"coordinates":[151.178344727,-33.7844314575],"type":"Point"}
}