{
  "type": "Feature",
  "properties": {
    "iso:country":"AU",
    "sg:address":"Shop 15 Centrepoint Arc",
    "sg:city":"Geelong",
    "sg:classifiers":[
        {
            "category":"Personal",
            "type":"Services"
        }
    ],
    "sg:phone":"+61 3 5222 1478",
    "sg:postcode":"3220",
    "sg:province":"VIC",
    "sg:tags":[
        "dressmaker"
    ],
    "wof:name":"Flattery Designs",
    "wof:placetype":"venue"
},
  "geometry": {"coordinates":[144.361694,-38.14922],"type":"Point"}
}