{
  "type": "Feature",
  "properties": {
    "addr:full":"4- 8 Rosslyn St Mile End SA 5031",
    "addr:housenumber":"8",
    "addr:postcode":"5031",
    "addr:street":"Rosslyn St",
    "iso:country":"AU",
    "sg:address":"4- 8 Rosslyn St",
    "sg:city":"Mile End",
    "sg:classifiers":[
        {
            "category":"Utilities",
            "type":"Services"
        }
    ],
    "sg:phone":"+61 8 8234 5990",
    "sg:postcode":"5031",
    "sg:province":"SA",
    "sg:tags":[
        "refrigeration",
        "industrial",
        "commercial",
        "retail"
    ],
    "wof:name":"Quirks Australia",
    "wof:placetype":"venue"
},
  "geometry": {"coordinates":[138.573364258,-34.9317169189],"type":"Point"}
}