{
  "type": "Feature",
  "properties": {
    "addr:full":"56 Chapple St Gladstone QLD 4680",
    "addr:housenumber":"56",
    "addr:postcode":"4680",
    "addr:street":"Chapple St",
    "iso:country":"AU",
    "sg:address":"56 Chapple St",
    "sg:city":"Gladstone",
    "sg:classifiers":[
        {
            "category":"Home & Garden",
            "subcategory":"Building Materials",
            "type":"Retail Goods"
        }
    ],
    "sg:phone":"+61 7 4972 1577",
    "sg:postcode":"4680",
    "sg:province":"QLD",
    "sg:tags":[
        "fencing"
    ],
    "wof:name":"SV Steel Supplies Pty Ltd",
    "wof:placetype":"venue"
},
  "geometry": {"coordinates":[151.24078369099999,-23.8424701691],"type":"Point"}
}