{
  "type": "Feature",
  "properties": {
    "iso:country":"AU",
    "sg:address":"15-17 cherry St",
    "sg:city":"Pearcedale",
    "sg:classifiers":[
        {
            "category":"Professional",
            "subcategory":"Engineering",
            "type":"Services"
        }
    ],
    "sg:phone":"+61 3 5978 7198",
    "sg:postcode":"3912",
    "sg:province":"VIC",
    "sg:tags":[
        "aeronautical",
        "engineer"
    ],
    "wof:name":"Percy, Graham J.",
    "wof:placetype":"venue"
},
  "geometry": {"coordinates":[145.23434448200001,-38.1968536377],"type":"Point"}
}