{
  "type": "Feature",
  "properties": {
    "addr:full":"78c Port Stephens St Raymond Terrace NSW 2324",
    "addr:housenumber":"78c",
    "addr:postcode":"2324",
    "addr:street":"Port Stephens St",
    "iso:country":"AU",
    "sg:address":"78c Port Stephens St",
    "sg:city":"Raymond Terrace",
    "sg:classifiers":[
        {
            "category":"Education",
            "subcategory":"Dance Studio",
            "type":"Public Place"
        }
    ],
    "sg:phone":"+61 408 922 747",
    "sg:postcode":"2324",
    "sg:province":"NSW",
    "sg:tags":[
        "venue",
        "tuition"
    ],
    "wof:name":"Studio 2324 Raymond Terrace Dance",
    "wof:placetype":"venue"
},
  "geometry": {"coordinates":[151.742797852,-32.7607688904],"type":"Point"}
}