{
  "type": "Feature",
  "properties": {
    "addr:full":"53 Crosby Hill Rd Buderim QLD 4556",
    "addr:housenumber":"53",
    "addr:postcode":"4556",
    "addr:street":"Crosby Hill Rd",
    "iso:country":"AU",
    "sg:address":"53 Crosby Hill Rd",
    "sg:city":"Buderim",
    "sg:classifiers":[
        {
            "category":"Metro Station",
            "type":"Transportation"
        }
    ],
    "sg:phone":"+61 7 5445 1032",
    "sg:postcode":"4556",
    "sg:province":"QLD",
    "sg:tags":[
        "consultant",
        "marine"
    ],
    "wof:name":"Borlase F C",
    "wof:placetype":"venue"
},
  "geometry": {"coordinates":[153.04635620100001,-26.701385498],"type":"Point"}
}