{
  "type": "Feature",
  "properties": {
    "iso:country":"AU",
    "sg:address":"90 Greenwood St",
    "sg:city":"Wishart",
    "sg:classifiers":[
        {
            "category":"Professional",
            "subcategory":"Management & Consulting",
            "type":"Services"
        }
    ],
    "sg:phone":"+61 412 320 255",
    "sg:postcode":"4122",
    "sg:province":"QLD",
    "sg:tags":[
        "consultant"
    ],
    "wof:name":"Canham Ian Consulting",
    "wof:placetype":"venue"
},
  "geometry": {"coordinates":[153.103347778,-27.5588817596],"type":"Point"}
}