{
  "type": "Feature",
  "properties": {
    "addr:full":"12 Rosa Pl Richlands QLD 4077",
    "addr:housenumber":"12",
    "addr:postcode":"4077",
    "addr:street":"Rosa Pl",
    "iso:country":"AU",
    "sg:address":"12 Rosa Pl",
    "sg:city":"Richlands",
    "sg:classifiers":[
        {
            "category":"Building & Trades",
            "subcategory":"Construction",
            "type":"Services"
        }
    ],
    "sg:phone":"+61 7 3375 5944",
    "sg:postcode":"4077",
    "sg:province":"QLD",
    "sg:tags":[
        "contractor"
    ],
    "wof:name":"Inka Homes",
    "wof:placetype":"venue"
},
  "geometry": {"coordinates":[152.95681762699999,-27.5829715729],"type":"Point"}
}