{
  "type": "Feature",
  "properties": {
    "iso:country":"AU",
    "sg:address":"6 -12 Toppings Rd",
    "sg:city":"Wonga Park",
    "sg:classifiers":[
        {
            "category":"Building & Trades",
            "subcategory":"Plumbing",
            "type":"Services"
        }
    ],
    "sg:phone":"+61 3 9722 2244",
    "sg:postcode":"3115",
    "sg:province":"VIC",
    "sg:tags":[
        "plumber",
        "gasfitters"
    ],
    "wof:name":"Local Plumbing",
    "wof:placetype":"venue"
},
  "geometry": {"coordinates":[145.27096557600001,-37.7385520935],"type":"Point"}
}