{
  "type": "Feature",
  "properties": {
    "iso:country":"AU",
    "sg:address":"Racecourse Rd",
    "sg:city":"Pakenham",
    "sg:classifiers":[
        {
            "category":"Sports & Exercise",
            "subcategory":"Gym",
            "type":"Entertainment"
        }
    ],
    "sg:phone":"+61 3 5941 5105",
    "sg:postcode":"3810",
    "sg:province":"VIC",
    "sg:tags":[
        "health",
        "fitness"
    ],
    "wof:name":"Pakenham Fitness Factory",
    "wof:placetype":"venue"
},
  "geometry": {"coordinates":[145.492737,-38.070751],"type":"Point"}
}