{
  "type": "Feature",
  "properties": {
    "addr:full":"22 Wynyard St Belmont WA 6104",
    "addr:housenumber":"22",
    "addr:postcode":"6104",
    "addr:street":"Wynyard St",
    "iso:country":"AU",
    "sg:address":"22 Wynyard St",
    "sg:city":"Belmont",
    "sg:classifiers":[
        {
            "category":"Home & Garden",
            "subcategory":"Building Materials",
            "type":"Retail Goods"
        }
    ],
    "sg:phone":"+61 8 9479 6930",
    "sg:postcode":"6104",
    "sg:province":"WA",
    "sg:tags":[
        "shutter",
        "roller",
        "grille"
    ],
    "sg:website":"http://www.awningswa.com.au",
    "wof:name":"Awnings WA Pty Ltd",
    "wof:placetype":"venue"
},
  "geometry": {"coordinates":[115.92198944099999,-31.9514865875],"type":"Point"}
}