{
  "type": "Feature",
  "properties": {
    "iso:country":"AU",
    "sg:address":"2007 Gold Coast Hwy",
    "sg:city":"Burleigh Heads",
    "sg:classifiers":[
        {
            "category":"Travel",
            "subcategory":"Hotels & Motels",
            "type":"Entertainment"
        }
    ],
    "sg:phone":"+61 7 5535 1111",
    "sg:postcode":"4220",
    "sg:province":"QLD",
    "wof:name":"Outrigger Resort",
    "wof:placetype":"venue"
},
  "geometry": {"coordinates":[153.44515991200001,-28.0748176575],"type":"Point"}
}