{
  "type": "Feature",
  "properties": {
    "addr:full":"9 Keam St Essendon North VIC 3041",
    "addr:housenumber":"9",
    "addr:postcode":"3041",
    "addr:street":"Keam St",
    "iso:country":"AU",
    "sg:address":"9 Keam St",
    "sg:city":"Essendon North",
    "sg:classifiers":[
        {
            "category":"Shopping",
            "subcategory":"Computers & Home Electronics",
            "type":"Retail Goods"
        }
    ],
    "sg:phone":"+61 3 9374 1530",
    "sg:postcode":"3041",
    "sg:province":"VIC",
    "sg:tags":[
        "equipment",
        "part",
        "electronic"
    ],
    "wof:name":"A K Robotek",
    "wof:placetype":"venue"
},
  "geometry": {"coordinates":[144.899124145,-37.7393493652],"type":"Point"}
}