{
  "type": "Feature",
  "properties": {
    "addr:full":"1122 Glen Huntly Rd Glen Huntly VIC 3163",
    "addr:housenumber":"1122",
    "addr:postcode":"3163",
    "addr:street":"Glen Huntly Rd",
    "iso:country":"AU",
    "sg:address":"1122 Glen Huntly Rd",
    "sg:city":"Glen Huntly",
    "sg:classifiers":[
        {
            "category":"Cafe",
            "type":"Food & Drink"
        }
    ],
    "sg:phone":"+61 3 9569 2340",
    "sg:postcode":"3163",
    "sg:province":"VIC",
    "wof:name":"11 Twenty 2",
    "wof:placetype":"venue"
},
  "geometry": {"coordinates":[145.040924072,-37.8893661499],"type":"Point"}
}