{
  "type": "Feature",
  "properties": {
    "addr:full":"7 Peel St Kew VIC 3101",
    "addr:housenumber":"7",
    "addr:postcode":"3101",
    "addr:street":"Peel St",
    "iso:country":"AU",
    "sg:address":"7 Peel St",
    "sg:city":"Kew",
    "sg:classifiers":[
        {
            "category":"Food & Beverages",
            "subcategory":"Liquor & Beverages",
            "type":"Retail Goods"
        }
    ],
    "sg:phone":"+61 3 9853 1200",
    "sg:postcode":"3101",
    "sg:province":"VIC",
    "sg:tags":[
        "merchant",
        "spirit",
        "wine"
    ],
    "wof:name":"Peter Walker Wine Consultants Pty Ltd",
    "wof:placetype":"venue"
},
  "geometry": {"coordinates":[145.03305053700001,-37.8052520752],"type":"Point"}
}