{
  "type": "Feature",
  "properties": {
    "iso:country":"AU",
    "sg:address":"56 Killara Rd",
    "sg:city":"Campbellfield",
    "sg:classifiers":[
        {
            "category":"Home & Garden",
            "subcategory":"Building Materials",
            "type":"Retail Goods"
        }
    ],
    "sg:phone":"+61 3 9357 0862",
    "sg:postcode":"3061",
    "sg:province":"VIC",
    "sg:tags":[
        "shutter",
        "roller",
        "grille"
    ],
    "wof:name":"Greenvale Roller Doors",
    "wof:placetype":"venue"
},
  "geometry": {"coordinates":[144.96496582,-37.6634750366],"type":"Point"}
}