{
  "type": "Feature",
  "properties": {
    "addr:full":"Cnr Main Rd & Norfolk St Glendale NSW 2285",
    "addr:postcode":"2285",
    "addr:street":"Cnr Main Rd & Norfolk St",
    "iso:country":"AU",
    "sg:address":"Cnr Main Rd & Norfolk St",
    "sg:city":"Glendale",
    "sg:classifiers":[
        {
            "category":"Shopping",
            "subcategory":"Computers & Home Electronics",
            "type":"Retail Goods"
        }
    ],
    "sg:phone":"+61 2 4956 5540",
    "sg:postcode":"2285",
    "sg:province":"NSW",
    "sg:tags":[
        "small",
        "equipment",
        "business"
    ],
    "wof:name":"Cardiff Computers & TV",
    "wof:placetype":"venue"
},
  "geometry": {"coordinates":[151.64974975600001,-32.9301223755],"type":"Point"}
}