{
  "type": "Feature",
  "properties": {
    "addr:full":"105 Queen St Melbourne VIC 3000",
    "addr:housenumber":"105",
    "addr:postcode":"3000",
    "addr:street":"Queen St",
    "iso:country":"AU",
    "sg:address":"105 Queen St",
    "sg:city":"Melbourne",
    "sg:classifiers":[
        {
            "category":"Bars & Pubs",
            "subcategory":"Wine Bar",
            "type":"Food & Drink"
        }
    ],
    "sg:phone":"+61 3 9670 6120",
    "sg:postcode":"3000",
    "sg:province":"VIC",
    "sg:website":"http://www.chaiselounge.com.au",
    "wof:name":"Chaise Lounge",
    "wof:placetype":"venue"
},
  "geometry": {"coordinates":[144.96105957,-37.8160820007],"type":"Point"}
}