{
  "type": "Feature",
  "properties": {
    "addr:full":"PO Box 4074 Tinana QLD 4650",
    "addr:postcode":"4650",
    "iso:country":"AU",
    "sg:address":"PO Box 4074",
    "sg:city":"Tinana",
    "sg:classifiers":[
        {
            "category":"Home & Garden",
            "subcategory":"Garden Supply",
            "type":"Retail Goods"
        }
    ],
    "sg:phone":"+61 7 4123 0041",
    "sg:postcode":"4650",
    "sg:province":"QLD",
    "sg:tags":[
        "equipment"
    ],
    "wof:name":"Borderline Edging",
    "wof:placetype":"venue"
},
  "geometry": {"coordinates":[152.677628,-25.550871],"type":"Point"}
}