{
  "type": "Feature",
  "properties": {
    "iso:country":"AU",
    "sg:address":"Shop 19/ 121 Yala Rd",
    "sg:city":"Bangor",
    "sg:classifiers":[
        {
            "category":"Retail",
            "subcategory":"Car Wash",
            "type":"Services"
        }
    ],
    "sg:phone":"+61 2 9543 1199",
    "sg:postcode":"2234",
    "sg:province":"NSW",
    "sg:tags":[
        "truck",
        "cleaning"
    ],
    "wof:name":"Pink Elephant Hand Car Wash & Cafe",
    "wof:placetype":"venue"
},
  "geometry": {"coordinates":[151.030029297,-34.0182800293],"type":"Point"}
}