{
  "type": "Feature",
  "properties": {
    "addr:full":"255 Neeld St West Wyalong NSW 2671",
    "addr:housenumber":"255",
    "addr:postcode":"2671",
    "addr:street":"Neeld St West",
    "iso:country":"AU",
    "sg:address":"255 Neeld St",
    "sg:city":"West Wyalong",
    "sg:classifiers":[
        {
            "category":"Social Services",
            "subcategory":"Adult Care",
            "type":"Services"
        }
    ],
    "sg:phone":"+61 2 6972 3106",
    "sg:postcode":"2671",
    "sg:province":"NSW",
    "sg:tags":[
        "aged"
    ],
    "wof:name":"Wyalong & District Community Transport Group Inc",
    "wof:placetype":"venue"
},
  "geometry": {"coordinates":[147.201416016,-33.9222717285],"type":"Point"}
}