{
  "type": "Feature",
  "properties": {
    "addr:full":"Inala Ave Inala QLD 4077",
    "addr:postcode":"4077",
    "addr:street":"Inala Ave Inala",
    "iso:country":"AU",
    "sg:address":"Inala Ave",
    "sg:city":"Inala",
    "sg:classifiers":[
        {
            "category":"Health Services",
            "subcategory":"Doctor",
            "type":"Services"
        }
    ],
    "sg:phone":"+61 7 3372 2400",
    "sg:postcode":"4077",
    "sg:province":"QLD",
    "sg:tags":[
        "medical",
        "practitioner"
    ],
    "wof:name":"Dang Doan Dr",
    "wof:placetype":"venue"
},
  "geometry": {"coordinates":[152.98692321799999,-27.5963249207],"type":"Point"}
}