{
  "type": "Feature",
  "properties": {
    "iso:country":"AU",
    "sg:address":"960 High St",
    "sg:city":"Reservoir",
    "sg:classifiers":[
        {
            "category":"Banks & Credit Unions",
            "subcategory":"Bank",
            "type":"Services"
        }
    ],
    "sg:phone":"+61 3 9471 4744",
    "sg:postcode":"3073",
    "sg:province":"VIC",
    "sg:tags":[
        "broker",
        "mortgage"
    ],
    "wof:name":"Divine Finance Centre",
    "wof:placetype":"venue"
},
  "geometry": {"coordinates":[145.00749206500001,-37.7174682617],"type":"Point"}
}