{
  "type": "Feature",
  "properties": {
    "iso:country":"AU",
    "sg:address":"53 Pinnaroo Drv",
    "sg:city":"Padbury",
    "sg:classifiers":[
        {
            "category":"Shopping",
            "subcategory":"News",
            "type":"Retail Goods"
        }
    ],
    "sg:phone":"+61 8 9307 9887",
    "sg:postcode":"6025",
    "sg:province":"WA",
    "sg:tags":[
        "magazine",
        "periodical"
    ],
    "wof:name":"Burda Moden",
    "wof:placetype":"venue"
},
  "geometry": {"coordinates":[115.774368286,-31.8103275299],"type":"Point"}
}