{
  "type": "Feature",
  "properties": {
    "iso:country":"AU",
    "sg:address":"45 Ralston St",
    "sg:city":"South Yarra",
    "sg:classifiers":[
        {
            "category":"Personal",
            "subcategory":"Beauty Salon",
            "type":"Services"
        }
    ],
    "sg:phone":"+61 3 9820 8528",
    "sg:postcode":"3141",
    "sg:province":"VIC",
    "sg:tags":[
        "hairdresser"
    ],
    "wof:name":"Sien Hair Design",
    "wof:placetype":"venue"
},
  "geometry": {"coordinates":[144.98699951200001,-37.8384971619],"type":"Point"}
}