{
  "type": "Feature",
  "properties": {
    "addr:full":"82 Fryar Rd Eagleby QLD 4207",
    "addr:housenumber":"82",
    "addr:postcode":"4207",
    "addr:street":"Fryar Rd",
    "iso:country":"AU",
    "sg:address":"82 Fryar Rd",
    "sg:city":"Eagleby",
    "sg:classifiers":[
        {
            "category":"Social Services",
            "subcategory":"Child Care",
            "type":"Services"
        }
    ],
    "sg:phone":"+61 7 3807 3222",
    "sg:postcode":"4207",
    "sg:province":"QLD",
    "wof:name":"Playdays Child Care Centre",
    "wof:placetype":"venue"
},
  "geometry": {"coordinates":[153.211990356,-27.7075500488],"type":"Point"}
}