{
  "type": "Feature",
  "properties": {
    "addr:full":"10 Pilbara St Welshpool WA 6106",
    "addr:housenumber":"10",
    "addr:postcode":"6106",
    "addr:street":"Pilbara St",
    "iso:country":"AU",
    "sg:address":"10 Pilbara St",
    "sg:city":"Welshpool",
    "sg:classifiers":[
        {
            "category":"Social Services",
            "subcategory":"Retirement Home",
            "type":"Services"
        }
    ],
    "sg:phone":"+61 8 9458 4952",
    "sg:postcode":"6106",
    "sg:province":"WA",
    "sg:tags":[
        "environmental",
        "consultant",
        "pollution"
    ],
    "wof:name":"Neal Scholer Incineration",
    "wof:placetype":"venue"
},
  "geometry": {"coordinates":[115.937789917,-31.9947872162],"type":"Point"}
}