{
  "type": "Feature",
  "properties": {
    "addr:full":"Unit 1 1-5 Point St, Cnr William & Newman Sts Fremantle WA 6962",
    "addr:housenumber":"1-5",
    "addr:postcode":"6962",
    "addr:street":"Point St Cnr William & Newman Sts",
    "iso:country":"AU",
    "sg:address":"Unit 1 1-5 Point St, Cnr William & Newman Sts",
    "sg:city":"Fremantle",
    "sg:classifiers":[
        {
            "category":"Wholesale",
            "subcategory":"Medical Equipment & Supplies",
            "type":"Manufacturing & Wholesale Goods"
        }
    ],
    "sg:phone":"+61 8 9431 7790",
    "sg:postcode":"6962",
    "sg:province":"WA",
    "sg:tags":[
        "aids",
        "hearing"
    ],
    "wof:name":"Australian Hearing",
    "wof:placetype":"venue"
},
  "geometry": {"coordinates":[115.748299,-32.051746],"type":"Point"}
}