{
  "type": "Feature",
  "properties": {
    "iso:country":"AU",
    "sg:address":"85 Harold St",
    "sg:city":"Stafford",
    "sg:classifiers":[
        {
            "category":"Building & Trades",
            "subcategory":"Pest Control",
            "type":"Services"
        }
    ],
    "sg:phone":"+61 438 773 095",
    "sg:postcode":"4053",
    "sg:province":"QLD",
    "wof:name":"Today's Clean Sweep Pest Control & Carpet Cleaning",
    "wof:placetype":"venue"
},
  "geometry": {"coordinates":[153.00894165,-27.4081439972],"type":"Point"}
}