{
  "type": "Feature",
  "properties": {
    "iso:country":"AU",
    "sg:address":"PO Box 36",
    "sg:city":"San Remo",
    "sg:classifiers":[
        {
            "category":"Building & Trades",
            "subcategory":"Equipment Rental",
            "type":"Services"
        }
    ],
    "sg:phone":"+61 3 5956 6601",
    "sg:postcode":"3925",
    "sg:province":"VIC",
    "sg:tags":[
        "demolition",
        "contractor"
    ],
    "wof:name":"Aussie Demolition",
    "wof:placetype":"venue"
},
  "geometry": {"coordinates":[145.37376403799999,-38.5206184387],"type":"Point"}
}