{
  "type": "Feature",
  "properties": {
    "addr:full":"Druids House, level 4 407 Swanston St Melbourne VIC 3000",
    "addr:housenumber":"407",
    "addr:postcode":"3000",
    "addr:street":"Swanston St",
    "iso:country":"AU",
    "sg:address":"Druids House, level 4 407 Swanston St",
    "sg:city":"Melbourne",
    "sg:classifiers":[
        {
            "category":"Health Services",
            "subcategory":"Doctor",
            "type":"Services"
        }
    ],
    "sg:phone":"+61 3 9662 2395",
    "sg:postcode":"3000",
    "sg:province":"VIC",
    "sg:tags":[
        "podiatrist"
    ],
    "wof:name":"City Podiatry Clinic",
    "wof:placetype":"venue"
},
  "geometry": {"coordinates":[144.96331787099999,-37.8088493347],"type":"Point"}
}