{
  "type": "Feature",
  "properties": {
    "addr:full":"40 Nicholson St Essendon VIC 3040",
    "addr:housenumber":"40",
    "addr:postcode":"3040",
    "addr:street":"Nicholson St",
    "iso:country":"AU",
    "sg:address":"40 Nicholson St",
    "sg:city":"Essendon",
    "sg:classifiers":[
        {
            "category":"Cafe",
            "type":"Food & Drink"
        }
    ],
    "sg:phone":"+61 3 9326 2966",
    "sg:postcode":"3040",
    "sg:province":"VIC",
    "wof:name":"MJ Forty Cafe & Bar",
    "wof:placetype":"venue"
},
  "geometry": {"coordinates":[144.920852661,-37.7535133362],"type":"Point"}
}