{
  "type": "Feature",
  "properties": {
    "iso:country":"AU",
    "sg:address":"1/ 76 Sunnyholt Rd",
    "sg:city":"Blacktown",
    "sg:classifiers":[
        {
            "category":"Autos & Motor Vehicles",
            "subcategory":"Boat Sales",
            "type":"Retail Goods"
        }
    ],
    "sg:phone":"+61 2 9676 1400",
    "sg:postcode":"2148",
    "sg:province":"NSW",
    "sg:tags":[
        "yacht"
    ],
    "wof:name":"Watersports Marine",
    "wof:placetype":"venue"
},
  "geometry": {"coordinates":[150.911621094,-33.7712593079],"type":"Point"}
}