{
  "type": "Feature",
  "properties": {
    "iso:country":"AU",
    "sg:address":"Unit 3, 1 Evans Ave",
    "sg:city":"Moorabbin",
    "sg:classifiers":[
        {
            "category":"Professional",
            "subcategory":"Art Services",
            "type":"Services"
        }
    ],
    "sg:phone":"+61 3 9532 2825",
    "sg:postcode":"3189",
    "sg:province":"VIC",
    "sg:tags":[
        "picture",
        "frame",
        "framing"
    ],
    "wof:name":"Atkinson John",
    "wof:placetype":"venue"
},
  "geometry": {"coordinates":[145.03778076200001,-37.9442596436],"type":"Point"}
}