{
  "type": "Feature",
  "properties": {
    "addr:full":"4 Wayne Crt Dandenong VIC 3175",
    "addr:housenumber":"4",
    "addr:postcode":"3175",
    "addr:street":"Wayne Crt",
    "iso:country":"AU",
    "sg:address":"4 Wayne Crt",
    "sg:city":"Dandenong",
    "sg:classifiers":[
        {
            "category":"Retail",
            "subcategory":"Auto Repair",
            "type":"Services"
        }
    ],
    "sg:phone":"+61 3 9706 8012",
    "sg:postcode":"3175",
    "sg:province":"VIC",
    "sg:tags":[
        "repairer",
        "motor",
        "engineer"
    ],
    "wof:name":"Alfa Corse Pty Ltd",
    "wof:placetype":"venue"
},
  "geometry": {"coordinates":[145.196334839,-37.9889717102],"type":"Point"}
}