{
  "type": "Feature",
  "properties": {
    "addr:full":"479 Sydney Rd Coburg VIC 3058",
    "addr:housenumber":"479",
    "addr:postcode":"3058",
    "addr:street":"Sydney Rd",
    "iso:country":"AU",
    "sg:address":"479 Sydney Rd",
    "sg:city":"Coburg",
    "sg:classifiers":[
        {
            "category":"Shopping",
            "subcategory":"Baby Store",
            "type":"Retail Goods"
        }
    ],
    "sg:phone":"+61 3 9354 3863",
    "sg:postcode":"3058",
    "sg:province":"VIC",
    "sg:tags":[
        "children's",
        "wear"
    ],
    "wof:name":"Twiddly Dee Childrens Boutique",
    "wof:placetype":"venue"
},
  "geometry": {"coordinates":[144.966262817,-37.7419090271],"type":"Point"}
}