{
  "type": "Feature",
  "properties": {
    "iso:country":"AU",
    "sg:address":"Rear 42a Terralong St",
    "sg:city":"Kiama",
    "sg:classifiers":[
        {
            "category":"Shopping",
            "subcategory":"Party Supplies",
            "type":"Retail Goods"
        }
    ],
    "sg:phone":"+61 2 4232 2325",
    "sg:postcode":"2533",
    "sg:province":"NSW",
    "sg:tags":[
        "children's"
    ],
    "wof:name":"I Wish I Was Fairy Shop",
    "wof:placetype":"venue"
},
  "geometry": {"coordinates":[150.855026245,-34.6707611084],"type":"Point"}
}