{
  "type": "Feature",
  "properties": {
    "iso:country":"AU",
    "sg:address":"38 Lyons Rd",
    "sg:city":"Drummoyne",
    "sg:classifiers":[
        {
            "category":"Shopping",
            "subcategory":"Beauty & Cosmetics",
            "type":"Retail Goods"
        }
    ],
    "sg:phone":"+61 1300 658 499",
    "sg:postcode":"2047",
    "sg:province":"NSW",
    "sg:tags":[
        "equipment",
        "salon",
        "supply"
    ],
    "wof:name":"LHE/ Radiancy",
    "wof:placetype":"venue"
},
  "geometry": {"coordinates":[151.154343,-33.851017],"type":"Point"}
}