{
  "type": "Feature",
  "properties": {
    "iso:country":"AU",
    "sg:address":"8 Rickard Rd",
    "sg:city":"North Narrabeen",
    "sg:classifiers":[
        {
            "category":"Building & Trades",
            "subcategory":"Construction",
            "type":"Services"
        }
    ],
    "sg:phone":"+61 2 9970 8537",
    "sg:postcode":"2101",
    "sg:province":"NSW",
    "sg:tags":[
        "contractor"
    ],
    "wof:name":"Ant Building",
    "wof:placetype":"venue"
},
  "geometry": {"coordinates":[151.29530299999999,-33.708439],"type":"Point"}
}