{
  "type": "Feature",
  "properties": {
    "addr:full":"19 Smith St Capalaba QLD 4157",
    "addr:housenumber":"19",
    "addr:postcode":"4157",
    "addr:street":"Smith St",
    "iso:country":"AU",
    "sg:address":"19 Smith St",
    "sg:city":"Capalaba",
    "sg:classifiers":[
        {
            "category":"Landmark",
            "subcategory":"Scenic View",
            "type":"Public Place"
        }
    ],
    "sg:phone":"+61 7 3390 2946",
    "sg:postcode":"4157",
    "sg:province":"QLD",
    "sg:tags":[
        "staircase",
        "handrail"
    ],
    "sg:website":"http://www.stairwaysolutions.com.au",
    "wof:name":"Stairway Solutions",
    "wof:placetype":"venue"
},
  "geometry": {"coordinates":[153.19866943400001,-27.5291290283],"type":"Point"}
}