{
  "type": "Feature",
  "properties": {
    "addr:full":"95- 99 Nujooloo Rd Slacks Creek QLD 4127",
    "addr:housenumber":"99",
    "addr:postcode":"4127",
    "addr:street":"Nujooloo Rd",
    "iso:country":"AU",
    "sg:address":"95- 99 Nujooloo Rd",
    "sg:city":"Slacks Creek",
    "sg:classifiers":[
        {
            "category":"Recreation",
            "subcategory":"Boat Charter",
            "type":"Entertainment"
        }
    ],
    "sg:phone":"+61 1300 656 599",
    "sg:postcode":"4127",
    "sg:province":"QLD",
    "sg:tags":[
        "canopy",
        "motor"
    ],
    "wof:name":"Flexiglass",
    "wof:placetype":"venue"
},
  "geometry": {"coordinates":[153.15249633799999,-27.6478481293],"type":"Point"}
}