{
  "type": "Feature",
  "properties": {
    "iso:country":"AU",
    "sg:address":"64 Tennyson St",
    "sg:city":"Williamstown",
    "sg:classifiers":[
        {
            "category":"Banks & Credit Unions",
            "subcategory":"Financial Services",
            "type":"Services"
        }
    ],
    "sg:phone":"+61 3 9391 8911",
    "sg:postcode":"3016",
    "sg:province":"VIC",
    "sg:tags":[
        "wholesaler",
        "mfrs",
        "gear"
    ],
    "wof:name":"Carr Gear Company Pty Ltd",
    "wof:placetype":"venue"
},
  "geometry": {"coordinates":[144.85841369600001,-37.8524093628],"type":"Point"}
}