{
  "type": "Feature",
  "properties": {
    "iso:country":"AU",
    "sg:address":"75 Macquarie St",
    "sg:city":"Parramatta",
    "sg:classifiers":[
        {
            "category":"Banks & Credit Unions",
            "subcategory":"Bureau De Change",
            "type":"Services"
        }
    ],
    "sg:phone":"+61 1300 139 060",
    "sg:postcode":"2150",
    "sg:province":"NSW",
    "sg:tags":[
        "currency",
        "exchange",
        "foreign"
    ],
    "wof:name":"American Express Foreign Exchange Services",
    "wof:placetype":"venue"
},
  "geometry": {"coordinates":[151.180786133,-33.8944168091],"type":"Point"}
}