{
  "type": "Feature",
  "properties": {
    "addr:full":"Shop 5/ 25 Lonsdale St Braddon ACT 2612",
    "addr:housenumber":"shop 5 / 25",
    "addr:postcode":"2612",
    "addr:street":"Lonsdale St",
    "iso:country":"AU",
    "sg:address":"Shop 5/ 25 Lonsdale St",
    "sg:city":"Braddon",
    "sg:classifiers":[
        {
            "category":"Personal",
            "subcategory":"Beauty Salon",
            "type":"Services"
        }
    ],
    "sg:phone":"+61 2 6247 2016",
    "sg:postcode":"2612",
    "sg:province":"ACT",
    "sg:tags":[
        "hair",
        "treatment",
        "replacement"
    ],
    "wof:name":"UltraHair",
    "wof:placetype":"venue"
},
  "geometry": {"coordinates":[149.13279724099999,-35.2721633911],"type":"Point"}
}