{
  "type": "Feature",
  "properties": {
    "iso:country":"AU",
    "sg:address":"Unit 1/2 40 Hutton St",
    "sg:city":"Osborne Park",
    "sg:classifiers":[
        {
            "category":"Retail",
            "subcategory":"Auto Repair",
            "type":"Services"
        }
    ],
    "sg:phone":"+61 8 9345 3703",
    "sg:postcode":"6017",
    "sg:province":"WA",
    "sg:tags":[
        "clutch",
        "brake"
    ],
    "wof:name":"Balcatta Brake & Clutch",
    "wof:placetype":"venue"
},
  "geometry": {"coordinates":[115.818519592,-31.9034385681],"type":"Point"}
}