{
  "type": "Feature",
  "properties": {
    "iso:country":"AU",
    "sg:address":"Heydon Pl",
    "sg:city":"Evatt",
    "sg:classifiers":[
        {
            "category":"Shopping",
            "subcategory":"Beauty & Cosmetics",
            "type":"Retail Goods"
        }
    ],
    "sg:phone":"+61 2 6259 9200",
    "sg:postcode":"2617",
    "sg:province":"ACT",
    "wof:name":"Evatt Pharmacy",
    "wof:placetype":"venue"
},
  "geometry": {"coordinates":[149.07366943400001,-35.20911026],"type":"Point"}
}