{
  "type": "Feature",
  "properties": {
    "addr:full":"Stockland Plz 310 Ross River Rd Aitkenvale QLD 4814",
    "addr:housenumber":"310",
    "addr:postcode":"4814",
    "addr:street":"Stockland Plz;Ross River Rd",
    "iso:country":"AU",
    "sg:address":"Stockland Plz 310 Ross River Rd",
    "sg:city":"Aitkenvale",
    "sg:classifiers":[
        {
            "category":"Shopping",
            "subcategory":"Clothing, Apparel, & Fashions",
            "type":"Retail Goods"
        }
    ],
    "sg:phone":"+61 7 4775 6911",
    "sg:postcode":"4814",
    "sg:province":"QLD",
    "sg:tags":[
        "menswear"
    ],
    "wof:name":"Playtime Fashion Leaders",
    "wof:placetype":"venue"
},
  "geometry": {"coordinates":[146.76419100000001,-19.297947],"type":"Point"}
}