{
  "type": "Feature",
  "properties": {
    "addr:full":"1/ 187 Fairfield Rd Guildford NSW 2161",
    "addr:housenumber":"/ 187",
    "addr:postcode":"2161",
    "addr:street":"Fairfield Rd",
    "iso:country":"AU",
    "sg:address":"1/ 187 Fairfield Rd",
    "sg:city":"Guildford",
    "sg:classifiers":[
        {
            "category":"Home & Garden",
            "subcategory":"Building Materials",
            "type":"Retail Goods"
        }
    ],
    "sg:phone":"+61 2 9892 2788",
    "sg:postcode":"2161",
    "sg:province":"NSW",
    "sg:tags":[
        "merchant",
        "glass",
        "glazier"
    ],
    "wof:name":"Shorts Glass",
    "wof:placetype":"venue"
},
  "geometry": {"coordinates":[150.95956420900001,-33.8540649414],"type":"Point"}
}