{
  "type": "Feature",
  "properties": {
    "iso:country":"AU",
    "sg:address":"Taylor St",
    "sg:city":"Toowoomba",
    "sg:classifiers":[
        {
            "category":"Food & Beverages",
            "subcategory":"Liquor & Beverages",
            "type":"Retail Goods"
        }
    ],
    "sg:phone":"+61 7 4633 3099",
    "sg:postcode":"4350",
    "sg:province":"QLD",
    "sg:tags":[
        "store"
    ],
    "wof:name":"Wyalla Plaza Liquor Store",
    "wof:placetype":"venue"
},
  "geometry": {"coordinates":[151.902817,-27.550127],"type":"Point"}
}