{
  "type": "Feature",
  "properties": {
    "iso:country":"AU",
    "sg:address":"26 Tall Timbers Rd",
    "sg:city":"Wamberal",
    "sg:classifiers":[
        {
            "category":"Professional",
            "subcategory":"Art Services",
            "type":"Services"
        }
    ],
    "sg:phone":"+61 2 4384 2707",
    "sg:postcode":"2260",
    "sg:province":"NSW",
    "sg:tags":[
        "graphic",
        "designer"
    ],
    "wof:name":"Sally B Graphic Design",
    "wof:placetype":"venue"
},
  "geometry": {"coordinates":[151.447006,-33.418579],"type":"Point"}
}