{
  "type": "Feature",
  "properties": {
    "addr:full":"14a oaks Rd West Pennant Hills NSW 2125",
    "addr:housenumber":"14a",
    "addr:postcode":"2125",
    "addr:street":"Oaks Rd",
    "iso:country":"AU",
    "sg:address":"14a oaks Rd",
    "sg:city":"West Pennant Hills",
    "sg:classifiers":[
        {
            "category":"Home & Garden",
            "subcategory":"Carpets & Floor Coverings",
            "type":"Retail Goods"
        }
    ],
    "sg:phone":"+61 2 9890 2033",
    "sg:postcode":"2125",
    "sg:province":"NSW",
    "sg:tags":[
        "wood"
    ],
    "wof:name":"Kims Floor Sanding Service",
    "wof:placetype":"venue"
},
  "geometry": {"coordinates":[151.040817261,-33.756111145],"type":"Point"}
}