{
  "type": "Feature",
  "properties": {
    "addr:full":"2d Middlemiss St Mareeba QLD 4880",
    "addr:postcode":"4880",
    "addr:street":"Middlemiss St",
    "iso:country":"AU",
    "sg:address":"2d Middlemiss St",
    "sg:city":"Mareeba",
    "sg:classifiers":[
        {
            "category":"Communications",
            "type":"Services"
        }
    ],
    "sg:phone":"+61 7 4092 5911",
    "sg:postcode":"4880",
    "sg:province":"QLD",
    "sg:tags":[
        "equipment",
        "radio"
    ],
    "wof:name":"J.P.K. Electronics",
    "wof:placetype":"venue"
},
  "geometry": {"coordinates":[145.42266845699999,-16.9911651611],"type":"Point"}
}