{
  "type": "Feature",
  "properties": {
    "addr:full":"6-8 Main North Rd Willaston SA 5118",
    "addr:housenumber":"6-8",
    "addr:postcode":"5118",
    "addr:street":"Main North Rd",
    "iso:country":"AU",
    "sg:address":"6-8 Main North Rd",
    "sg:city":"Willaston",
    "sg:classifiers":[
        {
            "category":"Structure",
            "subcategory":"Bridge",
            "type":"Public Place"
        }
    ],
    "sg:phone":"+61 8 8522 4025",
    "sg:postcode":"5118",
    "sg:province":"SA",
    "sg:tags":[
        "chainsaw",
        "brushcutters"
    ],
    "wof:name":"Costin Hire & Sales",
    "wof:placetype":"venue"
},
  "geometry": {"coordinates":[138.74485799999999,-34.585922],"type":"Point"}
}