{
  "type": "Feature",
  "properties": {
    "iso:country":"AU",
    "sg:address":"10 Crowley Vale Rd",
    "sg:city":"Forest Hill",
    "sg:classifiers":[
        {
            "category":"Home & Garden",
            "subcategory":"Garden Supply",
            "type":"Retail Goods"
        }
    ],
    "sg:phone":"+61 7 5465 4728",
    "sg:postcode":"4342",
    "sg:province":"QLD",
    "sg:tags":[
        "equipment"
    ],
    "wof:name":"Full Moon Turf",
    "wof:placetype":"venue"
},
  "geometry": {"coordinates":[152.33456420900001,-27.6206016541],"type":"Point"}
}