{
  "type": "Feature",
  "properties": {
    "iso:country":"AU",
    "sg:address":"20 Challis St",
    "sg:city":"Dickson",
    "sg:classifiers":[
        {
            "category":"Building & Trades",
            "subcategory":"Construction",
            "type":"Services"
        }
    ],
    "sg:phone":"+61 2 6248 9995",
    "sg:postcode":"2602",
    "sg:province":"ACT",
    "sg:tags":[
        "management"
    ],
    "wof:name":"G. E. Shaw & Associates (ACT) Pty Ltd",
    "wof:placetype":"venue"
},
  "geometry": {"coordinates":[149.135528564,-35.2504768372],"type":"Point"}
}