{
  "type": "Feature",
  "properties": {
    "iso:country":"AU",
    "sg:address":"PO Box 155",
    "sg:city":"Kingsville",
    "sg:classifiers":[
        {
            "category":"Professional",
            "subcategory":"Detective & Security Services",
            "type":"Services"
        }
    ],
    "sg:phone":"+61 3 9315 1195",
    "sg:postcode":"3012",
    "sg:province":"VIC",
    "sg:tags":[
        "investigator"
    ],
    "wof:name":"SoftShoe Investigations",
    "wof:placetype":"venue"
},
  "geometry": {"coordinates":[144.87962341299999,-37.8057518005],"type":"Point"}
}