{
  "type": "Feature",
  "properties": {
    "iso:country":"AU",
    "sg:address":"25 Wishart Rd",
    "sg:city":"Berrimah",
    "sg:classifiers":[
        {
            "category":"Manufacturing",
            "subcategory":"Tools & Machinery",
            "type":"Manufacturing & Wholesale Goods"
        }
    ],
    "sg:phone":"+61 13 12 28",
    "sg:postcode":"0828",
    "sg:province":"NT",
    "sg:tags":[
        "earth",
        "excavating",
        "moving",
        "equipment"
    ],
    "wof:name":"Hastings Deering",
    "wof:placetype":"venue"
},
  "geometry": {"coordinates":[130.93437194800001,-12.4609336853],"type":"Point"}
}