{
  "type": "Feature",
  "properties": {
    "iso:country":"AU",
    "sg:address":"Anderson Rd",
    "sg:city":"Aloomba",
    "sg:classifiers":[
        {
            "category":"Farming",
            "subcategory":"Farm",
            "type":"Manufacturing & Wholesale Goods"
        }
    ],
    "sg:phone":"+61 7 4056 1331",
    "sg:postcode":"4871",
    "sg:province":"QLD",
    "sg:tags":[
        "farmer"
    ],
    "wof:name":"Wienert & Son",
    "wof:placetype":"venue"
},
  "geometry": {"coordinates":[145.81877136200001,-17.1079559326],"type":"Point"}
}