{
  "type": "Feature",
  "properties": {
    "addr:full":"95 Dover Rd Rose Bay NSW 2029",
    "addr:housenumber":"95",
    "addr:postcode":"2029",
    "addr:street":"Dover Rd",
    "iso:country":"AU",
    "sg:address":"95 Dover Rd",
    "sg:city":"Rose Bay",
    "sg:classifiers":[
        {
            "category":"Professional",
            "subcategory":"Art Services",
            "type":"Services"
        }
    ],
    "sg:phone":"+61 2 9371 8090",
    "sg:postcode":"2029",
    "sg:province":"NSW",
    "sg:tags":[
        "decorator",
        "painter"
    ],
    "wof:name":"Smithers W G",
    "wof:placetype":"venue"
},
  "geometry": {"coordinates":[151.27333068900001,-33.8733940125],"type":"Point"}
}