{
  "type": "Feature",
  "properties": {
    "addr:full":"6 - 159 William St Beverley SA 5009",
    "addr:housenumber":"6 159",
    "addr:postcode":"5009",
    "addr:street":"William St",
    "iso:country":"AU",
    "sg:address":"6 - 159 William St",
    "sg:city":"Beverley",
    "sg:classifiers":[
        {
            "category":"Home & Garden",
            "subcategory":"Kitchen Supply",
            "type":"Retail Goods"
        }
    ],
    "sg:phone":"+61 8 8345 1066",
    "sg:postcode":"5009",
    "sg:province":"SA",
    "sg:tags":[
        "traffic",
        "equipment",
        "safety",
        "road"
    ],
    "wof:name":"SA Safety Tape & Mesh",
    "wof:placetype":"venue"
},
  "geometry": {"coordinates":[138.54774475100001,-34.9024276733],"type":"Point"}
}