{
  "type": "Feature",
  "properties": {
    "addr:full":"881 Albany Hwy East Victoria Park WA 6101",
    "addr:housenumber":"881",
    "addr:postcode":"6101",
    "addr:street":"Albany Hwy",
    "iso:country":"AU",
    "sg:address":"881 Albany Hwy",
    "sg:city":"East Victoria Park",
    "sg:classifiers":[
        {
            "category":"Organizations",
            "subcategory":"Non-profit Organization",
            "type":"Services"
        }
    ],
    "sg:phone":"+61 8 9470 4188",
    "sg:postcode":"6101",
    "sg:province":"WA",
    "sg:tags":[
        "environmental",
        "organisation",
        "conservation"
    ],
    "wof:name":"Environment Centre Of W.A. (Inc)",
    "wof:placetype":"venue"
},
  "geometry": {"coordinates":[115.903869629,-31.9859905243],"type":"Point"}
}