{
  "type": "Feature",
  "properties": {
    "iso:country":"AU",
    "sg:address":"12 Davis Crt",
    "sg:city":"Rochedale South",
    "sg:classifiers":[
        {
            "category":"Health Services",
            "subcategory":"Health Practitioner",
            "type":"Services"
        }
    ],
    "sg:phone":"+61 7 3219 8494",
    "sg:postcode":"4123",
    "sg:province":"QLD",
    "sg:tags":[
        "hypnotherapy"
    ],
    "wof:name":"Anne Walter",
    "wof:placetype":"venue"
},
  "geometry": {"coordinates":[153.132736206,-27.5936698914],"type":"Point"}
}