{
  "type": "Feature",
  "properties": {
    "addr:full":"26 Mowbray Drv Wantirna South VIC 3152",
    "addr:housenumber":"26",
    "addr:postcode":"3152",
    "addr:street":"Mowbray Drv",
    "iso:country":"AU",
    "sg:address":"26 Mowbray Drv",
    "sg:city":"Wantirna South",
    "sg:classifiers":[
        {
            "category":"Communications",
            "type":"Services"
        }
    ],
    "sg:phone":"+61 402 010 888",
    "sg:postcode":"3152",
    "sg:province":"VIC",
    "sg:tags":[
        "translation"
    ],
    "wof:name":"Malay, Indonesian & Chinese Translation Services",
    "wof:placetype":"venue"
},
  "geometry": {"coordinates":[145.22300720199999,-37.8796691895],"type":"Point"}
}