{
  "type": "Feature",
  "properties": {
    "addr:full":"19 Willis St Teesdale VIC 3328",
    "addr:housenumber":"19",
    "addr:postcode":"3328",
    "addr:street":"Willis St",
    "iso:country":"AU",
    "sg:address":"19 Willis St",
    "sg:city":"Teesdale",
    "sg:classifiers":[
        {
            "category":"Cafe",
            "type":"Food & Drink"
        }
    ],
    "sg:phone":"+61 3 5281 5546",
    "sg:postcode":"3328",
    "sg:province":"VIC",
    "wof:name":"Highbury Tearooms",
    "wof:placetype":"venue"
},
  "geometry": {"coordinates":[144.045624,-38.025444],"type":"Point"}
}