{
  "type": "Feature",
  "properties": {
    "iso:country":"AU",
    "sg:address":"Newell Hwy",
    "sg:city":"Forbes",
    "sg:classifiers":[
        {
            "category":"Home & Garden",
            "subcategory":"Garden Supply",
            "type":"Retail Goods"
        }
    ],
    "sg:phone":"+61 2 6851 4584",
    "sg:postcode":"2871",
    "sg:province":"NSW",
    "sg:tags":[
        "nursery"
    ],
    "wof:name":"Willows Nursery",
    "wof:placetype":"venue"
},
  "geometry": {"coordinates":[148.011536,-33.380543],"type":"Point"}
}