{
  "type": "Feature",
  "properties": {
    "addr:full":"36 Kooranga Crs Cordeaux Heights NSW 2526",
    "addr:housenumber":"36",
    "addr:postcode":"2526",
    "addr:street":"Kooranga Crs",
    "iso:country":"AU",
    "sg:address":"36 Kooranga Crs",
    "sg:city":"Cordeaux Heights",
    "sg:classifiers":[
        {
            "category":"Professional",
            "subcategory":"Art Services",
            "type":"Services"
        }
    ],
    "sg:phone":"+61 411 764 177",
    "sg:postcode":"2526",
    "sg:province":"NSW",
    "sg:tags":[
        "decorator",
        "painter"
    ],
    "wof:name":"Nehme John",
    "wof:placetype":"venue"
},
  "geometry": {"coordinates":[150.83181762699999,-34.4444999695],"type":"Point"}
}