{
  "type": "Feature",
  "properties": {
    "iso:country":"AU",
    "sg:address":"Shop 73/ 2 Shore Rd",
    "sg:city":"Chiswick",
    "sg:classifiers":[
        {
            "category":"Real Estate",
            "subcategory":"Real Estate Agent",
            "type":"Services"
        }
    ],
    "sg:phone":"+61 2 9713 9300",
    "sg:postcode":"2046",
    "sg:province":"NSW",
    "wof:name":"Australian Property Support",
    "wof:placetype":"venue"
},
  "geometry": {"coordinates":[151.137024,-33.85038],"type":"Point"}
}