{
  "type": "Feature",
  "properties": {
    "addr:full":"63 Colebard St West Archerfield QLD 4108",
    "addr:housenumber":"63",
    "addr:postcode":"4108",
    "addr:street":"Colebard St West",
    "iso:country":"AU",
    "sg:address":"63 Colebard St",
    "sg:city":"West Archerfield",
    "sg:classifiers":[
        {
            "category":"Sports & Exercise",
            "subcategory":"Sports Center",
            "type":"Entertainment"
        }
    ],
    "sg:phone":"+61 7 3277 7745",
    "sg:postcode":"4108",
    "sg:province":"QLD",
    "sg:tags":[
        "ground"
    ],
    "wof:name":"Archerfield International Speedway",
    "wof:placetype":"venue"
},
  "geometry": {"coordinates":[153.00070190400001,-27.5775508881],"type":"Point"}
}