{
  "type": "Feature",
  "properties": {
    "addr:full":"Shop 52, Cairns Central Plaza, Spencer St Cairns QLD 4870",
    "addr:housenumber":"shop 52",
    "addr:postcode":"4870",
    "addr:street":"Spencer St",
    "iso:country":"AU",
    "sg:address":"Shop 52, Cairns Central Plaza, Spencer St",
    "sg:city":"Cairns",
    "sg:classifiers":[
        {
            "category":"Shopping",
            "subcategory":"Mobile Phones",
            "type":"Retail Goods"
        }
    ],
    "sg:phone":"+61 7 4051 3119",
    "sg:postcode":"4870",
    "sg:province":"QLD",
    "sg:tags":[
        "telephone",
        "accessory"
    ],
    "wof:name":"Vodafone",
    "wof:placetype":"venue"
},
  "geometry": {"coordinates":[145.75961303700001,-16.91056633],"type":"Point"}
}