{
  "type": "Feature",
  "properties": {
    "iso:country":"AU",
    "sg:address":"836 Glenferrie Rd",
    "sg:city":"Hawthorn",
    "sg:classifiers":[
        {
            "category":"Building & Trades",
            "subcategory":"Landscaping Services",
            "type":"Services"
        }
    ],
    "sg:phone":"+61 418 331 771",
    "sg:postcode":"3122",
    "sg:province":"VIC",
    "sg:tags":[
        "designer",
        "landscape",
        "contractor"
    ],
    "wof:name":"Black Rose Landscape & Gardens Maintenance",
    "wof:placetype":"venue"
},
  "geometry": {"coordinates":[145.03666687,-37.8164291382],"type":"Point"}
}