{
  "type": "Feature",
  "properties": {
    "addr:full":"Cobbitty Rd Cobbitty NSW 2570",
    "addr:postcode":"2570",
    "addr:street":"Cobbitty Rd",
    "iso:country":"AU",
    "sg:address":"Cobbitty Rd",
    "sg:city":"Cobbitty",
    "sg:classifiers":[
        {
            "category":"Farming",
            "subcategory":"Vineyard",
            "type":"Manufacturing & Wholesale Goods"
        }
    ],
    "sg:phone":"+61 2 4651 2281",
    "sg:postcode":"2570",
    "sg:province":"NSW",
    "sg:tags":[
        "winery"
    ],
    "wof:name":"Cobbitty Wines Pty Ltd",
    "wof:placetype":"venue"
},
  "geometry": {"coordinates":[150.687301636,-34.0153694153],"type":"Point"}
}