{
  "type": "Feature",
  "properties": {
    "addr:full":"42 Alma Ave Altona Meadows VIC 3028",
    "addr:housenumber":"42",
    "addr:postcode":"3028",
    "addr:street":"Alma Ave",
    "iso:country":"AU",
    "sg:address":"42 Alma Ave",
    "sg:city":"Altona Meadows",
    "sg:classifiers":[
        {
            "category":"Personal",
            "subcategory":"Beauty Salon",
            "type":"Services"
        }
    ],
    "sg:phone":"+61 3 9369 3809",
    "sg:postcode":"3028",
    "sg:province":"VIC",
    "sg:tags":[
        "hairdresser"
    ],
    "wof:name":"Hair With Beauty",
    "wof:placetype":"venue"
},
  "geometry": {"coordinates":[144.78338600000001,-37.869003],"type":"Point"}
}