{
  "type": "Feature",
  "properties": {
    "addr:full":"39 Holland St Goonellabah NSW 2480",
    "addr:housenumber":"39",
    "addr:postcode":"2480",
    "addr:street":"Holland St",
    "iso:country":"AU",
    "sg:address":"39 Holland St",
    "sg:city":"Goonellabah",
    "sg:classifiers":[
        {
            "category":"Fast Food",
            "type":"Food & Drink"
        }
    ],
    "sg:phone":"+61 2 6624 4199",
    "sg:postcode":"2480",
    "sg:province":"NSW",
    "sg:tags":[
        "away",
        "take"
    ],
    "wof:name":"Summerland Fruit Salad",
    "wof:placetype":"venue"
},
  "geometry": {"coordinates":[153.345947266,-28.8220462799],"type":"Point"}
}