{
  "type": "Feature",
  "properties": {
    "addr:full":"6- 8 Lucas Drv Lamb Island QLD 4184",
    "addr:housenumber":"8",
    "addr:postcode":"4184",
    "addr:street":"Lucas Drv",
    "iso:country":"AU",
    "sg:address":"6- 8 Lucas Drv",
    "sg:city":"Lamb Island",
    "sg:classifiers":[
        {
            "category":"Food & Beverages",
            "subcategory":"Groceries & Convenience Stores",
            "type":"Retail Goods"
        }
    ],
    "sg:phone":"+61 7 3409 5001",
    "sg:postcode":"4184",
    "sg:province":"QLD",
    "wof:name":"Lamb Island Kiosk",
    "wof:placetype":"venue"
},
  "geometry": {"coordinates":[153.373413086,-27.6302242279],"type":"Point"}
}