{
  "type": "Feature",
  "properties": {
    "iso:country":"AU",
    "sg:address":"36 Macrossan St",
    "sg:city":"South Townsville",
    "sg:classifiers":[
        {
            "category":"Transit Center",
            "subcategory":"Freight",
            "type":"Transportation"
        }
    ],
    "sg:phone":"+61 7 4721 4341",
    "sg:postcode":"4810",
    "sg:province":"QLD",
    "sg:tags":[
        "ship",
        "provedores"
    ],
    "wof:name":"USS - UBS International",
    "wof:placetype":"venue"
},
  "geometry": {"coordinates":[146.828049,-19.262842],"type":"Point"}
}