{
  "type": "Feature",
  "properties": {
    "addr:full":"16 Cronulla Ct Slacks Creek QLD 4127",
    "addr:housenumber":"16",
    "addr:postcode":"4127",
    "addr:street":"Cronulla Ct",
    "iso:country":"AU",
    "sg:address":"16 Cronulla Ct",
    "sg:city":"Slacks Creek",
    "sg:classifiers":[
        {
            "category":"Home & Garden",
            "subcategory":"Building Materials",
            "type":"Retail Goods"
        }
    ],
    "sg:phone":"+61 7 3808 8622",
    "sg:postcode":"4127",
    "sg:province":"QLD",
    "sg:tags":[
        "shutter",
        "roller",
        "grille"
    ],
    "wof:name":"I Deal Doors",
    "wof:placetype":"venue"
},
  "geometry": {"coordinates":[153.118896484,-27.6173744202],"type":"Point"}
}