{
  "type": "Feature",
  "properties": {
    "addr:full":"Centro Colonnades, Beach Rd Noarlunga Centre SA 5168",
    "addr:postcode":"5168",
    "addr:street":"Beach Rd",
    "iso:country":"AU",
    "sg:address":"Centro Colonnades, Beach Rd",
    "sg:city":"Noarlunga Centre",
    "sg:classifiers":[
        {
            "category":"Shopping",
            "subcategory":"Department Store",
            "type":"Retail Goods"
        }
    ],
    "sg:phone":"+61 8 8186 8555",
    "sg:postcode":"5168",
    "sg:province":"SA",
    "wof:name":"Myer Pty Ltd",
    "wof:placetype":"venue"
},
  "geometry": {"coordinates":[138.491790772,-35.1383476257],"type":"Point"}
}