{
  "type": "Feature",
  "properties": {
    "addr:full":"520 Seventeen Mile Rocks Rd Seventeen Mile Rocks QLD 4073",
    "addr:housenumber":"520",
    "addr:postcode":"4073",
    "addr:street":"Seventeen Mile Rocks Rd",
    "iso:country":"AU",
    "sg:address":"520 Seventeen Mile Rocks Rd",
    "sg:city":"Seventeen Mile Rocks",
    "sg:classifiers":[
        {
            "category":"Home & Garden",
            "subcategory":"Carpets & Floor Coverings",
            "type":"Retail Goods"
        }
    ],
    "sg:phone":"+61 7 3376 1311",
    "sg:postcode":"4073",
    "sg:province":"QLD",
    "sg:tags":[
        "wood"
    ],
    "wof:name":"J Notaras & Sons (Qld) Pty Ltd",
    "wof:placetype":"venue"
},
  "geometry": {"coordinates":[152.95513915999999,-27.54114151],"type":"Point"}
}