{
  "type": "Feature",
  "properties": {
    "addr:full":"30 Kamarooka Drv Wattle Glen VIC 3096",
    "addr:housenumber":"30",
    "addr:postcode":"3096",
    "addr:street":"Kamarooka Drv",
    "iso:country":"AU",
    "sg:address":"30 Kamarooka Drv",
    "sg:city":"Wattle Glen",
    "sg:classifiers":[
        {
            "category":"Building & Trades",
            "subcategory":"Construction",
            "type":"Services"
        }
    ],
    "sg:phone":"+61 407 603 538",
    "sg:postcode":"3096",
    "sg:province":"VIC",
    "sg:tags":[
        "fencing",
        "contractor"
    ],
    "wof:name":"Ageless Fences & Gates",
    "wof:placetype":"venue"
},
  "geometry": {"coordinates":[145.177642822,-37.6709671021],"type":"Point"}
}