{
  "type": "Feature",
  "properties": {
    "addr:full":"2 Cummings St Wodonga VIC 3690",
    "addr:housenumber":"2",
    "addr:postcode":"3690",
    "addr:street":"Cummings St",
    "iso:country":"AU",
    "sg:address":"2 Cummings St",
    "sg:city":"Wodonga",
    "sg:classifiers":[
        {
            "category":"Shopping",
            "subcategory":"Computers & Home Electronics",
            "type":"Retail Goods"
        }
    ],
    "sg:phone":"+61 2 6056 4273",
    "sg:postcode":"3690",
    "sg:province":"VIC",
    "sg:tags":[
        "equipment",
        "multimedia"
    ],
    "wof:name":"GOCREATIVE",
    "wof:placetype":"venue"
},
  "geometry": {"coordinates":[146.88639831500001,-36.1265296936],"type":"Point"}
}