{
  "type": "Feature",
  "properties": {
    "iso:country":"AU",
    "sg:address":"Shop 114",
    "sg:city":"Westfield Shopping Centre Airport West",
    "sg:classifiers":[
        {
            "category":"Personal",
            "subcategory":"Beauty Salon",
            "type":"Services"
        }
    ],
    "sg:phone":"+61 3 9335 6886",
    "sg:postcode":"3042",
    "sg:province":"VIC",
    "sg:tags":[
        "hairdresser"
    ],
    "wof:name":"Just Cuts",
    "wof:placetype":"venue"
},
  "geometry": {"coordinates":[144.88563537600001,-37.7126159668],"type":"Point"}
}