{
  "type": "Feature",
  "properties": {
    "addr:full":"Shp3/ 55 Emmett St Callala Bay NSW 2540",
    "addr:housenumber":"55",
    "addr:postcode":"2540",
    "addr:street":"Emmett St",
    "iso:country":"AU",
    "sg:address":"Shp3/ 55 Emmett St",
    "sg:city":"Callala Bay",
    "sg:classifiers":[
        {
            "category":"Food & Beverages",
            "subcategory":"Bakery",
            "type":"Retail Goods"
        }
    ],
    "sg:phone":"+61 2 4446 6858",
    "sg:postcode":"2540",
    "sg:province":"NSW",
    "sg:tags":[
        "baker"
    ],
    "wof:name":"Callala Bakery",
    "wof:placetype":"venue"
},
  "geometry": {"coordinates":[150.717895508,-34.9952545166],"type":"Point"}
}