{
  "type": "Feature",
  "properties": {
    "addr:full":"Glencoe Rd Glencoe QLD 4352",
    "addr:postcode":"4352",
    "addr:street":"Glencoe Rd",
    "iso:country":"AU",
    "sg:address":"Glencoe Rd",
    "sg:city":"Glencoe",
    "sg:classifiers":[
        {
            "category":"Building & Trades",
            "subcategory":"Construction",
            "type":"Services"
        }
    ],
    "sg:phone":"+61 7 4630 0209",
    "sg:postcode":"4352",
    "sg:province":"QLD",
    "sg:tags":[
        "equipment",
        "system",
        "automation"
    ],
    "wof:name":"Darryl O&#039;Brien Electrical",
    "wof:placetype":"venue"
},
  "geometry": {"coordinates":[152.03247099999999,-27.541739],"type":"Point"}
}