{
  "type": "Feature",
  "properties": {
    "addr:full":"PO Box 602 Charlestown NSW 2290",
    "addr:postcode":"2290",
    "iso:country":"AU",
    "sg:address":"PO Box 602",
    "sg:city":"Charlestown",
    "sg:classifiers":[
        {
            "category":"Professional",
            "subcategory":"Business Services",
            "type":"Services"
        }
    ],
    "sg:phone":"+61 2 4942 2848",
    "sg:postcode":"2290",
    "sg:province":"NSW",
    "sg:tags":[
        "drafting"
    ],
    "wof:name":"CoAssociates# pty# ltd#",
    "wof:placetype":"venue"
},
  "geometry": {"coordinates":[151.68812560999999,-32.9578514099],"type":"Point"}
}