{
  "type": "Feature",
  "properties": {
    "addr:full":"29 Ferrier Rd Narangba QLD 4504",
    "addr:housenumber":"29",
    "addr:postcode":"4504",
    "addr:street":"Ferrier Rd",
    "iso:country":"AU",
    "sg:address":"29 Ferrier Rd",
    "sg:city":"Narangba",
    "sg:classifiers":[
        {
            "category":"Building & Trades",
            "subcategory":"Plumbing",
            "type":"Services"
        }
    ],
    "sg:phone":"+61 7 3888 0457",
    "sg:postcode":"4504",
    "sg:province":"QLD",
    "sg:tags":[
        "plumber",
        "gasfitters"
    ],
    "wof:name":"Rosenlund Plumbing Pty Ltd",
    "wof:placetype":"venue"
},
  "geometry": {"coordinates":[152.97756957999999,-27.2048492432],"type":"Point"}
}