{
  "type": "Feature",
  "properties": {
    "iso:country":"AU",
    "sg:address":"Level 1, 97 Rose St",
    "sg:city":"Chippendale",
    "sg:classifiers":[
        {
            "category":"Professional",
            "subcategory":"Computer Services",
            "type":"Services"
        }
    ],
    "sg:phone":"+61 1800 700 300",
    "sg:postcode":"2008",
    "sg:province":"NSW",
    "sg:tags":[
        "package",
        "software"
    ],
    "wof:name":"Quark Australia",
    "wof:placetype":"venue"
},
  "geometry": {"coordinates":[151.19439697300001,-33.8875083923],"type":"Point"}
}