{
  "type": "Feature",
  "properties": {
    "addr:full":"11 Arkell Pl Charnwood ACT 2615",
    "addr:housenumber":"11",
    "addr:postcode":"2615",
    "addr:street":"Arkell Pl",
    "iso:country":"AU",
    "sg:address":"11 Arkell Pl",
    "sg:city":"Charnwood",
    "sg:classifiers":[
        {
            "category":"Building & Trades",
            "subcategory":"Construction",
            "type":"Services"
        }
    ],
    "sg:phone":"+61 419 632 438",
    "sg:postcode":"2615",
    "sg:province":"ACT",
    "sg:tags":[
        "renovation",
        "alterations",
        "extension",
        "contractor"
    ],
    "wof:name":"All Type Buildings Pty Ltd",
    "wof:placetype":"venue"
},
  "geometry": {"coordinates":[149.030593872,-35.1970787048],"type":"Point"}
}