{
  "type": "Feature",
  "properties": {
    "iso:country":"AU",
    "sg:address":"23 Oaktree Drv",
    "sg:city":"Hampton Park",
    "sg:classifiers":[
        {
            "category":"Food & Beverages",
            "subcategory":"Groceries & Convenience Stores",
            "type":"Retail Goods"
        }
    ],
    "sg:phone":"+61 3 9799 0982",
    "sg:postcode":"3976",
    "sg:province":"VIC",
    "wof:name":"Archer L & T",
    "wof:placetype":"venue"
},
  "geometry": {"coordinates":[145.26473999000001,-38.0253944397],"type":"Point"}
}