{
  "type": "Feature",
  "properties": {
    "addr:full":"PO Box 491 Alstonville NSW 2477",
    "addr:postcode":"2477",
    "iso:country":"AU",
    "sg:address":"PO Box 491",
    "sg:city":"Alstonville",
    "sg:classifiers":[
        {
            "category":"Home & Garden",
            "subcategory":"Household Appliances",
            "type":"Retail Goods"
        }
    ],
    "sg:phone":"+61 403 554 484",
    "sg:postcode":"2477",
    "sg:province":"NSW",
    "sg:tags":[
        "chemical",
        "equipment",
        "steam",
        "cleaning",
        "pressure"
    ],
    "wof:name":"Commercial Cleaning and Maintenance",
    "wof:placetype":"venue"
},
  "geometry": {"coordinates":[153.44003295900001,-28.8416900635],"type":"Point"}
}