{
  "type": "Feature",
  "properties": {
    "addr:full":"PO Box 684 Tweed Heads NSW 2485",
    "addr:postcode":"2485",
    "iso:country":"AU",
    "sg:address":"PO Box 684",
    "sg:city":"Tweed Heads",
    "sg:classifiers":[
        {
            "category":"Professional",
            "subcategory":"Management & Consulting",
            "type":"Services"
        }
    ],
    "sg:phone":"+61 7 5599 7119",
    "sg:postcode":"2485",
    "sg:province":"NSW",
    "sg:tags":[
        "consultant"
    ],
    "wof:name":"Magispring Pty Limited",
    "wof:placetype":"venue"
},
  "geometry": {"coordinates":[153.51756286599999,-28.1832504272],"type":"Point"}
}