{
  "type": "Feature",
  "properties": {
    "iso:country":"AU",
    "sg:address":"54 Jose St",
    "sg:city":"Melrose Park",
    "sg:classifiers":[
        {
            "category":"Home & Garden",
            "subcategory":"Furniture",
            "type":"Retail Goods"
        }
    ],
    "sg:phone":"+61 8 8276 9288",
    "sg:postcode":"5039",
    "sg:province":"SA",
    "sg:tags":[
        "business"
    ],
    "wof:name":"Brown T H Furniture",
    "wof:placetype":"venue"
},
  "geometry": {"coordinates":[138.58119201700001,-34.9898872375],"type":"Point"}
}