{
  "type": "Feature",
  "properties": {
    "addr:full":"9 Eleventh St Warragamba NSW 2752",
    "addr:housenumber":"9",
    "addr:postcode":"2752",
    "addr:street":"Eleventh St",
    "iso:country":"AU",
    "sg:address":"9 Eleventh St",
    "sg:city":"Warragamba",
    "sg:classifiers":[
        {
            "category":"Home & Garden",
            "subcategory":"Building Materials",
            "type":"Retail Goods"
        }
    ],
    "sg:phone":"+61 419 204 838",
    "sg:postcode":"2752",
    "sg:province":"NSW",
    "sg:tags":[
        "fitting",
        "door"
    ],
    "wof:name":"Complete Doors & Carpentery Pty Ltd",
    "wof:placetype":"venue"
},
  "geometry": {"coordinates":[150.605545044,-33.8839607239],"type":"Point"}
}