{
  "type": "Feature",
  "properties": {
    "iso:country":"AU",
    "sg:address":"20 Dale St",
    "sg:city":"Brookvale",
    "sg:classifiers":[
        {
            "category":"Home & Garden",
            "subcategory":"Carpets & Floor Coverings",
            "type":"Retail Goods"
        }
    ],
    "sg:phone":"+61 2 9939 1655",
    "sg:postcode":"2100",
    "sg:province":"NSW",
    "sg:tags":[
        "wood"
    ],
    "wof:name":"DIY Flooring",
    "wof:placetype":"venue"
},
  "geometry": {"coordinates":[151.268234253,-33.7652168274],"type":"Point"}
}