{
  "type": "Feature",
  "properties": {
    "iso:country":"AU",
    "sg:address":"55 Bonogin Rd",
    "sg:city":"Mudgeeraba",
    "sg:classifiers":[
        {
            "category":"Farming",
            "subcategory":"Nursery",
            "type":"Manufacturing & Wholesale Goods"
        }
    ],
    "sg:phone":"+61 7 5530 2621",
    "sg:postcode":"4213",
    "sg:province":"QLD",
    "wof:name":"Mudgeeraba Wholesale Nursery Pty Ltd",
    "wof:placetype":"venue"
},
  "geometry": {"coordinates":[153.36799621599999,-28.1025371552],"type":"Point"}
}