{
  "type": "Feature",
  "properties": {
    "addr:full":"23 Dudley Ave Roseville NSW 2069",
    "addr:housenumber":"23",
    "addr:postcode":"2069",
    "addr:street":"Dudley Ave",
    "iso:country":"AU",
    "sg:address":"23 Dudley Ave",
    "sg:city":"Roseville",
    "sg:classifiers":[
        {
            "category":"Real Estate",
            "subcategory":"Real Estate Services",
            "type":"Services"
        }
    ],
    "sg:phone":"+61 2 9416 5147",
    "sg:postcode":"2069",
    "sg:province":"NSW",
    "sg:tags":[
        "valuer"
    ],
    "wof:name":"Blackall's Property Services Pty Ltd",
    "wof:placetype":"venue"
},
  "geometry": {"coordinates":[151.182769775,-33.778842926],"type":"Point"}
}