{
  "type": "Feature",
  "properties": {
    "addr:full":"5 Nicholson St Coburg East VIC 3058",
    "addr:housenumber":"5",
    "addr:postcode":"3058",
    "addr:street":"Nicholson St",
    "iso:country":"AU",
    "sg:address":"5 Nicholson St",
    "sg:city":"Coburg East",
    "sg:classifiers":[
        {
            "category":"Health Services",
            "subcategory":"Doctor",
            "type":"Services"
        }
    ],
    "sg:phone":"+61 3 9383 3544",
    "sg:postcode":"3058",
    "sg:province":"VIC",
    "sg:tags":[
        "medical",
        "practitioner"
    ],
    "wof:name":"East Coburg Medical Centre",
    "wof:placetype":"venue"
},
  "geometry": {"coordinates":[144.97482299800001,-37.7562942505],"type":"Point"}
}