{
  "type": "Feature",
  "properties": {
    "addr:full":"1389 Centre Rd Clayton VIC 3168",
    "addr:housenumber":"1389",
    "addr:postcode":"3168",
    "addr:street":"Centre Rd",
    "iso:country":"AU",
    "sg:address":"1389 Centre Rd",
    "sg:city":"Clayton",
    "sg:classifiers":[
        {
            "category":"Food & Beverages",
            "subcategory":"Supermarket",
            "type":"Retail Goods"
        }
    ],
    "sg:phone":"+61 3 9544 9530",
    "sg:postcode":"3168",
    "sg:province":"VIC",
    "sg:tags":[
        "grocery",
        "store"
    ],
    "wof:name":"Bi-Lo Pty Ltd",
    "wof:placetype":"venue"
},
  "geometry": {"coordinates":[145.11869812,-37.9283447266],"type":"Point"}
}