{
  "type": "Feature",
  "properties": {
    "iso:country":"AU",
    "sg:address":"Grnd Flr, 44 Bay St",
    "sg:city":"Ultimo",
    "sg:classifiers":[
        {
            "category":"Banks & Credit Unions",
            "subcategory":"Financial Services",
            "type":"Services"
        }
    ],
    "sg:phone":"+61 13 72 67",
    "sg:postcode":"2007",
    "sg:province":"NSW",
    "sg:tags":[
        "loan",
        "finance",
        "mortgage"
    ],
    "wof:name":"RAMS Home Loans",
    "wof:placetype":"venue"
},
  "geometry": {"coordinates":[151.19497680699999,-33.8819351196],"type":"Point"}
}