{
  "type": "Feature",
  "properties": {
    "addr:full":"382 Main Rd Glenorchy TAS 7010",
    "addr:housenumber":"382",
    "addr:postcode":"7010",
    "addr:street":"Main Rd",
    "iso:country":"AU",
    "sg:address":"382 Main Rd",
    "sg:city":"Glenorchy",
    "sg:classifiers":[
        {
            "category":"Wholesale",
            "subcategory":"Medical Equipment & Supplies",
            "type":"Manufacturing & Wholesale Goods"
        }
    ],
    "sg:phone":"+61 3 6272 2400",
    "sg:postcode":"7010",
    "sg:province":"TAS",
    "sg:tags":[
        "aids",
        "hearing"
    ],
    "wof:name":"John King Hearing Aid Clinics",
    "wof:placetype":"venue"
},
  "geometry": {"coordinates":[147.274261475,-42.8329658508],"type":"Point"}
}