{
  "type": "Feature",
  "properties": {
    "addr:full":"2 Lindemans Rd Lowood QLD 4311",
    "addr:housenumber":"2",
    "addr:postcode":"4311",
    "addr:street":"Lindemans Rd",
    "iso:country":"AU",
    "sg:address":"2 Lindemans Rd",
    "sg:city":"Lowood",
    "sg:classifiers":[
        {
            "category":"Professional",
            "subcategory":"Business Services",
            "type":"Services"
        }
    ],
    "sg:phone":"+61 500 889 997",
    "sg:postcode":"4311",
    "sg:province":"QLD",
    "sg:tags":[
        "livestock",
        "transport"
    ],
    "wof:name":"Johny Oleary Horse Transport",
    "wof:placetype":"venue"
},
  "geometry": {"coordinates":[152.58934020999999,-27.4570446014],"type":"Point"}
}