{
  "type": "Feature",
  "properties": {
    "iso:country":"AU",
    "sg:address":"19 Louise Ave",
    "sg:city":"Ingleburn",
    "sg:classifiers":[
        {
            "category":"Building & Trades",
            "subcategory":"Construction",
            "type":"Services"
        }
    ],
    "sg:phone":"+61 2 9618 1811",
    "sg:postcode":"2565",
    "sg:province":"NSW",
    "sg:tags":[
        "contractor"
    ],
    "wof:name":"Amanda Constructions Pty Ltd",
    "wof:placetype":"venue"
},
  "geometry": {"coordinates":[150.865036011,-33.9942398071],"type":"Point"}
}