{
  "type": "Feature",
  "properties": {
    "addr:full":"12 Christensen Rd Stapylton QLD 4207",
    "addr:housenumber":"12",
    "addr:postcode":"4207",
    "addr:street":"Christensen Rd",
    "iso:country":"AU",
    "sg:address":"12 Christensen Rd",
    "sg:city":"Stapylton",
    "sg:classifiers":[
        {
            "category":"Utilities",
            "type":"Services"
        }
    ],
    "sg:phone":"+61 7 3287 5770",
    "sg:postcode":"4207",
    "sg:province":"QLD",
    "sg:tags":[
        "refrigeration",
        "industrial",
        "commercial",
        "retail"
    ],
    "wof:name":"Market Refrigeration & Electrical Services (QLD)",
    "wof:placetype":"venue"
},
  "geometry": {"coordinates":[153.23080444300001,-27.7358760834],"type":"Point"}
}