{
  "type": "Feature",
  "properties": {
    "addr:full":"33 Weldwood Rd Ocean Reef WA 6027",
    "addr:housenumber":"33",
    "addr:postcode":"6027",
    "addr:street":"Weldwood Rd",
    "iso:country":"AU",
    "sg:address":"33 Weldwood Rd",
    "sg:city":"Ocean Reef",
    "sg:classifiers":[
        {
            "category":"Building & Trades",
            "subcategory":"Equipment Rental",
            "type":"Services"
        }
    ],
    "sg:phone":"+61 8 9403 0551",
    "sg:postcode":"6027",
    "sg:province":"WA",
    "sg:tags":[
        "supply",
        "catering"
    ],
    "wof:name":"Oppenheimer Pty Ltd",
    "wof:placetype":"venue"
},
  "geometry": {"coordinates":[115.745750427,-31.7700099945],"type":"Point"}
}