{
  "type": "Feature",
  "properties": {
    "addr:full":"11 Hovea Ave Sorrento WA 6020",
    "addr:housenumber":"11",
    "addr:postcode":"6020",
    "addr:street":"Hovea Ave",
    "iso:country":"AU",
    "sg:address":"11 Hovea Ave",
    "sg:city":"Sorrento",
    "sg:classifiers":[
        {
            "category":"Utilities",
            "subcategory":"Electric",
            "type":"Services"
        }
    ],
    "sg:phone":"+61 400 406 305",
    "sg:postcode":"6020",
    "sg:province":"WA",
    "sg:tags":[
        "electrical",
        "contractor"
    ],
    "wof:name":"Precision Electrical & Instrumentation Pty Ltd",
    "wof:placetype":"venue"
},
  "geometry": {"coordinates":[115.761642456,-31.8333816528],"type":"Point"}
}