{
  "type": "Feature",
  "properties": {
    "iso:country":"AU",
    "sg:address":"44 Mort St",
    "sg:city":"Braddon",
    "sg:classifiers":[
        {
            "category":"Autos & Motor Vehicles",
            "subcategory":"Automobile Sales",
            "type":"Retail Goods"
        }
    ],
    "sg:phone":"+61 2 6248 7888",
    "sg:postcode":"2612",
    "sg:province":"ACT",
    "sg:tags":[
        "car",
        "new"
    ],
    "wof:name":"Holden Rolfe",
    "wof:placetype":"venue"
},
  "geometry": {"coordinates":[149.13180542000001,-35.2720909119],"type":"Point"}
}