{
  "type": "Feature",
  "properties": {
    "addr:full":"80 Whittakers La Riddells Creek VIC 3431",
    "addr:housenumber":"80",
    "addr:postcode":"3431",
    "addr:street":"Whittakers La",
    "iso:country":"AU",
    "sg:address":"80 Whittakers La",
    "sg:city":"Riddells Creek",
    "sg:classifiers":[
        {
            "category":"Professional",
            "subcategory":"Art Services",
            "type":"Services"
        }
    ],
    "sg:phone":"+61 3 5428 7032",
    "sg:postcode":"3431",
    "sg:province":"VIC",
    "sg:tags":[
        "graphic",
        "designer"
    ],
    "wof:name":"Radio Star Pty Ltd",
    "wof:placetype":"venue"
},
  "geometry": {"coordinates":[144.6746521,-37.4555015564],"type":"Point"}
}