{
  "type": "Feature",
  "properties": {
    "addr:full":"72- 76 Ryrie St Geelong VIC 3220",
    "addr:housenumber":"76",
    "addr:postcode":"3220",
    "addr:street":"Ryrie St",
    "iso:country":"AU",
    "sg:address":"72- 76 Ryrie St",
    "sg:city":"Geelong",
    "sg:classifiers":[
        {
            "category":"Professional",
            "subcategory":"Accounting & Tax Preparation",
            "type":"Services"
        }
    ],
    "sg:phone":"+61 3 5224 1133",
    "sg:postcode":"3220",
    "sg:province":"VIC",
    "sg:tags":[
        "accountant",
        "auditor"
    ],
    "wof:name":"Cleary John",
    "wof:placetype":"venue"
},
  "geometry": {"coordinates":[144.35673499999999,-38.148605],"type":"Point"}
}