{
  "type": "Feature",
  "properties": {
    "addr:full":"Factory 35, Cavehill Industrial Park, Cavehill Rd Lilydale VIC 3140",
    "addr:housenumber":"35",
    "addr:postcode":"3140",
    "addr:street":"Cavehill Industrial;Cavehill Rd",
    "iso:country":"AU",
    "sg:address":"Factory 35, Cavehill Industrial Park, Cavehill Rd",
    "sg:city":"Lilydale",
    "sg:classifiers":[
        {
            "category":"Wholesale",
            "subcategory":"Auto Parts",
            "type":"Manufacturing & Wholesale Goods"
        }
    ],
    "sg:phone":"+61 3 9739 7233",
    "sg:postcode":"3140",
    "sg:province":"VIC",
    "sg:tags":[
        "recyclers"
    ],
    "wof:name":"Magnas &#039;R&#039; Us",
    "wof:placetype":"venue"
},
  "geometry": {"coordinates":[145.35223388700001,-37.7479858398],"type":"Point"}
}