{
  "type": "Feature",
  "properties": {
    "iso:country":"AU",
    "sg:address":"287 Sturt St",
    "sg:city":"Townsville",
    "sg:classifiers":[
        {
            "category":"Professional",
            "subcategory":"Art Services",
            "type":"Services"
        }
    ],
    "sg:phone":"+61 7 4771 3280",
    "sg:postcode":"4810",
    "sg:province":"QLD",
    "sg:tags":[
        "picture",
        "frame",
        "framing"
    ],
    "wof:name":"Townsville Art & Framing",
    "wof:placetype":"venue"
},
  "geometry": {"coordinates":[146.813278,-19.261852],"type":"Point"}
}