{
  "type": "Feature",
  "properties": {
    "iso:country":"AU",
    "sg:address":"46 Bell St",
    "sg:city":"Torquay",
    "sg:classifiers":[
        {
            "category":"Fast Food",
            "type":"Food & Drink"
        }
    ],
    "sg:phone":"+61 3 5261 6303",
    "sg:postcode":"3228",
    "sg:province":"VIC",
    "sg:tags":[
        "away",
        "take"
    ],
    "wof:name":"Torquay Pizza Fish & Chips",
    "wof:placetype":"venue"
},
  "geometry": {"coordinates":[144.318329,-38.337574],"type":"Point"}
}