{
  "type": "Feature",
  "properties": {
    "addr:full":"105 Partridge St Glenelg South SA 5045",
    "addr:housenumber":"105",
    "addr:postcode":"5045",
    "addr:street":"Partridge St",
    "iso:country":"AU",
    "sg:address":"105 Partridge St",
    "sg:city":"Glenelg South",
    "sg:classifiers":[
        {
            "category":"Cafe",
            "type":"Food & Drink"
        }
    ],
    "sg:phone":"+61 8 8295 8808",
    "sg:postcode":"5045",
    "sg:province":"SA",
    "wof:name":"Sabai Cafe",
    "wof:placetype":"venue"
},
  "geometry": {"coordinates":[138.51838699999999,-34.990162],"type":"Point"}
}