{
  "type": "Feature",
  "properties": {
    "addr:full":"340 Lake Rd Glendale NSW 2285",
    "addr:housenumber":"340",
    "addr:postcode":"2285",
    "addr:street":"Lake Rd",
    "iso:country":"AU",
    "sg:address":"340 Lake Rd",
    "sg:city":"Glendale",
    "sg:classifiers":[
        {
            "category":"Autos & Motor Vehicles",
            "subcategory":"Auto Supplies",
            "type":"Retail Goods"
        }
    ],
    "sg:phone":"+61 2 4956 5652",
    "sg:postcode":"2285",
    "sg:province":"NSW",
    "sg:tags":[
        "battery",
        "automotive"
    ],
    "wof:name":"Glendale Automotive Services",
    "wof:placetype":"venue"
},
  "geometry": {"coordinates":[151.643676758,-32.9282417297],"type":"Point"}
}