{
  "type": "Feature",
  "properties": {
    "iso:country":"AU",
    "sg:address":"PO Box 781",
    "sg:city":"Hamilton",
    "sg:classifiers":[
        {
            "category":"Arts & Performance",
            "subcategory":"Art Gallery",
            "type":"Entertainment"
        }
    ],
    "sg:phone":"+61 2 4969 5162",
    "sg:postcode":"2303",
    "sg:province":"NSW",
    "sg:tags":[
        "aboriginal",
        "craft"
    ],
    "wof:name":"Didgeridoo Awakening",
    "wof:placetype":"venue"
},
  "geometry": {"coordinates":[151.746994,-32.923489],"type":"Point"}
}