{
  "type": "Feature",
  "properties": {
    "addr:full":"18 Lawyer St Maleny QLD 4552",
    "addr:housenumber":"18",
    "addr:postcode":"4552",
    "addr:street":"Lawyer St",
    "iso:country":"AU",
    "sg:address":"18 Lawyer St",
    "sg:city":"Maleny",
    "sg:classifiers":[
        {
            "category":"Utilities",
            "subcategory":"Electric",
            "type":"Services"
        }
    ],
    "sg:phone":"+61 7 5429 6626",
    "sg:postcode":"4552",
    "sg:province":"QLD",
    "sg:tags":[
        "electrical",
        "contractor"
    ],
    "wof:name":"Andersen Trevor Electrical",
    "wof:placetype":"venue"
},
  "geometry": {"coordinates":[152.85386657699999,-26.7592582703],"type":"Point"}
}