{
  "type": "Feature",
  "properties": {
    "addr:full":"43 Boolwey St Bowral NSW 2576",
    "addr:housenumber":"43",
    "addr:postcode":"2576",
    "addr:street":"Boolwey St",
    "iso:country":"AU",
    "sg:address":"43 Boolwey St",
    "sg:city":"Bowral",
    "sg:classifiers":[
        {
            "category":"Building & Trades",
            "subcategory":"Construction",
            "type":"Services"
        }
    ],
    "sg:phone":"+61 2 4861 2185",
    "sg:postcode":"2576",
    "sg:province":"NSW",
    "sg:tags":[
        "contractor"
    ],
    "wof:name":"Springett John",
    "wof:placetype":"venue"
},
  "geometry": {"coordinates":[150.42424011200001,-34.481426239],"type":"Point"}
}