{
  "type": "Feature",
  "properties": {
    "addr:full":"Tenancy C, 366 New England Hwy Rutherford NSW 2320",
    "addr:housenumber":"366",
    "addr:postcode":"2320",
    "addr:street":"C;New England Hwy",
    "iso:country":"AU",
    "sg:address":"Tenancy C, 366 New England Hwy",
    "sg:city":"Rutherford",
    "sg:classifiers":[
        {
            "category":"Building & Trades",
            "subcategory":"Equipment Rental",
            "type":"Services"
        }
    ],
    "sg:phone":"+61 2 4932 1444",
    "sg:postcode":"2320",
    "sg:province":"NSW",
    "sg:tags":[
        "party",
        "hire"
    ],
    "wof:name":"Spotlight Party Supplies Pty Ltd (SPARTYS)",
    "wof:placetype":"venue"
},
  "geometry": {"coordinates":[151.51901245100001,-32.7117767334],"type":"Point"}
}