{
  "type": "Feature",
  "properties": {
    "addr:full":"45 Planthurst Rd Carlton NSW 2218",
    "addr:housenumber":"45",
    "addr:postcode":"2218",
    "addr:street":"Planthurst Rd",
    "iso:country":"AU",
    "sg:address":"45 Planthurst Rd",
    "sg:city":"Carlton",
    "sg:classifiers":[
        {
            "category":"Retail",
            "subcategory":"Car Wash",
            "type":"Services"
        }
    ],
    "sg:phone":"+61 2 9546 7711",
    "sg:postcode":"2218",
    "sg:province":"NSW",
    "sg:tags":[
        "truck",
        "cleaning"
    ],
    "wof:name":"Carlton Car Engine Steam Cleaning",
    "wof:placetype":"venue"
},
  "geometry": {"coordinates":[151.115555,-33.977474],"type":"Point"}
}