{
  "type": "Feature",
  "properties": {
    "iso:country":"AU",
    "sg:address":"173 Concord Rd",
    "sg:city":"North Strathfield",
    "sg:classifiers":[
        {
            "category":"Personal",
            "subcategory":"Beauty Salon",
            "type":"Services"
        }
    ],
    "sg:phone":"+61 2 9743 1662",
    "sg:postcode":"2137",
    "sg:province":"NSW",
    "sg:tags":[
        "hairdresser"
    ],
    "wof:name":"Mojo Hair & Beauty",
    "wof:placetype":"venue"
},
  "geometry": {"coordinates":[151.092254639,-33.8578643799],"type":"Point"}
}