{
  "type": "Feature",
  "properties": {
    "addr:full":"49 Herbert St Bowen QLD 4805",
    "addr:housenumber":"49",
    "addr:postcode":"4805",
    "addr:street":"Herbert St",
    "iso:country":"AU",
    "sg:address":"49 Herbert St",
    "sg:city":"Bowen",
    "sg:classifiers":[
        {
            "category":"Shopping",
            "subcategory":"Clothing, Apparel, & Fashions",
            "type":"Retail Goods"
        }
    ],
    "sg:phone":"+61 7 4786 1231",
    "sg:postcode":"4805",
    "sg:province":"QLD",
    "sg:tags":[
        "menswear"
    ],
    "wof:name":"Meehan P & O - The Shop for Men",
    "wof:placetype":"venue"
},
  "geometry": {"coordinates":[148.24087524399999,-20.003282547],"type":"Point"}
}