{
  "type": "Feature",
  "properties": {
    "addr:full":"3 Diana Drv Blackburn North VIC 3130",
    "addr:housenumber":"3",
    "addr:postcode":"3130",
    "addr:street":"Diana Drv",
    "iso:country":"AU",
    "sg:address":"3 Diana Drv",
    "sg:city":"Blackburn North",
    "sg:classifiers":[
        {
            "category":"Autos & Motor Vehicles",
            "subcategory":"Auto Supplies",
            "type":"Retail Goods"
        }
    ],
    "sg:phone":"+61 3 9878 8467",
    "sg:postcode":"3130",
    "sg:province":"VIC",
    "sg:tags":[
        "accessory"
    ],
    "wof:name":"Dash Design International Pty Ltd",
    "wof:placetype":"venue"
},
  "geometry": {"coordinates":[145.16383361800001,-37.8073158264],"type":"Point"}
}