{
  "type": "Feature",
  "properties": {
    "iso:country":"AU",
    "sg:address":"373 Scarborough Rd",
    "sg:city":"Scarborough",
    "sg:classifiers":[
        {
            "category":"Utilities",
            "subcategory":"Electric",
            "type":"Services"
        }
    ],
    "sg:phone":"+61 418 198 513",
    "sg:postcode":"4020",
    "sg:province":"QLD",
    "sg:tags":[
        "electrical",
        "contractor"
    ],
    "wof:name":"Martin Terry Electrical",
    "wof:placetype":"venue"
},
  "geometry": {"coordinates":[153.110855,-27.199303],"type":"Point"}
}