{
  "type": "Feature",
  "properties": {
    "addr:full":"35 Fernhill Drv Dingley VIC 3172",
    "addr:housenumber":"35",
    "addr:postcode":"3172",
    "addr:street":"Fernhill Drv",
    "iso:country":"AU",
    "sg:address":"35 Fernhill Drv",
    "sg:city":"Dingley",
    "sg:classifiers":[
        {
            "category":"Professional",
            "subcategory":"Detective & Security Services",
            "type":"Services"
        }
    ],
    "sg:phone":"+61 418 583 581",
    "sg:postcode":"3172",
    "sg:province":"VIC",
    "sg:tags":[
        "domestic",
        "alarm",
        "commercial",
        "burglar"
    ],
    "wof:name":"Access Security Pty Ltd",
    "wof:placetype":"venue"
},
  "geometry": {"coordinates":[145.12416076700001,-37.9723243713],"type":"Point"}
}