{
  "type": "Feature",
  "properties": {
    "addr:full":"18 Haig Rd Milton QLD 4064",
    "addr:housenumber":"18",
    "addr:postcode":"4064",
    "addr:street":"Haig Rd",
    "iso:country":"AU",
    "sg:address":"18 Haig Rd",
    "sg:city":"Milton",
    "sg:classifiers":[
        {
            "category":"Health Services",
            "subcategory":"Health Practitioner",
            "type":"Services"
        }
    ],
    "sg:phone":"+61 7 3367 3817",
    "sg:postcode":"4064",
    "sg:province":"QLD",
    "sg:tags":[
        "alternative"
    ],
    "wof:name":"Australian Association of Yoga in Daily Life",
    "wof:placetype":"venue"
},
  "geometry": {"coordinates":[153.000396728,-27.4673595428],"type":"Point"}
}