{
  "type": "Feature",
  "properties": {
    "iso:country":"AU",
    "sg:address":"280 Beatty Rd",
    "sg:city":"Archerfield",
    "sg:classifiers":[
        {
            "category":"Professional",
            "subcategory":"Employment Agencies",
            "type":"Services"
        }
    ],
    "sg:phone":"+61 7 3272 9569",
    "sg:postcode":"4108",
    "sg:province":"QLD",
    "sg:tags":[
        "entertainer",
        "agent"
    ],
    "wof:name":"Fireworx",
    "wof:placetype":"venue"
},
  "geometry": {"coordinates":[153.015167236,-27.5678215027],"type":"Point"}
}