{
  "type": "Feature",
  "properties": {
    "addr:full":"80 Toowoon Bay Rd Toowoon Bay NSW 2261",
    "addr:housenumber":"80",
    "addr:postcode":"2261",
    "addr:street":"Toowoon Bay Rd",
    "iso:country":"AU",
    "sg:address":"80 Toowoon Bay Rd",
    "sg:city":"Toowoon Bay",
    "sg:classifiers":[
        {
            "category":"Food & Beverages",
            "subcategory":"Groceries & Convenience Stores",
            "type":"Retail Goods"
        }
    ],
    "sg:phone":"+61 2 4332 1398",
    "sg:postcode":"2261",
    "sg:province":"NSW",
    "wof:name":"Toowoon Bay General Store",
    "wof:placetype":"venue"
},
  "geometry": {"coordinates":[151.49580399999999,-33.357735],"type":"Point"}
}