{
  "type": "Feature",
  "properties": {
    "iso:country":"AU",
    "sg:address":"16 Redmond St",
    "sg:city":"Manning",
    "sg:classifiers":[
        {
            "category":"Retail",
            "subcategory":"Auto Rental",
            "type":"Services"
        }
    ],
    "sg:phone":"+61 8 9450 3724",
    "sg:postcode":"6152",
    "sg:province":"WA",
    "sg:tags":[
        "chauffeur",
        "car",
        "hire",
        "driven",
        "limousine"
    ],
    "wof:name":"Wedding Limousine Hire",
    "wof:placetype":"venue"
},
  "geometry": {"coordinates":[115.868294,-32.021782],"type":"Point"}
}