{
  "type": "Feature",
  "properties": {
    "iso:country":"AU",
    "sg:address":"Shop 21, Market Square, Hunter St Mall",
    "sg:city":"Newcastle",
    "sg:classifiers":[
        {
            "category":"Personal",
            "subcategory":"Beauty Salon",
            "type":"Services"
        }
    ],
    "sg:phone":"+61 2 4925 2088",
    "sg:postcode":"2300",
    "sg:province":"NSW",
    "sg:tags":[
        "hairdresser"
    ],
    "wof:name":"David Stewart Hairdressing",
    "wof:placetype":"venue"
},
  "geometry": {"coordinates":[151.78123500000001,-32.926548],"type":"Point"}
}