{
  "type": "Feature",
  "properties": {
    "iso:country":"AU",
    "sg:address":"8 Coplestone St",
    "sg:city":"Scottsdale",
    "sg:classifiers":[
        {
            "category":"Commercial Area",
            "type":"Public Place"
        }
    ],
    "sg:phone":"+61 3 6352 2457",
    "sg:postcode":"7260",
    "sg:province":"TAS",
    "sg:tags":[
        "heavy",
        "carrier"
    ],
    "wof:name":"Stagoll Transport",
    "wof:placetype":"venue"
},
  "geometry": {"coordinates":[147.511688,-41.154476],"type":"Point"}
}