{
  "type": "Feature",
  "properties": {
    "addr:full":"Shop MM4b/ Cnr Neale & Station Rds Deer Park VIC 3023",
    "addr:postcode":"3023",
    "iso:country":"AU",
    "sg:address":"Shop MM4b/ Cnr Neale & Station Rds",
    "sg:city":"Deer Park",
    "sg:classifiers":[
        {
            "category":"Fast Food",
            "type":"Food & Drink"
        }
    ],
    "sg:phone":"+61 3 9361 2888",
    "sg:postcode":"3023",
    "sg:province":"VIC",
    "sg:tags":[
        "away",
        "take"
    ],
    "wof:name":"Noodle Land",
    "wof:placetype":"venue"
},
  "geometry": {"coordinates":[144.776657,-37.752533],"type":"Point"}
}