{
  "type": "Feature",
  "properties": {
    "addr:full":"Shed 1/ 27 Rigby St Nambour QLD 4560",
    "addr:housenumber":"1 / 27",
    "addr:postcode":"4560",
    "addr:street":"Rigby St",
    "iso:country":"AU",
    "sg:address":"Shed 1/ 27 Rigby St",
    "sg:city":"Nambour",
    "sg:classifiers":[
        {
            "category":"Retail",
            "subcategory":"Auto Repair",
            "type":"Services"
        }
    ],
    "sg:phone":"+61 7 5441 7773",
    "sg:postcode":"4560",
    "sg:province":"QLD",
    "sg:tags":[
        "repairer",
        "motor",
        "engineer"
    ],
    "wof:name":"Nambour Automotive Services",
    "wof:placetype":"venue"
},
  "geometry": {"coordinates":[152.96246337900001,-26.6172523499],"type":"Point"}
}