{
  "type": "Feature",
  "properties": {
    "addr:full":"47 Golf Course Drv Tewantin QLD 4565",
    "addr:housenumber":"47",
    "addr:postcode":"4565",
    "addr:street":"Golf Course Drv",
    "iso:country":"AU",
    "sg:address":"47 Golf Course Drv",
    "sg:city":"Tewantin",
    "sg:classifiers":[
        {
            "category":"Food & Beverages",
            "subcategory":"Specialty",
            "type":"Retail Goods"
        }
    ],
    "sg:phone":"+61 7 5474 1072",
    "sg:postcode":"4565",
    "sg:province":"QLD",
    "sg:tags":[
        "product",
        "health"
    ],
    "wof:name":"Amanda & Andrew Campbell Hebalife Distributor",
    "wof:placetype":"venue"
},
  "geometry": {"coordinates":[153.015014648,-26.3919696808],"type":"Point"}
}