{
  "type": "Feature",
  "properties": {
    "iso:country":"AU",
    "sg:address":"1/ 120 Coxs Rd",
    "sg:city":"North Ryde",
    "sg:classifiers":[
        {
            "category":"Health Services",
            "subcategory":"Dentist",
            "type":"Services"
        }
    ],
    "sg:phone":"+61 2 9887 5953",
    "sg:postcode":"2113",
    "sg:province":"NSW",
    "wof:name":"Ryde East School Dental Clinic",
    "wof:placetype":"venue"
},
  "geometry": {"coordinates":[151.120269775,-33.7937355042],"type":"Point"}
}