{
  "type": "Feature",
  "properties": {
    "iso:country":"AU",
    "sg:address":"10 Armstrong St",
    "sg:city":"(North) Ballarat",
    "sg:classifiers":[
        {
            "category":"Communications",
            "subcategory":"Film & Video Production",
            "type":"Services"
        }
    ],
    "sg:phone":"+61 3 5331 6554",
    "sg:postcode":"3350",
    "sg:province":"VIC",
    "sg:tags":[
        "mirror"
    ],
    "wof:name":"Creative Framing Gallery",
    "wof:placetype":"venue"
},
  "geometry": {"coordinates":[143.856247,-37.562859],"type":"Point"}
}