{
  "type": "Feature",
  "properties": {
    "iso:country":"AU",
    "sg:address":"Collier St",
    "sg:city":"Newdegate",
    "sg:classifiers":[
        {
            "category":"Shopping",
            "type":"Retail Goods"
        }
    ],
    "sg:phone":"+61 8 9871 1640",
    "sg:postcode":"6355",
    "sg:province":"WA",
    "sg:tags":[
        "agent",
        "stock"
    ],
    "wof:name":"Elders Limited",
    "wof:placetype":"venue"
},
  "geometry": {"coordinates":[119.02343,-33.094368],"type":"Point"}
}