{
  "type": "Feature",
  "properties": {
    "addr:full":"42 Villers St Grafton NSW 2460",
    "addr:housenumber":"42",
    "addr:postcode":"2460",
    "addr:street":"Villers St",
    "iso:country":"AU",
    "sg:address":"42 Villers St",
    "sg:city":"Grafton",
    "sg:classifiers":[
        {
            "category":"Shopping",
            "type":"Retail Goods"
        }
    ],
    "sg:phone":"+61 2 6643 3989",
    "sg:postcode":"2460",
    "sg:province":"NSW",
    "sg:tags":[
        "equipment",
        "safety",
        "accessory"
    ],
    "wof:name":"Paint Spec",
    "wof:placetype":"venue"
},
  "geometry": {"coordinates":[152.93876648,-29.6912746429],"type":"Point"}
}