{
  "type": "Feature",
  "properties": {
    "addr:full":"142 Bell St Preston VIC 3072",
    "addr:housenumber":"142",
    "addr:postcode":"3072",
    "addr:street":"Bell St",
    "iso:country":"AU",
    "sg:address":"142 Bell St",
    "sg:city":"Preston",
    "sg:classifiers":[
        {
            "category":"Shopping",
            "subcategory":"Clothing, Apparel, & Fashions",
            "type":"Retail Goods"
        }
    ],
    "sg:phone":"+61 3 9416 8149",
    "sg:postcode":"3072",
    "sg:province":"VIC",
    "sg:tags":[
        "menswear"
    ],
    "wof:name":"Najee",
    "wof:placetype":"venue"
},
  "geometry": {"coordinates":[145.01986694300001,-37.7468566895],"type":"Point"}
}