{
  "type": "Feature",
  "properties": {
    "iso:country":"AU",
    "sg:address":"Shop 51 Canelands Shoppingtown",
    "sg:city":"Mackay",
    "sg:classifiers":[
        {
            "category":"Shopping",
            "subcategory":"Clothing, Apparel, & Fashions",
            "type":"Retail Goods"
        }
    ],
    "sg:phone":"+61 7 4951 4667",
    "sg:postcode":"4740",
    "sg:province":"QLD",
    "sg:tags":[
        "lady",
        "wear"
    ],
    "wof:name":"Rockmans Stores Pty Limited",
    "wof:placetype":"venue"
},
  "geometry": {"coordinates":[149.11184700000001,-21.15519],"type":"Point"}
}