{
  "type": "Feature",
  "properties": {
    "iso:country":"AU",
    "sg:address":"Unit 4/ 5 Carlo Drv",
    "sg:city":"Cannonvale",
    "sg:classifiers":[
        {
            "category":"Shopping",
            "subcategory":"Stationery & Office Supplies",
            "type":"Retail Goods"
        }
    ],
    "sg:phone":"+61 7 4948 3322",
    "sg:postcode":"4802",
    "sg:province":"QLD",
    "sg:tags":[
        "equipment",
        "sailboarding"
    ],
    "wof:name":"Ullman Sails Whitsundays",
    "wof:placetype":"venue"
},
  "geometry": {"coordinates":[148.673583984,-20.28814888],"type":"Point"}
}