{
  "type": "Feature",
  "properties": {
    "addr:full":"U1/ 9 Enterprise Pl Wetherill Park NSW 2164",
    "addr:housenumber":"9",
    "addr:postcode":"2164",
    "addr:street":"U1 /;Pl",
    "iso:country":"AU",
    "sg:address":"U1/ 9 Enterprise Pl",
    "sg:city":"Wetherill Park",
    "sg:classifiers":[
        {
            "category":"Professional",
            "type":"Services"
        }
    ],
    "sg:phone":"+61 2 9756 4456",
    "sg:postcode":"2164",
    "sg:province":"NSW",
    "sg:tags":[
        "transport"
    ],
    "wof:name":"Transport Mangement Soloutions",
    "wof:placetype":"venue"
},
  "geometry": {"coordinates":[150.88638305699999,-33.8517913818],"type":"Point"}
}