{
  "type": "Feature",
  "properties": {
    "iso:country":"AU",
    "sg:address":"326 Great Western Hwy",
    "sg:city":"Wentworthville",
    "sg:classifiers":[
        {
            "category":"Food & Beverages",
            "subcategory":"Bakery",
            "type":"Retail Goods"
        }
    ],
    "sg:phone":"+61 2 9688 4256",
    "sg:postcode":"2145",
    "sg:province":"NSW",
    "sg:tags":[
        "baker"
    ],
    "wof:name":"Highway Plaza Bakehouse",
    "wof:placetype":"venue"
},
  "geometry": {"coordinates":[150.969284058,-33.8152694702],"type":"Point"}
}