{
  "type": "Feature",
  "properties": {
    "addr:full":"31 Wallsend Rd Sandgate NSW 2304",
    "addr:housenumber":"31",
    "addr:postcode":"2304",
    "addr:street":"Wallsend Rd",
    "iso:country":"AU",
    "sg:address":"31 Wallsend Rd",
    "sg:city":"Sandgate",
    "sg:classifiers":[
        {
            "category":"Retail",
            "subcategory":"Auto Rental",
            "type":"Services"
        }
    ],
    "sg:phone":"+61 2 4967 2711",
    "sg:postcode":"2304",
    "sg:province":"NSW",
    "sg:tags":[
        "bus",
        "truck"
    ],
    "wof:name":"Banana Rentals",
    "wof:placetype":"venue"
},
  "geometry": {"coordinates":[151.70758056599999,-32.8717041016],"type":"Point"}
}