{
  "type": "Feature",
  "properties": {
    "iso:country":"AU",
    "sg:address":"2- 6 June Ave",
    "sg:city":"Dromana",
    "sg:classifiers":[
        {
            "category":"Wholesale",
            "subcategory":"Metals & Minerals",
            "type":"Manufacturing & Wholesale Goods"
        }
    ],
    "sg:phone":"+61 1300 720 597",
    "sg:postcode":"3936",
    "sg:province":"VIC",
    "sg:tags":[
        "steel",
        "merchant"
    ],
    "wof:name":"Robot Building Supplies",
    "wof:placetype":"venue"
},
  "geometry": {"coordinates":[144.98695373499999,-38.3330993652],"type":"Point"}
}