{
  "type": "Feature",
  "properties": {
    "addr:full":"Shop 8/ 216 Charles St Launceston TAS 7250",
    "addr:housenumber":"shop 8 / 216",
    "addr:postcode":"7250",
    "addr:street":"Charles St",
    "iso:country":"AU",
    "sg:address":"Shop 8/ 216 Charles St",
    "sg:city":"Launceston",
    "sg:classifiers":[
        {
            "category":"Organizations",
            "subcategory":"Community Association",
            "type":"Services"
        }
    ],
    "sg:phone":"+61 3 6334 9917",
    "sg:postcode":"7250",
    "sg:province":"TAS",
    "sg:tags":[
        "organisation",
        "family",
        "welfare"
    ],
    "wof:name":"Carers Tasmania Inc",
    "wof:placetype":"venue"
},
  "geometry": {"coordinates":[147.14065551799999,-41.4422874451],"type":"Point"}
}