{
  "type": "Feature",
  "properties": {
    "addr:full":"9 Park Ave Morwell VIC 3840",
    "addr:housenumber":"9",
    "addr:postcode":"3840",
    "addr:street":"Park Ave",
    "iso:country":"AU",
    "sg:address":"9 Park Ave",
    "sg:city":"Morwell",
    "sg:classifiers":[
        {
            "category":"Military Area",
            "subcategory":"Air Force Base",
            "type":"Public Place"
        }
    ],
    "sg:phone":"+61 419 141 038",
    "sg:postcode":"3840",
    "sg:province":"VIC",
    "sg:tags":[
        "men's",
        "tailor"
    ],
    "wof:name":"The House Of Petrucci Pty Ltd",
    "wof:placetype":"venue"
},
  "geometry": {"coordinates":[146.43377685600001,-38.2308387756],"type":"Point"}
}