{
  "type": "Feature",
  "properties": {
    "addr:full":"1576 Gympie Rd Carseldine QLD 4034",
    "addr:housenumber":"1576",
    "addr:postcode":"4034",
    "addr:street":"Gympie Rd",
    "iso:country":"AU",
    "sg:address":"1576 Gympie Rd",
    "sg:city":"Carseldine",
    "sg:classifiers":[
        {
            "category":"Professional",
            "subcategory":"Computer Services",
            "type":"Services"
        }
    ],
    "sg:phone":"+61 7 3862 7745",
    "sg:postcode":"4034",
    "sg:province":"QLD",
    "sg:tags":[
        "repairs",
        "upgrade",
        "equipment"
    ],
    "wof:name":"Access Computers",
    "wof:placetype":"venue"
},
  "geometry": {"coordinates":[153.014206,-27.352011],"type":"Point"}
}