{
  "type": "Feature",
  "properties": {
    "addr:full":"37 Manilla St East Brisbane QLD 4169",
    "addr:housenumber":"37",
    "addr:postcode":"4169",
    "addr:street":"Manilla St",
    "iso:country":"AU",
    "sg:address":"37 Manilla St",
    "sg:city":"East Brisbane",
    "sg:classifiers":[
        {
            "category":"Home & Garden",
            "subcategory":"Hardware",
            "type":"Retail Goods"
        }
    ],
    "sg:phone":"+61 7 3392 1511",
    "sg:postcode":"4169",
    "sg:province":"QLD",
    "sg:tags":[
        "plumber",
        "supply"
    ],
    "wof:name":"Specialised Plumbing Centre",
    "wof:placetype":"venue"
},
  "geometry": {"coordinates":[153.04182434099999,-27.4824314117],"type":"Point"}
}