{
  "type": "Feature",
  "properties": {
    "iso:country":"AU",
    "sg:address":"24 Crowd Rd",
    "sg:city":"Gelorup",
    "sg:classifiers":[
        {
            "category":"Building & Trades",
            "subcategory":"Cleaning & Sanitation",
            "type":"Services"
        }
    ],
    "sg:phone":"+61 407 441 972",
    "sg:postcode":"6230",
    "sg:province":"WA",
    "sg:tags":[
        "chemical",
        "pressure",
        "steam",
        "contractor"
    ],
    "wof:name":"Lotan Contractors Pty Ltd",
    "wof:placetype":"venue"
},
  "geometry": {"coordinates":[115.629501,-33.414337],"type":"Point"}
}