{
  "type": "Feature",
  "properties": {
    "iso:country":"AU",
    "sg:address":"859 Nepean Hwy",
    "sg:city":"Moorabbin",
    "sg:classifiers":[
        {
            "category":"Retail",
            "subcategory":"Auto Repair",
            "type":"Services"
        }
    ],
    "sg:phone":"+61 3 9557 4488",
    "sg:postcode":"3189",
    "sg:province":"VIC",
    "sg:tags":[
        "repairer",
        "motor",
        "engineer"
    ],
    "wof:name":"Southpoint HYUNDAI",
    "wof:placetype":"venue"
},
  "geometry": {"coordinates":[145.02818298299999,-37.9259986877],"type":"Point"}
}