{
  "type": "Feature",
  "properties": {
    "addr:full":"Biggera Waters Shpng Cntr Hollywell Rd Biggera Waters QLD 4216",
    "addr:postcode":"4216",
    "addr:street":"Hollywell Rd",
    "iso:country":"AU",
    "sg:address":"Biggera Waters Shpng Cntr Hollywell Rd",
    "sg:city":"Biggera Waters",
    "sg:classifiers":[
        {
            "category":"Health Services",
            "subcategory":"Optometrist",
            "type":"Services"
        }
    ],
    "sg:phone":"+61 7 5571 1159",
    "sg:postcode":"4216",
    "sg:province":"QLD",
    "wof:name":"Reynolds Geoffrey",
    "wof:placetype":"venue"
},
  "geometry": {"coordinates":[153.400588989,-27.9347782135],"type":"Point"}
}