{
  "type": "Feature",
  "properties": {
    "addr:full":"85 Conadilly St Gunnedah NSW 2380",
    "addr:housenumber":"85",
    "addr:postcode":"2380",
    "addr:street":"Conadilly St",
    "iso:country":"AU",
    "sg:address":"85 Conadilly St",
    "sg:city":"Gunnedah",
    "sg:classifiers":[
        {
            "category":"Food & Beverages",
            "subcategory":"Fruits & Vegetables",
            "type":"Retail Goods"
        }
    ],
    "sg:phone":"+61 2 6742 0010",
    "sg:postcode":"2380",
    "sg:province":"NSW",
    "sg:tags":[
        "wholesale"
    ],
    "wof:name":"Dave & Sue's Nature's Best",
    "wof:placetype":"venue"
},
  "geometry": {"coordinates":[150.24859619099999,-30.9755783081],"type":"Point"}
}