{
  "type": "Feature",
  "properties": {
    "iso:country":"AU",
    "sg:address":"1 Alfred St",
    "sg:city":"Blackburn",
    "sg:classifiers":[
        {
            "category":"Shopping",
            "subcategory":"Stationery & Office Supplies",
            "type":"Retail Goods"
        }
    ],
    "sg:phone":"+61 3 9894 0288",
    "sg:postcode":"3130",
    "sg:province":"VIC",
    "sg:tags":[
        "packaging",
        "equipment",
        "sealing",
        "filling"
    ],
    "wof:name":"Australian Multi Packaging Supplies Pty Ltd",
    "wof:placetype":"venue"
},
  "geometry": {"coordinates":[145.15846252399999,-37.8207206726],"type":"Point"}
}