{
  "type": "Feature",
  "properties": {
    "addr:full":"52 Fitzgerald Rd Morley WA 6062",
    "addr:housenumber":"52",
    "addr:postcode":"6062",
    "addr:street":"Fitzgerald Rd",
    "iso:country":"AU",
    "sg:address":"52 Fitzgerald Rd",
    "sg:city":"Morley",
    "sg:classifiers":[
        {
            "category":"Banks & Credit Unions",
            "subcategory":"Bureau De Change",
            "type":"Services"
        }
    ],
    "sg:phone":"+61 8 9276 2592",
    "sg:postcode":"6062",
    "sg:province":"WA",
    "sg:tags":[
        "archaeology"
    ],
    "wof:name":"Quartermaine Consultants",
    "wof:placetype":"venue"
},
  "geometry": {"coordinates":[115.909538269,-31.8889503479],"type":"Point"}
}