{
  "type": "Feature",
  "properties": {
    "addr:full":"Russell St Mt Evelyn VIC 3796",
    "addr:postcode":"3796",
    "addr:street":"Russell St",
    "iso:country":"AU",
    "sg:address":"Russell St",
    "sg:city":"Mt Evelyn",
    "sg:classifiers":[
        {
            "category":"Professional",
            "subcategory":"Computer Services",
            "type":"Services"
        }
    ],
    "sg:phone":"+61 3 9736 3245",
    "sg:postcode":"3796",
    "sg:province":"VIC",
    "sg:tags":[
        "package",
        "software"
    ],
    "wof:name":"Exact Systems",
    "wof:placetype":"venue"
},
  "geometry": {"coordinates":[145.390457153,-37.7804489136],"type":"Point"}
}