{
  "type": "Feature",
  "properties": {
    "iso:country":"AU",
    "sg:address":"PO Box 309",
    "sg:city":"Belgrave",
    "sg:classifiers":[
        {
            "category":"Social Services",
            "subcategory":"Job Training",
            "type":"Services"
        }
    ],
    "sg:phone":"+61 419 520 486",
    "sg:postcode":"3160",
    "sg:province":"VIC",
    "sg:tags":[
        "lighting",
        "maintenance"
    ],
    "wof:name":"Mr. Tube",
    "wof:placetype":"venue"
},
  "geometry": {"coordinates":[145.35601806599999,-37.9088592529],"type":"Point"}
}