{
  "type": "Feature",
  "properties": {
    "addr:full":"Shop 3, Lvl 1/ 537 Boundary St Spring Hill QLD 4000",
    "addr:housenumber":"shop;/ 537",
    "addr:postcode":"4000",
    "addr:street":"Boundary St",
    "iso:country":"AU",
    "sg:address":"Shop 3, Lvl 1/ 537 Boundary St",
    "sg:city":"Spring Hill",
    "sg:classifiers":[
        {
            "category":"Personal",
            "subcategory":"Beauty Salon",
            "type":"Services"
        }
    ],
    "sg:phone":"+61 7 3839 3591",
    "sg:postcode":"4000",
    "sg:province":"QLD",
    "wof:name":"Todays Brazilian",
    "wof:placetype":"venue"
},
  "geometry": {"coordinates":[153.02137756400001,-27.4602508545],"type":"Point"}
}