{
  "type": "Feature",
  "properties": {
    "addr:full":"New Beach Rd Edgecliff NSW 2027",
    "addr:postcode":"2027",
    "addr:street":"Beach Rd",
    "iso:country":"AU",
    "sg:address":"New Beach Rd",
    "sg:city":"Edgecliff",
    "sg:classifiers":[
        {
            "category":"Recreation",
            "subcategory":"Sailing Club",
            "type":"Entertainment"
        }
    ],
    "sg:phone":"+61 2 9363 5067",
    "sg:postcode":"2027",
    "sg:province":"NSW",
    "sg:tags":[
        "yacht"
    ],
    "wof:name":"RAN Sailing Asscn",
    "wof:placetype":"venue"
},
  "geometry": {"coordinates":[151.232147217,-33.8758811951],"type":"Point"}
}