{
  "type": "Feature",
  "properties": {
    "iso:country":"AU",
    "sg:address":"29 Strabane Ave",
    "sg:city":"Box Hill",
    "sg:classifiers":[
        {
            "category":"Education",
            "subcategory":"University",
            "type":"Public Place"
        }
    ],
    "sg:phone":"+61 3 9898 3336",
    "sg:postcode":"3128",
    "sg:province":"VIC",
    "sg:tags":[
        "educational",
        "organisation",
        "cultural"
    ],
    "wof:name":"Universities Of The Third Age (U3A) - Victorian Network",
    "wof:placetype":"venue"
},
  "geometry": {"coordinates":[145.11236572300001,-37.8073539734],"type":"Point"}
}