{
  "type": "Feature",
  "properties": {
    "addr:full":"36 Park Rd Milton QLD 4064",
    "addr:housenumber":"36",
    "addr:postcode":"4064",
    "addr:street":"Park Rd",
    "iso:country":"AU",
    "sg:address":"36 Park Rd",
    "sg:city":"Milton",
    "sg:classifiers":[
        {
            "category":"Personal",
            "subcategory":"Day Spa",
            "type":"Services"
        }
    ],
    "sg:phone":"+61 7 3511 7044",
    "sg:postcode":"4064",
    "sg:province":"QLD",
    "wof:name":"Beautiful Beings",
    "wof:placetype":"venue"
},
  "geometry": {"coordinates":[153.00498962399999,-27.4713764191],"type":"Point"}
}