{
  "type": "Feature",
  "properties": {
    "addr:full":"487 King St North Melbourne VIC 3051",
    "addr:housenumber":"487",
    "addr:postcode":"3051",
    "addr:street":"King St",
    "iso:country":"AU",
    "sg:address":"487 King St",
    "sg:city":"North Melbourne",
    "sg:classifiers":[
        {
            "category":"Arena",
            "subcategory":"Sports Club",
            "type":"Entertainment"
        }
    ],
    "sg:phone":"+61 3 9329 7766",
    "sg:postcode":"3051",
    "sg:province":"VIC",
    "sg:tags":[
        "organisation",
        "sporting"
    ],
    "wof:name":"Netball Victoria",
    "wof:placetype":"venue"
},
  "geometry": {"coordinates":[144.95173645,-37.8084602356],"type":"Point"}
}