{
  "type": "Feature",
  "properties": {
    "iso:country":"AU",
    "sg:address":"14 Church St",
    "sg:city":"Benalla",
    "sg:classifiers":[
        {
            "category":"Government",
            "subcategory":"Court House",
            "type":"Public Place"
        }
    ],
    "sg:phone":"+61 3 5762 3365",
    "sg:postcode":"3672",
    "sg:province":"VIC",
    "sg:tags":[
        "personal",
        "marriage",
        "family",
        "counselling"
    ],
    "wof:name":"Positive Directions",
    "wof:placetype":"venue"
},
  "geometry": {"coordinates":[145.98178100000001,-36.550091],"type":"Point"}
}