{
  "type": "Feature",
  "properties": {
    "iso:country":"AU",
    "sg:address":"11 Mary St",
    "sg:city":"Hawthorn",
    "sg:classifiers":[
        {
            "category":"Real Estate",
            "subcategory":"Real Estate Agent",
            "type":"Services"
        }
    ],
    "sg:phone":"+61 3 9819 6819",
    "sg:postcode":"3122",
    "sg:province":"VIC",
    "wof:name":"John Partridge Rural Properties",
    "wof:placetype":"venue"
},
  "geometry": {"coordinates":[145.02897644000001,-37.8172454834],"type":"Point"}
}