{
  "type": "Feature",
  "properties": {
    "addr:full":"21 Canyon Rd Baulkham Hills NSW 2153",
    "addr:housenumber":"21",
    "addr:postcode":"2153",
    "addr:street":"Canyon Rd",
    "iso:country":"AU",
    "sg:address":"21 Canyon Rd",
    "sg:city":"Baulkham Hills",
    "sg:classifiers":[
        {
            "category":"Insurance",
            "subcategory":"Insurance Agent",
            "type":"Services"
        }
    ],
    "sg:phone":"+61 2 9686 6488",
    "sg:postcode":"2153",
    "sg:province":"NSW",
    "wof:name":"MultiSource Insurance Analysis & Planning Pty Ltd",
    "wof:placetype":"venue"
},
  "geometry": {"coordinates":[150.999557495,-33.7656784058],"type":"Point"}
}