{
  "type": "Feature",
  "properties": {
    "addr:full":"153 Macquarie St Parramatta NSW 2150",
    "addr:housenumber":"153",
    "addr:postcode":"2150",
    "addr:street":"Macquarie St",
    "iso:country":"AU",
    "sg:address":"153 Macquarie St",
    "sg:city":"Parramatta",
    "sg:classifiers":[
        {
            "category":"Government",
            "subcategory":"Post Office",
            "type":"Public Place"
        }
    ],
    "sg:phone":"+61 13 11 18",
    "sg:postcode":"2150",
    "sg:province":"NSW",
    "sg:tags":[
        "postal"
    ],
    "wof:name":"Australia Post Business Centre",
    "wof:placetype":"venue"
},
  "geometry": {"coordinates":[151.01458740199999,-33.8069152832],"type":"Point"}
}