{
  "type": "Feature",
  "properties": {
    "addr:full":"728c Marion Rd Marion SA 5043",
    "addr:housenumber":"728c",
    "addr:postcode":"5043",
    "addr:street":"Marion Rd",
    "iso:country":"AU",
    "sg:address":"728c Marion Rd",
    "sg:city":"Marion",
    "sg:classifiers":[
        {
            "category":"Personal",
            "subcategory":"Barber",
            "type":"Services"
        }
    ],
    "sg:phone":"+61 8 8276 5888",
    "sg:postcode":"5043",
    "sg:province":"SA",
    "wof:name":"Gents Hair Studio",
    "wof:placetype":"venue"
},
  "geometry": {"coordinates":[138.558029,-35.00872],"type":"Point"}
}