{
  "type": "Feature",
  "properties": {
    "addr:full":"10 Lexington Rd Underwood QLD 4119",
    "addr:housenumber":"10",
    "addr:postcode":"4119",
    "addr:street":"Lexington Rd",
    "iso:country":"AU",
    "sg:address":"10 Lexington Rd",
    "sg:city":"Underwood",
    "sg:classifiers":[
        {
            "category":"Retail",
            "subcategory":"Car Wash",
            "type":"Services"
        }
    ],
    "sg:phone":"+61 7 3841 1666",
    "sg:postcode":"4119",
    "sg:province":"QLD",
    "sg:tags":[
        "auction",
        "motor"
    ],
    "wof:name":"Auto Group Auctions",
    "wof:placetype":"venue"
},
  "geometry": {"coordinates":[153.12181091299999,-27.613117218],"type":"Point"}
}