{
  "type": "Feature",
  "properties": {
    "addr:full":"8 Claverton Ave Mt Dandenong VIC 3767",
    "addr:housenumber":"8",
    "addr:postcode":"3767",
    "addr:street":"Claverton Ave Mt",
    "iso:country":"AU",
    "sg:address":"8 Claverton Ave",
    "sg:city":"Mt Dandenong",
    "sg:classifiers":[
        {
            "category":"Farming",
            "subcategory":"Nursery",
            "type":"Manufacturing & Wholesale Goods"
        }
    ],
    "sg:phone":"+61 3 9751 1341",
    "sg:postcode":"3767",
    "sg:province":"VIC",
    "wof:name":"Bushy Park Nursery",
    "wof:placetype":"venue"
},
  "geometry": {"coordinates":[145.354782105,-37.842212677],"type":"Point"}
}