{
  "type": "Feature",
  "properties": {
    "iso:country":"AU",
    "sg:address":"25 Landseer Crs",
    "sg:city":"Dernancourt",
    "sg:classifiers":[
        {
            "category":"Wholesale",
            "subcategory":"Home Furnishings",
            "type":"Manufacturing & Wholesale Goods"
        }
    ],
    "sg:phone":"+61 1800 252 624",
    "sg:postcode":"5075",
    "sg:province":"SA",
    "sg:tags":[
        "wholesaler",
        "mfrs",
        "kitchenware"
    ],
    "wof:name":"Victorinox Cutlery",
    "wof:placetype":"venue"
},
  "geometry": {"coordinates":[138.683792114,-34.8610191345],"type":"Point"}
}