{
  "type": "Feature",
  "properties": {
    "iso:country":"AU",
    "sg:address":"54 Kembla St",
    "sg:city":"Wollongong",
    "sg:classifiers":[
        {
            "category":"Travel",
            "subcategory":"Hotels & Motels",
            "type":"Entertainment"
        }
    ],
    "sg:phone":"+61 2 4225 2548",
    "sg:postcode":"2500",
    "sg:province":"NSW",
    "sg:website":"http://www.wollongongapartments.com.au",
    "wof:name":"Wollongong Serviced Apartments",
    "wof:placetype":"venue"
},
  "geometry": {"coordinates":[150.897873,-34.422657],"type":"Point"}
}