{
  "type": "Feature",
  "properties": {
    "iso:country":"AU",
    "sg:address":"37 Challis Ave",
    "sg:city":"Potts Point",
    "sg:classifiers":[
        {
            "category":"Retail",
            "subcategory":"Laundry & Dry Cleaning",
            "type":"Services"
        }
    ],
    "sg:phone":"+61 2 9368 1324",
    "sg:postcode":"2011",
    "sg:province":"NSW",
    "wof:name":"Challis Ave Laundry",
    "wof:placetype":"venue"
},
  "geometry": {"coordinates":[151.224243164,-33.8689193726],"type":"Point"}
}