{
  "type": "Feature",
  "properties": {
    "iso:country":"AU",
    "sg:address":"7 Gambrinus Crt",
    "sg:city":"Rochedale South",
    "sg:classifiers":[
        {
            "category":"Building & Trades",
            "subcategory":"Locksmith",
            "type":"Services"
        }
    ],
    "sg:phone":"+61 7 3801 4411",
    "sg:postcode":"4123",
    "sg:province":"QLD",
    "sg:tags":[
        "lock"
    ],
    "wof:name":"A ABD Mobile Locksmith",
    "wof:placetype":"venue"
},
  "geometry": {"coordinates":[153.13006591800001,-27.6052742004],"type":"Point"}
}