{
  "type": "Feature",
  "properties": {
    "iso:country":"AU",
    "sg:address":"32 Wolverhampton St",
    "sg:city":"Stafford",
    "sg:classifiers":[
        {
            "category":"Manufacturing",
            "subcategory":"Motor Vehicles & Parts",
            "type":"Manufacturing & Wholesale Goods"
        }
    ],
    "sg:phone":"+61 7 3356 6066",
    "sg:postcode":"4053",
    "sg:province":"QLD",
    "sg:tags":[
        "replacement"
    ],
    "wof:name":"Qld Converter Engineering Services",
    "wof:placetype":"venue"
},
  "geometry": {"coordinates":[153.01402282699999,-27.4173622131],"type":"Point"}
}