{
  "type": "Feature",
  "properties": {
    "iso:country":"AU",
    "sg:address":"13 Raymond St",
    "sg:city":"Ashwood",
    "sg:classifiers":[
        {
            "category":"Professional",
            "subcategory":"Art Services",
            "type":"Services"
        }
    ],
    "sg:phone":"+61 3 9888 3849",
    "sg:postcode":"3147",
    "sg:province":"VIC",
    "sg:tags":[
        "decorator",
        "painter"
    ],
    "wof:name":"True Colour Painting Service",
    "wof:placetype":"venue"
},
  "geometry": {"coordinates":[145.10948181099999,-37.8645019531],"type":"Point"}
}