{
  "type": "Feature",
  "properties": {
    "addr:full":"190 Montpelier Rd Bowen Hills QLD 4006",
    "addr:housenumber":"190",
    "addr:postcode":"4006",
    "addr:street":"Montpelier Rd",
    "iso:country":"AU",
    "sg:address":"190 Montpelier Rd",
    "sg:city":"Bowen Hills",
    "sg:classifiers":[
        {
            "category":"Building & Trades",
            "subcategory":"Construction",
            "type":"Services"
        }
    ],
    "sg:phone":"+61 7 3251 8800",
    "sg:postcode":"4006",
    "sg:province":"QLD",
    "sg:tags":[
        "contractor"
    ],
    "wof:name":"Walton Construction ( Qld ) Pty Ltd",
    "wof:placetype":"venue"
},
  "geometry": {"coordinates":[153.038330078,-27.4481163025],"type":"Point"}
}