{
  "type": "Feature",
  "properties": {
    "addr:full":"36 Haldon St Lakemba NSW 2195",
    "addr:housenumber":"36",
    "addr:postcode":"2195",
    "addr:street":"Haldon St",
    "iso:country":"AU",
    "sg:address":"36 Haldon St",
    "sg:city":"Lakemba",
    "sg:classifiers":[
        {
            "category":"Food & Beverages",
            "subcategory":"Meat & Fish",
            "type":"Retail Goods"
        }
    ],
    "sg:phone":"+61 2 9758 9170",
    "sg:postcode":"2195",
    "sg:province":"NSW",
    "sg:tags":[
        "seafood"
    ],
    "wof:name":"Ocean City Fish Shop",
    "wof:placetype":"venue"
},
  "geometry": {"coordinates":[151.076324,-33.9189],"type":"Point"}
}