{
  "type": "Feature",
  "properties": {
    "iso:country":"AU",
    "sg:address":"7 Massey Pl St",
    "sg:city":"Ives Chase",
    "sg:classifiers":[
        {
            "category":"Manufacturing",
            "subcategory":"Jewelry",
            "type":"Manufacturing & Wholesale Goods"
        }
    ],
    "sg:phone":"+61 2 9988 4815",
    "sg:postcode":"2075",
    "sg:province":"NSW",
    "sg:tags":[
        "mfrg",
        "jeweller"
    ],
    "wof:name":"Treasures Jewellery",
    "wof:placetype":"venue"
},
  "geometry": {"coordinates":[151.160232544,-33.7164382935],"type":"Point"}
}