{
  "type": "Feature",
  "properties": {
    "iso:country":"AU",
    "sg:address":"97a Kelly St",
    "sg:city":"Scone",
    "sg:classifiers":[
        {
            "category":"Professional",
            "subcategory":"Accounting & Tax Preparation",
            "type":"Services"
        }
    ],
    "sg:phone":"+61 2 6544 4400",
    "sg:postcode":"2337",
    "sg:province":"NSW",
    "sg:tags":[
        "bookkeeping"
    ],
    "wof:name":"Scone Sourcing + Solutions",
    "wof:placetype":"venue"
},
  "geometry": {"coordinates":[150.86799621599999,-32.04712677],"type":"Point"}
}