{
  "type": "Feature",
  "properties": {
    "addr:full":"245 Leith Rd Leith TAS 7315",
    "addr:housenumber":"245",
    "addr:postcode":"7315",
    "addr:street":"Leith Rd",
    "iso:country":"AU",
    "sg:address":"245 Leith Rd",
    "sg:city":"Leith",
    "sg:classifiers":[
        {
            "category":"Professional",
            "subcategory":"Business Services",
            "type":"Services"
        }
    ],
    "sg:phone":"+61 3 6428 2795",
    "sg:postcode":"7315",
    "sg:province":"TAS",
    "sg:tags":[
        "livestock",
        "transport"
    ],
    "wof:name":"Viney R G & D J",
    "wof:placetype":"venue"
},
  "geometry": {"coordinates":[146.255203247,-41.1562995911],"type":"Point"}
}