{
  "type": "Feature",
  "properties": {
    "iso:country":"AU",
    "sg:address":"10 Tradelink Rd",
    "sg:city":"Browns Plains",
    "sg:classifiers":[
        {
            "category":"Retail",
            "subcategory":"Auto Repair",
            "type":"Services"
        }
    ],
    "sg:phone":"+61 7 3800 2340",
    "sg:postcode":"4118",
    "sg:province":"QLD",
    "sg:tags":[
        "clutch",
        "brake"
    ],
    "wof:name":"Power Shift Transmissions",
    "wof:placetype":"venue"
},
  "geometry": {"coordinates":[153.03408813499999,-27.6648254395],"type":"Point"}
}