{
  "type": "Feature",
  "properties": {
    "addr:full":"40 Gibbons St Narrabri NSW 2390",
    "addr:housenumber":"40",
    "addr:postcode":"2390",
    "addr:street":"Gibbons St",
    "iso:country":"AU",
    "sg:address":"40 Gibbons St",
    "sg:city":"Narrabri",
    "sg:classifiers":[
        {
            "category":"Health Services",
            "subcategory":"Chiropractor",
            "type":"Services"
        }
    ],
    "sg:phone":"+61 2 6792 2644",
    "sg:postcode":"2390",
    "sg:province":"NSW",
    "wof:name":"Galati Catherine",
    "wof:placetype":"venue"
},
  "geometry": {"coordinates":[149.78074645999999,-30.3341007233],"type":"Point"}
}