{
  "type": "Feature",
  "properties": {
    "addr:full":"27 Shadbolt St Mukinbudin WA 6479",
    "addr:housenumber":"27",
    "addr:postcode":"6479",
    "addr:street":"Shadbolt St",
    "iso:country":"AU",
    "sg:address":"27 Shadbolt St",
    "sg:city":"Mukinbudin",
    "sg:classifiers":[
        {
            "category":"Food & Beverages",
            "subcategory":"Supermarket",
            "type":"Retail Goods"
        }
    ],
    "sg:phone":"+61 8 9047 1153",
    "sg:postcode":"6479",
    "sg:province":"WA",
    "sg:tags":[
        "grocery",
        "store"
    ],
    "wof:name":"IGA Supermarket Mukinbudin",
    "wof:placetype":"venue"
},
  "geometry": {"coordinates":[118.20687866199999,-30.9146957397],"type":"Point"}
}