{
  "type": "Feature",
  "properties": {
    "addr:full":"8 Troode St Spearwood WA 6163",
    "addr:housenumber":"8",
    "addr:postcode":"6163",
    "addr:street":"Troode St",
    "iso:country":"AU",
    "sg:address":"8 Troode St",
    "sg:city":"Spearwood",
    "sg:classifiers":[
        {
            "category":"Communications",
            "subcategory":"News Services",
            "type":"Services"
        }
    ],
    "sg:phone":"+61 8 9418 6888",
    "sg:postcode":"6163",
    "sg:province":"WA",
    "sg:tags":[
        "information",
        "tourist",
        "attractions"
    ],
    "wof:name":"Cables Water Ski Park",
    "wof:placetype":"venue"
},
  "geometry": {"coordinates":[115.77855700000001,-32.120472],"type":"Point"}
}