{
  "type": "Feature",
  "properties": {
    "addr:full":"8 Laver Pl Crookwell NSW 2583",
    "addr:housenumber":"8",
    "addr:postcode":"2583",
    "addr:street":"Laver Pl",
    "iso:country":"AU",
    "sg:address":"8 Laver Pl",
    "sg:city":"Crookwell",
    "sg:classifiers":[
        {
            "category":"Building & Trades",
            "subcategory":"Construction",
            "type":"Services"
        }
    ],
    "sg:phone":"+61 2 4832 1886",
    "sg:postcode":"2583",
    "sg:province":"NSW",
    "sg:tags":[
        "joiner",
        "carpenter"
    ],
    "wof:name":"Peter Smith",
    "wof:placetype":"venue"
},
  "geometry": {"coordinates":[149.46209716800001,-34.4522399902],"type":"Point"}
}