{
  "type": "Feature",
  "properties": {
    "addr:full":"AMA Place, 88 L&#039;Estrange Tce Kelvin Grove QLD 4059",
    "addr:housenumber":"88",
    "addr:postcode":"4059",
    "addr:street":"Ama;Estrange Tce",
    "iso:country":"AU",
    "sg:address":"AMA Place, 88",
    "sg:city":"L&#039;Estrange Tce Kelvin Grove",
    "sg:classifiers":[
        {
            "category":"Health Services",
            "subcategory":"Doctor",
            "type":"Services"
        }
    ],
    "sg:phone":"+61 7 3856 5566",
    "sg:postcode":"4059",
    "sg:province":"QLD",
    "sg:tags":[
        "podiatrist"
    ],
    "wof:name":"Eadie Podiatry",
    "wof:placetype":"venue"
},
  "geometry": {"coordinates":[152.999176025,-27.4593601227],"type":"Point"}
}