{
  "type": "Feature",
  "properties": {
    "addr:full":"Woodburn St Evans Head NSW 2473",
    "addr:postcode":"2473",
    "addr:street":"Woodburn St Evans",
    "iso:country":"AU",
    "sg:address":"Woodburn St",
    "sg:city":"Evans Head",
    "sg:classifiers":[
        {
            "category":"Autos & Motor Vehicles",
            "subcategory":"Fuel & Gas Station",
            "type":"Retail Goods"
        }
    ],
    "sg:phone":"+61 2 6682 4219",
    "sg:postcode":"2473",
    "sg:province":"NSW",
    "wof:name":"BP Australia Limited",
    "wof:placetype":"venue"
},
  "geometry": {"coordinates":[153.425125122,-29.1113262177],"type":"Point"}
}