{
  "type": "Feature",
  "properties": {
    "addr:full":"4 Yarra St Kew VIC 3101",
    "addr:housenumber":"4",
    "addr:postcode":"3101",
    "addr:street":"Yarra",
    "iso:country":"AU",
    "sg:address":"4 Yarra St",
    "sg:city":"Kew",
    "sg:classifiers":[
        {
            "category":"Organizations",
            "subcategory":"Community Association",
            "type":"Services"
        }
    ],
    "sg:phone":"+61 3 9853 0604",
    "sg:postcode":"3101",
    "sg:province":"VIC",
    "sg:tags":[
        "shiatsu",
        "therapy"
    ],
    "wof:name":"Kew Natural Therapies",
    "wof:placetype":"venue"
},
  "geometry": {"coordinates":[145.023162842,-37.8043441772],"type":"Point"}
}