{
  "type": "Feature",
  "properties": {
    "addr:full":"62 Main St Mornington VIC 3931",
    "addr:housenumber":"62",
    "addr:postcode":"3931",
    "addr:street":"Main St",
    "iso:country":"AU",
    "sg:address":"62 Main St",
    "sg:city":"Mornington",
    "sg:classifiers":[
        {
            "category":"Travel",
            "subcategory":"Hotels & Motels",
            "type":"Entertainment"
        }
    ],
    "sg:phone":"+61 3 5976 2222",
    "sg:postcode":"3931",
    "sg:province":"VIC",
    "sg:tags":[
        "accommodation"
    ],
    "wof:name":"The Bay Hotel",
    "wof:placetype":"venue"
},
  "geometry": {"coordinates":[145.03779602,-38.2181167603],"type":"Point"}
}