{
  "type": "Feature",
  "properties": {
    "iso:country":"AU",
    "sg:address":"1/ 114 Bell St",
    "sg:city":"Coburg",
    "sg:classifiers":[
        {
            "category":"Restaurant",
            "type":"Food & Drink"
        }
    ],
    "sg:phone":"+61 3 9918 8087",
    "sg:postcode":"3058",
    "sg:province":"VIC",
    "wof:name":"Alamaro Restaurant",
    "wof:placetype":"venue"
},
  "geometry": {"coordinates":[144.96543884299999,-37.7410812378],"type":"Point"}
}