{
  "type": "Feature",
  "properties": {
    "addr:full":"7 Sloans Rd Warrandyte North VIC 3113",
    "addr:housenumber":"7",
    "addr:postcode":"3113",
    "addr:street":"Sloans Rd",
    "iso:country":"AU",
    "sg:address":"7 Sloans Rd",
    "sg:city":"Warrandyte North",
    "sg:classifiers":[
        {
            "category":"Building & Trades",
            "subcategory":"Construction",
            "type":"Services"
        }
    ],
    "sg:phone":"+61 417 397 925",
    "sg:postcode":"3113",
    "sg:province":"VIC",
    "sg:tags":[
        "industrial",
        "commercial",
        "air conditioning"
    ],
    "wof:name":"Kardenair Mechanical Services Pty Ltd",
    "wof:placetype":"venue"
},
  "geometry": {"coordinates":[145.220825195,-37.7393951416],"type":"Point"}
}