{
  "type": "Feature",
  "properties": {
    "iso:country":"AU",
    "sg:address":"6 Kiah Crt",
    "sg:city":"Kingsley",
    "sg:classifiers":[
        {
            "category":"Professional",
            "subcategory":"Printing & Photocopies",
            "type":"Services"
        }
    ],
    "sg:phone":"+61 8 9409 1390",
    "sg:postcode":"6026",
    "sg:province":"WA",
    "sg:tags":[
        "photocopying"
    ],
    "wof:name":"Customised Colour Photocopying",
    "wof:placetype":"venue"
},
  "geometry": {"coordinates":[115.80596160899999,-31.8129177094],"type":"Point"}
}