{
  "type": "Feature",
  "properties": {
    "addr:full":"Level 2, 156 Collins St Melbourne VIC 3000",
    "addr:housenumber":"156",
    "addr:postcode":"3000",
    "addr:street":"Collins St",
    "iso:country":"AU",
    "sg:address":"Level 2, 156 Collins St",
    "sg:city":"Melbourne",
    "sg:classifiers":[
        {
            "category":"Social Services",
            "subcategory":"Child Care",
            "type":"Services"
        }
    ],
    "sg:phone":"+61 3 9654 6377",
    "sg:postcode":"3000",
    "sg:province":"VIC",
    "sg:tags":[
        "baby",
        "sitter"
    ],
    "wof:name":"Susan Rogan Family Care",
    "wof:placetype":"venue"
},
  "geometry": {"coordinates":[144.968826294,-37.8146781921],"type":"Point"}
}