{
  "type": "Feature",
  "properties": {
    "addr:full":"3 Margaret St Parkdale VIC 3195",
    "addr:housenumber":"3",
    "addr:postcode":"3195",
    "addr:street":"Margaret St",
    "iso:country":"AU",
    "sg:address":"3 Margaret St",
    "sg:city":"Parkdale",
    "sg:classifiers":[
        {
            "category":"Professional",
            "subcategory":"Engineering",
            "type":"Services"
        }
    ],
    "sg:phone":"+61 3 9580 1138",
    "sg:postcode":"3195",
    "sg:province":"VIC",
    "sg:tags":[
        "engineer",
        "designing"
    ],
    "wof:name":"Product And Technical Engineering New Technologies Service (P.A.T.E.N.T.S.)",
    "wof:placetype":"venue"
},
  "geometry": {"coordinates":[145.09146118199999,-37.9848518372],"type":"Point"}
}