{
  "type": "Feature",
  "properties": {
    "addr:full":"Centre 175 Maroondah Hwy Ringwood VIC 3134",
    "addr:housenumber":"175",
    "addr:postcode":"3134",
    "addr:street":"Maroondah Hwy",
    "iso:country":"AU",
    "sg:address":"Centre 175 Maroondah Hwy",
    "sg:city":"Ringwood",
    "sg:classifiers":[
        {
            "category":"Shopping",
            "subcategory":"Beauty & Cosmetics",
            "type":"Retail Goods"
        }
    ],
    "sg:phone":"+61 3 9879 1875",
    "sg:postcode":"3134",
    "sg:province":"VIC",
    "wof:name":"Red Earth",
    "wof:placetype":"venue"
},
  "geometry": {"coordinates":[145.229614258,-37.8148727417],"type":"Point"}
}