{
  "type": "Feature",
  "properties": {
    "iso:country":"AU",
    "sg:address":"43 Caple St",
    "sg:city":"Young",
    "sg:classifiers":[
        {
            "category":"Utilities",
            "subcategory":"Refuse",
            "type":"Services"
        }
    ],
    "sg:phone":"+61 2 6382 3268",
    "sg:postcode":"2594",
    "sg:province":"NSW",
    "sg:tags":[
        "disposal",
        "reduction",
        "waste"
    ],
    "wof:name":"Young Trash Paks",
    "wof:placetype":"venue"
},
  "geometry": {"coordinates":[148.289505005,-34.3181037903],"type":"Point"}
}