{
  "type": "Feature",
  "properties": {
    "iso:country":"AU",
    "sg:address":"24 Maud St",
    "sg:city":"Newstead",
    "sg:classifiers":[
        {
            "category":"Professional",
            "subcategory":"Printing & Photocopies",
            "type":"Services"
        }
    ],
    "sg:phone":"+61 7 3216 0425",
    "sg:postcode":"4006",
    "sg:province":"QLD",
    "sg:tags":[
        "textile",
        "clothing"
    ],
    "wof:name":"Sontex Sportswear",
    "wof:placetype":"venue"
},
  "geometry": {"coordinates":[153.04495239299999,-27.4448432922],"type":"Point"}
}