{
  "type": "Feature",
  "properties": {
    "addr:full":"45 South Western Hwy Waroona WA 6215",
    "addr:housenumber":"45",
    "addr:postcode":"6215",
    "addr:street":"South Western Hwy",
    "iso:country":"AU",
    "sg:address":"45 South Western Hwy",
    "sg:city":"Waroona",
    "sg:classifiers":[
        {
            "category":"Retail",
            "subcategory":"Veterinary Services",
            "type":"Services"
        }
    ],
    "sg:phone":"+61 8 9733 1356",
    "sg:postcode":"6215",
    "sg:province":"WA",
    "sg:tags":[
        "surgeon"
    ],
    "wof:name":"Waroona Veterinary Clinic",
    "wof:placetype":"venue"
},
  "geometry": {"coordinates":[115.920609,-32.841587],"type":"Point"}
}