{
  "type": "Feature",
  "properties": {
    "iso:country":"AU",
    "sg:address":"3 Wallsend Rd",
    "sg:city":"Sandgate",
    "sg:classifiers":[
        {
            "category":"Donuts",
            "subcategory":"None",
            "type":"Food & Drink"
        }
    ],
    "sg:phone":"+61 2 4960 0030",
    "sg:postcode":"2304",
    "sg:province":"NSW",
    "sg:tags":[
        "die",
        "engraver",
        "sinker"
    ],
    "wof:name":"Hi-Impact Signs",
    "wof:placetype":"venue"
},
  "geometry": {"coordinates":[151.70993042000001,-32.8709793091],"type":"Point"}
}