{
  "type": "Feature",
  "properties": {
    "iso:country":"AU",
    "sg:address":"22 - 24 The Concourse",
    "sg:city":"Cowes",
    "sg:classifiers":[
        {
            "category":"Home & Garden",
            "subcategory":"Carpets & Floor Coverings",
            "type":"Retail Goods"
        }
    ],
    "sg:phone":"+61 3 5952 1488",
    "sg:postcode":"3922",
    "sg:province":"VIC",
    "sg:tags":[
        "mattress"
    ],
    "wof:name":"South Coast Furnishings",
    "wof:placetype":"venue"
},
  "geometry": {"coordinates":[145.24995422399999,-38.4575157166],"type":"Point"}
}