{
  "type": "Feature",
  "properties": {
    "addr:full":"6 Hyam St Hamilton Hill WA 6163",
    "addr:housenumber":"6",
    "addr:postcode":"6163",
    "addr:street":"Hyam St",
    "iso:country":"AU",
    "sg:address":"6 Hyam St",
    "sg:city":"Hamilton Hill",
    "sg:classifiers":[
        {
            "category":"Home & Garden",
            "subcategory":"Carpets & Floor Coverings",
            "type":"Retail Goods"
        }
    ],
    "sg:phone":"+61 8 9337 5980",
    "sg:postcode":"6163",
    "sg:province":"WA",
    "wof:name":"Sciascia Tony",
    "wof:placetype":"venue"
},
  "geometry": {"coordinates":[115.78421,-32.083035],"type":"Point"}
}