{
  "type": "Feature",
  "properties": {
    "iso:country":"AU",
    "sg:address":"30 Malbon St",
    "sg:city":"Bungendore",
    "sg:classifiers":[
        {
            "category":"Real Estate",
            "subcategory":"Real Estate Agent",
            "type":"Services"
        }
    ],
    "sg:phone":"+61 2 6238 1106",
    "sg:postcode":"2621",
    "sg:province":"ACT",
    "wof:name":"Horizon Real Estate",
    "wof:placetype":"venue"
},
  "geometry": {"coordinates":[149.43406677199999,-35.2524909973],"type":"Point"}
}