{
  "type": "Feature",
  "properties": {
    "iso:country":"AU",
    "sg:address":"Millers Rd",
    "sg:city":"Mt Blowhard",
    "sg:classifiers":[
        {
            "category":"Education",
            "subcategory":"School",
            "type":"Public Place"
        }
    ],
    "sg:phone":"+61 3 5334 6354",
    "sg:postcode":"3352",
    "sg:province":"VIC",
    "sg:tags":[
        "state",
        "except",
        "nsw"
    ],
    "wof:name":"Mt Blowhard Primary School",
    "wof:placetype":"venue"
},
  "geometry": {"coordinates":[143.802444,-37.430843],"type":"Point"}
}