{
  "type": "Feature",
  "properties": {
    "addr:full":"Cnr Crockford St & Bellare Ave Northgate QLD 4013",
    "addr:postcode":"4013",
    "addr:street":"Cnr Crockford St & Bellare Ave",
    "iso:country":"AU",
    "sg:address":"Cnr Crockford St & Bellare Ave",
    "sg:city":"Northgate",
    "sg:classifiers":[
        {
            "category":"Freight",
            "type":"Transportation"
        }
    ],
    "sg:phone":"+61 1300 651 700",
    "sg:postcode":"4013",
    "sg:province":"QLD",
    "sg:tags":[
        "cargo",
        "container"
    ],
    "wof:name":"Royal Wolf",
    "wof:placetype":"venue"
},
  "geometry": {"coordinates":[153.07824707,-27.3872203827],"type":"Point"}
}