{
  "type": "Feature",
  "properties": {
    "addr:full":"PO Box 3669 North Mackay QLD 4740",
    "addr:postcode":"4740",
    "iso:country":"AU",
    "sg:address":"PO Box 3669",
    "sg:city":"North Mackay",
    "sg:classifiers":[
        {
            "category":"Professional",
            "subcategory":"Engineering",
            "type":"Services"
        }
    ],
    "sg:phone":"+61 7 4914 2555",
    "sg:postcode":"4740",
    "sg:province":"QLD",
    "sg:tags":[
        "consulting",
        "engineer"
    ],
    "wof:name":"Cell Consultancy Pty Ltd",
    "wof:placetype":"venue"
},
  "geometry": {"coordinates":[149.18261699999999,-21.123739],"type":"Point"}
}