{
  "type": "Feature",
  "properties": {
    "addr:full":"PO Box 3035 Kirrawee NSW 2232",
    "addr:postcode":"2232",
    "iso:country":"AU",
    "sg:address":"PO Box 3035",
    "sg:city":"Kirrawee",
    "sg:classifiers":[
        {
            "category":"Building & Trades",
            "subcategory":"Construction",
            "type":"Services"
        }
    ],
    "sg:phone":"+61 417 920 310",
    "sg:postcode":"2232",
    "sg:province":"NSW",
    "sg:tags":[
        "brick",
        "paving"
    ],
    "wof:name":"Bedrock Landscapes",
    "wof:placetype":"venue"
},
  "geometry": {"coordinates":[151.07110595699999,-34.0342292786],"type":"Point"}
}