{
  "type": "Feature",
  "properties": {
    "addr:full":"23 Tedder Ave Main Beach QLD 4217",
    "addr:housenumber":"23",
    "addr:postcode":"4217",
    "addr:street":"Tedder Ave",
    "iso:country":"AU",
    "sg:address":"23 Tedder Ave",
    "sg:city":"Main Beach",
    "sg:classifiers":[
        {
            "category":"Real Estate",
            "subcategory":"Real Estate Agent",
            "type":"Services"
        }
    ],
    "sg:phone":"+61 7 5526 4555",
    "sg:postcode":"4217",
    "sg:province":"QLD",
    "wof:name":"Ray White Surfers Paradise At Main Beach",
    "wof:placetype":"venue"
},
  "geometry": {"coordinates":[153.425125122,-27.979057312],"type":"Point"}
}