{
  "type": "Feature",
  "properties": {
    "iso:country":"AU",
    "sg:address":"Level 1/ 2 Morecroft Pl",
    "sg:city":"Lilydale",
    "sg:classifiers":[
        {
            "category":"Real Estate",
            "subcategory":"Surveying",
            "type":"Services"
        }
    ],
    "sg:phone":"+61 3 9739 6055",
    "sg:postcode":"3140",
    "sg:province":"VIC",
    "sg:tags":[
        "building",
        "surveyor"
    ],
    "wof:name":"Samuel Perna & Assocs",
    "wof:placetype":"venue"
},
  "geometry": {"coordinates":[145.35420227,-37.7568778992],"type":"Point"}
}