{
  "type": "Feature",
  "properties": {
    "iso:country":"AU",
    "sg:address":"7 Glencairn Ave",
    "sg:city":"Camberwell",
    "sg:classifiers":[
        {
            "category":"Professional",
            "subcategory":"Employment Agencies",
            "type":"Services"
        }
    ],
    "sg:phone":"+61 413 006 066",
    "sg:postcode":"3124",
    "sg:province":"VIC",
    "sg:tags":[
        "provider",
        "internet"
    ],
    "wof:name":"Swimnet Pty Ltd",
    "wof:placetype":"venue"
},
  "geometry": {"coordinates":[145.08076477,-37.8479499817],"type":"Point"}
}