{
  "type": "Feature",
  "properties": {
    "iso:country":"AU",
    "sg:address":"Gorman House Art Centre currong St",
    "sg:city":"Ainslie",
    "sg:classifiers":[
        {
            "category":"Education",
            "subcategory":"University",
            "type":"Public Place"
        }
    ],
    "sg:phone":"+61 2 6262 8035",
    "sg:postcode":"2602",
    "sg:province":"ACT",
    "sg:tags":[
        "educational",
        "organisation",
        "cultural"
    ],
    "wof:name":"Embroiderers' Guild ACT Inc.",
    "wof:placetype":"venue"
},
  "geometry": {"coordinates":[149.13601684599999,-35.2767219543],"type":"Point"}
}