{
  "type": "Feature",
  "properties": {
    "addr:full":"101 Therry St Melbourne VIC 3000",
    "addr:housenumber":"101",
    "addr:postcode":"3000",
    "addr:street":"Therry St",
    "iso:country":"AU",
    "sg:address":"101 Therry St",
    "sg:city":"Melbourne",
    "sg:classifiers":[
        {
            "category":"Shopping",
            "subcategory":"Clothing, Apparel, & Fashions",
            "type":"Retail Goods"
        }
    ],
    "sg:phone":"+61 3 9326 9971",
    "sg:postcode":"3000",
    "sg:province":"VIC",
    "sg:tags":[
        "lady",
        "wear"
    ],
    "wof:name":"Jackie Brown",
    "wof:placetype":"venue"
},
  "geometry": {"coordinates":[144.95921325699999,-37.8074226379],"type":"Point"}
}