{
  "type": "Feature",
  "properties": {
    "addr:full":"Unit 2, 13 Cnr Flinders & Edward St Wollongong NSW 2500",
    "addr:housenumber":"13",
    "addr:postcode":"2500",
    "addr:street":"Cnr Flinders;Edward St",
    "iso:country":"AU",
    "sg:address":"Unit 2, 13 Cnr Flinders & Edward St",
    "sg:city":"Wollongong",
    "sg:classifiers":[
        {
            "category":"Building & Trades",
            "subcategory":"Construction",
            "type":"Services"
        }
    ],
    "sg:phone":"+61 2 4228 0376",
    "sg:postcode":"2500",
    "sg:province":"NSW",
    "sg:tags":[
        "window",
        "tinting"
    ],
    "wof:name":"Tint.a.Car Solace",
    "wof:placetype":"venue"
},
  "geometry": {"coordinates":[150.892501831,-34.4113616943],"type":"Point"}
}