{
  "type": "Feature",
  "properties": {
    "addr:full":"Kennedy Hwy Tolga QLD 4882",
    "addr:postcode":"4882",
    "addr:street":"Kennedy Hwy",
    "iso:country":"AU",
    "sg:address":"Kennedy Hwy",
    "sg:city":"Tolga",
    "sg:classifiers":[
        {
            "category":"Communications",
            "subcategory":"News Services",
            "type":"Services"
        }
    ],
    "sg:phone":"+61 7 4095 4488",
    "sg:postcode":"4882",
    "sg:province":"QLD",
    "sg:tags":[
        "information",
        "tourist",
        "attractions"
    ],
    "wof:name":"Tolga Woodworks Gallery & Cafe",
    "wof:placetype":"venue"
},
  "geometry": {"coordinates":[145.466873169,-17.1869392395],"type":"Point"}
}