{
  "type": "Feature",
  "properties": {
    "addr:full":"75 Lascelles St Hopetoun VIC 3396",
    "addr:housenumber":"75",
    "addr:postcode":"3396",
    "addr:street":"Lascelles St",
    "iso:country":"AU",
    "sg:address":"75 Lascelles St",
    "sg:city":"Hopetoun",
    "sg:classifiers":[
        {
            "category":"Education",
            "subcategory":"University",
            "type":"Public Place"
        }
    ],
    "sg:phone":"+61 3 5083 3001",
    "sg:postcode":"3396",
    "sg:province":"VIC",
    "sg:tags":[
        "educational",
        "organisation",
        "cultural"
    ],
    "wof:name":"Gateway BEET",
    "wof:placetype":"venue"
},
  "geometry": {"coordinates":[142.364868164,-35.7276115417],"type":"Point"}
}