{
  "type": "Feature",
  "properties": {
    "iso:country":"AU",
    "sg:address":"15 Station St",
    "sg:city":"Kew East",
    "sg:classifiers":[
        {
            "category":"Wholesale",
            "subcategory":"Furniture",
            "type":"Manufacturing & Wholesale Goods"
        }
    ],
    "sg:phone":"+61 3 9859 7195",
    "sg:postcode":"3102",
    "sg:province":"VIC",
    "sg:tags":[
        "wholesaler",
        "mfrs"
    ],
    "wof:name":"Ercol Furniture (U.K.)",
    "wof:placetype":"venue"
},
  "geometry": {"coordinates":[145.05372619600001,-37.7982368469],"type":"Point"}
}