{
  "type": "Feature",
  "properties": {
    "addr:full":"Kent St Maryborough QLD 4650",
    "addr:postcode":"4650",
    "addr:street":"Kent St",
    "iso:country":"AU",
    "sg:address":"Kent St",
    "sg:city":"Maryborough",
    "sg:classifiers":[
        {
            "category":"Professional",
            "subcategory":"Management & Consulting",
            "type":"Services"
        }
    ],
    "sg:phone":"+61 7 4122 3756",
    "sg:postcode":"4650",
    "sg:province":"QLD",
    "sg:tags":[
        "consultant",
        "educational"
    ],
    "wof:name":"Learning Network Qld",
    "wof:placetype":"venue"
},
  "geometry": {"coordinates":[152.694839,-25.532106],"type":"Point"}
}