{
  "type": "Feature",
  "properties": {
    "iso:country":"AU",
    "sg:address":"PO Box 218",
    "sg:city":"Woonona",
    "sg:classifiers":[
        {
            "category":"Manufacturing",
            "subcategory":"Tools & Machinery",
            "type":"Manufacturing & Wholesale Goods"
        }
    ],
    "sg:phone":"+61 2 4283 8879",
    "sg:postcode":"2517",
    "sg:province":"NSW",
    "wof:name":"Taske Tools",
    "wof:placetype":"venue"
},
  "geometry": {"coordinates":[150.907135,-34.340481],"type":"Point"}
}