{
  "type": "Feature",
  "properties": {
    "addr:full":"1082 Doncaster Rd Doncaster East VIC 3109",
    "addr:housenumber":"1082",
    "addr:postcode":"3109",
    "addr:street":"Doncaster Rd",
    "iso:country":"AU",
    "sg:address":"1082 Doncaster Rd",
    "sg:city":"Doncaster East",
    "sg:classifiers":[
        {
            "category":"Retail",
            "subcategory":"Auto Rental",
            "type":"Services"
        }
    ],
    "sg:phone":"+61 3 9842 6302",
    "sg:postcode":"3109",
    "sg:province":"VIC",
    "sg:tags":[
        "chauffeur",
        "car",
        "hire",
        "driven",
        "limousine"
    ],
    "wof:name":"Limousines Of Victoria",
    "wof:placetype":"venue"
},
  "geometry": {"coordinates":[145.16810607900001,-37.7900543213],"type":"Point"}
}