{
  "type": "Feature",
  "properties": {
    "addr:full":"Cnr Pearce St & Thomas Mitchell Drive Wodonga VIC 3689",
    "addr:postcode":"3689",
    "addr:street":"Pearce St & Thomas Mitchell Drive",
    "iso:country":"AU",
    "sg:address":"Cnr Pearce St & Thomas Mitchell Drive",
    "sg:city":"Wodonga",
    "sg:classifiers":[
        {
            "category":"Utilities",
            "subcategory":"Natural Gas",
            "type":"Services"
        }
    ],
    "sg:phone":"+61 2 6049 1400",
    "sg:postcode":"3689",
    "sg:province":"VIC",
    "sg:tags":[
        "supplier"
    ],
    "wof:name":"Elgas Limited",
    "wof:placetype":"venue"
},
  "geometry": {"coordinates":[146.90425099999999,-36.134281],"type":"Point"}
}