{
  "type": "Feature",
  "properties": {
    "addr:full":"Unit 4/ 173 Camboon Rd Malaga WA 6090",
    "addr:housenumber":"/ 173",
    "addr:postcode":"6090",
    "addr:street":"Camboon Rd",
    "iso:country":"AU",
    "sg:address":"Unit 4/ 173 Camboon Rd",
    "sg:city":"Malaga",
    "sg:classifiers":[
        {
            "category":"Retail",
            "subcategory":"Auto Repair",
            "type":"Services"
        }
    ],
    "sg:phone":"+61 8 9248 7027",
    "sg:postcode":"6090",
    "sg:province":"WA",
    "sg:tags":[
        "repairer",
        "motor",
        "engineer"
    ],
    "wof:name":"5 Star Auto Service Centre",
    "wof:placetype":"venue"
},
  "geometry": {"coordinates":[115.887649536,-31.8582000732],"type":"Point"}
}