{
  "type": "Feature",
  "properties": {
    "addr:full":"Unit 2 Lot 30 Turton St East Maitland NSW 2323",
    "addr:housenumber":"lot 30",
    "addr:postcode":"2323",
    "addr:street":"Turton St",
    "iso:country":"AU",
    "sg:address":"Unit 2 Lot 30 Turton St",
    "sg:city":"East Maitland",
    "sg:classifiers":[
        {
            "category":"Manufacturing",
            "subcategory":"Retail Goods",
            "type":"Manufacturing & Wholesale Goods"
        }
    ],
    "sg:phone":"+61 2 4934 5740",
    "sg:postcode":"2323",
    "sg:province":"NSW",
    "sg:tags":[
        "merchant",
        "pump",
        "mfrs"
    ],
    "wof:name":"Monsoon Irrigators Aust Pty Ltd",
    "wof:placetype":"venue"
},
  "geometry": {"coordinates":[151.60002136200001,-32.7565917969],"type":"Point"}
}