{
  "type": "Feature",
  "properties": {
    "iso:country":"AU",
    "sg:address":"Shop 23, Piazza on the Blvd 3221 Gold Coast Hwy",
    "sg:city":"Surfers Paradise",
    "sg:classifiers":[
        {
            "category":"Fast Food",
            "type":"Food & Drink"
        }
    ],
    "sg:phone":"+61 7 5504 5236",
    "sg:postcode":"4217",
    "sg:province":"QLD",
    "sg:tags":[
        "away",
        "take"
    ],
    "wof:name":"La Porchetta On the Piazza",
    "wof:placetype":"venue"
},
  "geometry": {"coordinates":[153.42953491200001,-28.0110912323],"type":"Point"}
}