{
  "type": "Feature",
  "properties": {
    "addr:full":"80-82 Toole St Hopetoun VIC 3396",
    "addr:housenumber":"80-82",
    "addr:postcode":"3396",
    "addr:street":"Toole St",
    "iso:country":"AU",
    "sg:address":"80-82 Toole St",
    "sg:city":"Hopetoun",
    "sg:classifiers":[
        {
            "category":"Manufacturing",
            "subcategory":"Chemicals & Compounds",
            "type":"Manufacturing & Wholesale Goods"
        }
    ],
    "sg:phone":"+61 3 5083 3344",
    "sg:postcode":"3396",
    "sg:province":"VIC",
    "sg:tags":[
        "agricultural"
    ],
    "wof:name":"I.A.M.A.",
    "wof:placetype":"venue"
},
  "geometry": {"coordinates":[142.364303589,-35.7287101746],"type":"Point"}
}