{
  "type": "Feature",
  "properties": {
    "addr:full":"39 Glenelg Ave Wembley Downs WA 6019",
    "addr:housenumber":"39",
    "addr:postcode":"6019",
    "addr:street":"Glenelg Ave Wembley Downs",
    "iso:country":"AU",
    "sg:address":"39 Glenelg Ave",
    "sg:city":"Wembley Downs",
    "sg:classifiers":[
        {
            "category":"Manufacturing",
            "subcategory":"Jewelry",
            "type":"Manufacturing & Wholesale Goods"
        }
    ],
    "sg:phone":"+61 8 9446 2173",
    "sg:postcode":"6019",
    "sg:province":"WA",
    "sg:tags":[
        "mfrg",
        "jeweller"
    ],
    "wof:name":"Hypa Jewellery",
    "wof:placetype":"venue"
},
  "geometry": {"coordinates":[115.778266907,-31.9136352539],"type":"Point"}
}