{
  "type": "Feature",
  "properties": {
    "addr:full":"13 Boundary Rd Kincumber NSW 2251",
    "addr:housenumber":"13",
    "addr:postcode":"2251",
    "addr:street":"Boundary Rd",
    "iso:country":"AU",
    "sg:address":"13 Boundary Rd",
    "sg:city":"Kincumber",
    "sg:classifiers":[
        {
            "category":"Health Services",
            "subcategory":"Medical Lab",
            "type":"Services"
        }
    ],
    "sg:phone":"+61 2 4368 1457",
    "sg:postcode":"2251",
    "sg:province":"NSW",
    "sg:tags":[
        "laboratory",
        "dental"
    ],
    "wof:name":"Kenmai Dental Laboratory",
    "wof:placetype":"venue"
},
  "geometry": {"coordinates":[151.40521240199999,-33.4744682312],"type":"Point"}
}