{
  "type": "Feature",
  "properties": {
    "iso:country":"AU",
    "sg:address":"16 Forge St",
    "sg:city":"East Wagga Wagga",
    "sg:classifiers":[
        {
            "category":"Professional",
            "type":"Services"
        }
    ],
    "sg:phone":"+61 2 6921 2577",
    "sg:postcode":"2650",
    "sg:province":"NSW",
    "sg:tags":[
        "transport"
    ],
    "wof:name":"Winnel Transport Pty Ltd",
    "wof:placetype":"venue"
},
  "geometry": {"coordinates":[147.393768311,-35.1239051819],"type":"Point"}
}