{
  "type": "Feature",
  "properties": {
    "addr:full":"6 Carpenter St Lakes Entrance VIC 3909",
    "addr:housenumber":"6",
    "addr:postcode":"3909",
    "addr:street":"Carpenter St",
    "iso:country":"AU",
    "sg:address":"6 Carpenter St",
    "sg:city":"Lakes Entrance",
    "sg:classifiers":[
        {
            "category":"Shopping",
            "subcategory":"Stationery & Office Supplies",
            "type":"Retail Goods"
        }
    ],
    "sg:phone":"+61 3 5155 1850",
    "sg:postcode":"3909",
    "sg:province":"VIC",
    "sg:tags":[
        "equipment",
        "facsimile"
    ],
    "wof:name":"Loukes Electronics",
    "wof:placetype":"venue"
},
  "geometry": {"coordinates":[147.991088867,-37.8793792725],"type":"Point"}
}