{
  "type": "Feature",
  "properties": {
    "addr:full":"3/ 20 Ace Crs Tuggerah NSW 2259",
    "addr:housenumber":"/ 20",
    "addr:postcode":"2259",
    "addr:street":"Ace Crs",
    "iso:country":"AU",
    "sg:address":"3/ 20 Ace Crs",
    "sg:city":"Tuggerah",
    "sg:classifiers":[
        {
            "category":"Retail",
            "subcategory":"Auto Repair",
            "type":"Services"
        }
    ],
    "sg:phone":"+61 2 4353 2676",
    "sg:postcode":"2259",
    "sg:province":"NSW",
    "sg:tags":[
        "repairer",
        "motor",
        "engineer"
    ],
    "wof:name":"Wyong Exhaust & Mechanical Services",
    "wof:placetype":"venue"
},
  "geometry": {"coordinates":[151.420410156,-33.3050003052],"type":"Point"}
}