{
  "type": "Feature",
  "properties": {
    "addr:full":"St Kilda Sea Baths, 10-18 Jacka Blvd St Kilda VIC 3182",
    "addr:housenumber":"10-18",
    "addr:postcode":"3182",
    "addr:street":"Jacka Blvd",
    "iso:country":"AU",
    "sg:address":"St Kilda Sea Baths, 10-18 Jacka Blvd",
    "sg:city":"St Kilda",
    "sg:classifiers":[
        {
            "category":"Sports & Exercise",
            "subcategory":"Gym",
            "type":"Entertainment"
        }
    ],
    "sg:phone":"+61 3 9525 4888",
    "sg:postcode":"3182",
    "sg:province":"VIC",
    "sg:tags":[
        "pilate",
        "method"
    ],
    "wof:name":"Breathing Space Studio",
    "wof:placetype":"venue"
},
  "geometry": {"coordinates":[144.97381591800001,-37.8663711548],"type":"Point"}
}