{
  "type": "Feature",
  "properties": {
    "iso:country":"AU",
    "sg:address":"28 Sammut St",
    "sg:city":"Smithfield",
    "sg:classifiers":[
        {
            "category":"Retail",
            "subcategory":"Storage",
            "type":"Services"
        }
    ],
    "sg:phone":"+61 2 9725 5505",
    "sg:postcode":"2164",
    "sg:province":"NSW",
    "sg:tags":[
        "removal",
        "furniture"
    ],
    "wof:name":"Pilot Relocation",
    "wof:placetype":"venue"
},
  "geometry": {"coordinates":[150.933670044,-33.8400688171],"type":"Point"}
}