{
  "type": "Feature",
  "properties": {
    "addr:full":"66 Gilbert Rd Windsor QLD 4030",
    "addr:housenumber":"66",
    "addr:postcode":"4030",
    "addr:street":"Gilbert Rd",
    "iso:country":"AU",
    "sg:address":"66 Gilbert Rd",
    "sg:city":"Windsor",
    "sg:classifiers":[
        {
            "category":"Retail",
            "subcategory":"Driving School",
            "type":"Services"
        }
    ],
    "sg:phone":"+61 7 3356 9651",
    "sg:postcode":"4030",
    "sg:province":"QLD",
    "wof:name":"Bob Claytons Driving School",
    "wof:placetype":"venue"
},
  "geometry": {"coordinates":[153.02409399999999,-27.424543],"type":"Point"}
}