{
  "type": "Feature",
  "properties": {
    "addr:full":"174 Allambie Rd Allambie Heights NSW 2100",
    "addr:housenumber":"174",
    "addr:postcode":"2100",
    "addr:street":"Allambie Rd",
    "iso:country":"AU",
    "sg:address":"174 Allambie Rd",
    "sg:city":"Allambie Heights",
    "sg:classifiers":[
        {
            "category":"Home & Garden",
            "subcategory":"Building Materials",
            "type":"Retail Goods"
        }
    ],
    "sg:phone":"+61 2 9452 4044",
    "sg:postcode":"2100",
    "sg:province":"NSW",
    "sg:tags":[
        "retaining",
        "wall"
    ],
    "wof:name":"Teluta Pty Ltd",
    "wof:placetype":"venue"
},
  "geometry": {"coordinates":[151.24659729000001,-33.7615356445],"type":"Point"}
}