{
  "type": "Feature",
  "properties": {
    "addr:full":"lvl 28 680 George St Sydney NSW 2000",
    "addr:housenumber":"680",
    "addr:postcode":"2000",
    "addr:street":"George St",
    "iso:country":"AU",
    "sg:address":"lvl 28 680 George St",
    "sg:city":"Sydney",
    "sg:classifiers":[
        {
            "category":"Travel",
            "subcategory":"Hotels & Motels",
            "type":"Entertainment"
        }
    ],
    "sg:phone":"+61 2 8263 5143",
    "sg:postcode":"2000",
    "sg:province":"NSW",
    "sg:tags":[
        "accommodation"
    ],
    "wof:name":"Fairview Travel Pty Ltd",
    "wof:placetype":"venue"
},
  "geometry": {"coordinates":[151.206008911,-33.8774833679],"type":"Point"}
}