{
  "type": "Feature",
  "properties": {
    "iso:country":"AU",
    "sg:address":"8 Carrington Rd",
    "sg:city":"Toowoomba",
    "sg:classifiers":[
        {
            "category":"Shopping",
            "subcategory":"Clothing, Apparel, & Fashions",
            "type":"Retail Goods"
        }
    ],
    "sg:phone":"+61 7 4634 4336",
    "sg:postcode":"4350",
    "sg:province":"QLD",
    "sg:tags":[
        "menswear"
    ],
    "wof:name":"R.M. Williams",
    "wof:placetype":"venue"
},
  "geometry": {"coordinates":[151.878693,-27.542345],"type":"Point"}
}