{
  "type": "Feature",
  "properties": {
    "addr:full":"694 Military Rd Mosman NSW 2088",
    "addr:housenumber":"694",
    "addr:postcode":"2088",
    "addr:street":"Military Rd",
    "iso:country":"AU",
    "sg:address":"694 Military Rd",
    "sg:city":"Mosman",
    "sg:classifiers":[
        {
            "category":"Personal",
            "subcategory":"Beauty Salon",
            "type":"Services"
        }
    ],
    "sg:phone":"+61 2 9960 4051",
    "sg:postcode":"2088",
    "sg:province":"NSW",
    "wof:name":"Ella Bache Mosman",
    "wof:placetype":"venue"
},
  "geometry": {"coordinates":[151.24206543,-33.824886322],"type":"Point"}
}