{
  "type": "Feature",
  "properties": {
    "addr:full":"Virginia Palms Resort, Cnr Sandgate & Zillmere Rds Boondall QLD 4034",
    "addr:postcode":"4034",
    "addr:street":"Cnr Sandgate & Zillmere Rds",
    "iso:country":"AU",
    "sg:address":"Virginia Palms Resort, Cnr Sandgate & Zillmere Rds",
    "sg:city":"Boondall",
    "sg:classifiers":[
        {
            "category":"Professional",
            "subcategory":"Art Services",
            "type":"Services"
        }
    ],
    "sg:phone":"+61 418 928 456",
    "sg:postcode":"4034",
    "sg:province":"QLD",
    "sg:tags":[
        "decorator",
        "painter"
    ],
    "wof:name":"Colourfic Painting Contractors",
    "wof:placetype":"venue"
},
  "geometry": {"coordinates":[153.06057699999999,-27.35088],"type":"Point"}
}