{
  "type": "Feature",
  "properties": {
    "iso:country":"AU",
    "sg:address":"10 Russell St",
    "sg:city":"Vaucluse",
    "sg:classifiers":[
        {
            "category":"Personal",
            "type":"Services"
        }
    ],
    "sg:phone":"+61 2 9337 1478",
    "sg:postcode":"2030",
    "sg:province":"NSW",
    "sg:tags":[
        "career",
        "counselling"
    ],
    "wof:name":"Humphrey - Reeve H J",
    "wof:placetype":"venue"
},
  "geometry": {"coordinates":[151.28251648,-33.8488960266],"type":"Point"}
}