{
  "type": "Feature",
  "properties": {
    "addr:full":"New Park Shopping Centre 3A/ 64 Marangaroo Drv Girrawheen WA 6064",
    "addr:housenumber":"3a / 64",
    "addr:postcode":"6064",
    "addr:street":"Marangaroo Drv",
    "iso:country":"AU",
    "sg:address":"New Park Shopping Centre 3A/ 64 Marangaroo Drv",
    "sg:city":"Girrawheen",
    "sg:classifiers":[
        {
            "category":"Government",
            "subcategory":"Post Office",
            "type":"Public Place"
        }
    ],
    "sg:phone":"+61 8 9342 3079",
    "sg:postcode":"6064",
    "sg:province":"WA",
    "sg:tags":[
        "postal"
    ],
    "wof:name":"Australia Post",
    "wof:placetype":"venue"
},
  "geometry": {"coordinates":[115.831481934,-31.8418102264],"type":"Point"}
}