{
  "type": "Feature",
  "properties": {
    "addr:full":"44 Crocus St Inala QLD 4077",
    "addr:housenumber":"44",
    "addr:postcode":"4077",
    "addr:street":"Crocus St",
    "iso:country":"AU",
    "sg:address":"44 Crocus St",
    "sg:city":"Inala",
    "sg:classifiers":[
        {
            "category":"Health Services",
            "subcategory":"Health Practitioner",
            "type":"Services"
        }
    ],
    "sg:phone":"+61 7 3879 1062",
    "sg:postcode":"4077",
    "sg:province":"QLD",
    "sg:tags":[
        "bowen",
        "therapy"
    ],
    "wof:name":"Bowen Life",
    "wof:placetype":"venue"
},
  "geometry": {"coordinates":[152.96736145,-27.5897045135],"type":"Point"}
}