{
  "type": "Feature",
  "properties": {
    "addr:full":"62 Wattlebird Drv Twin Waters QLD 4564",
    "addr:housenumber":"62",
    "addr:postcode":"4564",
    "addr:street":"Wattlebird Drv Twin",
    "iso:country":"AU",
    "sg:address":"62 Wattlebird Drv",
    "sg:city":"Twin Waters",
    "sg:classifiers":[
        {
            "category":"Shopping",
            "type":"Retail Goods"
        }
    ],
    "sg:phone":"+61 7 5448 8004",
    "sg:postcode":"4564",
    "sg:province":"QLD",
    "sg:tags":[
        "new age",
        "product"
    ],
    "wof:name":"Amanda Woods",
    "wof:placetype":"venue"
},
  "geometry": {"coordinates":[153.07728576700001,-26.6281299591],"type":"Point"}
}