{
  "type": "Feature",
  "properties": {
    "addr:full":"2378 Gold Coast Hwy Mermaid Beach QLD 4218",
    "addr:housenumber":"2378",
    "addr:postcode":"4218",
    "addr:street":"Gold Coast Hwy",
    "iso:country":"AU",
    "sg:address":"2378 Gold Coast Hwy",
    "sg:city":"Mermaid Beach",
    "sg:classifiers":[
        {
            "category":"Personal",
            "subcategory":"Beauty Salon",
            "type":"Services"
        }
    ],
    "sg:phone":"+61 7 5572 8711",
    "sg:postcode":"4218",
    "sg:province":"QLD",
    "sg:tags":[
        "hairdresser"
    ],
    "wof:name":"Gables Hair Design",
    "wof:placetype":"venue"
},
  "geometry": {"coordinates":[153.43586730999999,-28.0495834351],"type":"Point"}
}