{
  "type": "Feature",
  "properties": {
    "addr:full":"\"Cunningdroo\" Tarcutta Rd Via Wagga Wagga NSW 2650",
    "addr:postcode":"2650",
    "addr:street":"Tarcutta Rd Via Wagga Wagga",
    "iso:country":"AU",
    "sg:address":"\"Cunningdroo\" Tarcutta Rd Via",
    "sg:city":"Wagga Wagga",
    "sg:classifiers":[
        {
            "category":"Building & Trades",
            "subcategory":"Landscaping Services",
            "type":"Services"
        }
    ],
    "sg:phone":"+61 2 6922 7218",
    "sg:postcode":"2650",
    "sg:province":"NSW",
    "sg:tags":[
        "grazier"
    ],
    "wof:name":"Mutton B E & Tony",
    "wof:placetype":"venue"
},
  "geometry": {"coordinates":[147.375076294,-35.1133270264],"type":"Point"}
}