{
  "type": "Feature",
  "properties": {
    "addr:full":"Grenfell Rd Young NSW 2594",
    "addr:postcode":"2594",
    "addr:street":"Grenfell Rd",
    "iso:country":"AU",
    "sg:address":"Grenfell Rd",
    "sg:city":"Young",
    "sg:classifiers":[
        {
            "category":"Farming",
            "subcategory":"Farm & Veterinary Services",
            "type":"Manufacturing & Wholesale Goods"
        }
    ],
    "sg:phone":"+61 2 6382 1038",
    "sg:postcode":"2594",
    "sg:province":"NSW",
    "sg:tags":[
        "drying",
        "seed",
        "cleaning",
        "grading"
    ],
    "wof:name":"Universal Seeds (Aust)",
    "wof:placetype":"venue"
},
  "geometry": {"coordinates":[148.29434204099999,-34.3139686584],"type":"Point"}
}