{
  "type": "Feature",
  "properties": {
    "iso:country":"AU",
    "sg:address":"Tuggerah Hall Anzac Rd",
    "sg:city":"Tuggerah",
    "sg:classifiers":[
        {
            "category":"Recreation",
            "type":"Entertainment"
        }
    ],
    "sg:phone":"+61 2 4392 0924",
    "sg:postcode":"2259",
    "sg:province":"NSW",
    "sg:tags":[
        "children's",
        "play",
        "programme"
    ],
    "wof:name":"GymbaROO",
    "wof:placetype":"venue"
},
  "geometry": {"coordinates":[151.417892456,-33.3069572449],"type":"Point"}
}