{
  "type": "Feature",
  "properties": {
    "addr:full":"Hollands Creek Rd Cudlee Creek SA 5232",
    "addr:postcode":"5232",
    "addr:street":"Hollands Creek Rd",
    "iso:country":"AU",
    "sg:address":"Hollands Creek Rd",
    "sg:city":"Cudlee Creek",
    "sg:classifiers":[
        {
            "category":"Sports & Exercise",
            "subcategory":"Golf",
            "type":"Entertainment"
        }
    ],
    "sg:phone":"+61 8 8389 2317",
    "sg:postcode":"5232",
    "sg:province":"SA",
    "sg:tags":[
        "club"
    ],
    "wof:name":"Cudlee Creek Golf Course",
    "wof:placetype":"venue"
},
  "geometry": {"coordinates":[138.82168579099999,-34.8452339172],"type":"Point"}
}