{
  "type": "Feature",
  "properties": {
    "addr:full":"Cnr Mains & Birkdale Rds Wellington Point QLD 4160",
    "addr:postcode":"4160",
    "addr:street":"Cnr",
    "iso:country":"AU",
    "sg:address":"Cnr Mains & Birkdale Rds",
    "sg:city":"Wellington Point",
    "sg:classifiers":[
        {
            "category":"Autos & Motor Vehicles",
            "subcategory":"Fuel & Gas Station",
            "type":"Retail Goods"
        }
    ],
    "sg:phone":"+61 7 3822 8288",
    "sg:postcode":"4160",
    "sg:province":"QLD",
    "wof:name":"BP Wellington Point",
    "wof:placetype":"venue"
},
  "geometry": {"coordinates":[153.23283386200001,-27.4882030487],"type":"Point"}
}