{
  "type": "Feature",
  "properties": {
    "addr:full":"91 Union St Lismore NSW 2480",
    "addr:housenumber":"91",
    "addr:postcode":"2480",
    "addr:street":"Union St",
    "iso:country":"AU",
    "sg:address":"91 Union St",
    "sg:city":"Lismore",
    "sg:classifiers":[
        {
            "category":"Food & Beverages",
            "subcategory":"Bakery",
            "type":"Retail Goods"
        }
    ],
    "sg:phone":"+61 2 6622 0330",
    "sg:postcode":"2480",
    "sg:province":"NSW",
    "sg:tags":[
        "baker"
    ],
    "wof:name":"South Side Hot Bread",
    "wof:placetype":"venue"
},
  "geometry": {"coordinates":[153.269775391,-28.8089771271],"type":"Point"}
}