{
  "type": "Feature",
  "properties": {
    "addr:full":"16 King Edward St Ulverstone TAS 7315",
    "addr:housenumber":"16",
    "addr:postcode":"7315",
    "addr:street":"King Edward St",
    "iso:country":"AU",
    "sg:address":"16 King Edward St",
    "sg:city":"Ulverstone",
    "sg:classifiers":[
        {
            "category":"Organizations",
            "subcategory":"Community Association",
            "type":"Services"
        }
    ],
    "sg:phone":"+61 3 6425 2584",
    "sg:postcode":"7315",
    "sg:province":"TAS",
    "sg:tags":[
        "club",
        "senior",
        "citizen"
    ],
    "wof:name":"Ulverstone Senior Citizens Club",
    "wof:placetype":"venue"
},
  "geometry": {"coordinates":[146.17201232900001,-41.1554450989],"type":"Point"}
}