{
  "type": "Feature",
  "properties": {
    "addr:full":"145 Bromley Rd Herne Hill WA 6056",
    "addr:housenumber":"145",
    "addr:postcode":"6056",
    "addr:street":"Bromley Rd",
    "iso:country":"AU",
    "sg:address":"145 Bromley Rd",
    "sg:city":"Herne Hill",
    "sg:classifiers":[
        {
            "category":"Home & Garden",
            "subcategory":"Building Materials",
            "type":"Retail Goods"
        }
    ],
    "sg:phone":"+61 8 9296 2960",
    "sg:postcode":"6056",
    "sg:province":"WA",
    "sg:tags":[
        "supply"
    ],
    "wof:name":"Suspended Ceilings & Co.",
    "wof:placetype":"venue"
},
  "geometry": {"coordinates":[116.04258728000001,-31.8398647308],"type":"Point"}
}