{
  "type": "Feature",
  "properties": {
    "addr:full":"Dowling St Thargomindah QLD 4492",
    "addr:postcode":"4492",
    "addr:street":"Dowling St",
    "iso:country":"AU",
    "sg:address":"Dowling St",
    "sg:city":"Thargomindah",
    "sg:classifiers":[
        {
            "category":"Food & Beverages",
            "subcategory":"Fruits & Vegetables",
            "type":"Retail Goods"
        }
    ],
    "sg:phone":"+61 7 4655 3232",
    "sg:postcode":"4492",
    "sg:province":"QLD",
    "sg:tags":[
        "greengrocer",
        "fruiterer"
    ],
    "wof:name":"Thargomindah General Store",
    "wof:placetype":"venue"
},
  "geometry": {"coordinates":[143.82304382300001,-27.996509552],"type":"Point"}
}