{
  "type": "Feature",
  "properties": {
    "addr:full":"2 Ulmarra Pl East Lindfield NSW 2070",
    "addr:housenumber":"2",
    "addr:postcode":"2070",
    "addr:street":"Pl",
    "iso:country":"AU",
    "sg:address":"2 Ulmarra Pl",
    "sg:city":"East Lindfield",
    "sg:classifiers":[
        {
            "category":"Social Services",
            "subcategory":"Retirement Home",
            "type":"Services"
        }
    ],
    "sg:phone":"+61 2 9416 8466",
    "sg:postcode":"2070",
    "sg:province":"NSW",
    "sg:tags":[
        "village"
    ],
    "wof:name":"Aveo Lindfield Gardens",
    "wof:placetype":"venue"
},
  "geometry": {"coordinates":[151.17015075699999,-33.7773017883],"type":"Point"}
}