{
  "type": "Feature",
  "properties": {
    "addr:full":"288- 302 Little Collins St Melbourne VIC 3000",
    "addr:housenumber":"302",
    "addr:postcode":"3000",
    "addr:street":"Little Collins St",
    "iso:country":"AU",
    "sg:address":"288- 302 Little Collins St",
    "sg:city":"Melbourne",
    "sg:classifiers":[
        {
            "category":"Shopping",
            "subcategory":"Clothing, Apparel, & Fashions",
            "type":"Retail Goods"
        }
    ],
    "sg:phone":"+61 3 9650 1318",
    "sg:postcode":"3000",
    "sg:province":"VIC",
    "sg:tags":[
        "lady",
        "wear"
    ],
    "wof:name":"Witchery",
    "wof:placetype":"venue"
},
  "geometry": {"coordinates":[144.96488952600001,-37.8149795532],"type":"Point"}
}