{
  "type": "Feature",
  "properties": {
    "addr:full":"187 - 191 Byng St Orange NSW 2800",
    "addr:housenumber":"191",
    "addr:postcode":"2800",
    "addr:street":"Byng St",
    "iso:country":"AU",
    "sg:address":"187 - 191 Byng St",
    "sg:city":"Orange",
    "sg:classifiers":[
        {
            "category":"Home & Garden",
            "subcategory":"Hardware",
            "type":"Retail Goods"
        }
    ],
    "sg:phone":"+61 2 6362 1322",
    "sg:postcode":"2800",
    "sg:province":"NSW",
    "sg:tags":[
        "plumber",
        "supply"
    ],
    "wof:name":"Tradelink Plumbing Centres",
    "wof:placetype":"venue"
},
  "geometry": {"coordinates":[149.10809326200001,-33.2825050354],"type":"Point"}
}