{
  "type": "Feature",
  "properties": {
    "iso:country":"AU",
    "sg:address":"38 Richard St",
    "sg:city":"Bridport",
    "sg:classifiers":[
        {
            "category":"Utilities",
            "subcategory":"Fuel Oil & Lpg",
            "type":"Services"
        }
    ],
    "sg:phone":"+61 418 386 007",
    "sg:postcode":"7262",
    "sg:province":"TAS",
    "sg:tags":[
        "merchant"
    ],
    "wof:name":"Jenkins T G",
    "wof:placetype":"venue"
},
  "geometry": {"coordinates":[147.387009,-40.996902],"type":"Point"}
}