{
  "type": "Feature",
  "properties": {
    "addr:full":"16 Dendle St Grovedale VIC 3216",
    "addr:housenumber":"16",
    "addr:postcode":"3216",
    "addr:street":"Dendle St",
    "iso:country":"AU",
    "sg:address":"16 Dendle St",
    "sg:city":"Grovedale",
    "sg:classifiers":[
        {
            "category":"Retail",
            "subcategory":"Auto Repair",
            "type":"Services"
        }
    ],
    "sg:phone":"+61 3 5241 2355",
    "sg:postcode":"3216",
    "sg:province":"VIC",
    "sg:tags":[
        "electrical"
    ],
    "wof:name":"Howard's Auto Electrical",
    "wof:placetype":"venue"
},
  "geometry": {"coordinates":[144.34596252399999,-38.1942253113],"type":"Point"}
}