{
  "type": "Feature",
  "properties": {
    "addr:full":"Level 3 190 Goondoon St Gladstone QLD 4680",
    "addr:housenumber":"190",
    "addr:postcode":"4680",
    "addr:street":"Goondoon St",
    "iso:country":"AU",
    "sg:address":"Level 3 190 Goondoon St",
    "sg:city":"Gladstone",
    "sg:classifiers":[
        {
            "category":"Professional",
            "subcategory":"Engineering",
            "type":"Services"
        }
    ],
    "sg:phone":"+61 7 4970 6000",
    "sg:postcode":"4680",
    "sg:province":"QLD",
    "sg:tags":[
        "consulting",
        "engineer"
    ],
    "wof:name":"WorleyParsons Services Pty Ltd",
    "wof:placetype":"venue"
},
  "geometry": {"coordinates":[151.259475708,-23.8485031128],"type":"Point"}
}