{
  "type": "Feature",
  "properties": {
    "addr:full":"Shop C3, Northlands Shopping Centre, 2-50 Murray Rd Preston East VIC 3072",
    "addr:housenumber":"c3;2-50",
    "addr:postcode":"3072",
    "addr:street":"Murray Rd",
    "iso:country":"AU",
    "sg:address":"Shop C3, Northlands Shopping Centre, 2-50 Murray Rd",
    "sg:city":"Preston East",
    "sg:classifiers":[
        {
            "category":"Shopping",
            "subcategory":"Clothing, Apparel, & Fashions",
            "type":"Retail Goods"
        }
    ],
    "sg:phone":"+61 3 9471 3597",
    "sg:postcode":"3072",
    "sg:province":"VIC",
    "sg:tags":[
        "menswear"
    ],
    "wof:name":"Jag",
    "wof:placetype":"venue"
},
  "geometry": {"coordinates":[145.02931213400001,-37.740650177],"type":"Point"}
}