{
  "type": "Feature",
  "properties": {
    "iso:country":"AU",
    "sg:address":"72 Planthurst Rd",
    "sg:city":"Carlton",
    "sg:classifiers":[
        {
            "category":"Government",
            "subcategory":"Department Of Motor Vehicles",
            "type":"Public Place"
        }
    ],
    "sg:phone":"+61 2 9546 5488",
    "sg:postcode":"2218",
    "sg:province":"NSW",
    "sg:tags":[
        "wholesaler",
        "mfrs",
        "accessory"
    ],
    "wof:name":"Xdc Pty Ltd",
    "wof:placetype":"venue"
},
  "geometry": {"coordinates":[151.114792,-33.978024],"type":"Point"}
}