{
  "type": "Feature",
  "properties": {
    "addr:full":"200 Belair Rd Hawthorn SA 5062",
    "addr:housenumber":"200",
    "addr:postcode":"5062",
    "addr:street":"Belair Rd",
    "iso:country":"AU",
    "sg:address":"200 Belair Rd",
    "sg:city":"Hawthorn",
    "sg:classifiers":[
        {
            "category":"Sports & Exercise",
            "subcategory":"Gym",
            "type":"Entertainment"
        }
    ],
    "sg:phone":"+61 1300 669 669",
    "sg:postcode":"5062",
    "sg:province":"SA",
    "sg:tags":[
        "personal",
        "trainer",
        "fitness"
    ],
    "wof:name":"Australian Institute Of Fitness",
    "wof:placetype":"venue"
},
  "geometry": {"coordinates":[138.60896301299999,-34.9719772339],"type":"Point"}
}