{
  "type": "Feature",
  "properties": {
    "addr:full":"92 Kings Rd Five Dock NSW 2046",
    "addr:housenumber":"92",
    "addr:postcode":"2046",
    "addr:street":"Kings Rd",
    "iso:country":"AU",
    "sg:address":"92 Kings Rd",
    "sg:city":"Five Dock",
    "sg:classifiers":[
        {
            "category":"Retail",
            "subcategory":"Auto Repair",
            "type":"Services"
        }
    ],
    "sg:phone":"+61 2 9713 7281",
    "sg:postcode":"2046",
    "sg:province":"NSW",
    "sg:tags":[
        "beater",
        "painter",
        "panel"
    ],
    "wof:name":"P & G Accident Repair Centre",
    "wof:placetype":"venue"
},
  "geometry": {"coordinates":[151.122986,-33.868603],"type":"Point"}
}