{
  "type": "Feature",
  "properties": {
    "iso:country":"AU",
    "sg:address":"14 Orange St",
    "sg:city":"Manildra",
    "sg:classifiers":[
        {
            "category":"Farming",
            "subcategory":"Farm & Veterinary Services",
            "type":"Manufacturing & Wholesale Goods"
        }
    ],
    "sg:phone":"+61 2 6364 5279",
    "sg:postcode":"2865",
    "sg:province":"NSW",
    "sg:tags":[
        "drying",
        "seed",
        "cleaning",
        "grading"
    ],
    "wof:name":"AJ & KM Gosper",
    "wof:placetype":"venue"
},
  "geometry": {"coordinates":[148.69248999999999,-33.182579],"type":"Point"}
}