{
  "type": "Feature",
  "properties": {
    "iso:country":"AU",
    "sg:address":"22- 28 Nepean Hwy",
    "sg:city":"Mentone",
    "sg:classifiers":[
        {
            "category":"Shopping",
            "subcategory":"Mobile Phones",
            "type":"Retail Goods"
        }
    ],
    "sg:phone":"+61 3 8543 4801",
    "sg:postcode":"3194",
    "sg:province":"VIC",
    "sg:tags":[
        "telephone",
        "accessory"
    ],
    "wof:name":"Telstra Shop",
    "wof:placetype":"venue"
},
  "geometry": {"coordinates":[145.06570434599999,-37.9761199951],"type":"Point"}
}