{
  "type": "Feature",
  "properties": {
    "addr:full":"36 Irvine St Bayswater WA 6053",
    "addr:housenumber":"36",
    "addr:postcode":"6053",
    "addr:street":"Irvine St",
    "iso:country":"AU",
    "sg:address":"36 Irvine St",
    "sg:city":"Bayswater",
    "sg:classifiers":[
        {
            "category":"Wholesale",
            "subcategory":"Scrap",
            "type":"Manufacturing & Wholesale Goods"
        }
    ],
    "sg:phone":"+61 8 9272 5286",
    "sg:postcode":"6053",
    "sg:province":"WA",
    "sg:tags":[
        "merchant",
        "metal"
    ],
    "wof:name":"K & F Scrap Metal",
    "wof:placetype":"venue"
},
  "geometry": {"coordinates":[115.919952393,-31.9110431671],"type":"Point"}
}