{
  "type": "Feature",
  "properties": {
    "addr:full":"86 Shaftesbury Rd Burwood NSW 2134",
    "addr:housenumber":"86",
    "addr:postcode":"2134",
    "addr:street":"Shaftesbury Rd",
    "iso:country":"AU",
    "sg:address":"86 Shaftesbury Rd",
    "sg:city":"Burwood",
    "sg:classifiers":[
        {
            "category":"Health Services",
            "subcategory":"Doctor",
            "type":"Services"
        }
    ],
    "sg:phone":"+61 2 9744 8470",
    "sg:postcode":"2134",
    "sg:province":"NSW",
    "sg:tags":[
        "medical",
        "practitioner"
    ],
    "wof:name":"Campbell D V",
    "wof:placetype":"venue"
},
  "geometry": {"coordinates":[151.107025147,-33.8784751892],"type":"Point"}
}