{
  "type": "Feature",
  "properties": {
    "iso:country":"AU",
    "sg:address":"86 Browning St",
    "sg:city":"Portland",
    "sg:classifiers":[
        {
            "category":"Building & Trades",
            "subcategory":"Construction",
            "type":"Services"
        }
    ],
    "sg:phone":"+61 3 5523 5919",
    "sg:postcode":"3305",
    "sg:province":"VIC",
    "sg:tags":[
        "earth",
        "excavating",
        "moving",
        "contractor"
    ],
    "wof:name":"Doherty T & L Pty Ltd",
    "wof:placetype":"venue"
},
  "geometry": {"coordinates":[141.59260559099999,-38.3349151611],"type":"Point"}
}