{
  "type": "Feature",
  "properties": {
    "iso:country":"AU",
    "sg:address":"1230 High St",
    "sg:city":"Armadale",
    "sg:classifiers":[
        {
            "category":"Personal",
            "subcategory":"Massage",
            "type":"Services"
        }
    ],
    "sg:phone":"+61 3 9509 7622",
    "sg:postcode":"3143",
    "sg:province":"VIC",
    "sg:tags":[
        "therapy"
    ],
    "wof:name":"Voight Suzette",
    "wof:placetype":"venue"
},
  "geometry": {"coordinates":[145.02789306599999,-37.8565444946],"type":"Point"}
}