{
  "type": "Feature",
  "properties": {
    "iso:country":"AU",
    "sg:address":"24 Waldo St",
    "sg:city":"Norman Park",
    "sg:classifiers":[
        {
            "category":"Professional",
            "subcategory":"Engineering",
            "type":"Services"
        }
    ],
    "sg:phone":"+61 7 3899 2085",
    "sg:postcode":"4170",
    "sg:province":"QLD",
    "sg:tags":[
        "consulting",
        "engineer"
    ],
    "wof:name":"Pierce James & Associates",
    "wof:placetype":"venue"
},
  "geometry": {"coordinates":[153.05764770499999,-27.4720363617],"type":"Point"}
}