{
  "type": "Feature",
  "properties": {
    "addr:full":"229 Miller St North Sydney NSW 2060",
    "addr:housenumber":"229",
    "addr:postcode":"2060",
    "addr:street":"Miller St",
    "iso:country":"AU",
    "sg:address":"229 Miller St",
    "sg:city":"North Sydney",
    "sg:classifiers":[
        {
            "category":"Health Services",
            "subcategory":"Medical Lab",
            "type":"Services"
        }
    ],
    "sg:phone":"+61 2 9955 2750",
    "sg:postcode":"2060",
    "sg:province":"NSW",
    "sg:tags":[
        "laboratory",
        "dental"
    ],
    "wof:name":"Park West Dental Technology",
    "wof:placetype":"venue"
},
  "geometry": {"coordinates":[151.20773315400001,-33.8353652954],"type":"Point"}
}