{
  "type": "Feature",
  "properties": {
    "addr:full":"Unit 9/ 1 Rothcote Crt Burleigh Heads QLD 4220",
    "addr:housenumber":"1",
    "addr:postcode":"4220",
    "addr:street":"Rothcote Crt",
    "iso:country":"AU",
    "sg:address":"Unit 9/ 1 Rothcote Crt",
    "sg:city":"Burleigh Heads",
    "sg:classifiers":[
        {
            "category":"Manufacturing",
            "subcategory":"Glass & Minerals",
            "type":"Manufacturing & Wholesale Goods"
        }
    ],
    "sg:phone":"+61 7 5593 7073",
    "sg:postcode":"4220",
    "sg:province":"QLD",
    "sg:tags":[
        "merchant",
        "granite",
        "marble"
    ],
    "wof:name":"Grioli Stone Pty Ltd",
    "wof:placetype":"venue"
},
  "geometry": {"coordinates":[153.418212891,-28.1008625031],"type":"Point"}
}