{
  "type": "Feature",
  "properties": {
    "addr:full":"501 Derril Rd Moorooduc VIC 3933",
    "addr:housenumber":"501",
    "addr:postcode":"3933",
    "addr:street":"Derril Rd",
    "iso:country":"AU",
    "sg:address":"501 Derril Rd",
    "sg:city":"Moorooduc",
    "sg:classifiers":[
        {
            "category":"Health Services",
            "subcategory":"Doctor",
            "type":"Services"
        }
    ],
    "sg:phone":"+61 3 5971 8505",
    "sg:postcode":"3933",
    "sg:province":"VIC",
    "sg:tags":[
        "medical",
        "practitioner"
    ],
    "wof:name":"McIntyre Richard L E",
    "wof:placetype":"venue"
},
  "geometry": {"coordinates":[145.09817504899999,-38.2755813599],"type":"Point"}
}