{
  "type": "Feature",
  "properties": {
    "addr:full":"St Bedes Hall 200 Military Rd Semaphore SA 5019",
    "addr:housenumber":"200",
    "addr:postcode":"5019",
    "addr:street":"St;Military Rd",
    "iso:country":"AU",
    "sg:address":"St Bedes Hall 200 Military Rd",
    "sg:city":"Semaphore",
    "sg:classifiers":[
        {
            "category":"Arts & Performance",
            "subcategory":"Dance",
            "type":"Entertainment"
        }
    ],
    "sg:phone":"+61 8 8449 7594",
    "sg:postcode":"5019",
    "sg:province":"SA",
    "sg:tags":[
        "theatrical",
        "ballet",
        "tuition"
    ],
    "wof:name":"Desalyne Dancers",
    "wof:placetype":"venue"
},
  "geometry": {"coordinates":[138.484085083,-34.8389587402],"type":"Point"}
}