{
  "type": "Feature",
  "properties": {
    "addr:full":"4 Barry Drv Canberra ACT 0230",
    "addr:housenumber":"4",
    "addr:postcode":"0230",
    "addr:street":"Barry Drv",
    "iso:country":"AU",
    "sg:address":"4 Barry Drv",
    "sg:city":"Canberra",
    "sg:classifiers":[
        {
            "category":"Home & Garden",
            "subcategory":"Carpets & Floor Coverings",
            "type":"Retail Goods"
        }
    ],
    "sg:phone":"+61 1300 301 038",
    "sg:postcode":"0230",
    "sg:province":"ACT",
    "sg:tags":[
        "mat",
        "matting"
    ],
    "wof:name":"Signature Marketing",
    "wof:placetype":"venue"
},
  "geometry": {"coordinates":[149.128082275,-35.2753562927],"type":"Point"}
}