{
  "type": "Feature",
  "properties": {
    "addr:full":"Ste3b/ 48 Sugar Rd Maroochydore QLD 4558",
    "addr:housenumber":"48",
    "addr:postcode":"4558",
    "addr:street":"Sugar Rd",
    "iso:country":"AU",
    "sg:address":"Ste3b/ 48 Sugar Rd",
    "sg:city":"Maroochydore",
    "sg:classifiers":[
        {
            "category":"Professional",
            "subcategory":"Accounting & Tax Preparation",
            "type":"Services"
        }
    ],
    "sg:phone":"+61 7 5452 7761",
    "sg:postcode":"4558",
    "sg:province":"QLD",
    "sg:tags":[
        "accountant",
        "auditor"
    ],
    "wof:name":"Phil Wright",
    "wof:placetype":"venue"
},
  "geometry": {"coordinates":[153.092193603,-26.6665115356],"type":"Point"}
}