{
  "type": "Feature",
  "properties": {
    "iso:country":"AU",
    "sg:address":"6 Leath Rd",
    "sg:city":"Kwinana",
    "sg:classifiers":[
        {
            "category":"Building & Trades",
            "subcategory":"Plumbing",
            "type":"Services"
        }
    ],
    "sg:phone":"+61 8 9437 8280",
    "sg:postcode":"6167",
    "sg:province":"WA",
    "sg:tags":[
        "fitting",
        "hose",
        "supply"
    ],
    "wof:name":"ACJ Enterprises",
    "wof:placetype":"venue"
},
  "geometry": {"coordinates":[115.776329,-32.208591],"type":"Point"}
}