{
  "type": "Feature",
  "properties": {
    "addr:full":"Hunter St Newcastle NSW 2300",
    "addr:postcode":"2300",
    "addr:street":"Hunter St",
    "iso:country":"AU",
    "sg:address":"Hunter St",
    "sg:city":"Newcastle",
    "sg:classifiers":[
        {
            "category":"Food & Beverages",
            "subcategory":"Liquor & Beverages",
            "type":"Retail Goods"
        }
    ],
    "sg:phone":"+61 2 4929 5237",
    "sg:postcode":"2300",
    "sg:province":"NSW",
    "sg:tags":[
        "store"
    ],
    "wof:name":"Phone-A-Drink",
    "wof:placetype":"venue"
},
  "geometry": {"coordinates":[151.781036,-32.926991],"type":"Point"}
}