{
  "type": "Feature",
  "properties": {
    "addr:full":"37 Healey Rd Dandenong VIC 3175",
    "addr:housenumber":"37",
    "addr:postcode":"3175",
    "addr:street":"Healey Rd",
    "iso:country":"AU",
    "sg:address":"37 Healey Rd",
    "sg:city":"Dandenong",
    "sg:classifiers":[
        {
            "category":"Professional",
            "type":"Services"
        }
    ],
    "sg:phone":"+61 3 9768 2194",
    "sg:postcode":"3175",
    "sg:province":"VIC",
    "sg:tags":[
        "shop",
        "fitting"
    ],
    "wof:name":"Dawson Custom Interiors",
    "wof:placetype":"venue"
},
  "geometry": {"coordinates":[145.22558593799999,-38.0278244019],"type":"Point"}
}