{
  "type": "Feature",
  "properties": {
    "addr:full":"119 Sandagate Rd Albion QLD 4010",
    "addr:housenumber":"119",
    "addr:postcode":"4010",
    "addr:street":"Sandagate Rd",
    "iso:country":"AU",
    "sg:address":"119 Sandagate Rd",
    "sg:city":"Albion",
    "sg:classifiers":[
        {
            "category":"Wholesale",
            "subcategory":"Apparel",
            "type":"Manufacturing & Wholesale Goods"
        }
    ],
    "sg:phone":"+61 7 3262 8869",
    "sg:postcode":"4010",
    "sg:province":"QLD",
    "sg:tags":[
        "wholesaler",
        "mfrs",
        "sportswear",
        "women's"
    ],
    "sg:website":"http://www.official.com.au",
    "wof:name":"Official Clothing & Promotions",
    "wof:placetype":"venue"
},
  "geometry": {"coordinates":[153.04385375999999,-27.4357070923],"type":"Point"}
}