{
  "type": "Feature",
  "properties": {
    "addr:full":"Level 2/ 387 George St Sydney NSW 2000",
    "addr:housenumber":"/ 387",
    "addr:postcode":"2000",
    "addr:street":"George St",
    "iso:country":"AU",
    "sg:address":"Level 2/ 387 George St",
    "sg:city":"Sydney",
    "sg:classifiers":[
        {
            "category":"Ice Cream",
            "type":"Food & Drink"
        }
    ],
    "sg:phone":"+61 2 9290 3233",
    "sg:postcode":"2000",
    "sg:province":"NSW",
    "sg:tags":[
        "specialised",
        "fitting",
        "lady",
        "wear"
    ],
    "wof:name":"Sonsi Design Pty Ltd",
    "wof:placetype":"venue"
},
  "geometry": {"coordinates":[151.206787109,-33.8693618774],"type":"Point"}
}