{
  "type": "Feature",
  "properties": {
    "addr:full":"39 Suscatand St Rocklea QLD 4106",
    "addr:housenumber":"39",
    "addr:postcode":"4106",
    "addr:street":"Suscatand St",
    "iso:country":"AU",
    "sg:address":"39 Suscatand St",
    "sg:city":"Rocklea",
    "sg:classifiers":[
        {
            "category":"Professional",
            "type":"Services"
        }
    ],
    "sg:phone":"+61 413 055 685",
    "sg:postcode":"4106",
    "sg:province":"QLD",
    "sg:tags":[
        "transport"
    ],
    "wof:name":"Freightrite Transport",
    "wof:placetype":"venue"
},
  "geometry": {"coordinates":[152.996948242,-27.5559577942],"type":"Point"}
}