{
  "type": "Feature",
  "properties": {
    "iso:country":"AU",
    "sg:address":"205 Murradoc Rd",
    "sg:city":"Drysdale",
    "sg:classifiers":[
        {
            "category":"Commercial Area",
            "type":"Public Place"
        }
    ],
    "sg:phone":"+61 3 5251 2325",
    "sg:postcode":"3222",
    "sg:province":"VIC",
    "sg:tags":[
        "heavy",
        "carrier"
    ],
    "wof:name":"Jennings R L",
    "wof:placetype":"venue"
},
  "geometry": {"coordinates":[144.59314000000001,-38.175495],"type":"Point"}
}