{
  "type": "Feature",
  "properties": {
    "addr:full":"18 De Havilland Rd Mordialloc VIC 3195",
    "addr:postcode":"3195",
    "addr:street":"18 De Havilland Rd",
    "iso:country":"AU",
    "sg:address":"18 De Havilland Rd",
    "sg:city":"Mordialloc",
    "sg:classifiers":[
        {
            "category":"Community Center",
            "subcategory":"Social",
            "type":"Public Place"
        }
    ],
    "sg:phone":"+61 3 9580 8422",
    "sg:postcode":"3195",
    "sg:province":"VIC",
    "sg:tags":[
        "precision",
        "grinding"
    ],
    "wof:name":"Cooper Geo. F.",
    "wof:placetype":"venue"
},
  "geometry": {"coordinates":[145.10076904300001,-37.9866065979],"type":"Point"}
}