{
  "type": "Feature",
  "properties": {
    "addr:full":"209 Barrington St Bibra Lake WA 6163",
    "addr:housenumber":"209",
    "addr:postcode":"6163",
    "addr:street":"Barrington St",
    "iso:country":"AU",
    "sg:address":"209 Barrington St",
    "sg:city":"Bibra Lake",
    "sg:classifiers":[
        {
            "category":"Building & Trades",
            "subcategory":"Plumbing",
            "type":"Services"
        }
    ],
    "sg:phone":"+61 8 9330 1144",
    "sg:postcode":"6163",
    "sg:province":"WA",
    "sg:tags":[
        "pump",
        "repairer"
    ],
    "wof:name":"Western Irrigation Pty Ltd",
    "wof:placetype":"venue"
},
  "geometry": {"coordinates":[115.811562,-32.116741],"type":"Point"}
}