{
  "type": "Feature",
  "properties": {
    "iso:country":"AU",
    "sg:address":"22 Scott St",
    "sg:city":"Weston",
    "sg:classifiers":[
        {
            "category":"Social Services",
            "subcategory":"Child Care",
            "type":"Services"
        }
    ],
    "sg:phone":"+61 2 4937 4790",
    "sg:postcode":"2326",
    "sg:province":"NSW",
    "wof:name":"Weston Community Pre-School",
    "wof:placetype":"venue"
},
  "geometry": {"coordinates":[151.45799255399999,-32.8157691956],"type":"Point"}
}