{
  "type": "Feature",
  "properties": {
    "addr:full":"Gamenya Ave Merredin WA 6415",
    "addr:postcode":"6415",
    "addr:street":"Gamenya Ave",
    "iso:country":"AU",
    "sg:address":"Gamenya Ave",
    "sg:city":"Merredin",
    "sg:classifiers":[
        {
            "category":"Autos & Motor Vehicles",
            "subcategory":"Fuel & Gas Station",
            "type":"Retail Goods"
        }
    ],
    "sg:phone":"+61 8 9041 1082",
    "sg:postcode":"6415",
    "sg:province":"WA",
    "wof:name":"BP Australia Limited",
    "wof:placetype":"venue"
},
  "geometry": {"coordinates":[118.27205658,-31.4828529358],"type":"Point"}
}