{
  "type": "Feature",
  "properties": {
    "iso:country":"AU",
    "sg:address":"2 McNaught St",
    "sg:city":"Point Lonsdale",
    "sg:classifiers":[
        {
            "category":"Building & Trades",
            "subcategory":"Construction",
            "type":"Services"
        }
    ],
    "sg:phone":"+61 3 5258 1634",
    "sg:postcode":"3225",
    "sg:province":"VIC",
    "sg:tags":[
        "contractor"
    ],
    "wof:name":"O&#039;Dowd Design and Construction",
    "wof:placetype":"venue"
},
  "geometry": {"coordinates":[144.609161,-38.277481],"type":"Point"}
}