{
  "type": "Feature",
  "properties": {
    "addr:full":"Grace St Sandy Bay TAS 7005",
    "addr:postcode":"7005",
    "addr:street":"Grace St",
    "iso:country":"AU",
    "sg:address":"Grace St",
    "sg:city":"Sandy Bay",
    "sg:classifiers":[
        {
            "category":"Social Services",
            "subcategory":"Child Care",
            "type":"Services"
        }
    ],
    "sg:phone":"+61 3 6226 2088",
    "sg:postcode":"7005",
    "sg:province":"TAS",
    "wof:name":"University Community Child Care Centre",
    "wof:placetype":"venue"
},
  "geometry": {"coordinates":[147.32957458499999,-42.9000473022],"type":"Point"}
}