{
  "type": "Feature",
  "properties": {
    "addr:full":"Gas Rd Selfs Point TAS 7008",
    "addr:postcode":"7008",
    "addr:street":"Gas Rd Selfs",
    "iso:country":"AU",
    "sg:address":"Gas Rd",
    "sg:city":"Selfs Point",
    "sg:classifiers":[
        {
            "category":"Utilities",
            "subcategory":"Natural Gas",
            "type":"Services"
        }
    ],
    "sg:phone":"+61 13 24 62",
    "sg:postcode":"7008",
    "sg:province":"TAS",
    "sg:tags":[
        "supplier"
    ],
    "wof:name":"Origin Energy",
    "wof:placetype":"venue"
},
  "geometry": {"coordinates":[147.315963745,-42.8503761292],"type":"Point"}
}