{
  "type": "Feature",
  "properties": {
    "addr:full":"46 Park Ave Coffs Harbour NSW 2450",
    "addr:housenumber":"46",
    "addr:postcode":"2450",
    "addr:street":"Park Ave",
    "iso:country":"AU",
    "sg:address":"46 Park Ave",
    "sg:city":"Coffs Harbour",
    "sg:classifiers":[
        {
            "category":"Banks & Credit Unions",
            "subcategory":"Financial Services",
            "type":"Services"
        }
    ],
    "sg:phone":"+61 2 6648 7500",
    "sg:postcode":"2450",
    "sg:province":"NSW",
    "sg:tags":[
        "financier"
    ],
    "wof:name":"North State Finance Limited",
    "wof:placetype":"venue"
},
  "geometry": {"coordinates":[153.11695900000001,-30.29999],"type":"Point"}
}