{
  "type": "Feature",
  "properties": {
    "iso:country":"AU",
    "sg:address":"22 Robert St",
    "sg:city":"Henley Brook",
    "sg:classifiers":[
        {
            "category":"Farming",
            "subcategory":"Farm & Veterinary Services",
            "type":"Manufacturing & Wholesale Goods"
        }
    ],
    "sg:phone":"+61 8 9296 4948",
    "sg:postcode":"6055",
    "sg:province":"WA",
    "sg:tags":[
        "irrigation",
        "reticulation",
        "system"
    ],
    "wof:name":"Henley Brook Turf Farm",
    "wof:placetype":"venue"
},
  "geometry": {"coordinates":[115.982971,-31.803867],"type":"Point"}
}