{
  "type": "Feature",
  "properties": {
    "addr:full":"Level 9, Suite 903, 121 Walker St North Sydney NSW 2060",
    "addr:housenumber":"121",
    "addr:postcode":"2060",
    "addr:street":"Walker St",
    "iso:country":"AU",
    "sg:address":"Level 9, Suite 903, 121 Walker St",
    "sg:city":"North Sydney",
    "sg:classifiers":[
        {
            "category":"Transit Center",
            "subcategory":"Freight",
            "type":"Transportation"
        }
    ],
    "sg:phone":"+61 2 9959 3688",
    "sg:postcode":"2060",
    "sg:province":"NSW",
    "sg:tags":[
        "agent",
        "shipping"
    ],
    "wof:name":"DS Logistics Pty Ltd",
    "wof:placetype":"venue"
},
  "geometry": {"coordinates":[151.20903015100001,-33.8388442993],"type":"Point"}
}