{
  "type": "Feature",
  "properties": {
    "addr:full":"1 Oban Crt Greenvale VIC 3059",
    "addr:housenumber":"1",
    "addr:postcode":"3059",
    "addr:street":"Oban Crt",
    "iso:country":"AU",
    "sg:address":"1 Oban Crt",
    "sg:city":"Greenvale",
    "sg:classifiers":[
        {
            "category":"Building & Trades",
            "subcategory":"Cleaning & Sanitation",
            "type":"Services"
        }
    ],
    "sg:phone":"+61 3 9333 1097",
    "sg:postcode":"3059",
    "sg:province":"VIC",
    "sg:tags":[
        "industrial",
        "commercial",
        "contractor"
    ],
    "wof:name":"Tulla Cleaning",
    "wof:placetype":"venue"
},
  "geometry": {"coordinates":[144.89894104000001,-37.6460952759],"type":"Point"}
}