{
  "type": "Feature",
  "properties": {
    "addr:full":"Unit 3/ 1353 The Horsley Drv Wetherill Park NSW 2164",
    "addr:housenumber":"/ 1353",
    "addr:postcode":"2164",
    "addr:street":"The Horsley Drv",
    "iso:country":"AU",
    "sg:address":"Unit 3/ 1353 The Horsley Drv",
    "sg:city":"Wetherill Park",
    "sg:classifiers":[
        {
            "category":"Professional",
            "subcategory":"Detective & Security Services",
            "type":"Services"
        }
    ],
    "sg:phone":"+61 2 9756 6033",
    "sg:postcode":"2164",
    "sg:province":"NSW",
    "sg:tags":[
        "equipment",
        "window",
        "doors"
    ],
    "wof:name":"Dinkha Y",
    "wof:placetype":"venue"
},
  "geometry": {"coordinates":[150.882125855,-33.8522949219],"type":"Point"}
}