{
  "type": "Feature",
  "properties": {
    "iso:country":"AU",
    "sg:address":"1934 Hume Hwy",
    "sg:city":"Campbellfield",
    "sg:classifiers":[
        {
            "category":"Building & Trades",
            "subcategory":"Equipment Rental",
            "type":"Services"
        }
    ],
    "sg:phone":"+61 3 9354 1400",
    "sg:postcode":"3061",
    "sg:province":"VIC",
    "sg:tags":[
        "supply",
        "catering"
    ],
    "wof:name":"Kitchens On The Run Australia",
    "wof:placetype":"venue"
},
  "geometry": {"coordinates":[144.95396423299999,-37.6565628052],"type":"Point"}
}