{
  "type": "Feature",
  "properties": {
    "addr:full":"Shop 31 Warriewood Sq Warriewood NSW 2102",
    "addr:housenumber":"shop 31",
    "addr:postcode":"2102",
    "addr:street":"Warriewood Sq",
    "iso:country":"AU",
    "sg:address":"Shop 31",
    "sg:city":"Warriewood Sq Warriewood",
    "sg:classifiers":[
        {
            "category":"Banks & Credit Unions",
            "subcategory":"Bank",
            "type":"Services"
        }
    ],
    "sg:phone":"+61 13 33 30",
    "sg:postcode":"2102",
    "sg:province":"NSW",
    "wof:name":"St.George Bank Limited",
    "wof:placetype":"venue"
},
  "geometry": {"coordinates":[151.30059800000001,-33.687588],"type":"Point"}
}