{
  "type": "Feature",
  "properties": {
    "iso:country":"AU",
    "sg:address":"35 Belgrave Rd",
    "sg:city":"Bees Creek",
    "sg:classifiers":[
        {
            "category":"Building & Trades",
            "subcategory":"Construction",
            "type":"Services"
        }
    ],
    "sg:phone":"+61 413 128 660",
    "sg:postcode":"0822",
    "sg:province":"NT",
    "sg:tags":[
        "contractor"
    ],
    "wof:name":"Belgrave Homes",
    "wof:placetype":"venue"
},
  "geometry": {"coordinates":[131.070724,-12.567265],"type":"Point"}
}