{
  "type": "Feature",
  "properties": {
    "addr:full":"253 Elizabeth St Melbourne VIC 3000",
    "addr:housenumber":"253",
    "addr:postcode":"3000",
    "addr:street":"Elizabeth St",
    "iso:country":"AU",
    "sg:address":"253 Elizabeth St",
    "sg:city":"Melbourne",
    "sg:classifiers":[
        {
            "category":"Shopping",
            "subcategory":"Mobile Phones",
            "type":"Retail Goods"
        }
    ],
    "sg:phone":"+61 3 9642 2222",
    "sg:postcode":"3000",
    "sg:province":"VIC",
    "sg:tags":[
        "telephone",
        "accessory"
    ],
    "wof:name":"Masterlink Communications",
    "wof:placetype":"venue"
},
  "geometry": {"coordinates":[144.96224975600001,-37.8125991821],"type":"Point"}
}