{
  "type": "Feature",
  "properties": {
    "addr:full":"Bowds Rd Strathdownie VIC 3312",
    "addr:postcode":"3312",
    "addr:street":"Bowds Rd",
    "iso:country":"AU",
    "sg:address":"Bowds Rd",
    "sg:city":"Strathdownie",
    "sg:classifiers":[
        {
            "category":"Manufacturing",
            "subcategory":"Lumber",
            "type":"Manufacturing & Wholesale Goods"
        }
    ],
    "sg:phone":"+61 3 5584 7297",
    "sg:postcode":"3312",
    "sg:province":"VIC",
    "sg:tags":[
        "sawmillers"
    ],
    "wof:name":"SL & JM Bowd Portable Sawmill",
    "wof:placetype":"venue"
},
  "geometry": {"coordinates":[141.03233337399999,-37.7709922791],"type":"Point"}
}