{
  "type": "Feature",
  "properties": {
    "addr:full":"6 Memorial Ave Nuriootpa SA 5355",
    "addr:housenumber":"6",
    "addr:postcode":"5355",
    "addr:street":"Memorial Ave",
    "iso:country":"AU",
    "sg:address":"6 Memorial Ave",
    "sg:city":"Nuriootpa",
    "sg:classifiers":[
        {
            "category":"Health Services",
            "subcategory":"Doctor",
            "type":"Services"
        }
    ],
    "sg:phone":"+61 8 8562 2444",
    "sg:postcode":"5355",
    "sg:province":"SA",
    "sg:tags":[
        "medical",
        "practitioner"
    ],
    "wof:name":"Markey J Dr",
    "wof:placetype":"venue"
},
  "geometry": {"coordinates":[138.997924805,-34.4705276489],"type":"Point"}
}