{
  "type": "Feature",
  "properties": {
    "addr:full":"Loch St Derby WA 6728",
    "addr:postcode":"6728",
    "addr:street":"Loch St",
    "iso:country":"AU",
    "sg:address":"Loch St",
    "sg:city":"Derby",
    "sg:classifiers":[
        {
            "category":"Government",
            "subcategory":"Post Office",
            "type":"Public Place"
        }
    ],
    "sg:phone":"+61 8 9191 1350",
    "sg:postcode":"6728",
    "sg:province":"WA",
    "sg:tags":[
        "postal"
    ],
    "wof:name":"Australia Post",
    "wof:placetype":"venue"
},
  "geometry": {"coordinates":[123.647720337,-17.3093242645],"type":"Point"}
}