{
  "type": "Feature",
  "properties": {
    "addr:full":"Sandgate Rd Virginia QLD 4014",
    "addr:postcode":"4014",
    "addr:street":"Sandgate Rd",
    "iso:country":"AU",
    "sg:address":"Sandgate Rd",
    "sg:city":"Virginia",
    "sg:classifiers":[
        {
            "category":"Retail",
            "subcategory":"Car Wash",
            "type":"Services"
        }
    ],
    "sg:phone":"+61 7 3865 4976",
    "sg:postcode":"4014",
    "sg:province":"QLD",
    "sg:tags":[
        "truck",
        "cleaning"
    ],
    "wof:name":"Carlovers Carwash Limited",
    "wof:placetype":"venue"
},
  "geometry": {"coordinates":[153.063323975,-27.380361557],"type":"Point"}
}