{
  "type": "Feature",
  "properties": {
    "addr:full":"95 Marian Rd Firle SA 5070",
    "addr:housenumber":"95",
    "addr:postcode":"5070",
    "addr:street":"Marian Rd",
    "iso:country":"AU",
    "sg:address":"95 Marian Rd",
    "sg:city":"Firle",
    "sg:classifiers":[
        {
            "category":"Building & Trades",
            "subcategory":"Cleaning & Sanitation",
            "type":"Services"
        }
    ],
    "sg:phone":"+61 411 751 899",
    "sg:postcode":"5070",
    "sg:province":"SA",
    "sg:tags":[
        "commercial",
        "maintenance"
    ],
    "wof:name":"Sortini Carpentry & Maintenance",
    "wof:placetype":"venue"
},
  "geometry": {"coordinates":[138.648925781,-34.9014854431],"type":"Point"}
}