{
  "type": "Feature",
  "properties": {
    "iso:country":"AU",
    "sg:address":"Shop 43 Waverley Gardens Shopping Centre",
    "sg:city":"Mulgrave",
    "sg:classifiers":[
        {
            "category":"Recreation",
            "subcategory":"Amusement Park",
            "type":"Entertainment"
        }
    ],
    "sg:phone":"+61 3 9562 3955",
    "sg:postcode":"3170",
    "sg:province":"VIC",
    "wof:name":"Tunza Fun",
    "wof:placetype":"venue"
},
  "geometry": {"coordinates":[145.122146606,-37.8839378357],"type":"Point"}
}