{
  "type": "Feature",
  "properties": {
    "addr:full":"21 Stoneham St Stones Corner QLD 4120",
    "addr:housenumber":"21",
    "addr:postcode":"4120",
    "addr:street":"Stoneham St",
    "iso:country":"AU",
    "sg:address":"21 Stoneham St",
    "sg:city":"Stones Corner",
    "sg:classifiers":[
        {
            "category":"Health Services",
            "subcategory":"Doctor",
            "type":"Services"
        }
    ],
    "sg:phone":"+61 7 3366 5651",
    "sg:postcode":"4120",
    "sg:province":"QLD",
    "sg:tags":[
        "medical",
        "practitioner"
    ],
    "wof:name":"Bartley Paul C",
    "wof:placetype":"venue"
},
  "geometry": {"coordinates":[153.04559326200001,-27.4991130829],"type":"Point"}
}