{
  "type": "Feature",
  "properties": {
    "addr:full":"Cnr Cook & Wood Sts Flinders VIC 3929",
    "addr:postcode":"3929",
    "addr:street":"Cnr",
    "iso:country":"AU",
    "sg:address":"Cnr Cook & Wood Sts",
    "sg:city":"Flinders",
    "sg:classifiers":[
        {
            "category":"Travel",
            "subcategory":"Hotels & Motels",
            "type":"Entertainment"
        }
    ],
    "sg:phone":"+61 3 5989 0201",
    "sg:postcode":"3929",
    "sg:province":"VIC",
    "wof:name":"Hotel Flinders",
    "wof:placetype":"venue"
},
  "geometry": {"coordinates":[145.01753234899999,-38.4739608765],"type":"Point"}
}