{
  "type": "Feature",
  "properties": {
    "addr:full":"231 Merrylands Rd Merrylands NSW 2160",
    "addr:housenumber":"231",
    "addr:postcode":"2160",
    "addr:street":"Merrylands Rd",
    "iso:country":"AU",
    "sg:address":"231 Merrylands Rd",
    "sg:city":"Merrylands",
    "sg:classifiers":[
        {
            "category":"Shopping",
            "subcategory":"Gifts & Souvenirs",
            "type":"Retail Goods"
        }
    ],
    "sg:phone":"+61 2 9637 2658",
    "sg:postcode":"2160",
    "sg:province":"NSW",
    "sg:tags":[
        "greeting",
        "card"
    ],
    "wof:name":"Merrylands Card Shoppe",
    "wof:placetype":"venue"
},
  "geometry": {"coordinates":[150.98834228499999,-33.836025238],"type":"Point"}
}