{
  "type": "Feature",
  "properties": {
    "addr:full":"384- 392 Beamish St Campsie NSW 2194",
    "addr:housenumber":"392",
    "addr:postcode":"2194",
    "addr:street":"Beamish St",
    "iso:country":"AU",
    "sg:address":"384- 392 Beamish St",
    "sg:city":"Campsie",
    "sg:classifiers":[
        {
            "category":"Retail",
            "subcategory":"Auto Repair",
            "type":"Services"
        }
    ],
    "sg:phone":"+61 2 9787 3933",
    "sg:postcode":"2194",
    "sg:province":"NSW",
    "sg:tags":[
        "muffler",
        "exhaust",
        "system"
    ],
    "wof:name":"Midas Mufflers",
    "wof:placetype":"venue"
},
  "geometry": {"coordinates":[151.104141,-33.917278],"type":"Point"}
}