{
  "type": "Feature",
  "properties": {
    "addr:full":"18- 20 Intrepid St Berwick VIC 3806",
    "addr:housenumber":"20",
    "addr:postcode":"3806",
    "addr:street":"Intrepid St",
    "iso:country":"AU",
    "sg:address":"18- 20 Intrepid St",
    "sg:city":"Berwick",
    "sg:classifiers":[
        {
            "category":"Wholesale",
            "subcategory":"Metals & Minerals",
            "type":"Manufacturing & Wholesale Goods"
        }
    ],
    "sg:phone":"+61 3 9769 9799",
    "sg:postcode":"3806",
    "sg:province":"VIC",
    "sg:tags":[
        "steel",
        "merchant"
    ],
    "wof:name":"Bosanko Steel Pty Ltd",
    "wof:placetype":"venue"
},
  "geometry": {"coordinates":[145.338424683,-38.0372428894],"type":"Point"}
}