{
  "type": "Feature",
  "properties": {
    "addr:full":"162 Gray St Hamilton VIC 3300",
    "addr:housenumber":"162",
    "addr:postcode":"3300",
    "addr:street":"Gray St",
    "iso:country":"AU",
    "sg:address":"162 Gray St",
    "sg:city":"Hamilton",
    "sg:classifiers":[
        {
            "category":"Shopping",
            "subcategory":"Optical Goods",
            "type":"Retail Goods"
        }
    ],
    "sg:phone":"+61 3 5571 9799",
    "sg:postcode":"3300",
    "sg:province":"VIC",
    "sg:tags":[
        "dispenser",
        "prescription"
    ],
    "wof:name":"Eye Room The",
    "wof:placetype":"venue"
},
  "geometry": {"coordinates":[142.024932861,-37.7430381775],"type":"Point"}
}