{
  "type": "Feature",
  "properties": {
    "addr:full":"PO Box 1955 Geraldton Private Boxes WA 6531",
    "addr:postcode":"6531",
    "iso:country":"AU",
    "sg:address":"PO Box 1955",
    "sg:city":"Geraldton Private Boxes",
    "sg:classifiers":[
        {
            "category":"Professional",
            "subcategory":"Lawyer & Legal Services",
            "type":"Services"
        }
    ],
    "sg:phone":"+61 8 9965 4220",
    "sg:postcode":"6531",
    "sg:province":"WA",
    "sg:tags":[
        "process",
        "server"
    ],
    "wof:name":"Geraldton Legal Process Servers",
    "wof:placetype":"venue"
},
  "geometry": {"coordinates":[114.61126709,-28.7730693817],"type":"Point"}
}