{
  "type": "Feature",
  "properties": {
    "addr:full":"PO Box 4150 Ashmore Plaza QLD 4214",
    "addr:postcode":"4214",
    "iso:country":"AU",
    "sg:address":"PO Box 4150",
    "sg:city":"Ashmore Plaza",
    "sg:classifiers":[
        {
            "category":"Shopping",
            "subcategory":"Bicycles & Sporting Goods",
            "type":"Retail Goods"
        }
    ],
    "sg:phone":"+61 7 5574 4048",
    "sg:postcode":"4214",
    "sg:province":"QLD",
    "sg:tags":[
        "chemical",
        "equipment",
        "pool",
        "swimming"
    ],
    "wof:name":"Magic Pool Care",
    "wof:placetype":"venue"
},
  "geometry": {"coordinates":[153.35531616200001,-27.9640426636],"type":"Point"}
}