{
  "type": "Feature",
  "properties": {
    "addr:full":"Ilkley Rd Ilkley QLD 4554",
    "addr:postcode":"4554",
    "addr:street":"Ilkley Rd",
    "iso:country":"AU",
    "sg:address":"Ilkley Rd",
    "sg:city":"Ilkley",
    "sg:classifiers":[
        {
            "category":"Arena",
            "subcategory":"Horse Racetrack",
            "type":"Entertainment"
        }
    ],
    "sg:phone":"+61 7 5445 0308",
    "sg:postcode":"4554",
    "sg:province":"QLD",
    "sg:tags":[
        "retail",
        "swimwear"
    ],
    "wof:name":"Giyz Swimwear",
    "wof:placetype":"venue"
},
  "geometry": {"coordinates":[153.004196167,-26.7172203064],"type":"Point"}
}