{
  "type": "Feature",
  "properties": {
    "addr:full":"Level 19 644 Chapel St South Yarra VIC 3141",
    "addr:housenumber":"644",
    "addr:postcode":"3141",
    "addr:street":"Chapel St",
    "iso:country":"AU",
    "sg:address":"Level 19 644 Chapel St",
    "sg:city":"South Yarra",
    "sg:classifiers":[
        {
            "category":"Professional",
            "subcategory":"Employment Agencies",
            "type":"Services"
        }
    ],
    "sg:phone":"+61 3 8790 4499",
    "sg:postcode":"3141",
    "sg:province":"VIC",
    "wof:name":"Branton Mannix International Executive Search",
    "wof:placetype":"venue"
},
  "geometry": {"coordinates":[144.995925903,-37.838760376],"type":"Point"}
}