{
  "type": "Feature",
  "properties": {
    "addr:full":"PO Box 160 Wangaratta VIC 3676",
    "addr:postcode":"3676",
    "iso:country":"AU",
    "sg:address":"PO Box 160",
    "sg:city":"Wangaratta",
    "sg:classifiers":[
        {
            "category":"Banks & Credit Unions",
            "subcategory":"Financial Services",
            "type":"Services"
        }
    ],
    "sg:phone":"+61 3 5722 2820",
    "sg:postcode":"3676",
    "sg:province":"VIC",
    "sg:tags":[
        "loan",
        "finance",
        "mortgage"
    ],
    "wof:name":"Mortgage Finance Solutions",
    "wof:placetype":"venue"
},
  "geometry": {"coordinates":[146.32493600000001,-36.35371],"type":"Point"}
}