{
  "type": "Feature",
  "properties": {
    "addr:full":"Shop 2 11 Station St Cottesloe WA 6011",
    "addr:housenumber":"shop;11",
    "addr:postcode":"6011",
    "addr:street":"Station St",
    "iso:country":"AU",
    "sg:address":"Shop 2 11 Station St",
    "sg:city":"Cottesloe",
    "sg:classifiers":[
        {
            "category":"Social Services",
            "subcategory":"Child Care",
            "type":"Services"
        }
    ],
    "sg:phone":"+61 8 9284 5966",
    "sg:postcode":"6011",
    "sg:province":"WA",
    "sg:tags":[
        "equipment",
        "supply"
    ],
    "wof:name":"Windmill Educational P/L",
    "wof:placetype":"venue"
},
  "geometry": {"coordinates":[115.762420654,-31.9972248077],"type":"Point"}
}