{
  "type": "Feature",
  "properties": {
    "addr:full":"1/ 3 Barnett Pl Molendinar QLD 4214",
    "addr:housenumber":"/ 3",
    "addr:postcode":"4214",
    "addr:street":"Barnett Pl",
    "iso:country":"AU",
    "sg:address":"1/ 3 Barnett Pl",
    "sg:city":"Molendinar",
    "sg:classifiers":[
        {
            "category":"Professional",
            "subcategory":"Art Services",
            "type":"Services"
        }
    ],
    "sg:phone":"+61 7 5571 5055",
    "sg:postcode":"4214",
    "sg:province":"QLD",
    "sg:tags":[
        "interior",
        "decorator"
    ],
    "wof:name":"Living Worlds",
    "wof:placetype":"venue"
},
  "geometry": {"coordinates":[153.36111450199999,-27.9656066895],"type":"Point"}
}