{
  "type": "Feature",
  "properties": {
    "addr:full":"133 Alexander St Crows Nest NSW 2065",
    "addr:housenumber":"133",
    "addr:postcode":"2065",
    "addr:street":"Alexander St",
    "iso:country":"AU",
    "sg:address":"133 Alexander St",
    "sg:city":"Crows Nest",
    "sg:classifiers":[
        {
            "category":"Insurance",
            "subcategory":"Insurance Agent",
            "type":"Services"
        }
    ],
    "sg:phone":"+61 2 9906 8566",
    "sg:postcode":"2065",
    "sg:province":"NSW",
    "wof:name":"Roche T F & Associates Pty Ltd",
    "wof:placetype":"venue"
},
  "geometry": {"coordinates":[151.20291137699999,-33.8240013123],"type":"Point"}
}