{
  "type": "Feature",
  "properties": {
    "iso:country":"AU",
    "sg:address":"Suite 4B/ 20 Somerset Ave",
    "sg:city":"Narellan",
    "sg:classifiers":[
        {
            "category":"Banks & Credit Unions",
            "subcategory":"Investment Brokerage",
            "type":"Services"
        }
    ],
    "sg:phone":"+61 2 4648 1099",
    "sg:postcode":"2567",
    "sg:province":"NSW",
    "sg:tags":[
        "finance",
        "broker"
    ],
    "wof:name":"United Financial Services",
    "wof:placetype":"venue"
},
  "geometry": {"coordinates":[150.73936462399999,-34.0413322449],"type":"Point"}
}