{
  "type": "Feature",
  "properties": {
    "addr:full":"Lot 5 Old Bruce Hwy Woombye QLD 4559",
    "addr:postcode":"4559",
    "addr:street":"Old Bruce Hwy",
    "iso:country":"AU",
    "sg:address":"Lot 5 Old Bruce Hwy",
    "sg:city":"Woombye",
    "sg:classifiers":[
        {
            "category":"Train Station",
            "subcategory":"Rail",
            "type":"Transportation"
        }
    ],
    "sg:phone":"+61 7 5442 2102",
    "sg:postcode":"4559",
    "sg:province":"QLD",
    "sg:tags":[
        "marine",
        "engineer"
    ],
    "wof:name":"Mobile Marine Mechanic Electrician",
    "wof:placetype":"venue"
},
  "geometry": {"coordinates":[152.97456359899999,-26.6690292358],"type":"Point"}
}