{
  "type": "Feature",
  "properties": {
    "addr:full":"8 Flower Pl Melba ACT 2615",
    "addr:housenumber":"8",
    "addr:postcode":"2615",
    "addr:street":"Flower Pl Melba",
    "iso:country":"AU",
    "sg:address":"8 Flower Pl",
    "sg:city":"Melba",
    "sg:classifiers":[
        {
            "category":"Professional",
            "subcategory":"Management & Consulting",
            "type":"Services"
        }
    ],
    "sg:phone":"+61 2 6259 2799",
    "sg:postcode":"2615",
    "sg:province":"ACT",
    "sg:tags":[
        "consultant"
    ],
    "wof:name":"Moz Consulting",
    "wof:placetype":"venue"
},
  "geometry": {"coordinates":[149.05917358400001,-35.2048072815],"type":"Point"}
}