{
  "type": "Feature",
  "properties": {
    "addr:full":"1 Asling St Brighton VIC 3186",
    "addr:housenumber":"1",
    "addr:postcode":"3186",
    "addr:street":"Asling St",
    "iso:country":"AU",
    "sg:address":"1 Asling St",
    "sg:city":"Brighton",
    "sg:classifiers":[
        {
            "category":"Manufacturing",
            "subcategory":"Food",
            "type":"Manufacturing & Wholesale Goods"
        }
    ],
    "sg:phone":"+61 3 9593 2922",
    "sg:postcode":"3186",
    "sg:province":"VIC",
    "sg:tags":[
        "function",
        "catering"
    ],
    "wof:name":"Jill Murray Catering",
    "wof:placetype":"venue"
},
  "geometry": {"coordinates":[145.001785278,-37.9051628113],"type":"Point"}
}