{
  "type": "Feature",
  "properties": {
    "addr:full":"102 Coonong Rd Gymea Bay NSW 2227",
    "addr:housenumber":"102",
    "addr:postcode":"2227",
    "addr:street":"Coonong Rd",
    "iso:country":"AU",
    "sg:address":"102 Coonong Rd",
    "sg:city":"Gymea Bay",
    "sg:classifiers":[
        {
            "category":"Food & Beverages",
            "subcategory":"Supermarket",
            "type":"Retail Goods"
        }
    ],
    "sg:phone":"+61 2 9525 6593",
    "sg:postcode":"2227",
    "sg:province":"NSW",
    "sg:tags":[
        "grocery",
        "store"
    ],
    "wof:name":"Hijazi Four Square",
    "wof:placetype":"venue"
},
  "geometry": {"coordinates":[151.08372497600001,-34.0507392883],"type":"Point"}
}