{
  "type": "Feature",
  "properties": {
    "iso:country":"AU",
    "sg:address":"Suite 3 72 Simpson St",
    "sg:city":"Beerwah",
    "sg:classifiers":[
        {
            "category":"Health Services",
            "subcategory":"Doctor",
            "type":"Services"
        }
    ],
    "sg:phone":"+61 7 5494 0377",
    "sg:postcode":"4519",
    "sg:province":"QLD",
    "sg:tags":[
        "medical",
        "practitioner"
    ],
    "wof:name":"Ridgway Denzil",
    "wof:placetype":"venue"
},
  "geometry": {"coordinates":[152.957764,-26.858524],"type":"Point"}
}