{
  "type": "Feature",
  "properties": {
    "iso:country":"AU",
    "sg:address":"29 Bahloo Ave",
    "sg:city":"Mitchell Park",
    "sg:classifiers":[
        {
            "category":"Building & Trades",
            "subcategory":"Cleaning & Sanitation",
            "type":"Services"
        }
    ],
    "sg:phone":"+61 417 812 653",
    "sg:postcode":"5043",
    "sg:province":"SA",
    "sg:tags":[
        "cleaner",
        "repairer",
        "roof"
    ],
    "wof:name":"Silvano Tregambe Roof Restoration",
    "wof:placetype":"venue"
},
  "geometry": {"coordinates":[138.56488,-35.007267],"type":"Point"}
}