{
  "type": "Feature",
  "properties": {
    "addr:full":"Shop 5, 78 York St Gosford East NSW 2250",
    "addr:housenumber":"shop;78",
    "addr:postcode":"2250",
    "addr:street":"York St",
    "iso:country":"AU",
    "sg:address":"Shop 5, 78 York St",
    "sg:city":"Gosford East",
    "sg:classifiers":[
        {
            "category":"Health Services",
            "subcategory":"Optometrist",
            "type":"Services"
        }
    ],
    "sg:phone":"+61 2 4325 0328",
    "sg:postcode":"2250",
    "sg:province":"NSW",
    "wof:name":"ProVision Optometrists",
    "wof:placetype":"venue"
},
  "geometry": {"coordinates":[151.35252380399999,-33.4371376038],"type":"Point"}
}