{
  "type": "Feature",
  "properties": {
    "addr:full":"9 Cordia Pl Rivett ACT 2611",
    "addr:housenumber":"9",
    "addr:postcode":"2611",
    "addr:street":"Cordia Pl",
    "iso:country":"AU",
    "sg:address":"9 Cordia Pl",
    "sg:city":"Rivett",
    "sg:classifiers":[
        {
            "category":"Sports & Exercise",
            "subcategory":"Sports Center",
            "type":"Entertainment"
        }
    ],
    "sg:phone":"+61 2 6288 0483",
    "sg:postcode":"2611",
    "sg:province":"ACT",
    "sg:tags":[
        "card",
        "memorabilia"
    ],
    "wof:name":"Phoenix Collectables",
    "wof:placetype":"venue"
},
  "geometry": {"coordinates":[149.03526306099999,-35.3473625183],"type":"Point"}
}