{
  "type": "Feature",
  "properties": {
    "iso:country":"AU",
    "sg:address":"24 Anderson St",
    "sg:city":"Chifley",
    "sg:classifiers":[
        {
            "category":"Professional",
            "subcategory":"Management & Consulting",
            "type":"Services"
        }
    ],
    "sg:phone":"+61 2 6281 5417",
    "sg:postcode":"2606",
    "sg:province":"ACT",
    "sg:tags":[
        "consultant",
        "economic"
    ],
    "wof:name":"Dean Wallace & Associates Pty Ltd",
    "wof:placetype":"venue"
},
  "geometry": {"coordinates":[149.083129883,-35.3495063782],"type":"Point"}
}