{
  "type": "Feature",
  "properties": {
    "addr:full":"95- 103 Hyde Rd Yeronga QLD 4104",
    "addr:housenumber":"103",
    "addr:postcode":"4104",
    "addr:street":"95;Hyde Rd",
    "iso:country":"AU",
    "sg:address":"95- 103 Hyde Rd",
    "sg:city":"Yeronga",
    "sg:classifiers":[
        {
            "category":"Education",
            "subcategory":"Junior College",
            "type":"Public Place"
        }
    ],
    "sg:phone":"+61 7 3848 5855",
    "sg:postcode":"4104",
    "sg:province":"QLD",
    "sg:tags":[
        "wholesaler",
        "school",
        "mfrs",
        "uniform"
    ],
    "wof:name":"Trutex Pty Ltd",
    "wof:placetype":"venue"
},
  "geometry": {"coordinates":[153.014129639,-27.5112705231],"type":"Point"}
}