{
  "type": "Feature",
  "properties": {
    "addr:full":"Ground Floor, 169 Macquarie St Newcastle NSW 2300",
    "addr:housenumber":"169",
    "addr:postcode":"2300",
    "addr:street":"Macquarie St",
    "iso:country":"AU",
    "sg:address":"Ground Floor, 169 Macquarie St",
    "sg:city":"Newcastle",
    "sg:classifiers":[
        {
            "category":"Professional",
            "subcategory":"Employment Agencies",
            "type":"Services"
        }
    ],
    "sg:phone":"+61 413 629 002",
    "sg:postcode":"2300",
    "sg:province":"NSW",
    "sg:tags":[
        "hire",
        "labour",
        "contractor"
    ],
    "wof:name":"BDS Recruit",
    "wof:placetype":"venue"
},
  "geometry": {"coordinates":[151.73271199999999,-32.942581],"type":"Point"}
}