{
  "type": "Feature",
  "properties": {
    "addr:full":"32 Hudson Rd Albion QLD 4010",
    "addr:housenumber":"32",
    "addr:postcode":"4010",
    "addr:street":"Hudson Rd",
    "iso:country":"AU",
    "sg:address":"32 Hudson Rd",
    "sg:city":"Albion",
    "sg:classifiers":[
        {
            "category":"Retail",
            "subcategory":"Car Wash",
            "type":"Services"
        }
    ],
    "sg:phone":"+61 400 772 627",
    "sg:postcode":"4010",
    "sg:province":"QLD",
    "sg:tags":[
        "truck",
        "cleaning"
    ],
    "wof:name":"Pro-Glaze Automotive",
    "wof:placetype":"venue"
},
  "geometry": {"coordinates":[153.04112243599999,-27.431055069],"type":"Point"}
}