{
  "type": "Feature",
  "properties": {
    "addr:full":"U10/ 254 Kingsgrove Rd Kingsgrove NSW 2208",
    "addr:postcode":"2208",
    "addr:street":"/ 254 Kingsgrove Rd",
    "iso:country":"AU",
    "sg:address":"U10/ 254 Kingsgrove Rd",
    "sg:city":"Kingsgrove",
    "sg:classifiers":[
        {
            "category":"Personal",
            "subcategory":"Beauty Salon",
            "type":"Services"
        }
    ],
    "sg:phone":"+61 2 9150 9689",
    "sg:postcode":"2208",
    "sg:province":"NSW",
    "wof:name":"Tiny Nail & Beauty",
    "wof:placetype":"venue"
},
  "geometry": {"coordinates":[151.101395,-33.941463],"type":"Point"}
}