{
  "type": "Feature",
  "properties": {
    "addr:full":"90 Calder Rd Rydalmere NSW 2116",
    "addr:housenumber":"90",
    "addr:postcode":"2116",
    "addr:street":"Calder Rd",
    "iso:country":"AU",
    "sg:address":"90 Calder Rd",
    "sg:city":"Rydalmere",
    "sg:classifiers":[
        {
            "category":"Professional",
            "subcategory":"Detective & Security Services",
            "type":"Services"
        }
    ],
    "sg:phone":"+61 1300 138 890",
    "sg:postcode":"2116",
    "sg:province":"NSW",
    "sg:tags":[
        "consultant",
        "system"
    ],
    "wof:name":"Alarm-Ace",
    "wof:placetype":"venue"
},
  "geometry": {"coordinates":[151.03010559099999,-33.8107376099],"type":"Point"}
}