{
  "type": "Feature",
  "properties": {
    "addr:full":"1st Floor 373 Lonsdale St Dandenong VIC 3175",
    "addr:housenumber":"373",
    "addr:postcode":"3175",
    "addr:street":"Lonsdale St",
    "iso:country":"AU",
    "sg:address":"1st Floor 373 Lonsdale St",
    "sg:city":"Dandenong",
    "sg:classifiers":[
        {
            "category":"Professional",
            "subcategory":"Accounting & Tax Preparation",
            "type":"Services"
        }
    ],
    "sg:phone":"+61 3 9791 8997",
    "sg:postcode":"3175",
    "sg:province":"VIC",
    "sg:tags":[
        "consultant",
        "taxation"
    ],
    "wof:name":"Goldberg Leon",
    "wof:placetype":"venue"
},
  "geometry": {"coordinates":[145.213790894,-37.9849739075],"type":"Point"}
}