{
  "type": "Feature",
  "properties": {
    "addr:full":"58 Wentworth St Glen Innes NSW 2370",
    "addr:housenumber":"58",
    "addr:postcode":"2370",
    "addr:street":"Wentworth St",
    "iso:country":"AU",
    "sg:address":"58 Wentworth St",
    "sg:city":"Glen Innes",
    "sg:classifiers":[
        {
            "category":"Food & Beverages",
            "subcategory":"Groceries & Convenience Stores",
            "type":"Retail Goods"
        }
    ],
    "sg:phone":"+61 2 6732 2003",
    "sg:postcode":"2370",
    "sg:province":"NSW",
    "wof:name":"Station Store",
    "wof:placetype":"venue"
},
  "geometry": {"coordinates":[151.73013305699999,-29.7403736115],"type":"Point"}
}