{
  "type": "Feature",
  "properties": {
    "addr:full":"672 Diddillibah Rd Woombye QLD 4559",
    "addr:housenumber":"672",
    "addr:postcode":"4559",
    "addr:street":"Diddillibah Rd",
    "iso:country":"AU",
    "sg:address":"672 Diddillibah Rd",
    "sg:city":"Woombye",
    "sg:classifiers":[
        {
            "category":"Professional",
            "subcategory":"Detective & Security Services",
            "type":"Services"
        }
    ],
    "sg:phone":"+61 7 5448 5211",
    "sg:postcode":"4559",
    "sg:province":"QLD",
    "sg:tags":[
        "equipment",
        "window",
        "doors"
    ],
    "wof:name":"Gray Robert",
    "wof:placetype":"venue"
},
  "geometry": {"coordinates":[153.025558472,-26.6470756531],"type":"Point"}
}