{
  "type": "Feature",
  "properties": {
    "iso:country":"AU",
    "sg:address":"''Rowes Lagoon'' 6332 Federal Highway",
    "sg:city":"Goulburn",
    "sg:classifiers":[
        {
            "category":"Retail",
            "subcategory":"Veterinary Services",
            "type":"Services"
        }
    ],
    "sg:phone":"+61 2 4848 0023",
    "sg:postcode":"2580",
    "sg:province":"NSW",
    "sg:tags":[
        "surgeon"
    ],
    "wof:name":"Ian Nielsen & Associates Equine Veterinary Centre",
    "wof:placetype":"venue"
},
  "geometry": {"coordinates":[149.59776306099999,-34.8221206665],"type":"Point"}
}