{
  "type": "Feature",
  "properties": {
    "addr:full":"14 Margaret St Bremer Bay WA 6338",
    "addr:housenumber":"14",
    "addr:postcode":"6338",
    "addr:street":"Margaret St",
    "iso:country":"AU",
    "sg:address":"14 Margaret St",
    "sg:city":"Bremer Bay",
    "sg:classifiers":[
        {
            "category":"Shopping",
            "type":"Retail Goods"
        }
    ],
    "sg:phone":"+61 8 9837 4177",
    "sg:postcode":"6338",
    "sg:province":"WA",
    "sg:tags":[
        "agent",
        "stock"
    ],
    "wof:name":"Wesfarmers CSBP Limited",
    "wof:placetype":"venue"
},
  "geometry": {"coordinates":[119.378761291,-34.3879852295],"type":"Point"}
}