{
  "type": "Feature",
  "properties": {
    "iso:country":"AU",
    "sg:address":"Suite 3/307- 317 Condamine St",
    "sg:city":"Manly Vale",
    "sg:classifiers":[
        {
            "category":"Health Services",
            "subcategory":"Chiropractor",
            "type":"Services"
        }
    ],
    "sg:phone":"+61 2 9907 7139",
    "sg:postcode":"2093",
    "sg:province":"NSW",
    "wof:name":"Chiropractic Solutions",
    "wof:placetype":"venue"
},
  "geometry": {"coordinates":[151.26705932600001,-33.7841796875],"type":"Point"}
}