{
  "type": "Feature",
  "properties": {
    "iso:country":"AU",
    "sg:address":"32 Bowden St",
    "sg:city":"Alexandria",
    "sg:classifiers":[
        {
            "category":"Professional",
            "subcategory":"Computer Services",
            "type":"Services"
        }
    ],
    "sg:phone":"+61 2 8303 6800",
    "sg:postcode":"2015",
    "sg:province":"NSW",
    "sg:tags":[
        "package",
        "software"
    ],
    "wof:name":"Atari Asia Pacific",
    "wof:placetype":"venue"
},
  "geometry": {"coordinates":[151.197753906,-33.9059181213],"type":"Point"}
}