{
  "type": "Feature",
  "properties": {
    "iso:country":"AU",
    "sg:address":"21 Charlescotte Ave",
    "sg:city":"Punchbowl",
    "sg:classifiers":[
        {
            "category":"Manufacturing",
            "subcategory":"Food",
            "type":"Manufacturing & Wholesale Goods"
        }
    ],
    "sg:phone":"+61 2 9750 6931",
    "sg:postcode":"2196",
    "sg:province":"NSW",
    "sg:tags":[
        "product",
        "nut",
        "edible"
    ],
    "wof:name":"Happy Nut Pty Ltd The",
    "wof:placetype":"venue"
},
  "geometry": {"coordinates":[151.056702,-33.932949],"type":"Point"}
}