{
  "type": "Feature",
  "properties": {
    "addr:full":"711 Don Rd Healesville VIC 3777",
    "addr:housenumber":"711",
    "addr:postcode":"3777",
    "addr:street":"Don Rd",
    "iso:country":"AU",
    "sg:address":"711 Don Rd",
    "sg:city":"Healesville",
    "sg:classifiers":[
        {
            "category":"Personal",
            "subcategory":"Beauty Salon",
            "type":"Services"
        }
    ],
    "sg:phone":"+61 3 5962 2797",
    "sg:postcode":"3777",
    "sg:province":"VIC",
    "sg:tags":[
        "hairdresser"
    ],
    "wof:name":"Piaf Salon",
    "wof:placetype":"venue"
},
  "geometry": {"coordinates":[145.523132,-37.650936],"type":"Point"}
}