{
  "type": "Feature",
  "properties": {
    "iso:country":"AU",
    "sg:address":"1/ 9 Peace St",
    "sg:city":"Mackay",
    "sg:classifiers":[
        {
            "category":"Home & Garden",
            "subcategory":"Hardware",
            "type":"Retail Goods"
        }
    ],
    "sg:phone":"+61 7 4952 3737",
    "sg:postcode":"4740",
    "sg:province":"QLD",
    "sg:tags":[
        "supply",
        "maker",
        "cabinet"
    ],
    "wof:name":"Lincoln Sentry",
    "wof:placetype":"venue"
},
  "geometry": {"coordinates":[149.172653,-21.172089],"type":"Point"}
}