{
  "type": "Feature",
  "properties": {
    "addr:full":"8 Lanceley Pl Artarmon NSW 2064",
    "addr:housenumber":"8",
    "addr:postcode":"2064",
    "addr:street":"Lanceley Pl",
    "iso:country":"AU",
    "sg:address":"8 Lanceley Pl",
    "sg:city":"Artarmon",
    "sg:classifiers":[
        {
            "category":"Shopping",
            "subcategory":"Party Supplies",
            "type":"Retail Goods"
        }
    ],
    "sg:phone":"+61 2 8333 5757",
    "sg:postcode":"2064",
    "sg:province":"NSW",
    "sg:tags":[
        "hire",
        "costume"
    ],
    "wof:name":"ABC Costumes",
    "wof:placetype":"venue"
},
  "geometry": {"coordinates":[151.186477661,-33.8178672791],"type":"Point"}
}