{
  "type": "Feature",
  "properties": {
    "addr:full":"119 Eggleston Crs Chifley ACT 2606",
    "addr:housenumber":"119",
    "addr:postcode":"2606",
    "addr:street":"Eggleston Crs",
    "iso:country":"AU",
    "sg:address":"119 Eggleston Crs",
    "sg:city":"Chifley",
    "sg:classifiers":[
        {
            "category":"Personal",
            "subcategory":"Massage",
            "type":"Services"
        }
    ],
    "sg:phone":"+61 2 6281 6181",
    "sg:postcode":"2606",
    "sg:province":"ACT",
    "sg:tags":[
        "therapy"
    ],
    "wof:name":"Holistic Therapies of Canberra",
    "wof:placetype":"venue"
},
  "geometry": {"coordinates":[149.07546997099999,-35.3525009155],"type":"Point"}
}