{
  "type": "Feature",
  "properties": {
    "iso:country":"AU",
    "sg:address":"1806 Pelverata Rd",
    "sg:city":"Upper Woodstock",
    "sg:classifiers":[
        {
            "category":"Farming",
            "subcategory":"Livestock Farm",
            "type":"Manufacturing & Wholesale Goods"
        }
    ],
    "sg:phone":"+61 3 6266 3866",
    "sg:postcode":"7150",
    "sg:province":"TAS",
    "sg:tags":[
        "breeder",
        "horse",
        "stud"
    ],
    "wof:name":"Carnegie Clydesdale Stud",
    "wof:placetype":"venue"
},
  "geometry": {"coordinates":[147.068237305,-43.0757675171],"type":"Point"}
}