{
  "type": "Feature",
  "properties": {
    "addr:full":"757 Anzac Pde Maroubra NSW 2035",
    "addr:housenumber":"757",
    "addr:postcode":"2035",
    "addr:street":"Anzac Pde",
    "iso:country":"AU",
    "sg:address":"757 Anzac Pde",
    "sg:city":"Maroubra",
    "sg:classifiers":[
        {
            "category":"Fast Food",
            "type":"Food & Drink"
        }
    ],
    "sg:phone":"+61 2 9344 0967",
    "sg:postcode":"2035",
    "sg:province":"NSW",
    "sg:tags":[
        "away",
        "take"
    ],
    "wof:name":"McDonald's Family Restaurants",
    "wof:placetype":"venue"
},
  "geometry": {"coordinates":[151.239135742,-33.942237854],"type":"Point"}
}