{
  "type": "Feature",
  "properties": {
    "iso:country":"AU",
    "sg:address":"Bankstown Airport 611 Tower Rd",
    "sg:city":"Bankstown",
    "sg:classifiers":[
        {
            "category":"Wholesale",
            "subcategory":"Furniture",
            "type":"Manufacturing & Wholesale Goods"
        }
    ],
    "sg:phone":"+61 2 9791 9555",
    "sg:postcode":"2200",
    "sg:province":"NSW",
    "sg:tags":[
        "wholesaler",
        "mfrs"
    ],
    "wof:name":"Sofas International",
    "wof:placetype":"venue"
},
  "geometry": {"coordinates":[150.981369,-33.918217],"type":"Point"}
}