{
  "type": "Feature",
  "properties": {
    "addr:full":"6 River Valley Rd Woorree WA 6530",
    "addr:housenumber":"6",
    "addr:postcode":"6530",
    "addr:street":"River Valley Rd",
    "iso:country":"AU",
    "sg:address":"6 River Valley Rd",
    "sg:city":"Woorree",
    "sg:classifiers":[
        {
            "category":"Building & Trades",
            "subcategory":"Construction",
            "type":"Services"
        }
    ],
    "sg:phone":"+61 419 904 165",
    "sg:postcode":"6530",
    "sg:province":"WA",
    "sg:tags":[
        "contractor"
    ],
    "wof:name":"Jones L R & B J",
    "wof:placetype":"venue"
},
  "geometry": {"coordinates":[114.653701782,-28.7582626343],"type":"Point"}
}