{
  "type": "Feature",
  "properties": {
    "iso:country":"AU",
    "sg:address":"Lot 1 Flora Ave",
    "sg:city":"Cabarita",
    "sg:classifiers":[
        {
            "category":"Home & Garden",
            "subcategory":"Building Materials",
            "type":"Retail Goods"
        }
    ],
    "sg:phone":"+61 3 5025 2507",
    "sg:postcode":"3505",
    "sg:province":"VIC",
    "sg:tags":[
        "lawn",
        "cutting",
        "maintenance"
    ],
    "wof:name":"Petes & Lyns Lawnmowing",
    "wof:placetype":"venue"
},
  "geometry": {"coordinates":[142.08479309099999,-34.2085037231],"type":"Point"}
}