{
  "type": "Feature",
  "properties": {
    "addr:full":"3 Spring St Chatswood NSW 2067",
    "addr:housenumber":"3",
    "addr:postcode":"2067",
    "addr:street":"Spring St",
    "iso:country":"AU",
    "sg:address":"3 Spring St",
    "sg:city":"Chatswood",
    "sg:classifiers":[
        {
            "category":"Health Services",
            "subcategory":"Health Practitioner",
            "type":"Services"
        }
    ],
    "sg:phone":"+61 2 9456 5599",
    "sg:postcode":"2067",
    "sg:province":"NSW",
    "sg:tags":[
        "hypnotherapy"
    ],
    "wof:name":"PSH Therapy Centre",
    "wof:placetype":"venue"
},
  "geometry": {"coordinates":[151.18513488799999,-33.7970695496],"type":"Point"}
}