{
  "type": "Feature",
  "properties": {
    "iso:country":"AU",
    "sg:address":"72d Tabrett St",
    "sg:city":"Banksia",
    "sg:classifiers":[
        {
            "category":"Building & Trades",
            "subcategory":"Pest Control",
            "type":"Services"
        }
    ],
    "sg:phone":"+61 2 9556 3302",
    "sg:postcode":"2216",
    "sg:province":"NSW",
    "wof:name":"Fumigate All Hours Co Pty Ltd",
    "wof:placetype":"venue"
},
  "geometry": {"coordinates":[151.146027,-33.94672],"type":"Point"}
}