{
  "type": "Feature",
  "properties": {
    "addr:full":"43-53 Elizabeth St Melbourne VIC 3000",
    "addr:housenumber":"43-53",
    "addr:postcode":"3000",
    "addr:street":"Elizabeth St",
    "iso:country":"AU",
    "sg:address":"43-53 Elizabeth St",
    "sg:city":"Melbourne",
    "sg:classifiers":[
        {
            "category":"Education",
            "subcategory":"Dance Studio",
            "type":"Public Place"
        }
    ],
    "sg:phone":"+61 3 9629 9966",
    "sg:postcode":"3000",
    "sg:province":"VIC",
    "sg:tags":[
        "instruction",
        "language"
    ],
    "wof:name":"Melbourne Language Centre",
    "wof:placetype":"venue"
},
  "geometry": {"coordinates":[144.964233398,-37.8169059753],"type":"Point"}
}