{
  "type": "Feature",
  "properties": {
    "addr:full":"Unit 2, 43 Lara Way Campbellfield VIC 3061",
    "addr:housenumber":"43",
    "addr:postcode":"3061",
    "addr:street":"Lara Way",
    "iso:country":"AU",
    "sg:address":"Unit 2, 43 Lara Way",
    "sg:city":"Campbellfield",
    "sg:classifiers":[
        {
            "category":"Government",
            "subcategory":"Fire Station",
            "type":"Public Place"
        }
    ],
    "sg:phone":"+61 13 19 50",
    "sg:postcode":"3061",
    "sg:province":"VIC",
    "sg:tags":[
        "equipment",
        "protection",
        "consultant"
    ],
    "wof:name":"FMS Fire Protection Services",
    "wof:placetype":"venue"
},
  "geometry": {"coordinates":[144.96807861299999,-37.6604652405],"type":"Point"}
}