{
  "type": "Feature",
  "properties": {
    "addr:full":"Tenth St Harvey WA 6220",
    "addr:postcode":"6220",
    "addr:street":"Tenth St",
    "iso:country":"AU",
    "sg:address":"Tenth St",
    "sg:city":"Harvey",
    "sg:classifiers":[
        {
            "category":"Home & Garden",
            "subcategory":"Building Materials",
            "type":"Retail Goods"
        }
    ],
    "sg:phone":"+61 8 9729 1616",
    "sg:postcode":"6220",
    "sg:province":"WA",
    "sg:tags":[
        "lawn",
        "cutting",
        "maintenance"
    ],
    "wof:name":"Daves Lawn & Garden",
    "wof:placetype":"venue"
},
  "geometry": {"coordinates":[115.858261,-33.070435],"type":"Point"}
}