{
  "type": "Feature",
  "properties": {
    "addr:full":"Shed1/ 120 Raglan St Roma QLD 4455",
    "addr:housenumber":"120",
    "addr:postcode":"4455",
    "addr:street":"Raglan St",
    "iso:country":"AU",
    "sg:address":"Shed1/ 120 Raglan St",
    "sg:city":"Roma",
    "sg:classifiers":[
        {
            "category":"Manufacturing",
            "subcategory":"Tools & Machinery",
            "type":"Manufacturing & Wholesale Goods"
        }
    ],
    "sg:phone":"+61 7 4622 7544",
    "sg:postcode":"4455",
    "sg:province":"QLD",
    "wof:name":"Roma Tools & Industrial Supplies",
    "wof:placetype":"venue"
},
  "geometry": {"coordinates":[148.784103394,-26.581073761],"type":"Point"}
}