{
  "type": "Feature",
  "properties": {
    "iso:country":"AU",
    "sg:address":"1096 High St",
    "sg:city":"Armadale",
    "sg:classifiers":[
        {
            "category":"Personal",
            "subcategory":"Beauty Salon",
            "type":"Services"
        }
    ],
    "sg:phone":"+61 3 9509 7650",
    "sg:postcode":"3143",
    "sg:province":"VIC",
    "wof:name":"Ella Bache Armadale",
    "wof:placetype":"venue"
},
  "geometry": {"coordinates":[145.02377319300001,-37.8560066223],"type":"Point"}
}