{
  "type": "Feature",
  "properties": {
    "addr:full":"11 Connemara Crt Kelso QLD 4815",
    "addr:housenumber":"11",
    "addr:postcode":"4815",
    "addr:street":"Connemara Crt",
    "iso:country":"AU",
    "sg:address":"11 Connemara Crt",
    "sg:city":"Kelso",
    "sg:classifiers":[
        {
            "category":"Building & Trades",
            "subcategory":"Construction",
            "type":"Services"
        }
    ],
    "sg:phone":"+61 7 4774 0795",
    "sg:postcode":"4815",
    "sg:province":"QLD",
    "sg:tags":[
        "road",
        "contractor"
    ],
    "wof:name":"Caton Construction Co Pty Ltd",
    "wof:placetype":"venue"
},
  "geometry": {"coordinates":[146.720123,-19.386501],"type":"Point"}
}