{
  "type": "Feature",
  "properties": {
    "addr:full":"19 Emlyn St Coorparoo QLD 4151",
    "addr:housenumber":"19",
    "addr:postcode":"4151",
    "addr:street":"Emlyn St",
    "iso:country":"AU",
    "sg:address":"19 Emlyn St",
    "sg:city":"Coorparoo",
    "sg:classifiers":[
        {
            "category":"Health Services",
            "subcategory":"Dentist",
            "type":"Services"
        }
    ],
    "sg:phone":"+61 7 3244 2456",
    "sg:postcode":"4151",
    "sg:province":"QLD",
    "sg:tags":[
        "prosthodontist"
    ],
    "wof:name":"Russell Peter",
    "wof:placetype":"venue"
},
  "geometry": {"coordinates":[153.060546875,-27.5014801025],"type":"Point"}
}