{
  "type": "Feature",
  "properties": {
    "iso:country":"AU",
    "sg:address":"Unit 10 Pegasus Centre, 42 Bundall Rd",
    "sg:city":"Bundall",
    "sg:classifiers":[
        {
            "category":"Professional",
            "subcategory":"Accounting & Tax Preparation",
            "type":"Services"
        }
    ],
    "sg:phone":"+61 7 5592 3644",
    "sg:postcode":"4217",
    "sg:province":"QLD",
    "sg:tags":[
        "consultant",
        "taxation"
    ],
    "sg:website":"http://www.walshaccountants.com",
    "wof:name":"Walsh & Walsh Chartered Accountants",
    "wof:placetype":"venue"
},
  "geometry": {"coordinates":[153.41049194300001,-27.9702701569],"type":"Point"}
}