{
  "type": "Feature",
  "properties": {
    "addr:full":"18 Swanbourne Drv Northgate SA 5085",
    "addr:housenumber":"18",
    "addr:postcode":"5085",
    "addr:street":"Swanbourne Drv",
    "iso:country":"AU",
    "sg:address":"18 Swanbourne Drv",
    "sg:city":"Northgate",
    "sg:classifiers":[
        {
            "category":"Retail",
            "subcategory":"Driving School",
            "type":"Services"
        }
    ],
    "sg:phone":"+61 8 8369 3506",
    "sg:postcode":"5085",
    "sg:province":"SA",
    "wof:name":"School Of Professional Motoring",
    "wof:placetype":"venue"
},
  "geometry": {"coordinates":[138.63130188,-34.8492698669],"type":"Point"}
}