{
  "type": "Feature",
  "properties": {
    "iso:country":"AU",
    "sg:address":"U6a/ 101 Newmarket Rd",
    "sg:city":"Windsor",
    "sg:classifiers":[
        {
            "category":"Utilities",
            "subcategory":"Cable",
            "type":"Services"
        }
    ],
    "sg:phone":"+61 7 3359 3233",
    "sg:postcode":"4030",
    "sg:province":"QLD",
    "sg:tags":[
        "equipment",
        "meters"
    ],
    "wof:name":"AMRS (Aust) Pty Ltd",
    "wof:placetype":"venue"
},
  "geometry": {"coordinates":[153.024719,-27.436983],"type":"Point"}
}