{
  "type": "Feature",
  "properties": {
    "iso:country":"AU",
    "sg:address":"71 Hardiman St",
    "sg:city":"Kensington",
    "sg:classifiers":[
        {
            "category":"Home & Garden",
            "subcategory":"Furniture",
            "type":"Retail Goods"
        }
    ],
    "sg:phone":"+61 3 9671 3900",
    "sg:postcode":"3031",
    "sg:province":"VIC",
    "sg:tags":[
        "business"
    ],
    "wof:name":"Ridley Office Furnishers",
    "wof:placetype":"venue"
},
  "geometry": {"coordinates":[144.934998,-37.795692],"type":"Point"}
}