{
  "type": "Feature",
  "properties": {
    "iso:country":"AU",
    "sg:address":"Eltham Health Foods 929 Main Rd",
    "sg:city":"Eltham",
    "sg:classifiers":[
        {
            "category":"Health Services",
            "subcategory":"Health Practitioner",
            "type":"Services"
        }
    ],
    "sg:phone":"+61 3 9439 8693",
    "sg:postcode":"3095",
    "sg:province":"VIC",
    "sg:tags":[
        "acupuncture"
    ],
    "wof:name":"Michael Hook",
    "wof:placetype":"venue"
},
  "geometry": {"coordinates":[145.14805602999999,-37.7144966125],"type":"Point"}
}