{
  "type": "Feature",
  "properties": {
    "addr:full":"Suite 1/ 14 Arthur St Coffs Harbour NSW 2450",
    "addr:housenumber":"14",
    "addr:postcode":"2450",
    "addr:street":"Arthur St",
    "iso:country":"AU",
    "sg:address":"Suite 1/ 14 Arthur St",
    "sg:city":"Coffs Harbour",
    "sg:classifiers":[
        {
            "category":"Health Services",
            "subcategory":"Doctor",
            "type":"Services"
        }
    ],
    "sg:phone":"+61 2 6652 9822",
    "sg:postcode":"2450",
    "sg:province":"NSW",
    "sg:tags":[
        "medical",
        "practitioner"
    ],
    "wof:name":"Midnorth Coast Arthritis Clinic",
    "wof:placetype":"venue"
},
  "geometry": {"coordinates":[153.13313299999999,-30.281242],"type":"Point"}
}