{
  "type": "Feature",
  "properties": {
    "addr:full":"Cnr Glenmorris & Kensington Sts Bundaberg QLD 4670",
    "addr:postcode":"4670",
    "addr:street":"Cnr",
    "iso:country":"AU",
    "sg:address":"Cnr Glenmorris & Kensington Sts",
    "sg:city":"Bundaberg",
    "sg:classifiers":[
        {
            "category":"Manufacturing",
            "subcategory":"Glass & Minerals",
            "type":"Manufacturing & Wholesale Goods"
        }
    ],
    "sg:phone":"+61 7 4151 5673",
    "sg:postcode":"4670",
    "sg:province":"QLD",
    "sg:tags":[
        "stained"
    ],
    "wof:name":"Glass Art Studio",
    "wof:placetype":"venue"
},
  "geometry": {"coordinates":[152.34687805199999,-24.8806591034],"type":"Point"}
}