{
  "type": "Feature",
  "properties": {
    "addr:full":"4 Park Drv Bundoora VIC 3083",
    "addr:housenumber":"4",
    "addr:postcode":"3083",
    "addr:street":"Park Drv",
    "iso:country":"AU",
    "sg:address":"4 Park Drv",
    "sg:city":"Bundoora",
    "sg:classifiers":[
        {
            "category":"Professional",
            "subcategory":"Computer Services",
            "type":"Services"
        }
    ],
    "sg:phone":"+61 3 9459 2722",
    "sg:postcode":"3083",
    "sg:province":"VIC",
    "sg:tags":[
        "information"
    ],
    "wof:name":"Caval Ltd",
    "wof:placetype":"venue"
},
  "geometry": {"coordinates":[145.029006958,-37.7143135071],"type":"Point"}
}