{
  "type": "Feature",
  "properties": {
    "iso:country":"AU",
    "sg:address":"Shp8a/ 250 Tottenham St",
    "sg:city":"Woolloongabba",
    "sg:classifiers":[
        {
            "category":"Personal",
            "subcategory":"Nail Salon",
            "type":"Services"
        }
    ],
    "sg:phone":"+61 7 3391 1525",
    "sg:postcode":"4102",
    "sg:province":"QLD",
    "sg:tags":[
        "artificial"
    ],
    "wof:name":"New York Nails",
    "wof:placetype":"venue"
},
  "geometry": {"coordinates":[153.03593444800001,-27.500043869],"type":"Point"}
}