{
  "type": "Feature",
  "properties": {
    "addr:full":"Unit 2, 56 Lavarack Ave Eagle Farm QLD 4009",
    "addr:housenumber":"56",
    "addr:postcode":"4009",
    "addr:street":"Lavarack Ave",
    "iso:country":"AU",
    "sg:address":"Unit 2, 56 Lavarack Ave",
    "sg:city":"Eagle Farm",
    "sg:classifiers":[
        {
            "category":"Autos & Motor Vehicles",
            "subcategory":"Auto Supplies",
            "type":"Retail Goods"
        }
    ],
    "sg:phone":"+61 7 3861 7777",
    "sg:postcode":"4009",
    "sg:province":"QLD",
    "sg:tags":[
        "electric"
    ],
    "wof:name":"Hyundai",
    "wof:placetype":"venue"
},
  "geometry": {"coordinates":[153.09471130399999,-27.4323177338],"type":"Point"}
}