{
  "type": "Feature",
  "properties": {
    "iso:country":"AU",
    "sg:address":"32 Cocos Drv",
    "sg:city":"Bibra Lake",
    "sg:classifiers":[
        {
            "category":"Manufacturing",
            "subcategory":"Metals",
            "type":"Manufacturing & Wholesale Goods"
        }
    ],
    "sg:phone":"+61 8 9418 6352",
    "sg:postcode":"6163",
    "sg:province":"WA",
    "sg:tags":[
        "steel",
        "fabricator",
        "mfrs"
    ],
    "wof:name":"Perna Engineering & Crane Hire",
    "wof:placetype":"venue"
},
  "geometry": {"coordinates":[115.815048,-32.11034],"type":"Point"}
}