{
  "type": "Feature",
  "properties": {
    "iso:country":"AU",
    "sg:address":"Epping Plaza Cnr Cooper & High St",
    "sg:city":"Epping",
    "sg:classifiers":[
        {
            "category":"Travel",
            "subcategory":"Hotels & Motels",
            "type":"Entertainment"
        }
    ],
    "sg:phone":"+61 3 9408 9309",
    "sg:postcode":"3076",
    "sg:province":"VIC",
    "sg:tags":[
        "accommodation"
    ],
    "wof:name":"Epping Plaza Hotel",
    "wof:placetype":"venue"
},
  "geometry": {"coordinates":[145.009490967,-37.6383590698],"type":"Point"}
}