{
  "type": "Feature",
  "properties": {
    "addr:full":"50 Sheffield Rd Welshpool WA 6106",
    "addr:housenumber":"50",
    "addr:postcode":"6106",
    "addr:street":"Sheffield Rd",
    "iso:country":"AU",
    "sg:address":"50 Sheffield Rd",
    "sg:city":"Welshpool",
    "sg:classifiers":[
        {
            "category":"Real Estate",
            "subcategory":"Architect",
            "type":"Services"
        }
    ],
    "sg:phone":"+61 8 9350 5455",
    "sg:postcode":"6106",
    "sg:province":"WA",
    "sg:tags":[
        "raw",
        "material",
        "plastic"
    ],
    "wof:name":"Amtrade International Pty Ltd",
    "wof:placetype":"venue"
},
  "geometry": {"coordinates":[115.975341797,-31.9957370758],"type":"Point"}
}