{
  "type": "Feature",
  "properties": {
    "addr:full":"137 Jells Rd Wheelers Hill VIC 3150",
    "addr:housenumber":"137",
    "addr:postcode":"3150",
    "addr:street":"Jells Rd",
    "iso:country":"AU",
    "sg:address":"137 Jells Rd",
    "sg:city":"Wheelers Hill",
    "sg:classifiers":[
        {
            "category":"Building & Trades",
            "subcategory":"Construction",
            "type":"Services"
        }
    ],
    "sg:phone":"+61 3 9562 1184",
    "sg:postcode":"3150",
    "sg:province":"VIC",
    "sg:tags":[
        "contractor"
    ],
    "wof:name":"Kingswood Constructions",
    "wof:placetype":"venue"
},
  "geometry": {"coordinates":[145.18910217300001,-37.9057197571],"type":"Point"}
}