{
  "type": "Feature",
  "properties": {
    "addr:full":"29 Harold St Wendouree VIC 3355",
    "addr:housenumber":"29",
    "addr:postcode":"3355",
    "addr:street":"Harold St",
    "iso:country":"AU",
    "sg:address":"29 Harold St",
    "sg:city":"Wendouree",
    "sg:classifiers":[
        {
            "category":"Personal",
            "subcategory":"Beauty Salon",
            "type":"Services"
        }
    ],
    "sg:phone":"+61 3 5339 2518",
    "sg:postcode":"3355",
    "sg:province":"VIC",
    "sg:tags":[
        "hairdresser"
    ],
    "wof:name":"Salon 29",
    "wof:placetype":"venue"
},
  "geometry": {"coordinates":[143.83166499999999,-37.530182],"type":"Point"}
}