{
  "type": "Feature",
  "properties": {
    "addr:full":"14 Beresford Rd Yarrawonga NT 0830",
    "addr:housenumber":"14",
    "addr:postcode":"nt 0830",
    "addr:street":"Beresford Rd",
    "iso:country":"AU",
    "sg:address":"14 Beresford Rd",
    "sg:city":"Yarrawonga",
    "sg:classifiers":[
        {
            "category":"Manufacturing",
            "subcategory":"Tools & Machinery",
            "type":"Manufacturing & Wholesale Goods"
        }
    ],
    "sg:phone":"+61 439 200 713",
    "sg:postcode":"0830",
    "sg:province":"NT",
    "sg:tags":[
        "earth",
        "excavating",
        "moving",
        "equipment"
    ],
    "wof:name":"Sherrin Equipment",
    "wof:placetype":"venue"
},
  "geometry": {"coordinates":[130.987167,-12.473823],"type":"Point"}
}