{
  "type": "Feature",
  "properties": {
    "iso:country":"AU",
    "sg:address":"176 High St",
    "sg:city":"Preston",
    "sg:classifiers":[
        {
            "category":"Shopping",
            "subcategory":"Mobile Phones",
            "type":"Retail Goods"
        }
    ],
    "sg:phone":"+61 3 9480 0081",
    "sg:postcode":"3072",
    "sg:province":"VIC",
    "sg:tags":[
        "telephone",
        "accessory"
    ],
    "wof:name":"Blue Communications",
    "wof:placetype":"venue"
},
  "geometry": {"coordinates":[145.00296020499999,-37.7456130981],"type":"Point"}
}