{
  "type": "Feature",
  "properties": {
    "addr:full":"Shop 4 16 McCartin St Leongatha VIC 3953",
    "addr:housenumber":"shop;16",
    "addr:postcode":"3953",
    "addr:street":"Mccartin St",
    "iso:country":"AU",
    "sg:address":"Shop 4 16 McCartin St",
    "sg:city":"Leongatha",
    "sg:classifiers":[
        {
            "category":"Real Estate",
            "subcategory":"Real Estate Agent",
            "type":"Services"
        }
    ],
    "sg:phone":"+61 3 5662 3523",
    "sg:postcode":"3953",
    "sg:province":"VIC",
    "wof:name":"Elders Real Estate",
    "wof:placetype":"venue"
},
  "geometry": {"coordinates":[145.94578552199999,-38.4763526917],"type":"Point"}
}