{
  "type": "Feature",
  "properties": {
    "addr:full":"PO Box 201 Noble Park VIC 3174",
    "addr:postcode":"3174",
    "iso:country":"AU",
    "sg:address":"PO Box 201",
    "sg:city":"Noble Park",
    "sg:classifiers":[
        {
            "category":"Home & Garden",
            "subcategory":"Building Materials",
            "type":"Retail Goods"
        }
    ],
    "sg:phone":"+61 401 278 559",
    "sg:postcode":"3174",
    "sg:province":"VIC",
    "sg:tags":[
        "plaster",
        "plasterboard",
        "supply"
    ],
    "wof:name":"Custom Fit Plaster Supplies",
    "wof:placetype":"venue"
},
  "geometry": {"coordinates":[145.189987183,-37.9669685364],"type":"Point"}
}