{
  "type": "Feature",
  "properties": {
    "addr:full":"Goobarabah Ave Gorokan NSW 2263",
    "addr:postcode":"2263",
    "addr:street":"Goobarabah Ave",
    "iso:country":"AU",
    "sg:address":"Goobarabah Ave",
    "sg:city":"Gorokan",
    "sg:classifiers":[
        {
            "category":"Education",
            "subcategory":"School",
            "type":"Public Place"
        }
    ],
    "sg:phone":"+61 2 4393 7000",
    "sg:postcode":"2263",
    "sg:province":"NSW",
    "sg:tags":[
        "state",
        "-",
        "nsw"
    ],
    "wof:name":"Gorokan High School",
    "wof:placetype":"venue"
},
  "geometry": {"coordinates":[151.50711100000001,-33.243862],"type":"Point"}
}