{
  "type": "Feature",
  "properties": {
    "addr:full":"183 Aumuller St Cairns QLD 4870",
    "addr:housenumber":"183",
    "addr:postcode":"4870",
    "addr:street":"Aumuller St",
    "iso:country":"AU",
    "sg:address":"183 Aumuller St",
    "sg:city":"Cairns",
    "sg:classifiers":[
        {
            "category":"Retail",
            "subcategory":"Driving School",
            "type":"Services"
        }
    ],
    "sg:phone":"+61 402 329 372",
    "sg:postcode":"4870",
    "sg:province":"QLD",
    "sg:tags":[
        "defensive",
        "advanced"
    ],
    "wof:name":"Cairns Off Road",
    "wof:placetype":"venue"
},
  "geometry": {"coordinates":[145.759963989,-16.9323825836],"type":"Point"}
}