{
  "type": "Feature",
  "properties": {
    "addr:full":"RMB 131 Kyogle NSW 2474",
    "addr:postcode":"2474",
    "iso:country":"AU",
    "sg:address":"RMB 131",
    "sg:city":"Kyogle",
    "sg:classifiers":[
        {
            "category":"Food & Beverages",
            "subcategory":"Bakery",
            "type":"Retail Goods"
        }
    ],
    "sg:phone":"+61 2 6635 1479",
    "sg:postcode":"2474",
    "sg:province":"NSW",
    "sg:tags":[
        "baker"
    ],
    "wof:name":"Heidis Organic Products",
    "wof:placetype":"venue"
},
  "geometry": {"coordinates":[153.00465393100001,-28.6164779663],"type":"Point"}
}