{
  "type": "Feature",
  "properties": {
    "addr:full":"Shp 1/ 1 Carters Ave Toorak VIC 3142",
    "addr:housenumber":"/ 1",
    "addr:postcode":"3142",
    "addr:street":"Carters Ave",
    "iso:country":"AU",
    "sg:address":"Shp 1/ 1 Carters Ave",
    "sg:city":"Toorak",
    "sg:classifiers":[
        {
            "category":"Personal",
            "subcategory":"Beauty Salon",
            "type":"Services"
        }
    ],
    "sg:phone":"+61 3 9827 7555",
    "sg:postcode":"3142",
    "sg:province":"VIC",
    "sg:tags":[
        "hairdresser"
    ],
    "wof:name":"Nixon Hair",
    "wof:placetype":"venue"
},
  "geometry": {"coordinates":[145.00924682600001,-37.8412780762],"type":"Point"}
}