{
  "type": "Feature",
  "properties": {
    "addr:full":"153 Kays Rd Wardell NSW 2477",
    "addr:housenumber":"153",
    "addr:postcode":"2477",
    "addr:street":"Kays Rd",
    "iso:country":"AU",
    "sg:address":"153 Kays Rd",
    "sg:city":"Wardell",
    "sg:classifiers":[
        {
            "category":"Home & Garden",
            "subcategory":"Garden Supply",
            "type":"Retail Goods"
        }
    ],
    "sg:phone":"+61 402 411 633",
    "sg:postcode":"2477",
    "sg:province":"NSW",
    "sg:tags":[
        "turf",
        "lawn"
    ],
    "wof:name":"North Coast Turf Services",
    "wof:placetype":"venue"
},
  "geometry": {"coordinates":[153.47523498499999,-28.9265155792],"type":"Point"}
}