{
  "type": "Feature",
  "properties": {
    "addr:full":"6 Leslie St Winmalee NSW 2777",
    "addr:housenumber":"6",
    "addr:postcode":"2777",
    "addr:street":"Leslie St",
    "iso:country":"AU",
    "sg:address":"6 Leslie St",
    "sg:city":"Winmalee",
    "sg:classifiers":[
        {
            "category":"Professional",
            "subcategory":"Business Services",
            "type":"Services"
        }
    ],
    "sg:phone":"+61 412 299 080",
    "sg:postcode":"2777",
    "sg:province":"NSW",
    "sg:tags":[
        "drafting"
    ],
    "wof:name":"Anderson Brett",
    "wof:placetype":"venue"
},
  "geometry": {"coordinates":[150.60716247600001,-33.669467926],"type":"Point"}
}