{
  "type": "Feature",
  "properties": {
    "addr:full":"21b Clarence St Grafton NSW 2460",
    "addr:housenumber":"21b",
    "addr:postcode":"2460",
    "addr:street":"Clarence St",
    "iso:country":"AU",
    "sg:address":"21b Clarence St",
    "sg:city":"Grafton",
    "sg:classifiers":[
        {
            "category":"Professional",
            "subcategory":"Detective & Security Services",
            "type":"Services"
        }
    ],
    "sg:phone":"+61 418 665 212",
    "sg:postcode":"2460",
    "sg:province":"NSW",
    "sg:tags":[
        "consultant",
        "system"
    ],
    "wof:name":"Darryl Smith",
    "wof:placetype":"venue"
},
  "geometry": {"coordinates":[152.94029235799999,-29.6925773621],"type":"Point"}
}