{
  "type": "Feature",
  "properties": {
    "addr:full":"9- 11 New St Frankston VIC 3199",
    "addr:housenumber":"11",
    "addr:postcode":"3199",
    "addr:street":"9;New St",
    "iso:country":"AU",
    "sg:address":"9- 11 New St",
    "sg:city":"Frankston",
    "sg:classifiers":[
        {
            "category":"Home & Garden",
            "subcategory":"Carpets & Floor Coverings",
            "type":"Retail Goods"
        }
    ],
    "sg:phone":"+61 3 9781 1443",
    "sg:postcode":"3199",
    "sg:province":"VIC",
    "wof:name":"D.M.K.Carpets",
    "wof:placetype":"venue"
},
  "geometry": {"coordinates":[145.17698669399999,-38.2284431458],"type":"Point"}
}