{
  "type": "Feature",
  "properties": {
    "iso:country":"AU",
    "sg:address":"Unit 1 31 Moreau Mews",
    "sg:city":"Applecross",
    "sg:classifiers":[
        {
            "category":"Health Services",
            "subcategory":"Health Practitioner",
            "type":"Services"
        }
    ],
    "sg:phone":"+61 8 9364 3762",
    "sg:postcode":"6153",
    "sg:province":"WA",
    "sg:tags":[
        "psychologist"
    ],
    "wof:name":"Applecross Psychological Services",
    "wof:placetype":"venue"
},
  "geometry": {"coordinates":[115.848618,-32.012413],"type":"Point"}
}