{
  "type": "Feature",
  "properties": {
    "addr:full":"Unit 20/ 88 Port Stephens Drv Taylors Beach NSW 2316",
    "addr:housenumber":"/ 88",
    "addr:postcode":"2316",
    "addr:street":"Port Stephens Drv",
    "iso:country":"AU",
    "sg:address":"Unit 20/ 88 Port Stephens Drv",
    "sg:city":"Taylors Beach",
    "sg:classifiers":[
        {
            "category":"Sports & Exercise",
            "subcategory":"Ski Resort",
            "type":"Entertainment"
        }
    ],
    "sg:phone":"+61 2 4981 9827",
    "sg:postcode":"2316",
    "sg:province":"NSW",
    "sg:tags":[
        "propelled",
        "jet"
    ],
    "wof:name":"Nelson Bay Marine & Outboard Service",
    "wof:placetype":"venue"
},
  "geometry": {"coordinates":[152.068375,-32.753792],"type":"Point"}
}