{
  "type": "Feature",
  "properties": {
    "addr:full":"530 Benetook Ave Mildura VIC 3500",
    "addr:housenumber":"530",
    "addr:postcode":"3500",
    "addr:street":"Benetook Ave",
    "iso:country":"AU",
    "sg:address":"530 Benetook Ave",
    "sg:city":"Mildura",
    "sg:classifiers":[
        {
            "category":"Wholesale",
            "subcategory":"Machinery & Supplies",
            "type":"Manufacturing & Wholesale Goods"
        }
    ],
    "sg:phone":"+61 3 5022 1073",
    "sg:postcode":"3500",
    "sg:province":"VIC",
    "sg:tags":[
        "bearing",
        "bushing"
    ],
    "wof:name":"Benetook Bearings",
    "wof:placetype":"venue"
},
  "geometry": {"coordinates":[142.164962769,-34.207988739],"type":"Point"}
}