{
  "type": "Feature",
  "properties": {
    "iso:country":"AU",
    "sg:address":"346 Rocky Point Rd",
    "sg:city":"Ramsgate",
    "sg:classifiers":[
        {
            "category":"Sports & Exercise",
            "subcategory":"Gym",
            "type":"Entertainment"
        }
    ],
    "sg:phone":"+61 2 9529 0489",
    "sg:postcode":"2217",
    "sg:province":"NSW",
    "sg:tags":[
        "personal",
        "trainer",
        "fitness"
    ],
    "wof:name":"Christopher Massage Therapy",
    "wof:placetype":"venue"
},
  "geometry": {"coordinates":[151.1362,-33.985371],"type":"Point"}
}