{
  "type": "Feature",
  "properties": {
    "addr:full":"Shop 1 & 2/13 Alford St Kingaroy QLD 4610",
    "addr:housenumber":"shop 1 & 2 / 13",
    "addr:postcode":"4610",
    "addr:street":"Alford St",
    "iso:country":"AU",
    "sg:address":"Shop 1 & 2/13 Alford St",
    "sg:city":"Kingaroy",
    "sg:classifiers":[
        {
            "category":"Shopping",
            "subcategory":"Computers & Home Electronics",
            "type":"Retail Goods"
        }
    ],
    "sg:phone":"+61 7 4162 2155",
    "sg:postcode":"4610",
    "sg:province":"QLD",
    "sg:tags":[
        "equipment",
        "part",
        "electronic"
    ],
    "wof:name":"Dick Smith Electronics",
    "wof:placetype":"venue"
},
  "geometry": {"coordinates":[151.83607482900001,-26.5404186249],"type":"Point"}
}