{
  "type": "Feature",
  "properties": {
    "addr:full":"12 Woolley St Dickson ACT 2602",
    "addr:housenumber":"12",
    "addr:postcode":"2602",
    "addr:street":"Woolley St",
    "iso:country":"AU",
    "sg:address":"12 Woolley St",
    "sg:city":"Dickson",
    "sg:classifiers":[
        {
            "category":"Shopping",
            "subcategory":"Clothing, Apparel, & Fashions",
            "type":"Retail Goods"
        }
    ],
    "sg:phone":"+61 2 6249 6170",
    "sg:postcode":"2602",
    "sg:province":"ACT",
    "sg:tags":[
        "accessory"
    ],
    "wof:name":"Oriental Styles",
    "wof:placetype":"venue"
},
  "geometry": {"coordinates":[149.13676452600001,-35.2505912781],"type":"Point"}
}