{
  "type": "Feature",
  "properties": {
    "addr:full":"53 Beasley Crs Rankin Park NSW 2287",
    "addr:housenumber":"53",
    "addr:postcode":"2287",
    "addr:street":"Beasley Crs Rankin",
    "iso:country":"AU",
    "sg:address":"53 Beasley Crs",
    "sg:city":"Rankin Park",
    "sg:classifiers":[
        {
            "category":"Building & Trades",
            "subcategory":"Construction",
            "type":"Services"
        }
    ],
    "sg:phone":"+61 2 4957 3015",
    "sg:postcode":"2287",
    "sg:province":"NSW",
    "sg:tags":[
        "rendering",
        "cement"
    ],
    "wof:name":"Solid Style Building Services Pty Ltd",
    "wof:placetype":"venue"
},
  "geometry": {"coordinates":[151.68678283700001,-32.9265289307],"type":"Point"}
}