{
  "type": "Feature",
  "properties": {
    "addr:full":"210 Elizabeth St Hobart TAS 7000",
    "addr:housenumber":"210",
    "addr:postcode":"7000",
    "addr:street":"Elizabeth St",
    "iso:country":"AU",
    "sg:address":"210 Elizabeth St",
    "sg:city":"Hobart",
    "sg:classifiers":[
        {
            "category":"Wholesale",
            "subcategory":"Apparel",
            "type":"Manufacturing & Wholesale Goods"
        }
    ],
    "sg:phone":"+61 3 6234 3705",
    "sg:postcode":"7000",
    "sg:province":"TAS",
    "sg:tags":[
        "wholesaler",
        "mfrs",
        "uniform"
    ],
    "wof:name":"Van Dieman Uniforms",
    "wof:placetype":"venue"
},
  "geometry": {"coordinates":[147.320922852,-42.8785972595],"type":"Point"}
}