{
  "type": "Feature",
  "properties": {
    "addr:full":"Cnr Donnison St & Mortimer La Gosford NSW 2250",
    "addr:postcode":"2250",
    "addr:street":"Cnr Donnison St &;La",
    "iso:country":"AU",
    "sg:address":"Cnr Donnison St & Mortimer La",
    "sg:city":"Gosford",
    "sg:classifiers":[
        {
            "category":"Insurance",
            "subcategory":"Hazard Insurance",
            "type":"Services"
        }
    ],
    "sg:phone":"+61 2 4324 6000",
    "sg:postcode":"2250",
    "sg:province":"NSW",
    "sg:tags":[
        "motor",
        "vehicle"
    ],
    "wof:name":"CGU",
    "wof:placetype":"venue"
},
  "geometry": {"coordinates":[151.341262817,-33.4268226624],"type":"Point"}
}