{
  "type": "Feature",
  "properties": {
    "addr:full":"136 Considine St Ellen Grove QLD 4078",
    "addr:housenumber":"136",
    "addr:postcode":"4078",
    "addr:street":"Considine St Ellen Grove",
    "iso:country":"AU",
    "sg:address":"136 Considine St",
    "sg:city":"Ellen Grove",
    "sg:classifiers":[
        {
            "category":"Shopping",
            "subcategory":"Computers & Home Electronics",
            "type":"Retail Goods"
        }
    ],
    "sg:phone":"+61 7 3271 3588",
    "sg:postcode":"4078",
    "sg:province":"QLD",
    "sg:tags":[
        "hardware",
        "equipment"
    ],
    "wof:name":"Anacom Pty Ltd",
    "wof:placetype":"venue"
},
  "geometry": {"coordinates":[152.94314575199999,-27.6215057373],"type":"Point"}
}