{
  "type": "Feature",
  "properties": {
    "addr:full":"Cnr Sheridan & Aplin Sts Cairns QLD 4870",
    "addr:postcode":"4870",
    "addr:street":"Cnr",
    "iso:country":"AU",
    "sg:address":"Cnr Sheridan & Aplin Sts",
    "sg:city":"Cairns",
    "sg:classifiers":[
        {
            "category":"Professional",
            "subcategory":"Accounting & Tax Preparation",
            "type":"Services"
        }
    ],
    "sg:phone":"+61 7 4046 0000",
    "sg:postcode":"4870",
    "sg:province":"QLD",
    "sg:tags":[
        "consultant",
        "taxation"
    ],
    "wof:name":"Horwath",
    "wof:placetype":"venue"
},
  "geometry": {"coordinates":[145.77784729000001,-16.9287967682],"type":"Point"}
}