{
  "type": "Feature",
  "properties": {
    "addr:full":"58 Baillie St North Melbourne VIC 3051",
    "addr:housenumber":"58",
    "addr:postcode":"3051",
    "addr:street":"Baillie St",
    "iso:country":"AU",
    "sg:address":"58 Baillie St",
    "sg:city":"North Melbourne",
    "sg:classifiers":[
        {
            "category":"Professional",
            "subcategory":"Management & Consulting",
            "type":"Services"
        }
    ],
    "sg:phone":"+61 3 9329 1940",
    "sg:postcode":"3051",
    "sg:province":"VIC",
    "sg:tags":[
        "consultant"
    ],
    "wof:name":"Maddock Mary Consulting",
    "wof:placetype":"venue"
},
  "geometry": {"coordinates":[144.94619750999999,-37.8011894226],"type":"Point"}
}