{
  "type": "Feature",
  "properties": {
    "addr:full":"Bedford Ave Rottnest WA 6161",
    "addr:postcode":"6161",
    "addr:street":"Bedford Ave",
    "iso:country":"AU",
    "sg:address":"Bedford Ave",
    "sg:city":"Rottnest",
    "sg:classifiers":[
        {
            "category":"Travel",
            "subcategory":"Hotels & Motels",
            "type":"Entertainment"
        }
    ],
    "sg:phone":"+61 8 9292 5011",
    "sg:postcode":"6161",
    "sg:province":"WA",
    "sg:tags":[
        "accommodation"
    ],
    "wof:name":"Quokka Arms",
    "wof:placetype":"venue"
},
  "geometry": {"coordinates":[115.50393699999999,-32.007488],"type":"Point"}
}