{
  "type": "Feature",
  "properties": {
    "addr:full":"Suite 12 37- 43 Alexander St Crows Nest NSW 2065",
    "addr:housenumber":"37 43",
    "addr:postcode":"2065",
    "addr:street":"Alexander St",
    "iso:country":"AU",
    "sg:address":"Suite 12 37- 43 Alexander St",
    "sg:city":"Crows Nest",
    "sg:classifiers":[
        {
            "category":"Professional",
            "subcategory":"Computer Services",
            "type":"Services"
        }
    ],
    "sg:phone":"+61 419 335 806",
    "sg:postcode":"2065",
    "sg:province":"NSW",
    "sg:tags":[
        "package",
        "software"
    ],
    "wof:name":"ClubNet International Pty Ltd",
    "wof:placetype":"venue"
},
  "geometry": {"coordinates":[151.202102661,-33.8275909424],"type":"Point"}
}