{
  "type": "Feature",
  "properties": {
    "iso:country":"AU",
    "sg:address":"Centenary Pde",
    "sg:city":"Nambucca Heads",
    "sg:classifiers":[
        {
            "category":"Education",
            "subcategory":"School",
            "type":"Public Place"
        }
    ],
    "sg:phone":"+61 2 6568 9311",
    "sg:postcode":"2448",
    "sg:province":"NSW",
    "wof:name":"Nambucca Valley Christian Community School",
    "wof:placetype":"venue"
},
  "geometry": {"coordinates":[152.98429899999999,-30.642076],"type":"Point"}
}