{
  "type": "Feature",
  "properties": {
    "iso:country":"AU",
    "sg:address":"110 Ryrie St",
    "sg:city":"Geelong",
    "sg:classifiers":[
        {
            "category":"Professional",
            "subcategory":"Printing & Photocopies",
            "type":"Services"
        }
    ],
    "sg:phone":"+61 3 5221 9156",
    "sg:postcode":"3220",
    "sg:province":"VIC",
    "sg:tags":[
        "equipment",
        "plan"
    ],
    "wof:name":"Cavalier Digital Print",
    "wof:placetype":"venue"
},
  "geometry": {"coordinates":[144.35820000000001,-38.148998],"type":"Point"}
}