{
  "type": "Feature",
  "properties": {
    "addr:full":"1312 Western Hwy Caroline Springs VIC 3023",
    "addr:housenumber":"1312",
    "addr:postcode":"3023",
    "addr:street":"Western Hwy",
    "iso:country":"AU",
    "sg:address":"1312 Western Hwy",
    "sg:city":"Caroline Springs",
    "sg:classifiers":[
        {
            "category":"Travel",
            "subcategory":"Hotels & Motels",
            "type":"Entertainment"
        }
    ],
    "sg:phone":"+61 3 8390 2445",
    "sg:postcode":"3023",
    "sg:province":"VIC",
    "sg:tags":[
        "pub"
    ],
    "wof:name":"The Club",
    "wof:placetype":"venue"
},
  "geometry": {"coordinates":[144.740814,-37.756184],"type":"Point"}
}