{
  "type": "Feature",
  "properties": {
    "addr:full":"Percell Ave Wee Waa NSW 2388",
    "addr:postcode":"2388",
    "addr:street":"Percell Ave",
    "iso:country":"AU",
    "sg:address":"Percell Ave",
    "sg:city":"Wee Waa",
    "sg:classifiers":[
        {
            "category":"Education",
            "subcategory":"School",
            "type":"Public Place"
        }
    ],
    "sg:phone":"+61 2 6795 4477",
    "sg:postcode":"2388",
    "sg:province":"NSW",
    "sg:tags":[
        "state",
        "-",
        "nsw"
    ],
    "wof:name":"Wee Waa High",
    "wof:placetype":"venue"
},
  "geometry": {"coordinates":[149.437576294,-30.2262001038],"type":"Point"}
}