{
  "type": "Feature",
  "properties": {
    "iso:country":"AU",
    "sg:address":"34 William St",
    "sg:city":"Toronto",
    "sg:classifiers":[
        {
            "category":"Professional",
            "type":"Services"
        }
    ],
    "sg:phone":"+61 2 4959 2483",
    "sg:postcode":"2283",
    "sg:province":"NSW",
    "sg:tags":[
        "courier"
    ],
    "wof:name":"Barclay Bob",
    "wof:placetype":"venue"
},
  "geometry": {"coordinates":[151.603240967,-32.9645729065],"type":"Point"}
}