{
  "type": "Feature",
  "properties": {
    "addr:full":"34 Victoria St Smithfield NSW 2164",
    "addr:housenumber":"34",
    "addr:postcode":"2164",
    "addr:street":"Victoria St",
    "iso:country":"AU",
    "sg:address":"34 Victoria St",
    "sg:city":"Smithfield",
    "sg:classifiers":[
        {
            "category":"Landmark",
            "subcategory":"Scenic View",
            "type":"Public Place"
        }
    ],
    "sg:phone":"+61 2 9729 1166",
    "sg:postcode":"2164",
    "sg:province":"NSW",
    "sg:tags":[
        "staircase",
        "handrail"
    ],
    "wof:name":"Australian Stair Builders",
    "wof:placetype":"venue"
},
  "geometry": {"coordinates":[150.940475464,-33.8512382507],"type":"Point"}
}