{
  "type": "Feature",
  "properties": {
    "iso:country":"AU",
    "sg:address":"18 Jenner St",
    "sg:city":"Seaforth",
    "sg:classifiers":[
        {
            "category":"Professional",
            "subcategory":"Management & Consulting",
            "type":"Services"
        }
    ],
    "sg:phone":"+61 2 9948 3890",
    "sg:postcode":"2092",
    "sg:province":"NSW",
    "sg:tags":[
        "consultant"
    ],
    "wof:name":"EPS Growth",
    "wof:placetype":"venue"
},
  "geometry": {"coordinates":[151.240966797,-33.7968902588],"type":"Point"}
}