{
  "type": "Feature",
  "properties": {
    "addr:full":"4 Birdwood St Hughes ACT 2605",
    "addr:housenumber":"4",
    "addr:postcode":"2605",
    "addr:street":"Birdwood St",
    "iso:country":"AU",
    "sg:address":"4 Birdwood St",
    "sg:city":"Hughes",
    "sg:classifiers":[
        {
            "category":"Education",
            "subcategory":"Special Training",
            "type":"Public Place"
        }
    ],
    "sg:phone":"+61 2 6282 3150",
    "sg:postcode":"2605",
    "sg:province":"ACT",
    "sg:tags":[
        "development"
    ],
    "wof:name":"VT Coach Pty Ltd",
    "wof:placetype":"venue"
},
  "geometry": {"coordinates":[149.09498596200001,-35.3300552368],"type":"Point"}
}