{
  "type": "Feature",
  "properties": {
    "addr:full":"Weaber Plain Rd Kununurra WA 6743",
    "addr:postcode":"6743",
    "addr:street":"Weaber Plain Rd",
    "iso:country":"AU",
    "sg:address":"Weaber Plain Rd",
    "sg:city":"Kununurra",
    "sg:classifiers":[
        {
            "category":"Building & Trades",
            "subcategory":"Construction",
            "type":"Services"
        }
    ],
    "sg:phone":"+61 8 9168 2190",
    "sg:postcode":"6743",
    "sg:province":"WA",
    "sg:tags":[
        "renovation",
        "alterations",
        "extension",
        "contractor"
    ],
    "wof:name":"D.E. Carpenters",
    "wof:placetype":"venue"
},
  "geometry": {"coordinates":[128.744873047,-15.7726078033],"type":"Point"}
}