{
  "type": "Feature",
  "properties": {
    "iso:country":"AU",
    "sg:address":"37 Hunter St",
    "sg:city":"Syndal",
    "sg:classifiers":[
        {
            "category":"Social Services",
            "subcategory":"Child Care",
            "type":"Services"
        }
    ],
    "sg:phone":"+61 3 9802 9194",
    "sg:postcode":"3149",
    "sg:province":"VIC",
    "wof:name":"Croxley Hall Child Care Centre",
    "wof:placetype":"venue"
},
  "geometry": {"coordinates":[145.15003967300001,-37.8760719299],"type":"Point"}
}