{
  "type": "Feature",
  "properties": {
    "addr:full":"Unit 2/ 47 Railway Rd Kalamunda WA 6076",
    "addr:housenumber":"47",
    "addr:postcode":"6076",
    "addr:street":"Railway Rd",
    "iso:country":"AU",
    "sg:address":"Unit 2/ 47 Railway Rd",
    "sg:city":"Kalamunda",
    "sg:classifiers":[
        {
            "category":"Farming",
            "subcategory":"Fish & Marine Products",
            "type":"Manufacturing & Wholesale Goods"
        }
    ],
    "sg:phone":"+61 8 9293 2688",
    "sg:postcode":"6076",
    "sg:province":"WA",
    "sg:tags":[
        "organic"
    ],
    "wof:name":"Image One",
    "wof:placetype":"venue"
},
  "geometry": {"coordinates":[116.06012725799999,-31.9718990326],"type":"Point"}
}