{
  "type": "Feature",
  "properties": {
    "addr:full":"PO Box 1552 Sunshine Plaza QLD 4558",
    "addr:postcode":"4558",
    "iso:country":"AU",
    "sg:address":"PO Box 1552",
    "sg:city":"Sunshine Plaza",
    "sg:classifiers":[
        {
            "category":"Food & Beverages",
            "subcategory":"Fruits & Vegetables",
            "type":"Retail Goods"
        }
    ],
    "sg:phone":"+61 7 5443 9696",
    "sg:postcode":"4558",
    "sg:province":"QLD",
    "sg:tags":[
        "wholesale"
    ],
    "wof:name":"Natoli Brothers",
    "wof:placetype":"venue"
},
  "geometry": {"coordinates":[153.08903503400001,-26.653219223],"type":"Point"}
}