{
  "type": "Feature",
  "properties": {
    "addr:full":"34 Hickson Rd The Rocks NSW 2000",
    "addr:housenumber":"34",
    "addr:postcode":"2000",
    "addr:street":"Hickson Rd",
    "iso:country":"AU",
    "sg:address":"34 Hickson Rd",
    "sg:city":"The Rocks",
    "sg:classifiers":[
        {
            "category":"Home & Garden",
            "subcategory":"Building Materials",
            "type":"Retail Goods"
        }
    ],
    "sg:phone":"+61 2 9247 2677",
    "sg:postcode":"2000",
    "sg:province":"NSW",
    "sg:tags":[
        "plaster",
        "plasterboard",
        "supply"
    ],
    "wof:name":"Stud & Track Manufacturing Co",
    "wof:placetype":"venue"
},
  "geometry": {"coordinates":[151.20616149899999,-33.8561859131],"type":"Point"}
}