{
  "type": "Feature",
  "properties": {
    "addr:full":"103 Tudor St Hamilton NSW 2303",
    "addr:housenumber":"103",
    "addr:postcode":"2303",
    "addr:street":"Tudor St",
    "iso:country":"AU",
    "sg:address":"103 Tudor St",
    "sg:city":"Hamilton",
    "sg:classifiers":[
        {
            "category":"Banks & Credit Unions",
            "subcategory":"Investment Brokerage",
            "type":"Services"
        }
    ],
    "sg:phone":"+61 2 4921 9179",
    "sg:postcode":"2303",
    "sg:province":"NSW",
    "sg:tags":[
        "finance",
        "broker"
    ],
    "wof:name":"Centrepoint Alliance",
    "wof:placetype":"venue"
},
  "geometry": {"coordinates":[151.74653599999999,-32.924152],"type":"Point"}
}