{
  "type": "Feature",
  "properties": {
    "addr:full":"17 Holzer St Sandringham VIC 3191",
    "addr:housenumber":"17",
    "addr:postcode":"3191",
    "addr:street":"Holzer St",
    "iso:country":"AU",
    "sg:address":"17 Holzer St",
    "sg:city":"Sandringham",
    "sg:classifiers":[
        {
            "category":"Building & Trades",
            "subcategory":"Plumbing",
            "type":"Services"
        }
    ],
    "sg:phone":"+61 3 9598 6332",
    "sg:postcode":"3191",
    "sg:province":"VIC",
    "sg:tags":[
        "plumber",
        "gasfitters"
    ],
    "wof:name":"Warner Plumbing Pty Ltd",
    "wof:placetype":"venue"
},
  "geometry": {"coordinates":[145.01315307600001,-37.947303772],"type":"Point"}
}