{
  "type": "Feature",
  "properties": {
    "addr:full":"1/ 379 Rocky Point Rd Sans Souci NSW 2219",
    "addr:housenumber":"/ 379",
    "addr:postcode":"2219",
    "addr:street":"Rocky Point Rd",
    "iso:country":"AU",
    "sg:address":"1/ 379 Rocky Point Rd",
    "sg:city":"Sans Souci",
    "sg:classifiers":[
        {
            "category":"Banks & Credit Unions",
            "subcategory":"Financial Services",
            "type":"Services"
        }
    ],
    "sg:phone":"+61 1300 307 840",
    "sg:postcode":"2219",
    "sg:province":"NSW",
    "sg:tags":[
        "loan",
        "finance",
        "mortgage"
    ],
    "wof:name":"Mortgage Wisdom",
    "wof:placetype":"venue"
},
  "geometry": {"coordinates":[151.131653,-33.992546],"type":"Point"}
}