{
  "type": "Feature",
  "properties": {
    "addr:full":"77 York St Sydney NSW 2000",
    "addr:housenumber":"77",
    "addr:postcode":"2000",
    "addr:street":"York St",
    "iso:country":"AU",
    "sg:address":"77 York St",
    "sg:city":"Sydney",
    "sg:classifiers":[
        {
            "category":"Conference Center",
            "type":"Public Place"
        }
    ],
    "sg:phone":"+61 2 9272 6888",
    "sg:postcode":"2000",
    "sg:province":"NSW",
    "sg:tags":[
        "venue",
        "convention"
    ],
    "wof:name":"Grace Hotel The",
    "wof:placetype":"venue"
},
  "geometry": {"coordinates":[151.20591735799999,-33.8688011169],"type":"Point"}
}