{
  "type": "Feature",
  "properties": {
    "addr:full":"21 Paramount Drv Wangara WA 6065",
    "addr:housenumber":"21",
    "addr:postcode":"6065",
    "addr:street":"Paramount Drv",
    "iso:country":"AU",
    "sg:address":"21 Paramount Drv",
    "sg:city":"Wangara",
    "sg:classifiers":[
        {
            "category":"Wholesale",
            "subcategory":"Auto Parts",
            "type":"Manufacturing & Wholesale Goods"
        }
    ],
    "sg:phone":"+61 8 9302 3519",
    "sg:postcode":"6065",
    "sg:province":"WA",
    "sg:tags":[
        "recyclers"
    ],
    "sg:website":"http://www.japanesewholesale.com.au",
    "wof:name":"Japanese Wholesale Spares",
    "wof:placetype":"venue"
},
  "geometry": {"coordinates":[115.83055877699999,-31.7901229858],"type":"Point"}
}