{
  "type": "Feature",
  "properties": {
    "iso:country":"AU",
    "sg:address":"Grafton Wellbeing Centre, 93 Fitzroy Street, Grafton",
    "sg:city":"Grafton",
    "sg:classifiers":[
        {
            "category":"Health Services",
            "subcategory":"Health Practitioner",
            "type":"Services"
        }
    ],
    "sg:phone":"+61 2 6643 3466",
    "sg:postcode":"2460",
    "sg:province":"NSW",
    "sg:tags":[
        "hypnotherapy"
    ],
    "wof:name":"Dunbar Mardi",
    "wof:placetype":"venue"
},
  "geometry": {"coordinates":[152.933959961,-29.6917667389],"type":"Point"}
}