{
  "type": "Feature",
  "properties": {
    "addr:full":"Rear 189 Parramatta Rd Flemington NSW 2140",
    "addr:housenumber":"189",
    "addr:postcode":"2140",
    "addr:street":"Parramatta Rd",
    "iso:country":"AU",
    "sg:address":"Rear 189 Parramatta Rd",
    "sg:city":"Flemington",
    "sg:classifiers":[
        {
            "category":"Retail",
            "subcategory":"Repair Shop",
            "type":"Services"
        }
    ],
    "sg:phone":"+61 2 8746 0318",
    "sg:postcode":"2140",
    "sg:province":"NSW",
    "sg:tags":[
        "machine",
        "sewing"
    ],
    "wof:name":"Cush Sewing Machines",
    "wof:placetype":"venue"
},
  "geometry": {"coordinates":[151.07391357399999,-33.8601493835],"type":"Point"}
}