{
  "type": "Feature",
  "properties": {
    "addr:full":"79A Grimshaw St Greensborough VIC 3088",
    "addr:housenumber":"79a",
    "addr:postcode":"3088",
    "addr:street":"Grimshaw St",
    "iso:country":"AU",
    "sg:address":"79A Grimshaw St",
    "sg:city":"Greensborough",
    "sg:classifiers":[
        {
            "category":"Personal",
            "type":"Services"
        }
    ],
    "sg:phone":"+61 3 9432 5599",
    "sg:postcode":"3088",
    "sg:province":"VIC",
    "sg:tags":[
        "reducing",
        "treatment",
        "weight"
    ],
    "wof:name":"Curves Greensborough",
    "wof:placetype":"venue"
},
  "geometry": {"coordinates":[145.102172852,-37.7045860291],"type":"Point"}
}