{
  "type": "Feature",
  "properties": {
    "addr:full":"1/1 Perry St Matraville NSW 2036",
    "addr:housenumber":"/ 1",
    "addr:postcode":"2036",
    "addr:street":"Perry St",
    "iso:country":"AU",
    "sg:address":"1/1 Perry St",
    "sg:city":"Matraville",
    "sg:classifiers":[
        {
            "category":"Communications",
            "type":"Services"
        }
    ],
    "sg:phone":"+61 2 9700 0120",
    "sg:postcode":"2036",
    "sg:province":"NSW",
    "sg:tags":[
        "public",
        "system",
        "address"
    ],
    "wof:name":"Jazzright P A Hire",
    "wof:placetype":"venue"
},
  "geometry": {"coordinates":[151.22190856899999,-33.9594116211],"type":"Point"}
}