{
  "type": "Feature",
  "properties": {
    "iso:country":"AU",
    "sg:address":"PO Box 27",
    "sg:city":"Berala",
    "sg:classifiers":[
        {
            "category":"Shopping",
            "subcategory":"Stationery & Office Supplies",
            "type":"Retail Goods"
        }
    ],
    "sg:phone":"+61 2 9646 4609",
    "sg:postcode":"2141",
    "sg:province":"NSW",
    "sg:tags":[
        "partition"
    ],
    "wof:name":"Intewall Office Interiors",
    "wof:placetype":"venue"
},
  "geometry": {"coordinates":[151.03363037099999,-33.8706703186],"type":"Point"}
}