{
  "type": "Feature",
  "properties": {
    "iso:country":"AU",
    "sg:address":"Shp 4, 3 - 6",
    "sg:city":"The Strand Dee Why",
    "sg:classifiers":[
        {
            "category":"Restaurant",
            "type":"Food & Drink"
        }
    ],
    "sg:phone":"+61 2 9984 8644",
    "sg:postcode":"2099",
    "sg:province":"NSW",
    "wof:name":"Sea La Vie",
    "wof:placetype":"venue"
},
  "geometry": {"coordinates":[151.296142578,-33.7549781799],"type":"Point"}
}