{
  "type": "Feature",
  "properties": {
    "addr:full":"Unit 7, 2 Bishop St St Peters NSW 2044",
    "addr:housenumber":"2",
    "addr:postcode":"2044",
    "addr:street":"Bishop St",
    "iso:country":"AU",
    "sg:address":"Unit 7, 2 Bishop St St",
    "sg:city":"Peters",
    "sg:classifiers":[
        {
            "category":"Professional",
            "subcategory":"Computer Services",
            "type":"Services"
        }
    ],
    "sg:phone":"+61 2 8568 3700",
    "sg:postcode":"2044",
    "sg:province":"NSW",
    "sg:tags":[
        "equipment",
        "networking",
        "installation"
    ],
    "wof:name":"Network Brokers Pty Ltd",
    "wof:placetype":"venue"
},
  "geometry": {"coordinates":[151.17846700000001,-33.913795],"type":"Point"}
}