{
  "type": "Feature",
  "properties": {
    "iso:country":"AU",
    "sg:address":"21 Beh St",
    "sg:city":"Toowoomba",
    "sg:classifiers":[
        {
            "category":"Professional",
            "subcategory":"Art Services",
            "type":"Services"
        }
    ],
    "sg:phone":"+61 419 676 574",
    "sg:postcode":"4350",
    "sg:province":"QLD",
    "sg:tags":[
        "decorator",
        "painter"
    ],
    "wof:name":"Des Ryle Painter and Decorator",
    "wof:placetype":"venue"
},
  "geometry": {"coordinates":[151.935013,-27.588871],"type":"Point"}
}