{
  "type": "Feature",
  "properties": {
    "addr:full":"59 Northern Ave West Beach SA 5024",
    "addr:housenumber":"59",
    "addr:postcode":"5024",
    "addr:street":"Northern Ave",
    "iso:country":"AU",
    "sg:address":"59 Northern Ave",
    "sg:city":"West Beach",
    "sg:classifiers":[
        {
            "category":"Professional",
            "subcategory":"Engineering",
            "type":"Services"
        }
    ],
    "sg:phone":"+61 8 8356 9705",
    "sg:postcode":"5024",
    "sg:province":"SA",
    "sg:tags":[
        "consulting",
        "engineer"
    ],
    "wof:name":"Raymol AirConditioning",
    "wof:placetype":"venue"
},
  "geometry": {"coordinates":[138.51054382300001,-34.9405212402],"type":"Point"}
}