{
  "type": "Feature",
  "properties": {
    "addr:full":"157 Para Rd Greensborough VIC 3088",
    "addr:housenumber":"157",
    "addr:postcode":"3088",
    "addr:street":"Para Rd",
    "iso:country":"AU",
    "sg:address":"157 Para Rd",
    "sg:city":"Greensborough",
    "sg:classifiers":[
        {
            "category":"Retail",
            "subcategory":"Auto Repair",
            "type":"Services"
        }
    ],
    "sg:phone":"+61 3 9435 1255",
    "sg:postcode":"3088",
    "sg:province":"VIC",
    "sg:tags":[
        "beater",
        "painter",
        "panel"
    ],
    "wof:name":"Grimshaw Panels",
    "wof:placetype":"venue"
},
  "geometry": {"coordinates":[145.11134338400001,-37.7081871033],"type":"Point"}
}