{
  "type": "Feature",
  "properties": {
    "iso:country":"AU",
    "sg:address":"29 Nelson Drv",
    "sg:city":"Hunterview",
    "sg:classifiers":[
        {
            "category":"Professional",
            "subcategory":"Business Services",
            "type":"Services"
        }
    ],
    "sg:phone":"+61 411 168 159",
    "sg:postcode":"2330",
    "sg:province":"NSW",
    "sg:tags":[
        "management",
        "event"
    ],
    "wof:name":"Ainslies Wedding & Event Hire",
    "wof:placetype":"venue"
},
  "geometry": {"coordinates":[151.17770400000001,-32.540016],"type":"Point"}
}