{
  "type": "Feature",
  "properties": {
    "addr:full":"57 Kendall St West Pymble NSW 2073",
    "addr:housenumber":"57",
    "addr:postcode":"2073",
    "addr:street":"Kendall St",
    "iso:country":"AU",
    "sg:address":"57 Kendall St",
    "sg:city":"West Pymble",
    "sg:classifiers":[
        {
            "category":"Education",
            "subcategory":"Kindergarten",
            "type":"Public Place"
        }
    ],
    "sg:phone":"+61 2 9498 1684",
    "sg:postcode":"2073",
    "sg:province":"NSW",
    "sg:tags":[
        "pre-schools"
    ],
    "wof:name":"Kendall Street Kindergarten",
    "wof:placetype":"venue"
},
  "geometry": {"coordinates":[151.13107299800001,-33.7604751587],"type":"Point"}
}