{
  "type": "Feature",
  "properties": {
    "addr:full":"24 Marguerita Ave Mt Martha VIC 3934",
    "addr:housenumber":"24",
    "addr:postcode":"3934",
    "addr:street":"Marguerita Ave Mt Martha",
    "iso:country":"AU",
    "sg:address":"24 Marguerita Ave",
    "sg:city":"Mt Martha",
    "sg:classifiers":[
        {
            "category":"Utilities",
            "subcategory":"Electric",
            "type":"Services"
        }
    ],
    "sg:phone":"+61 428 321 175",
    "sg:postcode":"3934",
    "sg:province":"VIC",
    "sg:tags":[
        "electrical",
        "contractor"
    ],
    "wof:name":"Kec Maintenance Services",
    "wof:placetype":"venue"
},
  "geometry": {"coordinates":[145.00306701700001,-38.2795829773],"type":"Point"}
}