{
  "type": "Feature",
  "properties": {
    "addr:full":"Shop 2 11 Bulcock St Caloundra QLD 4551",
    "addr:housenumber":"shop;11",
    "addr:postcode":"4551",
    "addr:street":"Bulcock St",
    "iso:country":"AU",
    "sg:address":"Shop 2 11 Bulcock St",
    "sg:city":"Caloundra",
    "sg:classifiers":[
        {
            "category":"Travel",
            "subcategory":"Travel Agent",
            "type":"Entertainment"
        }
    ],
    "sg:phone":"+61 7 5491 9111",
    "sg:postcode":"4551",
    "sg:province":"QLD",
    "sg:tags":[
        "consultant"
    ],
    "wof:name":"Harvey World Travel",
    "wof:placetype":"venue"
},
  "geometry": {"coordinates":[153.129959106,-26.804693222],"type":"Point"}
}