{
  "type": "Feature",
  "properties": {
    "addr:full":"550 George St Sydney NSW 2000",
    "addr:housenumber":"550",
    "addr:postcode":"2000",
    "addr:street":"George St",
    "iso:country":"AU",
    "sg:address":"550 George St",
    "sg:city":"Sydney",
    "sg:classifiers":[
        {
            "category":"Restaurant",
            "type":"Food & Drink"
        }
    ],
    "sg:phone":"+61 2 9267 3321",
    "sg:postcode":"2000",
    "sg:province":"NSW",
    "wof:name":"Alexanders At Town Hall Restaurant",
    "wof:placetype":"venue"
},
  "geometry": {"coordinates":[151.207122803,-33.8734588623],"type":"Point"}
}