{
  "type": "Feature",
  "properties": {
    "addr:full":"Unit 5, 12 Boronia St Dee Why NSW 2099",
    "addr:housenumber":"12",
    "addr:postcode":"2099",
    "addr:street":"Boronia St",
    "iso:country":"AU",
    "sg:address":"Unit 5, 12 Boronia St",
    "sg:city":"Dee Why",
    "sg:classifiers":[
        {
            "category":"Building & Trades",
            "subcategory":"Construction",
            "type":"Services"
        }
    ],
    "sg:phone":"+61 425 778 706",
    "sg:postcode":"2099",
    "sg:province":"NSW",
    "sg:tags":[
        "joiner",
        "carpenter"
    ],
    "wof:name":"Meehan Anthony B",
    "wof:placetype":"venue"
},
  "geometry": {"coordinates":[151.295684814,-33.7569007874],"type":"Point"}
}