{
  "type": "Feature",
  "properties": {
    "iso:country":"AU",
    "sg:address":"489 Cross Keys Rd",
    "sg:city":"Cavan",
    "sg:classifiers":[
        {
            "category":"Home & Garden",
            "subcategory":"Carpets & Floor Coverings",
            "type":"Retail Goods"
        }
    ],
    "sg:phone":"+61 8 8359 8661",
    "sg:postcode":"5094",
    "sg:province":"SA",
    "sg:tags":[
        "double",
        "window",
        "glazed"
    ],
    "wof:name":"Southern Star Windows",
    "wof:placetype":"venue"
},
  "geometry": {"coordinates":[138.60040283199999,-34.8260231018],"type":"Point"}
}