{
  "type": "Feature",
  "properties": {
    "addr:full":"Fy 1a/ 11a Venture Drv Noosaville QLD 4566",
    "addr:housenumber":"1a / 11a",
    "addr:postcode":"4566",
    "addr:street":"Fy;Venture Drv",
    "iso:country":"AU",
    "sg:address":"Fy 1a/ 11a Venture Drv",
    "sg:city":"Noosaville",
    "sg:classifiers":[
        {
            "category":"Building & Trades",
            "subcategory":"Cleaning & Sanitation",
            "type":"Services"
        }
    ],
    "sg:phone":"+61 7 5442 4076",
    "sg:postcode":"4566",
    "sg:province":"QLD",
    "sg:tags":[
        "commercial",
        "maintenance"
    ],
    "wof:name":"Noosa Property Maintenance",
    "wof:placetype":"venue"
},
  "geometry": {"coordinates":[153.046508789,-26.4085292816],"type":"Point"}
}