{
  "type": "Feature",
  "properties": {
    "addr:full":"41 Cecilia St St Helens TAS 7216",
    "addr:housenumber":"41",
    "addr:postcode":"7216",
    "addr:street":"Cecilia St",
    "iso:country":"AU",
    "sg:address":"41 Cecilia St",
    "sg:city":"St Helens",
    "sg:classifiers":[
        {
            "category":"Shopping",
            "subcategory":"Clothing, Apparel, & Fashions",
            "type":"Retail Goods"
        }
    ],
    "sg:phone":"+61 3 6376 1175",
    "sg:postcode":"7216",
    "sg:province":"TAS",
    "sg:tags":[
        "lady",
        "wear"
    ],
    "wof:name":"Carlyle The",
    "wof:placetype":"venue"
},
  "geometry": {"coordinates":[148.24989299999999,-41.32151],"type":"Point"}
}