{
  "type": "Feature",
  "properties": {
    "addr:full":"1/ 2 Johnson St Maitland NSW 2320",
    "addr:housenumber":"/ 2",
    "addr:postcode":"2320",
    "addr:street":"Johnson St",
    "iso:country":"AU",
    "sg:address":"1/ 2 Johnson St",
    "sg:city":"Maitland",
    "sg:classifiers":[
        {
            "category":"Health Services",
            "subcategory":"Doctor",
            "type":"Services"
        }
    ],
    "sg:phone":"+61 2 4932 6882",
    "sg:postcode":"2320",
    "sg:province":"NSW",
    "sg:tags":[
        "medical",
        "practitioner"
    ],
    "wof:name":"Newcastle & Hunter Cardiac Services",
    "wof:placetype":"venue"
},
  "geometry": {"coordinates":[151.54180908199999,-32.7237358093],"type":"Point"}
}