{
  "type": "Feature",
  "properties": {
    "addr:full":"86 Sturt St Echuca VIC 3564",
    "addr:housenumber":"86",
    "addr:postcode":"3564",
    "addr:street":"Sturt St",
    "iso:country":"AU",
    "sg:address":"86 Sturt St",
    "sg:city":"Echuca",
    "sg:classifiers":[
        {
            "category":"Building & Trades",
            "subcategory":"Construction",
            "type":"Services"
        }
    ],
    "sg:phone":"+61 3 5482 3582",
    "sg:postcode":"3564",
    "sg:province":"VIC",
    "sg:tags":[
        "earth",
        "excavating",
        "moving",
        "contractor"
    ],
    "wof:name":"Pete Glanville",
    "wof:placetype":"venue"
},
  "geometry": {"coordinates":[144.75460815400001,-36.1327514648],"type":"Point"}
}