{
  "type": "Feature",
  "properties": {
    "addr:full":"376 North East Rd Windsor Gardens SA 5087",
    "addr:housenumber":"376",
    "addr:postcode":"5087",
    "addr:street":"North East Rd",
    "iso:country":"AU",
    "sg:address":"376 North East Rd",
    "sg:city":"Windsor Gardens",
    "sg:classifiers":[
        {
            "category":"Autos & Motor Vehicles",
            "subcategory":"Automobile Sales",
            "type":"Retail Goods"
        }
    ],
    "sg:phone":"+61 8 8369 2577",
    "sg:postcode":"5087",
    "sg:province":"SA",
    "sg:tags":[
        "car",
        "used"
    ],
    "wof:name":"Assured Cars",
    "wof:placetype":"venue"
},
  "geometry": {"coordinates":[138.64309692399999,-34.8669281006],"type":"Point"}
}