{
  "type": "Feature",
  "properties": {
    "addr:full":"259 East Derwent Hwy Lindisfarne TAS 7015",
    "addr:housenumber":"259",
    "addr:postcode":"7015",
    "addr:street":"East Derwent Hwy",
    "iso:country":"AU",
    "sg:address":"259 East Derwent Hwy",
    "sg:city":"Lindisfarne",
    "sg:classifiers":[
        {
            "category":"Fast Food",
            "type":"Food & Drink"
        }
    ],
    "sg:phone":"+61 3 6243 9980",
    "sg:postcode":"7015",
    "sg:province":"TAS",
    "sg:tags":[
        "away",
        "take"
    ],
    "wof:name":"Geilsten Bay Fish Shop",
    "wof:placetype":"venue"
},
  "geometry": {"coordinates":[147.35197448700001,-42.8403968811],"type":"Point"}
}