{
  "type": "Feature",
  "properties": {
    "addr:full":"Darroch House 6 Briar Rd Felixstow SA 5070",
    "addr:housenumber":"6",
    "addr:postcode":"5070",
    "addr:street":"Briar Rd",
    "iso:country":"AU",
    "sg:address":"Darroch House 6 Briar Rd",
    "sg:city":"Felixstow",
    "sg:classifiers":[
        {
            "category":"Retail",
            "subcategory":"Funeral Services",
            "type":"Services"
        }
    ],
    "sg:phone":"+61 8 8336 9994",
    "sg:postcode":"5070",
    "sg:province":"SA",
    "sg:tags":[
        "director"
    ],
    "wof:name":"Bowen Des",
    "wof:placetype":"venue"
},
  "geometry": {"coordinates":[138.645019531,-34.8923873901],"type":"Point"}
}