{
  "type": "Feature",
  "properties": {
    "addr:full":"5 Toohey St Portsmith QLD 4870",
    "addr:housenumber":"5",
    "addr:postcode":"4870",
    "addr:street":"Toohey St Portsmith",
    "iso:country":"AU",
    "sg:address":"5 Toohey St",
    "sg:city":"Portsmith",
    "sg:classifiers":[
        {
            "category":"Utilities",
            "subcategory":"Electric",
            "type":"Services"
        }
    ],
    "sg:phone":"+61 7 4035 1075",
    "sg:postcode":"4870",
    "sg:province":"QLD",
    "sg:tags":[
        "electrical",
        "contractor"
    ],
    "wof:name":"Panther Electrics",
    "wof:placetype":"venue"
},
  "geometry": {"coordinates":[145.76167297399999,-16.9417266846],"type":"Point"}
}