{
  "type": "Feature",
  "properties": {
    "addr:full":"45 Pacific Pde Manly NSW 2095",
    "addr:housenumber":"45",
    "addr:postcode":"2095",
    "addr:street":"Pacific Pde",
    "iso:country":"AU",
    "sg:address":"45 Pacific Pde",
    "sg:city":"Manly",
    "sg:classifiers":[
        {
            "category":"Social Services",
            "subcategory":"Child Care",
            "type":"Services"
        }
    ],
    "sg:phone":"+61 2 9977 4333",
    "sg:postcode":"2095",
    "sg:province":"NSW",
    "wof:name":"Manly Noahs Ark Child Care Centre",
    "wof:placetype":"venue"
},
  "geometry": {"coordinates":[151.28196716299999,-33.7897453308],"type":"Point"}
}