{
  "type": "Feature",
  "properties": {
    "addr:full":"PO Box 98 Manunda QLD 4870",
    "addr:postcode":"4870",
    "iso:country":"AU",
    "sg:address":"PO Box 98",
    "sg:city":"Manunda",
    "sg:classifiers":[
        {
            "category":"Professional",
            "subcategory":"Business Services",
            "type":"Services"
        }
    ],
    "sg:phone":"+61 7 4053 2964",
    "sg:postcode":"4870",
    "sg:province":"QLD",
    "sg:tags":[
        "processing",
        "word"
    ],
    "wof:name":"Rae of Service",
    "wof:placetype":"venue"
},
  "geometry": {"coordinates":[145.74989318900001,-16.9132595062],"type":"Point"}
}