{
  "type": "Feature",
  "properties": {
    "addr:full":"Lot 1 Avoca Est Wellington NSW 2820",
    "addr:postcode":"2820",
    "iso:country":"AU",
    "sg:address":"Lot 1 Avoca Est",
    "sg:city":"Wellington",
    "sg:classifiers":[
        {
            "category":"Utilities",
            "subcategory":"Water",
            "type":"Services"
        }
    ],
    "sg:phone":"+61 427 101 626",
    "sg:postcode":"2820",
    "sg:province":"NSW",
    "sg:tags":[
        "hot",
        "system"
    ],
    "wof:name":"Bill Brown's Gas Service",
    "wof:placetype":"venue"
},
  "geometry": {"coordinates":[148.942962647,-32.5556411743],"type":"Point"}
}