{
  "type": "Feature",
  "properties": {
    "iso:country":"AU",
    "sg:address":"66 Canberra Drv",
    "sg:city":"Ashgrove",
    "sg:classifiers":[
        {
            "category":"Manufacturing",
            "subcategory":"Musical Instruments",
            "type":"Manufacturing & Wholesale Goods"
        }
    ],
    "sg:phone":"+61 7 3366 8210",
    "sg:postcode":"4060",
    "sg:province":"QLD",
    "sg:tags":[
        "repair",
        "maker"
    ],
    "wof:name":"Bull Guitars",
    "wof:placetype":"venue"
},
  "geometry": {"coordinates":[152.98353576700001,-27.4349994659],"type":"Point"}
}