{
  "type": "Feature",
  "properties": {
    "iso:country":"AU",
    "sg:address":"471 Maroondah Hwy",
    "sg:city":"Lilydale",
    "sg:classifiers":[
        {
            "category":"Restaurant",
            "type":"Food & Drink"
        }
    ],
    "sg:phone":"+61 3 9735 0555",
    "sg:postcode":"3140",
    "sg:province":"VIC",
    "sg:website":"http://www.theinternational.com.au",
    "wof:name":"The International At Lilydale",
    "wof:placetype":"venue"
},
  "geometry": {"coordinates":[145.365234375,-37.7531280518],"type":"Point"}
}