{
  "type": "Feature",
  "properties": {
    "addr:full":"Studio 9 ANCA Rosevear Pl Dickson ACT 2602",
    "addr:postcode":"2602",
    "iso:country":"AU",
    "sg:address":"Studio 9 ANCA Rosevear Pl",
    "sg:city":"Dickson",
    "sg:classifiers":[
        {
            "category":"Professional",
            "subcategory":"Art Services",
            "type":"Services"
        }
    ],
    "sg:phone":"+61 2 6248 9485",
    "sg:postcode":"2602",
    "sg:province":"ACT",
    "sg:tags":[
        "artist"
    ],
    "wof:name":"Cherylynn Holmes",
    "wof:placetype":"venue"
},
  "geometry": {"coordinates":[149.14358520499999,-35.2495117188],"type":"Point"}
}