{
  "type": "Feature",
  "properties": {
    "addr:full":"453 Princes Hwy Rockdale NSW 2216",
    "addr:housenumber":"453",
    "addr:postcode":"2216",
    "addr:street":"Princes Hwy",
    "iso:country":"AU",
    "sg:address":"453 Princes Hwy",
    "sg:city":"Rockdale",
    "sg:classifiers":[
        {
            "category":"Shopping",
            "subcategory":"Shoes",
            "type":"Retail Goods"
        }
    ],
    "sg:phone":"+61 2 9567 0263",
    "sg:postcode":"2216",
    "sg:province":"NSW",
    "sg:tags":[
        "footwear"
    ],
    "wof:name":"Mandic N",
    "wof:placetype":"venue"
},
  "geometry": {"coordinates":[151.13836699999999,-33.950989],"type":"Point"}
}