{
  "type": "Feature",
  "properties": {
    "iso:country":"AU",
    "sg:address":"577 Plummer St (cnr Bridge Rd),",
    "sg:city":"Port Melbourne",
    "sg:classifiers":[
        {
            "category":"Building & Trades",
            "subcategory":"Equipment Rental",
            "type":"Services"
        }
    ],
    "sg:phone":"+61 3 9646 7922",
    "sg:postcode":"3207",
    "sg:province":"VIC",
    "sg:tags":[
        "demolition",
        "contractor"
    ],
    "sg:website":"http://www.whelanthewrecker.com.au",
    "wof:name":"Whelan The Wrecker",
    "wof:placetype":"venue"
},
  "geometry": {"coordinates":[144.936157,-37.830448],"type":"Point"}
}