{
  "type": "Feature",
  "properties": {
    "addr:full":"154 Parramatta Rd Homebush NSW 2140",
    "addr:housenumber":"154",
    "addr:postcode":"2140",
    "addr:street":"Parramatta Rd",
    "iso:country":"AU",
    "sg:address":"154 Parramatta Rd",
    "sg:city":"Homebush",
    "sg:classifiers":[
        {
            "category":"Autos & Motor Vehicles",
            "subcategory":"Automobile Sales",
            "type":"Retail Goods"
        }
    ],
    "sg:phone":"+61 2 9746 5488",
    "sg:postcode":"2140",
    "sg:province":"NSW",
    "sg:tags":[
        "car",
        "used"
    ],
    "wof:name":"Homebush Intersection Pty Ltd",
    "wof:placetype":"venue"
},
  "geometry": {"coordinates":[151.08218383799999,-33.8639907837],"type":"Point"}
}