{
  "type": "Feature",
  "properties": {
    "addr:full":"U 1/ 59 Captain Cook Drv Caringbah NSW 2229",
    "addr:housenumber":"59",
    "addr:postcode":"2229",
    "addr:street":"Captain Cook Drv",
    "iso:country":"AU",
    "sg:address":"U 1/ 59 Captain Cook Drv",
    "sg:city":"Caringbah",
    "sg:classifiers":[
        {
            "category":"Professional",
            "type":"Services"
        }
    ],
    "sg:phone":"+61 2 9524 3755",
    "sg:postcode":"2229",
    "sg:province":"NSW",
    "sg:tags":[
        "overlocking",
        "rug",
        "carpet"
    ],
    "wof:name":"Carpet Choice (Caringbah)",
    "wof:placetype":"venue"
},
  "geometry": {"coordinates":[151.12115478499999,-34.0318717957],"type":"Point"}
}