{
  "type": "Feature",
  "properties": {
    "iso:country":"AU",
    "sg:address":"Research Rd",
    "sg:city":"Tanunda",
    "sg:classifiers":[
        {
            "category":"Real Estate",
            "subcategory":"Surveying",
            "type":"Services"
        }
    ],
    "sg:phone":"+61 8 8563 3677",
    "sg:postcode":"5352",
    "sg:province":"SA",
    "sg:tags":[
        "surveyor",
        "land"
    ],
    "wof:name":"McCarthy Alan",
    "wof:placetype":"venue"
},
  "geometry": {"coordinates":[138.985473633,-34.5171890259],"type":"Point"}
}