{
  "type": "Feature",
  "properties": {
    "iso:country":"AU",
    "sg:address":"42 Coonawarra Drv",
    "sg:city":"Vermont South",
    "sg:classifiers":[
        {
            "category":"Building & Trades",
            "subcategory":"Plumbing",
            "type":"Services"
        }
    ],
    "sg:phone":"+61 3 9801 1704",
    "sg:postcode":"3133",
    "sg:province":"VIC",
    "sg:tags":[
        "plumber",
        "gasfitters"
    ],
    "wof:name":"Vermont Plumbing Service",
    "wof:placetype":"venue"
},
  "geometry": {"coordinates":[145.201446533,-37.8524627686],"type":"Point"}
}