{
  "type": "Feature",
  "properties": {
    "iso:country":"AU",
    "sg:address":"Hogbin Drv",
    "sg:city":"Coffs Harbour",
    "sg:classifiers":[
        {
            "category":"Arena",
            "subcategory":"Sports Club",
            "type":"Entertainment"
        }
    ],
    "sg:phone":"+61 2 6653 1779",
    "sg:postcode":"2450",
    "sg:province":"NSW",
    "sg:tags":[
        "league",
        "rugby"
    ],
    "wof:name":"Coffs Harbour Leagues Club",
    "wof:placetype":"venue"
},
  "geometry": {"coordinates":[153.12153599999999,-30.307045],"type":"Point"}
}