{
  "type": "Feature",
  "properties": {
    "addr:full":"Shp 4/ 36 Riverview St North Richmond NSW 2754",
    "addr:housenumber":"/ 36",
    "addr:postcode":"2754",
    "addr:street":"Riverview St",
    "iso:country":"AU",
    "sg:address":"Shp 4/ 36 Riverview St",
    "sg:city":"North Richmond",
    "sg:classifiers":[
        {
            "category":"Shopping",
            "subcategory":"Beauty & Cosmetics",
            "type":"Retail Goods"
        }
    ],
    "sg:phone":"+61 2 4571 4323",
    "sg:postcode":"2754",
    "sg:province":"NSW",
    "wof:name":"Kerrys Discount Beauty Products",
    "wof:placetype":"venue"
},
  "geometry": {"coordinates":[150.71890258799999,-33.580745697],"type":"Point"}
}