{
  "type": "Feature",
  "properties": {
    "iso:country":"AU",
    "sg:address":"Lowens La",
    "sg:city":"Benalla",
    "sg:classifiers":[
        {
            "category":"Professional",
            "type":"Services"
        }
    ],
    "sg:phone":"+61 3 5762 3479",
    "sg:postcode":"3672",
    "sg:province":"VIC",
    "sg:tags":[
        "spray",
        "painting"
    ],
    "wof:name":"Greg Young",
    "wof:placetype":"venue"
},
  "geometry": {"coordinates":[146.010666,-36.541416],"type":"Point"}
}