{
  "type": "Feature",
  "properties": {
    "addr:full":"56 Gleneagles Rd Mt Osmond SA 5064",
    "addr:housenumber":"56",
    "addr:postcode":"5064",
    "addr:street":"Gleneagles Rd;Osmond",
    "iso:country":"AU",
    "sg:address":"56 Gleneagles Rd",
    "sg:city":"Mt Osmond",
    "sg:classifiers":[
        {
            "category":"Personal",
            "subcategory":"Beauty Salon",
            "type":"Services"
        }
    ],
    "sg:phone":"+61 417 379 333",
    "sg:postcode":"5064",
    "sg:province":"SA",
    "sg:tags":[
        "hairdresser"
    ],
    "wof:name":"Coco Raffles",
    "wof:placetype":"venue"
},
  "geometry": {"coordinates":[138.657913208,-34.9678382874],"type":"Point"}
}