{
  "type": "Feature",
  "properties": {
    "addr:full":"8 Lovell St Hawthorn East VIC 3123",
    "addr:housenumber":"8",
    "addr:postcode":"3123",
    "addr:street":"Lovell St",
    "iso:country":"AU",
    "sg:address":"8 Lovell St",
    "sg:city":"Hawthorn East",
    "sg:classifiers":[
        {
            "category":"Social Services",
            "subcategory":"Retirement Home",
            "type":"Services"
        }
    ],
    "sg:phone":"+61 3 9822 1123",
    "sg:postcode":"3123",
    "sg:province":"VIC",
    "sg:tags":[
        "life",
        "coaching"
    ],
    "wof:name":"Inspired Reality",
    "wof:placetype":"venue"
},
  "geometry": {"coordinates":[145.046600342,-37.8425598145],"type":"Point"}
}