{
  "type": "Feature",
  "properties": {
    "addr:full":"Shop 3 16b Level 3 Redbank Plz Redbank QLD 4301",
    "addr:housenumber":"shop;16b",
    "addr:postcode":"4301",
    "addr:street":"Plz",
    "iso:country":"AU",
    "sg:address":"Shop 3",
    "sg:city":"16b Level 3 Redbank Plz Redbank",
    "sg:classifiers":[
        {
            "category":"Health Services",
            "subcategory":"Optometrist",
            "type":"Services"
        }
    ],
    "sg:phone":"+61 7 3818 7700",
    "sg:postcode":"4301",
    "sg:province":"QLD",
    "wof:name":"Matthew Walcott Optometrist",
    "wof:placetype":"venue"
},
  "geometry": {"coordinates":[152.85017395,-27.6409759521],"type":"Point"}
}