{
  "type": "Feature",
  "properties": {
    "addr:full":"PO Box 4012 Woolloongabba QLD 4102",
    "addr:postcode":"4102",
    "iso:country":"AU",
    "sg:address":"PO Box 4012",
    "sg:city":"Woolloongabba",
    "sg:classifiers":[
        {
            "category":"Restaurant",
            "type":"Food & Drink"
        }
    ],
    "sg:phone":"+61 7 3391 1413",
    "sg:postcode":"4102",
    "sg:province":"QLD",
    "wof:name":"Fiasco Steakhouse",
    "wof:placetype":"venue"
},
  "geometry": {"coordinates":[153.03060913100001,-27.4856376648],"type":"Point"}
}