{
  "type": "Feature",
  "properties": {
    "addr:full":"13 Turnberry Pl Carindale QLD 4152",
    "addr:housenumber":"13",
    "addr:postcode":"4152",
    "addr:street":"Turnberry Pl",
    "iso:country":"AU",
    "sg:address":"13 Turnberry Pl",
    "sg:city":"Carindale",
    "sg:classifiers":[
        {
            "category":"Building & Trades",
            "subcategory":"Landscaping Services",
            "type":"Services"
        }
    ],
    "sg:phone":"+61 7 3849 1588",
    "sg:postcode":"4152",
    "sg:province":"QLD",
    "sg:tags":[
        "consultant"
    ],
    "wof:name":"Le Rocks",
    "wof:placetype":"venue"
},
  "geometry": {"coordinates":[153.10426330600001,-27.525018692],"type":"Point"}
}