{
  "type": "Feature",
  "properties": {
    "iso:country":"AU",
    "sg:address":"320 Townsend Rd",
    "sg:city":"Moolap",
    "sg:classifiers":[
        {
            "category":"Home & Garden",
            "subcategory":"Garden Supply",
            "type":"Retail Goods"
        }
    ],
    "sg:phone":"+61 3 5248 8218",
    "sg:postcode":"3221",
    "sg:province":"VIC",
    "sg:tags":[
        "fertilizer"
    ],
    "wof:name":"Sykes Equestrian Centre Pty-Ltd",
    "wof:placetype":"venue"
},
  "geometry": {"coordinates":[144.417603,-38.184376],"type":"Point"}
}