{
  "type": "Feature",
  "properties": {
    "addr:full":"Shop 16A Riverton Forum, Cnr High Rd & Willeri Dr Riverton WA 6148",
    "addr:housenumber":"16a",
    "addr:postcode":"6148",
    "addr:street":"High Rd & Willeri Dr",
    "iso:country":"AU",
    "sg:address":"Shop 16A Riverton Forum, Cnr High Rd & Willeri Dr",
    "sg:city":"Riverton",
    "sg:classifiers":[
        {
            "category":"Professional",
            "subcategory":"Computer Services",
            "type":"Services"
        }
    ],
    "sg:phone":"+61 8 9354 5255",
    "sg:postcode":"6148",
    "sg:province":"WA",
    "sg:tags":[
        "repairs",
        "upgrade",
        "equipment"
    ],
    "wof:name":"Techno Electronix",
    "wof:placetype":"venue"
},
  "geometry": {"coordinates":[115.894211,-32.038651],"type":"Point"}
}