{
  "type": "Feature",
  "properties": {
    "addr:full":"Shp23/ 89 Pine Ave Leeton NSW 2705",
    "addr:housenumber":"89",
    "addr:postcode":"2705",
    "addr:street":"Pine Ave",
    "iso:country":"AU",
    "sg:address":"Shp23/ 89 Pine Ave",
    "sg:city":"Leeton",
    "sg:classifiers":[
        {
            "category":"Food & Beverages",
            "subcategory":"Liquor & Beverages",
            "type":"Retail Goods"
        }
    ],
    "sg:phone":"+61 2 6953 2294",
    "sg:postcode":"2705",
    "sg:province":"NSW",
    "sg:tags":[
        "store"
    ],
    "wof:name":"Liquor Barrell",
    "wof:placetype":"venue"
},
  "geometry": {"coordinates":[146.405197144,-34.5515174866],"type":"Point"}
}