{
  "type": "Feature",
  "properties": {
    "addr:full":"75 Brighton Pde Southport QLD 4215",
    "addr:housenumber":"75",
    "addr:postcode":"4215",
    "addr:street":"Brighton Pde",
    "iso:country":"AU",
    "sg:address":"75 Brighton Pde",
    "sg:city":"Southport",
    "sg:classifiers":[
        {
            "category":"Restaurant",
            "type":"Food & Drink"
        }
    ],
    "sg:phone":"+61 7 5531 4099",
    "sg:postcode":"4215",
    "sg:province":"QLD",
    "wof:name":"L'Esprit On The Water",
    "wof:placetype":"venue"
},
  "geometry": {"coordinates":[153.40586852999999,-27.9363689423],"type":"Point"}
}