{
  "type": "Feature",
  "properties": {
    "addr:full":"59 Boxgrove Ave Wynnum North QLD 4178",
    "addr:housenumber":"59",
    "addr:postcode":"4178",
    "addr:street":"Boxgrove Ave",
    "iso:country":"AU",
    "sg:address":"59 Boxgrove Ave",
    "sg:city":"Wynnum North",
    "sg:classifiers":[
        {
            "category":"Retail",
            "subcategory":"Car Wash",
            "type":"Services"
        }
    ],
    "sg:phone":"+61 412 036 583",
    "sg:postcode":"4178",
    "sg:province":"QLD",
    "sg:tags":[
        "truck",
        "cleaning"
    ],
    "wof:name":"Master Mobile Car Detailing",
    "wof:placetype":"venue"
},
  "geometry": {"coordinates":[153.16122436500001,-27.441696167],"type":"Point"}
}