{
  "type": "Feature",
  "properties": {
    "iso:country":"AU",
    "sg:address":"602- 630 Doncaster Rd",
    "sg:city":"Doncaster",
    "sg:classifiers":[
        {
            "category":"Building & Trades",
            "subcategory":"Construction",
            "type":"Services"
        }
    ],
    "sg:phone":"+61 3 9840 6555",
    "sg:postcode":"3108",
    "sg:province":"VIC",
    "sg:tags":[
        "pool",
        "swimming"
    ],
    "wof:name":"Clark Pools & Spas",
    "wof:placetype":"venue"
},
  "geometry": {"coordinates":[145.12640380900001,-37.7875022888],"type":"Point"}
}