{
  "type": "Feature",
  "properties": {
    "iso:country":"AU",
    "sg:address":"176a Somerville Rd",
    "sg:city":"Kingsville",
    "sg:classifiers":[
        {
            "category":"Food & Beverages",
            "subcategory":"Fruits & Vegetables",
            "type":"Retail Goods"
        }
    ],
    "sg:phone":"+61 3 9314 9962",
    "sg:postcode":"3012",
    "sg:province":"VIC",
    "sg:tags":[
        "greengrocer",
        "fruiterer"
    ],
    "wof:name":"West Footscray Fruit Market",
    "wof:placetype":"venue"
},
  "geometry": {"coordinates":[144.88250732399999,-37.8125457764],"type":"Point"}
}