{
  "type": "Feature",
  "properties": {
    "iso:country":"AU",
    "sg:address":"28 Barnett Pl",
    "sg:city":"Ernest Junction",
    "sg:classifiers":[
        {
            "category":"Wholesale",
            "subcategory":"Construction Materials",
            "type":"Manufacturing & Wholesale Goods"
        }
    ],
    "sg:phone":"+61 7 5594 6988",
    "sg:postcode":"4215",
    "sg:province":"QLD",
    "sg:tags":[
        "wholesaler",
        "lighting",
        "mfrs",
        "accessory"
    ],
    "wof:name":"Cosmoluce Pty Ltd",
    "wof:placetype":"venue"
},
  "geometry": {"coordinates":[153.358642578,-27.963809967],"type":"Point"}
}