{
  "type": "Feature",
  "properties": {
    "addr:full":"14 Rooty Hill Rd South Rooty Hill NSW 2766",
    "addr:housenumber":"14",
    "addr:postcode":"2766",
    "addr:street":"Rooty Hill Rd South",
    "iso:country":"AU",
    "sg:address":"14 Rooty Hill Rd South",
    "sg:city":"Rooty Hill",
    "sg:classifiers":[
        {
            "category":"Food & Beverages",
            "subcategory":"Bakery",
            "type":"Retail Goods"
        }
    ],
    "sg:phone":"+61 2 9675 7790",
    "sg:postcode":"2766",
    "sg:province":"NSW",
    "sg:tags":[
        "baker"
    ],
    "wof:name":"Hughie Bakery",
    "wof:placetype":"venue"
},
  "geometry": {"coordinates":[150.84442138700001,-33.7726249695],"type":"Point"}
}