{
  "type": "Feature",
  "properties": {
    "addr:full":"383 Main Rd Glenorchy TAS 7010",
    "addr:housenumber":"383",
    "addr:postcode":"7010",
    "addr:street":"Main Rd",
    "iso:country":"AU",
    "sg:address":"383 Main Rd",
    "sg:city":"Glenorchy",
    "sg:classifiers":[
        {
            "category":"Shopping",
            "subcategory":"Optical Goods",
            "type":"Retail Goods"
        }
    ],
    "sg:phone":"+61 3 6245 0822",
    "sg:postcode":"7010",
    "sg:province":"TAS",
    "sg:tags":[
        "dispenser",
        "prescription"
    ],
    "sg:website":"http://www.eyelines.com.au",
    "wof:name":"Eye Lines",
    "wof:placetype":"venue"
},
  "geometry": {"coordinates":[147.275192261,-42.8328552246],"type":"Point"}
}