{
  "type": "Feature",
  "properties": {
    "iso:country":"AU",
    "sg:address":"283 King St",
    "sg:city":"Newtown",
    "sg:classifiers":[
        {
            "category":"Food & Beverages",
            "subcategory":"Bakery",
            "type":"Retail Goods"
        }
    ],
    "sg:phone":"+61 2 9557 2565",
    "sg:postcode":"2042",
    "sg:province":"NSW",
    "sg:tags":[
        "cake",
        "shop",
        "pastry"
    ],
    "wof:name":"Shakespeares Pie Co Australia Pty Ltd",
    "wof:placetype":"venue"
},
  "geometry": {"coordinates":[151.179733,-33.896454],"type":"Point"}
}