{
  "type": "Feature",
  "properties": {
    "addr:full":"61 Commonwealth St Bathurst NSW 2795",
    "addr:housenumber":"61",
    "addr:postcode":"2795",
    "addr:street":"Commonwealth St",
    "iso:country":"AU",
    "sg:address":"61 Commonwealth St",
    "sg:city":"Bathurst",
    "sg:classifiers":[
        {
            "category":"Recreation",
            "subcategory":"Fishing",
            "type":"Entertainment"
        }
    ],
    "sg:phone":"+61 427 986 473",
    "sg:postcode":"2795",
    "sg:province":"NSW",
    "sg:tags":[
        "trip"
    ],
    "wof:name":"Fish River Fly Fishing Co",
    "wof:placetype":"venue"
},
  "geometry": {"coordinates":[149.56761169399999,-33.4077796936],"type":"Point"}
}