{
  "type": "Feature",
  "properties": {
    "addr:full":"3/ 98 Elizabeth St Tighes Hill NSW 2297",
    "addr:housenumber":"/ 98",
    "addr:postcode":"2297",
    "addr:street":"Elizabeth St",
    "iso:country":"AU",
    "sg:address":"3/ 98 Elizabeth St",
    "sg:city":"Tighes Hill",
    "sg:classifiers":[
        {
            "category":"Wholesale",
            "subcategory":"Metals & Minerals",
            "type":"Manufacturing & Wholesale Goods"
        }
    ],
    "sg:phone":"+61 2 4962 4700",
    "sg:postcode":"2297",
    "sg:province":"NSW",
    "sg:tags":[
        "steel",
        "merchant"
    ],
    "wof:name":"Ezimetal",
    "wof:placetype":"venue"
},
  "geometry": {"coordinates":[151.756958008,-32.907245636],"type":"Point"}
}