{
  "type": "Feature",
  "properties": {
    "iso:country":"AU",
    "sg:address":"166 Boat Harbour Drv",
    "sg:city":"Hervey Bay",
    "sg:classifiers":[
        {
            "category":"Utilities",
            "subcategory":"Telephone",
            "type":"Services"
        }
    ],
    "sg:phone":"+61 1300 009 433",
    "sg:postcode":"4655",
    "sg:province":"QLD",
    "wof:name":"Widelinx",
    "wof:placetype":"venue"
},
  "geometry": {"coordinates":[152.837357,-25.287842],"type":"Point"}
}