{
  "type": "Feature",
  "properties": {
    "iso:country":"AU",
    "sg:address":"5 Esperance St",
    "sg:city":"Belmont North",
    "sg:classifiers":[
        {
            "category":"Building & Trades",
            "subcategory":"Plumbing",
            "type":"Services"
        }
    ],
    "sg:phone":"+61 2 4965 7695",
    "sg:postcode":"2280",
    "sg:province":"NSW",
    "sg:tags":[
        "plumber",
        "gasfitters"
    ],
    "wof:name":"Anschau D",
    "wof:placetype":"venue"
},
  "geometry": {"coordinates":[151.67835998499999,-33.0125846863],"type":"Point"}
}