{
  "type": "Feature",
  "properties": {
    "iso:country":"AU",
    "sg:address":"47 Grigg St",
    "sg:city":"Ravenshoe",
    "sg:classifiers":[
        {
            "category":"Travel",
            "subcategory":"Hotels & Motels",
            "type":"Entertainment"
        }
    ],
    "sg:phone":"+61 7 4097 6109",
    "sg:postcode":"4872",
    "sg:province":"QLD",
    "wof:name":"Club Hotel-Motel",
    "wof:placetype":"venue"
},
  "geometry": {"coordinates":[145.48333740199999,-17.6085586548],"type":"Point"}
}