{
  "type": "Feature",
  "properties": {
    "addr:full":"19 Konkerberry Drv Kununurra WA 6743",
    "addr:housenumber":"19",
    "addr:postcode":"6743",
    "addr:street":"Konkerberry Drv",
    "iso:country":"AU",
    "sg:address":"19 Konkerberry Drv",
    "sg:city":"Kununurra",
    "sg:classifiers":[
        {
            "category":"Shopping",
            "subcategory":"Clothing, Apparel, & Fashions",
            "type":"Retail Goods"
        }
    ],
    "sg:phone":"+61 8 9169 1425",
    "sg:postcode":"6743",
    "sg:province":"WA",
    "sg:tags":[
        "recycled",
        "clothing"
    ],
    "wof:name":"Recycled Clothing Shed",
    "wof:placetype":"venue"
},
  "geometry": {"coordinates":[128.735671997,-15.7770042419],"type":"Point"}
}