{
  "type": "Feature",
  "properties": {
    "addr:full":"44 Raedon St Biloela QLD 4715",
    "addr:housenumber":"44",
    "addr:postcode":"4715",
    "addr:street":"Raedon St",
    "iso:country":"AU",
    "sg:address":"44 Raedon St",
    "sg:city":"Biloela",
    "sg:classifiers":[
        {
            "category":"Retail",
            "subcategory":"Auto Repair",
            "type":"Services"
        }
    ],
    "sg:phone":"+61 7 4992 1237",
    "sg:postcode":"4715",
    "sg:province":"QLD",
    "sg:tags":[
        "beater",
        "painter",
        "panel"
    ],
    "wof:name":"Daniel Hey Smash Repairs",
    "wof:placetype":"venue"
},
  "geometry": {"coordinates":[150.50213623100001,-24.4040393829],"type":"Point"}
}