{
  "type": "Feature",
  "properties": {
    "addr:full":"Bronberg Plaza Slatyer Ave Southport QLD 4215",
    "addr:postcode":"4215",
    "addr:street":"Bronberg;Slatyer Ave",
    "iso:country":"AU",
    "sg:address":"Bronberg Plaza Slatyer Ave",
    "sg:city":"Southport",
    "sg:classifiers":[
        {
            "category":"Food & Beverages",
            "subcategory":"Liquor & Beverages",
            "type":"Retail Goods"
        }
    ],
    "sg:phone":"+61 7 5597 7555",
    "sg:postcode":"4215",
    "sg:province":"QLD",
    "sg:tags":[
        "store"
    ],
    "wof:name":"Bronberg Bottle Shop",
    "wof:placetype":"venue"
},
  "geometry": {"coordinates":[153.41392517099999,-27.997543335],"type":"Point"}
}