{
  "type": "Feature",
  "properties": {
    "iso:country":"AU",
    "sg:address":"PO Box 5277",
    "sg:city":"Wodonga",
    "sg:classifiers":[
        {
            "category":"Shopping",
            "subcategory":"Discount & Variety Stores",
            "type":"Retail Goods"
        }
    ],
    "sg:phone":"+61 428 561 668",
    "sg:postcode":"3690",
    "sg:province":"VIC",
    "sg:tags":[
        "register",
        "cash"
    ],
    "wof:name":"Central Printers & PCs",
    "wof:placetype":"venue"
},
  "geometry": {"coordinates":[146.84840393100001,-36.1168785095],"type":"Point"}
}