{
  "type": "Feature",
  "properties": {
    "iso:country":"AU",
    "sg:address":"197 Eumarella Rd",
    "sg:city":"Doonan",
    "sg:classifiers":[
        {
            "category":"Building & Trades",
            "subcategory":"Landscaping Services",
            "type":"Services"
        }
    ],
    "sg:phone":"+61 7 5471 1407",
    "sg:postcode":"4562",
    "sg:province":"QLD",
    "sg:tags":[
        "designer",
        "landscape",
        "contractor"
    ],
    "wof:name":"Simon Bland Landscaping",
    "wof:placetype":"venue"
},
  "geometry": {"coordinates":[153.052825928,-26.4413414001],"type":"Point"}
}