{
  "type": "Feature",
  "properties": {
    "addr:full":"3 Edward St Orange NSW 2800",
    "addr:housenumber":"3",
    "addr:postcode":"2800",
    "addr:street":"Edward St",
    "iso:country":"AU",
    "sg:address":"3 Edward St",
    "sg:city":"Orange",
    "sg:classifiers":[
        {
            "category":"Wholesale",
            "subcategory":"Fruits & Vegetables",
            "type":"Manufacturing & Wholesale Goods"
        }
    ],
    "sg:phone":"+61 2 6362 9560",
    "sg:postcode":"2800",
    "sg:province":"NSW",
    "sg:tags":[
        "produce",
        "grain"
    ],
    "wof:name":"Martin Bros (Orange) Pty Ltd",
    "wof:placetype":"venue"
},
  "geometry": {"coordinates":[149.104812622,-33.2935028076],"type":"Point"}
}