{
  "type": "Feature",
  "properties": {
    "iso:country":"AU",
    "sg:address":"32/ 23 Baden St",
    "sg:city":"Coogee",
    "sg:classifiers":[
        {
            "category":"Retail",
            "subcategory":"Repair Shop",
            "type":"Services"
        }
    ],
    "sg:phone":"+61 2 9665 0222",
    "sg:postcode":"2034",
    "sg:province":"NSW",
    "sg:tags":[
        "machine",
        "sewing"
    ],
    "wof:name":"Reynolds Sewing Machines",
    "wof:placetype":"venue"
},
  "geometry": {"coordinates":[151.26017761200001,-33.9180412292],"type":"Point"}
}