{
  "type": "Feature",
  "properties": {
    "iso:country":"AU",
    "sg:address":"38 Crown St",
    "sg:city":"Dubbo",
    "sg:classifiers":[
        {
            "category":"Building & Trades",
            "subcategory":"Construction",
            "type":"Services"
        }
    ],
    "sg:phone":"+61 2 6884 0639",
    "sg:postcode":"2830",
    "sg:province":"NSW",
    "sg:tags":[
        "home",
        "air conditioning"
    ],
    "wof:name":"Tim Blyton",
    "wof:placetype":"venue"
},
  "geometry": {"coordinates":[148.61668395999999,-32.2666053772],"type":"Point"}
}