{
  "type": "Feature",
  "properties": {
    "addr:full":"208 Walcott St Mt Lawley WA 6050",
    "addr:housenumber":"208",
    "addr:postcode":"6050",
    "addr:street":"Walcott St",
    "iso:country":"AU",
    "sg:address":"208 Walcott St",
    "sg:city":"Mt Lawley",
    "sg:classifiers":[
        {
            "category":"Arts & Performance",
            "subcategory":"Theater",
            "type":"Entertainment"
        }
    ],
    "sg:phone":"+61 419 943 416",
    "sg:postcode":"6050",
    "sg:province":"WA",
    "sg:tags":[
        "theatrical",
        "supply"
    ],
    "wof:name":"Great Pretender",
    "wof:placetype":"venue"
},
  "geometry": {"coordinates":[115.868339539,-31.9309768677],"type":"Point"}
}