{
  "type": "Feature",
  "properties": {
    "addr:full":"1 Whipbird Pl Glenview QLD 4553",
    "addr:housenumber":"1",
    "addr:postcode":"4553",
    "addr:street":"Whipbird Pl",
    "iso:country":"AU",
    "sg:address":"1 Whipbird Pl",
    "sg:city":"Glenview",
    "sg:classifiers":[
        {
            "category":"Building & Trades",
            "subcategory":"Construction",
            "type":"Services"
        }
    ],
    "sg:phone":"+61 7 5494 5451",
    "sg:postcode":"4553",
    "sg:province":"QLD",
    "sg:tags":[
        "fencing",
        "contractor"
    ],
    "wof:name":"Glenview Fencing",
    "wof:placetype":"venue"
},
  "geometry": {"coordinates":[153.02108799999999,-26.763021],"type":"Point"}
}