{
  "type": "Feature",
  "properties": {
    "addr:full":"31 Thomas Wedge Drv Wangaratta VIC 3677",
    "addr:housenumber":"31",
    "addr:postcode":"3677",
    "addr:street":"Thomas Wedge Drv",
    "iso:country":"AU",
    "sg:address":"31 Thomas Wedge Drv",
    "sg:city":"Wangaratta",
    "sg:classifiers":[
        {
            "category":"Professional",
            "subcategory":"Art Services",
            "type":"Services"
        }
    ],
    "sg:phone":"+61 408 574 216",
    "sg:postcode":"3677",
    "sg:province":"VIC",
    "sg:tags":[
        "decorator",
        "painter"
    ],
    "wof:name":"Andrews Phil",
    "wof:placetype":"venue"
},
  "geometry": {"coordinates":[146.322555542,-36.380279541],"type":"Point"}
}