{
  "type": "Feature",
  "properties": {
    "iso:country":"AU",
    "sg:address":"Lot 2 Boundary Rd",
    "sg:city":"Deception Bay",
    "sg:classifiers":[
        {
            "category":"Home & Garden",
            "subcategory":"Building Materials",
            "type":"Retail Goods"
        }
    ],
    "sg:phone":"+61 7 3203 2760",
    "sg:postcode":"4508",
    "sg:province":"QLD",
    "sg:tags":[
        "secondhand"
    ],
    "wof:name":"Knijff Demolition",
    "wof:placetype":"venue"
},
  "geometry": {"coordinates":[153.00932312,-27.2029342651],"type":"Point"}
}