{
  "type": "Feature",
  "properties": {
    "addr:full":"327 Armidale St South Grafton NSW 2460",
    "addr:housenumber":"327",
    "addr:postcode":"2460",
    "addr:street":"Armidale St",
    "iso:country":"AU",
    "sg:address":"327 Armidale St",
    "sg:city":"South Grafton",
    "sg:classifiers":[
        {
            "category":"Food & Beverages",
            "subcategory":"Farmers Market",
            "type":"Retail Goods"
        }
    ],
    "sg:phone":"+61 2 6642 7107",
    "sg:postcode":"2460",
    "sg:province":"NSW",
    "sg:tags":[
        "beekeeper"
    ],
    "wof:name":"G & B Apiaries Pty Ltd",
    "wof:placetype":"venue"
},
  "geometry": {"coordinates":[152.94146728499999,-29.7104568481],"type":"Point"}
}