{
  "type": "Feature",
  "properties": {
    "addr:full":"17- 19 Industrial Ave Thomastown VIC 3074",
    "addr:housenumber":"19",
    "addr:postcode":"3074",
    "addr:street":"Industrial Ave",
    "iso:country":"AU",
    "sg:address":"17- 19 Industrial Ave",
    "sg:city":"Thomastown",
    "sg:classifiers":[
        {
            "category":"Building & Trades",
            "subcategory":"Construction",
            "type":"Services"
        }
    ],
    "sg:phone":"+61 3 8807 2158",
    "sg:postcode":"3074",
    "sg:province":"VIC",
    "sg:tags":[
        "fitting",
        "line",
        "electric",
        "power"
    ],
    "wof:name":"Coslee Poles",
    "wof:placetype":"venue"
},
  "geometry": {"coordinates":[144.979171753,-37.6893310547],"type":"Point"}
}