{
  "type": "Feature",
  "properties": {
    "addr:full":"Display Home, Cnr Victoria Rd & The Gateway, Lilydale Lilydale VIC 3140",
    "addr:postcode":"3140",
    "addr:street":"Cnr Victoria Rd & The",
    "iso:country":"AU",
    "sg:address":"Display Home, Cnr Victoria Rd",
    "sg:city":"& The Gateway, Lilydale Lilydale",
    "sg:classifiers":[
        {
            "category":"Real Estate",
            "subcategory":"Real Estate Agent",
            "type":"Services"
        }
    ],
    "sg:phone":"+61 3 9739 6455",
    "sg:postcode":"3140",
    "sg:province":"VIC",
    "wof:name":"Max Brown Real Estate",
    "wof:placetype":"venue"
},
  "geometry": {"coordinates":[145.33522033700001,-37.7566299438],"type":"Point"}
}