{
  "type": "Feature",
  "properties": {
    "iso:country":"AU",
    "sg:address":"105 Colin Rd",
    "sg:city":"Wembley Downs",
    "sg:classifiers":[
        {
            "category":"Professional",
            "subcategory":"Management & Consulting",
            "type":"Services"
        }
    ],
    "sg:phone":"+61 8 9245 1777",
    "sg:postcode":"6019",
    "sg:province":"WA",
    "sg:tags":[
        "consultant"
    ],
    "wof:name":"Centre For Continuous Improvement",
    "wof:placetype":"venue"
},
  "geometry": {"coordinates":[115.766822815,-31.9096355438],"type":"Point"}
}