{
  "type": "Feature",
  "properties": {
    "iso:country":"AU",
    "sg:address":"Unit 2, 444- 446 South Gippsland Hwy",
    "sg:city":"Dandenong South",
    "sg:classifiers":[
        {
            "category":"Home & Garden",
            "subcategory":"Hardware",
            "type":"Retail Goods"
        }
    ],
    "sg:phone":"+61 3 8795 2466",
    "sg:postcode":"3164",
    "sg:province":"VIC",
    "sg:tags":[
        "part",
        "air conditioning"
    ],
    "wof:name":"Bonaire",
    "wof:placetype":"venue"
},
  "geometry": {"coordinates":[145.24473571799999,-38.0341720581],"type":"Point"}
}