{
  "type": "Feature",
  "properties": {
    "addr:full":"1a Haines Rd Tea Tree Gully SA 5091",
    "addr:housenumber":"1a",
    "addr:postcode":"5091",
    "addr:street":"Haines Rd Tea Tree",
    "iso:country":"AU",
    "sg:address":"1a Haines Rd",
    "sg:city":"Tea Tree Gully",
    "sg:classifiers":[
        {
            "category":"Travel",
            "subcategory":"Travel Agent",
            "type":"Entertainment"
        }
    ],
    "sg:phone":"+61 8 8264 1487",
    "sg:postcode":"5091",
    "sg:province":"SA",
    "sg:tags":[
        "consultant"
    ],
    "wof:name":"Bryley Coachlines",
    "wof:placetype":"venue"
},
  "geometry": {"coordinates":[138.73106384299999,-34.8200378418],"type":"Point"}
}