{
  "type": "Feature",
  "properties": {
    "iso:country":"AU",
    "sg:address":"9- 11 Harcourt St",
    "sg:city":"Bendigo",
    "sg:classifiers":[
        {
            "category":"Organizations",
            "subcategory":"Non-profit Organization",
            "type":"Services"
        }
    ],
    "sg:phone":"+61 3 5443 3826",
    "sg:postcode":"3550",
    "sg:province":"VIC",
    "sg:tags":[
        "support",
        "disability",
        "organisation"
    ],
    "wof:name":"Peter Harcourt Disability Services",
    "wof:placetype":"venue"
},
  "geometry": {"coordinates":[144.28929138199999,-36.7652206421],"type":"Point"}
}