{
  "type": "Feature",
  "properties": {
    "addr:full":"47 Lade St Gaythorne QLD 4051",
    "addr:housenumber":"47",
    "addr:postcode":"4051",
    "addr:street":"Lade St",
    "iso:country":"AU",
    "sg:address":"47 Lade St",
    "sg:city":"Gaythorne",
    "sg:classifiers":[
        {
            "category":"Building & Trades",
            "subcategory":"Plumbing",
            "type":"Services"
        }
    ],
    "sg:phone":"+61 418 491 004",
    "sg:postcode":"4051",
    "sg:province":"QLD",
    "sg:tags":[
        "plumber",
        "gasfitters"
    ],
    "wof:name":"Plumbers We Are",
    "wof:placetype":"venue"
},
  "geometry": {"coordinates":[152.984542847,-27.4154834747],"type":"Point"}
}