{
  "type": "Feature",
  "properties": {
    "addr:full":"120 Narrabeen Park Pde Warriewood NSW 2102",
    "addr:housenumber":"120",
    "addr:postcode":"2102",
    "addr:street":"Narrabeen Park Pde",
    "iso:country":"AU",
    "sg:address":"120 Narrabeen Park Pde",
    "sg:city":"Warriewood",
    "sg:classifiers":[
        {
            "category":"Personal",
            "subcategory":"Beauty Salon",
            "type":"Services"
        }
    ],
    "sg:phone":"+61 2 9979 3379",
    "sg:postcode":"2102",
    "sg:province":"NSW",
    "sg:tags":[
        "hairdresser"
    ],
    "wof:name":"Hairdazzled",
    "wof:placetype":"venue"
},
  "geometry": {"coordinates":[151.30725100000001,-33.691715],"type":"Point"}
}