{
  "type": "Feature",
  "properties": {
    "addr:full":"Factory 3/ 6 Macquarie Drv Thomastown VIC 3074",
    "addr:housenumber":"/ 6",
    "addr:postcode":"3074",
    "addr:street":"Macquarie Drv",
    "iso:country":"AU",
    "sg:address":"Factory 3/ 6 Macquarie Drv",
    "sg:city":"Thomastown",
    "sg:classifiers":[
        {
            "category":"Building & Trades",
            "subcategory":"Construction",
            "type":"Services"
        }
    ],
    "sg:phone":"+61 3 9465 8155",
    "sg:postcode":"3074",
    "sg:province":"VIC",
    "sg:tags":[
        "contractor"
    ],
    "wof:name":"Kent I D & R N Bros Pty Ltd",
    "wof:placetype":"venue"
},
  "geometry": {"coordinates":[145.033081055,-37.6917877197],"type":"Point"}
}