{
  "type": "Feature",
  "properties": {
    "addr:full":"24 Crescent Drv Margate TAS 7054",
    "addr:housenumber":"24",
    "addr:postcode":"7054",
    "addr:street":"Crescent Drv",
    "iso:country":"AU",
    "sg:address":"24 Crescent Drv",
    "sg:city":"Margate",
    "sg:classifiers":[
        {
            "category":"Home & Garden",
            "subcategory":"Carpets & Floor Coverings",
            "type":"Retail Goods"
        }
    ],
    "sg:phone":"+61 3 6267 2632",
    "sg:postcode":"7054",
    "sg:province":"TAS",
    "sg:tags":[
        "double",
        "window",
        "glazed"
    ],
    "wof:name":"Hansson's Joinery",
    "wof:placetype":"venue"
},
  "geometry": {"coordinates":[147.266403,-43.034489],"type":"Point"}
}