{
  "type": "Feature",
  "properties": {
    "iso:country":"AU",
    "sg:address":"55 Barkley St",
    "sg:city":"Mornington",
    "sg:classifiers":[
        {
            "category":"Restaurant",
            "type":"Food & Drink"
        }
    ],
    "sg:phone":"+61 3 5975 9988",
    "sg:postcode":"3931",
    "sg:province":"VIC",
    "wof:name":"Casa Blanca",
    "wof:placetype":"venue"
},
  "geometry": {"coordinates":[145.038619995,-38.2214050293],"type":"Point"}
}