{
  "type": "Feature",
  "properties": {
    "iso:country":"AU",
    "sg:address":"314 Military Rd",
    "sg:city":"Grange",
    "sg:classifiers":[
        {
            "category":"Health Services",
            "subcategory":"Doctor",
            "type":"Services"
        }
    ],
    "sg:phone":"+61 8 8235 9333",
    "sg:postcode":"5022",
    "sg:province":"SA",
    "sg:tags":[
        "medical",
        "practitioner"
    ],
    "wof:name":"Tsirgiotis Pan",
    "wof:placetype":"venue"
},
  "geometry": {"coordinates":[138.49081420900001,-34.9017333984],"type":"Point"}
}