{
  "type": "Feature",
  "properties": {
    "addr:full":"27 Jessie St Richmond VIC 3121",
    "addr:housenumber":"27",
    "addr:postcode":"3121",
    "addr:street":"Jessie St",
    "iso:country":"AU",
    "sg:address":"27 Jessie St",
    "sg:city":"Richmond",
    "sg:classifiers":[
        {
            "category":"Professional",
            "subcategory":"Art Services",
            "type":"Services"
        }
    ],
    "sg:phone":"+61 3 9421 3811",
    "sg:postcode":"3121",
    "sg:province":"VIC",
    "sg:tags":[
        "decorator",
        "painter"
    ],
    "wof:name":"Bishop Decorative Finishes",
    "wof:placetype":"venue"
},
  "geometry": {"coordinates":[144.99038696299999,-37.8262405396],"type":"Point"}
}