{
  "type": "Feature",
  "properties": {
    "addr:full":"4 Parrot Rd Aldinga Beach SA 5173",
    "addr:housenumber":"4",
    "addr:postcode":"5173",
    "addr:street":"Parrot Rd",
    "iso:country":"AU",
    "sg:address":"4 Parrot Rd",
    "sg:city":"Aldinga Beach",
    "sg:classifiers":[
        {
            "category":"Professional",
            "type":"Services"
        }
    ],
    "sg:phone":"+61 407 445 669",
    "sg:postcode":"5173",
    "sg:province":"SA",
    "sg:tags":[
        "courier"
    ],
    "wof:name":"Speedy Gonzales Courier",
    "wof:placetype":"venue"
},
  "geometry": {"coordinates":[138.449584961,-35.3065261841],"type":"Point"}
}