{
  "type": "Feature",
  "properties": {
    "addr:full":"Grandridge Rd Mirboo North VIC 3871",
    "addr:postcode":"3871",
    "addr:street":"Grandridge Rd",
    "iso:country":"AU",
    "sg:address":"Grandridge Rd",
    "sg:city":"Mirboo North",
    "sg:classifiers":[
        {
            "category":"Education",
            "subcategory":"School",
            "type":"Public Place"
        }
    ],
    "sg:phone":"+61 3 5668 1375",
    "sg:postcode":"3871",
    "sg:province":"VIC",
    "sg:tags":[
        "state",
        "except",
        "nsw"
    ],
    "wof:name":"Mirboo North Primary School",
    "wof:placetype":"venue"
},
  "geometry": {"coordinates":[146.12828064000001,-38.3866920471],"type":"Point"}
}