{
  "type": "Feature",
  "properties": {
    "iso:country":"AU",
    "sg:address":"1880 Malvern Rd",
    "sg:city":"Malvern East",
    "sg:classifiers":[
        {
            "category":"Professional",
            "subcategory":"Management & Consulting",
            "type":"Services"
        }
    ],
    "sg:phone":"+61 3 9532 9787",
    "sg:postcode":"3145",
    "sg:province":"VIC",
    "sg:tags":[
        "consultant"
    ],
    "wof:name":"Mac Attack Pty Ltd",
    "wof:placetype":"venue"
},
  "geometry": {"coordinates":[145.062057495,-37.8712654114],"type":"Point"}
}