{
  "type": "Feature",
  "properties": {
    "iso:country":"AU",
    "sg:address":"307 Peel St",
    "sg:city":"Tamworth",
    "sg:classifiers":[
        {
            "category":"Insurance",
            "subcategory":"Insurance Agent",
            "type":"Services"
        }
    ],
    "sg:phone":"+61 2 6766 5255",
    "sg:postcode":"2340",
    "sg:province":"NSW",
    "wof:name":"AMP Life Ltd",
    "wof:placetype":"venue"
},
  "geometry": {"coordinates":[150.92904663100001,-31.0899276733],"type":"Point"}
}