{
  "type": "Feature",
  "properties": {
    "addr:full":"17 Sevenoak Rd Burwood East VIC 3151",
    "addr:housenumber":"17",
    "addr:postcode":"3151",
    "addr:street":"Sevenoak Rd",
    "iso:country":"AU",
    "sg:address":"17 Sevenoak Rd",
    "sg:city":"Burwood East",
    "sg:classifiers":[
        {
            "category":"Personal",
            "subcategory":"Beauty Salon",
            "type":"Services"
        }
    ],
    "sg:phone":"+61 3 9886 5400",
    "sg:postcode":"3151",
    "sg:province":"VIC",
    "wof:name":"Nortone Body Toning Studio",
    "wof:placetype":"venue"
},
  "geometry": {"coordinates":[145.158035278,-37.8544921875],"type":"Point"}
}