{
  "type": "Feature",
  "properties": {
    "iso:country":"AU",
    "sg:address":"162 Clovelly Rd",
    "sg:city":"Randwick",
    "sg:classifiers":[
        {
            "category":"Utilities",
            "subcategory":"Electric",
            "type":"Services"
        }
    ],
    "sg:phone":"+61 2 9399 5549",
    "sg:postcode":"2031",
    "sg:province":"NSW",
    "sg:tags":[
        "electrical",
        "contractor"
    ],
    "wof:name":"Easyfix Electrics Pty Ltd",
    "wof:placetype":"venue"
},
  "geometry": {"coordinates":[151.25164794899999,-33.9104003906],"type":"Point"}
}