{
  "type": "Feature",
  "properties": {
    "addr:full":"42 Simmons Drv Altona VIC 3018",
    "addr:housenumber":"42",
    "addr:postcode":"3018",
    "addr:street":"Simmons Drv",
    "iso:country":"AU",
    "sg:address":"42 Simmons Drv",
    "sg:city":"Altona",
    "sg:classifiers":[
        {
            "category":"Building & Trades",
            "subcategory":"Plumbing",
            "type":"Services"
        }
    ],
    "sg:phone":"+61 3 9398 6237",
    "sg:postcode":"3018",
    "sg:province":"VIC",
    "sg:tags":[
        "plumber",
        "gasfitters"
    ],
    "wof:name":"R & M O&#039;Brian Plumbing",
    "wof:placetype":"venue"
},
  "geometry": {"coordinates":[144.84600830100001,-37.8625068665],"type":"Point"}
}