{
  "type": "Feature",
  "properties": {
    "addr:full":"6 Bonville St Coffs Harbour NSW 2450",
    "addr:housenumber":"6",
    "addr:postcode":"2450",
    "addr:street":"Bonville St",
    "iso:country":"AU",
    "sg:address":"6 Bonville St",
    "sg:city":"Coffs Harbour",
    "sg:classifiers":[
        {
            "category":"Health Services",
            "subcategory":"Nursing And Care Facility",
            "type":"Services"
        }
    ],
    "sg:phone":"+61 2 6656 8100",
    "sg:postcode":"2450",
    "sg:province":"NSW",
    "sg:tags":[
        "home"
    ],
    "wof:name":"St Augustines Nursing Home",
    "wof:placetype":"venue"
},
  "geometry": {"coordinates":[153.11404400000001,-30.301163],"type":"Point"}
}