{
  "type": "Feature",
  "properties": {
    "iso:country":"AU",
    "sg:address":"179 Oxford St",
    "sg:city":"Darlinghurst",
    "sg:classifiers":[
        {
            "category":"Cafe",
            "type":"Food & Drink"
        }
    ],
    "sg:phone":"+61 2 9331 3229",
    "sg:postcode":"2010",
    "sg:province":"NSW",
    "wof:name":"Battuta",
    "wof:placetype":"venue"
},
  "geometry": {"coordinates":[151.21649169899999,-33.8805046082],"type":"Point"}
}