{
  "type": "Feature",
  "properties": {
    "addr:full":"9 Strickland St Rose Bay NSW 2029",
    "addr:housenumber":"9",
    "addr:postcode":"2029",
    "addr:street":"Strickland St",
    "iso:country":"AU",
    "sg:address":"9 Strickland St",
    "sg:city":"Rose Bay",
    "sg:classifiers":[
        {
            "category":"Building & Trades",
            "subcategory":"Plumbing",
            "type":"Services"
        }
    ],
    "sg:phone":"+61 418 427 670",
    "sg:postcode":"2029",
    "sg:province":"NSW",
    "sg:tags":[
        "plumber",
        "gasfitters"
    ],
    "wof:name":"Neowhouse Plumbing",
    "wof:placetype":"venue"
},
  "geometry": {"coordinates":[151.27540588400001,-33.8727645874],"type":"Point"}
}