{
  "type": "Feature",
  "properties": {
    "iso:country":"AU",
    "sg:address":"21 Clifton Springs Rd",
    "sg:city":"Drysdale",
    "sg:classifiers":[
        {
            "category":"Food & Beverages",
            "subcategory":"Groceries & Convenience Stores",
            "type":"Retail Goods"
        }
    ],
    "sg:phone":"+61 3 5253 1865",
    "sg:postcode":"3222",
    "sg:province":"VIC",
    "wof:name":"Drysdale Village Milkbar",
    "wof:placetype":"venue"
},
  "geometry": {"coordinates":[144.573486,-38.159431],"type":"Point"}
}