{
  "type": "Feature",
  "properties": {
    "addr:full":"3 Witt Ave Carrara QLD 4211",
    "addr:housenumber":"3",
    "addr:postcode":"4211",
    "addr:street":"Witt Ave",
    "iso:country":"AU",
    "sg:address":"3 Witt Ave",
    "sg:city":"Carrara",
    "sg:classifiers":[
        {
            "category":"Building & Trades",
            "subcategory":"Construction",
            "type":"Services"
        }
    ],
    "sg:phone":"+61 7 5594 4263",
    "sg:postcode":"4211",
    "sg:province":"QLD",
    "sg:tags":[
        "contractor"
    ],
    "wof:name":"Coastal Project Pty Ltd",
    "wof:placetype":"venue"
},
  "geometry": {"coordinates":[153.384643555,-28.021112442],"type":"Point"}
}