{
  "type": "Feature",
  "properties": {
    "addr:full":"PO Box 2591 Nambour West QLD 4560",
    "addr:postcode":"4560",
    "iso:country":"AU",
    "sg:address":"PO Box 2591",
    "sg:city":"Nambour West",
    "sg:classifiers":[
        {
            "category":"Professional",
            "subcategory":"Accounting & Tax Preparation",
            "type":"Services"
        }
    ],
    "sg:phone":"+61 422 196 308",
    "sg:postcode":"4560",
    "sg:province":"QLD",
    "sg:tags":[
        "bookkeeping"
    ],
    "wof:name":"Carter Ray MAAT",
    "wof:placetype":"venue"
},
  "geometry": {"coordinates":[152.941864014,-26.6222190857],"type":"Point"}
}