{
  "type": "Feature",
  "properties": {
    "iso:country":"AU",
    "sg:address":"141 Brighton Rd",
    "sg:city":"Glenelg South",
    "sg:classifiers":[
        {
            "category":"Autos & Motor Vehicles",
            "subcategory":"Automobile Sales",
            "type":"Retail Goods"
        }
    ],
    "sg:phone":"+61 8 8294 3444",
    "sg:postcode":"5045",
    "sg:province":"SA",
    "sg:tags":[
        "car",
        "new"
    ],
    "wof:name":"Dave Potter Motors Pty Ltd",
    "wof:placetype":"venue"
},
  "geometry": {"coordinates":[138.52072100000001,-34.989586],"type":"Point"}
}