{
  "type": "Feature",
  "properties": {
    "iso:country":"AU",
    "sg:address":"95 Sydney St",
    "sg:city":"Mackay",
    "sg:classifiers":[
        {
            "category":"Professional",
            "subcategory":"Engineering",
            "type":"Services"
        }
    ],
    "sg:phone":"+61 7 4951 0091",
    "sg:postcode":"4740",
    "sg:province":"QLD",
    "sg:tags":[
        "consulting",
        "engineer"
    ],
    "wof:name":"Capricorn Consulting Pty Ltd",
    "wof:placetype":"venue"
},
  "geometry": {"coordinates":[149.185913,-21.150423],"type":"Point"}
}