{
  "type": "Feature",
  "properties": {
    "addr:full":"23 Kenwick Rd Kenwick WA 6107",
    "addr:housenumber":"23",
    "addr:postcode":"6107",
    "addr:street":"Kenwick Rd",
    "iso:country":"AU",
    "sg:address":"23 Kenwick Rd",
    "sg:city":"Kenwick",
    "sg:classifiers":[
        {
            "category":"Health Services",
            "subcategory":"Doctor",
            "type":"Services"
        }
    ],
    "sg:phone":"+61 8 6161 0252",
    "sg:postcode":"6107",
    "sg:province":"WA",
    "sg:tags":[
        "occupational",
        "safety"
    ],
    "wof:name":"The Safety Doctor",
    "wof:placetype":"venue"
},
  "geometry": {"coordinates":[115.971313477,-32.0354118347],"type":"Point"}
}