{
  "type": "Feature",
  "properties": {
    "iso:country":"AU",
    "sg:address":"1215 Sturt St",
    "sg:city":"Ballarat",
    "sg:classifiers":[
        {
            "category":"Health Services",
            "subcategory":"Dentist",
            "type":"Services"
        }
    ],
    "sg:phone":"+61 3 5332 2160",
    "sg:postcode":"3350",
    "sg:province":"VIC",
    "sg:tags":[
        "technician",
        "dental"
    ],
    "wof:name":"Williams T R",
    "wof:placetype":"venue"
},
  "geometry": {"coordinates":[143.845428,-37.560833],"type":"Point"}
}