{
  "type": "Feature",
  "properties": {
    "addr:full":"2 Marlborough St Longford TAS 7301",
    "addr:housenumber":"2",
    "addr:postcode":"7301",
    "addr:street":"Marlborough St",
    "iso:country":"AU",
    "sg:address":"2 Marlborough St",
    "sg:city":"Longford",
    "sg:classifiers":[
        {
            "category":"Organizations",
            "subcategory":"Community Association",
            "type":"Services"
        }
    ],
    "sg:phone":"+61 3 6391 2498",
    "sg:postcode":"7301",
    "sg:province":"TAS",
    "sg:tags":[
        "organisation",
        "family",
        "welfare"
    ],
    "wof:name":"Helping Hand Ass. Inc. The",
    "wof:placetype":"venue"
},
  "geometry": {"coordinates":[147.12185700000001,-41.595093],"type":"Point"}
}