{
  "type": "Feature",
  "properties": {
    "addr:full":"261 Raymond St Sale VIC 3850",
    "addr:housenumber":"261",
    "addr:postcode":"3850",
    "addr:street":"Raymond St",
    "iso:country":"AU",
    "sg:address":"261 Raymond St",
    "sg:city":"Sale",
    "sg:classifiers":[
        {
            "category":"Insurance",
            "subcategory":"Hazard Insurance",
            "type":"Services"
        }
    ],
    "sg:phone":"+61 3 5144 1411",
    "sg:postcode":"3850",
    "sg:province":"VIC",
    "sg:tags":[
        "fire",
        "accident",
        "marine"
    ],
    "wof:name":"RACV Insurance",
    "wof:placetype":"venue"
},
  "geometry": {"coordinates":[147.06544494600001,-38.1077003479],"type":"Point"}
}