{
  "type": "Feature",
  "properties": {
    "addr:full":"48 Princes Hwy Eden NSW 2551",
    "addr:housenumber":"48",
    "addr:postcode":"2551",
    "addr:street":"Princes Hwy",
    "iso:country":"AU",
    "sg:address":"48 Princes Hwy",
    "sg:city":"Eden",
    "sg:classifiers":[
        {
            "category":"Travel",
            "subcategory":"Hotels & Motels",
            "type":"Entertainment"
        }
    ],
    "sg:phone":"+61 2 6496 1200",
    "sg:postcode":"2551",
    "sg:province":"NSW",
    "wof:name":"Sapphire Coast Restaurant",
    "wof:placetype":"venue"
},
  "geometry": {"coordinates":[149.88807678200001,-37.0662498474],"type":"Point"}
}