{
  "type": "Feature",
  "properties": {
    "addr:full":"13 Bess St Vincentia NSW 2540",
    "addr:housenumber":"13",
    "addr:postcode":"2540",
    "addr:street":"Bess St",
    "iso:country":"AU",
    "sg:address":"13 Bess St",
    "sg:city":"Vincentia",
    "sg:classifiers":[
        {
            "category":"Shopping",
            "subcategory":"Gifts & Souvenirs",
            "type":"Retail Goods"
        }
    ],
    "sg:phone":"+61 2 4441 7198",
    "sg:postcode":"2540",
    "sg:province":"NSW",
    "sg:tags":[
        "wrapping"
    ],
    "wof:name":"Oz Wrap (International) Pty Ltd",
    "wof:placetype":"venue"
},
  "geometry": {"coordinates":[150.683151245,-35.0734138489],"type":"Point"}
}