{
  "type": "Feature",
  "properties": {
    "iso:country":"AU",
    "sg:address":"Stockwell Pl",
    "sg:city":"Archerfield",
    "sg:classifiers":[
        {
            "category":"Cafe",
            "type":"Food & Drink"
        }
    ],
    "sg:phone":"+61 7 3373 8044",
    "sg:postcode":"4108",
    "sg:province":"QLD",
    "wof:name":"Cafe Stockwell",
    "wof:placetype":"venue"
},
  "geometry": {"coordinates":[153.01451110799999,-27.5682506561],"type":"Point"}
}