{
  "type": "Feature",
  "properties": {
    "addr:full":"8 Laurence Rd Walliston WA 6076",
    "addr:housenumber":"8",
    "addr:postcode":"6076",
    "addr:street":"Laurence Rd",
    "iso:country":"AU",
    "sg:address":"8 Laurence Rd",
    "sg:city":"Walliston",
    "sg:classifiers":[
        {
            "category":"Retail",
            "subcategory":"Storage",
            "type":"Services"
        }
    ],
    "sg:phone":"+61 8 9291 9644",
    "sg:postcode":"6076",
    "sg:province":"WA",
    "wof:name":"Alcatraz Storage",
    "wof:placetype":"venue"
},
  "geometry": {"coordinates":[116.07221984900001,-31.9943809509],"type":"Point"}
}