{
  "type": "Feature",
  "properties": {
    "addr:full":"25 Ocean St Maroochydore QLD 4558",
    "addr:housenumber":"25",
    "addr:postcode":"4558",
    "addr:street":"Ocean St",
    "iso:country":"AU",
    "sg:address":"25 Ocean St",
    "sg:city":"Maroochydore",
    "sg:classifiers":[
        {
            "category":"Banks & Credit Unions",
            "subcategory":"Financial Services",
            "type":"Services"
        }
    ],
    "sg:phone":"+61 7 5451 1577",
    "sg:postcode":"4558",
    "sg:province":"QLD",
    "sg:tags":[
        "loan",
        "finance",
        "mortgage"
    ],
    "wof:name":"Resi Mortgage Sunshine Coast",
    "wof:placetype":"venue"
},
  "geometry": {"coordinates":[153.08990478499999,-26.6528167725],"type":"Point"}
}