{
  "type": "Feature",
  "properties": {
    "addr:full":"157 Lygon St Brunswick East VIC 3057",
    "addr:housenumber":"157",
    "addr:postcode":"3057",
    "addr:street":"Lygon St",
    "iso:country":"AU",
    "sg:address":"157 Lygon St",
    "sg:city":"Brunswick East",
    "sg:classifiers":[
        {
            "category":"Food & Beverages",
            "subcategory":"Fruits & Vegetables",
            "type":"Retail Goods"
        }
    ],
    "sg:phone":"+61 3 9381 1416",
    "sg:postcode":"3057",
    "sg:province":"VIC",
    "sg:tags":[
        "greengrocer",
        "fruiterer"
    ],
    "wof:name":"Smith & Maloney",
    "wof:placetype":"venue"
},
  "geometry": {"coordinates":[144.971237183,-37.7732162476],"type":"Point"}
}