{
  "type": "Feature",
  "properties": {
    "iso:country":"AU",
    "sg:address":"Narellan Rd",
    "sg:city":"Mt Annan",
    "sg:classifiers":[
        {
            "category":"Building & Trades",
            "subcategory":"Construction",
            "type":"Services"
        }
    ],
    "sg:phone":"+61 2 4647 4288",
    "sg:postcode":"2567",
    "sg:province":"NSW",
    "sg:tags":[
        "pool",
        "swimming"
    ],
    "wof:name":"Combined Pools & Spas",
    "wof:placetype":"venue"
},
  "geometry": {"coordinates":[150.76312255900001,-34.049118042],"type":"Point"}
}