{
  "type": "Feature",
  "properties": {
    "addr:full":"Lot 51 Fortune St Balcatta WA 6021",
    "addr:postcode":"6021",
    "addr:street":"Fortune St",
    "iso:country":"AU",
    "sg:address":"Lot 51 Fortune St",
    "sg:city":"Balcatta",
    "sg:classifiers":[
        {
            "category":"Education",
            "subcategory":"Dance Studio",
            "type":"Public Place"
        }
    ],
    "sg:phone":"+61 8 6263 4484",
    "sg:postcode":"6021",
    "sg:province":"WA",
    "sg:tags":[
        "venue",
        "tuition"
    ],
    "wof:name":"Club Latino",
    "wof:placetype":"venue"
},
  "geometry": {"coordinates":[115.82450103799999,-31.884973526],"type":"Point"}
}