{
  "type": "Feature",
  "properties": {
    "iso:country":"AU",
    "sg:address":"19 - 21 East St",
    "sg:city":"Lidcombe",
    "sg:classifiers":[
        {
            "category":"Building & Trades",
            "subcategory":"Construction",
            "type":"Services"
        }
    ],
    "sg:phone":"+61 2 9649 1442",
    "sg:postcode":"2141",
    "sg:province":"NSW",
    "sg:tags":[
        "control",
        "manual",
        "system"
    ],
    "wof:name":"Cables & Controls",
    "wof:placetype":"venue"
},
  "geometry": {"coordinates":[151.047531128,-33.8662643433],"type":"Point"}
}