{
  "type": "Feature",
  "properties": {
    "addr:full":"174 Hillsborough Drv Nollamara WA 6061",
    "addr:housenumber":"174",
    "addr:postcode":"6061",
    "addr:street":"Hillsborough Drv",
    "iso:country":"AU",
    "sg:address":"174 Hillsborough Drv",
    "sg:city":"Nollamara",
    "sg:classifiers":[
        {
            "category":"Home & Garden",
            "subcategory":"Household Appliances",
            "type":"Retail Goods"
        }
    ],
    "sg:phone":"+61 419 422 822",
    "sg:postcode":"6061",
    "sg:province":"WA",
    "sg:tags":[
        "equipment",
        "gas"
    ],
    "wof:name":"ABC Gas Services",
    "wof:placetype":"venue"
},
  "geometry": {"coordinates":[115.83467102,-31.8745594025],"type":"Point"}
}