{
  "type": "Feature",
  "properties": {
    "addr:full":"8 Mills Rd Geraldton WA 6530",
    "addr:housenumber":"8",
    "addr:postcode":"6530",
    "addr:street":"Mills Rd",
    "iso:country":"AU",
    "sg:address":"8 Mills Rd",
    "sg:city":"Geraldton",
    "sg:classifiers":[
        {
            "category":"Building & Trades",
            "subcategory":"Landscaping Services",
            "type":"Services"
        }
    ],
    "sg:phone":"+61 8 9938 2800",
    "sg:postcode":"6530",
    "sg:province":"WA",
    "sg:tags":[
        "stump",
        "tree",
        "felling",
        "removal"
    ],
    "wof:name":"Parry D & D",
    "wof:placetype":"venue"
},
  "geometry": {"coordinates":[114.669563294,-28.722026825],"type":"Point"}
}