{
  "type": "Feature",
  "properties": {
    "addr:full":"33 Milton Ave Clayton South VIC 3169",
    "addr:housenumber":"33",
    "addr:postcode":"3169",
    "addr:street":"Milton Ave",
    "iso:country":"AU",
    "sg:address":"33 Milton Ave",
    "sg:city":"Clayton South",
    "sg:classifiers":[
        {
            "category":"Organizations",
            "subcategory":"Professional Association",
            "type":"Services"
        }
    ],
    "sg:phone":"+61 412 901 844",
    "sg:postcode":"3169",
    "sg:province":"VIC",
    "sg:tags":[
        "web",
        "internet"
    ],
    "wof:name":"Fieldcraft",
    "wof:placetype":"venue"
},
  "geometry": {"coordinates":[145.130615234,-37.9370384216],"type":"Point"}
}