{
  "type": "Feature",
  "properties": {
    "iso:country":"AU",
    "sg:address":"Suite 1/ 277 Great Eastern Hwy",
    "sg:city":"Belmont",
    "sg:classifiers":[
        {
            "category":"Organizations",
            "subcategory":"Professional Association",
            "type":"Services"
        }
    ],
    "sg:phone":"+61 8 9479 7315",
    "sg:postcode":"6104",
    "sg:province":"WA",
    "sg:tags":[
        "rural",
        "organisation",
        "production",
        "primary"
    ],
    "wof:name":"West Australian Pork Producers Association",
    "wof:placetype":"venue"
},
  "geometry": {"coordinates":[115.930137634,-31.9393081665],"type":"Point"}
}