{
  "type": "Feature",
  "properties": {
    "iso:country":"AU",
    "sg:address":"109 Holland Rd",
    "sg:city":"Holland Park",
    "sg:classifiers":[
        {
            "category":"Home & Garden",
            "subcategory":"Furniture",
            "type":"Retail Goods"
        }
    ],
    "sg:phone":"+61 7 3397 6254",
    "sg:postcode":"4121",
    "sg:province":"QLD",
    "sg:tags":[
        "repair",
        "restoration"
    ],
    "wof:name":"Barabas Upholstery",
    "wof:placetype":"venue"
},
  "geometry": {"coordinates":[153.070999145,-27.5162792206],"type":"Point"}
}