{
  "type": "Feature",
  "properties": {
    "iso:country":"AU",
    "sg:address":"Cnr Fremantle & Rouse Rds",
    "sg:city":"Mandurah",
    "sg:classifiers":[
        {
            "category":"Home & Garden",
            "subcategory":"Carpets & Floor Coverings",
            "type":"Retail Goods"
        }
    ],
    "sg:phone":"+61 8 9582 0100",
    "sg:postcode":"6210",
    "sg:province":"WA",
    "sg:tags":[
        "tile",
        "wall"
    ],
    "wof:name":"Imported Ceramics",
    "wof:placetype":"venue"
},
  "geometry": {"coordinates":[115.74788700000001,-32.517078],"type":"Point"}
}