{
  "type": "Feature",
  "properties": {
    "iso:country":"AU",
    "sg:address":"3 / 518 Goodwood Rd",
    "sg:city":"Daw Park",
    "sg:classifiers":[
        {
            "category":"Shopping",
            "subcategory":"Music",
            "type":"Retail Goods"
        }
    ],
    "sg:phone":"+61 8 8172 1332",
    "sg:postcode":"5041",
    "sg:province":"SA",
    "sg:tags":[
        "instrument",
        "musical"
    ],
    "wof:name":"Karaoke Light & Sound",
    "wof:placetype":"venue"
},
  "geometry": {"coordinates":[138.591537,-34.978252],"type":"Point"}
}