{
  "type": "Feature",
  "properties": {
    "iso:country":"AU",
    "sg:address":"256 West Coast Hwy",
    "sg:city":"Scarborough",
    "sg:classifiers":[
        {
            "category":"Professional",
            "subcategory":"Employment Agencies",
            "type":"Services"
        }
    ],
    "sg:phone":"+61 8 9245 3388",
    "sg:postcode":"6019",
    "sg:province":"WA",
    "sg:tags":[
        "provider",
        "internet"
    ],
    "wof:name":"Indigo Net Cafe & Lodge - Scarborough",
    "wof:placetype":"venue"
},
  "geometry": {"coordinates":[115.758079529,-31.8982944489],"type":"Point"}
}