{
  "type": "Feature",
  "properties": {
    "addr:full":"13 Douglas St Clovelly NSW 2031",
    "addr:housenumber":"13",
    "addr:postcode":"2031",
    "addr:street":"Douglas St",
    "iso:country":"AU",
    "sg:address":"13 Douglas St",
    "sg:city":"Clovelly",
    "sg:classifiers":[
        {
            "category":"Real Estate",
            "subcategory":"Real Estate Agent",
            "type":"Services"
        }
    ],
    "sg:phone":"+61 2 9665 8789",
    "sg:postcode":"2031",
    "sg:province":"NSW",
    "wof:name":"Teldar Real Estate Pty Ltd",
    "wof:placetype":"venue"
},
  "geometry": {"coordinates":[151.254272461,-33.9078445435],"type":"Point"}
}