{
  "type": "Feature",
  "properties": {
    "addr:full":"466 Windsor Rd Vineyard NSW 2765",
    "addr:housenumber":"466",
    "addr:postcode":"2765",
    "addr:street":"Windsor Rd",
    "iso:country":"AU",
    "sg:address":"466 Windsor Rd",
    "sg:city":"Vineyard",
    "sg:classifiers":[
        {
            "category":"Farming",
            "subcategory":"Poultry Farm",
            "type":"Manufacturing & Wholesale Goods"
        }
    ],
    "sg:phone":"+61 2 9838 1649",
    "sg:postcode":"2765",
    "sg:province":"NSW",
    "sg:tags":[
        "farmer"
    ],
    "wof:name":"Country Style Eggs Producers",
    "wof:placetype":"venue"
},
  "geometry": {"coordinates":[150.86538696299999,-33.6513366699],"type":"Point"}
}