{
  "type": "Feature",
  "properties": {
    "addr:full":"31 Holmes Rd Morwell VIC 3840",
    "addr:housenumber":"31",
    "addr:postcode":"3840",
    "addr:street":"Holmes Rd",
    "iso:country":"AU",
    "sg:address":"31 Holmes Rd",
    "sg:city":"Morwell",
    "sg:classifiers":[
        {
            "category":"Autos & Motor Vehicles",
            "subcategory":"Motorcycle Sales",
            "type":"Retail Goods"
        }
    ],
    "sg:phone":"+61 3 5133 7314",
    "sg:postcode":"3840",
    "sg:province":"VIC",
    "sg:tags":[
        "outboard"
    ],
    "wof:name":"S.D. Marine Services",
    "wof:placetype":"venue"
},
  "geometry": {"coordinates":[146.39877319300001,-38.2288131714],"type":"Point"}
}