{
  "type": "Feature",
  "properties": {
    "addr:full":"55 Seventh St East Mildura VIC 3500",
    "addr:housenumber":"55",
    "addr:postcode":"3500",
    "addr:street":"Seventh St East",
    "iso:country":"AU",
    "sg:address":"55 Seventh St East",
    "sg:city":"Mildura",
    "sg:classifiers":[
        {
            "category":"Utilities",
            "type":"Services"
        }
    ],
    "sg:phone":"+61 3 5021 3213",
    "sg:postcode":"3500",
    "sg:province":"VIC",
    "sg:tags":[
        "equipment",
        "towing"
    ],
    "wof:name":"Mildura 4WD Accessories",
    "wof:placetype":"venue"
},
  "geometry": {"coordinates":[142.154098511,-34.2107391357],"type":"Point"}
}