{
  "type": "Feature",
  "properties": {
    "addr:full":"138 Chesterville Rd Cheltenham VIC 3192",
    "addr:housenumber":"138",
    "addr:postcode":"3192",
    "addr:street":"Chesterville Rd",
    "iso:country":"AU",
    "sg:address":"138 Chesterville Rd",
    "sg:city":"Cheltenham",
    "sg:classifiers":[
        {
            "category":"Building & Trades",
            "subcategory":"Construction",
            "type":"Services"
        }
    ],
    "sg:phone":"+61 3 9553 5445",
    "sg:postcode":"3192",
    "sg:province":"VIC",
    "sg:tags":[
        "equipment",
        "system",
        "automation"
    ],
    "wof:name":"Machine Dynamics",
    "wof:placetype":"venue"
},
  "geometry": {"coordinates":[145.058349609,-37.9520339966],"type":"Point"}
}