{
  "type": "Feature",
  "properties": {
    "iso:country":"AU",
    "sg:address":"37- 41 Morayfield Rd",
    "sg:city":"Caboolture",
    "sg:classifiers":[
        {
            "category":"Wholesale",
            "subcategory":"Furniture",
            "type":"Manufacturing & Wholesale Goods"
        }
    ],
    "sg:phone":"+61 7 5498 9066",
    "sg:postcode":"4510",
    "sg:province":"QLD",
    "sg:tags":[
        "wholesaler",
        "mfrs"
    ],
    "wof:name":"Queensland Outdoor Furniture",
    "wof:placetype":"venue"
},
  "geometry": {"coordinates":[152.950027,-27.093185],"type":"Point"}
}