{
  "type": "Feature",
  "properties": {
    "addr:full":"357 Beamish St Campsie NSW 2194",
    "addr:housenumber":"357",
    "addr:postcode":"2194",
    "addr:street":"Beamish St",
    "iso:country":"AU",
    "sg:address":"357 Beamish St",
    "sg:city":"Campsie",
    "sg:classifiers":[
        {
            "category":"Health Services",
            "subcategory":"Doctor",
            "type":"Services"
        }
    ],
    "sg:phone":"+61 2 9787 6374",
    "sg:postcode":"2194",
    "sg:province":"NSW",
    "sg:tags":[
        "medical",
        "practitioner"
    ],
    "wof:name":"Retsas C",
    "wof:placetype":"venue"
},
  "geometry": {"coordinates":[151.104355,-33.915165],"type":"Point"}
}