{
  "type": "Feature",
  "properties": {
    "addr:full":"Baylis Centre 2 /47 Baylis Wagga Wagga NSW 2650",
    "addr:housenumber":"2 / 47",
    "addr:postcode":"2650",
    "iso:country":"AU",
    "sg:address":"Baylis Centre 2",
    "sg:city":"/47 Baylis Wagga Wagga",
    "sg:classifiers":[
        {
            "category":"Professional",
            "subcategory":"Accounting & Tax Preparation",
            "type":"Services"
        }
    ],
    "sg:phone":"+61 2 6971 9344",
    "sg:postcode":"2650",
    "sg:province":"NSW",
    "sg:tags":[
        "consultant",
        "taxation"
    ],
    "wof:name":"Kahlefeldt Jared",
    "wof:placetype":"venue"
},
  "geometry": {"coordinates":[147.36929321299999,-35.1171798706],"type":"Point"}
}