{
  "type": "Feature",
  "properties": {
    "addr:full":"139 March St Richmond NSW 2753",
    "addr:housenumber":"139",
    "addr:postcode":"2753",
    "addr:street":"March St",
    "iso:country":"AU",
    "sg:address":"139 March St",
    "sg:city":"Richmond",
    "sg:classifiers":[
        {
            "category":"Professional",
            "subcategory":"Printing & Photocopies",
            "type":"Services"
        }
    ],
    "sg:phone":"+61 2 4588 5610",
    "sg:postcode":"2753",
    "sg:province":"NSW",
    "sg:tags":[
        "trophy"
    ],
    "wof:name":"Richmond Trophies",
    "wof:placetype":"venue"
},
  "geometry": {"coordinates":[150.75094604500001,-33.596660614],"type":"Point"}
}