{
  "type": "Feature",
  "properties": {
    "addr:full":"108 Station St Fairfield VIC 3078",
    "addr:housenumber":"108",
    "addr:postcode":"3078",
    "addr:street":"Station St",
    "iso:country":"AU",
    "sg:address":"108 Station St",
    "sg:city":"Fairfield",
    "sg:classifiers":[
        {
            "category":"Food & Beverages",
            "subcategory":"Specialty",
            "type":"Retail Goods"
        }
    ],
    "sg:phone":"+61 3 9481 4718",
    "sg:postcode":"3078",
    "sg:province":"VIC",
    "sg:tags":[
        "product",
        "health"
    ],
    "wof:name":"Inergi Healthfood",
    "wof:placetype":"venue"
},
  "geometry": {"coordinates":[145.01846313499999,-37.7780227661],"type":"Point"}
}