{
  "type": "Feature",
  "properties": {
    "addr:full":"10 Spit Rd Mosman NSW 2088",
    "addr:housenumber":"10",
    "addr:postcode":"2088",
    "addr:street":"Spit Rd",
    "iso:country":"AU",
    "sg:address":"10 Spit Rd",
    "sg:city":"Mosman",
    "sg:classifiers":[
        {
            "category":"Shopping",
            "subcategory":"Clothing, Apparel, & Fashions",
            "type":"Retail Goods"
        }
    ],
    "sg:phone":"+61 2 9960 1030",
    "sg:postcode":"2088",
    "sg:province":"NSW",
    "sg:tags":[
        "recycled",
        "clothing"
    ],
    "wof:name":"St Vincent De Paul Society",
    "wof:placetype":"venue"
},
  "geometry": {"coordinates":[151.24105835,-33.8242340088],"type":"Point"}
}