{
  "type": "Feature",
  "properties": {
    "iso:country":"AU",
    "sg:address":"PO Box 360",
    "sg:city":"Merewether",
    "sg:classifiers":[
        {
            "category":"Professional",
            "subcategory":"Accounting & Tax Preparation",
            "type":"Services"
        }
    ],
    "sg:phone":"+61 2 4963 6439",
    "sg:postcode":"2291",
    "sg:province":"NSW",
    "sg:tags":[
        "accountant",
        "auditor"
    ],
    "wof:name":"Fratangelo Maria",
    "wof:placetype":"venue"
},
  "geometry": {"coordinates":[151.74896240199999,-32.943359375],"type":"Point"}
}