{
  "type": "Feature",
  "properties": {
    "addr:full":"622 Nicholson St Fitzroy North VIC 3068",
    "addr:housenumber":"622",
    "addr:postcode":"3068",
    "addr:street":"Nicholson St",
    "iso:country":"AU",
    "sg:address":"622 Nicholson St",
    "sg:city":"Fitzroy North",
    "sg:classifiers":[
        {
            "category":"Professional",
            "subcategory":"Art Services",
            "type":"Services"
        }
    ],
    "sg:phone":"+61 3 9489 5687",
    "sg:postcode":"3068",
    "sg:province":"VIC",
    "sg:tags":[
        "picture",
        "frame",
        "framing"
    ],
    "wof:name":"Vrettos Co",
    "wof:placetype":"venue"
},
  "geometry": {"coordinates":[144.97752380399999,-37.7846641541],"type":"Point"}
}