{
  "type": "Feature",
  "properties": {
    "iso:country":"AU",
    "sg:address":"Albert St",
    "sg:city":"Warragul",
    "sg:classifiers":[
        {
            "category":"Autos & Motor Vehicles",
            "subcategory":"Fuel & Gas Station",
            "type":"Retail Goods"
        }
    ],
    "sg:phone":"+61 3 5623 4064",
    "sg:postcode":"3820",
    "sg:province":"VIC",
    "wof:name":"&#034;Kellys Stop N Go&#034;",
    "wof:placetype":"venue"
},
  "geometry": {"coordinates":[145.931686,-38.159286],"type":"Point"}
}