{
  "type": "Feature",
  "properties": {
    "addr:full":"Millway St Kedron QLD 4031",
    "addr:postcode":"4031",
    "addr:street":"Millway St",
    "iso:country":"AU",
    "sg:address":"Millway St",
    "sg:city":"Kedron",
    "sg:classifiers":[
        {
            "category":"Arts & Performance",
            "subcategory":"Dance",
            "type":"Entertainment"
        }
    ],
    "sg:phone":"+61 7 3357 9086",
    "sg:postcode":"4031",
    "sg:province":"QLD",
    "sg:tags":[
        "theatrical",
        "ballet",
        "tuition"
    ],
    "wof:name":"Promenade Dance Studio",
    "wof:placetype":"venue"
},
  "geometry": {"coordinates":[153.02179000000001,-27.396301],"type":"Point"}
}