{
  "type": "Feature",
  "properties": {
    "addr:full":"74 Western Drv Gatton QLD 4343",
    "addr:housenumber":"74",
    "addr:postcode":"4343",
    "addr:street":"Western Drv",
    "iso:country":"AU",
    "sg:address":"74 Western Drv",
    "sg:city":"Gatton",
    "sg:classifiers":[
        {
            "category":"Home & Garden",
            "subcategory":"Building Materials",
            "type":"Retail Goods"
        }
    ],
    "sg:phone":"+61 7 5462 4266",
    "sg:postcode":"4343",
    "sg:province":"QLD",
    "sg:tags":[
        "merchant",
        "glass",
        "glazier"
    ],
    "wof:name":"Gatton Glass",
    "wof:placetype":"venue"
},
  "geometry": {"coordinates":[152.270584106,-27.5683956146],"type":"Point"}
}