{
  "type": "Feature",
  "properties": {
    "iso:country":"AU",
    "sg:address":"33 Victoria St (Cnr Hoskins St)",
    "sg:city":"Hall",
    "sg:classifiers":[
        {
            "category":"Retail",
            "subcategory":"Veterinary Services",
            "type":"Services"
        }
    ],
    "sg:phone":"+61 2 6230 2223",
    "sg:postcode":"2618",
    "sg:province":"ACT",
    "sg:tags":[
        "surgeon"
    ],
    "wof:name":"Purdam Helen",
    "wof:placetype":"venue"
},
  "geometry": {"coordinates":[149.06773376500001,-35.1672821045],"type":"Point"}
}