{
  "type": "Feature",
  "properties": {
    "addr:full":"10- 12 Blackburn Rd Blackburn VIC 3130",
    "addr:housenumber":"12",
    "addr:postcode":"3130",
    "addr:street":"Blackburn Rd",
    "iso:country":"AU",
    "sg:address":"10- 12 Blackburn Rd",
    "sg:city":"Blackburn",
    "sg:classifiers":[
        {
            "category":"Professional",
            "subcategory":"Employment Agencies",
            "type":"Services"
        }
    ],
    "sg:phone":"+61 3 9289 9688",
    "sg:postcode":"3130",
    "sg:province":"VIC",
    "wof:name":"Adecco",
    "wof:placetype":"venue"
},
  "geometry": {"coordinates":[145.15281677199999,-37.8201179504],"type":"Point"}
}