{
  "type": "Feature",
  "properties": {
    "iso:country":"AU",
    "sg:address":"Cnr Corinne St & Pye Rd",
    "sg:city":"Quakers Hill",
    "sg:classifiers":[
        {
            "category":"Health Services",
            "subcategory":"Health Practitioner",
            "type":"Services"
        }
    ],
    "sg:phone":"+61 2 9626 8867",
    "sg:postcode":"2763",
    "sg:province":"NSW",
    "sg:tags":[
        "physiotherapist"
    ],
    "wof:name":"Quakers Hill Physiotherapy Centre",
    "wof:placetype":"venue"
},
  "geometry": {"coordinates":[150.906692505,-33.7313537598],"type":"Point"}
}