{
  "type": "Feature",
  "properties": {
    "addr:full":"3 Princes Hwy Warragul VIC 3820",
    "addr:housenumber":"3",
    "addr:postcode":"3820",
    "addr:street":"Princes Hwy",
    "iso:country":"AU",
    "sg:address":"3 Princes Hwy",
    "sg:city":"Warragul",
    "sg:classifiers":[
        {
            "category":"Building & Trades",
            "subcategory":"Construction",
            "type":"Services"
        }
    ],
    "sg:phone":"+61 3 5622 3068",
    "sg:postcode":"3820",
    "sg:province":"VIC",
    "sg:tags":[
        "earth",
        "excavating",
        "moving",
        "contractor"
    ],
    "wof:name":"Trenerry N & J Pty Ltd",
    "wof:placetype":"venue"
},
  "geometry": {"coordinates":[145.94366500000001,-38.170616],"type":"Point"}
}