{
  "type": "Feature",
  "properties": {
    "addr:full":"134 Maidstone Crs Exmouth WA 6707",
    "addr:housenumber":"134",
    "addr:postcode":"6707",
    "addr:street":"Maidstone Crs",
    "iso:country":"AU",
    "sg:address":"134 Maidstone Crs",
    "sg:city":"Exmouth",
    "sg:classifiers":[
        {
            "category":"Food & Beverages",
            "subcategory":"Liquor & Beverages",
            "type":"Retail Goods"
        }
    ],
    "sg:phone":"+61 8 9949 1303",
    "sg:postcode":"6707",
    "sg:province":"WA",
    "sg:tags":[
        "store"
    ],
    "wof:name":"Sam's Cellar",
    "wof:placetype":"venue"
},
  "geometry": {"coordinates":[114.133277893,-21.9462604523],"type":"Point"}
}