{
  "type": "Feature",
  "properties": {
    "iso:country":"AU",
    "sg:address":"48 Ingham Rd",
    "sg:city":"West End (Townsville)",
    "sg:classifiers":[
        {
            "category":"Government",
            "subcategory":"City Hall",
            "type":"Public Place"
        }
    ],
    "sg:phone":"+61 7 4779 1969",
    "sg:postcode":"4810",
    "sg:province":"QLD",
    "wof:name":"O E S Hall",
    "wof:placetype":"venue"
},
  "geometry": {"coordinates":[146.80069,-19.268642],"type":"Point"}
}