{
  "type": "Feature",
  "properties": {
    "addr:full":"119 Main St Ulverstone TAS 7315",
    "addr:housenumber":"119",
    "addr:postcode":"7315",
    "addr:street":"Main St",
    "iso:country":"AU",
    "sg:address":"119 Main St",
    "sg:city":"Ulverstone",
    "sg:classifiers":[
        {
            "category":"Food & Beverages",
            "subcategory":"Supermarket",
            "type":"Retail Goods"
        }
    ],
    "sg:phone":"+61 3 6425 2217",
    "sg:postcode":"7315",
    "sg:province":"TAS",
    "sg:tags":[
        "grocery",
        "store"
    ],
    "wof:name":"Friendly Grocer IGA Stores",
    "wof:placetype":"venue"
},
  "geometry": {"coordinates":[146.184280395,-41.1614074707],"type":"Point"}
}