{
  "type": "Feature",
  "properties": {
    "addr:full":"116 Dudley St Gorokan NSW 2263",
    "addr:housenumber":"116",
    "addr:postcode":"2263",
    "addr:street":"Dudley St",
    "iso:country":"AU",
    "sg:address":"116 Dudley St",
    "sg:city":"Gorokan",
    "sg:classifiers":[
        {
            "category":"Personal",
            "subcategory":"Tanning Parlor",
            "type":"Services"
        }
    ],
    "sg:phone":"+61 425 359 504",
    "sg:postcode":"2263",
    "sg:province":"NSW",
    "sg:tags":[
        "solarium"
    ],
    "wof:name":"Asyana",
    "wof:placetype":"venue"
},
  "geometry": {"coordinates":[151.50700399999999,-33.255955],"type":"Point"}
}