{
  "type": "Feature",
  "properties": {
    "addr:full":"Public Schl Windsor Rd Kellyville NSW 2153",
    "addr:postcode":"2153",
    "addr:street":"Windsor Rd",
    "iso:country":"AU",
    "sg:address":"Public Schl Windsor Rd",
    "sg:city":"Kellyville",
    "sg:classifiers":[
        {
            "category":"Social Services",
            "subcategory":"Child Care",
            "type":"Services"
        }
    ],
    "sg:phone":"+61 2 9629 2292",
    "sg:postcode":"2153",
    "sg:province":"NSW",
    "sg:tags":[
        "support",
        "health"
    ],
    "wof:name":"Early Childhood Health Centres",
    "wof:placetype":"venue"
},
  "geometry": {"coordinates":[150.97642517099999,-33.7541503906],"type":"Point"}
}