{
  "type": "Feature",
  "properties": {
    "addr:full":"Cnr Colgan & Dillon Sts Cobram VIC 3644",
    "addr:postcode":"3644",
    "addr:street":"Cnr",
    "iso:country":"AU",
    "sg:address":"Cnr Colgan & Dillon Sts",
    "sg:city":"Cobram",
    "sg:classifiers":[
        {
            "category":"Wholesale",
            "subcategory":"Farm Supplies",
            "type":"Manufacturing & Wholesale Goods"
        }
    ],
    "sg:phone":"+61 3 5872 2888",
    "sg:postcode":"3644",
    "sg:province":"VIC",
    "sg:tags":[
        "feed",
        "supplement",
        "stock"
    ],
    "wof:name":"Murray Valley Produce Pty Ltd",
    "wof:placetype":"venue"
},
  "geometry": {"coordinates":[145.644775391,-35.919380188],"type":"Point"}
}