{
  "type": "Feature",
  "properties": {
    "iso:country":"AU",
    "sg:address":"2d Fifth Ave",
    "sg:city":"St Peters",
    "sg:classifiers":[
        {
            "category":"Real Estate",
            "subcategory":"Architect",
            "type":"Services"
        }
    ],
    "sg:phone":"+61 8 8362 5860",
    "sg:postcode":"5069",
    "sg:province":"SA",
    "wof:name":"Feltus Terence R",
    "wof:placetype":"venue"
},
  "geometry": {"coordinates":[138.61984252900001,-34.9092826843],"type":"Point"}
}