{
  "type": "Feature",
  "properties": {
    "addr:full":"200 Main Rd Blackwood SA 5051",
    "addr:housenumber":"200",
    "addr:postcode":"5051",
    "addr:street":"Main Rd",
    "iso:country":"AU",
    "sg:address":"200 Main Rd",
    "sg:city":"Blackwood",
    "sg:classifiers":[
        {
            "category":"Food & Beverages",
            "subcategory":"Supermarket",
            "type":"Retail Goods"
        }
    ],
    "sg:phone":"+61 8 8278 6099",
    "sg:postcode":"5051",
    "sg:province":"SA",
    "sg:tags":[
        "grocery",
        "store"
    ],
    "wof:name":"Timesavers Supermarket",
    "wof:placetype":"venue"
},
  "geometry": {"coordinates":[138.616592,-35.016541],"type":"Point"}
}