{
  "type": "Feature",
  "properties": {
    "addr:full":"1/ 25 leda Drv Burleigh Heads QLD 4220",
    "addr:housenumber":"/ 25",
    "addr:postcode":"4220",
    "addr:street":"Leda Drv",
    "iso:country":"AU",
    "sg:address":"1/ 25 leda Drv",
    "sg:city":"Burleigh Heads",
    "sg:classifiers":[
        {
            "category":"Coffee & Tea",
            "type":"Food & Drink"
        }
    ],
    "sg:phone":"+61 1800 086 929",
    "sg:postcode":"4220",
    "sg:province":"QLD",
    "sg:tags":[
        "synthetic",
        "marble"
    ],
    "wof:name":"Transitions Polishing And Grinding",
    "wof:placetype":"venue"
},
  "geometry": {"coordinates":[153.43101501500001,-28.1052398682],"type":"Point"}
}