{
  "type": "Feature",
  "properties": {
    "addr:full":"13 Arnott Pl Wetherill Park NSW 2164",
    "addr:housenumber":"13",
    "addr:postcode":"2164",
    "addr:street":"Arnott Pl",
    "iso:country":"AU",
    "sg:address":"13 Arnott Pl",
    "sg:city":"Wetherill Park",
    "sg:classifiers":[
        {
            "category":"Manufacturing",
            "subcategory":"Retail Goods",
            "type":"Manufacturing & Wholesale Goods"
        }
    ],
    "sg:phone":"+61 2 9725 5199",
    "sg:postcode":"2164",
    "sg:province":"NSW",
    "sg:tags":[
        "merchant",
        "pump",
        "mfrs"
    ],
    "sg:website":"http://www.gdnash.com.au",
    "wof:name":"Gardner Denver Nash Australia Pty Ltd",
    "wof:placetype":"venue"
},
  "geometry": {"coordinates":[150.90159606899999,-33.8349647522],"type":"Point"}
}