{
  "type": "Feature",
  "properties": {
    "addr:full":"Rear 890 Hay St Perth WA 6000",
    "addr:housenumber":"890",
    "addr:postcode":"6000",
    "addr:street":"Hay St",
    "iso:country":"AU",
    "sg:address":"Rear 890 Hay St",
    "sg:city":"Perth",
    "sg:classifiers":[
        {
            "category":"Utilities",
            "subcategory":"Electric",
            "type":"Services"
        }
    ],
    "sg:phone":"+61 8 9321 2515",
    "sg:postcode":"6000",
    "sg:province":"WA",
    "sg:tags":[
        "electrical",
        "contractor"
    ],
    "sg:website":"http://www.leadercabling.com.au",
    "wof:name":"Leader Cabling Systems",
    "wof:placetype":"venue"
},
  "geometry": {"coordinates":[115.849517822,-31.9512500763],"type":"Point"}
}