{
  "type": "Feature",
  "properties": {
    "addr:full":"832 High St Kew East VIC 3102",
    "addr:housenumber":"832",
    "addr:postcode":"3102",
    "addr:street":"High St",
    "iso:country":"AU",
    "sg:address":"832 High St",
    "sg:city":"Kew East",
    "sg:classifiers":[
        {
            "category":"Building & Trades",
            "subcategory":"Construction",
            "type":"Services"
        }
    ],
    "sg:phone":"+61 3 9249 9517",
    "sg:postcode":"3102",
    "sg:province":"VIC",
    "sg:tags":[
        "window",
        "tinting"
    ],
    "wof:name":"Solabloc-Tintech",
    "wof:placetype":"venue"
},
  "geometry": {"coordinates":[145.063034058,-37.7940292358],"type":"Point"}
}