{
  "type": "Feature",
  "properties": {
    "iso:country":"AU",
    "sg:address":"Shed 9 63 Burnside Rd",
    "sg:city":"Stapylton",
    "sg:classifiers":[
        {
            "category":"Manufacturing",
            "subcategory":"Metals",
            "type":"Manufacturing & Wholesale Goods"
        }
    ],
    "sg:phone":"+61 7 3807 8330",
    "sg:postcode":"4207",
    "sg:province":"QLD",
    "sg:tags":[
        "steel",
        "fabricator",
        "mfrs"
    ],
    "wof:name":"Byrne Engineering",
    "wof:placetype":"venue"
},
  "geometry": {"coordinates":[153.253616333,-27.7496623993],"type":"Point"}
}