{
  "type": "Feature",
  "properties": {
    "addr:full":"1/ 11 Leader St Campbellfield VIC 3061",
    "addr:housenumber":"/ 11",
    "addr:postcode":"3061",
    "addr:street":"Leader St",
    "iso:country":"AU",
    "sg:address":"1/ 11 Leader St",
    "sg:city":"Campbellfield",
    "sg:classifiers":[
        {
            "category":"Autos & Motor Vehicles",
            "subcategory":"Auto Supplies",
            "type":"Retail Goods"
        }
    ],
    "sg:phone":"+61 3 9308 7311",
    "sg:postcode":"3061",
    "sg:province":"VIC",
    "sg:tags":[
        "camper-trailers",
        "caravan",
        "equipment"
    ],
    "wof:name":"Aussie Traveller Pty Ltd",
    "wof:placetype":"venue"
},
  "geometry": {"coordinates":[144.94337463400001,-37.6433334351],"type":"Point"}
}