{
  "type": "Feature",
  "properties": {
    "addr:full":"Shp 3a/ 27 Old Great Northern Hwy Midland WA 6056",
    "addr:housenumber":"3a / 27",
    "addr:postcode":"6056",
    "addr:street":"Old Great Northern Hwy",
    "iso:country":"AU",
    "sg:address":"Shp 3a/ 27 Old Great Northern Hwy",
    "sg:city":"Midland",
    "sg:classifiers":[
        {
            "category":"Cafe",
            "type":"Food & Drink"
        }
    ],
    "sg:phone":"+61 8 9250 1023",
    "sg:postcode":"6056",
    "sg:province":"WA",
    "wof:name":"Ritz Cafe",
    "wof:placetype":"venue"
},
  "geometry": {"coordinates":[116.003112793,-31.8878211975],"type":"Point"}
}