{
  "type": "Feature",
  "properties": {
    "addr:full":"Suite 2/ 16 Fisher Rd Dee Why NSW 2099",
    "addr:housenumber":"16",
    "addr:postcode":"2099",
    "addr:street":"Fisher Rd",
    "iso:country":"AU",
    "sg:address":"Suite 2/ 16 Fisher Rd",
    "sg:city":"Dee Why",
    "sg:classifiers":[
        {
            "category":"Professional",
            "subcategory":"Management & Consulting",
            "type":"Services"
        }
    ],
    "sg:phone":"+61 2 9972 2642",
    "sg:postcode":"2099",
    "sg:province":"NSW",
    "sg:tags":[
        "consultant",
        "business"
    ],
    "wof:name":"Profit Link Pty Ltd",
    "wof:placetype":"venue"
},
  "geometry": {"coordinates":[151.28468322800001,-33.7531356812],"type":"Point"}
}