{
  "type": "Feature",
  "properties": {
    "addr:full":"60 Goondoon St Gladstone QLD 4680",
    "addr:housenumber":"60",
    "addr:postcode":"4680",
    "addr:street":"Goondoon St",
    "iso:country":"AU",
    "sg:address":"60 Goondoon St",
    "sg:city":"Gladstone",
    "sg:classifiers":[
        {
            "category":"Banks & Credit Unions",
            "subcategory":"Investment Brokerage",
            "type":"Services"
        }
    ],
    "sg:phone":"+61 7 4972 4044",
    "sg:postcode":"4680",
    "sg:province":"QLD",
    "sg:tags":[
        "management",
        "property"
    ],
    "wof:name":"Richardson Realty",
    "wof:placetype":"venue"
},
  "geometry": {"coordinates":[151.25462341299999,-23.8411273956],"type":"Point"}
}