{
  "type": "Feature",
  "properties": {
    "iso:country":"AU",
    "sg:address":"Suite 2, 195 Main St",
    "sg:city":"Osborne Park",
    "sg:classifiers":[
        {
            "category":"Manufacturing",
            "subcategory":"Textiles",
            "type":"Manufacturing & Wholesale Goods"
        }
    ],
    "sg:phone":"+61 8 9345 1200",
    "sg:postcode":"6017",
    "sg:province":"WA",
    "sg:tags":[
        "agent"
    ],
    "wof:name":"David Michael Agencies",
    "wof:placetype":"venue"
},
  "geometry": {"coordinates":[115.828102112,-31.8986644745],"type":"Point"}
}