{
  "type": "Feature",
  "properties": {
    "iso:country":"AU",
    "sg:address":"Unit 7,4- 10 Farrall Rd",
    "sg:city":"Midvale",
    "sg:classifiers":[
        {
            "category":"Shopping",
            "subcategory":"Gifts & Souvenirs",
            "type":"Retail Goods"
        }
    ],
    "sg:phone":"+61 8 9250 1660",
    "sg:postcode":"6056",
    "sg:province":"WA",
    "sg:tags":[
        "print",
        "poster",
        "pictures"
    ],
    "wof:name":"Framing Factory The",
    "wof:placetype":"venue"
},
  "geometry": {"coordinates":[116.033630371,-31.8840770721],"type":"Point"}
}