{
  "type": "Feature",
  "properties": {
    "addr:full":"99 Forrester Rd St Marys NSW 2760",
    "addr:housenumber":"99",
    "addr:postcode":"2760",
    "addr:street":"Forrester Rd",
    "iso:country":"AU",
    "sg:address":"99 Forrester Rd",
    "sg:city":"St Marys",
    "sg:classifiers":[
        {
            "category":"Farming",
            "subcategory":"Fish & Marine Products",
            "type":"Manufacturing & Wholesale Goods"
        }
    ],
    "sg:phone":"+61 2 9673 2505",
    "sg:postcode":"2760",
    "sg:province":"NSW",
    "sg:tags":[
        "equipment",
        "salvage"
    ],
    "wof:name":"Barges Australia",
    "wof:placetype":"venue"
},
  "geometry": {"coordinates":[150.775588989,-33.7578086853],"type":"Point"}
}