{
  "type": "Feature",
  "properties": {
    "addr:full":"365 Springvale Rd Springvale VIC 3171",
    "addr:housenumber":"365",
    "addr:postcode":"3171",
    "addr:street":"Springvale Rd",
    "iso:country":"AU",
    "sg:address":"365 Springvale Rd",
    "sg:city":"Springvale",
    "sg:classifiers":[
        {
            "category":"Health Services",
            "subcategory":"Optometrist",
            "type":"Services"
        }
    ],
    "sg:phone":"+61 3 9574 0388",
    "sg:postcode":"3171",
    "sg:province":"VIC",
    "wof:name":"Helen Higgins (Genitsaris) & Vivien Rutter",
    "wof:placetype":"venue"
},
  "geometry": {"coordinates":[145.15235900900001,-37.9530296326],"type":"Point"}
}