{
  "type": "Feature",
  "properties": {
    "addr:full":"18 Park St Mooroopna VIC 3629",
    "addr:housenumber":"18",
    "addr:postcode":"3629",
    "addr:street":"Park St",
    "iso:country":"AU",
    "sg:address":"18 Park St",
    "sg:city":"Mooroopna",
    "sg:classifiers":[
        {
            "category":"Home & Garden",
            "subcategory":"Building Materials",
            "type":"Retail Goods"
        }
    ],
    "sg:phone":"+61 419 506 726",
    "sg:postcode":"3629",
    "sg:province":"VIC",
    "sg:tags":[
        "lawn",
        "cutting",
        "maintenance"
    ],
    "wof:name":"The Mower Man",
    "wof:placetype":"venue"
},
  "geometry": {"coordinates":[145.36380004899999,-36.3909683228],"type":"Point"}
}