{
  "type": "Feature",
  "properties": {
    "addr:full":"Level 1, 239 King St Newcastle NSW 2300",
    "addr:housenumber":"239",
    "addr:postcode":"2300",
    "addr:street":"King St",
    "iso:country":"AU",
    "sg:address":"Level 1, 239 King St",
    "sg:city":"Newcastle",
    "sg:classifiers":[
        {
            "category":"Banks & Credit Unions",
            "subcategory":"Financial Services",
            "type":"Services"
        }
    ],
    "sg:phone":"+61 1300 587 673",
    "sg:postcode":"2300",
    "sg:province":"NSW",
    "sg:tags":[
        "annuity",
        "rollover",
        "superannuation",
        "consultant"
    ],
    "wof:name":"Self Managed Super Specialists",
    "wof:placetype":"venue"
},
  "geometry": {"coordinates":[151.77049299999999,-32.928413],"type":"Point"}
}