{
  "type": "Feature",
  "properties": {
    "addr:full":"98 Herbert St Bowen QLD 4805",
    "addr:housenumber":"98",
    "addr:postcode":"4805",
    "addr:street":"Herbert St",
    "iso:country":"AU",
    "sg:address":"98 Herbert St",
    "sg:city":"Bowen",
    "sg:classifiers":[
        {
            "category":"Autos & Motor Vehicles",
            "subcategory":"Auto Supplies",
            "type":"Retail Goods"
        }
    ],
    "sg:phone":"+61 7 4786 1355",
    "sg:postcode":"4805",
    "sg:province":"QLD",
    "sg:tags":[
        "accessory"
    ],
    "wof:name":"McDermott Holden",
    "wof:placetype":"venue"
},
  "geometry": {"coordinates":[148.240631103,-20.0029087067],"type":"Point"}
}