{
  "type": "Feature",
  "properties": {
    "addr:full":"Ste 1/ 31 Macquarie St Parramatta NSW 2150",
    "addr:housenumber":"31",
    "addr:postcode":"2150",
    "addr:street":"Macquarie St",
    "iso:country":"AU",
    "sg:address":"Ste 1/ 31 Macquarie St",
    "sg:city":"Parramatta",
    "sg:classifiers":[
        {
            "category":"Cafe",
            "type":"Food & Drink"
        }
    ],
    "sg:phone":"+61 2 9633 1454",
    "sg:postcode":"2150",
    "sg:province":"NSW",
    "wof:name":"Cafe 31 On Macquarie",
    "wof:placetype":"venue"
},
  "geometry": {"coordinates":[150.94367980999999,-33.8709259033],"type":"Point"}
}