{
  "type": "Feature",
  "properties": {
    "addr:full":"Ashmore City Shopng Cntr 206 Currumburra Rd Ashmore QLD 4214",
    "addr:housenumber":"206",
    "addr:postcode":"4214",
    "addr:street":"Currumburra Rd",
    "iso:country":"AU",
    "sg:address":"Ashmore City Shopng Cntr 206 Currumburra Rd",
    "sg:city":"Ashmore",
    "sg:classifiers":[
        {
            "category":"Travel",
            "subcategory":"Travel Agent",
            "type":"Entertainment"
        }
    ],
    "sg:phone":"+61 13 18 66",
    "sg:postcode":"4214",
    "sg:province":"QLD",
    "sg:tags":[
        "consultant"
    ],
    "wof:name":"Flight Centre",
    "wof:placetype":"venue"
},
  "geometry": {"coordinates":[153.38183593799999,-27.9799594879],"type":"Point"}
}