{
  "type": "Feature",
  "properties": {
    "iso:country":"AU",
    "sg:address":"48 Boundary St",
    "sg:city":"Forster",
    "sg:classifiers":[
        {
            "category":"Farming",
            "subcategory":"Fish & Marine Products",
            "type":"Manufacturing & Wholesale Goods"
        }
    ],
    "sg:phone":"+61 2 6554 6821",
    "sg:postcode":"2428",
    "sg:province":"NSW",
    "sg:tags":[
        "supplier",
        "oyster",
        "farmer"
    ],
    "wof:name":"Barclay P L",
    "wof:placetype":"venue"
},
  "geometry": {"coordinates":[152.527786,-32.188725],"type":"Point"}
}