{
  "type": "Feature",
  "properties": {
    "addr:full":"36 Maud St Maroochydore QLD 4558",
    "addr:housenumber":"36",
    "addr:postcode":"4558",
    "addr:street":"Maud St",
    "iso:country":"AU",
    "sg:address":"36 Maud St",
    "sg:city":"Maroochydore",
    "sg:classifiers":[
        {
            "category":"Real Estate",
            "subcategory":"Surveying",
            "type":"Services"
        }
    ],
    "sg:phone":"+61 7 5479 5311",
    "sg:postcode":"4558",
    "sg:province":"QLD",
    "sg:tags":[
        "surveyor",
        "land"
    ],
    "sg:website":"http://www.cadcon.com.au",
    "wof:name":"Cadcon Surveying & Town Planning",
    "wof:placetype":"venue"
},
  "geometry": {"coordinates":[153.093139648,-26.6584892273],"type":"Point"}
}