{
  "type": "Feature",
  "properties": {
    "addr:full":"6 Sydenham Rd Brookvale NSW 2100",
    "addr:housenumber":"6",
    "addr:postcode":"2100",
    "addr:street":"Sydenham Rd",
    "iso:country":"AU",
    "sg:address":"6 Sydenham Rd",
    "sg:city":"Brookvale",
    "sg:classifiers":[
        {
            "category":"Real Estate",
            "subcategory":"Architect",
            "type":"Services"
        }
    ],
    "sg:phone":"+61 2 9905 5323",
    "sg:postcode":"2100",
    "sg:province":"NSW",
    "sg:tags":[
        "magnet",
        "magnetic",
        "material"
    ],
    "wof:name":"Advertising Signmaker",
    "wof:placetype":"venue"
},
  "geometry": {"coordinates":[151.27239990199999,-33.764339447],"type":"Point"}
}