{
  "type": "Feature",
  "properties": {
    "addr:full":"PO Box 40 Blairgowrie VIC 3942",
    "addr:postcode":"3942",
    "iso:country":"AU",
    "sg:address":"PO Box 40",
    "sg:city":"Blairgowrie",
    "sg:classifiers":[
        {
            "category":"Home & Garden",
            "subcategory":"Building Materials",
            "type":"Retail Goods"
        }
    ],
    "sg:phone":"+61 3 5988 5648",
    "sg:postcode":"3942",
    "sg:province":"VIC",
    "sg:tags":[
        "lawn",
        "cutting",
        "maintenance"
    ],
    "wof:name":"Fine Cut",
    "wof:placetype":"venue"
},
  "geometry": {"coordinates":[144.770553589,-38.3693389893],"type":"Point"}
}