{
  "type": "Feature",
  "properties": {
    "addr:full":"Level 49 80 Collins St Melbourne VIC 3000",
    "addr:housenumber":"80",
    "addr:postcode":"3000",
    "addr:street":"Collins St",
    "iso:country":"AU",
    "sg:address":"Level 49 80 Collins St",
    "sg:city":"Melbourne",
    "sg:classifiers":[
        {
            "category":"Airline",
            "type":"Transportation"
        }
    ],
    "sg:phone":"+61 3 9653 2406",
    "sg:postcode":"3000",
    "sg:province":"VIC",
    "sg:tags":[
        "agent"
    ],
    "wof:name":"Air Nauru",
    "wof:placetype":"venue"
},
  "geometry": {"coordinates":[144.97105407699999,-37.8140335083],"type":"Point"}
}