{
  "type": "Feature",
  "properties": {
    "addr:full":"12a Darcy St Parramatta NSW 2150",
    "addr:housenumber":"12a",
    "addr:postcode":"2150",
    "addr:street":"Darcy St",
    "iso:country":"AU",
    "sg:address":"12a Darcy St",
    "sg:city":"Parramatta",
    "sg:classifiers":[
        {
            "category":"Personal",
            "subcategory":"Tattoo Parlor",
            "type":"Services"
        }
    ],
    "sg:phone":"+61 2 9635 3331",
    "sg:postcode":"2150",
    "sg:province":"NSW",
    "sg:tags":[
        "tattooing"
    ],
    "wof:name":"The Tattoo Temple",
    "wof:placetype":"venue"
},
  "geometry": {"coordinates":[151.107788086,-33.7850265503],"type":"Point"}
}