{
  "type": "Feature",
  "properties": {
    "iso:country":"AU",
    "sg:address":"RMB 4225 Thomsons Rd",
    "sg:city":"Hazelwood North",
    "sg:classifiers":[
        {
            "category":"Building & Trades",
            "subcategory":"Construction",
            "type":"Services"
        }
    ],
    "sg:phone":"+61 3 5166 1749",
    "sg:postcode":"3840",
    "sg:province":"VIC",
    "sg:tags":[
        "contractor"
    ],
    "wof:name":"Brett Roberts Builder",
    "wof:placetype":"venue"
},
  "geometry": {"coordinates":[146.460739136,-38.2959671021],"type":"Point"}
}