{
  "type": "Feature",
  "properties": {
    "addr:full":"19B Mohr St Tullamarine VIC 3043",
    "addr:housenumber":"19b",
    "addr:postcode":"3043",
    "addr:street":"Mohr St",
    "iso:country":"AU",
    "sg:address":"19B Mohr St",
    "sg:city":"Tullamarine",
    "sg:classifiers":[
        {
            "category":"Professional",
            "subcategory":"Employment Agencies",
            "type":"Services"
        }
    ],
    "sg:phone":"+61 3 9335 3833",
    "sg:postcode":"3043",
    "sg:province":"VIC",
    "sg:tags":[
        "broker",
        "custom"
    ],
    "wof:name":"Yugo Transport Shipping Services",
    "wof:placetype":"venue"
},
  "geometry": {"coordinates":[144.86448669399999,-37.7097740173],"type":"Point"}
}