{
  "type": "Feature",
  "properties": {
    "iso:country":"AU",
    "sg:address":"Shed 5",
    "sg:city":"Laidlaw Drive Ballarat",
    "sg:classifiers":[
        {
            "category":"Manufacturing",
            "subcategory":"Tools & Machinery",
            "type":"Manufacturing & Wholesale Goods"
        }
    ],
    "sg:phone":"+61 438 503 345",
    "sg:postcode":"3350",
    "sg:province":"VIC",
    "sg:tags":[
        "earth",
        "excavating",
        "moving",
        "equipment"
    ],
    "wof:name":"A & J Bobcat Hire & Asphalting",
    "wof:placetype":"venue"
},
  "geometry": {"coordinates":[143.824783,-37.577511],"type":"Point"}
}