{
  "type": "Feature",
  "properties": {
    "iso:country":"AU",
    "sg:address":"20 Kellett St",
    "sg:city":"Kings Cross",
    "sg:classifiers":[
        {
            "category":"Personal",
            "subcategory":"Adult",
            "type":"Services"
        }
    ],
    "sg:phone":"+61 2 9357 1125",
    "sg:postcode":"2011",
    "sg:province":"NSW",
    "sg:tags":[
        "vic",
        "except",
        "state",
        "escort",
        "social",
        "qld"
    ],
    "wof:name":"Maggies Place",
    "wof:placetype":"venue"
},
  "geometry": {"coordinates":[151.223312378,-33.874584198],"type":"Point"}
}