{
  "type": "Feature",
  "properties": {
    "addr:full":"63 Main St Koondrook VIC 3580",
    "addr:housenumber":"63",
    "addr:postcode":"3580",
    "addr:street":"Main St",
    "iso:country":"AU",
    "sg:address":"63 Main St",
    "sg:city":"Koondrook",
    "sg:classifiers":[
        {
            "category":"Real Estate",
            "subcategory":"Surveying",
            "type":"Services"
        }
    ],
    "sg:phone":"+61 417 501 880",
    "sg:postcode":"3580",
    "sg:province":"VIC",
    "sg:tags":[
        "surveyor",
        "land"
    ],
    "wof:name":"Beacom Hatch",
    "wof:placetype":"venue"
},
  "geometry": {"coordinates":[144.13128662099999,-35.6453895569],"type":"Point"}
}