{
  "type": "Feature",
  "properties": {
    "addr:full":"15 Crest Ave Balwyn VIC 3103",
    "addr:housenumber":"15",
    "addr:postcode":"3103",
    "addr:street":"Crest Ave",
    "iso:country":"AU",
    "sg:address":"15 Crest Ave",
    "sg:city":"Balwyn",
    "sg:classifiers":[
        {
            "category":"Professional",
            "subcategory":"Management & Consulting",
            "type":"Services"
        }
    ],
    "sg:phone":"+61 3 9817 5730",
    "sg:postcode":"3103",
    "sg:province":"VIC",
    "sg:tags":[
        "consultant"
    ],
    "wof:name":"Evaluation Training & Services Australia Pty Ltd",
    "wof:placetype":"venue"
},
  "geometry": {"coordinates":[145.07089233400001,-37.8132743835],"type":"Point"}
}