{
  "type": "Feature",
  "properties": {
    "iso:country":"AU",
    "sg:address":"72- 76 Station St",
    "sg:city":"Norlane",
    "sg:classifiers":[
        {
            "category":"Utilities",
            "subcategory":"Cable",
            "type":"Services"
        }
    ],
    "sg:phone":"+61 3 5275 8180",
    "sg:postcode":"3214",
    "sg:province":"VIC",
    "sg:tags":[
        "synthetic",
        "rope",
        "fitting",
        "wire"
    ],
    "wof:name":"Bay Lifting & Testing Pty Ltd",
    "wof:placetype":"venue"
},
  "geometry": {"coordinates":[144.366424561,-38.0911140442],"type":"Point"}
}