{
  "type": "Feature",
  "properties": {
    "addr:full":"67 Trawalla Ave Thomastown VIC 3074",
    "addr:housenumber":"67",
    "addr:postcode":"3074",
    "addr:street":"Trawalla Ave",
    "iso:country":"AU",
    "sg:address":"67 Trawalla Ave",
    "sg:city":"Thomastown",
    "sg:classifiers":[
        {
            "category":"Building & Trades",
            "subcategory":"Construction",
            "type":"Services"
        }
    ],
    "sg:phone":"+61 3 9357 4863",
    "sg:postcode":"3074",
    "sg:province":"VIC",
    "sg:tags":[
        "tennis court",
        "repair"
    ],
    "wof:name":"Tennis Court Aggregate Pty Ltd",
    "wof:placetype":"venue"
},
  "geometry": {"coordinates":[144.973587036,-37.6875762939],"type":"Point"}
}