{
  "type": "Feature",
  "properties": {
    "addr:full":"200 Strickland Rd Bendigo East VIC 3550",
    "addr:housenumber":"200",
    "addr:postcode":"3550",
    "addr:street":"Strickland Rd",
    "iso:country":"AU",
    "sg:address":"200 Strickland Rd",
    "sg:city":"Bendigo East",
    "sg:classifiers":[
        {
            "category":"Home & Garden",
            "subcategory":"Building Materials",
            "type":"Retail Goods"
        }
    ],
    "sg:phone":"+61 3 5449 3500",
    "sg:postcode":"3550",
    "sg:province":"VIC",
    "sg:tags":[
        "fencing"
    ],
    "wof:name":"CVR Fencing",
    "wof:placetype":"venue"
},
  "geometry": {"coordinates":[144.32362365700001,-36.7538146973],"type":"Point"}
}