{
  "type": "Feature",
  "properties": {
    "iso:country":"AU",
    "sg:address":"Cnr Koonya Cct & Taren Point Rd",
    "sg:city":"Taren Point",
    "sg:classifiers":[
        {
            "category":"Building & Trades",
            "subcategory":"Equipment Rental",
            "type":"Services"
        }
    ],
    "sg:phone":"+61 1300 555 348",
    "sg:postcode":"2229",
    "sg:province":"NSW",
    "sg:tags":[
        "fitness"
    ],
    "wof:name":"Exercise Australia",
    "wof:placetype":"venue"
},
  "geometry": {"coordinates":[151.124465942,-34.0145988464],"type":"Point"}
}