{
  "type": "Feature",
  "properties": {
    "addr:full":"Nerang-Broadbeach Rd Carrara QLD 4211",
    "addr:postcode":"4211",
    "addr:street":"Nerang-Broadbeach Rd",
    "iso:country":"AU",
    "sg:address":"Nerang-Broadbeach Rd",
    "sg:city":"Carrara",
    "sg:classifiers":[
        {
            "category":"Sports & Exercise",
            "subcategory":"Sports Center",
            "type":"Entertainment"
        }
    ],
    "sg:phone":"+61 7 5596 0935",
    "sg:postcode":"4211",
    "sg:province":"QLD",
    "sg:tags":[
        "ground"
    ],
    "wof:name":"Croatian Sports Centre",
    "wof:placetype":"venue"
},
  "geometry": {"coordinates":[153.366653442,-28.0085773468],"type":"Point"}
}