{
  "type": "Feature",
  "properties": {
    "addr:full":"12- 14 Dunlop Rd Mulgrave VIC 3170",
    "addr:housenumber":"14",
    "addr:postcode":"3170",
    "addr:street":"Dunlop Rd",
    "iso:country":"AU",
    "sg:address":"12- 14 Dunlop Rd",
    "sg:city":"Mulgrave",
    "sg:classifiers":[
        {
            "category":"Shopping",
            "subcategory":"Stationery & Office Supplies",
            "type":"Retail Goods"
        }
    ],
    "sg:phone":"+61 3 8561 2222",
    "sg:postcode":"3170",
    "sg:province":"VIC",
    "sg:tags":[
        "partition"
    ],
    "wof:name":"Rondo Building Services Pty Ltd",
    "wof:placetype":"venue"
},
  "geometry": {"coordinates":[145.155151367,-37.9103927612],"type":"Point"}
}