{
  "type": "Feature",
  "properties": {
    "addr:full":"Shop 5, 286- 292 Maitland Rd Mayfield NSW 2304",
    "addr:housenumber":"shop 5;292",
    "addr:postcode":"286;2304",
    "addr:street":"Maitland Rd",
    "iso:country":"AU",
    "sg:address":"Shop 5, 286- 292 Maitland Rd",
    "sg:city":"Mayfield",
    "sg:classifiers":[
        {
            "category":"Professional",
            "subcategory":"Accounting & Tax Preparation",
            "type":"Services"
        }
    ],
    "sg:phone":"+61 2 4967 6221",
    "sg:postcode":"2304",
    "sg:province":"NSW",
    "sg:tags":[
        "consultant",
        "taxation"
    ],
    "wof:name":"Smart Tax Solutions",
    "wof:placetype":"venue"
},
  "geometry": {"coordinates":[151.73600769000001,-32.8970832825],"type":"Point"}
}