{
  "type": "Feature",
  "properties": {
    "addr:full":"15 George St Marmong Point NSW 2284",
    "addr:housenumber":"15",
    "addr:postcode":"2284",
    "addr:street":"George St",
    "iso:country":"AU",
    "sg:address":"15 George St",
    "sg:city":"Marmong Point",
    "sg:classifiers":[
        {
            "category":"Professional",
            "subcategory":"Art Services",
            "type":"Services"
        }
    ],
    "sg:phone":"+61 2 4958 4501",
    "sg:postcode":"2284",
    "sg:province":"NSW",
    "sg:tags":[
        "interior",
        "decorator"
    ],
    "wof:name":"Silk Gardens",
    "wof:placetype":"venue"
},
  "geometry": {"coordinates":[151.61822509800001,-32.9820213318],"type":"Point"}
}