{
  "type": "Feature",
  "properties": {
    "iso:country":"AU",
    "sg:address":"31 John St",
    "sg:city":"Forresters Beach",
    "sg:classifiers":[
        {
            "category":"Health Services",
            "subcategory":"Health Practitioner",
            "type":"Services"
        }
    ],
    "sg:phone":"+61 410 441 601",
    "sg:postcode":"2260",
    "sg:province":"NSW",
    "sg:tags":[
        "naturopath"
    ],
    "wof:name":"Hibiscus Natural Health",
    "wof:placetype":"venue"
},
  "geometry": {"coordinates":[151.458466,-33.414417],"type":"Point"}
}