{
  "type": "Feature",
  "properties": {
    "iso:country":"AU",
    "sg:address":"6 Simpson St",
    "sg:city":"Mt Isa",
    "sg:classifiers":[
        {
            "category":"Building & Trades",
            "subcategory":"Plumbing",
            "type":"Services"
        }
    ],
    "sg:phone":"+61 7 4743 9671",
    "sg:postcode":"4825",
    "sg:province":"QLD",
    "sg:tags":[
        "pump",
        "repairer"
    ],
    "wof:name":"CC's Pool Maintenance & Supplies",
    "wof:placetype":"venue"
},
  "geometry": {"coordinates":[139.494125,-20.729227],"type":"Point"}
}