{
  "type": "Feature",
  "properties": {
    "addr:full":"Linke House 6 Second St Nuriootpa SA 5355",
    "addr:housenumber":"6",
    "addr:postcode":"5355",
    "addr:street":"Second St",
    "iso:country":"AU",
    "sg:address":"Linke House 6 Second St",
    "sg:city":"Nuriootpa",
    "sg:classifiers":[
        {
            "category":"Insurance",
            "subcategory":"Hazard Insurance",
            "type":"Services"
        }
    ],
    "sg:phone":"+61 8 8562 1956",
    "sg:postcode":"5355",
    "sg:province":"SA",
    "sg:tags":[
        "motor",
        "vehicle"
    ],
    "wof:name":"Hampel Woodards Pty Ltd",
    "wof:placetype":"venue"
},
  "geometry": {"coordinates":[138.99551391599999,-34.4702072144],"type":"Point"}
}