{
  "type": "Feature",
  "properties": {
    "addr:full":"Cnr Woodstock Ave & Duke St Mt Druitt NSW 2770",
    "addr:postcode":"2770",
    "addr:street":"Cnr Woodstock Ave & Duke St Mt",
    "iso:country":"AU",
    "sg:address":"Cnr Woodstock Ave & Duke St",
    "sg:city":"Mt Druitt",
    "sg:classifiers":[
        {
            "category":"Food & Beverages",
            "subcategory":"Liquor & Beverages",
            "type":"Retail Goods"
        }
    ],
    "sg:phone":"+61 2 9625 0347",
    "sg:postcode":"2770",
    "sg:province":"NSW",
    "sg:tags":[
        "store"
    ],
    "wof:name":"Liquor Stax Australia Pty Ltd",
    "wof:placetype":"venue"
},
  "geometry": {"coordinates":[150.8177948,-33.7556152344],"type":"Point"}
}