{
  "type": "Feature",
  "properties": {
    "addr:full":"PO Box 1087 Croydon NSW 8674",
    "addr:postcode":"8674",
    "iso:country":"AU",
    "sg:address":"PO Box 1087",
    "sg:city":"Croydon",
    "sg:classifiers":[
        {
            "category":"Utilities",
            "subcategory":"Electric",
            "type":"Services"
        }
    ],
    "sg:phone":"+61 419 282 802",
    "sg:postcode":"8674",
    "sg:province":"NSW",
    "sg:tags":[
        "electrical",
        "contractor"
    ],
    "wof:name":"Daysan Electrical Pty Ltd",
    "wof:placetype":"venue"
},
  "geometry": {"coordinates":[145.279754639,-37.7989196777],"type":"Point"}
}