{
  "type": "Feature",
  "properties": {
    "addr:full":"Shop 12, Boyne Plaza Boyne Island QLD 4680",
    "addr:housenumber":"shop 12",
    "addr:postcode":"4680",
    "addr:street":"Boyne Plaza",
    "iso:country":"AU",
    "sg:address":"Shop 12, Boyne Plaza",
    "sg:city":"Boyne Island",
    "sg:classifiers":[
        {
            "category":"Shopping",
            "subcategory":"Shoes",
            "type":"Retail Goods"
        }
    ],
    "sg:phone":"+61 7 4973 3000",
    "sg:postcode":"4680",
    "sg:province":"QLD",
    "sg:tags":[
        "footwear"
    ],
    "wof:name":"Exposed",
    "wof:placetype":"venue"
},
  "geometry": {"coordinates":[151.30718994099999,-23.9703407288],"type":"Point"}
}