{
  "type": "Feature",
  "properties": {
    "addr:full":"95 Telopea Ave Caringbah NSW 2229",
    "addr:housenumber":"95",
    "addr:postcode":"2229",
    "addr:street":"Telopea Ave",
    "iso:country":"AU",
    "sg:address":"95 Telopea Ave",
    "sg:city":"Caringbah",
    "sg:classifiers":[
        {
            "category":"Professional",
            "subcategory":"Art Services",
            "type":"Services"
        }
    ],
    "sg:phone":"+61 2 9524 4820",
    "sg:postcode":"2229",
    "sg:province":"NSW",
    "sg:tags":[
        "picture",
        "frame",
        "framing"
    ],
    "wof:name":"Wright Phones",
    "wof:placetype":"venue"
},
  "geometry": {"coordinates":[151.115524292,-34.0540924072],"type":"Point"}
}