{
  "type": "Feature",
  "properties": {
    "iso:country":"AU",
    "sg:address":"47 Jacaranda Rd",
    "sg:city":"Caringbah",
    "sg:classifiers":[
        {
            "category":"Personal",
            "subcategory":"Beauty Salon",
            "type":"Services"
        }
    ],
    "sg:phone":"+61 2 9524 4660",
    "sg:postcode":"2229",
    "sg:province":"NSW",
    "sg:tags":[
        "hairdresser"
    ],
    "wof:name":"Olly's Hair Culture",
    "wof:placetype":"venue"
},
  "geometry": {"coordinates":[151.12298584000001,-34.0418281555],"type":"Point"}
}