{
  "type": "Feature",
  "properties": {
    "iso:country":"AU",
    "sg:address":"120 Days Rd",
    "sg:city":"Ferryden Park",
    "sg:classifiers":[
        {
            "category":"Farming",
            "subcategory":"Crops",
            "type":"Manufacturing & Wholesale Goods"
        }
    ],
    "sg:phone":"+61 1300 722 534",
    "sg:postcode":"5010",
    "sg:province":"SA",
    "sg:tags":[
        "warehousing"
    ],
    "wof:name":"Northline Pty Ltd",
    "wof:placetype":"venue"
},
  "geometry": {"coordinates":[138.56578064000001,-34.8698692322],"type":"Point"}
}