{
  "type": "Feature",
  "properties": {
    "addr:full":"31 Neerim Rd Castle Cove NSW 2069",
    "addr:housenumber":"31",
    "addr:postcode":"2069",
    "addr:street":"Neerim Rd",
    "iso:country":"AU",
    "sg:address":"31 Neerim Rd",
    "sg:city":"Castle Cove",
    "sg:classifiers":[
        {
            "category":"Professional",
            "subcategory":"Business Services",
            "type":"Services"
        }
    ],
    "sg:phone":"+61 2 9417 8726",
    "sg:postcode":"2069",
    "sg:province":"NSW",
    "sg:tags":[
        "broker"
    ],
    "wof:name":"Simgo Services Pty Ltd",
    "wof:placetype":"venue"
},
  "geometry": {"coordinates":[151.209915161,-33.782875061],"type":"Point"}
}