{
  "type": "Feature",
  "properties": {
    "iso:country":"AU",
    "sg:address":"762A Beaufort St",
    "sg:city":"Mt Lawley",
    "sg:classifiers":[
        {
            "category":"Manufacturing",
            "subcategory":"Musical Instruments",
            "type":"Manufacturing & Wholesale Goods"
        }
    ],
    "sg:phone":"+61 8 9371 8822",
    "sg:postcode":"6050",
    "sg:province":"WA",
    "sg:tags":[
        "repair",
        "maker"
    ],
    "sg:website":"http://www.therockinn.com",
    "wof:name":"The Rock Inn",
    "wof:placetype":"venue"
},
  "geometry": {"coordinates":[115.878311157,-31.9279460907],"type":"Point"}
}