{
  "type": "Feature",
  "properties": {
    "iso:country":"AU",
    "sg:address":"Horton Pde",
    "sg:city":"Maroochydore",
    "sg:classifiers":[
        {
            "category":"Autos & Motor Vehicles",
            "subcategory":"Auto Supplies",
            "type":"Retail Goods"
        }
    ],
    "sg:phone":"+61 7 5443 4160",
    "sg:postcode":"4558",
    "sg:province":"QLD",
    "sg:tags":[
        "tyre"
    ],
    "wof:name":"Kmart Tyre & Auto Service Maroochydore",
    "wof:placetype":"venue"
},
  "geometry": {"coordinates":[153.089675903,-26.6531066895],"type":"Point"}
}