{
  "type": "Feature",
  "properties": {
    "addr:full":"9 Carroll St Mt Louisa QLD 4814",
    "addr:housenumber":"9",
    "addr:postcode":"4814",
    "addr:street":"Carroll St Mt Louisa",
    "iso:country":"AU",
    "sg:address":"9 Carroll St",
    "sg:city":"Mt Louisa",
    "sg:classifiers":[
        {
            "category":"Autos & Motor Vehicles",
            "subcategory":"Auto Supplies",
            "type":"Retail Goods"
        }
    ],
    "sg:phone":"+61 7 4774 6900",
    "sg:postcode":"4814",
    "sg:province":"QLD",
    "sg:tags":[
        "equipment",
        "part",
        "truck"
    ],
    "wof:name":"Red Australia Equipment Pty. Ltd.",
    "wof:placetype":"venue"
},
  "geometry": {"coordinates":[146.74783300000001,-19.265335],"type":"Point"}
}