{
  "type": "Feature",
  "properties": {
    "addr:full":"33 Redleaf Ave Wahroonga NSW 2076",
    "addr:housenumber":"33",
    "addr:postcode":"2076",
    "addr:street":"Redleaf Ave",
    "iso:country":"AU",
    "sg:address":"33 Redleaf Ave",
    "sg:city":"Wahroonga",
    "sg:classifiers":[
        {
            "category":"Personal",
            "subcategory":"Shoe Repair & Shine",
            "type":"Services"
        }
    ],
    "sg:phone":"+61 2 9489 1970",
    "sg:postcode":"2076",
    "sg:province":"NSW",
    "sg:tags":[
        "footwear"
    ],
    "wof:name":"Wahroonga Cobblers Shoppe",
    "wof:placetype":"venue"
},
  "geometry": {"coordinates":[151.11720275900001,-33.7189254761],"type":"Point"}
}