{
  "type": "Feature",
  "properties": {
    "iso:country":"AU",
    "sg:address":"41 O.G. Rd",
    "sg:city":"Klemzig",
    "sg:classifiers":[
        {
            "category":"Health Services",
            "subcategory":"Health Practitioner",
            "type":"Services"
        }
    ],
    "sg:phone":"+61 8 8266 1694",
    "sg:postcode":"5087",
    "sg:province":"SA",
    "sg:tags":[
        "herbalist"
    ],
    "wof:name":"Woo Steven",
    "wof:placetype":"venue"
},
  "geometry": {"coordinates":[138.63548278799999,-34.8799934387],"type":"Point"}
}