{
  "type": "Feature",
  "properties": {
    "addr:full":"43 Strathallan Rd Macleod VIC 3085",
    "addr:housenumber":"43",
    "addr:postcode":"3085",
    "addr:street":"Strathallan Rd",
    "iso:country":"AU",
    "sg:address":"43 Strathallan Rd",
    "sg:city":"Macleod",
    "sg:classifiers":[
        {
            "category":"Home & Garden",
            "subcategory":"Building Materials",
            "type":"Retail Goods"
        }
    ],
    "sg:phone":"+61 3 9459 7857",
    "sg:postcode":"3085",
    "sg:province":"VIC",
    "sg:tags":[
        "merchant",
        "glass",
        "glazier"
    ],
    "wof:name":"Anyhour Glazing Pty Ltd",
    "wof:placetype":"venue"
},
  "geometry": {"coordinates":[145.07601928700001,-37.7241020203],"type":"Point"}
}