{
  "type": "Feature",
  "properties": {
    "addr:full":"33 Pirie St Adelaide SA 5000",
    "addr:housenumber":"33",
    "addr:postcode":"5000",
    "addr:street":"Pirie St",
    "iso:country":"AU",
    "sg:address":"33 Pirie St",
    "sg:city":"Adelaide",
    "sg:classifiers":[
        {
            "category":"Health Services",
            "subcategory":"Chiropractor",
            "type":"Services"
        }
    ],
    "sg:phone":"+61 8 8212 4187",
    "sg:postcode":"5000",
    "sg:province":"SA",
    "wof:name":"Swaffer Tamara Dr",
    "wof:placetype":"venue"
},
  "geometry": {"coordinates":[138.60113525400001,-34.9258308411],"type":"Point"}
}