{
  "type": "Feature",
  "properties": {
    "addr:full":"24 Hunter St Castlemaine VIC 3450",
    "addr:housenumber":"24",
    "addr:postcode":"3450",
    "addr:street":"Hunter St",
    "iso:country":"AU",
    "sg:address":"24 Hunter St",
    "sg:city":"Castlemaine",
    "sg:classifiers":[
        {
            "category":"Organizations",
            "subcategory":"Community Association",
            "type":"Services"
        }
    ],
    "sg:phone":"+61 3 5470 5154",
    "sg:postcode":"3450",
    "sg:province":"VIC",
    "sg:tags":[
        "organisation",
        "family",
        "welfare"
    ],
    "wof:name":"A Shared Vision",
    "wof:placetype":"venue"
},
  "geometry": {"coordinates":[144.219192505,-37.0575294495],"type":"Point"}
}