{
  "type": "Feature",
  "properties": {
    "addr:full":"271 Huntingdale Rd Huntingdale VIC 3166",
    "addr:housenumber":"271",
    "addr:postcode":"3166",
    "addr:street":"Huntingdale Rd",
    "iso:country":"AU",
    "sg:address":"271 Huntingdale Rd",
    "sg:city":"Huntingdale",
    "sg:classifiers":[
        {
            "category":"Autos & Motor Vehicles",
            "subcategory":"Automobile Sales",
            "type":"Retail Goods"
        }
    ],
    "sg:phone":"+61 3 9562 9984",
    "sg:postcode":"3166",
    "sg:province":"VIC",
    "sg:tags":[
        "car",
        "used"
    ],
    "wof:name":"Showroom The",
    "wof:placetype":"venue"
},
  "geometry": {"coordinates":[145.103713989,-37.9090499878],"type":"Point"}
}