{
  "type": "Feature",
  "properties": {
    "iso:country":"AU",
    "sg:address":"47 Jesica Rd",
    "sg:city":"Campbellfield",
    "sg:classifiers":[
        {
            "category":"Communications",
            "subcategory":"Film & Video Production",
            "type":"Services"
        }
    ],
    "sg:phone":"+61 3 9357 7464",
    "sg:postcode":"3061",
    "sg:province":"VIC",
    "sg:tags":[
        "fan",
        "blower"
    ],
    "wof:name":"Nicotra Gebhardt Australia Pty Ltd",
    "wof:placetype":"venue"
},
  "geometry": {"coordinates":[144.95692443900001,-37.6582298279],"type":"Point"}
}