{
  "type": "Feature",
  "properties": {
    "iso:country":"AU",
    "sg:address":"PO Box 6",
    "sg:city":"Nabiac",
    "sg:classifiers":[
        {
            "category":"Building & Trades",
            "subcategory":"Construction",
            "type":"Services"
        }
    ],
    "sg:phone":"+61 2 6554 3068",
    "sg:postcode":"2312",
    "sg:province":"NSW",
    "sg:tags":[
        "earth",
        "excavating",
        "moving",
        "contractor"
    ],
    "wof:name":"Intercivil",
    "wof:placetype":"venue"
},
  "geometry": {"coordinates":[152.354446,-32.097198],"type":"Point"}
}