{
  "type": "Feature",
  "properties": {
    "iso:country":"AU",
    "sg:address":"31 Helen St",
    "sg:city":"Mt Gambier",
    "sg:classifiers":[
        {
            "category":"Health Services",
            "subcategory":"Dentist",
            "type":"Services"
        }
    ],
    "sg:phone":"+61 8 8724 9430",
    "sg:postcode":"5290",
    "sg:province":"SA",
    "wof:name":"Dharmarajah V K",
    "wof:placetype":"venue"
},
  "geometry": {"coordinates":[140.777039,-37.82972],"type":"Point"}
}