{
  "type": "Feature",
  "properties": {
    "addr:full":"140 Princes Hwy Ulladulla NSW 2539",
    "addr:housenumber":"140",
    "addr:postcode":"2539",
    "addr:street":"Princes Hwy",
    "iso:country":"AU",
    "sg:address":"140 Princes Hwy",
    "sg:city":"Ulladulla",
    "sg:classifiers":[
        {
            "category":"Professional",
            "subcategory":"Printing & Photocopies",
            "type":"Services"
        }
    ],
    "sg:phone":"+61 2 4455 2810",
    "sg:postcode":"2539",
    "sg:province":"NSW",
    "sg:tags":[
        "equipment",
        "plan"
    ],
    "wof:name":"Peter Smith",
    "wof:placetype":"venue"
},
  "geometry": {"coordinates":[150.473587036,-35.3614234924],"type":"Point"}
}