{
  "type": "Feature",
  "properties": {
    "addr:full":"13 Pilkington St Garbutt QLD 4814",
    "addr:housenumber":"13",
    "addr:postcode":"4814",
    "addr:street":"Pilkington St",
    "iso:country":"AU",
    "sg:address":"13 Pilkington St",
    "sg:city":"Garbutt",
    "sg:classifiers":[
        {
            "category":"Commercial Area",
            "type":"Public Place"
        }
    ],
    "sg:phone":"+61 7 4779 0699",
    "sg:postcode":"4814",
    "sg:province":"QLD",
    "sg:tags":[
        "heavy",
        "carrier"
    ],
    "wof:name":"Chemtrans",
    "wof:placetype":"venue"
},
  "geometry": {"coordinates":[146.767822,-19.264322],"type":"Point"}
}