{
  "type": "Feature",
  "properties": {
    "addr:full":"3 Tait Crt Oakleigh South VIC 3167",
    "addr:housenumber":"3",
    "addr:postcode":"3167",
    "addr:street":"Tait Crt",
    "iso:country":"AU",
    "sg:address":"3 Tait Crt",
    "sg:city":"Oakleigh South",
    "sg:classifiers":[
        {
            "category":"Building & Trades",
            "subcategory":"Construction",
            "type":"Services"
        }
    ],
    "sg:phone":"+61 412 323 193",
    "sg:postcode":"3167",
    "sg:province":"VIC",
    "sg:tags":[
        "installation",
        "air conditioning"
    ],
    "wof:name":"(ACAR) Air-Conditioning And Refrigeration Services",
    "wof:placetype":"venue"
},
  "geometry": {"coordinates":[145.09559631400001,-37.9347686768],"type":"Point"}
}