{
  "type": "Feature",
  "properties": {
    "addr:full":"127 Sydney Rd Coburg VIC 3058",
    "addr:housenumber":"127",
    "addr:postcode":"3058",
    "addr:street":"Sydney Rd",
    "iso:country":"AU",
    "sg:address":"127 Sydney Rd",
    "sg:city":"Coburg",
    "sg:classifiers":[
        {
            "category":"Health Services",
            "subcategory":"Dentist",
            "type":"Services"
        }
    ],
    "sg:phone":"+61 3 9386 1805",
    "sg:postcode":"3058",
    "sg:province":"VIC",
    "wof:name":"Yuen Tanya Dr",
    "wof:placetype":"venue"
},
  "geometry": {"coordinates":[144.96458435100001,-37.7518424988],"type":"Point"}
}