{
  "type": "Feature",
  "properties": {
    "addr:full":"445 Cross Rd South Plympton SA 5038",
    "addr:housenumber":"445",
    "addr:postcode":"5038",
    "addr:street":"Cross Rd",
    "iso:country":"AU",
    "sg:address":"445 Cross Rd",
    "sg:city":"South Plympton",
    "sg:classifiers":[
        {
            "category":"Government",
            "subcategory":"Court House",
            "type":"Public Place"
        }
    ],
    "sg:phone":"+61 8 8351 6664",
    "sg:postcode":"5038",
    "sg:province":"SA",
    "sg:tags":[
        "personal",
        "marriage",
        "family",
        "counselling"
    ],
    "wof:name":"Brett Williams Family Therapy",
    "wof:placetype":"venue"
},
  "geometry": {"coordinates":[138.56373596200001,-34.9678955078],"type":"Point"}
}