{
  "type": "Feature",
  "properties": {
    "addr:full":"556- 558 Marrickville Rd Dulwich Hill NSW 2203",
    "addr:housenumber":"558",
    "addr:postcode":"2203",
    "addr:street":"Marrickville Rd",
    "iso:country":"AU",
    "sg:address":"556- 558 Marrickville Rd",
    "sg:city":"Dulwich Hill",
    "sg:classifiers":[
        {
            "category":"Health Services",
            "subcategory":"Doctor",
            "type":"Services"
        }
    ],
    "sg:phone":"+61 2 9572 7421",
    "sg:postcode":"2203",
    "sg:province":"NSW",
    "sg:tags":[
        "medical",
        "practitioner"
    ],
    "wof:name":"Latif Wagdy Dr",
    "wof:placetype":"venue"
},
  "geometry": {"coordinates":[151.14276100000001,-33.903843],"type":"Point"}
}