{
  "type": "Feature",
  "properties": {
    "iso:country":"AU",
    "sg:address":"22 Gault Rd",
    "sg:city":"Belair",
    "sg:classifiers":[
        {
            "category":"Organizations",
            "subcategory":"Professional Association",
            "type":"Services"
        }
    ],
    "sg:phone":"+61 8 8357 1781",
    "sg:postcode":"5052",
    "sg:province":"SA",
    "sg:tags":[
        "web",
        "internet"
    ],
    "wof:name":"Access Japan Pty Ltd",
    "wof:placetype":"venue"
},
  "geometry": {"coordinates":[138.61702,-35.005867],"type":"Point"}
}