{
  "type": "Feature",
  "properties": {
    "addr:full":"18-20 Bank Pl Melbourne VIC 3000",
    "addr:housenumber":"18-20",
    "addr:postcode":"3000",
    "addr:street":"Bank Pl",
    "iso:country":"AU",
    "sg:address":"18-20 Bank Pl",
    "sg:city":"Melbourne",
    "sg:classifiers":[
        {
            "category":"Restaurant",
            "type":"Food & Drink"
        }
    ],
    "sg:phone":"+61 3 9600 0144",
    "sg:postcode":"3000",
    "sg:province":"VIC",
    "wof:name":"Curry Vault Indian Restaurant & Bar",
    "wof:placetype":"venue"
},
  "geometry": {"coordinates":[144.96052551299999,-37.8164863586],"type":"Point"}
}