{
  "type": "Feature",
  "properties": {
    "addr:full":"19 Turner St Mollymook NSW 2539",
    "addr:housenumber":"19",
    "addr:postcode":"2539",
    "addr:street":"Turner St",
    "iso:country":"AU",
    "sg:address":"19 Turner St",
    "sg:city":"Mollymook",
    "sg:classifiers":[
        {
            "category":"Building & Trades",
            "subcategory":"Construction",
            "type":"Services"
        }
    ],
    "sg:phone":"+61 2 4455 5069",
    "sg:postcode":"2539",
    "sg:province":"NSW",
    "sg:tags":[
        "home",
        "air conditioning"
    ],
    "wof:name":"Brians Refrigeration & Air Conditioning",
    "wof:placetype":"venue"
},
  "geometry": {"coordinates":[150.46754455600001,-35.3400382996],"type":"Point"}
}