{
  "type": "Feature",
  "properties": {
    "iso:country":"AU",
    "sg:address":"Platinum Medical Centre Cnr Gympie Rd & Banfield S",
    "sg:city":"Chermside",
    "sg:classifiers":[
        {
            "category":"Health Services",
            "subcategory":"Doctor",
            "type":"Services"
        }
    ],
    "sg:phone":"+61 1300 763 366",
    "sg:postcode":"4032",
    "sg:province":"QLD",
    "sg:tags":[
        "podiatrist"
    ],
    "wof:name":"Advance Foot Clinic",
    "wof:placetype":"venue"
},
  "geometry": {"coordinates":[153.031113,-27.386387],"type":"Point"}
}