{
  "type": "Feature",
  "properties": {
    "addr:full":"19 Endiandra St Algester QLD 4115",
    "addr:housenumber":"19",
    "addr:postcode":"4115",
    "addr:street":"Endiandra St",
    "iso:country":"AU",
    "sg:address":"19 Endiandra St",
    "sg:city":"Algester",
    "sg:classifiers":[
        {
            "category":"Education",
            "subcategory":"School",
            "type":"Public Place"
        }
    ],
    "sg:phone":"+61 7 3712 5111",
    "sg:postcode":"4115",
    "sg:province":"QLD",
    "sg:tags":[
        "state",
        "except",
        "nsw"
    ],
    "wof:name":"Algester Primary",
    "wof:placetype":"venue"
},
  "geometry": {"coordinates":[153.03437805199999,-27.6177139282],"type":"Point"}
}