{
  "type": "Feature",
  "properties": {
    "iso:country":"AU",
    "sg:address":"PO Box 81",
    "sg:city":"Northgate",
    "sg:classifiers":[
        {
            "category":"Utilities",
            "subcategory":"Electric",
            "type":"Services"
        }
    ],
    "sg:phone":"+61 418 886 362",
    "sg:postcode":"4013",
    "sg:province":"QLD",
    "sg:tags":[
        "electrical",
        "contractor"
    ],
    "wof:name":"A J R Electrical (Qld) Pty Ltd",
    "wof:placetype":"venue"
},
  "geometry": {"coordinates":[153.07354736299999,-27.3899993896],"type":"Point"}
}