{
  "type": "Feature",
  "properties": {
    "addr:full":"280 Pulteney St Adelaide SA 5000",
    "addr:housenumber":"280",
    "addr:postcode":"5000",
    "addr:street":"Pulteney St",
    "iso:country":"AU",
    "sg:address":"280 Pulteney St",
    "sg:city":"Adelaide",
    "sg:classifiers":[
        {
            "category":"Professional",
            "subcategory":"Accounting & Tax Preparation",
            "type":"Services"
        }
    ],
    "sg:phone":"+61 1300 737 373",
    "sg:postcode":"5000",
    "sg:province":"SA",
    "sg:tags":[
        "accountant",
        "auditor"
    ],
    "wof:name":"CPA Australia",
    "wof:placetype":"venue"
},
  "geometry": {"coordinates":[138.606155395,-34.928527832],"type":"Point"}
}