{
  "type": "Feature",
  "properties": {
    "addr:full":"Lot 5 Belford Pl Cardiff NSW 2285",
    "addr:housenumber":"5",
    "addr:postcode":"2285",
    "addr:street":"Belford Pl",
    "iso:country":"AU",
    "sg:address":"Lot 5 Belford Pl",
    "sg:city":"Cardiff",
    "sg:classifiers":[
        {
            "category":"Retail",
            "subcategory":"Storage",
            "type":"Services"
        }
    ],
    "sg:phone":"+61 2 4954 8344",
    "sg:postcode":"2285",
    "sg:province":"NSW",
    "sg:tags":[
        "removal",
        "furniture"
    ],
    "wof:name":"Allied Pickfords",
    "wof:placetype":"venue"
},
  "geometry": {"coordinates":[151.64373779300001,-32.9410324097],"type":"Point"}
}