{
  "type": "Feature",
  "properties": {
    "addr:full":"1a Bridge St Gawler SA 5118",
    "addr:housenumber":"1a",
    "addr:postcode":"5118",
    "addr:street":"Bridge St",
    "iso:country":"AU",
    "sg:address":"1a Bridge St",
    "sg:city":"Gawler",
    "sg:classifiers":[
        {
            "category":"Personal",
            "subcategory":"Massage",
            "type":"Services"
        }
    ],
    "sg:phone":"+61 8 8523 4233",
    "sg:postcode":"5118",
    "sg:province":"SA",
    "sg:tags":[
        "therapy"
    ],
    "wof:name":"Denise's House of Inspiring Beauty",
    "wof:placetype":"venue"
},
  "geometry": {"coordinates":[138.74795499999999,-34.593601],"type":"Point"}
}