{
  "type": "Feature",
  "properties": {
    "addr:full":"PO Box 586 Launceston TAS 7250",
    "addr:postcode":"7250",
    "iso:country":"AU",
    "sg:address":"PO Box 586",
    "sg:city":"Launceston",
    "sg:classifiers":[
        {
            "category":"Building & Trades",
            "subcategory":"Plumbing",
            "type":"Services"
        }
    ],
    "sg:phone":"+61 3 6344 9751",
    "sg:postcode":"7250",
    "sg:province":"TAS",
    "sg:tags":[
        "plumber",
        "gasfitters"
    ],
    "wof:name":"Andrew Foley Plumbing Pty Ltd",
    "wof:placetype":"venue"
},
  "geometry": {"coordinates":[147.138504028,-41.4452018738],"type":"Point"}
}