{
  "type": "Feature",
  "properties": {
    "iso:country":"AU",
    "sg:address":"28 Leysdown Ave",
    "sg:city":"North Rocks",
    "sg:classifiers":[
        {
            "category":"Personal",
            "subcategory":"Massage",
            "type":"Services"
        }
    ],
    "sg:phone":"+61 2 9871 8395",
    "sg:postcode":"2151",
    "sg:province":"NSW",
    "sg:tags":[
        "therapy"
    ],
    "wof:name":"Remedial & Lymphatic Drainage Massage Centre",
    "wof:placetype":"venue"
},
  "geometry": {"coordinates":[151.03135681099999,-33.7709541321],"type":"Point"}
}