{
  "type": "Feature",
  "properties": {
    "addr:full":"Level 6, 10 William St Perth WA 6000",
    "addr:housenumber":"10",
    "addr:postcode":"6000",
    "addr:street":"William St",
    "iso:country":"AU",
    "sg:address":"Level 6, 10 William St",
    "sg:city":"Perth",
    "sg:classifiers":[
        {
            "category":"Professional",
            "subcategory":"Computer Services",
            "type":"Services"
        }
    ],
    "sg:phone":"+61 8 9338 3000",
    "sg:postcode":"6000",
    "sg:province":"WA",
    "sg:tags":[
        "package",
        "software"
    ],
    "wof:name":"Harvestroad Ltd",
    "wof:placetype":"venue"
},
  "geometry": {"coordinates":[115.856330872,-31.9554157257],"type":"Point"}
}