{
  "type": "Feature",
  "properties": {
    "addr:full":"10 Moresby St Kensington WA 6151",
    "addr:housenumber":"10",
    "addr:postcode":"6151",
    "addr:street":"Moresby St",
    "iso:country":"AU",
    "sg:address":"10 Moresby St",
    "sg:city":"Kensington",
    "sg:classifiers":[
        {
            "category":"Personal",
            "subcategory":"Beauty Salon",
            "type":"Services"
        }
    ],
    "sg:phone":"+61 8 9367 1971",
    "sg:postcode":"6151",
    "sg:province":"WA",
    "sg:tags":[
        "hairdresser"
    ],
    "wof:name":"This.above.all",
    "wof:placetype":"venue"
},
  "geometry": {"coordinates":[115.879921,-31.987946],"type":"Point"}
}