{
  "type": "Feature",
  "properties": {
    "addr:full":"295 Commercial St West Mt Gambier SA 5290",
    "addr:housenumber":"295",
    "addr:postcode":"5290",
    "addr:street":"Commercial St West",
    "iso:country":"AU",
    "sg:address":"295 Commercial St West",
    "sg:city":"Mt Gambier",
    "sg:classifiers":[
        {
            "category":"Manufacturing",
            "subcategory":"Rubber & Plastics",
            "type":"Manufacturing & Wholesale Goods"
        }
    ],
    "sg:phone":"+61 8 8725 5333",
    "sg:postcode":"5290",
    "sg:province":"SA",
    "sg:tags":[
        "lime"
    ],
    "wof:name":"Mount Gambier Limestone",
    "wof:placetype":"venue"
},
  "geometry": {"coordinates":[140.761887,-37.822392],"type":"Point"}
}