{
  "type": "Feature",
  "properties": {
    "addr:full":"Shop 30 Mudgeeraba Market Shopng Cntr Mudgeeraba QLD 4213",
    "addr:housenumber":"shop 30",
    "addr:postcode":"4213",
    "iso:country":"AU",
    "sg:address":"Shop 30 Mudgeeraba Market Shopng Cntr",
    "sg:city":"Mudgeeraba",
    "sg:classifiers":[
        {
            "category":"Fast Food",
            "type":"Food & Drink"
        }
    ],
    "sg:phone":"+61 7 5530 7366",
    "sg:postcode":"4213",
    "sg:province":"QLD",
    "sg:tags":[
        "away",
        "take"
    ],
    "wof:name":"Fresh Coral Seafoods",
    "wof:placetype":"venue"
},
  "geometry": {"coordinates":[153.35528564399999,-28.0535163879],"type":"Point"}
}