{
  "type": "Feature",
  "properties": {
    "iso:country":"AU",
    "sg:address":"41 Oakover St",
    "sg:city":"East Fremantle",
    "sg:classifiers":[
        {
            "category":"Building & Trades",
            "subcategory":"Cleaning & Sanitation",
            "type":"Services"
        }
    ],
    "sg:phone":"+61 8 9438 3801",
    "sg:postcode":"6158",
    "sg:province":"WA",
    "sg:tags":[
        "duct"
    ],
    "wof:name":"Indoor Air Quality WA Pty Ltd",
    "wof:placetype":"venue"
},
  "geometry": {"coordinates":[115.774841,-32.042953],"type":"Point"}
}