{
  "type": "Feature",
  "properties": {
    "addr:full":"PO Box 3021 Broadmeadows VIC 3047",
    "addr:postcode":"3047",
    "iso:country":"AU",
    "sg:address":"PO Box 3021",
    "sg:city":"Broadmeadows",
    "sg:classifiers":[
        {
            "category":"Arts & Performance",
            "subcategory":"Music",
            "type":"Entertainment"
        }
    ],
    "sg:phone":"+61 425 857 928",
    "sg:postcode":"3047",
    "sg:province":"VIC",
    "sg:tags":[
        "mobile",
        "jockey",
        "disc"
    ],
    "wof:name":"DJ Mr-G",
    "wof:placetype":"venue"
},
  "geometry": {"coordinates":[144.926345825,-37.6860694885],"type":"Point"}
}