{
  "type": "Feature",
  "properties": {
    "addr:full":"133 Sharp St Cooma NSW 2630",
    "addr:housenumber":"133",
    "addr:postcode":"2630",
    "addr:street":"Sharp St",
    "iso:country":"AU",
    "sg:address":"133 Sharp St",
    "sg:city":"Cooma",
    "sg:classifiers":[
        {
            "category":"Shopping",
            "subcategory":"Clothing, Apparel, & Fashions",
            "type":"Retail Goods"
        }
    ],
    "sg:phone":"+61 2 6452 2146",
    "sg:postcode":"2630",
    "sg:province":"NSW",
    "sg:tags":[
        "lingerie",
        "hosiery",
        "sleepwear"
    ],
    "wof:name":"Taffas",
    "wof:placetype":"venue"
},
  "geometry": {"coordinates":[149.13409423799999,-36.2312316895],"type":"Point"}
}