{
  "type": "Feature",
  "properties": {
    "iso:country":"AU",
    "sg:address":"1 Royston Pde",
    "sg:city":"Asquith",
    "sg:classifiers":[
        {
            "category":"Education",
            "subcategory":"School",
            "type":"Public Place"
        }
    ],
    "sg:phone":"+61 2 9477 3800",
    "sg:postcode":"2077",
    "sg:province":"NSW",
    "sg:tags":[
        "co-educational"
    ],
    "wof:name":"St Patrick's School",
    "wof:placetype":"venue"
},
  "geometry": {"coordinates":[151.10960388199999,-33.6879882812],"type":"Point"}
}