{
  "type": "Feature",
  "properties": {
    "addr:full":"Shp 4/ 418 Payneham Rd Glynde SA 5070",
    "addr:housenumber":"/ 418",
    "addr:postcode":"5070",
    "addr:street":"Payneham Rd",
    "iso:country":"AU",
    "sg:address":"Shp 4/ 418 Payneham Rd",
    "sg:city":"Glynde",
    "sg:classifiers":[
        {
            "category":"Fast Food",
            "type":"Food & Drink"
        }
    ],
    "sg:phone":"+61 8 8336 8311",
    "sg:postcode":"5070",
    "sg:province":"SA",
    "sg:tags":[
        "away",
        "take"
    ],
    "wof:name":"Dianas Chips & Fish",
    "wof:placetype":"venue"
},
  "geometry": {"coordinates":[138.648895264,-34.8926124573],"type":"Point"}
}