{
  "type": "Feature",
  "properties": {
    "addr:full":"7 Kintore St Camberwell VIC 3124",
    "addr:housenumber":"7",
    "addr:postcode":"3124",
    "addr:street":"Kintore St",
    "iso:country":"AU",
    "sg:address":"7 Kintore St",
    "sg:city":"Camberwell",
    "sg:classifiers":[
        {
            "category":"Social Services",
            "type":"Services"
        }
    ],
    "sg:phone":"+61 1300 301 828",
    "sg:postcode":"3124",
    "sg:province":"VIC",
    "sg:tags":[
        "domestic",
        "help"
    ],
    "wof:name":"Professional Home Sitters",
    "wof:placetype":"venue"
},
  "geometry": {"coordinates":[145.059494019,-37.8224372864],"type":"Point"}
}