{
  "type": "Feature",
  "properties": {
    "addr:full":"122 Smith St Cleveland QLD 4163",
    "addr:housenumber":"122",
    "addr:postcode":"4163",
    "addr:street":"Smith St",
    "iso:country":"AU",
    "sg:address":"122 Smith St",
    "sg:city":"Cleveland",
    "sg:phone":"+61 411 888 229",
    "sg:postcode":"4163",
    "sg:province":"QLD",
    "wof:name":"Phil Mack Plumbing Pty Ltd",
    "wof:placetype":"venue"
},
  "geometry": {"coordinates":[153.25920105,-27.5404281616],"type":"Point"}
}