{
  "type": "Feature",
  "properties": {
    "iso:country":"AU",
    "sg:address":"294- 298 Cormack Rd",
    "sg:city":"Wingfield",
    "sg:classifiers":[
        {
            "category":"Manufacturing",
            "subcategory":"Wood Products",
            "type":"Manufacturing & Wholesale Goods"
        }
    ],
    "sg:phone":"+61 8 8349 8401",
    "sg:postcode":"5013",
    "sg:province":"SA",
    "sg:tags":[
        "pallet",
        "platform"
    ],
    "wof:name":"A.A Secondhand Pallets",
    "wof:placetype":"venue"
},
  "geometry": {"coordinates":[138.569290161,-34.840171814],"type":"Point"}
}