{
  "type": "Feature",
  "properties": {
    "addr:full":"47 Church St Benalla VIC 3672",
    "addr:housenumber":"47",
    "addr:postcode":"3672",
    "addr:street":"Church St",
    "iso:country":"AU",
    "sg:address":"47 Church St",
    "sg:city":"Benalla",
    "sg:classifiers":[
        {
            "category":"Personal",
            "subcategory":"Massage",
            "type":"Services"
        }
    ],
    "sg:phone":"+61 3 5762 8057",
    "sg:postcode":"3672",
    "sg:province":"VIC",
    "sg:tags":[
        "therapy"
    ],
    "wof:name":"Day Dreaming Massage",
    "wof:placetype":"venue"
},
  "geometry": {"coordinates":[145.98599200000001,-36.548851],"type":"Point"}
}