{
  "type": "Feature",
  "properties": {
    "iso:country":"AU",
    "sg:address":"6 Roper Rd",
    "sg:city":"Blue Haven",
    "sg:classifiers":[
        {
            "category":"Social Services",
            "subcategory":"Child Care",
            "type":"Services"
        }
    ],
    "sg:phone":"+61 2 4399 3499",
    "sg:postcode":"2262",
    "sg:province":"NSW",
    "wof:name":"Blue Haven Jelli-Beanz Kindergarten",
    "wof:placetype":"venue"
},
  "geometry": {"coordinates":[151.49675,-33.207058],"type":"Point"}
}