{
  "type": "Feature",
  "properties": {
    "iso:country":"AU",
    "sg:address":"370 Main Rd West St",
    "sg:city":"Albans",
    "sg:classifiers":[
        {
            "category":"Health Services",
            "subcategory":"Doctor",
            "type":"Services"
        }
    ],
    "sg:phone":"+61 3 9366 4554",
    "sg:postcode":"3021",
    "sg:province":"VIC",
    "sg:tags":[
        "medical",
        "practitioner"
    ],
    "wof:name":"Lui Gabriel P K Dr",
    "wof:placetype":"venue"
},
  "geometry": {"coordinates":[144.76904300000001,-37.740852],"type":"Point"}
}