{
  "type": "Feature",
  "properties": {
    "iso:country":"AU",
    "sg:address":"347 Great Western Hwy",
    "sg:city":"Wentworthville",
    "sg:classifiers":[
        {
            "category":"Retail",
            "subcategory":"Auto Rental",
            "type":"Services"
        }
    ],
    "sg:phone":"+61 2 9896 4122",
    "sg:postcode":"2145",
    "sg:province":"NSW",
    "sg:tags":[
        "car",
        "hire",
        "minibus"
    ],
    "wof:name":"Wenty Rentals",
    "wof:placetype":"venue"
},
  "geometry": {"coordinates":[150.968826294,-33.8156661987],"type":"Point"}
}