{
  "type": "Feature",
  "properties": {
    "iso:country":"AU",
    "sg:address":"148 Lower Mountain Rd",
    "sg:city":"Dundowran",
    "sg:classifiers":[
        {
            "category":"Retail",
            "subcategory":"Storage",
            "type":"Services"
        }
    ],
    "sg:phone":"+61 1800 777 652",
    "sg:postcode":"4655",
    "sg:province":"QLD",
    "wof:name":"Davis Removals & Storage",
    "wof:placetype":"venue"
},
  "geometry": {"coordinates":[152.800262,-25.29928],"type":"Point"}
}