{
  "type": "Feature",
  "properties": {
    "addr:full":"237 River St Maclean NSW 2463",
    "addr:housenumber":"237",
    "addr:postcode":"2463",
    "addr:street":"River St",
    "iso:country":"AU",
    "sg:address":"237 River St",
    "sg:city":"Maclean",
    "sg:classifiers":[
        {
            "category":"Retail",
            "subcategory":"Repair Shop",
            "type":"Services"
        }
    ],
    "sg:phone":"+61 2 6645 1480",
    "sg:postcode":"2463",
    "sg:province":"NSW",
    "sg:tags":[
        "machine",
        "sewing"
    ],
    "wof:name":"Sew Excited",
    "wof:placetype":"venue"
},
  "geometry": {"coordinates":[153.19674682600001,-29.4574642181],"type":"Point"}
}