{
  "type": "Feature",
  "properties": {
    "iso:country":"AU",
    "sg:address":"127 Yulara Drv",
    "sg:city":"Yulara",
    "sg:classifiers":[
        {
            "category":"Airport",
            "subcategory":"General Aviation",
            "type":"Transportation"
        }
    ],
    "sg:phone":"+61 8 8956 2730",
    "sg:postcode":"0872",
    "sg:province":"NT",
    "sg:tags":[
        "helicopter"
    ],
    "wof:name":"Helicopter Group Pty Ltd The",
    "wof:placetype":"venue"
},
  "geometry": {"coordinates":[130.984573364,-25.2412128448],"type":"Point"}
}