{
  "type": "Feature",
  "properties": {
    "addr:full":"42 Urquhart St Woodend VIC 3442",
    "addr:housenumber":"42",
    "addr:postcode":"3442",
    "addr:street":"Urquhart St",
    "iso:country":"AU",
    "sg:address":"42 Urquhart St",
    "sg:city":"Woodend",
    "sg:classifiers":[
        {
            "category":"Manufacturing",
            "subcategory":"Signs",
            "type":"Manufacturing & Wholesale Goods"
        }
    ],
    "sg:phone":"+61 3 5427 1616",
    "sg:postcode":"3442",
    "sg:province":"VIC",
    "sg:tags":[
        "traffic",
        "safety"
    ],
    "wof:name":"Macedon Ranges Signs",
    "wof:placetype":"venue"
},
  "geometry": {"coordinates":[144.52915954599999,-37.3583145142],"type":"Point"}
}