{
  "type": "Feature",
  "properties": {
    "addr:full":"2 Glendale Crt Werribee VIC 3030",
    "addr:housenumber":"2",
    "addr:postcode":"3030",
    "addr:street":"Glendale Crt",
    "iso:country":"AU",
    "sg:address":"2 Glendale Crt",
    "sg:city":"Werribee",
    "sg:classifiers":[
        {
            "category":"Health Services",
            "subcategory":"Nursing And Care Facility",
            "type":"Services"
        }
    ],
    "sg:phone":"+61 3 9749 9916",
    "sg:postcode":"3030",
    "sg:province":"VIC",
    "sg:tags":[
        "home"
    ],
    "wof:name":"Glendale High Care Unit",
    "wof:placetype":"venue"
},
  "geometry": {"coordinates":[144.67892499999999,-37.877663],"type":"Point"}
}