{
  "type": "Feature",
  "properties": {
    "iso:country":"AU",
    "sg:address":"37B Northgate Drv",
    "sg:city":"Thomastown",
    "sg:classifiers":[
        {
            "category":"Retail",
            "subcategory":"Auto Repair",
            "type":"Services"
        }
    ],
    "sg:phone":"+61 3 9466 1164",
    "sg:postcode":"3074",
    "sg:province":"VIC",
    "sg:tags":[
        "body",
        "motor",
        "trimmer"
    ],
    "wof:name":"Just Tonneaus",
    "wof:placetype":"venue"
},
  "geometry": {"coordinates":[145.03956604000001,-37.6911773682],"type":"Point"}
}