{
  "type": "Feature",
  "properties": {
    "addr:full":"24 Brooker Drv Goonellabah NSW 2480",
    "addr:housenumber":"24",
    "addr:postcode":"2480",
    "addr:street":"Brooker Drv",
    "iso:country":"AU",
    "sg:address":"24 Brooker Drv",
    "sg:city":"Goonellabah",
    "sg:classifiers":[
        {
            "category":"Building & Trades",
            "subcategory":"Construction",
            "type":"Services"
        }
    ],
    "sg:phone":"+61 427 246 612",
    "sg:postcode":"2480",
    "sg:province":"NSW",
    "sg:tags":[
        "bitumen",
        "paving",
        "asphalt"
    ],
    "wof:name":"Clark Asphalt",
    "wof:placetype":"venue"
},
  "geometry": {"coordinates":[153.308425903,-28.8297939301],"type":"Point"}
}