{
  "type": "Feature",
  "properties": {
    "addr:full":"310 Station St Chelsea VIC 3196",
    "addr:housenumber":"310",
    "addr:postcode":"3196",
    "addr:street":"Station St",
    "iso:country":"AU",
    "sg:address":"310 Station St",
    "sg:city":"Chelsea",
    "sg:classifiers":[
        {
            "category":"Fast Food",
            "type":"Food & Drink"
        }
    ],
    "sg:phone":"+61 3 9773 2122",
    "sg:postcode":"3196",
    "sg:province":"VIC",
    "sg:tags":[
        "away",
        "take"
    ],
    "wof:name":"Chelsea Pizza",
    "wof:placetype":"venue"
},
  "geometry": {"coordinates":[145.11570739699999,-38.0503692627],"type":"Point"}
}