{
  "type": "Feature",
  "properties": {
    "iso:country":"AU",
    "sg:address":"315 Clovelly Rd",
    "sg:city":"Clovelly",
    "sg:classifiers":[
        {
            "category":"Personal",
            "subcategory":"Beauty Salon",
            "type":"Services"
        }
    ],
    "sg:phone":"+61 2 9664 1336",
    "sg:postcode":"2031",
    "sg:province":"NSW",
    "sg:tags":[
        "hairdresser"
    ],
    "wof:name":"Hair Bloom",
    "wof:placetype":"venue"
},
  "geometry": {"coordinates":[151.26368713400001,-33.9129943848],"type":"Point"}
}