{
  "type": "Feature",
  "properties": {
    "addr:full":"Unit 4/ 25 Roxburgh Ave Lonsdale SA 5160",
    "addr:housenumber":"25",
    "addr:postcode":"5160",
    "addr:street":"Roxburgh Ave",
    "iso:country":"AU",
    "sg:address":"Unit 4/ 25 Roxburgh Ave",
    "sg:city":"Lonsdale",
    "sg:classifiers":[
        {
            "category":"Professional",
            "type":"Services"
        }
    ],
    "sg:phone":"+61 8 8186 2332",
    "sg:postcode":"5160",
    "sg:province":"SA",
    "sg:tags":[
        "overlocking",
        "rug",
        "carpet"
    ],
    "wof:name":"Sew All",
    "wof:placetype":"venue"
},
  "geometry": {"coordinates":[138.499267578,-35.1187057495],"type":"Point"}
}