{
  "type": "Feature",
  "properties": {
    "addr:full":"12 Champion St Doncaster East VIC 3109",
    "addr:housenumber":"12",
    "addr:postcode":"3109",
    "addr:street":"Champion St",
    "iso:country":"AU",
    "sg:address":"12 Champion St",
    "sg:city":"Doncaster East",
    "sg:classifiers":[
        {
            "category":"Building & Trades",
            "subcategory":"Construction",
            "type":"Services"
        }
    ],
    "sg:phone":"+61 407 849 097",
    "sg:postcode":"3109",
    "sg:province":"VIC",
    "sg:tags":[
        "mural"
    ],
    "wof:name":"Martins Murals",
    "wof:placetype":"venue"
},
  "geometry": {"coordinates":[145.14991760300001,-37.7868537903],"type":"Point"}
}