{
  "type": "Feature",
  "properties": {
    "addr:full":"43 Westland Drv Ballina NSW 2478",
    "addr:housenumber":"43",
    "addr:postcode":"2478",
    "addr:street":"Westland Drv",
    "iso:country":"AU",
    "sg:address":"43 Westland Drv",
    "sg:city":"Ballina",
    "sg:classifiers":[
        {
            "category":"Building & Trades",
            "subcategory":"Construction",
            "type":"Services"
        }
    ],
    "sg:phone":"+61 2 6681 1115",
    "sg:postcode":"2478",
    "sg:province":"NSW",
    "sg:tags":[
        "earth",
        "excavating",
        "moving",
        "contractor"
    ],
    "wof:name":"Besseling Nick",
    "wof:placetype":"venue"
},
  "geometry": {"coordinates":[153.53642273,-28.860250473],"type":"Point"}
}