{
  "type": "Feature",
  "properties": {
    "addr:full":"49 Church St Abbotsford VIC 3067",
    "addr:housenumber":"49",
    "addr:postcode":"3067",
    "addr:street":"Church St",
    "iso:country":"AU",
    "sg:address":"49 Church St",
    "sg:city":"Abbotsford",
    "sg:classifiers":[
        {
            "category":"Retail",
            "subcategory":"Auto Repair",
            "type":"Services"
        }
    ],
    "sg:phone":"+61 3 9428 8189",
    "sg:postcode":"3067",
    "sg:province":"VIC",
    "sg:tags":[
        "beater",
        "painter",
        "panel"
    ],
    "wof:name":"Pro Car Collision Repair Centre",
    "wof:placetype":"venue"
},
  "geometry": {"coordinates":[145.00083923299999,-37.808380127],"type":"Point"}
}