{
  "type": "Feature",
  "properties": {
    "addr:full":"31 Forster St Invermay TAS 7248",
    "addr:housenumber":"31",
    "addr:postcode":"7248",
    "addr:street":"Forster St",
    "iso:country":"AU",
    "sg:address":"31 Forster St",
    "sg:city":"Invermay",
    "sg:classifiers":[
        {
            "category":"Autos & Motor Vehicles",
            "subcategory":"Auto Supplies",
            "type":"Retail Goods"
        }
    ],
    "sg:phone":"+61 3 6331 2028",
    "sg:postcode":"7248",
    "sg:province":"TAS",
    "sg:tags":[
        "tyre"
    ],
    "wof:name":"Discount Tyres Tasmania",
    "wof:placetype":"venue"
},
  "geometry": {"coordinates":[147.13815307600001,-41.4234046936],"type":"Point"}
}