{
  "type": "Feature",
  "properties": {
    "iso:country":"AU",
    "sg:address":"401 Great Eastern Hwy",
    "sg:city":"Midland",
    "sg:classifiers":[
        {
            "category":"Home & Garden",
            "subcategory":"Furniture",
            "type":"Retail Goods"
        }
    ],
    "sg:phone":"+61 8 9250 2755",
    "sg:postcode":"6056",
    "sg:province":"WA",
    "sg:tags":[
        "business"
    ],
    "wof:name":"Furniture Spot",
    "wof:placetype":"venue"
},
  "geometry": {"coordinates":[116.012870789,-31.8918819427],"type":"Point"}
}