{
  "type": "Feature",
  "properties": {
    "iso:country":"AU",
    "sg:address":"Unit 4/5- 13 Comley St",
    "sg:city":"Sunshine North",
    "sg:classifiers":[
        {
            "category":"Professional",
            "subcategory":"Detective & Security Services",
            "type":"Services"
        }
    ],
    "sg:phone":"+61 3 9311 7322",
    "sg:postcode":"3020",
    "sg:province":"VIC",
    "sg:tags":[
        "equipment",
        "window",
        "doors"
    ],
    "wof:name":"M.I Security Systems",
    "wof:placetype":"venue"
},
  "geometry": {"coordinates":[144.828888,-37.767456],"type":"Point"}
}