{
  "type": "Feature",
  "properties": {
    "iso:country":"AU",
    "sg:address":"6 Maxwell Pl",
    "sg:city":"West Launceston",
    "sg:classifiers":[
        {
            "category":"Structure",
            "subcategory":"Office Building",
            "type":"Public Place"
        }
    ],
    "sg:phone":"+61 3 6334 3497",
    "sg:postcode":"7250",
    "sg:province":"TAS",
    "sg:tags":[
        "slater",
        "tiler",
        "roof"
    ],
    "wof:name":"Damien Walsh",
    "wof:placetype":"venue"
},
  "geometry": {"coordinates":[147.12889099099999,-41.4613037109],"type":"Point"}
}