{
  "type": "Feature",
  "properties": {
    "addr:full":"Cnr Birkdale Rd & Agnes St Birkdale QLD 4159",
    "addr:postcode":"4159",
    "addr:street":"Cnr Birkdale Rd & Agnes St",
    "iso:country":"AU",
    "sg:address":"Cnr Birkdale Rd & Agnes St",
    "sg:city":"Birkdale",
    "sg:classifiers":[
        {
            "category":"Food & Beverages",
            "subcategory":"Supermarket",
            "type":"Retail Goods"
        }
    ],
    "sg:phone":"+61 7 3207 2111",
    "sg:postcode":"4159",
    "sg:province":"QLD",
    "sg:tags":[
        "grocery",
        "store"
    ],
    "wof:name":"Buy-Rite Fresh Foodmarket",
    "wof:placetype":"venue"
},
  "geometry": {"coordinates":[153.208618164,-27.5049152374],"type":"Point"}
}