{
  "type": "Feature",
  "properties": {
    "addr:full":"RMB 1641 Lima South VIC 3673",
    "addr:postcode":"3673",
    "iso:country":"AU",
    "sg:address":"RMB 1641",
    "sg:city":"Lima South",
    "sg:classifiers":[
        {
            "category":"Bars & Pubs",
            "subcategory":"Biergarten",
            "type":"Food & Drink"
        }
    ],
    "sg:phone":"+61 3 5768 2347",
    "sg:postcode":"3673",
    "sg:province":"VIC",
    "sg:tags":[
        "eucalyptus",
        "oil",
        "tree",
        "essential",
        "tea"
    ],
    "wof:name":"Forest Fringe Emu Oil",
    "wof:placetype":"venue"
},
  "geometry": {"coordinates":[145.99650600000001,-36.86644],"type":"Point"}
}