{
  "type": "Feature",
  "properties": {
    "addr:full":"383 Edward St Wagga Wagga NSW 2650",
    "addr:housenumber":"383",
    "addr:postcode":"2650",
    "addr:street":"Edward St",
    "iso:country":"AU",
    "sg:address":"383 Edward St",
    "sg:city":"Wagga Wagga",
    "sg:classifiers":[
        {
            "category":"Professional",
            "subcategory":"Printing & Photocopies",
            "type":"Services"
        }
    ],
    "sg:phone":"+61 2 6925 0466",
    "sg:postcode":"2650",
    "sg:province":"NSW",
    "sg:tags":[
        "photocopying"
    ],
    "wof:name":"Sheather & Merrigan Business Equipment",
    "wof:placetype":"venue"
},
  "geometry": {"coordinates":[147.34698486299999,-35.1156196594],"type":"Point"}
}