{
  "type": "Feature",
  "properties": {
    "iso:country":"AU",
    "sg:address":"Unit 9/ 1 Masters Rd",
    "sg:city":"Coniston",
    "sg:classifiers":[
        {
            "category":"Professional",
            "type":"Services"
        }
    ],
    "sg:phone":"+61 2 4225 3363",
    "sg:postcode":"2500",
    "sg:province":"NSW",
    "sg:tags":[
        "spray",
        "painting"
    ],
    "wof:name":"Davids Accident Repair Centre",
    "wof:placetype":"venue"
},
  "geometry": {"coordinates":[150.86918600000001,-34.443649],"type":"Point"}
}