{
  "type": "Feature",
  "properties": {
    "addr:full":"2 Binns St Montmorency VIC 3094",
    "addr:housenumber":"2",
    "addr:postcode":"3094",
    "addr:street":"Binns St",
    "iso:country":"AU",
    "sg:address":"2 Binns St",
    "sg:city":"Montmorency",
    "sg:classifiers":[
        {
            "category":"Fast Food",
            "type":"Food & Drink"
        }
    ],
    "sg:phone":"+61 3 9432 5551",
    "sg:postcode":"3094",
    "sg:province":"VIC",
    "sg:tags":[
        "away",
        "take"
    ],
    "wof:name":"Monty's Noodles",
    "wof:placetype":"venue"
},
  "geometry": {"coordinates":[145.12144470199999,-37.7157516479],"type":"Point"}
}