{
  "type": "Feature",
  "properties": {
    "iso:country":"AU",
    "sg:address":"41 Goshawk Crt",
    "sg:city":"Caboolture",
    "sg:classifiers":[
        {
            "category":"Building & Trades",
            "subcategory":"Equipment Rental",
            "type":"Services"
        }
    ],
    "sg:phone":"+61 417 619 120",
    "sg:postcode":"4510",
    "sg:province":"QLD",
    "sg:tags":[
        "platform",
        "hire",
        "work",
        "elevating"
    ],
    "wof:name":"Qld Selferecting Cranes",
    "wof:placetype":"venue"
},
  "geometry": {"coordinates":[152.954559,-27.060705],"type":"Point"}
}