{
  "type": "Feature",
  "properties": {
    "iso:country":"AU",
    "sg:address":"Lampton Ave",
    "sg:city":"Derwent Park",
    "sg:classifiers":[
        {
            "category":"Professional",
            "type":"Services"
        }
    ],
    "sg:phone":"+61 419 153 299",
    "sg:postcode":"7009",
    "sg:province":"TAS",
    "sg:tags":[
        "transport"
    ],
    "wof:name":"East Coast Freight",
    "wof:placetype":"venue"
},
  "geometry": {"coordinates":[147.29690551799999,-42.8338279724],"type":"Point"}
}