{
  "type": "Feature",
  "properties": {
    "addr:full":"7 The River Rd Revesby NSW 2212",
    "addr:housenumber":"7",
    "addr:postcode":"2212",
    "addr:street":"The River Rd",
    "iso:country":"AU",
    "sg:address":"7 The River Rd",
    "sg:city":"Revesby",
    "sg:classifiers":[
        {
            "category":"Home & Garden",
            "subcategory":"Building Materials",
            "type":"Retail Goods"
        }
    ],
    "sg:phone":"+61 2 9771 0195",
    "sg:postcode":"2212",
    "sg:province":"NSW",
    "sg:tags":[
        "roofing"
    ],
    "wof:name":"Hiland Group",
    "wof:placetype":"venue"
},
  "geometry": {"coordinates":[151.01660200000001,-33.960445],"type":"Point"}
}