{
  "type": "Feature",
  "properties": {
    "addr:full":"Barry Beach Rd Welshpool VIC 3966",
    "addr:postcode":"3966",
    "addr:street":"Beach Rd",
    "iso:country":"AU",
    "sg:address":"Barry Beach Rd",
    "sg:city":"Welshpool",
    "sg:classifiers":[
        {
            "category":"Building & Trades",
            "subcategory":"Landscaping Services",
            "type":"Services"
        }
    ],
    "sg:phone":"+61 3 5688 1294",
    "sg:postcode":"3966",
    "sg:province":"VIC",
    "sg:tags":[
        "grazier"
    ],
    "wof:name":"Throckmorton A H",
    "wof:placetype":"venue"
},
  "geometry": {"coordinates":[146.39576721200001,-38.6708068848],"type":"Point"}
}