{
  "type": "Feature",
  "properties": {
    "addr:full":"Lvl1/ 261 Glenferrie Rd Malvern VIC 3144",
    "addr:housenumber":"261",
    "addr:postcode":"3144",
    "addr:street":"Glenferrie Rd",
    "iso:country":"AU",
    "sg:address":"Lvl1/ 261 Glenferrie Rd",
    "sg:city":"Malvern",
    "sg:classifiers":[
        {
            "category":"Manufacturing",
            "subcategory":"Jewelry",
            "type":"Manufacturing & Wholesale Goods"
        }
    ],
    "sg:phone":"+61 3 9509 5756",
    "sg:postcode":"3144",
    "sg:province":"VIC",
    "sg:tags":[
        "designer",
        "jewellery"
    ],
    "wof:name":"Tati17",
    "wof:placetype":"venue"
},
  "geometry": {"coordinates":[145.02896118199999,-37.8575668335],"type":"Point"}
}