{
  "type": "Feature",
  "properties": {
    "addr:full":"1809 Lytton Rd Lytton QLD 4178",
    "addr:housenumber":"1809",
    "addr:postcode":"4178",
    "addr:street":"Lytton Rd",
    "iso:country":"AU",
    "sg:address":"1809 Lytton Rd",
    "sg:city":"Lytton",
    "sg:classifiers":[
        {
            "category":"Food & Beverages",
            "subcategory":"Specialty",
            "type":"Retail Goods"
        }
    ],
    "sg:phone":"+61 7 3308 5200",
    "sg:postcode":"4178",
    "sg:province":"QLD",
    "sg:tags":[
        "solvent"
    ],
    "wof:name":"Recochem Inc",
    "wof:placetype":"venue"
},
  "geometry": {"coordinates":[153.14596557600001,-27.4245891571],"type":"Point"}
}