{
  "type": "Feature",
  "properties": {
    "addr:full":"47A Roberts Ave (Via Ward St) Horsham VIC 3400",
    "addr:housenumber":"47a",
    "addr:postcode":"3400",
    "addr:street":"Roberts Ave Via Ward St",
    "iso:country":"AU",
    "sg:address":"47A Roberts Ave",
    "sg:city":"(Via Ward St) Horsham",
    "sg:classifiers":[
        {
            "category":"Banks & Credit Unions",
            "subcategory":"Bank",
            "type":"Services"
        }
    ],
    "sg:phone":"+61 3 5382 7333",
    "sg:postcode":"3400",
    "sg:province":"VIC",
    "wof:name":"Rabobank",
    "wof:placetype":"venue"
},
  "geometry": {"coordinates":[142.198120117,-36.7144126892],"type":"Point"}
}