{
  "type": "Feature",
  "properties": {
    "addr:full":"37 Plateau Rd Reservoir VIC 3073",
    "addr:housenumber":"37",
    "addr:postcode":"3073",
    "addr:street":"Plateau Rd",
    "iso:country":"AU",
    "sg:address":"37 Plateau Rd",
    "sg:city":"Reservoir",
    "sg:classifiers":[
        {
            "category":"Wholesale",
            "subcategory":"Furniture",
            "type":"Manufacturing & Wholesale Goods"
        }
    ],
    "sg:phone":"+61 3 9460 3144",
    "sg:postcode":"3073",
    "sg:province":"VIC",
    "sg:tags":[
        "wholesaler",
        "mfrs"
    ],
    "wof:name":"Alfa Furniture",
    "wof:placetype":"venue"
},
  "geometry": {"coordinates":[144.98614501899999,-37.7098121643],"type":"Point"}
}