{
  "type": "Feature",
  "properties": {
    "addr:full":"3 Grumman Pl Raby NSW 2566",
    "addr:housenumber":"3",
    "addr:postcode":"2566",
    "addr:street":"Grumman Pl Raby",
    "iso:country":"AU",
    "sg:address":"3 Grumman Pl",
    "sg:city":"Raby",
    "sg:classifiers":[
        {
            "category":"Utilities",
            "subcategory":"Electric",
            "type":"Services"
        }
    ],
    "sg:phone":"+61 2 9820 8381",
    "sg:postcode":"2566",
    "sg:province":"NSW",
    "sg:tags":[
        "electrical",
        "contractor"
    ],
    "wof:name":"Graeme Oyston Electrical",
    "wof:placetype":"venue"
},
  "geometry": {"coordinates":[150.81098938,-34.0197219849],"type":"Point"}
}