{
  "type": "Feature",
  "properties": {
    "addr:full":"12 High St Kyneton VIC 3444",
    "addr:housenumber":"12",
    "addr:postcode":"3444",
    "addr:street":"High St",
    "iso:country":"AU",
    "sg:address":"12 High St",
    "sg:city":"Kyneton",
    "sg:classifiers":[
        {
            "category":"Professional",
            "subcategory":"Employment Agencies",
            "type":"Services"
        }
    ],
    "sg:phone":"+61 3 5422 6422",
    "sg:postcode":"3444",
    "sg:province":"VIC",
    "wof:name":"CVGT Employment & Training Specialists",
    "wof:placetype":"venue"
},
  "geometry": {"coordinates":[144.453857422,-37.2495574951],"type":"Point"}
}