{
  "type": "Feature",
  "properties": {
    "addr:full":"82 High St Yea VIC 3717",
    "addr:housenumber":"82",
    "addr:postcode":"3717",
    "addr:street":"High St",
    "iso:country":"AU",
    "sg:address":"82 High St",
    "sg:city":"Yea",
    "sg:classifiers":[
        {
            "category":"Real Estate",
            "subcategory":"Surveying",
            "type":"Services"
        }
    ],
    "sg:phone":"+61 3 5797 2056",
    "sg:postcode":"3717",
    "sg:province":"VIC",
    "sg:tags":[
        "surveyor",
        "land"
    ],
    "wof:name":"Rodney Aujard & Associates",
    "wof:placetype":"venue"
},
  "geometry": {"coordinates":[145.42251586899999,-37.211566925],"type":"Point"}
}