{
  "type": "Feature",
  "properties": {
    "addr:full":"30 Station St Wentworthville NSW 2145",
    "addr:housenumber":"30",
    "addr:postcode":"2145",
    "addr:street":"Station St",
    "iso:country":"AU",
    "sg:address":"30 Station St",
    "sg:city":"Wentworthville",
    "sg:classifiers":[
        {
            "category":"Real Estate",
            "subcategory":"Real Estate Agent",
            "type":"Services"
        }
    ],
    "sg:phone":"+61 2 9688 4000",
    "sg:postcode":"2145",
    "sg:province":"NSW",
    "wof:name":"Laing + Simmons Wentworthville",
    "wof:placetype":"venue"
},
  "geometry": {"coordinates":[150.97222900400001,-33.8081359863],"type":"Point"}
}