{
  "type": "Feature",
  "properties": {
    "addr:full":"Clorane St Aspley QLD 4034",
    "addr:postcode":"4034",
    "addr:street":"St",
    "iso:country":"AU",
    "sg:address":"Clorane St",
    "sg:city":"Aspley",
    "sg:classifiers":[
        {
            "category":"Education",
            "subcategory":"School",
            "type":"Public Place"
        }
    ],
    "sg:phone":"+61 7 3263 2528",
    "sg:postcode":"4034",
    "sg:province":"QLD",
    "sg:tags":[
        "state",
        "except",
        "nsw"
    ],
    "wof:name":"Aspley East Preschool",
    "wof:placetype":"venue"
},
  "geometry": {"coordinates":[153.02432300000001,-27.363934],"type":"Point"}
}