{
  "type": "Feature",
  "properties": {
    "iso:country":"AU",
    "sg:address":"9 Eades St",
    "sg:city":"Laverton",
    "sg:classifiers":[
        {
            "category":"Utilities",
            "subcategory":"Refuse",
            "type":"Services"
        }
    ],
    "sg:phone":"+61 413 465 688",
    "sg:postcode":"3028",
    "sg:province":"VIC",
    "sg:tags":[
        "remover",
        "rubbish"
    ],
    "wof:name":"AAA 24/7 Bin Hire",
    "wof:placetype":"venue"
},
  "geometry": {"coordinates":[144.777466,-37.855343],"type":"Point"}
}