{
  "type": "Feature",
  "properties": {
    "addr:full":"\"The Firestation\" 20a Jephson St Toowong QLD 4066",
    "addr:housenumber":"20a",
    "addr:postcode":"4066",
    "addr:street":"Jephson St",
    "iso:country":"AU",
    "sg:address":"\"The Firestation\" 20a Jephson St",
    "sg:city":"Toowong",
    "sg:classifiers":[
        {
            "category":"Real Estate",
            "subcategory":"Real Estate Agent",
            "type":"Services"
        }
    ],
    "sg:phone":"+61 7 3377 4999",
    "sg:postcode":"4066",
    "sg:province":"QLD",
    "wof:name":"Honeycombes Real Estate",
    "wof:placetype":"venue"
},
  "geometry": {"coordinates":[152.991287231,-27.4820327759],"type":"Point"}
}