{
  "type": "Feature",
  "properties": {
    "addr:full":"5 Barak St Parkville VIC 3052",
    "addr:housenumber":"5",
    "addr:postcode":"3052",
    "addr:street":"Barak St",
    "iso:country":"AU",
    "sg:address":"5 Barak St",
    "sg:city":"Parkville",
    "sg:classifiers":[
        {
            "category":"Professional",
            "subcategory":"Engineering",
            "type":"Services"
        }
    ],
    "sg:phone":"+61 3 9387 0808",
    "sg:postcode":"3052",
    "sg:province":"VIC",
    "sg:tags":[
        "consulting",
        "engineer"
    ],
    "wof:name":"Duga Technologies Pty Ltd",
    "wof:placetype":"venue"
},
  "geometry": {"coordinates":[145.086105347,-37.7755661011],"type":"Point"}
}