{
  "type": "Feature",
  "properties": {
    "addr:full":"PO Box 67A Bermagui NSW 2546",
    "addr:postcode":"2546",
    "iso:country":"AU",
    "sg:address":"PO Box 67A",
    "sg:city":"Bermagui",
    "sg:classifiers":[
        {
            "category":"Real Estate",
            "subcategory":"Real Estate Agent",
            "type":"Services"
        }
    ],
    "sg:phone":"+61 2 6493 3369",
    "sg:postcode":"2546",
    "sg:province":"NSW",
    "wof:name":"Agent for Buyers",
    "wof:placetype":"venue"
},
  "geometry": {"coordinates":[150.07612609899999,-36.4285583496],"type":"Point"}
}