{
  "type": "Feature",
  "properties": {
    "iso:country":"AU",
    "sg:address":"14A Pitt St",
    "sg:city":"Mortdale",
    "sg:classifiers":[
        {
            "category":"Health Services",
            "subcategory":"Doctor",
            "type":"Services"
        }
    ],
    "sg:phone":"+61 2 9580 9555",
    "sg:postcode":"2223",
    "sg:province":"NSW",
    "sg:tags":[
        "reflexology"
    ],
    "wof:name":"Total Wellbeing Homoeopathy & Reflexology",
    "wof:placetype":"venue"
},
  "geometry": {"coordinates":[151.07989501899999,-33.971534729],"type":"Point"}
}