{
  "type": "Feature",
  "properties": {
    "addr:full":"15 Old Prospect Rd Wentworthville NSW 2145",
    "addr:housenumber":"15",
    "addr:postcode":"2145",
    "addr:street":"Old Prospect Rd",
    "iso:country":"AU",
    "sg:address":"15 Old Prospect Rd",
    "sg:city":"Wentworthville",
    "sg:classifiers":[
        {
            "category":"Building & Trades",
            "subcategory":"Plumbing",
            "type":"Services"
        }
    ],
    "sg:phone":"+61 2 9631 5469",
    "sg:postcode":"2145",
    "sg:province":"NSW",
    "sg:tags":[
        "plumber",
        "gasfitters"
    ],
    "wof:name":"Drain Master",
    "wof:placetype":"venue"
},
  "geometry": {"coordinates":[150.97140502900001,-33.8165664673],"type":"Point"}
}