{
  "type": "Feature",
  "properties": {
    "iso:country":"AU",
    "sg:address":"PMB 168",
    "sg:city":"Katherine",
    "sg:classifiers":[
        {
            "category":"Building & Trades",
            "subcategory":"Landscaping Services",
            "type":"Services"
        }
    ],
    "sg:phone":"+61 8 8975 9920",
    "sg:postcode":"0850",
    "sg:province":"NT",
    "sg:tags":[
        "grazier"
    ],
    "wof:name":"Hayfield Shenandoah Station",
    "wof:placetype":"venue"
},
  "geometry": {"coordinates":[132.317215,-14.40013],"type":"Point"}
}