{
  "type": "Feature",
  "properties": {
    "addr:full":"128 Kooyong Rd Caulfield North VIC 3161",
    "addr:housenumber":"128",
    "addr:postcode":"3161",
    "addr:street":"Kooyong Rd",
    "iso:country":"AU",
    "sg:address":"128 Kooyong Rd",
    "sg:city":"Caulfield North",
    "sg:classifiers":[
        {
            "category":"Retail",
            "subcategory":"Repair Shop",
            "type":"Services"
        }
    ],
    "sg:phone":"+61 3 9527 3540",
    "sg:postcode":"3161",
    "sg:province":"VIC",
    "sg:tags":[
        "machine",
        "repairs",
        "part",
        "dryer",
        "washing"
    ],
    "wof:name":"Caulfield Washing Machine & Dryer Service",
    "wof:placetype":"venue"
},
  "geometry": {"coordinates":[145.01754760700001,-37.8735084534],"type":"Point"}
}