{
  "type": "Feature",
  "properties": {
    "iso:country":"AU",
    "sg:address":"Shp5/ 12 Ocean St",
    "sg:city":"Budgewoi",
    "sg:classifiers":[
        {
            "category":"Health Services",
            "subcategory":"Health Practitioner",
            "type":"Services"
        }
    ],
    "sg:phone":"+61 2 4390 3435",
    "sg:postcode":"2262",
    "sg:province":"NSW",
    "sg:tags":[
        "alternative"
    ],
    "wof:name":"Budgewoi Family Wellness Clinic",
    "wof:placetype":"venue"
},
  "geometry": {"coordinates":[151.563705,-33.237301],"type":"Point"}
}