{
  "type": "Feature",
  "properties": {
    "iso:country":"AU",
    "sg:address":"PO Box 3192",
    "sg:city":"Asquith",
    "sg:classifiers":[
        {
            "category":"Professional",
            "subcategory":"Computer Services",
            "type":"Services"
        }
    ],
    "sg:phone":"+61 419 287 792",
    "sg:postcode":"2077",
    "sg:province":"NSW",
    "sg:tags":[
        "consultant",
        "system"
    ],
    "wof:name":"Comix Consulting Pty Ltd",
    "wof:placetype":"venue"
},
  "geometry": {"coordinates":[151.10940551799999,-33.6891212463],"type":"Point"}
}