{
  "type": "Feature",
  "properties": {
    "addr:full":"40 Silva Ave Queanbeyan NSW 2620",
    "addr:housenumber":"40",
    "addr:postcode":"2620",
    "addr:street":"Silva Ave",
    "iso:country":"AU",
    "sg:address":"40 Silva Ave",
    "sg:city":"Queanbeyan",
    "sg:classifiers":[
        {
            "category":"Home & Garden",
            "subcategory":"Home Furnishings",
            "type":"Retail Goods"
        }
    ],
    "sg:phone":"+61 2 6232 9033",
    "sg:postcode":"2620",
    "sg:province":"NSW",
    "sg:tags":[
        "storage",
        "rack",
        "wine"
    ],
    "wof:name":"Australian Winerack Manufacturers Pty Ltd",
    "wof:placetype":"venue"
},
  "geometry": {"coordinates":[149.24847412099999,-35.3426055908],"type":"Point"}
}