{
  "type": "Feature",
  "properties": {
    "iso:country":"AU",
    "sg:address":"451 Hume Hwy",
    "sg:city":"Casula",
    "sg:classifiers":[
        {
            "category":"Real Estate",
            "subcategory":"Architect",
            "type":"Services"
        }
    ],
    "sg:phone":"+61 2 9602 2400",
    "sg:postcode":"2170",
    "sg:province":"NSW",
    "sg:tags":[
        "building",
        "designer"
    ],
    "wof:name":"Ardesign",
    "wof:placetype":"venue"
},
  "geometry": {"coordinates":[150.90065002399999,-33.9526290894],"type":"Point"}
}