{
  "type": "Feature",
  "properties": {
    "addr:full":"19 Settlement Rd Belmont VIC 3216",
    "addr:housenumber":"19",
    "addr:postcode":"3216",
    "addr:street":"Settlement Rd",
    "iso:country":"AU",
    "sg:address":"19 Settlement Rd",
    "sg:city":"Belmont",
    "sg:classifiers":[
        {
            "category":"Autos & Motor Vehicles",
            "subcategory":"Fuel & Gas Station",
            "type":"Retail Goods"
        }
    ],
    "sg:phone":"+61 3 5243 4639",
    "sg:postcode":"3216",
    "sg:province":"VIC",
    "wof:name":"Mobil Oil Australia Pty Ltd",
    "wof:placetype":"venue"
},
  "geometry": {"coordinates":[144.35142517099999,-38.179309845],"type":"Point"}
}