{
  "type": "Feature",
  "properties": {
    "addr:full":"Shop 3 & 4/ 1 Banksia Drv Byron Bay NSW 2481",
    "addr:housenumber":"shop 3 & 4 / 1",
    "addr:postcode":"2481",
    "addr:street":"Banksia Drv",
    "iso:country":"AU",
    "sg:address":"Shop 3 & 4/ 1 Banksia Drv",
    "sg:city":"Byron Bay",
    "sg:classifiers":[
        {
            "category":"Personal",
            "subcategory":"Beauty Salon",
            "type":"Services"
        }
    ],
    "sg:phone":"+61 413 898 999",
    "sg:postcode":"2481",
    "sg:province":"NSW",
    "wof:name":"Azula Beauty & Body Treats",
    "wof:placetype":"venue"
},
  "geometry": {"coordinates":[153.58578491200001,-28.6378288269],"type":"Point"}
}