{
  "type": "Feature",
  "properties": {
    "addr:full":"26 View Grand Rd Maribyrnong VIC 3032",
    "addr:housenumber":"26",
    "addr:postcode":"3032",
    "addr:street":"View Grand Rd",
    "iso:country":"AU",
    "sg:address":"26 View Grand Rd",
    "sg:city":"Maribyrnong",
    "sg:classifiers":[
        {
            "category":"Shopping",
            "subcategory":"Bridal",
            "type":"Retail Goods"
        }
    ],
    "sg:phone":"+61 413 778 119",
    "sg:postcode":"3032",
    "sg:province":"VIC",
    "sg:tags":[
        "hire",
        "wear"
    ],
    "wof:name":"Absolute Bellissimo Formal & Beauty",
    "wof:placetype":"venue"
},
  "geometry": {"coordinates":[144.88415499999999,-37.765465],"type":"Point"}
}