{
  "type": "Feature",
  "properties": {
    "iso:country":"AU",
    "sg:address":"65 Wortley St",
    "sg:city":"Kalgoorlie",
    "sg:classifiers":[
        {
            "category":"Building & Trades",
            "subcategory":"Cleaning & Sanitation",
            "type":"Services"
        }
    ],
    "sg:phone":"+61 8 9021 7381",
    "sg:postcode":"6430",
    "sg:province":"WA",
    "sg:tags":[
        "window"
    ],
    "wof:name":"A. & M. Commercial & Domestic Services",
    "wof:placetype":"venue"
},
  "geometry": {"coordinates":[121.43939209,-30.770067215],"type":"Point"}
}