{
  "type": "Feature",
  "properties": {
    "iso:country":"AU",
    "sg:address":"68 Bold St",
    "sg:city":"Laurieton",
    "sg:classifiers":[
        {
            "category":"Real Estate",
            "subcategory":"Real Estate Agent",
            "type":"Services"
        }
    ],
    "sg:phone":"+61 2 6559 9400",
    "sg:postcode":"2443",
    "sg:province":"NSW",
    "wof:name":"PRD Nationwide",
    "wof:placetype":"venue"
},
  "geometry": {"coordinates":[152.796585,-31.650585],"type":"Point"}
}