{
  "type": "Feature",
  "properties": {
    "iso:country":"AU",
    "sg:address":"PO Box 140 \"Boundary Point\"",
    "sg:city":"Murtho",
    "sg:classifiers":[
        {
            "category":"Farming",
            "subcategory":"Farm",
            "type":"Manufacturing & Wholesale Goods"
        }
    ],
    "sg:phone":"+61 8 8595 8054",
    "sg:postcode":"5341",
    "sg:province":"SA",
    "sg:tags":[
        "farmer"
    ],
    "wof:name":"Boundary Point Farming",
    "wof:placetype":"venue"
},
  "geometry": {"coordinates":[140.742919922,-34.1744422913],"type":"Point"}
}