{
  "type": "Feature",
  "properties": {
    "iso:country":"AU",
    "sg:address":"68 Deering St",
    "sg:city":"Ulladulla",
    "sg:classifiers":[
        {
            "category":"Professional",
            "subcategory":"Accounting & Tax Preparation",
            "type":"Services"
        }
    ],
    "sg:phone":"+61 2 4455 6666",
    "sg:postcode":"2539",
    "sg:province":"NSW",
    "sg:tags":[
        "consultant",
        "taxation"
    ],
    "wof:name":"Shane Roberts",
    "wof:placetype":"venue"
},
  "geometry": {"coordinates":[150.474243164,-35.3626022339],"type":"Point"}
}