{
  "type": "Feature",
  "properties": {
    "iso:country":"AU",
    "sg:address":"23 Rowland St",
    "sg:city":"Slacks Creek",
    "sg:classifiers":[
        {
            "category":"Retail",
            "subcategory":"Auto Repair",
            "type":"Services"
        }
    ],
    "sg:phone":"+61 7 3290 0049",
    "sg:postcode":"4127",
    "sg:province":"QLD",
    "sg:tags":[
        "beater",
        "painter",
        "panel"
    ],
    "wof:name":"Auto Reinstatements",
    "wof:placetype":"venue"
},
  "geometry": {"coordinates":[153.126495361,-27.6307048798],"type":"Point"}
}