{
  "type": "Feature",
  "properties": {
    "addr:full":"19 Fiveways Blv Keysborough VIC 3173",
    "addr:housenumber":"19",
    "addr:postcode":"3173",
    "addr:street":"Fiveways Blv",
    "iso:country":"AU",
    "sg:address":"19 Fiveways Blv",
    "sg:city":"Keysborough",
    "sg:classifiers":[
        {
            "category":"Wholesale",
            "subcategory":"Machinery & Supplies",
            "type":"Manufacturing & Wholesale Goods"
        }
    ],
    "sg:phone":"+61 3 9701 5577",
    "sg:postcode":"3173",
    "sg:province":"VIC",
    "sg:website":"http://www.ctsmachinery.com.au",
    "wof:name":"CTS Plastics Machinery Pty Ltd",
    "wof:placetype":"venue"
},
  "geometry": {"coordinates":[145.15032959000001,-37.9881973267],"type":"Point"}
}