{
  "type": "Feature",
  "properties": {
    "addr:full":"190 Main St Croydon VIC 3136",
    "addr:housenumber":"190",
    "addr:postcode":"3136",
    "addr:street":"Main St",
    "iso:country":"AU",
    "sg:address":"190 Main St",
    "sg:city":"Croydon",
    "sg:classifiers":[
        {
            "category":"Health Services",
            "subcategory":"Optometrist",
            "type":"Services"
        }
    ],
    "sg:phone":"+61 3 9723 3292",
    "sg:postcode":"3136",
    "sg:province":"VIC",
    "wof:name":"Dove & Schubert Optometrists",
    "wof:placetype":"venue"
},
  "geometry": {"coordinates":[145.28073120100001,-37.7984962463],"type":"Point"}
}