{
  "type": "Feature",
  "properties": {
    "addr:full":"385 Martin Rd Mundaring WA 6073",
    "addr:housenumber":"385",
    "addr:postcode":"6073",
    "addr:street":"Martin Rd",
    "iso:country":"AU",
    "sg:address":"385 Martin Rd",
    "sg:city":"Mundaring",
    "sg:classifiers":[
        {
            "category":"Professional",
            "subcategory":"Computer Services",
            "type":"Services"
        }
    ],
    "sg:phone":"+61 8 9295 3970",
    "sg:postcode":"6073",
    "sg:province":"WA",
    "sg:tags":[
        "package",
        "software"
    ],
    "wof:name":"Datapro Pty Ltd",
    "wof:placetype":"venue"
},
  "geometry": {"coordinates":[116.162246704,-31.9094543457],"type":"Point"}
}