{
  "type": "Feature",
  "properties": {
    "addr:full":"24 McPhee St Chester Hill NSW 2162",
    "addr:housenumber":"24",
    "addr:postcode":"2162",
    "addr:street":"Mcphee St",
    "iso:country":"AU",
    "sg:address":"24 McPhee St",
    "sg:city":"Chester Hill",
    "sg:classifiers":[
        {
            "category":"Building & Trades",
            "subcategory":"Construction",
            "type":"Services"
        }
    ],
    "sg:phone":"+61 2 9786 8982",
    "sg:postcode":"2162",
    "sg:province":"NSW",
    "sg:tags":[
        "concrete",
        "treatment",
        "repair"
    ],
    "wof:name":"Sydney Stencils",
    "wof:placetype":"venue"
},
  "geometry": {"coordinates":[151.005737305,-33.8792228699],"type":"Point"}
}