{
  "type": "Feature",
  "properties": {
    "addr:full":"590 Hay St Subiaco WA 6008",
    "addr:housenumber":"590",
    "addr:postcode":"6008",
    "addr:street":"Hay St",
    "iso:country":"AU",
    "sg:address":"590 Hay St",
    "sg:city":"Subiaco",
    "sg:classifiers":[
        {
            "category":"Wholesale",
            "subcategory":"Machinery & Supplies",
            "type":"Manufacturing & Wholesale Goods"
        }
    ],
    "sg:phone":"+61 1800 658 278",
    "sg:postcode":"6008",
    "sg:province":"WA",
    "sg:tags":[
        "equipment",
        "laboratory"
    ],
    "wof:name":"BOC Gases",
    "wof:placetype":"venue"
},
  "geometry": {"coordinates":[115.815071106,-31.9468574524],"type":"Point"}
}