{
  "type": "Feature",
  "properties": {
    "iso:country":"AU",
    "sg:address":"William St",
    "sg:city":"Beaudesert",
    "sg:classifiers":[
        {
            "category":"Health Services",
            "subcategory":"Doctor",
            "type":"Services"
        }
    ],
    "sg:phone":"+61 7 5541 3324",
    "sg:postcode":"4285",
    "sg:province":"QLD",
    "sg:tags":[
        "medical",
        "practitioner"
    ],
    "wof:name":"Beaudesert Family Practice",
    "wof:placetype":"venue"
},
  "geometry": {"coordinates":[152.99617000000001,-27.988377],"type":"Point"}
}