{
  "type": "Feature",
  "properties": {
    "addr:full":"49 Wade Ave Leeton NSW 2705",
    "addr:housenumber":"49",
    "addr:postcode":"2705",
    "addr:street":"Wade Ave",
    "iso:country":"AU",
    "sg:address":"49 Wade Ave",
    "sg:city":"Leeton",
    "sg:classifiers":[
        {
            "category":"Health Services",
            "subcategory":"Dentist",
            "type":"Services"
        }
    ],
    "sg:phone":"+61 2 6953 2496",
    "sg:postcode":"2705",
    "sg:province":"NSW",
    "sg:tags":[
        "dental",
        "prosthetist"
    ],
    "wof:name":"Ernst D J",
    "wof:placetype":"venue"
},
  "geometry": {"coordinates":[146.40620422399999,-34.5520401001],"type":"Point"}
}