{
  "type": "Feature",
  "properties": {
    "iso:country":"AU",
    "sg:address":"12 Claret Ash Crt",
    "sg:city":"Helena Valley",
    "sg:classifiers":[
        {
            "category":"Professional",
            "subcategory":"Art Services",
            "type":"Services"
        }
    ],
    "sg:phone":"+61 8 9250 3505",
    "sg:postcode":"6056",
    "sg:province":"WA",
    "sg:tags":[
        "picture",
        "frame",
        "framing"
    ],
    "wof:name":"Excelsior Pictures & Crafts",
    "wof:placetype":"venue"
},
  "geometry": {"coordinates":[116.02887725799999,-31.9128723145],"type":"Point"}
}