{
  "type": "Feature",
  "properties": {
    "addr:full":"310 Memorial Drv Eumundi QLD 4562",
    "addr:housenumber":"310",
    "addr:postcode":"4562",
    "addr:street":"Memorial Drv",
    "iso:country":"AU",
    "sg:address":"310 Memorial Drv",
    "sg:city":"Eumundi",
    "sg:classifiers":[
        {
            "category":"Farming",
            "subcategory":"Vineyard",
            "type":"Manufacturing & Wholesale Goods"
        }
    ],
    "sg:phone":"+61 7 5442 7444",
    "sg:postcode":"4562",
    "sg:province":"QLD",
    "sg:tags":[
        "winery"
    ],
    "wof:name":"Eumundi Winery",
    "wof:placetype":"venue"
},
  "geometry": {"coordinates":[152.933197022,-26.4617290497],"type":"Point"}
}