{
  "type": "Feature",
  "properties": {
    "addr:full":"PO Box 1057 Morley WA 6943",
    "addr:postcode":"6943",
    "iso:country":"AU",
    "sg:address":"PO Box 1057",
    "sg:city":"Morley",
    "sg:classifiers":[
        {
            "category":"Autos & Motor Vehicles",
            "subcategory":"Auto Supplies",
            "type":"Retail Goods"
        }
    ],
    "sg:phone":"+61 403 608 056",
    "sg:postcode":"6943",
    "sg:province":"WA",
    "sg:tags":[
        "accessory"
    ],
    "wof:name":"ModYourCar",
    "wof:placetype":"venue"
},
  "geometry": {"coordinates":[115.904602051,-31.8957290649],"type":"Point"}
}