{
  "type": "Feature",
  "properties": {
    "addr:full":"2/ 347 Barrenjoey Rd Newport NSW 2106",
    "addr:housenumber":"/ 347",
    "addr:postcode":"2106",
    "addr:street":"Barrenjoey Rd",
    "iso:country":"AU",
    "sg:address":"2/ 347 Barrenjoey Rd",
    "sg:city":"Newport",
    "sg:classifiers":[
        {
            "category":"Government",
            "subcategory":"Court House",
            "type":"Public Place"
        }
    ],
    "sg:phone":"+61 2 9999 1415",
    "sg:postcode":"2106",
    "sg:province":"NSW",
    "sg:tags":[
        "personal",
        "marriage",
        "family",
        "counselling"
    ],
    "wof:name":"Shiloh Counselling Centre",
    "wof:placetype":"venue"
},
  "geometry": {"coordinates":[151.32005310100001,-33.6551475525],"type":"Point"}
}