{
  "type": "Feature",
  "properties": {
    "addr:full":"18 Wood St Newcastle West NSW 2302",
    "addr:housenumber":"18",
    "addr:postcode":"2302",
    "addr:street":"Wood St",
    "iso:country":"AU",
    "sg:address":"18 Wood St",
    "sg:city":"Newcastle West",
    "sg:classifiers":[
        {
            "category":"Professional",
            "subcategory":"Computer Services",
            "type":"Services"
        }
    ],
    "sg:phone":"+61 2 4962 4040",
    "sg:postcode":"2302",
    "sg:province":"NSW",
    "sg:tags":[
        "training"
    ],
    "sg:website":"http://www.newcastlecomputertraining.com.au",
    "wof:name":"Newcastle Computer Training",
    "wof:placetype":"venue"
},
  "geometry": {"coordinates":[151.75715600000001,-32.925663],"type":"Point"}
}