{
  "type": "Feature",
  "properties": {
    "iso:country":"AU",
    "sg:address":"229 Macquarie Grove Rd",
    "sg:city":"Camden",
    "sg:classifiers":[
        {
            "category":"Organizations",
            "subcategory":"Non-profit Organization",
            "type":"Services"
        }
    ],
    "sg:phone":"+61 2 4655 7440",
    "sg:postcode":"2570",
    "sg:province":"NSW",
    "sg:tags":[
        "support",
        "disability",
        "organisation"
    ],
    "wof:name":"Bethany Early Intervention",
    "wof:placetype":"venue"
},
  "geometry": {"coordinates":[150.711013794,-34.0203285217],"type":"Point"}
}