{
  "type": "Feature",
  "properties": {
    "iso:country":"AU",
    "sg:address":"ETSA Park 155 Railway Tce",
    "sg:city":"Mile End South",
    "sg:classifiers":[
        {
            "category":"Arena",
            "subcategory":"Sports Club",
            "type":"Entertainment"
        }
    ],
    "sg:phone":"+61 8 8238 0500",
    "sg:postcode":"5031",
    "sg:province":"SA",
    "sg:tags":[
        "organisation",
        "sporting"
    ],
    "wof:name":"Netball SA",
    "wof:placetype":"venue"
},
  "geometry": {"coordinates":[138.576782227,-34.935585022],"type":"Point"}
}