{
  "type": "Feature",
  "properties": {
    "addr:full":"Shop 1010 , Westfield Shopping Centre Bondi Junction NSW 2022",
    "addr:housenumber":"1010",
    "addr:postcode":"2022",
    "addr:street":"Westfield Shopping",
    "iso:country":"AU",
    "sg:address":"Shop 1010",
    "sg:city":", Westfield Shopping Centre Bondi Junction",
    "sg:classifiers":[
        {
            "category":"Shopping",
            "subcategory":"Optical Goods",
            "type":"Retail Goods"
        }
    ],
    "sg:phone":"+61 2 9387 5531",
    "sg:postcode":"2022",
    "sg:province":"NSW",
    "sg:tags":[
        "dispenser",
        "prescription"
    ],
    "wof:name":"Master Specs",
    "wof:placetype":"venue"
},
  "geometry": {"coordinates":[151.24720764200001,-33.892829895],"type":"Point"}
}