{
  "type": "Feature",
  "properties": {
    "iso:country":"AU",
    "sg:address":"60 Blair St",
    "sg:city":"North Bondi",
    "sg:classifiers":[
        {
            "category":"Personal",
            "subcategory":"Beauty Salon",
            "type":"Services"
        }
    ],
    "sg:phone":"+61 2 9130 1117",
    "sg:postcode":"2026",
    "sg:province":"NSW",
    "sg:tags":[
        "hairdresser"
    ],
    "wof:name":"Ray & Kay's Hairdressers",
    "wof:placetype":"venue"
},
  "geometry": {"coordinates":[151.27627563499999,-33.8853111267],"type":"Point"}
}