{
  "type": "Feature",
  "properties": {
    "iso:country":"AU",
    "sg:address":"The Trade Centre Mulgoa Rd",
    "sg:city":"Penrith",
    "sg:classifiers":[
        {
            "category":"Personal",
            "type":"Services"
        }
    ],
    "sg:phone":"+61 412 486 925",
    "sg:postcode":"2750",
    "sg:province":"NSW",
    "sg:tags":[
        "reducing",
        "treatment",
        "weight"
    ],
    "wof:name":"Victor Tuballa Natural Therapies",
    "wof:placetype":"venue"
},
  "geometry": {"coordinates":[150.68734741200001,-33.7535896301],"type":"Point"}
}