{
  "type": "Feature",
  "properties": {
    "addr:full":"Shop 3 Karalta Plz Erina NSW 2250",
    "addr:housenumber":"shop 3",
    "addr:postcode":"2250",
    "addr:street":"Karalta Plz",
    "iso:country":"AU",
    "sg:address":"Shop 3",
    "sg:city":"Karalta Plz Erina",
    "sg:classifiers":[
        {
            "category":"Retail",
            "subcategory":"Laundry & Dry Cleaning",
            "type":"Services"
        }
    ],
    "sg:phone":"+61 2 4365 4797",
    "sg:postcode":"2250",
    "sg:province":"NSW",
    "sg:tags":[
        "manicurist"
    ],
    "wof:name":"Beautique Beauty Spa",
    "wof:placetype":"venue"
},
  "geometry": {"coordinates":[151.38531494099999,-33.4387893677],"type":"Point"}
}