{
  "type": "Feature",
  "properties": {
    "addr:full":"764 Church Plains Rd Wagga Wagga NSW 2650",
    "addr:housenumber":"764",
    "addr:postcode":"2650",
    "addr:street":"Church Plains Rd",
    "iso:country":"AU",
    "sg:address":"764 Church Plains Rd",
    "sg:city":"Wagga Wagga",
    "sg:classifiers":[
        {
            "category":"Building & Trades",
            "subcategory":"Construction",
            "type":"Services"
        }
    ],
    "sg:phone":"+61 2 6922 9762",
    "sg:postcode":"2650",
    "sg:province":"NSW",
    "sg:tags":[
        "earth",
        "excavating",
        "moving",
        "contractor"
    ],
    "wof:name":"Bill Robertson",
    "wof:placetype":"venue"
},
  "geometry": {"coordinates":[147.24598693900001,-35.1863670349],"type":"Point"}
}