{
  "type": "Feature",
  "properties": {
    "iso:country":"AU",
    "sg:address":"Lysterfield Rd",
    "sg:city":"Orange",
    "sg:classifiers":[
        {
            "category":"Farming",
            "subcategory":"Orchard",
            "type":"Manufacturing & Wholesale Goods"
        }
    ],
    "sg:phone":"+61 2 6365 3109",
    "sg:postcode":"2800",
    "sg:province":"NSW",
    "sg:tags":[
        "pear",
        "apple",
        "grower"
    ],
    "wof:name":"Hawke D A",
    "wof:placetype":"venue"
},
  "geometry": {"coordinates":[149.077301025,-33.3048820496],"type":"Point"}
}