{
  "type": "Feature",
  "properties": {
    "addr:full":"33 St David St Fitzroy VIC 3065",
    "addr:housenumber":"33",
    "addr:postcode":"3065",
    "addr:street":"St David St",
    "iso:country":"AU",
    "sg:address":"33 St David St",
    "sg:city":"Fitzroy",
    "sg:classifiers":[
        {
            "category":"Education",
            "subcategory":"School",
            "type":"Public Place"
        }
    ],
    "sg:phone":"+61 3 9419 5666",
    "sg:postcode":"3065",
    "sg:province":"VIC",
    "sg:tags":[
        "supply"
    ],
    "wof:name":"Melbourne Etching Supplies",
    "wof:placetype":"venue"
},
  "geometry": {"coordinates":[144.979568481,-37.800617218],"type":"Point"}
}