{
  "type": "Feature",
  "properties": {
    "addr:full":"Shop 16 Centrepoint Arc, Canberra City ACT 2601",
    "addr:housenumber":"shop 16",
    "addr:postcode":"2601",
    "addr:street":"Centrepoint Arc",
    "iso:country":"AU",
    "sg:address":"Shop 16",
    "sg:city":"Centrepoint Arc, Canberra City",
    "sg:classifiers":[
        {
            "category":"Personal",
            "subcategory":"Beauty Salon",
            "type":"Services"
        }
    ],
    "sg:phone":"+61 2 6247 5585",
    "sg:postcode":"2601",
    "sg:province":"ACT",
    "sg:tags":[
        "hair",
        "treatment",
        "replacement"
    ],
    "wof:name":"Antics Hair",
    "wof:placetype":"venue"
},
  "geometry": {"coordinates":[149.13090515100001,-35.2801513672],"type":"Point"}
}