{
  "type": "Feature",
  "properties": {
    "addr:full":"Unit 2/ 40 Munibung Rd Cardiff NSW 2285",
    "addr:postcode":"2285",
    "addr:street":"40 Munibung Rd",
    "iso:country":"AU",
    "sg:address":"Unit 2/ 40 Munibung Rd",
    "sg:city":"Cardiff",
    "sg:classifiers":[
        {
            "category":"Communications",
            "subcategory":"Film & Video Production",
            "type":"Services"
        }
    ],
    "sg:phone":"+61 2 4956 9700",
    "sg:postcode":"2285",
    "sg:province":"NSW",
    "sg:tags":[
        "fan",
        "blower"
    ],
    "wof:name":"westaflex (Aust) P/L",
    "wof:placetype":"venue"
},
  "geometry": {"coordinates":[151.645996094,-32.9427070618],"type":"Point"}
}