{
  "type": "Feature",
  "properties": {
    "iso:country":"AU",
    "sg:address":"248 Churchill Rd",
    "sg:city":"Prospect",
    "sg:classifiers":[
        {
            "category":"Bars & Pubs",
            "subcategory":"Lounge",
            "type":"Food & Drink"
        }
    ],
    "sg:phone":"+61 8 8344 9433",
    "sg:postcode":"5082",
    "sg:province":"SA",
    "sg:tags":[
        "water",
        "filter",
        "drinking"
    ],
    "wof:name":"Northern Plumbing Maintenance",
    "wof:placetype":"venue"
},
  "geometry": {"coordinates":[138.58421325699999,-34.8779296875],"type":"Point"}
}