{
  "type": "Feature",
  "properties": {
    "addr:full":"PO Box 58 Wyong NSW 2259",
    "addr:postcode":"2259",
    "iso:country":"AU",
    "sg:address":"PO Box 58",
    "sg:city":"Wyong",
    "sg:classifiers":[
        {
            "category":"Professional",
            "subcategory":"Accounting & Tax Preparation",
            "type":"Services"
        }
    ],
    "sg:phone":"+61 1300 885 565",
    "sg:postcode":"2259",
    "sg:province":"NSW",
    "sg:tags":[
        "bookkeeping"
    ],
    "wof:name":"First Class Accounts Wyong",
    "wof:placetype":"venue"
},
  "geometry": {"coordinates":[151.42552185100001,-33.2829093933],"type":"Point"}
}