{
  "type": "Feature",
  "properties": {
    "addr:full":"1/ 24 David Muir St Slade Point QLD 4740",
    "addr:housenumber":"/ 24",
    "addr:postcode":"4740",
    "addr:street":"David Muir St",
    "iso:country":"AU",
    "sg:address":"1/ 24 David Muir St",
    "sg:city":"Slade Point",
    "sg:classifiers":[
        {
            "category":"Food & Beverages",
            "subcategory":"Meat & Fish",
            "type":"Retail Goods"
        }
    ],
    "sg:phone":"+61 7 4955 4111",
    "sg:postcode":"4740",
    "sg:province":"QLD",
    "sg:tags":[
        "seafood"
    ],
    "wof:name":"Debbie's Seafood",
    "wof:placetype":"venue"
},
  "geometry": {"coordinates":[149.21276900000001,-21.0909],"type":"Point"}
}