{
  "type": "Feature",
  "properties": {
    "addr:full":"10 William St Rockhampton QLD 4700",
    "addr:housenumber":"10",
    "addr:postcode":"4700",
    "addr:street":"William St",
    "iso:country":"AU",
    "sg:address":"10 William St",
    "sg:city":"Rockhampton",
    "sg:classifiers":[
        {
            "category":"Real Estate",
            "subcategory":"Real Estate Agent",
            "type":"Services"
        }
    ],
    "sg:phone":"+61 7 4922 9355",
    "sg:postcode":"4700",
    "sg:province":"QLD",
    "wof:name":"Huxtable Peter A",
    "wof:placetype":"venue"
},
  "geometry": {"coordinates":[150.50895690900001,-23.383392334],"type":"Point"}
}