{
  "type": "Feature",
  "properties": {
    "iso:country":"AU",
    "sg:address":"Warrah St",
    "sg:city":"Hamilton East",
    "sg:classifiers":[
        {
            "category":"Organizations",
            "subcategory":"Professional Association",
            "type":"Services"
        }
    ],
    "sg:phone":"+61 413 515 406",
    "sg:postcode":"2303",
    "sg:province":"NSW",
    "sg:tags":[
        "web",
        "internet"
    ],
    "wof:name":"Liquid Sky Studios",
    "wof:placetype":"venue"
},
  "geometry": {"coordinates":[151.756775,-32.927166],"type":"Point"}
}