{
  "type": "Feature",
  "properties": {
    "addr:full":"156 Davey St Hobart TAS 7000",
    "addr:housenumber":"156",
    "addr:postcode":"7000",
    "addr:street":"Davey St",
    "iso:country":"AU",
    "sg:address":"156 Davey St",
    "sg:city":"Hobart",
    "sg:classifiers":[
        {
            "category":"Retail",
            "subcategory":"Auto Rental",
            "type":"Services"
        }
    ],
    "sg:phone":"+61 3 6224 4878",
    "sg:postcode":"7000",
    "sg:province":"TAS",
    "sg:tags":[
        "car",
        "hire",
        "minibus"
    ],
    "wof:name":"A. 1. Ute Hire",
    "wof:placetype":"venue"
},
  "geometry": {"coordinates":[147.324676514,-42.8885536194],"type":"Point"}
}