{
  "type": "Feature",
  "properties": {
    "addr:full":"11 Glossop St Wangara WA 6065",
    "addr:housenumber":"11",
    "addr:postcode":"6065",
    "addr:street":"Glossop St",
    "iso:country":"AU",
    "sg:address":"11 Glossop St",
    "sg:city":"Wangara",
    "sg:classifiers":[
        {
            "category":"Insurance",
            "subcategory":"Life Insurance",
            "type":"Services"
        }
    ],
    "sg:phone":"+61 8 9302 1186",
    "sg:postcode":"6065",
    "sg:province":"WA",
    "wof:name":"Doug Gall & Associates",
    "wof:placetype":"venue"
},
  "geometry": {"coordinates":[115.821380615,-31.7883987427],"type":"Point"}
}