{
  "type": "Feature",
  "properties": {
    "addr:full":"19 Hakea St Tecoma VIC 3160",
    "addr:housenumber":"19",
    "addr:postcode":"3160",
    "addr:street":"Hakea St",
    "iso:country":"AU",
    "sg:address":"19 Hakea St",
    "sg:city":"Tecoma",
    "sg:classifiers":[
        {
            "category":"Utilities",
            "subcategory":"Electric",
            "type":"Services"
        }
    ],
    "sg:phone":"+61 3 9754 4219",
    "sg:postcode":"3160",
    "sg:province":"VIC",
    "sg:tags":[
        "electrical",
        "contractor"
    ],
    "wof:name":"Sherbrooke Electrical",
    "wof:placetype":"venue"
},
  "geometry": {"coordinates":[145.34201049800001,-37.9032402039],"type":"Point"}
}