{
  "type": "Feature",
  "properties": {
    "addr:full":"18 Bank St Adelaide SA 5000",
    "addr:housenumber":"18",
    "addr:postcode":"5000",
    "addr:street":"Bank St",
    "iso:country":"AU",
    "sg:address":"18 Bank St",
    "sg:city":"Adelaide",
    "sg:classifiers":[
        {
            "category":"Shopping",
            "subcategory":"Music",
            "type":"Retail Goods"
        }
    ],
    "sg:phone":"+61 8 8221 6511",
    "sg:postcode":"5000",
    "sg:province":"SA",
    "sg:tags":[
        "store"
    ],
    "wof:name":"Rockin&#039; Rooster The",
    "wof:placetype":"venue"
},
  "geometry": {"coordinates":[138.59780883799999,-34.9225654602],"type":"Point"}
}