{
  "type": "Feature",
  "properties": {
    "addr:full":"15 Menzies Ave Point Cook VIC 3030",
    "addr:housenumber":"15",
    "addr:postcode":"3030",
    "addr:street":"Menzies Ave",
    "iso:country":"AU",
    "sg:address":"15 Menzies Ave",
    "sg:city":"Point Cook",
    "sg:classifiers":[
        {
            "category":"Wholesale",
            "subcategory":"Furniture",
            "type":"Manufacturing & Wholesale Goods"
        }
    ],
    "sg:phone":"+61 3 9395 9352",
    "sg:postcode":"3030",
    "sg:province":"VIC",
    "sg:tags":[
        "wholesaler",
        "mfrs"
    ],
    "wof:name":"Impact Distributors",
    "wof:placetype":"venue"
},
  "geometry": {"coordinates":[144.73388700000001,-37.89584],"type":"Point"}
}