{
  "type": "Feature",
  "properties": {
    "addr:full":"R.M.B. 6311 Melba Hwy Glenburn VIC 3717",
    "addr:housenumber":"6311",
    "addr:postcode":"3717",
    "addr:street":"R.M.B.;Melba Hwy",
    "iso:country":"AU",
    "sg:address":"R.M.B. 6311 Melba Hwy",
    "sg:city":"Glenburn",
    "sg:classifiers":[
        {
            "category":"Building & Trades",
            "subcategory":"Construction",
            "type":"Services"
        }
    ],
    "sg:phone":"+61 3 5797 8420",
    "sg:postcode":"3717",
    "sg:province":"VIC",
    "sg:tags":[
        "contractor"
    ],
    "wof:name":"Glenburn Valley Homes",
    "wof:placetype":"venue"
},
  "geometry": {"coordinates":[145.47363281200001,-37.3827056885],"type":"Point"}
}