{
  "type": "Feature",
  "properties": {
    "iso:country":"AU",
    "sg:address":"34 Ryrie St",
    "sg:city":"Geelong",
    "sg:classifiers":[
        {
            "category":"Home & Garden",
            "subcategory":"Hardware",
            "type":"Retail Goods"
        }
    ],
    "sg:phone":"+61 3 5225 4400",
    "sg:postcode":"3220",
    "sg:province":"VIC",
    "sg:tags":[
        "manufacturer"
    ],
    "wof:name":"Geelong Sales Co Pty Ltd",
    "wof:placetype":"venue"
},
  "geometry": {"coordinates":[144.354614,-38.14801],"type":"Point"}
}