{
  "type": "Feature",
  "properties": {
    "addr:full":"75 Chadstone Rd Chadstone VIC 3148",
    "addr:housenumber":"75",
    "addr:postcode":"3148",
    "addr:street":"Chadstone Rd",
    "iso:country":"AU",
    "sg:address":"75 Chadstone Rd",
    "sg:city":"Chadstone",
    "sg:classifiers":[
        {
            "category":"Personal",
            "subcategory":"Beauty Salon",
            "type":"Services"
        }
    ],
    "sg:phone":"+61 3 9568 1970",
    "sg:postcode":"3148",
    "sg:province":"VIC",
    "sg:tags":[
        "hairdresser"
    ],
    "wof:name":"Les Images Hair & Beauty Salon Pty Ltd",
    "wof:placetype":"venue"
},
  "geometry": {"coordinates":[145.079025269,-37.8815879822],"type":"Point"}
}