{
  "type": "Feature",
  "properties": {
    "iso:country":"AU",
    "sg:address":"179 Turbot St",
    "sg:city":"Brisbane",
    "sg:classifiers":[
        {
            "category":"Building & Trades",
            "subcategory":"Construction",
            "type":"Services"
        }
    ],
    "sg:phone":"+61 7 3221 8886",
    "sg:postcode":"4000",
    "sg:province":"QLD",
    "sg:tags":[
        "management"
    ],
    "wof:name":"Amalgamated Constructions Pty Ltd",
    "wof:placetype":"venue"
},
  "geometry": {"coordinates":[153.02232360799999,-27.4681358337],"type":"Point"}
}