{
  "type": "Feature",
  "properties": {
    "addr:full":"U3/ 408 Onsdale St Melbourne VIC 3000",
    "addr:housenumber":"408",
    "addr:postcode":"3000",
    "addr:street":"U3 /;St",
    "iso:country":"AU",
    "sg:address":"U3/ 408 Onsdale St",
    "sg:city":"Melbourne",
    "sg:classifiers":[
        {
            "category":"Fast Food",
            "type":"Food & Drink"
        }
    ],
    "sg:phone":"+61 3 9670 7822",
    "sg:postcode":"3000",
    "sg:province":"VIC",
    "sg:tags":[
        "away",
        "take"
    ],
    "wof:name":"Food & Tea Gallery",
    "wof:placetype":"venue"
},
  "geometry": {"coordinates":[144.96043395999999,-37.8126678467],"type":"Point"}
}