{
  "type": "Feature",
  "properties": {
    "iso:country":"AU",
    "sg:address":"Shp19/ 2 Eighth Ave",
    "sg:city":"Palm Beach",
    "sg:classifiers":[
        {
            "category":"Restaurant",
            "type":"Food & Drink"
        }
    ],
    "sg:phone":"+61 7 5534 2388",
    "sg:postcode":"4221",
    "sg:province":"QLD",
    "wof:name":"Chinese Smorgasbord",
    "wof:placetype":"venue"
},
  "geometry": {"coordinates":[153.47279357900001,-28.1213493347],"type":"Point"}
}