{
  "type": "Feature",
  "properties": {
    "addr:full":"35- 37 Applebee St St Peters NSW 2044",
    "addr:housenumber":"37",
    "addr:postcode":"2044",
    "addr:street":"Applebee St",
    "iso:country":"AU",
    "sg:address":"35- 37 Applebee St",
    "sg:city":"St Peters",
    "sg:classifiers":[
        {
            "category":"Building & Trades",
            "subcategory":"Electrical",
            "type":"Services"
        }
    ],
    "sg:phone":"+61 2 9550 5277",
    "sg:postcode":"2044",
    "sg:province":"NSW",
    "sg:tags":[
        "harness",
        "wholesaler",
        "wire",
        "mfrs"
    ],
    "wof:name":"Garland Cables and Accessories",
    "wof:placetype":"venue"
},
  "geometry": {"coordinates":[151.17944299999999,-33.910255],"type":"Point"}
}