{
  "type": "Feature",
  "properties": {
    "iso:country":"AU",
    "sg:address":"Emu Bay Rd",
    "sg:city":"Deloraine",
    "sg:classifiers":[
        {
            "category":"Food & Beverages",
            "subcategory":"Supermarket",
            "type":"Retail Goods"
        }
    ],
    "sg:phone":"+61 3 6362 2763",
    "sg:postcode":"7304",
    "sg:province":"TAS",
    "sg:tags":[
        "grocery",
        "store"
    ],
    "wof:name":"Roelf Vos Supermarkets",
    "wof:placetype":"venue"
},
  "geometry": {"coordinates":[146.658752,-41.524761],"type":"Point"}
}