{
  "type": "Feature",
  "properties": {
    "addr:full":"142 Queen St Bendigo VIC 3550",
    "addr:housenumber":"142",
    "addr:postcode":"3550",
    "addr:street":"Queen St",
    "iso:country":"AU",
    "sg:address":"142 Queen St",
    "sg:city":"Bendigo",
    "sg:classifiers":[
        {
            "category":"Health Services",
            "subcategory":"Health Practitioner",
            "type":"Services"
        }
    ],
    "sg:phone":"+61 3 5442 1972",
    "sg:postcode":"3550",
    "sg:province":"VIC",
    "sg:tags":[
        "psychologist"
    ],
    "wof:name":"Ivan Honey & Associates",
    "wof:placetype":"venue"
},
  "geometry": {"coordinates":[144.27528381400001,-36.7648124695],"type":"Point"}
}