{
  "type": "Feature",
  "properties": {
    "addr:full":"Office 5 120 Burgundy St Heidelberg VIC 3084",
    "addr:housenumber":"120",
    "addr:postcode":"3084",
    "addr:street":"Burgundy St",
    "iso:country":"AU",
    "sg:address":"Office 5 120 Burgundy St",
    "sg:city":"Heidelberg",
    "sg:classifiers":[
        {
            "category":"Organizations",
            "subcategory":"Professional Association",
            "type":"Services"
        }
    ],
    "sg:phone":"+61 3 9458 3112",
    "sg:postcode":"3084",
    "sg:province":"VIC",
    "sg:tags":[
        "organisation",
        "business"
    ],
    "wof:name":"Heidelberg Central Traders Association",
    "wof:placetype":"venue"
},
  "geometry": {"coordinates":[145.06614685100001,-37.7560386658],"type":"Point"}
}