{
  "type": "Feature",
  "properties": {
    "addr:full":"8 Jones St Innisfail QLD 4860",
    "addr:housenumber":"8",
    "addr:postcode":"4860",
    "addr:street":"Jones St",
    "iso:country":"AU",
    "sg:address":"8 Jones St",
    "sg:city":"Innisfail",
    "sg:classifiers":[
        {
            "category":"Building & Trades",
            "subcategory":"Construction",
            "type":"Services"
        }
    ],
    "sg:phone":"+61 7 4061 1956",
    "sg:postcode":"4860",
    "sg:province":"QLD",
    "sg:tags":[
        "renovation",
        "alterations",
        "extension",
        "contractor"
    ],
    "wof:name":"Beare J F",
    "wof:placetype":"venue"
},
  "geometry": {"coordinates":[146.02734375,-17.5333652496],"type":"Point"}
}