{
  "type": "Feature",
  "properties": {
    "iso:country":"AU",
    "sg:address":"Level One 301 Coronation Drv",
    "sg:city":"Milton",
    "sg:classifiers":[
        {
            "category":"Professional",
            "subcategory":"Engineering",
            "type":"Services"
        }
    ],
    "sg:phone":"+61 7 3369 5733",
    "sg:postcode":"4064",
    "sg:province":"QLD",
    "sg:tags":[
        "electronic",
        "engineer"
    ],
    "wof:name":"Omnitronics Pty Ltd",
    "wof:placetype":"venue"
},
  "geometry": {"coordinates":[153.003814697,-27.4741306305],"type":"Point"}
}