{
  "type": "Feature",
  "properties": {
    "addr:full":"21 Mark Rd Elizabeth Vale SA 5112",
    "addr:housenumber":"21",
    "addr:postcode":"5112",
    "addr:street":"Mark Rd",
    "iso:country":"AU",
    "sg:address":"21 Mark Rd",
    "sg:city":"Elizabeth Vale",
    "sg:classifiers":[
        {
            "category":"Building & Trades",
            "subcategory":"Cleaning & Sanitation",
            "type":"Services"
        }
    ],
    "sg:phone":"+61 8 8255 8079",
    "sg:postcode":"5112",
    "sg:province":"SA",
    "sg:tags":[
        "industrial",
        "commercial",
        "contractor"
    ],
    "wof:name":"Data Cleaning Services",
    "wof:placetype":"venue"
},
  "geometry": {"coordinates":[138.66122436500001,-34.7496452332],"type":"Point"}
}