{
  "type": "Feature",
  "properties": {
    "iso:country":"AU",
    "sg:address":"15A Sutton Grange Rd",
    "sg:city":"Elphinstone",
    "sg:classifiers":[
        {
            "category":"Sports & Exercise",
            "subcategory":"Gym",
            "type":"Entertainment"
        }
    ],
    "sg:phone":"+61 438 469 511",
    "sg:postcode":"3448",
    "sg:province":"VIC",
    "sg:tags":[
        "health",
        "fitness"
    ],
    "wof:name":"Imperial Fitness Personal Training",
    "wof:placetype":"venue"
},
  "geometry": {"coordinates":[144.34005737300001,-36.9508361816],"type":"Point"}
}