{
  "type": "Feature",
  "properties": {
    "addr:full":"55 Supply Rd Edmonton QLD 4869",
    "addr:postcode":"4869",
    "addr:street":"Supply Rd",
    "iso:country":"AU",
    "sg:address":"55 Supply Rd",
    "sg:city":"Edmonton",
    "sg:classifiers":[
        {
            "category":"Building & Trades",
            "subcategory":"Landscaping Services",
            "type":"Services"
        }
    ],
    "sg:phone":"+61 7 4055 5422",
    "sg:postcode":"4869",
    "sg:province":"QLD",
    "sg:tags":[
        "control",
        "weed"
    ],
    "wof:name":"Centrogen Pty Ltd",
    "wof:placetype":"venue"
},
  "geometry": {"coordinates":[145.74305725100001,-17.0004444122],"type":"Point"}
}