{
  "type": "Feature",
  "properties": {
    "iso:country":"AU",
    "sg:address":"48 Albert St",
    "sg:city":"Warragul",
    "sg:classifiers":[
        {
            "category":"Professional",
            "subcategory":"Accounting & Tax Preparation",
            "type":"Services"
        }
    ],
    "sg:phone":"+61 3 5622 6513",
    "sg:postcode":"3820",
    "sg:province":"VIC",
    "sg:tags":[
        "bookkeeping"
    ],
    "wof:name":"Wright Books Business Services",
    "wof:placetype":"venue"
},
  "geometry": {"coordinates":[145.933594,-38.159935],"type":"Point"}
}