{
  "type": "Feature",
  "properties": {
    "addr:full":"Shellharbour Rd Warilla NSW 2528",
    "addr:postcode":"2528",
    "addr:street":"Shellharbour Rd",
    "iso:country":"AU",
    "sg:address":"Shellharbour Rd",
    "sg:city":"Warilla",
    "sg:classifiers":[
        {
            "category":"Fast Food",
            "type":"Food & Drink"
        }
    ],
    "sg:phone":"+61 2 4297 3641",
    "sg:postcode":"2528",
    "sg:province":"NSW",
    "sg:tags":[
        "away",
        "take"
    ],
    "wof:name":"McDonald's Family Restaurants",
    "wof:placetype":"venue"
},
  "geometry": {"coordinates":[150.86082458499999,-34.5494003296],"type":"Point"}
}