{
  "type": "Feature",
  "properties": {
    "addr:full":"49 Milburn St Chermside West QLD 4032",
    "addr:housenumber":"49",
    "addr:postcode":"4032",
    "addr:street":"Milburn St",
    "iso:country":"AU",
    "sg:address":"49 Milburn St",
    "sg:city":"Chermside West",
    "sg:classifiers":[
        {
            "category":"Food & Beverages",
            "subcategory":"Specialty",
            "type":"Retail Goods"
        }
    ],
    "sg:phone":"+61 7 3350 5266",
    "sg:postcode":"4032",
    "sg:province":"QLD",
    "sg:tags":[
        "delicacy"
    ],
    "wof:name":"Reimers & Davies",
    "wof:placetype":"venue"
},
  "geometry": {"coordinates":[153.01889,-27.378561],"type":"Point"}
}