{
  "type": "Feature",
  "properties": {
    "addr:full":"1 Martin St Pascoe Vale VIC 3044",
    "addr:housenumber":"1",
    "addr:postcode":"3044",
    "addr:street":"Martin St",
    "iso:country":"AU",
    "sg:address":"1 Martin St",
    "sg:city":"Pascoe Vale",
    "sg:classifiers":[
        {
            "category":"Utilities",
            "subcategory":"Electric",
            "type":"Services"
        }
    ],
    "sg:phone":"+61 412 363 669",
    "sg:postcode":"3044",
    "sg:province":"VIC",
    "sg:tags":[
        "electrical",
        "contractor"
    ],
    "wof:name":"Ian Reid Electrics",
    "wof:placetype":"venue"
},
  "geometry": {"coordinates":[144.94708251899999,-37.7226867676],"type":"Point"}
}