{
  "type": "Feature",
  "properties": {
    "addr:full":"\"Hopewood\" Ropers Rd Binnaway NSW 2395",
    "addr:postcode":"2395",
    "addr:street":"Ropers Rd",
    "iso:country":"AU",
    "sg:address":"\"Hopewood\" Ropers Rd",
    "sg:city":"Binnaway",
    "sg:classifiers":[
        {
            "category":"Real Estate",
            "subcategory":"Surveying",
            "type":"Services"
        }
    ],
    "sg:phone":"+61 2 6844 1140",
    "sg:postcode":"2395",
    "sg:province":"NSW",
    "sg:tags":[
        "surveyor",
        "land"
    ],
    "wof:name":"Keith Rhynehart",
    "wof:placetype":"venue"
},
  "geometry": {"coordinates":[149.39242553700001,-31.5528068542],"type":"Point"}
}