{
  "type": "Feature",
  "properties": {
    "addr:full":"45 Reibey St Ulverstone TAS 7315",
    "addr:housenumber":"45",
    "addr:postcode":"7315",
    "addr:street":"Reibey St",
    "iso:country":"AU",
    "sg:address":"45 Reibey St",
    "sg:city":"Ulverstone",
    "sg:classifiers":[
        {
            "category":"Shopping",
            "subcategory":"Baby Store",
            "type":"Retail Goods"
        }
    ],
    "sg:phone":"+61 3 6425 1234",
    "sg:postcode":"7315",
    "sg:province":"TAS",
    "sg:tags":[
        "wear"
    ],
    "wof:name":"Little Scallywags",
    "wof:placetype":"venue"
},
  "geometry": {"coordinates":[146.17199707,-41.1571998596],"type":"Point"}
}