{
  "type": "Feature",
  "properties": {
    "addr:full":"160 Vienna Rd Alexandra Hills QLD 4161",
    "addr:housenumber":"160",
    "addr:postcode":"4161",
    "addr:street":"Vienna Rd",
    "iso:country":"AU",
    "sg:address":"160 Vienna Rd",
    "sg:city":"Alexandra Hills",
    "sg:classifiers":[
        {
            "category":"Education",
            "subcategory":"Special Training",
            "type":"Public Place"
        }
    ],
    "sg:phone":"+61 7 3820 2077",
    "sg:postcode":"4161",
    "sg:province":"QLD",
    "sg:tags":[
        "equipment",
        "driving",
        "facility"
    ],
    "wof:name":"Driving Management Australia",
    "wof:placetype":"venue"
},
  "geometry": {"coordinates":[153.222045898,-27.5476760864],"type":"Point"}
}