{
  "type": "Feature",
  "properties": {
    "addr:full":"1429 Malvern Rd Malvern VIC 3144",
    "addr:housenumber":"1429",
    "addr:postcode":"3144",
    "addr:street":"Malvern Rd",
    "iso:country":"AU",
    "sg:address":"1429 Malvern Rd",
    "sg:city":"Malvern",
    "sg:classifiers":[
        {
            "category":"Personal",
            "type":"Services"
        }
    ],
    "sg:phone":"+61 3 9822 9866",
    "sg:postcode":"3144",
    "sg:province":"VIC",
    "sg:tags":[
        "reducing",
        "treatment",
        "weight"
    ],
    "wof:name":"A Body Basics Salon",
    "wof:placetype":"venue"
},
  "geometry": {"coordinates":[145.04173278799999,-37.853012085],"type":"Point"}
}