{
  "type": "Feature",
  "properties": {
    "addr:full":"Biboohra Rd Mareeba QLD 4880",
    "addr:postcode":"4880",
    "addr:street":"Biboohra Rd",
    "iso:country":"AU",
    "sg:address":"Biboohra Rd",
    "sg:city":"Mareeba",
    "sg:classifiers":[
        {
            "category":"Utilities",
            "subcategory":"Fuel Oil & Lpg",
            "type":"Services"
        }
    ],
    "sg:phone":"+61 7 4092 7477",
    "sg:postcode":"4880",
    "sg:province":"QLD",
    "sg:tags":[
        "merchant"
    ],
    "wof:name":"Northern Fuel & Oils",
    "wof:placetype":"venue"
},
  "geometry": {"coordinates":[145.417480469,-16.9819812775],"type":"Point"}
}