{
  "type": "Feature",
  "properties": {
    "addr:full":"PO Box 3204 McKinnon VIC 3204",
    "addr:postcode":"3204",
    "iso:country":"AU",
    "sg:address":"PO Box 3204",
    "sg:city":"McKinnon",
    "sg:classifiers":[
        {
            "category":"Professional",
            "subcategory":"Detective & Security Services",
            "type":"Services"
        }
    ],
    "sg:phone":"+61 3 9576 9575",
    "sg:postcode":"3204",
    "sg:province":"VIC",
    "sg:tags":[
        "domestic",
        "alarm",
        "commercial",
        "burglar"
    ],
    "wof:name":"A. AAABAB Telephone Outlets, ADSL, Splitters, Filters, Installed",
    "wof:placetype":"venue"
},
  "geometry": {"coordinates":[145.03956600000001,-37.91119],"type":"Point"}
}