{
  "type": "Feature",
  "properties": {
    "iso:country":"AU",
    "sg:address":"4 Bettsons Crt",
    "sg:city":"Newcomb",
    "sg:classifiers":[
        {
            "category":"Home & Garden",
            "subcategory":"Carpets & Floor Coverings",
            "type":"Retail Goods"
        }
    ],
    "sg:phone":"+61 418 106 155",
    "sg:postcode":"3219",
    "sg:province":"VIC",
    "sg:tags":[
        "tile",
        "wall",
        "layer"
    ],
    "wof:name":"Baycity Tiling",
    "wof:placetype":"venue"
},
  "geometry": {"coordinates":[144.386322022,-38.1723098755],"type":"Point"}
}