{
  "type": "Feature",
  "properties": {
    "addr:full":"Shop 19, Auto Plaza, 16 - 26 Waratah St Kirrawee NSW 2232",
    "addr:housenumber":"shop 19;16 26",
    "addr:postcode":"2232",
    "addr:street":"Auto Plaza;Waratah St",
    "iso:country":"AU",
    "sg:address":"Shop 19, Auto Plaza, 16 - 26 Waratah St",
    "sg:city":"Kirrawee",
    "sg:classifiers":[
        {
            "category":"Retail",
            "subcategory":"Auto Repair",
            "type":"Services"
        }
    ],
    "sg:phone":"+61 2 9545 2414",
    "sg:postcode":"2232",
    "sg:province":"NSW",
    "sg:tags":[
        "testing",
        "inspection",
        "motor",
        "vehicle"
    ],
    "wof:name":"Niss Serv",
    "wof:placetype":"venue"
},
  "geometry": {"coordinates":[151.07652282699999,-34.0289726257],"type":"Point"}
}