{
  "type": "Feature",
  "properties": {
    "addr:full":"16 Melba Ave Sunbury VIC 3429",
    "addr:housenumber":"16",
    "addr:postcode":"3429",
    "addr:street":"Melba Ave",
    "iso:country":"AU",
    "sg:address":"16 Melba Ave",
    "sg:city":"Sunbury",
    "sg:classifiers":[
        {
            "category":"Food & Beverages",
            "subcategory":"Supermarket",
            "type":"Retail Goods"
        }
    ],
    "sg:phone":"+61 3 9744 5179",
    "sg:postcode":"3429",
    "sg:province":"VIC",
    "sg:tags":[
        "grocery",
        "store"
    ],
    "wof:name":"Melba Supermarket",
    "wof:placetype":"venue"
},
  "geometry": {"coordinates":[144.705841064,-37.5741577148],"type":"Point"}
}