{
  "type": "Feature",
  "properties": {
    "iso:country":"AU",
    "sg:address":"Fcty1/ 5 Hi-Tech Pl",
    "sg:city":"Seaford",
    "sg:classifiers":[
        {
            "category":"Retail",
            "subcategory":"Storage",
            "type":"Services"
        }
    ],
    "sg:phone":"+61 3 9773 5455",
    "sg:postcode":"3198",
    "sg:province":"VIC",
    "wof:name":"The Vault Secured Storage",
    "wof:placetype":"venue"
},
  "geometry": {"coordinates":[145.138916016,-38.1167106628],"type":"Point"}
}