{
  "type": "Feature",
  "properties": {
    "iso:country":"AU",
    "sg:address":"7 Nola Ave",
    "sg:city":"Scarborough",
    "sg:classifiers":[
        {
            "category":"Personal",
            "subcategory":"Massage",
            "type":"Services"
        }
    ],
    "sg:phone":"+61 8 9245 6099",
    "sg:postcode":"6019",
    "sg:province":"WA",
    "sg:tags":[
        "therapy"
    ],
    "sg:website":"http://www.herbfactory.iinet.net.au",
    "wof:name":"The Herb Factory",
    "wof:placetype":"venue"
},
  "geometry": {"coordinates":[115.7631073,-31.9023361206],"type":"Point"}
}