{
  "type": "Feature",
  "properties": {
    "addr:full":"Peel St Wynnum QLD 4178",
    "addr:postcode":"4178",
    "addr:street":"Peel St",
    "iso:country":"AU",
    "sg:address":"Peel St",
    "sg:city":"Wynnum",
    "sg:classifiers":[
        {
            "category":"Education",
            "subcategory":"School",
            "type":"Public Place"
        }
    ],
    "sg:phone":"+61 7 3906 7333",
    "sg:postcode":"4178",
    "sg:province":"QLD",
    "sg:tags":[
        "state",
        "except",
        "nsw"
    ],
    "wof:name":"Wynnum High",
    "wof:placetype":"venue"
},
  "geometry": {"coordinates":[153.17706298799999,-27.4546508789],"type":"Point"}
}