{
  "type": "Feature",
  "properties": {
    "addr:full":"2695 Logan Rd Rochedale QLD 4123",
    "addr:housenumber":"2695",
    "addr:postcode":"4123",
    "addr:street":"Logan Rd",
    "iso:country":"AU",
    "sg:address":"2695 Logan Rd",
    "sg:city":"Rochedale",
    "sg:classifiers":[
        {
            "category":"Shopping",
            "subcategory":"Party Supplies",
            "type":"Retail Goods"
        }
    ],
    "sg:phone":"+61 7 3841 2346",
    "sg:postcode":"4123",
    "sg:province":"QLD",
    "sg:tags":[
        "hire",
        "costume"
    ],
    "wof:name":"A And K Costume Hire",
    "wof:placetype":"venue"
},
  "geometry": {"coordinates":[153.105911255,-27.5886268616],"type":"Point"}
}