{
  "type": "Feature",
  "properties": {
    "addr:full":"50 Smith St Collingwood VIC 3066",
    "addr:housenumber":"50",
    "addr:postcode":"3066",
    "addr:street":"Smith St",
    "iso:country":"AU",
    "sg:address":"50 Smith St",
    "sg:city":"Collingwood",
    "sg:classifiers":[
        {
            "category":"Arts & Performance",
            "subcategory":"Art Gallery",
            "type":"Entertainment"
        }
    ],
    "sg:phone":"+61 3 9417 0800",
    "sg:postcode":"3066",
    "sg:province":"VIC",
    "wof:name":"Australian Galleries Works on Paper",
    "wof:placetype":"venue"
},
  "geometry": {"coordinates":[144.98306274399999,-37.8069229126],"type":"Point"}
}