{
  "type": "Feature",
  "properties": {
    "iso:country":"AU",
    "sg:address":"Factory 3 10 Coora Rd",
    "sg:city":"Oakleigh East",
    "sg:classifiers":[
        {
            "category":"Freight",
            "type":"Transportation"
        }
    ],
    "sg:phone":"+61 3 9562 8558",
    "sg:postcode":"3166",
    "sg:province":"VIC",
    "sg:tags":[
        "car",
        "carrier",
        "transporting"
    ],
    "wof:name":"Ideal Self Storage",
    "wof:placetype":"venue"
},
  "geometry": {"coordinates":[145.120193481,-37.8897819519],"type":"Point"}
}