{
  "type": "Feature",
  "properties": {
    "iso:country":"AU",
    "sg:address":"81 Hunter St",
    "sg:city":"Newcastle",
    "sg:classifiers":[
        {
            "category":"Personal",
            "subcategory":"Beauty Salon",
            "type":"Services"
        }
    ],
    "sg:phone":"+61 2 4929 3904",
    "sg:postcode":"2300",
    "sg:province":"NSW",
    "sg:tags":[
        "hairdresser"
    ],
    "wof:name":"Antoines",
    "wof:placetype":"venue"
},
  "geometry": {"coordinates":[151.78286700000001,-32.927578],"type":"Point"}
}