{
  "type": "Feature",
  "properties": {
    "addr:full":"PO Box 447 Canterbury VIC 3126",
    "addr:postcode":"3126",
    "iso:country":"AU",
    "sg:address":"PO Box 447",
    "sg:city":"Canterbury",
    "sg:classifiers":[
        {
            "category":"Professional",
            "subcategory":"Art Services",
            "type":"Services"
        }
    ],
    "sg:phone":"+61 419 375 902",
    "sg:postcode":"3126",
    "sg:province":"VIC",
    "sg:tags":[
        "interior",
        "decorator"
    ],
    "wof:name":"Elizabeth Anne Interiors",
    "wof:placetype":"venue"
},
  "geometry": {"coordinates":[145.07310485799999,-37.8242492676],"type":"Point"}
}