{
  "type": "Feature",
  "properties": {
    "addr:full":"PO Box 634 Brentford Square VIC 3131",
    "addr:postcode":"3131",
    "addr:street":"Brentford Square",
    "iso:country":"AU",
    "sg:address":"PO Box 634",
    "sg:city":"Brentford Square",
    "sg:classifiers":[
        {
            "category":"Professional",
            "subcategory":"Employment Agencies",
            "type":"Services"
        }
    ],
    "sg:phone":"+61 3 9874 0800",
    "sg:postcode":"3131",
    "sg:province":"VIC",
    "sg:tags":[
        "consultant",
        "corrosion"
    ],
    "wof:name":"Australasian Corrosion Association",
    "wof:placetype":"venue"
},
  "geometry": {"coordinates":[145.18316650400001,-37.8370246887],"type":"Point"}
}