{
  "type": "Feature",
  "properties": {
    "iso:country":"AU",
    "sg:address":"Howe St",
    "sg:city":"Miners Rest",
    "sg:classifiers":[
        {
            "category":"Autos & Motor Vehicles",
            "subcategory":"Fuel & Gas Station",
            "type":"Retail Goods"
        }
    ],
    "sg:phone":"+61 3 5334 6855",
    "sg:postcode":"3352",
    "sg:province":"VIC",
    "wof:name":"Miners&#039; Rest Roadhouse",
    "wof:placetype":"venue"
},
  "geometry": {"coordinates":[143.80015599999999,-37.478825],"type":"Point"}
}