{
  "type": "Feature",
  "properties": {
    "addr:full":"Suite 2/ 23 Oaks Ave Dee Why NSW 2099",
    "addr:postcode":"2099",
    "addr:street":"23 Oaks Ave",
    "iso:country":"AU",
    "sg:address":"Suite 2/ 23 Oaks Ave",
    "sg:city":"Dee Why",
    "sg:classifiers":[
        {
            "category":"Health Services",
            "subcategory":"Health Practitioner",
            "type":"Services"
        }
    ],
    "sg:phone":"+61 2 9984 0945",
    "sg:postcode":"2099",
    "sg:province":"NSW",
    "sg:tags":[
        "physiotherapist"
    ],
    "sg:website":"http://www.sportsfeet.com.au",
    "wof:name":"Sports Feet",
    "wof:placetype":"venue"
},
  "geometry": {"coordinates":[151.288040161,-33.7538528442],"type":"Point"}
}