{
  "type": "Feature",
  "properties": {
    "addr:full":"Unit 1/ 35 Central park Drv Yandina QLD 4561",
    "addr:postcode":"4561",
    "addr:street":"Central Park Drv",
    "iso:country":"AU",
    "sg:address":"Unit 1/ 35 Central park Drv",
    "sg:city":"Yandina",
    "sg:classifiers":[
        {
            "category":"Building & Trades",
            "subcategory":"Construction",
            "type":"Services"
        }
    ],
    "sg:phone":"+61 7 5472 8722",
    "sg:postcode":"4561",
    "sg:province":"QLD",
    "sg:tags":[
        "welding"
    ],
    "wof:name":"Coolum Engineering & Sheetmetal Pty Ltd",
    "wof:placetype":"venue"
},
  "geometry": {"coordinates":[152.960372925,-26.5720043182],"type":"Point"}
}