{
  "type": "Feature",
  "properties": {
    "addr:full":"Allotment 2 Queen Elizabeth Drv Barmera SA 5345",
    "addr:housenumber":"2",
    "addr:postcode":"5345",
    "addr:street":"Queen Elizabeth Drv",
    "iso:country":"AU",
    "sg:address":"Allotment 2 Queen Elizabeth Drv",
    "sg:city":"Barmera",
    "sg:classifiers":[
        {
            "category":"Building & Trades",
            "subcategory":"Landscaping Services",
            "type":"Services"
        }
    ],
    "sg:phone":"+61 8 8588 7095",
    "sg:postcode":"5345",
    "sg:province":"SA",
    "sg:tags":[
        "grazier"
    ],
    "wof:name":"Pickering M J & L",
    "wof:placetype":"venue"
},
  "geometry": {"coordinates":[140.471160889,-34.2380180359],"type":"Point"}
}