{
  "type": "Feature",
  "properties": {
    "addr:full":"Benarba St Garah NSW 2405",
    "addr:postcode":"2405",
    "iso:country":"AU",
    "sg:address":"Benarba St",
    "sg:city":"Garah",
    "sg:classifiers":[
        {
            "category":"Education",
            "subcategory":"School",
            "type":"Public Place"
        }
    ],
    "sg:phone":"+61 2 6754 3218",
    "sg:postcode":"2405",
    "sg:province":"NSW",
    "sg:tags":[
        "state",
        "-",
        "nsw"
    ],
    "wof:name":"Garah Public School",
    "wof:placetype":"venue"
},
  "geometry": {"coordinates":[149.63572692899999,-29.0757408142],"type":"Point"}
}