{
  "type": "Feature",
  "properties": {
    "addr:full":"14 Oakdale Rd Gateshead NSW 2290",
    "addr:housenumber":"14",
    "addr:postcode":"2290",
    "addr:street":"Oakdale Rd",
    "iso:country":"AU",
    "sg:address":"14 Oakdale Rd",
    "sg:city":"Gateshead",
    "sg:classifiers":[
        {
            "category":"Retail",
            "subcategory":"Auto Repair",
            "type":"Services"
        }
    ],
    "sg:phone":"+61 2 4920 9988",
    "sg:postcode":"2290",
    "sg:province":"NSW",
    "sg:tags":[
        "repairer",
        "motor",
        "engineer"
    ],
    "wof:name":"Ultra Tune",
    "wof:placetype":"venue"
},
  "geometry": {"coordinates":[151.69413757300001,-32.9891357422],"type":"Point"}
}