{
  "type": "Feature",
  "properties": {
    "addr:full":"2 Orr St Queenstown TAS 7467",
    "addr:housenumber":"2",
    "addr:postcode":"7467",
    "addr:street":"Orr St",
    "iso:country":"AU",
    "sg:address":"2 Orr St",
    "sg:city":"Queenstown",
    "sg:classifiers":[
        {
            "category":"Travel",
            "subcategory":"Hotels & Motels",
            "type":"Entertainment"
        }
    ],
    "sg:phone":"+61 3 6471 1699",
    "sg:postcode":"7467",
    "sg:province":"TAS",
    "sg:tags":[
        "pub"
    ],
    "wof:name":"The Empire Hotel",
    "wof:placetype":"venue"
},
  "geometry": {"coordinates":[145.55484008799999,-42.079498291],"type":"Point"}
}