{
  "type": "Feature",
  "properties": {
    "iso:country":"AU",
    "sg:address":"53 Bingara Rd",
    "sg:city":"Beecroft",
    "sg:classifiers":[
        {
            "category":"Building & Trades",
            "subcategory":"Plumbing",
            "type":"Services"
        }
    ],
    "sg:phone":"+61 2 9868 5055",
    "sg:postcode":"2119",
    "sg:province":"NSW",
    "sg:tags":[
        "equipment",
        "valves"
    ],
    "wof:name":"Severn Glocon",
    "wof:placetype":"venue"
},
  "geometry": {"coordinates":[151.063186645,-33.7615470886],"type":"Point"}
}