{
  "type": "Feature",
  "properties": {
    "addr:full":"6/ 45 Station Rd Margaret River WA 6285",
    "addr:housenumber":"/ 45",
    "addr:postcode":"6285",
    "addr:street":"Station Rd",
    "iso:country":"AU",
    "sg:address":"6/ 45 Station Rd",
    "sg:city":"Margaret River",
    "sg:classifiers":[
        {
            "category":"Health Services",
            "subcategory":"Health Practitioner",
            "type":"Services"
        }
    ],
    "sg:phone":"+61 8 9757 9711",
    "sg:postcode":"6285",
    "sg:province":"WA",
    "sg:tags":[
        "naturopath"
    ],
    "wof:name":"Margaret River Natural Medicine",
    "wof:placetype":"venue"
},
  "geometry": {"coordinates":[115.07245636,-33.9508857727],"type":"Point"}
}