{
  "type": "Feature",
  "properties": {
    "addr:full":"Shop2/ 476 Dorset Rd Croydon South VIC 3136",
    "addr:housenumber":"476",
    "addr:postcode":"3136",
    "addr:street":"Dorset Rd",
    "iso:country":"AU",
    "sg:address":"Shop2/ 476 Dorset Rd",
    "sg:city":"Croydon South",
    "sg:classifiers":[
        {
            "category":"Fast Food",
            "type":"Food & Drink"
        }
    ],
    "sg:phone":"+61 3 9725 4408",
    "sg:postcode":"3136",
    "sg:province":"VIC",
    "sg:tags":[
        "away",
        "take"
    ],
    "wof:name":"Viva Pizzeria E Caffe",
    "wof:placetype":"venue"
},
  "geometry": {"coordinates":[145.28741455100001,-37.8162536621],"type":"Point"}
}