{
  "type": "Feature",
  "properties": {
    "iso:country":"AU",
    "sg:address":"Suite 2, Parry Village Parry Ave",
    "sg:city":"Bullcreek",
    "sg:classifiers":[
        {
            "category":"Professional",
            "subcategory":"Business Services",
            "type":"Services"
        }
    ],
    "sg:phone":"+61 8 9310 2066",
    "sg:postcode":"6149",
    "sg:province":"WA",
    "sg:tags":[
        "broker"
    ],
    "wof:name":"ABPS International",
    "wof:placetype":"venue"
},
  "geometry": {"coordinates":[115.866081,-32.056755],"type":"Point"}
}