{
  "type": "Feature",
  "properties": {
    "addr:full":"75 Mona St Auburn NSW 2144",
    "addr:housenumber":"75",
    "addr:postcode":"2144",
    "addr:street":"Mona St",
    "iso:country":"AU",
    "sg:address":"75 Mona St",
    "sg:city":"Auburn",
    "sg:classifiers":[
        {
            "category":"Building & Trades",
            "subcategory":"Construction",
            "type":"Services"
        }
    ],
    "sg:phone":"+61 2 9702 1500",
    "sg:postcode":"2144",
    "sg:province":"NSW",
    "sg:tags":[
        "waterproofing",
        "contractor"
    ],
    "wof:name":"A. Monarch Waterproofing",
    "wof:placetype":"venue"
},
  "geometry": {"coordinates":[151.02130126899999,-33.8479919434],"type":"Point"}
}