{
  "type": "Feature",
  "properties": {
    "addr:full":"22 Fulham St Toogoolawah QLD 4313",
    "addr:housenumber":"22",
    "addr:postcode":"4313",
    "addr:street":"Fulham St",
    "iso:country":"AU",
    "sg:address":"22 Fulham St",
    "sg:city":"Toogoolawah",
    "sg:classifiers":[
        {
            "category":"Insurance",
            "subcategory":"Insurance Agent",
            "type":"Services"
        }
    ],
    "sg:phone":"+61 1300 852 544",
    "sg:postcode":"4313",
    "sg:province":"QLD",
    "wof:name":"Lance Rowlands",
    "wof:placetype":"venue"
},
  "geometry": {"coordinates":[152.37681579599999,-27.0877323151],"type":"Point"}
}