{
  "type": "Feature",
  "properties": {
    "addr:full":"11 Hardy Ave Wagga Wagga NSW 2650",
    "addr:housenumber":"11",
    "addr:postcode":"2650",
    "addr:street":"Hardy Ave",
    "iso:country":"AU",
    "sg:address":"11 Hardy Ave",
    "sg:city":"Wagga Wagga",
    "sg:classifiers":[
        {
            "category":"Professional",
            "subcategory":"Art Services",
            "type":"Services"
        }
    ],
    "sg:phone":"+61 2 6925 1341",
    "sg:postcode":"2650",
    "sg:province":"NSW",
    "sg:tags":[
        "decorator",
        "painter"
    ],
    "wof:name":"Allen P.V.",
    "wof:placetype":"venue"
},
  "geometry": {"coordinates":[147.35494995100001,-35.1187477112],"type":"Point"}
}