{
  "type": "Feature",
  "properties": {
    "iso:country":"AU",
    "sg:address":"4 Macpherson St",
    "sg:city":"Cremorne",
    "sg:classifiers":[
        {
            "category":"Professional",
            "subcategory":"Art Services",
            "type":"Services"
        }
    ],
    "sg:phone":"+61 2 9904 0174",
    "sg:postcode":"2090",
    "sg:province":"NSW",
    "sg:tags":[
        "graphic",
        "designer"
    ],
    "wof:name":"Velvet Creative",
    "wof:placetype":"venue"
},
  "geometry": {"coordinates":[151.23089599599999,-33.8268814087],"type":"Point"}
}