{
  "type": "Feature",
  "properties": {
    "addr:full":"PO Box 55 Stockport SA 5410",
    "addr:postcode":"5410",
    "iso:country":"AU",
    "sg:address":"PO Box 55",
    "sg:city":"Stockport",
    "sg:classifiers":[
        {
            "category":"Building & Trades",
            "subcategory":"Landscaping Services",
            "type":"Services"
        }
    ],
    "sg:phone":"+61 438 846 019",
    "sg:postcode":"5410",
    "sg:province":"SA",
    "sg:tags":[
        "designer",
        "landscape",
        "contractor"
    ],
    "wof:name":"D & T Hill Earthworks",
    "wof:placetype":"venue"
},
  "geometry": {"coordinates":[138.732345581,-34.3344802856],"type":"Point"}
}