{
  "type": "Feature",
  "properties": {
    "addr:full":"71 Coral Drv Hampton Park VIC 3976",
    "addr:housenumber":"71",
    "addr:postcode":"3976",
    "addr:street":"Coral Drv",
    "iso:country":"AU",
    "sg:address":"71 Coral Drv",
    "sg:city":"Hampton Park",
    "sg:classifiers":[
        {
            "category":"Building & Trades",
            "subcategory":"Construction",
            "type":"Services"
        }
    ],
    "sg:phone":"+61 3 9702 9166",
    "sg:postcode":"3976",
    "sg:province":"VIC",
    "sg:tags":[
        "home",
        "air conditioning"
    ],
    "wof:name":"Anthony Air Conditioning & Refrigeration",
    "wof:placetype":"venue"
},
  "geometry": {"coordinates":[145.271759033,-38.0376548767],"type":"Point"}
}