{
  "type": "Feature",
  "properties": {
    "iso:country":"AU",
    "sg:address":"43 Hooper Rd",
    "sg:city":"Strathalbyn",
    "sg:classifiers":[
        {
            "category":"Professional",
            "subcategory":"Art Services",
            "type":"Services"
        }
    ],
    "sg:phone":"+61 407 362 501",
    "sg:postcode":"5255",
    "sg:province":"SA",
    "sg:tags":[
        "decorator",
        "painter"
    ],
    "wof:name":"Strath Painting & General Repairs",
    "wof:placetype":"venue"
},
  "geometry": {"coordinates":[138.897140503,-35.2628250122],"type":"Point"}
}