{
  "type": "Feature",
  "properties": {
    "addr:full":"28 Cleland Ave Dulwich SA 5065",
    "addr:housenumber":"28",
    "addr:postcode":"5065",
    "addr:street":"Cleland Ave",
    "iso:country":"AU",
    "sg:address":"28 Cleland Ave",
    "sg:city":"Dulwich",
    "sg:classifiers":[
        {
            "category":"Real Estate",
            "subcategory":"Architect",
            "type":"Services"
        }
    ],
    "sg:phone":"+61 8 8333 3035",
    "sg:postcode":"5065",
    "sg:province":"SA",
    "wof:name":"John Gallagher Architects",
    "wof:placetype":"venue"
},
  "geometry": {"coordinates":[138.62971496599999,-34.9381904602],"type":"Point"}
}