{
  "type": "Feature",
  "properties": {
    "iso:country":"AU",
    "sg:address":"55 Broadway St",
    "sg:city":"Chelsea",
    "sg:classifiers":[
        {
            "category":"Health Services",
            "subcategory":"Nursing And Care Facility",
            "type":"Services"
        }
    ],
    "sg:phone":"+61 3 9782 7000",
    "sg:postcode":"3196",
    "sg:province":"VIC",
    "sg:tags":[
        "home"
    ],
    "wof:name":"Chelsea Park Nursing Home",
    "wof:placetype":"venue"
},
  "geometry": {"coordinates":[145.125823975,-38.0579376221],"type":"Point"}
}