{
  "type": "Feature",
  "properties": {
    "addr:full":"Lot 9 Princes Hwy Newmerella VIC 3886",
    "addr:postcode":"3886",
    "addr:street":"Princes Hwy",
    "iso:country":"AU",
    "sg:address":"Lot 9 Princes Hwy",
    "sg:city":"Newmerella",
    "sg:classifiers":[
        {
            "category":"Utilities",
            "subcategory":"Electric",
            "type":"Services"
        }
    ],
    "sg:phone":"+61 3 5154 1544",
    "sg:postcode":"3886",
    "sg:province":"VIC",
    "sg:tags":[
        "electrical",
        "contractor"
    ],
    "wof:name":"&#034;Mectec&#034; Mekken",
    "wof:placetype":"venue"
},
  "geometry": {"coordinates":[148.43801879899999,-37.7321815491],"type":"Point"}
}