{
  "type": "Feature",
  "properties": {
    "addr:full":"31 Parkhill Rd Kew VIC 3101",
    "addr:housenumber":"31",
    "addr:postcode":"3101",
    "addr:street":"Parkhill Rd",
    "iso:country":"AU",
    "sg:address":"31 Parkhill Rd",
    "sg:city":"Kew",
    "sg:classifiers":[
        {
            "category":"Personal",
            "subcategory":"Massage",
            "type":"Services"
        }
    ],
    "sg:phone":"+61 3 9817 7636",
    "sg:postcode":"3101",
    "sg:province":"VIC",
    "sg:tags":[
        "therapy"
    ],
    "wof:name":"Alice Scully Massage Therapy",
    "wof:placetype":"venue"
},
  "geometry": {"coordinates":[145.049102783,-37.804889679],"type":"Point"}
}