{
  "type": "Feature",
  "properties": {
    "addr:full":"Shp 1/ 22 Toallo St Pambula NSW 2549",
    "addr:housenumber":"/ 22",
    "addr:postcode":"2549",
    "addr:street":"Toallo St",
    "iso:country":"AU",
    "sg:address":"Shp 1/ 22 Toallo St",
    "sg:city":"Pambula",
    "sg:classifiers":[
        {
            "category":"Restaurant",
            "type":"Food & Drink"
        }
    ],
    "sg:phone":"+61 2 6495 7012",
    "sg:postcode":"2549",
    "sg:province":"NSW",
    "wof:name":"Cafe Lush Pambula",
    "wof:placetype":"venue"
},
  "geometry": {"coordinates":[149.87355041500001,-36.9291496277],"type":"Point"}
}