{
  "type": "Feature",
  "properties": {
    "addr:full":"Shop 19A Kellyville Plaza, 90 Wrights Rd Kellyville NSW 2155",
    "addr:housenumber":"19a;90",
    "addr:postcode":"2155",
    "addr:street":"Plaza;Wrights Rd",
    "iso:country":"AU",
    "sg:address":"Shop 19A Kellyville Plaza, 90 Wrights Rd",
    "sg:city":"Kellyville",
    "sg:classifiers":[
        {
            "category":"Banks & Credit Unions",
            "subcategory":"Bank",
            "type":"Services"
        }
    ],
    "sg:phone":"+61 2 8884 8999",
    "sg:postcode":"2155",
    "sg:province":"NSW",
    "wof:name":"Bank of Queensland Limited",
    "wof:placetype":"venue"
},
  "geometry": {"coordinates":[150.971755981,-33.7144927979],"type":"Point"}
}