{
  "type": "Feature",
  "properties": {
    "addr:full":"27 Wonersh St Carina West QLD 4152",
    "addr:housenumber":"27",
    "addr:postcode":"4152",
    "addr:street":"Wonersh St",
    "iso:country":"AU",
    "sg:address":"27 Wonersh St",
    "sg:city":"Carina West",
    "sg:classifiers":[
        {
            "category":"Education",
            "subcategory":"Music School",
            "type":"Public Place"
        }
    ],
    "sg:phone":"+61 7 3324 8795",
    "sg:postcode":"4152",
    "sg:province":"QLD",
    "sg:tags":[
        "teacher"
    ],
    "wof:name":"Expressions Music",
    "wof:placetype":"venue"
},
  "geometry": {"coordinates":[153.07696533199999,-27.50041008],"type":"Point"}
}