{
  "type": "Feature",
  "properties": {
    "addr:full":"344 Bulwara Rd Ultimo NSW 2007",
    "addr:housenumber":"344",
    "addr:postcode":"2007",
    "addr:street":"Bulwara Rd",
    "iso:country":"AU",
    "sg:address":"344 Bulwara Rd",
    "sg:city":"Ultimo",
    "sg:classifiers":[
        {
            "category":"Education",
            "subcategory":"University",
            "type":"Public Place"
        }
    ],
    "sg:phone":"+61 2 9211 1411",
    "sg:postcode":"2007",
    "sg:province":"NSW",
    "sg:tags":[
        "educational",
        "organisation",
        "cultural"
    ],
    "wof:name":"Australian Association of Oriental Studies Pty Ltd",
    "wof:placetype":"venue"
},
  "geometry": {"coordinates":[151.198852539,-33.8799552917],"type":"Point"}
}