{
  "type": "Feature",
  "properties": {
    "addr:full":"87 Main St Blacktown NSW 2148",
    "addr:housenumber":"87",
    "addr:postcode":"2148",
    "addr:street":"Main St",
    "iso:country":"AU",
    "sg:address":"87 Main St",
    "sg:city":"Blacktown",
    "sg:classifiers":[
        {
            "category":"Health Services",
            "subcategory":"Dentist",
            "type":"Services"
        }
    ],
    "sg:phone":"+61 2 9831 2502",
    "sg:postcode":"2148",
    "sg:province":"NSW",
    "wof:name":"Abdollahi H Dr.",
    "wof:placetype":"venue"
},
  "geometry": {"coordinates":[150.909912109,-33.7704277039],"type":"Point"}
}