{
  "type": "Feature",
  "properties": {
    "addr:full":"Crn Mitchell Rd & Harley St Alexandria NSW 2015",
    "addr:postcode":"2015",
    "addr:street":"Crn Mitchell Rd & Harley St",
    "iso:country":"AU",
    "sg:address":"Crn Mitchell Rd & Harley St",
    "sg:city":"Alexandria",
    "sg:classifiers":[
        {
            "category":"Restaurant",
            "type":"Food & Drink"
        }
    ],
    "sg:phone":"+61 2 9557 1924",
    "sg:postcode":"2015",
    "sg:province":"NSW",
    "wof:name":"Parkview Hotel Terrace Restaurant",
    "wof:placetype":"venue"
},
  "geometry": {"coordinates":[151.19137573200001,-33.9028892517],"type":"Point"}
}