{
  "type": "Feature",
  "properties": {
    "addr:full":"Unit 1, 91 Tulip St Cheltenham VIC 3192",
    "addr:housenumber":"91",
    "addr:postcode":"3192",
    "addr:street":"Tulip St",
    "iso:country":"AU",
    "sg:address":"Unit 1, 91 Tulip St",
    "sg:city":"Cheltenham",
    "sg:classifiers":[
        {
            "category":"Building & Trades",
            "subcategory":"Construction",
            "type":"Services"
        }
    ],
    "sg:phone":"+61 3 9585 3811",
    "sg:postcode":"3192",
    "sg:province":"VIC",
    "sg:tags":[
        "industrial",
        "commercial",
        "air conditioning"
    ],
    "wof:name":"Custom Airconditioning (Vic) Pty Ltd",
    "wof:placetype":"venue"
},
  "geometry": {"coordinates":[145.034667969,-37.9636421204],"type":"Point"}
}