{
  "type": "Feature",
  "properties": {
    "addr:full":"3245 Logan Rd Underwood QLD 4119",
    "addr:housenumber":"3245",
    "addr:postcode":"4119",
    "addr:street":"Logan Rd",
    "iso:country":"AU",
    "sg:address":"3245 Logan Rd",
    "sg:city":"Underwood",
    "sg:classifiers":[
        {
            "category":"Shopping",
            "subcategory":"Computers & Home Electronics",
            "type":"Retail Goods"
        }
    ],
    "sg:phone":"+61 7 3341 0844",
    "sg:postcode":"4119",
    "sg:province":"QLD",
    "sg:tags":[
        "small",
        "equipment",
        "business"
    ],
    "wof:name":"Dick Smith Electronics",
    "wof:placetype":"venue"
},
  "geometry": {"coordinates":[153.112060547,-27.6087226868],"type":"Point"}
}