{
  "type": "Feature",
  "properties": {
    "addr:full":"15 Wyee Farms Rd Wyee NSW 2259",
    "addr:housenumber":"15",
    "addr:postcode":"2259",
    "addr:street":"Wyee Farms Rd",
    "iso:country":"AU",
    "sg:address":"15 Wyee Farms Rd",
    "sg:city":"Wyee",
    "sg:classifiers":[
        {
            "category":"Personal",
            "subcategory":"Massage",
            "type":"Services"
        }
    ],
    "sg:phone":"+61 2 4357 2173",
    "sg:postcode":"2259",
    "sg:province":"NSW",
    "sg:tags":[
        "therapy"
    ],
    "wof:name":"Collins Gerald Andrew",
    "wof:placetype":"venue"
},
  "geometry": {"coordinates":[151.460540772,-33.1782035828],"type":"Point"}
}