{
  "type": "Feature",
  "properties": {
    "addr:full":"16 Ryan St Belgian Gardens QLD 4810",
    "addr:housenumber":"16",
    "addr:postcode":"4810",
    "addr:street":"Ryan St",
    "iso:country":"AU",
    "sg:address":"16 Ryan St",
    "sg:city":"Belgian Gardens",
    "sg:classifiers":[
        {
            "category":"Personal",
            "subcategory":"Massage",
            "type":"Services"
        }
    ],
    "sg:phone":"+61 418 729 940",
    "sg:postcode":"4810",
    "sg:province":"QLD",
    "sg:tags":[
        "therapy"
    ],
    "wof:name":"Chris Mitchell",
    "wof:placetype":"venue"
},
  "geometry": {"coordinates":[146.79943800000001,-19.243198],"type":"Point"}
}