{
  "type": "Feature",
  "properties": {
    "addr:full":"1592 Burwood Hwy Tecoma VIC 3160",
    "addr:housenumber":"1592",
    "addr:postcode":"3160",
    "addr:street":"Burwood Hwy",
    "iso:country":"AU",
    "sg:address":"1592 Burwood Hwy",
    "sg:city":"Tecoma",
    "sg:classifiers":[
        {
            "category":"Health Services",
            "subcategory":"Health Practitioner",
            "type":"Services"
        }
    ],
    "sg:phone":"+61 3 9754 4088",
    "sg:postcode":"3160",
    "sg:province":"VIC",
    "sg:tags":[
        "osteopath"
    ],
    "wof:name":"Mackay T J",
    "wof:placetype":"venue"
},
  "geometry": {"coordinates":[145.34866332999999,-37.9077796936],"type":"Point"}
}