{
  "type": "Feature",
  "properties": {
    "addr:full":"17 Gannet St Mt Eliza VIC 3930",
    "addr:housenumber":"17",
    "addr:postcode":"3930",
    "addr:street":"Gannet St",
    "iso:country":"AU",
    "sg:address":"17 Gannet St",
    "sg:city":"Mt Eliza",
    "sg:classifiers":[
        {
            "category":"Real Estate",
            "subcategory":"Surveying",
            "type":"Services"
        }
    ],
    "sg:phone":"+61 3 9787 5501",
    "sg:postcode":"3930",
    "sg:province":"VIC",
    "sg:tags":[
        "surveyor",
        "land"
    ],
    "wof:name":"Reay Andrew",
    "wof:placetype":"venue"
},
  "geometry": {"coordinates":[145.081832886,-38.1998672485],"type":"Point"}
}