{
  "type": "Feature",
  "properties": {
    "iso:country":"AU",
    "sg:address":"223 -227 Sunshine Rd",
    "sg:city":"Tottenham",
    "sg:classifiers":[
        {
            "category":"Landmark",
            "subcategory":"Fountain",
            "type":"Public Place"
        }
    ],
    "sg:phone":"+61 3 9325 1111",
    "sg:postcode":"3012",
    "sg:province":"VIC",
    "sg:tags":[
        "wholesaler",
        "spring",
        "mfrs"
    ],
    "wof:name":"Jacob Springs Footscray",
    "wof:placetype":"venue"
},
  "geometry": {"coordinates":[144.850708008,-37.7985115051],"type":"Point"}
}