{
  "type": "Feature",
  "properties": {
    "addr:full":"73 Malpas St Preston VIC 3072",
    "addr:housenumber":"73",
    "addr:postcode":"3072",
    "addr:street":"Malpas St",
    "iso:country":"AU",
    "sg:address":"73 Malpas St",
    "sg:city":"Preston",
    "sg:classifiers":[
        {
            "category":"Professional",
            "type":"Services"
        }
    ],
    "sg:phone":"+61 412 375 633",
    "sg:postcode":"3072",
    "sg:province":"VIC",
    "sg:tags":[
        "courier"
    ],
    "wof:name":"Duc&#039;tell International",
    "wof:placetype":"venue"
},
  "geometry": {"coordinates":[145.01754760700001,-37.7339286804],"type":"Point"}
}