{
  "type": "Feature",
  "properties": {
    "addr:full":"4 Cambridge St Willoughby North NSW 2068",
    "addr:housenumber":"4",
    "addr:postcode":"2068",
    "addr:street":"Cambridge St",
    "iso:country":"AU",
    "sg:address":"4 Cambridge St",
    "sg:city":"Willoughby North",
    "sg:classifiers":[
        {
            "category":"Military Area",
            "subcategory":"Air Force Base",
            "type":"Public Place"
        }
    ],
    "sg:phone":"+61 2 9417 8866",
    "sg:postcode":"2068",
    "sg:province":"NSW",
    "sg:tags":[
        "fibre",
        "optic"
    ],
    "wof:name":"Ardayne Engineering Pty Ltd",
    "wof:placetype":"venue"
},
  "geometry": {"coordinates":[151.203781128,-33.7926559448],"type":"Point"}
}