{
  "type": "Feature",
  "properties": {
    "addr:full":"Woodland Ave Oxley Park NSW 2760",
    "addr:postcode":"2760",
    "addr:street":"Woodland Ave Oxley",
    "iso:country":"AU",
    "sg:address":"Woodland Ave",
    "sg:city":"Oxley Park",
    "sg:classifiers":[
        {
            "category":"Social Services",
            "subcategory":"Child Care",
            "type":"Services"
        }
    ],
    "sg:phone":"+61 2 9833 2431",
    "sg:postcode":"2760",
    "sg:province":"NSW",
    "wof:name":"Ridge- EE - Didge Child Care Centre",
    "wof:placetype":"venue"
},
  "geometry": {"coordinates":[150.793212891,-33.7737693787],"type":"Point"}
}