{
  "type": "Feature",
  "properties": {
    "iso:country":"AU",
    "sg:address":"143 Bell St",
    "sg:city":"Preston",
    "sg:classifiers":[
        {
            "category":"Shopping",
            "subcategory":"Computers & Home Electronics",
            "type":"Retail Goods"
        }
    ],
    "sg:phone":"+61 3 9484 9433",
    "sg:postcode":"3072",
    "sg:province":"VIC",
    "sg:tags":[
        "equipment",
        "multimedia"
    ],
    "wof:name":"IDEC",
    "wof:placetype":"venue"
},
  "geometry": {"coordinates":[145.01539611800001,-37.7466087341],"type":"Point"}
}