{
  "type": "Feature",
  "properties": {
    "iso:country":"AU",
    "sg:address":"Unit 7 35 Austin Ave",
    "sg:city":"Maddington",
    "sg:classifiers":[
        {
            "category":"Building & Trades",
            "subcategory":"Construction",
            "type":"Services"
        }
    ],
    "sg:phone":"+61 412 199 649",
    "sg:postcode":"6109",
    "sg:province":"WA",
    "sg:tags":[
        "repairing",
        "window"
    ],
    "wof:name":"Geary F J & S M",
    "wof:placetype":"venue"
},
  "geometry": {"coordinates":[115.98045349100001,-32.0427780151],"type":"Point"}
}