{
  "type": "Feature",
  "properties": {
    "addr:full":"122 Bridge St Benalla VIC 3671",
    "addr:housenumber":"122",
    "addr:postcode":"3671",
    "addr:street":"Bridge St",
    "iso:country":"AU",
    "sg:address":"122 Bridge St",
    "sg:city":"Benalla",
    "sg:classifiers":[
        {
            "category":"Professional",
            "subcategory":"Computer Services",
            "type":"Services"
        }
    ],
    "sg:phone":"+61 3 5761 3700",
    "sg:postcode":"3671",
    "sg:province":"VIC",
    "sg:tags":[
        "consultant",
        "system"
    ],
    "wof:name":"HumeNet Ltd",
    "wof:placetype":"venue"
},
  "geometry": {"coordinates":[145.987595,-36.550919],"type":"Point"}
}