{
  "type": "Feature",
  "properties": {
    "addr:full":"486 Albion St Brunswick West VIC 3055",
    "addr:housenumber":"486",
    "addr:postcode":"3055",
    "addr:street":"Albion St",
    "iso:country":"AU",
    "sg:address":"486 Albion St",
    "sg:city":"Brunswick West",
    "sg:classifiers":[
        {
            "category":"Professional",
            "subcategory":"Printing & Photocopies",
            "type":"Services"
        }
    ],
    "sg:phone":"+61 3 9384 0044",
    "sg:postcode":"3055",
    "sg:province":"VIC",
    "sg:tags":[
        "screen",
        "printer"
    ],
    "wof:name":"S.A.R. Screen Printers Pty Ltd",
    "wof:placetype":"venue"
},
  "geometry": {"coordinates":[144.93934631400001,-37.7581214905],"type":"Point"}
}