{
  "type": "Feature",
  "properties": {
    "iso:country":"AU",
    "sg:address":"29 Onslow St",
    "sg:city":"Canterbury",
    "sg:classifiers":[
        {
            "category":"Retail",
            "subcategory":"Auto Repair",
            "type":"Services"
        }
    ],
    "sg:phone":"+61 2 9789 1753",
    "sg:postcode":"2193",
    "sg:province":"NSW",
    "sg:tags":[
        "repairer",
        "motor",
        "engineer"
    ],
    "wof:name":"TruckofHorsepower Automotive Mechanical Repairs",
    "wof:placetype":"venue"
},
  "geometry": {"coordinates":[151.11189300000001,-33.91777],"type":"Point"}
}