{
  "type": "Feature",
  "properties": {
    "addr:full":"Market Pl Camberwell VIC 3124",
    "addr:postcode":"3124",
    "addr:street":"Market Pl",
    "iso:country":"AU",
    "sg:address":"Market Pl",
    "sg:city":"Camberwell",
    "sg:classifiers":[
        {
            "category":"Fast Food",
            "type":"Food & Drink"
        }
    ],
    "sg:phone":"+61 3 9882 9090",
    "sg:postcode":"3124",
    "sg:province":"VIC",
    "sg:tags":[
        "away",
        "take"
    ],
    "wof:name":"Legs &#039;n&#039; Breasts Pty Ltd",
    "wof:placetype":"venue"
},
  "geometry": {"coordinates":[145.057693481,-37.8299179077],"type":"Point"}
}