{
  "type": "Feature",
  "properties": {
    "iso:country":"AU",
    "sg:address":"Lvl2/ 212 King St",
    "sg:city":"Melbourne",
    "sg:classifiers":[
        {
            "category":"Education",
            "subcategory":"Special Training",
            "type":"Public Place"
        }
    ],
    "sg:phone":"+61 3 9600 4220",
    "sg:postcode":"3000",
    "sg:province":"VIC",
    "sg:tags":[
        "college",
        "hairdressing"
    ],
    "wof:name":"Southern Cross College Of Vocational Education",
    "wof:placetype":"venue"
},
  "geometry": {"coordinates":[144.955322266,-37.8150863647],"type":"Point"}
}