{
  "type": "Feature",
  "properties": {
    "addr:full":"262b Brunker Rd Adamstown NSW 2289",
    "addr:housenumber":"262b",
    "addr:postcode":"2289",
    "addr:street":"Brunker Rd",
    "iso:country":"AU",
    "sg:address":"262b Brunker Rd",
    "sg:city":"Adamstown",
    "sg:classifiers":[
        {
            "category":"Shopping",
            "subcategory":"Optical Goods",
            "type":"Retail Goods"
        }
    ],
    "sg:phone":"+61 2 4957 7455",
    "sg:postcode":"2289",
    "sg:province":"NSW",
    "sg:tags":[
        "supply"
    ],
    "wof:name":"Rodgers Optical Services",
    "wof:placetype":"venue"
},
  "geometry": {"coordinates":[151.72561645499999,-32.9348716736],"type":"Point"}
}