{
  "type": "Feature",
  "properties": {
    "addr:full":"67 Crockford St Port Melbourne VIC 3207",
    "addr:housenumber":"67",
    "addr:postcode":"3207",
    "addr:street":"Crockford St",
    "iso:country":"AU",
    "sg:address":"67 Crockford St",
    "sg:city":"Port Melbourne",
    "sg:classifiers":[
        {
            "category":"Autos & Motor Vehicles",
            "subcategory":"Automobile Sales",
            "type":"Retail Goods"
        }
    ],
    "sg:phone":"+61 3 9646 7422",
    "sg:postcode":"3207",
    "sg:province":"VIC",
    "sg:tags":[
        "car",
        "used"
    ],
    "wof:name":"Peter Wright's Cars",
    "wof:placetype":"venue"
},
  "geometry": {"coordinates":[144.94885300000001,-37.834087],"type":"Point"}
}