{
  "type": "Feature",
  "properties": {
    "addr:full":"7 Packham St Box Hill North VIC 3129",
    "addr:housenumber":"7",
    "addr:postcode":"3129",
    "addr:street":"Packham St",
    "iso:country":"AU",
    "sg:address":"7 Packham St",
    "sg:city":"Box Hill North",
    "sg:classifiers":[
        {
            "category":"Shopping",
            "subcategory":"Crafts & Fabrics",
            "type":"Retail Goods"
        }
    ],
    "sg:phone":"+61 3 9898 4369",
    "sg:postcode":"3129",
    "sg:province":"VIC",
    "sg:tags":[
        "supply"
    ],
    "wof:name":"Margarets Bears & Wombats",
    "wof:placetype":"venue"
},
  "geometry": {"coordinates":[145.139160156,-37.8080673218],"type":"Point"}
}