{
  "type": "Feature",
  "properties": {
    "addr:full":"7 Beaumont St Kingsgrove NSW 2208",
    "addr:housenumber":"7",
    "addr:postcode":"2208",
    "addr:street":"Beaumont St",
    "iso:country":"AU",
    "sg:address":"7 Beaumont St",
    "sg:city":"Kingsgrove",
    "sg:classifiers":[
        {
            "category":"Farming",
            "subcategory":"Fish & Marine Products",
            "type":"Manufacturing & Wholesale Goods"
        }
    ],
    "sg:phone":"+61 2 9554 8360",
    "sg:postcode":"2208",
    "sg:province":"NSW",
    "sg:tags":[
        "chemical",
        "supplier"
    ],
    "wof:name":"Ranachem Specialty Suppliers",
    "wof:placetype":"venue"
},
  "geometry": {"coordinates":[151.10682700000001,-33.937805],"type":"Point"}
}