{
  "type": "Feature",
  "properties": {
    "addr:full":"Suite 5 8 Pacific Pde Dee Why NSW 2099",
    "addr:housenumber":"8",
    "addr:postcode":"2099",
    "addr:street":"Pacific Pde",
    "iso:country":"AU",
    "sg:address":"Suite 5 8 Pacific Pde",
    "sg:city":"Dee Why",
    "sg:classifiers":[
        {
            "category":"Health Services",
            "subcategory":"Doctor",
            "type":"Services"
        }
    ],
    "sg:phone":"+61 2 9519 8301",
    "sg:postcode":"2099",
    "sg:province":"NSW",
    "sg:tags":[
        "medical",
        "practitioner"
    ],
    "wof:name":"Pressley Lynne",
    "wof:placetype":"venue"
},
  "geometry": {"coordinates":[151.28489685100001,-33.7543449402],"type":"Point"}
}