{
  "type": "Feature",
  "properties": {
    "addr:full":"12- 14 Sperry Rd Tullamarine VIC 3043",
    "addr:housenumber":"14",
    "addr:postcode":"3043",
    "addr:street":"Sperry Rd",
    "iso:country":"AU",
    "sg:address":"12- 14 Sperry Rd",
    "sg:city":"Tullamarine",
    "sg:classifiers":[
        {
            "category":"Military Area",
            "subcategory":"Naval Base",
            "type":"Public Place"
        }
    ],
    "sg:phone":"+61 3 9330 2787",
    "sg:postcode":"3043",
    "sg:province":"VIC",
    "sg:tags":[
        "stand",
        "rack"
    ],
    "wof:name":"Spacerack Storage Systems",
    "wof:placetype":"venue"
},
  "geometry": {"coordinates":[144.87413024899999,-37.6951141357],"type":"Point"}
}