{
  "type": "Feature",
  "properties": {
    "addr:full":"PO Box 197 Glebe NSW 2037",
    "addr:postcode":"2037",
    "iso:country":"AU",
    "sg:address":"PO Box 197",
    "sg:city":"Glebe",
    "sg:classifiers":[
        {
            "category":"Organizations",
            "subcategory":"Non-profit Organization",
            "type":"Services"
        }
    ],
    "sg:phone":"+61 2 9571 9900",
    "sg:postcode":"2037",
    "sg:province":"NSW",
    "sg:tags":[
        "support",
        "disability",
        "organisation"
    ],
    "wof:name":"Care1",
    "wof:placetype":"venue"
},
  "geometry": {"coordinates":[151.184936523,-33.8772010803],"type":"Point"}
}