{
  "type": "Feature",
  "properties": {
    "iso:country":"AU",
    "sg:address":"32 Gilbert St",
    "sg:city":"Torquay",
    "sg:classifiers":[
        {
            "category":"Shopping",
            "subcategory":"Clothing, Apparel, & Fashions",
            "type":"Retail Goods"
        }
    ],
    "sg:phone":"+61 3 5261 3010",
    "sg:postcode":"3228",
    "sg:province":"VIC",
    "sg:tags":[
        "lady",
        "wear"
    ],
    "wof:name":"Collections",
    "wof:placetype":"venue"
},
  "geometry": {"coordinates":[144.323837,-38.331917],"type":"Point"}
}