{
  "type": "Feature",
  "properties": {
    "addr:full":"768 Tinonee Rd Tinonee NSW 2430",
    "addr:housenumber":"768",
    "addr:postcode":"2430",
    "addr:street":"Tinonee Rd",
    "iso:country":"AU",
    "sg:address":"768 Tinonee Rd",
    "sg:city":"Tinonee",
    "sg:classifiers":[
        {
            "category":"Farming",
            "subcategory":"Nursery",
            "type":"Manufacturing & Wholesale Goods"
        }
    ],
    "sg:phone":"+61 2 6553 1012",
    "sg:postcode":"2430",
    "sg:province":"NSW",
    "wof:name":"Clement Ray & L",
    "wof:placetype":"venue"
},
  "geometry": {"coordinates":[152.40458699999999,-31.924353],"type":"Point"}
}