{
  "type": "Feature",
  "properties": {
    "addr:full":"Suite 31/ 136 Canterbury Rd Heathmont VIC 3135",
    "addr:housenumber":"31 / 136",
    "addr:postcode":"3135",
    "addr:street":"Canterbury Rd",
    "iso:country":"AU",
    "sg:address":"Suite 31/ 136 Canterbury Rd",
    "sg:city":"Heathmont",
    "sg:classifiers":[
        {
            "category":"Sports & Exercise",
            "subcategory":"Gym",
            "type":"Entertainment"
        }
    ],
    "sg:phone":"+61 3 9738 2555",
    "sg:postcode":"3135",
    "sg:province":"VIC",
    "sg:tags":[
        "personal",
        "trainer",
        "fitness"
    ],
    "wof:name":"Supertone Personal Training",
    "wof:placetype":"venue"
},
  "geometry": {"coordinates":[145.246658325,-37.8283729553],"type":"Point"}
}