{
  "type": "Feature",
  "properties": {
    "iso:country":"AU",
    "sg:address":"Suite 6, Level 9, 416 Collins St",
    "sg:city":"Melbourne",
    "sg:classifiers":[
        {
            "category":"Banks & Credit Unions",
            "subcategory":"Investment Brokerage",
            "type":"Services"
        }
    ],
    "sg:phone":"+61 3 9725 7528",
    "sg:postcode":"3000",
    "sg:province":"VIC",
    "sg:tags":[
        "finance",
        "broker"
    ],
    "wof:name":"All Asset Finance",
    "wof:placetype":"venue"
},
  "geometry": {"coordinates":[144.96043395999999,-37.8171272278],"type":"Point"}
}