{
  "type": "Feature",
  "properties": {
    "iso:country":"AU",
    "sg:address":"868 Mountain Hwy",
    "sg:city":"Bayswater",
    "sg:classifiers":[
        {
            "category":"Building & Trades",
            "subcategory":"Construction",
            "type":"Services"
        }
    ],
    "sg:phone":"+61 3 9720 3600",
    "sg:postcode":"3153",
    "sg:province":"VIC",
    "sg:tags":[
        "pool",
        "swimming"
    ],
    "wof:name":"Omega Pools and Spas Pty Ltd",
    "wof:placetype":"venue"
},
  "geometry": {"coordinates":[145.277252197,-37.8383407593],"type":"Point"}
}