{
  "type": "Feature",
  "properties": {
    "iso:country":"AU",
    "sg:address":"Nelson Plz Stockton St",
    "sg:city":"Nelson Bay",
    "sg:classifiers":[
        {
            "category":"Health Services",
            "subcategory":"Health Practitioner",
            "type":"Services"
        }
    ],
    "sg:phone":"+61 2 4984 2455",
    "sg:postcode":"2315",
    "sg:province":"NSW",
    "sg:tags":[
        "physiotherapist"
    ],
    "wof:name":"Ryan Helen",
    "wof:placetype":"venue"
},
  "geometry": {"coordinates":[152.143295,-32.722809],"type":"Point"}
}