{
  "type": "Feature",
  "properties": {
    "addr:full":"11 Spencer St Yokine WA 6060",
    "addr:housenumber":"11",
    "addr:postcode":"6060",
    "addr:street":"Spencer St",
    "iso:country":"AU",
    "sg:address":"11 Spencer St",
    "sg:city":"Yokine",
    "sg:classifiers":[
        {
            "category":"Building & Trades",
            "subcategory":"Construction",
            "type":"Services"
        }
    ],
    "sg:phone":"+61 8 9242 4122",
    "sg:postcode":"6060",
    "sg:province":"WA",
    "sg:tags":[
        "contractor"
    ],
    "wof:name":"R.K.M. Builders",
    "wof:placetype":"venue"
},
  "geometry": {"coordinates":[115.85777282700001,-31.9034442902],"type":"Point"}
}