{
  "type": "Feature",
  "properties": {
    "addr:full":"48 Anakie Drv Cornubia QLD 4130",
    "addr:housenumber":"48",
    "addr:postcode":"4130",
    "addr:street":"Anakie Drv",
    "iso:country":"AU",
    "sg:address":"48 Anakie Drv",
    "sg:city":"Cornubia",
    "sg:classifiers":[
        {
            "category":"Building & Trades",
            "subcategory":"Cleaning & Sanitation",
            "type":"Services"
        }
    ],
    "sg:phone":"+61 7 3801 1265",
    "sg:postcode":"4130",
    "sg:province":"QLD",
    "sg:tags":[
        "industrial",
        "commercial",
        "contractor"
    ],
    "wof:name":"Fonsbate Cleaning Services Pty Ltd",
    "wof:placetype":"venue"
},
  "geometry": {"coordinates":[153.192169189,-27.6638507843],"type":"Point"}
}