{
  "type": "Feature",
  "properties": {
    "addr:full":"101 Hartley St Portsmith QLD 4870",
    "addr:housenumber":"101",
    "addr:postcode":"4870",
    "addr:street":"Hartley St Portsmith",
    "iso:country":"AU",
    "sg:address":"101 Hartley St",
    "sg:city":"Portsmith",
    "sg:classifiers":[
        {
            "category":"Professional",
            "type":"Services"
        }
    ],
    "sg:phone":"+61 7 4035 5781",
    "sg:postcode":"4870",
    "sg:province":"QLD",
    "sg:tags":[
        "shop",
        "fitting"
    ],
    "wof:name":"Raffles Joinery Pty Ltd",
    "wof:placetype":"venue"
},
  "geometry": {"coordinates":[145.76846313499999,-16.9341583252],"type":"Point"}
}