{
  "type": "Feature",
  "properties": {
    "addr:full":"43 Westerfield Drv Clayton North VIC 3168",
    "addr:housenumber":"43",
    "addr:postcode":"3168",
    "addr:street":"Westerfield Drv",
    "iso:country":"AU",
    "sg:address":"43 Westerfield Drv",
    "sg:city":"Clayton North",
    "sg:classifiers":[
        {
            "category":"Manufacturing",
            "subcategory":"Petroleum Products",
            "type":"Manufacturing & Wholesale Goods"
        }
    ],
    "sg:phone":"+61 3 9561 1016",
    "sg:postcode":"3168",
    "sg:province":"VIC",
    "sg:tags":[
        "lubricant"
    ],
    "wof:name":"Superior Synthetic Lubricants Pty Ltd",
    "wof:placetype":"venue"
},
  "geometry": {"coordinates":[145.12176513700001,-37.914516449],"type":"Point"}
}