{
  "type": "Feature",
  "properties": {
    "iso:country":"AU",
    "sg:address":"PO Box 2189",
    "sg:city":"Carlisle North",
    "sg:classifiers":[
        {
            "category":"Social Services",
            "subcategory":"Job Training",
            "type":"Services"
        }
    ],
    "sg:phone":"+61 8 9362 4819",
    "sg:postcode":"6101",
    "sg:province":"WA",
    "sg:tags":[
        "interpreter"
    ],
    "wof:name":"WA Interpreters Pty Ltd",
    "wof:placetype":"venue"
},
  "geometry": {"coordinates":[115.914932251,-31.9750709534],"type":"Point"}
}