{
  "type": "Feature",
  "properties": {
    "addr:full":"189 King St Mascot NSW 2020",
    "addr:housenumber":"189",
    "addr:postcode":"2020",
    "addr:street":"King St",
    "iso:country":"AU",
    "sg:address":"189 King St",
    "sg:city":"Mascot",
    "sg:classifiers":[
        {
            "category":"Professional",
            "subcategory":"Accounting & Tax Preparation",
            "type":"Services"
        }
    ],
    "sg:phone":"+61 2 9669 5866",
    "sg:postcode":"2020",
    "sg:province":"NSW",
    "sg:tags":[
        "accountant",
        "auditor"
    ],
    "wof:name":"Rosen S M",
    "wof:placetype":"venue"
},
  "geometry": {"coordinates":[151.19564819300001,-33.9296646118],"type":"Point"}
}