{
  "type": "Feature",
  "properties": {
    "addr:full":"Cnr Coonans Rd & Parkstone Ave Pascoe Vale South VIC 3044",
    "addr:postcode":"3044",
    "addr:street":"Cnr Coonans Rd & Parkstone Ave",
    "iso:country":"AU",
    "sg:address":"Cnr Coonans Rd & Parkstone Ave",
    "sg:city":"Pascoe Vale South",
    "sg:classifiers":[
        {
            "category":"Social Services",
            "subcategory":"Retirement Home",
            "type":"Services"
        }
    ],
    "sg:phone":"+61 3 9383 5255",
    "sg:postcode":"3044",
    "sg:province":"VIC",
    "sg:tags":[
        "decoration",
        "supplier",
        "contractor"
    ],
    "wof:name":"Functions Of Distinction",
    "wof:placetype":"venue"
},
  "geometry": {"coordinates":[144.93829345699999,-37.7459945679],"type":"Point"}
}