{
  "type": "Feature",
  "properties": {
    "iso:country":"AU",
    "sg:address":"8a Faraday Rd",
    "sg:city":"Padstow",
    "sg:classifiers":[
        {
            "category":"Real Estate",
            "subcategory":"Real Estate Agent",
            "type":"Services"
        }
    ],
    "sg:phone":"+61 2 9772 4500",
    "sg:postcode":"2211",
    "sg:province":"NSW",
    "wof:name":"Elders Real Estate",
    "wof:placetype":"venue"
},
  "geometry": {"coordinates":[151.033676,-33.953812],"type":"Point"}
}