{
  "type": "Feature",
  "properties": {
    "addr:full":"2/ 7a Wentworth St Manly NSW 2095",
    "addr:housenumber":"/ 7a",
    "addr:postcode":"2095",
    "addr:street":"Wentworth St",
    "iso:country":"AU",
    "sg:address":"2/ 7a Wentworth St",
    "sg:city":"Manly",
    "sg:classifiers":[
        {
            "category":"Health Services",
            "subcategory":"Doctor",
            "type":"Services"
        }
    ],
    "sg:phone":"+61 2 9977 0866",
    "sg:postcode":"2095",
    "sg:province":"NSW",
    "sg:tags":[
        "medical",
        "practitioner"
    ],
    "wof:name":"Peninsula Skin Centre",
    "wof:placetype":"venue"
},
  "geometry": {"coordinates":[151.28640747099999,-33.7992248535],"type":"Point"}
}