{
  "type": "Feature",
  "properties": {
    "addr:full":"551 King St Melbourne VIC 3000",
    "addr:housenumber":"551",
    "addr:postcode":"3000",
    "addr:street":"King St",
    "iso:country":"AU",
    "sg:address":"551 King St",
    "sg:city":"Melbourne",
    "sg:classifiers":[
        {
            "category":"Real Estate",
            "subcategory":"Architect",
            "type":"Services"
        }
    ],
    "sg:phone":"+61 3 9576 8866",
    "sg:postcode":"3000",
    "sg:province":"VIC",
    "wof:name":"Ellis Group Architects The",
    "wof:placetype":"venue"
},
  "geometry": {"coordinates":[144.95039367699999,-37.8069839478],"type":"Point"}
}