{
  "type": "Feature",
  "properties": {
    "addr:full":"2086 Clementson St Broome WA 6725",
    "addr:housenumber":"2086",
    "addr:postcode":"6725",
    "addr:street":"Clementson St",
    "iso:country":"AU",
    "sg:address":"2086 Clementson St",
    "sg:city":"Broome",
    "sg:classifiers":[
        {
            "category":"Recreation",
            "subcategory":"Boat Charter",
            "type":"Entertainment"
        }
    ],
    "sg:phone":"+61 8 9192 1774",
    "sg:postcode":"6725",
    "sg:province":"WA",
    "wof:name":"Simara III Kimberley Fishing Charters Broome",
    "wof:placetype":"venue"
},
  "geometry": {"coordinates":[122.224021912,-17.9715805054],"type":"Point"}
}