{
  "type": "Feature",
  "properties": {
    "iso:country":"AU",
    "sg:address":"1370 Coomba Rd",
    "sg:city":"Coomba",
    "sg:classifiers":[
        {
            "category":"Farming",
            "subcategory":"Farm & Veterinary Services",
            "type":"Manufacturing & Wholesale Goods"
        }
    ],
    "sg:phone":"+61 2 6554 2033",
    "sg:postcode":"2428",
    "sg:province":"NSW",
    "sg:tags":[
        "contracting"
    ],
    "wof:name":"Wyohbie Pastoral Company",
    "wof:placetype":"venue"
},
  "geometry": {"coordinates":[152.45169100000001,-32.283474],"type":"Point"}
}