{
  "type": "Feature",
  "properties": {
    "addr:full":"McCann Rd Canberra Airport ACT 2609",
    "addr:postcode":"2609",
    "addr:street":"Mccann Rd",
    "iso:country":"AU",
    "sg:address":"McCann Rd",
    "sg:city":"Canberra Airport",
    "sg:classifiers":[
        {
            "category":"Manufacturing",
            "subcategory":"Aerospace",
            "type":"Manufacturing & Wholesale Goods"
        }
    ],
    "sg:phone":"+61 2 6257 2940",
    "sg:postcode":"2609",
    "sg:province":"ACT",
    "sg:tags":[
        "equipment",
        "aircraft",
        "maintenance"
    ],
    "wof:name":"Vee H Aviation Pty Ltd",
    "wof:placetype":"venue"
},
  "geometry": {"coordinates":[149.18858337399999,-35.3063087463],"type":"Point"}
}