{
  "type": "Feature",
  "properties": {
    "iso:country":"AU",
    "sg:address":"74 Prince St",
    "sg:city":"Orange",
    "sg:classifiers":[
        {
            "category":"Travel",
            "subcategory":"Hostel",
            "type":"Entertainment"
        }
    ],
    "sg:phone":"+61 2 6361 3757",
    "sg:postcode":"2800",
    "sg:province":"NSW",
    "sg:tags":[
        "home"
    ],
    "wof:name":"Wontama Homes Parkwood",
    "wof:placetype":"venue"
},
  "geometry": {"coordinates":[149.09686279300001,-33.27684021],"type":"Point"}
}