{
  "type": "Feature",
  "properties": {
    "addr:full":"479 Crown St West Wollongong NSW 2500",
    "addr:housenumber":"479",
    "addr:postcode":"2500",
    "addr:street":"Crown St West",
    "iso:country":"AU",
    "sg:address":"479 Crown St",
    "sg:city":"West Wollongong",
    "sg:classifiers":[
        {
            "category":"Health Services",
            "subcategory":"Doctor",
            "type":"Services"
        }
    ],
    "sg:phone":"+61 2 4228 4377",
    "sg:postcode":"2500",
    "sg:province":"NSW",
    "sg:tags":[
        "medical",
        "practitioner"
    ],
    "wof:name":"Etheredge S",
    "wof:placetype":"venue"
},
  "geometry": {"coordinates":[150.87196399999999,-34.425201],"type":"Point"}
}