{
  "type": "Feature",
  "properties": {
    "iso:country":"AU",
    "sg:address":"Greenhill Rd",
    "sg:city":"Uraidla",
    "sg:classifiers":[
        {
            "category":"Education",
            "subcategory":"School",
            "type":"Public Place"
        }
    ],
    "sg:phone":"+61 412 333 433",
    "sg:postcode":"5142",
    "sg:province":"SA",
    "sg:tags":[
        "teaching",
        "aid"
    ],
    "wof:name":"Doctor Bones",
    "wof:placetype":"venue"
},
  "geometry": {"coordinates":[138.745865,-34.958366],"type":"Point"}
}