{
  "type": "Feature",
  "properties": {
    "iso:country":"AU",
    "sg:address":"77- 79 Whitehorse Rd",
    "sg:city":"Blackburn",
    "sg:classifiers":[
        {
            "category":"Personal",
            "subcategory":"Massage",
            "type":"Services"
        }
    ],
    "sg:phone":"+61 3 9444 7408",
    "sg:postcode":"3130",
    "sg:province":"VIC",
    "sg:tags":[
        "therapy"
    ],
    "wof:name":"Aurora Therapeutics Remedial Massage & Spa",
    "wof:placetype":"venue"
},
  "geometry": {"coordinates":[145.148834228,-37.8172874451],"type":"Point"}
}