{
  "type": "Feature",
  "properties": {
    "addr:full":"10 Paterson St Norah Head NSW 2263",
    "addr:housenumber":"10",
    "addr:postcode":"2263",
    "addr:street":"Paterson St Norah",
    "iso:country":"AU",
    "sg:address":"10 Paterson St",
    "sg:city":"Norah Head",
    "sg:classifiers":[
        {
            "category":"Education",
            "subcategory":"Vocational School",
            "type":"Public Place"
        }
    ],
    "sg:phone":"+61 2 4396 5448",
    "sg:postcode":"2263",
    "sg:province":"NSW",
    "sg:tags":[
        "cake",
        "decorating",
        "decorator"
    ],
    "wof:name":"McGregor Pat",
    "wof:placetype":"venue"
},
  "geometry": {"coordinates":[151.562927,-33.275829],"type":"Point"}
}