{
  "type": "Feature",
  "properties": {
    "addr:full":"15 Walker St Merrylands NSW 2160",
    "addr:housenumber":"15",
    "addr:postcode":"2160",
    "addr:street":"Walker St",
    "iso:country":"AU",
    "sg:address":"15 Walker St",
    "sg:city":"Merrylands",
    "sg:classifiers":[
        {
            "category":"Manufacturing",
            "subcategory":"Tools & Machinery",
            "type":"Manufacturing & Wholesale Goods"
        }
    ],
    "sg:phone":"+61 414 797 950",
    "sg:postcode":"2160",
    "sg:province":"NSW",
    "sg:tags":[
        "earth",
        "excavating",
        "moving",
        "equipment"
    ],
    "wof:name":"Total Excavating and Demolition Pty Ltd",
    "wof:placetype":"venue"
},
  "geometry": {"coordinates":[150.98829650900001,-33.8417778015],"type":"Point"}
}