{
  "type": "Feature",
  "properties": {
    "addr:full":"132 Argyle St Hobart TAS 7000",
    "addr:housenumber":"132",
    "addr:postcode":"7000",
    "addr:street":"Argyle St",
    "iso:country":"AU",
    "sg:address":"132 Argyle St",
    "sg:city":"Hobart",
    "sg:classifiers":[
        {
            "category":"Manufacturing",
            "subcategory":"Motor Vehicles & Parts",
            "type":"Manufacturing & Wholesale Goods"
        }
    ],
    "sg:phone":"+61 3 6231 3707",
    "sg:postcode":"7000",
    "sg:province":"TAS",
    "sg:tags":[
        "replacement"
    ],
    "wof:name":"Burson Automotive Pty Ltd",
    "wof:placetype":"venue"
},
  "geometry": {"coordinates":[147.31582641599999,-42.8697662354],"type":"Point"}
}