{
  "type": "Feature",
  "properties": {
    "addr:full":"4 Mataro Crt Thornlands QLD 4164",
    "addr:housenumber":"4",
    "addr:postcode":"4164",
    "addr:street":"Mataro Crt",
    "iso:country":"AU",
    "sg:address":"4 Mataro Crt",
    "sg:city":"Thornlands",
    "sg:classifiers":[
        {
            "category":"Health Services",
            "subcategory":"Health Practitioner",
            "type":"Services"
        }
    ],
    "sg:phone":"+61 7 3206 1300",
    "sg:postcode":"4164",
    "sg:province":"QLD",
    "sg:tags":[
        "naturopath"
    ],
    "wof:name":"Cleveland Herbal & Homoeopathic Clinic",
    "wof:placetype":"venue"
},
  "geometry": {"coordinates":[153.26271057100001,-27.5603752136],"type":"Point"}
}