{
  "type": "Feature",
  "properties": {
    "addr:full":"9 Reedie St Henley Beach SA 5022",
    "addr:housenumber":"9",
    "addr:postcode":"5022",
    "addr:street":"Reedie St",
    "iso:country":"AU",
    "sg:address":"9 Reedie St",
    "sg:city":"Henley Beach",
    "sg:classifiers":[
        {
            "category":"Building & Trades",
            "subcategory":"Construction",
            "type":"Services"
        }
    ],
    "sg:phone":"+61 417 830 610",
    "sg:postcode":"5022",
    "sg:province":"SA",
    "sg:tags":[
        "fencing",
        "contractor"
    ],
    "wof:name":"Emergency Fencing",
    "wof:placetype":"venue"
},
  "geometry": {"coordinates":[138.49383544899999,-34.910785675],"type":"Point"}
}