{
  "type": "Feature",
  "properties": {
    "iso:country":"AU",
    "sg:address":"World Square Level 10/Shop 58, 684-686 George St",
    "sg:city":"Sydney",
    "sg:classifiers":[
        {
            "category":"Personal",
            "subcategory":"Beauty Salon",
            "type":"Services"
        }
    ],
    "sg:phone":"+61 2 9264 5533",
    "sg:postcode":"2000",
    "sg:province":"NSW",
    "sg:tags":[
        "hairdresser"
    ],
    "wof:name":"Toni & Guy Hairdressing Salons",
    "wof:placetype":"venue"
},
  "geometry": {"coordinates":[151.20596313499999,-33.8776435852],"type":"Point"}
}