{
  "type": "Feature",
  "properties": {
    "iso:country":"AU",
    "sg:address":"19 Allied Drv",
    "sg:city":"Tullamarine",
    "sg:classifiers":[
        {
            "category":"Professional",
            "type":"Services"
        }
    ],
    "sg:phone":"+61 3 9335 4400",
    "sg:postcode":"3043",
    "sg:province":"VIC",
    "sg:tags":[
        "packaging",
        "filling",
        "assembling"
    ],
    "wof:name":"Culbeag Holdings Pty Ltd",
    "wof:placetype":"venue"
},
  "geometry": {"coordinates":[144.872848511,-37.7103271484],"type":"Point"}
}