{
  "type": "Feature",
  "properties": {
    "addr:full":"Shop C 90 Harbour Town Shopping Centre Biggera Waters Biggera Waters QLD 4216",
    "addr:housenumber":"90",
    "addr:postcode":"4216",
    "addr:street":"C",
    "iso:country":"AU",
    "sg:address":"Shop C 90 Harbour Town Shopping Centre Biggera Waters",
    "sg:city":"Biggera Waters",
    "sg:classifiers":[
        {
            "category":"Shopping",
            "subcategory":"Clothing, Apparel, & Fashions",
            "type":"Retail Goods"
        }
    ],
    "sg:phone":"+61 7 5529 1979",
    "sg:postcode":"4216",
    "sg:province":"QLD",
    "sg:tags":[
        "lingerie",
        "hosiery",
        "sleepwear"
    ],
    "wof:name":"Wild Rose Lingerie",
    "wof:placetype":"venue"
},
  "geometry": {"coordinates":[153.38929748499999,-27.9290466309],"type":"Point"}
}