{
  "type": "Feature",
  "properties": {
    "iso:country":"AU",
    "sg:address":"39 McDowell St",
    "sg:city":"Welshpool",
    "sg:classifiers":[
        {
            "category":"Retail",
            "subcategory":"Storage",
            "type":"Services"
        }
    ],
    "sg:phone":"+61 1300 790 246",
    "sg:postcode":"6106",
    "sg:province":"WA",
    "wof:name":"AUSDOC Information Management",
    "wof:placetype":"venue"
},
  "geometry": {"coordinates":[115.965873718,-31.9956245422],"type":"Point"}
}