{
  "type": "Feature",
  "properties": {
    "addr:full":"87 Allenby Rd Rossmore NSW 2171",
    "addr:housenumber":"87",
    "addr:postcode":"2171",
    "addr:street":"Allenby Rd",
    "iso:country":"AU",
    "sg:address":"87 Allenby Rd",
    "sg:city":"Rossmore",
    "sg:classifiers":[
        {
            "category":"Utilities",
            "subcategory":"Electric",
            "type":"Services"
        }
    ],
    "sg:phone":"+61 2 9606 5433",
    "sg:postcode":"2171",
    "sg:province":"NSW",
    "sg:tags":[
        "vehicle"
    ],
    "wof:name":"All Seasons Golf Cars",
    "wof:placetype":"venue"
},
  "geometry": {"coordinates":[150.92265319800001,-33.8825340271],"type":"Point"}
}