{
  "type": "Feature",
  "properties": {
    "iso:country":"AU",
    "sg:address":"26 Ewell Ave",
    "sg:city":"Warradale",
    "sg:classifiers":[
        {
            "category":"Professional",
            "subcategory":"Computer Services",
            "type":"Services"
        }
    ],
    "sg:phone":"+61 422 996 571",
    "sg:postcode":"5046",
    "sg:province":"SA",
    "sg:tags":[
        "repairs",
        "upgrade",
        "equipment"
    ],
    "wof:name":"Smith D",
    "wof:placetype":"venue"
},
  "geometry": {"coordinates":[138.535156,-34.998272],"type":"Point"}
}