{
  "type": "Feature",
  "properties": {
    "addr:full":"PO Box 551 Laverton VIC 3028",
    "addr:postcode":"3028",
    "iso:country":"AU",
    "sg:address":"PO Box 551",
    "sg:city":"Laverton",
    "sg:classifiers":[
        {
            "category":"Sports & Exercise",
            "subcategory":"Sports Center",
            "type":"Entertainment"
        }
    ],
    "sg:phone":"+61 3 9360 0633",
    "sg:postcode":"3028",
    "sg:province":"VIC",
    "sg:tags":[
        "ground"
    ],
    "wof:name":"State Baseball Softball Centre",
    "wof:placetype":"venue"
},
  "geometry": {"coordinates":[144.769699,-37.86277],"type":"Point"}
}