{
  "type": "Feature",
  "properties": {
    "addr:full":"Un 3, 5 Brighton St Ballina NSW 2478",
    "addr:housenumber":"5",
    "addr:postcode":"2478",
    "addr:street":"Brighton St",
    "iso:country":"AU",
    "sg:address":"Un 3, 5 Brighton St",
    "sg:city":"Ballina",
    "sg:classifiers":[
        {
            "category":"Cafe",
            "type":"Food & Drink"
        }
    ],
    "sg:phone":"+61 2 6686 9071",
    "sg:postcode":"2478",
    "sg:province":"NSW",
    "wof:name":"2 Decadent",
    "wof:placetype":"venue"
},
  "geometry": {"coordinates":[153.57945251500001,-28.8652057648],"type":"Point"}
}