{
  "type": "Feature",
  "properties": {
    "iso:country":"AU",
    "sg:address":"Unit 4/ 27 Activity Crs",
    "sg:city":"Ernest",
    "sg:classifiers":[
        {
            "category":"Wholesale",
            "subcategory":"Painting Supplies",
            "type":"Manufacturing & Wholesale Goods"
        }
    ],
    "sg:phone":"+61 1800 738 383",
    "sg:postcode":"4214",
    "sg:province":"QLD",
    "sg:tags":[
        "wholesaler",
        "paint",
        "mfrs"
    ],
    "wof:name":"Resene Paints (Australia) Limited",
    "wof:placetype":"venue"
},
  "geometry": {"coordinates":[153.36180114699999,-27.9689006805],"type":"Point"}
}