{
  "type": "Feature",
  "properties": {
    "iso:country":"AU",
    "sg:address":"Shop 24 Boulevard Plaza Shopping Centre",
    "sg:city":"Port Hedland",
    "sg:classifiers":[
        {
            "category":"Fast Food",
            "type":"Food & Drink"
        }
    ],
    "sg:phone":"+61 8 9173 2428",
    "sg:postcode":"6721",
    "sg:province":"WA",
    "sg:tags":[
        "away",
        "take"
    ],
    "wof:name":"Chicken Treat",
    "wof:placetype":"venue"
},
  "geometry": {"coordinates":[118.46824646,-20.7532691956],"type":"Point"}
}