{
  "type": "Feature",
  "properties": {
    "iso:country":"AU",
    "sg:address":"2143 Great Northern Hwy",
    "sg:city":"Bullsbrook",
    "sg:classifiers":[
        {
            "category":"Home & Garden",
            "subcategory":"Garden Supply",
            "type":"Retail Goods"
        }
    ],
    "sg:phone":"+61 8 9571 1911",
    "sg:postcode":"6084",
    "sg:province":"WA",
    "sg:tags":[
        "turf",
        "lawn"
    ],
    "wof:name":"Turf Growers Australia",
    "wof:placetype":"venue"
},
  "geometry": {"coordinates":[116.029190063,-31.6665992737],"type":"Point"}
}