{
  "type": "Feature",
  "properties": {
    "addr:full":"Unit 1 8 Jay St Pooraka SA 5095",
    "addr:housenumber":"8",
    "addr:postcode":"5095",
    "addr:street":"Jay St",
    "iso:country":"AU",
    "sg:address":"Unit 1 8 Jay St",
    "sg:city":"Pooraka",
    "sg:classifiers":[
        {
            "category":"Retail",
            "subcategory":"Auto Repair",
            "type":"Services"
        }
    ],
    "sg:phone":"+61 8 8262 7266",
    "sg:postcode":"5095",
    "sg:province":"SA",
    "sg:tags":[
        "electrical"
    ],
    "wof:name":"Tim Upward Racing",
    "wof:placetype":"venue"
},
  "geometry": {"coordinates":[138.638137817,-34.8175735474],"type":"Point"}
}