{
  "type": "Feature",
  "properties": {
    "iso:country":"AU",
    "sg:address":"2 Elizabeth St",
    "sg:city":"Mallala",
    "sg:classifiers":[
        {
            "category":"Building & Trades",
            "subcategory":"Construction",
            "type":"Services"
        }
    ],
    "sg:phone":"+61 8 8527 2057",
    "sg:postcode":"5502",
    "sg:province":"SA",
    "sg:tags":[
        "earth",
        "excavating",
        "moving",
        "contractor"
    ],
    "wof:name":"D & C Davis Excavations",
    "wof:placetype":"venue"
},
  "geometry": {"coordinates":[138.512604,-34.436672],"type":"Point"}
}