{
  "type": "Feature",
  "properties": {
    "iso:country":"AU",
    "sg:address":"29/ 35 Chorlton St",
    "sg:city":"East Brisbane",
    "sg:classifiers":[
        {
            "category":"Professional",
            "type":"Services"
        }
    ],
    "sg:phone":"+61 7 3391 8277",
    "sg:postcode":"4169",
    "sg:province":"QLD",
    "sg:tags":[
        "auctioneer"
    ],
    "wof:name":"DMS Davlan Pty Ltd",
    "wof:placetype":"venue"
},
  "geometry": {"coordinates":[153.049316406,-27.4900569916],"type":"Point"}
}