{
  "type": "Feature",
  "properties": {
    "addr:full":"2948 Albany Hwy Kelmscott WA 6111",
    "addr:housenumber":"2948",
    "addr:postcode":"6111",
    "addr:street":"Albany Hwy",
    "iso:country":"AU",
    "sg:address":"2948 Albany Hwy",
    "sg:city":"Kelmscott",
    "sg:classifiers":[
        {
            "category":"Shopping",
            "subcategory":"Party Supplies",
            "type":"Retail Goods"
        }
    ],
    "sg:phone":"+61 8 9390 8020",
    "sg:postcode":"6111",
    "sg:province":"WA",
    "sg:tags":[
        "children's"
    ],
    "wof:name":"Foxys Indoor Sports Stadium",
    "wof:placetype":"venue"
},
  "geometry": {"coordinates":[116.018226623,-32.1242866516],"type":"Point"}
}