{
  "type": "Feature",
  "properties": {
    "iso:country":"AU",
    "sg:address":"29 Drummond St",
    "sg:city":"Carlton",
    "sg:classifiers":[
        {
            "category":"Education",
            "subcategory":"Special Training",
            "type":"Public Place"
        }
    ],
    "sg:phone":"+61 3 9654 1299",
    "sg:postcode":"3053",
    "sg:province":"VIC",
    "sg:tags":[
        "development"
    ],
    "wof:name":"Epic Industry Training Board",
    "wof:placetype":"venue"
},
  "geometry": {"coordinates":[144.967285156,-37.8063850403],"type":"Point"}
}