{
  "type": "Feature",
  "properties": {
    "addr:full":"2a York Rd Glen Iris VIC 3146",
    "addr:housenumber":"2a",
    "addr:postcode":"3146",
    "addr:street":"York Rd",
    "iso:country":"AU",
    "sg:address":"2a York Rd",
    "sg:city":"Glen Iris",
    "sg:classifiers":[
        {
            "category":"Retail",
            "subcategory":"Storage",
            "type":"Services"
        }
    ],
    "sg:phone":"+61 3 9886 9778",
    "sg:postcode":"3146",
    "sg:province":"VIC",
    "wof:name":"Guardian Facility Management Pty Ltd",
    "wof:placetype":"venue"
},
  "geometry": {"coordinates":[145.05674743599999,-37.8565597534],"type":"Point"}
}