{
  "type": "Feature",
  "properties": {
    "iso:country":"AU",
    "sg:address":"562 Lutwyche Rd",
    "sg:city":"Lutwyche",
    "sg:classifiers":[
        {
            "category":"Fast Food",
            "type":"Food & Drink"
        }
    ],
    "sg:phone":"+61 7 3857 3717",
    "sg:postcode":"4030",
    "sg:province":"QLD",
    "sg:tags":[
        "away",
        "take"
    ],
    "wof:name":"Leon Chinese Restaurant",
    "wof:placetype":"venue"
},
  "geometry": {"coordinates":[153.03387499999999,-27.420853],"type":"Point"}
}