{
  "type": "Feature",
  "properties": {
    "iso:country":"AU",
    "sg:address":"1575 Ferntree Gully Rd",
    "sg:city":"Knoxfield",
    "sg:classifiers":[
        {
            "category":"Fast Food",
            "type":"Food & Drink"
        }
    ],
    "sg:phone":"+61 3 9763 6609",
    "sg:postcode":"3180",
    "sg:province":"VIC",
    "sg:tags":[
        "away",
        "take"
    ],
    "wof:name":"Top Chook Shop",
    "wof:placetype":"venue"
},
  "geometry": {"coordinates":[145.24952697800001,-37.8949203491],"type":"Point"}
}