{
  "type": "Feature",
  "properties": {
    "iso:country":"AU",
    "sg:address":"56 Warburton Rd",
    "sg:city":"Canterbury",
    "sg:classifiers":[
        {
            "category":"Professional",
            "subcategory":"Computer Services",
            "type":"Services"
        }
    ],
    "sg:phone":"+61 3 9836 1809",
    "sg:postcode":"3126",
    "sg:province":"VIC",
    "sg:tags":[
        "repairs",
        "upgrade",
        "equipment"
    ],
    "wof:name":"@ Home Trouble Shooting",
    "wof:placetype":"venue"
},
  "geometry": {"coordinates":[145.07553100600001,-37.8264312744],"type":"Point"}
}