{
  "type": "Feature",
  "properties": {
    "addr:full":"Cnr Napoleon Rd & Lakesfield Drv Ferntree Gully VIC 3156",
    "addr:postcode":"3156",
    "addr:street":"Napoleon Rd & Lakesfield Drv",
    "iso:country":"AU",
    "sg:address":"Cnr Napoleon Rd & Lakesfield Drv",
    "sg:city":"Ferntree Gully",
    "sg:classifiers":[
        {
            "category":"Retail",
            "subcategory":"Auto Repair",
            "type":"Services"
        }
    ],
    "sg:phone":"+61 3 9759 6759",
    "sg:postcode":"3156",
    "sg:province":"VIC",
    "sg:tags":[
        "repairer",
        "motor",
        "engineer"
    ],
    "wof:name":"Austec Mechanical Services",
    "wof:placetype":"venue"
},
  "geometry": {"coordinates":[145.29179382300001,-37.9004478455],"type":"Point"}
}