{
  "type": "Feature",
  "properties": {
    "iso:country":"AU",
    "sg:address":"24 New Dookie Rd",
    "sg:city":"Shepparton",
    "sg:classifiers":[
        {
            "category":"Shopping",
            "type":"Retail Goods"
        }
    ],
    "sg:phone":"+61 3 5831 1535",
    "sg:postcode":"3630",
    "sg:province":"VIC",
    "sg:tags":[
        "agent",
        "stock"
    ],
    "wof:name":"Charles Medland and Co.",
    "wof:placetype":"venue"
},
  "geometry": {"coordinates":[145.418212891,-36.3680152893],"type":"Point"}
}