{
  "type": "Feature",
  "properties": {
    "iso:country":"AU",
    "sg:address":"100 Brushwood Brook Drv",
    "sg:city":"Yallingup",
    "sg:classifiers":[
        {
            "category":"Landmark",
            "subcategory":"Scenic View",
            "type":"Public Place"
        }
    ],
    "sg:phone":"+61 8 9755 2995",
    "sg:postcode":"6282",
    "sg:province":"WA",
    "sg:tags":[
        "staircase",
        "handrail"
    ],
    "wof:name":"Broekman M J",
    "wof:placetype":"venue"
},
  "geometry": {"coordinates":[115.07701873800001,-33.6761665344],"type":"Point"}
}