{
  "type": "Feature",
  "properties": {
    "addr:full":"71- 79 Bouverie St Carlton VIC 3053",
    "addr:housenumber":"79",
    "addr:postcode":"3053",
    "addr:street":"Bouverie St",
    "iso:country":"AU",
    "sg:address":"71- 79 Bouverie St",
    "sg:city":"Carlton",
    "sg:classifiers":[
        {
            "category":"Wholesale",
            "subcategory":"Non-durable Goods",
            "type":"Manufacturing & Wholesale Goods"
        }
    ],
    "sg:phone":"+61 3 9347 3422",
    "sg:postcode":"3053",
    "sg:province":"VIC",
    "sg:tags":[
        "wholesaler",
        "mfrs",
        "cosmetic"
    ],
    "wof:name":"Aesop",
    "wof:placetype":"venue"
},
  "geometry": {"coordinates":[144.96153259299999,-37.8047523499],"type":"Point"}
}