{
  "type": "Feature",
  "properties": {
    "iso:country":"AU",
    "sg:address":"7 Noon St",
    "sg:city":"Dandenong",
    "sg:classifiers":[
        {
            "category":"Communications",
            "type":"Services"
        }
    ],
    "sg:phone":"+61 3 9701 7180",
    "sg:postcode":"3175",
    "sg:province":"VIC",
    "sg:tags":[
        "translation"
    ],
    "wof:name":"Burmese Translations",
    "wof:placetype":"venue"
},
  "geometry": {"coordinates":[145.20344543499999,-37.9959754944],"type":"Point"}
}