{
  "type": "Feature",
  "properties": {
    "addr:full":"82 Station St Dandenong VIC 3175",
    "addr:housenumber":"82",
    "addr:postcode":"3175",
    "addr:street":"Station St",
    "iso:country":"AU",
    "sg:address":"82 Station St",
    "sg:city":"Dandenong",
    "sg:classifiers":[
        {
            "category":"Communications",
            "subcategory":"Film & Video Production",
            "type":"Services"
        }
    ],
    "sg:phone":"+61 3 9775 4050",
    "sg:postcode":"3175",
    "sg:province":"VIC",
    "sg:tags":[
        "consultant",
        "material",
        "handling"
    ],
    "wof:name":"Dynamic Forklifts",
    "wof:placetype":"venue"
},
  "geometry": {"coordinates":[145.209060669,-37.9910011292],"type":"Point"}
}