{
  "type": "Feature",
  "properties": {
    "addr:full":"1 Fenton St Mundaring WA 6073",
    "addr:housenumber":"1",
    "addr:postcode":"6073",
    "addr:street":"Fenton St",
    "iso:country":"AU",
    "sg:address":"1 Fenton St",
    "sg:city":"Mundaring",
    "sg:classifiers":[
        {
            "category":"Travel",
            "subcategory":"Hostel",
            "type":"Entertainment"
        }
    ],
    "sg:phone":"+61 8 9295 1511",
    "sg:postcode":"6073",
    "sg:province":"WA",
    "sg:tags":[
        "home"
    ],
    "wof:name":"Amana Living",
    "wof:placetype":"venue"
},
  "geometry": {"coordinates":[116.170013428,-31.9045639038],"type":"Point"}
}