{
  "type": "Feature",
  "properties": {
    "addr:full":"Suite 420/ 1 Queens Rd Melbourne VIC 3000",
    "addr:housenumber":"420 / 1",
    "addr:postcode":"3000",
    "addr:street":"Queens Rd",
    "iso:country":"AU",
    "sg:address":"Suite 420/ 1 Queens Rd",
    "sg:city":"Melbourne",
    "sg:classifiers":[
        {
            "category":"Professional",
            "subcategory":"Employment Agencies",
            "type":"Services"
        }
    ],
    "sg:phone":"+61 3 9863 7345",
    "sg:postcode":"3000",
    "sg:province":"VIC",
    "wof:name":"Sorensen Recruitment",
    "wof:placetype":"venue"
},
  "geometry": {"coordinates":[144.97369384800001,-37.8357315063],"type":"Point"}
}