{
  "type": "Feature",
  "properties": {
    "addr:full":"199 Bridge St Oakey QLD 4401",
    "addr:housenumber":"199",
    "addr:postcode":"4401",
    "addr:street":"Bridge St",
    "iso:country":"AU",
    "sg:address":"199 Bridge St",
    "sg:city":"Oakey",
    "sg:classifiers":[
        {
            "category":"Wholesale",
            "subcategory":"Farm Supplies",
            "type":"Manufacturing & Wholesale Goods"
        }
    ],
    "sg:phone":"+61 7 4691 1500",
    "sg:postcode":"4401",
    "sg:province":"QLD",
    "sg:tags":[
        "equipment"
    ],
    "wof:name":"Fieldquip",
    "wof:placetype":"venue"
},
  "geometry": {"coordinates":[151.71090698200001,-27.4271945953],"type":"Point"}
}