{
  "type": "Feature",
  "properties": {
    "addr:full":"Shp 6a, Ipswich Riverlink Shopping Centre Downs Rd Ipswich QLD 4305",
    "addr:housenumber":"6a",
    "addr:postcode":"4305",
    "addr:street":"Downs Rd",
    "iso:country":"AU",
    "sg:address":"Shp 6a, Ipswich Riverlink Shopping Centre Downs Rd",
    "sg:city":"Ipswich",
    "sg:classifiers":[
        {
            "category":"Banks & Credit Unions",
            "subcategory":"Bank",
            "type":"Services"
        }
    ],
    "sg:phone":"+61 7 3202 4607",
    "sg:postcode":"4305",
    "sg:province":"QLD",
    "wof:name":"Credit Union Australia (CUA)",
    "wof:placetype":"venue"
},
  "geometry": {"coordinates":[152.75999450699999,-27.6073760986],"type":"Point"}
}