{
  "type": "Feature",
  "properties": {
    "addr:full":"297 Pirie St Adelaide SA 5000",
    "addr:housenumber":"297",
    "addr:postcode":"5000",
    "addr:street":"Pirie St",
    "iso:country":"AU",
    "sg:address":"297 Pirie St",
    "sg:city":"Adelaide",
    "sg:classifiers":[
        {
            "category":"Health Services",
            "subcategory":"Health Practitioner",
            "type":"Services"
        }
    ],
    "sg:phone":"+61 411 717 977",
    "sg:postcode":"5000",
    "sg:province":"SA",
    "sg:tags":[
        "psychologist"
    ],
    "wof:name":"Bloke 2 Bloke",
    "wof:placetype":"venue"
},
  "geometry": {"coordinates":[138.610839844,-34.9253196716],"type":"Point"}
}