{
  "type": "Feature",
  "properties": {
    "addr:full":"18 Douglas St Coolamon NSW 2701",
    "addr:housenumber":"18",
    "addr:postcode":"2701",
    "addr:street":"Douglas St",
    "iso:country":"AU",
    "sg:address":"18 Douglas St",
    "sg:city":"Coolamon",
    "sg:classifiers":[
        {
            "category":"Building & Trades",
            "subcategory":"Construction",
            "type":"Services"
        }
    ],
    "sg:phone":"+61 2 6927 3151",
    "sg:postcode":"2701",
    "sg:province":"NSW",
    "sg:tags":[
        "contractor"
    ],
    "wof:name":"Kew N D",
    "wof:placetype":"venue"
},
  "geometry": {"coordinates":[147.19818115199999,-34.8116760254],"type":"Point"}
}