{
  "type": "Feature",
  "properties": {
    "addr:full":"5 Olive St Baulkham Hills NSW 2153",
    "addr:housenumber":"5",
    "addr:postcode":"2153",
    "addr:street":"Olive St",
    "iso:country":"AU",
    "sg:address":"5 Olive St",
    "sg:city":"Baulkham Hills",
    "sg:classifiers":[
        {
            "category":"Restaurant",
            "type":"Food & Drink"
        }
    ],
    "sg:phone":"+61 2 9686 1422",
    "sg:postcode":"2153",
    "sg:province":"NSW",
    "wof:name":"Belmonte's Pizzeria Restaurante",
    "wof:placetype":"venue"
},
  "geometry": {"coordinates":[150.93394470199999,-33.7772102356],"type":"Point"}
}