{
  "type": "Feature",
  "properties": {
    "addr:full":"Olympic Hwy The Rock NSW 2655",
    "addr:postcode":"2655",
    "addr:street":"Olympic Hwy",
    "iso:country":"AU",
    "sg:address":"Olympic Hwy",
    "sg:city":"The Rock",
    "sg:classifiers":[
        {
            "category":"Travel",
            "subcategory":"Hotels & Motels",
            "type":"Entertainment"
        }
    ],
    "sg:phone":"+61 2 6920 2011",
    "sg:postcode":"2655",
    "sg:province":"NSW",
    "sg:tags":[
        "accommodation"
    ],
    "wof:name":"Kings Own Hotel The",
    "wof:placetype":"venue"
},
  "geometry": {"coordinates":[147.118484497,-35.2721786499],"type":"Point"}
}