{
  "type": "Feature",
  "properties": {
    "iso:country":"AU",
    "sg:address":"1 Arthur St",
    "sg:city":"Naracoorte",
    "sg:classifiers":[
        {
            "category":"Home & Garden",
            "subcategory":"Building Materials",
            "type":"Retail Goods"
        }
    ],
    "sg:phone":"+61 408 836 343",
    "sg:postcode":"5271",
    "sg:province":"SA",
    "sg:tags":[
        "merchant",
        "glass",
        "glazier"
    ],
    "wof:name":"Glass Replacement Naracoorte",
    "wof:placetype":"venue"
},
  "geometry": {"coordinates":[140.74822998100001,-36.9554977417],"type":"Point"}
}