{
  "type": "Feature",
  "properties": {
    "iso:country":"AU",
    "sg:address":"199 Queen St",
    "sg:city":"St Marys",
    "sg:classifiers":[
        {
            "category":"Building & Trades",
            "subcategory":"Locksmith",
            "type":"Services"
        }
    ],
    "sg:phone":"+61 1800 654 419",
    "sg:postcode":"2760",
    "sg:province":"NSW",
    "sg:tags":[
        "lock"
    ],
    "wof:name":"Essential Locksmiths",
    "wof:placetype":"venue"
},
  "geometry": {"coordinates":[150.77365112300001,-33.7679862976],"type":"Point"}
}