{
  "type": "Feature",
  "properties": {
    "addr:full":"92 Molle St Hobart TAS 7000",
    "addr:housenumber":"92",
    "addr:postcode":"7000",
    "addr:street":"Molle St",
    "iso:country":"AU",
    "sg:address":"92 Molle St",
    "sg:city":"Hobart",
    "sg:classifiers":[
        {
            "category":"Parking",
            "type":"Transportation"
        }
    ],
    "sg:phone":"+61 3 6239 1023",
    "sg:postcode":"7000",
    "sg:province":"TAS",
    "wof:name":"Gurney Parking",
    "wof:placetype":"venue"
},
  "geometry": {"coordinates":[147.31887817399999,-42.8861961365],"type":"Point"}
}