{
  "type": "Feature",
  "properties": {
    "iso:country":"AU",
    "sg:address":"Unit 1/ 7 Hollingsworth St",
    "sg:city":"Cairns",
    "sg:classifiers":[
        {
            "category":"Professional",
            "subcategory":"Engineering",
            "type":"Services"
        }
    ],
    "sg:phone":"+61 7 4035 6057",
    "sg:postcode":"4870",
    "sg:province":"QLD",
    "sg:tags":[
        "precision",
        "engineer"
    ],
    "wof:name":"Cairns Precision Engineering",
    "wof:placetype":"venue"
},
  "geometry": {"coordinates":[145.761154175,-16.9433403015],"type":"Point"}
}