{
  "type": "Feature",
  "properties": {
    "addr:full":"PO Box 694 Pakenham VIC 3810",
    "addr:postcode":"3810",
    "iso:country":"AU",
    "sg:address":"PO Box 694",
    "sg:city":"Pakenham",
    "sg:classifiers":[
        {
            "category":"Professional",
            "subcategory":"Art Services",
            "type":"Services"
        }
    ],
    "sg:phone":"+61 3 5941 2086",
    "sg:postcode":"3810",
    "sg:province":"VIC",
    "sg:tags":[
        "graphic",
        "designer"
    ],
    "wof:name":"Imprint Graphic Design",
    "wof:placetype":"venue"
},
  "geometry": {"coordinates":[145.481506,-38.071499],"type":"Point"}
}