{
  "type": "Feature",
  "properties": {
    "iso:country":"AU",
    "sg:address":"1 Riches St",
    "sg:city":"Wyalkatchem",
    "sg:classifiers":[
        {
            "category":"Wholesale",
            "subcategory":"Machinery & Supplies",
            "type":"Manufacturing & Wholesale Goods"
        }
    ],
    "sg:phone":"+61 8 9681 1592",
    "sg:postcode":"6485",
    "sg:province":"WA",
    "sg:tags":[
        "agricultural"
    ],
    "wof:name":"Wyalkatchem Mechanical Services",
    "wof:placetype":"venue"
},
  "geometry": {"coordinates":[117.385322571,-31.1789608002],"type":"Point"}
}