{
  "type": "Feature",
  "properties": {
    "iso:country":"AU",
    "sg:address":"870 Nepean Hwy",
    "sg:city":"Rosebud",
    "sg:classifiers":[
        {
            "category":"Cafe",
            "type":"Food & Drink"
        }
    ],
    "sg:phone":"+61 3 5982 2156",
    "sg:postcode":"3939",
    "sg:province":"VIC",
    "wof:name":"Jetty's Cafe",
    "wof:placetype":"venue"
},
  "geometry": {"coordinates":[144.90345764200001,-38.3566513062],"type":"Point"}
}