{
  "type": "Feature",
  "properties": {
    "addr:full":"2/ 95 Hill Ave Burleigh Heads QLD 4220",
    "addr:housenumber":"/ 95",
    "addr:postcode":"4220",
    "addr:street":"Hill Ave",
    "iso:country":"AU",
    "sg:address":"2/ 95 Hill Ave",
    "sg:city":"Burleigh Heads",
    "sg:classifiers":[
        {
            "category":"Professional",
            "subcategory":"Business Services",
            "type":"Services"
        }
    ],
    "sg:phone":"+61 7 5568 7732",
    "sg:postcode":"4220",
    "sg:province":"QLD",
    "sg:tags":[
        "drafting"
    ],
    "wof:name":"Concept Designer Homes",
    "wof:placetype":"venue"
},
  "geometry": {"coordinates":[153.44541931099999,-28.0924129486],"type":"Point"}
}