{
  "type": "Feature",
  "properties": {
    "addr:full":"11/ 222 Kingsway South Melbourne VIC 3205",
    "addr:housenumber":"11 / 222",
    "addr:postcode":"3205",
    "iso:country":"AU",
    "sg:address":"11/ 222",
    "sg:city":"Kingsway South Melbourne",
    "sg:classifiers":[
        {
            "category":"Transit Center",
            "subcategory":"Freight",
            "type":"Transportation"
        }
    ],
    "sg:phone":"+61 3 9685 6996",
    "sg:postcode":"3205",
    "sg:province":"VIC",
    "sg:tags":[
        "agent",
        "shipping"
    ],
    "wof:name":"&#034;K&#034; Line (Australia) Pty Ltd",
    "wof:placetype":"venue"
},
  "geometry": {"coordinates":[144.95585600000001,-37.833881],"type":"Point"}
}