{
  "type": "Feature",
  "properties": {
    "addr:full":"Shop 11/ 1 Tibbing St Nerang QLD 4211",
    "addr:housenumber":"shop 11 / 1",
    "addr:postcode":"4211",
    "addr:street":"Tibbing St",
    "iso:country":"AU",
    "sg:address":"Shop 11/ 1 Tibbing St",
    "sg:city":"Nerang",
    "sg:classifiers":[
        {
            "category":"Professional",
            "subcategory":"Employment Agencies",
            "type":"Services"
        }
    ],
    "sg:phone":"+61 7 5527 2122",
    "sg:postcode":"4211",
    "sg:province":"QLD",
    "wof:name":"On-Q Human Resources",
    "wof:placetype":"venue"
},
  "geometry": {"coordinates":[153.332717895,-27.9927825928],"type":"Point"}
}