{
  "type": "Feature",
  "properties": {
    "addr:full":"80 Elizabeth St Launceston TAS 7250",
    "addr:housenumber":"80",
    "addr:postcode":"7250",
    "addr:street":"Elizabeth St",
    "iso:country":"AU",
    "sg:address":"80 Elizabeth St",
    "sg:city":"Launceston",
    "sg:classifiers":[
        {
            "category":"Personal",
            "subcategory":"Shoe Repair & Shine",
            "type":"Services"
        }
    ],
    "sg:phone":"+61 3 6334 6344",
    "sg:postcode":"7250",
    "sg:province":"TAS",
    "sg:tags":[
        "footwear"
    ],
    "wof:name":"Footwear To Fit",
    "wof:placetype":"venue"
},
  "geometry": {"coordinates":[147.13899230999999,-41.440284729],"type":"Point"}
}