{
  "type": "Feature",
  "properties": {
    "addr:full":"84 Henty St Casterton VIC 3311",
    "addr:housenumber":"84",
    "addr:postcode":"3311",
    "addr:street":"Henty St",
    "iso:country":"AU",
    "sg:address":"84 Henty St",
    "sg:city":"Casterton",
    "sg:classifiers":[
        {
            "category":"Shopping",
            "subcategory":"Shoes",
            "type":"Retail Goods"
        }
    ],
    "sg:phone":"+61 3 5581 1120",
    "sg:postcode":"3311",
    "sg:province":"VIC",
    "sg:tags":[
        "footwear"
    ],
    "wof:name":"Murrell's Shoe Shop",
    "wof:placetype":"venue"
},
  "geometry": {"coordinates":[141.40487670900001,-37.5846099854],"type":"Point"}
}