{
  "type": "Feature",
  "properties": {
    "iso:country":"AU",
    "sg:address":"Yappar St",
    "sg:city":"Karumba",
    "sg:classifiers":[
        {
            "category":"Autos & Motor Vehicles",
            "subcategory":"Motorcycle Sales",
            "type":"Retail Goods"
        }
    ],
    "sg:phone":"+61 7 4745 9159",
    "sg:postcode":"4891",
    "sg:province":"QLD",
    "sg:tags":[
        "outboard"
    ],
    "wof:name":"Jones Marine",
    "wof:placetype":"venue"
},
  "geometry": {"coordinates":[140.84019470199999,-17.4830226898],"type":"Point"}
}