{
  "type": "Feature",
  "properties": {
    "addr:full":"N/a Sydney NSW 2000",
    "addr:housenumber":"n / a",
    "addr:postcode":"2000",
    "iso:country":"AU",
    "sg:address":"N/a",
    "sg:city":"Sydney",
    "sg:classifiers":[
        {
            "category":"Shopping",
            "subcategory":"Clothing, Apparel, & Fashions",
            "type":"Retail Goods"
        }
    ],
    "sg:phone":"+61 2 9223 2449",
    "sg:postcode":"2000",
    "sg:province":"NSW",
    "sg:tags":[
        "accessory"
    ],
    "wof:name":"Oroton Pty Ltd",
    "wof:placetype":"venue"
},
  "geometry": {"coordinates":[151.20811462399999,-33.869052887],"type":"Point"}
}