{
  "type": "Feature",
  "properties": {
    "iso:country":"AU",
    "sg:address":"16 Densley Crt",
    "sg:city":"Bacchus Marsh",
    "sg:classifiers":[
        {
            "category":"Professional",
            "subcategory":"Art Services",
            "type":"Services"
        }
    ],
    "sg:phone":"+61 3 5367 5437",
    "sg:postcode":"3340",
    "sg:province":"VIC",
    "sg:tags":[
        "picture",
        "frame",
        "framing"
    ],
    "wof:name":"Frame -Mem",
    "wof:placetype":"venue"
},
  "geometry": {"coordinates":[144.429626,-37.644108],"type":"Point"}
}