{
  "type": "Feature",
  "properties": {
    "addr:full":"1362 Kingsford Smith Drv Eagle Farm QLD 4009",
    "addr:housenumber":"1362",
    "addr:postcode":"4009",
    "addr:street":"Kingsford Smith Drv",
    "iso:country":"AU",
    "sg:address":"1362 Kingsford Smith Drv",
    "sg:city":"Eagle Farm",
    "sg:classifiers":[
        {
            "category":"Banks & Credit Unions",
            "subcategory":"Bureau De Change",
            "type":"Services"
        }
    ],
    "sg:phone":"+61 7 3260 1383",
    "sg:postcode":"4009",
    "sg:province":"QLD",
    "sg:tags":[
        "gas",
        "natural",
        "lp",
        "equipment"
    ],
    "wof:name":"Gas Cylinder Testing & Inspection Services",
    "wof:placetype":"venue"
},
  "geometry": {"coordinates":[153.10949707,-27.4302616119],"type":"Point"}
}