{
  "type": "Feature",
  "properties": {
    "addr:full":"13 Courtenay Rd Rose Bay NSW 2029",
    "addr:housenumber":"13",
    "addr:postcode":"2029",
    "addr:street":"Courtenay Rd",
    "iso:country":"AU",
    "sg:address":"13 Courtenay Rd",
    "sg:city":"Rose Bay",
    "sg:classifiers":[
        {
            "category":"Shopping",
            "subcategory":"Computers & Home Electronics",
            "type":"Retail Goods"
        }
    ],
    "sg:phone":"+61 2 9371 1872",
    "sg:postcode":"2029",
    "sg:province":"NSW",
    "sg:tags":[
        "equipment",
        "multimedia"
    ],
    "wof:name":"The Knowledge Mill Pty Ltd",
    "wof:placetype":"venue"
},
  "geometry": {"coordinates":[151.27513122600001,-33.8679351807],"type":"Point"}
}