{
  "type": "Feature",
  "properties": {
    "addr:full":"16 Lovell St Young NSW 2594",
    "addr:housenumber":"16",
    "addr:postcode":"2594",
    "addr:street":"Lovell St",
    "iso:country":"AU",
    "sg:address":"16 Lovell St",
    "sg:city":"Young",
    "sg:classifiers":[
        {
            "category":"Structure",
            "subcategory":"Tunnel",
            "type":"Public Place"
        }
    ],
    "sg:phone":"+61 2 6382 5700",
    "sg:postcode":"2594",
    "sg:province":"NSW",
    "sg:tags":[
        "cleaner",
        "industrial",
        "vacuum"
    ],
    "wof:name":"Vacshack Pty Ltd",
    "wof:placetype":"venue"
},
  "geometry": {"coordinates":[148.29309082,-34.3109664917],"type":"Point"}
}