{
  "type": "Feature",
  "properties": {
    "iso:country":"AU",
    "sg:address":"Suite 9, 33 Stanley St",
    "sg:city":"Bankstown",
    "sg:classifiers":[
        {
            "category":"Building & Trades",
            "subcategory":"Pest Control",
            "type":"Services"
        }
    ],
    "sg:phone":"+61 1800 048 200",
    "sg:postcode":"2200",
    "sg:province":"NSW",
    "sg:website":"http://www.enviropest.com.au",
    "wof:name":"Enviropest Pty Ltd",
    "wof:placetype":"venue"
},
  "geometry": {"coordinates":[151.036697,-33.920742],"type":"Point"}
}