{
  "type": "Feature",
  "properties": {
    "addr:full":"41 Tolpuddle Drv Richmond TAS 7025",
    "addr:housenumber":"41",
    "addr:postcode":"7025",
    "addr:street":"Tolpuddle Drv",
    "iso:country":"AU",
    "sg:address":"41 Tolpuddle Drv",
    "sg:city":"Richmond",
    "sg:classifiers":[
        {
            "category":"Wholesale",
            "subcategory":"Construction Materials",
            "type":"Manufacturing & Wholesale Goods"
        }
    ],
    "sg:phone":"+61 3 6260 1008",
    "sg:postcode":"7025",
    "sg:province":"TAS",
    "sg:tags":[
        "protective",
        "coating"
    ],
    "wof:name":"Technicote Tasmania Australia",
    "wof:placetype":"venue"
},
  "geometry": {"coordinates":[147.388397217,-42.7663002014],"type":"Point"}
}