{
  "type": "Feature",
  "properties": {
    "iso:country":"AU",
    "sg:address":"5 Hambridge St",
    "sg:city":"Thevenard",
    "sg:classifiers":[
        {
            "category":"Building & Trades",
            "subcategory":"Construction",
            "type":"Services"
        }
    ],
    "sg:phone":"+61 8 8625 2484",
    "sg:postcode":"5690",
    "sg:province":"SA",
    "sg:tags":[
        "contractor"
    ],
    "wof:name":"Uzzell J D & M R Pty Ltd",
    "wof:placetype":"venue"
},
  "geometry": {"coordinates":[133.65325927699999,-32.1455001831],"type":"Point"}
}