{
  "type": "Feature",
  "properties": {
    "iso:country":"AU",
    "sg:address":"26 Don St",
    "sg:city":"Bowen",
    "sg:classifiers":[
        {
            "category":"Professional",
            "subcategory":"Engineering",
            "type":"Services"
        }
    ],
    "sg:phone":"+61 7 4786 2611",
    "sg:postcode":"4805",
    "sg:province":"QLD",
    "sg:tags":[
        "manufacturing",
        "engineer"
    ],
    "wof:name":"Maltby Engineering Pty Ltd",
    "wof:placetype":"venue"
},
  "geometry": {"coordinates":[148.23143005399999,-20.0093536377],"type":"Point"}
}