{
  "type": "Feature",
  "properties": {
    "iso:country":"AU",
    "sg:address":"269a Edgecliff Rd",
    "sg:city":"Woollahra",
    "sg:classifiers":[
        {
            "category":"Landmark",
            "subcategory":"Square",
            "type":"Public Place"
        }
    ],
    "sg:phone":"+61 2 9327 1274",
    "sg:postcode":"2025",
    "sg:province":"NSW",
    "sg:tags":[
        "lampshade"
    ],
    "wof:name":"Silkcrafts Design",
    "wof:placetype":"venue"
},
  "geometry": {"coordinates":[151.24232482900001,-33.8845596313],"type":"Point"}
}