{
  "type": "Feature",
  "properties": {
    "addr:full":"15 Curtis St Armidale NSW 2350",
    "addr:housenumber":"15",
    "addr:postcode":"2350",
    "addr:street":"Curtis St",
    "iso:country":"AU",
    "sg:address":"15 Curtis St",
    "sg:city":"Armidale",
    "sg:classifiers":[
        {
            "category":"Building & Trades",
            "subcategory":"Landscaping Services",
            "type":"Services"
        }
    ],
    "sg:phone":"+61 2 6772 8467",
    "sg:postcode":"2350",
    "sg:province":"NSW",
    "sg:tags":[
        "grazier"
    ],
    "wof:name":"McLeod D J",
    "wof:placetype":"venue"
},
  "geometry": {"coordinates":[151.67091369600001,-30.4962463379],"type":"Point"}
}