{
  "type": "Feature",
  "properties": {
    "iso:country":"AU",
    "sg:address":"220 Pakington St",
    "sg:city":"Geelong West",
    "sg:classifiers":[
        {
            "category":"Fast Food",
            "type":"Food & Drink"
        }
    ],
    "sg:phone":"+61 3 5229 6738",
    "sg:postcode":"3218",
    "sg:province":"VIC",
    "sg:tags":[
        "away",
        "take"
    ],
    "wof:name":"Pako Fish & Chips & Take Away",
    "wof:placetype":"venue"
},
  "geometry": {"coordinates":[144.34806823700001,-38.1428070068],"type":"Point"}
}