{
  "type": "Feature",
  "properties": {
    "iso:country":"AU",
    "sg:address":"17 Craigieburn Rd",
    "sg:city":"Craigieburn",
    "sg:classifiers":[
        {
            "category":"Health Services",
            "subcategory":"Health Practitioner",
            "type":"Services"
        }
    ],
    "sg:phone":"+61 3 9305 7263",
    "sg:postcode":"3064",
    "sg:province":"VIC",
    "sg:tags":[
        "naturopath"
    ],
    "wof:name":"Michelle Smigielski",
    "wof:placetype":"venue"
},
  "geometry": {"coordinates":[144.941009522,-37.5990982056],"type":"Point"}
}