{
  "type": "Feature",
  "properties": {
    "addr:full":"121 Greenhill Rd Unley SA 5061",
    "addr:housenumber":"121",
    "addr:postcode":"5061",
    "addr:street":"Greenhill Rd",
    "iso:country":"AU",
    "sg:address":"121 Greenhill Rd",
    "sg:city":"Unley",
    "sg:classifiers":[
        {
            "category":"Professional",
            "subcategory":"Accounting & Tax Preparation",
            "type":"Services"
        }
    ],
    "sg:phone":"+61 8 8373 5111",
    "sg:postcode":"5061",
    "sg:province":"SA",
    "sg:tags":[
        "accountant",
        "auditor"
    ],
    "wof:name":"Basedows",
    "wof:placetype":"venue"
},
  "geometry": {"coordinates":[138.60325622600001,-34.9412956238],"type":"Point"}
}