{
  "type": "Feature",
  "properties": {
    "addr:full":"6 Bogan St Parkes NSW 2870",
    "addr:housenumber":"6",
    "addr:postcode":"2870",
    "addr:street":"Bogan St",
    "iso:country":"AU",
    "sg:address":"6 Bogan St",
    "sg:city":"Parkes",
    "sg:classifiers":[
        {
            "category":"Building & Trades",
            "subcategory":"Construction",
            "type":"Services"
        }
    ],
    "sg:phone":"+61 2 6862 6612",
    "sg:postcode":"2870",
    "sg:province":"NSW",
    "sg:tags":[
        "contractor"
    ],
    "wof:name":"Kitchen's Plus",
    "wof:placetype":"venue"
},
  "geometry": {"coordinates":[148.171539,-33.141079],"type":"Point"}
}