{
  "type": "Feature",
  "properties": {
    "addr:full":"Level 1, 30 Collins St Melbourne VIC 3000",
    "addr:housenumber":"30",
    "addr:postcode":"3000",
    "addr:street":"Collins St",
    "iso:country":"AU",
    "sg:address":"Level 1, 30 Collins St",
    "sg:city":"Melbourne",
    "sg:classifiers":[
        {
            "category":"Travel",
            "subcategory":"Travel Agent",
            "type":"Entertainment"
        }
    ],
    "sg:phone":"+61 3 8663 0222",
    "sg:postcode":"3000",
    "sg:province":"VIC",
    "sg:tags":[
        "consultant"
    ],
    "wof:name":"Garuda Indonesia",
    "wof:placetype":"venue"
},
  "geometry": {"coordinates":[144.97265625,-37.8135528564],"type":"Point"}
}