{
  "type": "Feature",
  "properties": {
    "iso:country":"AU",
    "sg:address":"16 Pindari Rd",
    "sg:city":"Dover Heights",
    "sg:classifiers":[
        {
            "category":"Health Services",
            "subcategory":"Health Practitioner",
            "type":"Services"
        }
    ],
    "sg:phone":"+61 2 9371 4158",
    "sg:postcode":"2030",
    "sg:province":"NSW",
    "sg:tags":[
        "physiotherapist"
    ],
    "wof:name":"Doctors Helen K",
    "wof:placetype":"venue"
},
  "geometry": {"coordinates":[151.28158569300001,-33.8794822693],"type":"Point"}
}