{
  "type": "Feature",
  "properties": {
    "iso:country":"AU",
    "sg:address":"229a Murrumbeena Rd",
    "sg:city":"Murrumbeena",
    "sg:classifiers":[
        {
            "category":"Fast Food",
            "type":"Food & Drink"
        }
    ],
    "sg:phone":"+61 3 9568 8370",
    "sg:postcode":"3163",
    "sg:province":"VIC",
    "sg:tags":[
        "away",
        "take"
    ],
    "wof:name":"Blue Sea Fish & Chips Take Away",
    "wof:placetype":"venue"
},
  "geometry": {"coordinates":[145.06419372600001,-37.9012298584],"type":"Point"}
}