{
  "type": "Feature",
  "properties": {
    "iso:country":"AU",
    "sg:address":"81- 85 Cranbourne Rd",
    "sg:city":"Langwarrin",
    "sg:classifiers":[
        {
            "category":"Personal",
            "subcategory":"Massage",
            "type":"Services"
        }
    ],
    "sg:phone":"+61 3 9789 8999",
    "sg:postcode":"3910",
    "sg:province":"VIC",
    "sg:tags":[
        "therapy"
    ],
    "wof:name":"Jackson Lyndie",
    "wof:placetype":"venue"
},
  "geometry": {"coordinates":[145.18035888700001,-38.1550102234],"type":"Point"}
}