{
  "type": "Feature",
  "properties": {
    "addr:full":"19 Port Pirie St Bibra Lake WA 6163",
    "addr:housenumber":"19",
    "addr:postcode":"6163",
    "addr:street":"Port Pirie St",
    "iso:country":"AU",
    "sg:address":"19 Port Pirie St",
    "sg:city":"Bibra Lake",
    "sg:classifiers":[
        {
            "category":"Utilities",
            "subcategory":"Electric",
            "type":"Services"
        }
    ],
    "sg:phone":"+61 8 9434 1514",
    "sg:postcode":"6163",
    "sg:province":"WA",
    "sg:tags":[
        "electrical",
        "contractor"
    ],
    "wof:name":"Triventi Electrical Services",
    "wof:placetype":"venue"
},
  "geometry": {"coordinates":[115.799362,-32.097084],"type":"Point"}
}