{
  "type": "Feature",
  "properties": {
    "iso:country":"AU",
    "sg:address":"Factory 5, 6 Leedham Pl",
    "sg:city":"Riverwood",
    "sg:classifiers":[
        {
            "category":"Building & Trades",
            "subcategory":"Cleaning & Sanitation",
            "type":"Services"
        }
    ],
    "sg:phone":"+61 2 9534 1111",
    "sg:postcode":"2210",
    "sg:province":"NSW",
    "sg:tags":[
        "chemical",
        "pressure",
        "steam",
        "contractor"
    ],
    "wof:name":"Kleenco",
    "wof:placetype":"venue"
},
  "geometry": {"coordinates":[151.049255,-33.939499],"type":"Point"}
}