{
  "type": "Feature",
  "properties": {
    "addr:full":"19 Victoria St Smithfield NSW 2164",
    "addr:housenumber":"19",
    "addr:postcode":"2164",
    "addr:street":"Victoria St",
    "iso:country":"AU",
    "sg:address":"19 Victoria St",
    "sg:city":"Smithfield",
    "sg:classifiers":[
        {
            "category":"Retail",
            "subcategory":"Auto Repair",
            "type":"Services"
        }
    ],
    "sg:phone":"+61 2 9604 3330",
    "sg:postcode":"2164",
    "sg:province":"NSW",
    "sg:tags":[
        "muffler",
        "exhaust",
        "system"
    ],
    "wof:name":"Carline Mufflers",
    "wof:placetype":"venue"
},
  "geometry": {"coordinates":[150.941864014,-33.8517227173],"type":"Point"}
}