{
  "type": "Feature",
  "properties": {
    "addr:full":"16 Minchinton St Caloundra QLD 4551",
    "addr:housenumber":"16",
    "addr:postcode":"4551",
    "addr:street":"Minchinton St",
    "iso:country":"AU",
    "sg:address":"16 Minchinton St",
    "sg:city":"Caloundra",
    "sg:classifiers":[
        {
            "category":"Professional",
            "subcategory":"Business Services",
            "type":"Services"
        }
    ],
    "sg:phone":"+61 7 5491 6444",
    "sg:postcode":"4551",
    "sg:province":"QLD",
    "sg:tags":[
        "management",
        "event"
    ],
    "wof:name":"Sunshine Coast Events Centre",
    "wof:placetype":"venue"
},
  "geometry": {"coordinates":[153.13064575199999,-26.8019561768],"type":"Point"}
}