{
  "type": "Feature",
  "properties": {
    "addr:full":"Shop 2009 Westfield Shopngtwn Miranda NSW 2228",
    "addr:housenumber":"2009",
    "addr:postcode":"2228",
    "addr:street":"Westfield Shopngtwn Miranda",
    "iso:country":"AU",
    "sg:address":"Shop 2009 Westfield Shopngtwn",
    "sg:city":"Miranda",
    "sg:classifiers":[
        {
            "category":"Fast Food",
            "type":"Food & Drink"
        }
    ],
    "sg:phone":"+61 2 9526 1988",
    "sg:postcode":"2228",
    "sg:province":"NSW",
    "sg:tags":[
        "away",
        "take"
    ],
    "wof:name":"Lam's Chinese & Asian Food",
    "wof:placetype":"venue"
},
  "geometry": {"coordinates":[151.102493286,-34.033908844],"type":"Point"}
}