{
  "type": "Feature",
  "properties": {
    "addr:full":"19a Letitia St Oatley NSW 2223",
    "addr:housenumber":"19a",
    "addr:postcode":"2223",
    "addr:street":"Letitia St",
    "iso:country":"AU",
    "sg:address":"19a Letitia St",
    "sg:city":"Oatley",
    "sg:classifiers":[
        {
            "category":"Health Services",
            "subcategory":"Doctor",
            "type":"Services"
        }
    ],
    "sg:phone":"+61 2 9580 3228",
    "sg:postcode":"2223",
    "sg:province":"NSW",
    "sg:tags":[
        "medical",
        "practitioner"
    ],
    "wof:name":"Letton Toni",
    "wof:placetype":"venue"
},
  "geometry": {"coordinates":[151.08128356899999,-33.9814071655],"type":"Point"}
}