{
  "type": "Feature",
  "properties": {
    "iso:country":"AU",
    "sg:address":"545 Great Ocean Rd",
    "sg:city":"Bellbrae",
    "sg:classifiers":[
        {
            "category":"Travel",
            "subcategory":"Hotels & Motels",
            "type":"Entertainment"
        }
    ],
    "sg:phone":"+61 3 5261 3844",
    "sg:postcode":"3228",
    "sg:province":"VIC",
    "sg:tags":[
        "accommodation"
    ],
    "wof:name":"Bells Estate Great Ocean Road Cottages",
    "wof:placetype":"venue"
},
  "geometry": {"coordinates":[144.26196300000001,-38.342705],"type":"Point"}
}