{
  "type": "Feature",
  "properties": {
    "iso:country":"AU",
    "sg:address":"123 Russell St",
    "sg:city":"Toowoomba",
    "sg:classifiers":[
        {
            "category":"Utilities",
            "subcategory":"Natural Gas",
            "type":"Services"
        }
    ],
    "sg:phone":"+61 7 4632 4534",
    "sg:postcode":"4350",
    "sg:province":"QLD",
    "sg:tags":[
        "magnetic",
        "therapy"
    ],
    "wof:name":"Reinke's Pharmacy & Sports Medicine Supplies",
    "wof:placetype":"venue"
},
  "geometry": {"coordinates":[151.946609,-27.558186],"type":"Point"}
}