{
  "type": "Feature",
  "properties": {
    "addr:full":"Shop 2143 Highpoint Shopng Cntr Rosamond Rd Maribyrnong VIC 3032",
    "addr:housenumber":"2143",
    "addr:postcode":"3032",
    "addr:street":"Highpoint Shopng Cntr Rosamond Rd",
    "iso:country":"AU",
    "sg:address":"Shop 2143 Highpoint Shopng Cntr Rosamond Rd",
    "sg:city":"Maribyrnong",
    "sg:classifiers":[
        {
            "category":"Shopping",
            "subcategory":"Clothing, Apparel, & Fashions",
            "type":"Retail Goods"
        }
    ],
    "sg:phone":"+61 3 9317 4659",
    "sg:postcode":"3032",
    "sg:province":"VIC",
    "sg:tags":[
        "menswear"
    ],
    "wof:name":"Lowes",
    "wof:placetype":"venue"
},
  "geometry": {"coordinates":[144.88632200000001,-37.771435],"type":"Point"}
}