{
  "type": "Feature",
  "properties": {
    "addr:full":"Victoria St Eaglehawk VIC 3556",
    "addr:postcode":"3556",
    "addr:street":"Victoria St",
    "iso:country":"AU",
    "sg:address":"Victoria St",
    "sg:city":"Eaglehawk",
    "sg:classifiers":[
        {
            "category":"Arena",
            "subcategory":"Sports Club",
            "type":"Entertainment"
        }
    ],
    "sg:phone":"+61 3 5446 7300",
    "sg:postcode":"3556",
    "sg:province":"VIC",
    "sg:tags":[
        "organisation",
        "sporting"
    ],
    "wof:name":"Eaglehawk & Bendigo Junior Badminton Association",
    "wof:placetype":"venue"
},
  "geometry": {"coordinates":[144.25730895999999,-36.716091156],"type":"Point"}
}