{
  "type": "Feature",
  "properties": {
    "iso:country":"AU",
    "sg:address":"Lvl 11",
    "sg:city":", Tower B, Zenith Centre Pacific Hwy, Chatswo",
    "sg:classifiers":[
        {
            "category":"Banks & Credit Unions",
            "subcategory":"Atm",
            "type":"Services"
        }
    ],
    "sg:phone":"+61 1800 069 065",
    "sg:postcode":"2067",
    "sg:province":"NSW",
    "sg:tags":[
        "wholesaler",
        "mfrs",
        "envelope"
    ],
    "wof:name":"Square Envelope Company The",
    "wof:placetype":"venue"
},
  "geometry": {"coordinates":[151.179489136,-33.7937393188],"type":"Point"}
}