{
  "type": "Feature",
  "properties": {
    "addr:full":"1 Craine St South Melbourne VIC 3205",
    "addr:housenumber":"1",
    "addr:postcode":"3205",
    "addr:street":"Craine St",
    "iso:country":"AU",
    "sg:address":"1 Craine St",
    "sg:city":"South Melbourne",
    "sg:classifiers":[
        {
            "category":"Professional",
            "type":"Services"
        }
    ],
    "sg:phone":"+61 13 15 21",
    "sg:postcode":"3205",
    "sg:province":"VIC",
    "sg:tags":[
        "courier"
    ],
    "wof:name":"CTI Logistics",
    "wof:placetype":"venue"
},
  "geometry": {"coordinates":[144.961243,-37.830551],"type":"Point"}
}