{
  "type": "Feature",
  "properties": {
    "addr:full":"47 Amhurst St Slade Point QLD 4740",
    "addr:housenumber":"47",
    "addr:postcode":"4740",
    "addr:street":"Amhurst St",
    "iso:country":"AU",
    "sg:address":"47 Amhurst St",
    "sg:city":"Slade Point",
    "sg:classifiers":[
        {
            "category":"Building & Trades",
            "subcategory":"Construction",
            "type":"Services"
        }
    ],
    "sg:phone":"+61 7 4955 4261",
    "sg:postcode":"4740",
    "sg:province":"QLD",
    "sg:tags":[
        "contractor"
    ],
    "wof:name":"Leyk & Cooper Masonry",
    "wof:placetype":"venue"
},
  "geometry": {"coordinates":[149.22384600000001,-21.075603],"type":"Point"}
}