{
  "type": "Feature",
  "properties": {
    "addr:full":"8 Towner St Galston NSW 2159",
    "addr:housenumber":"8",
    "addr:postcode":"2159",
    "addr:street":"Towner St",
    "iso:country":"AU",
    "sg:address":"8 Towner St",
    "sg:city":"Galston",
    "sg:classifiers":[
        {
            "category":"Building & Trades",
            "subcategory":"Landscaping Services",
            "type":"Services"
        }
    ],
    "sg:phone":"+61 2 9653 1136",
    "sg:postcode":"2159",
    "sg:province":"NSW",
    "sg:tags":[
        "designer",
        "landscape",
        "contractor"
    ],
    "wof:name":"Landscape 2000",
    "wof:placetype":"venue"
},
  "geometry": {"coordinates":[151.074981689,-33.6447792053],"type":"Point"}
}