{
  "type": "Feature",
  "properties": {
    "addr:full":"Tasman Hwy St Helens TAS 7216",
    "addr:postcode":"7216",
    "addr:street":"Tasman Hwy",
    "iso:country":"AU",
    "sg:address":"Tasman Hwy St",
    "sg:city":"Helens",
    "sg:classifiers":[
        {
            "category":"Recreation",
            "subcategory":"Fishing",
            "type":"Entertainment"
        }
    ],
    "sg:phone":"+61 3 6376 2800",
    "sg:postcode":"7216",
    "sg:province":"TAS",
    "sg:tags":[
        "tackle"
    ],
    "wof:name":"Georges Bay Marine Pty Ltd",
    "wof:placetype":"venue"
},
  "geometry": {"coordinates":[148.23608400000001,-41.315479],"type":"Point"}
}