{
  "type": "Feature",
  "properties": {
    "iso:country":"AU",
    "sg:address":"Shp 4/ 268 Balcombe Rd",
    "sg:city":"Beaumaris",
    "sg:classifiers":[
        {
            "category":"Personal",
            "subcategory":"Beauty Salon",
            "type":"Services"
        }
    ],
    "sg:phone":"+61 3 9585 4335",
    "sg:postcode":"3193",
    "sg:province":"VIC",
    "sg:tags":[
        "hairdresser"
    ],
    "wof:name":"Mischa Hair Salon",
    "wof:placetype":"venue"
},
  "geometry": {"coordinates":[145.05279540999999,-37.979637146],"type":"Point"}
}