{
  "type": "Feature",
  "properties": {
    "iso:country":"AU",
    "sg:address":"3 Brownleaf St",
    "sg:city":"Mansfield",
    "sg:classifiers":[
        {
            "category":"Manufacturing",
            "subcategory":"Printing",
            "type":"Manufacturing & Wholesale Goods"
        }
    ],
    "sg:phone":"+61 7 3219 3333",
    "sg:postcode":"4122",
    "sg:province":"QLD",
    "sg:tags":[
        "wholesaler",
        "mfrs",
        "greeting",
        "card"
    ],
    "wof:name":"Borivale Pty Ltd",
    "wof:placetype":"venue"
},
  "geometry": {"coordinates":[153.09890747099999,-27.5208950043],"type":"Point"}
}