{
  "type": "Feature",
  "properties": {
    "addr:full":"64 Ferry Rd Southport QLD 4215",
    "addr:housenumber":"64",
    "addr:postcode":"4215",
    "addr:street":"Ferry Rd",
    "iso:country":"AU",
    "sg:address":"64 Ferry Rd",
    "sg:city":"Southport",
    "sg:classifiers":[
        {
            "category":"Autos & Motor Vehicles",
            "subcategory":"Fuel & Gas Station",
            "type":"Retail Goods"
        }
    ],
    "sg:phone":"+61 7 5532 7988",
    "sg:postcode":"4215",
    "sg:province":"QLD",
    "wof:name":"Liberty Service Station",
    "wof:placetype":"venue"
},
  "geometry": {"coordinates":[153.411346436,-27.9767341614],"type":"Point"}
}