{
  "type": "Feature",
  "properties": {
    "addr:full":"835 B Mt Alexander Rd Moonee Ponds VIC 3039",
    "addr:housenumber":"835 b",
    "addr:postcode":"3039",
    "addr:street":"Mt Alexander Rd",
    "iso:country":"AU",
    "sg:address":"835 B Mt Alexander Rd",
    "sg:city":"Moonee Ponds",
    "sg:classifiers":[
        {
            "category":"Banks & Credit Unions",
            "subcategory":"Financial Services",
            "type":"Services"
        }
    ],
    "sg:phone":"+61 3 9372 9899",
    "sg:postcode":"3039",
    "sg:province":"VIC",
    "sg:tags":[
        "planning"
    ],
    "wof:name":"Maynards Financial Services pty ltd",
    "wof:placetype":"venue"
},
  "geometry": {"coordinates":[144.923157,-37.764397],"type":"Point"}
}