{
  "type": "Feature",
  "properties": {
    "addr:full":"72 Cassia St Red Cliffs VIC 3496",
    "addr:housenumber":"72",
    "addr:postcode":"3496",
    "addr:street":"Cassia St",
    "iso:country":"AU",
    "sg:address":"72 Cassia St",
    "sg:city":"Red Cliffs",
    "sg:classifiers":[
        {
            "category":"Home & Garden",
            "subcategory":"Building Materials",
            "type":"Retail Goods"
        }
    ],
    "sg:phone":"+61 408 502 153",
    "sg:postcode":"3496",
    "sg:province":"VIC",
    "sg:tags":[
        "skylight"
    ],
    "wof:name":"Laings Plumbing",
    "wof:placetype":"venue"
},
  "geometry": {"coordinates":[142.21409606899999,-34.3072357178],"type":"Point"}
}