{
  "type": "Feature",
  "properties": {
    "addr:full":"5 Graham St Narooma NSW 2546",
    "addr:housenumber":"5",
    "addr:postcode":"2546",
    "addr:street":"Graham St",
    "iso:country":"AU",
    "sg:address":"5 Graham St",
    "sg:city":"Narooma",
    "sg:classifiers":[
        {
            "category":"Retail",
            "subcategory":"Funeral Services",
            "type":"Services"
        }
    ],
    "sg:phone":"+61 2 4476 3888",
    "sg:postcode":"2546",
    "sg:province":"NSW",
    "sg:tags":[
        "cremation"
    ],
    "wof:name":"Narooma District Funerals Pty Ltd",
    "wof:placetype":"venue"
},
  "geometry": {"coordinates":[150.123580933,-36.2145271301],"type":"Point"}
}