{
  "type": "Feature",
  "properties": {
    "addr:full":"12 Massey St Gladesville NSW 2111",
    "addr:housenumber":"12",
    "addr:postcode":"2111",
    "addr:street":"Massey St",
    "iso:country":"AU",
    "sg:address":"12 Massey St",
    "sg:city":"Gladesville",
    "sg:classifiers":[
        {
            "category":"Home & Garden",
            "subcategory":"Carpets & Floor Coverings",
            "type":"Retail Goods"
        }
    ],
    "sg:phone":"+61 2 9879 0333",
    "sg:postcode":"2111",
    "sg:province":"NSW",
    "sg:tags":[
        "tile",
        "wall",
        "layer"
    ],
    "wof:name":"Onitsoga Tiling",
    "wof:placetype":"venue"
},
  "geometry": {"coordinates":[151.128616333,-33.8299636841],"type":"Point"}
}