{
  "type": "Feature",
  "properties": {
    "iso:country":"AU",
    "sg:address":"9 Hill St",
    "sg:city":"Kempsey",
    "sg:classifiers":[
        {
            "category":"Communications",
            "subcategory":"Television Station",
            "type":"Services"
        }
    ],
    "sg:phone":"+61 2 6562 6691",
    "sg:postcode":"2440",
    "sg:province":"NSW",
    "sg:tags":[
        "mfrs",
        "tank",
        "installation",
        "septic"
    ],
    "wof:name":"Evill Frank Plumbing",
    "wof:placetype":"venue"
},
  "geometry": {"coordinates":[152.837952,-31.087608],"type":"Point"}
}