{
  "type": "Feature",
  "properties": {
    "iso:country":"AU",
    "sg:address":"313 Pier St",
    "sg:city":"Perth",
    "sg:classifiers":[
        {
            "category":"Professional",
            "subcategory":"Accounting & Tax Preparation",
            "type":"Services"
        }
    ],
    "sg:phone":"+61 8 9328 3288",
    "sg:postcode":"6000",
    "sg:province":"WA",
    "sg:tags":[
        "consultant",
        "taxation"
    ],
    "wof:name":"Buck E & A",
    "wof:placetype":"venue"
},
  "geometry": {"coordinates":[115.868469238,-31.9455184937],"type":"Point"}
}