{
  "type": "Feature",
  "properties": {
    "addr:full":"No 1 Formation St Paget QLD 4740",
    "addr:postcode":"4740",
    "addr:street":"Formation St",
    "iso:country":"AU",
    "sg:address":"No 1 Formation St",
    "sg:city":"Paget",
    "sg:classifiers":[
        {
            "category":"Manufacturing",
            "subcategory":"Tools & Machinery",
            "type":"Manufacturing & Wholesale Goods"
        }
    ],
    "sg:phone":"+61 7 4963 3633",
    "sg:postcode":"4740",
    "sg:province":"QLD",
    "sg:tags":[
        "earth",
        "excavating",
        "moving",
        "equipment"
    ],
    "wof:name":"MMR Services Pty Ltd",
    "wof:placetype":"venue"
},
  "geometry": {"coordinates":[149.16188,-21.181732],"type":"Point"}
}