{
  "type": "Feature",
  "properties": {
    "addr:full":"12 Trout Pl St Clair NSW 2759",
    "addr:housenumber":"12",
    "addr:postcode":"2759",
    "addr:street":"Trout Pl St",
    "iso:country":"AU",
    "sg:address":"12 Trout Pl",
    "sg:city":"St Clair",
    "sg:classifiers":[
        {
            "category":"Building & Trades",
            "subcategory":"Landscaping Services",
            "type":"Services"
        }
    ],
    "sg:phone":"+61 2 9670 5529",
    "sg:postcode":"2759",
    "sg:province":"NSW",
    "sg:tags":[
        "stump",
        "tree",
        "felling",
        "removal"
    ],
    "wof:name":"Just Stumps",
    "wof:placetype":"venue"
},
  "geometry": {"coordinates":[150.77441406200001,-33.8059196472],"type":"Point"}
}