{
  "type": "Feature",
  "properties": {
    "addr:full":"3- 5 Arwun Crt Springvale VIC 3171",
    "addr:housenumber":"5",
    "addr:postcode":"3171",
    "addr:street":"Arwun Crt",
    "iso:country":"AU",
    "sg:address":"3- 5 Arwun Crt",
    "sg:city":"Springvale",
    "sg:classifiers":[
        {
            "category":"Autos & Motor Vehicles",
            "subcategory":"Automobile Sales",
            "type":"Retail Goods"
        }
    ],
    "sg:phone":"+61 3 9767 4900",
    "sg:postcode":"3171",
    "sg:province":"VIC",
    "sg:tags":[
        "equipment",
        "trailer"
    ],
    "wof:name":"Rising Star",
    "wof:placetype":"venue"
},
  "geometry": {"coordinates":[145.143112183,-37.9456367493],"type":"Point"}
}