{
  "type": "Feature",
  "properties": {
    "addr:full":"3 Euroka Ave Malua Bay NSW 2536",
    "addr:housenumber":"3",
    "addr:postcode":"2536",
    "addr:street":"Euroka Ave Malua",
    "iso:country":"AU",
    "sg:address":"3 Euroka Ave",
    "sg:city":"Malua Bay",
    "sg:classifiers":[
        {
            "category":"Personal",
            "subcategory":"Beauty Salon",
            "type":"Services"
        }
    ],
    "sg:phone":"+61 2 4471 1461",
    "sg:postcode":"2536",
    "sg:province":"NSW",
    "sg:tags":[
        "hairdresser"
    ],
    "wof:name":"Christelaines Hair & Beauty Salon",
    "wof:placetype":"venue"
},
  "geometry": {"coordinates":[150.22969055199999,-35.7826080322],"type":"Point"}
}