{
  "type": "Feature",
  "properties": {
    "iso:country":"AU",
    "sg:address":"8 Cottonview Rd",
    "sg:city":"Emerald",
    "sg:classifiers":[
        {
            "category":"Shopping",
            "type":"Retail Goods"
        }
    ],
    "sg:phone":"+61 7 4987 6900",
    "sg:postcode":"4720",
    "sg:province":"QLD",
    "sg:tags":[
        "equipment",
        "safety",
        "accessory"
    ],
    "wof:name":"Hayson-Smith Fire Pty Ltd",
    "wof:placetype":"venue"
},
  "geometry": {"coordinates":[148.151566,-23.503477],"type":"Point"}
}