{
  "type": "Feature",
  "properties": {
    "iso:country":"AU",
    "sg:address":"1017 Pacific Hwy",
    "sg:city":"Pymble",
    "sg:classifiers":[
        {
            "category":"Professional",
            "subcategory":"Art Services",
            "type":"Services"
        }
    ],
    "sg:phone":"+61 2 9488 9088",
    "sg:postcode":"2073",
    "sg:province":"NSW",
    "wof:name":"Pymble Gallery",
    "wof:placetype":"venue"
},
  "geometry": {"coordinates":[151.139404297,-33.7424087524],"type":"Point"}
}