{
  "type": "Feature",
  "properties": {
    "addr:full":"Cnr. Bosworth & Windsor Sts Richmond NSW 2753",
    "addr:postcode":"2753",
    "iso:country":"AU",
    "sg:address":"Cnr. Bosworth & Windsor Sts",
    "sg:city":"Richmond",
    "sg:classifiers":[
        {
            "category":"Building & Trades",
            "subcategory":"Construction",
            "type":"Services"
        }
    ],
    "sg:phone":"+61 2 4578 4199",
    "sg:postcode":"2753",
    "sg:province":"NSW",
    "sg:tags":[
        "welding"
    ],
    "wof:name":"T.H. Williams Automotive",
    "wof:placetype":"venue"
},
  "geometry": {"coordinates":[150.74740600600001,-33.5961914062],"type":"Point"}
}