{
  "type": "Feature",
  "properties": {
    "addr:full":"13 Hampden Rd Wentworthville NSW 2145",
    "addr:housenumber":"13",
    "addr:postcode":"2145",
    "addr:street":"Hampden Rd",
    "iso:country":"AU",
    "sg:address":"13 Hampden Rd",
    "sg:city":"Wentworthville",
    "sg:classifiers":[
        {
            "category":"Education",
            "subcategory":"Kindergarten",
            "type":"Public Place"
        }
    ],
    "sg:phone":"+61 2 9896 4504",
    "sg:postcode":"2145",
    "sg:province":"NSW",
    "sg:tags":[
        "pre-schools"
    ],
    "wof:name":"St Mary Kindergarten Long Day Care Centre",
    "wof:placetype":"venue"
},
  "geometry": {"coordinates":[150.96426391599999,-33.8176307678],"type":"Point"}
}