{
  "type": "Feature",
  "properties": {
    "iso:country":"AU",
    "sg:address":"PO Box 172",
    "sg:city":"Oaklands Park",
    "sg:classifiers":[
        {
            "category":"Building & Trades",
            "subcategory":"Construction",
            "type":"Services"
        }
    ],
    "sg:phone":"+61 419 867 276",
    "sg:postcode":"5046",
    "sg:province":"SA",
    "sg:tags":[
        "earth",
        "excavating",
        "moving",
        "contractor"
    ],
    "wof:name":"Altor Excavations",
    "wof:placetype":"venue"
},
  "geometry": {"coordinates":[138.54598999999999,-35.01244],"type":"Point"}
}