{
  "type": "Feature",
  "properties": {
    "iso:country":"AU",
    "sg:address":"560 High St",
    "sg:city":"Echuca",
    "sg:classifiers":[
        {
            "category":"Personal",
            "subcategory":"Barber",
            "type":"Services"
        }
    ],
    "sg:phone":"+61 3 5480 1805",
    "sg:postcode":"3564",
    "sg:province":"VIC",
    "wof:name":"Sima D's Barber Salon",
    "wof:placetype":"venue"
},
  "geometry": {"coordinates":[144.75296020499999,-36.147895813],"type":"Point"}
}