{
  "type": "Feature",
  "properties": {
    "addr:full":"Forbes Rd Ballarat VIC 3350",
    "addr:postcode":"3350",
    "addr:street":"Forbes Rd",
    "iso:country":"AU",
    "sg:address":"Forbes Rd",
    "sg:city":"Ballarat",
    "sg:classifiers":[
        {
            "category":"Communications",
            "subcategory":"News Services",
            "type":"Services"
        }
    ],
    "sg:phone":"+61 3 5334 7388",
    "sg:postcode":"3350",
    "sg:province":"VIC",
    "sg:tags":[
        "information",
        "tourist",
        "attractions"
    ],
    "wof:name":"Kryal Castle Accommodation",
    "wof:placetype":"venue"
},
  "geometry": {"coordinates":[143.87150600000001,-37.563358],"type":"Point"}
}