{
  "type": "Feature",
  "properties": {
    "addr:full":"104 Anzac Pde Kensington NSW 2033",
    "addr:housenumber":"104",
    "addr:postcode":"2033",
    "addr:street":"Anzac Pde",
    "iso:country":"AU",
    "sg:address":"104 Anzac Pde",
    "sg:city":"Kensington",
    "sg:classifiers":[
        {
            "category":"Retail",
            "subcategory":"Auto Repair",
            "type":"Services"
        }
    ],
    "sg:phone":"+61 2 9663 3205",
    "sg:postcode":"2033",
    "sg:province":"NSW",
    "sg:tags":[
        "clutch",
        "brake"
    ],
    "wof:name":"Kensington Brake & Mechanical Repair Service",
    "wof:placetype":"venue"
},
  "geometry": {"coordinates":[151.22403,-33.906662],"type":"Point"}
}