{
  "type": "Feature",
  "properties": {
    "iso:country":"AU",
    "sg:address":"21/ 8 Campbell St",
    "sg:city":"Artarmon",
    "sg:classifiers":[
        {
            "category":"Utilities",
            "subcategory":"Electric",
            "type":"Services"
        }
    ],
    "sg:phone":"+61 2 9966 9144",
    "sg:postcode":"2064",
    "sg:province":"NSW",
    "sg:tags":[
        "electrical",
        "contractor"
    ],
    "wof:name":"Colbros Electrical Contracting",
    "wof:placetype":"venue"
},
  "geometry": {"coordinates":[151.18661499000001,-33.8174438477],"type":"Point"}
}