{
  "type": "Feature",
  "properties": {
    "addr:full":"562 Beaufort St Mt Lawley WA 6050",
    "addr:housenumber":"562",
    "addr:postcode":"6050",
    "addr:street":"Beaufort St",
    "iso:country":"AU",
    "sg:address":"562 Beaufort St",
    "sg:city":"Mt Lawley",
    "sg:classifiers":[
        {
            "category":"Food & Beverages",
            "subcategory":"Bakery",
            "type":"Retail Goods"
        }
    ],
    "sg:phone":"+61 8 9328 6866",
    "sg:postcode":"6050",
    "sg:province":"WA",
    "sg:tags":[
        "baker"
    ],
    "wof:name":"Lawleys Bakery Cafe",
    "wof:placetype":"venue"
},
  "geometry": {"coordinates":[115.87068176299999,-31.937078476],"type":"Point"}
}