{
  "type": "Feature",
  "properties": {
    "iso:country":"AU",
    "sg:address":"35 Mountain View Ave",
    "sg:city":"Glen Alpine",
    "sg:classifiers":[
        {
            "category":"Sports & Exercise",
            "subcategory":"Gym",
            "type":"Entertainment"
        }
    ],
    "sg:phone":"+61 402 749 848",
    "sg:postcode":"2560",
    "sg:province":"NSW",
    "sg:tags":[
        "personal",
        "trainer",
        "fitness"
    ],
    "wof:name":"Jonathan Peacock",
    "wof:placetype":"venue"
},
  "geometry": {"coordinates":[150.78695678700001,-34.0914955139],"type":"Point"}
}