{
  "type": "Feature",
  "properties": {
    "addr:full":"35 Bridge St North Lismore NSW 2480",
    "addr:housenumber":"35",
    "addr:postcode":"2480",
    "addr:street":"Bridge St North",
    "iso:country":"AU",
    "sg:address":"35 Bridge St",
    "sg:city":"North Lismore",
    "sg:classifiers":[
        {
            "category":"Retail",
            "subcategory":"Auto Repair",
            "type":"Services"
        }
    ],
    "sg:phone":"+61 2 6621 5920",
    "sg:postcode":"2480",
    "sg:province":"NSW",
    "sg:tags":[
        "electrical"
    ],
    "wof:name":"Peter McDonald Auto Electrician",
    "wof:placetype":"venue"
},
  "geometry": {"coordinates":[153.275665283,-28.8039169312],"type":"Point"}
}