{
  "type": "Feature",
  "properties": {
    "iso:country":"AU",
    "sg:address":"66A Church St",
    "sg:city":"Brighton",
    "sg:classifiers":[
        {
            "category":"Health Services",
            "subcategory":"Health Practitioner",
            "type":"Services"
        }
    ],
    "sg:phone":"+61 411 727 736",
    "sg:postcode":"3186",
    "sg:province":"VIC",
    "sg:tags":[
        "dietitian"
    ],
    "wof:name":"Revital Nirim Dietitian",
    "wof:placetype":"venue"
},
  "geometry": {"coordinates":[144.994873047,-37.914478302],"type":"Point"}
}