{
  "type": "Feature",
  "properties": {
    "addr:full":"Shop 41, Garden City Shopping Centre, Riseley St Booragoon WA 6154",
    "addr:housenumber":"shop 41",
    "addr:postcode":"6154",
    "addr:street":"Riseley St",
    "iso:country":"AU",
    "sg:address":"Shop 41, Garden City Shopping Centre, Riseley St",
    "sg:city":"Booragoon",
    "sg:classifiers":[
        {
            "category":"Shopping",
            "subcategory":"Jewelry",
            "type":"Retail Goods"
        }
    ],
    "sg:phone":"+61 8 9364 7979",
    "sg:postcode":"6154",
    "sg:province":"WA",
    "sg:tags":[
        "jeweller"
    ],
    "wof:name":"Mazzuchelli's",
    "wof:placetype":"venue"
},
  "geometry": {"coordinates":[115.832329,-32.036018],"type":"Point"}
}