{
  "type": "Feature",
  "properties": {
    "iso:country":"AU",
    "sg:address":"310 Russells Bridge Rd",
    "sg:city":"Russell's Bridge",
    "sg:classifiers":[
        {
            "category":"Farming",
            "subcategory":"Vineyard",
            "type":"Manufacturing & Wholesale Goods"
        }
    ],
    "sg:phone":"+61 417 116 700",
    "sg:postcode":"3331",
    "sg:province":"VIC",
    "sg:tags":[
        "winery"
    ],
    "wof:name":"Eagles Rise",
    "wof:placetype":"venue"
},
  "geometry": {"coordinates":[144.17893981899999,-37.9762496948],"type":"Point"}
}