{
  "type": "Feature",
  "properties": {
    "iso:country":"AU",
    "sg:address":"Shop 2D Sunnybank Hills Shopping Town",
    "sg:city":"Sunnybank Hills",
    "sg:classifiers":[
        {
            "category":"Health Services",
            "subcategory":"Health Practitioner",
            "type":"Services"
        }
    ],
    "sg:phone":"+61 7 3272 5044",
    "sg:postcode":"4109",
    "sg:province":"QLD",
    "sg:tags":[
        "physiotherapist"
    ],
    "wof:name":"Amanda Bacon Physiotherapy",
    "wof:placetype":"venue"
},
  "geometry": {"coordinates":[153.06634521500001,-27.5968093872],"type":"Point"}
}