{
  "type": "Feature",
  "properties": {
    "iso:country":"AU",
    "sg:address":"Foster Care Program 7 Blackwood Pl",
    "sg:city":"North Parramatta",
    "sg:classifiers":[
        {
            "category":"Organizations",
            "subcategory":"Community Association",
            "type":"Services"
        }
    ],
    "sg:phone":"+61 2 9683 2255",
    "sg:postcode":"2151",
    "sg:province":"NSW",
    "sg:tags":[
        "organisation",
        "family",
        "welfare"
    ],
    "wof:name":"Burnside",
    "wof:placetype":"venue"
},
  "geometry": {"coordinates":[151.01612854000001,-33.7955284119],"type":"Point"}
}