{
  "type": "Feature",
  "properties": {
    "addr:full":"64 Chapel St Windsor VIC 3181",
    "addr:housenumber":"64",
    "addr:postcode":"3181",
    "addr:street":"Chapel St",
    "iso:country":"AU",
    "sg:address":"64 Chapel St",
    "sg:city":"Windsor",
    "sg:classifiers":[
        {
            "category":"Shopping",
            "subcategory":"Clothing, Apparel, & Fashions",
            "type":"Retail Goods"
        }
    ],
    "sg:phone":"+61 3 9533 2006",
    "sg:postcode":"3181",
    "sg:province":"VIC",
    "sg:tags":[
        "recycled",
        "clothing"
    ],
    "wof:name":"Shappere",
    "wof:placetype":"venue"
},
  "geometry": {"coordinates":[144.99285888700001,-37.8554611206],"type":"Point"}
}