{
  "type": "Feature",
  "properties": {
    "addr:full":"Lot 55 Quairading Rd York WA 6302",
    "addr:postcode":"6302",
    "addr:street":"Quairading Rd",
    "iso:country":"AU",
    "sg:address":"Lot 55 Quairading Rd",
    "sg:city":"York",
    "sg:classifiers":[
        {
            "category":"Arena",
            "subcategory":"Bull Ring",
            "type":"Entertainment"
        }
    ],
    "sg:phone":"+61 8 9641 1251",
    "sg:postcode":"6302",
    "sg:province":"WA",
    "sg:tags":[
        "breeder",
        "pig"
    ],
    "wof:name":"Testerink J & E",
    "wof:placetype":"venue"
},
  "geometry": {"coordinates":[116.821632385,-31.8907852173],"type":"Point"}
}