{
  "type": "Feature",
  "properties": {
    "iso:country":"AU",
    "sg:address":"31 Nelson St",
    "sg:city":"Nhill",
    "sg:classifiers":[
        {
            "category":"Travel",
            "subcategory":"Hotels & Motels",
            "type":"Entertainment"
        }
    ],
    "sg:phone":"+61 3 5391 1622",
    "sg:postcode":"3418",
    "sg:province":"VIC",
    "wof:name":"Zero Inn Motel",
    "wof:placetype":"venue"
},
  "geometry": {"coordinates":[141.65858459500001,-36.33411026],"type":"Point"}
}