{
  "type": "Feature",
  "properties": {
    "addr:full":"18 Cofton St Geelong West VIC 3218",
    "addr:housenumber":"18",
    "addr:postcode":"3218",
    "addr:street":"Cofton St",
    "iso:country":"AU",
    "sg:address":"18 Cofton St",
    "sg:city":"Geelong West",
    "sg:classifiers":[
        {
            "category":"Building & Trades",
            "subcategory":"Cleaning & Sanitation",
            "type":"Services"
        }
    ],
    "sg:phone":"+61 413 452 768",
    "sg:postcode":"3218",
    "sg:province":"VIC",
    "sg:tags":[
        "cleaner",
        "repairer",
        "roof"
    ],
    "wof:name":"Bayside Roofing",
    "wof:placetype":"venue"
},
  "geometry": {"coordinates":[144.340133667,-38.143032074],"type":"Point"}
}