{
  "type": "Feature",
  "properties": {
    "addr:full":"78 Albert St Warragul VIC 3820",
    "addr:housenumber":"78",
    "addr:postcode":"3820",
    "addr:street":"Albert St",
    "iso:country":"AU",
    "sg:address":"78 Albert St",
    "sg:city":"Warragul",
    "sg:classifiers":[
        {
            "category":"Health Services",
            "subcategory":"Doctor",
            "type":"Services"
        }
    ],
    "sg:phone":"+61 3 5623 5250",
    "sg:postcode":"3820",
    "sg:province":"VIC",
    "sg:tags":[
        "medical",
        "practitioner"
    ],
    "wof:name":"Warragul Medical Centre",
    "wof:placetype":"venue"
},
  "geometry": {"coordinates":[145.93661499999999,-38.160748],"type":"Point"}
}