{
  "type": "Feature",
  "properties": {
    "addr:full":"Shp 174/ 8 Gladstone Park Drv Gladstone Park VIC 3043",
    "addr:housenumber":"174 / 8",
    "addr:postcode":"3043",
    "addr:street":"Gladstone Park Drv",
    "iso:country":"AU",
    "sg:address":"Shp 174/ 8 Gladstone Park Drv",
    "sg:city":"Gladstone Park",
    "sg:classifiers":[
        {
            "category":"Personal",
            "subcategory":"Beauty Salon",
            "type":"Services"
        }
    ],
    "sg:phone":"+61 3 9335 4448",
    "sg:postcode":"3043",
    "sg:province":"VIC",
    "wof:name":"Tan City & Beauty",
    "wof:placetype":"venue"
},
  "geometry": {"coordinates":[144.88453674300001,-37.6891937256],"type":"Point"}
}