{
  "type": "Feature",
  "properties": {
    "addr:full":"14a Johnson St Oakleigh VIC 3166",
    "addr:housenumber":"14a",
    "addr:postcode":"3166",
    "addr:street":"Johnson St",
    "iso:country":"AU",
    "sg:address":"14a Johnson St",
    "sg:city":"Oakleigh",
    "sg:classifiers":[
        {
            "category":"Shopping",
            "subcategory":"Bicycles & Sporting Goods",
            "type":"Retail Goods"
        }
    ],
    "sg:phone":"+61 3 9564 7416",
    "sg:postcode":"3166",
    "sg:province":"VIC",
    "sg:tags":[
        "dance",
        "accessory",
        "wear",
        "supply"
    ],
    "wof:name":"Lilya Shoes by Zeralda",
    "wof:placetype":"venue"
},
  "geometry": {"coordinates":[145.087615967,-37.900932312],"type":"Point"}
}