{
  "type": "Feature",
  "properties": {
    "addr:full":"Shp 5/ 39 Lake St Cairns QLD 4870",
    "addr:housenumber":"/ 39",
    "addr:postcode":"4870",
    "addr:street":"Lake St",
    "iso:country":"AU",
    "sg:address":"Shp 5/ 39 Lake St",
    "sg:city":"Cairns",
    "sg:classifiers":[
        {
            "category":"Shopping",
            "subcategory":"Clothing, Apparel, & Fashions",
            "type":"Retail Goods"
        }
    ],
    "sg:phone":"+61 7 4052 1109",
    "sg:postcode":"4870",
    "sg:province":"QLD",
    "sg:tags":[
        "lady",
        "wear"
    ],
    "wof:name":"Twenty Four",
    "wof:placetype":"venue"
},
  "geometry": {"coordinates":[145.77699279800001,-16.9236736298],"type":"Point"}
}