{
  "type": "Feature",
  "properties": {
    "addr:full":"282 Blackburn Rd Doncaster East VIC 3109",
    "addr:housenumber":"282",
    "addr:postcode":"3109",
    "addr:street":"Blackburn Rd",
    "iso:country":"AU",
    "sg:address":"282 Blackburn Rd",
    "sg:city":"Doncaster East",
    "sg:classifiers":[
        {
            "category":"Real Estate",
            "subcategory":"Real Estate Agent",
            "type":"Services"
        }
    ],
    "sg:phone":"+61 3 9841 9000",
    "sg:postcode":"3109",
    "sg:province":"VIC",
    "wof:name":"Allens Estate Agents - Doncaster East",
    "wof:placetype":"venue"
},
  "geometry": {"coordinates":[145.163528442,-37.7817001343],"type":"Point"}
}