{
  "type": "Feature",
  "properties": {
    "addr:full":"25 Clair Crs Padstow NSW 2211",
    "addr:housenumber":"25",
    "addr:postcode":"2211",
    "addr:street":"Clair Crs",
    "iso:country":"AU",
    "sg:address":"25 Clair Crs",
    "sg:city":"Padstow",
    "sg:classifiers":[
        {
            "category":"Real Estate",
            "subcategory":"Surveying",
            "type":"Services"
        }
    ],
    "sg:phone":"+61 2 9773 7837",
    "sg:postcode":"2211",
    "sg:province":"NSW",
    "sg:tags":[
        "surveyor",
        "land"
    ],
    "wof:name":"John K Wicks & Associates",
    "wof:placetype":"venue"
},
  "geometry": {"coordinates":[151.03239400000001,-33.952171],"type":"Point"}
}