{
  "type": "Feature",
  "properties": {
    "addr:full":"45 Walkers Rd Lara VIC 3212",
    "addr:housenumber":"45",
    "addr:postcode":"3212",
    "addr:street":"Walkers Rd",
    "iso:country":"AU",
    "sg:address":"45 Walkers Rd",
    "sg:city":"Lara",
    "sg:classifiers":[
        {
            "category":"Health Services",
            "subcategory":"Doctor",
            "type":"Services"
        }
    ],
    "sg:phone":"+61 3 5282 2999",
    "sg:postcode":"3212",
    "sg:province":"VIC",
    "sg:tags":[
        "medical",
        "practitioner"
    ],
    "wof:name":"Milner Ric Dr",
    "wof:placetype":"venue"
},
  "geometry": {"coordinates":[144.406417847,-38.020942688],"type":"Point"}
}