{
  "type": "Feature",
  "properties": {
    "iso:country":"AU",
    "sg:address":"Angaston Rd",
    "sg:city":"Angaston",
    "sg:classifiers":[
        {
            "category":"Shopping",
            "subcategory":"Crafts & Fabrics",
            "type":"Retail Goods"
        }
    ],
    "sg:phone":"+61 8 8562 3212",
    "sg:postcode":"5353",
    "sg:province":"SA",
    "sg:tags":[
        "quilting"
    ],
    "wof:name":"Barossa Quilt & Craft Cottage The",
    "wof:placetype":"venue"
},
  "geometry": {"coordinates":[139.026687622,-34.4937553406],"type":"Point"}
}