{
  "type": "Feature",
  "properties": {
    "addr:full":"Youngman St Kingaroy QLD 4610",
    "addr:postcode":"4610",
    "addr:street":"Youngman St",
    "iso:country":"AU",
    "sg:address":"Youngman St",
    "sg:city":"Kingaroy",
    "sg:classifiers":[
        {
            "category":"Food & Beverages",
            "subcategory":"Supermarket",
            "type":"Retail Goods"
        }
    ],
    "sg:phone":"+61 7 4162 3666",
    "sg:postcode":"4610",
    "sg:province":"QLD",
    "sg:tags":[
        "grocery",
        "store"
    ],
    "wof:name":"Woolworths Limited",
    "wof:placetype":"venue"
},
  "geometry": {"coordinates":[151.83583068900001,-26.542848587],"type":"Point"}
}