{
  "type": "Feature",
  "properties": {
    "addr:full":"186 Shamrock St Blackall QLD 4472",
    "addr:housenumber":"186",
    "addr:postcode":"4472",
    "addr:street":"Shamrock St Blackall",
    "iso:country":"AU",
    "sg:address":"186 Shamrock St",
    "sg:city":"Blackall",
    "sg:classifiers":[
        {
            "category":"Personal",
            "subcategory":"Beauty Salon",
            "type":"Services"
        }
    ],
    "sg:phone":"+61 7 4657 6007",
    "sg:postcode":"4472",
    "sg:province":"QLD",
    "sg:tags":[
        "hairdresser"
    ],
    "wof:name":"Molly's Hair Design",
    "wof:placetype":"venue"
},
  "geometry": {"coordinates":[145.45753479000001,-24.4222316742],"type":"Point"}
}