{
  "type": "Feature",
  "properties": {
    "iso:country":"AU",
    "sg:address":"50 Raynham St",
    "sg:city":"Salisbury",
    "sg:classifiers":[
        {
            "category":"Wholesale",
            "subcategory":"Furniture",
            "type":"Manufacturing & Wholesale Goods"
        }
    ],
    "sg:phone":"+61 7 3274 2899",
    "sg:postcode":"4107",
    "sg:province":"QLD",
    "sg:tags":[
        "wholesaler",
        "mfrs"
    ],
    "wof:name":"Logo Furniture Australia Pty Ltd",
    "wof:placetype":"venue"
},
  "geometry": {"coordinates":[153.02639770499999,-27.5415744781],"type":"Point"}
}