{
  "type": "Feature",
  "properties": {
    "addr:full":"532 Goodwood Rd Daw Park SA 5041",
    "addr:housenumber":"532",
    "addr:postcode":"5041",
    "addr:street":"Goodwood Rd",
    "iso:country":"AU",
    "sg:address":"532 Goodwood Rd",
    "sg:city":"Daw Park",
    "sg:classifiers":[
        {
            "category":"Shopping",
            "subcategory":"Clothing, Apparel, & Fashions",
            "type":"Retail Goods"
        }
    ],
    "sg:phone":"+61 8 8177 1177",
    "sg:postcode":"5041",
    "sg:province":"SA",
    "sg:tags":[
        "recycled",
        "clothing"
    ],
    "wof:name":"Wisteria Wardrobe",
    "wof:placetype":"venue"
},
  "geometry": {"coordinates":[138.591736,-34.979607],"type":"Point"}
}