{
  "type": "Feature",
  "properties": {
    "addr:full":"1st Flr,2/ 10 Sunshine Beach Rd Noosa Heads QLD 4567",
    "addr:housenumber":"/ 10",
    "addr:postcode":"4567",
    "addr:street":"Sunshine Beach Rd",
    "iso:country":"AU",
    "sg:address":"1st Flr,2/ 10 Sunshine Beach Rd",
    "sg:city":"Noosa Heads",
    "sg:classifiers":[
        {
            "category":"Government",
            "subcategory":"Post Office",
            "type":"Public Place"
        }
    ],
    "sg:phone":"+61 7 5449 2020",
    "sg:postcode":"4567",
    "sg:province":"QLD",
    "sg:tags":[
        "yoga"
    ],
    "wof:name":"Noosa Yoga Centre",
    "wof:placetype":"venue"
},
  "geometry": {"coordinates":[153.09146118199999,-26.3977680206],"type":"Point"}
}