{
  "type": "Feature",
  "properties": {
    "addr:full":"Casterton Rd Drumborg VIC 3304",
    "addr:postcode":"3304",
    "addr:street":"Casterton Rd",
    "iso:country":"AU",
    "sg:address":"Casterton Rd",
    "sg:city":"Drumborg",
    "sg:classifiers":[
        {
            "category":"Building & Trades",
            "subcategory":"Landscaping Services",
            "type":"Services"
        }
    ],
    "sg:phone":"+61 3 5527 9266",
    "sg:postcode":"3304",
    "sg:province":"VIC",
    "sg:tags":[
        "grazier"
    ],
    "wof:name":"Croft A M",
    "wof:placetype":"venue"
},
  "geometry": {"coordinates":[141.55661010700001,-38.0549201965],"type":"Point"}
}