{
  "type": "Feature",
  "properties": {
    "iso:country":"AU",
    "sg:address":"115 Durham St",
    "sg:city":"Sunshine",
    "sg:classifiers":[
        {
            "category":"Banks & Credit Unions",
            "subcategory":"Financial Services",
            "type":"Services"
        }
    ],
    "sg:phone":"+61 3 9311 2532",
    "sg:postcode":"3020",
    "sg:province":"VIC",
    "sg:tags":[
        "loan",
        "finance",
        "mortgage"
    ],
    "wof:name":"GRO Financial Services",
    "wof:placetype":"venue"
},
  "geometry": {"coordinates":[144.830475,-37.788456],"type":"Point"}
}