{
  "type": "Feature",
  "properties": {
    "addr:full":"182 Manns Rd Gosford West NSW 2250",
    "addr:housenumber":"182",
    "addr:postcode":"2250",
    "addr:street":"Manns Rd",
    "iso:country":"AU",
    "sg:address":"182 Manns Rd",
    "sg:city":"Gosford West",
    "sg:classifiers":[
        {
            "category":"Recreation",
            "subcategory":"Fishing",
            "type":"Entertainment"
        }
    ],
    "sg:phone":"+61 2 4324 6522",
    "sg:postcode":"2250",
    "sg:province":"NSW",
    "sg:tags":[
        "tackle"
    ],
    "wof:name":"West Gosford Bait & Tackle",
    "wof:placetype":"venue"
},
  "geometry": {"coordinates":[151.319488525,-33.4242134094],"type":"Point"}
}