{
  "type": "Feature",
  "properties": {
    "addr:full":"28 Sir John Monash Drv Caulfield East VIC 3145",
    "addr:housenumber":"28",
    "addr:postcode":"3145",
    "addr:street":"Sir John Monash Drv",
    "iso:country":"AU",
    "sg:address":"28 Sir John Monash Drv",
    "sg:city":"Caulfield East",
    "sg:classifiers":[
        {
            "category":"Shopping",
            "subcategory":"Mobile Phones",
            "type":"Retail Goods"
        }
    ],
    "sg:phone":"+61 3 9572 2600",
    "sg:postcode":"3145",
    "sg:province":"VIC",
    "sg:tags":[
        "telephone",
        "accessory"
    ],
    "wof:name":"Planet Cyber",
    "wof:placetype":"venue"
},
  "geometry": {"coordinates":[145.04397582999999,-37.8775901794],"type":"Point"}
}