{
  "type": "Feature",
  "properties": {
    "addr:full":"12 Thorburn Ave Beechboro WA 6063",
    "addr:housenumber":"12",
    "addr:postcode":"6063",
    "addr:street":"Thorburn Ave",
    "iso:country":"AU",
    "sg:address":"12 Thorburn Ave",
    "sg:city":"Beechboro",
    "sg:classifiers":[
        {
            "category":"Home & Garden",
            "subcategory":"Carpets & Floor Coverings",
            "type":"Retail Goods"
        }
    ],
    "sg:phone":"+61 413 734 851",
    "sg:postcode":"6063",
    "sg:province":"WA",
    "sg:tags":[
        "tile",
        "wall",
        "layer"
    ],
    "wof:name":"Armindo's Tiling Service",
    "wof:placetype":"venue"
},
  "geometry": {"coordinates":[115.946769714,-31.8652305603],"type":"Point"}
}