{
  "type": "Feature",
  "properties": {
    "addr:full":"31 Old Perth Rd Bassendean WA 6054",
    "addr:housenumber":"31",
    "addr:postcode":"6054",
    "addr:street":"Old Perth Rd",
    "iso:country":"AU",
    "sg:address":"31 Old Perth Rd",
    "sg:city":"Bassendean",
    "sg:classifiers":[
        {
            "category":"Professional",
            "subcategory":"Detective & Security Services",
            "type":"Services"
        }
    ],
    "sg:phone":"+61 8 9379 3287",
    "sg:postcode":"6054",
    "sg:province":"WA",
    "sg:tags":[
        "alarm",
        "protection",
        "system",
        "machinery"
    ],
    "wof:name":"Myacom",
    "wof:placetype":"venue"
},
  "geometry": {"coordinates":[115.949150085,-31.9044494629],"type":"Point"}
}