{
  "type": "Feature",
  "properties": {
    "addr:full":"5/ 61 Lampton Ave Derwent Park TAS 7009",
    "addr:housenumber":"/ 61",
    "addr:postcode":"7009",
    "addr:street":"Lampton Ave",
    "iso:country":"AU",
    "sg:address":"5/ 61 Lampton Ave",
    "sg:city":"Derwent Park",
    "sg:classifiers":[
        {
            "category":"Retail",
            "subcategory":"Auto Repair",
            "type":"Services"
        }
    ],
    "sg:phone":"+61 407 803 014",
    "sg:postcode":"7009",
    "sg:province":"TAS",
    "sg:tags":[
        "repairer",
        "motor",
        "engineer"
    ],
    "wof:name":"Torque It",
    "wof:placetype":"venue"
},
  "geometry": {"coordinates":[147.295211792,-42.8343086243],"type":"Point"}
}