{
  "type": "Feature",
  "properties": {
    "addr:full":"12 June Rd Gooseberry Hill WA 6076",
    "addr:housenumber":"12",
    "addr:postcode":"6076",
    "addr:street":"June Rd",
    "iso:country":"AU",
    "sg:address":"12 June Rd",
    "sg:city":"Gooseberry Hill",
    "sg:classifiers":[
        {
            "category":"Retail",
            "subcategory":"Repair Shop",
            "type":"Services"
        }
    ],
    "sg:phone":"+61 8 9352 8255",
    "sg:postcode":"6076",
    "sg:province":"WA",
    "sg:tags":[
        "repairing",
        "piano",
        "tuning"
    ],
    "wof:name":"G.W. Ridge Pianos",
    "wof:placetype":"venue"
},
  "geometry": {"coordinates":[116.04132842999999,-31.9505653381],"type":"Point"}
}