{
  "type": "Feature",
  "properties": {
    "iso:country":"AU",
    "sg:address":"PO Box 44",
    "sg:city":"Woy Woy",
    "sg:classifiers":[
        {
            "category":"Arts & Performance",
            "subcategory":"Theater",
            "type":"Entertainment"
        }
    ],
    "sg:phone":"+61 2 4341 2931",
    "sg:postcode":"2256",
    "sg:province":"NSW",
    "sg:tags":[
        "theatre"
    ],
    "wof:name":"Woy Woy Little Theatre",
    "wof:placetype":"venue"
},
  "geometry": {"coordinates":[151.327468872,-33.4929008484],"type":"Point"}
}