{
  "type": "Feature",
  "properties": {
    "iso:country":"AU",
    "sg:address":"Lincoln Ave",
    "sg:city":"Salisbury East",
    "sg:classifiers":[
        {
            "category":"Education",
            "subcategory":"School",
            "type":"Public Place"
        }
    ],
    "sg:phone":"+61 8 8258 5405",
    "sg:postcode":"5109",
    "sg:province":"SA",
    "sg:tags":[
        "state",
        "except",
        "nsw"
    ],
    "wof:name":"Madison Junior Primary School",
    "wof:placetype":"venue"
},
  "geometry": {"coordinates":[138.66308593799999,-34.7851638794],"type":"Point"}
}