{
  "type": "Feature",
  "properties": {
    "addr:full":"Factory 5, 43- 45 Vinter Ave Croydon VIC 3136",
    "addr:housenumber":"43 45",
    "addr:postcode":"3136",
    "addr:street":"Vinter Ave",
    "iso:country":"AU",
    "sg:address":"Factory 5, 43- 45 Vinter Ave",
    "sg:city":"Croydon",
    "sg:classifiers":[
        {
            "category":"Mining & Drilling",
            "type":"Manufacturing & Wholesale Goods"
        }
    ],
    "sg:phone":"+61 3 9723 2455",
    "sg:postcode":"3136",
    "sg:province":"VIC",
    "sg:tags":[
        "concrete",
        "breaking",
        "grinding",
        "sawing"
    ],
    "sg:website":"http://www.conceptcuttinganddrilling.com.au",
    "wof:name":"Concept Cutting & Drilling",
    "wof:placetype":"venue"
},
  "geometry": {"coordinates":[145.278564453,-37.8058891296],"type":"Point"}
}