{
  "type": "Feature",
  "properties": {
    "iso:country":"AU",
    "sg:address":"69- 93 Grace St",
    "sg:city":"Wulkuraka",
    "sg:classifiers":[
        {
            "category":"Real Estate",
            "subcategory":"Real Estate Agent",
            "type":"Services"
        }
    ],
    "sg:phone":"+61 7 3202 4081",
    "sg:postcode":"4305",
    "sg:province":"QLD",
    "wof:name":"Rosehill Gardens",
    "wof:placetype":"venue"
},
  "geometry": {"coordinates":[152.71995544399999,-27.6046791077],"type":"Point"}
}