{
  "type": "Feature",
  "properties": {
    "iso:country":"AU",
    "sg:address":"2067 Marshall St",
    "sg:city":"Collie",
    "sg:classifiers":[
        {
            "category":"Wholesale",
            "subcategory":"Machinery & Supplies",
            "type":"Manufacturing & Wholesale Goods"
        }
    ],
    "sg:phone":"+61 8 9734 5332",
    "sg:postcode":"6225",
    "sg:province":"WA",
    "sg:tags":[
        "agricultural"
    ],
    "wof:name":"Agmaster",
    "wof:placetype":"venue"
},
  "geometry": {"coordinates":[116.145103,-33.34444],"type":"Point"}
}