{
  "type": "Feature",
  "properties": {
    "addr:full":"5 Parro St Greystanes NSW 2145",
    "addr:housenumber":"5",
    "addr:postcode":"2145",
    "addr:street":"Parro St",
    "iso:country":"AU",
    "sg:address":"5 Parro St",
    "sg:city":"Greystanes",
    "sg:classifiers":[
        {
            "category":"Building & Trades",
            "subcategory":"Construction",
            "type":"Services"
        }
    ],
    "sg:phone":"+61 2 9631 3539",
    "sg:postcode":"2145",
    "sg:province":"NSW",
    "sg:tags":[
        "concrete",
        "contractor"
    ],
    "wof:name":"Cumberland Decorative Coatings",
    "wof:placetype":"venue"
},
  "geometry": {"coordinates":[150.94612121599999,-33.8187904358],"type":"Point"}
}