{
  "type": "Feature",
  "properties": {
    "addr:full":"90 Vista St Mosman NSW 2088",
    "addr:housenumber":"90",
    "addr:postcode":"2088",
    "addr:street":"Vista St",
    "iso:country":"AU",
    "sg:address":"90 Vista St",
    "sg:city":"Mosman",
    "sg:classifiers":[
        {
            "category":"Cafe",
            "type":"Food & Drink"
        }
    ],
    "sg:phone":"+61 2 9969 5845",
    "sg:postcode":"2088",
    "sg:province":"NSW",
    "wof:name":"Bertoni Pty Ltd",
    "wof:placetype":"venue"
},
  "geometry": {"coordinates":[151.240356445,-33.8246116638],"type":"Point"}
}