{
  "type": "Feature",
  "properties": {
    "addr:full":"95 Willsmere Rd Kew VIC 3101",
    "addr:housenumber":"95",
    "addr:postcode":"3101",
    "addr:street":"Willsmere Rd",
    "iso:country":"AU",
    "sg:address":"95 Willsmere Rd",
    "sg:city":"Kew",
    "sg:classifiers":[
        {
            "category":"Health Services",
            "subcategory":"Health Practitioner",
            "type":"Services"
        }
    ],
    "sg:phone":"+61 3 9855 0606",
    "sg:postcode":"3101",
    "sg:province":"VIC",
    "sg:tags":[
        "osteopath"
    ],
    "wof:name":"Nigel Roff (OSTEO)",
    "wof:placetype":"venue"
},
  "geometry": {"coordinates":[145.035644531,-37.7958984375],"type":"Point"}
}