{
  "type": "Feature",
  "properties": {
    "addr:full":"Unit 3/ 7 Dougal St Byford WA 6122",
    "addr:postcode":"6122",
    "addr:street":"Dougal St",
    "iso:country":"AU",
    "sg:address":"Unit 3/ 7 Dougal St",
    "sg:city":"Byford",
    "sg:classifiers":[
        {
            "category":"Retail",
            "subcategory":"Auto Repair",
            "type":"Services"
        }
    ],
    "sg:phone":"+61 8 9525 1364",
    "sg:postcode":"6122",
    "sg:province":"WA",
    "sg:tags":[
        "repairer",
        "motor",
        "engineer"
    ],
    "wof:name":"Byford Exhaust & Automotive Centre",
    "wof:placetype":"venue"
},
  "geometry": {"coordinates":[116.010368347,-32.2275657654],"type":"Point"}
}