{
  "type": "Feature",
  "properties": {
    "addr:full":"22 Geddes St Balcatta WA 6021",
    "addr:housenumber":"22",
    "addr:postcode":"6021",
    "addr:street":"Geddes St",
    "iso:country":"AU",
    "sg:address":"22 Geddes St",
    "sg:city":"Balcatta",
    "sg:classifiers":[
        {
            "category":"Farming",
            "subcategory":"Dairy Farm",
            "type":"Manufacturing & Wholesale Goods"
        }
    ],
    "sg:phone":"+61 8 9441 7777",
    "sg:postcode":"6021",
    "sg:province":"WA",
    "sg:tags":[
        "wholesaler",
        "product",
        "mfrs"
    ],
    "wof:name":"Brownes Dairy",
    "wof:placetype":"venue"
},
  "geometry": {"coordinates":[115.822120666,-31.8606262207],"type":"Point"}
}