{
  "type": "Feature",
  "properties": {
    "iso:country":"AU",
    "sg:address":"497 Brighton Rd",
    "sg:city":"Brighton",
    "sg:classifiers":[
        {
            "category":"Professional",
            "subcategory":"Computer Services",
            "type":"Services"
        }
    ],
    "sg:phone":"+61 8 8298 1211",
    "sg:postcode":"5048",
    "sg:province":"SA",
    "sg:tags":[
        "package",
        "software"
    ],
    "wof:name":"Cherry Computers Brighton",
    "wof:placetype":"venue"
},
  "geometry": {"coordinates":[138.52301,-35.019402],"type":"Point"}
}