{
  "type": "Feature",
  "properties": {
    "iso:country":"AU",
    "sg:address":"38a Restwell St",
    "sg:city":"Bankstown",
    "sg:classifiers":[
        {
            "category":"Professional",
            "subcategory":"Printing & Photocopies",
            "type":"Services"
        }
    ],
    "sg:phone":"+61 2 9790 2112",
    "sg:postcode":"2200",
    "sg:province":"NSW",
    "sg:tags":[
        "photocopying"
    ],
    "wof:name":"Budget Instant Printing",
    "wof:placetype":"venue"
},
  "geometry": {"coordinates":[151.035004,-33.919872],"type":"Point"}
}