{
  "type": "Feature",
  "properties": {
    "iso:country":"AU",
    "sg:address":"69 Sandville Pl",
    "sg:city":"Sandford",
    "sg:classifiers":[
        {
            "category":"Health Services",
            "subcategory":"Chiropractor",
            "type":"Services"
        }
    ],
    "sg:phone":"+61 3 6239 9215",
    "sg:postcode":"7020",
    "sg:province":"TAS",
    "wof:name":"Ross Gaynor J Dr",
    "wof:placetype":"venue"
},
  "geometry": {"coordinates":[147.48614501899999,-42.9998970032],"type":"Point"}
}