{
  "type": "Feature",
  "properties": {
    "addr:full":"PO Box 527 Port Douglas QLD 4877",
    "addr:postcode":"4877",
    "iso:country":"AU",
    "sg:address":"PO Box 527",
    "sg:city":"Port Douglas",
    "sg:classifiers":[
        {
            "category":"Food & Beverages",
            "subcategory":"Fruits & Vegetables",
            "type":"Retail Goods"
        }
    ],
    "sg:phone":"+61 7 4099 4233",
    "sg:postcode":"4877",
    "sg:province":"QLD",
    "sg:tags":[
        "consultant",
        "catering"
    ],
    "wof:name":"Port Douglas Catering & Events",
    "wof:placetype":"venue"
},
  "geometry": {"coordinates":[145.46543884299999,-16.4844493866],"type":"Point"}
}