{
  "type": "Feature",
  "properties": {
    "addr:full":"Level 1, 315 Ross River Rd Aitkenvale QLD 4814",
    "addr:housenumber":"315",
    "addr:postcode":"4814",
    "addr:street":"Ross River Rd",
    "iso:country":"AU",
    "sg:address":"Level 1, 315 Ross River Rd",
    "sg:city":"Aitkenvale",
    "sg:classifiers":[
        {
            "category":"Banks & Credit Unions",
            "subcategory":"Investment Brokerage",
            "type":"Services"
        }
    ],
    "sg:phone":"+61 7 4725 5787",
    "sg:postcode":"4814",
    "sg:province":"QLD",
    "sg:tags":[
        "share",
        "broker",
        "stock"
    ],
    "wof:name":"Wilson HTM",
    "wof:placetype":"venue"
},
  "geometry": {"coordinates":[146.76387,-19.297621],"type":"Point"}
}