{
  "type": "Feature",
  "properties": {
    "addr:full":"27 Rene St Noosaville QLD 4566",
    "addr:housenumber":"27",
    "addr:postcode":"4566",
    "addr:street":"Rene St",
    "iso:country":"AU",
    "sg:address":"27 Rene St",
    "sg:city":"Noosaville",
    "sg:classifiers":[
        {
            "category":"Building & Trades",
            "subcategory":"Construction",
            "type":"Services"
        }
    ],
    "sg:phone":"+61 7 5448 7424",
    "sg:postcode":"4566",
    "sg:province":"QLD",
    "sg:tags":[
        "contractor"
    ],
    "wof:name":"Castle Bay Projects",
    "wof:placetype":"venue"
},
  "geometry": {"coordinates":[153.042312622,-26.4148788452],"type":"Point"}
}