{
  "type": "Feature",
  "properties": {
    "addr:full":"56 Lindsay St Toowoomba QLD 4350",
    "addr:housenumber":"56",
    "addr:postcode":"4350",
    "addr:street":"Lindsay St",
    "iso:country":"AU",
    "sg:address":"56 Lindsay St",
    "sg:city":"Toowoomba",
    "sg:classifiers":[
        {
            "category":"Health Services",
            "subcategory":"Dentist",
            "type":"Services"
        }
    ],
    "sg:phone":"+61 7 4632 0300",
    "sg:postcode":"4350",
    "sg:province":"QLD",
    "wof:name":"Goolburri Mobile Dental Service",
    "wof:placetype":"venue"
},
  "geometry": {"coordinates":[151.96435500000001,-27.560202],"type":"Point"}
}