{
  "type": "Feature",
  "properties": {
    "iso:country":"AU",
    "sg:address":"27 Connors Rd",
    "sg:city":"Mackay",
    "sg:classifiers":[
        {
            "category":"Autos & Motor Vehicles",
            "subcategory":"Auto Supplies",
            "type":"Retail Goods"
        }
    ],
    "sg:phone":"+61 7 4952 4326",
    "sg:postcode":"4740",
    "sg:province":"QLD",
    "sg:tags":[
        "tyre"
    ],
    "wof:name":"Transit T/S",
    "wof:placetype":"venue"
},
  "geometry": {"coordinates":[149.161133,-21.170797],"type":"Point"}
}