{
  "type": "Feature",
  "properties": {
    "addr:full":"Shop 6, Pine Mountain St Mt Gravatt East QLD 4122",
    "addr:housenumber":"shop 6",
    "addr:postcode":"4122",
    "addr:street":"Pine Mountain St",
    "iso:country":"AU",
    "sg:address":"Shop 6, Pine Mountain St",
    "sg:city":"Mt Gravatt East",
    "sg:classifiers":[
        {
            "category":"Personal",
            "subcategory":"Beauty Salon",
            "type":"Services"
        }
    ],
    "sg:phone":"+61 7 3849 5365",
    "sg:postcode":"4122",
    "sg:province":"QLD",
    "wof:name":"Nouvelle Skin & Beauty Clinic.",
    "wof:placetype":"venue"
},
  "geometry": {"coordinates":[153.089385986,-27.5163974762],"type":"Point"}
}