{
  "type": "Feature",
  "properties": {
    "addr:full":"Cnr Margaret & Dent Sts Toowoomba QLD 4350",
    "addr:postcode":"4350",
    "addr:street":"Cnr",
    "iso:country":"AU",
    "sg:address":"Cnr Margaret & Dent Sts",
    "sg:city":"Toowoomba",
    "sg:classifiers":[
        {
            "category":"Shopping",
            "subcategory":"Department Store",
            "type":"Retail Goods"
        }
    ],
    "sg:phone":"+61 7 4690 3111",
    "sg:postcode":"4350",
    "sg:province":"QLD",
    "wof:name":"Myer Toowoomba",
    "wof:placetype":"venue"
},
  "geometry": {"coordinates":[151.94923399999999,-27.563356],"type":"Point"}
}