{
  "type": "Feature",
  "properties": {
    "addr:full":"Unit 3/ 6 Anderson Pl Windsor South NSW 2756",
    "addr:housenumber":"6",
    "addr:postcode":"2756",
    "addr:street":"Anderson Pl",
    "iso:country":"AU",
    "sg:address":"Unit 3/ 6 Anderson Pl",
    "sg:city":"Windsor South",
    "sg:classifiers":[
        {
            "category":"Retail",
            "subcategory":"Auto Repair",
            "type":"Services"
        }
    ],
    "sg:phone":"+61 2 4577 2287",
    "sg:postcode":"2756",
    "sg:province":"NSW",
    "sg:tags":[
        "automotive",
        "air conditioning"
    ],
    "wof:name":"A.C.T. Auto Electrical Engineering Pty. Ltd.",
    "wof:placetype":"venue"
},
  "geometry": {"coordinates":[150.807540894,-33.6218528748],"type":"Point"}
}