{
  "type": "Feature",
  "properties": {
    "addr:full":"Flr 5/ 188 Collins St Hobart TAS 7000",
    "addr:housenumber":"/ 188",
    "addr:postcode":"7000",
    "addr:street":"Collins St",
    "iso:country":"AU",
    "sg:address":"Flr 5/ 188 Collins St",
    "sg:city":"Hobart",
    "sg:classifiers":[
        {
            "category":"Communications",
            "type":"Services"
        }
    ],
    "sg:phone":"+61 3 6224 5355",
    "sg:postcode":"7000",
    "sg:province":"TAS",
    "sg:tags":[
        "translation"
    ],
    "wof:name":"All World Languages",
    "wof:placetype":"venue"
},
  "geometry": {"coordinates":[147.32574462900001,-42.8860015869],"type":"Point"}
}