{
  "type": "Feature",
  "properties": {
    "addr:full":"PO Box 287 Paddington NSW 2021",
    "addr:postcode":"2021",
    "iso:country":"AU",
    "sg:address":"PO Box 287",
    "sg:city":"Paddington",
    "sg:classifiers":[
        {
            "category":"Personal",
            "subcategory":"Adult",
            "type":"Services"
        }
    ],
    "sg:phone":"+61 410 935 550",
    "sg:postcode":"2021",
    "sg:province":"NSW",
    "sg:tags":[
        "vic",
        "except",
        "state",
        "escort",
        "social",
        "qld"
    ],
    "wof:name":"Sydney Elite Escorts",
    "wof:placetype":"venue"
},
  "geometry": {"coordinates":[151.22581481899999,-33.8864593506],"type":"Point"}
}