{
  "type": "Feature",
  "properties": {
    "addr:full":"85 Robertson Drv Mornington VIC 3931",
    "addr:housenumber":"85",
    "addr:postcode":"3931",
    "addr:street":"Robertson Drv",
    "iso:country":"AU",
    "sg:address":"85 Robertson Drv",
    "sg:city":"Mornington",
    "sg:classifiers":[
        {
            "category":"Utilities",
            "subcategory":"Electric",
            "type":"Services"
        }
    ],
    "sg:phone":"+61 419 532 793",
    "sg:postcode":"3931",
    "sg:province":"VIC",
    "sg:tags":[
        "electrical",
        "contractor"
    ],
    "wof:name":"Mitchell Paul",
    "wof:placetype":"venue"
},
  "geometry": {"coordinates":[145.06224060100001,-38.2244758606],"type":"Point"}
}