{
  "type": "Feature",
  "properties": {
    "addr:full":"Slalom St Falls Creek VIC 3699",
    "addr:postcode":"3699",
    "addr:street":"Slalom St Falls Creek",
    "iso:country":"AU",
    "sg:address":"Slalom St",
    "sg:city":"Falls Creek",
    "sg:classifiers":[
        {
            "category":"Sports & Exercise",
            "subcategory":"Ski Resort",
            "type":"Entertainment"
        }
    ],
    "sg:phone":"+61 3 5758 3251",
    "sg:postcode":"3699",
    "sg:province":"VIC",
    "sg:tags":[
        "tour",
        "centres"
    ],
    "wof:name":"Ripparoo Ski Lodge",
    "wof:placetype":"venue"
},
  "geometry": {"coordinates":[147.27740478499999,-36.8635101318],"type":"Point"}
}