{
  "type": "Feature",
  "properties": {
    "addr:full":"5 Lochaven Drv Nowra North NSW 2541",
    "addr:housenumber":"5",
    "addr:postcode":"2541",
    "addr:street":"Lochaven Drv",
    "iso:country":"AU",
    "sg:address":"5 Lochaven Drv",
    "sg:city":"Nowra North",
    "sg:classifiers":[
        {
            "category":"Building & Trades",
            "subcategory":"Construction",
            "type":"Services"
        }
    ],
    "sg:phone":"+61 2 4421 5309",
    "sg:postcode":"2541",
    "sg:province":"NSW",
    "sg:tags":[
        "contractor"
    ],
    "wof:name":"Martin Paul Leedham Builder",
    "wof:placetype":"venue"
},
  "geometry": {"coordinates":[150.56390380900001,-34.8451766968],"type":"Point"}
}