{
  "type": "Feature",
  "properties": {
    "addr:full":"77 Victoria St Dubbo NSW 2830",
    "addr:housenumber":"77",
    "addr:postcode":"2830",
    "addr:street":"Victoria St",
    "iso:country":"AU",
    "sg:address":"77 Victoria St",
    "sg:city":"Dubbo",
    "sg:classifiers":[
        {
            "category":"Shopping",
            "subcategory":"Antiques",
            "type":"Retail Goods"
        }
    ],
    "sg:phone":"+61 2 6882 0879",
    "sg:postcode":"2830",
    "sg:province":"NSW",
    "sg:tags":[
        "collectable",
        "memorabilia"
    ],
    "wof:name":"Austin Bourke's Bastille Gun Shop",
    "wof:placetype":"venue"
},
  "geometry": {"coordinates":[148.59625244099999,-32.2509803772],"type":"Point"}
}