{
  "type": "Feature",
  "properties": {
    "addr:full":"1/ 17 Harvest Crt Southport QLD 4215",
    "addr:housenumber":"/ 17",
    "addr:postcode":"4215",
    "addr:street":"Harvest Crt",
    "iso:country":"AU",
    "sg:address":"1/ 17 Harvest Crt",
    "sg:city":"Southport",
    "sg:classifiers":[
        {
            "category":"Shopping",
            "subcategory":"Antiques",
            "type":"Retail Goods"
        }
    ],
    "sg:phone":"+61 7 5528 5441",
    "sg:postcode":"4215",
    "sg:province":"QLD",
    "sg:tags":[
        "collectable",
        "memorabilia"
    ],
    "wof:name":"blkmrkt",
    "wof:placetype":"venue"
},
  "geometry": {"coordinates":[153.40907287600001,-27.9783649445],"type":"Point"}
}