{
  "type": "Feature",
  "properties": {
    "addr:full":"4 Coglin Rd Elizabeth South SA 5112",
    "addr:housenumber":"4",
    "addr:postcode":"5112",
    "addr:street":"Coglin Rd",
    "iso:country":"AU",
    "sg:address":"4 Coglin Rd",
    "sg:city":"Elizabeth South",
    "sg:classifiers":[
        {
            "category":"Farming",
            "subcategory":"Nursery",
            "type":"Manufacturing & Wholesale Goods"
        }
    ],
    "sg:phone":"+61 8 8287 1055",
    "sg:postcode":"5112",
    "sg:province":"SA",
    "wof:name":"Fairview Plant Wholesalers",
    "wof:placetype":"venue"
},
  "geometry": {"coordinates":[138.65884399399999,-34.7491035461],"type":"Point"}
}