{
  "type": "Feature",
  "properties": {
    "addr:full":"PO Box 85 Mt Eliza VIC 3930",
    "addr:postcode":"3930",
    "iso:country":"AU",
    "sg:address":"PO Box 85",
    "sg:city":"Mt Eliza",
    "sg:classifiers":[
        {
            "category":"Food & Beverages",
            "subcategory":"Liquor & Beverages",
            "type":"Retail Goods"
        }
    ],
    "sg:phone":"+61 3 8707 0792",
    "sg:postcode":"3930",
    "sg:province":"VIC",
    "sg:tags":[
        "merchant",
        "spirit",
        "wine"
    ],
    "wof:name":"Restaurant House Wine",
    "wof:placetype":"venue"
},
  "geometry": {"coordinates":[145.09501648,-38.1936798096],"type":"Point"}
}