{
  "type": "Feature",
  "properties": {
    "iso:country":"AU",
    "sg:address":"208 Dundebar Rd",
    "sg:city":"Wanneroo",
    "sg:classifiers":[
        {
            "category":"Building & Trades",
            "subcategory":"Landscaping Services",
            "type":"Services"
        }
    ],
    "sg:phone":"+61 8 9405 1777",
    "sg:postcode":"6065",
    "sg:province":"WA",
    "sg:tags":[
        "gardener"
    ],
    "wof:name":"Balcatta Garden Centre",
    "wof:placetype":"venue"
},
  "geometry": {"coordinates":[115.82370758099999,-31.7449436188],"type":"Point"}
}