{
  "type": "Feature",
  "properties": {
    "addr:full":"19 Berry St Granville NSW 2142",
    "addr:housenumber":"19",
    "addr:postcode":"2142",
    "addr:street":"Berry St",
    "iso:country":"AU",
    "sg:address":"19 Berry St",
    "sg:city":"Granville",
    "sg:classifiers":[
        {
            "category":"Manufacturing",
            "subcategory":"Motor Vehicles & Parts",
            "type":"Manufacturing & Wholesale Goods"
        }
    ],
    "sg:phone":"+61 2 9354 5000",
    "sg:postcode":"2142",
    "sg:province":"NSW",
    "sg:tags":[
        "replacement"
    ],
    "wof:name":"Mitsubishi Motors Aust Ltd",
    "wof:placetype":"venue"
},
  "geometry": {"coordinates":[151.017379761,-33.8353500366],"type":"Point"}
}