{
  "type": "Feature",
  "properties": {
    "addr:full":"34 Fort St Petersham NSW 2049",
    "addr:housenumber":"34",
    "addr:postcode":"2049",
    "addr:street":"Fort St",
    "iso:country":"AU",
    "sg:address":"34 Fort St",
    "sg:city":"Petersham",
    "sg:classifiers":[
        {
            "category":"Building & Trades",
            "subcategory":"Construction",
            "type":"Services"
        }
    ],
    "sg:phone":"+61 414 427 022",
    "sg:postcode":"2049",
    "sg:province":"NSW",
    "sg:tags":[
        "renovation",
        "alterations",
        "extension",
        "contractor"
    ],
    "wof:name":"HL Renovations",
    "wof:placetype":"venue"
},
  "geometry": {"coordinates":[151.156036,-33.889668],"type":"Point"}
}