{
  "type": "Feature",
  "properties": {
    "addr:full":"Unit 6 142 James Ruse Drv Rosehill NSW 2142",
    "addr:housenumber":"142",
    "addr:postcode":"2142",
    "addr:street":"James Ruse Drv",
    "iso:country":"AU",
    "sg:address":"Unit 6 142 James Ruse Drv",
    "sg:city":"Rosehill",
    "sg:classifiers":[
        {
            "category":"Wholesale",
            "subcategory":"Hardware",
            "type":"Manufacturing & Wholesale Goods"
        }
    ],
    "sg:phone":"+61 2 9635 3566",
    "sg:postcode":"2142",
    "sg:province":"NSW",
    "wof:name":"Access Hardware Pty Ltd",
    "wof:placetype":"venue"
},
  "geometry": {"coordinates":[151.021774292,-33.8182373047],"type":"Point"}
}