{
  "type": "Feature",
  "properties": {
    "addr:full":"Belmont Rd Rockhampton QLD 4702",
    "addr:postcode":"4702",
    "addr:street":"Belmont Rd",
    "iso:country":"AU",
    "sg:address":"Belmont Rd",
    "sg:city":"Rockhampton",
    "sg:classifiers":[
        {
            "category":"Building & Trades",
            "subcategory":"Construction",
            "type":"Services"
        }
    ],
    "sg:phone":"+61 7 4936 1269",
    "sg:postcode":"4702",
    "sg:province":"QLD",
    "sg:tags":[
        "contractor"
    ],
    "wof:name":"GD & LT Nedwich",
    "wof:placetype":"venue"
},
  "geometry": {"coordinates":[150.42953491200001,-23.2525749207],"type":"Point"}
}