{
  "type": "Feature",
  "properties": {
    "iso:country":"AU",
    "sg:address":"8 George St",
    "sg:city":"Southport",
    "sg:classifiers":[
        {
            "category":"Professional",
            "type":"Services"
        }
    ],
    "sg:phone":"+61 7 5532 3088",
    "sg:postcode":"4215",
    "sg:province":"QLD",
    "sg:tags":[
        "transport"
    ],
    "wof:name":"Statewide Towing Service",
    "wof:placetype":"venue"
},
  "geometry": {"coordinates":[153.40530395499999,-27.967130661],"type":"Point"}
}