{
  "type": "Feature",
  "properties": {
    "addr:full":"Suite 7 418 Princes Hwy Narre Warren VIC 3805",
    "addr:housenumber":"418",
    "addr:postcode":"3805",
    "addr:street":"Princes Hwy",
    "iso:country":"AU",
    "sg:address":"Suite 7 418 Princes Hwy",
    "sg:city":"Narre Warren",
    "sg:classifiers":[
        {
            "category":"Building & Trades",
            "subcategory":"Landscaping Services",
            "type":"Services"
        }
    ],
    "sg:phone":"+61 3 9655 6461",
    "sg:postcode":"3805",
    "sg:province":"VIC",
    "sg:tags":[
        "consultant"
    ],
    "wof:name":"BSA- Sinclair Knight Merz",
    "wof:placetype":"venue"
},
  "geometry": {"coordinates":[145.30647300000001,-38.025684],"type":"Point"}
}