{
  "type": "Feature",
  "properties": {
    "iso:country":"AU",
    "sg:address":"South Gippsland Hwy",
    "sg:city":"Lang Lang",
    "sg:classifiers":[
        {
            "category":"Farming",
            "subcategory":"Farm",
            "type":"Manufacturing & Wholesale Goods"
        }
    ],
    "sg:phone":"+61 3 5997 5410",
    "sg:postcode":"3984",
    "sg:province":"VIC",
    "sg:tags":[
        "farmer"
    ],
    "wof:name":"Sayers N M & D E",
    "wof:placetype":"venue"
},
  "geometry": {"coordinates":[145.54946899399999,-38.2646598816],"type":"Point"}
}