{
  "type": "Feature",
  "properties": {
    "addr:full":"8 Hodel St Rosslea QLD 4812",
    "addr:housenumber":"8",
    "addr:postcode":"4812",
    "addr:street":"Hodel St",
    "iso:country":"AU",
    "sg:address":"8 Hodel St",
    "sg:city":"Rosslea",
    "sg:classifiers":[
        {
            "category":"Organizations",
            "subcategory":"Professional Association",
            "type":"Services"
        }
    ],
    "sg:phone":"+61 7 4728 7010",
    "sg:postcode":"4812",
    "sg:province":"QLD",
    "sg:tags":[
        "web",
        "internet"
    ],
    "wof:name":"Active Online",
    "wof:placetype":"venue"
},
  "geometry": {"coordinates":[146.80190999999999,-19.290924],"type":"Point"}
}