{
  "type": "Feature",
  "properties": {
    "addr:full":"Cnr of Old Northern & Keong Rds Albany Creek QLD 4035",
    "addr:postcode":"4035",
    "iso:country":"AU",
    "sg:address":"Cnr of Old Northern & Keong Rds",
    "sg:city":"Albany Creek",
    "sg:classifiers":[
        {
            "category":"Retail",
            "subcategory":"Veterinary Services",
            "type":"Services"
        }
    ],
    "sg:phone":"+61 7 3264 6700",
    "sg:postcode":"4035",
    "sg:province":"QLD",
    "sg:tags":[
        "surgeon"
    ],
    "wof:name":"Petmania Vet Surgery",
    "wof:placetype":"venue"
},
  "geometry": {"coordinates":[152.96537799999999,-27.345913],"type":"Point"}
}