{
  "type": "Feature",
  "properties": {
    "addr:full":"Flinders Place 14 Brisbane St Ipswich QLD 4305",
    "addr:housenumber":"14",
    "addr:postcode":"4305",
    "addr:street":"Flinders;Brisbane St",
    "iso:country":"AU",
    "sg:address":"Flinders Place 14 Brisbane St",
    "sg:city":"Ipswich",
    "sg:classifiers":[
        {
            "category":"Health Services",
            "subcategory":"Doctor",
            "type":"Services"
        }
    ],
    "sg:phone":"+61 7 3812 5166",
    "sg:postcode":"4305",
    "sg:province":"QLD",
    "sg:tags":[
        "medical",
        "practitioner"
    ],
    "wof:name":"Williams Derwin",
    "wof:placetype":"venue"
},
  "geometry": {"coordinates":[152.76446533199999,-27.6154747009],"type":"Point"}
}