{
  "type": "Feature",
  "properties": {
    "addr:full":"27 Quinlivan Rd Pooraka SA 5095",
    "addr:housenumber":"27",
    "addr:postcode":"5095",
    "addr:street":"Quinlivan Rd",
    "iso:country":"AU",
    "sg:address":"27 Quinlivan Rd",
    "sg:city":"Pooraka",
    "sg:classifiers":[
        {
            "category":"Professional",
            "subcategory":"Art Services",
            "type":"Services"
        }
    ],
    "sg:phone":"+61 8 8260 2714",
    "sg:postcode":"5095",
    "sg:province":"SA",
    "sg:tags":[
        "decorator",
        "painter"
    ],
    "wof:name":"Robson H R & Co",
    "wof:placetype":"venue"
},
  "geometry": {"coordinates":[138.62577819800001,-34.8266601562],"type":"Point"}
}