{
  "type": "Feature",
  "properties": {
    "addr:full":"Level 3, Shop 3013, Westfield Shopping Cntr, Miranda Miranda NSW 2228",
    "addr:housenumber":"shop 3013",
    "addr:postcode":"2228",
    "addr:street":"Westfield Shopping Cntr",
    "iso:country":"AU",
    "sg:address":"Level 3, Shop 3013, Westfield Shopping Cntr, Miranda",
    "sg:city":"Miranda",
    "sg:classifiers":[
        {
            "category":"Personal",
            "subcategory":"Hair Removal",
            "type":"Services"
        }
    ],
    "sg:phone":"+61 2 9531 8102",
    "sg:postcode":"2228",
    "sg:province":"NSW",
    "wof:name":"Nirvana Beauty",
    "wof:placetype":"venue"
},
  "geometry": {"coordinates":[151.106521606,-34.0335655212],"type":"Point"}
}