{
  "type": "Feature",
  "properties": {
    "addr:full":"7/ 78 Mulgrave Rd Cairns QLD 4870",
    "addr:housenumber":"/ 78",
    "addr:postcode":"4870",
    "addr:street":"Mulgrave Rd",
    "iso:country":"AU",
    "sg:address":"7/ 78 Mulgrave Rd",
    "sg:city":"Cairns",
    "sg:classifiers":[
        {
            "category":"Professional",
            "subcategory":"Engineering",
            "type":"Services"
        }
    ],
    "sg:phone":"+61 7 4031 8777",
    "sg:postcode":"4870",
    "sg:province":"QLD",
    "sg:tags":[
        "consulting",
        "engineer"
    ],
    "wof:name":"STP Consultants",
    "wof:placetype":"venue"
},
  "geometry": {"coordinates":[145.74664306599999,-16.9379043579],"type":"Point"}
}