{
  "type": "Feature",
  "properties": {
    "addr:full":"368 Huntress Rd Woodlands WA 6018",
    "addr:housenumber":"368",
    "addr:postcode":"6018",
    "addr:street":"Huntress Rd",
    "iso:country":"AU",
    "sg:address":"368 Huntress Rd",
    "sg:city":"Woodlands",
    "sg:classifiers":[
        {
            "category":"Insurance",
            "subcategory":"Insurance Agent",
            "type":"Services"
        }
    ],
    "sg:phone":"+61 8 9446 8195",
    "sg:postcode":"6018",
    "sg:province":"WA",
    "wof:name":"Dan Byrne",
    "wof:placetype":"venue"
},
  "geometry": {"coordinates":[115.78752899200001,-31.9055347443],"type":"Point"}
}