{
  "type": "Feature",
  "properties": {
    "addr:full":"Shp6/ 144 Brisbane Rd Mooloolaba QLD 4557",
    "addr:housenumber":"144",
    "addr:postcode":"4557",
    "addr:street":"Brisbane Rd",
    "iso:country":"AU",
    "sg:address":"Shp6/ 144 Brisbane Rd",
    "sg:city":"Mooloolaba",
    "sg:classifiers":[
        {
            "category":"Fast Food",
            "type":"Food & Drink"
        }
    ],
    "sg:phone":"+61 7 5444 4819",
    "sg:postcode":"4557",
    "sg:province":"QLD",
    "sg:tags":[
        "away",
        "take"
    ],
    "wof:name":"Wikid Fish & Chips",
    "wof:placetype":"venue"
},
  "geometry": {"coordinates":[153.11491394000001,-26.6900978088],"type":"Point"}
}