{
  "type": "Feature",
  "properties": {
    "iso:country":"AU",
    "sg:address":"U1/ 14",
    "sg:city":"Biscayne Way Jandakot",
    "sg:classifiers":[
        {
            "category":"Wholesale",
            "subcategory":"Machinery & Supplies",
            "type":"Manufacturing & Wholesale Goods"
        }
    ],
    "sg:phone":"+61 8 9479 6022",
    "sg:postcode":"6164",
    "sg:province":"WA",
    "sg:tags":[
        "instrument"
    ],
    "wof:name":"DG Instruments Pty. Ltd.",
    "wof:placetype":"venue"
},
  "geometry": {"coordinates":[115.87233,-32.121716],"type":"Point"}
}