{
  "type": "Feature",
  "properties": {
    "iso:country":"AU",
    "sg:address":"4 Durban Crt",
    "sg:city":"Keilor Downs",
    "sg:classifiers":[
        {
            "category":"Professional",
            "subcategory":"Art Services",
            "type":"Services"
        }
    ],
    "sg:phone":"+61 3 9367 4571",
    "sg:postcode":"3038",
    "sg:province":"VIC",
    "sg:tags":[
        "decorator",
        "painter"
    ],
    "wof:name":"Ivan's Maintenance & Painting Service",
    "wof:placetype":"venue"
},
  "geometry": {"coordinates":[144.808777,-37.722828],"type":"Point"}
}