{
  "type": "Feature",
  "properties": {
    "iso:country":"AU",
    "sg:address":"98 Enterprise St",
    "sg:city":"Bundaberg",
    "sg:classifiers":[
        {
            "category":"Autos & Motor Vehicles",
            "subcategory":"Auto Supplies",
            "type":"Retail Goods"
        }
    ],
    "sg:phone":"+61 7 4153 1581",
    "sg:postcode":"4670",
    "sg:province":"QLD",
    "sg:tags":[
        "wheel",
        "four",
        "equipment",
        "drive",
        "accessory"
    ],
    "wof:name":"Wide Bay Harvester Service Pty Ltd",
    "wof:placetype":"venue"
},
  "geometry": {"coordinates":[152.34078979500001,-24.8907546997],"type":"Point"}
}