{
  "type": "Feature",
  "properties": {
    "addr:full":"94 Sydney St Kilmore VIC 3764",
    "addr:housenumber":"94",
    "addr:postcode":"3764",
    "addr:street":"Sydney St",
    "iso:country":"AU",
    "sg:address":"94 Sydney St",
    "sg:city":"Kilmore",
    "sg:classifiers":[
        {
            "category":"Social Services",
            "subcategory":"Adult Care",
            "type":"Services"
        }
    ],
    "sg:phone":"+61 3 5781 0188",
    "sg:postcode":"3764",
    "sg:province":"VIC",
    "sg:tags":[
        "towing"
    ],
    "wof:name":"Kilmore Towing",
    "wof:placetype":"venue"
},
  "geometry": {"coordinates":[144.949615478,-37.288028717],"type":"Point"}
}