{
  "type": "Feature",
  "properties": {
    "addr:full":"4/ 8 Bonnal Rd Erina NSW 2250",
    "addr:housenumber":"/ 8",
    "addr:postcode":"2250",
    "addr:street":"Bonnal Rd",
    "iso:country":"AU",
    "sg:address":"4/ 8 Bonnal Rd",
    "sg:city":"Erina",
    "sg:classifiers":[
        {
            "category":"Social Services",
            "type":"Services"
        }
    ],
    "sg:phone":"+61 429 436 508",
    "sg:postcode":"2250",
    "sg:province":"NSW",
    "sg:tags":[
        "kinesiology"
    ],
    "wof:name":"Tammy Roberts",
    "wof:placetype":"venue"
},
  "geometry": {"coordinates":[151.38388061500001,-33.4352111816],"type":"Point"}
}