{
  "type": "Feature",
  "properties": {
    "iso:country":"AU",
    "sg:address":"22b Horwood Pl",
    "sg:city":"Parramatta",
    "sg:classifiers":[
        {
            "category":"Professional",
            "type":"Services"
        }
    ],
    "sg:phone":"+61 2 9893 7611",
    "sg:postcode":"2150",
    "sg:province":"NSW",
    "sg:tags":[
        "courier"
    ],
    "wof:name":"Pack & Send",
    "wof:placetype":"venue"
},
  "geometry": {"coordinates":[150.921600342,-33.7408447266],"type":"Point"}
}