{
  "type": "Feature",
  "properties": {
    "addr:full":"23 Kateena Ave Tascott NSW 2250",
    "addr:housenumber":"23",
    "addr:postcode":"2250",
    "addr:street":"Kateena Ave",
    "iso:country":"AU",
    "sg:address":"23 Kateena Ave",
    "sg:city":"Tascott",
    "sg:classifiers":[
        {
            "category":"Professional",
            "subcategory":"Art Services",
            "type":"Services"
        }
    ],
    "sg:phone":"+61 2 4324 6458",
    "sg:postcode":"2250",
    "sg:province":"NSW",
    "sg:tags":[
        "arranger",
        "music",
        "composer"
    ],
    "wof:name":"Brush Turkey Recording Studio",
    "wof:placetype":"venue"
},
  "geometry": {"coordinates":[151.31996154800001,-33.4475021362],"type":"Point"}
}