{
  "type": "Feature",
  "properties": {
    "addr:full":"38 Marine Pde Kingscliff NSW 2487",
    "addr:housenumber":"38",
    "addr:postcode":"2487",
    "addr:street":"Marine Pde",
    "iso:country":"AU",
    "sg:address":"38 Marine Pde",
    "sg:city":"Kingscliff",
    "sg:classifiers":[
        {
            "category":"Personal",
            "subcategory":"Beauty Salon",
            "type":"Services"
        }
    ],
    "sg:phone":"+61 2 6674 1155",
    "sg:postcode":"2487",
    "sg:province":"NSW",
    "sg:tags":[
        "hairdresser"
    ],
    "wof:name":"Coastal Hair",
    "wof:placetype":"venue"
},
  "geometry": {"coordinates":[153.569625855,-28.2469882965],"type":"Point"}
}