{
  "type": "Feature",
  "properties": {
    "addr:full":"38 Armstrong St Middle Park VIC 3206",
    "addr:housenumber":"38",
    "addr:postcode":"3206",
    "addr:street":"Armstrong St",
    "iso:country":"AU",
    "sg:address":"38 Armstrong St",
    "sg:city":"Middle Park",
    "sg:classifiers":[
        {
            "category":"Personal",
            "subcategory":"Beauty Salon",
            "type":"Services"
        }
    ],
    "sg:phone":"+61 3 9690 2834",
    "sg:postcode":"3206",
    "sg:province":"VIC",
    "sg:tags":[
        "hairdresser"
    ],
    "wof:name":"La Catalana",
    "wof:placetype":"venue"
},
  "geometry": {"coordinates":[144.963776,-37.85083],"type":"Point"}
}