{
  "type": "Feature",
  "properties": {
    "addr:full":"253 Gouger St Adelaide SA 5000",
    "addr:housenumber":"253",
    "addr:postcode":"5000",
    "addr:street":"Gouger St",
    "iso:country":"AU",
    "sg:address":"253 Gouger St",
    "sg:city":"Adelaide",
    "sg:classifiers":[
        {
            "category":"Arena",
            "subcategory":"Sports Club",
            "type":"Entertainment"
        }
    ],
    "sg:phone":"+61 8 8231 9600",
    "sg:postcode":"5000",
    "sg:province":"SA",
    "sg:tags":[
        "defence",
        "supply",
        "self",
        "instruction",
        "martial art"
    ],
    "wof:name":"Wing Chun Master Jim Fung's Academy",
    "wof:placetype":"venue"
},
  "geometry": {"coordinates":[138.58984375,-34.9307746887],"type":"Point"}
}