{
  "type": "Feature",
  "properties": {
    "addr:full":"590 Redland Bay Rd Alexandra Hills QLD 4161",
    "addr:housenumber":"590",
    "addr:postcode":"4161",
    "addr:street":"Redland Bay Rd",
    "iso:country":"AU",
    "sg:address":"590 Redland Bay Rd",
    "sg:city":"Alexandra Hills",
    "sg:classifiers":[
        {
            "category":"Health Services",
            "subcategory":"Health Practitioner",
            "type":"Services"
        }
    ],
    "sg:phone":"+61 7 3206 4303",
    "sg:postcode":"4161",
    "sg:province":"QLD",
    "sg:tags":[
        "acupuncture"
    ],
    "wof:name":"Martin Christine Paula",
    "wof:placetype":"venue"
},
  "geometry": {"coordinates":[153.221237183,-27.5470294952],"type":"Point"}
}