{
  "type": "Feature",
  "properties": {
    "addr:full":"PO Box 3730 Loganholme QLD 4129",
    "addr:postcode":"4129",
    "iso:country":"AU",
    "sg:address":"PO Box 3730",
    "sg:city":"Loganholme",
    "sg:classifiers":[
        {
            "category":"Wholesale",
            "subcategory":"Machinery & Supplies",
            "type":"Manufacturing & Wholesale Goods"
        }
    ],
    "sg:phone":"+61 7 3287 6815",
    "sg:postcode":"4129",
    "sg:province":"QLD",
    "sg:tags":[
        "machine",
        "tool",
        "engineer"
    ],
    "wof:name":"Hi-Tech Machine Tools Pty Ltd",
    "wof:placetype":"venue"
},
  "geometry": {"coordinates":[153.185791016,-27.6725502014],"type":"Point"}
}