{
  "type": "Feature",
  "properties": {
    "addr:full":"PO Box 761 Vaucluse NSW 2030",
    "addr:postcode":"2030",
    "iso:country":"AU",
    "sg:address":"PO Box 761",
    "sg:city":"Vaucluse",
    "sg:classifiers":[
        {
            "category":"Real Estate",
            "subcategory":"Real Estate Agent",
            "type":"Services"
        }
    ],
    "sg:phone":"+61 2 9337 5522",
    "sg:postcode":"2030",
    "sg:province":"NSW",
    "sg:website":"http://www.sirealty.com.au",
    "wof:name":"Sydney International Realty (S.I Realty)",
    "wof:placetype":"venue"
},
  "geometry": {"coordinates":[151.27986145,-33.8593482971],"type":"Point"}
}