{
  "type": "Feature",
  "properties": {
    "addr:full":"2 Trethina Mews Clarkson WA 6030",
    "addr:housenumber":"2",
    "addr:postcode":"6030",
    "addr:street":"Trethina Mews",
    "iso:country":"AU",
    "sg:address":"2 Trethina Mews",
    "sg:city":"Clarkson",
    "sg:classifiers":[
        {
            "category":"Home & Garden",
            "subcategory":"Carpets & Floor Coverings",
            "type":"Retail Goods"
        }
    ],
    "sg:phone":"+61 417 942 872",
    "sg:postcode":"6030",
    "sg:province":"WA",
    "sg:tags":[
        "tile",
        "wall",
        "layer"
    ],
    "wof:name":"Paul Kelly Tiling & Home Maintenance",
    "wof:placetype":"venue"
},
  "geometry": {"coordinates":[115.72720336899999,-31.6742725372],"type":"Point"}
}