{
  "type": "Feature",
  "properties": {
    "iso:country":"AU",
    "sg:address":"13 Alma Ave",
    "sg:city":"Murray Bridge",
    "sg:classifiers":[
        {
            "category":"Home & Garden",
            "subcategory":"Garden Supply",
            "type":"Retail Goods"
        }
    ],
    "sg:phone":"+61 8 8532 2673",
    "sg:postcode":"5253",
    "sg:province":"SA",
    "sg:tags":[
        "equipment"
    ],
    "wof:name":"Allstop Mowers",
    "wof:placetype":"venue"
},
  "geometry": {"coordinates":[139.262374878,-35.1151123047],"type":"Point"}
}