{
  "type": "Feature",
  "properties": {
    "addr:full":"1 James St Charlestown NSW 2290",
    "addr:housenumber":"1",
    "addr:postcode":"2290",
    "addr:street":"James St",
    "iso:country":"AU",
    "sg:address":"1 James St",
    "sg:city":"Charlestown",
    "sg:classifiers":[
        {
            "category":"Building & Trades",
            "subcategory":"Pest Control",
            "type":"Services"
        }
    ],
    "sg:phone":"+61 2 4942 5533",
    "sg:postcode":"2290",
    "sg:province":"NSW",
    "wof:name":"Canberra Pest Clearance",
    "wof:placetype":"venue"
},
  "geometry": {"coordinates":[151.695602417,-32.9687843323],"type":"Point"}
}