{
  "type": "Feature",
  "properties": {
    "addr:full":"Kos Village, 2 Finucane Rd Alexandra Hills QLD 4161",
    "addr:postcode":"4161",
    "addr:street":"Finucane Rd",
    "iso:country":"AU",
    "sg:address":"Kos Village, 2 Finucane Rd",
    "sg:city":"Alexandra Hills",
    "sg:classifiers":[
        {
            "category":"Health Services",
            "subcategory":"Dentist",
            "type":"Services"
        }
    ],
    "sg:phone":"+61 7 3245 5511",
    "sg:postcode":"4161",
    "sg:province":"QLD",
    "wof:name":"Bruce B Wilson",
    "wof:placetype":"venue"
},
  "geometry": {"coordinates":[153.22056579599999,-27.5228900909],"type":"Point"}
}