{
  "type": "Feature",
  "properties": {
    "addr:full":"Un 3, 11 Lagana Pl Wetherill Park NSW 2164",
    "addr:housenumber":"11",
    "addr:postcode":"2164",
    "addr:street":"Lagana Pl",
    "iso:country":"AU",
    "sg:address":"Un 3, 11 Lagana Pl",
    "sg:city":"Wetherill Park",
    "sg:classifiers":[
        {
            "category":"Building & Trades",
            "subcategory":"Construction",
            "type":"Services"
        }
    ],
    "sg:phone":"+61 2 9756 4942",
    "sg:postcode":"2164",
    "sg:province":"NSW",
    "sg:tags":[
        "earth",
        "excavating",
        "moving",
        "contractor"
    ],
    "wof:name":"Acclaimed Excavations Pty Ltd",
    "wof:placetype":"venue"
},
  "geometry": {"coordinates":[150.888397217,-33.8508720398],"type":"Point"}
}