{
  "type": "Feature",
  "properties": {
    "addr:full":"129 Abbott St Cairns QLD 4870",
    "addr:housenumber":"129",
    "addr:postcode":"4870",
    "addr:street":"Abbott St",
    "iso:country":"AU",
    "sg:address":"129 Abbott St",
    "sg:city":"Cairns",
    "sg:classifiers":[
        {
            "category":"Food & Beverages",
            "subcategory":"Specialty",
            "type":"Retail Goods"
        }
    ],
    "sg:phone":"+61 7 4051 5742",
    "sg:postcode":"4870",
    "sg:province":"QLD",
    "sg:tags":[
        "product",
        "health"
    ],
    "wof:name":"Health Bug The",
    "wof:placetype":"venue"
},
  "geometry": {"coordinates":[145.77877807600001,-16.9237289429],"type":"Point"}
}