{
  "type": "Feature",
  "properties": {
    "iso:country":"AU",
    "sg:address":"PO Box 5100",
    "sg:city":"Gwandalan",
    "sg:classifiers":[
        {
            "category":"Professional",
            "subcategory":"Business Services",
            "type":"Services"
        }
    ],
    "sg:phone":"+61 2 4972 5007",
    "sg:postcode":"2259",
    "sg:province":"NSW",
    "sg:tags":[
        "management",
        "event"
    ],
    "wof:name":"Somebodies Image",
    "wof:placetype":"venue"
},
  "geometry": {"coordinates":[151.580276489,-33.1394309998],"type":"Point"}
}