{
  "type": "Feature",
  "properties": {
    "iso:country":"AU",
    "sg:address":"38 Sheoak Rd",
    "sg:city":"Belair",
    "sg:classifiers":[
        {
            "category":"Cafe",
            "type":"Food & Drink"
        }
    ],
    "sg:phone":"+61 8 8278 2946",
    "sg:postcode":"5052",
    "sg:province":"SA",
    "wof:name":"Sheoak Cafe",
    "wof:placetype":"venue"
},
  "geometry": {"coordinates":[138.63035600000001,-34.997196],"type":"Point"}
}