{
  "type": "Feature",
  "properties": {
    "addr:full":"Cairns Golf Club Bruce Hwy Woree QLD 4868",
    "addr:postcode":"4868",
    "addr:street":"Bruce Hwy",
    "iso:country":"AU",
    "sg:address":"Cairns Golf Club Bruce Hwy",
    "sg:city":"Woree",
    "sg:classifiers":[
        {
            "category":"Sports & Exercise",
            "subcategory":"Golf",
            "type":"Entertainment"
        }
    ],
    "sg:phone":"+61 7 4054 1494",
    "sg:postcode":"4868",
    "sg:province":"QLD",
    "sg:tags":[
        "club"
    ],
    "wof:name":"Brett Wilson's Golf Shop",
    "wof:placetype":"venue"
},
  "geometry": {"coordinates":[145.74688720699999,-16.9543991089],"type":"Point"}
}