{
  "type": "Feature",
  "properties": {
    "addr:full":"Sayers Rd Tarneit VIC 3029",
    "addr:postcode":"3029",
    "addr:street":"Sayers Rd",
    "iso:country":"AU",
    "sg:address":"Sayers Rd",
    "sg:city":"Tarneit",
    "sg:classifiers":[
        {
            "category":"Real Estate",
            "subcategory":"Real Estate Agent",
            "type":"Services"
        }
    ],
    "sg:phone":"+61 3 9748 3011",
    "sg:postcode":"3029",
    "sg:province":"VIC",
    "wof:name":"Sweeney Estate Agents",
    "wof:placetype":"venue"
},
  "geometry": {"coordinates":[144.70820599999999,-37.850697],"type":"Point"}
}