{
  "type": "Feature",
  "properties": {
    "addr:full":"6 Boundary Rd Mosman Park WA 6012",
    "addr:housenumber":"6",
    "addr:postcode":"6012",
    "addr:street":"Boundary Rd",
    "iso:country":"AU",
    "sg:address":"6 Boundary Rd",
    "sg:city":"Mosman Park",
    "sg:classifiers":[
        {
            "category":"Retail",
            "subcategory":"Storage",
            "type":"Services"
        }
    ],
    "sg:phone":"+61 8 9310 1927",
    "sg:postcode":"6012",
    "sg:province":"WA",
    "sg:tags":[
        "removal",
        "furniture"
    ],
    "wof:name":"We Work For You Removals",
    "wof:placetype":"venue"
},
  "geometry": {"coordinates":[115.757957459,-32.0163116455],"type":"Point"}
}