{
  "type": "Feature",
  "properties": {
    "addr:full":"54 Grove St Earlwood NSW 2206",
    "addr:housenumber":"54",
    "addr:postcode":"2206",
    "addr:street":"Grove St",
    "iso:country":"AU",
    "sg:address":"54 Grove St",
    "sg:city":"Earlwood",
    "sg:classifiers":[
        {
            "category":"Professional",
            "subcategory":"Art Services",
            "type":"Services"
        }
    ],
    "sg:phone":"+61 422 443 799",
    "sg:postcode":"2206",
    "sg:province":"NSW",
    "sg:tags":[
        "decorator",
        "painter"
    ],
    "wof:name":"Colourfx Painting Services",
    "wof:placetype":"venue"
},
  "geometry": {"coordinates":[151.12233000000001,-33.922016],"type":"Point"}
}