{
  "type": "Feature",
  "properties": {
    "addr:full":"Unit 7 400 Grand Junction Rd Mansfield Park SA 5012",
    "addr:housenumber":"400",
    "addr:postcode":"5012",
    "addr:street":"Grand Junction Rd",
    "iso:country":"AU",
    "sg:address":"Unit 7 400 Grand Junction Rd",
    "sg:city":"Mansfield Park",
    "sg:classifiers":[
        {
            "category":"Wholesale",
            "subcategory":"Hardware",
            "type":"Manufacturing & Wholesale Goods"
        }
    ],
    "sg:phone":"+61 8 8347 1820",
    "sg:postcode":"5012",
    "sg:province":"SA",
    "wof:name":"Whitbread Marketing Pty Ltd",
    "wof:placetype":"venue"
},
  "geometry": {"coordinates":[138.54916381800001,-34.8506507874],"type":"Point"}
}