{
  "type": "Feature",
  "properties": {
    "iso:country":"AU",
    "sg:address":"24 Brysons Rd",
    "sg:city":"Warranwood",
    "sg:classifiers":[
        {
            "category":"Building & Trades",
            "subcategory":"Construction",
            "type":"Services"
        }
    ],
    "sg:phone":"+61 3 9876 2870",
    "sg:postcode":"3134",
    "sg:province":"VIC",
    "sg:tags":[
        "road",
        "contractor"
    ],
    "wof:name":"Liora Constructions Pty Ltd",
    "wof:placetype":"venue"
},
  "geometry": {"coordinates":[145.249267578,-37.7721405029],"type":"Point"}
}