{
  "type": "Feature",
  "properties": {
    "addr:full":"Level 1, Whistler St Manly NSW 2095",
    "addr:postcode":"2095",
    "addr:street":"Whistler St",
    "iso:country":"AU",
    "sg:address":"Level 1, Whistler St",
    "sg:city":"Manly",
    "sg:classifiers":[
        {
            "category":"Personal",
            "subcategory":"Beauty Salon",
            "type":"Services"
        }
    ],
    "sg:phone":"+61 2 9977 0349",
    "sg:postcode":"2095",
    "sg:province":"NSW",
    "wof:name":"Honey Body Salon",
    "wof:placetype":"venue"
},
  "geometry": {"coordinates":[151.28512573200001,-33.797958374],"type":"Point"}
}