{
  "type": "Feature",
  "properties": {
    "addr:full":"Canning Mills Rd Kelmscott WA 6111",
    "addr:postcode":"6111",
    "addr:street":"Mills Rd",
    "iso:country":"AU",
    "sg:address":"Canning Mills Rd",
    "sg:city":"Kelmscott",
    "sg:classifiers":[
        {
            "category":"Food & Beverages",
            "subcategory":"Fruits & Vegetables",
            "type":"Retail Goods"
        }
    ],
    "sg:phone":"+61 8 9390 5321",
    "sg:postcode":"6111",
    "sg:province":"WA",
    "sg:tags":[
        "wholesale"
    ],
    "wof:name":"Papalia D",
    "wof:placetype":"venue"
},
  "geometry": {"coordinates":[116.02438354500001,-32.120098114],"type":"Point"}
}