{
  "type": "Feature",
  "properties": {
    "addr:full":"Rockley Rd Atherton QLD 4883",
    "addr:postcode":"4883",
    "addr:street":"Rockley Rd",
    "iso:country":"AU",
    "sg:address":"Rockley Rd",
    "sg:city":"Atherton",
    "sg:classifiers":[
        {
            "category":"Building & Trades",
            "subcategory":"Construction",
            "type":"Services"
        }
    ],
    "sg:phone":"+61 7 4091 2696",
    "sg:postcode":"4883",
    "sg:province":"QLD",
    "sg:tags":[
        "contractor"
    ],
    "wof:name":"Cecolini V & K",
    "wof:placetype":"venue"
},
  "geometry": {"coordinates":[145.49597168,-17.275396347],"type":"Point"}
}