{
  "type": "Feature",
  "properties": {
    "iso:country":"AU",
    "sg:address":"Level 1 483 Riley St",
    "sg:city":"Surry Hills",
    "sg:classifiers":[
        {
            "category":"Professional",
            "subcategory":"Accounting & Tax Preparation",
            "type":"Services"
        }
    ],
    "sg:phone":"+61 2 9319 3533",
    "sg:postcode":"2010",
    "sg:province":"NSW",
    "sg:tags":[
        "accountant",
        "auditor"
    ],
    "wof:name":"Surry Partners Accountants",
    "wof:placetype":"venue"
},
  "geometry": {"coordinates":[151.21191406200001,-33.8878517151],"type":"Point"}
}