{
  "type": "Feature",
  "properties": {
    "addr:full":"1053 South Rd Melrose Park SA 5039",
    "addr:housenumber":"1053",
    "addr:postcode":"5039",
    "addr:street":"South Rd",
    "iso:country":"AU",
    "sg:address":"1053 South Rd",
    "sg:city":"Melrose Park",
    "sg:classifiers":[
        {
            "category":"Building & Trades",
            "subcategory":"Landscaping Services",
            "type":"Services"
        }
    ],
    "sg:phone":"+61 8 8296 3341",
    "sg:postcode":"5039",
    "sg:province":"SA",
    "sg:tags":[
        "stump",
        "tree",
        "felling",
        "removal"
    ],
    "wof:name":"Branching Out Tree Services",
    "wof:placetype":"venue"
},
  "geometry": {"coordinates":[138.574661255,-34.9870910645],"type":"Point"}
}