{
  "type": "Feature",
  "properties": {
    "addr:full":"2 Mitcham Rd Donvale VIC 3111",
    "addr:housenumber":"2",
    "addr:postcode":"3111",
    "addr:street":"Mitcham Rd",
    "iso:country":"AU",
    "sg:address":"2 Mitcham Rd",
    "sg:city":"Donvale",
    "sg:classifiers":[
        {
            "category":"Health Services",
            "subcategory":"Doctor",
            "type":"Services"
        }
    ],
    "sg:phone":"+61 3 9842 7700",
    "sg:postcode":"3111",
    "sg:province":"VIC",
    "sg:tags":[
        "medical",
        "practitioner"
    ],
    "wof:name":"Tunstall Square Family Medical Centre",
    "wof:placetype":"venue"
},
  "geometry": {"coordinates":[145.17349243199999,-37.7909126282],"type":"Point"}
}