{
  "type": "Feature",
  "properties": {
    "addr:full":"19 Sugarleaf Crt Burleigh Waters QLD 4220",
    "addr:housenumber":"19",
    "addr:postcode":"4220",
    "addr:street":"Sugarleaf Crt",
    "iso:country":"AU",
    "sg:address":"19 Sugarleaf Crt",
    "sg:city":"Burleigh Waters",
    "sg:classifiers":[
        {
            "category":"Building & Trades",
            "subcategory":"Construction",
            "type":"Services"
        }
    ],
    "sg:phone":"+61 401 061 105",
    "sg:postcode":"4220",
    "sg:province":"QLD",
    "sg:tags":[
        "concrete",
        "contractor"
    ],
    "wof:name":"Coastline Bricklaying & Concreting Services",
    "wof:placetype":"venue"
},
  "geometry": {"coordinates":[153.42460632300001,-28.0910873413],"type":"Point"}
}