{
  "type": "Feature",
  "properties": {
    "addr:full":"2a Stafford St Kingswood NSW 2747",
    "addr:housenumber":"2a",
    "addr:postcode":"2747",
    "addr:street":"Stafford St",
    "iso:country":"AU",
    "sg:address":"2a Stafford St",
    "sg:city":"Kingswood",
    "sg:classifiers":[
        {
            "category":"Personal",
            "subcategory":"Beauty Salon",
            "type":"Services"
        }
    ],
    "sg:phone":"+61 2 4736 8662",
    "sg:postcode":"2747",
    "sg:province":"NSW",
    "sg:tags":[
        "hairdresser"
    ],
    "wof:name":"Stafford St Hair Design",
    "wof:placetype":"venue"
},
  "geometry": {"coordinates":[150.71937560999999,-33.7639808655],"type":"Point"}
}