{
  "type": "Feature",
  "properties": {
    "iso:country":"AU",
    "sg:address":"19/ 71 Coorigil Rd",
    "sg:city":"Carnegie",
    "sg:classifiers":[
        {
            "category":"Professional",
            "subcategory":"Engineering",
            "type":"Services"
        }
    ],
    "sg:phone":"+61 3 9569 0426",
    "sg:postcode":"3163",
    "sg:province":"VIC",
    "sg:tags":[
        "consulting",
        "engineer"
    ],
    "wof:name":"Invent Design Develop Pty Ltd",
    "wof:placetype":"venue"
},
  "geometry": {"coordinates":[145.062957764,-37.8960380554],"type":"Point"}
}