{
  "type": "Feature",
  "properties": {
    "addr:full":"3 Glover St Mosman NSW 2088",
    "addr:housenumber":"3",
    "addr:postcode":"2088",
    "addr:street":"Glover St",
    "iso:country":"AU",
    "sg:address":"3 Glover St",
    "sg:city":"Mosman",
    "sg:classifiers":[
        {
            "category":"Professional",
            "subcategory":"Art Services",
            "type":"Services"
        }
    ],
    "sg:phone":"+61 2 9960 5675",
    "sg:postcode":"2088",
    "sg:province":"NSW",
    "sg:tags":[
        "artist"
    ],
    "wof:name":"Stack Ben",
    "wof:placetype":"venue"
},
  "geometry": {"coordinates":[151.23721313499999,-33.8287239075],"type":"Point"}
}