{
  "type": "Feature",
  "properties": {
    "addr:full":"2 / 11 Ireland St Bright VIC 3741",
    "addr:housenumber":"/ 11",
    "addr:postcode":"3741",
    "addr:street":"Ireland St",
    "iso:country":"AU",
    "sg:address":"2 / 11 Ireland St",
    "sg:city":"Bright",
    "sg:classifiers":[
        {
            "category":"Fast Food",
            "type":"Food & Drink"
        }
    ],
    "sg:phone":"+61 3 5755 2380",
    "sg:postcode":"3741",
    "sg:province":"VIC",
    "sg:tags":[
        "away",
        "take"
    ],
    "wof:name":"Get Spiced",
    "wof:placetype":"venue"
},
  "geometry": {"coordinates":[146.96095299999999,-36.729374],"type":"Point"}
}