{
  "type": "Feature",
  "properties": {
    "iso:country":"AU",
    "sg:address":"18/ 888 Bourke St",
    "sg:city":"Zetland",
    "sg:classifiers":[
        {
            "category":"Professional",
            "subcategory":"Computer Services",
            "type":"Services"
        }
    ],
    "sg:phone":"+61 2 9690 0041",
    "sg:postcode":"2017",
    "sg:province":"NSW",
    "sg:tags":[
        "consultant",
        "system"
    ],
    "wof:name":"Muscle Computers",
    "wof:placetype":"venue"
},
  "geometry": {"coordinates":[151.207275391,-33.9032402039],"type":"Point"}
}