{
  "type": "Feature",
  "properties": {
    "addr:full":"Unit 4/ 93 Rawson Rd Woy Woy NSW 2256",
    "addr:housenumber":"93",
    "addr:postcode":"2256",
    "addr:street":"Rawson Rd",
    "iso:country":"AU",
    "sg:address":"Unit 4/ 93 Rawson Rd",
    "sg:city":"Woy Woy",
    "sg:classifiers":[
        {
            "category":"Professional",
            "subcategory":"Computer Services",
            "type":"Services"
        }
    ],
    "sg:phone":"+61 2 4344 6777",
    "sg:postcode":"2256",
    "sg:province":"NSW",
    "sg:tags":[
        "consultant",
        "system"
    ],
    "wof:name":"Pardyline Networks",
    "wof:placetype":"venue"
},
  "geometry": {"coordinates":[151.32131957999999,-33.4937782288],"type":"Point"}
}