{
  "type": "Feature",
  "properties": {
    "iso:country":"AU",
    "sg:address":"Chopstix Arcade 249 Brunswick St",
    "sg:city":"Fortitude Valley",
    "sg:classifiers":[
        {
            "category":"Shopping",
            "subcategory":"Jewelry",
            "type":"Retail Goods"
        }
    ],
    "sg:phone":"+61 7 3252 2329",
    "sg:postcode":"4006",
    "sg:province":"QLD",
    "sg:tags":[
        "jeweller"
    ],
    "wof:name":"Milo M.",
    "wof:placetype":"venue"
},
  "geometry": {"coordinates":[153.03306579599999,-27.4571018219],"type":"Point"}
}