{
  "type": "Feature",
  "properties": {
    "iso:country":"AU",
    "sg:address":"7/ 52 Aurora Ave",
    "sg:city":"Queanbeyan",
    "sg:classifiers":[
        {
            "category":"Professional",
            "subcategory":"Engineering",
            "type":"Services"
        }
    ],
    "sg:phone":"+61 410 535 260",
    "sg:postcode":"2620",
    "sg:province":"NSW",
    "sg:tags":[
        "manufacturing",
        "engineer"
    ],
    "wof:name":"Canberra Hydraulic Engineering Services",
    "wof:placetype":"venue"
},
  "geometry": {"coordinates":[149.24961852999999,-35.3385353088],"type":"Point"}
}