{
  "type": "Feature",
  "properties": {
    "iso:country":"AU",
    "sg:address":"3 Pentland Rd",
    "sg:city":"Salisbury South",
    "sg:classifiers":[
        {
            "category":"Government",
            "subcategory":"Department Of Motor Vehicles",
            "type":"Public Place"
        }
    ],
    "sg:phone":"+61 8 8283 0888",
    "sg:postcode":"5106",
    "sg:province":"SA",
    "sg:tags":[
        "wholesaler",
        "mfrs",
        "accessory"
    ],
    "wof:name":"Coolchem SA",
    "wof:placetype":"venue"
},
  "geometry": {"coordinates":[138.643356,-34.783817],"type":"Point"}
}