{
  "type": "Feature",
  "properties": {
    "iso:country":"AU",
    "sg:address":"81 Glenelg Ave",
    "sg:city":"Wembley Downs",
    "sg:classifiers":[
        {
            "category":"Building & Trades",
            "subcategory":"Cleaning & Sanitation",
            "type":"Services"
        }
    ],
    "sg:phone":"+61 417 918 169",
    "sg:postcode":"6019",
    "sg:province":"WA",
    "sg:tags":[
        "industrial",
        "commercial",
        "contractor"
    ],
    "wof:name":"Superclene Window Cleaning",
    "wof:placetype":"venue"
},
  "geometry": {"coordinates":[115.775756836,-31.918838501],"type":"Point"}
}