{
  "type": "Feature",
  "properties": {
    "addr:full":"506 Bunnerong Rd Matraville NSW 2036",
    "addr:housenumber":"506",
    "addr:postcode":"2036",
    "addr:street":"Bunnerong Rd",
    "iso:country":"AU",
    "sg:address":"506 Bunnerong Rd",
    "sg:city":"Matraville",
    "sg:classifiers":[
        {
            "category":"Professional",
            "subcategory":"Accounting & Tax Preparation",
            "type":"Services"
        }
    ],
    "sg:phone":"+61 2 9661 8116",
    "sg:postcode":"2036",
    "sg:province":"NSW",
    "sg:tags":[
        "accountant",
        "auditor"
    ],
    "wof:name":"Savona S & Co",
    "wof:placetype":"venue"
},
  "geometry": {"coordinates":[151.231033325,-33.9583511353],"type":"Point"}
}