{
  "type": "Feature",
  "properties": {
    "addr:full":"Cnr Vauxhall St & Sandgate Rd Virginia QLD 4014",
    "addr:postcode":"4014",
    "addr:street":"St & Sandgate Rd",
    "iso:country":"AU",
    "sg:address":"Cnr Vauxhall St & Sandgate Rd",
    "sg:city":"Virginia",
    "sg:classifiers":[
        {
            "category":"Industrial Area",
            "type":"Public Place"
        }
    ],
    "sg:phone":"+61 7 3865 3955",
    "sg:postcode":"4014",
    "sg:province":"QLD",
    "sg:tags":[
        "protective",
        "clothing"
    ],
    "wof:name":"BOC",
    "wof:placetype":"venue"
},
  "geometry": {"coordinates":[153.063323975,-27.380361557],"type":"Point"}
}