{
  "type": "Feature",
  "properties": {
    "addr:full":"138 Monaro St Queanbeyan ACT 2620",
    "addr:housenumber":"138",
    "addr:postcode":"2620",
    "addr:street":"Monaro St",
    "iso:country":"AU",
    "sg:address":"138 Monaro St",
    "sg:city":"Queanbeyan",
    "sg:classifiers":[
        {
            "category":"Real Estate",
            "subcategory":"Real Estate Agent",
            "type":"Services"
        }
    ],
    "sg:phone":"+61 2 6297 3555",
    "sg:postcode":"2620",
    "sg:province":"ACT",
    "wof:name":"Southern Cross Real Estate",
    "wof:placetype":"venue"
},
  "geometry": {"coordinates":[149.23509216299999,-35.3531951904],"type":"Point"}
}