{
  "type": "Feature",
  "properties": {
    "iso:country":"AU",
    "sg:address":"10 Allison Ave",
    "sg:city":"Nowra",
    "sg:classifiers":[
        {
            "category":"Home & Garden",
            "subcategory":"Building Materials",
            "type":"Retail Goods"
        }
    ],
    "sg:phone":"+61 2 4423 4748",
    "sg:postcode":"2540",
    "sg:province":"NSW",
    "sg:tags":[
        "lawn",
        "cutting",
        "maintenance"
    ],
    "wof:name":"Rod Johnson Lawnmowing",
    "wof:placetype":"venue"
},
  "geometry": {"coordinates":[150.61500549300001,-34.886100769],"type":"Point"}
}