{
  "type": "Feature",
  "properties": {
    "addr:full":"5/ 270 Lower Dandenong Rd Mordialloc VIC 3195",
    "addr:housenumber":"/ 270",
    "addr:postcode":"3195",
    "addr:street":"Lower Dandenong Rd",
    "iso:country":"AU",
    "sg:address":"5/ 270 Lower Dandenong Rd",
    "sg:city":"Mordialloc",
    "sg:classifiers":[
        {
            "category":"Wholesale",
            "subcategory":"Medical Equipment & Supplies",
            "type":"Manufacturing & Wholesale Goods"
        }
    ],
    "sg:phone":"+61 3 9588 0833",
    "sg:postcode":"3195",
    "sg:province":"VIC",
    "sg:tags":[
        "aid",
        "care",
        "health",
        "home"
    ],
    "wof:name":"Smart-Caller Pty Ltd",
    "wof:placetype":"venue"
},
  "geometry": {"coordinates":[145.099685669,-37.9855079651],"type":"Point"}
}