{
  "type": "Feature",
  "properties": {
    "addr:full":"54 Barkly Hwy Mt Isa QLD 4825",
    "addr:housenumber":"54",
    "addr:postcode":"4825",
    "addr:street":"Barkly Hwy",
    "iso:country":"AU",
    "sg:address":"54 Barkly Hwy",
    "sg:city":"Mt Isa",
    "sg:classifiers":[
        {
            "category":"Professional",
            "subcategory":"Printing & Photocopies",
            "type":"Services"
        }
    ],
    "sg:phone":"+61 7 4743 9600",
    "sg:postcode":"4825",
    "sg:province":"QLD",
    "sg:tags":[
        "trophy"
    ],
    "wof:name":"Star Trophies",
    "wof:placetype":"venue"
},
  "geometry": {"coordinates":[139.485916,-20.699963],"type":"Point"}
}