{
  "type": "Feature",
  "properties": {
    "addr:full":"1 Gammie Crt Bundaberg QLD 4670",
    "addr:housenumber":"1",
    "addr:postcode":"4670",
    "addr:street":"Gammie Crt",
    "iso:country":"AU",
    "sg:address":"1 Gammie Crt",
    "sg:city":"Bundaberg",
    "sg:classifiers":[
        {
            "category":"Building & Trades",
            "subcategory":"Plumbing",
            "type":"Services"
        }
    ],
    "sg:phone":"+61 7 4152 5815",
    "sg:postcode":"4670",
    "sg:province":"QLD",
    "sg:tags":[
        "plumber",
        "gasfitters"
    ],
    "wof:name":"Robertson Ian Roofing & Plumbing",
    "wof:placetype":"venue"
},
  "geometry": {"coordinates":[152.36338806099999,-24.8930244446],"type":"Point"}
}