{
  "type": "Feature",
  "properties": {
    "iso:country":"AU",
    "sg:address":"105 Gow St",
    "sg:city":"Padstow",
    "sg:classifiers":[
        {
            "category":"Wholesale",
            "subcategory":"Auto Parts",
            "type":"Manufacturing & Wholesale Goods"
        }
    ],
    "sg:phone":"+61 2 9793 7399",
    "sg:postcode":"2211",
    "sg:province":"NSW",
    "sg:tags":[
        "recyclers"
    ],
    "wof:name":"All Parts R Us",
    "wof:placetype":"venue"
},
  "geometry": {"coordinates":[151.028885,-33.93705],"type":"Point"}
}