{
  "type": "Feature",
  "properties": {
    "addr:full":"174 Great Eastern Hwy Midland WA 6056",
    "addr:housenumber":"174",
    "addr:postcode":"6056",
    "addr:street":"Great Eastern Hwy",
    "iso:country":"AU",
    "sg:address":"174 Great Eastern Hwy",
    "sg:city":"Midland",
    "sg:classifiers":[
        {
            "category":"Home & Garden",
            "subcategory":"Carpets & Floor Coverings",
            "type":"Retail Goods"
        }
    ],
    "sg:phone":"+61 8 9250 1955",
    "sg:postcode":"6056",
    "sg:province":"WA",
    "sg:tags":[
        "mattress"
    ],
    "wof:name":"Bed Centre",
    "wof:placetype":"venue"
},
  "geometry": {"coordinates":[116.00971221899999,-31.8909912109],"type":"Point"}
}