{
  "type": "Feature",
  "properties": {
    "addr:full":"15 Holland Rd Blackburn South VIC 3130",
    "addr:housenumber":"15",
    "addr:postcode":"3130",
    "addr:street":"Holland Rd",
    "iso:country":"AU",
    "sg:address":"15 Holland Rd",
    "sg:city":"Blackburn South",
    "sg:classifiers":[
        {
            "category":"Manufacturing",
            "subcategory":"Rubber & Plastics",
            "type":"Manufacturing & Wholesale Goods"
        }
    ],
    "sg:phone":"+61 3 9878 8099",
    "sg:postcode":"3130",
    "sg:province":"VIC",
    "sg:tags":[
        "consultant"
    ],
    "wof:name":"G.V.U.T. Pty Ltd",
    "wof:placetype":"venue"
},
  "geometry": {"coordinates":[145.152175903,-37.8338699341],"type":"Point"}
}