{
  "type": "Feature",
  "properties": {
    "iso:country":"AU",
    "sg:address":"29b Thames St",
    "sg:city":"West Wollongong",
    "sg:classifiers":[
        {
            "category":"Personal",
            "subcategory":"Beauty Salon",
            "type":"Services"
        }
    ],
    "sg:phone":"+61 2 4228 7503",
    "sg:postcode":"2500",
    "sg:province":"NSW",
    "sg:tags":[
        "hairdresser"
    ],
    "wof:name":"Nella's Hair Studio",
    "wof:placetype":"venue"
},
  "geometry": {"coordinates":[150.863754,-34.432259],"type":"Point"}
}