{
  "type": "Feature",
  "properties": {
    "iso:country":"AU",
    "sg:address":"3 Marigold Pl",
    "sg:city":"Revesby",
    "sg:classifiers":[
        {
            "category":"Shopping",
            "subcategory":"Stationery & Office Supplies",
            "type":"Retail Goods"
        }
    ],
    "sg:phone":"+61 2 9771 9085",
    "sg:postcode":"2212",
    "sg:province":"NSW",
    "sg:tags":[
        "packaging",
        "material"
    ],
    "wof:name":"Paper Coaters Limited",
    "wof:placetype":"venue"
},
  "geometry": {"coordinates":[150.997787,-33.941208],"type":"Point"}
}