{
  "type": "Feature",
  "properties": {
    "addr:full":"Level 19, Pipe Networks House, 127 Creek St Brisbane QLD 4000",
    "addr:housenumber":"127",
    "addr:postcode":"4000",
    "addr:street":"Creek St",
    "iso:country":"AU",
    "sg:address":"Level 19, Pipe Networks House, 127 Creek St",
    "sg:city":"Brisbane",
    "sg:classifiers":[
        {
            "category":"Professional",
            "subcategory":"Employment Agencies",
            "type":"Services"
        }
    ],
    "sg:phone":"+61 1800 656 171",
    "sg:postcode":"4000",
    "sg:province":"QLD",
    "sg:tags":[
        "hire",
        "labour",
        "contractor"
    ],
    "wof:name":"Challenge Recruitment Ltd",
    "wof:placetype":"venue"
},
  "geometry": {"coordinates":[153.027709961,-27.4658489227],"type":"Point"}
}