{
  "type": "Feature",
  "properties": {
    "addr:full":"47 Parkside Ave Mt Pleasant WA 6153",
    "addr:housenumber":"47",
    "addr:postcode":"6153",
    "addr:street":"Parkside Ave",
    "iso:country":"AU",
    "sg:address":"47 Parkside Ave",
    "sg:city":"Mt Pleasant",
    "sg:classifiers":[
        {
            "category":"Wholesale",
            "subcategory":"Stationery",
            "type":"Manufacturing & Wholesale Goods"
        }
    ],
    "sg:phone":"+61 8 9316 4484",
    "sg:postcode":"6153",
    "sg:province":"WA",
    "sg:tags":[
        "mfrg"
    ],
    "wof:name":"Temax Pty Ltd",
    "wof:placetype":"venue"
},
  "geometry": {"coordinates":[115.849953,-32.039135],"type":"Point"}
}