{
  "type": "Feature",
  "properties": {
    "addr:full":"Diagonal Rd Glenelg East SA 5045",
    "addr:postcode":"5045",
    "addr:street":"Diagonal Rd",
    "iso:country":"AU",
    "sg:address":"Diagonal Rd",
    "sg:city":"Glenelg East",
    "sg:classifiers":[
        {
            "category":"Education",
            "subcategory":"School",
            "type":"Public Place"
        }
    ],
    "sg:phone":"+61 8 8295 3943",
    "sg:postcode":"5045",
    "sg:province":"SA",
    "sg:tags":[
        "state",
        "except",
        "nsw"
    ],
    "wof:name":"Glenelg Primary",
    "wof:placetype":"venue"
},
  "geometry": {"coordinates":[138.521896,-34.985561],"type":"Point"}
}