{
  "type": "Feature",
  "properties": {
    "addr:full":"74 Main St Alstonville NSW 2477",
    "addr:housenumber":"74",
    "addr:postcode":"2477",
    "addr:street":"Main St",
    "iso:country":"AU",
    "sg:address":"74 Main St",
    "sg:city":"Alstonville",
    "sg:classifiers":[
        {
            "category":"Food & Beverages",
            "subcategory":"Bakery",
            "type":"Retail Goods"
        }
    ],
    "sg:phone":"+61 2 6628 0239",
    "sg:postcode":"2477",
    "sg:province":"NSW",
    "sg:tags":[
        "baker"
    ],
    "wof:name":"Rads Bakery",
    "wof:placetype":"venue"
},
  "geometry": {"coordinates":[153.43595886200001,-28.8380317688],"type":"Point"}
}