{
  "type": "Feature",
  "properties": {
    "iso:country":"AU",
    "sg:address":"PO Box 1710",
    "sg:city":"Griffith",
    "sg:classifiers":[
        {
            "category":"Home & Garden",
            "subcategory":"Carpets & Floor Coverings",
            "type":"Retail Goods"
        }
    ],
    "sg:phone":"+61 413 256 166",
    "sg:postcode":"2680",
    "sg:province":"NSW",
    "sg:tags":[
        "tile",
        "wall",
        "layer"
    ],
    "wof:name":"Greg Hilton Tiling",
    "wof:placetype":"venue"
},
  "geometry": {"coordinates":[146.050323,-34.28944],"type":"Point"}
}