{
  "type": "Feature",
  "properties": {
    "iso:country":"AU",
    "sg:address":"5 Mount Joy St",
    "sg:city":"Woolloongabba",
    "sg:classifiers":[
        {
            "category":"Retail",
            "subcategory":"Auto Repair",
            "type":"Services"
        }
    ],
    "sg:phone":"+61 7 3891 6477",
    "sg:postcode":"4102",
    "sg:province":"QLD",
    "sg:tags":[
        "beater",
        "painter",
        "panel"
    ],
    "wof:name":"Lutzke R & A Paint & Panel",
    "wof:placetype":"venue"
},
  "geometry": {"coordinates":[153.042480469,-27.4916934967],"type":"Point"}
}