{
  "type": "Feature",
  "properties": {
    "addr:full":"69 Main St Lowood QLD 4311",
    "addr:housenumber":"69",
    "addr:postcode":"4311",
    "addr:street":"Main St",
    "iso:country":"AU",
    "sg:address":"69 Main St",
    "sg:city":"Lowood",
    "sg:classifiers":[
        {
            "category":"Real Estate",
            "subcategory":"Real Estate Agent",
            "type":"Services"
        }
    ],
    "sg:phone":"+61 7 5426 1999",
    "sg:postcode":"4311",
    "sg:province":"QLD",
    "wof:name":"Ray White Lowood",
    "wof:placetype":"venue"
},
  "geometry": {"coordinates":[152.58004760700001,-27.4649162292],"type":"Point"}
}