{
  "type": "Feature",
  "properties": {
    "addr:full":"108 High St Northcote VIC 3070",
    "addr:housenumber":"108",
    "addr:postcode":"3070",
    "addr:street":"High St",
    "iso:country":"AU",
    "sg:address":"108 High St",
    "sg:city":"Northcote",
    "sg:classifiers":[
        {
            "category":"Personal",
            "subcategory":"Beauty Salon",
            "type":"Services"
        }
    ],
    "sg:phone":"+61 3 9481 0219",
    "sg:postcode":"3070",
    "sg:province":"VIC",
    "wof:name":"4Me Beauty Therapy",
    "wof:placetype":"venue"
},
  "geometry": {"coordinates":[144.997146606,-37.7794876099],"type":"Point"}
}