{
  "type": "Feature",
  "properties": {
    "iso:country":"AU",
    "sg:address":"14a Verry St",
    "sg:city":"Mt Isa",
    "sg:classifiers":[
        {
            "category":"Building & Trades",
            "subcategory":"Landscaping Services",
            "type":"Services"
        }
    ],
    "sg:phone":"+61 7 4749 1106",
    "sg:postcode":"4825",
    "sg:province":"QLD",
    "sg:tags":[
        "grazier"
    ],
    "wof:name":"Lord J L & M A",
    "wof:placetype":"venue"
},
  "geometry": {"coordinates":[139.496216,-20.706806],"type":"Point"}
}