{
  "type": "Feature",
  "properties": {
    "addr:full":"88 Denison St Bondi Junction NSW 2022",
    "addr:housenumber":"88",
    "addr:postcode":"2022",
    "addr:street":"Denison St",
    "iso:country":"AU",
    "sg:address":"88 Denison St",
    "sg:city":"Bondi Junction",
    "sg:classifiers":[
        {
            "category":"Shopping",
            "subcategory":"Party Supplies",
            "type":"Retail Goods"
        }
    ],
    "sg:phone":"+61 2 9389 7385",
    "sg:postcode":"2022",
    "sg:province":"NSW",
    "sg:tags":[
        "children's"
    ],
    "sg:website":"http://www.therainbowfairies.com.au",
    "wof:name":"Good Fairies",
    "wof:placetype":"venue"
},
  "geometry": {"coordinates":[151.24468994099999,-33.8940200806],"type":"Point"}
}