{
  "type": "Feature",
  "properties": {
    "iso:country":"AU",
    "sg:address":"31 Bruce St",
    "sg:city":"Bexley",
    "sg:classifiers":[
        {
            "category":"Retail",
            "subcategory":"Driving School",
            "type":"Services"
        }
    ],
    "sg:phone":"+61 2 9587 0612",
    "sg:postcode":"2207",
    "sg:province":"NSW",
    "wof:name":"Willis George Driving School",
    "wof:placetype":"venue"
},
  "geometry": {"coordinates":[151.122665,-33.961056],"type":"Point"}
}