{
  "type": "Feature",
  "properties": {
    "addr:full":"567 Lutwyche Rd Lutwyche QLD 4030",
    "addr:housenumber":"567",
    "addr:postcode":"4030",
    "addr:street":"Lutwyche Rd",
    "iso:country":"AU",
    "sg:address":"567 Lutwyche Rd",
    "sg:city":"Lutwyche",
    "sg:classifiers":[
        {
            "category":"Banks & Credit Unions",
            "subcategory":"Financial Services",
            "type":"Services"
        }
    ],
    "sg:phone":"+61 7 3857 4881",
    "sg:postcode":"4030",
    "sg:province":"QLD",
    "sg:tags":[
        "loan",
        "finance",
        "mortgage"
    ],
    "wof:name":"RAMS Home Loans",
    "wof:placetype":"venue"
},
  "geometry": {"coordinates":[153.03431699999999,-27.420856],"type":"Point"}
}