{
  "type": "Feature",
  "properties": {
    "addr:full":"53- 63 Woombye Palmwoods Rd Woombye QLD 4559",
    "addr:housenumber":"63",
    "addr:postcode":"4559",
    "addr:street":"Woombye Palmwoods Rd",
    "iso:country":"AU",
    "sg:address":"53- 63 Woombye Palmwoods Rd",
    "sg:city":"Woombye",
    "sg:classifiers":[
        {
            "category":"Building & Trades",
            "subcategory":"Cleaning & Sanitation",
            "type":"Services"
        }
    ],
    "sg:phone":"+61 7 5457 3004",
    "sg:postcode":"4559",
    "sg:province":"QLD",
    "sg:tags":[
        "industrial",
        "commercial",
        "contractor"
    ],
    "wof:name":"Willow Services",
    "wof:placetype":"venue"
},
  "geometry": {"coordinates":[152.97373962399999,-26.6717205048],"type":"Point"}
}