{
  "type": "Feature",
  "properties": {
    "addr:full":"11 Brewer St Perth WA 6000",
    "addr:housenumber":"11",
    "addr:postcode":"6000",
    "addr:street":"Brewer St",
    "iso:country":"AU",
    "sg:address":"11 Brewer St",
    "sg:city":"Perth",
    "sg:classifiers":[
        {
            "category":"Professional",
            "subcategory":"Computer Services",
            "type":"Services"
        }
    ],
    "sg:phone":"+61 8 9328 1000",
    "sg:postcode":"6000",
    "sg:province":"WA",
    "sg:tags":[
        "repairs",
        "upgrade",
        "equipment"
    ],
    "wof:name":"Perfect Computer Solutions",
    "wof:placetype":"venue"
},
  "geometry": {"coordinates":[115.86823272700001,-31.9463291168],"type":"Point"}
}