{
  "type": "Feature",
  "properties": {
    "iso:country":"AU",
    "sg:address":"PO Box 9099",
    "sg:city":"Wyee",
    "sg:classifiers":[
        {
            "category":"Utilities",
            "subcategory":"Refuse",
            "type":"Services"
        }
    ],
    "sg:phone":"+61 2 4357 1306",
    "sg:postcode":"2259",
    "sg:province":"NSW",
    "sg:tags":[
        "remover",
        "rubbish"
    ],
    "wof:name":"Best Bin Hire",
    "wof:placetype":"venue"
},
  "geometry": {"coordinates":[151.48171997099999,-33.1759185791],"type":"Point"}
}