{
  "type": "Feature",
  "properties": {
    "addr:full":"Lvl 1, 333 Collins St Melbourne VIC 3000",
    "addr:housenumber":"333",
    "addr:postcode":"3000",
    "addr:street":"Collins St",
    "iso:country":"AU",
    "sg:address":"Lvl 1, 333 Collins St",
    "sg:city":"Melbourne",
    "sg:classifiers":[
        {
            "category":"Banks & Credit Unions",
            "subcategory":"Bank",
            "type":"Services"
        }
    ],
    "sg:phone":"+61 3 9629 9995",
    "sg:postcode":"3000",
    "sg:province":"VIC",
    "wof:name":"St.George Bank Limited Institutional and Financial Markets",
    "wof:placetype":"venue"
},
  "geometry": {"coordinates":[144.96321105999999,-37.8165855408],"type":"Point"}
}