{
  "type": "Feature",
  "properties": {
    "addr:full":"6 Hopkins St Greensborough VIC 3088",
    "addr:housenumber":"6",
    "addr:postcode":"3088",
    "addr:street":"Hopkins St",
    "iso:country":"AU",
    "sg:address":"6 Hopkins St",
    "sg:city":"Greensborough",
    "sg:classifiers":[
        {
            "category":"Building & Trades",
            "subcategory":"Plumbing",
            "type":"Services"
        }
    ],
    "sg:phone":"+61 413 128 991",
    "sg:postcode":"3088",
    "sg:province":"VIC",
    "sg:tags":[
        "plumber",
        "gasfitters"
    ],
    "wof:name":"Kett Plumbing Pty Ltd",
    "wof:placetype":"venue"
},
  "geometry": {"coordinates":[145.10682678200001,-37.7103118896],"type":"Point"}
}