{
  "type": "Feature",
  "properties": {
    "iso:country":"AU",
    "sg:address":"560 High St",
    "sg:city":"Epping",
    "sg:classifiers":[
        {
            "category":"Recreation",
            "type":"Entertainment"
        }
    ],
    "sg:phone":"+61 3 9401 3911",
    "sg:postcode":"3076",
    "sg:province":"VIC",
    "sg:tags":[
        "children's",
        "play",
        "programme"
    ],
    "wof:name":"Rug Rats Retreat",
    "wof:placetype":"venue"
},
  "geometry": {"coordinates":[145.00672912600001,-37.8537940979],"type":"Point"}
}