{
  "type": "Feature",
  "properties": {
    "iso:country":"AU",
    "sg:address":"75 Mayne St",
    "sg:city":"Murrurundi",
    "sg:classifiers":[
        {
            "category":"Real Estate",
            "subcategory":"Real Estate Agent",
            "type":"Services"
        }
    ],
    "sg:phone":"+61 2 6546 6149",
    "sg:postcode":"2338",
    "sg:province":"NSW",
    "wof:name":"Burraston H D Real Estate",
    "wof:placetype":"venue"
},
  "geometry": {"coordinates":[150.83758544899999,-31.7648391724],"type":"Point"}
}