{
  "type": "Feature",
  "properties": {
    "iso:country":"AU",
    "sg:address":"Coorparoo Kinesiology & Homeopathy Centre 12 Ferol St",
    "sg:city":"Coorparoo",
    "sg:classifiers":[
        {
            "category":"Health Services",
            "subcategory":"Health Practitioner",
            "type":"Services"
        }
    ],
    "sg:phone":"+61 7 3397 1898",
    "sg:postcode":"4151",
    "sg:province":"QLD",
    "sg:tags":[
        "homoeopath"
    ],
    "wof:name":"Demertzis Anna - Dip App Sc (Hom)",
    "wof:placetype":"venue"
},
  "geometry": {"coordinates":[153.07351684599999,-27.5122299194],"type":"Point"}
}