{
  "type": "Feature",
  "properties": {
    "addr:full":"37 Screw Creek La Inverloch VIC 3996",
    "addr:housenumber":"37",
    "addr:postcode":"3996",
    "addr:street":"Screw Creek La Inverloch",
    "iso:country":"AU",
    "sg:address":"37 Screw Creek La",
    "sg:city":"Inverloch",
    "sg:classifiers":[
        {
            "category":"Personal",
            "subcategory":"Massage",
            "type":"Services"
        }
    ],
    "sg:phone":"+61 3 5674 1322",
    "sg:postcode":"3996",
    "sg:province":"VIC",
    "sg:tags":[
        "therapy"
    ],
    "wof:name":"Carando Massage & Myotherapy",
    "wof:placetype":"venue"
},
  "geometry": {"coordinates":[145.77153000000001,-38.604477],"type":"Point"}
}