{
  "type": "Feature",
  "properties": {
    "addr:full":"Lot 72, Old Temora Rd Young NSW 2594",
    "addr:postcode":"2594",
    "addr:street":"Old Temora Rd",
    "iso:country":"AU",
    "sg:address":"Lot 72, Old Temora Rd",
    "sg:city":"Young",
    "sg:classifiers":[
        {
            "category":"Wholesale",
            "subcategory":"Metals & Minerals",
            "type":"Manufacturing & Wholesale Goods"
        }
    ],
    "sg:phone":"+61 2 6382 4049",
    "sg:postcode":"2594",
    "sg:province":"NSW",
    "sg:tags":[
        "steel",
        "merchant"
    ],
    "wof:name":"Smorgon Steel Distribution",
    "wof:placetype":"venue"
},
  "geometry": {"coordinates":[148.28135681099999,-34.3085136414],"type":"Point"}
}