{
  "type": "Feature",
  "properties": {
    "addr:full":"Lr Cairnbrook Rd Glengarry VIC 3854",
    "addr:postcode":"3854",
    "addr:street":"Cairnbrook Rd",
    "iso:country":"AU",
    "sg:address":"Lr Cairnbrook Rd",
    "sg:city":"Glengarry",
    "sg:classifiers":[
        {
            "category":"Building & Trades",
            "subcategory":"Landscaping Services",
            "type":"Services"
        }
    ],
    "sg:phone":"+61 3 5192 4287",
    "sg:postcode":"3854",
    "sg:province":"VIC",
    "sg:tags":[
        "grazier"
    ],
    "wof:name":"Morrison A K",
    "wof:placetype":"venue"
},
  "geometry": {"coordinates":[146.56704711899999,-38.1287498474],"type":"Point"}
}