{
  "type": "Feature",
  "properties": {
    "addr:full":"Hanger 13, Eleventh St Mascot NSW 2020",
    "addr:housenumber":"13",
    "addr:postcode":"2020",
    "addr:street":"Hanger;Eleventh St",
    "iso:country":"AU",
    "sg:address":"Hanger 13, Eleventh St",
    "sg:city":"Mascot",
    "sg:classifiers":[
        {
            "category":"Freight",
            "type":"Transportation"
        }
    ],
    "sg:phone":"+61 2 9700 9478",
    "sg:postcode":"2020",
    "sg:province":"NSW",
    "sg:tags":[
        "cargo",
        "air"
    ],
    "wof:name":"Virgin Blue Freight",
    "wof:placetype":"venue"
},
  "geometry": {"coordinates":[151.18670654300001,-33.9339103699],"type":"Point"}
}