{
  "type": "Feature",
  "properties": {
    "iso:country":"AU",
    "sg:address":"1 / 2898 Logan Rd",
    "sg:city":"Underwood",
    "sg:classifiers":[
        {
            "category":"Restaurant",
            "type":"Food & Drink"
        }
    ],
    "sg:phone":"+61 7 3841 3333",
    "sg:postcode":"4119",
    "sg:province":"QLD",
    "wof:name":"Antarctic Circle",
    "wof:placetype":"venue"
},
  "geometry": {"coordinates":[153.11575317399999,-27.6111469269],"type":"Point"}
}