{
  "type": "Feature",
  "properties": {
    "addr:full":"69 Third Ave Palm Beach QLD 4221",
    "addr:housenumber":"69",
    "addr:postcode":"4221",
    "addr:street":"Third Ave",
    "iso:country":"AU",
    "sg:address":"69 Third Ave",
    "sg:city":"Palm Beach",
    "sg:classifiers":[
        {
            "category":"Utilities",
            "subcategory":"Water",
            "type":"Services"
        }
    ],
    "sg:phone":"+61 7 5534 4769",
    "sg:postcode":"4221",
    "sg:province":"QLD",
    "sg:tags":[
        "equipment",
        "treatment"
    ],
    "wof:name":"Aqua Alert",
    "wof:placetype":"venue"
},
  "geometry": {"coordinates":[153.46774292000001,-28.1260509491],"type":"Point"}
}