{
  "type": "Feature",
  "properties": {
    "addr:full":"11 Stirling St Footscray VIC 3011",
    "addr:housenumber":"11",
    "addr:postcode":"3011",
    "addr:street":"Stirling St",
    "iso:country":"AU",
    "sg:address":"11 Stirling St",
    "sg:city":"Footscray",
    "sg:classifiers":[
        {
            "category":"Professional",
            "subcategory":"Management & Consulting",
            "type":"Services"
        }
    ],
    "sg:phone":"+61 3 9687 5682",
    "sg:postcode":"3011",
    "sg:province":"VIC",
    "sg:tags":[
        "consultant"
    ],
    "wof:name":"Berringer Management Services",
    "wof:placetype":"venue"
},
  "geometry": {"coordinates":[144.90492248499999,-37.7960395813],"type":"Point"}
}