{
  "type": "Feature",
  "properties": {
    "iso:country":"AU",
    "sg:address":"14a/ 1378 Gympie Rd",
    "sg:city":"Aspley",
    "sg:classifiers":[
        {
            "category":"Food & Beverages",
            "subcategory":"Liquor & Beverages",
            "type":"Retail Goods"
        }
    ],
    "sg:phone":"+61 7 3863 2833",
    "sg:postcode":"4034",
    "sg:province":"QLD",
    "sg:tags":[
        "store"
    ],
    "wof:name":"Vegas Liquor Aspley",
    "wof:placetype":"venue"
},
  "geometry": {"coordinates":[153.016907,-27.361893],"type":"Point"}
}