{
  "type": "Feature",
  "properties": {
    "iso:country":"AU",
    "sg:address":"257a Auburn St",
    "sg:city":"Goulburn",
    "sg:classifiers":[
        {
            "category":"Personal",
            "subcategory":"Beauty Salon",
            "type":"Services"
        }
    ],
    "sg:phone":"+61 2 4822 6856",
    "sg:postcode":"2580",
    "sg:province":"NSW",
    "sg:tags":[
        "hairdresser"
    ],
    "wof:name":"Goulburn's Barber Shop",
    "wof:placetype":"venue"
},
  "geometry": {"coordinates":[149.72151184099999,-34.7511558533],"type":"Point"}
}