{
  "type": "Feature",
  "properties": {
    "iso:country":"AU",
    "sg:address":"5 Lioyds Ave",
    "sg:city":"Carlingford",
    "sg:classifiers":[
        {
            "category":"Health Services",
            "subcategory":"Doctor",
            "type":"Services"
        }
    ],
    "sg:phone":"+61 2 9871 5884",
    "sg:postcode":"2118",
    "sg:province":"NSW",
    "sg:tags":[
        "medical",
        "practitioner"
    ],
    "wof:name":"Douglass Hanly Moir Pathology",
    "wof:placetype":"venue"
},
  "geometry": {"coordinates":[151.04698181099999,-33.7826576233],"type":"Point"}
}