{
  "type": "Feature",
  "properties": {
    "addr:full":"32A River Ave East Heybridge TAS 7316",
    "addr:housenumber":"32a",
    "addr:postcode":"7316",
    "addr:street":"River Ave East",
    "iso:country":"AU",
    "sg:address":"32A River Ave",
    "sg:city":"East Heybridge",
    "sg:classifiers":[
        {
            "category":"Building & Trades",
            "subcategory":"Construction",
            "type":"Services"
        }
    ],
    "sg:phone":"+61 419 155 521",
    "sg:postcode":"7316",
    "sg:province":"TAS",
    "sg:tags":[
        "welding"
    ],
    "wof:name":"Lehman Welding & Fabrication Pty Ltd",
    "wof:placetype":"venue"
},
  "geometry": {"coordinates":[145.990966797,-41.0769729614],"type":"Point"}
}