{
  "type": "Feature",
  "properties": {
    "iso:country":"AU",
    "sg:address":"137 Abbott Rd",
    "sg:city":"Hallam",
    "sg:classifiers":[
        {
            "category":"Home & Garden",
            "subcategory":"Building Materials",
            "type":"Retail Goods"
        }
    ],
    "sg:phone":"+61 3 9796 3922",
    "sg:postcode":"3803",
    "sg:province":"VIC",
    "sg:tags":[
        "shutter",
        "roller",
        "grille"
    ],
    "wof:name":"Arma Shutter",
    "wof:placetype":"venue"
},
  "geometry": {"coordinates":[145.25645446799999,-38.0077285767],"type":"Point"}
}