{
  "type": "Feature",
  "properties": {
    "addr:full":"297 Brighton Rd Somerton Park SA 5044",
    "addr:housenumber":"297",
    "addr:postcode":"5044",
    "addr:street":"Brighton Rd",
    "iso:country":"AU",
    "sg:address":"297 Brighton Rd",
    "sg:city":"Somerton Park",
    "sg:classifiers":[
        {
            "category":"Personal",
            "subcategory":"Beauty Salon",
            "type":"Services"
        }
    ],
    "sg:phone":"+61 8 8298 5555",
    "sg:postcode":"5044",
    "sg:province":"SA",
    "wof:name":"Skyes The Limit Hair Design",
    "wof:placetype":"venue"
},
  "geometry": {"coordinates":[138.52166700000001,-35.001793],"type":"Point"}
}