{
  "type": "Feature",
  "properties": {
    "iso:country":"AU",
    "sg:address":"119 Wren St",
    "sg:city":"Longreach",
    "sg:classifiers":[
        {
            "category":"Commercial Area",
            "type":"Public Place"
        }
    ],
    "sg:phone":"+61 7 4658 3517",
    "sg:postcode":"4730",
    "sg:province":"QLD",
    "sg:tags":[
        "heavy",
        "carrier"
    ],
    "wof:name":"Wyton R H & J L",
    "wof:placetype":"venue"
},
  "geometry": {"coordinates":[144.243256,-23.438869],"type":"Point"}
}