{
  "type": "Feature",
  "properties": {
    "addr:full":"28a Queen St Fremantle WA 6160",
    "addr:housenumber":"28a",
    "addr:postcode":"6160",
    "addr:street":"Queen St",
    "iso:country":"AU",
    "sg:address":"28a Queen St",
    "sg:city":"Fremantle",
    "sg:classifiers":[
        {
            "category":"Arts & Performance",
            "subcategory":"Art Gallery",
            "type":"Entertainment"
        }
    ],
    "sg:phone":"+61 8 9336 6972",
    "sg:postcode":"6160",
    "sg:province":"WA",
    "wof:name":"Urban Dingo Gallery",
    "wof:placetype":"venue"
},
  "geometry": {"coordinates":[115.74894,-32.05341],"type":"Point"}
}