{
  "type": "Feature",
  "properties": {
    "addr:full":"20 Fairlawn Rd Busselton WA 6280",
    "addr:housenumber":"20",
    "addr:postcode":"6280",
    "addr:street":"Fairlawn Rd",
    "iso:country":"AU",
    "sg:address":"20 Fairlawn Rd",
    "sg:city":"Busselton",
    "sg:classifiers":[
        {
            "category":"Home & Garden",
            "subcategory":"Building Materials",
            "type":"Retail Goods"
        }
    ],
    "sg:phone":"+61 8 9751 5544",
    "sg:postcode":"6280",
    "sg:province":"WA",
    "sg:tags":[
        "secondhand"
    ],
    "wof:name":"Direct Demolition & Salvage",
    "wof:placetype":"venue"
},
  "geometry": {"coordinates":[115.345741272,-33.6632804871],"type":"Point"}
}