{
  "type": "Feature",
  "properties": {
    "iso:country":"AU",
    "sg:address":"Retail SA Building, 60 Halifax St",
    "sg:city":"Adelaide",
    "sg:classifiers":[
        {
            "category":"Education",
            "subcategory":"Music School",
            "type":"Public Place"
        }
    ],
    "sg:phone":"+61 8 8359 3111",
    "sg:postcode":"5000",
    "sg:province":"SA",
    "sg:tags":[
        "television",
        "radio"
    ],
    "wof:name":"Vaughan Harvey Radio School",
    "wof:placetype":"venue"
},
  "geometry": {"coordinates":[138.602584839,-34.9325752258],"type":"Point"}
}