{
  "type": "Feature",
  "properties": {
    "addr:full":"PO Box 101 Denman NSW 2328",
    "addr:postcode":"2328",
    "iso:country":"AU",
    "sg:address":"PO Box 101",
    "sg:city":"Denman",
    "sg:classifiers":[
        {
            "category":"Banks & Credit Unions",
            "subcategory":"Atm",
            "type":"Services"
        }
    ],
    "sg:phone":"+61 2 6547 4428",
    "sg:postcode":"2328",
    "sg:province":"NSW",
    "sg:tags":[
        "control",
        "soil",
        "erosion",
        "stabilisation"
    ],
    "wof:name":"Dustex",
    "wof:placetype":"venue"
},
  "geometry": {"coordinates":[150.68443298299999,-32.3875198364],"type":"Point"}
}