{
  "type": "Feature",
  "properties": {
    "addr:full":"Oxley Hwy Warren NSW 2824",
    "addr:postcode":"2824",
    "addr:street":"Oxley Hwy",
    "iso:country":"AU",
    "sg:address":"Oxley Hwy",
    "sg:city":"Warren",
    "sg:classifiers":[
        {
            "category":"Manufacturing",
            "subcategory":"Textiles",
            "type":"Manufacturing & Wholesale Goods"
        }
    ],
    "sg:phone":"+61 2 6883 7306",
    "sg:postcode":"2824",
    "sg:province":"NSW",
    "sg:tags":[
        "cotton"
    ],
    "wof:name":"Auscott Limited",
    "wof:placetype":"venue"
},
  "geometry": {"coordinates":[147.835662842,-31.7004318237],"type":"Point"}
}