{
  "type": "Feature",
  "properties": {
    "iso:country":"AU",
    "sg:address":"141 Macquarie Rd",
    "sg:city":"Springwood",
    "sg:classifiers":[
        {
            "category":"Organizations",
            "subcategory":"Non-profit Organization",
            "type":"Services"
        }
    ],
    "sg:phone":"+61 2 4751 7911",
    "sg:postcode":"2777",
    "sg:province":"NSW",
    "sg:tags":[
        "support",
        "disability",
        "organisation"
    ],
    "wof:name":"Break Thru Personnel",
    "wof:placetype":"venue"
},
  "geometry": {"coordinates":[150.56695556599999,-33.6988868713],"type":"Point"}
}