{
  "type": "Feature",
  "properties": {
    "iso:country":"AU",
    "sg:address":"PO Box 82",
    "sg:city":"Morphett Vale",
    "sg:classifiers":[
        {
            "category":"Professional",
            "subcategory":"Employment Agencies",
            "type":"Services"
        }
    ],
    "sg:phone":"+61 8 8326 1212",
    "sg:postcode":"5162",
    "sg:province":"SA",
    "sg:tags":[
        "entertainer",
        "agent"
    ],
    "wof:name":"Bandit Entertainment",
    "wof:placetype":"venue"
},
  "geometry": {"coordinates":[138.52442932100001,-35.1262016296],"type":"Point"}
}