{
  "type": "Feature",
  "properties": {
    "addr:full":"PO Box 93 Curtin ACT 2605",
    "addr:postcode":"2605",
    "iso:country":"AU",
    "sg:address":"PO Box 93",
    "sg:city":"Curtin",
    "sg:classifiers":[
        {
            "category":"Organizations",
            "subcategory":"Membership Organization",
            "type":"Services"
        }
    ],
    "sg:phone":"+61 2 6287 4567",
    "sg:postcode":"2605",
    "sg:province":"ACT",
    "sg:tags":[
        "support",
        "health",
        "organisation"
    ],
    "wof:name":"O2C Solutions",
    "wof:placetype":"venue"
},
  "geometry": {"coordinates":[149.081298828,-35.3241615295],"type":"Point"}
}