{
  "type": "Feature",
  "properties": {
    "addr:full":"Market Pl Bothwell TAS 7030",
    "addr:postcode":"7030",
    "addr:street":"Market Pl",
    "iso:country":"AU",
    "sg:address":"Market Pl",
    "sg:city":"Bothwell",
    "sg:classifiers":[
        {
            "category":"Museum",
            "type":"Entertainment"
        }
    ],
    "sg:phone":"+61 3 6259 4033",
    "sg:postcode":"7030",
    "sg:province":"TAS",
    "wof:name":"Australasian Golf Museum",
    "wof:placetype":"venue"
},
  "geometry": {"coordinates":[147.00784301799999,-42.3835601807],"type":"Point"}
}