{
  "type": "Feature",
  "properties": {
    "addr:full":"423 Nepean Hwy Chelsea VIC 3196",
    "addr:housenumber":"423",
    "addr:postcode":"3196",
    "addr:street":"Nepean Hwy",
    "iso:country":"AU",
    "sg:address":"423 Nepean Hwy",
    "sg:city":"Chelsea",
    "sg:classifiers":[
        {
            "category":"Real Estate",
            "subcategory":"Real Estate Agent",
            "type":"Services"
        }
    ],
    "sg:phone":"+61 3 9772 7077",
    "sg:postcode":"3196",
    "sg:province":"VIC",
    "wof:name":"MPRE Harcourts",
    "wof:placetype":"venue"
},
  "geometry": {"coordinates":[145.116622925,-38.054058075],"type":"Point"}
}