{
  "type": "Feature",
  "properties": {
    "iso:country":"AU",
    "sg:address":"2 Alfonso St",
    "sg:city":"North Perth",
    "sg:classifiers":[
        {
            "category":"Social Services",
            "subcategory":"Retirement Home",
            "type":"Services"
        }
    ],
    "sg:phone":"+61 8 9337 0139",
    "sg:postcode":"6006",
    "sg:province":"WA",
    "sg:tags":[
        "village"
    ],
    "wof:name":"BF Prindivile Village",
    "wof:placetype":"venue"
},
  "geometry": {"coordinates":[115.85353088399999,-31.9362621307],"type":"Point"}
}