{
  "type": "Feature",
  "properties": {
    "iso:country":"AU",
    "sg:address":"Murray St",
    "sg:city":"Tocumwal",
    "sg:classifiers":[
        {
            "category":"Cafe",
            "type":"Food & Drink"
        }
    ],
    "sg:phone":"+61 3 5874 3173",
    "sg:postcode":"2714",
    "sg:province":"NSW",
    "wof:name":"Murray River Walk Cafe",
    "wof:placetype":"venue"
},
  "geometry": {"coordinates":[145.56466674800001,-35.8097076416],"type":"Point"}
}