{
  "type": "Feature",
  "properties": {
    "addr:full":"19 Timberland Pl Loganholme QLD 4129",
    "addr:housenumber":"19",
    "addr:postcode":"4129",
    "addr:street":"Timberland Pl",
    "iso:country":"AU",
    "sg:address":"19 Timberland Pl",
    "sg:city":"Loganholme",
    "sg:classifiers":[
        {
            "category":"Communications",
            "type":"Services"
        }
    ],
    "sg:phone":"+61 415 340 363",
    "sg:postcode":"4129",
    "sg:province":"QLD",
    "sg:tags":[
        "antenna"
    ],
    "wof:name":"Ozi Antennas & Satellites",
    "wof:placetype":"venue"
},
  "geometry": {"coordinates":[153.18316650400001,-27.6946048737],"type":"Point"}
}