{
  "type": "Feature",
  "properties": {
    "addr:full":"PO Box 494 Dromana VIC 3936",
    "addr:postcode":"3936",
    "iso:country":"AU",
    "sg:address":"PO Box 494",
    "sg:city":"Dromana",
    "sg:classifiers":[
        {
            "category":"Building & Trades",
            "subcategory":"Cleaning & Sanitation",
            "type":"Services"
        }
    ],
    "sg:phone":"+61 411 380 056",
    "sg:postcode":"3936",
    "sg:province":"VIC",
    "sg:tags":[
        "tank",
        "septic"
    ],
    "wof:name":"Blow Fly Septic Pumping",
    "wof:placetype":"venue"
},
  "geometry": {"coordinates":[144.964447022,-38.3328781128],"type":"Point"}
}