{
  "type": "Feature",
  "properties": {
    "iso:country":"AU",
    "sg:address":"3/ 11 Melbourne St",
    "sg:city":"Rocklea",
    "sg:classifiers":[
        {
            "category":"Food & Beverages",
            "subcategory":"Fruits & Vegetables",
            "type":"Retail Goods"
        }
    ],
    "sg:phone":"+61 7 3892 2552",
    "sg:postcode":"4106",
    "sg:province":"QLD",
    "sg:tags":[
        "greengrocer",
        "fruiterer"
    ],
    "wof:name":"Grocer-ease",
    "wof:placetype":"venue"
},
  "geometry": {"coordinates":[153.008575439,-27.5406341553],"type":"Point"}
}