{
  "type": "Feature",
  "properties": {
    "addr:full":"2/ 16 McDougall Rd Sunbury VIC 3429",
    "addr:housenumber":"/ 16",
    "addr:postcode":"3429",
    "addr:street":"Mcdougall Rd",
    "iso:country":"AU",
    "sg:address":"2/ 16 McDougall Rd",
    "sg:city":"Sunbury",
    "sg:classifiers":[
        {
            "category":"Government",
            "subcategory":"Fire Station",
            "type":"Public Place"
        }
    ],
    "sg:phone":"+61 3 9744 4899",
    "sg:postcode":"3429",
    "sg:province":"VIC",
    "sg:tags":[
        "equipment",
        "protection",
        "consultant"
    ],
    "wof:name":"Altaire Servicing Pty Ltd",
    "wof:placetype":"venue"
},
  "geometry": {"coordinates":[144.71759033199999,-37.589553833],"type":"Point"}
}