{
  "type": "Feature",
  "properties": {
    "iso:country":"AU",
    "sg:address":"4/ 31 Premier St",
    "sg:city":"Gymea",
    "sg:classifiers":[
        {
            "category":"Professional",
            "subcategory":"Computer Services",
            "type":"Services"
        }
    ],
    "sg:phone":"+61 2 9592 2883",
    "sg:postcode":"2227",
    "sg:province":"NSW",
    "sg:tags":[
        "repairs",
        "upgrade",
        "equipment"
    ],
    "wof:name":"Chilli Power Computing",
    "wof:placetype":"venue"
},
  "geometry": {"coordinates":[151.086761475,-34.0375213623],"type":"Point"}
}