{
  "type": "Feature",
  "properties": {
    "iso:country":"AU",
    "sg:address":"162 Nicholson St",
    "sg:city":"Abbotsford",
    "sg:classifiers":[
        {
            "category":"Building & Trades",
            "subcategory":"Plumbing",
            "type":"Services"
        }
    ],
    "sg:phone":"+61 3 9419 2833",
    "sg:postcode":"3067",
    "sg:province":"VIC",
    "sg:tags":[
        "plumber",
        "gasfitters"
    ],
    "wof:name":"C B S Plumbing",
    "wof:placetype":"venue"
},
  "geometry": {"coordinates":[144.997192383,-37.8036994934],"type":"Point"}
}