{
  "type": "Feature",
  "properties": {
    "addr:full":"Unit 5 157 Bussell Hwy Margaret River WA 6285",
    "addr:housenumber":"157",
    "addr:postcode":"6285",
    "addr:street":"Bussell Hwy",
    "iso:country":"AU",
    "sg:address":"Unit 5 157 Bussell Hwy",
    "sg:city":"Margaret River",
    "sg:classifiers":[
        {
            "category":"Education",
            "subcategory":"Special Training",
            "type":"Public Place"
        }
    ],
    "sg:phone":"+61 8 9757 2778",
    "sg:postcode":"6285",
    "sg:province":"WA",
    "sg:tags":[
        "tuition-educational"
    ],
    "wof:name":"Kip McGrath Education Centre",
    "wof:placetype":"venue"
},
  "geometry": {"coordinates":[115.07460021999999,-33.9476737976],"type":"Point"}
}