{
  "type": "Feature",
  "properties": {
    "addr:full":"3 Whitegum Pl Kellyville NSW 2153",
    "addr:housenumber":"3",
    "addr:postcode":"2153",
    "addr:street":"Whitegum Pl",
    "iso:country":"AU",
    "sg:address":"3 Whitegum Pl",
    "sg:city":"Kellyville",
    "sg:classifiers":[
        {
            "category":"Shopping",
            "subcategory":"Bicycles & Sporting Goods",
            "type":"Retail Goods"
        }
    ],
    "sg:phone":"+61 2 8824 6411",
    "sg:postcode":"2153",
    "sg:province":"NSW",
    "sg:tags":[
        "chemical",
        "equipment",
        "pool",
        "swimming"
    ],
    "wof:name":"Sunflow Pool Products Pty Ltd",
    "wof:placetype":"venue"
},
  "geometry": {"coordinates":[150.97642517099999,-33.7541503906],"type":"Point"}
}