{
  "type": "Feature",
  "properties": {
    "addr:full":"130a Eagle St Longreach QLD 4730",
    "addr:housenumber":"130a",
    "addr:postcode":"4730",
    "addr:street":"Eagle St",
    "iso:country":"AU",
    "sg:address":"130a Eagle St",
    "sg:city":"Longreach",
    "sg:classifiers":[
        {
            "category":"Personal",
            "subcategory":"Beauty Salon",
            "type":"Services"
        }
    ],
    "sg:phone":"+61 7 4658 3155",
    "sg:postcode":"4730",
    "sg:province":"QLD",
    "sg:tags":[
        "hairdresser"
    ],
    "wof:name":"The Incrowd",
    "wof:placetype":"venue"
},
  "geometry": {"coordinates":[144.24792500000001,-23.443708],"type":"Point"}
}