{
  "type": "Feature",
  "properties": {
    "addr:full":"30/145 Chelsea Vlge Stirling Hwy Nedlands WA 6009",
    "addr:housenumber":"30 / 145",
    "addr:postcode":"6009",
    "addr:street":"Chelsea Vlge Stirling Hwy",
    "iso:country":"AU",
    "sg:address":"30/145 Chelsea Vlge Stirling Hwy",
    "sg:city":"Nedlands",
    "sg:classifiers":[
        {
            "category":"Utilities",
            "subcategory":"Refuse",
            "type":"Services"
        }
    ],
    "sg:phone":"+61 8 9386 8634",
    "sg:postcode":"6009",
    "sg:province":"WA",
    "sg:tags":[
        "wholesale",
        "glassware",
        "china",
        "earthenware"
    ],
    "wof:name":"Waterford Wedgwood Australia Ltd",
    "wof:placetype":"venue"
},
  "geometry": {"coordinates":[115.806068,-31.978691],"type":"Point"}
}