{
  "type": "Feature",
  "properties": {
    "addr:full":"14 Clennam Ave Ambarvale NSW 2560",
    "addr:housenumber":"14",
    "addr:postcode":"2560",
    "addr:street":"Clennam Ave",
    "iso:country":"AU",
    "sg:address":"14 Clennam Ave",
    "sg:city":"Ambarvale",
    "sg:classifiers":[
        {
            "category":"Personal",
            "type":"Services"
        }
    ],
    "sg:phone":"+61 401 027 089",
    "sg:postcode":"2560",
    "sg:province":"NSW",
    "sg:tags":[
        "dressmaker"
    ],
    "wof:name":"Svetlana",
    "wof:placetype":"venue"
},
  "geometry": {"coordinates":[150.79188537600001,-34.0856819153],"type":"Point"}
}