{
  "type": "Feature",
  "properties": {
    "addr:full":"U20/ 25 Parramatta Rd Underwood QLD 4119",
    "addr:housenumber":"25",
    "addr:postcode":"4119",
    "addr:street":"/;Parramatta Rd",
    "iso:country":"AU",
    "sg:address":"U20/ 25 Parramatta Rd",
    "sg:city":"Underwood",
    "sg:classifiers":[
        {
            "category":"Shopping",
            "subcategory":"Stationery & Office Supplies",
            "type":"Retail Goods"
        }
    ],
    "sg:phone":"+61 7 3386 0188",
    "sg:postcode":"4119",
    "sg:province":"QLD",
    "sg:tags":[
        "equipment",
        "badge",
        "making"
    ],
    "wof:name":"Expertex Embroidery Service",
    "wof:placetype":"venue"
},
  "geometry": {"coordinates":[153.11659240700001,-27.6147289276],"type":"Point"}
}