{
  "type": "Feature",
  "properties": {
    "iso:country":"AU",
    "sg:address":"812 Forrest Rd",
    "sg:city":"Jandakot",
    "sg:classifiers":[
        {
            "category":"Autos & Motor Vehicles",
            "subcategory":"Fuel & Gas Station",
            "type":"Retail Goods"
        }
    ],
    "sg:phone":"+61 8 9417 9571",
    "sg:postcode":"6164",
    "sg:province":"WA",
    "wof:name":"Gull Petroleum (WA) Pty Ltd",
    "wof:placetype":"venue"
},
  "geometry": {"coordinates":[115.813759,-32.090256],"type":"Point"}
}