{
  "type": "Feature",
  "properties": {
    "iso:country":"AU",
    "sg:address":"162 Blackall Range Rd",
    "sg:city":"Woombye",
    "sg:classifiers":[
        {
            "category":"Wholesale",
            "subcategory":"Construction Materials",
            "type":"Manufacturing & Wholesale Goods"
        }
    ],
    "sg:phone":"+61 7 5442 1466",
    "sg:postcode":"4559",
    "sg:province":"QLD",
    "sg:tags":[
        "protective",
        "coating"
    ],
    "wof:name":"Armour Linings",
    "wof:placetype":"venue"
},
  "geometry": {"coordinates":[152.948654175,-26.6583824158],"type":"Point"}
}