{
  "type": "Feature",
  "properties": {
    "iso:country":"AU",
    "sg:address":"2392 Ballarto Rd",
    "sg:city":"Cardinia",
    "sg:classifiers":[
        {
            "category":"Retail",
            "subcategory":"Auto Repair",
            "type":"Services"
        }
    ],
    "sg:phone":"+61 417 884 601",
    "sg:postcode":"3978",
    "sg:province":"VIC",
    "sg:tags":[
        "electrical"
    ],
    "wof:name":"Franzini Auto Electrics",
    "wof:placetype":"venue"
},
  "geometry": {"coordinates":[145.42359924300001,-38.1460914612],"type":"Point"}
}