{
  "type": "Feature",
  "properties": {
    "addr:full":"Camp Rd Anglesea VIC 3230",
    "addr:postcode":"3230",
    "addr:street":"Camp Rd",
    "iso:country":"AU",
    "sg:address":"Camp Rd",
    "sg:city":"Anglesea",
    "sg:classifiers":[
        {
            "category":"Education",
            "subcategory":"School",
            "type":"Public Place"
        }
    ],
    "sg:phone":"+61 3 5263 1231",
    "sg:postcode":"3230",
    "sg:province":"VIC",
    "sg:tags":[
        "state",
        "except",
        "nsw"
    ],
    "wof:name":"Anglesea Primary School",
    "wof:placetype":"venue"
},
  "geometry": {"coordinates":[144.188828,-38.405075],"type":"Point"}
}