{
  "type": "Feature",
  "properties": {
    "iso:country":"AU",
    "sg:address":"1 Norring St",
    "sg:city":"Cooloongup",
    "sg:classifiers":[
        {
            "category":"Education",
            "subcategory":"Kindergarten",
            "type":"Public Place"
        }
    ],
    "sg:phone":"+61 8 9528 1796",
    "sg:postcode":"6168",
    "sg:province":"WA",
    "sg:tags":[
        "pre-schools"
    ],
    "wof:name":"Waikiki Play School",
    "wof:placetype":"venue"
},
  "geometry": {"coordinates":[115.75108299999999,-32.304001],"type":"Point"}
}