{
  "type": "Feature",
  "properties": {
    "iso:country":"AU",
    "sg:address":"Shp 1/ 32 Mullumbimbi St",
    "sg:city":"Brunswick Heads",
    "sg:classifiers":[
        {
            "category":"Arts & Performance",
            "subcategory":"Art Gallery",
            "type":"Entertainment"
        }
    ],
    "sg:phone":"+61 2 6685 0229",
    "sg:postcode":"2483",
    "sg:province":"NSW",
    "wof:name":"Mina Mina Art Gallery",
    "wof:placetype":"venue"
},
  "geometry": {"coordinates":[153.550338745,-28.5393314362],"type":"Point"}
}