{
  "type": "Feature",
  "properties": {
    "addr:full":"7 Arthur St Eltham VIC 3095",
    "addr:housenumber":"7",
    "addr:postcode":"3095",
    "addr:street":"Arthur St",
    "iso:country":"AU",
    "sg:address":"7 Arthur St",
    "sg:city":"Eltham",
    "sg:classifiers":[
        {
            "category":"Food & Beverages",
            "subcategory":"Supermarket",
            "type":"Retail Goods"
        }
    ],
    "sg:phone":"+61 3 9439 9438",
    "sg:postcode":"3095",
    "sg:province":"VIC",
    "sg:tags":[
        "grocery",
        "store"
    ],
    "wof:name":"Safeway",
    "wof:placetype":"venue"
},
  "geometry": {"coordinates":[145.14869689899999,-37.7142181396],"type":"Point"}
}