{
  "type": "Feature",
  "properties": {
    "iso:country":"AU",
    "sg:address":"61- 71",
    "sg:city":"Old Coach Way Yandina",
    "sg:classifiers":[
        {
            "category":"Building & Trades",
            "subcategory":"Construction",
            "type":"Services"
        }
    ],
    "sg:phone":"+61 419 719 905",
    "sg:postcode":"4561",
    "sg:province":"QLD",
    "sg:tags":[
        "contractor"
    ],
    "wof:name":"Tyson Peter",
    "wof:placetype":"venue"
},
  "geometry": {"coordinates":[152.970535278,-26.535238266],"type":"Point"}
}