{
  "type": "Feature",
  "properties": {
    "addr:full":"264 Centre Rd Bentleigh VIC 3204",
    "addr:housenumber":"264",
    "addr:postcode":"3204",
    "addr:street":"Centre Rd",
    "iso:country":"AU",
    "sg:address":"264 Centre Rd",
    "sg:city":"Bentleigh",
    "sg:classifiers":[
        {
            "category":"Manufacturing",
            "subcategory":"Food",
            "type":"Manufacturing & Wholesale Goods"
        }
    ],
    "sg:phone":"+61 3 9557 1635",
    "sg:postcode":"3204",
    "sg:province":"VIC",
    "sg:tags":[
        "function",
        "catering"
    ],
    "wof:name":"Catering By Kate",
    "wof:placetype":"venue"
},
  "geometry": {"coordinates":[145.031204,-37.917683],"type":"Point"}
}