{
  "type": "Feature",
  "properties": {
    "iso:country":"AU",
    "sg:address":"333 Smith St",
    "sg:city":"Fitzroy",
    "sg:classifiers":[
        {
            "category":"Travel",
            "subcategory":"Hotels & Motels",
            "type":"Entertainment"
        }
    ],
    "sg:phone":"+61 3 9417 2706",
    "sg:postcode":"3065",
    "sg:province":"VIC",
    "sg:tags":[
        "accommodation"
    ],
    "wof:name":"Birmingham Hotel",
    "wof:placetype":"venue"
},
  "geometry": {"coordinates":[144.98406982399999,-37.7990837097],"type":"Point"}
}