{
  "type": "Feature",
  "properties": {
    "addr:full":"24 Barnet Rd Evanston SA 5116",
    "addr:housenumber":"24",
    "addr:postcode":"5116",
    "addr:street":"Barnet Rd",
    "iso:country":"AU",
    "sg:address":"24 Barnet Rd",
    "sg:city":"Evanston",
    "sg:classifiers":[
        {
            "category":"Shopping",
            "subcategory":"Computers & Home Electronics",
            "type":"Retail Goods"
        }
    ],
    "sg:phone":"+61 8 8523 3811",
    "sg:postcode":"5116",
    "sg:province":"SA",
    "sg:tags":[
        "hardware",
        "equipment"
    ],
    "wof:name":"UR Computing",
    "wof:placetype":"venue"
},
  "geometry": {"coordinates":[138.737518311,-34.6080780029],"type":"Point"}
}