{
  "type": "Feature",
  "properties": {
    "iso:country":"AU",
    "sg:address":"2/ 12 Jillian Ave",
    "sg:city":"Highett",
    "sg:classifiers":[
        {
            "category":"Professional",
            "subcategory":"Testing Lab",
            "type":"Services"
        }
    ],
    "sg:phone":"+61 3 5971 3484",
    "sg:postcode":"3190",
    "sg:province":"VIC",
    "sg:tags":[
        "inspection"
    ],
    "wof:name":"Tag Right Australia",
    "wof:placetype":"venue"
},
  "geometry": {"coordinates":[145.023803711,-37.9476737976],"type":"Point"}
}