{
  "type": "Feature",
  "properties": {
    "iso:country":"AU",
    "sg:address":"277 Maroondah Hwy",
    "sg:city":"Croydon",
    "sg:classifiers":[
        {
            "category":"Home & Garden",
            "subcategory":"Building Materials",
            "type":"Retail Goods"
        }
    ],
    "sg:phone":"+61 425 830 221",
    "sg:postcode":"3136",
    "sg:province":"VIC",
    "sg:tags":[
        "merchant",
        "glass",
        "glazier"
    ],
    "wof:name":"Custom Shower Screens & Splashbacks",
    "wof:placetype":"venue"
},
  "geometry": {"coordinates":[145.28463745100001,-37.7821922302],"type":"Point"}
}