{
  "type": "Feature",
  "properties": {
    "addr:full":"3rd Flr/42-44 Parliament Pl West Perth WA 6005",
    "addr:housenumber":"/ 42-44",
    "addr:postcode":"6005",
    "addr:street":"Parliament Pl",
    "iso:country":"AU",
    "sg:address":"3rd Flr/42-44 Parliament Pl",
    "sg:city":"West Perth",
    "sg:classifiers":[
        {
            "category":"Metro Station",
            "type":"Transportation"
        }
    ],
    "sg:phone":"+61 8 9226 2855",
    "sg:postcode":"6005",
    "sg:province":"WA",
    "sg:tags":[
        "consultant",
        "marine"
    ],
    "wof:name":"Falconer Bryan Australia Pty Ltd",
    "wof:placetype":"venue"
},
  "geometry": {"coordinates":[115.846458435,-31.9512119293],"type":"Point"}
}