{
  "type": "Feature",
  "properties": {
    "iso:country":"AU",
    "sg:address":"13 Cashmere Crt",
    "sg:city":"Wyndham Vale",
    "sg:classifiers":[
        {
            "category":"Professional",
            "subcategory":"Computer Services",
            "type":"Services"
        }
    ],
    "sg:phone":"+61 3 9734 2466",
    "sg:postcode":"3024",
    "sg:province":"VIC",
    "sg:tags":[
        "consultant",
        "system"
    ],
    "wof:name":"Dazco Technology",
    "wof:placetype":"venue"
},
  "geometry": {"coordinates":[144.63005100000001,-37.887104],"type":"Point"}
}