{
  "type": "Feature",
  "properties": {
    "addr:full":"5 Gibbens Rd Gosford West NSW 2250",
    "addr:housenumber":"5",
    "addr:postcode":"2250",
    "addr:street":"Gibbens Rd",
    "iso:country":"AU",
    "sg:address":"5 Gibbens Rd",
    "sg:city":"Gosford West",
    "sg:classifiers":[
        {
            "category":"Retail",
            "subcategory":"Auto Repair",
            "type":"Services"
        }
    ],
    "sg:phone":"+61 2 4325 1552",
    "sg:postcode":"2250",
    "sg:province":"NSW",
    "sg:tags":[
        "bus",
        "truck"
    ],
    "wof:name":"All Coast Body Works Pty Ltd",
    "wof:placetype":"venue"
},
  "geometry": {"coordinates":[151.323654175,-33.4152107239],"type":"Point"}
}