{
  "type": "Feature",
  "properties": {
    "addr:full":"Cnr Berwick St & Canning Hwy South Perth WA 6151",
    "addr:postcode":"6151",
    "addr:street":"Cnr Berwick St & Canning Hwy South",
    "iso:country":"AU",
    "sg:address":"Cnr Berwick St & Canning Hwy",
    "sg:city":"South Perth",
    "sg:classifiers":[
        {
            "category":"Fast Food",
            "type":"Food & Drink"
        }
    ],
    "sg:phone":"+61 8 9474 4988",
    "sg:postcode":"6151",
    "sg:province":"WA",
    "sg:tags":[
        "away",
        "take"
    ],
    "wof:name":"McDonald's Family Restaurants",
    "wof:placetype":"venue"
},
  "geometry": {"coordinates":[115.883308,-31.974188],"type":"Point"}
}