{
  "type": "Feature",
  "properties": {
    "addr:full":"Bronzewing Ave Ellenbrook WA 6069",
    "addr:postcode":"6069",
    "addr:street":"Bronzewing Ave",
    "iso:country":"AU",
    "sg:address":"Bronzewing Ave",
    "sg:city":"Ellenbrook",
    "sg:classifiers":[
        {
            "category":"Building & Trades",
            "subcategory":"Construction",
            "type":"Services"
        }
    ],
    "sg:phone":"+61 8 9296 9002",
    "sg:postcode":"6069",
    "sg:province":"WA",
    "sg:tags":[
        "contractor"
    ],
    "wof:name":"Dale Alcock Homes Pty Ltd",
    "wof:placetype":"venue"
},
  "geometry": {"coordinates":[115.971069336,-31.7895927429],"type":"Point"}
}