{
  "type": "Feature",
  "properties": {
    "addr:full":"111 Gardens Drv Willawong QLD 4110",
    "addr:housenumber":"111",
    "addr:postcode":"4110",
    "addr:street":"Gardens Drv",
    "iso:country":"AU",
    "sg:address":"111 Gardens Drv",
    "sg:city":"Willawong",
    "sg:classifiers":[
        {
            "category":"Shopping",
            "subcategory":"Gifts & Souvenirs",
            "type":"Retail Goods"
        }
    ],
    "sg:phone":"+61 7 3272 3688",
    "sg:postcode":"4110",
    "sg:province":"QLD",
    "sg:tags":[
        "shop",
        "supply"
    ],
    "wof:name":"Aup Australia Pty Ltd",
    "wof:placetype":"venue"
},
  "geometry": {"coordinates":[153.02865600600001,-27.6062240601],"type":"Point"}
}