{
  "type": "Feature",
  "properties": {
    "iso:country":"AU",
    "sg:address":"Unit1 7A Fletcher St",
    "sg:city":"Wallsend",
    "sg:classifiers":[
        {
            "category":"Personal",
            "subcategory":"Massage",
            "type":"Services"
        }
    ],
    "sg:phone":"+61 422 402 750",
    "sg:postcode":"2287",
    "sg:province":"NSW",
    "sg:tags":[
        "therapy"
    ],
    "wof:name":"Care Support Massage Therapy",
    "wof:placetype":"venue"
},
  "geometry": {"coordinates":[151.66542053200001,-32.8914108276],"type":"Point"}
}