{
  "type": "Feature",
  "properties": {
    "addr:full":"715 Maroondah Hwy Coldstream VIC 3770",
    "addr:housenumber":"715",
    "addr:postcode":"3770",
    "addr:street":"Maroondah Hwy",
    "iso:country":"AU",
    "sg:address":"715 Maroondah Hwy",
    "sg:city":"Coldstream",
    "sg:classifiers":[
        {
            "category":"Farming",
            "subcategory":"Orchard",
            "type":"Manufacturing & Wholesale Goods"
        }
    ],
    "sg:phone":"+61 3 9739 1041",
    "sg:postcode":"3770",
    "sg:province":"VIC",
    "sg:tags":[
        "pear",
        "apple",
        "grower"
    ],
    "wof:name":"Maroondah Orchards",
    "wof:placetype":"venue"
},
  "geometry": {"coordinates":[145.421234,-37.695007],"type":"Point"}
}