{
  "type": "Feature",
  "properties": {
    "addr:full":"78 Osborne Rd Blacktown NSW 2148",
    "addr:housenumber":"78",
    "addr:postcode":"2148",
    "addr:street":"Osborne Rd",
    "iso:country":"AU",
    "sg:address":"78 Osborne Rd",
    "sg:city":"Blacktown",
    "sg:classifiers":[
        {
            "category":"Retail",
            "subcategory":"Auto Repair",
            "type":"Services"
        }
    ],
    "sg:phone":"+61 2 9622 3497",
    "sg:postcode":"2148",
    "sg:province":"NSW",
    "sg:tags":[
        "repairer",
        "motor",
        "engineer"
    ],
    "wof:name":"Road Runner Mobile Mechanical Repairs",
    "wof:placetype":"venue"
},
  "geometry": {"coordinates":[150.89030456500001,-33.7510643005],"type":"Point"}
}