{
  "type": "Feature",
  "properties": {
    "iso:country":"AU",
    "sg:address":"1/ 113 Johnston St",
    "sg:city":"Annandale",
    "sg:classifiers":[
        {
            "category":"Health Services",
            "subcategory":"Health Practitioner",
            "type":"Services"
        }
    ],
    "sg:phone":"+61 2 9692 9013",
    "sg:postcode":"2038",
    "sg:province":"NSW",
    "sg:tags":[
        "acupuncture"
    ],
    "wof:name":"Register Of Acupuncture & Traditional Chinese Medicine Inc",
    "wof:placetype":"venue"
},
  "geometry": {"coordinates":[151.17091369600001,-33.8812255859],"type":"Point"}
}