{
  "type": "Feature",
  "properties": {
    "iso:country":"AU",
    "sg:address":"71 Dunmore St",
    "sg:city":"Wentworthville",
    "sg:classifiers":[
        {
            "category":"Banks & Credit Unions",
            "subcategory":"Bank",
            "type":"Services"
        }
    ],
    "sg:phone":"+61 2 9631 7400",
    "sg:postcode":"2145",
    "sg:province":"NSW",
    "sg:tags":[
        "broker",
        "mortgage"
    ],
    "wof:name":"Loan Supermarket The",
    "wof:placetype":"venue"
},
  "geometry": {"coordinates":[150.969848633,-33.8072471619],"type":"Point"}
}