{
  "type": "Feature",
  "properties": {
    "addr:full":"Foxton Ave Mossman QLD 4873",
    "addr:postcode":"4873",
    "addr:street":"Foxton Ave Mossman",
    "iso:country":"AU",
    "sg:address":"Foxton Ave",
    "sg:city":"Mossman",
    "sg:classifiers":[
        {
            "category":"Education",
            "subcategory":"Kindergarten",
            "type":"Public Place"
        }
    ],
    "sg:phone":"+61 7 4098 1880",
    "sg:postcode":"4873",
    "sg:province":"QLD",
    "sg:tags":[
        "pre-schools"
    ],
    "wof:name":"Mossman Community Kindergarten",
    "wof:placetype":"venue"
},
  "geometry": {"coordinates":[145.37356567399999,-16.4591655731],"type":"Point"}
}