{
  "type": "Feature",
  "properties": {
    "iso:country":"AU",
    "sg:address":"10 Georges River Rd",
    "sg:city":"Oyster Bay",
    "sg:classifiers":[
        {
            "category":"Retail",
            "subcategory":"Repair Shop",
            "type":"Services"
        }
    ],
    "sg:phone":"+61 421 042 326",
    "sg:postcode":"2225",
    "sg:province":"NSW",
    "sg:tags":[
        "windscreen"
    ],
    "wof:name":"Keys",
    "wof:placetype":"venue"
},
  "geometry": {"coordinates":[151.076416016,-34.0079345703],"type":"Point"}
}