{
  "type": "Feature",
  "properties": {
    "addr:full":"47 Millenium Pl Tingalpa QLD 4173",
    "addr:housenumber":"47",
    "addr:postcode":"4173",
    "addr:street":"Millenium Pl",
    "iso:country":"AU",
    "sg:address":"47 Millenium Pl",
    "sg:city":"Tingalpa",
    "sg:classifiers":[
        {
            "category":"Home & Garden",
            "subcategory":"Hardware",
            "type":"Retail Goods"
        }
    ],
    "sg:phone":"+61 7 3348 3577",
    "sg:postcode":"4173",
    "sg:province":"QLD",
    "sg:tags":[
        "part",
        "air conditioning"
    ],
    "wof:name":"Trade Air Australia Pty Ltd",
    "wof:placetype":"venue"
},
  "geometry": {"coordinates":[153.14906310999999,-27.4662761688],"type":"Point"}
}