{
  "type": "Feature",
  "properties": {
    "iso:country":"AU",
    "sg:address":"1/ 10 O'Connell St",
    "sg:city":"Newtown",
    "sg:classifiers":[
        {
            "category":"Professional",
            "subcategory":"Art Services",
            "type":"Services"
        }
    ],
    "sg:phone":"+61 2 9517 4537",
    "sg:postcode":"2042",
    "sg:province":"NSW",
    "sg:tags":[
        "graphic",
        "designer"
    ],
    "wof:name":"Eyconology",
    "wof:placetype":"venue"
},
  "geometry": {"coordinates":[151.18220500000001,-33.892746],"type":"Point"}
}