{
  "type": "Feature",
  "properties": {
    "addr:full":"4/ 678 Beaufort St Mt Lawley WA 6050",
    "addr:housenumber":"/ 678",
    "addr:postcode":"6050",
    "addr:street":"Beaufort St",
    "iso:country":"AU",
    "sg:address":"4/ 678 Beaufort St",
    "sg:city":"Mt Lawley",
    "sg:classifiers":[
        {
            "category":"Real Estate",
            "subcategory":"Architect",
            "type":"Services"
        }
    ],
    "sg:phone":"+61 8 9371 7001",
    "sg:postcode":"6050",
    "sg:province":"WA",
    "wof:name":"Watt Architect & Construct",
    "wof:placetype":"venue"
},
  "geometry": {"coordinates":[115.873008728,-31.9336299896],"type":"Point"}
}