{
  "type": "Feature",
  "properties": {
    "addr:full":"61 High St Heathcote VIC 3523",
    "addr:housenumber":"61",
    "addr:postcode":"3523",
    "addr:street":"High St",
    "iso:country":"AU",
    "sg:address":"61 High St",
    "sg:city":"Heathcote",
    "sg:classifiers":[
        {
            "category":"Autos & Motor Vehicles",
            "subcategory":"Auto Supplies",
            "type":"Retail Goods"
        }
    ],
    "sg:phone":"+61 3 5433 2380",
    "sg:postcode":"3523",
    "sg:province":"VIC",
    "sg:tags":[
        "tyre"
    ],
    "wof:name":"Heathcote Tyre & Mechanical Services",
    "wof:placetype":"venue"
},
  "geometry": {"coordinates":[144.71177700000001,-36.92712],"type":"Point"}
}