{
  "type": "Feature",
  "properties": {
    "addr:full":"12 Hereford Rd Mt Evelyn VIC 3796",
    "addr:housenumber":"12",
    "addr:postcode":"3796",
    "addr:street":"Hereford Rd",
    "iso:country":"AU",
    "sg:address":"12 Hereford Rd",
    "sg:city":"Mt Evelyn",
    "sg:classifiers":[
        {
            "category":"Professional",
            "subcategory":"Art Services",
            "type":"Services"
        }
    ],
    "sg:phone":"+61 3 9736 2212",
    "sg:postcode":"3796",
    "sg:province":"VIC",
    "sg:tags":[
        "artist"
    ],
    "wof:name":"Buckmaster E",
    "wof:placetype":"venue"
},
  "geometry": {"coordinates":[145.38226318400001,-37.7843513489],"type":"Point"}
}