{
  "type": "Feature",
  "properties": {
    "iso:country":"AU",
    "sg:address":"82- 84 Abbott Rd",
    "sg:city":"Hallam",
    "sg:classifiers":[
        {
            "category":"Autos & Motor Vehicles",
            "subcategory":"Auto Supplies",
            "type":"Retail Goods"
        }
    ],
    "sg:phone":"+61 3 8796 9777",
    "sg:postcode":"3803",
    "sg:province":"VIC",
    "sg:tags":[
        "electric"
    ],
    "wof:name":"LINAK Australia Pty Ltd",
    "wof:placetype":"venue"
},
  "geometry": {"coordinates":[145.263061523,-38.0090408325],"type":"Point"}
}