{
  "type": "Feature",
  "properties": {
    "iso:country":"AU",
    "sg:address":"1 Cawley Rd",
    "sg:city":"Brooklyn",
    "sg:classifiers":[
        {
            "category":"Commercial Area",
            "type":"Public Place"
        }
    ],
    "sg:phone":"+61 3 9315 3999",
    "sg:postcode":"3025",
    "sg:province":"VIC",
    "sg:tags":[
        "heavy",
        "carrier"
    ],
    "wof:name":"Grove Haulage",
    "wof:placetype":"venue"
},
  "geometry": {"coordinates":[144.860336,-37.820229],"type":"Point"}
}