{
  "type": "Feature",
  "properties": {
    "addr:full":"Unit 7/ 25 Paramatta Rd Underwood QLD 4119",
    "addr:postcode":"4119",
    "addr:street":"25 Paramatta Rd",
    "iso:country":"AU",
    "sg:address":"Unit 7/ 25 Paramatta Rd",
    "sg:city":"Underwood",
    "sg:classifiers":[
        {
            "category":"Building & Trades",
            "subcategory":"Cleaning & Sanitation",
            "type":"Services"
        }
    ],
    "sg:phone":"+61 7 3208 5067",
    "sg:postcode":"4119",
    "sg:province":"QLD",
    "sg:tags":[
        "asbestos",
        "treatment",
        "removal"
    ],
    "wof:name":"IRT AUSTRALIA",
    "wof:placetype":"venue"
},
  "geometry": {"coordinates":[153.11659240700001,-27.6147289276],"type":"Point"}
}