{
  "type": "Feature",
  "properties": {
    "iso:country":"AU",
    "sg:address":"Shop 4, 62",
    "sg:city":"The Terrace Ocean Grove",
    "sg:classifiers":[
        {
            "category":"Professional",
            "subcategory":"Art Services",
            "type":"Services"
        }
    ],
    "sg:phone":"+61 3 5255 5861",
    "sg:postcode":"3226",
    "sg:province":"VIC",
    "sg:tags":[
        "picture",
        "frame",
        "framing"
    ],
    "wof:name":"HLB Frames",
    "wof:placetype":"venue"
},
  "geometry": {"coordinates":[144.522232,-38.267994],"type":"Point"}
}