{
  "type": "Feature",
  "properties": {
    "iso:country":"AU",
    "sg:address":"Lot 3321 Secrett Rd",
    "sg:city":"Knuckeys Lagoon",
    "sg:classifiers":[
        {
            "category":"Utilities",
            "subcategory":"Electric",
            "type":"Services"
        }
    ],
    "sg:phone":"+61 8 8984 3432",
    "sg:postcode":"0852",
    "sg:province":"NT",
    "sg:tags":[
        "electrical",
        "contractor"
    ],
    "wof:name":"Kyam Electrical Services",
    "wof:placetype":"venue"
},
  "geometry": {"coordinates":[133.373886,-16.30308],"type":"Point"}
}