{
  "type": "Feature",
  "properties": {
    "addr:full":"13 Parkwood Drv Samford QLD 4520",
    "addr:housenumber":"13",
    "addr:postcode":"4520",
    "addr:street":"Parkwood Drv",
    "iso:country":"AU",
    "sg:address":"13 Parkwood Drv",
    "sg:city":"Samford",
    "sg:classifiers":[
        {
            "category":"Building & Trades",
            "subcategory":"Construction",
            "type":"Services"
        }
    ],
    "sg:phone":"+61 418 722 595",
    "sg:postcode":"4520",
    "sg:province":"QLD",
    "sg:tags":[
        "contractor"
    ],
    "wof:name":"Cullen Constructions",
    "wof:placetype":"venue"
},
  "geometry": {"coordinates":[152.841217,-27.371017],"type":"Point"}
}