{
  "type": "Feature",
  "properties": {
    "addr:full":"17 Hanson St Freeling SA 5372",
    "addr:housenumber":"17",
    "addr:postcode":"5372",
    "addr:street":"Hanson St",
    "iso:country":"AU",
    "sg:address":"17 Hanson St",
    "sg:city":"Freeling",
    "sg:classifiers":[
        {
            "category":"Autos & Motor Vehicles",
            "subcategory":"Fuel & Gas Station",
            "type":"Retail Goods"
        }
    ],
    "sg:phone":"+61 8 8525 2007",
    "sg:postcode":"5372",
    "sg:province":"SA",
    "wof:name":"Schaefer E R & Son",
    "wof:placetype":"venue"
},
  "geometry": {"coordinates":[138.81207275400001,-34.454208374],"type":"Point"}
}