{
  "type": "Feature",
  "properties": {
    "iso:country":"AU",
    "sg:address":"83 High St",
    "sg:city":"Maryborough",
    "sg:classifiers":[
        {
            "category":"Fast Food",
            "type":"Food & Drink"
        }
    ],
    "sg:phone":"+61 3 5460 4441",
    "sg:postcode":"3465",
    "sg:province":"VIC",
    "sg:tags":[
        "away",
        "take"
    ],
    "wof:name":"Pinky's Pizza",
    "wof:placetype":"venue"
},
  "geometry": {"coordinates":[143.736236572,-37.0476722717],"type":"Point"}
}