{
  "type": "Feature",
  "properties": {
    "addr:full":"36 Tucabia St Coogee NSW 2034",
    "addr:housenumber":"36",
    "addr:postcode":"2034",
    "addr:street":"Tucabia St",
    "iso:country":"AU",
    "sg:address":"36 Tucabia St",
    "sg:city":"Coogee",
    "sg:classifiers":[
        {
            "category":"Professional",
            "subcategory":"Management & Consulting",
            "type":"Services"
        }
    ],
    "sg:phone":"+61 2 9315 5600",
    "sg:postcode":"2034",
    "sg:province":"NSW",
    "sg:tags":[
        "consultant"
    ],
    "wof:name":"Strategic Team Leadership Pty Ltd",
    "wof:placetype":"venue"
},
  "geometry": {"coordinates":[151.25413513199999,-33.9360923767],"type":"Point"}
}