{
  "type": "Feature",
  "properties": {
    "addr:full":"Unit 4, 26 Stennett Rd Ingleburn NSW 2565",
    "addr:housenumber":"26",
    "addr:postcode":"2565",
    "addr:street":"Stennett Rd",
    "iso:country":"AU",
    "sg:address":"Unit 4, 26 Stennett Rd",
    "sg:city":"Ingleburn",
    "sg:classifiers":[
        {
            "category":"Wholesale",
            "subcategory":"Stationery",
            "type":"Manufacturing & Wholesale Goods"
        }
    ],
    "sg:phone":"+61 2 9618 3055",
    "sg:postcode":"2565",
    "sg:province":"NSW",
    "sg:tags":[
        "mfrg"
    ],
    "wof:name":"Boundrite Paper & Leather Products",
    "wof:placetype":"venue"
},
  "geometry": {"coordinates":[150.85253906200001,-34.0030593872],"type":"Point"}
}