{
  "type": "Feature",
  "properties": {
    "iso:country":"AU",
    "sg:address":"11 Bellbird St",
    "sg:city":"Condon",
    "sg:classifiers":[
        {
            "category":"Professional",
            "subcategory":"Computer Services",
            "type":"Services"
        }
    ],
    "sg:phone":"+61 412 713 847",
    "sg:postcode":"4815",
    "sg:province":"QLD",
    "sg:tags":[
        "consultant",
        "system"
    ],
    "wof:name":"Comsol Technical",
    "wof:placetype":"venue"
},
  "geometry": {"coordinates":[146.720535,-19.330875],"type":"Point"}
}