{
  "type": "Feature",
  "properties": {
    "addr:full":"Shp3/ 261 Old Northern Rd Castle Hill NSW 2154",
    "addr:housenumber":"261",
    "addr:postcode":"2154",
    "addr:street":"Old Northern Rd",
    "iso:country":"AU",
    "sg:address":"Shp3/ 261 Old Northern Rd",
    "sg:city":"Castle Hill",
    "sg:classifiers":[
        {
            "category":"Personal",
            "subcategory":"Beauty Salon",
            "type":"Services"
        }
    ],
    "sg:phone":"+61 2 9680 3988",
    "sg:postcode":"2154",
    "sg:province":"NSW",
    "sg:tags":[
        "hairdresser"
    ],
    "wof:name":"Young Hair Salon",
    "wof:placetype":"venue"
},
  "geometry": {"coordinates":[151.00372314399999,-33.734539032],"type":"Point"}
}