{
  "type": "Feature",
  "properties": {
    "addr:full":"PO Box 918 Kalamunda WA 6076",
    "addr:postcode":"6076",
    "iso:country":"AU",
    "sg:address":"PO Box 918",
    "sg:city":"Kalamunda",
    "sg:classifiers":[
        {
            "category":"Insurance",
            "subcategory":"Hazard Insurance",
            "type":"Services"
        }
    ],
    "sg:phone":"+61 8 9352 8596",
    "sg:postcode":"6076",
    "sg:province":"WA",
    "sg:tags":[
        "fire",
        "accident",
        "marine"
    ],
    "wof:name":"Asset Record Management",
    "wof:placetype":"venue"
},
  "geometry": {"coordinates":[116.153198242,-32.0055885315],"type":"Point"}
}