{
  "type": "Feature",
  "properties": {
    "addr:full":"162 Golden Valley Drv Glossodia NSW 2756",
    "addr:housenumber":"162",
    "addr:postcode":"2756",
    "addr:street":"Golden Valley Drv",
    "iso:country":"AU",
    "sg:address":"162 Golden Valley Drv",
    "sg:city":"Glossodia",
    "sg:classifiers":[
        {
            "category":"Fast Food",
            "type":"Food & Drink"
        }
    ],
    "sg:phone":"+61 2 4576 5780",
    "sg:postcode":"2756",
    "sg:province":"NSW",
    "sg:tags":[
        "away",
        "take"
    ],
    "wof:name":"Glossodia Village Takeaway",
    "wof:placetype":"venue"
},
  "geometry": {"coordinates":[150.76724243199999,-33.5317001343],"type":"Point"}
}