{
  "type": "Feature",
  "properties": {
    "addr:full":"78 Rundle St Kent Town SA 5067",
    "addr:housenumber":"78",
    "addr:postcode":"5067",
    "addr:street":"Rundle St",
    "iso:country":"AU",
    "sg:address":"78 Rundle St",
    "sg:city":"Kent Town",
    "sg:classifiers":[
        {
            "category":"Professional",
            "type":"Services"
        }
    ],
    "sg:phone":"+61 8 8363 4655",
    "sg:postcode":"5067",
    "sg:province":"SA",
    "sg:tags":[
        "industrial",
        "commercial",
        "catering"
    ],
    "wof:name":"Metropolitan Canteens SA Pty Ltd",
    "wof:placetype":"venue"
},
  "geometry": {"coordinates":[138.61813354500001,-34.9204826355],"type":"Point"}
}