{
  "type": "Feature",
  "properties": {
    "addr:full":"Shop 9, 1015 Burwood Hwy Ferntree Gully VIC 3156",
    "addr:housenumber":"shop 9",
    "addr:postcode":"1015;3156",
    "addr:street":"Burwood Hwy",
    "iso:country":"AU",
    "sg:address":"Shop 9, 1015 Burwood Hwy",
    "sg:city":"Ferntree Gully",
    "sg:classifiers":[
        {
            "category":"Fast Food",
            "type":"Food & Drink"
        }
    ],
    "sg:phone":"+61 13 11 66",
    "sg:postcode":"3156",
    "sg:province":"VIC",
    "sg:tags":[
        "away",
        "take"
    ],
    "wof:name":"Pizza Hut Delivery",
    "wof:placetype":"venue"
},
  "geometry": {"coordinates":[145.289886475,-37.8881378174],"type":"Point"}
}