{
  "type": "Feature",
  "properties": {
    "addr:full":"Windsor Rd North Parramatta NSW 2151",
    "addr:postcode":"2151",
    "addr:street":"Windsor Rd",
    "iso:country":"AU",
    "sg:address":"Windsor Rd",
    "sg:city":"North Parramatta",
    "sg:classifiers":[
        {
            "category":"Retail",
            "subcategory":"Repair Shop",
            "type":"Services"
        }
    ],
    "sg:phone":"+61 2 9681 3308",
    "sg:postcode":"2151",
    "sg:province":"NSW",
    "sg:tags":[
        "upholsterer"
    ],
    "wof:name":"Ison Upholstery",
    "wof:placetype":"venue"
},
  "geometry": {"coordinates":[150.99989318900001,-33.7933883667],"type":"Point"}
}