{
  "type": "Feature",
  "properties": {
    "iso:country":"AU",
    "sg:address":"80/ 465 Glebe Point Rd",
    "sg:city":"Glebe",
    "sg:classifiers":[
        {
            "category":"Home & Garden",
            "subcategory":"Carpets & Floor Coverings",
            "type":"Retail Goods"
        }
    ],
    "sg:phone":"+61 2 9552 1507",
    "sg:postcode":"2037",
    "sg:province":"NSW",
    "sg:tags":[
        "flooring",
        "parquet"
    ],
    "wof:name":"Blackwattle Hardwood Floors",
    "wof:placetype":"venue"
},
  "geometry": {"coordinates":[151.181396484,-33.8724975586],"type":"Point"}
}