{
  "type": "Feature",
  "properties": {
    "addr:full":"121 Macquarie Rd Springwood NSW 2777",
    "addr:housenumber":"121",
    "addr:postcode":"2777",
    "addr:street":"Macquarie Rd",
    "iso:country":"AU",
    "sg:address":"121 Macquarie Rd",
    "sg:city":"Springwood",
    "sg:classifiers":[
        {
            "category":"Shopping",
            "subcategory":"Mobile Phones",
            "type":"Retail Goods"
        }
    ],
    "sg:phone":"+61 2 4751 1795",
    "sg:postcode":"2777",
    "sg:province":"NSW",
    "sg:tags":[
        "telephone",
        "accessory"
    ],
    "wof:name":"The Phone House",
    "wof:placetype":"venue"
},
  "geometry": {"coordinates":[150.567596436,-33.6989631653],"type":"Point"}
}