{
  "type": "Feature",
  "properties": {
    "iso:country":"AU",
    "sg:address":"1 / 59 Argyle St",
    "sg:city":"Camden",
    "sg:classifiers":[
        {
            "category":"Banks & Credit Unions",
            "subcategory":"Bank",
            "type":"Services"
        }
    ],
    "sg:phone":"+61 2 4655 7777",
    "sg:postcode":"2570",
    "sg:province":"NSW",
    "sg:tags":[
        "broker",
        "mortgage"
    ],
    "wof:name":"Camden Home Loans",
    "wof:placetype":"venue"
},
  "geometry": {"coordinates":[150.69723510700001,-34.0537643433],"type":"Point"}
}