{
  "type": "Feature",
  "properties": {
    "iso:country":"AU",
    "sg:address":"Shop 16, Parabanks Shopping Centre, John St",
    "sg:city":"Salisbury",
    "sg:classifiers":[
        {
            "category":"Personal",
            "subcategory":"Beauty Salon",
            "type":"Services"
        }
    ],
    "sg:phone":"+61 8 8258 6691",
    "sg:postcode":"5108",
    "sg:province":"SA",
    "wof:name":"Beyond Blonde",
    "wof:placetype":"venue"
},
  "geometry": {"coordinates":[138.644363403,-34.7626914978],"type":"Point"}
}