{
  "type": "Feature",
  "properties": {
    "addr:full":"Cnr Pittwater Rd & Vineyard St Mona Vale NSW 2103",
    "addr:postcode":"2103",
    "addr:street":"Cnr Pittwater Rd &;St",
    "iso:country":"AU",
    "sg:address":"Cnr Pittwater Rd & Vineyard St",
    "sg:city":"Mona Vale",
    "sg:classifiers":[
        {
            "category":"Food & Beverages",
            "subcategory":"Supermarket",
            "type":"Retail Goods"
        }
    ],
    "sg:phone":"+61 2 9979 5893",
    "sg:postcode":"2103",
    "sg:province":"NSW",
    "sg:tags":[
        "grocery",
        "store"
    ],
    "wof:name":"Food Plus Ltd",
    "wof:placetype":"venue"
},
  "geometry": {"coordinates":[151.30323791500001,-33.6785240173],"type":"Point"}
}