{
  "type": "Feature",
  "properties": {
    "iso:country":"AU",
    "sg:address":"55 Trade Pl",
    "sg:city":"Coburg North",
    "sg:classifiers":[
        {
            "category":"Wholesale",
            "subcategory":"Machinery & Supplies",
            "type":"Manufacturing & Wholesale Goods"
        }
    ],
    "sg:phone":"+61 3 9354 6776",
    "sg:postcode":"3058",
    "sg:province":"VIC",
    "sg:tags":[
        "equipment",
        "system",
        "elevating",
        "conveying"
    ],
    "wof:name":"Line Engineering Aust Pty Ltd",
    "wof:placetype":"venue"
},
  "geometry": {"coordinates":[144.96958923299999,-37.7242698669],"type":"Point"}
}