{
  "type": "Feature",
  "properties": {
    "addr:full":"Unit 7/ 87 Newlands Rd Reservoir VIC 3073",
    "addr:housenumber":"87",
    "addr:postcode":"3073",
    "addr:street":"Newlands Rd",
    "iso:country":"AU",
    "sg:address":"Unit 7/ 87 Newlands Rd",
    "sg:city":"Reservoir",
    "sg:classifiers":[
        {
            "category":"Home & Garden",
            "subcategory":"Garden Supply",
            "type":"Retail Goods"
        }
    ],
    "sg:phone":"+61 3 9460 5171",
    "sg:postcode":"3073",
    "sg:province":"VIC",
    "sg:tags":[
        "turf",
        "lawn"
    ],
    "wof:name":"Independent Turf Services Pty Ltd",
    "wof:placetype":"venue"
},
  "geometry": {"coordinates":[144.97300720199999,-37.7275276184],"type":"Point"}
}