{
  "type": "Feature",
  "properties": {
    "iso:country":"AU",
    "sg:address":"75 Morayfield Rd",
    "sg:city":"Caboolture",
    "sg:classifiers":[
        {
            "category":"Fast Food",
            "type":"Food & Drink"
        }
    ],
    "sg:phone":"+61 7 5428 0544",
    "sg:postcode":"4510",
    "sg:province":"QLD",
    "sg:tags":[
        "away",
        "take"
    ],
    "wof:name":"Aussie Rooster",
    "wof:placetype":"venue"
},
  "geometry": {"coordinates":[152.94958500000001,-27.095703],"type":"Point"}
}