{
  "type": "Feature",
  "properties": {
    "addr:full":"42 Nerang St Southport QLD 4215",
    "addr:housenumber":"42",
    "addr:postcode":"4215",
    "addr:street":"Nerang St",
    "iso:country":"AU",
    "sg:address":"42 Nerang St",
    "sg:city":"Southport",
    "sg:classifiers":[
        {
            "category":"Travel",
            "subcategory":"Hotels & Motels",
            "type":"Entertainment"
        }
    ],
    "sg:phone":"+61 7 5531 0700",
    "sg:postcode":"4215",
    "sg:province":"QLD",
    "sg:tags":[
        "accommodation"
    ],
    "wof:name":"Cecil Hotel",
    "wof:placetype":"venue"
},
  "geometry": {"coordinates":[153.4140625,-27.9676399231],"type":"Point"}
}