{
  "type": "Feature",
  "properties": {
    "addr:full":"9 Raper St Surry Hills NSW 2010",
    "addr:housenumber":"9",
    "addr:postcode":"2010",
    "addr:street":"Raper St",
    "iso:country":"AU",
    "sg:address":"9 Raper St",
    "sg:city":"Surry Hills",
    "sg:classifiers":[
        {
            "category":"Wholesale",
            "subcategory":"Apparel",
            "type":"Manufacturing & Wholesale Goods"
        }
    ],
    "sg:phone":"+61 2 9319 5282",
    "sg:postcode":"2010",
    "sg:province":"NSW",
    "sg:tags":[
        "wholesaler",
        "mfrs",
        "dress"
    ],
    "wof:name":"Three's Company Ltd",
    "wof:placetype":"venue"
},
  "geometry": {"coordinates":[151.21432495100001,-33.8888473511],"type":"Point"}
}