{
  "type": "Feature",
  "properties": {
    "iso:country":"AU",
    "sg:address":"15 Surrey St",
    "sg:city":"Bentleigh East",
    "sg:classifiers":[
        {
            "category":"Professional",
            "subcategory":"Computer Services",
            "type":"Services"
        }
    ],
    "sg:phone":"+61 1300 130 003",
    "sg:postcode":"3165",
    "sg:province":"VIC",
    "sg:tags":[
        "tele-communications",
        "consultant"
    ],
    "wof:name":"Elron Telecom",
    "wof:placetype":"venue"
},
  "geometry": {"coordinates":[145.05140685999999,-37.9279022217],"type":"Point"}
}