{
  "type": "Feature",
  "properties": {
    "addr:full":"45 Moore St Rochester VIC 3561",
    "addr:housenumber":"45",
    "addr:postcode":"3561",
    "addr:street":"Moore St",
    "iso:country":"AU",
    "sg:address":"45 Moore St",
    "sg:city":"Rochester",
    "sg:classifiers":[
        {
            "category":"Shopping",
            "subcategory":"Computers & Home Electronics",
            "type":"Retail Goods"
        }
    ],
    "sg:phone":"+61 3 5484 3000",
    "sg:postcode":"3561",
    "sg:province":"VIC",
    "sg:tags":[
        "small",
        "equipment",
        "business"
    ],
    "wof:name":"Andersons' Retravision",
    "wof:placetype":"venue"
},
  "geometry": {"coordinates":[144.69778442399999,-36.3640670776],"type":"Point"}
}