{
  "type": "Feature",
  "properties": {
    "addr:full":"6 McCourt Rd Yarrawonga NT 0830",
    "addr:housenumber":"6",
    "addr:postcode":"nt 0830",
    "addr:street":"Mccourt Rd",
    "iso:country":"AU",
    "sg:address":"6 McCourt Rd",
    "sg:city":"Yarrawonga",
    "sg:classifiers":[
        {
            "category":"Shopping",
            "subcategory":"Computers & Home Electronics",
            "type":"Retail Goods"
        }
    ],
    "sg:phone":"+61 8 8932 5366",
    "sg:postcode":"0830",
    "sg:province":"NT",
    "sg:tags":[
        "hardware",
        "equipment"
    ],
    "wof:name":"I Shop",
    "wof:placetype":"venue"
},
  "geometry": {"coordinates":[130.99191300000001,-12.473121],"type":"Point"}
}