{
  "type": "Feature",
  "properties": {
    "addr:full":"329 Preston Pt Rd Attadale WA 6156",
    "addr:housenumber":"329",
    "addr:postcode":"6156",
    "addr:street":"Preston Pt Rd",
    "iso:country":"AU",
    "sg:address":"329 Preston Pt Rd",
    "sg:city":"Attadale",
    "sg:classifiers":[
        {
            "category":"Real Estate",
            "subcategory":"Real Estate Agent",
            "type":"Services"
        }
    ],
    "sg:phone":"+61 8 9317 2127",
    "sg:postcode":"6156",
    "sg:province":"WA",
    "wof:name":"Ormsby & Co",
    "wof:placetype":"venue"
},
  "geometry": {"coordinates":[115.797112,-32.030411],"type":"Point"}
}