{
  "type": "Feature",
  "properties": {
    "addr:full":"365 Kettles Rd Lang Lang VIC 3984",
    "addr:housenumber":"365",
    "addr:postcode":"3984",
    "addr:street":"Kettles Rd",
    "iso:country":"AU",
    "sg:address":"365 Kettles Rd",
    "sg:city":"Lang Lang",
    "sg:classifiers":[
        {
            "category":"Building & Trades",
            "subcategory":"Plumbing",
            "type":"Services"
        }
    ],
    "sg:phone":"+61 3 5997 5586",
    "sg:postcode":"3984",
    "sg:province":"VIC",
    "sg:tags":[
        "plumber",
        "gasfitters"
    ],
    "wof:name":"Lang Lang Plumbing Service",
    "wof:placetype":"venue"
},
  "geometry": {"coordinates":[145.57063293499999,-38.2907562256],"type":"Point"}
}