{
  "type": "Feature",
  "properties": {
    "addr:full":"5 Wylie Crs West Moonah TAS 7009",
    "addr:housenumber":"5",
    "addr:postcode":"7009",
    "addr:street":"Wylie Crs West",
    "iso:country":"AU",
    "sg:address":"5 Wylie Crs",
    "sg:city":"West Moonah",
    "sg:classifiers":[
        {
            "category":"Building & Trades",
            "subcategory":"Construction",
            "type":"Services"
        }
    ],
    "sg:phone":"+61 3 6273 7303",
    "sg:postcode":"7009",
    "sg:province":"TAS",
    "sg:tags":[
        "plasterboard",
        "plasterer",
        "fixer"
    ],
    "wof:name":"Henryk Kasprzak",
    "wof:placetype":"venue"
},
  "geometry": {"coordinates":[147.27992248499999,-42.8481483459],"type":"Point"}
}