{
  "type": "Feature",
  "properties": {
    "addr:full":"26 Huntington St Clontarf QLD 4019",
    "addr:housenumber":"26",
    "addr:postcode":"4019",
    "addr:street":"Huntington St",
    "iso:country":"AU",
    "sg:address":"26 Huntington St",
    "sg:city":"Clontarf",
    "sg:classifiers":[
        {
            "category":"Food & Beverages",
            "subcategory":"Meat & Fish",
            "type":"Retail Goods"
        }
    ],
    "sg:phone":"+61 7 3284 2787",
    "sg:postcode":"4019",
    "sg:province":"QLD",
    "sg:tags":[
        "seafood"
    ],
    "wof:name":"K-Seas Trading Corporation Pty Ltd",
    "wof:placetype":"venue"
},
  "geometry": {"coordinates":[153.08161926299999,-27.2391357422],"type":"Point"}
}