{
  "type": "Feature",
  "properties": {
    "iso:country":"AU",
    "sg:address":"14 Patch St",
    "sg:city":"Sarina",
    "sg:classifiers":[
        {
            "category":"Commercial Area",
            "type":"Public Place"
        }
    ],
    "sg:phone":"+61 7 4952 4380",
    "sg:postcode":"4737",
    "sg:province":"QLD",
    "sg:tags":[
        "heavy",
        "carrier"
    ],
    "wof:name":"Sarina Carriers",
    "wof:placetype":"venue"
},
  "geometry": {"coordinates":[149.227142,-21.405649],"type":"Point"}
}