{
  "type": "Feature",
  "properties": {
    "addr:full":"176 Berserker St Rockhampton QLD 4700",
    "addr:housenumber":"176",
    "addr:postcode":"4700",
    "addr:street":"Berserker St",
    "iso:country":"AU",
    "sg:address":"176 Berserker St",
    "sg:city":"Rockhampton",
    "sg:classifiers":[
        {
            "category":"Professional",
            "subcategory":"Employment Agencies",
            "type":"Services"
        }
    ],
    "sg:phone":"+61 7 4926 2688",
    "sg:postcode":"4700",
    "sg:province":"QLD",
    "sg:tags":[
        "provider",
        "internet"
    ],
    "wof:name":"Fitzroy Computer Services",
    "wof:placetype":"venue"
},
  "geometry": {"coordinates":[150.52999877900001,-23.3632926941],"type":"Point"}
}