{
  "type": "Feature",
  "properties": {
    "addr:full":"20 Malcolm St Blacktown NSW 2148",
    "addr:housenumber":"20",
    "addr:postcode":"2148",
    "addr:street":"Malcolm St",
    "iso:country":"AU",
    "sg:address":"20 Malcolm St",
    "sg:city":"Blacktown",
    "sg:classifiers":[
        {
            "category":"Shopping",
            "subcategory":"Crafts & Fabrics",
            "type":"Retail Goods"
        }
    ],
    "sg:phone":"+61 2 9676 3898",
    "sg:postcode":"2148",
    "sg:province":"NSW",
    "sg:tags":[
        "supply"
    ],
    "wof:name":"The Tapestry Studio",
    "wof:placetype":"venue"
},
  "geometry": {"coordinates":[150.91142273,-33.7822341919],"type":"Point"}
}