{
  "type": "Feature",
  "properties": {
    "addr:full":"203 Brisbane Rd Mooloolaba QLD 4557",
    "addr:housenumber":"203",
    "addr:postcode":"4557",
    "addr:street":"Brisbane Rd",
    "iso:country":"AU",
    "sg:address":"203 Brisbane Rd",
    "sg:city":"Mooloolaba",
    "sg:classifiers":[
        {
            "category":"Building & Trades",
            "subcategory":"Construction",
            "type":"Services"
        }
    ],
    "sg:phone":"+61 7 5444 8555",
    "sg:postcode":"4557",
    "sg:province":"QLD",
    "sg:tags":[
        "decking",
        "contractor"
    ],
    "wof:name":"Better Patios & Decks Pty Ltd",
    "wof:placetype":"venue"
},
  "geometry": {"coordinates":[153.11555480999999,-26.6948432922],"type":"Point"}
}