{
  "type": "Feature",
  "properties": {
    "addr:full":"485 Bronte Rd Bronte NSW 2024",
    "addr:housenumber":"485",
    "addr:postcode":"2024",
    "addr:street":"Bronte Rd",
    "iso:country":"AU",
    "sg:address":"485 Bronte Rd",
    "sg:city":"Bronte",
    "sg:classifiers":[
        {
            "category":"Cafe",
            "type":"Food & Drink"
        }
    ],
    "sg:phone":"+61 2 9389 7498",
    "sg:postcode":"2024",
    "sg:province":"NSW",
    "wof:name":"Jennys Cafe",
    "wof:placetype":"venue"
},
  "geometry": {"coordinates":[151.267852783,-33.9051856995],"type":"Point"}
}