{
  "type": "Feature",
  "properties": {
    "iso:country":"AU",
    "sg:address":"20qg/ 8 Quay St",
    "sg:city":"Haymarket",
    "sg:classifiers":[
        {
            "category":"Food & Beverages",
            "subcategory":"Supermarket",
            "type":"Retail Goods"
        }
    ],
    "sg:phone":"+61 2 9281 0087",
    "sg:postcode":"2000",
    "sg:province":"NSW",
    "sg:tags":[
        "grocery",
        "store"
    ],
    "wof:name":"Indoshop 28",
    "wof:placetype":"venue"
},
  "geometry": {"coordinates":[151.202957153,-33.8806533813],"type":"Point"}
}