{
  "type": "Feature",
  "properties": {
    "addr:full":"1 High St Edgecliff NSW 2027",
    "addr:housenumber":"1",
    "addr:postcode":"2027",
    "addr:street":"High St",
    "iso:country":"AU",
    "sg:address":"1 High St",
    "sg:city":"Edgecliff",
    "sg:classifiers":[
        {
            "category":"Health Services",
            "subcategory":"Chiropractor",
            "type":"Services"
        }
    ],
    "sg:phone":"+61 2 9363 0766",
    "sg:postcode":"2027",
    "sg:province":"NSW",
    "wof:name":"Ackerman David",
    "wof:placetype":"venue"
},
  "geometry": {"coordinates":[151.23789977999999,-33.8811912537],"type":"Point"}
}