{
  "type": "Feature",
  "properties": {
    "addr:full":"2 Cecil St Australind WA 6233",
    "addr:housenumber":"2",
    "addr:postcode":"6233",
    "addr:street":"Cecil St",
    "iso:country":"AU",
    "sg:address":"2 Cecil St",
    "sg:city":"Australind",
    "sg:classifiers":[
        {
            "category":"Home & Garden",
            "subcategory":"Building Materials",
            "type":"Retail Goods"
        }
    ],
    "sg:phone":"+61 8 9797 1368",
    "sg:postcode":"6233",
    "sg:province":"WA",
    "sg:tags":[
        "concrete",
        "gutter",
        "kerb"
    ],
    "wof:name":"Liddle Elliot",
    "wof:placetype":"venue"
},
  "geometry": {"coordinates":[115.712379,-33.29351],"type":"Point"}
}