{
  "type": "Feature",
  "properties": {
    "addr:full":"1/ 919 Nudgee Rd Nudgee QLD 4014",
    "addr:housenumber":"/ 919",
    "addr:postcode":"4014",
    "addr:street":"Nudgee Rd",
    "iso:country":"AU",
    "sg:address":"1/ 919 Nudgee Rd",
    "sg:city":"Nudgee",
    "sg:classifiers":[
        {
            "category":"Wholesale",
            "subcategory":"Electrical",
            "type":"Manufacturing & Wholesale Goods"
        }
    ],
    "sg:phone":"+61 1300 202 525",
    "sg:postcode":"4014",
    "sg:province":"QLD",
    "sg:tags":[
        "wholesaler",
        "mfrs",
        "accessory"
    ],
    "wof:name":"Clipsal Australia Pty Ltd",
    "wof:placetype":"venue"
},
  "geometry": {"coordinates":[153.08656310999999,-27.3878040314],"type":"Point"}
}