{
  "type": "Feature",
  "properties": {
    "iso:country":"AU",
    "sg:address":"Riverbank Drv",
    "sg:city":"Katherine",
    "sg:classifiers":[
        {
            "category":"Education",
            "subcategory":"School",
            "type":"Public Place"
        }
    ],
    "sg:phone":"+61 8 8972 1277",
    "sg:postcode":"0850",
    "sg:province":"NT",
    "sg:tags":[
        "state",
        "except",
        "nsw"
    ],
    "wof:name":"Katherine South Primary School",
    "wof:placetype":"venue"
},
  "geometry": {"coordinates":[132.258484,-14.464258],"type":"Point"}
}