{
  "type": "Feature",
  "properties": {
    "iso:country":"AU",
    "sg:address":"1 Darling St",
    "sg:city":"Tilpa",
    "sg:classifiers":[
        {
            "category":"Travel",
            "subcategory":"Hotels & Motels",
            "type":"Entertainment"
        }
    ],
    "sg:phone":"+61 2 6837 3928",
    "sg:postcode":"2840",
    "sg:province":"NSW",
    "sg:tags":[
        "accommodation"
    ],
    "wof:name":"Tilpa Hotel",
    "wof:placetype":"venue"
},
  "geometry": {"coordinates":[145.94012499999999,-30.087933],"type":"Point"}
}