{
  "type": "Feature",
  "properties": {
    "iso:country":"AU",
    "sg:address":"18 Davey St",
    "sg:city":"Frankston",
    "sg:classifiers":[
        {
            "category":"Organizations",
            "subcategory":"Non-profit Organization",
            "type":"Services"
        }
    ],
    "sg:phone":"+61 3 9769 6799",
    "sg:postcode":"3199",
    "sg:province":"VIC",
    "sg:tags":[
        "support",
        "disability",
        "organisation"
    ],
    "wof:name":"Multiple Sclerosis Victoria Regional Resource Centres",
    "wof:placetype":"venue"
},
  "geometry": {"coordinates":[145.08804321299999,-37.9967842102],"type":"Point"}
}