{
  "type": "Feature",
  "properties": {
    "addr:full":"9/ 200 Richmond Rd Marleston SA 5033",
    "addr:housenumber":"/ 200",
    "addr:postcode":"5033",
    "addr:street":"Richmond Rd",
    "iso:country":"AU",
    "sg:address":"9/ 200 Richmond Rd",
    "sg:city":"Marleston",
    "sg:classifiers":[
        {
            "category":"Personal",
            "subcategory":"Beauty Salon",
            "type":"Services"
        }
    ],
    "sg:phone":"+61 8 8234 8399",
    "sg:postcode":"5033",
    "sg:province":"SA",
    "sg:tags":[
        "hairdresser"
    ],
    "wof:name":"Sculptured Scissors",
    "wof:placetype":"venue"
},
  "geometry": {"coordinates":[138.562942505,-34.9426383972],"type":"Point"}
}