{
  "type": "Feature",
  "properties": {
    "addr:full":"21 Grove St Eden Hills SA 5050",
    "addr:housenumber":"21",
    "addr:postcode":"5050",
    "addr:street":"Grove St",
    "iso:country":"AU",
    "sg:address":"21 Grove St",
    "sg:city":"Eden Hills",
    "sg:classifiers":[
        {
            "category":"Professional",
            "subcategory":"Management & Consulting",
            "type":"Services"
        }
    ],
    "sg:phone":"+61 8 8370 2255",
    "sg:postcode":"5050",
    "sg:province":"SA",
    "sg:tags":[
        "consultant"
    ],
    "wof:name":"Richter Consultants",
    "wof:placetype":"venue"
},
  "geometry": {"coordinates":[138.60554500000001,-35.018066],"type":"Point"}
}