{
  "type": "Feature",
  "properties": {
    "addr:full":"268 Railway Pde Noble Park VIC 3174",
    "addr:housenumber":"268",
    "addr:postcode":"3174",
    "addr:street":"Railway Pde",
    "iso:country":"AU",
    "sg:address":"268 Railway Pde",
    "sg:city":"Noble Park",
    "sg:classifiers":[
        {
            "category":"Personal",
            "subcategory":"Beauty Salon",
            "type":"Services"
        }
    ],
    "sg:phone":"+61 3 9794 0032",
    "sg:postcode":"3174",
    "sg:province":"VIC",
    "sg:tags":[
        "hairdresser"
    ],
    "wof:name":"Future Line Hair Design",
    "wof:placetype":"venue"
},
  "geometry": {"coordinates":[145.18626403799999,-37.9736976624],"type":"Point"}
}