{
  "type": "Feature",
  "properties": {
    "addr:full":"6 Colthur St Reservoir VIC 3073",
    "addr:housenumber":"6",
    "addr:postcode":"3073",
    "addr:street":"Colthur St",
    "iso:country":"AU",
    "sg:address":"6 Colthur St",
    "sg:city":"Reservoir",
    "sg:classifiers":[
        {
            "category":"Utilities",
            "subcategory":"Recycling",
            "type":"Services"
        }
    ],
    "sg:phone":"+61 417 358 075",
    "sg:postcode":"3073",
    "sg:province":"VIC",
    "wof:name":"Blue North",
    "wof:placetype":"venue"
},
  "geometry": {"coordinates":[144.99282836899999,-37.7095031738],"type":"Point"}
}