{
  "type": "Feature",
  "properties": {
    "addr:full":"5 Flood Ave Sussex Inlet NSW 2540",
    "addr:housenumber":"5",
    "addr:postcode":"2540",
    "addr:street":"Flood Ave",
    "iso:country":"AU",
    "sg:address":"5 Flood Ave",
    "sg:city":"Sussex Inlet",
    "sg:classifiers":[
        {
            "category":"Retail",
            "subcategory":"Storage",
            "type":"Services"
        }
    ],
    "sg:phone":"+61 2 4441 2651",
    "sg:postcode":"2540",
    "sg:province":"NSW",
    "wof:name":"Sussex Inlet Storage",
    "wof:placetype":"venue"
},
  "geometry": {"coordinates":[150.57786560100001,-35.1607894897],"type":"Point"}
}