{
  "type": "Feature",
  "properties": {
    "addr:full":"689 Mt Alexander Rd Moonee Ponds VIC 3039",
    "addr:housenumber":"689",
    "addr:postcode":"3039",
    "addr:street":"Mt Alexander Rd",
    "iso:country":"AU",
    "sg:address":"689 Mt Alexander Rd",
    "sg:city":"Moonee Ponds",
    "sg:classifiers":[
        {
            "category":"Restaurant",
            "type":"Food & Drink"
        }
    ],
    "sg:phone":"+61 3 9370 5346",
    "sg:postcode":"3039",
    "sg:province":"VIC",
    "wof:name":"Chez Lucien",
    "wof:placetype":"venue"
},
  "geometry": {"coordinates":[144.92340100000001,-37.765003],"type":"Point"}
}