{
  "type": "Feature",
  "properties": {
    "iso:country":"AU",
    "sg:address":"689 Mt Alexander Rd",
    "sg:city":"Moonee Ponds",
    "sg:classifiers":[
        {
            "category":"Restaurant",
            "type":"Food & Drink"
        }
    ],
    "sg:phone":"+61 3 9370 5346",
    "sg:postcode":"3039",
    "sg:province":"VIC",
    "wof:name":"Chez Lucien",
    "wof:placetype":"venue"
},
  "geometry": {"coordinates":[144.923401,-37.765003],"type":"Point"}
}