{
  "type": "Feature",
  "properties": {
    "addr:full":"Suite B1 The Canberra Specialist Centre, 161 Stric Deakin Deakin ACT 2600",
    "addr:housenumber":"b1;161",
    "addr:postcode":"2600",
    "addr:street":"The;Stric Deakin",
    "iso:country":"AU",
    "sg:address":"Suite B1 The Canberra Specialist Centre, 161 Stric",
    "sg:city":"Deakin Deakin",
    "sg:classifiers":[
        {
            "category":"Health Services",
            "subcategory":"Doctor",
            "type":"Services"
        }
    ],
    "sg:phone":"+61 2 6285 4111",
    "sg:postcode":"2600",
    "sg:province":"ACT",
    "sg:tags":[
        "medical",
        "practitioner"
    ],
    "wof:name":"Moore Patrick Dr",
    "wof:placetype":"venue"
},
  "geometry": {"coordinates":[149.12803649899999,-35.3131370544],"type":"Point"}
}