{
  "type": "Feature",
  "properties": {
    "addr:full":"114 Bellerine Hwy Geelong VIC 3220",
    "addr:housenumber":"114",
    "addr:postcode":"3220",
    "addr:street":"Bellerine Hwy",
    "iso:country":"AU",
    "sg:address":"114 Bellerine Hwy",
    "sg:city":"Geelong",
    "sg:classifiers":[
        {
            "category":"Organizations",
            "subcategory":"Community Association",
            "type":"Services"
        }
    ],
    "sg:phone":"+61 3 5248 1403",
    "sg:postcode":"3220",
    "sg:province":"VIC",
    "sg:tags":[
        "organisation",
        "family",
        "welfare"
    ],
    "wof:name":"Salvation Army The",
    "wof:placetype":"venue"
},
  "geometry": {"coordinates":[144.36193800000001,-38.156956],"type":"Point"}
}