{
  "type": "Feature",
  "properties": {
    "iso:country":"AU",
    "sg:address":"RMB 1377 Yarramalong Rd",
    "sg:city":"Yarramalong",
    "sg:classifiers":[
        {
            "category":"Autos & Motor Vehicles",
            "subcategory":"Fuel & Gas Station",
            "type":"Retail Goods"
        }
    ],
    "sg:phone":"+61 2 4356 1222",
    "sg:postcode":"2259",
    "sg:province":"NSW",
    "wof:name":"Yarramalong Store",
    "wof:placetype":"venue"
},
  "geometry": {"coordinates":[151.299194336,-33.2348365784],"type":"Point"}
}