{
  "type": "Feature",
  "properties": {
    "addr:full":"35/38 Howard St Brisbane QLD 4000",
    "addr:housenumber":"35 / 38",
    "addr:postcode":"4000",
    "addr:street":"Howard St",
    "iso:country":"AU",
    "sg:address":"35/38 Howard St",
    "sg:city":"Brisbane",
    "sg:classifiers":[
        {
            "category":"Real Estate",
            "subcategory":"Developer",
            "type":"Services"
        }
    ],
    "sg:phone":"+61 7 3831 3635",
    "sg:postcode":"4000",
    "sg:province":"QLD",
    "sg:tags":[
        "development"
    ],
    "wof:name":"Branslawn Pty Ltd",
    "wof:placetype":"venue"
},
  "geometry": {"coordinates":[153.03228759800001,-27.4634494781],"type":"Point"}
}