{
  "type": "Feature",
  "properties": {
    "addr:full":"479 High St Prahran VIC 3181",
    "addr:housenumber":"479",
    "addr:postcode":"3181",
    "addr:street":"High St",
    "iso:country":"AU",
    "sg:address":"479 High St",
    "sg:city":"Prahran",
    "sg:classifiers":[
        {
            "category":"Personal",
            "subcategory":"Beauty Salon",
            "type":"Services"
        }
    ],
    "sg:phone":"+61 3 9521 1637",
    "sg:postcode":"3181",
    "sg:province":"VIC",
    "sg:tags":[
        "hairdresser"
    ],
    "wof:name":"Blondes to Brunettes",
    "wof:placetype":"venue"
},
  "geometry": {"coordinates":[145.00413513199999,-37.8531532288],"type":"Point"}
}