{
  "type": "Feature",
  "properties": {
    "iso:country":"AU",
    "sg:address":"Main St",
    "sg:city":"Warooka",
    "sg:classifiers":[
        {
            "category":"Education",
            "subcategory":"School",
            "type":"Public Place"
        }
    ],
    "sg:phone":"+61 8 8854 5034",
    "sg:postcode":"5577",
    "sg:province":"SA",
    "sg:tags":[
        "state",
        "except",
        "nsw"
    ],
    "wof:name":"Warooka Primary School",
    "wof:placetype":"venue"
},
  "geometry": {"coordinates":[137.390350342,-34.986579895],"type":"Point"}
}