{
  "type": "Feature",
  "properties": {
    "iso:country":"AU",
    "sg:address":"Lvl 1, 72 Pitt St",
    "sg:city":"Sydney",
    "sg:classifiers":[
        {
            "category":"Health Services",
            "subcategory":"Health Practitioner",
            "type":"Services"
        }
    ],
    "sg:phone":"+61 2 9420 3288",
    "sg:postcode":"2000",
    "sg:province":"NSW",
    "sg:tags":[
        "hypnotherapy"
    ],
    "wof:name":"All Body Mind and Soul Treatments",
    "wof:placetype":"venue"
},
  "geometry": {"coordinates":[151.20877075199999,-33.8660430908],"type":"Point"}
}