{
  "type": "Feature",
  "properties": {
    "addr:full":"Shop 2 269 Lawrence Hargrave Drv Thirroul NSW 2515",
    "addr:housenumber":"shop 2 269",
    "addr:postcode":"2515",
    "addr:street":"Lawrence Hargrave Drv",
    "iso:country":"AU",
    "sg:address":"Shop 2 269 Lawrence Hargrave Drv",
    "sg:city":"Thirroul",
    "sg:classifiers":[
        {
            "category":"Shopping",
            "subcategory":"Clothing, Apparel, & Fashions",
            "type":"Retail Goods"
        }
    ],
    "sg:phone":"+61 2 4268 2882",
    "sg:postcode":"2515",
    "sg:province":"NSW",
    "sg:tags":[
        "lady",
        "wear"
    ],
    "wof:name":"Ekho",
    "wof:placetype":"venue"
},
  "geometry": {"coordinates":[150.92404199999999,-34.314838],"type":"Point"}
}