{
  "type": "Feature",
  "properties": {
    "iso:country":"AU",
    "sg:address":"Unit 1 8k High St",
    "sg:city":"Prahran",
    "sg:classifiers":[
        {
            "category":"Real Estate",
            "subcategory":"Developer",
            "type":"Services"
        }
    ],
    "sg:phone":"+61 3 9529 6677",
    "sg:postcode":"3181",
    "sg:province":"VIC",
    "sg:tags":[
        "development"
    ],
    "wof:name":"Home Leader Pty Ltd",
    "wof:placetype":"venue"
},
  "geometry": {"coordinates":[144.984832764,-37.8508338928],"type":"Point"}
}