{
  "type": "Feature",
  "properties": {
    "addr:full":"PO Box 243 Terrey Hills NSW 2084",
    "addr:postcode":"2084",
    "iso:country":"AU",
    "sg:address":"PO Box 243",
    "sg:city":"Terrey Hills",
    "sg:classifiers":[
        {
            "category":"Government",
            "subcategory":"Post Office",
            "type":"Public Place"
        }
    ],
    "sg:phone":"+61 407 895 330",
    "sg:postcode":"2084",
    "sg:province":"NSW",
    "sg:tags":[
        "horse",
        "dentist"
    ],
    "wof:name":"Peter R Graney",
    "wof:placetype":"venue"
},
  "geometry": {"coordinates":[151.229705811,-33.6837692261],"type":"Point"}
}