{
  "type": "Feature",
  "properties": {
    "addr:full":"700A Inkerman Rd Caulfield VIC 3162",
    "addr:housenumber":"700a",
    "addr:postcode":"3162",
    "addr:street":"Inkerman Rd",
    "iso:country":"AU",
    "sg:address":"700A Inkerman Rd",
    "sg:city":"Caulfield",
    "sg:classifiers":[
        {
            "category":"Health Services",
            "subcategory":"Health Practitioner",
            "type":"Services"
        }
    ],
    "sg:phone":"+61 3 9517 3557",
    "sg:postcode":"3162",
    "sg:province":"VIC",
    "sg:tags":[
        "psychologist"
    ],
    "wof:name":"Andrews Marie",
    "wof:placetype":"venue"
},
  "geometry": {"coordinates":[145.02507019000001,-37.8694229126],"type":"Point"}
}