{
  "type": "Feature",
  "properties": {
    "addr:full":"Cranbourne Park High St Cranbourne VIC 3977",
    "addr:postcode":"3977",
    "addr:street":"High St",
    "iso:country":"AU",
    "sg:address":"Cranbourne Park High St",
    "sg:city":"Cranbourne",
    "sg:classifiers":[
        {
            "category":"Banks & Credit Unions",
            "subcategory":"Financial Services",
            "type":"Services"
        }
    ],
    "sg:phone":"+61 3 5995 0488",
    "sg:postcode":"3977",
    "sg:province":"VIC",
    "sg:tags":[
        "loan",
        "finance",
        "mortgage"
    ],
    "wof:name":"The Money Team Franchising Pty Ltd",
    "wof:placetype":"venue"
},
  "geometry": {"coordinates":[145.283004761,-38.098236084],"type":"Point"}
}