{
  "type": "Feature",
  "properties": {
    "addr:full":"150 Mann St Gosford NSW 2250",
    "addr:housenumber":"150",
    "addr:postcode":"2250",
    "addr:street":"Mann St",
    "iso:country":"AU",
    "sg:address":"150 Mann St",
    "sg:city":"Gosford",
    "sg:classifiers":[
        {
            "category":"Real Estate",
            "subcategory":"Real Estate Agent",
            "type":"Services"
        }
    ],
    "sg:phone":"+61 2 4324 7744",
    "sg:postcode":"2250",
    "sg:province":"NSW",
    "wof:name":"First National Group Of Independent Real Estate Agents Ltd",
    "wof:placetype":"venue"
},
  "geometry": {"coordinates":[151.34194946299999,-33.4257240295],"type":"Point"}
}