{
  "type": "Feature",
  "properties": {
    "addr:full":"28 Primrose St Wingham NSW 2429",
    "addr:housenumber":"28",
    "addr:postcode":"2429",
    "addr:street":"Primrose St",
    "iso:country":"AU",
    "sg:address":"28 Primrose St",
    "sg:city":"Wingham",
    "sg:classifiers":[
        {
            "category":"Shopping",
            "type":"Retail Goods"
        }
    ],
    "sg:phone":"+61 2 6553 4111",
    "sg:postcode":"2429",
    "sg:province":"NSW",
    "sg:tags":[
        "produce",
        "grain"
    ],
    "wof:name":"Taree & Wingham Produce Pty Ltd",
    "wof:placetype":"venue"
},
  "geometry": {"coordinates":[152.372818,-31.865137],"type":"Point"}
}