{
  "type": "Feature",
  "properties": {
    "iso:country":"AU",
    "sg:address":"891 Old Northern Rd",
    "sg:city":"Dural",
    "sg:classifiers":[
        {
            "category":"Retail",
            "subcategory":"Event Space",
            "type":"Services"
        }
    ],
    "sg:phone":"+61 2 9653 9807",
    "sg:postcode":"2158",
    "sg:province":"NSW",
    "sg:tags":[
        "venue",
        "reception",
        "wedding"
    ],
    "wof:name":"Fantasia Retreat",
    "wof:placetype":"venue"
},
  "geometry": {"coordinates":[151.02769470199999,-33.6865997314],"type":"Point"}
}