{
  "type": "Feature",
  "properties": {
    "iso:country":"AU",
    "sg:address":"3 Kelly St",
    "sg:city":"Glenrowan",
    "sg:classifiers":[
        {
            "category":"Building & Trades",
            "subcategory":"Construction",
            "type":"Services"
        }
    ],
    "sg:phone":"+61 419 303 503",
    "sg:postcode":"3675",
    "sg:province":"VIC",
    "sg:tags":[
        "earth",
        "excavating",
        "moving",
        "contractor"
    ],
    "wof:name":"Hansen Engineering Pty Ltd",
    "wof:placetype":"venue"
},
  "geometry": {"coordinates":[146.221054,-36.462273],"type":"Point"}
}