{
  "type": "Feature",
  "properties": {
    "addr:full":"550 Churchill Rd Kilburn SA 5084",
    "addr:housenumber":"550",
    "addr:postcode":"5084",
    "addr:street":"Churchill Rd",
    "iso:country":"AU",
    "sg:address":"550 Churchill Rd",
    "sg:city":"Kilburn",
    "sg:classifiers":[
        {
            "category":"Home & Garden",
            "subcategory":"Hardware",
            "type":"Retail Goods"
        }
    ],
    "sg:phone":"+61 8 8250 8940",
    "sg:postcode":"5084",
    "sg:province":"SA",
    "sg:tags":[
        "pipe",
        "fitting",
        "plastic"
    ],
    "wof:name":"Vinidex Tubemakers Pty Ltd",
    "wof:placetype":"venue"
},
  "geometry": {"coordinates":[138.582397461,-34.8514060974],"type":"Point"}
}