{
  "type": "Feature",
  "properties": {
    "iso:country":"AU",
    "sg:address":"187 South Beach Rd",
    "sg:city":"Bittern",
    "sg:classifiers":[
        {
            "category":"Manufacturing",
            "subcategory":"Food",
            "type":"Manufacturing & Wholesale Goods"
        }
    ],
    "sg:phone":"+61 422 236 309",
    "sg:postcode":"3918",
    "sg:province":"VIC",
    "sg:tags":[
        "function",
        "catering"
    ],
    "wof:name":"The Flying Calamari Brothers",
    "wof:placetype":"venue"
},
  "geometry": {"coordinates":[145.17245483400001,-38.3443527222],"type":"Point"}
}