{
  "type": "Feature",
  "properties": {
    "addr:full":"20 Carlisle St St Kilda VIC 3182",
    "addr:housenumber":"20",
    "addr:postcode":"3182",
    "addr:street":"Carlisle St",
    "iso:country":"AU",
    "sg:address":"20 Carlisle St",
    "sg:city":"St Kilda",
    "sg:classifiers":[
        {
            "category":"Education",
            "subcategory":"Special Training",
            "type":"Public Place"
        }
    ],
    "sg:phone":"+61 3 9534 0224",
    "sg:postcode":"3182",
    "sg:province":"VIC",
    "sg:tags":[
        "drama",
        "tuition"
    ],
    "sg:website":"http://www.nationaltheatre.org.au",
    "wof:name":"National Theatre",
    "wof:placetype":"venue"
},
  "geometry": {"coordinates":[144.981002808,-37.8669776917],"type":"Point"}
}