{
  "type": "Feature",
  "properties": {
    "addr:full":"PO Box 1313 Mackay QLD 4740",
    "addr:postcode":"4740",
    "iso:country":"AU",
    "sg:address":"PO Box 1313",
    "sg:city":"Mackay",
    "sg:classifiers":[
        {
            "category":"Arena",
            "subcategory":"Bull Ring",
            "type":"Entertainment"
        }
    ],
    "sg:phone":"+61 7 4958 3372",
    "sg:postcode":"4740",
    "sg:province":"QLD",
    "sg:tags":[
        "club",
        "bushwalking"
    ],
    "wof:name":"Mackay Bushwalkers Club Inc.",
    "wof:placetype":"venue"
},
  "geometry": {"coordinates":[149.11184700000001,-21.15519],"type":"Point"}
}