{
  "type": "Feature",
  "properties": {
    "addr:full":"286 Frankston-Flinders Rd Frankston South VIC 3199",
    "addr:housenumber":"286",
    "addr:postcode":"3199",
    "addr:street":"Frankston-Flinders Rd",
    "iso:country":"AU",
    "sg:address":"286 Frankston-Flinders Rd",
    "sg:city":"Frankston South",
    "sg:classifiers":[
        {
            "category":"Personal",
            "subcategory":"Massage",
            "type":"Services"
        }
    ],
    "sg:phone":"+61 3 5971 1060",
    "sg:postcode":"3199",
    "sg:province":"VIC",
    "sg:tags":[
        "therapy"
    ],
    "wof:name":"Studio Essence Massage & Day Spa",
    "wof:placetype":"venue"
},
  "geometry": {"coordinates":[145.140823364,-38.1832084656],"type":"Point"}
}