{
  "type": "Feature",
  "properties": {
    "iso:country":"AU",
    "sg:address":"Suite 1, 79 Wheatley Drv",
    "sg:city":"Bullcreek",
    "sg:classifiers":[
        {
            "category":"Health Services",
            "subcategory":"Dentist",
            "type":"Services"
        }
    ],
    "sg:phone":"+61 8 9332 3608",
    "sg:postcode":"6149",
    "sg:province":"WA",
    "wof:name":"Lau Terry Dr",
    "wof:placetype":"venue"
},
  "geometry": {"coordinates":[115.865891,-32.057892],"type":"Point"}
}