{
  "type": "Feature",
  "properties": {
    "addr:full":"8 Glengarriff Crs Montmorency VIC 3094",
    "addr:housenumber":"8",
    "addr:postcode":"3094",
    "addr:street":"Glengarriff Crs",
    "iso:country":"AU",
    "sg:address":"8 Glengarriff Crs",
    "sg:city":"Montmorency",
    "sg:classifiers":[
        {
            "category":"Building & Trades",
            "subcategory":"Construction",
            "type":"Services"
        }
    ],
    "sg:phone":"+61 3 9432 4411",
    "sg:postcode":"3094",
    "sg:province":"VIC",
    "sg:tags":[
        "roof"
    ],
    "wof:name":"Acorn Roofing Contractors",
    "wof:placetype":"venue"
},
  "geometry": {"coordinates":[145.12402343799999,-37.7202911377],"type":"Point"}
}