{
  "type": "Feature",
  "properties": {
    "iso:country":"AU",
    "sg:address":"Suite 9, 2nd Floor 12 North Lakes Drv",
    "sg:city":"North Lakes",
    "sg:classifiers":[
        {
            "category":"Health Services",
            "subcategory":"Chiropractor",
            "type":"Services"
        }
    ],
    "sg:phone":"+61 1300 554 275",
    "sg:postcode":"4509",
    "sg:province":"QLD",
    "wof:name":"Family Wellness Chiropractic",
    "wof:placetype":"venue"
},
  "geometry": {"coordinates":[153.01356506400001,-27.2402191162],"type":"Point"}
}