{
  "type": "Feature",
  "properties": {
    "addr:full":"3rd Floor, Albury Council Chambers, 553 Kiewa Street Albury NSW 2640",
    "addr:housenumber":"553",
    "addr:postcode":"2640",
    "addr:street":"Kiewa Street",
    "iso:country":"AU",
    "sg:address":"3rd Floor, Albury Council Chambers, 553 Kiewa Street",
    "sg:city":"Albury",
    "sg:classifiers":[
        {
            "category":"Professional",
            "subcategory":"Business Services",
            "type":"Services"
        }
    ],
    "sg:phone":"+61 2 6041 2244",
    "sg:postcode":"2640",
    "sg:province":"NSW",
    "sg:tags":[
        "small",
        "advisory"
    ],
    "wof:name":"W J Kell Lawyers",
    "wof:placetype":"venue"
},
  "geometry": {"coordinates":[146.917144775,-36.0710716248],"type":"Point"}
}