{
  "type": "Feature",
  "properties": {
    "addr:full":"Pope St Tallimba NSW 2669",
    "addr:postcode":"2669",
    "addr:street":"Pope St",
    "iso:country":"AU",
    "sg:address":"Pope St",
    "sg:city":"Tallimba",
    "sg:classifiers":[
        {
            "category":"Food & Beverages",
            "subcategory":"Groceries & Convenience Stores",
            "type":"Retail Goods"
        }
    ],
    "sg:phone":"+61 2 6975 7208",
    "sg:postcode":"2669",
    "sg:province":"NSW",
    "wof:name":"Heffer J A",
    "wof:placetype":"venue"
},
  "geometry": {"coordinates":[146.88209533700001,-33.9936294556],"type":"Point"}
}