{
  "type": "Feature",
  "properties": {
    "addr:full":"PO Box 132 Cobbitty NSW 2570",
    "addr:postcode":"2570",
    "iso:country":"AU",
    "sg:address":"PO Box 132",
    "sg:city":"Cobbitty",
    "sg:classifiers":[
        {
            "category":"Manufacturing",
            "subcategory":"Building Materials",
            "type":"Manufacturing & Wholesale Goods"
        }
    ],
    "sg:phone":"+61 2 4651 2396",
    "sg:postcode":"2570",
    "sg:province":"NSW",
    "sg:tags":[
        "equipment",
        "handling"
    ],
    "wof:name":"Mulley Engineering",
    "wof:placetype":"venue"
},
  "geometry": {"coordinates":[150.687255859,-34.0154190063],"type":"Point"}
}