{
  "type": "Feature",
  "properties": {
    "addr:full":"30 Gladstone Rd Biloela QLD 4715",
    "addr:housenumber":"30",
    "addr:postcode":"4715",
    "addr:street":"Gladstone Rd",
    "iso:country":"AU",
    "sg:address":"30 Gladstone Rd",
    "sg:city":"Biloela",
    "sg:classifiers":[
        {
            "category":"Food & Beverages",
            "subcategory":"Supermarket",
            "type":"Retail Goods"
        }
    ],
    "sg:phone":"+61 7 4992 2756",
    "sg:postcode":"4715",
    "sg:province":"QLD",
    "sg:tags":[
        "grocery",
        "store"
    ],
    "wof:name":"Biloela Fivestar Supermarket",
    "wof:placetype":"venue"
},
  "geometry": {"coordinates":[150.516082764,-24.399848938],"type":"Point"}
}