{
  "type": "Feature",
  "properties": {
    "iso:country":"AU",
    "sg:address":"4 Clarke St",
    "sg:city":"Crows Nest",
    "sg:classifiers":[
        {
            "category":"Professional",
            "subcategory":"Art Services",
            "type":"Services"
        }
    ],
    "sg:phone":"+61 2 9437 6621",
    "sg:postcode":"2065",
    "sg:province":"NSW",
    "sg:tags":[
        "picture",
        "frame",
        "framing"
    ],
    "wof:name":"Shore Style Framing",
    "wof:placetype":"venue"
},
  "geometry": {"coordinates":[151.20016479500001,-33.8260154724],"type":"Point"}
}