{
  "type": "Feature",
  "properties": {
    "iso:country":"AU",
    "sg:address":"PO Box 10737",
    "sg:city":"Kalgoorlie Prvte Bxes",
    "sg:classifiers":[
        {
            "category":"Professional",
            "subcategory":"Accounting & Tax Preparation",
            "type":"Services"
        }
    ],
    "sg:phone":"+61 417 094 849",
    "sg:postcode":"6433",
    "sg:province":"WA",
    "sg:tags":[
        "accountant",
        "auditor"
    ],
    "wof:name":"ABL",
    "wof:placetype":"venue"
},
  "geometry": {"coordinates":[121.472297669,-30.74766922],"type":"Point"}
}