{
  "type": "Feature",
  "properties": {
    "addr:full":"Shop 2 12A-B Market City 13-19 Hay St Haymarket NSW 2000",
    "addr:housenumber":"shop 2 12a-b;13-19",
    "addr:postcode":"2000",
    "addr:street":"Market City;Hay St",
    "iso:country":"AU",
    "sg:address":"Shop 2 12A-B Market City 13-19 Hay St",
    "sg:city":"Haymarket",
    "sg:classifiers":[
        {
            "category":"Shopping",
            "subcategory":"Clothing, Apparel, & Fashions",
            "type":"Retail Goods"
        }
    ],
    "sg:phone":"+61 2 9212 5486",
    "sg:postcode":"2000",
    "sg:province":"NSW",
    "sg:tags":[
        "jean"
    ],
    "wof:name":"General Pants Co Pty Ltd",
    "wof:placetype":"venue"
},
  "geometry": {"coordinates":[151.20364379899999,-33.8795204163],"type":"Point"}
}