{
  "type": "Feature",
  "properties": {
    "addr:full":"4324 Main Rd Beauty Point TAS 7270",
    "addr:housenumber":"4324",
    "addr:postcode":"7270",
    "addr:street":"Main Rd",
    "iso:country":"AU",
    "sg:address":"4324 Main Rd",
    "sg:city":"Beauty Point",
    "sg:classifiers":[
        {
            "category":"Autos & Motor Vehicles",
            "subcategory":"Boat Sales",
            "type":"Retail Goods"
        }
    ],
    "sg:phone":"+61 3 6383 1287",
    "sg:postcode":"7270",
    "sg:province":"TAS",
    "sg:tags":[
        "builder",
        "yacht",
        "repairer"
    ],
    "wof:name":"Garry Smedley Boat Building",
    "wof:placetype":"venue"
},
  "geometry": {"coordinates":[146.826705933,-41.1059379578],"type":"Point"}
}