{
  "type": "Feature",
  "properties": {
    "addr:full":"842 Centre Rd Bentleigh East VIC 3165",
    "addr:housenumber":"842",
    "addr:postcode":"3165",
    "addr:street":"Centre Rd",
    "iso:country":"AU",
    "sg:address":"842 Centre Rd",
    "sg:city":"Bentleigh East",
    "sg:classifiers":[
        {
            "category":"Education",
            "subcategory":"School",
            "type":"Public Place"
        }
    ],
    "sg:phone":"+61 3 9579 5068",
    "sg:postcode":"3165",
    "sg:province":"VIC",
    "sg:tags":[
        "co-educational"
    ],
    "wof:name":"St Peter's Primary",
    "wof:placetype":"venue"
},
  "geometry": {"coordinates":[145.071166992,-37.9227638245],"type":"Point"}
}