{
  "type": "Feature",
  "properties": {
    "iso:country":"AU",
    "sg:address":"27 First St",
    "sg:city":"Katherine",
    "sg:classifiers":[
        {
            "category":"Travel",
            "subcategory":"Hotels & Motels",
            "type":"Entertainment"
        }
    ],
    "sg:phone":"+61 8 8971 2288",
    "sg:postcode":"0850",
    "sg:province":"NT",
    "sg:tags":[
        "accommodation"
    ],
    "wof:name":"St Andrews Serviced Apartments",
    "wof:placetype":"venue"
},
  "geometry": {"coordinates":[132.262466,-14.462722],"type":"Point"}
}