{
  "type": "Feature",
  "properties": {
    "addr:full":"18 Cary St Gosford North NSW 2250",
    "addr:housenumber":"18",
    "addr:postcode":"2250",
    "addr:street":"Cary St",
    "iso:country":"AU",
    "sg:address":"18 Cary St",
    "sg:city":"Gosford North",
    "sg:classifiers":[
        {
            "category":"Home & Garden",
            "subcategory":"Carpets & Floor Coverings",
            "type":"Retail Goods"
        }
    ],
    "sg:phone":"+61 2 4323 7513",
    "sg:postcode":"2250",
    "sg:province":"NSW",
    "sg:tags":[
        "mat",
        "matting"
    ],
    "wof:name":"Spring Fresh Dry Cleaners",
    "wof:placetype":"venue"
},
  "geometry": {"coordinates":[151.34808349599999,-33.4115371704],"type":"Point"}
}