{
  "type": "Feature",
  "properties": {
    "iso:country":"AU",
    "sg:address":"1007 Mountain Hwy",
    "sg:city":"Boronia",
    "sg:classifiers":[
        {
            "category":"Autos & Motor Vehicles",
            "subcategory":"Boat Sales",
            "type":"Retail Goods"
        }
    ],
    "sg:phone":"+61 3 9738 1678",
    "sg:postcode":"3155",
    "sg:province":"VIC",
    "sg:tags":[
        "equipment",
        "yacht"
    ],
    "wof:name":"Futura Marine Manufacturing Pty Ltd",
    "wof:placetype":"venue"
},
  "geometry": {"coordinates":[145.29421997099999,-37.838886261],"type":"Point"}
}