{
  "type": "Feature",
  "properties": {
    "addr:full":"1/7 Clare St Bayswater VIC 3153",
    "addr:housenumber":"/ 7",
    "addr:postcode":"3153",
    "addr:street":"Clare St",
    "iso:country":"AU",
    "sg:address":"1/7 Clare St",
    "sg:city":"Bayswater",
    "sg:classifiers":[
        {
            "category":"Shopping",
            "subcategory":"Computers & Home Electronics",
            "type":"Retail Goods"
        }
    ],
    "sg:phone":"+61 1800 463 746",
    "sg:postcode":"3153",
    "sg:province":"VIC",
    "sg:tags":[
        "ergonomics"
    ],
    "wof:name":"Mobility Clinics Of Australia",
    "wof:placetype":"venue"
},
  "geometry": {"coordinates":[145.28179931599999,-37.8425102234],"type":"Point"}
}