{
  "type": "Feature",
  "properties": {
    "addr:full":"9 St Andrews Ave Port Macquarie NSW 2444",
    "addr:housenumber":"9",
    "addr:postcode":"2444",
    "addr:street":"St Andrews Ave",
    "iso:country":"AU",
    "sg:address":"9 St Andrews Ave",
    "sg:city":"Port Macquarie",
    "sg:classifiers":[
        {
            "category":"Health Services",
            "subcategory":"Health Practitioner",
            "type":"Services"
        }
    ],
    "sg:phone":"+61 2 6582 1962",
    "sg:postcode":"2444",
    "sg:province":"NSW",
    "sg:tags":[
        "naturopath"
    ],
    "wof:name":"Jason Carroll Naturopath",
    "wof:placetype":"venue"
},
  "geometry": {"coordinates":[152.91774000000001,-31.47983],"type":"Point"}
}