{
  "type": "Feature",
  "properties": {
    "iso:country":"AU",
    "sg:address":"PO Box 300",
    "sg:city":"Harbord",
    "sg:classifiers":[
        {
            "category":"Home & Garden",
            "subcategory":"Building Materials",
            "type":"Retail Goods"
        }
    ],
    "sg:phone":"+61 410 623 626",
    "sg:postcode":"2096",
    "sg:province":"NSW",
    "sg:tags":[
        "lawn",
        "cutting",
        "maintenance"
    ],
    "wof:name":"Dynamic Endeavours Pty Ltd",
    "wof:placetype":"venue"
},
  "geometry": {"coordinates":[151.28416442899999,-33.7750587463],"type":"Point"}
}