{
  "type": "Feature",
  "properties": {
    "addr:full":"20 Formosa St Sylvania NSW 2224",
    "addr:housenumber":"20",
    "addr:postcode":"2224",
    "addr:street":"Formosa St",
    "iso:country":"AU",
    "sg:address":"20 Formosa St",
    "sg:city":"Sylvania",
    "sg:classifiers":[
        {
            "category":"Personal",
            "subcategory":"Massage",
            "type":"Services"
        }
    ],
    "sg:phone":"+61 2 9544 7133",
    "sg:postcode":"2224",
    "sg:province":"NSW",
    "sg:tags":[
        "therapy"
    ],
    "wof:name":"Southside Goodhealth Natural Therapies Centre",
    "wof:placetype":"venue"
},
  "geometry": {"coordinates":[151.10310363799999,-34.0103797913],"type":"Point"}
}