{
  "type": "Feature",
  "properties": {
    "iso:country":"AU",
    "sg:address":"2 Wilbar Ave",
    "sg:city":"Cronulla",
    "sg:classifiers":[
        {
            "category":"Health Services",
            "subcategory":"Doctor",
            "type":"Services"
        }
    ],
    "sg:phone":"+61 2 9527 6355",
    "sg:postcode":"2230",
    "sg:province":"NSW",
    "sg:tags":[
        "medical",
        "practitioner"
    ],
    "wof:name":"Pitsis George DR",
    "wof:placetype":"venue"
},
  "geometry": {"coordinates":[151.15109252900001,-34.0515518188],"type":"Point"}
}