{
  "type": "Feature",
  "properties": {
    "addr:full":"Lot 1 Newbridge Rd Berkeley Vale NSW 2261",
    "addr:housenumber":"1",
    "addr:postcode":"2261",
    "addr:street":"Newbridge Rd",
    "iso:country":"AU",
    "sg:address":"Lot 1 Newbridge Rd",
    "sg:city":"Berkeley Vale",
    "sg:classifiers":[
        {
            "category":"Building & Trades",
            "subcategory":"Construction",
            "type":"Services"
        }
    ],
    "sg:phone":"+61 2 4388 6811",
    "sg:postcode":"2261",
    "sg:province":"NSW",
    "sg:tags":[
        "earth",
        "excavating",
        "moving",
        "contractor"
    ],
    "wof:name":"Pryor Plant Hire",
    "wof:placetype":"venue"
},
  "geometry": {"coordinates":[151.42103599999999,-33.325459],"type":"Point"}
}