{
  "type": "Feature",
  "properties": {
    "iso:country":"AU",
    "sg:address":"228 Forestry Rd",
    "sg:city":"Bluewater",
    "sg:classifiers":[
        {
            "category":"Farming",
            "subcategory":"Nursery",
            "type":"Manufacturing & Wholesale Goods"
        }
    ],
    "sg:phone":"+61 417 007 490",
    "sg:postcode":"4818",
    "sg:province":"QLD",
    "wof:name":"Bluewater Palms",
    "wof:placetype":"venue"
},
  "geometry": {"coordinates":[146.53225699999999,-19.186003],"type":"Point"}
}