{
  "type": "Feature",
  "properties": {
    "addr:full":"PO Box 1277 West Perth WA 6005",
    "addr:postcode":"6005",
    "iso:country":"AU",
    "sg:address":"PO Box 1277",
    "sg:city":"West Perth",
    "sg:classifiers":[
        {
            "category":"Professional",
            "subcategory":"Computer Services",
            "type":"Services"
        }
    ],
    "sg:phone":"+61 8 9388 1844",
    "sg:postcode":"6005",
    "sg:province":"WA",
    "sg:tags":[
        "package",
        "software"
    ],
    "wof:name":"Cashflow Manager",
    "wof:placetype":"venue"
},
  "geometry": {"coordinates":[115.8465271,-31.9449996948],"type":"Point"}
}