{
  "type": "Feature",
  "properties": {
    "addr:full":"MS 582 Connoly Rd Geham QLD 4352",
    "addr:housenumber":"582",
    "addr:postcode":"4352",
    "addr:street":"Connoly Rd",
    "iso:country":"AU",
    "sg:address":"MS 582 Connoly Rd",
    "sg:city":"Geham",
    "sg:classifiers":[
        {
            "category":"Manufacturing",
            "subcategory":"Tools & Machinery",
            "type":"Manufacturing & Wholesale Goods"
        }
    ],
    "sg:phone":"+61 7 4696 6158",
    "sg:postcode":"4352",
    "sg:province":"QLD",
    "sg:tags":[
        "earth",
        "excavating",
        "moving",
        "equipment"
    ],
    "wof:name":"Gary Patwald Earthmoving",
    "wof:placetype":"venue"
},
  "geometry": {"coordinates":[151.99955700000001,-27.391001],"type":"Point"}
}