{
  "type": "Feature",
  "properties": {
    "addr:full":"67 Clyde St Myrtleford VIC 3737",
    "addr:housenumber":"67",
    "addr:postcode":"3737",
    "addr:street":"Clyde St",
    "iso:country":"AU",
    "sg:address":"67 Clyde St",
    "sg:city":"Myrtleford",
    "sg:classifiers":[
        {
            "category":"Shopping",
            "subcategory":"Clothing, Apparel, & Fashions",
            "type":"Retail Goods"
        }
    ],
    "sg:phone":"+61 3 5752 2459",
    "sg:postcode":"3737",
    "sg:province":"VIC",
    "sg:tags":[
        "menswear"
    ],
    "wof:name":"Cartwright Fashions",
    "wof:placetype":"venue"
},
  "geometry": {"coordinates":[146.726806641,-36.5623130798],"type":"Point"}
}