{
  "type": "Feature",
  "properties": {
    "addr:full":"6 Ringwood St Ringwood VIC 3134",
    "addr:housenumber":"6",
    "addr:postcode":"3134",
    "addr:street":"Ringwood St",
    "iso:country":"AU",
    "sg:address":"6 Ringwood St",
    "sg:city":"Ringwood",
    "sg:classifiers":[
        {
            "category":"Personal",
            "subcategory":"Hair Removal",
            "type":"Services"
        }
    ],
    "sg:phone":"+61 3 9870 9122",
    "sg:postcode":"3134",
    "sg:province":"VIC",
    "wof:name":"Linnie Pohan",
    "wof:placetype":"venue"
},
  "geometry": {"coordinates":[145.22720336899999,-37.8151245117],"type":"Point"}
}