{
  "type": "Feature",
  "properties": {
    "iso:country":"AU",
    "sg:address":"10 Kennett St",
    "sg:city":"Kadina",
    "sg:classifiers":[
        {
            "category":"Wholesale",
            "subcategory":"Scrap",
            "type":"Manufacturing & Wholesale Goods"
        }
    ],
    "sg:phone":"+61 8 8821 1488",
    "sg:postcode":"5554",
    "sg:province":"SA",
    "sg:tags":[
        "merchant",
        "metal"
    ],
    "wof:name":"Copper Triangle Scrap Metal & Resale Steel",
    "wof:placetype":"venue"
},
  "geometry": {"coordinates":[137.71273803700001,-33.9715003967],"type":"Point"}
}