{
  "type": "Feature",
  "properties": {
    "iso:country":"AU",
    "sg:address":"87 Prospect Rd",
    "sg:city":"Garden Suburb",
    "sg:classifiers":[
        {
            "category":"Building & Trades",
            "subcategory":"Construction",
            "type":"Services"
        }
    ],
    "sg:phone":"+61 407 212 855",
    "sg:postcode":"2289",
    "sg:province":"NSW",
    "sg:tags":[
        "earth",
        "excavating",
        "moving",
        "contractor"
    ],
    "wof:name":"Walker Bruce E",
    "wof:placetype":"venue"
},
  "geometry": {"coordinates":[151.674957275,-32.9442977905],"type":"Point"}
}