{
  "type": "Feature",
  "properties": {
    "iso:country":"AU",
    "sg:address":"140 Eaglehawk Rd",
    "sg:city":"Bendigo",
    "sg:classifiers":[
        {
            "category":"Train Station",
            "subcategory":"Rail",
            "type":"Transportation"
        }
    ],
    "sg:phone":"+61 417 551 344",
    "sg:postcode":"3550",
    "sg:province":"VIC",
    "sg:tags":[
        "repair",
        "vinyl",
        "welding"
    ],
    "wof:name":"Ultra Bond Bendigo",
    "wof:placetype":"venue"
},
  "geometry": {"coordinates":[144.26632690400001,-36.7560119629],"type":"Point"}
}