{
  "type": "Feature",
  "properties": {
    "addr:full":"34 Knight St North Rockhampton QLD 4701",
    "addr:housenumber":"34",
    "addr:postcode":"4701",
    "addr:street":"Knight St North",
    "iso:country":"AU",
    "sg:address":"34 Knight St",
    "sg:city":"North Rockhampton",
    "sg:classifiers":[
        {
            "category":"Juice Bar",
            "subcategory":"None",
            "type":"Food & Drink"
        }
    ],
    "sg:phone":"+61 7 4928 3355",
    "sg:postcode":"4701",
    "sg:province":"QLD",
    "sg:tags":[
        "merchant",
        "fruit",
        "processor"
    ],
    "wof:name":"The Juice Factory",
    "wof:placetype":"venue"
},
  "geometry": {"coordinates":[150.514526367,-23.3618183136],"type":"Point"}
}