{
  "type": "Feature",
  "properties": {
    "addr:full":"Unit 20 2 Bishop St St Peters NSW 2044",
    "addr:housenumber":"2",
    "addr:postcode":"2044",
    "addr:street":"Bishop St",
    "iso:country":"AU",
    "sg:address":"Unit 20 2 Bishop St St",
    "sg:city":"Peters",
    "sg:classifiers":[
        {
            "category":"Professional",
            "type":"Services"
        }
    ],
    "sg:phone":"+61 2 9516 0005",
    "sg:postcode":"2044",
    "sg:province":"NSW",
    "sg:tags":[
        "shop",
        "fitting"
    ],
    "wof:name":"Star Commercial Interiors",
    "wof:placetype":"venue"
},
  "geometry": {"coordinates":[151.17846700000001,-33.913795],"type":"Point"}
}