{
  "type": "Feature",
  "properties": {
    "iso:country":"AU",
    "sg:address":"13a Halley Rd",
    "sg:city":"Balcatta",
    "sg:classifiers":[
        {
            "category":"Real Estate",
            "subcategory":"Architect",
            "type":"Services"
        }
    ],
    "sg:phone":"+61 8 9345 1611",
    "sg:postcode":"6021",
    "sg:province":"WA",
    "sg:tags":[
        "magnet",
        "magnetic",
        "material"
    ],
    "wof:name":"Action Graphics",
    "wof:placetype":"venue"
},
  "geometry": {"coordinates":[115.825950623,-31.8616733551],"type":"Point"}
}