{
  "type": "Feature",
  "properties": {
    "iso:country":"AU",
    "sg:address":"22 Pine Av",
    "sg:city":"Newstead",
    "sg:classifiers":[
        {
            "category":"Health Services",
            "subcategory":"Doctor",
            "type":"Services"
        }
    ],
    "sg:phone":"+61 3 6334 0333",
    "sg:postcode":"7250",
    "sg:province":"TAS",
    "sg:tags":[
        "occupational",
        "safety"
    ],
    "wof:name":"Australian Workforce Assessors",
    "wof:placetype":"venue"
},
  "geometry": {"coordinates":[147.16506957999999,-41.4393997192],"type":"Point"}
}