{
  "type": "Feature",
  "properties": {
    "addr:full":"24 Clark Rd Grafton NSW 2460",
    "addr:housenumber":"24",
    "addr:postcode":"2460",
    "addr:street":"Clark Rd",
    "iso:country":"AU",
    "sg:address":"24 Clark Rd",
    "sg:city":"Grafton",
    "sg:classifiers":[
        {
            "category":"Retail",
            "subcategory":"Storage",
            "type":"Services"
        }
    ],
    "sg:phone":"+61 2 6644 7840",
    "sg:postcode":"2460",
    "sg:province":"NSW",
    "wof:name":"Gortons Paint & Panel",
    "wof:placetype":"venue"
},
  "geometry": {"coordinates":[152.94154357900001,-29.620967865],"type":"Point"}
}