{
  "type": "Feature",
  "properties": {
    "addr:full":"44 Nepean Hwy Mentone VIC 3194",
    "addr:housenumber":"44",
    "addr:postcode":"3194",
    "addr:street":"Nepean Hwy",
    "iso:country":"AU",
    "sg:address":"44 Nepean Hwy",
    "sg:city":"Mentone",
    "sg:classifiers":[
        {
            "category":"Home & Garden",
            "subcategory":"Carpets & Floor Coverings",
            "type":"Retail Goods"
        }
    ],
    "sg:phone":"+61 3 9503 0325",
    "sg:postcode":"3194",
    "sg:province":"VIC",
    "sg:tags":[
        "double",
        "window",
        "glazed"
    ],
    "wof:name":"Marvonite",
    "wof:placetype":"venue"
},
  "geometry": {"coordinates":[145.065963745,-37.9764060974],"type":"Point"}
}