{
  "type": "Feature",
  "properties": {
    "addr:full":"41 Crestwood Drv Molendinar QLD 4214",
    "addr:housenumber":"41",
    "addr:postcode":"4214",
    "addr:street":"Crestwood Drv",
    "iso:country":"AU",
    "sg:address":"41 Crestwood Drv",
    "sg:city":"Molendinar",
    "sg:classifiers":[
        {
            "category":"Personal",
            "subcategory":"Beauty Salon",
            "type":"Services"
        }
    ],
    "sg:phone":"+61 7 5597 5918",
    "sg:postcode":"4214",
    "sg:province":"QLD",
    "wof:name":"Paradise Beauty Clinic",
    "wof:placetype":"venue"
},
  "geometry": {"coordinates":[153.37167358400001,-27.9696121216],"type":"Point"}
}