{
  "type": "Feature",
  "properties": {
    "iso:country":"AU",
    "sg:address":"Main Rd",
    "sg:city":"Wollombi",
    "sg:classifiers":[
        {
            "category":"Food & Beverages",
            "subcategory":"Groceries & Convenience Stores",
            "type":"Retail Goods"
        }
    ],
    "sg:phone":"+61 2 4998 3230",
    "sg:postcode":"2325",
    "sg:province":"NSW",
    "wof:name":"Wollombi General Store",
    "wof:placetype":"venue"
},
  "geometry": {"coordinates":[151.28518676799999,-32.9064216614],"type":"Point"}
}