{
  "type": "Feature",
  "properties": {
    "addr:full":"22 Haynes Ave Seven Hills NSW 2147",
    "addr:housenumber":"22",
    "addr:postcode":"2147",
    "addr:street":"Haynes Ave",
    "iso:country":"AU",
    "sg:address":"22 Haynes Ave",
    "sg:city":"Seven Hills",
    "sg:classifiers":[
        {
            "category":"Health Services",
            "subcategory":"Podiatrist",
            "type":"Services"
        }
    ],
    "sg:phone":"+61 2 9920 0303",
    "sg:postcode":"2147",
    "sg:province":"NSW",
    "sg:tags":[
        "cap",
        "hat",
        "renovation",
        "retail"
    ],
    "wof:name":"Parramatta Hatters",
    "wof:placetype":"venue"
},
  "geometry": {"coordinates":[150.92689514200001,-33.7680168152],"type":"Point"}
}