{
  "type": "Feature",
  "properties": {
    "addr:full":"Sale Maffra Rd Maffra VIC 3860",
    "addr:postcode":"3860",
    "addr:street":"Maffra Rd",
    "iso:country":"AU",
    "sg:address":"Sale Maffra Rd",
    "sg:city":"Maffra",
    "sg:classifiers":[
        {
            "category":"Food & Beverages",
            "subcategory":"Fruits & Vegetables",
            "type":"Retail Goods"
        }
    ],
    "sg:phone":"+61 3 5141 1756",
    "sg:postcode":"3860",
    "sg:province":"VIC",
    "sg:tags":[
        "grower"
    ],
    "wof:name":"All Seasons Farm Produce",
    "wof:placetype":"venue"
},
  "geometry": {"coordinates":[146.98373413100001,-37.9716835022],"type":"Point"}
}