{
  "type": "Feature",
  "properties": {
    "addr:full":"17 McDougall St Charnwood ACT 2615",
    "addr:housenumber":"17",
    "addr:postcode":"2615",
    "addr:street":"Mcdougall St",
    "iso:country":"AU",
    "sg:address":"17 McDougall St",
    "sg:city":"Charnwood",
    "sg:classifiers":[
        {
            "category":"Personal",
            "subcategory":"Massage",
            "type":"Services"
        }
    ],
    "sg:phone":"+61 2 6258 2635",
    "sg:postcode":"2615",
    "sg:province":"ACT",
    "sg:tags":[
        "therapy"
    ],
    "wof:name":"Healing Lakshmi",
    "wof:placetype":"venue"
},
  "geometry": {"coordinates":[149.04019165,-35.2021369934],"type":"Point"}
}