{
  "type": "Feature",
  "properties": {
    "iso:country":"AU",
    "sg:address":"31 Palmer St",
    "sg:city":"South Townsville",
    "sg:classifiers":[
        {
            "category":"Travel",
            "subcategory":"Hotels & Motels",
            "type":"Entertainment"
        }
    ],
    "sg:phone":"+61 7 4771 4351",
    "sg:postcode":"4810",
    "sg:province":"QLD",
    "sg:tags":[
        "accommodation"
    ],
    "wof:name":"Shamrock Hotel",
    "wof:placetype":"venue"
},
  "geometry": {"coordinates":[146.821564,-19.26012],"type":"Point"}
}