{
  "type": "Feature",
  "properties": {
    "iso:country":"AU",
    "sg:address":"34 Moore St",
    "sg:city":"Moe",
    "sg:classifiers":[
        {
            "category":"Shopping",
            "subcategory":"Jewelry",
            "type":"Retail Goods"
        }
    ],
    "sg:phone":"+61 3 5126 1754",
    "sg:postcode":"3825",
    "sg:province":"VIC",
    "sg:tags":[
        "jeweller"
    ],
    "wof:name":"Showcase Jewellers",
    "wof:placetype":"venue"
},
  "geometry": {"coordinates":[146.26101700000001,-38.175003],"type":"Point"}
}