{
  "type": "Feature",
  "properties": {
    "addr:full":"20/ 50 Stanley St East Sydney NSW 2010",
    "addr:housenumber":"20 / 50",
    "addr:postcode":"2010",
    "addr:street":"Stanley St East",
    "iso:country":"AU",
    "sg:address":"20/ 50 Stanley St",
    "sg:city":"East Sydney",
    "sg:classifiers":[
        {
            "category":"Real Estate",
            "subcategory":"Architect",
            "type":"Services"
        }
    ],
    "sg:phone":"+61 2 9366 1133",
    "sg:postcode":"2010",
    "sg:province":"NSW",
    "wof:name":"JPR Architects",
    "wof:placetype":"venue"
},
  "geometry": {"coordinates":[151.214569092,-33.8755378723],"type":"Point"}
}