{
  "type": "Feature",
  "properties": {
    "addr:full":"Unit 2, 158- 168 Browns Rd Noble Park VIC 3174",
    "addr:housenumber":"158 168",
    "addr:postcode":"3174",
    "addr:street":"Browns Rd",
    "iso:country":"AU",
    "sg:address":"Unit 2, 158- 168 Browns Rd",
    "sg:city":"Noble Park",
    "sg:classifiers":[
        {
            "category":"Shopping",
            "subcategory":"Crafts & Fabrics",
            "type":"Retail Goods"
        }
    ],
    "sg:phone":"+61 3 8793 5000",
    "sg:postcode":"3174",
    "sg:province":"VIC",
    "sg:tags":[
        "florist",
        "supply"
    ],
    "wof:name":"Ribtex International",
    "wof:placetype":"venue"
},
  "geometry": {"coordinates":[145.18206787099999,-37.9516334534],"type":"Point"}
}