{
  "type": "Feature",
  "properties": {
    "iso:country":"AU",
    "sg:address":"202A Cobden St",
    "sg:city":"Ballarat",
    "sg:classifiers":[
        {
            "category":"Real Estate",
            "subcategory":"Architect",
            "type":"Services"
        }
    ],
    "sg:phone":"+61 3 5331 1736",
    "sg:postcode":"3350",
    "sg:province":"VIC",
    "sg:tags":[
        "building",
        "designer"
    ],
    "wof:name":"Andrea Wilkinson Building Design",
    "wof:placetype":"venue"
},
  "geometry": {"coordinates":[143.857162,-37.577934],"type":"Point"}
}