{
  "type": "Feature",
  "properties": {
    "addr:full":"58 Brooks St Bowen Hills QLD 4006",
    "addr:housenumber":"58",
    "addr:postcode":"4006",
    "addr:street":"Brooks St",
    "iso:country":"AU",
    "sg:address":"58 Brooks St",
    "sg:city":"Bowen Hills",
    "sg:classifiers":[
        {
            "category":"Banks & Credit Unions",
            "subcategory":"Atm",
            "type":"Services"
        }
    ],
    "sg:phone":"+61 7 3620 5800",
    "sg:postcode":"4006",
    "sg:province":"QLD",
    "sg:tags":[
        "detector",
        "gas"
    ],
    "wof:name":"Control Equipment Pty Ltd",
    "wof:placetype":"venue"
},
  "geometry": {"coordinates":[153.03582763700001,-27.4513473511],"type":"Point"}
}