{
  "type": "Feature",
  "properties": {
    "addr:full":"16 Kelly Ave Hampton East VIC 3188",
    "addr:housenumber":"16",
    "addr:postcode":"3188",
    "addr:street":"Kelly Ave",
    "iso:country":"AU",
    "sg:address":"16 Kelly Ave",
    "sg:city":"Hampton East",
    "sg:classifiers":[
        {
            "category":"Manufacturing",
            "subcategory":"Paper Products",
            "type":"Manufacturing & Wholesale Goods"
        }
    ],
    "sg:phone":"+61 3 9555 7332",
    "sg:postcode":"3188",
    "sg:province":"VIC",
    "sg:tags":[
        "disposable"
    ],
    "wof:name":"Koala Bags",
    "wof:placetype":"venue"
},
  "geometry": {"coordinates":[145.02655029300001,-37.9334030151],"type":"Point"}
}