{
  "type": "Feature",
  "properties": {
    "addr:full":"120 Warren Rd Smithfield NSW 2164",
    "addr:housenumber":"120",
    "addr:postcode":"2164",
    "addr:street":"Warren Rd",
    "iso:country":"AU",
    "sg:address":"120 Warren Rd",
    "sg:city":"Smithfield",
    "sg:classifiers":[
        {
            "category":"Commercial Area",
            "type":"Public Place"
        }
    ],
    "sg:phone":"+61 2 9632 6342",
    "sg:postcode":"2164",
    "sg:province":"NSW",
    "sg:tags":[
        "heavy",
        "carrier"
    ],
    "wof:name":"Olsson Bros Carriers & Crane Hire",
    "wof:placetype":"venue"
},
  "geometry": {"coordinates":[150.94569397000001,-33.8488502502],"type":"Point"}
}