{
  "type": "Feature",
  "properties": {
    "addr:full":"27 Tedder Ave Main Beach QLD 4217",
    "addr:housenumber":"27",
    "addr:postcode":"4217",
    "addr:street":"Tedder Ave",
    "iso:country":"AU",
    "sg:address":"27 Tedder Ave",
    "sg:city":"Main Beach",
    "sg:classifiers":[
        {
            "category":"Restaurant",
            "type":"Food & Drink"
        }
    ],
    "sg:phone":"+61 7 5571 1777",
    "sg:postcode":"4217",
    "sg:province":"QLD",
    "sg:website":"http://www.cuisineguide.com.au/montegos/",
    "wof:name":"Montegos Of Main Beach",
    "wof:placetype":"venue"
},
  "geometry": {"coordinates":[153.42523193400001,-27.9784660339],"type":"Point"}
}