{
  "type": "Feature",
  "properties": {
    "addr:full":"44 Sapphire Coast Drv Merimbula NSW 2548",
    "addr:housenumber":"44",
    "addr:postcode":"2548",
    "addr:street":"Sapphire Coast Drv",
    "iso:country":"AU",
    "sg:address":"44 Sapphire Coast Drv",
    "sg:city":"Merimbula",
    "sg:classifiers":[
        {
            "category":"Building & Trades",
            "subcategory":"Construction",
            "type":"Services"
        }
    ],
    "sg:phone":"+61 2 6495 9183",
    "sg:postcode":"2548",
    "sg:province":"NSW",
    "sg:tags":[
        "stonework",
        "stone",
        "mason"
    ],
    "wof:name":"Ian Bradley",
    "wof:placetype":"venue"
},
  "geometry": {"coordinates":[149.90667724599999,-36.8831176758],"type":"Point"}
}