{
  "type": "Feature",
  "properties": {
    "addr:full":"Shop34, Wilson St Burnie TAS 7320",
    "addr:postcode":"7320",
    "addr:street":"Wilson St",
    "iso:country":"AU",
    "sg:address":"Shop34, Wilson St",
    "sg:city":"Burnie",
    "sg:classifiers":[
        {
            "category":"Shopping",
            "subcategory":"Clothing, Apparel, & Fashions",
            "type":"Retail Goods"
        }
    ],
    "sg:phone":"+61 3 6431 2384",
    "sg:postcode":"7320",
    "sg:province":"TAS",
    "sg:tags":[
        "lady",
        "wear"
    ],
    "wof:name":"Sussan",
    "wof:placetype":"venue"
},
  "geometry": {"coordinates":[145.905136,-41.060074],"type":"Point"}
}