{
  "type": "Feature",
  "properties": {
    "addr:full":"189 Flinders La Melbourne VIC 3000",
    "addr:housenumber":"189",
    "addr:postcode":"3000",
    "addr:street":"Flinders La",
    "iso:country":"AU",
    "sg:address":"189 Flinders La",
    "sg:city":"Melbourne",
    "sg:classifiers":[
        {
            "category":"Building & Trades",
            "subcategory":"Landscaping Services",
            "type":"Services"
        }
    ],
    "sg:phone":"+61 3 9663 9900",
    "sg:postcode":"3000",
    "sg:province":"VIC",
    "sg:tags":[
        "consultant"
    ],
    "wof:name":"McQuarie Property Inspections",
    "wof:placetype":"venue"
},
  "geometry": {"coordinates":[144.968185425,-37.8162536621],"type":"Point"}
}