{
  "type": "Feature",
  "properties": {
    "addr:full":"66 Osborne St Nowra NSW 2541",
    "addr:housenumber":"66",
    "addr:postcode":"2541",
    "addr:street":"Osborne St",
    "iso:country":"AU",
    "sg:address":"66 Osborne St",
    "sg:city":"Nowra",
    "sg:classifiers":[
        {
            "category":"Health Services",
            "subcategory":"Dentist",
            "type":"Services"
        }
    ],
    "sg:phone":"+61 2 4421 4000",
    "sg:postcode":"2541",
    "sg:province":"NSW",
    "sg:tags":[
        "state",
        "orthodontist",
        "qld",
        "exc"
    ],
    "wof:name":"LiveWire Orthodontics",
    "wof:placetype":"venue"
},
  "geometry": {"coordinates":[150.59791564899999,-34.8761253357],"type":"Point"}
}