{
  "type": "Feature",
  "properties": {
    "addr:full":"108 Wallace St Braidwood NSW 2622",
    "addr:housenumber":"108",
    "addr:postcode":"2622",
    "addr:street":"Wallace St",
    "iso:country":"AU",
    "sg:address":"108 Wallace St",
    "sg:city":"Braidwood",
    "sg:classifiers":[
        {
            "category":"Personal",
            "subcategory":"Beauty Salon",
            "type":"Services"
        }
    ],
    "sg:phone":"+61 2 4842 2033",
    "sg:postcode":"2622",
    "sg:province":"NSW",
    "sg:tags":[
        "hairdresser"
    ],
    "wof:name":"Kate's Mane Line Hair Fashions",
    "wof:placetype":"venue"
},
  "geometry": {"coordinates":[149.801147461,-35.4371261597],"type":"Point"}
}