{
  "type": "Feature",
  "properties": {
    "addr:full":"1st Floor, 14 Pakington St St Kilda VIC 3182",
    "addr:housenumber":"14",
    "addr:postcode":"3182",
    "addr:street":"Pakington St",
    "iso:country":"AU",
    "sg:address":"1st Floor, 14 Pakington St St",
    "sg:city":"Kilda",
    "sg:classifiers":[
        {
            "category":"Wholesale",
            "subcategory":"Painting Supplies",
            "type":"Manufacturing & Wholesale Goods"
        }
    ],
    "sg:phone":"+61 3 9534 9944",
    "sg:postcode":"3182",
    "sg:province":"VIC",
    "sg:tags":[
        "wholesaler",
        "paint",
        "mfrs"
    ],
    "wof:name":"Handycan Paint Products Pty Ltd",
    "wof:placetype":"venue"
},
  "geometry": {"coordinates":[144.98664855999999,-37.8656349182],"type":"Point"}
}