{
  "type": "Feature",
  "properties": {
    "iso:country":"AU",
    "sg:address":"4 Mcglone St",
    "sg:city":"Mitcham",
    "sg:classifiers":[
        {
            "category":"Retail",
            "subcategory":"Auto Repair",
            "type":"Services"
        }
    ],
    "sg:phone":"+61 3 9872 3011",
    "sg:postcode":"3132",
    "sg:province":"VIC",
    "sg:tags":[
        "repairer",
        "motor",
        "engineer"
    ],
    "wof:name":"Hardcore 4X4",
    "wof:placetype":"venue"
},
  "geometry": {"coordinates":[145.18865966800001,-37.8173675537],"type":"Point"}
}