{
  "type": "Feature",
  "properties": {
    "addr:full":"136 Paul Coe Crs Ngunnawal ACT 2913",
    "addr:housenumber":"136",
    "addr:postcode":"2913",
    "addr:street":"Paul Coe Crs",
    "iso:country":"AU",
    "sg:address":"136 Paul Coe Crs",
    "sg:city":"Ngunnawal",
    "sg:classifiers":[
        {
            "category":"Building & Trades",
            "subcategory":"Construction",
            "type":"Services"
        }
    ],
    "sg:phone":"+61 412 265 402",
    "sg:postcode":"2913",
    "sg:province":"ACT",
    "sg:tags":[
        "joiner",
        "carpenter"
    ],
    "wof:name":"Golding's Carpentry Pty Ltd",
    "wof:placetype":"venue"
},
  "geometry": {"coordinates":[149.108032227,-35.173160553],"type":"Point"}
}