{
  "type": "Feature",
  "properties": {
    "addr:full":"15 Nisbet Rd Applecross WA 6153",
    "addr:housenumber":"15",
    "addr:postcode":"6153",
    "addr:street":"Nisbet Rd",
    "iso:country":"AU",
    "sg:address":"15 Nisbet Rd",
    "sg:city":"Applecross",
    "sg:classifiers":[
        {
            "category":"Landmark",
            "subcategory":"Square",
            "type":"Public Place"
        }
    ],
    "sg:phone":"+61 403 984 840",
    "sg:postcode":"6153",
    "sg:province":"WA",
    "sg:tags":[
        "lampshade"
    ],
    "wof:name":"Jeni-An Lampshades",
    "wof:placetype":"venue"
},
  "geometry": {"coordinates":[115.841461,-32.007778],"type":"Point"}
}