{
  "type": "Feature",
  "properties": {
    "addr:full":"157 Prince Edward Ave Culburra Beach NSW 2540",
    "addr:housenumber":"157",
    "addr:postcode":"2540",
    "addr:street":"Prince Edward Ave",
    "iso:country":"AU",
    "sg:address":"157 Prince Edward Ave",
    "sg:city":"Culburra Beach",
    "sg:classifiers":[
        {
            "category":"Food & Beverages",
            "subcategory":"Fruits & Vegetables",
            "type":"Retail Goods"
        }
    ],
    "sg:phone":"+61 2 4447 2364",
    "sg:postcode":"2540",
    "sg:province":"NSW",
    "sg:tags":[
        "greengrocer",
        "fruiterer"
    ],
    "wof:name":"Culburra Fruit Shop",
    "wof:placetype":"venue"
},
  "geometry": {"coordinates":[150.758468628,-34.9303436279],"type":"Point"}
}