{
  "type": "Feature",
  "properties": {
    "addr:full":"206 Clarinda St Parkes NSW 2870",
    "addr:housenumber":"206",
    "addr:postcode":"2870",
    "addr:street":"Clarinda St",
    "iso:country":"AU",
    "sg:address":"206 Clarinda St",
    "sg:city":"Parkes",
    "sg:classifiers":[
        {
            "category":"Professional",
            "subcategory":"Employment Agencies",
            "type":"Services"
        }
    ],
    "sg:phone":"+61 2 6862 5485",
    "sg:postcode":"2870",
    "sg:province":"NSW",
    "sg:tags":[
        "hire",
        "labour",
        "contractor"
    ],
    "wof:name":"Inland Employment Services",
    "wof:placetype":"venue"
},
  "geometry": {"coordinates":[148.174835,-33.137104],"type":"Point"}
}