{
  "type": "Feature",
  "properties": {
    "addr:full":"44 Morrisset St Bathurst NSW 2795",
    "addr:housenumber":"44",
    "addr:postcode":"2795",
    "addr:street":"Morrisset St",
    "iso:country":"AU",
    "sg:address":"44 Morrisset St",
    "sg:city":"Bathurst",
    "sg:classifiers":[
        {
            "category":"Travel",
            "subcategory":"Hotels & Motels",
            "type":"Entertainment"
        }
    ],
    "sg:phone":"+61 2 6332 1777",
    "sg:postcode":"2795",
    "sg:province":"NSW",
    "sg:tags":[
        "accommodation"
    ],
    "wof:name":"Bathurst Apartments",
    "wof:placetype":"venue"
},
  "geometry": {"coordinates":[149.55354309099999,-33.5437316895],"type":"Point"}
}