{
  "type": "Feature",
  "properties": {
    "addr:full":"Level 1/ 133 Mary St Brisbane QLD 4000",
    "addr:housenumber":"/ 133",
    "addr:postcode":"4000",
    "addr:street":"Mary St",
    "iso:country":"AU",
    "sg:address":"Level 1/ 133 Mary St",
    "sg:city":"Brisbane",
    "sg:classifiers":[
        {
            "category":"Professional",
            "subcategory":"Employment Agencies",
            "type":"Services"
        }
    ],
    "sg:phone":"+61 7 3236 1655",
    "sg:postcode":"4000",
    "sg:province":"QLD",
    "sg:tags":[
        "hire",
        "labour",
        "contractor"
    ],
    "wof:name":"Corporate Outsourcing Pty Ltd",
    "wof:placetype":"venue"
},
  "geometry": {"coordinates":[153.02867126500001,-27.4711551666],"type":"Point"}
}