{
  "type": "Feature",
  "properties": {
    "iso:country":"AU",
    "sg:address":"665 Mt Alexander Rd",
    "sg:city":"Moonee Ponds",
    "sg:classifiers":[
        {
            "category":"Health Services",
            "subcategory":"Dentist",
            "type":"Services"
        }
    ],
    "sg:phone":"+61 3 9375 1600",
    "sg:postcode":"3039",
    "sg:province":"VIC",
    "wof:name":"The Look Orthodontics",
    "wof:placetype":"venue"
},
  "geometry": {"coordinates":[144.923935,-37.765903],"type":"Point"}
}