{
  "type": "Feature",
  "properties": {
    "addr:full":"217 Gympie Rd Tinana QLD 4650",
    "addr:housenumber":"217",
    "addr:postcode":"4650",
    "addr:street":"Gympie Rd",
    "iso:country":"AU",
    "sg:address":"217 Gympie Rd",
    "sg:city":"Tinana",
    "sg:classifiers":[
        {
            "category":"Building & Trades",
            "subcategory":"Landscaping Services",
            "type":"Services"
        }
    ],
    "sg:phone":"+61 7 4121 0374",
    "sg:postcode":"4650",
    "sg:province":"QLD",
    "sg:tags":[
        "stump",
        "tree",
        "felling",
        "removal"
    ],
    "wof:name":"Eastern Tree Service",
    "wof:placetype":"venue"
},
  "geometry": {"coordinates":[152.681793,-25.546154],"type":"Point"}
}