{
  "type": "Feature",
  "properties": {
    "iso:country":"AU",
    "sg:address":"9 Austin St",
    "sg:city":"Footscray",
    "sg:classifiers":[
        {
            "category":"Health Services",
            "subcategory":"Health Practitioner",
            "type":"Services"
        }
    ],
    "sg:phone":"+61 3 9687 4173",
    "sg:postcode":"3011",
    "sg:province":"VIC",
    "sg:tags":[
        "osteopath"
    ],
    "wof:name":"Acupoint Chinese Natural Therapy",
    "wof:placetype":"venue"
},
  "geometry": {"coordinates":[144.89634704599999,-37.8062400818],"type":"Point"}
}