{
  "type": "Feature",
  "properties": {
    "addr:full":"818 Duncans Rd Werribee South VIC 3030",
    "addr:housenumber":"818",
    "addr:postcode":"3030",
    "addr:street":"Duncans Rd",
    "iso:country":"AU",
    "sg:address":"818 Duncans Rd",
    "sg:city":"Werribee South",
    "sg:classifiers":[
        {
            "category":"Food & Beverages",
            "subcategory":"Fruits & Vegetables",
            "type":"Retail Goods"
        }
    ],
    "sg:phone":"+61 3 9742 1284",
    "sg:postcode":"3030",
    "sg:province":"VIC",
    "sg:tags":[
        "grower"
    ],
    "wof:name":"Faranda E",
    "wof:placetype":"venue"
},
  "geometry": {"coordinates":[144.70806899999999,-37.946205],"type":"Point"}
}