{
  "type": "Feature",
  "properties": {
    "iso:country":"AU",
    "sg:address":"75 Vineyard Rd",
    "sg:city":"Sunbury",
    "sg:classifiers":[
        {
            "category":"Recreation",
            "subcategory":"Fishing",
            "type":"Entertainment"
        }
    ],
    "sg:phone":"+61 3 9740 5100",
    "sg:postcode":"3429",
    "sg:province":"VIC",
    "sg:tags":[
        "tackle"
    ],
    "wof:name":"Tackle Shack",
    "wof:placetype":"venue"
},
  "geometry": {"coordinates":[144.71580505399999,-37.5878448486],"type":"Point"}
}