{
  "type": "Feature",
  "properties": {
    "iso:country":"AU",
    "sg:address":"29 Antimony St",
    "sg:city":"Carole Park",
    "sg:classifiers":[
        {
            "category":"Home & Garden",
            "subcategory":"Garden Supply",
            "type":"Retail Goods"
        }
    ],
    "sg:phone":"+61 418 190 583",
    "sg:postcode":"4300",
    "sg:province":"QLD",
    "sg:tags":[
        "nursery"
    ],
    "wof:name":"Peter Bacon Enterprises",
    "wof:placetype":"venue"
},
  "geometry": {"coordinates":[152.934036255,-27.6160964966],"type":"Point"}
}