{
  "type": "Feature",
  "properties": {
    "addr:full":"Bent's Rd Ballandean QLD 4382",
    "addr:postcode":"4382",
    "addr:street":"Bent'S Rd",
    "iso:country":"AU",
    "sg:address":"Bent's Rd",
    "sg:city":"Ballandean",
    "sg:classifiers":[
        {
            "category":"Education",
            "subcategory":"School",
            "type":"Public Place"
        }
    ],
    "sg:phone":"+61 7 4684 1254",
    "sg:postcode":"4382",
    "sg:province":"QLD",
    "sg:tags":[
        "state",
        "except",
        "nsw"
    ],
    "wof:name":"Ballandean Primary",
    "wof:placetype":"venue"
},
  "geometry": {"coordinates":[151.83990499999999,-28.798628],"type":"Point"}
}