{
  "type": "Feature",
  "properties": {
    "addr:full":"Killara St Gruyere VIC 3770",
    "addr:postcode":"3770",
    "addr:street":"Killara St",
    "iso:country":"AU",
    "sg:address":"Killara St",
    "sg:city":"Gruyere",
    "sg:classifiers":[
        {
            "category":"Education",
            "subcategory":"School",
            "type":"Public Place"
        }
    ],
    "sg:phone":"+61 3 5964 9260",
    "sg:postcode":"3770",
    "sg:province":"VIC",
    "sg:tags":[
        "state",
        "except",
        "nsw"
    ],
    "wof:name":"Gruyere Primary School",
    "wof:placetype":"venue"
},
  "geometry": {"coordinates":[145.44073499999999,-37.730968],"type":"Point"}
}