{
  "type": "Feature",
  "properties": {
    "addr:full":"4 Stanley St Merewether NSW 2291",
    "addr:housenumber":"4",
    "addr:postcode":"2291",
    "addr:street":"Stanley St",
    "iso:country":"AU",
    "sg:address":"4 Stanley St",
    "sg:city":"Merewether",
    "sg:classifiers":[
        {
            "category":"Building & Trades",
            "subcategory":"Construction",
            "type":"Services"
        }
    ],
    "sg:phone":"+61 418 490 178",
    "sg:postcode":"2291",
    "sg:province":"NSW",
    "sg:tags":[
        "contractor"
    ],
    "wof:name":"Rowsebuild Pty Ltd",
    "wof:placetype":"venue"
},
  "geometry": {"coordinates":[151.75535583499999,-32.9361610413],"type":"Point"}
}