{
  "type": "Feature",
  "properties": {
    "addr:full":"21 Taylor St Warwick QLD 4370",
    "addr:housenumber":"21",
    "addr:postcode":"4370",
    "addr:street":"Taylor St",
    "iso:country":"AU",
    "sg:address":"21 Taylor St",
    "sg:city":"Warwick",
    "sg:classifiers":[
        {
            "category":"Government",
            "subcategory":"Post Office",
            "type":"Public Place"
        }
    ],
    "sg:phone":"+61 418 716 391",
    "sg:postcode":"4370",
    "sg:province":"QLD",
    "sg:tags":[
        "equipment",
        "hole",
        "contractor"
    ],
    "wof:name":"ABC Bobcat & Bitumen Service",
    "wof:placetype":"venue"
},
  "geometry": {"coordinates":[152.00059509299999,-28.2127761841],"type":"Point"}
}