{
  "type": "Feature",
  "properties": {
    "addr:full":"L4, 60 Reservoir St Surry Hills NSW 2010",
    "addr:housenumber":"60",
    "addr:postcode":"2010",
    "addr:street":"L4;Reservoir St",
    "iso:country":"AU",
    "sg:address":"L4, 60 Reservoir St",
    "sg:city":"Surry Hills",
    "sg:classifiers":[
        {
            "category":"Manufacturing",
            "subcategory":"Printing",
            "type":"Manufacturing & Wholesale Goods"
        }
    ],
    "sg:phone":"+61 2 9217 9600",
    "sg:postcode":"2010",
    "sg:province":"NSW",
    "sg:tags":[
        "wholesaler",
        "mfrs",
        "greeting",
        "card"
    ],
    "wof:name":"The Ink Group",
    "wof:placetype":"venue"
},
  "geometry": {"coordinates":[151.20957946799999,-33.8811073303],"type":"Point"}
}