{
  "type": "Feature",
  "properties": {
    "iso:country":"AU",
    "sg:address":"20 Hamstead Crt",
    "sg:city":"Endeavour Hills",
    "sg:classifiers":[
        {
            "category":"Health Services",
            "subcategory":"Dentist",
            "type":"Services"
        }
    ],
    "sg:phone":"+61 3 9706 1100",
    "sg:postcode":"3802",
    "sg:province":"VIC",
    "wof:name":"Joanna Wilinska-Chojnacka",
    "wof:placetype":"venue"
},
  "geometry": {"coordinates":[145.25086975100001,-37.9672241211],"type":"Point"}
}