{
  "type": "Feature",
  "properties": {
    "iso:country":"AU",
    "sg:address":"86 View St",
    "sg:city":"Gymea",
    "sg:classifiers":[
        {
            "category":"Professional",
            "subcategory":"Art Services",
            "type":"Services"
        }
    ],
    "sg:phone":"+61 2 9524 2528",
    "sg:postcode":"2227",
    "sg:province":"NSW",
    "sg:tags":[
        "artist"
    ],
    "wof:name":"Vaughan M",
    "wof:placetype":"venue"
},
  "geometry": {"coordinates":[151.08909606899999,-34.0375022888],"type":"Point"}
}