{
  "type": "Feature",
  "properties": {
    "addr:full":"72 Womra Crs Glenmore Park NSW 2745",
    "addr:housenumber":"72",
    "addr:postcode":"2745",
    "addr:street":"Womra Crs",
    "iso:country":"AU",
    "sg:address":"72 Womra Crs",
    "sg:city":"Glenmore Park",
    "sg:classifiers":[
        {
            "category":"Building & Trades",
            "subcategory":"Construction",
            "type":"Services"
        }
    ],
    "sg:phone":"+61 2 4733 4974",
    "sg:postcode":"2745",
    "sg:province":"NSW",
    "sg:tags":[
        "earth",
        "excavating",
        "moving",
        "contractor"
    ],
    "wof:name":"D&#039;Amanda Bobcat & Tipper Pty Ltd",
    "wof:placetype":"venue"
},
  "geometry": {"coordinates":[150.67874145499999,-33.7848701477],"type":"Point"}
}