{
  "type": "Feature",
  "properties": {
    "addr:full":"5- 7 Conifer Crs Dingley Village VIC 3172",
    "addr:housenumber":"7",
    "addr:postcode":"3172",
    "addr:street":"Conifer Crs",
    "iso:country":"AU",
    "sg:address":"5- 7 Conifer Crs",
    "sg:city":"Dingley Village",
    "sg:classifiers":[
        {
            "category":"Shopping",
            "subcategory":"Books",
            "type":"Retail Goods"
        }
    ],
    "sg:phone":"+61 3 9551 6000",
    "sg:postcode":"3172",
    "sg:province":"VIC",
    "sg:tags":[
        "wholesaler",
        "canvas",
        "mfrs"
    ],
    "wof:name":"Radins Australia",
    "wof:placetype":"venue"
},
  "geometry": {"coordinates":[145.210083008,-37.9587059021],"type":"Point"}
}