{
  "type": "Feature",
  "properties": {
    "addr:full":"Cnr Coolgardie Ave & Great Eastern Hwy Ascot WA 6104",
    "addr:postcode":"6104",
    "addr:street":"Cnr Coolgardie Ave & Great Eastern Hwy",
    "iso:country":"AU",
    "sg:address":"Cnr Coolgardie Ave & Great Eastern Hwy",
    "sg:city":"Ascot",
    "sg:classifiers":[
        {
            "category":"Social Services",
            "subcategory":"Child Care",
            "type":"Services"
        }
    ],
    "sg:phone":"+61 8 9477 5155",
    "sg:postcode":"6104",
    "sg:province":"WA",
    "wof:name":"Mulberry Tree Childcare",
    "wof:placetype":"venue"
},
  "geometry": {"coordinates":[115.946243286,-31.9285736084],"type":"Point"}
}