{
  "type": "Feature",
  "properties": {
    "addr:full":"171 Nepean Hwy Mentone VIC 3194",
    "addr:housenumber":"171",
    "addr:postcode":"3194",
    "addr:street":"Nepean Hwy",
    "iso:country":"AU",
    "sg:address":"171 Nepean Hwy",
    "sg:city":"Mentone",
    "sg:classifiers":[
        {
            "category":"Travel",
            "subcategory":"Travel Agent",
            "type":"Entertainment"
        }
    ],
    "sg:phone":"+61 3 9584 0100",
    "sg:postcode":"3194",
    "sg:province":"VIC",
    "sg:tags":[
        "consultant"
    ],
    "wof:name":"Travelworld Mentone",
    "wof:placetype":"venue"
},
  "geometry": {"coordinates":[145.076446533,-37.9839401245],"type":"Point"}
}