{
  "type": "Feature",
  "properties": {
    "iso:country":"AU",
    "sg:address":"42 Conn St",
    "sg:city":"Ferntree Gully",
    "sg:classifiers":[
        {
            "category":"Professional",
            "subcategory":"Computer Services",
            "type":"Services"
        }
    ],
    "sg:phone":"+61 500 551 133",
    "sg:postcode":"3156",
    "sg:province":"VIC",
    "sg:tags":[
        "consultant",
        "system"
    ],
    "wof:name":"JPP Services",
    "wof:placetype":"venue"
},
  "geometry": {"coordinates":[145.273803711,-37.8854026794],"type":"Point"}
}