{
  "type": "Feature",
  "properties": {
    "iso:country":"AU",
    "sg:address":"Unit 4 / 36 Benara Rd",
    "sg:city":"Noranda",
    "sg:classifiers":[
        {
            "category":"Health Services",
            "subcategory":"Health Practitioner",
            "type":"Services"
        }
    ],
    "sg:phone":"+61 8 9376 1443",
    "sg:postcode":"6062",
    "sg:province":"WA",
    "sg:tags":[
        "physiotherapist"
    ],
    "wof:name":"Palms Physiotherapy",
    "wof:placetype":"venue"
},
  "geometry": {"coordinates":[115.894561768,-31.8756504059],"type":"Point"}
}