{
  "type": "Feature",
  "properties": {
    "addr:full":"Kennedy Hwy Mareeba QLD 4880",
    "addr:postcode":"4880",
    "addr:street":"Kennedy Hwy",
    "iso:country":"AU",
    "sg:address":"Kennedy Hwy",
    "sg:city":"Mareeba",
    "sg:classifiers":[
        {
            "category":"Cinema",
            "subcategory":"Movie Theater",
            "type":"Entertainment"
        }
    ],
    "sg:phone":"+61 7 4092 4944",
    "sg:postcode":"4880",
    "sg:province":"QLD",
    "wof:name":"Rodeo Drive In Theatre",
    "wof:placetype":"venue"
},
  "geometry": {"coordinates":[145.42547607399999,-17.015504837],"type":"Point"}
}