{
  "type": "Feature",
  "properties": {
    "iso:country":"AU",
    "sg:address":"Lvl 14/ 257 Collins St",
    "sg:city":"Melbourne",
    "sg:classifiers":[
        {
            "category":"Building & Trades",
            "subcategory":"Construction",
            "type":"Services"
        }
    ],
    "sg:phone":"+61 3 9660 9000",
    "sg:postcode":"3000",
    "sg:province":"VIC",
    "sg:tags":[
        "contractor"
    ],
    "wof:name":"Adamco Construction",
    "wof:placetype":"venue"
},
  "geometry": {"coordinates":[144.96536254899999,-37.8159637451],"type":"Point"}
}