{
  "type": "Feature",
  "properties": {
    "addr:full":"5/ 10 Webb Drv Wonthaggi VIC 3995",
    "addr:housenumber":"/ 10",
    "addr:postcode":"3995",
    "addr:street":"Webb Drv",
    "iso:country":"AU",
    "sg:address":"5/ 10 Webb Drv",
    "sg:city":"Wonthaggi",
    "sg:classifiers":[
        {
            "category":"Autos & Motor Vehicles",
            "subcategory":"Auto Supplies",
            "type":"Retail Goods"
        }
    ],
    "sg:phone":"+61 3 5672 5800",
    "sg:postcode":"3995",
    "sg:province":"VIC",
    "sg:tags":[
        "accessory"
    ],
    "wof:name":"South Gippsland Ute Accessories",
    "wof:placetype":"venue"
},
  "geometry": {"coordinates":[145.603973,-38.604504],"type":"Point"}
}