{
  "type": "Feature",
  "properties": {
    "addr:full":"10 Pegler St Beverley SA 5009",
    "addr:housenumber":"10",
    "addr:postcode":"5009",
    "addr:street":"Pegler St",
    "iso:country":"AU",
    "sg:address":"10 Pegler St",
    "sg:city":"Beverley",
    "sg:classifiers":[
        {
            "category":"Manufacturing",
            "subcategory":"Rubber & Plastics",
            "type":"Manufacturing & Wholesale Goods"
        }
    ],
    "sg:phone":"+61 8 8268 8777",
    "sg:postcode":"5009",
    "sg:province":"SA",
    "sg:tags":[
        "wholesaler",
        "product",
        "mfrs"
    ],
    "wof:name":"Express Plastics",
    "wof:placetype":"venue"
},
  "geometry": {"coordinates":[138.54440307600001,-34.8912162781],"type":"Point"}
}