{
  "type": "Feature",
  "properties": {
    "addr:full":"180 Macquarie St Dubbo NSW 2830",
    "addr:housenumber":"180",
    "addr:postcode":"2830",
    "addr:street":"Macquarie St",
    "iso:country":"AU",
    "sg:address":"180 Macquarie St",
    "sg:city":"Dubbo",
    "sg:classifiers":[
        {
            "category":"Shopping",
            "subcategory":"Jewelry",
            "type":"Retail Goods"
        }
    ],
    "sg:phone":"+61 2 6885 3500",
    "sg:postcode":"2830",
    "sg:province":"NSW",
    "sg:tags":[
        "jeweller"
    ],
    "sg:website":"http://www.kingshall.com.au",
    "wof:name":"Kings Hall Jewellers",
    "wof:placetype":"venue"
},
  "geometry": {"coordinates":[148.60121154800001,-32.248588562],"type":"Point"}
}