{
  "type": "Feature",
  "properties": {
    "addr:full":"8 Fourth Ave Sandgate QLD 4017",
    "addr:housenumber":"8",
    "addr:postcode":"4017",
    "addr:street":"Fourth Ave",
    "iso:country":"AU",
    "sg:address":"8 Fourth Ave",
    "sg:city":"Sandgate",
    "sg:classifiers":[
        {
            "category":"Professional",
            "subcategory":"Lawyer & Legal Services",
            "type":"Services"
        }
    ],
    "sg:phone":"+61 7 3269 1007",
    "sg:postcode":"4017",
    "sg:province":"QLD",
    "sg:tags":[
        "wills",
        "probate",
        "estate"
    ],
    "wof:name":"Gill & Lane",
    "wof:placetype":"venue"
},
  "geometry": {"coordinates":[153.06890869099999,-27.3184871674],"type":"Point"}
}