{
  "type": "Feature",
  "properties": {
    "iso:country":"AU",
    "sg:address":"54 Shoalhaven Rd",
    "sg:city":"Sylvania Waters",
    "sg:classifiers":[
        {
            "category":"Professional",
            "subcategory":"Accounting & Tax Preparation",
            "type":"Services"
        }
    ],
    "sg:phone":"+61 2 9522 4427",
    "sg:postcode":"2224",
    "sg:province":"NSW",
    "sg:tags":[
        "accountant",
        "auditor"
    ],
    "wof:name":"Muddle N N",
    "wof:placetype":"venue"
},
  "geometry": {"coordinates":[151.107788086,-34.0188941956],"type":"Point"}
}