{
  "type": "Feature",
  "properties": {
    "addr:full":"126 Baylis St Wagga Wagga NSW 2650",
    "addr:housenumber":"126",
    "addr:postcode":"2650",
    "addr:street":"Baylis St",
    "iso:country":"AU",
    "sg:address":"126 Baylis St",
    "sg:city":"Wagga Wagga",
    "sg:classifiers":[
        {
            "category":"Real Estate",
            "subcategory":"Real Estate Services",
            "type":"Services"
        }
    ],
    "sg:phone":"+61 2 6923 3200",
    "sg:postcode":"2650",
    "sg:province":"NSW",
    "sg:tags":[
        "valuer"
    ],
    "wof:name":"Re/Max",
    "wof:placetype":"venue"
},
  "geometry": {"coordinates":[147.36985778799999,-35.1125488281],"type":"Point"}
}