{
  "type": "Feature",
  "properties": {
    "addr:full":"Unit 3/ 27 Salisbury Rd Hornsby NSW 2077",
    "addr:housenumber":"27",
    "addr:postcode":"2077",
    "addr:street":"Salisbury Rd",
    "iso:country":"AU",
    "sg:address":"Unit 3/ 27 Salisbury Rd",
    "sg:city":"Hornsby",
    "sg:classifiers":[
        {
            "category":"Building & Trades",
            "subcategory":"Construction",
            "type":"Services"
        }
    ],
    "sg:phone":"+61 2 9482 2255",
    "sg:postcode":"2077",
    "sg:province":"NSW",
    "sg:tags":[
        "scaffolding"
    ],
    "wof:name":"Secure Domestic Safety Access Pty Ltd",
    "wof:placetype":"venue"
},
  "geometry": {"coordinates":[151.11129760700001,-33.6956787109],"type":"Point"}
}