{
  "type": "Feature",
  "properties": {
    "iso:country":"AU",
    "sg:address":"Shop 32",
    "sg:city":"Garden City Shopping Centre Booragoon",
    "sg:classifiers":[
        {
            "category":"Shopping",
            "subcategory":"Clothing, Apparel, & Fashions",
            "type":"Retail Goods"
        }
    ],
    "sg:phone":"+61 8 9316 0195",
    "sg:postcode":"6154",
    "sg:province":"WA",
    "sg:tags":[
        "lingerie",
        "hosiery",
        "sleepwear"
    ],
    "wof:name":"Bras &#039;N&#039; Things",
    "wof:placetype":"venue"
},
  "geometry": {"coordinates":[115.832329,-32.036018],"type":"Point"}
}