{
  "type": "Feature",
  "properties": {
    "addr:full":"386 Park Rd Luddenham NSW 2745",
    "addr:housenumber":"386",
    "addr:postcode":"2745",
    "addr:street":"Park Rd",
    "iso:country":"AU",
    "sg:address":"386 Park Rd",
    "sg:city":"Luddenham",
    "sg:classifiers":[
        {
            "category":"Commercial Area",
            "type":"Public Place"
        }
    ],
    "sg:phone":"+61 2 4773 4450",
    "sg:postcode":"2745",
    "sg:province":"NSW",
    "sg:tags":[
        "heavy",
        "carrier"
    ],
    "wof:name":"D & D Haulage",
    "wof:placetype":"venue"
},
  "geometry": {"coordinates":[150.68170165999999,-33.8731422424],"type":"Point"}
}