{
  "type": "Feature",
  "properties": {
    "iso:country":"AU",
    "sg:address":"14 Tennant St",
    "sg:city":"Fyshwick",
    "sg:classifiers":[
        {
            "category":"Building & Trades",
            "subcategory":"Construction",
            "type":"Services"
        }
    ],
    "sg:phone":"+61 2 4702 0860",
    "sg:postcode":"2609",
    "sg:province":"ACT",
    "sg:tags":[
        "pipe",
        "concrete"
    ],
    "wof:name":"Rocla Pipeline Products",
    "wof:placetype":"venue"
},
  "geometry": {"coordinates":[149.18208313,-35.3316307068],"type":"Point"}
}