{
  "type": "Feature",
  "properties": {
    "addr:full":"28 Palm Beach Ave Palm Beach QLD 4221",
    "addr:housenumber":"28",
    "addr:postcode":"4221",
    "addr:street":"Palm Beach Ave",
    "iso:country":"AU",
    "sg:address":"28 Palm Beach Ave",
    "sg:city":"Palm Beach",
    "sg:classifiers":[
        {
            "category":"Professional",
            "subcategory":"Accounting & Tax Preparation",
            "type":"Services"
        }
    ],
    "sg:phone":"+61 7 5598 3226",
    "sg:postcode":"4221",
    "sg:province":"QLD",
    "sg:tags":[
        "consultant",
        "taxation"
    ],
    "wof:name":"Mick Castle & Associates",
    "wof:placetype":"venue"
},
  "geometry": {"coordinates":[153.47151184099999,-28.1215648651],"type":"Point"}
}