{
  "type": "Feature",
  "properties": {
    "addr:full":"Tivers Rd Stewarts Range SA 5271",
    "addr:postcode":"5271",
    "addr:street":"Tivers Rd",
    "iso:country":"AU",
    "sg:address":"Tivers Rd",
    "sg:city":"Stewarts Range",
    "sg:classifiers":[
        {
            "category":"Building & Trades",
            "subcategory":"Landscaping Services",
            "type":"Services"
        }
    ],
    "sg:phone":"+61 8 8764 8176",
    "sg:postcode":"5271",
    "sg:province":"SA",
    "sg:tags":[
        "grazier"
    ],
    "wof:name":"McCallum P G",
    "wof:placetype":"venue"
},
  "geometry": {"coordinates":[140.600967,-36.979378],"type":"Point"}
}