{
  "type": "Feature",
  "properties": {
    "iso:country":"AU",
    "sg:address":"Malone Rd",
    "sg:city":"Emerald Creek",
    "sg:classifiers":[
        {
            "category":"Farming",
            "subcategory":"Farm",
            "type":"Manufacturing & Wholesale Goods"
        }
    ],
    "sg:phone":"+61 7 4093 3167",
    "sg:postcode":"4880",
    "sg:province":"QLD",
    "sg:tags":[
        "farmer"
    ],
    "wof:name":"Serafini D",
    "wof:placetype":"venue"
},
  "geometry": {"coordinates":[145.47128295900001,-16.9974746704],"type":"Point"}
}