{
  "type": "Feature",
  "properties": {
    "iso:country":"AU",
    "sg:address":"902 Pittwater Rd",
    "sg:city":"Dee Why",
    "sg:classifiers":[
        {
            "category":"Shopping",
            "subcategory":"Antiques",
            "type":"Retail Goods"
        }
    ],
    "sg:phone":"+61 2 9971 1550",
    "sg:postcode":"2099",
    "sg:province":"NSW",
    "wof:name":"Favourite Things",
    "wof:placetype":"venue"
},
  "geometry": {"coordinates":[151.28741455100001,-33.7523956299],"type":"Point"}
}