{
  "type": "Feature",
  "properties": {
    "addr:full":"Unit 6/ 16 Borec Rd Penrith NSW 2750",
    "addr:postcode":"2750",
    "addr:street":"16 Borec Rd",
    "iso:country":"AU",
    "sg:address":"Unit 6/ 16 Borec Rd",
    "sg:city":"Penrith",
    "sg:classifiers":[
        {
            "category":"Building & Trades",
            "subcategory":"Construction",
            "type":"Services"
        }
    ],
    "sg:phone":"+61 2 4722 8686",
    "sg:postcode":"2750",
    "sg:province":"NSW",
    "sg:tags":[
        "industrial",
        "commercial",
        "air conditioning"
    ],
    "wof:name":"Westaflex",
    "wof:placetype":"venue"
},
  "geometry": {"coordinates":[150.691116333,-33.7357177734],"type":"Point"}
}