{
  "type": "Feature",
  "properties": {
    "iso:country":"AU",
    "sg:address":"90 Kelly St",
    "sg:city":"Scone",
    "sg:classifiers":[
        {
            "category":"Organizations",
            "subcategory":"Community Association",
            "type":"Services"
        }
    ],
    "sg:phone":"+61 2 6545 1732",
    "sg:postcode":"2337",
    "sg:province":"NSW",
    "sg:tags":[
        "organisation",
        "family",
        "welfare"
    ],
    "wof:name":"Upper Hunter Neighbour Aid",
    "wof:placetype":"venue"
},
  "geometry": {"coordinates":[150.868484497,-32.0469322205],"type":"Point"}
}