{
  "type": "Feature",
  "properties": {
    "addr:full":"38 Paget St Hilton WA 6163",
    "addr:housenumber":"38",
    "addr:postcode":"6163",
    "addr:street":"Paget St",
    "iso:country":"AU",
    "sg:address":"38 Paget St",
    "sg:city":"Hilton",
    "sg:classifiers":[
        {
            "category":"Shopping",
            "subcategory":"Clothing, Apparel, & Fashions",
            "type":"Retail Goods"
        }
    ],
    "sg:phone":"+61 8 9314 1559",
    "sg:postcode":"6163",
    "sg:province":"WA",
    "sg:tags":[
        "recycled",
        "clothing"
    ],
    "wof:name":"Save The Children Australia Shop",
    "wof:placetype":"venue"
},
  "geometry": {"coordinates":[115.781479,-32.069729],"type":"Point"}
}