{
  "type": "Feature",
  "properties": {
    "addr:full":"18 Muru Ave Winmalee NSW 2777",
    "addr:housenumber":"18",
    "addr:postcode":"2777",
    "addr:street":"Muru Ave",
    "iso:country":"AU",
    "sg:address":"18 Muru Ave",
    "sg:city":"Winmalee",
    "sg:classifiers":[
        {
            "category":"Building & Trades",
            "subcategory":"Construction",
            "type":"Services"
        }
    ],
    "sg:phone":"+61 2 4754 1840",
    "sg:postcode":"2777",
    "sg:province":"NSW",
    "sg:tags":[
        "plasterboard",
        "plasterer",
        "fixer"
    ],
    "wof:name":"Elliot's Plastering",
    "wof:placetype":"venue"
},
  "geometry": {"coordinates":[150.59657287600001,-33.6811523438],"type":"Point"}
}