{
  "type": "Feature",
  "properties": {
    "iso:country":"AU",
    "sg:address":"Shop 2, 19 National Park St",
    "sg:city":"Newcastle West",
    "sg:classifiers":[
        {
            "category":"Retail",
            "subcategory":"Repair Shop",
            "type":"Services"
        }
    ],
    "sg:phone":"+61 2 4927 5700",
    "sg:postcode":"2302",
    "sg:province":"NSW",
    "sg:tags":[
        "machine",
        "sewing"
    ],
    "wof:name":"Brother Sewing Centre",
    "wof:placetype":"venue"
},
  "geometry": {"coordinates":[151.76104699999999,-32.927219],"type":"Point"}
}