{
  "type": "Feature",
  "properties": {
    "addr:full":"Shop 3, Robina Village Shops, 195 Ron Penhaligon Way Robina QLD 4226",
    "addr:housenumber":"shop 3;195",
    "addr:postcode":"4226",
    "addr:street":"Robina Village;Ron Penhaligon Way",
    "iso:country":"AU",
    "sg:address":"Shop 3, Robina Village Shops, 195",
    "sg:city":"Ron Penhaligon Way Robina",
    "sg:classifiers":[
        {
            "category":"Real Estate",
            "subcategory":"Real Estate Agent",
            "type":"Services"
        }
    ],
    "sg:phone":"+61 7 5593 3111",
    "sg:postcode":"4226",
    "sg:province":"QLD",
    "wof:name":"Harcourts Queensland Pty Ltd",
    "wof:placetype":"venue"
},
  "geometry": {"coordinates":[153.405883789,-28.0632781982],"type":"Point"}
}