{
  "type": "Feature",
  "properties": {
    "addr:full":"14 Federico Crt Ringwood North VIC 3134",
    "addr:postcode":"3134",
    "addr:street":"Federico Crt",
    "iso:country":"AU",
    "sg:address":"14 Federico Crt",
    "sg:city":"Ringwood North",
    "sg:classifiers":[
        {
            "category":"Building & Trades",
            "subcategory":"Construction",
            "type":"Services"
        }
    ],
    "sg:phone":"+61 412 524 635",
    "sg:postcode":"3134",
    "sg:province":"VIC",
    "sg:tags":[
        "contractor"
    ],
    "wof:name":"A & C Jeffrey Pty Ltd",
    "wof:placetype":"venue"
},
  "geometry": {"coordinates":[145.251052856,-37.7825126648],"type":"Point"}
}