{
  "type": "Feature",
  "properties": {
    "iso:country":"AU",
    "sg:address":"30 Harold St",
    "sg:city":"Kings Point",
    "sg:classifiers":[
        {
            "category":"Retail",
            "subcategory":"Repair Shop",
            "type":"Services"
        }
    ],
    "sg:phone":"+61 2 4455 4878",
    "sg:postcode":"2539",
    "sg:province":"NSW",
    "sg:tags":[
        "stove",
        "part",
        "range"
    ],
    "wof:name":"Kingspoint Appliance Repairs",
    "wof:placetype":"venue"
},
  "geometry": {"coordinates":[150.437866211,-35.3707122803],"type":"Point"}
}