{
  "type": "Feature",
  "properties": {
    "addr:full":"3 Naples Pl Wyong North NSW 2259",
    "addr:housenumber":"3",
    "addr:postcode":"2259",
    "addr:street":"Naples Pl",
    "iso:country":"AU",
    "sg:address":"3 Naples Pl",
    "sg:city":"Wyong North",
    "sg:classifiers":[
        {
            "category":"Professional",
            "subcategory":"Art Services",
            "type":"Services"
        }
    ],
    "sg:phone":"+61 2 4358 8599",
    "sg:postcode":"2259",
    "sg:province":"NSW",
    "sg:tags":[
        "decorator",
        "painter"
    ],
    "wof:name":"Dukes Painting Service",
    "wof:placetype":"venue"
},
  "geometry": {"coordinates":[151.48101806599999,-33.1748428345],"type":"Point"}
}