{
  "type": "Feature",
  "properties": {
    "addr:full":"145 Henley Beach Rd Torrensville SA 5031",
    "addr:housenumber":"145",
    "addr:postcode":"5031",
    "addr:street":"Henley Beach Rd",
    "iso:country":"AU",
    "sg:address":"145 Henley Beach Rd",
    "sg:city":"Torrensville",
    "sg:classifiers":[
        {
            "category":"Deli",
            "type":"Food & Drink"
        }
    ],
    "sg:phone":"+61 8 8234 0784",
    "sg:postcode":"5031",
    "sg:province":"SA",
    "sg:tags":[
        "delicatessen"
    ],
    "wof:name":"Delmonte Deli",
    "wof:placetype":"venue"
},
  "geometry": {"coordinates":[138.56390380900001,-34.9242210388],"type":"Point"}
}