{
  "type": "Feature",
  "properties": {
    "iso:country":"AU",
    "sg:address":"PO Box 189",
    "sg:city":"Bright",
    "sg:classifiers":[
        {
            "category":"Building & Trades",
            "subcategory":"Construction",
            "type":"Services"
        }
    ],
    "sg:phone":"+61 418 574 573",
    "sg:postcode":"3741",
    "sg:province":"VIC",
    "sg:tags":[
        "concrete",
        "paving"
    ],
    "wof:name":"Bright Concreting",
    "wof:placetype":"venue"
},
  "geometry": {"coordinates":[146.96012878400001,-36.7273902893],"type":"Point"}
}