{
  "type": "Feature",
  "properties": {
    "iso:country":"AU",
    "sg:address":"328 St Leonards Rd",
    "sg:city":"St Leonards",
    "sg:classifiers":[
        {
            "category":"Food & Beverages",
            "subcategory":"Bakery",
            "type":"Retail Goods"
        }
    ],
    "sg:phone":"+61 3 6339 2681",
    "sg:postcode":"7250",
    "sg:province":"TAS",
    "sg:tags":[
        "baker"
    ],
    "wof:name":"St Leonards Milk Bar",
    "wof:placetype":"venue"
},
  "geometry": {"coordinates":[147.20085144000001,-41.4587440491],"type":"Point"}
}