{
  "type": "Feature",
  "properties": {
    "addr:full":"4 Melaleuca St Yea VIC 3717",
    "addr:housenumber":"4",
    "addr:postcode":"3717",
    "addr:street":"Melaleuca St",
    "iso:country":"AU",
    "sg:address":"4 Melaleuca St",
    "sg:city":"Yea",
    "sg:classifiers":[
        {
            "category":"Commercial Area",
            "type":"Public Place"
        }
    ],
    "sg:phone":"+61 3 5797 8413",
    "sg:postcode":"3717",
    "sg:province":"VIC",
    "sg:tags":[
        "heavy",
        "carrier"
    ],
    "wof:name":"Yea Sands",
    "wof:placetype":"venue"
},
  "geometry": {"coordinates":[145.41421508799999,-37.2166404724],"type":"Point"}
}