{
  "type": "Feature",
  "properties": {
    "addr:full":"PO Box 3616 Caloundra DC QLD 4551",
    "addr:postcode":"4551",
    "iso:country":"AU",
    "sg:address":"PO Box 3616",
    "sg:city":"Caloundra DC",
    "sg:classifiers":[
        {
            "category":"Social Services",
            "type":"Services"
        }
    ],
    "sg:phone":"+61 7 5438 2464",
    "sg:postcode":"4551",
    "sg:province":"QLD",
    "sg:tags":[
        "domestic",
        "help"
    ],
    "wof:name":"Lifestyle Ironing & Alteration",
    "wof:placetype":"venue"
},
  "geometry": {"coordinates":[153.12998962399999,-26.8046951294],"type":"Point"}
}