{
  "type": "Feature",
  "properties": {
    "addr:full":"37 Hall St Chermside QLD 4032",
    "addr:housenumber":"37",
    "addr:postcode":"qld 4032",
    "addr:street":"Hall St",
    "iso:country":"AU",
    "sg:address":"37 Hall St",
    "sg:city":"Chermside",
    "sg:classifiers":[
        {
            "category":"Shopping",
            "subcategory":"Crafts & Fabrics",
            "type":"Retail Goods"
        }
    ],
    "sg:phone":"+61 7 3359 1922",
    "sg:postcode":"4032",
    "sg:province":"QLD",
    "sg:tags":[
        "supply"
    ],
    "wof:name":"Classy Crafts",
    "wof:placetype":"venue"
},
  "geometry": {"coordinates":[153.033524,-27.389185],"type":"Point"}
}