{
  "type": "Feature",
  "properties": {
    "addr:full":"101 Enterprise St Bundaberg QLD 4670",
    "addr:housenumber":"101",
    "addr:postcode":"4670",
    "addr:street":"Enterprise St",
    "iso:country":"AU",
    "sg:address":"101 Enterprise St",
    "sg:city":"Bundaberg",
    "sg:classifiers":[
        {
            "category":"Arts & Performance",
            "subcategory":"Music",
            "type":"Entertainment"
        }
    ],
    "sg:phone":"+61 7 4152 8855",
    "sg:postcode":"4670",
    "sg:province":"QLD",
    "sg:tags":[
        "hi-fi",
        "equipment"
    ],
    "wof:name":"Pimp My Ride Custom Car Sound & Auto Accessories",
    "wof:placetype":"venue"
},
  "geometry": {"coordinates":[152.3409729,-24.8906574249],"type":"Point"}
}