{
  "type": "Feature",
  "properties": {
    "addr:full":"Unit 47/ 59 Robertson St Fortitude Valley QLD 4006",
    "addr:housenumber":"/ 59",
    "addr:postcode":"4006",
    "addr:street":"Robertson St",
    "iso:country":"AU",
    "sg:address":"Unit 47/ 59 Robertson St",
    "sg:city":"Fortitude Valley",
    "sg:classifiers":[
        {
            "category":"Manufacturing",
            "subcategory":"Furniture",
            "type":"Manufacturing & Wholesale Goods"
        }
    ],
    "sg:phone":"+61 414 400 172",
    "sg:postcode":"4006",
    "sg:province":"QLD",
    "sg:tags":[
        "builder",
        "designer",
        "custom"
    ],
    "wof:name":"Nicholas Bailey Fine Furniture",
    "wof:placetype":"venue"
},
  "geometry": {"coordinates":[153.038238525,-27.4593276978],"type":"Point"}
}