{
  "type": "Feature",
  "properties": {
    "iso:country":"AU",
    "sg:address":"321 Lennox St",
    "sg:city":"Richmond",
    "sg:classifiers":[
        {
            "category":"Shopping",
            "subcategory":"Clothing, Apparel, & Fashions",
            "type":"Retail Goods"
        }
    ],
    "sg:phone":"+61 3 9421 6396",
    "sg:postcode":"3121",
    "sg:province":"VIC",
    "sg:tags":[
        "boutique"
    ],
    "wof:name":"Dairing",
    "wof:placetype":"venue"
},
  "geometry": {"coordinates":[144.993652344,-37.8244857788],"type":"Point"}
}