{
  "type": "Feature",
  "properties": {
    "addr:full":"Royd St Wandoan QLD 4419",
    "addr:postcode":"4419",
    "iso:country":"AU",
    "sg:address":"Royd St",
    "sg:city":"Wandoan",
    "sg:classifiers":[
        {
            "category":"Banks & Credit Unions",
            "subcategory":"Financial Services",
            "type":"Services"
        }
    ],
    "sg:phone":"+61 7 4627 5978",
    "sg:postcode":"4419",
    "sg:province":"QLD",
    "sg:tags":[
        "building",
        "society"
    ],
    "wof:name":"Heritage Building Society",
    "wof:placetype":"venue"
},
  "geometry": {"coordinates":[149.960403442,-26.1212844849],"type":"Point"}
}