{
  "type": "Feature",
  "properties": {
    "addr:full":"9 Willow Pl Beechboro WA 6063",
    "addr:housenumber":"9",
    "addr:postcode":"6063",
    "addr:street":"Willow Pl",
    "iso:country":"AU",
    "sg:address":"9 Willow Pl",
    "sg:city":"Beechboro",
    "sg:classifiers":[
        {
            "category":"Building & Trades",
            "subcategory":"Construction",
            "type":"Services"
        }
    ],
    "sg:phone":"+61 412 103 804",
    "sg:postcode":"6063",
    "sg:province":"WA",
    "sg:tags":[
        "welding"
    ],
    "wof:name":"All Weld Industries",
    "wof:placetype":"venue"
},
  "geometry": {"coordinates":[115.918243408,-31.8703136444],"type":"Point"}
}