{
  "type": "Feature",
  "properties": {
    "iso:country":"AU",
    "sg:address":"35 Myoora Drv",
    "sg:city":"Mooroolbark",
    "sg:classifiers":[
        {
            "category":"Education",
            "subcategory":"Special Training",
            "type":"Public Place"
        }
    ],
    "sg:phone":"+61 3 9727 4848",
    "sg:postcode":"3138",
    "sg:province":"VIC",
    "sg:tags":[
        "development"
    ],
    "wof:name":"Norquay Training & Development Pty Ltd",
    "wof:placetype":"venue"
},
  "geometry": {"coordinates":[145.319915772,-37.7783355713],"type":"Point"}
}