{
  "type": "Feature",
  "properties": {
    "iso:country":"AU",
    "sg:address":"14 Michelle Drv",
    "sg:city":"Kiewa",
    "sg:classifiers":[
        {
            "category":"School Buses",
            "type":"Transportation"
        }
    ],
    "sg:phone":"+61 2 6027 3476",
    "sg:postcode":"2669",
    "sg:province":"NSW",
    "sg:tags":[
        "brick"
    ],
    "wof:name":"Murrawood Mud Bricks",
    "wof:placetype":"venue"
},
  "geometry": {"coordinates":[146.616333008,-33.6207618713],"type":"Point"}
}