{
  "type": "Feature",
  "properties": {
    "addr:full":"5 Mitre Pl Ashmore QLD 4214",
    "addr:housenumber":"5",
    "addr:postcode":"4214",
    "addr:street":"Mitre Pl",
    "iso:country":"AU",
    "sg:address":"5 Mitre Pl",
    "sg:city":"Ashmore",
    "sg:classifiers":[
        {
            "category":"Professional",
            "subcategory":"Art Services",
            "type":"Services"
        }
    ],
    "sg:phone":"+61 414 305 900",
    "sg:postcode":"4214",
    "sg:province":"QLD",
    "sg:tags":[
        "decorator",
        "painter"
    ],
    "wof:name":"Tim Bennett Painting",
    "wof:placetype":"venue"
},
  "geometry": {"coordinates":[153.36077880900001,-27.9722518921],"type":"Point"}
}