{
  "type": "Feature",
  "properties": {
    "addr:full":"21 Queen St Hamilton VIC 3300",
    "addr:housenumber":"21",
    "addr:postcode":"3300",
    "addr:street":"Queen St",
    "iso:country":"AU",
    "sg:address":"21 Queen St",
    "sg:city":"Hamilton",
    "sg:classifiers":[
        {
            "category":"Building & Trades",
            "subcategory":"Construction",
            "type":"Services"
        }
    ],
    "sg:phone":"+61 3 5572 5640",
    "sg:postcode":"3300",
    "sg:province":"VIC",
    "sg:tags":[
        "plasterboard",
        "plasterer",
        "fixer"
    ],
    "wof:name":"Anton Desmond J",
    "wof:placetype":"venue"
},
  "geometry": {"coordinates":[142.00941467300001,-37.7379226685],"type":"Point"}
}