{
  "type": "Feature",
  "properties": {
    "iso:country":"AU",
    "sg:address":"212 Queen Victoria St",
    "sg:city":"North Fremantle",
    "sg:classifiers":[
        {
            "category":"Professional",
            "subcategory":"Art Services",
            "type":"Services"
        }
    ],
    "sg:phone":"+61 8 9524 2715",
    "sg:postcode":"6159",
    "sg:province":"WA",
    "sg:tags":[
        "graphic",
        "designer"
    ],
    "wof:name":"Turland Design",
    "wof:placetype":"venue"
},
  "geometry": {"coordinates":[115.753822,-32.036201],"type":"Point"}
}