{
  "type": "Feature",
  "properties": {
    "addr:full":"Garden City Shopng Cntr Kessels Rd Upper Mt Gravatt QLD 4122",
    "addr:postcode":"4122",
    "addr:street":"Kessels Rd Upper",
    "iso:country":"AU",
    "sg:address":"Garden City Shopng Cntr Kessels Rd",
    "sg:city":"Upper Mt Gravatt",
    "sg:classifiers":[
        {
            "category":"Shopping",
            "subcategory":"Optical Goods",
            "type":"Retail Goods"
        }
    ],
    "sg:phone":"+61 7 3343 5434",
    "sg:postcode":"4122",
    "sg:province":"QLD",
    "sg:tags":[
        "dispenser",
        "prescription"
    ],
    "wof:name":"Precision Eyewear",
    "wof:placetype":"venue"
},
  "geometry": {"coordinates":[153.08088684099999,-27.5599441528],"type":"Point"}
}