{
  "type": "Feature",
  "properties": {
    "addr:full":"737 Burwood Rd Hawthorne QLD 4171",
    "addr:housenumber":"737",
    "addr:postcode":"4171",
    "addr:street":"Burwood Rd",
    "iso:country":"AU",
    "sg:address":"737 Burwood Rd",
    "sg:city":"Hawthorne",
    "sg:classifiers":[
        {
            "category":"Wholesale",
            "subcategory":"Machinery & Supplies",
            "type":"Manufacturing & Wholesale Goods"
        }
    ],
    "sg:phone":"+61 3 8862 6338",
    "sg:postcode":"4171",
    "sg:province":"QLD",
    "sg:tags":[
        "engine",
        "petrol"
    ],
    "wof:name":"Volvo Penta Oceania",
    "wof:placetype":"venue"
},
  "geometry": {"coordinates":[153.05963134800001,-27.4660491943],"type":"Point"}
}