{
  "type": "Feature",
  "properties": {
    "addr:full":"45- 55 Annandale Rd Tullamarine VIC 3043",
    "addr:housenumber":"55",
    "addr:postcode":"3043",
    "addr:street":"Annandale Rd",
    "iso:country":"AU",
    "sg:address":"45- 55 Annandale Rd",
    "sg:city":"Tullamarine",
    "sg:classifiers":[
        {
            "category":"Freight",
            "type":"Transportation"
        }
    ],
    "sg:phone":"+61 13 23 45",
    "sg:postcode":"3043",
    "sg:province":"VIC",
    "sg:tags":[
        "cargo",
        "air"
    ],
    "wof:name":"Star Track Express",
    "wof:placetype":"venue"
},
  "geometry": {"coordinates":[144.86512756400001,-37.7198829651],"type":"Point"}
}