{
  "type": "Feature",
  "properties": {
    "addr:full":"246 Maroondah Hwy Healesville VIC 3777",
    "addr:housenumber":"246",
    "addr:postcode":"3777",
    "addr:street":"Maroondah Hwy",
    "iso:country":"AU",
    "sg:address":"246 Maroondah Hwy",
    "sg:city":"Healesville",
    "sg:classifiers":[
        {
            "category":"Fast Food",
            "type":"Food & Drink"
        }
    ],
    "sg:phone":"+61 3 5962 4640",
    "sg:postcode":"3777",
    "sg:province":"VIC",
    "sg:tags":[
        "away",
        "take"
    ],
    "wof:name":"Cherry Tree Cafe",
    "wof:placetype":"venue"
},
  "geometry": {"coordinates":[145.51559399999999,-37.654308],"type":"Point"}
}