{
  "type": "Feature",
  "properties": {
    "iso:country":"AU",
    "sg:address":"145 Canning Hwy",
    "sg:city":"South Perth",
    "sg:classifiers":[
        {
            "category":"Health Services",
            "subcategory":"Optometrist",
            "type":"Services"
        }
    ],
    "sg:phone":"+61 8 9367 4726",
    "sg:postcode":"6151",
    "sg:province":"WA",
    "wof:name":"Kane & Dawson Optometrists",
    "wof:placetype":"venue"
},
  "geometry": {"coordinates":[115.87545,-31.982792],"type":"Point"}
}