{
  "type": "Feature",
  "properties": {
    "iso:country":"AU",
    "sg:address":"9 Prospect St",
    "sg:city":"Paddington",
    "sg:classifiers":[
        {
            "category":"Building & Trades",
            "subcategory":"Landscaping Services",
            "type":"Services"
        }
    ],
    "sg:phone":"+61 411 219 567",
    "sg:postcode":"2021",
    "sg:province":"NSW",
    "sg:tags":[
        "designer",
        "landscape",
        "contractor"
    ],
    "wof:name":"STA Landscapes",
    "wof:placetype":"venue"
},
  "geometry": {"coordinates":[151.22340393100001,-33.8832511902],"type":"Point"}
}