{
  "type": "Feature",
  "properties": {
    "addr:full":"129 McIlwraith St Carlton North VIC 3054",
    "addr:housenumber":"129",
    "addr:postcode":"3054",
    "addr:street":"Mcilwraith St",
    "iso:country":"AU",
    "sg:address":"129 McIlwraith St",
    "sg:city":"Carlton North",
    "sg:classifiers":[
        {
            "category":"Real Estate",
            "subcategory":"Architect",
            "type":"Services"
        }
    ],
    "sg:phone":"+61 3 9388 2234",
    "sg:postcode":"3054",
    "sg:province":"VIC",
    "wof:name":"Rizzo & Rizzo Architects",
    "wof:placetype":"venue"
},
  "geometry": {"coordinates":[144.96839904800001,-37.7818717957],"type":"Point"}
}