{
  "type": "Feature",
  "properties": {
    "iso:country":"AU",
    "sg:address":"13 Jenkins Drv",
    "sg:city":"Templestowe",
    "sg:classifiers":[
        {
            "category":"Professional",
            "subcategory":"Art Services",
            "type":"Services"
        }
    ],
    "sg:phone":"+61 3 9662 3818",
    "sg:postcode":"3106",
    "sg:province":"VIC",
    "sg:tags":[
        "interior",
        "designer"
    ],
    "wof:name":"Melbourne Feng Shui Science & Services Centre",
    "wof:placetype":"venue"
},
  "geometry": {"coordinates":[145.158737183,-37.7633972168],"type":"Point"}
}