{
  "type": "Feature",
  "properties": {
    "iso:country":"AU",
    "sg:address":"&#034;Deerfield Park&#034; North Logan Rd",
    "sg:city":"Cowra",
    "sg:classifiers":[
        {
            "category":"Building & Trades",
            "subcategory":"Construction",
            "type":"Services"
        }
    ],
    "sg:phone":"+61 2 6342 9429",
    "sg:postcode":"2794",
    "sg:province":"NSW",
    "sg:tags":[
        "contractor"
    ],
    "wof:name":"Bridges Deerfield Park",
    "wof:placetype":"venue"
},
  "geometry": {"coordinates":[148.68020629899999,-33.8211898804],"type":"Point"}
}