{
  "type": "Feature",
  "properties": {
    "iso:country":"AU",
    "sg:address":"Suite 19, Level 11 418a Elizabeth St",
    "sg:city":"Surry Hills",
    "sg:classifiers":[
        {
            "category":"Education",
            "subcategory":"Special Training",
            "type":"Public Place"
        }
    ],
    "sg:phone":"+61 2 9282 9334",
    "sg:postcode":"2010",
    "sg:province":"NSW",
    "sg:tags":[
        "development"
    ],
    "wof:name":"H & H Accredited Training Australasia Inc",
    "wof:placetype":"venue"
},
  "geometry": {"coordinates":[151.20840454099999,-33.8863525391],"type":"Point"}
}