{
  "type": "Feature",
  "properties": {
    "addr:full":"Unit 1/85- 87 Arden St Coogee NSW 2034",
    "addr:housenumber":"87",
    "addr:postcode":"2034",
    "addr:street":"Arden St",
    "iso:country":"AU",
    "sg:address":"Unit 1/85- 87 Arden St",
    "sg:city":"Coogee",
    "sg:classifiers":[
        {
            "category":"Professional",
            "subcategory":"Engineering",
            "type":"Services"
        }
    ],
    "sg:phone":"+61 2 9665 8182",
    "sg:postcode":"2034",
    "sg:province":"NSW",
    "sg:tags":[
        "consulting",
        "engineer"
    ],
    "wof:name":"Campbell James Drafting Services Pty Ltd",
    "wof:placetype":"venue"
},
  "geometry": {"coordinates":[151.25851440400001,-33.9134407043],"type":"Point"}
}