{
  "type": "Feature",
  "properties": {
    "addr:full":"63 Church St Whittlesea VIC 3757",
    "addr:housenumber":"63",
    "addr:postcode":"3757",
    "addr:street":"Church St",
    "iso:country":"AU",
    "sg:address":"63 Church St",
    "sg:city":"Whittlesea",
    "sg:classifiers":[
        {
            "category":"Banks & Credit Unions",
            "subcategory":"Bank",
            "type":"Services"
        }
    ],
    "sg:phone":"+61 13 20 32",
    "sg:postcode":"3757",
    "sg:province":"VIC",
    "wof:name":"Westpac",
    "wof:placetype":"venue"
},
  "geometry": {"coordinates":[145.11781300000001,-37.512333],"type":"Point"}
}