{
  "type": "Feature",
  "properties": {
    "addr:full":"15 Cree St Greenfield Park NSW 2176",
    "addr:housenumber":"15",
    "addr:postcode":"2176",
    "addr:street":"Cree St",
    "iso:country":"AU",
    "sg:address":"15 Cree St",
    "sg:city":"Greenfield Park",
    "sg:classifiers":[
        {
            "category":"Building & Trades",
            "subcategory":"Equipment Rental",
            "type":"Services"
        }
    ],
    "sg:phone":"+61 402 315 847",
    "sg:postcode":"2176",
    "sg:province":"NSW",
    "sg:tags":[
        "platform",
        "hire",
        "work",
        "elevating"
    ],
    "wof:name":"Sky High Rentals",
    "wof:placetype":"venue"
},
  "geometry": {"coordinates":[150.88851928700001,-33.8792991638],"type":"Point"}
}