{
  "type": "Feature",
  "properties": {
    "iso:country":"AU",
    "sg:address":"Dianella Plaza Cnr Grand Promenade & Alexander Dr",
    "sg:city":"Dianella",
    "sg:classifiers":[
        {
            "category":"Shopping",
            "subcategory":"Optical Goods",
            "type":"Retail Goods"
        }
    ],
    "sg:phone":"+61 8 9463 4288",
    "sg:postcode":"6059",
    "sg:province":"WA",
    "sg:tags":[
        "dispenser",
        "prescription"
    ],
    "wof:name":"Visual Eyes Optical Centre",
    "wof:placetype":"venue"
},
  "geometry": {"coordinates":[115.86994934099999,-31.895740509],"type":"Point"}
}