{
  "type": "Feature",
  "properties": {
    "iso:country":"AU",
    "sg:address":"12498 Carnar Hwy St",
    "sg:city":"George",
    "sg:classifiers":[
        {
            "category":"Personal",
            "subcategory":"Skin Care",
            "type":"Services"
        }
    ],
    "sg:phone":"+61 7 4625 3279",
    "sg:postcode":"4487",
    "sg:province":"QLD",
    "sg:tags":[
        "merchant",
        "hide"
    ],
    "wof:name":"Wattle Glen Pet Foods",
    "wof:placetype":"venue"
},
  "geometry": {"coordinates":[148.58096313499999,-28.0376491547],"type":"Point"}
}