{
  "type": "Feature",
  "properties": {
    "iso:country":"AU",
    "sg:address":"169 Camp Rd",
    "sg:city":"Cowra",
    "sg:classifiers":[
        {
            "category":"Building & Trades",
            "subcategory":"Construction",
            "type":"Services"
        }
    ],
    "sg:phone":"+61 2 6342 1630",
    "sg:postcode":"2794",
    "sg:province":"NSW",
    "sg:tags":[
        "contractor"
    ],
    "wof:name":"Temple J W Builder",
    "wof:placetype":"venue"
},
  "geometry": {"coordinates":[148.73628234899999,-33.8329582214],"type":"Point"}
}