{
  "type": "Feature",
  "properties": {
    "addr:full":"5 Shinji Crt Joondalup WA 6027",
    "addr:housenumber":"5",
    "addr:postcode":"6027",
    "addr:street":"Shinji Crt",
    "iso:country":"AU",
    "sg:address":"5 Shinji Crt",
    "sg:city":"Joondalup",
    "sg:classifiers":[
        {
            "category":"Building & Trades",
            "subcategory":"Construction",
            "type":"Services"
        }
    ],
    "sg:phone":"+61 401 858 506",
    "sg:postcode":"6027",
    "sg:province":"WA",
    "sg:tags":[
        "brick",
        "paving"
    ],
    "wof:name":"Carramar Retaining & Brick Paving",
    "wof:placetype":"venue"
},
  "geometry": {"coordinates":[115.764373779,-31.7201061249],"type":"Point"}
}