{
  "type": "Feature",
  "properties": {
    "addr:full":"33 Croydon St Lakemba NSW 2195",
    "addr:housenumber":"33",
    "addr:postcode":"2195",
    "addr:street":"Croydon St",
    "iso:country":"AU",
    "sg:address":"33 Croydon St",
    "sg:city":"Lakemba",
    "sg:classifiers":[
        {
            "category":"Organizations",
            "subcategory":"Non-profit Organization",
            "type":"Services"
        }
    ],
    "sg:phone":"+61 2 9759 4494",
    "sg:postcode":"2195",
    "sg:province":"NSW",
    "sg:tags":[
        "support",
        "disability",
        "organisation"
    ],
    "wof:name":"Koorana Child & Family Centre",
    "wof:placetype":"venue"
},
  "geometry": {"coordinates":[151.07661438,-33.9218025208],"type":"Point"}
}