{
  "type": "Feature",
  "properties": {
    "iso:country":"AU",
    "sg:address":"101 Chandler St",
    "sg:city":"Garbutt",
    "sg:classifiers":[
        {
            "category":"Professional",
            "subcategory":"Employment Agencies",
            "type":"Services"
        }
    ],
    "sg:phone":"+61 417 199 744",
    "sg:postcode":"4814",
    "sg:province":"QLD",
    "sg:tags":[
        "entertainer",
        "agent"
    ],
    "wof:name":"Townsville Country Music Association",
    "wof:placetype":"venue"
},
  "geometry": {"coordinates":[146.77290300000001,-19.261301],"type":"Point"}
}