{
  "type": "Feature",
  "properties": {
    "addr:full":"35 Williamstown Rd Doubleview WA 6018",
    "addr:housenumber":"35",
    "addr:postcode":"6018",
    "addr:street":"Williamstown Rd",
    "iso:country":"AU",
    "sg:address":"35 Williamstown Rd",
    "sg:city":"Doubleview",
    "sg:classifiers":[
        {
            "category":"Education",
            "subcategory":"School",
            "type":"Public Place"
        }
    ],
    "sg:phone":"+61 8 9446 4558",
    "sg:postcode":"6018",
    "sg:province":"WA",
    "wof:name":"Holy Rosary Primary School",
    "wof:placetype":"venue"
},
  "geometry": {"coordinates":[115.78717041,-31.9083557129],"type":"Point"}
}