{
  "type": "Feature",
  "properties": {
    "iso:country":"AU",
    "sg:address":"PO Box 1346",
    "sg:city":"Cleveland",
    "sg:classifiers":[
        {
            "category":"Professional",
            "subcategory":"Detective & Security Services",
            "type":"Services"
        }
    ],
    "sg:phone":"+61 7 3821 7446",
    "sg:postcode":"4163",
    "sg:province":"QLD",
    "sg:tags":[
        "guard",
        "patrol"
    ],
    "wof:name":"SIA Security",
    "wof:placetype":"venue"
},
  "geometry": {"coordinates":[153.26710510300001,-27.5265293121],"type":"Point"}
}