{
  "type": "Feature",
  "properties": {
    "addr:full":"552-560 Church St North Parramatta NSW 2151",
    "addr:housenumber":"552-560",
    "addr:postcode":"2151",
    "addr:street":"Church St",
    "iso:country":"AU",
    "sg:address":"552-560 Church St",
    "sg:city":"North Parramatta",
    "sg:classifiers":[
        {
            "category":"Building & Trades",
            "subcategory":"Locksmith",
            "type":"Services"
        }
    ],
    "sg:phone":"+61 1300 500 605",
    "sg:postcode":"2151",
    "sg:province":"NSW",
    "sg:tags":[
        "lock"
    ],
    "wof:name":"Independent Locksmiths & Security",
    "wof:placetype":"venue"
},
  "geometry": {"coordinates":[151.003540039,-33.7989845276],"type":"Point"}
}