{
  "type": "Feature",
  "properties": {
    "iso:country":"AU",
    "sg:address":"54 John St",
    "sg:city":"Salisbury",
    "sg:classifiers":[
        {
            "category":"Food & Beverages",
            "subcategory":"Supermarket",
            "type":"Retail Goods"
        }
    ],
    "sg:phone":"+61 8 8258 5111",
    "sg:postcode":"5108",
    "sg:province":"SA",
    "sg:tags":[
        "grocery",
        "store"
    ],
    "wof:name":"Rite Price Grocery Clearance Store",
    "wof:placetype":"venue"
},
  "geometry": {"coordinates":[138.64495849599999,-34.7623405457],"type":"Point"}
}