{
  "type": "Feature",
  "properties": {
    "addr:full":"56 Old Coast Rd Australind WA 6233",
    "addr:housenumber":"56",
    "addr:postcode":"6233",
    "addr:street":"Old Coast Rd",
    "iso:country":"AU",
    "sg:address":"56 Old Coast Rd",
    "sg:city":"Australind",
    "sg:classifiers":[
        {
            "category":"Retail",
            "subcategory":"Veterinary Services",
            "type":"Services"
        }
    ],
    "sg:phone":"+61 8 9797 1584",
    "sg:postcode":"6233",
    "sg:province":"WA",
    "sg:tags":[
        "surgeon"
    ],
    "wof:name":"australind vet",
    "wof:placetype":"venue"
},
  "geometry": {"coordinates":[115.713707,-33.282955],"type":"Point"}
}