{
  "type": "Feature",
  "properties": {
    "addr:full":"184 Bapaume Rd Holland Park West QLD 4121",
    "addr:housenumber":"184",
    "addr:postcode":"4121",
    "addr:street":"Bapaume Rd",
    "iso:country":"AU",
    "sg:address":"184 Bapaume Rd",
    "sg:city":"Holland Park West",
    "sg:classifiers":[
        {
            "category":"Arena",
            "subcategory":"Sports Club",
            "type":"Entertainment"
        }
    ],
    "sg:phone":"+61 7 3830 5204",
    "sg:postcode":"4121",
    "sg:province":"QLD",
    "sg:tags":[
        "defence",
        "supply",
        "self",
        "instruction",
        "martial art"
    ],
    "wof:name":"Renshu Kai Australia",
    "wof:placetype":"venue"
},
  "geometry": {"coordinates":[153.06234741200001,-27.5342941284],"type":"Point"}
}