{
  "type": "Feature",
  "properties": {
    "addr:full":"Level 5/ 445 Upper Edward St Spring Hill QLD 4000",
    "addr:housenumber":"/ 445",
    "addr:postcode":"4000",
    "addr:street":"Upper Edward St",
    "iso:country":"AU",
    "sg:address":"Level 5/ 445 Upper Edward St",
    "sg:city":"Spring Hill",
    "sg:classifiers":[
        {
            "category":"Insurance",
            "subcategory":"Insurance Agent",
            "type":"Services"
        }
    ],
    "sg:phone":"+61 7 3831 1711",
    "sg:postcode":"4000",
    "sg:province":"QLD",
    "sg:tags":[
        "broker"
    ],
    "wof:name":"Zegenhagen Brett",
    "wof:placetype":"venue"
},
  "geometry": {"coordinates":[153.024490356,-27.4638004303],"type":"Point"}
}