{
  "type": "Feature",
  "properties": {
    "addr:full":"43 William St Orange NSW 2800",
    "addr:housenumber":"43",
    "addr:postcode":"2800",
    "addr:street":"William St",
    "iso:country":"AU",
    "sg:address":"43 William St",
    "sg:city":"Orange",
    "sg:classifiers":[
        {
            "category":"Shopping",
            "subcategory":"Mobile Phones",
            "type":"Retail Goods"
        }
    ],
    "sg:phone":"+61 2 6362 1523",
    "sg:postcode":"2800",
    "sg:province":"NSW",
    "sg:tags":[
        "telephone",
        "accessory"
    ],
    "wof:name":"Orange Retravision",
    "wof:placetype":"venue"
},
  "geometry": {"coordinates":[149.105636597,-33.2837142944],"type":"Point"}
}