{
  "type": "Feature",
  "properties": {
    "iso:country":"AU",
    "sg:address":"41 Burrows St",
    "sg:city":"Wondai",
    "sg:classifiers":[
        {
            "category":"Home & Garden",
            "subcategory":"Building Materials",
            "type":"Retail Goods"
        }
    ],
    "sg:phone":"+61 7 4162 3303",
    "sg:postcode":"4606",
    "sg:province":"QLD",
    "sg:tags":[
        "pre-mixed",
        "concrete"
    ],
    "wof:name":"KMM Concrete Pty Ltd",
    "wof:placetype":"venue"
},
  "geometry": {"coordinates":[151.868988,-26.306324],"type":"Point"}
}