{
  "type": "Feature",
  "properties": {
    "addr:full":"8 Crane St Homebush NSW 2140",
    "addr:housenumber":"8",
    "addr:postcode":"2140",
    "addr:street":"Crane St",
    "iso:country":"AU",
    "sg:address":"8 Crane St",
    "sg:city":"Homebush",
    "sg:classifiers":[
        {
            "category":"Building & Trades",
            "subcategory":"Plumbing",
            "type":"Services"
        }
    ],
    "sg:phone":"+61 2 9764 2790",
    "sg:postcode":"2140",
    "sg:province":"NSW",
    "sg:tags":[
        "plumber",
        "gasfitters"
    ],
    "wof:name":"Holland Bros Plumbing",
    "wof:placetype":"venue"
},
  "geometry": {"coordinates":[151.08059692399999,-33.8639984131],"type":"Point"}
}