{
  "type": "Feature",
  "properties": {
    "addr:full":"1 Peat Brooklyn NSW 2083 Brooklyn NSW 2083",
    "addr:housenumber":"1",
    "addr:postcode":"2083;2083",
    "addr:street":"Peat",
    "iso:country":"AU",
    "sg:address":"1 Peat Brooklyn NSW 2083",
    "sg:city":"Brooklyn",
    "sg:classifiers":[
        {
            "category":"Health Services",
            "subcategory":"Health Practitioner",
            "type":"Services"
        }
    ],
    "sg:phone":"+61 2 9985 8890",
    "sg:postcode":"2083",
    "sg:province":"NSW",
    "sg:tags":[
        "dietitian"
    ],
    "wof:name":"Easysteps Healthy Lifestyle Programs",
    "wof:placetype":"venue"
},
  "geometry": {"coordinates":[151.20709228499999,-33.5491065979],"type":"Point"}
}