{
  "type": "Feature",
  "properties": {
    "addr:full":"9 Ewan St Coburg VIC 3058",
    "addr:housenumber":"9",
    "addr:postcode":"3058",
    "addr:street":"Ewan St",
    "iso:country":"AU",
    "sg:address":"9 Ewan St",
    "sg:city":"Coburg",
    "sg:classifiers":[
        {
            "category":"Building & Trades",
            "subcategory":"Construction",
            "type":"Services"
        }
    ],
    "sg:phone":"+61 419 553 277",
    "sg:postcode":"3058",
    "sg:province":"VIC",
    "sg:tags":[
        "contractor"
    ],
    "wof:name":"Pergola n&#039; Things",
    "wof:placetype":"venue"
},
  "geometry": {"coordinates":[144.95855712900001,-37.7471046448],"type":"Point"}
}