{
  "type": "Feature",
  "properties": {
    "addr:full":"132 Jervis Bay Rd Falls Creek NSW 2540",
    "addr:housenumber":"132",
    "addr:postcode":"2540",
    "addr:street":"Jervis Bay Rd",
    "iso:country":"AU",
    "sg:address":"132 Jervis Bay Rd",
    "sg:city":"Falls Creek",
    "sg:classifiers":[
        {
            "category":"Farming",
            "subcategory":"Fish & Marine Products",
            "type":"Manufacturing & Wholesale Goods"
        }
    ],
    "sg:phone":"+61 2 4447 8505",
    "sg:postcode":"2540",
    "sg:province":"NSW",
    "sg:tags":[
        "emu",
        "farmer"
    ],
    "wof:name":"Marayong Park Emu Farm",
    "wof:placetype":"venue"
},
  "geometry": {"coordinates":[150.59754943900001,-34.992061615],"type":"Point"}
}