{
  "type": "Feature",
  "properties": {
    "iso:country":"AU",
    "sg:address":"32 Clapham Rd",
    "sg:city":"Regents Park",
    "sg:classifiers":[
        {
            "category":"Transit Center",
            "subcategory":"Passenger",
            "type":"Transportation"
        }
    ],
    "sg:phone":"+61 2 9644 9755",
    "sg:postcode":"2143",
    "sg:province":"NSW",
    "sg:tags":[
        "packing",
        "gasket"
    ],
    "wof:name":"James Walker Australia Pty Ltd",
    "wof:placetype":"venue"
},
  "geometry": {"coordinates":[151.01799011200001,-33.8843841553],"type":"Point"}
}