{
  "type": "Feature",
  "properties": {
    "addr:full":"154 Booran Rd Caulfield South VIC 3162",
    "addr:housenumber":"154",
    "addr:postcode":"3162",
    "addr:street":"Booran Rd",
    "iso:country":"AU",
    "sg:address":"154 Booran Rd",
    "sg:city":"Caulfield South",
    "sg:classifiers":[
        {
            "category":"Personal",
            "type":"Services"
        }
    ],
    "sg:phone":"+61 1300 764 609",
    "sg:postcode":"3162",
    "sg:province":"VIC",
    "sg:tags":[
        "introduction",
        "social"
    ],
    "wof:name":"Pair Of Hearts Pty Ltd",
    "wof:placetype":"venue"
},
  "geometry": {"coordinates":[145.03613281200001,-37.8959922791],"type":"Point"}
}