{
  "type": "Feature",
  "properties": {
    "addr:full":"141 Shakespeare St Mackay QLD 4740",
    "addr:housenumber":"141",
    "addr:postcode":"4740",
    "addr:street":"Shakespeare St",
    "iso:country":"AU",
    "sg:address":"141 Shakespeare St",
    "sg:city":"Mackay",
    "sg:classifiers":[
        {
            "category":"Autos & Motor Vehicles",
            "subcategory":"Automobile Sales",
            "type":"Retail Goods"
        }
    ],
    "sg:phone":"+61 7 4957 5075",
    "sg:postcode":"4740",
    "sg:province":"QLD",
    "sg:tags":[
        "equipment",
        "trailer"
    ],
    "wof:name":"Mackay Tyrepower",
    "wof:placetype":"venue"
},
  "geometry": {"coordinates":[149.18220500000001,-21.147123],"type":"Point"}
}