{
  "type": "Feature",
  "properties": {
    "iso:country":"AU",
    "sg:address":"3 Suter St",
    "sg:city":"Southport",
    "sg:classifiers":[
        {
            "category":"Professional",
            "subcategory":"Employment Agencies",
            "type":"Services"
        }
    ],
    "sg:phone":"+61 7 5527 1832",
    "sg:postcode":"4215",
    "sg:province":"QLD",
    "wof:name":"Mission Australia",
    "wof:placetype":"venue"
},
  "geometry": {"coordinates":[153.41209411599999,-27.9699497223],"type":"Point"}
}