{
  "type": "Feature",
  "properties": {
    "addr:full":"7 Rosslyn St West Leederville WA 6007",
    "addr:housenumber":"7",
    "addr:postcode":"6007",
    "addr:street":"Rosslyn St West",
    "iso:country":"AU",
    "sg:address":"7 Rosslyn St",
    "sg:city":"West Leederville",
    "sg:classifiers":[
        {
            "category":"Manufacturing",
            "subcategory":"Glass & Minerals",
            "type":"Manufacturing & Wholesale Goods"
        }
    ],
    "sg:phone":"+61 8 9388 1166",
    "sg:postcode":"6007",
    "sg:province":"WA",
    "sg:tags":[
        "exploration"
    ],
    "wof:name":"Azumah Resources Limited",
    "wof:placetype":"venue"
},
  "geometry": {"coordinates":[115.833091736,-31.9417285919],"type":"Point"}
}