{
  "type": "Feature",
  "properties": {
    "addr:full":"7 Eveleigh St Wooloowin QLD 4030",
    "addr:housenumber":"7",
    "addr:postcode":"4030",
    "addr:street":"Eveleigh St",
    "iso:country":"AU",
    "sg:address":"7 Eveleigh St",
    "sg:city":"Wooloowin",
    "sg:classifiers":[
        {
            "category":"Health Services",
            "subcategory":"Doctor",
            "type":"Services"
        }
    ],
    "sg:phone":"+61 7 3857 3773",
    "sg:postcode":"4030",
    "sg:province":"QLD",
    "sg:tags":[
        "podiatrist"
    ],
    "wof:name":"Burton Margaret",
    "wof:placetype":"venue"
},
  "geometry": {"coordinates":[153.04020700000001,-27.415365],"type":"Point"}
}