{
  "type": "Feature",
  "properties": {
    "addr:full":"30 Dalton Drv Maroochydore QLD 4558",
    "addr:housenumber":"30",
    "addr:postcode":"4558",
    "addr:street":"Dalton Drv",
    "iso:country":"AU",
    "sg:address":"30 Dalton Drv",
    "sg:city":"Maroochydore",
    "sg:classifiers":[
        {
            "category":"Education",
            "subcategory":"Kindergarten",
            "type":"Public Place"
        }
    ],
    "sg:phone":"+61 7 5479 1411",
    "sg:postcode":"4558",
    "sg:province":"QLD",
    "sg:tags":[
        "pre-schools"
    ],
    "wof:name":"Horton Lakes Child Care Centre",
    "wof:placetype":"venue"
},
  "geometry": {"coordinates":[153.08880615199999,-26.6670532227],"type":"Point"}
}