{
  "type": "Feature",
  "properties": {
    "addr:full":"25 Damons Rd Mt Taylor VIC 3875",
    "addr:housenumber":"25",
    "addr:postcode":"3875",
    "addr:street":"Damons Rd",
    "iso:country":"AU",
    "sg:address":"25 Damons Rd",
    "sg:city":"Mt Taylor",
    "sg:classifiers":[
        {
            "category":"Building & Trades",
            "subcategory":"Landscaping Services",
            "type":"Services"
        }
    ],
    "sg:phone":"+61 3 5157 9366",
    "sg:postcode":"3875",
    "sg:province":"VIC",
    "sg:tags":[
        "designer",
        "landscape",
        "contractor"
    ],
    "wof:name":"Greenfingers Landscaping",
    "wof:placetype":"venue"
},
  "geometry": {"coordinates":[147.59715270999999,-37.7646102905],"type":"Point"}
}