{
  "type": "Feature",
  "properties": {
    "addr:full":"Unit 1/91 Hemphill Ave, Mt Prichard NSW 2170 Liverpool NSW 2170",
    "addr:housenumber":"91",
    "addr:postcode":"2170;2170",
    "addr:street":"Hemphill Ave",
    "iso:country":"AU",
    "sg:address":"Unit 1/91 Hemphill Ave, Mt Prichard NSW 2170",
    "sg:city":"Liverpool",
    "sg:classifiers":[
        {
            "category":"Retail",
            "subcategory":"Driving School",
            "type":"Services"
        }
    ],
    "sg:phone":"+61 413 597 265",
    "sg:postcode":"2170",
    "sg:province":"NSW",
    "wof:name":"Petrous Driving School",
    "wof:placetype":"venue"
},
  "geometry": {"coordinates":[150.89956665,-33.9034233093],"type":"Point"}
}