{
  "type": "Feature",
  "properties": {
    "addr:full":"Shp 235, Lvl 1 , Westfield Shoppingtown Burwood NSW 2134",
    "addr:housenumber":"235",
    "addr:postcode":"2134",
    "iso:country":"AU",
    "sg:address":"Shp 235, Lvl 1",
    "sg:city":", Westfield Shoppingtown Burwood",
    "sg:classifiers":[
        {
            "category":"Personal",
            "subcategory":"Beauty Salon",
            "type":"Services"
        }
    ],
    "sg:phone":"+61 2 9745 2629",
    "sg:postcode":"2134",
    "sg:province":"NSW",
    "sg:tags":[
        "hairdresser"
    ],
    "wof:name":"Hair By Nivine",
    "wof:placetype":"venue"
},
  "geometry": {"coordinates":[151.103515625,-33.8781852722],"type":"Point"}
}