{
  "type": "Feature",
  "properties": {
    "iso:country":"AU",
    "sg:address":"Burnside Diabetes Centre 2 Kensington Rd",
    "sg:city":"Rose Park",
    "sg:classifiers":[
        {
            "category":"Health Services",
            "subcategory":"Doctor",
            "type":"Services"
        }
    ],
    "sg:phone":"+61 8 8332 4844",
    "sg:postcode":"5067",
    "sg:province":"SA",
    "sg:tags":[
        "medical",
        "practitioner"
    ],
    "wof:name":"Coates Penelope Dr",
    "wof:placetype":"venue"
},
  "geometry": {"coordinates":[138.625656128,-34.9276542664],"type":"Point"}
}