{
  "type": "Feature",
  "properties": {
    "addr:full":"31 Couch Rd Griffith NSW 2680",
    "addr:housenumber":"31",
    "addr:postcode":"2680",
    "addr:street":"Couch Rd",
    "iso:country":"AU",
    "sg:address":"31 Couch Rd",
    "sg:city":"Griffith",
    "sg:classifiers":[
        {
            "category":"Building & Trades",
            "subcategory":"Construction",
            "type":"Services"
        }
    ],
    "sg:phone":"+61 2 6962 7442",
    "sg:postcode":"2680",
    "sg:province":"NSW",
    "sg:tags":[
        "earth",
        "excavating",
        "moving",
        "contractor"
    ],
    "wof:name":"Fred Stevenson Earthmoving",
    "wof:placetype":"venue"
},
  "geometry": {"coordinates":[146.049057,-34.293484],"type":"Point"}
}