{
  "type": "Feature",
  "properties": {
    "iso:country":"AU",
    "sg:address":"3 Harris St",
    "sg:city":"Blackburn North",
    "sg:classifiers":[
        {
            "category":"Professional",
            "subcategory":"Employment Agencies",
            "type":"Services"
        }
    ],
    "sg:phone":"+61 3 9878 5898",
    "sg:postcode":"3130",
    "sg:province":"VIC",
    "sg:tags":[
        "occupational",
        "therapist"
    ],
    "wof:name":"Kearns Janet",
    "wof:placetype":"venue"
},
  "geometry": {"coordinates":[145.153686523,-37.8085823059],"type":"Point"}
}