{
  "type": "Feature",
  "properties": {
    "iso:country":"AU",
    "sg:address":"24 Windsor Rd",
    "sg:city":"Croydon",
    "sg:classifiers":[
        {
            "category":"Home & Garden",
            "subcategory":"Hardware",
            "type":"Retail Goods"
        }
    ],
    "sg:phone":"+61 3 9722 8975",
    "sg:postcode":"3136",
    "sg:province":"VIC",
    "sg:tags":[
        "compressor",
        "air"
    ],
    "sg:website":"http://www.kaeser.com",
    "wof:name":"Promptair & Electrical Pty Ltd",
    "wof:placetype":"venue"
},
  "geometry": {"coordinates":[145.285766602,-37.7941741943],"type":"Point"}
}