{
  "type": "Feature",
  "properties": {
    "addr:full":"8 Station St Wollongong NSW 2500",
    "addr:housenumber":"8",
    "addr:postcode":"2500",
    "addr:street":"Station St",
    "iso:country":"AU",
    "sg:address":"8 Station St",
    "sg:city":"Wollongong",
    "sg:classifiers":[
        {
            "category":"Building & Trades",
            "subcategory":"Equipment Rental",
            "type":"Services"
        }
    ],
    "sg:phone":"+61 2 4223 6500",
    "sg:postcode":"2500",
    "sg:province":"NSW",
    "sg:tags":[
        "charting",
        "chart"
    ],
    "wof:name":"R.A.N. Hydrographic Office",
    "wof:placetype":"venue"
},
  "geometry": {"coordinates":[150.89236500000001,-34.412098],"type":"Point"}
}