{
  "type": "Feature",
  "properties": {
    "iso:country":"AU",
    "sg:address":"49 Mary St",
    "sg:city":"Ethelton",
    "sg:classifiers":[
        {
            "category":"Professional",
            "subcategory":"Art Services",
            "type":"Services"
        }
    ],
    "sg:phone":"+61 8 8341 7919",
    "sg:postcode":"5015",
    "sg:province":"SA",
    "sg:tags":[
        "picture",
        "frame",
        "framing"
    ],
    "wof:name":"Arid Zone Framing",
    "wof:placetype":"venue"
},
  "geometry": {"coordinates":[138.49382019000001,-34.8487968445],"type":"Point"}
}