{
  "type": "Feature",
  "properties": {
    "addr:full":"55 Stanley Ave Mt Waverley VIC 3149",
    "addr:housenumber":"55",
    "addr:postcode":"3149",
    "addr:street":"Stanley Ave Mt",
    "iso:country":"AU",
    "sg:address":"55 Stanley Ave",
    "sg:city":"Mt Waverley",
    "sg:classifiers":[
        {
            "category":"Professional",
            "subcategory":"Accounting & Tax Preparation",
            "type":"Services"
        }
    ],
    "sg:phone":"+61 3 9544 2800",
    "sg:postcode":"3149",
    "sg:province":"VIC",
    "sg:tags":[
        "consultant",
        "taxation"
    ],
    "wof:name":"Falconer Accountax",
    "wof:placetype":"venue"
},
  "geometry": {"coordinates":[145.114379883,-37.8943367004],"type":"Point"}
}