{
  "type": "Feature",
  "properties": {
    "addr:full":"1st Floor/ 160 Stirling Hwy Nedlands WA 6907",
    "addr:housenumber":"/ 160",
    "addr:postcode":"6907",
    "addr:street":"Stirling Hwy",
    "iso:country":"AU",
    "sg:address":"1st Floor/ 160 Stirling Hwy",
    "sg:city":"Nedlands",
    "sg:classifiers":[
        {
            "category":"Professional",
            "subcategory":"Accounting & Tax Preparation",
            "type":"Services"
        }
    ],
    "sg:phone":"+61 8 9389 7779",
    "sg:postcode":"6907",
    "sg:province":"WA",
    "sg:tags":[
        "accountant",
        "auditor"
    ],
    "wof:name":"Paragon",
    "wof:placetype":"venue"
},
  "geometry": {"coordinates":[115.79360199,-31.9810085297],"type":"Point"}
}