{
  "type": "Feature",
  "properties": {
    "iso:country":"AU",
    "sg:address":"3 Sugarloaf Rd",
    "sg:city":"Beaconsfield Upper",
    "sg:classifiers":[
        {
            "category":"Building & Trades",
            "subcategory":"Cleaning & Sanitation",
            "type":"Services"
        }
    ],
    "sg:phone":"+61 3 5944 3646",
    "sg:postcode":"3808",
    "sg:province":"VIC",
    "sg:tags":[
        "grease",
        "trap"
    ],
    "wof:name":"Amclear Liquid Waste",
    "wof:placetype":"venue"
},
  "geometry": {"coordinates":[145.42103599999999,-38.007015],"type":"Point"}
}