{
  "type": "Feature",
  "properties": {
    "addr:full":"20 Scarba St Middle Park QLD 4074",
    "addr:housenumber":"20",
    "addr:postcode":"4074",
    "addr:street":"Scarba St",
    "iso:country":"AU",
    "sg:address":"20 Scarba St",
    "sg:city":"Middle Park",
    "sg:classifiers":[
        {
            "category":"Train Station",
            "subcategory":"Rail",
            "type":"Transportation"
        }
    ],
    "sg:phone":"+61 419 715 591",
    "sg:postcode":"4074",
    "sg:province":"QLD",
    "sg:tags":[
        "marine",
        "engineer"
    ],
    "wof:name":"I.P.K. Marine Electrics Pty Ltd",
    "wof:placetype":"venue"
},
  "geometry": {"coordinates":[152.92515564000001,-27.5512638092],"type":"Point"}
}