{
  "type": "Feature",
  "properties": {
    "addr:full":"21 Hale St Orange NSW 2800",
    "addr:housenumber":"21",
    "addr:postcode":"2800",
    "addr:street":"Hale St",
    "iso:country":"AU",
    "sg:address":"21 Hale St",
    "sg:city":"Orange",
    "sg:classifiers":[
        {
            "category":"Retail",
            "subcategory":"Repair Shop",
            "type":"Services"
        }
    ],
    "sg:phone":"+61 2 6361 2430",
    "sg:postcode":"2800",
    "sg:province":"NSW",
    "sg:tags":[
        "restorer",
        "repairer",
        "carpet"
    ],
    "wof:name":"Beath Terry",
    "wof:placetype":"venue"
},
  "geometry": {"coordinates":[149.11593627900001,-33.2796783447],"type":"Point"}
}