{
  "type": "Feature",
  "properties": {
    "iso:country":"AU",
    "sg:address":"1725 Albany Hwy",
    "sg:city":"Kenwick",
    "sg:classifiers":[
        {
            "category":"Autos & Motor Vehicles",
            "subcategory":"Automobile Sales",
            "type":"Retail Goods"
        }
    ],
    "sg:phone":"+61 8 9493 4134",
    "sg:postcode":"6107",
    "sg:province":"WA",
    "sg:tags":[
        "car",
        "used"
    ],
    "wof:name":"Trademark Motor Co",
    "wof:placetype":"venue"
},
  "geometry": {"coordinates":[115.97032165500001,-32.0393562317],"type":"Point"}
}