{
  "type": "Feature",
  "properties": {
    "iso:country":"AU",
    "sg:address":"72 Burns Bay Rd",
    "sg:city":"Lane Cove",
    "sg:classifiers":[
        {
            "category":"Retail",
            "subcategory":"Event Space",
            "type":"Services"
        }
    ],
    "sg:phone":"+61 2 9427 3696",
    "sg:postcode":"2066",
    "sg:province":"NSW",
    "sg:tags":[
        "venue",
        "reception",
        "wedding"
    ],
    "wof:name":"Mandalay Function Centre",
    "wof:placetype":"venue"
},
  "geometry": {"coordinates":[151.16604614299999,-33.814994812],"type":"Point"}
}