{
  "type": "Feature",
  "properties": {
    "addr:full":"Shop 4/ 152 Fern St Gerringong NSW 2534",
    "addr:housenumber":"shop 4 / 152",
    "addr:postcode":"2534",
    "addr:street":"Fern St",
    "iso:country":"AU",
    "sg:address":"Shop 4/ 152 Fern St",
    "sg:city":"Gerringong",
    "sg:classifiers":[
        {
            "category":"Fast Food",
            "type":"Food & Drink"
        }
    ],
    "sg:phone":"+61 2 4234 4989",
    "sg:postcode":"2534",
    "sg:province":"NSW",
    "sg:tags":[
        "away",
        "take"
    ],
    "wof:name":"Lucky Harbour Chinese Restaurant",
    "wof:placetype":"venue"
},
  "geometry": {"coordinates":[150.82725524899999,-34.7476043701],"type":"Point"}
}