{
  "type": "Feature",
  "properties": {
    "addr:full":"230 Richmond Rd Marleston SA 5033",
    "addr:housenumber":"230",
    "addr:postcode":"5033",
    "addr:street":"Richmond Rd",
    "iso:country":"AU",
    "sg:address":"230 Richmond Rd",
    "sg:city":"Marleston",
    "sg:phone":"+61 8 8443 9061",
    "sg:postcode":"5033",
    "sg:province":"SA",
    "wof:name":"Master Tanks",
    "wof:placetype":"venue"
},
  "geometry": {"coordinates":[138.559616089,-34.9428062439],"type":"Point"}
}