{
  "type": "Feature",
  "properties": {
    "iso:country":"AU",
    "sg:address":"32 Scantlebury Crs",
    "sg:city":"Theodore",
    "sg:classifiers":[
        {
            "category":"Professional",
            "subcategory":"Computer Services",
            "type":"Services"
        }
    ],
    "sg:phone":"+61 422 397 979",
    "sg:postcode":"2905",
    "sg:province":"ACT",
    "sg:tags":[
        "consultant",
        "system"
    ],
    "wof:name":"M@c Services",
    "wof:placetype":"venue"
},
  "geometry": {"coordinates":[149.124557495,-35.4470710754],"type":"Point"}
}