{
  "type": "Feature",
  "properties": {
    "iso:country":"AU",
    "sg:address":"46 Robertson St",
    "sg:city":"Merrylands",
    "sg:classifiers":[
        {
            "category":"Professional",
            "subcategory":"Computer Services",
            "type":"Services"
        }
    ],
    "sg:phone":"+61 407 702 417",
    "sg:postcode":"2160",
    "sg:province":"NSW",
    "sg:tags":[
        "consultant",
        "system"
    ],
    "wof:name":"Aspiring Technology Pty Ltd",
    "wof:placetype":"venue"
},
  "geometry": {"coordinates":[150.98817443900001,-33.83618927],"type":"Point"}
}