{
  "type": "Feature",
  "properties": {
    "iso:country":"AU",
    "sg:address":"6 Albert St",
    "sg:city":"Rockhampton",
    "sg:classifiers":[
        {
            "category":"Autos & Motor Vehicles",
            "subcategory":"Automobile Sales",
            "type":"Retail Goods"
        }
    ],
    "sg:phone":"+61 7 4927 5666",
    "sg:postcode":"4702",
    "sg:province":"QLD",
    "sg:tags":[
        "car",
        "used"
    ],
    "wof:name":"CQ Auto Sales",
    "wof:placetype":"venue"
},
  "geometry": {"coordinates":[150.32307434099999,-23.4823226929],"type":"Point"}
}