{
  "type": "Feature",
  "properties": {
    "addr:full":"32 Foord Ave Hurlstone Park NSW 2193",
    "addr:housenumber":"32",
    "addr:postcode":"2193",
    "addr:street":"Foord Ave",
    "iso:country":"AU",
    "sg:address":"32 Foord Ave",
    "sg:city":"Hurlstone Park",
    "sg:classifiers":[
        {
            "category":"Banks & Credit Unions",
            "subcategory":"Bureau De Change",
            "type":"Services"
        }
    ],
    "sg:phone":"+61 2 9591 1419",
    "sg:postcode":"2193",
    "sg:province":"NSW",
    "sg:tags":[
        "publisher",
        "music"
    ],
    "wof:name":"Adrenalin Sounds",
    "wof:placetype":"venue"
},
  "geometry": {"coordinates":[151.12840299999999,-33.914345],"type":"Point"}
}