{
  "type": "Feature",
  "properties": {
    "addr:full":"2 Ingara Crt Erskine Park NSW 2759",
    "addr:housenumber":"2",
    "addr:postcode":"2759",
    "addr:street":"Ingara Crt",
    "iso:country":"AU",
    "sg:address":"2 Ingara Crt",
    "sg:city":"Erskine Park",
    "sg:classifiers":[
        {
            "category":"Retail",
            "subcategory":"Repair Shop",
            "type":"Services"
        }
    ],
    "sg:phone":"+61 2 9834 4445",
    "sg:postcode":"2759",
    "sg:province":"NSW",
    "sg:tags":[
        "upholsterer"
    ],
    "wof:name":"Delaporte Upholstery",
    "wof:placetype":"venue"
},
  "geometry": {"coordinates":[150.788986206,-33.8101425171],"type":"Point"}
}