{
  "type": "Feature",
  "properties": {
    "addr:full":"30 Elizabeth St Adelaide SA 5000",
    "addr:housenumber":"30",
    "addr:postcode":"5000",
    "addr:street":"Elizabeth St",
    "iso:country":"AU",
    "sg:address":"30 Elizabeth St",
    "sg:city":"Adelaide",
    "sg:classifiers":[
        {
            "category":"Professional",
            "subcategory":"Art Services",
            "type":"Services"
        }
    ],
    "sg:phone":"+61 8 8211 6101",
    "sg:postcode":"5000",
    "sg:province":"SA",
    "sg:tags":[
        "picture",
        "frame",
        "framing"
    ],
    "wof:name":"Moglia Fine Art",
    "wof:placetype":"venue"
},
  "geometry": {"coordinates":[138.59182739299999,-34.9249954224],"type":"Point"}
}