{
  "type": "Feature",
  "properties": {
    "addr:full":"Cnr Bowral & Jellore St Welby NSW 2575",
    "addr:postcode":"2575",
    "addr:street":"Cnr;St",
    "iso:country":"AU",
    "sg:address":"Cnr Bowral & Jellore St",
    "sg:city":"Welby",
    "sg:classifiers":[
        {
            "category":"Manufacturing",
            "subcategory":"Rubber & Plastics",
            "type":"Manufacturing & Wholesale Goods"
        }
    ],
    "sg:phone":"+61 2 4872 3300",
    "sg:postcode":"2575",
    "sg:province":"NSW",
    "sg:tags":[
        "fabricator"
    ],
    "wof:name":"Light Industries Pty Ltd",
    "wof:placetype":"venue"
},
  "geometry": {"coordinates":[150.42254638700001,-34.4381332397],"type":"Point"}
}