{
  "type": "Feature",
  "properties": {
    "addr:full":"443 Elizabeth St Melbourne VIC 3000",
    "addr:housenumber":"443",
    "addr:postcode":"3000",
    "addr:street":"Elizabeth St",
    "iso:country":"AU",
    "sg:address":"443 Elizabeth St",
    "sg:city":"Melbourne",
    "sg:classifiers":[
        {
            "category":"Building & Trades",
            "subcategory":"Locksmith",
            "type":"Services"
        }
    ],
    "sg:phone":"+61 3 9602 3400",
    "sg:postcode":"3000",
    "sg:province":"VIC",
    "sg:tags":[
        "lock"
    ],
    "wof:name":"Advance Locksmiths",
    "wof:placetype":"venue"
},
  "geometry": {"coordinates":[144.96043395999999,-37.8086433411],"type":"Point"}
}