{
  "type": "Feature",
  "properties": {
    "addr:full":"16 Celestial Ave Melbourne VIC 3000",
    "addr:housenumber":"16",
    "addr:postcode":"3000",
    "addr:street":"Celestial Ave",
    "iso:country":"AU",
    "sg:address":"16 Celestial Ave",
    "sg:city":"Melbourne",
    "sg:classifiers":[
        {
            "category":"Health Services",
            "subcategory":"Dentist",
            "type":"Services"
        }
    ],
    "sg:phone":"+61 3 9866 2230",
    "sg:postcode":"3000",
    "sg:province":"VIC",
    "wof:name":"Lee Stella Dr",
    "wof:placetype":"venue"
},
  "geometry": {"coordinates":[144.96635437,-37.811668396],"type":"Point"}
}