{
  "type": "Feature",
  "properties": {
    "addr:full":"6 Anderson St Yarraville VIC 3013",
    "addr:housenumber":"6",
    "addr:postcode":"3013",
    "addr:street":"Anderson St",
    "iso:country":"AU",
    "sg:address":"6 Anderson St",
    "sg:city":"Yarraville",
    "sg:classifiers":[
        {
            "category":"Food & Beverages",
            "subcategory":"Supermarket",
            "type":"Retail Goods"
        }
    ],
    "sg:phone":"+61 3 9318 0233",
    "sg:postcode":"3013",
    "sg:province":"VIC",
    "sg:tags":[
        "grocery",
        "store"
    ],
    "wof:name":"Tuckerbag Supermarkets",
    "wof:placetype":"venue"
},
  "geometry": {"coordinates":[144.89178466800001,-37.8166313171],"type":"Point"}
}