{
  "type": "Feature",
  "properties": {
    "addr:full":"119 Cecil Rd Cecil Park NSW 2171",
    "addr:housenumber":"119",
    "addr:postcode":"2171",
    "addr:street":"Cecil Rd",
    "iso:country":"AU",
    "sg:address":"119 Cecil Rd",
    "sg:city":"Cecil Park",
    "sg:classifiers":[
        {
            "category":"Real Estate",
            "subcategory":"Real Estate Operator",
            "type":"Services"
        }
    ],
    "sg:phone":"+61 2 9826 1311",
    "sg:postcode":"2171",
    "sg:province":"NSW",
    "sg:tags":[
        "concrete",
        "pumping"
    ],
    "wof:name":"Adduso Concrete & Pumping",
    "wof:placetype":"venue"
},
  "geometry": {"coordinates":[150.846237183,-33.9284286499],"type":"Point"}
}