{
  "type": "Feature",
  "properties": {
    "iso:country":"AU",
    "sg:address":"Prospect Vale Market Pl",
    "sg:city":"Prospect",
    "sg:classifiers":[
        {
            "category":"Health Services",
            "subcategory":"Optometrist",
            "type":"Services"
        }
    ],
    "sg:phone":"+61 3 6343 3329",
    "sg:postcode":"7250",
    "sg:province":"TAS",
    "wof:name":"Petchkov Alex",
    "wof:placetype":"venue"
},
  "geometry": {"coordinates":[147.14163207999999,-41.4667396545],"type":"Point"}
}