{
  "type": "Feature",
  "properties": {
    "iso:country":"AU",
    "sg:address":"Shop 8",
    "sg:city":"-10 Kippa-Ring Village Shopping Centre Kippa-",
    "sg:classifiers":[
        {
            "category":"Food & Beverages",
            "subcategory":"Fruits & Vegetables",
            "type":"Retail Goods"
        }
    ],
    "sg:phone":"+61 7 3283 1632",
    "sg:postcode":"4021",
    "sg:province":"QLD",
    "sg:tags":[
        "greengrocer",
        "fruiterer"
    ],
    "wof:name":"Kippa-Ring Fresh Market",
    "wof:placetype":"venue"
},
  "geometry": {"coordinates":[153.077225,-27.217278],"type":"Point"}
}