{
  "type": "Feature",
  "properties": {
    "addr:full":"172 Aumuller St Bungalow QLD 4870",
    "addr:housenumber":"172",
    "addr:postcode":"4870",
    "addr:street":"Aumuller St",
    "iso:country":"AU",
    "sg:address":"172 Aumuller St",
    "sg:city":"Bungalow",
    "sg:classifiers":[
        {
            "category":"Recreation",
            "subcategory":"Fishing",
            "type":"Entertainment"
        }
    ],
    "sg:phone":"+61 7 4031 4040",
    "sg:postcode":"4870",
    "sg:province":"QLD",
    "sg:tags":[
        "tackle"
    ],
    "wof:name":"Cairns Tackle World",
    "wof:placetype":"venue"
},
  "geometry": {"coordinates":[145.76026916500001,-16.9323501587],"type":"Point"}
}