{
  "type": "Feature",
  "properties": {
    "addr:full":"Hughes St Leongatha VIC 3953",
    "addr:postcode":"3953",
    "addr:street":"Hughes St",
    "iso:country":"AU",
    "sg:address":"Hughes St",
    "sg:city":"Leongatha",
    "sg:classifiers":[
        {
            "category":"Retail",
            "subcategory":"Auto Repair",
            "type":"Services"
        }
    ],
    "sg:phone":"+61 3 5662 5115",
    "sg:postcode":"3953",
    "sg:province":"VIC",
    "sg:tags":[
        "repairer",
        "motor",
        "engineer"
    ],
    "wof:name":"Ackland Automotive Repairs",
    "wof:placetype":"venue"
},
  "geometry": {"coordinates":[145.94749450699999,-38.4750137329],"type":"Point"}
}