{
  "type": "Feature",
  "properties": {
    "addr:full":"PO Box 337 Prahran VIC 3181",
    "addr:postcode":"3181",
    "iso:country":"AU",
    "sg:address":"PO Box 337",
    "sg:city":"Prahran",
    "sg:classifiers":[
        {
            "category":"Building & Trades",
            "subcategory":"Construction",
            "type":"Services"
        }
    ],
    "sg:phone":"+61 417 306 626",
    "sg:postcode":"3181",
    "sg:province":"VIC",
    "sg:tags":[
        "installation",
        "air conditioning"
    ],
    "wof:name":"Deluxair Airconditioning & Refrigeration Mechanical Services",
    "wof:placetype":"venue"
},
  "geometry": {"coordinates":[144.99342346200001,-37.8513412476],"type":"Point"}
}