{
  "type": "Feature",
  "properties": {
    "addr:full":"303 Padstow Rd Eight Mile Plains QLD 4113",
    "addr:housenumber":"303",
    "addr:postcode":"4113",
    "addr:street":"Padstow Rd",
    "iso:country":"AU",
    "sg:address":"303 Padstow Rd",
    "sg:city":"Eight Mile Plains",
    "sg:classifiers":[
        {
            "category":"Organizations",
            "subcategory":"Non-profit Organization",
            "type":"Services"
        }
    ],
    "sg:phone":"+61 7 3341 6644",
    "sg:postcode":"4113",
    "sg:province":"QLD",
    "sg:tags":[
        "support",
        "disability",
        "organisation"
    ],
    "wof:name":"Multiple Handicapped Association Of Queensland (Multicap)",
    "wof:placetype":"venue"
},
  "geometry": {"coordinates":[153.09101867699999,-27.57579422],"type":"Point"}
}