{
  "type": "Feature",
  "properties": {
    "addr:full":"21 Handley Ave Turramurra NSW 2074",
    "addr:housenumber":"21",
    "addr:postcode":"2074",
    "addr:street":"Handley Ave",
    "iso:country":"AU",
    "sg:address":"21 Handley Ave",
    "sg:city":"Turramurra",
    "sg:classifiers":[
        {
            "category":"Education",
            "subcategory":"Kindergarten",
            "type":"Public Place"
        }
    ],
    "sg:phone":"+61 2 9449 1445",
    "sg:postcode":"2074",
    "sg:province":"NSW",
    "sg:tags":[
        "pre-schools"
    ],
    "wof:name":"Pymble-Turramurra Kindergarten Inc",
    "wof:placetype":"venue"
},
  "geometry": {"coordinates":[151.14100647000001,-33.7232589722],"type":"Point"}
}