{
  "type": "Feature",
  "properties": {
    "iso:country":"AU",
    "sg:address":"72b Golda Ave",
    "sg:city":"Salisbury",
    "sg:classifiers":[
        {
            "category":"Food & Beverages",
            "subcategory":"Specialty",
            "type":"Retail Goods"
        }
    ],
    "sg:phone":"+61 7 3275 1047",
    "sg:postcode":"4107",
    "sg:province":"QLD",
    "sg:tags":[
        "product",
        "health"
    ],
    "wof:name":"Mannatech\ufffd Independant Associates",
    "wof:placetype":"venue"
},
  "geometry": {"coordinates":[153.03741455100001,-27.5572338104],"type":"Point"}
}