{
  "type": "Feature",
  "properties": {
    "addr:full":"Shp 66 /67 Westfield Shopngtwn Strathpine QLD 4500",
    "addr:housenumber":"66 / 67",
    "addr:postcode":"4500",
    "addr:street":"Westfield Shopngtwn",
    "iso:country":"AU",
    "sg:address":"Shp 66",
    "sg:city":"/67 Westfield Shopngtwn Strathpine",
    "sg:classifiers":[
        {
            "category":"Shopping",
            "subcategory":"Computers & Home Electronics",
            "type":"Retail Goods"
        }
    ],
    "sg:phone":"+61 7 3881 3199",
    "sg:postcode":"4500",
    "sg:province":"QLD",
    "sg:tags":[
        "equipment",
        "part",
        "electronic"
    ],
    "wof:name":"Dick Smith Electronics",
    "wof:placetype":"venue"
},
  "geometry": {"coordinates":[152.987823486,-27.3017196655],"type":"Point"}
}