{
  "type": "Feature",
  "properties": {
    "addr:full":"132 Imlay St Eden NSW 2551",
    "addr:housenumber":"132",
    "addr:postcode":"2551",
    "addr:street":"Imlay St",
    "iso:country":"AU",
    "sg:address":"132 Imlay St",
    "sg:city":"Eden",
    "sg:classifiers":[
        {
            "category":"Insurance",
            "subcategory":"Insurance Agent",
            "type":"Services"
        }
    ],
    "sg:phone":"+61 2 6492 1955",
    "sg:postcode":"2551",
    "sg:province":"NSW",
    "sg:tags":[
        "broker"
    ],
    "wof:name":"M & F Agencies",
    "wof:placetype":"venue"
},
  "geometry": {"coordinates":[149.91131591800001,-37.0728416443],"type":"Point"}
}