{
  "type": "Feature",
  "properties": {
    "addr:full":"PO Box 4305 Gumdale QLD 4154",
    "addr:postcode":"4154",
    "iso:country":"AU",
    "sg:address":"PO Box 4305",
    "sg:city":"Gumdale",
    "sg:classifiers":[
        {
            "category":"Utilities",
            "subcategory":"Telephone",
            "type":"Services"
        }
    ],
    "sg:phone":"+61 412 115 021",
    "sg:postcode":"4154",
    "sg:province":"QLD",
    "sg:tags":[
        "installation",
        "system",
        "maintenance"
    ],
    "wof:name":"Touchtone Voice & Data",
    "wof:placetype":"venue"
},
  "geometry": {"coordinates":[153.15179443400001,-27.4767303467],"type":"Point"}
}