{
  "type": "Feature",
  "properties": {
    "addr:full":"Factory 1, 13 Cameron St Cranbourne VIC 3977",
    "addr:housenumber":"13",
    "addr:postcode":"3977",
    "addr:street":"Cameron St",
    "iso:country":"AU",
    "sg:address":"Factory 1, 13 Cameron St",
    "sg:city":"Cranbourne",
    "sg:classifiers":[
        {
            "category":"Professional",
            "type":"Services"
        }
    ],
    "sg:phone":"+61 3 5995 5444",
    "sg:postcode":"3977",
    "sg:province":"VIC",
    "sg:tags":[
        "coating",
        "powder"
    ],
    "wof:name":"Blackdog Powdercoating Pty Ltd",
    "wof:placetype":"venue"
},
  "geometry": {"coordinates":[145.28834533700001,-38.1201248169],"type":"Point"}
}