{
  "type": "Feature",
  "properties": {
    "addr:full":"Shop 2, Luxford Crt Mt Druitt NSW 2770",
    "addr:housenumber":"shop 2",
    "addr:postcode":"2770",
    "addr:street":"Luxford Crt Mt",
    "iso:country":"AU",
    "sg:address":"Shop 2, Luxford Crt",
    "sg:city":"Mt Druitt",
    "sg:classifiers":[
        {
            "category":"Health Services",
            "subcategory":"Dentist",
            "type":"Services"
        }
    ],
    "sg:phone":"+61 2 9832 8577",
    "sg:postcode":"2770",
    "sg:province":"NSW",
    "wof:name":"Rezk Emad Dr",
    "wof:placetype":"venue"
},
  "geometry": {"coordinates":[150.82078552199999,-33.7645263672],"type":"Point"}
}