{
  "type": "Feature",
  "properties": {
    "addr:full":"1/13 Project Ave Noosaville QLD 4566",
    "addr:housenumber":"/",
    "addr:postcode":"4566",
    "addr:street":"Project Ave",
    "iso:country":"AU",
    "sg:address":"1/13 Project Ave",
    "sg:city":"Noosaville",
    "sg:classifiers":[
        {
            "category":"Manufacturing",
            "subcategory":"Building Materials",
            "type":"Manufacturing & Wholesale Goods"
        }
    ],
    "sg:phone":"+61 7 5474 3841",
    "sg:postcode":"4566",
    "sg:province":"QLD",
    "sg:tags":[
        "equipment",
        "handling"
    ],
    "wof:name":"Shelving & Racking Systems",
    "wof:placetype":"venue"
},
  "geometry": {"coordinates":[153.04620361299999,-26.4091892242],"type":"Point"}
}