{
  "type": "Feature",
  "properties": {
    "addr:full":"16 Trepid Crt Scarborough QLD 4020",
    "addr:housenumber":"16",
    "addr:postcode":"4020",
    "addr:street":"Trepid Crt",
    "iso:country":"AU",
    "sg:address":"16 Trepid Crt",
    "sg:city":"Scarborough",
    "sg:classifiers":[
        {
            "category":"Professional",
            "subcategory":"Accounting & Tax Preparation",
            "type":"Services"
        }
    ],
    "sg:phone":"+61 7 3203 4644",
    "sg:postcode":"4020",
    "sg:province":"QLD",
    "sg:tags":[
        "accountant",
        "auditor"
    ],
    "wof:name":"F Carter & Associates",
    "wof:placetype":"venue"
},
  "geometry": {"coordinates":[153.114014,-27.20532],"type":"Point"}
}