{
  "type": "Feature",
  "properties": {
    "addr:full":"96 Mansfield St Earlville QLD 4870",
    "addr:housenumber":"96",
    "addr:postcode":"4870",
    "addr:street":"Mansfield St",
    "iso:country":"AU",
    "sg:address":"96 Mansfield St",
    "sg:city":"Earlville",
    "sg:classifiers":[
        {
            "category":"Building & Trades",
            "subcategory":"Construction",
            "type":"Services"
        }
    ],
    "sg:phone":"+61 429 725 779",
    "sg:postcode":"4870",
    "sg:province":"QLD",
    "sg:tags":[
        "earth",
        "excavating",
        "moving",
        "contractor"
    ],
    "wof:name":"Gregg Construction",
    "wof:placetype":"venue"
},
  "geometry": {"coordinates":[145.72413635300001,-16.9454860687],"type":"Point"}
}