{
  "type": "Feature",
  "properties": {
    "iso:country":"AU",
    "sg:address":"Saltwater 8 First Ave",
    "sg:city":"Maroochydore",
    "sg:classifiers":[
        {
            "category":"Health Services",
            "subcategory":"Doctor",
            "type":"Services"
        }
    ],
    "sg:phone":"+61 1800 777 877",
    "sg:postcode":"4558",
    "sg:province":"QLD",
    "sg:tags":[
        "medical",
        "practitioner"
    ],
    "wof:name":"Sullivan Nicolaides Pathology",
    "wof:placetype":"venue"
},
  "geometry": {"coordinates":[153.09312439000001,-26.6545181274],"type":"Point"}
}