{
  "type": "Feature",
  "properties": {
    "iso:country":"AU",
    "sg:address":"43 Nicholson St",
    "sg:city":"Mitchelton",
    "sg:classifiers":[
        {
            "category":"Education",
            "subcategory":"School",
            "type":"Public Place"
        }
    ],
    "sg:phone":"+61 7 3354 2601",
    "sg:postcode":"4053",
    "sg:province":"QLD",
    "sg:tags":[
        "state",
        "except",
        "nsw"
    ],
    "wof:name":"Mitchelton State Preschool",
    "wof:placetype":"venue"
},
  "geometry": {"coordinates":[152.97055053700001,-27.4084949493],"type":"Point"}
}