{
  "type": "Feature",
  "properties": {
    "addr:full":"101 Riverway St Kidman Park SA 5025",
    "addr:housenumber":"101",
    "addr:postcode":"5025",
    "addr:street":"Riverway St",
    "iso:country":"AU",
    "sg:address":"101 Riverway St",
    "sg:city":"Kidman Park",
    "sg:classifiers":[
        {
            "category":"Professional",
            "subcategory":"Employment Agencies",
            "type":"Services"
        }
    ],
    "sg:phone":"+61 1800 242 453",
    "sg:postcode":"5025",
    "sg:province":"SA",
    "sg:tags":[
        "provider",
        "internet"
    ],
    "wof:name":"Two Wells Internet Service",
    "wof:placetype":"venue"
},
  "geometry": {"coordinates":[138.52716064399999,-34.9170379639],"type":"Point"}
}