{
  "type": "Feature",
  "properties": {
    "addr:full":"Suite 1/ 15 Terminus St Castle Hill NSW 2154",
    "addr:housenumber":"15",
    "addr:postcode":"2154",
    "addr:street":"Terminus St",
    "iso:country":"AU",
    "sg:address":"Suite 1/ 15 Terminus St",
    "sg:city":"Castle Hill",
    "sg:classifiers":[
        {
            "category":"Personal",
            "subcategory":"Beauty Salon",
            "type":"Services"
        }
    ],
    "sg:phone":"+61 2 9659 1766",
    "sg:postcode":"2154",
    "sg:province":"NSW",
    "sg:tags":[
        "hairdresser"
    ],
    "wof:name":"Pure Hair Pure Body",
    "wof:placetype":"venue"
},
  "geometry": {"coordinates":[151.00559997600001,-33.7326049805],"type":"Point"}
}