{
  "type": "Feature",
  "properties": {
    "iso:country":"AU",
    "sg:address":"Shop 11 Big Bear Shopping Cent 116 Military Rd",
    "sg:city":"Neutral Bay",
    "sg:classifiers":[
        {
            "category":"Food & Beverages",
            "subcategory":"Bakery",
            "type":"Retail Goods"
        }
    ],
    "sg:phone":"+61 2 9904 0544",
    "sg:postcode":"2089",
    "sg:province":"NSW",
    "sg:tags":[
        "cake",
        "shop",
        "pastry"
    ],
    "wof:name":"Michels Patisserie",
    "wof:placetype":"venue"
},
  "geometry": {"coordinates":[151.219314575,-33.830242157],"type":"Point"}
}