{
  "type": "Feature",
  "properties": {
    "addr:full":"Freedom Cntr 67 Redland Bay Rd Capalaba QLD 4157",
    "addr:housenumber":"67",
    "addr:postcode":"4157",
    "addr:street":"Redland Bay Rd",
    "iso:country":"AU",
    "sg:address":"Freedom Cntr 67 Redland Bay Rd",
    "sg:city":"Capalaba",
    "sg:classifiers":[
        {
            "category":"Shopping",
            "subcategory":"Mobile Phones",
            "type":"Retail Goods"
        }
    ],
    "sg:phone":"+61 7 3823 3666",
    "sg:postcode":"4157",
    "sg:province":"QLD",
    "sg:tags":[
        "telephone",
        "accessory"
    ],
    "wof:name":"Optus World",
    "wof:placetype":"venue"
},
  "geometry": {"coordinates":[153.20787048299999,-27.5357513428],"type":"Point"}
}