{
  "type": "Feature",
  "properties": {
    "iso:country":"AU",
    "sg:address":"2 Dewar Mews",
    "sg:city":"Clarkson",
    "sg:classifiers":[
        {
            "category":"Social Services",
            "subcategory":"Child Care",
            "type":"Services"
        }
    ],
    "sg:phone":"+61 8 9407 7606",
    "sg:postcode":"6030",
    "sg:province":"WA",
    "wof:name":"Clarkson Safe &#039;N&#039; Sound Day Care",
    "wof:placetype":"venue"
},
  "geometry": {"coordinates":[115.724281311,-31.6844844818],"type":"Point"}
}