{
  "type": "Feature",
  "properties": {
    "addr:full":"Room 4, 7th Floor, 37 Swanston St Melbourne VIC 3000",
    "addr:housenumber":"37",
    "addr:postcode":"3000",
    "addr:street":"Swanston St",
    "iso:country":"AU",
    "sg:address":"Room 4, 7th Floor, 37 Swanston St",
    "sg:city":"Melbourne",
    "sg:classifiers":[
        {
            "category":"Shopping",
            "subcategory":"Clothing, Apparel, & Fashions",
            "type":"Retail Goods"
        }
    ],
    "sg:phone":"+61 418 613 470",
    "sg:postcode":"3000",
    "sg:province":"VIC",
    "sg:tags":[
        "millinery"
    ],
    "wof:name":"Mandy Murphy Millinery",
    "wof:placetype":"venue"
},
  "geometry": {"coordinates":[144.96693420400001,-37.8166503906],"type":"Point"}
}