{
  "type": "Feature",
  "properties": {
    "addr:full":"8a Holland St St Peters NSW 2044",
    "addr:housenumber":"8a",
    "addr:postcode":"2044",
    "addr:street":"Holland St",
    "iso:country":"AU",
    "sg:address":"8a Holland St",
    "sg:city":"St Peters",
    "sg:classifiers":[
        {
            "category":"Professional",
            "subcategory":"Art Services",
            "type":"Services"
        }
    ],
    "sg:phone":"+61 2 9550 4998",
    "sg:postcode":"2044",
    "sg:province":"NSW",
    "sg:tags":[
        "picture",
        "frame",
        "framing"
    ],
    "wof:name":"McGoldrick Frames Pty Ltd",
    "wof:placetype":"venue"
},
  "geometry": {"coordinates":[151.18319700000001,-33.915257],"type":"Point"}
}