{
  "type": "Feature",
  "properties": {
    "addr:full":"14 Sheridon Crt Munster WA 6166",
    "addr:housenumber":"14",
    "addr:postcode":"6166",
    "addr:street":"Sheridon Crt",
    "iso:country":"AU",
    "sg:address":"14 Sheridon Crt",
    "sg:city":"Munster",
    "sg:classifiers":[
        {
            "category":"Building & Trades",
            "subcategory":"Construction",
            "type":"Services"
        }
    ],
    "sg:phone":"+61 419 903 273",
    "sg:postcode":"6166",
    "sg:province":"WA",
    "sg:tags":[
        "scaffolding"
    ],
    "wof:name":"Reynolds Scaffolding",
    "wof:placetype":"venue"
},
  "geometry": {"coordinates":[115.787857,-32.117332],"type":"Point"}
}