{
  "type": "Feature",
  "properties": {
    "iso:country":"AU",
    "sg:address":"3/ 1a Berryl Rd",
    "sg:city":"Narwee",
    "sg:classifiers":[
        {
            "category":"Professional",
            "subcategory":"Computer Services",
            "type":"Services"
        }
    ],
    "sg:phone":"+61 409 423 280",
    "sg:postcode":"2209",
    "sg:province":"NSW",
    "sg:tags":[
        "repairs",
        "upgrade",
        "equipment"
    ],
    "wof:name":"Bennett K",
    "wof:placetype":"venue"
},
  "geometry": {"coordinates":[151.071045,-33.94841],"type":"Point"}
}