{
  "type": "Feature",
  "properties": {
    "addr:full":"5 Caroona Rd Port Augusta SA 5700",
    "addr:housenumber":"5",
    "addr:postcode":"5700",
    "addr:street":"Caroona Rd",
    "iso:country":"AU",
    "sg:address":"5 Caroona Rd",
    "sg:city":"Port Augusta",
    "sg:classifiers":[
        {
            "category":"Social Services",
            "subcategory":"Adult Care",
            "type":"Services"
        }
    ],
    "sg:phone":"+61 8 8641 1238",
    "sg:postcode":"5700",
    "sg:province":"SA",
    "sg:tags":[
        "towing"
    ],
    "wof:name":"Forsyth Crash Repairs",
    "wof:placetype":"venue"
},
  "geometry": {"coordinates":[137.75721740700001,-32.4844512939],"type":"Point"}
}