{
  "type": "Feature",
  "properties": {
    "iso:country":"AU",
    "sg:address":"PO Box 392",
    "sg:city":"Church Point",
    "sg:classifiers":[
        {
            "category":"Professional",
            "subcategory":"Secretarial Services",
            "type":"Services"
        }
    ],
    "sg:phone":"+61 2 9999 0489",
    "sg:postcode":"2105",
    "sg:province":"NSW",
    "sg:tags":[
        "typing"
    ],
    "wof:name":"Advanced Office Services",
    "wof:placetype":"venue"
},
  "geometry": {"coordinates":[151.284454,-33.644852],"type":"Point"}
}