{
  "type": "Feature",
  "properties": {
    "addr:full":"16 Hall St Hawthorn East VIC 3123",
    "addr:housenumber":"16",
    "addr:postcode":"3123",
    "addr:street":"Hall St",
    "iso:country":"AU",
    "sg:address":"16 Hall St",
    "sg:city":"Hawthorn East",
    "sg:classifiers":[
        {
            "category":"Shopping",
            "subcategory":"Beauty & Cosmetics",
            "type":"Retail Goods"
        }
    ],
    "sg:phone":"+61 3 9822 7800",
    "sg:postcode":"3123",
    "sg:province":"VIC",
    "sg:tags":[
        "equipment",
        "salon",
        "supply"
    ],
    "wof:name":"SalonQuip",
    "wof:placetype":"venue"
},
  "geometry": {"coordinates":[145.04292297399999,-37.8443603516],"type":"Point"}
}