{
  "type": "Feature",
  "properties": {
    "addr:full":"Suite 4/Level 1/ 20 Cato St Hawthorn East VIC 3123",
    "addr:housenumber":"/ 20",
    "addr:postcode":"3123",
    "addr:street":"Cato St",
    "iso:country":"AU",
    "sg:address":"Suite 4/Level 1/ 20 Cato St",
    "sg:city":"Hawthorn East",
    "sg:classifiers":[
        {
            "category":"Sports & Exercise",
            "subcategory":"Golf",
            "type":"Entertainment"
        }
    ],
    "sg:phone":"+61 1300 752 946",
    "sg:postcode":"3123",
    "sg:province":"VIC",
    "sg:tags":[
        "club"
    ],
    "wof:name":"Golf Club Properties Ltd",
    "wof:placetype":"venue"
},
  "geometry": {"coordinates":[145.043899536,-37.8433532715],"type":"Point"}
}