{
  "type": "Feature",
  "properties": {
    "iso:country":"AU",
    "sg:address":"87 Karine St",
    "sg:city":"Swan Hill",
    "sg:classifiers":[
        {
            "category":"Retail",
            "subcategory":"Auto Repair",
            "type":"Services"
        }
    ],
    "sg:phone":"+61 3 5033 0333",
    "sg:postcode":"3585",
    "sg:province":"VIC",
    "sg:tags":[
        "repairer",
        "motor",
        "engineer"
    ],
    "wof:name":"Emmet Motors",
    "wof:placetype":"venue"
},
  "geometry": {"coordinates":[143.552292,-35.327316],"type":"Point"}
}