{
  "type": "Feature",
  "properties": {
    "addr:full":"940 Thompson Rd Cranbourne VIC 3977",
    "addr:housenumber":"940",
    "addr:postcode":"3977",
    "addr:street":"Thompson Rd",
    "iso:country":"AU",
    "sg:address":"940 Thompson Rd",
    "sg:city":"Cranbourne",
    "sg:classifiers":[
        {
            "category":"Retail",
            "subcategory":"Veterinary Services",
            "type":"Services"
        }
    ],
    "sg:phone":"+61 1300 653 277",
    "sg:postcode":"3977",
    "sg:province":"VIC",
    "sg:tags":[
        "surgeon"
    ],
    "wof:name":"Cleelands Veterinary Clinic",
    "wof:placetype":"venue"
},
  "geometry": {"coordinates":[145.191238403,-38.0715713501],"type":"Point"}
}