{
  "type": "Feature",
  "properties": {
    "addr:full":"39 Harry St Cranbourne VIC 3977",
    "addr:housenumber":"39",
    "addr:postcode":"3977",
    "addr:street":"Harry St",
    "iso:country":"AU",
    "sg:address":"39 Harry St",
    "sg:city":"Cranbourne",
    "sg:classifiers":[
        {
            "category":"Education",
            "subcategory":"Music School",
            "type":"Public Place"
        }
    ],
    "sg:phone":"+61 3 5996 3624",
    "sg:postcode":"3977",
    "sg:province":"VIC",
    "sg:tags":[
        "teacher"
    ],
    "wof:name":"Soulfinger Guitar Tuition",
    "wof:placetype":"venue"
},
  "geometry": {"coordinates":[145.27679443400001,-38.1060600281],"type":"Point"}
}