{
  "type": "Feature",
  "properties": {
    "addr:full":"2 / 24 Mason St Warragul VIC 3820",
    "addr:housenumber":"/ 24",
    "addr:postcode":"3820",
    "addr:street":"Mason St",
    "iso:country":"AU",
    "sg:address":"2 / 24 Mason St",
    "sg:city":"Warragul",
    "sg:classifiers":[
        {
            "category":"Professional",
            "subcategory":"Accounting & Tax Preparation",
            "type":"Services"
        }
    ],
    "sg:phone":"+61 3 5623 2143",
    "sg:postcode":"3820",
    "sg:province":"VIC",
    "sg:tags":[
        "consultant",
        "taxation"
    ],
    "wof:name":"Panebianco & Associates",
    "wof:placetype":"venue"
},
  "geometry": {"coordinates":[145.93403599999999,-38.161728],"type":"Point"}
}