{
  "type": "Feature",
  "properties": {
    "iso:country":"AU",
    "sg:address":"636 Wellington Rd",
    "sg:city":"Mulgrave",
    "sg:classifiers":[
        {
            "category":"Shopping",
            "subcategory":"Stationery & Office Supplies",
            "type":"Retail Goods"
        }
    ],
    "sg:phone":"+61 3 9518 5600",
    "sg:postcode":"3170",
    "sg:province":"VIC",
    "wof:name":"Boise Cascade Office Products",
    "wof:placetype":"venue"
},
  "geometry": {"coordinates":[145.18963623100001,-37.9225959778],"type":"Point"}
}