{
  "type": "Feature",
  "properties": {
    "iso:country":"AU",
    "sg:address":"Curtin University",
    "sg:city":"Bentley",
    "sg:classifiers":[
        {
            "category":"Health Services",
            "subcategory":"Optometrist",
            "type":"Services"
        }
    ],
    "sg:phone":"+61 8 9451 4130",
    "sg:postcode":"6102",
    "sg:province":"WA",
    "wof:name":"Curtin Eye Gallery",
    "wof:placetype":"venue"
},
  "geometry": {"coordinates":[115.892738342,-32.0005912781],"type":"Point"}
}