{
  "type": "Feature",
  "properties": {
    "iso:country":"AU",
    "sg:address":"533 Glenferrie Rd",
    "sg:city":"Hawthorn",
    "sg:classifiers":[
        {
            "category":"Shopping",
            "subcategory":"Clothing, Apparel, & Fashions",
            "type":"Retail Goods"
        }
    ],
    "sg:phone":"+61 3 9818 4766",
    "sg:postcode":"3122",
    "sg:province":"VIC",
    "sg:tags":[
        "lady",
        "wear"
    ],
    "wof:name":"The Little Shop On Glenferrie Hill",
    "wof:placetype":"venue"
},
  "geometry": {"coordinates":[145.03392028799999,-37.829372406],"type":"Point"}
}