{
  "type": "Feature",
  "properties": {
    "iso:country":"AU",
    "sg:address":"5/174- 180 Pacific Hwy",
    "sg:city":"North Sydney",
    "sg:classifiers":[
        {
            "category":"Professional",
            "subcategory":"Computer Services",
            "type":"Services"
        }
    ],
    "sg:phone":"+61 2 9966 1098",
    "sg:postcode":"2060",
    "sg:province":"NSW",
    "sg:tags":[
        "repairs",
        "upgrade",
        "equipment"
    ],
    "wof:name":"Computer Service Group",
    "wof:placetype":"venue"
},
  "geometry": {"coordinates":[151.204956055,-33.8348693848],"type":"Point"}
}