{
  "type": "Feature",
  "properties": {
    "addr:full":"26 Pickering St Enoggera QLD 4051",
    "addr:housenumber":"26",
    "addr:postcode":"4051",
    "addr:street":"Pickering St",
    "iso:country":"AU",
    "sg:address":"26 Pickering St",
    "sg:city":"Enoggera",
    "sg:classifiers":[
        {
            "category":"Freight",
            "type":"Transportation"
        }
    ],
    "sg:phone":"+61 7 3355 0034",
    "sg:postcode":"4051",
    "sg:province":"QLD",
    "sg:tags":[
        "light",
        "carrier"
    ],
    "wof:name":"Brisbane Bus Lines",
    "wof:placetype":"venue"
},
  "geometry": {"coordinates":[152.99757385300001,-27.4200534821],"type":"Point"}
}