{
  "type": "Feature",
  "properties": {
    "addr:full":"105 Vincent St Cessnock NSW 2325",
    "addr:housenumber":"105",
    "addr:postcode":"2325",
    "addr:street":"Vincent St",
    "iso:country":"AU",
    "sg:address":"105 Vincent St",
    "sg:city":"Cessnock",
    "sg:classifiers":[
        {
            "category":"Travel",
            "subcategory":"Travel Agent",
            "type":"Entertainment"
        }
    ],
    "sg:phone":"+61 2 4991 2779",
    "sg:postcode":"2325",
    "sg:province":"NSW",
    "sg:tags":[
        "consultant"
    ],
    "wof:name":"Travelworld",
    "wof:placetype":"venue"
},
  "geometry": {"coordinates":[151.35610961899999,-32.8351860046],"type":"Point"}
}