{
  "type": "Feature",
  "properties": {
    "addr:full":"PO Box 758 Abbeywood QLD 4613",
    "addr:postcode":"4613",
    "iso:country":"AU",
    "sg:address":"PO Box 758",
    "sg:city":"Abbeywood",
    "sg:classifiers":[
        {
            "category":"Organizations",
            "subcategory":"Professional Association",
            "type":"Services"
        }
    ],
    "sg:phone":"+61 1300 552 065",
    "sg:postcode":"4613",
    "sg:province":"QLD",
    "sg:tags":[
        "web",
        "internet"
    ],
    "wof:name":"International",
    "wof:placetype":"venue"
},
  "geometry": {"coordinates":[151.628372192,-26.1066799164],"type":"Point"}
}