{
  "type": "Feature",
  "properties": {
    "iso:country":"AU",
    "sg:address":"Unit 1/ 176 Hoare St",
    "sg:city":"Manunda",
    "sg:classifiers":[
        {
            "category":"Utilities",
            "subcategory":"Water",
            "type":"Services"
        }
    ],
    "sg:phone":"+61 7 4053 2807",
    "sg:postcode":"4870",
    "sg:province":"QLD",
    "sg:tags":[
        "equipment",
        "treatment"
    ],
    "wof:name":"Ron W Ruffley & Associates",
    "wof:placetype":"venue"
},
  "geometry": {"coordinates":[145.740325928,-16.9225845337],"type":"Point"}
}