{
  "type": "Feature",
  "properties": {
    "addr:full":"2/ 8 Virginia St Mornington VIC 3931",
    "addr:housenumber":"/ 8",
    "addr:postcode":"3931",
    "addr:street":"Virginia St",
    "iso:country":"AU",
    "sg:address":"2/ 8 Virginia St",
    "sg:city":"Mornington",
    "sg:classifiers":[
        {
            "category":"Retail",
            "subcategory":"Auto Repair",
            "type":"Services"
        }
    ],
    "sg:phone":"+61 3 5975 1866",
    "sg:postcode":"3931",
    "sg:province":"VIC",
    "sg:tags":[
        "testing",
        "inspection",
        "motor",
        "vehicle"
    ],
    "wof:name":"Spiers Automotive Repairs",
    "wof:placetype":"venue"
},
  "geometry": {"coordinates":[145.04725647000001,-38.2316360474],"type":"Point"}
}