{
  "type": "Feature",
  "properties": {
    "addr:full":"2 Colac Rd Belmont VIC 3216",
    "addr:housenumber":"2",
    "addr:postcode":"3216",
    "addr:street":"Colac Rd",
    "iso:country":"AU",
    "sg:address":"2 Colac Rd",
    "sg:city":"Belmont",
    "sg:classifiers":[
        {
            "category":"Government",
            "subcategory":"City Hall",
            "type":"Public Place"
        }
    ],
    "sg:phone":"+61 3 5227 0732",
    "sg:postcode":"3216",
    "sg:province":"VIC",
    "wof:name":"Civic Centre Belmont",
    "wof:placetype":"venue"
},
  "geometry": {"coordinates":[144.32780456500001,-38.1868019104],"type":"Point"}
}