{
  "type": "Feature",
  "properties": {
    "addr:full":"87 Fuller St Collaroy Plateau NSW 2097",
    "addr:housenumber":"87",
    "addr:postcode":"2097",
    "addr:street":"Fuller St",
    "iso:country":"AU",
    "sg:address":"87 Fuller St",
    "sg:city":"Collaroy Plateau",
    "sg:classifiers":[
        {
            "category":"Building & Trades",
            "subcategory":"Cleaning & Sanitation",
            "type":"Services"
        }
    ],
    "sg:phone":"+61 2 9982 2115",
    "sg:postcode":"2097",
    "sg:province":"NSW",
    "sg:tags":[
        "cleaner",
        "repairer",
        "roof"
    ],
    "wof:name":"Northern Beaches Metal Roofing",
    "wof:placetype":"venue"
},
  "geometry": {"coordinates":[151.288208008,-33.726108551],"type":"Point"}
}