{
  "type": "Feature",
  "properties": {
    "iso:country":"AU",
    "sg:address":"1 Caladonia St",
    "sg:city":"Paddington",
    "sg:classifiers":[
        {
            "category":"Professional",
            "subcategory":"Art Services",
            "type":"Services"
        }
    ],
    "sg:phone":"+61 2 9006 3310",
    "sg:postcode":"2021",
    "sg:province":"NSW",
    "sg:tags":[
        "interior",
        "designer"
    ],
    "wof:name":"Bee Design",
    "wof:placetype":"venue"
},
  "geometry": {"coordinates":[151.23216247600001,-33.8861999512],"type":"Point"}
}