{
  "type": "Feature",
  "properties": {
    "iso:country":"AU",
    "sg:address":"93 Gellibrand St",
    "sg:city":"Colac",
    "sg:classifiers":[
        {
            "category":"Health Services",
            "subcategory":"Dentist",
            "type":"Services"
        }
    ],
    "sg:phone":"+61 3 5231 1235",
    "sg:postcode":"3250",
    "sg:province":"VIC",
    "wof:name":"Braces &#039;N&#039; Faces Orthodontics",
    "wof:placetype":"venue"
},
  "geometry": {"coordinates":[143.586884,-38.338684],"type":"Point"}
}