{
  "type": "Feature",
  "properties": {
    "addr:full":"169 Albany Hwy Victoria Park WA 6100",
    "addr:housenumber":"169",
    "addr:postcode":"6100",
    "addr:street":"Albany Hwy Victoria",
    "iso:country":"AU",
    "sg:address":"169 Albany Hwy",
    "sg:city":"Victoria Park",
    "sg:classifiers":[
        {
            "category":"Autos & Motor Vehicles",
            "subcategory":"Automobile Sales",
            "type":"Retail Goods"
        }
    ],
    "sg:phone":"+61 8 9416 0888",
    "sg:postcode":"6100",
    "sg:province":"WA",
    "sg:tags":[
        "car",
        "new"
    ],
    "wof:name":"City Subaru",
    "wof:placetype":"venue"
},
  "geometry": {"coordinates":[115.891853333,-31.9703216553],"type":"Point"}
}