{
  "type": "Feature",
  "properties": {
    "addr:full":"Unit 10/ 136 Magower Rd Girraween NSW 2145",
    "addr:housenumber":"/ 136",
    "addr:postcode":"2145",
    "addr:street":"Magower Rd",
    "iso:country":"AU",
    "sg:address":"Unit 10/ 136 Magower Rd",
    "sg:city":"Girraween",
    "sg:classifiers":[
        {
            "category":"Shopping",
            "subcategory":"Computers & Home Electronics",
            "type":"Retail Goods"
        }
    ],
    "sg:phone":"+61 2 9831 2750",
    "sg:postcode":"2145",
    "sg:province":"NSW",
    "sg:tags":[
        "detector",
        "electronic"
    ],
    "wof:name":"On Line Pipe & Cable Locating",
    "wof:placetype":"venue"
},
  "geometry": {"coordinates":[150.941848755,-33.8007507324],"type":"Point"}
}