{
  "type": "Feature",
  "properties": {
    "addr:full":"60 Fourth Ave Maroochydore QLD 4558",
    "addr:housenumber":"60",
    "addr:postcode":"4558",
    "addr:street":"Fourth Ave",
    "iso:country":"AU",
    "sg:address":"60 Fourth Ave",
    "sg:city":"Maroochydore",
    "sg:classifiers":[
        {
            "category":"Health Services",
            "subcategory":"Dentist",
            "type":"Services"
        }
    ],
    "sg:phone":"+61 7 5443 1263",
    "sg:postcode":"4558",
    "sg:province":"QLD",
    "wof:name":"C.J. Carter Dental",
    "wof:placetype":"venue"
},
  "geometry": {"coordinates":[153.09950256400001,-26.6595726013],"type":"Point"}
}