{
  "type": "Feature",
  "properties": {
    "iso:country":"AU",
    "sg:address":"170 Sydney Rd",
    "sg:city":"Kelso",
    "sg:classifiers":[
        {
            "category":"Shopping",
            "subcategory":"Pets & Pet Supplies",
            "type":"Retail Goods"
        }
    ],
    "sg:phone":"+61 2 6332 3613",
    "sg:postcode":"2795",
    "sg:province":"NSW",
    "sg:tags":[
        "food"
    ],
    "wof:name":"Bathurst Petstop",
    "wof:placetype":"venue"
},
  "geometry": {"coordinates":[149.61177063,-33.4192085266],"type":"Point"}
}