{
  "type": "Feature",
  "properties": {
    "addr:full":"140 Port Curtis Rd Port Curtis QLD 4700",
    "addr:housenumber":"140",
    "addr:postcode":"4700",
    "addr:street":"Port Curtis Rd",
    "iso:country":"AU",
    "sg:address":"140 Port Curtis Rd",
    "sg:city":"Port Curtis",
    "sg:classifiers":[
        {
            "category":"Travel",
            "subcategory":"Hotels & Motels",
            "type":"Entertainment"
        }
    ],
    "sg:phone":"+61 7 4922 1669",
    "sg:postcode":"4700",
    "sg:province":"QLD",
    "sg:tags":[
        "pub"
    ],
    "wof:name":"Archer Hotel",
    "wof:placetype":"venue"
},
  "geometry": {"coordinates":[150.51194763199999,-23.4121761322],"type":"Point"}
}