{
  "type": "Feature",
  "properties": {
    "iso:country":"AU",
    "sg:address":"1/ 16 Rob Pl",
    "sg:city":"Vineyard",
    "sg:classifiers":[
        {
            "category":"Professional",
            "subcategory":"Detective & Security Services",
            "type":"Services"
        }
    ],
    "sg:phone":"+61 2 4587 7934",
    "sg:postcode":"2765",
    "sg:province":"NSW",
    "sg:tags":[
        "equipment",
        "window",
        "doors"
    ],
    "wof:name":"Bligh Window Fashions",
    "wof:placetype":"venue"
},
  "geometry": {"coordinates":[150.84121704099999,-33.6316642761],"type":"Point"}
}