{
  "type": "Feature",
  "properties": {
    "iso:country":"AU",
    "sg:address":"Suite 303",
    "sg:city":", Woden Cntr Woden",
    "sg:classifiers":[
        {
            "category":"Health Services",
            "subcategory":"Dentist",
            "type":"Services"
        }
    ],
    "sg:phone":"+61 2 6281 4955",
    "sg:postcode":"2606",
    "sg:province":"ACT",
    "wof:name":"Lindsay Ian",
    "wof:placetype":"venue"
},
  "geometry": {"coordinates":[149.081420898,-35.3464202881],"type":"Point"}
}