{
  "type": "Feature",
  "properties": {
    "addr:full":"46 Solandra St Wynnum West QLD 4178",
    "addr:housenumber":"46",
    "addr:postcode":"4178",
    "addr:street":"Solandra St",
    "iso:country":"AU",
    "sg:address":"46 Solandra St",
    "sg:city":"Wynnum West",
    "sg:classifiers":[
        {
            "category":"Retail",
            "subcategory":"Driving School",
            "type":"Services"
        }
    ],
    "sg:phone":"+61 7 3396 4572",
    "sg:postcode":"4178",
    "sg:province":"QLD",
    "wof:name":"Den's Driving School",
    "wof:placetype":"venue"
},
  "geometry": {"coordinates":[153.154907227,-27.4508533478],"type":"Point"}
}