{
  "type": "Feature",
  "properties": {
    "addr:full":"295 Victoria St Abbotsford VIC 3067",
    "addr:housenumber":"295",
    "addr:postcode":"3067",
    "addr:street":"Victoria St",
    "iso:country":"AU",
    "sg:address":"295 Victoria St",
    "sg:city":"Abbotsford",
    "sg:classifiers":[
        {
            "category":"Health Services",
            "subcategory":"Doctor",
            "type":"Services"
        }
    ],
    "sg:phone":"+61 3 9429 8855",
    "sg:postcode":"3067",
    "sg:province":"VIC",
    "sg:tags":[
        "medical",
        "practitioner"
    ],
    "wof:name":"Nguyen Jimmy",
    "wof:placetype":"venue"
},
  "geometry": {"coordinates":[144.994384766,-37.8097648621],"type":"Point"}
}