{
  "type": "Feature",
  "properties": {
    "iso:country":"AU",
    "sg:address":"160 Pacific Hwy",
    "sg:city":"Tuggerah",
    "sg:classifiers":[
        {
            "category":"Autos & Motor Vehicles",
            "subcategory":"Auto Supplies",
            "type":"Retail Goods"
        }
    ],
    "sg:phone":"+61 2 4353 3988",
    "sg:postcode":"2259",
    "sg:province":"NSW",
    "sg:tags":[
        "tyre"
    ],
    "wof:name":"Midcoast Auto Repairs & Tyres",
    "wof:placetype":"venue"
},
  "geometry": {"coordinates":[151.42172241200001,-33.2984848022],"type":"Point"}
}