{
  "type": "Feature",
  "properties": {
    "addr:full":"Unit 1 Princeton Court, 18 Brookfield Rd Kenmore QLD 4069",
    "addr:housenumber":"18",
    "addr:postcode":"4069",
    "addr:street":"Princeton;Brookfield Rd",
    "iso:country":"AU",
    "sg:address":"Unit 1 Princeton Court, 18 Brookfield Rd",
    "sg:city":"Kenmore",
    "sg:classifiers":[
        {
            "category":"Health Services",
            "subcategory":"Dentist",
            "type":"Services"
        }
    ],
    "sg:phone":"+61 7 3378 4243",
    "sg:postcode":"4069",
    "sg:province":"QLD",
    "wof:name":"Smith Neil F",
    "wof:placetype":"venue"
},
  "geometry": {"coordinates":[152.937957764,-27.5071163177],"type":"Point"}
}