{
  "type": "Feature",
  "properties": {
    "iso:country":"AU",
    "sg:address":"Unit 1, 28- 30 Law Crt",
    "sg:city":"Sunshine",
    "sg:classifiers":[
        {
            "category":"Professional",
            "type":"Services"
        }
    ],
    "sg:phone":"+61 3 9314 9314",
    "sg:postcode":"3020",
    "sg:province":"VIC",
    "sg:tags":[
        "shop",
        "fitting"
    ],
    "wof:name":"Action Glazing Contractors",
    "wof:placetype":"venue"
},
  "geometry": {"coordinates":[144.813751,-37.806347],"type":"Point"}
}