{
  "type": "Feature",
  "properties": {
    "iso:country":"AU",
    "sg:address":"9 Waterloo Rd",
    "sg:city":"North Ryde",
    "sg:classifiers":[
        {
            "category":"Government",
            "subcategory":"Fire Station",
            "type":"Public Place"
        }
    ],
    "sg:phone":"+61 2 9855 6677",
    "sg:postcode":"2113",
    "sg:province":"NSW",
    "sg:tags":[
        "equipment",
        "protection",
        "consultant"
    ],
    "wof:name":"Heyday Group",
    "wof:placetype":"venue"
},
  "geometry": {"coordinates":[151.13011169399999,-33.786113739],"type":"Point"}
}