{
  "type": "Feature",
  "properties": {
    "addr:full":"124 Bourbong St Bundaberg QLD 4670",
    "addr:housenumber":"124",
    "addr:postcode":"4670",
    "addr:street":"Bourbong St",
    "iso:country":"AU",
    "sg:address":"124 Bourbong St",
    "sg:city":"Bundaberg",
    "sg:classifiers":[
        {
            "category":"Banks & Credit Unions",
            "subcategory":"Bank",
            "type":"Services"
        }
    ],
    "sg:phone":"+61 7 4150 4220",
    "sg:postcode":"4670",
    "sg:province":"QLD",
    "wof:name":"Wide Bay Australia Ltd",
    "wof:placetype":"venue"
},
  "geometry": {"coordinates":[152.34947204599999,-24.8661346436],"type":"Point"}
}