{
  "type": "Feature",
  "properties": {
    "addr:full":"14 Stoddard St Port Augusta SA 5700",
    "addr:housenumber":"14",
    "addr:postcode":"5700",
    "addr:street":"Stoddard St",
    "iso:country":"AU",
    "sg:address":"14 Stoddard St",
    "sg:city":"Port Augusta",
    "sg:classifiers":[
        {
            "category":"Building & Trades",
            "subcategory":"Landscaping Services",
            "type":"Services"
        }
    ],
    "sg:phone":"+61 8 8642 4874",
    "sg:postcode":"5700",
    "sg:province":"SA",
    "sg:tags":[
        "gardener"
    ],
    "wof:name":"Augusta Mowing",
    "wof:placetype":"venue"
},
  "geometry": {"coordinates":[137.76918029800001,-32.4884643555],"type":"Point"}
}