{
  "type": "Feature",
  "properties": {
    "addr:full":"6 Empress Crt Sunshine VIC 3020",
    "addr:housenumber":"6",
    "addr:postcode":"3020",
    "addr:street":"Empress Crt",
    "iso:country":"AU",
    "sg:address":"6 Empress Crt",
    "sg:city":"Sunshine",
    "sg:classifiers":[
        {
            "category":"Home & Garden",
            "subcategory":"Building Materials",
            "type":"Retail Goods"
        }
    ],
    "sg:phone":"+61 3 9363 5334",
    "sg:postcode":"3020",
    "sg:province":"VIC",
    "sg:tags":[
        "fencing"
    ],
    "wof:name":"Southern Empress Enterprises",
    "wof:placetype":"venue"
},
  "geometry": {"coordinates":[144.79264800000001,-37.791401],"type":"Point"}
}