{
  "type": "Feature",
  "properties": {
    "addr:full":"249- 251 Esplanade Nr Henley Beach SA 5022",
    "addr:housenumber":"251",
    "addr:postcode":"5022",
    "addr:street":"Esplanade Nr",
    "iso:country":"AU",
    "sg:address":"249- 251",
    "sg:city":"Esplanade Nr Henley Beach",
    "sg:classifiers":[
        {
            "category":"Banks & Credit Unions",
            "subcategory":"Investment Brokerage",
            "type":"Services"
        }
    ],
    "sg:phone":"+61 8 8355 1101",
    "sg:postcode":"5022",
    "sg:province":"SA",
    "sg:tags":[
        "finance",
        "broker"
    ],
    "wof:name":"Accrue Finance",
    "wof:placetype":"venue"
},
  "geometry": {"coordinates":[138.495803833,-34.9272232056],"type":"Point"}
}