{
  "type": "Feature",
  "properties": {
    "iso:country":"AU",
    "sg:address":"Shed 3 87 Connaught St",
    "sg:city":"Sandgate",
    "sg:classifiers":[
        {
            "category":"Retail",
            "subcategory":"Auto Repair",
            "type":"Services"
        }
    ],
    "sg:phone":"+61 7 3869 0184",
    "sg:postcode":"4017",
    "sg:province":"QLD",
    "sg:tags":[
        "repairer",
        "motor",
        "engineer"
    ],
    "wof:name":"Northside Transmissions",
    "wof:placetype":"venue"
},
  "geometry": {"coordinates":[153.05929565400001,-27.3187065125],"type":"Point"}
}