{
  "type": "Feature",
  "properties": {
    "iso:country":"AU",
    "sg:address":"17 Behland St",
    "sg:city":"Toowoomba",
    "sg:classifiers":[
        {
            "category":"Building & Trades",
            "subcategory":"Pest Control",
            "type":"Services"
        }
    ],
    "sg:phone":"+61 7 4687 7105",
    "sg:postcode":"4350",
    "sg:province":"QLD",
    "wof:name":"Mick Moody's Pest Control",
    "wof:placetype":"venue"
},
  "geometry": {"coordinates":[151.94950900000001,-27.587475],"type":"Point"}
}