{
  "type": "Feature",
  "properties": {
    "iso:country":"AU",
    "sg:address":"Unit 19 275",
    "sg:city":"South Tce South Fremantle",
    "sg:classifiers":[
        {
            "category":"Banks & Credit Unions",
            "subcategory":"Financial Services",
            "type":"Services"
        }
    ],
    "sg:phone":"+61 8 9335 3525",
    "sg:postcode":"6162",
    "sg:province":"WA",
    "sg:tags":[
        "advisory",
        "planning",
        "retirement"
    ],
    "wof:name":"Cameron Walshe",
    "wof:placetype":"venue"
},
  "geometry": {"coordinates":[115.974152,-32.067917],"type":"Point"}
}