{
  "type": "Feature",
  "properties": {
    "addr:full":"Renshaw St Binnaway NSW 2395",
    "addr:postcode":"2395",
    "addr:street":"Renshaw St",
    "iso:country":"AU",
    "sg:address":"Renshaw St",
    "sg:city":"Binnaway",
    "sg:classifiers":[
        {
            "category":"Travel",
            "subcategory":"Hotels & Motels",
            "type":"Entertainment"
        }
    ],
    "sg:phone":"+61 2 6844 1603",
    "sg:postcode":"2395",
    "sg:province":"NSW",
    "sg:tags":[
        "accommodation"
    ],
    "wof:name":"Royal Hotel",
    "wof:placetype":"venue"
},
  "geometry": {"coordinates":[149.37916564899999,-31.5523662567],"type":"Point"}
}