{
  "type": "Feature",
  "properties": {
    "iso:country":"AU",
    "sg:address":"Lvl 20 344 Queen St",
    "sg:city":"Brisbane",
    "sg:classifiers":[
        {
            "category":"Utilities",
            "subcategory":"Natural Gas",
            "type":"Services"
        }
    ],
    "sg:phone":"+61 7 3831 8582",
    "sg:postcode":"4000",
    "sg:province":"QLD",
    "sg:tags":[
        "consultant",
        "resource"
    ],
    "wof:name":"Chenoweth Environmental Planning & Landscape Architecture",
    "wof:placetype":"venue"
},
  "geometry": {"coordinates":[153.029006958,-27.4665374756],"type":"Point"}
}