{
  "type": "Feature",
  "properties": {
    "addr:full":"Lot 56 Bridges St Gwabegar NSW 2356",
    "addr:postcode":"2356",
    "addr:street":"Bridges St",
    "iso:country":"AU",
    "sg:address":"Lot 56 Bridges St",
    "sg:city":"Gwabegar",
    "sg:classifiers":[
        {
            "category":"Commercial Area",
            "type":"Public Place"
        }
    ],
    "sg:phone":"+61 2 6843 6286",
    "sg:postcode":"2356",
    "sg:province":"NSW",
    "sg:tags":[
        "heavy",
        "carrier"
    ],
    "wof:name":"Andrews V & H D (Jack) Haulage Pty Ltd",
    "wof:placetype":"venue"
},
  "geometry": {"coordinates":[148.97114563,-30.6085186005],"type":"Point"}
}