{
  "type": "Feature",
  "properties": {
    "iso:country":"AU",
    "sg:address":"8 Baywater Drv",
    "sg:city":"Homebush Bay",
    "sg:classifiers":[
        {
            "category":"Autos & Motor Vehicles",
            "subcategory":"Automobile Sales",
            "type":"Retail Goods"
        }
    ],
    "sg:phone":"+61 2 9763 3666",
    "sg:postcode":"2127",
    "sg:province":"NSW",
    "sg:tags":[
        "car",
        "new"
    ],
    "wof:name":"Audi Australia Pty Ltd",
    "wof:placetype":"venue"
},
  "geometry": {"coordinates":[151.07591247600001,-33.8294258118],"type":"Point"}
}