{
  "type": "Feature",
  "properties": {
    "addr:full":"46 Arthur St Yeppoon QLD 4703",
    "addr:housenumber":"46",
    "addr:postcode":"4703",
    "addr:street":"Arthur St",
    "iso:country":"AU",
    "sg:address":"46 Arthur St",
    "sg:city":"Yeppoon",
    "sg:classifiers":[
        {
            "category":"Professional",
            "subcategory":"Art Services",
            "type":"Services"
        }
    ],
    "sg:phone":"+61 7 4939 1902",
    "sg:postcode":"4703",
    "sg:province":"QLD",
    "sg:tags":[
        "decorator",
        "painter"
    ],
    "wof:name":"D A & L M Tomkins",
    "wof:placetype":"venue"
},
  "geometry": {"coordinates":[150.74293518100001,-23.1273059845],"type":"Point"}
}