{
  "type": "Feature",
  "properties": {
    "addr:full":"28 - 30 Fleet St Somerton VIC 3062",
    "addr:housenumber":"30",
    "addr:postcode":"3062",
    "addr:street":"Fleet St",
    "iso:country":"AU",
    "sg:address":"28 - 30 Fleet St",
    "sg:city":"Somerton",
    "sg:classifiers":[
        {
            "category":"Home & Garden",
            "subcategory":"Building Materials",
            "type":"Retail Goods"
        }
    ],
    "sg:phone":"+61 3 9303 7791",
    "sg:postcode":"3062",
    "sg:province":"VIC",
    "sg:tags":[
        "decorative",
        "coating"
    ],
    "wof:name":"Quikcote Victoria Plaster Technologies Pty Ltd",
    "wof:placetype":"venue"
},
  "geometry": {"coordinates":[144.96061706500001,-37.6428565979],"type":"Point"}
}