{
  "type": "Feature",
  "properties": {
    "iso:country":"AU",
    "sg:address":"94 Balo St",
    "sg:city":"Moree",
    "sg:classifiers":[
        {
            "category":"Insurance",
            "subcategory":"Insurance Agent",
            "type":"Services"
        }
    ],
    "sg:phone":"+61 2 6752 3838",
    "sg:postcode":"2400",
    "sg:province":"NSW",
    "wof:name":"AMP Society",
    "wof:placetype":"venue"
},
  "geometry": {"coordinates":[149.84175109899999,-29.4648990631],"type":"Point"}
}