{
  "type": "Feature",
  "properties": {
    "iso:country":"AU",
    "sg:address":"49 Barkly St",
    "sg:city":"Mordialloc",
    "sg:classifiers":[
        {
            "category":"Building & Trades",
            "subcategory":"Construction",
            "type":"Services"
        }
    ],
    "sg:phone":"+61 418 327 036",
    "sg:postcode":"3195",
    "sg:province":"VIC",
    "sg:tags":[
        "contractor"
    ],
    "wof:name":"Milne Builders & Plumbers",
    "wof:placetype":"venue"
},
  "geometry": {"coordinates":[145.08790588400001,-38.002494812],"type":"Point"}
}