{
  "type": "Feature",
  "properties": {
    "addr:full":"82 Mona Vale Rd Mona Vale NSW 2103",
    "addr:housenumber":"82",
    "addr:postcode":"2103",
    "addr:street":"Mona Vale Rd",
    "iso:country":"AU",
    "sg:address":"82 Mona Vale Rd",
    "sg:city":"Mona Vale",
    "sg:classifiers":[
        {
            "category":"Retail",
            "subcategory":"Event Space",
            "type":"Services"
        }
    ],
    "sg:phone":"+61 2 9997 3833",
    "sg:postcode":"2103",
    "sg:province":"NSW",
    "sg:tags":[
        "function",
        "organiser"
    ],
    "wof:name":"Pittwater RSL Club",
    "wof:placetype":"venue"
},
  "geometry": {"coordinates":[151.29318237300001,-33.677318573],"type":"Point"}
}