{
  "type": "Feature",
  "properties": {
    "addr:full":"42 Canterbury Rd Heathmont VIC 3135",
    "addr:housenumber":"42",
    "addr:postcode":"3135",
    "addr:street":"Canterbury Rd",
    "iso:country":"AU",
    "sg:address":"42 Canterbury Rd",
    "sg:city":"Heathmont",
    "sg:classifiers":[
        {
            "category":"Retail",
            "subcategory":"Repair Shop",
            "type":"Services"
        }
    ],
    "sg:phone":"+61 3 9720 3619",
    "sg:postcode":"3135",
    "sg:province":"VIC",
    "sg:tags":[
        "machine",
        "repairs",
        "part",
        "dryer",
        "washing"
    ],
    "wof:name":"Eastern Homewares",
    "wof:placetype":"venue"
},
  "geometry": {"coordinates":[145.255783081,-37.8264923096],"type":"Point"}
}