{
  "type": "Feature",
  "properties": {
    "addr:full":"68 Derwent Park Rd Derwent Park TAS 7009",
    "addr:housenumber":"68",
    "addr:postcode":"7009",
    "addr:street":"Derwent Park Rd",
    "iso:country":"AU",
    "sg:address":"68 Derwent Park Rd",
    "sg:city":"Derwent Park",
    "sg:classifiers":[
        {
            "category":"Fast Food",
            "type":"Food & Drink"
        }
    ],
    "sg:phone":"+61 3 6272 6566",
    "sg:postcode":"7009",
    "sg:province":"TAS",
    "sg:tags":[
        "away",
        "take"
    ],
    "wof:name":"Cravings Takeaway",
    "wof:placetype":"venue"
},
  "geometry": {"coordinates":[147.299758911,-42.8384056091],"type":"Point"}
}