{
  "type": "Feature",
  "properties": {
    "addr:full":"123 Dawson Rd Raymond Terrace NSW 2324",
    "addr:housenumber":"123",
    "addr:postcode":"2324",
    "addr:street":"Dawson Rd",
    "iso:country":"AU",
    "sg:address":"123 Dawson Rd",
    "sg:city":"Raymond Terrace",
    "sg:classifiers":[
        {
            "category":"Home & Garden",
            "subcategory":"Carpets & Floor Coverings",
            "type":"Retail Goods"
        }
    ],
    "sg:phone":"+61 412 470 472",
    "sg:postcode":"2324",
    "sg:province":"NSW",
    "sg:tags":[
        "tile",
        "wall",
        "layer"
    ],
    "wof:name":"Alexander Bill",
    "wof:placetype":"venue"
},
  "geometry": {"coordinates":[151.76754760700001,-32.7448196411],"type":"Point"}
}