{
  "type": "Feature",
  "properties": {
    "addr:full":"25 Elizabeth St Scottsdale TAS 7260",
    "addr:housenumber":"25",
    "addr:postcode":"7260",
    "addr:street":"Elizabeth St",
    "iso:country":"AU",
    "sg:address":"25 Elizabeth St",
    "sg:city":"Scottsdale",
    "sg:classifiers":[
        {
            "category":"Utilities",
            "subcategory":"Electric",
            "type":"Services"
        }
    ],
    "sg:phone":"+61 3 6352 2027",
    "sg:postcode":"7260",
    "sg:province":"TAS",
    "sg:tags":[
        "electrical",
        "contractor"
    ],
    "wof:name":"Arch Ranson Electric",
    "wof:placetype":"venue"
},
  "geometry": {"coordinates":[147.50782799999999,-41.162594],"type":"Point"}
}