{
  "type": "Feature",
  "properties": {
    "addr:full":"21 Windsor Rd Berkeley Vale NSW 2261",
    "addr:housenumber":"21",
    "addr:postcode":"2261",
    "addr:street":"Windsor Rd",
    "iso:country":"AU",
    "sg:address":"21 Windsor Rd",
    "sg:city":"Berkeley Vale",
    "sg:classifiers":[
        {
            "category":"Building & Trades",
            "subcategory":"Construction",
            "type":"Services"
        }
    ],
    "sg:phone":"+61 417 675 318",
    "sg:postcode":"2261",
    "sg:province":"NSW",
    "sg:tags":[
        "rendering",
        "cement"
    ],
    "wof:name":"Ray Farrant Cement Rendering",
    "wof:placetype":"venue"
},
  "geometry": {"coordinates":[151.43675200000001,-33.335655],"type":"Point"}
}