{
  "type": "Feature",
  "properties": {
    "iso:country":"AU",
    "sg:address":"U7/ 11 Elizabeth St",
    "sg:city":"Campsie",
    "sg:classifiers":[
        {
            "category":"Home & Garden",
            "subcategory":"Building Materials",
            "type":"Retail Goods"
        }
    ],
    "sg:phone":"+61 2 9787 2533",
    "sg:postcode":"2194",
    "sg:province":"NSW",
    "sg:tags":[
        "ventilating",
        "equipment",
        "system"
    ],
    "wof:name":"Ace Ventilation Pty Ltd",
    "wof:placetype":"venue"
},
  "geometry": {"coordinates":[151.099365,-33.92181],"type":"Point"}
}