{
  "type": "Feature",
  "properties": {
    "addr:full":"277 Liverpool St East Sydney NSW 2010",
    "addr:housenumber":"277",
    "addr:postcode":"2010",
    "addr:street":"Liverpool St East",
    "iso:country":"AU",
    "sg:address":"277 Liverpool St",
    "sg:city":"East Sydney",
    "sg:classifiers":[
        {
            "category":"Professional",
            "subcategory":"Computer Services",
            "type":"Services"
        }
    ],
    "sg:phone":"+61 2 9380 6220",
    "sg:postcode":"2010",
    "sg:province":"NSW",
    "sg:tags":[
        "consultant",
        "system"
    ],
    "wof:name":"Exchequer Software (Australia) Pty Ltd",
    "wof:placetype":"venue"
},
  "geometry": {"coordinates":[151.216140747,-33.87758255],"type":"Point"}
}