{
  "type": "Feature",
  "properties": {
    "addr:full":"8 Sunshine St Campbellfield VIC 3061",
    "addr:housenumber":"8",
    "addr:postcode":"3061",
    "addr:street":"Sunshine St",
    "iso:country":"AU",
    "sg:address":"8 Sunshine St",
    "sg:city":"Campbellfield",
    "sg:classifiers":[
        {
            "category":"Manufacturing",
            "subcategory":"Tools & Machinery",
            "type":"Manufacturing & Wholesale Goods"
        }
    ],
    "sg:phone":"+61 3 9357 2994",
    "sg:postcode":"3061",
    "sg:province":"VIC",
    "sg:tags":[
        "wholesaler",
        "mfrs",
        "hosiery"
    ],
    "wof:name":"Rizzi Quality Socks Pty Ltd",
    "wof:placetype":"venue"
},
  "geometry": {"coordinates":[144.956954956,-37.6833953857],"type":"Point"}
}