{
  "type": "Feature",
  "properties": {
    "addr:full":"Level 1, 2- 14 Kings Cross Rd Darlinghurst NSW 2010",
    "addr:housenumber":"2 14",
    "addr:postcode":"2010",
    "addr:street":"Kings Cross Rd",
    "iso:country":"AU",
    "sg:address":"Level 1, 2- 14 Kings Cross Rd",
    "sg:city":"Darlinghurst",
    "sg:classifiers":[
        {
            "category":"Health Services",
            "subcategory":"Dentist",
            "type":"Services"
        }
    ],
    "sg:phone":"+61 2 9361 4044",
    "sg:postcode":"2010",
    "sg:province":"NSW",
    "wof:name":"Nevin Ryan Dr",
    "wof:placetype":"venue"
},
  "geometry": {"coordinates":[151.22149658199999,-33.8785705566],"type":"Point"}
}