{
  "type": "Feature",
  "properties": {
    "iso:country":"AU",
    "sg:address":"7 Dorothy St",
    "sg:city":"Burwood East",
    "sg:classifiers":[
        {
            "category":"Parking",
            "subcategory":"Lot",
            "type":"Transportation"
        }
    ],
    "sg:phone":"+61 3 9887 9214",
    "sg:postcode":"3151",
    "sg:province":"VIC",
    "sg:tags":[
        "tank",
        "calibration"
    ],
    "wof:name":"Tank Calibrators",
    "wof:placetype":"venue"
},
  "geometry": {"coordinates":[145.14375305199999,-37.8544616699],"type":"Point"}
}