{
  "type": "Feature",
  "properties": {
    "addr:full":"Cnr High & Maude Sts Shepparton VIC 3630",
    "addr:postcode":"3630",
    "iso:country":"AU",
    "sg:address":"Cnr High & Maude Sts",
    "sg:city":"Shepparton",
    "sg:classifiers":[
        {
            "category":"Shopping",
            "subcategory":"Clothing, Apparel, & Fashions",
            "type":"Retail Goods"
        }
    ],
    "sg:phone":"+61 3 5831 5266",
    "sg:postcode":"3630",
    "sg:province":"VIC",
    "sg:tags":[
        "lady",
        "wear"
    ],
    "wof:name":"Rockmans Stores Ltd",
    "wof:placetype":"venue"
},
  "geometry": {"coordinates":[145.39956665,-36.3873443604],"type":"Point"}
}