{
  "type": "Feature",
  "properties": {
    "addr:full":"330 Pacific Hwy Crows Nest NSW 2065",
    "addr:housenumber":"330",
    "addr:postcode":"2065",
    "addr:street":"Pacific Hwy",
    "iso:country":"AU",
    "sg:address":"330 Pacific Hwy",
    "sg:city":"Crows Nest",
    "sg:classifiers":[
        {
            "category":"Restaurant",
            "type":"Food & Drink"
        }
    ],
    "sg:phone":"+61 2 9438 3941",
    "sg:postcode":"2065",
    "sg:province":"NSW",
    "wof:name":"Bai Yok Thai Restaurant",
    "wof:placetype":"venue"
},
  "geometry": {"coordinates":[151.198760986,-33.8253593445],"type":"Point"}
}