{
  "type": "Feature",
  "properties": {
    "addr:full":"4 Caroline St Yeppoon QLD 4703",
    "addr:housenumber":"4",
    "addr:postcode":"4703",
    "addr:street":"Caroline St",
    "iso:country":"AU",
    "sg:address":"4 Caroline St",
    "sg:city":"Yeppoon",
    "sg:classifiers":[
        {
            "category":"Professional",
            "subcategory":"Art Services",
            "type":"Services"
        }
    ],
    "sg:phone":"+61 7 4939 3113",
    "sg:postcode":"4703",
    "sg:province":"QLD",
    "sg:tags":[
        "decorator",
        "painter"
    ],
    "wof:name":"A J & L M Warren",
    "wof:placetype":"venue"
},
  "geometry": {"coordinates":[150.734649658,-23.1212730408],"type":"Point"}
}