{
  "type": "Feature",
  "properties": {
    "iso:country":"AU",
    "sg:address":"Factory 12, 27- 29 Aster Ave",
    "sg:city":"Carrum Downs",
    "sg:classifiers":[
        {
            "category":"Retail",
            "subcategory":"Auto Repair",
            "type":"Services"
        }
    ],
    "sg:phone":"+61 3 9775 1331",
    "sg:postcode":"3201",
    "sg:province":"VIC",
    "sg:tags":[
        "repairer",
        "motor",
        "engineer"
    ],
    "wof:name":"Auto Gas Connection",
    "wof:placetype":"venue"
},
  "geometry": {"coordinates":[145.165466,-38.102173],"type":"Point"}
}