{
  "type": "Feature",
  "properties": {
    "addr:full":"69- 73 Erskineville Rd Erskineville NSW 2043",
    "addr:housenumber":"73",
    "addr:postcode":"2043",
    "addr:street":"Erskineville Rd",
    "iso:country":"AU",
    "sg:address":"69- 73 Erskineville Rd",
    "sg:city":"Erskineville",
    "sg:classifiers":[
        {
            "category":"Retail",
            "subcategory":"Veterinary Services",
            "type":"Services"
        }
    ],
    "sg:phone":"+61 2 9519 4111",
    "sg:postcode":"2043",
    "sg:province":"NSW",
    "sg:tags":[
        "surgeon"
    ],
    "wof:name":"Erskineville Veterinary Hospital",
    "wof:placetype":"venue"
},
  "geometry": {"coordinates":[151.18421900000001,-33.899826],"type":"Point"}
}