{
  "type": "Feature",
  "properties": {
    "addr:full":"61- 63 Railway Pde Marrickville NSW 2204",
    "addr:housenumber":"63",
    "addr:postcode":"2204",
    "addr:street":"Railway Pde",
    "iso:country":"AU",
    "sg:address":"61- 63 Railway Pde",
    "sg:city":"Marrickville",
    "sg:classifiers":[
        {
            "category":"Home & Garden",
            "subcategory":"Building Materials",
            "type":"Retail Goods"
        }
    ],
    "sg:phone":"+61 2 8795 0030",
    "sg:postcode":"2204",
    "sg:province":"NSW",
    "sg:tags":[
        "fitting",
        "door"
    ],
    "wof:name":"Crown Doors International",
    "wof:placetype":"venue"
},
  "geometry": {"coordinates":[151.16625999999999,-33.913692],"type":"Point"}
}