{
  "type": "Feature",
  "properties": {
    "iso:country":"AU",
    "sg:address":"91 Main St",
    "sg:city":"Thomastown",
    "sg:classifiers":[
        {
            "category":"Banks & Credit Unions",
            "subcategory":"Bureau De Change",
            "type":"Services"
        }
    ],
    "sg:phone":"+61 400 122 641",
    "sg:postcode":"3074",
    "sg:province":"VIC",
    "sg:tags":[
        "escort",
        "transport",
        "pilot"
    ],
    "wof:name":"Pilot Sam",
    "wof:placetype":"venue"
},
  "geometry": {"coordinates":[145.002197266,-37.679069519],"type":"Point"}
}