{
  "type": "Feature",
  "properties": {
    "addr:full":"Southside Psychology Centre 163 Boundary St South Townsville QLD 4810",
    "addr:housenumber":"163",
    "addr:postcode":"4810",
    "addr:street":"Boundary St",
    "iso:country":"AU",
    "sg:address":"Southside Psychology Centre 163 Boundary St",
    "sg:city":"South Townsville",
    "sg:classifiers":[
        {
            "category":"Health Services",
            "subcategory":"Health Practitioner",
            "type":"Services"
        }
    ],
    "sg:phone":"+61 7 4721 1763",
    "sg:postcode":"4810",
    "sg:province":"QLD",
    "sg:tags":[
        "psychologist"
    ],
    "wof:name":"Zemaitis, R J",
    "wof:placetype":"venue"
},
  "geometry": {"coordinates":[146.823486,-19.269747],"type":"Point"}
}