{
  "type": "Feature",
  "properties": {
    "iso:country":"AU",
    "sg:address":"Marine Pde",
    "sg:city":"Newell",
    "sg:classifiers":[
        {
            "category":"Food & Beverages",
            "subcategory":"Groceries & Convenience Stores",
            "type":"Retail Goods"
        }
    ],
    "sg:phone":"+61 7 4098 1812",
    "sg:postcode":"4873",
    "sg:province":"QLD",
    "wof:name":"Newell Beach Store & Takeaway",
    "wof:placetype":"venue"
},
  "geometry": {"coordinates":[145.40594482399999,-16.4271278381],"type":"Point"}
}