{
  "type": "Feature",
  "properties": {
    "addr:full":"807/ 20 Rakaia Way Docklands VIC 3008",
    "addr:housenumber":"807 / 20",
    "addr:postcode":"3008",
    "addr:street":"Rakaia Way",
    "iso:country":"AU",
    "sg:address":"807/ 20",
    "sg:city":"Rakaia Way Docklands",
    "sg:classifiers":[
        {
            "category":"Education",
            "subcategory":"Special Training",
            "type":"Public Place"
        }
    ],
    "sg:phone":"+61 3 8685 8157",
    "sg:postcode":"3008",
    "sg:province":"VIC",
    "sg:tags":[
        "development"
    ],
    "wof:name":"Diamondlife Learning Pty Ltd",
    "wof:placetype":"venue"
},
  "geometry": {"coordinates":[144.940948486,-37.8146934509],"type":"Point"}
}