{
  "type": "Feature",
  "properties": {
    "addr:full":"546 Middle Rd Greenbank QLD 4124",
    "addr:housenumber":"546",
    "addr:postcode":"4124",
    "addr:street":"Middle Rd",
    "iso:country":"AU",
    "sg:address":"546 Middle Rd",
    "sg:city":"Greenbank",
    "sg:classifiers":[
        {
            "category":"Retail",
            "subcategory":"Auto Repair",
            "type":"Services"
        }
    ],
    "sg:phone":"+61 7 3200 0792",
    "sg:postcode":"4124",
    "sg:province":"QLD",
    "sg:tags":[
        "electrical"
    ],
    "wof:name":"A Allcars Auto Electrical",
    "wof:placetype":"venue"
},
  "geometry": {"coordinates":[152.999343872,-27.7092628479],"type":"Point"}
}