{
  "type": "Feature",
  "properties": {
    "addr:full":"25 Stephen Rd Dandenong South VIC 3175",
    "addr:housenumber":"25",
    "addr:postcode":"3175",
    "addr:street":"Stephen Rd",
    "iso:country":"AU",
    "sg:address":"25 Stephen Rd",
    "sg:city":"Dandenong South",
    "sg:classifiers":[
        {
            "category":"Shopping",
            "subcategory":"Stationery & Office Supplies",
            "type":"Retail Goods"
        }
    ],
    "sg:phone":"+61 3 9794 0122",
    "sg:postcode":"3175",
    "sg:province":"VIC",
    "sg:tags":[
        "packaging",
        "material"
    ],
    "wof:name":"Sealapak",
    "wof:placetype":"venue"
},
  "geometry": {"coordinates":[145.212966919,-38.0089759827],"type":"Point"}
}