{
  "type": "Feature",
  "properties": {
    "addr:full":"304 Drummond St Carlton VIC 3053",
    "addr:housenumber":"304",
    "addr:postcode":"3053",
    "addr:street":"Drummond St",
    "iso:country":"AU",
    "sg:address":"304 Drummond St",
    "sg:city":"Carlton",
    "sg:classifiers":[
        {
            "category":"Professional",
            "subcategory":"Computer Services",
            "type":"Services"
        }
    ],
    "sg:phone":"+61 3 9347 7822",
    "sg:postcode":"3053",
    "sg:province":"VIC",
    "sg:tags":[
        "consultant",
        "system"
    ],
    "wof:name":"Accounting Systems Assist",
    "wof:placetype":"venue"
},
  "geometry": {"coordinates":[144.96896362300001,-37.7986068726],"type":"Point"}
}