{
  "type": "Feature",
  "properties": {
    "iso:country":"AU",
    "sg:address":"280 Conadilly St",
    "sg:city":"Gunnedah",
    "sg:classifiers":[
        {
            "category":"Personal",
            "subcategory":"Beauty Salon",
            "type":"Services"
        }
    ],
    "sg:phone":"+61 2 6742 1003",
    "sg:postcode":"2380",
    "sg:province":"NSW",
    "sg:tags":[
        "hairdresser"
    ],
    "wof:name":"Lynelle Hairdressing Salon",
    "wof:placetype":"venue"
},
  "geometry": {"coordinates":[150.25454711899999,-30.9779605865],"type":"Point"}
}