{
  "type": "Feature",
  "properties": {
    "iso:country":"AU",
    "sg:address":"9 Blackbutts Rd",
    "sg:city":"Frenchs Forest",
    "sg:classifiers":[
        {
            "category":"Health Services",
            "subcategory":"Doctor",
            "type":"Services"
        }
    ],
    "sg:phone":"+61 2 9451 9432",
    "sg:postcode":"2086",
    "sg:province":"NSW",
    "sg:tags":[
        "podiatrist"
    ],
    "wof:name":"Belrose-Frenchs Forest Podiatry",
    "wof:placetype":"venue"
},
  "geometry": {"coordinates":[151.218948364,-33.7437286377],"type":"Point"}
}