{
  "type": "Feature",
  "properties": {
    "addr:full":"11 Huntley Rd Orange NSW 2800",
    "addr:housenumber":"11",
    "addr:postcode":"2800",
    "addr:street":"Huntley Rd",
    "iso:country":"AU",
    "sg:address":"11 Huntley Rd",
    "sg:city":"Orange",
    "sg:classifiers":[
        {
            "category":"Retail",
            "subcategory":"Car Wash",
            "type":"Services"
        }
    ],
    "sg:phone":"+61 2 6361 0700",
    "sg:postcode":"2800",
    "sg:province":"NSW",
    "sg:tags":[
        "bitumen",
        "spraying"
    ],
    "wof:name":"Patches Asphalt",
    "wof:placetype":"venue"
},
  "geometry": {"coordinates":[149.100463867,-33.3064880371],"type":"Point"}
}