{
  "type": "Feature",
  "properties": {
    "addr:full":"1060 Rochdale Rd Springwood QLD 4127",
    "addr:housenumber":"1060",
    "addr:postcode":"4127",
    "addr:street":"Rochdale Rd",
    "iso:country":"AU",
    "sg:address":"1060 Rochdale Rd",
    "sg:city":"Springwood",
    "sg:classifiers":[
        {
            "category":"Real Estate",
            "subcategory":"Real Estate Agent",
            "type":"Services"
        }
    ],
    "sg:phone":"+61 7 3208 4011",
    "sg:postcode":"4127",
    "sg:province":"QLD",
    "wof:name":"Cavalier Realty Southside",
    "wof:placetype":"venue"
},
  "geometry": {"coordinates":[153.12530517600001,-27.6165885925],"type":"Point"}
}