{
  "type": "Feature",
  "properties": {
    "iso:country":"AU",
    "sg:address":"Mt Baimbridge Rd",
    "sg:city":"Hamilton",
    "sg:classifiers":[
        {
            "category":"Professional",
            "subcategory":"Management & Consulting",
            "type":"Services"
        }
    ],
    "sg:phone":"+61 3 5571 2940",
    "sg:postcode":"3300",
    "sg:province":"VIC",
    "sg:tags":[
        "consultant",
        "educational"
    ],
    "wof:name":"District Education Consultants",
    "wof:placetype":"venue"
},
  "geometry": {"coordinates":[142.01441955600001,-37.7442817688],"type":"Point"}
}