{
  "type": "Feature",
  "properties": {
    "addr:full":"39 Aumuller St Portsmith QLD 4870",
    "addr:housenumber":"39",
    "addr:postcode":"4870",
    "addr:street":"Aumuller St Portsmith",
    "iso:country":"AU",
    "sg:address":"39 Aumuller St",
    "sg:city":"Portsmith",
    "sg:classifiers":[
        {
            "category":"Food & Beverages",
            "subcategory":"Meat & Fish",
            "type":"Retail Goods"
        }
    ],
    "sg:phone":"+61 7 4035 2633",
    "sg:postcode":"4870",
    "sg:province":"QLD",
    "sg:tags":[
        "seafood"
    ],
    "wof:name":"Great Barrier Reef Tuna",
    "wof:placetype":"venue"
},
  "geometry": {"coordinates":[145.769134522,-16.9426651001],"type":"Point"}
}