{
  "type": "Feature",
  "properties": {
    "addr:full":"4/ 140 Russell St Toowoomba QLD 4350",
    "addr:housenumber":"/ 140",
    "addr:postcode":"4350",
    "addr:street":"Russell St",
    "iso:country":"AU",
    "sg:address":"4/ 140 Russell St",
    "sg:city":"Toowoomba",
    "sg:classifiers":[
        {
            "category":"Government",
            "subcategory":"Court House",
            "type":"Public Place"
        }
    ],
    "sg:phone":"+61 428 220 148",
    "sg:postcode":"4350",
    "sg:province":"QLD",
    "sg:tags":[
        "personal",
        "marriage",
        "family",
        "counselling"
    ],
    "wof:name":"Addie Elizabeth",
    "wof:placetype":"venue"
},
  "geometry": {"coordinates":[151.948273,-27.5592],"type":"Point"}
}