{
  "type": "Feature",
  "properties": {
    "iso:country":"AU",
    "sg:address":"21 Wongala Crescent",
    "sg:city":"Beecroft",
    "sg:classifiers":[
        {
            "category":"Health Services",
            "subcategory":"Doctor",
            "type":"Services"
        }
    ],
    "sg:phone":"+61 2 9875 3200",
    "sg:postcode":"2119",
    "sg:province":"NSW",
    "sg:tags":[
        "podiatrist"
    ],
    "wof:name":"Beecroft Podiatry Clinic",
    "wof:placetype":"venue"
},
  "geometry": {"coordinates":[151.06576538100001,-33.7496376038],"type":"Point"}
}