{
  "type": "Feature",
  "properties": {
    "iso:country":"AU",
    "sg:address":"135- 149 Kings Way",
    "sg:city":"South Melbourne",
    "sg:classifiers":[
        {
            "category":"Banks & Credit Unions",
            "subcategory":"Investment Brokerage",
            "type":"Services"
        }
    ],
    "sg:phone":"+61 3 9690 8833",
    "sg:postcode":"3205",
    "sg:province":"VIC",
    "sg:tags":[
        "finance",
        "broker"
    ],
    "wof:name":"Mercedes-Benz Of Melbourne",
    "wof:placetype":"venue"
},
  "geometry": {"coordinates":[144.94622799999999,-37.828388],"type":"Point"}
}