{
  "type": "Feature",
  "properties": {
    "addr:full":"136 Glad Gunson Drv Eleebana NSW 2282",
    "addr:housenumber":"136",
    "addr:postcode":"2282",
    "addr:street":"Glad Gunson Drv",
    "iso:country":"AU",
    "sg:address":"136 Glad Gunson Drv",
    "sg:city":"Eleebana",
    "sg:classifiers":[
        {
            "category":"Professional",
            "subcategory":"Art Services",
            "type":"Services"
        }
    ],
    "sg:phone":"+61 2 4942 7350",
    "sg:postcode":"2282",
    "sg:province":"NSW",
    "sg:tags":[
        "decorator",
        "painter"
    ],
    "wof:name":"Brufhstrokas Pty Ltd",
    "wof:placetype":"venue"
},
  "geometry": {"coordinates":[151.64793395999999,-32.9906005859],"type":"Point"}
}