{
  "type": "Feature",
  "properties": {
    "addr:full":"Heidke Rd (off Topaz Rd) Malanda QLD 4885",
    "addr:postcode":"4885",
    "addr:street":"Heidke Rd Off Topaz Rd",
    "iso:country":"AU",
    "sg:address":"Heidke Rd",
    "sg:city":"(off Topaz Rd) Malanda",
    "sg:classifiers":[
        {
            "category":"Travel",
            "subcategory":"Hotels & Motels",
            "type":"Entertainment"
        }
    ],
    "sg:phone":"+61 7 4096 8173",
    "sg:postcode":"4885",
    "sg:province":"QLD",
    "wof:name":"Honeyflow Homestead",
    "wof:placetype":"venue"
},
  "geometry": {"coordinates":[145.658569336,-17.3324985504],"type":"Point"}
}