{
  "type": "Feature",
  "properties": {
    "iso:country":"AU",
    "sg:address":"32 Victory Rd",
    "sg:city":"Airport West",
    "sg:classifiers":[
        {
            "category":"Professional",
            "subcategory":"Detective & Security Services",
            "type":"Services"
        }
    ],
    "sg:phone":"+61 3 9334 5060",
    "sg:postcode":"3042",
    "sg:province":"VIC",
    "sg:tags":[
        "consultant",
        "system"
    ],
    "wof:name":"Paradyne Corporation Pty Ltd",
    "wof:placetype":"venue"
},
  "geometry": {"coordinates":[144.889129639,-37.7183189392],"type":"Point"}
}