{
  "type": "Feature",
  "properties": {
    "addr:full":"188 Barry Pde Fortitude Valley QLD 4006",
    "addr:housenumber":"188",
    "addr:postcode":"4006",
    "addr:street":"Barry Pde",
    "iso:country":"AU",
    "sg:address":"188 Barry Pde",
    "sg:city":"Fortitude Valley",
    "sg:classifiers":[
        {
            "category":"Shopping",
            "subcategory":"Music",
            "type":"Retail Goods"
        }
    ],
    "sg:phone":"+61 7 3252 4299",
    "sg:postcode":"4006",
    "sg:province":"QLD",
    "sg:tags":[
        "instrument",
        "musical"
    ],
    "wof:name":"Guitar Garage The",
    "wof:placetype":"venue"
},
  "geometry": {"coordinates":[153.030883789,-27.458650589],"type":"Point"}
}