{
  "type": "Feature",
  "properties": {
    "addr:full":"29 Lampton Ave Derwent Park TAS 7009",
    "addr:housenumber":"29",
    "addr:postcode":"7009",
    "addr:street":"Lampton Ave",
    "iso:country":"AU",
    "sg:address":"29 Lampton Ave",
    "sg:city":"Derwent Park",
    "sg:classifiers":[
        {
            "category":"Juice Bar",
            "subcategory":"None",
            "type":"Food & Drink"
        }
    ],
    "sg:phone":"+61 3 6248 5955",
    "sg:postcode":"7009",
    "sg:province":"TAS",
    "sg:tags":[
        "merchant",
        "fruit",
        "processor"
    ],
    "wof:name":"Juicy Isle Fruit Juices Pty Ltd",
    "wof:placetype":"venue"
},
  "geometry": {"coordinates":[147.29151916500001,-42.8352813721],"type":"Point"}
}