{
  "type": "Feature",
  "properties": {
    "iso:country":"AU",
    "sg:address":"U2/ 231 Barrington St",
    "sg:city":"Bibra Lake",
    "sg:classifiers":[
        {
            "category":"Retail",
            "subcategory":"Auto Repair",
            "type":"Services"
        }
    ],
    "sg:phone":"+61 8 9434 9310",
    "sg:postcode":"6163",
    "sg:province":"WA",
    "sg:tags":[
        "repairer",
        "motor",
        "engineer"
    ],
    "wof:name":"Global Automatics",
    "wof:placetype":"venue"
},
  "geometry": {"coordinates":[115.811119,-32.116741],"type":"Point"}
}