{
  "type": "Feature",
  "properties": {
    "addr:full":"15 Plumer Rd Rose Bay NSW 2029",
    "addr:housenumber":"15",
    "addr:postcode":"2029",
    "addr:street":"Plumer Rd",
    "iso:country":"AU",
    "sg:address":"15 Plumer Rd",
    "sg:city":"Rose Bay",
    "sg:classifiers":[
        {
            "category":"Food & Beverages",
            "subcategory":"Bakery",
            "type":"Retail Goods"
        }
    ],
    "sg:phone":"+61 2 9327 3646",
    "sg:postcode":"2029",
    "sg:province":"NSW",
    "sg:tags":[
        "cake",
        "shop",
        "pastry"
    ],
    "wof:name":"La Bretagne Patisserie",
    "wof:placetype":"venue"
},
  "geometry": {"coordinates":[151.259307861,-33.8754005432],"type":"Point"}
}