{
  "type": "Feature",
  "properties": {
    "addr:full":"PO Box 561 Inglewood WA 6052",
    "addr:postcode":"6052",
    "iso:country":"AU",
    "sg:address":"PO Box 561",
    "sg:city":"Inglewood",
    "sg:classifiers":[
        {
            "category":"Building & Trades",
            "subcategory":"Cleaning & Sanitation",
            "type":"Services"
        }
    ],
    "sg:phone":"+61 8 9370 3909",
    "sg:postcode":"6052",
    "sg:province":"WA",
    "sg:tags":[
        "industrial",
        "commercial",
        "contractor"
    ],
    "wof:name":"Kleenduct Australia Pty Ltd",
    "wof:placetype":"venue"
},
  "geometry": {"coordinates":[115.886817932,-31.9206104279],"type":"Point"}
}