{
  "type": "Feature",
  "properties": {
    "addr:full":"Gnd Flr 229 Hoddle St Collingwood VIC 3066",
    "addr:housenumber":"229",
    "addr:postcode":"3066",
    "addr:street":"Hoddle St",
    "iso:country":"AU",
    "sg:address":"Gnd Flr 229 Hoddle St",
    "sg:city":"Collingwood",
    "sg:classifiers":[
        {
            "category":"Education",
            "subcategory":"Dance Studio",
            "type":"Public Place"
        }
    ],
    "sg:phone":"+61 3 9419 1674",
    "sg:postcode":"3066",
    "sg:province":"VIC",
    "sg:tags":[
        "instruction",
        "language"
    ],
    "wof:name":"Collingwood Turkish Welfare Association",
    "wof:placetype":"venue"
},
  "geometry": {"coordinates":[144.992111206,-37.8022766113],"type":"Point"}
}