{
  "type": "Feature",
  "properties": {
    "addr:full":"5 John St Bayswater WA 6053",
    "addr:housenumber":"5",
    "addr:postcode":"6053",
    "addr:street":"John St",
    "iso:country":"AU",
    "sg:address":"5 John St",
    "sg:city":"Bayswater",
    "sg:classifiers":[
        {
            "category":"Manufacturing",
            "subcategory":"Metals",
            "type":"Manufacturing & Wholesale Goods"
        }
    ],
    "sg:phone":"+61 8 9272 5695",
    "sg:postcode":"6053",
    "sg:province":"WA",
    "sg:tags":[
        "steel",
        "fabricator",
        "mfrs"
    ],
    "wof:name":"Atkinson Steel Products",
    "wof:placetype":"venue"
},
  "geometry": {"coordinates":[115.91784668,-31.9105148315],"type":"Point"}
}