{
  "type": "Feature",
  "properties": {
    "iso:country":"AU",
    "sg:address":"119 Hampton St",
    "sg:city":"Bridgetown",
    "sg:classifiers":[
        {
            "category":"Shopping",
            "subcategory":"Baby Store",
            "type":"Retail Goods"
        }
    ],
    "sg:phone":"+61 8 9761 1811",
    "sg:postcode":"6255",
    "sg:province":"WA",
    "sg:tags":[
        "children's",
        "wear"
    ],
    "wof:name":"Puddletown Toyshop",
    "wof:placetype":"venue"
},
  "geometry": {"coordinates":[116.137046814,-33.9577178955],"type":"Point"}
}