{
  "type": "Feature",
  "properties": {
    "addr:full":"PO Box 357 Chester Hill NSW 2162",
    "addr:postcode":"2162",
    "iso:country":"AU",
    "sg:address":"PO Box 357",
    "sg:city":"Chester Hill",
    "sg:classifiers":[
        {
            "category":"Banks & Credit Unions",
            "subcategory":"Financial Services",
            "type":"Services"
        }
    ],
    "sg:phone":"+61 2 9738 0207",
    "sg:postcode":"2162",
    "sg:province":"NSW",
    "sg:tags":[
        "loan",
        "finance",
        "mortgage"
    ],
    "wof:name":"Connect Home Loans",
    "wof:placetype":"venue"
},
  "geometry": {"coordinates":[151.00013732900001,-33.8829994202],"type":"Point"}
}