{
  "type": "Feature",
  "properties": {
    "addr:full":"Ste 2/ 109 Maroondah Hwy Chirnside Park VIC 3116",
    "addr:housenumber":"/ 109",
    "addr:postcode":"3116",
    "addr:street":"Maroondah Hwy",
    "iso:country":"AU",
    "sg:address":"Ste 2/ 109 Maroondah Hwy",
    "sg:city":"Chirnside Park",
    "sg:classifiers":[
        {
            "category":"Professional",
            "subcategory":"Accounting & Tax Preparation",
            "type":"Services"
        }
    ],
    "sg:phone":"+61 3 9735 2711",
    "sg:postcode":"3116",
    "sg:province":"VIC",
    "sg:tags":[
        "accountant",
        "auditor"
    ],
    "wof:name":"Grills Kerry & Associates",
    "wof:placetype":"venue"
},
  "geometry": {"coordinates":[145.355072022,-37.7574462891],"type":"Point"}
}