{
  "type": "Feature",
  "properties": {
    "addr:full":"PO Box 217 Thornleigh NSW 2120",
    "addr:postcode":"2120",
    "iso:country":"AU",
    "sg:address":"PO Box 217",
    "sg:city":"Thornleigh",
    "sg:classifiers":[
        {
            "category":"Real Estate",
            "subcategory":"Developer",
            "type":"Services"
        }
    ],
    "sg:phone":"+61 2 9484 4764",
    "sg:postcode":"2120",
    "sg:province":"NSW",
    "sg:tags":[
        "development"
    ],
    "wof:name":"Loukari Corporation Pty Ltd",
    "wof:placetype":"venue"
},
  "geometry": {"coordinates":[151.08340454099999,-33.7282104492],"type":"Point"}
}