{
  "type": "Feature",
  "properties": {
    "iso:country":"AU",
    "sg:address":"21 Jason Pl",
    "sg:city":"North Rocks",
    "sg:classifiers":[
        {
            "category":"Education",
            "subcategory":"Special Training",
            "type":"Public Place"
        }
    ],
    "sg:phone":"+61 2 9871 1847",
    "sg:postcode":"2151",
    "sg:province":"NSW",
    "sg:tags":[
        "drama",
        "speech",
        "speaking",
        "tuition"
    ],
    "wof:name":"ASCA Australian Speech Communication Asscn",
    "wof:placetype":"venue"
},
  "geometry": {"coordinates":[151.02204895,-33.7728767395],"type":"Point"}
}