{
  "type": "Feature",
  "properties": {
    "iso:country":"AU",
    "sg:address":"Robin St",
    "sg:city":"Robinvale",
    "sg:classifiers":[
        {
            "category":"Organizations",
            "subcategory":"Community Association",
            "type":"Services"
        }
    ],
    "sg:phone":"+61 3 5026 3521",
    "sg:postcode":"3549",
    "sg:province":"VIC",
    "sg:tags":[
        "club",
        "senior",
        "citizen"
    ],
    "wof:name":"Robinvale Senior Citizens",
    "wof:placetype":"venue"
},
  "geometry": {"coordinates":[142.77301025400001,-34.5821685791],"type":"Point"}
}