{
  "type": "Feature",
  "properties": {
    "iso:country":"AU",
    "sg:address":"49-51 Colvin St",
    "sg:city":"Toowoomba",
    "sg:classifiers":[
        {
            "category":"Retail",
            "subcategory":"Auto Repair",
            "type":"Services"
        }
    ],
    "sg:phone":"+61 7 4630 1600",
    "sg:postcode":"4350",
    "sg:province":"QLD",
    "sg:tags":[
        "sport",
        "motor"
    ],
    "wof:name":"Profab Custom Engineering",
    "wof:placetype":"venue"
},
  "geometry": {"coordinates":[151.911591,-27.59432],"type":"Point"}
}