{
  "type": "Feature",
  "properties": {
    "addr:full":"PO Box 301 Montrose VIC 3765",
    "addr:postcode":"3765",
    "iso:country":"AU",
    "sg:address":"PO Box 301",
    "sg:city":"Montrose",
    "sg:classifiers":[
        {
            "category":"Health Services",
            "subcategory":"Doctor",
            "type":"Services"
        }
    ],
    "sg:phone":"+61 3 9728 6869",
    "sg:postcode":"3765",
    "sg:province":"VIC",
    "sg:tags":[
        "medical",
        "practitioner"
    ],
    "wof:name":"Swansea Rd Clinic",
    "wof:placetype":"venue"
},
  "geometry": {"coordinates":[145.34880065900001,-37.8171806335],"type":"Point"}
}