{
  "type": "Feature",
  "properties": {
    "addr:full":"Lot 9 Adair St Oakey QLD 4401",
    "addr:postcode":"4401",
    "addr:street":"Adair St",
    "iso:country":"AU",
    "sg:address":"Lot 9 Adair St",
    "sg:city":"Oakey",
    "sg:classifiers":[
        {
            "category":"Farming",
            "subcategory":"Farm",
            "type":"Manufacturing & Wholesale Goods"
        }
    ],
    "sg:phone":"+61 7 4691 1253",
    "sg:postcode":"4401",
    "sg:province":"QLD",
    "sg:tags":[
        "farmer"
    ],
    "wof:name":"Brennan J D",
    "wof:placetype":"venue"
},
  "geometry": {"coordinates":[151.731689453,-27.4558181763],"type":"Point"}
}