{
  "type": "Feature",
  "properties": {
    "addr:full":"87/ 248 Miller St North Sydney NSW 2060",
    "addr:housenumber":"87 / 248",
    "addr:postcode":"2060",
    "addr:street":"Miller St",
    "iso:country":"AU",
    "sg:address":"87/ 248 Miller St",
    "sg:city":"North Sydney",
    "sg:classifiers":[
        {
            "category":"Building & Trades",
            "subcategory":"Plumbing",
            "type":"Services"
        }
    ],
    "sg:phone":"+61 2 9922 5360",
    "sg:postcode":"2060",
    "sg:province":"NSW",
    "sg:tags":[
        "plumber",
        "gasfitters"
    ],
    "wof:name":"The Plumbing Professionals",
    "wof:placetype":"venue"
},
  "geometry": {"coordinates":[151.20794677699999,-33.8327102661],"type":"Point"}
}