{
  "type": "Feature",
  "properties": {
    "addr:full":"125-127 Graham St Wonthaggi VIC 3995",
    "addr:housenumber":"125-127",
    "addr:postcode":"3995",
    "addr:street":"Graham St",
    "iso:country":"AU",
    "sg:address":"125-127 Graham St",
    "sg:city":"Wonthaggi",
    "sg:classifiers":[
        {
            "category":"Shopping",
            "subcategory":"Clothing, Apparel, & Fashions",
            "type":"Retail Goods"
        }
    ],
    "sg:phone":"+61 3 5672 5252",
    "sg:postcode":"3995",
    "sg:province":"VIC",
    "sg:tags":[
        "hire",
        "men's",
        "wear",
        "formal"
    ],
    "wof:name":"Scotts",
    "wof:placetype":"venue"
},
  "geometry": {"coordinates":[145.590103,-38.606285],"type":"Point"}
}