{
  "type": "Feature",
  "properties": {
    "addr:full":"Suite 2/ 6 Beverley Ave Warilla NSW 2528",
    "addr:housenumber":"6",
    "addr:postcode":"2528",
    "addr:street":"Beverley Ave",
    "iso:country":"AU",
    "sg:address":"Suite 2/ 6 Beverley Ave",
    "sg:city":"Warilla",
    "sg:classifiers":[
        {
            "category":"Professional",
            "subcategory":"Accounting & Tax Preparation",
            "type":"Services"
        }
    ],
    "sg:phone":"+61 2 4297 3700",
    "sg:postcode":"2528",
    "sg:province":"NSW",
    "sg:tags":[
        "consultant",
        "taxation"
    ],
    "wof:name":"James Denis",
    "wof:placetype":"venue"
},
  "geometry": {"coordinates":[150.861419678,-34.5517425537],"type":"Point"}
}