{
  "type": "Feature",
  "properties": {
    "iso:country":"AU",
    "sg:address":"405 Colwyn Rd",
    "sg:city":"Mt Helena",
    "sg:classifiers":[
        {
            "category":"Retail",
            "subcategory":"Repair Shop",
            "type":"Services"
        }
    ],
    "sg:phone":"+61 8 9572 1090",
    "sg:postcode":"6082",
    "sg:province":"WA",
    "sg:tags":[
        "repairing",
        "piano",
        "tuning"
    ],
    "wof:name":"Haass Walter",
    "wof:placetype":"venue"
},
  "geometry": {"coordinates":[116.197486877,-31.8688716888],"type":"Point"}
}