{
  "type": "Feature",
  "properties": {
    "iso:country":"AU",
    "sg:address":"52 Commercial Rd",
    "sg:city":"Salisbury",
    "sg:classifiers":[
        {
            "category":"Food & Beverages",
            "subcategory":"Liquor & Beverages",
            "type":"Retail Goods"
        }
    ],
    "sg:phone":"+61 8 8281 5200",
    "sg:postcode":"5108",
    "sg:province":"SA",
    "sg:tags":[
        "store"
    ],
    "wof:name":"Salisbury Liquor Store",
    "wof:placetype":"venue"
},
  "geometry": {"coordinates":[138.649124145,-34.7554321289],"type":"Point"}
}