{
  "type": "Feature",
  "properties": {
    "addr:full":"19 Clifford St Torrensville SA 5031",
    "addr:housenumber":"19",
    "addr:postcode":"5031",
    "addr:street":"Clifford St",
    "iso:country":"AU",
    "sg:address":"19 Clifford St",
    "sg:city":"Torrensville",
    "sg:classifiers":[
        {
            "category":"Education",
            "subcategory":"Dance Studio",
            "type":"Public Place"
        }
    ],
    "sg:phone":"+61 8 8352 2849",
    "sg:postcode":"5031",
    "sg:province":"SA",
    "sg:tags":[
        "instruction",
        "language"
    ],
    "wof:name":"Pappas Sam",
    "wof:placetype":"venue"
},
  "geometry": {"coordinates":[138.559890747,-34.9226417542],"type":"Point"}
}