{
  "type": "Feature",
  "properties": {
    "addr:full":"89 Alice St Grafton NSW 2460",
    "addr:housenumber":"89",
    "addr:postcode":"2460",
    "addr:street":"Alice St",
    "iso:country":"AU",
    "sg:address":"89 Alice St",
    "sg:city":"Grafton",
    "sg:classifiers":[
        {
            "category":"Health Services",
            "subcategory":"Health Practitioner",
            "type":"Services"
        }
    ],
    "sg:phone":"+61 2 6643 5646",
    "sg:postcode":"2460",
    "sg:province":"NSW",
    "sg:tags":[
        "physiotherapist"
    ],
    "wof:name":"Burns Jane-Anne",
    "wof:placetype":"venue"
},
  "geometry": {"coordinates":[152.93084716800001,-29.6819248199],"type":"Point"}
}