{
  "type": "Feature",
  "properties": {
    "iso:country":"AU",
    "sg:address":"328 Hamhead Rd",
    "sg:city":"Taigum",
    "sg:classifiers":[
        {
            "category":"Personal",
            "subcategory":"Beauty Salon",
            "type":"Services"
        }
    ],
    "sg:phone":"+61 412 996 283",
    "sg:postcode":"4018",
    "sg:province":"QLD",
    "sg:tags":[
        "supply",
        "artist",
        "make-up"
    ],
    "wof:name":"Stoj Make Up artists",
    "wof:placetype":"venue"
},
  "geometry": {"coordinates":[153.04629499999999,-27.35043],"type":"Point"}
}