{
  "type": "Feature",
  "properties": {
    "addr:full":"69 Gunn St Bridgewater TAS 7030",
    "addr:housenumber":"69",
    "addr:postcode":"7030",
    "addr:street":"Gunn St",
    "iso:country":"AU",
    "sg:address":"69 Gunn St",
    "sg:city":"Bridgewater",
    "sg:classifiers":[
        {
            "category":"Professional",
            "subcategory":"Computer Services",
            "type":"Services"
        }
    ],
    "sg:phone":"+61 417 012 927",
    "sg:postcode":"7030",
    "sg:province":"TAS",
    "sg:tags":[
        "equipment",
        "networking",
        "installation"
    ],
    "wof:name":"Barry's Telephone Services",
    "wof:placetype":"venue"
},
  "geometry": {"coordinates":[147.233978272,-42.7382278442],"type":"Point"}
}