{
  "type": "Feature",
  "properties": {
    "iso:country":"AU",
    "sg:address":"97 West Fyans St",
    "sg:city":"Newtown",
    "sg:classifiers":[
        {
            "category":"Wholesale",
            "subcategory":"Construction Materials",
            "type":"Manufacturing & Wholesale Goods"
        }
    ],
    "sg:phone":"+61 3 5229 9007",
    "sg:postcode":"3220",
    "sg:province":"VIC",
    "sg:tags":[
        "wholesaler",
        "lighting",
        "mfrs",
        "accessory"
    ],
    "wof:name":"Sonic Lighting Pty Ltd",
    "wof:placetype":"venue"
},
  "geometry": {"coordinates":[144.342041,-38.159336],"type":"Point"}
}