{
  "type": "Feature",
  "properties": {
    "addr:full":"37 Hogarth St Cannington WA 6107",
    "addr:housenumber":"37",
    "addr:postcode":"6107",
    "addr:street":"Hogarth St",
    "iso:country":"AU",
    "sg:address":"37 Hogarth St",
    "sg:city":"Cannington",
    "sg:classifiers":[
        {
            "category":"Retail",
            "subcategory":"Auto Repair",
            "type":"Services"
        }
    ],
    "sg:phone":"+61 8 9358 6102",
    "sg:postcode":"6107",
    "sg:province":"WA",
    "sg:tags":[
        "repairer",
        "motor",
        "engineer"
    ],
    "wof:name":"Carousel Repair Centre",
    "wof:placetype":"venue"
},
  "geometry": {"coordinates":[115.949707031,-32.0206756592],"type":"Point"}
}