{
  "type": "Feature",
  "properties": {
    "addr:full":"97 Great Eastern Hwy Belmont WA 6104",
    "addr:housenumber":"97",
    "addr:postcode":"6104",
    "addr:street":"Great Eastern Hwy",
    "iso:country":"AU",
    "sg:address":"97 Great Eastern Hwy",
    "sg:city":"Belmont",
    "sg:classifiers":[
        {
            "category":"Military Area",
            "subcategory":"Air Force Base",
            "type":"Public Place"
        }
    ],
    "sg:phone":"+61 8 9361 7700",
    "sg:postcode":"6104",
    "sg:province":"WA",
    "sg:tags":[
        "merchant",
        "eftpos",
        "facility"
    ],
    "wof:name":"Intellect Australia Pty Ltd",
    "wof:placetype":"venue"
},
  "geometry": {"coordinates":[115.946128845,-31.9289321899],"type":"Point"}
}