{
  "type": "Feature",
  "properties": {
    "iso:country":"AU",
    "sg:address":"87 Crebert St",
    "sg:city":"Mayfield",
    "sg:classifiers":[
        {
            "category":"Building & Trades",
            "subcategory":"Landscaping Services",
            "type":"Services"
        }
    ],
    "sg:phone":"+61 408 006 109",
    "sg:postcode":"2540",
    "sg:province":"NSW",
    "sg:tags":[
        "stump",
        "tree",
        "felling",
        "removal"
    ],
    "wof:name":"Half Price Tree Service",
    "wof:placetype":"venue"
},
  "geometry": {"coordinates":[150.67332458499999,-34.9161071777],"type":"Point"}
}