{
  "type": "Feature",
  "properties": {
    "addr:full":"40 King Edward St Penguin TAS 7316",
    "addr:housenumber":"40",
    "addr:postcode":"7316",
    "addr:street":"King Edward St",
    "iso:country":"AU",
    "sg:address":"40 King Edward St",
    "sg:city":"Penguin",
    "sg:classifiers":[
        {
            "category":"Professional",
            "subcategory":"Computer Services",
            "type":"Services"
        }
    ],
    "sg:phone":"+61 3 6311 0700",
    "sg:postcode":"7316",
    "sg:province":"TAS",
    "sg:tags":[
        "package",
        "software"
    ],
    "wof:name":"Tassietek Online",
    "wof:placetype":"venue"
},
  "geometry": {"coordinates":[146.07484435999999,-41.1162605286],"type":"Point"}
}