{
  "type": "Feature",
  "properties": {
    "addr:full":"635 Warringah Rd Forestville NSW 2087",
    "addr:housenumber":"635",
    "addr:postcode":"2087",
    "addr:street":"Warringah Rd",
    "iso:country":"AU",
    "sg:address":"635 Warringah Rd",
    "sg:city":"Forestville",
    "sg:classifiers":[
        {
            "category":"Retail",
            "subcategory":"Veterinary Services",
            "type":"Services"
        }
    ],
    "sg:phone":"+61 2 9451 3512",
    "sg:postcode":"2087",
    "sg:province":"NSW",
    "sg:tags":[
        "surgeon"
    ],
    "wof:name":"Matthews R",
    "wof:placetype":"venue"
},
  "geometry": {"coordinates":[151.22052001899999,-33.7570152283],"type":"Point"}
}