{
  "type": "Feature",
  "properties": {
    "addr:full":"233 York St Sale VIC 3850",
    "addr:housenumber":"233",
    "addr:postcode":"3850",
    "addr:street":"York St",
    "iso:country":"AU",
    "sg:address":"233 York St",
    "sg:city":"Sale",
    "sg:classifiers":[
        {
            "category":"Sports & Exercise",
            "subcategory":"Playing Field",
            "type":"Entertainment"
        }
    ],
    "sg:phone":"+61 3 5143 2345",
    "sg:postcode":"3850",
    "sg:province":"VIC",
    "sg:tags":[
        "gaming",
        "venue"
    ],
    "wof:name":"Sporting Legends of Sale",
    "wof:placetype":"venue"
},
  "geometry": {"coordinates":[147.0677948,-38.1044692993],"type":"Point"}
}