{
  "type": "Feature",
  "properties": {
    "addr:full":"Firle Plaza Centre 151-161 Glynburn Rd Firle SA 5070",
    "addr:housenumber":"151-161",
    "addr:postcode":"5070",
    "addr:street":"Glynburn Rd",
    "iso:country":"AU",
    "sg:address":"Firle Plaza Centre 151-161 Glynburn Rd",
    "sg:city":"Firle",
    "sg:classifiers":[
        {
            "category":"Cafe",
            "type":"Food & Drink"
        }
    ],
    "sg:phone":"+61 8 8333 0044",
    "sg:postcode":"5070",
    "sg:province":"SA",
    "wof:name":"Caffe Primo",
    "wof:placetype":"venue"
},
  "geometry": {"coordinates":[138.65731811500001,-34.9026565552],"type":"Point"}
}