{
  "type": "Feature",
  "properties": {
    "iso:country":"AU",
    "sg:address":"Unit 5/2- 4 Gray La",
    "sg:city":"Wentworthville",
    "sg:classifiers":[
        {
            "category":"Banks & Credit Unions",
            "subcategory":"Bank",
            "type":"Services"
        }
    ],
    "sg:phone":"+61 2 9531 1337",
    "sg:postcode":"2145",
    "sg:province":"NSW",
    "sg:tags":[
        "concrete",
        "reinforcement"
    ],
    "wof:name":"Qubix International Pty Ltd",
    "wof:placetype":"venue"
},
  "geometry": {"coordinates":[150.97215270999999,-33.8030815125],"type":"Point"}
}