{
  "type": "Feature",
  "properties": {
    "iso:country":"AU",
    "sg:address":"37 Manning St",
    "sg:city":"Taree",
    "sg:classifiers":[
        {
            "category":"Personal",
            "subcategory":"Beauty Salon",
            "type":"Services"
        }
    ],
    "sg:phone":"+61 2 6552 3438",
    "sg:postcode":"2430",
    "sg:province":"NSW",
    "sg:tags":[
        "hairdresser"
    ],
    "wof:name":"Barber's Chair The",
    "wof:placetype":"venue"
},
  "geometry": {"coordinates":[152.46130400000001,-31.912006],"type":"Point"}
}