{
  "type": "Feature",
  "properties": {
    "addr:full":"16 Narooma Drv Ocean Shores NSW 2483",
    "addr:housenumber":"16",
    "addr:postcode":"2483",
    "addr:street":"Narooma Drv",
    "iso:country":"AU",
    "sg:address":"16 Narooma Drv",
    "sg:city":"Ocean Shores",
    "sg:classifiers":[
        {
            "category":"Building & Trades",
            "subcategory":"Plumbing",
            "type":"Services"
        }
    ],
    "sg:phone":"+61 2 6680 1403",
    "sg:postcode":"2483",
    "sg:province":"NSW",
    "sg:tags":[
        "plumber",
        "gasfitters"
    ],
    "wof:name":"Connors Plumbing Services Pty Ltd",
    "wof:placetype":"venue"
},
  "geometry": {"coordinates":[153.542678833,-28.5185222626],"type":"Point"}
}