{
  "type": "Feature",
  "properties": {
    "addr:full":"The Glen Shopping Village 48 Gaskell St Eight Mile Plains QLD 4113",
    "addr:housenumber":"48",
    "addr:postcode":"4113",
    "addr:street":"Gaskell St",
    "iso:country":"AU",
    "sg:address":"The Glen Shopping Village 48 Gaskell St",
    "sg:city":"Eight Mile Plains",
    "sg:classifiers":[
        {
            "category":"Personal",
            "subcategory":"Beauty Salon",
            "type":"Services"
        }
    ],
    "sg:phone":"+61 7 3841 0664",
    "sg:postcode":"4113",
    "sg:province":"QLD",
    "sg:tags":[
        "hairdresser"
    ],
    "wof:name":"Southern Hair Designs",
    "wof:placetype":"venue"
},
  "geometry": {"coordinates":[153.09611511200001,-27.5846195221],"type":"Point"}
}