{
  "type": "Feature",
  "properties": {
    "addr:full":"28 Reginald Ave Belmore NSW 2192",
    "addr:housenumber":"28",
    "addr:postcode":"2192",
    "addr:street":"Reginald Ave",
    "iso:country":"AU",
    "sg:address":"28 Reginald Ave",
    "sg:city":"Belmore",
    "sg:classifiers":[
        {
            "category":"Health Services",
            "subcategory":"Health Practitioner",
            "type":"Services"
        }
    ],
    "sg:phone":"+61 2 9789 6400",
    "sg:postcode":"2192",
    "sg:province":"NSW",
    "sg:tags":[
        "alternative"
    ],
    "wof:name":"Rebirthing Australia",
    "wof:placetype":"venue"
},
  "geometry": {"coordinates":[151.09184300000001,-33.921215],"type":"Point"}
}