{
  "type": "Feature",
  "properties": {
    "addr:full":"8 Charles St Gledhow WA 6330",
    "addr:housenumber":"8",
    "addr:postcode":"6330",
    "addr:street":"Charles St",
    "iso:country":"AU",
    "sg:address":"8 Charles St",
    "sg:city":"Gledhow",
    "sg:classifiers":[
        {
            "category":"Professional",
            "subcategory":"Business Services",
            "type":"Services"
        }
    ],
    "sg:phone":"+61 8 9841 5127",
    "sg:postcode":"6330",
    "sg:province":"WA",
    "sg:tags":[
        "livestock",
        "transport"
    ],
    "wof:name":"Lister J F & D M",
    "wof:placetype":"venue"
},
  "geometry": {"coordinates":[117.820640564,-34.9998893738],"type":"Point"}
}