{
  "type": "Feature",
  "properties": {
    "iso:country":"AU",
    "sg:address":"The Loxton Cellars Bookpurnong Rd",
    "sg:city":"Loxton",
    "sg:classifiers":[
        {
            "category":"Farming",
            "subcategory":"Vineyard",
            "type":"Manufacturing & Wholesale Goods"
        }
    ],
    "sg:phone":"+61 8 8584 7236",
    "sg:postcode":"5333",
    "sg:province":"SA",
    "sg:tags":[
        "winery"
    ],
    "wof:name":"Australian Vintage Ltd",
    "wof:placetype":"venue"
},
  "geometry": {"coordinates":[140.58076477,-34.4452819824],"type":"Point"}
}