{
  "type": "Feature",
  "properties": {
    "iso:country":"AU",
    "sg:address":"Shop 4 Jonson La",
    "sg:city":"Byron Bay",
    "sg:classifiers":[
        {
            "category":"Arts & Performance",
            "subcategory":"Art Gallery",
            "type":"Entertainment"
        }
    ],
    "sg:phone":"+61 2 6680 8485",
    "sg:postcode":"2481",
    "sg:province":"NSW",
    "wof:name":"Laughing Horse Gallery",
    "wof:placetype":"venue"
},
  "geometry": {"coordinates":[153.61247253400001,-28.6448802948],"type":"Point"}
}