{
  "type": "Feature",
  "properties": {
    "addr:full":"39 Hallstrom Pl Wetherill Park NSW 2164",
    "addr:housenumber":"39",
    "addr:postcode":"2164",
    "addr:street":"Hallstrom Pl",
    "iso:country":"AU",
    "sg:address":"39 Hallstrom Pl",
    "sg:city":"Wetherill Park",
    "sg:classifiers":[
        {
            "category":"Manufacturing",
            "subcategory":"Metals",
            "type":"Manufacturing & Wholesale Goods"
        }
    ],
    "sg:phone":"+61 2 9756 1343",
    "sg:postcode":"2164",
    "sg:province":"NSW",
    "sg:tags":[
        "sheet",
        "worker"
    ],
    "wof:name":"ENR Fabrications",
    "wof:placetype":"venue"
},
  "geometry": {"coordinates":[150.88531494099999,-33.8451538086],"type":"Point"}
}