{
  "type": "Feature",
  "properties": {
    "addr:full":"32 Scotch Pde Chelsea VIC 3196",
    "addr:housenumber":"32",
    "addr:postcode":"3196",
    "addr:street":"Scotch Pde",
    "iso:country":"AU",
    "sg:address":"32 Scotch Pde",
    "sg:city":"Chelsea",
    "sg:classifiers":[
        {
            "category":"Health Services",
            "subcategory":"Health Practitioner",
            "type":"Services"
        }
    ],
    "sg:phone":"+61 3 9772 8469",
    "sg:postcode":"3196",
    "sg:province":"VIC",
    "sg:tags":[
        "alternative"
    ],
    "wof:name":"Health For Harmony",
    "wof:placetype":"venue"
},
  "geometry": {"coordinates":[145.12922668499999,-38.0554008484],"type":"Point"}
}