{
  "type": "Feature",
  "properties": {
    "iso:country":"AU",
    "sg:address":"51- 63 Cavan Rd",
    "sg:city":"Gepps Cross",
    "sg:classifiers":[
        {
            "category":"Banks & Credit Unions",
            "subcategory":"Bank",
            "type":"Services"
        }
    ],
    "sg:phone":"+61 8 8360 1111",
    "sg:postcode":"5094",
    "sg:province":"SA",
    "sg:tags":[
        "concrete",
        "reinforcement"
    ],
    "wof:name":"Mike Marner Reinforcing Pty Ltd",
    "wof:placetype":"venue"
},
  "geometry": {"coordinates":[138.59909057600001,-34.8375053406],"type":"Point"}
}