{
  "type": "Feature",
  "properties": {
    "iso:country":"AU",
    "sg:address":"14 Ellesmere Rd",
    "sg:city":"Gymea Bay",
    "sg:classifiers":[
        {
            "category":"Utilities",
            "subcategory":"Electric",
            "type":"Services"
        }
    ],
    "sg:phone":"+61 410 632 412",
    "sg:postcode":"2227",
    "sg:province":"NSW",
    "sg:tags":[
        "electrical",
        "contractor"
    ],
    "wof:name":"St. George Elecrical Data & Communications",
    "wof:placetype":"venue"
},
  "geometry": {"coordinates":[151.091064453,-34.0503845215],"type":"Point"}
}