{
  "type": "Feature",
  "properties": {
    "addr:full":"Lot 580/ Moses St Mt Magnet WA 6638",
    "addr:postcode":"6638",
    "addr:street":"St",
    "iso:country":"AU",
    "sg:address":"Lot 580/ Moses St",
    "sg:city":"Mt Magnet",
    "sg:classifiers":[
        {
            "category":"Professional",
            "type":"Services"
        }
    ],
    "sg:phone":"+61 8 9963 4866",
    "sg:postcode":"6638",
    "sg:province":"WA",
    "sg:tags":[
        "courier"
    ],
    "wof:name":"Mt Magnet Freight & Services",
    "wof:placetype":"venue"
},
  "geometry": {"coordinates":[117.83952331499999,-28.0651531219],"type":"Point"}
}