{
  "type": "Feature",
  "properties": {
    "iso:country":"AU",
    "sg:address":"145 Stud Rd",
    "sg:city":"Wantirna",
    "sg:classifiers":[
        {
            "category":"Health Services",
            "subcategory":"Dentist",
            "type":"Services"
        }
    ],
    "sg:phone":"+61 3 9887 1304",
    "sg:postcode":"3152",
    "sg:province":"VIC",
    "wof:name":"Wantirna Dental",
    "wof:placetype":"venue"
},
  "geometry": {"coordinates":[145.24382019000001,-37.8528823853],"type":"Point"}
}