{
  "type": "Feature",
  "properties": {
    "addr:full":"568 Hume Hwy Casula NSW 2170",
    "addr:housenumber":"568",
    "addr:postcode":"2170",
    "addr:street":"Hume Hwy",
    "iso:country":"AU",
    "sg:address":"568 Hume Hwy",
    "sg:city":"Casula",
    "sg:classifiers":[
        {
            "category":"Travel",
            "subcategory":"Hotels & Motels",
            "type":"Entertainment"
        }
    ],
    "sg:phone":"+61 2 9602 6399",
    "sg:postcode":"2170",
    "sg:province":"NSW",
    "wof:name":"Jolly Knight Motel",
    "wof:placetype":"venue"
},
  "geometry": {"coordinates":[150.905059814,-33.950176239],"type":"Point"}
}