{
  "type": "Feature",
  "properties": {
    "addr:full":"Gracemere Trade Centre 27 Old Capricorn Hwy Gracemere QLD 4702",
    "addr:housenumber":"gracemere;27",
    "addr:postcode":"4702",
    "addr:street":"Old Capricorn Hwy",
    "iso:country":"AU",
    "sg:address":"Gracemere Trade Centre 27 Old Capricorn Hwy",
    "sg:city":"Gracemere",
    "sg:classifiers":[
        {
            "category":"Manufacturing",
            "subcategory":"Metals",
            "type":"Manufacturing & Wholesale Goods"
        }
    ],
    "sg:phone":"+61 7 4933 3223",
    "sg:postcode":"4702",
    "sg:province":"QLD",
    "sg:tags":[
        "steel",
        "fabricator",
        "mfrs"
    ],
    "wof:name":"Gracemere Sheetmetal",
    "wof:placetype":"venue"
},
  "geometry": {"coordinates":[150.456207275,-23.4325504303],"type":"Point"}
}