{
  "type": "Feature",
  "properties": {
    "addr:full":"51 Butler St Tully QLD 4854",
    "addr:housenumber":"51",
    "addr:postcode":"4854",
    "addr:street":"Butler St",
    "iso:country":"AU",
    "sg:address":"51 Butler St",
    "sg:city":"Tully",
    "sg:classifiers":[
        {
            "category":"Fast Food",
            "type":"Food & Drink"
        }
    ],
    "sg:phone":"+61 7 4068 2114",
    "sg:postcode":"4854",
    "sg:province":"QLD",
    "sg:tags":[
        "away",
        "take"
    ],
    "wof:name":"Tropicana Diner",
    "wof:placetype":"venue"
},
  "geometry": {"coordinates":[145.92684936500001,-17.9341754913],"type":"Point"}
}