{
  "type": "Feature",
  "properties": {
    "addr:full":"4 Glenayr Ave North Bondi NSW 2026",
    "addr:housenumber":"4",
    "addr:postcode":"2026",
    "addr:street":"Glenayr Ave",
    "iso:country":"AU",
    "sg:address":"4 Glenayr Ave",
    "sg:city":"North Bondi",
    "sg:classifiers":[
        {
            "category":"Personal",
            "subcategory":"Beauty Salon",
            "type":"Services"
        }
    ],
    "sg:phone":"+61 2 9300 0335",
    "sg:postcode":"2026",
    "sg:province":"NSW",
    "wof:name":"Wax & Polish",
    "wof:placetype":"venue"
},
  "geometry": {"coordinates":[151.27583313,-33.8821563721],"type":"Point"}
}