{
  "type": "Feature",
  "properties": {
    "iso:country":"AU",
    "sg:address":"54 Cleveland St",
    "sg:city":"Chippendale",
    "sg:classifiers":[
        {
            "category":"Travel",
            "subcategory":"Hotels & Motels",
            "type":"Entertainment"
        }
    ],
    "sg:phone":"+61 2 9318 1133",
    "sg:postcode":"2008",
    "sg:province":"NSW",
    "sg:tags":[
        "accommodation"
    ],
    "wof:name":"The Rose Hotel",
    "wof:placetype":"venue"
},
  "geometry": {"coordinates":[151.19500732399999,-33.8879432678],"type":"Point"}
}