{
  "type": "Feature",
  "properties": {
    "addr:full":"16 Monticle St Highbury SA 5089",
    "addr:housenumber":"16",
    "addr:postcode":"5089",
    "addr:street":"Monticle St",
    "iso:country":"AU",
    "sg:address":"16 Monticle St",
    "sg:city":"Highbury",
    "sg:classifiers":[
        {
            "category":"Building & Trades",
            "subcategory":"Landscaping Services",
            "type":"Services"
        }
    ],
    "sg:phone":"+61 8 8263 8188",
    "sg:postcode":"5089",
    "sg:province":"SA",
    "sg:tags":[
        "inspection"
    ],
    "wof:name":"G P White Building Services",
    "wof:placetype":"venue"
},
  "geometry": {"coordinates":[138.71220398,-34.8516311646],"type":"Point"}
}