{
  "type": "Feature",
  "properties": {
    "iso:country":"AU",
    "sg:address":"U2/ 2 Welder Rd",
    "sg:city":"Seven Hills",
    "sg:classifiers":[
        {
            "category":"Manufacturing",
            "subcategory":"Metals",
            "type":"Manufacturing & Wholesale Goods"
        }
    ],
    "sg:phone":"+61 2 9624 8333",
    "sg:postcode":"2147",
    "sg:province":"NSW",
    "sg:tags":[
        "steel",
        "fabricator",
        "mfrs"
    ],
    "wof:name":"M1 Fabrication & Engineering",
    "wof:placetype":"venue"
},
  "geometry": {"coordinates":[150.95826721200001,-33.770778656],"type":"Point"}
}