{
  "type": "Feature",
  "properties": {
    "addr:full":"Shepparton Rd Euroa VIC 3666",
    "addr:postcode":"3666",
    "addr:street":"Shepparton Rd",
    "iso:country":"AU",
    "sg:address":"Shepparton Rd",
    "sg:city":"Euroa",
    "sg:classifiers":[
        {
            "category":"Retail",
            "subcategory":"Animal Services",
            "type":"Services"
        }
    ],
    "sg:phone":"+61 3 5795 2827",
    "sg:postcode":"3666",
    "sg:province":"VIC",
    "sg:tags":[
        "breeder",
        "sheep",
        "stud",
        "cattle"
    ],
    "wof:name":"Castle Brangus",
    "wof:placetype":"venue"
},
  "geometry": {"coordinates":[145.58433532699999,-36.7453804016],"type":"Point"}
}