{
  "type": "Feature",
  "properties": {
    "addr:full":"Medicross Medical Cnr Churchill & Warwick Sts Ipswich QLD 4305",
    "addr:postcode":"4305",
    "addr:street":"Cnr",
    "iso:country":"AU",
    "sg:address":"Medicross Medical Cnr Churchill & Warwick Sts",
    "sg:city":"Ipswich",
    "sg:classifiers":[
        {
            "category":"Health Services",
            "subcategory":"Doctor",
            "type":"Services"
        }
    ],
    "sg:phone":"+61 7 3202 1131",
    "sg:postcode":"4305",
    "sg:province":"QLD",
    "sg:tags":[
        "podiatrist"
    ],
    "wof:name":"Jason McLellan",
    "wof:placetype":"venue"
},
  "geometry": {"coordinates":[152.76097106899999,-27.6198425293],"type":"Point"}
}