{
  "type": "Feature",
  "properties": {
    "iso:country":"AU",
    "sg:address":"171 High St",
    "sg:city":"Heathcote",
    "sg:classifiers":[
        {
            "category":"Travel",
            "subcategory":"Hotels & Motels",
            "type":"Entertainment"
        }
    ],
    "sg:phone":"+61 3 5433 2032",
    "sg:postcode":"3523",
    "sg:province":"VIC",
    "sg:tags":[
        "accommodation"
    ],
    "wof:name":"Union Hotel",
    "wof:placetype":"venue"
},
  "geometry": {"coordinates":[144.706207,-36.919609],"type":"Point"}
}