{
  "type": "Feature",
  "properties": {
    "addr:full":"Shop 3, 149-163 Argyle St Traralgon VIC 3844",
    "addr:housenumber":"shop 3",
    "addr:postcode":"149-163;3844",
    "addr:street":"Argyle St",
    "iso:country":"AU",
    "sg:address":"Shop 3, 149-163 Argyle St",
    "sg:city":"Traralgon",
    "sg:classifiers":[
        {
            "category":"Industrial Area",
            "type":"Public Place"
        }
    ],
    "sg:phone":"+61 3 5176 5900",
    "sg:postcode":"3844",
    "sg:province":"VIC",
    "sg:tags":[
        "protective",
        "clothing"
    ],
    "wof:name":"Totally Workwear",
    "wof:placetype":"venue"
},
  "geometry": {"coordinates":[146.55622863799999,-38.1912384033],"type":"Point"}
}