{
  "type": "Feature",
  "properties": {
    "addr:full":"1/ 167 Kilby Rd Kew East VIC 3102",
    "addr:housenumber":"/ 167",
    "addr:postcode":"3102",
    "addr:street":"Kilby Rd",
    "iso:country":"AU",
    "sg:address":"1/ 167 Kilby Rd",
    "sg:city":"Kew East",
    "sg:classifiers":[
        {
            "category":"Real Estate",
            "subcategory":"Architect",
            "type":"Services"
        }
    ],
    "sg:phone":"+61 3 9859 9719",
    "sg:postcode":"3102",
    "sg:province":"VIC",
    "wof:name":"Paciocco Tom Architect",
    "wof:placetype":"venue"
},
  "geometry": {"coordinates":[145.059036255,-37.7926330566],"type":"Point"}
}