{
  "type": "Feature",
  "properties": {
    "addr:full":"66 Port Stephens St Raymond Terrace NSW 2324",
    "addr:housenumber":"66",
    "addr:postcode":"2324",
    "addr:street":"Port Stephens St",
    "iso:country":"AU",
    "sg:address":"66 Port Stephens St",
    "sg:city":"Raymond Terrace",
    "sg:classifiers":[
        {
            "category":"Banks & Credit Unions",
            "subcategory":"Investment Brokerage",
            "type":"Services"
        }
    ],
    "sg:phone":"+61 2 4983 1088",
    "sg:postcode":"2324",
    "sg:province":"NSW",
    "sg:tags":[
        "debt",
        "collection"
    ],
    "wof:name":"Marshall & Partners",
    "wof:placetype":"venue"
},
  "geometry": {"coordinates":[151.74252319300001,-32.7609481812],"type":"Point"}
}