{
  "type": "Feature",
  "properties": {
    "iso:country":"AU",
    "sg:address":"PO Box 8",
    "sg:city":"Earlwood",
    "sg:classifiers":[
        {
            "category":"Arts & Performance",
            "subcategory":"Music",
            "type":"Entertainment"
        }
    ],
    "sg:phone":"+61 411 137 444",
    "sg:postcode":"2206",
    "sg:province":"NSW",
    "sg:tags":[
        "mobile",
        "jockey",
        "disc"
    ],
    "wof:name":"Global Mobile Disco's",
    "wof:placetype":"venue"
},
  "geometry": {"coordinates":[151.12493900000001,-33.926922],"type":"Point"}
}