{
  "type": "Feature",
  "properties": {
    "addr:full":"2/ 12 Spoonbill St Hinchinbrook NSW 2168",
    "addr:housenumber":"/ 12",
    "addr:postcode":"2168",
    "addr:street":"Spoonbill St",
    "iso:country":"AU",
    "sg:address":"2/ 12 Spoonbill St",
    "sg:city":"Hinchinbrook",
    "sg:classifiers":[
        {
            "category":"Education",
            "subcategory":"Special Training",
            "type":"Public Place"
        }
    ],
    "sg:phone":"+61 2 8783 9796",
    "sg:postcode":"2168",
    "sg:province":"NSW",
    "sg:tags":[
        "tuition-educational"
    ],
    "wof:name":"Maths & Science Coaching Centre",
    "wof:placetype":"venue"
},
  "geometry": {"coordinates":[150.86958313,-33.9192008972],"type":"Point"}
}