{
  "type": "Feature",
  "properties": {
    "addr:full":"455 Old Geelong Rd Hoppers Crossing VIC 3029",
    "addr:housenumber":"455",
    "addr:postcode":"3029",
    "addr:street":"Old Geelong Rd",
    "iso:country":"AU",
    "sg:address":"455 Old Geelong Rd",
    "sg:city":"Hoppers Crossing",
    "sg:classifiers":[
        {
            "category":"Autos & Motor Vehicles",
            "subcategory":"Auto Supplies",
            "type":"Retail Goods"
        }
    ],
    "sg:phone":"+61 3 9931 0811",
    "sg:postcode":"3029",
    "sg:province":"VIC",
    "sg:tags":[
        "accessory"
    ],
    "wof:name":"Motorco Parts",
    "wof:placetype":"venue"
},
  "geometry": {"coordinates":[144.73286400000001,-37.868],"type":"Point"}
}