{
  "type": "Feature",
  "properties": {
    "iso:country":"AU",
    "sg:address":"12 Verrell St",
    "sg:city":"Wetherill Park",
    "sg:classifiers":[
        {
            "category":"Professional",
            "subcategory":"Printing & Photocopies",
            "type":"Services"
        }
    ],
    "sg:phone":"+61 2 9609 5357",
    "sg:postcode":"2164",
    "sg:province":"NSW",
    "sg:tags":[
        "trophy"
    ],
    "wof:name":"Fairfield Trophies Trading",
    "wof:placetype":"venue"
},
  "geometry": {"coordinates":[150.92202758799999,-33.8438682556],"type":"Point"}
}