{
  "type": "Feature",
  "properties": {
    "iso:country":"AU",
    "sg:address":"21 Claremont St",
    "sg:city":"Campsie",
    "sg:classifiers":[
        {
            "category":"Health Services",
            "subcategory":"Doctor",
            "type":"Services"
        }
    ],
    "sg:phone":"+61 2 9789 6994",
    "sg:postcode":"2194",
    "sg:province":"NSW",
    "sg:tags":[
        "medical",
        "practitioner"
    ],
    "wof:name":"Wei Marc Dr",
    "wof:placetype":"venue"
},
  "geometry": {"coordinates":[151.10257,-33.914639],"type":"Point"}
}