{
  "type": "Feature",
  "properties": {
    "iso:country":"AU",
    "sg:address":"PO Box 3121",
    "sg:city":"Asquith",
    "sg:classifiers":[
        {
            "category":"Arena",
            "subcategory":"Bull Ring",
            "type":"Entertainment"
        }
    ],
    "sg:phone":"+61 409 917 776",
    "sg:postcode":"2077",
    "sg:province":"NSW",
    "sg:tags":[
        "club",
        "bushwalking"
    ],
    "wof:name":"Sydney Bushwalks",
    "wof:placetype":"venue"
},
  "geometry": {"coordinates":[151.10940551799999,-33.6891212463],"type":"Point"}
}