{
  "type": "Feature",
  "properties": {
    "addr:full":"Queen Adelaide Building Advanced Salon Ground Level, 90-112 Queen St Brisbane QLD 4000",
    "addr:housenumber":"90-112",
    "addr:postcode":"4000",
    "addr:street":"Queen St",
    "iso:country":"AU",
    "sg:address":"Queen Adelaide Building Advanced Salon Ground Level, 90-112 Queen St",
    "sg:city":"Brisbane",
    "sg:classifiers":[
        {
            "category":"Education",
            "subcategory":"Special Training",
            "type":"Public Place"
        }
    ],
    "sg:phone":"+61 7 3210 2099",
    "sg:postcode":"4000",
    "sg:province":"QLD",
    "sg:tags":[
        "college",
        "hairdressing"
    ],
    "wof:name":"Brisbane School Of Hairdressing",
    "wof:placetype":"venue"
},
  "geometry": {"coordinates":[153.02471923799999,-27.4698524475],"type":"Point"}
}