{
  "type": "Feature",
  "properties": {
    "addr:full":"2 Minnie St Belmore NSW 2192",
    "addr:housenumber":"2",
    "addr:postcode":"2192",
    "addr:street":"Minnie St",
    "iso:country":"AU",
    "sg:address":"2 Minnie St",
    "sg:city":"Belmore",
    "sg:classifiers":[
        {
            "category":"Building & Trades",
            "subcategory":"Construction",
            "type":"Services"
        }
    ],
    "sg:phone":"+61 2 9759 6631",
    "sg:postcode":"2192",
    "sg:province":"NSW",
    "sg:tags":[
        "fencing",
        "contractor"
    ],
    "wof:name":"D & H Fencing",
    "wof:placetype":"venue"
},
  "geometry": {"coordinates":[151.07914700000001,-33.908768],"type":"Point"}
}