{
  "type": "Feature",
  "properties": {
    "addr:full":"1690 Cox Peninsula Rd Darwin River NT 0822",
    "addr:housenumber":"1690",
    "addr:postcode":"0822",
    "addr:street":"Cox Peninsula Rd",
    "iso:country":"AU",
    "sg:address":"1690 Cox Peninsula Rd",
    "sg:city":"Darwin River",
    "sg:classifiers":[
        {
            "category":"Manufacturing",
            "subcategory":"Tools & Machinery",
            "type":"Manufacturing & Wholesale Goods"
        }
    ],
    "sg:phone":"+61 8 8988 6090",
    "sg:postcode":"0822",
    "sg:province":"NT",
    "sg:tags":[
        "earth",
        "excavating",
        "moving",
        "equipment"
    ],
    "wof:name":"Tracks Tilt & Crane",
    "wof:placetype":"venue"
},
  "geometry": {"coordinates":[131.080139,-12.673453],"type":"Point"}
}