{
  "type": "Feature",
  "properties": {
    "addr:full":"54 Ellen St Port Pirie SA 5540",
    "addr:housenumber":"54",
    "addr:postcode":"5540",
    "addr:street":"Ellen St",
    "iso:country":"AU",
    "sg:address":"54 Ellen St",
    "sg:city":"Port Pirie",
    "sg:classifiers":[
        {
            "category":"Professional",
            "subcategory":"Employment Agencies",
            "type":"Services"
        }
    ],
    "sg:phone":"+61 8 8633 0955",
    "sg:postcode":"5540",
    "sg:province":"SA",
    "sg:tags":[
        "provider",
        "internet"
    ],
    "wof:name":"Tell Technology",
    "wof:placetype":"venue"
},
  "geometry": {"coordinates":[138.009857178,-33.1755905151],"type":"Point"}
}