{
  "type": "Feature",
  "properties": {
    "addr:full":"PO Box 147 Brisbane Markets QLD 4106",
    "addr:postcode":"4106",
    "iso:country":"AU",
    "sg:address":"PO Box 147",
    "sg:city":"Brisbane Markets",
    "sg:classifiers":[
        {
            "category":"Personal",
            "type":"Services"
        }
    ],
    "sg:phone":"+61 7 3272 9147",
    "sg:postcode":"4106",
    "sg:province":"QLD",
    "sg:tags":[
        "gift"
    ],
    "wof:name":"Baskets & Things",
    "wof:placetype":"venue"
},
  "geometry": {"coordinates":[153.00386047399999,-27.5508708954],"type":"Point"}
}