{
  "type": "Feature",
  "properties": {
    "addr:full":"2a/ 2 Mary St Leichhardt NSW 2040",
    "addr:housenumber":"2a / 2",
    "addr:postcode":"2040",
    "addr:street":"Mary St",
    "iso:country":"AU",
    "sg:address":"2a/ 2 Mary St",
    "sg:city":"Leichhardt",
    "sg:classifiers":[
        {
            "category":"Personal",
            "subcategory":"Massage",
            "type":"Services"
        }
    ],
    "sg:phone":"+61 2 9810 9019",
    "sg:postcode":"2040",
    "sg:province":"NSW",
    "sg:tags":[
        "therapy"
    ],
    "wof:name":"Christopher Chin Massage Therapist",
    "wof:placetype":"venue"
},
  "geometry": {"coordinates":[151.15524300000001,-33.872902],"type":"Point"}
}