{
  "type": "Feature",
  "properties": {
    "iso:country":"AU",
    "sg:address":"2a/ 2 Mary St",
    "sg:city":"Leichhardt",
    "sg:classifiers":[
        {
            "category":"Personal",
            "subcategory":"Massage",
            "type":"Services"
        }
    ],
    "sg:phone":"+61 2 9810 9019",
    "sg:postcode":"2040",
    "sg:province":"NSW",
    "sg:tags":[
        "therapy"
    ],
    "wof:name":"Christopher Chin Massage Therapist",
    "wof:placetype":"venue"
},
  "geometry": {"coordinates":[151.155243,-33.872902],"type":"Point"}
}