{
  "type": "Feature",
  "properties": {
    "addr:full":"15 Beach St Gladesville NSW 2111",
    "addr:housenumber":"15",
    "addr:postcode":"2111",
    "addr:street":"Beach St",
    "iso:country":"AU",
    "sg:address":"15 Beach St",
    "sg:city":"Gladesville",
    "sg:classifiers":[
        {
            "category":"Building & Trades",
            "subcategory":"Landscaping Services",
            "type":"Services"
        }
    ],
    "sg:phone":"+61 415 700 800",
    "sg:postcode":"2111",
    "sg:province":"NSW",
    "sg:tags":[
        "horticultural",
        "consultant"
    ],
    "wof:name":"Four Seasons Garden Advisory Service",
    "wof:placetype":"venue"
},
  "geometry": {"coordinates":[151.11526489299999,-33.8319854736],"type":"Point"}
}