{
  "type": "Feature",
  "properties": {
    "addr:full":"Macrossan St Ravenswood QLD 4816",
    "addr:postcode":"4816",
    "addr:street":"Macrossan St",
    "iso:country":"AU",
    "sg:address":"Macrossan St",
    "sg:city":"Ravenswood",
    "sg:classifiers":[
        {
            "category":"Museum",
            "type":"Entertainment"
        }
    ],
    "sg:phone":"+61 7 4770 2047",
    "sg:postcode":"4816",
    "sg:province":"QLD",
    "wof:name":"Ravenswood Court House & Museum",
    "wof:placetype":"venue"
},
  "geometry": {"coordinates":[146.88171399999999,-20.095375],"type":"Point"}
}