{
  "type": "Feature",
  "properties": {
    "iso:country":"AU",
    "sg:address":"Lot 2 Croydon Rd",
    "sg:city":"Karratha",
    "sg:classifiers":[
        {
            "category":"Retail",
            "subcategory":"Auto Repair",
            "type":"Services"
        }
    ],
    "sg:phone":"+61 8 9185 4666",
    "sg:postcode":"6714",
    "sg:province":"WA",
    "sg:tags":[
        "camper-trailers",
        "caravan",
        "servicing"
    ],
    "wof:name":"Karratha Caravans",
    "wof:placetype":"venue"
},
  "geometry": {"coordinates":[116.85974883999999,-20.7692604065],"type":"Point"}
}