{
  "type": "Feature",
  "properties": {
    "iso:country":"AU",
    "sg:address":"1/ 9 Brooks Ave",
    "sg:city":"Wyoming",
    "sg:classifiers":[
        {
            "category":"Education",
            "subcategory":"Music School",
            "type":"Public Place"
        }
    ],
    "sg:phone":"+61 2 4328 1878",
    "sg:postcode":"2250",
    "sg:province":"NSW",
    "sg:tags":[
        "therapy",
        "relaxation"
    ],
    "wof:name":"Mellow Monkeys",
    "wof:placetype":"venue"
},
  "geometry": {"coordinates":[151.34687805199999,-33.4011955261],"type":"Point"}
}