{
  "type": "Feature",
  "properties": {
    "addr:full":"104 Swan St Richmond VIC 3121",
    "addr:housenumber":"104",
    "addr:postcode":"3121",
    "addr:street":"Swan St",
    "iso:country":"AU",
    "sg:address":"104 Swan St",
    "sg:city":"Richmond",
    "sg:classifiers":[
        {
            "category":"Restaurant",
            "type":"Food & Drink"
        }
    ],
    "sg:phone":"+61 3 9427 7771",
    "sg:postcode":"3121",
    "sg:province":"VIC",
    "wof:name":"Buddha's Banquet",
    "wof:placetype":"venue"
},
  "geometry": {"coordinates":[144.99354553200001,-37.8253097534],"type":"Point"}
}