{
  "type": "Feature",
  "properties": {
    "iso:country":"AU",
    "sg:address":"Middle Rd",
    "sg:city":"Hillcrest",
    "sg:classifiers":[
        {
            "category":"Autos & Motor Vehicles",
            "subcategory":"Automobile Sales",
            "type":"Retail Goods"
        }
    ],
    "sg:phone":"+61 7 3809 0922",
    "sg:postcode":"4118",
    "sg:province":"QLD",
    "sg:tags":[
        "equipment",
        "trailer"
    ],
    "wof:name":"U-Haul Trailers",
    "wof:placetype":"venue"
},
  "geometry": {"coordinates":[153.030853272,-27.6729011536],"type":"Point"}
}