{
  "type": "Feature",
  "properties": {
    "addr:full":"47 Showground Rd Tamworth NSW 2340",
    "addr:housenumber":"47",
    "addr:postcode":"2340",
    "addr:street":"Showground Rd",
    "iso:country":"AU",
    "sg:address":"47 Showground Rd",
    "sg:city":"Tamworth",
    "sg:classifiers":[
        {
            "category":"Professional",
            "type":"Services"
        }
    ],
    "sg:phone":"+61 2 6762 1511",
    "sg:postcode":"2340",
    "sg:province":"NSW",
    "sg:tags":[
        "coating",
        "powder"
    ],
    "wof:name":"Tamworth Balustrade & Fabrication",
    "wof:placetype":"venue"
},
  "geometry": {"coordinates":[150.90936279300001,-31.0945663452],"type":"Point"}
}