{
  "type": "Feature",
  "properties": {
    "iso:country":"AU",
    "sg:address":"365 High St",
    "sg:city":"Kew",
    "sg:classifiers":[
        {
            "category":"Arts & Performance",
            "subcategory":"Music",
            "type":"Entertainment"
        }
    ],
    "sg:phone":"+61 3 9853 6885",
    "sg:postcode":"3101",
    "sg:province":"VIC",
    "sg:tags":[
        "hi-fi",
        "equipment"
    ],
    "wof:name":"Joll Electronics",
    "wof:placetype":"venue"
},
  "geometry": {"coordinates":[145.03782653799999,-37.8041114807],"type":"Point"}
}