{
  "type": "Feature",
  "properties": {
    "iso:country":"AU",
    "sg:address":"Unit 5, 1 Reliance Drv",
    "sg:city":"Tuggerah",
    "sg:classifiers":[
        {
            "category":"Social Services",
            "subcategory":"Child Care",
            "type":"Services"
        }
    ],
    "sg:phone":"+61 2 4351 9566",
    "sg:postcode":"2259",
    "sg:province":"NSW",
    "sg:tags":[
        "equipment",
        "identification"
    ],
    "sg:website":"http://www.wizid.com.au",
    "wof:name":"Wizid Pty Ltd",
    "wof:placetype":"venue"
},
  "geometry": {"coordinates":[151.42123413100001,-33.3134422302],"type":"Point"}
}