{
  "type": "Feature",
  "properties": {
    "addr:full":"PO Box 763 Woy Woy NSW 2256",
    "addr:postcode":"2256",
    "iso:country":"AU",
    "sg:address":"PO Box 763",
    "sg:city":"Woy Woy",
    "sg:classifiers":[
        {
            "category":"Building & Trades",
            "subcategory":"Landscaping Services",
            "type":"Services"
        }
    ],
    "sg:phone":"+61 417 626 538",
    "sg:postcode":"2256",
    "sg:province":"NSW",
    "sg:tags":[
        "firebreak",
        "clearing",
        "land",
        "contractor"
    ],
    "wof:name":"Davmar Excavations Pty Ltd",
    "wof:placetype":"venue"
},
  "geometry": {"coordinates":[151.327468872,-33.4929008484],"type":"Point"}
}