{
  "type": "Feature",
  "properties": {
    "iso:country":"AU",
    "sg:address":"Mildura Airport Terminal Building",
    "sg:city":"Mildura",
    "sg:classifiers":[
        {
            "category":"Retail",
            "subcategory":"Auto Rental",
            "type":"Services"
        }
    ],
    "sg:phone":"+61 3 5022 1688",
    "sg:postcode":"3500",
    "sg:province":"VIC",
    "sg:tags":[
        "car",
        "hire",
        "minibus"
    ],
    "wof:name":"Europcar",
    "wof:placetype":"venue"
},
  "geometry": {"coordinates":[142.153244019,-34.1758880615],"type":"Point"}
}