{
  "type": "Feature",
  "properties": {
    "addr:full":"83 Wanneroo Rd Tuart Hill WA 6060",
    "addr:housenumber":"83",
    "addr:postcode":"6060",
    "addr:street":"Wanneroo Rd",
    "iso:country":"AU",
    "sg:address":"83 Wanneroo Rd",
    "sg:city":"Tuart Hill",
    "sg:classifiers":[
        {
            "category":"Home & Garden",
            "subcategory":"Carpets & Floor Coverings",
            "type":"Retail Goods"
        }
    ],
    "sg:phone":"+61 8 9207 3199",
    "sg:postcode":"6060",
    "sg:province":"WA",
    "sg:tags":[
        "tile",
        "wall"
    ],
    "wof:name":"Natural Stone & Tile Centre",
    "wof:placetype":"venue"
},
  "geometry": {"coordinates":[115.84230804400001,-31.9013996124],"type":"Point"}
}