{
  "type": "Feature",
  "properties": {
    "iso:country":"AU",
    "sg:address":"39 Balwyn Rd",
    "sg:city":"Bulleen",
    "sg:classifiers":[
        {
            "category":"Personal",
            "subcategory":"Beauty Salon",
            "type":"Services"
        }
    ],
    "sg:phone":"+61 3 9850 5827",
    "sg:postcode":"3105",
    "sg:province":"VIC",
    "sg:tags":[
        "hairdresser"
    ],
    "wof:name":"Cutters Corner",
    "wof:placetype":"venue"
},
  "geometry": {"coordinates":[145.089477539,-37.7743721008],"type":"Point"}
}