{
  "type": "Feature",
  "properties": {
    "iso:country":"AU",
    "sg:address":"40 Renmark Ave",
    "sg:city":"Renmark",
    "sg:classifiers":[
        {
            "category":"Food & Beverages",
            "subcategory":"Bakery",
            "type":"Retail Goods"
        }
    ],
    "sg:phone":"+61 8 8586 6156",
    "sg:postcode":"5341",
    "sg:province":"SA",
    "sg:tags":[
        "cake",
        "shop",
        "pastry"
    ],
    "wof:name":"Renmark Patisserie",
    "wof:placetype":"venue"
},
  "geometry": {"coordinates":[140.741577148,-34.178653717],"type":"Point"}
}