{
  "type": "Feature",
  "properties": {
    "iso:country":"AU",
    "sg:address":"105 Dora St",
    "sg:city":"Morisset",
    "sg:classifiers":[
        {
            "category":"Food & Beverages",
            "subcategory":"Bakery",
            "type":"Retail Goods"
        }
    ],
    "sg:phone":"+61 2 4973 2470",
    "sg:postcode":"2264",
    "sg:province":"NSW",
    "sg:tags":[
        "baker"
    ],
    "wof:name":"Morisset Bakery",
    "wof:placetype":"venue"
},
  "geometry": {"coordinates":[151.48597699999999,-33.109554],"type":"Point"}
}