{
  "type": "Feature",
  "properties": {
    "iso:country":"AU",
    "sg:address":"19a Fernleigh St",
    "sg:city":"Newtown",
    "sg:classifiers":[
        {
            "category":"Commercial Area",
            "type":"Public Place"
        }
    ],
    "sg:phone":"+61 3 5223 2767",
    "sg:postcode":"3220",
    "sg:province":"VIC",
    "sg:tags":[
        "heavy",
        "carrier"
    ],
    "wof:name":"Transtex",
    "wof:placetype":"venue"
},
  "geometry": {"coordinates":[144.34773300000001,-38.161404],"type":"Point"}
}