{
  "type": "Feature",
  "properties": {
    "addr:full":"17 Elizabeth St Fennell Bay NSW 2283",
    "addr:housenumber":"17",
    "addr:postcode":"2283",
    "addr:street":"Elizabeth St",
    "iso:country":"AU",
    "sg:address":"17 Elizabeth St",
    "sg:city":"Fennell Bay",
    "sg:classifiers":[
        {
            "category":"Professional",
            "subcategory":"Detective & Security Services",
            "type":"Services"
        }
    ],
    "sg:phone":"+61 2 4959 7094",
    "sg:postcode":"2283",
    "sg:province":"NSW",
    "sg:tags":[
        "guard",
        "patrol"
    ],
    "wof:name":"Fennell Enterprises",
    "wof:placetype":"venue"
},
  "geometry": {"coordinates":[151.595535278,-32.9936790466],"type":"Point"}
}