{
  "type": "Feature",
  "properties": {
    "addr:full":"13 Toogood Ave Beverley SA 5009",
    "addr:housenumber":"13",
    "addr:postcode":"5009",
    "addr:street":"Toogood Ave Beverley",
    "iso:country":"AU",
    "sg:address":"13 Toogood Ave",
    "sg:city":"Beverley",
    "sg:classifiers":[
        {
            "category":"Shopping",
            "subcategory":"Crafts & Fabrics",
            "type":"Retail Goods"
        }
    ],
    "sg:phone":"+61 8 8268 2511",
    "sg:postcode":"5009",
    "sg:province":"SA",
    "sg:tags":[
        "adhesive"
    ],
    "wof:name":"Ardex Australia Pty Ltd",
    "wof:placetype":"venue"
},
  "geometry": {"coordinates":[138.54232788100001,-34.8986968994],"type":"Point"}
}