{
  "type": "Feature",
  "properties": {
    "iso:country":"AU",
    "sg:address":"316 Wingham Rd",
    "sg:city":"Taree",
    "sg:classifiers":[
        {
            "category":"Social Services",
            "subcategory":"Adult Care",
            "type":"Services"
        }
    ],
    "sg:phone":"+61 2 6551 4214",
    "sg:postcode":"2430",
    "sg:province":"NSW",
    "sg:tags":[
        "disadvantaged",
        "aid",
        "organisation",
        "group"
    ],
    "wof:name":"Dundaloo Foundation Ltd",
    "wof:placetype":"venue"
},
  "geometry": {"coordinates":[152.442719,-31.886581],"type":"Point"}
}