{
  "type": "Feature",
  "properties": {
    "addr:full":"4 Loton Pl Stirling ACT 2611",
    "addr:housenumber":"4",
    "addr:postcode":"2611",
    "addr:street":"Loton Pl",
    "iso:country":"AU",
    "sg:address":"4 Loton Pl",
    "sg:city":"Stirling",
    "sg:classifiers":[
        {
            "category":"Building & Trades",
            "subcategory":"Plumbing",
            "type":"Services"
        }
    ],
    "sg:phone":"+61 418 623 133",
    "sg:postcode":"2611",
    "sg:province":"ACT",
    "sg:tags":[
        "plumber",
        "gasfitters"
    ],
    "wof:name":"B & A Plumbing Maintenance Service",
    "wof:placetype":"venue"
},
  "geometry": {"coordinates":[149.05607605,-35.3463783264],"type":"Point"}
}