{
  "type": "Feature",
  "properties": {
    "iso:country":"AU",
    "sg:address":"32 Reading St",
    "sg:city":"Paddington",
    "sg:classifiers":[
        {
            "category":"Retail",
            "subcategory":"Veterinary Services",
            "type":"Services"
        }
    ],
    "sg:phone":"+61 7 3217 5434",
    "sg:postcode":"4064",
    "sg:province":"QLD",
    "sg:tags":[
        "surgeon"
    ],
    "wof:name":"Smith C",
    "wof:placetype":"venue"
},
  "geometry": {"coordinates":[152.991363525,-27.460609436],"type":"Point"}
}