{
  "type": "Feature",
  "properties": {
    "addr:full":"Shed 3 / 15 Caloundra Rd Caloundra QLD 4551",
    "addr:housenumber":"3 / 15",
    "addr:postcode":"4551",
    "addr:street":"Caloundra Rd",
    "iso:country":"AU",
    "sg:address":"Shed 3 / 15 Caloundra Rd",
    "sg:city":"Caloundra",
    "sg:classifiers":[
        {
            "category":"Wholesale",
            "subcategory":"Painting Supplies",
            "type":"Manufacturing & Wholesale Goods"
        }
    ],
    "sg:phone":"+61 7 5491 6044",
    "sg:postcode":"4551",
    "sg:province":"QLD",
    "sg:tags":[
        "painter"
    ],
    "wof:name":"Queensland Paint Makers Pty Ltd",
    "wof:placetype":"venue"
},
  "geometry": {"coordinates":[153.11358642600001,-26.798002243],"type":"Point"}
}