{
  "type": "Feature",
  "properties": {
    "addr:full":"46 St John St Launceston TAS 7250",
    "addr:housenumber":"46",
    "addr:postcode":"7250",
    "addr:street":"St John St",
    "iso:country":"AU",
    "sg:address":"46 St John St",
    "sg:city":"Launceston",
    "sg:classifiers":[
        {
            "category":"Real Estate",
            "subcategory":"Developer",
            "type":"Services"
        }
    ],
    "sg:phone":"+61 400 130 000",
    "sg:postcode":"7250",
    "sg:province":"TAS",
    "sg:tags":[
        "development"
    ],
    "wof:name":"Schouten Developments Pty Ltd",
    "wof:placetype":"venue"
},
  "geometry": {"coordinates":[147.13824462900001,-41.4367485046],"type":"Point"}
}