{
  "type": "Feature",
  "properties": {
    "iso:country":"AU",
    "sg:address":"57b Walter Rd",
    "sg:city":"Dianella",
    "sg:classifiers":[
        {
            "category":"Fast Food",
            "type":"Food & Drink"
        }
    ],
    "sg:phone":"+61 13 19 94",
    "sg:postcode":"6059",
    "sg:province":"WA",
    "sg:tags":[
        "away",
        "take"
    ],
    "wof:name":"Pizza Force",
    "wof:placetype":"venue"
},
  "geometry": {"coordinates":[115.93502807599999,-31.8946151733],"type":"Point"}
}