{
  "type": "Feature",
  "properties": {
    "addr:full":"6 Lanyon St Dandenong VIC 3175",
    "addr:housenumber":"6",
    "addr:postcode":"3175",
    "addr:street":"Lanyon St",
    "iso:country":"AU",
    "sg:address":"6 Lanyon St",
    "sg:city":"Dandenong",
    "sg:classifiers":[
        {
            "category":"Home & Garden",
            "subcategory":"Furniture",
            "type":"Retail Goods"
        }
    ],
    "sg:phone":"+61 3 9706 7699",
    "sg:postcode":"3175",
    "sg:province":"VIC",
    "sg:tags":[
        "outdoor"
    ],
    "wof:name":"Custom Fabrications Pty Ltd",
    "wof:placetype":"venue"
},
  "geometry": {"coordinates":[145.22174072300001,-38.0163574219],"type":"Point"}
}