{
  "type": "Feature",
  "properties": {
    "iso:country":"AU",
    "sg:address":"2 Vaughan Crs",
    "sg:city":"Kew",
    "sg:classifiers":[
        {
            "category":"Professional",
            "subcategory":"Computer Services",
            "type":"Services"
        }
    ],
    "sg:phone":"+61 412 128 812",
    "sg:postcode":"3101",
    "sg:province":"VIC",
    "sg:tags":[
        "package",
        "software"
    ],
    "wof:name":"Oak Technology Pty Ltd",
    "wof:placetype":"venue"
},
  "geometry": {"coordinates":[145.01083374000001,-37.8165245056],"type":"Point"}
}