{
  "type": "Feature",
  "properties": {
    "iso:country":"AU",
    "sg:address":"Cnr Lancelot & Edgar Sts",
    "sg:city":"Condell Park",
    "sg:classifiers":[
        {
            "category":"Autos & Motor Vehicles",
            "subcategory":"Fuel & Gas Station",
            "type":"Retail Goods"
        }
    ],
    "sg:phone":"+61 2 9709 3363",
    "sg:postcode":"2200",
    "sg:province":"NSW",
    "wof:name":"BP Australia Pty Ltd",
    "wof:placetype":"venue"
},
  "geometry": {"coordinates":[151.011932,-33.922077],"type":"Point"}
}