{
  "type": "Feature",
  "properties": {
    "addr:full":"1 Avoca St Highett VIC 3190",
    "addr:housenumber":"1",
    "addr:postcode":"3190",
    "addr:street":"Avoca St",
    "iso:country":"AU",
    "sg:address":"1 Avoca St",
    "sg:city":"Highett",
    "sg:classifiers":[
        {
            "category":"Professional",
            "subcategory":"Computer Services",
            "type":"Services"
        }
    ],
    "sg:phone":"+61 3 9553 4099",
    "sg:postcode":"3190",
    "sg:province":"VIC",
    "sg:tags":[
        "package",
        "software"
    ],
    "wof:name":"Megabus Pty Ltd",
    "wof:placetype":"venue"
},
  "geometry": {"coordinates":[145.03222656200001,-37.9545021057],"type":"Point"}
}