{
  "type": "Feature",
  "properties": {
    "addr:full":"Unit 1, 29 Annie St Coopers Plains QLD 4108",
    "addr:housenumber":"29",
    "addr:postcode":"4108",
    "addr:street":"Annie St",
    "iso:country":"AU",
    "sg:address":"Unit 1, 29 Annie St",
    "sg:city":"Coopers Plains",
    "sg:classifiers":[
        {
            "category":"Wholesale",
            "subcategory":"Machinery & Supplies",
            "type":"Manufacturing & Wholesale Goods"
        }
    ],
    "sg:phone":"+61 7 3277 3161",
    "sg:postcode":"4108",
    "sg:province":"QLD",
    "sg:tags":[
        "equipment",
        "welding"
    ],
    "wof:name":"Torchmaster",
    "wof:placetype":"venue"
},
  "geometry": {"coordinates":[153.03262329099999,-27.5650196075],"type":"Point"}
}