{
  "type": "Feature",
  "properties": {
    "iso:country":"AU",
    "sg:address":"PO Box 168",
    "sg:city":"Kellyville",
    "sg:classifiers":[
        {
            "category":"Real Estate",
            "subcategory":"Surveying",
            "type":"Services"
        }
    ],
    "sg:phone":"+61 431 925 832",
    "sg:postcode":"2153",
    "sg:province":"NSW",
    "sg:tags":[
        "building",
        "surveyor"
    ],
    "wof:name":"Sitepoint Building Certifiers",
    "wof:placetype":"venue"
},
  "geometry": {"coordinates":[150.97642517099999,-33.7541503906],"type":"Point"}
}