{
  "type": "Feature",
  "properties": {
    "iso:country":"AU",
    "sg:address":"PO Box 320",
    "sg:city":"Leederville",
    "sg:classifiers":[
        {
            "category":"Banks & Credit Unions",
            "subcategory":"Investment Brokerage",
            "type":"Services"
        }
    ],
    "sg:phone":"+61 8 9328 0999",
    "sg:postcode":"6903",
    "sg:province":"WA",
    "sg:tags":[
        "management",
        "property"
    ],
    "wof:name":"Realmark",
    "wof:placetype":"venue"
},
  "geometry": {"coordinates":[115.8412323,-31.9364795685],"type":"Point"}
}