{
  "type": "Feature",
  "properties": {
    "addr:full":"24 Arnold Ave Kellyville NSW 2155",
    "addr:housenumber":"24",
    "addr:postcode":"2155",
    "addr:street":"Arnold Ave",
    "iso:country":"AU",
    "sg:address":"24 Arnold Ave",
    "sg:city":"Kellyville",
    "sg:classifiers":[
        {
            "category":"Social Services",
            "subcategory":"Child Care",
            "type":"Services"
        }
    ],
    "sg:phone":"+61 2 9629 5499",
    "sg:postcode":"2155",
    "sg:province":"NSW",
    "sg:website":"http://www.childcare.com.au",
    "wof:name":"ABC Kellyville",
    "wof:placetype":"venue"
},
  "geometry": {"coordinates":[150.94143676799999,-33.714969635],"type":"Point"}
}