{
  "type": "Feature",
  "properties": {
    "addr:full":"Christine Cnr Shopping Cntr Varsity Lakes QLD 4226",
    "addr:postcode":"4226",
    "addr:street":"Christine;Shopping",
    "iso:country":"AU",
    "sg:address":"Christine Cnr Shopping Cntr",
    "sg:city":"Varsity Lakes",
    "sg:classifiers":[
        {
            "category":"Personal",
            "subcategory":"Beauty Salon",
            "type":"Services"
        }
    ],
    "sg:phone":"+61 7 5520 1122",
    "sg:postcode":"4226",
    "sg:province":"QLD",
    "sg:tags":[
        "hairdresser"
    ],
    "wof:name":"Shapes Hair By Debbie",
    "wof:placetype":"venue"
},
  "geometry": {"coordinates":[153.38667297399999,-28.0812683105],"type":"Point"}
}