{
  "type": "Feature",
  "properties": {
    "iso:country":"AU",
    "sg:address":"138 Pirates Bay Drv",
    "sg:city":"Eaglehawk Neck",
    "sg:classifiers":[
        {
            "category":"Building & Trades",
            "subcategory":"Construction",
            "type":"Services"
        }
    ],
    "sg:phone":"+61 3 6250 3274",
    "sg:postcode":"7179",
    "sg:province":"TAS",
    "sg:tags":[
        "earth",
        "excavating",
        "moving",
        "contractor"
    ],
    "wof:name":"Mison Diverse Fishing",
    "wof:placetype":"venue"
},
  "geometry": {"coordinates":[147.929885864,-42.9961700439],"type":"Point"}
}