{
  "type": "Feature",
  "properties": {
    "addr:full":"12 Avlona St Mordialloc VIC 3195",
    "addr:housenumber":"12",
    "addr:postcode":"3195",
    "addr:street":"Avlona St",
    "iso:country":"AU",
    "sg:address":"12 Avlona St",
    "sg:city":"Mordialloc",
    "sg:classifiers":[
        {
            "category":"Shopping",
            "subcategory":"Stationery & Office Supplies",
            "type":"Retail Goods"
        }
    ],
    "sg:phone":"+61 3 9587 8600",
    "sg:postcode":"3195",
    "sg:province":"VIC",
    "sg:tags":[
        "packaging",
        "equipment",
        "sealing",
        "filling"
    ],
    "wof:name":"Australian Filling & Packaging Machines Pty Ltd",
    "wof:placetype":"venue"
},
  "geometry": {"coordinates":[145.096633911,-38.0072631836],"type":"Point"}
}