{
  "type": "Feature",
  "properties": {
    "addr:full":"Shop 70 Pines Shopping Centre Elanora QLD 4221",
    "addr:housenumber":"shop 70",
    "addr:postcode":"4221",
    "iso:country":"AU",
    "sg:address":"Shop 70 Pines Shopping Centre",
    "sg:city":"Elanora",
    "sg:classifiers":[
        {
            "category":"Communications",
            "subcategory":"Film & Video Production",
            "type":"Services"
        }
    ],
    "sg:phone":"+61 7 5598 2331",
    "sg:postcode":"4221",
    "sg:province":"QLD",
    "sg:tags":[
        "dvd",
        "library"
    ],
    "wof:name":"Video Ezy",
    "wof:placetype":"venue"
},
  "geometry": {"coordinates":[153.46052551299999,-28.1234397888],"type":"Point"}
}