{
  "type": "Feature",
  "properties": {
    "addr:full":"19 Hansen Rd Seville Grove WA 6112",
    "addr:housenumber":"19",
    "addr:postcode":"6112",
    "addr:street":"Hansen Rd",
    "iso:country":"AU",
    "sg:address":"19 Hansen Rd",
    "sg:city":"Seville Grove",
    "sg:classifiers":[
        {
            "category":"Home & Garden",
            "subcategory":"Building Materials",
            "type":"Retail Goods"
        }
    ],
    "sg:phone":"+61 404 164 613",
    "sg:postcode":"6112",
    "sg:province":"WA",
    "sg:tags":[
        "lawn",
        "cutting",
        "maintenance"
    ],
    "wof:name":"Seville Mowing",
    "wof:placetype":"venue"
},
  "geometry": {"coordinates":[115.98200225799999,-32.1392402649],"type":"Point"}
}