{
  "type": "Feature",
  "properties": {
    "addr:full":"256 Belmore Rd Riverwood NSW 2210",
    "addr:housenumber":"256",
    "addr:postcode":"2210",
    "addr:street":"Belmore Rd",
    "iso:country":"AU",
    "sg:address":"256 Belmore Rd",
    "sg:city":"Riverwood",
    "sg:classifiers":[
        {
            "category":"Food & Beverages",
            "subcategory":"Bakery",
            "type":"Retail Goods"
        }
    ],
    "sg:phone":"+61 2 9533 7226",
    "sg:postcode":"2210",
    "sg:province":"NSW",
    "sg:tags":[
        "baker"
    ],
    "wof:name":"Harmouche Lebanese Bakery",
    "wof:placetype":"venue"
},
  "geometry": {"coordinates":[151.052582,-33.950089],"type":"Point"}
}