{
  "type": "Feature",
  "properties": {
    "addr:full":"McDonald St Morwell VIC 3840",
    "addr:postcode":"3840",
    "addr:street":"Mcdonald St",
    "iso:country":"AU",
    "sg:address":"McDonald St",
    "sg:city":"Morwell",
    "sg:classifiers":[
        {
            "category":"Education",
            "subcategory":"School",
            "type":"Public Place"
        }
    ],
    "sg:phone":"+61 3 5134 2054",
    "sg:postcode":"3840",
    "sg:province":"VIC",
    "sg:tags":[
        "state",
        "except",
        "nsw"
    ],
    "wof:name":"The Victorian P-12 College Koorie Education Woolum Bellum Campus",
    "wof:placetype":"venue"
},
  "geometry": {"coordinates":[146.404754639,-38.2384796143],"type":"Point"}
}