{
  "type": "Feature",
  "properties": {
    "addr:full":"3/372- 388 Anzac Pde Kingsford NSW 2032",
    "addr:housenumber":"/ 372 388",
    "addr:postcode":"2032",
    "addr:street":"Anzac Pde",
    "iso:country":"AU",
    "sg:address":"3/372- 388 Anzac Pde",
    "sg:city":"Kingsford",
    "sg:classifiers":[
        {
            "category":"Professional",
            "subcategory":"Accounting & Tax Preparation",
            "type":"Services"
        }
    ],
    "sg:phone":"+61 2 9663 3886",
    "sg:postcode":"2032",
    "sg:province":"NSW",
    "sg:tags":[
        "consultant",
        "taxation"
    ],
    "wof:name":"Stavrou William & Co",
    "wof:placetype":"venue"
},
  "geometry": {"coordinates":[151.22671508799999,-33.9200820923],"type":"Point"}
}