{
  "type": "Feature",
  "properties": {
    "iso:country":"AU",
    "sg:address":"Gp Surgery 567 Lower North East Rd",
    "sg:city":"Campbelltown",
    "sg:classifiers":[
        {
            "category":"Health Services",
            "subcategory":"Doctor",
            "type":"Services"
        }
    ],
    "sg:phone":"+61 8 8337 1849",
    "sg:postcode":"5074",
    "sg:province":"SA",
    "sg:tags":[
        "medical",
        "practitioner"
    ],
    "wof:name":"Caruso John Dr",
    "wof:placetype":"venue"
},
  "geometry": {"coordinates":[138.66177368199999,-34.8807830811],"type":"Point"}
}