{
  "type": "Feature",
  "properties": {
    "addr:full":"560 Olsen Ave Southport QLD 4215",
    "addr:housenumber":"560",
    "addr:postcode":"4215",
    "addr:street":"Olsen Ave",
    "iso:country":"AU",
    "sg:address":"560 Olsen Ave",
    "sg:city":"Southport",
    "sg:classifiers":[
        {
            "category":"Banks & Credit Unions",
            "subcategory":"Bank",
            "type":"Services"
        }
    ],
    "sg:phone":"+61 7 5501 1914",
    "sg:postcode":"4215",
    "sg:province":"QLD",
    "sg:tags":[
        "concrete",
        "reinforcement"
    ],
    "wof:name":"Welded Mesh",
    "wof:placetype":"venue"
},
  "geometry": {"coordinates":[153.38311767600001,-27.9547042847],"type":"Point"}
}