{
  "type": "Feature",
  "properties": {
    "iso:country":"AU",
    "sg:address":"Unit 2/ 35 Tacoma Cct",
    "sg:city":"Canning Vale",
    "sg:classifiers":[
        {
            "category":"Manufacturing",
            "subcategory":"Rubber & Plastics",
            "type":"Manufacturing & Wholesale Goods"
        }
    ],
    "sg:phone":"+61 8 9256 2011",
    "sg:postcode":"6155",
    "sg:province":"WA",
    "sg:tags":[
        "wholesaler",
        "product",
        "mfrs"
    ],
    "wof:name":"Mainline Plastics",
    "wof:placetype":"venue"
},
  "geometry": {"coordinates":[115.924171,-32.06366],"type":"Point"}
}