{
  "type": "Feature",
  "properties": {
    "addr:full":"276b Johnston St Annandale NSW 2038",
    "addr:housenumber":"276b",
    "addr:postcode":"2038",
    "addr:street":"Johnston St",
    "iso:country":"AU",
    "sg:address":"276b Johnston St",
    "sg:city":"Annandale",
    "sg:classifiers":[
        {
            "category":"Health Services",
            "subcategory":"Health Practitioner",
            "type":"Services"
        }
    ],
    "sg:phone":"+61 2 9555 1374",
    "sg:postcode":"2038",
    "sg:province":"NSW",
    "sg:tags":[
        "alternative"
    ],
    "wof:name":"Feldenkrais Method",
    "wof:placetype":"venue"
},
  "geometry": {"coordinates":[151.17381286599999,-33.8741073608],"type":"Point"}
}