{
  "type": "Feature",
  "properties": {
    "addr:full":"115 Mulyan St Como NSW 2226",
    "addr:housenumber":"115",
    "addr:postcode":"2226",
    "addr:street":"Mulyan St",
    "iso:country":"AU",
    "sg:address":"115 Mulyan St",
    "sg:city":"Como",
    "sg:classifiers":[
        {
            "category":"Shopping",
            "subcategory":"Baby Store",
            "type":"Retail Goods"
        }
    ],
    "sg:phone":"+61 407 928 691",
    "sg:postcode":"2226",
    "sg:province":"NSW",
    "sg:tags":[
        "wear"
    ],
    "wof:name":"Cheeky Chops Bibs for Kids",
    "wof:placetype":"venue"
},
  "geometry": {"coordinates":[151.06262207,-34.0081596375],"type":"Point"}
}