{
  "type": "Feature",
  "properties": {
    "addr:full":"Rear 70 Jersey St Jolimont WA 6014",
    "addr:housenumber":"70",
    "addr:postcode":"6014",
    "addr:street":"Jersey St",
    "iso:country":"AU",
    "sg:address":"Rear 70 Jersey St",
    "sg:city":"Jolimont",
    "sg:classifiers":[
        {
            "category":"Shopping",
            "type":"Retail Goods"
        }
    ],
    "sg:phone":"+61 8 9284 1000",
    "sg:postcode":"6014",
    "sg:province":"WA",
    "sg:tags":[
        "new age",
        "product"
    ],
    "wof:name":"Edwards Book Agencies",
    "wof:placetype":"venue"
},
  "geometry": {"coordinates":[115.81175231900001,-31.945482254],"type":"Point"}
}