{
  "type": "Feature",
  "properties": {
    "iso:country":"AU",
    "sg:address":"76 Watson St",
    "sg:city":"Bundaberg",
    "sg:classifiers":[
        {
            "category":"Building & Trades",
            "subcategory":"Construction",
            "type":"Services"
        }
    ],
    "sg:phone":"+61 7 4151 3972",
    "sg:postcode":"4670",
    "sg:province":"QLD",
    "sg:tags":[
        "joinery"
    ],
    "wof:name":"Richters Joinery",
    "wof:placetype":"venue"
},
  "geometry": {"coordinates":[152.35072326700001,-24.8782272339],"type":"Point"}
}