{
  "type": "Feature",
  "properties": {
    "addr:full":"478 Beach Rd Beaumaris VIC 3193",
    "addr:housenumber":"478",
    "addr:postcode":"3193",
    "addr:street":"Beach Rd",
    "iso:country":"AU",
    "sg:address":"478 Beach Rd",
    "sg:city":"Beaumaris",
    "sg:classifiers":[
        {
            "category":"Professional",
            "subcategory":"Business Services",
            "type":"Services"
        }
    ],
    "sg:phone":"+61 418 538 886",
    "sg:postcode":"3193",
    "sg:province":"VIC",
    "sg:tags":[
        "drafting"
    ],
    "wof:name":"Crowhurst Building Design",
    "wof:placetype":"venue"
},
  "geometry": {"coordinates":[145.043045044,-37.9902954102],"type":"Point"}
}