{
  "type": "Feature",
  "properties": {
    "addr:full":"Plaza 85 Prospect Road Prospect SA 5082",
    "addr:housenumber":"85",
    "addr:postcode":"5082",
    "addr:street":"Prospect Road",
    "iso:country":"AU",
    "sg:address":"Plaza 85 Prospect Road",
    "sg:city":"Prospect",
    "sg:classifiers":[
        {
            "category":"Food & Beverages",
            "subcategory":"Supermarket",
            "type":"Retail Goods"
        }
    ],
    "sg:phone":"+61 8 8344 6746",
    "sg:postcode":"5082",
    "sg:province":"SA",
    "sg:tags":[
        "grocery",
        "store"
    ],
    "wof:name":"Foodland Supermarkets",
    "wof:placetype":"venue"
},
  "geometry": {"coordinates":[138.59425354000001,-34.8879241943],"type":"Point"}
}