{
  "type": "Feature",
  "properties": {
    "addr:full":"Meyer Ave Wangan QLD 4871",
    "addr:postcode":"4871",
    "addr:street":"Meyer Ave",
    "iso:country":"AU",
    "sg:address":"Meyer Ave",
    "sg:city":"Wangan",
    "sg:classifiers":[
        {
            "category":"Travel",
            "subcategory":"Hotels & Motels",
            "type":"Entertainment"
        }
    ],
    "sg:phone":"+61 7 4064 2336",
    "sg:postcode":"4871",
    "sg:province":"QLD",
    "sg:tags":[
        "accommodation"
    ],
    "wof:name":"Currajah Hotel",
    "wof:placetype":"venue"
},
  "geometry": {"coordinates":[146.00955200199999,-17.5766067505],"type":"Point"}
}