{
  "type": "Feature",
  "properties": {
    "addr:full":"144- 146 Union Rd Surrey Hills VIC 3127",
    "addr:housenumber":"146",
    "addr:postcode":"3127",
    "addr:street":"Union Rd",
    "iso:country":"AU",
    "sg:address":"144- 146 Union Rd",
    "sg:city":"Surrey Hills",
    "sg:classifiers":[
        {
            "category":"Health Services",
            "subcategory":"Health Practitioner",
            "type":"Services"
        }
    ],
    "sg:phone":"+61 3 9888 6862",
    "sg:postcode":"3127",
    "sg:province":"VIC",
    "sg:tags":[
        "psychologist"
    ],
    "wof:name":"Malangre Kate",
    "wof:placetype":"venue"
},
  "geometry": {"coordinates":[145.09751892099999,-37.823600769],"type":"Point"}
}