{
  "type": "Feature",
  "properties": {
    "addr:full":"146a High St Ashburton VIC 3147",
    "addr:housenumber":"146a",
    "addr:postcode":"3147",
    "addr:street":"High St",
    "iso:country":"AU",
    "sg:address":"146a High St",
    "sg:city":"Ashburton",
    "sg:classifiers":[
        {
            "category":"Health Services",
            "subcategory":"Doctor",
            "type":"Services"
        }
    ],
    "sg:phone":"+61 3 9885 1869",
    "sg:postcode":"3147",
    "sg:province":"VIC",
    "sg:tags":[
        "medical",
        "practitioner"
    ],
    "wof:name":"Copland Dr. Colin Russell",
    "wof:placetype":"venue"
},
  "geometry": {"coordinates":[145.07565307600001,-37.8630523682],"type":"Point"}
}