{
  "type": "Feature",
  "properties": {
    "addr:full":"Shp2/ 10 Drayton St Dalby QLD 4405",
    "addr:housenumber":"10",
    "addr:postcode":"4405",
    "addr:street":"Drayton St",
    "iso:country":"AU",
    "sg:address":"Shp2/ 10 Drayton St",
    "sg:city":"Dalby",
    "sg:classifiers":[
        {
            "category":"Recreation",
            "subcategory":"Fishing",
            "type":"Entertainment"
        }
    ],
    "sg:phone":"+61 7 4662 3773",
    "sg:postcode":"4405",
    "sg:province":"QLD",
    "sg:tags":[
        "tackle"
    ],
    "wof:name":"Bass To Barra Marine Dalby",
    "wof:placetype":"venue"
},
  "geometry": {"coordinates":[151.25907898,-27.1793613434],"type":"Point"}
}