{
  "type": "Feature",
  "properties": {
    "addr:full":"Unit 1/ 1 Edmondstone St Newstead QLD 4006",
    "addr:postcode":"4006",
    "addr:street":"Edmondstone St",
    "iso:country":"AU",
    "sg:address":"Unit 1/ 1 Edmondstone St",
    "sg:city":"Newstead",
    "sg:classifiers":[
        {
            "category":"Professional",
            "subcategory":"Detective & Security Services",
            "type":"Services"
        }
    ],
    "sg:phone":"+61 1300 305 945",
    "sg:postcode":"4006",
    "sg:province":"QLD",
    "sg:tags":[
        "consultant",
        "system"
    ],
    "wof:name":"Securecam",
    "wof:placetype":"venue"
},
  "geometry": {"coordinates":[153.01698303200001,-27.43816185],"type":"Point"}
}