{
  "type": "Feature",
  "properties": {
    "iso:country":"AU",
    "sg:address":"Rohs Rd",
    "sg:city":"Bendigo",
    "sg:classifiers":[
        {
            "category":"Home & Garden",
            "subcategory":"Garden Supply",
            "type":"Retail Goods"
        }
    ],
    "sg:phone":"+61 3 5444 4285",
    "sg:postcode":"3550",
    "sg:province":"VIC",
    "sg:tags":[
        "statuary",
        "fountains",
        "sundial"
    ],
    "wof:name":"Concrete Creations",
    "wof:placetype":"venue"
},
  "geometry": {"coordinates":[144.31112670900001,-36.7469711304],"type":"Point"}
}