{
  "type": "Feature",
  "properties": {
    "addr:full":"201 East Boundary Rd Bentleigh East VIC 3165",
    "addr:housenumber":"201",
    "addr:postcode":"3165",
    "addr:street":"East Boundary Rd",
    "iso:country":"AU",
    "sg:address":"201 East Boundary Rd",
    "sg:city":"Bentleigh East",
    "sg:classifiers":[
        {
            "category":"Health Services",
            "subcategory":"Health Practitioner",
            "type":"Services"
        }
    ],
    "sg:phone":"+61 409 294 150",
    "sg:postcode":"3165",
    "sg:province":"VIC",
    "sg:tags":[
        "psychologist"
    ],
    "wof:name":"Ian Woodhouse",
    "wof:placetype":"venue"
},
  "geometry": {"coordinates":[145.05937194800001,-37.9183578491],"type":"Point"}
}