{
  "type": "Feature",
  "properties": {
    "iso:country":"AU",
    "sg:address":"23 Crescent St",
    "sg:city":"Granville",
    "sg:classifiers":[
        {
            "category":"Professional",
            "subcategory":"Engineering",
            "type":"Services"
        }
    ],
    "sg:phone":"+61 2 9682 5233",
    "sg:postcode":"2142",
    "sg:province":"NSW",
    "sg:tags":[
        "engineer"
    ],
    "wof:name":"Vic James & Sons Engineering Pty Ltd",
    "wof:placetype":"venue"
},
  "geometry": {"coordinates":[151.003082275,-33.8290939331],"type":"Point"}
}