{
  "type": "Feature",
  "properties": {
    "iso:country":"AU",
    "sg:address":"Morgan St",
    "sg:city":"Ravensthorpe",
    "sg:classifiers":[
        {
            "category":"Autos & Motor Vehicles",
            "subcategory":"Fuel & Gas Station",
            "type":"Retail Goods"
        }
    ],
    "sg:phone":"+61 8 9838 1047",
    "sg:postcode":"6346",
    "sg:province":"WA",
    "wof:name":"BP Australia Limited",
    "wof:placetype":"venue"
},
  "geometry": {"coordinates":[120.045776,-33.58176],"type":"Point"}
}