{
  "type": "Feature",
  "properties": {
    "iso:country":"AU",
    "sg:address":"159 Davey St",
    "sg:city":"Hobart",
    "sg:classifiers":[
        {
            "category":"Professional",
            "subcategory":"Testing Lab",
            "type":"Services"
        }
    ],
    "sg:phone":"+61 3 6223 8877",
    "sg:postcode":"7000",
    "sg:province":"TAS",
    "sg:tags":[
        "soil",
        "investigation"
    ],
    "wof:name":"Gandy & Roberts Pty Ltd",
    "wof:placetype":"venue"
},
  "geometry": {"coordinates":[147.321655273,-42.8905220032],"type":"Point"}
}