{
  "type": "Feature",
  "properties": {
    "iso:country":"AU",
    "sg:address":"20 Minnie St",
    "sg:city":"Belmore",
    "sg:classifiers":[
        {
            "category":"Shopping",
            "subcategory":"Pets & Pet Supplies",
            "type":"Retail Goods"
        }
    ],
    "sg:phone":"+61 2 9029 9385",
    "sg:postcode":"2192",
    "sg:province":"NSW",
    "sg:tags":[
        "shop",
        "supplier"
    ],
    "wof:name":"Ezypets",
    "wof:placetype":"venue"
},
  "geometry": {"coordinates":[151.077988,-33.908638],"type":"Point"}
}