{
  "type": "Feature",
  "properties": {
    "addr:full":"6/ 63 Mitchell St Bondi Beach NSW 2026",
    "addr:housenumber":"/ 63",
    "addr:postcode":"2026",
    "addr:street":"Mitchell St",
    "iso:country":"AU",
    "sg:address":"6/ 63 Mitchell St",
    "sg:city":"Bondi Beach",
    "sg:classifiers":[
        {
            "category":"Professional",
            "subcategory":"Art Services",
            "type":"Services"
        }
    ],
    "sg:phone":"+61 410 600 627",
    "sg:postcode":"2026",
    "sg:province":"NSW",
    "sg:tags":[
        "arranger",
        "music",
        "composer"
    ],
    "wof:name":"Soulsonic",
    "wof:placetype":"venue"
},
  "geometry": {"coordinates":[151.27557373100001,-33.8867912292],"type":"Point"}
}