{
  "type": "Feature",
  "properties": {
    "iso:country":"AU",
    "sg:address":"459 Bownds St",
    "sg:city":"Lavington",
    "sg:classifiers":[
        {
            "category":"Building & Trades",
            "subcategory":"Plumbing",
            "type":"Services"
        }
    ],
    "sg:phone":"+61 2 6025 3960",
    "sg:postcode":"2641",
    "sg:province":"NSW",
    "sg:tags":[
        "plumber",
        "gasfitters"
    ],
    "wof:name":"Dave Tanner Plumbing",
    "wof:placetype":"venue"
},
  "geometry": {"coordinates":[146.931762695,-36.0414047241],"type":"Point"}
}