{
  "type": "Feature",
  "properties": {
    "addr:full":"Shp3/ 25 Sunshine Beach Rd Noosa Heads QLD 4567",
    "addr:postcode":"4567",
    "addr:street":"Sunshine Beach Rd",
    "iso:country":"AU",
    "sg:address":"Shp3/ 25 Sunshine Beach Rd",
    "sg:city":"Noosa Heads",
    "sg:classifiers":[
        {
            "category":"Shopping",
            "subcategory":"Clothing, Apparel, & Fashions",
            "type":"Retail Goods"
        }
    ],
    "sg:phone":"+61 7 5449 2377",
    "sg:postcode":"4567",
    "sg:province":"QLD",
    "sg:tags":[
        "accessory"
    ],
    "wof:name":"I Cherry Shoe",
    "wof:placetype":"venue"
},
  "geometry": {"coordinates":[153.09243774399999,-26.3988246918],"type":"Point"}
}