{
  "type": "Feature",
  "properties": {
    "addr:full":"1 Farnham Rd Dennington VIC 3280",
    "addr:housenumber":"1",
    "addr:postcode":"3280",
    "addr:street":"Farnham Rd",
    "iso:country":"AU",
    "sg:address":"1 Farnham Rd",
    "sg:city":"Dennington",
    "sg:classifiers":[
        {
            "category":"Building & Trades",
            "subcategory":"Landscaping Services",
            "type":"Services"
        }
    ],
    "sg:phone":"+61 427 336 583",
    "sg:postcode":"3280",
    "sg:province":"VIC",
    "sg:tags":[
        "consultant"
    ],
    "wof:name":"South West Building Approvals",
    "wof:placetype":"venue"
},
  "geometry": {"coordinates":[142.430908203,-38.352016449],"type":"Point"}
}