{
  "type": "Feature",
  "properties": {
    "addr:full":"Cnr River Side Drive & Jane St West End QLD 4101",
    "addr:postcode":"4101",
    "addr:street":"Cnr River Side Drive & Jane St",
    "iso:country":"AU",
    "sg:address":"Cnr River Side Drive & Jane St",
    "sg:city":"West End",
    "sg:classifiers":[
        {
            "category":"Professional",
            "subcategory":"Employment Agencies",
            "type":"Services"
        }
    ],
    "sg:phone":"+61 7 3013 6292",
    "sg:postcode":"4101",
    "sg:province":"QLD",
    "sg:tags":[
        "consultant",
        "casting"
    ],
    "wof:name":"People Management",
    "wof:placetype":"venue"
},
  "geometry": {"coordinates":[153.012008667,-27.4791297913],"type":"Point"}
}