{
  "type": "Feature",
  "properties": {
    "addr:full":"PO Box 851 Byron Bay NSW 2481",
    "addr:postcode":"2481",
    "iso:country":"AU",
    "sg:address":"PO Box 851",
    "sg:city":"Byron Bay",
    "sg:classifiers":[
        {
            "category":"Recreation",
            "type":"Entertainment"
        }
    ],
    "sg:phone":"+61 2 6684 7390",
    "sg:postcode":"2481",
    "sg:province":"NSW",
    "sg:tags":[
        "supply",
        "outdoor",
        "adventure",
        "activity"
    ],
    "wof:name":"Rusty Miller Personalised Surfing Instruction",
    "wof:placetype":"venue"
},
  "geometry": {"coordinates":[153.612823486,-28.6468906403],"type":"Point"}
}