{
  "type": "Feature",
  "properties": {
    "iso:country":"AU",
    "sg:address":"195 Townsend Rd",
    "sg:city":"Moolap",
    "sg:classifiers":[
        {
            "category":"Commercial Area",
            "type":"Public Place"
        }
    ],
    "sg:phone":"+61 3 5248 6328",
    "sg:postcode":"3221",
    "sg:province":"VIC",
    "sg:tags":[
        "heavy",
        "carrier"
    ],
    "wof:name":"Brennan G P & H",
    "wof:placetype":"venue"
},
  "geometry": {"coordinates":[144.402893,-38.182583],"type":"Point"}
}