{
  "type": "Feature",
  "properties": {
    "addr:full":"21 Stephen St Yarraville VIC 3013",
    "addr:housenumber":"21",
    "addr:postcode":"3013",
    "addr:street":"Stephen St",
    "iso:country":"AU",
    "sg:address":"21 Stephen St",
    "sg:city":"Yarraville",
    "sg:classifiers":[
        {
            "category":"Professional",
            "subcategory":"Management & Consulting",
            "type":"Services"
        }
    ],
    "sg:phone":"+61 3 9687 1093",
    "sg:postcode":"3013",
    "sg:province":"VIC",
    "sg:tags":[
        "consultant"
    ],
    "wof:name":"J G Human Resources Consulting",
    "wof:placetype":"venue"
},
  "geometry": {"coordinates":[144.89556884800001,-37.8110198975],"type":"Point"}
}