{
  "type": "Feature",
  "properties": {
    "iso:country":"AU",
    "sg:address":"678 High St",
    "sg:city":"Glen Waverley",
    "sg:classifiers":[
        {
            "category":"Government",
            "subcategory":"Fire Station",
            "type":"Public Place"
        }
    ],
    "sg:phone":"+61 3 9886 8136",
    "sg:postcode":"3150",
    "sg:province":"VIC",
    "sg:tags":[
        "spring",
        "shock",
        "absorbers",
        "suspension"
    ],
    "wof:name":"Mr Muffler Shockers",
    "wof:placetype":"venue"
},
  "geometry": {"coordinates":[145.15838623100001,-37.8734931946],"type":"Point"}
}