{
  "type": "Feature",
  "properties": {
    "iso:country":"AU",
    "sg:address":"Suite 5, 999 Lower North East Rd",
    "sg:city":"Highbury",
    "sg:classifiers":[
        {
            "category":"Banks & Credit Unions",
            "subcategory":"Bank",
            "type":"Services"
        }
    ],
    "sg:phone":"+61 8 8395 5668",
    "sg:postcode":"5089",
    "sg:province":"SA",
    "sg:tags":[
        "broker",
        "mortgage"
    ],
    "wof:name":"Sapphire Mortgage Dynamics",
    "wof:placetype":"venue"
},
  "geometry": {"coordinates":[138.71498107900001,-34.8497009277],"type":"Point"}
}