{
  "type": "Feature",
  "properties": {
    "addr:full":"Suite 1, Pulteney Arcade, Pulteney St Taree NSW 2430",
    "addr:postcode":"2430",
    "addr:street":"Pulteney Arcade Pulteney St",
    "iso:country":"AU",
    "sg:address":"Suite 1, Pulteney Arcade, Pulteney St",
    "sg:city":"Taree",
    "sg:classifiers":[
        {
            "category":"Professional",
            "subcategory":"Employment Agencies",
            "type":"Services"
        }
    ],
    "sg:phone":"+61 2 6551 3800",
    "sg:postcode":"2430",
    "sg:province":"NSW",
    "wof:name":"H & H Accredited Training",
    "wof:placetype":"venue"
},
  "geometry": {"coordinates":[152.460205,-31.91452],"type":"Point"}
}