{
  "type": "Feature",
  "properties": {
    "iso:country":"AU",
    "sg:address":"14 / 10 Victoria Ave",
    "sg:city":"Castle Hill",
    "sg:classifiers":[
        {
            "category":"Banks & Credit Unions",
            "subcategory":"Financial Services",
            "type":"Services"
        }
    ],
    "sg:phone":"+61 1300 362 770",
    "sg:postcode":"2154",
    "sg:province":"NSW",
    "sg:tags":[
        "equipment",
        "chain"
    ],
    "wof:name":"Miller Chains Australia Pty Ltd",
    "wof:placetype":"venue"
},
  "geometry": {"coordinates":[150.979125977,-33.7300338745],"type":"Point"}
}