{
  "type": "Feature",
  "properties": {
    "addr:full":"Un 9, 210 Winton Rd Joondalup WA 6027",
    "addr:housenumber":"210",
    "addr:postcode":"6027",
    "addr:street":"Winton Rd",
    "iso:country":"AU",
    "sg:address":"Un 9, 210 Winton Rd",
    "sg:city":"Joondalup",
    "sg:classifiers":[
        {
            "category":"Farming",
            "subcategory":"Fish & Marine Products",
            "type":"Manufacturing & Wholesale Goods"
        }
    ],
    "sg:phone":"+61 8 9300 1557",
    "sg:postcode":"6027",
    "sg:province":"WA",
    "sg:tags":[
        "chemical",
        "supplier"
    ],
    "wof:name":"Polymer Technologies",
    "wof:placetype":"venue"
},
  "geometry": {"coordinates":[115.763931274,-31.7489376068],"type":"Point"}
}