{
  "type": "Feature",
  "properties": {
    "addr:full":"207 Yarra St Warrandyte VIC 3113",
    "addr:housenumber":"207",
    "addr:postcode":"3113",
    "addr:street":"Yarra St",
    "iso:country":"AU",
    "sg:address":"207 Yarra St",
    "sg:city":"Warrandyte",
    "sg:classifiers":[
        {
            "category":"Shopping",
            "subcategory":"Antiques",
            "type":"Retail Goods"
        }
    ],
    "sg:phone":"+61 3 9844 4207",
    "sg:postcode":"3113",
    "sg:province":"VIC",
    "wof:name":"Ratty & Moles Riverbank Antiques",
    "wof:placetype":"venue"
},
  "geometry": {"coordinates":[145.22137451200001,-37.7367477417],"type":"Point"}
}