{
  "type": "Feature",
  "properties": {
    "iso:country":"AU",
    "sg:address":"Unit 10/7- 9 Kent Rd",
    "sg:city":"Mascot",
    "sg:classifiers":[
        {
            "category":"Retail",
            "subcategory":"Storage",
            "type":"Services"
        }
    ],
    "sg:phone":"+61 2 9317 0900",
    "sg:postcode":"2020",
    "sg:province":"NSW",
    "wof:name":"File Pty Limited",
    "wof:placetype":"venue"
},
  "geometry": {"coordinates":[151.18438720699999,-33.9221687317],"type":"Point"}
}