{
  "type": "Feature",
  "properties": {
    "iso:country":"AU",
    "sg:address":"7 Gascoyne St",
    "sg:city":"Albion Park",
    "sg:classifiers":[
        {
            "category":"Building & Trades",
            "subcategory":"Construction",
            "type":"Services"
        }
    ],
    "sg:phone":"+61 408 425 864",
    "sg:postcode":"2527",
    "sg:province":"NSW",
    "sg:tags":[
        "roof"
    ],
    "wof:name":"Shep's Roofing Service",
    "wof:placetype":"venue"
},
  "geometry": {"coordinates":[150.78239440900001,-34.590877533],"type":"Point"}
}