{
  "type": "Feature",
  "properties": {
    "addr:full":"9 Barrack St Hobart TAS 7000",
    "addr:housenumber":"9",
    "addr:postcode":"7000",
    "addr:street":"Barrack St",
    "iso:country":"AU",
    "sg:address":"9 Barrack St",
    "sg:city":"Hobart",
    "sg:classifiers":[
        {
            "category":"Personal",
            "subcategory":"Beauty Salon",
            "type":"Services"
        }
    ],
    "sg:phone":"+61 3 6223 3444",
    "sg:postcode":"7000",
    "sg:province":"TAS",
    "sg:tags":[
        "hairdresser"
    ],
    "wof:name":"Perry Hair",
    "wof:placetype":"venue"
},
  "geometry": {"coordinates":[147.32485961899999,-42.8870773315],"type":"Point"}
}