{
  "type": "Feature",
  "properties": {
    "iso:country":"AU",
    "sg:address":"8 Nigella Drv",
    "sg:city":"Point Cook",
    "sg:classifiers":[
        {
            "category":"Professional",
            "type":"Services"
        }
    ],
    "sg:phone":"+61 3 9395 5620",
    "sg:postcode":"3030",
    "sg:province":"VIC",
    "sg:tags":[
        "transport"
    ],
    "wof:name":"Sanmar Consulting Group",
    "wof:placetype":"venue"
},
  "geometry": {"coordinates":[144.73683199999999,-37.888397],"type":"Point"}
}