{
  "type": "Feature",
  "properties": {
    "addr:full":"66 Pacific Hwy St Leonards NSW 2065",
    "addr:housenumber":"66",
    "addr:postcode":"2065",
    "addr:street":"Pacific Hwy",
    "iso:country":"AU",
    "sg:address":"66 Pacific Hwy St",
    "sg:city":"Leonards",
    "sg:classifiers":[
        {
            "category":"Health Services",
            "subcategory":"Health Practitioner",
            "type":"Services"
        }
    ],
    "sg:phone":"+61 2 9439 9360",
    "sg:postcode":"2065",
    "sg:province":"NSW",
    "sg:tags":[
        "dietitian"
    ],
    "wof:name":"Linda Hodge",
    "wof:placetype":"venue"
},
  "geometry": {"coordinates":[151.19915771500001,-33.8257675171],"type":"Point"}
}