{
  "type": "Feature",
  "properties": {
    "addr:full":"225 Castlereagh St Sydney NSW 2000",
    "addr:housenumber":"225",
    "addr:postcode":"2000",
    "addr:street":"Castlereagh St",
    "iso:country":"AU",
    "sg:address":"225 Castlereagh St",
    "sg:city":"Sydney",
    "sg:classifiers":[
        {
            "category":"Personal",
            "type":"Services"
        }
    ],
    "sg:phone":"+61 2 9267 9434",
    "sg:postcode":"2000",
    "sg:province":"NSW",
    "sg:tags":[
        "dressmaker"
    ],
    "wof:name":"Yora Dressmakers",
    "wof:placetype":"venue"
},
  "geometry": {"coordinates":[151.208786011,-33.8753852844],"type":"Point"}
}