{
  "type": "Feature",
  "properties": {
    "iso:country":"AU",
    "sg:address":"5 Seventh Ave",
    "sg:city":"Toukley",
    "sg:classifiers":[
        {
            "category":"Professional",
            "subcategory":"Art Services",
            "type":"Services"
        }
    ],
    "sg:phone":"+61 2 4396 6809",
    "sg:postcode":"2263",
    "sg:province":"NSW",
    "sg:tags":[
        "decorator",
        "painter"
    ],
    "wof:name":"B.A. & D.L. Roy Painter & Decorator",
    "wof:placetype":"venue"
},
  "geometry": {"coordinates":[151.546249,-33.255657],"type":"Point"}
}