{
  "type": "Feature",
  "properties": {
    "iso:country":"AU",
    "sg:address":"354 Balcombe Rd",
    "sg:city":"Beaumaris",
    "sg:classifiers":[
        {
            "category":"Health Services",
            "subcategory":"Health Practitioner",
            "type":"Services"
        }
    ],
    "sg:phone":"+61 3 9583 8495",
    "sg:postcode":"3193",
    "sg:province":"VIC",
    "sg:tags":[
        "psychologist"
    ],
    "wof:name":"Droege Marise",
    "wof:placetype":"venue"
},
  "geometry": {"coordinates":[145.04525756800001,-37.9787368774],"type":"Point"}
}