{
  "type": "Feature",
  "properties": {
    "addr:full":"PO Box 26 Wodonga VIC 3690",
    "addr:postcode":"3690",
    "iso:country":"AU",
    "sg:address":"PO Box 26",
    "sg:city":"Wodonga",
    "sg:classifiers":[
        {
            "category":"Sports & Exercise",
            "subcategory":"Ski Resort",
            "type":"Entertainment"
        }
    ],
    "sg:phone":"+61 417 041 529",
    "sg:postcode":"3690",
    "sg:province":"VIC",
    "sg:tags":[
        "repair",
        "lift",
        "maintenance"
    ],
    "wof:name":"Otis Elevator Company Pty Ltd",
    "wof:placetype":"venue"
},
  "geometry": {"coordinates":[146.84840393100001,-36.1168785095],"type":"Point"}
}