{
  "type": "Feature",
  "properties": {
    "addr:full":"1a Swan St Mosman Park WA 6012",
    "addr:housenumber":"1a",
    "addr:postcode":"6012",
    "addr:street":"Swan St",
    "iso:country":"AU",
    "sg:address":"1a Swan St",
    "sg:city":"Mosman Park",
    "sg:classifiers":[
        {
            "category":"Professional",
            "subcategory":"Management & Consulting",
            "type":"Services"
        }
    ],
    "sg:phone":"+61 417 903 652",
    "sg:postcode":"6012",
    "sg:province":"WA",
    "sg:tags":[
        "consultant"
    ],
    "wof:name":"The Utterly Organised Consulting Group",
    "wof:placetype":"venue"
},
  "geometry": {"coordinates":[115.762489319,-32.0052452087],"type":"Point"}
}