{
  "type": "Feature",
  "properties": {
    "iso:country":"AU",
    "sg:address":"47 Junction Rd",
    "sg:city":"Leumeah",
    "sg:classifiers":[
        {
            "category":"Building & Trades",
            "subcategory":"Construction",
            "type":"Services"
        }
    ],
    "sg:phone":"+61 408 441 776",
    "sg:postcode":"2560",
    "sg:province":"NSW",
    "sg:tags":[
        "concrete",
        "contractor"
    ],
    "wof:name":"S & M Concreting Services",
    "wof:placetype":"venue"
},
  "geometry": {"coordinates":[150.848342895,-34.0549697876],"type":"Point"}
}