{
  "type": "Feature",
  "properties": {
    "addr:full":"3 Grose St Leura NSW 2780",
    "addr:housenumber":"3",
    "addr:postcode":"2780",
    "addr:street":"Grose St",
    "iso:country":"AU",
    "sg:address":"3 Grose St",
    "sg:city":"Leura",
    "sg:classifiers":[
        {
            "category":"Professional",
            "subcategory":"Accounting & Tax Preparation",
            "type":"Services"
        }
    ],
    "sg:phone":"+61 2 4784 3322",
    "sg:postcode":"2780",
    "sg:province":"NSW",
    "sg:tags":[
        "accountant",
        "auditor"
    ],
    "wof:name":"Wolthers Rijk & Associates",
    "wof:placetype":"venue"
},
  "geometry": {"coordinates":[150.333053589,-33.7124443054],"type":"Point"}
}