{
  "type": "Feature",
  "properties": {
    "iso:country":"AU",
    "sg:address":"PO Box 398",
    "sg:city":"Capalaba",
    "sg:classifiers":[
        {
            "category":"Building & Trades",
            "subcategory":"Construction",
            "type":"Services"
        }
    ],
    "sg:phone":"+61 7 3245 4228",
    "sg:postcode":"4157",
    "sg:province":"QLD",
    "sg:tags":[
        "ceiling"
    ],
    "wof:name":"Holmes L & I Ceilings",
    "wof:placetype":"venue"
},
  "geometry": {"coordinates":[153.230667114,-27.5616836548],"type":"Point"}
}