{
  "type": "Feature",
  "properties": {
    "addr:full":"PO Box 7119 Mt Crosby QLD 4306",
    "addr:postcode":"4306",
    "iso:country":"AU",
    "sg:address":"PO Box 7119",
    "sg:city":"Mt Crosby",
    "sg:classifiers":[
        {
            "category":"Home & Garden",
            "subcategory":"Building Materials",
            "type":"Retail Goods"
        }
    ],
    "sg:phone":"+61 7 3202 6177",
    "sg:postcode":"4306",
    "sg:province":"QLD",
    "sg:tags":[
        "concrete",
        "panel",
        "pre-cast"
    ],
    "wof:name":"Tiltcorp Construction Vic Pty Ltd",
    "wof:placetype":"venue"
},
  "geometry": {"coordinates":[152.831832886,-27.5269203186],"type":"Point"}
}