{
  "type": "Feature",
  "properties": {
    "iso:country":"AU",
    "sg:address":"11 Withers St",
    "sg:city":"West Wallsend",
    "sg:classifiers":[
        {
            "category":"Organizations",
            "subcategory":"Community Association",
            "type":"Services"
        }
    ],
    "sg:phone":"+61 2 4953 1488",
    "sg:postcode":"2286",
    "sg:province":"NSW",
    "sg:tags":[
        "organisation",
        "family",
        "welfare"
    ],
    "wof:name":"Meals On Wheels",
    "wof:placetype":"venue"
},
  "geometry": {"coordinates":[151.581756592,-32.9046173096],"type":"Point"}
}