{
  "type": "Feature",
  "properties": {
    "iso:country":"AU",
    "sg:address":"PO Box 909",
    "sg:city":"Exmouth",
    "sg:classifiers":[
        {
            "category":"Airline",
            "type":"Transportation"
        }
    ],
    "sg:phone":"+61 8 9949 2888",
    "sg:postcode":"6707",
    "sg:province":"WA",
    "sg:tags":[
        "aircraft",
        "rental",
        "charter"
    ],
    "wof:name":"Norwest Air Work & Air Transport",
    "wof:placetype":"venue"
},
  "geometry": {"coordinates":[114.133277893,-21.9462604523],"type":"Point"}
}