{
  "type": "Feature",
  "properties": {
    "iso:country":"AU",
    "sg:address":"4/ 1567 Burwood Hwy",
    "sg:city":"Tecoma",
    "sg:classifiers":[
        {
            "category":"Health Services",
            "subcategory":"Health Practitioner",
            "type":"Services"
        }
    ],
    "sg:phone":"+61 3 9754 8244",
    "sg:postcode":"3160",
    "sg:province":"VIC",
    "sg:tags":[
        "naturopath"
    ],
    "wof:name":"Veanne Bluhm",
    "wof:placetype":"venue"
},
  "geometry": {"coordinates":[145.34585571299999,-37.9068756104],"type":"Point"}
}