{
  "type": "Feature",
  "properties": {
    "addr:full":"303 Trafalgar Ave Umina Beach NSW 2257",
    "addr:housenumber":"303",
    "addr:postcode":"2257",
    "addr:street":"Trafalgar Ave",
    "iso:country":"AU",
    "sg:address":"303 Trafalgar Ave",
    "sg:city":"Umina Beach",
    "sg:classifiers":[
        {
            "category":"Personal",
            "subcategory":"Beauty Salon",
            "type":"Services"
        }
    ],
    "sg:phone":"+61 2 4341 5224",
    "sg:postcode":"2257",
    "sg:province":"NSW",
    "wof:name":"Radiance By The Sea",
    "wof:placetype":"venue"
},
  "geometry": {"coordinates":[151.32072448700001,-33.5218887329],"type":"Point"}
}