{
  "type": "Feature",
  "properties": {
    "addr:full":"North Rocks Rd North Rocks NSW 2151",
    "addr:postcode":"2151",
    "addr:street":"North Rocks Rd",
    "iso:country":"AU",
    "sg:address":"North Rocks Rd",
    "sg:city":"North Rocks",
    "sg:classifiers":[
        {
            "category":"Retail",
            "subcategory":"Funeral Services",
            "type":"Services"
        }
    ],
    "sg:phone":"+61 2 9649 6423",
    "sg:postcode":"2151",
    "sg:province":"NSW",
    "sg:tags":[
        "cemetery"
    ],
    "wof:name":"North Rocks Catholic Cemetery",
    "wof:placetype":"venue"
},
  "geometry": {"coordinates":[151.021316528,-33.77501297],"type":"Point"}
}