{
  "type": "Feature",
  "properties": {
    "iso:country":"AU",
    "sg:address":"827-828 Koolama St",
    "sg:city":"Wyndham",
    "sg:classifiers":[
        {
            "category":"Social Services",
            "subcategory":"Child Care",
            "type":"Services"
        }
    ],
    "sg:phone":"+61 8 9161 1035",
    "sg:postcode":"6740",
    "sg:province":"WA",
    "wof:name":"Wyndham Neighbourhood Centre",
    "wof:placetype":"venue"
},
  "geometry": {"coordinates":[128.12345886200001,-15.4864864349],"type":"Point"}
}