{
  "type": "Feature",
  "properties": {
    "addr:full":"85 MacLeod St Bairnsdale VIC 3875",
    "addr:housenumber":"85",
    "addr:postcode":"3875",
    "addr:street":"Macleod St",
    "iso:country":"AU",
    "sg:address":"85 MacLeod St",
    "sg:city":"Bairnsdale",
    "sg:classifiers":[
        {
            "category":"Retail",
            "subcategory":"Auto Repair",
            "type":"Services"
        }
    ],
    "sg:phone":"+61 3 5152 4570",
    "sg:postcode":"3875",
    "sg:province":"VIC",
    "sg:tags":[
        "wheel",
        "balancing",
        "alignment"
    ],
    "wof:name":"Bairnsdale Tyre Service",
    "wof:placetype":"venue"
},
  "geometry": {"coordinates":[147.63018798799999,-37.8276939392],"type":"Point"}
}