{
  "type": "Feature",
  "properties": {
    "addr:full":"14 Carver St Burwood East VIC 3151",
    "addr:housenumber":"14",
    "addr:postcode":"3151",
    "addr:street":"Carver St",
    "iso:country":"AU",
    "sg:address":"14 Carver St",
    "sg:city":"Burwood East",
    "sg:classifiers":[
        {
            "category":"Taxi",
            "type":"Transportation"
        }
    ],
    "sg:phone":"+61 411 196 237",
    "sg:postcode":"3151",
    "sg:province":"VIC",
    "sg:tags":[
        "cab"
    ],
    "wof:name":"Thernbak Maxi Taxis",
    "wof:placetype":"venue"
},
  "geometry": {"coordinates":[145.144775391,-37.8568344116],"type":"Point"}
}