{
  "type": "Feature",
  "properties": {
    "addr:full":"27 Metropolitan Ave Nunawading VIC 3131",
    "addr:housenumber":"27",
    "addr:postcode":"3131",
    "addr:street":"Metropolitan Ave",
    "iso:country":"AU",
    "sg:address":"27 Metropolitan Ave",
    "sg:city":"Nunawading",
    "sg:classifiers":[
        {
            "category":"Retail",
            "subcategory":"Auto Repair",
            "type":"Services"
        }
    ],
    "sg:phone":"+61 3 9878 2666",
    "sg:postcode":"3131",
    "sg:province":"VIC",
    "sg:tags":[
        "wheel",
        "balancing",
        "alignment"
    ],
    "wof:name":"Computer Line Nunawading",
    "wof:placetype":"venue"
},
  "geometry": {"coordinates":[145.16810607900001,-37.8207168579],"type":"Point"}
}