{
  "type": "Feature",
  "properties": {
    "iso:country":"AU",
    "sg:address":"Lot 101 Seaview Rd",
    "sg:city":"McLaren Vale",
    "sg:classifiers":[
        {
            "category":"Food & Beverages",
            "subcategory":"Liquor & Beverages",
            "type":"Retail Goods"
        }
    ],
    "sg:phone":"+61 8 8323 7344",
    "sg:postcode":"5171",
    "sg:province":"SA",
    "sg:tags":[
        "merchant",
        "spirit",
        "wine"
    ],
    "wof:name":"Settlement Wines",
    "wof:placetype":"venue"
},
  "geometry": {"coordinates":[138.54284668,-35.2075805664],"type":"Point"}
}