{
  "type": "Feature",
  "properties": {
    "addr:full":"7/ 200- 218 Scott St Cairns QLD 4870",
    "addr:housenumber":"/ 200 218",
    "addr:postcode":"4870",
    "addr:street":"Scott St",
    "iso:country":"AU",
    "sg:address":"7/ 200- 218 Scott St",
    "sg:city":"Cairns",
    "sg:classifiers":[
        {
            "category":"Building & Trades",
            "subcategory":"Construction",
            "type":"Services"
        }
    ],
    "sg:phone":"+61 7 4054 2277",
    "sg:postcode":"4870",
    "sg:province":"QLD",
    "sg:tags":[
        "home",
        "air conditioning"
    ],
    "sg:website":"http://www.hendersonac.com.au",
    "wof:name":"Henderson Air-Conditioning",
    "wof:placetype":"venue"
},
  "geometry": {"coordinates":[145.75088500999999,-16.941116333],"type":"Point"}
}