{
  "type": "Feature",
  "properties": {
    "addr:full":"Cnr Thompsons Rd & Sth Gippsland Hwy Cranbourne North VIC 3977",
    "addr:postcode":"3977",
    "addr:street":"Thompsons Rd & Sth Gippsland Hwy",
    "iso:country":"AU",
    "sg:address":"Cnr Thompsons Rd & Sth Gippsland Hwy",
    "sg:city":"Cranbourne North",
    "sg:classifiers":[
        {
            "category":"Food & Beverages",
            "subcategory":"Supermarket",
            "type":"Retail Goods"
        }
    ],
    "sg:phone":"+61 3 5996 9177",
    "sg:postcode":"3977",
    "sg:province":"VIC",
    "sg:tags":[
        "grocery",
        "store"
    ],
    "wof:name":"Safeway",
    "wof:placetype":"venue"
},
  "geometry": {"coordinates":[145.27265930199999,-38.0760765076],"type":"Point"}
}