{
  "type": "Feature",
  "properties": {
    "addr:full":"23 Kenrick St The Junction NSW 2291",
    "addr:housenumber":"23",
    "addr:postcode":"2291",
    "addr:street":"Kenrick St",
    "iso:country":"AU",
    "sg:address":"23 Kenrick St",
    "sg:city":"The Junction",
    "sg:classifiers":[
        {
            "category":"Real Estate",
            "subcategory":"Real Estate Agent",
            "type":"Services"
        }
    ],
    "sg:phone":"+61 2 4961 6888",
    "sg:postcode":"2291",
    "sg:province":"NSW",
    "wof:name":"Professionals",
    "wof:placetype":"venue"
},
  "geometry": {"coordinates":[151.75971984899999,-32.9378318787],"type":"Point"}
}