{
  "type": "Feature",
  "properties": {
    "iso:country":"AU",
    "sg:address":"28 Baretta Rd",
    "sg:city":"Wangara",
    "sg:classifiers":[
        {
            "category":"Banks & Credit Unions",
            "subcategory":"Investment Brokerage",
            "type":"Services"
        }
    ],
    "sg:phone":"+61 8 9309 1599",
    "sg:postcode":"6065",
    "sg:province":"WA",
    "sg:tags":[
        "equipment",
        "spray",
        "painting",
        "supply"
    ],
    "sg:website":"http://www.murphyperkins.com.au",
    "wof:name":"Murphy Perkins Spray Services Pty Ltd",
    "wof:placetype":"venue"
},
  "geometry": {"coordinates":[115.822372437,-31.7922401428],"type":"Point"}
}