{
  "type": "Feature",
  "properties": {
    "addr:full":"60 Bayliss St Auchenflower QLD 4066",
    "addr:housenumber":"60",
    "addr:postcode":"4066",
    "addr:street":"Bayliss St",
    "iso:country":"AU",
    "sg:address":"60 Bayliss St",
    "sg:city":"Auchenflower",
    "sg:classifiers":[
        {
            "category":"Farming",
            "subcategory":"Livestock Farm",
            "type":"Manufacturing & Wholesale Goods"
        }
    ],
    "sg:phone":"+61 7 3377 9940",
    "sg:postcode":"4066",
    "sg:province":"QLD",
    "sg:tags":[
        "school",
        "theological"
    ],
    "wof:name":"Coolamon College",
    "wof:placetype":"venue"
},
  "geometry": {"coordinates":[152.99331665,-27.4784393311],"type":"Point"}
}