{
  "type": "Feature",
  "properties": {
    "addr:full":"Unit 301/ 856 Pacific Hwy Chatswood NSW 2067",
    "addr:housenumber":"/ 856",
    "addr:postcode":"2067",
    "addr:street":"Pacific Hwy",
    "iso:country":"AU",
    "sg:address":"Unit 301/ 856 Pacific Hwy",
    "sg:city":"Chatswood",
    "sg:classifiers":[
        {
            "category":"Professional",
            "subcategory":"Engineering",
            "type":"Services"
        }
    ],
    "sg:phone":"+61 2 9419 4019",
    "sg:postcode":"2067",
    "sg:province":"NSW",
    "sg:tags":[
        "consulting",
        "engineer"
    ],
    "wof:name":"Nad-Kali (Australia) Pty Ltd",
    "wof:placetype":"venue"
},
  "geometry": {"coordinates":[151.180252075,-33.7907524109],"type":"Point"}
}