{
  "type": "Feature",
  "properties": {
    "addr:full":"54 Colville St Battery Point TAS 7004",
    "addr:housenumber":"54",
    "addr:postcode":"7004",
    "addr:street":"Colville St",
    "iso:country":"AU",
    "sg:address":"54 Colville St",
    "sg:city":"Battery Point",
    "sg:classifiers":[
        {
            "category":"Arts & Performance",
            "subcategory":"Art Gallery",
            "type":"Entertainment"
        }
    ],
    "sg:phone":"+61 3 6224 4088",
    "sg:postcode":"7004",
    "sg:province":"TAS",
    "wof:name":"Collville Street Art Gallery",
    "wof:placetype":"venue"
},
  "geometry": {"coordinates":[147.333526611,-42.8926582336],"type":"Point"}
}