{
  "type": "Feature",
  "properties": {
    "addr:full":"Monbulk- Seville Rd Silvan VIC 3795",
    "addr:postcode":"3795",
    "addr:street":"Seville Rd",
    "iso:country":"AU",
    "sg:address":"Monbulk- Seville Rd",
    "sg:city":"Silvan",
    "sg:classifiers":[
        {
            "category":"Farming",
            "subcategory":"Farm",
            "type":"Manufacturing & Wholesale Goods"
        }
    ],
    "sg:phone":"+61 3 9737 9376",
    "sg:postcode":"3795",
    "sg:province":"VIC",
    "sg:tags":[
        "farmer"
    ],
    "wof:name":"Molluso A & C",
    "wof:placetype":"venue"
},
  "geometry": {"coordinates":[145.43780517600001,-37.8470420837],"type":"Point"}
}