{
  "type": "Feature",
  "properties": {
    "addr:full":"19 Mt Maroon St Algester QLD 4115",
    "addr:housenumber":"19",
    "addr:postcode":"4115",
    "addr:street":"Mt Maroon St",
    "iso:country":"AU",
    "sg:address":"19 Mt Maroon St",
    "sg:city":"Algester",
    "sg:classifiers":[
        {
            "category":"Building & Trades",
            "subcategory":"Construction",
            "type":"Services"
        }
    ],
    "sg:phone":"+61 410 881 751",
    "sg:postcode":"4115",
    "sg:province":"QLD",
    "sg:tags":[
        "fencing",
        "contractor"
    ],
    "wof:name":"All About Steel Fencing & Concrete",
    "wof:placetype":"venue"
},
  "geometry": {"coordinates":[153.03706359899999,-27.6020812988],"type":"Point"}
}