{
  "type": "Feature",
  "properties": {
    "iso:country":"AU",
    "sg:address":"Eastern Crt",
    "sg:city":"Helensvale",
    "sg:classifiers":[
        {
            "category":"Retail",
            "subcategory":"Auto Repair",
            "type":"Services"
        }
    ],
    "sg:phone":"+61 418 758 277",
    "sg:postcode":"4212",
    "sg:province":"QLD",
    "sg:tags":[
        "body",
        "motor",
        "trimmer"
    ],
    "wof:name":"Broberg Steve",
    "wof:placetype":"venue"
},
  "geometry": {"coordinates":[153.33161926299999,-27.8935146332],"type":"Point"}
}