{
  "type": "Feature",
  "properties": {
    "addr:full":"90 Marshall St Goondiwindi QLD 4390",
    "addr:housenumber":"90",
    "addr:postcode":"4390",
    "addr:street":"Marshall St",
    "iso:country":"AU",
    "sg:address":"90 Marshall St",
    "sg:city":"Goondiwindi",
    "sg:classifiers":[
        {
            "category":"Personal",
            "subcategory":"Beauty Salon",
            "type":"Services"
        }
    ],
    "sg:phone":"+61 7 4671 1574",
    "sg:postcode":"4390",
    "sg:province":"QLD",
    "wof:name":"The Hair Company",
    "wof:placetype":"venue"
},
  "geometry": {"coordinates":[150.30607605,-28.5468997955],"type":"Point"}
}