{
  "type": "Feature",
  "properties": {
    "addr:full":"Suite 7, 7 Narabang Way Belrose NSW 2085",
    "addr:housenumber":"7",
    "addr:postcode":"2085",
    "addr:street":"Narabang Way",
    "iso:country":"AU",
    "sg:address":"Suite 7, 7 Narabang Way",
    "sg:city":"Belrose",
    "sg:classifiers":[
        {
            "category":"Professional",
            "subcategory":"Accounting & Tax Preparation",
            "type":"Services"
        }
    ],
    "sg:phone":"+61 2 9450 1331",
    "sg:postcode":"2085",
    "sg:province":"NSW",
    "sg:tags":[
        "accountant",
        "auditor"
    ],
    "wof:name":"Bruce N. Clarke & Associates",
    "wof:placetype":"venue"
},
  "geometry": {"coordinates":[151.212356567,-33.70520401],"type":"Point"}
}