{
  "type": "Feature",
  "properties": {
    "addr:full":"9 Mildred Ave Manly Vale NSW 2093",
    "addr:housenumber":"9",
    "addr:postcode":"2093",
    "addr:street":"Mildred Ave",
    "iso:country":"AU",
    "sg:address":"9 Mildred Ave",
    "sg:city":"Manly Vale",
    "sg:classifiers":[
        {
            "category":"Building & Trades",
            "subcategory":"Plumbing",
            "type":"Services"
        }
    ],
    "sg:phone":"+61 2 9948 4560",
    "sg:postcode":"2093",
    "sg:province":"NSW",
    "sg:tags":[
        "plumber",
        "gasfitters"
    ],
    "wof:name":"Zubrinich Allan",
    "wof:placetype":"venue"
},
  "geometry": {"coordinates":[151.26174926799999,-33.7849235535],"type":"Point"}
}