{
  "type": "Feature",
  "properties": {
    "iso:country":"AU",
    "sg:address":"Shop 3, 68 Old Bells Line Of Rd",
    "sg:city":"Kurrajong",
    "sg:classifiers":[
        {
            "category":"Real Estate",
            "subcategory":"Real Estate Agent",
            "type":"Services"
        }
    ],
    "sg:phone":"+61 2 4573 2466",
    "sg:postcode":"2758",
    "sg:province":"NSW",
    "wof:name":"Cantwell Associates",
    "wof:placetype":"venue"
},
  "geometry": {"coordinates":[150.66679382300001,-33.5535583496],"type":"Point"}
}