{
  "type": "Feature",
  "properties": {
    "iso:country":"AU",
    "sg:address":"15 Newcastle Drv",
    "sg:city":"Toormina",
    "sg:classifiers":[
        {
            "category":"Autos & Motor Vehicles",
            "subcategory":"Motorcycle Sales",
            "type":"Retail Goods"
        }
    ],
    "sg:phone":"+61 2 6658 2299",
    "sg:postcode":"2452",
    "sg:province":"NSW",
    "sg:tags":[
        "part",
        "recyclers",
        "cycle"
    ],
    "wof:name":"JDK Motorcycle Wreckers",
    "wof:placetype":"venue"
},
  "geometry": {"coordinates":[153.091812,-30.361956],"type":"Point"}
}