{
  "type": "Feature",
  "properties": {
    "addr:full":"1 Jan St Newton SA 5074",
    "addr:housenumber":"1",
    "addr:postcode":"5074",
    "addr:street":"Jan St",
    "iso:country":"AU",
    "sg:address":"1 Jan St",
    "sg:city":"Newton",
    "sg:classifiers":[
        {
            "category":"Food & Beverages",
            "subcategory":"Fruits & Vegetables",
            "type":"Retail Goods"
        }
    ],
    "sg:phone":"+61 8 8337 0103",
    "sg:postcode":"5074",
    "sg:province":"SA",
    "sg:tags":[
        "greengrocer",
        "fruiterer"
    ],
    "wof:name":"Adelaide Fresh Fruiterers",
    "wof:placetype":"venue"
},
  "geometry": {"coordinates":[138.67361450199999,-34.877155304],"type":"Point"}
}