{
  "type": "Feature",
  "properties": {
    "iso:country":"AU",
    "sg:address":"1 Gardner Crt",
    "sg:city":"Toowoomba",
    "sg:classifiers":[
        {
            "category":"Shopping",
            "subcategory":"Crafts & Fabrics",
            "type":"Retail Goods"
        }
    ],
    "sg:phone":"+61 7 4634 1527",
    "sg:postcode":"4352",
    "sg:province":"QLD",
    "sg:tags":[
        "synthetic",
        "canvas",
        "product"
    ],
    "wof:name":"Glenvale Canvas Pty Ltd",
    "wof:placetype":"venue"
},
  "geometry": {"coordinates":[151.90422100000001,-27.547386],"type":"Point"}
}