{
  "type": "Feature",
  "properties": {
    "iso:country":"AU",
    "sg:address":"32 Barrow Drv",
    "sg:city":"Heathmont",
    "sg:classifiers":[
        {
            "category":"Building & Trades",
            "subcategory":"Construction",
            "type":"Services"
        }
    ],
    "sg:phone":"+61 3 9720 7066",
    "sg:postcode":"3135",
    "sg:province":"VIC",
    "sg:tags":[
        "industrial",
        "commercial",
        "air conditioning"
    ],
    "wof:name":"Legend Installation Pty Ltd",
    "wof:placetype":"venue"
},
  "geometry": {"coordinates":[145.24623107900001,-37.8371505737],"type":"Point"}
}