{
  "type": "Feature",
  "properties": {
    "addr:full":"1 Byron St Brunswick Heads NSW 2483",
    "addr:housenumber":"1",
    "addr:postcode":"2483",
    "addr:street":"Byron St",
    "iso:country":"AU",
    "sg:address":"1 Byron St",
    "sg:city":"Brunswick Heads",
    "sg:classifiers":[
        {
            "category":"Building & Trades",
            "subcategory":"Construction",
            "type":"Services"
        }
    ],
    "sg:phone":"+61 2 6685 1554",
    "sg:postcode":"2483",
    "sg:province":"NSW",
    "sg:tags":[
        "contractor"
    ],
    "wof:name":"Brunswick Building Services",
    "wof:placetype":"venue"
},
  "geometry": {"coordinates":[153.545684814,-28.5408325195],"type":"Point"}
}