{
  "type": "Feature",
  "properties": {
    "addr:full":"6/26 Fortune St Coomera QLD 4209",
    "addr:housenumber":"/ 26",
    "addr:postcode":"4209",
    "addr:street":"Fortune St",
    "iso:country":"AU",
    "sg:address":"6/26 Fortune St",
    "sg:city":"Coomera",
    "sg:classifiers":[
        {
            "category":"Professional",
            "subcategory":"Computer Services",
            "type":"Services"
        }
    ],
    "sg:phone":"+61 403 904 482",
    "sg:postcode":"4209",
    "sg:province":"QLD",
    "sg:tags":[
        "consultant",
        "system"
    ],
    "wof:name":"Apex",
    "wof:placetype":"venue"
},
  "geometry": {"coordinates":[153.318527222,-27.8738422394],"type":"Point"}
}