{
  "type": "Feature",
  "properties": {
    "addr:full":"Cnr Kingsway & Wren Rd Moorabbin VIC 3189",
    "addr:postcode":"3189",
    "addr:street":"Cnr Kingsway & Wren Rd",
    "iso:country":"AU",
    "sg:address":"Cnr Kingsway & Wren Rd",
    "sg:city":"Moorabbin",
    "sg:classifiers":[
        {
            "category":"Retail",
            "subcategory":"Storage",
            "type":"Services"
        }
    ],
    "sg:phone":"+61 3 9553 3622",
    "sg:postcode":"3189",
    "sg:province":"VIC",
    "sg:tags":[
        "removal",
        "furniture"
    ],
    "wof:name":"Macs",
    "wof:placetype":"venue"
},
  "geometry": {"coordinates":[145.073776245,-37.938293457],"type":"Point"}
}