{
  "type": "Feature",
  "properties": {
    "addr:full":"29 Robinson St Riverstone NSW 2765",
    "addr:housenumber":"29",
    "addr:postcode":"2765",
    "addr:street":"Robinson St",
    "iso:country":"AU",
    "sg:address":"29 Robinson St",
    "sg:city":"Riverstone",
    "sg:classifiers":[
        {
            "category":"Building & Trades",
            "subcategory":"Construction",
            "type":"Services"
        }
    ],
    "sg:phone":"+61 2 9627 5586",
    "sg:postcode":"2765",
    "sg:province":"NSW",
    "sg:tags":[
        "home",
        "air conditioning"
    ],
    "wof:name":"R & M Rogers",
    "wof:placetype":"venue"
},
  "geometry": {"coordinates":[150.86578369099999,-33.6837463379],"type":"Point"}
}