{
  "type": "Feature",
  "properties": {
    "iso:country":"AU",
    "sg:address":"41 Strickland St",
    "sg:city":"Bunbury",
    "sg:classifiers":[
        {
            "category":"Home & Garden",
            "subcategory":"Carpets & Floor Coverings",
            "type":"Retail Goods"
        }
    ],
    "sg:phone":"+61 8 9791 2510",
    "sg:postcode":"6230",
    "sg:province":"WA",
    "sg:tags":[
        "tile",
        "wall"
    ],
    "wof:name":"Tiles Plus",
    "wof:placetype":"venue"
},
  "geometry": {"coordinates":[115.647369,-33.336388],"type":"Point"}
}