{
  "type": "Feature",
  "properties": {
    "addr:full":"123 Wright St East Devonport TAS 7310",
    "addr:housenumber":"123",
    "addr:postcode":"7310",
    "addr:street":"Wright St East",
    "iso:country":"AU",
    "sg:address":"123 Wright St",
    "sg:city":"East Devonport",
    "sg:classifiers":[
        {
            "category":"Wholesale",
            "subcategory":"Machinery & Supplies",
            "type":"Manufacturing & Wholesale Goods"
        }
    ],
    "sg:phone":"+61 3 6427 0908",
    "sg:postcode":"7310",
    "sg:province":"TAS",
    "sg:tags":[
        "equipment",
        "hydraulic"
    ],
    "wof:name":"Southcott Pty Limited",
    "wof:placetype":"venue"
},
  "geometry": {"coordinates":[146.369262695,-41.18491745],"type":"Point"}
}