{
  "type": "Feature",
  "properties": {
    "addr:full":"PO Box 1405 Gympie QLD 4570",
    "addr:postcode":"4570",
    "iso:country":"AU",
    "sg:address":"PO Box 1405",
    "sg:city":"Gympie",
    "sg:classifiers":[
        {
            "category":"Retail",
            "subcategory":"Repair Shop",
            "type":"Services"
        }
    ],
    "sg:phone":"+61 7 5482 1772",
    "sg:postcode":"4570",
    "sg:province":"QLD",
    "sg:tags":[
        "machine",
        "repairs",
        "part",
        "dryer",
        "washing"
    ],
    "wof:name":"Gympie Appliance Service",
    "wof:placetype":"venue"
},
  "geometry": {"coordinates":[152.574905395,-26.2030849457],"type":"Point"}
}