{
  "type": "Feature",
  "properties": {
    "addr:full":"31 Wells Rd Frankston VIC 3199",
    "addr:housenumber":"31",
    "addr:postcode":"3199",
    "addr:street":"Wells Rd",
    "iso:country":"AU",
    "sg:address":"31 Wells Rd",
    "sg:city":"Frankston",
    "sg:classifiers":[
        {
            "category":"Professional",
            "subcategory":"Employment Agencies",
            "type":"Services"
        }
    ],
    "sg:phone":"+61 3 9786 7222",
    "sg:postcode":"3199",
    "sg:province":"VIC",
    "sg:tags":[
        "vic",
        "escort"
    ],
    "wof:name":"Palace Playmates",
    "wof:placetype":"venue"
},
  "geometry": {"coordinates":[145.13429260300001,-38.1231307983],"type":"Point"}
}