{
  "type": "Feature",
  "properties": {
    "addr:full":"124 Aberford St Coonamble NSW 2829",
    "addr:housenumber":"124",
    "addr:postcode":"2829",
    "addr:street":"Aberford St",
    "iso:country":"AU",
    "sg:address":"124 Aberford St",
    "sg:city":"Coonamble",
    "sg:classifiers":[
        {
            "category":"Retail",
            "subcategory":"Repair Shop",
            "type":"Services"
        }
    ],
    "sg:phone":"+61 2 6822 2499",
    "sg:postcode":"2829",
    "sg:province":"NSW",
    "sg:tags":[
        "upholsterer"
    ],
    "wof:name":"Coonamble Auto Trim",
    "wof:placetype":"venue"
},
  "geometry": {"coordinates":[148.39175415,-30.9548568726],"type":"Point"}
}