{
  "type": "Feature",
  "properties": {
    "addr:full":"605 Pacific Hwy Mt Colah NSW 2079",
    "addr:housenumber":"605",
    "addr:postcode":"2079",
    "addr:street":"Pacific Hwy Mt Colah",
    "iso:country":"AU",
    "sg:address":"605 Pacific Hwy",
    "sg:city":"Mt Colah",
    "sg:classifiers":[
        {
            "category":"Professional",
            "subcategory":"Computer Services",
            "type":"Services"
        }
    ],
    "sg:phone":"+61 2 9482 8200",
    "sg:postcode":"2079",
    "sg:province":"NSW",
    "sg:tags":[
        "consultant",
        "system"
    ],
    "wof:name":"Datasync Consulting",
    "wof:placetype":"venue"
},
  "geometry": {"coordinates":[151.11509704599999,-33.6781921387],"type":"Point"}
}