{
  "type": "Feature",
  "properties": {
    "iso:country":"AU",
    "sg:address":"44 McAlister St",
    "sg:city":"Oonoonba",
    "sg:classifiers":[
        {
            "category":"Utilities",
            "subcategory":"Electric",
            "type":"Services"
        }
    ],
    "sg:phone":"+61 403 182 266",
    "sg:postcode":"4811",
    "sg:province":"QLD",
    "sg:tags":[
        "electrical",
        "contractor"
    ],
    "wof:name":"Peel Electrical",
    "wof:placetype":"venue"
},
  "geometry": {"coordinates":[146.82048,-19.298386],"type":"Point"}
}