{
  "type": "Feature",
  "properties": {
    "iso:country":"AU",
    "sg:address":"3- 5 Eltham St",
    "sg:city":"Dallas",
    "sg:classifiers":[
        {
            "category":"Social Services",
            "subcategory":"Child Care",
            "type":"Services"
        }
    ],
    "sg:phone":"+61 3 9309 2846",
    "sg:postcode":"3047",
    "sg:province":"VIC",
    "wof:name":"The Playhouse",
    "wof:placetype":"venue"
},
  "geometry": {"coordinates":[144.92898559599999,-37.674697876],"type":"Point"}
}