{
  "type": "Feature",
  "properties": {
    "iso:country":"AU",
    "sg:address":"251 Thomas St",
    "sg:city":"Hampton",
    "sg:classifiers":[
        {
            "category":"Professional",
            "subcategory":"Detective & Security Services",
            "type":"Services"
        }
    ],
    "sg:phone":"+61 1300 553 735",
    "sg:postcode":"3188",
    "sg:province":"VIC",
    "sg:tags":[
        "guard",
        "patrol"
    ],
    "wof:name":"S.T.A.S Corporate Services P/L",
    "wof:placetype":"venue"
},
  "geometry": {"coordinates":[145.02291870100001,-37.9407272339],"type":"Point"}
}