{
  "type": "Feature",
  "properties": {
    "addr:full":"75 Victoria St Potts Point NSW 2011",
    "addr:housenumber":"75",
    "addr:postcode":"2011",
    "addr:street":"Victoria St",
    "iso:country":"AU",
    "sg:address":"75 Victoria St",
    "sg:city":"Potts Point",
    "sg:classifiers":[
        {
            "category":"Professional",
            "subcategory":"Accounting & Tax Preparation",
            "type":"Services"
        }
    ],
    "sg:phone":"+61 2 9368 7351",
    "sg:postcode":"2011",
    "sg:province":"NSW",
    "sg:tags":[
        "consultant",
        "taxation"
    ],
    "wof:name":"McGill & Co",
    "wof:placetype":"venue"
},
  "geometry": {"coordinates":[151.22297668499999,-33.8703041077],"type":"Point"}
}