{
  "type": "Feature",
  "properties": {
    "addr:full":"Level 29 221 St Georges Tce Perth WA 6000",
    "addr:housenumber":"221",
    "addr:postcode":"6000",
    "addr:street":"St Georges Tce",
    "iso:country":"AU",
    "sg:address":"Level 29 221 St Georges Tce",
    "sg:city":"Perth",
    "sg:classifiers":[
        {
            "category":"Professional",
            "subcategory":"Computer Services",
            "type":"Services"
        }
    ],
    "sg:phone":"+61 8 9237 3400",
    "sg:postcode":"6000",
    "sg:province":"WA",
    "sg:tags":[
        "tele-communications",
        "consultant"
    ],
    "wof:name":"Lane Telecommunications",
    "wof:placetype":"venue"
},
  "geometry": {"coordinates":[115.851867676,-31.9532966614],"type":"Point"}
}