{
  "type": "Feature",
  "properties": {
    "addr:full":"Shp 3/ 1 Simms Rd Hamilton Hill WA 6163",
    "addr:housenumber":"/ 1",
    "addr:postcode":"6163",
    "addr:street":"Simms Rd",
    "iso:country":"AU",
    "sg:address":"Shp 3/ 1 Simms Rd",
    "sg:city":"Hamilton Hill",
    "sg:classifiers":[
        {
            "category":"Personal",
            "subcategory":"Beauty Salon",
            "type":"Services"
        }
    ],
    "sg:phone":"+61 8 9337 2814",
    "sg:postcode":"6163",
    "sg:province":"WA",
    "sg:tags":[
        "hairdresser"
    ],
    "wof:name":"Chisel Hair",
    "wof:placetype":"venue"
},
  "geometry": {"coordinates":[115.781761,-32.075333],"type":"Point"}
}