{
  "type": "Feature",
  "properties": {
    "addr:full":"PO Box 413 Greensborough VIC 3088",
    "addr:postcode":"3088",
    "iso:country":"AU",
    "sg:address":"PO Box 413",
    "sg:city":"Greensborough",
    "sg:classifiers":[
        {
            "category":"Shopping",
            "subcategory":"Computers & Home Electronics",
            "type":"Retail Goods"
        }
    ],
    "sg:phone":"+61 3 9434 1429",
    "sg:postcode":"3088",
    "sg:province":"VIC",
    "sg:tags":[
        "equipment",
        "supply"
    ],
    "wof:name":"G.M.A. & Associates",
    "wof:placetype":"venue"
},
  "geometry": {"coordinates":[145.10215759299999,-37.7044715881],"type":"Point"}
}