{
  "type": "Feature",
  "properties": {
    "addr:full":"45 Vincent Rd Wagga Wagga NSW 2650",
    "addr:housenumber":"45",
    "addr:postcode":"2650",
    "addr:street":"Vincent Rd",
    "iso:country":"AU",
    "sg:address":"45 Vincent Rd",
    "sg:city":"Wagga Wagga",
    "sg:classifiers":[
        {
            "category":"Sports & Exercise",
            "subcategory":"Sports Center",
            "type":"Entertainment"
        }
    ],
    "sg:phone":"+61 2 6922 4963",
    "sg:postcode":"2650",
    "sg:province":"NSW",
    "sg:tags":[
        "coach",
        "tennis"
    ],
    "wof:name":"Adamcewicz Roman",
    "wof:placetype":"venue"
},
  "geometry": {"coordinates":[147.3881073,-35.1574935913],"type":"Point"}
}