{
  "type": "Feature",
  "properties": {
    "addr:full":"76 Scarborough St Monterey NSW 2217",
    "addr:housenumber":"76",
    "addr:postcode":"2217",
    "addr:street":"Scarborough St",
    "iso:country":"AU",
    "sg:address":"76 Scarborough St",
    "sg:city":"Monterey",
    "sg:classifiers":[
        {
            "category":"Professional",
            "subcategory":"Secretarial Services",
            "type":"Services"
        }
    ],
    "sg:phone":"+61 407 712 616",
    "sg:postcode":"2217",
    "sg:province":"NSW",
    "sg:tags":[
        "typing"
    ],
    "wof:name":"Diamond Medical Secretaries",
    "wof:placetype":"venue"
},
  "geometry": {"coordinates":[151.14471399999999,-33.974781],"type":"Point"}
}