{
  "type": "Feature",
  "properties": {
    "iso:country":"AU",
    "sg:address":"Level 1, 355 Queen St",
    "sg:city":"Brisbane",
    "sg:classifiers":[
        {
            "category":"Banks & Credit Unions",
            "subcategory":"Financial Services",
            "type":"Services"
        }
    ],
    "sg:phone":"+61 7 3815 0011",
    "sg:postcode":"4000",
    "sg:province":"QLD",
    "sg:tags":[
        "loan",
        "finance",
        "mortgage"
    ],
    "wof:name":"Ashe Morgan Winthrop",
    "wof:placetype":"venue"
},
  "geometry": {"coordinates":[153.02963256800001,-27.4678344727],"type":"Point"}
}