{
  "type": "Feature",
  "properties": {
    "iso:country":"AU",
    "sg:address":"849 Burwood Rd",
    "sg:city":"Camberwell",
    "sg:classifiers":[
        {
            "category":"Health Services",
            "subcategory":"Health Practitioner",
            "type":"Services"
        }
    ],
    "sg:phone":"+61 3 9882 2201",
    "sg:postcode":"3124",
    "sg:province":"VIC",
    "sg:tags":[
        "acupuncture"
    ],
    "wof:name":"Marinaccio Tania",
    "wof:placetype":"venue"
},
  "geometry": {"coordinates":[145.05763244600001,-37.8251724243],"type":"Point"}
}