{
  "type": "Feature",
  "properties": {
    "addr:full":"30 Clarke St Young NSW 2594",
    "addr:housenumber":"30",
    "addr:postcode":"2594",
    "addr:street":"Clarke St",
    "iso:country":"AU",
    "sg:address":"30 Clarke St",
    "sg:city":"Young",
    "sg:classifiers":[
        {
            "category":"Manufacturing",
            "subcategory":"Textiles",
            "type":"Manufacturing & Wholesale Goods"
        }
    ],
    "sg:phone":"+61 2 6382 4110",
    "sg:postcode":"2594",
    "sg:province":"NSW",
    "sg:tags":[
        "knitted",
        "woven",
        "fabric"
    ],
    "wof:name":"Margaret's Town & Country Fabrics",
    "wof:placetype":"venue"
},
  "geometry": {"coordinates":[148.29261779800001,-34.3132629395],"type":"Point"}
}