{
  "type": "Feature",
  "properties": {
    "addr:full":"2 Marcella St Punchbowl NSW 2196",
    "addr:housenumber":"2",
    "addr:postcode":"2196",
    "addr:street":"Marcella St",
    "iso:country":"AU",
    "sg:address":"2 Marcella St",
    "sg:city":"Punchbowl",
    "sg:classifiers":[
        {
            "category":"Retail",
            "subcategory":"Auto Repair",
            "type":"Services"
        }
    ],
    "sg:phone":"+61 2 9709 8192",
    "sg:postcode":"2196",
    "sg:province":"NSW",
    "sg:tags":[
        "electrical"
    ],
    "wof:name":"Iass Electronic",
    "wof:placetype":"venue"
},
  "geometry": {"coordinates":[151.03877299999999,-33.926418],"type":"Point"}
}