{
  "type": "Feature",
  "properties": {
    "iso:country":"AU",
    "sg:address":"3/ 717 Military Rd",
    "sg:city":"Mosman",
    "sg:classifiers":[
        {
            "category":"Shopping",
            "subcategory":"Bridal",
            "type":"Retail Goods"
        }
    ],
    "sg:phone":"+61 2 9904 1177",
    "sg:postcode":"2088",
    "sg:province":"NSW",
    "sg:tags":[
        "hire",
        "wear"
    ],
    "sg:website":"http://www.sarahdevine.com.au",
    "wof:name":"Sarah Devine Bridal Couture",
    "wof:placetype":"venue"
},
  "geometry": {"coordinates":[151.243850708,-33.8279838562],"type":"Point"}
}