{
  "type": "Feature",
  "properties": {
    "addr:full":"14 Plaza St Bunbury WA 6230",
    "addr:housenumber":"14",
    "addr:postcode":"6230",
    "addr:street":"Plaza St",
    "iso:country":"AU",
    "sg:address":"14 Plaza St",
    "sg:city":"Bunbury",
    "sg:classifiers":[
        {
            "category":"Recreation",
            "subcategory":"Boat Charter",
            "type":"Entertainment"
        }
    ],
    "sg:phone":"+61 8 9721 7664",
    "sg:postcode":"6230",
    "sg:province":"WA",
    "wof:name":"South West Yacht Charters",
    "wof:placetype":"venue"
},
  "geometry": {"coordinates":[115.63761100000001,-33.337971],"type":"Point"}
}