{
  "type": "Feature",
  "properties": {
    "iso:country":"AU",
    "sg:address":"Lot 2",
    "sg:city":"/ Crofters Way Bilambil",
    "sg:classifiers":[
        {
            "category":"Military Area",
            "subcategory":"Coast Guard Base",
            "type":"Public Place"
        }
    ],
    "sg:phone":"+61 416 177 874",
    "sg:postcode":"2486",
    "sg:province":"NSW",
    "sg:tags":[
        "sound",
        "engineer"
    ],
    "wof:name":"Darren Ottery",
    "wof:placetype":"venue"
},
  "geometry": {"coordinates":[153.48692321799999,-28.2333297729],"type":"Point"}
}