{
  "type": "Feature",
  "properties": {
    "addr:full":"2 Ruling St Sinnamon Park QLD 4073",
    "addr:housenumber":"2",
    "addr:postcode":"4073",
    "addr:street":"Ruling St",
    "iso:country":"AU",
    "sg:address":"2 Ruling St",
    "sg:city":"Sinnamon Park",
    "sg:classifiers":[
        {
            "category":"Building & Trades",
            "subcategory":"Construction",
            "type":"Services"
        }
    ],
    "sg:phone":"+61 411 709 433",
    "sg:postcode":"4073",
    "sg:province":"QLD",
    "sg:tags":[
        "plasterboard",
        "plasterer",
        "fixer"
    ],
    "wof:name":"A & S Poljak Plasterers",
    "wof:placetype":"venue"
},
  "geometry": {"coordinates":[152.95045471200001,-27.55037117],"type":"Point"}
}