{
  "type": "Feature",
  "properties": {
    "iso:country":"AU",
    "sg:address":"48 Torquay Rd",
    "sg:city":"Belmont",
    "sg:classifiers":[
        {
            "category":"Health Services",
            "subcategory":"Chiropractor",
            "type":"Services"
        }
    ],
    "sg:phone":"+61 3 5243 0233",
    "sg:postcode":"3216",
    "sg:province":"VIC",
    "wof:name":"Chirolife",
    "wof:placetype":"venue"
},
  "geometry": {"coordinates":[144.34478759800001,-38.1837730408],"type":"Point"}
}