{
  "type": "Feature",
  "properties": {
    "addr:full":"Unit 5 / 2A Pioneer Ave Thornleigh NSW 2120",
    "addr:housenumber":"/ 2a",
    "addr:postcode":"2120",
    "addr:street":"Pioneer Ave",
    "iso:country":"AU",
    "sg:address":"Unit 5 / 2A Pioneer Ave",
    "sg:city":"Thornleigh",
    "sg:classifiers":[
        {
            "category":"Shopping",
            "subcategory":"Stationery & Office Supplies",
            "type":"Retail Goods"
        }
    ],
    "sg:phone":"+61 2 9484 9667",
    "sg:postcode":"2120",
    "sg:province":"NSW",
    "sg:tags":[
        "partition"
    ],
    "wof:name":"Form Commercial Building Pty Ltd",
    "wof:placetype":"venue"
},
  "geometry": {"coordinates":[151.08355712900001,-33.7255058289],"type":"Point"}
}