{
  "type": "Feature",
  "properties": {
    "iso:country":"AU",
    "sg:address":"11 Leopold St",
    "sg:city":"Caulfield",
    "sg:classifiers":[
        {
            "category":"Utilities",
            "subcategory":"Mobile Phone",
            "type":"Services"
        }
    ],
    "sg:phone":"+61 3 9572 2779",
    "sg:postcode":"3162",
    "sg:province":"VIC",
    "sg:tags":[
        "wire",
        "straightener",
        "cutter"
    ],
    "wof:name":"Dancore",
    "wof:placetype":"venue"
},
  "geometry": {"coordinates":[145.03379821799999,-37.9022140503],"type":"Point"}
}