{
  "type": "Feature",
  "properties": {
    "addr:full":"Wheatsheaf Rd Morphett Vale SA 5162",
    "addr:postcode":"5162",
    "addr:street":"Wheatsheaf Rd",
    "iso:country":"AU",
    "sg:address":"Wheatsheaf Rd",
    "sg:city":"Morphett Vale",
    "sg:classifiers":[
        {
            "category":"Arena",
            "subcategory":"Sports Club",
            "type":"Entertainment"
        }
    ],
    "sg:phone":"+61 8 8382 7219",
    "sg:postcode":"5162",
    "sg:province":"SA",
    "sg:tags":[
        "australian",
        "football",
        "rule"
    ],
    "wof:name":"Morphett Vale Football & Sports Club Inc",
    "wof:placetype":"venue"
},
  "geometry": {"coordinates":[138.52442932100001,-35.1262016296],"type":"Point"}
}