{
  "type": "Feature",
  "properties": {
    "addr:full":"98a Sydenham Rd Norwood SA 5067",
    "addr:housenumber":"98a",
    "addr:postcode":"5067",
    "addr:street":"Sydenham Rd",
    "iso:country":"AU",
    "sg:address":"98a Sydenham Rd",
    "sg:city":"Norwood",
    "sg:classifiers":[
        {
            "category":"Building & Trades",
            "subcategory":"Construction",
            "type":"Services"
        }
    ],
    "sg:phone":"+61 8 8364 6251",
    "sg:postcode":"5067",
    "sg:province":"SA",
    "sg:tags":[
        "contractor"
    ],
    "wof:name":"Wattle Constructions Pty Ltd",
    "wof:placetype":"venue"
},
  "geometry": {"coordinates":[138.627975464,-34.9243965149],"type":"Point"}
}