{
  "type": "Feature",
  "properties": {
    "addr:full":"PO Box 302 Mullumbimby NSW 2482",
    "addr:postcode":"2482",
    "iso:country":"AU",
    "sg:address":"PO Box 302",
    "sg:city":"Mullumbimby",
    "sg:classifiers":[
        {
            "category":"Building & Trades",
            "subcategory":"Construction",
            "type":"Services"
        }
    ],
    "sg:phone":"+61 2 6684 2836",
    "sg:postcode":"2482",
    "sg:province":"NSW",
    "sg:tags":[
        "earth",
        "excavating",
        "moving",
        "contractor"
    ],
    "wof:name":"Brunswick Byron Plant Hire",
    "wof:placetype":"venue"
},
  "geometry": {"coordinates":[153.49993896500001,-28.5531997681],"type":"Point"}
}