{
  "type": "Feature",
  "properties": {
    "iso:country":"AU",
    "sg:address":"Suite B, Ground Floor, 188 Oxford St",
    "sg:city":"Paddington",
    "sg:classifiers":[
        {
            "category":"Real Estate",
            "subcategory":"Real Estate Agent",
            "type":"Services"
        }
    ],
    "sg:phone":"+61 2 9331 7000",
    "sg:postcode":"2021",
    "sg:province":"NSW",
    "sg:tags":[
        "buyer"
    ],
    "wof:name":"Sydney Property Finders Pty Ltd",
    "wof:placetype":"venue"
},
  "geometry": {"coordinates":[151.22439575199999,-33.8844985962],"type":"Point"}
}