{
  "type": "Feature",
  "properties": {
    "addr:full":"Princes Hwy Tailem Bend SA 5260",
    "addr:postcode":"5260",
    "addr:street":"Princes Hwy",
    "iso:country":"AU",
    "sg:address":"Princes Hwy",
    "sg:city":"Tailem Bend",
    "sg:classifiers":[
        {
            "category":"Autos & Motor Vehicles",
            "subcategory":"Fuel & Gas Station",
            "type":"Retail Goods"
        }
    ],
    "sg:phone":"+61 8 8572 4155",
    "sg:postcode":"5260",
    "sg:province":"SA",
    "wof:name":"BP Australia Limited",
    "wof:placetype":"venue"
},
  "geometry": {"coordinates":[139.45979309099999,-35.2723960876],"type":"Point"}
}