{
  "type": "Feature",
  "properties": {
    "addr:full":"2 Lockyer St Goulburn NSW 2580",
    "addr:housenumber":"2",
    "addr:postcode":"2580",
    "addr:street":"Lockyer St",
    "iso:country":"AU",
    "sg:address":"2 Lockyer St",
    "sg:city":"Goulburn",
    "sg:classifiers":[
        {
            "category":"Utilities",
            "subcategory":"Electric",
            "type":"Services"
        }
    ],
    "sg:phone":"+61 427 483 211",
    "sg:postcode":"2580",
    "sg:province":"NSW",
    "sg:tags":[
        "electrical",
        "contractor"
    ],
    "wof:name":"Cookies Electrical",
    "wof:placetype":"venue"
},
  "geometry": {"coordinates":[149.69171142600001,-34.7736816406],"type":"Point"}
}