{
  "type": "Feature",
  "properties": {
    "addr:full":"2 Sneyd St Bowen Hills QLD 4006",
    "addr:housenumber":"2",
    "addr:postcode":"4006",
    "addr:street":"Sneyd St",
    "iso:country":"AU",
    "sg:address":"2 Sneyd St",
    "sg:city":"Bowen Hills",
    "sg:classifiers":[
        {
            "category":"Professional",
            "subcategory":"Management & Consulting",
            "type":"Services"
        }
    ],
    "sg:phone":"+61 7 3852 1244",
    "sg:postcode":"4006",
    "sg:province":"QLD",
    "sg:tags":[
        "consultant",
        "energy"
    ],
    "wof:name":"Enertec Australia Pty Ltd",
    "wof:placetype":"venue"
},
  "geometry": {"coordinates":[153.031814575,-27.4480743408],"type":"Point"}
}