{
  "type": "Feature",
  "properties": {
    "iso:country":"AU",
    "sg:address":"PO Box 81",
    "sg:city":"Woolgoolga",
    "sg:classifiers":[
        {
            "category":"Real Estate",
            "subcategory":"Architect",
            "type":"Services"
        }
    ],
    "sg:phone":"+61 427 562 133",
    "sg:postcode":"2456",
    "sg:province":"NSW",
    "sg:tags":[
        "building",
        "designer"
    ],
    "wof:name":"Abrahams Steve Building Designer",
    "wof:placetype":"venue"
},
  "geometry": {"coordinates":[153.190338,-30.11187],"type":"Point"}
}