{
  "type": "Feature",
  "properties": {
    "addr:full":"30 Princess St Campbells Creek VIC 3451",
    "addr:housenumber":"30",
    "addr:postcode":"3451",
    "addr:street":"Princess St",
    "iso:country":"AU",
    "sg:address":"30 Princess St",
    "sg:city":"Campbells Creek",
    "sg:classifiers":[
        {
            "category":"Farming",
            "subcategory":"Farm & Veterinary Services",
            "type":"Manufacturing & Wholesale Goods"
        }
    ],
    "sg:phone":"+61 3 5472 3647",
    "sg:postcode":"3451",
    "sg:province":"VIC",
    "sg:tags":[
        "contracting"
    ],
    "wof:name":"Dzioba T R & L M",
    "wof:placetype":"venue"
},
  "geometry": {"coordinates":[144.20413207999999,-37.0868721008],"type":"Point"}
}