{
  "type": "Feature",
  "properties": {
    "addr:full":"PO Box 62 Coominya QLD 4311",
    "addr:postcode":"4311",
    "iso:country":"AU",
    "sg:address":"PO Box 62",
    "sg:city":"Coominya",
    "sg:classifiers":[
        {
            "category":"Wholesale",
            "subcategory":"Scrap",
            "type":"Manufacturing & Wholesale Goods"
        }
    ],
    "sg:phone":"+61 416 045 022",
    "sg:postcode":"4311",
    "sg:province":"QLD",
    "sg:tags":[
        "merchant",
        "metal"
    ],
    "wof:name":"Shift-Eze",
    "wof:placetype":"venue"
},
  "geometry": {"coordinates":[152.50238037099999,-27.3911590576],"type":"Point"}
}