{
  "type": "Feature",
  "properties": {
    "addr:full":"26 Sibbick St Five Dock NSW 2046",
    "addr:housenumber":"26",
    "addr:postcode":"2046",
    "addr:street":"Sibbick St",
    "iso:country":"AU",
    "sg:address":"26 Sibbick St",
    "sg:city":"Five Dock",
    "sg:classifiers":[
        {
            "category":"Train Station",
            "subcategory":"Rail",
            "type":"Transportation"
        }
    ],
    "sg:phone":"+61 438 605 772",
    "sg:postcode":"2046",
    "sg:province":"NSW",
    "sg:tags":[
        "marine",
        "engineer"
    ],
    "wof:name":"Taranto Marine Engineering",
    "wof:placetype":"venue"
},
  "geometry": {"coordinates":[151.13797,-33.859966],"type":"Point"}
}