{
  "type": "Feature",
  "properties": {
    "iso:country":"AU",
    "sg:address":"430 Wanneroo Rd",
    "sg:city":"Balcatta",
    "sg:classifiers":[
        {
            "category":"Autos & Motor Vehicles",
            "subcategory":"Motorcycle Sales",
            "type":"Retail Goods"
        }
    ],
    "sg:phone":"+61 8 9345 4311",
    "sg:postcode":"6021",
    "sg:province":"WA",
    "sg:tags":[
        "outboard"
    ],
    "wof:name":"Boat City",
    "wof:placetype":"venue"
},
  "geometry": {"coordinates":[115.829917908,-31.8683223724],"type":"Point"}
}