{
  "type": "Feature",
  "properties": {
    "addr:full":"1341 Burke Rd Kew VIC 3101",
    "addr:housenumber":"1341",
    "addr:postcode":"3101",
    "addr:street":"Burke Rd",
    "iso:country":"AU",
    "sg:address":"1341 Burke Rd",
    "sg:city":"Kew",
    "sg:classifiers":[
        {
            "category":"Personal",
            "type":"Services"
        }
    ],
    "sg:phone":"+61 3 9817 2661",
    "sg:postcode":"3101",
    "sg:province":"VIC",
    "sg:tags":[
        "nappy"
    ],
    "wof:name":"The Nappy Shop",
    "wof:placetype":"venue"
},
  "geometry": {"coordinates":[145.06224060100001,-37.8014183044],"type":"Point"}
}