{
  "type": "Feature",
  "properties": {
    "addr:full":"PO Box 2845 Geraldton WA 6530",
    "addr:postcode":"6530",
    "iso:country":"AU",
    "sg:address":"PO Box 2845",
    "sg:city":"Geraldton",
    "sg:classifiers":[
        {
            "category":"Building & Trades",
            "subcategory":"Landscaping Services",
            "type":"Services"
        }
    ],
    "sg:phone":"+61 428 654 510",
    "sg:postcode":"6530",
    "sg:province":"WA",
    "sg:tags":[
        "designer",
        "landscape",
        "contractor"
    ],
    "wof:name":"JD's Landscaping",
    "wof:placetype":"venue"
},
  "geometry": {"coordinates":[114.64060974100001,-28.7494506836],"type":"Point"}
}