{
  "type": "Feature",
  "properties": {
    "addr:full":"Un 5, 8 Project Ave Noosaville QLD 4566",
    "addr:housenumber":"8",
    "addr:postcode":"4566",
    "addr:street":"Project Ave",
    "iso:country":"AU",
    "sg:address":"Un 5, 8 Project Ave",
    "sg:city":"Noosaville",
    "sg:classifiers":[
        {
            "category":"Education",
            "subcategory":"Music School",
            "type":"Public Place"
        }
    ],
    "sg:phone":"+61 415 195 710",
    "sg:postcode":"4566",
    "sg:province":"QLD",
    "sg:tags":[
        "teacher"
    ],
    "wof:name":"Noosa School Of Rock",
    "wof:placetype":"venue"
},
  "geometry": {"coordinates":[153.04624939000001,-26.4086990356],"type":"Point"}
}