{
  "type": "Feature",
  "properties": {
    "iso:country":"AU",
    "sg:address":"Shop 4/ 516- 520 Henley Beach Rd",
    "sg:city":"Fulham",
    "sg:classifiers":[
        {
            "category":"Restaurant",
            "type":"Food & Drink"
        }
    ],
    "sg:phone":"+61 8 8235 2111",
    "sg:postcode":"5024",
    "sg:province":"SA",
    "sg:tags":[
        "pizza"
    ],
    "wof:name":"Domino's Pizza",
    "wof:placetype":"venue"
},
  "geometry": {"coordinates":[138.516967773,-34.9262046814],"type":"Point"}
}