{
  "type": "Feature",
  "properties": {
    "addr:full":"First Floor Room 2 934 Whitehorse Rd Box Hill VIC 3128",
    "addr:housenumber":"934",
    "addr:postcode":"3128",
    "addr:street":"Whitehorse Rd",
    "iso:country":"AU",
    "sg:address":"First Floor Room 2 934 Whitehorse Rd",
    "sg:city":"Box Hill",
    "sg:classifiers":[
        {
            "category":"Health Services",
            "subcategory":"Dentist",
            "type":"Services"
        }
    ],
    "sg:phone":"+61 3 9898 6999",
    "sg:postcode":"3128",
    "sg:province":"VIC",
    "wof:name":"Lee S P Dr",
    "wof:placetype":"venue"
},
  "geometry": {"coordinates":[145.12278747600001,-37.8182792664],"type":"Point"}
}