{
  "type": "Feature",
  "properties": {
    "iso:country":"AU",
    "sg:address":"2 Gosby Ave",
    "sg:city":"Miranda",
    "sg:classifiers":[
        {
            "category":"Personal",
            "type":"Services"
        }
    ],
    "sg:phone":"+61 2 9531 5643",
    "sg:postcode":"2228",
    "sg:province":"NSW",
    "sg:tags":[
        "reducing",
        "treatment",
        "weight"
    ],
    "wof:name":"Whitaker Elizabeth",
    "wof:placetype":"venue"
},
  "geometry": {"coordinates":[151.09588623100001,-34.0378837585],"type":"Point"}
}