{
  "type": "Feature",
  "properties": {
    "addr:full":"128 Military Rd Guildford NSW 2161",
    "addr:housenumber":"128",
    "addr:postcode":"2161",
    "addr:street":"Military Rd",
    "iso:country":"AU",
    "sg:address":"128 Military Rd",
    "sg:city":"Guildford",
    "sg:classifiers":[
        {
            "category":"Fast Food",
            "type":"Food & Drink"
        }
    ],
    "sg:phone":"+61 2 9681 3129",
    "sg:postcode":"2161",
    "sg:province":"NSW",
    "sg:tags":[
        "away",
        "take"
    ],
    "wof:name":"Guildford West Take Away",
    "wof:placetype":"venue"
},
  "geometry": {"coordinates":[150.98405456500001,-33.8542175293],"type":"Point"}
}