{
  "type": "Feature",
  "properties": {
    "addr:full":"9 Ashby St Whitebridge NSW 2290",
    "addr:housenumber":"9",
    "addr:postcode":"2290",
    "addr:street":"Ashby St",
    "iso:country":"AU",
    "sg:address":"9 Ashby St",
    "sg:city":"Whitebridge",
    "sg:classifiers":[
        {
            "category":"Education",
            "subcategory":"Junior College",
            "type":"Public Place"
        }
    ],
    "sg:phone":"+61 2 4944 8421",
    "sg:postcode":"2290",
    "sg:province":"NSW",
    "sg:tags":[
        "wholesaler",
        "school",
        "mfrs",
        "uniform"
    ],
    "wof:name":"Abel Sportswear",
    "wof:placetype":"venue"
},
  "geometry": {"coordinates":[151.716796875,-32.9821929932],"type":"Point"}
}