{
  "type": "Feature",
  "properties": {
    "iso:country":"AU",
    "sg:address":"Unit 2 / 19A King Edward Rd",
    "sg:city":"Osborne Park",
    "sg:classifiers":[
        {
            "category":"Building & Trades",
            "subcategory":"Construction",
            "type":"Services"
        }
    ],
    "sg:phone":"+61 8 9204 3300",
    "sg:postcode":"6017",
    "sg:province":"WA",
    "sg:tags":[
        "scaffolding"
    ],
    "wof:name":"ADV Scaffold",
    "wof:placetype":"venue"
},
  "geometry": {"coordinates":[115.806106567,-31.9024753571],"type":"Point"}
}