{
  "type": "Feature",
  "properties": {
    "addr:full":"76 Corrys Rd Thurgoona NSW 2640",
    "addr:housenumber":"76",
    "addr:postcode":"2640",
    "addr:street":"Corrys Rd",
    "iso:country":"AU",
    "sg:address":"76 Corrys Rd",
    "sg:city":"Thurgoona",
    "sg:classifiers":[
        {
            "category":"Real Estate",
            "subcategory":"Real Estate Agent",
            "type":"Services"
        }
    ],
    "sg:phone":"+61 2 6043 2728",
    "sg:postcode":"2640",
    "sg:province":"NSW",
    "sg:tags":[
        "handyman's",
        "equipment",
        "hire",
        "builders",
        "contractor"
    ],
    "wof:name":"Tara Earthmoving",
    "wof:placetype":"venue"
},
  "geometry": {"coordinates":[146.97186279300001,-36.0542259216],"type":"Point"}
}