{
  "type": "Feature",
  "properties": {
    "iso:country":"AU",
    "sg:address":"5 Clark St",
    "sg:city":"Dunsborough",
    "sg:classifiers":[
        {
            "category":"Retail",
            "subcategory":"Veterinary Services",
            "type":"Services"
        }
    ],
    "sg:phone":"+61 8 9755 3931",
    "sg:postcode":"6281",
    "sg:province":"WA",
    "sg:tags":[
        "surgeon"
    ],
    "wof:name":"Dunsborough Veterinary Hospital",
    "wof:placetype":"venue"
},
  "geometry": {"coordinates":[115.104110718,-33.6143417358],"type":"Point"}
}