{
  "type": "Feature",
  "properties": {
    "addr:full":"Shp 4/ 115 High St Woodend VIC 3442",
    "addr:housenumber":"/ 115",
    "addr:postcode":"3442",
    "addr:street":"High St",
    "iso:country":"AU",
    "sg:address":"Shp 4/ 115 High St",
    "sg:city":"Woodend",
    "sg:classifiers":[
        {
            "category":"Fast Food",
            "type":"Food & Drink"
        }
    ],
    "sg:phone":"+61 3 5427 3767",
    "sg:postcode":"3442",
    "sg:province":"VIC",
    "sg:tags":[
        "away",
        "take"
    ],
    "wof:name":"Woodend Bbq Chicken",
    "wof:placetype":"venue"
},
  "geometry": {"coordinates":[144.52874755900001,-37.3548736572],"type":"Point"}
}