{
  "type": "Feature",
  "properties": {
    "addr:full":"Level 12 167 Eagle St Brisbane QLD 4000",
    "addr:housenumber":"167",
    "addr:postcode":"4000",
    "addr:street":"Eagle St",
    "iso:country":"AU",
    "sg:address":"Level 12 167 Eagle St",
    "sg:city":"Brisbane",
    "sg:classifiers":[
        {
            "category":"Health Services",
            "subcategory":"Health Practitioner",
            "type":"Services"
        }
    ],
    "sg:phone":"+61 7 3221 4644",
    "sg:postcode":"4000",
    "sg:province":"QLD",
    "sg:tags":[
        "naturopath"
    ],
    "wof:name":"Advanced Allergy Elimation",
    "wof:placetype":"venue"
},
  "geometry": {"coordinates":[153.03045654300001,-27.4660186768],"type":"Point"}
}