{
  "type": "Feature",
  "properties": {
    "addr:full":"Ste 3/ 16 Salmon St Port Melbourne VIC 3207",
    "addr:housenumber":"16",
    "addr:postcode":"3207",
    "addr:street":"Salmon St",
    "iso:country":"AU",
    "sg:address":"Ste 3/ 16 Salmon St",
    "sg:city":"Port Melbourne",
    "sg:classifiers":[
        {
            "category":"Building & Trades",
            "subcategory":"Construction",
            "type":"Services"
        }
    ],
    "sg:phone":"+61 3 9644 7000",
    "sg:postcode":"3207",
    "sg:province":"VIC",
    "sg:tags":[
        "contractor"
    ],
    "wof:name":"Buxton Group Pty Ltd",
    "wof:placetype":"venue"
},
  "geometry": {"coordinates":[144.92501799999999,-37.834469],"type":"Point"}
}