{
  "type": "Feature",
  "properties": {
    "addr:full":"Old Coast Rd Wannanup WA 6210",
    "addr:postcode":"6210",
    "addr:street":"Coast Rd",
    "iso:country":"AU",
    "sg:address":"Old Coast Rd",
    "sg:city":"Wannanup",
    "sg:classifiers":[
        {
            "category":"Retail",
            "subcategory":"Veterinary Services",
            "type":"Services"
        }
    ],
    "sg:phone":"+61 8 9582 2000",
    "sg:postcode":"6210",
    "sg:province":"WA",
    "sg:tags":[
        "surgeon"
    ],
    "wof:name":"Mandurah South Veterinary Hospital",
    "wof:placetype":"venue"
},
  "geometry": {"coordinates":[115.64666699999999,-32.599506],"type":"Point"}
}