{
  "type": "Feature",
  "properties": {
    "addr:full":"5 Wellington St Baradine NSW 2396",
    "addr:housenumber":"5",
    "addr:postcode":"2396",
    "addr:street":"Wellington St",
    "iso:country":"AU",
    "sg:address":"5 Wellington St",
    "sg:city":"Baradine",
    "sg:classifiers":[
        {
            "category":"Communications",
            "subcategory":"News Services",
            "type":"Services"
        }
    ],
    "sg:phone":"+61 2 6843 1035",
    "sg:postcode":"2396",
    "sg:province":"NSW",
    "sg:tags":[
        "information",
        "tourist",
        "attractions"
    ],
    "wof:name":"Camp Cypress",
    "wof:placetype":"venue"
},
  "geometry": {"coordinates":[149.068847656,-30.9497451782],"type":"Point"}
}