{
  "type": "Feature",
  "properties": {
    "addr:full":"19 Dunoon St Colac VIC 3250",
    "addr:housenumber":"19",
    "addr:postcode":"3250",
    "addr:street":"Dunoon St",
    "iso:country":"AU",
    "sg:address":"19 Dunoon St",
    "sg:city":"Colac",
    "sg:classifiers":[
        {
            "category":"Education",
            "subcategory":"Kindergarten",
            "type":"Public Place"
        }
    ],
    "sg:phone":"+61 3 5231 4552",
    "sg:postcode":"3250",
    "sg:province":"VIC",
    "sg:tags":[
        "pre-schools"
    ],
    "wof:name":"Wydinia Kindergarten & Occasional Child Care Centre",
    "wof:placetype":"venue"
},
  "geometry": {"coordinates":[143.57635500000001,-38.345428],"type":"Point"}
}