{
  "type": "Feature",
  "properties": {
    "addr:full":"36 The Groves Rd Bennetts Green NSW 2290",
    "addr:housenumber":"36",
    "addr:postcode":"2290",
    "addr:street":"The Groves Rd",
    "iso:country":"AU",
    "sg:address":"36 The Groves Rd",
    "sg:city":"Bennetts Green",
    "sg:classifiers":[
        {
            "category":"Retail",
            "subcategory":"Auto Repair",
            "type":"Services"
        }
    ],
    "sg:phone":"+61 2 4948 8503",
    "sg:postcode":"2290",
    "sg:province":"NSW",
    "sg:tags":[
        "repairer",
        "motor",
        "engineer"
    ],
    "wof:name":"Groves Motors The",
    "wof:placetype":"venue"
},
  "geometry": {"coordinates":[151.68804931599999,-32.9951248169],"type":"Point"}
}