{
  "type": "Feature",
  "properties": {
    "addr:full":"37 Cawthorne St Thebarton SA 5031",
    "addr:housenumber":"37",
    "addr:postcode":"5031",
    "addr:street":"Cawthorne St",
    "iso:country":"AU",
    "sg:address":"37 Cawthorne St",
    "sg:city":"Thebarton",
    "sg:classifiers":[
        {
            "category":"Manufacturing",
            "subcategory":"Food",
            "type":"Manufacturing & Wholesale Goods"
        }
    ],
    "sg:phone":"+61 8 8352 3094",
    "sg:postcode":"5031",
    "sg:province":"SA",
    "sg:tags":[
        "function",
        "catering"
    ],
    "wof:name":"Premium Wines Direct",
    "wof:placetype":"venue"
},
  "geometry": {"coordinates":[138.57496643100001,-34.9123802185],"type":"Point"}
}