{
  "type": "Feature",
  "properties": {
    "addr:full":"64 Smith St Darwin NT 0800",
    "addr:housenumber":"64",
    "addr:postcode":"nt 0800",
    "addr:street":"Smith St",
    "iso:country":"AU",
    "sg:address":"64 Smith St",
    "sg:city":"Darwin",
    "sg:classifiers":[
        {
            "category":"Manufacturing",
            "subcategory":"Food",
            "type":"Manufacturing & Wholesale Goods"
        }
    ],
    "sg:phone":"+61 8 8941 3110",
    "sg:postcode":"0800",
    "sg:province":"NT",
    "sg:tags":[
        "function",
        "catering"
    ],
    "wof:name":"Giuseppes Italian & Seafood Restaurant",
    "wof:placetype":"venue"
},
  "geometry": {"coordinates":[130.840866089,-12.462012291],"type":"Point"}
}