{
  "type": "Feature",
  "properties": {
    "addr:full":"King St Whyalla Playford SA 5600",
    "addr:postcode":"5600",
    "addr:street":"King St",
    "iso:country":"AU",
    "sg:address":"King St",
    "sg:city":"Whyalla Playford",
    "sg:classifiers":[
        {
            "category":"Manufacturing",
            "subcategory":"Rubber & Plastics",
            "type":"Manufacturing & Wholesale Goods"
        }
    ],
    "sg:phone":"+61 8 8645 0444",
    "sg:postcode":"5600",
    "sg:province":"SA",
    "sg:tags":[
        "wholesaler",
        "product",
        "mfrs"
    ],
    "wof:name":"Specialised Tyre & Rubber Repairers",
    "wof:placetype":"venue"
},
  "geometry": {"coordinates":[137.55543499999999,-33.036049],"type":"Point"}
}