{
  "type": "Feature",
  "properties": {
    "iso:country":"AU",
    "sg:address":"3/ 201 Fore Shore Drv",
    "sg:city":"Geraldton",
    "sg:classifiers":[
        {
            "category":"Real Estate",
            "subcategory":"Real Estate Agent",
            "type":"Services"
        }
    ],
    "sg:phone":"+61 8 9965 7600",
    "sg:postcode":"6530",
    "sg:province":"WA",
    "wof:name":"Ray White Real Estate",
    "wof:placetype":"venue"
},
  "geometry": {"coordinates":[114.611328125,-28.7696552277],"type":"Point"}
}