{
  "type": "Feature",
  "properties": {
    "iso:country":"AU",
    "sg:address":"754 Queensberry St",
    "sg:city":"North Melbourne",
    "sg:classifiers":[
        {
            "category":"Shopping",
            "subcategory":"Computers & Home Electronics",
            "type":"Retail Goods"
        }
    ],
    "sg:phone":"+61 3 8379 3333",
    "sg:postcode":"3051",
    "sg:province":"VIC",
    "sg:tags":[
        "hardware",
        "equipment"
    ],
    "wof:name":"TPG",
    "wof:placetype":"venue"
},
  "geometry": {"coordinates":[144.94212341299999,-37.8020095825],"type":"Point"}
}