{
  "type": "Feature",
  "properties": {
    "addr:full":"U4 / 4 Enterprise Cl Gosford West NSW 2250",
    "addr:housenumber":"4",
    "addr:postcode":"2250",
    "addr:street":"U4 /;Enterprise Cl Gosford West",
    "iso:country":"AU",
    "sg:address":"U4",
    "sg:city":"/ 4 Enterprise Cl Gosford West",
    "sg:classifiers":[
        {
            "category":"Autos & Motor Vehicles",
            "subcategory":"Auto Supplies",
            "type":"Retail Goods"
        }
    ],
    "sg:phone":"+61 2 4324 6662",
    "sg:postcode":"2250",
    "sg:province":"NSW",
    "sg:tags":[
        "transmission",
        "equipment",
        "power"
    ],
    "wof:name":"GB Power Transmission",
    "wof:placetype":"venue"
},
  "geometry": {"coordinates":[151.38226318400001,-33.3467292786],"type":"Point"}
}