{
  "type": "Feature",
  "properties": {
    "iso:country":"AU",
    "sg:address":"9 Naelcm",
    "sg:city":"Killarney Vale",
    "sg:phone":"+61 2 4388 2036",
    "sg:postcode":"2261",
    "sg:province":"NSW",
    "sg:website":"http://www.tankinstallations.com.au",
    "wof:name":"Central Coast Tank Installations",
    "wof:placetype":"venue"
},
  "geometry": {"coordinates":[151.469208,-33.36668],"type":"Point"}
}