{
  "type": "Feature",
  "properties": {
    "addr:full":"PO Box 110 Concord NSW 2137",
    "addr:postcode":"2137",
    "iso:country":"AU",
    "sg:address":"PO Box 110",
    "sg:city":"Concord",
    "sg:classifiers":[
        {
            "category":"Sports & Exercise",
            "subcategory":"Gym",
            "type":"Entertainment"
        }
    ],
    "sg:phone":"+61 418 940 213",
    "sg:postcode":"2137",
    "sg:province":"NSW",
    "sg:tags":[
        "health",
        "fitness"
    ],
    "wof:name":"Unlimited Potential",
    "wof:placetype":"venue"
},
  "geometry": {"coordinates":[151.10325622600001,-33.8560791016],"type":"Point"}
}