{
  "type": "Feature",
  "properties": {
    "addr:full":"60 Panorama Drv Tweed Heads NSW 2485",
    "addr:housenumber":"60",
    "addr:postcode":"2485",
    "addr:street":"Panorama Drv",
    "iso:country":"AU",
    "sg:address":"60 Panorama Drv",
    "sg:city":"Tweed Heads",
    "sg:classifiers":[
        {
            "category":"Building & Trades",
            "subcategory":"Construction",
            "type":"Services"
        }
    ],
    "sg:phone":"+61 413 481 212",
    "sg:postcode":"2485",
    "sg:province":"NSW",
    "sg:tags":[
        "joiner",
        "carpenter"
    ],
    "wof:name":"Bob Black Carpenter & Joiner",
    "wof:placetype":"venue"
},
  "geometry": {"coordinates":[153.50390625,-28.1939468384],"type":"Point"}
}