{
  "type": "Feature",
  "properties": {
    "addr:full":"Westfield Fountain Gate, 352 Princes Hwy Fountain Gate VIC 3805",
    "addr:housenumber":"352",
    "addr:postcode":"3805",
    "addr:street":"Gate;Princes Hwy Fountain",
    "iso:country":"AU",
    "sg:address":"Westfield Fountain Gate, 352 Princes Hwy",
    "sg:city":"Fountain Gate",
    "sg:classifiers":[
        {
            "category":"Shopping",
            "subcategory":"Mobile Phones",
            "type":"Retail Goods"
        }
    ],
    "sg:phone":"+61 3 9705 9011",
    "sg:postcode":"3805",
    "sg:province":"VIC",
    "sg:tags":[
        "telephone",
        "accessory"
    ],
    "wof:name":"Fone Zone",
    "wof:placetype":"venue"
},
  "geometry": {"coordinates":[145.30552700000001,-38.0252],"type":"Point"}
}