{
  "type": "Feature",
  "properties": {
    "addr:full":"PO Box 242 Bentleigh VIC 3204",
    "addr:postcode":"3204",
    "iso:country":"AU",
    "sg:address":"PO Box 242",
    "sg:city":"Bentleigh",
    "sg:classifiers":[
        {
            "category":"Real Estate",
            "subcategory":"Real Estate Services",
            "type":"Services"
        }
    ],
    "sg:phone":"+61 3 9576 5457",
    "sg:postcode":"3204",
    "sg:province":"VIC",
    "sg:tags":[
        "listing"
    ],
    "wof:name":"Your Estate.com.au",
    "wof:placetype":"venue"
},
  "geometry": {"coordinates":[145.026962,-37.91193],"type":"Point"}
}