{
  "type": "Feature",
  "properties": {
    "iso:country":"AU",
    "sg:address":"PO Box 205",
    "sg:city":"Prospect",
    "sg:classifiers":[
        {
            "category":"Real Estate",
            "subcategory":"Real Estate Services",
            "type":"Services"
        }
    ],
    "sg:phone":"+61 1300 135 230",
    "sg:postcode":"7250",
    "sg:province":"TAS",
    "sg:tags":[
        "listing"
    ],
    "wof:name":"Private Sale Company The",
    "wof:placetype":"venue"
},
  "geometry": {"coordinates":[147.13926696799999,-41.4683914185],"type":"Point"}
}