{
  "type": "Feature",
  "properties": {
    "addr:full":"Suite 1/ 76 Woodlark St Lismore NSW 2480",
    "addr:housenumber":"76",
    "addr:postcode":"2480",
    "addr:street":"Woodlark St",
    "iso:country":"AU",
    "sg:address":"Suite 1/ 76 Woodlark St",
    "sg:city":"Lismore",
    "sg:classifiers":[
        {
            "category":"Organizations",
            "subcategory":"Labor Organization",
            "type":"Services"
        }
    ],
    "sg:phone":"+61 2 6621 3187",
    "sg:postcode":"2480",
    "sg:province":"NSW",
    "sg:tags":[
        "union"
    ],
    "wof:name":"Community & Public Sector Union",
    "wof:placetype":"venue"
},
  "geometry": {"coordinates":[153.278640747,-28.8072071075],"type":"Point"}
}