{
  "type": "Feature",
  "properties": {
    "addr:full":"685 Hunter St Newcastle West NSW 2302",
    "addr:housenumber":"685",
    "addr:postcode":"2302",
    "addr:street":"Hunter St",
    "iso:country":"AU",
    "sg:address":"685 Hunter St",
    "sg:city":"Newcastle West",
    "sg:classifiers":[
        {
            "category":"Shopping",
            "subcategory":"Clothing, Apparel, & Fashions",
            "type":"Retail Goods"
        }
    ],
    "sg:phone":"+61 2 4929 6699",
    "sg:postcode":"2302",
    "sg:province":"NSW",
    "sg:tags":[
        "lingerie",
        "hosiery",
        "sleepwear"
    ],
    "wof:name":"Vibes Lingerie",
    "wof:placetype":"venue"
},
  "geometry": {"coordinates":[151.76243600000001,-32.92654],"type":"Point"}
}