{
  "type": "Feature",
  "properties": {
    "iso:country":"AU",
    "sg:address":"6 Lomond Crt",
    "sg:city":"Varsity Lakes",
    "sg:classifiers":[
        {
            "category":"Building & Trades",
            "subcategory":"Construction",
            "type":"Services"
        }
    ],
    "sg:phone":"+61 417 752 080",
    "sg:postcode":"4226",
    "sg:province":"QLD",
    "sg:tags":[
        "roof"
    ],
    "wof:name":"Sid's Roofing",
    "wof:placetype":"venue"
},
  "geometry": {"coordinates":[153.42062377900001,-28.0874729156],"type":"Point"}
}