{
  "type": "Feature",
  "properties": {
    "iso:country":"AU",
    "sg:address":"Level 7 KPMG Centre 111 Phillip St",
    "sg:city":"Parramatta",
    "sg:classifiers":[
        {
            "category":"Education",
            "subcategory":"Special Training",
            "type":"Public Place"
        }
    ],
    "sg:phone":"+61 2 9891 5688",
    "sg:postcode":"2150",
    "sg:province":"NSW",
    "sg:tags":[
        "development"
    ],
    "wof:name":"C.I.M. Critical Incident Management Services",
    "wof:placetype":"venue"
},
  "geometry": {"coordinates":[151.211212158,-33.8666992188],"type":"Point"}
}