{
  "type": "Feature",
  "properties": {
    "addr:full":"2 Fielman Drv Leda WA 6170",
    "addr:housenumber":"2",
    "addr:postcode":"6170",
    "addr:street":"Fielman Drv",
    "iso:country":"AU",
    "sg:address":"2 Fielman Drv",
    "sg:city":"Leda",
    "sg:classifiers":[
        {
            "category":"Food & Beverages",
            "subcategory":"Groceries & Convenience Stores",
            "type":"Retail Goods"
        }
    ],
    "sg:phone":"+61 8 9439 3661",
    "sg:postcode":"6170",
    "sg:province":"WA",
    "wof:name":"Quix Food Stores",
    "wof:placetype":"venue"
},
  "geometry": {"coordinates":[115.80645800000001,-32.260155],"type":"Point"}
}