{
  "type": "Feature",
  "properties": {
    "iso:country":"AU",
    "sg:address":"15 Dinterra Ave",
    "sg:city":"Ferny Hills",
    "sg:classifiers":[
        {
            "category":"Building & Trades",
            "subcategory":"Landscaping Services",
            "type":"Services"
        }
    ],
    "sg:phone":"+61 7 3351 3219",
    "sg:postcode":"4055",
    "sg:province":"QLD",
    "sg:tags":[
        "designer",
        "landscape",
        "contractor"
    ],
    "wof:name":"Landscaping Adventures",
    "wof:placetype":"venue"
},
  "geometry": {"coordinates":[152.947265625,-27.4002723694],"type":"Point"}
}