{
  "type": "Feature",
  "properties": {
    "addr:full":"94 Cubitt St Richmond VIC 3121",
    "addr:housenumber":"94",
    "addr:postcode":"3121",
    "addr:street":"Cubitt St",
    "iso:country":"AU",
    "sg:address":"94 Cubitt St",
    "sg:city":"Richmond",
    "sg:classifiers":[
        {
            "category":"Home & Garden",
            "subcategory":"Carpets & Floor Coverings",
            "type":"Retail Goods"
        }
    ],
    "sg:phone":"+61 3 9421 0880",
    "sg:postcode":"3121",
    "sg:province":"VIC",
    "sg:tags":[
        "flooring",
        "parquet"
    ],
    "wof:name":"True Grid Flooring",
    "wof:placetype":"venue"
},
  "geometry": {"coordinates":[144.9921875,-37.8289642334],"type":"Point"}
}