{
  "type": "Feature",
  "properties": {
    "iso:country":"AU",
    "sg:address":"14 Wild Fire Crt",
    "sg:city":"Robina",
    "sg:classifiers":[
        {
            "category":"Building & Trades",
            "subcategory":"Cleaning & Sanitation",
            "type":"Services"
        }
    ],
    "sg:phone":"+61 1300 651 659",
    "sg:postcode":"4226",
    "sg:province":"QLD",
    "sg:tags":[
        "cleaner",
        "repairer",
        "roof"
    ],
    "wof:name":"Gutter Solutions",
    "wof:placetype":"venue"
},
  "geometry": {"coordinates":[153.39378356899999,-28.0808238983],"type":"Point"}
}