{
  "type": "Feature",
  "properties": {
    "iso:country":"AU",
    "sg:address":"640 Beenak Rd",
    "sg:city":"Seville",
    "sg:classifiers":[
        {
            "category":"Professional",
            "subcategory":"Accounting & Tax Preparation",
            "type":"Services"
        }
    ],
    "sg:phone":"+61 3 5964 8588",
    "sg:postcode":"3139",
    "sg:province":"VIC",
    "sg:tags":[
        "accountant",
        "auditor"
    ],
    "wof:name":"Leafield Accounting Services",
    "wof:placetype":"venue"
},
  "geometry": {"coordinates":[145.48562622099999,-37.8064346313],"type":"Point"}
}