{
  "type": "Feature",
  "properties": {
    "iso:country":"AU",
    "sg:address":"Shop 5 15 Cross St",
    "sg:city":"Double Bay",
    "sg:classifiers":[
        {
            "category":"Personal",
            "subcategory":"Beauty Salon",
            "type":"Services"
        }
    ],
    "sg:phone":"+61 2 9328 9511",
    "sg:postcode":"2028",
    "sg:province":"NSW",
    "sg:tags":[
        "hairdresser"
    ],
    "wof:name":"Sandys Hairdressing",
    "wof:placetype":"venue"
},
  "geometry": {"coordinates":[151.244049072,-33.8765296936],"type":"Point"}
}