{
  "type": "Feature",
  "properties": {
    "addr:full":"29 Rudloc Rd Morley WA 6062",
    "addr:housenumber":"29",
    "addr:postcode":"6062",
    "addr:street":"Rudloc Rd",
    "iso:country":"AU",
    "sg:address":"29 Rudloc Rd",
    "sg:city":"Morley",
    "sg:classifiers":[
        {
            "category":"Home & Garden",
            "subcategory":"Building Materials",
            "type":"Retail Goods"
        }
    ],
    "sg:phone":"+61 8 9375 5566",
    "sg:postcode":"6062",
    "sg:province":"WA",
    "sg:tags":[
        "merchant",
        "glass",
        "glazier"
    ],
    "wof:name":"Mt Lawley 24hr Glass",
    "wof:placetype":"venue"
},
  "geometry": {"coordinates":[115.897743225,-31.9007415771],"type":"Point"}
}