{
  "type": "Feature",
  "properties": {
    "addr:full":"22 Hall Rd Gympie QLD 4570",
    "addr:housenumber":"22",
    "addr:postcode":"4570",
    "addr:street":"Hall Rd",
    "iso:country":"AU",
    "sg:address":"22 Hall Rd",
    "sg:city":"Gympie",
    "sg:classifiers":[
        {
            "category":"Shopping",
            "type":"Retail Goods"
        }
    ],
    "sg:phone":"+61 7 5482 1021",
    "sg:postcode":"4570",
    "sg:province":"QLD",
    "sg:tags":[
        "equipment",
        "safety",
        "accessory"
    ],
    "wof:name":"Gympie Safety Shop",
    "wof:placetype":"venue"
},
  "geometry": {"coordinates":[152.691314697,-26.2240543365],"type":"Point"}
}