{
  "type": "Feature",
  "properties": {
    "addr:full":"12 Pirie St Adelaide SA 5000",
    "addr:housenumber":"12",
    "addr:postcode":"5000",
    "addr:street":"Pirie St",
    "iso:country":"AU",
    "sg:address":"12 Pirie St",
    "sg:city":"Adelaide",
    "sg:classifiers":[
        {
            "category":"Health Services",
            "subcategory":"Health Practitioner",
            "type":"Services"
        }
    ],
    "sg:phone":"+61 8 8461 4444",
    "sg:postcode":"5000",
    "sg:province":"SA",
    "sg:tags":[
        "psychologist"
    ],
    "wof:name":"Speakman Stillwell & Associates Pty Ltd",
    "wof:placetype":"venue"
},
  "geometry": {"coordinates":[138.60008239699999,-34.9256324768],"type":"Point"}
}