{
  "type": "Feature",
  "properties": {
    "addr:full":"Shop1, 16 Central Park Ave Ashmore QLD 4214",
    "addr:housenumber":"16",
    "addr:postcode":"4214",
    "addr:street":"Central Park Ave",
    "iso:country":"AU",
    "sg:address":"Shop1, 16 Central Park Ave",
    "sg:city":"Ashmore",
    "sg:classifiers":[
        {
            "category":"Shopping",
            "subcategory":"Computers & Home Electronics",
            "type":"Retail Goods"
        }
    ],
    "sg:phone":"+61 7 5597 4214",
    "sg:postcode":"4214",
    "sg:province":"QLD",
    "sg:tags":[
        "equipment",
        "supply"
    ],
    "wof:name":"IT Warehouse",
    "wof:placetype":"venue"
},
  "geometry": {"coordinates":[153.35984802199999,-27.987657547],"type":"Point"}
}