{
  "type": "Feature",
  "properties": {
    "addr:full":"PO Box 5664 Port Macquarie NSW 2444",
    "addr:postcode":"2444",
    "iso:country":"AU",
    "sg:address":"PO Box 5664",
    "sg:city":"Port Macquarie",
    "sg:classifiers":[
        {
            "category":"Building & Trades",
            "subcategory":"Construction",
            "type":"Services"
        }
    ],
    "sg:phone":"+61 2 6582 2308",
    "sg:postcode":"2444",
    "sg:province":"NSW",
    "sg:tags":[
        "plasterboard",
        "plasterer",
        "fixer"
    ],
    "wof:name":"Clarke Plastering",
    "wof:placetype":"venue"
},
  "geometry": {"coordinates":[152.90817300000001,-31.4296],"type":"Point"}
}