{
  "type": "Feature",
  "properties": {
    "iso:country":"AU",
    "sg:address":"4 Apprentice Drv",
    "sg:city":"Berkeley Vale",
    "sg:classifiers":[
        {
            "category":"Building & Trades",
            "subcategory":"Landscaping Services",
            "type":"Services"
        }
    ],
    "sg:phone":"+61 412 433 362",
    "sg:postcode":"2261",
    "sg:province":"NSW",
    "sg:tags":[
        "consultant"
    ],
    "wof:name":"J Huntington",
    "wof:placetype":"venue"
},
  "geometry": {"coordinates":[151.422134,-33.328632],"type":"Point"}
}