{
  "type": "Feature",
  "properties": {
    "iso:country":"AU",
    "sg:address":"34 Stephens St",
    "sg:city":"Burleigh Heads",
    "sg:classifiers":[
        {
            "category":"Utilities",
            "subcategory":"Mobile Phone",
            "type":"Services"
        }
    ],
    "sg:phone":"+61 7 5576 0755",
    "sg:postcode":"4220",
    "sg:province":"QLD",
    "sg:tags":[
        "aviation",
        "consultant"
    ],
    "wof:name":"Burleigh Consulting Services Pty Ltd",
    "wof:placetype":"venue"
},
  "geometry": {"coordinates":[153.445922852,-28.0895118713],"type":"Point"}
}