{
  "type": "Feature",
  "properties": {
    "addr:full":"Shop 1 Oxley La Wauchope NSW 2446",
    "addr:housenumber":"shop 1",
    "addr:postcode":"2446",
    "addr:street":"Oxley La",
    "iso:country":"AU",
    "sg:address":"Shop 1 Oxley La",
    "sg:city":"Wauchope",
    "sg:classifiers":[
        {
            "category":"Personal",
            "subcategory":"Beauty Salon",
            "type":"Services"
        }
    ],
    "sg:phone":"+61 2 6585 1992",
    "sg:postcode":"2446",
    "sg:province":"NSW",
    "sg:tags":[
        "hairdresser"
    ],
    "wof:name":"Jennifers Unisex Hair Salon",
    "wof:placetype":"venue"
},
  "geometry": {"coordinates":[152.71142599999999,-31.470337],"type":"Point"}
}