{
  "type": "Feature",
  "properties": {
    "addr:full":"414 Huntly St Footscray VIC 3011",
    "addr:housenumber":"414",
    "addr:postcode":"3011",
    "addr:street":"Huntly St",
    "iso:country":"AU",
    "sg:address":"414 Huntly St",
    "sg:city":"Footscray",
    "sg:classifiers":[
        {
            "category":"Real Estate",
            "subcategory":"Real Estate Operator",
            "type":"Services"
        }
    ],
    "sg:phone":"+61 433 006 677",
    "sg:postcode":"3011",
    "sg:province":"VIC",
    "sg:tags":[
        "concrete",
        "pumping"
    ],
    "wof:name":"Cheap Pumping",
    "wof:placetype":"venue"
},
  "geometry": {"coordinates":[144.89356994600001,-37.8018302917],"type":"Point"}
}