{
  "type": "Feature",
  "properties": {
    "addr:full":"61 Buckley St Marrickville NSW 2204",
    "addr:housenumber":"61",
    "addr:postcode":"2204",
    "addr:street":"Buckley St",
    "iso:country":"AU",
    "sg:address":"61 Buckley St",
    "sg:city":"Marrickville",
    "sg:classifiers":[
        {
            "category":"Shopping",
            "subcategory":"Clothing, Apparel, & Fashions",
            "type":"Retail Goods"
        }
    ],
    "sg:phone":"+61 2 9519 8092",
    "sg:postcode":"2204",
    "sg:province":"NSW",
    "sg:tags":[
        "lingerie",
        "hosiery",
        "sleepwear"
    ],
    "wof:name":"Sock Warehouse Pty Ltd The",
    "wof:placetype":"venue"
},
  "geometry": {"coordinates":[151.163895,-33.914368],"type":"Point"}
}