{
  "type": "Feature",
  "properties": {
    "addr:full":"42 Wilkinson Crs Ingleburn NSW 2565",
    "addr:housenumber":"42",
    "addr:postcode":"2565",
    "addr:street":"Wilkinson Crs",
    "iso:country":"AU",
    "sg:address":"42 Wilkinson Crs",
    "sg:city":"Ingleburn",
    "sg:classifiers":[
        {
            "category":"Professional",
            "subcategory":"Business Services",
            "type":"Services"
        }
    ],
    "sg:phone":"+61 411 162 314",
    "sg:postcode":"2565",
    "sg:province":"NSW",
    "sg:tags":[
        "drafting"
    ],
    "wof:name":"Salvador P",
    "wof:placetype":"venue"
},
  "geometry": {"coordinates":[150.865997314,-33.9984893799],"type":"Point"}
}