{
  "type": "Feature",
  "properties": {
    "addr:full":"94 Long St Smithfield NSW 2164",
    "addr:housenumber":"94",
    "addr:postcode":"2164",
    "addr:street":"Long St",
    "iso:country":"AU",
    "sg:address":"94 Long St",
    "sg:city":"Smithfield",
    "sg:classifiers":[
        {
            "category":"Building & Trades",
            "subcategory":"Cleaning & Sanitation",
            "type":"Services"
        }
    ],
    "sg:phone":"+61 2 9729 4155",
    "sg:postcode":"2164",
    "sg:province":"NSW",
    "sg:tags":[
        "abrasive",
        "blasting"
    ],
    "sg:website":"http://www.ivorycoatings.com.au",
    "wof:name":"Ivorys Special Coatings",
    "wof:placetype":"venue"
},
  "geometry": {"coordinates":[150.93466186500001,-33.8421440125],"type":"Point"}
}