{
  "type": "Feature",
  "properties": {
    "addr:full":"Southwell Park Ellenborough St Lyneham ACT 2602",
    "addr:postcode":"2602",
    "addr:street":"Ellenborough St",
    "iso:country":"AU",
    "sg:address":"Southwell Park Ellenborough St",
    "sg:city":"Lyneham",
    "sg:classifiers":[
        {
            "category":"Arena",
            "subcategory":"Sports Club",
            "type":"Entertainment"
        }
    ],
    "sg:phone":"+61 2 6247 8804",
    "sg:postcode":"2602",
    "sg:province":"ACT",
    "sg:tags":[
        "organisation",
        "sporting"
    ],
    "wof:name":"Australian Capital Territory Tennis Asscn Inc",
    "wof:placetype":"venue"
},
  "geometry": {"coordinates":[149.12663269000001,-35.2428474426],"type":"Point"}
}