{
  "type": "Feature",
  "properties": {
    "addr:full":"8 Sheehan St Eastwood NSW 2122",
    "addr:housenumber":"8",
    "addr:postcode":"2122",
    "addr:street":"Sheehan St",
    "iso:country":"AU",
    "sg:address":"8 Sheehan St",
    "sg:city":"Eastwood",
    "sg:classifiers":[
        {
            "category":"Professional",
            "subcategory":"Computer Services",
            "type":"Services"
        }
    ],
    "sg:phone":"+61 2 9878 2651",
    "sg:postcode":"2122",
    "sg:province":"NSW",
    "sg:tags":[
        "consultant",
        "system"
    ],
    "wof:name":"Becklyn Pty Ltd",
    "wof:placetype":"venue"
},
  "geometry": {"coordinates":[151.099533081,-33.7892837524],"type":"Point"}
}