{
  "type": "Feature",
  "properties": {
    "addr:full":"Johnson & Dowling St Forbes NSW 2871",
    "addr:postcode":"2871",
    "addr:street":"St",
    "iso:country":"AU",
    "sg:address":"Johnson & Dowling St",
    "sg:city":"Forbes",
    "sg:classifiers":[
        {
            "category":"Autos & Motor Vehicles",
            "subcategory":"Fuel & Gas Station",
            "type":"Retail Goods"
        }
    ],
    "sg:phone":"+61 2 6852 2245",
    "sg:postcode":"2871",
    "sg:province":"NSW",
    "wof:name":"BP Australia Limited",
    "wof:placetype":"venue"
},
  "geometry": {"coordinates":[148.01036099999999,-33.381832],"type":"Point"}
}