{
  "type": "Feature",
  "properties": {
    "addr:full":"15 Robusta Pde Taree NSW 2430",
    "addr:housenumber":"15",
    "addr:postcode":"2430",
    "addr:street":"Robusta Pde",
    "iso:country":"AU",
    "sg:address":"15 Robusta Pde",
    "sg:city":"Taree",
    "sg:classifiers":[
        {
            "category":"Professional",
            "subcategory":"Computer Services",
            "type":"Services"
        }
    ],
    "sg:phone":"+61 2 6551 0189",
    "sg:postcode":"2430",
    "sg:province":"NSW",
    "sg:tags":[
        "repairs",
        "upgrade",
        "equipment"
    ],
    "wof:name":"Darson Computers",
    "wof:placetype":"venue"
},
  "geometry": {"coordinates":[152.45185900000001,-31.892338],"type":"Point"}
}