{
  "type": "Feature",
  "properties": {
    "iso:country":"AU",
    "sg:address":"PO Box 789",
    "sg:city":"Sunnybank",
    "sg:classifiers":[
        {
            "category":"Professional",
            "subcategory":"Employment Agencies",
            "type":"Services"
        }
    ],
    "sg:phone":"+61 7 3344 1967",
    "sg:postcode":"4109",
    "sg:province":"QLD",
    "sg:tags":[
        "provider",
        "internet"
    ],
    "wof:name":"EZ ADSL",
    "wof:placetype":"venue"
},
  "geometry": {"coordinates":[153.061157227,-27.5790500641],"type":"Point"}
}