{
  "type": "Feature",
  "properties": {
    "addr:full":"4 Lloyd George St Eastern Heights QLD 4305",
    "addr:housenumber":"4",
    "addr:postcode":"4305",
    "addr:street":"Lloyd George St",
    "iso:country":"AU",
    "sg:address":"4 Lloyd George St",
    "sg:city":"Eastern Heights",
    "sg:classifiers":[
        {
            "category":"Professional",
            "subcategory":"Engineering",
            "type":"Services"
        }
    ],
    "sg:phone":"+61 7 3810 0000",
    "sg:postcode":"4305",
    "sg:province":"QLD",
    "sg:tags":[
        "consulting",
        "engineer"
    ],
    "wof:name":"Kobold Systems",
    "wof:placetype":"venue"
},
  "geometry": {"coordinates":[152.769287109,-27.6281852722],"type":"Point"}
}