{
  "type": "Feature",
  "properties": {
    "addr:full":"Shop 1 122 High St Mansfield VIC 3722",
    "addr:housenumber":"shop 1 122",
    "addr:postcode":"3722",
    "addr:street":"High St",
    "iso:country":"AU",
    "sg:address":"Shop 1 122 High St",
    "sg:city":"Mansfield",
    "sg:classifiers":[
        {
            "category":"Fast Food",
            "type":"Food & Drink"
        }
    ],
    "sg:phone":"+61 3 5775 1388",
    "sg:postcode":"3722",
    "sg:province":"VIC",
    "sg:tags":[
        "away",
        "take"
    ],
    "wof:name":"Red's Authentic Charcoal Chicken",
    "wof:placetype":"venue"
},
  "geometry": {"coordinates":[146.084884644,-37.0520591736],"type":"Point"}
}