{
  "type": "Feature",
  "properties": {
    "iso:country":"AU",
    "sg:address":"334 Karrinyup Rd",
    "sg:city":"Karrinyup",
    "sg:classifiers":[
        {
            "category":"Personal",
            "subcategory":"Massage",
            "type":"Services"
        }
    ],
    "sg:phone":"+61 8 9446 4809",
    "sg:postcode":"6018",
    "sg:province":"WA",
    "sg:tags":[
        "therapy"
    ],
    "wof:name":"Active Care Massage",
    "wof:placetype":"venue"
},
  "geometry": {"coordinates":[115.770782471,-31.8734512329],"type":"Point"}
}