{
  "type": "Feature",
  "properties": {
    "iso:country":"AU",
    "sg:address":"Heath Rd",
    "sg:city":"Alice Springs",
    "sg:classifiers":[
        {
            "category":"Professional",
            "subcategory":"Research",
            "type":"Services"
        }
    ],
    "sg:phone":"+61 8 8950 7162",
    "sg:postcode":"0870",
    "sg:province":"NT",
    "sg:tags":[
        "industrial",
        "scientific"
    ],
    "wof:name":"Desert Knowledge Cooperative Research Centre",
    "wof:placetype":"venue"
},
  "geometry": {"coordinates":[133.878341675,-23.7560634613],"type":"Point"}
}