{
  "type": "Feature",
  "properties": {
    "addr:full":"92a Double Jump Rd Redland Bay QLD 4165",
    "addr:housenumber":"92a",
    "addr:postcode":"4165",
    "addr:street":"Double Jump Rd",
    "iso:country":"AU",
    "sg:address":"92a Double Jump Rd",
    "sg:city":"Redland Bay",
    "sg:classifiers":[
        {
            "category":"Retail",
            "subcategory":"Auto Repair",
            "type":"Services"
        }
    ],
    "sg:phone":"+61 7 3206 6477",
    "sg:postcode":"4165",
    "sg:province":"QLD",
    "sg:tags":[
        "camper-trailers",
        "caravan",
        "servicing"
    ],
    "wof:name":"Price Custom Caravans & Repairs",
    "wof:placetype":"venue"
},
  "geometry": {"coordinates":[153.261627197,-27.6019077301],"type":"Point"}
}