{
  "type": "Feature",
  "properties": {
    "iso:country":"AU",
    "sg:address":"Ste310/ 431 Sussex St",
    "sg:city":"Sydney",
    "sg:classifiers":[
        {
            "category":"Shopping",
            "subcategory":"Computers & Home Electronics",
            "type":"Retail Goods"
        }
    ],
    "sg:phone":"+61 2 8197 1947",
    "sg:postcode":"2000",
    "sg:province":"NSW",
    "sg:tags":[
        "wholesaler",
        "mfrs",
        "part",
        "electronic"
    ],
    "wof:name":"Vfj Technology Pty Ltd",
    "wof:placetype":"venue"
},
  "geometry": {"coordinates":[151.204711914,-33.8789710999],"type":"Point"}
}