{
  "type": "Feature",
  "properties": {
    "iso:country":"AU",
    "sg:address":"66 Jardine Drv",
    "sg:city":"Springwood",
    "sg:classifiers":[
        {
            "category":"Retail",
            "subcategory":"Storage",
            "type":"Services"
        }
    ],
    "sg:phone":"+61 7 3808 3628",
    "sg:postcode":"4127",
    "sg:province":"QLD",
    "sg:tags":[
        "removal",
        "furniture"
    ],
    "wof:name":"T & S Smith",
    "wof:placetype":"venue"
},
  "geometry": {"coordinates":[153.13734435999999,-27.6218395233],"type":"Point"}
}