{
  "type": "Feature",
  "properties": {
    "addr:full":"9 Ridley Crt Doncaster East VIC 3109",
    "addr:housenumber":"9",
    "addr:postcode":"3109",
    "addr:street":"Ridley Crt",
    "iso:country":"AU",
    "sg:address":"9 Ridley Crt",
    "sg:city":"Doncaster East",
    "sg:classifiers":[
        {
            "category":"Building & Trades",
            "subcategory":"Construction",
            "type":"Services"
        }
    ],
    "sg:phone":"+61 414 550 894",
    "sg:postcode":"3109",
    "sg:province":"VIC",
    "sg:tags":[
        "earth",
        "excavating",
        "moving",
        "contractor"
    ],
    "wof:name":"Montanaro Engineering Pty Ltd",
    "wof:placetype":"venue"
},
  "geometry": {"coordinates":[145.17620849599999,-37.7641143799],"type":"Point"}
}