{
  "type": "Feature",
  "properties": {
    "iso:country":"AU",
    "sg:address":"7b Miller St",
    "sg:city":"Merrylands",
    "sg:classifiers":[
        {
            "category":"Health Services",
            "subcategory":"Doctor",
            "type":"Services"
        }
    ],
    "sg:phone":"+61 2 9637 3060",
    "sg:postcode":"2160",
    "sg:province":"NSW",
    "sg:tags":[
        "medical",
        "practitioner"
    ],
    "wof:name":"Leong D Dr",
    "wof:placetype":"venue"
},
  "geometry": {"coordinates":[150.99017334000001,-33.8371658325],"type":"Point"}
}