{
  "type": "Feature",
  "properties": {
    "addr:full":"35 Oaktree Rd Croydon VIC 3136",
    "addr:housenumber":"35",
    "addr:postcode":"3136",
    "addr:street":"Oaktree Rd",
    "iso:country":"AU",
    "sg:address":"35 Oaktree Rd",
    "sg:city":"Croydon",
    "sg:classifiers":[
        {
            "category":"Wholesale",
            "subcategory":"Toys & Hobbies",
            "type":"Manufacturing & Wholesale Goods"
        }
    ],
    "sg:phone":"+61 3 9723 5153",
    "sg:postcode":"3136",
    "sg:province":"VIC",
    "sg:tags":[
        "mfrs"
    ],
    "wof:name":"Sams Handcrafts",
    "wof:placetype":"venue"
},
  "geometry": {"coordinates":[145.283081055,-37.7797813416],"type":"Point"}
}