{
  "type": "Feature",
  "properties": {
    "addr:full":"21 Marcus Ave Booragoon WA 6154",
    "addr:housenumber":"21",
    "addr:postcode":"6154",
    "addr:street":"Marcus Ave",
    "iso:country":"AU",
    "sg:address":"21 Marcus Ave",
    "sg:city":"Booragoon",
    "sg:classifiers":[
        {
            "category":"Building & Trades",
            "subcategory":"Construction",
            "type":"Services"
        }
    ],
    "sg:phone":"+61 8 9316 2729",
    "sg:postcode":"6154",
    "sg:province":"WA",
    "sg:tags":[
        "contractor"
    ],
    "wof:name":"MTD & Co",
    "wof:placetype":"venue"
},
  "geometry": {"coordinates":[115.83017,-32.043072],"type":"Point"}
}