{
  "type": "Feature",
  "properties": {
    "addr:full":"410 Elizabeth St Melbourne VIC 3000",
    "addr:housenumber":"410",
    "addr:postcode":"3000",
    "addr:street":"Elizabeth St",
    "iso:country":"AU",
    "sg:address":"410 Elizabeth St",
    "sg:city":"Melbourne",
    "sg:classifiers":[
        {
            "category":"Shopping",
            "subcategory":"Antiques",
            "type":"Retail Goods"
        }
    ],
    "sg:phone":"+61 409 829 115",
    "sg:postcode":"3000",
    "sg:province":"VIC",
    "wof:name":"A 1 Cash",
    "wof:placetype":"venue"
},
  "geometry": {"coordinates":[144.96090698200001,-37.8089141846],"type":"Point"}
}