{
  "type": "Feature",
  "properties": {
    "addr:full":"108 Fitzroy St Sale VIC 3850",
    "addr:housenumber":"108",
    "addr:postcode":"3850",
    "addr:street":"Fitzroy St",
    "iso:country":"AU",
    "sg:address":"108 Fitzroy St",
    "sg:city":"Sale",
    "sg:classifiers":[
        {
            "category":"Building & Trades",
            "subcategory":"Plumbing",
            "type":"Services"
        }
    ],
    "sg:phone":"+61 429 314 340",
    "sg:postcode":"3850",
    "sg:province":"VIC",
    "sg:tags":[
        "plumber",
        "gasfitters"
    ],
    "wof:name":"Troy Jeffries Plumbing & Gasfitting",
    "wof:placetype":"venue"
},
  "geometry": {"coordinates":[147.071365356,-38.1010055542],"type":"Point"}
}