{
  "type": "Feature",
  "properties": {
    "addr:full":"9 Cavenagh St Darwin NT 0800",
    "addr:housenumber":"9",
    "addr:postcode":"nt 0800",
    "addr:street":"Cavenagh St",
    "iso:country":"AU",
    "sg:address":"9 Cavenagh St",
    "sg:city":"Darwin",
    "sg:classifiers":[
        {
            "category":"Airline",
            "type":"Transportation"
        }
    ],
    "sg:phone":"+61 1300 365 330",
    "sg:postcode":"0800",
    "sg:province":"NT",
    "sg:tags":[
        "agent"
    ],
    "wof:name":"Garuda Indonesia",
    "wof:placetype":"venue"
},
  "geometry": {"coordinates":[130.84385681099999,-12.4633493423],"type":"Point"}
}