{
  "type": "Feature",
  "properties": {
    "addr:full":"15 Deakin St Traralgon VIC 3844",
    "addr:housenumber":"15",
    "addr:postcode":"3844",
    "addr:street":"Deakin St",
    "iso:country":"AU",
    "sg:address":"15 Deakin St",
    "sg:city":"Traralgon",
    "sg:classifiers":[
        {
            "category":"Home & Garden",
            "subcategory":"Kitchen Supply",
            "type":"Retail Goods"
        }
    ],
    "sg:phone":"+61 3 5174 1475",
    "sg:postcode":"3844",
    "sg:province":"VIC",
    "sg:tags":[
        "sharpening"
    ],
    "wof:name":"Deakin Engineering",
    "wof:placetype":"venue"
},
  "geometry": {"coordinates":[146.534255981,-38.1973686218],"type":"Point"}
}