{
  "type": "Feature",
  "properties": {
    "addr:full":"96 Queen St Woollahra NSW 2025",
    "addr:housenumber":"96",
    "addr:postcode":"2025",
    "addr:street":"Queen St",
    "iso:country":"AU",
    "sg:address":"96 Queen St",
    "sg:city":"Woollahra",
    "sg:classifiers":[
        {
            "category":"Shopping",
            "subcategory":"Antiques",
            "type":"Retail Goods"
        }
    ],
    "sg:phone":"+61 2 9363 4453",
    "sg:postcode":"2025",
    "sg:province":"NSW",
    "wof:name":"Bradshaw W F",
    "wof:placetype":"venue"
},
  "geometry": {"coordinates":[151.23617553700001,-33.8884811401],"type":"Point"}
}