{
  "type": "Feature",
  "properties": {
    "iso:country":"AU",
    "sg:address":"84 Barmah Rd",
    "sg:city":"Wantirna",
    "sg:classifiers":[
        {
            "category":"Building & Trades",
            "subcategory":"Landscaping Services",
            "type":"Services"
        }
    ],
    "sg:phone":"+61 3 9801 9814",
    "sg:postcode":"3152",
    "sg:province":"VIC",
    "sg:tags":[
        "consultant"
    ],
    "wof:name":"Gallagher B & Associates Pty Ltd",
    "wof:placetype":"venue"
},
  "geometry": {"coordinates":[145.21925354000001,-37.8568916321],"type":"Point"}
}