{
  "type": "Feature",
  "properties": {
    "addr:full":"432 Elizabeth St North Hobart TAS 7000",
    "addr:housenumber":"432",
    "addr:postcode":"7000",
    "addr:street":"Elizabeth St",
    "iso:country":"AU",
    "sg:address":"432 Elizabeth St",
    "sg:city":"North Hobart",
    "sg:classifiers":[
        {
            "category":"Professional",
            "subcategory":"Employment Agencies",
            "type":"Services"
        }
    ],
    "sg:phone":"+61 1300 367 776",
    "sg:postcode":"7000",
    "sg:province":"TAS",
    "wof:name":"Jobnet Tasmania",
    "wof:placetype":"venue"
},
  "geometry": {"coordinates":[147.31324768100001,-42.8712768555],"type":"Point"}
}