{
  "type": "Feature",
  "properties": {
    "addr:full":"Suite 3, 23 Bentham St Yarralumla ACT 2600",
    "addr:housenumber":"23",
    "addr:postcode":"2600",
    "addr:street":"Bentham St",
    "iso:country":"AU",
    "sg:address":"Suite 3, 23 Bentham St",
    "sg:city":"Yarralumla",
    "sg:classifiers":[
        {
            "category":"Professional",
            "subcategory":"Employment Agencies",
            "type":"Services"
        }
    ],
    "sg:phone":"+61 2 6282 9997",
    "sg:postcode":"2600",
    "sg:province":"ACT",
    "sg:tags":[
        "provider",
        "internet"
    ],
    "wof:name":"Silverscope",
    "wof:placetype":"venue"
},
  "geometry": {"coordinates":[149.097488403,-35.3075294495],"type":"Point"}
}