{
  "type": "Feature",
  "properties": {
    "iso:country":"AU",
    "sg:address":"53 York St",
    "sg:city":"Beenleigh",
    "sg:classifiers":[
        {
            "category":"Health Services",
            "subcategory":"Doctor",
            "type":"Services"
        }
    ],
    "sg:phone":"+61 7 3807 3511",
    "sg:postcode":"4207",
    "sg:province":"QLD",
    "sg:tags":[
        "medical",
        "practitioner"
    ],
    "wof:name":"Ting Anthony S",
    "wof:placetype":"venue"
},
  "geometry": {"coordinates":[153.20132446299999,-27.713722229],"type":"Point"}
}