{
  "type": "Feature",
  "properties": {
    "iso:country":"AU",
    "sg:address":"42 Grafton St",
    "sg:city":"Warwick",
    "sg:classifiers":[
        {
            "category":"Professional",
            "type":"Services"
        }
    ],
    "sg:phone":"+61 7 4661 3169",
    "sg:postcode":"4370",
    "sg:province":"QLD",
    "sg:tags":[
        "spray",
        "painting"
    ],
    "wof:name":"Mid City Paint n'# Detail",
    "wof:placetype":"venue"
},
  "geometry": {"coordinates":[152.032104492,-28.2162189484],"type":"Point"}
}