{
  "type": "Feature",
  "properties": {
    "addr:full":"253 Hoddle St Collingwood VIC 3066",
    "addr:housenumber":"253",
    "addr:postcode":"3066",
    "addr:street":"Hoddle St",
    "iso:country":"AU",
    "sg:address":"253 Hoddle St",
    "sg:city":"Collingwood",
    "sg:classifiers":[
        {
            "category":"Social Services",
            "subcategory":"Child Care",
            "type":"Services"
        }
    ],
    "sg:phone":"+61 3 9205 5581",
    "sg:postcode":"3066",
    "sg:province":"VIC",
    "sg:tags":[
        "support",
        "health"
    ],
    "wof:name":"Maternal & Child Health Centres",
    "wof:placetype":"venue"
},
  "geometry": {"coordinates":[144.992462158,-37.8009109497],"type":"Point"}
}