{
  "type": "Feature",
  "properties": {
    "iso:country":"AU",
    "sg:address":"PO Box 182",
    "sg:city":"Woody Point",
    "sg:classifiers":[
        {
            "category":"Professional",
            "subcategory":"Employment Agencies",
            "type":"Services"
        }
    ],
    "sg:phone":"+61 1300 732 708",
    "sg:postcode":"4019",
    "sg:province":"QLD",
    "sg:tags":[
        "provider",
        "internet"
    ],
    "wof:name":"Bytesite Internet",
    "wof:placetype":"venue"
},
  "geometry": {"coordinates":[153.10220336899999,-27.2587890625],"type":"Point"}
}