{
  "type": "Feature",
  "properties": {
    "addr:full":"U4/ 1 Tooth St Mitchell ACT 2911",
    "addr:housenumber":"1",
    "addr:postcode":"2911",
    "addr:street":"U4 /;Tooth St",
    "iso:country":"AU",
    "sg:address":"U4/ 1 Tooth St",
    "sg:city":"Mitchell",
    "sg:classifiers":[
        {
            "category":"Building & Trades",
            "subcategory":"Construction",
            "type":"Services"
        }
    ],
    "sg:phone":"+61 2 6253 8563",
    "sg:postcode":"2911",
    "sg:province":"ACT",
    "sg:tags":[
        "contractor"
    ],
    "wof:name":"TI Construction",
    "wof:placetype":"venue"
},
  "geometry": {"coordinates":[149.134857178,-35.2107276917],"type":"Point"}
}