{
  "type": "Feature",
  "properties": {
    "addr:full":"418 San Mateo Ave Mildura VIC 3500",
    "addr:housenumber":"418",
    "addr:postcode":"3500",
    "addr:street":"San Mateo Ave",
    "iso:country":"AU",
    "sg:address":"418 San Mateo Ave",
    "sg:city":"Mildura",
    "sg:classifiers":[
        {
            "category":"Professional",
            "subcategory":"Advertising",
            "type":"Services"
        }
    ],
    "sg:phone":"+61 3 5021 0053",
    "sg:postcode":"3500",
    "sg:province":"VIC",
    "sg:tags":[
        "balloon",
        "novelty"
    ],
    "wof:name":"Fish An Things",
    "wof:placetype":"venue"
},
  "geometry": {"coordinates":[142.144042969,-34.2089805603],"type":"Point"}
}