{
  "type": "Feature",
  "properties": {
    "iso:country":"AU",
    "sg:address":"Shop 4, Globe Arcade, Kiewa St",
    "sg:city":"Albury",
    "sg:classifiers":[
        {
            "category":"Building & Trades",
            "subcategory":"Construction",
            "type":"Services"
        }
    ],
    "sg:phone":"+61 1800 012 027",
    "sg:postcode":"2640",
    "sg:province":"NSW",
    "sg:tags":[
        "monumental",
        "mason"
    ],
    "wof:name":"Waites Robson Stonemasons",
    "wof:placetype":"venue"
},
  "geometry": {"coordinates":[146.91502380399999,-36.0800590515],"type":"Point"}
}