{
  "type": "Feature",
  "properties": {
    "addr:full":"5 Anzed Crt Mulgrave VIC 3170",
    "addr:housenumber":"5",
    "addr:postcode":"3170",
    "addr:street":"Anzed Crt",
    "iso:country":"AU",
    "sg:address":"5 Anzed Crt",
    "sg:city":"Mulgrave",
    "sg:classifiers":[
        {
            "category":"Professional",
            "type":"Services"
        }
    ],
    "sg:phone":"+61 3 9561 5566",
    "sg:postcode":"3170",
    "sg:province":"VIC",
    "sg:tags":[
        "shop",
        "fitting"
    ],
    "wof:name":"Muggleton & Roper Pty Ltd",
    "wof:placetype":"venue"
},
  "geometry": {"coordinates":[145.14987182600001,-37.921421051],"type":"Point"}
}