{
  "type": "Feature",
  "properties": {
    "iso:country":"AU",
    "sg:address":"150 Drummond St",
    "sg:city":"Oakleigh",
    "sg:classifiers":[
        {
            "category":"Government",
            "subcategory":"City Hall",
            "type":"Public Place"
        }
    ],
    "sg:phone":"+61 3 9568 7704",
    "sg:postcode":"3166",
    "sg:province":"VIC",
    "wof:name":"Masonic Centre",
    "wof:placetype":"venue"
},
  "geometry": {"coordinates":[145.090133667,-37.8974113464],"type":"Point"}
}