{
  "type": "Feature",
  "properties": {
    "addr:full":"14 Rosewood Pl Evans Head NSW 2473",
    "addr:housenumber":"14",
    "addr:postcode":"2473",
    "addr:street":"Rosewood Pl Evans",
    "iso:country":"AU",
    "sg:address":"14 Rosewood Pl",
    "sg:city":"Evans Head",
    "sg:classifiers":[
        {
            "category":"Building & Trades",
            "subcategory":"Cleaning & Sanitation",
            "type":"Services"
        }
    ],
    "sg:phone":"+61 2 6682 5625",
    "sg:postcode":"2473",
    "sg:province":"NSW",
    "sg:tags":[
        "cleaner",
        "repairer",
        "roof"
    ],
    "wof:name":"P & S Wall Pty Ltd",
    "wof:placetype":"venue"
},
  "geometry": {"coordinates":[153.42378234899999,-29.1082897186],"type":"Point"}
}