{
  "type": "Feature",
  "properties": {
    "addr:full":"Shp3/ 46 Downey St Alexandra VIC 3714",
    "addr:housenumber":"46",
    "addr:postcode":"3714",
    "addr:street":"Downey St",
    "iso:country":"AU",
    "sg:address":"Shp3/ 46 Downey St",
    "sg:city":"Alexandra",
    "sg:classifiers":[
        {
            "category":"Communications",
            "subcategory":"Film & Video Production",
            "type":"Services"
        }
    ],
    "sg:phone":"+61 3 5772 2619",
    "sg:postcode":"3714",
    "sg:province":"VIC",
    "sg:tags":[
        "dvd",
        "library"
    ],
    "wof:name":"Parkside Video",
    "wof:placetype":"venue"
},
  "geometry": {"coordinates":[145.70875549300001,-37.1919517517],"type":"Point"}
}