{
  "type": "Feature",
  "properties": {
    "addr:full":"150 De Kerrilleau Drv Wodonga VIC 3690",
    "addr:housenumber":"150",
    "addr:postcode":"3690",
    "addr:street":"De Kerrilleau Drv",
    "iso:country":"AU",
    "sg:address":"150 De Kerrilleau Drv",
    "sg:city":"Wodonga",
    "sg:classifiers":[
        {
            "category":"Building & Trades",
            "subcategory":"Construction",
            "type":"Services"
        }
    ],
    "sg:phone":"+61 2 6024 7095",
    "sg:postcode":"3690",
    "sg:province":"VIC",
    "sg:tags":[
        "roof"
    ],
    "wof:name":"J.&M. Scammell Roofing",
    "wof:placetype":"venue"
},
  "geometry": {"coordinates":[146.90733337399999,-36.1269798279],"type":"Point"}
}