{
  "type": "Feature",
  "properties": {
    "addr:full":"192 Gray St Hamilton VIC 3300",
    "addr:housenumber":"192",
    "addr:postcode":"3300",
    "addr:street":"Gray St",
    "iso:country":"AU",
    "sg:address":"192 Gray St",
    "sg:city":"Hamilton",
    "sg:classifiers":[
        {
            "category":"Shopping",
            "subcategory":"Crafts & Fabrics",
            "type":"Retail Goods"
        }
    ],
    "sg:phone":"+61 3 5572 1498",
    "sg:postcode":"3300",
    "sg:province":"VIC",
    "sg:tags":[
        "supply"
    ],
    "wof:name":"Golden Spindle",
    "wof:placetype":"venue"
},
  "geometry": {"coordinates":[142.02580261200001,-37.7425842285],"type":"Point"}
}