{
  "type": "Feature",
  "properties": {
    "addr:full":"8 Prospect St Paddington NSW 2021",
    "addr:housenumber":"8",
    "addr:postcode":"2021",
    "addr:street":"Prospect St",
    "iso:country":"AU",
    "sg:address":"8 Prospect St",
    "sg:city":"Paddington",
    "sg:classifiers":[
        {
            "category":"Professional",
            "subcategory":"Art Services",
            "type":"Services"
        }
    ],
    "sg:phone":"+61 419 500 030",
    "sg:postcode":"2021",
    "sg:province":"NSW",
    "wof:name":"Very Nice Group Pty Ltd The",
    "wof:placetype":"venue"
},
  "geometry": {"coordinates":[151.223114014,-33.8832054138],"type":"Point"}
}