{
  "type": "Feature",
  "properties": {
    "iso:country":"AU",
    "sg:address":"Lot3 / Payne St",
    "sg:city":"Cloncurry",
    "sg:classifiers":[
        {
            "category":"Building & Trades",
            "subcategory":"Construction",
            "type":"Services"
        }
    ],
    "sg:phone":"+61 7 4742 0096",
    "sg:postcode":"4824",
    "sg:province":"QLD",
    "sg:tags":[
        "earth",
        "excavating",
        "moving",
        "contractor"
    ],
    "wof:name":"Pratt T C & S D",
    "wof:placetype":"venue"
},
  "geometry": {"coordinates":[140.51217700000001,-20.707001],"type":"Point"}
}