{
  "type": "Feature",
  "properties": {
    "iso:country":"AU",
    "sg:address":"517 Regency Rd",
    "sg:city":"Sefton Park",
    "sg:classifiers":[
        {
            "category":"Health Services",
            "subcategory":"Doctor",
            "type":"Services"
        }
    ],
    "sg:phone":"+61 8 8269 1900",
    "sg:postcode":"5083",
    "sg:province":"SA",
    "sg:tags":[
        "medical",
        "practitioner"
    ],
    "wof:name":"Mauviel Ashley",
    "wof:placetype":"venue"
},
  "geometry": {"coordinates":[138.60601806599999,-34.8735580444],"type":"Point"}
}