{
  "type": "Feature",
  "properties": {
    "addr:full":"39 Sorrell St North Parramatta NSW 2151",
    "addr:housenumber":"39",
    "addr:postcode":"2151",
    "addr:street":"Sorrell St",
    "iso:country":"AU",
    "sg:address":"39 Sorrell St",
    "sg:city":"North Parramatta",
    "sg:classifiers":[
        {
            "category":"Building & Trades",
            "subcategory":"Construction",
            "type":"Services"
        }
    ],
    "sg:phone":"+61 2 9683 4249",
    "sg:postcode":"2151",
    "sg:province":"NSW",
    "sg:tags":[
        "roof"
    ],
    "wof:name":"H W Pristor",
    "wof:placetype":"venue"
},
  "geometry": {"coordinates":[151.007415772,-33.805721283],"type":"Point"}
}