{
  "type": "Feature",
  "properties": {
    "addr:full":"Crowdy Rd Crowdy Head NSW 2427",
    "addr:postcode":"2427",
    "addr:street":"Crowdy Rd Crowdy",
    "iso:country":"AU",
    "sg:address":"Crowdy Rd",
    "sg:city":"Crowdy Head",
    "sg:classifiers":[
        {
            "category":"Arena",
            "subcategory":"Sports Club",
            "type":"Entertainment"
        }
    ],
    "sg:phone":"+61 2 6556 1325",
    "sg:postcode":"2427",
    "sg:province":"NSW",
    "sg:tags":[
        "life",
        "surfing",
        "saving"
    ],
    "wof:name":"Crowdy Head Surf Life Saving Club House",
    "wof:placetype":"venue"
},
  "geometry": {"coordinates":[152.69667100000001,-31.868044],"type":"Point"}
}