{
  "type": "Feature",
  "properties": {
    "addr:full":"261 Charles St Launceston TAS 7250",
    "addr:housenumber":"261",
    "addr:postcode":"7250",
    "addr:street":"Charles St",
    "iso:country":"AU",
    "sg:address":"261 Charles St",
    "sg:city":"Launceston",
    "sg:classifiers":[
        {
            "category":"Health Services",
            "subcategory":"Dentist",
            "type":"Services"
        }
    ],
    "sg:phone":"+61 3 6334 8840",
    "sg:postcode":"7250",
    "sg:province":"TAS",
    "wof:name":"Alexander A D",
    "wof:placetype":"venue"
},
  "geometry": {"coordinates":[147.14219665499999,-41.4444465637],"type":"Point"}
}