{
  "type": "Feature",
  "properties": {
    "addr:full":"Cnr Blackburn Rd & Burwood Highway Burwood East VIC 3151",
    "addr:postcode":"3151",
    "addr:street":"Cnr Blackburn Rd & Burwood Highway",
    "iso:country":"AU",
    "sg:address":"Cnr Blackburn Rd",
    "sg:city":"& Burwood Highway Burwood East",
    "sg:classifiers":[
        {
            "category":"Retail",
            "subcategory":"Auto Rental",
            "type":"Services"
        }
    ],
    "sg:phone":"+61 3 9887 9800",
    "sg:postcode":"3151",
    "sg:province":"VIC",
    "sg:tags":[
        "bus",
        "truck"
    ],
    "wof:name":"Mobil",
    "wof:placetype":"venue"
},
  "geometry": {"coordinates":[145.151687622,-37.85364151],"type":"Point"}
}