{
  "type": "Feature",
  "properties": {
    "addr:full":"13 Maude Ave Doncaster East VIC 3109",
    "addr:housenumber":"13",
    "addr:postcode":"3109",
    "addr:street":"Maude Ave",
    "iso:country":"AU",
    "sg:address":"13 Maude Ave",
    "sg:city":"Doncaster East",
    "sg:classifiers":[
        {
            "category":"Home & Garden",
            "subcategory":"Carpets & Floor Coverings",
            "type":"Retail Goods"
        }
    ],
    "sg:phone":"+61 413 756 445",
    "sg:postcode":"3109",
    "sg:province":"VIC",
    "sg:tags":[
        "layer"
    ],
    "wof:name":"Sodlers Flooring",
    "wof:placetype":"venue"
},
  "geometry": {"coordinates":[145.165939331,-37.7927513123],"type":"Point"}
}