{
  "type": "Feature",
  "properties": {
    "addr:full":"14 Tallarook St Seymour VIC 3660",
    "addr:housenumber":"14",
    "addr:postcode":"3660",
    "addr:street":"Tallarook St",
    "iso:country":"AU",
    "sg:address":"14 Tallarook St",
    "sg:city":"Seymour",
    "sg:classifiers":[
        {
            "category":"Taxi",
            "type":"Transportation"
        }
    ],
    "sg:phone":"+61 3 5792 1644",
    "sg:postcode":"3660",
    "sg:province":"VIC",
    "sg:tags":[
        "truck"
    ],
    "wof:name":"Seymour Taxi Service",
    "wof:placetype":"venue"
},
  "geometry": {"coordinates":[145.133911133,-37.0248527527],"type":"Point"}
}