{
  "type": "Feature",
  "properties": {
    "iso:country":"AU",
    "sg:address":"Cnr Bunda & Spence Sts",
    "sg:city":"Cairns",
    "sg:classifiers":[
        {
            "category":"Travel",
            "subcategory":"Hotels & Motels",
            "type":"Entertainment"
        }
    ],
    "sg:phone":"+61 7 4051 2008",
    "sg:postcode":"4870",
    "sg:province":"QLD",
    "sg:tags":[
        "accommodation"
    ],
    "wof:name":"Cape York Hotel",
    "wof:placetype":"venue"
},
  "geometry": {"coordinates":[145.775512695,-16.9311943054],"type":"Point"}
}