{
  "type": "Feature",
  "properties": {
    "addr:full":"Lot 2404 Stuart Hwy Pinelands NT 0829",
    "addr:housenumber":"2404",
    "addr:postcode":"nt 0829",
    "addr:street":"Stuart Hwy",
    "iso:country":"AU",
    "sg:address":"Lot 2404 Stuart Hwy",
    "sg:city":"Pinelands",
    "sg:classifiers":[
        {
            "category":"Building & Trades",
            "subcategory":"Equipment Rental",
            "type":"Services"
        }
    ],
    "sg:phone":"+61 8 8932 2734",
    "sg:postcode":"0829",
    "sg:province":"NT",
    "sg:tags":[
        "crane",
        "hire"
    ],
    "wof:name":"A 1 Hire",
    "wof:placetype":"venue"
},
  "geometry": {"coordinates":[130.96502685600001,-12.4546070099],"type":"Point"}
}