{
  "type": "Feature",
  "properties": {
    "addr:full":"39 Queen St Melbourne VIC 3000",
    "addr:housenumber":"39",
    "addr:postcode":"3000",
    "addr:street":"Queen St",
    "iso:country":"AU",
    "sg:address":"39 Queen St",
    "sg:city":"Melbourne",
    "sg:classifiers":[
        {
            "category":"Travel",
            "subcategory":"Hotels & Motels",
            "type":"Entertainment"
        }
    ],
    "sg:phone":"+61 3 5249 1244",
    "sg:postcode":"3000",
    "sg:province":"VIC",
    "sg:tags":[
        "accommodation"
    ],
    "wof:name":"Honey Apartments",
    "wof:placetype":"venue"
},
  "geometry": {"coordinates":[144.961868286,-37.817779541],"type":"Point"}
}