{
  "type": "Feature",
  "properties": {
    "addr:full":"Shop 6, 457 Glynburn Rd Leabrook SA 5068",
    "addr:housenumber":"shop 6",
    "addr:postcode":"457;5068",
    "addr:street":"Glynburn Rd",
    "iso:country":"AU",
    "sg:address":"Shop 6, 457 Glynburn Rd",
    "sg:city":"Leabrook",
    "sg:classifiers":[
        {
            "category":"Personal",
            "subcategory":"Beauty Salon",
            "type":"Services"
        }
    ],
    "sg:phone":"+61 8 8431 5842",
    "sg:postcode":"5068",
    "sg:province":"SA",
    "sg:tags":[
        "hairdresser"
    ],
    "wof:name":"Beyond Blonde",
    "wof:placetype":"venue"
},
  "geometry": {"coordinates":[138.65957641599999,-34.9327468872],"type":"Point"}
}