{
  "type": "Feature",
  "properties": {
    "addr:full":"533 Sydney Rd Seaforth NSW 2092",
    "addr:housenumber":"533",
    "addr:postcode":"2092",
    "addr:street":"Sydney Rd",
    "iso:country":"AU",
    "sg:address":"533 Sydney Rd",
    "sg:city":"Seaforth",
    "sg:classifiers":[
        {
            "category":"Health Services",
            "subcategory":"Dentist",
            "type":"Services"
        }
    ],
    "sg:phone":"+61 2 9949 3222",
    "sg:postcode":"2092",
    "sg:province":"NSW",
    "wof:name":"Seaforth Dental",
    "wof:placetype":"venue"
},
  "geometry": {"coordinates":[151.252075195,-33.796749115],"type":"Point"}
}