{
  "type": "Feature",
  "properties": {
    "addr:full":"Archer St Broome WA 6725",
    "addr:postcode":"6725",
    "addr:street":"Archer St",
    "iso:country":"AU",
    "sg:address":"Archer St",
    "sg:city":"Broome",
    "sg:classifiers":[
        {
            "category":"Professional",
            "subcategory":"Business Services",
            "type":"Services"
        }
    ],
    "sg:phone":"+61 8 9192 1486",
    "sg:postcode":"6725",
    "sg:province":"WA",
    "sg:tags":[
        "livestock",
        "transport"
    ],
    "wof:name":"Bagshaw Bros",
    "wof:placetype":"venue"
},
  "geometry": {"coordinates":[122.207206726,-17.983039856],"type":"Point"}
}