{
  "type": "Feature",
  "properties": {
    "addr:full":"100 Beechboro Rd Bayswater WA 6053",
    "addr:housenumber":"100",
    "addr:postcode":"6053",
    "addr:street":"Beechboro Rd",
    "iso:country":"AU",
    "sg:address":"100 Beechboro Rd",
    "sg:city":"Bayswater",
    "sg:classifiers":[
        {
            "category":"Autos & Motor Vehicles",
            "subcategory":"Automobile Sales",
            "type":"Retail Goods"
        }
    ],
    "sg:phone":"+61 8 9272 7500",
    "sg:postcode":"6053",
    "sg:province":"WA",
    "sg:tags":[
        "equipment",
        "trailer"
    ],
    "wof:name":"Roadwest Transport Equipment",
    "wof:placetype":"venue"
},
  "geometry": {"coordinates":[115.915077209,-31.9067058563],"type":"Point"}
}