{
  "type": "Feature",
  "properties": {
    "iso:country":"AU",
    "sg:address":"380 Wentworth Ave",
    "sg:city":"Toongabbie",
    "sg:classifiers":[
        {
            "category":"Banks & Credit Unions",
            "subcategory":"Bureau De Change",
            "type":"Services"
        }
    ],
    "sg:phone":"+61 414 249 004",
    "sg:postcode":"2146",
    "sg:province":"NSW",
    "sg:tags":[
        "repairs",
        "part",
        "appliance",
        "electrical"
    ],
    "wof:name":"Shakti Corp Pty Ltd",
    "wof:placetype":"venue"
},
  "geometry": {"coordinates":[150.95039367699999,-33.7864532471],"type":"Point"}
}