{
  "type": "Feature",
  "properties": {
    "iso:country":"AU",
    "sg:address":"134 Tanti Ave",
    "sg:city":"Mornington",
    "sg:classifiers":[
        {
            "category":"Health Services",
            "subcategory":"Dentist",
            "type":"Services"
        }
    ],
    "sg:phone":"+61 3 5975 5166",
    "sg:postcode":"3931",
    "sg:province":"VIC",
    "wof:name":"Vidovic Antony",
    "wof:placetype":"venue"
},
  "geometry": {"coordinates":[145.047805786,-38.2251205444],"type":"Point"}
}