{
  "type": "Feature",
  "properties": {
    "iso:country":"AU",
    "sg:address":"2 Tink Taylor Ave",
    "sg:city":"Sisters Beach",
    "sg:classifiers":[
        {
            "category":"Professional",
            "subcategory":"Business Services",
            "type":"Services"
        }
    ],
    "sg:phone":"+61 3 6445 1889",
    "sg:postcode":"7321",
    "sg:province":"TAS",
    "sg:tags":[
        "drafting"
    ],
    "wof:name":"A & K Skellington Pty Ltd",
    "wof:placetype":"venue"
},
  "geometry": {"coordinates":[145.57746900000001,-40.928059],"type":"Point"}
}