{
  "type": "Feature",
  "properties": {
    "addr:full":"Unit 2/ 62 Victoria Rd Smithfield NSW 2164",
    "addr:housenumber":"62",
    "addr:postcode":"2164",
    "addr:street":"Victoria Rd",
    "iso:country":"AU",
    "sg:address":"Unit 2/ 62 Victoria Rd",
    "sg:city":"Smithfield",
    "sg:classifiers":[
        {
            "category":"Home & Garden",
            "subcategory":"Home Furnishings",
            "type":"Retail Goods"
        }
    ],
    "sg:phone":"+61 2 9604 9900",
    "sg:postcode":"2164",
    "sg:province":"NSW",
    "sg:tags":[
        "shower",
        "screen"
    ],
    "wof:name":"Perfect Australian Shower Screens",
    "wof:placetype":"venue"
},
  "geometry": {"coordinates":[150.93748474099999,-33.8507957458],"type":"Point"}
}