{
  "type": "Feature",
  "properties": {
    "addr:full":"139 Pring St Hendra QLD 4011",
    "addr:housenumber":"139",
    "addr:postcode":"4011",
    "addr:street":"Pring St",
    "iso:country":"AU",
    "sg:address":"139 Pring St",
    "sg:city":"Hendra",
    "sg:classifiers":[
        {
            "category":"Professional",
            "subcategory":"Employment Agencies",
            "type":"Services"
        }
    ],
    "sg:phone":"+61 7 3268 6688",
    "sg:postcode":"4011",
    "sg:province":"QLD",
    "wof:name":"Executive & Professional Selection",
    "wof:placetype":"venue"
},
  "geometry": {"coordinates":[153.06660500000001,-27.415451],"type":"Point"}
}