{
  "type": "Feature",
  "properties": {
    "iso:country":"AU",
    "sg:address":"7 Edenvale St",
    "sg:city":"Tanah Merah",
    "sg:classifiers":[
        {
            "category":"Building & Trades",
            "subcategory":"Construction",
            "type":"Services"
        }
    ],
    "sg:phone":"+61 7 3802 6299",
    "sg:postcode":"4128",
    "sg:province":"QLD",
    "sg:tags":[
        "installation",
        "air conditioning"
    ],
    "wof:name":"Relax Airconditioning & Refrigeration",
    "wof:placetype":"venue"
},
  "geometry": {"coordinates":[153.180984497,-27.6772403717],"type":"Point"}
}