{
  "type": "Feature",
  "properties": {
    "addr:full":"Shop 145 Gladstone Park Shopng Cntr 124 Gladstone Park Rd Gladstone Park VIC 3043",
    "addr:housenumber":"145;124",
    "addr:postcode":"3043",
    "addr:street":"Gladstone;Gladstone Park Rd",
    "iso:country":"AU",
    "sg:address":"Shop 145 Gladstone Park Shopng Cntr 124 Gladstone Park Rd",
    "sg:city":"Gladstone Park",
    "sg:classifiers":[
        {
            "category":"Food & Beverages",
            "subcategory":"Bakery",
            "type":"Retail Goods"
        }
    ],
    "sg:phone":"+61 3 8336 1886",
    "sg:postcode":"3043",
    "sg:province":"VIC",
    "sg:tags":[
        "cake",
        "shop",
        "pastry"
    ],
    "wof:name":"Michel's Patisserie",
    "wof:placetype":"venue"
},
  "geometry": {"coordinates":[144.88259887699999,-37.6881256104],"type":"Point"}
}