{
  "type": "Feature",
  "properties": {
    "iso:country":"AU",
    "sg:address":"PO Box 900",
    "sg:city":"Mona Vale",
    "sg:classifiers":[
        {
            "category":"Building & Trades",
            "subcategory":"Construction",
            "type":"Services"
        }
    ],
    "sg:phone":"+61 2 9450 1999",
    "sg:postcode":"2103",
    "sg:province":"NSW",
    "sg:tags":[
        "earth",
        "excavating",
        "moving",
        "contractor"
    ],
    "wof:name":"Rick Davis Contracting Pty Ltd",
    "wof:placetype":"venue"
},
  "geometry": {"coordinates":[151.300323486,-33.6770706177],"type":"Point"}
}