{
  "type": "Feature",
  "properties": {
    "addr:full":"Suite 33, Lvl 2 42-46 Wattle Rd Brookvale NSW 2100",
    "addr:housenumber":"42-46",
    "addr:postcode":"2100",
    "addr:street":"Wattle Rd",
    "iso:country":"AU",
    "sg:address":"Suite 33, Lvl 2 42-46 Wattle Rd",
    "sg:city":"Brookvale",
    "sg:classifiers":[
        {
            "category":"Banks & Credit Unions",
            "subcategory":"Financial Services",
            "type":"Services"
        }
    ],
    "sg:phone":"+61 2 9453 1223",
    "sg:postcode":"2100",
    "sg:province":"NSW",
    "sg:tags":[
        "financier"
    ],
    "wof:name":"Ricochet Technology Rentals Pty Ltd",
    "wof:placetype":"venue"
},
  "geometry": {"coordinates":[151.27487182600001,-33.7677192688],"type":"Point"}
}