{
  "type": "Feature",
  "properties": {
    "addr:full":"Shop 3, 16 Freshwater Point Rd Legana TAS 7277",
    "addr:housenumber":"shop;16",
    "addr:postcode":"7277",
    "addr:street":"Freshwater Point Rd",
    "iso:country":"AU",
    "sg:address":"Shop 3, 16 Freshwater Point Rd",
    "sg:city":"Legana",
    "sg:classifiers":[
        {
            "category":"Building & Trades",
            "subcategory":"Construction",
            "type":"Services"
        }
    ],
    "sg:phone":"+61 3 6330 2699",
    "sg:postcode":"7277",
    "sg:province":"TAS",
    "sg:tags":[
        "contractor"
    ],
    "wof:name":"Craftsman Homes",
    "wof:placetype":"venue"
},
  "geometry": {"coordinates":[147.04069519000001,-41.364566803],"type":"Point"}
}