{
  "type": "Feature",
  "properties": {
    "addr:full":"103 Hindley St Adelaide SA 5000",
    "addr:housenumber":"103",
    "addr:postcode":"5000",
    "addr:street":"Hindley St",
    "iso:country":"AU",
    "sg:address":"103 Hindley St",
    "sg:city":"Adelaide",
    "sg:classifiers":[
        {
            "category":"Professional",
            "subcategory":"Printing & Photocopies",
            "type":"Services"
        }
    ],
    "sg:phone":"+61 8 8410 6885",
    "sg:postcode":"5000",
    "sg:province":"SA",
    "sg:tags":[
        "screen",
        "printer"
    ],
    "wof:name":"The Embroidery Shop",
    "wof:placetype":"venue"
},
  "geometry": {"coordinates":[138.595703125,-34.9233093262],"type":"Point"}
}