{
  "type": "Feature",
  "properties": {
    "iso:country":"AU",
    "sg:address":"25 Allard Ave",
    "sg:city":"Roseville Chase",
    "sg:classifiers":[
        {
            "category":"Professional",
            "subcategory":"Computer Services",
            "type":"Services"
        }
    ],
    "sg:phone":"+61 407 278 260",
    "sg:postcode":"2069",
    "sg:province":"NSW",
    "sg:tags":[
        "consultant",
        "system"
    ],
    "wof:name":"Carr R & C Consulting Pty Ltd",
    "wof:placetype":"venue"
},
  "geometry": {"coordinates":[151.20347595199999,-33.7773094177],"type":"Point"}
}