{
  "type": "Feature",
  "properties": {
    "addr:full":"PO Box 2996 Nerang Business Centre QLD 4211",
    "addr:postcode":"4211",
    "iso:country":"AU",
    "sg:address":"PO Box 2996",
    "sg:city":"Nerang Business Centre",
    "sg:classifiers":[
        {
            "category":"Professional",
            "subcategory":"Art Services",
            "type":"Services"
        }
    ],
    "sg:phone":"+61 7 5596 9916",
    "sg:postcode":"4211",
    "sg:province":"QLD",
    "sg:tags":[
        "graphic",
        "designer"
    ],
    "wof:name":"M + M Design and Marketing",
    "wof:placetype":"venue"
},
  "geometry": {"coordinates":[153.3359375,-27.9926815033],"type":"Point"}
}