{
  "type": "Feature",
  "properties": {
    "iso:country":"AU",
    "sg:address":"55 Tyne St",
    "sg:city":"North Richmond",
    "sg:classifiers":[
        {
            "category":"Food & Beverages",
            "subcategory":"Fruits & Vegetables",
            "type":"Retail Goods"
        }
    ],
    "sg:phone":"+61 2 4571 1715",
    "sg:postcode":"2754",
    "sg:province":"NSW",
    "sg:tags":[
        "bush",
        "ingredient"
    ],
    "wof:name":"Kurrajong Australian Native Foods",
    "wof:placetype":"venue"
},
  "geometry": {"coordinates":[150.706497192,-33.5791778564],"type":"Point"}
}