{
  "type": "Feature",
  "properties": {
    "iso:country":"AU",
    "sg:address":"Shp 14/ 220 George St",
    "sg:city":"Liverpool",
    "sg:classifiers":[
        {
            "category":"Shopping",
            "type":"Retail Goods"
        }
    ],
    "sg:phone":"+61 2 9602 1166",
    "sg:postcode":"2170",
    "sg:province":"NSW",
    "sg:tags":[
        "new age",
        "product"
    ],
    "wof:name":"Earthly Times",
    "wof:placetype":"venue"
},
  "geometry": {"coordinates":[150.92497253400001,-33.9231834412],"type":"Point"}
}