{
  "type": "Feature",
  "properties": {
    "addr:full":"Gungahlin Market Pl Gungahlin ACT 2912",
    "addr:postcode":"2912",
    "addr:street":"Market Pl",
    "iso:country":"AU",
    "sg:address":"Gungahlin Market Pl",
    "sg:city":"Gungahlin",
    "sg:classifiers":[
        {
            "category":"Retail",
            "subcategory":"Repair Shop",
            "type":"Services"
        }
    ],
    "sg:phone":"+61 2 6262 2050",
    "sg:postcode":"2912",
    "sg:province":"ACT",
    "sg:tags":[
        "mending",
        "clothing",
        "alteration"
    ],
    "wof:name":"First Choice Dry Cleaners",
    "wof:placetype":"venue"
},
  "geometry": {"coordinates":[149.135665894,-35.183506012],"type":"Point"}
}