{
  "type": "Feature",
  "properties": {
    "addr:full":"20 Currawong Crs Coleambally NSW 2707",
    "addr:housenumber":"20",
    "addr:postcode":"2707",
    "addr:street":"Currawong Crs",
    "iso:country":"AU",
    "sg:address":"20 Currawong Crs",
    "sg:city":"Coleambally",
    "sg:classifiers":[
        {
            "category":"Utilities",
            "subcategory":"Electric",
            "type":"Services"
        }
    ],
    "sg:phone":"+61 2 6954 4688",
    "sg:postcode":"2707",
    "sg:province":"NSW",
    "sg:tags":[
        "electrical",
        "contractor"
    ],
    "wof:name":"CIA Electrical Pty Ltd",
    "wof:placetype":"venue"
},
  "geometry": {"coordinates":[145.89910888700001,-34.7905197144],"type":"Point"}
}