{
  "type": "Feature",
  "properties": {
    "addr:full":"6 Sharron Drv Granton TAS 7030",
    "addr:housenumber":"6",
    "addr:postcode":"7030",
    "addr:street":"Sharron Drv",
    "iso:country":"AU",
    "sg:address":"6 Sharron Drv",
    "sg:city":"Granton",
    "sg:classifiers":[
        {
            "category":"Building & Trades",
            "subcategory":"Construction",
            "type":"Services"
        }
    ],
    "sg:phone":"+61 3 6249 1106",
    "sg:postcode":"7030",
    "sg:province":"TAS",
    "sg:tags":[
        "contractor"
    ],
    "wof:name":"McLoughlin Construction Services",
    "wof:placetype":"venue"
},
  "geometry": {"coordinates":[147.23806762699999,-42.7611618042],"type":"Point"}
}