{
  "type": "Feature",
  "properties": {
    "addr:full":"2000 Warburton Hwy Launching Place VIC 3139",
    "addr:housenumber":"2000",
    "addr:postcode":"3139",
    "addr:street":"Warburton Hwy",
    "iso:country":"AU",
    "sg:address":"2000 Warburton Hwy",
    "sg:city":"Launching Place",
    "sg:classifiers":[
        {
            "category":"Retail",
            "subcategory":"Auto Repair",
            "type":"Services"
        }
    ],
    "sg:phone":"+61 3 5964 7621",
    "sg:postcode":"3139",
    "sg:province":"VIC",
    "sg:tags":[
        "repairer",
        "motor",
        "engineer"
    ],
    "wof:name":"Log Cabin Service Station",
    "wof:placetype":"venue"
},
  "geometry": {"coordinates":[145.56747436500001,-37.7804374695],"type":"Point"}
}