{
  "type": "Feature",
  "properties": {
    "iso:country":"AU",
    "sg:address":"257 Balaclava Rd",
    "sg:city":"Caulfield",
    "sg:classifiers":[
        {
            "category":"Health Services",
            "subcategory":"Doctor",
            "type":"Services"
        }
    ],
    "sg:phone":"+61 3 9532 9106",
    "sg:postcode":"3162",
    "sg:province":"VIC",
    "sg:tags":[
        "medical",
        "practitioner"
    ],
    "wof:name":"Glowinski L",
    "wof:placetype":"venue"
},
  "geometry": {"coordinates":[145.028366089,-37.8732261658],"type":"Point"}
}