{
  "type": "Feature",
  "properties": {
    "iso:country":"AU",
    "sg:address":"16 Young St",
    "sg:city":"Wollongong",
    "sg:classifiers":[
        {
            "category":"Personal",
            "subcategory":"Beauty Salon",
            "type":"Services"
        }
    ],
    "sg:phone":"+61 2 4227 3533",
    "sg:postcode":"2500",
    "sg:province":"NSW",
    "sg:tags":[
        "hairdresser"
    ],
    "wof:name":"Solevunique",
    "wof:placetype":"venue"
},
  "geometry": {"coordinates":[150.89065600000001,-34.421619],"type":"Point"}
}