{
  "type": "Feature",
  "properties": {
    "addr:full":"12 Terama Crt Salisbury Heights SA 5109",
    "addr:housenumber":"12",
    "addr:postcode":"5109",
    "addr:street":"Terama Crt",
    "iso:country":"AU",
    "sg:address":"12 Terama Crt",
    "sg:city":"Salisbury Heights",
    "sg:classifiers":[
        {
            "category":"Donuts",
            "subcategory":"None",
            "type":"Food & Drink"
        }
    ],
    "sg:phone":"+61 8 8288 0391",
    "sg:postcode":"5109",
    "sg:province":"SA",
    "sg:tags":[
        "die",
        "engraver",
        "sinker"
    ],
    "wof:name":"Quick Signs",
    "wof:placetype":"venue"
},
  "geometry": {"coordinates":[138.69679260300001,-34.7619361877],"type":"Point"}
}