{
  "type": "Feature",
  "properties": {
    "iso:country":"AU",
    "sg:address":"368b Kensington Rd",
    "sg:city":"Erindale",
    "sg:classifiers":[
        {
            "category":"Personal",
            "subcategory":"Beauty Salon",
            "type":"Services"
        }
    ],
    "sg:phone":"+61 8 8331 7055",
    "sg:postcode":"5066",
    "sg:province":"SA",
    "wof:name":"Designer Nails By Tanja",
    "wof:placetype":"venue"
},
  "geometry": {"coordinates":[138.66302490199999,-34.9259643555],"type":"Point"}
}