{
  "type": "Feature",
  "properties": {
    "addr:full":"479 Waterworks Rd Ashgrove QLD 4060",
    "addr:housenumber":"479",
    "addr:postcode":"4060",
    "addr:street":"Waterworks Rd",
    "iso:country":"AU",
    "sg:address":"479 Waterworks Rd",
    "sg:city":"Ashgrove",
    "sg:classifiers":[
        {
            "category":"Organizations",
            "subcategory":"Professional Association",
            "type":"Services"
        }
    ],
    "sg:phone":"+61 7 3366 9935",
    "sg:postcode":"4060",
    "sg:province":"QLD",
    "sg:tags":[
        "web",
        "internet"
    ],
    "wof:name":"Creative Intersection",
    "wof:placetype":"venue"
},
  "geometry": {"coordinates":[152.977859497,-27.4489803314],"type":"Point"}
}