{
  "type": "Feature",
  "properties": {
    "addr:full":"PO Box 555 Guildford NSW 2161",
    "addr:postcode":"2161",
    "iso:country":"AU",
    "sg:address":"PO Box 555",
    "sg:city":"Guildford",
    "sg:classifiers":[
        {
            "category":"Building & Trades",
            "subcategory":"Construction",
            "type":"Services"
        }
    ],
    "sg:phone":"+61 425 325 544",
    "sg:postcode":"2161",
    "sg:province":"NSW",
    "sg:tags":[
        "contractor"
    ],
    "sg:website":"http://www.mdconstructions.com.au",
    "wof:name":"Mirage Design & Constructions",
    "wof:placetype":"venue"
},
  "geometry": {"coordinates":[150.97166442899999,-33.8485145569],"type":"Point"}
}