{
  "type": "Feature",
  "properties": {
    "addr:full":"Cnr O'Bryan & Box Sts Merbein VIC 3505",
    "addr:postcode":"3505",
    "addr:street":"Cnr",
    "iso:country":"AU",
    "sg:address":"Cnr O'Bryan & Box Sts",
    "sg:city":"Merbein",
    "sg:classifiers":[
        {
            "category":"Education",
            "subcategory":"Kindergarten",
            "type":"Public Place"
        }
    ],
    "sg:phone":"+61 3 5025 2491",
    "sg:postcode":"3505",
    "sg:province":"VIC",
    "sg:tags":[
        "pre-schools"
    ],
    "wof:name":"Merbein Pre-School Kindergarten",
    "wof:placetype":"venue"
},
  "geometry": {"coordinates":[142.076705933,-34.1697502136],"type":"Point"}
}