{
  "type": "Feature",
  "properties": {
    "addr:full":"4 Main St Cudal NSW 2864",
    "addr:housenumber":"4",
    "addr:postcode":"2864",
    "addr:street":"Main St",
    "iso:country":"AU",
    "sg:address":"4 Main St",
    "sg:city":"Cudal",
    "sg:classifiers":[
        {
            "category":"Food & Beverages",
            "subcategory":"Supermarket",
            "type":"Retail Goods"
        }
    ],
    "sg:phone":"+61 2 6364 2526",
    "sg:postcode":"2864",
    "sg:province":"NSW",
    "sg:tags":[
        "grocery",
        "store"
    ],
    "wof:name":"Cudal Minimart & Coffee Shop",
    "wof:placetype":"venue"
},
  "geometry": {"coordinates":[148.738708,-33.28664],"type":"Point"}
}