{
  "type": "Feature",
  "properties": {
    "iso:country":"AU",
    "sg:address":"Unit 14 121 Gormanston Rd",
    "sg:city":"Moonah",
    "sg:classifiers":[
        {
            "category":"Utilities",
            "subcategory":"Telephone",
            "type":"Services"
        }
    ],
    "sg:phone":"+61 3 6273 7563",
    "sg:postcode":"7009",
    "sg:province":"TAS",
    "sg:tags":[
        "installation",
        "system",
        "maintenance"
    ],
    "wof:name":"TR Communications (TAS)",
    "wof:placetype":"venue"
},
  "geometry": {"coordinates":[147.297805786,-42.8368835449],"type":"Point"}
}