{
  "type": "Feature",
  "properties": {
    "iso:country":"AU",
    "sg:address":"2/ 10 Dorset St",
    "sg:city":"Lonsdale",
    "sg:classifiers":[
        {
            "category":"Manufacturing",
            "subcategory":"Tools & Machinery",
            "type":"Manufacturing & Wholesale Goods"
        }
    ],
    "sg:phone":"+61 8 8384 5688",
    "sg:postcode":"5160",
    "sg:province":"SA",
    "sg:tags":[
        "earth",
        "excavating",
        "moving",
        "equipment"
    ],
    "wof:name":"Keech Castings Australia Pty Ltd",
    "wof:placetype":"venue"
},
  "geometry": {"coordinates":[138.50328064000001,-35.1151046753],"type":"Point"}
}