{
  "type": "Feature",
  "properties": {
    "iso:country":"AU",
    "sg:address":"198 Gordon St",
    "sg:city":"Footscray",
    "sg:classifiers":[
        {
            "category":"Food & Beverages",
            "subcategory":"Groceries & Convenience Stores",
            "type":"Retail Goods"
        }
    ],
    "sg:phone":"+61 3 9689 7930",
    "sg:postcode":"3011",
    "sg:province":"VIC",
    "wof:name":"Le Kim",
    "wof:placetype":"venue"
},
  "geometry": {"coordinates":[144.888748169,-37.794670105],"type":"Point"}
}