{
  "type": "Feature",
  "properties": {
    "addr:full":"2/ 18 Manning Rd Double Bay NSW 2028",
    "addr:housenumber":"/ 18",
    "addr:postcode":"2028",
    "addr:street":"Manning Rd",
    "iso:country":"AU",
    "sg:address":"2/ 18 Manning Rd",
    "sg:city":"Double Bay",
    "sg:classifiers":[
        {
            "category":"Health Services",
            "subcategory":"Health Practitioner",
            "type":"Services"
        }
    ],
    "sg:phone":"+61 418 216 923",
    "sg:postcode":"2028",
    "sg:province":"NSW",
    "sg:tags":[
        "psychotherapist"
    ],
    "wof:name":"Kyriakou Aphrodite",
    "wof:placetype":"venue"
},
  "geometry": {"coordinates":[151.24307250999999,-33.879360199],"type":"Point"}
}