{
  "type": "Feature",
  "properties": {
    "iso:country":"AU",
    "sg:address":"14 Maillard St",
    "sg:city":"Cockatoo",
    "sg:classifiers":[
        {
            "category":"Building & Trades",
            "subcategory":"Landscaping Services",
            "type":"Services"
        }
    ],
    "sg:phone":"+61 438 228 663",
    "sg:postcode":"3781",
    "sg:province":"VIC",
    "sg:tags":[
        "stump",
        "tree",
        "felling",
        "removal"
    ],
    "wof:name":"John Palmer Tree Stump Removals",
    "wof:placetype":"venue"
},
  "geometry": {"coordinates":[145.492004,-37.943939],"type":"Point"}
}