{
  "type": "Feature",
  "properties": {
    "addr:full":"PO Box 234 Mosman Park WA 6012",
    "addr:postcode":"6012",
    "iso:country":"AU",
    "sg:address":"PO Box 234",
    "sg:city":"Mosman Park",
    "sg:classifiers":[
        {
            "category":"Professional",
            "subcategory":"Art Services",
            "type":"Services"
        }
    ],
    "sg:phone":"+61 421 386 683",
    "sg:postcode":"6012",
    "sg:province":"WA",
    "wof:name":"Richardson Pictures",
    "wof:placetype":"venue"
},
  "geometry": {"coordinates":[115.76612854,-32.0142402649],"type":"Point"}
}