{
  "type": "Feature",
  "properties": {
    "addr:full":"2/173 Oakleigh Rd Carnegie VIC 3163",
    "addr:housenumber":"/ 173",
    "addr:postcode":"3163",
    "addr:street":"Oakleigh Rd",
    "iso:country":"AU",
    "sg:address":"2/173 Oakleigh Rd",
    "sg:city":"Carnegie",
    "sg:classifiers":[
        {
            "category":"Professional",
            "subcategory":"Employment Agencies",
            "type":"Services"
        }
    ],
    "sg:phone":"+61 403 302 243",
    "sg:postcode":"3163",
    "sg:province":"VIC",
    "sg:tags":[
        "occupational",
        "therapist"
    ],
    "wof:name":"Monjo Consulting",
    "wof:placetype":"venue"
},
  "geometry": {"coordinates":[145.06300354000001,-37.9002418518],"type":"Point"}
}