{
  "type": "Feature",
  "properties": {
    "addr:full":"210 Forest Drv Mt Martha VIC 3934",
    "addr:housenumber":"210",
    "addr:postcode":"3934",
    "addr:street":"Forest Drv Mt Martha",
    "iso:country":"AU",
    "sg:address":"210 Forest Drv",
    "sg:city":"Mt Martha",
    "sg:classifiers":[
        {
            "category":"Building & Trades",
            "subcategory":"Cleaning & Sanitation",
            "type":"Services"
        }
    ],
    "sg:phone":"+61 3 5974 2244",
    "sg:postcode":"3934",
    "sg:province":"VIC",
    "sg:tags":[
        "chemical",
        "pressure",
        "steam",
        "contractor"
    ],
    "wof:name":"First Choice Home Care",
    "wof:placetype":"venue"
},
  "geometry": {"coordinates":[145.01754760700001,-38.2905387878],"type":"Point"}
}