{
  "type": "Feature",
  "properties": {
    "addr:full":"70 Derby St Penrith NSW 2750",
    "addr:housenumber":"70",
    "addr:postcode":"2750",
    "addr:street":"Derby St",
    "iso:country":"AU",
    "sg:address":"70 Derby St",
    "sg:city":"Penrith",
    "sg:classifiers":[
        {
            "category":"Health Services",
            "subcategory":"Health Practitioner",
            "type":"Services"
        }
    ],
    "sg:phone":"+61 2 4721 1976",
    "sg:postcode":"2750",
    "sg:province":"NSW",
    "sg:tags":[
        "physiotherapist"
    ],
    "wof:name":"Centre 70",
    "wof:placetype":"venue"
},
  "geometry": {"coordinates":[150.711624145,-33.7609100342],"type":"Point"}
}