{
  "type": "Feature",
  "properties": {
    "addr:full":"43-47 Pine Rd Fairfield NSW 2165",
    "addr:housenumber":"43-47",
    "addr:postcode":"2165",
    "addr:street":"Pine Rd",
    "iso:country":"AU",
    "sg:address":"43-47 Pine Rd",
    "sg:city":"Fairfield",
    "sg:classifiers":[
        {
            "category":"Professional",
            "subcategory":"Art Services",
            "type":"Services"
        }
    ],
    "sg:phone":"+61 1800 224 334",
    "sg:postcode":"2165",
    "sg:province":"NSW",
    "sg:tags":[
        "medical",
        "industrial",
        "gas"
    ],
    "wof:name":"Air Liquide Australia Limited",
    "wof:placetype":"venue"
},
  "geometry": {"coordinates":[150.963134766,-33.8643264771],"type":"Point"}
}