{
  "type": "Feature",
  "properties": {
    "addr:full":"61 Garland Rd Naremburn NSW 2065",
    "addr:housenumber":"61",
    "addr:postcode":"2065",
    "addr:street":"Garland Rd",
    "iso:country":"AU",
    "sg:address":"61 Garland Rd",
    "sg:city":"Naremburn",
    "sg:classifiers":[
        {
            "category":"Building & Trades",
            "subcategory":"Construction",
            "type":"Services"
        }
    ],
    "sg:phone":"+61 2 9437 6626",
    "sg:postcode":"2065",
    "sg:province":"NSW",
    "sg:tags":[
        "joiner",
        "carpenter"
    ],
    "wof:name":"A A A Carpenter",
    "wof:placetype":"venue"
},
  "geometry": {"coordinates":[151.201293945,-33.8137664795],"type":"Point"}
}