{
  "type": "Feature",
  "properties": {
    "addr:full":"Arminor Industrial Park Fact 1 / 173 Wellington Rd Clayton VIC 3168",
    "addr:housenumber":"1 / 173",
    "addr:postcode":"3168",
    "addr:street":"Fact;Wellington Rd",
    "iso:country":"AU",
    "sg:address":"Arminor Industrial Park Fact 1 / 173 Wellington Rd",
    "sg:city":"Clayton",
    "sg:classifiers":[
        {
            "category":"Transit Center",
            "subcategory":"Freight",
            "type":"Transportation"
        }
    ],
    "sg:phone":"+61 430 120 600",
    "sg:postcode":"3168",
    "sg:province":"VIC",
    "sg:tags":[
        "forklift",
        "truck"
    ],
    "wof:name":"ABC Forklifts Pty Ltd",
    "wof:placetype":"venue"
},
  "geometry": {"coordinates":[145.145996094,-37.9167709351],"type":"Point"}
}