{
  "type": "Feature",
  "properties": {
    "addr:full":"13 Karoola Crs Surfside NSW 2536",
    "addr:housenumber":"13",
    "addr:postcode":"2536",
    "addr:street":"Karoola Crs",
    "iso:country":"AU",
    "sg:address":"13 Karoola Crs",
    "sg:city":"Surfside",
    "sg:classifiers":[
        {
            "category":"Shopping",
            "subcategory":"Crafts & Fabrics",
            "type":"Retail Goods"
        }
    ],
    "sg:phone":"+61 2 4472 7401",
    "sg:postcode":"2536",
    "sg:province":"NSW",
    "sg:tags":[
        "merchant",
        "cork"
    ],
    "wof:name":"Coastal Cork",
    "wof:placetype":"venue"
},
  "geometry": {"coordinates":[150.19273376500001,-35.6944389343],"type":"Point"}
}