{
  "type": "Feature",
  "properties": {
    "addr:full":"12 Ilma St Condell Park NSW 2200",
    "addr:housenumber":"12",
    "addr:postcode":"2200",
    "addr:street":"Ilma St",
    "iso:country":"AU",
    "sg:address":"12 Ilma St",
    "sg:city":"Condell Park",
    "sg:classifiers":[
        {
            "category":"Shopping",
            "subcategory":"Jewelry",
            "type":"Retail Goods"
        }
    ],
    "sg:phone":"+61 2 9792 5769",
    "sg:postcode":"2200",
    "sg:province":"NSW",
    "sg:tags":[
        "jeweller"
    ],
    "wof:name":"Diamond Marble Granite",
    "wof:placetype":"venue"
},
  "geometry": {"coordinates":[151.013443,-33.932709],"type":"Point"}
}