{
  "type": "Feature",
  "properties": {
    "addr:full":"779a Port Rd Woodville SA 5011",
    "addr:housenumber":"779a",
    "addr:postcode":"5011",
    "addr:street":"Port Rd",
    "iso:country":"AU",
    "sg:address":"779a Port Rd",
    "sg:city":"Woodville",
    "sg:classifiers":[
        {
            "category":"Wholesale",
            "subcategory":"Apparel",
            "type":"Manufacturing & Wholesale Goods"
        }
    ],
    "sg:phone":"+61 8 8268 1155",
    "sg:postcode":"5011",
    "sg:province":"SA",
    "sg:tags":[
        "wholesaler",
        "mfrs",
        "sportswear",
        "women's"
    ],
    "wof:name":"Emmsee Sportswear",
    "wof:placetype":"venue"
},
  "geometry": {"coordinates":[138.536087036,-34.880897522],"type":"Point"}
}