{
  "type": "Feature",
  "properties": {
    "addr:full":"2/ 13 Tucks Rd Seven Hills NSW 2147",
    "addr:housenumber":"/ 13",
    "addr:postcode":"2147",
    "addr:street":"Tucks Rd",
    "iso:country":"AU",
    "sg:address":"2/ 13 Tucks Rd",
    "sg:city":"Seven Hills",
    "sg:classifiers":[
        {
            "category":"Structure",
            "subcategory":"Building",
            "type":"Public Place"
        }
    ],
    "sg:phone":"+61 2 9674 8248",
    "sg:postcode":"2147",
    "sg:province":"NSW",
    "sg:tags":[
        "sail",
        "shade"
    ],
    "wof:name":"Australian Shadola Pty Ltd",
    "wof:placetype":"venue"
},
  "geometry": {"coordinates":[150.95640564000001,-33.77784729],"type":"Point"}
}