{
  "type": "Feature",
  "properties": {
    "addr:full":"95 Dunlop St Mortlake VIC 3272",
    "addr:housenumber":"95",
    "addr:postcode":"3272",
    "addr:street":"Dunlop St",
    "iso:country":"AU",
    "sg:address":"95 Dunlop St",
    "sg:city":"Mortlake",
    "sg:classifiers":[
        {
            "category":"Cafe",
            "type":"Food & Drink"
        }
    ],
    "sg:phone":"+61 3 5599 2008",
    "sg:postcode":"3272",
    "sg:province":"VIC",
    "wof:name":"Jackies Coffee & Wine Bar",
    "wof:placetype":"venue"
},
  "geometry": {"coordinates":[142.80596923799999,-38.0809898376],"type":"Point"}
}