{
  "type": "Feature",
  "properties": {
    "iso:country":"AU",
    "sg:address":"1181 Sandgate Rd",
    "sg:city":"Nundah",
    "sg:classifiers":[
        {
            "category":"Personal",
            "subcategory":"Beauty Salon",
            "type":"Services"
        }
    ],
    "sg:phone":"+61 7 3266 3338",
    "sg:postcode":"4012",
    "sg:province":"QLD",
    "sg:tags":[
        "hairdresser"
    ],
    "wof:name":"G Lordi",
    "wof:placetype":"venue"
},
  "geometry": {"coordinates":[153.06057739299999,-27.4036464691],"type":"Point"}
}