{
  "type": "Feature",
  "properties": {
    "iso:country":"AU",
    "sg:address":"Apartment 110 17 Marlow St",
    "sg:city":"Logan Central",
    "sg:classifiers":[
        {
            "category":"Professional",
            "subcategory":"Research",
            "type":"Services"
        }
    ],
    "sg:phone":"+61 417 727 384",
    "sg:postcode":"4114",
    "sg:province":"QLD",
    "sg:tags":[
        "industrial",
        "scientific"
    ],
    "wof:name":"Veterinary-Meat Animal Research & Consultants",
    "wof:placetype":"venue"
},
  "geometry": {"coordinates":[153.11607360799999,-27.6270084381],"type":"Point"}
}