{
  "type": "Feature",
  "properties": {
    "iso:country":"AU",
    "sg:address":"32 Steel St",
    "sg:city":"Devonport",
    "sg:classifiers":[
        {
            "category":"Retail",
            "subcategory":"Repair Shop",
            "type":"Services"
        }
    ],
    "sg:phone":"+61 3 6424 5440",
    "sg:postcode":"7310",
    "sg:province":"TAS",
    "sg:tags":[
        "machine",
        "sewing"
    ],
    "wof:name":"Stewarts Sewing Machine Centre Pty Ltd",
    "wof:placetype":"venue"
},
  "geometry": {"coordinates":[146.36053466800001,-41.1813850403],"type":"Point"}
}