{
  "type": "Feature",
  "properties": {
    "addr:full":"Liversidge La Leonards Hill VIC 3461",
    "addr:postcode":"3461",
    "iso:country":"AU",
    "sg:address":"Liversidge La",
    "sg:city":"Leonards Hill",
    "sg:classifiers":[
        {
            "category":"Farming",
            "subcategory":"Farm",
            "type":"Manufacturing & Wholesale Goods"
        }
    ],
    "sg:phone":"+61 3 5348 6550",
    "sg:postcode":"3461",
    "sg:province":"VIC",
    "sg:tags":[
        "farmer"
    ],
    "wof:name":"R & N Liversidge Pty Ltd",
    "wof:placetype":"venue"
},
  "geometry": {"coordinates":[144.12051391599999,-37.4054031372],"type":"Point"}
}