{
  "type": "Feature",
  "properties": {
    "addr:full":"63 Rea St Shepparton VIC 3630",
    "addr:housenumber":"63",
    "addr:postcode":"3630",
    "addr:street":"Rea St",
    "iso:country":"AU",
    "sg:address":"63 Rea St",
    "sg:city":"Shepparton",
    "sg:classifiers":[
        {
            "category":"Utilities",
            "subcategory":"Water",
            "type":"Services"
        }
    ],
    "sg:phone":"+61 3 5821 7809",
    "sg:postcode":"3630",
    "sg:province":"VIC",
    "sg:tags":[
        "hot",
        "system"
    ],
    "wof:name":"Nappa Electrical",
    "wof:placetype":"venue"
},
  "geometry": {"coordinates":[145.408111572,-36.3707733154],"type":"Point"}
}