{
  "type": "Feature",
  "properties": {
    "addr:full":"2 Rosmead Ave Beechboro WA 6063",
    "addr:housenumber":"2",
    "addr:postcode":"6063",
    "addr:street":"Rosmead Ave",
    "iso:country":"AU",
    "sg:address":"2 Rosmead Ave",
    "sg:city":"Beechboro",
    "sg:classifiers":[
        {
            "category":"Building & Trades",
            "subcategory":"Landscaping Services",
            "type":"Services"
        }
    ],
    "sg:phone":"+61 8 9377 7096",
    "sg:postcode":"6063",
    "sg:province":"WA",
    "sg:tags":[
        "designer",
        "landscape",
        "contractor"
    ],
    "wof:name":"Kwik Kerb Beechboro",
    "wof:placetype":"venue"
},
  "geometry": {"coordinates":[115.93212127699999,-31.871591568],"type":"Point"}
}