{
  "type": "Feature",
  "properties": {
    "addr:full":"138 Boorowa St Young NSW 2594",
    "addr:housenumber":"138",
    "addr:postcode":"2594",
    "addr:street":"Boorowa St",
    "iso:country":"AU",
    "sg:address":"138 Boorowa St",
    "sg:city":"Young",
    "sg:classifiers":[
        {
            "category":"Personal",
            "type":"Services"
        }
    ],
    "sg:phone":"+61 2 6382 1512",
    "sg:postcode":"2594",
    "sg:province":"NSW",
    "sg:tags":[
        "gift"
    ],
    "wof:name":"Penson Giftware & Toyworld",
    "wof:placetype":"venue"
},
  "geometry": {"coordinates":[148.286453247,-34.3103179932],"type":"Point"}
}