{
  "type": "Feature",
  "properties": {
    "addr:full":"9 / 145 Maroondah Hwy Ringwood VIC 3134",
    "addr:housenumber":"/ 145",
    "addr:postcode":"3134",
    "addr:street":"Maroondah Hwy",
    "iso:country":"AU",
    "sg:address":"9 / 145 Maroondah Hwy",
    "sg:city":"Ringwood",
    "sg:classifiers":[
        {
            "category":"Professional",
            "subcategory":"Management & Consulting",
            "type":"Services"
        }
    ],
    "sg:phone":"+61 3 9870 9777",
    "sg:postcode":"3134",
    "sg:province":"VIC",
    "sg:tags":[
        "consultant"
    ],
    "wof:name":"McNicol Williams Management and Marketing Services",
    "wof:placetype":"venue"
},
  "geometry": {"coordinates":[145.228027344,-37.8153381348],"type":"Point"}
}