{
  "type": "Feature",
  "properties": {
    "addr:full":"8 Dalby St Fyshwick ACT 2609",
    "addr:housenumber":"8",
    "addr:postcode":"2609",
    "addr:street":"Dalby St",
    "iso:country":"AU",
    "sg:address":"8 Dalby St",
    "sg:city":"Fyshwick",
    "sg:classifiers":[
        {
            "category":"Professional",
            "type":"Services"
        }
    ],
    "sg:phone":"+61 2 6295 3844",
    "sg:postcode":"2609",
    "sg:province":"ACT",
    "sg:tags":[
        "transport"
    ],
    "wof:name":"Regional Transport",
    "wof:placetype":"venue"
},
  "geometry": {"coordinates":[149.153686523,-35.3247146606],"type":"Point"}
}