{
  "type": "Feature",
  "properties": {
    "iso:country":"AU",
    "sg:address":"3/ 42 Carmal St",
    "sg:city":"Garbutt",
    "sg:classifiers":[
        {
            "category":"Shopping",
            "subcategory":"Pets & Pet Supplies",
            "type":"Retail Goods"
        }
    ],
    "sg:phone":"+61 7 4728 1074",
    "sg:postcode":"4814",
    "sg:province":"QLD",
    "sg:tags":[
        "boring",
        "drilling",
        "equipment"
    ],
    "wof:name":"Daws Drilling & Cutting Service",
    "wof:placetype":"venue"
},
  "geometry": {"coordinates":[146.761765,-19.26936],"type":"Point"}
}