{
  "type": "Feature",
  "properties": {
    "addr:full":"54 The High Rd Blaxland NSW 2774",
    "addr:housenumber":"54",
    "addr:postcode":"2774",
    "addr:street":"The High Rd",
    "iso:country":"AU",
    "sg:address":"54 The High Rd",
    "sg:city":"Blaxland",
    "sg:classifiers":[
        {
            "category":"Arts & Performance",
            "subcategory":"Music",
            "type":"Entertainment"
        }
    ],
    "sg:phone":"+61 2 4739 6401",
    "sg:postcode":"2774",
    "sg:province":"NSW",
    "sg:tags":[
        "mobile",
        "jockey",
        "disc"
    ],
    "wof:name":"De Vincenzo E",
    "wof:placetype":"venue"
},
  "geometry": {"coordinates":[150.62269592300001,-33.7489433289],"type":"Point"}
}