{
  "type": "Feature",
  "properties": {
    "addr:full":"Level 2, 91 Havelock St West Perth WA 6005",
    "addr:housenumber":"91",
    "addr:postcode":"6005",
    "addr:street":"Havelock St",
    "iso:country":"AU",
    "sg:address":"Level 2, 91 Havelock St",
    "sg:city":"West Perth",
    "sg:classifiers":[
        {
            "category":"Professional",
            "subcategory":"Accounting & Tax Preparation",
            "type":"Services"
        }
    ],
    "sg:phone":"+61 8 9481 0481",
    "sg:postcode":"6005",
    "sg:province":"WA",
    "sg:tags":[
        "deduction",
        "payroll"
    ],
    "wof:name":"Paypac Payroll Services",
    "wof:placetype":"venue"
},
  "geometry": {"coordinates":[115.845199585,-31.9471282959],"type":"Point"}
}