{
  "type": "Feature",
  "properties": {
    "iso:country":"AU",
    "sg:address":"1116 Mt Alexander Rd",
    "sg:city":"Essendon",
    "sg:classifiers":[
        {
            "category":"Autos & Motor Vehicles",
            "subcategory":"Boat Sales",
            "type":"Retail Goods"
        }
    ],
    "sg:phone":"+61 3 9379 6993",
    "sg:postcode":"3040",
    "sg:province":"VIC",
    "sg:tags":[
        "yacht"
    ],
    "wof:name":"Starflyte Marine",
    "wof:placetype":"venue"
},
  "geometry": {"coordinates":[144.911087036,-37.7451324463],"type":"Point"}
}