{
  "type": "Feature",
  "properties": {
    "addr:full":"Shop 6/ 27 Bank St Meadowbank NSW 2114",
    "addr:housenumber":"shop 6 / 27",
    "addr:postcode":"2114",
    "addr:street":"Bank St",
    "iso:country":"AU",
    "sg:address":"Shop 6/ 27 Bank St",
    "sg:city":"Meadowbank",
    "sg:classifiers":[
        {
            "category":"Food & Beverages",
            "subcategory":"Bakery",
            "type":"Retail Goods"
        }
    ],
    "sg:phone":"+61 2 9809 2088",
    "sg:postcode":"2114",
    "sg:province":"NSW",
    "sg:tags":[
        "cake",
        "shop",
        "pastry"
    ],
    "wof:name":"Cake It Away",
    "wof:placetype":"venue"
},
  "geometry": {"coordinates":[151.08958435100001,-33.8156471252],"type":"Point"}
}