{
  "type": "Feature",
  "properties": {
    "iso:country":"AU",
    "sg:address":"Shop 3, 11 Bellevue Hill Rd",
    "sg:city":"Bellevue Hill",
    "sg:classifiers":[
        {
            "category":"Health Services",
            "subcategory":"Dentist",
            "type":"Services"
        }
    ],
    "sg:phone":"+61 2 9369 4429",
    "sg:postcode":"2023",
    "sg:province":"NSW",
    "wof:name":"Complete Dental Solutions",
    "wof:placetype":"venue"
},
  "geometry": {"coordinates":[151.25831604000001,-33.886390686],"type":"Point"}
}