{
  "type": "Feature",
  "properties": {
    "iso:country":"AU",
    "sg:address":"40/ 10 Craigieburn Rd",
    "sg:city":"Craigieburn",
    "sg:classifiers":[
        {
            "category":"Real Estate",
            "subcategory":"Real Estate Agent",
            "type":"Services"
        }
    ],
    "sg:phone":"+61 3 9305 5533",
    "sg:postcode":"3064",
    "sg:province":"VIC",
    "wof:name":"L J Hooker Craigieburn",
    "wof:placetype":"venue"
},
  "geometry": {"coordinates":[144.94125366200001,-37.5987243652],"type":"Point"}
}