{
  "type": "Feature",
  "properties": {
    "addr:full":"40 Suscatand St Rocklea QLD 4106",
    "addr:housenumber":"40",
    "addr:postcode":"4106",
    "addr:street":"Suscatand St",
    "iso:country":"AU",
    "sg:address":"40 Suscatand St",
    "sg:city":"Rocklea",
    "sg:classifiers":[
        {
            "category":"Food & Beverages",
            "subcategory":"Specialty",
            "type":"Retail Goods"
        }
    ],
    "sg:phone":"+61 7 3277 1799",
    "sg:postcode":"4106",
    "sg:province":"QLD",
    "sg:tags":[
        "delicacy"
    ],
    "wof:name":"T & D Trading Pty Ltd",
    "wof:placetype":"venue"
},
  "geometry": {"coordinates":[152.99642944300001,-27.5556335449],"type":"Point"}
}