{
  "type": "Feature",
  "properties": {
    "addr:full":"23 Forbes Rd Parkes NSW 2870",
    "addr:housenumber":"23",
    "addr:postcode":"2870",
    "addr:street":"Forbes Rd",
    "iso:country":"AU",
    "sg:address":"23 Forbes Rd",
    "sg:city":"Parkes",
    "sg:classifiers":[
        {
            "category":"Fast Food",
            "type":"Food & Drink"
        }
    ],
    "sg:phone":"+61 2 6862 3294",
    "sg:postcode":"2870",
    "sg:province":"NSW",
    "sg:tags":[
        "away",
        "take"
    ],
    "wof:name":"Middleton Mini Mart",
    "wof:placetype":"venue"
},
  "geometry": {"coordinates":[148.17073099999999,-33.144444],"type":"Point"}
}