{
  "type": "Feature",
  "properties": {
    "addr:full":"20 Jasmine Ave Subiaco WA 6008",
    "addr:housenumber":"20",
    "addr:postcode":"6008",
    "addr:street":"Jasmine Ave",
    "iso:country":"AU",
    "sg:address":"20 Jasmine Ave",
    "sg:city":"Subiaco",
    "sg:classifiers":[
        {
            "category":"Professional",
            "subcategory":"Art Services",
            "type":"Services"
        }
    ],
    "sg:phone":"+61 409 118 897",
    "sg:postcode":"6008",
    "sg:province":"WA",
    "sg:tags":[
        "interior",
        "designer"
    ],
    "wof:name":"Etherington-Gray Sherren",
    "wof:placetype":"venue"
},
  "geometry": {"coordinates":[115.818588257,-31.9428462982],"type":"Point"}
}