{
  "type": "Feature",
  "properties": {
    "iso:country":"AU",
    "sg:address":"16 Wandilla Drv",
    "sg:city":"Helensvale",
    "sg:classifiers":[
        {
            "category":"Sports & Exercise",
            "subcategory":"Golf",
            "type":"Entertainment"
        }
    ],
    "sg:phone":"+61 7 5573 1329",
    "sg:postcode":"4212",
    "sg:province":"QLD",
    "sg:tags":[
        "club"
    ],
    "wof:name":"Helensvale Golf Club Limited",
    "wof:placetype":"venue"
},
  "geometry": {"coordinates":[153.33096313499999,-27.9089412689],"type":"Point"}
}