{
  "type": "Feature",
  "properties": {
    "addr:full":"5 John Phillip Drv Bonny Hills NSW 2445",
    "addr:housenumber":"5",
    "addr:postcode":"2445",
    "addr:street":"John Phillip Drv",
    "iso:country":"AU",
    "sg:address":"5 John Phillip Drv",
    "sg:city":"Bonny Hills",
    "sg:classifiers":[
        {
            "category":"Professional",
            "subcategory":"Art Services",
            "type":"Services"
        }
    ],
    "sg:phone":"+61 2 6585 5148",
    "sg:postcode":"2445",
    "sg:province":"NSW",
    "sg:tags":[
        "decorator",
        "painter"
    ],
    "wof:name":"Holmes Painting",
    "wof:placetype":"venue"
},
  "geometry": {"coordinates":[152.83485400000001,-31.592768],"type":"Point"}
}