{
  "type": "Feature",
  "properties": {
    "iso:country":"AU",
    "sg:address":"Cnr Ernest St & Park Ave",
    "sg:city":"Cammeray",
    "sg:classifiers":[
        {
            "category":"Sports & Exercise",
            "subcategory":"Sports Center",
            "type":"Entertainment"
        }
    ],
    "sg:phone":"+61 412 676 527",
    "sg:postcode":"2062",
    "sg:province":"NSW",
    "sg:tags":[
        "coach",
        "tennis"
    ],
    "wof:name":"Cammeray Tennis Coaching",
    "wof:placetype":"venue"
},
  "geometry": {"coordinates":[151.21307373100001,-33.8273582458],"type":"Point"}
}