{
  "type": "Feature",
  "properties": {
    "addr:full":"Meurantis La Glenwood Park NSW 2768",
    "addr:postcode":"2768",
    "iso:country":"AU",
    "sg:address":"Meurantis La",
    "sg:city":"Glenwood Park",
    "sg:classifiers":[
        {
            "category":"Building & Trades",
            "subcategory":"Construction",
            "type":"Services"
        }
    ],
    "sg:phone":"+61 2 9676 3133",
    "sg:postcode":"2768",
    "sg:province":"NSW",
    "sg:tags":[
        "contractor"
    ],
    "wof:name":"Westminster Homes Pty Ltd",
    "wof:placetype":"venue"
},
  "geometry": {"coordinates":[150.92962600000001,-33.728397],"type":"Point"}
}