{
  "type": "Feature",
  "properties": {
    "addr:full":"3 Kingsfordsmith St Tamworth NSW 2340",
    "addr:housenumber":"3",
    "addr:postcode":"2340",
    "addr:street":"Kingsfordsmith St",
    "iso:country":"AU",
    "sg:address":"3 Kingsfordsmith St",
    "sg:city":"Tamworth",
    "sg:classifiers":[
        {
            "category":"Farming",
            "subcategory":"Dairy Farm",
            "type":"Manufacturing & Wholesale Goods"
        }
    ],
    "sg:phone":"+61 2 6762 1236",
    "sg:postcode":"2340",
    "sg:province":"NSW",
    "sg:tags":[
        "wholesaler",
        "product",
        "mfrs"
    ],
    "wof:name":"National Foods Limited",
    "wof:placetype":"venue"
},
  "geometry": {"coordinates":[150.897872925,-31.0915679932],"type":"Point"}
}