{
  "type": "Feature",
  "properties": {
    "addr:full":"43 Lee Point Rd Moil NT 0810",
    "addr:housenumber":"43",
    "addr:postcode":"nt 0810",
    "addr:street":"Lee Point Rd",
    "iso:country":"AU",
    "sg:address":"43 Lee Point Rd",
    "sg:city":"Moil",
    "sg:classifiers":[
        {
            "category":"Professional",
            "subcategory":"Art Services",
            "type":"Services"
        }
    ],
    "sg:phone":"+61 408 847 448",
    "sg:postcode":"0810",
    "sg:province":"NT",
    "sg:tags":[
        "decorator",
        "painter"
    ],
    "wof:name":"Michael Anasis Painting Service",
    "wof:placetype":"venue"
},
  "geometry": {"coordinates":[130.88424682600001,-12.3901443481],"type":"Point"}
}