{
  "type": "Feature",
  "properties": {
    "addr:full":"115 Plenty Rd Bundoora VIC 3083",
    "addr:housenumber":"115",
    "addr:postcode":"3083",
    "addr:street":"Plenty Rd",
    "iso:country":"AU",
    "sg:address":"115 Plenty Rd",
    "sg:city":"Bundoora",
    "sg:classifiers":[
        {
            "category":"Health Services",
            "subcategory":"Doctor",
            "type":"Services"
        }
    ],
    "sg:phone":"+61 3 9467 5555",
    "sg:postcode":"3083",
    "sg:province":"VIC",
    "sg:tags":[
        "medical",
        "practitioner"
    ],
    "wof:name":"Hill G J Dr",
    "wof:placetype":"venue"
},
  "geometry": {"coordinates":[145.061157227,-37.6933784485],"type":"Point"}
}