{
  "type": "Feature",
  "properties": {
    "iso:country":"AU",
    "sg:address":"30a Montague St",
    "sg:city":"Balmain",
    "sg:classifiers":[
        {
            "category":"Professional",
            "subcategory":"Art Services",
            "type":"Services"
        }
    ],
    "sg:phone":"+61 2 9810 7311",
    "sg:postcode":"2041",
    "sg:province":"NSW",
    "sg:tags":[
        "interior",
        "designer"
    ],
    "wof:name":"Cate Young Design Pty Ltd",
    "wof:placetype":"venue"
},
  "geometry": {"coordinates":[151.17781099999999,-33.858013],"type":"Point"}
}