{
  "type": "Feature",
  "properties": {
    "iso:country":"AU",
    "sg:address":"25 Dredge St",
    "sg:city":"Yenda",
    "sg:classifiers":[
        {
            "category":"Building & Trades",
            "subcategory":"Construction",
            "type":"Services"
        }
    ],
    "sg:phone":"+61 2 6968 1547",
    "sg:postcode":"2681",
    "sg:province":"NSW",
    "sg:tags":[
        "earth",
        "excavating",
        "moving",
        "contractor"
    ],
    "wof:name":"Kirkman Excavations",
    "wof:placetype":"venue"
},
  "geometry": {"coordinates":[146.19212300000001,-34.253441],"type":"Point"}
}