{
  "type": "Feature",
  "properties": {
    "addr:full":"34 Banksia Rd Welshpool WA 6106",
    "addr:housenumber":"34",
    "addr:postcode":"6106",
    "addr:street":"Banksia Rd",
    "iso:country":"AU",
    "sg:address":"34 Banksia Rd",
    "sg:city":"Welshpool",
    "sg:classifiers":[
        {
            "category":"Manufacturing",
            "subcategory":"Metals",
            "type":"Manufacturing & Wholesale Goods"
        }
    ],
    "sg:phone":"+61 8 9451 2844",
    "sg:postcode":"6106",
    "sg:province":"WA",
    "sg:tags":[
        "sheet",
        "worker"
    ],
    "wof:name":"Mitchell Industries W.A.",
    "wof:placetype":"venue"
},
  "geometry": {"coordinates":[115.961761475,-31.9963321686],"type":"Point"}
}