{
  "type": "Feature",
  "properties": {
    "addr:full":"114 Delta Street Geebung QLD 4034",
    "addr:housenumber":"114",
    "addr:postcode":"4034",
    "addr:street":"Delta Street",
    "iso:country":"AU",
    "sg:address":"114 Delta Street",
    "sg:city":"Geebung",
    "sg:classifiers":[
        {
            "category":"Building & Trades",
            "subcategory":"Plumbing",
            "type":"Services"
        }
    ],
    "sg:phone":"+61 7 3000 9555",
    "sg:postcode":"4034",
    "sg:province":"QLD",
    "sg:tags":[
        "plumber",
        "gasfitters"
    ],
    "sg:website":"http://www.vosgroup.com",
    "wof:name":"Vos Construction & Joinery (Qld) Pty Ltd",
    "wof:placetype":"venue"
},
  "geometry": {"coordinates":[153.05360400000001,-27.366325],"type":"Point"}
}