{
  "type": "Feature",
  "properties": {
    "addr:full":"39 Springbett St Kambah ACT 2902",
    "addr:housenumber":"39",
    "addr:postcode":"2902",
    "addr:street":"Springbett St",
    "iso:country":"AU",
    "sg:address":"39 Springbett St",
    "sg:city":"Kambah",
    "sg:classifiers":[
        {
            "category":"Utilities",
            "subcategory":"Electric",
            "type":"Services"
        }
    ],
    "sg:phone":"+61 414 314 008",
    "sg:postcode":"2902",
    "sg:province":"ACT",
    "sg:tags":[
        "electrical",
        "contractor"
    ],
    "wof:name":"A & K Electrical",
    "wof:placetype":"venue"
},
  "geometry": {"coordinates":[149.06121826200001,-35.3912200928],"type":"Point"}
}