{
  "type": "Feature",
  "properties": {
    "iso:country":"AU",
    "sg:address":"Unit 11 Brickwork Centre Warehouse Rd",
    "sg:city":"Southport",
    "sg:classifiers":[
        {
            "category":"Shopping",
            "subcategory":"Computers & Home Electronics",
            "type":"Retail Goods"
        }
    ],
    "sg:phone":"+61 7 5531 2599",
    "sg:postcode":"4215",
    "sg:province":"QLD",
    "sg:tags":[
        "equipment",
        "part",
        "electronic"
    ],
    "wof:name":"Prime Electronics",
    "wof:placetype":"venue"
},
  "geometry": {"coordinates":[153.408935547,-27.979801178],"type":"Point"}
}