{
  "type": "Feature",
  "properties": {
    "iso:country":"AU",
    "sg:address":"50 Reid Drv",
    "sg:city":"Coffs Harbour",
    "sg:classifiers":[
        {
            "category":"Building & Trades",
            "subcategory":"Construction",
            "type":"Services"
        }
    ],
    "sg:phone":"+61 2 6651 9968",
    "sg:postcode":"2450",
    "sg:province":"NSW",
    "sg:tags":[
        "window",
        "tinting"
    ],
    "wof:name":"AAA Richard Howell Glass Tinting",
    "wof:placetype":"venue"
},
  "geometry": {"coordinates":[153.10931400000001,-30.309826],"type":"Point"}
}