{
  "type": "Feature",
  "properties": {
    "addr:full":"Unit 2, 18 Josephine St Loganholme QLD 4129",
    "addr:housenumber":"18",
    "addr:postcode":"4129",
    "addr:street":"Josephine St",
    "iso:country":"AU",
    "sg:address":"Unit 2, 18 Josephine St",
    "sg:city":"Loganholme",
    "sg:classifiers":[
        {
            "category":"Manufacturing",
            "subcategory":"Printing",
            "type":"Manufacturing & Wholesale Goods"
        }
    ],
    "sg:phone":"+61 7 3806 2766",
    "sg:postcode":"4129",
    "sg:province":"QLD",
    "sg:tags":[
        "wholesaler",
        "mfrs",
        "greeting",
        "card"
    ],
    "wof:name":"All Australian Greetings",
    "wof:placetype":"venue"
},
  "geometry": {"coordinates":[153.19610595699999,-27.6823310852],"type":"Point"}
}