{
  "type": "Feature",
  "properties": {
    "addr:full":"188 Torrens Rd Renown Park SA 5008",
    "addr:housenumber":"188",
    "addr:postcode":"5008",
    "addr:street":"Torrens Rd",
    "iso:country":"AU",
    "sg:address":"188 Torrens Rd",
    "sg:city":"Renown Park",
    "sg:classifiers":[
        {
            "category":"Health Services",
            "subcategory":"Chiropractor",
            "type":"Services"
        }
    ],
    "sg:phone":"+61 8 8346 3495",
    "sg:postcode":"5008",
    "sg:province":"SA",
    "wof:name":"Supple Rodney & Trevor Drs",
    "wof:placetype":"venue"
},
  "geometry": {"coordinates":[138.570663,-34.888435],"type":"Point"}
}