{
  "type": "Feature",
  "properties": {
    "addr:full":"Pinkerton Rd Coraki NSW 2471",
    "addr:postcode":"2471",
    "addr:street":"Pinkerton Rd",
    "iso:country":"AU",
    "sg:address":"Pinkerton Rd",
    "sg:city":"Coraki",
    "sg:classifiers":[
        {
            "category":"Building & Trades",
            "subcategory":"Plumbing",
            "type":"Services"
        }
    ],
    "sg:phone":"+61 2 6683 2986",
    "sg:postcode":"2471",
    "sg:province":"NSW",
    "sg:tags":[
        "plumber",
        "gasfitters"
    ],
    "wof:name":"Darton Gas",
    "wof:placetype":"venue"
},
  "geometry": {"coordinates":[153.272583008,-28.9464359283],"type":"Point"}
}