{
  "type": "Feature",
  "properties": {
    "addr:full":"10 Lambrook Crt Mackay QLD 4740",
    "addr:housenumber":"10",
    "addr:postcode":"4740",
    "addr:street":"Lambrook Crt",
    "iso:country":"AU",
    "sg:address":"10 Lambrook Crt",
    "sg:city":"Mackay",
    "sg:classifiers":[
        {
            "category":"Building & Trades",
            "subcategory":"Construction",
            "type":"Services"
        }
    ],
    "sg:phone":"+61 7 4954 5214",
    "sg:postcode":"4740",
    "sg:province":"QLD",
    "sg:tags":[
        "contractor"
    ],
    "wof:name":"Graham J.G",
    "wof:placetype":"venue"
},
  "geometry": {"coordinates":[149.09726000000001,-21.163601],"type":"Point"}
}