{
  "type": "Feature",
  "properties": {
    "iso:country":"AU",
    "sg:address":"Lot 52 Stockwell Rd",
    "sg:city":"Angaston",
    "sg:classifiers":[
        {
            "category":"Professional",
            "subcategory":"Engineering",
            "type":"Services"
        }
    ],
    "sg:phone":"+61 8 8564 3608",
    "sg:postcode":"5353",
    "sg:province":"SA",
    "sg:tags":[
        "engineer"
    ],
    "wof:name":"A & G Engineering Pty Ltd",
    "wof:placetype":"venue"
},
  "geometry": {"coordinates":[139.028274536,-34.4914665222],"type":"Point"}
}