{
  "type": "Feature",
  "properties": {
    "iso:country":"AU",
    "sg:address":"30 Fuller St",
    "sg:city":"Collaroy Plateau",
    "sg:classifiers":[
        {
            "category":"Banks & Credit Unions",
            "subcategory":"Bank",
            "type":"Services"
        }
    ],
    "sg:phone":"+61 1300 889 928",
    "sg:postcode":"2097",
    "sg:province":"NSW",
    "sg:tags":[
        "broker",
        "mortgage"
    ],
    "wof:name":"The Brokerage Pty Ltd",
    "wof:placetype":"venue"
},
  "geometry": {"coordinates":[151.28729248100001,-33.7295532227],"type":"Point"}
}