{
  "type": "Feature",
  "properties": {
    "addr:full":"40 Shannon St Birdwood SA 5234",
    "addr:housenumber":"40",
    "addr:postcode":"5234",
    "addr:street":"Shannon St",
    "iso:country":"AU",
    "sg:address":"40 Shannon St",
    "sg:city":"Birdwood",
    "sg:classifiers":[
        {
            "category":"Health Services",
            "subcategory":"Dentist",
            "type":"Services"
        }
    ],
    "sg:phone":"+61 8 8568 5013",
    "sg:postcode":"5234",
    "sg:province":"SA",
    "wof:name":"Birdwood Dental Surgery",
    "wof:placetype":"venue"
},
  "geometry": {"coordinates":[138.959259033,-34.8195838928],"type":"Point"}
}