{
  "type": "Feature",
  "properties": {
    "addr:full":"513-519 Wattle St Ultimo NSW 2007",
    "addr:postcode":"513-519;2007",
    "addr:street":"Wattle St",
    "iso:country":"AU",
    "sg:address":"513-519 Wattle St",
    "sg:city":"Ultimo",
    "sg:classifiers":[
        {
            "category":"Shopping",
            "subcategory":"Computers & Home Electronics",
            "type":"Retail Goods"
        }
    ],
    "sg:phone":"+61 1300 773 334",
    "sg:postcode":"2007",
    "sg:province":"NSW",
    "sg:tags":[
        "global",
        "positioning",
        "system"
    ],
    "wof:name":"Smart Car Technologies",
    "wof:placetype":"venue"
},
  "geometry": {"coordinates":[151.1980896,-33.8837966919],"type":"Point"}
}