{
  "type": "Feature",
  "properties": {
    "iso:country":"AU",
    "sg:address":"81 Grindle Rd",
    "sg:city":"Rocklea",
    "sg:classifiers":[
        {
            "category":"Wholesale",
            "subcategory":"Office Equipment",
            "type":"Manufacturing & Wholesale Goods"
        }
    ],
    "sg:phone":"+61 1300 361 483",
    "sg:postcode":"4106",
    "sg:province":"QLD",
    "sg:tags":[
        "hire",
        "workshop",
        "factory"
    ],
    "wof:name":"On Site Rentals",
    "wof:placetype":"venue"
},
  "geometry": {"coordinates":[153.00131225600001,-27.554851532],"type":"Point"}
}