{
  "type": "Feature",
  "properties": {
    "addr:full":"2192 Maroondah Hwy Buxton VIC 3711",
    "addr:housenumber":"2192",
    "addr:postcode":"3711",
    "addr:street":"Maroondah Hwy",
    "iso:country":"AU",
    "sg:address":"2192 Maroondah Hwy",
    "sg:city":"Buxton",
    "sg:classifiers":[
        {
            "category":"Travel",
            "subcategory":"Hotels & Motels",
            "type":"Entertainment"
        }
    ],
    "sg:phone":"+61 3 5774 7381",
    "sg:postcode":"3711",
    "sg:province":"VIC",
    "sg:tags":[
        "accommodation"
    ],
    "wof:name":"Buxton Hotel Motel",
    "wof:placetype":"venue"
},
  "geometry": {"coordinates":[145.709106445,-37.4228591919],"type":"Point"}
}