{
  "type": "Feature",
  "properties": {
    "addr:full":"Ste 2/ 1307 Pacific Hwy Turramurra NSW 2074",
    "addr:housenumber":"/ 1307",
    "addr:postcode":"2074",
    "addr:street":"Pacific Hwy",
    "iso:country":"AU",
    "sg:address":"Ste 2/ 1307 Pacific Hwy",
    "sg:city":"Turramurra",
    "sg:classifiers":[
        {
            "category":"Health Services",
            "subcategory":"Doctor",
            "type":"Services"
        }
    ],
    "sg:phone":"+61 2 9144 6227",
    "sg:postcode":"2074",
    "sg:province":"NSW",
    "sg:tags":[
        "podiatrist"
    ],
    "wof:name":"Henry Renee",
    "wof:placetype":"venue"
},
  "geometry": {"coordinates":[151.1277771,-33.7333526611],"type":"Point"}
}