{
  "type": "Feature",
  "properties": {
    "addr:full":"Bruce Hwy Bellenden Ker QLD 4871",
    "addr:postcode":"4871",
    "addr:street":"Bruce Hwy;Ker",
    "iso:country":"AU",
    "sg:address":"Bruce Hwy",
    "sg:city":"Bellenden Ker",
    "sg:classifiers":[
        {
            "category":"Farming",
            "subcategory":"Farm",
            "type":"Manufacturing & Wholesale Goods"
        }
    ],
    "sg:phone":"+61 7 4067 1180",
    "sg:postcode":"4871",
    "sg:province":"QLD",
    "sg:tags":[
        "farmer"
    ],
    "wof:name":"Calcagno B",
    "wof:placetype":"venue"
},
  "geometry": {"coordinates":[145.91993713400001,-17.271478653],"type":"Point"}
}