{
  "type": "Feature",
  "properties": {
    "addr:full":"Bourke St Carrington NSW 2294",
    "addr:postcode":"2294",
    "addr:street":"Bourke St",
    "iso:country":"AU",
    "sg:address":"Bourke St",
    "sg:city":"Carrington",
    "sg:classifiers":[
        {
            "category":"Travel",
            "subcategory":"Hotels & Motels",
            "type":"Entertainment"
        }
    ],
    "sg:phone":"+61 2 4961 3044",
    "sg:postcode":"2294",
    "sg:province":"NSW",
    "sg:tags":[
        "accommodation"
    ],
    "wof:name":"Criterion Hotel",
    "wof:placetype":"venue"
},
  "geometry": {"coordinates":[151.767822266,-32.9121131897],"type":"Point"}
}