{
  "type": "Feature",
  "properties": {
    "iso:country":"AU",
    "sg:address":"94 Laggan Rd",
    "sg:city":"Crookwell",
    "sg:classifiers":[
        {
            "category":"Banks & Credit Unions",
            "subcategory":"Investment Brokerage",
            "type":"Services"
        }
    ],
    "sg:phone":"+61 2 4832 1706",
    "sg:postcode":"2583",
    "sg:province":"NSW",
    "sg:tags":[
        "radiator",
        "motor"
    ],
    "wof:name":"Evans Bodyworks Crookwell",
    "wof:placetype":"venue"
},
  "geometry": {"coordinates":[149.47511291500001,-34.4479866028],"type":"Point"}
}