{
  "type": "Feature",
  "properties": {
    "addr:full":"Shop 2, 2 Cohen St Belconnen ACT 2617",
    "addr:housenumber":"shop;2",
    "addr:postcode":"2617",
    "addr:street":"Cohen St",
    "iso:country":"AU",
    "sg:address":"Shop 2, 2 Cohen St",
    "sg:city":"Belconnen",
    "sg:classifiers":[
        {
            "category":"Restaurant",
            "type":"Food & Drink"
        }
    ],
    "sg:phone":"+61 2 6251 3919",
    "sg:postcode":"2617",
    "sg:province":"ACT",
    "wof:name":"Cafe De Chine",
    "wof:placetype":"venue"
},
  "geometry": {"coordinates":[149.05891418499999,-35.2403259277],"type":"Point"}
}