{
  "type": "Feature",
  "properties": {
    "iso:country":"AU",
    "sg:address":"2 Martin St",
    "sg:city":"Irymple",
    "sg:classifiers":[
        {
            "category":"Building & Trades",
            "subcategory":"Construction",
            "type":"Services"
        }
    ],
    "sg:phone":"+61 3 5024 5082",
    "sg:postcode":"3498",
    "sg:province":"VIC",
    "sg:tags":[
        "renovation",
        "alterations",
        "extension",
        "contractor"
    ],
    "wof:name":"P.W. & C.A. O'Reilly",
    "wof:placetype":"venue"
},
  "geometry": {"coordinates":[142.173950195,-34.2353782654],"type":"Point"}
}