{
  "type": "Feature",
  "properties": {
    "addr:full":"Level 1/ 209 Lords Pl Orange NSW 2800",
    "addr:housenumber":"/ 209",
    "addr:postcode":"2800",
    "addr:street":"Lords Pl",
    "iso:country":"AU",
    "sg:address":"Level 1/ 209 Lords Pl",
    "sg:city":"Orange",
    "sg:classifiers":[
        {
            "category":"Professional",
            "subcategory":"Art Services",
            "type":"Services"
        }
    ],
    "sg:phone":"+61 2 6360 0222",
    "sg:postcode":"2800",
    "sg:province":"NSW",
    "sg:tags":[
        "graphic",
        "designer"
    ],
    "wof:name":"Sauce Design",
    "wof:placetype":"venue"
},
  "geometry": {"coordinates":[149.10092163100001,-33.284286499],"type":"Point"}
}