{
  "type": "Feature",
  "properties": {
    "addr:full":"27 Quintin St Roma QLD 4455",
    "addr:housenumber":"27",
    "addr:postcode":"4455",
    "addr:street":"Quintin St",
    "iso:country":"AU",
    "sg:address":"27 Quintin St",
    "sg:city":"Roma",
    "sg:classifiers":[
        {
            "category":"Health Services",
            "subcategory":"Doctor",
            "type":"Services"
        }
    ],
    "sg:phone":"+61 7 4622 2266",
    "sg:postcode":"4455",
    "sg:province":"QLD",
    "sg:tags":[
        "medical",
        "practitioner"
    ],
    "wof:name":"Maranoa Medical Centre",
    "wof:placetype":"venue"
},
  "geometry": {"coordinates":[148.78692626899999,-26.5710067749],"type":"Point"}
}