{
  "type": "Feature",
  "properties": {
    "addr:full":"John Fawkner Hospital 267 Moreland Rd Coburg VIC 3058",
    "addr:housenumber":"267",
    "addr:postcode":"3058",
    "addr:street":"Moreland Rd",
    "iso:country":"AU",
    "sg:address":"John Fawkner Hospital 267 Moreland Rd",
    "sg:city":"Coburg",
    "sg:classifiers":[
        {
            "category":"Health Services",
            "subcategory":"Doctor",
            "type":"Services"
        }
    ],
    "sg:phone":"+61 3 9383 2744",
    "sg:postcode":"3058",
    "sg:province":"VIC",
    "sg:tags":[
        "medical",
        "practitioner"
    ],
    "wof:name":"Smith Neil Dr",
    "wof:placetype":"venue"
},
  "geometry": {"coordinates":[144.95932006800001,-37.7547111511],"type":"Point"}
}