{
  "type": "Feature",
  "properties": {
    "iso:country":"AU",
    "sg:address":"42A Church St",
    "sg:city":"Hawthorn",
    "sg:classifiers":[
        {
            "category":"Health Services",
            "subcategory":"Health Practitioner",
            "type":"Services"
        }
    ],
    "sg:phone":"+61 3 9819 3628",
    "sg:postcode":"3122",
    "sg:province":"VIC",
    "sg:tags":[
        "acupuncture"
    ],
    "wof:name":"Li Wong",
    "wof:placetype":"venue"
},
  "geometry": {"coordinates":[145.02189636200001,-37.8145370483],"type":"Point"}
}