{
  "type": "Feature",
  "properties": {
    "iso:country":"AU",
    "sg:address":"100 Barton St",
    "sg:city":"Mayfield",
    "sg:classifiers":[
        {
            "category":"Health Services",
            "subcategory":"Health Practitioner",
            "type":"Services"
        }
    ],
    "sg:phone":"+61 2 4967 3419",
    "sg:postcode":"2304",
    "sg:province":"NSW",
    "sg:tags":[
        "reiki"
    ],
    "wof:name":"Annette Moxey",
    "wof:placetype":"venue"
},
  "geometry": {"coordinates":[151.73701477,-32.8897514343],"type":"Point"}
}