{
  "type": "Feature",
  "properties": {
    "addr:full":"14 Browning St Portland VIC 3305",
    "addr:housenumber":"14",
    "addr:postcode":"3305",
    "addr:street":"Browning St",
    "iso:country":"AU",
    "sg:address":"14 Browning St",
    "sg:city":"Portland",
    "sg:classifiers":[
        {
            "category":"Fast Food",
            "type":"Food & Drink"
        }
    ],
    "sg:phone":"+61 3 5523 1797",
    "sg:postcode":"3305",
    "sg:province":"VIC",
    "sg:tags":[
        "away",
        "take"
    ],
    "wof:name":"Browning St Milkbar",
    "wof:placetype":"venue"
},
  "geometry": {"coordinates":[141.592559814,-38.339805603],"type":"Point"}
}