{
  "type": "Feature",
  "properties": {
    "addr:full":"81- 87 Sharton Ave Buccan QLD 4207",
    "addr:housenumber":"87",
    "addr:postcode":"4207",
    "addr:street":"Sharton Ave",
    "iso:country":"AU",
    "sg:address":"81- 87 Sharton Ave",
    "sg:city":"Buccan",
    "sg:classifiers":[
        {
            "category":"Commercial Area",
            "type":"Public Place"
        }
    ],
    "sg:phone":"+61 7 3805 1211",
    "sg:postcode":"4207",
    "sg:province":"QLD",
    "sg:tags":[
        "heavy",
        "carrier"
    ],
    "wof:name":"Cliff's Towing & Heavy Haulage Pty Ltd",
    "wof:placetype":"venue"
},
  "geometry": {"coordinates":[153.15191650400001,-27.7325458527],"type":"Point"}
}