{
  "type": "Feature",
  "properties": {
    "addr:full":"28 Hay St Corowa NSW 2646",
    "addr:housenumber":"28",
    "addr:postcode":"2646",
    "addr:street":"Hay St",
    "iso:country":"AU",
    "sg:address":"28 Hay St",
    "sg:city":"Corowa",
    "sg:classifiers":[
        {
            "category":"Building & Trades",
            "subcategory":"Pest Control",
            "type":"Services"
        }
    ],
    "sg:phone":"+61 428 331 383",
    "sg:postcode":"2646",
    "sg:province":"NSW",
    "wof:name":"Border Pest Control",
    "wof:placetype":"venue"
},
  "geometry": {"coordinates":[146.37886047399999,-35.991985321],"type":"Point"}
}