{
  "type": "Feature",
  "properties": {
    "iso:country":"AU",
    "sg:address":"453 Morphett Rd",
    "sg:city":"Oaklands Park",
    "sg:classifiers":[
        {
            "category":"Health Services",
            "subcategory":"Health Practitioner",
            "type":"Services"
        }
    ],
    "sg:phone":"+61 8 8375 7040",
    "sg:postcode":"5046",
    "sg:province":"SA",
    "sg:tags":[
        "psychologist"
    ],
    "wof:name":"Marion Psychology",
    "wof:placetype":"venue"
},
  "geometry": {"coordinates":[138.540771,-35.013565],"type":"Point"}
}