{
  "type": "Feature",
  "properties": {
    "iso:country":"AU",
    "sg:address":"25 Harrier Ave",
    "sg:city":"Loganholme",
    "sg:classifiers":[
        {
            "category":"Building & Trades",
            "subcategory":"Construction",
            "type":"Services"
        }
    ],
    "sg:phone":"+61 418 733 191",
    "sg:postcode":"4129",
    "sg:province":"QLD",
    "sg:tags":[
        "concrete",
        "contractor"
    ],
    "wof:name":"Cambridge Concrete Services",
    "wof:placetype":"venue"
},
  "geometry": {"coordinates":[153.18153381400001,-27.6816272736],"type":"Point"}
}