{
  "type": "Feature",
  "properties": {
    "addr:full":"PO Box 4044 Alfredton VIC 3350",
    "addr:postcode":"3350",
    "iso:country":"AU",
    "sg:address":"PO Box 4044",
    "sg:city":"Alfredton",
    "sg:classifiers":[
        {
            "category":"Manufacturing",
            "subcategory":"Metals",
            "type":"Manufacturing & Wholesale Goods"
        }
    ],
    "sg:phone":"+61 407 530 158",
    "sg:postcode":"3350",
    "sg:province":"VIC",
    "sg:tags":[
        "steel",
        "fabricator",
        "mfrs"
    ],
    "wof:name":"Golden City Stainless",
    "wof:placetype":"venue"
},
  "geometry": {"coordinates":[143.80921900000001,-37.551579],"type":"Point"}
}