{
  "type": "Feature",
  "properties": {
    "iso:country":"AU",
    "sg:address":"2/ 140 Winton Rd",
    "sg:city":"Joondalup",
    "sg:classifiers":[
        {
            "category":"Home & Garden",
            "subcategory":"Building Materials",
            "type":"Retail Goods"
        }
    ],
    "sg:phone":"+61 8 9300 3155",
    "sg:postcode":"6027",
    "sg:province":"WA",
    "sg:tags":[
        "fencing"
    ],
    "wof:name":"Westcoast Lattice & Extenda Fence W.A.",
    "wof:placetype":"venue"
},
  "geometry": {"coordinates":[115.76083374,-31.7404785156],"type":"Point"}
}