{
  "type": "Feature",
  "properties": {
    "addr:full":"107- 111 Main St Murwillumbah NSW 2484",
    "addr:housenumber":"111",
    "addr:postcode":"2484",
    "addr:street":"Main St",
    "iso:country":"AU",
    "sg:address":"107- 111 Main St",
    "sg:city":"Murwillumbah",
    "sg:classifiers":[
        {
            "category":"Professional",
            "subcategory":"Accounting & Tax Preparation",
            "type":"Services"
        }
    ],
    "sg:phone":"+61 2 6672 1844",
    "sg:postcode":"2484",
    "sg:province":"NSW",
    "sg:tags":[
        "accountant",
        "auditor"
    ],
    "wof:name":"Brady Stuart L",
    "wof:placetype":"venue"
},
  "geometry": {"coordinates":[153.40342712399999,-28.3228321075],"type":"Point"}
}