{
  "type": "Feature",
  "properties": {
    "addr:full":"3/ 457 The Esplanade Manly QLD 4179",
    "addr:housenumber":"/ 457",
    "addr:postcode":"4179",
    "addr:street":"The Esplanade",
    "iso:country":"AU",
    "sg:address":"3/ 457",
    "sg:city":"The Esplanade Manly",
    "sg:classifiers":[
        {
            "category":"Health Services",
            "subcategory":"Dentist",
            "type":"Services"
        }
    ],
    "sg:phone":"+61 7 3348 7988",
    "sg:postcode":"4179",
    "sg:province":"QLD",
    "wof:name":"Marina Dental Centre",
    "wof:placetype":"venue"
},
  "geometry": {"coordinates":[153.18328857399999,-27.4465255737],"type":"Point"}
}