{
  "type": "Feature",
  "properties": {
    "addr:full":"Cnr Mile End & Windsor Rds Rouse Hill NSW 2155",
    "addr:postcode":"2155",
    "addr:street":"Cnr Mile",
    "iso:country":"AU",
    "sg:address":"Cnr Mile End & Windsor Rds",
    "sg:city":"Rouse Hill",
    "sg:classifiers":[
        {
            "category":"Fast Food",
            "type":"Food & Drink"
        }
    ],
    "sg:phone":"+61 2 9629 3786",
    "sg:postcode":"2155",
    "sg:province":"NSW",
    "sg:tags":[
        "away",
        "take"
    ],
    "wof:name":"Rouse Hill Take Away",
    "wof:placetype":"venue"
},
  "geometry": {"coordinates":[150.92460632300001,-33.6746711731],"type":"Point"}
}