{
  "type": "Feature",
  "properties": {
    "addr:full":"38 Johnston St Wagga Wagga NSW 2650",
    "addr:housenumber":"38",
    "addr:postcode":"2650",
    "addr:street":"Johnston St",
    "iso:country":"AU",
    "sg:address":"38 Johnston St",
    "sg:city":"Wagga Wagga",
    "sg:classifiers":[
        {
            "category":"Professional",
            "subcategory":"Accounting & Tax Preparation",
            "type":"Services"
        }
    ],
    "sg:phone":"+61 2 6921 3088",
    "sg:postcode":"2650",
    "sg:province":"NSW",
    "sg:tags":[
        "accountant",
        "auditor"
    ],
    "wof:name":"Cummins P M & Co",
    "wof:placetype":"venue"
},
  "geometry": {"coordinates":[147.36972045900001,-35.1076622009],"type":"Point"}
}