{
  "type": "Feature",
  "properties": {
    "addr:full":"334 Stanmore Rd Petersham NSW 2049",
    "addr:housenumber":"334",
    "addr:postcode":"2049",
    "addr:street":"Stanmore Rd",
    "iso:country":"AU",
    "sg:address":"334 Stanmore Rd",
    "sg:city":"Petersham",
    "sg:classifiers":[
        {
            "category":"Organizations",
            "subcategory":"Professional Association",
            "type":"Services"
        }
    ],
    "sg:phone":"+61 2 9560 4111",
    "sg:postcode":"2049",
    "sg:province":"NSW",
    "sg:tags":[
        "web",
        "internet"
    ],
    "sg:website":"http://www.zoomproductions.com.au",
    "wof:name":"Zoom Photography & Video Productions",
    "wof:placetype":"venue"
},
  "geometry": {"coordinates":[151.15741,-33.89595],"type":"Point"}
}