{
  "type": "Feature",
  "properties": {
    "addr:full":"458 High St Maitland NSW 2320",
    "addr:housenumber":"458",
    "addr:postcode":"2320",
    "addr:street":"High St",
    "iso:country":"AU",
    "sg:address":"458 High St",
    "sg:city":"Maitland",
    "sg:classifiers":[
        {
            "category":"Travel",
            "subcategory":"Hotels & Motels",
            "type":"Entertainment"
        }
    ],
    "sg:phone":"+61 2 4933 6566",
    "sg:postcode":"2320",
    "sg:province":"NSW",
    "sg:tags":[
        "pub"
    ],
    "wof:name":"Shenanigans At The Imperial",
    "wof:placetype":"venue"
},
  "geometry": {"coordinates":[151.55342102,-32.731086731],"type":"Point"}
}