{
  "type": "Feature",
  "properties": {
    "iso:country":"AU",
    "sg:address":"Bloomfield St",
    "sg:city":"Alice Springs",
    "sg:classifiers":[
        {
            "category":"Education",
            "subcategory":"University",
            "type":"Public Place"
        }
    ],
    "sg:phone":"+61 8 8951 8300",
    "sg:postcode":"0870",
    "sg:province":"NT",
    "sg:tags":[
        "college",
        "tertiary"
    ],
    "wof:name":"Batchelor Institute of Indigenous Tertiary Education",
    "wof:placetype":"venue"
},
  "geometry": {"coordinates":[133.86524963400001,-23.7178268433],"type":"Point"}
}