{
  "type": "Feature",
  "properties": {
    "addr:full":"7 Jabiru Drv Barmaryee QLD 4703",
    "addr:housenumber":"7",
    "addr:postcode":"4703",
    "addr:street":"Jabiru Drv",
    "iso:country":"AU",
    "sg:address":"7 Jabiru Drv",
    "sg:city":"Barmaryee",
    "sg:classifiers":[
        {
            "category":"Mining & Drilling",
            "type":"Manufacturing & Wholesale Goods"
        }
    ],
    "sg:phone":"+61 7 4925 0035",
    "sg:postcode":"4703",
    "sg:province":"QLD",
    "sg:tags":[
        "equipment",
        "quarrying",
        "supply"
    ],
    "wof:name":"Capricorn Mining Qld",
    "wof:placetype":"venue"
},
  "geometry": {"coordinates":[150.71293640100001,-23.1520423889],"type":"Point"}
}