{
  "type": "Feature",
  "properties": {
    "addr:full":"26 King St Manly Vale NSW 2093",
    "addr:housenumber":"26",
    "addr:postcode":"2093",
    "addr:street":"King St",
    "iso:country":"AU",
    "sg:address":"26 King St",
    "sg:city":"Manly Vale",
    "sg:classifiers":[
        {
            "category":"Arts & Performance",
            "subcategory":"Music",
            "type":"Entertainment"
        }
    ],
    "sg:phone":"+61 2 9948 5348",
    "sg:postcode":"2093",
    "sg:province":"NSW",
    "sg:tags":[
        "mobile",
        "jockey",
        "disc"
    ],
    "wof:name":"Excel Sound Mobile Discos",
    "wof:placetype":"venue"
},
  "geometry": {"coordinates":[151.265701294,-33.7824783325],"type":"Point"}
}