{
  "type": "Feature",
  "properties": {
    "iso:country":"AU",
    "sg:address":"27- 29 Endurance Ave",
    "sg:city":"Queanbeyan",
    "sg:classifiers":[
        {
            "category":"Wholesale",
            "subcategory":"Metals & Minerals",
            "type":"Manufacturing & Wholesale Goods"
        }
    ],
    "sg:phone":"+61 2 6298 4999",
    "sg:postcode":"2620",
    "sg:province":"ACT",
    "sg:tags":[
        "steel",
        "merchant"
    ],
    "wof:name":"Independent Steel Company",
    "wof:placetype":"venue"
},
  "geometry": {"coordinates":[149.247192383,-35.3403167725],"type":"Point"}
}