{
  "type": "Feature",
  "properties": {
    "iso:country":"AU",
    "sg:address":"68 Eurobodalla Rd",
    "sg:city":"Bodalla",
    "sg:classifiers":[
        {
            "category":"Utilities",
            "subcategory":"Water",
            "type":"Services"
        }
    ],
    "sg:phone":"+61 2 4473 5354",
    "sg:postcode":"2545",
    "sg:province":"NSW",
    "sg:tags":[
        "hot",
        "system"
    ],
    "wof:name":"Burnell John",
    "wof:placetype":"venue"
},
  "geometry": {"coordinates":[150.04202270499999,-36.0969352722],"type":"Point"}
}