{
  "type": "Feature",
  "properties": {
    "addr:full":"89 Egerton St Emerald QLD 4720",
    "addr:housenumber":"89",
    "addr:postcode":"4720",
    "addr:street":"Egerton St",
    "iso:country":"AU",
    "sg:address":"89 Egerton St",
    "sg:city":"Emerald",
    "sg:classifiers":[
        {
            "category":"Personal",
            "subcategory":"Beauty Salon",
            "type":"Services"
        }
    ],
    "sg:phone":"+61 7 4982 2687",
    "sg:postcode":"4720",
    "sg:province":"QLD",
    "sg:tags":[
        "hairdresser"
    ],
    "wof:name":"Hayes Kerrie",
    "wof:placetype":"venue"
},
  "geometry": {"coordinates":[148.158737,-23.524292],"type":"Point"}
}