{
  "type": "Feature",
  "properties": {
    "addr:full":"Unit 2 6- 8 Pendrey Crt Woodridge QLD 4114",
    "addr:housenumber":"6 8",
    "addr:postcode":"4114",
    "addr:street":"Pendrey Crt",
    "iso:country":"AU",
    "sg:address":"Unit 2 6- 8 Pendrey Crt",
    "sg:city":"Woodridge",
    "sg:classifiers":[
        {
            "category":"Building & Trades",
            "subcategory":"Equipment Rental",
            "type":"Services"
        }
    ],
    "sg:phone":"+61 1300 922 537",
    "sg:postcode":"4114",
    "sg:province":"QLD",
    "sg:tags":[
        "builder",
        "contractor"
    ],
    "wof:name":"Wacker Australia Pty Ltd",
    "wof:placetype":"venue"
},
  "geometry": {"coordinates":[153.113845825,-27.6211128235],"type":"Point"}
}