{
  "type": "Feature",
  "properties": {
    "addr:full":"Bldg 19, Charles Sturt Industrial Estate, Cheltenh Woodville SA 5011",
    "addr:housenumber":"19",
    "addr:postcode":"5011",
    "addr:street":"Charles Sturt Industrial",
    "iso:country":"AU",
    "sg:address":"Bldg 19, Charles Sturt Industrial Estate, Cheltenh",
    "sg:city":"Woodville",
    "sg:classifiers":[
        {
            "category":"Manufacturing",
            "subcategory":"Lumber",
            "type":"Manufacturing & Wholesale Goods"
        }
    ],
    "sg:phone":"+61 8 8243 1122",
    "sg:postcode":"5011",
    "sg:province":"SA",
    "sg:tags":[
        "sawmillers"
    ],
    "wof:name":"Allen Taylor & Co Ltd",
    "wof:placetype":"venue"
},
  "geometry": {"coordinates":[138.528274536,-34.8747062683],"type":"Point"}
}