{
  "type": "Feature",
  "properties": {
    "addr:full":"1/ 108-112 Florence St Wynnum QLD 4178",
    "addr:housenumber":"/ 108-112",
    "addr:postcode":"4178",
    "addr:street":"Florence St",
    "iso:country":"AU",
    "sg:address":"1/ 108-112 Florence St",
    "sg:city":"Wynnum",
    "sg:classifiers":[
        {
            "category":"Banks & Credit Unions",
            "subcategory":"Investment Brokerage",
            "type":"Services"
        }
    ],
    "sg:phone":"+61 7 3396 0689",
    "sg:postcode":"4178",
    "sg:province":"QLD",
    "sg:tags":[
        "testing",
        "licence",
        "boat"
    ],
    "wof:name":"Bayside Marine Training Centre",
    "wof:placetype":"venue"
},
  "geometry": {"coordinates":[153.172485352,-27.4446601868],"type":"Point"}
}