{
  "type": "Feature",
  "properties": {
    "addr:full":"17- 19 Arnold St Box Hill VIC 3128",
    "addr:housenumber":"19",
    "addr:postcode":"3128",
    "addr:street":"Arnold St",
    "iso:country":"AU",
    "sg:address":"17- 19 Arnold St",
    "sg:city":"Box Hill",
    "sg:classifiers":[
        {
            "category":"Health Services",
            "subcategory":"Health Practitioner",
            "type":"Services"
        }
    ],
    "sg:phone":"+61 3 9898 2400",
    "sg:postcode":"3128",
    "sg:province":"VIC",
    "sg:tags":[
        "physiotherapist"
    ],
    "sg:website":"http://www.physiotherapy.asn.au",
    "wof:name":"Active Health Solutions",
    "wof:placetype":"venue"
},
  "geometry": {"coordinates":[145.11730957,-37.8142318726],"type":"Point"}
}