{
  "type": "Feature",
  "properties": {
    "addr:full":"PO Box 144 Casula NSW 2170",
    "addr:postcode":"2170",
    "iso:country":"AU",
    "sg:address":"PO Box 144",
    "sg:city":"Casula",
    "sg:classifiers":[
        {
            "category":"Professional",
            "subcategory":"Detective & Security Services",
            "type":"Services"
        }
    ],
    "sg:phone":"+61 408 750 180",
    "sg:postcode":"2170",
    "sg:province":"NSW",
    "sg:tags":[
        "consultant",
        "system"
    ],
    "wof:name":"Weber Technologies",
    "wof:placetype":"venue"
},
  "geometry": {"coordinates":[150.90397644000001,-33.9497909546],"type":"Point"}
}