{
  "type": "Feature",
  "properties": {
    "iso:country":"AU",
    "sg:address":"1 Heather St",
    "sg:city":"Bentleigh East",
    "sg:classifiers":[
        {
            "category":"Food & Beverages",
            "subcategory":"Supermarket",
            "type":"Retail Goods"
        }
    ],
    "sg:phone":"+61 3 9570 4240",
    "sg:postcode":"3165",
    "sg:province":"VIC",
    "sg:tags":[
        "grocery",
        "store"
    ],
    "wof:name":"Ritchies Supa IGA",
    "wof:placetype":"venue"
},
  "geometry": {"coordinates":[145.057296753,-37.919883728],"type":"Point"}
}