{
  "type": "Feature",
  "properties": {
    "addr:full":"Parkinson St Weston ACT 2611",
    "addr:postcode":"2611",
    "addr:street":"Parkinson St",
    "iso:country":"AU",
    "sg:address":"Parkinson St",
    "sg:city":"Weston",
    "sg:classifiers":[
        {
            "category":"Social Services",
            "subcategory":"Adult Care",
            "type":"Services"
        }
    ],
    "sg:phone":"+61 2 6288 4744",
    "sg:postcode":"2611",
    "sg:province":"ACT",
    "sg:tags":[
        "aged"
    ],
    "wof:name":"Communities@Work",
    "wof:placetype":"venue"
},
  "geometry": {"coordinates":[149.05502319300001,-35.342590332],"type":"Point"}
}