{
  "type": "Feature",
  "properties": {
    "addr:full":"366/ 150 Queen St Woollahra NSW 2025",
    "addr:housenumber":"366 / 150",
    "addr:postcode":"2025",
    "addr:street":"Queen St",
    "iso:country":"AU",
    "sg:address":"366/ 150 Queen St",
    "sg:city":"Woollahra",
    "sg:classifiers":[
        {
            "category":"Wholesale",
            "subcategory":"Construction Materials",
            "type":"Manufacturing & Wholesale Goods"
        }
    ],
    "sg:phone":"+61 2 9386 9126",
    "sg:postcode":"2025",
    "sg:province":"NSW",
    "sg:tags":[
        "wholesaler",
        "lighting",
        "mfrs",
        "accessory"
    ],
    "wof:name":"Prisma Decor",
    "wof:placetype":"venue"
},
  "geometry": {"coordinates":[151.23840332,-33.8880729675],"type":"Point"}
}