{
  "type": "Feature",
  "properties": {
    "iso:country":"AU",
    "sg:address":"4 Grace St",
    "sg:city":"Sandy Bay",
    "sg:classifiers":[
        {
            "category":"Organizations",
            "subcategory":"Labor Organization",
            "type":"Services"
        }
    ],
    "sg:phone":"+61 3 6226 7575",
    "sg:postcode":"7005",
    "sg:province":"TAS",
    "sg:tags":[
        "union"
    ],
    "wof:name":"National Tertiary Education Union",
    "wof:placetype":"venue"
},
  "geometry": {"coordinates":[147.32974243199999,-42.8999938965],"type":"Point"}
}