{
  "type": "Feature",
  "properties": {
    "addr:full":"83 Kensington Rd Norwood SA 5067",
    "addr:housenumber":"83",
    "addr:postcode":"5067",
    "addr:street":"Kensington Rd",
    "iso:country":"AU",
    "sg:address":"83 Kensington Rd",
    "sg:city":"Norwood",
    "sg:classifiers":[
        {
            "category":"Health Services",
            "subcategory":"Doctor",
            "type":"Services"
        }
    ],
    "sg:phone":"+61 8 8333 0129",
    "sg:postcode":"5067",
    "sg:province":"SA",
    "sg:tags":[
        "medical",
        "practitioner"
    ],
    "wof:name":"Restoration Clinics Of Australia",
    "wof:placetype":"venue"
},
  "geometry": {"coordinates":[138.633666992,-34.927444458],"type":"Point"}
}