{
  "type": "Feature",
  "properties": {
    "addr:full":"8 Ascot Ave Sandy Bay TAS 7005",
    "addr:housenumber":"8",
    "addr:postcode":"7005",
    "addr:street":"Ascot Ave",
    "iso:country":"AU",
    "sg:address":"8 Ascot Ave",
    "sg:city":"Sandy Bay",
    "sg:classifiers":[
        {
            "category":"Wholesale",
            "subcategory":"Non-durable Goods",
            "type":"Manufacturing & Wholesale Goods"
        }
    ],
    "sg:phone":"+61 3 6225 3883",
    "sg:postcode":"7005",
    "sg:province":"TAS",
    "sg:tags":[
        "wholesaler",
        "craft",
        "mfrs"
    ],
    "wof:name":"Noras Craft",
    "wof:placetype":"venue"
},
  "geometry": {"coordinates":[147.343841553,-42.9159660339],"type":"Point"}
}