{
  "type": "Feature",
  "properties": {
    "addr:full":"7 Miller St Parramatta Park QLD 4870",
    "addr:housenumber":"7",
    "addr:postcode":"4870",
    "addr:street":"Miller St",
    "iso:country":"AU",
    "sg:address":"7 Miller St",
    "sg:city":"Parramatta Park",
    "sg:classifiers":[
        {
            "category":"Sports & Exercise",
            "subcategory":"Gym",
            "type":"Entertainment"
        }
    ],
    "sg:phone":"+61 7 4031 8000",
    "sg:postcode":"4870",
    "sg:province":"QLD",
    "sg:tags":[
        "meditation"
    ],
    "wof:name":"Siloam Centre",
    "wof:placetype":"venue"
},
  "geometry": {"coordinates":[145.765426636,-16.924785614],"type":"Point"}
}