{
  "type": "Feature",
  "properties": {
    "addr:full":"PO Box 690 Bendigo VIC 3550",
    "addr:postcode":"3550",
    "iso:country":"AU",
    "sg:address":"PO Box 690",
    "sg:city":"Bendigo",
    "sg:classifiers":[
        {
            "category":"Utilities",
            "subcategory":"Water",
            "type":"Services"
        }
    ],
    "sg:phone":"+61 3 5439 3748",
    "sg:postcode":"3550",
    "sg:province":"VIC",
    "sg:tags":[
        "equipment",
        "treatment"
    ],
    "wof:name":"Drink For Health",
    "wof:placetype":"venue"
},
  "geometry": {"coordinates":[144.28622436500001,-36.7638511658],"type":"Point"}
}