{
  "type": "Feature",
  "properties": {
    "iso:country":"AU",
    "sg:address":"34 Bell St",
    "sg:city":"Kangaroo Point",
    "sg:classifiers":[
        {
            "category":"Personal",
            "type":"Services"
        }
    ],
    "sg:phone":"+61 7 3891 1892",
    "sg:postcode":"4169",
    "sg:province":"QLD",
    "sg:tags":[
        "introduction",
        "social"
    ],
    "wof:name":"Elizabeth Reid & Associates",
    "wof:placetype":"venue"
},
  "geometry": {"coordinates":[153.03515625,-27.4791297913],"type":"Point"}
}