{
  "type": "Feature",
  "properties": {
    "addr:full":"Unit 1/ 3 Hinkler Crt Brendale QLD 4500",
    "addr:housenumber":"3",
    "addr:postcode":"4500",
    "addr:street":"Hinkler Crt",
    "iso:country":"AU",
    "sg:address":"Unit 1/ 3 Hinkler Crt",
    "sg:city":"Brendale",
    "sg:classifiers":[
        {
            "category":"Insurance",
            "subcategory":"Insurance Agent",
            "type":"Services"
        }
    ],
    "sg:phone":"+61 7 3490 9200",
    "sg:postcode":"4500",
    "sg:province":"QLD",
    "sg:tags":[
        "broker"
    ],
    "wof:name":"Assurity Pty Ltd",
    "wof:placetype":"venue"
},
  "geometry": {"coordinates":[152.989746094,-27.3158855438],"type":"Point"}
}