{
  "type": "Feature",
  "properties": {
    "addr:full":"View St Mansfield VIC 3722",
    "addr:postcode":"3722",
    "addr:street":"View St",
    "iso:country":"AU",
    "sg:address":"View St",
    "sg:city":"Mansfield",
    "sg:classifiers":[
        {
            "category":"Education",
            "subcategory":"School",
            "type":"Public Place"
        }
    ],
    "sg:phone":"+61 3 5775 2022",
    "sg:postcode":"3722",
    "sg:province":"VIC",
    "sg:tags":[
        "state",
        "except",
        "nsw"
    ],
    "wof:name":"Mansfield Secondary School",
    "wof:placetype":"venue"
},
  "geometry": {"coordinates":[146.089645386,-37.0623817444],"type":"Point"}
}