{
  "type": "Feature",
  "properties": {
    "iso:country":"AU",
    "sg:address":"123 Queen St",
    "sg:city":"Melbourne",
    "sg:classifiers":[
        {
            "category":"Real Estate",
            "subcategory":"Real Estate Services",
            "type":"Services"
        }
    ],
    "sg:phone":"+61 3 9606 0981",
    "sg:postcode":"3000",
    "sg:province":"VIC",
    "sg:tags":[
        "consultant",
        "property"
    ],
    "wof:name":"Andon Properties",
    "wof:placetype":"venue"
},
  "geometry": {"coordinates":[144.96087646500001,-37.8156929016],"type":"Point"}
}