{
  "type": "Feature",
  "properties": {
    "addr:full":"Shop 4 563 Sydney Rd Seaforth NSW 2092",
    "addr:housenumber":"shop 4 563",
    "addr:postcode":"2092",
    "addr:street":"Sydney Rd",
    "iso:country":"AU",
    "sg:address":"Shop 4 563 Sydney Rd",
    "sg:city":"Seaforth",
    "sg:classifiers":[
        {
            "category":"Banks & Credit Unions",
            "subcategory":"Bank",
            "type":"Services"
        }
    ],
    "sg:phone":"+61 2 9449 6110",
    "sg:postcode":"2092",
    "sg:province":"NSW",
    "sg:tags":[
        "broker",
        "mortgage"
    ],
    "wof:name":"Level 7 Finance",
    "wof:placetype":"venue"
},
  "geometry": {"coordinates":[151.25064086899999,-33.7974700928],"type":"Point"}
}