{
  "type": "Feature",
  "properties": {
    "iso:country":"AU",
    "sg:address":"7 Star St",
    "sg:city":"Macksville",
    "sg:classifiers":[
        {
            "category":"Health Services",
            "subcategory":"Doctor",
            "type":"Services"
        }
    ],
    "sg:phone":"+61 2 6568 1288",
    "sg:postcode":"2447",
    "sg:province":"NSW",
    "sg:tags":[
        "medical",
        "practitioner"
    ],
    "wof:name":"Willcocks N J Adams A R Paton R A & Robertson R C",
    "wof:placetype":"venue"
},
  "geometry": {"coordinates":[152.92193599999999,-30.707939],"type":"Point"}
}