{
  "type": "Feature",
  "properties": {
    "iso:country":"AU",
    "sg:address":"1853 Midlands Hwy",
    "sg:city":"Bagdad",
    "sg:classifiers":[
        {
            "category":"Autos & Motor Vehicles",
            "subcategory":"Fuel & Gas Station",
            "type":"Retail Goods"
        }
    ],
    "sg:phone":"+61 3 6268 6422",
    "sg:postcode":"7030",
    "sg:province":"TAS",
    "wof:name":"Heritage Highway Roadhouse Pty Ltd",
    "wof:placetype":"venue"
},
  "geometry": {"coordinates":[147.22000122099999,-42.6031608582],"type":"Point"}
}