{
  "type": "Feature",
  "properties": {
    "addr:full":"5 Hargraves Crs Ainslie ACT 2602",
    "addr:housenumber":"5",
    "addr:postcode":"2602",
    "addr:street":"Hargraves Crs",
    "iso:country":"AU",
    "sg:address":"5 Hargraves Crs",
    "sg:city":"Ainslie",
    "sg:classifiers":[
        {
            "category":"Building & Trades",
            "subcategory":"Construction",
            "type":"Services"
        }
    ],
    "sg:phone":"+61 2 6248 5518",
    "sg:postcode":"2602",
    "sg:province":"ACT",
    "sg:tags":[
        "contractor"
    ],
    "wof:name":"Bradley HJ Pty Ltd",
    "wof:placetype":"venue"
},
  "geometry": {"coordinates":[149.14654540999999,-35.2622108459],"type":"Point"}
}