{
  "type": "Feature",
  "properties": {
    "addr:full":"205 Byng St Orange NSW 2800",
    "addr:housenumber":"205",
    "addr:postcode":"2800",
    "addr:street":"Byng St",
    "iso:country":"AU",
    "sg:address":"205 Byng St",
    "sg:city":"Orange",
    "sg:classifiers":[
        {
            "category":"Building & Trades",
            "subcategory":"Construction",
            "type":"Services"
        }
    ],
    "sg:phone":"+61 2 6361 1122",
    "sg:postcode":"2800",
    "sg:province":"NSW",
    "sg:tags":[
        "contractor"
    ],
    "wof:name":"Sturgeon Building Services",
    "wof:placetype":"venue"
},
  "geometry": {"coordinates":[149.10823059099999,-33.2825202942],"type":"Point"}
}