{
  "type": "Feature",
  "properties": {
    "addr:full":"Shp 5a/ 2605 Beaudesert Rd Calamvale QLD 4116",
    "addr:housenumber":"5a / 2605",
    "addr:postcode":"4116",
    "addr:street":"Beaudesert Rd",
    "iso:country":"AU",
    "sg:address":"Shp 5a/ 2605 Beaudesert Rd",
    "sg:city":"Calamvale",
    "sg:classifiers":[
        {
            "category":"Travel",
            "subcategory":"Travel Agent",
            "type":"Entertainment"
        }
    ],
    "sg:phone":"+61 7 3711 6040",
    "sg:postcode":"4116",
    "sg:province":"QLD",
    "sg:tags":[
        "consultant"
    ],
    "wof:name":"Best Deal Travel & Tours",
    "wof:placetype":"venue"
},
  "geometry": {"coordinates":[153.04635620100001,-27.6304512024],"type":"Point"}
}