{
  "type": "Feature",
  "properties": {
    "addr:full":"171 Burgundy St Heidelberg VIC 3084",
    "addr:housenumber":"171",
    "addr:postcode":"3084",
    "addr:street":"Burgundy St",
    "iso:country":"AU",
    "sg:address":"171 Burgundy St",
    "sg:city":"Heidelberg",
    "sg:classifiers":[
        {
            "category":"Health Services",
            "subcategory":"Optometrist",
            "type":"Services"
        }
    ],
    "sg:phone":"+61 3 9459 5775",
    "sg:postcode":"3084",
    "sg:province":"VIC",
    "wof:name":"Eyecare Plus Optometrists",
    "wof:placetype":"venue"
},
  "geometry": {"coordinates":[145.06422424300001,-37.7560691833],"type":"Point"}
}