{
  "type": "Feature",
  "properties": {
    "iso:country":"AU",
    "sg:address":"9 Gibbes St",
    "sg:city":"Chatswood",
    "sg:classifiers":[
        {
            "category":"Wholesale",
            "subcategory":"Vending Machines",
            "type":"Manufacturing & Wholesale Goods"
        }
    ],
    "sg:phone":"+61 2 9417 8588",
    "sg:postcode":"2067",
    "sg:province":"NSW",
    "sg:tags":[
        "engraving",
        "accessory"
    ],
    "sg:website":"http://www.yarhamville.com.au",
    "wof:name":"Yarhamville Pty Ltd",
    "wof:placetype":"venue"
},
  "geometry": {"coordinates":[151.20046997099999,-33.7899551392],"type":"Point"}
}