{
  "type": "Feature",
  "properties": {
    "iso:country":"AU",
    "sg:address":"Shop 2, 12e Quay St",
    "sg:city":"Haymarket",
    "sg:classifiers":[
        {
            "category":"Shopping",
            "subcategory":"Clothing, Apparel, & Fashions",
            "type":"Retail Goods"
        }
    ],
    "sg:phone":"+61 2 9281 3583",
    "sg:postcode":"2000",
    "sg:province":"NSW",
    "sg:tags":[
        "sportswear"
    ],
    "wof:name":"Done Art And Design",
    "wof:placetype":"venue"
},
  "geometry": {"coordinates":[151.202957153,-33.880645752],"type":"Point"}
}