{
  "type": "Feature",
  "properties": {
    "addr:full":"99 Wattletree Rd Malvern VIC 3144",
    "addr:housenumber":"99",
    "addr:postcode":"3144",
    "addr:street":"Wattletree Rd",
    "iso:country":"AU",
    "sg:address":"99 Wattletree Rd",
    "sg:city":"Malvern",
    "sg:classifiers":[
        {
            "category":"Health Services",
            "subcategory":"Health Practitioner",
            "type":"Services"
        }
    ],
    "sg:phone":"+61 3 8508 9852",
    "sg:postcode":"3144",
    "sg:province":"VIC",
    "sg:tags":[
        "psychologist"
    ],
    "wof:name":"Johnston David",
    "wof:placetype":"venue"
},
  "geometry": {"coordinates":[145.02720642099999,-37.8620643616],"type":"Point"}
}