{
  "type": "Feature",
  "properties": {
    "addr:full":"52 Churchill Ave Subiaco WA 6008",
    "addr:housenumber":"52",
    "addr:postcode":"6008",
    "addr:street":"Churchill Ave",
    "iso:country":"AU",
    "sg:address":"52 Churchill Ave",
    "sg:city":"Subiaco",
    "sg:classifiers":[
        {
            "category":"Health Services",
            "subcategory":"Doctor",
            "type":"Services"
        }
    ],
    "sg:phone":"+61 8 9380 4224",
    "sg:postcode":"6008",
    "sg:province":"WA",
    "sg:tags":[
        "medical",
        "practitioner"
    ],
    "wof:name":"Minchin David E",
    "wof:placetype":"venue"
},
  "geometry": {"coordinates":[115.83450317400001,-31.9478359222],"type":"Point"}
}