{
  "type": "Feature",
  "properties": {
    "addr:full":"112 Blackwall Rd Woy Woy NSW 2256",
    "addr:housenumber":"112",
    "addr:postcode":"2256",
    "addr:street":"Blackwall Rd",
    "iso:country":"AU",
    "sg:address":"112 Blackwall Rd",
    "sg:city":"Woy Woy",
    "sg:classifiers":[
        {
            "category":"Health Services",
            "subcategory":"Dentist",
            "type":"Services"
        }
    ],
    "sg:phone":"+61 2 4360 2755",
    "sg:postcode":"2256",
    "sg:province":"NSW",
    "sg:tags":[
        "dental",
        "prosthetist"
    ],
    "wof:name":"Boyd Keith",
    "wof:placetype":"venue"
},
  "geometry": {"coordinates":[151.326416016,-33.4894866943],"type":"Point"}
}