{
  "type": "Feature",
  "properties": {
    "addr:full":"Unit 8/ 15 Dyer Rd Bassendean WA 6054",
    "addr:housenumber":"15",
    "addr:postcode":"6054",
    "addr:street":"Dyer Rd",
    "iso:country":"AU",
    "sg:address":"Unit 8/ 15 Dyer Rd",
    "sg:city":"Bassendean",
    "sg:classifiers":[
        {
            "category":"Education",
            "subcategory":"Special Training",
            "type":"Public Place"
        }
    ],
    "sg:phone":"+61 8 9379 1165",
    "sg:postcode":"6054",
    "sg:province":"WA",
    "sg:tags":[
        "development"
    ],
    "wof:name":"Quantum Digital Laboratories",
    "wof:placetype":"venue"
},
  "geometry": {"coordinates":[115.93665313699999,-31.9048957825],"type":"Point"}
}