{
  "type": "Feature",
  "properties": {
    "addr:full":"34 Ray Ave Morphett Vale SA 5162",
    "addr:housenumber":"34",
    "addr:postcode":"5162",
    "addr:street":"Ray Ave",
    "iso:country":"AU",
    "sg:address":"34 Ray Ave",
    "sg:city":"Morphett Vale",
    "sg:classifiers":[
        {
            "category":"Manufacturing",
            "subcategory":"Furniture",
            "type":"Manufacturing & Wholesale Goods"
        }
    ],
    "sg:phone":"+61 8 8382 4215",
    "sg:postcode":"5162",
    "sg:province":"SA",
    "sg:tags":[
        "equipment",
        "hire"
    ],
    "wof:name":"Neon Business Signs (S.A.)",
    "wof:placetype":"venue"
},
  "geometry": {"coordinates":[138.52000427199999,-35.1101455688],"type":"Point"}
}