{
  "type": "Feature",
  "properties": {
    "addr:full":"Shop 15/ 4 Hillcrest Rd Pennant Hills NSW 2120",
    "addr:housenumber":"shop 15 / 4",
    "addr:postcode":"2120",
    "addr:street":"Hillcrest Rd",
    "iso:country":"AU",
    "sg:address":"Shop 15/ 4 Hillcrest Rd",
    "sg:city":"Pennant Hills",
    "sg:classifiers":[
        {
            "category":"Food & Beverages",
            "subcategory":"Fruits & Vegetables",
            "type":"Retail Goods"
        }
    ],
    "sg:phone":"+61 2 9481 0439",
    "sg:postcode":"2120",
    "sg:province":"NSW",
    "sg:tags":[
        "greengrocer",
        "fruiterer"
    ],
    "wof:name":"Harris Farm Markets",
    "wof:placetype":"venue"
},
  "geometry": {"coordinates":[151.06997680699999,-33.737827301],"type":"Point"}
}