{
  "type": "Feature",
  "properties": {
    "iso:country":"AU",
    "sg:address":"44 Jaffa Rd",
    "sg:city":"Dural",
    "sg:classifiers":[
        {
            "category":"Building & Trades",
            "subcategory":"Construction",
            "type":"Services"
        }
    ],
    "sg:phone":"+61 2 9651 7226",
    "sg:postcode":"2158",
    "sg:province":"NSW",
    "sg:tags":[
        "home",
        "air conditioning"
    ],
    "wof:name":"Clint Matthews",
    "wof:placetype":"venue"
},
  "geometry": {"coordinates":[151.025924683,-33.6947021484],"type":"Point"}
}