{
  "type": "Feature",
  "properties": {
    "iso:country":"AU",
    "sg:address":"15 Ocean Ave",
    "sg:city":"Surfers Paradise",
    "sg:classifiers":[
        {
            "category":"Sports & Exercise",
            "subcategory":"Sports Center",
            "type":"Entertainment"
        }
    ],
    "sg:phone":"+61 7 5504 6324",
    "sg:postcode":"4217",
    "sg:province":"QLD",
    "sg:tags":[
        "coach",
        "tennis"
    ],
    "wof:name":"Australian Coaching Network",
    "wof:placetype":"venue"
},
  "geometry": {"coordinates":[153.42869567899999,-27.9932231903],"type":"Point"}
}