{
  "type": "Feature",
  "properties": {
    "iso:country":"AU",
    "sg:address":"24 Ace Ave",
    "sg:city":"Fairfield",
    "sg:classifiers":[
        {
            "category":"Health Services",
            "subcategory":"Health Practitioner",
            "type":"Services"
        }
    ],
    "sg:phone":"+61 2 8704 3495",
    "sg:postcode":"2165",
    "sg:province":"NSW",
    "sg:tags":[
        "naturopath"
    ],
    "wof:name":"Tryfoss Therapies-Keryn Coulter",
    "wof:placetype":"venue"
},
  "geometry": {"coordinates":[150.957763672,-33.8634223938],"type":"Point"}
}