{
  "type": "Feature",
  "properties": {
    "addr:full":"7 Allingham St Ingham QLD 4850",
    "addr:housenumber":"7",
    "addr:postcode":"4850",
    "addr:street":"Allingham St",
    "iso:country":"AU",
    "sg:address":"7 Allingham St",
    "sg:city":"Ingham",
    "sg:classifiers":[
        {
            "category":"Food & Beverages",
            "subcategory":"Fruits & Vegetables",
            "type":"Retail Goods"
        }
    ],
    "sg:phone":"+61 7 4776 1868",
    "sg:postcode":"4850",
    "sg:province":"QLD",
    "sg:tags":[
        "wholesale"
    ],
    "wof:name":"Beemart Enterprises",
    "wof:placetype":"venue"
},
  "geometry": {"coordinates":[146.163864136,-18.6438846588],"type":"Point"}
}