{
  "type": "Feature",
  "properties": {
    "iso:country":"AU",
    "sg:address":"Alvina St",
    "sg:city":"Oakleigh South",
    "sg:classifiers":[
        {
            "category":"Education",
            "subcategory":"School",
            "type":"Public Place"
        }
    ],
    "sg:phone":"+61 3 9544 5664",
    "sg:postcode":"3167",
    "sg:province":"VIC",
    "sg:tags":[
        "state",
        "except",
        "nsw"
    ],
    "wof:name":"Clayton West Primary School",
    "wof:placetype":"venue"
},
  "geometry": {"coordinates":[145.10624694800001,-37.9214668274],"type":"Point"}
}