{
  "type": "Feature",
  "properties": {
    "iso:country":"AU",
    "sg:address":"170 Rousset Rd",
    "sg:city":"Wanneroo",
    "sg:classifiers":[
        {
            "category":"Social Services",
            "subcategory":"Adult Care",
            "type":"Services"
        }
    ],
    "sg:phone":"+61 8 9306 3300",
    "sg:postcode":"6065",
    "sg:province":"WA",
    "sg:tags":[
        "aged"
    ],
    "wof:name":"Alternative Care Inc",
    "wof:placetype":"venue"
},
  "geometry": {"coordinates":[115.829421997,-31.7323932648],"type":"Point"}
}