{
  "type": "Feature",
  "properties": {
    "addr:full":"50 Chaleyer St Rose Bay NSW 2029",
    "addr:housenumber":"50",
    "addr:postcode":"2029",
    "addr:street":"Chaleyer St",
    "iso:country":"AU",
    "sg:address":"50 Chaleyer St",
    "sg:city":"Rose Bay",
    "sg:classifiers":[
        {
            "category":"Building & Trades",
            "subcategory":"Plumbing",
            "type":"Services"
        }
    ],
    "sg:phone":"+61 2 9371 6571",
    "sg:postcode":"2029",
    "sg:province":"NSW",
    "sg:tags":[
        "plumber",
        "gasfitters"
    ],
    "wof:name":"Vaucluse-Watsons Bay Plumbing Drainage & Gas Fitting Services",
    "wof:placetype":"venue"
},
  "geometry": {"coordinates":[151.27458190900001,-33.8771362305],"type":"Point"}
}