{
  "type": "Feature",
  "properties": {
    "iso:country":"AU",
    "sg:address":"1 Short St",
    "sg:city":"Fremantle",
    "sg:classifiers":[
        {
            "category":"Arts & Performance",
            "subcategory":"Theater",
            "type":"Entertainment"
        }
    ],
    "sg:phone":"+61 8 9335 5044",
    "sg:postcode":"6160",
    "sg:province":"WA",
    "sg:tags":[
        "theatre"
    ],
    "wof:name":"Spare Parts Puppet Theatre",
    "wof:placetype":"venue"
},
  "geometry": {"coordinates":[115.745483,-32.053116],"type":"Point"}
}