{
  "type": "Feature",
  "properties": {
    "iso:country":"AU",
    "sg:address":"14 Campbell St",
    "sg:city":"Bowen Hills",
    "sg:classifiers":[
        {
            "category":"Education",
            "subcategory":"Music School",
            "type":"Public Place"
        }
    ],
    "sg:phone":"+61 7 3852 1116",
    "sg:postcode":"4006",
    "sg:province":"QLD",
    "sg:tags":[
        "teacher"
    ],
    "sg:website":"http://www.independentmusic.com.au",
    "wof:name":"Independent Music Academy",
    "wof:placetype":"venue"
},
  "geometry": {"coordinates":[153.036987305,-27.4477500916],"type":"Point"}
}