{
  "type": "Feature",
  "properties": {
    "iso:country":"AU",
    "sg:address":"350 Great Western Hwy",
    "sg:city":"Wentworthville",
    "sg:classifiers":[
        {
            "category":"Autos & Motor Vehicles",
            "subcategory":"Automobile Sales",
            "type":"Retail Goods"
        }
    ],
    "sg:phone":"+61 2 9896 1558",
    "sg:postcode":"2145",
    "sg:province":"NSW",
    "sg:tags":[
        "car",
        "used"
    ],
    "wof:name":"Cortese Brothers Cars Pty Ltd",
    "wof:placetype":"venue"
},
  "geometry": {"coordinates":[150.96777343799999,-33.8149452209],"type":"Point"}
}