{
  "type": "Feature",
  "properties": {
    "addr:full":"Shop 22 Burwood Plaza Burwood NSW 2134",
    "addr:housenumber":"shop 22",
    "addr:postcode":"2134",
    "addr:street":"Burwood Plaza",
    "iso:country":"AU",
    "sg:address":"Shop 22",
    "sg:city":"Burwood Plaza Burwood",
    "sg:classifiers":[
        {
            "category":"Food & Beverages",
            "subcategory":"Specialty",
            "type":"Retail Goods"
        }
    ],
    "sg:phone":"+61 2 9744 0059",
    "sg:postcode":"2134",
    "sg:province":"NSW",
    "sg:tags":[
        "product",
        "health"
    ],
    "wof:name":"O&#039;Sullivans Health Foods",
    "wof:placetype":"venue"
},
  "geometry": {"coordinates":[151.105270386,-33.8701591492],"type":"Point"}
}