{
  "type": "Feature",
  "properties": {
    "iso:country":"AU",
    "sg:address":"41 Main St",
    "sg:city":"Kapunda",
    "sg:classifiers":[
        {
            "category":"Cafe",
            "type":"Food & Drink"
        }
    ],
    "sg:phone":"+61 8 8566 3222",
    "sg:postcode":"5373",
    "sg:province":"SA",
    "wof:name":"Fresh Fields Restaurant",
    "wof:placetype":"venue"
},
  "geometry": {"coordinates":[138.91665649399999,-34.3393554688],"type":"Point"}
}