{
  "type": "Feature",
  "properties": {
    "addr:full":"8 Railway Pde Eastwood NSW 2122",
    "addr:housenumber":"8",
    "addr:postcode":"2122",
    "addr:street":"Railway Pde",
    "iso:country":"AU",
    "sg:address":"8 Railway Pde",
    "sg:city":"Eastwood",
    "sg:classifiers":[
        {
            "category":"Fast Food",
            "type":"Food & Drink"
        }
    ],
    "sg:phone":"+61 2 9874 3788",
    "sg:postcode":"2122",
    "sg:province":"NSW",
    "sg:tags":[
        "away",
        "take"
    ],
    "wof:name":"Pearce Takeaway",
    "wof:placetype":"venue"
},
  "geometry": {"coordinates":[151.08262634299999,-33.7908363342],"type":"Point"}
}