{
  "type": "Feature",
  "properties": {
    "iso:country":"AU",
    "sg:address":"149 Maison Dieu Rd",
    "sg:city":"Singleton",
    "sg:classifiers":[
        {
            "category":"Professional",
            "subcategory":"Engineering",
            "type":"Services"
        }
    ],
    "sg:phone":"+61 2 6572 1115",
    "sg:postcode":"2330",
    "sg:province":"NSW",
    "sg:tags":[
        "engineer"
    ],
    "wof:name":"TFP Engineering Pty Ltd",
    "wof:placetype":"venue"
},
  "geometry": {"coordinates":[151.13540599999999,-32.549534],"type":"Point"}
}