{
  "type": "Feature",
  "properties": {
    "iso:country":"AU",
    "sg:address":"9 Monarch Drv",
    "sg:city":"Deception Bay",
    "sg:classifiers":[
        {
            "category":"Social Services",
            "subcategory":"Child Care",
            "type":"Services"
        }
    ],
    "sg:phone":"+61 7 3888 5355",
    "sg:postcode":"4508",
    "sg:province":"QLD",
    "wof:name":"Deception Bay Childcare",
    "wof:placetype":"venue"
},
  "geometry": {"coordinates":[153.00448608400001,-27.1812553406],"type":"Point"}
}