{
  "type": "Feature",
  "properties": {
    "addr:full":"Elliott Crt Browns Plains QLD 4118",
    "addr:postcode":"4118",
    "addr:street":"Crt",
    "iso:country":"AU",
    "sg:address":"Elliott Crt",
    "sg:city":"Browns Plains",
    "sg:classifiers":[
        {
            "category":"Home & Garden",
            "subcategory":"Building Materials",
            "type":"Retail Goods"
        }
    ],
    "sg:phone":"+61 1300 305 973",
    "sg:postcode":"4118",
    "sg:province":"QLD",
    "sg:tags":[
        "pre-mixed",
        "concrete"
    ],
    "wof:name":"Boral Concrete",
    "wof:placetype":"venue"
},
  "geometry": {"coordinates":[153.032714844,-27.6606464386],"type":"Point"}
}