{
  "type": "Feature",
  "properties": {
    "addr:full":"Nowra Campus 60 Beinda St Bomaderry NSW 2541",
    "addr:housenumber":"60",
    "addr:postcode":"2541",
    "addr:street":"Beinda St",
    "iso:country":"AU",
    "sg:address":"Nowra Campus 60 Beinda St",
    "sg:city":"Bomaderry",
    "sg:classifiers":[
        {
            "category":"Education",
            "subcategory":"Vocational School",
            "type":"Public Place"
        }
    ],
    "sg:phone":"+61 2 4421 9888",
    "sg:postcode":"2541",
    "sg:province":"NSW",
    "sg:tags":[
        "technical",
        "college",
        "trade"
    ],
    "wof:name":"Illawarra Institute Of Technology",
    "wof:placetype":"venue"
},
  "geometry": {"coordinates":[150.599884033,-34.8561935425],"type":"Point"}
}