{
  "type": "Feature",
  "properties": {
    "iso:country":"AU",
    "sg:address":"34 Macmahon St",
    "sg:city":"Hurstville",
    "sg:classifiers":[
        {
            "category":"Health Services",
            "subcategory":"Health Practitioner",
            "type":"Services"
        }
    ],
    "sg:phone":"+61 2 9580 6167",
    "sg:postcode":"2220",
    "sg:province":"NSW",
    "sg:tags":[
        "psychologist"
    ],
    "wof:name":"Llyod Margaret G",
    "wof:placetype":"venue"
},
  "geometry": {"coordinates":[151.101928711,-33.9654083252],"type":"Point"}
}