{
  "type": "Feature",
  "properties": {
    "addr:full":"Unit 3/ 34 O`Sullivan Beach Rd Lonsdale SA 5160",
    "addr:postcode":"5160",
    "addr:street":"34 O`Sullivan Beach Rd",
    "iso:country":"AU",
    "sg:address":"Unit 3/ 34 O`Sullivan Beach Rd",
    "sg:city":"Lonsdale",
    "sg:classifiers":[
        {
            "category":"Autos & Motor Vehicles",
            "subcategory":"Auto Supplies",
            "type":"Retail Goods"
        }
    ],
    "sg:phone":"+61 8 8326 1886",
    "sg:postcode":"5160",
    "sg:province":"SA",
    "sg:tags":[
        "wheel",
        "four",
        "equipment",
        "drive",
        "accessory"
    ],
    "wof:name":"Southern 4WD",
    "wof:placetype":"venue"
},
  "geometry": {"coordinates":[138.50367736800001,-35.1168708801],"type":"Point"}
}