{
  "type": "Feature",
  "properties": {
    "iso:country":"AU",
    "sg:address":"85 Baylis St",
    "sg:city":"Wagga Wagga",
    "sg:classifiers":[
        {
            "category":"Fast Food",
            "type":"Food & Drink"
        }
    ],
    "sg:phone":"+61 2 6921 4428",
    "sg:postcode":"2650",
    "sg:province":"NSW",
    "sg:tags":[
        "away",
        "take"
    ],
    "wof:name":"Montezuma's Mexican Restaurant",
    "wof:placetype":"venue"
},
  "geometry": {"coordinates":[147.36956787099999,-35.1156272888],"type":"Point"}
}