{
  "type": "Feature",
  "properties": {
    "addr:full":"Shop 17 Crowne Plz Terrigal NSW 2260",
    "addr:housenumber":"shop 17",
    "addr:postcode":"2260",
    "addr:street":"Crowne Plz",
    "iso:country":"AU",
    "sg:address":"Shop 17 Crowne Plz",
    "sg:city":"Terrigal",
    "sg:classifiers":[
        {
            "category":"Personal",
            "subcategory":"Beauty Salon",
            "type":"Services"
        }
    ],
    "sg:phone":"+61 2 4385 9944",
    "sg:postcode":"2260",
    "sg:province":"NSW",
    "sg:tags":[
        "hairdresser"
    ],
    "wof:name":"Ellis Perry",
    "wof:placetype":"venue"
},
  "geometry": {"coordinates":[151.44570899999999,-33.4478],"type":"Point"}
}