{
  "type": "Feature",
  "properties": {
    "iso:country":"AU",
    "sg:address":"20 Cumberland St",
    "sg:city":"Cessnock",
    "sg:classifiers":[
        {
            "category":"Professional",
            "subcategory":"Printing & Photocopies",
            "type":"Services"
        }
    ],
    "sg:phone":"+61 409 496 280",
    "sg:postcode":"2325",
    "sg:province":"NSW",
    "sg:tags":[
        "photocopying"
    ],
    "wof:name":"Kelso Colour Print",
    "wof:placetype":"venue"
},
  "geometry": {"coordinates":[151.35745239299999,-32.8354225159],"type":"Point"}
}