{
  "type": "Feature",
  "properties": {
    "iso:country":"AU",
    "sg:address":"26 Mitchell Rd",
    "sg:city":"Alexandria",
    "sg:classifiers":[
        {
            "category":"Professional",
            "subcategory":"Business Services",
            "type":"Services"
        }
    ],
    "sg:phone":"+61 2 9319 4523",
    "sg:postcode":"2015",
    "sg:province":"NSW",
    "sg:tags":[
        "management",
        "event"
    ],
    "wof:name":"Ronni Kahn Event Designs P/L",
    "wof:placetype":"venue"
},
  "geometry": {"coordinates":[151.195114136,-33.8988685608],"type":"Point"}
}