{
  "type": "Feature",
  "properties": {
    "addr:full":"813- 817 Nepean Hwy Rosebud VIC 3939",
    "addr:housenumber":"817",
    "addr:postcode":"3939",
    "addr:street":"Nepean Hwy",
    "iso:country":"AU",
    "sg:address":"813- 817 Nepean Hwy",
    "sg:city":"Rosebud",
    "sg:classifiers":[
        {
            "category":"School Buses",
            "type":"Transportation"
        }
    ],
    "sg:phone":"+61 3 5986 4784",
    "sg:postcode":"3939",
    "sg:province":"VIC",
    "sg:tags":[
        "brick"
    ],
    "wof:name":"Boral",
    "wof:placetype":"venue"
},
  "geometry": {"coordinates":[144.90345764200001,-38.3566513062],"type":"Point"}
}