{
  "type": "Feature",
  "properties": {
    "addr:full":"40 Yaroma Ave Swan Haven NSW 2540",
    "addr:housenumber":"40",
    "addr:postcode":"2540",
    "addr:street":"Yaroma Ave",
    "iso:country":"AU",
    "sg:address":"40 Yaroma Ave",
    "sg:city":"Swan Haven",
    "sg:classifiers":[
        {
            "category":"Building & Trades",
            "subcategory":"Landscaping Services",
            "type":"Services"
        }
    ],
    "sg:phone":"+61 2 4441 2462",
    "sg:postcode":"2540",
    "sg:province":"NSW",
    "sg:tags":[
        "stump",
        "tree",
        "felling",
        "removal"
    ],
    "wof:name":"Daley Steve",
    "wof:placetype":"venue"
},
  "geometry": {"coordinates":[150.572723389,-35.1792488098],"type":"Point"}
}