{
  "type": "Feature",
  "properties": {
    "addr:full":"13 Kamarooka St Barooga VIC 3644",
    "addr:housenumber":"13",
    "addr:postcode":"3644",
    "addr:street":"Kamarooka St",
    "iso:country":"AU",
    "sg:address":"13 Kamarooka St",
    "sg:city":"Barooga",
    "sg:classifiers":[
        {
            "category":"Ice Cream",
            "type":"Food & Drink"
        }
    ],
    "sg:phone":"+61 3 5873 4457",
    "sg:postcode":"3644",
    "sg:province":"VIC",
    "sg:tags":[
        "retail"
    ],
    "wof:name":"Lime Spider",
    "wof:placetype":"venue"
},
  "geometry": {"coordinates":[145.69338989299999,-35.9052276611],"type":"Point"}
}