{
  "type": "Feature",
  "properties": {
    "addr:full":"Shp 18/ 191 Ashmore Rd Benowa QLD 4217",
    "addr:housenumber":"18 / 191",
    "addr:postcode":"4217",
    "addr:street":"Ashmore Rd",
    "iso:country":"AU",
    "sg:address":"Shp 18/ 191 Ashmore Rd",
    "sg:city":"Benowa",
    "sg:classifiers":[
        {
            "category":"Shopping",
            "subcategory":"Jewelry",
            "type":"Retail Goods"
        }
    ],
    "sg:phone":"+61 7 5539 4333",
    "sg:postcode":"4217",
    "sg:province":"QLD",
    "sg:tags":[
        "jeweller"
    ],
    "wof:name":"Bijoux Philip",
    "wof:placetype":"venue"
},
  "geometry": {"coordinates":[153.39244079599999,-28.0098285675],"type":"Point"}
}