{
  "type": "Feature",
  "properties": {
    "addr:full":"15 Albert La Taree NSW 2430",
    "addr:housenumber":"15",
    "addr:postcode":"2430",
    "addr:street":"Albert La",
    "iso:country":"AU",
    "sg:address":"15 Albert La",
    "sg:city":"Taree",
    "sg:classifiers":[
        {
            "category":"Real Estate",
            "subcategory":"Architect",
            "type":"Services"
        }
    ],
    "sg:phone":"+61 2 6552 4077",
    "sg:postcode":"2430",
    "sg:province":"NSW",
    "sg:tags":[
        "building",
        "designer"
    ],
    "wof:name":"Eastern Solar Design",
    "wof:placetype":"venue"
},
  "geometry": {"coordinates":[152.459045,-31.91337],"type":"Point"}
}