{
  "type": "Feature",
  "properties": {
    "addr:full":"6/ 48 Bloomfield St Cleveland QLD 4163",
    "addr:housenumber":"/ 48",
    "addr:postcode":"4163",
    "addr:street":"Bloomfield St",
    "iso:country":"AU",
    "sg:address":"6/ 48 Bloomfield St",
    "sg:city":"Cleveland",
    "sg:classifiers":[
        {
            "category":"Health Services",
            "subcategory":"Health Practitioner",
            "type":"Services"
        }
    ],
    "sg:phone":"+61 7 3286 1090",
    "sg:postcode":"4163",
    "sg:province":"QLD",
    "sg:tags":[
        "naturopath"
    ],
    "wof:name":"Feeling Great Naturally",
    "wof:placetype":"venue"
},
  "geometry": {"coordinates":[153.26722717300001,-27.5266819],"type":"Point"}
}