{
  "type": "Feature",
  "properties": {
    "addr:full":"18 Langer Drv Eimeo QLD 4740",
    "addr:postcode":"4740",
    "addr:street":"Langer Drv",
    "iso:country":"AU",
    "sg:address":"18 Langer Drv",
    "sg:city":"Eimeo",
    "sg:classifiers":[
        {
            "category":"Professional",
            "subcategory":"Art Services",
            "type":"Services"
        }
    ],
    "sg:phone":"+61 413 112 427",
    "sg:postcode":"4740",
    "sg:province":"QLD",
    "sg:tags":[
        "decorator",
        "painter"
    ],
    "wof:name":"Banks Matthew",
    "wof:placetype":"venue"
},
  "geometry": {"coordinates":[149.17674299999999,-21.050095],"type":"Point"}
}