{
  "type": "Feature",
  "properties": {
    "addr:full":"Lot 54 Ditton Rd Oakford WA 6121",
    "addr:postcode":"6121",
    "addr:street":"Ditton Rd",
    "iso:country":"AU",
    "sg:address":"Lot 54 Ditton Rd",
    "sg:city":"Oakford",
    "sg:classifiers":[
        {
            "category":"Shopping",
            "subcategory":"Hobbies, Toys, & Games",
            "type":"Retail Goods"
        }
    ],
    "sg:phone":"+61 8 9397 2397",
    "sg:postcode":"6121",
    "sg:province":"WA",
    "sg:tags":[
        "stamp"
    ],
    "wof:name":"RLC Jewellery & Collectables",
    "wof:placetype":"venue"
},
  "geometry": {"coordinates":[115.91159057599999,-32.1829414368],"type":"Point"}
}