{
  "type": "Feature",
  "properties": {
    "iso:country":"AU",
    "sg:address":"10 Lochmaben Crt",
    "sg:city":"Greenvale",
    "sg:classifiers":[
        {
            "category":"Building & Trades",
            "subcategory":"Construction",
            "type":"Services"
        }
    ],
    "sg:phone":"+61 419 991 494",
    "sg:postcode":"3059",
    "sg:province":"VIC",
    "sg:tags":[
        "plasterboard",
        "plasterer",
        "fixer"
    ],
    "wof:name":"Daniel's Plastering",
    "wof:placetype":"venue"
},
  "geometry": {"coordinates":[144.89744567899999,-37.6504325867],"type":"Point"}
}