{
  "type": "Feature",
  "properties": {
    "iso:country":"AU",
    "sg:address":"83 Bridge St West",
    "sg:city":"Benalla",
    "sg:classifiers":[
        {
            "category":"Building & Trades",
            "subcategory":"Construction",
            "type":"Services"
        }
    ],
    "sg:phone":"+61 3 5762 1100",
    "sg:postcode":"3672",
    "sg:province":"VIC",
    "sg:tags":[
        "road",
        "contractor"
    ],
    "wof:name":"Road Development & Construction",
    "wof:placetype":"venue"
},
  "geometry": {"coordinates":[145.96624800000001,-36.555531],"type":"Point"}
}