{
  "type": "Feature",
  "properties": {
    "addr:full":"6 Jarrah St Leeton NSW 2705",
    "addr:housenumber":"6",
    "addr:postcode":"2705",
    "addr:street":"Jarrah St",
    "iso:country":"AU",
    "sg:address":"6 Jarrah St",
    "sg:city":"Leeton",
    "sg:classifiers":[
        {
            "category":"Health Services",
            "subcategory":"Doctor",
            "type":"Services"
        }
    ],
    "sg:phone":"+61 2 6953 3222",
    "sg:postcode":"2705",
    "sg:province":"NSW",
    "sg:tags":[
        "medical",
        "practitioner"
    ],
    "wof:name":"Shehab M A S",
    "wof:placetype":"venue"
},
  "geometry": {"coordinates":[146.405715942,-34.553188324],"type":"Point"}
}