{
  "type": "Feature",
  "properties": {
    "addr:full":"38 Laurel Ave Cairns QLD 4870",
    "addr:housenumber":"38",
    "addr:postcode":"4870",
    "addr:street":"Laurel Ave",
    "iso:country":"AU",
    "sg:address":"38 Laurel Ave",
    "sg:city":"Cairns",
    "sg:classifiers":[
        {
            "category":"Professional",
            "subcategory":"Accounting & Tax Preparation",
            "type":"Services"
        }
    ],
    "sg:phone":"+61 7 4045 1551",
    "sg:postcode":"4870",
    "sg:province":"QLD",
    "sg:tags":[
        "consultant",
        "taxation"
    ],
    "wof:name":"Complete Business Advisors",
    "wof:placetype":"venue"
},
  "geometry": {"coordinates":[145.73158264200001,-16.9899597168],"type":"Point"}
}