{
  "type": "Feature",
  "properties": {
    "iso:country":"AU",
    "sg:address":"159 military Rd",
    "sg:city":"Dover Heights",
    "sg:classifiers":[
        {
            "category":"Sports & Exercise",
            "subcategory":"Gym",
            "type":"Entertainment"
        }
    ],
    "sg:phone":"+61 2 9388 1650",
    "sg:postcode":"2030",
    "sg:province":"NSW",
    "sg:tags":[
        "health",
        "fitness"
    ],
    "wof:name":"Curves at Dover Heights",
    "wof:placetype":"venue"
},
  "geometry": {"coordinates":[151.280807495,-33.8730735779],"type":"Point"}
}