{
  "type": "Feature",
  "properties": {
    "addr:full":"1 Halls Rd Nunile WA 6566",
    "addr:housenumber":"1",
    "addr:postcode":"6566",
    "addr:street":"Halls Rd",
    "iso:country":"AU",
    "sg:address":"1 Halls Rd",
    "sg:city":"Nunile",
    "sg:classifiers":[
        {
            "category":"Farming",
            "subcategory":"Farm",
            "type":"Manufacturing & Wholesale Goods"
        }
    ],
    "sg:phone":"+61 8 9574 2391",
    "sg:postcode":"6566",
    "sg:province":"WA",
    "sg:tags":[
        "farmer"
    ],
    "wof:name":"Walton D G & J A",
    "wof:placetype":"venue"
},
  "geometry": {"coordinates":[116.52514600000001,-31.504721],"type":"Point"}
}