{
  "type": "Feature",
  "properties": {
    "addr:full":"Cnr Morafield & Torrens Caboolture QLD 4510",
    "addr:postcode":"4510",
    "addr:street":"Cnr Morafield &",
    "iso:country":"AU",
    "sg:address":"Cnr Morafield & Torrens",
    "sg:city":"Caboolture",
    "sg:classifiers":[
        {
            "category":"Professional",
            "subcategory":"Printing & Photocopies",
            "type":"Services"
        }
    ],
    "sg:phone":"+61 7 5495 3875",
    "sg:postcode":"4510",
    "sg:province":"QLD",
    "sg:tags":[
        "trophy"
    ],
    "wof:name":"Ozsports Trophies",
    "wof:placetype":"venue"
},
  "geometry": {"coordinates":[152.95138499999999,-27.085728],"type":"Point"}
}