{
  "type": "Feature",
  "properties": {
    "addr:full":"3/ 18 Tradelink Rd Browns Plains QLD 4118",
    "addr:housenumber":"/ 18",
    "addr:postcode":"4118",
    "addr:street":"Tradelink Rd",
    "iso:country":"AU",
    "sg:address":"3/ 18 Tradelink Rd",
    "sg:city":"Browns Plains",
    "sg:classifiers":[
        {
            "category":"Building & Trades",
            "subcategory":"Construction",
            "type":"Services"
        }
    ],
    "sg:phone":"+61 7 3809 0212",
    "sg:postcode":"4118",
    "sg:province":"QLD",
    "sg:tags":[
        "fencing",
        "contractor"
    ],
    "wof:name":"Aaron's Pool Fencing",
    "wof:placetype":"venue"
},
  "geometry": {"coordinates":[153.03407287600001,-27.6648235321],"type":"Point"}
}