{
  "type": "Feature",
  "properties": {
    "iso:country":"AU",
    "sg:address":"188 King St",
    "sg:city":"Newtown",
    "sg:classifiers":[
        {
            "category":"Personal",
            "subcategory":"Beauty Salon",
            "type":"Services"
        }
    ],
    "sg:phone":"+61 2 9565 2111",
    "sg:postcode":"2042",
    "sg:province":"NSW",
    "sg:tags":[
        "hairdresser"
    ],
    "wof:name":"Toni & Guy Hairdressing Salons",
    "wof:placetype":"venue"
},
  "geometry": {"coordinates":[151.182587,-33.894516],"type":"Point"}
}