{
  "type": "Feature",
  "properties": {
    "addr:full":"35 Hillside Rd Rosanna VIC 3084",
    "addr:housenumber":"35",
    "addr:postcode":"3084",
    "addr:street":"Hillside Rd",
    "iso:country":"AU",
    "sg:address":"35 Hillside Rd",
    "sg:city":"Rosanna",
    "sg:classifiers":[
        {
            "category":"Social Services",
            "subcategory":"Child Care",
            "type":"Services"
        }
    ],
    "sg:phone":"+61 3 9459 0646",
    "sg:postcode":"3084",
    "sg:province":"VIC",
    "sg:tags":[
        "support",
        "health"
    ],
    "wof:name":"Maternal & Child Health Centres",
    "wof:placetype":"venue"
},
  "geometry": {"coordinates":[145.06370544399999,-37.7450942993],"type":"Point"}
}