{
  "type": "Feature",
  "properties": {
    "addr:full":"297 Kent St Maryborough QLD 4650",
    "addr:housenumber":"297",
    "addr:postcode":"4650",
    "addr:street":"Kent St",
    "iso:country":"AU",
    "sg:address":"297 Kent St",
    "sg:city":"Maryborough",
    "sg:classifiers":[
        {
            "category":"Health Services",
            "subcategory":"Doctor",
            "type":"Services"
        }
    ],
    "sg:phone":"+61 7 4123 1544",
    "sg:postcode":"4650",
    "sg:province":"QLD",
    "sg:tags":[
        "medical",
        "practitioner"
    ],
    "wof:name":"Dous Medhat Dr",
    "wof:placetype":"venue"
},
  "geometry": {"coordinates":[152.698837,-25.535229],"type":"Point"}
}