{
  "type": "Feature",
  "properties": {
    "addr:full":"Factory 6 66 Whiters St Lakes Entrance VIC 3909",
    "addr:housenumber":"66",
    "addr:postcode":"3909",
    "addr:street":"Whiters St",
    "iso:country":"AU",
    "sg:address":"Factory 6 66 Whiters St",
    "sg:city":"Lakes Entrance",
    "sg:classifiers":[
        {
            "category":"Building & Trades",
            "subcategory":"Construction",
            "type":"Services"
        }
    ],
    "sg:phone":"+61 3 5155 3066",
    "sg:postcode":"3909",
    "sg:province":"VIC",
    "sg:tags":[
        "welding"
    ],
    "wof:name":"EGM Welding Services",
    "wof:placetype":"venue"
},
  "geometry": {"coordinates":[148.000396728,-37.8702087402],"type":"Point"}
}