{
  "type": "Feature",
  "properties": {
    "addr:full":"34 McAdam St Maffra VIC 3860",
    "addr:housenumber":"34",
    "addr:postcode":"3860",
    "addr:street":"Mcadam St",
    "iso:country":"AU",
    "sg:address":"34 McAdam St",
    "sg:city":"Maffra",
    "sg:classifiers":[
        {
            "category":"Government",
            "subcategory":"Fire Station",
            "type":"Public Place"
        }
    ],
    "sg:phone":"+61 3 5147 2605",
    "sg:postcode":"3860",
    "sg:province":"VIC",
    "sg:tags":[
        "equipment",
        "protection",
        "consultant"
    ],
    "wof:name":"McCarthy & Partners",
    "wof:placetype":"venue"
},
  "geometry": {"coordinates":[146.98731994600001,-37.9687423706],"type":"Point"}
}