{
  "type": "Feature",
  "properties": {
    "iso:country":"AU",
    "sg:address":"260 Musgrave Rd",
    "sg:city":"Coopers Plains",
    "sg:classifiers":[
        {
            "category":"Health Services",
            "subcategory":"Health Practitioner",
            "type":"Services"
        }
    ],
    "sg:phone":"+61 7 3277 2337",
    "sg:postcode":"4108",
    "sg:province":"QLD",
    "sg:tags":[
        "physiotherapist"
    ],
    "wof:name":"Maximize Physio Coopers Plains",
    "wof:placetype":"venue"
},
  "geometry": {"coordinates":[153.03533935600001,-27.5624408722],"type":"Point"}
}