{
  "type": "Feature",
  "properties": {
    "addr:full":"26 Main Rd Devenish VIC 3726",
    "addr:housenumber":"26",
    "addr:postcode":"3726",
    "addr:street":"Main Rd",
    "iso:country":"AU",
    "sg:address":"26 Main Rd",
    "sg:city":"Devenish",
    "sg:classifiers":[
        {
            "category":"Food & Beverages",
            "subcategory":"Groceries & Convenience Stores",
            "type":"Retail Goods"
        }
    ],
    "sg:phone":"+61 3 5764 4263",
    "sg:postcode":"3726",
    "sg:province":"VIC",
    "wof:name":"Devenish Store & Post Office",
    "wof:placetype":"venue"
},
  "geometry": {"coordinates":[145.89453125,-36.3306732178],"type":"Point"}
}