{
  "type": "Feature",
  "properties": {
    "addr:full":"42 Knight St Rockhampton QLD 4700",
    "addr:housenumber":"42",
    "addr:postcode":"4700",
    "addr:street":"Knight St",
    "iso:country":"AU",
    "sg:address":"42 Knight St",
    "sg:city":"Rockhampton",
    "sg:classifiers":[
        {
            "category":"Retail",
            "subcategory":"Auto Repair",
            "type":"Services"
        }
    ],
    "sg:phone":"+61 7 4926 2663",
    "sg:postcode":"4700",
    "sg:province":"QLD",
    "sg:tags":[
        "repairer",
        "motor",
        "engineer"
    ],
    "wof:name":"Master Cylinder Exchange Service",
    "wof:placetype":"venue"
},
  "geometry": {"coordinates":[150.51414489699999,-23.3608016968],"type":"Point"}
}