{
  "type": "Feature",
  "properties": {
    "addr:full":"38 Mitford St Craigieburn VIC 3064",
    "addr:housenumber":"38",
    "addr:postcode":"3064",
    "addr:street":"Mitford St",
    "iso:country":"AU",
    "sg:address":"38 Mitford St",
    "sg:city":"Craigieburn",
    "sg:classifiers":[
        {
            "category":"Retail",
            "subcategory":"Storage",
            "type":"Services"
        }
    ],
    "sg:phone":"+61 3 9305 5745",
    "sg:postcode":"3064",
    "sg:province":"VIC",
    "sg:tags":[
        "removal",
        "furniture"
    ],
    "wof:name":"B & D Removals & Packing Service",
    "wof:placetype":"venue"
},
  "geometry": {"coordinates":[144.93914794899999,-37.6073455811],"type":"Point"}
}