{
  "type": "Feature",
  "properties": {
    "addr:full":"865 Pt Nepean Rd Rosebud VIC 3939",
    "addr:housenumber":"865",
    "addr:postcode":"3939",
    "addr:street":"Pt Nepean Rd",
    "iso:country":"AU",
    "sg:address":"865 Pt Nepean Rd",
    "sg:city":"Rosebud",
    "sg:classifiers":[
        {
            "category":"Home & Garden",
            "subcategory":"Household Appliances",
            "type":"Retail Goods"
        }
    ],
    "sg:phone":"+61 1800 888 274",
    "sg:postcode":"3939",
    "sg:province":"VIC",
    "sg:tags":[
        "heating",
        "system"
    ],
    "wof:name":"Andca Services",
    "wof:placetype":"venue"
},
  "geometry": {"coordinates":[144.909255981,-38.3540534973],"type":"Point"}
}