{
  "type": "Feature",
  "properties": {
    "addr:full":"20 Goode Rd Ceduna SA 5690",
    "addr:housenumber":"20",
    "addr:postcode":"5690",
    "addr:street":"Goode Rd",
    "iso:country":"AU",
    "sg:address":"20 Goode Rd",
    "sg:city":"Ceduna",
    "sg:classifiers":[
        {
            "category":"Home & Garden",
            "subcategory":"Building Materials",
            "type":"Retail Goods"
        }
    ],
    "sg:phone":"+61 8 8625 2566",
    "sg:postcode":"5690",
    "sg:province":"SA",
    "sg:tags":[
        "merchant",
        "glass",
        "glazier"
    ],
    "wof:name":"Ceduna Glass",
    "wof:placetype":"venue"
},
  "geometry": {"coordinates":[133.68096923799999,-32.1189842224],"type":"Point"}
}