{
  "type": "Feature",
  "properties": {
    "iso:country":"AU",
    "sg:address":"296 Everingham Ave",
    "sg:city":"North Rockhampton",
    "sg:classifiers":[
        {
            "category":"Building & Trades",
            "subcategory":"Construction",
            "type":"Services"
        }
    ],
    "sg:phone":"+61 7 4928 9050",
    "sg:postcode":"4701",
    "sg:province":"QLD",
    "sg:tags":[
        "plasterboard",
        "plasterer",
        "fixer"
    ],
    "wof:name":"Conlon Paul",
    "wof:placetype":"venue"
},
  "geometry": {"coordinates":[150.54989624000001,-23.3516921997],"type":"Point"}
}