{
  "type": "Feature",
  "properties": {
    "iso:country":"AU",
    "sg:address":"20A Fifth Ave",
    "sg:city":"South Townsville",
    "sg:classifiers":[
        {
            "category":"Communications",
            "subcategory":"Film & Video Production",
            "type":"Services"
        }
    ],
    "sg:phone":"+61 7 4721 3606",
    "sg:postcode":"4810",
    "sg:province":"QLD",
    "sg:tags":[
        "print",
        "poster",
        "wholesale",
        "pictures"
    ],
    "wof:name":"BBNQ",
    "wof:placetype":"venue"
},
  "geometry": {"coordinates":[146.828766,-19.271999],"type":"Point"}
}