{
  "type": "Feature",
  "properties": {
    "addr:full":"670 Muddy Gates La Tooradin VIC 3980",
    "addr:housenumber":"670",
    "addr:postcode":"3980",
    "addr:street":"Muddy Gates La",
    "iso:country":"AU",
    "sg:address":"670 Muddy Gates La",
    "sg:city":"Tooradin",
    "sg:classifiers":[
        {
            "category":"Autos & Motor Vehicles",
            "subcategory":"Boat Sales",
            "type":"Retail Goods"
        }
    ],
    "sg:phone":"+61 3 5998 3619",
    "sg:postcode":"3980",
    "sg:province":"VIC",
    "sg:tags":[
        "builder",
        "yacht",
        "repairer"
    ],
    "wof:name":"A R Marine",
    "wof:placetype":"venue"
},
  "geometry": {"coordinates":[145.371459961,-38.1797447205],"type":"Point"}
}