{
  "type": "Feature",
  "properties": {
    "iso:country":"AU",
    "sg:address":"151 Sunrise Ave",
    "sg:city":"Budgewoi",
    "sg:classifiers":[
        {
            "category":"Home & Garden",
            "subcategory":"Building Materials",
            "type":"Retail Goods"
        }
    ],
    "sg:phone":"+61 2 4390 4895",
    "sg:postcode":"2262",
    "sg:province":"NSW",
    "sg:tags":[
        "retaining",
        "wall"
    ],
    "wof:name":"Beewise Landscaping Pty Ltd",
    "wof:placetype":"venue"
},
  "geometry": {"coordinates":[151.55403100000001,-33.230118],"type":"Point"}
}