{
  "type": "Feature",
  "properties": {
    "addr:full":"PO Box 164 Floreat WA 6014",
    "addr:postcode":"6014",
    "iso:country":"AU",
    "sg:address":"PO Box 164",
    "sg:city":"Floreat",
    "sg:classifiers":[
        {
            "category":"Building & Trades",
            "subcategory":"Plumbing",
            "type":"Services"
        }
    ],
    "sg:phone":"+61 8 9286 2450",
    "sg:postcode":"6014",
    "sg:province":"WA",
    "sg:tags":[
        "plumber",
        "gasfitters"
    ],
    "wof:name":"Leak-Tec",
    "wof:placetype":"venue"
},
  "geometry": {"coordinates":[115.795776367,-31.9442691803],"type":"Point"}
}