{
  "type": "Feature",
  "properties": {
    "addr:full":"922 Granadilla Rd El Arish QLD 4855",
    "addr:postcode":"4855",
    "addr:street":"Granadilla Rd",
    "iso:country":"AU",
    "sg:address":"922 Granadilla Rd",
    "sg:city":"El Arish",
    "sg:classifiers":[
        {
            "category":"Food & Beverages",
            "subcategory":"Fruits & Vegetables",
            "type":"Retail Goods"
        }
    ],
    "sg:phone":"+61 7 4068 5203",
    "sg:postcode":"4855",
    "sg:province":"QLD",
    "sg:tags":[
        "wholesale"
    ],
    "wof:name":"Lakey's Tropical Fruits",
    "wof:placetype":"venue"
},
  "geometry": {"coordinates":[146.01368713400001,-17.8268032074],"type":"Point"}
}