{
  "type": "Feature",
  "properties": {
    "iso:country":"AU",
    "sg:address":"29 Tubbarubba Rd",
    "sg:city":"Merricks North",
    "sg:classifiers":[
        {
            "category":"Farming",
            "subcategory":"Vineyard",
            "type":"Manufacturing & Wholesale Goods"
        }
    ],
    "sg:phone":"+61 3 5989 7202",
    "sg:postcode":"3926",
    "sg:province":"VIC",
    "sg:tags":[
        "winery"
    ],
    "wof:name":"Hillside Country Cellars",
    "wof:placetype":"venue"
},
  "geometry": {"coordinates":[145.076004028,-38.3380012512],"type":"Point"}
}