{
  "type": "Feature",
  "properties": {
    "addr:full":"Shp 6/ 361 Ogilvie Ave Echuca South VIC 3564",
    "addr:housenumber":"/ 361",
    "addr:postcode":"3564",
    "addr:street":"Ogilvie Ave",
    "iso:country":"AU",
    "sg:address":"Shp 6/ 361 Ogilvie Ave",
    "sg:city":"Echuca South",
    "sg:classifiers":[
        {
            "category":"Farming",
            "subcategory":"Farm & Veterinary Services",
            "type":"Manufacturing & Wholesale Goods"
        }
    ],
    "sg:phone":"+61 3 5480 2426",
    "sg:postcode":"3564",
    "sg:province":"VIC",
    "sg:tags":[
        "irrigation",
        "reticulation",
        "system"
    ],
    "wof:name":"A & R Water Solutions",
    "wof:placetype":"venue"
},
  "geometry": {"coordinates":[144.75929260300001,-36.1405601501],"type":"Point"}
}