{
  "type": "Feature",
  "properties": {
    "addr:full":"211 Hermitage Drv The Vines WA 6069",
    "addr:housenumber":"211",
    "addr:postcode":"6069",
    "addr:street":"Hermitage Drv",
    "iso:country":"AU",
    "sg:address":"211 Hermitage Drv",
    "sg:city":"The Vines",
    "sg:classifiers":[
        {
            "category":"Home & Garden",
            "subcategory":"Building Materials",
            "type":"Retail Goods"
        }
    ],
    "sg:phone":"+61 8 9297 3830",
    "sg:postcode":"6069",
    "sg:province":"WA",
    "sg:tags":[
        "roofing"
    ],
    "wof:name":"Thommos Roofing",
    "wof:placetype":"venue"
},
  "geometry": {"coordinates":[116.007820129,-31.755739212],"type":"Point"}
}