{
  "type": "Feature",
  "properties": {
    "iso:country":"AU",
    "sg:address":"2 Duncan St",
    "sg:city":"Kingston SE",
    "sg:classifiers":[
        {
            "category":"Autos & Motor Vehicles",
            "subcategory":"Auto Supplies",
            "type":"Retail Goods"
        }
    ],
    "sg:phone":"+61 8 8767 2900",
    "sg:postcode":"5275",
    "sg:province":"SA",
    "sg:tags":[
        "tyre"
    ],
    "wof:name":"Kingston Tyre Service",
    "wof:placetype":"venue"
},
  "geometry": {"coordinates":[139.85264599999999,-36.837029],"type":"Point"}
}