{
  "type": "Feature",
  "properties": {
    "iso:country":"AU",
    "sg:address":"52 Tasman Rd",
    "sg:city":"North Avalon",
    "sg:classifiers":[
        {
            "category":"Education",
            "subcategory":"Kindergarten",
            "type":"Public Place"
        }
    ],
    "sg:phone":"+61 2 9437 9754",
    "sg:postcode":"2107",
    "sg:province":"NSW",
    "sg:tags":[
        "pre-schools"
    ],
    "wof:name":"She-Oaks Kindergarten",
    "wof:placetype":"venue"
},
  "geometry": {"coordinates":[151.335693359,-33.6288566589],"type":"Point"}
}