{
  "type": "Feature",
  "properties": {
    "addr:full":"34 Reserve St Smithfield NSW 2164",
    "addr:housenumber":"34",
    "addr:postcode":"2164",
    "addr:street":"Reserve St",
    "iso:country":"AU",
    "sg:address":"34 Reserve St",
    "sg:city":"Smithfield",
    "sg:classifiers":[
        {
            "category":"Retail",
            "subcategory":"Auto Repair",
            "type":"Services"
        }
    ],
    "sg:phone":"+61 415 713 240",
    "sg:postcode":"2164",
    "sg:province":"NSW",
    "sg:tags":[
        "beater",
        "painter",
        "panel"
    ],
    "wof:name":"About All Painting",
    "wof:placetype":"venue"
},
  "geometry": {"coordinates":[150.93597412099999,-33.8595237732],"type":"Point"}
}