{
  "type": "Feature",
  "properties": {
    "addr:full":"30 Rosebud Pde Rosebud VIC 3939",
    "addr:housenumber":"30",
    "addr:postcode":"3939",
    "addr:street":"Rosebud Pde",
    "iso:country":"AU",
    "sg:address":"30 Rosebud Pde",
    "sg:city":"Rosebud",
    "sg:classifiers":[
        {
            "category":"Cinema",
            "subcategory":"Movie Theater",
            "type":"Entertainment"
        }
    ],
    "sg:phone":"+61 3 5981 2555",
    "sg:postcode":"3939",
    "sg:province":"VIC",
    "wof:name":"Rosebud Cinemas",
    "wof:placetype":"venue"
},
  "geometry": {"coordinates":[144.905487061,-38.3546600342],"type":"Point"}
}