{
  "type": "Feature",
  "properties": {
    "addr:full":"PO Box 2002 Hampton East VIC 3188",
    "addr:postcode":"3188",
    "iso:country":"AU",
    "sg:address":"PO Box 2002",
    "sg:city":"Hampton East",
    "sg:classifiers":[
        {
            "category":"Building & Trades",
            "subcategory":"Construction",
            "type":"Services"
        }
    ],
    "sg:phone":"+61 400 066 416",
    "sg:postcode":"3188",
    "sg:province":"VIC",
    "sg:tags":[
        "installation",
        "air conditioning"
    ],
    "wof:name":"AML Air Conditioning & Plumbing Services",
    "wof:placetype":"venue"
},
  "geometry": {"coordinates":[145.025299072,-37.9317817688],"type":"Point"}
}