{
  "type": "Feature",
  "properties": {
    "iso:country":"AU",
    "sg:address":"PO Box 360",
    "sg:city":"Terrey Hills",
    "sg:classifiers":[
        {
            "category":"Home & Garden",
            "subcategory":"Garden Supply",
            "type":"Retail Goods"
        }
    ],
    "sg:phone":"+61 2 9450 0116",
    "sg:postcode":"2084",
    "sg:province":"NSW",
    "sg:tags":[
        "fertilizer"
    ],
    "wof:name":"Warm Castings King Poo",
    "wof:placetype":"venue"
},
  "geometry": {"coordinates":[151.229705811,-33.6837692261],"type":"Point"}
}