{
  "type": "Feature",
  "properties": {
    "addr:full":"PO Box 8211 South Perth WA 6151",
    "addr:postcode":"6151",
    "iso:country":"AU",
    "sg:address":"PO Box 8211",
    "sg:city":"South Perth",
    "sg:classifiers":[
        {
            "category":"Social Services",
            "subcategory":"Job Training",
            "type":"Services"
        }
    ],
    "sg:phone":"+61 8 9367 1204",
    "sg:postcode":"6151",
    "sg:province":"WA",
    "sg:tags":[
        "interpreter"
    ],
    "wof:name":"MDR Translations",
    "wof:placetype":"venue"
},
  "geometry": {"coordinates":[115.870239,-31.98105],"type":"Point"}
}