{
  "type": "Feature",
  "properties": {
    "iso:country":"AU",
    "sg:address":"3/ 59 Wises Rd",
    "sg:city":"Maroochydore",
    "sg:classifiers":[
        {
            "category":"Building & Trades",
            "subcategory":"Equipment Rental",
            "type":"Services"
        }
    ],
    "sg:phone":"+61 1300 133 306",
    "sg:postcode":"4558",
    "sg:province":"QLD",
    "sg:tags":[
        "party",
        "hire"
    ],
    "wof:name":"Mooloolaba Party Hire",
    "wof:placetype":"venue"
},
  "geometry": {"coordinates":[153.085205078,-26.6712913513],"type":"Point"}
}