{
  "type": "Feature",
  "properties": {
    "addr:full":"17/213 Coxs Rd North Ryde NSW 2113",
    "addr:housenumber":"17 / 213",
    "addr:postcode":"2113",
    "addr:street":"Coxs Rd",
    "iso:country":"AU",
    "sg:address":"17/213 Coxs Rd",
    "sg:city":"North Ryde",
    "sg:classifiers":[
        {
            "category":"Deli",
            "type":"Food & Drink"
        }
    ],
    "sg:phone":"+61 2 9878 1603",
    "sg:postcode":"2113",
    "sg:province":"NSW",
    "sg:tags":[
        "delicatessen"
    ],
    "wof:name":"North Ryde Delicatessen",
    "wof:placetype":"venue"
},
  "geometry": {"coordinates":[151.121383667,-33.7942047119],"type":"Point"}
}