{
  "type": "Feature",
  "properties": {
    "addr:full":"Level 1/ 79 Hope St South Bank QLD 4101",
    "addr:housenumber":"/ 79",
    "addr:postcode":"4101",
    "addr:street":"Hope St",
    "iso:country":"AU",
    "sg:address":"Level 1/ 79 Hope St",
    "sg:city":"South Bank",
    "sg:classifiers":[
        {
            "category":"Personal",
            "subcategory":"Massage",
            "type":"Services"
        }
    ],
    "sg:phone":"+61 1300 339 339",
    "sg:postcode":"4101",
    "sg:province":"QLD",
    "sg:tags":[
        "therapy"
    ],
    "wof:name":"Australian Institute of Massage",
    "wof:placetype":"venue"
},
  "geometry": {"coordinates":[153.017456055,-27.4742259979],"type":"Point"}
}