{
  "type": "Feature",
  "properties": {
    "addr:full":"PO Box 223 Wentworth Falls NSW 2782",
    "addr:postcode":"2782",
    "iso:country":"AU",
    "sg:address":"PO Box 223",
    "sg:city":"Wentworth Falls",
    "sg:classifiers":[
        {
            "category":"Building & Trades",
            "subcategory":"Construction",
            "type":"Services"
        }
    ],
    "sg:phone":"+61 2 4757 2218",
    "sg:postcode":"2782",
    "sg:province":"NSW",
    "sg:tags":[
        "renovation",
        "alterations",
        "extension",
        "contractor"
    ],
    "wof:name":"Mountain Man Construction",
    "wof:placetype":"venue"
},
  "geometry": {"coordinates":[150.38864135700001,-33.7292289734],"type":"Point"}
}