{
  "type": "Feature",
  "properties": {
    "iso:country":"AU",
    "sg:address":"56 Darlot St",
    "sg:city":"Horsham",
    "sg:classifiers":[
        {
            "category":"Farming",
            "subcategory":"Farm & Veterinary Services",
            "type":"Manufacturing & Wholesale Goods"
        }
    ],
    "sg:phone":"+61 3 5382 6170",
    "sg:postcode":"3400",
    "sg:province":"VIC",
    "sg:tags":[
        "poultry",
        "processing",
        "supply"
    ],
    "wof:name":"Tender Breast Poultry",
    "wof:placetype":"venue"
},
  "geometry": {"coordinates":[142.196975708,-36.7169914246],"type":"Point"}
}