{
  "type": "Feature",
  "properties": {
    "addr:full":"10 Reflection Mews Safety Bay WA 6169",
    "addr:housenumber":"10",
    "addr:postcode":"6169",
    "addr:street":"Reflection Mews",
    "iso:country":"AU",
    "sg:address":"10 Reflection Mews",
    "sg:city":"Safety Bay",
    "sg:classifiers":[
        {
            "category":"Building & Trades",
            "subcategory":"Equipment Rental",
            "type":"Services"
        }
    ],
    "sg:phone":"+61 419 981 161",
    "sg:postcode":"6169",
    "sg:province":"WA",
    "sg:tags":[
        "saw"
    ],
    "wof:name":"Smooth Cut Sharpening",
    "wof:placetype":"venue"
},
  "geometry": {"coordinates":[115.720383,-32.301525],"type":"Point"}
}