{
  "type": "Feature",
  "properties": {
    "addr:full":"16 Arthur St Concord NSW 2137",
    "addr:housenumber":"16",
    "addr:postcode":"2137",
    "addr:street":"Arthur St",
    "iso:country":"AU",
    "sg:address":"16 Arthur St",
    "sg:city":"Concord",
    "sg:classifiers":[
        {
            "category":"Education",
            "subcategory":"Special Training",
            "type":"Public Place"
        }
    ],
    "sg:phone":"+61 2 9736 3475",
    "sg:postcode":"2137",
    "sg:province":"NSW",
    "sg:tags":[
        "development"
    ],
    "wof:name":"Learning By Design Pty Ltd",
    "wof:placetype":"venue"
},
  "geometry": {"coordinates":[151.09786987300001,-33.8583335876],"type":"Point"}
}