{
  "type": "Feature",
  "properties": {
    "addr:full":"PO Box 1078 Randwick NSW 2031",
    "addr:postcode":"2031",
    "iso:country":"AU",
    "sg:address":"PO Box 1078",
    "sg:city":"Randwick",
    "sg:classifiers":[
        {
            "category":"Wholesale",
            "subcategory":"Furniture",
            "type":"Manufacturing & Wholesale Goods"
        }
    ],
    "sg:phone":"+61 2 9300 1888",
    "sg:postcode":"2031",
    "sg:province":"NSW",
    "sg:tags":[
        "wholesaler",
        "mfrs"
    ],
    "wof:name":"Yazz Pty Ltd",
    "wof:placetype":"venue"
},
  "geometry": {"coordinates":[151.24847412099999,-33.9152488708],"type":"Point"}
}