{
  "type": "Feature",
  "properties": {
    "addr:full":"8 Cochranes Rd Moorabbin VIC 3189",
    "addr:housenumber":"8",
    "addr:postcode":"3189",
    "addr:street":"Cochranes Rd",
    "iso:country":"AU",
    "sg:address":"8 Cochranes Rd",
    "sg:city":"Moorabbin",
    "sg:classifiers":[
        {
            "category":"Retail",
            "subcategory":"Auto Repair",
            "type":"Services"
        }
    ],
    "sg:phone":"+61 3 9553 2340",
    "sg:postcode":"3189",
    "sg:province":"VIC",
    "sg:tags":[
        "beater",
        "painter",
        "panel"
    ],
    "wof:name":"Akers Mike Smash Repairs",
    "wof:placetype":"venue"
},
  "geometry": {"coordinates":[145.06095886200001,-37.9421005249],"type":"Point"}
}