{
  "type": "Feature",
  "properties": {
    "addr:full":"70 Marangaroo Drv Girrawheen WA 6064",
    "addr:housenumber":"70",
    "addr:postcode":"6064",
    "addr:street":"Marangaroo Drv",
    "iso:country":"AU",
    "sg:address":"70 Marangaroo Drv",
    "sg:city":"Girrawheen",
    "sg:classifiers":[
        {
            "category":"Fast Food",
            "type":"Food & Drink"
        }
    ],
    "sg:phone":"+61 8 9342 8630",
    "sg:postcode":"6064",
    "sg:province":"WA",
    "sg:tags":[
        "away",
        "take"
    ],
    "wof:name":"Kentucky Fried Chicken",
    "wof:placetype":"venue"
},
  "geometry": {"coordinates":[115.8307724,-31.834312439],"type":"Point"}
}