{
  "type": "Feature",
  "properties": {
    "iso:country":"AU",
    "sg:address":"90 Princess St",
    "sg:city":"Bundaberg",
    "sg:classifiers":[
        {
            "category":"Arena",
            "subcategory":"Sports Club",
            "type":"Entertainment"
        }
    ],
    "sg:phone":"+61 7 4159 8884",
    "sg:postcode":"4670",
    "sg:province":"QLD",
    "sg:tags":[
        "defence",
        "supply",
        "self",
        "instruction",
        "martial art"
    ],
    "wof:name":"ASP Taekwondo & Martial Arts Academy",
    "wof:placetype":"venue"
},
  "geometry": {"coordinates":[152.36480712900001,-24.8644180298],"type":"Point"}
}