{
  "type": "Feature",
  "properties": {
    "iso:country":"AU",
    "sg:address":"15 Albert Ave",
    "sg:city":"Broadbeach",
    "sg:classifiers":[
        {
            "category":"Personal",
            "subcategory":"Beauty Salon",
            "type":"Services"
        }
    ],
    "sg:phone":"+61 7 5539 0048",
    "sg:postcode":"4218",
    "sg:province":"QLD",
    "wof:name":"Renew You Cosmetic & Holistic Medicine",
    "wof:placetype":"venue"
},
  "geometry": {"coordinates":[153.432174683,-28.0280647278],"type":"Point"}
}