{
  "type": "Feature",
  "properties": {
    "addr:full":"1109 High St Armadale VIC 3143",
    "addr:housenumber":"1109",
    "addr:postcode":"3143",
    "addr:street":"High St",
    "iso:country":"AU",
    "sg:address":"1109 High St",
    "sg:city":"Armadale",
    "sg:classifiers":[
        {
            "category":"Personal",
            "subcategory":"Beauty Salon",
            "type":"Services"
        }
    ],
    "sg:phone":"+61 3 9824 8848",
    "sg:postcode":"3143",
    "sg:province":"VIC",
    "wof:name":"Brazilian Butterfly Armadale",
    "wof:placetype":"venue"
},
  "geometry": {"coordinates":[145.02430725100001,-37.8558311462],"type":"Point"}
}