{
  "type": "Feature",
  "properties": {
    "iso:country":"AU",
    "sg:address":"41 Burleigh Ave",
    "sg:city":"Woodville North",
    "sg:classifiers":[
        {
            "category":"Wholesale",
            "subcategory":"Medical Equipment & Supplies",
            "type":"Manufacturing & Wholesale Goods"
        }
    ],
    "sg:phone":"+61 8 8244 8475",
    "sg:postcode":"5012",
    "sg:province":"SA",
    "sg:tags":[
        "aid",
        "care",
        "health",
        "home"
    ],
    "wof:name":"Decpac",
    "wof:placetype":"venue"
},
  "geometry": {"coordinates":[138.53509521500001,-34.8628807068],"type":"Point"}
}