{
  "type": "Feature",
  "properties": {
    "addr:full":"High St Cundletown NSW 2430",
    "addr:postcode":"2430",
    "addr:street":"High St",
    "iso:country":"AU",
    "sg:address":"High St",
    "sg:city":"Cundletown",
    "sg:classifiers":[
        {
            "category":"Education",
            "subcategory":"School",
            "type":"Public Place"
        }
    ],
    "sg:phone":"+61 2 6553 9315",
    "sg:postcode":"2430",
    "sg:province":"NSW",
    "sg:tags":[
        "state",
        "-",
        "nsw"
    ],
    "wof:name":"Cundletown Public School",
    "wof:placetype":"venue"
},
  "geometry": {"coordinates":[152.51693700000001,-31.896303],"type":"Point"}
}