{
  "type": "Feature",
  "properties": {
    "iso:country":"AU",
    "sg:address":"157- 159 Waverley Rd",
    "sg:city":"Malvern East",
    "sg:classifiers":[
        {
            "category":"Building & Trades",
            "subcategory":"Construction",
            "type":"Services"
        }
    ],
    "sg:phone":"+61 3 9563 5566",
    "sg:postcode":"3145",
    "sg:province":"VIC",
    "sg:tags":[
        "home",
        "air conditioning"
    ],
    "wof:name":"Airconditioning Centre The",
    "wof:placetype":"venue"
},
  "geometry": {"coordinates":[145.05000305199999,-37.8760185242],"type":"Point"}
}