{
  "type": "Feature",
  "properties": {
    "addr:full":"3 Short St Broadford VIC 3658",
    "addr:housenumber":"3",
    "addr:postcode":"3658",
    "addr:street":"Short St",
    "iso:country":"AU",
    "sg:address":"3 Short St",
    "sg:city":"Broadford",
    "sg:classifiers":[
        {
            "category":"Travel",
            "subcategory":"Hotels & Motels",
            "type":"Entertainment"
        }
    ],
    "sg:phone":"+61 3 5784 1069",
    "sg:postcode":"3658",
    "sg:province":"VIC",
    "wof:name":"Sugarloaf Motel",
    "wof:placetype":"venue"
},
  "geometry": {"coordinates":[145.06198120100001,-37.2066802979],"type":"Point"}
}