{
  "type": "Feature",
  "properties": {
    "addr:full":"41 Perkins St South Townsville QLD 4810",
    "addr:housenumber":"41",
    "addr:postcode":"4810",
    "addr:street":"Perkins St",
    "iso:country":"AU",
    "sg:address":"41 Perkins St",
    "sg:city":"South Townsville",
    "sg:classifiers":[
        {
            "category":"Manufacturing",
            "subcategory":"Metals",
            "type":"Manufacturing & Wholesale Goods"
        }
    ],
    "sg:phone":"+61 7 4772 4528",
    "sg:postcode":"4810",
    "sg:province":"QLD",
    "sg:tags":[
        "steel",
        "fabricator",
        "mfrs"
    ],
    "wof:name":"Murphy Steel Fabrications Townsville Pty Ltd",
    "wof:placetype":"venue"
},
  "geometry": {"coordinates":[146.821777,-19.268959],"type":"Point"}
}