{
  "type": "Feature",
  "properties": {
    "addr:full":"21 Seaham St Holmesville NSW 2286",
    "addr:housenumber":"21",
    "addr:postcode":"2286",
    "addr:street":"Seaham St",
    "iso:country":"AU",
    "sg:address":"21 Seaham St",
    "sg:city":"Holmesville",
    "sg:classifiers":[
        {
            "category":"Utilities",
            "subcategory":"Water",
            "type":"Services"
        }
    ],
    "sg:phone":"+61 416 033 894",
    "sg:postcode":"2286",
    "sg:province":"NSW",
    "sg:tags":[
        "cartage"
    ],
    "wof:name":"Bruce's Water Cartage",
    "wof:placetype":"venue"
},
  "geometry": {"coordinates":[151.58245849599999,-32.9074440002],"type":"Point"}
}