{
  "type": "Feature",
  "properties": {
    "addr:full":"135 Merrivale La Turramurra NSW 2074",
    "addr:housenumber":"135",
    "addr:postcode":"2074",
    "addr:street":"Merrivale La",
    "iso:country":"AU",
    "sg:address":"135 Merrivale La",
    "sg:city":"Turramurra",
    "sg:classifiers":[
        {
            "category":"Professional",
            "subcategory":"Computer Services",
            "type":"Services"
        }
    ],
    "sg:phone":"+61 2 9402 5566",
    "sg:postcode":"2074",
    "sg:province":"NSW",
    "sg:tags":[
        "package",
        "software"
    ],
    "wof:name":"Lanrex Custom Software",
    "wof:placetype":"venue"
},
  "geometry": {"coordinates":[151.14817810100001,-33.7265472412],"type":"Point"}
}