{
  "type": "Feature",
  "properties": {
    "addr:full":"310 Guilford Drv Guildford NSW 2161",
    "addr:housenumber":"310",
    "addr:postcode":"2161",
    "addr:street":"Guilford Drv",
    "iso:country":"AU",
    "sg:address":"310 Guilford Drv",
    "sg:city":"Guildford",
    "sg:classifiers":[
        {
            "category":"Restaurant",
            "type":"Food & Drink"
        }
    ],
    "sg:phone":"+61 2 9632 7352",
    "sg:postcode":"2161",
    "sg:province":"NSW",
    "sg:tags":[
        "pizza"
    ],
    "wof:name":"Elmarouk Pizza",
    "wof:placetype":"venue"
},
  "geometry": {"coordinates":[150.98611450199999,-33.8541221619],"type":"Point"}
}