{
  "type": "Feature",
  "properties": {
    "addr:full":"Unit 4, 43 Cordelia St South Brisbane QLD 4101",
    "addr:housenumber":"43",
    "addr:postcode":"4101",
    "addr:street":"Cordelia St",
    "iso:country":"AU",
    "sg:address":"Unit 4, 43 Cordelia St",
    "sg:city":"South Brisbane",
    "sg:classifiers":[
        {
            "category":"Shopping",
            "subcategory":"Computers & Home Electronics",
            "type":"Retail Goods"
        }
    ],
    "sg:phone":"+61 7 3846 2212",
    "sg:postcode":"4101",
    "sg:province":"QLD",
    "sg:tags":[
        "hardware",
        "equipment"
    ],
    "wof:name":"Empire Digital / Business IT Solutions",
    "wof:placetype":"venue"
},
  "geometry": {"coordinates":[153.016082764,-27.4765853882],"type":"Point"}
}