{
  "type": "Feature",
  "properties": {
    "addr:full":"Unit 9 , 605 King St Newtown NSW 2042",
    "addr:housenumber":"605",
    "addr:postcode":"2042",
    "addr:street":"King St",
    "iso:country":"AU",
    "sg:address":"Unit 9 , 605 King St",
    "sg:city":"Newtown",
    "sg:classifiers":[
        {
            "category":"Building & Trades",
            "subcategory":"Equipment Rental",
            "type":"Services"
        }
    ],
    "sg:phone":"+61 2 9517 1033",
    "sg:postcode":"2042",
    "sg:province":"NSW",
    "sg:tags":[
        "supply",
        "catering"
    ],
    "wof:name":"Universal Commercial Catering Equipment",
    "wof:placetype":"venue"
},
  "geometry": {"coordinates":[151.181015,-33.90612],"type":"Point"}
}