{
  "type": "Feature",
  "properties": {
    "addr:full":"Suite 2 Lvl 1 360-364 The Horsley Drv Fairfield NSW 2165",
    "addr:housenumber":"360-364",
    "addr:postcode":"2165",
    "addr:street":"The Horsley Drv",
    "iso:country":"AU",
    "sg:address":"Suite 2 Lvl 1 360-364 The Horsley Drv",
    "sg:city":"Fairfield",
    "sg:classifiers":[
        {
            "category":"Professional",
            "subcategory":"Employment Agencies",
            "type":"Services"
        }
    ],
    "sg:phone":"+61 2 9723 3577",
    "sg:postcode":"2165",
    "sg:province":"NSW",
    "wof:name":"North West Personnel",
    "wof:placetype":"venue"
},
  "geometry": {"coordinates":[150.95817565900001,-33.8679199219],"type":"Point"}
}