{
  "type": "Feature",
  "properties": {
    "iso:country":"AU",
    "sg:address":"276 Neerim Rd",
    "sg:city":"Carnegie",
    "sg:classifiers":[
        {
            "category":"Health Services",
            "subcategory":"Dentist",
            "type":"Services"
        }
    ],
    "sg:phone":"+61 3 9571 9016",
    "sg:postcode":"3163",
    "sg:province":"VIC",
    "wof:name":"Borowski Jack Dr",
    "wof:placetype":"venue"
},
  "geometry": {"coordinates":[145.05609130900001,-37.8887214661],"type":"Point"}
}