{
  "type": "Feature",
  "properties": {
    "iso:country":"AU",
    "sg:address":"5 Selwyn Crt",
    "sg:city":"Templestowe",
    "sg:classifiers":[
        {
            "category":"Social Services",
            "subcategory":"Child Care",
            "type":"Services"
        }
    ],
    "sg:phone":"+61 3 9846 5765",
    "sg:postcode":"3106",
    "sg:province":"VIC",
    "wof:name":"Montesori Casa",
    "wof:placetype":"venue"
},
  "geometry": {"coordinates":[145.12664794899999,-37.7595748901],"type":"Point"}
}