{
  "type": "Feature",
  "properties": {
    "addr:full":"613 Warringah Rd Forestville NSW 2087",
    "addr:housenumber":"613",
    "addr:postcode":"2087",
    "addr:street":"Warringah Rd",
    "iso:country":"AU",
    "sg:address":"613 Warringah Rd",
    "sg:city":"Forestville",
    "sg:classifiers":[
        {
            "category":"Organizations",
            "subcategory":"Community Association",
            "type":"Services"
        }
    ],
    "sg:phone":"+61 2 9451 1199",
    "sg:postcode":"2087",
    "sg:province":"NSW",
    "sg:tags":[
        "international",
        "organisation",
        "relation",
        "aid"
    ],
    "wof:name":"Baptist World Aid",
    "wof:placetype":"venue"
},
  "geometry": {"coordinates":[151.221725464,-33.7554931641],"type":"Point"}
}