{
  "type": "Feature",
  "properties": {
    "addr:full":"7 Greenhill Rd Wayville SA 5034",
    "addr:housenumber":"7",
    "addr:postcode":"5034",
    "addr:street":"Greenhill Rd",
    "iso:country":"AU",
    "sg:address":"7 Greenhill Rd",
    "sg:city":"Wayville",
    "sg:classifiers":[
        {
            "category":"Professional",
            "subcategory":"Accounting & Tax Preparation",
            "type":"Services"
        }
    ],
    "sg:phone":"+61 8 8272 5500",
    "sg:postcode":"5034",
    "sg:province":"SA",
    "sg:tags":[
        "accountant",
        "auditor"
    ],
    "wof:name":"Adamson Penhall & Co",
    "wof:placetype":"venue"
},
  "geometry": {"coordinates":[138.584884644,-34.942276001],"type":"Point"}
}