{
  "type": "Feature",
  "properties": {
    "iso:country":"AU",
    "sg:address":"19 Gartside St",
    "sg:city":"Wanniassa",
    "sg:classifiers":[
        {
            "category":"Retail",
            "subcategory":"Auto Repair",
            "type":"Services"
        }
    ],
    "sg:phone":"+61 2 6296 1774",
    "sg:postcode":"2903",
    "sg:province":"ACT",
    "sg:tags":[
        "wheel",
        "balancing",
        "alignment"
    ],
    "wof:name":"Discount Tyre Service",
    "wof:placetype":"venue"
},
  "geometry": {"coordinates":[149.099365234,-35.4053611755],"type":"Point"}
}