{
  "type": "Feature",
  "properties": {
    "iso:country":"AU",
    "sg:address":"10 Walker St",
    "sg:city":"Helensburgh",
    "sg:classifiers":[
        {
            "category":"Fast Food",
            "type":"Food & Drink"
        }
    ],
    "sg:phone":"+61 2 4294 4668",
    "sg:postcode":"2508",
    "sg:province":"NSW",
    "sg:tags":[
        "away",
        "take"
    ],
    "wof:name":"Pizzarama",
    "wof:placetype":"venue"
},
  "geometry": {"coordinates":[150.98170500000001,-34.191792],"type":"Point"}
}