{
  "type": "Feature",
  "properties": {
    "iso:country":"AU",
    "sg:address":"233 Rocky Point Rd",
    "sg:city":"Ramsgate",
    "sg:classifiers":[
        {
            "category":"Banks & Credit Unions",
            "subcategory":"Investment Brokerage",
            "type":"Services"
        }
    ],
    "sg:phone":"+61 2 9529 3888",
    "sg:postcode":"2217",
    "sg:province":"NSW",
    "wof:name":"Advance Investment Advisory Services Pty Ltd",
    "wof:placetype":"venue"
},
  "geometry": {"coordinates":[151.13601700000001,-33.984753],"type":"Point"}
}