{
  "type": "Feature",
  "properties": {
    "iso:country":"AU",
    "sg:address":"23 Kirkham Rd West",
    "sg:city":"Keysborough",
    "sg:classifiers":[
        {
            "category":"Manufacturing",
            "subcategory":"Glass & Minerals",
            "type":"Manufacturing & Wholesale Goods"
        }
    ],
    "sg:phone":"+61 3 9798 7011",
    "sg:postcode":"3173",
    "sg:province":"VIC",
    "sg:tags":[
        "repair",
        "fibreglass",
        "product"
    ],
    "wof:name":"McArthur Composites Pty Ltd",
    "wof:placetype":"venue"
},
  "geometry": {"coordinates":[145.184158325,-37.9955215454],"type":"Point"}
}