{
  "type": "Feature",
  "properties": {
    "addr:full":"479 Pumicestone Rd Caboolture QLD 4510",
    "addr:housenumber":"479",
    "addr:postcode":"4510",
    "addr:street":"Pumicestone Rd",
    "iso:country":"AU",
    "sg:address":"479 Pumicestone Rd",
    "sg:city":"Caboolture",
    "sg:classifiers":[
        {
            "category":"Travel",
            "subcategory":"Hotels & Motels",
            "type":"Entertainment"
        }
    ],
    "sg:phone":"+61 7 5490 1500",
    "sg:postcode":"4510",
    "sg:province":"QLD",
    "sg:website":"http://www.carboolturem1motel.com.au",
    "wof:name":"Caboolture M1 Motel",
    "wof:placetype":"venue"
},
  "geometry": {"coordinates":[152.96064799999999,-27.054388],"type":"Point"}
}