{
  "type": "Feature",
  "properties": {
    "iso:country":"AU",
    "sg:address":"Morgan Ave",
    "sg:city":"Seaview Downs",
    "sg:classifiers":[
        {
            "category":"Health Services",
            "subcategory":"Health Practitioner",
            "type":"Services"
        }
    ],
    "sg:phone":"+61 405 972 911",
    "sg:postcode":"5049",
    "sg:province":"SA",
    "sg:tags":[
        "acupuncture"
    ],
    "wof:name":"Leanne Hall",
    "wof:placetype":"venue"
},
  "geometry": {"coordinates":[138.537277,-35.036575],"type":"Point"}
}