{
  "type": "Feature",
  "properties": {
    "addr:full":"25 Donkin St South Brisbane QLD 4101",
    "addr:housenumber":"25",
    "addr:postcode":"4101",
    "addr:street":"Donkin St",
    "iso:country":"AU",
    "sg:address":"25 Donkin St",
    "sg:city":"South Brisbane",
    "sg:classifiers":[
        {
            "category":"Professional",
            "subcategory":"Computer Services",
            "type":"Services"
        }
    ],
    "sg:phone":"+61 1300 739 732",
    "sg:postcode":"4101",
    "sg:province":"QLD",
    "sg:tags":[
        "consultant",
        "system"
    ],
    "wof:name":"GZD Pty Ltd",
    "wof:placetype":"venue"
},
  "geometry": {"coordinates":[153.008087158,-27.4761943817],"type":"Point"}
}