{
  "type": "Feature",
  "properties": {
    "iso:country":"AU",
    "sg:address":"22 Herbert St",
    "sg:city":"Laura",
    "sg:classifiers":[
        {
            "category":"Manufacturing",
            "subcategory":"Soap",
            "type":"Manufacturing & Wholesale Goods"
        }
    ],
    "sg:phone":"+61 8 8663 2535",
    "sg:postcode":"5480",
    "sg:province":"SA",
    "sg:tags":[
        "detergent"
    ],
    "wof:name":"Laura Soap Shoppe The",
    "wof:placetype":"venue"
},
  "geometry": {"coordinates":[138.30076599099999,-33.1851577759],"type":"Point"}
}