{
  "type": "Feature",
  "properties": {
    "iso:country":"AU",
    "sg:address":"U 1/ 4 Essex St",
    "sg:city":"Minto",
    "sg:classifiers":[
        {
            "category":"Retail",
            "subcategory":"Auto Repair",
            "type":"Services"
        }
    ],
    "sg:phone":"+61 2 9603 3557",
    "sg:postcode":"2566",
    "sg:province":"NSW",
    "sg:tags":[
        "beater",
        "painter",
        "panel"
    ],
    "wof:name":"Essex Street Smash Repairs",
    "wof:placetype":"venue"
},
  "geometry": {"coordinates":[150.84422302199999,-34.0210342407],"type":"Point"}
}