{
  "type": "Feature",
  "properties": {
    "iso:country":"AU",
    "sg:address":"PO Box 2679",
    "sg:city":"Cairns",
    "sg:classifiers":[
        {
            "category":"Professional",
            "subcategory":"Accounting & Tax Preparation",
            "type":"Services"
        }
    ],
    "sg:phone":"+61 410 875 406",
    "sg:postcode":"4870",
    "sg:province":"QLD",
    "sg:tags":[
        "bookkeeping"
    ],
    "wof:name":"Dee-Stress Bookkeeping",
    "wof:placetype":"venue"
},
  "geometry": {"coordinates":[145.73703002900001,-16.8978786469],"type":"Point"}
}