{
  "type": "Feature",
  "properties": {
    "addr:full":"33 Peak Ave Main Beach QLD 4217",
    "addr:housenumber":"33",
    "addr:postcode":"4217",
    "addr:street":"Peak Ave",
    "iso:country":"AU",
    "sg:address":"33 Peak Ave",
    "sg:city":"Main Beach",
    "sg:classifiers":[
        {
            "category":"Health Services",
            "subcategory":"Doctor",
            "type":"Services"
        }
    ],
    "sg:phone":"+61 7 5526 4955",
    "sg:postcode":"4217",
    "sg:province":"QLD",
    "sg:tags":[
        "medical",
        "practitioner"
    ],
    "wof:name":"Miller Terry Dr",
    "wof:placetype":"venue"
},
  "geometry": {"coordinates":[153.42449951200001,-27.9785804749],"type":"Point"}
}