{
  "type": "Feature",
  "properties": {
    "iso:country":"AU",
    "sg:address":"56 Tanby Rd",
    "sg:city":"Yeppoon",
    "sg:classifiers":[
        {
            "category":"Home & Garden",
            "subcategory":"Garden Supply",
            "type":"Retail Goods"
        }
    ],
    "sg:phone":"+61 7 4939 2115",
    "sg:postcode":"4703",
    "sg:province":"QLD",
    "sg:tags":[
        "equipment"
    ],
    "wof:name":"Yeppoon Small Motor Service",
    "wof:placetype":"venue"
},
  "geometry": {"coordinates":[150.738723755,-23.1379833221],"type":"Point"}
}