{
  "type": "Feature",
  "properties": {
    "iso:country":"AU",
    "sg:address":"North Ryde Public School 103 Coxs Rd",
    "sg:city":"North Ryde",
    "sg:classifiers":[
        {
            "category":"Arena",
            "subcategory":"Sports Club",
            "type":"Entertainment"
        }
    ],
    "sg:phone":"+61 2 9889 3958",
    "sg:postcode":"2113",
    "sg:province":"NSW",
    "sg:tags":[
        "defence",
        "supply",
        "self",
        "instruction",
        "martial art"
    ],
    "wof:name":"Karate Self Defence School",
    "wof:placetype":"venue"
},
  "geometry": {"coordinates":[151.12051391599999,-33.7939147949],"type":"Point"}
}