{
  "type": "Feature",
  "properties": {
    "addr:full":"25 Clarence St Bellerive TAS 7018",
    "addr:housenumber":"25",
    "addr:postcode":"7018",
    "addr:street":"Clarence St",
    "iso:country":"AU",
    "sg:address":"25 Clarence St",
    "sg:city":"Bellerive",
    "sg:classifiers":[
        {
            "category":"Autos & Motor Vehicles",
            "subcategory":"Automobile Sales",
            "type":"Retail Goods"
        }
    ],
    "sg:phone":"+61 3 6245 9222",
    "sg:postcode":"7018",
    "sg:province":"TAS",
    "sg:tags":[
        "car",
        "used"
    ],
    "wof:name":"Autos Unlimited",
    "wof:placetype":"venue"
},
  "geometry": {"coordinates":[147.37236023,-42.875087738],"type":"Point"}
}