{
  "type": "Feature",
  "properties": {
    "addr:full":"Coldstream St Yamba NSW 2464",
    "addr:postcode":"2464",
    "addr:street":"Coldstream St",
    "iso:country":"AU",
    "sg:address":"Coldstream St",
    "sg:city":"Yamba",
    "sg:classifiers":[
        {
            "category":"Food & Beverages",
            "subcategory":"Liquor & Beverages",
            "type":"Retail Goods"
        }
    ],
    "sg:phone":"+61 2 6646 2313",
    "sg:postcode":"2464",
    "sg:province":"NSW",
    "sg:tags":[
        "store"
    ],
    "wof:name":"Yamba Liquor Supplies",
    "wof:placetype":"venue"
},
  "geometry": {"coordinates":[153.356292725,-29.4395065308],"type":"Point"}
}