{
  "type": "Feature",
  "properties": {
    "addr:full":"100 Fehres Rd Margate TAS 7054",
    "addr:housenumber":"100",
    "addr:postcode":"7054",
    "addr:street":"Fehres Rd",
    "iso:country":"AU",
    "sg:address":"100 Fehres Rd",
    "sg:city":"Margate",
    "sg:classifiers":[
        {
            "category":"Professional",
            "subcategory":"Computer Services",
            "type":"Services"
        }
    ],
    "sg:phone":"+61 412 252 272",
    "sg:postcode":"7054",
    "sg:province":"TAS",
    "sg:tags":[
        "consultant",
        "system"
    ],
    "wof:name":"Viva Technologies Pty Ltd",
    "wof:placetype":"venue"
},
  "geometry": {"coordinates":[147.269104,-43.002609],"type":"Point"}
}