{
  "type": "Feature",
  "properties": {
    "iso:country":"AU",
    "sg:address":"Shop 1, 213 Unley Rd",
    "sg:city":"Unley",
    "sg:classifiers":[
        {
            "category":"Professional",
            "subcategory":"Art Services",
            "type":"Services"
        }
    ],
    "sg:phone":"+61 8 8357 2200",
    "sg:postcode":"5061",
    "sg:province":"SA",
    "sg:tags":[
        "interior",
        "decorator"
    ],
    "wof:name":"Biggie Best Interiors",
    "wof:placetype":"venue"
},
  "geometry": {"coordinates":[138.607910156,-34.953956604],"type":"Point"}
}