{
  "type": "Feature",
  "properties": {
    "iso:country":"AU",
    "sg:address":"26 Lawson La",
    "sg:city":"Orbost",
    "sg:classifiers":[
        {
            "category":"Retail",
            "subcategory":"Repair Shop",
            "type":"Services"
        }
    ],
    "sg:phone":"+61 3 5154 2881",
    "sg:postcode":"3888",
    "sg:province":"VIC",
    "sg:tags":[
        "restorer",
        "repairer",
        "carpet"
    ],
    "wof:name":"Marshall's Carpet Cleaning",
    "wof:placetype":"venue"
},
  "geometry": {"coordinates":[148.45892334000001,-37.7073059082],"type":"Point"}
}