{
  "type": "Feature",
  "properties": {
    "iso:country":"AU",
    "sg:address":"205 Harbour Drv",
    "sg:city":"Coffs Harbour",
    "sg:classifiers":[
        {
            "category":"Social Services",
            "subcategory":"Child Care",
            "type":"Services"
        }
    ],
    "sg:phone":"+61 2 6651 2377",
    "sg:postcode":"2450",
    "sg:province":"NSW",
    "wof:name":"Caterpillar House Occasional Child Care Centre",
    "wof:placetype":"venue"
},
  "geometry": {"coordinates":[153.119812,-30.300074],"type":"Point"}
}