{
  "type": "Feature",
  "properties": {
    "addr:full":"1168 Pittwater Rd Collaroy NSW 2097",
    "addr:housenumber":"1168",
    "addr:postcode":"2097",
    "addr:street":"Pittwater Rd",
    "iso:country":"AU",
    "sg:address":"1168 Pittwater Rd",
    "sg:city":"Collaroy",
    "sg:classifiers":[
        {
            "category":"Social Services",
            "subcategory":"Adult Care",
            "type":"Services"
        }
    ],
    "sg:phone":"+61 2 9971 3100",
    "sg:postcode":"2097",
    "sg:province":"NSW",
    "sg:tags":[
        "aged"
    ],
    "wof:name":"Daughterly Care",
    "wof:placetype":"venue"
},
  "geometry": {"coordinates":[151.30007934599999,-33.7288017273],"type":"Point"}
}