{
  "type": "Feature",
  "properties": {
    "iso:country":"AU",
    "sg:address":"7 Carruthers Crt",
    "sg:city":"Altona",
    "sg:classifiers":[
        {
            "category":"Retail",
            "subcategory":"Driving School",
            "type":"Services"
        }
    ],
    "sg:phone":"+61 3 9398 4585",
    "sg:postcode":"3018",
    "sg:province":"VIC",
    "wof:name":"Bruno Driving School",
    "wof:placetype":"venue"
},
  "geometry": {"coordinates":[144.823562622,-37.8613433838],"type":"Point"}
}