{
  "type": "Feature",
  "properties": {
    "addr:full":"51 Cootamundra Ave Rosebud VIC 3939",
    "addr:housenumber":"51",
    "addr:postcode":"3939",
    "addr:street":"Cootamundra Ave",
    "iso:country":"AU",
    "sg:address":"51 Cootamundra Ave",
    "sg:city":"Rosebud",
    "sg:classifiers":[
        {
            "category":"Personal",
            "subcategory":"Massage",
            "type":"Services"
        }
    ],
    "sg:phone":"+61 3 5981 1481",
    "sg:postcode":"3939",
    "sg:province":"VIC",
    "sg:tags":[
        "therapy"
    ],
    "wof:name":"New Avenue Massage Therapy",
    "wof:placetype":"venue"
},
  "geometry": {"coordinates":[144.874603272,-38.3715896606],"type":"Point"}
}