{
  "type": "Feature",
  "properties": {
    "addr:full":"166 King Rd Mooloolah QLD 4553",
    "addr:housenumber":"166",
    "addr:postcode":"4553",
    "addr:street":"King Rd",
    "iso:country":"AU",
    "sg:address":"166 King Rd",
    "sg:city":"Mooloolah",
    "sg:classifiers":[
        {
            "category":"Home & Garden",
            "subcategory":"Carpets & Floor Coverings",
            "type":"Retail Goods"
        }
    ],
    "sg:phone":"+61 412 844 474",
    "sg:postcode":"4553",
    "sg:province":"QLD",
    "sg:tags":[
        "layer",
        "planner"
    ],
    "wof:name":"L T Palmer Carpet",
    "wof:placetype":"venue"
},
  "geometry": {"coordinates":[152.94961499999999,-26.774475],"type":"Point"}
}