{
  "type": "Feature",
  "properties": {
    "addr:full":"Main Rd Spreyton TAS 7310",
    "addr:postcode":"7310",
    "addr:street":"Main Rd",
    "iso:country":"AU",
    "sg:address":"Main Rd",
    "sg:city":"Spreyton",
    "sg:classifiers":[
        {
            "category":"Retail",
            "subcategory":"Storage",
            "type":"Services"
        }
    ],
    "sg:phone":"+61 3 6427 2500",
    "sg:postcode":"7310",
    "sg:province":"TAS",
    "sg:tags":[
        "cold"
    ],
    "wof:name":"Mersey Valley Cool Stores",
    "wof:placetype":"venue"
},
  "geometry": {"coordinates":[146.35578918499999,-41.22290802],"type":"Point"}
}