{
  "type": "Feature",
  "properties": {
    "addr:full":"2 Harbour Drv Patterson Lakes VIC 3197",
    "addr:housenumber":"2",
    "addr:postcode":"3197",
    "addr:street":"Harbour Drv",
    "iso:country":"AU",
    "sg:address":"2 Harbour Drv",
    "sg:city":"Patterson Lakes",
    "sg:classifiers":[
        {
            "category":"Social Services",
            "subcategory":"Retirement Home",
            "type":"Services"
        }
    ],
    "sg:phone":"+61 403 914 384",
    "sg:postcode":"3197",
    "sg:province":"VIC",
    "sg:tags":[
        "life",
        "coaching"
    ],
    "wof:name":"Coach Pro",
    "wof:placetype":"venue"
},
  "geometry": {"coordinates":[145.14302063,-38.0554122925],"type":"Point"}
}