{
  "type": "Feature",
  "properties": {
    "addr:full":"4 Garema Crt Mooloolaba QLD 4557",
    "addr:housenumber":"4",
    "addr:postcode":"4557",
    "addr:street":"Garema Crt",
    "iso:country":"AU",
    "sg:address":"4 Garema Crt",
    "sg:city":"Mooloolaba",
    "sg:classifiers":[
        {
            "category":"Professional",
            "subcategory":"Computer Services",
            "type":"Services"
        }
    ],
    "sg:phone":"+61 7 5444 8496",
    "sg:postcode":"4557",
    "sg:province":"QLD",
    "sg:tags":[
        "training"
    ],
    "wof:name":"Robert Kerr",
    "wof:placetype":"venue"
},
  "geometry": {"coordinates":[153.09147644000001,-26.6957988739],"type":"Point"}
}