{
  "type": "Feature",
  "properties": {
    "addr:full":"92-94 Dunsmore Rd Cowes VIC 3922",
    "addr:housenumber":"92-94",
    "addr:postcode":"3922",
    "addr:street":"Dunsmore Rd",
    "iso:country":"AU",
    "sg:address":"92-94 Dunsmore Rd",
    "sg:city":"Cowes",
    "sg:classifiers":[
        {
            "category":"Building & Trades",
            "subcategory":"Construction",
            "type":"Services"
        }
    ],
    "sg:phone":"+61 418 357 537",
    "sg:postcode":"3922",
    "sg:province":"VIC",
    "sg:tags":[
        "fencing",
        "contractor"
    ],
    "wof:name":"Philip Island Temporary Fencing",
    "wof:placetype":"venue"
},
  "geometry": {"coordinates":[145.24855041500001,-38.4565391541],"type":"Point"}
}