{
  "type": "Feature",
  "properties": {
    "addr:full":"159 Monbulk Rd Silvan VIC 3795",
    "addr:housenumber":"159",
    "addr:postcode":"3795",
    "addr:street":"Monbulk Rd",
    "iso:country":"AU",
    "sg:address":"159 Monbulk Rd",
    "sg:city":"Silvan",
    "sg:classifiers":[
        {
            "category":"Restaurant",
            "type":"Food & Drink"
        }
    ],
    "sg:phone":"+61 3 9737 9774",
    "sg:postcode":"3795",
    "sg:province":"VIC",
    "sg:website":"http://www.twistedvine.com.au",
    "wof:name":"Twisted Vine Restaurant",
    "wof:placetype":"venue"
},
  "geometry": {"coordinates":[145.406005859,-37.8097038269],"type":"Point"}
}