{
  "type": "Feature",
  "properties": {
    "iso:country":"AU",
    "sg:address":"12 Kingsford Crt",
    "sg:city":"Port Kennedy",
    "sg:classifiers":[
        {
            "category":"Manufacturing",
            "subcategory":"Food",
            "type":"Manufacturing & Wholesale Goods"
        }
    ],
    "sg:phone":"+61 429 966 267",
    "sg:postcode":"6172",
    "sg:province":"WA",
    "sg:tags":[
        "function",
        "catering"
    ],
    "wof:name":"Aamelia's Catering",
    "wof:placetype":"venue"
},
  "geometry": {"coordinates":[115.756882,-32.353756],"type":"Point"}
}