{
  "type": "Feature",
  "properties": {
    "iso:country":"AU",
    "sg:address":"Shop 6/ 344 Jackson Rd",
    "sg:city":"Sunnybank Hills",
    "sg:classifiers":[
        {
            "category":"Personal",
            "subcategory":"Beauty Salon",
            "type":"Services"
        }
    ],
    "sg:phone":"+61 7 3272 0011",
    "sg:postcode":"4109",
    "sg:province":"QLD",
    "sg:tags":[
        "hairdresser"
    ],
    "wof:name":"Ginger's Hair Studio Hair Beauty & Nails",
    "wof:placetype":"venue"
},
  "geometry": {"coordinates":[153.046875,-27.5819301605],"type":"Point"}
}