{
  "type": "Feature",
  "properties": {
    "addr:full":"Anzac St Temora NSW 2666",
    "addr:postcode":"2666",
    "addr:street":"Anzac St",
    "iso:country":"AU",
    "sg:address":"Anzac St",
    "sg:city":"Temora",
    "sg:classifiers":[
        {
            "category":"Education",
            "subcategory":"School",
            "type":"Public Place"
        }
    ],
    "sg:phone":"+61 2 6977 1988",
    "sg:postcode":"2666",
    "sg:province":"NSW",
    "sg:tags":[
        "state",
        "-",
        "nsw"
    ],
    "wof:name":"Temora High School",
    "wof:placetype":"venue"
},
  "geometry": {"coordinates":[147.53465270999999,-34.4443778992],"type":"Point"}
}