{
  "type": "Feature",
  "properties": {
    "iso:country":"AU",
    "sg:address":"1 Manning St",
    "sg:city":"Scarborough",
    "sg:classifiers":[
        {
            "category":"Professional",
            "subcategory":"Computer Services",
            "type":"Services"
        }
    ],
    "sg:phone":"+61 8 9245 9900",
    "sg:postcode":"6019",
    "sg:province":"WA",
    "sg:tags":[
        "consultant",
        "system"
    ],
    "wof:name":"Pronto Software",
    "wof:placetype":"venue"
},
  "geometry": {"coordinates":[115.756782532,-31.8921699524],"type":"Point"}
}