{
  "type": "Feature",
  "properties": {
    "iso:country":"AU",
    "sg:address":"120 Charters Towers Rd",
    "sg:city":"Hermit Park",
    "sg:classifiers":[
        {
            "category":"Arts & Performance",
            "subcategory":"Music",
            "type":"Entertainment"
        }
    ],
    "sg:phone":"+61 7 4724 5400",
    "sg:postcode":"4812",
    "sg:province":"QLD",
    "sg:tags":[
        "mobile",
        "jockey",
        "disc"
    ],
    "wof:name":"Move N Groove",
    "wof:placetype":"venue"
},
  "geometry": {"coordinates":[146.800507,-19.277344],"type":"Point"}
}