{
  "type": "Feature",
  "properties": {
    "iso:country":"AU",
    "sg:address":"Cnr Muller, North East Roads, Shopping Centre",
    "sg:city":"Greenacres",
    "sg:classifiers":[
        {
            "category":"Manufacturing",
            "subcategory":"Motor Vehicles & Parts",
            "type":"Manufacturing & Wholesale Goods"
        }
    ],
    "sg:phone":"+61 8 8261 5266",
    "sg:postcode":"5086",
    "sg:province":"SA",
    "sg:tags":[
        "replacement"
    ],
    "wof:name":"Autostore",
    "wof:placetype":"venue"
},
  "geometry": {"coordinates":[138.63351440400001,-34.8713150024],"type":"Point"}
}