{
  "type": "Feature",
  "properties": {
    "addr:full":"8 Waverley Rd Launceston TAS 7250",
    "addr:housenumber":"8",
    "addr:postcode":"7250",
    "addr:street":"Waverley Rd",
    "iso:country":"AU",
    "sg:address":"8 Waverley Rd",
    "sg:city":"Launceston",
    "sg:classifiers":[
        {
            "category":"Industrial Area",
            "type":"Public Place"
        }
    ],
    "sg:phone":"+61 3 6339 4489",
    "sg:postcode":"7250",
    "sg:province":"TAS",
    "sg:tags":[
        "rural",
        "shed"
    ],
    "wof:name":"Cyclad Buildings",
    "wof:placetype":"venue"
},
  "geometry": {"coordinates":[147.16065979000001,-41.4412384033],"type":"Point"}
}