{
  "type": "Feature",
  "properties": {
    "iso:country":"AU",
    "sg:address":"455 Redland Bay Rd",
    "sg:city":"Capalaba",
    "sg:classifiers":[
        {
            "category":"Transit Center",
            "subcategory":"Freight",
            "type":"Transportation"
        }
    ],
    "sg:phone":"+61 7 3206 3549",
    "sg:postcode":"4157",
    "sg:province":"QLD",
    "sg:tags":[
        "honey",
        "merchant"
    ],
    "wof:name":"ABs# Honey",
    "wof:placetype":"venue"
},
  "geometry": {"coordinates":[153.21432495100001,-27.5407943726],"type":"Point"}
}