{
  "type": "Feature",
  "properties": {
    "addr:full":"20 Market St Wollongong NSW 2500",
    "addr:housenumber":"20",
    "addr:postcode":"2500",
    "addr:street":"Market St",
    "iso:country":"AU",
    "sg:address":"20 Market St",
    "sg:city":"Wollongong",
    "sg:classifiers":[
        {
            "category":"Health Services",
            "subcategory":"Doctor",
            "type":"Services"
        }
    ],
    "sg:phone":"+61 2 4229 4533",
    "sg:postcode":"2500",
    "sg:province":"NSW",
    "sg:tags":[
        "medical",
        "practitioner"
    ],
    "wof:name":"Tomlin A",
    "wof:placetype":"venue"
},
  "geometry": {"coordinates":[150.894363,-34.423389],"type":"Point"}
}