{
  "type": "Feature",
  "properties": {
    "addr:full":"291a Maroondah Hwy Ringwood VIC 3134",
    "addr:housenumber":"291a",
    "addr:postcode":"3134",
    "addr:street":"Maroondah Hwy",
    "iso:country":"AU",
    "sg:address":"291a Maroondah Hwy",
    "sg:city":"Ringwood",
    "sg:classifiers":[
        {
            "category":"Organizations",
            "subcategory":"Community Association",
            "type":"Services"
        }
    ],
    "sg:phone":"+61 3 9871 1539",
    "sg:postcode":"3134",
    "sg:province":"VIC",
    "sg:tags":[
        "organisation",
        "family",
        "welfare"
    ],
    "wof:name":"Friends For Older People",
    "wof:placetype":"venue"
},
  "geometry": {"coordinates":[145.235061645,-37.8124542236],"type":"Point"}
}