{
  "type": "Feature",
  "properties": {
    "addr:full":"435 Freemans Reach Rd Freemans Reach NSW 2756",
    "addr:housenumber":"435",
    "addr:postcode":"2756",
    "addr:street":"Freemans Reach Rd",
    "iso:country":"AU",
    "sg:address":"435 Freemans Reach Rd",
    "sg:city":"Freemans Reach",
    "sg:classifiers":[
        {
            "category":"Home & Garden",
            "subcategory":"Garden Supply",
            "type":"Retail Goods"
        }
    ],
    "sg:phone":"+61 1800 796 173",
    "sg:postcode":"2756",
    "sg:province":"NSW",
    "sg:tags":[
        "turf",
        "lawn"
    ],
    "wof:name":"Bill's Turf Supplies",
    "wof:placetype":"venue"
},
  "geometry": {"coordinates":[150.79960632300001,-33.5579185486],"type":"Point"}
}