{
  "type": "Feature",
  "properties": {
    "addr:full":"1/ 14 Industrial Ave Molendinar QLD 4214",
    "addr:housenumber":"/ 14",
    "addr:postcode":"4214",
    "addr:street":"Industrial Ave",
    "iso:country":"AU",
    "sg:address":"1/ 14 Industrial Ave",
    "sg:city":"Molendinar",
    "sg:classifiers":[
        {
            "category":"Wholesale",
            "subcategory":"Metals & Minerals",
            "type":"Manufacturing & Wholesale Goods"
        }
    ],
    "sg:phone":"+61 7 5539 5517",
    "sg:postcode":"4214",
    "sg:province":"QLD",
    "sg:tags":[
        "steel",
        "merchant"
    ],
    "wof:name":"SV Steel Supplies",
    "wof:placetype":"venue"
},
  "geometry": {"coordinates":[153.375076294,-27.9781284332],"type":"Point"}
}