{
  "type": "Feature",
  "properties": {
    "addr:full":"Unit 3, 2 Commerce Drv Warilla NSW 2528",
    "addr:housenumber":"2",
    "addr:postcode":"2528",
    "addr:street":"Commerce Drv",
    "iso:country":"AU",
    "sg:address":"Unit 3, 2 Commerce Drv",
    "sg:city":"Warilla",
    "sg:classifiers":[
        {
            "category":"Manufacturing",
            "subcategory":"Metals",
            "type":"Manufacturing & Wholesale Goods"
        }
    ],
    "sg:phone":"+61 2 4295 5591",
    "sg:postcode":"2528",
    "sg:province":"NSW",
    "sg:tags":[
        "sheet",
        "worker"
    ],
    "wof:name":"O'Briens Sheetmetal & Insulations",
    "wof:placetype":"venue"
},
  "geometry": {"coordinates":[150.866577148,-34.547542572],"type":"Point"}
}