{
  "type": "Feature",
  "properties": {
    "addr:full":"4/ 13 Industrial Drv Coffs Harbour NSW 2450",
    "addr:housenumber":"/ 13",
    "addr:postcode":"2450",
    "addr:street":"Industrial Drv",
    "iso:country":"AU",
    "sg:address":"4/ 13 Industrial Drv",
    "sg:city":"Coffs Harbour",
    "sg:classifiers":[
        {
            "category":"Utilities",
            "subcategory":"Telephone",
            "type":"Services"
        }
    ],
    "sg:phone":"+61 2 6658 1088",
    "sg:postcode":"2450",
    "sg:province":"NSW",
    "sg:tags":[
        "installation",
        "system",
        "maintenance"
    ],
    "wof:name":"Klaustel Communications",
    "wof:placetype":"venue"
},
  "geometry": {"coordinates":[153.11515800000001,-30.29701],"type":"Point"}
}