{
  "type": "Feature",
  "properties": {
    "iso:country":"AU",
    "sg:address":"Kruesler Rd",
    "sg:city":"Waikerie",
    "sg:classifiers":[
        {
            "category":"Professional",
            "subcategory":"Engineering",
            "type":"Services"
        }
    ],
    "sg:phone":"+61 8 8541 3685",
    "sg:postcode":"5330",
    "sg:province":"SA",
    "sg:tags":[
        "engineer"
    ],
    "wof:name":"Hart Metal Finishers",
    "wof:placetype":"venue"
},
  "geometry": {"coordinates":[139.99110412600001,-34.2097320557],"type":"Point"}
}