{
  "type": "Feature",
  "properties": {
    "iso:country":"AU",
    "sg:address":"1913 Dandenong Rd",
    "sg:city":"Clayton North",
    "sg:classifiers":[
        {
            "category":"Food & Beverages",
            "subcategory":"Groceries & Convenience Stores",
            "type":"Retail Goods"
        }
    ],
    "sg:phone":"+61 3 9544 1253",
    "sg:postcode":"3168",
    "sg:province":"VIC",
    "wof:name":"Hong QI Milk & Sandwich Bar",
    "wof:placetype":"venue"
},
  "geometry": {"coordinates":[145.12176513700001,-37.914516449],"type":"Point"}
}