{
  "type": "Feature",
  "properties": {
    "iso:country":"AU",
    "sg:address":"162 Princess St",
    "sg:city":"Drysdale",
    "sg:classifiers":[
        {
            "category":"Train Station",
            "subcategory":"Rail",
            "type":"Transportation"
        }
    ],
    "sg:phone":"+61 3 5253 1260",
    "sg:postcode":"3222",
    "sg:province":"VIC",
    "sg:tags":[
        "marine",
        "engineer"
    ],
    "wof:name":"Drysdale Trawler & Farm Services Pty Ltd",
    "wof:placetype":"venue"
},
  "geometry": {"coordinates":[144.56776400000001,-38.187897],"type":"Point"}
}