{
  "type": "Feature",
  "properties": {
    "addr:full":"Immarna Rd Rathmines NSW 2283",
    "addr:postcode":"2283",
    "addr:street":"Immarna Rd",
    "iso:country":"AU",
    "sg:address":"Immarna Rd",
    "sg:city":"Rathmines",
    "sg:classifiers":[
        {
            "category":"Manufacturing",
            "subcategory":"Tools & Machinery",
            "type":"Manufacturing & Wholesale Goods"
        }
    ],
    "sg:phone":"+61 2 4975 4100",
    "sg:postcode":"2283",
    "sg:province":"NSW",
    "sg:tags":[
        "toolmaker"
    ],
    "wof:name":"Design Tooling",
    "wof:placetype":"venue"
},
  "geometry": {"coordinates":[151.568084717,-33.0377426147],"type":"Point"}
}