{
  "type": "Feature",
  "properties": {
    "addr:full":"60 Macedon St Sunbury VIC 3429",
    "addr:housenumber":"60",
    "addr:postcode":"3429",
    "addr:street":"Macedon St",
    "iso:country":"AU",
    "sg:address":"60 Macedon St",
    "sg:city":"Sunbury",
    "sg:classifiers":[
        {
            "category":"Travel",
            "subcategory":"Hotels & Motels",
            "type":"Entertainment"
        }
    ],
    "sg:phone":"+61 3 9744 1310",
    "sg:postcode":"3429",
    "sg:province":"VIC",
    "sg:tags":[
        "accommodation"
    ],
    "wof:name":"Ballcourt Hotel",
    "wof:placetype":"venue"
},
  "geometry": {"coordinates":[144.736526489,-37.5809745789],"type":"Point"}
}