{
  "type": "Feature",
  "properties": {
    "addr:full":"Wolfram Camp Rd Kellow QLD 4872",
    "addr:postcode":"4872",
    "addr:street":"Rd",
    "iso:country":"AU",
    "sg:address":"Wolfram Camp Rd",
    "sg:city":"Kellow",
    "sg:classifiers":[
        {
            "category":"Farming",
            "subcategory":"Farm",
            "type":"Manufacturing & Wholesale Goods"
        }
    ],
    "sg:phone":"+61 7 4093 6161",
    "sg:postcode":"4872",
    "sg:province":"QLD",
    "sg:tags":[
        "farmer"
    ],
    "wof:name":"Cashews Australia",
    "wof:placetype":"venue"
},
  "geometry": {"coordinates":[145.1068573,-17.9841003418],"type":"Point"}
}