{
  "type": "Feature",
  "properties": {
    "iso:country":"AU",
    "sg:address":"87 Ocean Rd",
    "sg:city":"Anglesea",
    "sg:classifiers":[
        {
            "category":"Personal",
            "subcategory":"Beauty Salon",
            "type":"Services"
        }
    ],
    "sg:phone":"+61 417 549 455",
    "sg:postcode":"3230",
    "sg:province":"VIC",
    "sg:tags":[
        "hairdresser"
    ],
    "wof:name":"Josephine's Hair Design",
    "wof:placetype":"venue"
},
  "geometry": {"coordinates":[144.18721,-38.410789],"type":"Point"}
}