{
  "type": "Feature",
  "properties": {
    "addr:full":"13- 15 Auscan Crs Garbutt QLD 4814",
    "addr:housenumber":"15",
    "addr:postcode":"4814",
    "addr:street":"Auscan Crs",
    "iso:country":"AU",
    "sg:address":"13- 15 Auscan Crs",
    "sg:city":"Garbutt",
    "sg:classifiers":[
        {
            "category":"Retail",
            "subcategory":"Storage",
            "type":"Services"
        }
    ],
    "sg:phone":"+61 7 4775 6333",
    "sg:postcode":"4814",
    "sg:province":"QLD",
    "wof:name":"Fly In - Fly Out Vehicle Storage",
    "wof:placetype":"venue"
},
  "geometry": {"coordinates":[146.78376800000001,-19.26436],"type":"Point"}
}