{
  "type": "Feature",
  "properties": {
    "addr:full":"14 Graham Ave Gumly Gumly NSW 2652",
    "addr:housenumber":"14",
    "addr:postcode":"2652",
    "addr:street":"Graham Ave",
    "iso:country":"AU",
    "sg:address":"14 Graham Ave",
    "sg:city":"Gumly Gumly",
    "sg:classifiers":[
        {
            "category":"Building & Trades",
            "subcategory":"Construction",
            "type":"Services"
        }
    ],
    "sg:phone":"+61 2 6922 7353",
    "sg:postcode":"2652",
    "sg:province":"NSW",
    "sg:tags":[
        "concrete",
        "contractor"
    ],
    "wof:name":"Argus Steven",
    "wof:placetype":"venue"
},
  "geometry": {"coordinates":[147.44070434599999,-35.1147003174],"type":"Point"}
}