{
  "type": "Feature",
  "properties": {
    "addr:full":"205B Middleborough Rd Box Hill VIC 3128",
    "addr:housenumber":"205b",
    "addr:postcode":"3128",
    "addr:street":"Middleborough Rd",
    "iso:country":"AU",
    "sg:address":"205B Middleborough Rd",
    "sg:city":"Box Hill",
    "sg:classifiers":[
        {
            "category":"Wholesale",
            "subcategory":"Construction Materials",
            "type":"Manufacturing & Wholesale Goods"
        }
    ],
    "sg:phone":"+61 1300 300 301",
    "sg:postcode":"3128",
    "sg:province":"VIC",
    "sg:tags":[
        "wholesaler",
        "lighting",
        "mfrs",
        "accessory"
    ],
    "sg:website":"http://www.anl-light.com.au",
    "wof:name":"ANL Lighting Australia Pty Ltd",
    "wof:placetype":"venue"
},
  "geometry": {"coordinates":[145.13453674300001,-37.8391876221],"type":"Point"}
}