{
  "type": "Feature",
  "properties": {
    "addr:full":"137 Sturt Rd Dover Gardens SA 5048",
    "addr:housenumber":"137",
    "addr:postcode":"5048",
    "addr:street":"Sturt Rd",
    "iso:country":"AU",
    "sg:address":"137 Sturt Rd",
    "sg:city":"Dover Gardens",
    "sg:classifiers":[
        {
            "category":"Building & Trades",
            "subcategory":"Landscaping Services",
            "type":"Services"
        }
    ],
    "sg:phone":"+61 8 8298 1149",
    "sg:postcode":"5048",
    "sg:province":"SA",
    "sg:tags":[
        "stump",
        "tree",
        "felling",
        "removal"
    ],
    "wof:name":"Ingerson Dave",
    "wof:placetype":"venue"
},
  "geometry": {"coordinates":[138.53813199999999,-35.018532],"type":"Point"}
}