{
  "type": "Feature",
  "properties": {
    "addr:full":"34- 36 Whybrow St Griffith NSW 2680",
    "addr:housenumber":"36",
    "addr:postcode":"2680",
    "addr:street":"Whybrow St",
    "iso:country":"AU",
    "sg:address":"34- 36 Whybrow St",
    "sg:city":"Griffith",
    "sg:classifiers":[
        {
            "category":"Utilities",
            "subcategory":"Refuse",
            "type":"Services"
        }
    ],
    "sg:phone":"+61 412 951 316",
    "sg:postcode":"2680",
    "sg:province":"NSW",
    "sg:tags":[
        "disposal",
        "reduction",
        "waste"
    ],
    "wof:name":"Griffith Waste Removal",
    "wof:placetype":"venue"
},
  "geometry": {"coordinates":[146.07321200000001,-34.292023],"type":"Point"}
}