{
  "type": "Feature",
  "properties": {
    "addr:full":"Suite 36 35 Orchid Ave Surfers Paradise QLD 4217",
    "addr:housenumber":"35",
    "addr:postcode":"4217",
    "addr:street":"Orchid Ave",
    "iso:country":"AU",
    "sg:address":"Suite 36 35 Orchid Ave",
    "sg:city":"Surfers Paradise",
    "sg:classifiers":[
        {
            "category":"Insurance",
            "subcategory":"Insurance Agent",
            "type":"Services"
        }
    ],
    "sg:phone":"+61 7 5555 6222",
    "sg:postcode":"4217",
    "sg:province":"QLD",
    "sg:tags":[
        "broker"
    ],
    "wof:name":"Elkington Bishop Molineaux Insurance Brokers Pty Ltd",
    "wof:placetype":"venue"
},
  "geometry": {"coordinates":[153.42955017099999,-27.9991607666],"type":"Point"}
}