{
  "type": "Feature",
  "properties": {
    "addr:full":"40 Albany St St Leonards NSW 2065",
    "addr:housenumber":"40",
    "addr:postcode":"2065",
    "addr:street":"Albany St",
    "iso:country":"AU",
    "sg:address":"40 Albany St",
    "sg:city":"St Leonards",
    "sg:classifiers":[
        {
            "category":"Personal",
            "type":"Services"
        }
    ],
    "sg:phone":"+61 2 9901 4444",
    "sg:postcode":"2065",
    "sg:province":"NSW",
    "sg:tags":[
        "gift"
    ],
    "wof:name":"giftworks.com.au",
    "wof:placetype":"venue"
},
  "geometry": {"coordinates":[151.19767761200001,-33.8236579895],"type":"Point"}
}