{
  "type": "Feature",
  "properties": {
    "addr:full":"91 Beardy St Armidale NSW 2350",
    "addr:housenumber":"91",
    "addr:postcode":"2350",
    "addr:street":"Beardy St",
    "iso:country":"AU",
    "sg:address":"91 Beardy St",
    "sg:city":"Armidale",
    "sg:classifiers":[
        {
            "category":"Manufacturing",
            "subcategory":"Food",
            "type":"Manufacturing & Wholesale Goods"
        }
    ],
    "sg:phone":"+61 2 6771 4434",
    "sg:postcode":"2350",
    "sg:province":"NSW",
    "sg:tags":[
        "function",
        "catering"
    ],
    "wof:name":"Jazzamataz Professional Catering Service",
    "wof:placetype":"venue"
},
  "geometry": {"coordinates":[151.66950988799999,-30.5141601562],"type":"Point"}
}