{
  "type": "Feature",
  "properties": {
    "iso:country":"AU",
    "sg:address":"163- 167 The Boulevarde",
    "sg:city":"Fairfield Heights",
    "sg:classifiers":[
        {
            "category":"Retail",
            "subcategory":"Auto Repair",
            "type":"Services"
        }
    ],
    "sg:phone":"+61 2 9728 6111",
    "sg:postcode":"2165",
    "sg:province":"NSW",
    "sg:tags":[
        "repairer",
        "motor",
        "engineer"
    ],
    "wof:name":"Italiano Mechanical Repairs",
    "wof:placetype":"venue"
},
  "geometry": {"coordinates":[150.93797302199999,-33.8663139343],"type":"Point"}
}