{
  "type": "Feature",
  "properties": {
    "addr:full":"Shp 2, 61 Station St Engadine NSW 2233",
    "addr:housenumber":"61",
    "addr:postcode":"2233",
    "addr:street":"Station St",
    "iso:country":"AU",
    "sg:address":"Shp 2, 61 Station St",
    "sg:city":"Engadine",
    "sg:classifiers":[
        {
            "category":"Professional",
            "subcategory":"Accounting & Tax Preparation",
            "type":"Services"
        }
    ],
    "sg:phone":"+61 2 9548 1179",
    "sg:postcode":"2233",
    "sg:province":"NSW",
    "sg:tags":[
        "consultant",
        "taxation"
    ],
    "wof:name":"H&R Block",
    "wof:placetype":"venue"
},
  "geometry": {"coordinates":[151.013275147,-34.0659217834],"type":"Point"}
}