{
  "type": "Feature",
  "properties": {
    "iso:country":"AU",
    "sg:address":"596 Cross Rd",
    "sg:city":"South Plympton",
    "sg:classifiers":[
        {
            "category":"Professional",
            "subcategory":"Printing & Photocopies",
            "type":"Services"
        }
    ],
    "sg:phone":"+61 8 8293 8856",
    "sg:postcode":"5038",
    "sg:province":"SA",
    "sg:tags":[
        "photocopier"
    ],
    "wof:name":"Copy Tec Services P/L",
    "wof:placetype":"venue"
},
  "geometry": {"coordinates":[138.55781555199999,-34.9678153992],"type":"Point"}
}