{
  "type": "Feature",
  "properties": {
    "addr:full":"RMB 2252 Rd Yea VIC 3717",
    "addr:postcode":"3717",
    "addr:street":"2252 Rd",
    "iso:country":"AU",
    "sg:address":"RMB 2252 Rd",
    "sg:city":"Yea",
    "sg:classifiers":[
        {
            "category":"Professional",
            "subcategory":"Management & Consulting",
            "type":"Services"
        }
    ],
    "sg:phone":"+61 3 5797 2898",
    "sg:postcode":"3717",
    "sg:province":"VIC",
    "sg:tags":[
        "consultant",
        "energy"
    ],
    "wof:name":"Seymour Solar & Alternatives",
    "wof:placetype":"venue"
},
  "geometry": {"coordinates":[145.41664123499999,-37.2135009766],"type":"Point"}
}