{
  "type": "Feature",
  "properties": {
    "addr:full":"18 Whiting St Artarmon NSW 2064",
    "addr:housenumber":"18",
    "addr:postcode":"2064",
    "addr:street":"Whiting St",
    "iso:country":"AU",
    "sg:address":"18 Whiting St",
    "sg:city":"Artarmon",
    "sg:classifiers":[
        {
            "category":"Retail",
            "subcategory":"Auto Repair",
            "type":"Services"
        }
    ],
    "sg:phone":"+61 2 9906 5756",
    "sg:postcode":"2064",
    "sg:province":"NSW",
    "sg:tags":[
        "beater",
        "painter",
        "panel"
    ],
    "wof:name":"J A United Smash Repairs",
    "wof:placetype":"venue"
},
  "geometry": {"coordinates":[151.18423461899999,-33.8148574829],"type":"Point"}
}