{
  "type": "Feature",
  "properties": {
    "addr:full":"33/ 35 Weston Rd Brunswick VIC 3056",
    "addr:housenumber":"33 / 35",
    "addr:postcode":"3056",
    "addr:street":"Weston Rd",
    "iso:country":"AU",
    "sg:address":"33/ 35 Weston Rd",
    "sg:city":"Brunswick",
    "sg:classifiers":[
        {
            "category":"Shopping",
            "subcategory":"Pets & Pet Supplies",
            "type":"Retail Goods"
        }
    ],
    "sg:phone":"+61 3 9380 5566",
    "sg:postcode":"3056",
    "sg:province":"VIC",
    "sg:tags":[
        "shop",
        "supplier"
    ],
    "wof:name":"Brunswick Pet Shop",
    "wof:placetype":"venue"
},
  "geometry": {"coordinates":[144.96165466299999,-37.7706222534],"type":"Point"}
}