{
  "type": "Feature",
  "properties": {
    "addr:full":"28 Tombondan Crs Ferny Hills QLD 4055",
    "addr:housenumber":"28",
    "addr:postcode":"4055",
    "addr:street":"Tombondan Crs",
    "iso:country":"AU",
    "sg:address":"28 Tombondan Crs",
    "sg:city":"Ferny Hills",
    "sg:classifiers":[
        {
            "category":"Professional",
            "subcategory":"Detective & Security Services",
            "type":"Services"
        }
    ],
    "sg:phone":"+61 7 3351 4870",
    "sg:postcode":"4055",
    "sg:province":"QLD",
    "sg:tags":[
        "equipment",
        "window",
        "doors"
    ],
    "wof:name":"Quick Clip Insect Screens",
    "wof:placetype":"venue"
},
  "geometry": {"coordinates":[152.93775939899999,-27.4006195068],"type":"Point"}
}