{
  "type": "Feature",
  "properties": {
    "addr:full":"Cnr Keys Rd & Hewitt St Cheltenham VIC 3192",
    "addr:postcode":"3192",
    "addr:street":"Keys Rd & Hewitt St",
    "iso:country":"AU",
    "sg:address":"Cnr Keys Rd & Hewitt St",
    "sg:city":"Cheltenham",
    "sg:classifiers":[
        {
            "category":"Retail",
            "subcategory":"Auto Repair",
            "type":"Services"
        }
    ],
    "sg:phone":"+61 3 9553 3168",
    "sg:postcode":"3192",
    "sg:province":"VIC",
    "sg:tags":[
        "automotive",
        "air conditioning"
    ],
    "wof:name":"Bonny Auto Air",
    "wof:placetype":"venue"
},
  "geometry": {"coordinates":[145.07731628400001,-37.949798584],"type":"Point"}
}