{
  "type": "Feature",
  "properties": {
    "iso:country":"AU",
    "sg:address":"Level 3, 70 Hindmarsh Sq",
    "sg:city":"Adelaide",
    "sg:classifiers":[
        {
            "category":"Insurance",
            "subcategory":"Insurance Agent",
            "type":"Services"
        }
    ],
    "sg:phone":"+61 8 8418 0288",
    "sg:postcode":"5000",
    "sg:province":"SA",
    "sg:tags":[
        "broker"
    ],
    "wof:name":"Jardine Lloyd Thompson Pty Ltd",
    "wof:placetype":"venue"
},
  "geometry": {"coordinates":[138.6065979,-34.9244499207],"type":"Point"}
}