{
  "type": "Feature",
  "properties": {
    "iso:country":"AU",
    "sg:address":"31 Prince St",
    "sg:city":"Cronulla",
    "sg:classifiers":[
        {
            "category":"Building & Trades",
            "subcategory":"Construction",
            "type":"Services"
        }
    ],
    "sg:phone":"+61 2 9527 1206",
    "sg:postcode":"2230",
    "sg:province":"NSW",
    "sg:tags":[
        "sun",
        "product",
        "protection"
    ],
    "wof:name":"Absolute Privacy Window Tinting",
    "wof:placetype":"venue"
},
  "geometry": {"coordinates":[151.15647888199999,-34.0496406555],"type":"Point"}
}