{
  "type": "Feature",
  "properties": {
    "addr:full":"Shp4/ 4 Peel St Tamworth NSW 2340",
    "addr:housenumber":"4",
    "addr:postcode":"2340",
    "addr:street":"Peel St",
    "iso:country":"AU",
    "sg:address":"Shp4/ 4 Peel St",
    "sg:city":"Tamworth",
    "sg:classifiers":[
        {
            "category":"Fast Food",
            "type":"Food & Drink"
        }
    ],
    "sg:phone":"+61 2 6766 9505",
    "sg:postcode":"2340",
    "sg:province":"NSW",
    "sg:tags":[
        "away",
        "take"
    ],
    "wof:name":"Northgate Chickens And Takeaway",
    "wof:placetype":"venue"
},
  "geometry": {"coordinates":[150.92665100100001,-31.0869941711],"type":"Point"}
}