{
  "type": "Feature",
  "properties": {
    "addr:full":"7 Grand Ave Camellia NSW 2142",
    "addr:housenumber":"7",
    "addr:postcode":"2142",
    "addr:street":"Grand Ave",
    "iso:country":"AU",
    "sg:address":"7 Grand Ave",
    "sg:city":"Camellia",
    "sg:classifiers":[
        {
            "category":"Food & Beverages",
            "subcategory":"Bakery",
            "type":"Retail Goods"
        }
    ],
    "sg:phone":"+61 2 9898 1600",
    "sg:postcode":"2142",
    "sg:province":"NSW",
    "sg:tags":[
        "baker"
    ],
    "wof:name":"Croissant King Pty Ltd",
    "wof:placetype":"venue"
},
  "geometry": {"coordinates":[151.037643433,-33.8209838867],"type":"Point"}
}