{
  "type": "Feature",
  "properties": {
    "iso:country":"AU",
    "sg:address":"9 Riverdowns Drv",
    "sg:city":"Margate",
    "sg:classifiers":[
        {
            "category":"Personal",
            "subcategory":"Massage",
            "type":"Services"
        }
    ],
    "sg:phone":"+61 3 6267 1467",
    "sg:postcode":"7054",
    "sg:province":"TAS",
    "sg:tags":[
        "therapy"
    ],
    "wof:name":"Golden Moments Massage",
    "wof:placetype":"venue"
},
  "geometry": {"coordinates":[147.263229,-43.025661],"type":"Point"}
}