{
  "type": "Feature",
  "properties": {
    "addr:full":"Shop 27 Booval Fair Booval QLD 4304",
    "addr:housenumber":"shop 27",
    "addr:postcode":"4304",
    "iso:country":"AU",
    "sg:address":"Shop 27",
    "sg:city":"Booval Fair Booval",
    "sg:classifiers":[
        {
            "category":"Shopping",
            "subcategory":"Music",
            "type":"Retail Goods"
        }
    ],
    "sg:phone":"+61 7 3281 0206",
    "sg:postcode":"4304",
    "sg:province":"QLD",
    "sg:tags":[
        "store"
    ],
    "wof:name":"Booval Music",
    "wof:placetype":"venue"
},
  "geometry": {"coordinates":[152.787719727,-27.6111545563],"type":"Point"}
}