{
  "type": "Feature",
  "properties": {
    "addr:full":"Belyando Ave Moranbah QLD 4744",
    "addr:postcode":"4744",
    "addr:street":"Belyando Ave",
    "iso:country":"AU",
    "sg:address":"Belyando Ave",
    "sg:city":"Moranbah",
    "sg:classifiers":[
        {
            "category":"Autos & Motor Vehicles",
            "subcategory":"Fuel & Gas Station",
            "type":"Retail Goods"
        }
    ],
    "sg:phone":"+61 7 4941 8441",
    "sg:postcode":"4744",
    "sg:province":"QLD",
    "wof:name":"Ampol Belyando Service Station",
    "wof:placetype":"venue"
},
  "geometry": {"coordinates":[148.04861450199999,-21.9986724854],"type":"Point"}
}