{
  "type": "Feature",
  "properties": {
    "addr:full":"7 Bradwardine Rd Bathurst NSW 2795",
    "addr:housenumber":"7",
    "addr:postcode":"2795",
    "addr:street":"Bradwardine Rd",
    "iso:country":"AU",
    "sg:address":"7 Bradwardine Rd",
    "sg:city":"Bathurst",
    "sg:classifiers":[
        {
            "category":"Home & Garden",
            "subcategory":"Hardware",
            "type":"Retail Goods"
        }
    ],
    "sg:phone":"+61 2 6332 9829",
    "sg:postcode":"2795",
    "sg:province":"NSW",
    "sg:tags":[
        "tarpaulin"
    ],
    "wof:name":"All Cover Canvas",
    "wof:placetype":"venue"
},
  "geometry": {"coordinates":[149.54383850100001,-33.4146194458],"type":"Point"}
}