{
  "type": "Feature",
  "properties": {
    "addr:full":"374 Jamison Rd Penrith NSW 2750",
    "addr:housenumber":"374",
    "addr:postcode":"2750",
    "addr:street":"Jamison Rd",
    "iso:country":"AU",
    "sg:address":"374 Jamison Rd",
    "sg:city":"Penrith",
    "sg:classifiers":[
        {
            "category":"Building & Trades",
            "subcategory":"Construction",
            "type":"Services"
        }
    ],
    "sg:phone":"+61 2 4737 9970",
    "sg:postcode":"2750",
    "sg:province":"NSW",
    "sg:tags":[
        "contractor"
    ],
    "wof:name":"Summers Carpentry & Building",
    "wof:placetype":"venue"
},
  "geometry": {"coordinates":[150.68052673299999,-33.7603378296],"type":"Point"}
}