{
  "type": "Feature",
  "properties": {
    "addr:full":"281 Elizabeth St Sydney NSW 2000",
    "addr:housenumber":"281",
    "addr:postcode":"2000",
    "addr:street":"Elizabeth St",
    "iso:country":"AU",
    "sg:address":"281 Elizabeth St",
    "sg:city":"Sydney",
    "sg:classifiers":[
        {
            "category":"Travel",
            "subcategory":"Hotels & Motels",
            "type":"Entertainment"
        }
    ],
    "sg:phone":"+61 2 9283 8811",
    "sg:postcode":"2000",
    "sg:province":"NSW",
    "sg:tags":[
        "accommodation"
    ],
    "wof:name":"Somerset Hyde Park",
    "wof:placetype":"venue"
},
  "geometry": {"coordinates":[151.20950317399999,-33.8758888245],"type":"Point"}
}