{
  "type": "Feature",
  "properties": {
    "addr:full":"828 Pacific Hwy Niagara Park NSW 2250",
    "addr:housenumber":"828",
    "addr:postcode":"2250",
    "addr:street":"Pacific Hwy Niagara Park",
    "iso:country":"AU",
    "sg:address":"828 Pacific Hwy",
    "sg:city":"Niagara Park",
    "sg:classifiers":[
        {
            "category":"Social Services",
            "subcategory":"Adult Care",
            "type":"Services"
        }
    ],
    "sg:phone":"+61 2 4329 6664",
    "sg:postcode":"2250",
    "sg:province":"NSW",
    "sg:tags":[
        "aged"
    ],
    "wof:name":"Providence Projects",
    "wof:placetype":"venue"
},
  "geometry": {"coordinates":[151.355636597,-33.3841171265],"type":"Point"}
}