{
  "type": "Feature",
  "properties": {
    "iso:country":"AU",
    "sg:address":"30 Brook St",
    "sg:city":"Coogee",
    "sg:classifiers":[
        {
            "category":"Utilities",
            "subcategory":"Electric",
            "type":"Services"
        }
    ],
    "sg:phone":"+61 2 9665 3491",
    "sg:postcode":"2034",
    "sg:province":"NSW",
    "sg:tags":[
        "electrical",
        "contractor"
    ],
    "wof:name":"Pacitti G J",
    "wof:placetype":"venue"
},
  "geometry": {"coordinates":[151.25570678700001,-33.913028717],"type":"Point"}
}