{
  "type": "Feature",
  "properties": {
    "addr:full":"Shop 1a Ocean St Maroochydore QLD 4558",
    "addr:housenumber":"shop 1a",
    "addr:postcode":"4558",
    "addr:street":"Ocean St",
    "iso:country":"AU",
    "sg:address":"Shop 1a Ocean St",
    "sg:city":"Maroochydore",
    "sg:classifiers":[
        {
            "category":"Retail",
            "subcategory":"Repair Shop",
            "type":"Services"
        }
    ],
    "sg:phone":"+61 7 5443 8633",
    "sg:postcode":"4558",
    "sg:province":"QLD",
    "sg:tags":[
        "mending",
        "clothing",
        "alteration"
    ],
    "wof:name":"Allstyle Clothing Alterations & Repairs",
    "wof:placetype":"venue"
},
  "geometry": {"coordinates":[153.09184265100001,-26.6515007019],"type":"Point"}
}