{
  "type": "Feature",
  "properties": {
    "addr:full":"43 Bent St Lindfield NSW 2070",
    "addr:housenumber":"43",
    "addr:postcode":"2070",
    "addr:street":"Bent St",
    "iso:country":"AU",
    "sg:address":"43 Bent St",
    "sg:city":"Lindfield",
    "sg:classifiers":[
        {
            "category":"Health Services",
            "subcategory":"Health Practitioner",
            "type":"Services"
        }
    ],
    "sg:phone":"+61 2 9924 2232",
    "sg:postcode":"2070",
    "sg:province":"NSW",
    "sg:tags":[
        "naturopath"
    ],
    "wof:name":"Smith Judy",
    "wof:placetype":"venue"
},
  "geometry": {"coordinates":[151.16314697300001,-33.7769508362],"type":"Point"}
}