{
  "type": "Feature",
  "properties": {
    "iso:country":"AU",
    "sg:address":"311 Margaret St",
    "sg:city":"Toowoomba",
    "sg:classifiers":[
        {
            "category":"Health Services",
            "subcategory":"Health Practitioner",
            "type":"Services"
        }
    ],
    "sg:phone":"+61 7 4638 9600",
    "sg:postcode":"4350",
    "sg:province":"QLD",
    "sg:tags":[
        "naturopath"
    ],
    "wof:name":"Mim Dade",
    "wof:placetype":"venue"
},
  "geometry": {"coordinates":[151.94714400000001,-27.559969],"type":"Point"}
}