{
  "type": "Feature",
  "properties": {
    "addr:full":"Shp6 Ross Court 195 Bloomfield St Cleveland Cleveland QLD 4163",
    "addr:housenumber":"195",
    "addr:postcode":"4163",
    "addr:street":"Ross;Bloomfield St",
    "iso:country":"AU",
    "sg:address":"Shp6 Ross Court 195 Bloomfield St",
    "sg:city":"Cleveland Cleveland",
    "sg:classifiers":[
        {
            "category":"Health Services",
            "subcategory":"Health Practitioner",
            "type":"Services"
        }
    ],
    "sg:phone":"+61 7 3821 5111",
    "sg:postcode":"4163",
    "sg:province":"QLD",
    "sg:tags":[
        "naturopath"
    ],
    "wof:name":"Allied Health Centre",
    "wof:placetype":"venue"
},
  "geometry": {"coordinates":[153.26657104500001,-27.5306587219],"type":"Point"}
}