{
  "type": "Feature",
  "properties": {
    "addr:full":"12 Tarrant St Warracknabeal VIC 3393",
    "addr:housenumber":"12",
    "addr:postcode":"3393",
    "addr:street":"Tarrant St",
    "iso:country":"AU",
    "sg:address":"12 Tarrant St",
    "sg:city":"Warracknabeal",
    "sg:classifiers":[
        {
            "category":"Professional",
            "subcategory":"Engineering",
            "type":"Services"
        }
    ],
    "sg:phone":"+61 3 5398 1081",
    "sg:postcode":"3393",
    "sg:province":"VIC",
    "sg:tags":[
        "engineer"
    ],
    "wof:name":"Bells Farma Products Pty Ltd",
    "wof:placetype":"venue"
},
  "geometry": {"coordinates":[142.398681641,-36.2489204407],"type":"Point"}
}