{
  "type": "Feature",
  "properties": {
    "addr:full":"8 Lawson Crt Hoppers Crossing VIC 3029",
    "addr:housenumber":"8",
    "addr:postcode":"3029",
    "addr:street":"Lawson Crt",
    "iso:country":"AU",
    "sg:address":"8 Lawson Crt",
    "sg:city":"Hoppers Crossing",
    "sg:classifiers":[
        {
            "category":"Building & Trades",
            "subcategory":"Plumbing",
            "type":"Services"
        }
    ],
    "sg:phone":"+61 3 9749 4266",
    "sg:postcode":"3029",
    "sg:province":"VIC",
    "sg:tags":[
        "plumber",
        "gasfitters"
    ],
    "wof:name":"Allan Cailes Plumbing Service",
    "wof:placetype":"venue"
},
  "geometry": {"coordinates":[144.69778400000001,-37.858669],"type":"Point"}
}