{
  "type": "Feature",
  "properties": {
    "addr:full":"485 Punt Rd South Yarra VIC 3141",
    "addr:housenumber":"485",
    "addr:postcode":"3141",
    "addr:street":"Punt Rd",
    "iso:country":"AU",
    "sg:address":"485 Punt Rd",
    "sg:city":"South Yarra",
    "sg:classifiers":[
        {
            "category":"Health Services",
            "subcategory":"Health Practitioner",
            "type":"Services"
        }
    ],
    "sg:phone":"+61 3 9866 5576",
    "sg:postcode":"3141",
    "sg:province":"VIC",
    "sg:tags":[
        "osteopath"
    ],
    "wof:name":"Eva Benes, Nahla Khraim, Craig Russell",
    "wof:placetype":"venue"
},
  "geometry": {"coordinates":[144.98518371599999,-37.8440589905],"type":"Point"}
}