{
  "type": "Feature",
  "properties": {
    "addr:full":"103 Main St Romsey VIC 3434",
    "addr:housenumber":"103",
    "addr:postcode":"3434",
    "addr:street":"Main St",
    "iso:country":"AU",
    "sg:address":"103 Main St",
    "sg:city":"Romsey",
    "sg:classifiers":[
        {
            "category":"Professional",
            "subcategory":"Management & Consulting",
            "type":"Services"
        }
    ],
    "sg:phone":"+61 3 5429 6331",
    "sg:postcode":"3434",
    "sg:province":"VIC",
    "sg:tags":[
        "consultant"
    ],
    "wof:name":"Australian Strategic Services Pty Ltd",
    "wof:placetype":"venue"
},
  "geometry": {"coordinates":[144.74217224099999,-37.3484916687],"type":"Point"}
}