{
  "type": "Feature",
  "properties": {
    "iso:country":"AU",
    "sg:address":"328 Walcott St",
    "sg:city":"Menora",
    "sg:classifiers":[
        {
            "category":"Shopping",
            "subcategory":"Antiques",
            "type":"Retail Goods"
        }
    ],
    "sg:phone":"+61 8 9443 5367",
    "sg:postcode":"6050",
    "sg:province":"WA",
    "wof:name":"French Antiques & Interiors",
    "wof:placetype":"venue"
},
  "geometry": {"coordinates":[115.85736084,-31.9215717316],"type":"Point"}
}