{
  "type": "Feature",
  "properties": {
    "addr:full":"701 Sturt St Ballarat VIC 3350",
    "addr:housenumber":"701",
    "addr:postcode":"3350",
    "addr:street":"Sturt St",
    "iso:country":"AU",
    "sg:address":"701 Sturt St",
    "sg:city":"Ballarat",
    "sg:classifiers":[
        {
            "category":"Real Estate",
            "subcategory":"Real Estate Agent",
            "type":"Services"
        }
    ],
    "sg:phone":"+61 3 5333 4466",
    "sg:postcode":"3350",
    "sg:province":"VIC",
    "wof:name":"Wes Davidson Real Estate",
    "wof:placetype":"venue"
},
  "geometry": {"coordinates":[143.85020399999999,-37.561371],"type":"Point"}
}