{
  "type": "Feature",
  "properties": {
    "iso:country":"AU",
    "sg:address":"8 Burns St",
    "sg:city":"Lockington",
    "sg:classifiers":[
        {
            "category":"Education",
            "subcategory":"Kindergarten",
            "type":"Public Place"
        }
    ],
    "sg:phone":"+61 3 5486 2585",
    "sg:postcode":"3563",
    "sg:province":"VIC",
    "sg:tags":[
        "pre-schools"
    ],
    "wof:name":"Lockington Pre School Centre",
    "wof:placetype":"venue"
},
  "geometry": {"coordinates":[144.53753699999999,-36.267826],"type":"Point"}
}