{
  "type": "Feature",
  "properties": {
    "iso:country":"AU",
    "sg:address":"111 Airds Rd",
    "sg:city":"Minto",
    "sg:classifiers":[
        {
            "category":"Shopping",
            "subcategory":"Gifts & Souvenirs",
            "type":"Retail Goods"
        }
    ],
    "sg:phone":"+61 2 9603 5746",
    "sg:postcode":"2566",
    "sg:province":"NSW",
    "sg:tags":[
        "greeting",
        "card"
    ],
    "wof:name":"Fine Art Developments Pty Ltd",
    "wof:placetype":"venue"
},
  "geometry": {"coordinates":[150.83535766599999,-34.0365447998],"type":"Point"}
}