{
  "type": "Feature",
  "properties": {
    "addr:full":"4 Nelson Ave Padstow NSW 2211",
    "addr:housenumber":"4",
    "addr:postcode":"2211",
    "addr:street":"Nelson Ave",
    "iso:country":"AU",
    "sg:address":"4 Nelson Ave",
    "sg:city":"Padstow",
    "sg:classifiers":[
        {
            "category":"Wholesale",
            "subcategory":"Painting Supplies",
            "type":"Manufacturing & Wholesale Goods"
        }
    ],
    "sg:phone":"+61 2 9790 5158",
    "sg:postcode":"2211",
    "sg:province":"NSW",
    "sg:tags":[
        "wholesaler",
        "paint",
        "mfrs"
    ],
    "wof:name":"Flood Company Australia Pty Limited The",
    "wof:placetype":"venue"
},
  "geometry": {"coordinates":[151.02835099999999,-33.936882],"type":"Point"}
}