{
  "type": "Feature",
  "properties": {
    "addr:full":"Shop 6 , Apollo Parkways Shopping Centre, Civic Driv VIC 3088",
    "addr:housenumber":"shop 6",
    "addr:postcode":"3088",
    "addr:street":"Apollo Parkways;Civic",
    "iso:country":"AU",
    "sg:address":"Shop 6",
    "sg:city":", Apollo Parkways Shopping Centre, Civic Driv",
    "sg:classifiers":[
        {
            "category":"Personal",
            "subcategory":"Beauty Salon",
            "type":"Services"
        }
    ],
    "sg:phone":"+61 3 9434 1155",
    "sg:postcode":"3088",
    "sg:province":"VIC",
    "sg:tags":[
        "hairdresser"
    ],
    "wof:name":"Style &#039;N&#039; Smile",
    "wof:placetype":"venue"
},
  "geometry": {"coordinates":[145.10618591299999,-37.6879386902],"type":"Point"}
}