{
  "type": "Feature",
  "properties": {
    "addr:full":"40 Advantage Rd Highett VIC 3190",
    "addr:housenumber":"40",
    "addr:postcode":"3190",
    "addr:street":"Advantage Rd",
    "iso:country":"AU",
    "sg:address":"40 Advantage Rd",
    "sg:city":"Highett",
    "sg:classifiers":[
        {
            "category":"Manufacturing",
            "subcategory":"Building Materials",
            "type":"Manufacturing & Wholesale Goods"
        }
    ],
    "sg:phone":"+61 3 9555 1911",
    "sg:postcode":"3190",
    "sg:province":"VIC",
    "sg:tags":[
        "adhesive",
        "tape"
    ],
    "wof:name":"Fletcher Warwick Packaging Pty Ltd",
    "wof:placetype":"venue"
},
  "geometry": {"coordinates":[145.03036499000001,-37.9517784119],"type":"Point"}
}