{
  "type": "Feature",
  "properties": {
    "addr:full":"Level 3/ 75 King St Sydney NSW 2000",
    "addr:housenumber":"/ 75",
    "addr:postcode":"2000",
    "addr:street":"King St",
    "iso:country":"AU",
    "sg:address":"Level 3/ 75 King St",
    "sg:city":"Sydney",
    "sg:classifiers":[
        {
            "category":"Real Estate",
            "subcategory":"Architect",
            "type":"Services"
        }
    ],
    "sg:phone":"+61 2 9262 4008",
    "sg:postcode":"2000",
    "sg:province":"NSW",
    "wof:name":"Stephen Bowers Architect",
    "wof:placetype":"venue"
},
  "geometry": {"coordinates":[151.206756592,-33.8688278198],"type":"Point"}
}