{
  "type": "Feature",
  "properties": {
    "iso:country":"AU",
    "sg:address":"122 Fussell St",
    "sg:city":"Ballarat",
    "sg:classifiers":[
        {
            "category":"Utilities",
            "subcategory":"Water",
            "type":"Services"
        }
    ],
    "sg:phone":"+61 3 5333 2941",
    "sg:postcode":"3350",
    "sg:province":"VIC",
    "sg:tags":[
        "equipment",
        "treatment"
    ],
    "wof:name":"Westlab",
    "wof:placetype":"venue"
},
  "geometry": {"coordinates":[143.893463,-37.564087],"type":"Point"}
}