{
  "type": "Feature",
  "properties": {
    "addr:full":"Level 11, 459 Lt Collins St Melbourne VIC 3000",
    "addr:housenumber":"459",
    "addr:postcode":"3000",
    "addr:street":"Lt Collins St",
    "iso:country":"AU",
    "sg:address":"Level 11, 459 Lt Collins St",
    "sg:city":"Melbourne",
    "sg:classifiers":[
        {
            "category":"Insurance",
            "subcategory":"Title Insurance",
            "type":"Services"
        }
    ],
    "sg:phone":"+61 409 174 124",
    "sg:postcode":"3000",
    "sg:province":"VIC",
    "sg:tags":[
        "searcher"
    ],
    "wof:name":"Ian D Clarke & Associates",
    "wof:placetype":"venue"
},
  "geometry": {"coordinates":[144.96035766599999,-37.81457901],"type":"Point"}
}