{
  "type": "Feature",
  "properties": {
    "addr:full":"78 Monterey Keys Drv Helensvale QLD 4212",
    "addr:housenumber":"78",
    "addr:postcode":"4212",
    "addr:street":"Monterey Keys Drv",
    "iso:country":"AU",
    "sg:address":"78 Monterey Keys Drv",
    "sg:city":"Helensvale",
    "sg:classifiers":[
        {
            "category":"Health Services",
            "subcategory":"Dentist",
            "type":"Services"
        }
    ],
    "sg:phone":"+61 7 5529 8590",
    "sg:postcode":"4212",
    "sg:province":"QLD",
    "sg:tags":[
        "technician",
        "dental"
    ],
    "wof:name":"Helen's Denture Service",
    "wof:placetype":"venue"
},
  "geometry": {"coordinates":[153.33784484899999,-27.891910553],"type":"Point"}
}