{
  "type": "Feature",
  "properties": {
    "addr:full":"133 Panton St Golden Square VIC 3555",
    "addr:housenumber":"133",
    "addr:postcode":"3555",
    "addr:street":"Panton St",
    "iso:country":"AU",
    "sg:address":"133 Panton St",
    "sg:city":"Golden Square",
    "sg:classifiers":[
        {
            "category":"Professional",
            "subcategory":"Art Services",
            "type":"Services"
        }
    ],
    "sg:phone":"+61 3 5447 4469",
    "sg:postcode":"3555",
    "sg:province":"VIC",
    "sg:tags":[
        "decorator",
        "painter"
    ],
    "wof:name":"Glenn Conder Painting",
    "wof:placetype":"venue"
},
  "geometry": {"coordinates":[144.25018310600001,-36.782409668],"type":"Point"}
}