{
  "type": "Feature",
  "properties": {
    "iso:country":"AU",
    "sg:address":"37 Annie St",
    "sg:city":"Coopers Plains",
    "sg:classifiers":[
        {
            "category":"Mining & Drilling",
            "type":"Manufacturing & Wholesale Goods"
        }
    ],
    "sg:phone":"+61 7 3274 7000",
    "sg:postcode":"4108",
    "sg:province":"QLD",
    "sg:tags":[
        "concrete",
        "breaking",
        "grinding",
        "sawing"
    ],
    "wof:name":"Oakridge Sawing & Drilling",
    "wof:placetype":"venue"
},
  "geometry": {"coordinates":[153.03253173799999,-27.5655288696],"type":"Point"}
}