{
  "type": "Feature",
  "properties": {
    "addr:full":"24 Badgery St Macquarie ACT 2614",
    "addr:housenumber":"24",
    "addr:postcode":"2614",
    "addr:street":"Badgery St",
    "iso:country":"AU",
    "sg:address":"24 Badgery St",
    "sg:city":"Macquarie",
    "sg:classifiers":[
        {
            "category":"Sports & Exercise",
            "subcategory":"Gym",
            "type":"Entertainment"
        }
    ],
    "sg:phone":"+61 2 6161 0800",
    "sg:postcode":"2614",
    "sg:province":"ACT",
    "sg:tags":[
        "personal",
        "trainer",
        "fitness"
    ],
    "wof:name":"Realign Fitness",
    "wof:placetype":"venue"
},
  "geometry": {"coordinates":[149.06509399399999,-35.2516136169],"type":"Point"}
}