{
  "type": "Feature",
  "properties": {
    "iso:country":"AU",
    "sg:address":"17 Runaway Drv",
    "sg:city":"Marcoola",
    "sg:classifiers":[
        {
            "category":"Building & Trades",
            "subcategory":"Construction",
            "type":"Services"
        }
    ],
    "sg:phone":"+61 7 5453 1300",
    "sg:postcode":"4564",
    "sg:province":"QLD",
    "sg:tags":[
        "fencing",
        "contractor"
    ],
    "wof:name":"ARC Fences",
    "wof:placetype":"venue"
},
  "geometry": {"coordinates":[153.084884644,-26.6090908051],"type":"Point"}
}