{
  "type": "Feature",
  "properties": {
    "addr:full":"80- 90 Henley St Coopers Plains QLD 4108",
    "addr:housenumber":"90",
    "addr:postcode":"4108",
    "addr:street":"Henley St",
    "iso:country":"AU",
    "sg:address":"80- 90 Henley St",
    "sg:city":"Coopers Plains",
    "sg:classifiers":[
        {
            "category":"Wholesale",
            "subcategory":"Medical Equipment & Supplies",
            "type":"Manufacturing & Wholesale Goods"
        }
    ],
    "sg:phone":"+61 7 3344 6169",
    "sg:postcode":"4108",
    "sg:province":"QLD",
    "sg:tags":[
        "plastering"
    ],
    "wof:name":"Flexi Traxx By ITEC",
    "wof:placetype":"venue"
},
  "geometry": {"coordinates":[153.03489685100001,-27.5688438416],"type":"Point"}
}