{
  "type": "Feature",
  "properties": {
    "addr:full":"93 Warrigal Rd Oakleigh VIC 3166",
    "addr:housenumber":"93",
    "addr:postcode":"3166",
    "addr:street":"Warrigal Rd",
    "iso:country":"AU",
    "sg:address":"93 Warrigal Rd",
    "sg:city":"Oakleigh",
    "sg:classifiers":[
        {
            "category":"Insurance",
            "subcategory":"Insurance Agent",
            "type":"Services"
        }
    ],
    "sg:phone":"+61 3 9568 4822",
    "sg:postcode":"3166",
    "sg:province":"VIC",
    "sg:tags":[
        "broker"
    ],
    "wof:name":"John Bernard & Associates Pty Ltd",
    "wof:placetype":"venue"
},
  "geometry": {"coordinates":[145.08671569800001,-37.9005584717],"type":"Point"}
}