{
  "type": "Feature",
  "properties": {
    "addr:full":"471 High St Penrith NSW 2750",
    "addr:housenumber":"471",
    "addr:postcode":"2750",
    "addr:street":"High St",
    "iso:country":"AU",
    "sg:address":"471 High St",
    "sg:city":"Penrith",
    "sg:classifiers":[
        {
            "category":"Health Services",
            "subcategory":"Doctor",
            "type":"Services"
        }
    ],
    "sg:phone":"+61 2 4732 4488",
    "sg:postcode":"2750",
    "sg:province":"NSW",
    "sg:tags":[
        "medical",
        "practitioner"
    ],
    "wof:name":"Oze-Med Medical Centre",
    "wof:placetype":"venue"
},
  "geometry": {"coordinates":[150.915557861,-33.8949623108],"type":"Point"}
}