{
  "type": "Feature",
  "properties": {
    "addr:full":"Suite 1, 3- 5 Grosvenor St Neutral Bay NSW 2089",
    "addr:housenumber":"3 5",
    "addr:postcode":"2089",
    "addr:street":"Grosvenor St",
    "iso:country":"AU",
    "sg:address":"Suite 1, 3- 5 Grosvenor St",
    "sg:city":"Neutral Bay",
    "sg:classifiers":[
        {
            "category":"Shopping",
            "subcategory":"Clothing, Apparel, & Fashions",
            "type":"Retail Goods"
        }
    ],
    "sg:phone":"+61 2 9904 4294",
    "sg:postcode":"2089",
    "sg:province":"NSW",
    "sg:tags":[
        "style",
        "clothing",
        "western",
        "accessory"
    ],
    "wof:name":"Cathouse Hair & Beauty",
    "wof:placetype":"venue"
},
  "geometry": {"coordinates":[151.22000122099999,-33.8296318054],"type":"Point"}
}