{
  "type": "Feature",
  "properties": {
    "iso:country":"AU",
    "sg:address":"145 Parsons Rd",
    "sg:city":"Forest Glen",
    "sg:classifiers":[
        {
            "category":"Home & Garden",
            "subcategory":"Building Materials",
            "type":"Retail Goods"
        }
    ],
    "sg:phone":"+61 418 258 384",
    "sg:postcode":"4556",
    "sg:province":"QLD",
    "sg:tags":[
        "lawn",
        "cutting",
        "maintenance"
    ],
    "wof:name":"Total property image",
    "wof:placetype":"venue"
},
  "geometry": {"coordinates":[153.01296997099999,-26.6871929169],"type":"Point"}
}