{
  "type": "Feature",
  "properties": {
    "iso:country":"AU",
    "sg:address":"231 Wardell Rd",
    "sg:city":"Dulwich Hill",
    "sg:classifiers":[
        {
            "category":"Food & Beverages",
            "subcategory":"Groceries & Convenience Stores",
            "type":"Retail Goods"
        }
    ],
    "sg:phone":"+61 2 9558 0585",
    "sg:postcode":"2203",
    "sg:province":"NSW",
    "wof:name":"Cretan Corner",
    "wof:placetype":"venue"
},
  "geometry": {"coordinates":[151.14175399999999,-33.910278],"type":"Point"}
}