{
  "type": "Feature",
  "properties": {
    "addr:full":"1080 D'Aguilar Hwy Wamuran QLD 4512",
    "addr:postcode":"1080;4512",
    "addr:street":"D'Aguilar Hwy",
    "iso:country":"AU",
    "sg:address":"1080 D'Aguilar Hwy",
    "sg:city":"Wamuran",
    "sg:classifiers":[
        {
            "category":"Government",
            "subcategory":"Post Office",
            "type":"Public Place"
        }
    ],
    "sg:phone":"+61 7 5496 6581",
    "sg:postcode":"4512",
    "sg:province":"QLD",
    "sg:tags":[
        "postal"
    ],
    "wof:name":"Australia Post",
    "wof:placetype":"venue"
},
  "geometry": {"coordinates":[152.86144999999999,-27.039864],"type":"Point"}
}