{
  "type": "Feature",
  "properties": {
    "addr:full":"49 Herbert St Allora QLD 4362",
    "addr:housenumber":"49",
    "addr:postcode":"4362",
    "addr:street":"Herbert St",
    "iso:country":"AU",
    "sg:address":"49 Herbert St",
    "sg:city":"Allora",
    "sg:classifiers":[
        {
            "category":"Banks & Credit Unions",
            "subcategory":"Bank",
            "type":"Services"
        }
    ],
    "sg:phone":"+61 7 4666 3466",
    "sg:postcode":"4362",
    "sg:province":"QLD",
    "wof:name":"National Australia Bank Ltd",
    "wof:placetype":"venue"
},
  "geometry": {"coordinates":[151.98304748499999,-28.0348186493],"type":"Point"}
}