{
  "type": "Feature",
  "properties": {
    "iso:country":"AU",
    "sg:address":"12 Christopher Ave",
    "sg:city":"Camden",
    "sg:classifiers":[
        {
            "category":"Professional",
            "subcategory":"Business Services",
            "type":"Services"
        }
    ],
    "sg:phone":"+61 2 4655 2706",
    "sg:postcode":"2570",
    "sg:province":"NSW",
    "sg:tags":[
        "drafting"
    ],
    "wof:name":"Lane Keith",
    "wof:placetype":"venue"
},
  "geometry": {"coordinates":[150.69635009800001,-34.0678520203],"type":"Point"}
}