{
  "type": "Feature",
  "properties": {
    "addr:full":"20- 24 Dennis St Campbellfield VIC 3061",
    "addr:housenumber":"24",
    "addr:postcode":"3061",
    "addr:street":"Dennis St",
    "iso:country":"AU",
    "sg:address":"20- 24 Dennis St",
    "sg:city":"Campbellfield",
    "sg:classifiers":[
        {
            "category":"Utilities",
            "subcategory":"Recycling",
            "type":"Services"
        }
    ],
    "sg:phone":"+61 1300 858 550",
    "sg:postcode":"3061",
    "sg:province":"VIC",
    "sg:website":"http://www.mri.com.au",
    "wof:name":"MRI (Aust) Pty Ltd",
    "wof:placetype":"venue"
},
  "geometry": {"coordinates":[144.94143676799999,-37.6447486877],"type":"Point"}
}