{
  "type": "Feature",
  "properties": {
    "iso:country":"AU",
    "sg:address":"131 North Rd",
    "sg:city":"Toowoomba",
    "sg:classifiers":[
        {
            "category":"Transit Center",
            "subcategory":"Freight",
            "type":"Transportation"
        }
    ],
    "sg:phone":"+61 7 4632 2655",
    "sg:postcode":"4352",
    "sg:province":"QLD",
    "sg:tags":[
        "agent",
        "shipping"
    ],
    "wof:name":"Chess Taylors Removals",
    "wof:placetype":"venue"
},
  "geometry": {"coordinates":[151.953293,-27.561449],"type":"Point"}
}