{
  "type": "Feature",
  "properties": {
    "addr:full":"7 Thomas St Milton NSW 2538",
    "addr:housenumber":"7",
    "addr:postcode":"2538",
    "addr:street":"Thomas St",
    "iso:country":"AU",
    "sg:address":"7 Thomas St",
    "sg:city":"Milton",
    "sg:classifiers":[
        {
            "category":"Education",
            "subcategory":"School",
            "type":"Public Place"
        }
    ],
    "sg:phone":"+61 2 4455 1504",
    "sg:postcode":"2538",
    "sg:province":"NSW",
    "sg:tags":[
        "state",
        "-",
        "nsw"
    ],
    "wof:name":"Milton Public School",
    "wof:placetype":"venue"
},
  "geometry": {"coordinates":[150.43510437,-35.3148841858],"type":"Point"}
}