{
  "type": "Feature",
  "properties": {
    "iso:country":"AU",
    "sg:address":"91 Wood St",
    "sg:city":"Gol Gol",
    "sg:classifiers":[
        {
            "category":"Professional",
            "subcategory":"Art Services",
            "type":"Services"
        }
    ],
    "sg:phone":"+61 3 5024 8556",
    "sg:postcode":"2738",
    "sg:province":"NSW",
    "sg:tags":[
        "decorator",
        "painter"
    ],
    "wof:name":"Sammut D P",
    "wof:placetype":"venue"
},
  "geometry": {"coordinates":[142.21965,-34.177025],"type":"Point"}
}