{
  "type": "Feature",
  "properties": {
    "addr:full":"PO Box 640 Mildura VIC 3502",
    "addr:postcode":"3502",
    "iso:country":"AU",
    "sg:address":"PO Box 640",
    "sg:city":"Mildura",
    "sg:classifiers":[
        {
            "category":"Retail",
            "subcategory":"Event Space",
            "type":"Services"
        }
    ],
    "sg:phone":"+61 3 5023 2200",
    "sg:postcode":"3502",
    "sg:province":"VIC",
    "sg:tags":[
        "venue",
        "reception",
        "wedding"
    ],
    "wof:name":"Paddlesteamers Melbourne & Rothbury",
    "wof:placetype":"venue"
},
  "geometry": {"coordinates":[142.165557861,-34.184551239],"type":"Point"}
}