{
  "type": "Feature",
  "properties": {
    "addr:full":"40 Aldershot Drv Keilor Downs VIC 3038",
    "addr:housenumber":"40",
    "addr:postcode":"3038",
    "addr:street":"Aldershot Drv",
    "iso:country":"AU",
    "sg:address":"40 Aldershot Drv",
    "sg:city":"Keilor Downs",
    "sg:classifiers":[
        {
            "category":"Professional",
            "subcategory":"Art Services",
            "type":"Services"
        }
    ],
    "sg:phone":"+61 3 9366 0254",
    "sg:postcode":"3038",
    "sg:province":"VIC",
    "sg:tags":[
        "picture",
        "frame",
        "framing"
    ],
    "wof:name":"Framable",
    "wof:placetype":"venue"
},
  "geometry": {"coordinates":[144.808075,-37.719086],"type":"Point"}
}