{
  "type": "Feature",
  "properties": {
    "addr:full":"39 Evans Rd West Kleinton QLD 4352",
    "addr:housenumber":"39",
    "addr:postcode":"4352",
    "addr:street":"Evans Rd West",
    "iso:country":"AU",
    "sg:address":"39 Evans Rd West",
    "sg:city":"Kleinton",
    "sg:classifiers":[
        {
            "category":"Building & Trades",
            "subcategory":"Construction",
            "type":"Services"
        }
    ],
    "sg:phone":"+61 7 4696 6383",
    "sg:postcode":"4352",
    "sg:province":"QLD",
    "sg:tags":[
        "renovation",
        "alterations",
        "extension",
        "contractor"
    ],
    "wof:name":"Len Metcalfe",
    "wof:placetype":"venue"
},
  "geometry": {"coordinates":[151.973724,-27.429098],"type":"Point"}
}