{
  "type": "Feature",
  "properties": {
    "iso:country":"AU",
    "sg:address":"41a David St",
    "sg:city":"O'Connor",
    "sg:classifiers":[
        {
            "category":"Health Services",
            "subcategory":"Health Practitioner",
            "type":"Services"
        }
    ],
    "sg:phone":"+61 2 6247 0912",
    "sg:postcode":"2602",
    "sg:province":"ACT",
    "sg:tags":[
        "physiotherapist"
    ],
    "wof:name":"Hogg Catherine",
    "wof:placetype":"venue"
},
  "geometry": {"coordinates":[149.12362670900001,-35.2642326355],"type":"Point"}
}