{
  "type": "Feature",
  "properties": {
    "addr:full":"PO Box 317 Kenthurst NSW 2156",
    "addr:postcode":"2156",
    "iso:country":"AU",
    "sg:address":"PO Box 317",
    "sg:city":"Kenthurst",
    "sg:classifiers":[
        {
            "category":"Building & Trades",
            "subcategory":"Landscaping Services",
            "type":"Services"
        }
    ],
    "sg:phone":"+61 2 9654 2847",
    "sg:postcode":"2156",
    "sg:province":"NSW",
    "sg:tags":[
        "designer",
        "landscape",
        "contractor"
    ],
    "wof:name":"On-Track Landscapes",
    "wof:placetype":"venue"
},
  "geometry": {"coordinates":[151.002975464,-33.6617774963],"type":"Point"}
}