{
  "type": "Feature",
  "properties": {
    "addr:full":"Unit 23a Frances Bay Shopping Village Frances Bay Stuart Park NT 0820",
    "addr:housenumber":"unit 23a",
    "addr:postcode":"0820",
    "addr:street":"Frances Bay",
    "iso:country":"AU",
    "sg:address":"Unit 23a Frances Bay Shopping Village Frances Bay",
    "sg:city":"Stuart Park",
    "sg:classifiers":[
        {
            "category":"Banks & Credit Unions",
            "subcategory":"Financial Services",
            "type":"Services"
        }
    ],
    "sg:phone":"+61 8 8941 7555",
    "sg:postcode":"0820",
    "sg:province":"NT",
    "sg:tags":[
        "planning"
    ],
    "wof:name":"Count Financial Limited",
    "wof:placetype":"venue"
},
  "geometry": {"coordinates":[130.84956359899999,-12.4480009079],"type":"Point"}
}