{
  "type": "Feature",
  "properties": {
    "addr:full":"201 Collins St Hobart TAS 7000",
    "addr:housenumber":"201",
    "addr:postcode":"7000",
    "addr:street":"Collins St",
    "iso:country":"AU",
    "sg:address":"201 Collins St",
    "sg:city":"Hobart",
    "sg:classifiers":[
        {
            "category":"Food & Beverages",
            "subcategory":"Liquor & Beverages",
            "type":"Retail Goods"
        }
    ],
    "sg:phone":"+61 3 6234 9999",
    "sg:postcode":"7000",
    "sg:province":"TAS",
    "sg:tags":[
        "merchant",
        "spirit",
        "wine"
    ],
    "wof:name":"David Johnstone & Associates Pty Ltd",
    "wof:placetype":"venue"
},
  "geometry": {"coordinates":[147.32258605999999,-42.8868751526],"type":"Point"}
}