{
  "type": "Feature",
  "properties": {
    "iso:country":"AU",
    "sg:address":"Dandenong Plaza, 22 - 55 McCrae St",
    "sg:city":"Dandenong",
    "sg:classifiers":[
        {
            "category":"Shopping",
            "subcategory":"Computers & Home Electronics",
            "type":"Retail Goods"
        }
    ],
    "sg:phone":"+61 3 9293 4600",
    "sg:postcode":"3175",
    "sg:province":"VIC",
    "sg:tags":[
        "hardware",
        "equipment"
    ],
    "wof:name":"Telstra Shop",
    "wof:placetype":"venue"
},
  "geometry": {"coordinates":[145.217086792,-37.9877967834],"type":"Point"}
}