{
  "type": "Feature",
  "properties": {
    "iso:country":"AU",
    "sg:address":"2/ 41 South Pine Rd",
    "sg:city":"Brendale",
    "sg:classifiers":[
        {
            "category":"Autos & Motor Vehicles",
            "subcategory":"Auto Supplies",
            "type":"Retail Goods"
        }
    ],
    "sg:phone":"+61 7 3205 7282",
    "sg:postcode":"4500",
    "sg:province":"QLD",
    "sg:tags":[
        "part",
        "cycles",
        "accessory"
    ],
    "wof:name":"SC Choppers",
    "wof:placetype":"venue"
},
  "geometry": {"coordinates":[152.98475647000001,-27.327009201],"type":"Point"}
}