{
  "type": "Feature",
  "properties": {
    "addr:full":"51 Brooke St Coogee NSW 2034",
    "addr:housenumber":"51",
    "addr:postcode":"2034",
    "addr:street":"Brooke St",
    "iso:country":"AU",
    "sg:address":"51 Brooke St",
    "sg:city":"Coogee",
    "sg:classifiers":[
        {
            "category":"Banks & Credit Unions",
            "subcategory":"Financial Services",
            "type":"Services"
        }
    ],
    "sg:phone":"+61 2 9665 3968",
    "sg:postcode":"2034",
    "sg:province":"NSW",
    "sg:tags":[
        "loan",
        "finance",
        "mortgage"
    ],
    "wof:name":"Percentage Finance",
    "wof:placetype":"venue"
},
  "geometry": {"coordinates":[151.25604248100001,-33.9139938354],"type":"Point"}
}