{
  "type": "Feature",
  "properties": {
    "addr:full":"98 Lockyer Ave Albany WA 6330",
    "addr:housenumber":"98",
    "addr:postcode":"6330",
    "addr:street":"Lockyer Ave",
    "iso:country":"AU",
    "sg:address":"98 Lockyer Ave",
    "sg:city":"Albany",
    "sg:classifiers":[
        {
            "category":"Shopping",
            "subcategory":"Stationery & Office Supplies",
            "type":"Retail Goods"
        }
    ],
    "sg:phone":"+61 8 9842 1190",
    "sg:postcode":"6330",
    "sg:province":"WA",
    "wof:name":"Office National",
    "wof:placetype":"venue"
},
  "geometry": {"coordinates":[117.88461303699999,-35.0167617798],"type":"Point"}
}