{
  "type": "Feature",
  "properties": {
    "addr:full":"32b Fawkner St Westmeadows VIC 3049",
    "addr:housenumber":"32b",
    "addr:postcode":"3049",
    "addr:street":"Fawkner St",
    "iso:country":"AU",
    "sg:address":"32b Fawkner St",
    "sg:city":"Westmeadows",
    "sg:classifiers":[
        {
            "category":"Health Services",
            "subcategory":"Doctor",
            "type":"Services"
        }
    ],
    "sg:phone":"+61 3 9338 2305",
    "sg:postcode":"3049",
    "sg:province":"VIC",
    "sg:tags":[
        "medical",
        "practitioner"
    ],
    "wof:name":"Dewani R Dr",
    "wof:placetype":"venue"
},
  "geometry": {"coordinates":[144.886505,-37.677197],"type":"Point"}
}