{
  "type": "Feature",
  "properties": {
    "iso:country":"AU",
    "sg:address":"Toodyay Bindi Bindi Rd",
    "sg:city":"Yerecoin",
    "sg:classifiers":[
        {
            "category":"Farming",
            "subcategory":"Farm",
            "type":"Manufacturing & Wholesale Goods"
        }
    ],
    "sg:phone":"+61 8 9654 6037",
    "sg:postcode":"6571",
    "sg:province":"WA",
    "sg:tags":[
        "farmer"
    ],
    "wof:name":"Duggan P F & K A",
    "wof:placetype":"venue"
},
  "geometry": {"coordinates":[116.438781738,-30.9270401001],"type":"Point"}
}