{
  "type": "Feature",
  "properties": {
    "addr:full":"42 Peachtree Rd Penrith NSW 2750",
    "addr:housenumber":"42",
    "addr:postcode":"2750",
    "addr:street":"Peachtree Rd",
    "iso:country":"AU",
    "sg:address":"42 Peachtree Rd",
    "sg:city":"Penrith",
    "sg:classifiers":[
        {
            "category":"Professional",
            "subcategory":"Art Services",
            "type":"Services"
        }
    ],
    "sg:phone":"+61 2 4722 2753",
    "sg:postcode":"2750",
    "sg:province":"NSW",
    "sg:tags":[
        "picture",
        "frame",
        "framing"
    ],
    "wof:name":"Bodies Pty Ltd",
    "wof:placetype":"venue"
},
  "geometry": {"coordinates":[150.97529602,-33.7894020081],"type":"Point"}
}