{
  "type": "Feature",
  "properties": {
    "iso:country":"AU",
    "sg:address":"1st Flr Homebase Cntr Cnr Gympie & Zillmere Rds",
    "sg:city":"Aspley",
    "sg:classifiers":[
        {
            "category":"Health Services",
            "subcategory":"Doctor",
            "type":"Services"
        }
    ],
    "sg:phone":"+61 7 3263 5844",
    "sg:postcode":"4034",
    "sg:province":"QLD",
    "sg:tags":[
        "medical",
        "practitioner"
    ],
    "wof:name":"Catt Peter B",
    "wof:placetype":"venue"
},
  "geometry": {"coordinates":[153.017288,-27.364653],"type":"Point"}
}