{
  "type": "Feature",
  "properties": {
    "addr:full":"319 Liverpool St Hobart TAS 7000",
    "addr:housenumber":"319",
    "addr:postcode":"7000",
    "addr:street":"Liverpool St",
    "iso:country":"AU",
    "sg:address":"319 Liverpool St",
    "sg:city":"Hobart",
    "sg:classifiers":[
        {
            "category":"Organizations",
            "subcategory":"Membership Organization",
            "type":"Services"
        }
    ],
    "sg:phone":"+61 1800 005 900",
    "sg:postcode":"7000",
    "sg:province":"TAS",
    "sg:tags":[
        "support",
        "health",
        "organisation"
    ],
    "wof:name":"Tasmanian Council on AIDS Hepatitis and Related Diseases",
    "wof:placetype":"venue"
},
  "geometry": {"coordinates":[147.320999145,-42.8867721558],"type":"Point"}
}