{
  "type": "Feature",
  "properties": {
    "addr:full":"11 Wynton Crt Eltham VIC 3095",
    "addr:housenumber":"11",
    "addr:postcode":"3095",
    "addr:street":"Wynton Crt",
    "iso:country":"AU",
    "sg:address":"11 Wynton Crt",
    "sg:city":"Eltham",
    "sg:classifiers":[
        {
            "category":"Social Services",
            "subcategory":"Retirement Home",
            "type":"Services"
        }
    ],
    "sg:phone":"+61 3 9439 8204",
    "sg:postcode":"3095",
    "sg:province":"VIC",
    "sg:tags":[
        "environmental",
        "consultant",
        "pollution"
    ],
    "wof:name":"Buckland Cross Pty Ltd",
    "wof:placetype":"venue"
},
  "geometry": {"coordinates":[145.16346740700001,-37.7089424133],"type":"Point"}
}