{
  "type": "Feature",
  "properties": {
    "iso:country":"AU",
    "sg:address":"Collins St",
    "sg:city":"Kensington",
    "sg:classifiers":[
        {
            "category":"Conference Center",
            "type":"Public Place"
        }
    ],
    "sg:phone":"+61 8 9474 0855",
    "sg:postcode":"6151",
    "sg:province":"WA",
    "sg:tags":[
        "venue",
        "convention"
    ],
    "wof:name":"Collins Street Centre",
    "wof:placetype":"venue"
},
  "geometry": {"coordinates":[115.882599,-31.98712],"type":"Point"}
}