{
  "type": "Feature",
  "properties": {
    "iso:country":"AU",
    "sg:address":"60 Garden Rd",
    "sg:city":"Clayton",
    "sg:classifiers":[
        {
            "category":"School Buses",
            "type":"Transportation"
        }
    ],
    "sg:phone":"+61 3 9574 2511",
    "sg:postcode":"3168",
    "sg:province":"VIC",
    "sg:tags":[
        "brick"
    ],
    "wof:name":"Toby's Recycled Bricks",
    "wof:placetype":"venue"
},
  "geometry": {"coordinates":[145.145996094,-37.9237709045],"type":"Point"}
}