{
  "type": "Feature",
  "properties": {
    "iso:country":"AU",
    "sg:address":"11 Harris Rd",
    "sg:city":"Malaga",
    "sg:classifiers":[
        {
            "category":"Building & Trades",
            "subcategory":"Equipment Rental",
            "type":"Services"
        }
    ],
    "sg:phone":"+61 8 9248 3255",
    "sg:postcode":"6090",
    "sg:province":"WA",
    "sg:tags":[
        "builder",
        "contractor"
    ],
    "wof:name":"De Jong Hoists (Aus)",
    "wof:placetype":"venue"
},
  "geometry": {"coordinates":[115.884262085,-31.8658866882],"type":"Point"}
}