{
  "type": "Feature",
  "properties": {
    "addr:full":"Shop 3 Burnside Village Shopping Centre Sydney St Glenside SA 5065",
    "addr:housenumber":"shop 3",
    "addr:postcode":"5065",
    "addr:street":"Burnside Village;Sydney St",
    "iso:country":"AU",
    "sg:address":"Shop 3 Burnside Village Shopping Centre Sydney St",
    "sg:city":"Glenside",
    "sg:classifiers":[
        {
            "category":"Personal",
            "subcategory":"Beauty Salon",
            "type":"Services"
        }
    ],
    "sg:phone":"+61 8 8338 6444",
    "sg:postcode":"5065",
    "sg:province":"SA",
    "sg:tags":[
        "hairdresser"
    ],
    "wof:name":"Price Attack",
    "wof:placetype":"venue"
},
  "geometry": {"coordinates":[138.642654419,-34.9418182373],"type":"Point"}
}