{
  "type": "Feature",
  "properties": {
    "iso:country":"AU",
    "sg:address":"216 Great Western Hwy",
    "sg:city":"Blackheath",
    "sg:classifiers":[
        {
            "category":"Autos & Motor Vehicles",
            "subcategory":"Fuel & Gas Station",
            "type":"Retail Goods"
        }
    ],
    "sg:phone":"+61 2 4787 8151",
    "sg:postcode":"2785",
    "sg:province":"NSW",
    "wof:name":"Blackheath Automotive Services",
    "wof:placetype":"venue"
},
  "geometry": {"coordinates":[150.28482055699999,-33.6361618042],"type":"Point"}
}