{
  "type": "Feature",
  "properties": {
    "addr:full":"3-5 Jumal Pl Smithfield NSW 2164",
    "addr:housenumber":"3-5",
    "addr:postcode":"2164",
    "addr:street":"Jumal Pl",
    "iso:country":"AU",
    "sg:address":"3-5 Jumal Pl",
    "sg:city":"Smithfield",
    "sg:classifiers":[
        {
            "category":"Building & Trades",
            "subcategory":"Construction",
            "type":"Services"
        }
    ],
    "sg:phone":"+61 2 9725 5110",
    "sg:postcode":"2164",
    "sg:province":"NSW",
    "sg:tags":[
        "joinery"
    ],
    "wof:name":"Carrera By Design",
    "wof:placetype":"venue"
},
  "geometry": {"coordinates":[150.95086669899999,-33.8404998779],"type":"Point"}
}