{
  "type": "Feature",
  "properties": {
    "addr:full":"PO Box 153 Kurri Kurri NSW 2327",
    "addr:postcode":"2327",
    "iso:country":"AU",
    "sg:address":"PO Box 153",
    "sg:city":"Kurri Kurri",
    "sg:classifiers":[
        {
            "category":"Personal",
            "type":"Services"
        }
    ],
    "sg:phone":"+61 2 4930 8771",
    "sg:postcode":"2327",
    "sg:province":"NSW",
    "sg:tags":[
        "wallpapering",
        "wallcovering"
    ],
    "wof:name":"Adnum Mark",
    "wof:placetype":"venue"
},
  "geometry": {"coordinates":[151.481124878,-32.8189888],"type":"Point"}
}