{
  "type": "Feature",
  "properties": {
    "iso:country":"AU",
    "sg:address":"Smart St",
    "sg:city":"Mandurah",
    "sg:classifiers":[
        {
            "category":"Food & Beverages",
            "subcategory":"Groceries & Convenience Stores",
            "type":"Retail Goods"
        }
    ],
    "sg:phone":"+61 8 9535 1522",
    "sg:postcode":"6210",
    "sg:province":"WA",
    "wof:name":"Woolworths (WA) Pty Ltd",
    "wof:placetype":"venue"
},
  "geometry": {"coordinates":[115.720161,-32.53334],"type":"Point"}
}