{
  "type": "Feature",
  "properties": {
    "addr:full":"35 Princess St Bundaberg QLD 4670",
    "addr:housenumber":"35",
    "addr:postcode":"4670",
    "addr:street":"Princess St",
    "iso:country":"AU",
    "sg:address":"35 Princess St",
    "sg:city":"Bundaberg",
    "sg:classifiers":[
        {
            "category":"Home & Garden",
            "subcategory":"Carpets & Floor Coverings",
            "type":"Retail Goods"
        }
    ],
    "sg:phone":"+61 7 4152 2416",
    "sg:postcode":"4670",
    "sg:province":"QLD",
    "wof:name":"Concept Tiles and Surfaces",
    "wof:placetype":"venue"
},
  "geometry": {"coordinates":[152.369384766,-24.8584098816],"type":"Point"}
}