{
  "type": "Feature",
  "properties": {
    "iso:country":"AU",
    "sg:address":"Level 1/ Suite 10 902 Mount Alexander Rd",
    "sg:city":"Essendon",
    "sg:classifiers":[
        {
            "category":"Retail",
            "subcategory":"Auto Repair",
            "type":"Services"
        }
    ],
    "sg:phone":"+61 3 9372 7155",
    "sg:postcode":"3040",
    "sg:province":"VIC",
    "sg:tags":[
        "beater",
        "painter",
        "panel"
    ],
    "wof:name":"Suresafe License Auto Body Repairers",
    "wof:placetype":"venue"
},
  "geometry": {"coordinates":[144.91851806599999,-37.7558860779],"type":"Point"}
}