{
  "type": "Feature",
  "properties": {
    "iso:country":"AU",
    "sg:address":"5 Luckona Crt",
    "sg:city":"Gympie",
    "sg:classifiers":[
        {
            "category":"Professional",
            "subcategory":"Art Services",
            "type":"Services"
        }
    ],
    "sg:phone":"+61 7 5482 7945",
    "sg:postcode":"4570",
    "sg:province":"QLD",
    "sg:tags":[
        "decorator",
        "painter"
    ],
    "wof:name":"Kiwi Oz Co",
    "wof:placetype":"venue"
},
  "geometry": {"coordinates":[152.64997863799999,-26.2126255035],"type":"Point"}
}