{
  "type": "Feature",
  "properties": {
    "iso:country":"AU",
    "sg:address":"14 Argosy St",
    "sg:city":"Seaford",
    "sg:classifiers":[
        {
            "category":"Food & Beverages",
            "subcategory":"Specialty",
            "type":"Retail Goods"
        }
    ],
    "sg:phone":"+61 403 248 188",
    "sg:postcode":"5169",
    "sg:province":"SA",
    "sg:tags":[
        "product",
        "health"
    ],
    "wof:name":"GNLD Distributors S.A.",
    "wof:placetype":"venue"
},
  "geometry": {"coordinates":[138.47120666500001,-35.188621521],"type":"Point"}
}