{
  "type": "Feature",
  "properties": {
    "addr:full":"14 Middle St Labrador QLD 4215",
    "addr:housenumber":"14",
    "addr:postcode":"4215",
    "addr:street":"Middle St",
    "iso:country":"AU",
    "sg:address":"14 Middle St",
    "sg:city":"Labrador",
    "sg:classifiers":[
        {
            "category":"Personal",
            "subcategory":"Massage",
            "type":"Services"
        }
    ],
    "sg:phone":"+61 7 5537 1634",
    "sg:postcode":"4215",
    "sg:province":"QLD",
    "sg:tags":[
        "therapy"
    ],
    "wof:name":"Graham Schmocker",
    "wof:placetype":"venue"
},
  "geometry": {"coordinates":[153.404464722,-27.940158844],"type":"Point"}
}