{
  "type": "Feature",
  "properties": {
    "addr:full":"30 Mackenzie St Blackwater QLD 4717",
    "addr:housenumber":"30",
    "addr:postcode":"4717",
    "addr:street":"Mackenzie St",
    "iso:country":"AU",
    "sg:address":"30 Mackenzie St",
    "sg:city":"Blackwater",
    "sg:classifiers":[
        {
            "category":"Retail",
            "subcategory":"Repair Shop",
            "type":"Services"
        }
    ],
    "sg:phone":"+61 7 4982 7838",
    "sg:postcode":"4717",
    "sg:province":"QLD",
    "sg:tags":[
        "upholsterer"
    ],
    "wof:name":"Blackwater Upholstery",
    "wof:placetype":"venue"
},
  "geometry": {"coordinates":[148.878479,-23.57777],"type":"Point"}
}