{
  "type": "Feature",
  "properties": {
    "addr:full":"88 Vincent St Cessnock NSW 2325",
    "addr:housenumber":"88",
    "addr:postcode":"2325",
    "addr:street":"Vincent St",
    "iso:country":"AU",
    "sg:address":"88 Vincent St",
    "sg:city":"Cessnock",
    "sg:classifiers":[
        {
            "category":"Shopping",
            "subcategory":"Clothing, Apparel, & Fashions",
            "type":"Retail Goods"
        }
    ],
    "sg:phone":"+61 2 4990 1310",
    "sg:postcode":"2325",
    "sg:province":"NSW",
    "sg:tags":[
        "menswear"
    ],
    "wof:name":"Beveridge's Menswear & Formal Hire",
    "wof:placetype":"venue"
},
  "geometry": {"coordinates":[151.35630798299999,-32.8357505798],"type":"Point"}
}