{
  "type": "Feature",
  "properties": {
    "addr:full":"PO Box 75 Towong NSW 3707",
    "addr:postcode":"3707",
    "iso:country":"AU",
    "sg:address":"PO Box 75",
    "sg:city":"Towong",
    "sg:classifiers":[
        {
            "category":"Manufacturing",
            "subcategory":"Metals",
            "type":"Manufacturing & Wholesale Goods"
        }
    ],
    "sg:phone":"+61 3 5754 5280",
    "sg:postcode":"3707",
    "sg:province":"NSW",
    "sg:tags":[
        "steel",
        "fabricator",
        "mfrs"
    ],
    "wof:name":"Gentile Steel Fabrications",
    "wof:placetype":"venue"
},
  "geometry": {"coordinates":[147.996017456,-36.124080658],"type":"Point"}
}