{
  "type": "Feature",
  "properties": {
    "addr:full":"20 Mt Pleasant Drv Mt Waverley VIC 3149",
    "addr:housenumber":"20",
    "addr:postcode":"3149",
    "addr:street":"Mt Pleasant Drv Mt",
    "iso:country":"AU",
    "sg:address":"20 Mt Pleasant Drv",
    "sg:city":"Mt Waverley",
    "sg:classifiers":[
        {
            "category":"Shopping",
            "subcategory":"Musical Instruments",
            "type":"Retail Goods"
        }
    ],
    "sg:phone":"+61 407 484 538",
    "sg:postcode":"3149",
    "sg:province":"VIC",
    "sg:tags":[
        "musician",
        "agent"
    ],
    "wof:name":"Schneider Craig",
    "wof:placetype":"venue"
},
  "geometry": {"coordinates":[145.132720947,-37.8838920593],"type":"Point"}
}