{
  "type": "Feature",
  "properties": {
    "iso:country":"AU",
    "sg:address":"421 Illawarra Rd",
    "sg:city":"Marrickville",
    "sg:classifiers":[
        {
            "category":"Utilities",
            "subcategory":"Water",
            "type":"Services"
        }
    ],
    "sg:phone":"+61 2 9559 4811",
    "sg:postcode":"2204",
    "sg:province":"NSW",
    "sg:tags":[
        "hot",
        "system"
    ],
    "wof:name":"Hocking Hot Water Heater Co Pty Ltd",
    "wof:placetype":"venue"
},
  "geometry": {"coordinates":[151.15089399999999,-33.915668],"type":"Point"}
}