{
  "type": "Feature",
  "properties": {
    "addr:full":"105 Graves St Newton SA 5074",
    "addr:housenumber":"105",
    "addr:postcode":"5074",
    "addr:street":"Graves St",
    "iso:country":"AU",
    "sg:address":"105 Graves St",
    "sg:city":"Newton",
    "sg:classifiers":[
        {
            "category":"Retail",
            "subcategory":"Storage",
            "type":"Services"
        }
    ],
    "sg:phone":"+61 1800 888 229",
    "sg:postcode":"5074",
    "sg:province":"SA",
    "sg:tags":[
        "removal",
        "furniture"
    ],
    "wof:name":"A.Adelaide North East Removals Pty Ltd",
    "wof:placetype":"venue"
},
  "geometry": {"coordinates":[138.67864990199999,-34.8811912537],"type":"Point"}
}