{
  "type": "Feature",
  "properties": {
    "addr:full":"Henty Hwy Condah VIC 3303",
    "addr:postcode":"3303",
    "addr:street":"Henty Hwy",
    "iso:country":"AU",
    "sg:address":"Henty Hwy",
    "sg:city":"Condah",
    "sg:classifiers":[
        {
            "category":"Travel",
            "subcategory":"Hotels & Motels",
            "type":"Entertainment"
        }
    ],
    "sg:phone":"+61 3 5578 2220",
    "sg:postcode":"3303",
    "sg:province":"VIC",
    "sg:tags":[
        "accommodation"
    ],
    "wof:name":"Condah Green Hills Hotel",
    "wof:placetype":"venue"
},
  "geometry": {"coordinates":[141.7474823,-37.9538841248],"type":"Point"}
}