{
  "type": "Feature",
  "properties": {
    "iso:country":"AU",
    "sg:address":"250 Sydney Rd",
    "sg:city":"Coburg",
    "sg:classifiers":[
        {
            "category":"Professional",
            "subcategory":"Business Services",
            "type":"Services"
        }
    ],
    "sg:phone":"+61 3 9383 1711",
    "sg:postcode":"3058",
    "sg:province":"VIC",
    "sg:tags":[
        "drafting"
    ],
    "wof:name":"Professional Planning Pty Ltd",
    "wof:placetype":"venue"
},
  "geometry": {"coordinates":[144.96548461899999,-37.7485046387],"type":"Point"}
}