{
  "type": "Feature",
  "properties": {
    "iso:country":"AU",
    "sg:address":"Darlington Drv",
    "sg:city":"Banora Point",
    "sg:classifiers":[
        {
            "category":"Education",
            "subcategory":"Dance Studio",
            "type":"Public Place"
        }
    ],
    "sg:phone":"+61 410 441 020",
    "sg:postcode":"2486",
    "sg:province":"NSW",
    "sg:tags":[
        "venue",
        "tuition"
    ],
    "wof:name":"Dancetime Rock & Roll",
    "wof:placetype":"venue"
},
  "geometry": {"coordinates":[153.53265380900001,-28.2158298492],"type":"Point"}
}