{
  "type": "Feature",
  "properties": {
    "addr:full":"Cnr Hoskins & Polaris Sts Temora NSW 2666",
    "addr:postcode":"2666",
    "addr:street":"Cnr",
    "iso:country":"AU",
    "sg:address":"Cnr Hoskins & Polaris Sts",
    "sg:city":"Temora",
    "sg:classifiers":[
        {
            "category":"Autos & Motor Vehicles",
            "subcategory":"Fuel & Gas Station",
            "type":"Retail Goods"
        }
    ],
    "sg:phone":"+61 2 6978 0738",
    "sg:postcode":"2666",
    "sg:province":"NSW",
    "wof:name":"Woolworths Plus Petrol Service Station",
    "wof:placetype":"venue"
},
  "geometry": {"coordinates":[147.532104492,-34.4428939819],"type":"Point"}
}