{
  "type": "Feature",
  "properties": {
    "addr:full":"Stuart St Mackay QLD 4740",
    "addr:postcode":"4740",
    "addr:street":"Stuart St",
    "iso:country":"AU",
    "sg:address":"Stuart St",
    "sg:city":"Mackay",
    "sg:classifiers":[
        {
            "category":"School Buses",
            "type":"Transportation"
        }
    ],
    "sg:phone":"+61 430 537 143",
    "sg:postcode":"4740",
    "sg:province":"QLD",
    "sg:tags":[
        "nanny"
    ],
    "wof:name":"Australian Childcare Services",
    "wof:placetype":"venue"
},
  "geometry": {"coordinates":[149.15347299999999,-21.114336],"type":"Point"}
}