{
  "type": "Feature",
  "properties": {
    "iso:country":"AU",
    "sg:address":"20 Gilandra St",
    "sg:city":"Rochedale South",
    "sg:classifiers":[
        {
            "category":"Professional",
            "subcategory":"Engineering",
            "type":"Services"
        }
    ],
    "sg:phone":"+61 7 3341 1230",
    "sg:postcode":"4123",
    "sg:province":"QLD",
    "sg:tags":[
        "installation",
        "maintenance",
        "engineer"
    ],
    "wof:name":"KM Group Pty Ltd",
    "wof:placetype":"venue"
},
  "geometry": {"coordinates":[153.14041137699999,-27.592218399],"type":"Point"}
}