{
  "type": "Feature",
  "properties": {
    "iso:country":"AU",
    "sg:address":"4/ 2 View St",
    "sg:city":"Dianella",
    "sg:classifiers":[
        {
            "category":"Home & Garden",
            "subcategory":"Carpets & Floor Coverings",
            "type":"Retail Goods"
        }
    ],
    "sg:phone":"+61 419 983 264",
    "sg:postcode":"6059",
    "sg:province":"WA",
    "sg:tags":[
        "tile",
        "wall",
        "layer"
    ],
    "wof:name":"Exhibit Tiling",
    "wof:placetype":"venue"
},
  "geometry": {"coordinates":[115.858947754,-31.9315757751],"type":"Point"}
}