{
  "type": "Feature",
  "properties": {
    "addr:full":"2- 6 Crawford St Jindabyne NSW 2627",
    "addr:housenumber":"6",
    "addr:postcode":"2627",
    "addr:street":"Crawford St",
    "iso:country":"AU",
    "sg:address":"2- 6 Crawford St",
    "sg:city":"Jindabyne",
    "sg:classifiers":[
        {
            "category":"Home & Garden",
            "subcategory":"Garden Supply",
            "type":"Retail Goods"
        }
    ],
    "sg:phone":"+61 2 6456 2387",
    "sg:postcode":"2627",
    "sg:province":"NSW",
    "sg:tags":[
        "landscape"
    ],
    "wof:name":"Jindabyne Sand & Gravel",
    "wof:placetype":"venue"
},
  "geometry": {"coordinates":[148.60235595699999,-36.4375305176],"type":"Point"}
}