{
  "type": "Feature",
  "properties": {
    "addr:full":"110 Finch St Malvern East VIC 3145",
    "addr:housenumber":"110",
    "addr:postcode":"3145",
    "addr:street":"Finch St",
    "iso:country":"AU",
    "sg:address":"110 Finch St",
    "sg:city":"Malvern East",
    "sg:classifiers":[
        {
            "category":"Health Services",
            "subcategory":"Health Practitioner",
            "type":"Services"
        }
    ],
    "sg:phone":"+61 3 9576 0061",
    "sg:postcode":"3145",
    "sg:province":"VIC",
    "sg:tags":[
        "psychologist"
    ],
    "wof:name":"Cohen David Dr",
    "wof:placetype":"venue"
},
  "geometry": {"coordinates":[145.04444885300001,-37.8663406372],"type":"Point"}
}