{
  "type": "Feature",
  "properties": {
    "iso:country":"AU",
    "sg:address":"Level 1 / 160 St",
    "sg:city":"Georges Tce Perth",
    "sg:classifiers":[
        {
            "category":"Health Services",
            "subcategory":"Doctor",
            "type":"Services"
        }
    ],
    "sg:phone":"+61 8 9420 9125",
    "sg:postcode":"6000",
    "sg:province":"WA",
    "sg:tags":[
        "medical",
        "practitioner"
    ],
    "wof:name":"Gill Jag Dr",
    "wof:placetype":"venue"
},
  "geometry": {"coordinates":[115.855018616,-31.954076767],"type":"Point"}
}