{
  "type": "Feature",
  "properties": {
    "addr:full":"22 Hill St Camden NSW 2570",
    "addr:housenumber":"22",
    "addr:postcode":"2570",
    "addr:street":"Hill St",
    "iso:country":"AU",
    "sg:address":"22 Hill St",
    "sg:city":"Camden",
    "sg:classifiers":[
        {
            "category":"Retail",
            "subcategory":"Event Space",
            "type":"Services"
        }
    ],
    "sg:phone":"+61 2 4655 1451",
    "sg:postcode":"2570",
    "sg:province":"NSW",
    "sg:tags":[
        "venue",
        "reception",
        "wedding"
    ],
    "wof:name":"La Bella Vita",
    "wof:placetype":"venue"
},
  "geometry": {"coordinates":[150.697723389,-34.0549621582],"type":"Point"}
}