{
  "type": "Feature",
  "properties": {
    "addr:full":"393 Swanston St Melbourne VIC 3000",
    "addr:housenumber":"393",
    "addr:postcode":"3000",
    "addr:street":"Swanston St",
    "iso:country":"AU",
    "sg:address":"393 Swanston St",
    "sg:city":"Melbourne",
    "sg:classifiers":[
        {
            "category":"Health Services",
            "subcategory":"Dentist",
            "type":"Services"
        }
    ],
    "sg:phone":"+61 3 9671 4746",
    "sg:postcode":"3000",
    "sg:province":"VIC",
    "wof:name":"Metro Dental",
    "wof:placetype":"venue"
},
  "geometry": {"coordinates":[144.9634552,-37.8091773987],"type":"Point"}
}