{
  "type": "Feature",
  "properties": {
    "addr:full":"Cnr Oxford & Marian Sts Guildford NSW 2161",
    "addr:postcode":"2161",
    "iso:country":"AU",
    "sg:address":"Cnr Oxford & Marian Sts",
    "sg:city":"Guildford",
    "sg:classifiers":[
        {
            "category":"Shopping",
            "type":"Retail Goods"
        }
    ],
    "sg:phone":"+61 2 9795 1861",
    "sg:postcode":"2161",
    "sg:province":"NSW",
    "sg:tags":[
        "clearance",
        "factory",
        "outlet"
    ],
    "wof:name":"Leading Labels Apparel Factory Outlet",
    "wof:placetype":"venue"
},
  "geometry": {"coordinates":[150.99241638199999,-33.848236084],"type":"Point"}
}