{
  "type": "Feature",
  "properties": {
    "addr:full":"450 Victoria Ave Chatswood NSW 2067",
    "addr:housenumber":"450",
    "addr:postcode":"2067",
    "addr:street":"Victoria Ave",
    "iso:country":"AU",
    "sg:address":"450 Victoria Ave",
    "sg:city":"Chatswood",
    "sg:classifiers":[
        {
            "category":"Personal",
            "subcategory":"Beauty Salon",
            "type":"Services"
        }
    ],
    "sg:phone":"+61 411 054 241",
    "sg:postcode":"2067",
    "sg:province":"NSW",
    "sg:tags":[
        "supply",
        "artist",
        "make-up"
    ],
    "wof:name":"Buffett J",
    "wof:placetype":"venue"
},
  "geometry": {"coordinates":[151.179977417,-33.7973213196],"type":"Point"}
}