{
  "type": "Feature",
  "properties": {
    "iso:country":"AU",
    "sg:address":"Cnr Wilson Rd & Lord Howe Drv",
    "sg:city":"Hinchinbrook",
    "sg:classifiers":[
        {
            "category":"Real Estate",
            "subcategory":"Real Estate Agent",
            "type":"Services"
        }
    ],
    "sg:phone":"+61 1300 652 333",
    "sg:postcode":"2168",
    "sg:province":"NSW",
    "wof:name":"Land Sales & Management Pty Ltd",
    "wof:placetype":"venue"
},
  "geometry": {"coordinates":[150.86488342300001,-33.9112243652],"type":"Point"}
}