{
  "type": "Feature",
  "properties": {
    "iso:country":"AU",
    "sg:address":"3 Surrey Crt",
    "sg:city":"Deception Bay",
    "sg:classifiers":[
        {
            "category":"Home & Garden",
            "subcategory":"Building Materials",
            "type":"Retail Goods"
        }
    ],
    "sg:phone":"+61 7 3203 2569",
    "sg:postcode":"4508",
    "sg:province":"QLD",
    "sg:tags":[
        "shutter",
        "roller",
        "grille"
    ],
    "wof:name":"Central Coast Doors",
    "wof:placetype":"venue"
},
  "geometry": {"coordinates":[153.019607544,-27.1724452972],"type":"Point"}
}