{
  "type": "Feature",
  "properties": {
    "iso:country":"AU",
    "sg:address":"1215 Nepean Hwy",
    "sg:city":"Highett",
    "sg:classifiers":[
        {
            "category":"Health Services",
            "subcategory":"Dentist",
            "type":"Services"
        }
    ],
    "sg:phone":"+61 3 9583 8988",
    "sg:postcode":"3190",
    "sg:province":"VIC",
    "wof:name":"Cottrell Jenifer Dr",
    "wof:placetype":"venue"
},
  "geometry": {"coordinates":[145.051239014,-37.9556732178],"type":"Point"}
}