{
  "type": "Feature",
  "properties": {
    "iso:country":"AU",
    "sg:address":"Cnr Noranda Avenue & Wellington Rd",
    "sg:city":"Morley",
    "sg:classifiers":[
        {
            "category":"Food & Beverages",
            "subcategory":"Liquor & Beverages",
            "type":"Retail Goods"
        }
    ],
    "sg:phone":"+61 8 9276 1911",
    "sg:postcode":"6062",
    "sg:province":"WA",
    "sg:tags":[
        "store"
    ],
    "wof:name":"The BEER Store Morley",
    "wof:placetype":"venue"
},
  "geometry": {"coordinates":[115.888198852,-31.879491806],"type":"Point"}
}