{
  "type": "Feature",
  "properties": {
    "addr:full":"3/ 15 Hill St Hawthorn VIC 3122",
    "addr:housenumber":"/ 15",
    "addr:postcode":"3122",
    "addr:street":"Hill St",
    "iso:country":"AU",
    "sg:address":"3/ 15 Hill St",
    "sg:city":"Hawthorn",
    "sg:classifiers":[
        {
            "category":"Shopping",
            "subcategory":"Musical Instruments",
            "type":"Retail Goods"
        }
    ],
    "sg:phone":"+61 3 9818 1296",
    "sg:postcode":"3122",
    "sg:province":"VIC",
    "sg:tags":[
        "musician",
        "agent"
    ],
    "wof:name":"Faye Dumont Singers",
    "wof:placetype":"venue"
},
  "geometry": {"coordinates":[145.01976013199999,-37.8180389404],"type":"Point"}
}