{
  "type": "Feature",
  "properties": {
    "addr:full":"Industrial Ave Hoppers Crossing VIC 3029",
    "addr:postcode":"3029",
    "addr:street":"Industrial Ave",
    "iso:country":"AU",
    "sg:address":"Industrial Ave",
    "sg:city":"Hoppers Crossing",
    "sg:classifiers":[
        {
            "category":"Building & Trades",
            "subcategory":"Plumbing",
            "type":"Services"
        }
    ],
    "sg:phone":"+61 3 9369 1766",
    "sg:postcode":"3029",
    "sg:province":"VIC",
    "sg:tags":[
        "plumber",
        "gasfitters"
    ],
    "wof:name":"Spicer G & P Plumbing Pty Ltd",
    "wof:placetype":"venue"
},
  "geometry": {"coordinates":[144.72473099999999,-37.869438],"type":"Point"}
}