{
  "type": "Feature",
  "properties": {
    "addr:full":"TD Building Park St Hawthorn VIC 3122",
    "addr:postcode":"3122",
    "addr:street":"St",
    "iso:country":"AU",
    "sg:address":"TD Building Park St",
    "sg:city":"Hawthorn",
    "sg:classifiers":[
        {
            "category":"Conference Center",
            "type":"Public Place"
        }
    ],
    "sg:phone":"+61 3 9214 8117",
    "sg:postcode":"3122",
    "sg:province":"VIC",
    "sg:tags":[
        "venue",
        "convention"
    ],
    "wof:name":"Swinburne Conference Centres",
    "wof:placetype":"venue"
},
  "geometry": {"coordinates":[145.03805542000001,-37.8199653625],"type":"Point"}
}