{
  "type": "Feature",
  "properties": {
    "iso:country":"AU",
    "sg:address":"9 Glomar Crt",
    "sg:city":"Dandenong",
    "sg:classifiers":[
        {
            "category":"Retail",
            "subcategory":"Car Wash",
            "type":"Services"
        }
    ],
    "sg:phone":"+61 3 9793 7023",
    "sg:postcode":"3175",
    "sg:province":"VIC",
    "sg:tags":[
        "truck",
        "cleaning"
    ],
    "wof:name":"Pryme Polishing",
    "wof:placetype":"venue"
},
  "geometry": {"coordinates":[145.216674805,-38.0048675537],"type":"Point"}
}