{
  "type": "Feature",
  "properties": {
    "addr:full":"108 Mooringe Ave North Plympton SA 5037",
    "addr:housenumber":"108",
    "addr:postcode":"5037",
    "addr:street":"Mooringe Ave North",
    "iso:country":"AU",
    "sg:address":"108 Mooringe Ave",
    "sg:city":"North Plympton",
    "sg:classifiers":[
        {
            "category":"Professional",
            "subcategory":"Printing & Photocopies",
            "type":"Services"
        }
    ],
    "sg:phone":"+61 8 8350 0099",
    "sg:postcode":"5037",
    "sg:province":"SA",
    "sg:tags":[
        "screen",
        "printer"
    ],
    "wof:name":"Kingfisher Glass Print",
    "wof:placetype":"venue"
},
  "geometry": {"coordinates":[138.541473389,-34.9602203369],"type":"Point"}
}