{
  "type": "Feature",
  "properties": {
    "iso:country":"AU",
    "sg:address":"Bullsbrook District High School Chittering Rd",
    "sg:city":"Bullsbrook",
    "sg:classifiers":[
        {
            "category":"Education",
            "subcategory":"School",
            "type":"Public Place"
        }
    ],
    "sg:phone":"+61 8 9571 1220",
    "sg:postcode":"6084",
    "sg:province":"WA",
    "sg:tags":[
        "state",
        "except",
        "nsw"
    ],
    "wof:name":"Schools Government (Public)",
    "wof:placetype":"venue"
},
  "geometry": {"coordinates":[116.031517029,-31.6701374054],"type":"Point"}
}