{
  "type": "Feature",
  "properties": {
    "iso:country":"AU",
    "sg:address":"58 Vincent St",
    "sg:city":"Cessnock",
    "sg:classifiers":[
        {
            "category":"Personal",
            "subcategory":"Barber",
            "type":"Services"
        }
    ],
    "sg:phone":"+61 2 4991 5610",
    "sg:postcode":"2325",
    "sg:province":"NSW",
    "wof:name":"Antonios Barber Shop",
    "wof:placetype":"venue"
},
  "geometry": {"coordinates":[151.35653686500001,-32.8345184326],"type":"Point"}
}