{
  "type": "Feature",
  "properties": {
    "iso:country":"AU",
    "sg:address":"Unit 6, 13 Belmont Ave",
    "sg:city":"Wollstonecraft",
    "sg:classifiers":[
        {
            "category":"Shopping",
            "subcategory":"Gifts & Souvenirs",
            "type":"Retail Goods"
        }
    ],
    "sg:phone":"+61 2 9439 0515",
    "sg:postcode":"2065",
    "sg:province":"NSW",
    "sg:tags":[
        "shop",
        "supply"
    ],
    "wof:name":"Ali Bentley Enterprises",
    "wof:placetype":"venue"
},
  "geometry": {"coordinates":[151.195480347,-33.8327636719],"type":"Point"}
}