{
  "type": "Feature",
  "properties": {
    "addr:full":"Coachwood Drv Alfords Point NSW 2234",
    "addr:postcode":"2234",
    "addr:street":"Coachwood Drv",
    "iso:country":"AU",
    "sg:address":"Coachwood Drv",
    "sg:city":"Alfords Point",
    "sg:classifiers":[
        {
            "category":"Fast Food",
            "type":"Food & Drink"
        }
    ],
    "sg:phone":"+61 2 9543 8588",
    "sg:postcode":"2234",
    "sg:province":"NSW",
    "sg:tags":[
        "away",
        "take"
    ],
    "wof:name":"Alfords Point Take-Away Food",
    "wof:placetype":"venue"
},
  "geometry": {"coordinates":[151.02456665,-33.9936141968],"type":"Point"}
}