{
  "type": "Feature",
  "properties": {
    "iso:country":"AU",
    "sg:address":"5 King William Rd",
    "sg:city":"Unley",
    "sg:classifiers":[
        {
            "category":"Building & Trades",
            "subcategory":"Landscaping Services",
            "type":"Services"
        }
    ],
    "sg:phone":"+61 8 8373 1515",
    "sg:postcode":"5061",
    "sg:province":"SA",
    "sg:tags":[
        "grazier"
    ],
    "wof:name":"Mutooroo Pastoral Co Pty Ltd",
    "wof:placetype":"venue"
},
  "geometry": {"coordinates":[138.60043335,-34.9421234131],"type":"Point"}
}