{
  "type": "Feature",
  "properties": {
    "addr:full":"286 Great Eastern Hwy Redcliffe WA 6104",
    "addr:housenumber":"286",
    "addr:postcode":"6104",
    "addr:street":"Great Eastern Hwy",
    "iso:country":"AU",
    "sg:address":"286 Great Eastern Hwy",
    "sg:city":"Redcliffe",
    "sg:classifiers":[
        {
            "category":"Autos & Motor Vehicles",
            "subcategory":"Auto Supplies",
            "type":"Retail Goods"
        }
    ],
    "sg:phone":"+61 8 9366 3666",
    "sg:postcode":"6104",
    "sg:province":"WA",
    "sg:tags":[
        "equipment",
        "part",
        "truck"
    ],
    "wof:name":"Veale Autoparts",
    "wof:placetype":"venue"
},
  "geometry": {"coordinates":[115.945671081,-31.9292697906],"type":"Point"}
}