{
  "type": "Feature",
  "properties": {
    "addr:full":"77 Otho St Inverell NSW 2360",
    "addr:housenumber":"77",
    "addr:postcode":"2360",
    "addr:street":"Otho St",
    "iso:country":"AU",
    "sg:address":"77 Otho St",
    "sg:city":"Inverell",
    "sg:classifiers":[
        {
            "category":"Professional",
            "subcategory":"Accounting & Tax Preparation",
            "type":"Services"
        }
    ],
    "sg:phone":"+61 2 6722 5082",
    "sg:postcode":"2360",
    "sg:province":"NSW",
    "sg:tags":[
        "accountant",
        "auditor"
    ],
    "wof:name":"Hunt, Lloyd S",
    "wof:placetype":"venue"
},
  "geometry": {"coordinates":[151.11541748100001,-29.7774887085],"type":"Point"}
}