{
  "type": "Feature",
  "properties": {
    "addr:full":"1 High St Berwick VIC 3806",
    "addr:housenumber":"1",
    "addr:postcode":"3806",
    "addr:street":"High St",
    "iso:country":"AU",
    "sg:address":"1 High St",
    "sg:city":"Berwick",
    "sg:classifiers":[
        {
            "category":"Food & Beverages",
            "subcategory":"Liquor & Beverages",
            "type":"Retail Goods"
        }
    ],
    "sg:phone":"+61 3 9707 5413",
    "sg:postcode":"3806",
    "sg:province":"VIC",
    "sg:tags":[
        "store"
    ],
    "wof:name":"The Berwick Inn Taverner",
    "wof:placetype":"venue"
},
  "geometry": {"coordinates":[145.34452819800001,-38.0307235718],"type":"Point"}
}