{
  "type": "Feature",
  "properties": {
    "addr:full":"26 Buckett La Millingandi NSW 2549",
    "addr:housenumber":"26",
    "addr:postcode":"2549",
    "addr:street":"Buckett La Millingandi",
    "iso:country":"AU",
    "sg:address":"26 Buckett La",
    "sg:city":"Millingandi",
    "sg:classifiers":[
        {
            "category":"Building & Trades",
            "subcategory":"Construction",
            "type":"Services"
        }
    ],
    "sg:phone":"+61 2 6495 6253",
    "sg:postcode":"2549",
    "sg:province":"NSW",
    "sg:tags":[
        "earth",
        "excavating",
        "moving",
        "contractor"
    ],
    "wof:name":"Buckett Earthmoving Pty Ltd",
    "wof:placetype":"venue"
},
  "geometry": {"coordinates":[149.87408447300001,-36.9069404602],"type":"Point"}
}