{
  "type": "Feature",
  "properties": {
    "addr:full":"5 St James Crt Campbelltown SA 5074",
    "addr:housenumber":"5",
    "addr:postcode":"5074",
    "addr:street":"St James Crt",
    "iso:country":"AU",
    "sg:address":"5 St James Crt",
    "sg:city":"Campbelltown",
    "sg:classifiers":[
        {
            "category":"Manufacturing",
            "subcategory":"Tools & Machinery",
            "type":"Manufacturing & Wholesale Goods"
        }
    ],
    "sg:phone":"+61 8 8336 8297",
    "sg:postcode":"5074",
    "sg:province":"SA",
    "sg:tags":[
        "fastener",
        "industrial"
    ],
    "wof:name":"Shilpree International",
    "wof:placetype":"venue"
},
  "geometry": {"coordinates":[138.656784058,-34.8859214783],"type":"Point"}
}