{
  "type": "Feature",
  "properties": {
    "iso:country":"AU",
    "sg:address":"Park La",
    "sg:city":"Wangaratta",
    "sg:classifiers":[
        {
            "category":"Arena",
            "subcategory":"Sports Club",
            "type":"Entertainment"
        }
    ],
    "sg:phone":"+61 3 5721 6781",
    "sg:postcode":"3677",
    "sg:province":"VIC",
    "sg:tags":[
        "organisation",
        "sporting"
    ],
    "wof:name":"Wangaratta Basketball Association",
    "wof:placetype":"venue"
},
  "geometry": {"coordinates":[146.311935425,-36.3440170288],"type":"Point"}
}