{
  "type": "Feature",
  "properties": {
    "addr:full":"459 Ruthven St Toowoomba QLD 4350",
    "addr:housenumber":"459",
    "addr:postcode":"4350",
    "addr:street":"Ruthven St",
    "iso:country":"AU",
    "sg:address":"459 Ruthven St",
    "sg:city":"Toowoomba",
    "sg:classifiers":[
        {
            "category":"Shopping",
            "subcategory":"Shoes",
            "type":"Retail Goods"
        }
    ],
    "sg:phone":"+61 7 4632 3666",
    "sg:postcode":"4350",
    "sg:province":"QLD",
    "sg:tags":[
        "footwear"
    ],
    "wof:name":"Suna - Shoes & Accessories",
    "wof:placetype":"venue"
},
  "geometry": {"coordinates":[151.95230100000001,-27.568195],"type":"Point"}
}