{
  "type": "Feature",
  "properties": {
    "iso:country":"AU",
    "sg:address":"49 Metropolitan Rd",
    "sg:city":"Enmore",
    "sg:classifiers":[
        {
            "category":"Retail",
            "subcategory":"Veterinary Services",
            "type":"Services"
        }
    ],
    "sg:phone":"+61 2 9557 0672",
    "sg:postcode":"2042",
    "sg:province":"NSW",
    "sg:tags":[
        "surgeon"
    ],
    "wof:name":"The Australian Veterinary Association Ltd",
    "wof:placetype":"venue"
},
  "geometry": {"coordinates":[151.17244,-33.900948],"type":"Point"}
}