{
  "type": "Feature",
  "properties": {
    "addr:full":"1 Swamp St Wardell NSW 2477",
    "addr:housenumber":"1",
    "addr:postcode":"2477",
    "addr:street":"Swamp St",
    "iso:country":"AU",
    "sg:address":"1 Swamp St",
    "sg:city":"Wardell",
    "sg:classifiers":[
        {
            "category":"Building & Trades",
            "subcategory":"Pest Control",
            "type":"Services"
        }
    ],
    "sg:phone":"+61 2 6687 9559",
    "sg:postcode":"2477",
    "sg:province":"NSW",
    "sg:tags":[
        "breastfeeding",
        "support"
    ],
    "wof:name":"Jay-Elle Lactation",
    "wof:placetype":"venue"
},
  "geometry": {"coordinates":[153.46759033199999,-28.9517326355],"type":"Point"}
}