{
  "type": "Feature",
  "properties": {
    "addr:full":"PO Box 17 Willoughby NSW 2068",
    "addr:postcode":"2068",
    "iso:country":"AU",
    "sg:address":"PO Box 17",
    "sg:city":"Willoughby",
    "sg:classifiers":[
        {
            "category":"Building & Trades",
            "subcategory":"Plumbing",
            "type":"Services"
        }
    ],
    "sg:phone":"+61 2 9958 3726",
    "sg:postcode":"2068",
    "sg:province":"NSW",
    "sg:tags":[
        "drainers"
    ],
    "wof:name":"Norton & Ross Pty Ltd",
    "wof:placetype":"venue"
},
  "geometry": {"coordinates":[151.199386597,-33.8073310852],"type":"Point"}
}