{
  "type": "Feature",
  "properties": {
    "addr:full":"64 Nicholson Rd Subiaco WA 6008",
    "addr:housenumber":"64",
    "addr:postcode":"6008",
    "addr:street":"Nicholson Rd",
    "iso:country":"AU",
    "sg:address":"64 Nicholson Rd",
    "sg:city":"Subiaco",
    "sg:classifiers":[
        {
            "category":"Personal",
            "subcategory":"Massage",
            "type":"Services"
        }
    ],
    "sg:phone":"+61 8 9381 7507",
    "sg:postcode":"6008",
    "sg:province":"WA",
    "sg:tags":[
        "therapy"
    ],
    "wof:name":"Yu Services",
    "wof:placetype":"venue"
},
  "geometry": {"coordinates":[115.821800232,-31.9562473297],"type":"Point"}
}