{
  "type": "Feature",
  "properties": {
    "addr:full":"59 Fairbairn Pl Kyneton VIC 3444",
    "addr:housenumber":"59",
    "addr:postcode":"3444",
    "addr:street":"Fairbairn Pl",
    "iso:country":"AU",
    "sg:address":"59 Fairbairn Pl",
    "sg:city":"Kyneton",
    "sg:classifiers":[
        {
            "category":"Retail",
            "subcategory":"Auto Repair",
            "type":"Services"
        }
    ],
    "sg:phone":"+61 3 5422 1729",
    "sg:postcode":"3444",
    "sg:province":"VIC",
    "sg:tags":[
        "repairer",
        "motor",
        "engineer"
    ],
    "wof:name":"McClure B B & K M",
    "wof:placetype":"venue"
},
  "geometry": {"coordinates":[144.475143433,-37.2627029419],"type":"Point"}
}