{
  "type": "Feature",
  "properties": {
    "addr:full":"Lot 195 Sandy Creek Rd Aberdeen NSW 2336",
    "addr:postcode":"2336",
    "addr:street":"Sandy Creek Rd",
    "iso:country":"AU",
    "sg:address":"Lot 195 Sandy Creek Rd",
    "sg:city":"Aberdeen",
    "sg:classifiers":[
        {
            "category":"Freight",
            "type":"Transportation"
        }
    ],
    "sg:phone":"+61 2 6543 7211",
    "sg:postcode":"2336",
    "sg:province":"NSW",
    "sg:tags":[
        "light",
        "carrier"
    ],
    "wof:name":"Goodsell H & C",
    "wof:placetype":"venue"
},
  "geometry": {"coordinates":[150.840133667,-32.1535797119],"type":"Point"}
}