{
  "type": "Feature",
  "properties": {
    "addr:full":"Bundarra Rd Armidale NSW 2350",
    "addr:postcode":"2350",
    "addr:street":"Bundarra Rd",
    "iso:country":"AU",
    "sg:address":"Bundarra Rd",
    "sg:city":"Armidale",
    "sg:classifiers":[
        {
            "category":"Professional",
            "subcategory":"Accounting & Tax Preparation",
            "type":"Services"
        }
    ],
    "sg:phone":"+61 2 6775 2177",
    "sg:postcode":"2350",
    "sg:province":"NSW",
    "sg:tags":[
        "accountant",
        "auditor"
    ],
    "wof:name":"McGiveron D J",
    "wof:placetype":"venue"
},
  "geometry": {"coordinates":[151.649047852,-30.5185127258],"type":"Point"}
}