{
  "type": "Feature",
  "properties": {
    "addr:full":"Lillypool Rd South Grafton NSW 2460",
    "addr:postcode":"2460",
    "addr:street":"Lillypool Rd",
    "iso:country":"AU",
    "sg:address":"Lillypool Rd",
    "sg:city":"South Grafton",
    "sg:classifiers":[
        {
            "category":"Manufacturing",
            "subcategory":"Musical Instruments",
            "type":"Manufacturing & Wholesale Goods"
        }
    ],
    "sg:phone":"+61 2 6642 4804",
    "sg:postcode":"2460",
    "sg:province":"NSW",
    "sg:tags":[
        "logging",
        "timber"
    ],
    "wof:name":"Greensill Bros Pty Ltd",
    "wof:placetype":"venue"
},
  "geometry": {"coordinates":[152.94662475600001,-29.737575531],"type":"Point"}
}