{
  "type": "Feature",
  "properties": {
    "addr:full":"4 Burraloo St Frenchs Forest NSW 2086",
    "addr:housenumber":"4",
    "addr:postcode":"2086",
    "addr:street":"Burraloo St",
    "iso:country":"AU",
    "sg:address":"4 Burraloo St",
    "sg:city":"Frenchs Forest",
    "sg:classifiers":[
        {
            "category":"Professional",
            "subcategory":"Art Services",
            "type":"Services"
        }
    ],
    "sg:phone":"+61 2 9451 8003",
    "sg:postcode":"2086",
    "sg:province":"NSW",
    "sg:tags":[
        "graphic",
        "designer"
    ],
    "wof:name":"Winter Graphics Pty Ltd",
    "wof:placetype":"venue"
},
  "geometry": {"coordinates":[151.23150634800001,-33.7404632568],"type":"Point"}
}