{
  "type": "Feature",
  "properties": {
    "iso:country":"AU",
    "sg:address":"PO Box 1094",
    "sg:city":"Wangara",
    "sg:classifiers":[
        {
            "category":"Professional",
            "subcategory":"Accounting & Tax Preparation",
            "type":"Services"
        }
    ],
    "sg:phone":"+61 8 9456 0209",
    "sg:postcode":"6065",
    "sg:province":"WA",
    "sg:tags":[
        "consultant",
        "taxation"
    ],
    "wof:name":"I D Conroy Pty Ltd",
    "wof:placetype":"venue"
},
  "geometry": {"coordinates":[115.830238342,-31.7956504822],"type":"Point"}
}