{
  "type": "Feature",
  "properties": {
    "iso:country":"AU",
    "sg:address":"Shp 4/ 67 Bank St",
    "sg:city":"Molong",
    "sg:classifiers":[
        {
            "category":"Personal",
            "subcategory":"Beauty Salon",
            "type":"Services"
        }
    ],
    "sg:phone":"+61 2 6366 8825",
    "sg:postcode":"2866",
    "sg:province":"NSW",
    "wof:name":"Beaute Spot",
    "wof:placetype":"venue"
},
  "geometry": {"coordinates":[148.86914100000001,-33.09211],"type":"Point"}
}