{
  "type": "Feature",
  "properties": {
    "iso:country":"AU",
    "sg:address":"24- 26 Hudson St",
    "sg:city":"Hamilton",
    "sg:classifiers":[
        {
            "category":"Wholesale",
            "subcategory":"Painting Supplies",
            "type":"Manufacturing & Wholesale Goods"
        }
    ],
    "sg:phone":"+61 2 4961 5246",
    "sg:postcode":"2303",
    "sg:province":"NSW",
    "sg:tags":[
        "wholesaler",
        "paint",
        "mfrs"
    ],
    "wof:name":"PPG Industries Australia Pty Ltd",
    "wof:placetype":"venue"
},
  "geometry": {"coordinates":[151.746277,-32.918259],"type":"Point"}
}