{
  "type": "Feature",
  "properties": {
    "iso:country":"AU",
    "sg:address":"A25 Harbour Town Outlet Mall 840 Wellington St",
    "sg:city":"Perth",
    "sg:classifiers":[
        {
            "category":"Shopping",
            "type":"Retail Goods"
        }
    ],
    "sg:phone":"+61 8 9481 8144",
    "sg:postcode":"6000",
    "sg:province":"WA",
    "sg:tags":[
        "repair",
        "travel"
    ],
    "wof:name":"Victoria Station Travel Goods & Handbags",
    "wof:placetype":"venue"
},
  "geometry": {"coordinates":[115.847587585,-31.9475536346],"type":"Point"}
}