{
  "type": "Feature",
  "properties": {
    "addr:full":"22 Sunrise St Mt Cotton QLD 4165",
    "addr:housenumber":"22",
    "addr:postcode":"4165",
    "addr:street":"Sunrise St Mt Cotton",
    "iso:country":"AU",
    "sg:address":"22 Sunrise St",
    "sg:city":"Mt Cotton",
    "sg:classifiers":[
        {
            "category":"Building & Trades",
            "subcategory":"Construction",
            "type":"Services"
        }
    ],
    "sg:phone":"+61 7 3829 9427",
    "sg:postcode":"4165",
    "sg:province":"QLD",
    "sg:tags":[
        "fencing",
        "contractor"
    ],
    "wof:name":"Boundary Fencing",
    "wof:placetype":"venue"
},
  "geometry": {"coordinates":[153.24502563499999,-27.6345462799],"type":"Point"}
}