{
  "type": "Feature",
  "properties": {
    "addr:full":"366 Elizabeth St North Hobart TAS 7000",
    "addr:housenumber":"366",
    "addr:postcode":"7000",
    "addr:street":"Elizabeth St",
    "iso:country":"AU",
    "sg:address":"366 Elizabeth St",
    "sg:city":"North Hobart",
    "sg:classifiers":[
        {
            "category":"Food & Beverages",
            "subcategory":"Bakery",
            "type":"Retail Goods"
        }
    ],
    "sg:phone":"+61 3 6231 3594",
    "sg:postcode":"7000",
    "sg:province":"TAS",
    "sg:tags":[
        "cake",
        "shop",
        "pastry"
    ],
    "wof:name":"Pane Cucina",
    "wof:placetype":"venue"
},
  "geometry": {"coordinates":[147.31597900400001,-42.8737792969],"type":"Point"}
}