{
  "type": "Feature",
  "properties": {
    "addr:full":"2 Kantara Rd Toukley NSW 2263",
    "addr:housenumber":"2",
    "addr:postcode":"2263",
    "addr:street":"Kantara Rd",
    "iso:country":"AU",
    "sg:address":"2 Kantara Rd",
    "sg:city":"Toukley",
    "sg:classifiers":[
        {
            "category":"Travel",
            "subcategory":"Hostel",
            "type":"Entertainment"
        }
    ],
    "sg:phone":"+61 2 4396 4557",
    "sg:postcode":"2263",
    "sg:province":"NSW",
    "sg:tags":[
        "home"
    ],
    "wof:name":"Sandalwood Lodge",
    "wof:placetype":"venue"
},
  "geometry": {"coordinates":[151.54304500000001,-33.269367],"type":"Point"}
}