{
  "type": "Feature",
  "properties": {
    "iso:country":"AU",
    "sg:address":"8 Tennyson St",
    "sg:city":"Granville",
    "sg:classifiers":[
        {
            "category":"Bars & Pubs",
            "subcategory":"Oxygen Bar",
            "type":"Food & Drink"
        }
    ],
    "sg:phone":"+61 1800 307 115",
    "sg:postcode":"2142",
    "sg:province":"NSW",
    "sg:tags":[
        "equipment",
        "pump",
        "concrete"
    ],
    "sg:website":"http://www.concretepump.com.au",
    "wof:name":"Concrete Pumping Equipment Aust. Pty Ltd",
    "wof:placetype":"venue"
},
  "geometry": {"coordinates":[151.02728271500001,-33.8337249756],"type":"Point"}
}