{
  "type": "Feature",
  "properties": {
    "addr:full":"15 Mallinson Crt Airport West VIC 3042",
    "addr:housenumber":"15",
    "addr:postcode":"3042",
    "addr:street":"Mallinson Crt",
    "iso:country":"AU",
    "sg:address":"15 Mallinson Crt",
    "sg:city":"Airport West",
    "sg:classifiers":[
        {
            "category":"Utilities",
            "subcategory":"Electric",
            "type":"Services"
        }
    ],
    "sg:phone":"+61 409 302 030",
    "sg:postcode":"3042",
    "sg:province":"VIC",
    "sg:tags":[
        "electrical",
        "contractor"
    ],
    "wof:name":"Delaney Jim",
    "wof:placetype":"venue"
},
  "geometry": {"coordinates":[144.87226867699999,-37.7270774841],"type":"Point"}
}