{
  "type": "Feature",
  "properties": {
    "addr:full":"36 Broadwater Rd Mt Gravatt East QLD 4122",
    "addr:housenumber":"36",
    "addr:postcode":"4122",
    "addr:street":"Broadwater Rd",
    "iso:country":"AU",
    "sg:address":"36 Broadwater Rd",
    "sg:city":"Mt Gravatt East",
    "sg:classifiers":[
        {
            "category":"Bars & Pubs",
            "subcategory":"Biergarten",
            "type":"Food & Drink"
        }
    ],
    "sg:phone":"+61 7 3411 3757",
    "sg:postcode":"4122",
    "sg:province":"QLD",
    "sg:tags":[
        "tailor",
        "lady"
    ],
    "wof:name":"Clothing Link",
    "wof:placetype":"venue"
},
  "geometry": {"coordinates":[153.08334350600001,-27.5420455933],"type":"Point"}
}