{
  "type": "Feature",
  "properties": {
    "addr:full":"82 Albert St Taree NSW 2430",
    "addr:housenumber":"82",
    "addr:postcode":"2430",
    "addr:street":"Albert St",
    "iso:country":"AU",
    "sg:address":"82 Albert St",
    "sg:city":"Taree",
    "sg:classifiers":[
        {
            "category":"Health Services",
            "subcategory":"Doctor",
            "type":"Services"
        }
    ],
    "sg:phone":"+61 2 6551 6633",
    "sg:postcode":"2430",
    "sg:province":"NSW",
    "sg:tags":[
        "medical",
        "practitioner"
    ],
    "wof:name":"Johnson Allan Dr",
    "wof:placetype":"venue"
},
  "geometry": {"coordinates":[152.46174600000001,-31.910622],"type":"Point"}
}