{
  "type": "Feature",
  "properties": {
    "iso:country":"AU",
    "sg:address":"69 Saints Rd",
    "sg:city":"Salisbury Plain",
    "sg:classifiers":[
        {
            "category":"Manufacturing",
            "subcategory":"Metals",
            "type":"Manufacturing & Wholesale Goods"
        }
    ],
    "sg:phone":"+61 8 8281 4570",
    "sg:postcode":"5109",
    "sg:province":"SA",
    "sg:tags":[
        "sheet",
        "worker"
    ],
    "wof:name":"Salisbury Sheet Metal Pty Ltd",
    "wof:placetype":"venue"
},
  "geometry": {"coordinates":[138.665817261,-34.764175415],"type":"Point"}
}