{
  "type": "Feature",
  "properties": {
    "addr:full":"28 Gilarth St Highett VIC 3190",
    "addr:housenumber":"28",
    "addr:postcode":"3190",
    "addr:street":"Gilarth St",
    "iso:country":"AU",
    "sg:address":"28 Gilarth St",
    "sg:city":"Highett",
    "sg:classifiers":[
        {
            "category":"Communications",
            "type":"Services"
        }
    ],
    "sg:phone":"+61 3 9532 2800",
    "sg:postcode":"3190",
    "sg:province":"VIC",
    "sg:tags":[
        "translation"
    ],
    "wof:name":"ICP Productions",
    "wof:placetype":"venue"
},
  "geometry": {"coordinates":[145.02911376899999,-37.9489173889],"type":"Point"}
}