{
  "type": "Feature",
  "properties": {
    "addr:full":"PO Box 1556 Applecross WA 6153",
    "addr:postcode":"6153",
    "iso:country":"AU",
    "sg:address":"PO Box 1556",
    "sg:city":"Applecross",
    "sg:classifiers":[
        {
            "category":"Building & Trades",
            "subcategory":"Plumbing",
            "type":"Services"
        }
    ],
    "sg:phone":"+61 419 914 518",
    "sg:postcode":"6153",
    "sg:province":"WA",
    "sg:tags":[
        "plumber",
        "gasfitters"
    ],
    "wof:name":"Choice Plumbing W.A.",
    "wof:placetype":"venue"
},
  "geometry": {"coordinates":[115.834808,-32.010342],"type":"Point"}
}