{
  "type": "Feature",
  "properties": {
    "iso:country":"AU",
    "sg:address":"38 Thomas Rd",
    "sg:city":"Kwinana Beach",
    "sg:classifiers":[
        {
            "category":"Home & Garden",
            "subcategory":"Building Materials",
            "type":"Retail Goods"
        }
    ],
    "sg:phone":"+61 8 9419 1488",
    "sg:postcode":"6167",
    "sg:province":"WA",
    "sg:tags":[
        "concrete",
        "panel",
        "pre-cast"
    ],
    "wof:name":"F C I Fibre Concrete Products",
    "wof:placetype":"venue"
},
  "geometry": {"coordinates":[115.779289,-32.2262],"type":"Point"}
}