{
  "type": "Feature",
  "properties": {
    "addr:full":"21 Baxter-Tooradin Rd Pearcedale VIC 3912",
    "addr:housenumber":"21",
    "addr:postcode":"3912",
    "addr:street":"Baxter-Tooradin Rd",
    "iso:country":"AU",
    "sg:address":"21 Baxter-Tooradin Rd",
    "sg:city":"Pearcedale",
    "sg:classifiers":[
        {
            "category":"Utilities",
            "subcategory":"Recycling",
            "type":"Services"
        }
    ],
    "sg:phone":"+61 417 525 820",
    "sg:postcode":"3912",
    "sg:province":"VIC",
    "wof:name":"B & B Cartage",
    "wof:placetype":"venue"
},
  "geometry": {"coordinates":[145.238113403,-38.2031021118],"type":"Point"}
}