{
  "type": "Feature",
  "properties": {
    "iso:country":"AU",
    "sg:address":"49 Banole Ave",
    "sg:city":"Prahran East",
    "sg:classifiers":[
        {
            "category":"Real Estate",
            "subcategory":"Real Estate Services",
            "type":"Services"
        }
    ],
    "sg:phone":"+61 1300 736 638",
    "sg:postcode":"3181",
    "sg:province":"VIC",
    "sg:tags":[
        "valuer"
    ],
    "sg:website":"http://www.vip-consulting.com.au",
    "wof:name":"VIP Victorian Independent Property Consulting",
    "wof:placetype":"venue"
},
  "geometry": {"coordinates":[145.004837036,-37.8552246094],"type":"Point"}
}