{
  "type": "Feature",
  "properties": {
    "iso:country":"AU",
    "sg:address":"33 Kauri St",
    "sg:city":"Albion Park Rail",
    "sg:classifiers":[
        {
            "category":"Education",
            "subcategory":"Dance Studio",
            "type":"Public Place"
        }
    ],
    "sg:phone":"+61 409 981 991",
    "sg:postcode":"2527",
    "sg:province":"NSW",
    "sg:tags":[
        "venue",
        "tuition"
    ],
    "wof:name":"Diane Blaas School Of Dance",
    "wof:placetype":"venue"
},
  "geometry": {"coordinates":[150.80198669399999,-34.5759811401],"type":"Point"}
}