{
  "type": "Feature",
  "properties": {
    "iso:country":"AU",
    "sg:address":"Unit 3 21 Southern Cross Drv",
    "sg:city":"Ballina",
    "sg:classifiers":[
        {
            "category":"Banks & Credit Unions",
            "subcategory":"Investment Brokerage",
            "type":"Services"
        }
    ],
    "sg:phone":"+61 2 6686 5021",
    "sg:postcode":"2478",
    "sg:province":"NSW",
    "sg:tags":[
        "radiator",
        "motor"
    ],
    "wof:name":"Ballina Exhaust Undercar & Radiator Service",
    "wof:placetype":"venue"
},
  "geometry": {"coordinates":[153.55653381400001,-28.8519992828],"type":"Point"}
}