{
  "type": "Feature",
  "properties": {
    "iso:country":"AU",
    "sg:address":"1904 Hume Hwy",
    "sg:city":"Broadmeadows",
    "sg:classifiers":[
        {
            "category":"Wholesale",
            "subcategory":"Metals & Minerals",
            "type":"Manufacturing & Wholesale Goods"
        }
    ],
    "sg:phone":"+61 3 9357 9188",
    "sg:postcode":"3047",
    "sg:province":"VIC",
    "sg:tags":[
        "steel",
        "merchant"
    ],
    "wof:name":"SimsSteel",
    "wof:placetype":"venue"
},
  "geometry": {"coordinates":[144.956573486,-37.6797142029],"type":"Point"}
}