{
  "type": "Feature",
  "properties": {
    "addr:full":"69 Fitzroy St Surry Hills NSW 2010",
    "addr:housenumber":"69",
    "addr:postcode":"2010",
    "addr:street":"Fitzroy St",
    "iso:country":"AU",
    "sg:address":"69 Fitzroy St",
    "sg:city":"Surry Hills",
    "sg:classifiers":[
        {
            "category":"Communications",
            "subcategory":"Newspaper",
            "type":"Services"
        }
    ],
    "sg:phone":"+61 2 9360 0720",
    "sg:postcode":"2010",
    "sg:province":"NSW",
    "sg:tags":[
        "whiteboards",
        "chalkboard"
    ],
    "wof:name":"Alta Gallery",
    "wof:placetype":"venue"
},
  "geometry": {"coordinates":[151.216430664,-33.8856048584],"type":"Point"}
}