{
  "type": "Feature",
  "properties": {
    "addr:full":"26 The Northern Rd Luddenham NSW 2745",
    "addr:housenumber":"26",
    "addr:postcode":"2745",
    "addr:street":"The Northern Rd",
    "iso:country":"AU",
    "sg:address":"26 The Northern Rd",
    "sg:city":"Luddenham",
    "sg:classifiers":[
        {
            "category":"Social Services",
            "subcategory":"Child Care",
            "type":"Services"
        }
    ],
    "sg:phone":"+61 2 4773 3224",
    "sg:postcode":"2745",
    "sg:province":"NSW",
    "wof:name":"Luddenham Child Care Centre",
    "wof:placetype":"venue"
},
  "geometry": {"coordinates":[150.701568603,-33.8966789246],"type":"Point"}
}