{
  "type": "Feature",
  "properties": {
    "addr:full":"Unit 1/ 3 Endeavour Drv Port Adelaide SA 5015",
    "addr:housenumber":"3",
    "addr:postcode":"5015",
    "addr:street":"Endeavour Drv",
    "iso:country":"AU",
    "sg:address":"Unit 1/ 3 Endeavour Drv",
    "sg:city":"Port Adelaide",
    "sg:classifiers":[
        {
            "category":"Wholesale",
            "subcategory":"Machinery & Supplies",
            "type":"Manufacturing & Wholesale Goods"
        }
    ],
    "sg:phone":"+61 8 8341 2260",
    "sg:postcode":"5015",
    "sg:province":"SA",
    "sg:tags":[
        "equipment",
        "hydraulic"
    ],
    "wof:name":"Stauff Corporation Pty Ltd",
    "wof:placetype":"venue"
},
  "geometry": {"coordinates":[138.50378418,-34.8546333313],"type":"Point"}
}