{
  "type": "Feature",
  "properties": {
    "addr:full":"234 Mowbray Rd Chatswood NSW 2067",
    "addr:housenumber":"234",
    "addr:postcode":"2067",
    "addr:street":"Mowbray Rd",
    "iso:country":"AU",
    "sg:address":"234 Mowbray Rd",
    "sg:city":"Chatswood",
    "sg:classifiers":[
        {
            "category":"Education",
            "subcategory":"Music School",
            "type":"Public Place"
        }
    ],
    "sg:phone":"+61 2 9411 1760",
    "sg:postcode":"2067",
    "sg:province":"NSW",
    "sg:tags":[
        "teacher"
    ],
    "wof:name":"Square Music",
    "wof:placetype":"venue"
},
  "geometry": {"coordinates":[151.19102477999999,-33.801940918],"type":"Point"}
}