{
  "type": "Feature",
  "properties": {
    "addr:full":"80B Austral Tce Katanning WA 6317",
    "addr:housenumber":"80b",
    "addr:postcode":"6317",
    "addr:street":"Austral Tce",
    "iso:country":"AU",
    "sg:address":"80B Austral Tce",
    "sg:city":"Katanning",
    "sg:classifiers":[
        {
            "category":"Personal",
            "subcategory":"Beauty Salon",
            "type":"Services"
        }
    ],
    "sg:phone":"+61 8 9821 1615",
    "sg:postcode":"6317",
    "sg:province":"WA",
    "sg:tags":[
        "hairdresser"
    ],
    "wof:name":"Valerie Salon",
    "wof:placetype":"venue"
},
  "geometry": {"coordinates":[117.553100586,-33.6892242432],"type":"Point"}
}