{
  "type": "Feature",
  "properties": {
    "iso:country":"AU",
    "sg:address":"505 Willoughby Rd",
    "sg:city":"Willoughby",
    "sg:classifiers":[
        {
            "category":"Food & Beverages",
            "subcategory":"Meat & Fish",
            "type":"Retail Goods"
        }
    ],
    "sg:phone":"+61 2 9958 6604",
    "sg:postcode":"2068",
    "sg:province":"NSW",
    "sg:tags":[
        "seafood"
    ],
    "wof:name":"Willoughby Sea Foods",
    "wof:placetype":"venue"
},
  "geometry": {"coordinates":[151.19956970199999,-33.807434082],"type":"Point"}
}