{
  "type": "Feature",
  "properties": {
    "iso:country":"AU",
    "sg:address":"126 Brisbane St",
    "sg:city":"Dubbo",
    "sg:classifiers":[
        {
            "category":"Organizations",
            "subcategory":"Community Association",
            "type":"Services"
        }
    ],
    "sg:phone":"+61 2 6882 2845",
    "sg:postcode":"2830",
    "sg:province":"NSW",
    "sg:tags":[
        "organisation",
        "family",
        "welfare"
    ],
    "wof:name":"St Vincent de Paul Society",
    "wof:placetype":"venue"
},
  "geometry": {"coordinates":[148.60429382300001,-32.2455635071],"type":"Point"}
}