{
  "type": "Feature",
  "properties": {
    "iso:country":"AU",
    "sg:address":"20 Dewer Ave",
    "sg:city":"Ridgehaven",
    "sg:classifiers":[
        {
            "category":"Professional",
            "subcategory":"Art Services",
            "type":"Services"
        }
    ],
    "sg:phone":"+61 8 8395 7444",
    "sg:postcode":"5097",
    "sg:province":"SA",
    "sg:tags":[
        "decorator",
        "painter"
    ],
    "wof:name":"Commercial Painting Contractors",
    "wof:placetype":"venue"
},
  "geometry": {"coordinates":[138.69688415499999,-34.825214386],"type":"Point"}
}