{
  "type": "Feature",
  "properties": {
    "addr:full":"26 Bundarra Crt Craigmore SA 5114",
    "addr:housenumber":"26",
    "addr:postcode":"5114",
    "addr:street":"Bundarra Crt",
    "iso:country":"AU",
    "sg:address":"26 Bundarra Crt",
    "sg:city":"Craigmore",
    "sg:classifiers":[
        {
            "category":"Personal",
            "type":"Services"
        }
    ],
    "sg:phone":"+61 8 8287 3256",
    "sg:postcode":"5114",
    "sg:province":"SA",
    "sg:tags":[
        "gift"
    ],
    "wof:name":"Gifts With Love",
    "wof:placetype":"venue"
},
  "geometry": {"coordinates":[138.70486450199999,-34.7014465332],"type":"Point"}
}