{
  "type": "Feature",
  "properties": {
    "addr:full":"37 Churchill Park Drv Endeavour Hills VIC 3802",
    "addr:housenumber":"37",
    "addr:postcode":"3802",
    "addr:street":"Churchill Park Drv",
    "iso:country":"AU",
    "sg:address":"37 Churchill Park Drv",
    "sg:city":"Endeavour Hills",
    "sg:classifiers":[
        {
            "category":"Building & Trades",
            "subcategory":"Construction",
            "type":"Services"
        }
    ],
    "sg:phone":"+61 3 9700 1258",
    "sg:postcode":"3802",
    "sg:province":"VIC",
    "sg:tags":[
        "plasterboard",
        "plasterer",
        "fixer"
    ],
    "wof:name":"T A G Plasterboards Pty Ltd",
    "wof:placetype":"venue"
},
  "geometry": {"coordinates":[145.27583313,-37.9597892761],"type":"Point"}
}