{
  "type": "Feature",
  "properties": {
    "addr:full":"39b Leach Ave Riverton WA 6148",
    "addr:housenumber":"39b",
    "addr:postcode":"6148",
    "addr:street":"Leach Ave",
    "iso:country":"AU",
    "sg:address":"39b Leach Ave",
    "sg:city":"Riverton",
    "sg:classifiers":[
        {
            "category":"Shopping",
            "subcategory":"Gifts & Souvenirs",
            "type":"Retail Goods"
        }
    ],
    "sg:phone":"+61 8 9354 7111",
    "sg:postcode":"6148",
    "sg:province":"WA",
    "sg:tags":[
        "shop",
        "supply"
    ],
    "wof:name":"B.C. Agencies",
    "wof:placetype":"venue"
},
  "geometry": {"coordinates":[115.89617200000001,-32.038227],"type":"Point"}
}