{
  "type": "Feature",
  "properties": {
    "addr:full":"139 Surrey Rd North South Yarra VIC 3141",
    "addr:housenumber":"139",
    "addr:postcode":"3141",
    "addr:street":"Surrey Rd North",
    "iso:country":"AU",
    "sg:address":"139 Surrey Rd North",
    "sg:city":"South Yarra",
    "sg:classifiers":[
        {
            "category":"Wholesale",
            "subcategory":"Medical Equipment & Supplies",
            "type":"Manufacturing & Wholesale Goods"
        }
    ],
    "sg:phone":"+61 3 9827 7830",
    "sg:postcode":"3141",
    "sg:province":"VIC",
    "sg:tags":[
        "aids",
        "hearing"
    ],
    "wof:name":"About Ears",
    "wof:placetype":"venue"
},
  "geometry": {"coordinates":[144.99882507300001,-37.8402481079],"type":"Point"}
}