{
  "type": "Feature",
  "properties": {
    "addr:full":"141 Bayview St Runaway Bay QLD 4216",
    "addr:housenumber":"141",
    "addr:postcode":"4216",
    "addr:street":"Bayview St",
    "iso:country":"AU",
    "sg:address":"141 Bayview St",
    "sg:city":"Runaway Bay",
    "sg:classifiers":[
        {
            "category":"Health Services",
            "subcategory":"Dentist",
            "type":"Services"
        }
    ],
    "sg:phone":"+61 7 5537 3146",
    "sg:postcode":"4216",
    "sg:province":"QLD",
    "wof:name":"Wills John A McG",
    "wof:placetype":"venue"
},
  "geometry": {"coordinates":[153.40415954599999,-27.9216976166],"type":"Point"}
}