{
  "type": "Feature",
  "properties": {
    "addr:full":"Cnr Kamerunga & Fairweather Rds Redlynch QLD 4870",
    "addr:postcode":"4870",
    "addr:street":"Cnr Kamerunga & Fairweather Rds",
    "iso:country":"AU",
    "sg:address":"Cnr Kamerunga & Fairweather Rds",
    "sg:city":"Redlynch",
    "sg:classifiers":[
        {
            "category":"Social Services",
            "subcategory":"Adult Care",
            "type":"Services"
        }
    ],
    "sg:phone":"+61 7 4039 9700",
    "sg:postcode":"4870",
    "sg:province":"QLD",
    "sg:tags":[
        "aged"
    ],
    "wof:name":"St Johns After Hours Respite Care",
    "wof:placetype":"venue"
},
  "geometry": {"coordinates":[145.69422912600001,-16.8842391968],"type":"Point"}
}