{
  "type": "Feature",
  "properties": {
    "addr:full":"392 High St Penrith NSW 2750",
    "addr:housenumber":"392",
    "addr:postcode":"2750",
    "addr:street":"High St",
    "iso:country":"AU",
    "sg:address":"392 High St",
    "sg:city":"Penrith",
    "sg:classifiers":[
        {
            "category":"Food & Beverages",
            "subcategory":"Bakery",
            "type":"Retail Goods"
        }
    ],
    "sg:phone":"+61 2 4721 5372",
    "sg:postcode":"2750",
    "sg:province":"NSW",
    "sg:tags":[
        "baker"
    ],
    "wof:name":"Nepean Bakehouse The",
    "wof:placetype":"venue"
},
  "geometry": {"coordinates":[150.91557312,-33.894859314],"type":"Point"}
}