{
  "type": "Feature",
  "properties": {
    "addr:full":"228-234 Pacific Hwy Swansea NSW 2281",
    "addr:housenumber":"228-234",
    "addr:postcode":"2281",
    "addr:street":"Pacific Hwy",
    "iso:country":"AU",
    "sg:address":"228-234 Pacific Hwy",
    "sg:city":"Swansea",
    "sg:classifiers":[
        {
            "category":"Organizations",
            "subcategory":"Community Association",
            "type":"Services"
        }
    ],
    "sg:phone":"+61 2 4971 1229",
    "sg:postcode":"2281",
    "sg:province":"NSW",
    "sg:tags":[
        "organisation",
        "family",
        "welfare"
    ],
    "wof:name":"Swansea Community Cottage",
    "wof:placetype":"venue"
},
  "geometry": {"coordinates":[151.637619019,-33.0858078003],"type":"Point"}
}