{
  "type": "Feature",
  "properties": {
    "iso:country":"AU",
    "sg:address":"22 Thomas St",
    "sg:city":"Hampton",
    "sg:classifiers":[
        {
            "category":"Health Services",
            "subcategory":"Dentist",
            "type":"Services"
        }
    ],
    "sg:phone":"+61 3 9521 6500",
    "sg:postcode":"3188",
    "sg:province":"VIC",
    "wof:name":"Sheridan Charles Dr",
    "wof:placetype":"venue"
},
  "geometry": {"coordinates":[145.00486755399999,-37.9387359619],"type":"Point"}
}