{
  "type": "Feature",
  "properties": {
    "iso:country":"AU",
    "sg:address":"PO Box 2212",
    "sg:city":"Seaford",
    "sg:classifiers":[
        {
            "category":"Building & Trades",
            "subcategory":"Construction",
            "type":"Services"
        }
    ],
    "sg:phone":"+61 418 313 160",
    "sg:postcode":"3198",
    "sg:province":"VIC",
    "sg:tags":[
        "concrete",
        "contractor"
    ],
    "wof:name":"Cut & Drill Pty Ltd",
    "wof:placetype":"venue"
},
  "geometry": {"coordinates":[145.14215087900001,-38.1062583923],"type":"Point"}
}