{
  "type": "Feature",
  "properties": {
    "iso:country":"AU",
    "sg:address":"Warragul Rd",
    "sg:city":"Ranceby",
    "sg:classifiers":[
        {
            "category":"Farming",
            "subcategory":"Farm",
            "type":"Manufacturing & Wholesale Goods"
        }
    ],
    "sg:phone":"+61 3 5659 7226",
    "sg:postcode":"3951",
    "sg:province":"VIC",
    "sg:tags":[
        "farmer"
    ],
    "wof:name":"Connors P A",
    "wof:placetype":"venue"
},
  "geometry": {"coordinates":[145.84022522000001,-38.374370575],"type":"Point"}
}