{
  "type": "Feature",
  "properties": {
    "addr:full":"Lot 11 Goddard La Tamworth NSW 2340",
    "addr:postcode":"2340",
    "addr:street":"Goddard La",
    "iso:country":"AU",
    "sg:address":"Lot 11 Goddard La",
    "sg:city":"Tamworth",
    "sg:classifiers":[
        {
            "category":"Building & Trades",
            "subcategory":"Construction",
            "type":"Services"
        }
    ],
    "sg:phone":"+61 2 6761 5066",
    "sg:postcode":"2340",
    "sg:province":"NSW",
    "sg:tags":[
        "bitumen",
        "paving",
        "asphalt"
    ],
    "wof:name":"Pioneer Road Services Pty Ltd",
    "wof:placetype":"venue"
},
  "geometry": {"coordinates":[150.86453247099999,-31.072681427],"type":"Point"}
}