{
  "type": "Feature",
  "properties": {
    "addr:full":"40 Canada St Lake Cargelligo NSW 2672",
    "addr:housenumber":"40",
    "addr:postcode":"2672",
    "addr:street":"Canada St",
    "iso:country":"AU",
    "sg:address":"40 Canada St",
    "sg:city":"Lake Cargelligo",
    "sg:classifiers":[
        {
            "category":"Professional",
            "subcategory":"Engineering",
            "type":"Services"
        }
    ],
    "sg:phone":"+61 2 6898 1188",
    "sg:postcode":"2672",
    "sg:province":"NSW",
    "sg:tags":[
        "engineer"
    ],
    "wof:name":"AR & RM Coff Engineering",
    "wof:placetype":"venue"
},
  "geometry": {"coordinates":[146.37416076700001,-33.3001823425],"type":"Point"}
}