{
  "type": "Feature",
  "properties": {
    "addr:full":"647 Sydney Rd Brunswick VIC 3056",
    "addr:housenumber":"647",
    "addr:postcode":"3056",
    "addr:street":"Sydney Rd",
    "iso:country":"AU",
    "sg:address":"647 Sydney Rd",
    "sg:city":"Brunswick",
    "sg:classifiers":[
        {
            "category":"Fast Food",
            "type":"Food & Drink"
        }
    ],
    "sg:phone":"+61 3 9386 7285",
    "sg:postcode":"3056",
    "sg:province":"VIC",
    "sg:tags":[
        "away",
        "take"
    ],
    "wof:name":"Brunswick Rooster",
    "wof:placetype":"venue"
},
  "geometry": {"coordinates":[144.96304321299999,-37.7624130249],"type":"Point"}
}