{
  "type": "Feature",
  "properties": {
    "addr:full":"Spotlight Complex Queanbeyan ACT 2620",
    "addr:postcode":"2620",
    "iso:country":"AU",
    "sg:address":"Spotlight Complex",
    "sg:city":"Queanbeyan",
    "sg:classifiers":[
        {
            "category":"Cafe",
            "type":"Food & Drink"
        }
    ],
    "sg:phone":"+61 2 6299 7577",
    "sg:postcode":"2620",
    "sg:province":"ACT",
    "wof:name":"Creative Cafe",
    "wof:placetype":"venue"
},
  "geometry": {"coordinates":[149.217987061,-35.3758049011],"type":"Point"}
}