{
  "type": "Feature",
  "properties": {
    "addr:full":"14b Watervale Drv Green Fields SA 5107",
    "addr:housenumber":"14b",
    "addr:postcode":"5107",
    "addr:street":"Watervale Drv Green",
    "iso:country":"AU",
    "sg:address":"14b Watervale Drv",
    "sg:city":"Green Fields",
    "sg:classifiers":[
        {
            "category":"Professional",
            "subcategory":"Engineering",
            "type":"Services"
        }
    ],
    "sg:phone":"+61 8 8250 9077",
    "sg:postcode":"5107",
    "sg:province":"SA",
    "sg:tags":[
        "engineer"
    ],
    "wof:name":"K & A Engineering",
    "wof:placetype":"venue"
},
  "geometry": {"coordinates":[138.60449218799999,-34.797542572],"type":"Point"}
}