{
  "type": "Feature",
  "properties": {
    "addr:full":"63 Buxton Rd Wembley Downs WA 6019",
    "addr:housenumber":"63",
    "addr:postcode":"6019",
    "addr:street":"Buxton Rd",
    "iso:country":"AU",
    "sg:address":"63 Buxton Rd",
    "sg:city":"Wembley Downs",
    "sg:classifiers":[
        {
            "category":"Real Estate",
            "subcategory":"Architect",
            "type":"Services"
        }
    ],
    "sg:phone":"+61 8 9205 1599",
    "sg:postcode":"6019",
    "sg:province":"WA",
    "wof:name":"Santelli Alis",
    "wof:placetype":"venue"
},
  "geometry": {"coordinates":[115.769767761,-31.9208335876],"type":"Point"}
}