{
  "type": "Feature",
  "properties": {
    "addr:full":"Teviot Downs 195 Lyon Drv Greenbank QLD 4124",
    "addr:housenumber":"195",
    "addr:postcode":"4124",
    "addr:street":"Teviot;Lyon Drv",
    "iso:country":"AU",
    "sg:address":"Teviot Downs 195 Lyon Drv",
    "sg:city":"Greenbank",
    "sg:classifiers":[
        {
            "category":"Building & Trades",
            "subcategory":"Construction",
            "type":"Services"
        }
    ],
    "sg:phone":"+61 7 3200 1756",
    "sg:postcode":"4124",
    "sg:province":"QLD",
    "sg:tags":[
        "fencing",
        "contractor"
    ],
    "wof:name":"Gilbro Pty Ltd",
    "wof:placetype":"venue"
},
  "geometry": {"coordinates":[152.955932617,-27.7473239899],"type":"Point"}
}