{
  "type": "Feature",
  "properties": {
    "iso:country":"AU",
    "sg:address":"Shop 2/ 48 Railway Rd",
    "sg:city":"Marayong",
    "sg:classifiers":[
        {
            "category":"Real Estate",
            "subcategory":"Real Estate Agent",
            "type":"Services"
        }
    ],
    "sg:phone":"+61 2 9621 5000",
    "sg:postcode":"2148",
    "sg:province":"NSW",
    "wof:name":"Marie Baran & Co Real Estate",
    "wof:placetype":"venue"
},
  "geometry": {"coordinates":[150.899932861,-33.7476196289],"type":"Point"}
}