{
  "type": "Feature",
  "properties": {
    "iso:country":"AU",
    "sg:address":"26 Broad St ( Cnr East St )",
    "sg:city":"Sarina",
    "sg:classifiers":[
        {
            "category":"Health Services",
            "subcategory":"Dentist",
            "type":"Services"
        }
    ],
    "sg:phone":"+61 7 4943 1243",
    "sg:postcode":"4737",
    "sg:province":"QLD",
    "wof:name":"Smiles 4 Everyone",
    "wof:placetype":"venue"
},
  "geometry": {"coordinates":[149.217957,-21.423513],"type":"Point"}
}