{
  "type": "Feature",
  "properties": {
    "iso:country":"AU",
    "sg:address":"Dore St",
    "sg:city":"Katanning",
    "sg:classifiers":[
        {
            "category":"Social Services",
            "subcategory":"Child Care",
            "type":"Services"
        }
    ],
    "sg:phone":"+61 8 9821 2232",
    "sg:postcode":"6317",
    "sg:province":"WA",
    "sg:tags":[
        "support",
        "health"
    ],
    "wof:name":"Community & Child Health Services",
    "wof:placetype":"venue"
},
  "geometry": {"coordinates":[117.556007385,-33.6905555725],"type":"Point"}
}