{
  "type": "Feature",
  "properties": {
    "addr:full":"No 5 Smails Cl Woolgoolga NSW 2456",
    "addr:postcode":"2456",
    "addr:street":"Cl",
    "iso:country":"AU",
    "sg:address":"No 5",
    "sg:city":"Smails Cl Woolgoolga",
    "sg:classifiers":[
        {
            "category":"Building & Trades",
            "subcategory":"Construction",
            "type":"Services"
        }
    ],
    "sg:phone":"+61 410 465 845",
    "sg:postcode":"2456",
    "sg:province":"NSW",
    "sg:tags":[
        "concrete",
        "contractor"
    ],
    "wof:name":"Kema Industries",
    "wof:placetype":"venue"
},
  "geometry": {"coordinates":[153.190338,-30.11187],"type":"Point"}
}