{
  "type": "Feature",
  "properties": {
    "addr:full":"11 Presnell St Granton TAS 7030",
    "addr:housenumber":"11",
    "addr:postcode":"7030",
    "addr:street":"Presnell St",
    "iso:country":"AU",
    "sg:address":"11 Presnell St",
    "sg:city":"Granton",
    "sg:classifiers":[
        {
            "category":"Building & Trades",
            "subcategory":"Construction",
            "type":"Services"
        }
    ],
    "sg:phone":"+61 419 362 321",
    "sg:postcode":"7030",
    "sg:province":"TAS",
    "sg:tags":[
        "welding"
    ],
    "wof:name":"On- Call Contract Welding",
    "wof:placetype":"venue"
},
  "geometry": {"coordinates":[147.23866272000001,-42.7667884827],"type":"Point"}
}