{
  "type": "Feature",
  "properties": {
    "addr:full":"66 Rankin St Mareeba QLD 4880",
    "addr:housenumber":"66",
    "addr:postcode":"4880",
    "addr:street":"Rankin St",
    "iso:country":"AU",
    "sg:address":"66 Rankin St",
    "sg:city":"Mareeba",
    "sg:classifiers":[
        {
            "category":"Health Services",
            "subcategory":"Doctor",
            "type":"Services"
        }
    ],
    "sg:phone":"+61 7 4092 4513",
    "sg:postcode":"4880",
    "sg:province":"QLD",
    "sg:tags":[
        "nurse",
        "nursing"
    ],
    "wof:name":"Respite Services Mareeba/Kuranda",
    "wof:placetype":"venue"
},
  "geometry": {"coordinates":[145.42486572300001,-16.9968929291],"type":"Point"}
}