{
  "type": "Feature",
  "properties": {
    "iso:country":"AU",
    "sg:address":"9 Fleetwood Drv",
    "sg:city":"Narre Warren",
    "sg:classifiers":[
        {
            "category":"Health Services",
            "subcategory":"Health Practitioner",
            "type":"Services"
        }
    ],
    "sg:phone":"+61 3 9704 2444",
    "sg:postcode":"3805",
    "sg:province":"VIC",
    "sg:tags":[
        "naturopath"
    ],
    "wof:name":"Narre Warren Wellness Centre.",
    "wof:placetype":"venue"
},
  "geometry": {"coordinates":[145.306793,-38.038914],"type":"Point"}
}