{
  "type": "Feature",
  "properties": {
    "iso:country":"AU",
    "sg:address":"81 Macquarie Rd",
    "sg:city":"Arcadia Vale",
    "sg:classifiers":[
        {
            "category":"Arts & Performance",
            "subcategory":"Music",
            "type":"Entertainment"
        }
    ],
    "sg:phone":"+61 1300 666 878",
    "sg:postcode":"2283",
    "sg:province":"NSW",
    "sg:tags":[
        "mobile",
        "jockey",
        "disc"
    ],
    "wof:name":"Dynamic DJs",
    "wof:placetype":"venue"
},
  "geometry": {"coordinates":[151.59176635700001,-32.9882164001],"type":"Point"}
}