{
  "type": "Feature",
  "properties": {
    "addr:full":"1 Parsonage Rd Castle Hill NSW 2154",
    "addr:housenumber":"1",
    "addr:postcode":"2154",
    "addr:street":"Parsonage Rd",
    "iso:country":"AU",
    "sg:address":"1 Parsonage Rd",
    "sg:city":"Castle Hill",
    "sg:classifiers":[
        {
            "category":"Professional",
            "subcategory":"Employment Agencies",
            "type":"Services"
        }
    ],
    "sg:phone":"+61 2 9659 4111",
    "sg:postcode":"2154",
    "sg:province":"NSW",
    "sg:tags":[
        "entertainer",
        "agent"
    ],
    "wof:name":"Hotshots Entertainment",
    "wof:placetype":"venue"
},
  "geometry": {"coordinates":[151.00064086899999,-33.737991333],"type":"Point"}
}