{
  "type": "Feature",
  "properties": {
    "addr:full":"79 Commercial Rd Port Adelaide SA 5015",
    "addr:housenumber":"79",
    "addr:postcode":"5015",
    "addr:street":"Commercial Rd",
    "iso:country":"AU",
    "sg:address":"79 Commercial Rd",
    "sg:city":"Port Adelaide",
    "sg:classifiers":[
        {
            "category":"Shopping",
            "subcategory":"Clothing, Apparel, & Fashions",
            "type":"Retail Goods"
        }
    ],
    "sg:phone":"+61 8 8447 7760",
    "sg:postcode":"5015",
    "sg:province":"SA",
    "sg:tags":[
        "recycled",
        "clothing"
    ],
    "wof:name":"OARS SA Charity OpShops",
    "wof:placetype":"venue"
},
  "geometry": {"coordinates":[138.50584411599999,-34.8446083069],"type":"Point"}
}