{
  "type": "Feature",
  "properties": {
    "addr:full":"133 Somerville Rd Hampton Park VIC 3976",
    "addr:housenumber":"133",
    "addr:postcode":"3976",
    "addr:street":"Somerville Rd",
    "iso:country":"AU",
    "sg:address":"133 Somerville Rd",
    "sg:city":"Hampton Park",
    "sg:classifiers":[
        {
            "category":"Health Services",
            "subcategory":"Doctor",
            "type":"Services"
        }
    ],
    "sg:phone":"+61 3 9799 0903",
    "sg:postcode":"3976",
    "sg:province":"VIC",
    "sg:tags":[
        "medical",
        "practitioner"
    ],
    "wof:name":"Somerville Road Medical Centre",
    "wof:placetype":"venue"
},
  "geometry": {"coordinates":[145.26722717300001,-38.0319747925],"type":"Point"}
}