{
  "type": "Feature",
  "properties": {
    "iso:country":"AU",
    "sg:address":"8 Fletcher Rd",
    "sg:city":"Mt Barker",
    "sg:classifiers":[
        {
            "category":"Travel",
            "subcategory":"Hostel",
            "type":"Entertainment"
        }
    ],
    "sg:phone":"+61 8 8391 2486",
    "sg:postcode":"5251",
    "sg:province":"SA",
    "sg:tags":[
        "home"
    ],
    "wof:name":"Mount Barker & District Homes For The Aged",
    "wof:placetype":"venue"
},
  "geometry": {"coordinates":[138.86476135300001,-35.0712852478],"type":"Point"}
}