{
  "type": "Feature",
  "properties": {
    "addr:full":"3 Rooke St Devonport TAS 7310",
    "addr:housenumber":"3",
    "addr:postcode":"7310",
    "addr:street":"Rooke St",
    "iso:country":"AU",
    "sg:address":"3 Rooke St",
    "sg:city":"Devonport",
    "sg:classifiers":[
        {
            "category":"Shopping",
            "subcategory":"Crafts & Fabrics",
            "type":"Retail Goods"
        }
    ],
    "sg:phone":"+61 3 6424 6150",
    "sg:postcode":"7310",
    "sg:province":"TAS",
    "sg:tags":[
        "wool",
        "knitting",
        "accessory"
    ],
    "wof:name":"Stitch In Time",
    "wof:placetype":"venue"
},
  "geometry": {"coordinates":[146.360137939,-41.1812744141],"type":"Point"}
}