{
  "type": "Feature",
  "properties": {
    "iso:country":"AU",
    "sg:address":"347 Kenilworth St",
    "sg:city":"Albury",
    "sg:classifiers":[
        {
            "category":"Food & Beverages",
            "subcategory":"Groceries & Convenience Stores",
            "type":"Retail Goods"
        }
    ],
    "sg:phone":"+61 2 6021 4288",
    "sg:postcode":"2640",
    "sg:province":"NSW",
    "wof:name":"East View Store",
    "wof:placetype":"venue"
},
  "geometry": {"coordinates":[146.92848205600001,-36.0838508606],"type":"Point"}
}