{
  "type": "Feature",
  "properties": {
    "iso:country":"AU",
    "sg:address":"Isaacs St",
    "sg:city":"Dysart",
    "sg:classifiers":[
        {
            "category":"Building & Trades",
            "subcategory":"Construction",
            "type":"Services"
        }
    ],
    "sg:phone":"+61 7 4958 1278",
    "sg:postcode":"4745",
    "sg:province":"QLD",
    "sg:tags":[
        "contractor"
    ],
    "wof:name":"Citra Constructions Ltd",
    "wof:placetype":"venue"
},
  "geometry": {"coordinates":[148.349503,-22.58033],"type":"Point"}
}