{
  "type": "Feature",
  "properties": {
    "iso:country":"AU",
    "sg:address":"3/ 14 Veronica St",
    "sg:city":"Capalaba",
    "sg:classifiers":[
        {
            "category":"Shopping",
            "subcategory":"Stationery & Office Supplies",
            "type":"Retail Goods"
        }
    ],
    "sg:phone":"+61 7 3823 1033",
    "sg:postcode":"4157",
    "sg:province":"QLD",
    "sg:tags":[
        "packaging",
        "equipment",
        "sealing",
        "filling"
    ],
    "wof:name":"Bag Closing Systems",
    "wof:placetype":"venue"
},
  "geometry": {"coordinates":[153.19833374000001,-27.5273857117],"type":"Point"}
}