{
  "type": "Feature",
  "properties": {
    "iso:country":"AU",
    "sg:address":"Weatherall Rd",
    "sg:city":"Cheltenham",
    "sg:classifiers":[
        {
            "category":"Arena",
            "subcategory":"Sports Club",
            "type":"Entertainment"
        }
    ],
    "sg:phone":"+61 3 9585 1259",
    "sg:postcode":"3192",
    "sg:province":"VIC",
    "sg:tags":[
        "australian",
        "football",
        "rule"
    ],
    "wof:name":"Cheltenham Cricket & Football Clubs",
    "wof:placetype":"venue"
},
  "geometry": {"coordinates":[145.053344727,-37.9722976685],"type":"Point"}
}