{
  "type": "Feature",
  "properties": {
    "addr:full":"64 Heather St Heatherbrae NSW 2324",
    "addr:housenumber":"64",
    "addr:postcode":"2324",
    "addr:street":"Heather St",
    "iso:country":"AU",
    "sg:address":"64 Heather St",
    "sg:city":"Heatherbrae",
    "sg:classifiers":[
        {
            "category":"Professional",
            "subcategory":"Employment Agencies",
            "type":"Services"
        }
    ],
    "sg:phone":"+61 2 4987 1818",
    "sg:postcode":"2324",
    "sg:province":"NSW",
    "sg:tags":[
        "consultant",
        "corrosion"
    ],
    "wof:name":"Baron Fibreglass",
    "wof:placetype":"venue"
},
  "geometry": {"coordinates":[151.733932495,-32.7857208252],"type":"Point"}
}