{
  "type": "Feature",
  "properties": {
    "addr:full":"115 Rooke Mall Devonport TAS 7310",
    "addr:housenumber":"115",
    "addr:postcode":"7310",
    "addr:street":"Rooke Mall",
    "iso:country":"AU",
    "sg:address":"115 Rooke Mall",
    "sg:city":"Devonport",
    "sg:classifiers":[
        {
            "category":"Shopping",
            "subcategory":"Clothing, Apparel, & Fashions",
            "type":"Retail Goods"
        }
    ],
    "sg:phone":"+61 3 6424 9779",
    "sg:postcode":"7310",
    "sg:province":"TAS",
    "sg:tags":[
        "lady",
        "wear"
    ],
    "wof:name":"Fan Everyday Wear",
    "wof:placetype":"venue"
},
  "geometry": {"coordinates":[146.36076355,-41.1781692505],"type":"Point"}
}