{
  "type": "Feature",
  "properties": {
    "iso:country":"AU",
    "sg:address":"5 Willson Ave",
    "sg:city":"Mundubbera",
    "sg:classifiers":[
        {
            "category":"Building & Trades",
            "subcategory":"Construction",
            "type":"Services"
        }
    ],
    "sg:phone":"+61 7 4165 4888",
    "sg:postcode":"4626",
    "sg:province":"QLD",
    "sg:tags":[
        "contractor"
    ],
    "wof:name":"Halfpenny B J & M",
    "wof:placetype":"venue"
},
  "geometry": {"coordinates":[151.301788,-25.582174],"type":"Point"}
}