{
  "type": "Feature",
  "properties": {
    "addr:full":"Compuda St Salisbury SA 5108",
    "addr:postcode":"5108",
    "addr:street":"St",
    "iso:country":"AU",
    "sg:address":"Compuda St",
    "sg:city":"Salisbury",
    "sg:classifiers":[
        {
            "category":"Education",
            "subcategory":"School",
            "type":"Public Place"
        }
    ],
    "sg:phone":"+61 8 8258 9161",
    "sg:postcode":"5108",
    "sg:province":"SA",
    "sg:tags":[
        "state",
        "except",
        "nsw"
    ],
    "wof:name":"Salisbury Primary Dental Clinic",
    "wof:placetype":"venue"
},
  "geometry": {"coordinates":[138.64605712900001,-34.7677230835],"type":"Point"}
}