{
  "type": "Feature",
  "properties": {
    "addr:full":"Caves Beach Rd Caves Beach NSW 2281",
    "addr:postcode":"2281",
    "addr:street":"Caves Beach Rd",
    "iso:country":"AU",
    "sg:address":"Caves Beach Rd",
    "sg:city":"Caves Beach",
    "sg:classifiers":[
        {
            "category":"Personal",
            "subcategory":"Beauty Salon",
            "type":"Services"
        }
    ],
    "sg:phone":"+61 2 4971 2142",
    "sg:postcode":"2281",
    "sg:province":"NSW",
    "sg:tags":[
        "hairdresser"
    ],
    "wof:name":"Caves Hair Haven",
    "wof:placetype":"venue"
},
  "geometry": {"coordinates":[151.64553832999999,-33.1008224487],"type":"Point"}
}