{
  "type": "Feature",
  "properties": {
    "addr:full":"Building 2 14a Baker St Botany NSW 2019",
    "addr:housenumber":"14a",
    "addr:postcode":"2019",
    "addr:street":"Baker St",
    "iso:country":"AU",
    "sg:address":"Building 2 14a Baker St",
    "sg:city":"Botany",
    "sg:classifiers":[
        {
            "category":"Professional",
            "type":"Services"
        }
    ],
    "sg:phone":"+61 2 9666 6911",
    "sg:postcode":"2019",
    "sg:province":"NSW",
    "sg:tags":[
        "forwarding",
        "agent",
        "transport"
    ],
    "wof:name":"Cargoplan International Pty Ltd",
    "wof:placetype":"venue"
},
  "geometry": {"coordinates":[151.215576172,-33.9456481934],"type":"Point"}
}