{
  "type": "Feature",
  "properties": {
    "iso:country":"AU",
    "sg:address":"39 Wilmot St",
    "sg:city":"Burnie",
    "sg:classifiers":[
        {
            "category":"Shopping",
            "subcategory":"Clothing, Apparel, & Fashions",
            "type":"Retail Goods"
        }
    ],
    "sg:phone":"+61 3 6431 8505",
    "sg:postcode":"7320",
    "sg:province":"TAS",
    "sg:tags":[
        "menswear"
    ],
    "wof:name":"Cameron Stewarts Mens Fashions",
    "wof:placetype":"venue"
},
  "geometry": {"coordinates":[145.906204,-41.051037],"type":"Point"}
}