{
  "type": "Feature",
  "properties": {
    "addr:full":"67 Bank St Molong NSW 2866",
    "addr:housenumber":"67",
    "addr:postcode":"2866",
    "addr:street":"Bank St",
    "iso:country":"AU",
    "sg:address":"67 Bank St",
    "sg:city":"Molong",
    "sg:classifiers":[
        {
            "category":"Retail",
            "subcategory":"Self-service Laundry",
            "type":"Services"
        }
    ],
    "sg:phone":"+61 2 6366 9200",
    "sg:postcode":"2866",
    "sg:province":"NSW",
    "wof:name":"Molong Laundrymat & Laundry Service",
    "wof:placetype":"venue"
},
  "geometry": {"coordinates":[148.86914100000001,-33.09211],"type":"Point"}
}