{
  "type": "Feature",
  "properties": {
    "iso:country":"AU",
    "sg:address":"Unit 4 16 Abrams St",
    "sg:city":"Balcatta",
    "sg:classifiers":[
        {
            "category":"Wholesale",
            "subcategory":"Stationery",
            "type":"Manufacturing & Wholesale Goods"
        }
    ],
    "sg:phone":"+61 8 9345 2230",
    "sg:postcode":"6021",
    "sg:province":"WA",
    "sg:tags":[
        "mfrg"
    ],
    "wof:name":"Avery Dennison Office Products",
    "wof:placetype":"venue"
},
  "geometry": {"coordinates":[115.805030823,-31.8633956909],"type":"Point"}
}