{
  "type": "Feature",
  "properties": {
    "addr:full":"Phillip St Beulah VIC 3395",
    "addr:postcode":"3395",
    "addr:street":"Phillip St",
    "iso:country":"AU",
    "sg:address":"Phillip St",
    "sg:city":"Beulah",
    "sg:classifiers":[
        {
            "category":"Travel",
            "subcategory":"Hotels & Motels",
            "type":"Entertainment"
        }
    ],
    "sg:phone":"+61 3 5390 2248",
    "sg:postcode":"3395",
    "sg:province":"VIC",
    "sg:tags":[
        "accommodation"
    ],
    "wof:name":"Victoria Hotel",
    "wof:placetype":"venue"
},
  "geometry": {"coordinates":[142.420379639,-35.9410591125],"type":"Point"}
}