{
  "type": "Feature",
  "properties": {
    "addr:full":"258 Lawrence Hargrave Drv Thirroul NSW 2515",
    "addr:housenumber":"258",
    "addr:postcode":"2515",
    "addr:street":"Lawrence Hargrave Drv",
    "iso:country":"AU",
    "sg:address":"258 Lawrence Hargrave Drv",
    "sg:city":"Thirroul",
    "sg:classifiers":[
        {
            "category":"Government",
            "subcategory":"Post Office",
            "type":"Public Place"
        }
    ],
    "sg:phone":"+61 2 4267 1099",
    "sg:postcode":"2515",
    "sg:province":"NSW",
    "sg:tags":[
        "postal"
    ],
    "wof:name":"Australia Post",
    "wof:placetype":"venue"
},
  "geometry": {"coordinates":[150.92349200000001,-34.314651],"type":"Point"}
}