{
  "type": "Feature",
  "properties": {
    "iso:country":"AU",
    "sg:address":"260 Nottingham Rd",
    "sg:city":"Parkinson",
    "sg:classifiers":[
        {
            "category":"Retail",
            "subcategory":"Auto Repair",
            "type":"Services"
        }
    ],
    "sg:phone":"+61 7 3272 2083",
    "sg:postcode":"4115",
    "sg:province":"QLD",
    "sg:tags":[
        "testing",
        "inspection",
        "motor",
        "vehicle"
    ],
    "wof:name":"Safety Certificate Services",
    "wof:placetype":"venue"
},
  "geometry": {"coordinates":[153.02923584000001,-27.627790451],"type":"Point"}
}