{
  "type": "Feature",
  "properties": {
    "iso:country":"AU",
    "sg:address":"Shp 1/ 50 Northcott Drv",
    "sg:city":"Kotara",
    "sg:classifiers":[
        {
            "category":"Manufacturing",
            "subcategory":"Furniture",
            "type":"Manufacturing & Wholesale Goods"
        }
    ],
    "sg:phone":"+61 2 4952 5123",
    "sg:postcode":"2289",
    "sg:province":"NSW",
    "sg:tags":[
        "builder",
        "designer",
        "custom"
    ],
    "wof:name":"Lyall Buick Furniture",
    "wof:placetype":"venue"
},
  "geometry": {"coordinates":[151.71206665,-32.9396438599],"type":"Point"}
}