{
  "type": "Feature",
  "properties": {
    "addr:full":"Unit 5, 6 Hill St Emu Park QLD 4702",
    "addr:housenumber":"6",
    "addr:postcode":"4702",
    "addr:street":"Hill St",
    "iso:country":"AU",
    "sg:address":"Unit 5, 6 Hill St",
    "sg:city":"Emu Park",
    "sg:classifiers":[
        {
            "category":"Professional",
            "subcategory":"Computer Services",
            "type":"Services"
        }
    ],
    "sg:phone":"+61 7 4925 4400",
    "sg:postcode":"4702",
    "sg:province":"QLD",
    "sg:tags":[
        "package",
        "software"
    ],
    "wof:name":"Hospitality Computer Systems",
    "wof:placetype":"venue"
},
  "geometry": {"coordinates":[150.329147339,-23.4824829102],"type":"Point"}
}