{
  "type": "Feature",
  "properties": {
    "addr:full":"85 Azalea Ave Coffs Harbour NSW 2450",
    "addr:housenumber":"85",
    "addr:postcode":"2450",
    "addr:street":"Azalea Ave",
    "iso:country":"AU",
    "sg:address":"85 Azalea Ave",
    "sg:city":"Coffs Harbour",
    "sg:classifiers":[
        {
            "category":"Personal",
            "subcategory":"Beauty Salon",
            "type":"Services"
        }
    ],
    "sg:phone":"+61 2 6658 0553",
    "sg:postcode":"2450",
    "sg:province":"NSW",
    "wof:name":"Nail Trend",
    "wof:placetype":"venue"
},
  "geometry": {"coordinates":[153.10614000000001,-30.30327],"type":"Point"}
}