{
  "type": "Feature",
  "properties": {
    "addr:full":"21 Macquarie St Thomastown VIC 3074",
    "addr:housenumber":"21",
    "addr:postcode":"3074",
    "addr:street":"Macquarie St",
    "iso:country":"AU",
    "sg:address":"21 Macquarie St",
    "sg:city":"Thomastown",
    "sg:classifiers":[
        {
            "category":"Building & Trades",
            "subcategory":"Construction",
            "type":"Services"
        }
    ],
    "sg:phone":"+61 417 557 828",
    "sg:postcode":"3074",
    "sg:province":"VIC",
    "sg:tags":[
        "roof"
    ],
    "wof:name":"Fairfield Roof Tilers",
    "wof:placetype":"venue"
},
  "geometry": {"coordinates":[145.03111267099999,-37.6912727356],"type":"Point"}
}