{
  "type": "Feature",
  "properties": {
    "iso:country":"AU",
    "sg:address":"Level 5, 92 Parramatta Rd",
    "sg:city":"Camperdown",
    "sg:classifiers":[
        {
            "category":"Organizations",
            "subcategory":"Professional Association",
            "type":"Services"
        }
    ],
    "sg:phone":"+61 2 9036 3100",
    "sg:postcode":"2050",
    "sg:province":"NSW",
    "sg:tags":[
        "organisation",
        "business"
    ],
    "wof:name":"Clinical Oncological Society Of Australia (COSA)",
    "wof:placetype":"venue"
},
  "geometry": {"coordinates":[151.179916,-33.885883],"type":"Point"}
}