{
  "type": "Feature",
  "properties": {
    "iso:country":"AU",
    "sg:address":"Suite 7, Bulimba Specialist Centre, 204 Oxford St",
    "sg:city":"Bulimba",
    "sg:classifiers":[
        {
            "category":"Health Services",
            "subcategory":"Health Practitioner",
            "type":"Services"
        }
    ],
    "sg:phone":"+61 7 3899 1455",
    "sg:postcode":"4171",
    "sg:province":"QLD",
    "sg:tags":[
        "psychologist"
    ],
    "wof:name":"Zimmermann, Helga",
    "wof:placetype":"venue"
},
  "geometry": {"coordinates":[153.06149292000001,-27.4515190125],"type":"Point"}
}