{
  "type": "Feature",
  "properties": {
    "addr:full":"Fcty 2/ 31 Peel St Eltham VIC 3095",
    "addr:housenumber":"/ 31",
    "addr:postcode":"3095",
    "addr:street":"Peel St",
    "iso:country":"AU",
    "sg:address":"Fcty 2/ 31 Peel St",
    "sg:city":"Eltham",
    "sg:classifiers":[
        {
            "category":"Professional",
            "subcategory":"Computer Services",
            "type":"Services"
        }
    ],
    "sg:phone":"+61 1300 886 226",
    "sg:postcode":"3095",
    "sg:province":"VIC",
    "sg:tags":[
        "repairs",
        "upgrade",
        "equipment"
    ],
    "wof:name":"CCM - Corporate Cartridge Management",
    "wof:placetype":"venue"
},
  "geometry": {"coordinates":[145.14122009299999,-37.7200813293],"type":"Point"}
}