{
  "type": "Feature",
  "properties": {
    "addr:full":"14 Baxter Rd Geelong North VIC 3215",
    "addr:housenumber":"14",
    "addr:postcode":"3215",
    "addr:street":"Baxter Rd",
    "iso:country":"AU",
    "sg:address":"14 Baxter Rd",
    "sg:city":"Geelong North",
    "sg:classifiers":[
        {
            "category":"Professional",
            "subcategory":"Accounting & Tax Preparation",
            "type":"Services"
        }
    ],
    "sg:phone":"+61 3 5278 8188",
    "sg:postcode":"3215",
    "sg:province":"VIC",
    "sg:tags":[
        "consultant",
        "taxation"
    ],
    "wof:name":"Thorley Michael",
    "wof:placetype":"venue"
},
  "geometry": {"coordinates":[144.350509644,-38.1234588623],"type":"Point"}
}