{
  "type": "Feature",
  "properties": {
    "iso:country":"AU",
    "sg:address":"210 Anzac Pde",
    "sg:city":"Kensington",
    "sg:classifiers":[
        {
            "category":"Food & Beverages",
            "subcategory":"Groceries & Convenience Stores",
            "type":"Retail Goods"
        }
    ],
    "sg:phone":"+61 2 9313 6246",
    "sg:postcode":"2033",
    "sg:province":"NSW",
    "wof:name":"Kensington Mixed Business",
    "wof:placetype":"venue"
},
  "geometry": {"coordinates":[151.223434,-33.91103],"type":"Point"}
}