{
  "type": "Feature",
  "properties": {
    "iso:country":"AU",
    "sg:address":"182 Hindley St",
    "sg:city":"Adelaide",
    "sg:classifiers":[
        {
            "category":"Cafe",
            "type":"Food & Drink"
        }
    ],
    "sg:phone":"+61 8 8212 9888",
    "sg:postcode":"5000",
    "sg:province":"SA",
    "wof:name":"Elysium Lounge",
    "wof:placetype":"venue"
},
  "geometry": {"coordinates":[138.59263610799999,-34.9232063293],"type":"Point"}
}