{
  "type": "Feature",
  "properties": {
    "addr:full":"108 Auburn Rd Hawthorn VIC 3122",
    "addr:housenumber":"108",
    "addr:postcode":"3122",
    "addr:street":"Auburn Rd",
    "iso:country":"AU",
    "sg:address":"108 Auburn Rd",
    "sg:city":"Hawthorn",
    "sg:classifiers":[
        {
            "category":"Banks & Credit Unions",
            "subcategory":"Financial Services",
            "type":"Services"
        }
    ],
    "sg:phone":"+61 3 9816 6788",
    "sg:postcode":"3122",
    "sg:province":"VIC",
    "sg:tags":[
        "financier"
    ],
    "wof:name":"Victorian Finance & Leasing Limited",
    "wof:placetype":"venue"
},
  "geometry": {"coordinates":[145.04495239299999,-37.8220367432],"type":"Point"}
}