{
  "type": "Feature",
  "properties": {
    "iso:country":"AU",
    "sg:address":"U 38/ 18 Bienvenue Drv",
    "sg:city":"Currumbin Waters",
    "sg:classifiers":[
        {
            "category":"Utilities",
            "subcategory":"Telephone",
            "type":"Services"
        }
    ],
    "sg:phone":"+61 7 5598 8420",
    "sg:postcode":"4223",
    "sg:province":"QLD",
    "sg:tags":[
        "installation",
        "system",
        "maintenance"
    ],
    "wof:name":"Surf City Communications",
    "wof:placetype":"venue"
},
  "geometry": {"coordinates":[153.47137451200001,-28.1548538208],"type":"Point"}
}