{
  "type": "Feature",
  "properties": {
    "addr:full":"Shop 9 & 10/ 113-133 Mollison St Bendigo VIC 3550",
    "addr:housenumber":"shop 9 & 10 / 113-133",
    "addr:postcode":"3550",
    "addr:street":"Mollison St",
    "iso:country":"AU",
    "sg:address":"Shop 9 & 10/ 113-133 Mollison St",
    "sg:city":"Bendigo",
    "sg:classifiers":[
        {
            "category":"Food & Beverages",
            "subcategory":"Liquor & Beverages",
            "type":"Retail Goods"
        }
    ],
    "sg:phone":"+61 3 5442 3044",
    "sg:postcode":"3550",
    "sg:province":"VIC",
    "sg:tags":[
        "store"
    ],
    "wof:name":"Bendigo Wines & Spirits",
    "wof:placetype":"venue"
},
  "geometry": {"coordinates":[144.283493042,-36.7631111145],"type":"Point"}
}