{
  "type": "Feature",
  "properties": {
    "addr:full":"Lvl 1/ 45 Queen St Brisbane QLD 4000",
    "addr:housenumber":"/ 45",
    "addr:postcode":"4000",
    "addr:street":"Queen St",
    "iso:country":"AU",
    "sg:address":"Lvl 1/ 45 Queen St",
    "sg:city":"Brisbane",
    "sg:classifiers":[
        {
            "category":"Restaurant",
            "type":"Food & Drink"
        }
    ],
    "sg:phone":"+61 7 3210 0688",
    "sg:postcode":"4000",
    "sg:province":"QLD",
    "wof:name":"Beijing House",
    "wof:placetype":"venue"
},
  "geometry": {"coordinates":[153.02394104000001,-27.4707775116],"type":"Point"}
}