{
  "type": "Feature",
  "properties": {
    "addr:full":"363 Flemington Rd North Melbourne VIC 3051",
    "addr:housenumber":"363",
    "addr:postcode":"3051",
    "addr:street":"Flemington Rd",
    "iso:country":"AU",
    "sg:address":"363 Flemington Rd",
    "sg:city":"North Melbourne",
    "sg:classifiers":[
        {
            "category":"Utilities",
            "subcategory":"Electric",
            "type":"Services"
        }
    ],
    "sg:phone":"+61 3 9326 9300",
    "sg:postcode":"3051",
    "sg:province":"VIC",
    "sg:tags":[
        "electrical",
        "contractor"
    ],
    "wof:name":"Noron Electrical Services Pty Ltd",
    "wof:placetype":"venue"
},
  "geometry": {"coordinates":[144.94291687,-37.7903785706],"type":"Point"}
}