{
  "type": "Feature",
  "properties": {
    "addr:full":"70 Wollongong Rd Arncliffe NSW 2205",
    "addr:housenumber":"70",
    "addr:postcode":"2205",
    "addr:street":"Wollongong Rd",
    "iso:country":"AU",
    "sg:address":"70 Wollongong Rd",
    "sg:city":"Arncliffe",
    "sg:classifiers":[
        {
            "category":"Building & Trades",
            "subcategory":"Plumbing",
            "type":"Services"
        }
    ],
    "sg:phone":"+61 2 9567 6995",
    "sg:postcode":"2205",
    "sg:province":"NSW",
    "sg:tags":[
        "plumber",
        "gasfitters"
    ],
    "wof:name":"Oxford Chris Plumbing",
    "wof:placetype":"venue"
},
  "geometry": {"coordinates":[151.14381399999999,-33.935776],"type":"Point"}
}