{
  "type": "Feature",
  "properties": {
    "addr:full":"5 Mcpherson St Leongatha VIC 3953",
    "addr:housenumber":"5",
    "addr:postcode":"3953",
    "addr:street":"Mcpherson St",
    "iso:country":"AU",
    "sg:address":"5 Mcpherson St",
    "sg:city":"Leongatha",
    "sg:classifiers":[
        {
            "category":"Food & Beverages",
            "subcategory":"Specialty",
            "type":"Retail Goods"
        }
    ],
    "sg:phone":"+61 3 5662 2545",
    "sg:postcode":"3953",
    "sg:province":"VIC",
    "sg:tags":[
        "ice",
        "supply"
    ],
    "wof:name":"Coleman's Ice & Springwater Supplies",
    "wof:placetype":"venue"
},
  "geometry": {"coordinates":[145.95866394000001,-38.4695892334],"type":"Point"}
}