{
  "type": "Feature",
  "properties": {
    "iso:country":"AU",
    "sg:address":"Elizabeth St",
    "sg:city":"Serviceton",
    "sg:classifiers":[
        {
            "category":"Communications",
            "subcategory":"Film & Video Production",
            "type":"Services"
        }
    ],
    "sg:phone":"+61 3 5393 1371",
    "sg:postcode":"3420",
    "sg:province":"VIC",
    "sg:tags":[
        "equipment",
        "amplification",
        "music"
    ],
    "wof:name":"Road Runner P A Hire",
    "wof:placetype":"venue"
},
  "geometry": {"coordinates":[140.990402222,-36.3765716553],"type":"Point"}
}