{
  "type": "Feature",
  "properties": {
    "iso:country":"AU",
    "sg:address":"754 Hampton St",
    "sg:city":"Brighton",
    "sg:classifiers":[
        {
            "category":"Health Services",
            "subcategory":"Dentist",
            "type":"Services"
        }
    ],
    "sg:phone":"+61 3 9592 0583",
    "sg:postcode":"3186",
    "sg:province":"VIC",
    "wof:name":"Keogh Michelle Dr",
    "wof:placetype":"venue"
},
  "geometry": {"coordinates":[145.00619506800001,-37.9189987183],"type":"Point"}
}