{
  "type": "Feature",
  "properties": {
    "iso:country":"AU",
    "sg:address":"2704 Ipswich Rd",
    "sg:city":"Darra",
    "sg:classifiers":[
        {
            "category":"Travel",
            "subcategory":"Hotels & Motels",
            "type":"Entertainment"
        }
    ],
    "sg:phone":"+61 7 3375 5047",
    "sg:postcode":"4076",
    "sg:province":"QLD",
    "wof:name":"Darra Motel",
    "wof:placetype":"venue"
},
  "geometry": {"coordinates":[152.95707702600001,-27.5733146667],"type":"Point"}
}