{
  "type": "Feature",
  "properties": {
    "iso:country":"AU",
    "sg:address":"406-410 Sir Donald Bradman Drv",
    "sg:city":"Brooklyn Park",
    "sg:classifiers":[
        {
            "category":"Retail",
            "subcategory":"Event Space",
            "type":"Services"
        }
    ],
    "sg:phone":"+61 8 8234 3577",
    "sg:postcode":"5032",
    "sg:province":"SA",
    "sg:tags":[
        "function",
        "organiser"
    ],
    "wof:name":"Nathaniel's International Bar & Restaurant",
    "wof:placetype":"venue"
},
  "geometry": {"coordinates":[138.539352417,-34.9324493408],"type":"Point"}
}