{
  "type": "Feature",
  "properties": {
    "addr:full":"42 Yarramundi La Richmond NSW 2753",
    "addr:housenumber":"42",
    "addr:postcode":"2753",
    "addr:street":"Yarramundi La",
    "iso:country":"AU",
    "sg:address":"42 Yarramundi La",
    "sg:city":"Richmond",
    "sg:classifiers":[
        {
            "category":"Farming",
            "subcategory":"Orchard",
            "type":"Manufacturing & Wholesale Goods"
        }
    ],
    "sg:phone":"+61 2 4578 1213",
    "sg:postcode":"2753",
    "sg:province":"NSW",
    "sg:tags":[
        "citrus",
        "fruit",
        "grower"
    ],
    "wof:name":"Schofield A",
    "wof:placetype":"venue"
},
  "geometry": {"coordinates":[150.72253418,-33.5931777954],"type":"Point"}
}