{
  "type": "Feature",
  "properties": {
    "iso:country":"AU",
    "sg:address":"3 Karara Crt",
    "sg:city":"Alexandra Hills",
    "sg:classifiers":[
        {
            "category":"Health Services",
            "subcategory":"Health Practitioner",
            "type":"Services"
        }
    ],
    "sg:phone":"+61 7 3824 6949",
    "sg:postcode":"4161",
    "sg:province":"QLD",
    "sg:tags":[
        "acupuncture"
    ],
    "wof:name":"Laser Acupuncture & Sports Massage",
    "wof:placetype":"venue"
},
  "geometry": {"coordinates":[153.22911071799999,-27.5349159241],"type":"Point"}
}