{
  "type": "Feature",
  "properties": {
    "addr:full":"Post Box 1/55B Frenchmans Rd Randwick NSW 2031",
    "addr:housenumber":"/ 55b",
    "addr:postcode":"2031",
    "addr:street":"Frenchmans Rd",
    "iso:country":"AU",
    "sg:address":"Post Box 1/55B Frenchmans Rd",
    "sg:city":"Randwick",
    "sg:classifiers":[
        {
            "category":"Building & Trades",
            "subcategory":"Plumbing",
            "type":"Services"
        }
    ],
    "sg:phone":"+61 2 9314 5055",
    "sg:postcode":"2031",
    "sg:province":"NSW",
    "sg:tags":[
        "drainers"
    ],
    "wof:name":"A 1 Coogee Plumbing",
    "wof:placetype":"venue"
},
  "geometry": {"coordinates":[151.24789428700001,-33.9081115723],"type":"Point"}
}