{
  "type": "Feature",
  "properties": {
    "addr:full":"50 Sanger St Corowa NSW 2646",
    "addr:housenumber":"50",
    "addr:postcode":"2646",
    "addr:street":"Sanger St",
    "iso:country":"AU",
    "sg:address":"50 Sanger St",
    "sg:city":"Corowa",
    "sg:classifiers":[
        {
            "category":"Shopping",
            "subcategory":"Jewelry",
            "type":"Retail Goods"
        }
    ],
    "sg:phone":"+61 2 6033 1415",
    "sg:postcode":"2646",
    "sg:province":"NSW",
    "sg:tags":[
        "jeweller"
    ],
    "wof:name":"Gail Goodall's Arcade Jewellers",
    "wof:placetype":"venue"
},
  "geometry": {"coordinates":[146.39134216299999,-35.9948806763],"type":"Point"}
}