{
  "type": "Feature",
  "properties": {
    "addr:full":"Robertson Drv Bunbury WA 6230",
    "addr:postcode":"6230",
    "addr:street":"Robertson Drv",
    "iso:country":"AU",
    "sg:address":"Robertson Drv",
    "sg:city":"Bunbury",
    "sg:classifiers":[
        {
            "category":"Education",
            "subcategory":"University",
            "type":"Public Place"
        }
    ],
    "sg:phone":"+61 8 9780 7777",
    "sg:postcode":"6230",
    "sg:province":"WA",
    "sg:tags":[
        "college",
        "tertiary"
    ],
    "wof:name":"Edith Cowan University",
    "wof:placetype":"venue"
},
  "geometry": {"coordinates":[115.645554,-33.364586],"type":"Point"}
}