{
  "type": "Feature",
  "properties": {
    "addr:full":"40 Prince St Hampton VIC 3188",
    "addr:housenumber":"40",
    "addr:postcode":"3188",
    "addr:street":"Prince St",
    "iso:country":"AU",
    "sg:address":"40 Prince St",
    "sg:city":"Hampton",
    "sg:classifiers":[
        {
            "category":"Building & Trades",
            "subcategory":"Construction",
            "type":"Services"
        }
    ],
    "sg:phone":"+61 424 356 199",
    "sg:postcode":"3188",
    "sg:province":"VIC",
    "sg:tags":[
        "polishing",
        "sanding",
        "floor"
    ],
    "wof:name":"Mirror Image Floor Sanding & Polishing",
    "wof:placetype":"venue"
},
  "geometry": {"coordinates":[145.01449585,-37.9342041016],"type":"Point"}
}