{
  "type": "Feature",
  "properties": {
    "addr:full":"105 Clark Rd Londonderry NSW 2753",
    "addr:housenumber":"105",
    "addr:postcode":"2753",
    "addr:street":"Clark Rd",
    "iso:country":"AU",
    "sg:address":"105 Clark Rd",
    "sg:city":"Londonderry",
    "sg:classifiers":[
        {
            "category":"Wholesale",
            "subcategory":"Painting Supplies",
            "type":"Manufacturing & Wholesale Goods"
        }
    ],
    "sg:phone":"+61 2 4572 0466",
    "sg:postcode":"2753",
    "sg:province":"NSW",
    "sg:tags":[
        "product",
        "polyurethane"
    ],
    "wof:name":"Just Foam",
    "wof:placetype":"venue"
},
  "geometry": {"coordinates":[150.76190185600001,-33.635017395],"type":"Point"}
}