{
  "type": "Feature",
  "properties": {
    "addr:full":"PO Box 234 Cooranbong NSW 2265",
    "addr:postcode":"2265",
    "iso:country":"AU",
    "sg:address":"PO Box 234",
    "sg:city":"Cooranbong",
    "sg:classifiers":[
        {
            "category":"Retail",
            "subcategory":"Auto Rental",
            "type":"Services"
        }
    ],
    "sg:phone":"+61 2 4977 3224",
    "sg:postcode":"2265",
    "sg:province":"NSW",
    "sg:tags":[
        "chauffeur",
        "car",
        "hire",
        "driven",
        "limousine"
    ],
    "wof:name":"Harlequin HSV Bridal Cars",
    "wof:placetype":"venue"
},
  "geometry": {"coordinates":[151.46762100000001,-33.06699],"type":"Point"}
}