{
  "type": "Feature",
  "properties": {
    "iso:country":"AU",
    "sg:address":"122 Campbell St",
    "sg:city":"Rockhampton",
    "sg:classifiers":[
        {
            "category":"Manufacturing",
            "subcategory":"Food",
            "type":"Manufacturing & Wholesale Goods"
        }
    ],
    "sg:phone":"+61 7 4927 7077",
    "sg:postcode":"4700",
    "sg:province":"QLD",
    "sg:tags":[
        "function",
        "catering"
    ],
    "wof:name":"The Cheesecake Shop",
    "wof:placetype":"venue"
},
  "geometry": {"coordinates":[150.51077270499999,-23.3858108521],"type":"Point"}
}