{
  "type": "Feature",
  "properties": {
    "iso:country":"AU",
    "sg:address":"21- 43 Barnes Rd",
    "sg:city":"Altona North",
    "sg:classifiers":[
        {
            "category":"Professional",
            "type":"Services"
        }
    ],
    "sg:phone":"+61 3 9391 0222",
    "sg:postcode":"3025",
    "sg:province":"VIC",
    "sg:tags":[
        "transport"
    ],
    "wof:name":"CRT Bulk Haulage",
    "wof:placetype":"venue"
},
  "geometry": {"coordinates":[144.83880600000001,-37.84219],"type":"Point"}
}