{
  "type": "Feature",
  "properties": {
    "addr:full":"2 Eynsford St Carindale QLD 4152",
    "addr:housenumber":"2",
    "addr:postcode":"4152",
    "addr:street":"Eynsford St",
    "iso:country":"AU",
    "sg:address":"2 Eynsford St",
    "sg:city":"Carindale",
    "sg:classifiers":[
        {
            "category":"Organizations",
            "subcategory":"Professional Association",
            "type":"Services"
        }
    ],
    "sg:phone":"+61 7 3843 4334",
    "sg:postcode":"4152",
    "sg:province":"QLD",
    "sg:tags":[
        "web",
        "internet"
    ],
    "wof:name":"A1 Web Works Designs",
    "wof:placetype":"venue"
},
  "geometry": {"coordinates":[153.10516357399999,-27.4921512604],"type":"Point"}
}