{
  "type": "Feature",
  "properties": {
    "iso:country":"AU",
    "sg:address":"Ste158/ 236 Hyperdome Rd",
    "sg:city":"Loganholme",
    "sg:classifiers":[
        {
            "category":"Professional",
            "subcategory":"Accounting & Tax Preparation",
            "type":"Services"
        }
    ],
    "sg:phone":"+61 414 497 117",
    "sg:postcode":"4129",
    "sg:province":"QLD",
    "sg:tags":[
        "bookkeeping"
    ],
    "wof:name":"McDonnell B L",
    "wof:placetype":"venue"
},
  "geometry": {"coordinates":[153.185791016,-27.6725502014],"type":"Point"}
}