{
  "type": "Feature",
  "properties": {
    "addr:full":"Shop 4/ Ross Crt Cleveland QLD 4163",
    "addr:housenumber":"shop 4 /",
    "addr:postcode":"4163",
    "addr:street":"Ross Crt",
    "iso:country":"AU",
    "sg:address":"Shop 4/ Ross Crt",
    "sg:city":"Cleveland",
    "sg:classifiers":[
        {
            "category":"Retail",
            "subcategory":"Storage",
            "type":"Services"
        }
    ],
    "sg:phone":"+61 7 3821 0632",
    "sg:postcode":"4163",
    "sg:province":"QLD",
    "sg:tags":[
        "removal",
        "furniture"
    ],
    "wof:name":"Birkdale Furniture Removals",
    "wof:placetype":"venue"
},
  "geometry": {"coordinates":[153.266555786,-27.5319919586],"type":"Point"}
}