{
  "type": "Feature",
  "properties": {
    "addr:full":"Gold Creek Village, O'Hanlon Pl Nicholls ACT 2913",
    "addr:postcode":"2913",
    "addr:street":"Pl",
    "iso:country":"AU",
    "sg:address":"Gold Creek Village, O'Hanlon Pl",
    "sg:city":"Nicholls",
    "sg:classifiers":[
        {
            "category":"Travel",
            "subcategory":"Hotels & Motels",
            "type":"Entertainment"
        }
    ],
    "sg:phone":"+61 2 6241 3000",
    "sg:postcode":"2913",
    "sg:province":"ACT",
    "wof:name":"Gold Creek Tourist Resort",
    "wof:placetype":"venue"
},
  "geometry": {"coordinates":[149.08164977999999,-35.1889686584],"type":"Point"}
}