{
  "type": "Feature",
  "properties": {
    "addr:full":"1/ 34 Prime Drv Seven Hills NSW 2147",
    "addr:housenumber":"/ 34",
    "addr:postcode":"2147",
    "addr:street":"Prime Drv",
    "iso:country":"AU",
    "sg:address":"1/ 34 Prime Drv",
    "sg:city":"Seven Hills",
    "sg:classifiers":[
        {
            "category":"Real Estate",
            "subcategory":"Real Estate Agent",
            "type":"Services"
        }
    ],
    "sg:phone":"+61 2 9838 7188",
    "sg:postcode":"2147",
    "sg:province":"NSW",
    "sg:tags":[
        "handyman's",
        "equipment",
        "hire",
        "builders",
        "contractor"
    ],
    "wof:name":"Applied Climate Control",
    "wof:placetype":"venue"
},
  "geometry": {"coordinates":[150.95254516599999,-33.7728462219],"type":"Point"}
}