{
  "type": "Feature",
  "properties": {
    "iso:country":"AU",
    "sg:address":"17 Douglas St",
    "sg:city":"Flinders Park",
    "sg:classifiers":[
        {
            "category":"Personal",
            "subcategory":"Beauty Salon",
            "type":"Services"
        }
    ],
    "sg:phone":"+61 8 8354 4710",
    "sg:postcode":"5025",
    "sg:province":"SA",
    "sg:website":"http://www.rubesque.com.au",
    "wof:name":"Rubesque",
    "wof:placetype":"venue"
},
  "geometry": {"coordinates":[138.53518676799999,-34.9069633484],"type":"Point"}
}