{
  "type": "Feature",
  "properties": {
    "iso:country":"AU",
    "sg:address":"185- 189 Harrington St",
    "sg:city":"Hobart",
    "sg:classifiers":[
        {
            "category":"Building & Trades",
            "subcategory":"Plumbing",
            "type":"Services"
        }
    ],
    "sg:phone":"+61 419 281 748",
    "sg:postcode":"7000",
    "sg:province":"TAS",
    "sg:tags":[
        "plumber",
        "gasfitters"
    ],
    "wof:name":"MIKE THE PLUMBER",
    "wof:placetype":"venue"
},
  "geometry": {"coordinates":[147.320068359,-42.8808708191],"type":"Point"}
}