{
  "type": "Feature",
  "properties": {
    "iso:country":"AU",
    "sg:address":"183 King St",
    "sg:city":"Newcastle",
    "sg:classifiers":[
        {
            "category":"Cinema",
            "subcategory":"Movie Theater",
            "type":"Entertainment"
        }
    ],
    "sg:phone":"+61 2 4926 2233",
    "sg:postcode":"2300",
    "sg:province":"NSW",
    "wof:name":"The Greater Union Tower Cinemas",
    "wof:placetype":"venue"
},
  "geometry": {"coordinates":[151.77641299999999,-32.927143],"type":"Point"}
}