{
  "type": "Feature",
  "properties": {
    "iso:country":"AU",
    "sg:address":"lot 5 Garabaldi Crt",
    "sg:city":"Daylesford",
    "sg:classifiers":[
        {
            "category":"Utilities",
            "subcategory":"Electric",
            "type":"Services"
        }
    ],
    "sg:phone":"+61 3 5348 4072",
    "sg:postcode":"3460",
    "sg:province":"VIC",
    "sg:tags":[
        "electrical",
        "contractor"
    ],
    "wof:name":"Daylesford Electronics & Associated Contracting",
    "wof:placetype":"venue"
},
  "geometry": {"coordinates":[144.143310547,-37.3384628296],"type":"Point"}
}