{
  "type": "Feature",
  "properties": {
    "iso:country":"AU",
    "sg:address":"23 Pitman Rd",
    "sg:city":"Windsor Gardens",
    "sg:classifiers":[
        {
            "category":"Home & Garden",
            "subcategory":"Carpets & Floor Coverings",
            "type":"Retail Goods"
        }
    ],
    "sg:phone":"+61 8 8261 6930",
    "sg:postcode":"5087",
    "sg:province":"SA",
    "sg:tags":[
        "tile",
        "wall"
    ],
    "wof:name":"Luciani Concrete Terrazzo & Tile Industries Pty Ltd",
    "wof:placetype":"venue"
},
  "geometry": {"coordinates":[138.65238952600001,-34.8626327515],"type":"Point"}
}