{
  "type": "Feature",
  "properties": {
    "addr:full":"150 Tindals Rd Donvale VIC 3111",
    "addr:housenumber":"150",
    "addr:postcode":"3111",
    "addr:street":"Tindals Rd",
    "iso:country":"AU",
    "sg:address":"150 Tindals Rd",
    "sg:city":"Donvale",
    "sg:classifiers":[
        {
            "category":"Professional",
            "subcategory":"Computer Services",
            "type":"Services"
        }
    ],
    "sg:phone":"+61 3 9844 3021",
    "sg:postcode":"3111",
    "sg:province":"VIC",
    "sg:tags":[
        "consultant",
        "system"
    ],
    "wof:name":"Ratcliff & Associates Pty Ltd",
    "wof:placetype":"venue"
},
  "geometry": {"coordinates":[145.193817139,-37.7748451233],"type":"Point"}
}