{
  "type": "Feature",
  "properties": {
    "addr:full":"Level 4 217 Clarence St Sydney NSW 2000",
    "addr:housenumber":"217",
    "addr:postcode":"2000",
    "addr:street":"Clarence St",
    "iso:country":"AU",
    "sg:address":"Level 4 217 Clarence St",
    "sg:city":"Sydney",
    "sg:classifiers":[
        {
            "category":"Organizations",
            "subcategory":"Professional Association",
            "type":"Services"
        }
    ],
    "sg:phone":"+61 2 9279 0484",
    "sg:postcode":"2000",
    "sg:province":"NSW",
    "sg:tags":[
        "organisation",
        "business"
    ],
    "wof:name":"Building Science Forum of Australia",
    "wof:placetype":"venue"
},
  "geometry": {"coordinates":[151.20529174800001,-33.8700485229],"type":"Point"}
}