{
  "type": "Feature",
  "properties": {
    "addr:full":"Cnr Phillip St Bruce Highway Mackay QLD 4740",
    "addr:postcode":"4740",
    "addr:street":"Cnr Phillip St Bruce Highway",
    "iso:country":"AU",
    "sg:address":"Cnr Phillip St",
    "sg:city":"Bruce Highway Mackay",
    "sg:classifiers":[
        {
            "category":"Travel",
            "subcategory":"Hotels & Motels",
            "type":"Entertainment"
        }
    ],
    "sg:phone":"+61 7 4942 1077",
    "sg:postcode":"4740",
    "sg:province":"QLD",
    "wof:name":"Golden Chain Motel Northview",
    "wof:placetype":"venue"
},
  "geometry": {"coordinates":[149.119125,-21.115129],"type":"Point"}
}