{
  "type": "Feature",
  "properties": {
    "addr:full":"PO Box 166 Kilsyth VIC 3137",
    "addr:postcode":"3137",
    "iso:country":"AU",
    "sg:address":"PO Box 166",
    "sg:city":"Kilsyth",
    "sg:classifiers":[
        {
            "category":"Building & Trades",
            "subcategory":"Cleaning & Sanitation",
            "type":"Services"
        }
    ],
    "sg:phone":"+61 3 9725 1322",
    "sg:postcode":"3137",
    "sg:province":"VIC",
    "sg:tags":[
        "industrial",
        "commercial",
        "contractor"
    ],
    "wof:name":"Australian Environmental Cleaning Services",
    "wof:placetype":"venue"
},
  "geometry": {"coordinates":[145.31497192399999,-37.8026504517],"type":"Point"}
}