{
  "type": "Feature",
  "properties": {
    "addr:full":"Unit 10/12- 18 Clarendon St Artarmon NSW 2064",
    "addr:housenumber":"/;18",
    "addr:postcode":"2064",
    "addr:street":"Clarendon St",
    "iso:country":"AU",
    "sg:address":"Unit 10/12- 18 Clarendon St",
    "sg:city":"Artarmon",
    "sg:classifiers":[
        {
            "category":"Home & Garden",
            "subcategory":"Furniture",
            "type":"Retail Goods"
        }
    ],
    "sg:phone":"+61 2 9438 2544",
    "sg:postcode":"2064",
    "sg:province":"NSW",
    "sg:tags":[
        "business"
    ],
    "wof:name":"Craftmaster Interiors",
    "wof:placetype":"venue"
},
  "geometry": {"coordinates":[151.183883667,-33.8162536621],"type":"Point"}
}