{
  "type": "Feature",
  "properties": {
    "addr:full":"Shp 19, Tea Tree Plz, North East Rd Modbury SA 5092",
    "addr:housenumber":"19",
    "addr:postcode":"5092",
    "addr:street":"Tea Tree Plz North East Rd",
    "iso:country":"AU",
    "sg:address":"Shp 19, Tea Tree Plz, North East Rd",
    "sg:city":"Modbury",
    "sg:classifiers":[
        {
            "category":"Retail",
            "subcategory":"Repair Shop",
            "type":"Services"
        }
    ],
    "sg:phone":"+61 8 8263 1866",
    "sg:postcode":"5092",
    "sg:province":"SA",
    "sg:tags":[
        "cleaner",
        "part",
        "vacuum"
    ],
    "wof:name":"Godfreys",
    "wof:placetype":"venue"
},
  "geometry": {"coordinates":[138.68934631400001,-34.8309783936],"type":"Point"}
}