{
  "type": "Feature",
  "properties": {
    "addr:full":"Marius St Tamworth NSW 2340",
    "addr:postcode":"2340",
    "addr:street":"Marius St",
    "iso:country":"AU",
    "sg:address":"Marius St",
    "sg:city":"Tamworth",
    "sg:classifiers":[
        {
            "category":"Organizations",
            "subcategory":"Community Association",
            "type":"Services"
        }
    ],
    "sg:phone":"+61 2 6766 8266",
    "sg:postcode":"2340",
    "sg:province":"NSW",
    "sg:tags":[
        "organisation",
        "family",
        "welfare"
    ],
    "wof:name":"Home Care Service Of NSW",
    "wof:placetype":"venue"
},
  "geometry": {"coordinates":[150.93199157699999,-31.089630127],"type":"Point"}
}