{
  "type": "Feature",
  "properties": {
    "addr:full":"42 Buchanan Rd Berwick VIC 3806",
    "addr:housenumber":"42",
    "addr:postcode":"3806",
    "addr:street":"Buchanan Rd",
    "iso:country":"AU",
    "sg:address":"42 Buchanan Rd",
    "sg:city":"Berwick",
    "sg:classifiers":[
        {
            "category":"Health Services",
            "subcategory":"Health Practitioner",
            "type":"Services"
        }
    ],
    "sg:phone":"+61 3 9796 2352",
    "sg:postcode":"3806",
    "sg:province":"VIC",
    "sg:tags":[
        "naturopath"
    ],
    "wof:name":"Berwick Natural Therapies",
    "wof:placetype":"venue"
},
  "geometry": {"coordinates":[145.35690307600001,-38.0253677368],"type":"Point"}
}