{
  "type": "Feature",
  "properties": {
    "addr:full":"3 Fulham Rd Toogoolawah QLD 4313",
    "addr:housenumber":"3",
    "addr:postcode":"4313",
    "addr:street":"Fulham Rd",
    "iso:country":"AU",
    "sg:address":"3 Fulham Rd",
    "sg:city":"Toogoolawah",
    "sg:classifiers":[
        {
            "category":"Professional",
            "type":"Services"
        }
    ],
    "sg:phone":"+61 7 5423 1990",
    "sg:postcode":"4313",
    "sg:province":"QLD",
    "sg:tags":[
        "transport"
    ],
    "wof:name":"Kleidon Transport",
    "wof:placetype":"venue"
},
  "geometry": {"coordinates":[152.42481994600001,-27.0737514496],"type":"Point"}
}