{
  "type": "Feature",
  "properties": {
    "addr:full":"Rear 253a Burke Rd Glen Iris VIC 3146",
    "addr:housenumber":"253a",
    "addr:postcode":"3146",
    "addr:street":"Burke Rd",
    "iso:country":"AU",
    "sg:address":"Rear 253a Burke Rd",
    "sg:city":"Glen Iris",
    "sg:classifiers":[
        {
            "category":"Education",
            "subcategory":"Kindergarten",
            "type":"Public Place"
        }
    ],
    "sg:phone":"+61 3 9885 4040",
    "sg:postcode":"3146",
    "sg:province":"VIC",
    "sg:tags":[
        "pre-schools"
    ],
    "wof:name":"Gardiner Pre-School",
    "wof:placetype":"venue"
},
  "geometry": {"coordinates":[145.05201721200001,-37.8549118042],"type":"Point"}
}