{
  "type": "Feature",
  "properties": {
    "iso:country":"AU",
    "sg:address":"4/ 48 Prindiville Drv",
    "sg:city":"Wangara",
    "sg:classifiers":[
        {
            "category":"Home & Garden",
            "subcategory":"Hardware",
            "type":"Retail Goods"
        }
    ],
    "sg:phone":"+61 8 9409 1335",
    "sg:postcode":"6065",
    "sg:province":"WA",
    "sg:tags":[
        "repair",
        "tool",
        "power"
    ],
    "wof:name":"Household Appliance Parts",
    "wof:placetype":"venue"
},
  "geometry": {"coordinates":[115.82386779799999,-31.7911052704],"type":"Point"}
}