{
  "type": "Feature",
  "properties": {
    "addr:full":"46 Meehan Ave Hammondville NSW 2170",
    "addr:housenumber":"46",
    "addr:postcode":"2170",
    "addr:street":"Meehan Ave",
    "iso:country":"AU",
    "sg:address":"46 Meehan Ave",
    "sg:city":"Hammondville",
    "sg:classifiers":[
        {
            "category":"Transit Center",
            "subcategory":"Freight",
            "type":"Transportation"
        }
    ],
    "sg:phone":"+61 2 9731 0000",
    "sg:postcode":"2170",
    "sg:province":"NSW",
    "sg:tags":[
        "equipment",
        "truck",
        "transport",
        "refrigerated"
    ],
    "wof:name":"Cold Van Rentals",
    "wof:placetype":"venue"
},
  "geometry": {"coordinates":[150.95048523,-33.9476776123],"type":"Point"}
}