{
  "type": "Feature",
  "properties": {
    "addr:full":"49 Atherton Rd Oakleigh VIC 3166",
    "addr:housenumber":"49",
    "addr:postcode":"3166",
    "addr:street":"Atherton Rd",
    "iso:country":"AU",
    "sg:address":"49 Atherton Rd",
    "sg:city":"Oakleigh",
    "sg:classifiers":[
        {
            "category":"Real Estate",
            "subcategory":"Real Estate Agent",
            "type":"Services"
        }
    ],
    "sg:phone":"+61 3 9568 1188",
    "sg:postcode":"3166",
    "sg:province":"VIC",
    "wof:name":"Woodards",
    "wof:placetype":"venue"
},
  "geometry": {"coordinates":[145.09127807600001,-37.9003753662],"type":"Point"}
}