{
  "type": "Feature",
  "properties": {
    "addr:full":"227 Concord Rd North Strathfield NSW 2137",
    "addr:housenumber":"227",
    "addr:postcode":"2137",
    "addr:street":"Concord Rd",
    "iso:country":"AU",
    "sg:address":"227 Concord Rd",
    "sg:city":"North Strathfield",
    "sg:classifiers":[
        {
            "category":"Health Services",
            "subcategory":"Health Practitioner",
            "type":"Services"
        }
    ],
    "sg:phone":"+61 2 9809 0106",
    "sg:postcode":"2137",
    "sg:province":"NSW",
    "sg:tags":[
        "psychologist"
    ],
    "wof:name":"Maurice Lahoud Psychologist",
    "wof:placetype":"venue"
},
  "geometry": {"coordinates":[151.09185790999999,-33.8565483093],"type":"Point"}
}