{
  "type": "Feature",
  "properties": {
    "iso:country":"AU",
    "sg:address":"205 West Coast Hwy",
    "sg:city":"Scarborough",
    "sg:classifiers":[
        {
            "category":"Retail",
            "subcategory":"Auto Rental",
            "type":"Services"
        }
    ],
    "sg:phone":"+61 8 9245 1200",
    "sg:postcode":"6019",
    "sg:province":"WA",
    "sg:tags":[
        "bus",
        "truck"
    ],
    "wof:name":"Drivewest Car Rentals",
    "wof:placetype":"venue"
},
  "geometry": {"coordinates":[115.758079529,-31.898267746],"type":"Point"}
}