{
  "type": "Feature",
  "properties": {
    "iso:country":"AU",
    "sg:address":"Lot 229 Old Mill Rd",
    "sg:city":"Wolumla",
    "sg:classifiers":[
        {
            "category":"Manufacturing",
            "subcategory":"Metals",
            "type":"Manufacturing & Wholesale Goods"
        }
    ],
    "sg:phone":"+61 2 6494 9125",
    "sg:postcode":"2550",
    "sg:province":"NSW",
    "sg:tags":[
        "fabricator",
        "aluminium"
    ],
    "wof:name":"South Coast Railings & Gates",
    "wof:placetype":"venue"
},
  "geometry": {"coordinates":[149.834716797,-36.8127365112],"type":"Point"}
}