{
  "type": "Feature",
  "properties": {
    "addr:full":"Salerno St Roma Via Isle Of Capri QLD 4217",
    "addr:postcode":"4217",
    "addr:street":"Salerno St;Via Isle;Capri",
    "iso:country":"AU",
    "sg:address":"Salerno St",
    "sg:city":"Roma Via Isle Of Capri",
    "sg:classifiers":[
        {
            "category":"Autos & Motor Vehicles",
            "subcategory":"Fuel & Gas Station",
            "type":"Retail Goods"
        }
    ],
    "sg:phone":"+61 7 5539 9713",
    "sg:postcode":"4217",
    "sg:province":"QLD",
    "wof:name":"BP Australia Limited",
    "wof:placetype":"venue"
},
  "geometry": {"coordinates":[153.421676636,-28.0137023926],"type":"Point"}
}