{
  "type": "Feature",
  "properties": {
    "addr:full":"8 Sunshine Beach Rd Noosa Heads QLD 4567",
    "addr:housenumber":"8",
    "addr:postcode":"4567",
    "addr:street":"Sunshine Beach Rd",
    "iso:country":"AU",
    "sg:address":"8 Sunshine Beach Rd",
    "sg:city":"Noosa Heads",
    "sg:classifiers":[
        {
            "category":"Professional",
            "subcategory":"Business Services",
            "type":"Services"
        }
    ],
    "sg:phone":"+61 412 715 610",
    "sg:postcode":"4567",
    "sg:province":"QLD",
    "sg:tags":[
        "fashion",
        "agent"
    ],
    "wof:name":"The Avalon Fashion Agency",
    "wof:placetype":"venue"
},
  "geometry": {"coordinates":[153.09146118199999,-26.3977680206],"type":"Point"}
}