{
  "type": "Feature",
  "properties": {
    "addr:full":"78 Irvine St Kingsford NSW 2032",
    "addr:housenumber":"78",
    "addr:postcode":"2032",
    "addr:street":"Irvine St",
    "iso:country":"AU",
    "sg:address":"78 Irvine St",
    "sg:city":"Kingsford",
    "sg:classifiers":[
        {
            "category":"Building & Trades",
            "subcategory":"Plumbing",
            "type":"Services"
        }
    ],
    "sg:phone":"+61 412 026 726",
    "sg:postcode":"2032",
    "sg:province":"NSW",
    "sg:tags":[
        "plumber",
        "gasfitters"
    ],
    "wof:name":"Georges Kingsford Plumbing Service",
    "wof:placetype":"venue"
},
  "geometry": {"coordinates":[151.23362731899999,-33.9337654114],"type":"Point"}
}