{
  "type": "Feature",
  "properties": {
    "addr:full":"Unit 2, 4 Carole Rd Maddington WA 6109",
    "addr:housenumber":"4",
    "addr:postcode":"6109",
    "addr:street":"Carole Rd",
    "iso:country":"AU",
    "sg:address":"Unit 2, 4 Carole Rd",
    "sg:city":"Maddington",
    "sg:classifiers":[
        {
            "category":"Retail",
            "subcategory":"Auto Repair",
            "type":"Services"
        }
    ],
    "sg:phone":"+61 8 9459 0492",
    "sg:postcode":"6109",
    "sg:province":"WA",
    "sg:tags":[
        "repairer",
        "motor",
        "engineer"
    ],
    "wof:name":"Waverley Auto Service Centre",
    "wof:placetype":"venue"
},
  "geometry": {"coordinates":[115.981719971,-32.0461997986],"type":"Point"}
}