{
  "type": "Feature",
  "properties": {
    "addr:full":"214 Rundle St Adelaide SA 5000",
    "addr:housenumber":"214",
    "addr:postcode":"5000",
    "addr:street":"Rundle St",
    "iso:country":"AU",
    "sg:address":"214 Rundle St",
    "sg:city":"Adelaide",
    "sg:classifiers":[
        {
            "category":"Shopping",
            "subcategory":"Hobbies, Toys, & Games",
            "type":"Retail Goods"
        }
    ],
    "sg:phone":"+61 8 8232 9708",
    "sg:postcode":"5000",
    "sg:province":"SA",
    "sg:tags":[
        "stamp"
    ],
    "wof:name":"Unley Coins & Stamps",
    "wof:placetype":"venue"
},
  "geometry": {"coordinates":[138.60728454599999,-34.9224624634],"type":"Point"}
}