{
  "type": "Feature",
  "properties": {
    "iso:country":"AU",
    "sg:address":"U31/ 225 Beaconsfield Pde",
    "sg:city":"Middle Park",
    "sg:classifiers":[
        {
            "category":"Professional",
            "subcategory":"Management & Consulting",
            "type":"Services"
        }
    ],
    "sg:phone":"+61 3 9686 9462",
    "sg:postcode":"3206",
    "sg:province":"VIC",
    "sg:tags":[
        "consultant"
    ],
    "wof:name":"Hobson Bay Consulting Pty Ltd",
    "wof:placetype":"venue"
},
  "geometry": {"coordinates":[144.959625,-37.852867],"type":"Point"}
}