{
  "type": "Feature",
  "properties": {
    "addr:full":"Shop 8 Pioneer Vlge Armadale WA 6112",
    "addr:housenumber":"shop 8",
    "addr:postcode":"6112",
    "addr:street":"Pioneer Vlge",
    "iso:country":"AU",
    "sg:address":"Shop 8 Pioneer Vlge",
    "sg:city":"Armadale",
    "sg:classifiers":[
        {
            "category":"Health Services",
            "subcategory":"Clinic",
            "type":"Services"
        }
    ],
    "sg:phone":"+61 8 9498 2448",
    "sg:postcode":"6112",
    "sg:province":"WA",
    "sg:tags":[
        "aromatherapy"
    ],
    "wof:name":"Red Earth Angel",
    "wof:placetype":"venue"
},
  "geometry": {"coordinates":[116.02057647700001,-32.1510009766],"type":"Point"}
}