{
  "type": "Feature",
  "properties": {
    "iso:country":"AU",
    "sg:address":"PO Box 717",
    "sg:city":"Ballarat Forward",
    "sg:classifiers":[
        {
            "category":"Professional",
            "subcategory":"Employment Agencies",
            "type":"Services"
        }
    ],
    "sg:phone":"+61 3 5332 9955",
    "sg:postcode":"3352",
    "sg:province":"VIC",
    "wof:name":"JK Personnel Pty Ltd",
    "wof:placetype":"venue"
},
  "geometry": {"coordinates":[143.89198300000001,-37.435986],"type":"Point"}
}