{
  "type": "Feature",
  "properties": {
    "iso:country":"AU",
    "sg:address":"Shop 1, 128 Garden St",
    "sg:city":"Maroubra",
    "sg:classifiers":[
        {
            "category":"Personal",
            "subcategory":"Nail Salon",
            "type":"Services"
        }
    ],
    "sg:phone":"+61 2 9344 4612",
    "sg:postcode":"2035",
    "sg:province":"NSW",
    "sg:tags":[
        "artificial"
    ],
    "wof:name":"L.A. Nails & Beauty",
    "wof:placetype":"venue"
},
  "geometry": {"coordinates":[151.241455078,-33.9416503906],"type":"Point"}
}