{
  "type": "Feature",
  "properties": {
    "addr:full":"Greenlake Rd Parkhurst QLD 4702",
    "addr:postcode":"4702",
    "addr:street":"Greenlake Rd",
    "iso:country":"AU",
    "sg:address":"Greenlake Rd",
    "sg:city":"Parkhurst",
    "sg:classifiers":[
        {
            "category":"Building & Trades",
            "subcategory":"Landscaping Services",
            "type":"Services"
        }
    ],
    "sg:phone":"+61 7 4936 1584",
    "sg:postcode":"4702",
    "sg:province":"QLD",
    "sg:tags":[
        "grazier"
    ],
    "wof:name":"Beak R",
    "wof:placetype":"venue"
},
  "geometry": {"coordinates":[150.49810790999999,-23.2506256104],"type":"Point"}
}