{
  "type": "Feature",
  "properties": {
    "iso:country":"AU",
    "sg:address":"15 Richard Rd",
    "sg:city":"Melton South",
    "sg:classifiers":[
        {
            "category":"Building & Trades",
            "subcategory":"Construction",
            "type":"Services"
        }
    ],
    "sg:phone":"+61 3 9743 2364",
    "sg:postcode":"3338",
    "sg:province":"VIC",
    "sg:tags":[
        "spouting",
        "guttering"
    ],
    "wof:name":"Pekka's Gutters",
    "wof:placetype":"venue"
},
  "geometry": {"coordinates":[144.573563,-37.695347],"type":"Point"}
}