{
  "type": "Feature",
  "properties": {
    "addr:full":"John Fisher Ave Gumeracha SA 5233",
    "addr:postcode":"5233",
    "addr:street":"Ave",
    "iso:country":"AU",
    "sg:address":"John Fisher Ave",
    "sg:city":"Gumeracha",
    "sg:classifiers":[
        {
            "category":"Social Services",
            "subcategory":"Child Care",
            "type":"Services"
        }
    ],
    "sg:phone":"+61 8 8389 1335",
    "sg:postcode":"5233",
    "sg:province":"SA",
    "wof:name":"Torrens Valley Children's Centre",
    "wof:placetype":"venue"
},
  "geometry": {"coordinates":[138.88519287099999,-34.824005127],"type":"Point"}
}