{
  "type": "Feature",
  "properties": {
    "addr:full":"6 Lockett Drv Warrnambool VIC 3280",
    "addr:housenumber":"6",
    "addr:postcode":"3280",
    "addr:street":"Lockett Drv",
    "iso:country":"AU",
    "sg:address":"6 Lockett Drv",
    "sg:city":"Warrnambool",
    "sg:classifiers":[
        {
            "category":"Building & Trades",
            "subcategory":"Plumbing",
            "type":"Services"
        }
    ],
    "sg:phone":"+61 3 5561 1776",
    "sg:postcode":"3280",
    "sg:province":"VIC",
    "sg:tags":[
        "plumber",
        "gasfitters"
    ],
    "wof:name":"Langston James",
    "wof:placetype":"venue"
},
  "geometry": {"coordinates":[142.50932312,-38.3673477173],"type":"Point"}
}