{
  "type": "Feature",
  "properties": {
    "addr:full":"38 Lockhard Drv Rosebud VIC 3939",
    "addr:housenumber":"38",
    "addr:postcode":"3939",
    "addr:street":"Lockhard Drv",
    "iso:country":"AU",
    "sg:address":"38 Lockhard Drv",
    "sg:city":"Rosebud",
    "sg:classifiers":[
        {
            "category":"Education",
            "subcategory":"School",
            "type":"Public Place"
        }
    ],
    "sg:phone":"+61 3 5982 1689",
    "sg:postcode":"3939",
    "sg:province":"VIC",
    "sg:tags":[
        "supply"
    ],
    "wof:name":"Prac-Ed Supply",
    "wof:placetype":"venue"
},
  "geometry": {"coordinates":[144.894042969,-38.3779373169],"type":"Point"}
}