{
  "type": "Feature",
  "properties": {
    "iso:country":"AU",
    "sg:address":"Unit 1, 80 Zillmere Rd",
    "sg:city":"Geebung",
    "sg:classifiers":[
        {
            "category":"Industrial Area",
            "type":"Public Place"
        }
    ],
    "sg:phone":"+61 7 3265 1877",
    "sg:postcode":"4034",
    "sg:province":"QLD",
    "sg:tags":[
        "protective",
        "clothing"
    ],
    "wof:name":"Work Wise Uniforms",
    "wof:placetype":"venue"
},
  "geometry": {"coordinates":[153.05775499999999,-27.362444],"type":"Point"}
}