{
  "type": "Feature",
  "properties": {
    "addr:full":"9 Aminya Pl Orange NSW 2800",
    "addr:housenumber":"9",
    "addr:postcode":"2800",
    "addr:street":"Aminya Pl",
    "iso:country":"AU",
    "sg:address":"9 Aminya Pl",
    "sg:city":"Orange",
    "sg:classifiers":[
        {
            "category":"Building & Trades",
            "subcategory":"Cleaning & Sanitation",
            "type":"Services"
        }
    ],
    "sg:phone":"+61 2 6361 0202",
    "sg:postcode":"2800",
    "sg:province":"NSW",
    "sg:tags":[
        "cleaner",
        "repairer",
        "roof"
    ],
    "wof:name":"Roofsheen P/L",
    "wof:placetype":"venue"
},
  "geometry": {"coordinates":[149.07614135700001,-33.2752952576],"type":"Point"}
}