{
  "type": "Feature",
  "properties": {
    "addr:full":"Unit 3, 51 Stephen Tce St Peters SA 5069",
    "addr:housenumber":"51",
    "addr:postcode":"5069",
    "addr:street":"Stephen Tce",
    "iso:country":"AU",
    "sg:address":"Unit 3, 51 Stephen Tce St",
    "sg:city":"Peters",
    "sg:classifiers":[
        {
            "category":"Banks & Credit Unions",
            "subcategory":"Investment Brokerage",
            "type":"Services"
        }
    ],
    "sg:phone":"+61 8 8362 2477",
    "sg:postcode":"5069",
    "sg:province":"SA",
    "wof:name":"Haarsma Des",
    "wof:placetype":"venue"
},
  "geometry": {"coordinates":[138.623504639,-34.9047203064],"type":"Point"}
}