{
  "type": "Feature",
  "properties": {
    "iso:country":"AU",
    "sg:address":"1 Rankin St",
    "sg:city":"Bathurst",
    "sg:classifiers":[
        {
            "category":"Home & Garden",
            "subcategory":"Building Materials",
            "type":"Retail Goods"
        }
    ],
    "sg:phone":"+61 2 6331 4697",
    "sg:postcode":"2795",
    "sg:province":"NSW",
    "sg:tags":[
        "secondhand"
    ],
    "wof:name":"Bathurst Recycled Building Materials",
    "wof:placetype":"venue"
},
  "geometry": {"coordinates":[149.58360290499999,-33.4103317261],"type":"Point"}
}