{
  "type": "Feature",
  "properties": {
    "addr:full":"93 Anderson St Yarraville VIC 3013",
    "addr:housenumber":"93",
    "addr:postcode":"3013",
    "addr:street":"Anderson St",
    "iso:country":"AU",
    "sg:address":"93 Anderson St",
    "sg:city":"Yarraville",
    "sg:classifiers":[
        {
            "category":"Health Services",
            "subcategory":"Doctor",
            "type":"Services"
        }
    ],
    "sg:phone":"+61 3 9314 7675",
    "sg:postcode":"3013",
    "sg:province":"VIC",
    "sg:tags":[
        "medical",
        "practitioner"
    ],
    "wof:name":"A Yarraville Village Family Medical Centre",
    "wof:placetype":"venue"
},
  "geometry": {"coordinates":[144.88807678200001,-37.8164558411],"type":"Point"}
}