{
  "type": "Feature",
  "properties": {
    "addr:full":"27 Enright St Beresfield NSW 2322",
    "addr:housenumber":"27",
    "addr:postcode":"2322",
    "addr:street":"Enright St",
    "iso:country":"AU",
    "sg:address":"27 Enright St",
    "sg:city":"Beresfield",
    "sg:classifiers":[
        {
            "category":"Retail",
            "subcategory":"Storage",
            "type":"Services"
        }
    ],
    "sg:phone":"+61 2 4966 5324",
    "sg:postcode":"2322",
    "sg:province":"NSW",
    "sg:tags":[
        "removal",
        "furniture"
    ],
    "wof:name":"Willmott K",
    "wof:placetype":"venue"
},
  "geometry": {"coordinates":[151.64663696299999,-32.8052940369],"type":"Point"}
}