{
  "type": "Feature",
  "properties": {
    "addr:full":"36 Eric St Cottesloe WA 6011",
    "addr:housenumber":"36",
    "addr:postcode":"6011",
    "addr:street":"Eric St",
    "iso:country":"AU",
    "sg:address":"36 Eric St",
    "sg:city":"Cottesloe",
    "sg:classifiers":[
        {
            "category":"Food & Beverages",
            "subcategory":"Supermarket",
            "type":"Retail Goods"
        }
    ],
    "sg:phone":"+61 8 9383 1808",
    "sg:postcode":"6011",
    "sg:province":"WA",
    "sg:tags":[
        "grocery",
        "store"
    ],
    "wof:name":"IGA Supermarkets",
    "wof:placetype":"venue"
},
  "geometry": {"coordinates":[115.756896973,-31.9894657135],"type":"Point"}
}