{
  "type": "Feature",
  "properties": {
    "addr:full":"7 Cromarty Crs Anna Bay NSW 2316",
    "addr:housenumber":"7",
    "addr:postcode":"2316",
    "addr:street":"Cromarty Crs Anna Bay",
    "iso:country":"AU",
    "sg:address":"7 Cromarty Crs",
    "sg:city":"Anna Bay",
    "sg:classifiers":[
        {
            "category":"Building & Trades",
            "subcategory":"Landscaping Services",
            "type":"Services"
        }
    ],
    "sg:phone":"+61 2 4982 2330",
    "sg:postcode":"2316",
    "sg:province":"NSW",
    "sg:tags":[
        "designer",
        "landscape",
        "contractor"
    ],
    "wof:name":"Australian Tropical Landscapes",
    "wof:placetype":"venue"
},
  "geometry": {"coordinates":[152.08521999999999,-32.777599],"type":"Point"}
}