{
  "type": "Feature",
  "properties": {
    "iso:country":"AU",
    "sg:address":"PO Box 763",
    "sg:city":"Aspley",
    "sg:classifiers":[
        {
            "category":"Utilities",
            "subcategory":"Electric",
            "type":"Services"
        }
    ],
    "sg:phone":"+61 402 821 958",
    "sg:postcode":"4034",
    "sg:province":"QLD",
    "sg:tags":[
        "electrical",
        "contractor"
    ],
    "wof:name":"Fusion Electrical Services Pty Ltd",
    "wof:placetype":"venue"
},
  "geometry": {"coordinates":[153.019653,-27.36422],"type":"Point"}
}