{
  "type": "Feature",
  "properties": {
    "addr:full":"3/ 39 Elder St Alice Springs NT 0870",
    "addr:housenumber":"/ 39",
    "addr:postcode":"nt 0870",
    "addr:street":"Elder St",
    "iso:country":"AU",
    "sg:address":"3/ 39 Elder St",
    "sg:city":"Alice Springs",
    "sg:classifiers":[
        {
            "category":"Professional",
            "subcategory":"Printing & Photocopies",
            "type":"Services"
        }
    ],
    "sg:phone":"+61 8 8952 2919",
    "sg:postcode":"0870",
    "sg:province":"NT",
    "sg:tags":[
        "screen",
        "printer"
    ],
    "wof:name":"M & M Designs",
    "wof:placetype":"venue"
},
  "geometry": {"coordinates":[133.86703491200001,-23.6960906982],"type":"Point"}
}