{
  "type": "Feature",
  "properties": {
    "addr:full":"161 Fallon St Albury NSW 2640",
    "addr:housenumber":"161",
    "addr:postcode":"2640",
    "addr:street":"Fallon St",
    "iso:country":"AU",
    "sg:address":"161 Fallon St",
    "sg:city":"Albury",
    "sg:classifiers":[
        {
            "category":"Professional",
            "subcategory":"Engineering",
            "type":"Services"
        }
    ],
    "sg:phone":"+61 2 6040 1700",
    "sg:postcode":"2640",
    "sg:province":"NSW",
    "sg:tags":[
        "consulting",
        "engineer"
    ],
    "wof:name":"Australian Target Systems Pty Ltd",
    "wof:placetype":"venue"
},
  "geometry": {"coordinates":[146.927642822,-36.0623016357],"type":"Point"}
}