{
  "type": "Feature",
  "properties": {
    "addr:full":"8 Spence St Warrnambool VIC 3280",
    "addr:housenumber":"8",
    "addr:postcode":"3280",
    "addr:street":"Spence St",
    "iso:country":"AU",
    "sg:address":"8 Spence St",
    "sg:city":"Warrnambool",
    "sg:classifiers":[
        {
            "category":"Travel",
            "subcategory":"Hotels & Motels",
            "type":"Entertainment"
        }
    ],
    "sg:phone":"+61 3 5562 7144",
    "sg:postcode":"3280",
    "sg:province":"VIC",
    "wof:name":"Atwood Motor Inn",
    "wof:placetype":"venue"
},
  "geometry": {"coordinates":[142.48544311500001,-38.3796653748],"type":"Point"}
}