{
  "type": "Feature",
  "properties": {
    "addr:full":"Shop 1083 Centro Galleria Morley WA 6062",
    "addr:housenumber":"1083",
    "addr:postcode":"6062",
    "addr:street":"Galleria",
    "iso:country":"AU",
    "sg:address":"Shop 1083",
    "sg:city":"Centro Galleria Morley",
    "sg:classifiers":[
        {
            "category":"Personal",
            "subcategory":"Beauty Salon",
            "type":"Services"
        }
    ],
    "sg:phone":"+61 8 9375 7221",
    "sg:postcode":"6062",
    "sg:province":"WA",
    "sg:tags":[
        "hairdresser"
    ],
    "wof:name":"Just Cuts",
    "wof:placetype":"venue"
},
  "geometry": {"coordinates":[115.896888733,-31.8942699432],"type":"Point"}
}