{
  "type": "Feature",
  "properties": {
    "addr:full":"PO Box 1453 Bibra Lake DC WA 6965",
    "addr:postcode":"6965",
    "iso:country":"AU",
    "sg:address":"PO Box 1453",
    "sg:city":"Bibra Lake DC",
    "sg:classifiers":[
        {
            "category":"Professional",
            "subcategory":"Detective & Security Services",
            "type":"Services"
        }
    ],
    "sg:phone":"+61 8 9494 1713",
    "sg:postcode":"6965",
    "sg:province":"WA",
    "sg:tags":[
        "guard",
        "patrol"
    ],
    "wof:name":"Paramount Security Services",
    "wof:placetype":"venue"
},
  "geometry": {"coordinates":[115.837479,-32.09296],"type":"Point"}
}