{
  "type": "Feature",
  "properties": {
    "iso:country":"AU",
    "sg:address":"Ste1/ 41 Pacific Hwy",
    "sg:city":"Waitara",
    "sg:classifiers":[
        {
            "category":"Organizations",
            "subcategory":"Non-profit Organization",
            "type":"Services"
        }
    ],
    "sg:phone":"+61 2 9487 5088",
    "sg:postcode":"2077",
    "sg:province":"NSW",
    "sg:tags":[
        "support",
        "disability",
        "organisation"
    ],
    "wof:name":"Coeliac Society Of NSW Inc The",
    "wof:placetype":"venue"
},
  "geometry": {"coordinates":[151.10398864699999,-33.710849762],"type":"Point"}
}