{
  "type": "Feature",
  "properties": {
    "addr:full":"237 Nicholson St Carlton VIC 3053",
    "addr:housenumber":"237",
    "addr:postcode":"3053",
    "addr:street":"Nicholson St",
    "iso:country":"AU",
    "sg:address":"237 Nicholson St",
    "sg:city":"Carlton",
    "sg:classifiers":[
        {
            "category":"Food & Beverages",
            "subcategory":"Bakery",
            "type":"Retail Goods"
        }
    ],
    "sg:phone":"+61 3 9347 7311",
    "sg:postcode":"3053",
    "sg:province":"VIC",
    "sg:tags":[
        "cake",
        "shop",
        "pastry"
    ],
    "wof:name":"French Lettuce The",
    "wof:placetype":"venue"
},
  "geometry": {"coordinates":[144.97525024399999,-37.7944412231],"type":"Point"}
}