{
  "type": "Feature",
  "properties": {
    "iso:country":"AU",
    "sg:address":"223 Carlton River Rd",
    "sg:city":"Carlton Beach",
    "sg:classifiers":[
        {
            "category":"Social Services",
            "subcategory":"Child Care",
            "type":"Services"
        }
    ],
    "sg:phone":"+61 3 6265 9267",
    "sg:postcode":"7173",
    "sg:province":"TAS",
    "wof:name":"Sandcastles",
    "wof:placetype":"venue"
},
  "geometry": {"coordinates":[147.638473511,-42.8715934753],"type":"Point"}
}