{
  "type": "Feature",
  "properties": {
    "iso:country":"AU",
    "sg:address":"Shop 29, Grand Plaza S/C Brown Plains Rd",
    "sg:city":"Browns Plains",
    "sg:classifiers":[
        {
            "category":"Food & Beverages",
            "subcategory":"Specialty",
            "type":"Retail Goods"
        }
    ],
    "sg:phone":"+61 7 3800 7811",
    "sg:postcode":"4118",
    "sg:province":"QLD",
    "sg:tags":[
        "product",
        "health"
    ],
    "wof:name":"Healthy Life",
    "wof:placetype":"venue"
},
  "geometry": {"coordinates":[153.03828430199999,-27.664434433],"type":"Point"}
}