{
  "type": "Feature",
  "properties": {
    "addr:full":"2327 Point Nepean Rd Rye VIC 3941",
    "addr:housenumber":"2327",
    "addr:postcode":"3941",
    "addr:street":"Point Nepean Rd",
    "iso:country":"AU",
    "sg:address":"2327 Point Nepean Rd",
    "sg:city":"Rye",
    "sg:classifiers":[
        {
            "category":"Cafe",
            "type":"Food & Drink"
        }
    ],
    "sg:phone":"+61 3 5985 9944",
    "sg:postcode":"3941",
    "sg:province":"VIC",
    "wof:name":"Anthonys Italian Cafe",
    "wof:placetype":"venue"
},
  "geometry": {"coordinates":[144.82437133799999,-38.3706855774],"type":"Point"}
}