{
  "type": "Feature",
  "properties": {
    "iso:country":"AU",
    "sg:address":"251 Lang St",
    "sg:city":"Kurri Kurri",
    "sg:classifiers":[
        {
            "category":"Education",
            "subcategory":"University",
            "type":"Public Place"
        }
    ],
    "sg:phone":"+61 2 4936 2622",
    "sg:postcode":"2327",
    "sg:province":"NSW",
    "sg:tags":[
        "educational",
        "organisation",
        "cultural"
    ],
    "wof:name":"WEA Hunter",
    "wof:placetype":"venue"
},
  "geometry": {"coordinates":[151.47901916500001,-32.8198127747],"type":"Point"}
}