{
  "type": "Feature",
  "properties": {
    "addr:full":"38 Grantham St Brunswick VIC 3056",
    "addr:housenumber":"38",
    "addr:postcode":"3056",
    "addr:street":"Grantham St",
    "iso:country":"AU",
    "sg:address":"38 Grantham St",
    "sg:city":"Brunswick",
    "sg:classifiers":[
        {
            "category":"Food & Beverages",
            "subcategory":"Bakery",
            "type":"Retail Goods"
        }
    ],
    "sg:phone":"+61 3 9388 8996",
    "sg:postcode":"3056",
    "sg:province":"VIC",
    "sg:tags":[
        "baker"
    ],
    "wof:name":"Village Bakery Brunswick The",
    "wof:placetype":"venue"
},
  "geometry": {"coordinates":[144.94956970199999,-37.7722663879],"type":"Point"}
}