{
  "type": "Feature",
  "properties": {
    "addr:full":"Magill Rd Magill SA 5072",
    "addr:postcode":"5072",
    "addr:street":"Magill Rd",
    "iso:country":"AU",
    "sg:address":"Magill Rd",
    "sg:city":"Magill",
    "sg:classifiers":[
        {
            "category":"Building & Trades",
            "subcategory":"Cleaning & Sanitation",
            "type":"Services"
        }
    ],
    "sg:phone":"+61 8 8366 0621",
    "sg:postcode":"5072",
    "sg:province":"SA",
    "sg:tags":[
        "window"
    ],
    "wof:name":"We Clean Windows",
    "wof:placetype":"venue"
},
  "geometry": {"coordinates":[138.67544555699999,-34.9130554199],"type":"Point"}
}