{
  "type": "Feature",
  "properties": {
    "addr:full":"21 Stony Rise Rd Devonport TAS 7310",
    "addr:housenumber":"21",
    "addr:postcode":"7310",
    "addr:street":"Stony Rise Rd",
    "iso:country":"AU",
    "sg:address":"21 Stony Rise Rd",
    "sg:city":"Devonport",
    "sg:classifiers":[
        {
            "category":"Government",
            "subcategory":"Fire Station",
            "type":"Public Place"
        }
    ],
    "sg:phone":"+61 3 6424 7666",
    "sg:postcode":"7310",
    "sg:province":"TAS",
    "sg:tags":[
        "equipment",
        "protection",
        "consultant"
    ],
    "wof:name":"Tasmanian Fire Doors",
    "wof:placetype":"venue"
},
  "geometry": {"coordinates":[146.34385681099999,-41.2072906494],"type":"Point"}
}