{
  "type": "Feature",
  "properties": {
    "addr:full":"8a Humeside Drv Campbellfield VIC 3061",
    "addr:housenumber":"8a",
    "addr:postcode":"3061",
    "addr:street":"Humeside Drv",
    "iso:country":"AU",
    "sg:address":"8a Humeside Drv",
    "sg:city":"Campbellfield",
    "sg:classifiers":[
        {
            "category":"Home & Garden",
            "subcategory":"Furniture",
            "type":"Retail Goods"
        }
    ],
    "sg:phone":"+61 417 012 728",
    "sg:postcode":"3061",
    "sg:province":"VIC",
    "sg:tags":[
        "business"
    ],
    "wof:name":"Mark Perry Pty Ltd",
    "wof:placetype":"venue"
},
  "geometry": {"coordinates":[144.96383667000001,-37.6706848145],"type":"Point"}
}