{
  "type": "Feature",
  "properties": {
    "addr:full":"2 Candlebark Crs Morayfield QLD 4506",
    "addr:housenumber":"2",
    "addr:postcode":"4506",
    "addr:street":"Candlebark Crs",
    "iso:country":"AU",
    "sg:address":"2 Candlebark Crs",
    "sg:city":"Morayfield",
    "sg:classifiers":[
        {
            "category":"Building & Trades",
            "subcategory":"Construction",
            "type":"Services"
        }
    ],
    "sg:phone":"+61 7 3888 1802",
    "sg:postcode":"4506",
    "sg:province":"QLD",
    "sg:tags":[
        "contractor"
    ],
    "wof:name":"G R Wood Homes Pty Ltd",
    "wof:placetype":"venue"
},
  "geometry": {"coordinates":[152.94992065400001,-27.1089096069],"type":"Point"}
}