{
  "type": "Feature",
  "properties": {
    "addr:full":"9 Galvin St Harvey WA 6220",
    "addr:housenumber":"9",
    "addr:postcode":"6220",
    "addr:street":"Galvin St",
    "iso:country":"AU",
    "sg:address":"9 Galvin St",
    "sg:city":"Harvey",
    "sg:classifiers":[
        {
            "category":"Building & Trades",
            "subcategory":"Landscaping Services",
            "type":"Services"
        }
    ],
    "sg:phone":"+61 412 427 390",
    "sg:postcode":"6220",
    "sg:province":"WA",
    "sg:tags":[
        "stump",
        "tree",
        "felling",
        "removal"
    ],
    "wof:name":"Regional Tree Lopping",
    "wof:placetype":"venue"
},
  "geometry": {"coordinates":[115.88913700000001,-33.082863],"type":"Point"}
}