{
  "type": "Feature",
  "properties": {
    "addr:full":"19 Thompson St Ascot WA 6104",
    "addr:housenumber":"19",
    "addr:postcode":"6104",
    "addr:street":"Thompson St",
    "iso:country":"AU",
    "sg:address":"19 Thompson St",
    "sg:city":"Ascot",
    "sg:classifiers":[
        {
            "category":"Organizations",
            "subcategory":"Labor Organization",
            "type":"Services"
        }
    ],
    "sg:phone":"+61 8 9277 3505",
    "sg:postcode":"6104",
    "sg:province":"WA",
    "sg:tags":[
        "polishing",
        "stone",
        "machinery",
        "working"
    ],
    "wof:name":"Mediterranean Hard Floor Polishers",
    "wof:placetype":"venue"
},
  "geometry": {"coordinates":[115.933959961,-31.9321708679],"type":"Point"}
}