{
  "type": "Feature",
  "properties": {
    "addr:full":"135 Hannan St Kalgoorlie WA 6430",
    "addr:housenumber":"135",
    "addr:postcode":"6430",
    "addr:street":"Hannan St",
    "iso:country":"AU",
    "sg:address":"135 Hannan St",
    "sg:city":"Kalgoorlie",
    "sg:classifiers":[
        {
            "category":"Travel",
            "subcategory":"Hotels & Motels",
            "type":"Entertainment"
        }
    ],
    "sg:phone":"+61 8 9021 2833",
    "sg:postcode":"6430",
    "sg:province":"WA",
    "sg:tags":[
        "accommodation"
    ],
    "wof:name":"Paddy's Ale House Irish Pub",
    "wof:placetype":"venue"
},
  "geometry": {"coordinates":[121.46733856199999,-30.7519664764],"type":"Point"}
}