{
  "type": "Feature",
  "properties": {
    "iso:country":"AU",
    "sg:address":"24 Suzana Pl",
    "sg:city":"Rowville",
    "sg:classifiers":[
        {
            "category":"Real Estate",
            "subcategory":"Surveying",
            "type":"Services"
        }
    ],
    "sg:phone":"+61 3 9755 6883",
    "sg:postcode":"3178",
    "sg:province":"VIC",
    "sg:tags":[
        "surveyor",
        "land"
    ],
    "wof:name":"South East Surveys",
    "wof:placetype":"venue"
},
  "geometry": {"coordinates":[145.25128173799999,-37.9326286316],"type":"Point"}
}