{
  "type": "Feature",
  "properties": {
    "addr:full":"Rigters 179 Durlacher St Geraldton WA 6530",
    "addr:housenumber":"179",
    "addr:postcode":"6530",
    "addr:street":"Rigters;Durlacher St",
    "iso:country":"AU",
    "sg:address":"Rigters 179 Durlacher St",
    "sg:city":"Geraldton",
    "sg:classifiers":[
        {
            "category":"Food & Beverages",
            "subcategory":"Supermarket",
            "type":"Retail Goods"
        }
    ],
    "sg:phone":"+61 8 9921 2307",
    "sg:postcode":"6530",
    "sg:province":"WA",
    "sg:tags":[
        "grocery",
        "store"
    ],
    "wof:name":"IGA Supermarkets",
    "wof:placetype":"venue"
},
  "geometry": {"coordinates":[114.61753845200001,-28.7813625336],"type":"Point"}
}