{
  "type": "Feature",
  "properties": {
    "iso:country":"AU",
    "sg:address":"1/ 25 Manuka Circle",
    "sg:city":"Forrest",
    "sg:classifiers":[
        {
            "category":"Health Services",
            "subcategory":"Health Practitioner",
            "type":"Services"
        }
    ],
    "sg:phone":"+61 2 6260 6733",
    "sg:postcode":"2603",
    "sg:province":"ACT",
    "sg:tags":[
        "osteopath"
    ],
    "wof:name":"Patrick Carr",
    "wof:placetype":"venue"
},
  "geometry": {"coordinates":[149.132904053,-35.3170928955],"type":"Point"}
}