{
  "type": "Feature",
  "properties": {
    "iso:country":"AU",
    "sg:address":"1/ 12 Salisbury Rd",
    "sg:city":"Hornsby",
    "sg:classifiers":[
        {
            "category":"Communications",
            "type":"Services"
        }
    ],
    "sg:phone":"+61 418 973 250",
    "sg:postcode":"2077",
    "sg:province":"NSW",
    "sg:tags":[
        "public",
        "system",
        "address"
    ],
    "wof:name":"Ramsaudio Pty Ltd",
    "wof:placetype":"venue"
},
  "geometry": {"coordinates":[151.11135864299999,-33.6965789795],"type":"Point"}
}