{
  "type": "Feature",
  "properties": {
    "addr:full":"2/ 1-9 Kurnall Rd Welshpool WA 6106",
    "addr:housenumber":"/ 1-9",
    "addr:postcode":"6106",
    "addr:street":"Kurnall Rd",
    "iso:country":"AU",
    "sg:address":"2/ 1-9 Kurnall Rd",
    "sg:city":"Welshpool",
    "sg:classifiers":[
        {
            "category":"Building & Trades",
            "subcategory":"Equipment Rental",
            "type":"Services"
        }
    ],
    "sg:phone":"+61 8 6253 1900",
    "sg:postcode":"6106",
    "sg:province":"WA",
    "sg:tags":[
        "repairing",
        "changing",
        "retreading",
        "tyre"
    ],
    "wof:name":"Rema Tip Top Aust Pty Ltd",
    "wof:placetype":"venue"
},
  "geometry": {"coordinates":[115.95516204800001,-31.9953804016],"type":"Point"}
}