{
  "type": "Feature",
  "properties": {
    "addr:full":"96 Lower Mountain Rd Hervey Bay QLD 4655",
    "addr:housenumber":"96",
    "addr:postcode":"4655",
    "addr:street":"Lower Mountain Rd",
    "iso:country":"AU",
    "sg:address":"96 Lower Mountain Rd",
    "sg:city":"Hervey Bay",
    "sg:classifiers":[
        {
            "category":"Retail",
            "subcategory":"Auto Repair",
            "type":"Services"
        }
    ],
    "sg:phone":"+61 7 4124 5425",
    "sg:postcode":"4655",
    "sg:province":"QLD",
    "sg:tags":[
        "bus",
        "truck"
    ],
    "wof:name":"Bozmac",
    "wof:placetype":"venue"
},
  "geometry": {"coordinates":[152.79960600000001,-25.2992],"type":"Point"}
}