{
  "type": "Feature",
  "properties": {
    "addr:full":"187 Victoria Ave Albert Park VIC 3206",
    "addr:housenumber":"187",
    "addr:postcode":"3206",
    "addr:street":"Victoria Ave",
    "iso:country":"AU",
    "sg:address":"187 Victoria Ave",
    "sg:city":"Albert Park",
    "sg:classifiers":[
        {
            "category":"Fast Food",
            "type":"Food & Drink"
        }
    ],
    "sg:phone":"+61 3 9696 1651",
    "sg:postcode":"3206",
    "sg:province":"VIC",
    "sg:tags":[
        "away",
        "take"
    ],
    "wof:name":"Mussell Fish & Chippery",
    "wof:placetype":"venue"
},
  "geometry": {"coordinates":[144.948883,-37.847195],"type":"Point"}
}