{
  "type": "Feature",
  "properties": {
    "iso:country":"AU",
    "sg:address":"12 Rose St",
    "sg:city":"Bunbury",
    "sg:classifiers":[
        {
            "category":"Retail",
            "subcategory":"Auto Repair",
            "type":"Services"
        }
    ],
    "sg:phone":"+61 8 9721 4225",
    "sg:postcode":"6230",
    "sg:province":"WA",
    "sg:tags":[
        "electrical"
    ],
    "wof:name":"Bunbury Auto Electrics",
    "wof:placetype":"venue"
},
  "geometry": {"coordinates":[115.643173,-33.334782],"type":"Point"}
}