{
  "type": "Feature",
  "properties": {
    "addr:full":"38 Castle St Eaglemont VIC 3084",
    "addr:housenumber":"38",
    "addr:postcode":"3084",
    "addr:street":"Castle St",
    "iso:country":"AU",
    "sg:address":"38 Castle St",
    "sg:city":"Eaglemont",
    "sg:classifiers":[
        {
            "category":"Real Estate",
            "subcategory":"Architect",
            "type":"Services"
        }
    ],
    "sg:phone":"+61 3 9457 5130",
    "sg:postcode":"3084",
    "sg:province":"VIC",
    "sg:tags":[
        "building",
        "designer"
    ],
    "wof:name":"Leo Pegoli Architects Pty Ltd",
    "wof:placetype":"venue"
},
  "geometry": {"coordinates":[145.06324768100001,-37.7598342896],"type":"Point"}
}