{
  "type": "Feature",
  "properties": {
    "iso:country":"AU",
    "sg:address":"14 Lachlan Ave",
    "sg:city":"Molendinar",
    "sg:classifiers":[
        {
            "category":"Professional",
            "subcategory":"Art Services",
            "type":"Services"
        }
    ],
    "sg:phone":"+61 7 5539 5428",
    "sg:postcode":"4214",
    "sg:province":"QLD",
    "sg:tags":[
        "caricaturist",
        "cartoonist"
    ],
    "wof:name":"Dennis Holmes Cartoonist",
    "wof:placetype":"venue"
},
  "geometry": {"coordinates":[153.36587524399999,-27.9790592194],"type":"Point"}
}