{
  "type": "Feature",
  "properties": {
    "iso:country":"AU",
    "sg:address":"1214 Nepean Hwy",
    "sg:city":"Cheltenham",
    "sg:classifiers":[
        {
            "category":"Autos & Motor Vehicles",
            "subcategory":"Automobile Sales",
            "type":"Retail Goods"
        }
    ],
    "sg:phone":"+61 3 9584 3333",
    "sg:postcode":"3192",
    "sg:province":"VIC",
    "sg:tags":[
        "car",
        "new"
    ],
    "sg:website":"http://www.booransuzuki.com.au",
    "wof:name":"Booran Suzuki",
    "wof:placetype":"venue"
},
  "geometry": {"coordinates":[145.055587769,-37.963180542],"type":"Point"}
}