{
  "type": "Feature",
  "properties": {
    "iso:country":"AU",
    "sg:address":"Cnr Burke & Temerloh Sts",
    "sg:city":"Tolland",
    "sg:classifiers":[
        {
            "category":"Autos & Motor Vehicles",
            "subcategory":"Fuel & Gas Station",
            "type":"Retail Goods"
        }
    ],
    "sg:phone":"+61 2 6931 2328",
    "sg:postcode":"2650",
    "sg:province":"NSW",
    "wof:name":"Caltex",
    "wof:placetype":"venue"
},
  "geometry": {"coordinates":[147.35166931099999,-35.1425895691],"type":"Point"}
}