{
  "type": "Feature",
  "properties": {
    "addr:full":"PO Box 2188 West Perth WA 6005",
    "addr:postcode":"6005",
    "iso:country":"AU",
    "sg:address":"PO Box 2188",
    "sg:city":"West Perth",
    "sg:classifiers":[
        {
            "category":"Banks & Credit Unions",
            "subcategory":"Financial Services",
            "type":"Services"
        }
    ],
    "sg:phone":"+61 1800 055 599",
    "sg:postcode":"6005",
    "sg:province":"WA",
    "sg:tags":[
        "surge",
        "protection",
        "lightning"
    ],
    "wof:name":"Erico",
    "wof:placetype":"venue"
},
  "geometry": {"coordinates":[115.8465271,-31.9449996948],"type":"Point"}
}