{
  "type": "Feature",
  "properties": {
    "addr:full":"40- 46 Lesdon Ave Cranbourne VIC 3977",
    "addr:housenumber":"46",
    "addr:postcode":"3977",
    "addr:street":"Lesdon Ave",
    "iso:country":"AU",
    "sg:address":"40- 46 Lesdon Ave",
    "sg:city":"Cranbourne",
    "sg:classifiers":[
        {
            "category":"Education",
            "subcategory":"Kindergarten",
            "type":"Public Place"
        }
    ],
    "sg:phone":"+61 3 5996 4633",
    "sg:postcode":"3977",
    "sg:province":"VIC",
    "sg:tags":[
        "pre-schools"
    ],
    "wof:name":"Rangebank Pre-School",
    "wof:placetype":"venue"
},
  "geometry": {"coordinates":[145.27305602999999,-38.0874214172],"type":"Point"}
}