{
  "type": "Feature",
  "properties": {
    "iso:country":"AU",
    "sg:address":"48 Victor Rd",
    "sg:city":"Dee Why",
    "sg:classifiers":[
        {
            "category":"Building & Trades",
            "subcategory":"Construction",
            "type":"Services"
        }
    ],
    "sg:phone":"+61 419 430 214",
    "sg:postcode":"2099",
    "sg:province":"NSW",
    "sg:tags":[
        "window",
        "tinting"
    ],
    "wof:name":"Shademaster Mobile Window Tinting",
    "wof:placetype":"venue"
},
  "geometry": {"coordinates":[151.278106689,-33.7550430298],"type":"Point"}
}