{
  "type": "Feature",
  "properties": {
    "addr:full":"13 Lergessner Drv Biggera Waters QLD 4216",
    "addr:housenumber":"13",
    "addr:postcode":"4216",
    "addr:street":"Lergessner Drv",
    "iso:country":"AU",
    "sg:address":"13 Lergessner Drv",
    "sg:city":"Biggera Waters",
    "sg:classifiers":[
        {
            "category":"Building & Trades",
            "subcategory":"Construction",
            "type":"Services"
        }
    ],
    "sg:phone":"+61 1800 115 811",
    "sg:postcode":"4216",
    "sg:province":"QLD",
    "sg:tags":[
        "polishing",
        "sanding",
        "floor"
    ],
    "wof:name":"New Master Floor Sanding",
    "wof:placetype":"venue"
},
  "geometry": {"coordinates":[153.39779663100001,-27.934009552],"type":"Point"}
}