{
  "type": "Feature",
  "properties": {
    "iso:country":"AU",
    "sg:address":"Cnr Harbord & Wyuna Ave",
    "sg:city":"Harbord",
    "sg:classifiers":[
        {
            "category":"Autos & Motor Vehicles",
            "subcategory":"Fuel & Gas Station",
            "type":"Retail Goods"
        }
    ],
    "sg:phone":"+61 2 9905 5041",
    "sg:postcode":"2096",
    "sg:province":"NSW",
    "wof:name":"Prime Service Station",
    "wof:placetype":"venue"
},
  "geometry": {"coordinates":[151.279464722,-33.7759017944],"type":"Point"}
}