{
  "type": "Feature",
  "properties": {
    "addr:full":"107 Mulgrave Rd Cairns QLD 4870",
    "addr:housenumber":"107",
    "addr:postcode":"4870",
    "addr:street":"Mulgrave Rd",
    "iso:country":"AU",
    "sg:address":"107 Mulgrave Rd",
    "sg:city":"Cairns",
    "sg:classifiers":[
        {
            "category":"Structure",
            "subcategory":"Tunnel",
            "type":"Public Place"
        }
    ],
    "sg:phone":"+61 7 4031 6256",
    "sg:postcode":"4870",
    "sg:province":"QLD",
    "sg:tags":[
        "cleaner",
        "industrial",
        "vacuum"
    ],
    "wof:name":"Cairns Vacuum Centre",
    "wof:placetype":"venue"
},
  "geometry": {"coordinates":[145.74380493199999,-16.9397296906],"type":"Point"}
}