{
  "type": "Feature",
  "properties": {
    "iso:country":"AU",
    "sg:address":"9 Rochester St",
    "sg:city":"Botany",
    "sg:classifiers":[
        {
            "category":"Banks & Credit Unions",
            "subcategory":"Investment Brokerage",
            "type":"Services"
        }
    ],
    "sg:phone":"+61 2 9666 6746",
    "sg:postcode":"2019",
    "sg:province":"NSW",
    "sg:tags":[
        "mfrg",
        "wholesale",
        "product",
        "sheepskin"
    ],
    "wof:name":"Marylee & Vj Accessories",
    "wof:placetype":"venue"
},
  "geometry": {"coordinates":[151.19807434099999,-33.9498748779],"type":"Point"}
}