{
  "type": "Feature",
  "properties": {
    "addr:full":"66 William Webb Drv Evatt ACT 2617",
    "addr:housenumber":"66",
    "addr:postcode":"2617",
    "addr:street":"William Webb Drv",
    "iso:country":"AU",
    "sg:address":"66 William Webb Drv",
    "sg:city":"Evatt",
    "sg:classifiers":[
        {
            "category":"Professional",
            "subcategory":"Art Services",
            "type":"Services"
        }
    ],
    "sg:phone":"+61 412 080 348",
    "sg:postcode":"2617",
    "sg:province":"ACT",
    "sg:tags":[
        "decorator",
        "painter"
    ],
    "wof:name":"Hamad Rostom",
    "wof:placetype":"venue"
},
  "geometry": {"coordinates":[149.07650756800001,-35.2127037048],"type":"Point"}
}