{
  "type": "Feature",
  "properties": {
    "addr:full":"Woogenellup Rd Mt Barker WA 6324",
    "addr:postcode":"6324",
    "addr:street":"Woogenellup Rd",
    "iso:country":"AU",
    "sg:address":"Woogenellup Rd",
    "sg:city":"Mt Barker",
    "sg:classifiers":[
        {
            "category":"Education",
            "subcategory":"School",
            "type":"Public Place"
        }
    ],
    "sg:phone":"+61 8 9851 3400",
    "sg:postcode":"6324",
    "sg:province":"WA",
    "sg:tags":[
        "state",
        "except",
        "nsw"
    ],
    "wof:name":"Mount Barker Senior High School",
    "wof:placetype":"venue"
},
  "geometry": {"coordinates":[117.667610169,-34.6147689819],"type":"Point"}
}