{
  "type": "Feature",
  "properties": {
    "addr:full":"Shop 212a Gympie Rd Chermside QLD 4032",
    "addr:housenumber":"212a",
    "addr:postcode":"qld 4032",
    "addr:street":"Gympie Rd",
    "iso:country":"AU",
    "sg:address":"Shop 212a Gympie Rd",
    "sg:city":"Chermside",
    "sg:classifiers":[
        {
            "category":"Education",
            "subcategory":"Special Training",
            "type":"Public Place"
        }
    ],
    "sg:phone":"+61 7 3256 4617",
    "sg:postcode":"4032",
    "sg:province":"QLD",
    "sg:tags":[
        "college",
        "hairdressing"
    ],
    "wof:name":"S & S Hairdressing",
    "wof:placetype":"venue"
},
  "geometry": {"coordinates":[153.03105199999999,-27.385942],"type":"Point"}
}