{
  "type": "Feature",
  "properties": {
    "addr:full":"1736 Main North Rd Salisbury Plain SA 5109",
    "addr:housenumber":"1736",
    "addr:postcode":"5109",
    "addr:street":"Main North Rd",
    "iso:country":"AU",
    "sg:address":"1736 Main North Rd",
    "sg:city":"Salisbury Plain",
    "sg:classifiers":[
        {
            "category":"Retail",
            "subcategory":"Auto Repair",
            "type":"Services"
        }
    ],
    "sg:phone":"+61 8 8281 8800",
    "sg:postcode":"5109",
    "sg:province":"SA",
    "sg:tags":[
        "beater",
        "painter",
        "panel"
    ],
    "wof:name":"Carisbrook Crash",
    "wof:placetype":"venue"
},
  "geometry": {"coordinates":[138.66665649399999,-34.7690696716],"type":"Point"}
}