{
  "type": "Feature",
  "properties": {
    "addr:full":"324 Elizabeth St Sydney NSW 2000",
    "addr:housenumber":"324",
    "addr:postcode":"2000",
    "addr:street":"Elizabeth St",
    "iso:country":"AU",
    "sg:address":"324 Elizabeth St",
    "sg:city":"Sydney",
    "sg:classifiers":[
        {
            "category":"Travel",
            "subcategory":"Hotels & Motels",
            "type":"Entertainment"
        }
    ],
    "sg:phone":"+61 2 9211 3462",
    "sg:postcode":"2000",
    "sg:province":"NSW",
    "sg:tags":[
        "pub"
    ],
    "wof:name":"Aurora Hotel",
    "wof:placetype":"venue"
},
  "geometry": {"coordinates":[151.20831298799999,-33.8841705322],"type":"Point"}
}