{
  "type": "Feature",
  "properties": {
    "addr:full":"Cnr Benalla Rd & Watson St Shepparton VIC 3630",
    "addr:postcode":"3630",
    "addr:street":"Benalla Rd & Watson St",
    "iso:country":"AU",
    "sg:address":"Cnr Benalla Rd & Watson St",
    "sg:city":"Shepparton",
    "sg:classifiers":[
        {
            "category":"Retail",
            "subcategory":"Repair Shop",
            "type":"Services"
        }
    ],
    "sg:phone":"+61 13 16 16",
    "sg:postcode":"3630",
    "sg:province":"VIC",
    "sg:tags":[
        "windscreen"
    ],
    "wof:name":"O&#039;Brien",
    "wof:placetype":"venue"
},
  "geometry": {"coordinates":[145.43011474599999,-36.387840271],"type":"Point"}
}