{
  "type": "Feature",
  "properties": {
    "addr:full":"452 Iron Bark Rd Yarrambat VIC 3091",
    "addr:housenumber":"452",
    "addr:postcode":"3091",
    "addr:street":"Iron Bark Rd",
    "iso:country":"AU",
    "sg:address":"452 Iron Bark Rd",
    "sg:city":"Yarrambat",
    "sg:classifiers":[
        {
            "category":"Health Services",
            "subcategory":"Health Practitioner",
            "type":"Services"
        }
    ],
    "sg:phone":"+61 3 9436 1199",
    "sg:postcode":"3091",
    "sg:province":"VIC",
    "sg:tags":[
        "naturopath"
    ],
    "wof:name":"Whitehall Natural Therapy",
    "wof:placetype":"venue"
},
  "geometry": {"coordinates":[145.136276245,-37.6397018433],"type":"Point"}
}