{
  "type": "Feature",
  "properties": {
    "addr:full":"Lot 144 Langland St Karalee QLD 4306",
    "addr:postcode":"4306",
    "addr:street":"Langland St",
    "iso:country":"AU",
    "sg:address":"Lot 144 Langland St",
    "sg:city":"Karalee",
    "sg:classifiers":[
        {
            "category":"Building & Trades",
            "subcategory":"Construction",
            "type":"Services"
        }
    ],
    "sg:phone":"+61 418 730 084",
    "sg:postcode":"4306",
    "sg:province":"QLD",
    "sg:tags":[
        "earth",
        "excavating",
        "moving",
        "contractor"
    ],
    "wof:name":"Pryde E J & C J",
    "wof:placetype":"venue"
},
  "geometry": {"coordinates":[152.801025391,-27.5616016388],"type":"Point"}
}