{
  "type": "Feature",
  "properties": {
    "iso:country":"AU",
    "sg:address":"PO Box 4117",
    "sg:city":"Homebush South",
    "sg:classifiers":[
        {
            "category":"Professional",
            "type":"Services"
        }
    ],
    "sg:phone":"+61 1300 720 448",
    "sg:postcode":"2140",
    "sg:province":"NSW",
    "sg:tags":[
        "control",
        "equipment",
        "traffic"
    ],
    "wof:name":"Traffic Control Management Australia",
    "wof:placetype":"venue"
},
  "geometry": {"coordinates":[151.084472656,-33.8677711487],"type":"Point"}
}