{
  "type": "Feature",
  "properties": {
    "iso:country":"AU",
    "sg:address":"116 St Vincent St",
    "sg:city":"Ulladulla",
    "sg:classifiers":[
        {
            "category":"Manufacturing",
            "subcategory":"Metals",
            "type":"Manufacturing & Wholesale Goods"
        }
    ],
    "sg:phone":"+61 2 4455 1220",
    "sg:postcode":"2539",
    "sg:province":"NSW",
    "sg:tags":[
        "steel",
        "fabricator",
        "mfrs"
    ],
    "wof:name":"Geo Babington Engineering",
    "wof:placetype":"venue"
},
  "geometry": {"coordinates":[150.472854614,-35.3525161743],"type":"Point"}
}