{
  "type": "Feature",
  "properties": {
    "iso:country":"AU",
    "sg:address":"3/ 13 Nelson St",
    "sg:city":"Fairfield",
    "sg:classifiers":[
        {
            "category":"Health Services",
            "subcategory":"Doctor",
            "type":"Services"
        }
    ],
    "sg:phone":"+61 2 9754 2055",
    "sg:postcode":"2165",
    "sg:province":"NSW",
    "sg:tags":[
        "medical",
        "practitioner"
    ],
    "wof:name":"Cubas Susana",
    "wof:placetype":"venue"
},
  "geometry": {"coordinates":[150.95364379899999,-33.869354248],"type":"Point"}
}