{
  "type": "Feature",
  "properties": {
    "addr:full":"75 McIntyre Rd Sunshine North VIC 3020",
    "addr:housenumber":"75",
    "addr:postcode":"3020",
    "addr:street":"Mcintyre Rd",
    "iso:country":"AU",
    "sg:address":"75 McIntyre Rd",
    "sg:city":"Sunshine North",
    "sg:classifiers":[
        {
            "category":"Manufacturing",
            "subcategory":"Food",
            "type":"Manufacturing & Wholesale Goods"
        }
    ],
    "sg:phone":"+61 3 9311 6581",
    "sg:postcode":"3020",
    "sg:province":"VIC",
    "sg:tags":[
        "function",
        "catering"
    ],
    "wof:name":"J's Diner",
    "wof:placetype":"venue"
},
  "geometry": {"coordinates":[144.83004800000001,-37.769077],"type":"Point"}
}