{
  "type": "Feature",
  "properties": {
    "iso:country":"AU",
    "sg:address":"151 Prospect Hwy",
    "sg:city":"Seven Hills",
    "sg:classifiers":[
        {
            "category":"Retail",
            "subcategory":"Auto Repair",
            "type":"Services"
        }
    ],
    "sg:phone":"+61 2 9620 9001",
    "sg:postcode":"2147",
    "sg:province":"NSW",
    "sg:tags":[
        "repairer",
        "motor",
        "engineer"
    ],
    "wof:name":"Smart Touch Auto Repairs",
    "wof:placetype":"venue"
},
  "geometry": {"coordinates":[150.93968200699999,-33.7705688477],"type":"Point"}
}