{
  "type": "Feature",
  "properties": {
    "addr:full":"PO Box 720 Drummoyne NSW 2047",
    "addr:postcode":"2047",
    "iso:country":"AU",
    "sg:address":"PO Box 720",
    "sg:city":"Drummoyne",
    "sg:classifiers":[
        {
            "category":"Shopping",
            "subcategory":"Stationery & Office Supplies",
            "type":"Retail Goods"
        }
    ],
    "sg:phone":"+61 2 9181 4070",
    "sg:postcode":"2047",
    "sg:province":"NSW",
    "sg:tags":[
        "merchant",
        "paper"
    ],
    "wof:name":"Paper Exchange",
    "wof:placetype":"venue"
},
  "geometry": {"coordinates":[151.15353400000001,-33.8521],"type":"Point"}
}