{
  "type": "Feature",
  "properties": {
    "addr:full":"Bundilla Shopng Cntr 125 Brisbane Rd Mooloolaba QLD 4557",
    "addr:housenumber":"125",
    "addr:postcode":"4557",
    "addr:street":"Brisbane Rd",
    "iso:country":"AU",
    "sg:address":"Bundilla Shopng Cntr 125 Brisbane Rd",
    "sg:city":"Mooloolaba",
    "sg:classifiers":[
        {
            "category":"Health Services",
            "subcategory":"Dentist",
            "type":"Services"
        }
    ],
    "sg:phone":"+61 7 5444 6116",
    "sg:postcode":"4557",
    "sg:province":"QLD",
    "sg:tags":[
        "dental",
        "prosthetist"
    ],
    "wof:name":"Bruce Menzies",
    "wof:placetype":"venue"
},
  "geometry": {"coordinates":[153.11529540999999,-26.6898860931],"type":"Point"}
}