{
  "type": "Feature",
  "properties": {
    "iso:country":"AU",
    "sg:address":"U6/ 41 Badgally Rd",
    "sg:city":"Campbelltown",
    "sg:classifiers":[
        {
            "category":"Building & Trades",
            "subcategory":"Construction",
            "type":"Services"
        }
    ],
    "sg:phone":"+61 2 4626 7699",
    "sg:postcode":"2560",
    "sg:province":"NSW",
    "sg:tags":[
        "fencing",
        "contractor"
    ],
    "wof:name":"One Stop Fence Shop",
    "wof:placetype":"venue"
},
  "geometry": {"coordinates":[150.81413269000001,-34.0600738525],"type":"Point"}
}