{
  "type": "Feature",
  "properties": {
    "addr:full":"19 Allandale Drv Baulkham Hills NSW 2153",
    "addr:housenumber":"19",
    "addr:postcode":"2153",
    "addr:street":"Allandale Drv",
    "iso:country":"AU",
    "sg:address":"19 Allandale Drv",
    "sg:city":"Baulkham Hills",
    "sg:classifiers":[
        {
            "category":"Real Estate",
            "subcategory":"Surveying",
            "type":"Services"
        }
    ],
    "sg:phone":"+61 2 9674 5495",
    "sg:postcode":"2153",
    "sg:province":"NSW",
    "sg:tags":[
        "map",
        "mapping"
    ],
    "wof:name":"Professional Drafting & Photography",
    "wof:placetype":"venue"
},
  "geometry": {"coordinates":[150.96786499000001,-33.7466392517],"type":"Point"}
}