{
  "type": "Feature",
  "properties": {
    "addr:full":"Lot 3/ 100 Bridge Rd Keysborough VIC 3173",
    "addr:housenumber":"3 / 100",
    "addr:postcode":"3173",
    "addr:street":"Bridge Rd",
    "iso:country":"AU",
    "sg:address":"Lot 3/ 100 Bridge Rd",
    "sg:city":"Keysborough",
    "sg:classifiers":[
        {
            "category":"Building & Trades",
            "subcategory":"Construction",
            "type":"Services"
        }
    ],
    "sg:phone":"+61 3 9701 8975",
    "sg:postcode":"3173",
    "sg:province":"VIC",
    "sg:tags":[
        "contractor"
    ],
    "wof:name":"Rbh Building Group Pty Ltd",
    "wof:placetype":"venue"
},
  "geometry": {"coordinates":[145.19200134299999,-37.9879798889],"type":"Point"}
}