{
  "type": "Feature",
  "properties": {
    "addr:full":"Young St (next to TAB) Ayr QLD 4807",
    "addr:postcode":"4807",
    "addr:street":"Young St Next",
    "iso:country":"AU",
    "sg:address":"Young St",
    "sg:city":"(next to TAB) Ayr",
    "sg:classifiers":[
        {
            "category":"Real Estate",
            "subcategory":"Real Estate Agent",
            "type":"Services"
        }
    ],
    "sg:phone":"+61 7 4783 7522",
    "sg:postcode":"4807",
    "sg:province":"QLD",
    "wof:name":"Raine & Horne RURAL Ayr",
    "wof:placetype":"venue"
},
  "geometry": {"coordinates":[147.402908325,-19.5740146637],"type":"Point"}
}