{
  "type": "Feature",
  "properties": {
    "iso:country":"AU",
    "sg:address":"112 Briggs St",
    "sg:city":"Welshpool",
    "sg:classifiers":[
        {
            "category":"Wholesale",
            "subcategory":"Electrical",
            "type":"Manufacturing & Wholesale Goods"
        }
    ],
    "sg:phone":"+61 8 9472 8601",
    "sg:postcode":"6106",
    "sg:province":"WA",
    "sg:tags":[
        "control",
        "equipment",
        "switch"
    ],
    "wof:name":"Telemecanique & Controls P/L",
    "wof:placetype":"venue"
},
  "geometry": {"coordinates":[115.928718567,-31.9824409485],"type":"Point"}
}