{
  "type": "Feature",
  "properties": {
    "addr:full":"174 Phillip St Sydney NSW 2000",
    "addr:housenumber":"174",
    "addr:postcode":"2000",
    "addr:street":"Phillip St",
    "iso:country":"AU",
    "sg:address":"174 Phillip St",
    "sg:city":"Sydney",
    "sg:classifiers":[
        {
            "category":"Manufacturing",
            "subcategory":"Food",
            "type":"Manufacturing & Wholesale Goods"
        }
    ],
    "sg:phone":"+61 2 9223 6103",
    "sg:postcode":"2000",
    "sg:province":"NSW",
    "sg:tags":[
        "function",
        "catering"
    ],
    "wof:name":"Table Matters",
    "wof:placetype":"venue"
},
  "geometry": {"coordinates":[151.21125793499999,-33.8687896729],"type":"Point"}
}