{
  "type": "Feature",
  "properties": {
    "addr:full":"10 Baylis Pl North Richmond NSW 2754",
    "addr:housenumber":"10",
    "addr:postcode":"2754",
    "addr:street":"Pl",
    "iso:country":"AU",
    "sg:address":"10 Baylis Pl",
    "sg:city":"North Richmond",
    "sg:classifiers":[
        {
            "category":"Professional",
            "type":"Services"
        }
    ],
    "sg:phone":"+61 2 4571 2340",
    "sg:postcode":"2754",
    "sg:province":"NSW",
    "sg:tags":[
        "shop",
        "fitting"
    ],
    "wof:name":"R & K Installations",
    "wof:placetype":"venue"
},
  "geometry": {"coordinates":[150.70474243199999,-33.5803718567],"type":"Point"}
}