{
  "type": "Feature",
  "properties": {
    "addr:full":"74 Mt Pleasant Rd Kingston TAS 7050",
    "addr:housenumber":"74",
    "addr:postcode":"7050",
    "addr:street":"Mt Pleasant Rd",
    "iso:country":"AU",
    "sg:address":"74 Mt Pleasant Rd",
    "sg:city":"Kingston",
    "sg:classifiers":[
        {
            "category":"Farming",
            "subcategory":"Vineyard",
            "type":"Manufacturing & Wholesale Goods"
        }
    ],
    "sg:phone":"+61 419 340 545",
    "sg:postcode":"7050",
    "sg:province":"TAS",
    "sg:tags":[
        "winery"
    ],
    "wof:name":"Summerleas Wines",
    "wof:placetype":"venue"
},
  "geometry": {"coordinates":[147.27624499999999,-42.975449],"type":"Point"}
}