{
  "type": "Feature",
  "properties": {
    "addr:full":"Suite 1102, 221 Miller St North Sydney NSW 2060",
    "addr:housenumber":"221",
    "addr:postcode":"2060",
    "addr:street":"Miller St",
    "iso:country":"AU",
    "sg:address":"Suite 1102, 221 Miller St",
    "sg:city":"North Sydney",
    "sg:classifiers":[
        {
            "category":"Professional",
            "subcategory":"Accounting & Tax Preparation",
            "type":"Services"
        }
    ],
    "sg:phone":"+61 2 9923 1999",
    "sg:postcode":"2060",
    "sg:province":"NSW",
    "sg:tags":[
        "accountant",
        "auditor"
    ],
    "wof:name":"Cooney John W",
    "wof:placetype":"venue"
},
  "geometry": {"coordinates":[151.20765685999999,-33.8357315063],"type":"Point"}
}