{
  "type": "Feature",
  "properties": {
    "iso:country":"AU",
    "sg:address":"14 Pacific St",
    "sg:city":"Newcastle",
    "sg:classifiers":[
        {
            "category":"Building & Trades",
            "subcategory":"Construction",
            "type":"Services"
        }
    ],
    "sg:phone":"+61 412 112 902",
    "sg:postcode":"2300",
    "sg:province":"NSW",
    "sg:tags":[
        "plasterboard",
        "plasterer",
        "fixer"
    ],
    "wof:name":"D M P Building Improvements",
    "wof:placetype":"venue"
},
  "geometry": {"coordinates":[151.785339,-32.928909],"type":"Point"}
}