{
  "type": "Feature",
  "properties": {
    "addr:full":"8/ 262 Poath Rd Hughesdale VIC 3166",
    "addr:housenumber":"/ 262",
    "addr:postcode":"3166",
    "addr:street":"Poath Rd",
    "iso:country":"AU",
    "sg:address":"8/ 262 Poath Rd",
    "sg:city":"Hughesdale",
    "sg:classifiers":[
        {
            "category":"Professional",
            "subcategory":"Art Services",
            "type":"Services"
        }
    ],
    "sg:phone":"+61 3 9579 2587",
    "sg:postcode":"3166",
    "sg:province":"VIC",
    "sg:tags":[
        "decorator",
        "painter"
    ],
    "wof:name":"Mini Mite Murals",
    "wof:placetype":"venue"
},
  "geometry": {"coordinates":[145.074707031,-37.9064178467],"type":"Point"}
}