{
  "type": "Feature",
  "properties": {
    "iso:country":"AU",
    "sg:address":"127 Sheridan St",
    "sg:city":"Cairns",
    "sg:classifiers":[
        {
            "category":"Real Estate",
            "subcategory":"Real Estate Agent",
            "type":"Services"
        }
    ],
    "sg:phone":"+61 7 4051 3200",
    "sg:postcode":"4870",
    "sg:province":"QLD",
    "wof:name":"Accom Cairns Property Shop",
    "wof:placetype":"venue"
},
  "geometry": {"coordinates":[145.76948547399999,-16.919008255],"type":"Point"}
}