{
  "type": "Feature",
  "properties": {
    "addr:full":"32 Hanrahan St Robertson QLD 4109",
    "addr:housenumber":"32",
    "addr:postcode":"4109",
    "addr:street":"Hanrahan St",
    "iso:country":"AU",
    "sg:address":"32 Hanrahan St",
    "sg:city":"Robertson",
    "sg:classifiers":[
        {
            "category":"Professional",
            "subcategory":"Business Services",
            "type":"Services"
        }
    ],
    "sg:phone":"+61 7 3117 9313",
    "sg:postcode":"4109",
    "sg:province":"QLD",
    "sg:tags":[
        "broker"
    ],
    "wof:name":"Rl Pacific",
    "wof:placetype":"venue"
},
  "geometry": {"coordinates":[153.055084228,-27.5624656677],"type":"Point"}
}