{
  "type": "Feature",
  "properties": {
    "addr:full":"68 Pacific Hwy Tuggerah NSW 2259",
    "addr:housenumber":"68",
    "addr:postcode":"2259",
    "addr:street":"Pacific Hwy",
    "iso:country":"AU",
    "sg:address":"68 Pacific Hwy",
    "sg:city":"Tuggerah",
    "sg:classifiers":[
        {
            "category":"Retail",
            "subcategory":"Driving School",
            "type":"Services"
        }
    ],
    "sg:phone":"+61 2 4352 1348",
    "sg:postcode":"2259",
    "sg:province":"NSW",
    "wof:name":"All Wyong Driving School",
    "wof:placetype":"venue"
},
  "geometry": {"coordinates":[151.414993286,-33.3104476929],"type":"Point"}
}