{
  "type": "Feature",
  "properties": {
    "iso:country":"AU",
    "sg:address":"1 Marriner St",
    "sg:city":"Colac",
    "sg:classifiers":[
        {
            "category":"Shopping",
            "type":"Retail Goods"
        }
    ],
    "sg:phone":"+61 3 5231 4633",
    "sg:postcode":"3250",
    "sg:province":"VIC",
    "sg:tags":[
        "produce",
        "grain"
    ],
    "wof:name":"Colac Stockfeeds",
    "wof:placetype":"venue"
},
  "geometry": {"coordinates":[143.611343,-38.330303],"type":"Point"}
}