{
  "type": "Feature",
  "properties": {
    "iso:country":"AU",
    "sg:address":"24 Victoria Pde",
    "sg:city":"Port Augusta",
    "sg:classifiers":[
        {
            "category":"Professional",
            "subcategory":"Detective & Security Services",
            "type":"Services"
        }
    ],
    "sg:phone":"+61 409 714 345",
    "sg:postcode":"5700",
    "sg:province":"SA",
    "sg:tags":[
        "consultant",
        "system"
    ],
    "wof:name":"Northern Alarms",
    "wof:placetype":"venue"
},
  "geometry": {"coordinates":[137.77342224099999,-32.4969673157],"type":"Point"}
}