{
  "type": "Feature",
  "properties": {
    "iso:country":"AU",
    "sg:address":"PO Box 535",
    "sg:city":"Willoughby",
    "sg:classifiers":[
        {
            "category":"Professional",
            "subcategory":"Art Services",
            "type":"Services"
        }
    ],
    "sg:phone":"+61 2 9958 2595",
    "sg:postcode":"2068",
    "sg:province":"NSW",
    "sg:tags":[
        "interior",
        "designer"
    ],
    "wof:name":"id Projects",
    "wof:placetype":"venue"
},
  "geometry": {"coordinates":[151.19781494099999,-33.8057289124],"type":"Point"}
}