{
  "type": "Feature",
  "properties": {
    "iso:country":"AU",
    "sg:address":"176 Holdbrook Rd",
    "sg:city":"Underdale",
    "sg:classifiers":[
        {
            "category":"Retail",
            "subcategory":"Auto Repair",
            "type":"Services"
        }
    ],
    "sg:phone":"+61 419 831 482",
    "sg:postcode":"5032",
    "sg:province":"SA",
    "sg:tags":[
        "repairer",
        "motor",
        "engineer"
    ],
    "wof:name":"JD Motor Repairs",
    "wof:placetype":"venue"
},
  "geometry": {"coordinates":[138.54850769000001,-34.9199180603],"type":"Point"}
}