{
  "type": "Feature",
  "properties": {
    "iso:country":"AU",
    "sg:address":"60A Strickland St",
    "sg:city":"Bunbury",
    "sg:classifiers":[
        {
            "category":"Professional",
            "subcategory":"Printing & Photocopies",
            "type":"Services"
        }
    ],
    "sg:phone":"+61 8 9721 2636",
    "sg:postcode":"6230",
    "sg:province":"WA",
    "sg:tags":[
        "photocopying"
    ],
    "wof:name":"Dynamic Print",
    "wof:placetype":"venue"
},
  "geometry": {"coordinates":[115.650482,-33.336128],"type":"Point"}
}