{
  "type": "Feature",
  "properties": {
    "iso:country":"AU",
    "sg:address":"Unit 28 29 Johnston St",
    "sg:city":"Annandale",
    "sg:classifiers":[
        {
            "category":"Professional",
            "subcategory":"Accounting & Tax Preparation",
            "type":"Services"
        }
    ],
    "sg:phone":"+61 2 9550 3237",
    "sg:postcode":"2038",
    "sg:province":"NSW",
    "sg:tags":[
        "consultant",
        "taxation"
    ],
    "wof:name":"Home Tax Specialists",
    "wof:placetype":"venue"
},
  "geometry": {"coordinates":[151.16896057100001,-33.8853912354],"type":"Point"}
}