{
  "type": "Feature",
  "properties": {
    "addr:full":"5 Central Drv Burleigh Heads QLD 4220",
    "addr:housenumber":"5",
    "addr:postcode":"4220",
    "addr:street":"Central Drv",
    "iso:country":"AU",
    "sg:address":"5 Central Drv",
    "sg:city":"Burleigh Heads",
    "sg:classifiers":[
        {
            "category":"Manufacturing",
            "subcategory":"Glass & Minerals",
            "type":"Manufacturing & Wholesale Goods"
        }
    ],
    "sg:phone":"+61 7 5593 8277",
    "sg:postcode":"4220",
    "sg:province":"QLD",
    "sg:tags":[
        "fabricator",
        "foam",
        "processor"
    ],
    "wof:name":"P J Bowers Pty Ltd",
    "wof:placetype":"venue"
},
  "geometry": {"coordinates":[153.42480468799999,-28.1030254364],"type":"Point"}
}