{
  "type": "Feature",
  "properties": {
    "iso:country":"AU",
    "sg:address":"Devon Rd",
    "sg:city":"Devon Meadows",
    "sg:classifiers":[
        {
            "category":"Food & Beverages",
            "subcategory":"Fruits & Vegetables",
            "type":"Retail Goods"
        }
    ],
    "sg:phone":"+61 3 5998 2375",
    "sg:postcode":"3977",
    "sg:province":"VIC",
    "sg:tags":[
        "grower"
    ],
    "wof:name":"Gervasi G",
    "wof:placetype":"venue"
},
  "geometry": {"coordinates":[145.301513672,-38.1473999023],"type":"Point"}
}