{
  "type": "Feature",
  "properties": {
    "iso:country":"AU",
    "sg:address":"Jenkinsons Rd",
    "sg:city":"Pimpinio",
    "sg:classifiers":[
        {
            "category":"Farming",
            "subcategory":"Farm",
            "type":"Manufacturing & Wholesale Goods"
        }
    ],
    "sg:phone":"+61 3 5384 2264",
    "sg:postcode":"3401",
    "sg:province":"VIC",
    "sg:tags":[
        "farmer"
    ],
    "wof:name":"Jenkinson K R",
    "wof:placetype":"venue"
},
  "geometry": {"coordinates":[142.14263915999999,-36.6245231628],"type":"Point"}
}