{
  "type": "Feature",
  "properties": {
    "addr:full":"31 Rix St Glen Iris VIC 3146",
    "addr:housenumber":"31",
    "addr:postcode":"3146",
    "addr:street":"Rix St",
    "iso:country":"AU",
    "sg:address":"31 Rix St",
    "sg:city":"Glen Iris",
    "sg:classifiers":[
        {
            "category":"Building & Trades",
            "subcategory":"Construction",
            "type":"Services"
        }
    ],
    "sg:phone":"+61 3 9822 1126",
    "sg:postcode":"3146",
    "sg:province":"VIC",
    "sg:tags":[
        "management"
    ],
    "wof:name":"BILD Pty Ltd",
    "wof:placetype":"venue"
},
  "geometry": {"coordinates":[145.05226135300001,-37.8469314575],"type":"Point"}
}