{
  "type": "Feature",
  "properties": {
    "addr:full":"Legge's Rd Palm Creek QLD 4850",
    "addr:postcode":"4850",
    "addr:street":"Legge'S Rd",
    "iso:country":"AU",
    "sg:address":"Legge's Rd",
    "sg:city":"Palm Creek",
    "sg:classifiers":[
        {
            "category":"Farming",
            "subcategory":"Farm",
            "type":"Manufacturing & Wholesale Goods"
        }
    ],
    "sg:phone":"+61 7 4777 1654",
    "sg:postcode":"4850",
    "sg:province":"QLD",
    "sg:tags":[
        "farmer"
    ],
    "wof:name":"Maskell F H",
    "wof:placetype":"venue"
},
  "geometry": {"coordinates":[146.17935180699999,-18.6588802338],"type":"Point"}
}