{
  "type": "Feature",
  "properties": {
    "addr:full":"Mullewa Hospital Complex Elder St Mullewa WA 6630",
    "addr:postcode":"6630",
    "addr:street":"Elder St",
    "iso:country":"AU",
    "sg:address":"Mullewa Hospital Complex Elder St",
    "sg:city":"Mullewa",
    "sg:classifiers":[
        {
            "category":"Social Services",
            "subcategory":"Child Care",
            "type":"Services"
        }
    ],
    "sg:phone":"+61 8 9961 1183",
    "sg:postcode":"6630",
    "sg:province":"WA",
    "sg:tags":[
        "support",
        "health"
    ],
    "wof:name":"Child Health Services",
    "wof:placetype":"venue"
},
  "geometry": {"coordinates":[115.51342010499999,-28.5361804962],"type":"Point"}
}