{
  "type": "Feature",
  "properties": {
    "addr:full":"150 Bingham Rd Bullsbrook WA 6084",
    "addr:housenumber":"150",
    "addr:postcode":"6084",
    "addr:street":"Bingham Rd",
    "iso:country":"AU",
    "sg:address":"150 Bingham Rd",
    "sg:city":"Bullsbrook",
    "sg:classifiers":[
        {
            "category":"Farming",
            "subcategory":"Nursery",
            "type":"Manufacturing & Wholesale Goods"
        }
    ],
    "sg:phone":"+61 8 9571 3055",
    "sg:postcode":"6084",
    "sg:province":"WA",
    "wof:name":"Country Cottage Nursery",
    "wof:placetype":"venue"
},
  "geometry": {"coordinates":[115.96714782700001,-31.6504058838],"type":"Point"}
}