{
  "type": "Feature",
  "properties": {
    "addr:full":"16 Wellington St Cleveland QLD 4163",
    "addr:housenumber":"16",
    "addr:postcode":"4163",
    "addr:street":"Wellington St",
    "iso:country":"AU",
    "sg:address":"16 Wellington St",
    "sg:city":"Cleveland",
    "sg:classifiers":[
        {
            "category":"Real Estate",
            "subcategory":"Real Estate Agent",
            "type":"Services"
        }
    ],
    "sg:phone":"+61 7 3286 1200",
    "sg:postcode":"4163",
    "sg:province":"QLD",
    "sg:tags":[
        "handyman's",
        "equipment",
        "hire",
        "builders",
        "contractor"
    ],
    "wof:name":"Hire Plus",
    "wof:placetype":"venue"
},
  "geometry": {"coordinates":[153.25587463400001,-27.5245323181],"type":"Point"}
}