{
  "type": "Feature",
  "properties": {
    "iso:country":"AU",
    "sg:address":"47 Murray Rd",
    "sg:city":"Bicton",
    "sg:classifiers":[
        {
            "category":"Mining & Drilling",
            "type":"Manufacturing & Wholesale Goods"
        }
    ],
    "sg:phone":"+61 8 9339 5964",
    "sg:postcode":"6157",
    "sg:province":"WA",
    "sg:tags":[
        "geologist"
    ],
    "wof:name":"Lyndhurst Enterprises Pty Ltd",
    "wof:placetype":"venue"
},
  "geometry": {"coordinates":[115.789772,-32.032764],"type":"Point"}
}