{
  "type": "Feature",
  "properties": {
    "addr:full":"38 Chetwynd St Loganholme QLD 4129",
    "addr:housenumber":"38",
    "addr:postcode":"4129",
    "addr:street":"Chetwynd St",
    "iso:country":"AU",
    "sg:address":"38 Chetwynd St",
    "sg:city":"Loganholme",
    "sg:classifiers":[
        {
            "category":"Manufacturing",
            "subcategory":"Petroleum Products",
            "type":"Manufacturing & Wholesale Goods"
        }
    ],
    "sg:phone":"+61 7 3806 5722",
    "sg:postcode":"4129",
    "sg:province":"QLD",
    "sg:tags":[
        "lubricant"
    ],
    "wof:name":"Savcom Pty Ltd",
    "wof:placetype":"venue"
},
  "geometry": {"coordinates":[153.18728637699999,-27.6784114838],"type":"Point"}
}