{
  "type": "Feature",
  "properties": {
    "addr:full":"1203 Sturt St Ballarat VIC 3350",
    "addr:housenumber":"1203",
    "addr:postcode":"3350",
    "addr:street":"Sturt St",
    "iso:country":"AU",
    "sg:address":"1203 Sturt St",
    "sg:city":"Ballarat",
    "sg:classifiers":[
        {
            "category":"Food & Beverages",
            "subcategory":"Bakery",
            "type":"Retail Goods"
        }
    ],
    "sg:phone":"+61 3 5332 1354",
    "sg:postcode":"3350",
    "sg:province":"VIC",
    "sg:tags":[
        "baker"
    ],
    "wof:name":"Rosenhart Cake Shop",
    "wof:placetype":"venue"
},
  "geometry": {"coordinates":[143.842682,-37.560474],"type":"Point"}
}