{
  "type": "Feature",
  "properties": {
    "iso:country":"AU",
    "sg:address":"15 James St",
    "sg:city":"Burleigh Heads",
    "sg:classifiers":[
        {
            "category":"Shopping",
            "subcategory":"Clothing, Apparel, & Fashions",
            "type":"Retail Goods"
        }
    ],
    "sg:phone":"+61 7 5535 9600",
    "sg:postcode":"4220",
    "sg:province":"QLD",
    "sg:tags":[
        "boutique"
    ],
    "wof:name":"Beachside Resort Wear",
    "wof:placetype":"venue"
},
  "geometry": {"coordinates":[153.45150756800001,-28.0892429352],"type":"Point"}
}