{
  "type": "Feature",
  "properties": {
    "addr:full":"274- 278 Parramatta Rd Granville NSW 2142",
    "addr:housenumber":"278",
    "addr:postcode":"2142",
    "addr:street":"Parramatta Rd",
    "iso:country":"AU",
    "sg:address":"274- 278 Parramatta Rd",
    "sg:city":"Granville",
    "sg:classifiers":[
        {
            "category":"Autos & Motor Vehicles",
            "subcategory":"Auto Supplies",
            "type":"Retail Goods"
        }
    ],
    "sg:phone":"+61 2 9637 7977",
    "sg:postcode":"2142",
    "sg:province":"NSW",
    "sg:tags":[
        "tyre"
    ],
    "wof:name":"Bob Jane T-Marts",
    "wof:placetype":"venue"
},
  "geometry": {"coordinates":[151.00627136200001,-33.8283233643],"type":"Point"}
}