{
  "type": "Feature",
  "properties": {
    "addr:full":"William St Plz Gosford NSW 2250",
    "addr:postcode":"2250",
    "addr:street":"William St Plz",
    "iso:country":"AU",
    "sg:address":"William St",
    "sg:city":"Plz Gosford",
    "sg:classifiers":[
        {
            "category":"Social Services",
            "subcategory":"Job Training",
            "type":"Services"
        }
    ],
    "sg:phone":"+61 2 4324 6884",
    "sg:postcode":"2250",
    "sg:province":"NSW",
    "sg:tags":[
        "goldsmith",
        "silversmith"
    ],
    "wof:name":"R & T Hermann",
    "wof:placetype":"venue"
},
  "geometry": {"coordinates":[151.342407227,-33.4260978699],"type":"Point"}
}