{
  "type": "Feature",
  "properties": {
    "addr:full":"76 Lincoln Rd Essendon VIC 3040",
    "addr:housenumber":"76",
    "addr:postcode":"3040",
    "addr:street":"Lincoln Rd",
    "iso:country":"AU",
    "sg:address":"76 Lincoln Rd",
    "sg:city":"Essendon",
    "sg:classifiers":[
        {
            "category":"Banks & Credit Unions",
            "subcategory":"Financial Services",
            "type":"Services"
        }
    ],
    "sg:phone":"+61 3 9379 9313",
    "sg:postcode":"3040",
    "sg:province":"VIC",
    "sg:tags":[
        "planning"
    ],
    "wof:name":"Bob Quadara Financial Planning",
    "wof:placetype":"venue"
},
  "geometry": {"coordinates":[144.910064697,-37.7455635071],"type":"Point"}
}