{
  "type": "Feature",
  "properties": {
    "iso:country":"AU",
    "sg:address":"Shop 5/ 352",
    "sg:city":"Esplanade Scarness",
    "sg:classifiers":[
        {
            "category":"Shopping",
            "subcategory":"Clothing, Apparel, & Fashions",
            "type":"Retail Goods"
        }
    ],
    "sg:phone":"+61 7 4194 5422",
    "sg:postcode":"4655",
    "sg:province":"QLD",
    "sg:tags":[
        "lady",
        "wear"
    ],
    "wof:name":"Beach Bums Swim Wear",
    "wof:placetype":"venue"
},
  "geometry": {"coordinates":[152.80862400000001,-25.259825],"type":"Point"}
}