{
  "type": "Feature",
  "properties": {
    "addr:full":"6 Station Rd Cheltenham VIC 3192",
    "addr:housenumber":"6",
    "addr:postcode":"3192",
    "addr:street":"Station Rd",
    "iso:country":"AU",
    "sg:address":"6 Station Rd",
    "sg:city":"Cheltenham",
    "sg:classifiers":[
        {
            "category":"Shopping",
            "subcategory":"Computers & Home Electronics",
            "type":"Retail Goods"
        }
    ],
    "sg:phone":"+61 3 9583 6633",
    "sg:postcode":"3192",
    "sg:province":"VIC",
    "sg:tags":[
        "hardware",
        "equipment"
    ],
    "wof:name":"Pro P.C. Systems",
    "wof:placetype":"venue"
},
  "geometry": {"coordinates":[145.05580139200001,-37.9671363831],"type":"Point"}
}