{
  "type": "Feature",
  "properties": {
    "addr:full":"90 Moss St Nowra NSW 2541",
    "addr:housenumber":"90",
    "addr:postcode":"2541",
    "addr:street":"Moss St",
    "iso:country":"AU",
    "sg:address":"90 Moss St",
    "sg:city":"Nowra",
    "sg:classifiers":[
        {
            "category":"Education",
            "subcategory":"School",
            "type":"Public Place"
        }
    ],
    "sg:phone":"+61 2 4421 4977",
    "sg:postcode":"2541",
    "sg:province":"NSW",
    "sg:tags":[
        "state",
        "-",
        "nsw"
    ],
    "wof:name":"Nowra High School",
    "wof:placetype":"venue"
},
  "geometry": {"coordinates":[150.60784912099999,-34.8720550537],"type":"Point"}
}