{
  "type": "Feature",
  "properties": {
    "iso:country":"AU",
    "sg:address":"43 Gerrale St",
    "sg:city":"Cronulla",
    "sg:classifiers":[
        {
            "category":"Cafe",
            "type":"Food & Drink"
        }
    ],
    "sg:phone":"+61 2 9523 9381",
    "sg:postcode":"2230",
    "sg:province":"NSW",
    "wof:name":"Cafe 43",
    "wof:placetype":"venue"
},
  "geometry": {"coordinates":[151.15318298299999,-34.0549278259],"type":"Point"}
}