{
  "type": "Feature",
  "properties": {
    "addr:full":"PO Box 434 Avalon NSW 2107",
    "addr:postcode":"2107",
    "iso:country":"AU",
    "sg:address":"PO Box 434",
    "sg:city":"Avalon",
    "sg:classifiers":[
        {
            "category":"Professional",
            "subcategory":"Business Services",
            "type":"Services"
        }
    ],
    "sg:phone":"+61 2 9918 3915",
    "sg:postcode":"2107",
    "sg:province":"NSW",
    "sg:tags":[
        "drafting"
    ],
    "wof:name":"Planatec",
    "wof:placetype":"venue"
},
  "geometry": {"coordinates":[151.33171081500001,-33.6286201477],"type":"Point"}
}