{
  "type": "Feature",
  "properties": {
    "addr:full":"6 Toorak Ave Taren Point NSW 2229",
    "addr:housenumber":"6",
    "addr:postcode":"2229",
    "addr:street":"Toorak Ave",
    "iso:country":"AU",
    "sg:address":"6 Toorak Ave",
    "sg:city":"Taren Point",
    "sg:classifiers":[
        {
            "category":"Professional",
            "subcategory":"Detective & Security Services",
            "type":"Services"
        }
    ],
    "sg:phone":"+61 1300 303 833",
    "sg:postcode":"2229",
    "sg:province":"NSW",
    "sg:tags":[
        "domestic",
        "alarm",
        "commercial",
        "burglar"
    ],
    "wof:name":"Southguard Security",
    "wof:placetype":"venue"
},
  "geometry": {"coordinates":[151.12373352,-34.0195350647],"type":"Point"}
}