{
  "type": "Feature",
  "properties": {
    "iso:country":"AU",
    "sg:address":"32 Alfred St",
    "sg:city":"Belmont",
    "sg:classifiers":[
        {
            "category":"Building & Trades",
            "subcategory":"Construction",
            "type":"Services"
        }
    ],
    "sg:phone":"+61 438 161 174",
    "sg:postcode":"6104",
    "sg:province":"WA",
    "sg:tags":[
        "industrial",
        "commercial",
        "air conditioning"
    ],
    "wof:name":"Techcon Air Conditioning & Refrigeration Services",
    "wof:placetype":"venue"
},
  "geometry": {"coordinates":[115.931518555,-31.9537372589],"type":"Point"}
}