{
  "type": "Feature",
  "properties": {
    "addr:full":"11 Howrah Rd Howrah TAS 7018",
    "addr:housenumber":"11",
    "addr:postcode":"7018",
    "addr:street":"Howrah Rd",
    "iso:country":"AU",
    "sg:address":"11 Howrah Rd",
    "sg:city":"Howrah",
    "sg:classifiers":[
        {
            "category":"Retail",
            "subcategory":"Event Space",
            "type":"Services"
        }
    ],
    "sg:phone":"+61 3 6247 7711",
    "sg:postcode":"7018",
    "sg:province":"TAS",
    "sg:tags":[
        "venue",
        "reception",
        "wedding"
    ],
    "wof:name":"Howrah Recreation Centre",
    "wof:placetype":"venue"
},
  "geometry": {"coordinates":[147.40470886200001,-42.8827095032],"type":"Point"}
}