{
  "type": "Feature",
  "properties": {
    "addr:full":"25 Bolton St Newcastle NSW 2300",
    "addr:housenumber":"25",
    "addr:postcode":"2300",
    "addr:street":"Bolton St",
    "iso:country":"AU",
    "sg:address":"25 Bolton St",
    "sg:city":"Newcastle",
    "sg:classifiers":[
        {
            "category":"Real Estate",
            "subcategory":"Surveying",
            "type":"Services"
        }
    ],
    "sg:phone":"+61 2 4963 1316",
    "sg:postcode":"2300",
    "sg:province":"NSW",
    "sg:tags":[
        "surveyor",
        "land"
    ],
    "wof:name":"Monteath R J",
    "wof:placetype":"venue"
},
  "geometry": {"coordinates":[151.78323399999999,-32.927921],"type":"Point"}
}