{
  "type": "Feature",
  "properties": {
    "addr:full":"48 Bells Line Of Road St North Richmond NSW 2754",
    "addr:housenumber":"48",
    "addr:postcode":"2754",
    "addr:street":"Bells Line Of Road St",
    "iso:country":"AU",
    "sg:address":"48 Bells Line Of Road St",
    "sg:city":"North Richmond",
    "sg:classifiers":[
        {
            "category":"Autos & Motor Vehicles",
            "subcategory":"Fuel & Gas Station",
            "type":"Retail Goods"
        }
    ],
    "sg:phone":"+61 2 4571 1550",
    "sg:postcode":"2754",
    "sg:province":"NSW",
    "wof:name":"Caltex Oil (Aust) Pty Ltd",
    "wof:placetype":"venue"
},
  "geometry": {"coordinates":[150.72007751500001,-33.5801124573],"type":"Point"}
}