{
  "type": "Feature",
  "properties": {
    "addr:full":"80 Penneys Hill Rd Hackham SA 5163",
    "addr:housenumber":"80",
    "addr:postcode":"5163",
    "addr:street":"Penneys Hill Rd",
    "iso:country":"AU",
    "sg:address":"80 Penneys Hill Rd",
    "sg:city":"Hackham",
    "sg:classifiers":[
        {
            "category":"Home & Garden",
            "subcategory":"Carpets & Floor Coverings",
            "type":"Retail Goods"
        }
    ],
    "sg:phone":"+61 412 846 260",
    "sg:postcode":"5163",
    "sg:province":"SA",
    "sg:tags":[
        "layer",
        "planner"
    ],
    "wof:name":"Bode H & R",
    "wof:placetype":"venue"
},
  "geometry": {"coordinates":[138.525787353,-35.1472969055],"type":"Point"}
}