{
  "type": "Feature",
  "properties": {
    "addr:full":"Lot 23 Baggs Rd Jindabyne NSW 2627",
    "addr:postcode":"2627",
    "addr:street":"Baggs Rd",
    "iso:country":"AU",
    "sg:address":"Lot 23 Baggs Rd",
    "sg:city":"Jindabyne",
    "sg:phone":"+61 2 6456 1842",
    "sg:postcode":"2627",
    "sg:province":"NSW",
    "wof:name":"Jindabyne Plumbing Supplies",
    "wof:placetype":"venue"
},
  "geometry": {"coordinates":[148.60256957999999,-36.4362068176],"type":"Point"}
}