{
  "type": "Feature",
  "properties": {
    "addr:full":"1 McLaren Pde Port Adelaide SA 5015",
    "addr:housenumber":"1",
    "addr:postcode":"5015",
    "addr:street":"Mclaren Pde",
    "iso:country":"AU",
    "sg:address":"1 McLaren Pde",
    "sg:city":"Port Adelaide",
    "sg:classifiers":[
        {
            "category":"Education",
            "subcategory":"University",
            "type":"Public Place"
        }
    ],
    "sg:phone":"+61 8 8444 0400",
    "sg:postcode":"5015",
    "sg:province":"SA",
    "sg:tags":[
        "educational",
        "organisation",
        "cultural"
    ],
    "wof:name":"Country Arts SA",
    "wof:placetype":"venue"
},
  "geometry": {"coordinates":[138.50425720199999,-34.8429946899],"type":"Point"}
}