{
  "type": "Feature",
  "properties": {
    "addr:full":"322 Toorak Rd South Yarra VIC 3141",
    "addr:housenumber":"322",
    "addr:postcode":"3141",
    "addr:street":"Toorak Rd",
    "iso:country":"AU",
    "sg:address":"322 Toorak Rd",
    "sg:city":"South Yarra",
    "sg:classifiers":[
        {
            "category":"Personal",
            "subcategory":"Skin Care",
            "type":"Services"
        }
    ],
    "sg:phone":"+61 3 9827 8547",
    "sg:postcode":"3141",
    "sg:province":"VIC",
    "sg:tags":[
        "hair",
        "product"
    ],
    "wof:name":"South Yarra Hairdressing Supplies Pty Ltd",
    "wof:placetype":"venue"
},
  "geometry": {"coordinates":[144.99455261200001,-37.8410835266],"type":"Point"}
}