{
  "type": "Feature",
  "properties": {
    "iso:country":"AU",
    "sg:address":"PO Box 198 St",
    "sg:city":"Peters",
    "sg:classifiers":[
        {
            "category":"Structure",
            "subcategory":"Building",
            "type":"Public Place"
        }
    ],
    "sg:phone":"+61 2 9979 3341",
    "sg:postcode":"2044",
    "sg:province":"NSW",
    "sg:tags":[
        "sail",
        "shade"
    ],
    "wof:name":"Sail Structures Australia",
    "wof:placetype":"venue"
},
  "geometry": {"coordinates":[151.177353,-33.914299],"type":"Point"}
}