{
  "type": "Feature",
  "properties": {
    "iso:country":"AU",
    "sg:address":"Shop E, 59 Battams Rd",
    "sg:city":"Royston Park",
    "sg:classifiers":[
        {
            "category":"Social Services",
            "subcategory":"Adult Care",
            "type":"Services"
        }
    ],
    "sg:phone":"+61 8 8362 3777",
    "sg:postcode":"5070",
    "sg:province":"SA",
    "sg:tags":[
        "aged"
    ],
    "wof:name":"MaryAnns Kitchen",
    "wof:placetype":"venue"
},
  "geometry": {"coordinates":[138.63052368199999,-34.8953704834],"type":"Point"}
}