{
  "type": "Feature",
  "properties": {
    "addr:full":"27 Albert St Busselton WA 6280",
    "addr:housenumber":"27",
    "addr:postcode":"6280",
    "addr:street":"Albert St",
    "iso:country":"AU",
    "sg:address":"27 Albert St",
    "sg:city":"Busselton",
    "sg:classifiers":[
        {
            "category":"Cinema",
            "subcategory":"Movie Theater",
            "type":"Entertainment"
        }
    ],
    "sg:phone":"+61 8 9752 3655",
    "sg:postcode":"6280",
    "sg:province":"WA",
    "wof:name":"Ace Cinemas Busselton",
    "wof:placetype":"venue"
},
  "geometry": {"coordinates":[115.341819763,-33.6526298523],"type":"Point"}
}