{
  "type": "Feature",
  "properties": {
    "addr:full":"5 Patrick St Blacktown NSW 2148",
    "addr:housenumber":"5",
    "addr:postcode":"2148",
    "addr:street":"Patrick St",
    "iso:country":"AU",
    "sg:address":"5 Patrick St",
    "sg:city":"Blacktown",
    "sg:classifiers":[
        {
            "category":"Shopping",
            "subcategory":"Music",
            "type":"Retail Goods"
        }
    ],
    "sg:phone":"+61 2 9831 2978",
    "sg:postcode":"2148",
    "sg:province":"NSW",
    "sg:tags":[
        "store"
    ],
    "wof:name":"Organised Noise Pty Ltd",
    "wof:placetype":"venue"
},
  "geometry": {"coordinates":[150.948944092,-33.8248519897],"type":"Point"}
}