{
  "type": "Feature",
  "properties": {
    "addr:full":"PO Box 505 Belgian Gardens QLD 4810",
    "addr:postcode":"4810",
    "iso:country":"AU",
    "sg:address":"PO Box 505",
    "sg:city":"Belgian Gardens",
    "sg:classifiers":[
        {
            "category":"Home & Garden",
            "subcategory":"Household Appliances",
            "type":"Retail Goods"
        }
    ],
    "sg:phone":"+61 400 726 834",
    "sg:postcode":"4810",
    "sg:province":"QLD",
    "sg:tags":[
        "equipment",
        "gas"
    ],
    "wof:name":"Coastal Gasfitting & Plumbing (Townsville)",
    "wof:placetype":"venue"
},
  "geometry": {"coordinates":[146.798767,-19.2453],"type":"Point"}
}