{
  "type": "Feature",
  "properties": {
    "addr:full":"Shop 3, 4 Textile Ave Warana QLD 4575",
    "addr:housenumber":"shop;4",
    "addr:postcode":"4575",
    "addr:street":"Textile Ave",
    "iso:country":"AU",
    "sg:address":"Shop 3, 4 Textile Ave",
    "sg:city":"Warana",
    "sg:classifiers":[
        {
            "category":"Arena",
            "subcategory":"Sports Club",
            "type":"Entertainment"
        }
    ],
    "sg:phone":"+61 417 608 240",
    "sg:postcode":"4575",
    "sg:province":"QLD",
    "sg:tags":[
        "defence",
        "supply",
        "self",
        "instruction",
        "martial art"
    ],
    "wof:name":"Sunshine Coast Thai Boxing Centre",
    "wof:placetype":"venue"
},
  "geometry": {"coordinates":[153.12411499999999,-26.727795],"type":"Point"}
}