{
  "type": "Feature",
  "properties": {
    "addr:full":"23 Chief St Brompton SA 5007",
    "addr:housenumber":"23",
    "addr:postcode":"5007",
    "addr:street":"Chief St",
    "iso:country":"AU",
    "sg:address":"23 Chief St",
    "sg:city":"Brompton",
    "sg:classifiers":[
        {
            "category":"Home & Garden",
            "subcategory":"Building Materials",
            "type":"Retail Goods"
        }
    ],
    "sg:phone":"+61 8 8152 0759",
    "sg:postcode":"5007",
    "sg:province":"SA",
    "sg:tags":[
        "supply"
    ],
    "wof:name":"Seima",
    "wof:placetype":"venue"
},
  "geometry": {"coordinates":[138.57565307600001,-34.9021682739],"type":"Point"}
}