{
  "type": "Feature",
  "properties": {
    "iso:country":"AU",
    "sg:address":"6 Finniss St",
    "sg:city":"Marion",
    "sg:classifiers":[
        {
            "category":"Health Services",
            "subcategory":"Health Practitioner",
            "type":"Services"
        }
    ],
    "sg:phone":"+61 8 8357 4988",
    "sg:postcode":"5043",
    "sg:province":"SA",
    "sg:tags":[
        "physiotherapist"
    ],
    "wof:name":"PhysioXtra Marion",
    "wof:placetype":"venue"
},
  "geometry": {"coordinates":[138.556885,-35.007061],"type":"Point"}
}