{
  "type": "Feature",
  "properties": {
    "addr:full":"1345 Ross River Rd Kelso QLD 4815",
    "addr:housenumber":"1345",
    "addr:postcode":"4815",
    "addr:street":"Ross River Rd",
    "iso:country":"AU",
    "sg:address":"1345 Ross River Rd",
    "sg:city":"Kelso",
    "sg:classifiers":[
        {
            "category":"Real Estate",
            "subcategory":"Surveying",
            "type":"Services"
        }
    ],
    "sg:phone":"+61 7 4774 0452",
    "sg:postcode":"4815",
    "sg:province":"QLD",
    "sg:tags":[
        "surveyor",
        "land"
    ],
    "wof:name":"John Weber Surveys",
    "wof:placetype":"venue"
},
  "geometry": {"coordinates":[146.730133,-19.373842],"type":"Point"}
}