{
  "type": "Feature",
  "properties": {
    "iso:country":"AU",
    "sg:address":"103 Brunswick Rd",
    "sg:city":"Brunswick East",
    "sg:classifiers":[
        {
            "category":"Wholesale",
            "subcategory":"Furniture",
            "type":"Manufacturing & Wholesale Goods"
        }
    ],
    "sg:phone":"+61 3 9381 4333",
    "sg:postcode":"3057",
    "sg:province":"VIC",
    "sg:tags":[
        "wholesaler",
        "mfrs"
    ],
    "wof:name":"Indoor Outdoor Imports",
    "wof:placetype":"venue"
},
  "geometry": {"coordinates":[144.971466064,-37.7782211304],"type":"Point"}
}