{
  "type": "Feature",
  "properties": {
    "addr:full":"1/ 30 Hall St Moonee Ponds VIC 3039",
    "addr:housenumber":"/ 30",
    "addr:postcode":"3039",
    "addr:street":"Hall St",
    "iso:country":"AU",
    "sg:address":"1/ 30 Hall St",
    "sg:city":"Moonee Ponds",
    "sg:classifiers":[
        {
            "category":"Health Services",
            "subcategory":"Health Practitioner",
            "type":"Services"
        }
    ],
    "sg:phone":"+61 3 9734 1225",
    "sg:postcode":"3039",
    "sg:province":"VIC",
    "sg:tags":[
        "acupuncture"
    ],
    "wof:name":"Blue Dragon Health Services",
    "wof:placetype":"venue"
},
  "geometry": {"coordinates":[144.92132599999999,-37.7658],"type":"Point"}
}