{
  "type": "Feature",
  "properties": {
    "addr:full":"Unit 3/ 4 Industrial Ave Wacol QLD 4076",
    "addr:housenumber":"4",
    "addr:postcode":"4076",
    "addr:street":"Industrial Ave",
    "iso:country":"AU",
    "sg:address":"Unit 3/ 4 Industrial Ave",
    "sg:city":"Wacol",
    "sg:classifiers":[
        {
            "category":"Wholesale",
            "subcategory":"Painting Supplies",
            "type":"Manufacturing & Wholesale Goods"
        }
    ],
    "sg:phone":"+61 7 3879 4088",
    "sg:postcode":"4076",
    "sg:province":"QLD",
    "sg:tags":[
        "equipment",
        "spraying"
    ],
    "wof:name":"Bravo Company Pty Ltd",
    "wof:placetype":"venue"
},
  "geometry": {"coordinates":[152.92994689899999,-27.591299057],"type":"Point"}
}