{
  "type": "Feature",
  "properties": {
    "addr:full":"Level 11 32 Martin Pl Sydney NSW 2000",
    "addr:housenumber":"32",
    "addr:postcode":"2000",
    "addr:street":"Martin Pl",
    "iso:country":"AU",
    "sg:address":"Level 11 32 Martin Pl",
    "sg:city":"Sydney",
    "sg:classifiers":[
        {
            "category":"Professional",
            "subcategory":"Accounting & Tax Preparation",
            "type":"Services"
        }
    ],
    "sg:phone":"+61 2 9221 0444",
    "sg:postcode":"2000",
    "sg:province":"NSW",
    "sg:tags":[
        "accountant",
        "auditor"
    ],
    "wof:name":"DFK Richard Hill Pty Ltd",
    "wof:placetype":"venue"
},
  "geometry": {"coordinates":[151.20916748100001,-33.8674621582],"type":"Point"}
}