{
  "type": "Feature",
  "properties": {
    "iso:country":"AU",
    "sg:address":"Suite 305/ 161 Maitland Rd",
    "sg:city":"Mayfield",
    "sg:classifiers":[
        {
            "category":"Professional",
            "subcategory":"Detective & Security Services",
            "type":"Services"
        }
    ],
    "sg:phone":"+61 2 4969 4800",
    "sg:postcode":"2540",
    "sg:province":"NSW",
    "sg:tags":[
        "domestic",
        "alarm",
        "commercial",
        "burglar"
    ],
    "wof:name":"Newcastle Security",
    "wof:placetype":"venue"
},
  "geometry": {"coordinates":[150.67332458499999,-34.9161071777],"type":"Point"}
}