{
  "type": "Feature",
  "properties": {
    "iso:country":"AU",
    "sg:address":"45 Peninsula Ave",
    "sg:city":"Rye",
    "sg:classifiers":[
        {
            "category":"Professional",
            "type":"Services"
        }
    ],
    "sg:phone":"+61 3 5985 2383",
    "sg:postcode":"3941",
    "sg:province":"VIC",
    "sg:tags":[
        "shop",
        "fitting"
    ],
    "wof:name":"Coastal Shopfitters",
    "wof:placetype":"venue"
},
  "geometry": {"coordinates":[144.807174683,-38.3762283325],"type":"Point"}
}