{
  "type": "Feature",
  "properties": {
    "iso:country":"AU",
    "sg:address":"52 Childers St",
    "sg:city":"North Adelaide",
    "sg:classifiers":[
        {
            "category":"Health Services",
            "subcategory":"Doctor",
            "type":"Services"
        }
    ],
    "sg:phone":"+61 417 803 919",
    "sg:postcode":"5006",
    "sg:province":"SA",
    "sg:tags":[
        "medical",
        "practitioner"
    ],
    "wof:name":"Sly Jason P Dr",
    "wof:placetype":"venue"
},
  "geometry": {"coordinates":[138.59303283700001,-34.9036064148],"type":"Point"}
}