{
  "type": "Feature",
  "properties": {
    "iso:country":"AU",
    "sg:address":"725 George Street",
    "sg:city":"Sydney",
    "sg:classifiers":[
        {
            "category":"Health Services",
            "subcategory":"Health Practitioner",
            "type":"Services"
        }
    ],
    "sg:phone":"+61 2 9280 1133",
    "sg:postcode":"2000",
    "sg:province":"NSW",
    "sg:tags":[
        "herbalist"
    ],
    "sg:website":"http://www.btrt.com.au",
    "wof:name":"Beijing Tong Ren Tang",
    "wof:placetype":"venue"
},
  "geometry": {"coordinates":[151.20463562,-33.8811798096],"type":"Point"}
}