{
  "type": "Feature",
  "properties": {
    "addr:full":"Shop 3/ 62 Richmond St Rockhampton QLD 4700",
    "addr:housenumber":"shop 3 / 62",
    "addr:postcode":"4700",
    "addr:street":"Richmond St",
    "iso:country":"AU",
    "sg:address":"Shop 3/ 62 Richmond St",
    "sg:city":"Rockhampton",
    "sg:classifiers":[
        {
            "category":"Professional",
            "subcategory":"Employment Agencies",
            "type":"Services"
        }
    ],
    "sg:phone":"+61 7 4927 7400",
    "sg:postcode":"4700",
    "sg:province":"QLD",
    "wof:name":"Adecco",
    "wof:placetype":"venue"
},
  "geometry": {"coordinates":[150.524291992,-23.360200882],"type":"Point"}
}