{
  "type": "Feature",
  "properties": {
    "addr:full":"19 Langtree Ave Mildura VIC 3500",
    "addr:housenumber":"19",
    "addr:postcode":"3500",
    "addr:street":"Langtree Ave",
    "iso:country":"AU",
    "sg:address":"19 Langtree Ave",
    "sg:city":"Mildura",
    "sg:classifiers":[
        {
            "category":"Retail",
            "subcategory":"Event Space",
            "type":"Services"
        }
    ],
    "sg:phone":"+61 3 5023 0855",
    "sg:postcode":"3500",
    "sg:province":"VIC",
    "sg:tags":[
        "function",
        "organiser"
    ],
    "wof:name":"Henrys Restaurant & Liquid Lounge",
    "wof:placetype":"venue"
},
  "geometry": {"coordinates":[142.16252136200001,-34.183139801],"type":"Point"}
}