{
  "type": "Feature",
  "properties": {
    "addr:full":"84 Boundary Rd Rocklea QLD 4106",
    "addr:housenumber":"84",
    "addr:postcode":"4106",
    "addr:street":"Boundary Rd",
    "iso:country":"AU",
    "sg:address":"84 Boundary Rd",
    "sg:city":"Rocklea",
    "sg:classifiers":[
        {
            "category":"Shopping",
            "subcategory":"Crafts & Fabrics",
            "type":"Retail Goods"
        }
    ],
    "sg:phone":"+61 7 3277 9733",
    "sg:postcode":"4106",
    "sg:province":"QLD",
    "sg:tags":[
        "perforating",
        "perforated",
        "material"
    ],
    "wof:name":"Expanded & Metal Perforators Pty Ltd",
    "wof:placetype":"venue"
},
  "geometry": {"coordinates":[152.994415283,-27.5641937256],"type":"Point"}
}