{
  "type": "Feature",
  "properties": {
    "addr:full":"12 Cypress St Tamworth NSW 2340",
    "addr:housenumber":"12",
    "addr:postcode":"2340",
    "addr:street":"Cypress St",
    "iso:country":"AU",
    "sg:address":"12 Cypress St",
    "sg:city":"Tamworth",
    "sg:classifiers":[
        {
            "category":"Insurance",
            "subcategory":"Life Insurance",
            "type":"Services"
        }
    ],
    "sg:phone":"+61 2 6765 6997",
    "sg:postcode":"2340",
    "sg:province":"NSW",
    "wof:name":"Colonial Mutual",
    "wof:placetype":"venue"
},
  "geometry": {"coordinates":[150.903106689,-31.1099910736],"type":"Point"}
}