{
  "type": "Feature",
  "properties": {
    "iso:country":"AU",
    "sg:address":"21 Activity St (cnr Activity St)",
    "sg:city":"Warwick",
    "sg:classifiers":[
        {
            "category":"Manufacturing",
            "subcategory":"Buildings",
            "type":"Manufacturing & Wholesale Goods"
        }
    ],
    "sg:phone":"+61 1800 688 044",
    "sg:postcode":"4370",
    "sg:province":"QLD",
    "sg:tags":[
        "transportable",
        "domestic",
        "relocatable"
    ],
    "wof:name":"Westbuilt Quality Homes",
    "wof:placetype":"venue"
},
  "geometry": {"coordinates":[152.038894653,-28.2382278442],"type":"Point"}
}