{
  "type": "Feature",
  "properties": {
    "addr:full":"82 Belmont Ave Belmont WA 6104",
    "addr:housenumber":"82",
    "addr:postcode":"6104",
    "addr:street":"Belmont Ave",
    "iso:country":"AU",
    "sg:address":"82 Belmont Ave",
    "sg:city":"Belmont",
    "sg:classifiers":[
        {
            "category":"Professional",
            "subcategory":"Detective & Security Services",
            "type":"Services"
        }
    ],
    "sg:phone":"+61 8 9277 5266",
    "sg:postcode":"6104",
    "sg:province":"WA",
    "sg:tags":[
        "equipment",
        "window",
        "doors"
    ],
    "wof:name":"Aaaaabsolute Glass Service",
    "wof:placetype":"venue"
},
  "geometry": {"coordinates":[115.923789978,-31.9577007294],"type":"Point"}
}