{
  "type": "Feature",
  "properties": {
    "addr:full":"48 Heather St Heatherbrae NSW 2324",
    "addr:housenumber":"48",
    "addr:postcode":"2324",
    "addr:street":"Heather St",
    "iso:country":"AU",
    "sg:address":"48 Heather St",
    "sg:city":"Heatherbrae",
    "sg:phone":"+61 2 4987 3414",
    "sg:postcode":"2324",
    "sg:province":"NSW",
    "wof:name":"1st Choice Tanks",
    "wof:placetype":"venue"
},
  "geometry": {"coordinates":[151.733551025,-32.7859992981],"type":"Point"}
}