{
  "type": "Feature",
  "properties": {
    "iso:country":"AU",
    "sg:address":"19- 21",
    "sg:city":"Belmont Av Belmont",
    "sg:classifiers":[
        {
            "category":"Professional",
            "subcategory":"Detective & Security Services",
            "type":"Services"
        }
    ],
    "sg:phone":"+61 8 9227 6969",
    "sg:postcode":"6104",
    "sg:province":"WA",
    "sg:tags":[
        "equipment",
        "window",
        "doors"
    ],
    "wof:name":"Guardall Security",
    "wof:placetype":"venue"
},
  "geometry": {"coordinates":[115.918891907,-31.9531097412],"type":"Point"}
}