{
  "type": "Feature",
  "properties": {
    "iso:country":"AU",
    "sg:address":"90 Wyman St",
    "sg:city":"Broken Hill",
    "sg:classifiers":[
        {
            "category":"Taxi",
            "type":"Transportation"
        }
    ],
    "sg:phone":"+61 8 8087 6409",
    "sg:postcode":"2880",
    "sg:province":"NSW",
    "sg:tags":[
        "truck"
    ],
    "wof:name":"Turleys Taxi Trucks",
    "wof:placetype":"venue"
},
  "geometry": {"coordinates":[141.445587158,-31.946105957],"type":"Point"}
}