{
  "type": "Feature",
  "properties": {
    "addr:full":"Building A Stand 7-10 Sydney Markets Flemington NSW 2140",
    "addr:housenumber":"7-10;markets",
    "addr:postcode":"2140",
    "addr:street":"Sydney",
    "iso:country":"AU",
    "sg:address":"Building A Stand 7-10 Sydney Markets",
    "sg:city":"Flemington",
    "sg:classifiers":[
        {
            "category":"Food & Beverages",
            "subcategory":"Fruits & Vegetables",
            "type":"Retail Goods"
        }
    ],
    "sg:phone":"+61 2 9764 4566",
    "sg:postcode":"2140",
    "sg:province":"NSW",
    "sg:tags":[
        "wholesale"
    ],
    "wof:name":"Ralph Johns Pty Ltd",
    "wof:placetype":"venue"
},
  "geometry": {"coordinates":[151.066696167,-33.8666992188],"type":"Point"}
}