{
  "type": "Feature",
  "properties": {
    "addr:full":"PO Box 156 Tenterfield NSW 2372",
    "addr:postcode":"2372",
    "iso:country":"AU",
    "sg:address":"PO Box 156",
    "sg:city":"Tenterfield",
    "sg:classifiers":[
        {
            "category":"Utilities",
            "subcategory":"Electric",
            "type":"Services"
        }
    ],
    "sg:phone":"+61 402 115 416",
    "sg:postcode":"2372",
    "sg:province":"NSW",
    "sg:tags":[
        "electrical",
        "contractor"
    ],
    "wof:name":"Greg J Milne-Electrical",
    "wof:placetype":"venue"
},
  "geometry": {"coordinates":[152.01902770999999,-29.0539798737],"type":"Point"}
}