{
  "type": "Feature",
  "properties": {
    "addr:full":"PO Box 102 Hillston NSW 2675",
    "addr:postcode":"2675",
    "iso:country":"AU",
    "sg:address":"PO Box 102",
    "sg:city":"Hillston",
    "sg:classifiers":[
        {
            "category":"Building & Trades",
            "subcategory":"Equipment Rental",
            "type":"Services"
        }
    ],
    "sg:phone":"+61 2 6967 2149",
    "sg:postcode":"2675",
    "sg:province":"NSW",
    "sg:tags":[
        "crane",
        "hire"
    ],
    "wof:name":"Michael & Mandy Hutchison Pty Ltd",
    "wof:placetype":"venue"
},
  "geometry": {"coordinates":[145.536178589,-33.4815216064],"type":"Point"}
}