{
  "type": "Feature",
  "properties": {
    "addr:full":"Suite 1, Lang Offices, 19 Lang Parade Auchenflower QLD 4066",
    "addr:housenumber":"19",
    "addr:postcode":"4066",
    "addr:street":"Lang Parade",
    "iso:country":"AU",
    "sg:address":"Suite 1, Lang Offices, 19",
    "sg:city":"Lang Parade Auchenflower",
    "sg:classifiers":[
        {
            "category":"Health Services",
            "subcategory":"Doctor",
            "type":"Services"
        }
    ],
    "sg:phone":"+61 7 3345 7117",
    "sg:postcode":"4066",
    "sg:province":"QLD",
    "sg:tags":[
        "medical",
        "practitioner"
    ],
    "wof:name":"Craig Mark Dr",
    "wof:placetype":"venue"
},
  "geometry": {"coordinates":[153.001754761,-27.4740123749],"type":"Point"}
}