{
  "type": "Feature",
  "properties": {
    "addr:full":"Suite 9, 80 Cecil Ave Castle Hill NSW 2154",
    "addr:housenumber":"80",
    "addr:postcode":"2154",
    "addr:street":"Cecil Ave",
    "iso:country":"AU",
    "sg:address":"Suite 9, 80 Cecil Ave",
    "sg:city":"Castle Hill",
    "sg:classifiers":[
        {
            "category":"Personal",
            "type":"Services"
        }
    ],
    "sg:phone":"+61 2 9899 5208",
    "sg:postcode":"2154",
    "sg:province":"NSW",
    "sg:tags":[
        "reducing",
        "treatment",
        "weight"
    ],
    "wof:name":"Sue Radd and Associates",
    "wof:placetype":"venue"
},
  "geometry": {"coordinates":[151.004592895,-33.7356033325],"type":"Point"}
}