{
  "type": "Feature",
  "properties": {
    "addr:full":"7-9 Ormond Rd Geelong East VIC 3219",
    "addr:housenumber":"7-9",
    "addr:postcode":"3219",
    "addr:street":"Ormond Rd",
    "iso:country":"AU",
    "sg:address":"7-9 Ormond Rd",
    "sg:city":"Geelong East",
    "sg:classifiers":[
        {
            "category":"Shopping",
            "subcategory":"Clothing, Apparel, & Fashions",
            "type":"Retail Goods"
        }
    ],
    "sg:phone":"+61 3 5221 2233",
    "sg:postcode":"3219",
    "sg:province":"VIC",
    "sg:tags":[
        "accessory"
    ],
    "wof:name":"Gorgeous Jewellery",
    "wof:placetype":"venue"
},
  "geometry": {"coordinates":[144.37260437,-38.1556739807],"type":"Point"}
}