{
  "type": "Feature",
  "properties": {
    "iso:country":"AU",
    "sg:address":"14 Grandview Pde",
    "sg:city":"Moolap",
    "sg:classifiers":[
        {
            "category":"Professional",
            "subcategory":"Engineering",
            "type":"Services"
        }
    ],
    "sg:phone":"+61 3 5248 7447",
    "sg:postcode":"3221",
    "sg:province":"VIC",
    "sg:tags":[
        "manufacturing",
        "engineer"
    ],
    "wof:name":"Phoenix Fabrication & Welding Pty Ltd",
    "wof:placetype":"venue"
},
  "geometry": {"coordinates":[144.419174,-38.166752],"type":"Point"}
}