{
  "type": "Feature",
  "properties": {
    "addr:full":"Cnr Bay Rd & John Watson Drv Mt Gambier SA 5290",
    "addr:postcode":"5290",
    "addr:street":"Cnr Bay Rd & John Watson Drv",
    "iso:country":"AU",
    "sg:address":"Cnr Bay Rd & John Watson Drv",
    "sg:city":"Mt Gambier",
    "sg:classifiers":[
        {
            "category":"Landmark",
            "subcategory":"Tourist Information",
            "type":"Public Place"
        }
    ],
    "sg:phone":"+61 8 8723 1199",
    "sg:postcode":"5290",
    "sg:province":"SA",
    "sg:tags":[
        "bureau"
    ],
    "wof:name":"Aquifer Tours",
    "wof:placetype":"venue"
},
  "geometry": {"coordinates":[140.780563,-37.828697],"type":"Point"}
}