{
  "type": "Feature",
  "properties": {
    "addr:full":"60A Cox Ave Kingswood NSW 2747",
    "addr:housenumber":"60a",
    "addr:postcode":"2747",
    "addr:street":"Cox Ave",
    "iso:country":"AU",
    "sg:address":"60A Cox Ave",
    "sg:city":"Kingswood",
    "sg:classifiers":[
        {
            "category":"Arts & Performance",
            "subcategory":"Dance",
            "type":"Entertainment"
        }
    ],
    "sg:phone":"+61 2 4721 3750",
    "sg:postcode":"2747",
    "sg:province":"NSW",
    "sg:tags":[
        "theatrical",
        "ballet",
        "tuition"
    ],
    "wof:name":"PAWS (Performance Art Workshop)",
    "wof:placetype":"venue"
},
  "geometry": {"coordinates":[150.719940186,-33.7574195862],"type":"Point"}
}