{
  "type": "Feature",
  "properties": {
    "addr:full":"18a Florence St Moonah TAS 7009",
    "addr:housenumber":"18a",
    "addr:postcode":"7009",
    "addr:street":"Florence St",
    "iso:country":"AU",
    "sg:address":"18a Florence St",
    "sg:city":"Moonah",
    "sg:classifiers":[
        {
            "category":"Arts & Performance",
            "subcategory":"Theater",
            "type":"Entertainment"
        }
    ],
    "sg:phone":"+61 413 028 799",
    "sg:postcode":"7009",
    "sg:province":"TAS",
    "sg:tags":[
        "theatrical",
        "supply"
    ],
    "wof:name":"Watkins Rosemary",
    "wof:placetype":"venue"
},
  "geometry": {"coordinates":[147.29391479500001,-42.8505516052],"type":"Point"}
}