{
  "type": "Feature",
  "properties": {
    "addr:full":"9 Querrin Ave Willetton WA 6155",
    "addr:housenumber":"9",
    "addr:postcode":"6155",
    "addr:street":"Querrin Ave",
    "iso:country":"AU",
    "sg:address":"9 Querrin Ave",
    "sg:city":"Willetton",
    "sg:classifiers":[
        {
            "category":"Utilities",
            "subcategory":"Electric",
            "type":"Services"
        }
    ],
    "sg:phone":"+61 8 9457 5578",
    "sg:postcode":"6155",
    "sg:province":"WA",
    "sg:tags":[
        "electrical",
        "contractor"
    ],
    "wof:name":"Dunne J & S Electrics",
    "wof:placetype":"venue"
},
  "geometry": {"coordinates":[115.889923,-32.046181],"type":"Point"}
}