{
  "type": "Feature",
  "properties": {
    "addr:full":"297 Ocean Drv Bunbury WA 6230",
    "addr:housenumber":"297",
    "addr:postcode":"6230",
    "addr:street":"Ocean Drv",
    "iso:country":"AU",
    "sg:address":"297 Ocean Drv",
    "sg:city":"Bunbury",
    "sg:classifiers":[
        {
            "category":"Retail",
            "subcategory":"Driving School",
            "type":"Services"
        }
    ],
    "sg:phone":"+61 8 9795 8309",
    "sg:postcode":"6230",
    "sg:province":"WA",
    "wof:name":"Frenchy Driving School",
    "wof:placetype":"venue"
},
  "geometry": {"coordinates":[115.625908,-33.372047],"type":"Point"}
}