{
  "type": "Feature",
  "properties": {
    "addr:full":"2 Allen St Waterloo NSW 2017",
    "addr:housenumber":"2",
    "addr:postcode":"2017",
    "addr:street":"Allen St",
    "iso:country":"AU",
    "sg:address":"2 Allen St",
    "sg:city":"Waterloo",
    "sg:classifiers":[
        {
            "category":"Autos & Motor Vehicles",
            "subcategory":"Auto Supplies",
            "type":"Retail Goods"
        }
    ],
    "sg:phone":"+61 2 9699 3676",
    "sg:postcode":"2017",
    "sg:province":"NSW",
    "sg:tags":[
        "tyre"
    ],
    "wof:name":"Motorworks",
    "wof:placetype":"venue"
},
  "geometry": {"coordinates":[151.20213317899999,-33.9028358459],"type":"Point"}
}