{
  "type": "Feature",
  "properties": {
    "addr:full":"\"Strathyre\" Cadgee Rd Naracoorte SA 5271",
    "addr:postcode":"5271",
    "addr:street":"Cadgee Rd",
    "iso:country":"AU",
    "sg:address":"\"Strathyre\" Cadgee Rd",
    "sg:city":"Naracoorte",
    "sg:classifiers":[
        {
            "category":"Farming",
            "subcategory":"Farm & Veterinary Services",
            "type":"Manufacturing & Wholesale Goods"
        }
    ],
    "sg:phone":"+61 8 8762 2758",
    "sg:postcode":"5271",
    "sg:province":"SA",
    "sg:tags":[
        "seedsman"
    ],
    "wof:name":"Strathyre Proprietors",
    "wof:placetype":"venue"
},
  "geometry": {"coordinates":[140.74648999999999,-36.948597],"type":"Point"}
}