{
  "type": "Feature",
  "properties": {
    "iso:country":"AU",
    "sg:address":"63 Mount Lewis Ave",
    "sg:city":"Punchbowl",
    "sg:classifiers":[
        {
            "category":"Building & Trades",
            "subcategory":"Cleaning & Sanitation",
            "type":"Services"
        }
    ],
    "sg:phone":"+61 2 9793 3756",
    "sg:postcode":"2196",
    "sg:province":"NSW",
    "sg:tags":[
        "chemical",
        "pressure",
        "steam",
        "contractor"
    ],
    "wof:name":"ABC Cleaning Professionals",
    "wof:placetype":"venue"
},
  "geometry": {"coordinates":[151.052246,-33.919399],"type":"Point"}
}