{
  "type": "Feature",
  "properties": {
    "addr:full":"105 / 233 Chapel St St Prahran VIC 3181",
    "addr:housenumber":"105 / 233",
    "addr:postcode":"3181",
    "addr:street":"Chapel St St",
    "iso:country":"AU",
    "sg:address":"105 / 233 Chapel St St",
    "sg:city":"Prahran",
    "sg:classifiers":[
        {
            "category":"Professional",
            "subcategory":"Art Services",
            "type":"Services"
        }
    ],
    "sg:phone":"+61 3 9510 9699",
    "sg:postcode":"3181",
    "sg:province":"VIC",
    "sg:tags":[
        "graphic",
        "designer"
    ],
    "wof:name":"Studio Brave Pty Ltd",
    "wof:placetype":"venue"
},
  "geometry": {"coordinates":[144.99342346200001,-37.8503036499],"type":"Point"}
}