{
  "type": "Feature",
  "properties": {
    "iso:country":"AU",
    "sg:address":"69 Jellicoe St",
    "sg:city":"Lidcombe",
    "sg:classifiers":[
        {
            "category":"Autos & Motor Vehicles",
            "subcategory":"Auto Supplies",
            "type":"Retail Goods"
        }
    ],
    "sg:phone":"+61 2 9748 2777",
    "sg:postcode":"2141",
    "sg:province":"NSW",
    "sg:tags":[
        "accessory"
    ],
    "wof:name":"O.E.M Products Pty Ltd",
    "wof:placetype":"venue"
},
  "geometry": {"coordinates":[151.055908203,-33.852722168],"type":"Point"}
}