{
  "type": "Feature",
  "properties": {
    "iso:country":"AU",
    "sg:address":"84 Gibbons St",
    "sg:city":"Narrabri",
    "sg:classifiers":[
        {
            "category":"Health Services",
            "subcategory":"Nursing And Care Facility",
            "type":"Services"
        }
    ],
    "sg:phone":"+61 2 6792 3044",
    "sg:postcode":"2390",
    "sg:province":"NSW",
    "sg:tags":[
        "home"
    ],
    "wof:name":"Jessie Hunt Nursing Home",
    "wof:placetype":"venue"
},
  "geometry": {"coordinates":[149.78092956500001,-30.3343849182],"type":"Point"}
}