{
  "type": "Feature",
  "properties": {
    "addr:full":"24 Corina St Phillip ACT 2606",
    "addr:housenumber":"24",
    "addr:postcode":"2606",
    "addr:street":"Corina St",
    "iso:country":"AU",
    "sg:address":"24 Corina St",
    "sg:city":"Phillip",
    "sg:classifiers":[
        {
            "category":"Insurance",
            "subcategory":"Hazard Insurance",
            "type":"Services"
        }
    ],
    "sg:phone":"+61 13 25 55",
    "sg:postcode":"2606",
    "sg:province":"ACT",
    "sg:tags":[
        "motor",
        "vehicle"
    ],
    "wof:name":"Australian Pensioners Insurance Agency",
    "wof:placetype":"venue"
},
  "geometry": {"coordinates":[149.09544372600001,-35.3468704224],"type":"Point"}
}