{
  "type": "Feature",
  "properties": {
    "addr:full":"858 Pascoe Vale Rd Glenroy VIC 3046",
    "addr:housenumber":"858",
    "addr:postcode":"3046",
    "addr:street":"Pascoe Vale Rd",
    "iso:country":"AU",
    "sg:address":"858 Pascoe Vale Rd",
    "sg:city":"Glenroy",
    "sg:classifiers":[
        {
            "category":"Travel",
            "subcategory":"Hostel",
            "type":"Entertainment"
        }
    ],
    "sg:phone":"+61 3 9304 4399",
    "sg:postcode":"3046",
    "sg:province":"VIC",
    "sg:tags":[
        "home"
    ],
    "wof:name":"Monterey",
    "wof:placetype":"venue"
},
  "geometry": {"coordinates":[144.91520690900001,-37.6997489929],"type":"Point"}
}