{
  "type": "Feature",
  "properties": {
    "addr:full":"Cook St Anakie QLD 4702",
    "addr:postcode":"4702",
    "addr:street":"Cook St",
    "iso:country":"AU",
    "sg:address":"Cook St",
    "sg:city":"Anakie",
    "sg:classifiers":[
        {
            "category":"Education",
            "subcategory":"School",
            "type":"Public Place"
        }
    ],
    "sg:phone":"+61 7 4985 4133",
    "sg:postcode":"4702",
    "sg:province":"QLD",
    "sg:tags":[
        "state",
        "except",
        "nsw"
    ],
    "wof:name":"Anakie Primary School",
    "wof:placetype":"venue"
},
  "geometry": {"coordinates":[151.24293518100001,-23.8557186127],"type":"Point"}
}