{
  "type": "Feature",
  "properties": {
    "iso:country":"AU",
    "sg:address":"Lot 3 Martin Crt",
    "sg:city":"Warragul",
    "sg:classifiers":[
        {
            "category":"Professional",
            "subcategory":"Art Services",
            "type":"Services"
        }
    ],
    "sg:phone":"+61 3 5623 5451",
    "sg:postcode":"3820",
    "sg:province":"VIC",
    "sg:tags":[
        "decorator",
        "painter"
    ],
    "wof:name":"Jinnette Kevin",
    "wof:placetype":"venue"
},
  "geometry": {"coordinates":[145.939743,-38.178581],"type":"Point"}
}