{
  "type": "Feature",
  "properties": {
    "addr:full":"252 Montague Rd West End QLD 4810",
    "addr:housenumber":"252",
    "addr:postcode":"4810",
    "addr:street":"Montague Rd",
    "iso:country":"AU",
    "sg:address":"252 Montague Rd",
    "sg:city":"West End",
    "sg:classifiers":[
        {
            "category":"Professional",
            "subcategory":"Printing & Photocopies",
            "type":"Services"
        }
    ],
    "sg:phone":"+61 7 3840 1234",
    "sg:postcode":"4810",
    "sg:province":"QLD",
    "sg:tags":[
        "photocopier"
    ],
    "wof:name":"Xerox Business Centre",
    "wof:placetype":"venue"
},
  "geometry": {"coordinates":[146.79672199999999,-19.267879],"type":"Point"}
}