{
  "type": "Feature",
  "properties": {
    "addr:full":"Shp2/ 13 Fannie Bay Pl Fannie Bay NT 0820",
    "addr:postcode":"nt 0820",
    "addr:street":"Fannie Bay Pl",
    "iso:country":"AU",
    "sg:address":"Shp2/ 13 Fannie Bay Pl",
    "sg:city":"Fannie Bay",
    "sg:classifiers":[
        {
            "category":"Professional",
            "subcategory":"Computer Services",
            "type":"Services"
        }
    ],
    "sg:phone":"+61 8 8941 2119",
    "sg:postcode":"0820",
    "sg:province":"NT",
    "sg:tags":[
        "repairs",
        "upgrade",
        "equipment"
    ],
    "wof:name":"PC Solutions 4 U",
    "wof:placetype":"venue"
},
  "geometry": {"coordinates":[130.83677673299999,-12.4232606888],"type":"Point"}
}