{
  "type": "Feature",
  "properties": {
    "addr:full":"1021-1023 Mt Alexander Rd Essendon VIC 3040",
    "addr:housenumber":"1021-1023",
    "addr:postcode":"3040",
    "addr:street":"Mt Alexander Rd",
    "iso:country":"AU",
    "sg:address":"1021-1023 Mt Alexander Rd",
    "sg:city":"Essendon",
    "sg:classifiers":[
        {
            "category":"Shopping",
            "subcategory":"Clothing, Apparel, & Fashions",
            "type":"Retail Goods"
        }
    ],
    "sg:phone":"+61 3 9374 2522",
    "sg:postcode":"3040",
    "sg:province":"VIC",
    "sg:tags":[
        "menswear"
    ],
    "wof:name":"Williamson Classic Clothing",
    "wof:placetype":"venue"
},
  "geometry": {"coordinates":[144.91148376500001,-37.746963501],"type":"Point"}
}