{
  "type": "Feature",
  "properties": {
    "addr:full":"Unit 2/ 3 Yuin St Golden Bay WA 6174",
    "addr:housenumber":"3",
    "addr:postcode":"6174",
    "addr:street":"Yuin St",
    "iso:country":"AU",
    "sg:address":"Unit 2/ 3 Yuin St",
    "sg:city":"Golden Bay",
    "sg:classifiers":[
        {
            "category":"Health Services",
            "subcategory":"Dentist",
            "type":"Services"
        }
    ],
    "sg:phone":"+61 8 9537 3311",
    "sg:postcode":"6174",
    "sg:province":"WA",
    "wof:name":"Golden Bay Dental Clinic",
    "wof:placetype":"venue"
},
  "geometry": {"coordinates":[115.753708,-32.425594],"type":"Point"}
}