{
  "type": "Feature",
  "properties": {
    "iso:country":"AU",
    "sg:address":"4 Mews Rd",
    "sg:city":"Fremantle",
    "sg:classifiers":[
        {
            "category":"Autos & Motor Vehicles",
            "subcategory":"Boat Sales",
            "type":"Retail Goods"
        }
    ],
    "sg:phone":"+61 8 9335 9429",
    "sg:postcode":"6160",
    "sg:province":"WA",
    "sg:tags":[
        "builder",
        "yacht",
        "repairer"
    ],
    "wof:name":"Fremantle Boat Manufacturers",
    "wof:placetype":"venue"
},
  "geometry": {"coordinates":[115.747833,-32.060246],"type":"Point"}
}