{
  "type": "Feature",
  "properties": {
    "iso:country":"AU",
    "sg:address":"1312 Gregory St",
    "sg:city":"Lake Wendouree",
    "sg:classifiers":[
        {
            "category":"Building & Trades",
            "subcategory":"Construction",
            "type":"Services"
        }
    ],
    "sg:phone":"+61 3 5339 2058",
    "sg:postcode":"3355",
    "sg:province":"VIC",
    "sg:tags":[
        "contractor"
    ],
    "wof:name":"Petersen R & E Pty Ltd",
    "wof:placetype":"venue"
},
  "geometry": {"coordinates":[143.824905,-37.541107],"type":"Point"}
}