{
  "type": "Feature",
  "properties": {
    "addr:full":"227 Bilwon Rd Biboohra QLD 4880",
    "addr:housenumber":"227",
    "addr:postcode":"4880",
    "addr:street":"Bilwon Rd",
    "iso:country":"AU",
    "sg:address":"227 Bilwon Rd",
    "sg:city":"Biboohra",
    "sg:classifiers":[
        {
            "category":"Farming",
            "subcategory":"Vineyard",
            "type":"Manufacturing & Wholesale Goods"
        }
    ],
    "sg:phone":"+61 7 4093 2750",
    "sg:postcode":"4880",
    "sg:province":"QLD",
    "sg:tags":[
        "winery"
    ],
    "wof:name":"Golden Pride Wineries",
    "wof:placetype":"venue"
},
  "geometry": {"coordinates":[145.42230224599999,-16.9158267975],"type":"Point"}
}