{
  "type": "Feature",
  "properties": {
    "addr:full":"26 Dandaloo St Trangie NSW 2823",
    "addr:housenumber":"26",
    "addr:postcode":"2823",
    "addr:street":"Dandaloo St",
    "iso:country":"AU",
    "sg:address":"26 Dandaloo St",
    "sg:city":"Trangie",
    "sg:classifiers":[
        {
            "category":"Food & Beverages",
            "subcategory":"Groceries & Convenience Stores",
            "type":"Retail Goods"
        }
    ],
    "sg:phone":"+61 2 6888 7509",
    "sg:postcode":"2823",
    "sg:province":"NSW",
    "wof:name":"M P & C A Welch Trangie Stores",
    "wof:placetype":"venue"
},
  "geometry": {"coordinates":[147.983276367,-32.0324707031],"type":"Point"}
}