{
  "type": "Feature",
  "properties": {
    "iso:country":"AU",
    "sg:address":"PO Box 7072",
    "sg:city":"New England Mail Srtng Cntr",
    "sg:classifiers":[
        {
            "category":"Utilities",
            "subcategory":"Electric",
            "type":"Services"
        }
    ],
    "sg:phone":"+61 2 6761 5612",
    "sg:postcode":"2348",
    "sg:province":"NSW",
    "sg:tags":[
        "electrical",
        "contractor"
    ],
    "wof:name":"Tamworth Satellite & Electrical Services",
    "wof:placetype":"venue"
},
  "geometry": {"coordinates":[151.145263672,-31.3978900909],"type":"Point"}
}