{
  "type": "Feature",
  "properties": {
    "addr:full":"Cnr Holbrook & Dry Sts Invermay TAS 7248",
    "addr:postcode":"7248",
    "iso:country":"AU",
    "sg:address":"Cnr Holbrook & Dry Sts",
    "sg:city":"Invermay",
    "sg:classifiers":[
        {
            "category":"Wholesale",
            "subcategory":"Machinery & Supplies",
            "type":"Manufacturing & Wholesale Goods"
        }
    ],
    "sg:phone":"+61 3 6334 0021",
    "sg:postcode":"7248",
    "sg:province":"TAS",
    "sg:tags":[
        "engine",
        "petrol"
    ],
    "wof:name":"Tamar Hire",
    "wof:placetype":"venue"
},
  "geometry": {"coordinates":[147.13328552199999,-41.4231987],"type":"Point"}
}