{
  "type": "Feature",
  "properties": {
    "iso:country":"AU",
    "sg:address":"147 Rusden St",
    "sg:city":"Armidale",
    "sg:classifiers":[
        {
            "category":"Retail",
            "subcategory":"Auto Repair",
            "type":"Services"
        }
    ],
    "sg:phone":"+61 2 6772 3004",
    "sg:postcode":"2350",
    "sg:province":"NSW",
    "sg:tags":[
        "muffler",
        "exhaust",
        "system"
    ],
    "wof:name":"Carline Mufflers",
    "wof:placetype":"venue"
},
  "geometry": {"coordinates":[151.652954102,-30.5112247467],"type":"Point"}
}