{
  "type": "Feature",
  "properties": {
    "iso:country":"AU",
    "sg:address":"1 Commercial St East",
    "sg:city":"Mt Gambier",
    "sg:classifiers":[
        {
            "category":"Banks & Credit Unions",
            "subcategory":"Financial Services",
            "type":"Services"
        }
    ],
    "sg:phone":"+61 13 13 76",
    "sg:postcode":"5290",
    "sg:province":"SA",
    "sg:tags":[
        "planning"
    ],
    "wof:name":"BankSA#",
    "wof:placetype":"venue"
},
  "geometry": {"coordinates":[140.78088399999999,-37.828358],"type":"Point"}
}