{
  "type": "Feature",
  "properties": {
    "addr:full":"337 Pacific Hwy Heatherbrae NSW 2324",
    "addr:housenumber":"337",
    "addr:postcode":"2324",
    "addr:street":"Pacific Hwy",
    "iso:country":"AU",
    "sg:address":"337 Pacific Hwy",
    "sg:city":"Heatherbrae",
    "sg:classifiers":[
        {
            "category":"Retail",
            "subcategory":"Auto Repair",
            "type":"Services"
        }
    ],
    "sg:phone":"+61 2 4980 0622",
    "sg:postcode":"2324",
    "sg:province":"NSW",
    "sg:tags":[
        "bus",
        "truck"
    ],
    "wof:name":"North Star Motors",
    "wof:placetype":"venue"
},
  "geometry": {"coordinates":[151.72828674300001,-32.7882156372],"type":"Point"}
}