{
  "type": "Feature",
  "properties": {
    "addr:full":"151 Hawkesbury Rd Westmead NSW 2145",
    "addr:housenumber":"151",
    "addr:postcode":"2145",
    "addr:street":"Hawkesbury Rd",
    "iso:country":"AU",
    "sg:address":"151 Hawkesbury Rd",
    "sg:city":"Westmead",
    "sg:classifiers":[
        {
            "category":"Cafe",
            "type":"Food & Drink"
        }
    ],
    "sg:phone":"+61 2 9689 3880",
    "sg:postcode":"2145",
    "sg:province":"NSW",
    "wof:name":"Sit &#039;n&#039; Chats Cafe",
    "wof:placetype":"venue"
},
  "geometry": {"coordinates":[150.98756408700001,-33.8075561523],"type":"Point"}
}