{
  "type": "Feature",
  "properties": {
    "addr:full":"5 Bessemer Rd Bayswater North VIC 3153",
    "addr:housenumber":"5",
    "addr:postcode":"3153",
    "addr:street":"Bessemer Rd",
    "iso:country":"AU",
    "sg:address":"5 Bessemer Rd",
    "sg:city":"Bayswater North",
    "sg:classifiers":[
        {
            "category":"Wholesale",
            "subcategory":"Home Furnishings",
            "type":"Manufacturing & Wholesale Goods"
        }
    ],
    "sg:phone":"+61 3 9729 8244",
    "sg:postcode":"3153",
    "sg:province":"VIC",
    "sg:tags":[
        "wholesaler",
        "bedding",
        "mfrs",
        "bed"
    ],
    "wof:name":"Clipper Plastics Pty Ltd",
    "wof:placetype":"venue"
},
  "geometry": {"coordinates":[145.29840087900001,-37.8184509277],"type":"Point"}
}