{
  "type": "Feature",
  "properties": {
    "addr:full":"200 South Rd Mile End SA 5031",
    "addr:housenumber":"200",
    "addr:postcode":"5031",
    "addr:street":"South Rd",
    "iso:country":"AU",
    "sg:address":"200 South Rd",
    "sg:city":"Mile End",
    "sg:classifiers":[
        {
            "category":"Banks & Credit Unions",
            "subcategory":"Bank",
            "type":"Services"
        }
    ],
    "sg:phone":"+61 8 8300 8300",
    "sg:postcode":"5031",
    "sg:province":"SA",
    "sg:tags":[
        "broker",
        "mortgage"
    ],
    "sg:website":"http://www.bernielewis.com.au",
    "wof:name":"Bernie Lewis Home Loans",
    "wof:placetype":"venue"
},
  "geometry": {"coordinates":[138.56968689000001,-34.9264793396],"type":"Point"}
}