{
  "type": "Feature",
  "properties": {
    "iso:country":"AU",
    "sg:address":"368 Brighton Rd",
    "sg:city":"Hove",
    "sg:classifiers":[
        {
            "category":"Health Services",
            "subcategory":"Doctor",
            "type":"Services"
        }
    ],
    "sg:phone":"+61 8 8296 2700",
    "sg:postcode":"5048",
    "sg:province":"SA",
    "sg:tags":[
        "medical",
        "practitioner"
    ],
    "wof:name":"Surgery @ Hove",
    "wof:placetype":"venue"
},
  "geometry": {"coordinates":[138.522629,-35.010422],"type":"Point"}
}