{
  "type": "Feature",
  "properties": {
    "addr:full":"Ground Floor/ 33 York St Sydney NSW 2000",
    "addr:housenumber":"/ 33",
    "addr:postcode":"2000",
    "addr:street":"York St",
    "iso:country":"AU",
    "sg:address":"Ground Floor/ 33 York St",
    "sg:city":"Sydney",
    "sg:classifiers":[
        {
            "category":"Shopping",
            "subcategory":"Computers & Home Electronics",
            "type":"Retail Goods"
        }
    ],
    "sg:phone":"+61 2 9299 0022",
    "sg:postcode":"2000",
    "sg:province":"NSW",
    "sg:tags":[
        "equipment",
        "supply"
    ],
    "wof:name":"Ecom Computers",
    "wof:placetype":"venue"
},
  "geometry": {"coordinates":[151.20565795900001,-33.8664970398],"type":"Point"}
}