{
  "type": "Feature",
  "properties": {
    "addr:full":"28 Bennison Rd Hinchinbrook NSW 2168",
    "addr:housenumber":"28",
    "addr:postcode":"2168",
    "addr:street":"Bennison Rd",
    "iso:country":"AU",
    "sg:address":"28 Bennison Rd",
    "sg:city":"Hinchinbrook",
    "sg:classifiers":[
        {
            "category":"Building & Trades",
            "subcategory":"Cleaning & Sanitation",
            "type":"Services"
        }
    ],
    "sg:phone":"+61 2 9608 6184",
    "sg:postcode":"2168",
    "sg:province":"NSW",
    "sg:tags":[
        "asbestos",
        "treatment",
        "removal"
    ],
    "wof:name":"Lbs Asbestos & Technical Work",
    "wof:placetype":"venue"
},
  "geometry": {"coordinates":[150.85804748499999,-33.9170265198],"type":"Point"}
}