{
  "type": "Feature",
  "properties": {
    "addr:full":"43 Beaumont St Hamilton NSW 2303",
    "addr:housenumber":"43",
    "addr:postcode":"2303",
    "addr:street":"Beaumont St",
    "iso:country":"AU",
    "sg:address":"43 Beaumont St",
    "sg:city":"Hamilton",
    "sg:classifiers":[
        {
            "category":"Banks & Credit Unions",
            "subcategory":"Investment Brokerage",
            "type":"Services"
        }
    ],
    "sg:phone":"+61 2 4961 4413",
    "sg:postcode":"2303",
    "sg:province":"NSW",
    "sg:tags":[
        "money",
        "term",
        "short",
        "finance",
        "market"
    ],
    "wof:name":"Hamilton Loan Office",
    "wof:placetype":"venue"
},
  "geometry": {"coordinates":[151.74757399999999,-32.921455],"type":"Point"}
}