{
  "type": "Feature",
  "properties": {
    "addr:full":"U101/ 3 Railway Pde Burwood NSW 2134",
    "addr:housenumber":"u101 / 3",
    "addr:postcode":"2134",
    "addr:street":"Railway Pde",
    "iso:country":"AU",
    "sg:address":"U101/ 3 Railway Pde",
    "sg:city":"Burwood",
    "sg:classifiers":[
        {
            "category":"Food & Beverages",
            "subcategory":"Groceries & Convenience Stores",
            "type":"Retail Goods"
        }
    ],
    "sg:phone":"+61 2 9745 1618",
    "sg:postcode":"2134",
    "sg:province":"NSW",
    "wof:name":"Spiceland (Aust) Pty Ltd",
    "wof:placetype":"venue"
},
  "geometry": {"coordinates":[151.10679626500001,-33.8782310486],"type":"Point"}
}