{
  "type": "Feature",
  "properties": {
    "addr:full":"181 Charles St Beauty Point TAS 7270",
    "addr:housenumber":"181",
    "addr:postcode":"7270",
    "addr:street":"Charles St",
    "iso:country":"AU",
    "sg:address":"181 Charles St",
    "sg:city":"Beauty Point",
    "sg:classifiers":[
        {
            "category":"Food & Beverages",
            "subcategory":"Groceries & Convenience Stores",
            "type":"Retail Goods"
        }
    ],
    "sg:phone":"+61 3 6383 4146",
    "sg:postcode":"7270",
    "sg:province":"TAS",
    "wof:name":"Camerons Drapery",
    "wof:placetype":"venue"
},
  "geometry": {"coordinates":[146.818267822,-41.1490478516],"type":"Point"}
}