{
  "type": "Feature",
  "properties": {
    "addr:full":"28 Bellflower Rd Sippy Downs QLD 4556",
    "addr:housenumber":"28",
    "addr:postcode":"4556",
    "addr:street":"Bellflower Rd",
    "iso:country":"AU",
    "sg:address":"28 Bellflower Rd",
    "sg:city":"Sippy Downs",
    "sg:classifiers":[
        {
            "category":"Banks & Credit Unions",
            "subcategory":"Investment Brokerage",
            "type":"Services"
        }
    ],
    "sg:phone":"+61 1300 558 504",
    "sg:postcode":"4556",
    "sg:province":"QLD",
    "wof:name":"Paladin Australia",
    "wof:placetype":"venue"
},
  "geometry": {"coordinates":[153.05630493199999,-26.7268447876],"type":"Point"}
}