{
  "type": "Feature",
  "properties": {
    "addr:full":"12 Purches St Mitcham VIC 3132",
    "addr:housenumber":"12",
    "addr:postcode":"3132",
    "addr:street":"Purches St",
    "iso:country":"AU",
    "sg:address":"12 Purches St",
    "sg:city":"Mitcham",
    "sg:classifiers":[
        {
            "category":"Education",
            "subcategory":"Kindergarten",
            "type":"Public Place"
        }
    ],
    "sg:phone":"+61 3 9874 5020",
    "sg:postcode":"3132",
    "sg:province":"VIC",
    "sg:tags":[
        "pre-schools"
    ],
    "wof:name":"Heatherdale Pre-School",
    "wof:placetype":"venue"
},
  "geometry": {"coordinates":[145.20860290499999,-37.8203773499],"type":"Point"}
}