{
  "type": "Feature",
  "properties": {
    "addr:full":"96 Burswood Rd Victoria Park WA 6100",
    "addr:housenumber":"96",
    "addr:postcode":"6100",
    "addr:street":"Burswood Rd",
    "iso:country":"AU",
    "sg:address":"96 Burswood Rd",
    "sg:city":"Victoria Park",
    "sg:classifiers":[
        {
            "category":"Wholesale",
            "subcategory":"Seafood",
            "type":"Manufacturing & Wholesale Goods"
        }
    ],
    "sg:phone":"+61 8 9470 1999",
    "sg:postcode":"6100",
    "sg:province":"WA",
    "sg:tags":[
        "fish"
    ],
    "wof:name":"Perth Select Seafoods",
    "wof:placetype":"venue"
},
  "geometry": {"coordinates":[115.89515686,-31.9676895142],"type":"Point"}
}