{
  "type": "Feature",
  "properties": {
    "addr:full":"PO Box 1173 Buderim QLD 4556",
    "addr:postcode":"4556",
    "iso:country":"AU",
    "sg:address":"PO Box 1173",
    "sg:city":"Buderim",
    "sg:classifiers":[
        {
            "category":"Shopping",
            "subcategory":"Stationery & Office Supplies",
            "type":"Retail Goods"
        }
    ],
    "sg:phone":"+61 7 5445 1289",
    "sg:postcode":"4556",
    "sg:province":"QLD",
    "sg:tags":[
        "equipment",
        "display",
        "exhibition"
    ],
    "wof:name":"Marsan Carpentry & Joinery",
    "wof:placetype":"venue"
},
  "geometry": {"coordinates":[153.09310913100001,-26.6773891449],"type":"Point"}
}