{
  "type": "Feature",
  "properties": {
    "iso:country":"AU",
    "sg:address":"20 Lindsay St",
    "sg:city":"McKinnon",
    "sg:classifiers":[
        {
            "category":"Education",
            "subcategory":"Music School",
            "type":"Public Place"
        }
    ],
    "sg:phone":"+61 3 9578 3880",
    "sg:postcode":"3204",
    "sg:province":"VIC",
    "sg:tags":[
        "teacher"
    ],
    "wof:name":"Music Methods Pty Ltd",
    "wof:placetype":"venue"
},
  "geometry": {"coordinates":[145.044357,-37.913883],"type":"Point"}
}