{
  "type": "Feature",
  "properties": {
    "addr:full":"3 Scott St Cairns QLD 4870",
    "addr:housenumber":"3",
    "addr:postcode":"4870",
    "addr:street":"Scott St",
    "iso:country":"AU",
    "sg:address":"3 Scott St",
    "sg:city":"Cairns",
    "sg:classifiers":[
        {
            "category":"Social Services",
            "subcategory":"Job Training",
            "type":"Services"
        }
    ],
    "sg:phone":"+61 7 4033 1406",
    "sg:postcode":"4870",
    "sg:province":"QLD",
    "sg:tags":[
        "interpreter"
    ],
    "wof:name":"Uematsu Mika",
    "wof:placetype":"venue"
},
  "geometry": {"coordinates":[145.77050781200001,-16.9259357452],"type":"Point"}
}