{
  "type": "Feature",
  "properties": {
    "iso:country":"AU",
    "sg:address":"84 Commercial St East",
    "sg:city":"Mt Gambier",
    "sg:classifiers":[
        {
            "category":"Food & Beverages",
            "subcategory":"Meat & Fish",
            "type":"Retail Goods"
        }
    ],
    "sg:phone":"+61 8 8725 9083",
    "sg:postcode":"5290",
    "sg:province":"SA",
    "sg:tags":[
        "seafood"
    ],
    "wof:name":"Kapela Fish Shop",
    "wof:placetype":"venue"
},
  "geometry": {"coordinates":[140.78460699999999,-37.829784],"type":"Point"}
}