{
  "type": "Feature",
  "properties": {
    "addr:full":"55 Hope St Grovedale VIC 3216",
    "addr:housenumber":"55",
    "addr:postcode":"3216",
    "addr:street":"Hope St",
    "iso:country":"AU",
    "sg:address":"55 Hope St",
    "sg:city":"Grovedale",
    "sg:classifiers":[
        {
            "category":"Retail",
            "subcategory":"Funeral Services",
            "type":"Services"
        }
    ],
    "sg:phone":"+61 1300 662 677",
    "sg:postcode":"3216",
    "sg:province":"VIC",
    "sg:tags":[
        "director"
    ],
    "wof:name":"Tuckers Funeral & Bereavement Service",
    "wof:placetype":"venue"
},
  "geometry": {"coordinates":[144.36598205600001,-38.1586151123],"type":"Point"}
}