{
  "type": "Feature",
  "properties": {
    "addr:full":"Shp1/ 49 Mt Barker Rd Hahndorf SA 5245",
    "addr:housenumber":"49",
    "addr:postcode":"5245",
    "addr:street":"Mt Barker Rd",
    "iso:country":"AU",
    "sg:address":"Shp1/ 49 Mt Barker Rd",
    "sg:city":"Hahndorf",
    "sg:classifiers":[
        {
            "category":"Restaurant",
            "type":"Food & Drink"
        }
    ],
    "sg:phone":"+61 8 8388 7877",
    "sg:postcode":"5245",
    "sg:province":"SA",
    "wof:name":"Caffe Casalinga",
    "wof:placetype":"venue"
},
  "geometry": {"coordinates":[138.80984497099999,-35.0294418335],"type":"Point"}
}