{
  "type": "Feature",
  "properties": {
    "addr:full":"Suite 8/ Level 1 902 Mt Alexander Rd Essendon VIC 3040",
    "addr:housenumber":"1 902",
    "addr:postcode":"3040",
    "addr:street":"Mt Alexander Rd",
    "iso:country":"AU",
    "sg:address":"Suite 8/ Level 1 902 Mt Alexander Rd",
    "sg:city":"Essendon",
    "sg:classifiers":[
        {
            "category":"Real Estate",
            "subcategory":"Architect",
            "type":"Services"
        }
    ],
    "sg:phone":"+61 1800 615 007",
    "sg:postcode":"3040",
    "sg:province":"VIC",
    "sg:tags":[
        "building",
        "designer"
    ],
    "wof:name":"Valastro",
    "wof:placetype":"venue"
},
  "geometry": {"coordinates":[144.91851806599999,-37.7558860779],"type":"Point"}
}