{
  "type": "Feature",
  "properties": {
    "addr:full":"Shop 3 Cook St Atherton QLD 4883",
    "addr:housenumber":"shop 3",
    "addr:postcode":"4883",
    "addr:street":"Cook St",
    "iso:country":"AU",
    "sg:address":"Shop 3 Cook St",
    "sg:city":"Atherton",
    "sg:classifiers":[
        {
            "category":"Professional",
            "subcategory":"Art Services",
            "type":"Services"
        }
    ],
    "sg:phone":"+61 7 4091 4588",
    "sg:postcode":"4883",
    "sg:province":"QLD",
    "sg:tags":[
        "picture",
        "frame",
        "framing"
    ],
    "wof:name":"Lightwave Photography",
    "wof:placetype":"venue"
},
  "geometry": {"coordinates":[145.477615356,-17.2623138428],"type":"Point"}
}