{
  "type": "Feature",
  "properties": {
    "addr:full":"57 Raubers Rd Northgate QLD 4013",
    "addr:housenumber":"57",
    "addr:postcode":"4013",
    "addr:street":"Raubers Rd",
    "iso:country":"AU",
    "sg:address":"57 Raubers Rd",
    "sg:city":"Northgate",
    "sg:classifiers":[
        {
            "category":"Government",
            "subcategory":"Fire Station",
            "type":"Public Place"
        }
    ],
    "sg:phone":"+61 7 3267 8444",
    "sg:postcode":"4013",
    "sg:province":"QLD",
    "sg:tags":[
        "equipment",
        "protection",
        "consultant"
    ],
    "wof:name":"Tyco Building Products",
    "wof:placetype":"venue"
},
  "geometry": {"coordinates":[153.08688354500001,-27.3917675018],"type":"Point"}
}