{
  "type": "Feature",
  "properties": {
    "addr:full":"10 Comport St Cairns QLD 4870",
    "addr:housenumber":"10",
    "addr:postcode":"4870",
    "addr:street":"Comport St",
    "iso:country":"AU",
    "sg:address":"10 Comport St",
    "sg:city":"Cairns",
    "sg:classifiers":[
        {
            "category":"Home & Garden",
            "subcategory":"Hardware",
            "type":"Retail Goods"
        }
    ],
    "sg:phone":"+61 7 4050 7500",
    "sg:postcode":"4870",
    "sg:province":"QLD",
    "sg:tags":[
        "generating",
        "set",
        "generator"
    ],
    "wof:name":"Allclass North",
    "wof:placetype":"venue"
},
  "geometry": {"coordinates":[145.768966675,-16.9407844543],"type":"Point"}
}