{
  "type": "Feature",
  "properties": {
    "addr:full":"16 Helen St Ulverstone TAS 7315",
    "addr:housenumber":"16",
    "addr:postcode":"7315",
    "addr:street":"Helen St",
    "iso:country":"AU",
    "sg:address":"16 Helen St",
    "sg:city":"Ulverstone",
    "sg:classifiers":[
        {
            "category":"Building & Trades",
            "subcategory":"Construction",
            "type":"Services"
        }
    ],
    "sg:phone":"+61 419 366 915",
    "sg:postcode":"7315",
    "sg:province":"TAS",
    "sg:tags":[
        "ceiling"
    ],
    "wof:name":"Danny Lewis Plastering",
    "wof:placetype":"venue"
},
  "geometry": {"coordinates":[146.16380310100001,-41.1555099487],"type":"Point"}
}