{
  "type": "Feature",
  "properties": {
    "addr:full":"45- 49 Charters Towers Rd Hyde Park QLD 4812",
    "addr:housenumber":"49",
    "addr:postcode":"4812",
    "addr:street":"Charters Towers Rd",
    "iso:country":"AU",
    "sg:address":"45- 49 Charters Towers Rd",
    "sg:city":"Hyde Park",
    "sg:classifiers":[
        {
            "category":"Retail",
            "subcategory":"Auto Repair",
            "type":"Services"
        }
    ],
    "sg:phone":"+61 7 4772 3233",
    "sg:postcode":"4812",
    "sg:province":"QLD",
    "sg:tags":[
        "repairer",
        "motor",
        "engineer"
    ],
    "wof:name":"Bob Parkes Muffler City",
    "wof:placetype":"venue"
},
  "geometry": {"coordinates":[146.80316199999999,-19.273163],"type":"Point"}
}