{
  "type": "Feature",
  "properties": {
    "iso:country":"AU",
    "sg:address":"Catherine St",
    "sg:city":"Clapham",
    "sg:classifiers":[
        {
            "category":"Building & Trades",
            "subcategory":"Cleaning & Sanitation",
            "type":"Services"
        }
    ],
    "sg:phone":"+61 8 8357 4567",
    "sg:postcode":"5062",
    "sg:province":"SA",
    "sg:tags":[
        "window"
    ],
    "wof:name":"Spruce Cleaners",
    "wof:placetype":"venue"
},
  "geometry": {"coordinates":[138.60664367699999,-34.9858207703],"type":"Point"}
}