{
  "type": "Feature",
  "properties": {
    "addr:full":"116 Hawthorn Rd Caulfield North VIC 3161",
    "addr:housenumber":"116",
    "addr:postcode":"3161",
    "addr:street":"Hawthorn Rd",
    "iso:country":"AU",
    "sg:address":"116 Hawthorn Rd",
    "sg:city":"Caulfield North",
    "sg:classifiers":[
        {
            "category":"Real Estate",
            "subcategory":"Real Estate Agent",
            "type":"Services"
        }
    ],
    "sg:phone":"+61 3 9532 8111",
    "sg:postcode":"3161",
    "sg:province":"VIC",
    "wof:name":"Noel Jones",
    "wof:placetype":"venue"
},
  "geometry": {"coordinates":[145.02444457999999,-37.8731422424],"type":"Point"}
}