{
  "type": "Feature",
  "properties": {
    "iso:country":"AU",
    "sg:address":"38 Kennedy St",
    "sg:city":"Newnham",
    "sg:classifiers":[
        {
            "category":"Building & Trades",
            "subcategory":"Landscaping Services",
            "type":"Services"
        }
    ],
    "sg:phone":"+61 3 6331 5064",
    "sg:postcode":"7248",
    "sg:province":"TAS",
    "sg:tags":[
        "gardener"
    ],
    "wof:name":"Rolling Stone Garden Maintenance",
    "wof:placetype":"venue"
},
  "geometry": {"coordinates":[147.13270568900001,-41.3911094666],"type":"Point"}
}