{
  "type": "Feature",
  "properties": {
    "addr:full":"PO Box 1224 Kawana Waters QLD 4575",
    "addr:postcode":"4575",
    "iso:country":"AU",
    "sg:address":"PO Box 1224",
    "sg:city":"Kawana Waters",
    "sg:classifiers":[
        {
            "category":"Building & Trades",
            "subcategory":"Construction",
            "type":"Services"
        }
    ],
    "sg:phone":"+61 437 550 053",
    "sg:postcode":"4575",
    "sg:province":"QLD",
    "sg:tags":[
        "contractor"
    ],
    "wof:name":"David Reid Homes",
    "wof:placetype":"venue"
},
  "geometry": {"coordinates":[153.12910500000001,-26.73616],"type":"Point"}
}