{
  "type": "Feature",
  "properties": {
    "addr:full":"Factory 3 4 Aster Ave Carrum Downs VIC 3201",
    "addr:housenumber":"4",
    "addr:postcode":"3201",
    "addr:street":"Aster Ave",
    "iso:country":"AU",
    "sg:address":"Factory 3 4 Aster Ave",
    "sg:city":"Carrum Downs",
    "sg:classifiers":[
        {
            "category":"Autos & Motor Vehicles",
            "subcategory":"Auto Supplies",
            "type":"Retail Goods"
        }
    ],
    "sg:phone":"+61 3 9775 1906",
    "sg:postcode":"3201",
    "sg:province":"VIC",
    "sg:tags":[
        "electric"
    ],
    "wof:name":"Emu Engineering",
    "wof:placetype":"venue"
},
  "geometry": {"coordinates":[145.167923,-38.103905],"type":"Point"}
}