{
  "type": "Feature",
  "properties": {
    "iso:country":"AU",
    "sg:address":"Naas Rd",
    "sg:city":"Tharwa",
    "sg:classifiers":[
        {
            "category":"Retail",
            "subcategory":"Event Space",
            "type":"Services"
        }
    ],
    "sg:phone":"+61 2 6237 5099",
    "sg:postcode":"2620",
    "sg:province":"ACT",
    "sg:tags":[
        "venue",
        "reception",
        "wedding"
    ],
    "wof:name":"Cuppacumbalong",
    "wof:placetype":"venue"
},
  "geometry": {"coordinates":[149.06993102999999,-35.5159721375],"type":"Point"}
}