{
  "type": "Feature",
  "properties": {
    "addr:full":"2 Tasman Rd North Avalon NSW 2107",
    "addr:housenumber":"2",
    "addr:postcode":"2107",
    "addr:street":"Tasman Rd North",
    "iso:country":"AU",
    "sg:address":"2 Tasman Rd",
    "sg:city":"North Avalon",
    "sg:classifiers":[
        {
            "category":"Education",
            "subcategory":"Kindergarten",
            "type":"Public Place"
        }
    ],
    "sg:phone":"+61 2 9973 1422",
    "sg:postcode":"2107",
    "sg:province":"NSW",
    "sg:tags":[
        "pre-schools"
    ],
    "wof:name":"Montessori Barrenjoey Pre-School",
    "wof:placetype":"venue"
},
  "geometry": {"coordinates":[151.33496093799999,-33.633014679],"type":"Point"}
}