{
  "type": "Feature",
  "properties": {
    "addr:full":"96 Dynon Rd West Melbourne VIC 3003",
    "addr:housenumber":"96",
    "addr:postcode":"3003",
    "addr:street":"Dynon Rd",
    "iso:country":"AU",
    "sg:address":"96 Dynon Rd",
    "sg:city":"West Melbourne",
    "sg:classifiers":[
        {
            "category":"Banks & Credit Unions",
            "subcategory":"Investment Brokerage",
            "type":"Services"
        }
    ],
    "sg:phone":"+61 3 9371 5395",
    "sg:postcode":"3003",
    "sg:province":"VIC",
    "sg:tags":[
        "shutter",
        "louvre"
    ],
    "wof:name":"The Shutter Store",
    "wof:placetype":"venue"
},
  "geometry": {"coordinates":[144.93264770499999,-37.8036804199],"type":"Point"}
}