{
  "type": "Feature",
  "properties": {
    "iso:country":"AU",
    "sg:address":"28 Ainsworth St",
    "sg:city":"Lilyfield",
    "sg:classifiers":[
        {
            "category":"Building & Trades",
            "subcategory":"Landscaping Services",
            "type":"Services"
        }
    ],
    "sg:phone":"+61 419 227 624",
    "sg:postcode":"2040",
    "sg:province":"NSW",
    "sg:tags":[
        "gardener"
    ],
    "wof:name":"Jones Garden Management Services Pty Ltd",
    "wof:placetype":"venue"
},
  "geometry": {"coordinates":[151.16279599999999,-33.877537],"type":"Point"}
}