{
  "type": "Feature",
  "properties": {
    "iso:country":"AU",
    "sg:address":"1 Wilpena Rd",
    "sg:city":"Hawker",
    "sg:classifiers":[
        {
            "category":"Travel",
            "subcategory":"Hotels & Motels",
            "type":"Entertainment"
        }
    ],
    "sg:phone":"+61 8 8648 4100",
    "sg:postcode":"5434",
    "sg:province":"SA",
    "wof:name":"Outback Chapmanton Motel",
    "wof:placetype":"venue"
},
  "geometry": {"coordinates":[138.42254638700001,-31.8873310089],"type":"Point"}
}