{
  "type": "Feature",
  "properties": {
    "iso:country":"AU",
    "sg:address":"PO Box 82",
    "sg:city":"Leopold",
    "sg:classifiers":[
        {
            "category":"Utilities",
            "subcategory":"Electric",
            "type":"Services"
        }
    ],
    "sg:phone":"+61 418 520 956",
    "sg:postcode":"3224",
    "sg:province":"VIC",
    "sg:tags":[
        "electrical",
        "contractor"
    ],
    "wof:name":"Allan Garratt Electrical",
    "wof:placetype":"venue"
},
  "geometry": {"coordinates":[144.46254,-38.196381],"type":"Point"}
}