{
  "type": "Feature",
  "properties": {
    "iso:country":"AU",
    "sg:address":"9 Nundah St",
    "sg:city":"Nundah",
    "sg:classifiers":[
        {
            "category":"Retail",
            "subcategory":"Auto Repair",
            "type":"Services"
        }
    ],
    "sg:phone":"+61 7 3266 2566",
    "sg:postcode":"4012",
    "sg:province":"QLD",
    "sg:tags":[
        "electrical"
    ],
    "wof:name":"Nundah Auto Electrics & Air Conditioning",
    "wof:placetype":"venue"
},
  "geometry": {"coordinates":[153.061447144,-27.4006328583],"type":"Point"}
}