{
  "type": "Feature",
  "properties": {
    "iso:country":"AU",
    "sg:address":"35 Bevington St",
    "sg:city":"Tannum Sands",
    "sg:classifiers":[
        {
            "category":"Wholesale",
            "subcategory":"Machinery & Supplies",
            "type":"Manufacturing & Wholesale Goods"
        }
    ],
    "sg:phone":"+61 7 4973 8177",
    "sg:postcode":"4680",
    "sg:province":"QLD",
    "sg:tags":[
        "distributor",
        "crane",
        "mfrs"
    ],
    "wof:name":"KCI Konecranes",
    "wof:placetype":"venue"
},
  "geometry": {"coordinates":[151.364105225,-23.9567985535],"type":"Point"}
}