{
  "type": "Feature",
  "properties": {
    "addr:full":"10 Halsbury Drv Rowville VIC 3178",
    "addr:housenumber":"10",
    "addr:postcode":"3178",
    "addr:street":"Halsbury Drv",
    "iso:country":"AU",
    "sg:address":"10 Halsbury Drv",
    "sg:city":"Rowville",
    "sg:classifiers":[
        {
            "category":"Manufacturing",
            "subcategory":"Tools & Machinery",
            "type":"Manufacturing & Wholesale Goods"
        }
    ],
    "sg:phone":"+61 3 9764 4565",
    "sg:postcode":"3178",
    "sg:province":"VIC",
    "sg:tags":[
        "toolmaker"
    ],
    "wof:name":"Cad-Tech Design",
    "wof:placetype":"venue"
},
  "geometry": {"coordinates":[145.23886108400001,-37.9295806885],"type":"Point"}
}