{
  "type": "Feature",
  "properties": {
    "addr:full":"14 Kallay St Croydon VIC 3136",
    "addr:housenumber":"14",
    "addr:postcode":"3136",
    "addr:street":"Kallay St",
    "iso:country":"AU",
    "sg:address":"14 Kallay St",
    "sg:city":"Croydon",
    "sg:classifiers":[
        {
            "category":"Professional",
            "subcategory":"Computer Services",
            "type":"Services"
        }
    ],
    "sg:phone":"+61 3 9879 4595",
    "sg:postcode":"3136",
    "sg:province":"VIC",
    "sg:tags":[
        "repairs",
        "upgrade",
        "equipment"
    ],
    "wof:name":"Jaysee Computer Services",
    "wof:placetype":"venue"
},
  "geometry": {"coordinates":[145.25885009800001,-37.7919883728],"type":"Point"}
}