{
  "type": "Feature",
  "properties": {
    "iso:country":"AU",
    "sg:address":"12B Geneva St",
    "sg:city":"Kyogle",
    "sg:classifiers":[
        {
            "category":"Health Services",
            "subcategory":"Dentist",
            "type":"Services"
        }
    ],
    "sg:phone":"+61 2 6632 1598",
    "sg:postcode":"2474",
    "sg:province":"NSW",
    "wof:name":"Le Kim-Hoa",
    "wof:placetype":"venue"
},
  "geometry": {"coordinates":[153.003997803,-28.6197948456],"type":"Point"}
}