{
  "type": "Feature",
  "properties": {
    "addr:full":"U3/ 591 Woodstock Ave Glendenning NSW 2761",
    "addr:housenumber":"591",
    "addr:postcode":"2761",
    "addr:street":"U3 /;Woodstock Ave",
    "iso:country":"AU",
    "sg:address":"U3/ 591 Woodstock Ave",
    "sg:city":"Glendenning",
    "sg:classifiers":[
        {
            "category":"Home & Garden",
            "subcategory":"Furniture",
            "type":"Retail Goods"
        }
    ],
    "sg:phone":"+61 1300 273 876",
    "sg:postcode":"2761",
    "sg:province":"NSW",
    "sg:tags":[
        "business"
    ],
    "wof:name":"Stutchbury Arthur Furniture & Fit-out Pty Ltd",
    "wof:placetype":"venue"
},
  "geometry": {"coordinates":[150.849884,-33.761074],"type":"Point"}
}