{
  "type": "Feature",
  "properties": {
    "iso:country":"AU",
    "sg:address":"50 Northlakes Drv",
    "sg:city":"Cameron Park",
    "sg:classifiers":[
        {
            "category":"Building & Trades",
            "subcategory":"Construction",
            "type":"Services"
        }
    ],
    "sg:phone":"+61 2 4958 8790",
    "sg:postcode":"2285",
    "sg:province":"NSW",
    "sg:tags":[
        "contractor"
    ],
    "wof:name":"Mervac Homes Display Centre",
    "wof:placetype":"venue"
},
  "geometry": {"coordinates":[151.615402222,-32.9105758667],"type":"Point"}
}