{
  "type": "Feature",
  "properties": {
    "addr:full":"4/ 559 Waterloo Corner Rd Burton SA 5110",
    "addr:housenumber":"/ 559",
    "addr:postcode":"5110",
    "addr:street":"Waterloo Corner Rd",
    "iso:country":"AU",
    "sg:address":"4/ 559 Waterloo Corner Rd",
    "sg:city":"Burton",
    "sg:classifiers":[
        {
            "category":"Manufacturing",
            "subcategory":"Metals",
            "type":"Manufacturing & Wholesale Goods"
        }
    ],
    "sg:phone":"+61 8 8280 9929",
    "sg:postcode":"5110",
    "sg:province":"SA",
    "sg:tags":[
        "steel",
        "fabricator",
        "mfrs"
    ],
    "wof:name":"Industrial, Medical Piping Systems Pty Ltd",
    "wof:placetype":"venue"
},
  "geometry": {"coordinates":[138.60743713400001,-34.7415771484],"type":"Point"}
}