{
  "type": "Feature",
  "properties": {
    "addr:full":"100 Churchill Rd North Dry Creek SA 5094",
    "addr:housenumber":"100",
    "addr:postcode":"5094",
    "addr:street":"Churchill Rd North Dry",
    "iso:country":"AU",
    "sg:address":"100 Churchill Rd North",
    "sg:city":"Dry Creek",
    "sg:classifiers":[
        {
            "category":"Fast Food",
            "type":"Food & Drink"
        }
    ],
    "sg:phone":"+61 8 8359 0322",
    "sg:postcode":"5094",
    "sg:province":"SA",
    "sg:tags":[
        "away",
        "take"
    ],
    "wof:name":"Barrys Snack Bar",
    "wof:placetype":"venue"
},
  "geometry": {"coordinates":[138.588256836,-34.8364295959],"type":"Point"}
}