{
  "type": "Feature",
  "properties": {
    "addr:full":"4 Jacksons Rd Warriewood NSW 2102",
    "addr:housenumber":"4",
    "addr:postcode":"2102",
    "addr:street":"Jacksons Rd",
    "iso:country":"AU",
    "sg:address":"4 Jacksons Rd",
    "sg:city":"Warriewood",
    "sg:classifiers":[
        {
            "category":"Social Services",
            "subcategory":"Child Care",
            "type":"Services"
        }
    ],
    "sg:phone":"+61 2 9913 1474",
    "sg:postcode":"2102",
    "sg:province":"NSW",
    "wof:name":"Avalon Out Of School Hours Care Inc.",
    "wof:placetype":"venue"
},
  "geometry": {"coordinates":[151.30038500000001,-33.697762],"type":"Point"}
}