{
  "type": "Feature",
  "properties": {
    "addr:full":"139 Princes Hwy Arncliffe NSW 2205",
    "addr:housenumber":"139",
    "addr:postcode":"2205",
    "addr:street":"Princes Hwy",
    "iso:country":"AU",
    "sg:address":"139 Princes Hwy",
    "sg:city":"Arncliffe",
    "sg:classifiers":[
        {
            "category":"Autos & Motor Vehicles",
            "subcategory":"Automobile Sales",
            "type":"Retail Goods"
        }
    ],
    "sg:phone":"+61 2 9567 0241",
    "sg:postcode":"2205",
    "sg:province":"NSW",
    "sg:tags":[
        "car",
        "new"
    ],
    "wof:name":"Saab Automobile Australia Pty Ltd",
    "wof:placetype":"venue"
},
  "geometry": {"coordinates":[151.15003999999999,-33.93605],"type":"Point"}
}