{
  "type": "Feature",
  "properties": {
    "addr:full":"41 Best St Devonport TAS 7310",
    "addr:housenumber":"41",
    "addr:postcode":"7310",
    "addr:street":"Best St",
    "iso:country":"AU",
    "sg:address":"41 Best St",
    "sg:city":"Devonport",
    "sg:classifiers":[
        {
            "category":"Retail",
            "subcategory":"Auto Repair",
            "type":"Services"
        }
    ],
    "sg:phone":"+61 3 6424 5177",
    "sg:postcode":"7310",
    "sg:province":"TAS",
    "sg:tags":[
        "repairer",
        "motor",
        "engineer"
    ],
    "wof:name":"Bruce Gowans Toyota",
    "wof:placetype":"venue"
},
  "geometry": {"coordinates":[146.357696533,-41.1779937744],"type":"Point"}
}