{
  "type": "Feature",
  "properties": {
    "iso:country":"AU",
    "sg:address":"Ardross Primary School Links Rd",
    "sg:city":"Ardross",
    "sg:classifiers":[
        {
            "category":"Education",
            "subcategory":"School",
            "type":"Public Place"
        }
    ],
    "sg:phone":"+61 8 9364 2771",
    "sg:postcode":"6153",
    "sg:province":"WA",
    "sg:tags":[
        "state",
        "except",
        "nsw"
    ],
    "wof:name":"Schools Government (Public)",
    "wof:placetype":"venue"
},
  "geometry": {"coordinates":[115.83332799999999,-32.026348],"type":"Point"}
}