{
  "type": "Feature",
  "properties": {
    "addr:full":"PO Box 61 Cotton Tree QLD 4558",
    "addr:postcode":"4558",
    "iso:country":"AU",
    "sg:address":"PO Box 61",
    "sg:city":"Cotton Tree",
    "sg:classifiers":[
        {
            "category":"Home & Garden",
            "subcategory":"Home Furnishings",
            "type":"Retail Goods"
        }
    ],
    "sg:phone":"+61 1300 559 463",
    "sg:postcode":"4558",
    "sg:province":"QLD",
    "sg:tags":[
        "storage",
        "rack",
        "wine"
    ],
    "wof:name":"Get Wines Direct",
    "wof:placetype":"venue"
},
  "geometry": {"coordinates":[153.098754883,-26.6551895142],"type":"Point"}
}