{
  "type": "Feature",
  "properties": {
    "addr:full":"Lvl27/ 66 Queen St Brisbane QLD 4000",
    "addr:housenumber":"66",
    "addr:postcode":"4000",
    "addr:street":"Queen St",
    "iso:country":"AU",
    "sg:address":"Lvl27/ 66 Queen St",
    "sg:city":"Brisbane",
    "sg:classifiers":[
        {
            "category":"Travel",
            "subcategory":"Travel Agent",
            "type":"Entertainment"
        }
    ],
    "sg:phone":"+61 7 3012 7601",
    "sg:postcode":"4000",
    "sg:province":"QLD",
    "sg:tags":[
        "consultant"
    ],
    "wof:name":"Holiday Friends",
    "wof:placetype":"venue"
},
  "geometry": {"coordinates":[153.02403259299999,-27.4703578949],"type":"Point"}
}