{
  "type": "Feature",
  "properties": {
    "addr:full":"46- 48 Bridge St Epping NSW 2121",
    "addr:housenumber":"48",
    "addr:postcode":"2121",
    "addr:street":"Bridge St",
    "iso:country":"AU",
    "sg:address":"46- 48 Bridge St",
    "sg:city":"Epping",
    "sg:classifiers":[
        {
            "category":"Education",
            "subcategory":"Kindergarten",
            "type":"Public Place"
        }
    ],
    "sg:phone":"+61 2 9876 4420",
    "sg:postcode":"2121",
    "sg:province":"NSW",
    "sg:tags":[
        "pre-schools"
    ],
    "wof:name":"KU Children's Services",
    "wof:placetype":"venue"
},
  "geometry": {"coordinates":[151.078125,-33.7750473022],"type":"Point"}
}