{
  "type": "Feature",
  "properties": {
    "iso:country":"AU",
    "sg:address":"272 Military Rd",
    "sg:city":"Cremorne",
    "sg:classifiers":[
        {
            "category":"Education",
            "subcategory":"School",
            "type":"Public Place"
        }
    ],
    "sg:phone":"+61 2 9909 3133",
    "sg:postcode":"2090",
    "sg:province":"NSW",
    "sg:tags":[
        "co-educational"
    ],
    "wof:name":"redlands",
    "wof:placetype":"venue"
},
  "geometry": {"coordinates":[151.22584533700001,-33.8304023743],"type":"Point"}
}