{
  "type": "Feature",
  "properties": {
    "addr:full":"Unit 3/ 151 Robinson Rd East Geebung QLD 4034",
    "addr:housenumber":"/ 151",
    "addr:postcode":"4034",
    "addr:street":"Robinson Rd East",
    "iso:country":"AU",
    "sg:address":"Unit 3/ 151 Robinson Rd",
    "sg:city":"East Geebung",
    "sg:classifiers":[
        {
            "category":"Manufacturing",
            "subcategory":"Rubber & Plastics",
            "type":"Manufacturing & Wholesale Goods"
        }
    ],
    "sg:phone":"+61 7 3865 3331",
    "sg:postcode":"4034",
    "sg:province":"QLD",
    "sg:tags":[
        "moulders"
    ],
    "wof:name":"R & V Plastics",
    "wof:placetype":"venue"
},
  "geometry": {"coordinates":[153.05401599999999,-27.369165],"type":"Point"}
}