{
  "type": "Feature",
  "properties": {
    "addr:full":"67 Castlereagh St Sydney NSW 2000",
    "addr:housenumber":"67",
    "addr:postcode":"2000",
    "addr:street":"Castlereagh St",
    "iso:country":"AU",
    "sg:address":"67 Castlereagh St",
    "sg:city":"Sydney",
    "sg:classifiers":[
        {
            "category":"Travel",
            "subcategory":"Travel Agent",
            "type":"Entertainment"
        }
    ],
    "sg:phone":"+61 2 9232 8144",
    "sg:postcode":"2000",
    "sg:province":"NSW",
    "sg:tags":[
        "consultant"
    ],
    "wof:name":"IrishTravel Agency",
    "wof:placetype":"venue"
},
  "geometry": {"coordinates":[151.20950317399999,-33.8692016602],"type":"Point"}
}