{
  "type": "Feature",
  "properties": {
    "addr:full":"461 Pitt St Sydney NSW 2000",
    "addr:housenumber":"461",
    "addr:postcode":"2000",
    "addr:street":"Pitt St",
    "iso:country":"AU",
    "sg:address":"461 Pitt St",
    "sg:city":"Sydney",
    "sg:classifiers":[
        {
            "category":"Health Services",
            "subcategory":"Health Practitioner",
            "type":"Services"
        }
    ],
    "sg:phone":"+61 2 9281 0988",
    "sg:postcode":"2000",
    "sg:province":"NSW",
    "sg:tags":[
        "herbalist"
    ],
    "wof:name":"Lade, Heiko",
    "wof:placetype":"venue"
},
  "geometry": {"coordinates":[151.20687866200001,-33.879447937],"type":"Point"}
}