{
  "type": "Feature",
  "properties": {
    "addr:full":"155 Greens Rd Dandenong VIC 3175",
    "addr:housenumber":"155",
    "addr:postcode":"3175",
    "addr:street":"Greens Rd",
    "iso:country":"AU",
    "sg:address":"155 Greens Rd",
    "sg:city":"Dandenong",
    "sg:classifiers":[
        {
            "category":"Autos & Motor Vehicles",
            "subcategory":"Auto Supplies",
            "type":"Retail Goods"
        }
    ],
    "sg:phone":"+61 3 9791 8666",
    "sg:postcode":"3175",
    "sg:province":"VIC",
    "sg:tags":[
        "tyre"
    ],
    "wof:name":"One Stop Tyre Power Pty Ltd",
    "wof:placetype":"venue"
},
  "geometry": {"coordinates":[145.20854187,-38.01354599],"type":"Point"}
}