{
  "type": "Feature",
  "properties": {
    "addr:full":"2d Cross St Double Bay NSW 2028",
    "addr:housenumber":"2d",
    "addr:postcode":"2028",
    "addr:street":"Cross St",
    "iso:country":"AU",
    "sg:address":"2d Cross St",
    "sg:city":"Double Bay",
    "sg:classifiers":[
        {
            "category":"Health Services",
            "subcategory":"Dentist",
            "type":"Services"
        }
    ],
    "sg:phone":"+61 2 9327 1685",
    "sg:postcode":"2028",
    "sg:province":"NSW",
    "wof:name":"Andrew Cerexhe Dr & Associates",
    "wof:placetype":"venue"
},
  "geometry": {"coordinates":[151.24449157699999,-33.8768005371],"type":"Point"}
}