{
  "type": "Feature",
  "properties": {
    "addr:full":"2179- 2195 Elizabeth Drv Cecil Park NSW 2171",
    "addr:housenumber":"2179 2195",
    "addr:postcode":"2171",
    "addr:street":"Elizabeth Drv Cecil Park",
    "iso:country":"AU",
    "sg:address":"2179- 2195 Elizabeth Drv",
    "sg:city":"Cecil Park",
    "sg:classifiers":[
        {
            "category":"Professional",
            "subcategory":"Engineering",
            "type":"Services"
        }
    ],
    "sg:phone":"+61 2 9826 2236",
    "sg:postcode":"2171",
    "sg:province":"NSW",
    "sg:tags":[
        "manufacturing",
        "engineer"
    ],
    "wof:name":"Anford Engineering",
    "wof:placetype":"venue"
},
  "geometry": {"coordinates":[150.846237183,-33.9284286499],"type":"Point"}
}