{
  "type": "Feature",
  "properties": {
    "iso:country":"AU",
    "sg:address":"74A Military Rd",
    "sg:city":"Merrylands",
    "sg:classifiers":[
        {
            "category":"Banks & Credit Unions",
            "subcategory":"Investment Brokerage",
            "type":"Services"
        }
    ],
    "sg:phone":"+61 2 9681 6511",
    "sg:postcode":"2160",
    "sg:province":"NSW",
    "sg:tags":[
        "care",
        "day",
        "family",
        "child"
    ],
    "wof:name":"Merrylands Holroyd Family Daycare",
    "wof:placetype":"venue"
},
  "geometry": {"coordinates":[150.988815308,-33.8473854065],"type":"Point"}
}