{
  "type": "Feature",
  "properties": {
    "addr:full":"660b South Rd Moorabbin VIC 3189",
    "addr:housenumber":"660b",
    "addr:postcode":"3189",
    "addr:street":"South Rd",
    "iso:country":"AU",
    "sg:address":"660b South Rd",
    "sg:city":"Moorabbin",
    "sg:classifiers":[
        {
            "category":"Building & Trades",
            "subcategory":"Construction",
            "type":"Services"
        }
    ],
    "sg:phone":"+61 3 9553 5444",
    "sg:postcode":"3189",
    "sg:province":"VIC",
    "sg:tags":[
        "brick",
        "paving"
    ],
    "wof:name":"Komplete Bricks & Pavers",
    "wof:placetype":"venue"
},
  "geometry": {"coordinates":[145.07183837900001,-37.9378318787],"type":"Point"}
}