{
  "type": "Feature",
  "properties": {
    "iso:country":"AU",
    "sg:address":"22 Corrie St",
    "sg:city":"Chermside",
    "sg:classifiers":[
        {
            "category":"Retail",
            "subcategory":"Auto Rental",
            "type":"Services"
        }
    ],
    "sg:phone":"+61 7 3256 3592",
    "sg:postcode":"4032",
    "sg:province":"QLD",
    "sg:tags":[
        "car",
        "hire",
        "minibus"
    ],
    "wof:name":"Vroom Vroom Vroom",
    "wof:placetype":"venue"
},
  "geometry": {"coordinates":[153.039413,-27.386547],"type":"Point"}
}