{
  "type": "Feature",
  "properties": {
    "addr:full":"188 Avoca Drv Avoca Beach NSW 2251",
    "addr:housenumber":"188",
    "addr:postcode":"2251",
    "addr:street":"Avoca Drv",
    "iso:country":"AU",
    "sg:address":"188 Avoca Drv",
    "sg:city":"Avoca Beach",
    "sg:classifiers":[
        {
            "category":"Health Services",
            "subcategory":"Doctor",
            "type":"Services"
        }
    ],
    "sg:phone":"+61 2 4382 1333",
    "sg:postcode":"2251",
    "sg:province":"NSW",
    "sg:tags":[
        "medical",
        "practitioner"
    ],
    "wof:name":"Stoddart Emily",
    "wof:placetype":"venue"
},
  "geometry": {"coordinates":[151.432098389,-33.4650268555],"type":"Point"}
}