{
  "type": "Feature",
  "properties": {
    "addr:full":"Unit 2, 2 Cnr Summerholm & Warrego Hwy Hatton Vale QLD 4341",
    "addr:housenumber":"2",
    "addr:postcode":"4341",
    "addr:street":"Cnr Summerholm & Warrego Hwy Hatton",
    "iso:country":"AU",
    "sg:address":"Unit 2, 2 Cnr Summerholm & Warrego Hwy",
    "sg:city":"Hatton Vale",
    "sg:classifiers":[
        {
            "category":"Retail",
            "subcategory":"Auto Repair",
            "type":"Services"
        }
    ],
    "sg:phone":"+61 7 5465 7791",
    "sg:postcode":"4341",
    "sg:province":"QLD",
    "sg:tags":[
        "bus",
        "truck"
    ],
    "wof:name":"Minis 2 Macks",
    "wof:placetype":"venue"
},
  "geometry": {"coordinates":[152.46124267600001,-27.567155838],"type":"Point"}
}