{
  "type": "Feature",
  "properties": {
    "iso:country":"AU",
    "sg:address":"Shop 1, Deutsche Bank Place, 126 Phillip St",
    "sg:city":"Sydney",
    "sg:classifiers":[
        {
            "category":"Restaurant",
            "type":"Food & Drink"
        }
    ],
    "sg:phone":"+61 2 9232 1306",
    "sg:postcode":"2000",
    "sg:province":"NSW",
    "wof:name":"Dolce Ristorante",
    "wof:placetype":"venue"
},
  "geometry": {"coordinates":[151.21153259299999,-33.8665618896],"type":"Point"}
}