{
  "type": "Feature",
  "properties": {
    "iso:country":"AU",
    "sg:address":"56 Iverison Rd",
    "sg:city":"Sussex Inlet",
    "sg:classifiers":[
        {
            "category":"Travel",
            "subcategory":"Hotels & Motels",
            "type":"Entertainment"
        }
    ],
    "sg:phone":"+61 2 4441 2007",
    "sg:postcode":"2540",
    "sg:province":"NSW",
    "wof:name":"Ranch Motel",
    "wof:placetype":"venue"
},
  "geometry": {"coordinates":[150.58952331500001,-35.1693305969],"type":"Point"}
}