{
  "type": "Feature",
  "properties": {
    "addr:full":"5 Harch St Gatton QLD 4343",
    "addr:housenumber":"5",
    "addr:postcode":"4343",
    "addr:street":"Harch St",
    "iso:country":"AU",
    "sg:address":"5 Harch St",
    "sg:city":"Gatton",
    "sg:classifiers":[
        {
            "category":"Building & Trades",
            "subcategory":"Construction",
            "type":"Services"
        }
    ],
    "sg:phone":"+61 418 700 799",
    "sg:postcode":"4343",
    "sg:province":"QLD",
    "sg:tags":[
        "earth",
        "excavating",
        "moving",
        "contractor"
    ],
    "wof:name":"Gatton Bob Cat Hire",
    "wof:placetype":"venue"
},
  "geometry": {"coordinates":[152.274459839,-27.5598735809],"type":"Point"}
}