{
  "type": "Feature",
  "properties": {
    "addr:full":"Unit 2/ 79 Brighton Rd Glenelg SA 5045",
    "addr:postcode":"5045",
    "addr:street":"Brighton Rd",
    "iso:country":"AU",
    "sg:address":"Unit 2/ 79 Brighton Rd",
    "sg:city":"Glenelg",
    "sg:classifiers":[
        {
            "category":"Real Estate",
            "subcategory":"Real Estate Agent",
            "type":"Services"
        }
    ],
    "sg:phone":"+61 8 8376 8844",
    "sg:postcode":"5045",
    "sg:province":"SA",
    "wof:name":"Real Homes Pty Ltd",
    "wof:placetype":"venue"
},
  "geometry": {"coordinates":[138.52040099999999,-34.984776],"type":"Point"}
}