{
  "type": "Feature",
  "properties": {
    "addr:full":"81 McLennan St Mooroopna VIC 3629",
    "addr:housenumber":"81",
    "addr:postcode":"3629",
    "addr:street":"Mclennan St",
    "iso:country":"AU",
    "sg:address":"81 McLennan St",
    "sg:city":"Mooroopna",
    "sg:classifiers":[
        {
            "category":"Retail",
            "subcategory":"Laundry & Dry Cleaning",
            "type":"Services"
        }
    ],
    "sg:phone":"+61 3 5825 4852",
    "sg:postcode":"3629",
    "sg:province":"VIC",
    "wof:name":"Mooroopna Coin Laundry",
    "wof:placetype":"venue"
},
  "geometry": {"coordinates":[145.35963439899999,-36.3949584961],"type":"Point"}
}