{
  "type": "Feature",
  "properties": {
    "iso:country":"AU",
    "sg:address":"U4/ 46 Glenelg Ave",
    "sg:city":"Wembley Downs",
    "sg:classifiers":[
        {
            "category":"Manufacturing",
            "subcategory":"Building Materials",
            "type":"Manufacturing & Wholesale Goods"
        }
    ],
    "sg:phone":"+61 8 9244 4067",
    "sg:postcode":"6019",
    "sg:province":"WA",
    "sg:tags":[
        "stone",
        "product",
        "supply"
    ],
    "wof:name":"Investnet Australia Pty Ltd",
    "wof:placetype":"venue"
},
  "geometry": {"coordinates":[115.778266907,-31.9147129059],"type":"Point"}
}