{
  "type": "Feature",
  "properties": {
    "iso:country":"AU",
    "sg:address":"7 Old Perth Rd",
    "sg:city":"Bassendean",
    "sg:classifiers":[
        {
            "category":"Deli",
            "type":"Food & Drink"
        }
    ],
    "sg:phone":"+61 8 9279 1990",
    "sg:postcode":"6054",
    "sg:province":"WA",
    "sg:tags":[
        "delicatessen"
    ],
    "wof:name":"Bubble & Squeak",
    "wof:placetype":"venue"
},
  "geometry": {"coordinates":[115.94754791299999,-31.9039840698],"type":"Point"}
}