{
  "type": "Feature",
  "properties": {
    "iso:country":"AU",
    "sg:address":"Williams Rd",
    "sg:city":"Mt Barker",
    "sg:classifiers":[
        {
            "category":"Building & Trades",
            "subcategory":"Landscaping Services",
            "type":"Services"
        }
    ],
    "sg:phone":"+61 8 8398 3140",
    "sg:postcode":"5251",
    "sg:province":"SA",
    "sg:tags":[
        "designer",
        "landscape",
        "contractor"
    ],
    "wof:name":"Panoramic Landscapes",
    "wof:placetype":"venue"
},
  "geometry": {"coordinates":[138.902801514,-35.0739974976],"type":"Point"}
}