{
  "type": "Feature",
  "properties": {
    "addr:full":"Cnr Old Northern Rd & Explorer Drv Albany Creek QLD 4035",
    "addr:postcode":"4035",
    "addr:street":"Cnr Old Northern Rd & Explorer Drv",
    "iso:country":"AU",
    "sg:address":"Cnr Old Northern Rd & Explorer Drv",
    "sg:city":"Albany Creek",
    "sg:classifiers":[
        {
            "category":"Health Services",
            "subcategory":"Health Practitioner",
            "type":"Services"
        }
    ],
    "sg:phone":"+61 7 3264 5159",
    "sg:postcode":"4035",
    "sg:province":"QLD",
    "sg:tags":[
        "physiotherapist"
    ],
    "wof:name":"Slattery Marion",
    "wof:placetype":"venue"
},
  "geometry": {"coordinates":[152.96537799999999,-27.345913],"type":"Point"}
}