{
  "type": "Feature",
  "properties": {
    "iso:country":"AU",
    "sg:address":"369 High St",
    "sg:city":"Lalor",
    "sg:classifiers":[
        {
            "category":"Home & Garden",
            "subcategory":"Building Materials",
            "type":"Retail Goods"
        }
    ],
    "sg:phone":"+61 3 9465 6044",
    "sg:postcode":"3075",
    "sg:province":"VIC",
    "sg:tags":[
        "wall",
        "frame",
        "truss",
        "roof"
    ],
    "wof:name":"Alpine Truss Pty Ltd",
    "wof:placetype":"venue"
},
  "geometry": {"coordinates":[145.11845398,-37.7572898865],"type":"Point"}
}