{
  "type": "Feature",
  "properties": {
    "addr:full":"8 Abrams St Balcatta WA 6021",
    "addr:housenumber":"8",
    "addr:postcode":"6021",
    "addr:street":"Abrams St",
    "iso:country":"AU",
    "sg:address":"8 Abrams St",
    "sg:city":"Balcatta",
    "sg:classifiers":[
        {
            "category":"Wholesale",
            "subcategory":"Construction Materials",
            "type":"Manufacturing & Wholesale Goods"
        }
    ],
    "sg:phone":"+61 8 9240 1699",
    "sg:postcode":"6021",
    "sg:province":"WA",
    "sg:tags":[
        "wholesaler",
        "lighting",
        "mfrs",
        "accessory"
    ],
    "wof:name":"Electrical Distributors Of W.A.",
    "wof:placetype":"venue"
},
  "geometry": {"coordinates":[115.805030823,-31.8650455475],"type":"Point"}
}