{
  "type": "Feature",
  "properties": {
    "addr:full":"Level 4/ 68 Waterloo Rd North Ryde NSW 2113",
    "addr:housenumber":"/ 68",
    "addr:postcode":"2113",
    "addr:street":"Waterloo Rd",
    "iso:country":"AU",
    "sg:address":"Level 4/ 68 Waterloo Rd",
    "sg:city":"North Ryde",
    "sg:classifiers":[
        {
            "category":"Utilities",
            "subcategory":"Telephone",
            "type":"Services"
        }
    ],
    "sg:phone":"+61 2 9855 6000",
    "sg:postcode":"2113",
    "sg:province":"NSW",
    "wof:name":"AT & T Global Network Services Australia Pty Ltd",
    "wof:placetype":"venue"
},
  "geometry": {"coordinates":[151.125076294,-33.7827987671],"type":"Point"}
}