{
  "type": "Feature",
  "properties": {
    "addr:full":"660 Macarthur Ave Central Pinkenba QLD 4008",
    "addr:housenumber":"660",
    "addr:postcode":"4008",
    "addr:street":"Macarthur Ave Central",
    "iso:country":"AU",
    "sg:address":"660 Macarthur Ave",
    "sg:city":"Central Pinkenba",
    "sg:classifiers":[
        {
            "category":"Shopping",
            "subcategory":"Crafts & Fabrics",
            "type":"Retail Goods"
        }
    ],
    "sg:phone":"+61 7 3260 2206",
    "sg:postcode":"4008",
    "sg:province":"QLD",
    "sg:tags":[
        "adhesive"
    ],
    "wof:name":"AVS Adhesives",
    "wof:placetype":"venue"
},
  "geometry": {"coordinates":[153.11383056599999,-27.4325256348],"type":"Point"}
}