{
  "type": "Feature",
  "properties": {
    "addr:full":"228 Comur St Yass NSW 2582",
    "addr:housenumber":"228",
    "addr:postcode":"2582",
    "addr:street":"Comur St",
    "iso:country":"AU",
    "sg:address":"228 Comur St",
    "sg:city":"Yass",
    "sg:classifiers":[
        {
            "category":"Autos & Motor Vehicles",
            "subcategory":"Fuel & Gas Station",
            "type":"Retail Goods"
        }
    ],
    "sg:phone":"+61 2 6226 1542",
    "sg:postcode":"2582",
    "sg:province":"NSW",
    "wof:name":"Barry Petroleum",
    "wof:placetype":"venue"
},
  "geometry": {"coordinates":[148.91412353499999,-34.8451690674],"type":"Point"}
}