{
  "type": "Feature",
  "properties": {
    "iso:country":"AU",
    "sg:address":"2 Camira Ave",
    "sg:city":"Jindabyne East",
    "sg:classifiers":[
        {
            "category":"Utilities",
            "type":"Services"
        }
    ],
    "sg:phone":"+61 2 6456 2231",
    "sg:postcode":"2627",
    "sg:province":"NSW",
    "sg:tags":[
        "refrigeration",
        "industrial",
        "commercial",
        "retail"
    ],
    "wof:name":"Jindabyne Refrigeration",
    "wof:placetype":"venue"
},
  "geometry": {"coordinates":[148.651687622,-36.3920555115],"type":"Point"}
}