{
  "type": "Feature",
  "properties": {
    "addr:full":"41 Bembridge Ave Frankston South VIC 3199",
    "addr:housenumber":"41",
    "addr:postcode":"3199",
    "addr:street":"Bembridge Ave",
    "iso:country":"AU",
    "sg:address":"41 Bembridge Ave",
    "sg:city":"Frankston South",
    "sg:classifiers":[
        {
            "category":"Banks & Credit Unions",
            "subcategory":"Investment Brokerage",
            "type":"Services"
        }
    ],
    "sg:phone":"+61 407 754 917",
    "sg:postcode":"3199",
    "sg:province":"VIC",
    "sg:tags":[
        "paint",
        "supply",
        "removal"
    ],
    "wof:name":"Summerhill Maintenance Services",
    "wof:placetype":"venue"
},
  "geometry": {"coordinates":[145.10911560100001,-38.1604385376],"type":"Point"}
}