{
  "type": "Feature",
  "properties": {
    "addr:full":"Shop 5, 1215 Anzac Pde Malabar NSW 2036",
    "addr:housenumber":"shop 5",
    "addr:postcode":"1215;2036",
    "addr:street":"Anzac Pde",
    "iso:country":"AU",
    "sg:address":"Shop 5, 1215 Anzac Pde",
    "sg:city":"Malabar",
    "sg:classifiers":[
        {
            "category":"Travel",
            "subcategory":"Travel Agent",
            "type":"Entertainment"
        }
    ],
    "sg:phone":"+61 2 9311 4111",
    "sg:postcode":"2036",
    "sg:province":"NSW",
    "sg:tags":[
        "consultant"
    ],
    "wof:name":"Coconut Grove Travel Malabar",
    "wof:placetype":"venue"
},
  "geometry": {"coordinates":[151.245803833,-33.9632873535],"type":"Point"}
}