{
  "type": "Feature",
  "properties": {
    "addr:full":"178 South Creek Rd Dee Why NSW 2099",
    "addr:housenumber":"178",
    "addr:postcode":"2099",
    "addr:street":"South Creek Rd",
    "iso:country":"AU",
    "sg:address":"178 South Creek Rd",
    "sg:city":"Dee Why",
    "sg:classifiers":[
        {
            "category":"Retail",
            "subcategory":"Auto Repair",
            "type":"Services"
        }
    ],
    "sg:phone":"+61 2 9971 4190",
    "sg:postcode":"2099",
    "sg:province":"NSW",
    "sg:tags":[
        "clutch",
        "brake"
    ],
    "wof:name":"Dee Why Automotive Services",
    "wof:placetype":"venue"
},
  "geometry": {"coordinates":[151.27952575699999,-33.7341384888],"type":"Point"}
}