{
  "type": "Feature",
  "properties": {
    "addr:full":"PO Box 4264 Forster NSW 2428",
    "addr:postcode":"2428",
    "iso:country":"AU",
    "sg:address":"PO Box 4264",
    "sg:city":"Forster",
    "sg:classifiers":[
        {
            "category":"Home & Garden",
            "subcategory":"Carpets & Floor Coverings",
            "type":"Retail Goods"
        }
    ],
    "sg:phone":"+61 2 6555 2156",
    "sg:postcode":"2428",
    "sg:province":"NSW",
    "sg:tags":[
        "tile",
        "wall"
    ],
    "wof:name":"AMG Tiling",
    "wof:placetype":"venue"
},
  "geometry": {"coordinates":[152.51608300000001,-32.18552],"type":"Point"}
}