{
  "type": "Feature",
  "properties": {
    "addr:full":"1079 Frankston-Flinders Rd Somerville VIC 3912",
    "addr:housenumber":"1079",
    "addr:postcode":"3912",
    "addr:street":"Frankston-Flinders Rd",
    "iso:country":"AU",
    "sg:address":"1079 Frankston-Flinders Rd",
    "sg:city":"Somerville",
    "sg:classifiers":[
        {
            "category":"Structure",
            "subcategory":"Bridge",
            "type":"Public Place"
        }
    ],
    "sg:phone":"+61 3 5977 5122",
    "sg:postcode":"3912",
    "sg:province":"VIC",
    "sg:tags":[
        "chainsaw",
        "brushcutters"
    ],
    "wof:name":"Somerville W. & G. Mower Services",
    "wof:placetype":"venue"
},
  "geometry": {"coordinates":[145.17669677699999,-38.2246360779],"type":"Point"}
}