{
  "type": "Feature",
  "properties": {
    "addr:full":"50 William St Beaudesert QLD 4285",
    "addr:housenumber":"50",
    "addr:postcode":"4285",
    "addr:street":"William St",
    "iso:country":"AU",
    "sg:address":"50 William St",
    "sg:city":"Beaudesert",
    "sg:classifiers":[
        {
            "category":"Health Services",
            "subcategory":"Doctor",
            "type":"Services"
        }
    ],
    "sg:phone":"+61 7 5541 2280",
    "sg:postcode":"4285",
    "sg:province":"QLD",
    "sg:tags":[
        "nurse",
        "nursing"
    ],
    "wof:name":"Blue Nursing Service",
    "wof:placetype":"venue"
},
  "geometry": {"coordinates":[152.996475,-27.98839],"type":"Point"}
}