{
  "type": "Feature",
  "properties": {
    "addr:full":"Shp 1 & 2/ 297 Payneham Rd Royston Park SA 5070",
    "addr:housenumber":"1 & 2 / 297",
    "addr:postcode":"5070",
    "addr:street":"Payneham Rd",
    "iso:country":"AU",
    "sg:address":"Shp 1 & 2/ 297 Payneham Rd",
    "sg:city":"Royston Park",
    "sg:classifiers":[
        {
            "category":"Communications",
            "subcategory":"Film & Video Production",
            "type":"Services"
        }
    ],
    "sg:phone":"+61 8 8132 0052",
    "sg:postcode":"5070",
    "sg:province":"SA",
    "sg:tags":[
        "dvd",
        "library"
    ],
    "wof:name":"V.K's Video DVD & Games",
    "wof:placetype":"venue"
},
  "geometry": {"coordinates":[138.635421753,-34.9004096985],"type":"Point"}
}