{
  "type": "Feature",
  "properties": {
    "addr:full":"Level 4, Suite 14 35 Buckingham St Surry Hills NSW 2010",
    "addr:housenumber":"35",
    "addr:postcode":"2010",
    "addr:street":"Buckingham St",
    "iso:country":"AU",
    "sg:address":"Level 4, Suite 14 35 Buckingham St",
    "sg:city":"Surry Hills NSW",
    "sg:classifiers":[
        {
            "category":"Professional",
            "subcategory":"Computer Services",
            "type":"Services"
        }
    ],
    "sg:postcode":"2010",
    "sg:tags":[
        "business-networking-australia",
        "business-contacts"
    ],
    "sg:website":"http://www.zaabiz.com.au",
    "wof:name":"ZaaBiz Pty Ltd",
    "wof:placetype":"venue"
},
  "geometry": {"coordinates":[150.92334500000001,-33.806371],"type":"Point"}
}