{
  "type": "Feature",
  "properties": {
    "iso:country":"AU",
    "sg:address":"63 Vale St",
    "sg:city":"Cabramatta",
    "sg:classifiers":[
        {
            "category":"Building & Trades",
            "subcategory":"Plumbing",
            "type":"Services"
        }
    ],
    "sg:phone":"+61 419 465 838",
    "sg:postcode":"2166",
    "sg:province":"NSW",
    "sg:tags":[
        "drainers"
    ],
    "wof:name":"A.T.E. Plumbing & Drainage",
    "wof:placetype":"venue"
},
  "geometry": {"coordinates":[150.94854736299999,-33.8963432312],"type":"Point"}
}