{
  "type": "Feature",
  "properties": {
    "addr:full":"104 Herbert St Dandenong East VIC 3175",
    "addr:housenumber":"104",
    "addr:postcode":"3175",
    "addr:street":"Herbert St",
    "iso:country":"AU",
    "sg:address":"104 Herbert St",
    "sg:city":"Dandenong East",
    "sg:classifiers":[
        {
            "category":"Retail",
            "subcategory":"Self-service Laundry",
            "type":"Services"
        }
    ],
    "sg:phone":"+61 3 9706 7493",
    "sg:postcode":"3175",
    "sg:province":"VIC",
    "wof:name":"Herbert St Laundrette",
    "wof:placetype":"venue"
},
  "geometry": {"coordinates":[145.22268676799999,-37.9818878174],"type":"Point"}
}