{
  "type": "Feature",
  "properties": {
    "iso:country":"AU",
    "sg:address":"Shop 3/ 688 Pittwater Rd",
    "sg:city":"Brookvale",
    "sg:classifiers":[
        {
            "category":"Retail",
            "subcategory":"Repair Shop",
            "type":"Services"
        }
    ],
    "sg:phone":"+61 2 9939 5545",
    "sg:postcode":"2100",
    "sg:province":"NSW",
    "sg:tags":[
        "mending",
        "clothing",
        "alteration"
    ],
    "wof:name":"Bruno Vitale Tailor",
    "wof:placetype":"venue"
},
  "geometry": {"coordinates":[151.27186584500001,-33.7623558044],"type":"Point"}
}