{
  "type": "Feature",
  "properties": {
    "iso:country":"AU",
    "sg:address":"8 Rees Rd",
    "sg:city":"Sunbury",
    "sg:classifiers":[
        {
            "category":"Building & Trades",
            "subcategory":"Construction",
            "type":"Services"
        }
    ],
    "sg:phone":"+61 3 9740 7866",
    "sg:postcode":"3429",
    "sg:province":"VIC",
    "sg:tags":[
        "contractor"
    ],
    "wof:name":"D.M. CraftLine Constructions Pty Ltd",
    "wof:placetype":"venue"
},
  "geometry": {"coordinates":[144.70913696299999,-37.5622177124],"type":"Point"}
}