{
  "type": "Feature",
  "properties": {
    "addr:full":"30 Adelaide St Gosford East NSW 2250",
    "addr:housenumber":"30",
    "addr:postcode":"2250",
    "addr:street":"Adelaide St",
    "iso:country":"AU",
    "sg:address":"30 Adelaide St",
    "sg:city":"Gosford East",
    "sg:classifiers":[
        {
            "category":"Health Services",
            "subcategory":"Dentist",
            "type":"Services"
        }
    ],
    "sg:phone":"+61 2 4325 1584",
    "sg:postcode":"2250",
    "sg:province":"NSW",
    "wof:name":"Arndt Chris",
    "wof:placetype":"venue"
},
  "geometry": {"coordinates":[151.355545044,-33.4375572205],"type":"Point"}
}