{
  "type": "Feature",
  "properties": {
    "addr:full":"5 Bertana Drv Mudgeeraba QLD 4213",
    "addr:housenumber":"5",
    "addr:postcode":"4213",
    "addr:street":"Bertana Drv",
    "iso:country":"AU",
    "sg:address":"5 Bertana Drv",
    "sg:city":"Mudgeeraba",
    "sg:classifiers":[
        {
            "category":"Professional",
            "subcategory":"Secretarial Services",
            "type":"Services"
        }
    ],
    "sg:phone":"+61 7 5530 5005",
    "sg:postcode":"4213",
    "sg:province":"QLD",
    "sg:tags":[
        "typing"
    ],
    "wof:name":"Admin Secretarial And Promotion",
    "wof:placetype":"venue"
},
  "geometry": {"coordinates":[153.35469055199999,-28.0926952362],"type":"Point"}
}