{
  "type": "Feature",
  "properties": {
    "addr:full":"48 Riverview Rd Oyster Bay NSW 2225",
    "addr:housenumber":"48",
    "addr:postcode":"2225",
    "addr:street":"Riverview Rd",
    "iso:country":"AU",
    "sg:address":"48 Riverview Rd",
    "sg:city":"Oyster Bay",
    "sg:classifiers":[
        {
            "category":"Education",
            "subcategory":"Special Training",
            "type":"Public Place"
        }
    ],
    "sg:phone":"+61 2 9966 7363",
    "sg:postcode":"2225",
    "sg:province":"NSW",
    "sg:tags":[
        "development"
    ],
    "wof:name":"John Sleigh Management Training",
    "wof:placetype":"venue"
},
  "geometry": {"coordinates":[151.07333374000001,-34.006439209],"type":"Point"}
}