{
  "type": "Feature",
  "properties": {
    "addr:full":"Pipers Creek Rd Kempsey NSW 2440",
    "addr:postcode":"2440",
    "addr:street":"Pipers Creek Rd",
    "iso:country":"AU",
    "sg:address":"Pipers Creek Rd",
    "sg:city":"Kempsey",
    "sg:classifiers":[
        {
            "category":"Arts & Performance",
            "subcategory":"Music",
            "type":"Entertainment"
        }
    ],
    "sg:phone":"+61 2 6562 1147",
    "sg:postcode":"2440",
    "sg:province":"NSW",
    "sg:tags":[
        "mobile",
        "jockey",
        "disc"
    ],
    "wof:name":"CR's Mobile Music",
    "wof:placetype":"venue"
},
  "geometry": {"coordinates":[152.79716500000001,-31.102219],"type":"Point"}
}