{
  "type": "Feature",
  "properties": {
    "addr:full":"1 Doctors Rd Morphett Vale SA 5162",
    "addr:housenumber":"1",
    "addr:postcode":"5162",
    "addr:street":"Doctors Rd",
    "iso:country":"AU",
    "sg:address":"1 Doctors Rd",
    "sg:city":"Morphett Vale",
    "sg:classifiers":[
        {
            "category":"Health Services",
            "subcategory":"Health Practitioner",
            "type":"Services"
        }
    ],
    "sg:phone":"+61 8 8382 7788",
    "sg:postcode":"5162",
    "sg:province":"SA",
    "sg:tags":[
        "naturopath"
    ],
    "wof:name":"Feeling Good Naturally",
    "wof:placetype":"venue"
},
  "geometry": {"coordinates":[138.525192261,-35.1365127563],"type":"Point"}
}