{
  "type": "Feature",
  "properties": {
    "iso:country":"AU",
    "sg:address":"75 Jonson St",
    "sg:city":"Byron Bay",
    "sg:classifiers":[
        {
            "category":"Health Services",
            "subcategory":"Health Practitioner",
            "type":"Services"
        }
    ],
    "sg:phone":"+61 2 6685 5056",
    "sg:postcode":"2481",
    "sg:province":"NSW",
    "sg:tags":[
        "hypnotherapy"
    ],
    "wof:name":"Hypnotix Byron Bay",
    "wof:placetype":"venue"
},
  "geometry": {"coordinates":[153.61286926299999,-28.6482620239],"type":"Point"}
}