{
  "type": "Feature",
  "properties": {
    "addr:full":"12 Garfield Rd Riverstone NSW 2765",
    "addr:housenumber":"12",
    "addr:postcode":"2765",
    "addr:street":"Garfield Rd",
    "iso:country":"AU",
    "sg:address":"12 Garfield Rd",
    "sg:city":"Riverstone",
    "sg:classifiers":[
        {
            "category":"Shopping",
            "subcategory":"Pawn Shop",
            "type":"Retail Goods"
        }
    ],
    "sg:phone":"+61 2 9838 1022",
    "sg:postcode":"2765",
    "sg:province":"NSW",
    "sg:tags":[
        "pawnbroker"
    ],
    "wof:name":"Cashline",
    "wof:placetype":"venue"
},
  "geometry": {"coordinates":[150.86143493599999,-33.6796112061],"type":"Point"}
}