{
  "type": "Feature",
  "properties": {
    "iso:country":"AU",
    "sg:address":"432 Swift St",
    "sg:city":"Albury",
    "sg:classifiers":[
        {
            "category":"Health Services",
            "subcategory":"Doctor",
            "type":"Services"
        }
    ],
    "sg:phone":"+61 2 6021 1744",
    "sg:postcode":"2640",
    "sg:province":"NSW",
    "sg:tags":[
        "occupational",
        "safety"
    ],
    "wof:name":"RehabCo The Rehabilitation Company",
    "wof:placetype":"venue"
},
  "geometry": {"coordinates":[146.916412353,-36.0787963867],"type":"Point"}
}