{
  "type": "Feature",
  "properties": {
    "iso:country":"AU",
    "sg:address":"87 Enmore Rd",
    "sg:city":"Enmore",
    "sg:classifiers":[
        {
            "category":"Professional",
            "subcategory":"Art Services",
            "type":"Services"
        }
    ],
    "sg:phone":"+61 2 9519 0410",
    "sg:postcode":"2042",
    "sg:province":"NSW",
    "sg:tags":[
        "graphic",
        "designer"
    ],
    "wof:name":"iDesign & Print",
    "wof:placetype":"venue"
},
  "geometry": {"coordinates":[151.17477400000001,-33.898838],"type":"Point"}
}