{
  "type": "Feature",
  "properties": {
    "addr:full":"10 Ledgar Rd Balcatta WA 6021",
    "addr:housenumber":"10",
    "addr:postcode":"6021",
    "addr:street":"Ledgar Rd",
    "iso:country":"AU",
    "sg:address":"10 Ledgar Rd",
    "sg:city":"Balcatta",
    "sg:classifiers":[
        {
            "category":"Wholesale",
            "subcategory":"Medical Equipment & Supplies",
            "type":"Manufacturing & Wholesale Goods"
        }
    ],
    "sg:phone":"+61 8 9344 3111",
    "sg:postcode":"6021",
    "sg:province":"WA",
    "sg:tags":[
        "aid",
        "care",
        "health",
        "home"
    ],
    "wof:name":"Perth Surgical Supply Co Pty Ltd",
    "wof:placetype":"venue"
},
  "geometry": {"coordinates":[115.803817749,-31.8656616211],"type":"Point"}
}