{
  "type": "Feature",
  "properties": {
    "addr:full":"Argyle Rd Wilton NSW 2571",
    "addr:postcode":"2571",
    "addr:street":"Argyle Rd",
    "iso:country":"AU",
    "sg:address":"Argyle Rd",
    "sg:city":"Wilton",
    "sg:classifiers":[
        {
            "category":"Food & Beverages",
            "subcategory":"Liquor & Beverages",
            "type":"Retail Goods"
        }
    ],
    "sg:phone":"+61 2 4630 9033",
    "sg:postcode":"2571",
    "sg:province":"NSW",
    "sg:tags":[
        "store"
    ],
    "wof:name":"Wilton Liquor Store",
    "wof:placetype":"venue"
},
  "geometry": {"coordinates":[150.69639587399999,-34.2404251099],"type":"Point"}
}