{
  "type": "Feature",
  "properties": {
    "addr:full":"429 Newmarket Rd Newmarket QLD 4051",
    "addr:housenumber":"429",
    "addr:postcode":"4051",
    "addr:street":"Newmarket Rd",
    "iso:country":"AU",
    "sg:address":"429 Newmarket Rd",
    "sg:city":"Newmarket",
    "sg:classifiers":[
        {
            "category":"Retail",
            "subcategory":"Auto Repair",
            "type":"Services"
        }
    ],
    "sg:phone":"+61 7 3356 5188",
    "sg:postcode":"4051",
    "sg:province":"QLD",
    "sg:tags":[
        "beater",
        "painter",
        "panel"
    ],
    "wof:name":"Newmarket Auto Care",
    "wof:placetype":"venue"
},
  "geometry": {"coordinates":[153.01429748499999,-27.4370689392],"type":"Point"}
}