{
  "type": "Feature",
  "properties": {
    "addr:full":"58 Pine Ave Mildura VIC 3500",
    "addr:housenumber":"58",
    "addr:postcode":"3500",
    "addr:street":"Pine Ave",
    "iso:country":"AU",
    "sg:address":"58 Pine Ave",
    "sg:city":"Mildura",
    "sg:classifiers":[
        {
            "category":"Farming",
            "subcategory":"Orchard",
            "type":"Manufacturing & Wholesale Goods"
        }
    ],
    "sg:phone":"+61 3 5051 0500",
    "sg:postcode":"3500",
    "sg:province":"VIC",
    "sg:tags":[
        "citrus",
        "fruit",
        "grower"
    ],
    "wof:name":"Murray Valley Citrus Board",
    "wof:placetype":"venue"
},
  "geometry": {"coordinates":[142.159057617,-34.1830940247],"type":"Point"}
}