{
  "type": "Feature",
  "properties": {
    "iso:country":"AU",
    "sg:address":"18 Milton St",
    "sg:city":"Hamilton",
    "sg:classifiers":[
        {
            "category":"Wholesale",
            "subcategory":"Farm Supplies",
            "type":"Manufacturing & Wholesale Goods"
        }
    ],
    "sg:phone":"+61 429 721 523",
    "sg:postcode":"3300",
    "sg:province":"VIC",
    "sg:tags":[
        "equipment"
    ],
    "wof:name":"Ross Trahair Sustainable Agriculture Hamilton",
    "wof:placetype":"venue"
},
  "geometry": {"coordinates":[142.021316528,-37.7380905151],"type":"Point"}
}