{
  "type": "Feature",
  "properties": {
    "iso:country":"AU",
    "sg:address":"135 Rosedale Rd St",
    "sg:city":"Ives",
    "sg:classifiers":[
        {
            "category":"Building & Trades",
            "subcategory":"Construction",
            "type":"Services"
        }
    ],
    "sg:phone":"+61 2 9988 3449",
    "sg:postcode":"2075",
    "sg:province":"NSW",
    "sg:tags":[
        "decking",
        "contractor"
    ],
    "wof:name":"All Timber Repairs",
    "wof:placetype":"venue"
},
  "geometry": {"coordinates":[151.15994262699999,-33.7350959778],"type":"Point"}
}