{
  "type": "Feature",
  "properties": {
    "iso:country":"AU",
    "sg:address":"8 Juna Drv",
    "sg:city":"Malaga",
    "sg:classifiers":[
        {
            "category":"Banks & Credit Unions",
            "subcategory":"Financial Services",
            "type":"Services"
        }
    ],
    "sg:phone":"+61 8 9248 7570",
    "sg:postcode":"6090",
    "sg:province":"WA",
    "sg:tags":[
        "wholesaler",
        "mfrs",
        "tap"
    ],
    "wof:name":"Santec",
    "wof:placetype":"venue"
},
  "geometry": {"coordinates":[115.903526306,-31.8657455444],"type":"Point"}
}