{
  "type": "Feature",
  "properties": {
    "addr:full":"2 Powdrill Rd Lurnea NSW 2170",
    "addr:housenumber":"2",
    "addr:postcode":"2170",
    "addr:street":"Powdrill Rd",
    "iso:country":"AU",
    "sg:address":"2 Powdrill Rd",
    "sg:city":"Lurnea",
    "sg:classifiers":[
        {
            "category":"Home & Garden",
            "subcategory":"Building Materials",
            "type":"Retail Goods"
        }
    ],
    "sg:phone":"+61 2 9607 5759",
    "sg:postcode":"2170",
    "sg:province":"NSW",
    "sg:tags":[
        "supply"
    ],
    "wof:name":"Concrete Accessories Pty Ltd",
    "wof:placetype":"venue"
},
  "geometry": {"coordinates":[150.88917541500001,-33.9347572327],"type":"Point"}
}