{
  "type": "Feature",
  "properties": {
    "iso:country":"AU",
    "sg:address":"Unit 4/ 77 Batt St",
    "sg:city":"Penrith",
    "sg:classifiers":[
        {
            "category":"Utilities",
            "subcategory":"Water",
            "type":"Services"
        }
    ],
    "sg:phone":"+61 2 4776 2496",
    "sg:postcode":"2750",
    "sg:province":"NSW",
    "sg:tags":[
        "cartage"
    ],
    "wof:name":"Aquarius Water Cart Hire & Delivery",
    "wof:placetype":"venue"
},
  "geometry": {"coordinates":[150.68519592300001,-33.7677650452],"type":"Point"}
}