{
  "type": "Feature",
  "properties": {
    "addr:full":"13 William St Mile End South SA 5031",
    "addr:housenumber":"13",
    "addr:postcode":"5031",
    "addr:street":"William St",
    "iso:country":"AU",
    "sg:address":"13 William St",
    "sg:city":"Mile End South",
    "sg:classifiers":[
        {
            "category":"Communications",
            "type":"Services"
        }
    ],
    "sg:phone":"+61 8 8152 6700",
    "sg:postcode":"5031",
    "sg:province":"SA",
    "sg:tags":[
        "antenna"
    ],
    "wof:name":"Gridcomm Pty Ltd",
    "wof:placetype":"venue"
},
  "geometry": {"coordinates":[138.57188415499999,-34.9340820312],"type":"Point"}
}