{
  "type": "Feature",
  "properties": {
    "addr:full":"244a Huntingdale Rd Oakleigh VIC 3166",
    "addr:housenumber":"244a",
    "addr:postcode":"3166",
    "addr:street":"Huntingdale Rd",
    "iso:country":"AU",
    "sg:address":"244a Huntingdale Rd",
    "sg:city":"Oakleigh",
    "sg:classifiers":[
        {
            "category":"Autos & Motor Vehicles",
            "subcategory":"Fuel & Gas Station",
            "type":"Retail Goods"
        }
    ],
    "sg:phone":"+61 3 9562 9383",
    "sg:postcode":"3166",
    "sg:province":"VIC",
    "sg:tags":[
        "injection",
        "diesel"
    ],
    "wof:name":"Expert Injector Clean",
    "wof:placetype":"venue"
},
  "geometry": {"coordinates":[145.10476684599999,-37.9054107666],"type":"Point"}
}