{
  "type": "Feature",
  "properties": {
    "addr:full":"6 Bell St Watsons Bay NSW 2030",
    "addr:housenumber":"6",
    "addr:postcode":"2030",
    "addr:street":"Bell St",
    "iso:country":"AU",
    "sg:address":"6 Bell St",
    "sg:city":"Watsons Bay",
    "sg:classifiers":[
        {
            "category":"Professional",
            "subcategory":"Computer Services",
            "type":"Services"
        }
    ],
    "sg:phone":"+61 2 9337 4503",
    "sg:postcode":"2030",
    "sg:province":"NSW",
    "sg:tags":[
        "consultant",
        "system"
    ],
    "wof:name":"Publisoft Pty Ltd",
    "wof:placetype":"venue"
},
  "geometry": {"coordinates":[151.28390502900001,-33.8471603394],"type":"Point"}
}