{
  "type": "Feature",
  "properties": {
    "iso:country":"AU",
    "sg:address":"The Willows Herveys Range Rd",
    "sg:city":"Thuringowa Central",
    "sg:classifiers":[
        {
            "category":"Fast Food",
            "type":"Food & Drink"
        }
    ],
    "sg:phone":"+61 13 11 66",
    "sg:postcode":"4817",
    "sg:province":"QLD",
    "sg:tags":[
        "away",
        "take"
    ],
    "wof:name":"Pizza Hut",
    "wof:placetype":"venue"
},
  "geometry": {"coordinates":[146.723907,-19.31901],"type":"Point"}
}