{
  "type": "Feature",
  "properties": {
    "iso:country":"AU",
    "sg:address":"23 Providence Drv",
    "sg:city":"Bella Vista",
    "sg:classifiers":[
        {
            "category":"Professional",
            "subcategory":"Computer Services",
            "type":"Services"
        }
    ],
    "sg:phone":"+61 2 9620 5576",
    "sg:postcode":"2153",
    "sg:province":"NSW",
    "sg:tags":[
        "consultant",
        "system"
    ],
    "wof:name":"PakNet IT Services",
    "wof:placetype":"venue"
},
  "geometry": {"coordinates":[150.959594727,-33.7470626831],"type":"Point"}
}