{
  "type": "Feature",
  "properties": {
    "iso:country":"AU",
    "sg:address":"27 High St",
    "sg:city":"Coburg",
    "sg:classifiers":[
        {
            "category":"Personal",
            "subcategory":"Tattoo Parlor",
            "type":"Services"
        }
    ],
    "sg:phone":"+61 421 406 292",
    "sg:postcode":"3058",
    "sg:province":"VIC",
    "sg:tags":[
        "resume"
    ],
    "wof:name":"Resume Magic!",
    "wof:placetype":"venue"
},
  "geometry": {"coordinates":[144.956008911,-37.7385215759],"type":"Point"}
}