{
  "type": "Feature",
  "properties": {
    "iso:country":"AU",
    "sg:address":"509 Boundry Rd",
    "sg:city":"Darra",
    "sg:classifiers":[
        {
            "category":"Manufacturing",
            "subcategory":"Paper Products",
            "type":"Manufacturing & Wholesale Goods"
        }
    ],
    "sg:phone":"+61 7 3375 1033",
    "sg:postcode":"4076",
    "sg:province":"QLD",
    "sg:tags":[
        "wholesaler",
        "mfrs"
    ],
    "wof:name":"Amcor Paper",
    "wof:placetype":"venue"
},
  "geometry": {"coordinates":[152.961425781,-27.5758419037],"type":"Point"}
}