{
  "type": "Feature",
  "properties": {
    "iso:country":"AU",
    "sg:address":"75 King St",
    "sg:city":"Sydney",
    "sg:classifiers":[
        {
            "category":"Personal",
            "subcategory":"Beauty Salon",
            "type":"Services"
        }
    ],
    "sg:phone":"+61 2 9290 3419",
    "sg:postcode":"2000",
    "sg:province":"NSW",
    "sg:tags":[
        "hairdresser"
    ],
    "wof:name":"Rantzos",
    "wof:placetype":"venue"
},
  "geometry": {"coordinates":[151.206756592,-33.8688278198],"type":"Point"}
}