{
  "type": "Feature",
  "properties": {
    "iso:country":"AU",
    "sg:address":"2 South St",
    "sg:city":"Busselton",
    "sg:classifiers":[
        {
            "category":"Education",
            "subcategory":"Vocational School",
            "type":"Public Place"
        }
    ],
    "sg:phone":"+61 8 9752 6600",
    "sg:postcode":"6280",
    "sg:province":"WA",
    "sg:tags":[
        "technical",
        "college",
        "trade"
    ],
    "wof:name":"Busselton Campus",
    "wof:placetype":"venue"
},
  "geometry": {"coordinates":[115.327201843,-33.6574172974],"type":"Point"}
}