{
  "type": "Feature",
  "properties": {
    "addr:full":"Level 1, 333- 339 George St Sydney NSW 2000",
    "addr:housenumber":"333 339",
    "addr:postcode":"2000",
    "addr:street":"George St",
    "iso:country":"AU",
    "sg:address":"Level 1, 333- 339 George St",
    "sg:city":"Sydney",
    "sg:classifiers":[
        {
            "category":"Social Services",
            "subcategory":"Child Care",
            "type":"Services"
        }
    ],
    "sg:phone":"+61 1800 002 158",
    "sg:postcode":"2000",
    "sg:province":"NSW",
    "sg:tags":[
        "fleet",
        "management"
    ],
    "wof:name":"National Australia Bank",
    "wof:placetype":"venue"
},
  "geometry": {"coordinates":[151.20698547399999,-33.867023468],"type":"Point"}
}