{
  "type": "Feature",
  "properties": {
    "iso:country":"AU",
    "sg:address":"83b Graham St",
    "sg:city":"Wonthaggi",
    "sg:classifiers":[
        {
            "category":"Fast Food",
            "type":"Food & Drink"
        }
    ],
    "sg:phone":"+61 3 5672 4199",
    "sg:postcode":"3995",
    "sg:province":"VIC",
    "sg:tags":[
        "away",
        "take"
    ],
    "wof:name":"Rondels Take-Away",
    "wof:placetype":"venue"
},
  "geometry": {"coordinates":[145.592728,-38.60603],"type":"Point"}
}