{
  "type": "Feature",
  "properties": {
    "addr:full":"461 Golden Four Drv Tugun QLD 4224",
    "addr:housenumber":"461",
    "addr:postcode":"4224",
    "addr:street":"Golden Four Drv",
    "iso:country":"AU",
    "sg:address":"461 Golden Four Drv",
    "sg:city":"Tugun",
    "sg:classifiers":[
        {
            "category":"Food & Beverages",
            "subcategory":"Supermarket",
            "type":"Retail Goods"
        }
    ],
    "sg:phone":"+61 7 5534 5414",
    "sg:postcode":"4224",
    "sg:province":"QLD",
    "sg:tags":[
        "grocery",
        "store"
    ],
    "wof:name":"Foodworks Tugun Beach",
    "wof:placetype":"venue"
},
  "geometry": {"coordinates":[153.49378967300001,-28.1428108215],"type":"Point"}
}