{
  "type": "Feature",
  "properties": {
    "addr:full":"315 Karinie St Swan Hill VIC 3585",
    "addr:housenumber":"315",
    "addr:postcode":"3585",
    "addr:street":"Karinie St",
    "iso:country":"AU",
    "sg:address":"315 Karinie St",
    "sg:city":"Swan Hill",
    "sg:classifiers":[
        {
            "category":"Professional",
            "subcategory":"Engineering",
            "type":"Services"
        }
    ],
    "sg:phone":"+61 3 5032 1201",
    "sg:postcode":"3585",
    "sg:province":"VIC",
    "sg:tags":[
        "civil",
        "engineer"
    ],
    "wof:name":"Cadd G N",
    "wof:placetype":"venue"
},
  "geometry": {"coordinates":[143.52522300000001,-35.32415],"type":"Point"}
}