{
  "type": "Feature",
  "properties": {
    "iso:country":"AU",
    "sg:address":"103 Longueville Rd",
    "sg:city":"Lane Cove",
    "sg:classifiers":[
        {
            "category":"Professional",
            "subcategory":"Printing & Photocopies",
            "type":"Services"
        }
    ],
    "sg:phone":"+61 2 9420 2000",
    "sg:postcode":"2066",
    "sg:province":"NSW",
    "sg:tags":[
        "photocopier"
    ],
    "wof:name":"A Access Mobile Solutions",
    "wof:placetype":"venue"
},
  "geometry": {"coordinates":[151.170043945,-33.8142051697],"type":"Point"}
}