{
  "type": "Feature",
  "properties": {
    "addr:full":"286- 288 Wells Rd Aspendale Gardens VIC 3195",
    "addr:housenumber":"286 288",
    "addr:postcode":"3195",
    "addr:street":"Wells Rd",
    "iso:country":"AU",
    "sg:address":"286- 288 Wells Rd",
    "sg:city":"Aspendale Gardens",
    "sg:classifiers":[
        {
            "category":"Health Services",
            "subcategory":"Dentist",
            "type":"Services"
        }
    ],
    "sg:phone":"+61 3 9590 9120",
    "sg:postcode":"3195",
    "sg:province":"VIC",
    "wof:name":"Australian Smiles Pty Ltd",
    "wof:placetype":"venue"
},
  "geometry": {"coordinates":[145.12773132300001,-38.0255050659],"type":"Point"}
}