{
  "type": "Feature",
  "properties": {
    "addr:full":"Unit 1, 6 Finniss St Darwin NT 0800",
    "addr:housenumber":"6",
    "addr:postcode":"nt 0800",
    "addr:street":"Finniss St",
    "iso:country":"AU",
    "sg:address":"Unit 1, 6 Finniss St",
    "sg:city":"Darwin",
    "sg:classifiers":[
        {
            "category":"Shopping",
            "subcategory":"Crafts & Fabrics",
            "type":"Retail Goods"
        }
    ],
    "sg:phone":"+61 8 8981 1555",
    "sg:postcode":"0800",
    "sg:province":"NT",
    "sg:tags":[
        "upholstering",
        "supply"
    ],
    "wof:name":"Upholstering Distributors Australia (UDA)",
    "wof:placetype":"venue"
},
  "geometry": {"coordinates":[130.83900451700001,-12.4536724091],"type":"Point"}
}