{
  "type": "Feature",
  "properties": {
    "iso:country":"AU",
    "sg:address":"19 Ludeman Crt",
    "sg:city":"Reservoir",
    "sg:classifiers":[
        {
            "category":"Insurance",
            "subcategory":"Insurance Agent",
            "type":"Services"
        }
    ],
    "sg:phone":"+61 3 9462 2072",
    "sg:postcode":"3073",
    "sg:province":"VIC",
    "wof:name":"Calello Peter & Associates",
    "wof:placetype":"venue"
},
  "geometry": {"coordinates":[144.998657227,-37.6987228394],"type":"Point"}
}