{
  "type": "Feature",
  "properties": {
    "addr:full":"109 Holt Ave Cremorne NSW 2090",
    "addr:housenumber":"109",
    "addr:postcode":"2090",
    "addr:street":"Holt Ave",
    "iso:country":"AU",
    "sg:address":"109 Holt Ave",
    "sg:city":"Cremorne",
    "sg:classifiers":[
        {
            "category":"Health Services",
            "subcategory":"Health Practitioner",
            "type":"Services"
        }
    ],
    "sg:phone":"+61 2 9953 1121",
    "sg:postcode":"2090",
    "sg:province":"NSW",
    "sg:tags":[
        "alternative"
    ],
    "wof:name":"Feldenkrais Method",
    "wof:placetype":"venue"
},
  "geometry": {"coordinates":[151.22996520999999,-33.83070755],"type":"Point"}
}