{
  "type": "Feature",
  "properties": {
    "addr:full":"68 Throsby St Fairfield NSW 2165",
    "addr:housenumber":"68",
    "addr:postcode":"2165",
    "addr:street":"Throsby St",
    "iso:country":"AU",
    "sg:address":"68 Throsby St",
    "sg:city":"Fairfield",
    "sg:classifiers":[
        {
            "category":"Building & Trades",
            "subcategory":"Pest Control",
            "type":"Services"
        }
    ],
    "sg:phone":"+61 2 9788 6334",
    "sg:postcode":"2165",
    "sg:province":"NSW",
    "wof:name":"On-Site Pest Solution",
    "wof:placetype":"venue"
},
  "geometry": {"coordinates":[150.93289184599999,-33.868270874],"type":"Point"}
}