{
  "type": "Feature",
  "properties": {
    "addr:full":"PO Box 1385 Taree NSW 2430",
    "addr:postcode":"2430",
    "iso:country":"AU",
    "sg:address":"PO Box 1385",
    "sg:city":"Taree",
    "sg:classifiers":[
        {
            "category":"Utilities",
            "subcategory":"Water",
            "type":"Services"
        }
    ],
    "sg:phone":"+61 2 6550 5894",
    "sg:postcode":"2430",
    "sg:province":"NSW",
    "sg:tags":[
        "hot",
        "system"
    ],
    "wof:name":"Midco Electrical",
    "wof:placetype":"venue"
},
  "geometry": {"coordinates":[152.46151699999999,-31.91313],"type":"Point"}
}