{
  "type": "Feature",
  "properties": {
    "iso:country":"AU",
    "sg:address":"2a Beaconsfield St",
    "sg:city":"Doncaster",
    "sg:classifiers":[
        {
            "category":"Retail",
            "subcategory":"Auto Repair",
            "type":"Services"
        }
    ],
    "sg:phone":"+61 3 9848 1841",
    "sg:postcode":"3108",
    "sg:province":"VIC",
    "sg:tags":[
        "repairer",
        "motor",
        "engineer"
    ],
    "wof:name":"J M & J M Donohue Auto Repairs",
    "wof:placetype":"venue"
},
  "geometry": {"coordinates":[145.122024536,-37.7875022888],"type":"Point"}
}