{
  "type": "Feature",
  "properties": {
    "addr:full":"735 Stanley St Woolloongabba QLD 4102",
    "addr:housenumber":"735",
    "addr:postcode":"4102",
    "addr:street":"Stanley St",
    "iso:country":"AU",
    "sg:address":"735 Stanley St",
    "sg:city":"Woolloongabba",
    "sg:classifiers":[
        {
            "category":"Retail",
            "subcategory":"Event Space",
            "type":"Services"
        }
    ],
    "sg:phone":"+61 7 3896 6565",
    "sg:postcode":"4102",
    "sg:province":"QLD",
    "sg:tags":[
        "function",
        "organiser"
    ],
    "wof:name":"Chalk",
    "wof:placetype":"venue"
},
  "geometry": {"coordinates":[153.03335571299999,-27.4862308502],"type":"Point"}
}