{
  "type": "Feature",
  "properties": {
    "iso:country":"AU",
    "sg:address":"12 Carngham Rd",
    "sg:city":"Ballarat",
    "sg:classifiers":[
        {
            "category":"Building & Trades",
            "subcategory":"Construction",
            "type":"Services"
        }
    ],
    "sg:phone":"+61 419 589 668",
    "sg:postcode":"3350",
    "sg:province":"VIC",
    "sg:tags":[
        "plasterboard",
        "plasterer",
        "fixer"
    ],
    "wof:name":"Darren Reeves Plastering",
    "wof:placetype":"venue"
},
  "geometry": {"coordinates":[143.85737599999999,-37.581841],"type":"Point"}
}