{
  "type": "Feature",
  "properties": {
    "addr:full":"PO Box 900 Hamilton NSW 2303",
    "addr:postcode":"2303",
    "iso:country":"AU",
    "sg:address":"PO Box 900",
    "sg:city":"Hamilton",
    "sg:classifiers":[
        {
            "category":"Banks & Credit Unions",
            "subcategory":"Bank",
            "type":"Services"
        }
    ],
    "sg:phone":"+61 410 695 671",
    "sg:postcode":"2303",
    "sg:province":"NSW",
    "sg:tags":[
        "broker",
        "mortgage"
    ],
    "wof:name":"Smooth Financial Solutions",
    "wof:placetype":"venue"
},
  "geometry": {"coordinates":[151.746994,-32.923489],"type":"Point"}
}