{
  "type": "Feature",
  "properties": {
    "addr:full":"Shop 3, 291A Spring St Reservoir VIC 3073",
    "addr:housenumber":"shop 3 291a",
    "addr:postcode":"3073",
    "addr:street":"Spring St",
    "iso:country":"AU",
    "sg:address":"Shop 3, 291A Spring St",
    "sg:city":"Reservoir",
    "sg:classifiers":[
        {
            "category":"Travel",
            "subcategory":"Travel Agent",
            "type":"Entertainment"
        }
    ],
    "sg:phone":"+61 3 9460 7883",
    "sg:postcode":"3073",
    "sg:province":"VIC",
    "sg:tags":[
        "consultant"
    ],
    "wof:name":"Reservoir Travel",
    "wof:placetype":"venue"
},
  "geometry": {"coordinates":[145.007415772,-37.71459198],"type":"Point"}
}