{
  "type": "Feature",
  "properties": {
    "iso:country":"AU",
    "sg:address":"236 Merriworth Rd",
    "sg:city":"Tea Tree",
    "sg:classifiers":[
        {
            "category":"Food & Beverages",
            "subcategory":"Specialty",
            "type":"Retail Goods"
        }
    ],
    "sg:phone":"+61 3 6268 1165",
    "sg:postcode":"7017",
    "sg:province":"TAS",
    "sg:tags":[
        "product",
        "health"
    ],
    "wof:name":"Herbalife Australasia Pty Ltd",
    "wof:placetype":"venue"
},
  "geometry": {"coordinates":[147.332199097,-42.6715278625],"type":"Point"}
}