{
  "type": "Feature",
  "properties": {
    "addr:full":"Cnr Turnbull & Hoddle Sts Clifton Hill VIC 3068",
    "addr:postcode":"3068",
    "iso:country":"AU",
    "sg:address":"Cnr Turnbull & Hoddle Sts",
    "sg:city":"Clifton Hill",
    "sg:classifiers":[
        {
            "category":"Personal",
            "subcategory":"Massage",
            "type":"Services"
        }
    ],
    "sg:phone":"+61 3 9205 5522",
    "sg:postcode":"3068",
    "sg:province":"VIC",
    "sg:tags":[
        "therapy"
    ],
    "wof:name":"Peter Prskalo",
    "wof:placetype":"venue"
},
  "geometry": {"coordinates":[144.99461364699999,-37.7901763916],"type":"Point"}
}