{
  "type": "Feature",
  "properties": {
    "addr:full":"325 MacDonnell Rd Redcliffe QLD 4020",
    "addr:housenumber":"325",
    "addr:postcode":"4020",
    "addr:street":"Macdonnell Rd",
    "iso:country":"AU",
    "sg:address":"325 MacDonnell Rd",
    "sg:city":"Redcliffe",
    "sg:classifiers":[
        {
            "category":"Shopping",
            "subcategory":"Stationery & Office Supplies",
            "type":"Retail Goods"
        }
    ],
    "sg:phone":"+61 7 3883 1300",
    "sg:postcode":"4020",
    "sg:province":"QLD",
    "wof:name":"Office National",
    "wof:placetype":"venue"
},
  "geometry": {"coordinates":[153.10406499999999,-27.236977],"type":"Point"}
}