{
  "type": "Feature",
  "properties": {
    "iso:country":"AU",
    "sg:address":"Unit 71 Cnr Challis & Cape Sts",
    "sg:city":"Dickson",
    "sg:classifiers":[
        {
            "category":"Fast Food",
            "type":"Food & Drink"
        }
    ],
    "sg:phone":"+61 2 6262 7888",
    "sg:postcode":"2602",
    "sg:province":"ACT",
    "sg:tags":[
        "away",
        "take"
    ],
    "wof:name":"Wasabi Teppanyaki",
    "wof:placetype":"venue"
},
  "geometry": {"coordinates":[149.135055542,-35.252456665],"type":"Point"}
}