{
  "type": "Feature",
  "properties": {
    "iso:country":"AU",
    "sg:address":"Dodd Rd",
    "sg:city":"Port Lincoln",
    "sg:classifiers":[
        {
            "category":"Professional",
            "subcategory":"Detective & Security Services",
            "type":"Services"
        }
    ],
    "sg:phone":"+61 8 8682 4878",
    "sg:postcode":"5606",
    "sg:province":"SA",
    "sg:tags":[
        "protective",
        "rustproofing"
    ],
    "wof:name":"Rust Busters",
    "wof:placetype":"venue"
},
  "geometry": {"coordinates":[135.824783,-34.738323],"type":"Point"}
}