{
  "type": "Feature",
  "properties": {
    "iso:country":"AU",
    "sg:address":"397- 399 The Entrance Rd",
    "sg:city":"Long Jetty",
    "sg:classifiers":[
        {
            "category":"Social Services",
            "type":"Services"
        }
    ],
    "sg:phone":"+61 2 4332 4484",
    "sg:postcode":"2261",
    "sg:province":"NSW",
    "sg:tags":[
        "disabled",
        "person",
        "equipment"
    ],
    "wof:name":"The Mobility Centre",
    "wof:placetype":"venue"
},
  "geometry": {"coordinates":[151.485443,-33.357731],"type":"Point"}
}