{
  "type": "Feature",
  "properties": {
    "addr:full":"462 Parramatta Rd Petersham NSW 2049",
    "addr:housenumber":"462",
    "addr:postcode":"2049",
    "addr:street":"Parramatta Rd",
    "iso:country":"AU",
    "sg:address":"462 Parramatta Rd",
    "sg:city":"Petersham",
    "sg:classifiers":[
        {
            "category":"Real Estate",
            "subcategory":"Real Estate Agent",
            "type":"Services"
        }
    ],
    "sg:phone":"+61 2 9560 8466",
    "sg:postcode":"2049",
    "sg:province":"NSW",
    "wof:name":"NSW Home Unit Centre",
    "wof:placetype":"venue"
},
  "geometry": {"coordinates":[151.15872200000001,-33.888184],"type":"Point"}
}