{
  "type": "Feature",
  "properties": {
    "addr:full":"PO Box 424 Killara NSW 2071",
    "addr:postcode":"2071",
    "iso:country":"AU",
    "sg:address":"PO Box 424",
    "sg:city":"Killara",
    "sg:classifiers":[
        {
            "category":"Social Services",
            "subcategory":"Child Care",
            "type":"Services"
        }
    ],
    "sg:phone":"+61 2 9499 5200",
    "sg:postcode":"2071",
    "sg:province":"NSW",
    "sg:tags":[
        "equipment",
        "supply"
    ],
    "wof:name":"Promo One",
    "wof:placetype":"venue"
},
  "geometry": {"coordinates":[151.15687560999999,-33.7663116455],"type":"Point"}
}