{
  "type": "Feature",
  "properties": {
    "addr:full":"188 Willoughby Rd Crows Nest NSW 2065",
    "addr:housenumber":"188",
    "addr:postcode":"2065",
    "addr:street":"Willoughby Rd",
    "iso:country":"AU",
    "sg:address":"188 Willoughby Rd",
    "sg:city":"Crows Nest",
    "sg:classifiers":[
        {
            "category":"Real Estate",
            "subcategory":"Architect",
            "type":"Services"
        }
    ],
    "sg:phone":"+61 2 9439 6622",
    "sg:postcode":"2065",
    "sg:province":"NSW",
    "wof:name":"Morris Bray Architects Pty Ltd",
    "wof:placetype":"venue"
},
  "geometry": {"coordinates":[151.200775147,-33.8213920593],"type":"Point"}
}