{
  "type": "Feature",
  "properties": {
    "addr:full":"7 Elsum Ave Bayswater VIC 3153",
    "addr:housenumber":"7",
    "addr:postcode":"3153",
    "addr:street":"Elsum Ave",
    "iso:country":"AU",
    "sg:address":"7 Elsum Ave",
    "sg:city":"Bayswater",
    "sg:classifiers":[
        {
            "category":"Manufacturing",
            "subcategory":"Metals",
            "type":"Manufacturing & Wholesale Goods"
        }
    ],
    "sg:phone":"+61 3 9738 1966",
    "sg:postcode":"3153",
    "sg:province":"VIC",
    "sg:tags":[
        "steel",
        "fabricator",
        "mfrs"
    ],
    "wof:name":"Control Fab Pty Ltd",
    "wof:placetype":"venue"
},
  "geometry": {"coordinates":[145.279830933,-37.8241348267],"type":"Point"}
}