{
  "type": "Feature",
  "properties": {
    "addr:full":"4 / 24 William St Raymond Terrace NSW 2324",
    "addr:housenumber":"/ 24",
    "addr:postcode":"2324",
    "addr:street":"William St",
    "iso:country":"AU",
    "sg:address":"4 / 24 William St",
    "sg:city":"Raymond Terrace",
    "sg:classifiers":[
        {
            "category":"Shopping",
            "subcategory":"Clothing, Apparel, & Fashions",
            "type":"Retail Goods"
        }
    ],
    "sg:phone":"+61 2 4987 5634",
    "sg:postcode":"2324",
    "sg:province":"NSW",
    "sg:tags":[
        "boutique"
    ],
    "wof:name":"Bronny & Jules Boutique",
    "wof:placetype":"venue"
},
  "geometry": {"coordinates":[151.743041992,-32.7619590759],"type":"Point"}
}