{
  "type": "Feature",
  "properties": {
    "iso:country":"AU",
    "sg:address":"Level 4, 21 Victoria St",
    "sg:city":"Melbourne",
    "sg:classifiers":[
        {
            "category":"Health Services",
            "subcategory":"Health Practitioner",
            "type":"Services"
        }
    ],
    "sg:phone":"+61 425 795 706",
    "sg:postcode":"3000",
    "sg:province":"VIC",
    "sg:tags":[
        "psychologist"
    ],
    "wof:name":"Watson- Munro Tim",
    "wof:placetype":"venue"
},
  "geometry": {"coordinates":[144.96746826200001,-37.807258606],"type":"Point"}
}