{
  "type": "Feature",
  "properties": {
    "addr:full":"407 Sturt St Ballarat VIC 3350",
    "addr:housenumber":"407",
    "addr:postcode":"3350",
    "addr:street":"Sturt St",
    "iso:country":"AU",
    "sg:address":"407 Sturt St",
    "sg:city":"Ballarat",
    "sg:classifiers":[
        {
            "category":"Real Estate",
            "subcategory":"Real Estate Services",
            "type":"Services"
        }
    ],
    "sg:phone":"+61 3 5334 4441",
    "sg:postcode":"3350",
    "sg:province":"VIC",
    "sg:tags":[
        "valuer"
    ],
    "wof:name":"Ellis Property Group",
    "wof:placetype":"venue"
},
  "geometry": {"coordinates":[143.85434000000001,-37.561852],"type":"Point"}
}