{
  "type": "Feature",
  "properties": {
    "addr:full":"37 Turnham Ave Rosanna VIC 3084",
    "addr:housenumber":"37",
    "addr:postcode":"3084",
    "addr:street":"Turnham Ave",
    "iso:country":"AU",
    "sg:address":"37 Turnham Ave",
    "sg:city":"Rosanna",
    "sg:classifiers":[
        {
            "category":"Arts & Performance",
            "subcategory":"Theater",
            "type":"Entertainment"
        }
    ],
    "sg:phone":"+61 3 9457 4117",
    "sg:postcode":"3084",
    "sg:province":"VIC",
    "sg:tags":[
        "theatre"
    ],
    "wof:name":"Heidelberg Theatre Co",
    "wof:placetype":"venue"
},
  "geometry": {"coordinates":[145.06700134299999,-37.743850708],"type":"Point"}
}