{
  "type": "Feature",
  "properties": {
    "addr:full":"257 Hampshire Rd Sunshine VIC 3020",
    "addr:housenumber":"257",
    "addr:postcode":"3020",
    "addr:street":"Hampshire Rd",
    "iso:country":"AU",
    "sg:address":"257 Hampshire Rd",
    "sg:city":"Sunshine",
    "sg:classifiers":[
        {
            "category":"Shopping",
            "subcategory":"Clothing, Apparel, & Fashions",
            "type":"Retail Goods"
        }
    ],
    "sg:phone":"+61 3 9311 9355",
    "sg:postcode":"3020",
    "sg:province":"VIC",
    "sg:tags":[
        "hire",
        "men's",
        "wear",
        "formal"
    ],
    "wof:name":"Dress Circle",
    "wof:placetype":"venue"
},
  "geometry": {"coordinates":[144.83197000000001,-37.784382],"type":"Point"}
}