{
  "type": "Feature",
  "properties": {
    "addr:full":"Hamilton Rd Lismore VIC 3324",
    "addr:postcode":"3324",
    "addr:street":"Hamilton Rd",
    "iso:country":"AU",
    "sg:address":"Hamilton Rd",
    "sg:city":"Lismore",
    "sg:classifiers":[
        {
            "category":"Autos & Motor Vehicles",
            "subcategory":"Fuel & Gas Station",
            "type":"Retail Goods"
        }
    ],
    "sg:phone":"+61 3 5596 2064",
    "sg:postcode":"3324",
    "sg:province":"VIC",
    "wof:name":"BP Australia Limited",
    "wof:placetype":"venue"
},
  "geometry": {"coordinates":[143.32858300000001,-37.952057],"type":"Point"}
}