{
  "type": "Feature",
  "properties": {
    "iso:country":"AU",
    "sg:address":"182 York St",
    "sg:city":"South Melbourne",
    "sg:classifiers":[
        {
            "category":"Manufacturing",
            "subcategory":"Food",
            "type":"Manufacturing & Wholesale Goods"
        }
    ],
    "sg:phone":"+61 1800 068 444",
    "sg:postcode":"3205",
    "sg:province":"VIC",
    "sg:tags":[
        "function",
        "catering"
    ],
    "sg:website":"http://www.spitroast.com.au",
    "wof:name":"Event Catering & Hire Pty Ltd",
    "wof:placetype":"venue"
},
  "geometry": {"coordinates":[144.95581100000001,-37.831711],"type":"Point"}
}