{
  "type": "Feature",
  "properties": {
    "iso:country":"AU",
    "sg:address":"101 Upper Heidelberg Rd",
    "sg:city":"Ivanhoe",
    "sg:classifiers":[
        {
            "category":"Food & Beverages",
            "subcategory":"Bakery",
            "type":"Retail Goods"
        }
    ],
    "sg:phone":"+61 3 9499 4297",
    "sg:postcode":"3079",
    "sg:province":"VIC",
    "sg:tags":[
        "cake",
        "shop",
        "pastry"
    ],
    "wof:name":"Ivanhoe Cakes",
    "wof:placetype":"venue"
},
  "geometry": {"coordinates":[145.041625977,-37.7692108154],"type":"Point"}
}