{
  "type": "Feature",
  "properties": {
    "addr:full":"89 Garden St Geelong East VIC 3219",
    "addr:housenumber":"89",
    "addr:postcode":"3219",
    "addr:street":"Garden St",
    "iso:country":"AU",
    "sg:address":"89 Garden St",
    "sg:city":"Geelong East",
    "sg:classifiers":[
        {
            "category":"Personal",
            "subcategory":"Beauty Salon",
            "type":"Services"
        }
    ],
    "sg:phone":"+61 3 5221 8319",
    "sg:postcode":"3219",
    "sg:province":"VIC",
    "sg:tags":[
        "hairdresser"
    ],
    "wof:name":"On The Fringe",
    "wof:placetype":"venue"
},
  "geometry": {"coordinates":[144.371261597,-38.1556396484],"type":"Point"}
}