{
  "type": "Feature",
  "properties": {
    "addr:full":"Goldsborough Rd Gordonvale QLD 4865",
    "addr:postcode":"4865",
    "addr:street":"Goldsborough Rd",
    "iso:country":"AU",
    "sg:address":"Goldsborough Rd",
    "sg:city":"Gordonvale",
    "sg:classifiers":[
        {
            "category":"Train Station",
            "subcategory":"Light Rail",
            "type":"Transportation"
        }
    ],
    "sg:phone":"+61 7 4056 2131",
    "sg:postcode":"4865",
    "sg:province":"QLD",
    "sg:tags":[
        "equipment",
        "energy",
        "solar"
    ],
    "wof:name":"Maurie Morrisson Electrical",
    "wof:placetype":"venue"
},
  "geometry": {"coordinates":[145.75405883799999,-17.1468410492],"type":"Point"}
}