{
  "type": "Feature",
  "properties": {
    "addr:full":"8 Dewa St Mission Beach QLD 4852",
    "addr:housenumber":"8",
    "addr:postcode":"4852",
    "addr:street":"Dewa St",
    "iso:country":"AU",
    "sg:address":"8 Dewa St",
    "sg:city":"Mission Beach",
    "sg:classifiers":[
        {
            "category":"Autos & Motor Vehicles",
            "subcategory":"Automobile Sales",
            "type":"Retail Goods"
        }
    ],
    "sg:phone":"+61 7 4068 7800",
    "sg:postcode":"4852",
    "sg:province":"QLD",
    "sg:tags":[
        "equipment",
        "trailer"
    ],
    "wof:name":"Mager Constructions Pty Ltd",
    "wof:placetype":"venue"
},
  "geometry": {"coordinates":[146.09048461899999,-17.8704109192],"type":"Point"}
}