{
  "type": "Feature",
  "properties": {
    "iso:country":"AU",
    "sg:address":"12 Valmadre Crt",
    "sg:city":"Petrie",
    "sg:classifiers":[
        {
            "category":"Personal",
            "subcategory":"Tanning Parlor",
            "type":"Services"
        }
    ],
    "sg:phone":"+61 400 052 710",
    "sg:postcode":"4502",
    "sg:province":"QLD",
    "sg:tags":[
        "solarium"
    ],
    "wof:name":"Tan for all Seasons",
    "wof:placetype":"venue"
},
  "geometry": {"coordinates":[152.96998596200001,-27.2689590454],"type":"Point"}
}