{
  "type": "Feature",
  "properties": {
    "addr:full":"15 Lubbock St Wynn Vale SA 5127",
    "addr:housenumber":"15",
    "addr:postcode":"5127",
    "addr:street":"Lubbock St",
    "iso:country":"AU",
    "sg:address":"15 Lubbock St",
    "sg:city":"Wynn Vale",
    "sg:classifiers":[
        {
            "category":"Professional",
            "type":"Services"
        }
    ],
    "sg:phone":"+61 419 846 272",
    "sg:postcode":"5127",
    "sg:province":"SA",
    "sg:tags":[
        "transport"
    ],
    "wof:name":"Hooklift Transport Pty Ltd",
    "wof:placetype":"venue"
},
  "geometry": {"coordinates":[138.688796997,-34.8026885986],"type":"Point"}
}