{
  "type": "Feature",
  "properties": {
    "iso:country":"AU",
    "sg:address":"Level 3, 120 Harbour Esp",
    "sg:city":"Docklands",
    "sg:classifiers":[
        {
            "category":"Banks & Credit Unions",
            "subcategory":"Financial Services",
            "type":"Services"
        }
    ],
    "sg:phone":"+61 1800 850 509",
    "sg:postcode":"3008",
    "sg:province":"VIC",
    "sg:tags":[
        "finance",
        "factoring"
    ],
    "wof:name":"Oxford Funding",
    "wof:placetype":"venue"
},
  "geometry": {"coordinates":[144.946868897,-37.8188552856],"type":"Point"}
}