{
  "type": "Feature",
  "properties": {
    "addr:full":"245 Raglan St Mosman NSW 2088",
    "addr:housenumber":"245",
    "addr:postcode":"2088",
    "addr:street":"Raglan St",
    "iso:country":"AU",
    "sg:address":"245 Raglan St",
    "sg:city":"Mosman",
    "sg:classifiers":[
        {
            "category":"Professional",
            "subcategory":"Art Services",
            "type":"Services"
        }
    ],
    "sg:phone":"+61 2 9960 1964",
    "sg:postcode":"2088",
    "sg:province":"NSW",
    "sg:tags":[
        "decorator",
        "painter"
    ],
    "wof:name":"Valenti P & J",
    "wof:placetype":"venue"
},
  "geometry": {"coordinates":[151.25054931599999,-33.8272743225],"type":"Point"}
}