{
  "type": "Feature",
  "properties": {
    "addr:full":"1 / 1 The Esplanade Torquay VIC 3228",
    "addr:housenumber":"/ 1",
    "addr:postcode":"3228",
    "addr:street":"The Esplanade",
    "iso:country":"AU",
    "sg:address":"1",
    "sg:city":"/ 1 The Esplanade Torquay",
    "sg:classifiers":[
        {
            "category":"Professional",
            "subcategory":"Art Services",
            "type":"Services"
        }
    ],
    "sg:phone":"+61 3 5261 9146",
    "sg:postcode":"3228",
    "sg:province":"VIC",
    "sg:tags":[
        "artist"
    ],
    "wof:name":"Robert Mainland - Fine Artist",
    "wof:placetype":"venue"
},
  "geometry": {"coordinates":[144.32461499999999,-38.339157],"type":"Point"}
}