{
  "type": "Feature",
  "properties": {
    "iso:country":"AU",
    "sg:address":"18 Boonah St",
    "sg:city":"Griffith",
    "sg:classifiers":[
        {
            "category":"Utilities",
            "subcategory":"Electric",
            "type":"Services"
        }
    ],
    "sg:phone":"+61 2 6962 3022",
    "sg:postcode":"2680",
    "sg:province":"NSW",
    "sg:tags":[
        "electrical",
        "contractor"
    ],
    "wof:name":"Rosenboom Electrical Pty Ltd",
    "wof:placetype":"venue"
},
  "geometry": {"coordinates":[146.048935,-34.279335],"type":"Point"}
}