{
  "type": "Feature",
  "properties": {
    "iso:country":"AU",
    "sg:address":"4 Ashworth Dr",
    "sg:city":"Traralgon",
    "sg:classifiers":[
        {
            "category":"Food & Beverages",
            "subcategory":"Specialty",
            "type":"Retail Goods"
        }
    ],
    "sg:phone":"+61 414 882 390",
    "sg:postcode":"3844",
    "sg:province":"VIC",
    "sg:tags":[
        "product",
        "health"
    ],
    "wof:name":"Juice Plus",
    "wof:placetype":"venue"
},
  "geometry": {"coordinates":[146.50904846200001,-38.1805839539],"type":"Point"}
}