{
  "type": "Feature",
  "properties": {
    "addr:full":"43 Caronia Ave Cronulla NSW 2230",
    "addr:housenumber":"43",
    "addr:postcode":"2230",
    "addr:street":"Caronia Ave",
    "iso:country":"AU",
    "sg:address":"43 Caronia Ave",
    "sg:city":"Cronulla",
    "sg:classifiers":[
        {
            "category":"Building & Trades",
            "subcategory":"Cleaning & Sanitation",
            "type":"Services"
        }
    ],
    "sg:phone":"+61 2 9523 5227",
    "sg:postcode":"2230",
    "sg:province":"NSW",
    "sg:tags":[
        "window"
    ],
    "wof:name":"Clarity Window Cleaners",
    "wof:placetype":"venue"
},
  "geometry": {"coordinates":[151.14390564000001,-34.0501708984],"type":"Point"}
}