{
  "type": "Feature",
  "properties": {
    "addr:full":"899 Brooker Ave Berriedale TAS 7011",
    "addr:housenumber":"899",
    "addr:postcode":"7011",
    "addr:street":"Brooker Ave",
    "iso:country":"AU",
    "sg:address":"899 Brooker Ave",
    "sg:city":"Berriedale",
    "sg:classifiers":[
        {
            "category":"Health Services",
            "subcategory":"Nursing And Care Facility",
            "type":"Services"
        }
    ],
    "sg:phone":"+61 3 6208 3208",
    "sg:postcode":"7011",
    "sg:province":"TAS",
    "sg:tags":[
        "home"
    ],
    "wof:name":"Uniting Aged Care Southern Tasmania",
    "wof:placetype":"venue"
},
  "geometry": {"coordinates":[147.258865356,-42.8170013428],"type":"Point"}
}