{
  "type": "Feature",
  "properties": {
    "addr:full":"1 Ellsa St Balwyn North VIC 3104",
    "addr:housenumber":"1",
    "addr:postcode":"3104",
    "addr:street":"Ellsa St",
    "iso:country":"AU",
    "sg:address":"1 Ellsa St",
    "sg:city":"Balwyn North",
    "sg:classifiers":[
        {
            "category":"Health Services",
            "subcategory":"Doctor",
            "type":"Services"
        }
    ],
    "sg:phone":"+61 3 9857 8227",
    "sg:postcode":"3104",
    "sg:province":"VIC",
    "sg:tags":[
        "medical",
        "practitioner"
    ],
    "wof:name":"Jarman Frederick (Rick)",
    "wof:placetype":"venue"
},
  "geometry": {"coordinates":[145.09706115700001,-37.7909965515],"type":"Point"}
}