{
  "type": "Feature",
  "properties": {
    "iso:country":"AU",
    "sg:address":"4 Antarers Ave",
    "sg:city":"Kingston",
    "sg:classifiers":[
        {
            "category":"Real Estate",
            "subcategory":"Real Estate Agent",
            "type":"Services"
        }
    ],
    "sg:phone":"+61 7 3808 7680",
    "sg:postcode":"4114",
    "sg:province":"QLD",
    "wof:name":"Ian MacDonald Realty",
    "wof:placetype":"venue"
},
  "geometry": {"coordinates":[153.10440063499999,-27.6593112946],"type":"Point"}
}