{
  "type": "Feature",
  "properties": {
    "addr:full":"251 Wickam Rd Moorabbin VIC 3189",
    "addr:housenumber":"251",
    "addr:postcode":"3189",
    "addr:street":"Wickam Rd",
    "iso:country":"AU",
    "sg:address":"251 Wickam Rd",
    "sg:city":"Moorabbin",
    "sg:classifiers":[
        {
            "category":"Building & Trades",
            "subcategory":"Construction",
            "type":"Services"
        }
    ],
    "sg:phone":"+61 13 63 60",
    "sg:postcode":"3189",
    "sg:province":"VIC",
    "sg:tags":[
        "window",
        "tinting"
    ],
    "wof:name":"Tint A Car",
    "wof:placetype":"venue"
},
  "geometry": {"coordinates":[145.05337524399999,-37.9463424683],"type":"Point"}
}