{
  "type": "Feature",
  "properties": {
    "addr:full":"Level 1,696 High St Rd Glen Waverley VIC 3150",
    "addr:postcode":"3150",
    "addr:street":"High St Rd",
    "iso:country":"AU",
    "sg:address":"Level 1,696 High St Rd",
    "sg:city":"Glen Waverley",
    "sg:classifiers":[
        {
            "category":"Professional",
            "subcategory":"Secretarial Services",
            "type":"Services"
        }
    ],
    "sg:phone":"+61 3 9886 5564",
    "sg:postcode":"3150",
    "sg:province":"VIC",
    "sg:tags":[
        "typing"
    ],
    "wof:name":"MaddingCrowd Publishing",
    "wof:placetype":"venue"
},
  "geometry": {"coordinates":[145.15916442899999,-37.8735694885],"type":"Point"}
}