{
  "type": "Feature",
  "properties": {
    "iso:country":"AU",
    "sg:address":"5 Ross St",
    "sg:city":"Ebbw Vale",
    "sg:classifiers":[
        {
            "category":"Social Services",
            "type":"Services"
        }
    ],
    "sg:phone":"+61 416 184 141",
    "sg:postcode":"4304",
    "sg:province":"QLD",
    "sg:tags":[
        "worker"
    ],
    "wof:name":"Carolyn Perry",
    "wof:placetype":"venue"
},
  "geometry": {"coordinates":[152.82118225100001,-27.6069412231],"type":"Point"}
}