{
  "type": "Feature",
  "properties": {
    "addr:full":"17 Whitehill Ave Sunshine North VIC 3020",
    "addr:housenumber":"17",
    "addr:postcode":"3020",
    "addr:street":"Whitehill Ave",
    "iso:country":"AU",
    "sg:address":"17 Whitehill Ave",
    "sg:city":"Sunshine North",
    "sg:classifiers":[
        {
            "category":"Retail",
            "subcategory":"Repair Shop",
            "type":"Services"
        }
    ],
    "sg:phone":"+61 3 9364 5182",
    "sg:postcode":"3020",
    "sg:province":"VIC",
    "sg:tags":[
        "upholsterer"
    ],
    "wof:name":"Cassandra Upholstery",
    "wof:placetype":"venue"
},
  "geometry": {"coordinates":[144.835297,-37.754704],"type":"Point"}
}