{
  "type": "Feature",
  "properties": {
    "addr:full":"PO Box 3377 Mildura VIC 3502",
    "addr:postcode":"3502",
    "iso:country":"AU",
    "sg:address":"PO Box 3377",
    "sg:city":"Mildura",
    "sg:classifiers":[
        {
            "category":"Government",
            "subcategory":"Customs House",
            "type":"Public Place"
        }
    ],
    "sg:phone":"+61 3 5021 3421",
    "sg:postcode":"3502",
    "sg:province":"VIC",
    "sg:tags":[
        "title",
        "management",
        "stratum"
    ],
    "wof:name":"Ace Body Corporate Management (Mildura)",
    "wof:placetype":"venue"
},
  "geometry": {"coordinates":[142.165557861,-34.184551239],"type":"Point"}
}