{
  "type": "Feature",
  "properties": {
    "iso:country":"AU",
    "sg:address":"PO Box 347",
    "sg:city":"Coffs Harbour",
    "sg:classifiers":[
        {
            "category":"Building & Trades",
            "subcategory":"Construction",
            "type":"Services"
        }
    ],
    "sg:phone":"+61 2 6658 4485",
    "sg:postcode":"2450",
    "sg:province":"NSW",
    "sg:tags":[
        "window",
        "tinting"
    ],
    "wof:name":"Coastline Window Tinting",
    "wof:placetype":"venue"
},
  "geometry": {"coordinates":[153.115158081,-30.2970104218],"type":"Point"}
}