{
  "type": "Feature",
  "properties": {
    "iso:country":"AU",
    "sg:address":"26 Angove St",
    "sg:city":"North Perth",
    "sg:classifiers":[
        {
            "category":"Shopping",
            "subcategory":"Crafts & Fabrics",
            "type":"Retail Goods"
        }
    ],
    "sg:phone":"+61 8 9227 0414",
    "sg:postcode":"6006",
    "sg:province":"WA",
    "sg:tags":[
        "supply"
    ],
    "wof:name":"Elleny Beads",
    "wof:placetype":"venue"
},
  "geometry": {"coordinates":[115.85862731900001,-31.930305481],"type":"Point"}
}