{
  "type": "Feature",
  "properties": {
    "addr:full":"Kennedy Hwy Tolga QLD 4882",
    "addr:postcode":"4882",
    "addr:street":"Kennedy Hwy",
    "iso:country":"AU",
    "sg:address":"Kennedy Hwy",
    "sg:city":"Tolga",
    "sg:classifiers":[
        {
            "category":"Autos & Motor Vehicles",
            "subcategory":"Fuel & Gas Station",
            "type":"Retail Goods"
        }
    ],
    "sg:phone":"+61 7 4095 4297",
    "sg:postcode":"4882",
    "sg:province":"QLD",
    "wof:name":"Daleys Garage",
    "wof:placetype":"venue"
},
  "geometry": {"coordinates":[145.466873169,-17.1869392395],"type":"Point"}
}