{
  "type": "Feature",
  "properties": {
    "iso:country":"AU",
    "sg:address":"167 Cedar Rd",
    "sg:city":"Redbank Plains",
    "sg:classifiers":[
        {
            "category":"Mining & Drilling",
            "type":"Manufacturing & Wholesale Goods"
        }
    ],
    "sg:phone":"+61 7 3814 3945",
    "sg:postcode":"4301",
    "sg:province":"QLD",
    "sg:tags":[
        "boring",
        "contractor"
    ],
    "wof:name":"Kruger Earthmoving Pty Ltd",
    "wof:placetype":"venue"
},
  "geometry": {"coordinates":[152.86264038100001,-27.6385631561],"type":"Point"}
}