{
  "type": "Feature",
  "properties": {
    "addr:full":"Wombat Rd Young NSW 2594",
    "addr:postcode":"2594",
    "addr:street":"Wombat Rd",
    "iso:country":"AU",
    "sg:address":"Wombat Rd",
    "sg:city":"Young",
    "sg:classifiers":[
        {
            "category":"Building & Trades",
            "subcategory":"Construction",
            "type":"Services"
        }
    ],
    "sg:phone":"+61 428 620 323",
    "sg:postcode":"2594",
    "sg:province":"NSW",
    "sg:tags":[
        "earth",
        "excavating",
        "moving",
        "contractor"
    ],
    "wof:name":"Bobcat & Grader Hire",
    "wof:placetype":"venue"
},
  "geometry": {"coordinates":[148.296585083,-34.3166351318],"type":"Point"}
}