{
  "type": "Feature",
  "properties": {
    "addr:full":"581 Samford Rd Mitchelton QLD 4053",
    "addr:housenumber":"581",
    "addr:postcode":"4053",
    "addr:street":"Samford Rd",
    "iso:country":"AU",
    "sg:address":"581 Samford Rd",
    "sg:city":"Mitchelton",
    "sg:classifiers":[
        {
            "category":"Professional",
            "subcategory":"Computer Services",
            "type":"Services"
        }
    ],
    "sg:phone":"+61 1300 135 248",
    "sg:postcode":"4053",
    "sg:province":"QLD",
    "sg:tags":[
        "equipment",
        "networking",
        "installation"
    ],
    "wof:name":"First Integrated Solutions",
    "wof:placetype":"venue"
},
  "geometry": {"coordinates":[152.976318359,-27.4144649506],"type":"Point"}
}