{
  "type": "Feature",
  "properties": {
    "addr:full":"112 Prospect Rd Prospect SA 5082",
    "addr:housenumber":"112",
    "addr:postcode":"5082",
    "addr:street":"Prospect Rd",
    "iso:country":"AU",
    "sg:address":"112 Prospect Rd",
    "sg:city":"Prospect",
    "sg:classifiers":[
        {
            "category":"Health Services",
            "subcategory":"Health Practitioner",
            "type":"Services"
        }
    ],
    "sg:phone":"+61 8 8342 4109",
    "sg:postcode":"5082",
    "sg:province":"SA",
    "sg:tags":[
        "alternative"
    ],
    "wof:name":"Trager",
    "wof:placetype":"venue"
},
  "geometry": {"coordinates":[138.59388732900001,-34.8874740601],"type":"Point"}
}