{
  "type": "Feature",
  "properties": {
    "iso:country":"AU",
    "sg:address":"937 Waugh Rd",
    "sg:city":"Albury North",
    "sg:classifiers":[
        {
            "category":"Professional",
            "subcategory":"Employment Agencies",
            "type":"Services"
        }
    ],
    "sg:phone":"+61 2 6040 1282",
    "sg:postcode":"2640",
    "sg:province":"NSW",
    "sg:tags":[
        "hire",
        "labour",
        "contractor"
    ],
    "wof:name":"W.V. Management Pty Ltd",
    "wof:placetype":"venue"
},
  "geometry": {"coordinates":[146.92692565900001,-36.0575218201],"type":"Point"}
}