{
  "type": "Feature",
  "properties": {
    "addr:full":"Suite 1, 12 Jenkinson St Indooroopilly QLD 4068",
    "addr:housenumber":"12",
    "addr:postcode":"4068",
    "addr:street":"Jenkinson St",
    "iso:country":"AU",
    "sg:address":"Suite 1, 12 Jenkinson St",
    "sg:city":"Indooroopilly",
    "sg:classifiers":[
        {
            "category":"Real Estate",
            "subcategory":"Surveying",
            "type":"Services"
        }
    ],
    "sg:phone":"+61 7 3378 9744",
    "sg:postcode":"4068",
    "sg:province":"QLD",
    "sg:tags":[
        "surveyor",
        "quantity"
    ],
    "wof:name":"A P D Partnership",
    "wof:placetype":"venue"
},
  "geometry": {"coordinates":[152.96134948700001,-27.4968032837],"type":"Point"}
}