{
  "type": "Feature",
  "properties": {
    "iso:country":"AU",
    "sg:address":"700 Albany Creek Rd",
    "sg:city":"Albany Creek",
    "sg:classifiers":[
        {
            "category":"Shopping",
            "subcategory":"Jewelry",
            "type":"Retail Goods"
        }
    ],
    "sg:phone":"+61 7 3264 6088",
    "sg:postcode":"4035",
    "sg:province":"QLD",
    "sg:tags":[
        "jeweller"
    ],
    "wof:name":"Goddard Jewellers",
    "wof:placetype":"venue"
},
  "geometry": {"coordinates":[152.96582000000001,-27.345341],"type":"Point"}
}