{
  "type": "Feature",
  "properties": {
    "addr:full":"1 Barrpowell Rd Welland SA 5007",
    "addr:housenumber":"1",
    "addr:postcode":"5007",
    "addr:street":"Barrpowell Rd",
    "iso:country":"AU",
    "sg:address":"1 Barrpowell Rd",
    "sg:city":"Welland",
    "sg:classifiers":[
        {
            "category":"Farming",
            "subcategory":"Fish & Marine Products",
            "type":"Manufacturing & Wholesale Goods"
        }
    ],
    "sg:phone":"+61 8 8241 5733",
    "sg:postcode":"5007",
    "sg:province":"SA",
    "sg:tags":[
        "organic"
    ],
    "wof:name":"Wet Planet Beverages",
    "wof:placetype":"venue"
},
  "geometry": {"coordinates":[138.56080627399999,-34.9102058411],"type":"Point"}
}