{
  "type": "Feature",
  "properties": {
    "iso:country":"AU",
    "sg:address":"90 Spencer St",
    "sg:city":"Bunbury",
    "sg:classifiers":[
        {
            "category":"Travel",
            "subcategory":"Travel Agent",
            "type":"Entertainment"
        }
    ],
    "sg:phone":"+61 8 9721 5855",
    "sg:postcode":"6230",
    "sg:province":"WA",
    "sg:tags":[
        "consultant"
    ],
    "wof:name":"Jetset",
    "wof:placetype":"venue"
},
  "geometry": {"coordinates":[115.641579,-33.346626],"type":"Point"}
}