{
  "type": "Feature",
  "properties": {
    "addr:full":"3/ 3 Gibson Rd Noosaville QLD 4566",
    "addr:housenumber":"/ 3",
    "addr:postcode":"4566",
    "addr:street":"Gibson Rd",
    "iso:country":"AU",
    "sg:address":"3/ 3 Gibson Rd",
    "sg:city":"Noosaville",
    "sg:classifiers":[
        {
            "category":"Shopping",
            "subcategory":"Computers & Home Electronics",
            "type":"Retail Goods"
        }
    ],
    "sg:phone":"+61 7 5455 6300",
    "sg:postcode":"4566",
    "sg:province":"QLD",
    "sg:tags":[
        "hi-fi",
        "equipment"
    ],
    "wof:name":"fi# Audio Video Pty Limited",
    "wof:placetype":"venue"
},
  "geometry": {"coordinates":[153.05685424800001,-26.4013805389],"type":"Point"}
}