{
  "type": "Feature",
  "properties": {
    "addr:full":"112 Nicholson Pde Cronulla NSW 2230",
    "addr:housenumber":"112",
    "addr:postcode":"2230",
    "addr:street":"Nicholson Pde",
    "iso:country":"AU",
    "sg:address":"112 Nicholson Pde",
    "sg:city":"Cronulla",
    "sg:classifiers":[
        {
            "category":"Social Services",
            "subcategory":"Child Care",
            "type":"Services"
        }
    ],
    "sg:phone":"+61 2 9501 5755",
    "sg:postcode":"2230",
    "sg:province":"NSW",
    "wof:name":"Lullaby Baby Cottage",
    "wof:placetype":"venue"
},
  "geometry": {"coordinates":[151.149047852,-34.0655174255],"type":"Point"}
}