{
  "type": "Feature",
  "properties": {
    "iso:country":"AU",
    "sg:address":"Suite 60/Level 2 2 O'Connell St",
    "sg:city":"Parramatta",
    "sg:classifiers":[
        {
            "category":"Professional",
            "subcategory":"Accounting & Tax Preparation",
            "type":"Services"
        }
    ],
    "sg:phone":"+61 2 9891 3211",
    "sg:postcode":"2150",
    "sg:province":"NSW",
    "sg:tags":[
        "accountant",
        "auditor"
    ],
    "wof:name":"McCartin & Associates Public Accountants",
    "wof:placetype":"venue"
},
  "geometry": {"coordinates":[151.088256836,-34.0042228699],"type":"Point"}
}