{
  "type": "Feature",
  "properties": {
    "addr:full":"77 Burwood Hwy Burwood VIC 3125",
    "addr:housenumber":"77",
    "addr:postcode":"3125",
    "addr:street":"Burwood Hwy",
    "iso:country":"AU",
    "sg:address":"77 Burwood Hwy",
    "sg:city":"Burwood",
    "sg:classifiers":[
        {
            "category":"Wholesale",
            "subcategory":"Furniture",
            "type":"Manufacturing & Wholesale Goods"
        }
    ],
    "sg:phone":"+61 3 9808 8042",
    "sg:postcode":"3125",
    "sg:province":"VIC",
    "sg:tags":[
        "wholesaler",
        "mfrs"
    ],
    "wof:name":"Pylo Steel Furniture",
    "wof:placetype":"venue"
},
  "geometry": {"coordinates":[145.09902954099999,-37.8505554199],"type":"Point"}
}