{
  "type": "Feature",
  "properties": {
    "addr:full":"Unit 2-3/ 12 Watsford Rd Campbelltown NSW 2560",
    "addr:housenumber":"/ 12",
    "addr:postcode":"2560",
    "addr:street":"Watsford Rd",
    "iso:country":"AU",
    "sg:address":"Unit 2-3/ 12 Watsford Rd",
    "sg:city":"Campbelltown",
    "sg:classifiers":[
        {
            "category":"Communications",
            "subcategory":"Film & Video Production",
            "type":"Services"
        }
    ],
    "sg:phone":"+61 2 4620 4011",
    "sg:postcode":"2560",
    "sg:province":"NSW",
    "sg:tags":[
        "trestle",
        "ladders",
        "steps",
        "accessory"
    ],
    "wof:name":"Ladder Solutions Pty Ltd",
    "wof:placetype":"venue"
},
  "geometry": {"coordinates":[150.81979370100001,-34.0592308044],"type":"Point"}
}