{
  "type": "Feature",
  "properties": {
    "addr:full":"PO Box 1724 Southport Business Centre QLD 4215",
    "addr:postcode":"4215",
    "iso:country":"AU",
    "sg:address":"PO Box 1724",
    "sg:city":"Southport Business Centre",
    "sg:classifiers":[
        {
            "category":"Home & Garden",
            "subcategory":"Building Materials",
            "type":"Retail Goods"
        }
    ],
    "sg:phone":"+61 7 5537 6499",
    "sg:postcode":"4215",
    "sg:province":"QLD",
    "sg:tags":[
        "lawn",
        "cutting",
        "maintenance"
    ],
    "wof:name":"DAB Hand Property Services",
    "wof:placetype":"venue"
},
  "geometry": {"coordinates":[153.39855957,-27.9664897919],"type":"Point"}
}