{
  "type": "Feature",
  "properties": {
    "addr:full":"1485 Centre Rd Clayton VIC 3168",
    "addr:housenumber":"1485",
    "addr:postcode":"3168",
    "addr:street":"Centre Rd",
    "iso:country":"AU",
    "sg:address":"1485 Centre Rd",
    "sg:city":"Clayton",
    "sg:classifiers":[
        {
            "category":"Fast Food",
            "type":"Food & Drink"
        }
    ],
    "sg:phone":"+61 3 9545 6733",
    "sg:postcode":"3168",
    "sg:province":"VIC",
    "sg:tags":[
        "away",
        "take"
    ],
    "wof:name":"Big Boys Pizza, Pasta And Ribs",
    "wof:placetype":"venue"
},
  "geometry": {"coordinates":[145.129730225,-37.9297065735],"type":"Point"}
}