{
  "type": "Feature",
  "properties": {
    "iso:country":"AU",
    "sg:address":"40 Woodlark St",
    "sg:city":"Lismore",
    "sg:classifiers":[
        {
            "category":"Personal",
            "subcategory":"Barber",
            "type":"Services"
        }
    ],
    "sg:phone":"+61 434 122 340",
    "sg:postcode":"2480",
    "sg:province":"NSW",
    "wof:name":"The Badgers Bristle",
    "wof:placetype":"venue"
},
  "geometry": {"coordinates":[153.278106689,-28.8069534302],"type":"Point"}
}