{
  "type": "Feature",
  "properties": {
    "addr:full":"5 309 Young St Wayville SA 5034",
    "addr:housenumber":"5 309",
    "addr:postcode":"5034",
    "addr:street":"Young St",
    "iso:country":"AU",
    "sg:address":"5 309 Young St",
    "sg:city":"Wayville",
    "sg:classifiers":[
        {
            "category":"Professional",
            "subcategory":"Computer Services",
            "type":"Services"
        }
    ],
    "sg:phone":"+61 412 384 320",
    "sg:postcode":"5034",
    "sg:province":"SA",
    "sg:tags":[
        "package",
        "software"
    ],
    "wof:name":"Hardlight Interactive",
    "wof:placetype":"venue"
},
  "geometry": {"coordinates":[138.59197998100001,-34.9454841614],"type":"Point"}
}