{
  "type": "Feature",
  "properties": {
    "addr:full":"7 Kalmia Rd Bibra Lake WA 6163",
    "addr:housenumber":"7",
    "addr:postcode":"6163",
    "addr:street":"Kalmia Rd",
    "iso:country":"AU",
    "sg:address":"7 Kalmia Rd",
    "sg:city":"Bibra Lake",
    "sg:phone":"+61 8 9434 1707",
    "sg:postcode":"6163",
    "sg:province":"WA",
    "wof:name":"GRP Technology Pty. Ltd.",
    "wof:placetype":"venue"
},
  "geometry": {"coordinates":[115.81459,-32.112225],"type":"Point"}
}