{
  "type": "Feature",
  "properties": {
    "addr:full":"88 Mortimer St Mudgee NSW 2850",
    "addr:housenumber":"88",
    "addr:postcode":"2850",
    "addr:street":"Mortimer St",
    "iso:country":"AU",
    "sg:address":"88 Mortimer St",
    "sg:city":"Mudgee",
    "sg:classifiers":[
        {
            "category":"Food & Beverages",
            "subcategory":"Liquor & Beverages",
            "type":"Retail Goods"
        }
    ],
    "sg:phone":"+61 2 6372 4334",
    "sg:postcode":"2850",
    "sg:province":"NSW",
    "sg:tags":[
        "store"
    ],
    "wof:name":"Macs Liquor",
    "wof:placetype":"venue"
},
  "geometry": {"coordinates":[149.58694499999999,-32.592785],"type":"Point"}
}