{
  "type": "Feature",
  "properties": {
    "iso:country":"AU",
    "sg:address":"23 Preston Rd",
    "sg:city":"Old Toongabbie",
    "sg:classifiers":[
        {
            "category":"Home & Garden",
            "subcategory":"Kitchen Supply",
            "type":"Retail Goods"
        }
    ],
    "sg:phone":"+61 414 768 584",
    "sg:postcode":"2146",
    "sg:province":"NSW",
    "sg:tags":[
        "sharpening"
    ],
    "wof:name":"Terry The Knife Guy",
    "wof:placetype":"venue"
},
  "geometry": {"coordinates":[150.96771240199999,-33.7942962646],"type":"Point"}
}