{
  "type": "Feature",
  "properties": {
    "iso:country":"AU",
    "sg:address":"95 Hume Hwy",
    "sg:city":"Mittagong",
    "sg:classifiers":[
        {
            "category":"Restaurant",
            "type":"Food & Drink"
        }
    ],
    "sg:phone":"+61 2 4872 1677",
    "sg:postcode":"2575",
    "sg:province":"NSW",
    "wof:name":"Blue Cockerel Restaurant The",
    "wof:placetype":"venue"
},
  "geometry": {"coordinates":[150.447540283,-34.4326248169],"type":"Point"}
}