{
  "type": "Feature",
  "properties": {
    "iso:country":"AU",
    "sg:address":"1/ 3",
    "sg:city":"Bon Mace Cl Berkeley Vale",
    "sg:classifiers":[
        {
            "category":"Retail",
            "subcategory":"Auto Repair",
            "type":"Services"
        }
    ],
    "sg:phone":"+61 2 4388 6665",
    "sg:postcode":"2261",
    "sg:province":"NSW",
    "sg:tags":[
        "electrical"
    ],
    "wof:name":"Mobile Auto Air",
    "wof:placetype":"venue"
},
  "geometry": {"coordinates":[151.43858299999999,-33.344639],"type":"Point"}
}