{
  "type": "Feature",
  "properties": {
    "addr:full":"Lot 69 Sonning Loop Yallingup WA 6282",
    "addr:postcode":"6282",
    "iso:country":"AU",
    "sg:address":"Lot 69 Sonning Loop",
    "sg:city":"Yallingup",
    "sg:classifiers":[
        {
            "category":"Retail",
            "subcategory":"Repair Shop",
            "type":"Services"
        }
    ],
    "sg:phone":"+61 8 9755 2555",
    "sg:postcode":"6282",
    "sg:province":"WA",
    "sg:tags":[
        "machine",
        "repairs",
        "part",
        "dryer",
        "washing"
    ],
    "wof:name":"Dunsborough Washer & Dryer",
    "wof:placetype":"venue"
},
  "geometry": {"coordinates":[115.06842804,-33.6537475586],"type":"Point"}
}