{
  "type": "Feature",
  "properties": {
    "addr:full":"8 Premier Ave Mitcham VIC 3132",
    "addr:housenumber":"8",
    "addr:postcode":"3132",
    "addr:street":"Premier Ave",
    "iso:country":"AU",
    "sg:address":"8 Premier Ave",
    "sg:city":"Mitcham",
    "sg:classifiers":[
        {
            "category":"Social Services",
            "subcategory":"Retirement Home",
            "type":"Services"
        }
    ],
    "sg:phone":"+61 3 9879 2999",
    "sg:postcode":"3132",
    "sg:province":"VIC",
    "sg:tags":[
        "environmental",
        "consultant",
        "pollution"
    ],
    "wof:name":"Petrotest",
    "wof:placetype":"venue"
},
  "geometry": {"coordinates":[145.196166992,-37.83070755],"type":"Point"}
}