{
  "type": "Feature",
  "properties": {
    "addr:full":"37 Wheeler Rd Hamilton Hill WA 6163",
    "addr:housenumber":"37",
    "addr:postcode":"6163",
    "addr:street":"Wheeler Rd",
    "iso:country":"AU",
    "sg:address":"37 Wheeler Rd",
    "sg:city":"Hamilton Hill",
    "sg:classifiers":[
        {
            "category":"Professional",
            "subcategory":"Art Services",
            "type":"Services"
        }
    ],
    "sg:phone":"+61 8 9314 7323",
    "sg:postcode":"6163",
    "sg:province":"WA",
    "sg:tags":[
        "graphic",
        "designer"
    ],
    "wof:name":"Flaming Ideas",
    "wof:placetype":"venue"
},
  "geometry": {"coordinates":[115.78299699999999,-32.083061],"type":"Point"}
}