{
  "type": "Feature",
  "properties": {
    "addr:full":"80 Research Road, Pooraka SA 5095",
    "addr:housenumber":"80",
    "addr:postcode":"5095",
    "addr:street":"Research Road",
    "iso:country":"AU",
    "sg:address":"80 Research Road,",
    "sg:city":"Pooraka",
    "sg:classifiers":[
        {
            "category":"Building & Trades",
            "subcategory":"Construction",
            "type":"Services"
        }
    ],
    "sg:phone":"+61 8 8260 6000",
    "sg:postcode":"5095",
    "sg:province":"SA",
    "sg:tags":[
        "fencing",
        "contractor"
    ],
    "wof:name":"Pooraka Fencing Supplies",
    "wof:placetype":"venue"
},
  "geometry": {"coordinates":[138.63331604000001,-34.8153114319],"type":"Point"}
}