{
  "type": "Feature",
  "properties": {
    "addr:full":"11 Gertrude St Templestowe Lower VIC 3107",
    "addr:housenumber":"11",
    "addr:postcode":"3107",
    "addr:street":"Gertrude St",
    "iso:country":"AU",
    "sg:address":"11 Gertrude St",
    "sg:city":"Templestowe Lower",
    "sg:classifiers":[
        {
            "category":"Shopping",
            "subcategory":"Bridal",
            "type":"Retail Goods"
        }
    ],
    "sg:phone":"+61 3 9850 5661",
    "sg:postcode":"3107",
    "sg:province":"VIC",
    "sg:tags":[
        "hire",
        "wear"
    ],
    "wof:name":"Beau Ties",
    "wof:placetype":"venue"
},
  "geometry": {"coordinates":[145.102020264,-37.7646408081],"type":"Point"}
}