{
  "type": "Feature",
  "properties": {
    "addr:full":"Shop 46 Heart Of Victoria Park Shopng Cntr Victoria Park WA 6100",
    "addr:housenumber":"shop 46",
    "addr:postcode":"6100",
    "addr:street":"Heart",
    "iso:country":"AU",
    "sg:address":"Shop 46 Heart Of Victoria Park Shopng Cntr",
    "sg:city":"Victoria Park",
    "sg:classifiers":[
        {
            "category":"Fast Food",
            "type":"Food & Drink"
        }
    ],
    "sg:phone":"+61 8 9362 4341",
    "sg:postcode":"6100",
    "sg:province":"WA",
    "sg:tags":[
        "away",
        "take"
    ],
    "wof:name":"Tom Munchener Fast Food",
    "wof:placetype":"venue"
},
  "geometry": {"coordinates":[115.898368835,-31.9767799377],"type":"Point"}
}