{
  "type": "Feature",
  "properties": {
    "iso:country":"AU",
    "sg:address":"17 McIntosh St",
    "sg:city":"Gordon",
    "sg:classifiers":[
        {
            "category":"Communications",
            "subcategory":"News Services",
            "type":"Services"
        }
    ],
    "sg:phone":"+61 2 9498 2271",
    "sg:postcode":"2072",
    "sg:province":"NSW",
    "sg:tags":[
        "information",
        "tourist",
        "attractions"
    ],
    "wof:name":"Eryldene",
    "wof:placetype":"venue"
},
  "geometry": {"coordinates":[151.15769958499999,-33.7575683594],"type":"Point"}
}