{
  "type": "Feature",
  "properties": {
    "iso:country":"AU",
    "sg:address":"Chip Mill Rd",
    "sg:city":"Triabunna",
    "sg:classifiers":[
        {
            "category":"Utilities",
            "subcategory":"Fuel Oil & Lpg",
            "type":"Services"
        }
    ],
    "sg:phone":"+61 3 6257 3168",
    "sg:postcode":"7190",
    "sg:province":"TAS",
    "sg:tags":[
        "heating"
    ],
    "wof:name":"Bennetts Petroleum Supplies Pty Ltd",
    "wof:placetype":"venue"
},
  "geometry": {"coordinates":[147.912125,-42.502048],"type":"Point"}
}