{
  "type": "Feature",
  "properties": {
    "addr:full":"97 George St Launceston TAS 7250",
    "addr:housenumber":"97",
    "addr:postcode":"7250",
    "addr:street":"George St",
    "iso:country":"AU",
    "sg:address":"97 George St",
    "sg:city":"Launceston",
    "sg:classifiers":[
        {
            "category":"Recreation",
            "subcategory":"Fishing",
            "type":"Entertainment"
        }
    ],
    "sg:phone":"+61 3 6331 7090",
    "sg:postcode":"7250",
    "sg:province":"TAS",
    "sg:tags":[
        "tackle"
    ],
    "wof:name":"Sports Hut",
    "wof:placetype":"venue"
},
  "geometry": {"coordinates":[147.14105224599999,-41.4367332458],"type":"Point"}
}