{
  "type": "Feature",
  "properties": {
    "iso:country":"AU",
    "sg:address":"41 Scantlebury Crs",
    "sg:city":"Theodore",
    "sg:classifiers":[
        {
            "category":"Professional",
            "subcategory":"Accounting & Tax Preparation",
            "type":"Services"
        }
    ],
    "sg:phone":"+61 2 6292 2173",
    "sg:postcode":"2905",
    "sg:province":"ACT",
    "sg:tags":[
        "bookkeeping"
    ],
    "wof:name":"Paula Lee-Wicks",
    "wof:placetype":"venue"
},
  "geometry": {"coordinates":[149.124557495,-35.4470710754],"type":"Point"}
}