{
  "type": "Feature",
  "properties": {
    "addr:full":"PO Box 4 Ensay VIC 3895",
    "addr:postcode":"3895",
    "iso:country":"AU",
    "sg:address":"PO Box 4",
    "sg:city":"Ensay",
    "sg:classifiers":[
        {
            "category":"Farming",
            "subcategory":"Farm",
            "type":"Manufacturing & Wholesale Goods"
        }
    ],
    "sg:phone":"+61 3 5157 3210",
    "sg:postcode":"3895",
    "sg:province":"VIC",
    "sg:tags":[
        "farmer"
    ],
    "wof:name":"Cromb W R & F L",
    "wof:placetype":"venue"
},
  "geometry": {"coordinates":[147.83033752399999,-37.3804092407],"type":"Point"}
}