{
  "type": "Feature",
  "properties": {
    "addr:full":"29 Turner Ave Concord NSW 2137",
    "addr:housenumber":"29",
    "addr:postcode":"2137",
    "addr:street":"Turner Ave",
    "iso:country":"AU",
    "sg:address":"29 Turner Ave",
    "sg:city":"Concord",
    "sg:classifiers":[
        {
            "category":"Retail",
            "subcategory":"Laundry & Dry Cleaning",
            "type":"Services"
        }
    ],
    "sg:phone":"+61 2 9702 7020",
    "sg:postcode":"2137",
    "sg:province":"NSW",
    "sg:tags":[
        "ironing"
    ],
    "wof:name":"Neighbourhood Ironing Pty Ltd",
    "wof:placetype":"venue"
},
  "geometry": {"coordinates":[151.1040802,-33.8456115723],"type":"Point"}
}