{
  "type": "Feature",
  "properties": {
    "iso:country":"AU",
    "sg:address":"885 South Rd",
    "sg:city":"Clarence Gardens",
    "sg:classifiers":[
        {
            "category":"Health Services",
            "subcategory":"Dentist",
            "type":"Services"
        }
    ],
    "sg:phone":"+61 8 8293 1476",
    "sg:postcode":"5039",
    "sg:province":"SA",
    "wof:name":"Kropf W W",
    "wof:placetype":"venue"
},
  "geometry": {"coordinates":[138.573654175,-34.9737434387],"type":"Point"}
}