{
  "type": "Feature",
  "properties": {
    "addr:full":"160 Bromley Rd Robinvale VIC 3549",
    "addr:housenumber":"160",
    "addr:postcode":"3549",
    "addr:street":"Bromley Rd",
    "iso:country":"AU",
    "sg:address":"160 Bromley Rd",
    "sg:city":"Robinvale",
    "sg:classifiers":[
        {
            "category":"Health Services",
            "subcategory":"Dentist",
            "type":"Services"
        }
    ],
    "sg:phone":"+61 3 5026 3536",
    "sg:postcode":"3549",
    "sg:province":"VIC",
    "wof:name":"Tankard Dental Surgery",
    "wof:placetype":"venue"
},
  "geometry": {"coordinates":[142.771087647,-34.5852012634],"type":"Point"}
}