{
  "type": "Feature",
  "properties": {
    "iso:country":"AU",
    "sg:address":"130 Hector St",
    "sg:city":"Osborne Park",
    "sg:classifiers":[
        {
            "category":"Retail",
            "subcategory":"Auto Rental",
            "type":"Services"
        }
    ],
    "sg:phone":"+61 8 9242 4411",
    "sg:postcode":"6017",
    "sg:province":"WA",
    "sg:tags":[
        "bus",
        "truck"
    ],
    "wof:name":"Four Wheel Drive Hire",
    "wof:placetype":"venue"
},
  "geometry": {"coordinates":[115.824493408,-31.9043045044],"type":"Point"}
}