{
  "type": "Feature",
  "properties": {
    "addr:full":"66 Heather St Heatherbrae NSW 2324",
    "addr:housenumber":"66",
    "addr:postcode":"2324",
    "addr:street":"Heather St",
    "iso:country":"AU",
    "sg:address":"66 Heather St",
    "sg:city":"Heatherbrae",
    "sg:classifiers":[
        {
            "category":"Building & Trades",
            "subcategory":"Equipment Rental",
            "type":"Services"
        }
    ],
    "sg:phone":"+61 2 4987 4973",
    "sg:postcode":"2324",
    "sg:province":"NSW",
    "sg:tags":[
        "crane",
        "hire"
    ],
    "wof:name":"ACT Tower Hire",
    "wof:placetype":"venue"
},
  "geometry": {"coordinates":[151.73394775400001,-32.7857055664],"type":"Point"}
}