{
  "type": "Feature",
  "properties": {
    "iso:country":"AU",
    "sg:address":"PO Box 8025",
    "sg:city":"Oakleigh East",
    "sg:classifiers":[
        {
            "category":"Building & Trades",
            "subcategory":"Plumbing",
            "type":"Services"
        }
    ],
    "sg:phone":"+61 3 9569 1433",
    "sg:postcode":"3166",
    "sg:province":"VIC",
    "sg:tags":[
        "plumber",
        "gasfitters"
    ],
    "wof:name":"Hy Flow Plumbing and Gas Fitting",
    "wof:placetype":"venue"
},
  "geometry": {"coordinates":[145.114135742,-37.9014396667],"type":"Point"}
}