{
  "type": "Feature",
  "properties": {
    "addr:full":"U18/11- 15 Gardner Crt Toowoomba QLD 4350",
    "addr:housenumber":"15",
    "addr:postcode":"4350",
    "addr:street":"/ 11;Gardner Crt",
    "iso:country":"AU",
    "sg:address":"U18/11- 15 Gardner Crt",
    "sg:city":"Toowoomba",
    "sg:classifiers":[
        {
            "category":"Personal",
            "subcategory":"Shoe Repair & Shine",
            "type":"Services"
        }
    ],
    "sg:phone":"+61 7 4633 1788",
    "sg:postcode":"4350",
    "sg:province":"QLD",
    "sg:tags":[
        "reconditioning",
        "business",
        "furniture"
    ],
    "wof:name":"Struts-N-Stuff",
    "wof:placetype":"venue"
},
  "geometry": {"coordinates":[151.90422100000001,-27.547386],"type":"Point"}
}