{
  "type": "Feature",
  "properties": {
    "addr:full":"18 Nathanial St Pearcedale VIC 3912",
    "addr:housenumber":"18",
    "addr:postcode":"3912",
    "addr:street":"Nathanial St",
    "iso:country":"AU",
    "sg:address":"18 Nathanial St",
    "sg:city":"Pearcedale",
    "sg:classifiers":[
        {
            "category":"Manufacturing",
            "subcategory":"Tools & Machinery",
            "type":"Manufacturing & Wholesale Goods"
        }
    ],
    "sg:phone":"+61 428 567 008",
    "sg:postcode":"3912",
    "sg:province":"VIC",
    "sg:tags":[
        "earth",
        "excavating",
        "moving",
        "equipment"
    ],
    "wof:name":"Casey Diggin Riggin",
    "wof:placetype":"venue"
},
  "geometry": {"coordinates":[145.23226928700001,-38.1965637207],"type":"Point"}
}