{
  "type": "Feature",
  "properties": {
    "addr:full":"147 Carp St Bega NSW 2550",
    "addr:housenumber":"147",
    "addr:postcode":"2550",
    "addr:street":"Carp St",
    "iso:country":"AU",
    "sg:address":"147 Carp St",
    "sg:city":"Bega",
    "sg:classifiers":[
        {
            "category":"Travel",
            "subcategory":"Hotels & Motels",
            "type":"Entertainment"
        }
    ],
    "sg:phone":"+61 2 6492 1011",
    "sg:postcode":"2550",
    "sg:province":"NSW",
    "sg:tags":[
        "accommodation"
    ],
    "wof:name":"Commercial Hotel",
    "wof:placetype":"venue"
},
  "geometry": {"coordinates":[149.84498596200001,-36.6743164062],"type":"Point"}
}