{
  "type": "Feature",
  "properties": {
    "iso:country":"AU",
    "sg:address":"232 Hampshire Rd",
    "sg:city":"Sunshine",
    "sg:classifiers":[
        {
            "category":"Cafe",
            "type":"Food & Drink"
        }
    ],
    "sg:phone":"+61 3 9310 1919",
    "sg:postcode":"3020",
    "sg:province":"VIC",
    "wof:name":"Denizs Cafe",
    "wof:placetype":"venue"
},
  "geometry": {"coordinates":[144.831985,-37.786282],"type":"Point"}
}