{
  "type": "Feature",
  "properties": {
    "addr:full":"46- 50 Yale Drv Epping VIC 3076",
    "addr:housenumber":"50",
    "addr:postcode":"3076",
    "addr:street":"Yale Drv",
    "iso:country":"AU",
    "sg:address":"46- 50 Yale Drv",
    "sg:city":"Epping",
    "sg:classifiers":[
        {
            "category":"Wholesale",
            "subcategory":"Electrical",
            "type":"Manufacturing & Wholesale Goods"
        }
    ],
    "sg:phone":"+61 3 9408 5333",
    "sg:postcode":"3076",
    "sg:province":"VIC",
    "sg:tags":[
        "wholesaler",
        "mfrs",
        "accessory"
    ],
    "wof:name":"Condor Lighting Pty Ltd",
    "wof:placetype":"venue"
},
  "geometry": {"coordinates":[145.012741089,-37.6445007324],"type":"Point"}
}