{
  "type": "Feature",
  "properties": {
    "iso:country":"AU",
    "sg:address":"349 Pacific Hwy",
    "sg:city":"Crows Nest",
    "sg:classifiers":[
        {
            "category":"Professional",
            "subcategory":"Art Services",
            "type":"Services"
        }
    ],
    "sg:phone":"+61 2 9959 5777",
    "sg:postcode":"2065",
    "sg:province":"NSW",
    "sg:tags":[
        "graphic",
        "designer"
    ],
    "wof:name":"Bennett Raymond Design Associates",
    "wof:placetype":"venue"
},
  "geometry": {"coordinates":[151.198730469,-33.8253326416],"type":"Point"}
}