{
  "type": "Feature",
  "properties": {
    "iso:country":"AU",
    "sg:address":"U1/516 Alexander Drv",
    "sg:city":"Malaga",
    "sg:classifiers":[
        {
            "category":"Food & Beverages",
            "subcategory":"Bakery",
            "type":"Retail Goods"
        }
    ],
    "sg:phone":"+61 8 9248 4224",
    "sg:postcode":"6090",
    "sg:province":"WA",
    "sg:tags":[
        "baker"
    ],
    "wof:name":"La Pagnotta Italian Bakery",
    "wof:placetype":"venue"
},
  "geometry": {"coordinates":[115.886161804,-31.8639278412],"type":"Point"}
}