{
  "type": "Feature",
  "properties": {
    "addr:full":"24 Whitehorse Rd Balwyn VIC 3103",
    "addr:housenumber":"24",
    "addr:postcode":"3103",
    "addr:street":"Whitehorse Rd",
    "iso:country":"AU",
    "sg:address":"24 Whitehorse Rd",
    "sg:city":"Balwyn",
    "sg:classifiers":[
        {
            "category":"Home & Garden",
            "subcategory":"Furniture",
            "type":"Retail Goods"
        }
    ],
    "sg:phone":"+61 3 9816 9300",
    "sg:postcode":"3103",
    "sg:province":"VIC",
    "sg:tags":[
        "outdoor"
    ],
    "wof:name":"Town And Country Gardens",
    "wof:placetype":"venue"
},
  "geometry": {"coordinates":[145.06349182100001,-37.8108139038],"type":"Point"}
}