{
  "type": "Feature",
  "properties": {
    "iso:country":"AU",
    "sg:address":"120A Roberts St",
    "sg:city":"Yarraville",
    "sg:classifiers":[
        {
            "category":"Industrial Area",
            "type":"Public Place"
        }
    ],
    "sg:phone":"+61 3 9314 1661",
    "sg:postcode":"3013",
    "sg:province":"VIC",
    "sg:tags":[
        "floor"
    ],
    "sg:website":"http://www.industricoat.com.au",
    "wof:name":"Industricoat",
    "wof:placetype":"venue"
},
  "geometry": {"coordinates":[144.869308472,-37.8119430542],"type":"Point"}
}