{
  "type": "Feature",
  "properties": {
    "iso:country":"AU",
    "sg:address":"98c Marine Pde",
    "sg:city":"Southport",
    "sg:classifiers":[
        {
            "category":"Food & Beverages",
            "subcategory":"Groceries & Convenience Stores",
            "type":"Retail Goods"
        }
    ],
    "sg:phone":"+61 7 5531 4632",
    "sg:postcode":"4215",
    "sg:province":"QLD",
    "wof:name":"Jasmina Convenience Store",
    "wof:placetype":"venue"
},
  "geometry": {"coordinates":[153.41314697300001,-27.9623908997],"type":"Point"}
}