{
  "type": "Feature",
  "properties": {
    "iso:country":"AU",
    "sg:address":"Shop 1c / Collins Place 45 Collins St",
    "sg:city":"Melbourne",
    "sg:classifiers":[
        {
            "category":"Shopping",
            "subcategory":"Clothing, Apparel, & Fashions",
            "type":"Retail Goods"
        }
    ],
    "sg:phone":"+61 3 9662 1661",
    "sg:postcode":"3000",
    "sg:province":"VIC",
    "sg:tags":[
        "boutique"
    ],
    "wof:name":"Giorgio Armani",
    "wof:placetype":"venue"
},
  "geometry": {"coordinates":[144.97233581500001,-37.8139076233],"type":"Point"}
}