{
  "type": "Feature",
  "properties": {
    "addr:full":"3/ 108 Percival Rd Smithfield NSW 2164",
    "addr:housenumber":"/ 108",
    "addr:postcode":"2164",
    "addr:street":"Percival Rd",
    "iso:country":"AU",
    "sg:address":"3/ 108 Percival Rd",
    "sg:city":"Smithfield",
    "sg:classifiers":[
        {
            "category":"Home & Garden",
            "subcategory":"Building Materials",
            "type":"Retail Goods"
        }
    ],
    "sg:phone":"+61 2 9757 1100",
    "sg:postcode":"2164",
    "sg:province":"NSW",
    "sg:tags":[
        "laminate",
        "laminated",
        "panel"
    ],
    "wof:name":"Fleur De Lys Pty Ltd",
    "wof:placetype":"venue"
},
  "geometry": {"coordinates":[150.95062255900001,-33.8382492065],"type":"Point"}
}