{
  "type": "Feature",
  "properties": {
    "addr:full":"PO Box 2410 Malaga WA 6944",
    "addr:postcode":"6944",
    "iso:country":"AU",
    "sg:address":"PO Box 2410",
    "sg:city":"Malaga",
    "sg:classifiers":[
        {
            "category":"Building & Trades",
            "subcategory":"Cleaning & Sanitation",
            "type":"Services"
        }
    ],
    "sg:phone":"+61 412 262 519",
    "sg:postcode":"6944",
    "sg:province":"WA",
    "sg:tags":[
        "industrial",
        "commercial",
        "contractor"
    ],
    "wof:name":"Showdown Cleaning Services",
    "wof:placetype":"venue"
},
  "geometry": {"coordinates":[115.893409729,-31.8554382324],"type":"Point"}
}