{
  "type": "Feature",
  "properties": {
    "addr:full":"1151 Henty Hwy Hensley Park VIC 3301",
    "addr:housenumber":"1151",
    "addr:postcode":"3301",
    "addr:street":"Henty Hwy Hensley Park",
    "iso:country":"AU",
    "sg:address":"1151 Henty Hwy",
    "sg:city":"Hensley Park",
    "sg:classifiers":[
        {
            "category":"Professional",
            "subcategory":"Art Services",
            "type":"Services"
        }
    ],
    "sg:phone":"+61 3 5574 8297",
    "sg:postcode":"3301",
    "sg:province":"VIC",
    "sg:tags":[
        "decorator",
        "painter"
    ],
    "wof:name":"Fisher G J",
    "wof:placetype":"venue"
},
  "geometry": {"coordinates":[142.006103516,-37.6544799805],"type":"Point"}
}