{
  "type": "Feature",
  "properties": {
    "iso:country":"AU",
    "sg:address":"27 Links St",
    "sg:city":"Sunshine West",
    "sg:classifiers":[
        {
            "category":"Home & Garden",
            "subcategory":"Building Materials",
            "type":"Retail Goods"
        }
    ],
    "sg:phone":"+61 3 9363 1505",
    "sg:postcode":"3020",
    "sg:province":"VIC",
    "sg:tags":[
        "merchant",
        "glass",
        "glazier"
    ],
    "wof:name":"Pallasis Demetre",
    "wof:placetype":"venue"
},
  "geometry": {"coordinates":[144.807541,-37.789246],"type":"Point"}
}