{
  "type": "Feature",
  "properties": {
    "iso:country":"AU",
    "sg:address":"8 Fernie Pl",
    "sg:city":"Attwood",
    "sg:classifiers":[
        {
            "category":"Utilities",
            "subcategory":"Water",
            "type":"Services"
        }
    ],
    "sg:phone":"+61 419 542 660",
    "sg:postcode":"3049",
    "sg:province":"VIC",
    "sg:tags":[
        "hot",
        "system"
    ],
    "wof:name":"J & C Moloney Plumbing",
    "wof:placetype":"venue"
},
  "geometry": {"coordinates":[144.89750699999999,-37.672573],"type":"Point"}
}