{
  "type": "Feature",
  "properties": {
    "iso:country":"AU",
    "sg:address":"Shop 2/ 1 Normanby St",
    "sg:city":"Yeppoon",
    "sg:classifiers":[
        {
            "category":"Arena",
            "subcategory":"Horse Racetrack",
            "type":"Entertainment"
        }
    ],
    "sg:phone":"+61 7 4938 3440",
    "sg:postcode":"4703",
    "sg:province":"QLD",
    "sg:tags":[
        "retail",
        "swimwear"
    ],
    "wof:name":"Moana Blue",
    "wof:placetype":"venue"
},
  "geometry": {"coordinates":[150.74862670900001,-23.128944397],"type":"Point"}
}