{
  "type": "Feature",
  "properties": {
    "addr:full":"265 Cleveland St Redfern NSW 2016",
    "addr:housenumber":"265",
    "addr:postcode":"2016",
    "addr:street":"Cleveland St",
    "iso:country":"AU",
    "sg:address":"265 Cleveland St",
    "sg:city":"Redfern",
    "sg:classifiers":[
        {
            "category":"Shopping",
            "subcategory":"Computers & Home Electronics",
            "type":"Retail Goods"
        }
    ],
    "sg:phone":"+61 2 9319 5203",
    "sg:postcode":"2016",
    "sg:province":"NSW",
    "sg:tags":[
        "equipment",
        "supply"
    ],
    "wof:name":"Sydney Toner Supply",
    "wof:placetype":"venue"
},
  "geometry": {"coordinates":[151.206787109,-33.8898887634],"type":"Point"}
}