{
  "type": "Feature",
  "properties": {
    "addr:full":"26 Alma Ave Woy Woy NSW 2256",
    "addr:housenumber":"26",
    "addr:postcode":"2256",
    "addr:street":"Alma Ave",
    "iso:country":"AU",
    "sg:address":"26 Alma Ave",
    "sg:city":"Woy Woy",
    "sg:classifiers":[
        {
            "category":"Retail",
            "subcategory":"Auto Repair",
            "type":"Services"
        }
    ],
    "sg:phone":"+61 2 4344 6844",
    "sg:postcode":"2256",
    "sg:province":"NSW",
    "sg:tags":[
        "repairer",
        "motor",
        "engineer"
    ],
    "wof:name":"Peninsula Car Repairs Pty Ltd",
    "wof:placetype":"venue"
},
  "geometry": {"coordinates":[151.32426452600001,-33.5040283203],"type":"Point"}
}