{
  "type": "Feature",
  "properties": {
    "addr:full":"20 Richmond Rd Windsor NSW 2756",
    "addr:housenumber":"20",
    "addr:postcode":"2756",
    "addr:street":"Richmond Rd",
    "iso:country":"AU",
    "sg:address":"20 Richmond Rd",
    "sg:city":"Windsor",
    "sg:classifiers":[
        {
            "category":"Food & Beverages",
            "subcategory":"Groceries & Convenience Stores",
            "type":"Retail Goods"
        }
    ],
    "sg:phone":"+61 2 4577 8734",
    "sg:postcode":"2756",
    "sg:province":"NSW",
    "wof:name":"7 Eleven Food Store",
    "wof:placetype":"venue"
},
  "geometry": {"coordinates":[150.81182861299999,-33.6115531921],"type":"Point"}
}