{
  "type": "Feature",
  "properties": {
    "iso:country":"AU",
    "sg:address":"14 Clements St",
    "sg:city":"Drummoyne",
    "sg:classifiers":[
        {
            "category":"Travel",
            "subcategory":"Hostel",
            "type":"Entertainment"
        }
    ],
    "sg:phone":"+61 2 9713 5164",
    "sg:postcode":"2047",
    "sg:province":"NSW",
    "sg:tags":[
        "home"
    ],
    "wof:name":"Presbyterian Aged Care-Drummoyne",
    "wof:placetype":"venue"
},
  "geometry": {"coordinates":[151.148315,-33.860744],"type":"Point"}
}