{
  "type": "Feature",
  "properties": {
    "iso:country":"AU",
    "sg:address":"19 Quinns La",
    "sg:city":"Nowra South",
    "sg:classifiers":[
        {
            "category":"Building & Trades",
            "subcategory":"Equipment Rental",
            "type":"Services"
        }
    ],
    "sg:phone":"+61 2 4422 1323",
    "sg:postcode":"2541",
    "sg:province":"NSW",
    "sg:tags":[
        "demolition",
        "contractor"
    ],
    "wof:name":"Smiths Plant Hire Pty Ltd",
    "wof:placetype":"venue"
},
  "geometry": {"coordinates":[150.59387207,-34.8777999878],"type":"Point"}
}