{
  "type": "Feature",
  "properties": {
    "iso:country":"AU",
    "sg:address":"Monaro Hwy",
    "sg:city":"Bredbo",
    "sg:classifiers":[
        {
            "category":"Manufacturing",
            "subcategory":"Tools & Machinery",
            "type":"Manufacturing & Wholesale Goods"
        }
    ],
    "sg:phone":"+61 2 6454 4175",
    "sg:postcode":"2626",
    "sg:province":"NSW",
    "sg:tags":[
        "earth",
        "excavating",
        "moving",
        "equipment"
    ],
    "wof:name":"Corkhill Bros Sales Pty Ltd",
    "wof:placetype":"venue"
},
  "geometry": {"coordinates":[149.15028381400001,-35.9590187073],"type":"Point"}
}