{
  "type": "Feature",
  "properties": {
    "addr:full":"43A Ethel St Seaforth NSW 2092",
    "addr:housenumber":"43a",
    "addr:postcode":"2092",
    "addr:street":"Ethel St",
    "iso:country":"AU",
    "sg:address":"43A Ethel St",
    "sg:city":"Seaforth",
    "sg:classifiers":[
        {
            "category":"Professional",
            "subcategory":"Accounting & Tax Preparation",
            "type":"Services"
        }
    ],
    "sg:phone":"+61 2 9907 9222",
    "sg:postcode":"2092",
    "sg:province":"NSW",
    "sg:tags":[
        "bookkeeping"
    ],
    "wof:name":"Seaforth Business Services",
    "wof:placetype":"venue"
},
  "geometry": {"coordinates":[151.25184631400001,-33.7978820801],"type":"Point"}
}