{
  "type": "Feature",
  "properties": {
    "addr:full":"Shp60/ 64 Marangaroo Drv Girrawheen WA 6064",
    "addr:postcode":"6064",
    "addr:street":"Marangaroo Drv",
    "iso:country":"AU",
    "sg:address":"Shp60/ 64 Marangaroo Drv",
    "sg:city":"Girrawheen",
    "sg:classifiers":[
        {
            "category":"Food & Beverages",
            "subcategory":"Groceries & Convenience Stores",
            "type":"Retail Goods"
        }
    ],
    "sg:phone":"+61 8 9342 2827",
    "sg:postcode":"6064",
    "sg:province":"WA",
    "wof:name":"Girrawheen Gourmet Deli",
    "wof:placetype":"venue"
},
  "geometry": {"coordinates":[115.829910278,-31.834312439],"type":"Point"}
}