{
  "type": "Feature",
  "properties": {
    "addr:full":"14 Morley Crt Baulkham Hills NSW 2153",
    "addr:housenumber":"14",
    "addr:postcode":"2153",
    "addr:street":"Morley Crt",
    "iso:country":"AU",
    "sg:address":"14 Morley Crt",
    "sg:city":"Baulkham Hills",
    "sg:classifiers":[
        {
            "category":"Banks & Credit Unions",
            "subcategory":"Financial Services",
            "type":"Services"
        }
    ],
    "sg:phone":"+61 2 9620 8146",
    "sg:postcode":"2153",
    "sg:province":"NSW",
    "sg:tags":[
        "planning"
    ],
    "wof:name":"Maria Worthington",
    "wof:placetype":"venue"
},
  "geometry": {"coordinates":[150.96386718799999,-33.7454872131],"type":"Point"}
}