{
  "type": "Feature",
  "properties": {
    "addr:full":"684 - 686 George St Sydney NSW 2000",
    "addr:housenumber":"686",
    "addr:postcode":"2000",
    "addr:street":"George St",
    "iso:country":"AU",
    "sg:address":"684 - 686 George St",
    "sg:city":"Sydney",
    "sg:classifiers":[
        {
            "category":"Banks & Credit Unions",
            "subcategory":"Bank",
            "type":"Services"
        }
    ],
    "sg:phone":"+61 2 8276 7500",
    "sg:postcode":"2000",
    "sg:province":"NSW",
    "wof:name":"Bank of Queensland",
    "wof:placetype":"venue"
},
  "geometry": {"coordinates":[151.20596313499999,-33.8776435852],"type":"Point"}
}