{
  "type": "Feature",
  "properties": {
    "addr:full":"136 Ryrie St Geelong VIC 3220",
    "addr:housenumber":"136",
    "addr:postcode":"3220",
    "addr:street":"Ryrie St",
    "iso:country":"AU",
    "sg:address":"136 Ryrie St",
    "sg:city":"Geelong",
    "sg:classifiers":[
        {
            "category":"Shopping",
            "subcategory":"Crafts & Fabrics",
            "type":"Retail Goods"
        }
    ],
    "sg:phone":"+61 3 5229 4677",
    "sg:postcode":"3220",
    "sg:province":"VIC",
    "sg:tags":[
        "supply"
    ],
    "wof:name":"Artworx Geelong",
    "wof:placetype":"venue"
},
  "geometry": {"coordinates":[144.35882599999999,-38.148479],"type":"Point"}
}