{
  "type": "Feature",
  "properties": {
    "iso:country":"AU",
    "sg:address":"21 Keeble St",
    "sg:city":"Mareeba",
    "sg:classifiers":[
        {
            "category":"Building & Trades",
            "subcategory":"Equipment Rental",
            "type":"Services"
        }
    ],
    "sg:phone":"+61 7 4092 3400",
    "sg:postcode":"4880",
    "sg:province":"QLD",
    "sg:tags":[
        "party",
        "hire"
    ],
    "wof:name":"Mareeba Hire Equipment",
    "wof:placetype":"venue"
},
  "geometry": {"coordinates":[145.41737365700001,-16.9911117554],"type":"Point"}
}