{
  "type": "Feature",
  "properties": {
    "addr:full":"14 Production St Noosaville QLD 4566",
    "addr:housenumber":"14",
    "addr:postcode":"4566",
    "addr:street":"Production St",
    "iso:country":"AU",
    "sg:address":"14 Production St",
    "sg:city":"Noosaville",
    "sg:classifiers":[
        {
            "category":"Recreation",
            "subcategory":"Fishing",
            "type":"Entertainment"
        }
    ],
    "sg:phone":"+61 7 5447 1152",
    "sg:postcode":"4566",
    "sg:province":"QLD",
    "sg:tags":[
        "bait"
    ],
    "wof:name":"Sea Queen Marine Products",
    "wof:placetype":"venue"
},
  "geometry": {"coordinates":[153.04487609899999,-26.4167633057],"type":"Point"}
}