{
  "type": "Feature",
  "properties": {
    "iso:country":"AU",
    "sg:address":"20 Wetherill St",
    "sg:city":"Leichhardt",
    "sg:classifiers":[
        {
            "category":"Health Services",
            "subcategory":"Doctor",
            "type":"Services"
        }
    ],
    "sg:phone":"+61 2 9569 6317",
    "sg:postcode":"2040",
    "sg:province":"NSW",
    "sg:tags":[
        "medical",
        "practitioner"
    ],
    "wof:name":"Wetherill Street Health Care",
    "wof:placetype":"venue"
},
  "geometry": {"coordinates":[151.157837,-33.882683],"type":"Point"}
}