{
  "type": "Feature",
  "properties": {
    "iso:country":"AU",
    "sg:address":"19- 22 Condell Pl",
    "sg:city":"Forster",
    "sg:classifiers":[
        {
            "category":"Banks & Credit Unions",
            "subcategory":"Bank",
            "type":"Services"
        }
    ],
    "sg:phone":"+61 2 6554 8444",
    "sg:postcode":"2428",
    "sg:province":"NSW",
    "sg:tags":[
        "concrete",
        "reinforcement"
    ],
    "wof:name":"McNamara B & J Pty Ltd",
    "wof:placetype":"venue"
},
  "geometry": {"coordinates":[152.52179,-32.19772],"type":"Point"}
}