{
  "type": "Feature",
  "properties": {
    "iso:country":"AU",
    "sg:address":"Alice St",
    "sg:city":"Moree",
    "sg:classifiers":[
        {
            "category":"Travel",
            "subcategory":"Hotels & Motels",
            "type":"Entertainment"
        }
    ],
    "sg:phone":"+61 2 6752 1644",
    "sg:postcode":"2400",
    "sg:province":"NSW",
    "sg:tags":[
        "accommodation"
    ],
    "wof:name":"Moree Hotel",
    "wof:placetype":"venue"
},
  "geometry": {"coordinates":[149.84124755900001,-29.4712524414],"type":"Point"}
}