{
  "type": "Feature",
  "properties": {
    "addr:full":"160 Viaduct Rd Moorabool VIC 3221",
    "addr:housenumber":"160",
    "addr:postcode":"3221",
    "addr:street":"Viaduct Rd",
    "iso:country":"AU",
    "sg:address":"160 Viaduct Rd",
    "sg:city":"Moorabool",
    "sg:classifiers":[
        {
            "category":"Building & Trades",
            "subcategory":"Pest Control",
            "type":"Services"
        }
    ],
    "sg:phone":"+61 415 512 783",
    "sg:postcode":"3221",
    "sg:province":"VIC",
    "wof:name":"L.A. Pest Control",
    "wof:placetype":"venue"
},
  "geometry": {"coordinates":[144.27813699999999,-38.068714],"type":"Point"}
}