{
  "type": "Feature",
  "properties": {
    "addr:full":"81 Canterbury Rd (Cnr Sheehans & Canterbury Rds) Blackburn South VIC 3130",
    "addr:housenumber":"81",
    "addr:postcode":"3130",
    "addr:street":"Canterbury Rd Cnr Sheehans & Canterbury Rds",
    "iso:country":"AU",
    "sg:address":"81 Canterbury Rd (Cnr Sheehans & Canterbury Rds)",
    "sg:city":"Blackburn South",
    "sg:classifiers":[
        {
            "category":"Health Services",
            "subcategory":"Doctor",
            "type":"Services"
        }
    ],
    "sg:phone":"+61 3 9877 1200",
    "sg:postcode":"3130",
    "sg:province":"VIC",
    "sg:tags":[
        "medical",
        "practitioner"
    ],
    "wof:name":"Sheehans Medical Centre",
    "wof:placetype":"venue"
},
  "geometry": {"coordinates":[145.144165039,-37.8311576843],"type":"Point"}
}