{
  "type": "Feature",
  "properties": {
    "addr:full":"14 Jetty Rd Ryde NSW 2112",
    "addr:housenumber":"14",
    "addr:postcode":"2112",
    "addr:street":"Jetty Rd",
    "iso:country":"AU",
    "sg:address":"14 Jetty Rd",
    "sg:city":"Ryde",
    "sg:classifiers":[
        {
            "category":"Real Estate",
            "subcategory":"Architect",
            "type":"Services"
        }
    ],
    "sg:phone":"+61 2 9809 1512",
    "sg:postcode":"2112",
    "sg:province":"NSW",
    "wof:name":"Murray R O",
    "wof:placetype":"venue"
},
  "geometry": {"coordinates":[151.11062622099999,-33.8300857544],"type":"Point"}
}