{
  "type": "Feature",
  "properties": {
    "addr:full":"74 Maliwa Rd Narara NSW 2250",
    "addr:housenumber":"74",
    "addr:postcode":"2250",
    "addr:street":"Maliwa Rd",
    "iso:country":"AU",
    "sg:address":"74 Maliwa Rd",
    "sg:city":"Narara",
    "sg:classifiers":[
        {
            "category":"Real Estate",
            "subcategory":"Architect",
            "type":"Services"
        }
    ],
    "sg:phone":"+61 2 4322 5144",
    "sg:postcode":"2250",
    "sg:province":"NSW",
    "sg:tags":[
        "building",
        "designer"
    ],
    "wof:name":"Zaia Architects",
    "wof:placetype":"venue"
},
  "geometry": {"coordinates":[151.34341430699999,-33.4075012207],"type":"Point"}
}