{
  "type": "Feature",
  "properties": {
    "iso:country":"AU",
    "sg:address":"3 Moseley Pl",
    "sg:city":"Kambah",
    "sg:classifiers":[
        {
            "category":"Utilities",
            "subcategory":"Water",
            "type":"Services"
        }
    ],
    "sg:phone":"+61 2 6260 2766",
    "sg:postcode":"2902",
    "sg:province":"ACT",
    "sg:tags":[
        "hot",
        "system"
    ],
    "wof:name":"Eveready Plumbing",
    "wof:placetype":"venue"
},
  "geometry": {"coordinates":[149.05705261200001,-35.3945007324],"type":"Point"}
}