{
  "type": "Feature",
  "properties": {
    "iso:country":"AU",
    "sg:address":"Civic Centre Precinct Gordon St",
    "sg:city":"Mackay",
    "sg:classifiers":[
        {
            "category":"Manufacturing",
            "subcategory":"Food",
            "type":"Manufacturing & Wholesale Goods"
        }
    ],
    "sg:phone":"+61 7 4957 1719",
    "sg:postcode":"4740",
    "sg:province":"QLD",
    "sg:tags":[
        "function",
        "catering"
    ],
    "wof:name":"Foodspace",
    "wof:placetype":"venue"
},
  "geometry": {"coordinates":[149.17480499999999,-21.143391],"type":"Point"}
}