{
  "type": "Feature",
  "properties": {
    "addr:full":"55 Hesse St Colac VIC 3250",
    "addr:housenumber":"55",
    "addr:postcode":"3250",
    "addr:street":"Hesse St",
    "iso:country":"AU",
    "sg:address":"55 Hesse St",
    "sg:city":"Colac",
    "sg:classifiers":[
        {
            "category":"Education",
            "subcategory":"University",
            "type":"Public Place"
        }
    ],
    "sg:phone":"+61 3 5231 4435",
    "sg:postcode":"3250",
    "sg:province":"VIC",
    "sg:tags":[
        "educational",
        "organisation",
        "cultural"
    ],
    "wof:name":"U3a Colac Otway",
    "wof:placetype":"venue"
},
  "geometry": {"coordinates":[143.589584,-38.34013],"type":"Point"}
}