{
  "type": "Feature",
  "properties": {
    "iso:country":"AU",
    "sg:address":"Shop 2, 6F 800 Gympie Rd",
    "sg:city":"Chermside",
    "sg:classifiers":[
        {
            "category":"Health Services",
            "subcategory":"Dentist",
            "type":"Services"
        }
    ],
    "sg:phone":"+61 7 3350 1106",
    "sg:postcode":"4032",
    "sg:province":"QLD",
    "wof:name":"Law Vicky",
    "wof:placetype":"venue"
},
  "geometry": {"coordinates":[153.03080700000001,-27.386566],"type":"Point"}
}