{
  "type": "Feature",
  "properties": {
    "addr:full":"Unit 1/ 879 Springvale Rd Mulgrave VIC 3170",
    "addr:housenumber":"/ 879",
    "addr:postcode":"3170",
    "addr:street":"Springvale Rd",
    "iso:country":"AU",
    "sg:address":"Unit 1/ 879 Springvale Rd",
    "sg:city":"Mulgrave",
    "sg:classifiers":[
        {
            "category":"Banks & Credit Unions",
            "subcategory":"Financial Services",
            "type":"Services"
        }
    ],
    "sg:phone":"+61 3 9545 7555",
    "sg:postcode":"3170",
    "sg:province":"VIC",
    "sg:tags":[
        "finance",
        "motor",
        "vehicle"
    ],
    "wof:name":"Capitalcorp Financial Services",
    "wof:placetype":"venue"
},
  "geometry": {"coordinates":[145.156173706,-37.9303894043],"type":"Point"}
}