{
  "type": "Feature",
  "properties": {
    "addr:full":"14 Lower Park Rd Maddington WA 6109",
    "addr:housenumber":"14",
    "addr:postcode":"6109",
    "addr:street":"Lower Park Rd",
    "iso:country":"AU",
    "sg:address":"14 Lower Park Rd",
    "sg:city":"Maddington",
    "sg:classifiers":[
        {
            "category":"Professional",
            "subcategory":"Engineering",
            "type":"Services"
        }
    ],
    "sg:phone":"+61 8 9459 5911",
    "sg:postcode":"6109",
    "sg:province":"WA",
    "sg:tags":[
        "engineer"
    ],
    "wof:name":"Wulfruna Engineering",
    "wof:placetype":"venue"
},
  "geometry": {"coordinates":[115.985992432,-32.0447463989],"type":"Point"}
}