{
  "type": "Feature",
  "properties": {
    "addr:full":"Shop C08 Parkmore Shpng Cntr Cheltenham Rd Keysborough VIC 3173",
    "addr:housenumber":"c08",
    "addr:postcode":"3173",
    "addr:street":"Shpng;Cheltenham Rd",
    "iso:country":"AU",
    "sg:address":"Shop C08 Parkmore Shpng Cntr Cheltenham Rd",
    "sg:city":"Keysborough",
    "sg:classifiers":[
        {
            "category":"Shopping",
            "type":"Retail Goods"
        }
    ],
    "sg:phone":"+61 3 9798 5963",
    "sg:postcode":"3173",
    "sg:province":"VIC",
    "sg:tags":[
        "repair",
        "travel"
    ],
    "wof:name":"Strandbags",
    "wof:placetype":"venue"
},
  "geometry": {"coordinates":[145.17301940900001,-37.9947357178],"type":"Point"}
}