{
  "type": "Feature",
  "properties": {
    "addr:full":"34 Minimine St Stafford QLD 4053",
    "addr:housenumber":"34",
    "addr:postcode":"4053",
    "addr:street":"Minimine St",
    "iso:country":"AU",
    "sg:address":"34 Minimine St",
    "sg:city":"Stafford",
    "sg:classifiers":[
        {
            "category":"Health Services",
            "subcategory":"Doctor",
            "type":"Services"
        }
    ],
    "sg:phone":"+61 7 3356 7377",
    "sg:postcode":"4053",
    "sg:province":"QLD",
    "sg:tags":[
        "medical",
        "practitioner"
    ],
    "wof:name":"Dr Deb - The Travel Doctor",
    "wof:placetype":"venue"
},
  "geometry": {"coordinates":[153.016113281,-27.406337738],"type":"Point"}
}