{
  "type": "Feature",
  "properties": {
    "addr:full":"62 Strelly St Busselton WA 6280",
    "addr:housenumber":"62",
    "addr:postcode":"6280",
    "addr:street":"Strelly St",
    "iso:country":"AU",
    "sg:address":"62 Strelly St",
    "sg:city":"Busselton",
    "sg:classifiers":[
        {
            "category":"Retail",
            "subcategory":"Repair Shop",
            "type":"Services"
        }
    ],
    "sg:phone":"+61 8 9754 2390",
    "sg:postcode":"6280",
    "sg:province":"WA",
    "sg:tags":[
        "maintenance",
        "pool",
        "swimming"
    ],
    "wof:name":"Busselton Spa & Pool Specialist",
    "wof:placetype":"venue"
},
  "geometry": {"coordinates":[115.349533081,-33.6609191895],"type":"Point"}
}