{
  "type": "Feature",
  "properties": {
    "iso:country":"AU",
    "sg:address":"451 Warrandyte-Ringwood Rd",
    "sg:city":"Warrandyte South",
    "sg:classifiers":[
        {
            "category":"Farming",
            "subcategory":"Berry Farm",
            "type":"Manufacturing & Wholesale Goods"
        }
    ],
    "sg:phone":"+61 3 9844 2178",
    "sg:postcode":"3134",
    "sg:province":"VIC",
    "sg:tags":[
        "fruit",
        "grower"
    ],
    "wof:name":"Warrandyte Berry Farm",
    "wof:placetype":"venue"
},
  "geometry": {"coordinates":[145.22731018100001,-37.8055953979],"type":"Point"}
}