{
  "type": "Feature",
  "properties": {
    "iso:country":"AU",
    "sg:address":"198 Pitt St",
    "sg:city":"Sydney",
    "sg:classifiers":[
        {
            "category":"Professional",
            "subcategory":"Business Services",
            "type":"Services"
        }
    ],
    "sg:phone":"+61 2 9267 7605",
    "sg:postcode":"2000",
    "sg:province":"NSW",
    "sg:tags":[
        "bookmaker"
    ],
    "wof:name":"N.S.W. Bookmakers Co-op Ltd",
    "wof:placetype":"venue"
},
  "geometry": {"coordinates":[151.20835876500001,-33.8710708618],"type":"Point"}
}