{
  "type": "Feature",
  "properties": {
    "addr:full":"22 Vale Rd Bathurst NSW 2795",
    "addr:housenumber":"22",
    "addr:postcode":"2795",
    "addr:street":"Vale Rd",
    "iso:country":"AU",
    "sg:address":"22 Vale Rd",
    "sg:city":"Bathurst",
    "sg:classifiers":[
        {
            "category":"Manufacturing",
            "subcategory":"Metals",
            "type":"Manufacturing & Wholesale Goods"
        }
    ],
    "sg:phone":"+61 2 6331 4296",
    "sg:postcode":"2795",
    "sg:province":"NSW",
    "sg:tags":[
        "steel",
        "fabricator",
        "mfrs"
    ],
    "wof:name":"G.H. Sheetmetal",
    "wof:placetype":"venue"
},
  "geometry": {"coordinates":[149.56950378400001,-33.4664878845],"type":"Point"}
}