{
  "type": "Feature",
  "properties": {
    "iso:country":"AU",
    "sg:address":"5 Crestview Pl",
    "sg:city":"Lisarow",
    "sg:classifiers":[
        {
            "category":"Shopping",
            "subcategory":"Computers & Home Electronics",
            "type":"Retail Goods"
        }
    ],
    "sg:phone":"+61 2 4362 9362",
    "sg:postcode":"2250",
    "sg:province":"NSW",
    "sg:tags":[
        "ergonomics"
    ],
    "wof:name":"Sirrah Consulting & Training Services Pty Ltd",
    "wof:placetype":"venue"
},
  "geometry": {"coordinates":[151.38031005900001,-33.3820495605],"type":"Point"}
}