{
  "type": "Feature",
  "properties": {
    "iso:country":"AU",
    "sg:address":"PO Box 341",
    "sg:city":"Kwinana",
    "sg:classifiers":[
        {
            "category":"Professional",
            "subcategory":"Testing Lab",
            "type":"Services"
        }
    ],
    "sg:phone":"+61 8 9419 2754",
    "sg:postcode":"6167",
    "sg:province":"WA",
    "sg:tags":[
        "inspection"
    ],
    "wof:name":"Engineering QC",
    "wof:placetype":"venue"
},
  "geometry": {"coordinates":[115.82785,-32.220089],"type":"Point"}
}