{
  "type": "Feature",
  "properties": {
    "addr:full":"11 Miller St Elsternwick VIC 3185",
    "addr:housenumber":"11",
    "addr:postcode":"3185",
    "addr:street":"Miller St",
    "iso:country":"AU",
    "sg:address":"11 Miller St",
    "sg:city":"Elsternwick",
    "sg:classifiers":[
        {
            "category":"Arena",
            "subcategory":"Sports Club",
            "type":"Entertainment"
        }
    ],
    "sg:phone":"+61 422 634 274",
    "sg:postcode":"3185",
    "sg:province":"VIC",
    "sg:tags":[
        "defence",
        "supply",
        "self",
        "instruction",
        "martial art"
    ],
    "wof:name":"Traditional Shaolin Kung Fu",
    "wof:placetype":"venue"
},
  "geometry": {"coordinates":[144.99763488799999,-37.8830566406],"type":"Point"}
}