{
  "type": "Feature",
  "properties": {
    "addr:full":"St Helens Park NSW 2560",
    "addr:postcode":"2560",
    "iso:country":"AU",
    "sg:address":"St",
    "sg:city":"Helens Park",
    "sg:classifiers":[
        {
            "category":"Retail",
            "subcategory":"Car Wash",
            "type":"Services"
        }
    ],
    "sg:phone":"+61 413 992 567",
    "sg:postcode":"2560",
    "sg:province":"NSW",
    "sg:tags":[
        "truck",
        "cleaning"
    ],
    "wof:name":"Enviro Care Care",
    "wof:placetype":"venue"
},
  "geometry": {"coordinates":[150.80714416500001,-34.1051216125],"type":"Point"}
}