{
  "type": "Feature",
  "properties": {
    "addr:full":"23 Quarimor Rd Bibra Lake WA 6163",
    "addr:housenumber":"23",
    "addr:postcode":"6163",
    "addr:street":"Quarimor Rd",
    "iso:country":"AU",
    "sg:address":"23 Quarimor Rd",
    "sg:city":"Bibra Lake",
    "sg:classifiers":[
        {
            "category":"Wholesale",
            "subcategory":"Machinery & Supplies",
            "type":"Manufacturing & Wholesale Goods"
        }
    ],
    "sg:phone":"+61 8 9434 2393",
    "sg:postcode":"6163",
    "sg:province":"WA",
    "sg:tags":[
        "process",
        "instrument",
        "control"
    ],
    "wof:name":"Armwest Pty. Ltd.",
    "wof:placetype":"venue"
},
  "geometry": {"coordinates":[115.799004,-32.104935],"type":"Point"}
}