{
  "type": "Feature",
  "properties": {
    "iso:country":"AU",
    "sg:address":"Patricia Ave",
    "sg:city":"Charlestown",
    "sg:classifiers":[
        {
            "category":"Education",
            "subcategory":"School",
            "type":"Public Place"
        }
    ],
    "sg:phone":"+61 2 4943 5827",
    "sg:postcode":"2290",
    "sg:province":"NSW",
    "sg:tags":[
        "state",
        "-",
        "nsw"
    ],
    "wof:name":"Charlestown South Public",
    "wof:placetype":"venue"
},
  "geometry": {"coordinates":[151.6925354,-32.9655342102],"type":"Point"}
}