{
  "type": "Feature",
  "properties": {
    "addr:full":"70 Nicholson St Dalby QLD 4405",
    "addr:housenumber":"70",
    "addr:postcode":"4405",
    "addr:street":"Nicholson St",
    "iso:country":"AU",
    "sg:address":"70 Nicholson St",
    "sg:city":"Dalby",
    "sg:classifiers":[
        {
            "category":"Health Services",
            "subcategory":"Chiropractor",
            "type":"Services"
        }
    ],
    "sg:phone":"+61 7 4662 3898",
    "sg:postcode":"4405",
    "sg:province":"QLD",
    "wof:name":"Hooke Chiropractic",
    "wof:placetype":"venue"
},
  "geometry": {"coordinates":[151.251296997,-27.1845264435],"type":"Point"}
}