{
  "type": "Feature",
  "properties": {
    "addr:full":"385 Olympic Hwy North Young NSW 2594",
    "addr:housenumber":"385",
    "addr:postcode":"2594",
    "addr:street":"Olympic Hwy North",
    "iso:country":"AU",
    "sg:address":"385 Olympic Hwy North",
    "sg:city":"Young",
    "sg:classifiers":[
        {
            "category":"Building & Trades",
            "subcategory":"Construction",
            "type":"Services"
        }
    ],
    "sg:phone":"+61 2 6382 4023",
    "sg:postcode":"2594",
    "sg:province":"NSW",
    "sg:tags":[
        "earth",
        "excavating",
        "moving",
        "contractor"
    ],
    "wof:name":"Young Earthworks",
    "wof:placetype":"venue"
},
  "geometry": {"coordinates":[148.343551636,-34.2949180603],"type":"Point"}
}