{
  "type": "Feature",
  "properties": {
    "iso:country":"AU",
    "sg:address":"Lot 102 Clarendon Rd",
    "sg:city":"Clarendon",
    "sg:classifiers":[
        {
            "category":"Shopping",
            "subcategory":"Crafts & Fabrics",
            "type":"Retail Goods"
        }
    ],
    "sg:phone":"+61 403 150 227",
    "sg:postcode":"5157",
    "sg:province":"SA",
    "sg:tags":[
        "supply"
    ],
    "wof:name":"Bead Boutique",
    "wof:placetype":"venue"
},
  "geometry": {"coordinates":[138.62001037600001,-35.100769043],"type":"Point"}
}