{
  "type": "Feature",
  "properties": {
    "addr:full":"19 Brooklands Drv Orange NSW 2800",
    "addr:housenumber":"19",
    "addr:postcode":"2800",
    "addr:street":"Brooklands Drv",
    "iso:country":"AU",
    "sg:address":"19 Brooklands Drv",
    "sg:city":"Orange",
    "sg:classifiers":[
        {
            "category":"Professional",
            "subcategory":"Art Services",
            "type":"Services"
        }
    ],
    "sg:phone":"+61 2 6360 2530",
    "sg:postcode":"2800",
    "sg:province":"NSW",
    "sg:tags":[
        "decorator",
        "painter"
    ],
    "wof:name":"K & B Youse",
    "wof:placetype":"venue"
},
  "geometry": {"coordinates":[149.092926025,-33.264251709],"type":"Point"}
}