{
  "type": "Feature",
  "properties": {
    "addr:full":"14 Colwyn St Wishart QLD 4122",
    "addr:housenumber":"14",
    "addr:postcode":"4122",
    "addr:street":"Colwyn St",
    "iso:country":"AU",
    "sg:address":"14 Colwyn St",
    "sg:city":"Wishart",
    "sg:classifiers":[
        {
            "category":"Real Estate",
            "subcategory":"Surveying",
            "type":"Services"
        }
    ],
    "sg:phone":"+61 7 3349 9669",
    "sg:postcode":"4122",
    "sg:province":"QLD",
    "sg:tags":[
        "surveyor",
        "land"
    ],
    "wof:name":"Laurie Boddy Drafting",
    "wof:placetype":"venue"
},
  "geometry": {"coordinates":[153.09317016599999,-27.5487880707],"type":"Point"}
}