{
  "type": "Feature",
  "properties": {
    "iso:country":"AU",
    "sg:address":"5 Anebo St",
    "sg:city":"Liverpool",
    "sg:classifiers":[
        {
            "category":"Commercial Area",
            "type":"Public Place"
        }
    ],
    "sg:phone":"+61 410 567 613",
    "sg:postcode":"2170",
    "sg:province":"NSW",
    "sg:tags":[
        "heavy",
        "carrier"
    ],
    "wof:name":"Anders Freightlines",
    "wof:placetype":"venue"
},
  "geometry": {"coordinates":[150.91142273,-33.9240074158],"type":"Point"}
}