{
  "type": "Feature",
  "properties": {
    "addr:full":"Unit 2 83 Highbury St Prospect SA 5082",
    "addr:housenumber":"83",
    "addr:postcode":"5082",
    "addr:street":"Highbury St",
    "iso:country":"AU",
    "sg:address":"Unit 2 83 Highbury St",
    "sg:city":"Prospect",
    "sg:classifiers":[
        {
            "category":"Manufacturing",
            "subcategory":"Tools & Machinery",
            "type":"Manufacturing & Wholesale Goods"
        }
    ],
    "sg:phone":"+61 8 8344 7467",
    "sg:postcode":"5082",
    "sg:province":"SA",
    "sg:tags":[
        "crankshaft",
        "cylinder",
        "grinding"
    ],
    "wof:name":"Crankshaft Grinding Specialist",
    "wof:placetype":"venue"
},
  "geometry": {"coordinates":[138.601272583,-34.8944587708],"type":"Point"}
}