{
  "type": "Feature",
  "properties": {
    "iso:country":"AU",
    "sg:address":"U 2/ 214 Campbell Rd",
    "sg:city":"Canning Vale",
    "sg:classifiers":[
        {
            "category":"Fast Food",
            "type":"Food & Drink"
        }
    ],
    "sg:phone":"+61 8 9455 1244",
    "sg:postcode":"6155",
    "sg:province":"WA",
    "sg:tags":[
        "away",
        "take"
    ],
    "wof:name":"Rani's Indian Cuisine Pty Ltd",
    "wof:placetype":"venue"
},
  "geometry": {"coordinates":[115.918022,-32.099545],"type":"Point"}
}