{
  "type": "Feature",
  "properties": {
    "addr:full":"49 Gregory Tce Spring Hill QLD 4000",
    "addr:housenumber":"49",
    "addr:postcode":"4000",
    "addr:street":"Gregory Tce",
    "iso:country":"AU",
    "sg:address":"49 Gregory Tce",
    "sg:city":"Spring Hill",
    "sg:classifiers":[
        {
            "category":"Banks & Credit Unions",
            "subcategory":"Investment Brokerage",
            "type":"Services"
        }
    ],
    "sg:phone":"+61 7 3100 8880",
    "sg:postcode":"4000",
    "sg:province":"QLD",
    "sg:tags":[
        "debt",
        "collection"
    ],
    "sg:website":"http://www.afmqld.com.au",
    "wof:name":"A F M Qld Pty Ltd",
    "wof:placetype":"venue"
},
  "geometry": {"coordinates":[153.02386474599999,-27.4625301361],"type":"Point"}
}