{
  "type": "Feature",
  "properties": {
    "addr:full":"Cnr Mary & Market St Brisbane QLD 4000",
    "addr:postcode":"4000",
    "addr:street":"Cnr;St",
    "iso:country":"AU",
    "sg:address":"Cnr Mary & Market St",
    "sg:city":"Brisbane",
    "sg:classifiers":[
        {
            "category":"Cafe",
            "type":"Food & Drink"
        }
    ],
    "sg:phone":"+61 7 3003 0411",
    "sg:postcode":"4000",
    "sg:province":"QLD",
    "wof:name":"Sugar Bar",
    "wof:placetype":"venue"
},
  "geometry": {"coordinates":[153.02970886200001,-27.4694805145],"type":"Point"}
}