{
  "type": "Feature",
  "properties": {
    "addr:full":"22 Nimerette St Bellbird Park QLD 4300",
    "addr:housenumber":"22",
    "addr:postcode":"4300",
    "addr:street":"Nimerette St",
    "iso:country":"AU",
    "sg:address":"22 Nimerette St",
    "sg:city":"Bellbird Park",
    "sg:classifiers":[
        {
            "category":"Utilities",
            "subcategory":"Water",
            "type":"Services"
        }
    ],
    "sg:phone":"+61 416 295 180",
    "sg:postcode":"4300",
    "sg:province":"QLD",
    "sg:tags":[
        "hot",
        "system"
    ],
    "wof:name":"Acorn Plumbing & Gas",
    "wof:placetype":"venue"
},
  "geometry": {"coordinates":[152.892868042,-27.6344413757],"type":"Point"}
}