{
  "type": "Feature",
  "properties": {
    "addr:full":"Coradjil Rd Simpson VIC 3266",
    "addr:postcode":"3266",
    "addr:street":"Coradjil Rd",
    "iso:country":"AU",
    "sg:address":"Coradjil Rd",
    "sg:city":"Simpson",
    "sg:classifiers":[
        {
            "category":"Farming",
            "subcategory":"Farm & Veterinary Services",
            "type":"Manufacturing & Wholesale Goods"
        }
    ],
    "sg:phone":"+61 3 5594 3487",
    "sg:postcode":"3266",
    "sg:province":"VIC",
    "sg:tags":[
        "contracting"
    ],
    "wof:name":"Treble P & K",
    "wof:placetype":"venue"
},
  "geometry": {"coordinates":[143.22262573200001,-38.4670944214],"type":"Point"}
}