{
  "type": "Feature",
  "properties": {
    "iso:country":"AU",
    "sg:address":"19 - 21 Neumann Rd",
    "sg:city":"Capalaba",
    "sg:classifiers":[
        {
            "category":"Professional",
            "type":"Services"
        }
    ],
    "sg:phone":"+61 7 3823 2463",
    "sg:postcode":"4157",
    "sg:province":"QLD",
    "sg:tags":[
        "mail",
        "contractor"
    ],
    "wof:name":"Marketforce Mail & Finishing Services",
    "wof:placetype":"venue"
},
  "geometry": {"coordinates":[153.20585632300001,-27.5335769653],"type":"Point"}
}