{
  "type": "Feature",
  "properties": {
    "addr:full":"PO Box 6046 Gorokan NSW 2263",
    "addr:postcode":"2263",
    "iso:country":"AU",
    "sg:address":"PO Box 6046",
    "sg:city":"Gorokan",
    "sg:classifiers":[
        {
            "category":"Building & Trades",
            "subcategory":"Landscaping Services",
            "type":"Services"
        }
    ],
    "sg:phone":"+61 412 468 467",
    "sg:postcode":"2263",
    "sg:province":"NSW",
    "sg:tags":[
        "designer",
        "landscape",
        "contractor"
    ],
    "wof:name":"Dirt King Excavations Bobcat & Excavator Hire",
    "wof:placetype":"venue"
},
  "geometry": {"coordinates":[151.50355500000001,-33.254799],"type":"Point"}
}