{
  "type": "Feature",
  "properties": {
    "addr:full":"10/ 47 York St Sydney NSW 2000",
    "addr:housenumber":"10 / 47",
    "addr:postcode":"2000",
    "addr:street":"York St",
    "iso:country":"AU",
    "sg:address":"10/ 47 York St",
    "sg:city":"Sydney",
    "sg:classifiers":[
        {
            "category":"Professional",
            "subcategory":"Business Services",
            "type":"Services"
        }
    ],
    "sg:phone":"+61 2 9299 1595",
    "sg:postcode":"2000",
    "sg:province":"NSW",
    "sg:tags":[
        "small",
        "advisory"
    ],
    "wof:name":"DreamWeaver Publishing",
    "wof:placetype":"venue"
},
  "geometry": {"coordinates":[151.205688477,-33.8668670654],"type":"Point"}
}