{
  "type": "Feature",
  "properties": {
    "addr:full":"231 Timberlane Drv Woodvale WA 6026",
    "addr:housenumber":"231",
    "addr:postcode":"6026",
    "addr:street":"Timberlane Drv",
    "iso:country":"AU",
    "sg:address":"231 Timberlane Drv",
    "sg:city":"Woodvale",
    "sg:classifiers":[
        {
            "category":"Health Services",
            "subcategory":"Doctor",
            "type":"Services"
        }
    ],
    "sg:phone":"+61 8 9309 3222",
    "sg:postcode":"6026",
    "sg:province":"WA",
    "sg:tags":[
        "medical",
        "practitioner"
    ],
    "wof:name":"Digwood Dr. Ken",
    "wof:placetype":"venue"
},
  "geometry": {"coordinates":[115.797210693,-31.7922668457],"type":"Point"}
}