{
  "type": "Feature",
  "properties": {
    "iso:country":"AU",
    "sg:address":"247 Ryedale Rd",
    "sg:city":"Eastwood",
    "sg:classifiers":[
        {
            "category":"Health Services",
            "subcategory":"Doctor",
            "type":"Services"
        }
    ],
    "sg:phone":"+61 2 9874 6866",
    "sg:postcode":"2122",
    "sg:province":"NSW",
    "sg:tags":[
        "medical",
        "practitioner"
    ],
    "wof:name":"Rencoret R H",
    "wof:placetype":"venue"
},
  "geometry": {"coordinates":[151.08810424800001,-33.7952575684],"type":"Point"}
}