{
  "type": "Feature",
  "properties": {
    "iso:country":"AU",
    "sg:address":"Unit 2 4a Chalkley Pl",
    "sg:city":"Bayswater",
    "sg:classifiers":[
        {
            "category":"Home & Garden",
            "subcategory":"Building Materials",
            "type":"Retail Goods"
        }
    ],
    "sg:phone":"+61 8 9370 5200",
    "sg:postcode":"6053",
    "sg:province":"WA",
    "sg:tags":[
        "fire",
        "resistant",
        "supply"
    ],
    "wof:name":"Australian Fire Door Company Pty Ltd",
    "wof:placetype":"venue"
},
  "geometry": {"coordinates":[115.919761658,-31.9019432068],"type":"Point"}
}