{
  "type": "Feature",
  "properties": {
    "addr:full":"275 Wellington Rd Mulgrave VIC 3170",
    "addr:housenumber":"275",
    "addr:postcode":"3170",
    "addr:street":"Wellington Rd",
    "iso:country":"AU",
    "sg:address":"275 Wellington Rd",
    "sg:city":"Mulgrave",
    "sg:classifiers":[
        {
            "category":"Professional",
            "subcategory":"Printing & Photocopies",
            "type":"Services"
        }
    ],
    "sg:phone":"+61 3 9561 1444",
    "sg:postcode":"3170",
    "sg:province":"VIC",
    "sg:tags":[
        "textile",
        "clothing"
    ],
    "wof:name":"GPI Panther Sports",
    "wof:placetype":"venue"
},
  "geometry": {"coordinates":[145.15817260700001,-37.9182128906],"type":"Point"}
}