{
  "type": "Feature",
  "properties": {
    "iso:country":"AU",
    "sg:address":"45 Hedwig Drv",
    "sg:city":"Mooroolbark",
    "sg:classifiers":[
        {
            "category":"Utilities",
            "subcategory":"Refuse",
            "type":"Services"
        }
    ],
    "sg:phone":"+61 3 9727 3666",
    "sg:postcode":"3138",
    "sg:province":"VIC",
    "sg:tags":[
        "remover",
        "rubbish"
    ],
    "wof:name":"Vulture Waste Services",
    "wof:placetype":"venue"
},
  "geometry": {"coordinates":[145.309646606,-37.7660140991],"type":"Point"}
}