{
  "type": "Feature",
  "properties": {
    "iso:country":"AU",
    "sg:address":"2/37-39 Spencer St",
    "sg:city":"Rose Bay",
    "sg:classifiers":[
        {
            "category":"Manufacturing",
            "subcategory":"Food",
            "type":"Manufacturing & Wholesale Goods"
        }
    ],
    "sg:phone":"+61 2 9371 0191",
    "sg:postcode":"2029",
    "sg:province":"NSW",
    "sg:tags":[
        "function",
        "catering"
    ],
    "wof:name":"Mello Gifts",
    "wof:placetype":"venue"
},
  "geometry": {"coordinates":[151.27513122600001,-33.8699073792],"type":"Point"}
}