{
  "type": "Feature",
  "properties": {
    "addr:full":"148 Wilson Rd Hinchinbrook NSW 2168",
    "addr:housenumber":"148",
    "addr:postcode":"2168",
    "addr:street":"Wilson Rd",
    "iso:country":"AU",
    "sg:address":"148 Wilson Rd",
    "sg:city":"Hinchinbrook",
    "sg:classifiers":[
        {
            "category":"Health Services",
            "subcategory":"Doctor",
            "type":"Services"
        }
    ],
    "sg:phone":"+61 2 9607 8373",
    "sg:postcode":"2168",
    "sg:province":"NSW",
    "sg:tags":[
        "medical",
        "practitioner"
    ],
    "wof:name":"Tat T",
    "wof:placetype":"venue"
},
  "geometry": {"coordinates":[150.86538696299999,-33.908000946],"type":"Point"}
}