{
  "type": "Feature",
  "properties": {
    "iso:country":"AU",
    "sg:address":"22 Loftus St",
    "sg:city":"Arncliffe",
    "sg:classifiers":[
        {
            "category":"Education",
            "subcategory":"School",
            "type":"Public Place"
        }
    ],
    "sg:phone":"+61 2 9567 6196",
    "sg:postcode":"2205",
    "sg:province":"NSW",
    "wof:name":"Cairnsfoot Special School",
    "wof:placetype":"venue"
},
  "geometry": {"coordinates":[151.14454699999999,-33.931629],"type":"Point"}
}