{
  "type": "Feature",
  "properties": {
    "addr:full":"1 Bolingbroke Ave Devon Park SA 5008",
    "addr:housenumber":"1",
    "addr:postcode":"5008",
    "addr:street":"Bolingbroke Ave",
    "iso:country":"AU",
    "sg:address":"1 Bolingbroke Ave",
    "sg:city":"Devon Park",
    "sg:classifiers":[
        {
            "category":"Farming",
            "subcategory":"Crops",
            "type":"Manufacturing & Wholesale Goods"
        }
    ],
    "sg:phone":"+61 8 8340 9955",
    "sg:postcode":"5008",
    "sg:province":"SA",
    "sg:tags":[
        "warehousing"
    ],
    "sg:website":"http://www.easyfill.com",
    "wof:name":"Easyfill",
    "wof:placetype":"venue"
},
  "geometry": {"coordinates":[138.58041399999999,-34.889408],"type":"Point"}
}