{
  "type": "Feature",
  "properties": {
    "iso:country":"AU",
    "sg:address":"103 Fox St St",
    "sg:city":"Albans",
    "sg:classifiers":[
        {
            "category":"Retail",
            "subcategory":"Storage",
            "type":"Services"
        }
    ],
    "sg:phone":"+61 425 750 048",
    "sg:postcode":"3021",
    "sg:province":"VIC",
    "sg:tags":[
        "removal",
        "furniture"
    ],
    "wof:name":"Sammys Removals",
    "wof:placetype":"venue"
},
  "geometry": {"coordinates":[144.804489,-37.73288],"type":"Point"}
}