{
  "type": "Feature",
  "properties": {
    "addr:full":"153 Kylie Ave Ferny Hills QLD 4055",
    "addr:housenumber":"153",
    "addr:postcode":"4055",
    "addr:street":"Kylie Ave",
    "iso:country":"AU",
    "sg:address":"153 Kylie Ave",
    "sg:city":"Ferny Hills",
    "sg:classifiers":[
        {
            "category":"Professional",
            "subcategory":"Accounting & Tax Preparation",
            "type":"Services"
        }
    ],
    "sg:phone":"+61 7 3851 2133",
    "sg:postcode":"4055",
    "sg:province":"QLD",
    "sg:tags":[
        "bookkeeping"
    ],
    "wof:name":"MacNamara W T",
    "wof:placetype":"venue"
},
  "geometry": {"coordinates":[152.940673828,-27.4022388458],"type":"Point"}
}