{
  "type": "Feature",
  "properties": {
    "addr:full":"Toolooa Shopping Centre, Sh 10/121 Toolooa St Gladstone South QLD 4680",
    "addr:housenumber":"121",
    "addr:postcode":"4680",
    "addr:street":"Sh 10 /;Toolooa St",
    "iso:country":"AU",
    "sg:address":"Toolooa Shopping Centre, Sh 10/121 Toolooa St",
    "sg:city":"Gladstone South",
    "sg:classifiers":[
        {
            "category":"Personal",
            "subcategory":"Beauty Salon",
            "type":"Services"
        }
    ],
    "sg:phone":"+61 7 4972 9334",
    "sg:postcode":"4680",
    "sg:province":"QLD",
    "sg:tags":[
        "hairdresser"
    ],
    "wof:name":"Innovations Hair Studio",
    "wof:placetype":"venue"
},
  "geometry": {"coordinates":[151.26956176799999,-23.8577060699],"type":"Point"}
}