{
  "type": "Feature",
  "properties": {
    "iso:country":"AU",
    "sg:address":"PO Box 1246",
    "sg:city":"Coffs Harbour",
    "sg:classifiers":[
        {
            "category":"Communications",
            "subcategory":"News Services",
            "type":"Services"
        }
    ],
    "sg:phone":"+61 407 249 335",
    "sg:postcode":"2450",
    "sg:province":"NSW",
    "sg:tags":[
        "information",
        "tourist",
        "attractions"
    ],
    "wof:name":"Sandy Beach Almanac",
    "wof:placetype":"venue"
},
  "geometry": {"coordinates":[153.115158,-30.29701],"type":"Point"}
}