{
  "type": "Feature",
  "properties": {
    "iso:country":"AU",
    "sg:address":"3 English St",
    "sg:city":"Cronulla",
    "sg:classifiers":[
        {
            "category":"Real Estate",
            "subcategory":"Architect",
            "type":"Services"
        }
    ],
    "sg:phone":"+61 2 9523 3855",
    "sg:postcode":"2230",
    "sg:province":"NSW",
    "wof:name":"Elliot R J",
    "wof:placetype":"venue"
},
  "geometry": {"coordinates":[151.13613891599999,-34.049571991],"type":"Point"}
}