{
  "type": "Feature",
  "properties": {
    "addr:full":"1 Sidney St West End QLD 4810",
    "addr:housenumber":"1",
    "addr:postcode":"4810",
    "addr:street":"Sidney St",
    "iso:country":"AU",
    "sg:address":"1 Sidney St",
    "sg:city":"West End",
    "sg:classifiers":[
        {
            "category":"Wholesale",
            "subcategory":"Medical Equipment & Supplies",
            "type":"Manufacturing & Wholesale Goods"
        }
    ],
    "sg:phone":"+61 7 4721 2234",
    "sg:postcode":"4810",
    "sg:province":"QLD",
    "sg:tags":[
        "embroidery"
    ],
    "wof:name":"Spotless Creations",
    "wof:placetype":"venue"
},
  "geometry": {"coordinates":[146.79162600000001,-19.260502],"type":"Point"}
}