{
  "type": "Feature",
  "properties": {
    "addr:full":"4 Alison Crt Wodonga VIC 3690",
    "addr:housenumber":"4",
    "addr:postcode":"3690",
    "addr:street":"Alison Crt",
    "iso:country":"AU",
    "sg:address":"4 Alison Crt",
    "sg:city":"Wodonga",
    "sg:classifiers":[
        {
            "category":"Train Station",
            "subcategory":"Light Rail",
            "type":"Transportation"
        }
    ],
    "sg:phone":"+61 438 961 689",
    "sg:postcode":"3690",
    "sg:province":"VIC",
    "sg:tags":[
        "equipment",
        "energy",
        "solar"
    ],
    "wof:name":"Tidyworks",
    "wof:placetype":"venue"
},
  "geometry": {"coordinates":[146.880126953,-36.1151008606],"type":"Point"}
}