{
  "type": "Feature",
  "properties": {
    "iso:country":"AU",
    "sg:address":"13 Kearns Crs",
    "sg:city":"Applecross",
    "sg:classifiers":[
        {
            "category":"Banks & Credit Unions",
            "subcategory":"Bank",
            "type":"Services"
        }
    ],
    "sg:phone":"+61 13 20 32",
    "sg:postcode":"6153",
    "sg:province":"WA",
    "wof:name":"Westpac",
    "wof:placetype":"venue"
},
  "geometry": {"coordinates":[115.834808,-32.010342],"type":"Point"}
}