{
  "type": "Feature",
  "properties": {
    "addr:full":"Unit 6 43 Lawnton Pocket Rd Lawnton QLD 4501",
    "addr:housenumber":"43",
    "addr:postcode":"4501",
    "addr:street":"Pocket Rd",
    "iso:country":"AU",
    "sg:address":"Unit 6 43 Lawnton Pocket Rd",
    "sg:city":"Lawnton",
    "sg:phone":"+61 7 3889 2469",
    "sg:postcode":"4501",
    "sg:province":"QLD",
    "wof:name":"Briztanks Pty Ltd",
    "wof:placetype":"venue"
},
  "geometry": {"coordinates":[152.99302673299999,-27.2821903229],"type":"Point"}
}