{
  "type": "Feature",
  "properties": {
    "addr:full":"82 Nandi Ave Frenchs Forest NSW 2086",
    "addr:housenumber":"82",
    "addr:postcode":"2086",
    "addr:street":"Nandi Ave",
    "iso:country":"AU",
    "sg:address":"82 Nandi Ave",
    "sg:city":"Frenchs Forest",
    "sg:classifiers":[
        {
            "category":"Home & Garden",
            "subcategory":"Building Materials",
            "type":"Retail Goods"
        }
    ],
    "sg:phone":"+61 2 9451 0271",
    "sg:postcode":"2086",
    "sg:province":"NSW",
    "sg:tags":[
        "fitting",
        "door"
    ],
    "wof:name":"Ayling John Maintenance Services",
    "wof:placetype":"venue"
},
  "geometry": {"coordinates":[151.23846435600001,-33.7459259033],"type":"Point"}
}