{
  "type": "Feature",
  "properties": {
    "addr:full":"28- 38 Transport Drv Somerton VIC 3062",
    "addr:housenumber":"38",
    "addr:postcode":"3062",
    "addr:street":"Transport Drv",
    "iso:country":"AU",
    "sg:address":"28- 38 Transport Drv",
    "sg:city":"Somerton",
    "sg:classifiers":[
        {
            "category":"Wholesale",
            "subcategory":"Chemicals & Plastics",
            "type":"Manufacturing & Wholesale Goods"
        }
    ],
    "sg:phone":"+61 3 9303 3900",
    "sg:postcode":"3062",
    "sg:province":"VIC",
    "sg:tags":[
        "extruders"
    ],
    "wof:name":"PCC Packaging",
    "wof:placetype":"venue"
},
  "geometry": {"coordinates":[144.95622253400001,-37.6376724243],"type":"Point"}
}