{
  "type": "Feature",
  "properties": {
    "addr:full":"11 Eaton Pl Geraldton WA 6530",
    "addr:housenumber":"11",
    "addr:postcode":"6530",
    "addr:street":"Eaton Pl",
    "iso:country":"AU",
    "sg:address":"11 Eaton Pl",
    "sg:city":"Geraldton",
    "sg:classifiers":[
        {
            "category":"Retail",
            "subcategory":"Auto Repair",
            "type":"Services"
        }
    ],
    "sg:phone":"+61 8 9921 2000",
    "sg:postcode":"6530",
    "sg:province":"WA",
    "sg:tags":[
        "repairer",
        "motor",
        "engineer"
    ],
    "wof:name":"D & J Mechanic",
    "wof:placetype":"venue"
},
  "geometry": {"coordinates":[114.625442505,-28.7709884644],"type":"Point"}
}