{
  "type": "Feature",
  "properties": {
    "addr:full":"38b Autumn St Geelong West VIC 3218",
    "addr:housenumber":"38b",
    "addr:postcode":"3218",
    "addr:street":"Autumn St",
    "iso:country":"AU",
    "sg:address":"38b Autumn St",
    "sg:city":"Geelong West",
    "sg:classifiers":[
        {
            "category":"Manufacturing",
            "subcategory":"Electronics",
            "type":"Manufacturing & Wholesale Goods"
        }
    ],
    "sg:phone":"+61 3 5223 1088",
    "sg:postcode":"3218",
    "sg:province":"VIC",
    "sg:tags":[
        "wholesaler",
        "equipment",
        "part",
        "mfrs",
        "refrigeration"
    ],
    "wof:name":"Actrol Parts",
    "wof:placetype":"venue"
},
  "geometry": {"coordinates":[144.35122680699999,-38.1433258057],"type":"Point"}
}