{
  "type": "Feature",
  "properties": {
    "iso:country":"AU",
    "sg:address":"30 Beverage Drv",
    "sg:city":"Tullamarine",
    "sg:classifiers":[
        {
            "category":"Shopping",
            "subcategory":"Computers & Home Electronics",
            "type":"Retail Goods"
        }
    ],
    "sg:phone":"+61 3 9335 4600",
    "sg:postcode":"3043",
    "sg:province":"VIC",
    "sg:tags":[
        "equipment",
        "supply"
    ],
    "wof:name":"Software Supplies N.Z. Ltd",
    "wof:placetype":"venue"
},
  "geometry": {"coordinates":[144.86346435600001,-37.7187538147],"type":"Point"}
}