{
  "type": "Feature",
  "properties": {
    "addr:full":"140 Hogan St Tatura VIC 3616",
    "addr:housenumber":"140",
    "addr:postcode":"3616",
    "addr:street":"Hogan St",
    "iso:country":"AU",
    "sg:address":"140 Hogan St",
    "sg:city":"Tatura",
    "sg:classifiers":[
        {
            "category":"Real Estate",
            "subcategory":"Real Estate Agent",
            "type":"Services"
        }
    ],
    "sg:phone":"+61 3 5824 2300",
    "sg:postcode":"3616",
    "sg:province":"VIC",
    "wof:name":"Settlers Reality (Tatura)",
    "wof:placetype":"venue"
},
  "geometry": {"coordinates":[145.22764587399999,-36.4402427673],"type":"Point"}
}