{
  "type": "Feature",
  "properties": {
    "addr:full":"Suite 8, 7- 9 St. George Crs Faulconbridge NSW 2776",
    "addr:housenumber":"7 9",
    "addr:postcode":"2776",
    "addr:street":"St. George Crs",
    "iso:country":"AU",
    "sg:address":"Suite 8, 7- 9 St. George Crs",
    "sg:city":"Faulconbridge",
    "sg:classifiers":[
        {
            "category":"Health Services",
            "subcategory":"Health Practitioner",
            "type":"Services"
        }
    ],
    "sg:phone":"+61 2 4751 2150",
    "sg:postcode":"2776",
    "sg:province":"NSW",
    "sg:tags":[
        "physiotherapist"
    ],
    "wof:name":"Lower Mountains Physiotherapy",
    "wof:placetype":"venue"
},
  "geometry": {"coordinates":[151.08506774899999,-33.9644165039],"type":"Point"}
}