{
  "type": "Feature",
  "properties": {
    "iso:country":"AU",
    "sg:address":"45 May St",
    "sg:city":"Godwin Beach",
    "sg:classifiers":[
        {
            "category":"Building & Trades",
            "subcategory":"Cleaning & Sanitation",
            "type":"Services"
        }
    ],
    "sg:phone":"+61 1800 656 357",
    "sg:postcode":"4511",
    "sg:province":"QLD",
    "sg:tags":[
        "window"
    ],
    "wof:name":"B & B Clearvision Window Cleaning Service",
    "wof:placetype":"venue"
},
  "geometry": {"coordinates":[153.11203,-27.085136],"type":"Point"}
}