{
  "type": "Feature",
  "properties": {
    "addr:full":"29 Bonniebrae St Wynnum West QLD 4178",
    "addr:housenumber":"29",
    "addr:postcode":"4178",
    "addr:street":"Bonniebrae St",
    "iso:country":"AU",
    "sg:address":"29 Bonniebrae St",
    "sg:city":"Wynnum West",
    "sg:classifiers":[
        {
            "category":"Banks & Credit Unions",
            "subcategory":"Investment Brokerage",
            "type":"Services"
        }
    ],
    "sg:phone":"+61 7 3393 4444",
    "sg:postcode":"4178",
    "sg:province":"QLD",
    "sg:tags":[
        "care",
        "day",
        "family",
        "child"
    ],
    "wof:name":"Bayside Family Day Care",
    "wof:placetype":"venue"
},
  "geometry": {"coordinates":[153.158126831,-27.4614906311],"type":"Point"}
}