{
  "type": "Feature",
  "properties": {
    "addr:full":"361 Stumpy Gully Rd Balnarring VIC 3926",
    "addr:housenumber":"361",
    "addr:postcode":"3926",
    "addr:street":"Stumpy Gully Rd",
    "iso:country":"AU",
    "sg:address":"361 Stumpy Gully Rd",
    "sg:city":"Balnarring",
    "sg:classifiers":[
        {
            "category":"Farming",
            "subcategory":"Nursery",
            "type":"Manufacturing & Wholesale Goods"
        }
    ],
    "sg:phone":"+61 3 5983 5688",
    "sg:postcode":"3926",
    "sg:province":"VIC",
    "wof:name":"Toad Gully Growers",
    "wof:placetype":"venue"
},
  "geometry": {"coordinates":[145.127044678,-38.3400497437],"type":"Point"}
}