{
  "type": "Feature",
  "properties": {
    "addr:full":"60 Doctor Gully Rd Doreen VIC 3754",
    "addr:housenumber":"60",
    "addr:postcode":"3754",
    "addr:street":"Doctor Gully Rd",
    "iso:country":"AU",
    "sg:address":"60 Doctor Gully Rd",
    "sg:city":"Doreen",
    "sg:classifiers":[
        {
            "category":"Food & Beverages",
            "subcategory":"Groceries & Convenience Stores",
            "type":"Retail Goods"
        }
    ],
    "sg:phone":"+61 3 9717 3413",
    "sg:postcode":"3754",
    "sg:province":"VIC",
    "sg:tags":[
        "merchant",
        "egg"
    ],
    "wof:name":"Yarrambat Doreen Farm Fresh Eggs",
    "wof:placetype":"venue"
},
  "geometry": {"coordinates":[145.14660599999999,-37.606812],"type":"Point"}
}