{
  "type": "Feature",
  "properties": {
    "addr:full":"3 Castella St Lilydale VIC 3140",
    "addr:housenumber":"3",
    "addr:postcode":"3140",
    "addr:street":"Castella St",
    "iso:country":"AU",
    "sg:address":"3 Castella St",
    "sg:city":"Lilydale",
    "sg:classifiers":[
        {
            "category":"Recreation",
            "subcategory":"Fishing",
            "type":"Entertainment"
        }
    ],
    "sg:phone":"+61 3 9735 3987",
    "sg:postcode":"3140",
    "sg:province":"VIC",
    "sg:tags":[
        "tackle"
    ],
    "wof:name":"Lilydale Lakes Fishing Tackle",
    "wof:placetype":"venue"
},
  "geometry": {"coordinates":[145.35316467300001,-37.7574615479],"type":"Point"}
}