{
  "type": "Feature",
  "properties": {
    "iso:country":"AU",
    "sg:address":"125 Nelson St",
    "sg:city":"Fairfield",
    "sg:classifiers":[
        {
            "category":"Building & Trades",
            "subcategory":"Construction",
            "type":"Services"
        }
    ],
    "sg:phone":"+61 2 9728 2076",
    "sg:postcode":"2165",
    "sg:province":"NSW",
    "sg:tags":[
        "contractor"
    ],
    "wof:name":"United Design & Constructions Pty Ltd",
    "wof:placetype":"venue"
},
  "geometry": {"coordinates":[150.942962647,-33.8684692383],"type":"Point"}
}