{
  "type": "Feature",
  "properties": {
    "addr:full":"St Leonards NSW 2065",
    "addr:postcode":"2065",
    "iso:country":"AU",
    "sg:address":"St",
    "sg:city":"Leonards",
    "sg:classifiers":[
        {
            "category":"Building & Trades",
            "subcategory":"Construction",
            "type":"Services"
        }
    ],
    "sg:phone":"+61 405 674 919",
    "sg:postcode":"2065",
    "sg:province":"NSW",
    "sg:tags":[
        "welding"
    ],
    "wof:name":"Mobility Welding",
    "wof:placetype":"venue"
},
  "geometry": {"coordinates":[151.197509766,-33.8237915039],"type":"Point"}
}