{
  "type": "Feature",
  "properties": {
    "iso:country":"AU",
    "sg:address":"Factory 3 Grantville Drv",
    "sg:city":"Grantville",
    "sg:classifiers":[
        {
            "category":"Wholesale",
            "subcategory":"Painting Supplies",
            "type":"Manufacturing & Wholesale Goods"
        }
    ],
    "sg:phone":"+61 3 5678 8711",
    "sg:postcode":"3984",
    "sg:province":"VIC",
    "sg:tags":[
        "product",
        "cleaning"
    ],
    "wof:name":"X-Stream Quality Cleaning Products",
    "wof:placetype":"venue"
},
  "geometry": {"coordinates":[145.525192261,-38.4112701416],"type":"Point"}
}