{
  "type": "Feature",
  "properties": {
    "addr:full":"Acacia Ave Leeton NSW 2705",
    "addr:postcode":"2705",
    "addr:street":"Acacia Ave",
    "iso:country":"AU",
    "sg:address":"Acacia Ave",
    "sg:city":"Leeton",
    "sg:classifiers":[
        {
            "category":"Home & Garden",
            "subcategory":"Garden Supply",
            "type":"Retail Goods"
        }
    ],
    "sg:phone":"+61 2 6953 5323",
    "sg:postcode":"2705",
    "sg:province":"NSW",
    "sg:tags":[
        "fertilizer"
    ],
    "wof:name":"Smith's Fertilizer & Transport Pty Ltd",
    "wof:placetype":"venue"
},
  "geometry": {"coordinates":[146.40620422399999,-34.5520401001],"type":"Point"}
}