{
  "type": "Feature",
  "properties": {
    "addr:full":"Fcty4/ 28-30 Keon Pde Thomastown VIC 3074",
    "addr:housenumber":"28-30",
    "addr:postcode":"3074",
    "addr:street":"Keon Pde",
    "iso:country":"AU",
    "sg:address":"Fcty4/ 28-30 Keon Pde",
    "sg:city":"Thomastown",
    "sg:classifiers":[
        {
            "category":"Real Estate",
            "subcategory":"Real Estate Agent",
            "type":"Services"
        }
    ],
    "sg:phone":"+61 3 9460 8243",
    "sg:postcode":"3074",
    "sg:province":"VIC",
    "sg:tags":[
        "export"
    ],
    "wof:name":"Auscom Pty Ltd",
    "wof:placetype":"venue"
},
  "geometry": {"coordinates":[145.01580810600001,-37.6949882507],"type":"Point"}
}