{
  "type": "Feature",
  "properties": {
    "addr:full":"33 Glenwood Ave Helena Valley WA 6056",
    "addr:housenumber":"33",
    "addr:postcode":"6056",
    "addr:street":"Glenwood Ave",
    "iso:country":"AU",
    "sg:address":"33 Glenwood Ave",
    "sg:city":"Helena Valley",
    "sg:classifiers":[
        {
            "category":"Building & Trades",
            "subcategory":"Landscaping Services",
            "type":"Services"
        }
    ],
    "sg:phone":"+61 417 517 387",
    "sg:postcode":"6056",
    "sg:province":"WA",
    "sg:tags":[
        "designer",
        "landscape",
        "contractor"
    ],
    "wof:name":"Ash Contracting",
    "wof:placetype":"venue"
},
  "geometry": {"coordinates":[116.044372559,-31.9178142548],"type":"Point"}
}