{
  "type": "Feature",
  "properties": {
    "addr:full":"Wollola St Jericho QLD 4702",
    "addr:postcode":"4702",
    "addr:street":"St",
    "iso:country":"AU",
    "sg:address":"Wollola St",
    "sg:city":"Jericho",
    "sg:classifiers":[
        {
            "category":"Building & Trades",
            "subcategory":"Landscaping Services",
            "type":"Services"
        }
    ],
    "sg:phone":"+61 7 4651 4107",
    "sg:postcode":"4702",
    "sg:province":"QLD",
    "sg:tags":[
        "grazier"
    ],
    "wof:name":"Wells L F & A D",
    "wof:placetype":"venue"
},
  "geometry": {"coordinates":[145.690307617,-22.9983272552],"type":"Point"}
}