{
  "type": "Feature",
  "properties": {
    "addr:full":"56 Burnett St Buderim QLD 4556",
    "addr:housenumber":"56",
    "addr:postcode":"4556",
    "addr:street":"Burnett St",
    "iso:country":"AU",
    "sg:address":"56 Burnett St",
    "sg:city":"Buderim",
    "sg:classifiers":[
        {
            "category":"Shopping",
            "subcategory":"Clothing, Apparel, & Fashions",
            "type":"Retail Goods"
        }
    ],
    "sg:phone":"+61 7 5445 6616",
    "sg:postcode":"4556",
    "sg:province":"QLD",
    "sg:tags":[
        "boutique"
    ],
    "wof:name":"Gingers Boutique",
    "wof:placetype":"venue"
},
  "geometry": {"coordinates":[153.04994201700001,-26.6861915588],"type":"Point"}
}