{
  "type": "Feature",
  "properties": {
    "iso:country":"AU",
    "sg:address":"279 Dundas St",
    "sg:city":"Preston",
    "sg:classifiers":[
        {
            "category":"Home & Garden",
            "subcategory":"Carpets & Floor Coverings",
            "type":"Retail Goods"
        }
    ],
    "sg:phone":"+61 3 9484 0454",
    "sg:postcode":"3072",
    "sg:province":"VIC",
    "sg:tags":[
        "tile",
        "wall"
    ],
    "wof:name":"Alan Patrick Pty Ltd",
    "wof:placetype":"venue"
},
  "geometry": {"coordinates":[145.029693603,-37.7554016113],"type":"Point"}
}