{
  "type": "Feature",
  "properties": {
    "addr:full":"246 Marsden Rd Carlingford NSW 2118",
    "addr:housenumber":"246",
    "addr:postcode":"2118",
    "addr:street":"Marsden Rd",
    "iso:country":"AU",
    "sg:address":"246 Marsden Rd",
    "sg:city":"Carlingford",
    "sg:classifiers":[
        {
            "category":"Building & Trades",
            "subcategory":"Construction",
            "type":"Services"
        }
    ],
    "sg:phone":"+61 2 9804 7383",
    "sg:postcode":"2118",
    "sg:province":"NSW",
    "sg:tags":[
        "renovation",
        "alterations",
        "extension",
        "contractor"
    ],
    "wof:name":"M J Younis Constructions",
    "wof:placetype":"venue"
},
  "geometry": {"coordinates":[151.06312560999999,-33.7899971008],"type":"Point"}
}