{
  "type": "Feature",
  "properties": {
    "addr:full":"4365 Helena Valley Rd Helena Valley WA 6056",
    "addr:housenumber":"4365",
    "addr:postcode":"6056",
    "addr:street":"Helena Valley Rd",
    "iso:country":"AU",
    "sg:address":"4365 Helena Valley Rd",
    "sg:city":"Helena Valley",
    "sg:classifiers":[
        {
            "category":"Real Estate",
            "subcategory":"Architect",
            "type":"Services"
        }
    ],
    "sg:phone":"+61 8 9255 1397",
    "sg:postcode":"6056",
    "sg:province":"WA",
    "sg:tags":[
        "building",
        "designer"
    ],
    "wof:name":"Ipkendanz Michael",
    "wof:placetype":"venue"
},
  "geometry": {"coordinates":[116.05683136,-31.9276199341],"type":"Point"}
}