{
  "type": "Feature",
  "properties": {
    "addr:full":"Nockolds St Walpole WA 6398",
    "addr:postcode":"6398",
    "addr:street":"St",
    "iso:country":"AU",
    "sg:address":"Nockolds St",
    "sg:city":"Walpole",
    "sg:classifiers":[
        {
            "category":"Food & Beverages",
            "subcategory":"Supermarket",
            "type":"Retail Goods"
        }
    ],
    "sg:phone":"+61 8 9840 1031",
    "sg:postcode":"6398",
    "sg:province":"WA",
    "sg:tags":[
        "grocery",
        "store"
    ],
    "wof:name":"IGA Supermarkets",
    "wof:placetype":"venue"
},
  "geometry": {"coordinates":[116.734077454,-34.975692749],"type":"Point"}
}