{
  "type": "Feature",
  "properties": {
    "iso:country":"AU",
    "sg:address":"13 Gerona Crt",
    "sg:city":"Keilor",
    "sg:classifiers":[
        {
            "category":"Professional",
            "subcategory":"Art Services",
            "type":"Services"
        }
    ],
    "sg:phone":"+61 407 899 767",
    "sg:postcode":"3036",
    "sg:province":"VIC",
    "sg:tags":[
        "picture",
        "frame",
        "framing"
    ],
    "wof:name":"Aylesbury Picture Frames",
    "wof:placetype":"venue"
},
  "geometry": {"coordinates":[144.833801,-37.714828],"type":"Point"}
}