{
  "type": "Feature",
  "properties": {
    "iso:country":"AU",
    "sg:address":"142 Wommara Ave",
    "sg:city":"Belmont North",
    "sg:classifiers":[
        {
            "category":"Building & Trades",
            "subcategory":"Construction",
            "type":"Services"
        }
    ],
    "sg:phone":"+61 2 4945 3444",
    "sg:postcode":"2280",
    "sg:province":"NSW",
    "sg:tags":[
        "concrete",
        "contractor"
    ],
    "wof:name":"D&#039;Accione C J & A",
    "wof:placetype":"venue"
},
  "geometry": {"coordinates":[151.67515564000001,-33.0216598511],"type":"Point"}
}