{
  "type": "Feature",
  "properties": {
    "iso:country":"AU",
    "sg:address":"Bootooloo Rd",
    "sg:city":"Delta",
    "sg:classifiers":[
        {
            "category":"Farming",
            "subcategory":"Farm",
            "type":"Manufacturing & Wholesale Goods"
        }
    ],
    "sg:phone":"+61 7 4785 2172",
    "sg:postcode":"4805",
    "sg:province":"QLD",
    "sg:tags":[
        "farmer"
    ],
    "wof:name":"Wright S",
    "wof:placetype":"venue"
},
  "geometry": {"coordinates":[148.206573486,-20.0175571442],"type":"Point"}
}