{
  "type": "Feature",
  "properties": {
    "addr:full":"10 Brolga Crs Wandana Heights VIC 3216",
    "addr:housenumber":"10",
    "addr:postcode":"3216",
    "addr:street":"Brolga Crs",
    "iso:country":"AU",
    "sg:address":"10 Brolga Crs",
    "sg:city":"Wandana Heights",
    "sg:classifiers":[
        {
            "category":"Banks & Credit Unions",
            "subcategory":"Bank",
            "type":"Services"
        }
    ],
    "sg:phone":"+61 3 5244 3460",
    "sg:postcode":"3216",
    "sg:province":"VIC",
    "sg:tags":[
        "broker",
        "mortgage"
    ],
    "wof:name":"Mobile Mortgage Market",
    "wof:placetype":"venue"
},
  "geometry": {"coordinates":[144.299850464,-38.1742782593],"type":"Point"}
}