{
  "type": "Feature",
  "properties": {
    "addr:full":"4 Hinkins St Moonee Ponds VIC 3039",
    "addr:housenumber":"4",
    "addr:postcode":"3039",
    "addr:street":"Hinkins St",
    "iso:country":"AU",
    "sg:address":"4 Hinkins St",
    "sg:city":"Moonee Ponds",
    "sg:classifiers":[
        {
            "category":"Retail",
            "subcategory":"Auto Repair",
            "type":"Services"
        }
    ],
    "sg:phone":"+61 3 9370 3158",
    "sg:postcode":"3039",
    "sg:province":"VIC",
    "sg:tags":[
        "repairer",
        "motor",
        "engineer"
    ],
    "wof:name":"Moonee Valley Auto Repairs",
    "wof:placetype":"venue"
},
  "geometry": {"coordinates":[144.92607100000001,-37.768391],"type":"Point"}
}