{
  "type": "Feature",
  "properties": {
    "addr:full":"Cnr Pearson & Smart Sts Charlestown NSW 2290",
    "addr:postcode":"2290",
    "addr:street":"Cnr",
    "iso:country":"AU",
    "sg:address":"Cnr Pearson & Smart Sts",
    "sg:city":"Charlestown",
    "sg:classifiers":[
        {
            "category":"Health Services",
            "subcategory":"Dentist",
            "type":"Services"
        }
    ],
    "sg:phone":"+61 2 4943 4299",
    "sg:postcode":"2290",
    "sg:province":"NSW",
    "wof:name":"Abrahams Alex",
    "wof:placetype":"venue"
},
  "geometry": {"coordinates":[151.69670105,-32.9614181519],"type":"Point"}
}