{
  "type": "Feature",
  "properties": {
    "addr:full":"248 Shellharbour Rd Warilla NSW 2528",
    "addr:housenumber":"248",
    "addr:postcode":"2528",
    "addr:street":"Shellharbour Rd",
    "iso:country":"AU",
    "sg:address":"248 Shellharbour Rd",
    "sg:city":"Warilla",
    "sg:classifiers":[
        {
            "category":"Retail",
            "subcategory":"Auto Repair",
            "type":"Services"
        }
    ],
    "sg:phone":"+61 2 4296 2599",
    "sg:postcode":"2528",
    "sg:province":"NSW",
    "sg:tags":[
        "clutch",
        "brake"
    ],
    "wof:name":"FM Discount Spares (Warilla)",
    "wof:placetype":"venue"
},
  "geometry": {"coordinates":[150.85968017600001,-34.5595397949],"type":"Point"}
}