{
  "type": "Feature",
  "properties": {
    "addr:full":"111 Curragundi Rd Jindalee QLD 4074",
    "addr:housenumber":"111",
    "addr:postcode":"4074",
    "addr:street":"Curragundi Rd",
    "iso:country":"AU",
    "sg:address":"111 Curragundi Rd",
    "sg:city":"Jindalee",
    "sg:classifiers":[
        {
            "category":"Professional",
            "subcategory":"Employment Agencies",
            "type":"Services"
        }
    ],
    "sg:phone":"+61 7 3279 2634",
    "sg:postcode":"4074",
    "sg:province":"QLD",
    "sg:tags":[
        "occupational",
        "therapist"
    ],
    "wof:name":"Lyons Enza-Dynamic Learning & Health Centre",
    "wof:placetype":"venue"
},
  "geometry": {"coordinates":[152.93223571799999,-27.5329723358],"type":"Point"}
}