{
  "type": "Feature",
  "properties": {
    "iso:country":"AU",
    "sg:address":"Lot 1723/ Bingham Rd",
    "sg:city":"Bullsbrook",
    "sg:classifiers":[
        {
            "category":"Farming",
            "subcategory":"Berry Farm",
            "type":"Manufacturing & Wholesale Goods"
        }
    ],
    "sg:phone":"+61 8 9571 2295",
    "sg:postcode":"6084",
    "sg:province":"WA",
    "sg:tags":[
        "fruit",
        "grower"
    ],
    "wof:name":"Sweet To Eat",
    "wof:placetype":"venue"
},
  "geometry": {"coordinates":[115.969581604,-31.6389522552],"type":"Point"}
}