{
  "type": "Feature",
  "properties": {
    "addr:full":"Ste 2/ 1725 Pittwater Rd Mona Vale NSW 2103",
    "addr:housenumber":"/ 1725",
    "addr:postcode":"2103",
    "addr:street":"Pittwater Rd",
    "iso:country":"AU",
    "sg:address":"Ste 2/ 1725 Pittwater Rd",
    "sg:city":"Mona Vale",
    "sg:classifiers":[
        {
            "category":"Health Services",
            "subcategory":"Health Practitioner",
            "type":"Services"
        }
    ],
    "sg:phone":"+61 2 9999 2211",
    "sg:postcode":"2103",
    "sg:province":"NSW",
    "sg:tags":[
        "homoeopath"
    ],
    "wof:name":"Hardwick Margot",
    "wof:placetype":"venue"
},
  "geometry": {"coordinates":[151.30250549300001,-33.6803970337],"type":"Point"}
}