{
  "type": "Feature",
  "properties": {
    "addr:full":"Unit 6 47 Misgrave Rd Coopers Plains QLD 4108",
    "addr:housenumber":"47",
    "addr:postcode":"4108",
    "addr:street":"Misgrave Rd",
    "iso:country":"AU",
    "sg:address":"Unit 6 47 Misgrave Rd",
    "sg:city":"Coopers Plains",
    "sg:classifiers":[
        {
            "category":"Building & Trades",
            "subcategory":"Construction",
            "type":"Services"
        }
    ],
    "sg:phone":"+61 7 3711 3644",
    "sg:postcode":"4108",
    "sg:province":"QLD",
    "sg:tags":[
        "industrial",
        "commercial",
        "air conditioning"
    ],
    "wof:name":"Associated Air Qld Pty Ltd",
    "wof:placetype":"venue"
},
  "geometry": {"coordinates":[153.02540588400001,-27.5612373352],"type":"Point"}
}