{
  "type": "Feature",
  "properties": {
    "iso:country":"AU",
    "sg:address":"130 Norrie Ave",
    "sg:city":"Whyalla Playford",
    "sg:classifiers":[
        {
            "category":"Wholesale",
            "subcategory":"Machinery & Supplies",
            "type":"Manufacturing & Wholesale Goods"
        }
    ],
    "sg:phone":"+61 8 8645 8000",
    "sg:postcode":"5600",
    "sg:province":"SA",
    "sg:tags":[
        "equipment",
        "hydraulic"
    ],
    "wof:name":"Whyalla Hose & Fitting Services",
    "wof:placetype":"venue"
},
  "geometry": {"coordinates":[137.551666,-33.021339],"type":"Point"}
}