{
  "type": "Feature",
  "properties": {
    "addr:full":"121 Newmarket Rd Windsor QLD 4030",
    "addr:housenumber":"121",
    "addr:postcode":"4030",
    "addr:street":"Newmarket Rd",
    "iso:country":"AU",
    "sg:address":"121 Newmarket Rd",
    "sg:city":"Windsor",
    "sg:classifiers":[
        {
            "category":"Taxi",
            "type":"Transportation"
        }
    ],
    "sg:phone":"+61 7 3857 5595",
    "sg:postcode":"4030",
    "sg:province":"QLD",
    "sg:tags":[
        "cab"
    ],
    "wof:name":"Hughes Chauffeured Limousines",
    "wof:placetype":"venue"
},
  "geometry": {"coordinates":[153.02380400000001,-27.436901],"type":"Point"}
}