{
  "type": "Feature",
  "properties": {
    "iso:country":"AU",
    "sg:address":"25 Major St",
    "sg:city":"Bunbury",
    "sg:phone":"+61 8 9725 4830",
    "sg:postcode":"6230",
    "sg:province":"WA",
    "wof:name":"Roto Plastics (WA) Pty Ltd",
    "wof:placetype":"venue"
},
  "geometry": {"coordinates":[115.67939,-33.35812],"type":"Point"}
}