{
  "type": "Feature",
  "properties": {
    "addr:full":"Unit 3 21 Guthrie St Osborne Park WA 6017",
    "addr:housenumber":"21",
    "addr:postcode":"6017",
    "addr:street":"Guthrie St",
    "iso:country":"AU",
    "sg:address":"Unit 3 21 Guthrie St",
    "sg:city":"Osborne Park",
    "sg:classifiers":[
        {
            "category":"Manufacturing",
            "subcategory":"Motor Vehicles & Parts",
            "type":"Manufacturing & Wholesale Goods"
        }
    ],
    "sg:phone":"+61 8 9446 8788",
    "sg:postcode":"6017",
    "sg:province":"WA",
    "sg:tags":[
        "replacement"
    ],
    "wof:name":"Rare Spares",
    "wof:placetype":"venue"
},
  "geometry": {"coordinates":[115.81137085,-31.9015159607],"type":"Point"}
}