{
  "type": "Feature",
  "properties": {
    "addr:full":"5th Floor, 18 Mt Gravatt/Capalba Rd Upper Mt Gravatt QLD 4122",
    "addr:housenumber":"18",
    "addr:postcode":"4122",
    "addr:street":"Mt Gravatt / Capalba Rd Upper",
    "iso:country":"AU",
    "sg:address":"5th Floor, 18 Mt Gravatt/Capalba Rd",
    "sg:city":"Upper Mt Gravatt",
    "sg:classifiers":[
        {
            "category":"Government",
            "subcategory":"Court House",
            "type":"Public Place"
        }
    ],
    "sg:phone":"+61 7 3343 1677",
    "sg:postcode":"4122",
    "sg:province":"QLD",
    "sg:tags":[
        "personal",
        "marriage",
        "family",
        "counselling"
    ],
    "wof:name":"Christian Wholeness Counselling Centre",
    "wof:placetype":"venue"
},
  "geometry": {"coordinates":[153.082229614,-27.5593070984],"type":"Point"}
}