{
  "type": "Feature",
  "properties": {
    "addr:full":"237- 239 South Rd Mile End SA 5031",
    "addr:housenumber":"239",
    "addr:postcode":"5031",
    "addr:street":"South Rd",
    "iso:country":"AU",
    "sg:address":"237- 239 South Rd",
    "sg:city":"Mile End",
    "sg:classifiers":[
        {
            "category":"Professional",
            "subcategory":"Business Services",
            "type":"Services"
        }
    ],
    "sg:phone":"+61 8 8234 1212",
    "sg:postcode":"5031",
    "sg:province":"SA",
    "sg:tags":[
        "broker"
    ],
    "wof:name":"Lin Andrews Business Brokers",
    "wof:placetype":"venue"
},
  "geometry": {"coordinates":[138.57034301799999,-34.9289588928],"type":"Point"}
}