{
  "type": "Feature",
  "properties": {
    "addr:full":"2 Govetts Leap Rd Blackheath NSW 2785",
    "addr:housenumber":"2",
    "addr:postcode":"2785",
    "addr:street":"Govetts Leap Rd",
    "iso:country":"AU",
    "sg:address":"2 Govetts Leap Rd",
    "sg:city":"Blackheath",
    "sg:classifiers":[
        {
            "category":"Real Estate",
            "subcategory":"Real Estate Agent",
            "type":"Services"
        }
    ],
    "sg:phone":"+61 2 4787 8797",
    "sg:postcode":"2785",
    "sg:province":"NSW",
    "wof:name":"Ray White Blackheath",
    "wof:placetype":"venue"
},
  "geometry": {"coordinates":[150.285064697,-33.6354408264],"type":"Point"}
}