{
  "type": "Feature",
  "properties": {
    "addr:full":"140 Felton Rd Carlingford NSW 2118",
    "addr:housenumber":"140",
    "addr:postcode":"2118",
    "addr:street":"Felton Rd",
    "iso:country":"AU",
    "sg:address":"140 Felton Rd",
    "sg:city":"Carlingford",
    "sg:classifiers":[
        {
            "category":"Food & Beverages",
            "subcategory":"Supermarket",
            "type":"Retail Goods"
        }
    ],
    "sg:phone":"+61 2 9630 3416",
    "sg:postcode":"2118",
    "sg:province":"NSW",
    "sg:tags":[
        "grocery",
        "store"
    ],
    "wof:name":"Kingsdene Supermarket",
    "wof:placetype":"venue"
},
  "geometry": {"coordinates":[151.03306579599999,-33.7835578918],"type":"Point"}
}