{
  "type": "Feature",
  "properties": {
    "addr:full":"3 Ross Ave Rosny Park TAS 7018",
    "addr:housenumber":"3",
    "addr:postcode":"7018",
    "addr:street":"Ross Ave",
    "iso:country":"AU",
    "sg:address":"3 Ross Ave",
    "sg:city":"Rosny Park",
    "sg:classifiers":[
        {
            "category":"Health Services",
            "subcategory":"Doctor",
            "type":"Services"
        }
    ],
    "sg:phone":"+61 3 6233 1500",
    "sg:postcode":"7018",
    "sg:province":"TAS",
    "sg:tags":[
        "medical",
        "practitioner"
    ],
    "wof:name":"Xraysouth",
    "wof:placetype":"venue"
},
  "geometry": {"coordinates":[147.37171935999999,-42.8647232056],"type":"Point"}
}