{
  "type": "Feature",
  "properties": {
    "addr:full":"11 Freedman Rd Mt Lawley WA 6050",
    "addr:housenumber":"11",
    "addr:postcode":"6050",
    "addr:street":"Freedman Rd",
    "iso:country":"AU",
    "sg:address":"11 Freedman Rd",
    "sg:city":"Mt Lawley",
    "sg:classifiers":[
        {
            "category":"Social Services",
            "subcategory":"Retirement Home",
            "type":"Services"
        }
    ],
    "sg:phone":"+61 8 9424 6636",
    "sg:postcode":"6050",
    "sg:province":"WA",
    "sg:tags":[
        "village"
    ],
    "wof:name":"Marjorie Appleton Village",
    "wof:placetype":"venue"
},
  "geometry": {"coordinates":[115.863571167,-31.9174098969],"type":"Point"}
}