{
  "type": "Feature",
  "properties": {
    "addr:full":"Private Bag 16 Werribee VIC 3030",
    "addr:postcode":"3030",
    "iso:country":"AU",
    "sg:address":"Private Bag 16",
    "sg:city":"Werribee",
    "sg:classifiers":[
        {
            "category":"Food & Beverages",
            "subcategory":"Groceries & Convenience Stores",
            "type":"Retail Goods"
        }
    ],
    "sg:phone":"+61 3 9731 3200",
    "sg:postcode":"3030",
    "sg:province":"VIC",
    "wof:name":"Food Science Australia",
    "wof:placetype":"venue"
},
  "geometry": {"coordinates":[144.65728799999999,-37.906654],"type":"Point"}
}