{
  "type": "Feature",
  "properties": {
    "addr:full":"Unit 1, Bldg 5, 121 Evans Rd Salisbury QLD 4107",
    "addr:housenumber":"121",
    "addr:postcode":"4107",
    "addr:street":"Evans Rd",
    "iso:country":"AU",
    "sg:address":"Unit 1, Bldg 5, 121 Evans Rd",
    "sg:city":"Salisbury",
    "sg:classifiers":[
        {
            "category":"Professional",
            "subcategory":"Testing Lab",
            "type":"Services"
        }
    ],
    "sg:phone":"+61 7 3277 3467",
    "sg:postcode":"4107",
    "sg:province":"QLD",
    "sg:tags":[
        "inspection"
    ],
    "wof:name":"Australasian Infra Red Systems",
    "wof:placetype":"venue"
},
  "geometry": {"coordinates":[153.02708435100001,-27.544500351],"type":"Point"}
}