{
  "type": "Feature",
  "properties": {
    "addr:full":"691 Beaufort St Mt Lawley WA 6050",
    "addr:housenumber":"691",
    "addr:postcode":"6050",
    "addr:street":"Beaufort St",
    "iso:country":"AU",
    "sg:address":"691 Beaufort St",
    "sg:city":"Mt Lawley",
    "sg:classifiers":[
        {
            "category":"Health Services",
            "subcategory":"Doctor",
            "type":"Services"
        }
    ],
    "sg:phone":"+61 8 9262 8600",
    "sg:postcode":"6050",
    "sg:province":"WA",
    "sg:tags":[
        "medical",
        "practitioner"
    ],
    "wof:name":"SULLIVAN, Jill Dr",
    "wof:placetype":"venue"
},
  "geometry": {"coordinates":[115.868591309,-31.9403781891],"type":"Point"}
}