{
  "type": "Feature",
  "properties": {
    "addr:full":"Unit 2/ 10 Bonanza Drv Billinudgel NSW 2483",
    "addr:housenumber":"10",
    "addr:postcode":"2483",
    "addr:street":"Bonanza Drv",
    "iso:country":"AU",
    "sg:address":"Unit 2/ 10 Bonanza Drv",
    "sg:city":"Billinudgel",
    "sg:classifiers":[
        {
            "category":"Retail",
            "subcategory":"Auto Repair",
            "type":"Services"
        }
    ],
    "sg:phone":"+61 2 6680 4999",
    "sg:postcode":"2483",
    "sg:province":"NSW",
    "sg:tags":[
        "repairer",
        "motor",
        "engineer"
    ],
    "wof:name":"BSW Motors",
    "wof:placetype":"venue"
},
  "geometry": {"coordinates":[153.528396606,-28.5054092407],"type":"Point"}
}