{
  "type": "Feature",
  "properties": {
    "iso:country":"AU",
    "sg:address":"Shop 8, St",
    "sg:city":"James Arcade Sydney",
    "sg:classifiers":[
        {
            "category":"Personal",
            "subcategory":"Tattoo Parlor",
            "type":"Services"
        }
    ],
    "sg:phone":"+61 404 803 625",
    "sg:postcode":"2000",
    "sg:province":"NSW",
    "sg:tags":[
        "tattooing"
    ],
    "wof:name":"Henna, Airbrushing & Stick-On Tattoos",
    "wof:placetype":"venue"
},
  "geometry": {"coordinates":[151.21034240700001,-33.8702125549],"type":"Point"}
}