{
  "type": "Feature",
  "properties": {
    "addr:full":"5 Christian Crt Bayswater WA 6053",
    "addr:housenumber":"5",
    "addr:postcode":"6053",
    "addr:street":"Christian Crt",
    "iso:country":"AU",
    "sg:address":"5 Christian Crt",
    "sg:city":"Bayswater",
    "sg:classifiers":[
        {
            "category":"Utilities",
            "subcategory":"Refuse",
            "type":"Services"
        }
    ],
    "sg:phone":"+61 8 9371 2811",
    "sg:postcode":"6053",
    "sg:province":"WA",
    "sg:tags":[
        "remover",
        "rubbish"
    ],
    "wof:name":"WA Bins",
    "wof:placetype":"venue"
},
  "geometry": {"coordinates":[115.91609954800001,-31.9089889526],"type":"Point"}
}