{
  "type": "Feature",
  "properties": {
    "addr:full":"40 Minnesota Rd Hamlyn Terrace NSW 2259",
    "addr:housenumber":"40",
    "addr:postcode":"2259",
    "addr:street":"Minnesota Rd",
    "iso:country":"AU",
    "sg:address":"40 Minnesota Rd",
    "sg:city":"Hamlyn Terrace",
    "sg:classifiers":[
        {
            "category":"Freight",
            "type":"Transportation"
        }
    ],
    "sg:phone":"+61 410 214 856",
    "sg:postcode":"2259",
    "sg:province":"NSW",
    "sg:tags":[
        "light",
        "carrier"
    ],
    "wof:name":"Adtrac",
    "wof:placetype":"venue"
},
  "geometry": {"coordinates":[151.467895508,-33.2482414246],"type":"Point"}
}