{
  "type": "Feature",
  "properties": {
    "addr:full":"10a Eleanor Ave Belmore NSW 2192",
    "addr:housenumber":"10a",
    "addr:postcode":"2192",
    "addr:street":"Eleanor Ave",
    "iso:country":"AU",
    "sg:address":"10a Eleanor Ave",
    "sg:city":"Belmore",
    "sg:classifiers":[
        {
            "category":"Building & Trades",
            "subcategory":"Construction",
            "type":"Services"
        }
    ],
    "sg:phone":"+61 2 9758 2291",
    "sg:postcode":"2192",
    "sg:province":"NSW",
    "sg:tags":[
        "rendering",
        "cement"
    ],
    "wof:name":"Fernandes Plastering Pty Ltd",
    "wof:placetype":"venue"
},
  "geometry": {"coordinates":[151.089676,-33.928673],"type":"Point"}
}