{
  "type": "Feature",
  "properties": {
    "iso:country":"AU",
    "sg:address":"76 Andrew Rd",
    "sg:city":"Greenbank",
    "sg:classifiers":[
        {
            "category":"Social Services",
            "type":"Services"
        }
    ],
    "sg:phone":"+61 7 3802 0384",
    "sg:postcode":"4124",
    "sg:province":"QLD",
    "sg:tags":[
        "domestic",
        "help"
    ],
    "wof:name":"Express Ironing",
    "wof:placetype":"venue"
},
  "geometry": {"coordinates":[153.03053283700001,-27.7104454041],"type":"Point"}
}