{
  "type": "Feature",
  "properties": {
    "addr:full":"28 Feakes Pl Campbell ACT 2612",
    "addr:housenumber":"28",
    "addr:postcode":"2612",
    "addr:street":"Feakes Pl",
    "iso:country":"AU",
    "sg:address":"28 Feakes Pl",
    "sg:city":"Campbell",
    "sg:classifiers":[
        {
            "category":"Banks & Credit Unions",
            "subcategory":"Bureau De Change",
            "type":"Services"
        }
    ],
    "sg:phone":"+61 2 6162 0210",
    "sg:postcode":"2612",
    "sg:province":"ACT",
    "sg:tags":[
        "archaeology"
    ],
    "wof:name":"Heritage Consulting Australia Pty Ltd",
    "wof:placetype":"venue"
},
  "geometry": {"coordinates":[149.14662170400001,-35.2897109985],"type":"Point"}
}