{
  "type": "Feature",
  "properties": {
    "addr:full":"29 Rankin St Innisfail QLD 4860",
    "addr:housenumber":"29",
    "addr:postcode":"4860",
    "addr:street":"Rankin St",
    "iso:country":"AU",
    "sg:address":"29 Rankin St",
    "sg:city":"Innisfail",
    "sg:classifiers":[
        {
            "category":"Building & Trades",
            "subcategory":"Equipment Rental",
            "type":"Services"
        }
    ],
    "sg:phone":"+61 7 4061 6328",
    "sg:postcode":"4860",
    "sg:province":"QLD",
    "sg:tags":[
        "fitness"
    ],
    "wof:name":"Sportz Look",
    "wof:placetype":"venue"
},
  "geometry": {"coordinates":[146.03091430699999,-17.5231838226],"type":"Point"}
}