{
  "type": "Feature",
  "properties": {
    "iso:country":"AU",
    "sg:address":"16 Kentucky St",
    "sg:city":"Sunnybank Hills",
    "sg:classifiers":[
        {
            "category":"Banks & Credit Unions",
            "subcategory":"Investment Brokerage",
            "type":"Services"
        }
    ],
    "sg:phone":"+61 7 3344 5011",
    "sg:postcode":"4109",
    "sg:province":"QLD",
    "sg:tags":[
        "finance",
        "broker"
    ],
    "wof:name":"Brokers Australia",
    "wof:placetype":"venue"
},
  "geometry": {"coordinates":[153.052368164,-27.5935878754],"type":"Point"}
}