{
  "type": "Feature",
  "properties": {
    "addr:full":"PO Box 289 Maddington WA 6109",
    "addr:postcode":"6109",
    "iso:country":"AU",
    "sg:address":"PO Box 289",
    "sg:city":"Maddington",
    "sg:classifiers":[
        {
            "category":"Manufacturing",
            "subcategory":"Tools & Machinery",
            "type":"Manufacturing & Wholesale Goods"
        }
    ],
    "sg:phone":"+61 8 9172 1151",
    "sg:postcode":"6109",
    "sg:province":"WA",
    "sg:tags":[
        "earth",
        "excavating",
        "moving",
        "equipment"
    ],
    "wof:name":"Ridwest Mechanical Contracting Pty Ltd",
    "wof:placetype":"venue"
},
  "geometry": {"coordinates":[115.983459473,-32.0508384705],"type":"Point"}
}