{
  "type": "Feature",
  "properties": {
    "iso:country":"AU",
    "sg:address":"PO Box 2920",
    "sg:city":"Palmerston",
    "sg:classifiers":[
        {
            "category":"Home & Garden",
            "subcategory":"Building Materials",
            "type":"Retail Goods"
        }
    ],
    "sg:phone":"+61 409 094 781",
    "sg:postcode":"0831",
    "sg:province":"NT",
    "sg:tags":[
        "lawn",
        "cutting",
        "maintenance"
    ],
    "wof:name":"Tigers Lawn Mowing Service",
    "wof:placetype":"venue"
},
  "geometry": {"coordinates":[130.983215,-12.48065],"type":"Point"}
}