{
  "type": "Feature",
  "properties": {
    "iso:country":"AU",
    "sg:address":"Mermaid Waters Shopping Centre Cnr Sunshine Blv &",
    "sg:city":"Mermaid Waters",
    "sg:classifiers":[
        {
            "category":"Health Services",
            "subcategory":"Dentist",
            "type":"Services"
        }
    ],
    "sg:phone":"+61 7 5572 9300",
    "sg:postcode":"4218",
    "sg:province":"QLD",
    "wof:name":"Alfa Dental",
    "wof:placetype":"venue"
},
  "geometry": {"coordinates":[153.41465759299999,-28.0459346771],"type":"Point"}
}