{
  "type": "Feature",
  "properties": {
    "addr:full":"Taylors Lakes Community Shopng Cntr, Keilor-Melton Taylors Lakes VIC 3038",
    "addr:postcode":"3038",
    "iso:country":"AU",
    "sg:address":"Taylors Lakes Community Shopng Cntr, Keilor-Melton",
    "sg:city":"Taylors Lakes",
    "sg:classifiers":[
        {
            "category":"Food & Beverages",
            "subcategory":"Liquor & Beverages",
            "type":"Retail Goods"
        }
    ],
    "sg:phone":"+61 3 9390 9207",
    "sg:postcode":"3038",
    "sg:province":"VIC",
    "sg:tags":[
        "store"
    ],
    "wof:name":"Safeway Liquor Stores",
    "wof:placetype":"venue"
},
  "geometry": {"coordinates":[144.77650499999999,-37.726921],"type":"Point"}
}