{
  "type": "Feature",
  "properties": {
    "iso:country":"AU",
    "sg:address":"1 West St",
    "sg:city":"Ascot Vale",
    "sg:classifiers":[
        {
            "category":"Education",
            "subcategory":"Kindergarten",
            "type":"Public Place"
        }
    ],
    "sg:phone":"+61 3 9375 3548",
    "sg:postcode":"3032",
    "sg:province":"VIC",
    "sg:tags":[
        "pre-schools"
    ],
    "wof:name":"Ascot Kindergarten The",
    "wof:placetype":"venue"
},
  "geometry": {"coordinates":[144.92370600000001,-37.777611],"type":"Point"}
}