{
  "type": "Feature",
  "properties": {
    "addr:full":"Darwin River Rd Darwin River Dam NT 0822",
    "addr:postcode":"nt 0822",
    "addr:street":"River Rd",
    "iso:country":"AU",
    "sg:address":"Darwin River Rd",
    "sg:city":"Darwin River Dam",
    "sg:classifiers":[
        {
            "category":"Food & Beverages",
            "subcategory":"Supermarket",
            "type":"Retail Goods"
        }
    ],
    "sg:phone":"+61 8 8988 6104",
    "sg:postcode":"0822",
    "sg:province":"NT",
    "sg:tags":[
        "grocery",
        "store"
    ],
    "wof:name":"Majestic Trading Post",
    "wof:placetype":"venue"
},
  "geometry": {"coordinates":[130.96809400000001,-12.826909],"type":"Point"}
}