{
  "type": "Feature",
  "properties": {
    "iso:country":"AU",
    "sg:address":"6 Sale St",
    "sg:city":"Huonville",
    "sg:classifiers":[
        {
            "category":"Autos & Motor Vehicles",
            "subcategory":"Auto Supplies",
            "type":"Retail Goods"
        }
    ],
    "sg:phone":"+61 3 6264 1045",
    "sg:postcode":"7109",
    "sg:province":"TAS",
    "sg:tags":[
        "tyre"
    ],
    "wof:name":"Huon Tyre & Brake Service",
    "wof:placetype":"venue"
},
  "geometry": {"coordinates":[147.04884338400001,-43.0310134888],"type":"Point"}
}