{
  "type": "Feature",
  "properties": {
    "addr:full":"Cnr Pease & Anderson Sts Manunda QLD 4870",
    "addr:postcode":"4870",
    "addr:street":"Cnr",
    "iso:country":"AU",
    "sg:address":"Cnr Pease & Anderson Sts",
    "sg:city":"Manunda",
    "sg:classifiers":[
        {
            "category":"Health Services",
            "subcategory":"Dentist",
            "type":"Services"
        }
    ],
    "sg:phone":"+61 7 4046 3555",
    "sg:postcode":"4870",
    "sg:province":"QLD",
    "wof:name":"King Stephen Dr.",
    "wof:placetype":"venue"
},
  "geometry": {"coordinates":[145.741500855,-16.913690567],"type":"Point"}
}