{
  "type": "Feature",
  "properties": {
    "addr:full":"U7/ 74 Oak Rd Kirrawee NSW 2232",
    "addr:housenumber":"74",
    "addr:postcode":"2232",
    "addr:street":"U7 /;Oak Rd",
    "iso:country":"AU",
    "sg:address":"U7/ 74 Oak Rd",
    "sg:city":"Kirrawee",
    "sg:classifiers":[
        {
            "category":"Transit Center",
            "subcategory":"Passenger",
            "type":"Transportation"
        }
    ],
    "sg:phone":"+61 2 9545 4233",
    "sg:postcode":"2232",
    "sg:province":"NSW",
    "sg:tags":[
        "wholesaler",
        "mfrs",
        "toiletry",
        "perfume"
    ],
    "wof:name":"Eurofleur Enterprises Pty Ltd",
    "wof:placetype":"venue"
},
  "geometry": {"coordinates":[151.07615661599999,-34.0270004272],"type":"Point"}
}