{
  "type": "Feature",
  "properties": {
    "iso:country":"AU",
    "sg:address":"Churchill Rd",
    "sg:city":"Taroona",
    "sg:classifiers":[
        {
            "category":"Retail",
            "subcategory":"Repair Shop",
            "type":"Services"
        }
    ],
    "sg:phone":"+61 3 6227 9087",
    "sg:postcode":"7053",
    "sg:province":"TAS",
    "sg:tags":[
        "repairing",
        "piano",
        "tuning"
    ],
    "wof:name":"Martin Tucker",
    "wof:placetype":"venue"
},
  "geometry": {"coordinates":[147.345673,-42.949043],"type":"Point"}
}