{
  "type": "Feature",
  "properties": {
    "addr:full":"PO Box 305 Como WA 6952",
    "addr:postcode":"6952",
    "iso:country":"AU",
    "sg:address":"PO Box 305",
    "sg:city":"Como",
    "sg:classifiers":[
        {
            "category":"Real Estate",
            "subcategory":"Real Estate Operator",
            "type":"Services"
        }
    ],
    "sg:phone":"+61 8 9212 2161",
    "sg:postcode":"6952",
    "sg:province":"WA",
    "sg:tags":[
        "concrete",
        "pumping"
    ],
    "wof:name":"ICPS Concrete Pumping and Spraying",
    "wof:placetype":"venue"
},
  "geometry": {"coordinates":[115.766189575,-31.7263641357],"type":"Point"}
}