{
  "type": "Feature",
  "properties": {
    "addr:full":"Pacific Hwy Ewingsdale NSW 2481",
    "addr:postcode":"2481",
    "addr:street":"Pacific Hwy",
    "iso:country":"AU",
    "sg:address":"Pacific Hwy",
    "sg:city":"Ewingsdale",
    "sg:classifiers":[
        {
            "category":"Farming",
            "subcategory":"Nursery",
            "type":"Manufacturing & Wholesale Goods"
        }
    ],
    "sg:phone":"+61 2 6684 7415",
    "sg:postcode":"2481",
    "sg:province":"NSW",
    "wof:name":"Byron Palms Nursery",
    "wof:placetype":"venue"
},
  "geometry": {"coordinates":[153.548904419,-28.634727478],"type":"Point"}
}