{
  "type": "Feature",
  "properties": {
    "iso:country":"AU",
    "sg:address":"9 Glen Rd",
    "sg:city":"Glen Waverley",
    "sg:classifiers":[
        {
            "category":"Health Services",
            "subcategory":"Health Practitioner",
            "type":"Services"
        }
    ],
    "sg:phone":"+61 3 9562 5481",
    "sg:postcode":"3150",
    "sg:province":"VIC",
    "sg:tags":[
        "pathologist",
        "speech"
    ],
    "wof:name":"Communiskills",
    "wof:placetype":"venue"
},
  "geometry": {"coordinates":[145.169067383,-37.8809127808],"type":"Point"}
}