{
  "type": "Feature",
  "properties": {
    "addr:full":"Shop 7/ 288 Malton Rd Epping North NSW 2121",
    "addr:housenumber":"shop 7 / 288",
    "addr:postcode":"2121",
    "addr:street":"Malton Rd",
    "iso:country":"AU",
    "sg:address":"Shop 7/ 288 Malton Rd",
    "sg:city":"Epping North",
    "sg:classifiers":[
        {
            "category":"Food & Beverages",
            "subcategory":"Fruits & Vegetables",
            "type":"Retail Goods"
        }
    ],
    "sg:phone":"+61 2 9876 4377",
    "sg:postcode":"2121",
    "sg:province":"NSW",
    "sg:tags":[
        "greengrocer",
        "fruiterer"
    ],
    "wof:name":"Galluzo's Fine Foods",
    "wof:placetype":"venue"
},
  "geometry": {"coordinates":[151.09014892600001,-33.7572784424],"type":"Point"}
}