{
  "type": "Feature",
  "properties": {
    "addr:full":"13 Town View Crt Leopold VIC 3224",
    "addr:housenumber":"13",
    "addr:postcode":"3224",
    "addr:street":"Town View Crt Leopold",
    "iso:country":"AU",
    "sg:address":"13 Town View Crt",
    "sg:city":"Leopold",
    "sg:classifiers":[
        {
            "category":"Shopping",
            "subcategory":"Mobile Phones",
            "type":"Retail Goods"
        }
    ],
    "sg:phone":"+61 3 5250 3379",
    "sg:postcode":"3224",
    "sg:province":"VIC",
    "sg:tags":[
        "wholesaler",
        "mfrs",
        "electrical",
        "switchboard"
    ],
    "wof:name":"B & I Electrics Pty Ltd",
    "wof:placetype":"venue"
},
  "geometry": {"coordinates":[144.460678,-38.196815],"type":"Point"}
}