{
  "type": "Feature",
  "properties": {
    "addr:full":"3 Cook St Northam WA 6401",
    "addr:housenumber":"3",
    "addr:postcode":"6401",
    "addr:street":"Cook St",
    "iso:country":"AU",
    "sg:address":"3 Cook St",
    "sg:city":"Northam",
    "sg:classifiers":[
        {
            "category":"Retail",
            "subcategory":"Auto Rental",
            "type":"Services"
        }
    ],
    "sg:phone":"+61 8 9622 5676",
    "sg:postcode":"6401",
    "sg:province":"WA",
    "sg:tags":[
        "bus",
        "truck"
    ],
    "wof:name":"Glendas Bus Hire",
    "wof:placetype":"venue"
},
  "geometry": {"coordinates":[116.680152893,-31.6590843201],"type":"Point"}
}