{
  "type": "Feature",
  "properties": {
    "iso:country":"AU",
    "sg:address":"80 Toormina Rd",
    "sg:city":"Toormina",
    "sg:classifiers":[
        {
            "category":"Manufacturing",
            "subcategory":"Building Materials",
            "type":"Manufacturing & Wholesale Goods"
        }
    ],
    "sg:phone":"+61 448 737 493",
    "sg:postcode":"2452",
    "sg:province":"NSW",
    "sg:tags":[
        "concrete",
        "product"
    ],
    "wof:name":"All Styles Concreting",
    "wof:placetype":"venue"
},
  "geometry": {"coordinates":[153.089493,-30.359789],"type":"Point"}
}