{
  "type": "Feature",
  "properties": {
    "iso:country":"AU",
    "sg:address":"40 Beach Rd",
    "sg:city":"Christies Beach",
    "sg:classifiers":[
        {
            "category":"Health Services",
            "subcategory":"Health Practitioner",
            "type":"Services"
        }
    ],
    "sg:phone":"+61 8 8382 7394",
    "sg:postcode":"5165",
    "sg:province":"SA",
    "sg:tags":[
        "physiotherapist"
    ],
    "wof:name":"Physiologic Physiotherapy Services",
    "wof:placetype":"venue"
},
  "geometry": {"coordinates":[138.474731445,-35.1393814087],"type":"Point"}
}