{
  "type": "Feature",
  "properties": {
    "addr:full":"26 Rodney Rd North Geelong VIC 3215",
    "addr:housenumber":"26",
    "addr:postcode":"3215",
    "addr:street":"Rodney Rd",
    "iso:country":"AU",
    "sg:address":"26 Rodney Rd",
    "sg:city":"North Geelong",
    "sg:classifiers":[
        {
            "category":"Professional",
            "type":"Services"
        }
    ],
    "sg:phone":"+61 3 5277 1000",
    "sg:postcode":"3215",
    "sg:province":"VIC",
    "sg:tags":[
        "courier"
    ],
    "wof:name":"Wheels Transport & Courier Service",
    "wof:placetype":"venue"
},
  "geometry": {"coordinates":[144.34881591800001,-38.0993003845],"type":"Point"}
}