{
  "type": "Feature",
  "properties": {
    "addr:full":"43 College St Newtown NSW 2042",
    "addr:housenumber":"43",
    "addr:postcode":"2042",
    "addr:street":"College St",
    "iso:country":"AU",
    "sg:address":"43 College St",
    "sg:city":"Newtown",
    "sg:classifiers":[
        {
            "category":"Retail",
            "subcategory":"Auto Repair",
            "type":"Services"
        }
    ],
    "sg:phone":"+61 2 9550 2689",
    "sg:postcode":"2042",
    "sg:province":"NSW",
    "sg:tags":[
        "repairer",
        "motor",
        "engineer"
    ],
    "wof:name":"Graeme Cooper Automotive",
    "wof:placetype":"venue"
},
  "geometry": {"coordinates":[151.177368,-33.902138],"type":"Point"}
}