{
  "type": "Feature",
  "properties": {
    "addr:full":"156- 158 Cowper St Footscray VIC 3011",
    "addr:housenumber":"158",
    "addr:postcode":"3011",
    "addr:street":"Cowper St",
    "iso:country":"AU",
    "sg:address":"156- 158 Cowper St",
    "sg:city":"Footscray",
    "sg:classifiers":[
        {
            "category":"Manufacturing",
            "subcategory":"Motor Vehicles & Parts",
            "type":"Manufacturing & Wholesale Goods"
        }
    ],
    "sg:phone":"+61 3 9689 5988",
    "sg:postcode":"3011",
    "sg:province":"VIC",
    "sg:tags":[
        "engine",
        "equipment",
        "diesel"
    ],
    "wof:name":"Cornell Fuel Injection & Turbo Service Pty Ltd",
    "wof:placetype":"venue"
},
  "geometry": {"coordinates":[144.9009552,-37.8083267212],"type":"Point"}
}