{
  "type": "Feature",
  "properties": {
    "addr:full":"34 Burt St Boulder WA 6432",
    "addr:housenumber":"34",
    "addr:postcode":"6432",
    "addr:street":"Burt St",
    "iso:country":"AU",
    "sg:address":"34 Burt St",
    "sg:city":"Boulder",
    "sg:classifiers":[
        {
            "category":"Wholesale",
            "subcategory":"Painting Supplies",
            "type":"Manufacturing & Wholesale Goods"
        }
    ],
    "sg:phone":"+61 409 296 387",
    "sg:postcode":"6432",
    "sg:province":"WA",
    "sg:tags":[
        "product",
        "cleaning"
    ],
    "wof:name":"Cleaning Emporium",
    "wof:placetype":"venue"
},
  "geometry": {"coordinates":[121.490829468,-30.7819747925],"type":"Point"}
}