{
  "type": "Feature",
  "properties": {
    "addr:full":"Suite 103 55 Blaxland Rd Ryde NSW 2112",
    "addr:housenumber":"55",
    "addr:postcode":"2112",
    "addr:street":"Blaxland Rd",
    "iso:country":"AU",
    "sg:address":"Suite 103 55 Blaxland Rd",
    "sg:city":"Ryde",
    "sg:classifiers":[
        {
            "category":"Health Services",
            "subcategory":"Health Practitioner",
            "type":"Services"
        }
    ],
    "sg:phone":"+61 2 9809 3156",
    "sg:postcode":"2112",
    "sg:province":"NSW",
    "sg:tags":[
        "physiotherapist"
    ],
    "wof:name":"Cho Haely",
    "wof:placetype":"venue"
},
  "geometry": {"coordinates":[151.106689453,-33.8140220642],"type":"Point"}
}