{
  "type": "Feature",
  "properties": {
    "addr:full":"1 McGrath Ave Nowra NSW 2541",
    "addr:housenumber":"1",
    "addr:postcode":"2541",
    "addr:street":"Mcgrath Ave",
    "iso:country":"AU",
    "sg:address":"1 McGrath Ave",
    "sg:city":"Nowra",
    "sg:classifiers":[
        {
            "category":"Health Services",
            "subcategory":"Health Practitioner",
            "type":"Services"
        }
    ],
    "sg:phone":"+61 2 4423 5757",
    "sg:postcode":"2541",
    "sg:province":"NSW",
    "sg:tags":[
        "physiotherapist"
    ],
    "wof:name":"Wicks Larry Pty Ltd",
    "wof:placetype":"venue"
},
  "geometry": {"coordinates":[150.602325439,-34.8716430664],"type":"Point"}
}