{
  "type": "Feature",
  "properties": {
    "iso:country":"AU",
    "sg:address":"Virginia Park, 1 South Drive, 236-262 East Boundry",
    "sg:city":"Bentleigh East",
    "sg:classifiers":[
        {
            "category":"Professional",
            "subcategory":"Printing & Photocopies",
            "type":"Services"
        }
    ],
    "sg:phone":"+61 3 8575 1900",
    "sg:postcode":"3165",
    "sg:province":"VIC",
    "sg:tags":[
        "photocopying"
    ],
    "wof:name":"Officeworks",
    "wof:placetype":"venue"
},
  "geometry": {"coordinates":[145.06166076700001,-37.9086227417],"type":"Point"}
}