{
  "type": "Feature",
  "properties": {
    "iso:country":"AU",
    "sg:address":"21 Lynette Ave",
    "sg:city":"Warrandyte",
    "sg:classifiers":[
        {
            "category":"Building & Trades",
            "subcategory":"Construction",
            "type":"Services"
        }
    ],
    "sg:phone":"+61 412 373 383",
    "sg:postcode":"3113",
    "sg:province":"VIC",
    "sg:tags":[
        "contractor"
    ],
    "wof:name":"B.T.& M Building & Electrical Contractors Pty Ltd",
    "wof:placetype":"venue"
},
  "geometry": {"coordinates":[145.19906616200001,-37.7472648621],"type":"Point"}
}