{
  "type": "Feature",
  "properties": {
    "addr:full":"6 Pile St Gladesville NSW 2111",
    "addr:housenumber":"6",
    "addr:postcode":"2111",
    "addr:street":"Pile St",
    "iso:country":"AU",
    "sg:address":"6 Pile St",
    "sg:city":"Gladesville",
    "sg:classifiers":[
        {
            "category":"Professional",
            "subcategory":"Business Services",
            "type":"Services"
        }
    ],
    "sg:phone":"+61 2 9879 6477",
    "sg:postcode":"2111",
    "sg:province":"NSW",
    "sg:tags":[
        "exporter"
    ],
    "wof:name":"Arrow Export Services Pty Ltd",
    "wof:placetype":"venue"
},
  "geometry": {"coordinates":[151.12376403799999,-33.8386535645],"type":"Point"}
}