{
  "type": "Feature",
  "properties": {
    "addr:full":"Shp 10, Kim&#039;s Arcade, 974 High St Armadale VIC 3143",
    "addr:housenumber":"10;974",
    "addr:postcode":"3143",
    "addr:street":"S;High St",
    "iso:country":"AU",
    "sg:address":"Shp 10, Kim&#039;s Arcade, 974 High St",
    "sg:city":"Armadale",
    "sg:classifiers":[
        {
            "category":"Shopping",
            "subcategory":"Baby Store",
            "type":"Retail Goods"
        }
    ],
    "sg:phone":"+61 3 9509 2215",
    "sg:postcode":"3143",
    "sg:province":"VIC",
    "sg:tags":[
        "children's",
        "wear"
    ],
    "wof:name":"Izola",
    "wof:placetype":"venue"
},
  "geometry": {"coordinates":[145.02012634299999,-37.8555335999],"type":"Point"}
}