{
  "type": "Feature",
  "properties": {
    "addr:full":"PO Box 616 Balwyn North VIC 3104",
    "addr:postcode":"3104",
    "iso:country":"AU",
    "sg:address":"PO Box 616",
    "sg:city":"Balwyn North",
    "sg:phone":"+61 3 9857 7766",
    "sg:postcode":"3104",
    "sg:province":"VIC",
    "wof:name":"Lakos Separators",
    "wof:placetype":"venue"
},
  "geometry": {"coordinates":[145.085540772,-37.7907905579],"type":"Point"}
}