{
  "type": "Feature",
  "properties": {
    "addr:full":"106- 108 Mica St Carole Park QLD 4300",
    "addr:housenumber":"108",
    "addr:postcode":"4300",
    "addr:street":"Mica St",
    "iso:country":"AU",
    "sg:address":"106- 108 Mica St",
    "sg:city":"Carole Park",
    "sg:classifiers":[
        {
            "category":"Wholesale",
            "subcategory":"Metals & Minerals",
            "type":"Manufacturing & Wholesale Goods"
        }
    ],
    "sg:phone":"+61 7 3723 9200",
    "sg:postcode":"4300",
    "sg:province":"QLD",
    "sg:tags":[
        "steel",
        "merchant"
    ],
    "sg:website":"http://www.totalsteel.com.au",
    "wof:name":"Total Steel Of Australia Pty Ltd",
    "wof:placetype":"venue"
},
  "geometry": {"coordinates":[152.933517456,-27.6217536926],"type":"Point"}
}