{
  "type": "Feature",
  "properties": {
    "addr:full":"130 Aerodrome Rd Maroochydore QLD 4558",
    "addr:housenumber":"130",
    "addr:postcode":"4558",
    "addr:street":"Aerodrome Rd",
    "iso:country":"AU",
    "sg:address":"130 Aerodrome Rd",
    "sg:city":"Maroochydore",
    "sg:classifiers":[
        {
            "category":"Banks & Credit Unions",
            "subcategory":"Bank",
            "type":"Services"
        }
    ],
    "sg:phone":"+61 7 5475 0700",
    "sg:postcode":"4558",
    "sg:province":"QLD",
    "wof:name":"Bendigo Bank",
    "wof:placetype":"venue"
},
  "geometry": {"coordinates":[153.092926025,-26.6568775177],"type":"Point"}
}