{
  "type": "Feature",
  "properties": {
    "addr:full":"10 Collingwood Ave Hazelwood Park SA 5066",
    "addr:housenumber":"10",
    "addr:postcode":"5066",
    "addr:street":"Collingwood Ave",
    "iso:country":"AU",
    "sg:address":"10 Collingwood Ave",
    "sg:city":"Hazelwood Park",
    "sg:classifiers":[
        {
            "category":"Building & Trades",
            "subcategory":"Construction",
            "type":"Services"
        }
    ],
    "sg:phone":"+61 417 115 588",
    "sg:postcode":"5066",
    "sg:province":"SA",
    "sg:tags":[
        "concrete",
        "contractor"
    ],
    "wof:name":"Ozzie Concrete Foundations",
    "wof:placetype":"venue"
},
  "geometry": {"coordinates":[138.653274536,-34.9440498352],"type":"Point"}
}