{
  "type": "Feature",
  "properties": {
    "addr:full":"Flinders Rd Waterloo Corner SA 5110",
    "addr:postcode":"5110",
    "addr:street":"Flinders Rd",
    "iso:country":"AU",
    "sg:address":"Flinders Rd",
    "sg:city":"Waterloo Corner",
    "sg:classifiers":[
        {
            "category":"Farming",
            "subcategory":"Farm",
            "type":"Manufacturing & Wholesale Goods"
        }
    ],
    "sg:phone":"+61 8 8280 8369",
    "sg:postcode":"5110",
    "sg:province":"SA",
    "sg:tags":[
        "farmer"
    ],
    "wof:name":"Abela J&D",
    "wof:placetype":"venue"
},
  "geometry": {"coordinates":[138.55500793499999,-34.70154953],"type":"Point"}
}