{
  "type": "Feature",
  "properties": {
    "iso:country":"AU",
    "sg:address":"250 High St",
    "sg:city":"Penrith",
    "sg:classifiers":[
        {
            "category":"Retail",
            "subcategory":"Funeral Services",
            "type":"Services"
        }
    ],
    "sg:phone":"+61 2 4736 3883",
    "sg:postcode":"2750",
    "sg:province":"NSW",
    "sg:tags":[
        "director"
    ],
    "wof:name":"Monaghan & Gleeson",
    "wof:placetype":"venue"
},
  "geometry": {"coordinates":[150.91560363799999,-33.8946723938],"type":"Point"}
}