{
  "type": "Feature",
  "properties": {
    "addr:full":"103- 109 Prospect Hill Rd Narre Warren VIC 3805",
    "addr:housenumber":"103 109",
    "addr:postcode":"3805",
    "addr:street":"Prospect Hill Rd",
    "iso:country":"AU",
    "sg:address":"103- 109 Prospect Hill Rd",
    "sg:city":"Narre Warren",
    "sg:classifiers":[
        {
            "category":"Health Services",
            "subcategory":"Doctor",
            "type":"Services"
        }
    ],
    "sg:phone":"+61 3 9705 4400",
    "sg:postcode":"3805",
    "sg:province":"VIC",
    "sg:tags":[
        "medical",
        "practitioner"
    ],
    "wof:name":"Narre Warren North Medical Centre",
    "wof:placetype":"venue"
},
  "geometry": {"coordinates":[145.30958557100001,-38.01121521],"type":"Point"}
}