{
  "type": "Feature",
  "properties": {
    "addr:full":"5- 17 Taminga St Regency Park SA 5010",
    "addr:housenumber":"17",
    "addr:postcode":"5010",
    "addr:street":"5;St",
    "iso:country":"AU",
    "sg:address":"5- 17 Taminga St",
    "sg:city":"Regency Park",
    "sg:classifiers":[
        {
            "category":"Building & Trades",
            "subcategory":"Construction",
            "type":"Services"
        }
    ],
    "sg:phone":"+61 8 8348 5777",
    "sg:postcode":"5010",
    "sg:province":"SA",
    "sg:tags":[
        "spouting",
        "guttering"
    ],
    "wof:name":"Cowells Woodroffe",
    "wof:placetype":"venue"
},
  "geometry": {"coordinates":[138.570068359,-34.8603057861],"type":"Point"}
}