{
  "type": "Feature",
  "properties": {
    "addr:full":"3 Mariem St Shepparton VIC 3630",
    "addr:housenumber":"3",
    "addr:postcode":"3630",
    "addr:street":"Mariem St",
    "iso:country":"AU",
    "sg:address":"3 Mariem St",
    "sg:city":"Shepparton",
    "sg:classifiers":[
        {
            "category":"Organizations",
            "subcategory":"Professional Association",
            "type":"Services"
        }
    ],
    "sg:phone":"+61 3 5822 0766",
    "sg:postcode":"3630",
    "sg:province":"VIC",
    "sg:tags":[
        "web",
        "internet"
    ],
    "wof:name":"Websites Plus",
    "wof:placetype":"venue"
},
  "geometry": {"coordinates":[145.41679382300001,-36.3796463013],"type":"Point"}
}