{
  "type": "Feature",
  "properties": {
    "iso:country":"AU",
    "sg:address":"6 Baynes St",
    "sg:city":"Barmera",
    "sg:classifiers":[
        {
            "category":"Building & Trades",
            "subcategory":"Landscaping Services",
            "type":"Services"
        }
    ],
    "sg:phone":"+61 8 8588 1254",
    "sg:postcode":"5345",
    "sg:province":"SA",
    "sg:tags":[
        "gardener"
    ],
    "wof:name":"Gardiner Donald",
    "wof:placetype":"venue"
},
  "geometry": {"coordinates":[140.47541809099999,-34.2399635315],"type":"Point"}
}