{
  "type": "Feature",
  "properties": {
    "addr:full":"104 Ormond Rd Elwood VIC 3184",
    "addr:housenumber":"104",
    "addr:postcode":"3184",
    "addr:street":"Ormond Rd",
    "iso:country":"AU",
    "sg:address":"104 Ormond Rd",
    "sg:city":"Elwood",
    "sg:classifiers":[
        {
            "category":"Health Services",
            "subcategory":"Optometrist",
            "type":"Services"
        }
    ],
    "sg:phone":"+61 3 9531 8977",
    "sg:postcode":"3184",
    "sg:province":"VIC",
    "wof:name":"Wink Optometrists",
    "wof:placetype":"venue"
},
  "geometry": {"coordinates":[144.987625122,-37.8855476379],"type":"Point"}
}