{
  "type": "Feature",
  "properties": {
    "addr:full":"Shop 6, 81 Minjungbal Drv Tweed Heads South NSW 2486",
    "addr:housenumber":"shop;81",
    "addr:postcode":"2486",
    "addr:street":"Minjungbal Drv",
    "iso:country":"AU",
    "sg:address":"Shop 6, 81 Minjungbal Drv",
    "sg:city":"Tweed Heads South",
    "sg:classifiers":[
        {
            "category":"Professional",
            "subcategory":"Employment Agencies",
            "type":"Services"
        }
    ],
    "sg:phone":"+61 7 5523 4825",
    "sg:postcode":"2486",
    "sg:province":"NSW",
    "wof:name":"Tursa Employment & Training Inc.",
    "wof:placetype":"venue"
},
  "geometry": {"coordinates":[153.543701172,-28.1990661621],"type":"Point"}
}