{
  "type": "Feature",
  "properties": {
    "addr:full":"35 Julier Crs Hoppers Crossing VIC 3029",
    "addr:housenumber":"35",
    "addr:postcode":"3029",
    "addr:street":"Julier Crs",
    "iso:country":"AU",
    "sg:address":"35 Julier Crs",
    "sg:city":"Hoppers Crossing",
    "sg:classifiers":[
        {
            "category":"Banks & Credit Unions",
            "subcategory":"Bureau De Change",
            "type":"Services"
        }
    ],
    "sg:phone":"+61 3 9748 7077",
    "sg:postcode":"3029",
    "sg:province":"VIC",
    "sg:tags":[
        "wheel",
        "industrial"
    ],
    "wof:name":"Fastroll Mobility Solutions",
    "wof:placetype":"venue"
},
  "geometry": {"coordinates":[144.703934,-37.864319],"type":"Point"}
}