{
  "type": "Feature",
  "properties": {
    "addr:full":"294 Bourbong St Bundaberg QLD 4670",
    "addr:housenumber":"294",
    "addr:postcode":"4670",
    "addr:street":"Bourbong St",
    "iso:country":"AU",
    "sg:address":"294 Bourbong St",
    "sg:city":"Bundaberg",
    "sg:classifiers":[
        {
            "category":"Health Services",
            "subcategory":"Doctor",
            "type":"Services"
        }
    ],
    "sg:phone":"+61 7 4152 2266",
    "sg:postcode":"4670",
    "sg:province":"QLD",
    "sg:tags":[
        "medical",
        "practitioner"
    ],
    "wof:name":"Kolli Chalam Dr",
    "wof:placetype":"venue"
},
  "geometry": {"coordinates":[152.333740234,-24.8703746796],"type":"Point"}
}