{
  "type": "Feature",
  "properties": {
    "addr:full":"98 Ross St Tatura VIC 3616",
    "addr:housenumber":"98",
    "addr:postcode":"3616",
    "addr:street":"Ross St",
    "iso:country":"AU",
    "sg:address":"98 Ross St",
    "sg:city":"Tatura",
    "sg:classifiers":[
        {
            "category":"Autos & Motor Vehicles",
            "subcategory":"Auto Supplies",
            "type":"Retail Goods"
        }
    ],
    "sg:phone":"+61 3 5824 1077",
    "sg:postcode":"3616",
    "sg:province":"VIC",
    "sg:tags":[
        "tyre"
    ],
    "wof:name":"Waterwheel Tyre Centre",
    "wof:placetype":"venue"
},
  "geometry": {"coordinates":[145.22279357900001,-36.4452590942],"type":"Point"}
}