{
  "type": "Feature",
  "properties": {
    "addr:full":"107 Turpin Rd Labrador QLD 4215",
    "addr:housenumber":"107",
    "addr:postcode":"4215",
    "addr:street":"Turpin Rd",
    "iso:country":"AU",
    "sg:address":"107 Turpin Rd",
    "sg:city":"Labrador",
    "sg:classifiers":[
        {
            "category":"Real Estate",
            "subcategory":"Real Estate Agent",
            "type":"Services"
        }
    ],
    "sg:phone":"+61 7 5531 1221",
    "sg:postcode":"4215",
    "sg:province":"QLD",
    "wof:name":"Labrador Property Management",
    "wof:placetype":"venue"
},
  "geometry": {"coordinates":[153.40199279800001,-27.9487266541],"type":"Point"}
}