{
  "type": "Feature",
  "properties": {
    "addr:full":"170 Auckland St Gladstone QLD 4680",
    "addr:housenumber":"170",
    "addr:postcode":"4680",
    "addr:street":"Auckland St",
    "iso:country":"AU",
    "sg:address":"170 Auckland St",
    "sg:city":"Gladstone",
    "sg:classifiers":[
        {
            "category":"Health Services",
            "subcategory":"Doctor",
            "type":"Services"
        }
    ],
    "sg:phone":"+61 7 4972 4005",
    "sg:postcode":"4680",
    "sg:province":"QLD",
    "sg:tags":[
        "medical",
        "practitioner"
    ],
    "wof:name":"Hough J",
    "wof:placetype":"venue"
},
  "geometry": {"coordinates":[151.261993408,-23.8485145569],"type":"Point"}
}