{
  "type": "Feature",
  "properties": {
    "iso:country":"AU",
    "sg:address":"18 Frome St",
    "sg:city":"Port Augusta",
    "sg:classifiers":[
        {
            "category":"Government",
            "subcategory":"Court House",
            "type":"Public Place"
        }
    ],
    "sg:phone":"+61 8 8642 2944",
    "sg:postcode":"5700",
    "sg:province":"SA",
    "sg:tags":[
        "personal",
        "marriage",
        "family",
        "counselling"
    ],
    "wof:name":"Port Augusta Family Centre",
    "wof:placetype":"venue"
},
  "geometry": {"coordinates":[137.77554321299999,-32.4911766052],"type":"Point"}
}