{
  "type": "Feature",
  "properties": {
    "addr:full":"9 Steele St Winnellie NT 0820",
    "addr:housenumber":"9",
    "addr:postcode":"nt 0820",
    "addr:street":"Steele St",
    "iso:country":"AU",
    "sg:address":"9 Steele St",
    "sg:city":"Winnellie",
    "sg:classifiers":[
        {
            "category":"Retail",
            "subcategory":"Auto Repair",
            "type":"Services"
        }
    ],
    "sg:phone":"+61 8 8947 4746",
    "sg:postcode":"0820",
    "sg:province":"NT",
    "sg:tags":[
        "repairer",
        "motor",
        "engineer"
    ],
    "wof:name":"N.T. Auto Repairs",
    "wof:placetype":"venue"
},
  "geometry": {"coordinates":[130.86180114699999,-12.4294462204],"type":"Point"}
}