{
  "type": "Feature",
  "properties": {
    "addr:full":"Queen St Campbelltown NSW 2560",
    "addr:postcode":"2560",
    "addr:street":"Queen St",
    "iso:country":"AU",
    "sg:address":"Queen St",
    "sg:city":"Campbelltown",
    "sg:classifiers":[
        {
            "category":"Building & Trades",
            "subcategory":"Equipment Rental",
            "type":"Services"
        }
    ],
    "sg:phone":"+61 2 4625 2272",
    "sg:postcode":"2560",
    "sg:province":"NSW",
    "sg:tags":[
        "renting",
        "trailer"
    ],
    "wof:name":"U-Haul Trailer Rentals",
    "wof:placetype":"venue"
},
  "geometry": {"coordinates":[150.810302734,-34.0710601807],"type":"Point"}
}