{
  "type": "Feature",
  "properties": {
    "addr:full":"31 Celtis Pl Leeton NSW 2705",
    "addr:housenumber":"31",
    "addr:postcode":"2705",
    "addr:street":"Celtis Pl",
    "iso:country":"AU",
    "sg:address":"31 Celtis Pl",
    "sg:city":"Leeton",
    "sg:classifiers":[
        {
            "category":"Retail",
            "subcategory":"Storage",
            "type":"Services"
        }
    ],
    "sg:phone":"+61 2 6953 2619",
    "sg:postcode":"2705",
    "sg:province":"NSW",
    "sg:tags":[
        "removal",
        "furniture"
    ],
    "wof:name":"Leeton Removals",
    "wof:placetype":"venue"
},
  "geometry": {"coordinates":[146.401443481,-34.5452766418],"type":"Point"}
}