{
  "type": "Feature",
  "properties": {
    "addr:full":"18 Rowland St Slacks Creek QLD 4127",
    "addr:housenumber":"18",
    "addr:postcode":"4127",
    "addr:street":"Rowland St",
    "iso:country":"AU",
    "sg:address":"18 Rowland St",
    "sg:city":"Slacks Creek",
    "sg:classifiers":[
        {
            "category":"Building & Trades",
            "subcategory":"Construction",
            "type":"Services"
        }
    ],
    "sg:phone":"+61 7 3208 1188",
    "sg:postcode":"4127",
    "sg:province":"QLD",
    "sg:tags":[
        "decking",
        "contractor"
    ],
    "sg:website":"http://www.latticealone.com.au",
    "wof:name":"Lattice Alone",
    "wof:placetype":"venue"
},
  "geometry": {"coordinates":[153.12696838400001,-27.6293296814],"type":"Point"}
}