{
  "type": "Feature",
  "properties": {
    "iso:country":"AU",
    "sg:address":"3 Arch St",
    "sg:city":"Kingston",
    "sg:classifiers":[
        {
            "category":"Social Services",
            "subcategory":"Child Care",
            "type":"Services"
        }
    ],
    "sg:phone":"+61 7 3299 1516",
    "sg:postcode":"4114",
    "sg:province":"QLD",
    "wof:name":"Aussie Kids Child Care",
    "wof:placetype":"venue"
},
  "geometry": {"coordinates":[153.125762939,-27.6502685547],"type":"Point"}
}