{
  "type": "Feature",
  "properties": {
    "addr:full":"129 Sydney Rd Fairlight NSW 2094",
    "addr:housenumber":"129",
    "addr:postcode":"2094",
    "addr:street":"Sydney Rd",
    "iso:country":"AU",
    "sg:address":"129 Sydney Rd",
    "sg:city":"Fairlight",
    "sg:classifiers":[
        {
            "category":"Retail",
            "subcategory":"Laundry & Dry Cleaning",
            "type":"Services"
        }
    ],
    "sg:phone":"+61 2 9907 0125",
    "sg:postcode":"2094",
    "sg:province":"NSW",
    "sg:tags":[
        "ironing"
    ],
    "wof:name":"Kerri Harvey Ironing Service",
    "wof:placetype":"venue"
},
  "geometry": {"coordinates":[151.27833557100001,-33.7960777283],"type":"Point"}
}