{
  "type": "Feature",
  "properties": {
    "addr:full":"175a Botany Rd Waterloo NSW 2017",
    "addr:housenumber":"175a",
    "addr:postcode":"2017",
    "addr:street":"Botany Rd",
    "iso:country":"AU",
    "sg:address":"175a Botany Rd",
    "sg:city":"Waterloo",
    "sg:classifiers":[
        {
            "category":"Utilities",
            "subcategory":"Electric",
            "type":"Services"
        }
    ],
    "sg:phone":"+61 2 9319 1635",
    "sg:postcode":"2017",
    "sg:province":"NSW",
    "sg:tags":[
        "electrical",
        "contractor"
    ],
    "wof:name":"G.E. Consulting Australia Pty Ltd",
    "wof:placetype":"venue"
},
  "geometry": {"coordinates":[151.201095581,-33.9009857178],"type":"Point"}
}