{
  "type": "Feature",
  "properties": {
    "addr:full":"Shop 6/ 430 Brighton Rd Brighton SA 5048",
    "addr:housenumber":"shop 6 / 430",
    "addr:postcode":"5048",
    "addr:street":"Brighton Rd",
    "iso:country":"AU",
    "sg:address":"Shop 6/ 430 Brighton Rd",
    "sg:city":"Brighton",
    "sg:classifiers":[
        {
            "category":"Shopping",
            "subcategory":"Clothing, Apparel, & Fashions",
            "type":"Retail Goods"
        }
    ],
    "sg:phone":"+61 8 8298 8989",
    "sg:postcode":"5048",
    "sg:province":"SA",
    "sg:tags":[
        "lady",
        "wear"
    ],
    "wof:name":"Chasing Nel",
    "wof:placetype":"venue"
},
  "geometry": {"coordinates":[138.52314799999999,-35.01701],"type":"Point"}
}