{
  "type": "Feature",
  "properties": {
    "addr:full":"Shop 2, 6-20 Luck St Eltham VIC 3095",
    "addr:housenumber":"shop 2 6-20",
    "addr:postcode":"3095",
    "addr:street":"Luck St",
    "iso:country":"AU",
    "sg:address":"Shop 2, 6-20 Luck St",
    "sg:city":"Eltham",
    "sg:classifiers":[
        {
            "category":"Food & Beverages",
            "subcategory":"Liquor & Beverages",
            "type":"Retail Goods"
        }
    ],
    "sg:phone":"+61 1300 723 388",
    "sg:postcode":"3095",
    "sg:province":"VIC",
    "sg:tags":[
        "store"
    ],
    "wof:name":"Dan Murphy's",
    "wof:placetype":"venue"
},
  "geometry": {"coordinates":[145.15116882300001,-37.7127494812],"type":"Point"}
}