{
  "type": "Feature",
  "properties": {
    "iso:country":"AU",
    "sg:address":"84 Warrandyte Rd",
    "sg:city":"Research",
    "sg:classifiers":[
        {
            "category":"Professional",
            "subcategory":"Engineering",
            "type":"Services"
        }
    ],
    "sg:phone":"+61 3 9437 0222",
    "sg:postcode":"3095",
    "sg:province":"VIC",
    "sg:tags":[
        "consulting",
        "engineer"
    ],
    "wof:name":"Garner Max & Associates Pty Ltd",
    "wof:placetype":"venue"
},
  "geometry": {"coordinates":[145.16699218799999,-37.7500228882],"type":"Point"}
}