{
  "type": "Feature",
  "properties": {
    "addr:full":"Shp 8/ 160 Moss Vale Rd Kangaroo Valley NSW 2577",
    "addr:housenumber":"/ 160",
    "addr:postcode":"2577",
    "addr:street":"Moss Vale Rd",
    "iso:country":"AU",
    "sg:address":"Shp 8/ 160 Moss Vale Rd",
    "sg:city":"Kangaroo Valley",
    "sg:classifiers":[
        {
            "category":"Arts & Performance",
            "subcategory":"Art Gallery",
            "type":"Entertainment"
        }
    ],
    "sg:phone":"+61 2 4465 2333",
    "sg:postcode":"2577",
    "sg:province":"NSW",
    "wof:name":"JD Gallery",
    "wof:placetype":"venue"
},
  "geometry": {"coordinates":[150.52143859899999,-34.7281188965],"type":"Point"}
}