{
  "type": "Feature",
  "properties": {
    "iso:country":"AU",
    "sg:address":"13 Pindari Drv",
    "sg:city":"Bayswater",
    "sg:classifiers":[
        {
            "category":"Professional",
            "subcategory":"Accounting & Tax Preparation",
            "type":"Services"
        }
    ],
    "sg:phone":"+61 3 9738 1100",
    "sg:postcode":"3153",
    "sg:province":"VIC",
    "sg:tags":[
        "bookkeeping"
    ],
    "wof:name":"Brilliant Books Pty Ltd",
    "wof:placetype":"venue"
},
  "geometry": {"coordinates":[145.25227355999999,-37.8538856506],"type":"Point"}
}