{
  "type": "Feature",
  "properties": {
    "iso:country":"AU",
    "sg:address":"24 Marcia St",
    "sg:city":"Coffs Harbour",
    "sg:classifiers":[
        {
            "category":"Retail",
            "subcategory":"Storage",
            "type":"Services"
        }
    ],
    "sg:phone":"+61 2 6652 5151",
    "sg:postcode":"2450",
    "sg:province":"NSW",
    "sg:tags":[
        "shelving",
        "system"
    ],
    "wof:name":"Big H",
    "wof:placetype":"venue"
},
  "geometry": {"coordinates":[153.117157,-30.289474],"type":"Point"}
}