{
  "type": "Feature",
  "properties": {
    "addr:full":"180 Silverwater Rd Lidcombe NSW 2141",
    "addr:housenumber":"180",
    "addr:postcode":"2141",
    "addr:street":"Silverwater Rd",
    "iso:country":"AU",
    "sg:address":"180 Silverwater Rd",
    "sg:city":"Lidcombe",
    "sg:classifiers":[
        {
            "category":"Autos & Motor Vehicles",
            "subcategory":"Auto Supplies",
            "type":"Retail Goods"
        }
    ],
    "sg:phone":"+61 2 9741 9741",
    "sg:postcode":"2141",
    "sg:province":"NSW",
    "sg:tags":[
        "equipment",
        "part",
        "truck"
    ],
    "wof:name":"Transpec Limited",
    "wof:placetype":"venue"
},
  "geometry": {"coordinates":[151.04394531200001,-33.8428077698],"type":"Point"}
}