{
  "type": "Feature",
  "properties": {
    "iso:country":"AU",
    "sg:address":"34- 36 Harvester Ave",
    "sg:city":"Sunshine North",
    "sg:classifiers":[
        {
            "category":"Wholesale",
            "subcategory":"Chemicals & Plastics",
            "type":"Manufacturing & Wholesale Goods"
        }
    ],
    "sg:phone":"+61 3 9312 0144",
    "sg:postcode":"3020",
    "sg:province":"VIC",
    "sg:tags":[
        "extruders"
    ],
    "wof:name":"Procom Plastics Extrusion P/L",
    "wof:placetype":"venue"
},
  "geometry": {"coordinates":[144.83703600000001,-37.760731],"type":"Point"}
}