{
  "type": "Feature",
  "properties": {
    "addr:full":"82 Mountain View Drv Woongarrah NSW 2259",
    "addr:housenumber":"82",
    "addr:postcode":"2259",
    "addr:street":"Mountain View Drv",
    "iso:country":"AU",
    "sg:address":"82 Mountain View Drv",
    "sg:city":"Woongarrah",
    "sg:classifiers":[
        {
            "category":"Home & Garden",
            "subcategory":"Building Materials",
            "type":"Retail Goods"
        }
    ],
    "sg:phone":"+61 412 391 082",
    "sg:postcode":"2259",
    "sg:province":"NSW",
    "sg:tags":[
        "retaining",
        "wall"
    ],
    "wof:name":"Allan Vassallo Natural Landscaping",
    "wof:placetype":"venue"
},
  "geometry": {"coordinates":[151.48770141599999,-33.2468338013],"type":"Point"}
}