{
  "type": "Feature",
  "properties": {
    "addr:full":"27 Sciarra Crs Quakers Hill NSW 2763",
    "addr:housenumber":"27",
    "addr:postcode":"2763",
    "addr:street":"Sciarra Crs",
    "iso:country":"AU",
    "sg:address":"27 Sciarra Crs",
    "sg:city":"Quakers Hill",
    "sg:classifiers":[
        {
            "category":"Utilities",
            "subcategory":"Electric",
            "type":"Services"
        }
    ],
    "sg:phone":"+61 2 9626 0423",
    "sg:postcode":"2763",
    "sg:province":"NSW",
    "sg:tags":[
        "electrical",
        "contractor"
    ],
    "wof:name":"Callcott B G",
    "wof:placetype":"venue"
},
  "geometry": {"coordinates":[150.88661193900001,-33.7264213562],"type":"Point"}
}