{
  "type": "Feature",
  "properties": {
    "iso:country":"AU",
    "sg:address":"77 Strathaird Drv",
    "sg:city":"Narre Warren",
    "sg:classifiers":[
        {
            "category":"Building & Trades",
            "subcategory":"Locksmith",
            "type":"Services"
        }
    ],
    "sg:phone":"+61 408 390 984",
    "sg:postcode":"3805",
    "sg:province":"VIC",
    "sg:tags":[
        "lock"
    ],
    "wof:name":"South Eastern Locksmiths",
    "wof:placetype":"venue"
},
  "geometry": {"coordinates":[145.290207,-38.059856],"type":"Point"}
}