{
  "type": "Feature",
  "properties": {
    "addr:full":"Shop 19, 74-78 The Corso, Manly 2095 Manly NSW 2095",
    "addr:housenumber":"shop 19 74-78;2095",
    "addr:postcode":"2095",
    "addr:street":"The Corso Manly",
    "iso:country":"AU",
    "sg:address":"Shop 19, 74-78 The Corso, Manly 2095",
    "sg:city":"Manly",
    "sg:classifiers":[
        {
            "category":"Education",
            "subcategory":"Dance Studio",
            "type":"Public Place"
        }
    ],
    "sg:phone":"+61 2 9976 6988",
    "sg:postcode":"2095",
    "sg:province":"NSW",
    "sg:tags":[
        "instruction",
        "language"
    ],
    "wof:name":"Sydney English Academy (SEA)",
    "wof:placetype":"venue"
},
  "geometry": {"coordinates":[151.28707885700001,-33.7978782654],"type":"Point"}
}