{
  "type": "Feature",
  "properties": {
    "addr:full":"27 Chellaston St Camden NSW 2570",
    "addr:housenumber":"27",
    "addr:postcode":"2570",
    "addr:street":"Chellaston St",
    "iso:country":"AU",
    "sg:address":"27 Chellaston St",
    "sg:city":"Camden",
    "sg:classifiers":[
        {
            "category":"Personal",
            "subcategory":"Massage",
            "type":"Services"
        }
    ],
    "sg:phone":"+61 2 4655 4999",
    "sg:postcode":"2570",
    "sg:province":"NSW",
    "sg:tags":[
        "therapy"
    ],
    "wof:name":"Lewis Steven",
    "wof:placetype":"venue"
},
  "geometry": {"coordinates":[150.69824218799999,-34.0610771179],"type":"Point"}
}