{
  "type": "Feature",
  "properties": {
    "iso:country":"AU",
    "sg:address":"18 Roe St",
    "sg:city":"Roebourne",
    "sg:classifiers":[
        {
            "category":"Retail",
            "subcategory":"Auto Repair",
            "type":"Services"
        }
    ],
    "sg:phone":"+61 8 9182 1199",
    "sg:postcode":"6718",
    "sg:province":"WA",
    "sg:tags":[
        "repairer",
        "motor",
        "engineer"
    ],
    "wof:name":"Chris's Spares & Repairs",
    "wof:placetype":"venue"
},
  "geometry": {"coordinates":[117.14643096899999,-20.7704563141],"type":"Point"}
}