{
  "type": "Feature",
  "properties": {
    "addr:full":"47- 49 Neumann Rd Capalaba QLD 4157",
    "addr:housenumber":"49",
    "addr:postcode":"4157",
    "addr:street":"Neumann Rd",
    "iso:country":"AU",
    "sg:address":"47- 49 Neumann Rd",
    "sg:city":"Capalaba",
    "sg:classifiers":[
        {
            "category":"Utilities",
            "subcategory":"Recycling",
            "type":"Services"
        }
    ],
    "sg:phone":"+61 7 3823 3342",
    "sg:postcode":"4157",
    "sg:province":"QLD",
    "wof:name":"P & S Traders Pty Ltd",
    "wof:placetype":"venue"
},
  "geometry": {"coordinates":[153.20585632300001,-27.5335731506],"type":"Point"}
}