{
  "type": "Feature",
  "properties": {
    "iso:country":"AU",
    "sg:address":"64 Wee Waa St",
    "sg:city":"Walgett",
    "sg:classifiers":[
        {
            "category":"Cafe",
            "type":"Food & Drink"
        }
    ],
    "sg:phone":"+61 2 6828 1941",
    "sg:postcode":"2832",
    "sg:province":"NSW",
    "wof:name":"Seashells Cafe",
    "wof:placetype":"venue"
},
  "geometry": {"coordinates":[148.11920165999999,-30.0217018127],"type":"Point"}
}