{
  "type": "Feature",
  "properties": {
    "addr:full":"Unit 3, 40 Neville St Carnegie VIC 3163",
    "addr:housenumber":"40",
    "addr:postcode":"3163",
    "addr:street":"Neville St",
    "iso:country":"AU",
    "sg:address":"Unit 3, 40 Neville St",
    "sg:city":"Carnegie",
    "sg:classifiers":[
        {
            "category":"Professional",
            "subcategory":"Art Services",
            "type":"Services"
        }
    ],
    "sg:phone":"+61 3 9578 9279",
    "sg:postcode":"3163",
    "sg:province":"VIC",
    "sg:tags":[
        "decorator",
        "painter"
    ],
    "wof:name":"Anatoly Painting Service Pty Ltd",
    "wof:placetype":"venue"
},
  "geometry": {"coordinates":[145.04945373499999,-37.8975791931],"type":"Point"}
}