{
  "type": "Feature",
  "properties": {
    "iso:country":"AU",
    "sg:address":"Vulcan Rd (Cnr Bannister Rd)",
    "sg:city":"Canning Vale",
    "sg:classifiers":[
        {
            "category":"Manufacturing",
            "subcategory":"Motor Vehicles & Parts",
            "type":"Manufacturing & Wholesale Goods"
        }
    ],
    "sg:phone":"+61 13 32 27",
    "sg:postcode":"6155",
    "sg:province":"WA",
    "sg:tags":[
        "replacement"
    ],
    "wof:name":"Repco",
    "wof:placetype":"venue"
},
  "geometry": {"coordinates":[115.930794,-32.060188],"type":"Point"}
}