{
  "type": "Feature",
  "properties": {
    "addr:full":"Capricorn Hwy Kabra QLD 4702",
    "addr:postcode":"4702",
    "addr:street":"Capricorn Hwy",
    "iso:country":"AU",
    "sg:address":"Capricorn Hwy",
    "sg:city":"Kabra",
    "sg:classifiers":[
        {
            "category":"Travel",
            "subcategory":"Hotels & Motels",
            "type":"Entertainment"
        }
    ],
    "sg:phone":"+61 7 4933 1207",
    "sg:postcode":"4702",
    "sg:province":"QLD",
    "sg:tags":[
        "accommodation"
    ],
    "wof:name":"Kabra Hotel",
    "wof:placetype":"venue"
},
  "geometry": {"coordinates":[150.395141602,-23.4674968719],"type":"Point"}
}