{
  "type": "Feature",
  "properties": {
    "iso:country":"AU",
    "sg:address":"46 Albion St",
    "sg:city":"Harris Park",
    "sg:classifiers":[
        {
            "category":"Organizations",
            "subcategory":"Non-profit Organization",
            "type":"Services"
        }
    ],
    "sg:phone":"+61 2 9893 8210",
    "sg:postcode":"2150",
    "sg:province":"NSW",
    "sg:tags":[
        "support",
        "disability",
        "organisation"
    ],
    "wof:name":"Citizen Advocacy Western Sydney",
    "wof:placetype":"venue"
},
  "geometry": {"coordinates":[151.0103302,-33.8202476501],"type":"Point"}
}