{
  "type": "Feature",
  "properties": {
    "addr:full":"Graham St Ayr QLD 4807",
    "addr:postcode":"4807",
    "addr:street":"Graham St",
    "iso:country":"AU",
    "sg:address":"Graham St",
    "sg:city":"Ayr",
    "sg:classifiers":[
        {
            "category":"Food & Beverages",
            "subcategory":"Bakery",
            "type":"Retail Goods"
        }
    ],
    "sg:phone":"+61 7 4783 2049",
    "sg:postcode":"4807",
    "sg:province":"QLD",
    "sg:tags":[
        "baker"
    ],
    "wof:name":"Phelans Bakery",
    "wof:placetype":"venue"
},
  "geometry": {"coordinates":[147.40640258799999,-19.5728187561],"type":"Point"}
}