{
  "type": "Feature",
  "properties": {
    "addr:full":"Cnr South Rd & Linton St Moorabbin VIC 3189",
    "addr:postcode":"3189",
    "addr:street":"Cnr South Rd & Linton St",
    "iso:country":"AU",
    "sg:address":"Cnr South Rd & Linton St",
    "sg:city":"Moorabbin",
    "sg:classifiers":[
        {
            "category":"Autos & Motor Vehicles",
            "subcategory":"Fuel & Gas Station",
            "type":"Retail Goods"
        }
    ],
    "sg:phone":"+61 3 9532 1684",
    "sg:postcode":"3189",
    "sg:province":"VIC",
    "wof:name":"Shell Select Moorabbin",
    "wof:placetype":"venue"
},
  "geometry": {"coordinates":[145.058303833,-37.9361419678],"type":"Point"}
}