{
  "type": "Feature",
  "properties": {
    "addr:full":"PO Box 272 Milsons Point Prvt Bxs NSW 1565",
    "addr:postcode":"1565",
    "iso:country":"AU",
    "sg:address":"PO Box 272",
    "sg:city":"Milsons Point Prvt Bxs",
    "sg:classifiers":[
        {
            "category":"Professional",
            "subcategory":"Management & Consulting",
            "type":"Services"
        }
    ],
    "sg:phone":"+61 2 9410 3966",
    "sg:postcode":"1565",
    "sg:province":"NSW",
    "sg:tags":[
        "consultant",
        "industrial",
        "relation"
    ],
    "wof:name":"Leana Street Consulting",
    "wof:placetype":"venue"
},
  "geometry": {"coordinates":[151.21270751899999,-33.8462715149],"type":"Point"}
}