{
  "type": "Feature",
  "properties": {
    "addr:full":"55b Winnellie Rd Winnellie NT 0820",
    "addr:housenumber":"55b",
    "addr:postcode":"nt 0820",
    "addr:street":"Winnellie Rd",
    "iso:country":"AU",
    "sg:address":"55b Winnellie Rd",
    "sg:city":"Winnellie",
    "sg:classifiers":[
        {
            "category":"Structure",
            "subcategory":"Bridge",
            "type":"Public Place"
        }
    ],
    "sg:phone":"+61 8 8984 3008",
    "sg:postcode":"0820",
    "sg:province":"NT",
    "sg:tags":[
        "chainsaw",
        "brushcutters"
    ],
    "wof:name":"Northern Edge Services",
    "wof:placetype":"venue"
},
  "geometry": {"coordinates":[130.878341675,-12.4264888763],"type":"Point"}
}