{
  "type": "Feature",
  "properties": {
    "addr:full":"31 Mercator Pde St Huberts Island NSW 2257",
    "addr:housenumber":"31",
    "addr:postcode":"2257",
    "addr:street":"Mercator Pde St",
    "iso:country":"AU",
    "sg:address":"31 Mercator Pde St",
    "sg:city":"Huberts Island",
    "sg:classifiers":[
        {
            "category":"Health Services",
            "subcategory":"Health Practitioner",
            "type":"Services"
        }
    ],
    "sg:phone":"+61 419 632 220",
    "sg:postcode":"2257",
    "sg:province":"NSW",
    "sg:tags":[
        "physiotherapist"
    ],
    "wof:name":"Lisa Swan Physiotherapy",
    "wof:placetype":"venue"
},
  "geometry": {"coordinates":[151.344238281,-33.4985542297],"type":"Point"}
}