{
  "type": "Feature",
  "properties": {
    "addr:full":"89-91 Frost Rd Salisbury South SA 5106",
    "addr:housenumber":"89-91",
    "addr:postcode":"5106",
    "addr:street":"Frost Rd",
    "iso:country":"AU",
    "sg:address":"89-91 Frost Rd",
    "sg:city":"Salisbury South",
    "sg:classifiers":[
        {
            "category":"Autos & Motor Vehicles",
            "subcategory":"Automobile Sales",
            "type":"Retail Goods"
        }
    ],
    "sg:phone":"+61 8 8285 7233",
    "sg:postcode":"5106",
    "sg:province":"SA",
    "sg:tags":[
        "car",
        "used"
    ],
    "wof:name":"Cheviot Car Sales",
    "wof:placetype":"venue"
},
  "geometry": {"coordinates":[138.64837600000001,-34.779736],"type":"Point"}
}