{
  "type": "Feature",
  "properties": {
    "addr:full":"Dubbo Rd Coonamble NSW 2829",
    "addr:postcode":"2829",
    "addr:street":"Dubbo Rd",
    "iso:country":"AU",
    "sg:address":"Dubbo Rd",
    "sg:city":"Coonamble",
    "sg:classifiers":[
        {
            "category":"Building & Trades",
            "subcategory":"Equipment Rental",
            "type":"Services"
        }
    ],
    "sg:phone":"+61 2 6822 2668",
    "sg:postcode":"2829",
    "sg:province":"NSW",
    "sg:tags":[
        "crane",
        "hire"
    ],
    "wof:name":"Todd Joyce",
    "wof:placetype":"venue"
},
  "geometry": {"coordinates":[148.39398193400001,-30.9539432526],"type":"Point"}
}