{
  "type": "Feature",
  "properties": {
    "iso:country":"AU",
    "sg:address":"Level 1, 237- 239 Unley Rd",
    "sg:city":"Malvern",
    "sg:classifiers":[
        {
            "category":"Education",
            "subcategory":"Vocational School",
            "type":"Public Place"
        }
    ],
    "sg:phone":"+61 8 8373 4375",
    "sg:postcode":"5061",
    "sg:province":"SA",
    "sg:tags":[
        "beauty"
    ],
    "wof:name":"Hyde Park College Of Skin And Body Therapy",
    "wof:placetype":"venue"
},
  "geometry": {"coordinates":[138.608154297,-34.9566307068],"type":"Point"}
}