{
  "type": "Feature",
  "properties": {
    "addr:full":"228 Settlement Rd Thomastown VIC 3074",
    "addr:housenumber":"228",
    "addr:postcode":"3074",
    "addr:street":"Settlement Rd",
    "iso:country":"AU",
    "sg:address":"228 Settlement Rd",
    "sg:city":"Thomastown",
    "sg:classifiers":[
        {
            "category":"Retail",
            "subcategory":"Auto Repair",
            "type":"Services"
        }
    ],
    "sg:phone":"+61 3 9464 2249",
    "sg:postcode":"3074",
    "sg:province":"VIC",
    "sg:tags":[
        "repairer",
        "motor",
        "engineer"
    ],
    "wof:name":"Future Auto Care",
    "wof:placetype":"venue"
},
  "geometry": {"coordinates":[145.03305053700001,-37.6936187744],"type":"Point"}
}