{
  "type": "Feature",
  "properties": {
    "addr:full":"79 Kenbrae Ave Glenorchy TAS 7010",
    "addr:housenumber":"79",
    "addr:postcode":"7010",
    "addr:street":"Kenbrae Ave",
    "iso:country":"AU",
    "sg:address":"79 Kenbrae Ave",
    "sg:city":"Glenorchy",
    "sg:classifiers":[
        {
            "category":"Building & Trades",
            "subcategory":"Equipment Rental",
            "type":"Services"
        }
    ],
    "sg:phone":"+61 3 6273 4040",
    "sg:postcode":"7010",
    "sg:province":"TAS",
    "sg:tags":[
        "supply",
        "catering"
    ],
    "wof:name":"Angelo Po",
    "wof:placetype":"venue"
},
  "geometry": {"coordinates":[147.25897216800001,-42.8332824707],"type":"Point"}
}