{
  "type": "Feature",
  "properties": {
    "addr:full":"6 Queen St Bendigo VIC 3550",
    "addr:housenumber":"6",
    "addr:postcode":"3550",
    "addr:street":"Queen St",
    "iso:country":"AU",
    "sg:address":"6 Queen St",
    "sg:city":"Bendigo",
    "sg:classifiers":[
        {
            "category":"Shopping",
            "subcategory":"Clothing, Apparel, & Fashions",
            "type":"Retail Goods"
        }
    ],
    "sg:phone":"+61 3 5443 5011",
    "sg:postcode":"3550",
    "sg:province":"VIC",
    "sg:tags":[
        "boutique"
    ],
    "wof:name":"McCalmans Boutique",
    "wof:placetype":"venue"
},
  "geometry": {"coordinates":[144.280517578,-36.7609863281],"type":"Point"}
}