{
  "type": "Feature",
  "properties": {
    "addr:full":"616 Darling St Rozelle NSW 2039",
    "addr:housenumber":"616",
    "addr:postcode":"2039",
    "addr:street":"Darling St",
    "iso:country":"AU",
    "sg:address":"616 Darling St",
    "sg:city":"Rozelle",
    "sg:classifiers":[
        {
            "category":"Shopping",
            "subcategory":"Antiques",
            "type":"Retail Goods"
        }
    ],
    "sg:phone":"+61 2 9818 5839",
    "sg:postcode":"2039",
    "sg:province":"NSW",
    "wof:name":"Ancestry Antiques",
    "wof:placetype":"venue"
},
  "geometry": {"coordinates":[151.17132568400001,-33.8619804382],"type":"Point"}
}