{
  "type": "Feature",
  "properties": {
    "iso:country":"AU",
    "sg:address":"629 Wynnum Rd",
    "sg:city":"Morningside",
    "sg:classifiers":[
        {
            "category":"Food & Beverages",
            "subcategory":"Bakery",
            "type":"Retail Goods"
        }
    ],
    "sg:phone":"+61 7 3399 4151",
    "sg:postcode":"4170",
    "sg:province":"QLD",
    "sg:tags":[
        "baker"
    ],
    "wof:name":"Boulevard Bakery",
    "wof:placetype":"venue"
},
  "geometry": {"coordinates":[153.07142639200001,-27.4685077667],"type":"Point"}
}