{
  "type": "Feature",
  "properties": {
    "addr:full":"3/ 81 Holder Way Malaga WA 6090",
    "addr:housenumber":"/ 81",
    "addr:postcode":"6090",
    "addr:street":"Holder Way",
    "iso:country":"AU",
    "sg:address":"3/ 81",
    "sg:city":"Holder Way Malaga",
    "sg:classifiers":[
        {
            "category":"Social Services",
            "type":"Services"
        }
    ],
    "sg:phone":"+61 417 986 617",
    "sg:postcode":"6090",
    "sg:province":"WA",
    "sg:tags":[
        "disabled",
        "person",
        "equipment"
    ],
    "wof:name":"Tread-Rite",
    "wof:placetype":"venue"
},
  "geometry": {"coordinates":[115.890419006,-31.8585128784],"type":"Point"}
}