{
  "type": "Feature",
  "properties": {
    "iso:country":"AU",
    "sg:address":"350 Como Pde",
    "sg:city":"(West) Parkdale",
    "sg:classifiers":[
        {
            "category":"Retail",
            "subcategory":"Veterinary Services",
            "type":"Services"
        }
    ],
    "sg:phone":"+61 3 9580 3785",
    "sg:postcode":"3195",
    "sg:province":"VIC",
    "sg:tags":[
        "surgeon"
    ],
    "wof:name":"Parkdale Veterinary Clinic",
    "wof:placetype":"venue"
},
  "geometry": {"coordinates":[145.07835388199999,-37.9953231812],"type":"Point"}
}