{
  "type": "Feature",
  "properties": {
    "addr:full":"6 Iraking Ave Moorebank NSW 2170",
    "addr:housenumber":"6",
    "addr:postcode":"2170",
    "addr:street":"Iraking Ave",
    "iso:country":"AU",
    "sg:address":"6 Iraking Ave",
    "sg:city":"Moorebank",
    "sg:classifiers":[
        {
            "category":"Professional",
            "subcategory":"Detective & Security Services",
            "type":"Services"
        }
    ],
    "sg:phone":"+61 2 9602 0888",
    "sg:postcode":"2170",
    "sg:province":"NSW",
    "sg:tags":[
        "consultant",
        "laser"
    ],
    "wof:name":"Laser FX",
    "wof:placetype":"venue"
},
  "geometry": {"coordinates":[150.938720703,-33.9375686646],"type":"Point"}
}