{
  "type": "Feature",
  "properties": {
    "addr:full":"102 Muriawang Rd Murray Bridge SA 5253",
    "addr:housenumber":"102",
    "addr:postcode":"5253",
    "addr:street":"Muriawang Rd",
    "iso:country":"AU",
    "sg:address":"102 Muriawang Rd",
    "sg:city":"Murray Bridge",
    "sg:classifiers":[
        {
            "category":"Commercial Area",
            "type":"Public Place"
        }
    ],
    "sg:phone":"+61 408 813 449",
    "sg:postcode":"5253",
    "sg:province":"SA",
    "sg:tags":[
        "heavy",
        "carrier"
    ],
    "wof:name":"Earthworks Solutions Pty Ltd",
    "wof:placetype":"venue"
},
  "geometry": {"coordinates":[139.35313415499999,-35.0634841919],"type":"Point"}
}