{
  "type": "Feature",
  "properties": {
    "addr:full":"34 Eagleview Rd Minto NSW 2566",
    "addr:housenumber":"34",
    "addr:postcode":"2566",
    "addr:street":"Eagleview Rd",
    "iso:country":"AU",
    "sg:address":"34 Eagleview Rd",
    "sg:city":"Minto",
    "sg:classifiers":[
        {
            "category":"Banks & Credit Unions",
            "subcategory":"Bureau De Change",
            "type":"Services"
        }
    ],
    "sg:phone":"+61 2 9603 4105",
    "sg:postcode":"2566",
    "sg:province":"NSW",
    "sg:tags":[
        "supply",
        "equipment",
        "beating",
        "panel"
    ],
    "wof:name":"S & L Jackson Panel Beating Supplies Pty Ltd",
    "wof:placetype":"venue"
},
  "geometry": {"coordinates":[150.860595703,-34.0300979614],"type":"Point"}
}