{
  "type": "Feature",
  "properties": {
    "addr:full":"11 Walsh Crt Coromandel Valley SA 5051",
    "addr:housenumber":"11",
    "addr:postcode":"5051",
    "addr:street":"Walsh Crt",
    "iso:country":"AU",
    "sg:address":"11 Walsh Crt",
    "sg:city":"Coromandel Valley",
    "sg:classifiers":[
        {
            "category":"Personal",
            "type":"Services"
        }
    ],
    "sg:phone":"+61 8 8270 6699",
    "sg:postcode":"5051",
    "sg:province":"SA",
    "sg:tags":[
        "gift"
    ],
    "wof:name":"A Message in a Bottle",
    "wof:placetype":"venue"
},
  "geometry": {"coordinates":[138.62275700000001,-35.048855],"type":"Point"}
}