{
  "type": "Feature",
  "properties": {
    "addr:full":"74 Erskine St Dubbo NSW 2830",
    "addr:housenumber":"74",
    "addr:postcode":"2830",
    "addr:street":"Erskine St",
    "iso:country":"AU",
    "sg:address":"74 Erskine St",
    "sg:city":"Dubbo",
    "sg:classifiers":[
        {
            "category":"Retail",
            "subcategory":"Car Wash",
            "type":"Services"
        }
    ],
    "sg:phone":"+61 2 6885 1355",
    "sg:postcode":"2830",
    "sg:province":"NSW",
    "sg:tags":[
        "truck",
        "cleaning"
    ],
    "wof:name":"Mr Magic Car Wash & Car Detailing",
    "wof:placetype":"venue"
},
  "geometry": {"coordinates":[148.60392761200001,-32.2428588867],"type":"Point"}
}