{
  "type": "Feature",
  "properties": {
    "addr:full":"740 Doncaster Rd Doncaster VIC 3108",
    "addr:housenumber":"740",
    "addr:postcode":"3108",
    "addr:street":"Doncaster Rd",
    "iso:country":"AU",
    "sg:address":"740 Doncaster Rd",
    "sg:city":"Doncaster",
    "sg:classifiers":[
        {
            "category":"Professional",
            "subcategory":"Accounting & Tax Preparation",
            "type":"Services"
        }
    ],
    "sg:phone":"+61 3 9848 4883",
    "sg:postcode":"3108",
    "sg:province":"VIC",
    "sg:tags":[
        "accountant",
        "auditor"
    ],
    "wof:name":"Wong Melville & Associates",
    "wof:placetype":"venue"
},
  "geometry": {"coordinates":[145.13543701200001,-37.7869033813],"type":"Point"}
}