{
  "type": "Feature",
  "properties": {
    "iso:country":"AU",
    "sg:address":"Kurrajong Rd",
    "sg:city":"Prestons",
    "sg:classifiers":[
        {
            "category":"Education",
            "subcategory":"School",
            "type":"Public Place"
        }
    ],
    "sg:phone":"+61 2 9602 7435",
    "sg:postcode":"2170",
    "sg:province":"NSW",
    "sg:tags":[
        "state",
        "-",
        "nsw"
    ],
    "wof:name":"Prestons Public School",
    "wof:placetype":"venue"
},
  "geometry": {"coordinates":[150.86982727,-33.9425468445],"type":"Point"}
}