{
  "type": "Feature",
  "properties": {
    "iso:country":"AU",
    "sg:address":"38 Wellington St",
    "sg:city":"Mackay",
    "sg:classifiers":[
        {
            "category":"Professional",
            "subcategory":"Art Services",
            "type":"Services"
        }
    ],
    "sg:phone":"+61 7 4957 6588",
    "sg:postcode":"4740",
    "sg:province":"QLD",
    "sg:tags":[
        "graphic",
        "designer"
    ],
    "wof:name":"BB Print",
    "wof:placetype":"venue"
},
  "geometry": {"coordinates":[149.179596,-21.148018],"type":"Point"}
}