{
  "type": "Feature",
  "properties": {
    "iso:country":"AU",
    "sg:address":"5/187- 201 Rooks Rd",
    "sg:city":"Nunawading",
    "sg:classifiers":[
        {
            "category":"Wholesale",
            "subcategory":"Auto Parts",
            "type":"Manufacturing & Wholesale Goods"
        }
    ],
    "sg:phone":"+61 3 9873 4755",
    "sg:postcode":"3131",
    "sg:province":"VIC",
    "sg:tags":[
        "recyclers"
    ],
    "wof:name":"Australasian Auto Parts Pty Ltd",
    "wof:placetype":"venue"
},
  "geometry": {"coordinates":[145.18844604500001,-37.8364677429],"type":"Point"}
}