{
  "type": "Feature",
  "properties": {
    "addr:full":"Shop 8 12 Delwood St Granville NSW 2142",
    "addr:housenumber":"shop;12",
    "addr:postcode":"2142",
    "addr:street":"Delwood St",
    "iso:country":"AU",
    "sg:address":"Shop 8 12 Delwood St",
    "sg:city":"Granville",
    "sg:classifiers":[
        {
            "category":"Communications",
            "subcategory":"Film & Video Production",
            "type":"Services"
        }
    ],
    "sg:phone":"+61 2 9682 1430",
    "sg:postcode":"2142",
    "sg:province":"NSW",
    "sg:tags":[
        "dvd",
        "library"
    ],
    "wof:name":"Home Pics Video",
    "wof:placetype":"venue"
},
  "geometry": {"coordinates":[151.00971984899999,-33.8535346985],"type":"Point"}
}