{
  "type": "Feature",
  "properties": {
    "addr:full":"134 Hassall St Wetherill Park NSW 2164",
    "addr:housenumber":"134",
    "addr:postcode":"2164",
    "addr:street":"Hassall St",
    "iso:country":"AU",
    "sg:address":"134 Hassall St",
    "sg:city":"Wetherill Park",
    "sg:classifiers":[
        {
            "category":"Utilities",
            "subcategory":"Cable",
            "type":"Services"
        }
    ],
    "sg:phone":"+61 2 9756 6300",
    "sg:postcode":"2164",
    "sg:province":"NSW",
    "sg:tags":[
        "wholesaler",
        "wire",
        "mfrs"
    ],
    "wof:name":"Austral Wire Products",
    "wof:placetype":"venue"
},
  "geometry": {"coordinates":[150.912963867,-33.839969635],"type":"Point"}
}