{
  "type": "Feature",
  "properties": {
    "addr:full":"288 Rathdowne St Carlton North VIC 3054",
    "addr:housenumber":"288",
    "addr:postcode":"3054",
    "addr:street":"Rathdowne St",
    "iso:country":"AU",
    "sg:address":"288 Rathdowne St",
    "sg:city":"Carlton North",
    "sg:classifiers":[
        {
            "category":"Cafe",
            "type":"Food & Drink"
        }
    ],
    "sg:phone":"+61 3 9348 2998",
    "sg:postcode":"3054",
    "sg:province":"VIC",
    "wof:name":"Sweet Source",
    "wof:placetype":"venue"
},
  "geometry": {"coordinates":[144.97174072300001,-37.7918243408],"type":"Point"}
}