{
  "type": "Feature",
  "properties": {
    "addr:full":"43 Church St Lidcombe NSW 2141",
    "addr:housenumber":"43",
    "addr:postcode":"2141",
    "addr:street":"Church St",
    "iso:country":"AU",
    "sg:address":"43 Church St",
    "sg:city":"Lidcombe",
    "sg:classifiers":[
        {
            "category":"Health Services",
            "subcategory":"Nursing And Care Facility",
            "type":"Services"
        }
    ],
    "sg:phone":"+61 2 9749 4637",
    "sg:postcode":"2141",
    "sg:province":"NSW",
    "sg:tags":[
        "home"
    ],
    "wof:name":"St Joachims Nursing Home",
    "wof:placetype":"venue"
},
  "geometry": {"coordinates":[151.04327392600001,-33.8622550964],"type":"Point"}
}