{
  "type": "Feature",
  "properties": {
    "addr:full":"31 Essex St Pascoe Vale VIC 3044",
    "addr:housenumber":"31",
    "addr:postcode":"3044",
    "addr:street":"Essex St",
    "iso:country":"AU",
    "sg:address":"31 Essex St",
    "sg:city":"Pascoe Vale",
    "sg:classifiers":[
        {
            "category":"Banks & Credit Unions",
            "subcategory":"Bank",
            "type":"Services"
        }
    ],
    "sg:phone":"+61 3 9319 9800",
    "sg:postcode":"3044",
    "sg:province":"VIC",
    "sg:tags":[
        "equipment",
        "sale",
        "point"
    ],
    "wof:name":"Display & Design International",
    "wof:placetype":"venue"
},
  "geometry": {"coordinates":[144.94944763199999,-37.7276535034],"type":"Point"}
}