{
  "type": "Feature",
  "properties": {
    "addr:full":"level 67, MLC Centre, 19-29 Martin Pl Sydney NSW 2000",
    "addr:housenumber":"19-29",
    "addr:postcode":"2000",
    "addr:street":"Martin Pl",
    "iso:country":"AU",
    "sg:address":"level 67, MLC Centre, 19-29 Martin Pl",
    "sg:city":"Sydney",
    "sg:classifiers":[
        {
            "category":"Professional",
            "subcategory":"Accounting & Tax Preparation",
            "type":"Services"
        }
    ],
    "sg:phone":"+61 2 9238 2011",
    "sg:postcode":"2000",
    "sg:province":"NSW",
    "sg:tags":[
        "accountant",
        "auditor"
    ],
    "wof:name":"Robertson Shanahan",
    "wof:placetype":"venue"
},
  "geometry": {"coordinates":[151.20866394000001,-33.8676757812],"type":"Point"}
}