{
  "type": "Feature",
  "properties": {
    "addr:full":"2 Boisdale St Maffra VIC 3860",
    "addr:housenumber":"2",
    "addr:postcode":"3860",
    "addr:street":"Boisdale St",
    "iso:country":"AU",
    "sg:address":"2 Boisdale St",
    "sg:city":"Maffra",
    "sg:classifiers":[
        {
            "category":"Professional",
            "subcategory":"Computer Services",
            "type":"Services"
        }
    ],
    "sg:phone":"+61 3 5147 3051",
    "sg:postcode":"3860",
    "sg:province":"VIC",
    "sg:tags":[
        "repairs",
        "upgrade",
        "equipment"
    ],
    "wof:name":"T P C Gippsland Computers",
    "wof:placetype":"venue"
},
  "geometry": {"coordinates":[146.98272705100001,-37.9702568054],"type":"Point"}
}