{
  "type": "Feature",
  "properties": {
    "addr:full":"Buderim Meadows Shop 3, 163 Karawatha St Buderim QLD 4556",
    "addr:housenumber":"3 163",
    "addr:postcode":"4556",
    "addr:street":"Karawatha St",
    "iso:country":"AU",
    "sg:address":"Buderim Meadows Shop 3, 163 Karawatha St",
    "sg:city":"Buderim",
    "sg:classifiers":[
        {
            "category":"Food & Beverages",
            "subcategory":"Liquor & Beverages",
            "type":"Retail Goods"
        }
    ],
    "sg:phone":"+61 7 5444 8016",
    "sg:postcode":"4556",
    "sg:province":"QLD",
    "sg:tags":[
        "store"
    ],
    "wof:name":"BWS Liquor Stores",
    "wof:placetype":"venue"
},
  "geometry": {"coordinates":[153.08445739699999,-26.6959247589],"type":"Point"}
}