{
  "type": "Feature",
  "properties": {
    "iso:country":"AU",
    "sg:address":"10 Endeavour St",
    "sg:city":"Mackay",
    "sg:classifiers":[
        {
            "category":"Wholesale",
            "subcategory":"Seafood",
            "type":"Manufacturing & Wholesale Goods"
        }
    ],
    "sg:phone":"+61 7 4951 2477",
    "sg:postcode":"4740",
    "sg:province":"QLD",
    "sg:tags":[
        "fish"
    ],
    "wof:name":"Endeavour Seafoods",
    "wof:placetype":"venue"
},
  "geometry": {"coordinates":[149.19416799999999,-21.143375],"type":"Point"}
}