{
  "type": "Feature",
  "properties": {
    "iso:country":"AU",
    "sg:address":"15 Nolan St",
    "sg:city":"Maryborough",
    "sg:classifiers":[
        {
            "category":"Building & Trades",
            "subcategory":"Construction",
            "type":"Services"
        }
    ],
    "sg:phone":"+61 3 5460 5181",
    "sg:postcode":"3465",
    "sg:province":"VIC",
    "sg:tags":[
        "polishing",
        "sanding",
        "floor"
    ],
    "wof:name":"Attwoods Floor Sanding & Polishing",
    "wof:placetype":"venue"
},
  "geometry": {"coordinates":[143.74020385700001,-37.0514793396],"type":"Point"}
}