{
  "type": "Feature",
  "properties": {
    "iso:country":"AU",
    "sg:address":"16 Bundaroo St",
    "sg:city":"Bowral",
    "sg:classifiers":[
        {
            "category":"Personal",
            "subcategory":"Massage",
            "type":"Services"
        }
    ],
    "sg:phone":"+61 424 409 540",
    "sg:postcode":"2576",
    "sg:province":"NSW",
    "sg:tags":[
        "therapy"
    ],
    "wof:name":"Kim Bourke-Paull",
    "wof:placetype":"venue"
},
  "geometry": {"coordinates":[150.419799805,-34.4766693115],"type":"Point"}
}