{
  "type": "Feature",
  "properties": {
    "addr:full":"Gold Coast Arts Centre 135 Bundall Rd Bundall QLD 4217",
    "addr:housenumber":"135",
    "addr:postcode":"4217",
    "addr:street":"Bundall Rd",
    "iso:country":"AU",
    "sg:address":"Gold Coast Arts Centre 135 Bundall Rd",
    "sg:city":"Bundall",
    "sg:classifiers":[
        {
            "category":"Manufacturing",
            "subcategory":"Food",
            "type":"Manufacturing & Wholesale Goods"
        }
    ],
    "sg:phone":"+61 7 5581 6584",
    "sg:postcode":"4217",
    "sg:province":"QLD",
    "sg:tags":[
        "function",
        "catering"
    ],
    "wof:name":"Arts Restaurant",
    "wof:placetype":"venue"
},
  "geometry": {"coordinates":[153.41403198200001,-28.0024394989],"type":"Point"}
}