{
  "type": "Feature",
  "properties": {
    "iso:country":"AU",
    "sg:address":"34 Bell St",
    "sg:city":"Torquay",
    "sg:classifiers":[
        {
            "category":"Arena",
            "subcategory":"Sports Club",
            "type":"Entertainment"
        }
    ],
    "sg:phone":"+61 3 5261 2022",
    "sg:postcode":"3228",
    "sg:province":"VIC",
    "sg:tags":[
        "life",
        "surfing",
        "saving"
    ],
    "wof:name":"Torquay Surfing Academy",
    "wof:placetype":"venue"
},
  "geometry": {"coordinates":[144.319717,-38.33744],"type":"Point"}
}