{
  "type": "Feature",
  "properties": {
    "addr:full":"158 Nelson Pl Williamstown VIC 3016",
    "addr:housenumber":"158",
    "addr:postcode":"3016",
    "addr:street":"Nelson Pl",
    "iso:country":"AU",
    "sg:address":"158 Nelson Pl",
    "sg:city":"Williamstown",
    "sg:classifiers":[
        {
            "category":"Recreation",
            "subcategory":"Boat Charter",
            "type":"Entertainment"
        }
    ],
    "sg:phone":"+61 3 9397 8588",
    "sg:postcode":"3016",
    "sg:province":"VIC",
    "sg:tags":[
        "canopy",
        "motor"
    ],
    "wof:name":"Bayside Boat Covers",
    "wof:placetype":"venue"
},
  "geometry": {"coordinates":[144.90301513700001,-37.8621139526],"type":"Point"}
}