{
  "type": "Feature",
  "properties": {
    "iso:country":"AU",
    "sg:address":"55 Thuringowa Dr",
    "sg:city":"Kirwan",
    "sg:classifiers":[
        {
            "category":"Real Estate",
            "subcategory":"Real Estate Agent",
            "type":"Services"
        }
    ],
    "sg:phone":"+61 7 4755 1800",
    "sg:postcode":"4817",
    "sg:province":"QLD",
    "wof:name":"The Rental Managers",
    "wof:placetype":"venue"
},
  "geometry": {"coordinates":[146.73069799999999,-19.311165],"type":"Point"}
}