{
  "type": "Feature",
  "properties": {
    "addr:full":"PO Box 57 Bexley South NSW 2207",
    "addr:postcode":"2207",
    "iso:country":"AU",
    "sg:address":"PO Box 57",
    "sg:city":"Bexley South",
    "sg:classifiers":[
        {
            "category":"Utilities",
            "subcategory":"Electric",
            "type":"Services"
        }
    ],
    "sg:phone":"+61 2 9587 4346",
    "sg:postcode":"2207",
    "sg:province":"NSW",
    "sg:tags":[
        "electrical",
        "contractor"
    ],
    "wof:name":"Sinewave Electrical Contracting Pty Ltd",
    "wof:placetype":"venue"
},
  "geometry": {"coordinates":[151.11738600000001,-33.959549],"type":"Point"}
}