{
  "type": "Feature",
  "properties": {
    "addr:full":"150 Sheridan St Cairns QLD 4870",
    "addr:housenumber":"150",
    "addr:postcode":"4870",
    "addr:street":"Sheridan St",
    "iso:country":"AU",
    "sg:address":"150 Sheridan St",
    "sg:city":"Cairns",
    "sg:classifiers":[
        {
            "category":"Travel",
            "subcategory":"Travel Agent",
            "type":"Entertainment"
        }
    ],
    "sg:phone":"+61 408 066 024",
    "sg:postcode":"4870",
    "sg:province":"QLD",
    "sg:tags":[
        "tour",
        "holiday",
        "adventure"
    ],
    "wof:name":"Choppers Motorcycle Tours & Hire",
    "wof:placetype":"venue"
},
  "geometry": {"coordinates":[145.76838684099999,-16.9170799255],"type":"Point"}
}