{
  "type": "Feature",
  "properties": {
    "addr:full":"109 Flinders La Melbourne VIC 3000",
    "addr:housenumber":"109",
    "addr:postcode":"3000",
    "addr:street":"Flinders La",
    "iso:country":"AU",
    "sg:address":"109 Flinders La",
    "sg:city":"Melbourne",
    "sg:classifiers":[
        {
            "category":"Real Estate",
            "subcategory":"Architect",
            "type":"Services"
        }
    ],
    "sg:phone":"+61 3 9650 2747",
    "sg:postcode":"3000",
    "sg:province":"VIC",
    "wof:name":"Cox Architects & Planners",
    "wof:placetype":"venue"
},
  "geometry": {"coordinates":[144.97071838400001,-37.8155174255],"type":"Point"}
}