{
  "type": "Feature",
  "properties": {
    "iso:country":"AU",
    "sg:address":"Tootals Rd",
    "sg:city":"Dingley Village",
    "sg:classifiers":[
        {
            "category":"Utilities",
            "subcategory":"Refuse",
            "type":"Services"
        }
    ],
    "sg:phone":"+61 3 9551 5039",
    "sg:postcode":"3172",
    "sg:province":"VIC",
    "sg:tags":[
        "disposal",
        "reduction",
        "waste"
    ],
    "wof:name":"Din San Reclamation (Tip)",
    "wof:placetype":"venue"
},
  "geometry": {"coordinates":[145.12156677199999,-37.9725723267],"type":"Point"}
}