{
  "type": "Feature",
  "properties": {
    "addr:full":"60 Gleadow St Launceston TAS 7250",
    "addr:housenumber":"60",
    "addr:postcode":"7250",
    "addr:street":"Gleadow St",
    "iso:country":"AU",
    "sg:address":"60 Gleadow St",
    "sg:city":"Launceston",
    "sg:classifiers":[
        {
            "category":"Wholesale",
            "subcategory":"Painting Supplies",
            "type":"Manufacturing & Wholesale Goods"
        }
    ],
    "sg:phone":"+61 3 6331 4755",
    "sg:postcode":"7250",
    "sg:province":"TAS",
    "sg:tags":[
        "product",
        "cleaning"
    ],
    "wof:name":"Hunters Products (TAS) Pty Ltd",
    "wof:placetype":"venue"
},
  "geometry": {"coordinates":[147.13099670400001,-41.4276046753],"type":"Point"}
}