{
  "type": "Feature",
  "properties": {
    "addr:full":"Shp 5 Seaford Shopng Cntr, Cnr Commercial Rd Seaford Heights SA 5169",
    "addr:housenumber":"5",
    "addr:postcode":"5169",
    "addr:street":"Seaford Shopng Cntr Cnr Commercial Rd",
    "iso:country":"AU",
    "sg:address":"Shp 5 Seaford Shopng Cntr, Cnr Commercial Rd",
    "sg:city":"Seaford Heights",
    "sg:classifiers":[
        {
            "category":"Travel",
            "subcategory":"Travel Agent",
            "type":"Entertainment"
        }
    ],
    "sg:phone":"+61 8 8327 0666",
    "sg:postcode":"5169",
    "sg:province":"SA",
    "sg:tags":[
        "consultant"
    ],
    "wof:name":"Harvey World Travel",
    "wof:placetype":"venue"
},
  "geometry": {"coordinates":[138.47750854500001,-35.1907730103],"type":"Point"}
}