{
  "type": "Feature",
  "properties": {
    "iso:country":"AU",
    "sg:address":"142 Argyle St",
    "sg:city":"Hobart",
    "sg:classifiers":[
        {
            "category":"Banks & Credit Unions",
            "subcategory":"Investment Brokerage",
            "type":"Services"
        }
    ],
    "sg:phone":"+61 3 6231 2977",
    "sg:postcode":"7000",
    "sg:province":"TAS",
    "sg:tags":[
        "debt",
        "collection"
    ],
    "wof:name":"Collection Corporation of Australia Pty Ltd",
    "wof:placetype":"venue"
},
  "geometry": {"coordinates":[147.32324218799999,-42.8762435913],"type":"Point"}
}