{
  "type": "Feature",
  "properties": {
    "addr:full":"Break O' Day Rd Break Of Day VIC 3717",
    "addr:postcode":"3717",
    "addr:street":"Break;' Day Rd",
    "iso:country":"AU",
    "sg:address":"Break O' Day Rd",
    "sg:city":"Break Of Day",
    "sg:classifiers":[
        {
            "category":"Manufacturing",
            "subcategory":"Soap",
            "type":"Manufacturing & Wholesale Goods"
        }
    ],
    "sg:phone":"+61 3 5780 1515",
    "sg:postcode":"3717",
    "sg:province":"VIC",
    "sg:tags":[
        "detergent"
    ],
    "wof:name":"Rambilldeene Farm Soap",
    "wof:placetype":"venue"
},
  "geometry": {"coordinates":[145.45802307100001,-37.2794799805],"type":"Point"}
}