{
  "type": "Feature",
  "properties": {
    "iso:country":"AU",
    "sg:address":"Unit 4, 7 Birubi St",
    "sg:city":"Coorparoo",
    "sg:classifiers":[
        {
            "category":"Utilities",
            "subcategory":"Telephone",
            "type":"Services"
        }
    ],
    "sg:phone":"+61 1300 133 996",
    "sg:postcode":"4151",
    "sg:province":"QLD",
    "sg:tags":[
        "equipment",
        "system"
    ],
    "wof:name":"Australian Telephone Services",
    "wof:placetype":"venue"
},
  "geometry": {"coordinates":[153.05538940400001,-27.4866714478],"type":"Point"}
}