{
  "type": "Feature",
  "properties": {
    "addr:full":"236 Marius St Tamworth NSW 2340",
    "addr:housenumber":"236",
    "addr:postcode":"2340",
    "addr:street":"Marius St",
    "iso:country":"AU",
    "sg:address":"236 Marius St",
    "sg:city":"Tamworth",
    "sg:classifiers":[
        {
            "category":"Professional",
            "subcategory":"Art Services",
            "type":"Services"
        }
    ],
    "sg:phone":"+61 2 6766 6992",
    "sg:postcode":"2340",
    "sg:province":"NSW",
    "sg:tags":[
        "graphic",
        "designer"
    ],
    "wof:name":"Pedigree Print",
    "wof:placetype":"venue"
},
  "geometry": {"coordinates":[150.93510437,-31.0926151276],"type":"Point"}
}