{
  "type": "Feature",
  "properties": {
    "addr:full":"69 MacQuarie St Mayfield NSW 2304",
    "addr:housenumber":"69",
    "addr:postcode":"2304",
    "addr:street":"Macquarie St",
    "iso:country":"AU",
    "sg:address":"69 MacQuarie St",
    "sg:city":"Mayfield",
    "sg:classifiers":[
        {
            "category":"Building & Trades",
            "subcategory":"Construction",
            "type":"Services"
        }
    ],
    "sg:phone":"+61 2 4967 5500",
    "sg:postcode":"2304",
    "sg:province":"NSW",
    "sg:tags":[
        "contractor"
    ],
    "wof:name":"Positive Carpentry Pty Ltd",
    "wof:placetype":"venue"
},
  "geometry": {"coordinates":[151.73324585,-32.8999404907],"type":"Point"}
}