{
  "type": "Feature",
  "properties": {
    "addr:full":"399 Perwillowen Rd Nambour QLD 4560",
    "addr:housenumber":"399",
    "addr:postcode":"4560",
    "addr:street":"Perwillowen Rd",
    "iso:country":"AU",
    "sg:address":"399 Perwillowen Rd",
    "sg:city":"Nambour",
    "sg:classifiers":[
        {
            "category":"Personal",
            "subcategory":"Massage",
            "type":"Services"
        }
    ],
    "sg:phone":"+61 7 5441 1928",
    "sg:postcode":"4560",
    "sg:province":"QLD",
    "sg:tags":[
        "therapy"
    ],
    "wof:name":"Ralph Williams",
    "wof:placetype":"venue"
},
  "geometry": {"coordinates":[152.92590332,-26.6376171112],"type":"Point"}
}