{
  "type": "Feature",
  "properties": {
    "addr:full":"Shop 5 Argyle & Campdey St Wilton NSW 2571",
    "addr:housenumber":"shop 5",
    "addr:postcode":"2571",
    "addr:street":"St",
    "iso:country":"AU",
    "sg:address":"Shop 5 Argyle & Campdey St",
    "sg:city":"Wilton",
    "sg:classifiers":[
        {
            "category":"Fast Food",
            "type":"Food & Drink"
        }
    ],
    "sg:phone":"+61 2 4630 9003",
    "sg:postcode":"2571",
    "sg:province":"NSW",
    "sg:tags":[
        "away",
        "take"
    ],
    "wof:name":"Wilton Take-Away",
    "wof:placetype":"venue"
},
  "geometry": {"coordinates":[150.667724609,-34.2295913696],"type":"Point"}
}