{
  "type": "Feature",
  "properties": {
    "iso:country":"AU",
    "sg:address":"148 Kern Brothers Drv",
    "sg:city":"Kirwan",
    "sg:classifiers":[
        {
            "category":"Professional",
            "subcategory":"Business Services",
            "type":"Services"
        }
    ],
    "sg:phone":"+61 7 4773 9990",
    "sg:postcode":"4817",
    "sg:province":"QLD",
    "sg:tags":[
        "consultant",
        "leasing"
    ],
    "wof:name":"Savvy Financial Solutions",
    "wof:placetype":"venue"
},
  "geometry": {"coordinates":[146.72671500000001,-19.304705],"type":"Point"}
}