{
  "type": "Feature",
  "properties": {
    "iso:country":"AU",
    "sg:address":"2 Stuart St",
    "sg:city":"Kempsey",
    "sg:classifiers":[
        {
            "category":"Autos & Motor Vehicles",
            "subcategory":"Auto Supplies",
            "type":"Retail Goods"
        }
    ],
    "sg:phone":"+61 2 6562 8080",
    "sg:postcode":"2440",
    "sg:province":"NSW",
    "sg:tags":[
        "tyre"
    ],
    "wof:name":"Kempsey Tyre Service",
    "wof:placetype":"venue"
},
  "geometry": {"coordinates":[152.83947800000001,-31.07881],"type":"Point"}
}