{
  "type": "Feature",
  "properties": {
    "iso:country":"AU",
    "sg:address":"601 Little Collins St",
    "sg:city":"Melbourne",
    "sg:classifiers":[
        {
            "category":"Professional",
            "subcategory":"Business Services",
            "type":"Services"
        }
    ],
    "sg:phone":"+61 3 9629 6244",
    "sg:postcode":"3000",
    "sg:province":"VIC",
    "sg:tags":[
        "record",
        "management",
        "storage"
    ],
    "wof:name":"Strata Storage",
    "wof:placetype":"venue"
},
  "geometry": {"coordinates":[144.95503234899999,-37.8178291321],"type":"Point"}
}