{
  "type": "Feature",
  "properties": {
    "addr:full":"17 Hull Rd Beecroft NSW 2119",
    "addr:housenumber":"17",
    "addr:postcode":"2119",
    "addr:street":"Hull Rd",
    "iso:country":"AU",
    "sg:address":"17 Hull Rd",
    "sg:city":"Beecroft",
    "sg:classifiers":[
        {
            "category":"Government",
            "subcategory":"Fire Station",
            "type":"Public Place"
        }
    ],
    "sg:phone":"+61 2 9484 6204",
    "sg:postcode":"2119",
    "sg:province":"NSW",
    "sg:tags":[
        "equipment",
        "protection",
        "consultant"
    ],
    "wof:name":"RG Asia Pacific",
    "wof:placetype":"venue"
},
  "geometry": {"coordinates":[151.058517456,-33.7516403198],"type":"Point"}
}