{
  "type": "Feature",
  "properties": {
    "iso:country":"AU",
    "sg:address":"Shop 4, Rooty Hill Rd South",
    "sg:city":"Rooty Hill",
    "sg:classifiers":[
        {
            "category":"Real Estate",
            "subcategory":"Real Estate Agent",
            "type":"Services"
        }
    ],
    "sg:phone":"+61 2 9832 7500",
    "sg:postcode":"2766",
    "sg:province":"NSW",
    "wof:name":"Richardson & Wrench Pty Ltd",
    "wof:placetype":"venue"
},
  "geometry": {"coordinates":[150.84463500999999,-33.7728881836],"type":"Point"}
}