{
  "type": "Feature",
  "properties": {
    "iso:country":"AU",
    "sg:address":"PO Box 162",
    "sg:city":"Moorooka",
    "sg:classifiers":[
        {
            "category":"Professional",
            "subcategory":"Employment Agencies",
            "type":"Services"
        }
    ],
    "sg:phone":"+61 418 452 077",
    "sg:postcode":"4105",
    "sg:province":"QLD",
    "sg:tags":[
        "entertainer",
        "agent"
    ],
    "wof:name":"A Clown Called Sparky",
    "wof:placetype":"venue"
},
  "geometry": {"coordinates":[153.02772522000001,-27.5332107544],"type":"Point"}
}