{
  "type": "Feature",
  "properties": {
    "addr:full":"38 Tweed St Brunswick Heads NSW 2483",
    "addr:housenumber":"38",
    "addr:postcode":"2483",
    "addr:street":"Tweed St",
    "iso:country":"AU",
    "sg:address":"38 Tweed St",
    "sg:city":"Brunswick Heads",
    "sg:classifiers":[
        {
            "category":"Retail",
            "subcategory":"Auto Repair",
            "type":"Services"
        }
    ],
    "sg:phone":"+61 2 6685 0255",
    "sg:postcode":"2483",
    "sg:province":"NSW",
    "sg:tags":[
        "beater",
        "painter",
        "panel"
    ],
    "wof:name":"Bashforth Darryl Smash Repairs & Used Cars",
    "wof:placetype":"venue"
},
  "geometry": {"coordinates":[153.54779052699999,-28.5406455994],"type":"Point"}
}