{
  "type": "Feature",
  "properties": {
    "iso:country":"AU",
    "sg:address":"52 Remly St",
    "sg:city":"Roselands",
    "sg:classifiers":[
        {
            "category":"Building & Trades",
            "subcategory":"Construction",
            "type":"Services"
        }
    ],
    "sg:phone":"+61 2 9759 4774",
    "sg:postcode":"2196",
    "sg:province":"NSW",
    "sg:tags":[
        "contractor"
    ],
    "wof:name":"Mihas Builders",
    "wof:placetype":"venue"
},
  "geometry": {"coordinates":[151.08200099999999,-33.93092],"type":"Point"}
}