{
  "type": "Feature",
  "properties": {
    "addr:full":"275 Clarence St Sydney NSW 2000",
    "addr:housenumber":"275",
    "addr:postcode":"2000",
    "addr:street":"Clarence St",
    "iso:country":"AU",
    "sg:address":"275 Clarence St",
    "sg:city":"Sydney",
    "sg:classifiers":[
        {
            "category":"Shopping",
            "subcategory":"Computers & Home Electronics",
            "type":"Retail Goods"
        }
    ],
    "sg:phone":"+61 2 9264 4116",
    "sg:postcode":"2000",
    "sg:province":"NSW",
    "sg:tags":[
        "equipment",
        "multimedia"
    ],
    "wof:name":"Expost Facto Pty Ltd",
    "wof:placetype":"venue"
},
  "geometry": {"coordinates":[151.205535889,-33.872379303],"type":"Point"}
}