{
  "type": "Feature",
  "properties": {
    "addr:full":"7/ 97 Lewis Rd Wantirna South VIC 3152",
    "addr:housenumber":"/ 97",
    "addr:postcode":"3152",
    "addr:street":"Lewis Rd",
    "iso:country":"AU",
    "sg:address":"7/ 97 Lewis Rd",
    "sg:city":"Wantirna South",
    "sg:classifiers":[
        {
            "category":"Building & Trades",
            "subcategory":"Plumbing",
            "type":"Services"
        }
    ],
    "sg:phone":"+61 3 9887 1300",
    "sg:postcode":"3152",
    "sg:province":"VIC",
    "sg:tags":[
        "fitting",
        "hose",
        "supply"
    ],
    "wof:name":"Stokes (Australasia) Limited",
    "wof:placetype":"venue"
},
  "geometry": {"coordinates":[145.25079345699999,-37.8677635193],"type":"Point"}
}