{
  "type": "Feature",
  "properties": {
    "addr:full":"98 Sunderland St Moonah TAS 7009",
    "addr:housenumber":"98",
    "addr:postcode":"7009",
    "addr:street":"Sunderland St",
    "iso:country":"AU",
    "sg:address":"98 Sunderland St",
    "sg:city":"Moonah",
    "sg:classifiers":[
        {
            "category":"Professional",
            "subcategory":"Engineering",
            "type":"Services"
        }
    ],
    "sg:phone":"+61 3 6272 8388",
    "sg:postcode":"7009",
    "sg:province":"TAS",
    "sg:tags":[
        "engineer"
    ],
    "wof:name":"Purden Engineers",
    "wof:placetype":"venue"
},
  "geometry": {"coordinates":[147.29290771500001,-42.8369865417],"type":"Point"}
}