{
  "type": "Feature",
  "properties": {
    "iso:country":"AU",
    "sg:address":"10 Fig St",
    "sg:city":"Yungaburra",
    "sg:classifiers":[
        {
            "category":"Autos & Motor Vehicles",
            "subcategory":"Automobile Sales",
            "type":"Retail Goods"
        }
    ],
    "sg:phone":"+61 7 4095 3763",
    "sg:postcode":"4884",
    "sg:province":"QLD",
    "sg:tags":[
        "equipment",
        "trailer"
    ],
    "wof:name":"Jonsson's Trailers",
    "wof:placetype":"venue"
},
  "geometry": {"coordinates":[145.58428955100001,-17.2719402313],"type":"Point"}
}