{
  "type": "Feature",
  "properties": {
    "iso:country":"AU",
    "sg:address":"187 Bagot Rd",
    "sg:city":"Ludmilla",
    "sg:classifiers":[
        {
            "category":"Food & Beverages",
            "subcategory":"Fruits & Vegetables",
            "type":"Retail Goods"
        }
    ],
    "sg:phone":"+61 8 8948 1670",
    "sg:postcode":"0820",
    "sg:province":"NT",
    "sg:tags":[
        "wholesale"
    ],
    "wof:name":"Marty's Fruit Shop",
    "wof:placetype":"venue"
},
  "geometry": {"coordinates":[130.856033325,-12.4102687836],"type":"Point"}
}