{
  "type": "Feature",
  "properties": {
    "iso:country":"AU",
    "sg:address":"38 Victor Ave",
    "sg:city":"Paradise Point",
    "sg:classifiers":[
        {
            "category":"Home & Garden",
            "subcategory":"Building Materials",
            "type":"Retail Goods"
        }
    ],
    "sg:phone":"+61 7 5529 6930",
    "sg:postcode":"4216",
    "sg:province":"QLD",
    "sg:tags":[
        "lawn",
        "cutting",
        "maintenance"
    ],
    "wof:name":"Kev & Channy",
    "wof:placetype":"venue"
},
  "geometry": {"coordinates":[153.39254760700001,-27.8838348389],"type":"Point"}
}