{
  "type": "Feature",
  "properties": {
    "addr:full":"U2/ 25 Paisley Drv Lawnton QLD 4501",
    "addr:housenumber":"25",
    "addr:postcode":"4501",
    "addr:street":"U2 /;Paisley Drv",
    "iso:country":"AU",
    "sg:address":"U2/ 25 Paisley Drv",
    "sg:city":"Lawnton",
    "sg:classifiers":[
        {
            "category":"Retail",
            "subcategory":"Auto Repair",
            "type":"Services"
        }
    ],
    "sg:phone":"+61 7 3205 1911",
    "sg:postcode":"4501",
    "sg:province":"QLD",
    "sg:tags":[
        "repairer",
        "motor",
        "engineer"
    ],
    "wof:name":"Performance Centre The",
    "wof:placetype":"venue"
},
  "geometry": {"coordinates":[152.98832702600001,-27.2837677002],"type":"Point"}
}