{
  "type": "Feature",
  "properties": {
    "iso:country":"AU",
    "sg:address":"PO Box 301",
    "sg:city":"Peregian Beach",
    "sg:classifiers":[
        {
            "category":"Professional",
            "subcategory":"Accounting & Tax Preparation",
            "type":"Services"
        }
    ],
    "sg:phone":"+61 7 5449 1782",
    "sg:postcode":"4573",
    "sg:province":"QLD",
    "sg:tags":[
        "bookkeeping"
    ],
    "wof:name":"Coastal Computer Accounting",
    "wof:placetype":"venue"
},
  "geometry": {"coordinates":[153.095215,-26.47817],"type":"Point"}
}