{
  "type": "Feature",
  "properties": {
    "addr:full":"22 Pental Rd Caulfield North VIC 3161",
    "addr:housenumber":"22",
    "addr:postcode":"3161",
    "addr:street":"Pental Rd",
    "iso:country":"AU",
    "sg:address":"22 Pental Rd",
    "sg:city":"Caulfield North",
    "sg:classifiers":[
        {
            "category":"Building & Trades",
            "subcategory":"Construction",
            "type":"Services"
        }
    ],
    "sg:phone":"+61 418 585 805",
    "sg:postcode":"3161",
    "sg:province":"VIC",
    "sg:tags":[
        "contractor"
    ],
    "wof:name":"Grandbuild Pty Ltd",
    "wof:placetype":"venue"
},
  "geometry": {"coordinates":[145.023880005,-37.8664741516],"type":"Point"}
}