{
  "type": "Feature",
  "properties": {
    "addr:full":"1 Hardy St North Bondi NSW 2026",
    "addr:housenumber":"1",
    "addr:postcode":"2026",
    "addr:street":"Hardy St",
    "iso:country":"AU",
    "sg:address":"1 Hardy St",
    "sg:city":"North Bondi",
    "sg:classifiers":[
        {
            "category":"Professional",
            "subcategory":"Computer Services",
            "type":"Services"
        }
    ],
    "sg:phone":"+61 414 405 007",
    "sg:postcode":"2026",
    "sg:province":"NSW",
    "sg:tags":[
        "repairs",
        "upgrade",
        "equipment"
    ],
    "wof:name":"Making It Right",
    "wof:placetype":"venue"
},
  "geometry": {"coordinates":[151.277053833,-33.881816864],"type":"Point"}
}