{
  "type": "Feature",
  "properties": {
    "iso:country":"AU",
    "sg:address":"3 Lowani Crt",
    "sg:city":"Richmond Hill",
    "sg:classifiers":[
        {
            "category":"Professional",
            "subcategory":"Accounting & Tax Preparation",
            "type":"Services"
        }
    ],
    "sg:phone":"+61 2 6624 2507",
    "sg:postcode":"2480",
    "sg:province":"NSW",
    "sg:tags":[
        "accountant",
        "auditor"
    ],
    "wof:name":"Lunnon W D",
    "wof:placetype":"venue"
},
  "geometry": {"coordinates":[153.355545044,-28.7933006287],"type":"Point"}
}