{
  "type": "Feature",
  "properties": {
    "iso:country":"AU",
    "sg:address":"969 Pacific Hwy",
    "sg:city":"Pymble",
    "sg:classifiers":[
        {
            "category":"Building & Trades",
            "subcategory":"Cleaning & Sanitation",
            "type":"Services"
        }
    ],
    "sg:phone":"+61 2 9983 9981",
    "sg:postcode":"2073",
    "sg:province":"NSW",
    "sg:tags":[
        "commercial",
        "maintenance"
    ],
    "wof:name":"Hammer & Tongs",
    "wof:placetype":"venue"
},
  "geometry": {"coordinates":[151.14356994600001,-33.7455406189],"type":"Point"}
}