{
  "type": "Feature",
  "properties": {
    "addr:full":"15 Merchant Ave Thomastown VIC 3074",
    "addr:housenumber":"15",
    "addr:postcode":"3074",
    "addr:street":"Merchant Ave",
    "iso:country":"AU",
    "sg:address":"15 Merchant Ave",
    "sg:city":"Thomastown",
    "sg:classifiers":[
        {
            "category":"Building & Trades",
            "subcategory":"Construction",
            "type":"Services"
        }
    ],
    "sg:phone":"+61 3 9465 0288",
    "sg:postcode":"3074",
    "sg:province":"VIC",
    "sg:tags":[
        "stonework",
        "stone",
        "mason"
    ],
    "wof:name":"MDM Imports Pty Ltd",
    "wof:placetype":"venue"
},
  "geometry": {"coordinates":[145.041748047,-37.6916465759],"type":"Point"}
}