{
  "type": "Feature",
  "properties": {
    "addr:full":"4/207 Balcatta Rd Balcatta WA 6021",
    "addr:housenumber":"/ 207",
    "addr:postcode":"6021",
    "addr:street":"Balcatta Rd",
    "iso:country":"AU",
    "sg:address":"4/207 Balcatta Rd",
    "sg:city":"Balcatta",
    "sg:classifiers":[
        {
            "category":"Insurance",
            "subcategory":"Insurance Agent",
            "type":"Services"
        }
    ],
    "sg:phone":"+61 8 9240 2760",
    "sg:postcode":"6021",
    "sg:province":"WA",
    "wof:name":"T C B Insurance & Superannuation Agencies Pty Ltd",
    "wof:placetype":"venue"
},
  "geometry": {"coordinates":[115.812049866,-31.8611087799],"type":"Point"}
}