{
  "type": "Feature",
  "properties": {
    "addr:full":"PO Box 2162 Hilton SA 5033",
    "addr:postcode":"5033",
    "iso:country":"AU",
    "sg:address":"PO Box 2162",
    "sg:city":"Hilton",
    "sg:classifiers":[
        {
            "category":"Banks & Credit Unions",
            "subcategory":"Bank",
            "type":"Services"
        }
    ],
    "sg:phone":"+61 8 8354 2882",
    "sg:postcode":"5033",
    "sg:province":"SA",
    "sg:tags":[
        "broker",
        "mortgage"
    ],
    "wof:name":"Synectic Financial",
    "wof:placetype":"venue"
},
  "geometry": {"coordinates":[138.56449890100001,-34.931350708],"type":"Point"}
}