{
  "type": "Feature",
  "properties": {
    "addr:full":"School Of Arts, Paterson Rd Paterson NSW 2421",
    "addr:postcode":"2421",
    "addr:street":"Paterson Rd",
    "iso:country":"AU",
    "sg:address":"School Of Arts, Paterson Rd",
    "sg:city":"Paterson",
    "sg:classifiers":[
        {
            "category":"Social Services",
            "subcategory":"Child Care",
            "type":"Services"
        }
    ],
    "sg:phone":"+61 2 4932 9768",
    "sg:postcode":"2421",
    "sg:province":"NSW",
    "sg:tags":[
        "support",
        "health"
    ],
    "wof:name":"Child Health Centres",
    "wof:placetype":"venue"
},
  "geometry": {"coordinates":[151.61041299999999,-32.613003],"type":"Point"}
}