{
  "type": "Feature",
  "properties": {
    "addr:full":"114 Stockton St Nelson Bay NSW 2315",
    "addr:housenumber":"114",
    "addr:postcode":"2315",
    "addr:street":"Stockton St",
    "iso:country":"AU",
    "sg:address":"114 Stockton St",
    "sg:city":"Nelson Bay",
    "sg:classifiers":[
        {
            "category":"Personal",
            "subcategory":"Beauty Salon",
            "type":"Services"
        }
    ],
    "sg:phone":"+61 2 4981 3164",
    "sg:postcode":"2315",
    "sg:province":"NSW",
    "wof:name":"Port Stephens Health & Beauty Therapy Centre",
    "wof:placetype":"venue"
},
  "geometry": {"coordinates":[152.14389,-32.721119],"type":"Point"}
}