{
  "type": "Feature",
  "properties": {
    "addr:full":"92 Chapel St Prahran VIC 3181",
    "addr:housenumber":"92",
    "addr:postcode":"3181",
    "addr:street":"Chapel St",
    "iso:country":"AU",
    "sg:address":"92 Chapel St",
    "sg:city":"Prahran",
    "sg:classifiers":[
        {
            "category":"Real Estate",
            "subcategory":"Real Estate Agent",
            "type":"Services"
        }
    ],
    "sg:phone":"+61 3 9510 1966",
    "sg:postcode":"3181",
    "sg:province":"VIC",
    "wof:name":"Beller & Co Pty Ltd",
    "wof:placetype":"venue"
},
  "geometry": {"coordinates":[144.99299621599999,-37.854637146],"type":"Point"}
}