{
  "type": "Feature",
  "properties": {
    "addr:full":"Adelaid Park Rd Yeppoon QLD 4703",
    "addr:postcode":"4703",
    "addr:street":"Park Rd",
    "iso:country":"AU",
    "sg:address":"Adelaid Park Rd",
    "sg:city":"Yeppoon",
    "sg:classifiers":[
        {
            "category":"Manufacturing",
            "subcategory":"Metals",
            "type":"Manufacturing & Wholesale Goods"
        }
    ],
    "sg:phone":"+61 7 4939 7350",
    "sg:postcode":"4703",
    "sg:province":"QLD",
    "sg:tags":[
        "steel",
        "fabricator",
        "mfrs"
    ],
    "wof:name":"Yeppoon Steel Fabrications",
    "wof:placetype":"venue"
},
  "geometry": {"coordinates":[150.741912842,-23.126335144],"type":"Point"}
}