{
  "type": "Feature",
  "properties": {
    "addr:full":"12 Seaview Rd Frankston VIC 3199",
    "addr:housenumber":"12",
    "addr:postcode":"3199",
    "addr:street":"Seaview Rd",
    "iso:country":"AU",
    "sg:address":"12 Seaview Rd",
    "sg:city":"Frankston",
    "sg:classifiers":[
        {
            "category":"Building & Trades",
            "subcategory":"Construction",
            "type":"Services"
        }
    ],
    "sg:phone":"+61 3 9787 4084",
    "sg:postcode":"3199",
    "sg:province":"VIC",
    "sg:tags":[
        "renovation",
        "alterations",
        "extension",
        "contractor"
    ],
    "wof:name":"Valentine T J & B",
    "wof:placetype":"venue"
},
  "geometry": {"coordinates":[145.113525391,-38.1713943481],"type":"Point"}
}