{
  "type": "Feature",
  "properties": {
    "addr:full":"PO Box 664 , Artarmon NSW 1570",
    "addr:postcode":"1570",
    "iso:country":"AU",
    "sg:address":"PO Box 664",
    "sg:city":", Artarmon",
    "sg:classifiers":[
        {
            "category":"Building & Trades",
            "subcategory":"Electrical",
            "type":"Services"
        }
    ],
    "sg:phone":"+61 414 318 773",
    "sg:postcode":"1570",
    "sg:province":"NSW",
    "sg:tags":[
        "testing",
        "tagging"
    ],
    "wof:name":"Stranger Designs",
    "wof:placetype":"venue"
},
  "geometry": {"coordinates":[151.18627900000001,-33.807159],"type":"Point"}
}