{
  "type": "Feature",
  "properties": {
    "addr:full":"Cammeray Rd Claremont TAS 7011",
    "addr:postcode":"7011",
    "addr:street":"Cammeray Rd",
    "iso:country":"AU",
    "sg:address":"Cammeray Rd",
    "sg:city":"Claremont",
    "sg:classifiers":[
        {
            "category":"Education",
            "subcategory":"School",
            "type":"Public Place"
        }
    ],
    "sg:phone":"+61 3 6249 1726",
    "sg:postcode":"7011",
    "sg:province":"TAS",
    "sg:tags":[
        "state",
        "except",
        "nsw"
    ],
    "wof:name":"Roseneath Primary School",
    "wof:placetype":"venue"
},
  "geometry": {"coordinates":[147.23713684099999,-42.7881660461],"type":"Point"}
}