{
  "type": "Feature",
  "properties": {
    "iso:country":"AU",
    "sg:address":"376 Victoria St",
    "sg:city":"Darlinghurst",
    "sg:classifiers":[
        {
            "category":"Health Services",
            "subcategory":"Doctor",
            "type":"Services"
        }
    ],
    "sg:phone":"+61 2 9360 7665",
    "sg:postcode":"2010",
    "sg:province":"NSW",
    "sg:tags":[
        "medical",
        "practitioner"
    ],
    "wof:name":"Kearney John",
    "wof:placetype":"venue"
},
  "geometry": {"coordinates":[151.22149658199999,-33.8785705566],"type":"Point"}
}