{
  "type": "Feature",
  "properties": {
    "addr:full":"198 Cotham Rd Kew VIC 3101",
    "addr:housenumber":"198",
    "addr:postcode":"3101",
    "addr:street":"Cotham Rd",
    "iso:country":"AU",
    "sg:address":"198 Cotham Rd",
    "sg:city":"Kew",
    "sg:classifiers":[
        {
            "category":"Building & Trades",
            "subcategory":"Landscaping Services",
            "type":"Services"
        }
    ],
    "sg:phone":"+61 3 9817 5985",
    "sg:postcode":"3101",
    "sg:province":"VIC",
    "sg:tags":[
        "tour",
        "shopping"
    ],
    "wof:name":"United Shopping Tours",
    "wof:placetype":"venue"
},
  "geometry": {"coordinates":[145.044189453,-37.8084945679],"type":"Point"}
}