{
  "type": "Feature",
  "properties": {
    "addr:full":"284 High St Bendigo VIC 3550",
    "addr:housenumber":"284",
    "addr:postcode":"3550",
    "addr:street":"High St",
    "iso:country":"AU",
    "sg:address":"284 High St",
    "sg:city":"Bendigo",
    "sg:classifiers":[
        {
            "category":"Food & Beverages",
            "subcategory":"Bakery",
            "type":"Retail Goods"
        }
    ],
    "sg:phone":"+61 3 5442 8700",
    "sg:postcode":"3550",
    "sg:province":"VIC",
    "sg:tags":[
        "cake",
        "shop",
        "pastry"
    ],
    "wof:name":"Cheesecake Shop The",
    "wof:placetype":"venue"
},
  "geometry": {"coordinates":[144.27804565400001,-36.7598876953],"type":"Point"}
}