{
  "type": "Feature",
  "properties": {
    "iso:country":"AU",
    "sg:address":"U2/ 29 Gerrish St",
    "sg:city":"Gladesville",
    "sg:classifiers":[
        {
            "category":"Education",
            "subcategory":"Dance Studio",
            "type":"Public Place"
        }
    ],
    "sg:phone":"+61 2 9816 4568",
    "sg:postcode":"2111",
    "sg:province":"NSW",
    "sg:tags":[
        "instruction",
        "language"
    ],
    "wof:name":"Japan Affinity Pty Ltd",
    "wof:placetype":"venue"
},
  "geometry": {"coordinates":[151.13108825699999,-33.8248939514],"type":"Point"}
}