{
  "type": "Feature",
  "properties": {
    "addr:full":"14 Wood St Rosedale VIC 3847",
    "addr:housenumber":"14",
    "addr:postcode":"3847",
    "addr:street":"Wood St",
    "iso:country":"AU",
    "sg:address":"14 Wood St",
    "sg:city":"Rosedale",
    "sg:classifiers":[
        {
            "category":"Building & Trades",
            "subcategory":"Construction",
            "type":"Services"
        }
    ],
    "sg:phone":"+61 3 5199 2417",
    "sg:postcode":"3847",
    "sg:province":"VIC",
    "sg:tags":[
        "plasterboard",
        "plasterer",
        "fixer"
    ],
    "wof:name":"Leighton C W",
    "wof:placetype":"venue"
},
  "geometry": {"coordinates":[146.78077697800001,-38.1551055908],"type":"Point"}
}