{
  "type": "Feature",
  "properties": {
    "iso:country":"AU",
    "sg:address":"Unit 2 2-10 Claremont Ave",
    "sg:city":"Greenacre",
    "sg:classifiers":[
        {
            "category":"Personal",
            "type":"Services"
        }
    ],
    "sg:phone":"+61 29793173",
    "sg:postcode":"2190",
    "sg:province":"NSW",
    "sg:tags":[
        "gift"
    ],
    "wof:name":"The Hamper Connection",
    "wof:placetype":"venue"
},
  "geometry": {"coordinates":[151.03877299999999,-33.899746],"type":"Point"}
}