{
  "type": "Feature",
  "properties": {
    "addr:full":"Shop 1-2/9 Patrick St Blacktown NSW 2148",
    "addr:housenumber":"shop 1-2 / 9",
    "addr:postcode":"2148",
    "addr:street":"Patrick St",
    "iso:country":"AU",
    "sg:address":"Shop 1-2/9 Patrick St",
    "sg:city":"Blacktown",
    "sg:classifiers":[
        {
            "category":"Shopping",
            "subcategory":"Computers & Home Electronics",
            "type":"Retail Goods"
        }
    ],
    "sg:phone":"+61 2 9671 7722",
    "sg:postcode":"2148",
    "sg:province":"NSW",
    "sg:tags":[
        "small",
        "equipment",
        "business"
    ],
    "wof:name":"Dick Smith Electronics",
    "wof:placetype":"venue"
},
  "geometry": {"coordinates":[150.90350341800001,-33.7908935547],"type":"Point"}
}