{
  "type": "Feature",
  "properties": {
    "addr:full":"128 Edwardes St Reservoir VIC 3073",
    "addr:housenumber":"128",
    "addr:postcode":"3073",
    "addr:street":"Edwardes St",
    "iso:country":"AU",
    "sg:address":"128 Edwardes St",
    "sg:city":"Reservoir",
    "sg:classifiers":[
        {
            "category":"Shopping",
            "subcategory":"Clothing, Apparel, & Fashions",
            "type":"Retail Goods"
        }
    ],
    "sg:phone":"+61 3 9460 9300",
    "sg:postcode":"3073",
    "sg:province":"VIC",
    "sg:tags":[
        "sportswear"
    ],
    "wof:name":"Black & Blue International Pty Ltd",
    "wof:placetype":"venue"
},
  "geometry": {"coordinates":[145.00003051799999,-37.7154312134],"type":"Point"}
}