{
  "type": "Feature",
  "properties": {
    "addr:full":"193 Victoria Rd Drummoyne NSW 2047",
    "addr:housenumber":"193",
    "addr:postcode":"2047",
    "addr:street":"Victoria Rd",
    "iso:country":"AU",
    "sg:address":"193 Victoria Rd",
    "sg:city":"Drummoyne",
    "sg:classifiers":[
        {
            "category":"Health Services",
            "subcategory":"Doctor",
            "type":"Services"
        }
    ],
    "sg:phone":"+61 1300 426 869",
    "sg:postcode":"2047",
    "sg:province":"NSW",
    "sg:tags":[
        "medical",
        "practitioner"
    ],
    "wof:name":"Concept Cosmetic Surgery",
    "wof:placetype":"venue"
},
  "geometry": {"coordinates":[151.15455600000001,-33.851292],"type":"Point"}
}