{
  "type": "Feature",
  "properties": {
    "addr:full":"18 Benvenue Rd St Leonards TAS 7250",
    "addr:housenumber":"18",
    "addr:postcode":"7250",
    "addr:street":"Benvenue Rd",
    "iso:country":"AU",
    "sg:address":"18 Benvenue Rd",
    "sg:city":"St Leonards",
    "sg:classifiers":[
        {
            "category":"Building & Trades",
            "subcategory":"Construction",
            "type":"Services"
        }
    ],
    "sg:phone":"+61 419 102 702",
    "sg:postcode":"7250",
    "sg:province":"TAS",
    "sg:tags":[
        "contractor"
    ],
    "wof:name":"Dean J & T",
    "wof:placetype":"venue"
},
  "geometry": {"coordinates":[147.20118713400001,-41.4584541321],"type":"Point"}
}