{
  "type": "Feature",
  "properties": {
    "iso:country":"AU",
    "sg:address":"152 Nottingham Rd",
    "sg:city":"Calamvale",
    "sg:classifiers":[
        {
            "category":"Professional",
            "subcategory":"Employment Agencies",
            "type":"Services"
        }
    ],
    "sg:phone":"+61 7 3272 6613",
    "sg:postcode":"4116",
    "sg:province":"QLD",
    "wof:name":"RH International",
    "wof:placetype":"venue"
},
  "geometry": {"coordinates":[153.03912353499999,-27.6293811798],"type":"Point"}
}