{
  "type": "Feature",
  "properties": {
    "iso:country":"AU",
    "sg:address":"3/ 37 Sunderland Drv",
    "sg:city":"Banksia Beach",
    "sg:classifiers":[
        {
            "category":"Real Estate",
            "subcategory":"Real Estate Agent",
            "type":"Services"
        }
    ],
    "sg:phone":"+61 7 3408 8277",
    "sg:postcode":"4507",
    "sg:province":"QLD",
    "wof:name":"Richardson & Wrench Banksia Beach",
    "wof:placetype":"venue"
},
  "geometry": {"coordinates":[153.13963317899999,-27.0448570251],"type":"Point"}
}