{
  "type": "Feature",
  "properties": {
    "addr:full":"85 Seacombe Rd Seacombe Gardens SA 5047",
    "addr:housenumber":"85",
    "addr:postcode":"5047",
    "addr:street":"Seacombe Rd",
    "iso:country":"AU",
    "sg:address":"85 Seacombe Rd",
    "sg:city":"Seacombe Gardens",
    "sg:classifiers":[
        {
            "category":"Education",
            "subcategory":"Dance Studio",
            "type":"Public Place"
        }
    ],
    "sg:phone":"+61 8 8296 3349",
    "sg:postcode":"5047",
    "sg:province":"SA",
    "sg:tags":[
        "venue",
        "tuition"
    ],
    "wof:name":"Adelaide City Ballet",
    "wof:placetype":"venue"
},
  "geometry": {"coordinates":[138.54457099999999,-35.02879],"type":"Point"}
}