{
  "type": "Feature",
  "properties": {
    "addr:full":"Units 2-3-4 173 Airds Rd Leumeah NSW 2560",
    "addr:housenumber":"173",
    "addr:postcode":"2560",
    "addr:street":"Airds Rd",
    "iso:country":"AU",
    "sg:address":"Units 2-3-4 173 Airds Rd",
    "sg:city":"Leumeah",
    "sg:classifiers":[
        {
            "category":"Retail",
            "subcategory":"Auto Repair",
            "type":"Services"
        }
    ],
    "sg:phone":"+61 2 4628 2822",
    "sg:postcode":"2560",
    "sg:province":"NSW",
    "sg:tags":[
        "beater",
        "painter",
        "panel"
    ],
    "wof:name":"P & I Auto Body Repairs",
    "wof:placetype":"venue"
},
  "geometry": {"coordinates":[150.83132934599999,-34.0472984314],"type":"Point"}
}