{
  "type": "Feature",
  "properties": {
    "iso:country":"AU",
    "sg:address":"11 Bauhinia Drv",
    "sg:city":"Parafield Gardens",
    "sg:classifiers":[
        {
            "category":"Retail",
            "subcategory":"Auto Repair",
            "type":"Services"
        }
    ],
    "sg:phone":"+61 429 033 000",
    "sg:postcode":"5107",
    "sg:province":"SA",
    "sg:tags":[
        "repairer",
        "motor",
        "engineer"
    ],
    "sg:website":"http://www.rgcauto.com.au",
    "wof:name":"RGC Auto Mobile Mechanics",
    "wof:placetype":"venue"
},
  "geometry": {"coordinates":[138.61390685999999,-34.7822036743],"type":"Point"}
}