{
  "type": "Feature",
  "properties": {
    "addr:full":"1/ 20 The Esplanade Wagga Wagga NSW 2650",
    "addr:housenumber":"/ 20",
    "addr:postcode":"2650",
    "addr:street":"The Esplanade",
    "iso:country":"AU",
    "sg:address":"1/ 20",
    "sg:city":"The Esplanade Wagga Wagga",
    "sg:classifiers":[
        {
            "category":"Insurance",
            "subcategory":"Hazard Insurance",
            "type":"Services"
        }
    ],
    "sg:phone":"+61 2 6921 1955",
    "sg:postcode":"2650",
    "sg:province":"NSW",
    "sg:tags":[
        "fire",
        "accident",
        "marine"
    ],
    "wof:name":"CGU",
    "wof:placetype":"venue"
},
  "geometry": {"coordinates":[147.366897583,-35.1103286743],"type":"Point"}
}