{
  "type": "Feature",
  "properties": {
    "iso:country":"AU",
    "sg:address":"PO Box 18126",
    "sg:city":"Collins Street East",
    "sg:classifiers":[
        {
            "category":"Professional",
            "subcategory":"Accounting & Tax Preparation",
            "type":"Services"
        }
    ],
    "sg:phone":"+61 3 9639 7355",
    "sg:postcode":"8003",
    "sg:province":"VIC",
    "sg:tags":[
        "accountant",
        "auditor"
    ],
    "wof:name":"Sharyn Long Chartered Accountants",
    "wof:placetype":"venue"
},
  "geometry": {"coordinates":[144.963165283,-37.814250946],"type":"Point"}
}