{
  "type": "Feature",
  "properties": {
    "iso:country":"AU",
    "sg:address":"29 Blackall St",
    "sg:city":"Woombye",
    "sg:classifiers":[
        {
            "category":"Social Services",
            "subcategory":"Child Care",
            "type":"Services"
        }
    ],
    "sg:phone":"+61 7 5442 1999",
    "sg:postcode":"4559",
    "sg:province":"QLD",
    "wof:name":"Woombye Childcare & Early Development Centre",
    "wof:placetype":"venue"
},
  "geometry": {"coordinates":[152.965942383,-26.660326004],"type":"Point"}
}