{
  "type": "Feature",
  "properties": {
    "iso:country":"AU",
    "sg:address":"Kiosk K19 Garden City 125 Riseley St",
    "sg:city":"Booragoon",
    "sg:classifiers":[
        {
            "category":"Cafe",
            "type":"Food & Drink"
        }
    ],
    "sg:phone":"+61 8 9316 1645",
    "sg:postcode":"6154",
    "sg:province":"WA",
    "wof:name":"Coffee Club The",
    "wof:placetype":"venue"
},
  "geometry": {"coordinates":[115.83802,-32.032337],"type":"Point"}
}