{
  "type": "Feature",
  "properties": {
    "iso:country":"AU",
    "sg:address":"Cnr Alderley & Greenwattle Sts",
    "sg:city":"Toowoomba",
    "sg:classifiers":[
        {
            "category":"Retail",
            "subcategory":"Storage",
            "type":"Services"
        }
    ],
    "sg:phone":"+61 7 4638 5764",
    "sg:postcode":"4350",
    "sg:province":"QLD",
    "wof:name":"Alderley & Greenwattle Streets Self Storage Sheds",
    "wof:placetype":"venue"
},
  "geometry": {"coordinates":[151.91340600000001,-27.579803],"type":"Point"}
}