{
  "type": "Feature",
  "properties": {
    "iso:country":"AU",
    "sg:address":"11 Glenridge Ave",
    "sg:city":"West Pennant Hills",
    "sg:classifiers":[
        {
            "category":"Professional",
            "subcategory":"Art Services",
            "type":"Services"
        }
    ],
    "sg:phone":"+61 2 9894 5442",
    "sg:postcode":"2125",
    "sg:province":"NSW",
    "sg:tags":[
        "decorator",
        "painter"
    ],
    "wof:name":"Girraween Painting Services Pty Ltd",
    "wof:placetype":"venue"
},
  "geometry": {"coordinates":[151.02987670900001,-33.7423362732],"type":"Point"}
}