{
  "type": "Feature",
  "properties": {
    "addr:full":"PO Box 36654 Winnellie NT 0820",
    "addr:postcode":"nt 0820",
    "iso:country":"AU",
    "sg:address":"PO Box 36654",
    "sg:city":"Winnellie",
    "sg:classifiers":[
        {
            "category":"Utilities",
            "subcategory":"Electric",
            "type":"Services"
        }
    ],
    "sg:phone":"+61 410 550 644",
    "sg:postcode":"0820",
    "sg:province":"NT",
    "sg:tags":[
        "electrical",
        "contractor"
    ],
    "wof:name":"Koola Air & Electrical Pty Ltd",
    "wof:placetype":"venue"
},
  "geometry": {"coordinates":[130.89439392099999,-12.4263296127],"type":"Point"}
}