{
  "type": "Feature",
  "properties": {
    "iso:country":"AU",
    "sg:address":"108 MacPherson St",
    "sg:city":"Footscray",
    "sg:classifiers":[
        {
            "category":"Manufacturing",
            "subcategory":"Furniture",
            "type":"Manufacturing & Wholesale Goods"
        }
    ],
    "sg:phone":"+61 403 952 634",
    "sg:postcode":"3011",
    "sg:province":"VIC",
    "sg:tags":[
        "builder",
        "designer",
        "custom"
    ],
    "wof:name":"Against the Grain",
    "wof:placetype":"venue"
},
  "geometry": {"coordinates":[144.888305664,-37.7942314148],"type":"Point"}
}