{
  "type": "Feature",
  "properties": {
    "iso:country":"AU",
    "sg:address":"Suit 1/ 40 Edward St",
    "sg:city":"Brisbane",
    "sg:classifiers":[
        {
            "category":"Real Estate",
            "subcategory":"Developer",
            "type":"Services"
        }
    ],
    "sg:phone":"+61 7 3221 9288",
    "sg:postcode":"4000",
    "sg:province":"QLD",
    "sg:tags":[
        "development"
    ],
    "wof:name":"Jamieson Projects Pty Ltd",
    "wof:placetype":"venue"
},
  "geometry": {"coordinates":[153.029693603,-27.4713382721],"type":"Point"}
}