{
  "type": "Feature",
  "properties": {
    "iso:country":"AU",
    "sg:address":"396 Burwood Rd",
    "sg:city":"Hawthorn",
    "sg:classifiers":[
        {
            "category":"Food & Beverages",
            "subcategory":"Bakery",
            "type":"Retail Goods"
        }
    ],
    "sg:phone":"+61 3 9819 5883",
    "sg:postcode":"3122",
    "sg:province":"VIC",
    "sg:tags":[
        "baker"
    ],
    "wof:name":"Knead Bakers Pty Ltd",
    "wof:placetype":"venue"
},
  "geometry": {"coordinates":[145.03761291500001,-37.822971344],"type":"Point"}
}