{
  "type": "Feature",
  "properties": {
    "iso:country":"AU",
    "sg:address":"Murray St",
    "sg:city":"Forster",
    "sg:classifiers":[
        {
            "category":"Retail",
            "subcategory":"Driving School",
            "type":"Services"
        }
    ],
    "sg:phone":"+61 2 6555 7371",
    "sg:postcode":"2428",
    "sg:province":"NSW",
    "wof:name":"Holiday Coast Driving School",
    "wof:placetype":"venue"
},
  "geometry": {"coordinates":[152.52477999999999,-32.212753],"type":"Point"}
}