{
  "type": "Feature",
  "properties": {
    "iso:country":"AU",
    "sg:address":"2/ 20 Ralph Black Drv",
    "sg:city":"North Wollongong",
    "sg:classifiers":[
        {
            "category":"Autos & Motor Vehicles",
            "subcategory":"Auto Supplies",
            "type":"Retail Goods"
        }
    ],
    "sg:phone":"+61 2 4227 5100",
    "sg:postcode":"2500",
    "sg:province":"NSW",
    "sg:tags":[
        "part",
        "cycles",
        "accessory"
    ],
    "wof:name":"Urban X Motos",
    "wof:placetype":"venue"
},
  "geometry": {"coordinates":[150.89323400000001,-34.407902],"type":"Point"}
}