{
  "type": "Feature",
  "properties": {
    "iso:country":"AU",
    "sg:address":"PO Box 937",
    "sg:city":"Clare",
    "sg:classifiers":[
        {
            "category":"Building & Trades",
            "subcategory":"Landscaping Services",
            "type":"Services"
        }
    ],
    "sg:phone":"+61 8 8842 3566",
    "sg:postcode":"5453",
    "sg:province":"SA",
    "sg:tags":[
        "control",
        "weed"
    ],
    "wof:name":"Outback Pest Control",
    "wof:placetype":"venue"
},
  "geometry": {"coordinates":[138.610779,-33.83239],"type":"Point"}
}