{
  "type": "Feature",
  "properties": {
    "iso:country":"AU",
    "sg:address":"600 St Kilda Rd",
    "sg:city":"Melbourne",
    "sg:classifiers":[
        {
            "category":"Communications",
            "subcategory":"Film & Video Production",
            "type":"Services"
        }
    ],
    "sg:phone":"+61 3 9500 8822",
    "sg:postcode":"3000",
    "sg:province":"VIC",
    "sg:tags":[
        "information",
        "recorded",
        "telephone"
    ],
    "wof:name":"Phone Media",
    "wof:placetype":"venue"
},
  "geometry": {"coordinates":[144.98034668,-37.8504943848],"type":"Point"}
}