{
  "type": "Feature",
  "properties": {
    "addr:full":"147 High St Wodonga VIC 3690",
    "addr:housenumber":"147",
    "addr:postcode":"3690",
    "addr:street":"High St",
    "iso:country":"AU",
    "sg:address":"147 High St",
    "sg:city":"Wodonga",
    "sg:classifiers":[
        {
            "category":"Food & Beverages",
            "subcategory":"Bakery",
            "type":"Retail Goods"
        }
    ],
    "sg:phone":"+61 2 6056 1331",
    "sg:postcode":"3690",
    "sg:province":"VIC",
    "sg:tags":[
        "baker"
    ],
    "wof:name":"Valentines On High",
    "wof:placetype":"venue"
},
  "geometry": {"coordinates":[146.88795471200001,-36.1233291626],"type":"Point"}
}