{
  "type": "Feature",
  "properties": {
    "addr:full":"16 Reardon St Currajong QLD 4812",
    "addr:housenumber":"16",
    "addr:postcode":"4812",
    "addr:street":"Reardon St",
    "iso:country":"AU",
    "sg:address":"16 Reardon St",
    "sg:city":"Currajong",
    "sg:classifiers":[
        {
            "category":"Utilities",
            "type":"Services"
        }
    ],
    "sg:phone":"+61 7 4775 7544",
    "sg:postcode":"4812",
    "sg:province":"QLD",
    "sg:tags":[
        "refrigeration",
        "industrial",
        "commercial",
        "retail"
    ],
    "wof:name":"Nor-East Air Conditioning & Refrigeration",
    "wof:placetype":"venue"
},
  "geometry": {"coordinates":[146.78016700000001,-19.273926],"type":"Point"}
}