{
  "type": "Feature",
  "properties": {
    "addr:full":"97 Somerton Rd Campbellfield VIC 3061",
    "addr:housenumber":"97",
    "addr:postcode":"3061",
    "addr:street":"Somerton Rd",
    "iso:country":"AU",
    "sg:address":"97 Somerton Rd",
    "sg:city":"Campbellfield",
    "sg:classifiers":[
        {
            "category":"Retail",
            "subcategory":"Auto Repair",
            "type":"Services"
        }
    ],
    "sg:phone":"+61 3 9305 3333",
    "sg:postcode":"3061",
    "sg:province":"VIC",
    "sg:tags":[
        "repairer",
        "motor",
        "engineer"
    ],
    "wof:name":"Campbellfield Smash Repairs",
    "wof:placetype":"venue"
},
  "geometry": {"coordinates":[144.941940308,-37.6421051025],"type":"Point"}
}