{
  "type": "Feature",
  "properties": {
    "addr:full":"U7/ 31 Peel Rd O'Connor WA 6163",
    "addr:housenumber":"31",
    "addr:postcode":"6163",
    "addr:street":"U7 /;Peel Rd",
    "iso:country":"AU",
    "sg:address":"U7/ 31 Peel Rd",
    "sg:city":"O'Connor",
    "sg:classifiers":[
        {
            "category":"Cafe",
            "type":"Food & Drink"
        }
    ],
    "sg:phone":"+61 8 9314 1964",
    "sg:postcode":"6163",
    "sg:province":"WA",
    "wof:name":"Bedrock Cafe",
    "wof:placetype":"venue"
},
  "geometry": {"coordinates":[115.795479,-32.060345],"type":"Point"}
}