{
  "type": "Feature",
  "properties": {
    "iso:country":"AU",
    "sg:address":"21 Boundry Rd",
    "sg:city":"Dubbo",
    "sg:classifiers":[
        {
            "category":"Building & Trades",
            "subcategory":"Construction",
            "type":"Services"
        }
    ],
    "sg:phone":"+61 2 6885 2782",
    "sg:postcode":"2830",
    "sg:province":"NSW",
    "sg:tags":[
        "fencing",
        "contractor"
    ],
    "wof:name":"Central West Budget Tree Service",
    "wof:placetype":"venue"
},
  "geometry": {"coordinates":[148.605102539,-32.2674636841],"type":"Point"}
}