{
  "type": "Feature",
  "properties": {
    "iso:country":"AU",
    "sg:address":"Level 5 125 Melville Pde",
    "sg:city":"Como",
    "sg:classifiers":[
        {
            "category":"Professional",
            "subcategory":"Detective & Security Services",
            "type":"Services"
        }
    ],
    "sg:phone":"+61 1300 363 247",
    "sg:postcode":"6152",
    "sg:province":"WA",
    "sg:tags":[
        "investigator"
    ],
    "wof:name":"FBIS International Group",
    "wof:placetype":"venue"
},
  "geometry": {"coordinates":[115.855797,-31.992916],"type":"Point"}
}