{
  "type": "Feature",
  "properties": {
    "addr:full":"52- 54 Mologa Rd Heidelberg West VIC 3081",
    "addr:housenumber":"54",
    "addr:postcode":"3081",
    "addr:street":"Mologa Rd",
    "iso:country":"AU",
    "sg:address":"52- 54 Mologa Rd",
    "sg:city":"Heidelberg West",
    "sg:classifiers":[
        {
            "category":"Autos & Motor Vehicles",
            "subcategory":"Motorcycle Sales",
            "type":"Retail Goods"
        }
    ],
    "sg:phone":"+61 3 9457 1733",
    "sg:postcode":"3081",
    "sg:province":"VIC",
    "sg:tags":[
        "part",
        "recyclers",
        "cycle"
    ],
    "sg:website":"http://www.victorianmotorcyclewreckers.com.au",
    "wof:name":"Victorian Motorcycle Wreckers",
    "wof:placetype":"venue"
},
  "geometry": {"coordinates":[145.048294067,-37.7332191467],"type":"Point"}
}