{
  "type": "Feature",
  "properties": {
    "addr:full":"3 Oslo Pl Warnbro WA 6169",
    "addr:housenumber":"3",
    "addr:postcode":"6169",
    "addr:street":"Pl",
    "iso:country":"AU",
    "sg:address":"3 Oslo Pl",
    "sg:city":"Warnbro",
    "sg:classifiers":[
        {
            "category":"Education",
            "subcategory":"School",
            "type":"Public Place"
        }
    ],
    "sg:phone":"+61 8 9593 3212",
    "sg:postcode":"6169",
    "sg:province":"WA",
    "wof:name":"Russian Ethnic School",
    "wof:placetype":"venue"
},
  "geometry": {"coordinates":[115.759422,-32.332947],"type":"Point"}
}