{
  "type": "Feature",
  "properties": {
    "addr:full":"Lot 2/ 40 Hyde St South Grafton NSW 2460",
    "addr:housenumber":"2 / 40",
    "addr:postcode":"2460",
    "addr:street":"Hyde St",
    "iso:country":"AU",
    "sg:address":"Lot 2/ 40 Hyde St",
    "sg:city":"South Grafton",
    "sg:classifiers":[
        {
            "category":"Home & Garden",
            "subcategory":"Carpets & Floor Coverings",
            "type":"Retail Goods"
        }
    ],
    "sg:phone":"+61 2 6643 0309",
    "sg:postcode":"2460",
    "sg:province":"NSW",
    "sg:tags":[
        "mat",
        "matting"
    ],
    "wof:name":"Steve's Safety Surfacing",
    "wof:placetype":"venue"
},
  "geometry": {"coordinates":[152.94288635300001,-29.7262153625],"type":"Point"}
}