{
  "type": "Feature",
  "properties": {
    "iso:country":"AU",
    "sg:address":"8 Orielton Rd",
    "sg:city":"Narellan",
    "sg:classifiers":[
        {
            "category":"Wholesale",
            "subcategory":"Drugs",
            "type":"Manufacturing & Wholesale Goods"
        }
    ],
    "sg:phone":"+61 2 4647 4227",
    "sg:postcode":"2567",
    "sg:province":"NSW",
    "sg:tags":[
        "wholesaler",
        "pharmaceutical",
        "product",
        "mfrs"
    ],
    "wof:name":"Natures Goodness Australia Pty Ltd",
    "wof:placetype":"venue"
},
  "geometry": {"coordinates":[150.750823975,-34.0379104614],"type":"Point"}
}