{
  "type": "Feature",
  "properties": {
    "iso:country":"AU",
    "sg:address":"110 Manning St",
    "sg:city":"Tuncurry",
    "sg:classifiers":[
        {
            "category":"Fast Food",
            "type":"Food & Drink"
        }
    ],
    "sg:phone":"+61 2 6554 6762",
    "sg:postcode":"2428",
    "sg:province":"NSW",
    "sg:tags":[
        "away",
        "take"
    ],
    "wof:name":"Tuncurry Chinese Restaurant",
    "wof:placetype":"venue"
},
  "geometry": {"coordinates":[152.498444,-32.172676],"type":"Point"}
}