{
  "type": "Feature",
  "properties": {
    "addr:full":"143 Church St Parramatta NSW 2150",
    "addr:housenumber":"143",
    "addr:postcode":"2150",
    "addr:street":"Church St",
    "iso:country":"AU",
    "sg:address":"143 Church St",
    "sg:city":"Parramatta",
    "sg:classifiers":[
        {
            "category":"Food & Beverages",
            "subcategory":"Supermarket",
            "type":"Retail Goods"
        }
    ],
    "sg:phone":"+61 2 9689 2772",
    "sg:postcode":"2150",
    "sg:province":"NSW",
    "sg:tags":[
        "grocery",
        "store"
    ],
    "wof:name":"Tai Wah Asian Grocery",
    "wof:placetype":"venue"
},
  "geometry": {"coordinates":[151.11956787099999,-33.8753242493],"type":"Point"}
}