{
  "type": "Feature",
  "properties": {
    "addr:full":"Suite 30, 1 Park Rd Milton QLD 4064",
    "addr:housenumber":"1",
    "addr:postcode":"4064",
    "addr:street":"Park Rd",
    "iso:country":"AU",
    "sg:address":"Suite 30, 1 Park Rd",
    "sg:city":"Milton",
    "sg:classifiers":[
        {
            "category":"Banks & Credit Unions",
            "subcategory":"Financial Services",
            "type":"Services"
        }
    ],
    "sg:phone":"+61 7 3369 0188",
    "sg:postcode":"4064",
    "sg:province":"QLD",
    "sg:tags":[
        "planning"
    ],
    "wof:name":"Darrel Steer & Perry Wilkey",
    "wof:placetype":"venue"
},
  "geometry": {"coordinates":[153.00378418,-27.4693546295],"type":"Point"}
}