{
  "type": "Feature",
  "properties": {
    "addr:full":"Waringa Drv Wendouree VIC 3355",
    "addr:postcode":"3355",
    "addr:street":"Waringa Drv",
    "iso:country":"AU",
    "sg:address":"Waringa Drv",
    "sg:city":"Wendouree",
    "sg:classifiers":[
        {
            "category":"Shopping",
            "subcategory":"Stationery & Office Supplies",
            "type":"Retail Goods"
        }
    ],
    "sg:phone":"+61 3 5330 7111",
    "sg:postcode":"3355",
    "sg:province":"VIC",
    "sg:tags":[
        "packaging",
        "material"
    ],
    "wof:name":"Amcor Beverage Cans",
    "wof:placetype":"venue"
},
  "geometry": {"coordinates":[143.80917400000001,-37.518711],"type":"Point"}
}