{
  "type": "Feature",
  "properties": {
    "iso:country":"AU",
    "sg:address":"54 Piper St",
    "sg:city":"Bathurst",
    "sg:classifiers":[
        {
            "category":"Professional",
            "subcategory":"Art Services",
            "type":"Services"
        }
    ],
    "sg:phone":"+61 2 6331 1912",
    "sg:postcode":"2795",
    "sg:province":"NSW",
    "sg:tags":[
        "artist"
    ],
    "wof:name":"Lupp Graham",
    "wof:placetype":"venue"
},
  "geometry": {"coordinates":[149.577926636,-33.42370224],"type":"Point"}
}