{
  "type": "Feature",
  "properties": {
    "addr:full":"Warwick Rd Yamanto QLD 4305",
    "addr:postcode":"4305",
    "addr:street":"Warwick Rd",
    "iso:country":"AU",
    "sg:address":"Warwick Rd",
    "sg:city":"Yamanto",
    "sg:classifiers":[
        {
            "category":"Autos & Motor Vehicles",
            "subcategory":"Fuel & Gas Station",
            "type":"Retail Goods"
        }
    ],
    "sg:phone":"+61 7 3288 0403",
    "sg:postcode":"4305",
    "sg:province":"QLD",
    "wof:name":"Plus Petrol",
    "wof:placetype":"venue"
},
  "geometry": {"coordinates":[152.73866272000001,-27.6630306244],"type":"Point"}
}