{
  "type": "Feature",
  "properties": {
    "addr:full":"Kiosk 3 Northcote Plaza Separation St Northcote VIC 3070",
    "addr:postcode":"3070",
    "addr:street":"St",
    "iso:country":"AU",
    "sg:address":"Kiosk 3 Northcote Plaza Separation St",
    "sg:city":"Northcote",
    "sg:classifiers":[
        {
            "category":"Manufacturing",
            "subcategory":"Tools & Machinery",
            "type":"Manufacturing & Wholesale Goods"
        }
    ],
    "sg:phone":"+61 3 9482 6170",
    "sg:postcode":"3070",
    "sg:province":"VIC",
    "sg:tags":[
        "wholesaler",
        "mfrs",
        "hosiery"
    ],
    "wof:name":"Discount Socks",
    "wof:placetype":"venue"
},
  "geometry": {"coordinates":[145.00198399999999,-37.76963],"type":"Point"}
}