{
  "type": "Feature",
  "properties": {
    "addr:full":"12/ 41 Melville Rd St Clair NSW 2759",
    "addr:housenumber":"12 / 41",
    "addr:postcode":"2759",
    "addr:street":"Melville Rd",
    "iso:country":"AU",
    "sg:address":"12/ 41 Melville Rd",
    "sg:city":"St Clair",
    "sg:classifiers":[
        {
            "category":"Health Services",
            "subcategory":"Doctor",
            "type":"Services"
        }
    ],
    "sg:phone":"+61 2 9834 4233",
    "sg:postcode":"2759",
    "sg:province":"NSW",
    "sg:tags":[
        "medical",
        "practitioner"
    ],
    "wof:name":"Melville Rd Family Medical Centre",
    "wof:placetype":"venue"
},
  "geometry": {"coordinates":[150.78024292000001,-33.7917137146],"type":"Point"}
}