{
  "type": "Feature",
  "properties": {
    "iso:country":"AU",
    "sg:address":"260a Preston Point Rd",
    "sg:city":"Bicton",
    "sg:classifiers":[
        {
            "category":"Government",
            "subcategory":"Post Office",
            "type":"Public Place"
        }
    ],
    "sg:phone":"+61 8 9339 4817",
    "sg:postcode":"6157",
    "sg:province":"WA",
    "sg:tags":[
        "house",
        "doll"
    ],
    "wof:name":"Australian Dolls Hospital",
    "wof:placetype":"venue"
},
  "geometry": {"coordinates":[115.78861999999999,-32.029819],"type":"Point"}
}