{
  "type": "Feature",
  "properties": {
    "addr:full":"49- 51 Falcon St Crows Nest NSW 2065",
    "addr:housenumber":"51",
    "addr:postcode":"2065",
    "addr:street":"Falcon St",
    "iso:country":"AU",
    "sg:address":"49- 51 Falcon St",
    "sg:city":"Crows Nest",
    "sg:classifiers":[
        {
            "category":"Professional",
            "subcategory":"Management & Consulting",
            "type":"Services"
        }
    ],
    "sg:phone":"+61 2 9409 9000",
    "sg:postcode":"2065",
    "sg:province":"NSW",
    "sg:tags":[
        "consultant"
    ],
    "wof:name":"Quadrant Research Services Pty Ltd",
    "wof:placetype":"venue"
},
  "geometry": {"coordinates":[151.20335388199999,-33.8281402588],"type":"Point"}
}