{
  "type": "Feature",
  "properties": {
    "addr:full":"Modbury Triangle Shpng Cntr, Shp 13c, 954 North East Rd Modbury SA 5092",
    "addr:housenumber":"13c 954",
    "addr:postcode":"5092",
    "addr:street":"North East Rd",
    "iso:country":"AU",
    "sg:address":"Modbury Triangle Shpng Cntr, Shp 13c, 954 North East Rd",
    "sg:city":"Modbury",
    "sg:classifiers":[
        {
            "category":"Personal",
            "subcategory":"Beauty Salon",
            "type":"Services"
        }
    ],
    "sg:phone":"+61 8 8264 2008",
    "sg:postcode":"5092",
    "sg:province":"SA",
    "wof:name":"Beauty Zone",
    "wof:placetype":"venue"
},
  "geometry": {"coordinates":[138.684936523,-34.8319511414],"type":"Point"}
}