{
  "type": "Feature",
  "properties": {
    "addr:full":"Jamestown Rd Hallett SA 5419",
    "addr:postcode":"5419",
    "addr:street":"Jamestown Rd",
    "iso:country":"AU",
    "sg:address":"Jamestown Rd",
    "sg:city":"Hallett",
    "sg:classifiers":[
        {
            "category":"Travel",
            "subcategory":"Hotels & Motels",
            "type":"Entertainment"
        }
    ],
    "sg:phone":"+61 8 8894 2014",
    "sg:postcode":"5419",
    "sg:province":"SA",
    "sg:tags":[
        "accommodation"
    ],
    "wof:name":"Wildongoleechie Hotel",
    "wof:placetype":"venue"
},
  "geometry": {"coordinates":[138.89068603499999,-33.410949707],"type":"Point"}
}