{
  "type": "Feature",
  "properties": {
    "iso:country":"AU",
    "sg:address":"12 Watsford Rd",
    "sg:city":"Campbelltown",
    "sg:classifiers":[
        {
            "category":"Retail",
            "subcategory":"Auto Repair",
            "type":"Services"
        }
    ],
    "sg:phone":"+61 2 4626 4521",
    "sg:postcode":"2560",
    "sg:province":"NSW",
    "sg:tags":[
        "automotive",
        "air conditioning"
    ],
    "wof:name":"South West Automotive",
    "wof:placetype":"venue"
},
  "geometry": {"coordinates":[150.81979370100001,-34.0592308044],"type":"Point"}
}