{
  "type": "Feature",
  "properties": {
    "iso:country":"AU",
    "sg:address":"14 Cuthbert Ave",
    "sg:city":"Highton",
    "sg:classifiers":[
        {
            "category":"Social Services",
            "subcategory":"Retirement Home",
            "type":"Services"
        }
    ],
    "sg:phone":"+61 3 5241 9772",
    "sg:postcode":"3216",
    "sg:province":"VIC",
    "sg:tags":[
        "life",
        "coaching"
    ],
    "wof:name":"Nautilus Life Coaching",
    "wof:placetype":"venue"
},
  "geometry": {"coordinates":[144.319381714,-38.1803283691],"type":"Point"}
}