{
  "type": "Feature",
  "properties": {
    "iso:country":"AU",
    "sg:address":"Patrick St",
    "sg:city":"Stawell",
    "sg:classifiers":[
        {
            "category":"Education",
            "subcategory":"Vocational School",
            "type":"Public Place"
        }
    ],
    "sg:phone":"+61 3 5358 1700",
    "sg:postcode":"3380",
    "sg:province":"VIC",
    "sg:tags":[
        "technical",
        "college",
        "trade"
    ],
    "wof:name":"Stawell Secondary College",
    "wof:placetype":"venue"
},
  "geometry": {"coordinates":[142.78350830100001,-37.0553359985],"type":"Point"}
}