{
  "type": "Feature",
  "properties": {
    "iso:country":"AU",
    "sg:address":"54 Commerce St",
    "sg:city":"Taree",
    "sg:classifiers":[
        {
            "category":"Health Services",
            "subcategory":"Doctor",
            "type":"Services"
        }
    ],
    "sg:phone":"+61 2 6550 0744",
    "sg:postcode":"2430",
    "sg:province":"NSW",
    "sg:tags":[
        "medical",
        "practitioner"
    ],
    "wof:name":"Gayed Emil",
    "wof:placetype":"venue"
},
  "geometry": {"coordinates":[152.45657299999999,-31.914206],"type":"Point"}
}