{
  "type": "Feature",
  "properties": {
    "iso:country":"AU",
    "sg:address":"Santa Monica Drv",
    "sg:city":"Keilor North",
    "sg:classifiers":[
        {
            "category":"Education",
            "subcategory":"School",
            "type":"Public Place"
        }
    ],
    "sg:phone":"+61 3 9390 9466",
    "sg:postcode":"3036",
    "sg:province":"VIC",
    "sg:tags":[
        "co-educational"
    ],
    "wof:name":"Catholic Regional College North Keilor",
    "wof:placetype":"venue"
},
  "geometry": {"coordinates":[144.806046,-37.69928],"type":"Point"}
}