{
  "type": "Feature",
  "properties": {
    "iso:country":"AU",
    "sg:address":"311 Lindendale Rd",
    "sg:city":"Wollongbar",
    "sg:classifiers":[
        {
            "category":"Professional",
            "subcategory":"Accounting & Tax Preparation",
            "type":"Services"
        }
    ],
    "sg:phone":"+61 2 6629 5512",
    "sg:postcode":"2477",
    "sg:province":"NSW",
    "sg:tags":[
        "accountant",
        "auditor"
    ],
    "wof:name":"Morris P K & J H",
    "wof:placetype":"venue"
},
  "geometry": {"coordinates":[153.395187378,-28.8353443146],"type":"Point"}
}