{
  "type": "Feature",
  "properties": {
    "addr:full":"Cnr Terry St & Tongarra Rd Albion Park NSW 2527",
    "addr:postcode":"2527",
    "addr:street":"Cnr Terry St & Tongarra Rd",
    "iso:country":"AU",
    "sg:address":"Cnr Terry St & Tongarra Rd",
    "sg:city":"Albion Park",
    "sg:classifiers":[
        {
            "category":"Travel",
            "subcategory":"Hotels & Motels",
            "type":"Entertainment"
        }
    ],
    "sg:phone":"+61 2 4256 1799",
    "sg:postcode":"2527",
    "sg:province":"NSW",
    "sg:tags":[
        "accommodation"
    ],
    "wof:name":"Albion Park Hotel",
    "wof:placetype":"venue"
},
  "geometry": {"coordinates":[150.777542114,-34.5794181824],"type":"Point"}
}