{
  "type": "Feature",
  "properties": {
    "addr:full":"45 Border Rd Mungindi NSW 2406",
    "addr:housenumber":"45",
    "addr:postcode":"2406",
    "addr:street":"Border Rd",
    "iso:country":"AU",
    "sg:address":"45 Border Rd",
    "sg:city":"Mungindi",
    "sg:classifiers":[
        {
            "category":"Building & Trades",
            "subcategory":"Construction",
            "type":"Services"
        }
    ],
    "sg:phone":"+61 2 6753 2316",
    "sg:postcode":"2406",
    "sg:province":"NSW",
    "sg:tags":[
        "excavation",
        "foundation"
    ],
    "wof:name":"Ecotech Civil",
    "wof:placetype":"venue"
},
  "geometry": {"coordinates":[148.997848511,-28.9787998199],"type":"Point"}
}