{
  "type": "Feature",
  "properties": {
    "iso:country":"AU",
    "sg:address":"Suite 2 88 Boronia Rd",
    "sg:city":"Boronia",
    "sg:classifiers":[
        {
            "category":"Insurance",
            "subcategory":"Insurance Agent",
            "type":"Services"
        }
    ],
    "sg:phone":"+61 3 9762 0000",
    "sg:postcode":"3155",
    "sg:province":"VIC",
    "wof:name":"Staffpak Insurance Brokers",
    "wof:placetype":"venue"
},
  "geometry": {"coordinates":[145.28779602,-37.8628616333],"type":"Point"}
}