{
  "type": "Feature",
  "properties": {
    "iso:country":"AU",
    "sg:address":"6 Muriel St",
    "sg:city":"Glen Iris",
    "sg:classifiers":[
        {
            "category":"Real Estate",
            "subcategory":"Architect",
            "type":"Services"
        }
    ],
    "sg:phone":"+61 3 9889 7298",
    "sg:postcode":"3146",
    "sg:province":"VIC",
    "wof:name":"Walklate Kevin J",
    "wof:placetype":"venue"
},
  "geometry": {"coordinates":[145.08753967300001,-37.852897644],"type":"Point"}
}