{
  "type": "Feature",
  "properties": {
    "addr:full":"PO Box 579 Wonthaggi VIC 3995",
    "addr:postcode":"3995",
    "iso:country":"AU",
    "sg:address":"PO Box 579",
    "sg:city":"Wonthaggi",
    "sg:classifiers":[
        {
            "category":"Building & Trades",
            "subcategory":"Construction",
            "type":"Services"
        }
    ],
    "sg:phone":"+61 3 5672 4977",
    "sg:postcode":"3995",
    "sg:province":"VIC",
    "sg:tags":[
        "joinery"
    ],
    "wof:name":"Cailes Cabinets",
    "wof:placetype":"venue"
},
  "geometry": {"coordinates":[145.57620199999999,-38.58461],"type":"Point"}
}