{
  "type": "Feature",
  "properties": {
    "addr:full":"2 Green St Tamworth NSW 2340",
    "addr:housenumber":"2",
    "addr:postcode":"2340",
    "addr:street":"Green St",
    "iso:country":"AU",
    "sg:address":"2 Green St",
    "sg:city":"Tamworth",
    "sg:classifiers":[
        {
            "category":"Food & Beverages",
            "subcategory":"Supermarket",
            "type":"Retail Goods"
        }
    ],
    "sg:phone":"+61 2 6765 5740",
    "sg:postcode":"2340",
    "sg:province":"NSW",
    "sg:tags":[
        "grocery",
        "store"
    ],
    "wof:name":"Coledale Store",
    "wof:placetype":"venue"
},
  "geometry": {"coordinates":[150.89715576200001,-31.1096191406],"type":"Point"}
}