{
  "type": "Feature",
  "properties": {
    "addr:full":"33 Old Pacific Hwy Yatala QLD 4207",
    "addr:housenumber":"33",
    "addr:postcode":"4207",
    "addr:street":"Old Pacific Hwy",
    "iso:country":"AU",
    "sg:address":"33 Old Pacific Hwy",
    "sg:city":"Yatala",
    "sg:phone":"+61 7 3287 5966",
    "sg:postcode":"4207",
    "sg:province":"QLD",
    "wof:name":"Qld Air Cleaner Services",
    "wof:placetype":"venue"
},
  "geometry": {"coordinates":[153.224212647,-27.7335147858],"type":"Point"}
}