{
  "type": "Feature",
  "properties": {
    "iso:country":"AU",
    "sg:address":"7 Mathews St",
    "sg:city":"Davidson",
    "sg:classifiers":[
        {
            "category":"Manufacturing",
            "subcategory":"Jewelry",
            "type":"Manufacturing & Wholesale Goods"
        }
    ],
    "sg:phone":"+61 2 9975 5740",
    "sg:postcode":"2085",
    "sg:province":"NSW",
    "sg:tags":[
        "mfrg",
        "jeweller"
    ],
    "wof:name":"Massey B & M Pty Limited",
    "wof:placetype":"venue"
},
  "geometry": {"coordinates":[151.188995361,-33.7376213074],"type":"Point"}
}