{
  "type": "Feature",
  "properties": {
    "addr:full":"55B Dinah Pde Keilor East VIC 3033",
    "addr:housenumber":"55b",
    "addr:postcode":"3033",
    "addr:street":"Dinah Pde",
    "iso:country":"AU",
    "sg:address":"55B Dinah Pde",
    "sg:city":"Keilor East",
    "sg:classifiers":[
        {
            "category":"Health Services",
            "subcategory":"Dentist",
            "type":"Services"
        }
    ],
    "sg:phone":"+61 3 9331 2599",
    "sg:postcode":"3033",
    "sg:province":"VIC",
    "sg:tags":[
        "technician",
        "dental"
    ],
    "wof:name":"Clark Robert N",
    "wof:placetype":"venue"
},
  "geometry": {"coordinates":[144.86637899999999,-37.743984],"type":"Point"}
}