{
  "type": "Feature",
  "properties": {
    "addr:full":"281 David Rd Waggrakine WA 6530",
    "addr:housenumber":"281",
    "addr:postcode":"6530",
    "addr:street":"David Rd",
    "iso:country":"AU",
    "sg:address":"281 David Rd",
    "sg:city":"Waggrakine",
    "sg:classifiers":[
        {
            "category":"Building & Trades",
            "subcategory":"Construction",
            "type":"Services"
        }
    ],
    "sg:phone":"+61 8 9938 3325",
    "sg:postcode":"6530",
    "sg:province":"WA",
    "sg:tags":[
        "earth",
        "excavating",
        "moving",
        "contractor"
    ],
    "wof:name":"Walton Plant Hire",
    "wof:placetype":"venue"
},
  "geometry": {"coordinates":[114.64447784399999,-28.6915950775],"type":"Point"}
}