{
  "type": "Feature",
  "properties": {
    "addr:full":"189 South Rd Mile End SA 5031",
    "addr:housenumber":"189",
    "addr:postcode":"5031",
    "addr:street":"South Rd",
    "iso:country":"AU",
    "sg:address":"189 South Rd",
    "sg:city":"Mile End",
    "sg:classifiers":[
        {
            "category":"Manufacturing",
            "subcategory":"Rubber & Plastics",
            "type":"Manufacturing & Wholesale Goods"
        }
    ],
    "sg:phone":"+61 8 8443 3926",
    "sg:postcode":"5031",
    "sg:province":"SA",
    "sg:tags":[
        "wholesaler",
        "product",
        "mfrs"
    ],
    "wof:name":"DS Systems Pty Ltd",
    "wof:placetype":"venue"
},
  "geometry": {"coordinates":[138.570114136,-34.9258956909],"type":"Point"}
}