{
  "type": "Feature",
  "properties": {
    "iso:country":"AU",
    "sg:address":"PO Box 58",
    "sg:city":"Dulwich Hill",
    "sg:classifiers":[
        {
            "category":"Manufacturing",
            "subcategory":"Furniture",
            "type":"Manufacturing & Wholesale Goods"
        }
    ],
    "sg:phone":"+61 2 9569 6113",
    "sg:postcode":"2203",
    "sg:province":"NSW",
    "sg:tags":[
        "builder",
        "designer",
        "custom"
    ],
    "wof:name":"Hometogo",
    "wof:placetype":"venue"
},
  "geometry": {"coordinates":[151.13876300000001,-33.90469],"type":"Point"}
}