{
  "type": "Feature",
  "properties": {
    "iso:country":"AU",
    "sg:address":"15 McLean St",
    "sg:city":"Bundaberg",
    "sg:classifiers":[
        {
            "category":"Autos & Motor Vehicles",
            "subcategory":"Motorcycle Sales",
            "type":"Retail Goods"
        }
    ],
    "sg:phone":"+61 7 4152 5107",
    "sg:postcode":"4670",
    "sg:province":"QLD",
    "sg:tags":[
        "part",
        "recyclers",
        "cycle"
    ],
    "wof:name":"Bundaberg Bike Wreckers",
    "wof:placetype":"venue"
},
  "geometry": {"coordinates":[152.346801758,-24.8718166351],"type":"Point"}
}