{
  "type": "Feature",
  "properties": {
    "addr:full":"Shop 188, 2A Hollywood Ave Bondi Junction NSW 2022",
    "addr:housenumber":"188 2a",
    "addr:postcode":"2022",
    "addr:street":"Hollywood Ave",
    "iso:country":"AU",
    "sg:address":"Shop 188, 2A Hollywood Ave",
    "sg:city":"Bondi Junction",
    "sg:classifiers":[
        {
            "category":"Health Services",
            "subcategory":"Doctor",
            "type":"Services"
        }
    ],
    "sg:phone":"+61 2 9389 5988",
    "sg:postcode":"2022",
    "sg:province":"NSW",
    "sg:tags":[
        "medical",
        "practitioner"
    ],
    "wof:name":"Gray M.K.",
    "wof:placetype":"venue"
},
  "geometry": {"coordinates":[151.25164794899999,-33.894329071],"type":"Point"}
}