{
  "type": "Feature",
  "properties": {
    "addr:full":"40 Ruby St Essendon West VIC 3040",
    "addr:housenumber":"40",
    "addr:postcode":"3040",
    "addr:street":"Ruby St",
    "iso:country":"AU",
    "sg:address":"40 Ruby St",
    "sg:city":"Essendon West",
    "sg:classifiers":[
        {
            "category":"Building & Trades",
            "subcategory":"Plumbing",
            "type":"Services"
        }
    ],
    "sg:phone":"+61 3 9337 9013",
    "sg:postcode":"3040",
    "sg:province":"VIC",
    "sg:tags":[
        "plumber",
        "gasfitters"
    ],
    "wof:name":"Waddell W J",
    "wof:placetype":"venue"
},
  "geometry": {"coordinates":[144.88406372099999,-37.7522125244],"type":"Point"}
}