{
  "type": "Feature",
  "properties": {
    "addr:full":"Cnr Monbulk & Gully Crs Belgrave VIC 3160",
    "addr:postcode":"3160",
    "addr:street":"Cnr;Crs",
    "iso:country":"AU",
    "sg:address":"Cnr Monbulk & Gully Crs",
    "sg:city":"Belgrave",
    "sg:classifiers":[
        {
            "category":"Travel",
            "subcategory":"Hotels & Motels",
            "type":"Entertainment"
        }
    ],
    "sg:phone":"+61 3 9754 8660",
    "sg:postcode":"3160",
    "sg:province":"VIC",
    "sg:tags":[
        "accommodation"
    ],
    "wof:name":"Micawber Park Tavern",
    "wof:placetype":"venue"
},
  "geometry": {"coordinates":[145.355377197,-37.9077453613],"type":"Point"}
}