{
  "type": "Feature",
  "properties": {
    "addr:full":"10 Kilvington Drv Emerald VIC 3782",
    "addr:housenumber":"10",
    "addr:postcode":"3782",
    "addr:street":"Kilvington Drv",
    "iso:country":"AU",
    "sg:address":"10 Kilvington Drv",
    "sg:city":"Emerald",
    "sg:classifiers":[
        {
            "category":"Food & Beverages",
            "subcategory":"Liquor & Beverages",
            "type":"Retail Goods"
        }
    ],
    "sg:phone":"+61 3 5968 4205",
    "sg:postcode":"3782",
    "sg:province":"VIC",
    "sg:tags":[
        "store"
    ],
    "wof:name":"Cellarbrations",
    "wof:placetype":"venue"
},
  "geometry": {"coordinates":[145.44064299999999,-37.933014],"type":"Point"}
}