{
  "type": "Feature",
  "properties": {
    "addr:full":"Shop 4 221 Henley Beach Rd Torrensville SA 5031",
    "addr:housenumber":"shop 4 221",
    "addr:postcode":"5031",
    "addr:street":"Henley Beach Rd",
    "iso:country":"AU",
    "sg:address":"Shop 4 221 Henley Beach Rd",
    "sg:city":"Torrensville",
    "sg:classifiers":[
        {
            "category":"Professional",
            "subcategory":"Computer Services",
            "type":"Services"
        }
    ],
    "sg:phone":"+61 8 8234 6838",
    "sg:postcode":"5031",
    "sg:province":"SA",
    "sg:tags":[
        "repairs",
        "upgrade",
        "equipment"
    ],
    "wof:name":"Game Fix",
    "wof:placetype":"venue"
},
  "geometry": {"coordinates":[138.55621337900001,-34.9245567322],"type":"Point"}
}