{
  "type": "Feature",
  "properties": {
    "addr:full":"227 Charters Towers Rd Hermit Park QLD 4812",
    "addr:housenumber":"227",
    "addr:postcode":"4812",
    "addr:street":"Charters Towers Rd",
    "iso:country":"AU",
    "sg:address":"227 Charters Towers Rd",
    "sg:city":"Hermit Park",
    "sg:classifiers":[
        {
            "category":"Real Estate",
            "subcategory":"Real Estate Agent",
            "type":"Services"
        }
    ],
    "sg:phone":"+61 7 4779 9266",
    "sg:postcode":"4812",
    "sg:province":"QLD",
    "wof:name":"Martini Realty.Com",
    "wof:placetype":"venue"
},
  "geometry": {"coordinates":[146.796829,-19.286388],"type":"Point"}
}