{
  "type": "Feature",
  "properties": {
    "addr:full":"64 Victoria Rd Parramatta NSW 2150",
    "addr:housenumber":"64",
    "addr:postcode":"2150",
    "addr:street":"Victoria Rd",
    "iso:country":"AU",
    "sg:address":"64 Victoria Rd",
    "sg:city":"Parramatta",
    "sg:classifiers":[
        {
            "category":"Food & Beverages",
            "subcategory":"Groceries & Convenience Stores",
            "type":"Retail Goods"
        }
    ],
    "sg:phone":"+61 2 9683 4718",
    "sg:postcode":"2150",
    "sg:province":"NSW",
    "wof:name":"Stock & Shop",
    "wof:placetype":"venue"
},
  "geometry": {"coordinates":[151.05531310999999,-33.7385444641],"type":"Point"}
}