{
  "type": "Feature",
  "properties": {
    "iso:country":"AU",
    "sg:address":"57 Pacific Hwy",
    "sg:city":"Ourimbah",
    "sg:classifiers":[
        {
            "category":"Real Estate",
            "subcategory":"Real Estate Agent",
            "type":"Services"
        }
    ],
    "sg:phone":"+61 2 4362 3333",
    "sg:postcode":"2258",
    "sg:province":"NSW",
    "wof:name":"Central Coast Lifestyle Properties",
    "wof:placetype":"venue"
},
  "geometry": {"coordinates":[151.36949157699999,-33.3596305847],"type":"Point"}
}