{
  "type": "Feature",
  "properties": {
    "iso:country":"AU",
    "sg:address":"Shop 3 201 Elizabeth St",
    "sg:city":"Sydney",
    "sg:classifiers":[
        {
            "category":"Manufacturing",
            "subcategory":"Food",
            "type":"Manufacturing & Wholesale Goods"
        }
    ],
    "sg:phone":"+61 2 9264 7623",
    "sg:postcode":"2000",
    "sg:province":"NSW",
    "sg:tags":[
        "function",
        "catering"
    ],
    "wof:name":"A At Cross Roads Cuisine",
    "wof:placetype":"venue"
},
  "geometry": {"coordinates":[151.20979309099999,-33.8733978271],"type":"Point"}
}