{
  "type": "Feature",
  "properties": {
    "addr:full":"Shop 12 Seymour Arc Traralgon VIC 3844",
    "addr:housenumber":"shop 12",
    "addr:postcode":"3844",
    "addr:street":"Seymour Arc",
    "iso:country":"AU",
    "sg:address":"Shop 12 Seymour Arc",
    "sg:city":"Traralgon",
    "sg:classifiers":[
        {
            "category":"Personal",
            "subcategory":"Beauty Salon",
            "type":"Services"
        }
    ],
    "sg:phone":"+61 3 5174 3309",
    "sg:postcode":"3844",
    "sg:province":"VIC",
    "sg:tags":[
        "hairdresser"
    ],
    "wof:name":"Curl Up & Dye",
    "wof:placetype":"venue"
},
  "geometry": {"coordinates":[146.539337158,-38.1961746216],"type":"Point"}
}