{
  "type": "Feature",
  "properties": {
    "addr:full":"12 Lionel Rd Mt Waverley VIC 3149",
    "addr:housenumber":"12",
    "addr:postcode":"3149",
    "addr:street":"Lionel Rd",
    "iso:country":"AU",
    "sg:address":"12 Lionel Rd",
    "sg:city":"Mt Waverley",
    "sg:classifiers":[
        {
            "category":"Home & Garden",
            "subcategory":"Carpets & Floor Coverings",
            "type":"Retail Goods"
        }
    ],
    "sg:phone":"+61 3 9544 9544",
    "sg:postcode":"3149",
    "sg:province":"VIC",
    "sg:tags":[
        "tile",
        "wall"
    ],
    "wof:name":"Edwards",
    "wof:placetype":"venue"
},
  "geometry": {"coordinates":[145.14068603499999,-37.8987731934],"type":"Point"}
}