{
  "type": "Feature",
  "properties": {
    "addr:full":"56 Padbury Rd Gilles Plains SA 5086",
    "addr:housenumber":"56",
    "addr:postcode":"5086",
    "addr:street":"Padbury Rd",
    "iso:country":"AU",
    "sg:address":"56 Padbury Rd",
    "sg:city":"Gilles Plains",
    "sg:classifiers":[
        {
            "category":"Professional",
            "subcategory":"Detective & Security Services",
            "type":"Services"
        }
    ],
    "sg:phone":"+61 418 824 406",
    "sg:postcode":"5086",
    "sg:province":"SA",
    "sg:tags":[
        "equipment",
        "window",
        "doors"
    ],
    "wof:name":"Junction Locksmiths",
    "wof:placetype":"venue"
},
  "geometry": {"coordinates":[138.66380310100001,-34.8470649719],"type":"Point"}
}