{
  "type": "Feature",
  "properties": {
    "addr:full":"Shop 1, 787 High St Thornbury VIC 3071",
    "addr:housenumber":"shop 1 787",
    "addr:postcode":"3071",
    "addr:street":"High St",
    "iso:country":"AU",
    "sg:address":"Shop 1, 787 High St",
    "sg:city":"Thornbury",
    "sg:classifiers":[
        {
            "category":"Social Services",
            "subcategory":"Child Care",
            "type":"Services"
        }
    ],
    "sg:phone":"+61 3 9484 1036",
    "sg:postcode":"3071",
    "sg:province":"VIC",
    "wof:name":"Day 2 Day Family Day Care",
    "wof:placetype":"venue"
},
  "geometry": {"coordinates":[145.000732422,-37.7568206787],"type":"Point"}
}