{
  "type": "Feature",
  "properties": {
    "iso:country":"AU",
    "sg:address":"41014 Bruce Hwy",
    "sg:city":"Townsville",
    "sg:classifiers":[
        {
            "category":"Communications",
            "subcategory":"Film & Video Production",
            "type":"Services"
        }
    ],
    "sg:phone":"+61 415 724 848",
    "sg:postcode":"4810",
    "sg:province":"QLD",
    "sg:tags":[
        "yacht",
        "transport",
        "boat"
    ],
    "wof:name":"N.Q. Boat Haulage",
    "wof:placetype":"venue"
},
  "geometry": {"coordinates":[146.824448,-19.318274],"type":"Point"}
}