{
  "type": "Feature",
  "properties": {
    "addr:full":"1/ 51 Arthur St Forestville NSW 2087",
    "addr:housenumber":"/ 51",
    "addr:postcode":"2087",
    "addr:street":"Arthur St",
    "iso:country":"AU",
    "sg:address":"1/ 51 Arthur St",
    "sg:city":"Forestville",
    "sg:classifiers":[
        {
            "category":"Retail",
            "subcategory":"Repair Shop",
            "type":"Services"
        }
    ],
    "sg:phone":"+61 2 9451 2613",
    "sg:postcode":"2087",
    "sg:province":"NSW",
    "sg:tags":[
        "machine",
        "repairs",
        "part",
        "dryer",
        "washing"
    ],
    "wof:name":"A Aarons Forest Washing Machine Service",
    "wof:placetype":"venue"
},
  "geometry": {"coordinates":[151.203567505,-33.759967804],"type":"Point"}
}