{
  "type": "Feature",
  "properties": {
    "iso:country":"AU",
    "sg:address":"Suite 3/404- 412 Military St",
    "sg:city":"Cremorne",
    "sg:classifiers":[
        {
            "category":"Education",
            "subcategory":"School",
            "type":"Public Place"
        }
    ],
    "sg:phone":"+61 2 9908 1777",
    "sg:postcode":"2090",
    "sg:province":"NSW",
    "sg:tags":[
        "supply"
    ],
    "wof:name":"Rauland Australia Pty Ltd",
    "wof:placetype":"venue"
},
  "geometry": {"coordinates":[151.230392456,-33.8278923035],"type":"Point"}
}