{
  "type": "Feature",
  "properties": {
    "addr:full":"U14/ 258 Johnston St Annandale NSW 2038",
    "addr:housenumber":"258",
    "addr:postcode":"2038",
    "addr:street":"/;Johnston St",
    "iso:country":"AU",
    "sg:address":"U14/ 258 Johnston St",
    "sg:city":"Annandale",
    "sg:classifiers":[
        {
            "category":"Shopping",
            "subcategory":"Clothing, Apparel, & Fashions",
            "type":"Retail Goods"
        }
    ],
    "sg:phone":"+61 408 260 657",
    "sg:postcode":"2038",
    "sg:province":"NSW",
    "sg:tags":[
        "lady",
        "wear"
    ],
    "wof:name":"Russe Pty Ltd",
    "wof:placetype":"venue"
},
  "geometry": {"coordinates":[151.17315673799999,-33.8756256104],"type":"Point"}
}