{
  "type": "Feature",
  "properties": {
    "addr:full":"270B Mckinnon Rd McKinnon VIC 3204",
    "addr:housenumber":"270b",
    "addr:postcode":"3204",
    "addr:street":"Mckinnon Rd",
    "iso:country":"AU",
    "sg:address":"270B Mckinnon Rd",
    "sg:city":"McKinnon",
    "sg:classifiers":[
        {
            "category":"Retail",
            "subcategory":"Auto Repair",
            "type":"Services"
        }
    ],
    "sg:phone":"+61 3 9557 7770",
    "sg:postcode":"3204",
    "sg:province":"VIC",
    "sg:tags":[
        "beater",
        "painter",
        "panel"
    ],
    "wof:name":"Accident Repair Centre Mckinnon",
    "wof:placetype":"venue"
},
  "geometry": {"coordinates":[145.04312100000001,-37.911816],"type":"Point"}
}