{
  "type": "Feature",
  "properties": {
    "iso:country":"AU",
    "sg:address":"PO Box 1505",
    "sg:city":"North Rockhampton",
    "sg:classifiers":[
        {
            "category":"Professional",
            "subcategory":"Detective & Security Services",
            "type":"Services"
        }
    ],
    "sg:phone":"+61 7 4921 2201",
    "sg:postcode":"4701",
    "sg:province":"QLD",
    "sg:tags":[
        "consultant",
        "system"
    ],
    "wof:name":"Rely Security Networks",
    "wof:placetype":"venue"
},
  "geometry": {"coordinates":[150.54896545400001,-23.3510398865],"type":"Point"}
}