{
  "type": "Feature",
  "properties": {
    "iso:country":"AU",
    "sg:address":"U5/ 10 Millennium Crt",
    "sg:city":"Silverwater",
    "sg:classifiers":[
        {
            "category":"Utilities",
            "subcategory":"Electric",
            "type":"Services"
        }
    ],
    "sg:phone":"+61 2 9647 2862",
    "sg:postcode":"2128",
    "sg:province":"NSW",
    "sg:tags":[
        "element"
    ],
    "wof:name":"Wilson Elements",
    "wof:placetype":"venue"
},
  "geometry": {"coordinates":[151.041259766,-33.833114624],"type":"Point"}
}