{
  "type": "Feature",
  "properties": {
    "addr:full":"PO Box 3068 Norman Park QLD 4170",
    "addr:postcode":"4170",
    "iso:country":"AU",
    "sg:address":"PO Box 3068",
    "sg:city":"Norman Park",
    "sg:classifiers":[
        {
            "category":"Shopping",
            "subcategory":"Computers & Home Electronics",
            "type":"Retail Goods"
        }
    ],
    "sg:phone":"+61 7 3395 7807",
    "sg:postcode":"4170",
    "sg:province":"QLD",
    "sg:tags":[
        "hardware",
        "equipment"
    ],
    "wof:name":"PracPharm IT",
    "wof:placetype":"venue"
},
  "geometry": {"coordinates":[153.05592346200001,-27.4741001129],"type":"Point"}
}