{
  "type": "Feature",
  "properties": {
    "addr:full":"632 Mitcham Rd Mitcham VIC 3132",
    "addr:housenumber":"632",
    "addr:postcode":"3132",
    "addr:street":"Mitcham Rd",
    "iso:country":"AU",
    "sg:address":"632 Mitcham Rd",
    "sg:city":"Mitcham",
    "sg:classifiers":[
        {
            "category":"Education",
            "subcategory":"School",
            "type":"Public Place"
        }
    ],
    "sg:phone":"+61 3 9837 2626",
    "sg:postcode":"3132",
    "sg:province":"VIC",
    "sg:tags":[
        "supply"
    ],
    "wof:name":"Campion",
    "wof:placetype":"venue"
},
  "geometry": {"coordinates":[145.19464111299999,-37.8305053711],"type":"Point"}
}