{
  "type": "Feature",
  "properties": {
    "addr:full":"PO Box 124 Isle Of Capri QLD 4217",
    "addr:postcode":"4217",
    "iso:country":"AU",
    "sg:address":"PO Box 124",
    "sg:city":"Isle Of Capri",
    "sg:classifiers":[
        {
            "category":"Banks & Credit Unions",
            "subcategory":"Investment Brokerage",
            "type":"Services"
        }
    ],
    "sg:phone":"+61 7 5564 8626",
    "sg:postcode":"4217",
    "sg:province":"QLD",
    "wof:name":"Australian Investors Association Ltd",
    "wof:placetype":"venue"
},
  "geometry": {"coordinates":[153.42198181099999,-28.0107898712],"type":"Point"}
}