{
  "type": "Feature",
  "properties": {
    "addr:full":"246 Campbell St Rockhampton QLD 4700",
    "addr:housenumber":"246",
    "addr:postcode":"4700",
    "addr:street":"Campbell St",
    "iso:country":"AU",
    "sg:address":"246 Campbell St",
    "sg:city":"Rockhampton",
    "sg:classifiers":[
        {
            "category":"Building & Trades",
            "subcategory":"Plumbing",
            "type":"Services"
        }
    ],
    "sg:phone":"+61 7 4927 1403",
    "sg:postcode":"4700",
    "sg:province":"QLD",
    "sg:tags":[
        "plumber",
        "gasfitters"
    ],
    "wof:name":"Des Hill Gas Fitting",
    "wof:placetype":"venue"
},
  "geometry": {"coordinates":[150.51121520999999,-23.3863868713],"type":"Point"}
}