{
  "type": "Feature",
  "properties": {
    "iso:country":"AU",
    "sg:address":"5 206 CENTRAL COAST Hwy",
    "sg:city":"Erina",
    "sg:classifiers":[
        {
            "category":"Professional",
            "subcategory":"Accounting & Tax Preparation",
            "type":"Services"
        }
    ],
    "sg:phone":"+61 2 4365 5656",
    "sg:postcode":"2250",
    "sg:province":"NSW",
    "sg:tags":[
        "accountant",
        "auditor"
    ],
    "wof:name":"Rogers Lean & Co",
    "wof:placetype":"venue"
},
  "geometry": {"coordinates":[151.384674072,-33.4362068176],"type":"Point"}
}