{
  "type": "Feature",
  "properties": {
    "iso:country":"AU",
    "sg:address":"180 Reserve Rd",
    "sg:city":"Upper Coomera",
    "sg:classifiers":[
        {
            "category":"Retail",
            "subcategory":"Storage",
            "type":"Services"
        }
    ],
    "sg:phone":"+61 1800 738 386",
    "sg:postcode":"4209",
    "sg:province":"QLD",
    "sg:tags":[
        "removal",
        "furniture"
    ],
    "wof:name":"Coldwell Removals",
    "wof:placetype":"venue"
},
  "geometry": {"coordinates":[153.29522705100001,-27.8672981262],"type":"Point"}
}