{
  "type": "Feature",
  "properties": {
    "iso:country":"AU",
    "sg:address":"85 Capulet Crs",
    "sg:city":"Modbury",
    "sg:classifiers":[
        {
            "category":"Social Services",
            "subcategory":"Child Care",
            "type":"Services"
        }
    ],
    "sg:phone":"+61 8 8265 5824",
    "sg:postcode":"5092",
    "sg:province":"SA",
    "wof:name":"Lurra Community Child Care Centre",
    "wof:placetype":"venue"
},
  "geometry": {"coordinates":[138.67616272000001,-34.8291358948],"type":"Point"}
}