{
  "type": "Feature",
  "properties": {
    "addr:full":"32 Craig Drv Bellbridge VIC 3691",
    "addr:housenumber":"32",
    "addr:postcode":"3691",
    "addr:street":"Craig Drv",
    "iso:country":"AU",
    "sg:address":"32 Craig Drv",
    "sg:city":"Bellbridge",
    "sg:classifiers":[
        {
            "category":"Utilities",
            "subcategory":"Electric",
            "type":"Services"
        }
    ],
    "sg:phone":"+61 2 6026 4385",
    "sg:postcode":"3691",
    "sg:province":"VIC",
    "sg:tags":[
        "electrical",
        "contractor"
    ],
    "wof:name":"Ritchie D J & M G",
    "wof:placetype":"venue"
},
  "geometry": {"coordinates":[147.06004300000001,-36.100018],"type":"Point"}
}