{
  "type": "Feature",
  "properties": {
    "iso:country":"AU",
    "sg:address":"399 Old Geelong Rd",
    "sg:city":"Hoppers Crossing",
    "sg:classifiers":[
        {
            "category":"Home & Garden",
            "subcategory":"Building Materials",
            "type":"Retail Goods"
        }
    ],
    "sg:phone":"+61 410 174 479",
    "sg:postcode":"3029",
    "sg:province":"VIC",
    "sg:tags":[
        "shutter",
        "roller",
        "grille"
    ],
    "wof:name":"All Seasons Secure Roller Shutters",
    "wof:placetype":"venue"
},
  "geometry": {"coordinates":[144.729263,-37.869617],"type":"Point"}
}