{
  "type": "Feature",
  "properties": {
    "iso:country":"AU",
    "sg:address":"486 Thompson Rd",
    "sg:city":"Norlane",
    "sg:classifiers":[
        {
            "category":"Building & Trades",
            "subcategory":"Cleaning & Sanitation",
            "type":"Services"
        }
    ],
    "sg:phone":"+61 3 5278 8685",
    "sg:postcode":"3214",
    "sg:province":"VIC",
    "sg:tags":[
        "industrial",
        "commercial",
        "contractor"
    ],
    "wof:name":"Top Care Carpet Cleaning",
    "wof:placetype":"venue"
},
  "geometry": {"coordinates":[144.34791564899999,-38.0883636475],"type":"Point"}
}