{
  "type": "Feature",
  "properties": {
    "iso:country":"AU",
    "sg:address":"Suite 201/ 89 High St",
    "sg:city":"Kew",
    "sg:classifiers":[
        {
            "category":"Banks & Credit Unions",
            "subcategory":"Financial Services",
            "type":"Services"
        }
    ],
    "sg:phone":"+61 3 9854 6117",
    "sg:postcode":"3101",
    "sg:province":"VIC",
    "sg:tags":[
        "loan",
        "finance",
        "mortgage"
    ],
    "wof:name":"C & K Financial Services Pty Ltd",
    "wof:placetype":"venue"
},
  "geometry": {"coordinates":[145.028106689,-37.8080253601],"type":"Point"}
}