{
  "type": "Feature",
  "properties": {
    "addr:full":"Victoria St Yalgoo WA 6635",
    "addr:postcode":"6635",
    "addr:street":"Victoria St",
    "iso:country":"AU",
    "sg:address":"Victoria St",
    "sg:city":"Yalgoo",
    "sg:classifiers":[
        {
            "category":"Health Services",
            "subcategory":"Doctor",
            "type":"Services"
        }
    ],
    "sg:phone":"+61 8 9962 8600",
    "sg:postcode":"6635",
    "sg:province":"WA",
    "sg:tags":[
        "nurse",
        "nursing"
    ],
    "wof:name":"Yalgoo Nursing Post",
    "wof:placetype":"venue"
},
  "geometry": {"coordinates":[117.897499084,-27.4220161438],"type":"Point"}
}