{
  "type": "Feature",
  "properties": {
    "iso:country":"AU",
    "sg:address":"3/ 121 Flinders La",
    "sg:city":"Melbourne",
    "sg:classifiers":[
        {
            "category":"Home & Garden",
            "subcategory":"Building Materials",
            "type":"Retail Goods"
        }
    ],
    "sg:phone":"+61 3 9654 1332",
    "sg:postcode":"3000",
    "sg:province":"VIC",
    "sg:tags":[
        "concrete",
        "panel",
        "pre-cast"
    ],
    "wof:name":"Hyssil Pty Ltd",
    "wof:placetype":"venue"
},
  "geometry": {"coordinates":[144.97044372600001,-37.8155899048],"type":"Point"}
}