{
  "type": "Feature",
  "properties": {
    "iso:country":"AU",
    "sg:address":"PO Box 22",
    "sg:city":"Lucindale",
    "sg:classifiers":[
        {
            "category":"Building & Trades",
            "subcategory":"Landscaping Services",
            "type":"Services"
        }
    ],
    "sg:phone":"+61 8 8766 2193",
    "sg:postcode":"5272",
    "sg:province":"SA",
    "sg:tags":[
        "grazier"
    ],
    "wof:name":"Loechel R G & L A",
    "wof:placetype":"venue"
},
  "geometry": {"coordinates":[140.369766,-36.973679],"type":"Point"}
}