{
  "type": "Feature",
  "properties": {
    "addr:full":"PO Box 389 Leederville Pte Boxes WA 6903",
    "addr:postcode":"6903",
    "iso:country":"AU",
    "sg:address":"PO Box 389",
    "sg:city":"Leederville Pte Boxes",
    "sg:classifiers":[
        {
            "category":"Health Services",
            "subcategory":"Doctor",
            "type":"Services"
        }
    ],
    "sg:phone":"+61 8 9211 5888",
    "sg:postcode":"6903",
    "sg:province":"WA",
    "sg:tags":[
        "nurse",
        "nursing"
    ],
    "wof:name":"Bellhealth",
    "wof:placetype":"venue"
},
  "geometry": {"coordinates":[115.8412323,-31.9364795685],"type":"Point"}
}