{
  "type": "Feature",
  "properties": {
    "addr:full":"209 Endeavour Drv Banksia Beach QLD 4507",
    "addr:housenumber":"209",
    "addr:postcode":"4507",
    "addr:street":"Endeavour Drv",
    "iso:country":"AU",
    "sg:address":"209 Endeavour Drv",
    "sg:city":"Banksia Beach",
    "sg:classifiers":[
        {
            "category":"Autos & Motor Vehicles",
            "subcategory":"Boat Sales",
            "type":"Retail Goods"
        }
    ],
    "sg:phone":"+61 419 913 436",
    "sg:postcode":"4507",
    "sg:province":"QLD",
    "sg:tags":[
        "equipment",
        "yacht"
    ],
    "wof:name":"Leisure Marine Australia",
    "wof:placetype":"venue"
},
  "geometry": {"coordinates":[153.144622803,-27.0324745178],"type":"Point"}
}