{
  "type": "Feature",
  "properties": {
    "iso:country":"AU",
    "sg:address":"9b Waratah St",
    "sg:city":"Mona Vale",
    "sg:classifiers":[
        {
            "category":"Shopping",
            "subcategory":"Clothing, Apparel, & Fashions",
            "type":"Retail Goods"
        }
    ],
    "sg:phone":"+61 2 9999 2045",
    "sg:postcode":"2103",
    "sg:province":"NSW",
    "sg:tags":[
        "boutique"
    ],
    "wof:name":"Pisces Boutique",
    "wof:placetype":"venue"
},
  "geometry": {"coordinates":[151.30287170400001,-33.6777839661],"type":"Point"}
}