{
  "type": "Feature",
  "properties": {
    "iso:country":"AU",
    "sg:address":"318 Maitland Rd",
    "sg:city":"Cessnock",
    "sg:classifiers":[
        {
            "category":"Building & Trades",
            "subcategory":"Locksmith",
            "type":"Services"
        }
    ],
    "sg:phone":"+61 2 4991 2565",
    "sg:postcode":"2325",
    "sg:province":"NSW",
    "sg:tags":[
        "lock"
    ],
    "wof:name":"A.A.B.J. Locksmiths",
    "wof:placetype":"venue"
},
  "geometry": {"coordinates":[151.365036011,-32.828338623],"type":"Point"}
}