{
  "type": "Feature",
  "properties": {
    "addr:full":"32 Walker Rd Mt Waverley VIC 3149",
    "addr:housenumber":"32",
    "addr:postcode":"3149",
    "addr:street":"Walker Rd",
    "iso:country":"AU",
    "sg:address":"32 Walker Rd",
    "sg:city":"Mt Waverley",
    "sg:classifiers":[
        {
            "category":"Arts & Performance",
            "subcategory":"Music",
            "type":"Entertainment"
        }
    ],
    "sg:phone":"+61 3 9884 6509",
    "sg:postcode":"3149",
    "sg:province":"VIC",
    "sg:tags":[
        "mobile",
        "jockey",
        "disc"
    ],
    "wof:name":"Dickies Entertainment Pty Ltd",
    "wof:placetype":"venue"
},
  "geometry": {"coordinates":[145.14109802199999,-37.8621444702],"type":"Point"}
}