{
  "type": "Feature",
  "properties": {
    "addr:full":"Shop 1 Savoy Centre, Manning St Taree NSW 2430",
    "addr:housenumber":"shop 1",
    "addr:postcode":"2430",
    "addr:street":"Savoy Centre Manning St",
    "iso:country":"AU",
    "sg:address":"Shop 1 Savoy Centre, Manning St",
    "sg:city":"Taree",
    "sg:classifiers":[
        {
            "category":"Building & Trades",
            "subcategory":"Construction",
            "type":"Services"
        }
    ],
    "sg:phone":"+61 2 6551 0077",
    "sg:postcode":"2430",
    "sg:province":"NSW",
    "sg:tags":[
        "home",
        "air conditioning"
    ],
    "wof:name":"Scotts Betta Electrical",
    "wof:placetype":"venue"
},
  "geometry": {"coordinates":[152.46215799999999,-31.91324],"type":"Point"}
}