{
  "type": "Feature",
  "properties": {
    "addr:full":"Unit 6/ 14 King Edward Rd Osborne Park WA 6017",
    "addr:housenumber":"14",
    "addr:postcode":"6017",
    "addr:street":"King Edward Rd",
    "iso:country":"AU",
    "sg:address":"Unit 6/ 14 King Edward Rd",
    "sg:city":"Osborne Park",
    "sg:classifiers":[
        {
            "category":"Autos & Motor Vehicles",
            "subcategory":"Boat Sales",
            "type":"Retail Goods"
        }
    ],
    "sg:phone":"+61 8 9244 3261",
    "sg:postcode":"6017",
    "sg:province":"WA",
    "sg:tags":[
        "yacht"
    ],
    "wof:name":"Cygnet Inflatables",
    "wof:placetype":"venue"
},
  "geometry": {"coordinates":[115.80622863799999,-31.9027328491],"type":"Point"}
}