{
  "type": "Feature",
  "properties": {
    "addr:full":"Shp 4, Lakeside Walk 4 Market St Merimbula NSW 2548",
    "addr:housenumber":"4;4",
    "addr:postcode":"2548",
    "addr:street":"Lakeside Walk;Market St",
    "iso:country":"AU",
    "sg:address":"Shp 4, Lakeside Walk 4 Market St",
    "sg:city":"Merimbula",
    "sg:classifiers":[
        {
            "category":"Ice Cream",
            "type":"Food & Drink"
        }
    ],
    "sg:phone":"+61 2 6495 2054",
    "sg:postcode":"2548",
    "sg:province":"NSW",
    "sg:tags":[
        "retail"
    ],
    "wof:name":"Boardwalk Icecreamery & Crepe",
    "wof:placetype":"venue"
},
  "geometry": {"coordinates":[149.905792236,-36.8883018494],"type":"Point"}
}