{
  "type": "Feature",
  "properties": {
    "addr:full":"28 Bicheno St Clifton Beach TAS 7020",
    "addr:housenumber":"28",
    "addr:postcode":"7020",
    "addr:street":"Bicheno St",
    "iso:country":"AU",
    "sg:address":"28 Bicheno St",
    "sg:city":"Clifton Beach",
    "sg:classifiers":[
        {
            "category":"Home & Garden",
            "subcategory":"Building Materials",
            "type":"Retail Goods"
        }
    ],
    "sg:phone":"+61 438 103 857",
    "sg:postcode":"7020",
    "sg:province":"TAS",
    "sg:tags":[
        "lawn",
        "cutting",
        "maintenance"
    ],
    "wof:name":"Stapenell Dial a Job",
    "wof:placetype":"venue"
},
  "geometry": {"coordinates":[147.52122497600001,-42.9861450195],"type":"Point"}
}