{
  "type": "Feature",
  "properties": {
    "iso:country":"AU",
    "sg:address":"34 Pitt St",
    "sg:city":"Kensington",
    "sg:classifiers":[
        {
            "category":"Building & Trades",
            "subcategory":"Landscaping Services",
            "type":"Services"
        }
    ],
    "sg:phone":"+61 8 9367 9667",
    "sg:postcode":"6151",
    "sg:province":"WA",
    "sg:tags":[
        "designer",
        "landscape",
        "contractor"
    ],
    "wof:name":"Box Clever Garden Designs",
    "wof:placetype":"venue"
},
  "geometry": {"coordinates":[115.885536,-31.982691],"type":"Point"}
}