{
  "type": "Feature",
  "properties": {
    "addr:full":"675 Beach Rd Warwick WA 6024",
    "addr:housenumber":"675",
    "addr:postcode":"6024",
    "addr:street":"Beach Rd",
    "iso:country":"AU",
    "sg:address":"675 Beach Rd",
    "sg:city":"Warwick",
    "sg:classifiers":[
        {
            "category":"Real Estate",
            "subcategory":"Real Estate Agent",
            "type":"Services"
        }
    ],
    "sg:phone":"+61 8 9447 4444",
    "sg:postcode":"6024",
    "sg:province":"WA",
    "wof:name":"Roy Weston Warwick",
    "wof:placetype":"venue"
},
  "geometry": {"coordinates":[115.81214904799999,-31.845582962],"type":"Point"}
}