{
  "type": "Feature",
  "properties": {
    "iso:country":"AU",
    "sg:address":"Shop 2-4/ 6 Onslow Pl",
    "sg:city":"Joondalup",
    "sg:classifiers":[
        {
            "category":"Wholesale",
            "subcategory":"Home Furnishings",
            "type":"Manufacturing & Wholesale Goods"
        }
    ],
    "sg:phone":"+61 8 9301 0653",
    "sg:postcode":"6027",
    "sg:province":"WA",
    "sg:tags":[
        "tile",
        "wholesaler",
        "mfrs",
        "carpet"
    ],
    "wof:name":"Fabulous Carpets & Floors Pty Ltd",
    "wof:placetype":"venue"
},
  "geometry": {"coordinates":[115.766181946,-31.7486248016],"type":"Point"}
}