{
  "type": "Feature",
  "properties": {
    "addr:full":"61 Henderson Rd Wentworth Falls NSW 2782",
    "addr:housenumber":"61",
    "addr:postcode":"2782",
    "addr:street":"Henderson Rd",
    "iso:country":"AU",
    "sg:address":"61 Henderson Rd",
    "sg:city":"Wentworth Falls",
    "sg:classifiers":[
        {
            "category":"Social Services",
            "subcategory":"Retirement Home",
            "type":"Services"
        }
    ],
    "sg:phone":"+61 2 4757 3149",
    "sg:postcode":"2782",
    "sg:province":"NSW",
    "sg:tags":[
        "environmental",
        "consultant",
        "pollution"
    ],
    "wof:name":"Margaret Turton",
    "wof:placetype":"venue"
},
  "geometry": {"coordinates":[150.379730225,-33.7017974854],"type":"Point"}
}