{
  "type": "Feature",
  "properties": {
    "addr:full":"Shop 27 Terrace Pl Raymond Terrace NSW 2324",
    "addr:housenumber":"shop 27",
    "addr:postcode":"2324",
    "addr:street":"Terrace Pl",
    "iso:country":"AU",
    "sg:address":"Shop 27 Terrace Pl",
    "sg:city":"Raymond Terrace",
    "sg:classifiers":[
        {
            "category":"Shopping",
            "subcategory":"Clothing, Apparel, & Fashions",
            "type":"Retail Goods"
        }
    ],
    "sg:phone":"+61 2 4987 1774",
    "sg:postcode":"2324",
    "sg:province":"NSW",
    "sg:tags":[
        "maternity",
        "wear"
    ],
    "wof:name":"Sunima Clothing",
    "wof:placetype":"venue"
},
  "geometry": {"coordinates":[151.76373290999999,-32.7550582886],"type":"Point"}
}