{
  "type": "Feature",
  "properties": {
    "addr:full":"Shd1/ 31 Rene St Noosaville QLD 4566",
    "addr:postcode":"4566",
    "addr:street":"Rene St",
    "iso:country":"AU",
    "sg:address":"Shd1/ 31 Rene St",
    "sg:city":"Noosaville",
    "sg:classifiers":[
        {
            "category":"Retail",
            "subcategory":"Laundry & Dry Cleaning",
            "type":"Services"
        }
    ],
    "sg:phone":"+61 7 5473 0522",
    "sg:postcode":"4566",
    "sg:province":"QLD",
    "wof:name":"Tewantin Laundries",
    "wof:placetype":"venue"
},
  "geometry": {"coordinates":[153.04229736299999,-26.415014267],"type":"Point"}
}