{
  "type": "Feature",
  "properties": {
    "addr:full":"523 Lower North East Rd Campbelltown SA 5074",
    "addr:housenumber":"523",
    "addr:postcode":"5074",
    "addr:street":"Lower North East Rd",
    "iso:country":"AU",
    "sg:address":"523 Lower North East Rd",
    "sg:city":"Campbelltown",
    "sg:classifiers":[
        {
            "category":"Personal",
            "subcategory":"Hair Removal",
            "type":"Services"
        }
    ],
    "sg:phone":"+61 8 8365 8121",
    "sg:postcode":"5074",
    "sg:province":"SA",
    "wof:name":"Adelaide Laser Beauty",
    "wof:placetype":"venue"
},
  "geometry": {"coordinates":[138.661743164,-34.8808517456],"type":"Point"}
}