{
  "type": "Feature",
  "properties": {
    "addr:full":"Shop 2062, Westfield Shopping Centre, Macquarie Ave Liverpool NSW 2170",
    "addr:housenumber":"2062",
    "addr:postcode":"2170",
    "addr:street":"Westfield;Macquarie Ave",
    "iso:country":"AU",
    "sg:address":"Shop 2062, Westfield Shopping Centre, Macquarie Ave",
    "sg:city":"Liverpool",
    "sg:classifiers":[
        {
            "category":"Health Services",
            "subcategory":"Optometrist",
            "type":"Services"
        }
    ],
    "sg:phone":"+61 2 9601 1016",
    "sg:postcode":"2170",
    "sg:province":"NSW",
    "wof:name":"Laubman & Pank",
    "wof:placetype":"venue"
},
  "geometry": {"coordinates":[150.91822814899999,-33.9286499023],"type":"Point"}
}