{
  "type": "Feature",
  "properties": {
    "iso:country":"AU",
    "sg:address":"151 Regent St",
    "sg:city":"Redfern",
    "sg:classifiers":[
        {
            "category":"Real Estate",
            "subcategory":"Architect",
            "type":"Services"
        }
    ],
    "sg:phone":"+61 2 9319 2051",
    "sg:postcode":"2016",
    "sg:province":"NSW",
    "wof:name":"Mackenzie Bremner Pty Ltd",
    "wof:placetype":"venue"
},
  "geometry": {"coordinates":[151.19993591299999,-33.8937759399],"type":"Point"}
}