{
  "type": "Feature",
  "properties": {
    "iso:country":"AU",
    "sg:address":"9 Highlands Ave",
    "sg:city":"Gordon",
    "sg:classifiers":[
        {
            "category":"Education",
            "subcategory":"Special Training",
            "type":"Public Place"
        }
    ],
    "sg:phone":"+61 2 9499 8303",
    "sg:postcode":"2072",
    "sg:province":"NSW",
    "sg:tags":[
        "development"
    ],
    "wof:name":"Advanced Success Technologies",
    "wof:placetype":"venue"
},
  "geometry": {"coordinates":[151.153564453,-33.7489852905],"type":"Point"}
}