{
  "type": "Feature",
  "properties": {
    "iso:country":"AU",
    "sg:address":"264 Railway Pde",
    "sg:city":"West Leederville",
    "sg:classifiers":[
        {
            "category":"Wholesale",
            "subcategory":"Plants",
            "type":"Manufacturing & Wholesale Goods"
        }
    ],
    "sg:phone":"+61 8 9388 6066",
    "sg:postcode":"6007",
    "sg:province":"WA",
    "sg:tags":[
        "florist"
    ],
    "wof:name":"Butler Flowers",
    "wof:placetype":"venue"
},
  "geometry": {"coordinates":[115.832717895,-31.9422607422],"type":"Point"}
}