{
  "type": "Feature",
  "properties": {
    "iso:country":"AU",
    "sg:address":"51 Plantation Rd",
    "sg:city":"Beenleigh",
    "sg:classifiers":[
        {
            "category":"Building & Trades",
            "subcategory":"Equipment Rental",
            "type":"Services"
        }
    ],
    "sg:phone":"+61 7 3259 4422",
    "sg:postcode":"4207",
    "sg:province":"QLD",
    "sg:tags":[
        "crane",
        "hire"
    ],
    "wof:name":"Boom Logistics",
    "wof:placetype":"venue"
},
  "geometry": {"coordinates":[153.216705322,-27.7245597839],"type":"Point"}
}