{
  "type": "Feature",
  "properties": {
    "iso:country":"AU",
    "sg:address":"13 Counithan Pl",
    "sg:city":"Lysterfield",
    "sg:classifiers":[
        {
            "category":"Utilities",
            "subcategory":"Electric",
            "type":"Services"
        }
    ],
    "sg:phone":"+61 417 336 628",
    "sg:postcode":"3156",
    "sg:province":"VIC",
    "sg:tags":[
        "electrical",
        "contractor"
    ],
    "wof:name":"Mike Winters Electrical Contractors",
    "wof:placetype":"venue"
},
  "geometry": {"coordinates":[145.28825378400001,-37.9181480408],"type":"Point"}
}