{
  "type": "Feature",
  "properties": {
    "iso:country":"AU",
    "sg:address":"Shop 59 Mid Valley Shopng Cntr",
    "sg:city":"Morwell",
    "sg:classifiers":[
        {
            "category":"Health Services",
            "subcategory":"Doctor",
            "type":"Services"
        }
    ],
    "sg:phone":"+61 3 5134 3888",
    "sg:postcode":"3840",
    "sg:province":"VIC",
    "sg:tags":[
        "medical",
        "practitioner"
    ],
    "wof:name":"Mid Valley Family Medicine",
    "wof:placetype":"venue"
},
  "geometry": {"coordinates":[146.427566528,-38.2380180359],"type":"Point"}
}