{
  "type": "Feature",
  "properties": {
    "addr:full":"Lot4, Binnalong Rd Kenthurst NSW 2156",
    "addr:postcode":"2156",
    "addr:street":"Binnalong Rd",
    "iso:country":"AU",
    "sg:address":"Lot4, Binnalong Rd",
    "sg:city":"Kenthurst",
    "sg:classifiers":[
        {
            "category":"Organizations",
            "subcategory":"Professional Association",
            "type":"Services"
        }
    ],
    "sg:phone":"+61 405 123 006",
    "sg:postcode":"2156",
    "sg:province":"NSW",
    "sg:tags":[
        "web",
        "internet"
    ],
    "wof:name":"Net Spyder Designs",
    "wof:placetype":"venue"
},
  "geometry": {"coordinates":[151.010818481,-33.6808700562],"type":"Point"}
}