{
  "type": "Feature",
  "properties": {
    "iso:country":"AU",
    "sg:address":"46 Tudawali Crs",
    "sg:city":"Kariong",
    "sg:classifiers":[
        {
            "category":"Real Estate",
            "subcategory":"Surveying",
            "type":"Services"
        }
    ],
    "sg:phone":"+61 2 4340 1071",
    "sg:postcode":"2250",
    "sg:province":"NSW",
    "sg:tags":[
        "surveyor",
        "quantity"
    ],
    "wof:name":"Doug Brown -Wise & Horton",
    "wof:placetype":"venue"
},
  "geometry": {"coordinates":[151.29620361299999,-33.438331604],"type":"Point"}
}