{
  "type": "Feature",
  "properties": {
    "iso:country":"AU",
    "sg:address":"129 Drummond St",
    "sg:city":"Carlton",
    "sg:classifiers":[
        {
            "category":"Professional",
            "subcategory":"Art Services",
            "type":"Services"
        }
    ],
    "sg:phone":"+61 3 9663 9042",
    "sg:postcode":"3053",
    "sg:province":"VIC",
    "sg:tags":[
        "graphic",
        "designer"
    ],
    "sg:website":"http://www.adcore.com.au",
    "wof:name":"AdcoreCreative",
    "wof:placetype":"venue"
},
  "geometry": {"coordinates":[144.96777343799999,-37.8035697937],"type":"Point"}
}