{
  "type": "Feature",
  "properties": {
    "addr:full":"380 Hume Hrd Craigieburn VIC 3064",
    "addr:housenumber":"380",
    "addr:postcode":"3064",
    "addr:street":"Hume Hrd",
    "iso:country":"AU",
    "sg:address":"380 Hume Hrd",
    "sg:city":"Craigieburn",
    "sg:classifiers":[
        {
            "category":"Autos & Motor Vehicles",
            "subcategory":"Auto Supplies",
            "type":"Retail Goods"
        }
    ],
    "sg:phone":"+61 3 9308 4100",
    "sg:postcode":"3064",
    "sg:province":"VIC",
    "sg:tags":[
        "equipment",
        "part",
        "truck"
    ],
    "wof:name":"AAA Truck Parts",
    "wof:placetype":"venue"
},
  "geometry": {"coordinates":[144.948486328,-37.6122398376],"type":"Point"}
}