{
  "type": "Feature",
  "properties": {
    "addr:full":"Bellair St Kensington VIC 3031",
    "addr:postcode":"3031",
    "addr:street":"Bellair St",
    "iso:country":"AU",
    "sg:address":"Bellair St",
    "sg:city":"Kensington",
    "sg:classifiers":[
        {
            "category":"Shopping",
            "subcategory":"Music",
            "type":"Retail Goods"
        }
    ],
    "sg:phone":"+61 3 9376 3315",
    "sg:postcode":"3031",
    "sg:province":"VIC",
    "sg:tags":[
        "instrument",
        "musical"
    ],
    "wof:name":"Guitar Trader",
    "wof:placetype":"venue"
},
  "geometry": {"coordinates":[144.93022199999999,-37.793724],"type":"Point"}
}