{
  "type": "Feature",
  "properties": {
    "addr:full":"7 Taunton Drv Cheltenham VIC 3192",
    "addr:housenumber":"7",
    "addr:postcode":"3192",
    "addr:street":"Taunton Drv",
    "iso:country":"AU",
    "sg:address":"7 Taunton Drv",
    "sg:city":"Cheltenham",
    "sg:classifiers":[
        {
            "category":"Communications",
            "subcategory":"Television Station",
            "type":"Services"
        }
    ],
    "sg:phone":"+61 3 9584 6111",
    "sg:postcode":"3192",
    "sg:province":"VIC",
    "sg:tags":[
        "wholesaler",
        "wire",
        "mfrs",
        "electric",
        "cable"
    ],
    "wof:name":"Meldec Pty Ltd",
    "wof:placetype":"venue"
},
  "geometry": {"coordinates":[145.085205078,-37.9698143005],"type":"Point"}
}