{
  "type": "Feature",
  "properties": {
    "iso:country":"AU",
    "sg:address":"167B Queen St",
    "sg:city":"Ayr",
    "sg:classifiers":[
        {
            "category":"Real Estate",
            "subcategory":"Real Estate Services",
            "type":"Services"
        }
    ],
    "sg:phone":"+61 7 4783 6355",
    "sg:postcode":"4807",
    "sg:province":"QLD",
    "sg:tags":[
        "listing"
    ],
    "wof:name":"Helen Munro Real Estate",
    "wof:placetype":"venue"
},
  "geometry": {"coordinates":[147.403442383,-19.5776500702],"type":"Point"}
}