{
  "type": "Feature",
  "properties": {
    "iso:country":"AU",
    "sg:address":"8 Witham Rd",
    "sg:city":"Maleny",
    "sg:classifiers":[
        {
            "category":"Manufacturing",
            "subcategory":"Food",
            "type":"Manufacturing & Wholesale Goods"
        }
    ],
    "sg:phone":"+61 7 5494 3155",
    "sg:postcode":"4552",
    "sg:province":"QLD",
    "sg:tags":[
        "product",
        "nut",
        "edible"
    ],
    "wof:name":"Chic Nuts",
    "wof:placetype":"venue"
},
  "geometry": {"coordinates":[152.84153747600001,-26.7696075439],"type":"Point"}
}