{
  "type": "Feature",
  "properties": {
    "addr:full":"50 Chesterville Rd Cheltenham VIC 3192",
    "addr:housenumber":"50",
    "addr:postcode":"3192",
    "addr:street":"Chesterville Rd",
    "iso:country":"AU",
    "sg:address":"50 Chesterville Rd",
    "sg:city":"Cheltenham",
    "sg:classifiers":[
        {
            "category":"Health Services",
            "subcategory":"Doctor",
            "type":"Services"
        }
    ],
    "sg:phone":"+61 3 9584 9504",
    "sg:postcode":"3192",
    "sg:province":"VIC",
    "sg:tags":[
        "medical",
        "practitioner"
    ],
    "wof:name":"Wrennall Richard Dr",
    "wof:placetype":"venue"
},
  "geometry": {"coordinates":[145.057174683,-37.9585609436],"type":"Point"}
}