{
  "type": "Feature",
  "properties": {
    "addr:full":"Piralko Rd Giru QLD 4809",
    "addr:postcode":"4809",
    "addr:street":"Piralko Rd",
    "iso:country":"AU",
    "sg:address":"Piralko Rd",
    "sg:city":"Giru",
    "sg:classifiers":[
        {
            "category":"Farming",
            "subcategory":"Farm & Veterinary Services",
            "type":"Manufacturing & Wholesale Goods"
        }
    ],
    "sg:phone":"+61 7 4782 9294",
    "sg:postcode":"4809",
    "sg:province":"QLD",
    "sg:tags":[
        "worm"
    ],
    "wof:name":"Burdekin Worm Growers",
    "wof:placetype":"venue"
},
  "geometry": {"coordinates":[147.06068420400001,-19.5057258606],"type":"Point"}
}