{
  "type": "Feature",
  "properties": {
    "iso:country":"AU",
    "sg:address":"Shop 1/ 79 Old Maryborough Rd",
    "sg:city":"Pialba",
    "sg:classifiers":[
        {
            "category":"Retail",
            "subcategory":"Auto Repair",
            "type":"Services"
        }
    ],
    "sg:phone":"+61 7 4124 7800",
    "sg:postcode":"4655",
    "sg:province":"QLD",
    "sg:tags":[
        "transmission",
        "automotive",
        "car"
    ],
    "wof:name":"Wide Bay Automatics",
    "wof:placetype":"venue"
},
  "geometry": {"coordinates":[152.830307,-25.283028],"type":"Point"}
}