{
  "type": "Feature",
  "properties": {
    "iso:country":"AU",
    "sg:address":"3/ 79 The Parade",
    "sg:city":"Ocean Grove",
    "sg:classifiers":[
        {
            "category":"Health Services",
            "subcategory":"Health Practitioner",
            "type":"Services"
        }
    ],
    "sg:phone":"+61 3 5255 5755",
    "sg:postcode":"3226",
    "sg:province":"VIC",
    "sg:tags":[
        "physiotherapist"
    ],
    "wof:name":"Geelong Physiotherapy",
    "wof:placetype":"venue"
},
  "geometry": {"coordinates":[144.532211,-38.266647],"type":"Point"}
}