{
  "type": "Feature",
  "properties": {
    "iso:country":"AU",
    "sg:address":"PO Box 384",
    "sg:city":"Windsor",
    "sg:classifiers":[
        {
            "category":"Building & Trades",
            "subcategory":"Construction",
            "type":"Services"
        }
    ],
    "sg:phone":"+61 2 4578 4904",
    "sg:postcode":"2756",
    "sg:province":"NSW",
    "sg:tags":[
        "industrial",
        "commercial",
        "air conditioning"
    ],
    "wof:name":"Windsor & Districts Refrigeration Services Pty Ltd",
    "wof:placetype":"venue"
},
  "geometry": {"coordinates":[150.81382751500001,-33.6134490967],"type":"Point"}
}