{
  "type": "Feature",
  "properties": {
    "iso:country":"AU",
    "sg:address":"282 Flinders St",
    "sg:city":"Adelaide",
    "sg:classifiers":[
        {
            "category":"Health Services",
            "subcategory":"Doctor",
            "type":"Services"
        }
    ],
    "sg:phone":"+61 8 8227 1877",
    "sg:postcode":"5001",
    "sg:province":"SA",
    "sg:tags":[
        "medical",
        "practitioner"
    ],
    "wof:name":"The Trott Cosmetic And Plastic Surgery Centre",
    "wof:placetype":"venue"
},
  "geometry": {"coordinates":[138.61102294899999,-34.9264640808],"type":"Point"}
}