{
  "type": "Feature",
  "properties": {
    "addr:full":"175-177 Hume Hwy (Cnr Stanley Dve) Somerton VIC 3062",
    "addr:housenumber":"175-177",
    "addr:postcode":"3062",
    "addr:street":"Hume Hwy Cnr Stanley Dve",
    "iso:country":"AU",
    "sg:address":"175-177 Hume Hwy (Cnr Stanley Dve)",
    "sg:city":"Somerton",
    "sg:classifiers":[
        {
            "category":"Autos & Motor Vehicles",
            "subcategory":"Auto Supplies",
            "type":"Retail Goods"
        }
    ],
    "sg:phone":"+61 3 9305 3522",
    "sg:postcode":"3062",
    "sg:province":"VIC",
    "sg:tags":[
        "battery",
        "automotive"
    ],
    "wof:name":"Beaurepaires",
    "wof:placetype":"venue"
},
  "geometry": {"coordinates":[144.94841003400001,-37.6281204224],"type":"Point"}
}