{
  "type": "Feature",
  "properties": {
    "addr:full":"28 Pender Ave Mornington VIC 3931",
    "addr:housenumber":"28",
    "addr:postcode":"3931",
    "addr:street":"Pender Ave",
    "iso:country":"AU",
    "sg:address":"28 Pender Ave",
    "sg:city":"Mornington",
    "sg:classifiers":[
        {
            "category":"Education",
            "subcategory":"Special Training",
            "type":"Public Place"
        }
    ],
    "sg:phone":"+61 3 5975 8131",
    "sg:postcode":"3931",
    "sg:province":"VIC",
    "sg:tags":[
        "feldenkrais"
    ],
    "wof:name":"Mornington Peninsula Feldenkrais Centre",
    "wof:placetype":"venue"
},
  "geometry": {"coordinates":[145.03477477999999,-38.2373428345],"type":"Point"}
}