{
  "type": "Feature",
  "properties": {
    "addr:full":"6 College St Elsternwick VIC 3185",
    "addr:housenumber":"6",
    "addr:postcode":"3185",
    "addr:street":"College St",
    "iso:country":"AU",
    "sg:address":"6 College St",
    "sg:city":"Elsternwick",
    "sg:classifiers":[
        {
            "category":"Professional",
            "subcategory":"Accounting & Tax Preparation",
            "type":"Services"
        }
    ],
    "sg:phone":"+61 3 9530 6949",
    "sg:postcode":"3185",
    "sg:province":"VIC",
    "sg:tags":[
        "accountant",
        "auditor"
    ],
    "wof:name":"Accounting & Bookkeeping Services",
    "wof:placetype":"venue"
},
  "geometry": {"coordinates":[145.00822448700001,-37.8958129883],"type":"Point"}
}