{
  "type": "Feature",
  "properties": {
    "iso:country":"AU",
    "sg:address":"65 Ayr St",
    "sg:city":"Jamestown",
    "sg:classifiers":[
        {
            "category":"Shopping",
            "subcategory":"Pets & Pet Supplies",
            "type":"Retail Goods"
        }
    ],
    "sg:phone":"+61 8 8664 1005",
    "sg:postcode":"5491",
    "sg:province":"SA",
    "sg:tags":[
        "sheep",
        "equipment",
        "shearing"
    ],
    "wof:name":"Shear Magic Shearing Supplies",
    "wof:placetype":"venue"
},
  "geometry": {"coordinates":[138.60267639200001,-33.205406189],"type":"Point"}
}