{
  "type": "Feature",
  "properties": {
    "iso:country":"AU",
    "sg:address":"Shp 14, The Grove 166- 174 Military Rd",
    "sg:city":"Neutral Bay",
    "sg:classifiers":[
        {
            "category":"Professional",
            "subcategory":"Accounting & Tax Preparation",
            "type":"Services"
        }
    ],
    "sg:phone":"+61 2 9904 3373",
    "sg:postcode":"2089",
    "sg:province":"NSW",
    "sg:tags":[
        "consultant",
        "taxation"
    ],
    "wof:name":"H&R Block",
    "wof:placetype":"venue"
},
  "geometry": {"coordinates":[151.22169494600001,-33.8311271667],"type":"Point"}
}