{
  "type": "Feature",
  "properties": {
    "addr:full":"1st Floor 970 High St Armadale VIC 3143",
    "addr:housenumber":"970",
    "addr:postcode":"3143",
    "addr:street":"High St",
    "iso:country":"AU",
    "sg:address":"1st Floor 970 High St",
    "sg:city":"Armadale",
    "sg:classifiers":[
        {
            "category":"Travel",
            "subcategory":"Travel Agent",
            "type":"Entertainment"
        }
    ],
    "sg:phone":"+61 3 9537 1394",
    "sg:postcode":"3143",
    "sg:province":"VIC",
    "sg:tags":[
        "consultant"
    ],
    "wof:name":"Australians Studying Abroad",
    "wof:placetype":"venue"
},
  "geometry": {"coordinates":[145.02005004899999,-37.8555221558],"type":"Point"}
}