{
  "type": "Feature",
  "properties": {
    "addr:full":"1 Lower Castlereagh St Gilgandra NSW 2827",
    "addr:housenumber":"1",
    "addr:postcode":"2827",
    "addr:street":"Lower Castlereagh St",
    "iso:country":"AU",
    "sg:address":"1 Lower Castlereagh St",
    "sg:city":"Gilgandra",
    "sg:classifiers":[
        {
            "category":"Professional",
            "subcategory":"Art Services",
            "type":"Services"
        }
    ],
    "sg:phone":"+61 427 638 661",
    "sg:postcode":"2827",
    "sg:province":"NSW",
    "sg:tags":[
        "decorator",
        "painter"
    ],
    "wof:name":"Jordison Painting & Maintenance",
    "wof:placetype":"venue"
},
  "geometry": {"coordinates":[148.67123413100001,-31.7023639679],"type":"Point"}
}