{
  "type": "Feature",
  "properties": {
    "addr:full":"26 Lucille Ave Croydon VIC 3136",
    "addr:housenumber":"26",
    "addr:postcode":"3136",
    "addr:street":"Lucille Ave",
    "iso:country":"AU",
    "sg:address":"26 Lucille Ave",
    "sg:city":"Croydon",
    "sg:classifiers":[
        {
            "category":"Home & Garden",
            "subcategory":"Carpets & Floor Coverings",
            "type":"Retail Goods"
        }
    ],
    "sg:phone":"+61 411 862 918",
    "sg:postcode":"3136",
    "sg:province":"VIC",
    "sg:tags":[
        "tile",
        "wall",
        "layer"
    ],
    "wof:name":"La Roche Trevor Slate & Ceramic Tiling Services P/L",
    "wof:placetype":"venue"
},
  "geometry": {"coordinates":[145.266067505,-37.8117332458],"type":"Point"}
}