{
  "type": "Feature",
  "properties": {
    "addr:full":"209 Grange Rd Fairfield VIC 3078",
    "addr:housenumber":"209",
    "addr:postcode":"3078",
    "addr:street":"Grange Rd",
    "iso:country":"AU",
    "sg:address":"209 Grange Rd",
    "sg:city":"Fairfield",
    "sg:classifiers":[
        {
            "category":"Shopping",
            "subcategory":"Computers & Home Electronics",
            "type":"Retail Goods"
        }
    ],
    "sg:phone":"+61 3 9497 8000",
    "sg:postcode":"3078",
    "sg:province":"VIC",
    "sg:tags":[
        "equipment",
        "supply"
    ],
    "wof:name":"AAA Boomerang TCR",
    "wof:placetype":"venue"
},
  "geometry": {"coordinates":[145.02719116200001,-37.7665519714],"type":"Point"}
}