{
  "type": "Feature",
  "properties": {
    "iso:country":"AU",
    "sg:address":"237 Great Western Hwy",
    "sg:city":"Blackheath",
    "sg:classifiers":[
        {
            "category":"Communications",
            "subcategory":"Film & Video Production",
            "type":"Services"
        }
    ],
    "sg:phone":"+61 2 4787 6062",
    "sg:postcode":"2785",
    "sg:province":"NSW",
    "sg:tags":[
        "dvd",
        "library"
    ],
    "wof:name":"Kristi's Home Videos",
    "wof:placetype":"venue"
},
  "geometry": {"coordinates":[150.28497314399999,-33.634311676],"type":"Point"}
}