{
  "type": "Feature",
  "properties": {
    "addr:full":"2 Baileys Rd Tallai QLD 4213",
    "addr:housenumber":"2",
    "addr:postcode":"4213",
    "addr:street":"Baileys Rd",
    "iso:country":"AU",
    "sg:address":"2 Baileys Rd",
    "sg:city":"Tallai",
    "sg:classifiers":[
        {
            "category":"Building & Trades",
            "subcategory":"Construction",
            "type":"Services"
        }
    ],
    "sg:phone":"+61 415 149 501",
    "sg:postcode":"4213",
    "sg:province":"QLD",
    "sg:tags":[
        "fencing",
        "contractor"
    ],
    "wof:name":"MC Industries",
    "wof:placetype":"venue"
},
  "geometry": {"coordinates":[153.339385986,-28.0752449036],"type":"Point"}
}