{
  "type": "Feature",
  "properties": {
    "iso:country":"AU",
    "sg:address":"1 Zanzibar Crt",
    "sg:city":"Parrearra",
    "sg:classifiers":[
        {
            "category":"Organizations",
            "subcategory":"Professional Association",
            "type":"Services"
        }
    ],
    "sg:phone":"+61 416 735 463",
    "sg:postcode":"4575",
    "sg:province":"QLD",
    "sg:tags":[
        "web",
        "internet"
    ],
    "wof:name":"thumbprint creative",
    "wof:placetype":"venue"
},
  "geometry": {"coordinates":[153.12385599999999,-26.715452],"type":"Point"}
}