{
  "type": "Feature",
  "properties": {
    "iso:country":"AU",
    "sg:address":"170 Ryrie St",
    "sg:city":"Geelong",
    "sg:classifiers":[
        {
            "category":"Shopping",
            "subcategory":"Clothing, Apparel, & Fashions",
            "type":"Retail Goods"
        }
    ],
    "sg:phone":"+61 3 5222 7055",
    "sg:postcode":"3220",
    "sg:province":"VIC",
    "sg:tags":[
        "lady",
        "wear"
    ],
    "wof:name":"Issima Boutique",
    "wof:placetype":"venue"
},
  "geometry": {"coordinates":[144.36016799999999,-38.149586],"type":"Point"}
}