{
  "type": "Feature",
  "properties": {
    "addr:full":"39 Colebard St Archerfield West QLD 4108",
    "addr:housenumber":"39",
    "addr:postcode":"4108",
    "addr:street":"Colebard St",
    "iso:country":"AU",
    "sg:address":"39 Colebard St",
    "sg:city":"Archerfield West",
    "sg:classifiers":[
        {
            "category":"Building & Trades",
            "subcategory":"Cleaning & Sanitation",
            "type":"Services"
        }
    ],
    "sg:phone":"+61 7 3277 7135",
    "sg:postcode":"4108",
    "sg:province":"QLD",
    "sg:tags":[
        "abrasive",
        "blasting"
    ],
    "wof:name":"Vision Glass Recycling",
    "wof:placetype":"venue"
},
  "geometry": {"coordinates":[153.00238037099999,-27.5770969391],"type":"Point"}
}