{
  "type": "Feature",
  "properties": {
    "addr:full":"20 Bougainville St Manuka ACT 2603",
    "addr:housenumber":"20",
    "addr:postcode":"2603",
    "addr:street":"Bougainville St",
    "iso:country":"AU",
    "sg:address":"20 Bougainville St",
    "sg:city":"Manuka",
    "sg:classifiers":[
        {
            "category":"Professional",
            "subcategory":"Employment Agencies",
            "type":"Services"
        }
    ],
    "sg:phone":"+61 1300 555 903",
    "sg:postcode":"2603",
    "sg:province":"ACT",
    "sg:tags":[
        "hire",
        "labour",
        "contractor"
    ],
    "wof:name":"Public Affairs Recruitment Company The",
    "wof:placetype":"venue"
},
  "geometry": {"coordinates":[149.13246154800001,-35.321105957],"type":"Point"}
}