{
  "type": "Feature",
  "properties": {
    "addr:full":"Unit5/ 18 Napier Cl Deakin ACT 2600",
    "addr:housenumber":"18",
    "addr:postcode":"2600",
    "addr:street":"Napier Cl Deakin",
    "iso:country":"AU",
    "sg:address":"Unit5/ 18",
    "sg:city":"Napier Cl Deakin",
    "sg:classifiers":[
        {
            "category":"Organizations",
            "subcategory":"Labor Organization",
            "type":"Services"
        }
    ],
    "sg:phone":"+61 2 6273 3710",
    "sg:postcode":"2600",
    "sg:province":"ACT",
    "sg:tags":[
        "union"
    ],
    "wof:name":"Independent Education Union (NSW/ACT)",
    "wof:placetype":"venue"
},
  "geometry": {"coordinates":[149.10842895499999,-35.314781189],"type":"Point"}
}