{
  "type": "Feature",
  "properties": {
    "iso:country":"AU",
    "sg:address":"53 Sheridan St",
    "sg:city":"Cairns",
    "sg:classifiers":[
        {
            "category":"Health Services",
            "subcategory":"Health Practitioner",
            "type":"Services"
        }
    ],
    "sg:phone":"+61 7 4041 7000",
    "sg:postcode":"4870",
    "sg:province":"QLD",
    "sg:tags":[
        "osteopath"
    ],
    "wof:name":"Cairns Osteopathic Clinic",
    "wof:placetype":"venue"
},
  "geometry": {"coordinates":[145.77313232399999,-16.9233131409],"type":"Point"}
}