{
  "type": "Feature",
  "properties": {
    "addr:full":"PO Box 516 Kempsey NSW 2440",
    "addr:postcode":"2440",
    "iso:country":"AU",
    "sg:address":"PO Box 516",
    "sg:city":"Kempsey",
    "sg:classifiers":[
        {
            "category":"Real Estate",
            "subcategory":"Surveying",
            "type":"Services"
        }
    ],
    "sg:phone":"+61 2 6562 2405",
    "sg:postcode":"2440",
    "sg:province":"NSW",
    "sg:tags":[
        "surveyor",
        "land"
    ],
    "wof:name":"Phillis & Associates",
    "wof:placetype":"venue"
},
  "geometry": {"coordinates":[152.84234599999999,-31.07839],"type":"Point"}
}