{
  "type": "Feature",
  "properties": {
    "iso:country":"AU",
    "sg:address":"Shop 7 104 John St",
    "sg:city":"Cabramatta",
    "sg:classifiers":[
        {
            "category":"Real Estate",
            "subcategory":"Real Estate Agent",
            "type":"Services"
        }
    ],
    "sg:phone":"+61 2 9728 3000",
    "sg:postcode":"2166",
    "sg:province":"NSW",
    "wof:name":"Stan's Real Estate Pty Ltd",
    "wof:placetype":"venue"
},
  "geometry": {"coordinates":[150.933868408,-33.8949127197],"type":"Point"}
}