{
  "type": "Feature",
  "properties": {
    "addr:full":"139 Ballantyne Rd Waikerie SA 5330",
    "addr:housenumber":"139",
    "addr:postcode":"5330",
    "addr:street":"Ballantyne Rd",
    "iso:country":"AU",
    "sg:address":"139 Ballantyne Rd",
    "sg:city":"Waikerie",
    "sg:classifiers":[
        {
            "category":"Building & Trades",
            "subcategory":"Equipment Rental",
            "type":"Services"
        }
    ],
    "sg:phone":"+61 428 839 530",
    "sg:postcode":"5330",
    "sg:province":"SA",
    "sg:tags":[
        "crane",
        "hire"
    ],
    "wof:name":"Waikerie Crane Service",
    "wof:placetype":"venue"
},
  "geometry": {"coordinates":[139.951934814,-34.1994361877],"type":"Point"}
}