{
  "type": "Feature",
  "properties": {
    "iso:country":"AU",
    "sg:address":"19 Railway Ave",
    "sg:city":"Wahroonga",
    "sg:classifiers":[
        {
            "category":"Food & Beverages",
            "subcategory":"Supermarket",
            "type":"Retail Goods"
        }
    ],
    "sg:phone":"+61 2 9489 6033",
    "sg:postcode":"2076",
    "sg:province":"NSW",
    "sg:tags":[
        "grocery",
        "store"
    ],
    "wof:name":"IGA Rite-Way Supermarkets",
    "wof:placetype":"venue"
},
  "geometry": {"coordinates":[151.116333008,-33.7181015015],"type":"Point"}
}