{
  "type": "Feature",
  "properties": {
    "addr:full":"Lot 10 Fern Hill Rd Inverell NSW 2360",
    "addr:housenumber":"10",
    "addr:postcode":"2360",
    "addr:street":"Fern Hill Rd",
    "iso:country":"AU",
    "sg:address":"Lot 10 Fern Hill Rd",
    "sg:city":"Inverell",
    "sg:classifiers":[
        {
            "category":"Banks & Credit Unions",
            "subcategory":"Bureau De Change",
            "type":"Services"
        }
    ],
    "sg:phone":"+61 2 6722 4654",
    "sg:postcode":"2360",
    "sg:province":"NSW",
    "sg:tags":[
        "repairs",
        "part",
        "appliance",
        "electrical"
    ],
    "wof:name":"Hindley P Maj",
    "wof:placetype":"venue"
},
  "geometry": {"coordinates":[151.102783203,-29.7576980591],"type":"Point"}
}