{
  "type": "Feature",
  "properties": {
    "iso:country":"AU",
    "sg:address":"8 Gilbert St",
    "sg:city":"Braybrook",
    "sg:classifiers":[
        {
            "category":"Autos & Motor Vehicles",
            "subcategory":"Auto Supplies",
            "type":"Retail Goods"
        }
    ],
    "sg:phone":"+61 3 9311 6815",
    "sg:postcode":"3019",
    "sg:province":"VIC",
    "sg:tags":[
        "tyre"
    ],
    "wof:name":"Leslie's Tyre Sales",
    "wof:placetype":"venue"
},
  "geometry": {"coordinates":[144.85383605999999,-37.7786216736],"type":"Point"}
}