{
  "type": "Feature",
  "properties": {
    "iso:country":"AU",
    "sg:address":"Central Rd",
    "sg:city":"Tom Price",
    "sg:classifiers":[
        {
            "category":"Health Services",
            "subcategory":"Doctor",
            "type":"Services"
        }
    ],
    "sg:phone":"+61 8 9189 1901",
    "sg:postcode":"6751",
    "sg:province":"WA",
    "sg:tags":[
        "medical",
        "practitioner"
    ],
    "wof:name":"Thrussell Sheryl Dr",
    "wof:placetype":"venue"
},
  "geometry": {"coordinates":[117.792900085,-22.6862545013],"type":"Point"}
}