{
  "type": "Feature",
  "properties": {
    "iso:country":"AU",
    "sg:address":"320 Greenhill Rd",
    "sg:city":"Glenside",
    "sg:classifiers":[
        {
            "category":"Health Services",
            "subcategory":"Dentist",
            "type":"Services"
        }
    ],
    "sg:phone":"+61 8 8379 6627",
    "sg:postcode":"5065",
    "sg:province":"SA",
    "wof:name":"Wright Jeffrey J",
    "wof:placetype":"venue"
},
  "geometry": {"coordinates":[138.636352539,-34.9396781921],"type":"Point"}
}