{
  "type": "Feature",
  "properties": {
    "addr:full":"24 Richardson St West Perth WA 6005",
    "addr:housenumber":"24",
    "addr:postcode":"6005",
    "addr:street":"Richardson St",
    "iso:country":"AU",
    "sg:address":"24 Richardson St",
    "sg:city":"West Perth",
    "sg:classifiers":[
        {
            "category":"Health Services",
            "subcategory":"Health Practitioner",
            "type":"Services"
        }
    ],
    "sg:phone":"+61 8 9324 4644",
    "sg:postcode":"6005",
    "sg:province":"WA",
    "sg:tags":[
        "psychologist"
    ],
    "wof:name":"Sylvia Johnstone",
    "wof:placetype":"venue"
},
  "geometry": {"coordinates":[115.841522217,-31.9497261047],"type":"Point"}
}