{
  "type": "Feature",
  "properties": {
    "addr:full":"Steels Rd Benalla VIC 3672",
    "addr:postcode":"3672",
    "addr:street":"Steels Rd",
    "iso:country":"AU",
    "sg:address":"Steels Rd",
    "sg:city":"Benalla",
    "sg:classifiers":[
        {
            "category":"Building & Trades",
            "subcategory":"Landscaping Services",
            "type":"Services"
        }
    ],
    "sg:phone":"+61 3 5762 4364",
    "sg:postcode":"3672",
    "sg:province":"VIC",
    "sg:tags":[
        "stump",
        "tree",
        "felling",
        "removal"
    ],
    "wof:name":"B & C Logging Pty Ltd",
    "wof:placetype":"venue"
},
  "geometry": {"coordinates":[145.936981,-36.560017],"type":"Point"}
}