{
  "type": "Feature",
  "properties": {
    "addr:full":"Suite 2 182 Albert Rd South Melbourne VIC 3205",
    "addr:housenumber":"182",
    "addr:postcode":"3205",
    "addr:street":"Albert Rd",
    "iso:country":"AU",
    "sg:address":"Suite 2 182 Albert Rd",
    "sg:city":"South Melbourne",
    "sg:classifiers":[
        {
            "category":"Autos & Motor Vehicles",
            "subcategory":"Auto Supplies",
            "type":"Retail Goods"
        }
    ],
    "sg:phone":"+61 3 9682 6963",
    "sg:postcode":"3205",
    "sg:province":"VIC",
    "sg:tags":[
        "camper-trailers",
        "caravan",
        "equipment"
    ],
    "wof:name":"RVMA",
    "wof:placetype":"venue"
},
  "geometry": {"coordinates":[144.96818500000001,-37.836868],"type":"Point"}
}