{
  "type": "Feature",
  "properties": {
    "iso:country":"AU",
    "sg:address":"101 Matthew Flinders Drv",
    "sg:city":"Cooee Bay",
    "sg:classifiers":[
        {
            "category":"Food & Beverages",
            "subcategory":"Groceries & Convenience Stores",
            "type":"Retail Goods"
        }
    ],
    "sg:phone":"+61 7 4939 2337",
    "sg:postcode":"4703",
    "sg:province":"QLD",
    "wof:name":"Cooee Bay Store",
    "wof:placetype":"venue"
},
  "geometry": {"coordinates":[150.759933472,-23.1427345276],"type":"Point"}
}