{
  "type": "Feature",
  "properties": {
    "iso:country":"AU",
    "sg:address":"155 Holloway Rd",
    "sg:city":"Croydon North",
    "sg:classifiers":[
        {
            "category":"Professional",
            "subcategory":"Business Services",
            "type":"Services"
        }
    ],
    "sg:phone":"+61 3 9722 2399",
    "sg:postcode":"3136",
    "sg:province":"VIC",
    "sg:tags":[
        "fashion",
        "agent"
    ],
    "wof:name":"Bruce Dahmes Agencies",
    "wof:placetype":"venue"
},
  "geometry": {"coordinates":[145.27359008799999,-37.7628555298],"type":"Point"}
}