{
  "type": "Feature",
  "properties": {
    "iso:country":"AU",
    "sg:address":"23/ 82 Bergin Rd",
    "sg:city":"Ferny Grove",
    "sg:classifiers":[
        {
            "category":"Professional",
            "subcategory":"Art Services",
            "type":"Services"
        }
    ],
    "sg:phone":"+61 412 572 775",
    "sg:postcode":"4055",
    "sg:province":"QLD",
    "sg:tags":[
        "decorator",
        "painter"
    ],
    "wof:name":"Ian Bullivant",
    "wof:placetype":"venue"
},
  "geometry": {"coordinates":[152.92408752399999,-27.3994503021],"type":"Point"}
}