{
  "type": "Feature",
  "properties": {
    "addr:full":"Unit 2, 159 Mark Rd Caloundra West QLD 4551",
    "addr:housenumber":"159",
    "addr:postcode":"4551",
    "addr:street":"Mark Rd",
    "iso:country":"AU",
    "sg:address":"Unit 2, 159 Mark Rd",
    "sg:city":"Caloundra West",
    "sg:classifiers":[
        {
            "category":"Organizations",
            "subcategory":"Community Association",
            "type":"Services"
        }
    ],
    "sg:phone":"+61 7 5499 6770",
    "sg:postcode":"4551",
    "sg:province":"QLD",
    "sg:tags":[
        "equipment",
        "system",
        "vacuum"
    ],
    "wof:name":"Central Vacuum Services Pty Ltd",
    "wof:placetype":"venue"
},
  "geometry": {"coordinates":[153.11117553700001,-26.791929245],"type":"Point"}
}