{
  "type": "Feature",
  "properties": {
    "addr:full":"PO Box 505 Craigmore SA 5114",
    "addr:postcode":"5114",
    "iso:country":"AU",
    "sg:address":"PO Box 505",
    "sg:city":"Craigmore",
    "sg:classifiers":[
        {
            "category":"Building & Trades",
            "subcategory":"Construction",
            "type":"Services"
        }
    ],
    "sg:phone":"+61 417 841 978",
    "sg:postcode":"5114",
    "sg:province":"SA",
    "sg:tags":[
        "earth",
        "excavating",
        "moving",
        "contractor"
    ],
    "wof:name":"Brooklyn Contracting",
    "wof:placetype":"venue"
},
  "geometry": {"coordinates":[138.706176758,-34.6972618103],"type":"Point"}
}