{
  "type": "Feature",
  "properties": {
    "iso:country":"AU",
    "sg:address":"714 Mt Alexander Rd",
    "sg:city":"Moonee Ponds",
    "sg:classifiers":[
        {
            "category":"Personal",
            "subcategory":"Beauty Salon",
            "type":"Services"
        }
    ],
    "sg:phone":"+61 3 9372 0253",
    "sg:postcode":"3039",
    "sg:province":"VIC",
    "wof:name":"Eye Lash Queen",
    "wof:placetype":"venue"
},
  "geometry": {"coordinates":[144.925354,-37.768047],"type":"Point"}
}