{
  "type": "Feature",
  "properties": {
    "addr:full":"35a Main St Merimbula NSW 2548",
    "addr:housenumber":"35a",
    "addr:postcode":"2548",
    "addr:street":"Main St",
    "iso:country":"AU",
    "sg:address":"35a Main St",
    "sg:city":"Merimbula",
    "sg:classifiers":[
        {
            "category":"Professional",
            "subcategory":"Engineering",
            "type":"Services"
        }
    ],
    "sg:phone":"+61 2 6495 1670",
    "sg:postcode":"2548",
    "sg:province":"NSW",
    "sg:tags":[
        "civil",
        "engineer"
    ],
    "wof:name":"Andrew Marshman & Assoc Pty Ltd",
    "wof:placetype":"venue"
},
  "geometry": {"coordinates":[149.91096496599999,-36.8868751526],"type":"Point"}
}