{
  "type": "Feature",
  "properties": {
    "addr:full":"5 Grand Pde Lorne VIC 3232",
    "addr:housenumber":"5",
    "addr:postcode":"3232",
    "addr:street":"Grand Pde",
    "iso:country":"AU",
    "sg:address":"5 Grand Pde",
    "sg:city":"Lorne",
    "sg:classifiers":[
        {
            "category":"Manufacturing",
            "subcategory":"Food",
            "type":"Manufacturing & Wholesale Goods"
        }
    ],
    "sg:phone":"+61 3 5289 1001",
    "sg:postcode":"3232",
    "sg:province":"VIC",
    "sg:tags":[
        "function",
        "catering"
    ],
    "wof:name":"Catering By Bernie",
    "wof:placetype":"venue"
},
  "geometry": {"coordinates":[143.97178600000001,-38.536388],"type":"Point"}
}