{
  "type": "Feature",
  "properties": {
    "addr:full":"Roslyn Rd Belmont VIC 3216",
    "addr:postcode":"3216",
    "addr:street":"Roslyn Rd",
    "iso:country":"AU",
    "sg:address":"Roslyn Rd",
    "sg:city":"Belmont",
    "sg:classifiers":[
        {
            "category":"Education",
            "subcategory":"School",
            "type":"Public Place"
        }
    ],
    "sg:phone":"+61 3 5243 3538",
    "sg:postcode":"3216",
    "sg:province":"VIC",
    "sg:tags":[
        "state",
        "except",
        "nsw"
    ],
    "wof:name":"Roslyn Primary School",
    "wof:placetype":"venue"
},
  "geometry": {"coordinates":[144.34277343799999,-38.1753768921],"type":"Point"}
}