{
  "type": "Feature",
  "properties": {
    "addr:full":"138 Williams Rd Prahran VIC 3181",
    "addr:housenumber":"138",
    "addr:postcode":"3181",
    "addr:street":"Williams Rd",
    "iso:country":"AU",
    "sg:address":"138 Williams Rd",
    "sg:city":"Prahran",
    "sg:classifiers":[
        {
            "category":"Health Services",
            "subcategory":"Doctor",
            "type":"Services"
        }
    ],
    "sg:phone":"+61 3 9521 7040",
    "sg:postcode":"3181",
    "sg:province":"VIC",
    "sg:tags":[
        "medical",
        "practitioner"
    ],
    "wof:name":"Ferguson & Stokes",
    "wof:placetype":"venue"
},
  "geometry": {"coordinates":[145.003005981,-37.8502693176],"type":"Point"}
}