{
  "type": "Feature",
  "properties": {
    "addr:full":"205 Tuckers La North Rothbury NSW 2335",
    "addr:housenumber":"205",
    "addr:postcode":"2335",
    "addr:street":"Tuckers La North",
    "iso:country":"AU",
    "sg:address":"205 Tuckers La",
    "sg:city":"North Rothbury",
    "sg:classifiers":[
        {
            "category":"Retail",
            "subcategory":"Auto Repair",
            "type":"Services"
        }
    ],
    "sg:phone":"+61 2 4938 1956",
    "sg:postcode":"2335",
    "sg:province":"NSW",
    "sg:tags":[
        "body",
        "motor",
        "trimmer"
    ],
    "wof:name":"Keith Lang Upholstery",
    "wof:placetype":"venue"
},
  "geometry": {"coordinates":[151.36210632300001,-32.6943664551],"type":"Point"}
}