{
  "type": "Feature",
  "properties": {
    "addr:full":"59 Wentworth Ave Surry Hills NSW 2010",
    "addr:housenumber":"59",
    "addr:postcode":"2010",
    "addr:street":"Wentworth Ave",
    "iso:country":"AU",
    "sg:address":"59 Wentworth Ave",
    "sg:city":"Surry Hills",
    "sg:classifiers":[
        {
            "category":"Professional",
            "subcategory":"Employment Agencies",
            "type":"Services"
        }
    ],
    "sg:phone":"+61 2 8204 5888",
    "sg:postcode":"2010",
    "sg:province":"NSW",
    "sg:tags":[
        "provider",
        "internet"
    ],
    "wof:name":"Red Sheriff Ltd",
    "wof:placetype":"venue"
},
  "geometry": {"coordinates":[151.210494995,-33.8786354065],"type":"Point"}
}