{
  "type": "Feature",
  "properties": {
    "iso:country":"AU",
    "sg:address":"215 Grattan St",
    "sg:city":"Parkville",
    "sg:classifiers":[
        {
            "category":"Banks & Credit Unions",
            "subcategory":"Investment Brokerage",
            "type":"Services"
        }
    ],
    "sg:phone":"+61 3 9362 5804",
    "sg:postcode":"3052",
    "sg:province":"VIC",
    "wof:name":"Uniseed",
    "wof:placetype":"venue"
},
  "geometry": {"coordinates":[144.96134948700001,-37.8002510071],"type":"Point"}
}