{
  "type": "Feature",
  "properties": {
    "iso:country":"AU",
    "sg:address":"410 Campbell St",
    "sg:city":"Swan Hill",
    "sg:classifiers":[
        {
            "category":"Autos & Motor Vehicles",
            "subcategory":"Auto Supplies",
            "type":"Retail Goods"
        }
    ],
    "sg:phone":"+61 3 5032 3700",
    "sg:postcode":"3585",
    "sg:province":"NSW",
    "sg:tags":[
        "oil",
        "spirit"
    ],
    "wof:name":"BP",
    "wof:placetype":"venue"
},
  "geometry": {"coordinates":[143.56137100000001,-35.346691],"type":"Point"}
}