{
  "type": "Feature",
  "properties": {
    "iso:country":"AU",
    "sg:address":"Shp2/ 25 Coondoo St",
    "sg:city":"Kuranda",
    "sg:classifiers":[
        {
            "category":"Shopping",
            "subcategory":"Clothing, Apparel, & Fashions",
            "type":"Retail Goods"
        }
    ],
    "sg:phone":"+61 7 4093 8638",
    "sg:postcode":"4881",
    "sg:province":"QLD",
    "sg:tags":[
        "lady",
        "wear"
    ],
    "wof:name":"Madison On Coondoo",
    "wof:placetype":"venue"
},
  "geometry": {"coordinates":[145.63583374000001,-16.819480896],"type":"Point"}
}