{
  "type": "Feature",
  "properties": {
    "addr:full":"41 Christen Drv Beachmere QLD 4510",
    "addr:housenumber":"41",
    "addr:postcode":"4510",
    "addr:street":"Christen Drv",
    "iso:country":"AU",
    "sg:address":"41 Christen Drv",
    "sg:city":"Beachmere",
    "sg:classifiers":[
        {
            "category":"Building & Trades",
            "subcategory":"Pest Control",
            "type":"Services"
        }
    ],
    "sg:phone":"+61 7 5496 8918",
    "sg:postcode":"4510",
    "sg:province":"QLD",
    "wof:name":"Permanent Pest Control",
    "wof:placetype":"venue"
},
  "geometry": {"coordinates":[153.07646199999999,-27.095211],"type":"Point"}
}