{
  "type": "Feature",
  "properties": {
    "iso:country":"AU",
    "sg:address":"Cnr Empire Bay Drv & Kerta Rd",
    "sg:city":"Kincumber South",
    "sg:classifiers":[
        {
            "category":"Fast Food",
            "type":"Food & Drink"
        }
    ],
    "sg:phone":"+61 2 4368 1565",
    "sg:postcode":"2251",
    "sg:province":"NSW",
    "sg:tags":[
        "away",
        "take"
    ],
    "wof:name":"Dragon Paradise Chinese Restaurant",
    "wof:placetype":"venue"
},
  "geometry": {"coordinates":[151.38548278799999,-33.4820632935],"type":"Point"}
}