{
  "type": "Feature",
  "properties": {
    "iso:country":"AU",
    "sg:address":"41 The Strand St",
    "sg:city":"Port Elliot",
    "sg:classifiers":[
        {
            "category":"Government",
            "subcategory":"Post Office",
            "type":"Public Place"
        }
    ],
    "sg:phone":"+61 8 8554 2120",
    "sg:postcode":"5212",
    "sg:province":"SA",
    "sg:tags":[
        "postal"
    ],
    "wof:name":"Australia Post",
    "wof:placetype":"venue"
},
  "geometry": {"coordinates":[138.68145751899999,-35.5313491821],"type":"Point"}
}