{
  "type": "Feature",
  "properties": {
    "iso:country":"AU",
    "sg:address":"Units 19-20 89 Gow St",
    "sg:city":"Padstow",
    "sg:classifiers":[
        {
            "category":"Shopping",
            "subcategory":"Stationery & Office Supplies",
            "type":"Retail Goods"
        }
    ],
    "sg:phone":"+61 2 9790 4751",
    "sg:postcode":"2211",
    "sg:province":"NSW",
    "sg:tags":[
        "packaging",
        "material"
    ],
    "wof:name":"Antheo Packaging (South) Pty Ltd",
    "wof:placetype":"venue"
},
  "geometry": {"coordinates":[151.03048699999999,-33.937115],"type":"Point"}
}