{
  "type": "Feature",
  "properties": {
    "addr:full":"PO Box 6043 Maroochydore BC QLD 4558",
    "addr:postcode":"qld 4558",
    "iso:country":"AU",
    "sg:address":"PO Box 6043",
    "sg:city":"Maroochydore BC",
    "sg:classifiers":[
        {
            "category":"Autos & Motor Vehicles",
            "subcategory":"Auto Supplies",
            "type":"Retail Goods"
        }
    ],
    "sg:phone":"+61 7 5479 1118",
    "sg:postcode":"4558",
    "sg:province":"QLD",
    "sg:tags":[
        "accessory"
    ],
    "wof:name":"Hailsafe Pty Ltd",
    "wof:placetype":"venue"
},
  "geometry": {"coordinates":[153.09274292000001,-26.6657295227],"type":"Point"}
}