{
  "type": "Feature",
  "properties": {
    "iso:country":"AU",
    "sg:address":"2505 Sandgate Rd",
    "sg:city":"Boondall",
    "sg:classifiers":[
        {
            "category":"Wholesale",
            "subcategory":"Auto Parts",
            "type":"Manufacturing & Wholesale Goods"
        }
    ],
    "sg:phone":"+61 7 3265 5199",
    "sg:postcode":"4034",
    "sg:province":"QLD",
    "sg:tags":[
        "recyclers"
    ],
    "wof:name":"A. A. Car Parts Supplies",
    "wof:placetype":"venue"
},
  "geometry": {"coordinates":[153.059601,-27.339809],"type":"Point"}
}