{
  "type": "Feature",
  "properties": {
    "addr:full":"5 Gould St Wurruk VIC 3850",
    "addr:housenumber":"5",
    "addr:postcode":"3850",
    "addr:street":"Gould St",
    "iso:country":"AU",
    "sg:address":"5 Gould St",
    "sg:city":"Wurruk",
    "sg:classifiers":[
        {
            "category":"Building & Trades",
            "subcategory":"Construction",
            "type":"Services"
        }
    ],
    "sg:phone":"+61 408 507 349",
    "sg:postcode":"3850",
    "sg:province":"VIC",
    "sg:tags":[
        "earth",
        "excavating",
        "moving",
        "contractor"
    ],
    "wof:name":"Wurruk Excavations",
    "wof:placetype":"venue"
},
  "geometry": {"coordinates":[147.036834717,-38.1041069031],"type":"Point"}
}