{
  "type": "Feature",
  "properties": {
    "addr:full":"1109 Botany Rd Mascot NSW 2020",
    "addr:housenumber":"1109",
    "addr:postcode":"2020",
    "addr:street":"Botany Rd",
    "iso:country":"AU",
    "sg:address":"1109 Botany Rd",
    "sg:city":"Mascot",
    "sg:classifiers":[
        {
            "category":"Fast Food",
            "type":"Food & Drink"
        }
    ],
    "sg:phone":"+61 2 9667 4325",
    "sg:postcode":"2020",
    "sg:province":"NSW",
    "sg:tags":[
        "away",
        "take"
    ],
    "wof:name":"Anadolu Pizza Shop",
    "wof:placetype":"venue"
},
  "geometry": {"coordinates":[151.194946289,-33.9289703369],"type":"Point"}
}