{
  "type": "Feature",
  "properties": {
    "addr:full":"Factory 4, 244 Marine Pde Hastings VIC 3915",
    "addr:housenumber":"244",
    "addr:postcode":"3915",
    "addr:street":"Marine Pde",
    "iso:country":"AU",
    "sg:address":"Factory 4, 244 Marine Pde",
    "sg:city":"Hastings",
    "sg:classifiers":[
        {
            "category":"Building & Trades",
            "subcategory":"Plumbing",
            "type":"Services"
        }
    ],
    "sg:phone":"+61 411 178 682",
    "sg:postcode":"3915",
    "sg:province":"VIC",
    "sg:tags":[
        "plumber",
        "gasfitters"
    ],
    "wof:name":"Bell Plumbing & Excavator Hire",
    "wof:placetype":"venue"
},
  "geometry": {"coordinates":[145.190109253,-38.2884597778],"type":"Point"}
}