{
  "type": "Feature",
  "properties": {
    "iso:country":"AU",
    "sg:address":"4 Opal St",
    "sg:city":"Lightning Ridge",
    "sg:classifiers":[
        {
            "category":"Cafe",
            "type":"Food & Drink"
        }
    ],
    "sg:phone":"+61 2 6829 2725",
    "sg:postcode":"2834",
    "sg:province":"NSW",
    "wof:name":"Stardust Cafe",
    "wof:placetype":"venue"
},
  "geometry": {"coordinates":[147.979218,-29.428469],"type":"Point"}
}