{
  "type": "Feature",
  "properties": {
    "addr:full":"207 Campbell St Hobart TAS 7000",
    "addr:housenumber":"207",
    "addr:postcode":"7000",
    "addr:street":"Campbell St",
    "iso:country":"AU",
    "sg:address":"207 Campbell St",
    "sg:city":"Hobart",
    "sg:classifiers":[
        {
            "category":"Building & Trades",
            "subcategory":"Construction",
            "type":"Services"
        }
    ],
    "sg:phone":"+61 3 6234 4527",
    "sg:postcode":"7000",
    "sg:province":"TAS",
    "sg:tags":[
        "contractor"
    ],
    "wof:name":"P & C Management ( TAS ) Pty Ltd",
    "wof:placetype":"venue"
},
  "geometry": {"coordinates":[147.32325744600001,-42.8741378784],"type":"Point"}
}