{
  "type": "Feature",
  "properties": {
    "addr:full":"Unit 3 7- 29 Bridge Rd Stanmore NSW 2048",
    "addr:housenumber":"7 29",
    "addr:postcode":"2048",
    "addr:street":"Bridge Rd",
    "iso:country":"AU",
    "sg:address":"Unit 3 7- 29 Bridge Rd",
    "sg:city":"Stanmore",
    "sg:classifiers":[
        {
            "category":"Shopping",
            "subcategory":"Computers & Home Electronics",
            "type":"Retail Goods"
        }
    ],
    "sg:phone":"+61 2 9557 8111",
    "sg:postcode":"2048",
    "sg:province":"NSW",
    "sg:tags":[
        "hardware",
        "equipment"
    ],
    "wof:name":"Advance Pacific Peripherals Pty Ltd",
    "wof:placetype":"venue"
},
  "geometry": {"coordinates":[151.17121900000001,-33.889874],"type":"Point"}
}