{
  "type": "Feature",
  "properties": {
    "addr:full":"55 Queens Rd Silvan VIC 3795",
    "addr:housenumber":"55",
    "addr:postcode":"3795",
    "addr:street":"Queens Rd",
    "iso:country":"AU",
    "sg:address":"55 Queens Rd",
    "sg:city":"Silvan",
    "sg:classifiers":[
        {
            "category":"Wholesale",
            "subcategory":"Plants",
            "type":"Manufacturing & Wholesale Goods"
        }
    ],
    "sg:phone":"+61 3 9737 9436",
    "sg:postcode":"3795",
    "sg:province":"VIC",
    "sg:tags":[
        "florist"
    ],
    "wof:name":"Bakker & Co",
    "wof:placetype":"venue"
},
  "geometry": {"coordinates":[145.41744995100001,-37.8193969727],"type":"Point"}
}