{
  "type": "Feature",
  "properties": {
    "iso:country":"AU",
    "sg:address":"113 Fitzroy St St",
    "sg:city":"Kilda",
    "sg:classifiers":[
        {
            "category":"Professional",
            "subcategory":"Art Services",
            "type":"Services"
        }
    ],
    "sg:phone":"+61 3 9537 2855",
    "sg:postcode":"3182",
    "sg:province":"VIC",
    "sg:tags":[
        "graphic",
        "designer"
    ],
    "wof:name":"Igloo Design",
    "wof:placetype":"venue"
},
  "geometry": {"coordinates":[144.97706604000001,-37.8600959778],"type":"Point"}
}