{
  "type": "Feature",
  "properties": {
    "addr:full":"324 Raglan St Sale VIC 3850",
    "addr:housenumber":"324",
    "addr:postcode":"3850",
    "addr:street":"Raglan St",
    "iso:country":"AU",
    "sg:address":"324 Raglan St",
    "sg:city":"Sale",
    "sg:classifiers":[
        {
            "category":"Retail",
            "subcategory":"Auto Rental",
            "type":"Services"
        }
    ],
    "sg:phone":"+61 3 5144 2623",
    "sg:postcode":"3850",
    "sg:province":"VIC",
    "sg:tags":[
        "car",
        "hire",
        "minibus"
    ],
    "wof:name":"Little's Gippsland Coaches Pty Ltd",
    "wof:placetype":"venue"
},
  "geometry": {"coordinates":[147.08987426799999,-38.1012916565],"type":"Point"}
}