{
  "type": "Feature",
  "properties": {
    "addr:full":"41 Holmes Rd Moonee Ponds VIC 3039",
    "addr:housenumber":"41",
    "addr:postcode":"3039",
    "addr:street":"Holmes Rd",
    "iso:country":"AU",
    "sg:address":"41 Holmes Rd",
    "sg:city":"Moonee Ponds",
    "sg:classifiers":[
        {
            "category":"Restaurant",
            "type":"Food & Drink"
        }
    ],
    "sg:phone":"+61 3 9370 2752",
    "sg:postcode":"3039",
    "sg:province":"VIC",
    "wof:name":"Dragon Valley Chinese Restaurant",
    "wof:placetype":"venue"
},
  "geometry": {"coordinates":[144.917923,-37.766525],"type":"Point"}
}