{
  "type": "Feature",
  "properties": {
    "addr:full":"520 Tooronga Rd Hawthorn East VIC 3123",
    "addr:housenumber":"520",
    "addr:postcode":"3123",
    "addr:street":"Tooronga Rd",
    "iso:country":"AU",
    "sg:address":"520 Tooronga Rd",
    "sg:city":"Hawthorn East",
    "sg:classifiers":[
        {
            "category":"Building & Trades",
            "subcategory":"Landscaping Services",
            "type":"Services"
        }
    ],
    "sg:phone":"+61 410 608 287",
    "sg:postcode":"3123",
    "sg:province":"VIC",
    "sg:tags":[
        "stump",
        "tree",
        "felling",
        "removal"
    ],
    "wof:name":"Southern Arborists",
    "wof:placetype":"venue"
},
  "geometry": {"coordinates":[145.047531128,-37.8320655823],"type":"Point"}
}