{
  "type": "Feature",
  "properties": {
    "addr:full":"1st Flr, 97 Tamar St Ballina NSW 2478",
    "addr:housenumber":"97",
    "addr:postcode":"2478",
    "addr:street":"Tamar St",
    "iso:country":"AU",
    "sg:address":"1st Flr, 97 Tamar St",
    "sg:city":"Ballina",
    "sg:classifiers":[
        {
            "category":"Professional",
            "subcategory":"Accounting & Tax Preparation",
            "type":"Services"
        }
    ],
    "sg:phone":"+61 2 6686 3000",
    "sg:postcode":"2478",
    "sg:province":"NSW",
    "sg:tags":[
        "accountant",
        "auditor"
    ],
    "wof:name":"Collins Hume",
    "wof:placetype":"venue"
},
  "geometry": {"coordinates":[153.55857849099999,-28.8681259155],"type":"Point"}
}