{
  "type": "Feature",
  "properties": {
    "iso:country":"AU",
    "sg:address":"Fcty4/ 414 Dynon Rd",
    "sg:city":"West Melbourne",
    "sg:classifiers":[
        {
            "category":"Retail",
            "subcategory":"Auto Repair",
            "type":"Services"
        }
    ],
    "sg:phone":"+61 3 9687 7118",
    "sg:postcode":"3003",
    "sg:province":"VIC",
    "sg:tags":[
        "repairer",
        "motor",
        "engineer"
    ],
    "wof:name":"Chasers Motorworks",
    "wof:placetype":"venue"
},
  "geometry": {"coordinates":[144.914306641,-37.8013038635],"type":"Point"}
}