{
  "type": "Feature",
  "properties": {
    "iso:country":"AU",
    "sg:address":"Shop 34 Southgate S/C Cnr Port Hacking Rd & Princes Hwy",
    "sg:city":"Sylvania",
    "sg:classifiers":[
        {
            "category":"Food & Beverages",
            "subcategory":"Bakery",
            "type":"Retail Goods"
        }
    ],
    "sg:phone":"+61 2 9522 9933",
    "sg:postcode":"2224",
    "sg:province":"NSW",
    "sg:tags":[
        "baker"
    ],
    "wof:name":"Bakers Delight Ltd",
    "wof:placetype":"venue"
},
  "geometry": {"coordinates":[151.10504150400001,-34.0103302002],"type":"Point"}
}