{
  "type": "Feature",
  "properties": {
    "iso:country":"AU",
    "sg:address":"18 Valentino Drv",
    "sg:city":"Croydon",
    "sg:classifiers":[
        {
            "category":"Professional",
            "subcategory":"Accounting & Tax Preparation",
            "type":"Services"
        }
    ],
    "sg:phone":"+61 3 9723 2818",
    "sg:postcode":"3136",
    "sg:province":"VIC",
    "sg:tags":[
        "accountant",
        "auditor"
    ],
    "wof:name":"Anne Hadley / BookBreakers",
    "wof:placetype":"venue"
},
  "geometry": {"coordinates":[145.265060425,-37.8013305664],"type":"Point"}
}