{
  "type": "Feature",
  "properties": {
    "iso:country":"AU",
    "sg:address":"8/ 22 Miles St",
    "sg:city":"Hawthorne",
    "sg:classifiers":[
        {
            "category":"Professional",
            "subcategory":"Management & Consulting",
            "type":"Services"
        }
    ],
    "sg:phone":"+61 7 3217 9664",
    "sg:postcode":"4171",
    "sg:province":"QLD",
    "sg:tags":[
        "consultant"
    ],
    "wof:name":"PCS Corporate Development",
    "wof:placetype":"venue"
},
  "geometry": {"coordinates":[153.06320190400001,-27.4661903381],"type":"Point"}
}