{
  "type": "Feature",
  "properties": {
    "addr:full":"17 Tivoli Rd South Yarra VIC 3141",
    "addr:housenumber":"17",
    "addr:postcode":"3141",
    "addr:street":"Tivoli Rd",
    "iso:country":"AU",
    "sg:address":"17 Tivoli Rd",
    "sg:city":"South Yarra",
    "sg:classifiers":[
        {
            "category":"Shopping",
            "subcategory":"Clothing, Apparel, & Fashions",
            "type":"Retail Goods"
        }
    ],
    "sg:phone":"+61 3 9866 6663",
    "sg:postcode":"3141",
    "sg:province":"VIC",
    "sg:tags":[
        "millinery"
    ],
    "wof:name":"Wendy Mead Hats",
    "wof:placetype":"venue"
},
  "geometry": {"coordinates":[144.980072022,-37.8362121582],"type":"Point"}
}