{
  "type": "Feature",
  "properties": {
    "iso:country":"AU",
    "sg:address":"Unit 1/ 35",
    "sg:city":"Premier Cct Warana",
    "sg:classifiers":[
        {
            "category":"Professional",
            "subcategory":"Engineering",
            "type":"Services"
        }
    ],
    "sg:phone":"+61 7 5493 5455",
    "sg:postcode":"4575",
    "sg:province":"QLD",
    "sg:tags":[
        "diesel",
        "engineer"
    ],
    "sg:website":"http://www.dieselpower.com.au",
    "wof:name":"Diesel Power Systems",
    "wof:placetype":"venue"
},
  "geometry": {"coordinates":[153.13076799999999,-26.719839],"type":"Point"}
}