{
  "type": "Feature",
  "properties": {
    "iso:country":"AU",
    "sg:address":"8/ 565 Beenleigh Rd",
    "sg:city":"Sunnybank Hills",
    "sg:classifiers":[
        {
            "category":"Professional",
            "subcategory":"Accounting & Tax Preparation",
            "type":"Services"
        }
    ],
    "sg:phone":"+61 7 3345 8222",
    "sg:postcode":"4109",
    "sg:province":"QLD",
    "sg:tags":[
        "accountant",
        "auditor"
    ],
    "wof:name":"Alan Elphinstone & Co",
    "wof:placetype":"venue"
},
  "geometry": {"coordinates":[153.056396484,-27.585641861],"type":"Point"}
}