{
  "type": "Feature",
  "properties": {
    "addr:full":"8 Hawkesbury St Berwick VIC 3806",
    "addr:housenumber":"8",
    "addr:postcode":"3806",
    "addr:street":"Hawkesbury St",
    "iso:country":"AU",
    "sg:address":"8 Hawkesbury St",
    "sg:city":"Berwick",
    "sg:classifiers":[
        {
            "category":"Building & Trades",
            "subcategory":"Construction",
            "type":"Services"
        }
    ],
    "sg:phone":"+61 3 8786 8500",
    "sg:postcode":"3806",
    "sg:province":"VIC",
    "sg:tags":[
        "contractor"
    ],
    "wof:name":"Darmon Homes Pty Ltd",
    "wof:placetype":"venue"
},
  "geometry": {"coordinates":[145.349517822,-38.062412262],"type":"Point"}
}