{
  "type": "Feature",
  "properties": {
    "addr:full":"Cnr Florence St & Princes Hwy Fairy Meadow NSW 2519",
    "addr:postcode":"2519",
    "addr:street":"Cnr Florence St & Princes Hwy",
    "iso:country":"AU",
    "sg:address":"Cnr Florence St & Princes Hwy",
    "sg:city":"Fairy Meadow",
    "sg:classifiers":[
        {
            "category":"Autos & Motor Vehicles",
            "subcategory":"Auto Supplies",
            "type":"Retail Goods"
        }
    ],
    "sg:phone":"+61 2 4285 3011",
    "sg:postcode":"2519",
    "sg:province":"NSW",
    "sg:tags":[
        "wheel",
        "automotive",
        "rim"
    ],
    "wof:name":"JAXQuickfit Tyres",
    "wof:placetype":"venue"
},
  "geometry": {"coordinates":[150.89445499999999,-34.385941],"type":"Point"}
}