{
  "type": "Feature",
  "properties": {
    "iso:country":"AU",
    "sg:address":"75 Mulgrave St",
    "sg:city":"Gin Gin",
    "sg:classifiers":[
        {
            "category":"Food & Beverages",
            "subcategory":"Groceries & Convenience Stores",
            "type":"Retail Goods"
        }
    ],
    "sg:phone":"+61 7 4157 2230",
    "sg:postcode":"4671",
    "sg:province":"QLD",
    "wof:name":"Wills General Store",
    "wof:placetype":"venue"
},
  "geometry": {"coordinates":[151.956757,-24.992378],"type":"Point"}
}