{
  "type": "Feature",
  "properties": {
    "iso:country":"AU",
    "sg:address":"13 Pound St",
    "sg:city":"West Ipswich",
    "sg:classifiers":[
        {
            "category":"Retail",
            "subcategory":"Auto Repair",
            "type":"Services"
        }
    ],
    "sg:phone":"+61 7 3812 1877",
    "sg:postcode":"4305",
    "sg:province":"QLD",
    "sg:tags":[
        "repairer",
        "motor",
        "engineer"
    ],
    "wof:name":"Kinnane's Car Clinic",
    "wof:placetype":"venue"
},
  "geometry": {"coordinates":[152.74966430699999,-27.6226158142],"type":"Point"}
}