{
  "type": "Feature",
  "properties": {
    "iso:country":"AU",
    "sg:address":"Cnr Karobran Drive & Livingstone Rd",
    "sg:city":"Vermont South",
    "sg:classifiers":[
        {
            "category":"Social Services",
            "subcategory":"Child Care",
            "type":"Services"
        }
    ],
    "sg:phone":"+61 3 9887 9489",
    "sg:postcode":"3133",
    "sg:province":"VIC",
    "wof:name":"Vermont South Children's Services Centre",
    "wof:placetype":"venue"
},
  "geometry": {"coordinates":[145.181640625,-37.8538398743],"type":"Point"}
}