{
  "type": "Feature",
  "properties": {
    "iso:country":"AU",
    "sg:address":"Unit 3/ 167 Airds Rd",
    "sg:city":"Leumeah",
    "sg:classifiers":[
        {
            "category":"Home & Garden",
            "subcategory":"Building Materials",
            "type":"Retail Goods"
        }
    ],
    "sg:phone":"+61 13 16 16",
    "sg:postcode":"2560",
    "sg:province":"NSW",
    "sg:tags":[
        "merchant",
        "glass",
        "glazier"
    ],
    "wof:name":"O&#039;Brien",
    "wof:placetype":"venue"
},
  "geometry": {"coordinates":[150.831741333,-34.045211792],"type":"Point"}
}