{
  "type": "Feature",
  "properties": {
    "iso:country":"AU",
    "sg:address":"MacPherson St",
    "sg:city":"Carnamah",
    "sg:classifiers":[
        {
            "category":"Government",
            "subcategory":"Department Of Motor Vehicles",
            "type":"Public Place"
        }
    ],
    "sg:phone":"+61 8 9951 7000",
    "sg:postcode":"6517",
    "sg:province":"WA",
    "sg:tags":[
        "organisation",
        "local"
    ],
    "wof:name":"Carnamah Shire Of",
    "wof:placetype":"venue"
},
  "geometry": {"coordinates":[115.88548299999999,-29.688671],"type":"Point"}
}