{
  "type": "Feature",
  "properties": {
    "iso:country":"AU",
    "sg:address":"5 Allambie Crs",
    "sg:city":"Inverell",
    "sg:classifiers":[
        {
            "category":"Professional",
            "subcategory":"Art Services",
            "type":"Services"
        }
    ],
    "sg:phone":"+61 2 6722 2946",
    "sg:postcode":"2360",
    "sg:province":"NSW",
    "sg:tags":[
        "decorator",
        "painter"
    ],
    "wof:name":"McIntyre Athol",
    "wof:placetype":"venue"
},
  "geometry": {"coordinates":[151.113555908,-29.776309967],"type":"Point"}
}