{
  "type": "Feature",
  "properties": {
    "iso:country":"AU",
    "sg:address":"60 John St",
    "sg:city":"Camden",
    "sg:classifiers":[
        {
            "category":"Communications",
            "subcategory":"Film & Video Production",
            "type":"Services"
        }
    ],
    "sg:phone":"+61 2 4655 8140",
    "sg:postcode":"2570",
    "sg:province":"NSW",
    "sg:tags":[
        "fan",
        "blower"
    ],
    "wof:name":"Wandalite Pty. Ltd.",
    "wof:placetype":"venue"
},
  "geometry": {"coordinates":[150.695999145,-34.0546913147],"type":"Point"}
}