{
  "type": "Feature",
  "properties": {
    "addr:full":"Homemaker Centre 825 Zillmere Rd Aspley QLD 4034",
    "addr:housenumber":"825",
    "addr:postcode":"4034",
    "addr:street":"Zillmere Rd",
    "iso:country":"AU",
    "sg:address":"Homemaker Centre 825 Zillmere Rd",
    "sg:city":"Aspley",
    "sg:classifiers":[
        {
            "category":"Retail",
            "subcategory":"Repair Shop",
            "type":"Services"
        }
    ],
    "sg:phone":"+61 7 3863 3899",
    "sg:postcode":"4034",
    "sg:province":"QLD",
    "sg:tags":[
        "maintenance",
        "pool",
        "swimming"
    ],
    "wof:name":"Captain Nemos Pool & Spa Supplies",
    "wof:placetype":"venue"
},
  "geometry": {"coordinates":[153.017517,-27.356058],"type":"Point"}
}