{
  "type": "Feature",
  "properties": {
    "iso:country":"AU",
    "sg:address":"29 Beevers St",
    "sg:city":"Altona North",
    "sg:classifiers":[
        {
            "category":"Recreation",
            "subcategory":"Fishing",
            "type":"Entertainment"
        }
    ],
    "sg:phone":"+61 409 008 441",
    "sg:postcode":"3025",
    "sg:province":"VIC",
    "sg:tags":[
        "trip"
    ],
    "wof:name":"Matthew Hunt Fishing Services",
    "wof:placetype":"venue"
},
  "geometry": {"coordinates":[144.84158300000001,-37.830509],"type":"Point"}
}