{
  "type": "Feature",
  "properties": {
    "addr:full":"Suite 4, 26 Wilmot St Burnie TAS 7320",
    "addr:housenumber":"26",
    "addr:postcode":"7320",
    "addr:street":"Wilmot St",
    "iso:country":"AU",
    "sg:address":"Suite 4, 26 Wilmot St",
    "sg:city":"Burnie",
    "sg:classifiers":[
        {
            "category":"Professional",
            "subcategory":"Management & Consulting",
            "type":"Services"
        }
    ],
    "sg:phone":"+61 3 6432 1008",
    "sg:postcode":"7320",
    "sg:province":"TAS",
    "sg:tags":[
        "consultant"
    ],
    "wof:name":"Moore Consulting",
    "wof:placetype":"venue"
},
  "geometry": {"coordinates":[145.90748600000001,-41.050926],"type":"Point"}
}