{
  "type": "Feature",
  "properties": {
    "iso:country":"AU",
    "sg:address":"11 Barrett St",
    "sg:city":"Albert Park",
    "sg:classifiers":[
        {
            "category":"Home & Garden",
            "subcategory":"Carpets & Floor Coverings",
            "type":"Retail Goods"
        }
    ],
    "sg:phone":"+61 3 9690 2681",
    "sg:postcode":"3206",
    "sg:province":"VIC",
    "wof:name":"C & J Floor Laying Service",
    "wof:placetype":"venue"
},
  "geometry": {"coordinates":[144.948654,-37.843224],"type":"Point"}
}