{
  "type": "Feature",
  "properties": {
    "addr:full":"2-6 Brandon St Sarina QLD 4737",
    "addr:housenumber":"2-6",
    "addr:postcode":"4737",
    "addr:street":"Brandon St",
    "iso:country":"AU",
    "sg:address":"2-6 Brandon St",
    "sg:city":"Sarina",
    "sg:classifiers":[
        {
            "category":"Industrial Area",
            "type":"Public Place"
        }
    ],
    "sg:phone":"+61 7 4943 1844",
    "sg:postcode":"4737",
    "sg:province":"QLD",
    "sg:tags":[
        "rural",
        "shed"
    ],
    "wof:name":"Bosco Engineering Pty Ltd",
    "wof:placetype":"venue"
},
  "geometry": {"coordinates":[149.21653699999999,-21.418409],"type":"Point"}
}