{
  "type": "Feature",
  "properties": {
    "addr:full":"20 Fortune St South Perth WA 6151",
    "addr:housenumber":"20",
    "addr:postcode":"6151",
    "addr:street":"Fortune St South",
    "iso:country":"AU",
    "sg:address":"20 Fortune St",
    "sg:city":"South Perth",
    "sg:classifiers":[
        {
            "category":"Health Services",
            "subcategory":"Doctor",
            "type":"Services"
        }
    ],
    "sg:phone":"+61 8 9368 2333",
    "sg:postcode":"6151",
    "sg:province":"WA",
    "sg:tags":[
        "medical",
        "practitioner"
    ],
    "wof:name":"South Perth Endoscopy",
    "wof:placetype":"venue"
},
  "geometry": {"coordinates":[115.863274,-31.988363],"type":"Point"}
}