{
  "type": "Feature",
  "properties": {
    "iso:country":"AU",
    "sg:address":"Unit 4 81 Smart Rd",
    "sg:city":"Modbury",
    "sg:classifiers":[
        {
            "category":"Health Services",
            "subcategory":"Doctor",
            "type":"Services"
        }
    ],
    "sg:phone":"+61 8 8265 5922",
    "sg:postcode":"5092",
    "sg:province":"SA",
    "sg:tags":[
        "medical",
        "practitioner"
    ],
    "wof:name":"Bain Gregory I Dr",
    "wof:placetype":"venue"
},
  "geometry": {"coordinates":[138.69247436500001,-34.8332977295],"type":"Point"}
}