{
  "type": "Feature",
  "properties": {
    "addr:full":"Pierpoint Rd Pier Marketplace Cairns QLD 4870",
    "addr:postcode":"4870",
    "addr:street":"Pierpoint Rd",
    "iso:country":"AU",
    "sg:address":"Pierpoint Rd Pier Marketplace",
    "sg:city":"Cairns",
    "sg:classifiers":[
        {
            "category":"Shopping",
            "subcategory":"Clothing, Apparel, & Fashions",
            "type":"Retail Goods"
        }
    ],
    "sg:phone":"+61 7 4031 0531",
    "sg:postcode":"4870",
    "sg:province":"QLD",
    "sg:tags":[
        "lady",
        "wear"
    ],
    "wof:name":"Supremacy North",
    "wof:placetype":"venue"
},
  "geometry": {"coordinates":[145.66958618199999,-17.0185699463],"type":"Point"}
}