{
  "type": "Feature",
  "properties": {
    "iso:country":"AU",
    "sg:address":"23 Twenty-Third Ave",
    "sg:city":"Brighton",
    "sg:classifiers":[
        {
            "category":"Professional",
            "subcategory":"Art Services",
            "type":"Services"
        }
    ],
    "sg:phone":"+61 7 3269 9552",
    "sg:postcode":"4017",
    "sg:province":"QLD",
    "sg:tags":[
        "decorator",
        "painter"
    ],
    "wof:name":"Bay M & E Painting Contractors",
    "wof:placetype":"venue"
},
  "geometry": {"coordinates":[153.06088256800001,-27.2882099152],"type":"Point"}
}