{
  "type": "Feature",
  "properties": {
    "addr:full":"Bruce Hwy Koumala QLD 4738",
    "addr:postcode":"4738",
    "addr:street":"Bruce Hwy",
    "iso:country":"AU",
    "sg:address":"Bruce Hwy",
    "sg:city":"Koumala",
    "sg:classifiers":[
        {
            "category":"Farming",
            "subcategory":"Crops",
            "type":"Manufacturing & Wholesale Goods"
        }
    ],
    "sg:phone":"+61 7 4950 3850",
    "sg:postcode":"4738",
    "sg:province":"QLD",
    "sg:tags":[
        "sugarcane",
        "mill",
        "grower"
    ],
    "wof:name":"Borg R J",
    "wof:placetype":"venue"
},
  "geometry": {"coordinates":[149.24295000000001,-21.604092],"type":"Point"}
}