{
  "type": "Feature",
  "properties": {
    "addr:full":"62 Angove St North Perth WA 6006",
    "addr:housenumber":"62",
    "addr:postcode":"6006",
    "addr:street":"Angove St",
    "iso:country":"AU",
    "sg:address":"62 Angove St",
    "sg:city":"North Perth",
    "sg:classifiers":[
        {
            "category":"Professional",
            "subcategory":"Computer Services",
            "type":"Services"
        }
    ],
    "sg:phone":"+61 8 9227 6364",
    "sg:postcode":"6006",
    "sg:province":"WA",
    "sg:tags":[
        "training"
    ],
    "wof:name":"Integrity Business Services & Systems",
    "wof:placetype":"venue"
},
  "geometry": {"coordinates":[115.856887817,-31.92943573],"type":"Point"}
}