{
  "type": "Feature",
  "properties": {
    "iso:country":"AU",
    "sg:address":"8 Harden Rd",
    "sg:city":"Artarmon",
    "sg:classifiers":[
        {
            "category":"Professional",
            "subcategory":"Management & Consulting",
            "type":"Services"
        }
    ],
    "sg:phone":"+61 2 9419 4713",
    "sg:postcode":"2064",
    "sg:province":"NSW",
    "sg:tags":[
        "consultant"
    ],
    "wof:name":"Len Brandon & Assoc Pty Ltd",
    "wof:placetype":"venue"
},
  "geometry": {"coordinates":[151.18867492699999,-33.8081054688],"type":"Point"}
}