{
  "type": "Feature",
  "properties": {
    "iso:country":"AU",
    "sg:address":"23 Goobar St",
    "sg:city":"Narrabri",
    "sg:classifiers":[
        {
            "category":"Food & Beverages",
            "subcategory":"Supermarket",
            "type":"Retail Goods"
        }
    ],
    "sg:phone":"+61 2 6792 1116",
    "sg:postcode":"2390",
    "sg:province":"NSW",
    "sg:tags":[
        "grocery",
        "store"
    ],
    "wof:name":"Bell's Westland Supermarket",
    "wof:placetype":"venue"
},
  "geometry": {"coordinates":[149.753143311,-30.3381385803],"type":"Point"}
}