{
  "type": "Feature",
  "properties": {
    "addr:full":"151 Greville St Prahran VIC 3181",
    "addr:housenumber":"151",
    "addr:postcode":"3181",
    "addr:street":"Greville St",
    "iso:country":"AU",
    "sg:address":"151 Greville St",
    "sg:city":"Prahran",
    "sg:classifiers":[
        {
            "category":"Health Services",
            "subcategory":"Optometrist",
            "type":"Services"
        }
    ],
    "sg:phone":"+61 3 9533 8998",
    "sg:postcode":"3181",
    "sg:province":"VIC",
    "wof:name":"Luna Eyewear",
    "wof:placetype":"venue"
},
  "geometry": {"coordinates":[144.99176025400001,-37.8491783142],"type":"Point"}
}