{
  "type": "Feature",
  "properties": {
    "iso:country":"AU",
    "sg:address":"16 McBride Ave",
    "sg:city":"Wonthaggi",
    "sg:classifiers":[
        {
            "category":"Restaurant",
            "type":"Food & Drink"
        }
    ],
    "sg:phone":"+61 3 5672 1007",
    "sg:postcode":"3995",
    "sg:province":"VIC",
    "wof:name":"The Vineyard Restaurant",
    "wof:placetype":"venue"
},
  "geometry": {"coordinates":[145.590927,-38.605465],"type":"Point"}
}