{
  "type": "Feature",
  "properties": {
    "iso:country":"AU",
    "sg:address":"250 Ross River Rd",
    "sg:city":"Aitkenvale",
    "sg:classifiers":[
        {
            "category":"Professional",
            "subcategory":"Accounting & Tax Preparation",
            "type":"Services"
        }
    ],
    "sg:phone":"+61 7 4729 2222",
    "sg:postcode":"4814",
    "sg:province":"QLD",
    "sg:tags":[
        "accountant",
        "auditor"
    ],
    "wof:name":"Kerrisk John T",
    "wof:placetype":"venue"
},
  "geometry": {"coordinates":[146.769943,-19.296625],"type":"Point"}
}