{
  "type": "Feature",
  "properties": {
    "iso:country":"AU",
    "sg:address":"1/ 51 Jersey Rd",
    "sg:city":"Bayswater",
    "sg:classifiers":[
        {
            "category":"Manufacturing",
            "subcategory":"Rubber & Plastics",
            "type":"Manufacturing & Wholesale Goods"
        }
    ],
    "sg:phone":"+61 1800 338 903",
    "sg:postcode":"3153",
    "sg:province":"VIC",
    "sg:tags":[
        "equipment",
        "card"
    ],
    "wof:name":"Placard",
    "wof:placetype":"venue"
},
  "geometry": {"coordinates":[145.27903747600001,-37.8448677063],"type":"Point"}
}