{
  "type": "Feature",
  "properties": {
    "addr:full":"38 Bridge St Lismore NSW 2480",
    "addr:housenumber":"38",
    "addr:postcode":"2480",
    "addr:street":"Bridge St",
    "iso:country":"AU",
    "sg:address":"38 Bridge St",
    "sg:city":"Lismore",
    "sg:classifiers":[
        {
            "category":"Industrial Area",
            "type":"Public Place"
        }
    ],
    "sg:phone":"+61 2 6622 4686",
    "sg:postcode":"2480",
    "sg:province":"NSW",
    "sg:tags":[
        "protective",
        "clothing"
    ],
    "wof:name":"Aussie Digger Camping & Workwear",
    "wof:placetype":"venue"
},
  "geometry": {"coordinates":[153.275390625,-28.8037242889],"type":"Point"}
}