{
  "type": "Feature",
  "properties": {
    "iso:country":"AU",
    "sg:address":"PO Box 1573",
    "sg:city":"Double Bay",
    "sg:classifiers":[
        {
            "category":"Building & Trades",
            "subcategory":"Construction",
            "type":"Services"
        }
    ],
    "sg:phone":"+61 408 471 477",
    "sg:postcode":"1360",
    "sg:province":"NSW",
    "sg:tags":[
        "contractor"
    ],
    "wof:name":"Architectural Elements",
    "wof:placetype":"venue"
},
  "geometry": {"coordinates":[151.24476623499999,-33.8771896362],"type":"Point"}
}