{
  "type": "Feature",
  "properties": {
    "addr:full":"Suites 3-4/ 271 Brunker Rd Adamstown NSW 2289",
    "addr:housenumber":"3-4 / 271",
    "addr:postcode":"2289",
    "addr:street":"Brunker Rd",
    "iso:country":"AU",
    "sg:address":"Suites 3-4/ 271 Brunker Rd",
    "sg:city":"Adamstown",
    "sg:classifiers":[
        {
            "category":"Banks & Credit Unions",
            "subcategory":"Financial Services",
            "type":"Services"
        }
    ],
    "sg:phone":"+61 1300 885 046",
    "sg:postcode":"2289",
    "sg:province":"NSW",
    "sg:tags":[
        "planning"
    ],
    "wof:name":"Infocus Money Management",
    "wof:placetype":"venue"
},
  "geometry": {"coordinates":[151.725830078,-32.9352302551],"type":"Point"}
}