{
  "type": "Feature",
  "properties": {
    "iso:country":"AU",
    "sg:address":"394 Mortimer Rd",
    "sg:city":"Wellard",
    "sg:classifiers":[
        {
            "category":"Shopping",
            "subcategory":"Stationery & Office Supplies",
            "type":"Retail Goods"
        }
    ],
    "sg:phone":"+61 8 9439 2929",
    "sg:postcode":"6170",
    "sg:province":"WA",
    "sg:tags":[
        "equipment",
        "badge",
        "making"
    ],
    "wof:name":"Quibid Systems",
    "wof:placetype":"venue"
},
  "geometry": {"coordinates":[115.88561199999999,-32.255386],"type":"Point"}
}