{
  "type": "Feature",
  "properties": {
    "addr:full":"Ste 3, 1st Flr 182 Victoria Pde East Melbourne VIC 3002",
    "addr:housenumber":"182",
    "addr:postcode":"3002",
    "addr:street":"Victoria Pde",
    "iso:country":"AU",
    "sg:address":"Ste 3, 1st Flr 182 Victoria Pde",
    "sg:city":"East Melbourne",
    "sg:classifiers":[
        {
            "category":"Health Services",
            "subcategory":"Doctor",
            "type":"Services"
        }
    ],
    "sg:phone":"+61 3 9663 2199",
    "sg:postcode":"3002",
    "sg:province":"VIC",
    "sg:tags":[
        "medical",
        "practitioner"
    ],
    "wof:name":"Siemensma Dr Nicholas",
    "wof:placetype":"venue"
},
  "geometry": {"coordinates":[144.99140930199999,-37.8135986328],"type":"Point"}
}