{
  "type": "Feature",
  "properties": {
    "addr:full":"29 Bromley Rd Emu Plains NSW 2750",
    "addr:housenumber":"29",
    "addr:postcode":"2750",
    "addr:street":"Bromley Rd",
    "iso:country":"AU",
    "sg:address":"29 Bromley Rd",
    "sg:city":"Emu Plains",
    "sg:classifiers":[
        {
            "category":"Structure",
            "subcategory":"Tunnel",
            "type":"Public Place"
        }
    ],
    "sg:phone":"+61 2 4735 7112",
    "sg:postcode":"2750",
    "sg:province":"NSW",
    "sg:tags":[
        "cleaner",
        "industrial",
        "vacuum"
    ],
    "wof:name":"Dust Collector Rentals",
    "wof:placetype":"venue"
},
  "geometry": {"coordinates":[150.65049743599999,-33.7440910339],"type":"Point"}
}