{
  "type": "Feature",
  "properties": {
    "addr:full":"4 Mount View St Croydon VIC 3136",
    "addr:housenumber":"4",
    "addr:postcode":"3136",
    "addr:street":"Mount View St",
    "iso:country":"AU",
    "sg:address":"4 Mount View St",
    "sg:city":"Croydon",
    "sg:classifiers":[
        {
            "category":"Personal",
            "type":"Services"
        }
    ],
    "sg:phone":"+61 3 9723 2206",
    "sg:postcode":"3136",
    "sg:province":"VIC",
    "sg:tags":[
        "counselling",
        "alcohol",
        "drug"
    ],
    "wof:name":"Mountview Corner House",
    "wof:placetype":"venue"
},
  "geometry": {"coordinates":[145.28041076700001,-37.7987098694],"type":"Point"}
}