{
  "type": "Feature",
  "properties": {
    "addr:full":"131 Currie St Nambour QLD 4560",
    "addr:housenumber":"131",
    "addr:postcode":"4560",
    "addr:street":"Currie St",
    "iso:country":"AU",
    "sg:address":"131 Currie St",
    "sg:city":"Nambour",
    "sg:classifiers":[
        {
            "category":"Arts & Performance",
            "subcategory":"Dance",
            "type":"Entertainment"
        }
    ],
    "sg:phone":"+61 7 5441 1324",
    "sg:postcode":"4560",
    "sg:province":"QLD",
    "sg:tags":[
        "theatrical",
        "ballet",
        "tuition"
    ],
    "wof:name":"Sunshine Coast Academy Of Dance Arts",
    "wof:placetype":"venue"
},
  "geometry": {"coordinates":[152.959472656,-26.6274909973],"type":"Point"}
}