{
  "type": "Feature",
  "properties": {
    "addr:full":"57 Murray St Perth WA 6000",
    "addr:housenumber":"57",
    "addr:postcode":"6000",
    "addr:street":"Murray St",
    "iso:country":"AU",
    "sg:address":"57 Murray St",
    "sg:city":"Perth",
    "sg:classifiers":[
        {
            "category":"Government",
            "subcategory":"Court House",
            "type":"Public Place"
        }
    ],
    "sg:phone":"+61 8 9261 4444",
    "sg:postcode":"6000",
    "sg:province":"WA",
    "sg:tags":[
        "personal",
        "marriage",
        "family",
        "counselling"
    ],
    "wof:name":"Lifeline WA",
    "wof:placetype":"venue"
},
  "geometry": {"coordinates":[115.854736328,-31.9516601562],"type":"Point"}
}