{
  "type": "Feature",
  "properties": {
    "iso:country":"AU",
    "sg:address":"1/ 45 Toupein Rd",
    "sg:city":"Yarrawonga",
    "sg:classifiers":[
        {
            "category":"Shopping",
            "subcategory":"Bicycles & Sporting Goods",
            "type":"Retail Goods"
        }
    ],
    "sg:phone":"+61 8 8931 0041",
    "sg:postcode":"0830",
    "sg:province":"NT",
    "sg:tags":[
        "chemical",
        "equipment",
        "pool",
        "swimming"
    ],
    "wof:name":"Calipso Pools & Spas",
    "wof:placetype":"venue"
},
  "geometry": {"coordinates":[130.991684,-12.474509],"type":"Point"}
}