{
  "type": "Feature",
  "properties": {
    "addr:full":"Kay House Ground Floor Suite 2 35 Scarborough St Southport QLD 4215",
    "addr:housenumber":"35",
    "addr:postcode":"4215",
    "addr:street":"Scarborough St",
    "iso:country":"AU",
    "sg:address":"Kay House Ground Floor Suite 2 35 Scarborough St",
    "sg:city":"Southport",
    "sg:classifiers":[
        {
            "category":"Health Services",
            "subcategory":"Dentist",
            "type":"Services"
        }
    ],
    "sg:phone":"+61 7 5531 4858",
    "sg:postcode":"4215",
    "sg:province":"QLD",
    "wof:name":"Swagell William R.",
    "wof:placetype":"venue"
},
  "geometry": {"coordinates":[153.41537475600001,-27.9710445404],"type":"Point"}
}