{
  "type": "Feature",
  "properties": {
    "addr:full":"87 Planthurst Rd Carlton NSW 2218",
    "addr:housenumber":"87",
    "addr:postcode":"2218",
    "addr:street":"Planthurst Rd",
    "iso:country":"AU",
    "sg:address":"87 Planthurst Rd",
    "sg:city":"Carlton",
    "sg:classifiers":[
        {
            "category":"Retail",
            "subcategory":"Auto Repair",
            "type":"Services"
        }
    ],
    "sg:phone":"+61 2 9546 5115",
    "sg:postcode":"2218",
    "sg:province":"NSW",
    "sg:tags":[
        "repairer",
        "motor",
        "engineer"
    ],
    "wof:name":"Sam Toscano & Son Automotive Repairs",
    "wof:placetype":"venue"
},
  "geometry": {"coordinates":[151.11538696299999,-33.9796791077],"type":"Point"}
}