{
  "type": "Feature",
  "properties": {
    "addr:full":"204 High St Ashburton VIC 3147",
    "addr:housenumber":"204",
    "addr:postcode":"3147",
    "addr:street":"High St",
    "iso:country":"AU",
    "sg:address":"204 High St",
    "sg:city":"Ashburton",
    "sg:classifiers":[
        {
            "category":"Cafe",
            "type":"Food & Drink"
        }
    ],
    "sg:phone":"+61 3 9885 8164",
    "sg:postcode":"3147",
    "sg:province":"VIC",
    "wof:name":"E&#039;Latte Cafe",
    "wof:placetype":"venue"
},
  "geometry": {"coordinates":[145.07896423299999,-37.8634490967],"type":"Point"}
}