{
  "type": "Feature",
  "properties": {
    "addr:full":"9 Ruby Crs Willowbank QLD 4306",
    "addr:housenumber":"9",
    "addr:postcode":"4306",
    "addr:street":"Ruby Crs",
    "iso:country":"AU",
    "sg:address":"9 Ruby Crs",
    "sg:city":"Willowbank",
    "sg:classifiers":[
        {
            "category":"Home & Garden",
            "subcategory":"Building Materials",
            "type":"Retail Goods"
        }
    ],
    "sg:phone":"+61 7 5467 3286",
    "sg:postcode":"4306",
    "sg:province":"QLD",
    "sg:tags":[
        "concrete",
        "gutter",
        "kerb"
    ],
    "sg:website":"http://www.brisbanekerbing.com",
    "wof:name":"Brisbane Kerbing Service",
    "wof:placetype":"venue"
},
  "geometry": {"coordinates":[152.69374084500001,-27.6609802246],"type":"Point"}
}