{
  "type": "Feature",
  "properties": {
    "addr:full":"316 Cnr Pascoe Vale & Cameron Rd Essendon VIC 3040",
    "addr:housenumber":"316",
    "addr:postcode":"3040",
    "addr:street":"Cnr Pascoe;Rd",
    "iso:country":"AU",
    "sg:address":"316 Cnr Pascoe Vale & Cameron Rd",
    "sg:city":"Essendon",
    "sg:classifiers":[
        {
            "category":"Restaurant",
            "type":"Food & Drink"
        }
    ],
    "sg:phone":"+61 3 9379 8177",
    "sg:postcode":"3040",
    "sg:province":"VIC",
    "sg:tags":[
        "roadhouse"
    ],
    "wof:name":"Xpress Food&#039;N&#039;Fuel",
    "wof:placetype":"venue"
},
  "geometry": {"coordinates":[144.92530822800001,-37.751159668],"type":"Point"}
}