{
  "type": "Feature",
  "properties": {
    "iso:country":"AU",
    "sg:address":"Shop 8, Ctr Court Arcade, 32-34 Musgrave St",
    "sg:city":"Kirra",
    "sg:classifiers":[
        {
            "category":"Health Services",
            "subcategory":"Doctor",
            "type":"Services"
        }
    ],
    "sg:phone":"+61 7 5536 1911",
    "sg:postcode":"4225",
    "sg:province":"QLD",
    "sg:tags":[
        "medical",
        "practitioner"
    ],
    "wof:name":"Singh Dr",
    "wof:placetype":"venue"
},
  "geometry": {"coordinates":[153.526809692,-28.1673812866],"type":"Point"}
}