{
  "type": "Feature",
  "properties": {
    "iso:country":"AU",
    "sg:address":"89 Spooners Ave",
    "sg:city":"Kempsey West",
    "sg:classifiers":[
        {
            "category":"Shopping",
            "subcategory":"Crafts & Fabrics",
            "type":"Retail Goods"
        }
    ],
    "sg:phone":"+61 2 6562 8899",
    "sg:postcode":"2440",
    "sg:province":"NSW",
    "sg:tags":[
        "supply"
    ],
    "wof:name":"Kath's Kreations Unique Beads & Jewellery",
    "wof:placetype":"venue"
},
  "geometry": {"coordinates":[152.825424,-31.014236],"type":"Point"}
}