{
  "type": "Feature",
  "properties": {
    "addr:full":"Shp201/ 65 Albert Ave Chatswood NSW 2067",
    "addr:housenumber":"65",
    "addr:postcode":"2067",
    "addr:street":"Albert Ave",
    "iso:country":"AU",
    "sg:address":"Shp201/ 65 Albert Ave",
    "sg:city":"Chatswood",
    "sg:classifiers":[
        {
            "category":"Fast Food",
            "type":"Food & Drink"
        }
    ],
    "sg:phone":"+61 2 9410 2545",
    "sg:postcode":"2067",
    "sg:province":"NSW",
    "sg:tags":[
        "away",
        "take"
    ],
    "wof:name":"Just Food",
    "wof:placetype":"venue"
},
  "geometry": {"coordinates":[151.187057495,-33.7966308594],"type":"Point"}
}