{
  "type": "Feature",
  "properties": {
    "addr:full":"23 Nelson St Moorabbin VIC 3189",
    "addr:housenumber":"23",
    "addr:postcode":"3189",
    "addr:street":"Nelson St",
    "iso:country":"AU",
    "sg:address":"23 Nelson St",
    "sg:city":"Moorabbin",
    "sg:classifiers":[
        {
            "category":"Utilities",
            "type":"Services"
        }
    ],
    "sg:phone":"+61 3 9555 5981",
    "sg:postcode":"3189",
    "sg:province":"VIC",
    "sg:tags":[
        "refrigeration",
        "industrial",
        "commercial",
        "retail"
    ],
    "wof:name":"Woods C & V",
    "wof:placetype":"venue"
},
  "geometry": {"coordinates":[145.07081604000001,-37.9445953369],"type":"Point"}
}