{
  "type": "Feature",
  "properties": {
    "addr:full":"56 Glenorchy St Glenorchy TAS 7010",
    "addr:housenumber":"56",
    "addr:postcode":"7010",
    "addr:street":"Glenorchy St",
    "iso:country":"AU",
    "sg:address":"56 Glenorchy St",
    "sg:city":"Glenorchy",
    "sg:classifiers":[
        {
            "category":"Communications",
            "subcategory":"Film & Video Production",
            "type":"Services"
        }
    ],
    "sg:phone":"+61 438 721 918",
    "sg:postcode":"7010",
    "sg:province":"TAS",
    "sg:tags":[
        "dvd",
        "library"
    ],
    "wof:name":"Home Entertainment Express",
    "wof:placetype":"venue"
},
  "geometry": {"coordinates":[147.279754639,-42.8336982727],"type":"Point"}
}