{
  "type": "Feature",
  "properties": {
    "iso:country":"AU",
    "sg:address":"Casuarina School Cnr Garfield Rd & Piccadily St",
    "sg:city":"Riverstone",
    "sg:classifiers":[
        {
            "category":"Education",
            "subcategory":"Music School",
            "type":"Public Place"
        }
    ],
    "sg:phone":"+61 2 9627 7196",
    "sg:postcode":"2765",
    "sg:province":"NSW",
    "sg:tags":[
        "teacher"
    ],
    "wof:name":"International School Of Music",
    "wof:placetype":"venue"
},
  "geometry": {"coordinates":[150.86323547399999,-33.6785087585],"type":"Point"}
}