{
  "type": "Feature",
  "properties": {
    "addr:full":"38 - 40 Barkly Hwy Mt Isa QLD 4825",
    "addr:housenumber":"40",
    "addr:postcode":"4825",
    "addr:street":"Barkly Hwy",
    "iso:country":"AU",
    "sg:address":"38 - 40 Barkly Hwy",
    "sg:city":"Mt Isa",
    "sg:classifiers":[
        {
            "category":"Autos & Motor Vehicles",
            "subcategory":"Auto Supplies",
            "type":"Retail Goods"
        }
    ],
    "sg:phone":"+61 7 4743 6633",
    "sg:postcode":"4825",
    "sg:province":"QLD",
    "sg:tags":[
        "battery",
        "automotive"
    ],
    "wof:name":"Beaurepaires",
    "wof:placetype":"venue"
},
  "geometry": {"coordinates":[139.486008,-20.720865],"type":"Point"}
}