{
  "type": "Feature",
  "properties": {
    "addr:full":"26 Warrawolong St Wyee NSW 2259",
    "addr:housenumber":"26",
    "addr:postcode":"2259",
    "addr:street":"Warrawolong St",
    "iso:country":"AU",
    "sg:address":"26 Warrawolong St",
    "sg:city":"Wyee",
    "sg:classifiers":[
        {
            "category":"Communications",
            "type":"Services"
        }
    ],
    "sg:phone":"+61 2 4392 0688",
    "sg:postcode":"2259",
    "sg:province":"NSW",
    "sg:tags":[
        "equipment",
        "satellite"
    ],
    "wof:name":"Lakes Antenna Services",
    "wof:placetype":"venue"
},
  "geometry": {"coordinates":[151.489746094,-33.1745681763],"type":"Point"}
}