{
  "type": "Feature",
  "properties": {
    "addr:full":"3/ 7 Simcock St Somerville VIC 3912",
    "addr:housenumber":"/ 7",
    "addr:postcode":"3912",
    "addr:street":"Simcock St",
    "iso:country":"AU",
    "sg:address":"3/ 7 Simcock St",
    "sg:city":"Somerville",
    "sg:classifiers":[
        {
            "category":"Retail",
            "subcategory":"Auto Repair",
            "type":"Services"
        }
    ],
    "sg:phone":"+61 3 5977 8411",
    "sg:postcode":"3912",
    "sg:province":"VIC",
    "sg:tags":[
        "wheel",
        "balancing",
        "alignment"
    ],
    "wof:name":"Bridgestone Tyre Centres",
    "wof:placetype":"venue"
},
  "geometry": {"coordinates":[145.17791748100001,-38.221446991],"type":"Point"}
}