{
  "type": "Feature",
  "properties": {
    "addr:full":"8- 10 Hudson St Hamilton NSW 2303",
    "addr:housenumber":"10",
    "addr:postcode":"2303",
    "addr:street":"8;Hudson St",
    "iso:country":"AU",
    "sg:address":"8- 10 Hudson St",
    "sg:city":"Hamilton",
    "sg:classifiers":[
        {
            "category":"Banks & Credit Unions",
            "subcategory":"Investment Brokerage",
            "type":"Services"
        }
    ],
    "sg:phone":"+61 415 683 563",
    "sg:postcode":"2303",
    "sg:province":"NSW",
    "sg:tags":[
        "finance",
        "broker"
    ],
    "wof:name":"Ennis Garry",
    "wof:placetype":"venue"
},
  "geometry": {"coordinates":[151.74728400000001,-32.918427],"type":"Point"}
}