{
  "type": "Feature",
  "properties": {
    "iso:country":"AU",
    "sg:address":"19 Whyalla St",
    "sg:city":"Willetton",
    "sg:classifiers":[
        {
            "category":"Retail",
            "subcategory":"Repair Shop",
            "type":"Services"
        }
    ],
    "sg:phone":"+61 8 9457 5033",
    "sg:postcode":"6155",
    "sg:province":"WA",
    "sg:tags":[
        "maintenance",
        "pool",
        "swimming"
    ],
    "wof:name":"Shenton Pool Equipment",
    "wof:placetype":"venue"
},
  "geometry": {"coordinates":[115.88304100000001,-32.042343],"type":"Point"}
}