{
  "type": "Feature",
  "properties": {
    "addr:full":"21 McCulloch Ave Margate QLD 4019",
    "addr:housenumber":"21",
    "addr:postcode":"4019",
    "addr:street":"Mcculloch Ave",
    "iso:country":"AU",
    "sg:address":"21 McCulloch Ave",
    "sg:city":"Margate",
    "sg:classifiers":[
        {
            "category":"Building & Trades",
            "subcategory":"Plumbing",
            "type":"Services"
        }
    ],
    "sg:phone":"+61 413 878 053",
    "sg:postcode":"4019",
    "sg:province":"QLD",
    "sg:tags":[
        "plumber",
        "gasfitters"
    ],
    "wof:name":"Ross Urquhart Plumbing",
    "wof:placetype":"venue"
},
  "geometry": {"coordinates":[153.11085510300001,-27.2408409119],"type":"Point"}
}