{
  "type": "Feature",
  "properties": {
    "addr:full":"1 Alpine Crs Grindelwald TAS 7277",
    "addr:housenumber":"1",
    "addr:postcode":"7277",
    "addr:street":"Alpine Crs",
    "iso:country":"AU",
    "sg:address":"1 Alpine Crs",
    "sg:city":"Grindelwald",
    "sg:classifiers":[
        {
            "category":"Banks & Credit Unions",
            "subcategory":"Financial Services",
            "type":"Services"
        }
    ],
    "sg:phone":"+61 3 6330 2510",
    "sg:postcode":"7277",
    "sg:province":"TAS",
    "sg:tags":[
        "annuity",
        "rollover",
        "superannuation",
        "consultant"
    ],
    "wof:name":"bejahfinancial.com.au",
    "wof:placetype":"venue"
},
  "geometry": {"coordinates":[147.00125122099999,-41.3507194519],"type":"Point"}
}