{
  "type": "Feature",
  "properties": {
    "addr:full":"Suite 6, Level 1, Green House 173 Wickham Tce Spring Hill QLD 4000",
    "addr:housenumber":"173",
    "addr:postcode":"4000",
    "addr:street":"Wickham Tce",
    "iso:country":"AU",
    "sg:address":"Suite 6, Level 1, Green House 173",
    "sg:city":"Wickham Tce Spring Hill",
    "sg:classifiers":[
        {
            "category":"Banks & Credit Unions",
            "subcategory":"Financial Services",
            "type":"Services"
        }
    ],
    "sg:phone":"+61 7 3839 2427",
    "sg:postcode":"4000",
    "sg:province":"QLD",
    "sg:tags":[
        "planning"
    ],
    "wof:name":"Financial Planning Association Of Australia Ltd",
    "wof:placetype":"venue"
},
  "geometry": {"coordinates":[153.02438354500001,-27.4649887085],"type":"Point"}
}