{
  "type": "Feature",
  "properties": {
    "addr:full":"465 Elgar Rd Box Hill VIC 3128",
    "addr:housenumber":"465",
    "addr:postcode":"3128",
    "addr:street":"Elgar Rd",
    "iso:country":"AU",
    "sg:address":"465 Elgar Rd",
    "sg:city":"Box Hill",
    "sg:classifiers":[
        {
            "category":"Education",
            "subcategory":"Special Training",
            "type":"Public Place"
        }
    ],
    "sg:phone":"+61 3 9286 9490",
    "sg:postcode":"3128",
    "sg:province":"VIC",
    "sg:tags":[
        "college",
        "hairdressing"
    ],
    "wof:name":"Box Hill Institute of TAFE",
    "wof:placetype":"venue"
},
  "geometry": {"coordinates":[145.11502075199999,-37.8159332275],"type":"Point"}
}