{
  "type": "Feature",
  "properties": {
    "addr:full":"54a, Forest Lake Shopng Vlge, 235 Forest Lake Blvd Forest Lake QLD 4078",
    "addr:housenumber":"54a;235",
    "addr:postcode":"4078",
    "addr:street":"Forest;Forest Lake Blvd",
    "iso:country":"AU",
    "sg:address":"54a, Forest Lake Shopng Vlge, 235",
    "sg:city":"Forest Lake Blvd Forest Lake",
    "sg:classifiers":[
        {
            "category":"Banks & Credit Unions",
            "subcategory":"Financial Services",
            "type":"Services"
        }
    ],
    "sg:phone":"+61 7 3879 6911",
    "sg:postcode":"4078",
    "sg:province":"QLD",
    "sg:tags":[
        "loan",
        "finance",
        "mortgage"
    ],
    "wof:name":"Wizard",
    "wof:placetype":"venue"
},
  "geometry": {"coordinates":[152.96864318900001,-27.6256027222],"type":"Point"}
}