{
  "type": "Feature",
  "properties": {
    "iso:country":"AU",
    "sg:address":"Shop G103 Westfield Shopping Centre",
    "sg:city":"Doncaster",
    "sg:classifiers":[
        {
            "category":"Shopping",
            "subcategory":"Jewelry",
            "type":"Retail Goods"
        }
    ],
    "sg:phone":"+61 3 9840 2466",
    "sg:postcode":"3108",
    "sg:province":"VIC",
    "sg:tags":[
        "jeweller"
    ],
    "wof:name":"Salera's Jewellmasters",
    "wof:placetype":"venue"
},
  "geometry": {"coordinates":[145.127487183,-37.7825164795],"type":"Point"}
}