{
  "type": "Feature",
  "properties": {
    "addr:full":"41 Caloundra Rd Caloundra QLD 4551",
    "addr:housenumber":"41",
    "addr:postcode":"4551",
    "addr:street":"Caloundra Rd",
    "iso:country":"AU",
    "sg:address":"41 Caloundra Rd",
    "sg:city":"Caloundra",
    "sg:classifiers":[
        {
            "category":"Home & Garden",
            "subcategory":"Carpets & Floor Coverings",
            "type":"Retail Goods"
        }
    ],
    "sg:phone":"+61 7 5492 7277",
    "sg:postcode":"4551",
    "sg:province":"QLD",
    "wof:name":"Andersens",
    "wof:placetype":"venue"
},
  "geometry": {"coordinates":[153.10997009299999,-26.7958641052],"type":"Point"}
}