{
  "type": "Feature",
  "properties": {
    "addr:full":"PO Box 216 Kilsyth VIC 3137",
    "addr:postcode":"3137",
    "iso:country":"AU",
    "sg:address":"PO Box 216",
    "sg:city":"Kilsyth",
    "sg:classifiers":[
        {
            "category":"Utilities",
            "subcategory":"Telephone",
            "type":"Services"
        }
    ],
    "sg:phone":"+61 401 709 333",
    "sg:postcode":"3137",
    "sg:province":"VIC",
    "sg:tags":[
        "installation",
        "system",
        "maintenance"
    ],
    "wof:name":"New Wave Cable Guy",
    "wof:placetype":"venue"
},
  "geometry": {"coordinates":[145.31497192399999,-37.8026504517],"type":"Point"}
}