{
  "type": "Feature",
  "properties": {
    "addr:full":"Lvl1/ 424 St Kilda Rd Melbourne VIC 3000",
    "addr:housenumber":"424",
    "addr:postcode":"3000",
    "addr:street":"St Kilda Rd",
    "iso:country":"AU",
    "sg:address":"Lvl1/ 424 St Kilda Rd",
    "sg:city":"Melbourne",
    "sg:classifiers":[
        {
            "category":"Education",
            "subcategory":"Special Training",
            "type":"Public Place"
        }
    ],
    "sg:phone":"+61 3 9866 7737",
    "sg:postcode":"3000",
    "sg:province":"VIC",
    "sg:tags":[
        "development"
    ],
    "wof:name":"Britannia It Solutions Pty Ltd",
    "wof:placetype":"venue"
},
  "geometry": {"coordinates":[144.97528076200001,-37.8365516663],"type":"Point"}
}