{
  "type": "Feature",
  "properties": {
    "addr:full":"119 Borella Rd Albury NSW 2640",
    "addr:housenumber":"119",
    "addr:postcode":"2640",
    "addr:street":"Borella Rd",
    "iso:country":"AU",
    "sg:address":"119 Borella Rd",
    "sg:city":"Albury",
    "sg:classifiers":[
        {
            "category":"Building & Trades",
            "subcategory":"Construction",
            "type":"Services"
        }
    ],
    "sg:phone":"+61 13 15 79",
    "sg:postcode":"2640",
    "sg:province":"NSW",
    "sg:tags":[
        "brick",
        "paving"
    ],
    "wof:name":"CSR PGH (Bricks & Pavers)",
    "wof:placetype":"venue"
},
  "geometry": {"coordinates":[146.92874145499999,-36.0765075684],"type":"Point"}
}