{
  "type": "Feature",
  "properties": {
    "addr:full":"7 Grose St Leura NSW 2780",
    "addr:housenumber":"7",
    "addr:postcode":"2780",
    "addr:street":"Grose St",
    "iso:country":"AU",
    "sg:address":"7 Grose St",
    "sg:city":"Leura",
    "sg:classifiers":[
        {
            "category":"Health Services",
            "subcategory":"Chiropractor",
            "type":"Services"
        }
    ],
    "sg:phone":"+61 2 4784 3991",
    "sg:postcode":"2780",
    "sg:province":"NSW",
    "wof:name":"Swift Antonia",
    "wof:placetype":"venue"
},
  "geometry": {"coordinates":[150.33299255399999,-33.7127876282],"type":"Point"}
}