{
  "type": "Feature",
  "properties": {
    "addr:full":"Unit 21, 84 Reserve Rd Artarmon NSW 2064",
    "addr:housenumber":"84",
    "addr:postcode":"2064",
    "addr:street":"Reserve Rd",
    "iso:country":"AU",
    "sg:address":"Unit 21, 84 Reserve Rd",
    "sg:city":"Artarmon",
    "sg:classifiers":[
        {
            "category":"Professional",
            "subcategory":"Computer Services",
            "type":"Services"
        }
    ],
    "sg:phone":"+61 2 9439 1833",
    "sg:postcode":"2064",
    "sg:province":"NSW",
    "sg:tags":[
        "equipment",
        "networking",
        "installation"
    ],
    "wof:name":"A.P.E. (Protective Electronics)",
    "wof:placetype":"venue"
},
  "geometry": {"coordinates":[151.18760681099999,-33.8171081543],"type":"Point"}
}