{
  "type": "Feature",
  "properties": {
    "iso:country":"AU",
    "sg:address":"224a Cameron St",
    "sg:city":"Wauchope",
    "sg:classifiers":[
        {
            "category":"Wholesale",
            "subcategory":"Machinery & Supplies",
            "type":"Manufacturing & Wholesale Goods"
        }
    ],
    "sg:phone":"+61 2 6585 1859",
    "sg:postcode":"2446",
    "sg:province":"NSW",
    "sg:tags":[
        "agricultural"
    ],
    "wof:name":"Harman Don",
    "wof:placetype":"venue"
},
  "geometry": {"coordinates":[152.73057600000001,-31.476067],"type":"Point"}
}