{
  "type": "Feature",
  "properties": {
    "iso:country":"AU",
    "sg:address":"Unit 4, 24 Daniel St",
    "sg:city":"Wetherill Park",
    "sg:classifiers":[
        {
            "category":"Shopping",
            "subcategory":"Clothing, Apparel, & Fashions",
            "type":"Retail Goods"
        }
    ],
    "sg:phone":"+61 2 9757 3055",
    "sg:postcode":"2164",
    "sg:province":"NSW",
    "sg:tags":[
        "wholesaler",
        "children's",
        "mfrs",
        "wear"
    ],
    "wof:name":"Frank Sarpi Agencies",
    "wof:placetype":"venue"
},
  "geometry": {"coordinates":[150.90472412099999,-33.8487052917],"type":"Point"}
}