{
  "type": "Feature",
  "properties": {
    "addr:full":"5/ 24 Richmond Ave Fairbairn ACT 2609",
    "addr:housenumber":"/ 24",
    "addr:postcode":"2609",
    "addr:street":"Richmond Ave",
    "iso:country":"AU",
    "sg:address":"5/ 24 Richmond Ave",
    "sg:city":"Fairbairn",
    "sg:classifiers":[
        {
            "category":"Professional",
            "subcategory":"Detective & Security Services",
            "type":"Services"
        }
    ],
    "sg:phone":"+61 2 6212 3200",
    "sg:postcode":"2609",
    "sg:province":"ACT",
    "sg:tags":[
        "guard",
        "patrol"
    ],
    "wof:name":"ISS Security Pty Ltd",
    "wof:placetype":"venue"
},
  "geometry": {"coordinates":[149.179443359,-35.298625946],"type":"Point"}
}