{
  "type": "Feature",
  "properties": {
    "iso:country":"AU",
    "sg:address":"327 George St",
    "sg:city":"Deniliquin",
    "sg:classifiers":[
        {
            "category":"Food & Beverages",
            "subcategory":"Bakery",
            "type":"Retail Goods"
        }
    ],
    "sg:phone":"+61 3 5881 3499",
    "sg:postcode":"2710",
    "sg:province":"NSW",
    "sg:tags":[
        "baker"
    ],
    "wof:name":"Josh's Bakehouse",
    "wof:placetype":"venue"
},
  "geometry": {"coordinates":[144.96284484899999,-35.5265846252],"type":"Point"}
}