{
  "type": "Feature",
  "properties": {
    "addr:full":"43/ 5 Ponderosa Pde Warriewood NSW 2102",
    "addr:housenumber":"43 / 5",
    "addr:postcode":"2102",
    "addr:street":"Ponderosa Pde",
    "iso:country":"AU",
    "sg:address":"43/ 5 Ponderosa Pde",
    "sg:city":"Warriewood",
    "sg:classifiers":[
        {
            "category":"Utilities",
            "subcategory":"Natural Gas",
            "type":"Services"
        }
    ],
    "sg:phone":"+61 2 9979 9677",
    "sg:postcode":"2102",
    "sg:province":"NSW",
    "sg:tags":[
        "magnetic",
        "therapy"
    ],
    "wof:name":"Maglab Magnets",
    "wof:placetype":"venue"
},
  "geometry": {"coordinates":[151.28829999999999,-33.680737],"type":"Point"}
}