{
  "type": "Feature",
  "properties": {
    "iso:country":"AU",
    "sg:address":"828 Old Cleveland Rd",
    "sg:city":"Carina",
    "sg:classifiers":[
        {
            "category":"Food & Beverages",
            "subcategory":"Supermarket",
            "type":"Retail Goods"
        }
    ],
    "sg:phone":"+61 7 3398 5554",
    "sg:postcode":"4152",
    "sg:province":"QLD",
    "sg:tags":[
        "grocery",
        "store"
    ],
    "wof:name":"727 Stores",
    "wof:placetype":"venue"
},
  "geometry": {"coordinates":[153.09141540499999,-27.4951648712],"type":"Point"}
}