{
  "type": "Feature",
  "properties": {
    "addr:full":"69 Main St Monbulk VIC 3793",
    "addr:housenumber":"69",
    "addr:postcode":"3793",
    "addr:street":"Main St",
    "iso:country":"AU",
    "sg:address":"69 Main St",
    "sg:city":"Monbulk",
    "sg:classifiers":[
        {
            "category":"Health Services",
            "subcategory":"Optometrist",
            "type":"Services"
        }
    ],
    "sg:phone":"+61 3 9756 6626",
    "sg:postcode":"3793",
    "sg:province":"VIC",
    "wof:name":"Yarra Ranges Optical Pty Ltd",
    "wof:placetype":"venue"
},
  "geometry": {"coordinates":[145.280853272,-37.7964897156],"type":"Point"}
}