{
  "type": "Feature",
  "properties": {
    "iso:country":"AU",
    "sg:address":"PO Box 7704",
    "sg:city":"Cairns MC",
    "sg:classifiers":[
        {
            "category":"Sports & Exercise",
            "subcategory":"Race Track",
            "type":"Entertainment"
        }
    ],
    "sg:phone":"+61 7 4054 4213",
    "sg:postcode":"4870",
    "sg:province":"QLD",
    "sg:tags":[
        "club",
        "racing",
        "motor"
    ],
    "wof:name":"FNQ Motor Sports Car & Rally Club",
    "wof:placetype":"venue"
},
  "geometry": {"coordinates":[145.760955811,-16.9124393463],"type":"Point"}
}