{
  "type": "Feature",
  "properties": {
    "addr:full":"38 College Rd Karana Downs QLD 4306",
    "addr:housenumber":"38",
    "addr:postcode":"4306",
    "addr:street":"College Rd",
    "iso:country":"AU",
    "sg:address":"38 College Rd",
    "sg:city":"Karana Downs",
    "sg:classifiers":[
        {
            "category":"Health Services",
            "subcategory":"Doctor",
            "type":"Services"
        }
    ],
    "sg:phone":"+61 7 3201 2100",
    "sg:postcode":"4306",
    "sg:province":"QLD",
    "sg:tags":[
        "medical",
        "practitioner"
    ],
    "wof:name":"Karana Medical Centre",
    "wof:placetype":"venue"
},
  "geometry": {"coordinates":[152.810943603,-27.5526752472],"type":"Point"}
}