{
  "type": "Feature",
  "properties": {
    "addr:full":"Stall 34, Queen Victoria Market North Melbourne VIC 3051",
    "addr:housenumber":"34",
    "addr:postcode":"3051",
    "addr:street":"Queen;Market",
    "iso:country":"AU",
    "sg:address":"Stall 34, Queen Victoria Market",
    "sg:city":"North Melbourne",
    "sg:classifiers":[
        {
            "category":"Food & Beverages",
            "subcategory":"Meat & Fish",
            "type":"Retail Goods"
        }
    ],
    "sg:phone":"+61 3 9329 6161",
    "sg:postcode":"3051",
    "sg:province":"VIC",
    "sg:tags":[
        "seafood"
    ],
    "wof:name":"F & I Macquire nominees Pty Ltd",
    "wof:placetype":"venue"
},
  "geometry": {"coordinates":[144.94303894000001,-37.8032646179],"type":"Point"}
}