{
  "type": "Feature",
  "properties": {
    "addr:full":"PO Box 1553 Beenleigh QLD 4207",
    "addr:postcode":"4207",
    "iso:country":"AU",
    "sg:address":"PO Box 1553",
    "sg:city":"Beenleigh",
    "sg:classifiers":[
        {
            "category":"Building & Trades",
            "subcategory":"Construction",
            "type":"Services"
        }
    ],
    "sg:phone":"+61 418 699 303",
    "sg:postcode":"4207",
    "sg:province":"QLD",
    "sg:tags":[
        "repair",
        "maintenance",
        "contractor"
    ],
    "wof:name":"Albert & Logan Property Maintenance Services",
    "wof:placetype":"venue"
},
  "geometry": {"coordinates":[153.186965942,-27.7139492035],"type":"Point"}
}