{
  "type": "Feature",
  "properties": {
    "addr:full":"4b Scarborough St Southport QLD 4215",
    "addr:housenumber":"4b",
    "addr:postcode":"4215",
    "addr:street":"Scarborough St",
    "iso:country":"AU",
    "sg:address":"4b Scarborough St",
    "sg:city":"Southport",
    "sg:classifiers":[
        {
            "category":"Fast Food",
            "type":"Food & Drink"
        }
    ],
    "sg:phone":"+61 7 5532 4461",
    "sg:postcode":"4215",
    "sg:province":"QLD",
    "sg:tags":[
        "away",
        "take"
    ],
    "wof:name":"Scarborough Street Takeaways",
    "wof:placetype":"venue"
},
  "geometry": {"coordinates":[153.41537475600001,-27.9726486206],"type":"Point"}
}