{
  "type": "Feature",
  "properties": {
    "iso:country":"AU",
    "sg:address":"Cnr High Rd & Granville Way",
    "sg:city":"Willetton",
    "sg:classifiers":[
        {
            "category":"Health Services",
            "subcategory":"Doctor",
            "type":"Services"
        }
    ],
    "sg:phone":"+61 8 9457 9044",
    "sg:postcode":"6155",
    "sg:province":"WA",
    "sg:tags":[
        "medical",
        "practitioner"
    ],
    "wof:name":"Aquilina John",
    "wof:placetype":"venue"
},
  "geometry": {"coordinates":[115.888931,-32.038761],"type":"Point"}
}