{
  "type": "Feature",
  "properties": {
    "iso:country":"AU",
    "sg:address":"20 Coral St",
    "sg:city":"Maleny",
    "sg:classifiers":[
        {
            "category":"Retail",
            "subcategory":"Veterinary Services",
            "type":"Services"
        }
    ],
    "sg:phone":"+61 7 5499 9077",
    "sg:postcode":"4552",
    "sg:province":"QLD",
    "sg:tags":[
        "surgeon"
    ],
    "wof:name":"Coral Street Veterinary Clinic",
    "wof:placetype":"venue"
},
  "geometry": {"coordinates":[152.85122680699999,-26.7599449158],"type":"Point"}
}