{
  "type": "Feature",
  "properties": {
    "addr:full":"&#034;Centro on James&#034; 46 James St New Farm QLD 4005",
    "addr:housenumber":"46",
    "addr:postcode":"4005",
    "addr:street":"James St",
    "iso:country":"AU",
    "sg:address":"&#034;Centro on James&#034; 46 James St",
    "sg:city":"New Farm",
    "sg:classifiers":[
        {
            "category":"Personal",
            "subcategory":"Massage",
            "type":"Services"
        }
    ],
    "sg:phone":"+61 7 3854 0611",
    "sg:postcode":"4005",
    "sg:province":"QLD",
    "sg:tags":[
        "therapy"
    ],
    "wof:name":"New Farm Holistic Health Centre",
    "wof:placetype":"venue"
},
  "geometry": {"coordinates":[153.04029846200001,-27.4568519592],"type":"Point"}
}