{
  "type": "Feature",
  "properties": {
    "addr:full":"114 Oxford St Paddington NSW 2021",
    "addr:housenumber":"114",
    "addr:postcode":"2021",
    "addr:street":"Oxford St",
    "iso:country":"AU",
    "sg:address":"114 Oxford St",
    "sg:city":"Paddington",
    "sg:classifiers":[
        {
            "category":"Shopping",
            "subcategory":"Jewelry",
            "type":"Retail Goods"
        }
    ],
    "sg:phone":"+61 2 9332 2732",
    "sg:postcode":"2021",
    "sg:province":"NSW",
    "sg:tags":[
        "jeweller"
    ],
    "wof:name":"Duo Fashion Australia Pty Ltd",
    "wof:placetype":"venue"
},
  "geometry": {"coordinates":[151.22207641599999,-33.883644104],"type":"Point"}
}