{
  "type": "Feature",
  "properties": {
    "addr:full":"196 Stafford St Penrith NSW 2750",
    "addr:housenumber":"196",
    "addr:postcode":"2750",
    "addr:street":"Stafford St",
    "iso:country":"AU",
    "sg:address":"196 Stafford St",
    "sg:city":"Penrith",
    "sg:classifiers":[
        {
            "category":"Health Services",
            "subcategory":"Doctor",
            "type":"Services"
        }
    ],
    "sg:phone":"+61 2 4722 5444",
    "sg:postcode":"2750",
    "sg:province":"NSW",
    "sg:tags":[
        "medical",
        "practitioner"
    ],
    "wof:name":"Boshell Laurence L",
    "wof:placetype":"venue"
},
  "geometry": {"coordinates":[150.699783325,-33.7604141235],"type":"Point"}
}