{
  "type": "Feature",
  "properties": {
    "addr:full":"1 Chardonnay Pl Queanbeyan NSW 2620",
    "addr:housenumber":"1",
    "addr:postcode":"2620",
    "addr:street":"Chardonnay Pl",
    "iso:country":"AU",
    "sg:address":"1 Chardonnay Pl",
    "sg:city":"Queanbeyan",
    "sg:classifiers":[
        {
            "category":"Building & Trades",
            "subcategory":"Construction",
            "type":"Services"
        }
    ],
    "sg:phone":"+61 2 6284 4230",
    "sg:postcode":"2620",
    "sg:province":"NSW",
    "sg:tags":[
        "industrial",
        "commercial",
        "air conditioning"
    ],
    "wof:name":"Genlec",
    "wof:placetype":"venue"
},
  "geometry": {"coordinates":[149.200042725,-35.3621864319],"type":"Point"}
}