{
  "type": "Feature",
  "properties": {
    "iso:country":"AU",
    "sg:address":"Shp6/ 41 Burrendah Blv",
    "sg:city":"Willetton",
    "sg:classifiers":[
        {
            "category":"Fast Food",
            "type":"Food & Drink"
        }
    ],
    "sg:phone":"+61 8 9310 4006",
    "sg:postcode":"6155",
    "sg:province":"WA",
    "sg:tags":[
        "away",
        "take"
    ],
    "wof:name":"Southlands Fish & Chips",
    "wof:placetype":"venue"
},
  "geometry": {"coordinates":[115.880997,-32.056717],"type":"Point"}
}