{
  "type": "Feature",
  "properties": {
    "addr:full":"Martins Creek Rd Paterson NSW 2421",
    "addr:postcode":"2421",
    "addr:street":"Creek Rd",
    "iso:country":"AU",
    "sg:address":"Martins Creek Rd",
    "sg:city":"Paterson",
    "sg:classifiers":[
        {
            "category":"Commercial Area",
            "type":"Public Place"
        }
    ],
    "sg:phone":"+61 2 4968 4239",
    "sg:postcode":"2421",
    "sg:province":"NSW",
    "sg:tags":[
        "heavy",
        "carrier"
    ],
    "wof:name":"King C H Transport",
    "wof:placetype":"venue"
},
  "geometry": {"coordinates":[151.621490478,-32.6033210754],"type":"Point"}
}