{
  "type": "Feature",
  "properties": {
    "addr:full":"39 Jersey St Hornsby NSW 2077",
    "addr:housenumber":"39",
    "addr:postcode":"2077",
    "addr:street":"Jersey St",
    "iso:country":"AU",
    "sg:address":"39 Jersey St",
    "sg:city":"Hornsby",
    "sg:classifiers":[
        {
            "category":"Utilities",
            "subcategory":"Mobile Phone",
            "type":"Services"
        }
    ],
    "sg:phone":"+61 2 9476 6811",
    "sg:postcode":"2077",
    "sg:province":"NSW",
    "sg:tags":[
        "assembly",
        "part",
        "electronic"
    ],
    "sg:website":"http://www.cns.org.au",
    "wof:name":"CNS Precision Assembly",
    "wof:placetype":"venue"
},
  "geometry": {"coordinates":[151.098678589,-33.6990432739],"type":"Point"}
}