{
  "type": "Feature",
  "properties": {
    "addr:full":"283 Maribyrnong Rd Ascot Vale VIC 3032",
    "addr:housenumber":"283",
    "addr:postcode":"3032",
    "addr:street":"Maribyrnong Rd",
    "iso:country":"AU",
    "sg:address":"283 Maribyrnong Rd",
    "sg:city":"Ascot Vale",
    "sg:classifiers":[
        {
            "category":"Personal",
            "subcategory":"Massage",
            "type":"Services"
        }
    ],
    "sg:phone":"+61 409 403 462",
    "sg:postcode":"3032",
    "sg:province":"VIC",
    "sg:tags":[
        "therapy"
    ],
    "wof:name":"Anna Pedis Massage Therapy",
    "wof:placetype":"venue"
},
  "geometry": {"coordinates":[144.92051699999999,-37.772182],"type":"Point"}
}