{
  "type": "Feature",
  "properties": {
    "iso:country":"AU",
    "sg:address":"2 Hall St",
    "sg:city":"Cummins",
    "sg:classifiers":[
        {
            "category":"Utilities",
            "subcategory":"Electric",
            "type":"Services"
        }
    ],
    "sg:phone":"+61 8 8676 2218",
    "sg:postcode":"5631",
    "sg:province":"SA",
    "sg:tags":[
        "electrical",
        "contractor"
    ],
    "wof:name":"Richardson A",
    "wof:placetype":"venue"
},
  "geometry": {"coordinates":[135.72689819300001,-34.2638511658],"type":"Point"}
}