{
  "type": "Feature",
  "properties": {
    "addr:full":"13 Webb St Riverwood NSW 2210",
    "addr:housenumber":"13",
    "addr:postcode":"2210",
    "addr:street":"Webb St",
    "iso:country":"AU",
    "sg:address":"13 Webb St",
    "sg:city":"Riverwood",
    "sg:classifiers":[
        {
            "category":"Health Services",
            "subcategory":"Chiropractor",
            "type":"Services"
        }
    ],
    "sg:phone":"+61 2 9153 8135",
    "sg:postcode":"2210",
    "sg:province":"NSW",
    "wof:name":"South Riverwood Chiropractic Centre",
    "wof:placetype":"venue"
},
  "geometry": {"coordinates":[151.050262,-33.952976],"type":"Point"}
}