{
  "type": "Feature",
  "properties": {
    "addr:full":"81 Winbourne Rd Brookvale NSW 2100",
    "addr:housenumber":"81",
    "addr:postcode":"2100",
    "addr:street":"Winbourne Rd",
    "iso:country":"AU",
    "sg:address":"81 Winbourne Rd",
    "sg:city":"Brookvale",
    "sg:classifiers":[
        {
            "category":"Retail",
            "subcategory":"Auto Repair",
            "type":"Services"
        }
    ],
    "sg:phone":"+61 2 9939 6166",
    "sg:postcode":"2100",
    "sg:province":"NSW",
    "sg:tags":[
        "wheel",
        "balancing",
        "alignment"
    ],
    "wof:name":"Owen Tyres",
    "wof:placetype":"venue"
},
  "geometry": {"coordinates":[151.27330017099999,-33.7622337341],"type":"Point"}
}