{
  "type": "Feature",
  "properties": {
    "addr:full":"44 Lee Rd Winmalee NSW 2777",
    "addr:housenumber":"44",
    "addr:postcode":"2777",
    "addr:street":"Lee Rd",
    "iso:country":"AU",
    "sg:address":"44 Lee Rd",
    "sg:city":"Winmalee",
    "sg:classifiers":[
        {
            "category":"Building & Trades",
            "subcategory":"Construction",
            "type":"Services"
        }
    ],
    "sg:phone":"+61 2 4754 1870",
    "sg:postcode":"2777",
    "sg:province":"NSW",
    "sg:tags":[
        "brick",
        "paving"
    ],
    "wof:name":"Jaccoud Landscapes",
    "wof:placetype":"venue"
},
  "geometry": {"coordinates":[150.606033325,-33.6824035645],"type":"Point"}
}