{
  "type": "Feature",
  "properties": {
    "addr:full":"Unit 1/ 19 Nind St Southport QLD 4215",
    "addr:postcode":"4215",
    "addr:street":"19 Nind St",
    "iso:country":"AU",
    "sg:address":"Unit 1/ 19 Nind St",
    "sg:city":"Southport",
    "sg:classifiers":[
        {
            "category":"Personal",
            "subcategory":"Beauty Salon",
            "type":"Services"
        }
    ],
    "sg:phone":"+61 7 5531 1977",
    "sg:postcode":"4215",
    "sg:province":"QLD",
    "sg:tags":[
        "hairdresser"
    ],
    "wof:name":"Jae E Hair Beauty",
    "wof:placetype":"venue"
},
  "geometry": {"coordinates":[153.41299438499999,-27.9637718201],"type":"Point"}
}