{
  "type": "Feature",
  "properties": {
    "addr:full":"Suite 4, Level 2 &#034;The Precinct&#034;, 12 Brow South Brisbane QLD 4101",
    "addr:housenumber":"12",
    "addr:postcode":"4101",
    "addr:street":"The;Brow",
    "iso:country":"AU",
    "sg:address":"Suite 4, Level 2 &#034;The Precinct&#034;, 12 Brow",
    "sg:city":"South Brisbane",
    "sg:classifiers":[
        {
            "category":"Professional",
            "subcategory":"Employment Agencies",
            "type":"Services"
        }
    ],
    "sg:phone":"+61 7 3844 6333",
    "sg:postcode":"4101",
    "sg:province":"QLD",
    "sg:tags":[
        "occupational",
        "therapist"
    ],
    "wof:name":"Australian Rehabilitation Online",
    "wof:placetype":"venue"
},
  "geometry": {"coordinates":[153.01353454599999,-27.4781246185],"type":"Point"}
}