{
  "type": "Feature",
  "properties": {
    "addr:full":"3/ 90 Keppel St Bathurst NSW 2795",
    "addr:housenumber":"/ 90",
    "addr:postcode":"2795",
    "addr:street":"Keppel St",
    "iso:country":"AU",
    "sg:address":"3/ 90 Keppel St",
    "sg:city":"Bathurst",
    "sg:classifiers":[
        {
            "category":"Health Services",
            "subcategory":"Dentist",
            "type":"Services"
        }
    ],
    "sg:phone":"+61 2 6331 3699",
    "sg:postcode":"2795",
    "sg:province":"NSW",
    "wof:name":"Dr Mark Sinclair",
    "wof:placetype":"venue"
},
  "geometry": {"coordinates":[149.57904052699999,-33.4215621948],"type":"Point"}
}