{
  "type": "Feature",
  "properties": {
    "addr:full":"6 Cook St Croydon Park NSW 2133",
    "addr:housenumber":"6",
    "addr:postcode":"2133",
    "addr:street":"Cook St",
    "iso:country":"AU",
    "sg:address":"6 Cook St",
    "sg:city":"Croydon Park",
    "sg:classifiers":[
        {
            "category":"Education",
            "subcategory":"Vocational School",
            "type":"Public Place"
        }
    ],
    "sg:phone":"+61 414 448 565",
    "sg:postcode":"2133",
    "sg:province":"NSW",
    "sg:tags":[
        "cake",
        "decorating",
        "decorator"
    ],
    "wof:name":"Mara's Fine Cake Decorating",
    "wof:placetype":"venue"
},
  "geometry": {"coordinates":[151.10289001500001,-33.8980941772],"type":"Point"}
}