{
  "type": "Feature",
  "properties": {
    "iso:country":"AU",
    "sg:address":"Joseph St",
    "sg:city":"Lidcombe",
    "sg:classifiers":[
        {
            "category":"Health Services",
            "subcategory":"Nursing And Care Facility",
            "type":"Services"
        }
    ],
    "sg:phone":"+61 2 9646 3711",
    "sg:postcode":"2141",
    "sg:province":"NSW",
    "sg:tags":[
        "home"
    ],
    "wof:name":"Ferguson Lodge",
    "wof:placetype":"venue"
},
  "geometry": {"coordinates":[151.043533325,-33.8650741577],"type":"Point"}
}