{
  "type": "Feature",
  "properties": {
    "addr:full":"101 Molesworth St Lismore NSW 2480",
    "addr:housenumber":"101",
    "addr:postcode":"2480",
    "addr:street":"Molesworth St",
    "iso:country":"AU",
    "sg:address":"101 Molesworth St",
    "sg:city":"Lismore",
    "sg:classifiers":[
        {
            "category":"Banks & Credit Unions",
            "subcategory":"Financial Services",
            "type":"Services"
        }
    ],
    "sg:phone":"+61 1300 802 222",
    "sg:postcode":"2480",
    "sg:province":"NSW",
    "sg:tags":[
        "loan",
        "finance",
        "mortgage"
    ],
    "wof:name":"Summerland Credit Union",
    "wof:placetype":"venue"
},
  "geometry": {"coordinates":[153.27589416500001,-28.8084888458],"type":"Point"}
}