{
  "type": "Feature",
  "properties": {
    "iso:country":"AU",
    "sg:address":"891 Albany Hwy",
    "sg:city":"East Victoria Park",
    "sg:classifiers":[
        {
            "category":"Restaurant",
            "type":"Food & Drink"
        }
    ],
    "sg:phone":"+61 8 9361 9877",
    "sg:postcode":"6101",
    "sg:province":"WA",
    "wof:name":"Christina's Restaurant",
    "wof:placetype":"venue"
},
  "geometry": {"coordinates":[115.90418243400001,-31.9864788055],"type":"Point"}
}