{
  "type": "Feature",
  "properties": {
    "addr:full":"Cnr Golflinks Rd & Karawatha Drv Buderim QLD 4556",
    "addr:postcode":"4556",
    "addr:street":"Cnr Golflinks Rd & Karawatha Drv",
    "iso:country":"AU",
    "sg:address":"Cnr Golflinks Rd & Karawatha Drv",
    "sg:city":"Buderim",
    "sg:classifiers":[
        {
            "category":"Health Services",
            "subcategory":"Doctor",
            "type":"Services"
        }
    ],
    "sg:phone":"+61 7 5444 7355",
    "sg:postcode":"4556",
    "sg:province":"QLD",
    "sg:tags":[
        "medical",
        "practitioner"
    ],
    "wof:name":"MacKinnon Tibby (Elizabeth)",
    "wof:placetype":"venue"
},
  "geometry": {"coordinates":[153.08340454099999,-26.6942081451],"type":"Point"}
}