{
  "type": "Feature",
  "properties": {
    "iso:country":"AU",
    "sg:address":"Wellington Rd",
    "sg:city":"Auburn",
    "sg:classifiers":[
        {
            "category":"Utilities",
            "subcategory":"Electric",
            "type":"Services"
        }
    ],
    "sg:phone":"+61 2 9646 2949",
    "sg:postcode":"2144",
    "sg:province":"NSW",
    "sg:tags":[
        "electrical",
        "contractor"
    ],
    "wof:name":"Azzam Air Conditioning & Electrical Services Pty Ltd",
    "wof:placetype":"venue"
},
  "geometry": {"coordinates":[151.02174377399999,-33.8642883301],"type":"Point"}
}