{
  "type": "Feature",
  "properties": {
    "addr:full":"348 Forrest Rd Brookdale WA 6112",
    "addr:housenumber":"348",
    "addr:postcode":"6112",
    "addr:street":"Forrest Rd",
    "iso:country":"AU",
    "sg:address":"348 Forrest Rd",
    "sg:city":"Brookdale",
    "sg:classifiers":[
        {
            "category":"Wholesale",
            "subcategory":"Plants",
            "type":"Manufacturing & Wholesale Goods"
        }
    ],
    "sg:phone":"+61 8 9497 9994",
    "sg:postcode":"6112",
    "sg:province":"WA",
    "sg:tags":[
        "florist"
    ],
    "wof:name":"Romance Roses",
    "wof:placetype":"venue"
},
  "geometry": {"coordinates":[115.980369568,-32.1615180969],"type":"Point"}
}