{
  "type": "Feature",
  "properties": {
    "addr:full":"Lvl 4/ 141 Osborne St South Yarra VIC 3141",
    "addr:housenumber":"/ 141",
    "addr:postcode":"3141",
    "addr:street":"Osborne St",
    "iso:country":"AU",
    "sg:address":"Lvl 4/ 141 Osborne St",
    "sg:city":"South Yarra",
    "sg:classifiers":[
        {
            "category":"Education",
            "subcategory":"Special Training",
            "type":"Public Place"
        }
    ],
    "sg:phone":"+61 3 9279 3904",
    "sg:postcode":"3141",
    "sg:province":"VIC",
    "sg:tags":[
        "development"
    ],
    "wof:name":"Xperium Pty Ltd",
    "wof:placetype":"venue"
},
  "geometry": {"coordinates":[144.99137878400001,-37.8395042419],"type":"Point"}
}