{
  "type": "Feature",
  "properties": {
    "addr:full":"Shp17/ 23 Coondoo St Kuranda QLD 4881",
    "addr:postcode":"4881",
    "addr:street":"Coondoo St",
    "iso:country":"AU",
    "sg:address":"Shp17/ 23 Coondoo St",
    "sg:city":"Kuranda",
    "sg:classifiers":[
        {
            "category":"Food & Beverages",
            "subcategory":"Bakery",
            "type":"Retail Goods"
        }
    ],
    "sg:phone":"+61 7 4093 8005",
    "sg:postcode":"4881",
    "sg:province":"QLD",
    "sg:tags":[
        "baker"
    ],
    "wof:name":"Kuranda Bakery",
    "wof:placetype":"venue"
},
  "geometry": {"coordinates":[145.635696411,-16.8195590973],"type":"Point"}
}