{
  "type": "Feature",
  "properties": {
    "addr:full":"100 New St Ringwood VIC 3134",
    "addr:housenumber":"100",
    "addr:postcode":"3134",
    "addr:street":"New St",
    "iso:country":"AU",
    "sg:address":"100 New St",
    "sg:city":"Ringwood",
    "sg:classifiers":[
        {
            "category":"Health Services",
            "subcategory":"Health Practitioner",
            "type":"Services"
        }
    ],
    "sg:phone":"+61 3 9847 0177",
    "sg:postcode":"3134",
    "sg:province":"VIC",
    "sg:tags":[
        "audiologists"
    ],
    "wof:name":"Stinger Australia Pty Ltd",
    "wof:placetype":"venue"
},
  "geometry": {"coordinates":[145.220306397,-37.8212242126],"type":"Point"}
}