{
  "type": "Feature",
  "properties": {
    "iso:country":"AU",
    "sg:address":"446 Kooyong Rd",
    "sg:city":"Caulfield South",
    "sg:classifiers":[
        {
            "category":"Shopping",
            "subcategory":"Clothing, Apparel, & Fashions",
            "type":"Retail Goods"
        }
    ],
    "sg:phone":"+61 3 9505 0500",
    "sg:postcode":"3162",
    "sg:province":"VIC",
    "sg:tags":[
        "lingerie",
        "hosiery",
        "sleepwear"
    ],
    "wof:name":"Bridal Bras",
    "wof:placetype":"venue"
},
  "geometry": {"coordinates":[145.01351928700001,-37.8945388794],"type":"Point"}
}