{
  "type": "Feature",
  "properties": {
    "addr:full":"8 Drouyn St Sandgate QLD 4017",
    "addr:housenumber":"8",
    "addr:postcode":"4017",
    "addr:street":"Drouyn St",
    "iso:country":"AU",
    "sg:address":"8 Drouyn St",
    "sg:city":"Sandgate",
    "sg:classifiers":[
        {
            "category":"Professional",
            "subcategory":"Art Services",
            "type":"Services"
        }
    ],
    "sg:phone":"+61 7 3869 0605",
    "sg:postcode":"4017",
    "sg:province":"QLD",
    "sg:tags":[
        "decorator",
        "painter"
    ],
    "wof:name":"J. Kilmartin Painting & Decorating",
    "wof:placetype":"venue"
},
  "geometry": {"coordinates":[153.06044006400001,-27.3248596191],"type":"Point"}
}