{
  "type": "Feature",
  "properties": {
    "addr:full":"62 Creaney Drv Kingsley WA 6026",
    "addr:housenumber":"62",
    "addr:postcode":"6026",
    "addr:street":"Creaney Drv",
    "iso:country":"AU",
    "sg:address":"62 Creaney Drv",
    "sg:city":"Kingsley",
    "sg:classifiers":[
        {
            "category":"Health Services",
            "subcategory":"Health Practitioner",
            "type":"Services"
        }
    ],
    "sg:phone":"+61 8 9409 1676",
    "sg:postcode":"6026",
    "sg:province":"WA",
    "sg:tags":[
        "physiotherapist"
    ],
    "wof:name":"Bouckley Joanne",
    "wof:placetype":"venue"
},
  "geometry": {"coordinates":[115.790390015,-31.8082923889],"type":"Point"}
}