{
  "type": "Feature",
  "properties": {
    "addr:full":"124 Second Ave Rosebud VIC 3939",
    "addr:housenumber":"124",
    "addr:postcode":"3939",
    "addr:street":"Second Ave",
    "iso:country":"AU",
    "sg:address":"124 Second Ave",
    "sg:city":"Rosebud",
    "sg:classifiers":[
        {
            "category":"Building & Trades",
            "subcategory":"Plumbing",
            "type":"Services"
        }
    ],
    "sg:phone":"+61 404 077 887",
    "sg:postcode":"3939",
    "sg:province":"VIC",
    "sg:tags":[
        "plumber",
        "gasfitters"
    ],
    "wof:name":"Gavin Roche",
    "wof:placetype":"venue"
},
  "geometry": {"coordinates":[144.896575928,-38.3648605347],"type":"Point"}
}