{
  "type": "Feature",
  "properties": {
    "addr:full":"Shop 3 , Rosemeadow Centre, Fitzgibbon Lane Rosemead NSW 2560",
    "addr:housenumber":"shop 3",
    "addr:postcode":"2560",
    "addr:street":"Fitzgibbon Lane",
    "iso:country":"AU",
    "sg:address":"Shop 3",
    "sg:city":", Rosemeadow Centre, Fitzgibbon Lane Rosemead",
    "sg:classifiers":[
        {
            "category":"Fast Food",
            "type":"Food & Drink"
        }
    ],
    "sg:phone":"+61 13 11 66",
    "sg:postcode":"2560",
    "sg:province":"NSW",
    "sg:tags":[
        "away",
        "take"
    ],
    "wof:name":"Pizza Hut",
    "wof:placetype":"venue"
},
  "geometry": {"coordinates":[150.79461669899999,-34.100944519],"type":"Point"}
}