{
  "type": "Feature",
  "properties": {
    "addr:full":"4th Floor, Post Office Plaza Flinders St Mall Townsville QLD 4810",
    "addr:postcode":"4810",
    "addr:street":"Flinders St Mall",
    "iso:country":"AU",
    "sg:address":"4th Floor, Post Office Plaza Flinders St",
    "sg:city":"Mall Townsville",
    "sg:classifiers":[
        {
            "category":"Health Services",
            "subcategory":"Doctor",
            "type":"Services"
        }
    ],
    "sg:phone":"+61 7 4771 3000",
    "sg:postcode":"4810",
    "sg:province":"QLD",
    "sg:tags":[
        "reflexology"
    ],
    "wof:name":"Chill Out Body Treatments",
    "wof:placetype":"venue"
},
  "geometry": {"coordinates":[146.80641199999999,-19.268761],"type":"Point"}
}