{
  "type": "Feature",
  "properties": {
    "iso:country":"AU",
    "sg:address":"Shp1a/ 13 - 17 Dornoch Drv",
    "sg:city":"Sunbury",
    "sg:classifiers":[
        {
            "category":"Fast Food",
            "type":"Food & Drink"
        }
    ],
    "sg:phone":"+61 3 9740 3337",
    "sg:postcode":"3429",
    "sg:province":"VIC",
    "sg:tags":[
        "away",
        "take"
    ],
    "wof:name":"Goonawarrah Pizza",
    "wof:placetype":"venue"
},
  "geometry": {"coordinates":[144.75006103499999,-37.5789413452],"type":"Point"}
}