{
  "type": "Feature",
  "properties": {
    "addr:full":"PO Box 42 Brighton-le-Sands NSW 2216",
    "addr:postcode":"2216",
    "iso:country":"AU",
    "sg:address":"PO Box 42",
    "sg:city":"Brighton-le-Sands",
    "sg:classifiers":[
        {
            "category":"Organizations",
            "subcategory":"Non-profit Organization",
            "type":"Services"
        }
    ],
    "sg:phone":"+61 2 9556 1537",
    "sg:postcode":"2216",
    "sg:province":"NSW",
    "sg:tags":[
        "environmental",
        "organisation",
        "conservation"
    ],
    "wof:name":"Wildlife Preservation Society Of Australia",
    "wof:placetype":"venue"
},
  "geometry": {"coordinates":[151.155731,-33.96069],"type":"Point"}
}