{
  "type": "Feature",
  "properties": {
    "iso:country":"AU",
    "sg:address":"Cnr Wakool Rd & Stewart St",
    "sg:city":"Deniliquin",
    "sg:classifiers":[
        {
            "category":"Retail",
            "subcategory":"Storage",
            "type":"Services"
        }
    ],
    "sg:phone":"+61 3 5881 3304",
    "sg:postcode":"2710",
    "sg:province":"NSW",
    "wof:name":"Kings Self Storage",
    "wof:placetype":"venue"
},
  "geometry": {"coordinates":[144.94859314000001,-35.5293617249],"type":"Point"}
}