{
  "type": "Feature",
  "properties": {
    "iso:country":"AU",
    "sg:address":"109 Huntley St",
    "sg:city":"Gooseberry Hill",
    "sg:classifiers":[
        {
            "category":"Professional",
            "subcategory":"Management & Consulting",
            "type":"Services"
        }
    ],
    "sg:phone":"+61 419 900 779",
    "sg:postcode":"6076",
    "sg:province":"WA",
    "sg:tags":[
        "consultant",
        "business"
    ],
    "wof:name":"McIntyre Peter Business Consultant",
    "wof:placetype":"venue"
},
  "geometry": {"coordinates":[116.054550171,-31.9530067444],"type":"Point"}
}