{
  "type": "Feature",
  "properties": {
    "addr:full":"7- 11 The Quadrant Mall Launceston TAS 7250",
    "addr:housenumber":"11",
    "addr:postcode":"7250",
    "addr:street":"7;The Quadrant",
    "iso:country":"AU",
    "sg:address":"7- 11 The Quadrant Mall",
    "sg:city":"Launceston",
    "sg:classifiers":[
        {
            "category":"Shopping",
            "subcategory":"Music",
            "type":"Retail Goods"
        }
    ],
    "sg:phone":"+61 3 6331 5688",
    "sg:postcode":"7250",
    "sg:province":"TAS",
    "sg:tags":[
        "store"
    ],
    "wof:name":"Leading Edge Music",
    "wof:placetype":"venue"
},
  "geometry": {"coordinates":[147.13815307600001,-41.4377174377],"type":"Point"}
}