{
  "type": "Feature",
  "properties": {
    "iso:country":"AU",
    "sg:address":"PO Box 1350",
    "sg:city":"Traralgon",
    "sg:classifiers":[
        {
            "category":"Professional",
            "subcategory":"Detective & Security Services",
            "type":"Services"
        }
    ],
    "sg:phone":"+61 3 5122 3338",
    "sg:postcode":"3844",
    "sg:province":"VIC",
    "sg:tags":[
        "equipment",
        "window",
        "doors"
    ],
    "wof:name":"Latrobe Valley Glass Pty Ltd",
    "wof:placetype":"venue"
},
  "geometry": {"coordinates":[146.53814697300001,-38.1949501038],"type":"Point"}
}