{
  "type": "Feature",
  "properties": {
    "addr:full":"6 Portland St Richmond VIC 3121",
    "addr:housenumber":"6",
    "addr:postcode":"3121",
    "addr:street":"Portland St",
    "iso:country":"AU",
    "sg:address":"6 Portland St",
    "sg:city":"Richmond",
    "sg:classifiers":[
        {
            "category":"Wholesale",
            "subcategory":"Non-durable Goods",
            "type":"Manufacturing & Wholesale Goods"
        }
    ],
    "sg:phone":"+61 3 9429 5345",
    "sg:postcode":"3121",
    "sg:province":"VIC",
    "sg:tags":[
        "textile"
    ],
    "wof:name":"Robtex & Associates",
    "wof:placetype":"venue"
},
  "geometry": {"coordinates":[144.99473571799999,-37.8215179443],"type":"Point"}
}