{
  "type": "Feature",
  "properties": {
    "iso:country":"AU",
    "sg:address":"Kennedy St",
    "sg:city":"Kingston",
    "sg:classifiers":[
        {
            "category":"Shopping",
            "subcategory":"Crafts & Fabrics",
            "type":"Retail Goods"
        }
    ],
    "sg:phone":"+61 2 6295 7280",
    "sg:postcode":"2604",
    "sg:province":"ACT",
    "sg:tags":[
        "wool",
        "knitting",
        "accessory"
    ],
    "wof:name":"Cassidys",
    "wof:placetype":"venue"
},
  "geometry": {"coordinates":[149.14561462399999,-35.3194313049],"type":"Point"}
}