{
  "type": "Feature",
  "properties": {
    "addr:full":"171 Nicolson Ave Whyalla Norrie SA 5608",
    "addr:housenumber":"171",
    "addr:postcode":"5608",
    "addr:street":"Nicolson Ave",
    "iso:country":"AU",
    "sg:address":"171 Nicolson Ave",
    "sg:city":"Whyalla Norrie",
    "sg:classifiers":[
        {
            "category":"Health Services",
            "subcategory":"Doctor",
            "type":"Services"
        }
    ],
    "sg:phone":"+61 8 8645 5344",
    "sg:postcode":"5608",
    "sg:province":"SA",
    "sg:tags":[
        "medical",
        "practitioner"
    ],
    "wof:name":"Whyalla Family Practice",
    "wof:placetype":"venue"
},
  "geometry": {"coordinates":[137.53611799999999,-33.027237],"type":"Point"}
}