{
  "type": "Feature",
  "properties": {
    "iso:country":"AU",
    "sg:address":"19 Second St",
    "sg:city":"Magill",
    "sg:classifiers":[
        {
            "category":"Organizations",
            "subcategory":"Professional Association",
            "type":"Services"
        }
    ],
    "sg:phone":"+61 8 8237 7513",
    "sg:postcode":"5072",
    "sg:province":"SA",
    "sg:tags":[
        "web",
        "internet"
    ],
    "wof:name":"Neil De Susa",
    "wof:placetype":"venue"
},
  "geometry": {"coordinates":[138.67115783700001,-34.9048156738],"type":"Point"}
}