{
  "type": "Feature",
  "properties": {
    "addr:full":"66 Carlton Pde Carlton NSW 2218",
    "addr:housenumber":"66",
    "addr:postcode":"2218",
    "addr:street":"Carlton Pde",
    "iso:country":"AU",
    "sg:address":"66 Carlton Pde",
    "sg:city":"Carlton",
    "sg:classifiers":[
        {
            "category":"Professional",
            "subcategory":"Computer Services",
            "type":"Services"
        }
    ],
    "sg:phone":"+61 2 9587 0419",
    "sg:postcode":"2218",
    "sg:province":"NSW",
    "sg:tags":[
        "repairs",
        "upgrade",
        "equipment"
    ],
    "wof:name":"Gemini Technologies",
    "wof:placetype":"venue"
},
  "geometry": {"coordinates":[151.12266500000001,-33.968254],"type":"Point"}
}