{
  "type": "Feature",
  "properties": {
    "addr:full":"Parachilna Gorge Rd The Ranges SA 5172",
    "addr:postcode":"5172",
    "addr:street":"Gorge Rd",
    "iso:country":"AU",
    "sg:address":"Parachilna Gorge Rd",
    "sg:city":"The Ranges",
    "sg:classifiers":[
        {
            "category":"Food & Beverages",
            "subcategory":"Supermarket",
            "type":"Retail Goods"
        }
    ],
    "sg:phone":"+61 8 8648 4842",
    "sg:postcode":"5172",
    "sg:province":"SA",
    "sg:tags":[
        "grocery",
        "store"
    ],
    "wof:name":"Angorichina Store",
    "wof:placetype":"venue"
},
  "geometry": {"coordinates":[138.60690307600001,-35.2657318115],"type":"Point"}
}