{
  "type": "Feature",
  "properties": {
    "addr:full":"6 Newcombe St Drysdale VIC 3222",
    "addr:housenumber":"6",
    "addr:postcode":"3222",
    "addr:street":"Newcombe St",
    "iso:country":"AU",
    "sg:address":"6 Newcombe St",
    "sg:city":"Drysdale",
    "sg:classifiers":[
        {
            "category":"Home & Garden",
            "subcategory":"Carpets & Floor Coverings",
            "type":"Retail Goods"
        }
    ],
    "sg:phone":"+61 3 5251 3501",
    "sg:postcode":"3222",
    "sg:province":"VIC",
    "sg:tags":[
        "layer",
        "planner"
    ],
    "wof:name":"G J Welk",
    "wof:placetype":"venue"
},
  "geometry": {"coordinates":[144.56286600000001,-38.175987],"type":"Point"}
}