{
  "type": "Feature",
  "properties": {
    "addr:full":"2 Coal St Silverwater NSW 2128",
    "addr:housenumber":"2",
    "addr:postcode":"2128",
    "addr:street":"Coal St",
    "iso:country":"AU",
    "sg:address":"2 Coal St",
    "sg:city":"Silverwater",
    "sg:classifiers":[
        {
            "category":"Professional",
            "subcategory":"Employment Agencies",
            "type":"Services"
        }
    ],
    "sg:phone":"+61 2 8756 4100",
    "sg:postcode":"2128",
    "sg:province":"NSW",
    "sg:tags":[
        "hire",
        "labour",
        "contractor"
    ],
    "wof:name":"Service Stream Communications Pty Ltd",
    "wof:placetype":"venue"
},
  "geometry": {"coordinates":[151.04664611800001,-33.8311271667],"type":"Point"}
}