{
  "type": "Feature",
  "properties": {
    "addr:full":"PO Box 9574 Deakin ACT 2600",
    "addr:postcode":"2600",
    "iso:country":"AU",
    "sg:address":"PO Box 9574",
    "sg:city":"Deakin",
    "sg:classifiers":[
        {
            "category":"Professional",
            "subcategory":"Art Services",
            "type":"Services"
        }
    ],
    "sg:phone":"+61 2 6248 9992",
    "sg:postcode":"2600",
    "sg:province":"ACT",
    "sg:tags":[
        "graphic",
        "designer"
    ],
    "wof:name":"Kyliesmith Design",
    "wof:placetype":"venue"
},
  "geometry": {"coordinates":[149.10842895499999,-35.314781189],"type":"Point"}
}