{
  "type": "Feature",
  "properties": {
    "addr:full":"Unit 1/ 6 De Latour St Coconut Grove NT 0810",
    "addr:housenumber":"6",
    "addr:postcode":"0810",
    "addr:street":"De Latour St",
    "iso:country":"AU",
    "sg:address":"Unit 1/ 6 De Latour St",
    "sg:city":"Coconut Grove",
    "sg:classifiers":[
        {
            "category":"Manufacturing",
            "subcategory":"Musical Instruments",
            "type":"Manufacturing & Wholesale Goods"
        }
    ],
    "sg:phone":"+61 8 8948 1855",
    "sg:postcode":"0810",
    "sg:province":"NT",
    "sg:tags":[
        "repair",
        "maker"
    ],
    "wof:name":"Rocktown Music",
    "wof:placetype":"venue"
},
  "geometry": {"coordinates":[130.85523986800001,-12.4018669128],"type":"Point"}
}