{
  "type": "Feature",
  "properties": {
    "iso:country":"AU",
    "sg:address":"38 Maroong Drv",
    "sg:city":"Research",
    "sg:classifiers":[
        {
            "category":"Professional",
            "subcategory":"Research",
            "type":"Services"
        }
    ],
    "sg:phone":"+61 3 9437 0247",
    "sg:postcode":"3095",
    "sg:province":"VIC",
    "sg:tags":[
        "industrial",
        "scientific"
    ],
    "wof:name":"Yaxley Scientific Associates",
    "wof:placetype":"venue"
},
  "geometry": {"coordinates":[145.177276611,-37.6986274719],"type":"Point"}
}