{
  "type": "Feature",
  "properties": {
    "addr:full":"Cnr Bruce Hwy & Manaway Rd Coningsby via Mackay Coningsby QLD 4740",
    "addr:postcode":"4740",
    "addr:street":"Cnr Bruce Hwy & Manaway Rd;Via Mackay",
    "iso:country":"AU",
    "sg:address":"Cnr Bruce Hwy & Manaway Rd",
    "sg:city":"Coningsby via Mackay Coningsby",
    "sg:classifiers":[
        {
            "category":"Education",
            "subcategory":"School",
            "type":"Public Place"
        }
    ],
    "sg:phone":"+61 7 4959 8315",
    "sg:postcode":"4740",
    "sg:province":"QLD",
    "sg:tags":[
        "state",
        "except",
        "nsw"
    ],
    "wof:name":"Coningsby Primary School",
    "wof:placetype":"venue"
},
  "geometry": {"coordinates":[149.15020799999999,-21.190926],"type":"Point"}
}