{
  "type": "Feature",
  "properties": {
    "addr:full":"Shop 3 Mittagong Shopping Village Pioneer St Mittagong NSW 2575",
    "addr:housenumber":"shop 3",
    "addr:postcode":"2575",
    "addr:street":"Mittagong;Pioneer St",
    "iso:country":"AU",
    "sg:address":"Shop 3 Mittagong Shopping Village Pioneer St",
    "sg:city":"Mittagong",
    "sg:classifiers":[
        {
            "category":"Manufacturing",
            "subcategory":"Food",
            "type":"Manufacturing & Wholesale Goods"
        }
    ],
    "sg:phone":"+61 2 4872 1913",
    "sg:postcode":"2575",
    "sg:province":"NSW",
    "sg:tags":[
        "function",
        "catering"
    ],
    "wof:name":"Eco Catering",
    "wof:placetype":"venue"
},
  "geometry": {"coordinates":[150.44479370100001,-34.450881958],"type":"Point"}
}