{
  "type": "Feature",
  "properties": {
    "iso:country":"AU",
    "sg:address":"28 Dwyer St",
    "sg:city":"Clifton Hill",
    "sg:classifiers":[
        {
            "category":"Real Estate",
            "subcategory":"Architect",
            "type":"Services"
        }
    ],
    "sg:phone":"+61 3 9428 5717",
    "sg:postcode":"3068",
    "sg:province":"VIC",
    "wof:name":"J & B Wigley Pty Ltd",
    "wof:placetype":"venue"
},
  "geometry": {"coordinates":[145.003219605,-37.7875480652],"type":"Point"}
}