{
  "type": "Feature",
  "properties": {
    "iso:country":"AU",
    "sg:address":"141 Boundary St",
    "sg:city":"Mackay",
    "sg:classifiers":[
        {
            "category":"Building & Trades",
            "subcategory":"Equipment Rental",
            "type":"Services"
        }
    ],
    "sg:phone":"+61 7 4952 2213",
    "sg:postcode":"4740",
    "sg:province":"QLD",
    "sg:tags":[
        "crane",
        "hire"
    ],
    "wof:name":"Boom Logistics Ltd",
    "wof:placetype":"venue"
},
  "geometry": {"coordinates":[149.141403,-21.172649],"type":"Point"}
}