{
  "type": "Feature",
  "properties": {
    "iso:country":"AU",
    "sg:address":"6 Ozone Ave",
    "sg:city":"Seaford",
    "sg:classifiers":[
        {
            "category":"Manufacturing",
            "subcategory":"Jewelry",
            "type":"Manufacturing & Wholesale Goods"
        }
    ],
    "sg:phone":"+61 3 9773 6161",
    "sg:postcode":"3198",
    "sg:province":"VIC",
    "sg:tags":[
        "mfrg",
        "jeweller"
    ],
    "wof:name":"Ynot Jewellery",
    "wof:placetype":"venue"
},
  "geometry": {"coordinates":[145.125930786,-38.1182060242],"type":"Point"}
}