{
  "type": "Feature",
  "properties": {
    "iso:country":"AU",
    "sg:address":"196 Ontario Ave",
    "sg:city":"Mildura",
    "sg:classifiers":[
        {
            "category":"Health Services",
            "subcategory":"Doctor",
            "type":"Services"
        }
    ],
    "sg:phone":"+61 3 5023 7311",
    "sg:postcode":"3500",
    "sg:province":"VIC",
    "sg:tags":[
        "medical",
        "practitioner"
    ],
    "wof:name":"Joyce D",
    "wof:placetype":"venue"
},
  "geometry": {"coordinates":[142.14421081500001,-34.1840515137],"type":"Point"}
}