{
  "type": "Feature",
  "properties": {
    "iso:country":"AU",
    "sg:address":"Shop 2, 112 Main St",
    "sg:city":"Blacktown",
    "sg:classifiers":[
        {
            "category":"Banks & Credit Unions",
            "subcategory":"Financial Services",
            "type":"Services"
        }
    ],
    "sg:phone":"+61 2 9676 1433",
    "sg:postcode":"2148",
    "sg:province":"NSW",
    "sg:tags":[
        "financier"
    ],
    "wof:name":"Wizard Home Loans",
    "wof:placetype":"venue"
},
  "geometry": {"coordinates":[150.91058349599999,-33.7713356018],"type":"Point"}
}