{
  "type": "Feature",
  "properties": {
    "addr:full":"1, 58 Channel Hwy Kingston TAS 7050",
    "addr:housenumber":"58",
    "addr:postcode":"7050",
    "addr:street":"1;Channel Hwy",
    "iso:country":"AU",
    "sg:address":"1, 58 Channel Hwy",
    "sg:city":"Kingston",
    "sg:classifiers":[
        {
            "category":"Food & Beverages",
            "subcategory":"Bakery",
            "type":"Retail Goods"
        }
    ],
    "sg:phone":"+61 3 6227 1988",
    "sg:postcode":"7050",
    "sg:province":"TAS",
    "sg:tags":[
        "cake",
        "shop",
        "pastry"
    ],
    "wof:name":"Cheesecake Shop The",
    "wof:placetype":"venue"
},
  "geometry": {"coordinates":[147.306183,-42.975849],"type":"Point"}
}