{
  "type": "Feature",
  "properties": {
    "addr:full":"86 Turner Rd Highett VIC 3190",
    "addr:housenumber":"86",
    "addr:postcode":"3190",
    "addr:street":"Turner Rd",
    "iso:country":"AU",
    "sg:address":"86 Turner Rd",
    "sg:city":"Highett",
    "sg:classifiers":[
        {
            "category":"Personal",
            "subcategory":"Massage",
            "type":"Services"
        }
    ],
    "sg:phone":"+61 3 9553 0412",
    "sg:postcode":"3190",
    "sg:province":"VIC",
    "sg:tags":[
        "therapy"
    ],
    "wof:name":"Jiao Su Jun",
    "wof:placetype":"venue"
},
  "geometry": {"coordinates":[145.0572052,-37.9521484375],"type":"Point"}
}