{
  "type": "Feature",
  "properties": {
    "addr:full":"94 Queens Rd Hermit Park QLD 4812",
    "addr:housenumber":"94",
    "addr:postcode":"4812",
    "addr:street":"Queens Rd",
    "iso:country":"AU",
    "sg:address":"94 Queens Rd",
    "sg:city":"Hermit Park",
    "sg:classifiers":[
        {
            "category":"Professional",
            "subcategory":"Art Services",
            "type":"Services"
        }
    ],
    "sg:phone":"+61 408 188 540",
    "sg:postcode":"4812",
    "sg:province":"QLD",
    "sg:tags":[
        "decorator",
        "painter"
    ],
    "wof:name":"Wally Murdock",
    "wof:placetype":"venue"
},
  "geometry": {"coordinates":[146.80050700000001,-19.287212],"type":"Point"}
}