{
  "type": "Feature",
  "properties": {
    "addr:full":"71 Speets Rd Oakville NSW 2765",
    "addr:housenumber":"71",
    "addr:postcode":"2765",
    "addr:street":"Speets Rd",
    "iso:country":"AU",
    "sg:address":"71 Speets Rd",
    "sg:city":"Oakville",
    "sg:classifiers":[
        {
            "category":"Food & Beverages",
            "subcategory":"Fruits & Vegetables",
            "type":"Retail Goods"
        }
    ],
    "sg:phone":"+61 2 4573 6730",
    "sg:postcode":"2765",
    "sg:province":"NSW",
    "sg:tags":[
        "wholesale"
    ],
    "wof:name":"Grech J",
    "wof:placetype":"venue"
},
  "geometry": {"coordinates":[150.884689331,-33.6236572266],"type":"Point"}
}