{
  "type": "Feature",
  "properties": {
    "addr:full":"Suite 2/ 15 Hill St Roseville NSW 2069",
    "addr:housenumber":"15",
    "addr:postcode":"2069",
    "addr:street":"Hill St",
    "iso:country":"AU",
    "sg:address":"Suite 2/ 15 Hill St",
    "sg:city":"Roseville",
    "sg:classifiers":[
        {
            "category":"Real Estate",
            "subcategory":"Real Estate Agent",
            "type":"Services"
        }
    ],
    "sg:phone":"+61 2 9413 3885",
    "sg:postcode":"2069",
    "sg:province":"NSW",
    "wof:name":"Ray White Roseville",
    "wof:placetype":"venue"
},
  "geometry": {"coordinates":[151.17887878400001,-33.7848510742],"type":"Point"}
}