{
  "type": "Feature",
  "properties": {
    "iso:country":"AU",
    "sg:address":"119 Holberton St",
    "sg:city":"Toowoomba",
    "sg:classifiers":[
        {
            "category":"Personal",
            "subcategory":"Massage",
            "type":"Services"
        }
    ],
    "sg:phone":"+61 7 4634 4338",
    "sg:postcode":"4350",
    "sg:province":"QLD",
    "sg:tags":[
        "therapy"
    ],
    "wof:name":"East Meets West Massage Therapies",
    "wof:placetype":"venue"
},
  "geometry": {"coordinates":[151.934326,-27.550346],"type":"Point"}
}