{
  "type": "Feature",
  "properties": {
    "iso:country":"AU",
    "sg:address":"Suite 214 566 St Kilda Rd",
    "sg:city":"Melbourne",
    "sg:classifiers":[
        {
            "category":"Professional",
            "subcategory":"Employment Agencies",
            "type":"Services"
        }
    ],
    "sg:phone":"+61 3 9526 8188",
    "sg:postcode":"3000",
    "sg:province":"VIC",
    "wof:name":"Hillmcglynn Australia",
    "wof:placetype":"venue"
},
  "geometry": {"coordinates":[144.97903442399999,-37.8467979431],"type":"Point"}
}