{
  "type": "Feature",
  "properties": {
    "iso:country":"AU",
    "sg:address":"PO Box 523",
    "sg:city":"Smithfield (Cairns)",
    "sg:classifiers":[
        {
            "category":"Shopping",
            "subcategory":"Bicycles & Sporting Goods",
            "type":"Retail Goods"
        }
    ],
    "sg:phone":"+61 7 4057 6555",
    "sg:postcode":"4350",
    "sg:province":"QLD",
    "sg:tags":[
        "chemical",
        "equipment",
        "pool",
        "swimming"
    ],
    "wof:name":"Placid Pools Pty Ltd",
    "wof:placetype":"venue"
},
  "geometry": {"coordinates":[151.92860400000001,-27.586323],"type":"Point"}
}