{
  "type": "Feature",
  "properties": {
    "iso:country":"AU",
    "sg:address":"288 Kingsgrove Rd",
    "sg:city":"Kingsgrove",
    "sg:classifiers":[
        {
            "category":"Utilities",
            "subcategory":"Mobile Phone",
            "type":"Services"
        }
    ],
    "sg:phone":"+61 2 9554 4533",
    "sg:postcode":"2208",
    "sg:province":"NSW",
    "sg:tags":[
        "repair",
        "telephone"
    ],
    "wof:name":"Fone Tek",
    "wof:placetype":"venue"
},
  "geometry": {"coordinates":[151.101639,-33.942486],"type":"Point"}
}