{
  "type": "Feature",
  "properties": {
    "addr:full":"9/ 149-153 Sydney Rd Fairlight NSW 2094",
    "addr:housenumber":"/ 149-153",
    "addr:postcode":"2094",
    "addr:street":"Sydney Rd",
    "iso:country":"AU",
    "sg:address":"9/ 149-153 Sydney Rd",
    "sg:city":"Fairlight",
    "sg:classifiers":[
        {
            "category":"Health Services",
            "subcategory":"Doctor",
            "type":"Services"
        }
    ],
    "sg:phone":"+61 2 9907 7561",
    "sg:postcode":"2094",
    "sg:province":"NSW",
    "sg:tags":[
        "medical",
        "practitioner"
    ],
    "wof:name":"Lachter Bruce D Dr",
    "wof:placetype":"venue"
},
  "geometry": {"coordinates":[151.275665283,-33.7958374023],"type":"Point"}
}