{
  "type": "Feature",
  "properties": {
    "addr:full":"Shop 203 West Lakes Mall West Lakes SA 5021",
    "addr:housenumber":"203",
    "addr:postcode":"5021",
    "addr:street":"West",
    "iso:country":"AU",
    "sg:address":"Shop 203 West Lakes Mall",
    "sg:city":"West Lakes",
    "sg:classifiers":[
        {
            "category":"Food & Beverages",
            "subcategory":"Fruits & Vegetables",
            "type":"Retail Goods"
        }
    ],
    "sg:phone":"+61 8 8356 5378",
    "sg:postcode":"5021",
    "sg:province":"SA",
    "sg:tags":[
        "greengrocer",
        "fruiterer"
    ],
    "wof:name":"Adams Apple West Lakes",
    "wof:placetype":"venue"
},
  "geometry": {"coordinates":[138.49130249000001,-34.8754615784],"type":"Point"}
}