{
  "type": "Feature",
  "properties": {
    "iso:country":"AU",
    "sg:address":"54 Armstrong St",
    "sg:city":"North Rockhampton",
    "sg:classifiers":[
        {
            "category":"Health Services",
            "subcategory":"Doctor",
            "type":"Services"
        }
    ],
    "sg:phone":"+61 7 4927 4555",
    "sg:postcode":"4701",
    "sg:province":"QLD",
    "sg:tags":[
        "medical",
        "practitioner"
    ],
    "wof:name":"Power P A",
    "wof:placetype":"venue"
},
  "geometry": {"coordinates":[150.52259826700001,-23.3666954041],"type":"Point"}
}