{
  "type": "Feature",
  "properties": {
    "iso:country":"AU",
    "sg:address":"805 Old Cleveland Rd",
    "sg:city":"Carina",
    "sg:classifiers":[
        {
            "category":"Health Services",
            "subcategory":"Doctor",
            "type":"Services"
        }
    ],
    "sg:phone":"+61 7 3398 8800",
    "sg:postcode":"4152",
    "sg:province":"QLD",
    "sg:tags":[
        "medical",
        "practitioner"
    ],
    "wof:name":"O'Sullivan Maureen",
    "wof:placetype":"venue"
},
  "geometry": {"coordinates":[153.09092712399999,-27.4956169128],"type":"Point"}
}