{
  "type": "Feature",
  "properties": {
    "iso:country":"AU",
    "sg:address":"U3/ 34 Curtis Rd",
    "sg:city":"Mulgrave",
    "sg:classifiers":[
        {
            "category":"Train Station",
            "subcategory":"Rail",
            "type":"Transportation"
        }
    ],
    "sg:phone":"+61 2 4587 9035",
    "sg:postcode":"2756",
    "sg:province":"NSW",
    "sg:tags":[
        "marine",
        "engineer"
    ],
    "wof:name":"Indy Marine",
    "wof:placetype":"venue"
},
  "geometry": {"coordinates":[150.83070373499999,-33.6234931946],"type":"Point"}
}