{
  "type": "Feature",
  "properties": {
    "iso:country":"AU",
    "sg:address":"Shop 2/ 26 Ulong St",
    "sg:city":"Griffith",
    "sg:classifiers":[
        {
            "category":"Banks & Credit Unions",
            "subcategory":"Financial Services",
            "type":"Services"
        }
    ],
    "sg:phone":"+61 2 6962 1537",
    "sg:postcode":"2680",
    "sg:province":"NSW",
    "sg:tags":[
        "loan",
        "finance",
        "mortgage"
    ],
    "wof:name":"Integral Finance Solutions",
    "wof:placetype":"venue"
},
  "geometry": {"coordinates":[146.05249000000001,-34.290234],"type":"Point"}
}