{
  "type": "Feature",
  "properties": {
    "addr:full":"157 Numurkah Rd Shepparton VIC 3630",
    "addr:housenumber":"157",
    "addr:postcode":"3630",
    "addr:street":"Numurkah Rd",
    "iso:country":"AU",
    "sg:address":"157 Numurkah Rd",
    "sg:city":"Shepparton",
    "sg:classifiers":[
        {
            "category":"Retail",
            "subcategory":"Auto Repair",
            "type":"Services"
        }
    ],
    "sg:phone":"+61 3 5822 1242",
    "sg:postcode":"3630",
    "sg:province":"VIC",
    "sg:tags":[
        "beater",
        "painter",
        "panel"
    ],
    "wof:name":"Frankys Paint & Panel",
    "wof:placetype":"venue"
},
  "geometry": {"coordinates":[145.402420044,-36.3561248779],"type":"Point"}
}