{
  "type": "Feature",
  "properties": {
    "addr:full":"242 South St White Gum Valley WA 6162",
    "addr:housenumber":"242",
    "addr:postcode":"6162",
    "addr:street":"South St",
    "iso:country":"AU",
    "sg:address":"242 South St",
    "sg:city":"White Gum Valley",
    "sg:classifiers":[
        {
            "category":"Social Services",
            "subcategory":"Child Care",
            "type":"Services"
        }
    ],
    "sg:phone":"+61 8 9335 6941",
    "sg:postcode":"6162",
    "sg:province":"WA",
    "wof:name":"Little Tykes Early Learning Centre",
    "wof:placetype":"venue"
},
  "geometry": {"coordinates":[115.774452,-32.063183],"type":"Point"}
}