{
  "type": "Feature",
  "properties": {
    "iso:country":"AU",
    "sg:address":"U 4/ 176 Camboon Rd",
    "sg:city":"Malaga",
    "sg:classifiers":[
        {
            "category":"Retail",
            "subcategory":"Auto Repair",
            "type":"Services"
        }
    ],
    "sg:phone":"+61 8 9248 4334",
    "sg:postcode":"6090",
    "sg:province":"WA",
    "sg:tags":[
        "repairer",
        "motor",
        "engineer"
    ],
    "wof:name":"T .I. M. Automotive Services",
    "wof:placetype":"venue"
},
  "geometry": {"coordinates":[115.891281128,-31.8481369019],"type":"Point"}
}