{
  "type": "Feature",
  "properties": {
    "iso:country":"AU",
    "sg:address":"6b Watton St",
    "sg:city":"Werribee",
    "sg:classifiers":[
        {
            "category":"Health Services",
            "subcategory":"Doctor",
            "type":"Services"
        }
    ],
    "sg:phone":"+61 3 9742 6288",
    "sg:postcode":"3030",
    "sg:province":"VIC",
    "sg:tags":[
        "medical",
        "practitioner"
    ],
    "wof:name":"Supercare Family Medical Centres Group",
    "wof:placetype":"venue"
},
  "geometry": {"coordinates":[144.662827,-37.900055],"type":"Point"}
}