{
  "type": "Feature",
  "properties": {
    "addr:full":"Suite 9 2 Ilkeston Pl Mirrabooka WA 6061",
    "addr:housenumber":"2",
    "addr:postcode":"6061",
    "addr:street":"Pl",
    "iso:country":"AU",
    "sg:address":"Suite 9 2 Ilkeston Pl",
    "sg:city":"Mirrabooka",
    "sg:classifiers":[
        {
            "category":"Health Services",
            "subcategory":"Health Practitioner",
            "type":"Services"
        }
    ],
    "sg:phone":"+61 8 9344 5088",
    "sg:postcode":"6061",
    "sg:province":"WA",
    "sg:tags":[
        "dietitian"
    ],
    "wof:name":"Thompson Denise (APD)",
    "wof:placetype":"venue"
},
  "geometry": {"coordinates":[115.85874176,-31.8711357117],"type":"Point"}
}