{
  "type": "Feature",
  "properties": {
    "iso:country":"AU",
    "sg:address":"19 Kirikee St",
    "sg:city":"Ferny Grove",
    "sg:classifiers":[
        {
            "category":"Building & Trades",
            "subcategory":"Plumbing",
            "type":"Services"
        }
    ],
    "sg:phone":"+61 417 639 119",
    "sg:postcode":"4055",
    "sg:province":"QLD",
    "sg:tags":[
        "plumber",
        "gasfitters"
    ],
    "wof:name":"M & I Bowen Enterprises",
    "wof:placetype":"venue"
},
  "geometry": {"coordinates":[152.92655944800001,-27.3989601135],"type":"Point"}
}