{
  "type": "Feature",
  "properties": {
    "addr:full":"25 Davis St Berrigan NSW 2712",
    "addr:housenumber":"25",
    "addr:postcode":"2712",
    "addr:street":"Davis St",
    "iso:country":"AU",
    "sg:address":"25 Davis St",
    "sg:city":"Berrigan",
    "sg:classifiers":[
        {
            "category":"Farming",
            "subcategory":"Farm",
            "type":"Manufacturing & Wholesale Goods"
        }
    ],
    "sg:phone":"+61 3 5885 2215",
    "sg:postcode":"2712",
    "sg:province":"NSW",
    "sg:tags":[
        "farmer"
    ],
    "wof:name":"Ackerly J W",
    "wof:placetype":"venue"
},
  "geometry": {"coordinates":[145.810836792,-35.659034729],"type":"Point"}
}