{
  "type": "Feature",
  "properties": {
    "addr:full":"25 South Steyne Manly NSW 2095",
    "addr:housenumber":"25",
    "addr:postcode":"2095",
    "addr:street":"South Steyne",
    "iso:country":"AU",
    "sg:address":"25 South Steyne",
    "sg:city":"Manly",
    "sg:classifiers":[
        {
            "category":"Food & Beverages",
            "subcategory":"Meat & Fish",
            "type":"Retail Goods"
        }
    ],
    "sg:phone":"+61 2 9976 3777",
    "sg:postcode":"2095",
    "sg:province":"NSW",
    "sg:tags":[
        "seafood"
    ],
    "wof:name":"Manly Fish Market & Cafe",
    "wof:placetype":"venue"
},
  "geometry": {"coordinates":[151.28965759299999,-33.7995262146],"type":"Point"}
}