{
  "type": "Feature",
  "properties": {
    "addr:full":"U2/ 18 Ricketty St Mascot NSW 2020",
    "addr:postcode":"2020",
    "addr:street":"U2 / 18 Ricketty St",
    "iso:country":"AU",
    "sg:address":"U2/ 18 Ricketty St",
    "sg:city":"Mascot",
    "sg:classifiers":[
        {
            "category":"Professional",
            "subcategory":"Business Services",
            "type":"Services"
        }
    ],
    "sg:phone":"+61 2 9317 2422",
    "sg:postcode":"2020",
    "sg:province":"NSW",
    "sg:tags":[
        "management",
        "event"
    ],
    "wof:name":"Bnt Management Pty Ltd",
    "wof:placetype":"venue"
},
  "geometry": {"coordinates":[151.18365478499999,-33.9216041565],"type":"Point"}
}