{
  "type": "Feature",
  "properties": {
    "addr:full":"299 Brisbane Water Drv Gosford West NSW 2250",
    "addr:housenumber":"299",
    "addr:postcode":"2250",
    "addr:street":"Brisbane Water Drv",
    "iso:country":"AU",
    "sg:address":"299 Brisbane Water Drv",
    "sg:city":"Gosford West",
    "sg:classifiers":[
        {
            "category":"Shopping",
            "subcategory":"Optical Goods",
            "type":"Retail Goods"
        }
    ],
    "sg:phone":"+61 405 320 851",
    "sg:postcode":"2250",
    "sg:province":"NSW",
    "sg:tags":[
        "dispenser",
        "prescription"
    ],
    "wof:name":"West Gosford Optical Centre",
    "wof:placetype":"venue"
},
  "geometry": {"coordinates":[151.316696167,-33.4278297424],"type":"Point"}
}