{
  "type": "Feature",
  "properties": {
    "addr:full":"1533 Pt Nepean Rd Rosebud West VIC 3940",
    "addr:housenumber":"1533",
    "addr:postcode":"3940",
    "addr:street":"Pt Nepean Rd",
    "iso:country":"AU",
    "sg:address":"1533 Pt Nepean Rd",
    "sg:city":"Rosebud West",
    "sg:classifiers":[
        {
            "category":"Health Services",
            "subcategory":"Doctor",
            "type":"Services"
        }
    ],
    "sg:phone":"+61 3 5986 2155",
    "sg:postcode":"3940",
    "sg:province":"VIC",
    "sg:tags":[
        "medical",
        "practitioner"
    ],
    "wof:name":"Paterson I W Dr",
    "wof:placetype":"venue"
},
  "geometry": {"coordinates":[144.883712769,-38.3617095947],"type":"Point"}
}