{
  "type": "Feature",
  "properties": {
    "iso:country":"AU",
    "sg:address":"160 Montague St",
    "sg:city":"South Melbourne",
    "sg:classifiers":[
        {
            "category":"Retail",
            "subcategory":"Auto Repair",
            "type":"Services"
        }
    ],
    "sg:phone":"+61 3 9699 2800",
    "sg:postcode":"3205",
    "sg:province":"VIC",
    "sg:tags":[
        "muffler",
        "exhaust",
        "system"
    ],
    "wof:name":"Midas Mufflers",
    "wof:placetype":"venue"
},
  "geometry": {"coordinates":[144.951523,-37.832344],"type":"Point"}
}