{
  "type": "Feature",
  "properties": {
    "addr:full":"1013 Mair St Ballarat Central VIC 3350",
    "addr:housenumber":"1013",
    "addr:postcode":"3350",
    "addr:street":"Mair St",
    "iso:country":"AU",
    "sg:address":"1013 Mair St",
    "sg:city":"Ballarat Central",
    "sg:classifiers":[
        {
            "category":"Health Services",
            "subcategory":"Doctor",
            "type":"Services"
        }
    ],
    "sg:phone":"+61 3 5331 2221",
    "sg:postcode":"3350",
    "sg:province":"VIC",
    "sg:tags":[
        "medical",
        "practitioner"
    ],
    "wof:name":"Van Den Broek J Dr",
    "wof:placetype":"venue"
},
  "geometry": {"coordinates":[143.84515400000001,-37.558365],"type":"Point"}
}