{
  "type": "Feature",
  "properties": {
    "addr:full":"Bonney Pl 318 Junction Rd Clayfield QLD 4011",
    "addr:housenumber":"318",
    "addr:postcode":"4011",
    "addr:street":"Junction Rd",
    "iso:country":"AU",
    "sg:address":"Bonney Pl 318 Junction Rd",
    "sg:city":"Clayfield",
    "sg:classifiers":[
        {
            "category":"Personal",
            "subcategory":"Nail Salon",
            "type":"Services"
        }
    ],
    "sg:phone":"+61 7 3857 5755",
    "sg:postcode":"4011",
    "sg:province":"QLD",
    "sg:tags":[
        "artificial"
    ],
    "wof:name":"Aspinell Beauty Clinic",
    "wof:placetype":"venue"
},
  "geometry": {"coordinates":[153.048508,-27.414764],"type":"Point"}
}