{
  "type": "Feature",
  "properties": {
    "addr:full":"330c Miller St North Sydney NSW 2060",
    "addr:housenumber":"330c",
    "addr:postcode":"2060",
    "addr:street":"Miller St",
    "iso:country":"AU",
    "sg:address":"330c Miller St",
    "sg:city":"North Sydney",
    "sg:classifiers":[
        {
            "category":"Professional",
            "subcategory":"Printing & Photocopies",
            "type":"Services"
        }
    ],
    "sg:phone":"+61 2 9956 6544",
    "sg:postcode":"2060",
    "sg:province":"NSW",
    "sg:tags":[
        "photocopier"
    ],
    "wof:name":"Copyon Business Systems Pty Ltd",
    "wof:placetype":"venue"
},
  "geometry": {"coordinates":[151.20895385700001,-33.8282432556],"type":"Point"}
}