{
  "type": "Feature",
  "properties": {
    "addr:full":"336 Springvale Rd Springvale VIC 3171",
    "addr:housenumber":"336",
    "addr:postcode":"3171",
    "addr:street":"Springvale Rd",
    "iso:country":"AU",
    "sg:address":"336 Springvale Rd",
    "sg:city":"Springvale",
    "sg:classifiers":[
        {
            "category":"Education",
            "subcategory":"University",
            "type":"Public Place"
        }
    ],
    "sg:phone":"+61 3 9239 5164",
    "sg:postcode":"3171",
    "sg:province":"VIC",
    "sg:tags":[
        "educational",
        "organisation",
        "cultural"
    ],
    "wof:name":"City Of Greater Dandenong Libraries",
    "wof:placetype":"venue"
},
  "geometry": {"coordinates":[145.15130615199999,-37.9560966492],"type":"Point"}
}