{
  "type": "Feature",
  "properties": {
    "iso:country":"AU",
    "sg:address":"63 Devon Hills Rd",
    "sg:city":"Devon Hills",
    "sg:classifiers":[
        {
            "category":"Building & Trades",
            "subcategory":"Construction",
            "type":"Services"
        }
    ],
    "sg:phone":"+61 3 6398 1800",
    "sg:postcode":"7300",
    "sg:province":"TAS",
    "sg:tags":[
        "fencing",
        "contractor"
    ],
    "wof:name":"Stemic Fencing",
    "wof:placetype":"venue"
},
  "geometry": {"coordinates":[147.19038399999999,-41.556999],"type":"Point"}
}