{
  "type": "Feature",
  "properties": {
    "addr:full":"Poland St Hopevale QLD 4871",
    "addr:postcode":"4871",
    "addr:street":"Poland St",
    "iso:country":"AU",
    "sg:address":"Poland St",
    "sg:city":"Hopevale",
    "sg:classifiers":[
        {
            "category":"Education",
            "subcategory":"Kindergarten",
            "type":"Public Place"
        }
    ],
    "sg:phone":"+61 7 4060 9109",
    "sg:postcode":"4871",
    "sg:province":"QLD",
    "sg:tags":[
        "pre-schools"
    ],
    "wof:name":"George Bowen Memorial Kindergarten",
    "wof:placetype":"venue"
},
  "geometry": {"coordinates":[145.10801696799999,-15.2948732376],"type":"Point"}
}