{
  "type": "Feature",
  "properties": {
    "iso:country":"AU",
    "sg:address":"85 Monfarville St",
    "sg:city":"St Marys",
    "sg:classifiers":[
        {
            "category":"Communications",
            "subcategory":"Film & Video Production",
            "type":"Services"
        }
    ],
    "sg:phone":"+61 2 9623 4891",
    "sg:postcode":"2760",
    "sg:province":"NSW",
    "sg:tags":[
        "dvd",
        "library"
    ],
    "wof:name":"Civic Video Pty Ltd",
    "wof:placetype":"venue"
},
  "geometry": {"coordinates":[150.775558472,-33.7783126831],"type":"Point"}
}