{
  "type": "Feature",
  "properties": {
    "iso:country":"AU",
    "sg:address":"10 Westminster Ave",
    "sg:city":"Dandenong North",
    "sg:classifiers":[
        {
            "category":"Building & Trades",
            "subcategory":"Plumbing",
            "type":"Services"
        }
    ],
    "sg:phone":"+61 414 738 506",
    "sg:postcode":"3175",
    "sg:province":"VIC",
    "sg:tags":[
        "plumber",
        "gasfitters"
    ],
    "wof:name":"Royal Plumbing & Gasfitting",
    "wof:placetype":"venue"
},
  "geometry": {"coordinates":[145.21861267099999,-37.9489784241],"type":"Point"}
}