{
  "type": "Feature",
  "properties": {
    "addr:full":"283 Henley Beach Rd Brooklyn Park SA 5032",
    "addr:housenumber":"283",
    "addr:postcode":"5032",
    "addr:street":"Henley Beach Rd",
    "iso:country":"AU",
    "sg:address":"283 Henley Beach Rd",
    "sg:city":"Brooklyn Park",
    "sg:classifiers":[
        {
            "category":"Autos & Motor Vehicles",
            "subcategory":"Auto Supplies",
            "type":"Retail Goods"
        }
    ],
    "sg:phone":"+61 8 8352 2622",
    "sg:postcode":"5032",
    "sg:province":"SA",
    "sg:tags":[
        "battery",
        "automotive"
    ],
    "wof:name":"Bob Jane T-Marts",
    "wof:placetype":"venue"
},
  "geometry": {"coordinates":[138.54951477,-34.924861908],"type":"Point"}
}