{
  "type": "Feature",
  "properties": {
    "addr:full":"99 Valhalla St Sunnybank QLD 4109",
    "addr:housenumber":"99",
    "addr:postcode":"4109",
    "addr:street":"Valhalla St",
    "iso:country":"AU",
    "sg:address":"99 Valhalla St",
    "sg:city":"Sunnybank",
    "sg:classifiers":[
        {
            "category":"Professional",
            "subcategory":"Engineering",
            "type":"Services"
        }
    ],
    "sg:phone":"+61 7 3344 3670",
    "sg:postcode":"4109",
    "sg:province":"QLD",
    "sg:tags":[
        "electrical",
        "engineer"
    ],
    "wof:name":"Tree W E & S J",
    "wof:placetype":"venue"
},
  "geometry": {"coordinates":[153.06877136200001,-27.5758934021],"type":"Point"}
}