{
  "type": "Feature",
  "properties": {
    "addr:full":"177 Blackshaws Rd Newport VIC 3015",
    "addr:housenumber":"177",
    "addr:postcode":"3015",
    "addr:street":"Blackshaws Rd",
    "iso:country":"AU",
    "sg:address":"177 Blackshaws Rd",
    "sg:city":"Newport",
    "sg:classifiers":[
        {
            "category":"Real Estate",
            "subcategory":"Surveying",
            "type":"Services"
        }
    ],
    "sg:phone":"+61 3 9399 2030",
    "sg:postcode":"3015",
    "sg:province":"VIC",
    "sg:tags":[
        "building",
        "surveyor"
    ],
    "wof:name":"Fire Safe Building Pty Ltd",
    "wof:placetype":"venue"
},
  "geometry": {"coordinates":[144.86898803700001,-37.8335494995],"type":"Point"}
}