{
  "type": "Feature",
  "properties": {
    "iso:country":"AU",
    "sg:address":"15 Young St",
    "sg:city":"Port Augusta",
    "sg:classifiers":[
        {
            "category":"Retail",
            "subcategory":"Auto Repair",
            "type":"Services"
        }
    ],
    "sg:phone":"+61 8 8642 2786",
    "sg:postcode":"5700",
    "sg:province":"SA",
    "sg:tags":[
        "repairer",
        "motor",
        "engineer"
    ],
    "wof:name":"Augusta 4WD Service Centre",
    "wof:placetype":"venue"
},
  "geometry": {"coordinates":[137.76463317899999,-32.4893531799],"type":"Point"}
}