{
  "type": "Feature",
  "properties": {
    "iso:country":"AU",
    "sg:address":"152 Lime Ave",
    "sg:city":"Mildura",
    "sg:classifiers":[
        {
            "category":"Banks & Credit Unions",
            "subcategory":"Investment Brokerage",
            "type":"Services"
        }
    ],
    "sg:phone":"+61 418 346 118",
    "sg:postcode":"3500",
    "sg:province":"VIC",
    "wof:name":"Shugg Philip",
    "wof:placetype":"venue"
},
  "geometry": {"coordinates":[142.15591430699999,-34.1873168945],"type":"Point"}
}