{
  "type": "Feature",
  "properties": {
    "addr:full":"5/ 103 Neale St Bendigo VIC 3550",
    "addr:housenumber":"/ 103",
    "addr:postcode":"3550",
    "addr:street":"Neale St",
    "iso:country":"AU",
    "sg:address":"5/ 103 Neale St",
    "sg:city":"Bendigo",
    "sg:classifiers":[
        {
            "category":"Recreation",
            "type":"Entertainment"
        }
    ],
    "sg:phone":"+61 3 5442 1608",
    "sg:postcode":"3550",
    "sg:province":"VIC",
    "sg:tags":[
        "club",
        "card"
    ],
    "wof:name":"Bendigo Bridge Club",
    "wof:placetype":"venue"
},
  "geometry": {"coordinates":[144.293823242,-36.7699775696],"type":"Point"}
}