{
  "type": "Feature",
  "properties": {
    "iso:country":"AU",
    "sg:address":"1/ 30 Foundry Rd",
    "sg:city":"Seven Hills",
    "sg:classifiers":[
        {
            "category":"Real Estate",
            "subcategory":"Real Estate Agent",
            "type":"Services"
        }
    ],
    "sg:phone":"+61 2 9838 9588",
    "sg:postcode":"2147",
    "sg:province":"NSW",
    "sg:tags":[
        "export"
    ],
    "wof:name":"Aestar Australia Pty Ltd",
    "wof:placetype":"venue"
},
  "geometry": {"coordinates":[150.95512390100001,-33.7702865601],"type":"Point"}
}