{
  "type": "Feature",
  "properties": {
    "addr:full":"121 Ruby St Caboolture QLD 4510",
    "addr:housenumber":"121",
    "addr:postcode":"4510",
    "addr:street":"Ruby St",
    "iso:country":"AU",
    "sg:address":"121 Ruby St",
    "sg:city":"Caboolture",
    "sg:classifiers":[
        {
            "category":"Professional",
            "subcategory":"Accounting & Tax Preparation",
            "type":"Services"
        }
    ],
    "sg:phone":"+61 7 5495 1133",
    "sg:postcode":"4510",
    "sg:province":"QLD",
    "sg:tags":[
        "consultant",
        "taxation"
    ],
    "wof:name":"Brander Leigh M",
    "wof:placetype":"venue"
},
  "geometry": {"coordinates":[152.95343,-27.067699],"type":"Point"}
}