{
  "type": "Feature",
  "properties": {
    "addr:full":"90 Auburn St Goulburn NSW 2580",
    "addr:housenumber":"90",
    "addr:postcode":"2580",
    "addr:street":"Auburn St",
    "iso:country":"AU",
    "sg:address":"90 Auburn St",
    "sg:city":"Goulburn",
    "sg:classifiers":[
        {
            "category":"Shopping",
            "subcategory":"Computers & Home Electronics",
            "type":"Retail Goods"
        }
    ],
    "sg:phone":"+61 2 4822 1288",
    "sg:postcode":"2580",
    "sg:province":"NSW",
    "sg:tags":[
        "equipment",
        "part",
        "electronic"
    ],
    "wof:name":"Goulburn Electronics",
    "wof:placetype":"venue"
},
  "geometry": {"coordinates":[149.71592712399999,-34.7573547363],"type":"Point"}
}