{
  "type": "Feature",
  "properties": {
    "addr:full":"121 Nicholas Rd Wanneroo WA 6065",
    "addr:housenumber":"121",
    "addr:postcode":"6065",
    "addr:street":"Nicholas Rd",
    "iso:country":"AU",
    "sg:address":"121 Nicholas Rd",
    "sg:city":"Wanneroo",
    "sg:classifiers":[
        {
            "category":"Building & Trades",
            "subcategory":"Construction",
            "type":"Services"
        }
    ],
    "sg:phone":"+61 8 9405 2584",
    "sg:postcode":"6065",
    "sg:province":"WA",
    "sg:tags":[
        "earth",
        "excavating",
        "moving",
        "contractor"
    ],
    "wof:name":"Wanneroo Slashing Contractors",
    "wof:placetype":"venue"
},
  "geometry": {"coordinates":[115.82543182400001,-31.7699642181],"type":"Point"}
}