{
  "type": "Feature",
  "properties": {
    "addr:full":"Suite 120/ 243 Pyrmont St Darling Harbour NSW 2000",
    "addr:housenumber":"/ 243",
    "addr:postcode":"2000",
    "addr:street":"Pyrmont St",
    "iso:country":"AU",
    "sg:address":"Suite 120/ 243 Pyrmont St",
    "sg:city":"Darling Harbour",
    "sg:classifiers":[
        {
            "category":"Professional",
            "subcategory":"Employment Agencies",
            "type":"Services"
        }
    ],
    "sg:phone":"+61 2 9692 9099",
    "sg:postcode":"2000",
    "sg:province":"NSW",
    "wof:name":"Butler & Blackberry",
    "wof:placetype":"venue"
},
  "geometry": {"coordinates":[151.19711303700001,-33.8734931946],"type":"Point"}
}