{
  "type": "Feature",
  "properties": {
    "addr:full":"Unit 4/ 2 McPherson Cct Pambula NSW 2549",
    "addr:housenumber":"2",
    "addr:postcode":"2549",
    "addr:street":"Mcpherson Cct",
    "iso:country":"AU",
    "sg:address":"Unit 4/ 2 McPherson Cct",
    "sg:city":"Pambula",
    "sg:classifiers":[
        {
            "category":"Retail",
            "subcategory":"Laundry & Dry Cleaning",
            "type":"Services"
        }
    ],
    "sg:phone":"+61 2 6495 6599",
    "sg:postcode":"2549",
    "sg:province":"NSW",
    "wof:name":"South Coast Linen Service",
    "wof:placetype":"venue"
},
  "geometry": {"coordinates":[149.88670349099999,-36.9357414246],"type":"Point"}
}