{
  "type": "Feature",
  "properties": {
    "iso:country":"AU",
    "sg:address":"Unit 10, 10- 12 George St",
    "sg:city":"Leichhardt",
    "sg:classifiers":[
        {
            "category":"Professional",
            "subcategory":"Employment Agencies",
            "type":"Services"
        }
    ],
    "sg:phone":"+61 2 9331 5550",
    "sg:postcode":"2040",
    "sg:province":"NSW",
    "sg:tags":[
        "model"
    ],
    "wof:name":"Deveaux",
    "wof:placetype":"venue"
},
  "geometry": {"coordinates":[151.14856,-33.888874],"type":"Point"}
}