{
  "type": "Feature",
  "properties": {
    "iso:country":"AU",
    "sg:address":"160 Station Rd",
    "sg:city":"Yeerongpilly",
    "sg:classifiers":[
        {
            "category":"Home & Garden",
            "subcategory":"Building Materials",
            "type":"Retail Goods"
        }
    ],
    "sg:phone":"+61 7 3868 3088",
    "sg:postcode":"4105",
    "sg:province":"QLD",
    "sg:tags":[
        "fitting",
        "door"
    ],
    "wof:name":"Colonial Warehouse",
    "wof:placetype":"venue"
},
  "geometry": {"coordinates":[153.01556396500001,-27.528301239],"type":"Point"}
}