{
  "type": "Feature",
  "properties": {
    "addr:full":"6 Walters St Portsmith QLD 4870",
    "addr:housenumber":"6",
    "addr:postcode":"4870",
    "addr:street":"Walters St Portsmith",
    "iso:country":"AU",
    "sg:address":"6 Walters St",
    "sg:city":"Portsmith",
    "sg:classifiers":[
        {
            "category":"Manufacturing",
            "subcategory":"Metals",
            "type":"Manufacturing & Wholesale Goods"
        }
    ],
    "sg:phone":"+61 7 4035 1506",
    "sg:postcode":"4870",
    "sg:province":"QLD",
    "sg:tags":[
        "steel",
        "fabricator",
        "mfrs"
    ],
    "wof:name":"Cairns Steel Fabricators Pty Ltd",
    "wof:placetype":"venue"
},
  "geometry": {"coordinates":[145.76731872600001,-16.9482688904],"type":"Point"}
}