{
  "type": "Feature",
  "properties": {
    "addr:full":"Shop 12 Beaumont St Islington NSW 2296",
    "addr:housenumber":"shop 12",
    "addr:postcode":"2296",
    "addr:street":"Beaumont St",
    "iso:country":"AU",
    "sg:address":"Shop 12 Beaumont St",
    "sg:city":"Islington",
    "sg:classifiers":[
        {
            "category":"Personal",
            "subcategory":"Adult",
            "type":"Services"
        }
    ],
    "sg:phone":"+61 403 410 055",
    "sg:postcode":"2296",
    "sg:province":"NSW",
    "sg:tags":[
        "entertainment"
    ],
    "wof:name":"Ain&#039;t No Angels",
    "wof:placetype":"venue"
},
  "geometry": {"coordinates":[151.74919128400001,-32.9175643921],"type":"Point"}
}