{
  "type": "Feature",
  "properties": {
    "iso:country":"AU",
    "sg:address":"1a Deloraine Rd",
    "sg:city":"Edwardstown",
    "sg:classifiers":[
        {
            "category":"Manufacturing",
            "subcategory":"Paper Products",
            "type":"Manufacturing & Wholesale Goods"
        }
    ],
    "sg:phone":"+61 8 8276 6766",
    "sg:postcode":"5039",
    "sg:province":"SA",
    "sg:tags":[
        "metal",
        "non-ferrous",
        "foundry"
    ],
    "wof:name":"Bridge Castings Pty Ltd",
    "wof:placetype":"venue"
},
  "geometry": {"coordinates":[138.574295044,-34.9875106812],"type":"Point"}
}