{
  "type": "Feature",
  "properties": {
    "addr:full":"PO Box 1496 Wangara DC WA 6947",
    "addr:postcode":"6947",
    "iso:country":"AU",
    "sg:address":"PO Box 1496",
    "sg:city":"Wangara DC",
    "sg:classifiers":[
        {
            "category":"Building & Trades",
            "subcategory":"Landscaping Services",
            "type":"Services"
        }
    ],
    "sg:phone":"+61 8 9405 8188",
    "sg:postcode":"6947",
    "sg:province":"WA",
    "sg:tags":[
        "stump",
        "tree",
        "felling",
        "removal"
    ],
    "wof:name":"Tree Amigos Tree Surgeons",
    "wof:placetype":"venue"
},
  "geometry": {"coordinates":[115.83036041299999,-31.7966709137],"type":"Point"}
}