{
  "type": "Feature",
  "properties": {
    "addr:full":"15 Crittenden Rd Findon SA 5023",
    "addr:housenumber":"15",
    "addr:postcode":"5023",
    "addr:street":"Crittenden Rd",
    "iso:country":"AU",
    "sg:address":"15 Crittenden Rd",
    "sg:city":"Findon",
    "sg:classifiers":[
        {
            "category":"Building & Trades",
            "subcategory":"Equipment Rental",
            "type":"Services"
        }
    ],
    "sg:phone":"+61 8 8243 1506",
    "sg:postcode":"5023",
    "sg:province":"SA",
    "sg:tags":[
        "party",
        "hire"
    ],
    "wof:name":"Baked Potatoes By Michael",
    "wof:placetype":"venue"
},
  "geometry": {"coordinates":[138.54423523,-34.9035720825],"type":"Point"}
}