{
  "type": "Feature",
  "properties": {
    "iso:country":"AU",
    "sg:address":"67 Main St",
    "sg:city":"Mornington",
    "sg:classifiers":[
        {
            "category":"Cafe",
            "type":"Food & Drink"
        }
    ],
    "sg:phone":"+61 3 5975 7877",
    "sg:postcode":"3931",
    "sg:province":"VIC",
    "wof:name":"Bottom Of The Harbour Seafoods",
    "wof:placetype":"venue"
},
  "geometry": {"coordinates":[145.03791809099999,-38.2188911438],"type":"Point"}
}