{
  "type": "Feature",
  "properties": {
    "iso:country":"AU",
    "sg:address":"216 Eulgul St",
    "sg:city":"Dundowran",
    "sg:classifiers":[
        {
            "category":"Professional",
            "subcategory":"Art Services",
            "type":"Services"
        }
    ],
    "sg:phone":"+61 407 037 722",
    "sg:postcode":"4655",
    "sg:province":"QLD",
    "sg:tags":[
        "decorator",
        "painter"
    ],
    "wof:name":"Matt Thompson Painter & Decorator",
    "wof:placetype":"venue"
},
  "geometry": {"coordinates":[152.766983,-25.284361],"type":"Point"}
}