{
  "type": "Feature",
  "properties": {
    "addr:full":"51 Underwood Rd Forster NSW 2428",
    "addr:housenumber":"51",
    "addr:postcode":"2428",
    "addr:street":"Underwood Rd",
    "iso:country":"AU",
    "sg:address":"51 Underwood Rd",
    "sg:city":"Forster",
    "sg:classifiers":[
        {
            "category":"Farming",
            "subcategory":"Fish & Marine Products",
            "type":"Manufacturing & Wholesale Goods"
        }
    ],
    "sg:phone":"+61 2 6554 8251",
    "sg:postcode":"2428",
    "sg:province":"NSW",
    "sg:tags":[
        "supplier",
        "oyster",
        "farmer"
    ],
    "wof:name":"Verdich S J",
    "wof:placetype":"venue"
},
  "geometry": {"coordinates":[152.53526299999999,-32.193825],"type":"Point"}
}