{
  "type": "Feature",
  "properties": {
    "addr:full":"7 Anictomatis Rd Berrimah NT 0828",
    "addr:housenumber":"7",
    "addr:postcode":"nt 0828",
    "addr:street":"Anictomatis Rd",
    "iso:country":"AU",
    "sg:address":"7 Anictomatis Rd",
    "sg:city":"Berrimah",
    "sg:classifiers":[
        {
            "category":"Retail",
            "subcategory":"Auto Repair",
            "type":"Services"
        }
    ],
    "sg:phone":"+61 8 8984 3096",
    "sg:postcode":"0828",
    "sg:province":"NT",
    "sg:tags":[
        "recapping",
        "repairing",
        "retreading",
        "tyre"
    ],
    "wof:name":"Bandag",
    "wof:placetype":"venue"
},
  "geometry": {"coordinates":[130.945800781,-12.4436731339],"type":"Point"}
}