{
  "type": "Feature",
  "properties": {
    "addr:full":"105 Lower King Rd Albany WA 6330",
    "addr:housenumber":"105",
    "addr:postcode":"6330",
    "addr:street":"Lower King Rd",
    "iso:country":"AU",
    "sg:address":"105 Lower King Rd",
    "sg:city":"Albany",
    "sg:classifiers":[
        {
            "category":"Home & Garden",
            "subcategory":"Garden Supply",
            "type":"Retail Goods"
        }
    ],
    "sg:phone":"+61 428 464 072",
    "sg:postcode":"6330",
    "sg:province":"WA",
    "sg:tags":[
        "landscape"
    ],
    "wof:name":"Oyster Harbour Landscape Supplies",
    "wof:placetype":"venue"
},
  "geometry": {"coordinates":[117.917678833,-34.9983596802],"type":"Point"}
}