{
  "type": "Feature",
  "properties": {
    "iso:country":"AU",
    "sg:address":"Stirling Centre 54 Sanford St",
    "sg:city":"Geraldton",
    "sg:classifiers":[
        {
            "category":"Shopping",
            "subcategory":"Department Store",
            "type":"Retail Goods"
        }
    ],
    "sg:phone":"+61 8 9921 1444",
    "sg:postcode":"6530",
    "sg:province":"WA",
    "wof:name":"Harris Scarfe Ltd",
    "wof:placetype":"venue"
},
  "geometry": {"coordinates":[114.612579346,-28.7745475769],"type":"Point"}
}