{
  "type": "Feature",
  "properties": {
    "iso:country":"AU",
    "sg:address":"Elgin St",
    "sg:city":"Forbes",
    "sg:classifiers":[
        {
            "category":"Health Services",
            "subcategory":"Doctor",
            "type":"Services"
        }
    ],
    "sg:phone":"+61 2 6851 1300",
    "sg:postcode":"2871",
    "sg:province":"NSW",
    "sg:tags":[
        "medical",
        "practitioner"
    ],
    "wof:name":"Whittaker R G",
    "wof:placetype":"venue"
},
  "geometry": {"coordinates":[148.007553,-33.386311],"type":"Point"}
}