{
  "type": "Feature",
  "properties": {
    "addr:full":"4 Kiernan Pl Kallaroo WA 6025",
    "addr:housenumber":"4",
    "addr:postcode":"6025",
    "addr:street":"Kiernan Pl",
    "iso:country":"AU",
    "sg:address":"4 Kiernan Pl",
    "sg:city":"Kallaroo",
    "sg:classifiers":[
        {
            "category":"Home & Garden",
            "subcategory":"Building Materials",
            "type":"Retail Goods"
        }
    ],
    "sg:phone":"+61 8 9402 9634",
    "sg:postcode":"6025",
    "sg:province":"WA",
    "sg:tags":[
        "shutter",
        "roller",
        "grille"
    ],
    "wof:name":"Country Wide Roller Shutters",
    "wof:placetype":"venue"
},
  "geometry": {"coordinates":[115.74266815199999,-31.7944355011],"type":"Point"}
}