{
  "type": "Feature",
  "properties": {
    "addr:full":"304 Bay Rd Cheltenham VIC 3192",
    "addr:housenumber":"304",
    "addr:postcode":"3192",
    "addr:street":"Bay Rd",
    "iso:country":"AU",
    "sg:address":"304 Bay Rd",
    "sg:city":"Cheltenham",
    "sg:classifiers":[
        {
            "category":"Retail",
            "subcategory":"Auto Repair",
            "type":"Services"
        }
    ],
    "sg:phone":"+61 3 9585 4833",
    "sg:postcode":"3192",
    "sg:province":"VIC",
    "sg:tags":[
        "muffler",
        "exhaust",
        "system"
    ],
    "sg:website":"http://www.bayrdexhaust.com.au",
    "wof:name":"Bay Road Exhaust Centre",
    "wof:placetype":"venue"
},
  "geometry": {"coordinates":[145.039230347,-37.9560317993],"type":"Point"}
}