{
  "type": "Feature",
  "properties": {
    "iso:country":"AU",
    "sg:address":"Unit 6/ 146 Teralba Rd",
    "sg:city":"Adamstown",
    "sg:classifiers":[
        {
            "category":"Education",
            "subcategory":"Special Training",
            "type":"Public Place"
        }
    ],
    "sg:phone":"+61 2 4952 7800",
    "sg:postcode":"2289",
    "sg:province":"NSW",
    "sg:tags":[
        "tuition-educational"
    ],
    "wof:name":"Scholar Mathematics",
    "wof:placetype":"venue"
},
  "geometry": {"coordinates":[151.72525024399999,-32.9318504333],"type":"Point"}
}