{
  "type": "Feature",
  "properties": {
    "addr:full":"72 Bacon St Hindmarsh SA 5007",
    "addr:housenumber":"72",
    "addr:postcode":"5007",
    "addr:street":"Bacon St",
    "iso:country":"AU",
    "sg:address":"72 Bacon St",
    "sg:city":"Hindmarsh",
    "sg:classifiers":[
        {
            "category":"Utilities",
            "subcategory":"Electric",
            "type":"Services"
        }
    ],
    "sg:phone":"+61 8 8340 7740",
    "sg:postcode":"5007",
    "sg:province":"SA",
    "sg:tags":[
        "electrical",
        "contractor"
    ],
    "wof:name":"Emtrol",
    "wof:placetype":"venue"
},
  "geometry": {"coordinates":[138.56634521500001,-34.9100570679],"type":"Point"}
}