{
  "type": "Feature",
  "properties": {
    "addr:full":"Caroline Rd Yahl SA 5291",
    "addr:postcode":"5291",
    "addr:street":"Caroline Rd",
    "iso:country":"AU",
    "sg:address":"Caroline Rd",
    "sg:city":"Yahl",
    "sg:classifiers":[
        {
            "category":"Utilities",
            "subcategory":"Natural Gas",
            "type":"Services"
        }
    ],
    "sg:phone":"+61 8 8725 5046",
    "sg:postcode":"5291",
    "sg:province":"SA",
    "sg:tags":[
        "solid",
        "plasterer"
    ],
    "wof:name":"Days Plastering",
    "wof:placetype":"venue"
},
  "geometry": {"coordinates":[140.836533,-37.863869],"type":"Point"}
}