{
  "type": "Feature",
  "properties": {
    "addr:full":"Concord General Hospital Hospital Rd Concord West NSW 2138",
    "addr:postcode":"2138",
    "addr:street":"Hospital Rd",
    "iso:country":"AU",
    "sg:address":"Concord General Hospital Hospital Rd",
    "sg:city":"Concord West",
    "sg:classifiers":[
        {
            "category":"Organizations",
            "subcategory":"Non-profit Organization",
            "type":"Services"
        }
    ],
    "sg:phone":"+61 2 9743 0396",
    "sg:postcode":"2138",
    "sg:province":"NSW",
    "sg:tags":[
        "support",
        "disability",
        "organisation"
    ],
    "wof:name":"Motor Neurone Disease Research Institute of Australia Inc",
    "wof:placetype":"venue"
},
  "geometry": {"coordinates":[151.08886718799999,-33.8392524719],"type":"Point"}
}