{
  "type": "Feature",
  "properties": {
    "iso:country":"AU",
    "sg:address":"Beach Rd",
    "sg:city":"Parkdale",
    "sg:classifiers":[
        {
            "category":"Recreation",
            "subcategory":"Sailing Club",
            "type":"Entertainment"
        }
    ],
    "sg:phone":"+61 3 9580 2788",
    "sg:postcode":"3195",
    "sg:province":"VIC",
    "sg:tags":[
        "yacht"
    ],
    "wof:name":"Parkdale Yacht Club",
    "wof:placetype":"venue"
},
  "geometry": {"coordinates":[145.07249450699999,-37.9970397949],"type":"Point"}
}