{
  "type": "Feature",
  "properties": {
    "addr:full":"131 Langtree Ave Mildura VIC 3500",
    "addr:housenumber":"131",
    "addr:postcode":"3500",
    "addr:street":"Langtree Ave",
    "iso:country":"AU",
    "sg:address":"131 Langtree Ave",
    "sg:city":"Mildura",
    "sg:classifiers":[
        {
            "category":"Professional",
            "subcategory":"Business Services",
            "type":"Services"
        }
    ],
    "sg:phone":"+61 13 22 15",
    "sg:postcode":"3500",
    "sg:province":"VIC",
    "sg:tags":[
        "small",
        "advisory"
    ],
    "wof:name":"Victorian Business Line",
    "wof:placetype":"venue"
},
  "geometry": {"coordinates":[142.157546997,-34.1872520447],"type":"Point"}
}