{
  "type": "Feature",
  "properties": {
    "iso:country":"AU",
    "sg:address":"Shop 1, 134- 136 Pascoe Vale Rd",
    "sg:city":"Moonee Ponds",
    "sg:classifiers":[
        {
            "category":"Professional",
            "subcategory":"Accounting & Tax Preparation",
            "type":"Services"
        }
    ],
    "sg:phone":"+61 3 9326 0761",
    "sg:postcode":"3039",
    "sg:province":"VIC",
    "sg:tags":[
        "consultant",
        "taxation"
    ],
    "wof:name":"Walsh Philip Patrick",
    "wof:placetype":"venue"
},
  "geometry": {"coordinates":[144.926163,-37.760811],"type":"Point"}
}