{
  "type": "Feature",
  "properties": {
    "addr:full":"44 Heatherton Rd Endeavour Hills VIC 3802",
    "addr:housenumber":"44",
    "addr:postcode":"3802",
    "addr:street":"Heatherton Rd",
    "iso:country":"AU",
    "sg:address":"44 Heatherton Rd",
    "sg:city":"Endeavour Hills",
    "sg:classifiers":[
        {
            "category":"Health Services",
            "subcategory":"Health Practitioner",
            "type":"Services"
        }
    ],
    "sg:phone":"+61 3 9700 1768",
    "sg:postcode":"3802",
    "sg:province":"VIC",
    "sg:tags":[
        "physiotherapist"
    ],
    "wof:name":"Cocking Nicholas",
    "wof:placetype":"venue"
},
  "geometry": {"coordinates":[145.24830627399999,-37.974029541],"type":"Point"}
}