{
  "type": "Feature",
  "properties": {
    "iso:country":"AU",
    "sg:address":"142 Chapel St",
    "sg:city":"St Kilda",
    "sg:classifiers":[
        {
            "category":"Utilities",
            "subcategory":"Cable",
            "type":"Services"
        }
    ],
    "sg:phone":"+61 3 9531 8011",
    "sg:postcode":"3182",
    "sg:province":"VIC",
    "sg:tags":[
        "equipment",
        "meters"
    ],
    "wof:name":"Schmidt Electronic Laboratories Pty Ltd",
    "wof:placetype":"venue"
},
  "geometry": {"coordinates":[144.993286133,-37.8532028198],"type":"Point"}
}