{
  "type": "Feature",
  "properties": {
    "addr:full":"10 Dobell St Mooroolbark VIC 3138",
    "addr:housenumber":"10",
    "addr:postcode":"3138",
    "addr:street":"Dobell St",
    "iso:country":"AU",
    "sg:address":"10 Dobell St",
    "sg:city":"Mooroolbark",
    "sg:classifiers":[
        {
            "category":"Travel",
            "subcategory":"Travel Agent",
            "type":"Entertainment"
        }
    ],
    "sg:phone":"+61 3 9726 6006",
    "sg:postcode":"3138",
    "sg:province":"VIC",
    "sg:tags":[
        "consultant"
    ],
    "wof:name":"Christian Fellowship Tours",
    "wof:placetype":"venue"
},
  "geometry": {"coordinates":[145.323852539,-37.7698478699],"type":"Point"}
}