{
  "type": "Feature",
  "properties": {
    "iso:country":"AU",
    "sg:address":"Fryers Rd",
    "sg:city":"Elphinstone",
    "sg:classifiers":[
        {
            "category":"Building & Trades",
            "subcategory":"Cleaning & Sanitation",
            "type":"Services"
        }
    ],
    "sg:phone":"+61 3 5473 3307",
    "sg:postcode":"3448",
    "sg:province":"VIC",
    "sg:tags":[
        "industrial",
        "commercial",
        "contractor"
    ],
    "wof:name":"Gisborne Cleaning Services",
    "wof:placetype":"venue"
},
  "geometry": {"coordinates":[144.34686279300001,-37.103099823],"type":"Point"}
}