{
  "type": "Feature",
  "properties": {
    "addr:full":"Cnr Duke & Kirchner Sts Grafton NSW 2460",
    "addr:postcode":"2460",
    "iso:country":"AU",
    "sg:address":"Cnr Duke & Kirchner Sts",
    "sg:city":"Grafton",
    "sg:classifiers":[
        {
            "category":"Utilities",
            "subcategory":"Recycling",
            "type":"Services"
        }
    ],
    "sg:phone":"+61 2 6642 6428",
    "sg:postcode":"2460",
    "sg:province":"NSW",
    "wof:name":"Riverside Recycling",
    "wof:placetype":"venue"
},
  "geometry": {"coordinates":[152.947875977,-29.6749668121],"type":"Point"}
}