{
  "type": "Feature",
  "properties": {
    "addr:full":"Unit 4/ 5 Harford St Penrith NSW 2750",
    "addr:postcode":"2750",
    "addr:street":"St",
    "iso:country":"AU",
    "sg:address":"Unit 4/ 5 Harford St",
    "sg:city":"Penrith",
    "sg:classifiers":[
        {
            "category":"Autos & Motor Vehicles",
            "subcategory":"Auto Supplies",
            "type":"Retail Goods"
        }
    ],
    "sg:phone":"+61 2 4732 2626",
    "sg:postcode":"2750",
    "sg:province":"NSW",
    "sg:tags":[
        "part",
        "cycles",
        "accessory"
    ],
    "wof:name":"Teknik",
    "wof:placetype":"venue"
},
  "geometry": {"coordinates":[150.68617248499999,-33.764667511],"type":"Point"}
}