{
  "type": "Feature",
  "properties": {
    "iso:country":"AU",
    "sg:address":"Shop 4, Wellington Way",
    "sg:city":"Strathfieldsaye",
    "sg:classifiers":[
        {
            "category":"Farming",
            "subcategory":"Fish & Marine Products",
            "type":"Manufacturing & Wholesale Goods"
        }
    ],
    "sg:phone":"+61 3 5439 5022",
    "sg:postcode":"3551",
    "sg:province":"VIC",
    "sg:tags":[
        "organic"
    ],
    "wof:name":"Country Feeling Fresh Foods & Vegetables",
    "wof:placetype":"venue"
},
  "geometry": {"coordinates":[144.34147644000001,-36.7959785461],"type":"Point"}
}