{
  "type": "Feature",
  "properties": {
    "addr:full":"Rear 733 High St Thornbury VIC 3071",
    "addr:housenumber":"733",
    "addr:postcode":"3071",
    "addr:street":"High St",
    "iso:country":"AU",
    "sg:address":"Rear 733 High St",
    "sg:city":"Thornbury",
    "sg:classifiers":[
        {
            "category":"Utilities",
            "subcategory":"Telephone",
            "type":"Services"
        }
    ],
    "sg:phone":"+61 1300 566 835",
    "sg:postcode":"3071",
    "sg:province":"VIC",
    "sg:tags":[
        "equipment",
        "system"
    ],
    "wof:name":"Komtel Communications",
    "wof:placetype":"venue"
},
  "geometry": {"coordinates":[145.00042724599999,-37.7586288452],"type":"Point"}
}