{
  "type": "Feature",
  "properties": {
    "addr:full":"236 Mount St Upper Burnie TAS 7320",
    "addr:housenumber":"236",
    "addr:postcode":"7320",
    "addr:street":"Mount St",
    "iso:country":"AU",
    "sg:address":"236 Mount St",
    "sg:city":"Upper Burnie",
    "sg:classifiers":[
        {
            "category":"Sports & Exercise",
            "subcategory":"Gym",
            "type":"Entertainment"
        }
    ],
    "sg:phone":"+61 417 552 939",
    "sg:postcode":"7320",
    "sg:province":"TAS",
    "sg:tags":[
        "personal",
        "trainer",
        "fitness"
    ],
    "wof:name":"Ian Treloar",
    "wof:placetype":"venue"
},
  "geometry": {"coordinates":[145.900757,-41.070522],"type":"Point"}
}