{
  "type": "Feature",
  "properties": {
    "addr:full":"326 Pacific Hwy Hexham NSW 2322",
    "addr:housenumber":"326",
    "addr:postcode":"2322",
    "addr:street":"Pacific Hwy",
    "iso:country":"AU",
    "sg:address":"326 Pacific Hwy",
    "sg:city":"Hexham",
    "sg:classifiers":[
        {
            "category":"Manufacturing",
            "subcategory":"Buildings",
            "type":"Manufacturing & Wholesale Goods"
        }
    ],
    "sg:phone":"+61 2 4028 0111",
    "sg:postcode":"2322",
    "sg:province":"NSW",
    "sg:tags":[
        "transportable",
        "domestic",
        "relocatable"
    ],
    "sg:website":"http://www.newcastlecaravans.com",
    "wof:name":"Newcastle Caravan & Homes",
    "wof:placetype":"venue"
},
  "geometry": {"coordinates":[151.72361755399999,-32.7925186157],"type":"Point"}
}