{
  "type": "Feature",
  "properties": {
    "addr:full":"49 Mt Eliza Way Mt Eliza VIC 3930",
    "addr:housenumber":"49",
    "addr:postcode":"3930",
    "addr:street":"Mt Eliza Way",
    "iso:country":"AU",
    "sg:address":"49 Mt Eliza Way",
    "sg:city":"Mt Eliza",
    "sg:classifiers":[
        {
            "category":"Fast Food",
            "type":"Food & Drink"
        }
    ],
    "sg:phone":"+61 3 9787 3356",
    "sg:postcode":"3930",
    "sg:province":"VIC",
    "sg:tags":[
        "away",
        "take"
    ],
    "wof:name":"Chill Australia",
    "wof:placetype":"venue"
},
  "geometry": {"coordinates":[145.09129333499999,-38.1828918457],"type":"Point"}
}