{
  "type": "Feature",
  "properties": {
    "addr:full":"6/ 34 The Esplanade Paradise Point QLD 4216",
    "addr:housenumber":"/ 34",
    "addr:postcode":"4216",
    "addr:street":"The Esplanade",
    "iso:country":"AU",
    "sg:address":"6/ 34 The Esplanade",
    "sg:city":"Paradise Point",
    "sg:classifiers":[
        {
            "category":"Building & Trades",
            "subcategory":"Construction",
            "type":"Services"
        }
    ],
    "sg:phone":"+61 7 5577 3577",
    "sg:postcode":"4216",
    "sg:province":"QLD",
    "sg:tags":[
        "concrete",
        "contractor"
    ],
    "wof:name":"Procrete",
    "wof:placetype":"venue"
},
  "geometry": {"coordinates":[153.39517211899999,-27.8863334656],"type":"Point"}
}