{
  "type": "Feature",
  "properties": {
    "addr:full":"St Martins Village Field 8 Bungarribee Rd Blacktown NSW 2148",
    "addr:postcode":"2148",
    "addr:street":"Bungarribee Rd",
    "iso:country":"AU",
    "sg:address":"St Martins Village Field 8 Bungarribee Rd",
    "sg:city":"Blacktown",
    "sg:classifiers":[
        {
            "category":"Fast Food",
            "type":"Food & Drink"
        }
    ],
    "sg:phone":"+61 2 9831 7472",
    "sg:postcode":"2148",
    "sg:province":"NSW",
    "sg:tags":[
        "away",
        "take"
    ],
    "wof:name":"Red Rooster",
    "wof:placetype":"venue"
},
  "geometry": {"coordinates":[150.897613525,-33.7762489319],"type":"Point"}
}