{
  "type": "Feature",
  "properties": {
    "addr:full":"27A/ 617 Goodwood Rd Panorama SA 5041",
    "addr:housenumber":"27a / 617",
    "addr:postcode":"5041",
    "addr:street":"Goodwood Rd",
    "iso:country":"AU",
    "sg:address":"27A/ 617 Goodwood Rd",
    "sg:city":"Panorama",
    "sg:classifiers":[
        {
            "category":"Home & Garden",
            "subcategory":"Garden Supply",
            "type":"Retail Goods"
        }
    ],
    "sg:phone":"+61 407 758 633",
    "sg:postcode":"5041",
    "sg:province":"SA",
    "sg:tags":[
        "equipment",
        "hydroponics"
    ],
    "wof:name":"Global Hydroponics",
    "wof:placetype":"venue"
},
  "geometry": {"coordinates":[138.59300200000001,-34.992966],"type":"Point"}
}