{
  "type": "Feature",
  "properties": {
    "addr:full":"149 Therry St Melbourne PLB VIC 3001",
    "addr:housenumber":"149",
    "addr:postcode":"3001",
    "addr:street":"Therry St",
    "iso:country":"AU",
    "sg:address":"149 Therry St",
    "sg:city":"Melbourne PLB",
    "sg:classifiers":[
        {
            "category":"Manufacturing",
            "subcategory":"Soap",
            "type":"Manufacturing & Wholesale Goods"
        }
    ],
    "sg:phone":"+61 3 9329 9913",
    "sg:postcode":"3001",
    "sg:province":"VIC",
    "sg:tags":[
        "detergent"
    ],
    "wof:name":"Victoria Market Soapbox",
    "wof:placetype":"venue"
},
  "geometry": {"coordinates":[144.95820617699999,-37.8077278137],"type":"Point"}
}