{
  "type": "Feature",
  "properties": {
    "iso:country":"AU",
    "sg:address":"Level 3, 11 Bank Pl",
    "sg:city":"Melbourne",
    "sg:classifiers":[
        {
            "category":"Professional",
            "subcategory":"Employment Agencies",
            "type":"Services"
        }
    ],
    "sg:phone":"+61 3 9601 6111",
    "sg:postcode":"3000",
    "sg:province":"VIC",
    "wof:name":"IPA Personnel",
    "wof:placetype":"venue"
},
  "geometry": {"coordinates":[144.96026611299999,-37.8166503906],"type":"Point"}
}