{
  "type": "Feature",
  "properties": {
    "iso:country":"AU",
    "sg:address":"Unit 1, 30 Pilbara St",
    "sg:city":"Welshpool",
    "sg:classifiers":[
        {
            "category":"Wholesale",
            "subcategory":"Auto Parts",
            "type":"Manufacturing & Wholesale Goods"
        }
    ],
    "sg:phone":"+61 13 38 03",
    "sg:postcode":"6106",
    "sg:province":"WA",
    "sg:tags":[
        "recyclers"
    ],
    "wof:name":"Yamato",
    "wof:placetype":"venue"
},
  "geometry": {"coordinates":[115.938720703,-31.9936904907],"type":"Point"}
}