{
  "type": "Feature",
  "properties": {
    "addr:full":"31- 33 Sydney Rd Benalla VIC 3671",
    "addr:housenumber":"33",
    "addr:postcode":"3671",
    "addr:street":"Sydney Rd",
    "iso:country":"AU",
    "sg:address":"31- 33 Sydney Rd",
    "sg:city":"Benalla",
    "sg:classifiers":[
        {
            "category":"Social Services",
            "subcategory":"Child Care",
            "type":"Services"
        }
    ],
    "sg:phone":"+61 3 5762 2215",
    "sg:postcode":"3671",
    "sg:province":"VIC",
    "wof:name":"ABC Learning Centres",
    "wof:placetype":"venue"
},
  "geometry": {"coordinates":[146.00003100000001,-36.547237],"type":"Point"}
}