{
  "type": "Feature",
  "properties": {
    "iso:country":"AU",
    "sg:address":"138a Sailors Bay Rd",
    "sg:city":"Northbridge",
    "sg:classifiers":[
        {
            "category":"Manufacturing",
            "subcategory":"Food",
            "type":"Manufacturing & Wholesale Goods"
        }
    ],
    "sg:phone":"+61 2 9967 4246",
    "sg:postcode":"2063",
    "sg:province":"NSW",
    "sg:tags":[
        "function",
        "catering"
    ],
    "wof:name":"Schmooze Cafe",
    "wof:placetype":"venue"
},
  "geometry": {"coordinates":[151.211227417,-33.8110351562],"type":"Point"}
}