{
  "type": "Feature",
  "properties": {
    "addr:full":"44 Tudhoe St Wagin WA 6315",
    "addr:housenumber":"44",
    "addr:postcode":"6315",
    "addr:street":"Tudhoe St",
    "iso:country":"AU",
    "sg:address":"44 Tudhoe St",
    "sg:city":"Wagin",
    "sg:classifiers":[
        {
            "category":"Shopping",
            "subcategory":"Jewelry",
            "type":"Retail Goods"
        }
    ],
    "sg:phone":"+61 8 9861 1202",
    "sg:postcode":"6315",
    "sg:province":"WA",
    "sg:tags":[
        "jeweller"
    ],
    "wof:name":"Wagin Jewellers & Giftware",
    "wof:placetype":"venue"
},
  "geometry": {"coordinates":[117.344352722,-33.3087310791],"type":"Point"}
}