{
  "type": "Feature",
  "properties": {
    "iso:country":"AU",
    "sg:address":"20 Harts Pde",
    "sg:city":"Hawthorn East",
    "sg:classifiers":[
        {
            "category":"Professional",
            "subcategory":"Accounting & Tax Preparation",
            "type":"Services"
        }
    ],
    "sg:phone":"+61 3 9813 5007",
    "sg:postcode":"3123",
    "sg:province":"VIC",
    "sg:tags":[
        "consultant",
        "taxation"
    ],
    "wof:name":"Renaissance Taxation & Accountig Services",
    "wof:placetype":"venue"
},
  "geometry": {"coordinates":[145.044845581,-37.8320808411],"type":"Point"}
}