{
  "type": "Feature",
  "properties": {
    "iso:country":"AU",
    "sg:address":"76 Trevenar St",
    "sg:city":"Ashbury",
    "sg:classifiers":[
        {
            "category":"Social Services",
            "subcategory":"Child Care",
            "type":"Services"
        }
    ],
    "sg:phone":"+61 2 9797 8854",
    "sg:postcode":"2193",
    "sg:province":"NSW",
    "wof:name":"Splash Centre",
    "wof:placetype":"venue"
},
  "geometry": {"coordinates":[151.120743,-33.898209],"type":"Point"}
}