{
  "type": "Feature",
  "properties": {
    "iso:country":"AU",
    "sg:address":"2 Cawley St",
    "sg:city":"Bellambi",
    "sg:classifiers":[
        {
            "category":"Education",
            "subcategory":"School",
            "type":"Public Place"
        }
    ],
    "sg:phone":"+61 2 4285 2877",
    "sg:postcode":"2518",
    "sg:province":"NSW",
    "wof:name":"Holy Spirit College",
    "wof:placetype":"venue"
},
  "geometry": {"coordinates":[150.916977,-34.365139],"type":"Point"}
}