{
  "type": "Feature",
  "properties": {
    "addr:full":"1/ 2 Campbell St Artarmon NSW 2064",
    "addr:housenumber":"/ 2",
    "addr:postcode":"2064",
    "addr:street":"Campbell St",
    "iso:country":"AU",
    "sg:address":"1/ 2 Campbell St",
    "sg:city":"Artarmon",
    "sg:classifiers":[
        {
            "category":"Building & Trades",
            "subcategory":"Cleaning & Sanitation",
            "type":"Services"
        }
    ],
    "sg:phone":"+61 2 9460 9066",
    "sg:postcode":"2064",
    "sg:province":"NSW",
    "sg:tags":[
        "commercial",
        "maintenance"
    ],
    "wof:name":"Transformex Pty Ltd",
    "wof:placetype":"venue"
},
  "geometry": {"coordinates":[151.18736267099999,-33.8170433044],"type":"Point"}
}