{
  "type": "Feature",
  "properties": {
    "addr:full":"4 Nale Rd Evandale TAS 7212",
    "addr:housenumber":"4",
    "addr:postcode":"7212",
    "addr:street":"Nale Rd",
    "iso:country":"AU",
    "sg:address":"4 Nale Rd",
    "sg:city":"Evandale",
    "sg:classifiers":[
        {
            "category":"Personal",
            "subcategory":"Beauty Salon",
            "type":"Services"
        }
    ],
    "sg:phone":"+61 3 6391 8575",
    "sg:postcode":"7212",
    "sg:province":"TAS",
    "sg:tags":[
        "hairdresser"
    ],
    "wof:name":"Evandale Hair & Beauty",
    "wof:placetype":"venue"
},
  "geometry": {"coordinates":[147.25010700000001,-41.571045],"type":"Point"}
}