{
  "type": "Feature",
  "properties": {
    "iso:country":"AU",
    "sg:address":"10 Renshaw Rd",
    "sg:city":"Parkes",
    "sg:classifiers":[
        {
            "category":"Building & Trades",
            "subcategory":"Cleaning & Sanitation",
            "type":"Services"
        }
    ],
    "sg:phone":"+61 2 6862 5080",
    "sg:postcode":"2870",
    "sg:province":"NSW",
    "sg:tags":[
        "abrasive",
        "blasting"
    ],
    "wof:name":"Protector Pty Ltd",
    "wof:placetype":"venue"
},
  "geometry": {"coordinates":[148.16246000000001,-33.152775],"type":"Point"}
}