{
  "type": "Feature",
  "properties": {
    "iso:country":"AU",
    "sg:address":"200 Coombe St",
    "sg:city":"Frenchville",
    "sg:classifiers":[
        {
            "category":"Building & Trades",
            "subcategory":"Construction",
            "type":"Services"
        }
    ],
    "sg:phone":"+61 408 288 759",
    "sg:postcode":"4701",
    "sg:province":"QLD",
    "sg:tags":[
        "earth",
        "excavating",
        "moving",
        "contractor"
    ],
    "wof:name":"Deep Creek Excavations",
    "wof:placetype":"venue"
},
  "geometry": {"coordinates":[150.54026794399999,-23.3464355469],"type":"Point"}
}