{
  "type": "Feature",
  "properties": {
    "addr:full":"363 Douglas Pde Newport VIC 3015",
    "addr:housenumber":"363",
    "addr:postcode":"3015",
    "addr:street":"Douglas Pde",
    "iso:country":"AU",
    "sg:address":"363 Douglas Pde",
    "sg:city":"Newport",
    "sg:classifiers":[
        {
            "category":"Retail",
            "subcategory":"Auto Repair",
            "type":"Services"
        }
    ],
    "sg:phone":"+61 3 9391 0485",
    "sg:postcode":"3015",
    "sg:province":"VIC",
    "sg:tags":[
        "repairer",
        "motor",
        "engineer"
    ],
    "wof:name":"Douglas Parade Motors",
    "wof:placetype":"venue"
},
  "geometry": {"coordinates":[144.892852783,-37.8405952454],"type":"Point"}
}