{
  "type": "Feature",
  "properties": {
    "iso:country":"AU",
    "sg:address":"Farm 1866",
    "sg:city":"Lake Wyangan",
    "sg:classifiers":[
        {
            "category":"Farming",
            "subcategory":"Farm",
            "type":"Manufacturing & Wholesale Goods"
        }
    ],
    "sg:phone":"+61 2 6962 3245",
    "sg:postcode":"2680",
    "sg:province":"NSW",
    "sg:tags":[
        "farmer"
    ],
    "wof:name":"Fabris V",
    "wof:placetype":"venue"
},
  "geometry": {"coordinates":[146.042191,-34.280251],"type":"Point"}
}