{
  "type": "Feature",
  "properties": {
    "addr:full":"1/ 4 Nevada Crt Hoppers Crossing VIC 3029",
    "addr:housenumber":"/ 4",
    "addr:postcode":"3029",
    "addr:street":"Nevada Crt",
    "iso:country":"AU",
    "sg:address":"1/ 4 Nevada Crt",
    "sg:city":"Hoppers Crossing",
    "sg:classifiers":[
        {
            "category":"Structure",
            "subcategory":"Office Building",
            "type":"Public Place"
        }
    ],
    "sg:phone":"+61 3 8742 2211",
    "sg:postcode":"3029",
    "sg:province":"VIC",
    "sg:tags":[
        "tie",
        "concrete",
        "formwork",
        "form",
        "accessory"
    ],
    "sg:website":"http://www.conset.com.au",
    "wof:name":"Conset",
    "wof:placetype":"venue"
},
  "geometry": {"coordinates":[144.70993000000001,-37.876469],"type":"Point"}
}