{
  "type": "Feature",
  "properties": {
    "addr:full":"12- 18 Federation St Bungalow QLD 4870",
    "addr:housenumber":"18",
    "addr:postcode":"4870",
    "addr:street":"Federation St",
    "iso:country":"AU",
    "sg:address":"12- 18 Federation St",
    "sg:city":"Bungalow",
    "sg:classifiers":[
        {
            "category":"Manufacturing",
            "subcategory":"Aerospace",
            "type":"Manufacturing & Wholesale Goods"
        }
    ],
    "sg:phone":"+61 7 4031 3077",
    "sg:postcode":"4870",
    "sg:province":"QLD",
    "sg:tags":[
        "equipment",
        "aircraft",
        "maintenance"
    ],
    "wof:name":"Trinity Fire Services Pty Ltd",
    "wof:placetype":"venue"
},
  "geometry": {"coordinates":[145.75352477999999,-16.9394798279],"type":"Point"}
}