{
  "type": "Feature",
  "properties": {
    "iso:country":"AU",
    "sg:address":"86 Walker St",
    "sg:city":"Maryborough",
    "sg:classifiers":[
        {
            "category":"Home & Garden",
            "subcategory":"Building Materials",
            "type":"Retail Goods"
        }
    ],
    "sg:phone":"+61 7 4123 3799",
    "sg:postcode":"4650",
    "sg:province":"QLD",
    "sg:tags":[
        "lawn",
        "cutting",
        "maintenance"
    ],
    "wof:name":"C & T Garden Construction & Lawn Maintenance",
    "wof:placetype":"venue"
},
  "geometry": {"coordinates":[152.69841,-25.52976],"type":"Point"}
}