{
  "type": "Feature",
  "properties": {
    "iso:country":"AU",
    "sg:address":"493 Ruthven St",
    "sg:city":"Toowoomba",
    "sg:classifiers":[
        {
            "category":"Professional",
            "subcategory":"Art Services",
            "type":"Services"
        }
    ],
    "sg:phone":"+61 7 4632 9173",
    "sg:postcode":"4350",
    "sg:province":"QLD",
    "sg:tags":[
        "interior",
        "decorator"
    ],
    "wof:name":"Curtain Warehouse",
    "wof:placetype":"venue"
},
  "geometry": {"coordinates":[151.95230100000001,-27.568159],"type":"Point"}
}