{
  "type": "Feature",
  "properties": {
    "addr:full":"72 McPherson St Horsham VIC 3400",
    "addr:housenumber":"72",
    "addr:postcode":"3400",
    "addr:street":"Mcpherson St",
    "iso:country":"AU",
    "sg:address":"72 McPherson St",
    "sg:city":"Horsham",
    "sg:classifiers":[
        {
            "category":"Autos & Motor Vehicles",
            "subcategory":"Auto Supplies",
            "type":"Retail Goods"
        }
    ],
    "sg:phone":"+61 3 5381 1766",
    "sg:postcode":"3400",
    "sg:province":"VIC",
    "sg:tags":[
        "wheel",
        "four",
        "equipment",
        "drive",
        "accessory"
    ],
    "wof:name":"Horsham Off Road",
    "wof:placetype":"venue"
},
  "geometry": {"coordinates":[142.20477294899999,-36.7210083008],"type":"Point"}
}