{
  "type": "Feature",
  "properties": {
    "addr:full":"82 South Pde Blackburn VIC 3130",
    "addr:housenumber":"82",
    "addr:postcode":"3130",
    "addr:street":"South Pde",
    "iso:country":"AU",
    "sg:address":"82 South Pde",
    "sg:city":"Blackburn",
    "sg:classifiers":[
        {
            "category":"Shopping",
            "subcategory":"Clothing, Apparel, & Fashions",
            "type":"Retail Goods"
        }
    ],
    "sg:phone":"+61 3 9894 8266",
    "sg:postcode":"3130",
    "sg:province":"VIC",
    "sg:tags":[
        "recycled",
        "clothing"
    ],
    "wof:name":"Epilepsy Foundation Of Victoria",
    "wof:placetype":"venue"
},
  "geometry": {"coordinates":[145.15049743599999,-37.8206787109],"type":"Point"}
}