{
  "type": "Feature",
  "properties": {
    "iso:country":"AU",
    "sg:address":"9 Rudman Pde",
    "sg:city":"Burleigh Waters",
    "sg:classifiers":[
        {
            "category":"Freight",
            "type":"Transportation"
        }
    ],
    "sg:phone":"+61 413 838 722",
    "sg:postcode":"4220",
    "sg:province":"QLD",
    "sg:tags":[
        "cargo",
        "container"
    ],
    "wof:name":"Allsafe Storage And Container Hire & Sales",
    "wof:placetype":"venue"
},
  "geometry": {"coordinates":[153.42027282699999,-28.1025371552],"type":"Point"}
}