{
  "type": "Feature",
  "properties": {
    "addr:full":"28 Metherall St Sunshine VIC 3020",
    "addr:housenumber":"28",
    "addr:postcode":"3020",
    "addr:street":"Metherall St",
    "iso:country":"AU",
    "sg:address":"28 Metherall St",
    "sg:city":"Sunshine",
    "sg:classifiers":[
        {
            "category":"Banks & Credit Unions",
            "subcategory":"Financial Services",
            "type":"Services"
        }
    ],
    "sg:phone":"+61 3 9312 3537",
    "sg:postcode":"3020",
    "sg:province":"VIC",
    "sg:tags":[
        "assistance",
        "roadside"
    ],
    "wof:name":"Pauls Vehicle Transportation",
    "wof:placetype":"venue"
},
  "geometry": {"coordinates":[144.82635500000001,-37.765106],"type":"Point"}
}