{
  "type": "Feature",
  "properties": {
    "addr:full":"Shop 9 Winthrop Shopng Cntr Winthrop WA 6150",
    "addr:housenumber":"shop 9",
    "addr:postcode":"6150",
    "addr:street":"Winthrop Shopng Cntr",
    "iso:country":"AU",
    "sg:address":"Shop 9 Winthrop Shopng Cntr",
    "sg:city":"Winthrop",
    "sg:classifiers":[
        {
            "category":"Food & Beverages",
            "subcategory":"Supermarket",
            "type":"Retail Goods"
        }
    ],
    "sg:phone":"+61 8 9310 5022",
    "sg:postcode":"6150",
    "sg:province":"WA",
    "sg:tags":[
        "grocery",
        "store"
    ],
    "wof:name":"Stammers Supermarkets",
    "wof:placetype":"venue"
},
  "geometry": {"coordinates":[115.825706,-32.047535],"type":"Point"}
}