{
  "type": "Feature",
  "properties": {
    "addr:full":"139 Railway St Bluff Point WA 6530",
    "addr:housenumber":"139",
    "addr:postcode":"6530",
    "addr:street":"Railway St Bluff",
    "iso:country":"AU",
    "sg:address":"139 Railway St",
    "sg:city":"Bluff Point",
    "sg:classifiers":[
        {
            "category":"Retail",
            "subcategory":"Auto Repair",
            "type":"Services"
        }
    ],
    "sg:phone":"+61 8 9964 3779",
    "sg:postcode":"6530",
    "sg:province":"WA",
    "sg:tags":[
        "bus",
        "truck"
    ],
    "wof:name":"Leeds Truck & Agri Mechanical Repairs",
    "wof:placetype":"venue"
},
  "geometry": {"coordinates":[114.625358581,-28.7384967804],"type":"Point"}
}