{
  "type": "Feature",
  "properties": {
    "addr:full":"Namatjira Ave Hope Valley SA 5090",
    "addr:postcode":"5090",
    "addr:street":"Namatjira Ave",
    "iso:country":"AU",
    "sg:address":"Namatjira Ave",
    "sg:city":"Hope Valley",
    "sg:classifiers":[
        {
            "category":"Shopping",
            "subcategory":"Musical Instruments",
            "type":"Retail Goods"
        }
    ],
    "sg:phone":"+61 407 709 523",
    "sg:postcode":"5090",
    "sg:province":"SA",
    "sg:tags":[
        "case"
    ],
    "wof:name":"Strongbox Flight Cases",
    "wof:placetype":"venue"
},
  "geometry": {"coordinates":[138.68617248499999,-34.839641571],"type":"Point"}
}