{
  "type": "Feature",
  "properties": {
    "addr:full":"66 Auburn St Wollongong NSW 2500",
    "addr:housenumber":"66",
    "addr:postcode":"2500",
    "addr:street":"Auburn St",
    "iso:country":"AU",
    "sg:address":"66 Auburn St",
    "sg:city":"Wollongong",
    "sg:classifiers":[
        {
            "category":"Home & Garden",
            "subcategory":"Furniture",
            "type":"Retail Goods"
        }
    ],
    "sg:phone":"+61 2 4226 3216",
    "sg:postcode":"2500",
    "sg:province":"NSW",
    "sg:tags":[
        "business"
    ],
    "wof:name":"Cyclo Office Interiors",
    "wof:placetype":"venue"
},
  "geometry": {"coordinates":[150.888428,-34.431416],"type":"Point"}
}