{
  "type": "Feature",
  "properties": {
    "iso:country":"AU",
    "sg:address":"Kemp St",
    "sg:city":"Kempsey",
    "sg:classifiers":[
        {
            "category":"Travel",
            "subcategory":"Travel Agent",
            "type":"Entertainment"
        }
    ],
    "sg:phone":"+61 2 6563 1698",
    "sg:postcode":"2440",
    "sg:province":"NSW",
    "sg:tags":[
        "consultant"
    ],
    "wof:name":"Countrylink",
    "wof:placetype":"venue"
},
  "geometry": {"coordinates":[152.83213799999999,-31.077621],"type":"Point"}
}