{
  "type": "Feature",
  "properties": {
    "addr:full":"59/ 61-65 Glencoe St Sutherland NSW 2232",
    "addr:housenumber":"59 / 61-65",
    "addr:postcode":"2232",
    "addr:street":"Glencoe St",
    "iso:country":"AU",
    "sg:address":"59/ 61-65 Glencoe St",
    "sg:city":"Sutherland",
    "sg:classifiers":[
        {
            "category":"Health Services",
            "subcategory":"Health Practitioner",
            "type":"Services"
        }
    ],
    "sg:phone":"+61 2 8539 7111",
    "sg:postcode":"2232",
    "sg:province":"NSW",
    "sg:tags":[
        "physiotherapist"
    ],
    "wof:name":"Wiltshire Rachael",
    "wof:placetype":"venue"
},
  "geometry": {"coordinates":[151.06317138700001,-34.0315170288],"type":"Point"}
}