{
  "type": "Feature",
  "properties": {
    "addr:full":"56 Johnson St Maffra VIC 3860",
    "addr:housenumber":"56",
    "addr:postcode":"3860",
    "addr:street":"Johnson St",
    "iso:country":"AU",
    "sg:address":"56 Johnson St",
    "sg:city":"Maffra",
    "sg:classifiers":[
        {
            "category":"Shopping",
            "subcategory":"Bridal",
            "type":"Retail Goods"
        }
    ],
    "sg:phone":"+61 3 5141 1400",
    "sg:postcode":"3860",
    "sg:province":"VIC",
    "sg:tags":[
        "hire",
        "wear"
    ],
    "wof:name":"Little Lady's",
    "wof:placetype":"venue"
},
  "geometry": {"coordinates":[146.974487305,-37.9657402039],"type":"Point"}
}