{
  "type": "Feature",
  "properties": {
    "iso:country":"AU",
    "sg:address":"16 Edward St",
    "sg:city":"Bellevue",
    "sg:classifiers":[
        {
            "category":"Autos & Motor Vehicles",
            "subcategory":"Automobile Sales",
            "type":"Retail Goods"
        }
    ],
    "sg:phone":"+61 8 9274 2429",
    "sg:postcode":"6056",
    "sg:province":"WA",
    "sg:tags":[
        "equipment",
        "trailer"
    ],
    "wof:name":"WestCoast Trailer Parts And Accessories",
    "wof:placetype":"venue"
},
  "geometry": {"coordinates":[116.02149963399999,-31.897611618],"type":"Point"}
}