{
  "type": "Feature",
  "properties": {
    "addr:full":"Suite 5, 41 Rawson St Epping NSW 2121",
    "addr:housenumber":"41",
    "addr:postcode":"2121",
    "addr:street":"Rawson St",
    "iso:country":"AU",
    "sg:address":"Suite 5, 41 Rawson St",
    "sg:city":"Epping",
    "sg:classifiers":[
        {
            "category":"Health Services",
            "subcategory":"Health Practitioner",
            "type":"Services"
        }
    ],
    "sg:phone":"+61 2 9868 1437",
    "sg:postcode":"2121",
    "sg:province":"NSW",
    "sg:tags":[
        "physiotherapist"
    ],
    "wof:name":"Epping Central Physiotherapy Clinic",
    "wof:placetype":"venue"
},
  "geometry": {"coordinates":[151.081008911,-33.774017334],"type":"Point"}
}