{
  "type": "Feature",
  "properties": {
    "addr:full":"Suite 5 - 72/ 74 Cecil Ave Castle Hill NSW 2154",
    "addr:housenumber":"72 / 74",
    "addr:postcode":"2154",
    "addr:street":"Cecil Ave",
    "iso:country":"AU",
    "sg:address":"Suite 5 - 72/ 74 Cecil Ave",
    "sg:city":"Castle Hill",
    "sg:classifiers":[
        {
            "category":"Health Services",
            "subcategory":"Doctor",
            "type":"Services"
        }
    ],
    "sg:phone":"+61 2 9476 2288",
    "sg:postcode":"2154",
    "sg:province":"NSW",
    "sg:tags":[
        "medical",
        "practitioner"
    ],
    "wof:name":"Middleton Philip D",
    "wof:placetype":"venue"
},
  "geometry": {"coordinates":[151.001556397,-33.7341346741],"type":"Point"}
}