{
  "type": "Feature",
  "properties": {
    "iso:country":"AU",
    "sg:address":"U 15/ 83 Keilor Park Drv",
    "sg:city":"Tullamarine",
    "sg:classifiers":[
        {
            "category":"Wholesale",
            "subcategory":"Apparel",
            "type":"Manufacturing & Wholesale Goods"
        }
    ],
    "sg:phone":"+61 3 9335 2500",
    "sg:postcode":"3043",
    "sg:province":"VIC",
    "sg:tags":[
        "wholesaler",
        "mfrs",
        "menswear"
    ],
    "wof:name":"Warrant Pty Ltd",
    "wof:placetype":"venue"
},
  "geometry": {"coordinates":[144.858932495,-37.713684082],"type":"Point"}
}