{
  "type": "Feature",
  "properties": {
    "iso:country":"AU",
    "sg:address":"16 Bermill St",
    "sg:city":"Rockdale",
    "sg:classifiers":[
        {
            "category":"Manufacturing",
            "subcategory":"Building Materials",
            "type":"Manufacturing & Wholesale Goods"
        }
    ],
    "sg:phone":"+61 2 9567 0788",
    "sg:postcode":"2216",
    "sg:province":"NSW",
    "sg:tags":[
        "adhesive",
        "tape"
    ],
    "wof:name":"Husky Tape Converting",
    "wof:placetype":"venue"
},
  "geometry": {"coordinates":[151.146729,-33.960304],"type":"Point"}
}