{
  "type": "Feature",
  "properties": {
    "iso:country":"AU",
    "sg:address":"422 Main St",
    "sg:city":"Lilydale",
    "sg:classifiers":[
        {
            "category":"Government",
            "subcategory":"Fire Station",
            "type":"Public Place"
        }
    ],
    "sg:phone":"+61 3 9739 5892",
    "sg:postcode":"3140",
    "sg:province":"VIC",
    "sg:tags":[
        "spring",
        "shock",
        "absorbers",
        "suspension"
    ],
    "wof:name":"Bridgestone Tyre Centre Lilydale",
    "wof:placetype":"venue"
},
  "geometry": {"coordinates":[145.08467102,-38.0028915405],"type":"Point"}
}