{
  "type": "Feature",
  "properties": {
    "addr:full":"160 Fairy St Warrnambool VIC 3280",
    "addr:housenumber":"160",
    "addr:postcode":"3280",
    "addr:street":"Fairy St",
    "iso:country":"AU",
    "sg:address":"160 Fairy St",
    "sg:city":"Warrnambool",
    "sg:classifiers":[
        {
            "category":"Professional",
            "subcategory":"Printing & Photocopies",
            "type":"Services"
        }
    ],
    "sg:phone":"+61 3 5562 6622",
    "sg:postcode":"3280",
    "sg:province":"VIC",
    "sg:tags":[
        "photocopier"
    ],
    "wof:name":"Warrnambool Business Machines",
    "wof:placetype":"venue"
},
  "geometry": {"coordinates":[142.480911255,-38.3793640137],"type":"Point"}
}