{
  "type": "Feature",
  "properties": {
    "addr:full":"Lloyd St Dimboola VIC 3414",
    "addr:postcode":"3414",
    "addr:street":"Lloyd St",
    "iso:country":"AU",
    "sg:address":"Lloyd St",
    "sg:city":"Dimboola",
    "sg:classifiers":[
        {
            "category":"Sports & Exercise",
            "subcategory":"Gym",
            "type":"Entertainment"
        }
    ],
    "sg:phone":"+61 3 5389 1383",
    "sg:postcode":"3414",
    "sg:province":"VIC",
    "sg:tags":[
        "health",
        "fitness"
    ],
    "wof:name":"Dimboola Outdoor Pool",
    "wof:placetype":"venue"
},
  "geometry": {"coordinates":[142.028244019,-36.4564399719],"type":"Point"}
}