{
  "type": "Feature",
  "properties": {
    "addr:full":"PO Box 141 Sumner QLD 4074",
    "addr:postcode":"4074",
    "iso:country":"AU",
    "sg:address":"PO Box 141",
    "sg:city":"Sumner",
    "sg:classifiers":[
        {
            "category":"Building & Trades",
            "subcategory":"Equipment Rental",
            "type":"Services"
        }
    ],
    "sg:phone":"+61 401 747 538",
    "sg:postcode":"4074",
    "sg:province":"QLD",
    "sg:tags":[
        "platform",
        "hire",
        "work",
        "elevating"
    ],
    "wof:name":"Travel Tower Hire Pty Ltd",
    "wof:placetype":"venue"
},
  "geometry": {"coordinates":[152.934692383,-27.5603599548],"type":"Point"}
}