{
  "type": "Feature",
  "properties": {
    "iso:country":"AU",
    "sg:address":"24 Ace Crs",
    "sg:city":"Tuggerah",
    "sg:classifiers":[
        {
            "category":"Building & Trades",
            "subcategory":"Construction",
            "type":"Services"
        }
    ],
    "sg:phone":"+61 2 4351 2778",
    "sg:postcode":"2259",
    "sg:province":"NSW",
    "sg:tags":[
        "welding"
    ],
    "wof:name":"Metal As Anything Pty Ltd",
    "wof:placetype":"venue"
},
  "geometry": {"coordinates":[151.420410156,-33.3050003052],"type":"Point"}
}