{
  "type": "Feature",
  "properties": {
    "addr:full":"8/ 11 Malcolm Rd Maddington WA 6109",
    "addr:housenumber":"/ 11",
    "addr:postcode":"6109",
    "addr:street":"Malcolm Rd",
    "iso:country":"AU",
    "sg:address":"8/ 11 Malcolm Rd",
    "sg:city":"Maddington",
    "sg:classifiers":[
        {
            "category":"Retail",
            "subcategory":"Auto Repair",
            "type":"Services"
        }
    ],
    "sg:phone":"+61 8 9459 1215",
    "sg:postcode":"6109",
    "sg:province":"WA",
    "sg:tags":[
        "camper-trailers",
        "caravan",
        "servicing"
    ],
    "wof:name":"Rays Caravan Refrigeration",
    "wof:placetype":"venue"
},
  "geometry": {"coordinates":[115.984863281,-32.0416107178],"type":"Point"}
}