{
  "type": "Feature",
  "properties": {
    "addr:full":"23 Harveys Farm Rd Bicheno TAS 7215",
    "addr:housenumber":"23",
    "addr:postcode":"7215",
    "addr:street":"Harveys Farm Rd",
    "iso:country":"AU",
    "sg:address":"23 Harveys Farm Rd",
    "sg:city":"Bicheno",
    "sg:classifiers":[
        {
            "category":"Food & Beverages",
            "subcategory":"Meat & Fish",
            "type":"Retail Goods"
        }
    ],
    "sg:phone":"+61 3 6375 1412",
    "sg:postcode":"7215",
    "sg:province":"TAS",
    "sg:tags":[
        "aquaculture"
    ],
    "wof:name":"Abalone Farms Australia",
    "wof:placetype":"venue"
},
  "geometry": {"coordinates":[148.29963699999999,-41.88522],"type":"Point"}
}