{
  "type": "Feature",
  "properties": {
    "addr:full":"Alexandrina Drv Yarralumla ACT 2600",
    "addr:postcode":"2600",
    "addr:street":"Alexandrina Drv",
    "iso:country":"AU",
    "sg:address":"Alexandrina Drv",
    "sg:city":"Yarralumla",
    "sg:classifiers":[
        {
            "category":"Farming",
            "subcategory":"Crops",
            "type":"Manufacturing & Wholesale Goods"
        }
    ],
    "sg:phone":"+61 2 6251 8180",
    "sg:postcode":"2600",
    "sg:province":"ACT",
    "sg:tags":[
        "club",
        "rowing"
    ],
    "wof:name":"Canberra Rowing Club",
    "wof:placetype":"venue"
},
  "geometry": {"coordinates":[149.10159301799999,-35.3015518188],"type":"Point"}
}