{
  "type": "Feature",
  "properties": {
    "iso:country":"AU",
    "sg:address":"Suite 2/ 15 Wallangra Rd",
    "sg:city":"Dover Heights",
    "sg:classifiers":[
        {
            "category":"Government",
            "subcategory":"Court House",
            "type":"Public Place"
        }
    ],
    "sg:phone":"+61 2 9371 6635",
    "sg:postcode":"2030",
    "sg:province":"NSW",
    "sg:tags":[
        "personal",
        "marriage",
        "family",
        "counselling"
    ],
    "wof:name":"Nitya Amrita",
    "wof:placetype":"venue"
},
  "geometry": {"coordinates":[151.27908325199999,-33.875377655],"type":"Point"}
}