{
  "type": "Feature",
  "properties": {
    "addr:full":"31 Janet St Maylands SA 5069",
    "addr:housenumber":"31",
    "addr:postcode":"5069",
    "addr:street":"Janet St",
    "iso:country":"AU",
    "sg:address":"31 Janet St",
    "sg:city":"Maylands",
    "sg:classifiers":[
        {
            "category":"Organizations",
            "subcategory":"Non-profit Organization",
            "type":"Services"
        }
    ],
    "sg:phone":"+61 8 8362 0556",
    "sg:postcode":"5069",
    "sg:province":"SA",
    "sg:tags":[
        "support",
        "disability",
        "organisation"
    ],
    "wof:name":"Independent Disabled Persons Association Inc",
    "wof:placetype":"venue"
},
  "geometry": {"coordinates":[138.63917541500001,-34.9075012207],"type":"Point"}
}