{
  "type": "Feature",
  "properties": {
    "addr:full":"10 St Wilfred Ave Stirling SA 5152",
    "addr:housenumber":"10",
    "addr:postcode":"5152",
    "addr:street":"St Wilfred Ave",
    "iso:country":"AU",
    "sg:address":"10 St Wilfred Ave",
    "sg:city":"Stirling",
    "sg:classifiers":[
        {
            "category":"Professional",
            "subcategory":"Computer Services",
            "type":"Services"
        }
    ],
    "sg:phone":"+61 8 8370 8262",
    "sg:postcode":"5152",
    "sg:province":"SA",
    "sg:tags":[
        "package",
        "software"
    ],
    "wof:name":"T 3 Solutions Pty Ltd",
    "wof:placetype":"venue"
},
  "geometry": {"coordinates":[138.732498169,-35.0036430359],"type":"Point"}
}