{
  "type": "Feature",
  "properties": {
    "addr:full":"77 Prowse St Toowoomba QLD 4350",
    "addr:housenumber":"77",
    "addr:postcode":"4350",
    "addr:street":"Prowse St",
    "iso:country":"AU",
    "sg:address":"77 Prowse St",
    "sg:city":"Toowoomba",
    "sg:classifiers":[
        {
            "category":"Health Services",
            "subcategory":"Health Practitioner",
            "type":"Services"
        }
    ],
    "sg:phone":"+61 7 4633 4405",
    "sg:postcode":"4350",
    "sg:province":"QLD",
    "sg:tags":[
        "naturopath"
    ],
    "wof:name":"O&#039;Brien Margaret",
    "wof:placetype":"venue"
},
  "geometry": {"coordinates":[151.932526,-27.541662],"type":"Point"}
}