{
  "type": "Feature",
  "properties": {
    "addr:full":"138 Brisbane St Ipswich QLD 4305",
    "addr:housenumber":"138",
    "addr:postcode":"4305",
    "addr:street":"Brisbane St",
    "iso:country":"AU",
    "sg:address":"138 Brisbane St",
    "sg:city":"Ipswich",
    "sg:classifiers":[
        {
            "category":"Building & Trades",
            "subcategory":"Locksmith",
            "type":"Services"
        }
    ],
    "sg:phone":"+61 7 3281 1440",
    "sg:postcode":"4305",
    "sg:province":"QLD",
    "sg:tags":[
        "lock"
    ],
    "wof:name":"Vogler & Son",
    "wof:placetype":"venue"
},
  "geometry": {"coordinates":[152.75721740700001,-27.6141910553],"type":"Point"}
}