{
  "type": "Feature",
  "properties": {
    "addr:full":"2 East St Granville NSW 2142",
    "addr:housenumber":"2",
    "addr:postcode":"2142",
    "addr:street":"East St",
    "iso:country":"AU",
    "sg:address":"2 East St",
    "sg:city":"Granville",
    "sg:classifiers":[
        {
            "category":"Retail",
            "subcategory":"Auto Repair",
            "type":"Services"
        }
    ],
    "sg:phone":"+61 2 9760 0336",
    "sg:postcode":"2142",
    "sg:province":"NSW",
    "sg:tags":[
        "repairer",
        "motor",
        "engineer"
    ],
    "wof:name":"East St Body Repairs",
    "wof:placetype":"venue"
},
  "geometry": {"coordinates":[151.01481628400001,-33.8335418701],"type":"Point"}
}