{
  "type": "Feature",
  "properties": {
    "iso:country":"AU",
    "sg:address":"PO Box 1181",
    "sg:city":"South Perth",
    "sg:classifiers":[
        {
            "category":"Home & Garden",
            "subcategory":"Building Materials",
            "type":"Retail Goods"
        }
    ],
    "sg:phone":"+61 409 371 174",
    "sg:postcode":"6951",
    "sg:province":"WA",
    "sg:tags":[
        "merchant",
        "glass",
        "glazier"
    ],
    "wof:name":"Always Affordable Glass Service",
    "wof:placetype":"venue"
},
  "geometry": {"coordinates":[115.862831116,-31.9807891846],"type":"Point"}
}