{
  "type": "Feature",
  "properties": {
    "addr:full":"PO Box 4206 Dandenong South VIC 3164",
    "addr:postcode":"3164",
    "iso:country":"AU",
    "sg:address":"PO Box 4206",
    "sg:city":"Dandenong South",
    "sg:classifiers":[
        {
            "category":"Professional",
            "subcategory":"Engineering",
            "type":"Services"
        }
    ],
    "sg:phone":"+61 3 5997 1547",
    "sg:postcode":"3164",
    "sg:province":"VIC",
    "sg:tags":[
        "engineer"
    ],
    "wof:name":"Glazson Engineering",
    "wof:placetype":"venue"
},
  "geometry": {"coordinates":[145.201705933,-38.0340309143],"type":"Point"}
}