{
  "type": "Feature",
  "properties": {
    "iso:country":"AU",
    "sg:address":"8 Naroma Crt",
    "sg:city":"Coolum Beach",
    "sg:classifiers":[
        {
            "category":"Professional",
            "subcategory":"Employment Agencies",
            "type":"Services"
        }
    ],
    "sg:phone":"+61 409 520 049",
    "sg:postcode":"4573",
    "sg:province":"QLD",
    "sg:tags":[
        "entertainer",
        "agent"
    ],
    "wof:name":"Lionhouse Reggae Band",
    "wof:placetype":"venue"
},
  "geometry": {"coordinates":[153.08607499999999,-26.521481],"type":"Point"}
}