{
  "type": "Feature",
  "properties": {
    "addr:full":"Campbelltown Mall Shopping Centre, Lwr lvl Car Park. Hurley & Queen St Campbelltown NSW 2560",
    "addr:postcode":"2560",
    "addr:street":"St",
    "iso:country":"AU",
    "sg:address":"Campbelltown Mall Shopping Centre, Lwr lvl Car Park. Hurley & Queen St",
    "sg:city":"Campbelltown",
    "sg:classifiers":[
        {
            "category":"Autos & Motor Vehicles",
            "subcategory":"Auto Supplies",
            "type":"Retail Goods"
        }
    ],
    "sg:phone":"+61 2 4628 6345",
    "sg:postcode":"2560",
    "sg:province":"NSW",
    "sg:tags":[
        "tyre"
    ],
    "wof:name":"Kmart Tyre & Auto Service Campbelltown",
    "wof:placetype":"venue"
},
  "geometry": {"coordinates":[150.810302734,-34.0710601807],"type":"Point"}
}