{
  "type": "Feature",
  "properties": {
    "addr:full":"80 Henley St Como WA 6152",
    "addr:housenumber":"80",
    "addr:postcode":"6152",
    "addr:street":"Henley St",
    "iso:country":"AU",
    "sg:address":"80 Henley St",
    "sg:city":"Como",
    "sg:classifiers":[
        {
            "category":"Travel",
            "subcategory":"Hostel",
            "type":"Entertainment"
        }
    ],
    "sg:phone":"+61 8 9313 2955",
    "sg:postcode":"6152",
    "sg:province":"WA",
    "sg:tags":[
        "home"
    ],
    "wof:name":"Meath Care",
    "wof:placetype":"venue"
},
  "geometry": {"coordinates":[115.871521,-32.005829],"type":"Point"}
}