{
  "type": "Feature",
  "properties": {
    "addr:full":"Shp 3/ 71 Saywell Rd Macquarie Fields NSW 2564",
    "addr:housenumber":"/ 71",
    "addr:postcode":"2564",
    "addr:street":"Saywell Rd",
    "iso:country":"AU",
    "sg:address":"Shp 3/ 71 Saywell Rd",
    "sg:city":"Macquarie Fields",
    "sg:classifiers":[
        {
            "category":"Restaurant",
            "type":"Food & Drink"
        }
    ],
    "sg:phone":"+61 2 9618 3300",
    "sg:postcode":"2564",
    "sg:province":"NSW",
    "wof:name":"Cookie Thai Restaurant",
    "wof:placetype":"venue"
},
  "geometry": {"coordinates":[150.88795471200001,-33.9936332703],"type":"Point"}
}