{
  "type": "Feature",
  "properties": {
    "addr:full":"2 Massey St East Bundaberg QLD 4670",
    "addr:housenumber":"2",
    "addr:postcode":"4670",
    "addr:street":"Massey St East",
    "iso:country":"AU",
    "sg:address":"2 Massey St",
    "sg:city":"East Bundaberg",
    "sg:phone":"+61 7 4152 5199",
    "sg:postcode":"4670",
    "sg:province":"QLD",
    "wof:name":"Ron Smit Filters",
    "wof:placetype":"venue"
},
  "geometry": {"coordinates":[152.37045288100001,-24.8529491425],"type":"Point"}
}