{
  "type": "Feature",
  "properties": {
    "iso:country":"AU",
    "sg:address":"134 Carruthers St",
    "sg:city":"Curtin",
    "sg:classifiers":[
        {
            "category":"Health Services",
            "subcategory":"Health Practitioner",
            "type":"Services"
        }
    ],
    "sg:phone":"+61 2 6282 4545",
    "sg:postcode":"2605",
    "sg:province":"ACT",
    "sg:tags":[
        "psychologist"
    ],
    "wof:name":"Adele Hamilton",
    "wof:placetype":"venue"
},
  "geometry": {"coordinates":[149.079177856,-35.323890686],"type":"Point"}
}