{
  "type": "Feature",
  "properties": {
    "iso:country":"AU",
    "sg:address":"1/ 525 Brighton Rd",
    "sg:city":"Brighton",
    "sg:classifiers":[
        {
            "category":"Professional",
            "subcategory":"Printing & Photocopies",
            "type":"Services"
        }
    ],
    "sg:phone":"+61 8 8296 1392",
    "sg:postcode":"5048",
    "sg:province":"SA",
    "sg:tags":[
        "rubber",
        "stamp",
        "metal"
    ],
    "wof:name":"Active Office Supplies",
    "wof:placetype":"venue"
},
  "geometry": {"coordinates":[138.523239,-35.021801],"type":"Point"}
}