{
  "type": "Feature",
  "properties": {
    "addr:full":"329 Pimlico Rd Pimlico NSW 2478",
    "addr:housenumber":"329",
    "addr:postcode":"2478",
    "addr:street":"Pimlico Rd",
    "iso:country":"AU",
    "sg:address":"329 Pimlico Rd",
    "sg:city":"Pimlico",
    "sg:classifiers":[
        {
            "category":"Professional",
            "subcategory":"Computer Services",
            "type":"Services"
        }
    ],
    "sg:phone":"+61 2 6687 9800",
    "sg:postcode":"2478",
    "sg:province":"NSW",
    "sg:tags":[
        "training"
    ],
    "wof:name":"J & S Mitchell Software Training & Consulting",
    "wof:placetype":"venue"
},
  "geometry": {"coordinates":[153.49107360799999,-28.8986549377],"type":"Point"}
}