{
  "type": "Feature",
  "properties": {
    "addr:full":"29 Pine Ave Tuncurry NSW 2428",
    "addr:housenumber":"29",
    "addr:postcode":"2428",
    "addr:street":"Pine Ave",
    "iso:country":"AU",
    "sg:address":"29 Pine Ave",
    "sg:city":"Tuncurry",
    "sg:classifiers":[
        {
            "category":"Retail",
            "subcategory":"Auto Repair",
            "type":"Services"
        }
    ],
    "sg:phone":"+61 2 6554 7837",
    "sg:postcode":"2428",
    "sg:province":"NSW",
    "sg:tags":[
        "beater",
        "painter",
        "panel"
    ],
    "wof:name":"Tuncurry Smash Repairs",
    "wof:placetype":"venue"
},
  "geometry": {"coordinates":[152.49438499999999,-32.166573],"type":"Point"}
}