{
  "type": "Feature",
  "properties": {
    "addr:full":"15 Sylvan Drv Benowa QLD 4217",
    "addr:housenumber":"15",
    "addr:postcode":"4217",
    "addr:street":"Sylvan Drv",
    "iso:country":"AU",
    "sg:address":"15 Sylvan Drv",
    "sg:city":"Benowa",
    "sg:classifiers":[
        {
            "category":"Manufacturing",
            "subcategory":"Tools & Machinery",
            "type":"Manufacturing & Wholesale Goods"
        }
    ],
    "sg:phone":"+61 411 176 071",
    "sg:postcode":"4217",
    "sg:province":"QLD",
    "wof:name":"Cool Tools Gold Coast",
    "wof:placetype":"venue"
},
  "geometry": {"coordinates":[153.388214111,-28.0006866455],"type":"Point"}
}