{
  "type": "Feature",
  "properties": {
    "addr:full":"Cnr Philippine Parade & Second Ave Palm Beach QLD 4221",
    "addr:postcode":"4221",
    "addr:street":"Cnr Philippine Parade & Second Ave",
    "iso:country":"AU",
    "sg:address":"Cnr Philippine Parade & Second Ave",
    "sg:city":"Palm Beach",
    "sg:classifiers":[
        {
            "category":"Health Services",
            "subcategory":"Doctor",
            "type":"Services"
        }
    ],
    "sg:phone":"+61 7 5598 1727",
    "sg:postcode":"4221",
    "sg:province":"QLD",
    "sg:tags":[
        "medical",
        "practitioner"
    ],
    "wof:name":"Mills, Ken Dr",
    "wof:placetype":"venue"
},
  "geometry": {"coordinates":[153.46975707999999,-28.1227588654],"type":"Point"}
}