{
  "type": "Feature",
  "properties": {
    "addr:full":"154 Bennett Rd St Clair NSW 2759",
    "addr:housenumber":"154",
    "addr:postcode":"2759",
    "addr:street":"Bennett Rd",
    "iso:country":"AU",
    "sg:address":"154 Bennett Rd St",
    "sg:city":"Clair",
    "sg:classifiers":[
        {
            "category":"Health Services",
            "subcategory":"Dentist",
            "type":"Services"
        }
    ],
    "sg:phone":"+61 2 9670 6991",
    "sg:postcode":"2759",
    "sg:province":"NSW",
    "wof:name":"Campbell Dr John & Associates",
    "wof:placetype":"venue"
},
  "geometry": {"coordinates":[150.79037475600001,-33.79454422],"type":"Point"}
}