{
  "type": "Feature",
  "properties": {
    "iso:country":"AU",
    "sg:address":"50- 52 Sturt St",
    "sg:city":"Echuca",
    "sg:classifiers":[
        {
            "category":"Shopping",
            "subcategory":"Clothing, Apparel, & Fashions",
            "type":"Retail Goods"
        }
    ],
    "sg:phone":"+61 3 5480 9755",
    "sg:postcode":"3564",
    "sg:province":"VIC",
    "sg:tags":[
        "recycled",
        "clothing"
    ],
    "wof:name":"Salvation Army The",
    "wof:placetype":"venue"
},
  "geometry": {"coordinates":[144.75511169399999,-36.1368026733],"type":"Point"}
}