{
  "type": "Feature",
  "properties": {
    "addr:full":"59 Brendon Ave West Pennant Hills NSW 2125",
    "addr:housenumber":"59",
    "addr:postcode":"2125",
    "addr:street":"Brendon Ave",
    "iso:country":"AU",
    "sg:address":"59 Brendon Ave",
    "sg:city":"West Pennant Hills",
    "sg:classifiers":[
        {
            "category":"School Buses",
            "type":"Transportation"
        }
    ],
    "sg:phone":"+61 2 9769 1122",
    "sg:postcode":"2125",
    "sg:province":"NSW",
    "sg:tags":[
        "nanny"
    ],
    "wof:name":"Australian Professional Nannies",
    "wof:placetype":"venue"
},
  "geometry": {"coordinates":[151.025665283,-33.7375640869],"type":"Point"}
}