{
  "type": "Feature",
  "properties": {
    "addr:full":"71 Belair Rd Kingswood SA 5062",
    "addr:housenumber":"71",
    "addr:postcode":"5062",
    "addr:street":"Belair Rd",
    "iso:country":"AU",
    "sg:address":"71 Belair Rd",
    "sg:city":"Kingswood",
    "sg:classifiers":[
        {
            "category":"Real Estate",
            "subcategory":"Architect",
            "type":"Services"
        }
    ],
    "sg:phone":"+61 8 8299 9744",
    "sg:postcode":"5062",
    "sg:province":"SA",
    "wof:name":"Parker Christopher Architects",
    "wof:placetype":"venue"
},
  "geometry": {"coordinates":[138.60931396500001,-34.9723815918],"type":"Point"}
}