{
  "type": "Feature",
  "properties": {
    "addr:full":"Suite 5/ 280 Hay St Subiaco WA 6008",
    "addr:housenumber":"/ 280",
    "addr:postcode":"6008",
    "addr:street":"Hay St",
    "iso:country":"AU",
    "sg:address":"Suite 5/ 280 Hay St",
    "sg:city":"Subiaco",
    "sg:classifiers":[
        {
            "category":"Health Services",
            "subcategory":"Doctor",
            "type":"Services"
        }
    ],
    "sg:phone":"+61 8 9380 6868",
    "sg:postcode":"6008",
    "sg:province":"WA",
    "sg:tags":[
        "medical",
        "practitioner"
    ],
    "wof:name":"Bioscor International",
    "wof:placetype":"venue"
},
  "geometry": {"coordinates":[115.82926178,-31.9471702576],"type":"Point"}
}