{
  "type": "Feature",
  "properties": {
    "addr:full":"Level 3, 200 Mary St Brisbane QLD 4000",
    "addr:housenumber":"200",
    "addr:postcode":"4000",
    "addr:street":"Mary St",
    "iso:country":"AU",
    "sg:address":"Level 3, 200 Mary St",
    "sg:city":"Brisbane",
    "sg:classifiers":[
        {
            "category":"Insurance",
            "subcategory":"Insurance Agent",
            "type":"Services"
        }
    ],
    "sg:phone":"+61 7 3002 2200",
    "sg:postcode":"4000",
    "sg:province":"QLD",
    "sg:tags":[
        "broker"
    ],
    "wof:name":"BLUE BROKING PTY LTD",
    "wof:placetype":"venue"
},
  "geometry": {"coordinates":[153.029418945,-27.4702377319],"type":"Point"}
}