{
  "type": "Feature",
  "properties": {
    "iso:country":"AU",
    "sg:address":"6 Campbell St",
    "sg:city":"Tongala",
    "sg:classifiers":[
        {
            "category":"Home & Garden",
            "subcategory":"Carpets & Floor Coverings",
            "type":"Retail Goods"
        }
    ],
    "sg:phone":"+61 414 532 827",
    "sg:postcode":"3621",
    "sg:province":"VIC",
    "sg:tags":[
        "tile",
        "wall",
        "layer"
    ],
    "wof:name":"D & D Tiling",
    "wof:placetype":"venue"
},
  "geometry": {"coordinates":[144.958740234,-36.2478981018],"type":"Point"}
}