{
  "type": "Feature",
  "properties": {
    "iso:country":"AU",
    "sg:address":"1st Floor, 33- 35 Graham Crt",
    "sg:city":"Hoppers Crossing",
    "sg:classifiers":[
        {
            "category":"Professional",
            "subcategory":"Accounting & Tax Preparation",
            "type":"Services"
        }
    ],
    "sg:phone":"+61 3 9369 1223",
    "sg:postcode":"3029",
    "sg:province":"VIC",
    "sg:tags":[
        "accountant",
        "auditor"
    ],
    "wof:name":"Geermans A C Associates Pty Ltd",
    "wof:placetype":"venue"
},
  "geometry": {"coordinates":[144.729858,-37.873852],"type":"Point"}
}