{
  "type": "Feature",
  "properties": {
    "addr:full":"21 Puckle St Moonee Ponds VIC 3039",
    "addr:housenumber":"21",
    "addr:postcode":"3039",
    "addr:street":"Puckle St",
    "iso:country":"AU",
    "sg:address":"21 Puckle St",
    "sg:city":"Moonee Ponds",
    "sg:classifiers":[
        {
            "category":"Personal",
            "subcategory":"Hair Removal",
            "type":"Services"
        }
    ],
    "sg:phone":"+61 1300 786 166",
    "sg:postcode":"3039",
    "sg:province":"VIC",
    "wof:name":"Australian Laser & Skin Clinic The",
    "wof:placetype":"venue"
},
  "geometry": {"coordinates":[144.923721,-37.767094],"type":"Point"}
}