{
  "type": "Feature",
  "properties": {
    "iso:country":"AU",
    "sg:address":"Shop 2, 89A Barrabool Rd",
    "sg:city":"Highton",
    "sg:classifiers":[
        {
            "category":"Food & Beverages",
            "subcategory":"Specialty",
            "type":"Retail Goods"
        }
    ],
    "sg:phone":"+61 3 5243 9084",
    "sg:postcode":"3216",
    "sg:province":"VIC",
    "sg:tags":[
        "product",
        "health"
    ],
    "wof:name":"Mammoth Health",
    "wof:placetype":"venue"
},
  "geometry": {"coordinates":[144.324386597,-38.1719779968],"type":"Point"}
}