{
  "type": "Feature",
  "properties": {
    "addr:full":"PO Box 916 Port Hedland WA 6721",
    "addr:postcode":"6721",
    "iso:country":"AU",
    "sg:address":"PO Box 916",
    "sg:city":"Port Hedland",
    "sg:classifiers":[
        {
            "category":"Building & Trades",
            "subcategory":"Landscaping Services",
            "type":"Services"
        }
    ],
    "sg:phone":"+61 417 954 484",
    "sg:postcode":"6721",
    "sg:province":"WA",
    "sg:tags":[
        "gardener"
    ],
    "wof:name":"Sticks 'N' Stones Gardening Services",
    "wof:placetype":"venue"
},
  "geometry": {"coordinates":[118.46824646,-20.7532691956],"type":"Point"}
}