{
  "type": "Feature",
  "properties": {
    "iso:country":"AU",
    "sg:address":"2 Glenavon Ave",
    "sg:city":"Cobram",
    "sg:classifiers":[
        {
            "category":"Professional",
            "subcategory":"Art Services",
            "type":"Services"
        }
    ],
    "sg:phone":"+61 3 5872 1839",
    "sg:postcode":"3644",
    "sg:province":"NSW",
    "sg:tags":[
        "decorator",
        "painter"
    ],
    "wof:name":"Ballerini V",
    "wof:placetype":"venue"
},
  "geometry": {"coordinates":[145.65133667000001,-35.9118232727],"type":"Point"}
}