{
  "type": "Feature",
  "properties": {
    "iso:country":"AU",
    "sg:address":"51 High St",
    "sg:city":"Kippa-Ring",
    "sg:classifiers":[
        {
            "category":"Train Station",
            "subcategory":"Light Rail",
            "type":"Transportation"
        }
    ],
    "sg:phone":"+61 7 3880 3199",
    "sg:postcode":"4021",
    "sg:province":"QLD",
    "sg:tags":[
        "equipment",
        "energy",
        "solar"
    ],
    "wof:name":"Sundream Homes",
    "wof:placetype":"venue"
},
  "geometry": {"coordinates":[153.090393,-27.225967],"type":"Point"}
}