{
  "type": "Feature",
  "properties": {
    "addr:full":"Shop 2 26 Wood St Beaconsfield VIC 3807",
    "addr:housenumber":"shop;26",
    "addr:postcode":"3807",
    "addr:street":"Wood St",
    "iso:country":"AU",
    "sg:address":"Shop 2 26 Wood St",
    "sg:city":"Beaconsfield",
    "sg:classifiers":[
        {
            "category":"Shopping",
            "subcategory":"Crafts & Fabrics",
            "type":"Retail Goods"
        }
    ],
    "sg:phone":"+61 3 9796 1667",
    "sg:postcode":"3807",
    "sg:province":"VIC",
    "sg:tags":[
        "supply"
    ],
    "wof:name":"Just Patchwork",
    "wof:placetype":"venue"
},
  "geometry": {"coordinates":[145.36785888700001,-38.0471000671],"type":"Point"}
}