{
  "type": "Feature",
  "properties": {
    "addr:full":"24 Cecilia St North Brighton SA 5048",
    "addr:housenumber":"24",
    "addr:postcode":"5048",
    "addr:street":"Cecilia St",
    "iso:country":"AU",
    "sg:address":"24 Cecilia St",
    "sg:city":"North Brighton",
    "sg:classifiers":[
        {
            "category":"Manufacturing",
            "subcategory":"Tools & Machinery",
            "type":"Manufacturing & Wholesale Goods"
        }
    ],
    "sg:phone":"+61 8 8358 3831",
    "sg:postcode":"5048",
    "sg:province":"SA",
    "sg:tags":[
        "earth",
        "excavating",
        "moving",
        "equipment"
    ],
    "wof:name":"Bobcat Blitz",
    "wof:placetype":"venue"
},
  "geometry": {"coordinates":[138.52475000000001,-35.007835],"type":"Point"}
}