{
  "type": "Feature",
  "properties": {
    "addr:full":"34 Byer St Enfield NSW 2136",
    "addr:housenumber":"34",
    "addr:postcode":"2136",
    "addr:street":"Byer St",
    "iso:country":"AU",
    "sg:address":"34 Byer St",
    "sg:city":"Enfield",
    "sg:classifiers":[
        {
            "category":"Building & Trades",
            "subcategory":"Construction",
            "type":"Services"
        }
    ],
    "sg:phone":"+61 418 611 368",
    "sg:postcode":"2136",
    "sg:province":"NSW",
    "sg:tags":[
        "rigging",
        "erection",
        "contractor"
    ],
    "wof:name":"Luscombe Tony",
    "wof:placetype":"venue"
},
  "geometry": {"coordinates":[151.093017578,-33.8876838684],"type":"Point"}
}