{
  "type": "Feature",
  "properties": {
    "iso:country":"AU",
    "sg:address":"7 Docker Pl",
    "sg:city":"Kambah",
    "sg:classifiers":[
        {
            "category":"Retail",
            "subcategory":"Repair Shop",
            "type":"Services"
        }
    ],
    "sg:phone":"+61 2 6231 5546",
    "sg:postcode":"2902",
    "sg:province":"ACT",
    "sg:tags":[
        "upholsterer"
    ],
    "wof:name":"Paul's Upholstery",
    "wof:placetype":"venue"
},
  "geometry": {"coordinates":[149.08958435100001,-35.3841667175],"type":"Point"}
}