{
  "type": "Feature",
  "properties": {
    "iso:country":"AU",
    "sg:address":"16 Gordon St",
    "sg:city":"Canberra City",
    "sg:classifiers":[
        {
            "category":"Government",
            "subcategory":"Court House",
            "type":"Public Place"
        }
    ],
    "sg:phone":"+61 2 6247 2726",
    "sg:postcode":"2601",
    "sg:province":"ACT",
    "sg:tags":[
        "personal",
        "marriage",
        "family",
        "counselling"
    ],
    "wof:name":"Gay Information & Support Services",
    "wof:placetype":"venue"
},
  "geometry": {"coordinates":[149.123443603,-35.2827072144],"type":"Point"}
}