{
  "type": "Feature",
  "properties": {
    "addr:full":"9 Webb Rd Airport West VIC 3042",
    "addr:housenumber":"9",
    "addr:postcode":"3042",
    "addr:street":"Webb Rd",
    "iso:country":"AU",
    "sg:address":"9 Webb Rd",
    "sg:city":"Airport West",
    "sg:classifiers":[
        {
            "category":"Building & Trades",
            "subcategory":"Construction",
            "type":"Services"
        }
    ],
    "sg:phone":"+61 412 095 789",
    "sg:postcode":"3042",
    "sg:province":"VIC",
    "sg:tags":[
        "earth",
        "excavating",
        "moving",
        "contractor"
    ],
    "wof:name":"Hughes Demolition",
    "wof:placetype":"venue"
},
  "geometry": {"coordinates":[144.89117431599999,-37.7162590027],"type":"Point"}
}