{
  "type": "Feature",
  "properties": {
    "addr:full":"PO Box 2352 Lower Templestowe VIC 3107",
    "addr:postcode":"3107",
    "iso:country":"AU",
    "sg:address":"PO Box 2352",
    "sg:city":"Lower Templestowe",
    "sg:classifiers":[
        {
            "category":"Social Services",
            "subcategory":"Job Training",
            "type":"Services"
        }
    ],
    "sg:phone":"+61 3 9855 8382",
    "sg:postcode":"3107",
    "sg:province":"VIC",
    "sg:tags":[
        "interpreter"
    ],
    "wof:name":"Connect Language Services",
    "wof:placetype":"venue"
},
  "geometry": {"coordinates":[145.11213684099999,-37.7572479248],"type":"Point"}
}