{
  "type": "Feature",
  "properties": {
    "addr:full":"PO Box 33 Strawberry Hills NSW 2013",
    "addr:postcode":"2013",
    "iso:country":"AU",
    "sg:address":"PO Box 33",
    "sg:city":"Strawberry Hills",
    "sg:classifiers":[
        {
            "category":"Home & Garden",
            "subcategory":"Building Materials",
            "type":"Retail Goods"
        }
    ],
    "sg:phone":"+61 2 8303 0580",
    "sg:postcode":"2013",
    "sg:province":"NSW",
    "sg:tags":[
        "supply"
    ],
    "wof:name":"Building Centre The",
    "wof:placetype":"venue"
},
  "geometry": {"coordinates":[151.213287353,-33.8940582275],"type":"Point"}
}