{
  "type": "Feature",
  "properties": {
    "addr:full":"18 Luxworth St Moorooka QLD 4105",
    "addr:housenumber":"18",
    "addr:postcode":"4105",
    "addr:street":"Luxworth St",
    "iso:country":"AU",
    "sg:address":"18 Luxworth St",
    "sg:city":"Moorooka",
    "sg:classifiers":[
        {
            "category":"Government",
            "subcategory":"Fire Station",
            "type":"Public Place"
        }
    ],
    "sg:phone":"+61 7 3892 2758",
    "sg:postcode":"4105",
    "sg:province":"QLD",
    "sg:tags":[
        "equipment",
        "protection",
        "consultant"
    ],
    "wof:name":"Blair Neil & Associates",
    "wof:placetype":"venue"
},
  "geometry": {"coordinates":[153.02354431099999,-27.5327205658],"type":"Point"}
}