{
  "type": "Feature",
  "properties": {
    "addr:full":"682 New Canterbury Rd Hurlstone Park NSW 2193",
    "addr:housenumber":"682",
    "addr:postcode":"2193",
    "addr:street":"New Canterbury Rd",
    "iso:country":"AU",
    "sg:address":"682 New Canterbury Rd",
    "sg:city":"Hurlstone Park",
    "sg:classifiers":[
        {
            "category":"Fast Food",
            "type":"Food & Drink"
        }
    ],
    "sg:phone":"+61 2 9559 7640",
    "sg:postcode":"2193",
    "sg:province":"NSW",
    "sg:tags":[
        "away",
        "take"
    ],
    "wof:name":"Golden Rice Chinese Take Away",
    "wof:placetype":"venue"
},
  "geometry": {"coordinates":[151.12939499999999,-33.904987],"type":"Point"}
}