{
  "type": "Feature",
  "properties": {
    "iso:country":"AU",
    "sg:address":"402 Canterbury Rd",
    "sg:city":"Canterbury",
    "sg:classifiers":[
        {
            "category":"Retail",
            "subcategory":"Auto Repair",
            "type":"Services"
        }
    ],
    "sg:phone":"+61 2 9787 1253",
    "sg:postcode":"2193",
    "sg:province":"NSW",
    "sg:tags":[
        "automotive",
        "air conditioning"
    ],
    "wof:name":"Strong Auto Air",
    "wof:placetype":"venue"
},
  "geometry": {"coordinates":[151.108475,-33.91671],"type":"Point"}
}