{
  "type": "Feature",
  "properties": {
    "addr:full":"U8/ 122 Brisbane Rd Labrador QLD 4215",
    "addr:housenumber":"122",
    "addr:postcode":"4215",
    "addr:street":"U8 /;Brisbane Rd",
    "iso:country":"AU",
    "sg:address":"U8/ 122 Brisbane Rd",
    "sg:city":"Labrador",
    "sg:classifiers":[
        {
            "category":"Professional",
            "subcategory":"Art Services",
            "type":"Services"
        }
    ],
    "sg:phone":"+61 7 5563 8844",
    "sg:postcode":"4215",
    "sg:province":"QLD",
    "sg:tags":[
        "interior",
        "designer"
    ],
    "wof:name":"Window Dresser Pty Ltd",
    "wof:placetype":"venue"
},
  "geometry": {"coordinates":[153.394805908,-27.9356384277],"type":"Point"}
}