{
  "type": "Feature",
  "properties": {
    "iso:country":"AU",
    "sg:address":"Coolalinga Shopping Centre Shop 10",
    "sg:city":"Coolalinga",
    "sg:classifiers":[
        {
            "category":"Restaurant",
            "type":"Food & Drink"
        }
    ],
    "sg:phone":"+61 8 8983 2766",
    "sg:postcode":"0835",
    "sg:province":"NT",
    "wof:name":"Chianti & Coffee",
    "wof:placetype":"venue"
},
  "geometry": {"coordinates":[131.041473,-12.52306],"type":"Point"}
}