{
  "type": "Feature",
  "properties": {
    "addr:full":"355 Nepean Hwy Dromana VIC 3936",
    "addr:housenumber":"355",
    "addr:postcode":"3936",
    "addr:street":"Nepean Hwy",
    "iso:country":"AU",
    "sg:address":"355 Nepean Hwy",
    "sg:city":"Dromana",
    "sg:classifiers":[
        {
            "category":"Fast Food",
            "type":"Food & Drink"
        }
    ],
    "sg:phone":"+61 3 5987 1413",
    "sg:postcode":"3936",
    "sg:province":"VIC",
    "sg:tags":[
        "away",
        "take"
    ],
    "wof:name":"La Best Pizza & Pasta",
    "wof:placetype":"venue"
},
  "geometry": {"coordinates":[144.97419738799999,-38.328327179],"type":"Point"}
}