{
  "type": "Feature",
  "properties": {
    "addr:full":"303 The Horsley Drv Fairfield NSW 2165",
    "addr:housenumber":"303",
    "addr:postcode":"2165",
    "addr:street":"The Horsley Drv",
    "iso:country":"AU",
    "sg:address":"303 The Horsley Drv",
    "sg:city":"Fairfield",
    "sg:classifiers":[
        {
            "category":"Wholesale",
            "subcategory":"Machinery & Supplies",
            "type":"Manufacturing & Wholesale Goods"
        }
    ],
    "sg:phone":"+61 2 9728 3399",
    "sg:postcode":"2165",
    "sg:province":"NSW",
    "wof:name":"Luna Mitre Saws",
    "wof:placetype":"venue"
},
  "geometry": {"coordinates":[150.95979309099999,-33.8690834045],"type":"Point"}
}