{
  "type": "Feature",
  "properties": {
    "addr:full":"6 George St Green Fields SA 5107",
    "addr:housenumber":"6",
    "addr:postcode":"5107",
    "addr:street":"George St Green",
    "iso:country":"AU",
    "sg:address":"6 George St",
    "sg:city":"Green Fields",
    "sg:classifiers":[
        {
            "category":"Professional",
            "type":"Services"
        }
    ],
    "sg:phone":"+61 8 8285 1599",
    "sg:postcode":"5107",
    "sg:province":"SA",
    "sg:tags":[
        "transport"
    ],
    "wof:name":"Bluestar Logistics",
    "wof:placetype":"venue"
},
  "geometry": {"coordinates":[138.60304260300001,-34.7928657532],"type":"Point"}
}