{
  "type": "Feature",
  "properties": {
    "iso:country":"AU",
    "sg:address":"PO Box 1988",
    "sg:city":"Port Lincoln",
    "sg:classifiers":[
        {
            "category":"Utilities",
            "subcategory":"Electric",
            "type":"Services"
        }
    ],
    "sg:phone":"+61 428 260 570",
    "sg:postcode":"5606",
    "sg:province":"SA",
    "sg:tags":[
        "electrical",
        "contractor"
    ],
    "wof:name":"Adam Wilkins Electrical",
    "wof:placetype":"venue"
},
  "geometry": {"coordinates":[135.852036,-34.728481],"type":"Point"}
}