{
  "type": "Feature",
  "properties": {
    "iso:country":"AU",
    "sg:address":"14 Langton Street",
    "sg:city":"Garbutt",
    "sg:classifiers":[
        {
            "category":"Retail",
            "subcategory":"Auto Repair",
            "type":"Services"
        }
    ],
    "sg:phone":"+61 7 4779 3338",
    "sg:postcode":"4814",
    "sg:province":"QLD",
    "sg:tags":[
        "repairer",
        "motor",
        "engineer"
    ],
    "wof:name":"Garbutt Auto Repairs",
    "wof:placetype":"venue"
},
  "geometry": {"coordinates":[146.77204900000001,-19.267082],"type":"Point"}
}