{
  "type": "Feature",
  "properties": {
    "addr:full":"291 River St Ballina NSW 2478",
    "addr:housenumber":"291",
    "addr:postcode":"2478",
    "addr:street":"River St",
    "iso:country":"AU",
    "sg:address":"291 River St",
    "sg:city":"Ballina",
    "sg:classifiers":[
        {
            "category":"Professional",
            "subcategory":"Computer Services",
            "type":"Services"
        }
    ],
    "sg:phone":"+61 2 6686 3055",
    "sg:postcode":"2478",
    "sg:province":"NSW",
    "sg:tags":[
        "repairs",
        "upgrade",
        "equipment"
    ],
    "wof:name":"Dirkwoods Computers",
    "wof:placetype":"venue"
},
  "geometry": {"coordinates":[153.553466797,-28.8674373627],"type":"Point"}
}