{
  "type": "Feature",
  "properties": {
    "addr:full":"23 Wilmot St Huonville TAS 7109",
    "addr:housenumber":"23",
    "addr:postcode":"7109",
    "addr:street":"Wilmot St",
    "iso:country":"AU",
    "sg:address":"23 Wilmot St",
    "sg:city":"Huonville",
    "sg:classifiers":[
        {
            "category":"Professional",
            "subcategory":"Employment Agencies",
            "type":"Services"
        }
    ],
    "sg:phone":"+61 3 6264 3441",
    "sg:postcode":"7109",
    "sg:province":"TAS",
    "sg:tags":[
        "provider",
        "internet"
    ],
    "wof:name":"Online Access Centres",
    "wof:placetype":"venue"
},
  "geometry": {"coordinates":[147.04820251500001,-43.031211853],"type":"Point"}
}