{
  "type": "Feature",
  "properties": {
    "iso:country":"AU",
    "sg:address":"5 Tate Pl",
    "sg:city":"Lugarno",
    "sg:classifiers":[
        {
            "category":"Professional",
            "type":"Services"
        }
    ],
    "sg:phone":"+61 2 9522 7593",
    "sg:postcode":"2210",
    "sg:province":"NSW",
    "sg:tags":[
        "marine",
        "contractor"
    ],
    "wof:name":"Azure Yachts",
    "wof:placetype":"venue"
},
  "geometry": {"coordinates":[151.04461699999999,-33.989059],"type":"Point"}
}