{
  "type": "Feature",
  "properties": {
    "iso:country":"AU",
    "sg:address":"\"Tilba Downs\" Pindari Rd",
    "sg:city":"Manoora",
    "sg:classifiers":[
        {
            "category":"Farming",
            "subcategory":"Farm",
            "type":"Manufacturing & Wholesale Goods"
        }
    ],
    "sg:phone":"+61 8 8848 4282",
    "sg:postcode":"5414",
    "sg:province":"SA",
    "sg:tags":[
        "farmer"
    ],
    "wof:name":"Schwartz J H & P R",
    "wof:placetype":"venue"
},
  "geometry": {"coordinates":[138.840377808,-33.9701919556],"type":"Point"}
}