{
  "type": "Feature",
  "properties": {
    "iso:country":"AU",
    "sg:address":"52 Beerburrum Rd",
    "sg:city":"Caboolture",
    "sg:classifiers":[
        {
            "category":"Retail",
            "subcategory":"Auto Repair",
            "type":"Services"
        }
    ],
    "sg:phone":"+61 7 5495 6511",
    "sg:postcode":"4510",
    "sg:province":"QLD",
    "sg:tags":[
        "testing",
        "inspection",
        "motor",
        "vehicle"
    ],
    "wof:name":"Caboolture Exhaust Centre",
    "wof:placetype":"venue"
},
  "geometry": {"coordinates":[152.95045500000001,-27.076687],"type":"Point"}
}