{
  "type": "Feature",
  "properties": {
    "addr:full":"16 Kingston Rd Surrey Hills VIC 3127",
    "addr:housenumber":"16",
    "addr:postcode":"3127",
    "addr:street":"Kingston Rd",
    "iso:country":"AU",
    "sg:address":"16 Kingston Rd",
    "sg:city":"Surrey Hills",
    "sg:classifiers":[
        {
            "category":"Professional",
            "subcategory":"Business Services",
            "type":"Services"
        }
    ],
    "sg:phone":"+61 3 9830 1366",
    "sg:postcode":"3127",
    "sg:province":"VIC",
    "sg:tags":[
        "broker"
    ],
    "wof:name":"Alison Dews & Associates",
    "wof:placetype":"venue"
},
  "geometry": {"coordinates":[145.088165283,-37.8236198425],"type":"Point"}
}