{
  "type": "Feature",
  "properties": {
    "addr:full":"Cnr Yalgoo Ave & Stevens St White Gum Valley WA 6162",
    "addr:postcode":"6162",
    "addr:street":"Cnr Yalgoo Ave & Stevens St",
    "iso:country":"AU",
    "sg:address":"Cnr Yalgoo Ave & Stevens St",
    "sg:city":"White Gum Valley",
    "sg:classifiers":[
        {
            "category":"Education",
            "subcategory":"School",
            "type":"Public Place"
        }
    ],
    "sg:phone":"+61 8 9335 7933",
    "sg:postcode":"6162",
    "sg:province":"WA",
    "sg:tags":[
        "state",
        "except",
        "nsw"
    ],
    "wof:name":"Kim Beazley School",
    "wof:placetype":"venue"
},
  "geometry": {"coordinates":[115.77262899999999,-32.059624],"type":"Point"}
}