{
  "type": "Feature",
  "properties": {
    "iso:country":"AU",
    "sg:address":"174 Basting St",
    "sg:city":"Northcote",
    "sg:classifiers":[
        {
            "category":"Building & Trades",
            "subcategory":"Construction",
            "type":"Services"
        }
    ],
    "sg:phone":"+61 402 182 420",
    "sg:postcode":"3070",
    "sg:province":"VIC",
    "sg:tags":[
        "fencing",
        "contractor"
    ],
    "wof:name":"TLB Fencing",
    "wof:placetype":"venue"
},
  "geometry": {"coordinates":[145.012863,-37.775703],"type":"Point"}
}