{
  "type": "Feature",
  "properties": {
    "addr:full":"116 Alderley Ave Alderley QLD 4051",
    "addr:housenumber":"116",
    "addr:postcode":"4051",
    "addr:street":"Alderley Ave",
    "iso:country":"AU",
    "sg:address":"116 Alderley Ave",
    "sg:city":"Alderley",
    "sg:classifiers":[
        {
            "category":"Professional",
            "subcategory":"Accounting & Tax Preparation",
            "type":"Services"
        }
    ],
    "sg:phone":"+61 7 3856 4006",
    "sg:postcode":"4051",
    "sg:province":"QLD",
    "sg:tags":[
        "consultant",
        "taxation"
    ],
    "wof:name":"Cowlishaw & Co",
    "wof:placetype":"venue"
},
  "geometry": {"coordinates":[153.00190734899999,-27.4247169495],"type":"Point"}
}