{
  "type": "Feature",
  "properties": {
    "addr:full":"280 Charlestown Rd Charlestown NSW 2290",
    "addr:housenumber":"280",
    "addr:postcode":"2290",
    "addr:street":"Charlestown Rd",
    "iso:country":"AU",
    "sg:address":"280 Charlestown Rd",
    "sg:city":"Charlestown",
    "sg:classifiers":[
        {
            "category":"Personal",
            "subcategory":"Shoe Repair & Shine",
            "type":"Services"
        }
    ],
    "sg:phone":"+61 2 4942 5769",
    "sg:postcode":"2290",
    "sg:province":"NSW",
    "sg:tags":[
        "footwear"
    ],
    "wof:name":"Specialist Shoemaker",
    "wof:placetype":"venue"
},
  "geometry": {"coordinates":[151.691680908,-32.9590530396],"type":"Point"}
}