{
  "type": "Feature",
  "properties": {
    "addr:full":"72 Cochranes Rd Moorabbin VIC 3189",
    "addr:housenumber":"72",
    "addr:postcode":"3189",
    "addr:street":"Cochranes Rd",
    "iso:country":"AU",
    "sg:address":"72 Cochranes Rd",
    "sg:city":"Moorabbin",
    "sg:classifiers":[
        {
            "category":"Professional",
            "subcategory":"Printing & Photocopies",
            "type":"Services"
        }
    ],
    "sg:phone":"+61 3 9553 6886",
    "sg:postcode":"3189",
    "sg:province":"VIC",
    "sg:tags":[
        "embroidery"
    ],
    "wof:name":"Smart Stitches Design & Embroidery",
    "wof:placetype":"venue"
},
  "geometry": {"coordinates":[145.068603516,-37.9431190491],"type":"Point"}
}