{
  "type": "Feature",
  "properties": {
    "addr:full":"56 Chapel St Cowes VIC 3922",
    "addr:housenumber":"56",
    "addr:postcode":"3922",
    "addr:street":"Chapel St",
    "iso:country":"AU",
    "sg:address":"56 Chapel St",
    "sg:city":"Cowes",
    "sg:classifiers":[
        {
            "category":"Education",
            "subcategory":"Kindergarten",
            "type":"Public Place"
        }
    ],
    "sg:phone":"+61 3 5952 2336",
    "sg:postcode":"3922",
    "sg:province":"VIC",
    "sg:tags":[
        "pre-schools"
    ],
    "wof:name":"Phillip Island Kindergarten",
    "wof:placetype":"venue"
},
  "geometry": {"coordinates":[145.23991394000001,-38.4501571655],"type":"Point"}
}