{
  "type": "Feature",
  "properties": {
    "addr:full":"39 Charles St North Rockhampton QLD 4701",
    "addr:housenumber":"39",
    "addr:postcode":"4701",
    "addr:street":"Charles St North",
    "iso:country":"AU",
    "sg:address":"39 Charles St",
    "sg:city":"North Rockhampton",
    "sg:classifiers":[
        {
            "category":"Professional",
            "subcategory":"Accounting & Tax Preparation",
            "type":"Services"
        }
    ],
    "sg:phone":"+61 7 4927 5569",
    "sg:postcode":"4701",
    "sg:province":"QLD",
    "sg:tags":[
        "jukebox"
    ],
    "wof:name":"Acoustical Enterprises",
    "wof:placetype":"venue"
},
  "geometry": {"coordinates":[150.52903747600001,-23.3665275574],"type":"Point"}
}