{
  "type": "Feature",
  "properties": {
    "addr:full":"320 Princes Hwy Rockdale NSW 2216",
    "addr:housenumber":"320",
    "addr:postcode":"2216",
    "addr:street":"Princes Hwy",
    "iso:country":"AU",
    "sg:address":"320 Princes Hwy",
    "sg:city":"Rockdale",
    "sg:classifiers":[
        {
            "category":"Utilities",
            "subcategory":"Mobile Phone",
            "type":"Services"
        }
    ],
    "sg:phone":"+61 2 9556 2088",
    "sg:postcode":"2216",
    "sg:province":"NSW",
    "sg:tags":[
        "repair",
        "telephone"
    ],
    "wof:name":"Fonebiz Australia Pty Ltd",
    "wof:placetype":"venue"
},
  "geometry": {"coordinates":[151.14138800000001,-33.945873],"type":"Point"}
}