{
  "type": "Feature",
  "properties": {
    "iso:country":"AU",
    "sg:address":"110 Nepean Hwy",
    "sg:city":"Aspendale",
    "sg:classifiers":[
        {
            "category":"Health Services",
            "subcategory":"Dentist",
            "type":"Services"
        }
    ],
    "sg:phone":"+61 3 9580 3904",
    "sg:postcode":"3195",
    "sg:province":"VIC",
    "wof:name":"Walsh-Buckley James Dr",
    "wof:placetype":"venue"
},
  "geometry": {"coordinates":[145.099777222,-38.0240516663],"type":"Point"}
}