{
  "type": "Feature",
  "properties": {
    "addr:full":"179 Otago Bay Rd Otago TAS 7017",
    "addr:housenumber":"179",
    "addr:postcode":"7017",
    "addr:street":"Otago Bay Rd",
    "iso:country":"AU",
    "sg:address":"179 Otago Bay Rd",
    "sg:city":"Otago",
    "sg:classifiers":[
        {
            "category":"Building & Trades",
            "subcategory":"Construction",
            "type":"Services"
        }
    ],
    "sg:phone":"+61 3 6272 5997",
    "sg:postcode":"7017",
    "sg:province":"TAS",
    "sg:tags":[
        "stonework",
        "stone",
        "mason"
    ],
    "wof:name":"Brick & Concrete Dwelling",
    "wof:placetype":"venue"
},
  "geometry": {"coordinates":[147.28939819300001,-42.7993621826],"type":"Point"}
}