{
  "type": "Feature",
  "properties": {
    "iso:country":"AU",
    "sg:address":"4 75 Ford St",
    "sg:city":"Beechworth",
    "sg:classifiers":[
        {
            "category":"Personal",
            "subcategory":"Beauty Salon",
            "type":"Services"
        }
    ],
    "sg:phone":"+61 3 5728 2434",
    "sg:postcode":"3747",
    "sg:province":"VIC",
    "sg:tags":[
        "hairdresser"
    ],
    "wof:name":"Rubens Of Beechworth Eco Hairdressing",
    "wof:placetype":"venue"
},
  "geometry": {"coordinates":[146.68632500000001,-36.359695],"type":"Point"}
}