{
  "type": "Feature",
  "properties": {
    "iso:country":"AU",
    "sg:address":"176 Rogers Rd",
    "sg:city":"Cape Schanck",
    "sg:classifiers":[
        {
            "category":"Farming",
            "subcategory":"Vineyard",
            "type":"Manufacturing & Wholesale Goods"
        }
    ],
    "sg:phone":"+61 3 5988 5350",
    "sg:postcode":"3939",
    "sg:province":"VIC",
    "sg:tags":[
        "winery"
    ],
    "wof:name":"La Campagna Winery",
    "wof:placetype":"venue"
},
  "geometry": {"coordinates":[144.92089843799999,-38.4336433411],"type":"Point"}
}