{
  "type": "Feature",
  "properties": {
    "addr:full":"26 Carpenter St Brighton VIC 3186",
    "addr:housenumber":"26",
    "addr:postcode":"3186",
    "addr:street":"Carpenter St",
    "iso:country":"AU",
    "sg:address":"26 Carpenter St",
    "sg:city":"Brighton",
    "sg:classifiers":[
        {
            "category":"Health Services",
            "subcategory":"Doctor",
            "type":"Services"
        }
    ],
    "sg:phone":"+61 3 9592 0222",
    "sg:postcode":"3186",
    "sg:province":"VIC",
    "sg:tags":[
        "medical",
        "practitioner"
    ],
    "wof:name":"Leber Danny Dr",
    "wof:placetype":"venue"
},
  "geometry": {"coordinates":[144.994216919,-37.9147109985],"type":"Point"}
}