{
  "type": "Feature",
  "properties": {
    "addr:full":"Suite 228, Level 2/180 Queen St Brisbane QLD 4000",
    "addr:housenumber":"/ 180",
    "addr:postcode":"4000",
    "addr:street":"228;Queen St",
    "iso:country":"AU",
    "sg:address":"Suite 228, Level 2/180 Queen St",
    "sg:city":"Brisbane",
    "sg:classifiers":[
        {
            "category":"Professional",
            "subcategory":"Accounting & Tax Preparation",
            "type":"Services"
        }
    ],
    "sg:phone":"+61 7 3012 7310",
    "sg:postcode":"4000",
    "sg:province":"QLD",
    "sg:tags":[
        "consultant",
        "taxation"
    ],
    "wof:name":"Stephen Blake Chartered Accountants",
    "wof:placetype":"venue"
},
  "geometry": {"coordinates":[153.02630615199999,-27.4686336517],"type":"Point"}
}