{
  "type": "Feature",
  "properties": {
    "addr:full":"614 Stirling Hwy Mosman Park WA 6012",
    "addr:housenumber":"614",
    "addr:postcode":"6012",
    "addr:street":"Stirling Hwy Mosman",
    "iso:country":"AU",
    "sg:address":"614 Stirling Hwy",
    "sg:city":"Mosman Park",
    "sg:classifiers":[
        {
            "category":"Professional",
            "subcategory":"Accounting & Tax Preparation",
            "type":"Services"
        }
    ],
    "sg:phone":"+61 8 9385 3784",
    "sg:postcode":"6012",
    "sg:province":"WA",
    "sg:tags":[
        "consultant",
        "taxation"
    ],
    "wof:name":"H & R Block",
    "wof:placetype":"venue"
},
  "geometry": {"coordinates":[115.75785827599999,-32.0070381165],"type":"Point"}
}