{
  "type": "Feature",
  "properties": {
    "addr:full":"535 Main St Mordialloc VIC 3195",
    "addr:housenumber":"535",
    "addr:postcode":"3195",
    "addr:street":"Main St",
    "iso:country":"AU",
    "sg:address":"535 Main St",
    "sg:city":"Mordialloc",
    "sg:classifiers":[
        {
            "category":"Personal",
            "subcategory":"Beauty Salon",
            "type":"Services"
        }
    ],
    "sg:phone":"+61 3 9580 4855",
    "sg:postcode":"3195",
    "sg:province":"VIC",
    "sg:tags":[
        "hairdresser"
    ],
    "wof:name":"A1 Hairmax",
    "wof:placetype":"venue"
},
  "geometry": {"coordinates":[145.087615967,-38.0075645447],"type":"Point"}
}