{
  "type": "Feature",
  "properties": {
    "addr:full":"11 Kalang Rd Elanora Heights NSW 2101",
    "addr:housenumber":"11",
    "addr:postcode":"2101",
    "addr:street":"Kalang Rd",
    "iso:country":"AU",
    "sg:address":"11 Kalang Rd",
    "sg:city":"Elanora Heights",
    "sg:classifiers":[
        {
            "category":"Health Services",
            "subcategory":"Doctor",
            "type":"Services"
        }
    ],
    "sg:phone":"+61 2 9913 8126",
    "sg:postcode":"2101",
    "sg:province":"NSW",
    "sg:tags":[
        "medical",
        "practitioner"
    ],
    "wof:name":"Brown Norman",
    "wof:placetype":"venue"
},
  "geometry": {"coordinates":[151.279999,-33.700268],"type":"Point"}
}