{
  "type": "Feature",
  "properties": {
    "addr:full":"South Maddingley Rd Bacchus Marsh VIC 3340",
    "addr:postcode":"3340",
    "addr:street":"Maddingley Rd",
    "iso:country":"AU",
    "sg:address":"South Maddingley Rd",
    "sg:city":"Bacchus Marsh",
    "sg:classifiers":[
        {
            "category":"Education",
            "subcategory":"School",
            "type":"Public Place"
        }
    ],
    "sg:phone":"+61 3 5366 4800",
    "sg:postcode":"3340",
    "sg:province":"VIC",
    "sg:tags":[
        "co-educational"
    ],
    "wof:name":"Bacchus Marsh Grammar School",
    "wof:placetype":"venue"
},
  "geometry": {"coordinates":[144.432999,-37.687595],"type":"Point"}
}