{
  "type": "Feature",
  "properties": {
    "addr:full":"PO Box 71 Belfield NSW 2191",
    "addr:postcode":"2191",
    "iso:country":"AU",
    "sg:address":"PO Box 71",
    "sg:city":"Belfield",
    "sg:classifiers":[
        {
            "category":"Building & Trades",
            "subcategory":"Plumbing",
            "type":"Services"
        }
    ],
    "sg:phone":"+61 2 9214 8363",
    "sg:postcode":"2191",
    "sg:province":"NSW",
    "sg:tags":[
        "drainers"
    ],
    "wof:name":"Western Water Blasting",
    "wof:placetype":"venue"
},
  "geometry": {"coordinates":[151.08616599999999,-33.90453],"type":"Point"}
}