{
  "type": "Feature",
  "properties": {
    "iso:country":"AU",
    "sg:address":"18 Munro St",
    "sg:city":"Auchenflower",
    "sg:classifiers":[
        {
            "category":"Personal",
            "subcategory":"Massage",
            "type":"Services"
        }
    ],
    "sg:phone":"+61 7 3701 2285",
    "sg:postcode":"4066",
    "sg:province":"QLD",
    "sg:tags":[
        "therapy"
    ],
    "wof:name":"Sanctuary Aromatherapy & Massage Therapy",
    "wof:placetype":"venue"
},
  "geometry": {"coordinates":[152.99418640100001,-27.473772049],"type":"Point"}
}