{
  "type": "Feature",
  "properties": {
    "addr:full":"4/ 26 Lock Ave Werribee VIC 3030",
    "addr:housenumber":"/ 26",
    "addr:postcode":"3030",
    "addr:street":"Lock Ave",
    "iso:country":"AU",
    "sg:address":"4/ 26 Lock Ave",
    "sg:city":"Werribee",
    "sg:classifiers":[
        {
            "category":"Retail",
            "subcategory":"Storage",
            "type":"Services"
        }
    ],
    "sg:phone":"+61 3 9741 8681",
    "sg:postcode":"3030",
    "sg:province":"VIC",
    "sg:tags":[
        "removal",
        "furniture"
    ],
    "wof:name":"Westend Selfstorage",
    "wof:placetype":"venue"
},
  "geometry": {"coordinates":[144.66137699999999,-37.911121],"type":"Point"}
}