{
  "type": "Feature",
  "properties": {
    "iso:country":"AU",
    "sg:address":"27 Fourth St",
    "sg:city":"Blackheath",
    "sg:classifiers":[
        {
            "category":"Building & Trades",
            "subcategory":"Construction",
            "type":"Services"
        }
    ],
    "sg:phone":"+61 415 631 552",
    "sg:postcode":"2785",
    "sg:province":"NSW",
    "sg:tags":[
        "joiner",
        "carpenter"
    ],
    "wof:name":"Oldfield's Carpentry",
    "wof:placetype":"venue"
},
  "geometry": {"coordinates":[150.29570007300001,-33.6333694458],"type":"Point"}
}