{
  "type": "Feature",
  "properties": {
    "addr:full":"92 Mollison St Kyneton VIC 3444",
    "addr:housenumber":"92",
    "addr:postcode":"3444",
    "addr:street":"Mollison St",
    "iso:country":"AU",
    "sg:address":"92 Mollison St",
    "sg:city":"Kyneton",
    "sg:classifiers":[
        {
            "category":"Education",
            "subcategory":"School",
            "type":"Public Place"
        }
    ],
    "sg:phone":"+61 3 5422 3500",
    "sg:postcode":"3444",
    "sg:province":"VIC",
    "sg:tags":[
        "supply"
    ],
    "wof:name":"Kyneton Art Supplies",
    "wof:placetype":"venue"
},
  "geometry": {"coordinates":[144.45346069300001,-37.2487869263],"type":"Point"}
}