{
  "type": "Feature",
  "properties": {
    "iso:country":"AU",
    "sg:address":"29a Twin St",
    "sg:city":"Adelaide",
    "sg:classifiers":[
        {
            "category":"Retail",
            "subcategory":"Event Space",
            "type":"Services"
        }
    ],
    "sg:phone":"+61 8 8232 0950",
    "sg:postcode":"5000",
    "sg:province":"SA",
    "sg:tags":[
        "function",
        "organiser"
    ],
    "wof:name":"The Jade Monkey",
    "wof:placetype":"venue"
},
  "geometry": {"coordinates":[138.60466003400001,-34.9238777161],"type":"Point"}
}