{
  "type": "Feature",
  "properties": {
    "iso:country":"AU",
    "sg:address":"Shp9/ 10 Croydon Rd",
    "sg:city":"Logan Central",
    "sg:classifiers":[
        {
            "category":"Personal",
            "subcategory":"Barber",
            "type":"Services"
        }
    ],
    "sg:phone":"+61 7 3208 9908",
    "sg:postcode":"4114",
    "sg:province":"QLD",
    "wof:name":"Hair Care Studio",
    "wof:placetype":"venue"
},
  "geometry": {"coordinates":[153.104644775,-27.6364841461],"type":"Point"}
}