{
  "type": "Feature",
  "properties": {
    "addr:full":"1990 Logan Rd Upper Mt Gravatt QLD 4122",
    "addr:housenumber":"1990",
    "addr:postcode":"4122",
    "addr:street":"Logan Rd Upper",
    "iso:country":"AU",
    "sg:address":"1990 Logan Rd",
    "sg:city":"Upper Mt Gravatt",
    "sg:classifiers":[
        {
            "category":"Wholesale",
            "subcategory":"Home Furnishings",
            "type":"Manufacturing & Wholesale Goods"
        }
    ],
    "sg:phone":"+61 7 3349 8955",
    "sg:postcode":"4122",
    "sg:province":"QLD",
    "sg:tags":[
        "tile",
        "wholesaler",
        "mfrs",
        "carpet"
    ],
    "wof:name":"Redbook Carpets",
    "wof:placetype":"venue"
},
  "geometry": {"coordinates":[153.08062744099999,-27.5582733154],"type":"Point"}
}