{
  "type": "Feature",
  "properties": {
    "addr:full":"Unit 4/ 12 Hayter St Currumbin QLD 4223",
    "addr:housenumber":"12",
    "addr:postcode":"4223",
    "addr:street":"Hayter St",
    "iso:country":"AU",
    "sg:address":"Unit 4/ 12 Hayter St",
    "sg:city":"Currumbin",
    "sg:classifiers":[
        {
            "category":"Retail",
            "subcategory":"Auto Repair",
            "type":"Services"
        }
    ],
    "sg:phone":"+61 7 5598 3911",
    "sg:postcode":"4223",
    "sg:province":"QLD",
    "sg:tags":[
        "recapping",
        "repairing",
        "retreading",
        "tyre"
    ],
    "wof:name":"Currumbin Discount Tyres",
    "wof:placetype":"venue"
},
  "geometry": {"coordinates":[153.474685669,-28.1458396912],"type":"Point"}
}