{
  "type": "Feature",
  "properties": {
    "addr:full":"Brisbane Water Private Hosp. Consulting Rms,21 Vid Woy Woy NSW 2256",
    "addr:housenumber":"21",
    "addr:postcode":"2256",
    "addr:street":"Rms;Vid Woy",
    "iso:country":"AU",
    "sg:address":"Brisbane Water Private Hosp. Consulting Rms,21 Vid",
    "sg:city":"Woy Woy",
    "sg:classifiers":[
        {
            "category":"Health Services",
            "subcategory":"Doctor",
            "type":"Services"
        }
    ],
    "sg:phone":"+61 2 4343 0274",
    "sg:postcode":"2256",
    "sg:province":"NSW",
    "sg:tags":[
        "medical",
        "practitioner"
    ],
    "wof:name":"Duke Peter Dr",
    "wof:placetype":"venue"
},
  "geometry": {"coordinates":[151.32211303700001,-33.4952545166],"type":"Point"}
}