{
  "type": "Feature",
  "properties": {
    "iso:country":"AU",
    "sg:address":"35 Kelsey St",
    "sg:city":"Coorparoo",
    "sg:classifiers":[
        {
            "category":"Real Estate",
            "subcategory":"Real Estate Agent",
            "type":"Services"
        }
    ],
    "sg:phone":"+61 7 3395 1288",
    "sg:postcode":"4151",
    "sg:province":"QLD",
    "wof:name":"Lifestyle Property Sales",
    "wof:placetype":"venue"
},
  "geometry": {"coordinates":[153.06794738799999,-27.4994678497],"type":"Point"}
}