{
  "type": "Feature",
  "properties": {
    "addr:full":"101 Burwood Rd Concord NSW 2137",
    "addr:housenumber":"101",
    "addr:postcode":"2137",
    "addr:street":"Burwood Rd",
    "iso:country":"AU",
    "sg:address":"101 Burwood Rd",
    "sg:city":"Concord",
    "sg:classifiers":[
        {
            "category":"Home & Garden",
            "subcategory":"Carpets & Floor Coverings",
            "type":"Retail Goods"
        }
    ],
    "sg:phone":"+61 2 9747 1686",
    "sg:postcode":"2137",
    "sg:province":"NSW",
    "sg:tags":[
        "flooring",
        "parquet"
    ],
    "wof:name":"Concord Timber Flooring",
    "wof:placetype":"venue"
},
  "geometry": {"coordinates":[151.10794067399999,-33.8630943298],"type":"Point"}
}