{
  "type": "Feature",
  "properties": {
    "iso:country":"AU",
    "sg:address":"Unit D 58 Stanley St",
    "sg:city":"Peakhurst",
    "sg:classifiers":[
        {
            "category":"Autos & Motor Vehicles",
            "subcategory":"Boat Sales",
            "type":"Retail Goods"
        }
    ],
    "sg:phone":"+61 2 9584 0055",
    "sg:postcode":"2210",
    "sg:province":"NSW",
    "sg:tags":[
        "builder",
        "yacht",
        "repairer"
    ],
    "wof:name":"Windward Mark Marine Services",
    "wof:placetype":"venue"
},
  "geometry": {"coordinates":[151.061554,-33.963001],"type":"Point"}
}