{
  "type": "Feature",
  "properties": {
    "addr:full":"1/ 47 Aberford St Coonamble NSW 2829",
    "addr:housenumber":"/ 47",
    "addr:postcode":"2829",
    "addr:street":"Aberford St",
    "iso:country":"AU",
    "sg:address":"1/ 47 Aberford St",
    "sg:city":"Coonamble",
    "sg:classifiers":[
        {
            "category":"Professional",
            "subcategory":"Accounting & Tax Preparation",
            "type":"Services"
        }
    ],
    "sg:phone":"+61 2 6822 3253",
    "sg:postcode":"2829",
    "sg:province":"NSW",
    "sg:tags":[
        "consultant",
        "taxation"
    ],
    "wof:name":"Watson David R & Co",
    "wof:placetype":"venue"
},
  "geometry": {"coordinates":[148.392181397,-30.954908371],"type":"Point"}
}