{
  "type": "Feature",
  "properties": {
    "iso:country":"AU",
    "sg:address":"Suite A7 550 Canning Hwy",
    "sg:city":"Attadale",
    "sg:classifiers":[
        {
            "category":"Education",
            "subcategory":"Special Training",
            "type":"Public Place"
        }
    ],
    "sg:phone":"+61 8 9330 8989",
    "sg:postcode":"6156",
    "sg:province":"WA",
    "sg:tags":[
        "development"
    ],
    "wof:name":"Agenda Communication Pty Ltd",
    "wof:placetype":"venue"
},
  "geometry": {"coordinates":[115.800613,-32.032238],"type":"Point"}
}