{
  "type": "Feature",
  "properties": {
    "addr:full":"69 Smith Rd Woodridge QLD 4114",
    "addr:housenumber":"69",
    "addr:postcode":"4114",
    "addr:street":"Smith Rd",
    "iso:country":"AU",
    "sg:address":"69 Smith Rd",
    "sg:city":"Woodridge",
    "sg:classifiers":[
        {
            "category":"Wholesale",
            "subcategory":"Machinery & Supplies",
            "type":"Manufacturing & Wholesale Goods"
        }
    ],
    "sg:phone":"+61 418 195 789",
    "sg:postcode":"4114",
    "sg:province":"QLD",
    "sg:tags":[
        "equipment",
        "system",
        "elevating",
        "conveying"
    ],
    "wof:name":"Belcon Pty Ltd",
    "wof:placetype":"venue"
},
  "geometry": {"coordinates":[153.108276367,-27.6286506653],"type":"Point"}
}