{
  "type": "Feature",
  "properties": {
    "addr:full":"10 Captain Cook Hwy Craiglie QLD 4871",
    "addr:housenumber":"10",
    "addr:postcode":"4871",
    "addr:street":"Captain Cook Hwy",
    "iso:country":"AU",
    "sg:address":"10 Captain Cook Hwy",
    "sg:city":"Craiglie",
    "sg:classifiers":[
        {
            "category":"Retail",
            "subcategory":"Auto Repair",
            "type":"Services"
        }
    ],
    "sg:phone":"+61 7 4098 5055",
    "sg:postcode":"4871",
    "sg:province":"QLD",
    "sg:tags":[
        "repairer",
        "motor",
        "engineer"
    ],
    "wof:name":"Walkers Auto Repairs",
    "wof:placetype":"venue"
},
  "geometry": {"coordinates":[145.56617736800001,-16.658197403],"type":"Point"}
}