{
  "type": "Feature",
  "properties": {
    "addr:full":"33 Agincourt Rd Marsfield NSW 2122",
    "addr:housenumber":"33",
    "addr:postcode":"2122",
    "addr:street":"Agincourt Rd",
    "iso:country":"AU",
    "sg:address":"33 Agincourt Rd",
    "sg:city":"Marsfield",
    "sg:classifiers":[
        {
            "category":"Education",
            "subcategory":"Kindergarten",
            "type":"Public Place"
        }
    ],
    "sg:phone":"+61 2 9877 0562",
    "sg:postcode":"2122",
    "sg:province":"NSW",
    "sg:tags":[
        "pre-schools"
    ],
    "wof:name":"Imaginations Pre-School",
    "wof:placetype":"venue"
},
  "geometry": {"coordinates":[151.10215759299999,-33.7763938904],"type":"Point"}
}