{
  "type": "Feature",
  "properties": {
    "iso:country":"AU",
    "sg:address":"Hunter St",
    "sg:city":"Rutherglen",
    "sg:classifiers":[
        {
            "category":"Commercial Area",
            "type":"Public Place"
        }
    ],
    "sg:phone":"+61 2 6032 9311",
    "sg:postcode":"3685",
    "sg:province":"VIC",
    "sg:tags":[
        "heavy",
        "carrier"
    ],
    "wof:name":"Francis Hec",
    "wof:placetype":"venue"
},
  "geometry": {"coordinates":[146.46720886200001,-36.0570755005],"type":"Point"}
}