{
  "type": "Feature",
  "properties": {
    "iso:country":"AU",
    "sg:address":"17 Lyell St",
    "sg:city":"Mittagong",
    "sg:classifiers":[
        {
            "category":"Utilities",
            "subcategory":"Water",
            "type":"Services"
        }
    ],
    "sg:phone":"+61 2 4871 3585",
    "sg:postcode":"2575",
    "sg:province":"NSW",
    "sg:tags":[
        "hot",
        "system"
    ],
    "wof:name":"Plumbers&#039; Supplies Co-op",
    "wof:placetype":"venue"
},
  "geometry": {"coordinates":[150.431350708,-34.4494819641],"type":"Point"}
}