{
  "type": "Feature",
  "properties": {
    "addr:full":"392 Coolangatta Rd Tugun QLD 4224",
    "addr:housenumber":"392",
    "addr:postcode":"4224",
    "addr:street":"Coolangatta Rd",
    "iso:country":"AU",
    "sg:address":"392 Coolangatta Rd",
    "sg:city":"Tugun",
    "sg:classifiers":[
        {
            "category":"Manufacturing",
            "subcategory":"Buildings",
            "type":"Manufacturing & Wholesale Goods"
        }
    ],
    "sg:phone":"+61 1300 730 022",
    "sg:postcode":"4224",
    "sg:province":"QLD",
    "sg:tags":[
        "house",
        "gazebo",
        "shade"
    ],
    "wof:name":"Gazeboz",
    "wof:placetype":"venue"
},
  "geometry": {"coordinates":[153.501556397,-28.1516494751],"type":"Point"}
}