{
  "type": "Feature",
  "properties": {
    "addr:full":"PO Box 57 Wallacia NSW 2745",
    "addr:postcode":"2745",
    "iso:country":"AU",
    "sg:address":"PO Box 57",
    "sg:city":"Wallacia",
    "sg:classifiers":[
        {
            "category":"Home & Garden",
            "subcategory":"Carpets & Floor Coverings",
            "type":"Retail Goods"
        }
    ],
    "sg:phone":"+61 2 4773 8824",
    "sg:postcode":"2745",
    "sg:province":"NSW",
    "sg:tags":[
        "tile",
        "wall",
        "layer"
    ],
    "wof:name":"Colin Boyd Tiling",
    "wof:placetype":"venue"
},
  "geometry": {"coordinates":[150.64050293,-33.8655014038],"type":"Point"}
}