{
  "type": "Feature",
  "properties": {
    "addr:full":"408 Milne Rd Redwood Park SA 5097",
    "addr:housenumber":"408",
    "addr:postcode":"5097",
    "addr:street":"Milne Rd",
    "iso:country":"AU",
    "sg:address":"408 Milne Rd",
    "sg:city":"Redwood Park",
    "sg:classifiers":[
        {
            "category":"Building & Trades",
            "subcategory":"Cleaning & Sanitation",
            "type":"Services"
        }
    ],
    "sg:phone":"+61 439 365 981",
    "sg:postcode":"5097",
    "sg:province":"SA",
    "sg:tags":[
        "industrial",
        "commercial",
        "contractor"
    ],
    "wof:name":"Spic N Span",
    "wof:placetype":"venue"
},
  "geometry": {"coordinates":[138.705612183,-34.8167686462],"type":"Point"}
}