{
  "type": "Feature",
  "properties": {
    "addr:full":"880 Pacific Hwy Gordon NSW 2072",
    "addr:housenumber":"880",
    "addr:postcode":"2072",
    "addr:street":"Pacific Hwy",
    "iso:country":"AU",
    "sg:address":"880 Pacific Hwy",
    "sg:city":"Gordon",
    "sg:classifiers":[
        {
            "category":"Autos & Motor Vehicles",
            "subcategory":"Automobile Sales",
            "type":"Retail Goods"
        }
    ],
    "sg:phone":"+61 2 8817 7777",
    "sg:postcode":"2072",
    "sg:province":"NSW",
    "sg:tags":[
        "car",
        "new"
    ],
    "wof:name":"Alto Mitsubishi",
    "wof:placetype":"venue"
},
  "geometry": {"coordinates":[151.148803711,-33.7521934509],"type":"Point"}
}