{
  "type": "Feature",
  "properties": {
    "addr:full":"Bong Bong Rd Mittagong NSW 2575",
    "addr:postcode":"2575",
    "addr:street":"Bong Rd",
    "iso:country":"AU",
    "sg:address":"Bong Bong Rd",
    "sg:city":"Mittagong",
    "sg:classifiers":[
        {
            "category":"Education",
            "subcategory":"School",
            "type":"Public Place"
        }
    ],
    "sg:phone":"+61 2 4871 1636",
    "sg:postcode":"2575",
    "sg:province":"NSW",
    "sg:tags":[
        "state",
        "-",
        "nsw"
    ],
    "wof:name":"Tangara S.S.P. School",
    "wof:placetype":"venue"
},
  "geometry": {"coordinates":[150.462768555,-34.4461364746],"type":"Point"}
}