{
  "type": "Feature",
  "properties": {
    "iso:country":"AU",
    "sg:address":"218- 220 Rouse St",
    "sg:city":"Tenterfield",
    "sg:classifiers":[
        {
            "category":"Food & Beverages",
            "subcategory":"Liquor & Beverages",
            "type":"Retail Goods"
        }
    ],
    "sg:phone":"+61 2 6736 1682",
    "sg:postcode":"2372",
    "sg:province":"NSW",
    "sg:tags":[
        "store"
    ],
    "wof:name":"Sellers Foodmarket & Bottle Shop",
    "wof:placetype":"venue"
},
  "geometry": {"coordinates":[152.01866149899999,-29.0551433563],"type":"Point"}
}