{
  "type": "Feature",
  "properties": {
    "addr:full":"184 Old Wilby Rd Yarrawonga VIC 3730",
    "addr:housenumber":"184",
    "addr:postcode":"3730",
    "addr:street":"Old Wilby Rd",
    "iso:country":"AU",
    "sg:address":"184 Old Wilby Rd",
    "sg:city":"Yarrawonga",
    "sg:classifiers":[
        {
            "category":"Retail",
            "subcategory":"Auto Repair",
            "type":"Services"
        }
    ],
    "sg:phone":"+61 3 5743 1698",
    "sg:postcode":"3730",
    "sg:province":"VIC",
    "sg:tags":[
        "electrical"
    ],
    "wof:name":"Acacia Auto Electrical",
    "wof:placetype":"venue"
},
  "geometry": {"coordinates":[145.99940490700001,-36.020526886],"type":"Point"}
}