{
  "type": "Feature",
  "properties": {
    "addr:full":"39 Ringwood St Durack QLD 4077",
    "addr:housenumber":"39",
    "addr:postcode":"4077",
    "addr:street":"Ringwood St",
    "iso:country":"AU",
    "sg:address":"39 Ringwood St",
    "sg:city":"Durack",
    "sg:classifiers":[
        {
            "category":"Health Services",
            "subcategory":"Health Practitioner",
            "type":"Services"
        }
    ],
    "sg:phone":"+61 422 460 422",
    "sg:postcode":"4077",
    "sg:province":"QLD",
    "sg:tags":[
        "reiki"
    ],
    "wof:name":"People & Petz Reiki",
    "wof:placetype":"venue"
},
  "geometry": {"coordinates":[152.979614258,-27.5822505951],"type":"Point"}
}