{
  "type": "Feature",
  "properties": {
    "addr:full":"Lvl2/ 130 Macquarie St Hobart TAS 7000",
    "addr:housenumber":"130",
    "addr:postcode":"7000",
    "addr:street":"Macquarie St",
    "iso:country":"AU",
    "sg:address":"Lvl2/ 130 Macquarie St",
    "sg:city":"Hobart",
    "sg:classifiers":[
        {
            "category":"Education",
            "subcategory":"Vocational School",
            "type":"Public Place"
        }
    ],
    "sg:phone":"+61 3 6223 7191",
    "sg:postcode":"7000",
    "sg:province":"TAS",
    "sg:tags":[
        "finishing",
        "modelling"
    ],
    "wof:name":"Stellar Girls Academy The",
    "wof:placetype":"venue"
},
  "geometry": {"coordinates":[147.32844543499999,-42.8843002319],"type":"Point"}
}