{
  "type": "Feature",
  "properties": {
    "addr:full":"Shafto Lane Shop 7B/ 401 Murray St Perth WA 6000",
    "addr:housenumber":"shop 7b / 401",
    "addr:postcode":"6000",
    "addr:street":"Shafto;Murray St",
    "iso:country":"AU",
    "sg:address":"Shafto Lane Shop 7B/ 401 Murray St",
    "sg:city":"Perth",
    "sg:classifiers":[
        {
            "category":"Personal",
            "subcategory":"Beauty Salon",
            "type":"Services"
        }
    ],
    "sg:phone":"+61 8 9485 0850",
    "sg:postcode":"6000",
    "sg:province":"WA",
    "sg:tags":[
        "hairdresser"
    ],
    "wof:name":"Jim's Hairstylist for Men",
    "wof:placetype":"venue"
},
  "geometry": {"coordinates":[115.859703064,-31.9532852173],"type":"Point"}
}