{
  "type": "Feature",
  "properties": {
    "addr:full":"Shop 3, 441 Keilor Rd Niddrie VIC 3042",
    "addr:housenumber":"shop 3",
    "addr:postcode":"441;3042",
    "addr:street":"Keilor Rd",
    "iso:country":"AU",
    "sg:address":"Shop 3, 441 Keilor Rd",
    "sg:city":"Niddrie",
    "sg:classifiers":[
        {
            "category":"Personal",
            "subcategory":"Beauty Salon",
            "type":"Services"
        }
    ],
    "sg:phone":"+61 3 9351 0556",
    "sg:postcode":"3042",
    "sg:province":"VIC",
    "wof:name":"Myanh Beauty Therapist",
    "wof:placetype":"venue"
},
  "geometry": {"coordinates":[144.89059448200001,-37.7367401123],"type":"Point"}
}