{
  "type": "Feature",
  "properties": {
    "iso:country":"AU",
    "sg:address":"11 Unley Rd",
    "sg:city":"Parkside",
    "sg:classifiers":[
        {
            "category":"Autos & Motor Vehicles",
            "subcategory":"Automobile Sales",
            "type":"Retail Goods"
        }
    ],
    "sg:phone":"+61 8 8373 2588",
    "sg:postcode":"5063",
    "sg:province":"SA",
    "sg:tags":[
        "car",
        "used"
    ],
    "wof:name":"Somerville Motors",
    "wof:placetype":"venue"
},
  "geometry": {"coordinates":[138.60699462900001,-34.9418411255],"type":"Point"}
}