{
  "type": "Feature",
  "properties": {
    "addr:full":"27 Newcastle Rd Northam WA 6401",
    "addr:housenumber":"27",
    "addr:postcode":"6401",
    "addr:street":"Newcastle Rd",
    "iso:country":"AU",
    "sg:address":"27 Newcastle Rd",
    "sg:city":"Northam",
    "sg:classifiers":[
        {
            "category":"Manufacturing",
            "subcategory":"Pottery",
            "type":"Manufacturing & Wholesale Goods"
        }
    ],
    "sg:phone":"+61 8 9622 2407",
    "sg:postcode":"6401",
    "sg:province":"WA",
    "wof:name":"Dragonfire Pottery",
    "wof:placetype":"venue"
},
  "geometry": {"coordinates":[116.66378021200001,-31.6527938843],"type":"Point"}
}