{
  "type": "Feature",
  "properties": {
    "addr:full":"112 Hampton St Bridgetown WA 6255",
    "addr:housenumber":"112",
    "addr:postcode":"6255",
    "addr:street":"Hampton St",
    "iso:country":"AU",
    "sg:address":"112 Hampton St",
    "sg:city":"Bridgetown",
    "sg:classifiers":[
        {
            "category":"Banks & Credit Unions",
            "subcategory":"Bank",
            "type":"Services"
        }
    ],
    "sg:phone":"+61 13 20 32",
    "sg:postcode":"6255",
    "sg:province":"WA",
    "wof:name":"Westpac",
    "wof:placetype":"venue"
},
  "geometry": {"coordinates":[116.137046814,-33.9577331543],"type":"Point"}
}