{
  "type": "Feature",
  "properties": {
    "addr:full":"9 Bowen St O&#039;Connor WA 6163",
    "addr:housenumber":"9",
    "addr:postcode":"6163",
    "addr:street":"Bowen St",
    "iso:country":"AU",
    "sg:address":"9 Bowen St",
    "sg:city":"O&#039;Connor",
    "sg:classifiers":[
        {
            "category":"Retail",
            "subcategory":"Auto Repair",
            "type":"Services"
        }
    ],
    "sg:phone":"+61 8 9337 5566",
    "sg:postcode":"6163",
    "sg:province":"WA",
    "sg:tags":[
        "repairer",
        "motor",
        "engineer"
    ],
    "wof:name":"Engine Rebuilders (W.A.)",
    "wof:placetype":"venue"
},
  "geometry": {"coordinates":[115.803009,-32.061481],"type":"Point"}
}