{
  "type": "Feature",
  "properties": {
    "iso:country":"AU",
    "sg:address":"Level 1, 85 Havelock St",
    "sg:city":"West Perth",
    "sg:classifiers":[
        {
            "category":"Building & Trades",
            "subcategory":"Electrical",
            "type":"Services"
        }
    ],
    "sg:phone":"+61 8 9483 9500",
    "sg:postcode":"6005",
    "sg:province":"WA",
    "sg:tags":[
        "wholesaler",
        "mfrs",
        "appliance"
    ],
    "wof:name":"Samsung Electronics Australia Pty Ltd",
    "wof:placetype":"venue"
},
  "geometry": {"coordinates":[115.845169067,-31.9472064972],"type":"Point"}
}