{
  "type": "Feature",
  "properties": {
    "iso:country":"AU",
    "sg:address":"22 Trotters La",
    "sg:city":"Cudgee",
    "sg:classifiers":[
        {
            "category":"Park",
            "subcategory":"County",
            "type":"Public Place"
        }
    ],
    "sg:phone":"+61 3 5567 6260",
    "sg:postcode":"3265",
    "sg:province":"VIC",
    "sg:tags":[
        "sanctuary",
        "zoos",
        "animal"
    ],
    "wof:name":"Cudgee Creek Wildlife Park",
    "wof:placetype":"venue"
},
  "geometry": {"coordinates":[142.64938354500001,-38.34192276],"type":"Point"}
}