{
  "type": "Feature",
  "properties": {
    "addr:full":"Shp11/ 1 Centenary Hwy Springfield Lakes QLD 4300",
    "addr:housenumber":"1",
    "addr:postcode":"4300",
    "addr:street":"Centenary Hwy",
    "iso:country":"AU",
    "sg:address":"Shp11/ 1 Centenary Hwy",
    "sg:city":"Springfield Lakes",
    "sg:classifiers":[
        {
            "category":"Food & Beverages",
            "subcategory":"Bakery",
            "type":"Retail Goods"
        }
    ],
    "sg:phone":"+61 7 3818 7109",
    "sg:postcode":"4300",
    "sg:province":"QLD",
    "sg:tags":[
        "baker"
    ],
    "wof:name":"Vuong Bakery & Takeaway",
    "wof:placetype":"venue"
},
  "geometry": {"coordinates":[152.91281127900001,-27.6702861786],"type":"Point"}
}