{
  "type": "Feature",
  "properties": {
    "addr:full":"274 North East Rd Klemzig SA 5087",
    "addr:housenumber":"274",
    "addr:postcode":"5087",
    "addr:street":"North East Rd",
    "iso:country":"AU",
    "sg:address":"274 North East Rd",
    "sg:city":"Klemzig",
    "sg:classifiers":[
        {
            "category":"Professional",
            "subcategory":"Employment Agencies",
            "type":"Services"
        }
    ],
    "sg:phone":"+61 8 8360 0800",
    "sg:postcode":"5087",
    "sg:province":"SA",
    "wof:name":"Multiple Solutions Employment Specialists",
    "wof:placetype":"venue"
},
  "geometry": {"coordinates":[138.633911133,-34.8739318848],"type":"Point"}
}