{
  "type": "Feature",
  "properties": {
    "iso:country":"AU",
    "sg:address":"55 Coachwood Crs",
    "sg:city":"Alfords Point",
    "sg:classifiers":[
        {
            "category":"Sports & Exercise",
            "subcategory":"Gym",
            "type":"Entertainment"
        }
    ],
    "sg:phone":"+61 410 061 889",
    "sg:postcode":"2234",
    "sg:province":"NSW",
    "sg:tags":[
        "personal",
        "trainer",
        "fitness"
    ],
    "wof:name":"Jeanettic Moves",
    "wof:placetype":"venue"
},
  "geometry": {"coordinates":[151.02471923799999,-33.9934692383],"type":"Point"}
}