{
  "type": "Feature",
  "properties": {
    "addr:full":"105 Old Maryborough Rd Pialba QLD 4655",
    "addr:housenumber":"105",
    "addr:postcode":"4655",
    "addr:street":"Old Maryborough Rd",
    "iso:country":"AU",
    "sg:address":"105 Old Maryborough Rd",
    "sg:city":"Pialba",
    "sg:classifiers":[
        {
            "category":"Building & Trades",
            "subcategory":"Construction",
            "type":"Services"
        }
    ],
    "sg:phone":"+61 7 4124 3550",
    "sg:postcode":"4655",
    "sg:province":"QLD",
    "sg:tags":[
        "window",
        "aluminium"
    ],
    "wof:name":"Hervey Bay Glass, Glazing & Screens",
    "wof:placetype":"venue"
},
  "geometry": {"coordinates":[152.83045999999999,-25.28331],"type":"Point"}
}