{
  "type": "Feature",
  "properties": {
    "addr:full":"144 Boundary St West End (Brisbane) QLD 4101",
    "addr:housenumber":"144",
    "addr:postcode":"4101",
    "addr:street":"Boundary St",
    "iso:country":"AU",
    "sg:address":"144 Boundary St",
    "sg:city":"West End (Brisbane)",
    "sg:classifiers":[
        {
            "category":"Health Services",
            "subcategory":"Health Practitioner",
            "type":"Services"
        }
    ],
    "sg:phone":"+61 7 3844 7961",
    "sg:postcode":"4101",
    "sg:province":"QLD",
    "sg:tags":[
        "herbalist"
    ],
    "wof:name":"Sarah Speedy",
    "wof:placetype":"venue"
},
  "geometry": {"coordinates":[153.01226806599999,-27.4804515839],"type":"Point"}
}