{
  "type": "Feature",
  "properties": {
    "addr:full":"431 Great Eastern Hwy Redcliffe WA 6104",
    "addr:housenumber":"431",
    "addr:postcode":"6104",
    "addr:street":"Great Eastern Hwy",
    "iso:country":"AU",
    "sg:address":"431 Great Eastern Hwy",
    "sg:city":"Redcliffe",
    "sg:classifiers":[
        {
            "category":"Fast Food",
            "type":"Food & Drink"
        }
    ],
    "sg:phone":"+61 8 9277 3166",
    "sg:postcode":"6104",
    "sg:province":"WA",
    "sg:tags":[
        "away",
        "take"
    ],
    "wof:name":"Brewster's Fine Foods",
    "wof:placetype":"venue"
},
  "geometry": {"coordinates":[115.945281982,-31.9299087524],"type":"Point"}
}