{
  "type": "Feature",
  "properties": {
    "iso:country":"AU",
    "sg:address":"53 Riaweena St",
    "sg:city":"The Gap",
    "sg:classifiers":[
        {
            "category":"Building & Trades",
            "subcategory":"Construction",
            "type":"Services"
        }
    ],
    "sg:phone":"+61 7 3300 9462",
    "sg:postcode":"4061",
    "sg:province":"QLD",
    "sg:tags":[
        "fencing",
        "contractor"
    ],
    "wof:name":"Anderson Fencing",
    "wof:placetype":"venue"
},
  "geometry": {"coordinates":[152.94407653799999,-27.445400238],"type":"Point"}
}