{
  "type": "Feature",
  "properties": {
    "iso:country":"AU",
    "sg:address":"Cnr Of Cairns Road & George St",
    "sg:city":"Gordonvale",
    "sg:classifiers":[
        {
            "category":"Social Services",
            "subcategory":"Child Care",
            "type":"Services"
        }
    ],
    "sg:phone":"+61 7 4056 6777",
    "sg:postcode":"4865",
    "sg:province":"QLD",
    "wof:name":"Gordonvale Childcare & Education Centre",
    "wof:placetype":"venue"
},
  "geometry": {"coordinates":[145.78440856899999,-17.0877838135],"type":"Point"}
}