{
  "type": "Feature",
  "properties": {
    "addr:full":"Unit 2, 15 Brookhollow Ave Baulkham Hills NSW 2153",
    "addr:housenumber":"15",
    "addr:postcode":"2153",
    "addr:street":"Brookhollow Ave",
    "iso:country":"AU",
    "sg:address":"Unit 2, 15 Brookhollow Ave",
    "sg:city":"Baulkham Hills",
    "sg:classifiers":[
        {
            "category":"Wholesale",
            "subcategory":"Electrical",
            "type":"Manufacturing & Wholesale Goods"
        }
    ],
    "sg:phone":"+61 1800 334 802",
    "sg:postcode":"2153",
    "sg:province":"NSW",
    "sg:tags":[
        "control",
        "equipment",
        "switch"
    ],
    "wof:name":"Sick",
    "wof:placetype":"venue"
},
  "geometry": {"coordinates":[150.969680786,-33.7331085205],"type":"Point"}
}