{
  "type": "Feature",
  "properties": {
    "addr:full":"30 Barokee St Stafford QLD 4053",
    "addr:housenumber":"30",
    "addr:postcode":"4053",
    "addr:street":"Barokee St",
    "iso:country":"AU",
    "sg:address":"30 Barokee St",
    "sg:city":"Stafford",
    "sg:classifiers":[
        {
            "category":"Building & Trades",
            "subcategory":"Plumbing",
            "type":"Services"
        }
    ],
    "sg:phone":"+61 7 3356 7640",
    "sg:postcode":"4053",
    "sg:province":"QLD",
    "sg:tags":[
        "plumber",
        "gasfitters"
    ],
    "wof:name":"Around The Bend",
    "wof:placetype":"venue"
},
  "geometry": {"coordinates":[153.013946533,-27.4053230286],"type":"Point"}
}