{
  "type": "Feature",
  "properties": {
    "addr:full":"Shop 6a, The Hub Shopping Centre, Hub Drive Aberfoyle Park SA 5159",
    "addr:housenumber":"shop 6a",
    "addr:postcode":"5159",
    "addr:street":"The;Drive",
    "iso:country":"AU",
    "sg:address":"Shop 6a, The Hub Shopping Centre, Hub Drive",
    "sg:city":"Aberfoyle Park",
    "sg:classifiers":[
        {
            "category":"Fast Food",
            "type":"Food & Drink"
        }
    ],
    "sg:phone":"+61 8 8358 6677",
    "sg:postcode":"5159",
    "sg:province":"SA",
    "sg:tags":[
        "away",
        "take"
    ],
    "wof:name":"Hub Charcoal Chicken & Seafood",
    "wof:placetype":"venue"
},
  "geometry": {"coordinates":[138.593292236,-35.0763168335],"type":"Point"}
}