{
  "type": "Feature",
  "properties": {
    "addr:full":"7 Chestnut Rd Port Macquarie NSW 2444",
    "addr:housenumber":"7",
    "addr:postcode":"2444",
    "addr:street":"Chestnut Rd",
    "iso:country":"AU",
    "sg:address":"7 Chestnut Rd",
    "sg:city":"Port Macquarie",
    "sg:classifiers":[
        {
            "category":"Professional",
            "subcategory":"Art Services",
            "type":"Services"
        }
    ],
    "sg:phone":"+61 2 6581 0125",
    "sg:postcode":"2444",
    "sg:province":"NSW",
    "sg:tags":[
        "graphic",
        "designer"
    ],
    "wof:name":"Chrysalis",
    "wof:placetype":"venue"
},
  "geometry": {"coordinates":[152.89039600000001,-31.449715],"type":"Point"}
}