{
  "type": "Feature",
  "properties": {
    "iso:country":"AU",
    "sg:address":"737 Elizabeth St",
    "sg:city":"Zetland",
    "sg:classifiers":[
        {
            "category":"Utilities",
            "subcategory":"Refuse",
            "type":"Services"
        }
    ],
    "sg:phone":"+61 1300 850 898",
    "sg:postcode":"2017",
    "sg:province":"NSW",
    "sg:tags":[
        "remover",
        "rubbish"
    ],
    "wof:name":"Just Shift It Pty Ltd",
    "wof:placetype":"venue"
},
  "geometry": {"coordinates":[151.20555114699999,-33.9048538208],"type":"Point"}
}