{
  "type": "Feature",
  "properties": {
    "addr:full":"34 Laura St Aspendale VIC 3195",
    "addr:housenumber":"34",
    "addr:postcode":"3195",
    "addr:street":"Laura St",
    "iso:country":"AU",
    "sg:address":"34 Laura St",
    "sg:city":"Aspendale",
    "sg:classifiers":[
        {
            "category":"Personal",
            "subcategory":"Beauty Salon",
            "type":"Services"
        }
    ],
    "sg:phone":"+61 3 9580 1303",
    "sg:postcode":"3195",
    "sg:province":"VIC",
    "wof:name":"Angel House Beauty Therapy",
    "wof:placetype":"venue"
},
  "geometry": {"coordinates":[145.100006103,-38.0214004517],"type":"Point"}
}