{
  "type": "Feature",
  "properties": {
    "addr:full":"2 Gesham Way Bomaderry NSW 2541",
    "addr:housenumber":"2",
    "addr:postcode":"2541",
    "addr:street":"Gesham Way",
    "iso:country":"AU",
    "sg:address":"2 Gesham Way",
    "sg:city":"Bomaderry",
    "sg:classifiers":[
        {
            "category":"Professional",
            "subcategory":"Engineering",
            "type":"Services"
        }
    ],
    "sg:phone":"+61 2 4421 5204",
    "sg:postcode":"2541",
    "sg:province":"NSW",
    "sg:tags":[
        "engineer"
    ],
    "wof:name":"Bratan Engineering Pty Ltd",
    "wof:placetype":"venue"
},
  "geometry": {"coordinates":[150.611618042,-34.8450469971],"type":"Point"}
}