{
  "type": "Feature",
  "properties": {
    "iso:country":"AU",
    "sg:address":"77 Sorrell St",
    "sg:city":"North Parramatta",
    "sg:classifiers":[
        {
            "category":"Banks & Credit Unions",
            "subcategory":"Financial Services",
            "type":"Services"
        }
    ],
    "sg:phone":"+61 2 9630 6677",
    "sg:postcode":"2151",
    "sg:province":"NSW",
    "sg:tags":[
        "advisory",
        "planning",
        "retirement"
    ],
    "wof:name":"Skeggs Goldstien Associates Pty Ltd",
    "wof:placetype":"venue"
},
  "geometry": {"coordinates":[151.00802612300001,-33.8024597168],"type":"Point"}
}