{
  "type": "Feature",
  "properties": {
    "iso:country":"AU",
    "sg:address":"13 Sanananda Ave",
    "sg:city":"Allambie Heights",
    "sg:classifiers":[
        {
            "category":"Wholesale",
            "subcategory":"Electrical",
            "type":"Manufacturing & Wholesale Goods"
        }
    ],
    "sg:phone":"+61 2 9452 3831",
    "sg:postcode":"2100",
    "sg:province":"NSW",
    "sg:tags":[
        "equipment",
        "testing",
        "electronic",
        "electric"
    ],
    "wof:name":"Consultant Technology Aust",
    "wof:placetype":"venue"
},
  "geometry": {"coordinates":[151.25042724599999,-33.7640037537],"type":"Point"}
}