{
  "type": "Feature",
  "properties": {
    "addr:full":"Cnr Grant & Warner St Port Douglas QLD 4877",
    "addr:postcode":"4877",
    "addr:street":"Cnr;St",
    "iso:country":"AU",
    "sg:address":"Cnr Grant & Warner St",
    "sg:city":"Port Douglas",
    "sg:classifiers":[
        {
            "category":"Personal",
            "type":"Services"
        }
    ],
    "sg:phone":"+61 7 4099 5566",
    "sg:postcode":"4877",
    "sg:province":"QLD",
    "sg:tags":[
        "gift"
    ],
    "wof:name":"Port Douglas Tropical Florist",
    "wof:placetype":"venue"
},
  "geometry": {"coordinates":[145.464111328,-16.4841251373],"type":"Point"}
}