{
  "type": "Feature",
  "properties": {
    "addr:full":"35 Deberis Crs Frankston VIC 3199",
    "addr:housenumber":"35",
    "addr:postcode":"3199",
    "addr:street":"Deberis Crs",
    "iso:country":"AU",
    "sg:address":"35 Deberis Crs",
    "sg:city":"Frankston",
    "sg:classifiers":[
        {
            "category":"Building & Trades",
            "subcategory":"Construction",
            "type":"Services"
        }
    ],
    "sg:phone":"+61 412 367 855",
    "sg:postcode":"3199",
    "sg:province":"VIC",
    "sg:tags":[
        "joiner",
        "carpenter"
    ],
    "wof:name":"Casleys Carpentry",
    "wof:placetype":"venue"
},
  "geometry": {"coordinates":[145.12179565400001,-38.1415710449],"type":"Point"}
}