{
  "type": "Feature",
  "properties": {
    "iso:country":"AU",
    "sg:address":"89 Market St",
    "sg:city":"Sydney",
    "sg:classifiers":[
        {
            "category":"Shopping",
            "subcategory":"Jewelry",
            "type":"Retail Goods"
        }
    ],
    "sg:phone":"+61 2 9283 5667",
    "sg:postcode":"2000",
    "sg:province":"NSW",
    "sg:tags":[
        "jeweller"
    ],
    "wof:name":"Readco Jewellery Pty Ltd",
    "wof:placetype":"venue"
},
  "geometry": {"coordinates":[151.20979309099999,-33.8708610535],"type":"Point"}
}