{
  "type": "Feature",
  "properties": {
    "addr:full":"36 Cunninghame St Sale VIC 3850",
    "addr:housenumber":"36",
    "addr:postcode":"3850",
    "addr:street":"Cunninghame St",
    "iso:country":"AU",
    "sg:address":"36 Cunninghame St",
    "sg:city":"Sale",
    "sg:classifiers":[
        {
            "category":"Health Services",
            "subcategory":"Doctor",
            "type":"Services"
        }
    ],
    "sg:phone":"+61 3 5143 0077",
    "sg:postcode":"3850",
    "sg:province":"VIC",
    "sg:tags":[
        "medical",
        "practitioner"
    ],
    "wof:name":"Jarman John",
    "wof:placetype":"venue"
},
  "geometry": {"coordinates":[147.060668945,-38.1076278687],"type":"Point"}
}