{
  "type": "Feature",
  "properties": {
    "iso:country":"AU",
    "sg:address":"111 Denham St",
    "sg:city":"Hawthorn",
    "sg:classifiers":[
        {
            "category":"Travel",
            "subcategory":"Hostel",
            "type":"Entertainment"
        }
    ],
    "sg:phone":"+61 3 9818 7519",
    "sg:postcode":"3122",
    "sg:province":"VIC",
    "sg:tags":[
        "home"
    ],
    "wof:name":"Seston Lodge",
    "wof:placetype":"venue"
},
  "geometry": {"coordinates":[145.02609252900001,-37.8196182251],"type":"Point"}
}