{
  "type": "Feature",
  "properties": {
    "addr:full":"Corse St Roma QLD 4455",
    "addr:postcode":"4455",
    "addr:street":"Corse St",
    "iso:country":"AU",
    "sg:address":"Corse St",
    "sg:city":"Roma",
    "sg:classifiers":[
        {
            "category":"Professional",
            "subcategory":"Employment Agencies",
            "type":"Services"
        }
    ],
    "sg:phone":"+61 7 4622 3695",
    "sg:postcode":"4455",
    "sg:province":"QLD",
    "sg:tags":[
        "entertainer",
        "agent"
    ],
    "wof:name":"Silver Blues Dance Band",
    "wof:placetype":"venue"
},
  "geometry": {"coordinates":[148.78732299800001,-26.5734291077],"type":"Point"}
}