{
  "type": "Feature",
  "properties": {
    "addr:full":"Shop 2 12 Leonard Ave Noble Park VIC 3174",
    "addr:housenumber":"shop;12",
    "addr:postcode":"3174",
    "addr:street":"Leonard Ave",
    "iso:country":"AU",
    "sg:address":"Shop 2 12 Leonard Ave",
    "sg:city":"Noble Park",
    "sg:classifiers":[
        {
            "category":"Fast Food",
            "type":"Food & Drink"
        }
    ],
    "sg:phone":"+61 3 9547 8810",
    "sg:postcode":"3174",
    "sg:province":"VIC",
    "sg:tags":[
        "away",
        "take"
    ],
    "wof:name":"N G R Spices",
    "wof:placetype":"venue"
},
  "geometry": {"coordinates":[145.17573547399999,-37.9685211182],"type":"Point"}
}