{
  "type": "Feature",
  "properties": {
    "addr:full":"1 Albemarle St Williamstown VIC 3016",
    "addr:housenumber":"1",
    "addr:postcode":"3016",
    "addr:street":"Albemarle St",
    "iso:country":"AU",
    "sg:address":"1 Albemarle St",
    "sg:city":"Williamstown",
    "sg:classifiers":[
        {
            "category":"Home & Garden",
            "subcategory":"Building Materials",
            "type":"Retail Goods"
        }
    ],
    "sg:phone":"+61 3 9397 8533",
    "sg:postcode":"3016",
    "sg:province":"VIC",
    "sg:tags":[
        "lawn",
        "cutting",
        "maintenance"
    ],
    "sg:website":"http://www.grasscare.com.au",
    "wof:name":"Grass Care",
    "wof:placetype":"venue"
},
  "geometry": {"coordinates":[144.863357544,-37.8499183655],"type":"Point"}
}