{
  "type": "Feature",
  "properties": {
    "iso:country":"AU",
    "sg:address":"Shop 1/12- 14 Enmore Rd",
    "sg:city":"Newtown",
    "sg:classifiers":[
        {
            "category":"Health Services",
            "subcategory":"Dentist",
            "type":"Services"
        }
    ],
    "sg:phone":"+61 2 9557 3888",
    "sg:postcode":"2042",
    "sg:province":"NSW",
    "wof:name":"Espino Yipella Dr",
    "wof:placetype":"venue"
},
  "geometry": {"coordinates":[151.17544599999999,-33.898766],"type":"Point"}
}