{
  "type": "Feature",
  "properties": {
    "addr:full":"19 Pardoo Drv Modbury SA 5092",
    "addr:housenumber":"19",
    "addr:postcode":"5092",
    "addr:street":"Pardoo Drv",
    "iso:country":"AU",
    "sg:address":"19 Pardoo Drv",
    "sg:city":"Modbury",
    "sg:classifiers":[
        {
            "category":"Shopping",
            "subcategory":"Antiques",
            "type":"Retail Goods"
        }
    ],
    "sg:phone":"+61 8 8264 7989",
    "sg:postcode":"5092",
    "sg:province":"SA",
    "sg:tags":[
        "restoration",
        "reproduction"
    ],
    "wof:name":"Hodson D J & C E",
    "wof:placetype":"venue"
},
  "geometry": {"coordinates":[138.67752075199999,-34.831111908],"type":"Point"}
}