{
  "type": "Feature",
  "properties": {
    "addr:full":"Shop 1 122 Bourke St Glen Innes NSW 2370",
    "addr:housenumber":"shop 1 122",
    "addr:postcode":"2370",
    "addr:street":"Bourke St",
    "iso:country":"AU",
    "sg:address":"Shop 1 122 Bourke St",
    "sg:city":"Glen Innes",
    "sg:classifiers":[
        {
            "category":"Fast Food",
            "type":"Food & Drink"
        }
    ],
    "sg:phone":"+61 2 6732 5666",
    "sg:postcode":"2370",
    "sg:province":"NSW",
    "sg:tags":[
        "away",
        "take"
    ],
    "wof:name":"Eagle Boys Pizza",
    "wof:placetype":"venue"
},
  "geometry": {"coordinates":[151.73385620100001,-29.7387008667],"type":"Point"}
}