{
  "type": "Feature",
  "properties": {
    "addr:full":"189 Haly St Kingaroy QLD 4610",
    "addr:housenumber":"189",
    "addr:postcode":"4610",
    "addr:street":"Haly St",
    "iso:country":"AU",
    "sg:address":"189 Haly St",
    "sg:city":"Kingaroy",
    "sg:classifiers":[
        {
            "category":"Personal",
            "subcategory":"Beauty Salon",
            "type":"Services"
        }
    ],
    "sg:phone":"+61 7 4162 2137",
    "sg:postcode":"4610",
    "sg:province":"QLD",
    "sg:tags":[
        "hairdresser"
    ],
    "wof:name":"Crimpers Hair Salon",
    "wof:placetype":"venue"
},
  "geometry": {"coordinates":[151.83888244600001,-26.5392513275],"type":"Point"}
}