{
  "type": "Feature",
  "properties": {
    "addr:full":"45 Silvan Rd Wattle Glen VIC 3096",
    "addr:housenumber":"45",
    "addr:postcode":"3096",
    "addr:street":"Silvan Rd",
    "iso:country":"AU",
    "sg:address":"45 Silvan Rd",
    "sg:city":"Wattle Glen",
    "sg:classifiers":[
        {
            "category":"Health Services",
            "subcategory":"Nursing And Care Facility",
            "type":"Services"
        }
    ],
    "sg:phone":"+61 3 9718 2267",
    "sg:postcode":"3096",
    "sg:province":"VIC",
    "sg:tags":[
        "home"
    ],
    "wof:name":"Wattle Glen Private Nursing Home",
    "wof:placetype":"venue"
},
  "geometry": {"coordinates":[145.19395446799999,-37.6543083191],"type":"Point"}
}