{
  "type": "Feature",
  "properties": {
    "addr:full":"89- 91 Lawes St East Maitland NSW 2323",
    "addr:housenumber":"91",
    "addr:postcode":"2323",
    "addr:street":"Lawes St",
    "iso:country":"AU",
    "sg:address":"89- 91 Lawes St",
    "sg:city":"East Maitland",
    "sg:classifiers":[
        {
            "category":"Manufacturing",
            "subcategory":"Electronics",
            "type":"Manufacturing & Wholesale Goods"
        }
    ],
    "sg:phone":"+61 2 4933 3966",
    "sg:postcode":"2323",
    "sg:province":"NSW",
    "sg:tags":[
        "oven",
        "microwave"
    ],
    "wof:name":"A A Electronics",
    "wof:placetype":"venue"
},
  "geometry": {"coordinates":[151.58900451700001,-32.7501182556],"type":"Point"}
}