{
  "type": "Feature",
  "properties": {
    "iso:country":"AU",
    "sg:address":"384 Warwick Rd",
    "sg:city":"Yamanto",
    "sg:classifiers":[
        {
            "category":"Fast Food",
            "type":"Food & Drink"
        }
    ],
    "sg:phone":"+61 7 3288 6033",
    "sg:postcode":"4305",
    "sg:province":"QLD",
    "sg:tags":[
        "away",
        "take"
    ],
    "wof:name":"Pizza Capers",
    "wof:placetype":"venue"
},
  "geometry": {"coordinates":[152.750564575,-27.6540966034],"type":"Point"}
}