{
  "type": "Feature",
  "properties": {
    "addr:full":"247 Alison Rd Randwick NSW 2031",
    "addr:housenumber":"247",
    "addr:postcode":"2031",
    "addr:street":"Alison Rd",
    "iso:country":"AU",
    "sg:address":"247 Alison Rd",
    "sg:city":"Randwick",
    "sg:classifiers":[
        {
            "category":"Home & Garden",
            "subcategory":"Building Materials",
            "type":"Retail Goods"
        }
    ],
    "sg:phone":"+61 2 9399 3347",
    "sg:postcode":"2031",
    "sg:province":"NSW",
    "sg:tags":[
        "lawn",
        "cutting",
        "maintenance"
    ],
    "wof:name":"O'Loughlin Lawn & Garden Service",
    "wof:placetype":"venue"
},
  "geometry": {"coordinates":[151.24681091299999,-33.9137573242],"type":"Point"}
}