{
  "type": "Feature",
  "properties": {
    "addr:full":"325 Great Eastern Hwy Redcliffe WA 6104",
    "addr:housenumber":"325",
    "addr:postcode":"6104",
    "addr:street":"Great Eastern Hwy",
    "iso:country":"AU",
    "sg:address":"325 Great Eastern Hwy",
    "sg:city":"Redcliffe",
    "sg:classifiers":[
        {
            "category":"Health Services",
            "subcategory":"Medical Lab",
            "type":"Services"
        }
    ],
    "sg:phone":"+61 8 9277 5671",
    "sg:postcode":"6104",
    "sg:province":"WA",
    "sg:tags":[
        "laboratory",
        "dental"
    ],
    "wof:name":"Denny Paul",
    "wof:placetype":"venue"
},
  "geometry": {"coordinates":[115.945579529,-31.9293384552],"type":"Point"}
}