{
  "type": "Feature",
  "properties": {
    "iso:country":"AU",
    "sg:address":"187 Keira St",
    "sg:city":"Wollongong",
    "sg:classifiers":[
        {
            "category":"Fast Food",
            "type":"Food & Drink"
        }
    ],
    "sg:phone":"+61 2 4225 1888",
    "sg:postcode":"2500",
    "sg:province":"NSW",
    "sg:tags":[
        "away",
        "take"
    ],
    "wof:name":"Coconut Thai Restaurant",
    "wof:placetype":"venue"
},
  "geometry": {"coordinates":[150.89343299999999,-34.424171],"type":"Point"}
}