{
  "type": "Feature",
  "properties": {
    "addr:full":"26 St.Georges Rd Norlane VIC 3214",
    "addr:housenumber":"26",
    "addr:postcode":"3214",
    "addr:street":"St.Georges Rd",
    "iso:country":"AU",
    "sg:address":"26 St.Georges Rd",
    "sg:city":"Norlane",
    "sg:classifiers":[
        {
            "category":"Professional",
            "subcategory":"Employment Agencies",
            "type":"Services"
        }
    ],
    "sg:phone":"+61 3 5275 2881",
    "sg:postcode":"3214",
    "sg:province":"VIC",
    "sg:tags":[
        "consultant",
        "corrosion"
    ],
    "wof:name":"Hydro-Blast P/L",
    "wof:placetype":"venue"
},
  "geometry": {"coordinates":[144.35643005399999,-38.0738601685],"type":"Point"}
}