{
  "type": "Feature",
  "properties": {
    "addr:full":"79 Kew St Welshpool WA 6106",
    "addr:housenumber":"79",
    "addr:postcode":"6106",
    "addr:street":"Kew St",
    "iso:country":"AU",
    "sg:address":"79 Kew St",
    "sg:city":"Welshpool",
    "sg:classifiers":[
        {
            "category":"Manufacturing",
            "subcategory":"Metals",
            "type":"Manufacturing & Wholesale Goods"
        }
    ],
    "sg:phone":"+61 8 9361 0071",
    "sg:postcode":"6106",
    "sg:province":"WA",
    "sg:tags":[
        "polisher"
    ],
    "wof:name":"Anvil Industries",
    "wof:placetype":"venue"
},
  "geometry": {"coordinates":[115.929153442,-31.9870681763],"type":"Point"}
}