{
  "type": "Feature",
  "properties": {
    "addr:full":"40 Jones Rd Bellbird Park QLD 4300",
    "addr:housenumber":"40",
    "addr:postcode":"4300",
    "addr:street":"Jones Rd",
    "iso:country":"AU",
    "sg:address":"40 Jones Rd",
    "sg:city":"Bellbird Park",
    "sg:classifiers":[
        {
            "category":"Professional",
            "subcategory":"Art Services",
            "type":"Services"
        }
    ],
    "sg:phone":"+61 7 3814 3850",
    "sg:postcode":"4300",
    "sg:province":"QLD",
    "sg:tags":[
        "artist"
    ],
    "wof:name":"Alan Tulloch",
    "wof:placetype":"venue"
},
  "geometry": {"coordinates":[152.87867736800001,-27.6470241547],"type":"Point"}
}