{
  "type": "Feature",
  "properties": {
    "iso:country":"AU",
    "sg:address":"Shop 2, 181 Murray St",
    "sg:city":"Tanunda",
    "sg:classifiers":[
        {
            "category":"Shopping",
            "subcategory":"Clothing, Apparel, & Fashions",
            "type":"Retail Goods"
        }
    ],
    "sg:phone":"+61 8 8563 3814",
    "sg:postcode":"5352",
    "sg:province":"SA",
    "sg:tags":[
        "recycled",
        "clothing"
    ],
    "wof:name":"Lifeline Shop The",
    "wof:placetype":"venue"
},
  "geometry": {"coordinates":[138.96925354000001,-34.5170898438],"type":"Point"}
}