{
  "type": "Feature",
  "properties": {
    "addr:full":"PO Box 1241 Palm Beach QLD 4221",
    "addr:postcode":"4221",
    "iso:country":"AU",
    "sg:address":"PO Box 1241",
    "sg:city":"Palm Beach",
    "sg:classifiers":[
        {
            "category":"Social Services",
            "subcategory":"Retirement Home",
            "type":"Services"
        }
    ],
    "sg:phone":"+61 414 489 905",
    "sg:postcode":"4221",
    "sg:province":"QLD",
    "sg:tags":[
        "environmental",
        "consultant",
        "pollution"
    ],
    "wof:name":"Australian Fauna Group",
    "wof:placetype":"venue"
},
  "geometry": {"coordinates":[153.47279357900001,-28.1213493347],"type":"Point"}
}