{
  "type": "Feature",
  "properties": {
    "addr:full":"Carandotta St Mayfield West NSW 2304",
    "addr:postcode":"2304",
    "addr:street":"St",
    "iso:country":"AU",
    "sg:address":"Carandotta St",
    "sg:city":"Mayfield West",
    "sg:classifiers":[
        {
            "category":"Personal",
            "subcategory":"Massage",
            "type":"Services"
        }
    ],
    "sg:phone":"+61 2 4967 5004",
    "sg:postcode":"2304",
    "sg:province":"NSW",
    "sg:tags":[
        "therapy"
    ],
    "wof:name":"Lotherington Donna",
    "wof:placetype":"venue"
},
  "geometry": {"coordinates":[151.724807739,-32.8893852234],"type":"Point"}
}