{
  "type": "Feature",
  "properties": {
    "addr:full":"406 Jamberoo Mountain Rd Jamberoo NSW 2533",
    "addr:housenumber":"406",
    "addr:postcode":"2533",
    "addr:street":"Jamberoo Mountain Rd",
    "iso:country":"AU",
    "sg:address":"406 Jamberoo Mountain Rd",
    "sg:city":"Jamberoo",
    "sg:classifiers":[
        {
            "category":"Retail",
            "subcategory":"Event Space",
            "type":"Services"
        }
    ],
    "sg:phone":"+61 2 4236 0269",
    "sg:postcode":"2533",
    "sg:province":"NSW",
    "sg:tags":[
        "venue",
        "reception",
        "wedding"
    ],
    "wof:name":"Foresters",
    "wof:placetype":"venue"
},
  "geometry": {"coordinates":[150.73469543499999,-34.6556510925],"type":"Point"}
}