{
  "type": "Feature",
  "properties": {
    "addr:full":"13 St Andrews Ave Bendigo VIC 3550",
    "addr:housenumber":"13",
    "addr:postcode":"3550",
    "addr:street":"St Andrews Ave",
    "iso:country":"AU",
    "sg:address":"13 St Andrews Ave",
    "sg:city":"Bendigo",
    "sg:classifiers":[
        {
            "category":"Home & Garden",
            "subcategory":"Hardware",
            "type":"Retail Goods"
        }
    ],
    "sg:phone":"+61 3 5443 0666",
    "sg:postcode":"3550",
    "sg:province":"VIC",
    "sg:tags":[
        "plumber",
        "supply"
    ],
    "wof:name":"Tradelink Plumbing Centres",
    "wof:placetype":"venue"
},
  "geometry": {"coordinates":[144.284057617,-36.7600212097],"type":"Point"}
}