{
  "type": "Feature",
  "properties": {
    "addr:full":"124a Manning St Kiama NSW 2533",
    "addr:housenumber":"124a",
    "addr:postcode":"2533",
    "addr:street":"Manning St",
    "iso:country":"AU",
    "sg:address":"124a Manning St",
    "sg:city":"Kiama",
    "sg:classifiers":[
        {
            "category":"Health Services",
            "subcategory":"Dentist",
            "type":"Services"
        }
    ],
    "sg:phone":"+61 2 4232 2999",
    "sg:postcode":"2533",
    "sg:province":"NSW",
    "sg:tags":[
        "dental",
        "prosthetist"
    ],
    "wof:name":"Association Of Dental Prosthetists Inc",
    "wof:placetype":"venue"
},
  "geometry": {"coordinates":[150.85118102999999,-34.6780433655],"type":"Point"}
}