{
  "type": "Feature",
  "properties": {
    "addr:full":"Shp8/ 1a Grange Rd Toorak VIC 3142",
    "addr:housenumber":"/ 1a",
    "addr:postcode":"3142",
    "addr:street":"Grange Rd",
    "iso:country":"AU",
    "sg:address":"Shp8/ 1a Grange Rd",
    "sg:city":"Toorak",
    "sg:classifiers":[
        {
            "category":"Bars & Pubs",
            "subcategory":"Wine Bar",
            "type":"Food & Drink"
        }
    ],
    "sg:phone":"+61 3 9827 4755",
    "sg:postcode":"3142",
    "sg:province":"VIC",
    "wof:name":"La Petite Gi Gis",
    "wof:placetype":"venue"
},
  "geometry": {"coordinates":[145.010665894,-37.8409538269],"type":"Point"}
}