{
  "type": "Feature",
  "properties": {
    "addr:full":"Suite 2/ 137 Ingham Rd Townsville QLD 4810",
    "addr:housenumber":"/ 137",
    "addr:postcode":"4810",
    "addr:street":"Ingham Rd",
    "iso:country":"AU",
    "sg:address":"Suite 2/ 137 Ingham Rd",
    "sg:city":"Townsville",
    "sg:classifiers":[
        {
            "category":"Utilities",
            "subcategory":"Telephone",
            "type":"Services"
        }
    ],
    "sg:phone":"+61 7 4722 0888",
    "sg:postcode":"4810",
    "sg:province":"QLD",
    "sg:tags":[
        "equipment",
        "system"
    ],
    "wof:name":"Deltacomm",
    "wof:placetype":"venue"
},
  "geometry": {"coordinates":[146.79342700000001,-19.267366],"type":"Point"}
}