{
  "type": "Feature",
  "properties": {
    "iso:country":"AU",
    "sg:address":"Bular Rd",
    "sg:city":"Kilkivan",
    "sg:classifiers":[
        {
            "category":"Building & Trades",
            "subcategory":"Landscaping Services",
            "type":"Services"
        }
    ],
    "sg:phone":"+61 7 5484 7310",
    "sg:postcode":"4600",
    "sg:province":"QLD",
    "sg:tags":[
        "grazier"
    ],
    "wof:name":"Elliott V & D",
    "wof:placetype":"venue"
},
  "geometry": {"coordinates":[152.318298,-26.077995],"type":"Point"}
}