{
  "type": "Feature",
  "properties": {
    "iso:country":"AU",
    "sg:address":"218 Lilleys Rd",
    "sg:city":"Swan Bay",
    "sg:classifiers":[
        {
            "category":"Building & Trades",
            "subcategory":"Landscaping Services",
            "type":"Services"
        }
    ],
    "sg:phone":"+61 2 4997 5243",
    "sg:postcode":"2324",
    "sg:province":"NSW",
    "sg:tags":[
        "consultant"
    ],
    "wof:name":"Peake Project Services Pty Ltd",
    "wof:placetype":"venue"
},
  "geometry": {"coordinates":[151.936599731,-32.6923484802],"type":"Point"}
}