{
  "type": "Feature",
  "properties": {
    "iso:country":"AU",
    "sg:address":"72- 78 Bell St",
    "sg:city":"Heidelberg",
    "sg:classifiers":[
        {
            "category":"Professional",
            "subcategory":"Detective & Security Services",
            "type":"Services"
        }
    ],
    "sg:phone":"+61 13 11 49",
    "sg:postcode":"3084",
    "sg:province":"VIC",
    "sg:tags":[
        "consultant",
        "system"
    ],
    "wof:name":"Mr Antenna Communications Pty Ltd",
    "wof:placetype":"venue"
},
  "geometry": {"coordinates":[145.05354309099999,-37.7538261414],"type":"Point"}
}