{
  "type": "Feature",
  "properties": {
    "addr:full":"227 Draper St Cairns QLD 4870",
    "addr:housenumber":"227",
    "addr:postcode":"4870",
    "addr:street":"Draper St",
    "iso:country":"AU",
    "sg:address":"227 Draper St",
    "sg:city":"Cairns",
    "sg:classifiers":[
        {
            "category":"Professional",
            "subcategory":"Engineering",
            "type":"Services"
        }
    ],
    "sg:phone":"+61 7 4030 1000",
    "sg:postcode":"4870",
    "sg:province":"QLD",
    "sg:tags":[
        "consulting",
        "engineer"
    ],
    "sg:website":"http://www.mgfnq.com.au",
    "wof:name":"M G F Consultants (NQ) Pty Ltd",
    "wof:placetype":"venue"
},
  "geometry": {"coordinates":[145.769332886,-16.9276046753],"type":"Point"}
}