{
  "type": "Feature",
  "properties": {
    "addr:full":"235 Lava St Warrnambool VIC 3280",
    "addr:housenumber":"235",
    "addr:postcode":"3280",
    "addr:street":"Lava St",
    "iso:country":"AU",
    "sg:address":"235 Lava St",
    "sg:city":"Warrnambool",
    "sg:classifiers":[
        {
            "category":"Shopping",
            "subcategory":"Clothing, Apparel, & Fashions",
            "type":"Retail Goods"
        }
    ],
    "sg:phone":"+61 3 5562 4004",
    "sg:postcode":"3280",
    "sg:province":"VIC",
    "sg:tags":[
        "recycled",
        "clothing"
    ],
    "wof:name":"Salvation Army Family Store & Home Collection",
    "wof:placetype":"venue"
},
  "geometry": {"coordinates":[142.48008727999999,-38.3796806335],"type":"Point"}
}