{
  "type": "Feature",
  "properties": {
    "addr:full":"346 Candoormakh Creek Rd Nabiac NSW 2312",
    "addr:housenumber":"346",
    "addr:postcode":"2312",
    "addr:street":"Candoormakh Creek Rd",
    "iso:country":"AU",
    "sg:address":"346 Candoormakh Creek Rd",
    "sg:city":"Nabiac",
    "sg:classifiers":[
        {
            "category":"Building & Trades",
            "subcategory":"Landscaping Services",
            "type":"Services"
        }
    ],
    "sg:phone":"+61 2 6554 1364",
    "sg:postcode":"2312",
    "sg:province":"NSW",
    "sg:tags":[
        "horticultural",
        "consultant"
    ],
    "wof:name":"Coast & Country Horticulture",
    "wof:placetype":"venue"
},
  "geometry": {"coordinates":[152.354446,-32.097198],"type":"Point"}
}