{
  "type": "Feature",
  "properties": {
    "addr:full":"31 Cobah Rd Arcadia NSW 2159",
    "addr:housenumber":"31",
    "addr:postcode":"2159",
    "addr:street":"Cobah Rd",
    "iso:country":"AU",
    "sg:address":"31 Cobah Rd",
    "sg:city":"Arcadia",
    "sg:classifiers":[
        {
            "category":"Sports & Exercise",
            "subcategory":"Gym",
            "type":"Entertainment"
        }
    ],
    "sg:phone":"+61 2 9653 1115",
    "sg:postcode":"2159",
    "sg:province":"NSW",
    "sg:tags":[
        "health",
        "fitness"
    ],
    "wof:name":"Arcadia Health Centre P/L",
    "wof:placetype":"venue"
},
  "geometry": {"coordinates":[151.04107665999999,-33.615272522],"type":"Point"}
}