{
  "type": "Feature",
  "properties": {
    "addr:full":"13 Bronwyn St Caloundra QLD 4551",
    "addr:housenumber":"13",
    "addr:postcode":"4551",
    "addr:street":"Bronwyn St",
    "iso:country":"AU",
    "sg:address":"13 Bronwyn St",
    "sg:city":"Caloundra",
    "sg:classifiers":[
        {
            "category":"Sports & Exercise",
            "subcategory":"Gym",
            "type":"Entertainment"
        }
    ],
    "sg:phone":"+61 7 5491 2883",
    "sg:postcode":"4551",
    "sg:province":"QLD",
    "sg:tags":[
        "health",
        "fitness"
    ],
    "wof:name":"Caloundra Gym & Caloundra Fitness Centre",
    "wof:placetype":"venue"
},
  "geometry": {"coordinates":[153.11117553700001,-26.7946147919],"type":"Point"}
}