{
  "type": "Feature",
  "properties": {
    "addr:full":"23 Ellworthy St Mitchelton QLD 4053",
    "addr:housenumber":"23",
    "addr:postcode":"4053",
    "addr:street":"Ellworthy St",
    "iso:country":"AU",
    "sg:address":"23 Ellworthy St",
    "sg:city":"Mitchelton",
    "sg:classifiers":[
        {
            "category":"Building & Trades",
            "subcategory":"Landscaping Services",
            "type":"Services"
        }
    ],
    "sg:phone":"+61 7 3355 5274",
    "sg:postcode":"4053",
    "sg:province":"QLD",
    "sg:tags":[
        "architect",
        "landscape"
    ],
    "wof:name":"Intrigue Excavations",
    "wof:placetype":"venue"
},
  "geometry": {"coordinates":[152.970977783,-27.4113101959],"type":"Point"}
}