{
  "type": "Feature",
  "properties": {
    "iso:country":"AU",
    "sg:address":"228 Cowper St",
    "sg:city":"Warrawong",
    "sg:classifiers":[
        {
            "category":"Health Services",
            "subcategory":"Doctor",
            "type":"Services"
        }
    ],
    "sg:phone":"+61 2 4274 3141",
    "sg:postcode":"2502",
    "sg:province":"NSW",
    "sg:tags":[
        "medical",
        "practitioner"
    ],
    "wof:name":"Yuen K W",
    "wof:placetype":"venue"
},
  "geometry": {"coordinates":[150.88647499999999,-34.485313],"type":"Point"}
}