{
  "type": "Feature",
  "properties": {
    "addr:full":"20 Angel St Newtown NSW 2042",
    "addr:housenumber":"20",
    "addr:postcode":"2042",
    "addr:street":"Angel St",
    "iso:country":"AU",
    "sg:address":"20 Angel St",
    "sg:city":"Newtown",
    "sg:classifiers":[
        {
            "category":"Personal",
            "subcategory":"Massage",
            "type":"Services"
        }
    ],
    "sg:phone":"+61 2 9519 6950",
    "sg:postcode":"2042",
    "sg:province":"NSW",
    "sg:tags":[
        "therapy"
    ],
    "wof:name":"Elaine Parry Therapeutic & Remedial Massage",
    "wof:placetype":"venue"
},
  "geometry": {"coordinates":[151.180847,-33.899544],"type":"Point"}
}