{
  "type": "Feature",
  "properties": {
    "addr:full":"Unit 8/ 190 Invermay Rd Invermay TAS 7248",
    "addr:housenumber":"/ 190",
    "addr:postcode":"7248",
    "addr:street":"Invermay Rd",
    "iso:country":"AU",
    "sg:address":"Unit 8/ 190 Invermay Rd",
    "sg:city":"Invermay",
    "sg:classifiers":[
        {
            "category":"Building & Trades",
            "subcategory":"Locksmith",
            "type":"Services"
        }
    ],
    "sg:phone":"+61 1300 559 627",
    "sg:postcode":"7248",
    "sg:province":"TAS",
    "sg:tags":[
        "equipment",
        "operating",
        "door",
        "gate"
    ],
    "wof:name":"CBS Tasmania Pty Ltd",
    "wof:placetype":"venue"
},
  "geometry": {"coordinates":[147.13255310100001,-41.4106903076],"type":"Point"}
}