{
  "type": "Feature",
  "properties": {
    "addr:full":"42 Massie St Cooma NSW 2630",
    "addr:housenumber":"42",
    "addr:postcode":"2630",
    "addr:street":"Massie St",
    "iso:country":"AU",
    "sg:address":"42 Massie St",
    "sg:city":"Cooma",
    "sg:classifiers":[
        {
            "category":"Personal",
            "subcategory":"Beauty Salon",
            "type":"Services"
        }
    ],
    "sg:phone":"+61 2 6452 3800",
    "sg:postcode":"2630",
    "sg:province":"NSW",
    "sg:tags":[
        "hairdresser"
    ],
    "wof:name":"Dieter's Hair Care",
    "wof:placetype":"venue"
},
  "geometry": {"coordinates":[149.127975464,-36.2328109741],"type":"Point"}
}