{
  "type": "Feature",
  "properties": {
    "addr:full":"Shop 6 Arndale Shopping Centre Cinderella Drv Springwood QLD 4127",
    "addr:housenumber":"shop 6",
    "addr:postcode":"4127",
    "addr:street":"Arndale Shopping;Cinderella Drv",
    "iso:country":"AU",
    "sg:address":"Shop 6 Arndale Shopping Centre Cinderella Drv",
    "sg:city":"Springwood",
    "sg:classifiers":[
        {
            "category":"Travel",
            "subcategory":"Travel Agent",
            "type":"Entertainment"
        }
    ],
    "sg:phone":"+61 7 3208 8644",
    "sg:postcode":"4127",
    "sg:province":"QLD",
    "sg:tags":[
        "consultant"
    ],
    "wof:name":"Harvey World Travel",
    "wof:placetype":"venue"
},
  "geometry": {"coordinates":[153.13267517099999,-27.6164894104],"type":"Point"}
}