{
  "type": "Feature",
  "properties": {
    "iso:country":"AU",
    "sg:address":"3 Dalmar Pl",
    "sg:city":"Carlingford",
    "sg:classifiers":[
        {
            "category":"Health Services",
            "subcategory":"Doctor",
            "type":"Services"
        }
    ],
    "sg:phone":"+61 2 9874 4566",
    "sg:postcode":"2118",
    "sg:province":"NSW",
    "sg:tags":[
        "medical",
        "practitioner"
    ],
    "wof:name":"Berecry D S",
    "wof:placetype":"venue"
},
  "geometry": {"coordinates":[151.061935425,-33.7847938538],"type":"Point"}
}