{
  "type": "Feature",
  "properties": {
    "iso:country":"AU",
    "sg:address":"88 Union St",
    "sg:city":"Armadale",
    "sg:classifiers":[
        {
            "category":"Personal",
            "subcategory":"Beauty Salon",
            "type":"Services"
        }
    ],
    "sg:phone":"+61 3 9509 3750",
    "sg:postcode":"3143",
    "sg:province":"VIC",
    "sg:tags":[
        "hairdresser"
    ],
    "wof:name":"Emma's Hair & Beauty Centre",
    "wof:placetype":"venue"
},
  "geometry": {"coordinates":[145.02859497099999,-37.8596763611],"type":"Point"}
}