{
  "type": "Feature",
  "properties": {
    "addr:full":"Balo St Moree NSW 2400",
    "addr:postcode":"2400",
    "addr:street":"Balo St",
    "iso:country":"AU",
    "sg:address":"Balo St",
    "sg:city":"Moree",
    "sg:classifiers":[
        {
            "category":"Retail",
            "subcategory":"Event Space",
            "type":"Services"
        }
    ],
    "sg:phone":"+61 2 6752 1227",
    "sg:postcode":"2400",
    "sg:province":"NSW",
    "sg:tags":[
        "function",
        "organiser"
    ],
    "wof:name":"Max Function & Conference Centre",
    "wof:placetype":"venue"
},
  "geometry": {"coordinates":[149.841598511,-29.4641361237],"type":"Point"}
}