{
  "type": "Feature",
  "properties": {
    "addr:full":"120 Muller Rd Greenacres SA 5086",
    "addr:housenumber":"120",
    "addr:postcode":"5086",
    "addr:street":"Muller Rd",
    "iso:country":"AU",
    "sg:address":"120 Muller Rd",
    "sg:city":"Greenacres",
    "sg:classifiers":[
        {
            "category":"Farming",
            "subcategory":"Fish & Marine Products",
            "type":"Manufacturing & Wholesale Goods"
        }
    ],
    "sg:phone":"+61 8 8266 1622",
    "sg:postcode":"5086",
    "sg:province":"SA",
    "sg:tags":[
        "lead",
        "supply"
    ],
    "wof:name":"Solder-Tech Pty Ltd",
    "wof:placetype":"venue"
},
  "geometry": {"coordinates":[138.63333129899999,-34.8711929321],"type":"Point"}
}