{
  "type": "Feature",
  "properties": {
    "addr:full":"240 Severin St Cairns QLD 4870",
    "addr:housenumber":"240",
    "addr:postcode":"4870",
    "addr:street":"Severin St",
    "iso:country":"AU",
    "sg:address":"240 Severin St",
    "sg:city":"Cairns",
    "sg:classifiers":[
        {
            "category":"Manufacturing",
            "subcategory":"Furniture",
            "type":"Manufacturing & Wholesale Goods"
        }
    ],
    "sg:phone":"+61 7 4041 0190",
    "sg:postcode":"4870",
    "sg:province":"QLD",
    "sg:tags":[
        "builder",
        "designer",
        "custom"
    ],
    "wof:name":"A Touch Of Iron",
    "wof:placetype":"venue"
},
  "geometry": {"coordinates":[145.767669678,-16.9285564423],"type":"Point"}
}