{
  "type": "Feature",
  "properties": {
    "addr:full":"36 Bolong Rd Bomaderry NSW 2541",
    "addr:housenumber":"36",
    "addr:postcode":"2541",
    "addr:street":"Bolong Rd",
    "iso:country":"AU",
    "sg:address":"36 Bolong Rd",
    "sg:city":"Bomaderry",
    "sg:classifiers":[
        {
            "category":"Wholesale",
            "subcategory":"Farm Supplies",
            "type":"Manufacturing & Wholesale Goods"
        }
    ],
    "sg:phone":"+61 2 4421 2215",
    "sg:postcode":"2541",
    "sg:province":"NSW",
    "sg:tags":[
        "equipment"
    ],
    "wof:name":"Dairy Farmers Country Stores",
    "wof:placetype":"venue"
},
  "geometry": {"coordinates":[150.61007690400001,-34.8559265137],"type":"Point"}
}