{
  "type": "Feature",
  "properties": {
    "iso:country":"AU",
    "sg:address":"Unit 2, 17 Clare Mace Crs",
    "sg:city":"Berkeley Vale",
    "sg:classifiers":[
        {
            "category":"Home & Garden",
            "subcategory":"Hardware",
            "type":"Retail Goods"
        }
    ],
    "sg:phone":"+61 2 4388 3044",
    "sg:postcode":"2261",
    "sg:province":"NSW",
    "sg:tags":[
        "plumber",
        "supply"
    ],
    "wof:name":"Bathroomware Centre The",
    "wof:placetype":"venue"
},
  "geometry": {"coordinates":[151.438583,-33.344639],"type":"Point"}
}