{
  "type": "Feature",
  "properties": {
    "iso:country":"AU",
    "sg:address":"1290 Logan Rd",
    "sg:city":"Mt Gravatt",
    "sg:classifiers":[
        {
            "category":"Retail",
            "subcategory":"Repair Shop",
            "type":"Services"
        }
    ],
    "sg:phone":"+61 7 3849 4176",
    "sg:postcode":"4122",
    "sg:province":"QLD",
    "sg:tags":[
        "machine",
        "sewing"
    ],
    "wof:name":"Sewco Sewing & Patchwork Centre",
    "wof:placetype":"venue"
},
  "geometry": {"coordinates":[153.07359314000001,-27.5314979553],"type":"Point"}
}