{
  "type": "Feature",
  "properties": {
    "iso:country":"AU",
    "sg:address":"64- 66 Benalla Rd",
    "sg:city":"Yarrawonga",
    "sg:classifiers":[
        {
            "category":"Wholesale",
            "subcategory":"Electrical",
            "type":"Manufacturing & Wholesale Goods"
        }
    ],
    "sg:phone":"+61 3 5743 2644",
    "sg:postcode":"3730",
    "sg:province":"VIC",
    "sg:tags":[
        "wholesaler"
    ],
    "wof:name":"Middendorp Electric Co Pty Ltd",
    "wof:placetype":"venue"
},
  "geometry": {"coordinates":[145.99940490700001,-36.020526886],"type":"Point"}
}