{
  "type": "Feature",
  "properties": {
    "addr:full":"16 Argyle St Bilgola Plateau NSW 2107",
    "addr:housenumber":"16",
    "addr:postcode":"2107",
    "addr:street":"Argyle St",
    "iso:country":"AU",
    "sg:address":"16 Argyle St",
    "sg:city":"Bilgola Plateau",
    "sg:classifiers":[
        {
            "category":"Building & Trades",
            "subcategory":"Landscaping Services",
            "type":"Services"
        }
    ],
    "sg:phone":"+61 2 9918 3698",
    "sg:postcode":"2107",
    "sg:province":"NSW",
    "sg:tags":[
        "designer",
        "landscape",
        "contractor"
    ],
    "wof:name":"Bilgola Botanics",
    "wof:placetype":"venue"
},
  "geometry": {"coordinates":[151.313598633,-33.6474952698],"type":"Point"}
}