{
  "type": "Feature",
  "properties": {
    "iso:country":"AU",
    "sg:address":"Tempe Reserve Site Office Holbeach Drv",
    "sg:city":"Tempe",
    "sg:classifiers":[
        {
            "category":"Building & Trades",
            "subcategory":"Landscaping Services",
            "type":"Services"
        }
    ],
    "sg:phone":"+61 2 9559 0500",
    "sg:postcode":"2044",
    "sg:province":"NSW",
    "sg:tags":[
        "consultant"
    ],
    "wof:name":"Transfield Bouygues Joint Venture",
    "wof:placetype":"venue"
},
  "geometry": {"coordinates":[151.15913399999999,-33.927464],"type":"Point"}
}