{
  "type": "Feature",
  "properties": {
    "addr:full":"241 George St Liverpool NSW 2170",
    "addr:housenumber":"241",
    "addr:postcode":"2170",
    "addr:street":"George St",
    "iso:country":"AU",
    "sg:address":"241 George St",
    "sg:city":"Liverpool",
    "sg:classifiers":[
        {
            "category":"Real Estate",
            "subcategory":"Real Estate Agent",
            "type":"Services"
        }
    ],
    "sg:phone":"+61 2 9602 0055",
    "sg:postcode":"2170",
    "sg:province":"NSW",
    "wof:name":"LJ Hooker Real Estate",
    "wof:placetype":"venue"
},
  "geometry": {"coordinates":[150.924484253,-33.9239959717],"type":"Point"}
}