{
  "type": "Feature",
  "properties": {
    "addr:full":"Unit 14, 25 Alexandra Rd Glebe NSW 2037",
    "addr:housenumber":"25",
    "addr:postcode":"2037",
    "addr:street":"Alexandra Rd",
    "iso:country":"AU",
    "sg:address":"Unit 14, 25 Alexandra Rd",
    "sg:city":"Glebe",
    "sg:classifiers":[
        {
            "category":"Manufacturing",
            "subcategory":"Furniture",
            "type":"Manufacturing & Wholesale Goods"
        }
    ],
    "sg:phone":"+61 2 9584 3341",
    "sg:postcode":"2037",
    "sg:province":"NSW",
    "sg:tags":[
        "builder",
        "designer",
        "custom"
    ],
    "wof:name":"Matt Long",
    "wof:placetype":"venue"
},
  "geometry": {"coordinates":[151.17979431099999,-33.8737831116],"type":"Point"}
}