{
  "type": "Feature",
  "properties": {
    "iso:country":"AU",
    "sg:address":"12- 14 Glenferrie Rd",
    "sg:city":"Malvern",
    "sg:classifiers":[
        {
            "category":"Home & Garden",
            "subcategory":"Carpets & Floor Coverings",
            "type":"Retail Goods"
        }
    ],
    "sg:phone":"+61 3 9509 9500",
    "sg:postcode":"3144",
    "sg:province":"VIC",
    "sg:tags":[
        "mattress"
    ],
    "wof:name":"Ken Bruce (Rentals) Pty Ltd",
    "wof:placetype":"venue"
},
  "geometry": {"coordinates":[145.02813720699999,-37.8645515442],"type":"Point"}
}