{
  "type": "Feature",
  "properties": {
    "addr:full":"66 Wattle St Lyneham ACT 2602",
    "addr:housenumber":"66",
    "addr:postcode":"2602",
    "addr:street":"Wattle St",
    "iso:country":"AU",
    "sg:address":"66 Wattle St",
    "sg:city":"Lyneham",
    "sg:classifiers":[
        {
            "category":"Autos & Motor Vehicles",
            "subcategory":"Fuel & Gas Station",
            "type":"Retail Goods"
        }
    ],
    "sg:phone":"+61 2 6248 5185",
    "sg:postcode":"2602",
    "sg:province":"ACT",
    "wof:name":"Ampol Limited",
    "wof:placetype":"venue"
},
  "geometry": {"coordinates":[149.125488281,-35.2533302307],"type":"Point"}
}