{
  "type": "Feature",
  "properties": {
    "iso:country":"AU",
    "sg:address":"180 Currans Rd",
    "sg:city":"Cooranbong",
    "sg:classifiers":[
        {
            "category":"Manufacturing",
            "subcategory":"Tools & Machinery",
            "type":"Manufacturing & Wholesale Goods"
        }
    ],
    "sg:phone":"+61 438 773 307",
    "sg:postcode":"2265",
    "sg:province":"NSW",
    "sg:tags":[
        "earth",
        "excavating",
        "moving",
        "equipment"
    ],
    "wof:name":"Coastal Earthmoving Repairs Pty Ltd",
    "wof:placetype":"venue"
},
  "geometry": {"coordinates":[151.472595,-33.081703],"type":"Point"}
}