{
  "type": "Feature",
  "properties": {
    "iso:country":"AU",
    "sg:address":"18 Brown St",
    "sg:city":"Avondale Heights",
    "sg:classifiers":[
        {
            "category":"Building & Trades",
            "subcategory":"Cleaning & Sanitation",
            "type":"Services"
        }
    ],
    "sg:phone":"+61 1800 442 855",
    "sg:postcode":"3034",
    "sg:province":"VIC",
    "sg:tags":[
        "cleaner",
        "repairer",
        "roof"
    ],
    "wof:name":"O.A.P. Maintenance Roofing & Guttering",
    "wof:placetype":"venue"
},
  "geometry": {"coordinates":[144.85498,-37.767887],"type":"Point"}
}