{
  "type": "Feature",
  "properties": {
    "iso:country":"AU",
    "sg:address":"Shelsley House, 1 Frederick St",
    "sg:city":"Frewville",
    "sg:classifiers":[
        {
            "category":"Health Services",
            "subcategory":"Doctor",
            "type":"Services"
        }
    ],
    "sg:phone":"+61 8 8379 2926",
    "sg:postcode":"5063",
    "sg:province":"SA",
    "sg:tags":[
        "medical",
        "practitioner"
    ],
    "wof:name":"Begg Jules Dr",
    "wof:placetype":"venue"
},
  "geometry": {"coordinates":[138.630325317,-34.9487876892],"type":"Point"}
}