{
  "type": "Feature",
  "properties": {
    "addr:full":"PO Box 101 Coldstream VIC 3770",
    "addr:postcode":"3770",
    "iso:country":"AU",
    "sg:address":"PO Box 101",
    "sg:city":"Coldstream",
    "sg:classifiers":[
        {
            "category":"Health Services",
            "subcategory":"Doctor",
            "type":"Services"
        }
    ],
    "sg:phone":"+61 3 9739 1978",
    "sg:postcode":"3770",
    "sg:province":"VIC",
    "sg:tags":[
        "medical",
        "practitioner"
    ],
    "wof:name":"MacGowan K M Dr",
    "wof:placetype":"venue"
},
  "geometry": {"coordinates":[145.378525,-37.724941],"type":"Point"}
}