{
  "type": "Feature",
  "properties": {
    "addr:full":"Lot 340 Chapman Valley Rd Geraldton WA 6530",
    "addr:postcode":"6530",
    "addr:street":"Chapman Valley Rd",
    "iso:country":"AU",
    "sg:address":"Lot 340 Chapman Valley Rd",
    "sg:city":"Geraldton",
    "sg:classifiers":[
        {
            "category":"Utilities",
            "type":"Services"
        }
    ],
    "sg:phone":"+61 8 9938 3905",
    "sg:postcode":"6530",
    "sg:province":"WA",
    "sg:tags":[
        "refrigeration",
        "industrial",
        "commercial",
        "retail"
    ],
    "wof:name":"Option Refrigeration & Air Conditioning",
    "wof:placetype":"venue"
},
  "geometry": {"coordinates":[114.636749268,-28.7199840546],"type":"Point"}
}