{
  "type": "Feature",
  "properties": {
    "addr:full":"6/ 400 St Kilda Rd St Kilda VIC 3182",
    "addr:housenumber":"/ 400",
    "addr:postcode":"3182",
    "addr:street":"St Kilda Rd",
    "iso:country":"AU",
    "sg:address":"6/ 400 St Kilda Rd",
    "sg:city":"St Kilda",
    "sg:classifiers":[
        {
            "category":"Organizations",
            "subcategory":"Professional Association",
            "type":"Services"
        }
    ],
    "sg:phone":"+61 3 9534 9000",
    "sg:postcode":"3182",
    "sg:province":"VIC",
    "sg:tags":[
        "web",
        "internet"
    ],
    "wof:name":"GO 4 Multimedia",
    "wof:placetype":"venue"
},
  "geometry": {"coordinates":[144.98707580600001,-37.867313385],"type":"Point"}
}