{
  "type": "Feature",
  "properties": {
    "iso:country":"AU",
    "sg:address":"Shop 6",
    "sg:city":"A/21 Birtwill Street, Coolum Beach",
    "sg:classifiers":[
        {
            "category":"Health Services",
            "subcategory":"Health Practitioner",
            "type":"Services"
        }
    ],
    "sg:phone":"+61 7 5446 1630",
    "sg:postcode":"4573",
    "sg:province":"QLD",
    "sg:tags":[
        "physiotherapist"
    ],
    "wof:name":"Birtwill Physiotherapy",
    "wof:placetype":"venue"
},
  "geometry": {"coordinates":[153.08860799999999,-26.52704],"type":"Point"}
}