{
  "type": "Feature",
  "properties": {
    "addr:full":"New Lake Entrance Rd Shellharbour NSW 2529",
    "addr:postcode":"2529",
    "addr:street":"New;Entrance Rd",
    "iso:country":"AU",
    "sg:address":"New Lake Entrance Rd",
    "sg:city":"Shellharbour",
    "sg:classifiers":[
        {
            "category":"Restaurant",
            "type":"Food & Drink"
        }
    ],
    "sg:phone":"+61 2 4297 2799",
    "sg:postcode":"2529",
    "sg:province":"NSW",
    "wof:name":"Burger King",
    "wof:placetype":"venue"
},
  "geometry": {"coordinates":[150.82247924800001,-34.5730705261],"type":"Point"}
}