{
  "type": "Feature",
  "properties": {
    "addr:full":"189 River St Maclean NSW 2463",
    "addr:housenumber":"189",
    "addr:postcode":"2463",
    "addr:street":"River St",
    "iso:country":"AU",
    "sg:address":"189 River St",
    "sg:city":"Maclean",
    "sg:classifiers":[
        {
            "category":"Professional",
            "subcategory":"Accounting & Tax Preparation",
            "type":"Services"
        }
    ],
    "sg:phone":"+61 2 6645 3083",
    "sg:postcode":"2463",
    "sg:province":"NSW",
    "sg:tags":[
        "consultant",
        "taxation"
    ],
    "wof:name":"Hamilton Simmons & Co",
    "wof:placetype":"venue"
},
  "geometry": {"coordinates":[153.19692993199999,-29.4549865723],"type":"Point"}
}