{
  "type": "Feature",
  "properties": {
    "addr:full":"Shop 6/ 1 Maleny Rd Landsborough QLD 4550",
    "addr:housenumber":"shop 6 / 1",
    "addr:postcode":"4550",
    "addr:street":"Maleny Rd",
    "iso:country":"AU",
    "sg:address":"Shop 6/ 1 Maleny Rd",
    "sg:city":"Landsborough",
    "sg:classifiers":[
        {
            "category":"Shopping",
            "subcategory":"Crafts & Fabrics",
            "type":"Retail Goods"
        }
    ],
    "sg:phone":"+61 7 5494 1588",
    "sg:postcode":"4550",
    "sg:province":"QLD",
    "sg:tags":[
        "supply"
    ],
    "wof:name":"Scrappidoo Scrap Booking",
    "wof:placetype":"venue"
},
  "geometry": {"coordinates":[152.96551513700001,-26.8091011047],"type":"Point"}
}