{
  "type": "Feature",
  "properties": {
    "addr:full":"Old Supreme Court 42 - 48 East St Rockhampton QLD 4700",
    "addr:housenumber":"42 48",
    "addr:postcode":"4700",
    "addr:street":"East St",
    "iso:country":"AU",
    "sg:address":"Old Supreme Court 42 - 48 East St",
    "sg:city":"Rockhampton",
    "sg:classifiers":[
        {
            "category":"Health Services",
            "subcategory":"Health Practitioner",
            "type":"Services"
        }
    ],
    "sg:phone":"+61 7 4922 6138",
    "sg:postcode":"4700",
    "sg:province":"QLD",
    "sg:tags":[
        "psychologist"
    ],
    "wof:name":"Quaife-Ryan & Associates",
    "wof:placetype":"venue"
},
  "geometry": {"coordinates":[150.525115967,-23.3919944763],"type":"Point"}
}