{
  "type": "Feature",
  "properties": {
    "addr:full":"244 Preston Rd Wynnum West QLD 4178",
    "addr:housenumber":"244",
    "addr:postcode":"4178",
    "addr:street":"Preston Rd",
    "iso:country":"AU",
    "sg:address":"244 Preston Rd",
    "sg:city":"Wynnum West",
    "sg:classifiers":[
        {
            "category":"Retail",
            "subcategory":"Veterinary Services",
            "type":"Services"
        }
    ],
    "sg:phone":"+61 7 3893 0858",
    "sg:postcode":"4178",
    "sg:province":"QLD",
    "sg:tags":[
        "surgeon"
    ],
    "wof:name":"Hollingsworth Ken Dr",
    "wof:placetype":"venue"
},
  "geometry": {"coordinates":[153.16363525400001,-27.4539871216],"type":"Point"}
}