{
  "type": "Feature",
  "properties": {
    "iso:country":"AU",
    "sg:address":"41 Scarfe St",
    "sg:city":"Camdale",
    "sg:classifiers":[
        {
            "category":"Retail",
            "subcategory":"Auto Repair",
            "type":"Services"
        }
    ],
    "sg:phone":"+61 3 6435 1721",
    "sg:postcode":"7320",
    "sg:province":"TAS",
    "sg:tags":[
        "body",
        "builder",
        "motor"
    ],
    "wof:name":"Rod Stone Bodyworks",
    "wof:placetype":"venue"
},
  "geometry": {"coordinates":[145.840454,-41.043831],"type":"Point"}
}