{
  "type": "Feature",
  "properties": {
    "addr:full":"38 Cherylnne Crs Kilsyth VIC 3137",
    "addr:housenumber":"38",
    "addr:postcode":"3137",
    "addr:street":"Cherylnne Crs",
    "iso:country":"AU",
    "sg:address":"38 Cherylnne Crs",
    "sg:city":"Kilsyth",
    "sg:classifiers":[
        {
            "category":"Communications",
            "type":"Services"
        }
    ],
    "sg:phone":"+61 418 606 065",
    "sg:postcode":"3137",
    "sg:province":"VIC",
    "sg:tags":[
        "data"
    ],
    "wof:name":"Kopek Communications",
    "wof:placetype":"venue"
},
  "geometry": {"coordinates":[145.31497192399999,-37.8026504517],"type":"Point"}
}