{
  "type": "Feature",
  "properties": {
    "addr:full":"25 Compass Rd Jandakot WA 6164",
    "addr:housenumber":"25",
    "addr:postcode":"6164",
    "addr:street":"Compass Rd",
    "iso:country":"AU",
    "sg:address":"25 Compass Rd",
    "sg:city":"Jandakot",
    "sg:classifiers":[
        {
            "category":"Retail",
            "subcategory":"Auto Repair",
            "type":"Services"
        }
    ],
    "sg:phone":"+61 8 9417 2555",
    "sg:postcode":"6164",
    "sg:province":"WA",
    "sg:tags":[
        "beater",
        "painter",
        "panel"
    ],
    "wof:name":"Kolor Boost",
    "wof:placetype":"venue"
},
  "geometry": {"coordinates":[115.880753,-32.090637],"type":"Point"}
}