{
  "type": "Feature",
  "properties": {
    "iso:country":"AU",
    "sg:address":"1199 Riverway Drv",
    "sg:city":"Rasmussen",
    "sg:classifiers":[
        {
            "category":"Health Services",
            "subcategory":"Doctor",
            "type":"Services"
        }
    ],
    "sg:phone":"+61 7 4774 0299",
    "sg:postcode":"4815",
    "sg:province":"QLD",
    "sg:tags":[
        "medical",
        "practitioner"
    ],
    "wof:name":"Gillman M A",
    "wof:placetype":"venue"
},
  "geometry": {"coordinates":[146.728714,-19.345501],"type":"Point"}
}