{
  "type": "Feature",
  "properties": {
    "addr:full":"689 Pine Ridge Rd Coombabah QLD 4216",
    "addr:housenumber":"689",
    "addr:postcode":"4216",
    "addr:street":"Pine Ridge Rd",
    "iso:country":"AU",
    "sg:address":"689 Pine Ridge Rd",
    "sg:city":"Coombabah",
    "sg:classifiers":[
        {
            "category":"Retail",
            "subcategory":"Auto Repair",
            "type":"Services"
        }
    ],
    "sg:phone":"+61 7 5594 7826",
    "sg:postcode":"4216",
    "sg:province":"QLD",
    "sg:tags":[
        "repairer",
        "motor",
        "engineer"
    ],
    "wof:name":"Autocoast",
    "wof:placetype":"venue"
},
  "geometry": {"coordinates":[153.38787841800001,-27.9119625092],"type":"Point"}
}