{
  "type": "Feature",
  "properties": {
    "addr:full":"3 Watsford Rd Campbelltown NSW 2560",
    "addr:housenumber":"3",
    "addr:postcode":"2560",
    "addr:street":"Watsford Rd",
    "iso:country":"AU",
    "sg:address":"3 Watsford Rd",
    "sg:city":"Campbelltown",
    "sg:classifiers":[
        {
            "category":"Building & Trades",
            "subcategory":"Construction",
            "type":"Services"
        }
    ],
    "sg:phone":"+61 2 4625 2715",
    "sg:postcode":"2560",
    "sg:province":"NSW",
    "sg:tags":[
        "window",
        "aluminium"
    ],
    "wof:name":"Campbelltown Windows & Doors Pty Ltd",
    "wof:placetype":"venue"
},
  "geometry": {"coordinates":[150.81626892099999,-34.0607261658],"type":"Point"}
}