{
  "type": "Feature",
  "properties": {
    "addr:full":"PO Box 238 Seaford SA 5169",
    "addr:postcode":"5169",
    "iso:country":"AU",
    "sg:address":"PO Box 238",
    "sg:city":"Seaford",
    "sg:classifiers":[
        {
            "category":"Building & Trades",
            "subcategory":"Construction",
            "type":"Services"
        }
    ],
    "sg:phone":"+61 8 8386 1509",
    "sg:postcode":"5169",
    "sg:province":"SA",
    "sg:tags":[
        "concrete",
        "contractor"
    ],
    "wof:name":"Pritchard L C",
    "wof:placetype":"venue"
},
  "geometry": {"coordinates":[138.475906372,-35.1824645996],"type":"Point"}
}