{
  "type": "Feature",
  "properties": {
    "iso:country":"AU",
    "sg:address":"2 Craigmore Pl",
    "sg:city":"Melton West",
    "sg:classifiers":[
        {
            "category":"Building & Trades",
            "subcategory":"Cleaning & Sanitation",
            "type":"Services"
        }
    ],
    "sg:phone":"+61 3 9746 9088",
    "sg:postcode":"3337",
    "sg:province":"VIC",
    "sg:tags":[
        "industrial",
        "commercial",
        "contractor"
    ],
    "wof:name":"Blu-Bar Cleaning Service",
    "wof:placetype":"venue"
},
  "geometry": {"coordinates":[144.562515,-37.677719],"type":"Point"}
}