{
  "type": "Feature",
  "properties": {
    "addr:full":"Cnr William & Newcastle Rd East Maitland NSW 2323",
    "addr:postcode":"2323",
    "addr:street":"Rd",
    "iso:country":"AU",
    "sg:address":"Cnr William & Newcastle Rd",
    "sg:city":"East Maitland",
    "sg:classifiers":[
        {
            "category":"Retail",
            "subcategory":"Repair Shop",
            "type":"Services"
        }
    ],
    "sg:phone":"+61 2 4933 7590",
    "sg:postcode":"2323",
    "sg:province":"NSW",
    "sg:tags":[
        "windscreen"
    ],
    "wof:name":"Jackson's Motor Glass",
    "wof:placetype":"venue"
},
  "geometry": {"coordinates":[151.591339111,-32.761013031],"type":"Point"}
}