{
  "type": "Feature",
  "properties": {
    "addr:full":"61- 77 Egerton St Silverwater NSW 2128",
    "addr:housenumber":"77",
    "addr:postcode":"2128",
    "addr:street":"Egerton St",
    "iso:country":"AU",
    "sg:address":"61- 77 Egerton St",
    "sg:city":"Silverwater",
    "sg:classifiers":[
        {
            "category":"Professional",
            "subcategory":"Detective & Security Services",
            "type":"Services"
        }
    ],
    "sg:phone":"+61 2 9647 1277",
    "sg:postcode":"2128",
    "sg:province":"NSW",
    "sg:tags":[
        "consultant",
        "laser"
    ],
    "wof:name":"WH Williams Sheetmetal Engineering",
    "wof:placetype":"venue"
},
  "geometry": {"coordinates":[151.04586792000001,-33.8351821899],"type":"Point"}
}