{
  "type": "Feature",
  "properties": {
    "addr:full":"57 Wooloware Rd Woolooware NSW 2230",
    "addr:housenumber":"57",
    "addr:postcode":"2230",
    "addr:street":"Wooloware Rd",
    "iso:country":"AU",
    "sg:address":"57 Wooloware Rd",
    "sg:city":"Woolooware",
    "sg:classifiers":[
        {
            "category":"Personal",
            "subcategory":"Beauty Salon",
            "type":"Services"
        }
    ],
    "sg:phone":"+61 2 9544 4247",
    "sg:postcode":"2230",
    "sg:province":"NSW",
    "sg:tags":[
        "hairdresser"
    ],
    "wof:name":"Hair Depot",
    "wof:placetype":"venue"
},
  "geometry": {"coordinates":[151.152175903,-34.0584831238],"type":"Point"}
}