{
  "type": "Feature",
  "properties": {
    "iso:country":"AU",
    "sg:address":"12 Dickson Crt",
    "sg:city":"Williamstown",
    "sg:classifiers":[
        {
            "category":"Utilities",
            "subcategory":"Electric",
            "type":"Services"
        }
    ],
    "sg:phone":"+61 3 9399 9943",
    "sg:postcode":"3016",
    "sg:province":"VIC",
    "sg:tags":[
        "electrical",
        "contractor"
    ],
    "wof:name":"Lectek Electrical",
    "wof:placetype":"venue"
},
  "geometry": {"coordinates":[144.88002014200001,-37.8588790894],"type":"Point"}
}