{
  "type": "Feature",
  "properties": {
    "addr:full":"Unit 4 Eaton Fair Shopping Centre Cnr Recreation & Eaton Drvs Eaton WA 6232",
    "addr:postcode":"6232",
    "iso:country":"AU",
    "sg:address":"Unit 4 Eaton Fair Shopping Centre Cnr Recreation & Eaton Drvs",
    "sg:city":"Eaton",
    "sg:classifiers":[
        {
            "category":"Fast Food",
            "type":"Food & Drink"
        }
    ],
    "sg:phone":"+61 8 9725 0366",
    "sg:postcode":"6232",
    "sg:province":"WA",
    "sg:tags":[
        "away",
        "take"
    ],
    "wof:name":"Domino's Pizza",
    "wof:placetype":"venue"
},
  "geometry": {"coordinates":[115.715233,-33.323139],"type":"Point"}
}