{
  "type": "Feature",
  "properties": {
    "addr:full":"Unit 2 4 Yamanda Pl Mornington TAS 7018",
    "addr:housenumber":"4",
    "addr:postcode":"7018",
    "addr:street":"Yamanda Pl",
    "iso:country":"AU",
    "sg:address":"Unit 2 4 Yamanda Pl",
    "sg:city":"Mornington",
    "sg:classifiers":[
        {
            "category":"Manufacturing",
            "subcategory":"Metals",
            "type":"Manufacturing & Wholesale Goods"
        }
    ],
    "sg:phone":"+61 3 6244 7200",
    "sg:postcode":"7018",
    "sg:province":"TAS",
    "sg:tags":[
        "sheet",
        "worker"
    ],
    "wof:name":"A.E. Smith & Son Pty Ltd",
    "wof:placetype":"venue"
},
  "geometry": {"coordinates":[147.403030395,-42.8607673645],"type":"Point"}
}