{
  "type": "Feature",
  "properties": {
    "addr:full":"15 Belmore Rd Peakhurst NSW 2210",
    "addr:housenumber":"15",
    "addr:postcode":"2210",
    "addr:street":"Belmore Rd",
    "iso:country":"AU",
    "sg:address":"15 Belmore Rd",
    "sg:city":"Peakhurst",
    "sg:classifiers":[
        {
            "category":"Building & Trades",
            "subcategory":"Locksmith",
            "type":"Services"
        }
    ],
    "sg:phone":"+61 418 649 629",
    "sg:postcode":"2210",
    "sg:province":"NSW",
    "sg:tags":[
        "lock"
    ],
    "wof:name":"P J Locksmiths & Security",
    "wof:placetype":"venue"
},
  "geometry": {"coordinates":[151.051605,-33.955402],"type":"Point"}
}