{
  "type": "Feature",
  "properties": {
    "addr:full":"Cnr Rodmay & Leo Sts Tuncurry NSW 2428",
    "addr:postcode":"2428",
    "addr:street":"Cnr Rodmay",
    "iso:country":"AU",
    "sg:address":"Cnr Rodmay & Leo Sts",
    "sg:city":"Tuncurry",
    "sg:classifiers":[
        {
            "category":"Transit Center",
            "subcategory":"Freight",
            "type":"Transportation"
        }
    ],
    "sg:phone":"+61 2 6555 3352",
    "sg:postcode":"2428",
    "sg:province":"NSW",
    "sg:tags":[
        "forklift",
        "truck"
    ],
    "wof:name":"McQuillan's Forster Gas",
    "wof:placetype":"venue"
},
  "geometry": {"coordinates":[152.491333,-32.164753],"type":"Point"}
}