{
  "type": "Feature",
  "properties": {
    "addr:full":"40 Charles St St Marys NSW 2760",
    "addr:housenumber":"40",
    "addr:postcode":"2760",
    "addr:street":"Charles St",
    "iso:country":"AU",
    "sg:address":"40 Charles St",
    "sg:city":"St Marys",
    "sg:classifiers":[
        {
            "category":"Wholesale",
            "subcategory":"Machinery & Supplies",
            "type":"Manufacturing & Wholesale Goods"
        }
    ],
    "sg:phone":"+61 2 9673 3125",
    "sg:postcode":"2760",
    "sg:province":"NSW",
    "sg:tags":[
        "equipment",
        "system",
        "elevating",
        "conveying"
    ],
    "wof:name":"Jones Mason Pty Ltd",
    "wof:placetype":"venue"
},
  "geometry": {"coordinates":[150.76893615700001,-33.744052887],"type":"Point"}
}