{
  "type": "Feature",
  "properties": {
    "addr:full":"5 Green St Brandon QLD 4808",
    "addr:housenumber":"5",
    "addr:postcode":"4808",
    "addr:street":"Green St",
    "iso:country":"AU",
    "sg:address":"5 Green St",
    "sg:city":"Brandon",
    "sg:classifiers":[
        {
            "category":"Farming",
            "subcategory":"Farm & Veterinary Services",
            "type":"Manufacturing & Wholesale Goods"
        }
    ],
    "sg:phone":"+61 7 4782 5381",
    "sg:postcode":"4808",
    "sg:province":"QLD",
    "sg:tags":[
        "contracting"
    ],
    "wof:name":"Dennis W A & C A",
    "wof:placetype":"venue"
},
  "geometry": {"coordinates":[147.35670471200001,-19.5574645996],"type":"Point"}
}