{
  "type": "Feature",
  "properties": {
    "addr:full":"58 Park Rd Kerang VIC 3579",
    "addr:housenumber":"58",
    "addr:postcode":"3579",
    "addr:street":"Park Rd",
    "iso:country":"AU",
    "sg:address":"58 Park Rd",
    "sg:city":"Kerang",
    "sg:classifiers":[
        {
            "category":"Professional",
            "subcategory":"Art Services",
            "type":"Services"
        }
    ],
    "sg:phone":"+61 3 5450 3811",
    "sg:postcode":"3579",
    "sg:province":"VIC",
    "sg:tags":[
        "decorator",
        "painter"
    ],
    "wof:name":"Hogg Barry",
    "wof:placetype":"venue"
},
  "geometry": {"coordinates":[143.92425537099999,-35.7300338745],"type":"Point"}
}