{
  "type": "Feature",
  "properties": {
    "addr:full":"Shop 14-15 Belmont Village Shpng Cntr Belmont VIC 3216",
    "addr:housenumber":"14-15",
    "addr:postcode":"3216",
    "addr:street":"Belmont Village Shpng Cntr",
    "iso:country":"AU",
    "sg:address":"Shop 14-15 Belmont Village Shpng Cntr",
    "sg:city":"Belmont",
    "sg:classifiers":[
        {
            "category":"Communications",
            "subcategory":"Film & Video Production",
            "type":"Services"
        }
    ],
    "sg:phone":"+61 3 5241 1966",
    "sg:postcode":"3216",
    "sg:province":"VIC",
    "sg:tags":[
        "dvd",
        "library"
    ],
    "wof:name":"Video Ezy",
    "wof:placetype":"venue"
},
  "geometry": {"coordinates":[144.344436645,-38.1751899719],"type":"Point"}
}