{
  "type": "Feature",
  "properties": {
    "iso:country":"AU",
    "sg:address":"Omeo Hwy",
    "sg:city":"Bruthen",
    "sg:classifiers":[
        {
            "category":"Building & Trades",
            "subcategory":"Construction",
            "type":"Services"
        }
    ],
    "sg:phone":"+61 3 5157 5558",
    "sg:postcode":"3885",
    "sg:province":"VIC",
    "sg:tags":[
        "earth",
        "excavating",
        "moving",
        "contractor"
    ],
    "wof:name":"D.A.D. Pty Ltd",
    "wof:placetype":"venue"
},
  "geometry": {"coordinates":[147.83404540999999,-37.7066802979],"type":"Point"}
}