{
  "type": "Feature",
  "properties": {
    "addr:full":"16/ 1 Burnside Rd Yatala QLD 4207",
    "addr:housenumber":"16 / 1",
    "addr:postcode":"4207",
    "addr:street":"Burnside Rd",
    "iso:country":"AU",
    "sg:address":"16/ 1 Burnside Rd",
    "sg:city":"Yatala",
    "sg:classifiers":[
        {
            "category":"Real Estate",
            "subcategory":"Real Estate Agent",
            "type":"Services"
        }
    ],
    "sg:phone":"+61 7 5546 6483",
    "sg:postcode":"4207",
    "sg:province":"QLD",
    "wof:name":"Harcourts Commercial",
    "wof:placetype":"venue"
},
  "geometry": {"coordinates":[153.240066528,-27.7555675507],"type":"Point"}
}