{
  "type": "Feature",
  "properties": {
    "addr:full":"Unit 4 27 Anvil Rd Seven Hills NSW 2147",
    "addr:housenumber":"27",
    "addr:postcode":"2147",
    "addr:street":"Anvil Rd",
    "iso:country":"AU",
    "sg:address":"Unit 4 27 Anvil Rd",
    "sg:city":"Seven Hills",
    "sg:classifiers":[
        {
            "category":"Banks & Credit Unions",
            "subcategory":"Bureau De Change",
            "type":"Services"
        }
    ],
    "sg:phone":"+61 2 9674 5651",
    "sg:postcode":"2147",
    "sg:province":"NSW",
    "sg:tags":[
        "wheel",
        "industrial"
    ],
    "wof:name":"Circle Track Wheels",
    "wof:placetype":"venue"
},
  "geometry": {"coordinates":[150.958374023,-33.7786369324],"type":"Point"}
}