{
  "type": "Feature",
  "properties": {
    "addr:full":"Shop 12-13 Tivoli Arcade 235- 251 Bourke St Melbourne VIC 3000",
    "addr:housenumber":"12-13;235 251",
    "addr:postcode":"3000",
    "addr:street":"Tivoli Arcade;Bourke St",
    "iso:country":"AU",
    "sg:address":"Shop 12-13 Tivoli Arcade 235- 251 Bourke St",
    "sg:city":"Melbourne",
    "sg:classifiers":[
        {
            "category":"Personal",
            "subcategory":"Beauty Salon",
            "type":"Services"
        }
    ],
    "sg:phone":"+61 3 9654 5497",
    "sg:postcode":"3000",
    "sg:province":"VIC",
    "sg:tags":[
        "hairdresser"
    ],
    "wof:name":"Renaissance Hairdressing",
    "wof:placetype":"venue"
},
  "geometry": {"coordinates":[144.965942383,-37.8135566711],"type":"Point"}
}