{
  "type": "Feature",
  "properties": {
    "iso:country":"AU",
    "sg:address":"27 Moubray St",
    "sg:city":"Albert Park",
    "sg:classifiers":[
        {
            "category":"Real Estate",
            "subcategory":"Architect",
            "type":"Services"
        }
    ],
    "sg:phone":"+61 3 9699 6756",
    "sg:postcode":"3206",
    "sg:province":"VIC",
    "wof:name":"Hampton Tony",
    "wof:placetype":"venue"
},
  "geometry": {"coordinates":[144.95249899999999,-37.842873],"type":"Point"}
}