{
  "type": "Feature",
  "properties": {
    "addr:full":"7 Horsley St Kooringal NSW 2650",
    "addr:housenumber":"7",
    "addr:postcode":"2650",
    "addr:street":"Horsley St",
    "iso:country":"AU",
    "sg:address":"7 Horsley St",
    "sg:city":"Kooringal",
    "sg:classifiers":[
        {
            "category":"Education",
            "subcategory":"Music School",
            "type":"Public Place"
        }
    ],
    "sg:phone":"+61 2 6926 1593",
    "sg:postcode":"2650",
    "sg:province":"NSW",
    "sg:tags":[
        "teacher"
    ],
    "wof:name":"Manning Shirley Music Centre",
    "wof:placetype":"venue"
},
  "geometry": {"coordinates":[147.36862182600001,-35.1507072449],"type":"Point"}
}