{
  "type": "Feature",
  "properties": {
    "addr:full":"60 Fitzroy St Nanango QLD 4615",
    "addr:housenumber":"60",
    "addr:postcode":"4615",
    "addr:street":"Fitzroy St",
    "iso:country":"AU",
    "sg:address":"60 Fitzroy St",
    "sg:city":"Nanango",
    "sg:classifiers":[
        {
            "category":"Health Services",
            "subcategory":"Doctor",
            "type":"Services"
        }
    ],
    "sg:phone":"+61 7 4163 1777",
    "sg:postcode":"4615",
    "sg:province":"QLD",
    "sg:tags":[
        "medical",
        "practitioner"
    ],
    "wof:name":"Morgan Frederick",
    "wof:placetype":"venue"
},
  "geometry": {"coordinates":[152.00041198700001,-26.6694564819],"type":"Point"}
}