{
  "type": "Feature",
  "properties": {
    "addr:full":"2- 4 Bong Bong Rd Dapto NSW 2530",
    "addr:housenumber":"4",
    "addr:postcode":"2530",
    "addr:street":"Bong Bong Rd",
    "iso:country":"AU",
    "sg:address":"2- 4 Bong Bong Rd",
    "sg:city":"Dapto",
    "sg:classifiers":[
        {
            "category":"Banks & Credit Unions",
            "subcategory":"Financial Services",
            "type":"Services"
        }
    ],
    "sg:phone":"+61 2 4261 1955",
    "sg:postcode":"2530",
    "sg:province":"NSW",
    "sg:tags":[
        "building",
        "society"
    ],
    "wof:name":"IMB",
    "wof:placetype":"venue"
},
  "geometry": {"coordinates":[150.793792725,-34.4940872192],"type":"Point"}
}