{
  "type": "Feature",
  "properties": {
    "addr:full":"18 Wolverhampton St Stafford QLD 4053",
    "addr:housenumber":"18",
    "addr:postcode":"4053",
    "addr:street":"Wolverhampton St",
    "iso:country":"AU",
    "sg:address":"18 Wolverhampton St",
    "sg:city":"Stafford",
    "sg:classifiers":[
        {
            "category":"Retail",
            "subcategory":"Auto Repair",
            "type":"Services"
        }
    ],
    "sg:phone":"+61 7 3856 4605",
    "sg:postcode":"4053",
    "sg:province":"QLD",
    "sg:tags":[
        "transmission",
        "automotive",
        "car"
    ],
    "wof:name":"Swan Transmission Parts",
    "wof:placetype":"venue"
},
  "geometry": {"coordinates":[153.01455688499999,-27.4174251556],"type":"Point"}
}