{
  "type": "Feature",
  "properties": {
    "iso:country":"AU",
    "sg:address":"80 Ventura Pl",
    "sg:city":"Dandenong South",
    "sg:classifiers":[
        {
            "category":"Wholesale",
            "subcategory":"Metals & Minerals",
            "type":"Manufacturing & Wholesale Goods"
        }
    ],
    "sg:phone":"+61 3 9704 2711",
    "sg:postcode":"3175",
    "sg:province":"VIC",
    "sg:tags":[
        "steel",
        "merchant"
    ],
    "wof:name":"Reinforcement Services",
    "wof:placetype":"venue"
},
  "geometry": {"coordinates":[145.23277282699999,-38.0257072449],"type":"Point"}
}