{
  "type": "Feature",
  "properties": {
    "iso:country":"AU",
    "sg:address":"Cnr Ipswich Rd & Keats St",
    "sg:city":"Moorooka",
    "sg:classifiers":[
        {
            "category":"Autos & Motor Vehicles",
            "subcategory":"Automobile Sales",
            "type":"Retail Goods"
        }
    ],
    "sg:phone":"+61 7 3426 7222",
    "sg:postcode":"4105",
    "sg:province":"QLD",
    "sg:tags":[
        "car",
        "new"
    ],
    "wof:name":"Toyota Motorama",
    "wof:placetype":"venue"
},
  "geometry": {"coordinates":[153.01985168499999,-27.5285778046],"type":"Point"}
}