{
  "type": "Feature",
  "properties": {
    "addr:full":"Terang-Mortlake Rd Noorat VIC 3265",
    "addr:postcode":"3265",
    "addr:street":"Terang-Mortlake Rd",
    "iso:country":"AU",
    "sg:address":"Terang-Mortlake Rd",
    "sg:city":"Noorat",
    "sg:classifiers":[
        {
            "category":"Social Services",
            "subcategory":"Child Care",
            "type":"Services"
        }
    ],
    "sg:phone":"+61 3 5592 5461",
    "sg:postcode":"3265",
    "sg:province":"VIC",
    "sg:tags":[
        "breeding",
        "artificial"
    ],
    "wof:name":"Nationwide Artificial Breeders",
    "wof:placetype":"venue"
},
  "geometry": {"coordinates":[142.92750549300001,-38.1913795471],"type":"Point"}
}