{
  "type": "Feature",
  "properties": {
    "iso:country":"AU",
    "sg:address":"31 Lady Penrhyn Drv",
    "sg:city":"Beacon Hill",
    "sg:classifiers":[
        {
            "category":"Social Services",
            "subcategory":"Retirement Home",
            "type":"Services"
        }
    ],
    "sg:phone":"+61 2 9453 5928",
    "sg:postcode":"2100",
    "sg:province":"NSW",
    "sg:tags":[
        "environmental",
        "consultant",
        "pollution"
    ],
    "wof:name":"AEBN Pty Ltd",
    "wof:placetype":"venue"
},
  "geometry": {"coordinates":[151.25912475600001,-33.7437438965],"type":"Point"}
}