{
  "type": "Feature",
  "properties": {
    "addr:full":"Unit 2, 23- 25 Springvale Rd Springvale VIC 3171",
    "addr:housenumber":"23 25",
    "addr:postcode":"3171",
    "addr:street":"Springvale Rd",
    "iso:country":"AU",
    "sg:address":"Unit 2, 23- 25 Springvale Rd",
    "sg:city":"Springvale",
    "sg:classifiers":[
        {
            "category":"Fast Food",
            "type":"Food & Drink"
        }
    ],
    "sg:phone":"+61 3 9548 4899",
    "sg:postcode":"3171",
    "sg:province":"VIC",
    "sg:tags":[
        "away",
        "take"
    ],
    "wof:name":"Nando's Flame Grilled Chicken",
    "wof:placetype":"venue"
},
  "geometry": {"coordinates":[145.15565490700001,-37.9350852966],"type":"Point"}
}