{
  "type": "Feature",
  "properties": {
    "addr:full":"21 Montana St Glen Iris VIC 3146",
    "addr:housenumber":"21",
    "addr:postcode":"3146",
    "addr:street":"Montana St",
    "iso:country":"AU",
    "sg:address":"21 Montana St",
    "sg:city":"Glen Iris",
    "sg:classifiers":[
        {
            "category":"Building & Trades",
            "subcategory":"Plumbing",
            "type":"Services"
        }
    ],
    "sg:phone":"+61 3 9889 2964",
    "sg:postcode":"3146",
    "sg:province":"VIC",
    "sg:tags":[
        "plumber",
        "gasfitters"
    ],
    "wof:name":"Acclaim Drain Services",
    "wof:placetype":"venue"
},
  "geometry": {"coordinates":[145.08152770999999,-37.8575897217],"type":"Point"}
}