{
  "type": "Feature",
  "properties": {
    "addr:full":"100 Miller St North Sydney NSW 2060",
    "addr:housenumber":"100",
    "addr:postcode":"2060",
    "addr:street":"Miller St",
    "iso:country":"AU",
    "sg:address":"100 Miller St",
    "sg:city":"North Sydney",
    "sg:classifiers":[
        {
            "category":"Real Estate",
            "subcategory":"Real Estate Agent",
            "type":"Services"
        }
    ],
    "sg:phone":"+61 2 9936 5888",
    "sg:postcode":"2060",
    "sg:province":"NSW",
    "wof:name":"Jones Lang LaSalle",
    "wof:placetype":"venue"
},
  "geometry": {"coordinates":[151.206954956,-33.8375396729],"type":"Point"}
}