{
  "type": "Feature",
  "properties": {
    "addr:full":"99 Commercial St Korumburra VIC 3950",
    "addr:housenumber":"99",
    "addr:postcode":"3950",
    "addr:street":"Commercial St",
    "iso:country":"AU",
    "sg:address":"99 Commercial St",
    "sg:city":"Korumburra",
    "sg:classifiers":[
        {
            "category":"Food & Beverages",
            "subcategory":"Groceries & Convenience Stores",
            "type":"Retail Goods"
        }
    ],
    "sg:phone":"+61 3 5655 1341",
    "sg:postcode":"3950",
    "sg:province":"VIC",
    "wof:name":"Wardles Milk Bar",
    "wof:placetype":"venue"
},
  "geometry": {"coordinates":[145.82281494099999,-38.4323501587],"type":"Point"}
}