{
  "type": "Feature",
  "properties": {
    "addr:full":"19- 21 Balaclava St Woolloongabba QLD 4102",
    "addr:housenumber":"21",
    "addr:postcode":"4102",
    "addr:street":"Balaclava St",
    "iso:country":"AU",
    "sg:address":"19- 21 Balaclava St",
    "sg:city":"Woolloongabba",
    "sg:classifiers":[
        {
            "category":"Autos & Motor Vehicles",
            "subcategory":"Automobile Sales",
            "type":"Retail Goods"
        }
    ],
    "sg:phone":"+61 7 3391 6055",
    "sg:postcode":"4102",
    "sg:province":"QLD",
    "sg:tags":[
        "car",
        "new"
    ],
    "wof:name":"John French Motors",
    "wof:placetype":"venue"
},
  "geometry": {"coordinates":[153.03741455100001,-27.4902801514],"type":"Point"}
}