{
  "type": "Feature",
  "properties": {
    "addr:full":"114-116 Bell St Preston VIC 3072",
    "addr:postcode":"3072",
    "addr:street":"Bell St",
    "iso:country":"AU",
    "sg:address":"114-116 Bell St",
    "sg:city":"Preston",
    "sg:classifiers":[
        {
            "category":"Autos & Motor Vehicles",
            "subcategory":"Automobile Sales",
            "type":"Retail Goods"
        }
    ],
    "sg:phone":"+61 3 9480 3555",
    "sg:postcode":"3072",
    "sg:province":"VIC",
    "sg:tags":[
        "car",
        "new"
    ],
    "wof:name":"Max Kirwan",
    "wof:placetype":"venue"
},
  "geometry": {"coordinates":[145.02340698200001,-37.7472915649],"type":"Point"}
}