{
  "type": "Feature",
  "properties": {
    "addr:full":"76 York St Launceston TAS 7250",
    "addr:housenumber":"76",
    "addr:postcode":"7250",
    "addr:street":"York St",
    "iso:country":"AU",
    "sg:address":"76 York St",
    "sg:city":"Launceston",
    "sg:classifiers":[
        {
            "category":"Banks & Credit Unions",
            "subcategory":"Bank",
            "type":"Services"
        }
    ],
    "sg:phone":"+61 3 6334 2381",
    "sg:postcode":"7250",
    "sg:province":"TAS",
    "wof:name":"Primary Industry Bank Of Australia",
    "wof:placetype":"venue"
},
  "geometry": {"coordinates":[147.14187622099999,-41.4371261597],"type":"Point"}
}