{
  "type": "Feature",
  "properties": {
    "addr:full":"Unit 2, 42 Kay St Traralgon VIC 3844",
    "addr:housenumber":"42",
    "addr:postcode":"3844",
    "addr:street":"Kay St",
    "iso:country":"AU",
    "sg:address":"Unit 2, 42 Kay St",
    "sg:city":"Traralgon",
    "sg:classifiers":[
        {
            "category":"Personal",
            "subcategory":"Hair Removal",
            "type":"Services"
        }
    ],
    "sg:phone":"+61 3 5174 5177",
    "sg:postcode":"3844",
    "sg:province":"VIC",
    "wof:name":"Traralgon Beauty Salon",
    "wof:placetype":"venue"
},
  "geometry": {"coordinates":[146.533203125,-38.1937866211],"type":"Point"}
}