{
  "type": "Feature",
  "properties": {
    "addr:full":"2 Persic St Belfield NSW 2191",
    "addr:housenumber":"2",
    "addr:postcode":"2191",
    "addr:street":"Persic St",
    "iso:country":"AU",
    "sg:address":"2 Persic St",
    "sg:city":"Belfield",
    "sg:classifiers":[
        {
            "category":"Shopping",
            "subcategory":"Stationery & Office Supplies",
            "type":"Retail Goods"
        }
    ],
    "sg:phone":"+61 2 9742 5862",
    "sg:postcode":"2191",
    "sg:province":"NSW",
    "sg:tags":[
        "stocktaker"
    ],
    "wof:name":"Conroy R J Pty Ltd",
    "wof:placetype":"venue"
},
  "geometry": {"coordinates":[151.08216899999999,-33.906788],"type":"Point"}
}