{
  "type": "Feature",
  "properties": {
    "iso:country":"AU",
    "sg:address":"241 Marrickville Rd",
    "sg:city":"Marrickville",
    "sg:classifiers":[
        {
            "category":"Banks & Credit Unions",
            "subcategory":"Bank",
            "type":"Services"
        }
    ],
    "sg:phone":"+61 13 20 32",
    "sg:postcode":"2204",
    "sg:province":"NSW",
    "wof:name":"Westpac",
    "wof:placetype":"venue"
},
  "geometry": {"coordinates":[151.156631,-33.910484],"type":"Point"}
}