{
  "type": "Feature",
  "properties": {
    "iso:country":"AU",
    "sg:address":"2/ 48 Vinnicombe Drv",
    "sg:city":"Canning Vale",
    "sg:classifiers":[
        {
            "category":"Education",
            "subcategory":"Dance Studio",
            "type":"Public Place"
        }
    ],
    "sg:phone":"+61 1300 883 601",
    "sg:postcode":"6155",
    "sg:province":"WA",
    "sg:tags":[
        "venue",
        "tuition"
    ],
    "wof:name":"Just Jazz Talent Company",
    "wof:placetype":"venue"
},
  "geometry": {"coordinates":[115.916039,-32.058914],"type":"Point"}
}