{
  "type": "Feature",
  "properties": {
    "addr:full":"28 Tuaggra St Maryborough VIC 3465",
    "addr:housenumber":"28",
    "addr:postcode":"3465",
    "addr:street":"Tuaggra St",
    "iso:country":"AU",
    "sg:address":"28 Tuaggra St",
    "sg:city":"Maryborough",
    "sg:classifiers":[
        {
            "category":"Communications",
            "subcategory":"Film & Video Production",
            "type":"Services"
        }
    ],
    "sg:phone":"+61 3 5461 4344",
    "sg:postcode":"3465",
    "sg:province":"VIC",
    "sg:tags":[
        "dvd",
        "library"
    ],
    "wof:name":"Family Videoland",
    "wof:placetype":"venue"
},
  "geometry": {"coordinates":[143.74148559599999,-37.0473976135],"type":"Point"}
}