{
  "type": "Feature",
  "properties": {
    "iso:country":"AU",
    "sg:address":"PO Box 318",
    "sg:city":"Annandale",
    "sg:classifiers":[
        {
            "category":"Retail",
            "subcategory":"Repair Shop",
            "type":"Services"
        }
    ],
    "sg:phone":"+61 2 9819 6173",
    "sg:postcode":"2038",
    "sg:province":"NSW",
    "sg:tags":[
        "upholsterer"
    ],
    "wof:name":"Stokes Furniture Restoration Pty Ltd",
    "wof:placetype":"venue"
},
  "geometry": {"coordinates":[151.169723511,-33.8796691895],"type":"Point"}
}