{
  "type": "Feature",
  "properties": {
    "iso:country":"AU",
    "sg:address":"Shop 20 Casuarina Village Bradshaw Tce",
    "sg:city":"Nakara",
    "sg:classifiers":[
        {
            "category":"Sports & Exercise",
            "subcategory":"Gym",
            "type":"Entertainment"
        }
    ],
    "sg:phone":"+61 8 8945 4062",
    "sg:postcode":"0810",
    "sg:province":"NT",
    "sg:tags":[
        "health",
        "fitness"
    ],
    "wof:name":"Ruis Gym",
    "wof:placetype":"venue"
},
  "geometry": {"coordinates":[130.88015747099999,-12.3725299835],"type":"Point"}
}