{
  "type": "Feature",
  "properties": {
    "addr:full":"267 Station St Edithvale VIC 3196",
    "addr:housenumber":"267",
    "addr:postcode":"3196",
    "addr:street":"Station St",
    "iso:country":"AU",
    "sg:address":"267 Station St",
    "sg:city":"Edithvale",
    "sg:classifiers":[
        {
            "category":"Health Services",
            "subcategory":"Doctor",
            "type":"Services"
        }
    ],
    "sg:phone":"+61 3 9773 1001",
    "sg:postcode":"3196",
    "sg:province":"VIC",
    "sg:tags":[
        "medical",
        "practitioner"
    ],
    "wof:name":"McBeth Kathleen Dr",
    "wof:placetype":"venue"
},
  "geometry": {"coordinates":[145.112625122,-38.0443725586],"type":"Point"}
}