{
  "type": "Feature",
  "properties": {
    "addr:full":"49 Medbury Ave Greensborough VIC 3088",
    "addr:housenumber":"49",
    "addr:postcode":"3088",
    "addr:street":"Medbury Ave",
    "iso:country":"AU",
    "sg:address":"49 Medbury Ave",
    "sg:city":"Greensborough",
    "sg:classifiers":[
        {
            "category":"Personal",
            "subcategory":"Beauty Salon",
            "type":"Services"
        }
    ],
    "sg:phone":"+61 3 9444 6139",
    "sg:postcode":"3088",
    "sg:province":"VIC",
    "wof:name":"1-2-1 Beauty Salon",
    "wof:placetype":"venue"
},
  "geometry": {"coordinates":[145.097045898,-37.7095375061],"type":"Point"}
}