{
  "type": "Feature",
  "properties": {
    "addr:full":"University Hill Town Centre Shop 5, 224 Plenty Rd Bundoora VIC 3083",
    "addr:housenumber":"shop 5 224",
    "addr:postcode":"3083",
    "addr:street":"Plenty Rd",
    "iso:country":"AU",
    "sg:address":"University Hill Town Centre Shop 5, 224 Plenty Rd",
    "sg:city":"Bundoora",
    "sg:classifiers":[
        {
            "category":"Health Services",
            "subcategory":"Optometrist",
            "type":"Services"
        }
    ],
    "sg:phone":"+61 3 9467 7580",
    "sg:postcode":"3083",
    "sg:province":"VIC",
    "wof:name":"University Hill Eyecare Plus",
    "wof:placetype":"venue"
},
  "geometry": {"coordinates":[145.069824219,-37.6787261963],"type":"Point"}
}