{
  "type": "Feature",
  "properties": {
    "iso:country":"AU",
    "sg:address":"Ste6/ 100 Mill Point Rd",
    "sg:city":"South Perth",
    "sg:classifiers":[
        {
            "category":"Organizations",
            "subcategory":"Professional Association",
            "type":"Services"
        }
    ],
    "sg:phone":"+61 8 9474 3366",
    "sg:postcode":"6151",
    "sg:province":"WA",
    "sg:tags":[
        "web",
        "internet"
    ],
    "wof:name":"Positionmeonline",
    "wof:placetype":"venue"
},
  "geometry": {"coordinates":[115.851738,-31.97279],"type":"Point"}
}