{
  "type": "Feature",
  "properties": {
    "iso:country":"AU",
    "sg:address":"Unit 1/ 460 Canning Hwy",
    "sg:city":"Como",
    "sg:classifiers":[
        {
            "category":"Sports & Exercise",
            "subcategory":"Gym",
            "type":"Entertainment"
        }
    ],
    "sg:phone":"+61 8 9450 8888",
    "sg:postcode":"6152",
    "sg:province":"WA",
    "sg:tags":[
        "health",
        "fitness"
    ],
    "wof:name":"Como Health & Fitness Centre",
    "wof:placetype":"venue"
},
  "geometry": {"coordinates":[115.859962,-32.005386],"type":"Point"}
}