{
  "type": "Feature",
  "properties": {
    "iso:country":"AU",
    "sg:address":"15 Andrew Ave",
    "sg:city":"Pottsville",
    "sg:classifiers":[
        {
            "category":"Building & Trades",
            "subcategory":"Plumbing",
            "type":"Services"
        }
    ],
    "sg:phone":"+61 2 6676 2304",
    "sg:postcode":"2489",
    "sg:province":"NSW",
    "sg:tags":[
        "plumber",
        "gasfitters"
    ],
    "wof:name":"Peter Loxley-Lewis Plumbing",
    "wof:placetype":"venue"
},
  "geometry": {"coordinates":[153.558837891,-28.3960933685],"type":"Point"}
}