{
  "type": "Feature",
  "properties": {
    "addr:full":"8 Balfour Rd Kensington NSW 2033",
    "addr:housenumber":"8",
    "addr:postcode":"2033",
    "addr:street":"Balfour Rd",
    "iso:country":"AU",
    "sg:address":"8 Balfour Rd",
    "sg:city":"Kensington",
    "sg:classifiers":[
        {
            "category":"Building & Trades",
            "subcategory":"Construction",
            "type":"Services"
        }
    ],
    "sg:phone":"+61 2 9663 1052",
    "sg:postcode":"2033",
    "sg:province":"NSW",
    "sg:tags":[
        "contractor"
    ],
    "wof:name":"G N E Building Service",
    "wof:placetype":"venue"
},
  "geometry": {"coordinates":[151.219559,-33.910027],"type":"Point"}
}