{
  "type": "Feature",
  "properties": {
    "addr:full":"Unit 24 / 2 - 4 Damian Crt Dandenong VIC 3175",
    "addr:housenumber":"/ 2 4",
    "addr:postcode":"3175",
    "addr:street":"Damian Crt",
    "iso:country":"AU",
    "sg:address":"Unit 24 / 2 - 4 Damian Crt",
    "sg:city":"Dandenong",
    "sg:classifiers":[
        {
            "category":"Professional",
            "subcategory":"Printing & Photocopies",
            "type":"Services"
        }
    ],
    "sg:phone":"+61 3 9793 7707",
    "sg:postcode":"3175",
    "sg:province":"VIC",
    "sg:tags":[
        "photocopying"
    ],
    "wof:name":"Copi-Image Aust P/L",
    "wof:placetype":"venue"
},
  "geometry": {"coordinates":[145.203781128,-37.9871826172],"type":"Point"}
}