{
  "type": "Feature",
  "properties": {
    "iso:country":"AU",
    "sg:address":"8 / 28 Barcoo St",
    "sg:city":"Roseville",
    "sg:classifiers":[
        {
            "category":"Wholesale",
            "subcategory":"Medical Equipment & Supplies",
            "type":"Manufacturing & Wholesale Goods"
        }
    ],
    "sg:phone":"+61 1800 158 676",
    "sg:postcode":"2069",
    "sg:province":"NSW",
    "sg:tags":[
        "aid",
        "care",
        "health",
        "home"
    ],
    "wof:name":"Acorn Stairlifts",
    "wof:placetype":"venue"
},
  "geometry": {"coordinates":[151.19497680699999,-33.7849273682],"type":"Point"}
}