{
  "type": "Feature",
  "properties": {
    "addr:full":"Level 11/ 46 Edward St Brisbane QLD 4000",
    "addr:housenumber":"/ 46",
    "addr:postcode":"4000",
    "addr:street":"Edward St",
    "iso:country":"AU",
    "sg:address":"Level 11/ 46 Edward St",
    "sg:city":"Brisbane",
    "sg:classifiers":[
        {
            "category":"Real Estate",
            "subcategory":"Architect",
            "type":"Services"
        }
    ],
    "sg:phone":"+61 7 3012 9522",
    "sg:postcode":"4000",
    "sg:province":"QLD",
    "wof:name":"Dimitriou Architects & Interior Designers",
    "wof:placetype":"venue"
},
  "geometry": {"coordinates":[153.02961730999999,-27.4712600708],"type":"Point"}
}