{
  "type": "Feature",
  "properties": {
    "addr:full":"Unit 1/ 15 Westgate St Wacol QLD 4076",
    "addr:postcode":"4076",
    "addr:street":"Westgate St",
    "iso:country":"AU",
    "sg:address":"Unit 1/ 15 Westgate St",
    "sg:city":"Wacol",
    "sg:classifiers":[
        {
            "category":"Wholesale",
            "subcategory":"Machinery & Supplies",
            "type":"Manufacturing & Wholesale Goods"
        }
    ],
    "sg:phone":"+61 1300 728 720",
    "sg:postcode":"4076",
    "sg:province":"QLD",
    "sg:tags":[
        "equipment",
        "welding"
    ],
    "wof:name":"Lincoln Electric Co. (Aust.) Pty Ltd",
    "wof:placetype":"venue"
},
  "geometry": {"coordinates":[152.93357849099999,-27.5903301239],"type":"Point"}
}