{
  "type": "Feature",
  "properties": {
    "addr:full":"44 Sundew St Mjmba Bh Mudjimba Beach QLD 4564",
    "addr:housenumber":"44;mudjimba",
    "addr:postcode":"4564",
    "addr:street":"Sundew St Mjmba",
    "iso:country":"AU",
    "sg:address":"44 Sundew St",
    "sg:city":"Mjmba Bh Mudjimba Beach",
    "sg:classifiers":[
        {
            "category":"Building & Trades",
            "subcategory":"Construction",
            "type":"Services"
        }
    ],
    "sg:phone":"+61 7 5448 7593",
    "sg:postcode":"4564",
    "sg:province":"QLD",
    "sg:tags":[
        "contractor"
    ],
    "wof:name":"Conran S & D",
    "wof:placetype":"venue"
},
  "geometry": {"coordinates":[153.085647583,-26.6150798798],"type":"Point"}
}