{
  "type": "Feature",
  "properties": {
    "addr:full":"Factory 5 16-20 Amcor Way Campbellfield VIC 3061",
    "addr:housenumber":"5 16-20",
    "addr:postcode":"3061",
    "addr:street":"Amcor Way",
    "iso:country":"AU",
    "sg:address":"Factory 5 16-20 Amcor Way",
    "sg:city":"Campbellfield",
    "sg:classifiers":[
        {
            "category":"Professional",
            "subcategory":"Engineering",
            "type":"Services"
        }
    ],
    "sg:phone":"+61 3 9357 0561",
    "sg:postcode":"3061",
    "sg:province":"VIC",
    "sg:tags":[
        "manufacturing",
        "engineer"
    ],
    "wof:name":"Edenvale Engineering Pty Ltd",
    "wof:placetype":"venue"
},
  "geometry": {"coordinates":[144.95899963400001,-37.6562919617],"type":"Point"}
}