{
  "type": "Feature",
  "properties": {
    "addr:full":"56-58 Junction St Nowra NSW 2541",
    "addr:housenumber":"56-58",
    "addr:postcode":"2541",
    "addr:street":"Junction St",
    "iso:country":"AU",
    "sg:address":"56-58 Junction St",
    "sg:city":"Nowra",
    "sg:classifiers":[
        {
            "category":"Wholesale",
            "subcategory":"Stationery",
            "type":"Manufacturing & Wholesale Goods"
        }
    ],
    "sg:phone":"+61 2 4421 5466",
    "sg:postcode":"2541",
    "sg:province":"NSW",
    "sg:tags":[
        "mfrg"
    ],
    "wof:name":"Shoalhaven Commercial Printers Pty Ltd",
    "wof:placetype":"venue"
},
  "geometry": {"coordinates":[150.59974670400001,-34.8742790222],"type":"Point"}
}