{
  "type": "Feature",
  "properties": {
    "iso:country":"AU",
    "sg:address":"PO Box 945",
    "sg:city":"Victor Harbor",
    "sg:classifiers":[
        {
            "category":"Building & Trades",
            "subcategory":"Plumbing",
            "type":"Services"
        }
    ],
    "sg:phone":"+61 417 807 813",
    "sg:postcode":"5211",
    "sg:province":"SA",
    "sg:tags":[
        "plumber",
        "gasfitters"
    ],
    "wof:name":"Ebes Plumbing & Gasfitting",
    "wof:placetype":"venue"
},
  "geometry": {"coordinates":[138.624435425,-35.5497398376],"type":"Point"}
}