{
  "type": "Feature",
  "properties": {
    "addr:full":"21 Bentley St Wetherill Park NSW 2164",
    "addr:housenumber":"21",
    "addr:postcode":"2164",
    "addr:street":"Bentley St",
    "iso:country":"AU",
    "sg:address":"21 Bentley St",
    "sg:city":"Wetherill Park",
    "sg:classifiers":[
        {
            "category":"Autos & Motor Vehicles",
            "subcategory":"Auto Supplies",
            "type":"Retail Goods"
        }
    ],
    "sg:phone":"+61 1300 303 741",
    "sg:postcode":"2164",
    "sg:province":"NSW",
    "sg:tags":[
        "accessory"
    ],
    "wof:name":"BMG Holdings Pty. Ltd.",
    "wof:placetype":"venue"
},
  "geometry": {"coordinates":[150.883422852,-33.8463249207],"type":"Point"}
}