{
  "type": "Feature",
  "properties": {
    "addr:full":"22a Healey Rd Dandenong VIC 3175",
    "addr:housenumber":"22a",
    "addr:postcode":"3175",
    "addr:street":"Healey Rd",
    "iso:country":"AU",
    "sg:address":"22a Healey Rd",
    "sg:city":"Dandenong",
    "sg:classifiers":[
        {
            "category":"Professional",
            "type":"Services"
        }
    ],
    "sg:phone":"+61 3 9768 3221",
    "sg:postcode":"3175",
    "sg:province":"VIC",
    "sg:tags":[
        "transport"
    ],
    "wof:name":"Dusting J R & M L P/L",
    "wof:placetype":"venue"
},
  "geometry": {"coordinates":[145.22108459500001,-38.0298309326],"type":"Point"}
}