{
  "type": "Feature",
  "properties": {
    "iso:country":"AU",
    "sg:address":"109 Powderworks Rd",
    "sg:city":"Elanora Heights",
    "sg:classifiers":[
        {
            "category":"Professional",
            "subcategory":"Business Services",
            "type":"Services"
        }
    ],
    "sg:phone":"+61 2 9970 5235",
    "sg:postcode":"2101",
    "sg:province":"NSW",
    "sg:tags":[
        "exporter"
    ],
    "wof:name":"Vita Fresh",
    "wof:placetype":"venue"
},
  "geometry": {"coordinates":[151.286652,-33.697296],"type":"Point"}
}