{
  "type": "Feature",
  "properties": {
    "addr:full":"7/ 9 Campbell St Singleton NSW 2330",
    "addr:housenumber":"/ 9",
    "addr:postcode":"2330",
    "addr:street":"Campbell St",
    "iso:country":"AU",
    "sg:address":"7/ 9 Campbell St",
    "sg:city":"Singleton",
    "sg:classifiers":[
        {
            "category":"Autos & Motor Vehicles",
            "subcategory":"Auto Supplies",
            "type":"Retail Goods"
        }
    ],
    "sg:phone":"+61 2 6572 2177",
    "sg:postcode":"2330",
    "sg:province":"NSW",
    "sg:tags":[
        "tyre"
    ],
    "wof:name":"Yokohama",
    "wof:placetype":"venue"
},
  "geometry": {"coordinates":[151.17283599999999,-32.560986],"type":"Point"}
}