{
  "type": "Feature",
  "properties": {
    "iso:country":"AU",
    "sg:address":"PO Box 1",
    "sg:city":"James Cook University",
    "sg:classifiers":[
        {
            "category":"Education",
            "subcategory":"Kindergarten",
            "type":"Public Place"
        }
    ],
    "sg:phone":"+61 7 4781 5934",
    "sg:postcode":"4811",
    "sg:province":"QLD",
    "sg:tags":[
        "pre-schools"
    ],
    "wof:name":"JCU Student Association Child Care Centre",
    "wof:placetype":"venue"
},
  "geometry": {"coordinates":[146.81167600000001,-19.317719],"type":"Point"}
}