{
  "type": "Feature",
  "properties": {
    "addr:full":"Shed 8 Lester St Bundaberg QLD 4670",
    "addr:housenumber":"8",
    "addr:postcode":"4670",
    "addr:street":"Lester St",
    "iso:country":"AU",
    "sg:address":"Shed 8 Lester St",
    "sg:city":"Bundaberg",
    "sg:classifiers":[
        {
            "category":"Manufacturing",
            "subcategory":"Motor Vehicles & Parts",
            "type":"Manufacturing & Wholesale Goods"
        }
    ],
    "sg:phone":"+61 7 4151 7420",
    "sg:postcode":"4670",
    "sg:province":"QLD",
    "sg:tags":[
        "engine",
        "equipment",
        "diesel"
    ],
    "wof:name":"CQ Diesel Spares Pty Ltd",
    "wof:placetype":"venue"
},
  "geometry": {"coordinates":[152.351272583,-24.8910713196],"type":"Point"}
}