{
  "type": "Feature",
  "properties": {
    "iso:country":"AU",
    "sg:address":"283 Church St",
    "sg:city":"Parramatta",
    "sg:classifiers":[
        {
            "category":"Insurance",
            "subcategory":"Health Insurance",
            "type":"Services"
        }
    ],
    "sg:phone":"+61 13 13 72",
    "sg:postcode":"2150",
    "sg:province":"NSW",
    "wof:name":"Manchester Unity",
    "wof:placetype":"venue"
},
  "geometry": {"coordinates":[151.003662109,-33.812286377],"type":"Point"}
}