{
  "type": "Feature",
  "properties": {
    "iso:country":"AU",
    "sg:address":"Equilibrium 5 Boolwey Street",
    "sg:city":"Bowral",
    "sg:classifiers":[
        {
            "category":"Health Services",
            "subcategory":"Health Practitioner",
            "type":"Services"
        }
    ],
    "sg:phone":"+61 402 916 291",
    "sg:postcode":"2576",
    "sg:province":"NSW",
    "sg:tags":[
        "alternative"
    ],
    "wof:name":"Nina Eagle",
    "wof:placetype":"venue"
},
  "geometry": {"coordinates":[150.41659545900001,-34.4801826477],"type":"Point"}
}