{
  "type": "Feature",
  "properties": {
    "iso:country":"AU",
    "sg:address":"5th Floor, South Shore Piazza, 85 The Esplanade",
    "sg:city":"South Perth",
    "sg:classifiers":[
        {
            "category":"Bars & Pubs",
            "subcategory":"Nightclub",
            "type":"Food & Drink"
        }
    ],
    "sg:phone":"+61 8 9367 9111",
    "sg:postcode":"6151",
    "sg:province":"WA",
    "sg:tags":[
        "discotheque"
    ],
    "wof:name":"Entertainment Enterprises Pty Ltd",
    "wof:placetype":"venue"
},
  "geometry": {"coordinates":[115.850197,-32.012627],"type":"Point"}
}