{
  "type": "Feature",
  "properties": {
    "addr:full":"41-43 High St Terang VIC 3264",
    "addr:housenumber":"41-43",
    "addr:postcode":"3264",
    "addr:street":"High St",
    "iso:country":"AU",
    "sg:address":"41-43 High St",
    "sg:city":"Terang",
    "sg:classifiers":[
        {
            "category":"Manufacturing",
            "subcategory":"Motor Vehicles & Parts",
            "type":"Manufacturing & Wholesale Goods"
        }
    ],
    "sg:phone":"+61 3 5592 2480",
    "sg:postcode":"3264",
    "sg:province":"VIC",
    "sg:tags":[
        "replacement"
    ],
    "wof:name":"Centrewest",
    "wof:placetype":"venue"
},
  "geometry": {"coordinates":[142.920318603,-38.2409172058],"type":"Point"}
}