{
  "type": "Feature",
  "properties": {
    "iso:country":"AU",
    "sg:address":"100 Boundary St",
    "sg:city":"Roseville",
    "sg:classifiers":[
        {
            "category":"Professional",
            "subcategory":"Art Services",
            "type":"Services"
        }
    ],
    "sg:phone":"+61 2 9417 8066",
    "sg:postcode":"2069",
    "sg:province":"NSW",
    "sg:tags":[
        "interior",
        "decorator"
    ],
    "wof:name":"Troppo Design",
    "wof:placetype":"venue"
},
  "geometry": {"coordinates":[151.180374145,-33.7872200012],"type":"Point"}
}