{
  "type": "Feature",
  "properties": {
    "addr:full":"14 Hunter Rd Camberwell VIC 3124",
    "addr:housenumber":"14",
    "addr:postcode":"3124",
    "addr:street":"Hunter Rd",
    "iso:country":"AU",
    "sg:address":"14 Hunter Rd",
    "sg:city":"Camberwell",
    "sg:classifiers":[
        {
            "category":"Social Services",
            "subcategory":"Retirement Home",
            "type":"Services"
        }
    ],
    "sg:phone":"+61 1800 550 550",
    "sg:postcode":"3124",
    "sg:province":"VIC",
    "sg:tags":[
        "village"
    ],
    "wof:name":"Meadowvale Retirement Living",
    "wof:placetype":"venue"
},
  "geometry": {"coordinates":[145.08287048299999,-37.8376464844],"type":"Point"}
}