{
  "type": "Feature",
  "properties": {
    "addr:full":"PO Box 461 Capel WA 6271",
    "addr:postcode":"6271",
    "iso:country":"AU",
    "sg:address":"PO Box 461",
    "sg:city":"Capel",
    "sg:classifiers":[
        {
            "category":"Professional",
            "subcategory":"Engineering",
            "type":"Services"
        }
    ],
    "sg:phone":"+61 8 9727 2511",
    "sg:postcode":"6271",
    "sg:province":"WA",
    "sg:tags":[
        "engineer"
    ],
    "wof:name":"C C H Constructions",
    "wof:placetype":"venue"
},
  "geometry": {"coordinates":[115.55467224100001,-33.5524711609],"type":"Point"}
}