{
  "type": "Feature",
  "properties": {
    "iso:country":"AU",
    "sg:address":"Unit 4/ 579 Kessels Rd",
    "sg:city":"MacGregor",
    "sg:classifiers":[
        {
            "category":"Communications",
            "subcategory":"Film & Video Production",
            "type":"Services"
        }
    ],
    "sg:phone":"+61 7 3849 7411",
    "sg:postcode":"4109",
    "sg:province":"QLD",
    "sg:tags":[
        "fan",
        "blower"
    ],
    "wof:name":"Ziehl-EBM Australia Pty Ltd",
    "wof:placetype":"venue"
},
  "geometry": {"coordinates":[153.07232665999999,-27.5620536804],"type":"Point"}
}