{
  "type": "Feature",
  "properties": {
    "iso:country":"AU",
    "sg:address":"120 Fitzroy St",
    "sg:city":"Dubbo",
    "sg:classifiers":[
        {
            "category":"Building & Trades",
            "subcategory":"Cleaning & Sanitation",
            "type":"Services"
        }
    ],
    "sg:phone":"+61 402 987 290",
    "sg:postcode":"2830",
    "sg:province":"NSW",
    "sg:tags":[
        "abrasive",
        "blasting"
    ],
    "wof:name":"Orana Sand Blasting",
    "wof:placetype":"venue"
},
  "geometry": {"coordinates":[148.613479614,-32.2498245239],"type":"Point"}
}