{
  "type": "Feature",
  "properties": {
    "addr:full":"806 Pascoe Vale Rd Glenroy VIC 3046",
    "addr:housenumber":"806",
    "addr:postcode":"3046",
    "addr:street":"Pascoe Vale Rd",
    "iso:country":"AU",
    "sg:address":"806 Pascoe Vale Rd",
    "sg:city":"Glenroy",
    "sg:classifiers":[
        {
            "category":"Travel",
            "subcategory":"Travel Agent",
            "type":"Entertainment"
        }
    ],
    "sg:phone":"+61 3 9306 2844",
    "sg:postcode":"3046",
    "sg:province":"VIC",
    "sg:tags":[
        "consultant"
    ],
    "wof:name":"Trident Travel",
    "wof:placetype":"venue"
},
  "geometry": {"coordinates":[144.91603088400001,-37.7051124573],"type":"Point"}
}