{
  "type": "Feature",
  "properties": {
    "addr:full":"49 Parnell Rd Tomerong NSW 2540",
    "addr:housenumber":"49",
    "addr:postcode":"2540",
    "addr:street":"Parnell Rd",
    "iso:country":"AU",
    "sg:address":"49 Parnell Rd",
    "sg:city":"Tomerong",
    "sg:classifiers":[
        {
            "category":"Shopping",
            "subcategory":"Clothing, Apparel, & Fashions",
            "type":"Retail Goods"
        }
    ],
    "sg:phone":"+61 2 4443 4884",
    "sg:postcode":"2540",
    "sg:province":"NSW",
    "sg:tags":[
        "accessory"
    ],
    "wof:name":"Bradford Potter Pty Ltd",
    "wof:placetype":"venue"
},
  "geometry": {"coordinates":[150.60420227,-35.0554275513],"type":"Point"}
}