{
  "type": "Feature",
  "properties": {
    "iso:country":"AU",
    "sg:address":"78 Shenstone Rd",
    "sg:city":"Riverwood",
    "sg:classifiers":[
        {
            "category":"Wholesale",
            "subcategory":"Auto Parts",
            "type":"Manufacturing & Wholesale Goods"
        }
    ],
    "sg:phone":"+61 2 9596 1561",
    "sg:postcode":"2210",
    "sg:province":"NSW",
    "sg:tags":[
        "recyclers"
    ],
    "wof:name":"Sydney Scrap Cars",
    "wof:placetype":"venue"
},
  "geometry": {"coordinates":[151.045074,-33.954338],"type":"Point"}
}