{
  "type": "Feature",
  "properties": {
    "addr:full":"21 Wolseley Rd Blackwood SA 5051",
    "addr:housenumber":"21",
    "addr:postcode":"5051",
    "addr:street":"Wolseley Rd",
    "iso:country":"AU",
    "sg:address":"21 Wolseley Rd",
    "sg:city":"Blackwood",
    "sg:classifiers":[
        {
            "category":"Health Services",
            "subcategory":"Health Practitioner",
            "type":"Services"
        }
    ],
    "sg:phone":"+61 414 462 759",
    "sg:postcode":"5051",
    "sg:province":"SA",
    "sg:tags":[
        "psychologist"
    ],
    "wof:name":"Southern Psychology & Consultancy",
    "wof:placetype":"venue"
},
  "geometry": {"coordinates":[138.61691300000001,-35.028877],"type":"Point"}
}