{
  "type": "Feature",
  "properties": {
    "addr:full":"3/ 4 Charles St Parramatta NSW 2150",
    "addr:housenumber":"/ 4",
    "addr:postcode":"2150",
    "addr:street":"Charles St",
    "iso:country":"AU",
    "sg:address":"3/ 4 Charles St",
    "sg:city":"Parramatta",
    "sg:classifiers":[
        {
            "category":"Health Services",
            "subcategory":"Health Practitioner",
            "type":"Services"
        }
    ],
    "sg:phone":"+61 2 9633 3096",
    "sg:postcode":"2150",
    "sg:province":"NSW",
    "sg:tags":[
        "physiotherapist"
    ],
    "wof:name":"Parramatta Physiotherapy Centre",
    "wof:placetype":"venue"
},
  "geometry": {"coordinates":[151.025024414,-33.7966041565],"type":"Point"}
}