{
  "type": "Feature",
  "properties": {
    "iso:country":"AU",
    "sg:address":"11 Cragside Pl",
    "sg:city":"Glenhaven",
    "sg:classifiers":[
        {
            "category":"Autos & Motor Vehicles",
            "subcategory":"Auto Supplies",
            "type":"Retail Goods"
        }
    ],
    "sg:phone":"+61 425 305 590",
    "sg:postcode":"2156",
    "sg:province":"NSW",
    "sg:tags":[
        "wheel",
        "automotive",
        "rim"
    ],
    "wof:name":"Mobile Alloy Wheel Repairs",
    "wof:placetype":"venue"
},
  "geometry": {"coordinates":[150.99919128400001,-33.7113685608],"type":"Point"}
}