{
  "type": "Feature",
  "properties": {
    "iso:country":"AU",
    "sg:address":"Sutherland St",
    "sg:city":"Lane Cove",
    "sg:classifiers":[
        {
            "category":"Professional",
            "subcategory":"Art Services",
            "type":"Services"
        }
    ],
    "sg:phone":"+61 2 9427 9329",
    "sg:postcode":"2066",
    "sg:province":"NSW",
    "sg:tags":[
        "graphic",
        "designer"
    ],
    "wof:name":"Creative Solutions Pty Ltd",
    "wof:placetype":"venue"
},
  "geometry": {"coordinates":[151.16636657699999,-33.8145751953],"type":"Point"}
}