{
  "type": "Feature",
  "properties": {
    "iso:country":"AU",
    "sg:address":"179/ 806 Bourke St",
    "sg:city":"Waterloo",
    "sg:classifiers":[
        {
            "category":"Professional",
            "subcategory":"Computer Services",
            "type":"Services"
        }
    ],
    "sg:phone":"+61 2 9698 8812",
    "sg:postcode":"2017",
    "sg:province":"NSW",
    "sg:tags":[
        "equipment",
        "networking",
        "installation"
    ],
    "wof:name":"Eozi Computer",
    "wof:placetype":"venue"
},
  "geometry": {"coordinates":[151.21124267600001,-33.8993377686],"type":"Point"}
}