{
  "type": "Feature",
  "properties": {
    "addr:full":"Suite 11, 55 Bulcock St Caloundra QLD 4551",
    "addr:housenumber":"55",
    "addr:postcode":"4551",
    "addr:street":"Bulcock St",
    "iso:country":"AU",
    "sg:address":"Suite 11, 55 Bulcock St",
    "sg:city":"Caloundra",
    "sg:classifiers":[
        {
            "category":"Professional",
            "subcategory":"Business Services",
            "type":"Services"
        }
    ],
    "sg:phone":"+61 7 5492 7711",
    "sg:postcode":"4551",
    "sg:province":"QLD",
    "sg:tags":[
        "small",
        "advisory"
    ],
    "wof:name":"Powell Law",
    "wof:placetype":"venue"
},
  "geometry": {"coordinates":[153.129272461,-26.804643631],"type":"Point"}
}