{
  "type": "Feature",
  "properties": {
    "iso:country":"AU",
    "sg:address":"21 Station Rd",
    "sg:city":"Indooroopilly",
    "sg:classifiers":[
        {
            "category":"Health Services",
            "subcategory":"Health Practitioner",
            "type":"Services"
        }
    ],
    "sg:phone":"+61 7 3378 3488",
    "sg:postcode":"4068",
    "sg:province":"QLD",
    "sg:tags":[
        "homoeopath"
    ],
    "wof:name":"Station Rd Homeopathic Centre",
    "wof:placetype":"venue"
},
  "geometry": {"coordinates":[152.974533081,-27.5019435883],"type":"Point"}
}