{
  "type": "Feature",
  "properties": {
    "addr:full":"235a Whitehorse Rd Balwyn VIC 3103",
    "addr:housenumber":"235a",
    "addr:postcode":"3103",
    "addr:street":"Whitehorse Rd",
    "iso:country":"AU",
    "sg:address":"235a Whitehorse Rd",
    "sg:city":"Balwyn",
    "sg:classifiers":[
        {
            "category":"Personal",
            "subcategory":"Massage",
            "type":"Services"
        }
    ],
    "sg:phone":"+61 3 9817 5984",
    "sg:postcode":"3103",
    "sg:province":"VIC",
    "sg:tags":[
        "therapy"
    ],
    "wof:name":"Contours Unit Trust",
    "wof:placetype":"venue"
},
  "geometry": {"coordinates":[145.07574462900001,-37.8120193481],"type":"Point"}
}