{
  "type": "Feature",
  "properties": {
    "addr:full":"119 Ewing St Welshpool WA 6106",
    "addr:housenumber":"119",
    "addr:postcode":"6106",
    "addr:street":"Ewing St",
    "iso:country":"AU",
    "sg:address":"119 Ewing St",
    "sg:city":"Welshpool",
    "sg:classifiers":[
        {
            "category":"Wholesale",
            "subcategory":"Painting Supplies",
            "type":"Manufacturing & Wholesale Goods"
        }
    ],
    "sg:phone":"+61 8 9451 2111",
    "sg:postcode":"6106",
    "sg:province":"WA",
    "sg:tags":[
        "wholesaler",
        "paint",
        "mfrs"
    ],
    "wof:name":"Robayne Distributors",
    "wof:placetype":"venue"
},
  "geometry": {"coordinates":[115.93125915500001,-31.9951572418],"type":"Point"}
}