{
  "type": "Feature",
  "properties": {
    "iso:country":"AU",
    "sg:address":"7 Larkin Crt",
    "sg:city":"Bundoora",
    "sg:classifiers":[
        {
            "category":"Health Services",
            "subcategory":"Health Practitioner",
            "type":"Services"
        }
    ],
    "sg:phone":"+61 3 9440 1862",
    "sg:postcode":"3083",
    "sg:province":"VIC",
    "sg:tags":[
        "acupuncture"
    ],
    "wof:name":"Maxwell Sheena",
    "wof:placetype":"venue"
},
  "geometry": {"coordinates":[145.06068420400001,-37.6836738586],"type":"Point"}
}