{
  "type": "Feature",
  "properties": {
    "iso:country":"AU",
    "sg:address":"U 3/ 15 Parry St",
    "sg:city":"Fremantle",
    "sg:classifiers":[
        {
            "category":"Health Services",
            "subcategory":"Health Practitioner",
            "type":"Services"
        }
    ],
    "sg:phone":"+61 8 9336 7261",
    "sg:postcode":"6160",
    "sg:province":"WA",
    "sg:tags":[
        "physiotherapist"
    ],
    "wof:name":"Adams Carolyn",
    "wof:placetype":"venue"
},
  "geometry": {"coordinates":[115.751022,-32.052204],"type":"Point"}
}