{
  "type": "Feature",
  "properties": {
    "addr:full":"24 Kalimna St Balwyn VIC 3103",
    "addr:housenumber":"24",
    "addr:postcode":"3103",
    "addr:street":"Kalimna St",
    "iso:country":"AU",
    "sg:address":"24 Kalimna St",
    "sg:city":"Balwyn",
    "sg:classifiers":[
        {
            "category":"Professional",
            "subcategory":"Advertising",
            "type":"Services"
        }
    ],
    "sg:phone":"+61 3 9836 4147",
    "sg:postcode":"3103",
    "sg:province":"VIC",
    "sg:tags":[
        "balloon",
        "novelty"
    ],
    "wof:name":"Balloon Supply Of Australia",
    "wof:placetype":"venue"
},
  "geometry": {"coordinates":[145.07847595199999,-37.8096733093],"type":"Point"}
}