{
  "type": "Feature",
  "properties": {
    "addr:full":"Suite 8, 15 Barron Pde Joondalup WA 6027",
    "addr:housenumber":"15",
    "addr:postcode":"6027",
    "addr:street":"Barron Pde",
    "iso:country":"AU",
    "sg:address":"Suite 8, 15 Barron Pde",
    "sg:city":"Joondalup",
    "sg:classifiers":[
        {
            "category":"Recreation",
            "subcategory":"Sailing Club",
            "type":"Entertainment"
        }
    ],
    "sg:phone":"+61 8 9301 5880",
    "sg:postcode":"6027",
    "sg:province":"WA",
    "sg:tags":[
        "merchant",
        "diamond"
    ],
    "wof:name":"The Diamond Club.Com.Au",
    "wof:placetype":"venue"
},
  "geometry": {"coordinates":[115.767700195,-31.7503623962],"type":"Point"}
}