{
  "type": "Feature",
  "properties": {
    "iso:country":"AU",
    "sg:address":"Factory 2/6 - 8 Kelvin Rd",
    "sg:city":"Bayswater North",
    "sg:classifiers":[
        {
            "category":"Building & Trades",
            "subcategory":"Pest Control",
            "type":"Services"
        }
    ],
    "sg:phone":"+61 3 9761 5656",
    "sg:postcode":"3153",
    "sg:province":"VIC",
    "wof:name":"Propest",
    "wof:placetype":"venue"
},
  "geometry": {"coordinates":[145.29635620100001,-37.819152832],"type":"Point"}
}