{
  "type": "Feature",
  "properties": {
    "addr:full":"Cnr Forster St & New Town Rd New Town TAS 7008",
    "addr:postcode":"7008",
    "addr:street":"Forster St & New Town Rd",
    "iso:country":"AU",
    "sg:address":"Cnr Forster St & New Town Rd",
    "sg:city":"New Town",
    "sg:classifiers":[
        {
            "category":"Fast Food",
            "type":"Food & Drink"
        }
    ],
    "sg:phone":"+61 3 6228 0202",
    "sg:postcode":"7008",
    "sg:province":"TAS",
    "sg:tags":[
        "away",
        "take"
    ],
    "wof:name":"Pizza Hut",
    "wof:placetype":"venue"
},
  "geometry": {"coordinates":[147.30230712900001,-42.8566627502],"type":"Point"}
}