{
  "type": "Feature",
  "properties": {
    "addr:full":"rear 19 Redleaf Ave Wahroonga NSW 2076",
    "addr:housenumber":"19",
    "addr:postcode":"2076",
    "addr:street":"Redleaf Ave",
    "iso:country":"AU",
    "sg:address":"rear 19 Redleaf Ave",
    "sg:city":"Wahroonga",
    "sg:classifiers":[
        {
            "category":"Shopping",
            "type":"Retail Goods"
        }
    ],
    "sg:phone":"+61 2 9489 2434",
    "sg:postcode":"2076",
    "sg:province":"NSW",
    "sg:tags":[
        "repair",
        "travel"
    ],
    "wof:name":"Itchy Feet-The Traveller's Shop",
    "wof:placetype":"venue"
},
  "geometry": {"coordinates":[151.11723327600001,-33.718711853],"type":"Point"}
}