{
  "type": "Feature",
  "properties": {
    "iso:country":"AU",
    "sg:address":"253 Hanson Rd",
    "sg:city":"Wingfield",
    "sg:classifiers":[
        {
            "category":"Manufacturing",
            "subcategory":"Tools & Machinery",
            "type":"Manufacturing & Wholesale Goods"
        }
    ],
    "sg:phone":"+61 8 8243 0788",
    "sg:postcode":"5013",
    "sg:province":"SA",
    "sg:tags":[
        "earth",
        "excavating",
        "moving",
        "equipment"
    ],
    "sg:website":"http://www.saliftandloader.com.au",
    "wof:name":"S.A. Lift & Loader Pty Ltd",
    "wof:placetype":"venue"
},
  "geometry": {"coordinates":[138.54646301299999,-34.8489761353],"type":"Point"}
}