{
  "type": "Feature",
  "properties": {
    "addr:full":"62a Scott Creek Rd Scott Creek SA 5153",
    "addr:housenumber":"62a",
    "addr:postcode":"5153",
    "addr:street":"Scott Creek Rd",
    "iso:country":"AU",
    "sg:address":"62a Scott Creek Rd",
    "sg:city":"Scott Creek",
    "sg:classifiers":[
        {
            "category":"Professional",
            "subcategory":"Engineering",
            "type":"Services"
        }
    ],
    "sg:phone":"+61 8 8388 2130",
    "sg:postcode":"5153",
    "sg:province":"SA",
    "sg:tags":[
        "electronic",
        "engineer"
    ],
    "wof:name":"Trewmac Systems Pty Ltd",
    "wof:placetype":"venue"
},
  "geometry": {"coordinates":[138.703567505,-35.0574569702],"type":"Point"}
}