{
  "type": "Feature",
  "properties": {
    "iso:country":"AU",
    "sg:address":"Golf Pl",
    "sg:city":"Primbee",
    "sg:classifiers":[
        {
            "category":"Retail",
            "subcategory":"Event Space",
            "type":"Services"
        }
    ],
    "sg:phone":"+61 2 4274 1159",
    "sg:postcode":"2502",
    "sg:province":"NSW",
    "sg:tags":[
        "venue",
        "reception",
        "wedding"
    ],
    "wof:name":"Port Kembla Golf Club",
    "wof:placetype":"venue"
},
  "geometry": {"coordinates":[150.87716699999999,-34.50684],"type":"Point"}
}