{
  "type": "Feature",
  "properties": {
    "addr:full":"580 Warburton Hwy Seville VIC 3139",
    "addr:housenumber":"580",
    "addr:postcode":"3139",
    "addr:street":"Warburton Hwy",
    "iso:country":"AU",
    "sg:address":"580 Warburton Hwy",
    "sg:city":"Seville",
    "sg:classifiers":[
        {
            "category":"Farming",
            "subcategory":"Vineyard",
            "type":"Manufacturing & Wholesale Goods"
        }
    ],
    "sg:phone":"+61 3 5964 2822",
    "sg:postcode":"3139",
    "sg:province":"VIC",
    "sg:tags":[
        "winery"
    ],
    "wof:name":"Whispering Hills Vineyard Pty Ltd",
    "wof:placetype":"venue"
},
  "geometry": {"coordinates":[145.45457458499999,-37.7798995972],"type":"Point"}
}