{
  "type": "Feature",
  "properties": {
    "addr:full":"Laggan Rd Crookwell NSW 2583",
    "addr:postcode":"2583",
    "addr:street":"Laggan Rd",
    "iso:country":"AU",
    "sg:address":"Laggan Rd",
    "sg:city":"Crookwell",
    "sg:classifiers":[
        {
            "category":"Autos & Motor Vehicles",
            "subcategory":"Fuel & Gas Station",
            "type":"Retail Goods"
        }
    ],
    "sg:phone":"+61 2 4832 1242",
    "sg:postcode":"2583",
    "sg:province":"NSW",
    "wof:name":"Ampol Ltd",
    "wof:placetype":"venue"
},
  "geometry": {"coordinates":[149.46751403799999,-34.4553604126],"type":"Point"}
}