{
  "type": "Feature",
  "properties": {
    "addr:full":"49 Taylor St Bulimba QLD 4171",
    "addr:housenumber":"49",
    "addr:postcode":"4171",
    "addr:street":"Taylor St",
    "iso:country":"AU",
    "sg:address":"49 Taylor St",
    "sg:city":"Bulimba",
    "sg:classifiers":[
        {
            "category":"Utilities",
            "subcategory":"Water",
            "type":"Services"
        }
    ],
    "sg:phone":"+61 7 3399 2203",
    "sg:postcode":"4171",
    "sg:province":"QLD",
    "sg:tags":[
        "hot",
        "system"
    ],
    "wof:name":"Reynolds Trezona & Lister Pty. Ltd.",
    "wof:placetype":"venue"
},
  "geometry": {"coordinates":[153.06942749000001,-27.4501037598],"type":"Point"}
}