{
  "type": "Feature",
  "properties": {
    "addr:full":"Walkers Rd Lara VIC 3212",
    "addr:postcode":"3212",
    "addr:street":"Walkers Rd",
    "iso:country":"AU",
    "sg:address":"Walkers Rd",
    "sg:city":"Lara",
    "sg:classifiers":[
        {
            "category":"Social Services",
            "subcategory":"Child Care",
            "type":"Services"
        }
    ],
    "sg:phone":"+61 3 5282 1530",
    "sg:postcode":"3212",
    "sg:province":"VIC",
    "sg:tags":[
        "support",
        "health"
    ],
    "wof:name":"Lara",
    "wof:placetype":"venue"
},
  "geometry": {"coordinates":[144.404205322,-38.0205879211],"type":"Point"}
}