{
  "type": "Feature",
  "properties": {
    "iso:country":"AU",
    "sg:address":"65 Montague St",
    "sg:city":"North Wollongong",
    "sg:classifiers":[
        {
            "category":"Manufacturing",
            "subcategory":"Metals",
            "type":"Manufacturing & Wholesale Goods"
        }
    ],
    "sg:phone":"+61 2 4228 4986",
    "sg:postcode":"2500",
    "sg:province":"NSW",
    "sg:tags":[
        "steel",
        "fabricator",
        "mfrs"
    ],
    "wof:name":"Frank's Truck Bodies Pty Ltd",
    "wof:placetype":"venue"
},
  "geometry": {"coordinates":[150.895462,-34.402599],"type":"Point"}
}