{
  "type": "Feature",
  "properties": {
    "addr:full":"1 The Crofts St Richmond VIC 3121",
    "addr:housenumber":"1",
    "addr:postcode":"3121",
    "addr:street":"The Crofts St",
    "iso:country":"AU",
    "sg:address":"1 The Crofts St",
    "sg:city":"Richmond",
    "sg:classifiers":[
        {
            "category":"Professional",
            "subcategory":"Art Services",
            "type":"Services"
        }
    ],
    "sg:phone":"+61 3 9429 8696",
    "sg:postcode":"3121",
    "sg:province":"VIC",
    "sg:tags":[
        "interior",
        "decorator"
    ],
    "wof:name":"Richmond Painting Service",
    "wof:placetype":"venue"
},
  "geometry": {"coordinates":[144.98988342300001,-37.8194503784],"type":"Point"}
}