{
  "type": "Feature",
  "properties": {
    "addr:full":"5/ 52 Vinniecombe Drv Canning Vale WA 6155",
    "addr:housenumber":"/ 52",
    "addr:postcode":"6155",
    "addr:street":"Vinniecombe Drv",
    "iso:country":"AU",
    "sg:address":"5/ 52 Vinniecombe Drv",
    "sg:city":"Canning Vale",
    "sg:classifiers":[
        {
            "category":"Shopping",
            "subcategory":"Computers & Home Electronics",
            "type":"Retail Goods"
        }
    ],
    "sg:phone":"+61 1300 887 735",
    "sg:postcode":"6155",
    "sg:province":"WA",
    "sg:tags":[
        "detector",
        "electronic"
    ],
    "wof:name":"Accurate Detection Pty Ltd",
    "wof:placetype":"venue"
},
  "geometry": {"coordinates":[115.91600800000001,-32.058918],"type":"Point"}
}