{
  "type": "Feature",
  "properties": {
    "addr:full":"192 Sharp St Cooma NSW 2630",
    "addr:housenumber":"192",
    "addr:postcode":"2630",
    "addr:street":"Sharp St",
    "iso:country":"AU",
    "sg:address":"192 Sharp St",
    "sg:city":"Cooma",
    "sg:classifiers":[
        {
            "category":"Travel",
            "subcategory":"Hotels & Motels",
            "type":"Entertainment"
        }
    ],
    "sg:phone":"+61 2 6452 1211",
    "sg:postcode":"2630",
    "sg:province":"NSW",
    "wof:name":"Greenleigh Cooma Motel",
    "wof:placetype":"venue"
},
  "geometry": {"coordinates":[149.13409423799999,-36.2312316895],"type":"Point"}
}