{
  "type": "Feature",
  "properties": {
    "addr:full":"Shop 328, The Corner, Erina Fair Erina Fair NSW 2250",
    "addr:housenumber":"328",
    "addr:postcode":"2250",
    "addr:street":"The Corner Erina Fair Erina Fair",
    "iso:country":"AU",
    "sg:address":"Shop 328, The Corner, Erina Fair",
    "sg:city":"Erina Fair",
    "sg:classifiers":[
        {
            "category":"Deli",
            "type":"Food & Drink"
        }
    ],
    "sg:phone":"+61 2 4365 6164",
    "sg:postcode":"2250",
    "sg:province":"NSW",
    "sg:tags":[
        "delicatessen"
    ],
    "wof:name":"Peters Deli",
    "wof:placetype":"venue"
},
  "geometry": {"coordinates":[151.341720581,-33.4248847961],"type":"Point"}
}