{
  "type": "Feature",
  "properties": {
    "iso:country":"AU",
    "sg:address":"4 Beach St",
    "sg:city":"Leith",
    "sg:classifiers":[
        {
            "category":"Organizations",
            "subcategory":"Non-profit Organization",
            "type":"Services"
        }
    ],
    "sg:phone":"+61 3 6428 2396",
    "sg:postcode":"7315",
    "sg:province":"TAS",
    "sg:tags":[
        "environmental",
        "organisation",
        "conservation"
    ],
    "wof:name":"Australian Plants Society Tasmania Inc.",
    "wof:placetype":"venue"
},
  "geometry": {"coordinates":[146.253631592,-41.1575622559],"type":"Point"}
}