{
  "type": "Feature",
  "properties": {
    "addr:full":"Moorebank Shopping Vlge, 136 Stockton Ave Moorebank NSW 2170",
    "addr:housenumber":"136",
    "addr:postcode":"2170",
    "addr:street":"Stockton Ave",
    "iso:country":"AU",
    "sg:address":"Moorebank Shopping Vlge, 136 Stockton Ave",
    "sg:city":"Moorebank",
    "sg:classifiers":[
        {
            "category":"Food & Beverages",
            "subcategory":"Liquor & Beverages",
            "type":"Retail Goods"
        }
    ],
    "sg:phone":"+61 2 9602 2508",
    "sg:postcode":"2170",
    "sg:province":"NSW",
    "sg:tags":[
        "store"
    ],
    "wof:name":"Woolworths Liquor",
    "wof:placetype":"venue"
},
  "geometry": {"coordinates":[150.947463989,-33.9375724792],"type":"Point"}
}