{
  "type": "Feature",
  "properties": {
    "addr:full":"74 Terralong St Kiama NSW 2533",
    "addr:housenumber":"74",
    "addr:postcode":"2533",
    "addr:street":"Terralong St",
    "iso:country":"AU",
    "sg:address":"74 Terralong St",
    "sg:city":"Kiama",
    "sg:classifiers":[
        {
            "category":"Shopping",
            "subcategory":"Baby Store",
            "type":"Retail Goods"
        }
    ],
    "sg:phone":"+61 2 4233 2330",
    "sg:postcode":"2533",
    "sg:province":"NSW",
    "sg:tags":[
        "children's",
        "wear"
    ],
    "wof:name":"Crystal Bears",
    "wof:placetype":"venue"
},
  "geometry": {"coordinates":[150.85394287099999,-34.67004776],"type":"Point"}
}