{
  "type": "Feature",
  "properties": {
    "iso:country":"AU",
    "sg:address":"78 William St",
    "sg:city":"Brighton",
    "sg:classifiers":[
        {
            "category":"Professional",
            "subcategory":"Management & Consulting",
            "type":"Services"
        }
    ],
    "sg:phone":"+61 3 9592 8581",
    "sg:postcode":"3186",
    "sg:province":"VIC",
    "sg:tags":[
        "consultant",
        "energy"
    ],
    "wof:name":"Sustainable Solutions Pty Ltd",
    "wof:placetype":"venue"
},
  "geometry": {"coordinates":[145.00402832,-37.9120674133],"type":"Point"}
}