{
  "type": "Feature",
  "properties": {
    "addr:full":"Alness St Applecross WA 6153",
    "addr:postcode":"6153",
    "addr:street":"Alness St",
    "iso:country":"AU",
    "sg:address":"Alness St",
    "sg:city":"Applecross",
    "sg:classifiers":[
        {
            "category":"Education",
            "subcategory":"Kindergarten",
            "type":"Public Place"
        }
    ],
    "sg:phone":"+61 8 9364 5836",
    "sg:postcode":"6153",
    "sg:province":"WA",
    "sg:tags":[
        "pre-schools"
    ],
    "wof:name":"Catholic Church",
    "wof:placetype":"venue"
},
  "geometry": {"coordinates":[115.834648,-32.012516],"type":"Point"}
}