{
  "type": "Feature",
  "properties": {
    "addr:full":"Unit 1 Fellowship Drv Doonan QLD 4562",
    "addr:postcode":"4562",
    "addr:street":"Fellowship Drv",
    "iso:country":"AU",
    "sg:address":"Unit 1 Fellowship Drv",
    "sg:city":"Doonan",
    "sg:classifiers":[
        {
            "category":"Wholesale",
            "subcategory":"Apparel",
            "type":"Manufacturing & Wholesale Goods"
        }
    ],
    "sg:phone":"+61 7 5471 0922",
    "sg:postcode":"4562",
    "sg:province":"QLD",
    "sg:tags":[
        "wholesaler",
        "mfrs",
        "sportswear",
        "women's"
    ],
    "wof:name":"Heatwave Cool Fashions",
    "wof:placetype":"venue"
},
  "geometry": {"coordinates":[153.023605347,-26.4456062317],"type":"Point"}
}