{
  "type": "Feature",
  "properties": {
    "addr:full":"Grenfell Rd Surrey Downs SA 5126",
    "addr:postcode":"5126",
    "addr:street":"Grenfell Rd",
    "iso:country":"AU",
    "sg:address":"Grenfell Rd",
    "sg:city":"Surrey Downs",
    "sg:classifiers":[
        {
            "category":"Food & Beverages",
            "subcategory":"Liquor & Beverages",
            "type":"Retail Goods"
        }
    ],
    "sg:phone":"+61 8 8251 4500",
    "sg:postcode":"5126",
    "sg:province":"SA",
    "sg:tags":[
        "store"
    ],
    "wof:name":"Liquor Marketing Group - S.A. Pty Ltd Sip&#039;N Save",
    "wof:placetype":"venue"
},
  "geometry": {"coordinates":[138.70602417000001,-34.8061332703],"type":"Point"}
}