{
  "type": "Feature",
  "properties": {
    "addr:full":"1/ 50 Wrights Rd Drummoyne NSW 2047",
    "addr:housenumber":"/ 50",
    "addr:postcode":"2047",
    "addr:street":"Wrights Rd",
    "iso:country":"AU",
    "sg:address":"1/ 50 Wrights Rd",
    "sg:city":"Drummoyne",
    "sg:classifiers":[
        {
            "category":"Banks & Credit Unions",
            "subcategory":"Bureau De Change",
            "type":"Services"
        }
    ],
    "sg:phone":"+61 3 6311 0609",
    "sg:postcode":"2047",
    "sg:province":"NSW",
    "sg:tags":[
        "preparation",
        "processing",
        "data"
    ],
    "wof:name":"Ivery Holdings",
    "wof:placetype":"venue"
},
  "geometry": {"coordinates":[151.15254200000001,-33.846539],"type":"Point"}
}