{
  "type": "Feature",
  "properties": {
    "iso:country":"AU",
    "sg:address":"85 Brighton Pde",
    "sg:city":"Blackwood",
    "sg:classifiers":[
        {
            "category":"Health Services",
            "subcategory":"Doctor",
            "type":"Services"
        }
    ],
    "sg:phone":"+61 415 874 423",
    "sg:postcode":"5051",
    "sg:province":"SA",
    "sg:tags":[
        "occupational",
        "safety"
    ],
    "wof:name":"Dragon Safe Consulting",
    "wof:placetype":"venue"
},
  "geometry": {"coordinates":[138.61575300000001,-35.032368],"type":"Point"}
}