{
  "type": "Feature",
  "properties": {
    "addr:full":"Shop 33, Bullcreek Shopng Cntr, South St Bull Creek WA 6149",
    "addr:housenumber":"shop 33",
    "addr:postcode":"6149",
    "addr:street":"Bullcreek Shopng Cntr South St",
    "iso:country":"AU",
    "sg:address":"Shop 33, Bullcreek Shopng Cntr, South St",
    "sg:city":"Bull Creek",
    "sg:classifiers":[
        {
            "category":"Travel",
            "subcategory":"Travel Agent",
            "type":"Entertainment"
        }
    ],
    "sg:phone":"+61 8 9310 2900",
    "sg:postcode":"6149",
    "sg:province":"WA",
    "sg:tags":[
        "consultant"
    ],
    "wof:name":"Travelworld-Bullcreek",
    "wof:placetype":"venue"
},
  "geometry": {"coordinates":[115.86621100000001,-32.065674],"type":"Point"}
}