{
  "type": "Feature",
  "properties": {
    "iso:country":"AU",
    "sg:address":"36 Racecourse Rd",
    "sg:city":"Pakenham",
    "sg:classifiers":[
        {
            "category":"Social Services",
            "subcategory":"Retirement Home",
            "type":"Services"
        }
    ],
    "sg:phone":"+61 1800 112 955",
    "sg:postcode":"3810",
    "sg:province":"VIC",
    "sg:tags":[
        "village"
    ],
    "wof:name":"Azola Waters",
    "wof:placetype":"venue"
},
  "geometry": {"coordinates":[145.492737,-38.070751],"type":"Point"}
}