{
  "type": "Feature",
  "properties": {
    "iso:country":"AU",
    "sg:address":"374 Eighth St",
    "sg:city":"Woorree",
    "sg:classifiers":[
        {
            "category":"Wholesale",
            "subcategory":"Farm Supplies",
            "type":"Manufacturing & Wholesale Goods"
        }
    ],
    "sg:phone":"+61 8 9921 8437",
    "sg:postcode":"6530",
    "sg:province":"WA",
    "sg:tags":[
        "feed",
        "supplement",
        "stock"
    ],
    "wof:name":"Woorree Stockfeeds",
    "wof:placetype":"venue"
},
  "geometry": {"coordinates":[114.658660889,-28.7683811188],"type":"Point"}
}