{
  "type": "Feature",
  "properties": {
    "addr:full":"Cnr Industrial Hwy & Woodstock St Mayfield NSW 2304",
    "addr:postcode":"2304",
    "addr:street":"Industrial;St",
    "iso:country":"AU",
    "sg:address":"Cnr Industrial Hwy & Woodstock St",
    "sg:city":"Mayfield",
    "sg:classifiers":[
        {
            "category":"Wholesale",
            "subcategory":"Machinery & Supplies",
            "type":"Manufacturing & Wholesale Goods"
        }
    ],
    "sg:phone":"+61 2 4924 2150",
    "sg:postcode":"2304",
    "sg:province":"NSW",
    "sg:tags":[
        "equipment",
        "welding"
    ],
    "wof:name":"Sandvik (Australia) Pty Ltd",
    "wof:placetype":"venue"
},
  "geometry": {"coordinates":[151.73425293,-32.894695282],"type":"Point"}
}