{
  "type": "Feature",
  "properties": {
    "addr:full":"3 Vista St Kensington WA 6151",
    "addr:housenumber":"3",
    "addr:postcode":"6151",
    "addr:street":"Vista St",
    "iso:country":"AU",
    "sg:address":"3 Vista St",
    "sg:city":"Kensington",
    "sg:classifiers":[
        {
            "category":"Wholesale",
            "subcategory":"Durable Goods & Equipment",
            "type":"Manufacturing & Wholesale Goods"
        }
    ],
    "sg:phone":"+61 8 9367 9121",
    "sg:postcode":"6151",
    "sg:province":"WA",
    "sg:tags":[
        "wholesaler",
        "mfrs",
        "lubrication"
    ],
    "wof:name":"Lubrication Engineers Pty Ltd",
    "wof:placetype":"venue"
},
  "geometry": {"coordinates":[115.876244,-31.98381],"type":"Point"}
}