{
  "type": "Feature",
  "properties": {
    "addr:full":"22 Westering Rd Christmas Hills VIC 3775",
    "addr:housenumber":"22",
    "addr:postcode":"3775",
    "addr:street":"Westering Rd",
    "iso:country":"AU",
    "sg:address":"22 Westering Rd",
    "sg:city":"Christmas Hills",
    "sg:classifiers":[
        {
            "category":"Utilities",
            "subcategory":"Electric",
            "type":"Services"
        }
    ],
    "sg:phone":"+61 407 839 440",
    "sg:postcode":"3775",
    "sg:province":"VIC",
    "sg:tags":[
        "electrical",
        "contractor"
    ],
    "wof:name":"P.L.S. Electrical Services",
    "wof:placetype":"venue"
},
  "geometry": {"coordinates":[145.275024,-37.671528],"type":"Point"}
}