{
  "type": "Feature",
  "properties": {
    "addr:full":"Crn Canning Hwy Kearns Cres Applecross WA 6153",
    "addr:postcode":"6153",
    "addr:street":"Crn Canning Hwy Kearns Cres",
    "iso:country":"AU",
    "sg:address":"Crn Canning Hwy Kearns Cres",
    "sg:city":"Applecross",
    "sg:classifiers":[
        {
            "category":"Food & Beverages",
            "subcategory":"Meat & Fish",
            "type":"Retail Goods"
        }
    ],
    "sg:phone":"+61 8 9316 9316",
    "sg:postcode":"6153",
    "sg:province":"WA",
    "sg:tags":[
        "seafood"
    ],
    "wof:name":"Freshocean Seafood Markets",
    "wof:placetype":"venue"
},
  "geometry": {"coordinates":[115.83551799999999,-32.020565],"type":"Point"}
}