{
  "type": "Feature",
  "properties": {
    "iso:country":"AU",
    "sg:address":"PO Box 377",
    "sg:city":"Avalon Beach",
    "sg:classifiers":[
        {
            "category":"Professional",
            "subcategory":"Art Services",
            "type":"Services"
        }
    ],
    "sg:phone":"+61 417 281 044",
    "sg:postcode":"2107",
    "sg:province":"NSW",
    "sg:tags":[
        "decorator",
        "painter"
    ],
    "wof:name":"Palm Beach Painting & Decorating",
    "wof:placetype":"venue"
},
  "geometry": {"coordinates":[151.33059692399999,-33.6363182068],"type":"Point"}
}