{
  "type": "Feature",
  "properties": {
    "addr:full":"Shop 23, Sharpe Ave, Karratha Village Karratha WA 6714",
    "addr:housenumber":"shop 23",
    "addr:postcode":"6714",
    "addr:street":"Sharpe Ave Karratha Village",
    "iso:country":"AU",
    "sg:address":"Shop 23, Sharpe Ave, Karratha Village",
    "sg:city":"Karratha",
    "sg:classifiers":[
        {
            "category":"Personal",
            "subcategory":"Beauty Salon",
            "type":"Services"
        }
    ],
    "sg:phone":"+61 8 9185 3394",
    "sg:postcode":"6714",
    "sg:province":"WA",
    "sg:tags":[
        "hairdresser"
    ],
    "wof:name":"Sharpe Avenue Mens Hairdresser",
    "wof:placetype":"venue"
},
  "geometry": {"coordinates":[116.845001221,-20.7331104279],"type":"Point"}
}