{
  "type": "Feature",
  "properties": {
    "iso:country":"AU",
    "sg:address":"PO Box 6022",
    "sg:city":"Shepparton",
    "sg:classifiers":[
        {
            "category":"Utilities",
            "subcategory":"Water",
            "type":"Services"
        }
    ],
    "sg:phone":"+61 408 021 500",
    "sg:postcode":"3632",
    "sg:province":"VIC",
    "sg:tags":[
        "hot",
        "system"
    ],
    "wof:name":"Shepparton Plumbing Services Pty Ltd",
    "wof:placetype":"venue"
},
  "geometry": {"coordinates":[145.399291992,-36.3811683655],"type":"Point"}
}