{
  "type": "Feature",
  "properties": {
    "addr:full":"655 Gympie Rd Lawnton QLD 4501",
    "addr:housenumber":"655",
    "addr:postcode":"4501",
    "addr:street":"Gympie Rd",
    "iso:country":"AU",
    "sg:address":"655 Gympie Rd",
    "sg:city":"Lawnton",
    "sg:classifiers":[
        {
            "category":"Home & Garden",
            "subcategory":"Carpets & Floor Coverings",
            "type":"Retail Goods"
        }
    ],
    "sg:phone":"+61 7 3881 0898",
    "sg:postcode":"4501",
    "sg:province":"QLD",
    "wof:name":"Style Carpets & Vinyls",
    "wof:placetype":"venue"
},
  "geometry": {"coordinates":[152.98257446299999,-27.2804374695],"type":"Point"}
}