{
  "type": "Feature",
  "properties": {
    "iso:country":"AU",
    "sg:address":"39 Beale St",
    "sg:city":"Southport",
    "sg:classifiers":[
        {
            "category":"Food & Beverages",
            "subcategory":"Groceries & Convenience Stores",
            "type":"Retail Goods"
        }
    ],
    "sg:phone":"+61 7 5531 2448",
    "sg:postcode":"4215",
    "sg:province":"QLD",
    "wof:name":"Beale Street General Store",
    "wof:placetype":"venue"
},
  "geometry": {"coordinates":[153.40057373100001,-27.9641532898],"type":"Point"}
}