{
  "type": "Feature",
  "properties": {
    "iso:country":"AU",
    "sg:address":"371 Nierinna Rd",
    "sg:city":"Margate",
    "sg:classifiers":[
        {
            "category":"Farming",
            "subcategory":"Berry Farm",
            "type":"Manufacturing & Wholesale Goods"
        }
    ],
    "sg:phone":"+61 3 6267 2581",
    "sg:postcode":"7054",
    "sg:province":"TAS",
    "sg:tags":[
        "fruit",
        "grower"
    ],
    "wof:name":"Nierinna Blueberries",
    "wof:placetype":"venue"
},
  "geometry": {"coordinates":[147.217209,-43.035793],"type":"Point"}
}