{
  "type": "Feature",
  "properties": {
    "iso:country":"AU",
    "sg:address":"Lot 16 Callemondah Drv",
    "sg:city":"Gladstone",
    "sg:classifiers":[
        {
            "category":"Professional",
            "type":"Services"
        }
    ],
    "sg:phone":"+61 7 4978 4848",
    "sg:postcode":"4680",
    "sg:province":"QLD",
    "sg:tags":[
        "spray",
        "painting"
    ],
    "wof:name":"Harbour City Body Repairs",
    "wof:placetype":"venue"
},
  "geometry": {"coordinates":[151.238937378,-23.8570308685],"type":"Point"}
}