{
  "type": "Feature",
  "properties": {
    "addr:full":"Glen Stuart Rd Magill SA 5072",
    "addr:postcode":"5072",
    "addr:street":"Stuart Rd",
    "iso:country":"AU",
    "sg:address":"Glen Stuart Rd",
    "sg:city":"Magill",
    "sg:classifiers":[
        {
            "category":"Education",
            "subcategory":"School",
            "type":"Public Place"
        }
    ],
    "sg:phone":"+61 8 8366 6426",
    "sg:postcode":"5072",
    "sg:province":"SA",
    "sg:tags":[
        "state",
        "except",
        "nsw"
    ],
    "wof:name":"Magill Education Centre",
    "wof:placetype":"venue"
},
  "geometry": {"coordinates":[138.68455505399999,-34.905506134],"type":"Point"}
}