{
  "type": "Feature",
  "properties": {
    "addr:full":"1 Cleveland Rd Ashwood VIC 3147",
    "addr:housenumber":"1",
    "addr:postcode":"3147",
    "addr:street":"Cleveland Rd",
    "iso:country":"AU",
    "sg:address":"1 Cleveland Rd",
    "sg:city":"Ashwood",
    "sg:classifiers":[
        {
            "category":"Food & Beverages",
            "subcategory":"Liquor & Beverages",
            "type":"Retail Goods"
        }
    ],
    "sg:phone":"+61 3 9807 3266",
    "sg:postcode":"3147",
    "sg:province":"VIC",
    "sg:tags":[
        "store"
    ],
    "wof:name":"The Wine Barrel",
    "wof:placetype":"venue"
},
  "geometry": {"coordinates":[145.10540771500001,-37.8673324585],"type":"Point"}
}