{
  "type": "Feature",
  "properties": {
    "iso:country":"AU",
    "sg:address":"Yea Rd",
    "sg:city":"Flowerdale",
    "sg:classifiers":[
        {
            "category":"Wholesale",
            "subcategory":"Farm Supplies",
            "type":"Manufacturing & Wholesale Goods"
        }
    ],
    "sg:phone":"+61 3 5780 1202",
    "sg:postcode":"3717",
    "sg:province":"VIC",
    "sg:tags":[
        "feed",
        "supplement",
        "stock"
    ],
    "wof:name":"Hazeldene General Store",
    "wof:placetype":"venue"
},
  "geometry": {"coordinates":[145.346160889,-37.2774543762],"type":"Point"}
}