{
  "type": "Feature",
  "properties": {
    "addr:full":"Shop 2 967 Benetook Ave Mildura VIC 3500",
    "addr:housenumber":"shop 2",
    "addr:postcode":"967;3500",
    "addr:street":"Benetook Ave",
    "iso:country":"AU",
    "sg:address":"Shop 2 967 Benetook Ave",
    "sg:city":"Mildura",
    "sg:classifiers":[
        {
            "category":"Building & Trades",
            "subcategory":"Construction",
            "type":"Services"
        }
    ],
    "sg:phone":"+61 3 5022 8888",
    "sg:postcode":"3500",
    "sg:province":"VIC",
    "sg:tags":[
        "welding"
    ],
    "wof:name":"Sunraysia Engineering and Sales Pty Ltd",
    "wof:placetype":"venue"
},
  "geometry": {"coordinates":[142.18145751899999,-34.195110321],"type":"Point"}
}