{
  "type": "Feature",
  "properties": {
    "iso:country":"AU",
    "sg:address":"Wormbete Station Rd",
    "sg:city":"Winchelsea South",
    "sg:classifiers":[
        {
            "category":"Social Services",
            "subcategory":"Child Care",
            "type":"Services"
        }
    ],
    "sg:phone":"+61 3 5288 7240",
    "sg:postcode":"3241",
    "sg:province":"VIC",
    "sg:tags":[
        "shearer"
    ],
    "wof:name":"Mawson N G",
    "wof:placetype":"venue"
},
  "geometry": {"coordinates":[144.019805908,-38.3143310547],"type":"Point"}
}