{
  "type": "Feature",
  "properties": {
    "addr:full":"478 Dean St Albury NSW 2640",
    "addr:housenumber":"478",
    "addr:postcode":"2640",
    "addr:street":"Dean St",
    "iso:country":"AU",
    "sg:address":"478 Dean St",
    "sg:city":"Albury",
    "sg:classifiers":[
        {
            "category":"Home & Garden",
            "subcategory":"Building Materials",
            "type":"Retail Goods"
        }
    ],
    "sg:phone":"+61 2 6021 4886",
    "sg:postcode":"2640",
    "sg:province":"NSW",
    "sg:tags":[
        "supply"
    ],
    "wof:name":"Vicwardian Effects",
    "wof:placetype":"venue"
},
  "geometry": {"coordinates":[146.91960144000001,-36.0810241699],"type":"Point"}
}