{
  "type": "Feature",
  "properties": {
    "addr:full":"Cnr The Horsley Drv & Nello Pl Wetherill Park NSW 2164",
    "addr:postcode":"2164",
    "addr:street":"Cnr The Horsley Drv & Nello Pl",
    "iso:country":"AU",
    "sg:address":"Cnr The Horsley Drv & Nello Pl",
    "sg:city":"Wetherill Park",
    "sg:classifiers":[
        {
            "category":"Building & Trades",
            "subcategory":"Equipment Rental",
            "type":"Services"
        }
    ],
    "sg:phone":"+61 2 9725 3288",
    "sg:postcode":"2164",
    "sg:province":"NSW",
    "sg:tags":[
        "renting",
        "trailer"
    ],
    "wof:name":"Kennards Trailer Hire",
    "wof:placetype":"venue"
},
  "geometry": {"coordinates":[150.89431762699999,-33.8520355225],"type":"Point"}
}