{
  "type": "Feature",
  "properties": {
    "iso:country":"AU",
    "sg:address":"18 Webb Rd",
    "sg:city":"Airport West",
    "sg:classifiers":[
        {
            "category":"Shopping Center",
            "type":"Public Place"
        }
    ],
    "sg:phone":"+61 3 9335 4995",
    "sg:postcode":"3042",
    "sg:province":"VIC",
    "sg:tags":[
        "spawn",
        "supplier",
        "mushroom"
    ],
    "wof:name":"Better Mushrooms",
    "wof:placetype":"venue"
},
  "geometry": {"coordinates":[144.88998413100001,-37.7158546448],"type":"Point"}
}