{
  "type": "Feature",
  "properties": {
    "addr:full":"Southern Districts Memorial Hospital Aldersey St McLaren Vale SA 5171",
    "addr:postcode":"5171",
    "addr:street":"St",
    "iso:country":"AU",
    "sg:address":"Southern Districts Memorial Hospital Aldersey St",
    "sg:city":"McLaren Vale",
    "sg:classifiers":[
        {
            "category":"Health Services",
            "subcategory":"Health Practitioner",
            "type":"Services"
        }
    ],
    "sg:phone":"+61 8 8323 6600",
    "sg:postcode":"5171",
    "sg:province":"SA",
    "sg:tags":[
        "psychologist"
    ],
    "wof:name":"Finster Wendy",
    "wof:placetype":"venue"
},
  "geometry": {"coordinates":[138.54371643100001,-35.219078064],"type":"Point"}
}