{
  "type": "Feature",
  "properties": {
    "iso:country":"AU",
    "sg:address":"31 Jarrad St",
    "sg:city":"Cottesloe",
    "sg:classifiers":[
        {
            "category":"Shopping",
            "subcategory":"Clothing, Apparel, & Fashions",
            "type":"Retail Goods"
        }
    ],
    "sg:phone":"+61 8 6103 4520",
    "sg:postcode":"6011",
    "sg:province":"WA",
    "sg:tags":[
        "underclothing"
    ],
    "wof:name":"Mainpeak",
    "wof:placetype":"venue"
},
  "geometry": {"coordinates":[115.76109314,-31.9991474152],"type":"Point"}
}