{
  "type": "Feature",
  "properties": {
    "addr:full":"2807 Fourteenth St Irymple VIC 3498",
    "addr:housenumber":"2807",
    "addr:postcode":"3498",
    "addr:street":"Fourteenth St",
    "iso:country":"AU",
    "sg:address":"2807 Fourteenth St",
    "sg:city":"Irymple",
    "sg:classifiers":[
        {
            "category":"Food & Beverages",
            "subcategory":"Bakery",
            "type":"Retail Goods"
        }
    ],
    "sg:phone":"+61 3 5024 7297",
    "sg:postcode":"3498",
    "sg:province":"VIC",
    "sg:tags":[
        "cake",
        "shop",
        "pastry"
    ],
    "wof:name":"Cake Creations - by Lynne",
    "wof:placetype":"venue"
},
  "geometry": {"coordinates":[142.183670044,-34.2288703918],"type":"Point"}
}