{
  "type": "Feature",
  "properties": {
    "iso:country":"AU",
    "sg:address":"260e Zillmere Rd",
    "sg:city":"Zillmere",
    "sg:classifiers":[
        {
            "category":"Building & Trades",
            "subcategory":"Cleaning & Sanitation",
            "type":"Services"
        }
    ],
    "sg:phone":"+61 7 3216 5822",
    "sg:postcode":"4034",
    "sg:province":"QLD",
    "sg:tags":[
        "abrasive",
        "blasting"
    ],
    "wof:name":"Alistrip Systems",
    "wof:placetype":"venue"
},
  "geometry": {"coordinates":[153.04736299999999,-27.360893],"type":"Point"}
}