{
  "type": "Feature",
  "properties": {
    "iso:country":"AU",
    "sg:address":"7 Chanter St",
    "sg:city":"Berrigan",
    "sg:classifiers":[
        {
            "category":"Retail",
            "subcategory":"Veterinary Services",
            "type":"Services"
        }
    ],
    "sg:phone":"+61 3 5885 2021",
    "sg:postcode":"2712",
    "sg:province":"NSW",
    "sg:tags":[
        "surgeon"
    ],
    "wof:name":"Berrigan Veterinary Clinic",
    "wof:placetype":"venue"
},
  "geometry": {"coordinates":[145.81149292000001,-35.6572914124],"type":"Point"}
}