{
  "type": "Feature",
  "properties": {
    "iso:country":"AU",
    "sg:address":"Suite 43, 47-53 Neridah St",
    "sg:city":"Chatswood",
    "sg:classifiers":[
        {
            "category":"Personal",
            "subcategory":"Beauty Salon",
            "type":"Services"
        }
    ],
    "sg:phone":"+61 2 9411 2136",
    "sg:postcode":"2067",
    "sg:province":"NSW",
    "wof:name":"Jinna Permanent Makeup",
    "wof:placetype":"venue"
},
  "geometry": {"coordinates":[151.187576294,-33.7962150574],"type":"Point"}
}