{
  "type": "Feature",
  "properties": {
    "addr:full":"38 Peterkin St Acacia Ridge QLD 4110",
    "addr:housenumber":"38",
    "addr:postcode":"4110",
    "addr:street":"Peterkin St",
    "iso:country":"AU",
    "sg:address":"38 Peterkin St",
    "sg:city":"Acacia Ridge",
    "sg:classifiers":[
        {
            "category":"Professional",
            "subcategory":"Employment Agencies",
            "type":"Services"
        }
    ],
    "sg:phone":"+61 7 3323 9090",
    "sg:postcode":"4110",
    "sg:province":"QLD",
    "sg:tags":[
        "hire",
        "labour",
        "contractor"
    ],
    "wof:name":"Labourforce Solutions",
    "wof:placetype":"venue"
},
  "geometry": {"coordinates":[153.03451538100001,-27.5772666931],"type":"Point"}
}