{
  "type": "Feature",
  "properties": {
    "addr:full":"3A 42-44 Hartnett Drv Seaford VIC 3198",
    "addr:housenumber":"3a 42-44",
    "addr:postcode":"3198",
    "addr:street":"Hartnett Drv",
    "iso:country":"AU",
    "sg:address":"3A 42-44 Hartnett Drv",
    "sg:city":"Seaford",
    "sg:classifiers":[
        {
            "category":"Wholesale",
            "subcategory":"Machinery & Supplies",
            "type":"Manufacturing & Wholesale Goods"
        }
    ],
    "sg:phone":"+61 3 8796 3414",
    "sg:postcode":"3198",
    "sg:province":"VIC",
    "sg:tags":[
        "process",
        "instrument",
        "control"
    ],
    "wof:name":"E Q A M S Pty Ltd",
    "wof:placetype":"venue"
},
  "geometry": {"coordinates":[145.14088439899999,-38.1153182983],"type":"Point"}
}