{
  "type": "Feature",
  "properties": {
    "iso:country":"AU",
    "sg:address":"3-4/ 162 Rokeby Rd",
    "sg:city":"Subiaco",
    "sg:classifiers":[
        {
            "category":"Cafe",
            "type":"Food & Drink"
        }
    ],
    "sg:phone":"+61 8 9388 7272",
    "sg:postcode":"6008",
    "sg:province":"WA",
    "wof:name":"Brew-Ha",
    "wof:placetype":"venue"
},
  "geometry": {"coordinates":[115.824142456,-31.9495010376],"type":"Point"}
}