{
  "type": "Feature",
  "properties": {
    "iso:country":"AU",
    "sg:address":"Lynch St",
    "sg:city":"Corrigin",
    "sg:classifiers":[
        {
            "category":"Travel",
            "subcategory":"Hostel",
            "type":"Entertainment"
        }
    ],
    "sg:phone":"+61 8 9063 2502",
    "sg:postcode":"6375",
    "sg:province":"WA",
    "sg:tags":[
        "home"
    ],
    "wof:name":"Wogerlin House",
    "wof:placetype":"venue"
},
  "geometry": {"coordinates":[117.876251,-32.332474],"type":"Point"}
}