{
  "type": "Feature",
  "properties": {
    "addr:full":"156 Sanyer St Corowa NSW 2646",
    "addr:housenumber":"156",
    "addr:postcode":"2646",
    "addr:street":"Sanyer St",
    "iso:country":"AU",
    "sg:address":"156 Sanyer St",
    "sg:city":"Corowa",
    "sg:classifiers":[
        {
            "category":"Professional",
            "subcategory":"Accounting & Tax Preparation",
            "type":"Services"
        }
    ],
    "sg:phone":"+61 2 6033 2494",
    "sg:postcode":"2646",
    "sg:province":"NSW",
    "sg:tags":[
        "consultant",
        "taxation"
    ],
    "wof:name":"H&R Block",
    "wof:placetype":"venue"
},
  "geometry": {"coordinates":[146.391357422,-35.9956436157],"type":"Point"}
}