{
  "type": "Feature",
  "properties": {
    "addr:full":"59 Hume Hwy Chullora NSW 2190",
    "addr:housenumber":"59",
    "addr:postcode":"2190",
    "addr:street":"Hume Hwy",
    "iso:country":"AU",
    "sg:address":"59 Hume Hwy",
    "sg:city":"Chullora",
    "sg:classifiers":[
        {
            "category":"Professional",
            "subcategory":"Detective & Security Services",
            "type":"Services"
        }
    ],
    "sg:phone":"+61 2 9742 3100",
    "sg:postcode":"2190",
    "sg:province":"NSW",
    "sg:tags":[
        "protective",
        "rustproofing"
    ],
    "wof:name":"VIP Car Care",
    "wof:placetype":"venue"
},
  "geometry": {"coordinates":[151.05746500000001,-33.891769],"type":"Point"}
}