{
  "type": "Feature",
  "properties": {
    "addr:full":"833 Hazeldean Rd Cloverlea VIC 3822",
    "addr:housenumber":"833",
    "addr:postcode":"3822",
    "addr:street":"Hazeldean Rd",
    "iso:country":"AU",
    "sg:address":"833 Hazeldean Rd",
    "sg:city":"Cloverlea",
    "sg:classifiers":[
        {
            "category":"Building & Trades",
            "subcategory":"Construction",
            "type":"Services"
        }
    ],
    "sg:phone":"+61 3 5627 8401",
    "sg:postcode":"3822",
    "sg:province":"VIC",
    "sg:tags":[
        "fencing",
        "contractor"
    ],
    "wof:name":"Sandy I J & L M",
    "wof:placetype":"venue"
},
  "geometry": {"coordinates":[145.991455,-38.245716],"type":"Point"}
}