{
  "type": "Feature",
  "properties": {
    "iso:country":"AU",
    "sg:address":"Bacon Factory Rd",
    "sg:city":"Smithton",
    "sg:classifiers":[
        {
            "category":"Autos & Motor Vehicles",
            "subcategory":"Fuel & Gas Station",
            "type":"Retail Goods"
        }
    ],
    "sg:phone":"+61 3 6452 1526",
    "sg:postcode":"7330",
    "sg:province":"TAS",
    "wof:name":"Carter Mechanical",
    "wof:placetype":"venue"
},
  "geometry": {"coordinates":[145.133743,-40.859074],"type":"Point"}
}