{
  "type": "Feature",
  "properties": {
    "addr:full":"Unit 2/11 Reliance Drv, Tuggerah Business Park Tuggerah NSW 2259",
    "addr:housenumber":"11;business",
    "addr:postcode":"2259",
    "addr:street":"Reliance Drv",
    "iso:country":"AU",
    "sg:address":"Unit 2/11 Reliance Drv, Tuggerah Business Park",
    "sg:city":"Tuggerah",
    "sg:classifiers":[
        {
            "category":"Building & Trades",
            "subcategory":"Cleaning & Sanitation",
            "type":"Services"
        }
    ],
    "sg:phone":"+61 1800 009 881",
    "sg:postcode":"2259",
    "sg:province":"NSW",
    "sg:tags":[
        "industrial",
        "commercial",
        "contractor"
    ],
    "wof:name":"Crystal Waters Cleaning",
    "wof:placetype":"venue"
},
  "geometry": {"coordinates":[151.41966247600001,-33.3162994385],"type":"Point"}
}