{
  "type": "Feature",
  "properties": {
    "addr:full":"134- 136 Glenayr Ave Bondi Beach NSW 2026",
    "addr:housenumber":"136",
    "addr:postcode":"2026",
    "addr:street":"Glenayr Ave",
    "iso:country":"AU",
    "sg:address":"134- 136 Glenayr Ave",
    "sg:city":"Bondi Beach",
    "sg:classifiers":[
        {
            "category":"Building & Trades",
            "subcategory":"Locksmith",
            "type":"Services"
        }
    ],
    "sg:phone":"+61 2 9365 4623",
    "sg:postcode":"2026",
    "sg:province":"NSW",
    "sg:tags":[
        "lock"
    ],
    "wof:name":"Budget Hardware & Locksmith",
    "wof:placetype":"venue"
},
  "geometry": {"coordinates":[151.271682739,-33.8878707886],"type":"Point"}
}