{
  "type": "Feature",
  "properties": {
    "iso:country":"AU",
    "sg:address":"86 Carlingford St",
    "sg:city":"Sefton",
    "sg:classifiers":[
        {
            "category":"Retail",
            "subcategory":"Auto Repair",
            "type":"Services"
        }
    ],
    "sg:phone":"+61 2 9644 9888",
    "sg:postcode":"2162",
    "sg:province":"NSW",
    "sg:tags":[
        "repairer",
        "motor",
        "engineer"
    ],
    "wof:name":"Colan Bros Automotive Services Pty Ltd",
    "wof:placetype":"venue"
},
  "geometry": {"coordinates":[151.013183594,-33.8846588135],"type":"Point"}
}