{
  "type": "Feature",
  "properties": {
    "addr:full":"139a Cabramatta Rd Cabramatta NSW 2166",
    "addr:housenumber":"139a",
    "addr:postcode":"2166",
    "addr:street":"Cabramatta Rd",
    "iso:country":"AU",
    "sg:address":"139a Cabramatta Rd",
    "sg:city":"Cabramatta",
    "sg:classifiers":[
        {
            "category":"Health Services",
            "subcategory":"Doctor",
            "type":"Services"
        }
    ],
    "sg:phone":"+61 2 9724 1622",
    "sg:postcode":"2166",
    "sg:province":"NSW",
    "sg:tags":[
        "medical",
        "practitioner"
    ],
    "wof:name":"So Gabriel",
    "wof:placetype":"venue"
},
  "geometry": {"coordinates":[150.9034729,-33.8947105408],"type":"Point"}
}