{
  "type": "Feature",
  "properties": {
    "addr:full":"Shop 15a Mount Annan Shopping Village Mt Annan NSW 2567",
    "addr:housenumber":"15a",
    "addr:postcode":"2567",
    "addr:street":"Mount Annan",
    "iso:country":"AU",
    "sg:address":"Shop 15a Mount Annan Shopping Village",
    "sg:city":"Mt Annan",
    "sg:classifiers":[
        {
            "category":"Health Services",
            "subcategory":"Dentist",
            "type":"Services"
        }
    ],
    "sg:phone":"+61 2 4648 1122",
    "sg:postcode":"2567",
    "sg:province":"NSW",
    "wof:name":"Krajewski Steven Dr",
    "wof:placetype":"venue"
},
  "geometry": {"coordinates":[150.77203369099999,-34.0544090271],"type":"Point"}
}