{
  "type": "Feature",
  "properties": {
    "iso:country":"AU",
    "sg:address":"12 Tasman Hwy",
    "sg:city":"Weldborough",
    "sg:classifiers":[
        {
            "category":"Travel",
            "subcategory":"Hotels & Motels",
            "type":"Entertainment"
        }
    ],
    "sg:phone":"+61 3 6354 2223",
    "sg:postcode":"7264",
    "sg:province":"TAS",
    "sg:tags":[
        "accommodation"
    ],
    "wof:name":"Weldborough Hotel The",
    "wof:placetype":"venue"
},
  "geometry": {"coordinates":[147.906754,-41.186485],"type":"Point"}
}