{
  "type": "Feature",
  "properties": {
    "addr:full":"13 Hill Rd West Pennant Hills NSW 2125",
    "addr:housenumber":"13",
    "addr:postcode":"2125",
    "addr:street":"Hill Rd",
    "iso:country":"AU",
    "sg:address":"13 Hill Rd",
    "sg:city":"West Pennant Hills",
    "sg:classifiers":[
        {
            "category":"Professional",
            "subcategory":"Secretarial Services",
            "type":"Services"
        }
    ],
    "sg:phone":"+61 2 9871 3338",
    "sg:postcode":"2125",
    "sg:province":"NSW",
    "sg:tags":[
        "typing"
    ],
    "wof:name":"Abbey National",
    "wof:placetype":"venue"
},
  "geometry": {"coordinates":[151.02841186500001,-33.7487030029],"type":"Point"}
}