{
  "type": "Feature",
  "properties": {
    "addr:full":"Level 15, Exchange Plaza, 2 The Esplanade Perth WA 6000",
    "addr:housenumber":"2",
    "addr:postcode":"6000",
    "addr:street":"The Esplanade",
    "iso:country":"AU",
    "sg:address":"Level 15, Exchange Plaza, 2 The Esplanade",
    "sg:city":"Perth",
    "sg:classifiers":[
        {
            "category":"Professional",
            "subcategory":"Computer Services",
            "type":"Services"
        }
    ],
    "sg:phone":"+61 1300 135 070",
    "sg:postcode":"6000",
    "sg:province":"WA",
    "sg:tags":[
        "information"
    ],
    "wof:name":"Australian Bureau Of Statistics",
    "wof:placetype":"venue"
},
  "geometry": {"coordinates":[115.858642578,-31.9566688538],"type":"Point"}
}