{
  "type": "Feature",
  "properties": {
    "addr:full":"Pacific Hwy Broadwater NSW 2472",
    "addr:postcode":"2472",
    "addr:street":"Pacific Hwy",
    "iso:country":"AU",
    "sg:address":"Pacific Hwy",
    "sg:city":"Broadwater",
    "sg:classifiers":[
        {
            "category":"Farming",
            "subcategory":"Crops",
            "type":"Manufacturing & Wholesale Goods"
        }
    ],
    "sg:phone":"+61 2 6620 8200",
    "sg:postcode":"2472",
    "sg:province":"NSW",
    "sg:tags":[
        "sugarcane",
        "mill",
        "grower"
    ],
    "wof:name":"New South Wales Sugar Milling Co-Operative Ltd",
    "wof:placetype":"venue"
},
  "geometry": {"coordinates":[153.43463134800001,-29.0115280151],"type":"Point"}
}