{
  "type": "Feature",
  "properties": {
    "addr:full":"Martin St Nyabing WA 6341",
    "addr:postcode":"6341",
    "addr:street":"Martin St",
    "iso:country":"AU",
    "sg:address":"Martin St",
    "sg:city":"Nyabing",
    "sg:classifiers":[
        {
            "category":"Sports & Exercise",
            "subcategory":"Sports Center",
            "type":"Entertainment"
        }
    ],
    "sg:phone":"+61 8 9829 1120",
    "sg:postcode":"6341",
    "sg:province":"WA",
    "sg:tags":[
        "ground"
    ],
    "wof:name":"Nyabing Sports Pavillion",
    "wof:placetype":"venue"
},
  "geometry": {"coordinates":[118.14669000000001,-33.543404],"type":"Point"}
}