{
  "type": "Feature",
  "properties": {
    "addr:full":"237 Maroubra Rd Maroubra NSW 2035",
    "addr:housenumber":"237",
    "addr:postcode":"2035",
    "addr:street":"Maroubra Rd",
    "iso:country":"AU",
    "sg:address":"237 Maroubra Rd",
    "sg:city":"Maroubra",
    "sg:classifiers":[
        {
            "category":"Military Area",
            "subcategory":"Air Force Base",
            "type":"Public Place"
        }
    ],
    "sg:phone":"+61 2 9349 6820",
    "sg:postcode":"2035",
    "sg:province":"NSW",
    "sg:tags":[
        "men's",
        "tailor"
    ],
    "wof:name":"V A Tailoring",
    "wof:placetype":"venue"
},
  "geometry": {"coordinates":[151.240890503,-33.94190979],"type":"Point"}
}