{
  "type": "Feature",
  "properties": {
    "addr:full":"U211/ 105 Scarborough St Southport QLD 4215",
    "addr:housenumber":"u211 / 105",
    "addr:postcode":"4215",
    "addr:street":"Scarborough St",
    "iso:country":"AU",
    "sg:address":"U211/ 105 Scarborough St",
    "sg:city":"Southport",
    "sg:classifiers":[
        {
            "category":"Professional",
            "type":"Services"
        }
    ],
    "sg:phone":"+61 7 5531 1611",
    "sg:postcode":"4215",
    "sg:province":"QLD",
    "sg:tags":[
        "transport"
    ],
    "wof:name":"Transport Works",
    "wof:placetype":"venue"
},
  "geometry": {"coordinates":[153.41346740700001,-27.9660072327],"type":"Point"}
}