{
  "type": "Feature",
  "properties": {
    "iso:country":"AU",
    "sg:address":"Sydney Rd",
    "sg:city":"Manly",
    "sg:classifiers":[
        {
            "category":"Building & Trades",
            "subcategory":"Landscaping Services",
            "type":"Services"
        }
    ],
    "sg:phone":"+61 2 9315 7011",
    "sg:postcode":"2095",
    "sg:province":"NSW",
    "sg:tags":[
        "market"
    ],
    "wof:name":"Manly Arts & Craft Market",
    "wof:placetype":"venue"
},
  "geometry": {"coordinates":[151.28761291500001,-33.7972869873],"type":"Point"}
}