{
  "type": "Feature",
  "properties": {
    "addr:full":"Unit 2 20 Booran Drv Underwood QLD 4119",
    "addr:housenumber":"20",
    "addr:postcode":"4119",
    "addr:street":"Booran Drv",
    "iso:country":"AU",
    "sg:address":"Unit 2 20 Booran Drv",
    "sg:city":"Underwood",
    "sg:classifiers":[
        {
            "category":"Building & Trades",
            "subcategory":"Construction",
            "type":"Services"
        }
    ],
    "sg:phone":"+61 7 3808 4441",
    "sg:postcode":"4119",
    "sg:province":"QLD",
    "sg:tags":[
        "renovation",
        "alterations",
        "extension",
        "contractor"
    ],
    "wof:name":"Inntec Refurbishments Pty Ltd",
    "wof:placetype":"venue"
},
  "geometry": {"coordinates":[153.11416625999999,-27.6230640411],"type":"Point"}
}