{
  "type": "Feature",
  "properties": {
    "addr:full":"18 Railway Pde Kurri Kurri NSW 2327",
    "addr:housenumber":"18",
    "addr:postcode":"2327",
    "addr:street":"Railway Pde",
    "iso:country":"AU",
    "sg:address":"18 Railway Pde",
    "sg:city":"Kurri Kurri",
    "sg:classifiers":[
        {
            "category":"Building & Trades",
            "subcategory":"Cleaning & Sanitation",
            "type":"Services"
        }
    ],
    "sg:phone":"+61 2 4937 2592",
    "sg:postcode":"2327",
    "sg:province":"NSW",
    "sg:tags":[
        "industrial",
        "commercial",
        "contractor"
    ],
    "wof:name":"Deep Impact Cleaning Services",
    "wof:placetype":"venue"
},
  "geometry": {"coordinates":[151.47511291500001,-32.8092842102],"type":"Point"}
}