{
  "type": "Feature",
  "properties": {
    "addr:full":"Un 8 , 8 Yampi Way Willetton WA 6155",
    "addr:housenumber":"8",
    "addr:postcode":"6155",
    "addr:street":"Yampi Way",
    "iso:country":"AU",
    "sg:address":"Un 8",
    "sg:city":", 8 Yampi Way Willetton",
    "sg:classifiers":[
        {
            "category":"Banks & Credit Unions",
            "subcategory":"Bureau De Change",
            "type":"Services"
        }
    ],
    "sg:phone":"+61 8 9354 8826",
    "sg:postcode":"6155",
    "sg:province":"WA",
    "sg:tags":[
        "preparation",
        "processing",
        "data"
    ],
    "wof:name":"Phoenix Data Services",
    "wof:placetype":"venue"
},
  "geometry": {"coordinates":[115.885582,-32.040684],"type":"Point"}
}