{
  "type": "Feature",
  "properties": {
    "iso:country":"AU",
    "sg:address":"258- 260 Burwood Rd",
    "sg:city":"Hawthorn",
    "sg:classifiers":[
        {
            "category":"Professional",
            "subcategory":"Printing & Photocopies",
            "type":"Services"
        }
    ],
    "sg:phone":"+61 3 9815 1200",
    "sg:postcode":"3122",
    "sg:province":"VIC",
    "sg:tags":[
        "photocopier"
    ],
    "wof:name":"Copyguard Australia Pty Ltd",
    "wof:placetype":"venue"
},
  "geometry": {"coordinates":[145.032592773,-37.8224182129],"type":"Point"}
}