{
  "type": "Feature",
  "properties": {
    "addr:full":"97f McInerney Ave Mitchell Park SA 5043",
    "addr:housenumber":"97f",
    "addr:postcode":"5043",
    "addr:street":"Mcinerney Ave",
    "iso:country":"AU",
    "sg:address":"97f McInerney Ave",
    "sg:city":"Mitchell Park",
    "sg:classifiers":[
        {
            "category":"Shopping",
            "subcategory":"Gifts & Souvenirs",
            "type":"Retail Goods"
        }
    ],
    "sg:phone":"+61 8 8276 3095",
    "sg:postcode":"5043",
    "sg:province":"SA",
    "sg:tags":[
        "greeting",
        "card"
    ],
    "wof:name":"Mitchell Park Pharmacy",
    "wof:placetype":"venue"
},
  "geometry": {"coordinates":[138.56222500000001,-35.010429],"type":"Point"}
}