{
  "type": "Feature",
  "properties": {
    "addr:full":"PO Box 4541 Kirwan QLD 4817",
    "addr:postcode":"4817",
    "iso:country":"AU",
    "sg:address":"PO Box 4541",
    "sg:city":"Kirwan",
    "sg:classifiers":[
        {
            "category":"Professional",
            "subcategory":"Advertising",
            "type":"Services"
        }
    ],
    "sg:phone":"+61 7 4774 5252",
    "sg:postcode":"4817",
    "sg:province":"QLD",
    "sg:tags":[
        "balloon",
        "novelty"
    ],
    "wof:name":"Balloon Decor",
    "wof:placetype":"venue"
},
  "geometry": {"coordinates":[146.73516799999999,-19.30369],"type":"Point"}
}