{
  "type": "Feature",
  "properties": {
    "addr:full":"2 Deloraine Drv Albany WA 6330",
    "addr:housenumber":"2",
    "addr:postcode":"6330",
    "addr:street":"Deloraine Drv",
    "iso:country":"AU",
    "sg:address":"2 Deloraine Drv",
    "sg:city":"Albany",
    "sg:classifiers":[
        {
            "category":"Home & Garden",
            "subcategory":"Building Materials",
            "type":"Retail Goods"
        }
    ],
    "sg:phone":"+61 8 9841 4408",
    "sg:postcode":"6330",
    "sg:province":"WA",
    "sg:tags":[
        "lawn",
        "cutting",
        "maintenance"
    ],
    "wof:name":"The Gardeners Friend",
    "wof:placetype":"venue"
},
  "geometry": {"coordinates":[117.847862244,-34.975769043],"type":"Point"}
}