{
  "type": "Feature",
  "properties": {
    "iso:country":"AU",
    "sg:address":"160 Redland Bay Rd",
    "sg:city":"Capalaba",
    "sg:classifiers":[
        {
            "category":"Home & Garden",
            "subcategory":"Carpets & Floor Coverings",
            "type":"Retail Goods"
        }
    ],
    "sg:phone":"+61 7 3245 4444",
    "sg:postcode":"4157",
    "sg:province":"QLD",
    "sg:tags":[
        "mattress"
    ],
    "wof:name":"Factory First",
    "wof:placetype":"venue"
},
  "geometry": {"coordinates":[153.200042725,-27.533285141],"type":"Point"}
}