{
  "type": "Feature",
  "properties": {
    "addr:full":"20 Hayman Rd Bentley WA 6102",
    "addr:housenumber":"20",
    "addr:postcode":"6102",
    "addr:street":"Hayman Rd",
    "iso:country":"AU",
    "sg:address":"20 Hayman Rd",
    "sg:city":"Bentley",
    "sg:classifiers":[
        {
            "category":"Farming",
            "subcategory":"Livestock Farm",
            "type":"Manufacturing & Wholesale Goods"
        }
    ],
    "sg:phone":"+61 8 9361 9962",
    "sg:postcode":"6102",
    "sg:province":"WA",
    "sg:tags":[
        "school",
        "theological"
    ],
    "wof:name":"Baptist Theological College Of WA",
    "wof:placetype":"venue"
},
  "geometry": {"coordinates":[115.89642334,-32.0037841797],"type":"Point"}
}