{
  "type": "Feature",
  "properties": {
    "addr:full":"798 Marion Rd Marion SA 5043",
    "addr:housenumber":"798",
    "addr:postcode":"5043",
    "addr:street":"Marion Rd",
    "iso:country":"AU",
    "sg:address":"798 Marion Rd",
    "sg:city":"Marion",
    "sg:classifiers":[
        {
            "category":"Autos & Motor Vehicles",
            "subcategory":"Auto Supplies",
            "type":"Retail Goods"
        }
    ],
    "sg:phone":"+61 8 8298 5963",
    "sg:postcode":"5043",
    "sg:province":"SA",
    "sg:tags":[
        "part",
        "cycles",
        "accessory"
    ],
    "wof:name":"Ardill Engineering",
    "wof:placetype":"venue"
},
  "geometry": {"coordinates":[138.558075,-35.00935],"type":"Point"}
}