{
  "type": "Feature",
  "properties": {
    "iso:country":"AU",
    "sg:address":"17 Bloomfield St",
    "sg:city":"Winton",
    "sg:classifiers":[
        {
            "category":"Farming",
            "subcategory":"Farm & Veterinary Services",
            "type":"Manufacturing & Wholesale Goods"
        }
    ],
    "sg:phone":"+61 7 4657 1350",
    "sg:postcode":"4735",
    "sg:province":"QLD",
    "sg:tags":[
        "shearing",
        "contractor"
    ],
    "wof:name":"Elliott P A",
    "wof:placetype":"venue"
},
  "geometry": {"coordinates":[143.040527,-22.391609],"type":"Point"}
}