{
  "type": "Feature",
  "properties": {
    "addr:full":"75 Northgate Drv Thomastown VIC 3074",
    "addr:housenumber":"75",
    "addr:postcode":"3074",
    "addr:street":"Northgate Drv",
    "iso:country":"AU",
    "sg:address":"75 Northgate Drv",
    "sg:city":"Thomastown",
    "sg:classifiers":[
        {
            "category":"Wholesale",
            "subcategory":"Machinery & Supplies",
            "type":"Manufacturing & Wholesale Goods"
        }
    ],
    "sg:phone":"+61 3 9464 0222",
    "sg:postcode":"3074",
    "sg:province":"VIC",
    "sg:tags":[
        "equipment",
        "hydraulic"
    ],
    "wof:name":"Bosch Hydraulic Systems Pty Ltd",
    "wof:placetype":"venue"
},
  "geometry": {"coordinates":[145.03457641599999,-37.6887054443],"type":"Point"}
}