{
  "type": "Feature",
  "properties": {
    "iso:country":"AU",
    "sg:address":"194 Milperra Rd",
    "sg:city":"Revesby",
    "sg:classifiers":[
        {
            "category":"Building & Trades",
            "subcategory":"Plumbing",
            "type":"Services"
        }
    ],
    "sg:phone":"+61 2 9772 0166",
    "sg:postcode":"2212",
    "sg:province":"NSW",
    "sg:tags":[
        "sink"
    ],
    "wof:name":"Email Kitchen & Bathroom Products Pty Ltd",
    "wof:placetype":"venue"
},
  "geometry": {"coordinates":[151.024338,-33.935436],"type":"Point"}
}