{
  "type": "Feature",
  "properties": {
    "addr:full":"25 Amax Ave Girraween NSW 2145",
    "addr:housenumber":"25",
    "addr:postcode":"2145",
    "addr:street":"Amax Ave",
    "iso:country":"AU",
    "sg:address":"25 Amax Ave",
    "sg:city":"Girraween",
    "sg:classifiers":[
        {
            "category":"Fast Food",
            "type":"Food & Drink"
        }
    ],
    "sg:phone":"+61 2 9631 4187",
    "sg:postcode":"2145",
    "sg:province":"NSW",
    "sg:tags":[
        "away",
        "take"
    ],
    "wof:name":"Matildas Food Bar",
    "wof:placetype":"venue"
},
  "geometry": {"coordinates":[150.93731689399999,-33.8054695129],"type":"Point"}
}