{
  "type": "Feature",
  "properties": {
    "addr:full":"34 O&#039;Loughlin Rd Valley View SA 5093",
    "addr:housenumber":"34",
    "addr:postcode":"5093",
    "addr:street":"O &;Loughlin Rd",
    "iso:country":"AU",
    "sg:address":"34 O&#039;Loughlin Rd",
    "sg:city":"Valley View",
    "sg:classifiers":[
        {
            "category":"Personal",
            "type":"Services"
        }
    ],
    "sg:phone":"+61 8 8261 7535",
    "sg:postcode":"5093",
    "sg:province":"SA",
    "sg:tags":[
        "reducing",
        "treatment",
        "weight"
    ],
    "wof:name":"Herbalife Australasia - Independent Distributor",
    "wof:placetype":"venue"
},
  "geometry": {"coordinates":[138.65208435100001,-34.8418807983],"type":"Point"}
}