{
  "type": "Feature",
  "properties": {
    "addr:full":"1336-1340 Centre Rd (Cnr Clayton Rd) Clayton VIC 3168",
    "addr:housenumber":"1336-1340",
    "addr:postcode":"3168",
    "addr:street":"Centre Rd Cnr Clayton Rd",
    "iso:country":"AU",
    "sg:address":"1336-1340 Centre Rd (Cnr Clayton Rd)",
    "sg:city":"Clayton",
    "sg:classifiers":[
        {
            "category":"Manufacturing",
            "subcategory":"Furniture",
            "type":"Manufacturing & Wholesale Goods"
        }
    ],
    "sg:phone":"+61 3 9544 6904",
    "sg:postcode":"3168",
    "sg:province":"VIC",
    "sg:tags":[
        "builder",
        "designer",
        "custom"
    ],
    "wof:name":"Inmode Furniture",
    "wof:placetype":"venue"
},
  "geometry": {"coordinates":[145.11947631800001,-37.9287109375],"type":"Point"}
}