{
  "type": "Feature",
  "properties": {
    "addr:full":"6 South Cncrse Beaumaris VIC 3193",
    "addr:housenumber":"6",
    "addr:postcode":"3193",
    "addr:street":"South Cncrse",
    "iso:country":"AU",
    "sg:address":"6 South Cncrse",
    "sg:city":"Beaumaris",
    "sg:classifiers":[
        {
            "category":"Food & Beverages",
            "subcategory":"Supermarket",
            "type":"Retail Goods"
        }
    ],
    "sg:phone":"+61 3 9589 5100",
    "sg:postcode":"3193",
    "sg:province":"VIC",
    "sg:tags":[
        "grocery",
        "store"
    ],
    "wof:name":"Beaumaris IGA",
    "wof:placetype":"venue"
},
  "geometry": {"coordinates":[145.05137634299999,-37.9860687256],"type":"Point"}
}