{
  "type": "Feature",
  "properties": {
    "addr:full":"276- 282 Ballarat Rd Footscray VIC 3011",
    "addr:housenumber":"282",
    "addr:postcode":"3011",
    "addr:street":"Ballarat Rd",
    "iso:country":"AU",
    "sg:address":"276- 282 Ballarat Rd",
    "sg:city":"Footscray",
    "sg:classifiers":[
        {
            "category":"Home & Garden",
            "subcategory":"Building Materials",
            "type":"Retail Goods"
        }
    ],
    "sg:phone":"+61 13 38 80",
    "sg:postcode":"3011",
    "sg:province":"VIC",
    "sg:tags":[
        "fitting",
        "door"
    ],
    "wof:name":"Doors Plus",
    "wof:placetype":"venue"
},
  "geometry": {"coordinates":[144.883575439,-37.7885780334],"type":"Point"}
}