{
  "type": "Feature",
  "properties": {
    "iso:country":"AU",
    "sg:address":"Canberra Technology Park - 49 Phillip Ave",
    "sg:city":"Watson",
    "sg:classifiers":[
        {
            "category":"Education",
            "subcategory":"Vocational School",
            "type":"Public Place"
        }
    ],
    "sg:phone":"+61 2 6163 9590",
    "sg:postcode":"2602",
    "sg:province":"ACT",
    "sg:tags":[
        "beauty"
    ],
    "wof:name":"Canberra MakeUp Academy",
    "wof:placetype":"venue"
},
  "geometry": {"coordinates":[149.14959716800001,-35.2407798767],"type":"Point"}
}