{
  "type": "Feature",
  "properties": {
    "addr:full":"3 Winchester Rd Bibra Lake WA 6163",
    "addr:housenumber":"3",
    "addr:postcode":"6163",
    "addr:street":"Winchester Rd",
    "iso:country":"AU",
    "sg:address":"3 Winchester Rd",
    "sg:city":"Bibra Lake",
    "sg:classifiers":[
        {
            "category":"Building & Trades",
            "subcategory":"Construction",
            "type":"Services"
        }
    ],
    "sg:phone":"+61 1300 888 522",
    "sg:postcode":"6163",
    "sg:province":"WA",
    "sg:tags":[
        "insulation",
        "contractor"
    ],
    "sg:website":"http://www.superbceilings.com.au",
    "wof:name":"Superb Insulation",
    "wof:placetype":"venue"
},
  "geometry": {"coordinates":[115.798637,-32.111137],"type":"Point"}
}