{
  "type": "Feature",
  "properties": {
    "iso:country":"AU",
    "sg:address":"7 Bronwyn St",
    "sg:city":"Caloundra",
    "sg:classifiers":[
        {
            "category":"Building & Trades",
            "subcategory":"Construction",
            "type":"Services"
        }
    ],
    "sg:phone":"+61 7 5491 9550",
    "sg:postcode":"4551",
    "sg:province":"QLD",
    "sg:tags":[
        "fencing",
        "contractor"
    ],
    "wof:name":"Tom Crerar Fences",
    "wof:placetype":"venue"
},
  "geometry": {"coordinates":[153.11126709000001,-26.7939720154],"type":"Point"}
}