{
  "type": "Feature",
  "properties": {
    "iso:country":"AU",
    "sg:address":"38 Bevan St",
    "sg:city":"Northmead",
    "sg:classifiers":[
        {
            "category":"Professional",
            "subcategory":"Business Services",
            "type":"Services"
        }
    ],
    "sg:phone":"+61 2 9630 0035",
    "sg:postcode":"2152",
    "sg:province":"NSW",
    "sg:tags":[
        "drafting"
    ],
    "wof:name":"Crickmay W D Geological Drafting",
    "wof:placetype":"venue"
},
  "geometry": {"coordinates":[150.99465942399999,-33.7981758118],"type":"Point"}
}