{
  "type": "Feature",
  "properties": {
    "addr:full":"66 Burdoo Drv Grovedale VIC 3216",
    "addr:housenumber":"66",
    "addr:postcode":"3216",
    "addr:street":"Burdoo Drv",
    "iso:country":"AU",
    "sg:address":"66 Burdoo Drv",
    "sg:city":"Grovedale",
    "sg:classifiers":[
        {
            "category":"Professional",
            "subcategory":"Employment Agencies",
            "type":"Services"
        }
    ],
    "sg:phone":"+61 3 5243 2422",
    "sg:postcode":"3216",
    "sg:province":"VIC",
    "sg:tags":[
        "provider",
        "internet"
    ],
    "wof:name":"Gee Web Advertising",
    "wof:placetype":"venue"
},
  "geometry": {"coordinates":[144.331375122,-38.2009963989],"type":"Point"}
}