{
  "type": "Feature",
  "properties": {
    "addr:full":"4 Kelly St Atherton QLD 4883",
    "addr:housenumber":"4",
    "addr:postcode":"4883",
    "addr:street":"Kelly St",
    "iso:country":"AU",
    "sg:address":"4 Kelly St",
    "sg:city":"Atherton",
    "sg:classifiers":[
        {
            "category":"Building & Trades",
            "subcategory":"Construction",
            "type":"Services"
        }
    ],
    "sg:phone":"+61 7 4091 2298",
    "sg:postcode":"4883",
    "sg:province":"QLD",
    "sg:tags":[
        "contractor"
    ],
    "wof:name":"Knight D & B",
    "wof:placetype":"venue"
},
  "geometry": {"coordinates":[145.48541259800001,-17.2600688934],"type":"Point"}
}