{
  "type": "Feature",
  "properties": {
    "addr:full":"Suite 8/ 100 Murdoch Drv Murdoch WA 6150",
    "addr:housenumber":"/ 100",
    "addr:postcode":"6150",
    "addr:street":"Murdoch Drv",
    "iso:country":"AU",
    "sg:address":"Suite 8/ 100 Murdoch Drv",
    "sg:city":"Murdoch",
    "sg:classifiers":[
        {
            "category":"Health Services",
            "subcategory":"Doctor",
            "type":"Services"
        }
    ],
    "sg:phone":"+61 8 9391 1178",
    "sg:postcode":"6150",
    "sg:province":"WA",
    "sg:tags":[
        "medical",
        "practitioner"
    ],
    "wof:name":"Deague Jenny Dr",
    "wof:placetype":"venue"
},
  "geometry": {"coordinates":[115.84223900000001,-32.068344],"type":"Point"}
}