{
  "type": "Feature",
  "properties": {
    "iso:country":"AU",
    "sg:address":"Unit 1, 7 Hitech Pl",
    "sg:city":"Rowville",
    "sg:classifiers":[
        {
            "category":"Wholesale",
            "subcategory":"Non-durable Goods",
            "type":"Manufacturing & Wholesale Goods"
        }
    ],
    "sg:phone":"+61 3 9764 9577",
    "sg:postcode":"3178",
    "sg:province":"VIC",
    "sg:tags":[
        "wholesaler",
        "mfrs",
        "elastic"
    ],
    "wof:name":"Girflex-VXL Pty Limited",
    "wof:placetype":"venue"
},
  "geometry": {"coordinates":[145.245849609,-37.9107208252],"type":"Point"}
}