{
  "type": "Feature",
  "properties": {
    "addr:full":"PO Box 4322 Gosford East NSW 2250",
    "addr:postcode":"2250",
    "iso:country":"AU",
    "sg:address":"PO Box 4322",
    "sg:city":"Gosford East",
    "sg:classifiers":[
        {
            "category":"Health Services",
            "subcategory":"Health Practitioner",
            "type":"Services"
        }
    ],
    "sg:phone":"+61 1800 811 360",
    "sg:postcode":"2250",
    "sg:province":"NSW",
    "sg:tags":[
        "hypnotherapy"
    ],
    "wof:name":"Insight To Solutions",
    "wof:placetype":"venue"
},
  "geometry": {"coordinates":[151.32798767099999,-33.4495162964],"type":"Point"}
}