{
  "type": "Feature",
  "properties": {
    "addr:full":"108 Windsor Rd Wangara WA 6065",
    "addr:housenumber":"108",
    "addr:postcode":"6065",
    "addr:street":"Windsor Rd",
    "iso:country":"AU",
    "sg:address":"108 Windsor Rd",
    "sg:city":"Wangara",
    "sg:classifiers":[
        {
            "category":"Manufacturing",
            "subcategory":"Tools & Machinery",
            "type":"Manufacturing & Wholesale Goods"
        }
    ],
    "sg:phone":"+61 8 9409 2648",
    "sg:postcode":"6065",
    "sg:province":"WA",
    "sg:tags":[
        "earth",
        "excavating",
        "moving",
        "equipment"
    ],
    "wof:name":"As Works",
    "wof:placetype":"venue"
},
  "geometry": {"coordinates":[115.825439453,-31.7947902679],"type":"Point"}
}