{
  "type": "Feature",
  "properties": {
    "addr:full":"4/ 72 Hallam South Rd Hallam VIC 3803",
    "addr:housenumber":"/ 72",
    "addr:postcode":"3803",
    "addr:street":"South Rd",
    "iso:country":"AU",
    "sg:address":"4/ 72 Hallam South Rd",
    "sg:city":"Hallam",
    "sg:classifiers":[
        {
            "category":"Banks & Credit Unions",
            "subcategory":"Investment Brokerage",
            "type":"Services"
        }
    ],
    "sg:phone":"+61 3 9796 5602",
    "sg:postcode":"3803",
    "sg:province":"VIC",
    "sg:tags":[
        "paint",
        "supply",
        "removal"
    ],
    "wof:name":"Top Coat Pty Ltd",
    "wof:placetype":"venue"
},
  "geometry": {"coordinates":[145.27146911599999,-38.0156784058],"type":"Point"}
}