{
  "type": "Feature",
  "properties": {
    "addr:full":"Unit 2/ 17 Hook St Capalaba QLD 4157",
    "addr:housenumber":"17",
    "addr:postcode":"4157",
    "addr:street":"Hook St",
    "iso:country":"AU",
    "sg:address":"Unit 2/ 17 Hook St",
    "sg:city":"Capalaba",
    "sg:classifiers":[
        {
            "category":"Manufacturing",
            "subcategory":"Electronics",
            "type":"Manufacturing & Wholesale Goods"
        }
    ],
    "sg:phone":"+61 7 3823 4026",
    "sg:postcode":"4157",
    "sg:province":"QLD",
    "sg:tags":[
        "wholesaler",
        "equipment",
        "part",
        "mfrs",
        "refrigeration"
    ],
    "wof:name":"Koldpak Pty Ltd",
    "wof:placetype":"venue"
},
  "geometry": {"coordinates":[153.20208740199999,-27.5303535461],"type":"Point"}
}