{
  "type": "Feature",
  "properties": {
    "addr:full":"188 Main Rd Blackwood SA 5051",
    "addr:housenumber":"188",
    "addr:postcode":"5051",
    "addr:street":"Main Rd",
    "iso:country":"AU",
    "sg:address":"188 Main Rd",
    "sg:city":"Blackwood",
    "sg:classifiers":[
        {
            "category":"Utilities",
            "type":"Services"
        }
    ],
    "sg:phone":"+61 8 8370 3111",
    "sg:postcode":"5051",
    "sg:province":"SA",
    "sg:tags":[
        "refrigeration",
        "industrial",
        "commercial",
        "retail"
    ],
    "sg:website":"http://www.simsrefrig.com.au",
    "wof:name":"Sims John R & Co Pty Ltd",
    "wof:placetype":"venue"
},
  "geometry": {"coordinates":[138.617065,-35.015522],"type":"Point"}
}