{
  "type": "Feature",
  "properties": {
    "addr:full":"2056 Wanneroo Rd Neerabup WA 6031",
    "addr:housenumber":"2056",
    "addr:postcode":"6031",
    "addr:street":"Wanneroo Rd",
    "iso:country":"AU",
    "sg:address":"2056 Wanneroo Rd",
    "sg:city":"Neerabup",
    "sg:classifiers":[
        {
            "category":"Fast Food",
            "type":"Food & Drink"
        }
    ],
    "sg:phone":"+61 8 9407 5091",
    "sg:postcode":"6031",
    "sg:province":"WA",
    "sg:tags":[
        "away",
        "take"
    ],
    "wof:name":"Neerabup Pizza",
    "wof:placetype":"venue"
},
  "geometry": {"coordinates":[115.741851807,-31.6714477539],"type":"Point"}
}