{
  "type": "Feature",
  "properties": {
    "addr:full":"856 Military Rd Mosman NSW 2088",
    "addr:housenumber":"856",
    "addr:postcode":"2088",
    "addr:street":"Military Rd",
    "iso:country":"AU",
    "sg:address":"856 Military Rd",
    "sg:city":"Mosman",
    "sg:classifiers":[
        {
            "category":"Health Services",
            "subcategory":"Optometrist",
            "type":"Services"
        }
    ],
    "sg:phone":"+61 2 9960 2700",
    "sg:postcode":"2088",
    "sg:province":"NSW",
    "wof:name":"Eyecare Plus Associated Optometrists",
    "wof:placetype":"venue"
},
  "geometry": {"coordinates":[151.244262695,-33.8293800354],"type":"Point"}
}