{
  "type": "Feature",
  "properties": {
    "addr:full":"Unit 3, 10 Fortune St Geebung QLD 4034",
    "addr:housenumber":"10",
    "addr:postcode":"4034",
    "addr:street":"Fortune St",
    "iso:country":"AU",
    "sg:address":"Unit 3, 10 Fortune St",
    "sg:city":"Geebung",
    "sg:classifiers":[
        {
            "category":"Home & Garden",
            "subcategory":"Hardware",
            "type":"Retail Goods"
        }
    ],
    "sg:phone":"+61 7 3865 5666",
    "sg:postcode":"4034",
    "sg:province":"QLD",
    "sg:tags":[
        "compressor",
        "air"
    ],
    "wof:name":"Gardner Denver Australia P/L",
    "wof:placetype":"venue"
},
  "geometry": {"coordinates":[153.04714999999999,-27.36548],"type":"Point"}
}