{
  "type": "Feature",
  "properties": {
    "addr:full":"Unit 10/ 1 Bell St Preston VIC 3072",
    "addr:housenumber":"/ 1",
    "addr:postcode":"3072",
    "addr:street":"Bell St",
    "iso:country":"AU",
    "sg:address":"Unit 10/ 1 Bell St",
    "sg:city":"Preston",
    "sg:classifiers":[
        {
            "category":"Home & Garden",
            "subcategory":"Household Appliances",
            "type":"Retail Goods"
        }
    ],
    "sg:phone":"+61 3 9484 1490",
    "sg:postcode":"3072",
    "sg:province":"VIC",
    "sg:tags":[
        "equipment",
        "gas"
    ],
    "wof:name":"Niche Gas Products Pty Ltd",
    "wof:placetype":"venue"
},
  "geometry": {"coordinates":[145.030807495,-37.7485809326],"type":"Point"}
}