{
  "type": "Feature",
  "properties": {
    "addr:full":"Fulcher Rd Red Hill QLD 4059",
    "addr:postcode":"4059",
    "addr:street":"Fulcher Rd",
    "iso:country":"AU",
    "sg:address":"Fulcher Rd",
    "sg:city":"Red Hill",
    "sg:classifiers":[
        {
            "category":"Professional",
            "subcategory":"Management & Consulting",
            "type":"Services"
        }
    ],
    "sg:phone":"+61 7 3259 9072",
    "sg:postcode":"4059",
    "sg:province":"QLD",
    "sg:tags":[
        "consultant",
        "energy"
    ],
    "wof:name":"Solar Energy Society (ANZSES)",
    "wof:placetype":"venue"
},
  "geometry": {"coordinates":[152.99708557100001,-27.4465465546],"type":"Point"}
}