{
  "type": "Feature",
  "properties": {
    "addr:full":"Sandon St Brewarrina NSW 2839",
    "addr:postcode":"2839",
    "addr:street":"Sandon St",
    "iso:country":"AU",
    "sg:address":"Sandon St",
    "sg:city":"Brewarrina",
    "sg:classifiers":[
        {
            "category":"Social Services",
            "subcategory":"Child Care",
            "type":"Services"
        }
    ],
    "sg:phone":"+61 2 6839 2428",
    "sg:postcode":"2839",
    "sg:province":"NSW",
    "wof:name":"Brewarrina Mobile Resource Van",
    "wof:placetype":"venue"
},
  "geometry": {"coordinates":[146.85730000000001,-29.959736],"type":"Point"}
}