{
  "type": "Feature",
  "properties": {
    "iso:country":"AU",
    "sg:address":"190 Foster St",
    "sg:city":"East Dandenong",
    "sg:classifiers":[
        {
            "category":"Health Services",
            "subcategory":"Dentist",
            "type":"Services"
        }
    ],
    "sg:phone":"+61 3 9791 6230",
    "sg:postcode":"3175",
    "sg:province":"VIC",
    "wof:name":"Varughese Jacob",
    "wof:placetype":"venue"
},
  "geometry": {"coordinates":[145.22120666500001,-37.98695755],"type":"Point"}
}