{
  "type": "Feature",
  "properties": {
    "addr:full":"Cnr Mansell & Eyers Sts Toowoomba QLD 4350",
    "addr:postcode":"4350",
    "addr:street":"Cnr",
    "iso:country":"AU",
    "sg:address":"Cnr Mansell & Eyers Sts",
    "sg:city":"Toowoomba",
    "sg:classifiers":[
        {
            "category":"Autos & Motor Vehicles",
            "subcategory":"Automobile Sales",
            "type":"Retail Goods"
        }
    ],
    "sg:phone":"+61 7 4633 3222",
    "sg:postcode":"4350",
    "sg:province":"QLD",
    "sg:tags":[
        "car",
        "used"
    ],
    "wof:name":"Mansell Street Used Cars",
    "wof:placetype":"venue"
},
  "geometry": {"coordinates":[151.91012599999999,-27.548975],"type":"Point"}
}