{
  "type": "Feature",
  "properties": {
    "addr:full":"172 High St Kew VIC 3101",
    "addr:housenumber":"172",
    "addr:postcode":"3101",
    "addr:street":"High St",
    "iso:country":"AU",
    "sg:address":"172 High St",
    "sg:city":"Kew",
    "sg:classifiers":[
        {
            "category":"Shopping",
            "subcategory":"Jewelry",
            "type":"Retail Goods"
        }
    ],
    "sg:phone":"+61 3 9853 8237",
    "sg:postcode":"3101",
    "sg:province":"VIC",
    "sg:tags":[
        "jeweller"
    ],
    "wof:name":"Sparkles Fine Jewellery",
    "wof:placetype":"venue"
},
  "geometry": {"coordinates":[145.03045654300001,-37.8070411682],"type":"Point"}
}