{
  "type": "Feature",
  "properties": {
    "addr:full":"Cnr Morphett & Hutchinson Sts Mt Barker SA 5251",
    "addr:postcode":"5251",
    "addr:street":"Cnr;Sts Mt",
    "iso:country":"AU",
    "sg:address":"Cnr Morphett & Hutchinson Sts",
    "sg:city":"Mt Barker",
    "sg:classifiers":[
        {
            "category":"Retail",
            "subcategory":"Repair Shop",
            "type":"Services"
        }
    ],
    "sg:phone":"+61 8 8398 2422",
    "sg:postcode":"5251",
    "sg:province":"SA",
    "sg:tags":[
        "windscreen"
    ],
    "wof:name":"Adelaide Hills Windscreens",
    "wof:placetype":"venue"
},
  "geometry": {"coordinates":[138.856491089,-35.0665359497],"type":"Point"}
}