{
  "type": "Feature",
  "properties": {
    "addr:full":"Shop 6 Howick St Bathurst City Centre Bathurst NSW 2795",
    "addr:housenumber":"shop 6",
    "addr:postcode":"2795",
    "addr:street":"Howick St",
    "iso:country":"AU",
    "sg:address":"Shop 6 Howick St Bathurst City Centre",
    "sg:city":"Bathurst",
    "sg:classifiers":[
        {
            "category":"Shopping",
            "subcategory":"Jewelry",
            "type":"Retail Goods"
        }
    ],
    "sg:phone":"+61 2 6331 5241",
    "sg:postcode":"2795",
    "sg:province":"NSW",
    "sg:tags":[
        "jeweller"
    ],
    "wof:name":"Goldmark Jewellers",
    "wof:placetype":"venue"
},
  "geometry": {"coordinates":[149.573028564,-33.4083480835],"type":"Point"}
}