{
  "type": "Feature",
  "properties": {
    "addr:full":"3 Waldron Rd Sefton NSW 2162",
    "addr:housenumber":"3",
    "addr:postcode":"2162",
    "addr:street":"Waldron Rd",
    "iso:country":"AU",
    "sg:address":"3 Waldron Rd",
    "sg:city":"Sefton",
    "sg:classifiers":[
        {
            "category":"Professional",
            "subcategory":"Accounting & Tax Preparation",
            "type":"Services"
        }
    ],
    "sg:phone":"+61 2 9743 9500",
    "sg:postcode":"2162",
    "sg:province":"NSW",
    "sg:tags":[
        "consultant",
        "taxation"
    ],
    "wof:name":"Tax Professionals & Associates Pty Ltd",
    "wof:placetype":"venue"
},
  "geometry": {"coordinates":[151.01075744600001,-33.8843688965],"type":"Point"}
}