{
  "type": "Feature",
  "properties": {
    "addr:full":"10 College Rd Karana Downs QLD 4306",
    "addr:housenumber":"10",
    "addr:postcode":"4306",
    "addr:street":"College Rd",
    "iso:country":"AU",
    "sg:address":"10 College Rd",
    "sg:city":"Karana Downs",
    "sg:classifiers":[
        {
            "category":"Health Services",
            "subcategory":"Health Practitioner",
            "type":"Services"
        }
    ],
    "sg:phone":"+61 7 3201 1022",
    "sg:postcode":"4306",
    "sg:province":"QLD",
    "sg:tags":[
        "physiotherapist"
    ],
    "wof:name":"Chong Anna",
    "wof:placetype":"venue"
},
  "geometry": {"coordinates":[152.807662964,-27.5526065826],"type":"Point"}
}