{
  "type": "Feature",
  "properties": {
    "addr:full":"21 Bridge St North Lismore NSW 2480",
    "addr:housenumber":"21",
    "addr:postcode":"2480",
    "addr:street":"Bridge St North",
    "iso:country":"AU",
    "sg:address":"21 Bridge St",
    "sg:city":"North Lismore",
    "sg:classifiers":[
        {
            "category":"Sports & Exercise",
            "subcategory":"Sports Center",
            "type":"Entertainment"
        }
    ],
    "sg:phone":"+61 2 6621 6565",
    "sg:postcode":"2480",
    "sg:province":"NSW",
    "sg:tags":[
        "ground"
    ],
    "wof:name":"Lismore Skating & Putt Putt",
    "wof:placetype":"venue"
},
  "geometry": {"coordinates":[153.275299072,-28.804271698],"type":"Point"}
}