{
  "type": "Feature",
  "properties": {
    "addr:full":"2/ 67 Magnus St Nelson Bay NSW 2315",
    "addr:housenumber":"/ 67",
    "addr:postcode":"2315",
    "addr:street":"Magnus St",
    "iso:country":"AU",
    "sg:address":"2/ 67 Magnus St",
    "sg:city":"Nelson Bay",
    "sg:classifiers":[
        {
            "category":"Banks & Credit Unions",
            "subcategory":"Bank",
            "type":"Services"
        }
    ],
    "sg:phone":"+61 2 4981 5766",
    "sg:postcode":"2315",
    "sg:province":"NSW",
    "sg:tags":[
        "broker",
        "mortgage"
    ],
    "wof:name":"Capital Trust",
    "wof:placetype":"venue"
},
  "geometry": {"coordinates":[152.14511100000001,-32.721561],"type":"Point"}
}