{
  "type": "Feature",
  "properties": {
    "addr:full":"25 Kenneth Crt Hazelwood North VIC 3840",
    "addr:housenumber":"25",
    "addr:postcode":"3840",
    "addr:street":"Kenneth Crt",
    "iso:country":"AU",
    "sg:address":"25 Kenneth Crt",
    "sg:city":"Hazelwood North",
    "sg:classifiers":[
        {
            "category":"Farming",
            "subcategory":"Farm & Veterinary Services",
            "type":"Manufacturing & Wholesale Goods"
        }
    ],
    "sg:phone":"+61 3 5166 1715",
    "sg:postcode":"3840",
    "sg:province":"VIC",
    "sg:tags":[
        "blacksmith",
        "farrier"
    ],
    "wof:name":"Richard Farrar",
    "wof:placetype":"venue"
},
  "geometry": {"coordinates":[146.456832886,-38.2487068176],"type":"Point"}
}