{
  "type": "Feature",
  "properties": {
    "iso:country":"AU",
    "sg:address":"14 Slater Pde",
    "sg:city":"Keilor East",
    "sg:classifiers":[
        {
            "category":"Building & Trades",
            "subcategory":"Plumbing",
            "type":"Services"
        }
    ],
    "sg:phone":"+61 3 9331 6900",
    "sg:postcode":"3033",
    "sg:province":"VIC",
    "sg:tags":[
        "repair",
        "appliance",
        "system",
        "heating"
    ],
    "wof:name":"Optima Heating Air Conditioning Pty. Ltd.",
    "wof:placetype":"venue"
},
  "geometry": {"coordinates":[144.854141,-37.735558],"type":"Point"}
}