{
  "type": "Feature",
  "properties": {
    "addr:full":"2 first St Murray Bridge SA 5253",
    "addr:housenumber":"2",
    "addr:postcode":"5253",
    "addr:street":"First St",
    "iso:country":"AU",
    "sg:address":"2 first St",
    "sg:city":"Murray Bridge",
    "sg:classifiers":[
        {
            "category":"Cinema",
            "subcategory":"Movie Theater",
            "type":"Entertainment"
        }
    ],
    "sg:phone":"+61 8 8531 0222",
    "sg:postcode":"5253",
    "sg:province":"SA",
    "wof:name":"Cameo Cinema",
    "wof:placetype":"venue"
},
  "geometry": {"coordinates":[139.272018433,-35.1176185608],"type":"Point"}
}