{
  "type": "Feature",
  "properties": {
    "iso:country":"AU",
    "sg:address":"53 Isabella St",
    "sg:city":"Wingham",
    "sg:classifiers":[
        {
            "category":"Health Services",
            "subcategory":"Dentist",
            "type":"Services"
        }
    ],
    "sg:phone":"+61 2 6553 5062",
    "sg:postcode":"2429",
    "sg:province":"NSW",
    "sg:tags":[
        "technician",
        "dental"
    ],
    "wof:name":"Wingham Denture Clinic",
    "wof:placetype":"venue"
},
  "geometry": {"coordinates":[152.37489299999999,-31.868959],"type":"Point"}
}