{
  "type": "Feature",
  "properties": {
    "addr:full":"11 Channon St Port Elliot SA 5212",
    "addr:housenumber":"11",
    "addr:postcode":"5212",
    "addr:street":"Channon St",
    "iso:country":"AU",
    "sg:address":"11 Channon St",
    "sg:city":"Port Elliot",
    "sg:classifiers":[
        {
            "category":"Building & Trades",
            "subcategory":"Cleaning & Sanitation",
            "type":"Services"
        }
    ],
    "sg:phone":"+61 8 8554 2451",
    "sg:postcode":"5212",
    "sg:province":"SA",
    "sg:tags":[
        "chemical",
        "pressure",
        "steam",
        "contractor"
    ],
    "wof:name":"South Coast Commercial Cleaners",
    "wof:placetype":"venue"
},
  "geometry": {"coordinates":[138.666107178,-35.5337677002],"type":"Point"}
}