{
  "type": "Feature",
  "properties": {
    "iso:country":"AU",
    "sg:address":"Shop 4/ 1 Aldinga Rd",
    "sg:city":"Willunga",
    "sg:classifiers":[
        {
            "category":"Fast Food",
            "type":"Food & Drink"
        }
    ],
    "sg:phone":"+61 8 8556 2290",
    "sg:postcode":"5172",
    "sg:province":"SA",
    "sg:tags":[
        "away",
        "take"
    ],
    "wof:name":"Willunga Take Away",
    "wof:placetype":"venue"
},
  "geometry": {"coordinates":[138.55406189000001,-35.2718772888],"type":"Point"}
}