{
  "type": "Feature",
  "properties": {
    "iso:country":"AU",
    "sg:address":"PO Box 559",
    "sg:city":"Hazelbrook",
    "sg:classifiers":[
        {
            "category":"Professional",
            "subcategory":"Detective & Security Services",
            "type":"Services"
        }
    ],
    "sg:phone":"+61 2 4759 3722",
    "sg:postcode":"2779",
    "sg:province":"NSW",
    "sg:tags":[
        "consultant",
        "laser"
    ],
    "wof:name":"Hunt Lasercut",
    "wof:placetype":"venue"
},
  "geometry": {"coordinates":[150.45307922399999,-33.7224311829],"type":"Point"}
}