{
  "type": "Feature",
  "properties": {
    "addr:full":"148 Wallandra Rd Mudgeeraba QLD 4213",
    "addr:housenumber":"148",
    "addr:postcode":"4213",
    "addr:street":"Wallandra Rd",
    "iso:country":"AU",
    "sg:address":"148 Wallandra Rd",
    "sg:city":"Mudgeeraba",
    "sg:classifiers":[
        {
            "category":"Social Services",
            "subcategory":"Child Care",
            "type":"Services"
        }
    ],
    "sg:phone":"+61 7 5530 4513",
    "sg:postcode":"4213",
    "sg:province":"QLD",
    "wof:name":"Baxter Bears Pre-School & Early Learning Centre",
    "wof:placetype":"venue"
},
  "geometry": {"coordinates":[153.345535278,-28.0806865692],"type":"Point"}
}