{
  "type": "Feature",
  "properties": {
    "addr:full":"PO Box 460 Mermaid Beach QLD 4218",
    "addr:postcode":"4218",
    "iso:country":"AU",
    "sg:address":"PO Box 460",
    "sg:city":"Mermaid Beach",
    "sg:classifiers":[
        {
            "category":"Home & Garden",
            "subcategory":"Garden Supply",
            "type":"Retail Goods"
        }
    ],
    "sg:phone":"+61 437 295 893",
    "sg:postcode":"4218",
    "sg:province":"QLD",
    "sg:tags":[
        "statuary",
        "fountains",
        "sundial"
    ],
    "wof:name":"Pond Squad",
    "wof:placetype":"venue"
},
  "geometry": {"coordinates":[153.432037353,-28.0367908478],"type":"Point"}
}