{
  "type": "Feature",
  "properties": {
    "addr:full":"18 Menmuir St Winnellie NT 0820",
    "addr:housenumber":"18",
    "addr:postcode":"nt 0820",
    "addr:street":"Menmuir St",
    "iso:country":"AU",
    "sg:address":"18 Menmuir St",
    "sg:city":"Winnellie",
    "sg:classifiers":[
        {
            "category":"Manufacturing",
            "subcategory":"Electronics",
            "type":"Manufacturing & Wholesale Goods"
        }
    ],
    "sg:phone":"+61 8 8947 1898",
    "sg:postcode":"0820",
    "sg:province":"NT",
    "sg:tags":[
        "oven",
        "microwave"
    ],
    "wof:name":"Mr Vac",
    "wof:placetype":"venue"
},
  "geometry": {"coordinates":[130.878829956,-12.4292058945],"type":"Point"}
}