{
  "type": "Feature",
  "properties": {
    "addr:full":"Suite 4, Level 2, 19 Rundle St Kent Town SA 5067",
    "addr:housenumber":"19",
    "addr:postcode":"5067",
    "addr:street":"Rundle St",
    "iso:country":"AU",
    "sg:address":"Suite 4, Level 2, 19 Rundle St",
    "sg:city":"Kent Town",
    "sg:classifiers":[
        {
            "category":"Shopping",
            "subcategory":"Computers & Home Electronics",
            "type":"Retail Goods"
        }
    ],
    "sg:phone":"+61 8 8363 8733",
    "sg:postcode":"5067",
    "sg:province":"SA",
    "sg:tags":[
        "equipment",
        "multimedia"
    ],
    "wof:name":"Charterhouse Pty Ltd",
    "wof:placetype":"venue"
},
  "geometry": {"coordinates":[138.61677551299999,-34.921169281],"type":"Point"}
}