{
  "type": "Feature",
  "properties": {
    "iso:country":"AU",
    "sg:address":"18 Gleneagles Ave",
    "sg:city":"Tarneit",
    "sg:classifiers":[
        {
            "category":"Retail",
            "subcategory":"Auto Repair",
            "type":"Services"
        }
    ],
    "sg:phone":"+61 418 350 449",
    "sg:postcode":"3029",
    "sg:province":"VIC",
    "sg:tags":[
        "body",
        "motor",
        "trimmer"
    ],
    "wof:name":"Vinyl Welding Services",
    "wof:placetype":"venue"
},
  "geometry": {"coordinates":[144.679855,-37.852726],"type":"Point"}
}