{
  "type": "Feature",
  "properties": {
    "iso:country":"AU",
    "sg:address":"6/ 29 Lamington Tce",
    "sg:city":"Dutton Park",
    "sg:classifiers":[
        {
            "category":"Shopping",
            "subcategory":"Music",
            "type":"Retail Goods"
        }
    ],
    "sg:phone":"+61 7 3844 6090",
    "sg:postcode":"4102",
    "sg:province":"QLD",
    "sg:tags":[
        "instrument",
        "musical"
    ],
    "wof:name":"The Violin Studio",
    "wof:placetype":"venue"
},
  "geometry": {"coordinates":[153.023727417,-27.493227005],"type":"Point"}
}