{
  "type": "Feature",
  "properties": {
    "addr:full":"9-11 Homestead Rd Berwick VIC 3806",
    "addr:housenumber":"9-11",
    "addr:postcode":"3806",
    "addr:street":"Homestead Rd",
    "iso:country":"AU",
    "sg:address":"9-11 Homestead Rd",
    "sg:city":"Berwick",
    "sg:classifiers":[
        {
            "category":"Social Services",
            "subcategory":"Child Care",
            "type":"Services"
        }
    ],
    "sg:phone":"+61 3 9702 2666",
    "sg:postcode":"3806",
    "sg:province":"VIC",
    "wof:name":"Berwick Early Learning Centre",
    "wof:placetype":"venue"
},
  "geometry": {"coordinates":[145.33877563499999,-38.0553817749],"type":"Point"}
}