{
  "type": "Feature",
  "properties": {
    "addr:full":"123 Camberwell Rd Hawthorn East VIC 3123",
    "addr:housenumber":"123",
    "addr:postcode":"3123",
    "addr:street":"Camberwell Rd",
    "iso:country":"AU",
    "sg:address":"123 Camberwell Rd",
    "sg:city":"Hawthorn East",
    "sg:classifiers":[
        {
            "category":"Professional",
            "subcategory":"Accounting & Tax Preparation",
            "type":"Services"
        }
    ],
    "sg:phone":"+61 3 9835 8200",
    "sg:postcode":"3123",
    "sg:province":"VIC",
    "sg:tags":[
        "accountant",
        "auditor"
    ],
    "wof:name":"Farr Ian J",
    "wof:placetype":"venue"
},
  "geometry": {"coordinates":[145.05372619600001,-37.8285064697],"type":"Point"}
}