{
  "type": "Feature",
  "properties": {
    "addr:full":"39 Barry St Bayswater VIC 3153",
    "addr:housenumber":"39",
    "addr:postcode":"3153",
    "addr:street":"Barry St",
    "iso:country":"AU",
    "sg:address":"39 Barry St",
    "sg:city":"Bayswater",
    "sg:classifiers":[
        {
            "category":"Manufacturing",
            "subcategory":"Building Materials",
            "type":"Manufacturing & Wholesale Goods"
        }
    ],
    "sg:phone":"+61 3 9720 7104",
    "sg:postcode":"3153",
    "sg:province":"VIC",
    "sg:tags":[
        "equipment",
        "handling"
    ],
    "wof:name":"Toddco Australia Pty Ltd",
    "wof:placetype":"venue"
},
  "geometry": {"coordinates":[145.277954102,-37.8471755981],"type":"Point"}
}