{
  "type": "Feature",
  "properties": {
    "addr:full":"52 Taylor St Kilcoy QLD 4515",
    "addr:housenumber":"52",
    "addr:postcode":"4515",
    "addr:street":"Taylor St",
    "iso:country":"AU",
    "sg:address":"52 Taylor St",
    "sg:city":"Kilcoy",
    "sg:classifiers":[
        {
            "category":"Social Services",
            "subcategory":"Child Care",
            "type":"Services"
        }
    ],
    "sg:phone":"+61 7 5422 4599",
    "sg:postcode":"4515",
    "sg:province":"QLD",
    "wof:name":"We Rock! Childcare Centre",
    "wof:placetype":"venue"
},
  "geometry": {"coordinates":[152.56272899999999,-26.939451],"type":"Point"}
}