{
  "type": "Feature",
  "properties": {
    "iso:country":"AU",
    "sg:address":"Shellharbour Rd",
    "sg:city":"Kemblawarra",
    "sg:classifiers":[
        {
            "category":"Professional",
            "type":"Services"
        }
    ],
    "sg:phone":"+61 2 4275 1644",
    "sg:postcode":"2505",
    "sg:province":"NSW",
    "sg:tags":[
        "valuer"
    ],
    "wof:name":"South Coast Auctions Pty Ltd",
    "wof:placetype":"venue"
},
  "geometry": {"coordinates":[150.893051,-34.486938],"type":"Point"}
}