{
  "type": "Feature",
  "properties": {
    "addr:full":"14 Bussell Hwy Busselton WA 6280",
    "addr:housenumber":"14",
    "addr:postcode":"6280",
    "addr:street":"Bussell Hwy",
    "iso:country":"AU",
    "sg:address":"14 Bussell Hwy",
    "sg:city":"Busselton",
    "sg:classifiers":[
        {
            "category":"Autos & Motor Vehicles",
            "subcategory":"Auto Supplies",
            "type":"Retail Goods"
        }
    ],
    "sg:phone":"+61 8 9754 1777",
    "sg:postcode":"6280",
    "sg:province":"WA",
    "sg:tags":[
        "tyre"
    ],
    "wof:name":"Geographe Ford",
    "wof:placetype":"venue"
},
  "geometry": {"coordinates":[115.340042114,-33.6532440186],"type":"Point"}
}