{
  "type": "Feature",
  "properties": {
    "addr:full":"Shop 65 a, Erina Fair Erina NSW 2250",
    "addr:housenumber":"shop 65 a",
    "addr:postcode":"2250",
    "iso:country":"AU",
    "sg:address":"Shop 65",
    "sg:city":"a, Erina Fair Erina",
    "sg:classifiers":[
        {
            "category":"Shopping",
            "subcategory":"Mobile Phones",
            "type":"Retail Goods"
        }
    ],
    "sg:phone":"+61 2 4367 7466",
    "sg:postcode":"2250",
    "sg:province":"NSW",
    "sg:tags":[
        "telephone",
        "accessory"
    ],
    "wof:name":"Digicall",
    "wof:placetype":"venue"
},
  "geometry": {"coordinates":[151.347412109,-33.4256591797],"type":"Point"}
}