{
  "type": "Feature",
  "properties": {
    "addr:full":"7 Fourth St Warooka SA 5577",
    "addr:housenumber":"7",
    "addr:postcode":"5577",
    "addr:street":"Fourth St",
    "iso:country":"AU",
    "sg:address":"7 Fourth St",
    "sg:city":"Warooka",
    "sg:classifiers":[
        {
            "category":"Professional",
            "type":"Services"
        }
    ],
    "sg:phone":"+61 8 8854 5071",
    "sg:postcode":"5577",
    "sg:province":"SA",
    "sg:tags":[
        "transport"
    ],
    "wof:name":"Minlaton Warooka Transport",
    "wof:placetype":"venue"
},
  "geometry": {"coordinates":[137.399093628,-34.9911079407],"type":"Point"}
}