{
  "type": "Feature",
  "properties": {
    "addr:full":"197 Main Rd McLaren Vale SA 5171",
    "addr:housenumber":"197",
    "addr:postcode":"5171",
    "addr:street":"Main Rd",
    "iso:country":"AU",
    "sg:address":"197 Main Rd",
    "sg:city":"McLaren Vale",
    "sg:classifiers":[
        {
            "category":"Farming",
            "subcategory":"Vineyard",
            "type":"Manufacturing & Wholesale Goods"
        }
    ],
    "sg:phone":"+61 8 8323 8438",
    "sg:postcode":"5171",
    "sg:province":"SA",
    "sg:tags":[
        "winery"
    ],
    "wof:name":"McLaren Vale Estate",
    "wof:placetype":"venue"
},
  "geometry": {"coordinates":[138.537597656,-35.2152709961],"type":"Point"}
}