{
  "type": "Feature",
  "properties": {
    "iso:country":"AU",
    "sg:address":"440C High St",
    "sg:city":"Penrith",
    "sg:classifiers":[
        {
            "category":"Shopping",
            "subcategory":"Beauty & Cosmetics",
            "type":"Retail Goods"
        }
    ],
    "sg:phone":"+61 2 4731 2470",
    "sg:postcode":"2750",
    "sg:province":"NSW",
    "wof:name":"Penrith Beauty Salon",
    "wof:placetype":"venue"
},
  "geometry": {"coordinates":[150.91557312,-33.8949203491],"type":"Point"}
}