{
  "type": "Feature",
  "properties": {
    "iso:country":"AU",
    "sg:address":"Lot 15 Riverside Rd",
    "sg:city":"Emu Heights",
    "sg:classifiers":[
        {
            "category":"Personal",
            "subcategory":"Massage",
            "type":"Services"
        }
    ],
    "sg:phone":"+61 2 4735 7090",
    "sg:postcode":"2750",
    "sg:province":"NSW",
    "sg:tags":[
        "therapy"
    ],
    "wof:name":"Martin Clinic",
    "wof:placetype":"venue"
},
  "geometry": {"coordinates":[150.651412964,-33.7271270752],"type":"Point"}
}