{
  "type": "Feature",
  "properties": {
    "addr:full":"Lot 8 Pioneer Ave Malanda QLD 4885",
    "addr:housenumber":"8",
    "addr:postcode":"4885",
    "addr:street":"Pioneer Ave",
    "iso:country":"AU",
    "sg:address":"Lot 8 Pioneer Ave",
    "sg:city":"Malanda",
    "sg:classifiers":[
        {
            "category":"Manufacturing",
            "subcategory":"Furniture",
            "type":"Manufacturing & Wholesale Goods"
        }
    ],
    "sg:phone":"+61 7 4096 6123",
    "sg:postcode":"4885",
    "sg:province":"QLD",
    "sg:tags":[
        "builder",
        "designer",
        "custom"
    ],
    "wof:name":"Hausware",
    "wof:placetype":"venue"
},
  "geometry": {"coordinates":[145.60406494099999,-17.3554077148],"type":"Point"}
}