{
  "type": "Feature",
  "properties": {
    "addr:full":"146 Main Rd Toukley NSW 2263",
    "addr:housenumber":"146",
    "addr:postcode":"2263",
    "addr:street":"Main Rd",
    "iso:country":"AU",
    "sg:address":"146 Main Rd",
    "sg:city":"Toukley",
    "sg:classifiers":[
        {
            "category":"Retail",
            "subcategory":"Auto Repair",
            "type":"Services"
        }
    ],
    "sg:phone":"+61 2 4396 3221",
    "sg:postcode":"2263",
    "sg:province":"NSW",
    "sg:tags":[
        "wheel",
        "balancing",
        "alignment"
    ],
    "wof:name":"Steer (Rite) Motors",
    "wof:placetype":"venue"
},
  "geometry": {"coordinates":[151.54295300000001,-33.264194],"type":"Point"}
}