{
  "type": "Feature",
  "properties": {
    "addr:full":"112 Maude St Shepparton VIC 3630",
    "addr:housenumber":"112",
    "addr:postcode":"3630",
    "addr:street":"Maude St",
    "iso:country":"AU",
    "sg:address":"112 Maude St",
    "sg:city":"Shepparton",
    "sg:classifiers":[
        {
            "category":"Health Services",
            "subcategory":"Doctor",
            "type":"Services"
        }
    ],
    "sg:phone":"+61 3 5821 8888",
    "sg:postcode":"3630",
    "sg:province":"VIC",
    "sg:tags":[
        "medical",
        "practitioner"
    ],
    "wof:name":"Horton Richard W",
    "wof:placetype":"venue"
},
  "geometry": {"coordinates":[145.40150451700001,-36.3769035339],"type":"Point"}
}