{
  "type": "Feature",
  "properties": {
    "addr:full":"941 Whitehorse Rd Box Hill VIC 3128",
    "addr:housenumber":"941",
    "addr:postcode":"3128",
    "addr:street":"Whitehorse Rd",
    "iso:country":"AU",
    "sg:address":"941 Whitehorse Rd",
    "sg:city":"Box Hill",
    "sg:classifiers":[
        {
            "category":"Health Services",
            "subcategory":"Health Practitioner",
            "type":"Services"
        }
    ],
    "sg:phone":"+61 3 9899 6788",
    "sg:postcode":"3128",
    "sg:province":"VIC",
    "sg:tags":[
        "acupuncture"
    ],
    "wof:name":"Yao's Chinese Therapy Centre",
    "wof:placetype":"venue"
},
  "geometry": {"coordinates":[145.123413086,-37.8177337646],"type":"Point"}
}