{
  "type": "Feature",
  "properties": {
    "addr:full":"Eric Rd Artarmon NSW 2064",
    "addr:postcode":"2064",
    "addr:street":"Eric Rd",
    "iso:country":"AU",
    "sg:address":"Eric Rd",
    "sg:city":"Artarmon",
    "sg:classifiers":[
        {
            "category":"Health Services",
            "subcategory":"Health Practitioner",
            "type":"Services"
        }
    ],
    "sg:phone":"+61 2 9418 3692",
    "sg:postcode":"2064",
    "sg:province":"NSW",
    "sg:tags":[
        "psychologist"
    ],
    "wof:name":"Anca Ramsden - Artarmon",
    "wof:placetype":"venue"
},
  "geometry": {"coordinates":[151.180084228,-33.8079986572],"type":"Point"}
}