{
  "type": "Feature",
  "properties": {
    "addr:full":"159 Hawthorne Rd Hawthorne QLD 4171",
    "addr:housenumber":"159",
    "addr:postcode":"4171",
    "addr:street":"Hawthorne Rd",
    "iso:country":"AU",
    "sg:address":"159 Hawthorne Rd",
    "sg:city":"Hawthorne",
    "sg:classifiers":[
        {
            "category":"Social Services",
            "subcategory":"Child Care",
            "type":"Services"
        }
    ],
    "sg:phone":"+61 7 3899 1955",
    "sg:postcode":"4171",
    "sg:province":"QLD",
    "wof:name":"Hawthorne House Preschool and Child Care Centre",
    "wof:placetype":"venue"
},
  "geometry": {"coordinates":[153.05995178200001,-27.4651489258],"type":"Point"}
}