{
  "type": "Feature",
  "properties": {
    "addr:full":"3 Kyte Pl Tumbi Umbi NSW 2261",
    "addr:housenumber":"3",
    "addr:postcode":"2261",
    "addr:street":"Kyte Pl",
    "iso:country":"AU",
    "sg:address":"3 Kyte Pl",
    "sg:city":"Tumbi Umbi",
    "sg:classifiers":[
        {
            "category":"Health Services",
            "subcategory":"Doctor",
            "type":"Services"
        }
    ],
    "sg:phone":"+61 418 841 604",
    "sg:postcode":"2261",
    "sg:province":"NSW",
    "sg:tags":[
        "reflexology"
    ],
    "wof:name":"Forresters Sports Injury & Massage Therapy",
    "wof:placetype":"venue"
},
  "geometry": {"coordinates":[151.45997600000001,-33.397465],"type":"Point"}
}