{
  "type": "Feature",
  "properties": {
    "addr:full":"28 Lonsdale St Braddon ACT 2612",
    "addr:housenumber":"28",
    "addr:postcode":"2612",
    "addr:street":"Lonsdale St",
    "iso:country":"AU",
    "sg:address":"28 Lonsdale St",
    "sg:city":"Braddon",
    "sg:classifiers":[
        {
            "category":"Building & Trades",
            "subcategory":"Construction",
            "type":"Services"
        }
    ],
    "sg:phone":"+61 2 6230 1166",
    "sg:postcode":"2612",
    "sg:province":"ACT",
    "sg:tags":[
        "contractor"
    ],
    "wof:name":"B & T Homes",
    "wof:placetype":"venue"
},
  "geometry": {"coordinates":[149.13313293499999,-35.2719306946],"type":"Point"}
}