{
  "type": "Feature",
  "properties": {
    "iso:country":"AU",
    "sg:address":"Kingsway Shopping Centre, 168 Wanneroo Rd",
    "sg:city":"Madeley",
    "sg:classifiers":[
        {
            "category":"Retail",
            "subcategory":"Veterinary Services",
            "type":"Services"
        }
    ],
    "sg:phone":"+61 8 9309 9993",
    "sg:postcode":"6065",
    "sg:province":"WA",
    "sg:tags":[
        "surgeon"
    ],
    "wof:name":"Kingsway Veterinary Centre",
    "wof:placetype":"venue"
},
  "geometry": {"coordinates":[115.821006775,-31.8193531036],"type":"Point"}
}