{
  "type": "Feature",
  "properties": {
    "addr:full":"96 Buckley St Morwell VIC 3840",
    "addr:housenumber":"96",
    "addr:postcode":"3840",
    "addr:street":"Buckley St",
    "iso:country":"AU",
    "sg:address":"96 Buckley St",
    "sg:city":"Morwell",
    "sg:classifiers":[
        {
            "category":"Personal",
            "subcategory":"Hair Removal",
            "type":"Services"
        }
    ],
    "sg:phone":"+61 3 5134 6954",
    "sg:postcode":"3840",
    "sg:province":"VIC",
    "wof:name":"Cherry Moore Ultima Day Spa",
    "wof:placetype":"venue"
},
  "geometry": {"coordinates":[146.40034484899999,-38.2361984253],"type":"Point"}
}