{
  "type": "Feature",
  "properties": {
    "addr:full":"9 Clarence St Bentleigh East VIC 3165",
    "addr:housenumber":"9",
    "addr:postcode":"3165",
    "addr:street":"Clarence St",
    "iso:country":"AU",
    "sg:address":"9 Clarence St",
    "sg:city":"Bentleigh East",
    "sg:classifiers":[
        {
            "category":"Retail",
            "subcategory":"Auto Repair",
            "type":"Services"
        }
    ],
    "sg:phone":"+61 3 9579 3733",
    "sg:postcode":"3165",
    "sg:province":"VIC",
    "sg:tags":[
        "repairer",
        "motor",
        "engineer"
    ],
    "wof:name":"East Bentleigh Auto Care",
    "wof:placetype":"venue"
},
  "geometry": {"coordinates":[145.058395386,-37.9278182983],"type":"Point"}
}