{
  "type": "Feature",
  "properties": {
    "addr:full":"459 Belair Rd Belair SA 5052",
    "addr:housenumber":"459",
    "addr:postcode":"5052",
    "addr:street":"Belair Rd",
    "iso:country":"AU",
    "sg:address":"459 Belair Rd",
    "sg:city":"Belair",
    "sg:classifiers":[
        {
            "category":"Health Services",
            "subcategory":"Doctor",
            "type":"Services"
        }
    ],
    "sg:phone":"+61 8 8278 8900",
    "sg:postcode":"5052",
    "sg:province":"SA",
    "sg:tags":[
        "medical",
        "practitioner"
    ],
    "wof:name":"Belair Family Health Centre",
    "wof:placetype":"venue"
},
  "geometry": {"coordinates":[138.62101699999999,-34.998135],"type":"Point"}
}