{
  "type": "Feature",
  "properties": {
    "addr:full":"20 Railway Pde Highett VIC 3190",
    "addr:housenumber":"20",
    "addr:postcode":"3190",
    "addr:street":"Railway Pde",
    "iso:country":"AU",
    "sg:address":"20 Railway Pde",
    "sg:city":"Highett",
    "sg:classifiers":[
        {
            "category":"Health Services",
            "subcategory":"Health Practitioner",
            "type":"Services"
        }
    ],
    "sg:phone":"+61 3 9515 0210",
    "sg:postcode":"3190",
    "sg:province":"VIC",
    "sg:tags":[
        "acupuncture"
    ],
    "wof:name":"Aculife",
    "wof:placetype":"venue"
},
  "geometry": {"coordinates":[145.04197692899999,-37.9477767944],"type":"Point"}
}