{
  "type": "Feature",
  "properties": {
    "addr:full":"Suite 2, 11 Amy St Campsie NSW 2194",
    "addr:housenumber":"11",
    "addr:postcode":"2194",
    "addr:street":"Amy St",
    "iso:country":"AU",
    "sg:address":"Suite 2, 11 Amy St",
    "sg:city":"Campsie",
    "sg:classifiers":[
        {
            "category":"Real Estate",
            "subcategory":"Architect",
            "type":"Services"
        }
    ],
    "sg:phone":"+61 2 9787 2164",
    "sg:postcode":"2194",
    "sg:province":"NSW",
    "wof:name":"Em Hauri & Co",
    "wof:placetype":"venue"
},
  "geometry": {"coordinates":[151.103195,-33.912048],"type":"Point"}
}