{
  "type": "Feature",
  "properties": {
    "iso:country":"AU",
    "sg:address":"153 Mella Rd",
    "sg:city":"Smithton",
    "sg:classifiers":[
        {
            "category":"Building & Trades",
            "subcategory":"Landscaping Services",
            "type":"Services"
        }
    ],
    "sg:phone":"+61 3 6452 3800",
    "sg:postcode":"7330",
    "sg:province":"TAS",
    "sg:tags":[
        "fertilizer",
        "spreading",
        "insecticide"
    ],
    "wof:name":"Circular Head Spreading Service",
    "wof:placetype":"venue"
},
  "geometry": {"coordinates":[145.08105499999999,-40.839176],"type":"Point"}
}