{
  "type": "Feature",
  "properties": {
    "addr:full":"14 Picasso Crt Ayr QLD 4807",
    "addr:housenumber":"14",
    "addr:postcode":"4807",
    "addr:street":"Picasso Crt",
    "iso:country":"AU",
    "sg:address":"14 Picasso Crt",
    "sg:city":"Ayr",
    "sg:classifiers":[
        {
            "category":"Professional",
            "type":"Services"
        }
    ],
    "sg:phone":"+61 7 4783 2940",
    "sg:postcode":"4807",
    "sg:province":"QLD",
    "sg:tags":[
        "courier"
    ],
    "wof:name":"Burdekin Service Cars",
    "wof:placetype":"venue"
},
  "geometry": {"coordinates":[147.40202331500001,-19.5692977905],"type":"Point"}
}