{
  "type": "Feature",
  "properties": {
    "addr:full":"Fith Ave Gosford NSW 2250",
    "addr:postcode":"2250",
    "addr:street":"Fith Ave",
    "iso:country":"AU",
    "sg:address":"Fith Ave",
    "sg:city":"Gosford",
    "sg:classifiers":[
        {
            "category":"Professional",
            "type":"Services"
        }
    ],
    "sg:phone":"+61 2 4325 5720",
    "sg:postcode":"2250",
    "sg:province":"NSW",
    "sg:tags":[
        "courier"
    ],
    "wof:name":"Australian AirEXPRESS# Regional",
    "wof:placetype":"venue"
},
  "geometry": {"coordinates":[151.34249877900001,-33.4237213135],"type":"Point"}
}