{
  "type": "Feature",
  "properties": {
    "iso:country":"AU",
    "sg:address":"63 Walcott St",
    "sg:city":"Broome",
    "sg:classifiers":[
        {
            "category":"Health Services",
            "subcategory":"Dentist",
            "type":"Services"
        }
    ],
    "sg:phone":"+61 8 9192 8800",
    "sg:postcode":"6725",
    "sg:province":"WA",
    "wof:name":"Vernon Joe",
    "wof:placetype":"venue"
},
  "geometry": {"coordinates":[122.23487854,-17.9657516479],"type":"Point"}
}