{
  "type": "Feature",
  "properties": {
    "iso:country":"AU",
    "sg:address":"38 Sussex St",
    "sg:city":"Maryborough",
    "sg:classifiers":[
        {
            "category":"Banks & Credit Unions",
            "subcategory":"Investment Brokerage",
            "type":"Services"
        }
    ],
    "sg:phone":"+61 7 4122 3714",
    "sg:postcode":"4650",
    "sg:province":"QLD",
    "sg:tags":[
        "care",
        "day",
        "family",
        "child"
    ],
    "wof:name":"Maryborough After School Care",
    "wof:placetype":"venue"
},
  "geometry": {"coordinates":[152.700485,-25.533644],"type":"Point"}
}