{
  "type": "Feature",
  "properties": {
    "iso:country":"AU",
    "sg:address":"29 Morris St",
    "sg:city":"St Marys",
    "sg:classifiers":[
        {
            "category":"Building & Trades",
            "subcategory":"Plumbing",
            "type":"Services"
        }
    ],
    "sg:phone":"+61 429 800 700",
    "sg:postcode":"2760",
    "sg:province":"NSW",
    "sg:tags":[
        "plumber",
        "gasfitters"
    ],
    "wof:name":"Sydwest Plumbing",
    "wof:placetype":"venue"
},
  "geometry": {"coordinates":[150.783111572,-33.7734909058],"type":"Point"}
}