{
  "type": "Feature",
  "properties": {
    "iso:country":"AU",
    "sg:address":"18 Risley St",
    "sg:city":"Carina",
    "sg:classifiers":[
        {
            "category":"Professional",
            "subcategory":"Art Services",
            "type":"Services"
        }
    ],
    "sg:phone":"+61 7 3398 2807",
    "sg:postcode":"4152",
    "sg:province":"QLD",
    "sg:tags":[
        "artist"
    ],
    "wof:name":"Mollison Stephen G",
    "wof:placetype":"venue"
},
  "geometry": {"coordinates":[153.089447022,-27.4894752502],"type":"Point"}
}