{
  "type": "Feature",
  "properties": {
    "addr:full":"25 High St Manly NSW 2095",
    "addr:housenumber":"25",
    "addr:postcode":"2095",
    "addr:street":"High St",
    "iso:country":"AU",
    "sg:address":"25 High St",
    "sg:city":"Manly",
    "sg:classifiers":[
        {
            "category":"Professional",
            "subcategory":"Computer Services",
            "type":"Services"
        }
    ],
    "sg:phone":"+61 2 9977 4330",
    "sg:postcode":"2095",
    "sg:province":"NSW",
    "sg:tags":[
        "information"
    ],
    "wof:name":"Murray J",
    "wof:placetype":"venue"
},
  "geometry": {"coordinates":[151.28985595699999,-33.8040962219],"type":"Point"}
}