{
  "type": "Feature",
  "properties": {
    "iso:country":"AU",
    "sg:address":"Shop 31a, Northgate S/C, Main Rd",
    "sg:city":"Glenorchy",
    "sg:classifiers":[
        {
            "category":"Shopping",
            "subcategory":"Mobile Phones",
            "type":"Retail Goods"
        }
    ],
    "sg:phone":"+61 3 6273 7522",
    "sg:postcode":"7010",
    "sg:province":"TAS",
    "sg:tags":[
        "telephone",
        "accessory"
    ],
    "wof:name":"Vodafone Glenorchy",
    "wof:placetype":"venue"
},
  "geometry": {"coordinates":[147.279754639,-42.8336982727],"type":"Point"}
}