{
  "type": "Feature",
  "properties": {
    "iso:country":"AU",
    "sg:address":"Suite 3, Level 2",
    "sg:city":"Clinical Services Building Strickland Crescen",
    "sg:classifiers":[
        {
            "category":"Health Services",
            "subcategory":"Health Practitioner",
            "type":"Services"
        }
    ],
    "sg:phone":"+61 2 6282 5898",
    "sg:postcode":"2600",
    "sg:province":"ACT",
    "sg:tags":[
        "physiotherapist"
    ],
    "wof:name":"O&#039;Keefe Deborah",
    "wof:placetype":"venue"
},
  "geometry": {"coordinates":[149.11323547399999,-35.3206176758],"type":"Point"}
}