{
  "type": "Feature",
  "properties": {
    "addr:full":"PO Box 18 Wauchope NSW 2446",
    "addr:postcode":"2446",
    "iso:country":"AU",
    "sg:address":"PO Box 18",
    "sg:city":"Wauchope",
    "sg:classifiers":[
        {
            "category":"Shopping",
            "subcategory":"Bicycles & Sporting Goods",
            "type":"Retail Goods"
        }
    ],
    "sg:phone":"+61 418 367 321",
    "sg:postcode":"2446",
    "sg:province":"NSW",
    "sg:tags":[
        "chemical",
        "equipment",
        "pool",
        "swimming"
    ],
    "wof:name":"Port Pool Care",
    "wof:placetype":"venue"
},
  "geometry": {"coordinates":[152.73371900000001,-31.45739],"type":"Point"}
}