{
  "type": "Feature",
  "properties": {
    "addr:full":"120 Bungaree Rd Pendle Hill NSW 2145",
    "addr:housenumber":"120",
    "addr:postcode":"2145",
    "addr:street":"Bungaree Rd",
    "iso:country":"AU",
    "sg:address":"120 Bungaree Rd",
    "sg:city":"Pendle Hill",
    "sg:classifiers":[
        {
            "category":"Retail",
            "subcategory":"Auto Repair",
            "type":"Services"
        }
    ],
    "sg:phone":"+61 2 9896 7979",
    "sg:postcode":"2145",
    "sg:province":"NSW",
    "sg:tags":[
        "automotive",
        "air conditioning"
    ],
    "wof:name":"All Type Auto Air",
    "wof:placetype":"venue"
},
  "geometry": {"coordinates":[150.9584198,-33.8005828857],"type":"Point"}
}