{
  "type": "Feature",
  "properties": {
    "addr:full":"Sugarloaf Rd Corryong NSW 3707",
    "addr:postcode":"3707",
    "addr:street":"Sugarloaf Rd",
    "iso:country":"AU",
    "sg:address":"Sugarloaf Rd",
    "sg:city":"Corryong",
    "sg:classifiers":[
        {
            "category":"Building & Trades",
            "subcategory":"Landscaping Services",
            "type":"Services"
        }
    ],
    "sg:phone":"+61 2 6076 2323",
    "sg:postcode":"3707",
    "sg:province":"NSW",
    "sg:tags":[
        "stump",
        "tree",
        "felling",
        "removal"
    ],
    "wof:name":"Upper Murray Hardwood",
    "wof:placetype":"venue"
},
  "geometry": {"coordinates":[147.890380859,-36.2046661377],"type":"Point"}
}