{
  "type": "Feature",
  "properties": {
    "addr:full":"7 Coolibah St Dalby QLD 4405",
    "addr:housenumber":"7",
    "addr:postcode":"4405",
    "addr:street":"Coolibah St",
    "iso:country":"AU",
    "sg:address":"7 Coolibah St",
    "sg:city":"Dalby",
    "sg:classifiers":[
        {
            "category":"Professional",
            "subcategory":"Printing & Photocopies",
            "type":"Services"
        }
    ],
    "sg:phone":"+61 1300 949 528",
    "sg:postcode":"4405",
    "sg:province":"QLD",
    "sg:tags":[
        "embroidery"
    ],
    "wof:name":"Why Not Kates",
    "wof:placetype":"venue"
},
  "geometry": {"coordinates":[151.27012634299999,-27.1788272858],"type":"Point"}
}