{
  "type": "Feature",
  "properties": {
    "iso:country":"AU",
    "sg:address":"50 Browns Rd",
    "sg:city":"Kingston",
    "sg:classifiers":[
        {
            "category":"Building & Trades",
            "subcategory":"Construction",
            "type":"Services"
        }
    ],
    "sg:phone":"+61 3 6229 5266",
    "sg:postcode":"7050",
    "sg:province":"TAS",
    "sg:tags":[
        "contractor"
    ],
    "wof:name":"Wyatt Constructions",
    "wof:placetype":"venue"
},
  "geometry": {"coordinates":[147.31308000000001,-42.969452],"type":"Point"}
}