{
  "type": "Feature",
  "properties": {
    "addr:full":"Grant St Camp Hill QLD 4152",
    "addr:postcode":"4152",
    "addr:street":"Grant St",
    "iso:country":"AU",
    "sg:address":"Grant St",
    "sg:city":"Camp Hill",
    "sg:classifiers":[
        {
            "category":"Personal",
            "type":"Services"
        }
    ],
    "sg:phone":"+61 7 3395 3730",
    "sg:postcode":"4152",
    "sg:province":"QLD",
    "sg:tags":[
        "reducing",
        "treatment",
        "weight"
    ],
    "wof:name":"Herbalife Camp Hill",
    "wof:placetype":"venue"
},
  "geometry": {"coordinates":[153.07078552199999,-27.4963207245],"type":"Point"}
}