{
  "type": "Feature",
  "properties": {
    "iso:country":"AU",
    "sg:address":"779 Logan Rd",
    "sg:city":"Holland Park",
    "sg:classifiers":[
        {
            "category":"Retail",
            "subcategory":"Auto Repair",
            "type":"Services"
        }
    ],
    "sg:phone":"+61 7 3397 0446",
    "sg:postcode":"4121",
    "sg:province":"QLD",
    "sg:tags":[
        "electrical"
    ],
    "wof:name":"Holland Park Auto Electrics",
    "wof:placetype":"venue"
},
  "geometry": {"coordinates":[153.05450439399999,-27.5140171051],"type":"Point"}
}