{
  "type": "Feature",
  "properties": {
    "addr:full":"151 Osborne Ave Clayton South VIC 3169",
    "addr:housenumber":"151",
    "addr:postcode":"3169",
    "addr:street":"Osborne Ave",
    "iso:country":"AU",
    "sg:address":"151 Osborne Ave",
    "sg:city":"Clayton South",
    "sg:classifiers":[
        {
            "category":"Home & Garden",
            "subcategory":"Furniture",
            "type":"Retail Goods"
        }
    ],
    "sg:phone":"+61 3 9547 6889",
    "sg:postcode":"3169",
    "sg:province":"VIC",
    "sg:tags":[
        "business"
    ],
    "wof:name":"Chairlink Pty Ltd",
    "wof:placetype":"venue"
},
  "geometry": {"coordinates":[145.13116455100001,-37.9446716309],"type":"Point"}
}