{
  "type": "Feature",
  "properties": {
    "iso:country":"AU",
    "sg:address":"Hall Rd",
    "sg:city":"Springwood",
    "sg:classifiers":[
        {
            "category":"Government",
            "subcategory":"City Hall",
            "type":"Public Place"
        }
    ],
    "sg:phone":"+61 7 3826 5410",
    "sg:postcode":"4127",
    "sg:province":"QLD",
    "wof:name":"Slacks Creek Progress Hall",
    "wof:placetype":"venue"
},
  "geometry": {"coordinates":[153.134887695,-27.6298007965],"type":"Point"}
}