{
  "type": "Feature",
  "properties": {
    "addr:full":"8 St Albans Crt Grindelwald TAS 7277",
    "addr:housenumber":"8",
    "addr:postcode":"7277",
    "addr:street":"St Albans Crt",
    "iso:country":"AU",
    "sg:address":"8 St Albans Crt",
    "sg:city":"Grindelwald",
    "sg:classifiers":[
        {
            "category":"Home & Garden",
            "subcategory":"Building Materials",
            "type":"Retail Goods"
        }
    ],
    "sg:phone":"+61 418 317 733",
    "sg:postcode":"7277",
    "sg:province":"TAS",
    "sg:tags":[
        "lawn",
        "cutting",
        "maintenance"
    ],
    "wof:name":"Northern Mowing & Rubbish Removal",
    "wof:placetype":"venue"
},
  "geometry": {"coordinates":[147.00242614699999,-41.3539237976],"type":"Point"}
}