{
  "type": "Feature",
  "properties": {
    "addr:full":"924 Riversdale Rd Surrey Hills VIC 3127",
    "addr:housenumber":"924",
    "addr:postcode":"3127",
    "addr:street":"Riversdale Rd",
    "iso:country":"AU",
    "sg:address":"924 Riversdale Rd",
    "sg:city":"Surrey Hills",
    "sg:classifiers":[
        {
            "category":"Professional",
            "subcategory":"Secretarial Services",
            "type":"Services"
        }
    ],
    "sg:phone":"+61 3 9830 4586",
    "sg:postcode":"3127",
    "sg:province":"VIC",
    "sg:tags":[
        "typing"
    ],
    "wof:name":"Copycat Copying & Secretarial Service",
    "wof:placetype":"venue"
},
  "geometry": {"coordinates":[145.093185425,-37.8355026245],"type":"Point"}
}