{
  "type": "Feature",
  "properties": {
    "addr:full":"275 Barkly St Footscray VIC 3011",
    "addr:housenumber":"275",
    "addr:postcode":"3011",
    "addr:street":"Barkly St",
    "iso:country":"AU",
    "sg:address":"275 Barkly St",
    "sg:city":"Footscray",
    "sg:classifiers":[
        {
            "category":"Cafe",
            "type":"Food & Drink"
        }
    ],
    "sg:phone":"+61 3 9687 4094",
    "sg:postcode":"3011",
    "sg:province":"VIC",
    "wof:name":"Poon E P",
    "wof:placetype":"venue"
},
  "geometry": {"coordinates":[144.894973755,-37.7992897034],"type":"Point"}
}