{
  "type": "Feature",
  "properties": {
    "addr:full":"164 High St Fremantle WA 6160",
    "addr:housenumber":"164",
    "addr:postcode":"6160",
    "addr:street":"High St",
    "iso:country":"AU",
    "sg:address":"164 High St",
    "sg:city":"Fremantle",
    "sg:classifiers":[
        {
            "category":"Health Services",
            "subcategory":"Health Practitioner",
            "type":"Services"
        }
    ],
    "sg:phone":"+61 8 9335 7055",
    "sg:postcode":"6160",
    "sg:province":"WA",
    "sg:tags":[
        "physiotherapist"
    ],
    "wof:name":"Renner Patrick",
    "wof:placetype":"venue"
},
  "geometry": {"coordinates":[115.753387,-32.052162],"type":"Point"}
}