{
  "type": "Feature",
  "properties": {
    "addr:full":"75 Belgrave St Kempsey NSW 2440",
    "addr:housenumber":"75",
    "addr:postcode":"2440",
    "addr:street":"Belgrave St",
    "iso:country":"AU",
    "sg:address":"75 Belgrave St",
    "sg:city":"Kempsey",
    "sg:classifiers":[
        {
            "category":"Health Services",
            "subcategory":"Doctor",
            "type":"Services"
        }
    ],
    "sg:phone":"+61 2 6562 2000",
    "sg:postcode":"2440",
    "sg:province":"NSW",
    "sg:tags":[
        "medical",
        "practitioner"
    ],
    "wof:name":"Tristar Medical Group",
    "wof:placetype":"venue"
},
  "geometry": {"coordinates":[152.833878,-31.079353],"type":"Point"}
}