{
  "type": "Feature",
  "properties": {
    "addr:full":"6 Gatwick Rd Bayswater VIC 3153",
    "addr:housenumber":"6",
    "addr:postcode":"3153",
    "addr:street":"Gatwick Rd",
    "iso:country":"AU",
    "sg:address":"6 Gatwick Rd",
    "sg:city":"Bayswater",
    "sg:classifiers":[
        {
            "category":"Professional",
            "subcategory":"Detective & Security Services",
            "type":"Services"
        }
    ],
    "sg:phone":"+61 3 9729 8888",
    "sg:postcode":"3153",
    "sg:province":"VIC",
    "sg:tags":[
        "protective",
        "rustproofing"
    ],
    "wof:name":"AMAC Corrosion Protection Pty Ltd",
    "wof:placetype":"venue"
},
  "geometry": {"coordinates":[145.29672241200001,-37.8229827881],"type":"Point"}
}