{
  "type": "Feature",
  "properties": {
    "addr:full":"Bougainville St Soldiers Hill QLD 4825",
    "addr:postcode":"4825",
    "addr:street":"Bougainville St",
    "iso:country":"AU",
    "sg:address":"Bougainville St",
    "sg:city":"Soldiers Hill",
    "sg:classifiers":[
        {
            "category":"Education",
            "subcategory":"School",
            "type":"Public Place"
        }
    ],
    "sg:phone":"+61 7 4743 2513",
    "sg:postcode":"4825",
    "sg:province":"QLD",
    "sg:tags":[
        "state",
        "except",
        "nsw"
    ],
    "wof:name":"Barkly Highway Primary",
    "wof:placetype":"venue"
},
  "geometry": {"coordinates":[139.48873900000001,-20.707581],"type":"Point"}
}