{
  "type": "Feature",
  "properties": {
    "addr:full":"U1, 102 Glebe Rd The Junction NSW 2291",
    "addr:housenumber":"102",
    "addr:postcode":"2291",
    "addr:street":"U1;Glebe Rd",
    "iso:country":"AU",
    "sg:address":"U1, 102 Glebe Rd",
    "sg:city":"The Junction",
    "sg:classifiers":[
        {
            "category":"Health Services",
            "subcategory":"Health Practitioner",
            "type":"Services"
        }
    ],
    "sg:phone":"+61 2 4965 4482",
    "sg:postcode":"2291",
    "sg:province":"NSW",
    "sg:tags":[
        "consultant",
        "conservation",
        "hearing"
    ],
    "wof:name":"Ear Defender Australasia",
    "wof:placetype":"venue"
},
  "geometry": {"coordinates":[151.75776672399999,-32.9384918213],"type":"Point"}
}