{
  "type": "Feature",
  "properties": {
    "iso:country":"AU",
    "sg:address":"22 Singleton St",
    "sg:city":"Collingwood",
    "sg:classifiers":[
        {
            "category":"Banks & Credit Unions",
            "subcategory":"Atm",
            "type":"Services"
        }
    ],
    "sg:phone":"+61 3 9419 9797",
    "sg:postcode":"3066",
    "sg:province":"VIC",
    "sg:tags":[
        "wholesaler",
        "mfrs",
        "shirt",
        "pyjama"
    ],
    "wof:name":"Studio Kids",
    "wof:placetype":"venue"
},
  "geometry": {"coordinates":[144.98733520499999,-37.8036422729],"type":"Point"}
}