{
  "type": "Feature",
  "properties": {
    "addr:full":"222 Wellington St South Launceston TAS 7249",
    "addr:housenumber":"222",
    "addr:postcode":"7249",
    "addr:street":"Wellington St",
    "iso:country":"AU",
    "sg:address":"222 Wellington St",
    "sg:city":"South Launceston",
    "sg:classifiers":[
        {
            "category":"Shopping",
            "subcategory":"Party Supplies",
            "type":"Retail Goods"
        }
    ],
    "sg:phone":"+61 3 6343 6322",
    "sg:postcode":"7249",
    "sg:province":"TAS",
    "wof:name":"Parties Presents & Play",
    "wof:placetype":"venue"
},
  "geometry": {"coordinates":[147.14231872600001,-41.4516334534],"type":"Point"}
}