{
  "type": "Feature",
  "properties": {
    "addr:full":"31 Exhibition Rd Gympie QLD 4570",
    "addr:housenumber":"31",
    "addr:postcode":"4570",
    "addr:street":"Exhibition Rd",
    "iso:country":"AU",
    "sg:address":"31 Exhibition Rd",
    "sg:city":"Gympie",
    "sg:classifiers":[
        {
            "category":"Food & Beverages",
            "subcategory":"Fruits & Vegetables",
            "type":"Retail Goods"
        }
    ],
    "sg:phone":"+61 7 5482 5180",
    "sg:postcode":"4570",
    "sg:province":"QLD",
    "sg:tags":[
        "greengrocer",
        "fruiterer"
    ],
    "wof:name":"Ginger's Fruit & Vegetable & Convenience Store",
    "wof:placetype":"venue"
},
  "geometry": {"coordinates":[152.64944457999999,-26.198217392],"type":"Point"}
}