{
  "type": "Feature",
  "properties": {
    "iso:country":"AU",
    "sg:address":"45 Otway St",
    "sg:city":"Portland",
    "sg:classifiers":[
        {
            "category":"Food & Beverages",
            "subcategory":"Groceries & Convenience Stores",
            "type":"Retail Goods"
        }
    ],
    "sg:phone":"+61 3 5523 6353",
    "sg:postcode":"3305",
    "sg:province":"VIC",
    "wof:name":"Big O Milk Bar",
    "wof:placetype":"venue"
},
  "geometry": {"coordinates":[141.60029602,-38.3421211243],"type":"Point"}
}