{
  "type": "Feature",
  "properties": {
    "iso:country":"AU",
    "sg:address":"Mt Robertson Rd",
    "sg:city":"New Gisborne",
    "sg:classifiers":[
        {
            "category":"Retail",
            "subcategory":"Animal Services",
            "type":"Services"
        }
    ],
    "sg:phone":"+61 3 5426 2140",
    "sg:postcode":"3438",
    "sg:province":"VIC",
    "sg:tags":[
        "breeder",
        "sheep",
        "stud",
        "cattle"
    ],
    "wof:name":"W Turnbull & Sons",
    "wof:placetype":"venue"
},
  "geometry": {"coordinates":[144.61759948700001,-37.4310684204],"type":"Point"}
}