{
  "type": "Feature",
  "properties": {
    "addr:full":"300 Anzac Ave Toowoomba QLD 4350",
    "addr:housenumber":"300",
    "addr:postcode":"4350",
    "addr:street":"Anzac Ave",
    "iso:country":"AU",
    "sg:address":"300 Anzac Ave",
    "sg:city":"Toowoomba",
    "sg:classifiers":[
        {
            "category":"Wholesale",
            "subcategory":"Farm Supplies",
            "type":"Manufacturing & Wholesale Goods"
        }
    ],
    "sg:phone":"+61 7 4637 3300",
    "sg:postcode":"4350",
    "sg:province":"QLD",
    "sg:tags":[
        "equipment"
    ],
    "wof:name":"Bowdler English & Wehl Seed & Grain",
    "wof:placetype":"venue"
},
  "geometry": {"coordinates":[151.91925000000001,-27.582479],"type":"Point"}
}