{
  "type": "Feature",
  "properties": {
    "iso:country":"AU",
    "sg:address":"Redwood Garden Estate, 20",
    "sg:city":"Garden Blv Dingley",
    "sg:classifiers":[
        {
            "category":"Building & Trades",
            "subcategory":"Cleaning & Sanitation",
            "type":"Services"
        }
    ],
    "sg:phone":"+61 1300 654 664",
    "sg:postcode":"3172",
    "sg:province":"VIC",
    "sg:tags":[
        "commercial",
        "maintenance"
    ],
    "wof:name":"Hirotec",
    "wof:placetype":"venue"
},
  "geometry": {"coordinates":[145.113845825,-37.9787597656],"type":"Point"}
}