{
  "type": "Feature",
  "properties": {
    "iso:country":"AU",
    "sg:address":"77 Commercial Rd",
    "sg:city":"Port Adelaide",
    "sg:classifiers":[
        {
            "category":"Health Services",
            "subcategory":"Chiropractor",
            "type":"Services"
        }
    ],
    "sg:phone":"+61 8 8341 0995",
    "sg:postcode":"5015",
    "sg:province":"SA",
    "wof:name":"McAllister W J",
    "wof:placetype":"venue"
},
  "geometry": {"coordinates":[138.50581359899999,-34.8445625305],"type":"Point"}
}