{
  "type": "Feature",
  "properties": {
    "iso:country":"AU",
    "sg:address":"24 Cameron St",
    "sg:city":"Railway Estate",
    "sg:classifiers":[
        {
            "category":"Wholesale",
            "subcategory":"Machinery & Supplies",
            "type":"Manufacturing & Wholesale Goods"
        }
    ],
    "sg:phone":"+61 409 489 128",
    "sg:postcode":"4810",
    "sg:province":"QLD",
    "sg:tags":[
        "equipment",
        "system",
        "elevating",
        "conveying"
    ],
    "wof:name":"Conveyor Maintenance Service",
    "wof:placetype":"venue"
},
  "geometry": {"coordinates":[146.820557,-19.285879],"type":"Point"}
}