{
  "type": "Feature",
  "properties": {
    "addr:full":"216 Woodpark Rd Smithfield NSW 2164",
    "addr:housenumber":"216",
    "addr:postcode":"2164",
    "addr:street":"Woodpark Rd",
    "iso:country":"AU",
    "sg:address":"216 Woodpark Rd",
    "sg:city":"Smithfield",
    "sg:classifiers":[
        {
            "category":"Professional",
            "type":"Services"
        }
    ],
    "sg:phone":"+61 2 9609 2500",
    "sg:postcode":"2164",
    "sg:province":"NSW",
    "sg:tags":[
        "transport"
    ],
    "wof:name":"KBT Overnight Express Pty Ltd",
    "wof:placetype":"venue"
},
  "geometry": {"coordinates":[150.93446350100001,-33.8364715576],"type":"Point"}
}