{
  "type": "Feature",
  "properties": {
    "iso:country":"AU",
    "sg:address":"U5/ 2328 Albany Hwy",
    "sg:city":"Gosnells",
    "sg:classifiers":[
        {
            "category":"Personal",
            "type":"Services"
        }
    ],
    "sg:phone":"+61 8 9490 1717",
    "sg:postcode":"6110",
    "sg:province":"WA",
    "sg:tags":[
        "gift"
    ],
    "wof:name":"Blossom Florist",
    "wof:placetype":"venue"
},
  "geometry": {"coordinates":[116.005599976,-32.0744476318],"type":"Point"}
}