{
  "type": "Feature",
  "properties": {
    "addr:full":"23 Hartley Rd Wonga Park VIC 3115",
    "addr:housenumber":"23",
    "addr:postcode":"3115",
    "addr:street":"Hartley Rd",
    "iso:country":"AU",
    "sg:address":"23 Hartley Rd",
    "sg:city":"Wonga Park",
    "sg:classifiers":[
        {
            "category":"Building & Trades",
            "subcategory":"Plumbing",
            "type":"Services"
        }
    ],
    "sg:phone":"+61 3 9722 2999",
    "sg:postcode":"3115",
    "sg:province":"VIC",
    "sg:tags":[
        "drainers"
    ],
    "wof:name":"P F & L Collins Contractors Pty Ltd",
    "wof:placetype":"venue"
},
  "geometry": {"coordinates":[145.265258789,-37.7289657593],"type":"Point"}
}