{
  "type": "Feature",
  "properties": {
    "iso:country":"AU",
    "sg:address":"Locality Mail Bag LPO Box 7128 Gardenvale",
    "sg:city":"Brighton",
    "sg:classifiers":[
        {
            "category":"Banks & Credit Unions",
            "subcategory":"Bank",
            "type":"Services"
        }
    ],
    "sg:phone":"+61 3 9578 1077",
    "sg:postcode":"3186",
    "sg:province":"VIC",
    "sg:tags":[
        "broker",
        "mortgage"
    ],
    "wof:name":"Star Finance Corp Pty Ltd",
    "wof:placetype":"venue"
},
  "geometry": {"coordinates":[145.005584717,-37.897605896],"type":"Point"}
}