{
  "type": "Feature",
  "properties": {
    "addr:full":"2 Francis Rd Port Denison WA 6525",
    "addr:housenumber":"2",
    "addr:postcode":"6525",
    "addr:street":"Francis Rd",
    "iso:country":"AU",
    "sg:address":"2 Francis Rd",
    "sg:city":"Port Denison",
    "sg:classifiers":[
        {
            "category":"Farming",
            "subcategory":"Fish & Marine Products",
            "type":"Manufacturing & Wholesale Goods"
        }
    ],
    "sg:phone":"+61 8 9927 1284",
    "sg:postcode":"6525",
    "sg:province":"WA",
    "sg:tags":[
        "fisherman"
    ],
    "wof:name":"Crofts T J",
    "wof:placetype":"venue"
},
  "geometry": {"coordinates":[114.932731628,-29.2644271851],"type":"Point"}
}