{
  "type": "Feature",
  "properties": {
    "addr:full":"55 Wellington St Riverstone NSW 2765",
    "addr:housenumber":"55",
    "addr:postcode":"2765",
    "addr:street":"Wellington St",
    "iso:country":"AU",
    "sg:address":"55 Wellington St",
    "sg:city":"Riverstone",
    "sg:classifiers":[
        {
            "category":"Professional",
            "subcategory":"Detective & Security Services",
            "type":"Services"
        }
    ],
    "sg:phone":"+61 2 9627 2366",
    "sg:postcode":"2765",
    "sg:province":"NSW",
    "sg:tags":[
        "identification",
        "system"
    ],
    "wof:name":"Du Cros Tapes Pty Ltd",
    "wof:placetype":"venue"
},
  "geometry": {"coordinates":[150.86106872600001,-33.6659469604],"type":"Point"}
}