{
  "type": "Feature",
  "properties": {
    "iso:country":"AU",
    "sg:address":"27 High St",
    "sg:city":"Charlton",
    "sg:classifiers":[
        {
            "category":"Cafe",
            "type":"Food & Drink"
        }
    ],
    "sg:phone":"+61 3 5491 1414",
    "sg:postcode":"3525",
    "sg:province":"VIC",
    "wof:name":"Bush Poet Cafe The",
    "wof:placetype":"venue"
},
  "geometry": {"coordinates":[143.348984,-36.26825],"type":"Point"}
}