{
  "type": "Feature",
  "properties": {
    "addr:full":"39 Archer St Dickson ACT 2602",
    "addr:housenumber":"39",
    "addr:postcode":"2602",
    "addr:street":"Archer St",
    "iso:country":"AU",
    "sg:address":"39 Archer St",
    "sg:city":"Dickson",
    "sg:classifiers":[
        {
            "category":"Professional",
            "subcategory":"Accounting & Tax Preparation",
            "type":"Services"
        }
    ],
    "sg:phone":"+61 2 6249 1136",
    "sg:postcode":"2602",
    "sg:province":"ACT",
    "sg:tags":[
        "accountant",
        "auditor"
    ],
    "wof:name":"Wei & Wei Accountants CPA",
    "wof:placetype":"venue"
},
  "geometry": {"coordinates":[149.14143371599999,-35.2527923584],"type":"Point"}
}