{
  "type": "Feature",
  "properties": {
    "addr:full":"36 John St Lidcombe NSW 2141",
    "addr:housenumber":"36",
    "addr:postcode":"2141",
    "addr:street":"John St",
    "iso:country":"AU",
    "sg:address":"36 John St",
    "sg:city":"Lidcombe",
    "sg:classifiers":[
        {
            "category":"Health Services",
            "subcategory":"Dentist",
            "type":"Services"
        }
    ],
    "sg:phone":"+61 2 9649 7376",
    "sg:postcode":"2141",
    "sg:province":"NSW",
    "wof:name":"McGloin John B",
    "wof:placetype":"venue"
},
  "geometry": {"coordinates":[151.04473876899999,-33.8614730835],"type":"Point"}
}