{
  "type": "Feature",
  "properties": {
    "addr:full":"Casey Ave Mackay QLD 4740",
    "addr:postcode":"4740",
    "addr:street":"Casey Ave",
    "iso:country":"AU",
    "sg:address":"Casey Ave",
    "sg:city":"Mackay",
    "sg:classifiers":[
        {
            "category":"Airline",
            "type":"Transportation"
        }
    ],
    "sg:phone":"+61 7 4957 2446",
    "sg:postcode":"4740",
    "sg:province":"QLD",
    "sg:tags":[
        "aircraft",
        "rental",
        "charter"
    ],
    "wof:name":"Horizon Airways",
    "wof:placetype":"venue"
},
  "geometry": {"coordinates":[149.18331900000001,-21.163357],"type":"Point"}
}