{
  "type": "Feature",
  "properties": {
    "addr:full":"Level 1 55 Little Edward St Spring Hill QLD 4000",
    "addr:housenumber":"55",
    "addr:postcode":"4000",
    "addr:street":"Little Edward St",
    "iso:country":"AU",
    "sg:address":"Level 1 55 Little Edward St",
    "sg:city":"Spring Hill",
    "sg:classifiers":[
        {
            "category":"Personal",
            "type":"Services"
        }
    ],
    "sg:phone":"+61 7 3834 0200",
    "sg:postcode":"4000",
    "sg:province":"QLD",
    "sg:tags":[
        "counselling",
        "alcohol",
        "drug"
    ],
    "wof:name":"Alcohol & Drug Foundation -QLD",
    "wof:placetype":"venue"
},
  "geometry": {"coordinates":[153.02513122600001,-27.462770462],"type":"Point"}
}