{
  "type": "Feature",
  "properties": {
    "iso:country":"AU",
    "sg:address":"35 Grandis Drv",
    "sg:city":"Tuncurry",
    "sg:classifiers":[
        {
            "category":"Personal",
            "subcategory":"Beauty Salon",
            "type":"Services"
        }
    ],
    "sg:phone":"+61 2 6555 3343",
    "sg:postcode":"2428",
    "sg:province":"NSW",
    "sg:tags":[
        "hairdresser"
    ],
    "wof:name":"Jos Snip &#039;N&#039; Clip Hair Salon",
    "wof:placetype":"venue"
},
  "geometry": {"coordinates":[152.487976,-32.160366],"type":"Point"}
}