{
  "type": "Feature",
  "properties": {
    "addr:full":"Stephen St Urana NSW 2645",
    "addr:postcode":"2645",
    "addr:street":"Stephen St",
    "iso:country":"AU",
    "sg:address":"Stephen St",
    "sg:city":"Urana",
    "sg:classifiers":[
        {
            "category":"Commercial Area",
            "type":"Public Place"
        }
    ],
    "sg:phone":"+61 2 6920 8219",
    "sg:postcode":"2645",
    "sg:province":"NSW",
    "sg:tags":[
        "heavy",
        "carrier"
    ],
    "wof:name":"Hemphill B J",
    "wof:placetype":"venue"
},
  "geometry": {"coordinates":[146.26809692399999,-35.332698822],"type":"Point"}
}