{
  "type": "Feature",
  "properties": {
    "addr:full":"56 Godalla Rd Freemans Reach NSW 2756",
    "addr:housenumber":"56",
    "addr:postcode":"2756",
    "addr:street":"Godalla Rd",
    "iso:country":"AU",
    "sg:address":"56 Godalla Rd",
    "sg:city":"Freemans Reach",
    "sg:classifiers":[
        {
            "category":"Farming",
            "subcategory":"Livestock Farm",
            "type":"Manufacturing & Wholesale Goods"
        }
    ],
    "sg:phone":"+61 2 4579 7172",
    "sg:postcode":"2756",
    "sg:province":"NSW",
    "sg:tags":[
        "breeder",
        "horse",
        "stud"
    ],
    "wof:name":"Burke Paint & Quarter Horse Stud",
    "wof:placetype":"venue"
},
  "geometry": {"coordinates":[150.802536011,-33.5437164307],"type":"Point"}
}