{
  "type": "Feature",
  "properties": {
    "iso:country":"AU",
    "sg:address":"15/ 39 Banks St",
    "sg:city":"Monterey",
    "sg:classifiers":[
        {
            "category":"Professional",
            "subcategory":"Employment Agencies",
            "type":"Services"
        }
    ],
    "sg:phone":"+61 2 9553 8085",
    "sg:postcode":"2217",
    "sg:province":"NSW",
    "sg:tags":[
        "entertainer",
        "agent"
    ],
    "wof:name":"Executive Decision NSW Pty Ltd",
    "wof:placetype":"venue"
},
  "geometry": {"coordinates":[151.150864,-33.967934],"type":"Point"}
}