{
  "type": "Feature",
  "properties": {
    "iso:country":"AU",
    "sg:address":"28 Camp St",
    "sg:city":"Ballarat",
    "sg:classifiers":[
        {
            "category":"Organizations",
            "subcategory":"Labor Organization",
            "type":"Services"
        }
    ],
    "sg:phone":"+61 3 5333 7049",
    "sg:postcode":"3350",
    "sg:province":"VIC",
    "sg:tags":[
        "union"
    ],
    "wof:name":"Building Construction Furnishing Industry Federation Unions",
    "wof:placetype":"venue"
},
  "geometry": {"coordinates":[143.85943599999999,-37.560841],"type":"Point"}
}