{
  "type": "Feature",
  "properties": {
    "addr:full":"72- 80 Lake Rd Port Macquarie NSW 2444",
    "addr:housenumber":"80",
    "addr:postcode":"2444",
    "addr:street":"Lake Rd",
    "iso:country":"AU",
    "sg:address":"72- 80 Lake Rd",
    "sg:city":"Port Macquarie",
    "sg:classifiers":[
        {
            "category":"Health Services",
            "subcategory":"Doctor",
            "type":"Services"
        }
    ],
    "sg:phone":"+61 2 6583 2811",
    "sg:postcode":"2444",
    "sg:province":"NSW",
    "sg:tags":[
        "medical",
        "practitioner"
    ],
    "wof:name":"The Hermitage Family Medical Centre Pty Ltd",
    "wof:placetype":"venue"
},
  "geometry": {"coordinates":[152.90791300000001,-31.442917],"type":"Point"}
}