{
  "type": "Feature",
  "properties": {
    "iso:country":"AU",
    "sg:address":"2 Kent Rd",
    "sg:city":"Turramurra",
    "sg:classifiers":[
        {
            "category":"Building & Trades",
            "subcategory":"Construction",
            "type":"Services"
        }
    ],
    "sg:phone":"+61 2 9449 7126",
    "sg:postcode":"2074",
    "sg:province":"NSW",
    "sg:tags":[
        "renovation",
        "alterations",
        "extension",
        "contractor"
    ],
    "wof:name":"Mitchell R G Pty Ltd",
    "wof:placetype":"venue"
},
  "geometry": {"coordinates":[151.1459198,-33.7212905884],"type":"Point"}
}