{
  "type": "Feature",
  "properties": {
    "iso:country":"AU",
    "sg:address":"40a Education La",
    "sg:city":"Cremorne",
    "sg:classifiers":[
        {
            "category":"Professional",
            "subcategory":"Accounting & Tax Preparation",
            "type":"Services"
        }
    ],
    "sg:phone":"+61 2 9908 4293",
    "sg:postcode":"2090",
    "sg:province":"NSW",
    "sg:tags":[
        "accountant",
        "auditor"
    ],
    "wof:name":"Adams Lesley K M",
    "wof:placetype":"venue"
},
  "geometry": {"coordinates":[151.227386475,-33.8325843811],"type":"Point"}
}