{
  "type": "Feature",
  "properties": {
    "addr:full":"Lvl1/ 1371 Botany Rd Botany NSW 2019",
    "addr:housenumber":"1371",
    "addr:postcode":"2019",
    "addr:street":"Botany Rd",
    "iso:country":"AU",
    "sg:address":"Lvl1/ 1371 Botany Rd",
    "sg:city":"Botany",
    "sg:classifiers":[
        {
            "category":"Arena",
            "subcategory":"Sports Club",
            "type":"Entertainment"
        }
    ],
    "sg:phone":"+61 2 9666 8686",
    "sg:postcode":"2019",
    "sg:province":"NSW",
    "sg:tags":[
        "organisation",
        "sporting"
    ],
    "wof:name":"Eastern Suburbs Soccer Football Association",
    "wof:placetype":"venue"
},
  "geometry": {"coordinates":[151.195877075,-33.9432830811],"type":"Point"}
}