{
  "type": "Feature",
  "properties": {
    "addr:full":"39 Gladstone Rd Highgate Hill QLD 4101",
    "addr:housenumber":"39",
    "addr:postcode":"4101",
    "addr:street":"Gladstone Rd",
    "iso:country":"AU",
    "sg:address":"39 Gladstone Rd",
    "sg:city":"Highgate Hill",
    "sg:classifiers":[
        {
            "category":"Health Services",
            "subcategory":"Doctor",
            "type":"Services"
        }
    ],
    "sg:phone":"+61 7 3844 4000",
    "sg:postcode":"4101",
    "sg:province":"QLD",
    "sg:tags":[
        "medical",
        "practitioner"
    ],
    "wof:name":"Southcity 7 Day Family Medical Centre",
    "wof:placetype":"venue"
},
  "geometry": {"coordinates":[153.01956176799999,-27.4846725464],"type":"Point"}
}