{
  "type": "Feature",
  "properties": {
    "addr:full":"158 Melrose Drv Phillip ACT 2606",
    "addr:housenumber":"158",
    "addr:postcode":"2606",
    "addr:street":"Melrose Drv",
    "iso:country":"AU",
    "sg:address":"158 Melrose Drv",
    "sg:city":"Phillip",
    "sg:classifiers":[
        {
            "category":"Retail",
            "subcategory":"Auto Repair",
            "type":"Services"
        }
    ],
    "sg:phone":"+61 2 6121 2800",
    "sg:postcode":"2606",
    "sg:province":"ACT",
    "sg:tags":[
        "repairer",
        "motor",
        "engineer"
    ],
    "wof:name":"Holden",
    "wof:placetype":"venue"
},
  "geometry": {"coordinates":[149.08595275900001,-35.3529586792],"type":"Point"}
}