{
  "type": "Feature",
  "properties": {
    "addr:full":"12 Summerhaze Pl Hornsby NSW 2077",
    "addr:housenumber":"12",
    "addr:postcode":"2077",
    "addr:street":"Summerhaze Pl",
    "iso:country":"AU",
    "sg:address":"12 Summerhaze Pl",
    "sg:city":"Hornsby",
    "sg:classifiers":[
        {
            "category":"Arts & Performance",
            "subcategory":"Music",
            "type":"Entertainment"
        }
    ],
    "sg:phone":"+61 402 147 767",
    "sg:postcode":"2077",
    "sg:province":"NSW",
    "sg:tags":[
        "mobile",
        "jockey",
        "disc"
    ],
    "wof:name":"Ellison",
    "wof:placetype":"venue"
},
  "geometry": {"coordinates":[151.10038757300001,-33.6638870239],"type":"Point"}
}