{
  "type": "Feature",
  "properties": {
    "addr:full":"4 Ray Crt Scoresby VIC 3179",
    "addr:housenumber":"4",
    "addr:postcode":"3179",
    "addr:street":"Ray Crt",
    "iso:country":"AU",
    "sg:address":"4 Ray Crt",
    "sg:city":"Scoresby",
    "sg:classifiers":[
        {
            "category":"Building & Trades",
            "subcategory":"Landscaping Services",
            "type":"Services"
        }
    ],
    "sg:phone":"+61 419 519 858",
    "sg:postcode":"3179",
    "sg:province":"VIC",
    "sg:tags":[
        "gardener"
    ],
    "wof:name":"Mowing Systems Pty Ltd",
    "wof:placetype":"venue"
},
  "geometry": {"coordinates":[145.23533630399999,-37.8972930908],"type":"Point"}
}