{
  "type": "Feature",
  "properties": {
    "iso:country":"AU",
    "sg:address":"117a Wyndham St",
    "sg:city":"Shepparton",
    "sg:classifiers":[
        {
            "category":"Fast Food",
            "type":"Food & Drink"
        }
    ],
    "sg:phone":"+61 3 5821 4402",
    "sg:postcode":"3630",
    "sg:province":"VIC",
    "sg:tags":[
        "away",
        "take"
    ],
    "wof:name":"Riviera Pizza",
    "wof:placetype":"venue"
},
  "geometry": {"coordinates":[145.40054321299999,-36.3758468628],"type":"Point"}
}