{
  "type": "Feature",
  "properties": {
    "addr:full":"4/ 401 Manns Rd Gosford West NSW 2250",
    "addr:housenumber":"/ 401",
    "addr:postcode":"2250",
    "addr:street":"Manns Rd",
    "iso:country":"AU",
    "sg:address":"4/ 401 Manns Rd",
    "sg:city":"Gosford West",
    "sg:classifiers":[
        {
            "category":"Manufacturing",
            "subcategory":"Glass & Minerals",
            "type":"Manufacturing & Wholesale Goods"
        }
    ],
    "sg:phone":"+61 2 4322 4355",
    "sg:postcode":"2250",
    "sg:province":"NSW",
    "sg:tags":[
        "merchant",
        "granite",
        "marble"
    ],
    "wof:name":"Granite Transformations",
    "wof:placetype":"venue"
},
  "geometry": {"coordinates":[151.31918335,-33.4241867065],"type":"Point"}
}