{
  "type": "Feature",
  "properties": {
    "addr:full":"PO Box 14 Officer VIC 3809",
    "addr:postcode":"3809",
    "iso:country":"AU",
    "sg:address":"PO Box 14",
    "sg:city":"Officer",
    "sg:classifiers":[
        {
            "category":"Professional",
            "subcategory":"Computer Services",
            "type":"Services"
        }
    ],
    "sg:phone":"+61 412 643 548",
    "sg:postcode":"3809",
    "sg:province":"VIC",
    "sg:tags":[
        "repairs",
        "upgrade",
        "equipment"
    ],
    "wof:name":"Cardinia Consulting Services",
    "wof:placetype":"venue"
},
  "geometry": {"coordinates":[145.406036,-38.05938],"type":"Point"}
}