{
  "type": "Feature",
  "properties": {
    "addr:full":"Unit 2/ 14 Tradelink Rd Browns Plains QLD 4118",
    "addr:postcode":"4118",
    "addr:street":"14 Tradelink Rd",
    "iso:country":"AU",
    "sg:address":"Unit 2/ 14 Tradelink Rd",
    "sg:city":"Browns Plains",
    "sg:classifiers":[
        {
            "category":"Professional",
            "subcategory":"Engineering",
            "type":"Services"
        }
    ],
    "sg:phone":"+61 7 3800 3053",
    "sg:postcode":"4118",
    "sg:province":"QLD",
    "sg:tags":[
        "precision",
        "engineer"
    ],
    "wof:name":"Quality Assured Engineering",
    "wof:placetype":"venue"
},
  "geometry": {"coordinates":[153.03407287600001,-27.6648254395],"type":"Point"}
}