{
  "type": "Feature",
  "properties": {
    "iso:country":"AU",
    "sg:address":"Lvl1/ 22 Lilydale St",
    "sg:city":"Marrickville",
    "sg:classifiers":[
        {
            "category":"Organizations",
            "subcategory":"Professional Association",
            "type":"Services"
        }
    ],
    "sg:phone":"+61 2 9518 0891",
    "sg:postcode":"2204",
    "sg:province":"NSW",
    "sg:tags":[
        "web",
        "internet"
    ],
    "wof:name":"Video Internet Delivery Networks",
    "wof:placetype":"venue"
},
  "geometry": {"coordinates":[151.15327500000001,-33.908844],"type":"Point"}
}