{
  "type": "Feature",
  "properties": {
    "iso:country":"AU",
    "sg:address":"231 Main Rd",
    "sg:city":"McLaren Vale",
    "sg:classifiers":[
        {
            "category":"Autos & Motor Vehicles",
            "subcategory":"Auto Supplies",
            "type":"Retail Goods"
        }
    ],
    "sg:phone":"+61 8 8323 8166",
    "sg:postcode":"5171",
    "sg:province":"SA",
    "sg:tags":[
        "tyre"
    ],
    "wof:name":"Southern Vales Tyre & Battery Service Pty Ltd",
    "wof:placetype":"venue"
},
  "geometry": {"coordinates":[138.533203125,-35.2120132446],"type":"Point"}
}