{
  "type": "Feature",
  "properties": {
    "iso:country":"AU",
    "sg:address":"30 Delapine Pl",
    "sg:city":"Seventeen Mile Rocks",
    "sg:classifiers":[
        {
            "category":"Professional",
            "subcategory":"Accounting & Tax Preparation",
            "type":"Services"
        }
    ],
    "sg:phone":"+61 7 3375 3805",
    "sg:postcode":"4073",
    "sg:province":"QLD",
    "sg:tags":[
        "bookkeeping"
    ],
    "wof:name":"Centenary Bookkeeping Services",
    "wof:placetype":"venue"
},
  "geometry": {"coordinates":[152.960327148,-27.5488243103],"type":"Point"}
}