{
  "type": "Feature",
  "properties": {
    "iso:country":"AU",
    "sg:address":"36 Kularoo Drv",
    "sg:city":"Forster",
    "sg:classifiers":[
        {
            "category":"Home & Garden",
            "subcategory":"Carpets & Floor Coverings",
            "type":"Retail Goods"
        }
    ],
    "sg:phone":"+61 2 6555 2156",
    "sg:postcode":"2428",
    "sg:province":"NSW",
    "sg:tags":[
        "tile",
        "wall",
        "layer"
    ],
    "wof:name":"Great Lakes Ceramics",
    "wof:placetype":"venue"
},
  "geometry": {"coordinates":[152.51808199999999,-32.19672],"type":"Point"}
}