{
  "type": "Feature",
  "properties": {
    "addr:full":"South Coast Hwy Denmark WA 6333",
    "addr:postcode":"6333",
    "addr:street":"South Coast Hwy",
    "iso:country":"AU",
    "sg:address":"South Coast Hwy",
    "sg:city":"Denmark",
    "sg:classifiers":[
        {
            "category":"Farming",
            "subcategory":"Vineyard",
            "type":"Manufacturing & Wholesale Goods"
        }
    ],
    "sg:phone":"+61 8 9840 9349",
    "sg:postcode":"6333",
    "sg:province":"WA",
    "sg:tags":[
        "winery"
    ],
    "wof:name":"Bartholomew's Meadery",
    "wof:placetype":"venue"
},
  "geometry": {"coordinates":[117.3543396,-34.9601898193],"type":"Point"}
}