{
  "type": "Feature",
  "properties": {
    "iso:country":"AU",
    "sg:address":"26 kooringa Ave",
    "sg:city":"Cleveland",
    "sg:classifiers":[
        {
            "category":"Military Area",
            "subcategory":"Air Force Base",
            "type":"Public Place"
        }
    ],
    "sg:phone":"+61 1300 303 278",
    "sg:postcode":"4163",
    "sg:province":"QLD",
    "sg:tags":[
        "merchant",
        "eftpos",
        "facility"
    ],
    "wof:name":"Bill Buddy",
    "wof:placetype":"venue"
},
  "geometry": {"coordinates":[153.26974487300001,-27.5450649261],"type":"Point"}
}