{
  "type": "Feature",
  "properties": {
    "addr:full":"7 Langlands Rd Annangrove NSW 2156",
    "addr:housenumber":"7",
    "addr:postcode":"2156",
    "addr:street":"Langlands Rd",
    "iso:country":"AU",
    "sg:address":"7 Langlands Rd",
    "sg:city":"Annangrove",
    "sg:classifiers":[
        {
            "category":"Utilities",
            "subcategory":"Electric",
            "type":"Services"
        }
    ],
    "sg:phone":"+61 2 9679 1482",
    "sg:postcode":"2156",
    "sg:province":"NSW",
    "sg:tags":[
        "electrical",
        "contractor"
    ],
    "wof:name":"Corrigan Electrics",
    "wof:placetype":"venue"
},
  "geometry": {"coordinates":[150.94276428200001,-33.6630096436],"type":"Point"}
}