{
  "type": "Feature",
  "properties": {
    "addr:full":"'A Rainbeau Place' Findlay La Yeppoon QLD 4703",
    "addr:postcode":"4703",
    "addr:street":"';Place;Findlay La",
    "iso:country":"AU",
    "sg:address":"'A Rainbeau Place' Findlay La",
    "sg:city":"Yeppoon",
    "sg:classifiers":[
        {
            "category":"Health Services",
            "subcategory":"Health Practitioner",
            "type":"Services"
        }
    ],
    "sg:phone":"+61 413 556 145",
    "sg:postcode":"4703",
    "sg:province":"QLD",
    "sg:tags":[
        "osteopath"
    ],
    "wof:name":"Asaadi Afshean",
    "wof:placetype":"venue"
},
  "geometry": {"coordinates":[150.74720764200001,-23.1294879913],"type":"Point"}
}