{
  "type": "Feature",
  "properties": {
    "iso:country":"AU",
    "sg:address":"Arndale Shoppng Cntre 224 Mt Dandenong Rd",
    "sg:city":"Croydon",
    "sg:classifiers":[
        {
            "category":"Health Services",
            "subcategory":"Dentist",
            "type":"Services"
        }
    ],
    "sg:phone":"+61 3 9723 7666",
    "sg:postcode":"3136",
    "sg:province":"VIC",
    "wof:name":"Fun Alan S C Dr",
    "wof:placetype":"venue"
},
  "geometry": {"coordinates":[145.28520202600001,-37.7992324829],"type":"Point"}
}