{
  "type": "Feature",
  "properties": {
    "iso:country":"AU",
    "sg:address":"Marine Pde",
    "sg:city":"The Entrance",
    "sg:classifiers":[
        {
            "category":"Communications",
            "subcategory":"News Services",
            "type":"Services"
        }
    ],
    "sg:phone":"+61 2 4333 5377",
    "sg:postcode":"2261",
    "sg:province":"NSW",
    "sg:tags":[
        "information",
        "tourist",
        "attractions"
    ],
    "wof:name":"The Entrance Town Centre Management",
    "wof:placetype":"venue"
},
  "geometry": {"coordinates":[151.496399,-33.344421],"type":"Point"}
}