{
  "type": "Feature",
  "properties": {
    "addr:full":"Cnr Fearnley & Kenny Sts Cairns QLD 4870",
    "addr:postcode":"4870",
    "addr:street":"Cnr Fearnley & Kenny Sts",
    "iso:country":"AU",
    "sg:address":"Cnr Fearnley & Kenny Sts",
    "sg:city":"Cairns",
    "sg:classifiers":[
        {
            "category":"Manufacturing",
            "subcategory":"Motor Vehicles & Parts",
            "type":"Manufacturing & Wholesale Goods"
        }
    ],
    "sg:phone":"+61 13 12 28",
    "sg:postcode":"4870",
    "sg:province":"QLD",
    "sg:tags":[
        "engine",
        "equipment",
        "diesel"
    ],
    "wof:name":"Hastings Deering",
    "wof:placetype":"venue"
},
  "geometry": {"coordinates":[145.772247314,-16.9380016327],"type":"Point"}
}