{
  "type": "Feature",
  "properties": {
    "addr:full":"Shop 3, 89 Plenty Rd Bundoora VIC 3083",
    "addr:housenumber":"shop;89",
    "addr:postcode":"3083",
    "addr:street":"Plenty Rd",
    "iso:country":"AU",
    "sg:address":"Shop 3, 89 Plenty Rd",
    "sg:city":"Bundoora",
    "sg:classifiers":[
        {
            "category":"Fast Food",
            "type":"Food & Drink"
        }
    ],
    "sg:phone":"+61 3 9467 7177",
    "sg:postcode":"3083",
    "sg:province":"VIC",
    "sg:tags":[
        "away",
        "take"
    ],
    "wof:name":"Babaluie's Pizza & Pasta Cafe",
    "wof:placetype":"venue"
},
  "geometry": {"coordinates":[145.059936523,-37.6947555542],"type":"Point"}
}