{
  "type": "Feature",
  "properties": {
    "addr:full":"110 High St Northcote VIC 3070",
    "addr:housenumber":"110",
    "addr:postcode":"3070",
    "addr:street":"High St",
    "iso:country":"AU",
    "sg:address":"110 High St",
    "sg:city":"Northcote",
    "sg:classifiers":[
        {
            "category":"Banks & Credit Unions",
            "subcategory":"Investment Brokerage",
            "type":"Services"
        }
    ],
    "sg:phone":"+61 3 9489 9710",
    "sg:postcode":"3070",
    "sg:province":"VIC",
    "wof:name":"Bleakleys Ltd",
    "wof:placetype":"venue"
},
  "geometry": {"coordinates":[144.99714700000001,-37.779453],"type":"Point"}
}