{
  "type": "Feature",
  "properties": {
    "addr:full":"PO Box 124 Parap NT 0820",
    "addr:postcode":"nt 0820",
    "iso:country":"AU",
    "sg:address":"PO Box 124",
    "sg:city":"Parap",
    "sg:classifiers":[
        {
            "category":"Real Estate",
            "subcategory":"Real Estate Agent",
            "type":"Services"
        }
    ],
    "sg:phone":"+61 8 8981 6758",
    "sg:postcode":"0820",
    "sg:province":"NT",
    "sg:tags":[
        "handyman's",
        "equipment",
        "hire",
        "builders",
        "contractor"
    ],
    "wof:name":"Mike Excavations Pty Ltd",
    "wof:placetype":"venue"
},
  "geometry": {"coordinates":[130.84628295900001,-12.4301576614],"type":"Point"}
}