{
  "type": "Feature",
  "properties": {
    "addr:full":"52 Malpas St Boyne Island QLD 4680",
    "addr:housenumber":"52",
    "addr:postcode":"4680",
    "addr:street":"Malpas St",
    "iso:country":"AU",
    "sg:address":"52 Malpas St",
    "sg:city":"Boyne Island",
    "sg:classifiers":[
        {
            "category":"Fast Food",
            "type":"Food & Drink"
        }
    ],
    "sg:phone":"+61 7 4973 7289",
    "sg:postcode":"4680",
    "sg:province":"QLD",
    "sg:tags":[
        "away",
        "take"
    ],
    "wof:name":"Mangrove Jacks",
    "wof:placetype":"venue"
},
  "geometry": {"coordinates":[151.34928894000001,-23.9588336945],"type":"Point"}
}