{
  "type": "Feature",
  "properties": {
    "iso:country":"AU",
    "sg:address":"Waterloo Rd",
    "sg:city":"Waterloo",
    "sg:classifiers":[
        {
            "category":"Farming",
            "subcategory":"Farm",
            "type":"Manufacturing & Wholesale Goods"
        }
    ],
    "sg:phone":"+61 8 9726 3107",
    "sg:postcode":"6228",
    "sg:province":"WA",
    "sg:tags":[
        "farmer"
    ],
    "wof:name":"Edwards G J & C M",
    "wof:placetype":"venue"
},
  "geometry": {"coordinates":[115.770554,-33.32494],"type":"Point"}
}