{
  "type": "Feature",
  "properties": {
    "addr:full":"137 Outrim Ave Calwell ACT 2905",
    "addr:housenumber":"137",
    "addr:postcode":"2905",
    "addr:street":"Outrim Ave",
    "iso:country":"AU",
    "sg:address":"137 Outrim Ave",
    "sg:city":"Calwell",
    "sg:classifiers":[
        {
            "category":"Professional",
            "subcategory":"Art Services",
            "type":"Services"
        }
    ],
    "sg:phone":"+61 415 263 738",
    "sg:postcode":"2905",
    "sg:province":"ACT",
    "sg:tags":[
        "decorator",
        "painter"
    ],
    "wof:name":"Ezy Azz Painting Services",
    "wof:placetype":"venue"
},
  "geometry": {"coordinates":[149.11175537099999,-35.4353752136],"type":"Point"}
}