{
  "type": "Feature",
  "properties": {
    "iso:country":"AU",
    "sg:address":"17 Bonney Ave",
    "sg:city":"Clayfield",
    "sg:classifiers":[
        {
            "category":"Travel",
            "subcategory":"Hostel",
            "type":"Entertainment"
        }
    ],
    "sg:phone":"+61 7 3862 3342",
    "sg:postcode":"4011",
    "sg:province":"QLD",
    "sg:tags":[
        "home"
    ],
    "wof:name":"Montray Villa Hostel",
    "wof:placetype":"venue"
},
  "geometry": {"coordinates":[153.04638700000001,-27.426897],"type":"Point"}
}