{
  "type": "Feature",
  "properties": {
    "addr:full":"313 Princess Hwy Werribee VIC 3030",
    "addr:housenumber":"313",
    "addr:postcode":"3030",
    "addr:street":"Princess Hwy",
    "iso:country":"AU",
    "sg:address":"313 Princess Hwy",
    "sg:city":"Werribee",
    "sg:classifiers":[
        {
            "category":"Home & Garden",
            "subcategory":"Household Appliances",
            "type":"Retail Goods"
        }
    ],
    "sg:phone":"+61 3 8742 3911",
    "sg:postcode":"3030",
    "sg:province":"VIC",
    "sg:tags":[
        "heating",
        "system"
    ],
    "wof:name":"Superior Heating & Cooling",
    "wof:placetype":"venue"
},
  "geometry": {"coordinates":[144.698013,-37.885269],"type":"Point"}
}