{
  "type": "Feature",
  "properties": {
    "addr:full":"46 Hampstead Rd Broadview SA 5083",
    "addr:housenumber":"46",
    "addr:postcode":"5083",
    "addr:street":"Hampstead Rd",
    "iso:country":"AU",
    "sg:address":"46 Hampstead Rd",
    "sg:city":"Broadview",
    "sg:classifiers":[
        {
            "category":"Deli",
            "type":"Food & Drink"
        }
    ],
    "sg:phone":"+61 8 8269 6278",
    "sg:postcode":"5083",
    "sg:province":"SA",
    "sg:tags":[
        "delicatessen"
    ],
    "wof:name":"Broadview Deli & Snackbar",
    "wof:placetype":"venue"
},
  "geometry": {"coordinates":[138.619537353,-34.8797912598],"type":"Point"}
}