{
  "type": "Feature",
  "properties": {
    "addr:full":"86 Woodward St Edge Hill QLD 4870",
    "addr:housenumber":"86",
    "addr:postcode":"4870",
    "addr:street":"Woodward St",
    "iso:country":"AU",
    "sg:address":"86 Woodward St",
    "sg:city":"Edge Hill",
    "sg:classifiers":[
        {
            "category":"Food & Beverages",
            "subcategory":"Liquor & Beverages",
            "type":"Retail Goods"
        }
    ],
    "sg:phone":"+61 7 4032 5236",
    "sg:postcode":"4870",
    "sg:province":"QLD",
    "sg:tags":[
        "store"
    ],
    "wof:name":"Edge Hill Bottle Shop",
    "wof:placetype":"venue"
},
  "geometry": {"coordinates":[145.74055480999999,-16.9009666443],"type":"Point"}
}