{
  "type": "Feature",
  "properties": {
    "iso:country":"AU",
    "sg:address":"48 Dudley St",
    "sg:city":"Pagewood",
    "sg:classifiers":[
        {
            "category":"Education",
            "subcategory":"Special Training",
            "type":"Public Place"
        }
    ],
    "sg:phone":"+61 2 9316 4996",
    "sg:postcode":"2035",
    "sg:province":"NSW",
    "sg:tags":[
        "tuition-educational"
    ],
    "wof:name":"Faxmaths",
    "wof:placetype":"venue"
},
  "geometry": {"coordinates":[151.20994567899999,-33.941444397],"type":"Point"}
}