{
  "type": "Feature",
  "properties": {
    "iso:country":"AU",
    "sg:address":"PO Box 1196",
    "sg:city":"Clayton South",
    "sg:classifiers":[
        {
            "category":"Education",
            "subcategory":"Music School",
            "type":"Public Place"
        }
    ],
    "sg:phone":"+61 408 136 686",
    "sg:postcode":"3169",
    "sg:province":"VIC",
    "sg:tags":[
        "choir",
        "bands",
        "orchestra"
    ],
    "wof:name":"We&#039;re Cruisin",
    "wof:placetype":"venue"
},
  "geometry": {"coordinates":[145.12875366200001,-37.9418411255],"type":"Point"}
}