{
  "type": "Feature",
  "properties": {
    "iso:country":"AU",
    "sg:address":"13 Bolton Point Rd",
    "sg:city":"Bolton Point",
    "sg:classifiers":[
        {
            "category":"Professional",
            "subcategory":"Accounting & Tax Preparation",
            "type":"Services"
        }
    ],
    "sg:phone":"+61 2 4959 6241",
    "sg:postcode":"2283",
    "sg:province":"NSW",
    "sg:tags":[
        "bookkeeping"
    ],
    "wof:name":"Add 123",
    "wof:placetype":"venue"
},
  "geometry": {"coordinates":[151.613937378,-33.0055618286],"type":"Point"}
}