{
  "type": "Feature",
  "properties": {
    "iso:country":"AU",
    "sg:address":"40 Cronulla St",
    "sg:city":"Cronulla",
    "sg:classifiers":[
        {
            "category":"Food & Beverages",
            "subcategory":"Bakery",
            "type":"Retail Goods"
        }
    ],
    "sg:phone":"+61 2 9527 6644",
    "sg:postcode":"2230",
    "sg:province":"NSW",
    "sg:tags":[
        "cake",
        "shop",
        "pastry"
    ],
    "wof:name":"Shakespeares Pie Co Australia Pty Ltd",
    "wof:placetype":"venue"
},
  "geometry": {"coordinates":[151.15286254899999,-34.052734375],"type":"Point"}
}