{
  "type": "Feature",
  "properties": {
    "addr:full":"Lvl 1, 3 - 5 Seymour St Ringwood VIC 3134",
    "addr:housenumber":"3 5",
    "addr:postcode":"3134",
    "addr:street":"Seymour St",
    "iso:country":"AU",
    "sg:address":"Lvl 1, 3 - 5 Seymour St",
    "sg:city":"Ringwood",
    "sg:classifiers":[
        {
            "category":"Education",
            "subcategory":"Special Training",
            "type":"Public Place"
        }
    ],
    "sg:phone":"+61 3 9870 8236",
    "sg:postcode":"3134",
    "sg:province":"VIC",
    "sg:tags":[
        "development"
    ],
    "wof:name":"Compact-Compliance & Corporate Training",
    "wof:placetype":"venue"
},
  "geometry": {"coordinates":[145.226028442,-37.8154602051],"type":"Point"}
}