{
  "type": "Feature",
  "properties": {
    "iso:country":"AU",
    "sg:address":"474 Anzac Hwy",
    "sg:city":"Camden Park",
    "sg:classifiers":[
        {
            "category":"Building & Trades",
            "subcategory":"Construction",
            "type":"Services"
        }
    ],
    "sg:phone":"+61 8 8376 6555",
    "sg:postcode":"5038",
    "sg:province":"SA",
    "sg:tags":[
        "management"
    ],
    "wof:name":"Scott Salisbury Homes",
    "wof:placetype":"venue"
},
  "geometry": {"coordinates":[138.538375855,-34.9749259949],"type":"Point"}
}