{
  "type": "Feature",
  "properties": {
    "iso:country":"AU",
    "sg:address":"117 Princes Hwy",
    "sg:city":"Murray Bridge",
    "sg:classifiers":[
        {
            "category":"Home & Garden",
            "subcategory":"Garden Supply",
            "type":"Retail Goods"
        }
    ],
    "sg:phone":"+61 400 323 703",
    "sg:postcode":"5253",
    "sg:province":"SA",
    "sg:tags":[
        "equipment"
    ],
    "wof:name":"Classic Garden Decor",
    "wof:placetype":"venue"
},
  "geometry": {"coordinates":[139.324127197,-35.1295013428],"type":"Point"}
}