{
  "type": "Feature",
  "properties": {
    "iso:country":"AU",
    "sg:address":"6 Curran Rd",
    "sg:city":"Blacktown",
    "sg:classifiers":[
        {
            "category":"Professional",
            "subcategory":"Computer Services",
            "type":"Services"
        }
    ],
    "sg:phone":"+61 2 9621 5136",
    "sg:postcode":"2148",
    "sg:province":"NSW",
    "sg:tags":[
        "repairs",
        "upgrade",
        "equipment"
    ],
    "wof:name":"Aarts Computer On-Site Service Pc Repairs & Sales",
    "wof:placetype":"venue"
},
  "geometry": {"coordinates":[150.89103698700001,-33.7540588379],"type":"Point"}
}