{
  "type": "Feature",
  "properties": {
    "addr:full":"105 Beresford Rd Lilydale VIC 3140",
    "addr:housenumber":"105",
    "addr:postcode":"3140",
    "addr:street":"Beresford Rd",
    "iso:country":"AU",
    "sg:address":"105 Beresford Rd",
    "sg:city":"Lilydale",
    "sg:classifiers":[
        {
            "category":"Social Services",
            "subcategory":"Child Care",
            "type":"Services"
        }
    ],
    "sg:phone":"+61 3 9739 4150",
    "sg:postcode":"3140",
    "sg:province":"VIC",
    "sg:tags":[
        "fleet",
        "management"
    ],
    "wof:name":"Serv Group (AUST)",
    "wof:placetype":"venue"
},
  "geometry": {"coordinates":[145.3487854,-37.7509880066],"type":"Point"}
}