{
  "type": "Feature",
  "properties": {
    "addr:full":"Suite 275a Hunter St Newcastle NSW 2300",
    "addr:housenumber":"275a",
    "addr:postcode":"2300",
    "addr:street":"Hunter St",
    "iso:country":"AU",
    "sg:address":"Suite 275a Hunter St",
    "sg:city":"Newcastle",
    "sg:classifiers":[
        {
            "category":"Building & Trades",
            "subcategory":"Construction",
            "type":"Services"
        }
    ],
    "sg:phone":"+61 2 4926 4165",
    "sg:postcode":"2300",
    "sg:province":"NSW",
    "sg:tags":[
        "contractor"
    ],
    "wof:name":"Pullin Projects",
    "wof:placetype":"venue"
},
  "geometry": {"coordinates":[151.77610799999999,-32.926693],"type":"Point"}
}