{
  "type": "Feature",
  "properties": {
    "addr:full":"75 Illaroo Rd Nowra North NSW 2541",
    "addr:housenumber":"75",
    "addr:postcode":"2541",
    "addr:street":"Illaroo Rd",
    "iso:country":"AU",
    "sg:address":"75 Illaroo Rd",
    "sg:city":"Nowra North",
    "sg:classifiers":[
        {
            "category":"Building & Trades",
            "subcategory":"Construction",
            "type":"Services"
        }
    ],
    "sg:phone":"+61 2 4421 5733",
    "sg:postcode":"2541",
    "sg:province":"NSW",
    "sg:tags":[
        "plasterboard",
        "plasterer",
        "fixer"
    ],
    "wof:name":"Arthur D W",
    "wof:placetype":"venue"
},
  "geometry": {"coordinates":[150.59280395499999,-34.8609886169],"type":"Point"}
}