{
  "type": "Feature",
  "properties": {
    "addr:full":"45 McLachlan St Long Jetty NSW 2261",
    "addr:housenumber":"45",
    "addr:postcode":"2261",
    "addr:street":"Mclachlan St",
    "iso:country":"AU",
    "sg:address":"45 McLachlan St",
    "sg:city":"Long Jetty",
    "sg:classifiers":[
        {
            "category":"Building & Trades",
            "subcategory":"Cleaning & Sanitation",
            "type":"Services"
        }
    ],
    "sg:phone":"+61 405 735 738",
    "sg:postcode":"2261",
    "sg:province":"NSW",
    "sg:tags":[
        "cleaner",
        "repairer",
        "roof"
    ],
    "wof:name":"Saphire Coast Plumbing and Roofing",
    "wof:placetype":"venue"
},
  "geometry": {"coordinates":[151.48355100000001,-33.364349],"type":"Point"}
}