{
  "type": "Feature",
  "properties": {
    "addr:full":"PO Box 1239 Atherton QLD 4883",
    "addr:postcode":"4883",
    "iso:country":"AU",
    "sg:address":"PO Box 1239",
    "sg:city":"Atherton",
    "sg:classifiers":[
        {
            "category":"Building & Trades",
            "subcategory":"Landscaping Services",
            "type":"Services"
        }
    ],
    "sg:phone":"+61 7 4091 3149",
    "sg:postcode":"4883",
    "sg:province":"QLD",
    "sg:tags":[
        "stump",
        "tree",
        "felling",
        "removal"
    ],
    "wof:name":"Simmo's Tree Lopping, Timber Salvaging & Saw Milling",
    "wof:placetype":"venue"
},
  "geometry": {"coordinates":[145.474975586,-17.2683391571],"type":"Point"}
}