{
  "type": "Feature",
  "properties": {
    "addr:full":"473 Newman Rd Geebung QLD 4034",
    "addr:housenumber":"473",
    "addr:postcode":"4034",
    "addr:street":"Newman Rd",
    "iso:country":"AU",
    "sg:address":"473 Newman Rd",
    "sg:city":"Geebung",
    "sg:classifiers":[
        {
            "category":"Real Estate",
            "subcategory":"Developer",
            "type":"Services"
        }
    ],
    "sg:phone":"+61 7 3865 3287",
    "sg:postcode":"4034",
    "sg:province":"QLD",
    "sg:tags":[
        "development"
    ],
    "wof:name":"Vann Investments Pty Ltd",
    "wof:placetype":"venue"
},
  "geometry": {"coordinates":[153.04917900000001,-27.362907],"type":"Point"}
}