{
  "type": "Feature",
  "properties": {
    "addr:full":"Mitton Ave Henley Beach SA 5022",
    "addr:postcode":"5022",
    "addr:street":"Mitton Ave",
    "iso:country":"AU",
    "sg:address":"Mitton Ave",
    "sg:city":"Henley Beach",
    "sg:classifiers":[
        {
            "category":"Shopping",
            "subcategory":"Computers & Home Electronics",
            "type":"Retail Goods"
        }
    ],
    "sg:phone":"+61 418 816 570",
    "sg:postcode":"5022",
    "sg:province":"SA",
    "sg:tags":[
        "small",
        "equipment",
        "business"
    ],
    "wof:name":"Bitzer",
    "wof:placetype":"venue"
},
  "geometry": {"coordinates":[138.504669189,-34.9156723022],"type":"Point"}
}