{
  "type": "Feature",
  "properties": {
    "addr:full":"Suite 2004 / 70 Lorimer St Docklands VIC 3008",
    "addr:housenumber":"2004 / 70",
    "addr:postcode":"3008",
    "addr:street":"Lorimer St",
    "iso:country":"AU",
    "sg:address":"Suite 2004 / 70 Lorimer St",
    "sg:city":"Docklands",
    "sg:classifiers":[
        {
            "category":"Professional",
            "subcategory":"Business Services",
            "type":"Services"
        }
    ],
    "sg:phone":"+61 3 9645 1193",
    "sg:postcode":"3008",
    "sg:province":"VIC",
    "sg:tags":[
        "management",
        "event"
    ],
    "wof:name":"Sublime Events",
    "wof:placetype":"venue"
},
  "geometry": {"coordinates":[144.944259644,-37.8248023987],"type":"Point"}
}