{
  "type": "Feature",
  "properties": {
    "addr:full":"8/ 31 Springfield lakes Blv Springfield Lakes QLD 4300",
    "addr:housenumber":"/ 31",
    "addr:postcode":"4300",
    "addr:street":"Springfield Lakes Blv Springfield",
    "iso:country":"AU",
    "sg:address":"8/ 31",
    "sg:city":"Springfield lakes Blv Springfield Lakes",
    "sg:classifiers":[
        {
            "category":"Building & Trades",
            "subcategory":"Construction",
            "type":"Services"
        }
    ],
    "sg:phone":"+61 7 3818 6545",
    "sg:postcode":"4300",
    "sg:province":"QLD",
    "sg:tags":[
        "contractor"
    ],
    "wof:name":"Ali & Son Building Construction",
    "wof:placetype":"venue"
},
  "geometry": {"coordinates":[152.92089843799999,-27.6681499481],"type":"Point"}
}