{
  "type": "Feature",
  "properties": {
    "iso:country":"AU",
    "sg:address":"Unit 1/ 44 Deering St",
    "sg:city":"Ulladulla",
    "sg:classifiers":[
        {
            "category":"Home & Garden",
            "subcategory":"Hardware",
            "type":"Retail Goods"
        }
    ],
    "sg:phone":"+61 2 4455 7577",
    "sg:postcode":"2539",
    "sg:province":"NSW",
    "sg:tags":[
        "plumber",
        "supply"
    ],
    "wof:name":"Your Local Paint Place",
    "wof:placetype":"venue"
},
  "geometry": {"coordinates":[150.47096252399999,-35.3621711731],"type":"Point"}
}