{
  "type": "Feature",
  "properties": {
    "addr:full":"121 Scotchmer St Fitzroy North VIC 3068",
    "addr:housenumber":"121",
    "addr:postcode":"3068",
    "addr:street":"Scotchmer St",
    "iso:country":"AU",
    "sg:address":"121 Scotchmer St",
    "sg:city":"Fitzroy North",
    "sg:classifiers":[
        {
            "category":"Farming",
            "subcategory":"Farm & Veterinary Services",
            "type":"Manufacturing & Wholesale Goods"
        }
    ],
    "sg:phone":"+61 3 9486 2774",
    "sg:postcode":"3068",
    "sg:province":"VIC",
    "sg:tags":[
        "poultry",
        "processing",
        "supply"
    ],
    "wof:name":"North Fitzroy Poultry",
    "wof:placetype":"venue"
},
  "geometry": {"coordinates":[144.98301696799999,-37.7830657959],"type":"Point"}
}