{
  "type": "Feature",
  "properties": {
    "iso:country":"AU",
    "sg:address":"How Rd",
    "sg:city":"Aldinga",
    "sg:classifiers":[
        {
            "category":"Utilities",
            "subcategory":"Recycling",
            "type":"Services"
        }
    ],
    "sg:phone":"+61 8 8556 5654",
    "sg:postcode":"5173",
    "sg:province":"SA",
    "wof:name":"Aldinga Recycle Centre",
    "wof:placetype":"venue"
},
  "geometry": {"coordinates":[138.47056579599999,-35.2701072693],"type":"Point"}
}