{
  "type": "Feature",
  "properties": {
    "addr:full":"10 Daly St South Yarra VIC 3141",
    "addr:housenumber":"10",
    "addr:postcode":"3141",
    "addr:street":"Daly St",
    "iso:country":"AU",
    "sg:address":"10 Daly St",
    "sg:city":"South Yarra",
    "sg:classifiers":[
        {
            "category":"Social Services",
            "subcategory":"Adult Care",
            "type":"Services"
        }
    ],
    "sg:phone":"+61 3 9829 9100",
    "sg:postcode":"3141",
    "sg:province":"VIC",
    "sg:tags":[
        "aged"
    ],
    "sg:website":"http://www.nextthealth.com.au",
    "wof:name":"Nextt Health",
    "wof:placetype":"venue"
},
  "geometry": {"coordinates":[144.99464416500001,-37.8377685547],"type":"Point"}
}