{
  "type": "Feature",
  "properties": {
    "addr:full":"18- 20 George St Sandringham VIC 3191",
    "addr:housenumber":"20",
    "addr:postcode":"3191",
    "addr:street":"George St",
    "iso:country":"AU",
    "sg:address":"18- 20 George St",
    "sg:city":"Sandringham",
    "sg:classifiers":[
        {
            "category":"Insurance",
            "subcategory":"Hazard Insurance",
            "type":"Services"
        }
    ],
    "sg:phone":"+61 1300 369 769",
    "sg:postcode":"3191",
    "sg:province":"VIC",
    "sg:tags":[
        "motor",
        "vehicle"
    ],
    "wof:name":"Torque Underwriting - Melbourne",
    "wof:placetype":"venue"
},
  "geometry": {"coordinates":[145.02862548799999,-37.9613723755],"type":"Point"}
}