{
  "type": "Feature",
  "properties": {
    "iso:country":"AU",
    "sg:address":"21 Park Ave",
    "sg:city":"Coffs Harbour",
    "sg:classifiers":[
        {
            "category":"Airline",
            "type":"Transportation"
        }
    ],
    "sg:phone":"+61 2 6651 2456",
    "sg:postcode":"2450",
    "sg:province":"NSW",
    "sg:tags":[
        "agent"
    ],
    "wof:name":"City Centre Travel Service",
    "wof:placetype":"venue"
},
  "geometry": {"coordinates":[153.114487,-30.298264],"type":"Point"}
}