{
  "type": "Feature",
  "properties": {
    "addr:full":"21 Park Ave Coffs Harbour NSW 2450",
    "addr:housenumber":"21",
    "addr:postcode":"2450",
    "addr:street":"Park Ave",
    "iso:country":"AU",
    "sg:address":"21 Park Ave",
    "sg:city":"Coffs Harbour",
    "sg:classifiers":[
        {
            "category":"Airline",
            "type":"Transportation"
        }
    ],
    "sg:phone":"+61 2 6651 2456",
    "sg:postcode":"2450",
    "sg:province":"NSW",
    "sg:tags":[
        "agent"
    ],
    "wof:name":"City Centre Travel Service",
    "wof:placetype":"venue"
},
  "geometry": {"coordinates":[153.114487,-30.298264],"type":"Point"}
}