{
  "type": "Feature",
  "properties": {
    "addr:full":"9 Etty St Castlemaine VIC 3450",
    "addr:housenumber":"9",
    "addr:postcode":"3450",
    "addr:street":"Etty St",
    "iso:country":"AU",
    "sg:address":"9 Etty St",
    "sg:city":"Castlemaine",
    "sg:classifiers":[
        {
            "category":"Education",
            "subcategory":"Kindergarten",
            "type":"Public Place"
        }
    ],
    "sg:phone":"+61 3 5472 2432",
    "sg:postcode":"3450",
    "sg:province":"VIC",
    "sg:tags":[
        "pre-schools"
    ],
    "wof:name":"Castlemaine (South) Kindergarten",
    "wof:placetype":"venue"
},
  "geometry": {"coordinates":[144.214752197,-37.0776405334],"type":"Point"}
}