{
  "type": "Feature",
  "properties": {
    "addr:full":"281 Orrong Rd St Kilda East VIC 3183",
    "addr:housenumber":"281",
    "addr:postcode":"3183",
    "addr:street":"Orrong Rd",
    "iso:country":"AU",
    "sg:address":"281 Orrong Rd St",
    "sg:city":"Kilda East",
    "sg:classifiers":[
        {
            "category":"Health Services",
            "subcategory":"Dentist",
            "type":"Services"
        }
    ],
    "sg:phone":"+61 3 9527 2273",
    "sg:postcode":"3183",
    "sg:province":"VIC",
    "wof:name":"Kolber B Dr & Jacobson S Dr",
    "wof:placetype":"venue"
},
  "geometry": {"coordinates":[145.00906372099999,-37.8672790527],"type":"Point"}
}