{
  "type": "Feature",
  "properties": {
    "addr:full":"Suite 405/ 81 Queens Rd Melbourne VIC 3004",
    "addr:housenumber":"/ 81",
    "addr:postcode":"3004",
    "addr:street":"Queens Rd",
    "iso:country":"AU",
    "sg:address":"Suite 405/ 81 Queens Rd",
    "sg:city":"Melbourne",
    "sg:classifiers":[
        {
            "category":"Sports & Exercise",
            "subcategory":"Sports Center",
            "type":"Entertainment"
        }
    ],
    "sg:phone":"+61 403 886 779",
    "sg:postcode":"3004",
    "sg:province":"VIC",
    "sg:tags":[
        "coach",
        "tennis"
    ],
    "wof:name":"Dan Power Tennis",
    "wof:placetype":"venue"
},
  "geometry": {"coordinates":[144.97952270499999,-37.8536186218],"type":"Point"}
}