{
  "type": "Feature",
  "properties": {
    "addr:full":"1894 Gold Coast Hwy Miami QLD 4220",
    "addr:housenumber":"1894",
    "addr:postcode":"4220",
    "addr:street":"Gold Coast Hwy",
    "iso:country":"AU",
    "sg:address":"1894 Gold Coast Hwy",
    "sg:city":"Miami",
    "sg:classifiers":[
        {
            "category":"Health Services",
            "subcategory":"Dentist",
            "type":"Services"
        }
    ],
    "sg:phone":"+61 7 5576 3244",
    "sg:postcode":"4220",
    "sg:province":"QLD",
    "sg:tags":[
        "dental",
        "prosthetist"
    ],
    "wof:name":"Anthony C Nest",
    "wof:placetype":"venue"
},
  "geometry": {"coordinates":[153.445602417,-28.0773773193],"type":"Point"}
}