{
  "type": "Feature",
  "properties": {
    "iso:country":"AU",
    "sg:address":"85 Hargreaves Rd",
    "sg:city":"West End",
    "sg:classifiers":[
        {
            "category":"Retail",
            "subcategory":"Self-service Laundry",
            "type":"Services"
        }
    ],
    "sg:phone":"+61 7 3278 1838",
    "sg:postcode":"4101",
    "sg:province":"QLD",
    "wof:name":"Rob Cadden Laundries",
    "wof:placetype":"venue"
},
  "geometry": {"coordinates":[153.00677490199999,-27.4826107025],"type":"Point"}
}