{
  "type": "Feature",
  "properties": {
    "addr:full":"467b Hawthorn Rd Caulfield South VIC 3162",
    "addr:housenumber":"467b",
    "addr:postcode":"3162",
    "addr:street":"Hawthorn Rd",
    "iso:country":"AU",
    "sg:address":"467b Hawthorn Rd",
    "sg:city":"Caulfield South",
    "sg:classifiers":[
        {
            "category":"Organizations",
            "subcategory":"Professional Association",
            "type":"Services"
        }
    ],
    "sg:phone":"+61 1300 463 362",
    "sg:postcode":"3162",
    "sg:province":"VIC",
    "sg:tags":[
        "web",
        "internet"
    ],
    "wof:name":"inDemand",
    "wof:placetype":"venue"
},
  "geometry": {"coordinates":[145.02070617699999,-37.8944396973],"type":"Point"}
}