{
  "type": "Feature",
  "properties": {
    "iso:country":"AU",
    "sg:address":"6 Cowper St",
    "sg:city":"Granville",
    "sg:classifiers":[
        {
            "category":"Building & Trades",
            "subcategory":"Equipment Rental",
            "type":"Services"
        }
    ],
    "sg:phone":"+61 2 9637 0444",
    "sg:postcode":"2142",
    "sg:province":"NSW",
    "sg:tags":[
        "party",
        "hire"
    ],
    "wof:name":"Astrodisc Pty Ltd",
    "wof:placetype":"venue"
},
  "geometry": {"coordinates":[151.01495361299999,-33.8327636719],"type":"Point"}
}