{
  "type": "Feature",
  "properties": {
    "addr:full":"24 Station St Werribee VIC 3030",
    "addr:housenumber":"24",
    "addr:postcode":"3030",
    "addr:street":"Station St",
    "iso:country":"AU",
    "sg:address":"24 Station St",
    "sg:city":"Werribee",
    "sg:classifiers":[
        {
            "category":"Personal",
            "subcategory":"Beauty Salon",
            "type":"Services"
        }
    ],
    "sg:phone":"+61 3 9741 8979",
    "sg:postcode":"3030",
    "sg:province":"VIC",
    "sg:tags":[
        "hairdresser"
    ],
    "wof:name":"Lentini D & Sammartino V",
    "wof:placetype":"venue"
},
  "geometry": {"coordinates":[144.66171299999999,-37.900375],"type":"Point"}
}