{
  "type": "Feature",
  "properties": {
    "addr:full":"5/ 12 Dulacca St Acacia Ridge QLD 4110",
    "addr:housenumber":"/ 12",
    "addr:postcode":"4110",
    "addr:street":"Dulacca St",
    "iso:country":"AU",
    "sg:address":"5/ 12 Dulacca St",
    "sg:city":"Acacia Ridge",
    "sg:classifiers":[
        {
            "category":"Manufacturing",
            "subcategory":"Metals",
            "type":"Manufacturing & Wholesale Goods"
        }
    ],
    "sg:phone":"+61 7 3273 7997",
    "sg:postcode":"4110",
    "sg:province":"QLD",
    "sg:tags":[
        "sheet",
        "worker"
    ],
    "wof:name":"Alpha Sheetmetal",
    "wof:placetype":"venue"
},
  "geometry": {"coordinates":[153.035614014,-27.592622757],"type":"Point"}
}