{
  "type": "Feature",
  "properties": {
    "addr:full":"PO Box 378 Maryborough, QLD 3465 Maryborough VIC 3465",
    "addr:postcode":"3465;3465",
    "iso:country":"AU",
    "sg:address":"PO Box 378 Maryborough, QLD 3465",
    "sg:city":"Maryborough",
    "sg:classifiers":[
        {
            "category":"Government",
            "subcategory":"Post Office",
            "type":"Public Place"
        }
    ],
    "sg:phone":"+61 427 309 358",
    "sg:postcode":"3465",
    "sg:province":"VIC",
    "sg:tags":[
        "equipment",
        "hole",
        "contractor"
    ],
    "wof:name":"Tama Plant Hire",
    "wof:placetype":"venue"
},
  "geometry": {"coordinates":[143.73561096200001,-37.0486412048],"type":"Point"}
}