{
  "type": "Feature",
  "properties": {
    "addr:full":"Shop 29 Underwood Market Place 3215 Logan Rd Underwood QLD 4119",
    "addr:housenumber":"shop 29;3215",
    "addr:postcode":"4119",
    "addr:street":"Underwood Market Place;Logan Rd",
    "iso:country":"AU",
    "sg:address":"Shop 29 Underwood Market Place 3215 Logan Rd",
    "sg:city":"Underwood",
    "sg:classifiers":[
        {
            "category":"Travel",
            "subcategory":"Travel Agent",
            "type":"Entertainment"
        }
    ],
    "sg:phone":"+61 13 18 66",
    "sg:postcode":"4119",
    "sg:province":"QLD",
    "sg:tags":[
        "consultant"
    ],
    "wof:name":"Flight Centre",
    "wof:placetype":"venue"
},
  "geometry": {"coordinates":[153.11070251500001,-27.6068115234],"type":"Point"}
}