{
  "type": "Feature",
  "properties": {
    "addr:full":"21 Green St Newmarket QLD 4051",
    "addr:housenumber":"21",
    "addr:postcode":"4051",
    "addr:street":"Green St",
    "iso:country":"AU",
    "sg:address":"21 Green St",
    "sg:city":"Newmarket",
    "sg:classifiers":[
        {
            "category":"Professional",
            "subcategory":"Accounting & Tax Preparation",
            "type":"Services"
        }
    ],
    "sg:phone":"+61 7 3356 5166",
    "sg:postcode":"4051",
    "sg:province":"QLD",
    "sg:tags":[
        "consultant",
        "taxation"
    ],
    "wof:name":"Property Depreciation Specialist",
    "wof:placetype":"venue"
},
  "geometry": {"coordinates":[153.009597778,-27.4346199036],"type":"Point"}
}