{
  "type": "Feature",
  "properties": {
    "addr:full":"PO Box 57 Delamere SA 5204",
    "addr:postcode":"5204",
    "iso:country":"AU",
    "sg:address":"PO Box 57",
    "sg:city":"Delamere",
    "sg:classifiers":[
        {
            "category":"Education",
            "subcategory":"Special Training",
            "type":"Public Place"
        }
    ],
    "sg:phone":"+61 8 8598 3088",
    "sg:postcode":"5204",
    "sg:province":"SA",
    "sg:tags":[
        "development"
    ],
    "wof:name":"Cultural Diversity Services Pty Ltd",
    "wof:placetype":"venue"
},
  "geometry": {"coordinates":[138.219238281,-35.5537910461],"type":"Point"}
}