{
  "type": "Feature",
  "properties": {
    "iso:country":"AU",
    "sg:address":"PO Box 244",
    "sg:city":"Dallas",
    "sg:classifiers":[
        {
            "category":"Home & Garden",
            "subcategory":"Hardware",
            "type":"Retail Goods"
        }
    ],
    "sg:phone":"+61 411 174 000",
    "sg:postcode":"3047",
    "sg:province":"VIC",
    "sg:tags":[
        "pumping",
        "contractor"
    ],
    "wof:name":"Direct Concrete Pumping",
    "wof:placetype":"venue"
},
  "geometry": {"coordinates":[144.933029175,-37.6654891968],"type":"Point"}
}