{
  "type": "Feature",
  "properties": {
    "iso:country":"AU",
    "sg:address":"Unit 6/ 1 Bennelong Rd",
    "sg:city":"Homebush Bay",
    "sg:classifiers":[
        {
            "category":"Food & Beverages",
            "subcategory":"Liquor & Beverages",
            "type":"Retail Goods"
        }
    ],
    "sg:phone":"+61 2 9202 4350",
    "sg:postcode":"2127",
    "sg:province":"NSW",
    "sg:tags":[
        "store"
    ],
    "wof:name":"Liquor Marketing Group Ltd",
    "wof:placetype":"venue"
},
  "geometry": {"coordinates":[151.07632446299999,-33.8350524902],"type":"Point"}
}