{
  "type": "Feature",
  "properties": {
    "iso:country":"AU",
    "sg:address":"1911 Lyell Hwy",
    "sg:city":"Lawitta",
    "sg:classifiers":[
        {
            "category":"Building & Trades",
            "subcategory":"Landscaping Services",
            "type":"Services"
        }
    ],
    "sg:phone":"+61 3 6261 4385",
    "sg:postcode":"7140",
    "sg:province":"TAS",
    "sg:tags":[
        "designer",
        "landscape",
        "contractor"
    ],
    "wof:name":"Majestic Garden & Landscaping",
    "wof:placetype":"venue"
},
  "geometry": {"coordinates":[147.02937299999999,-42.769924],"type":"Point"}
}