{
  "type": "Feature",
  "properties": {
    "addr:full":"139- 141 Franklin St Melbourne VIC 3000",
    "addr:housenumber":"141",
    "addr:postcode":"3000",
    "addr:street":"Franklin St",
    "iso:country":"AU",
    "sg:address":"139- 141 Franklin St",
    "sg:city":"Melbourne",
    "sg:classifiers":[
        {
            "category":"Building & Trades",
            "subcategory":"Cleaning & Sanitation",
            "type":"Services"
        }
    ],
    "sg:phone":"+61 3 9329 1744",
    "sg:postcode":"3000",
    "sg:province":"VIC",
    "sg:tags":[
        "chemical",
        "pressure",
        "steam",
        "contractor"
    ],
    "wof:name":"Menzies International (Aust) Pty Ltd",
    "wof:placetype":"venue"
},
  "geometry": {"coordinates":[144.959915161,-37.8084411621],"type":"Point"}
}