{
  "type": "Feature",
  "properties": {
    "addr:full":"106A Bailey St Grovedale VIC 3216",
    "addr:housenumber":"106a",
    "addr:postcode":"3216",
    "addr:street":"Bailey St",
    "iso:country":"AU",
    "sg:address":"106A Bailey St",
    "sg:city":"Grovedale",
    "sg:classifiers":[
        {
            "category":"Building & Trades",
            "subcategory":"Construction",
            "type":"Services"
        }
    ],
    "sg:phone":"+61 3 5243 5347",
    "sg:postcode":"3216",
    "sg:province":"VIC",
    "sg:tags":[
        "contractor"
    ],
    "wof:name":"Cameron D. C.",
    "wof:placetype":"venue"
},
  "geometry": {"coordinates":[144.347854614,-38.1951599121],"type":"Point"}
}