{
  "type": "Feature",
  "properties": {
    "iso:country":"AU",
    "sg:address":"120 Lang St",
    "sg:city":"Kurri Kurri",
    "sg:classifiers":[
        {
            "category":"Communications",
            "subcategory":"News Services",
            "type":"Services"
        }
    ],
    "sg:phone":"+61 2 4960 3999",
    "sg:postcode":"2327",
    "sg:province":"NSW",
    "sg:tags":[
        "information",
        "tourist",
        "attractions"
    ],
    "wof:name":"Hunter Valley Tourist Information Centre",
    "wof:placetype":"venue"
},
  "geometry": {"coordinates":[151.479904175,-32.8191604614],"type":"Point"}
}