{
  "type": "Feature",
  "properties": {
    "addr:full":"3 Ferndell St South Granville NSW 2142",
    "addr:housenumber":"3",
    "addr:postcode":"2142",
    "addr:street":"Ferndell St",
    "iso:country":"AU",
    "sg:address":"3 Ferndell St",
    "sg:city":"South Granville",
    "sg:classifiers":[
        {
            "category":"Wholesale",
            "subcategory":"Machinery & Supplies",
            "type":"Manufacturing & Wholesale Goods"
        }
    ],
    "sg:phone":"+61 2 9790 9790",
    "sg:postcode":"2142",
    "sg:province":"NSW",
    "sg:tags":[
        "rigging",
        "equipment",
        "hoisting"
    ],
    "wof:name":"Alimak Hek Pty Ltd",
    "wof:placetype":"venue"
},
  "geometry": {"coordinates":[151.009155273,-33.8645706177],"type":"Point"}
}