{
  "type": "Feature",
  "properties": {
    "iso:country":"AU",
    "sg:address":"124 Main St",
    "sg:city":"Bacchus Marsh",
    "sg:classifiers":[
        {
            "category":"Cafe",
            "type":"Food & Drink"
        }
    ],
    "sg:phone":"+61 3 5367 6281",
    "sg:postcode":"3340",
    "sg:province":"VIC",
    "wof:name":"Loot Cottage Garden Cafe",
    "wof:placetype":"venue"
},
  "geometry": {"coordinates":[144.436554,-37.675537],"type":"Point"}
}