{
  "type": "Feature",
  "properties": {
    "addr:full":"189 Reynell Rd Happy Valley SA 5159",
    "addr:housenumber":"189",
    "addr:postcode":"5159",
    "addr:street":"Reynell Rd",
    "iso:country":"AU",
    "sg:address":"189 Reynell Rd",
    "sg:city":"Happy Valley",
    "sg:classifiers":[
        {
            "category":"Home & Garden",
            "subcategory":"Building Materials",
            "type":"Retail Goods"
        }
    ],
    "sg:phone":"+61 402 125 509",
    "sg:postcode":"5159",
    "sg:province":"SA",
    "sg:tags":[
        "retaining",
        "wall"
    ],
    "wof:name":"Retaining Wall Concepts",
    "wof:placetype":"venue"
},
  "geometry": {"coordinates":[138.56573486299999,-35.0925102234],"type":"Point"}
}