{
  "type": "Feature",
  "properties": {
    "addr:full":"489 Payneham Rd Felixstow SA 5070",
    "addr:housenumber":"489",
    "addr:postcode":"5070",
    "addr:street":"Payneham Rd",
    "iso:country":"AU",
    "sg:address":"489 Payneham Rd",
    "sg:city":"Felixstow",
    "sg:classifiers":[
        {
            "category":"Restaurant",
            "type":"Food & Drink"
        }
    ],
    "sg:phone":"+61 8 8336 7577",
    "sg:postcode":"5070",
    "sg:province":"SA",
    "wof:name":"Sapore Ristorante",
    "wof:placetype":"venue"
},
  "geometry": {"coordinates":[138.65603637699999,-34.8897476196],"type":"Point"}
}