{
  "type": "Feature",
  "properties": {
    "addr:full":"76 Regent St Junee NSW 2663",
    "addr:housenumber":"76",
    "addr:postcode":"2663",
    "addr:street":"Regent St",
    "iso:country":"AU",
    "sg:address":"76 Regent St",
    "sg:city":"Junee",
    "sg:classifiers":[
        {
            "category":"Retail",
            "subcategory":"Storage",
            "type":"Services"
        }
    ],
    "sg:phone":"+61 2 6924 1295",
    "sg:postcode":"2663",
    "sg:province":"NSW",
    "sg:tags":[
        "removal",
        "furniture"
    ],
    "wof:name":"Cootamundra Removals",
    "wof:placetype":"venue"
},
  "geometry": {"coordinates":[147.57911682100001,-34.8588676453],"type":"Point"}
}