{
  "type": "Feature",
  "properties": {
    "iso:country":"AU",
    "sg:address":"637 Princes Hwy",
    "sg:city":"Tempe",
    "sg:classifiers":[
        {
            "category":"Professional",
            "subcategory":"Art Services",
            "type":"Services"
        }
    ],
    "sg:phone":"+61 2 9558 1355",
    "sg:postcode":"2044",
    "sg:province":"NSW",
    "sg:tags":[
        "picture",
        "frame",
        "framing"
    ],
    "wof:name":"Frame King",
    "wof:placetype":"venue"
},
  "geometry": {"coordinates":[151.16339099999999,-33.922386],"type":"Point"}
}