{
  "type": "Feature",
  "properties": {
    "addr:full":"70 Falvey St Ripley QLD 4306",
    "addr:housenumber":"70",
    "addr:postcode":"4306",
    "addr:street":"Falvey St",
    "iso:country":"AU",
    "sg:address":"70 Falvey St",
    "sg:city":"Ripley",
    "sg:classifiers":[
        {
            "category":"Health Services",
            "subcategory":"Health Practitioner",
            "type":"Services"
        }
    ],
    "sg:phone":"+61 7 3288 8565",
    "sg:postcode":"4306",
    "sg:province":"QLD",
    "sg:tags":[
        "acupuncture"
    ],
    "wof:name":"Litzow Mark",
    "wof:placetype":"venue"
},
  "geometry": {"coordinates":[152.789352417,-27.6651668549],"type":"Point"}
}