{
  "type": "Feature",
  "properties": {
    "iso:country":"AU",
    "sg:address":"125 Buchan St",
    "sg:city":"Bungalow",
    "sg:classifiers":[
        {
            "category":"Personal",
            "subcategory":"Beauty Salon",
            "type":"Services"
        }
    ],
    "sg:phone":"+61 7 4035 4486",
    "sg:postcode":"4870",
    "sg:province":"QLD",
    "sg:tags":[
        "hairdresser"
    ],
    "wof:name":"Meade Judith",
    "wof:placetype":"venue"
},
  "geometry": {"coordinates":[145.764801025,-16.9340438843],"type":"Point"}
}