{
  "type": "Feature",
  "properties": {
    "addr:full":"Level 1, 2 Edward St Brisbane QLD 4000",
    "addr:housenumber":"2",
    "addr:postcode":"4000",
    "addr:street":"Edward St",
    "iso:country":"AU",
    "sg:address":"Level 1, 2 Edward St",
    "sg:city":"Brisbane",
    "sg:classifiers":[
        {
            "category":"Real Estate",
            "subcategory":"Architect",
            "type":"Services"
        }
    ],
    "sg:phone":"+61 7 3012 7815",
    "sg:postcode":"4000",
    "sg:province":"QLD",
    "wof:name":"Schifilliti Peter",
    "wof:placetype":"venue"
},
  "geometry": {"coordinates":[153.03044128400001,-27.4720497131],"type":"Point"}
}