{
  "type": "Feature",
  "properties": {
    "iso:country":"AU",
    "sg:address":"49 Henry St",
    "sg:city":"Traralgon",
    "sg:classifiers":[
        {
            "category":"Health Services",
            "subcategory":"Health Practitioner",
            "type":"Services"
        }
    ],
    "sg:phone":"+61 3 5176 0586",
    "sg:postcode":"3844",
    "sg:province":"VIC",
    "sg:tags":[
        "pathologist",
        "speech"
    ],
    "wof:name":"P Jane Taylor",
    "wof:placetype":"venue"
},
  "geometry": {"coordinates":[146.52603149399999,-38.1975631714],"type":"Point"}
}