{
  "type": "Feature",
  "properties": {
    "addr:full":"285 Coventry St South Melbourne VIC 3205",
    "addr:housenumber":"285",
    "addr:postcode":"3205",
    "addr:street":"Coventry St",
    "iso:country":"AU",
    "sg:address":"285 Coventry St",
    "sg:city":"South Melbourne",
    "sg:classifiers":[
        {
            "category":"Shopping",
            "subcategory":"Baby Store",
            "type":"Retail Goods"
        }
    ],
    "sg:phone":"+61 3 9686 4111",
    "sg:postcode":"3205",
    "sg:province":"VIC",
    "sg:tags":[
        "children's",
        "wear"
    ],
    "wof:name":"Fragile",
    "wof:placetype":"venue"
},
  "geometry": {"coordinates":[144.958099,-37.832542],"type":"Point"}
}