{
  "type": "Feature",
  "properties": {
    "iso:country":"AU",
    "sg:address":"123 Framara Drv",
    "sg:city":"Kelso",
    "sg:classifiers":[
        {
            "category":"Manufacturing",
            "subcategory":"Musical Instruments",
            "type":"Manufacturing & Wholesale Goods"
        }
    ],
    "sg:phone":"+61 7 4774 0769",
    "sg:postcode":"4815",
    "sg:province":"QLD",
    "sg:tags":[
        "repair",
        "maker"
    ],
    "wof:name":"Music Aid",
    "wof:placetype":"venue"
},
  "geometry": {"coordinates":[146.735596,-19.382044],"type":"Point"}
}