{
  "type": "Feature",
  "properties": {
    "addr:full":"Shop 10 36 Quay St Bundaberg QLD 4670",
    "addr:housenumber":"shop 10 36",
    "addr:postcode":"4670",
    "addr:street":"Quay St",
    "iso:country":"AU",
    "sg:address":"Shop 10 36 Quay St",
    "sg:city":"Bundaberg",
    "sg:classifiers":[
        {
            "category":"Banks & Credit Unions",
            "subcategory":"Investment Brokerage",
            "type":"Services"
        }
    ],
    "sg:phone":"+61 407 754 111",
    "sg:postcode":"4670",
    "sg:province":"QLD",
    "sg:tags":[
        "finance",
        "broker"
    ],
    "wof:name":"Auscredits",
    "wof:placetype":"venue"
},
  "geometry": {"coordinates":[152.34910583499999,-24.8649101257],"type":"Point"}
}