{
  "type": "Feature",
  "properties": {
    "addr:full":"246 Pakington St Geelong West VIC 3218",
    "addr:housenumber":"246",
    "addr:postcode":"3218",
    "addr:street":"Pakington St",
    "iso:country":"AU",
    "sg:address":"246 Pakington St",
    "sg:city":"Geelong West",
    "sg:classifiers":[
        {
            "category":"Professional",
            "subcategory":"Art Services",
            "type":"Services"
        }
    ],
    "sg:phone":"+61 3 5229 2795",
    "sg:postcode":"3218",
    "sg:province":"VIC",
    "sg:tags":[
        "interior",
        "decorator"
    ],
    "wof:name":"Tassel Design",
    "wof:placetype":"venue"
},
  "geometry": {"coordinates":[144.34777832,-38.1442718506],"type":"Point"}
}