{
  "type": "Feature",
  "properties": {
    "iso:country":"AU",
    "sg:address":"277 Pirie St",
    "sg:city":"Adelaide",
    "sg:classifiers":[
        {
            "category":"Travel",
            "subcategory":"Hostel",
            "type":"Entertainment"
        }
    ],
    "sg:phone":"+61 8 8227 0349",
    "sg:postcode":"5000",
    "sg:province":"SA",
    "sg:tags":[
        "home"
    ],
    "wof:name":"Salvation Army Towards Independence Supported Accommodation Services",
    "wof:placetype":"venue"
},
  "geometry": {"coordinates":[138.610229492,-34.925365448],"type":"Point"}
}