{
  "type": "Feature",
  "properties": {
    "addr:full":"153- 163 Fitzmaurice St, Wga Wga Wagga Wagga NSW 2650",
    "addr:housenumber":"163",
    "addr:postcode":"2650",
    "addr:street":"Fitzmaurice St Wga",
    "iso:country":"AU",
    "sg:address":"153- 163",
    "sg:city":"Fitzmaurice St, Wga Wga Wagga Wagga",
    "sg:classifiers":[
        {
            "category":"Food & Beverages",
            "subcategory":"Fruits & Vegetables",
            "type":"Retail Goods"
        }
    ],
    "sg:phone":"+61 2 6921 4124",
    "sg:postcode":"2650",
    "sg:province":"NSW",
    "sg:tags":[
        "wholesale"
    ],
    "wof:name":"Kincaid Heritage Fruit Market",
    "wof:placetype":"venue"
},
  "geometry": {"coordinates":[147.36843872099999,-35.1027793884],"type":"Point"}
}