{
  "type": "Feature",
  "properties": {
    "addr:full":"147 Victoria Ave Albert Park VIC 3206",
    "addr:housenumber":"147",
    "addr:postcode":"3206",
    "addr:street":"Victoria Ave",
    "iso:country":"AU",
    "sg:address":"147 Victoria Ave",
    "sg:city":"Albert Park",
    "sg:classifiers":[
        {
            "category":"Food & Beverages",
            "subcategory":"Groceries & Convenience Stores",
            "type":"Retail Goods"
        }
    ],
    "sg:phone":"+61 3 9690 1649",
    "sg:postcode":"3206",
    "sg:province":"VIC",
    "wof:name":"7-Eleven Stores Pty Ltd",
    "wof:placetype":"venue"
},
  "geometry": {"coordinates":[144.949783,-37.846115],"type":"Point"}
}