{
  "type": "Feature",
  "properties": {
    "iso:country":"AU",
    "sg:address":"18 Archer Ave",
    "sg:city":"Ascot Vale",
    "sg:classifiers":[
        {
            "category":"Manufacturing",
            "subcategory":"Tools & Machinery",
            "type":"Manufacturing & Wholesale Goods"
        }
    ],
    "sg:phone":"+61 3 9370 9178",
    "sg:postcode":"3032",
    "sg:province":"VIC",
    "wof:name":"Kato Trading",
    "wof:placetype":"venue"
},
  "geometry": {"coordinates":[144.907425,-37.778961],"type":"Point"}
}