{
  "type": "Feature",
  "properties": {
    "addr:full":"Unit 17 Truck City Complex 1805-1825 Sydney Rd Campbellfield VIC 3061",
    "addr:postcode":"3061",
    "addr:street":"Sydney Rd",
    "iso:country":"AU",
    "sg:address":"Unit 17 Truck City Complex 1805-1825 Sydney Rd",
    "sg:city":"Campbellfield",
    "sg:classifiers":[
        {
            "category":"Retail",
            "subcategory":"Auto Repair",
            "type":"Services"
        }
    ],
    "sg:phone":"+61 3 9305 3711",
    "sg:postcode":"3061",
    "sg:province":"VIC",
    "sg:tags":[
        "wheel",
        "balancing",
        "alignment"
    ],
    "wof:name":"Hogan's Axle Correction",
    "wof:placetype":"venue"
},
  "geometry": {"coordinates":[144.94778442399999,-37.6478729248],"type":"Point"}
}