{
  "type": "Feature",
  "properties": {
    "iso:country":"AU",
    "sg:address":"PO Box 94",
    "sg:city":"Camp Hill",
    "sg:classifiers":[
        {
            "category":"Building & Trades",
            "subcategory":"Construction",
            "type":"Services"
        }
    ],
    "sg:phone":"+61 423 976 016",
    "sg:postcode":"4152",
    "sg:province":"QLD",
    "sg:tags":[
        "contractor"
    ],
    "wof:name":"Roxby Carpentry",
    "wof:placetype":"venue"
},
  "geometry": {"coordinates":[153.07696533199999,-27.50041008],"type":"Point"}
}