{
  "type": "Feature",
  "properties": {
    "addr:full":"1/ 18 Lyell St Fyshwick ACT 2609",
    "addr:housenumber":"/ 18",
    "addr:postcode":"2609",
    "addr:street":"Lyell St",
    "iso:country":"AU",
    "sg:address":"1/ 18 Lyell St",
    "sg:city":"Fyshwick",
    "sg:classifiers":[
        {
            "category":"Home & Garden",
            "subcategory":"Carpets & Floor Coverings",
            "type":"Retail Goods"
        }
    ],
    "sg:phone":"+61 2 6228 1186",
    "sg:postcode":"2609",
    "sg:province":"ACT",
    "sg:tags":[
        "wood"
    ],
    "wof:name":"Antalie Solid Timber Flooring",
    "wof:placetype":"venue"
},
  "geometry": {"coordinates":[149.17433166500001,-35.3279685974],"type":"Point"}
}