{
  "type": "Feature",
  "properties": {
    "addr:full":"3 Stent St Beechboro WA 6063",
    "addr:housenumber":"3",
    "addr:postcode":"6063",
    "addr:street":"Stent St",
    "iso:country":"AU",
    "sg:address":"3 Stent St",
    "sg:city":"Beechboro",
    "sg:classifiers":[
        {
            "category":"Shopping",
            "subcategory":"Stationery & Office Supplies",
            "type":"Retail Goods"
        }
    ],
    "sg:phone":"+61 412 553 712",
    "sg:postcode":"6063",
    "sg:province":"WA",
    "sg:tags":[
        "partition"
    ],
    "wof:name":"Boab Ceilings & Partitions",
    "wof:placetype":"venue"
},
  "geometry": {"coordinates":[115.94814300500001,-31.8673114777],"type":"Point"}
}