{
  "type": "Feature",
  "properties": {
    "addr:full":"PO Box 12 Sheffield TAS 7306",
    "addr:postcode":"7306",
    "iso:country":"AU",
    "sg:address":"PO Box 12",
    "sg:city":"Sheffield",
    "sg:classifiers":[
        {
            "category":"Farming",
            "subcategory":"Fish & Marine Products",
            "type":"Manufacturing & Wholesale Goods"
        }
    ],
    "sg:phone":"+61 3 6491 1439",
    "sg:postcode":"7306",
    "sg:province":"TAS",
    "sg:tags":[
        "organic"
    ],
    "wof:name":"Bio-Distributors - Biodynamic & Organic Wholesalers of Tasmania",
    "wof:placetype":"venue"
},
  "geometry": {"coordinates":[146.330872,-41.384521],"type":"Point"}
}