{
  "type": "Feature",
  "properties": {
    "iso:country":"AU",
    "sg:address":"17 Bellini Rd",
    "sg:city":"Burpengary",
    "sg:classifiers":[
        {
            "category":"Home & Garden",
            "subcategory":"Carpets & Floor Coverings",
            "type":"Retail Goods"
        }
    ],
    "sg:phone":"+61 7 3888 0585",
    "sg:postcode":"4505",
    "sg:province":"QLD",
    "sg:tags":[
        "tile",
        "wall",
        "layer"
    ],
    "wof:name":"Fiorello N & C Tiling Contractor",
    "wof:placetype":"venue"
},
  "geometry": {"coordinates":[152.968261719,-27.1609134674],"type":"Point"}
}