{
  "type": "Feature",
  "properties": {
    "iso:country":"AU",
    "sg:address":"75 Christie St",
    "sg:city":"St Leonards",
    "sg:classifiers":[
        {
            "category":"Travel",
            "subcategory":"Hotels & Motels",
            "type":"Entertainment"
        }
    ],
    "sg:phone":"+61 2 9439 2213",
    "sg:postcode":"2065",
    "sg:province":"NSW",
    "sg:tags":[
        "pub"
    ],
    "wof:name":"Gilroy's Hotel",
    "wof:placetype":"venue"
},
  "geometry": {"coordinates":[151.195602417,-33.8228530884],"type":"Point"}
}