{
  "type": "Feature",
  "properties": {
    "addr:full":"15 Bangor St Archerfield QLD 4108",
    "addr:housenumber":"15",
    "addr:postcode":"4108",
    "addr:street":"Bangor St",
    "iso:country":"AU",
    "sg:address":"15 Bangor St",
    "sg:city":"Archerfield",
    "sg:classifiers":[
        {
            "category":"Manufacturing",
            "subcategory":"Tools & Machinery",
            "type":"Manufacturing & Wholesale Goods"
        }
    ],
    "sg:phone":"+61 7 3272 7622",
    "sg:postcode":"4108",
    "sg:province":"QLD",
    "sg:tags":[
        "earth",
        "excavating",
        "moving",
        "equipment"
    ],
    "wof:name":"Roller Parts Australia",
    "wof:placetype":"venue"
},
  "geometry": {"coordinates":[153.01705932600001,-27.5628356934],"type":"Point"}
}