{
  "type": "Feature",
  "properties": {
    "iso:country":"AU",
    "sg:address":"189 Queen St",
    "sg:city":"Ayr",
    "sg:classifiers":[
        {
            "category":"Retail",
            "subcategory":"Auto Repair",
            "type":"Services"
        }
    ],
    "sg:phone":"+61 7 4783 3237",
    "sg:postcode":"4807",
    "sg:province":"QLD",
    "sg:tags":[
        "muffler",
        "exhaust",
        "system"
    ],
    "wof:name":"Ayr Exhaust And Service Centre",
    "wof:placetype":"venue"
},
  "geometry": {"coordinates":[147.40238952600001,-19.5788211823],"type":"Point"}
}