{
  "type": "Feature",
  "properties": {
    "iso:country":"AU",
    "sg:address":"6 Glenburnie Ave",
    "sg:city":"Torrens Park",
    "sg:classifiers":[
        {
            "category":"Education",
            "subcategory":"Music School",
            "type":"Public Place"
        }
    ],
    "sg:phone":"+61 403 175 913",
    "sg:postcode":"5062",
    "sg:province":"SA",
    "sg:tags":[
        "choir",
        "bands",
        "orchestra"
    ],
    "wof:name":"Beat That Entertainment",
    "wof:placetype":"venue"
},
  "geometry": {"coordinates":[138.61573791500001,-34.984375],"type":"Point"}
}