{
  "type": "Feature",
  "properties": {
    "iso:country":"AU",
    "sg:address":"Shop 2/ 14- 16 The Avenue",
    "sg:city":"Hurstville",
    "sg:classifiers":[
        {
            "category":"Health Services",
            "subcategory":"Dentist",
            "type":"Services"
        }
    ],
    "sg:phone":"+61 2 9570 9809",
    "sg:postcode":"2220",
    "sg:province":"NSW",
    "wof:name":"Lee Charles",
    "wof:placetype":"venue"
},
  "geometry": {"coordinates":[151.10694885300001,-33.9658584595],"type":"Point"}
}