{
  "type": "Feature",
  "properties": {
    "addr:full":"8 Joyce St Springvale VIC 3171",
    "addr:housenumber":"8",
    "addr:postcode":"3171",
    "addr:street":"Joyce St",
    "iso:country":"AU",
    "sg:address":"8 Joyce St",
    "sg:city":"Springvale",
    "sg:classifiers":[
        {
            "category":"Manufacturing",
            "subcategory":"Tools & Machinery",
            "type":"Manufacturing & Wholesale Goods"
        }
    ],
    "sg:phone":"+61 3 9574 1122",
    "sg:postcode":"3171",
    "sg:province":"VIC",
    "sg:tags":[
        "machine",
        "knife"
    ],
    "wof:name":"Australian Specialty Knife Pty Ltd",
    "wof:placetype":"venue"
},
  "geometry": {"coordinates":[145.150665283,-37.9337501526],"type":"Point"}
}