{
  "type": "Feature",
  "properties": {
    "iso:country":"AU",
    "sg:address":"U2/ 52 Warners Ave",
    "sg:city":"Bondi",
    "sg:classifiers":[
        {
            "category":"Professional",
            "subcategory":"Art Services",
            "type":"Services"
        }
    ],
    "sg:phone":"+61 2 9369 5863",
    "sg:postcode":"2026",
    "sg:province":"NSW",
    "sg:tags":[
        "decorator",
        "painter"
    ],
    "wof:name":"Master Palette",
    "wof:placetype":"venue"
},
  "geometry": {"coordinates":[151.27243042000001,-33.8848419189],"type":"Point"}
}