{
  "type": "Feature",
  "properties": {
    "iso:country":"AU",
    "sg:address":"74b Sheridan St",
    "sg:city":"Cairns",
    "sg:classifiers":[
        {
            "category":"Recreation",
            "subcategory":"Boat Charter",
            "type":"Entertainment"
        }
    ],
    "sg:phone":"+61 7 4031 4742",
    "sg:postcode":"4870",
    "sg:province":"QLD",
    "wof:name":"Cairns Reef Charter Services",
    "wof:placetype":"venue"
},
  "geometry": {"coordinates":[145.774047852,-16.9237747192],"type":"Point"}
}