{
  "type": "Feature",
  "properties": {
    "addr:full":"8 Milburn Pl Moonah West TAS 7009",
    "addr:housenumber":"8",
    "addr:postcode":"7009",
    "addr:street":"Milburn Pl",
    "iso:country":"AU",
    "sg:address":"8 Milburn Pl",
    "sg:city":"Moonah West",
    "sg:classifiers":[
        {
            "category":"Building & Trades",
            "subcategory":"Plumbing",
            "type":"Services"
        }
    ],
    "sg:phone":"+61 3 6272 3205",
    "sg:postcode":"7009",
    "sg:province":"TAS",
    "sg:tags":[
        "repair",
        "appliance",
        "system",
        "heating"
    ],
    "wof:name":"Robin White",
    "wof:placetype":"venue"
},
  "geometry": {"coordinates":[147.269073486,-42.8473472595],"type":"Point"}
}