{
  "type": "Feature",
  "properties": {
    "iso:country":"AU",
    "sg:address":"990 The Northern Rd",
    "sg:city":"Llandilo",
    "sg:classifiers":[
        {
            "category":"Retail",
            "subcategory":"Laundry & Dry Cleaning",
            "type":"Services"
        }
    ],
    "sg:phone":"+61 2 4729 2294",
    "sg:postcode":"2747",
    "sg:province":"NSW",
    "sg:tags":[
        "truck",
        "tip",
        "contractor"
    ],
    "wof:name":"M & T Tipper Hire Pty Ltd",
    "wof:placetype":"venue"
},
  "geometry": {"coordinates":[150.72254943900001,-33.7097358704],"type":"Point"}
}