{
  "type": "Feature",
  "properties": {
    "addr:full":"Unit 5, 295 Copeland St Wagga Wagga NSW 2650",
    "addr:housenumber":"295",
    "addr:postcode":"2650",
    "addr:street":"Copeland St",
    "iso:country":"AU",
    "sg:address":"Unit 5, 295 Copeland St",
    "sg:city":"Wagga Wagga",
    "sg:classifiers":[
        {
            "category":"Home & Garden",
            "subcategory":"Building Materials",
            "type":"Retail Goods"
        }
    ],
    "sg:phone":"+61 13 31 66",
    "sg:postcode":"2650",
    "sg:province":"NSW",
    "sg:tags":[
        "fire",
        "resistant",
        "supply"
    ],
    "wof:name":"Wormald",
    "wof:placetype":"venue"
},
  "geometry": {"coordinates":[147.41522216800001,-35.1300086975],"type":"Point"}
}