{
  "type": "Feature",
  "properties": {
    "iso:country":"AU",
    "sg:address":"426 Grand Junction Rd",
    "sg:city":"Mansfield Park",
    "sg:classifiers":[
        {
            "category":"Food & Beverages",
            "subcategory":"Liquor & Beverages",
            "type":"Retail Goods"
        }
    ],
    "sg:phone":"+61 8 8445 6606",
    "sg:postcode":"5012",
    "sg:province":"SA",
    "sg:tags":[
        "store"
    ],
    "wof:name":"Liquor Marketing Group - S.A. Pty Ltd Sip'N Save",
    "wof:placetype":"venue"
},
  "geometry": {"coordinates":[138.552536011,-34.8504981995],"type":"Point"}
}