{
  "type": "Feature",
  "properties": {
    "addr:full":"3 Bell Crt Broadford VIC 3658",
    "addr:housenumber":"3",
    "addr:postcode":"3658",
    "addr:street":"Bell Crt",
    "iso:country":"AU",
    "sg:address":"3 Bell Crt",
    "sg:city":"Broadford",
    "sg:classifiers":[
        {
            "category":"Building & Trades",
            "subcategory":"Cleaning & Sanitation",
            "type":"Services"
        }
    ],
    "sg:phone":"+61 3 5784 1613",
    "sg:postcode":"3658",
    "sg:province":"VIC",
    "sg:tags":[
        "washroom",
        "toilet",
        "equipment"
    ],
    "wof:name":"Bella Hygiene Services",
    "wof:placetype":"venue"
},
  "geometry": {"coordinates":[145.06022644000001,-37.2113685608],"type":"Point"}
}