{
  "type": "Feature",
  "properties": {
    "iso:country":"AU",
    "sg:address":"Unit 1, 211 Bannister Rd",
    "sg:city":"Canning Vale",
    "sg:classifiers":[
        {
            "category":"Home & Garden",
            "subcategory":"Hardware",
            "type":"Retail Goods"
        }
    ],
    "sg:phone":"+61 8 9456 3999",
    "sg:postcode":"6155",
    "sg:province":"WA",
    "sg:tags":[
        "repair",
        "tool",
        "power"
    ],
    "wof:name":"Industrial Power Tool Services",
    "wof:placetype":"venue"
},
  "geometry": {"coordinates":[115.904022,-32.062382],"type":"Point"}
}