{
  "type": "Feature",
  "properties": {
    "addr:full":"Unit 2/ 128 Ham St Windsor South NSW 2756",
    "addr:housenumber":"/ 128",
    "addr:postcode":"2756",
    "addr:street":"Ham St",
    "iso:country":"AU",
    "sg:address":"Unit 2/ 128 Ham St",
    "sg:city":"Windsor South",
    "sg:classifiers":[
        {
            "category":"Manufacturing",
            "subcategory":"Pottery",
            "type":"Manufacturing & Wholesale Goods"
        }
    ],
    "sg:phone":"+61 2 9651 1199",
    "sg:postcode":"2756",
    "sg:province":"NSW",
    "wof:name":"Pot About Garden Supplies & Garden Potential",
    "wof:placetype":"venue"
},
  "geometry": {"coordinates":[150.81347656200001,-33.6265335083],"type":"Point"}
}