{
  "type": "Feature",
  "properties": {
    "iso:country":"AU",
    "sg:address":"5 High St",
    "sg:city":"Prahran",
    "sg:classifiers":[
        {
            "category":"Wholesale",
            "subcategory":"Medical Equipment & Supplies",
            "type":"Manufacturing & Wholesale Goods"
        }
    ],
    "sg:phone":"+61 3 9510 1577",
    "sg:postcode":"3181",
    "sg:province":"VIC",
    "sg:tags":[
        "aids",
        "hearing"
    ],
    "wof:name":"Better Hearing Australia (Vic) Inc",
    "wof:placetype":"venue"
},
  "geometry": {"coordinates":[144.98501586899999,-37.8506011963],"type":"Point"}
}