{
  "type": "Feature",
  "properties": {
    "iso:country":"AU",
    "sg:address":"1 Lush Rd",
    "sg:city":"Pooraka",
    "sg:classifiers":[
        {
            "category":"Food & Beverages",
            "subcategory":"Bakery",
            "type":"Retail Goods"
        }
    ],
    "sg:phone":"+61 8 8289 4450",
    "sg:postcode":"5095",
    "sg:province":"SA",
    "sg:tags":[
        "baker"
    ],
    "wof:name":"Lifestyle Bakery Pty Ltd",
    "wof:placetype":"venue"
},
  "geometry": {"coordinates":[138.637283325,-34.8216323853],"type":"Point"}
}