{
  "type": "Feature",
  "properties": {
    "addr:full":"5 Cawston Rd Attadale WA 6156",
    "addr:housenumber":"5",
    "addr:postcode":"6156",
    "addr:street":"Cawston Rd",
    "iso:country":"AU",
    "sg:address":"5 Cawston Rd",
    "sg:city":"Attadale",
    "sg:classifiers":[
        {
            "category":"Education",
            "subcategory":"School",
            "type":"Public Place"
        }
    ],
    "sg:phone":"+61 8 9330 1013",
    "sg:postcode":"6156",
    "sg:province":"WA",
    "wof:name":"Mel Maria",
    "wof:placetype":"venue"
},
  "geometry": {"coordinates":[115.79554,-32.019993],"type":"Point"}
}