{
  "type": "Feature",
  "properties": {
    "addr:full":"30 Cocora St Eden NSW 2551",
    "addr:housenumber":"30",
    "addr:postcode":"2551",
    "addr:street":"Cocora St",
    "iso:country":"AU",
    "sg:address":"30 Cocora St",
    "sg:city":"Eden",
    "sg:classifiers":[
        {
            "category":"Home & Garden",
            "subcategory":"Carpets & Floor Coverings",
            "type":"Retail Goods"
        }
    ],
    "sg:phone":"+61 2 6496 1152",
    "sg:postcode":"2551",
    "sg:province":"NSW",
    "sg:tags":[
        "flooring",
        "parquet"
    ],
    "wof:name":"Whiter Bros. (Builders)",
    "wof:placetype":"venue"
},
  "geometry": {"coordinates":[149.90443420400001,-37.0699615479],"type":"Point"}
}