{
  "type": "Feature",
  "properties": {
    "addr:full":"253 Prince Edward Park Rd Woronora NSW 2232",
    "addr:housenumber":"253",
    "addr:postcode":"2232",
    "addr:street":"Prince;Park Rd",
    "iso:country":"AU",
    "sg:address":"253 Prince Edward Park Rd",
    "sg:city":"Woronora",
    "sg:classifiers":[
        {
            "category":"Shopping",
            "subcategory":"Jewelry",
            "type":"Retail Goods"
        }
    ],
    "sg:phone":"+61 2 9542 3222",
    "sg:postcode":"2232",
    "sg:province":"NSW",
    "sg:tags":[
        "jeweller"
    ],
    "wof:name":"Lanman's Fine Jewellery",
    "wof:placetype":"venue"
},
  "geometry": {"coordinates":[151.04728698700001,-34.0262985229],"type":"Point"}
}