{
  "type": "Feature",
  "properties": {
    "addr:full":"53 Devonshire Rd Sunshine VIC 3020",
    "addr:housenumber":"53",
    "addr:postcode":"3020",
    "addr:street":"Devonshire Rd",
    "iso:country":"AU",
    "sg:address":"53 Devonshire Rd",
    "sg:city":"Sunshine",
    "sg:classifiers":[
        {
            "category":"Health Services",
            "subcategory":"Doctor",
            "type":"Services"
        }
    ],
    "sg:phone":"+61 3 9311 0691",
    "sg:postcode":"3020",
    "sg:province":"VIC",
    "sg:tags":[
        "medical",
        "practitioner"
    ],
    "wof:name":"Poynton Neville D.",
    "wof:placetype":"venue"
},
  "geometry": {"coordinates":[144.83543399999999,-37.785107],"type":"Point"}
}