{
  "type": "Feature",
  "properties": {
    "iso:country":"AU",
    "sg:address":"3 Cato Pl",
    "sg:city":"Illawong",
    "sg:classifiers":[
        {
            "category":"Utilities",
            "subcategory":"Electric",
            "type":"Services"
        }
    ],
    "sg:phone":"+61 2 9543 1169",
    "sg:postcode":"2234",
    "sg:province":"NSW",
    "sg:tags":[
        "electrical",
        "contractor"
    ],
    "wof:name":"C & R Electrics Pty Ltd",
    "wof:placetype":"venue"
},
  "geometry": {"coordinates":[151.02804565400001,-34.0011558533],"type":"Point"}
}