{
  "type": "Feature",
  "properties": {
    "addr:full":"138 Don Rd Devonport TAS 7310",
    "addr:housenumber":"138",
    "addr:postcode":"7310",
    "addr:street":"Don Rd",
    "iso:country":"AU",
    "sg:address":"138 Don Rd",
    "sg:city":"Devonport",
    "sg:classifiers":[
        {
            "category":"Utilities",
            "type":"Services"
        }
    ],
    "sg:phone":"+61 3 6424 8088",
    "sg:postcode":"7310",
    "sg:province":"TAS",
    "sg:tags":[
        "refrigeration",
        "industrial",
        "commercial",
        "retail"
    ],
    "wof:name":"Degree C",
    "wof:placetype":"venue"
},
  "geometry": {"coordinates":[146.32409668,-41.1847267151],"type":"Point"}
}