{
  "type": "Feature",
  "properties": {
    "iso:country":"AU",
    "sg:address":"8 Opal Crt",
    "sg:city":"Kelso",
    "sg:classifiers":[
        {
            "category":"Building & Trades",
            "subcategory":"Cleaning & Sanitation",
            "type":"Services"
        }
    ],
    "sg:phone":"+61 7 4789 0377",
    "sg:postcode":"4815",
    "sg:province":"QLD",
    "sg:tags":[
        "industrial",
        "commercial",
        "contractor"
    ],
    "wof:name":"Big Red Carpet Cleaning Townsville",
    "wof:placetype":"venue"
},
  "geometry": {"coordinates":[146.728653,-19.382023],"type":"Point"}
}