{
  "type": "Feature",
  "properties": {
    "addr:full":"18 Hill St Bega NSW 2550",
    "addr:housenumber":"18",
    "addr:postcode":"2550",
    "addr:street":"Hill St",
    "iso:country":"AU",
    "sg:address":"18 Hill St",
    "sg:city":"Bega",
    "sg:classifiers":[
        {
            "category":"Health Services",
            "subcategory":"Doctor",
            "type":"Services"
        }
    ],
    "sg:phone":"+61 2 6492 2200",
    "sg:postcode":"2550",
    "sg:province":"NSW",
    "sg:tags":[
        "medical",
        "practitioner"
    ],
    "wof:name":"Gault EJ",
    "wof:placetype":"venue"
},
  "geometry": {"coordinates":[149.837356567,-36.6745643616],"type":"Point"}
}