{
  "type": "Feature",
  "properties": {
    "iso:country":"AU",
    "sg:address":"61G Jetty Rd",
    "sg:city":"Glenelg",
    "sg:classifiers":[
        {
            "category":"Shopping",
            "subcategory":"Clothing, Apparel, & Fashions",
            "type":"Retail Goods"
        }
    ],
    "sg:phone":"+61 8 8376 6300",
    "sg:postcode":"5045",
    "sg:province":"SA",
    "sg:tags":[
        "lady",
        "wear"
    ],
    "wof:name":"Brown Sugar",
    "wof:placetype":"venue"
},
  "geometry": {"coordinates":[138.51513700000001,-34.98016],"type":"Point"}
}