{
  "type": "Feature",
  "properties": {
    "addr:full":"PO Box 379 Bentleigh East VIC 3165",
    "addr:postcode":"3165",
    "iso:country":"AU",
    "sg:address":"PO Box 379",
    "sg:city":"Bentleigh East",
    "sg:classifiers":[
        {
            "category":"Social Services",
            "subcategory":"Retirement Home",
            "type":"Services"
        }
    ],
    "sg:phone":"+61 3 9503 8454",
    "sg:postcode":"3165",
    "sg:province":"VIC",
    "sg:tags":[
        "accommodation",
        "special"
    ],
    "wof:name":"Parentlink",
    "wof:placetype":"venue"
},
  "geometry": {"coordinates":[145.06695556599999,-37.9222412109],"type":"Point"}
}