{
  "type": "Feature",
  "properties": {
    "iso:country":"AU",
    "sg:address":"6- 8 Carter St St",
    "sg:city":"Homebush Bay",
    "sg:classifiers":[
        {
            "category":"Personal",
            "type":"Services"
        }
    ],
    "sg:phone":"+61 2 8748 6600",
    "sg:postcode":"2127",
    "sg:province":"NSW",
    "sg:tags":[
        "gift"
    ],
    "wof:name":"Moraitis Fresh Fruit Baskets",
    "wof:placetype":"venue"
},
  "geometry": {"coordinates":[151.05987548799999,-33.8513412476],"type":"Point"}
}