{
  "type": "Feature",
  "properties": {
    "iso:country":"AU",
    "sg:address":"Lot 1 Triangle Park",
    "sg:city":"Roma",
    "sg:classifiers":[
        {
            "category":"Manufacturing",
            "subcategory":"Tools & Machinery",
            "type":"Manufacturing & Wholesale Goods"
        }
    ],
    "sg:phone":"+61 7 4622 1633",
    "sg:postcode":"4455",
    "sg:province":"QLD",
    "sg:tags":[
        "earth",
        "excavating",
        "moving",
        "equipment"
    ],
    "wof:name":"Queensland Compaction Hire Pty Ltd",
    "wof:placetype":"venue"
},
  "geometry": {"coordinates":[148.78732299800001,-26.5734291077],"type":"Point"}
}