{
  "type": "Feature",
  "properties": {
    "addr:full":"43 York St South Perth WA 6151",
    "addr:housenumber":"43",
    "addr:postcode":"6151",
    "addr:street":"York St South",
    "iso:country":"AU",
    "sg:address":"43 York St",
    "sg:city":"South Perth",
    "sg:classifiers":[
        {
            "category":"Professional",
            "type":"Services"
        }
    ],
    "sg:phone":"+61 8 9368 5660",
    "sg:postcode":"6151",
    "sg:province":"WA",
    "sg:tags":[
        "shop",
        "fitting"
    ],
    "wof:name":"Total Office Fitouts",
    "wof:placetype":"venue"
},
  "geometry": {"coordinates":[115.861572,-31.979637],"type":"Point"}
}