{
  "type": "Feature",
  "properties": {
    "iso:country":"AU",
    "sg:address":"Unit 11, 15 Carbon Crt",
    "sg:city":"Osborne Park",
    "sg:classifiers":[
        {
            "category":"Shopping",
            "subcategory":"Computers & Home Electronics",
            "type":"Retail Goods"
        }
    ],
    "sg:phone":"+61 8 9445 6991",
    "sg:postcode":"6017",
    "sg:province":"WA",
    "sg:tags":[
        "equipment",
        "supply"
    ],
    "wof:name":"Boomerang Imaging Products",
    "wof:placetype":"venue"
},
  "geometry": {"coordinates":[115.805351257,-31.9025917053],"type":"Point"}
}