{
  "type": "Feature",
  "properties": {
    "iso:country":"AU",
    "sg:address":"14 Gurney St",
    "sg:city":"Garbutt",
    "sg:classifiers":[
        {
            "category":"Retail",
            "subcategory":"Auto Repair",
            "type":"Services"
        }
    ],
    "sg:phone":"+61 7 4775 4571",
    "sg:postcode":"4814",
    "sg:province":"QLD",
    "sg:tags":[
        "beater",
        "painter",
        "panel"
    ],
    "wof:name":"David Lewis Spray Painting & Panel Beating",
    "wof:placetype":"venue"
},
  "geometry": {"coordinates":[146.765823,-19.265568],"type":"Point"}
}