{
  "type": "Feature",
  "properties": {
    "addr:full":"Dilhorn House 2 bulwer St Perth WA 6000",
    "addr:housenumber":"2",
    "addr:postcode":"6000",
    "addr:street":"Bulwer St",
    "iso:country":"AU",
    "sg:address":"Dilhorn House 2 bulwer St",
    "sg:city":"Perth",
    "sg:classifiers":[
        {
            "category":"Social Services",
            "subcategory":"Retirement Home",
            "type":"Services"
        }
    ],
    "sg:phone":"+61 8 6462 7900",
    "sg:postcode":"6000",
    "sg:province":"WA",
    "sg:tags":[
        "environmental",
        "consultant",
        "pollution"
    ],
    "wof:name":"Coffey Environments",
    "wof:placetype":"venue"
},
  "geometry": {"coordinates":[115.858306885,-31.9384536743],"type":"Point"}
}