{
  "type": "Feature",
  "properties": {
    "addr:full":"C/o The Entertainment Quarter FSA #258 / 116 Lang Rd Moore Park NSW 2021",
    "addr:housenumber":"/ 116",
    "addr:postcode":"2021",
    "addr:street":"C;O;Lang Rd",
    "iso:country":"AU",
    "sg:address":"C/o The Entertainment Quarter FSA #258 / 116 Lang Rd",
    "sg:city":"Moore Park",
    "sg:classifiers":[
        {
            "category":"Education",
            "subcategory":"Dance Studio",
            "type":"Public Place"
        }
    ],
    "sg:phone":"+61 2 9357 3783",
    "sg:postcode":"2021",
    "sg:province":"NSW",
    "sg:tags":[
        "training",
        "video",
        "film"
    ],
    "wof:name":"1st Avenue TV",
    "wof:placetype":"venue"
},
  "geometry": {"coordinates":[151.22621154800001,-33.8963851929],"type":"Point"}
}