{
  "type": "Feature",
  "properties": {
    "addr:full":"45 Caroline St South Yarra VIC 3141",
    "addr:housenumber":"45",
    "addr:postcode":"3141",
    "addr:street":"Caroline St",
    "iso:country":"AU",
    "sg:address":"45 Caroline St",
    "sg:city":"South Yarra",
    "sg:classifiers":[
        {
            "category":"Health Services",
            "subcategory":"Doctor",
            "type":"Services"
        }
    ],
    "sg:phone":"+61 3 9866 1462",
    "sg:postcode":"3141",
    "sg:province":"VIC",
    "sg:tags":[
        "medical",
        "practitioner"
    ],
    "wof:name":"Levou M",
    "wof:placetype":"venue"
},
  "geometry": {"coordinates":[144.988006592,-37.8377380371],"type":"Point"}
}