{
  "type": "Feature",
  "properties": {
    "addr:full":"2 Iron St Malaga WA 6090",
    "addr:housenumber":"2",
    "addr:postcode":"6090",
    "addr:street":"Iron St",
    "iso:country":"AU",
    "sg:address":"2 Iron St",
    "sg:city":"Malaga",
    "sg:classifiers":[
        {
            "category":"Building & Trades",
            "subcategory":"Locksmith",
            "type":"Services"
        }
    ],
    "sg:phone":"+61 8 9248 8675",
    "sg:postcode":"6090",
    "sg:province":"WA",
    "sg:tags":[
        "equipment",
        "operating",
        "door",
        "gate"
    ],
    "sg:website":"http://www.dgdoors.com.au",
    "wof:name":"Designer Garage Doors",
    "wof:placetype":"venue"
},
  "geometry": {"coordinates":[115.90688324,-31.859375],"type":"Point"}
}