{
  "type": "Feature",
  "properties": {
    "addr:full":"Suite 1 174 Goondoon St Gladstone QLD 4680",
    "addr:housenumber":"174",
    "addr:postcode":"4680",
    "addr:street":"Goondoon St",
    "iso:country":"AU",
    "sg:address":"Suite 1 174 Goondoon St",
    "sg:city":"Gladstone",
    "sg:classifiers":[
        {
            "category":"Banks & Credit Unions",
            "subcategory":"Financial Services",
            "type":"Services"
        }
    ],
    "sg:phone":"+61 7 4972 6311",
    "sg:postcode":"4680",
    "sg:province":"QLD",
    "sg:tags":[
        "annuity",
        "rollover",
        "superannuation",
        "consultant"
    ],
    "wof:name":"AMP Financial Planning",
    "wof:placetype":"venue"
},
  "geometry": {"coordinates":[151.258636475,-23.8472442627],"type":"Point"}
}