{
  "type": "Feature",
  "properties": {
    "addr:full":"74 Mons Ave Maroubra NSW 2035",
    "addr:housenumber":"74",
    "addr:postcode":"2035",
    "addr:street":"Mons Ave",
    "iso:country":"AU",
    "sg:address":"74 Mons Ave",
    "sg:city":"Maroubra",
    "sg:classifiers":[
        {
            "category":"Professional",
            "subcategory":"Accounting & Tax Preparation",
            "type":"Services"
        }
    ],
    "sg:phone":"+61 2 9344 8916",
    "sg:postcode":"2035",
    "sg:province":"NSW",
    "sg:tags":[
        "accountant",
        "auditor"
    ],
    "wof:name":"Jones Belinda",
    "wof:placetype":"venue"
},
  "geometry": {"coordinates":[151.24736023,-33.9448623657],"type":"Point"}
}