{
  "type": "Feature",
  "properties": {
    "iso:country":"AU",
    "sg:address":"6 Rasmussen Ave",
    "sg:city":"Hamilton",
    "sg:classifiers":[
        {
            "category":"Professional",
            "subcategory":"Computer Services",
            "type":"Services"
        }
    ],
    "sg:phone":"+61 419 119 930",
    "sg:postcode":"3300",
    "sg:province":"VIC",
    "sg:tags":[
        "repairs",
        "upgrade",
        "equipment"
    ],
    "wof:name":"Dyerwood Pty Ltd",
    "wof:placetype":"venue"
},
  "geometry": {"coordinates":[142.041946411,-37.7374000549],"type":"Point"}
}