{
  "type": "Feature",
  "properties": {
    "addr:full":"26 Vidler St Cloverdale WA 6105",
    "addr:housenumber":"26",
    "addr:postcode":"6105",
    "addr:street":"Vidler St",
    "iso:country":"AU",
    "sg:address":"26 Vidler St",
    "sg:city":"Cloverdale",
    "sg:classifiers":[
        {
            "category":"Building & Trades",
            "subcategory":"Construction",
            "type":"Services"
        }
    ],
    "sg:phone":"+61 401 608 338",
    "sg:postcode":"6105",
    "sg:province":"WA",
    "sg:tags":[
        "earth",
        "excavating",
        "moving",
        "contractor"
    ],
    "wof:name":"Shift That Bobcat",
    "wof:placetype":"venue"
},
  "geometry": {"coordinates":[115.950210571,-31.9594020844],"type":"Point"}
}