{
  "type": "Feature",
  "properties": {
    "addr:full":"30 Pitt St Sydney NSW 2000",
    "addr:housenumber":"30",
    "addr:postcode":"2000",
    "addr:street":"Pitt St",
    "iso:country":"AU",
    "sg:address":"30 Pitt St",
    "sg:city":"Sydney",
    "sg:classifiers":[
        {
            "category":"Travel",
            "subcategory":"Hotels & Motels",
            "type":"Entertainment"
        }
    ],
    "sg:phone":"+61 2 9259 7000",
    "sg:postcode":"2000",
    "sg:province":"NSW",
    "sg:tags":[
        "accommodation"
    ],
    "wof:name":"Sydney Harbour Marriott Hotel at Circular Quay",
    "wof:placetype":"venue"
},
  "geometry": {"coordinates":[151.209228516,-33.8625679016],"type":"Point"}
}