{
  "type": "Feature",
  "properties": {
    "addr:full":"210 Roberts Rd Denmark WA 6333",
    "addr:housenumber":"210",
    "addr:postcode":"6333",
    "addr:street":"Roberts Rd",
    "iso:country":"AU",
    "sg:address":"210 Roberts Rd",
    "sg:city":"Denmark",
    "sg:classifiers":[
        {
            "category":"Farming",
            "subcategory":"Vineyard",
            "type":"Manufacturing & Wholesale Goods"
        }
    ],
    "sg:phone":"+61 8 9840 9324",
    "sg:postcode":"6333",
    "sg:province":"WA",
    "sg:tags":[
        "winery"
    ],
    "wof:name":"Mariners Rest Wines",
    "wof:placetype":"venue"
},
  "geometry": {"coordinates":[117.278892517,-34.9297218323],"type":"Point"}
}