{
  "type": "Feature",
  "properties": {
    "addr:full":"44 Queen St Busselton WA 6280",
    "addr:housenumber":"44",
    "addr:postcode":"6280",
    "addr:street":"Queen St",
    "iso:country":"AU",
    "sg:address":"44 Queen St",
    "sg:city":"Busselton",
    "sg:classifiers":[
        {
            "category":"Food & Beverages",
            "subcategory":"Liquor & Beverages",
            "type":"Retail Goods"
        }
    ],
    "sg:phone":"+61 8 9752 1455",
    "sg:postcode":"6280",
    "sg:province":"WA",
    "sg:tags":[
        "store"
    ],
    "wof:name":"Route 66 Drive-Ins",
    "wof:placetype":"venue"
},
  "geometry": {"coordinates":[115.343788147,-33.6470375061],"type":"Point"}
}