{
  "type": "Feature",
  "properties": {
    "addr:full":"1 Slade St Naremburn NSW 2065",
    "addr:housenumber":"1",
    "addr:postcode":"2065",
    "addr:street":"Slade St",
    "iso:country":"AU",
    "sg:address":"1 Slade St",
    "sg:city":"Naremburn",
    "sg:classifiers":[
        {
            "category":"Building & Trades",
            "subcategory":"Landscaping Services",
            "type":"Services"
        }
    ],
    "sg:phone":"+61 2 9460 9951",
    "sg:postcode":"2065",
    "sg:province":"NSW",
    "sg:tags":[
        "designer",
        "landscape",
        "contractor"
    ],
    "wof:name":"Adam's Outdoor Service",
    "wof:placetype":"venue"
},
  "geometry": {"coordinates":[151.205200195,-33.817073822],"type":"Point"}
}