{
  "type": "Feature",
  "properties": {
    "iso:country":"AU",
    "sg:address":"20 Minnie St",
    "sg:city":"Belmore",
    "sg:classifiers":[
        {
            "category":"Shopping",
            "subcategory":"Pets & Pet Supplies",
            "type":"Retail Goods"
        }
    ],
    "sg:phone":"+61 2 9750 5715",
    "sg:postcode":"2192",
    "sg:province":"NSW",
    "sg:tags":[
        "food"
    ],
    "wof:name":"Vebo Trading Pty Ltd",
    "wof:placetype":"venue"
},
  "geometry": {"coordinates":[151.077988,-33.908638],"type":"Point"}
}