{
  "type": "Feature",
  "properties": {
    "iso:country":"AU",
    "sg:address":"4 Buckmaster Crs",
    "sg:city":"Dunlop",
    "sg:classifiers":[
        {
            "category":"Building & Trades",
            "subcategory":"Construction",
            "type":"Services"
        }
    ],
    "sg:phone":"+61 415 115 631",
    "sg:postcode":"2615",
    "sg:province":"ACT",
    "sg:tags":[
        "concrete",
        "contractor"
    ],
    "wof:name":"Risetop Constructions",
    "wof:placetype":"venue"
},
  "geometry": {"coordinates":[149.019699097,-35.1909408569],"type":"Point"}
}