{
  "type": "Feature",
  "properties": {
    "addr:full":"188 Cavendish Rd Coorparoo QLD 4151",
    "addr:housenumber":"188",
    "addr:postcode":"4151",
    "addr:street":"Cavendish Rd",
    "iso:country":"AU",
    "sg:address":"188 Cavendish Rd",
    "sg:city":"Coorparoo",
    "sg:classifiers":[
        {
            "category":"Personal",
            "subcategory":"Beauty Salon",
            "type":"Services"
        }
    ],
    "sg:phone":"+61 7 3847 2666",
    "sg:postcode":"4151",
    "sg:province":"QLD",
    "sg:tags":[
        "hairdresser"
    ],
    "wof:name":"Adapt Hair Artistry",
    "wof:placetype":"venue"
},
  "geometry": {"coordinates":[153.05917358400001,-27.494134903],"type":"Point"}
}