{
  "type": "Feature",
  "properties": {
    "addr:full":"6 Sidwell Crt Lower Plenty VIC 3093",
    "addr:housenumber":"6",
    "addr:postcode":"3093",
    "addr:street":"Sidwell Crt",
    "iso:country":"AU",
    "sg:address":"6 Sidwell Crt",
    "sg:city":"Lower Plenty",
    "sg:classifiers":[
        {
            "category":"Professional",
            "subcategory":"Accounting & Tax Preparation",
            "type":"Services"
        }
    ],
    "sg:phone":"+61 3 9431 4776",
    "sg:postcode":"3093",
    "sg:province":"VIC",
    "sg:tags":[
        "bookkeeping"
    ],
    "wof:name":"LJK Services",
    "wof:placetype":"venue"
},
  "geometry": {"coordinates":[145.118377686,-37.7394638062],"type":"Point"}
}