{
  "type": "Feature",
  "properties": {
    "addr:full":"78 Warburton Ave Padbury WA 6025",
    "addr:housenumber":"78",
    "addr:postcode":"6025",
    "addr:street":"Warburton Ave",
    "iso:country":"AU",
    "sg:address":"78 Warburton Ave",
    "sg:city":"Padbury",
    "sg:classifiers":[
        {
            "category":"Social Services",
            "subcategory":"Child Care",
            "type":"Services"
        }
    ],
    "sg:phone":"+61 8 9402 5599",
    "sg:postcode":"6025",
    "sg:province":"WA",
    "wof:name":"Jellybeans Child Care Padbury",
    "wof:placetype":"venue"
},
  "geometry": {"coordinates":[115.765701294,-31.8112983704],"type":"Point"}
}