{
  "type": "Feature",
  "properties": {
    "addr:full":"119 Green St Richmond VIC 3121",
    "addr:housenumber":"119",
    "addr:postcode":"3121",
    "addr:street":"Green St",
    "iso:country":"AU",
    "sg:address":"119 Green St",
    "sg:city":"Richmond",
    "sg:classifiers":[
        {
            "category":"Professional",
            "subcategory":"Art Services",
            "type":"Services"
        }
    ],
    "sg:phone":"+61 3 9421 6279",
    "sg:postcode":"3121",
    "sg:province":"VIC",
    "sg:tags":[
        "graphic",
        "designer"
    ],
    "wof:name":"Studio Syn-RG Pty Ltd",
    "wof:placetype":"venue"
},
  "geometry": {"coordinates":[144.994506836,-37.8304710388],"type":"Point"}
}