{
  "type": "Feature",
  "properties": {
    "addr:full":"29 Chadford St MacGregor QLD 4109",
    "addr:housenumber":"29",
    "addr:postcode":"4109",
    "addr:street":"Chadford St",
    "iso:country":"AU",
    "sg:address":"29 Chadford St",
    "sg:city":"MacGregor",
    "sg:classifiers":[
        {
            "category":"Insurance",
            "subcategory":"Insurance Agent",
            "type":"Services"
        }
    ],
    "sg:phone":"+61 7 3344 2954",
    "sg:postcode":"4109",
    "sg:province":"QLD",
    "wof:name":"Royal Penny Financial Group Pty Ltd",
    "wof:placetype":"venue"
},
  "geometry": {"coordinates":[153.06846618599999,-27.569858551],"type":"Point"}
}