{
  "type": "Feature",
  "properties": {
    "addr:full":"PO Box 602 Caloundra QLD 4551",
    "addr:postcode":"4551",
    "iso:country":"AU",
    "sg:address":"PO Box 602",
    "sg:city":"Caloundra",
    "sg:classifiers":[
        {
            "category":"Building & Trades",
            "subcategory":"Construction",
            "type":"Services"
        }
    ],
    "sg:phone":"+61 7 5494 0930",
    "sg:postcode":"4551",
    "sg:province":"QLD",
    "sg:tags":[
        "pool",
        "swimming"
    ],
    "wof:name":"Rock & Water Constructions",
    "wof:placetype":"venue"
},
  "geometry": {"coordinates":[153.124755859,-26.7936191559],"type":"Point"}
}