{
  "type": "Feature",
  "properties": {
    "iso:country":"AU",
    "sg:address":"Shp4/ 1 Mcdonald St",
    "sg:city":"Cronulla",
    "sg:classifiers":[
        {
            "category":"Cafe",
            "type":"Food & Drink"
        }
    ],
    "sg:phone":"+61 2 9544 4159",
    "sg:postcode":"2230",
    "sg:province":"NSW",
    "wof:name":"Cafe Monz",
    "wof:placetype":"venue"
},
  "geometry": {"coordinates":[151.155059814,-34.0525817871],"type":"Point"}
}