{
  "type": "Feature",
  "properties": {
    "addr:full":"14 Karen Ave Mermaid Beach QLD 4218",
    "addr:housenumber":"14",
    "addr:postcode":"4218",
    "addr:street":"Karen Ave",
    "iso:country":"AU",
    "sg:address":"14 Karen Ave",
    "sg:city":"Mermaid Beach",
    "sg:classifiers":[
        {
            "category":"Retail",
            "subcategory":"Auto Repair",
            "type":"Services"
        }
    ],
    "sg:phone":"+61 7 5578 6844",
    "sg:postcode":"4218",
    "sg:province":"QLD",
    "sg:tags":[
        "repairer",
        "motor",
        "engineer"
    ],
    "wof:name":"R.P.M. Automotives",
    "wof:placetype":"venue"
},
  "geometry": {"coordinates":[153.43247985799999,-28.0401515961],"type":"Point"}
}