{
  "type": "Feature",
  "properties": {
    "addr:full":"Suite 210, Level 2 Joondalup Specialist Centre Joondalup WA 6027",
    "addr:postcode":"6027",
    "addr:street":"210",
    "iso:country":"AU",
    "sg:address":"Suite 210, Level 2 Joondalup Specialist Centre",
    "sg:city":"Joondalup",
    "sg:classifiers":[
        {
            "category":"Health Services",
            "subcategory":"Doctor",
            "type":"Services"
        }
    ],
    "sg:phone":"+61 8 9400 9822",
    "sg:postcode":"6027",
    "sg:province":"WA",
    "sg:tags":[
        "medical",
        "practitioner"
    ],
    "wof:name":"Geddes Anthony Mr",
    "wof:placetype":"venue"
},
  "geometry": {"coordinates":[115.77719116199999,-31.7677173615],"type":"Point"}
}