{
  "type": "Feature",
  "properties": {
    "iso:country":"AU",
    "sg:address":"PO Box 6076",
    "sg:city":"Wantirna",
    "sg:classifiers":[
        {
            "category":"Professional",
            "subcategory":"Detective & Security Services",
            "type":"Services"
        }
    ],
    "sg:phone":"+61 3 9720 5065",
    "sg:postcode":"3152",
    "sg:province":"VIC",
    "sg:tags":[
        "investigator"
    ],
    "wof:name":"Wantirna Investigations Pty Ltd",
    "wof:placetype":"venue"
},
  "geometry": {"coordinates":[145.22923278799999,-37.8482017517],"type":"Point"}
}