{
  "type": "Feature",
  "properties": {
    "addr:full":"85 McEvoy St Warwick QLD 4370",
    "addr:housenumber":"85",
    "addr:postcode":"4370",
    "addr:street":"Mcevoy St",
    "iso:country":"AU",
    "sg:address":"85 McEvoy St",
    "sg:city":"Warwick",
    "sg:classifiers":[
        {
            "category":"Retail",
            "subcategory":"Auto Repair",
            "type":"Services"
        }
    ],
    "sg:phone":"+61 7 4661 5209",
    "sg:postcode":"4370",
    "sg:province":"QLD",
    "sg:tags":[
        "bus",
        "truck"
    ],
    "wof:name":"EZR Automotive Services",
    "wof:placetype":"venue"
},
  "geometry": {"coordinates":[152.03871154800001,-28.2288303375],"type":"Point"}
}