{
  "type": "Feature",
  "properties": {
    "addr:full":"442 Murray St Perth WA 6000",
    "addr:housenumber":"442",
    "addr:postcode":"6000",
    "addr:street":"Murray St",
    "iso:country":"AU",
    "sg:address":"442 Murray St",
    "sg:city":"Perth",
    "sg:classifiers":[
        {
            "category":"Deli",
            "type":"Food & Drink"
        }
    ],
    "sg:phone":"+61 8 9322 4344",
    "sg:postcode":"6000",
    "sg:province":"WA",
    "sg:tags":[
        "delicatessen"
    ],
    "wof:name":"Swan Convenience Store",
    "wof:placetype":"venue"
},
  "geometry": {"coordinates":[115.852653503,-31.9507198334],"type":"Point"}
}