{
  "type": "Feature",
  "properties": {
    "addr:full":"96 Marius St Tamworth NSW 2340",
    "addr:housenumber":"96",
    "addr:postcode":"2340",
    "addr:street":"Marius St",
    "iso:country":"AU",
    "sg:address":"96 Marius St",
    "sg:city":"Tamworth",
    "sg:classifiers":[
        {
            "category":"Health Services",
            "subcategory":"Doctor",
            "type":"Services"
        }
    ],
    "sg:phone":"+61 2 6761 2377",
    "sg:postcode":"2340",
    "sg:province":"NSW",
    "sg:tags":[
        "medical",
        "practitioner"
    ],
    "wof:name":"Hughes James Dr",
    "wof:placetype":"venue"
},
  "geometry": {"coordinates":[150.93536376899999,-31.093536377],"type":"Point"}
}