{
  "type": "Feature",
  "properties": {
    "addr:full":"122 Merrylands Rd Merrylands NSW 2160",
    "addr:housenumber":"122",
    "addr:postcode":"2160",
    "addr:street":"Merrylands Rd",
    "iso:country":"AU",
    "sg:address":"122 Merrylands Rd",
    "sg:city":"Merrylands",
    "sg:classifiers":[
        {
            "category":"Retail",
            "subcategory":"Veterinary Services",
            "type":"Services"
        }
    ],
    "sg:phone":"+61 2 9897 5466",
    "sg:postcode":"2160",
    "sg:province":"NSW",
    "sg:tags":[
        "surgeon"
    ],
    "wof:name":"Animal Medical Centre Merrylands",
    "wof:placetype":"venue"
},
  "geometry": {"coordinates":[150.991500855,-33.8369407654],"type":"Point"}
}