{
  "type": "Feature",
  "properties": {
    "addr:full":"187b Windsor St Richmond NSW 2753",
    "addr:housenumber":"187b",
    "addr:postcode":"2753",
    "addr:street":"Windsor St",
    "iso:country":"AU",
    "sg:address":"187b Windsor St",
    "sg:city":"Richmond",
    "sg:classifiers":[
        {
            "category":"Real Estate",
            "subcategory":"Real Estate Agent",
            "type":"Services"
        }
    ],
    "sg:phone":"+61 2 4588 0999",
    "sg:postcode":"2753",
    "sg:province":"NSW",
    "wof:name":"Ray White Richmond",
    "wof:placetype":"venue"
},
  "geometry": {"coordinates":[150.75225830100001,-33.5972747803],"type":"Point"}
}