{
  "type": "Feature",
  "properties": {
    "addr:full":"Cobden Rd Camperdown VIC 3260",
    "addr:postcode":"3260",
    "addr:street":"Cobden Rd",
    "iso:country":"AU",
    "sg:address":"Cobden Rd",
    "sg:city":"Camperdown",
    "sg:classifiers":[
        {
            "category":"Farming",
            "subcategory":"Farm",
            "type":"Manufacturing & Wholesale Goods"
        }
    ],
    "sg:phone":"+61 3 5595 1538",
    "sg:postcode":"3260",
    "sg:province":"VIC",
    "sg:tags":[
        "farmer"
    ],
    "wof:name":"Morrissey P W & L M",
    "wof:placetype":"venue"
},
  "geometry": {"coordinates":[143.14210510300001,-38.2296600342],"type":"Point"}
}