{
  "type": "Feature",
  "properties": {
    "addr:full":"51 March St Richmond NSW 2753",
    "addr:housenumber":"51",
    "addr:postcode":"2753",
    "addr:street":"March St",
    "iso:country":"AU",
    "sg:address":"51 March St",
    "sg:city":"Richmond",
    "sg:classifiers":[
        {
            "category":"Autos & Motor Vehicles",
            "subcategory":"Auto Supplies",
            "type":"Retail Goods"
        }
    ],
    "sg:phone":"+61 13 66 73",
    "sg:postcode":"2753",
    "sg:province":"NSW",
    "sg:tags":[
        "tyre"
    ],
    "wof:name":"Tyres & More",
    "wof:placetype":"venue"
},
  "geometry": {"coordinates":[150.75369262699999,-33.5998268127],"type":"Point"}
}