{
  "type": "Feature",
  "properties": {
    "addr:full":"9 Melville Rd Brunswick West VIC 3055",
    "addr:housenumber":"9",
    "addr:postcode":"3055",
    "addr:street":"Melville Rd",
    "iso:country":"AU",
    "sg:address":"9 Melville Rd",
    "sg:city":"Brunswick West",
    "sg:classifiers":[
        {
            "category":"Health Services",
            "subcategory":"Doctor",
            "type":"Services"
        }
    ],
    "sg:phone":"+61 3 9387 9088",
    "sg:postcode":"3055",
    "sg:province":"VIC",
    "sg:tags":[
        "medical",
        "practitioner"
    ],
    "wof:name":"Leslie H",
    "wof:placetype":"venue"
},
  "geometry": {"coordinates":[144.94317626899999,-37.7669754028],"type":"Point"}
}