{
  "type": "Feature",
  "properties": {
    "addr:full":"469 Heidelberg Rd Fairfield VIC 3078",
    "addr:housenumber":"469",
    "addr:postcode":"3078",
    "addr:street":"Heidelberg Rd",
    "iso:country":"AU",
    "sg:address":"469 Heidelberg Rd",
    "sg:city":"Fairfield",
    "sg:classifiers":[
        {
            "category":"Home & Garden",
            "subcategory":"Furniture",
            "type":"Retail Goods"
        }
    ],
    "sg:phone":"+61 3 9486 8313",
    "sg:postcode":"3078",
    "sg:province":"VIC",
    "sg:tags":[
        "business"
    ],
    "wof:name":"Access Office Furniture",
    "wof:placetype":"venue"
},
  "geometry": {"coordinates":[145.01919555699999,-37.7829322815],"type":"Point"}
}