{
  "type": "Feature",
  "properties": {
    "addr:full":"346 Bay St Brighton-le-Sands NSW 2216",
    "addr:housenumber":"346",
    "addr:postcode":"2216",
    "addr:street":"Bay St",
    "iso:country":"AU",
    "sg:address":"346 Bay St",
    "sg:city":"Brighton-le-Sands",
    "sg:classifiers":[
        {
            "category":"Shopping",
            "subcategory":"Clothing, Apparel, & Fashions",
            "type":"Retail Goods"
        }
    ],
    "sg:phone":"+61 2 9567 2006",
    "sg:postcode":"2216",
    "sg:province":"NSW",
    "sg:tags":[
        "lady",
        "wear"
    ],
    "wof:name":"De Bleu Boutique",
    "wof:placetype":"venue"
},
  "geometry": {"coordinates":[151.15389999999999,-33.959743],"type":"Point"}
}