{
  "type": "Feature",
  "properties": {
    "iso:country":"AU",
    "sg:address":"26 Computer Rd",
    "sg:city":"Yatala",
    "sg:classifiers":[
        {
            "category":"Shopping",
            "subcategory":"Gifts & Souvenirs",
            "type":"Retail Goods"
        }
    ],
    "sg:phone":"+61 7 3807 5122",
    "sg:postcode":"4207",
    "sg:province":"QLD",
    "sg:tags":[
        "shop",
        "supply"
    ],
    "wof:name":"Australian Clayworkers",
    "wof:placetype":"venue"
},
  "geometry": {"coordinates":[153.23468017600001,-27.7596950531],"type":"Point"}
}