{
  "type": "Feature",
  "properties": {
    "iso:country":"AU",
    "sg:address":"Crawford Rd",
    "sg:city":"Crawford",
    "sg:classifiers":[
        {
            "category":"Manufacturing",
            "subcategory":"Food",
            "type":"Manufacturing & Wholesale Goods"
        }
    ],
    "sg:phone":"+61 7 4162 2635",
    "sg:postcode":"4610",
    "sg:province":"QLD",
    "sg:tags":[
        "product",
        "nut",
        "edible"
    ],
    "wof:name":"Crumpton G & Sons",
    "wof:placetype":"venue"
},
  "geometry": {"coordinates":[151.82421875,-26.4976863861],"type":"Point"}
}