{
  "type": "Feature",
  "properties": {
    "iso:country":"AU",
    "sg:address":"Cnr North West Coastal Hwy, Jensen St",
    "sg:city":"Geraldton",
    "sg:classifiers":[
        {
            "category":"Home & Garden",
            "subcategory":"Carpets & Floor Coverings",
            "type":"Retail Goods"
        }
    ],
    "sg:phone":"+61 8 9964 4599",
    "sg:postcode":"6530",
    "sg:province":"WA",
    "sg:tags":[
        "wood"
    ],
    "wof:name":"Geraldton Carpet Factory",
    "wof:placetype":"venue"
},
  "geometry": {"coordinates":[114.625343323,-28.7729263306],"type":"Point"}
}