{
  "type": "Feature",
  "properties": {
    "addr:full":"Blueberry Rd Moree NSW 2400",
    "addr:postcode":"2400",
    "addr:street":"Blueberry Rd",
    "iso:country":"AU",
    "sg:address":"Blueberry Rd",
    "sg:city":"Moree",
    "sg:classifiers":[
        {
            "category":"Farming",
            "subcategory":"Crops",
            "type":"Manufacturing & Wholesale Goods"
        }
    ],
    "sg:phone":"+61 2 6752 8190",
    "sg:postcode":"2400",
    "sg:province":"NSW",
    "sg:tags":[
        "warehousing"
    ],
    "wof:name":"Farm Store",
    "wof:placetype":"venue"
},
  "geometry": {"coordinates":[149.84046935999999,-29.4902896881],"type":"Point"}
}