{
  "type": "Feature",
  "properties": {
    "addr:full":"1/ 31 Fitzmaurice St Wagga Wagga NSW 2650",
    "addr:housenumber":"/ 31",
    "addr:postcode":"2650",
    "addr:street":"Fitzmaurice St",
    "iso:country":"AU",
    "sg:address":"1/ 31 Fitzmaurice St",
    "sg:city":"Wagga Wagga",
    "sg:classifiers":[
        {
            "category":"Shopping",
            "subcategory":"Party Supplies",
            "type":"Retail Goods"
        }
    ],
    "sg:phone":"+61 2 6931 9466",
    "sg:postcode":"2650",
    "sg:province":"NSW",
    "sg:tags":[
        "hire",
        "costume"
    ],
    "wof:name":"Riverina Theatre Company",
    "wof:placetype":"venue"
},
  "geometry": {"coordinates":[147.370727539,-35.1075897217],"type":"Point"}
}