{
  "type": "Feature",
  "properties": {
    "iso:country":"AU",
    "sg:address":"Coonara Rd",
    "sg:city":"Olinda",
    "sg:classifiers":[
        {
            "category":"Sports & Exercise",
            "subcategory":"Golf",
            "type":"Entertainment"
        }
    ],
    "sg:phone":"+61 3 9751 1809",
    "sg:postcode":"3788",
    "sg:province":"VIC",
    "sg:tags":[
        "club"
    ],
    "wof:name":"Olinda Golf Club Incorporated",
    "wof:placetype":"venue"
},
  "geometry": {"coordinates":[145.386505,-37.871788],"type":"Point"}
}