{
  "type": "Feature",
  "properties": {
    "addr:full":"19 McIntyre Rd Para Hills West SA 5096",
    "addr:housenumber":"19",
    "addr:postcode":"5096",
    "addr:street":"Mcintyre Rd Para Hills West",
    "iso:country":"AU",
    "sg:address":"19 McIntyre Rd",
    "sg:city":"Para Hills West",
    "sg:classifiers":[
        {
            "category":"Autos & Motor Vehicles",
            "subcategory":"Automobile Sales",
            "type":"Retail Goods"
        }
    ],
    "sg:phone":"+61 8 8281 2330",
    "sg:postcode":"5096",
    "sg:province":"SA",
    "sg:tags":[
        "car",
        "used"
    ],
    "wof:name":"McIntyre Motors",
    "wof:placetype":"venue"
},
  "geometry": {"coordinates":[138.6484375,-34.7928123474],"type":"Point"}
}