{
  "type": "Feature",
  "properties": {
    "addr:full":"28 Blind Rd Nelson NSW 2765",
    "addr:housenumber":"28",
    "addr:postcode":"2765",
    "addr:street":"Blind Rd",
    "iso:country":"AU",
    "sg:address":"28 Blind Rd",
    "sg:city":"Nelson",
    "sg:classifiers":[
        {
            "category":"Building & Trades",
            "subcategory":"Construction",
            "type":"Services"
        }
    ],
    "sg:phone":"+61 2 9679 2043",
    "sg:postcode":"2765",
    "sg:province":"NSW",
    "sg:tags":[
        "earth",
        "excavating",
        "moving",
        "contractor"
    ],
    "wof:name":"J.S.J. Excavations",
    "wof:placetype":"venue"
},
  "geometry": {"coordinates":[150.934051514,-33.6480140686],"type":"Point"}
}