{
  "type": "Feature",
  "properties": {
    "iso:country":"AU",
    "sg:address":"68 Great Northern Hwy",
    "sg:city":"Midland",
    "sg:classifiers":[
        {
            "category":"Professional",
            "subcategory":"Employment Agencies",
            "type":"Services"
        }
    ],
    "sg:phone":"+61 8 9274 3833",
    "sg:postcode":"6056",
    "sg:province":"WA",
    "sg:tags":[
        "occupational",
        "therapist"
    ],
    "wof:name":"Cornwall House Occupational Therapy Services",
    "wof:placetype":"venue"
},
  "geometry": {"coordinates":[116.00591278100001,-31.8845615387],"type":"Point"}
}