{
  "type": "Feature",
  "properties": {
    "iso:country":"AU",
    "sg:address":"462 Main North Rd",
    "sg:city":"Blair Athol",
    "sg:classifiers":[
        {
            "category":"Autos & Motor Vehicles",
            "subcategory":"Auto Supplies",
            "type":"Retail Goods"
        }
    ],
    "sg:phone":"+61 8 8349 6242",
    "sg:postcode":"5084",
    "sg:province":"SA",
    "sg:tags":[
        "slot",
        "car",
        "equipment"
    ],
    "wof:name":"Hobby Habit",
    "wof:placetype":"venue"
},
  "geometry": {"coordinates":[138.60043335,-34.854801178],"type":"Point"}
}