{
  "type": "Feature",
  "properties": {
    "iso:country":"AU",
    "sg:address":"449 Newman Rd",
    "sg:city":"Geebung",
    "sg:classifiers":[
        {
            "category":"Home & Garden",
            "subcategory":"Carpets & Floor Coverings",
            "type":"Retail Goods"
        }
    ],
    "sg:phone":"+61 7 3865 7333",
    "sg:postcode":"4034",
    "sg:province":"QLD",
    "sg:tags":[
        "material",
        "waterproofing"
    ],
    "sg:website":"http://www.astecpaints.com.au",
    "wof:name":"Astec Paints Qld",
    "wof:placetype":"venue"
},
  "geometry": {"coordinates":[153.04892000000001,-27.364244],"type":"Point"}
}