{
  "type": "Feature",
  "properties": {
    "addr:full":"14 Gordon St Wodonga VIC 3690",
    "addr:housenumber":"14",
    "addr:postcode":"3690",
    "addr:street":"Gordon St",
    "iso:country":"AU",
    "sg:address":"14 Gordon St",
    "sg:city":"Wodonga",
    "sg:classifiers":[
        {
            "category":"Retail",
            "subcategory":"Auto Repair",
            "type":"Services"
        }
    ],
    "sg:phone":"+61 2 6024 1940",
    "sg:postcode":"3690",
    "sg:province":"VIC",
    "sg:tags":[
        "electrical"
    ],
    "wof:name":"Gordon Motors Wodonga",
    "wof:placetype":"venue"
},
  "geometry": {"coordinates":[146.88424682600001,-36.1296653748],"type":"Point"}
}