{
  "type": "Feature",
  "properties": {
    "iso:country":"AU",
    "sg:address":"3876 Murray Valley Hwy",
    "sg:city":"Cobram",
    "sg:classifiers":[
        {
            "category":"Building & Trades",
            "subcategory":"Construction",
            "type":"Services"
        }
    ],
    "sg:phone":"+61 3 5872 2393",
    "sg:postcode":"3644",
    "sg:province":"VIC",
    "sg:tags":[
        "earth",
        "excavating",
        "moving",
        "contractor"
    ],
    "wof:name":"Jobling Excavations Pty Ltd",
    "wof:placetype":"venue"
},
  "geometry": {"coordinates":[145.59437560999999,-35.9254798889],"type":"Point"}
}