{
  "type": "Feature",
  "properties": {
    "addr:full":"University of QLD School of Pschology St Lucia QLD 4067",
    "addr:postcode":"4067",
    "iso:country":"AU",
    "sg:address":"University of QLD School of Pschology St",
    "sg:city":"Lucia",
    "sg:classifiers":[
        {
            "category":"Health Services",
            "subcategory":"Health Practitioner",
            "type":"Services"
        }
    ],
    "sg:phone":"+61 409 053 752",
    "sg:postcode":"4067",
    "sg:province":"QLD",
    "sg:tags":[
        "psychologist"
    ],
    "wof:name":"Ruschena Annette",
    "wof:placetype":"venue"
},
  "geometry": {"coordinates":[153.01252746599999,-27.4963760376],"type":"Point"}
}