{
  "type": "Feature",
  "properties": {
    "addr:full":"Unit 14 A & B / 622 Stuart Hwy Berrimah NT 0828",
    "addr:housenumber":"&;/ 622",
    "addr:postcode":"nt 0828",
    "addr:street":"Stuart Hwy",
    "iso:country":"AU",
    "sg:address":"Unit 14 A & B / 622 Stuart Hwy",
    "sg:city":"Berrimah",
    "sg:classifiers":[
        {
            "category":"Retail",
            "subcategory":"Auto Repair",
            "type":"Services"
        }
    ],
    "sg:phone":"+61 8 8947 2499",
    "sg:postcode":"0828",
    "sg:province":"NT",
    "sg:tags":[
        "repairer",
        "motor",
        "engineer"
    ],
    "wof:name":"C & H Autoline",
    "wof:placetype":"venue"
},
  "geometry": {"coordinates":[130.91014099099999,-12.4282808304],"type":"Point"}
}