{
  "type": "Feature",
  "properties": {
    "addr:full":"148 Hawthorn Rd Caulfield North VIC 3161",
    "addr:housenumber":"148",
    "addr:postcode":"3161",
    "addr:street":"Hawthorn Rd",
    "iso:country":"AU",
    "sg:address":"148 Hawthorn Rd",
    "sg:city":"Caulfield North",
    "sg:classifiers":[
        {
            "category":"Shopping",
            "subcategory":"Optical Goods",
            "type":"Retail Goods"
        }
    ],
    "sg:phone":"+61 1300 853 937",
    "sg:postcode":"3161",
    "sg:province":"VIC",
    "sg:tags":[
        "dispenser",
        "prescription"
    ],
    "wof:name":"Darcy Tony",
    "wof:placetype":"venue"
},
  "geometry": {"coordinates":[145.02430725100001,-37.873916626],"type":"Point"}
}