{
  "type": "Feature",
  "properties": {
    "addr:full":"Unit1/ 19 Reliance Drv Tuggerah NSW 2259",
    "addr:housenumber":"19",
    "addr:postcode":"2259",
    "addr:street":"Reliance Drv",
    "iso:country":"AU",
    "sg:address":"Unit1/ 19 Reliance Drv",
    "sg:city":"Tuggerah",
    "sg:classifiers":[
        {
            "category":"Real Estate",
            "subcategory":"Real Estate Agent",
            "type":"Services"
        }
    ],
    "sg:phone":"+61 2 4351 0155",
    "sg:postcode":"2259",
    "sg:province":"NSW",
    "wof:name":"Smartnet Property Management Pty Ltd",
    "wof:placetype":"venue"
},
  "geometry": {"coordinates":[151.42494201700001,-33.3204612732],"type":"Point"}
}