{
  "type": "Feature",
  "properties": {
    "addr:full":"13 Speedwell St Somerville VIC 3912",
    "addr:housenumber":"13",
    "addr:postcode":"3912",
    "addr:street":"Speedwell St",
    "iso:country":"AU",
    "sg:address":"13 Speedwell St",
    "sg:city":"Somerville",
    "sg:classifiers":[
        {
            "category":"Wholesale",
            "subcategory":"Farm Supplies",
            "type":"Manufacturing & Wholesale Goods"
        }
    ],
    "sg:phone":"+61 3 5977 7227",
    "sg:postcode":"3912",
    "sg:province":"VIC",
    "sg:tags":[
        "feed",
        "supplement",
        "stock"
    ],
    "wof:name":"Somerville Stockfeeds Pty Ltd",
    "wof:placetype":"venue"
},
  "geometry": {"coordinates":[145.17984008799999,-38.2179527283],"type":"Point"}
}