{
  "type": "Feature",
  "properties": {
    "addr:full":"271 Gympie Rd Kedron QLD 4031",
    "addr:housenumber":"271",
    "addr:postcode":"4031",
    "addr:street":"Gympie Rd",
    "iso:country":"AU",
    "sg:address":"271 Gympie Rd",
    "sg:city":"Kedron",
    "sg:classifiers":[
        {
            "category":"Home & Garden",
            "subcategory":"Hardware",
            "type":"Retail Goods"
        }
    ],
    "sg:phone":"+61 7 3359 1126",
    "sg:postcode":"4031",
    "sg:province":"QLD",
    "sg:tags":[
        "plumber",
        "supply"
    ],
    "wof:name":"Wilston Builders Supplies",
    "wof:placetype":"venue"
},
  "geometry": {"coordinates":[153.032715,-27.407776],"type":"Point"}
}