{
  "type": "Feature",
  "properties": {
    "addr:full":"144 Juno Pde Greenacre NSW 2190",
    "addr:housenumber":"144",
    "addr:postcode":"2190",
    "addr:street":"Juno Pde",
    "iso:country":"AU",
    "sg:address":"144 Juno Pde",
    "sg:city":"Greenacre",
    "sg:classifiers":[
        {
            "category":"Professional",
            "subcategory":"Art Services",
            "type":"Services"
        }
    ],
    "sg:phone":"+61 412 038 886",
    "sg:postcode":"2190",
    "sg:province":"NSW",
    "sg:tags":[
        "decorator",
        "painter"
    ],
    "wof:name":"Golden Touch Painting & Decorating Pty Ltd",
    "wof:placetype":"venue"
},
  "geometry": {"coordinates":[151.06256099999999,-33.907616],"type":"Point"}
}