{
  "type": "Feature",
  "properties": {
    "addr:full":"765 Warringah Rd Forestville NSW 2087",
    "addr:housenumber":"765",
    "addr:postcode":"2087",
    "addr:street":"Warringah Rd",
    "iso:country":"AU",
    "sg:address":"765 Warringah Rd",
    "sg:city":"Forestville",
    "sg:classifiers":[
        {
            "category":"Health Services",
            "subcategory":"Doctor",
            "type":"Services"
        }
    ],
    "sg:phone":"+61 2 9451 6511",
    "sg:postcode":"2087",
    "sg:province":"NSW",
    "sg:tags":[
        "medical",
        "practitioner"
    ],
    "wof:name":"Chan Ying C",
    "wof:placetype":"venue"
},
  "geometry": {"coordinates":[151.20982360799999,-33.7602729797],"type":"Point"}
}