{
  "type": "Feature",
  "properties": {
    "iso:country":"AU",
    "sg:address":"4 203 Ballarat Rd",
    "sg:city":"Footscray",
    "sg:classifiers":[
        {
            "category":"Fast Food",
            "type":"Food & Drink"
        }
    ],
    "sg:phone":"+61 3 9317 3811",
    "sg:postcode":"3011",
    "sg:province":"VIC",
    "sg:tags":[
        "away",
        "take"
    ],
    "wof:name":"Southern Spice",
    "wof:placetype":"venue"
},
  "geometry": {"coordinates":[144.88926696799999,-37.7911911011],"type":"Point"}
}