{
  "type": "Feature",
  "properties": {
    "addr:full":"16 Wellesley Rd Ringwood North VIC 3134",
    "addr:housenumber":"16",
    "addr:postcode":"3134",
    "addr:street":"Wellesley Rd",
    "iso:country":"AU",
    "sg:address":"16 Wellesley Rd",
    "sg:city":"Ringwood North",
    "sg:classifiers":[
        {
            "category":"Professional",
            "subcategory":"Management & Consulting",
            "type":"Services"
        }
    ],
    "sg:phone":"+61 402 022 420",
    "sg:postcode":"3134",
    "sg:province":"VIC",
    "sg:tags":[
        "consultant"
    ],
    "wof:name":"Albany Interactive Pty Ltd",
    "wof:placetype":"venue"
},
  "geometry": {"coordinates":[145.23635864299999,-37.7794151306],"type":"Point"}
}