{
  "type": "Feature",
  "properties": {
    "addr:full":"137 Gwydir Hwy Inverell NSW 2360",
    "addr:housenumber":"137",
    "addr:postcode":"2360",
    "addr:street":"Gwydir Hwy",
    "iso:country":"AU",
    "sg:address":"137 Gwydir Hwy",
    "sg:city":"Inverell",
    "sg:classifiers":[
        {
            "category":"Travel",
            "subcategory":"Hotels & Motels",
            "type":"Entertainment"
        }
    ],
    "sg:phone":"+61 2 6722 4044",
    "sg:postcode":"2360",
    "sg:province":"NSW",
    "wof:name":"Top Of The Town",
    "wof:placetype":"venue"
},
  "geometry": {"coordinates":[151.01603698700001,-29.74310112],"type":"Point"}
}