{
  "type": "Feature",
  "properties": {
    "addr:full":"Shop 1 45 River st Riverside Plaza Mackay QLD 4740",
    "addr:housenumber":"shop;45",
    "addr:postcode":"4740",
    "addr:street":"River St Riverside Plaza",
    "iso:country":"AU",
    "sg:address":"Shop 1 45 River st Riverside Plaza",
    "sg:city":"Mackay",
    "sg:classifiers":[
        {
            "category":"Personal",
            "subcategory":"Beauty Salon",
            "type":"Services"
        }
    ],
    "sg:phone":"+61 7 4957 3168",
    "sg:postcode":"4740",
    "sg:province":"QLD",
    "sg:tags":[
        "hairdresser"
    ],
    "wof:name":"Sha-Sharrons Hair Stylist",
    "wof:placetype":"venue"
},
  "geometry": {"coordinates":[149.18553199999999,-21.142601],"type":"Point"}
}