{
  "type": "Feature",
  "properties": {
    "iso:country":"AU",
    "sg:address":"YSC, Lvl 2, Ste 4, 3 Spring St",
    "sg:city":"Sydney",
    "sg:classifiers":[
        {
            "category":"Health Services",
            "subcategory":"Health Practitioner",
            "type":"Services"
        }
    ],
    "sg:phone":"+61 2 9252 3332",
    "sg:postcode":"2000",
    "sg:province":"NSW",
    "sg:tags":[
        "psychologist"
    ],
    "wof:name":"Angela David",
    "wof:placetype":"venue"
},
  "geometry": {"coordinates":[151.20930480999999,-33.8643188477],"type":"Point"}
}