{
  "type": "Feature",
  "properties": {
    "iso:country":"AU",
    "sg:address":"7 Ellingworth Pde",
    "sg:city":"Box Hill",
    "sg:classifiers":[
        {
            "category":"Real Estate",
            "subcategory":"Surveying",
            "type":"Services"
        }
    ],
    "sg:phone":"+61 3 9898 0761",
    "sg:postcode":"3128",
    "sg:province":"VIC",
    "sg:tags":[
        "surveyor",
        "land"
    ],
    "wof:name":"Carson Simpson Pty Ltd",
    "wof:placetype":"venue"
},
  "geometry": {"coordinates":[145.12402343799999,-37.8203697205],"type":"Point"}
}