{
  "type": "Feature",
  "properties": {
    "addr:full":"39 Whitaker St Yennora NSW 2161",
    "addr:housenumber":"39",
    "addr:postcode":"2161",
    "addr:street":"Whitaker St",
    "iso:country":"AU",
    "sg:address":"39 Whitaker St",
    "sg:city":"Yennora",
    "sg:classifiers":[
        {
            "category":"Retail",
            "subcategory":"Auto Repair",
            "type":"Services"
        }
    ],
    "sg:phone":"+61 2 9892 1291",
    "sg:postcode":"2161",
    "sg:province":"NSW",
    "sg:tags":[
        "repairer",
        "motor",
        "engineer"
    ],
    "wof:name":"Sunshine Mechanical Repairs",
    "wof:placetype":"venue"
},
  "geometry": {"coordinates":[150.975067139,-33.8646240234],"type":"Point"}
}