{
  "type": "Feature",
  "properties": {
    "addr:full":"Unit 1/ 49 Blaxland Rd Campbelltown NSW 2560",
    "addr:housenumber":"49",
    "addr:postcode":"2560",
    "addr:street":"Blaxland Rd",
    "iso:country":"AU",
    "sg:address":"Unit 1/ 49 Blaxland Rd",
    "sg:city":"Campbelltown",
    "sg:classifiers":[
        {
            "category":"Building & Trades",
            "subcategory":"Construction",
            "type":"Services"
        }
    ],
    "sg:phone":"+61 2 4620 4420",
    "sg:postcode":"2560",
    "sg:province":"NSW",
    "sg:tags":[
        "home",
        "air conditioning"
    ],
    "wof:name":"Shear Comfort",
    "wof:placetype":"venue"
},
  "geometry": {"coordinates":[150.813186645,-34.0598182678],"type":"Point"}
}