{
  "type": "Feature",
  "properties": {
    "addr:full":"95 Epping Rd Macquarie Park NSW 2113",
    "addr:housenumber":"95",
    "addr:postcode":"2113",
    "addr:street":"Epping Rd",
    "iso:country":"AU",
    "sg:address":"95 Epping Rd",
    "sg:city":"Macquarie Park",
    "sg:classifiers":[
        {
            "category":"Health Services",
            "subcategory":"Doctor",
            "type":"Services"
        }
    ],
    "sg:phone":"+61 2 9855 5144",
    "sg:postcode":"2113",
    "sg:province":"NSW",
    "sg:tags":[
        "occupational",
        "safety"
    ],
    "wof:name":"Douglass Hanly Moir Pathology",
    "wof:placetype":"venue"
},
  "geometry": {"coordinates":[151.12355041500001,-33.7860603333],"type":"Point"}
}