{
  "type": "Feature",
  "properties": {
    "iso:country":"AU",
    "sg:address":"6 Coronado Crt",
    "sg:city":"Highton",
    "sg:classifiers":[
        {
            "category":"Building & Trades",
            "subcategory":"Plumbing",
            "type":"Services"
        }
    ],
    "sg:phone":"+61 3 5244 0625",
    "sg:postcode":"3216",
    "sg:province":"VIC",
    "sg:tags":[
        "plumber",
        "gasfitters"
    ],
    "wof:name":"Hardwick David",
    "wof:placetype":"venue"
},
  "geometry": {"coordinates":[144.31924438499999,-38.1865272522],"type":"Point"}
}