{
  "type": "Feature",
  "properties": {
    "addr:full":"15 Bright St Eaglehawk VIC 3556",
    "addr:housenumber":"15",
    "addr:postcode":"3556",
    "addr:street":"Bright St",
    "iso:country":"AU",
    "sg:address":"15 Bright St",
    "sg:city":"Eaglehawk",
    "sg:classifiers":[
        {
            "category":"Education",
            "subcategory":"Kindergarten",
            "type":"Public Place"
        }
    ],
    "sg:phone":"+61 3 5446 8691",
    "sg:postcode":"3556",
    "sg:province":"VIC",
    "sg:tags":[
        "pre-schools"
    ],
    "wof:name":"Eaglehawk Pre-School",
    "wof:placetype":"venue"
},
  "geometry": {"coordinates":[144.259368897,-36.7206954956],"type":"Point"}
}