{
  "type": "Feature",
  "properties": {
    "addr:full":"Lot 54 Flett Rd Roseworthy SA 5371",
    "addr:postcode":"5371",
    "addr:street":"Flett Rd",
    "iso:country":"AU",
    "sg:address":"Lot 54 Flett Rd",
    "sg:city":"Roseworthy",
    "sg:classifiers":[
        {
            "category":"Manufacturing",
            "subcategory":"Rubber & Plastics",
            "type":"Manufacturing & Wholesale Goods"
        }
    ],
    "sg:phone":"+61 8 8524 8723",
    "sg:postcode":"5371",
    "sg:province":"SA",
    "sg:tags":[
        "wholesaler",
        "product",
        "mfrs"
    ],
    "wof:name":"Tymac Australia",
    "wof:placetype":"venue"
},
  "geometry": {"coordinates":[138.752243042,-34.5361671448],"type":"Point"}
}