{
  "type": "Feature",
  "properties": {
    "addr:full":"Suite 45 33 Southbank Blv South Melbourne VIC 3205",
    "addr:housenumber":"33",
    "addr:postcode":"3205",
    "addr:street":"Southbank Blv",
    "iso:country":"AU",
    "sg:address":"Suite 45 33 Southbank Blv",
    "sg:city":"South Melbourne",
    "sg:classifiers":[
        {
            "category":"Building & Trades",
            "subcategory":"Construction",
            "type":"Services"
        }
    ],
    "sg:phone":"+61 3 9645 8811",
    "sg:postcode":"3205",
    "sg:province":"VIC",
    "sg:tags":[
        "waterproofing",
        "contractor"
    ],
    "wof:name":"Esha Products (Australia) Pty Ltd",
    "wof:placetype":"venue"
},
  "geometry": {"coordinates":[144.96397400000001,-37.82225],"type":"Point"}
}