{
  "type": "Feature",
  "properties": {
    "addr:full":"29 Hastings Rd Frankston VIC 3199",
    "addr:housenumber":"29",
    "addr:postcode":"3199",
    "addr:street":"Hastings Rd",
    "iso:country":"AU",
    "sg:address":"29 Hastings Rd",
    "sg:city":"Frankston",
    "sg:classifiers":[
        {
            "category":"Health Services",
            "subcategory":"Doctor",
            "type":"Services"
        }
    ],
    "sg:phone":"+61 3 9770 2139",
    "sg:postcode":"3199",
    "sg:province":"VIC",
    "sg:tags":[
        "medical",
        "practitioner"
    ],
    "wof:name":"Holmes Romayne",
    "wof:placetype":"venue"
},
  "geometry": {"coordinates":[145.05133056599999,-37.8327217102],"type":"Point"}
}