{
  "type": "Feature",
  "properties": {
    "iso:country":"AU",
    "sg:address":"Shop 5, 127",
    "sg:city":"Moolanda Blv Kingsley",
    "sg:classifiers":[
        {
            "category":"Personal",
            "subcategory":"Beauty Salon",
            "type":"Services"
        }
    ],
    "sg:phone":"+61 8 9309 1177",
    "sg:postcode":"6026",
    "sg:province":"WA",
    "sg:tags":[
        "hairdresser"
    ],
    "wof:name":"Raffertys For Hair",
    "wof:placetype":"venue"
},
  "geometry": {"coordinates":[115.80510711700001,-31.8074836731],"type":"Point"}
}