{
  "type": "Feature",
  "properties": {
    "addr:full":"348 Arden St Kensington VIC 3031",
    "addr:housenumber":"348",
    "addr:postcode":"3031",
    "addr:street":"Arden St",
    "iso:country":"AU",
    "sg:address":"348 Arden St",
    "sg:city":"Kensington",
    "sg:classifiers":[
        {
            "category":"Professional",
            "subcategory":"Detective & Security Services",
            "type":"Services"
        }
    ],
    "sg:phone":"+61 3 9372 6400",
    "sg:postcode":"3031",
    "sg:province":"VIC",
    "sg:tags":[
        "consultant",
        "system"
    ],
    "wof:name":"Visual Security Systems VSS",
    "wof:placetype":"venue"
},
  "geometry": {"coordinates":[144.934235,-37.799023],"type":"Point"}
}