{
  "type": "Feature",
  "properties": {
    "addr:full":"85 A Fitzroy St Warwick QLD 4370",
    "addr:housenumber":"85 a",
    "addr:postcode":"4370",
    "addr:street":"Fitzroy St",
    "iso:country":"AU",
    "sg:address":"85 A Fitzroy St",
    "sg:city":"Warwick",
    "sg:classifiers":[
        {
            "category":"Shopping",
            "subcategory":"Mobile Phones",
            "type":"Retail Goods"
        }
    ],
    "sg:phone":"+61 7 4667 1252",
    "sg:postcode":"4370",
    "sg:province":"QLD",
    "sg:tags":[
        "telephone",
        "accessory"
    ],
    "wof:name":"Mobile XS",
    "wof:placetype":"venue"
},
  "geometry": {"coordinates":[152.03660583499999,-28.2145786285],"type":"Point"}
}