{
  "type": "Feature",
  "properties": {
    "addr:full":"70 Brieses Rd Peats Ridge NSW 2250",
    "addr:housenumber":"70",
    "addr:postcode":"2250",
    "addr:street":"Brieses Rd",
    "iso:country":"AU",
    "sg:address":"70 Brieses Rd",
    "sg:city":"Peats Ridge",
    "sg:classifiers":[
        {
            "category":"Farming",
            "subcategory":"Nursery",
            "type":"Manufacturing & Wholesale Goods"
        }
    ],
    "sg:phone":"+61 2 4375 1199",
    "sg:postcode":"2250",
    "sg:province":"NSW",
    "wof:name":"Royale Orchids",
    "wof:placetype":"venue"
},
  "geometry": {"coordinates":[151.23144531200001,-33.3737831116],"type":"Point"}
}