{
  "type": "Feature",
  "properties": {
    "iso:country":"AU",
    "sg:address":"36a High St",
    "sg:city":"Campbell Town",
    "sg:classifiers":[
        {
            "category":"Retail",
            "subcategory":"Funeral Services",
            "type":"Services"
        }
    ],
    "sg:phone":"+61 3 6381 1167",
    "sg:postcode":"7210",
    "sg:province":"TAS",
    "sg:tags":[
        "director"
    ],
    "wof:name":"Lockett W & Sons",
    "wof:placetype":"venue"
},
  "geometry": {"coordinates":[147.488174,-41.920227],"type":"Point"}
}