{
  "type": "Feature",
  "properties": {
    "iso:country":"AU",
    "sg:address":"32 Albertine Crs",
    "sg:city":"Sydenham",
    "sg:classifiers":[
        {
            "category":"Professional",
            "subcategory":"Management & Consulting",
            "type":"Services"
        }
    ],
    "sg:phone":"+61 1300 865 327",
    "sg:postcode":"3037",
    "sg:province":"VIC",
    "sg:tags":[
        "consultant"
    ],
    "wof:name":"Ozeedial 1300 To-Lease",
    "wof:placetype":"venue"
},
  "geometry": {"coordinates":[144.763428,-37.701809],"type":"Point"}
}