{
  "type": "Feature",
  "properties": {
    "addr:full":"114 Albert St Sebastopol VIC 3356",
    "addr:housenumber":"114",
    "addr:postcode":"3356",
    "addr:street":"Albert St",
    "iso:country":"AU",
    "sg:address":"114 Albert St",
    "sg:city":"Sebastopol",
    "sg:classifiers":[
        {
            "category":"Manufacturing",
            "subcategory":"Petroleum Products",
            "type":"Manufacturing & Wholesale Goods"
        }
    ],
    "sg:phone":"+61 3 5335 7333",
    "sg:postcode":"3356",
    "sg:province":"VIC",
    "sg:tags":[
        "lubricant"
    ],
    "wof:name":"&#034;U&#034; Change",
    "wof:placetype":"venue"
},
  "geometry": {"coordinates":[143.840836,-37.591515],"type":"Point"}
}