{
  "type": "Feature",
  "properties": {
    "addr:full":"5 Wellington St Flemington VIC 3031",
    "addr:housenumber":"5",
    "addr:postcode":"3031",
    "addr:street":"Wellington St",
    "iso:country":"AU",
    "sg:address":"5 Wellington St",
    "sg:city":"Flemington",
    "sg:classifiers":[
        {
            "category":"Personal",
            "subcategory":"Beauty Salon",
            "type":"Services"
        }
    ],
    "sg:phone":"+61 3 9376 8131",
    "sg:postcode":"3031",
    "sg:province":"VIC",
    "sg:tags":[
        "hairdresser"
    ],
    "wof:name":"21st Century Hair Studio",
    "wof:placetype":"venue"
},
  "geometry": {"coordinates":[144.93139600000001,-37.787601],"type":"Point"}
}