{
  "type": "Feature",
  "properties": {
    "addr:full":"57 Dawson St Tullamarine VIC 3043",
    "addr:housenumber":"57",
    "addr:postcode":"3043",
    "addr:street":"Dawson St",
    "iso:country":"AU",
    "sg:address":"57 Dawson St",
    "sg:city":"Tullamarine",
    "sg:classifiers":[
        {
            "category":"Communications",
            "subcategory":"Film & Video Production",
            "type":"Services"
        }
    ],
    "sg:phone":"+61 3 9335 2169",
    "sg:postcode":"3043",
    "sg:province":"VIC",
    "sg:tags":[
        "dvd",
        "library"
    ],
    "wof:name":"Video 57",
    "wof:placetype":"venue"
},
  "geometry": {"coordinates":[144.87396240199999,-37.7005157471],"type":"Point"}
}