{
  "type": "Feature",
  "properties": {
    "iso:country":"AU",
    "sg:address":"Bundall Rd",
    "sg:city":"Bundall",
    "sg:classifiers":[
        {
            "category":"Building & Trades",
            "subcategory":"Construction",
            "type":"Services"
        }
    ],
    "sg:phone":"+61 401 696 040",
    "sg:postcode":"4217",
    "sg:province":"QLD",
    "sg:tags":[
        "window",
        "tinting"
    ],
    "wof:name":"All Clear Tinting",
    "wof:placetype":"venue"
},
  "geometry": {"coordinates":[153.411987305,-28.0108585358],"type":"Point"}
}