{
  "type": "Feature",
  "properties": {
    "iso:country":"AU",
    "sg:address":"4 Jessop St",
    "sg:city":"Whyalla Playford",
    "sg:classifiers":[
        {
            "category":"Retail",
            "subcategory":"Storage",
            "type":"Services"
        }
    ],
    "sg:phone":"+61 417 896 176",
    "sg:postcode":"5600",
    "sg:province":"SA",
    "wof:name":"Spencer Gulf Sef Storage",
    "wof:placetype":"venue"
},
  "geometry": {"coordinates":[137.552658,-33.038139],"type":"Point"}
}