{
  "type": "Feature",
  "properties": {
    "addr:full":"Dorsett Rd Waroona WA 6215",
    "addr:postcode":"6215",
    "addr:street":"Dorsett Rd",
    "iso:country":"AU",
    "sg:address":"Dorsett Rd",
    "sg:city":"Waroona",
    "sg:classifiers":[
        {
            "category":"Farming",
            "subcategory":"Farm",
            "type":"Manufacturing & Wholesale Goods"
        }
    ],
    "sg:phone":"+61 8 9733 1435",
    "sg:postcode":"6215",
    "sg:province":"WA",
    "sg:tags":[
        "farmer"
    ],
    "wof:name":"Stacey C",
    "wof:placetype":"venue"
},
  "geometry": {"coordinates":[115.818169,-32.833542],"type":"Point"}
}