{
  "type": "Feature",
  "properties": {
    "iso:country":"AU",
    "sg:address":"40 Susan Rd",
    "sg:city":"Landsdale",
    "sg:classifiers":[
        {
            "category":"Building & Trades",
            "subcategory":"Construction",
            "type":"Services"
        }
    ],
    "sg:phone":"+61 8 9409 9051",
    "sg:postcode":"6065",
    "sg:province":"WA",
    "sg:tags":[
        "concrete",
        "contractor"
    ],
    "wof:name":"Ravi Basil",
    "wof:placetype":"venue"
},
  "geometry": {"coordinates":[115.824157715,-31.8047275543],"type":"Point"}
}