{
  "type": "Feature",
  "properties": {
    "iso:country":"AU",
    "sg:address":"Lot 582/ Gum Park",
    "sg:city":"Broken Hill",
    "sg:classifiers":[
        {
            "category":"Building & Trades",
            "subcategory":"Landscaping Services",
            "type":"Services"
        }
    ],
    "sg:phone":"+61 8 8091 2596",
    "sg:postcode":"2880",
    "sg:province":"NSW",
    "sg:tags":[
        "grazier"
    ],
    "wof:name":"Herring P & J",
    "wof:placetype":"venue"
},
  "geometry": {"coordinates":[141.46548461899999,-31.9583301544],"type":"Point"}
}