{
  "type": "Feature",
  "properties": {
    "addr:full":"Shop 4 Maddington Metro Maddington WA 6109",
    "addr:housenumber":"shop 4",
    "addr:postcode":"6109",
    "iso:country":"AU",
    "sg:address":"Shop 4 Maddington Metro",
    "sg:city":"Maddington",
    "sg:classifiers":[
        {
            "category":"Fast Food",
            "type":"Food & Drink"
        }
    ],
    "sg:phone":"+61 8 9493 2880",
    "sg:postcode":"6109",
    "sg:province":"WA",
    "sg:tags":[
        "away",
        "take"
    ],
    "wof:name":"Kebab Company The",
    "wof:placetype":"venue"
},
  "geometry": {"coordinates":[116.01087188699999,-32.0391387939],"type":"Point"}
}