{
  "type": "Feature",
  "properties": {
    "addr:full":"Shop 18, Wilsonton Shopping Centre Wilsonton QLD 4350",
    "addr:housenumber":"shop 18",
    "addr:postcode":"4350",
    "iso:country":"AU",
    "sg:address":"Shop 18, Wilsonton Shopping Centre",
    "sg:city":"Wilsonton",
    "sg:classifiers":[
        {
            "category":"Fast Food",
            "type":"Food & Drink"
        }
    ],
    "sg:phone":"+61 7 4634 0086",
    "sg:postcode":"4350",
    "sg:province":"QLD",
    "sg:tags":[
        "away",
        "take"
    ],
    "wof:name":"Fresh Katch",
    "wof:placetype":"venue"
},
  "geometry": {"coordinates":[151.913376,-27.539141],"type":"Point"}
}