{
  "type": "Feature",
  "properties": {
    "addr:full":"Office 2 12-14 Rutherford Rd Seaford VIC 3198",
    "addr:housenumber":"12-14",
    "addr:postcode":"3198",
    "addr:street":"Rutherford Rd",
    "iso:country":"AU",
    "sg:address":"Office 2 12-14 Rutherford Rd",
    "sg:city":"Seaford",
    "sg:classifiers":[
        {
            "category":"Professional",
            "subcategory":"Management & Consulting",
            "type":"Services"
        }
    ],
    "sg:phone":"+61 3 9789 4651",
    "sg:postcode":"3198",
    "sg:province":"VIC",
    "sg:tags":[
        "consultant"
    ],
    "wof:name":"Options Business Strategy Consultants",
    "wof:placetype":"venue"
},
  "geometry": {"coordinates":[145.15020751899999,-38.0986938477],"type":"Point"}
}