{
  "type": "Feature",
  "properties": {
    "iso:country":"AU",
    "sg:address":"Endeavour Education Support Centre 38 Endeavour Rd",
    "sg:city":"Port Kennedy",
    "sg:classifiers":[
        {
            "category":"Education",
            "subcategory":"School",
            "type":"Public Place"
        }
    ],
    "sg:phone":"+61 8 9524 5000",
    "sg:postcode":"6172",
    "sg:province":"WA",
    "sg:tags":[
        "state",
        "except",
        "nsw"
    ],
    "wof:name":"Schools Government (Public)",
    "wof:placetype":"venue"
},
  "geometry": {"coordinates":[115.752319,-32.370796],"type":"Point"}
}