{
  "type": "Feature",
  "properties": {
    "iso:country":"AU",
    "sg:address":"Ste 4, 159- 167 Victoria Rd",
    "sg:city":"Drummoyne",
    "sg:classifiers":[
        {
            "category":"Professional",
            "subcategory":"Accounting & Tax Preparation",
            "type":"Services"
        }
    ],
    "sg:phone":"+61 2 9181 3000",
    "sg:postcode":"2047",
    "sg:province":"NSW",
    "sg:tags":[
        "accountant",
        "auditor"
    ],
    "wof:name":"D&#039;Ambrosio & Co.",
    "wof:placetype":"venue"
},
  "geometry": {"coordinates":[151.155334,-33.852058],"type":"Point"}
}