{
  "type": "Feature",
  "properties": {
    "iso:country":"AU",
    "sg:address":"Unit 6 14-16 Babdoyle St",
    "sg:city":"Loganholme",
    "sg:classifiers":[
        {
            "category":"Shopping",
            "type":"Retail Goods"
        }
    ],
    "sg:phone":"+61 7 3806 4480",
    "sg:postcode":"4129",
    "sg:province":"QLD",
    "sg:tags":[
        "product",
        "plastic"
    ],
    "wof:name":"Logan City Plastics",
    "wof:placetype":"venue"
},
  "geometry": {"coordinates":[153.192092895,-27.6806621552],"type":"Point"}
}