{
  "type": "Feature",
  "properties": {
    "addr:full":"58 Furnace Rd Welshpool WA 6106",
    "addr:housenumber":"58",
    "addr:postcode":"6106",
    "addr:street":"Furnace Rd",
    "iso:country":"AU",
    "sg:address":"58 Furnace Rd",
    "sg:city":"Welshpool",
    "sg:classifiers":[
        {
            "category":"Mining & Drilling",
            "type":"Manufacturing & Wholesale Goods"
        }
    ],
    "sg:phone":"+61 8 9351 9119",
    "sg:postcode":"6106",
    "sg:province":"WA",
    "sg:tags":[
        "equipment",
        "quarrying",
        "supply"
    ],
    "wof:name":"Caudo Group",
    "wof:placetype":"venue"
},
  "geometry": {"coordinates":[115.95439148,-31.9962158203],"type":"Point"}
}