{
  "type": "Feature",
  "properties": {
    "iso:country":"AU",
    "sg:address":"1/48- 54 Railway Crs",
    "sg:city":"Jannali",
    "sg:classifiers":[
        {
            "category":"Health Services",
            "subcategory":"Health Practitioner",
            "type":"Services"
        }
    ],
    "sg:phone":"+61 2 9589 4014",
    "sg:postcode":"2226",
    "sg:province":"NSW",
    "sg:tags":[
        "physiotherapist"
    ],
    "wof:name":"Jannali Physiotherapy & Sports Injury Clinic",
    "wof:placetype":"venue"
},
  "geometry": {"coordinates":[151.06890869099999,-34.0054702759],"type":"Point"}
}