{
  "type": "Feature",
  "properties": {
    "addr:full":"Unit 2 102 Neville St Carnegie VIC 3163",
    "addr:housenumber":"102",
    "addr:postcode":"3163",
    "addr:street":"Neville St",
    "iso:country":"AU",
    "sg:address":"Unit 2 102 Neville St",
    "sg:city":"Carnegie",
    "sg:classifiers":[
        {
            "category":"Sports & Exercise",
            "subcategory":"Gym",
            "type":"Entertainment"
        }
    ],
    "sg:phone":"+61 3 9576 7270",
    "sg:postcode":"3163",
    "sg:province":"VIC",
    "sg:tags":[
        "health",
        "fitness"
    ],
    "wof:name":"Adam Williams Personal Trainer",
    "wof:placetype":"venue"
},
  "geometry": {"coordinates":[145.05413818400001,-37.8981361389],"type":"Point"}
}