{
  "type": "Feature",
  "properties": {
    "iso:country":"AU",
    "sg:address":"Lvl 1, 1/ 5 Railway Ave",
    "sg:city":"Wahroonga",
    "sg:classifiers":[
        {
            "category":"Real Estate",
            "subcategory":"Architect",
            "type":"Services"
        }
    ],
    "sg:phone":"+61 2 9487 4033",
    "sg:postcode":"2076",
    "sg:province":"NSW",
    "wof:name":"G Gordon Fuller Architects",
    "wof:placetype":"venue"
},
  "geometry": {"coordinates":[151.11695861800001,-33.7181854248],"type":"Point"}
}