{
  "type": "Feature",
  "properties": {
    "iso:country":"AU",
    "sg:address":"Factory 1/ 17",
    "sg:city":"Carbine Way Mornington",
    "sg:classifiers":[
        {
            "category":"Professional",
            "subcategory":"Testing Lab",
            "type":"Services"
        }
    ],
    "sg:phone":"+61 1300 557 260",
    "sg:postcode":"3931",
    "sg:province":"VIC",
    "sg:tags":[
        "soil",
        "investigation"
    ],
    "wof:name":"Site Geo Technical",
    "wof:placetype":"venue"
},
  "geometry": {"coordinates":[145.067260742,-38.2303504944],"type":"Point"}
}