{
  "type": "Feature",
  "properties": {
    "addr:full":"295 Dandos Rd Lara VIC 3212",
    "addr:housenumber":"295",
    "addr:postcode":"3212",
    "addr:street":"Dandos Rd",
    "iso:country":"AU",
    "sg:address":"295 Dandos Rd",
    "sg:city":"Lara",
    "sg:classifiers":[
        {
            "category":"Food & Beverages",
            "subcategory":"Meat & Fish",
            "type":"Retail Goods"
        }
    ],
    "sg:phone":"+61 3 5282 5350",
    "sg:postcode":"3212",
    "sg:province":"VIC",
    "sg:tags":[
        "aquaculture"
    ],
    "wof:name":"Ocean Wave Seafoods",
    "wof:placetype":"venue"
},
  "geometry": {"coordinates":[144.43663024899999,-38.0568885803],"type":"Point"}
}