{
  "type": "Feature",
  "properties": {
    "addr:full":"Westfield Shopping Centre, Millaroo Drv Helensvale QLD 4212",
    "addr:postcode":"4212",
    "addr:street":"Millaroo Drv",
    "iso:country":"AU",
    "sg:address":"Westfield Shopping Centre, Millaroo Drv",
    "sg:city":"Helensvale",
    "sg:classifiers":[
        {
            "category":"Insurance",
            "subcategory":"Health Insurance",
            "type":"Services"
        }
    ],
    "sg:phone":"+61 13 23 31",
    "sg:postcode":"4212",
    "sg:province":"QLD",
    "wof:name":"Medibank Private",
    "wof:placetype":"venue"
},
  "geometry": {"coordinates":[153.33462524399999,-27.9292602539],"type":"Point"}
}