{
  "type": "Feature",
  "properties": {
    "addr:full":"174 Neerim Rd Carnegie VIC 3163",
    "addr:housenumber":"174",
    "addr:postcode":"3163",
    "addr:street":"Neerim Rd",
    "iso:country":"AU",
    "sg:address":"174 Neerim Rd",
    "sg:city":"Carnegie",
    "sg:classifiers":[
        {
            "category":"Manufacturing",
            "subcategory":"Food",
            "type":"Manufacturing & Wholesale Goods"
        }
    ],
    "sg:phone":"+61 3 9572 3644",
    "sg:postcode":"3163",
    "sg:province":"VIC",
    "sg:tags":[
        "function",
        "catering"
    ],
    "wof:name":"Best & Fresh",
    "wof:placetype":"venue"
},
  "geometry": {"coordinates":[145.05288696299999,-37.8882141113],"type":"Point"}
}