{
  "type": "Feature",
  "properties": {
    "addr:full":"10 Sugargum Crt View Bank VIC 3084",
    "addr:housenumber":"10",
    "addr:postcode":"3084",
    "addr:street":"Sugargum Crt View Bank",
    "iso:country":"AU",
    "sg:address":"10 Sugargum Crt",
    "sg:city":"View Bank",
    "sg:classifiers":[
        {
            "category":"Building & Trades",
            "subcategory":"Plumbing",
            "type":"Services"
        }
    ],
    "sg:phone":"+61 417 558 370",
    "sg:postcode":"3084",
    "sg:province":"VIC",
    "sg:tags":[
        "plumber",
        "gasfitters"
    ],
    "wof:name":"Robert Butling Plumbing",
    "wof:placetype":"venue"
},
  "geometry": {"coordinates":[145.09693908700001,-37.7353782654],"type":"Point"}
}