{
  "type": "Feature",
  "properties": {
    "iso:country":"AU",
    "sg:address":"66 Winsome Rd",
    "sg:city":"Salisbury",
    "sg:classifiers":[
        {
            "category":"Personal",
            "subcategory":"Skin Care",
            "type":"Services"
        }
    ],
    "sg:phone":"+61 7 3216 6640",
    "sg:postcode":"4107",
    "sg:province":"QLD",
    "sg:tags":[
        "hair",
        "product"
    ],
    "wof:name":"Fingers Need Nails",
    "wof:placetype":"venue"
},
  "geometry": {"coordinates":[153.030059814,-27.5494766235],"type":"Point"}
}