{
  "type": "Feature",
  "properties": {
    "addr:full":"Shop 19 Cusack Centre, Eyre St Kingston ACT 2604",
    "addr:housenumber":"shop 19;centre",
    "addr:postcode":"2604",
    "addr:street":"Cusack;Eyre St",
    "iso:country":"AU",
    "sg:address":"Shop 19 Cusack Centre, Eyre St",
    "sg:city":"Kingston",
    "sg:classifiers":[
        {
            "category":"Autos & Motor Vehicles",
            "subcategory":"Recreational Vehicle Sales",
            "type":"Retail Goods"
        }
    ],
    "sg:phone":"+61 2 6162 0881",
    "sg:postcode":"2604",
    "sg:province":"ACT",
    "sg:tags":[
        "confectionery"
    ],
    "wof:name":"All Things Chocolate",
    "wof:placetype":"venue"
},
  "geometry": {"coordinates":[149.146682739,-35.3145294189],"type":"Point"}
}