{
  "type": "Feature",
  "properties": {
    "addr:full":"21 Sherwood Rd Rocklea QLD 4106",
    "addr:housenumber":"21",
    "addr:postcode":"4106",
    "addr:street":"Sherwood Rd",
    "iso:country":"AU",
    "sg:address":"21 Sherwood Rd",
    "sg:city":"Rocklea",
    "sg:classifiers":[
        {
            "category":"Transit Center",
            "subcategory":"Freight",
            "type":"Transportation"
        }
    ],
    "sg:phone":"+61 7 3848 4191",
    "sg:postcode":"4106",
    "sg:province":"QLD",
    "sg:tags":[
        "forklift",
        "truck"
    ],
    "wof:name":"Beaurepaires",
    "wof:placetype":"venue"
},
  "geometry": {"coordinates":[153.01094055199999,-27.5409984589],"type":"Point"}
}