{
  "type": "Feature",
  "properties": {
    "addr:full":"2 Revesby Pl Revesby NSW 2212",
    "addr:housenumber":"2",
    "addr:postcode":"2212",
    "addr:street":"Revesby Pl",
    "iso:country":"AU",
    "sg:address":"2 Revesby Pl",
    "sg:city":"Revesby",
    "sg:classifiers":[
        {
            "category":"Shopping",
            "subcategory":"Gifts & Souvenirs",
            "type":"Retail Goods"
        }
    ],
    "sg:phone":"+61 2 9771 4760",
    "sg:postcode":"2212",
    "sg:province":"NSW",
    "sg:tags":[
        "shop",
        "supply"
    ],
    "wof:name":"Quicky Mart",
    "wof:placetype":"venue"
},
  "geometry": {"coordinates":[151.015457,-33.953613],"type":"Point"}
}