{
  "type": "Feature",
  "properties": {
    "addr:full":"22 Fairfax Rd Bellevue Hill NSW 2023",
    "addr:housenumber":"22",
    "addr:postcode":"2023",
    "addr:street":"Fairfax Rd",
    "iso:country":"AU",
    "sg:address":"22 Fairfax Rd",
    "sg:city":"Bellevue Hill",
    "sg:classifiers":[
        {
            "category":"Personal",
            "subcategory":"Beauty Salon",
            "type":"Services"
        }
    ],
    "sg:phone":"+61 413 085 242",
    "sg:postcode":"2023",
    "sg:province":"NSW",
    "sg:tags":[
        "supply",
        "artist",
        "make-up"
    ],
    "wof:name":"Bernard Sarah",
    "wof:placetype":"venue"
},
  "geometry": {"coordinates":[151.247116089,-33.8764457703],"type":"Point"}
}