{
  "type": "Feature",
  "properties": {
    "addr:full":"Suite 7, The Heights Medical Centre, Lookout Rd New Lambton NSW 2305",
    "addr:postcode":"2305",
    "addr:street":"Lookout Rd",
    "iso:country":"AU",
    "sg:address":"Suite 7, The Heights Medical Centre, Lookout Rd",
    "sg:city":"New Lambton",
    "sg:classifiers":[
        {
            "category":"Health Services",
            "subcategory":"Doctor",
            "type":"Services"
        }
    ],
    "sg:phone":"+61 2 4952 3900",
    "sg:postcode":"2305",
    "sg:province":"NSW",
    "sg:tags":[
        "medical",
        "practitioner"
    ],
    "wof:name":"Thambar Dr Suku",
    "wof:placetype":"venue"
},
  "geometry": {"coordinates":[151.70137,-32.922161],"type":"Point"}
}