{
  "type": "Feature",
  "properties": {
    "addr:full":"377 Crown St Surry Hills NSW 2010",
    "addr:housenumber":"377",
    "addr:postcode":"2010",
    "addr:street":"Crown St",
    "iso:country":"AU",
    "sg:address":"377 Crown St",
    "sg:city":"Surry Hills",
    "sg:classifiers":[
        {
            "category":"Fast Food",
            "type":"Food & Drink"
        }
    ],
    "sg:phone":"+61 2 9331 7008",
    "sg:postcode":"2010",
    "sg:province":"NSW",
    "sg:tags":[
        "away",
        "take"
    ],
    "wof:name":"Top Hot Food Take Away Shop",
    "wof:placetype":"venue"
},
  "geometry": {"coordinates":[151.21386718799999,-33.8852653503],"type":"Point"}
}