{
  "type": "Feature",
  "properties": {
    "iso:country":"AU",
    "sg:address":"18 Regent St",
    "sg:city":"Belmont",
    "sg:classifiers":[
        {
            "category":"Health Services",
            "subcategory":"Doctor",
            "type":"Services"
        }
    ],
    "sg:phone":"+61 3 5244 3349",
    "sg:postcode":"3216",
    "sg:province":"VIC",
    "sg:tags":[
        "medical",
        "practitioner"
    ],
    "wof:name":"Lake Imaging",
    "wof:placetype":"venue"
},
  "geometry": {"coordinates":[144.34492492699999,-38.173374176],"type":"Point"}
}