{
  "type": "Feature",
  "properties": {
    "iso:country":"AU",
    "sg:address":"33 Welshpool Rd",
    "sg:city":"Welshpool",
    "sg:classifiers":[
        {
            "category":"Autos & Motor Vehicles",
            "subcategory":"Auto Supplies",
            "type":"Retail Goods"
        }
    ],
    "sg:phone":"+61 8 9361 3725",
    "sg:postcode":"6106",
    "sg:province":"WA",
    "sg:tags":[
        "tyre"
    ],
    "wof:name":"Welshpool Tyre Service",
    "wof:placetype":"venue"
},
  "geometry": {"coordinates":[115.917999268,-31.9940433502],"type":"Point"}
}