{
  "type": "Feature",
  "properties": {
    "addr:full":"167 Wickham St Ayr QLD 4807",
    "addr:housenumber":"167",
    "addr:postcode":"4807",
    "addr:street":"Wickham St",
    "iso:country":"AU",
    "sg:address":"167 Wickham St",
    "sg:city":"Ayr",
    "sg:classifiers":[
        {
            "category":"Building & Trades",
            "subcategory":"Construction",
            "type":"Services"
        }
    ],
    "sg:phone":"+61 7 4783 2886",
    "sg:postcode":"4807",
    "sg:province":"QLD",
    "sg:tags":[
        "contractor"
    ],
    "wof:name":"Aguirre A & L",
    "wof:placetype":"venue"
},
  "geometry": {"coordinates":[147.402542114,-19.5826301575],"type":"Point"}
}