{
  "type": "Feature",
  "properties": {
    "addr:full":"78 High St Woodend VIC 3442",
    "addr:housenumber":"78",
    "addr:postcode":"3442",
    "addr:street":"High St",
    "iso:country":"AU",
    "sg:address":"78 High St",
    "sg:city":"Woodend",
    "sg:classifiers":[
        {
            "category":"Restaurant",
            "type":"Food & Drink"
        }
    ],
    "sg:phone":"+61 3 5427 1600",
    "sg:postcode":"3442",
    "sg:province":"VIC",
    "wof:name":"Double Eight Restaurant",
    "wof:placetype":"venue"
},
  "geometry": {"coordinates":[144.52813720699999,-37.3554649353],"type":"Point"}
}