{
  "type": "Feature",
  "properties": {
    "addr:full":"Unit 1/ 86 Commonage Rd Dunsborough WA 6281",
    "addr:postcode":"6281",
    "addr:street":"86 Commonage Rd",
    "iso:country":"AU",
    "sg:address":"Unit 1/ 86 Commonage Rd",
    "sg:city":"Dunsborough",
    "sg:classifiers":[
        {
            "category":"Autos & Motor Vehicles",
            "subcategory":"Auto Supplies",
            "type":"Retail Goods"
        }
    ],
    "sg:phone":"+61 8 9759 1400",
    "sg:postcode":"6281",
    "sg:province":"WA",
    "sg:tags":[
        "tyre"
    ],
    "wof:name":"Tyres & More Dunsborough",
    "wof:placetype":"venue"
},
  "geometry": {"coordinates":[115.120262146,-33.6306762695],"type":"Point"}
}