{
  "type": "Feature",
  "properties": {
    "iso:country":"AU",
    "sg:address":"222 Albert St",
    "sg:city":"Sebastopol",
    "sg:classifiers":[
        {
            "category":"Autos & Motor Vehicles",
            "subcategory":"Auto Supplies",
            "type":"Retail Goods"
        }
    ],
    "sg:phone":"+61 3 5335 8405",
    "sg:postcode":"3356",
    "sg:province":"VIC",
    "sg:tags":[
        "camper-trailers",
        "caravan",
        "equipment"
    ],
    "wof:name":"On Your Behalf Warehouse",
    "wof:placetype":"venue"
},
  "geometry": {"coordinates":[143.84082,-37.600559],"type":"Point"}
}