{
  "type": "Feature",
  "properties": {
    "iso:country":"AU",
    "sg:address":"76 Railway Rd",
    "sg:city":"Blackburn",
    "sg:classifiers":[
        {
            "category":"Organizations",
            "subcategory":"Non-profit Organization",
            "type":"Services"
        }
    ],
    "sg:phone":"+61 3 9845 2721",
    "sg:postcode":"3130",
    "sg:province":"VIC",
    "sg:tags":[
        "support",
        "disability",
        "organisation"
    ],
    "wof:name":"MS Society of Victoria Community Shops",
    "wof:placetype":"venue"
},
  "geometry": {"coordinates":[145.15550231899999,-37.8189506531],"type":"Point"}
}