{
  "type": "Feature",
  "properties": {
    "iso:country":"AU",
    "sg:address":"403 Hume Hwy",
    "sg:city":"Picton",
    "sg:classifiers":[
        {
            "category":"Retail",
            "subcategory":"Auto Rental",
            "type":"Services"
        }
    ],
    "sg:phone":"+61 2 4677 1535",
    "sg:postcode":"2571",
    "sg:province":"NSW",
    "sg:tags":[
        "car",
        "hire",
        "minibus"
    ],
    "wof:name":"Ascot Ute Hire",
    "wof:placetype":"venue"
},
  "geometry": {"coordinates":[150.67175293,-34.2247924805],"type":"Point"}
}