{
  "type": "Feature",
  "properties": {
    "iso:country":"AU",
    "sg:address":"26 Laura St",
    "sg:city":"Nedlands",
    "sg:classifiers":[
        {
            "category":"Health Services",
            "subcategory":"Medical Lab",
            "type":"Services"
        }
    ],
    "sg:phone":"+61 8 9389 1022",
    "sg:postcode":"6009",
    "sg:province":"WA",
    "sg:tags":[
        "laboratory",
        "pathology"
    ],
    "wof:name":"Cutaneous Pathology",
    "wof:placetype":"venue"
},
  "geometry": {"coordinates":[115.812241,-31.975134],"type":"Point"}
}