{
  "type": "Feature",
  "properties": {
    "iso:country":"AU",
    "sg:address":"Melbourne Market, Market Box 49",
    "sg:city":"West Melbourne",
    "sg:classifiers":[
        {
            "category":"Home & Garden",
            "subcategory":"Kitchen Supply",
            "type":"Retail Goods"
        }
    ],
    "sg:phone":"+61 3 9689 5122",
    "sg:postcode":"3003",
    "sg:province":"VIC",
    "sg:tags":[
        "vegetable",
        "fruit",
        "grain",
        "exporter"
    ],
    "wof:name":"Holman Fresh Pty Ltd",
    "wof:placetype":"venue"
},
  "geometry": {"coordinates":[144.92155456500001,-37.8076972961],"type":"Point"}
}