{
  "type": "Feature",
  "properties": {
    "addr:full":"151 Grays Point Rd Grays Point NSW 2232",
    "addr:housenumber":"151",
    "addr:postcode":"2232",
    "addr:street":"Grays Point Rd",
    "iso:country":"AU",
    "sg:address":"151 Grays Point Rd",
    "sg:city":"Grays Point",
    "sg:classifiers":[
        {
            "category":"Education",
            "subcategory":"Special Training",
            "type":"Public Place"
        }
    ],
    "sg:phone":"+61 2 9531 6676",
    "sg:postcode":"2232",
    "sg:province":"NSW",
    "sg:tags":[
        "development"
    ],
    "wof:name":"Hospitality Clean Train",
    "wof:placetype":"venue"
},
  "geometry": {"coordinates":[151.076461792,-34.0581207275],"type":"Point"}
}