{
  "type": "Feature",
  "properties": {
    "addr:full":"19 Binnacle Rd Ocean Reef WA 6027",
    "addr:housenumber":"19",
    "addr:postcode":"6027",
    "addr:street":"Binnacle Rd",
    "iso:country":"AU",
    "sg:address":"19 Binnacle Rd",
    "sg:city":"Ocean Reef",
    "sg:classifiers":[
        {
            "category":"Professional",
            "subcategory":"Art Services",
            "type":"Services"
        }
    ],
    "sg:phone":"+61 8 9307 4180",
    "sg:postcode":"6027",
    "sg:province":"WA",
    "sg:tags":[
        "arranger",
        "music",
        "composer"
    ],
    "wof:name":"Notable Productions",
    "wof:placetype":"venue"
},
  "geometry": {"coordinates":[115.747253418,-31.7650413513],"type":"Point"}
}