{
  "type": "Feature",
  "properties": {
    "addr:full":"24 Drovers Pl Pakenham VIC 3810",
    "addr:housenumber":"24",
    "addr:postcode":"3810",
    "addr:street":"Drovers Pl",
    "iso:country":"AU",
    "sg:address":"24 Drovers Pl",
    "sg:city":"Pakenham",
    "sg:classifiers":[
        {
            "category":"Utilities",
            "subcategory":"Refuse",
            "type":"Services"
        }
    ],
    "sg:phone":"+61 3 5941 4418",
    "sg:postcode":"3810",
    "sg:province":"VIC",
    "sg:tags":[
        "remover",
        "rubbish"
    ],
    "wof:name":"Pakenham Transfer Station",
    "wof:placetype":"venue"
},
  "geometry": {"coordinates":[145.498947144,-38.0980949402],"type":"Point"}
}