{
  "type": "Feature",
  "properties": {
    "iso:country":"AU",
    "sg:address":"6 Padua Crt",
    "sg:city":"Vermont",
    "sg:classifiers":[
        {
            "category":"Professional",
            "subcategory":"Art Services",
            "type":"Services"
        }
    ],
    "sg:phone":"+61 3 9873 8883",
    "sg:postcode":"3133",
    "sg:province":"VIC",
    "sg:tags":[
        "interior",
        "designer"
    ],
    "wof:name":"Globalhaus",
    "wof:placetype":"venue"
},
  "geometry": {"coordinates":[145.20817565900001,-37.8412590027],"type":"Point"}
}