{
  "type": "Feature",
  "properties": {
    "iso:country":"AU",
    "sg:address":"2 270 Rocky Point Rd",
    "sg:city":"Ramsgate",
    "sg:classifiers":[
        {
            "category":"Health Services",
            "subcategory":"Doctor",
            "type":"Services"
        }
    ],
    "sg:phone":"+61 2 9529 6929",
    "sg:postcode":"2217",
    "sg:province":"NSW",
    "sg:tags":[
        "medical",
        "practitioner"
    ],
    "wof:name":"Maybir R DR",
    "wof:placetype":"venue"
},
  "geometry": {"coordinates":[151.13670300000001,-33.98291],"type":"Point"}
}