{
  "type": "Feature",
  "properties": {
    "addr:full":"80 Church St Hurlstone Park NSW 2193",
    "addr:housenumber":"80",
    "addr:postcode":"2193",
    "addr:street":"Church St",
    "iso:country":"AU",
    "sg:address":"80 Church St",
    "sg:city":"Hurlstone Park",
    "sg:classifiers":[
        {
            "category":"Utilities",
            "subcategory":"Refuse",
            "type":"Services"
        }
    ],
    "sg:phone":"+61 408 419 485",
    "sg:postcode":"2193",
    "sg:province":"NSW",
    "sg:tags":[
        "remover",
        "rubbish"
    ],
    "wof:name":"Waynes Waste",
    "wof:placetype":"venue"
},
  "geometry": {"coordinates":[151.12231399999999,-33.912231],"type":"Point"}
}