{
  "type": "Feature",
  "properties": {
    "iso:country":"AU",
    "sg:address":"6a Elboden St",
    "sg:city":"South Hobart",
    "sg:classifiers":[
        {
            "category":"Professional",
            "subcategory":"Business Services",
            "type":"Services"
        }
    ],
    "sg:phone":"+61 419 583 048",
    "sg:postcode":"7004",
    "sg:province":"TAS",
    "sg:tags":[
        "drafting"
    ],
    "wof:name":"Parker Design Nominees Pty Ltd",
    "wof:placetype":"venue"
},
  "geometry": {"coordinates":[147.31695556599999,-42.8945426941],"type":"Point"}
}