{
  "type": "Feature",
  "properties": {
    "iso:country":"AU",
    "sg:address":"115 Neil St",
    "sg:city":"Toowoomba",
    "sg:classifiers":[
        {
            "category":"Retail",
            "subcategory":"Auto Repair",
            "type":"Services"
        }
    ],
    "sg:phone":"+61 7 4632 4690",
    "sg:postcode":"4350",
    "sg:province":"QLD",
    "sg:tags":[
        "beater",
        "painter",
        "panel"
    ],
    "wof:name":"Ryan's Smash Repairs",
    "wof:placetype":"venue"
},
  "geometry": {"coordinates":[151.95414700000001,-27.568319],"type":"Point"}
}