{
  "type": "Feature",
  "properties": {
    "iso:country":"AU",
    "sg:address":"Gladstone St",
    "sg:city":"Kogarah",
    "sg:classifiers":[
        {
            "category":"Education",
            "subcategory":"Dance Studio",
            "type":"Public Place"
        }
    ],
    "sg:phone":"+61 2 9587 0529",
    "sg:postcode":"2217",
    "sg:province":"NSW",
    "sg:tags":[
        "instruction",
        "language"
    ],
    "wof:name":"Kogarah Intensive English Centre",
    "wof:placetype":"venue"
},
  "geometry": {"coordinates":[151.13705400000001,-33.963684],"type":"Point"}
}