{
  "type": "Feature",
  "properties": {
    "addr:full":"223 Barnard St Bendigo VIC 3550",
    "addr:housenumber":"223",
    "addr:postcode":"3550",
    "addr:street":"Barnard St",
    "iso:country":"AU",
    "sg:address":"223 Barnard St",
    "sg:city":"Bendigo",
    "sg:classifiers":[
        {
            "category":"Communications",
            "subcategory":"Film & Video Production",
            "type":"Services"
        }
    ],
    "sg:phone":"+61 438 436 199",
    "sg:postcode":"3550",
    "sg:province":"VIC",
    "sg:tags":[
        "television",
        "system",
        "circuit",
        "closed"
    ],
    "wof:name":"Bertuch Ray",
    "wof:placetype":"venue"
},
  "geometry": {"coordinates":[144.272903442,-36.7560119629],"type":"Point"}
}