{
  "type": "Feature",
  "properties": {
    "addr:full":"2/ 2 Hillend Rd Doonside NSW 2767",
    "addr:housenumber":"/ 2",
    "addr:postcode":"2767",
    "addr:street":"Hillend Rd",
    "iso:country":"AU",
    "sg:address":"2/ 2 Hillend Rd",
    "sg:city":"Doonside",
    "sg:classifiers":[
        {
            "category":"Real Estate",
            "subcategory":"Real Estate Agent",
            "type":"Services"
        }
    ],
    "sg:phone":"+61 2 9676 5000",
    "sg:postcode":"2767",
    "sg:province":"NSW",
    "wof:name":"Century 21 Fe Hayward Realty",
    "wof:placetype":"venue"
},
  "geometry": {"coordinates":[150.869308472,-33.7633705139],"type":"Point"}
}