{
  "type": "Feature",
  "properties": {
    "addr:full":"126 Belford St Broadmeadow NSW 2292",
    "addr:housenumber":"126",
    "addr:postcode":"2292",
    "addr:street":"Belford St",
    "iso:country":"AU",
    "sg:address":"126 Belford St",
    "sg:city":"Broadmeadow",
    "sg:classifiers":[
        {
            "category":"Social Services",
            "subcategory":"Retirement Home",
            "type":"Services"
        }
    ],
    "sg:phone":"+61 2 4940 8882",
    "sg:postcode":"2292",
    "sg:province":"NSW",
    "sg:tags":[
        "environmental",
        "consultant",
        "pollution"
    ],
    "wof:name":"WBM Oceanics Australia",
    "wof:placetype":"venue"
},
  "geometry": {"coordinates":[151.73736572300001,-32.9240226746],"type":"Point"}
}