{
  "type": "Feature",
  "properties": {
    "iso:country":"AU",
    "sg:address":"158/A Canterbury Rd",
    "sg:city":"Bayswater",
    "sg:classifiers":[
        {
            "category":"Professional",
            "subcategory":"Engineering",
            "type":"Services"
        }
    ],
    "sg:phone":"+61 3 9720 9920",
    "sg:postcode":"3153",
    "sg:province":"VIC",
    "sg:tags":[
        "engineer"
    ],
    "wof:name":"Allsteel International Trading p/l",
    "wof:placetype":"venue"
},
  "geometry": {"coordinates":[145.267944336,-37.8326950073],"type":"Point"}
}