{
  "type": "Feature",
  "properties": {
    "addr:full":"84 North Oatlands Rd Yarrambat VIC 3091",
    "addr:housenumber":"84",
    "addr:postcode":"3091",
    "addr:street":"North Oatlands Rd",
    "iso:country":"AU",
    "sg:address":"84 North Oatlands Rd",
    "sg:city":"Yarrambat",
    "sg:classifiers":[
        {
            "category":"Building & Trades",
            "subcategory":"Construction",
            "type":"Services"
        }
    ],
    "sg:phone":"+61 417 528 517",
    "sg:postcode":"3091",
    "sg:province":"VIC",
    "sg:tags":[
        "contractor"
    ],
    "wof:name":"Combara Constructions",
    "wof:placetype":"venue"
},
  "geometry": {"coordinates":[145.12254333499999,-37.6417617798],"type":"Point"}
}