{
  "type": "Feature",
  "properties": {
    "addr:full":"Shp 8/ 9 Elizabeth Ave Clontarf QLD 4019",
    "addr:housenumber":"/ 9",
    "addr:postcode":"4019",
    "addr:street":"Elizabeth Ave",
    "iso:country":"AU",
    "sg:address":"Shp 8/ 9 Elizabeth Ave",
    "sg:city":"Clontarf",
    "sg:classifiers":[
        {
            "category":"Personal",
            "subcategory":"Beauty Salon",
            "type":"Services"
        }
    ],
    "sg:phone":"+61 7 3283 1722",
    "sg:postcode":"4019",
    "sg:province":"QLD",
    "sg:tags":[
        "hairdresser"
    ],
    "wof:name":"Bio Point Nail Hair & Beauty",
    "wof:placetype":"venue"
},
  "geometry": {"coordinates":[153.079833984,-27.2613754272],"type":"Point"}
}