{
  "type": "Feature",
  "properties": {
    "iso:country":"AU",
    "sg:address":"Orange Rd",
    "sg:city":"Parkes",
    "sg:classifiers":[
        {
            "category":"Utilities",
            "subcategory":"Electric",
            "type":"Services"
        }
    ],
    "sg:phone":"+61 2 6862 3710",
    "sg:postcode":"2870",
    "sg:province":"NSW",
    "sg:tags":[
        "electrical",
        "contractor"
    ],
    "wof:name":"Barry Allen Electrical",
    "wof:placetype":"venue"
},
  "geometry": {"coordinates":[148.191101,-33.142834],"type":"Point"}
}