{
  "type": "Feature",
  "properties": {
    "iso:country":"AU",
    "sg:address":"37 Laycock St",
    "sg:city":"Cranebrook",
    "sg:classifiers":[
        {
            "category":"Health Services",
            "subcategory":"Dentist",
            "type":"Services"
        }
    ],
    "sg:phone":"+61 2 4729 0940",
    "sg:postcode":"2749",
    "sg:province":"NSW",
    "wof:name":"Tomkins Glen A DR",
    "wof:placetype":"venue"
},
  "geometry": {"coordinates":[150.70860290499999,-33.7194137573],"type":"Point"}
}