{
  "type": "Feature",
  "properties": {
    "addr:full":"Clarence St Bellerive TAS 7018",
    "addr:postcode":"7018",
    "addr:street":"Clarence St",
    "iso:country":"AU",
    "sg:address":"Clarence St",
    "sg:city":"Bellerive",
    "sg:classifiers":[
        {
            "category":"Retail",
            "subcategory":"Funeral Services",
            "type":"Services"
        }
    ],
    "sg:phone":"+61 3 6244 8988",
    "sg:postcode":"7018",
    "sg:province":"TAS",
    "sg:tags":[
        "director"
    ],
    "wof:name":"Eastern Shore Funerals",
    "wof:placetype":"venue"
},
  "geometry": {"coordinates":[147.37240600600001,-42.8749656677],"type":"Point"}
}