{
  "type": "Feature",
  "properties": {
    "addr:full":"269 Princes Hwy Corrimal NSW 2518",
    "addr:housenumber":"269",
    "addr:postcode":"2518",
    "addr:street":"Princes Hwy",
    "iso:country":"AU",
    "sg:address":"269 Princes Hwy",
    "sg:city":"Corrimal",
    "sg:classifiers":[
        {
            "category":"Autos & Motor Vehicles",
            "subcategory":"Fuel & Gas Station",
            "type":"Retail Goods"
        }
    ],
    "sg:phone":"+61 2 4285 2192",
    "sg:postcode":"2518",
    "sg:province":"NSW",
    "wof:name":"Shell Select Corrimal",
    "wof:placetype":"venue"
},
  "geometry": {"coordinates":[150.896637,-34.373257],"type":"Point"}
}