{
  "type": "Feature",
  "properties": {
    "iso:country":"AU",
    "sg:address":"PO Box 3898",
    "sg:city":"Palmerston",
    "sg:classifiers":[
        {
            "category":"Real Estate",
            "subcategory":"Real Estate Agent",
            "type":"Services"
        }
    ],
    "sg:phone":"+61 8 8932 2233",
    "sg:postcode":"0831",
    "sg:province":"NT",
    "wof:name":"Sterling Realty",
    "wof:placetype":"venue"
},
  "geometry": {"coordinates":[130.983215,-12.48065],"type":"Point"}
}