{
  "type": "Feature",
  "properties": {
    "addr:full":"PO Box 41899 Casuarina NT 0811",
    "addr:postcode":"nt 0811",
    "iso:country":"AU",
    "sg:address":"PO Box 41899",
    "sg:city":"Casuarina",
    "sg:classifiers":[
        {
            "category":"Building & Trades",
            "subcategory":"Cleaning & Sanitation",
            "type":"Services"
        }
    ],
    "sg:phone":"+61 418 895 243",
    "sg:postcode":"0811",
    "sg:province":"NT",
    "sg:tags":[
        "industrial",
        "commercial",
        "contractor"
    ],
    "wof:name":"Commercial & General Cleaning",
    "wof:placetype":"venue"
},
  "geometry": {"coordinates":[130.858886719,-12.3764762878],"type":"Point"}
}