{
  "type": "Feature",
  "properties": {
    "iso:country":"AU",
    "sg:address":"Shop 29",
    "sg:city":", Lake Macquarie Fair Mt Hutton",
    "sg:classifiers":[
        {
            "category":"Shopping",
            "subcategory":"Clothing, Apparel, & Fashions",
            "type":"Retail Goods"
        }
    ],
    "sg:phone":"+61 2 4948 0788",
    "sg:postcode":"2290",
    "sg:province":"NSW",
    "sg:tags":[
        "lady",
        "wear"
    ],
    "wof:name":"Petronella Fashions",
    "wof:placetype":"venue"
},
  "geometry": {"coordinates":[151.68287658700001,-32.9921569824],"type":"Point"}
}