{
  "type": "Feature",
  "properties": {
    "iso:country":"AU",
    "sg:address":"23- 25 Wentworth St",
    "sg:city":"Greenacre",
    "sg:classifiers":[
        {
            "category":"Home & Garden",
            "subcategory":"Building Materials",
            "type":"Retail Goods"
        }
    ],
    "sg:phone":"+61 2 9642 4745",
    "sg:postcode":"2190",
    "sg:province":"NSW",
    "sg:tags":[
        "fire",
        "resistant",
        "supply"
    ],
    "wof:name":"Fazzini L & A Manufacturing Pty Ltd",
    "wof:placetype":"venue"
},
  "geometry": {"coordinates":[151.06878699999999,-33.898365],"type":"Point"}
}