{
  "type": "Feature",
  "properties": {
    "addr:full":"90-92 Audley St Narrandera NSW 2700",
    "addr:housenumber":"90-92",
    "addr:postcode":"2700",
    "addr:street":"Audley St",
    "iso:country":"AU",
    "sg:address":"90-92 Audley St",
    "sg:city":"Narrandera",
    "sg:classifiers":[
        {
            "category":"Wholesale",
            "subcategory":"Stationery",
            "type":"Manufacturing & Wholesale Goods"
        }
    ],
    "sg:phone":"+61 2 6959 3611",
    "sg:postcode":"2700",
    "sg:province":"NSW",
    "sg:tags":[
        "mfrg"
    ],
    "wof:name":"Process Printers",
    "wof:placetype":"venue"
},
  "geometry": {"coordinates":[146.552642822,-34.7482681274],"type":"Point"}
}