{
  "type": "Feature",
  "properties": {
    "addr:full":"9/ 13 Malvern St Bayswater VIC 3153",
    "addr:housenumber":"/ 13",
    "addr:postcode":"3153",
    "addr:street":"Malvern St",
    "iso:country":"AU",
    "sg:address":"9/ 13 Malvern St",
    "sg:city":"Bayswater",
    "sg:classifiers":[
        {
            "category":"Landmark",
            "subcategory":"Scenic View",
            "type":"Public Place"
        }
    ],
    "sg:phone":"+61 3 9738 1422",
    "sg:postcode":"3153",
    "sg:province":"VIC",
    "sg:tags":[
        "staircase",
        "handrail"
    ],
    "wof:name":"Commercial Metal Products",
    "wof:placetype":"venue"
},
  "geometry": {"coordinates":[145.27171325699999,-37.8426170349],"type":"Point"}
}