{
  "type": "Feature",
  "properties": {
    "addr:full":"PO Box 1474+ Thuringowa Central QLD 4817",
    "addr:postcode":"4817",
    "iso:country":"AU",
    "sg:address":"PO Box 1474+",
    "sg:city":"Thuringowa Central",
    "sg:classifiers":[
        {
            "category":"Shopping",
            "subcategory":"Computers & Home Electronics",
            "type":"Retail Goods"
        }
    ],
    "sg:phone":"+61 7 4723 6346",
    "sg:postcode":"4817",
    "sg:province":"QLD",
    "sg:tags":[
        "hire",
        "video",
        "game"
    ],
    "wof:name":"Gamers Loft",
    "wof:placetype":"venue"
},
  "geometry": {"coordinates":[146.723907,-19.31901],"type":"Point"}
}