{
  "type": "Feature",
  "properties": {
    "iso:country":"AU",
    "sg:address":"356 White Rock Rd",
    "sg:city":"Bathurst",
    "sg:classifiers":[
        {
            "category":"Home & Garden",
            "subcategory":"Building Materials",
            "type":"Retail Goods"
        }
    ],
    "sg:phone":"+61 412 449 209",
    "sg:postcode":"2795",
    "sg:province":"NSW",
    "sg:tags":[
        "retaining",
        "wall"
    ],
    "wof:name":"Nu-Scape Landscapes",
    "wof:placetype":"venue"
},
  "geometry": {"coordinates":[149.61607360799999,-33.4613761902],"type":"Point"}
}