{
  "type": "Feature",
  "properties": {
    "addr:full":"U4/ 226 Star St Carlisle WA 6101",
    "addr:housenumber":"226",
    "addr:postcode":"6101",
    "addr:street":"U4 /;Star St",
    "iso:country":"AU",
    "sg:address":"U4/ 226 Star St",
    "sg:city":"Carlisle",
    "sg:classifiers":[
        {
            "category":"Shopping",
            "subcategory":"Pets & Pet Supplies",
            "type":"Retail Goods"
        }
    ],
    "sg:phone":"+61 8 9361 9344",
    "sg:postcode":"6101",
    "sg:province":"WA",
    "sg:tags":[
        "shop",
        "supplier"
    ],
    "wof:name":"Companions Choice Products",
    "wof:placetype":"venue"
},
  "geometry": {"coordinates":[115.921836853,-31.9808959961],"type":"Point"}
}