{
  "type": "Feature",
  "properties": {
    "addr:full":"Scoresby Rd Knoxfield VIC 3180",
    "addr:postcode":"3180",
    "addr:street":"Scoresby Rd",
    "iso:country":"AU",
    "sg:address":"Scoresby Rd",
    "sg:city":"Knoxfield",
    "sg:classifiers":[
        {
            "category":"Education",
            "subcategory":"School",
            "type":"Public Place"
        }
    ],
    "sg:phone":"+61 3 9758 5022",
    "sg:postcode":"3180",
    "sg:province":"VIC",
    "sg:tags":[
        "state",
        "except",
        "nsw"
    ],
    "wof:name":"Fairhills High School",
    "wof:placetype":"venue"
},
  "geometry": {"coordinates":[145.257614136,-37.8860244751],"type":"Point"}
}