{
  "type": "Feature",
  "properties": {
    "addr:full":"Level 2/ 1 Little Collins St Melbourne VIC 3000",
    "addr:housenumber":"/ 1",
    "addr:postcode":"3000",
    "addr:street":"Little Collins St",
    "iso:country":"AU",
    "sg:address":"Level 2/ 1 Little Collins St",
    "sg:city":"Melbourne",
    "sg:classifiers":[
        {
            "category":"Real Estate",
            "subcategory":"Real Estate Services",
            "type":"Services"
        }
    ],
    "sg:phone":"+61 3 9009 8181",
    "sg:postcode":"3000",
    "sg:province":"VIC",
    "sg:tags":[
        "listing"
    ],
    "wof:name":"Corporate Real Estate Advisory",
    "wof:placetype":"venue"
},
  "geometry": {"coordinates":[144.97343444800001,-37.8124809265],"type":"Point"}
}