{
  "type": "Feature",
  "properties": {
    "iso:country":"AU",
    "sg:address":"7 Ironbark St",
    "sg:city":"Temora",
    "sg:classifiers":[
        {
            "category":"Retail",
            "subcategory":"Auto Repair",
            "type":"Services"
        }
    ],
    "sg:phone":"+61 2 6978 1125",
    "sg:postcode":"2666",
    "sg:province":"NSW",
    "sg:tags":[
        "bus",
        "truck"
    ],
    "wof:name":"Temora Trailer & Truck Sales",
    "wof:placetype":"venue"
},
  "geometry": {"coordinates":[147.54983520499999,-34.4476852417],"type":"Point"}
}