{
  "type": "Feature",
  "properties": {
    "addr:full":"30 Calala Drv Strathpine QLD 4500",
    "addr:housenumber":"30",
    "addr:postcode":"4500",
    "addr:street":"Calala Drv",
    "iso:country":"AU",
    "sg:address":"30 Calala Drv",
    "sg:city":"Strathpine",
    "sg:classifiers":[
        {
            "category":"Home & Garden",
            "subcategory":"Carpets & Floor Coverings",
            "type":"Retail Goods"
        }
    ],
    "sg:phone":"+61 411 373 330",
    "sg:postcode":"4500",
    "sg:province":"QLD",
    "sg:tags":[
        "tile",
        "wall",
        "layer"
    ],
    "wof:name":"All Tiling Service",
    "wof:placetype":"venue"
},
  "geometry": {"coordinates":[152.96751403799999,-27.3033599854],"type":"Point"}
}