{
  "type": "Feature",
  "properties": {
    "iso:country":"AU",
    "sg:address":"493 Beach Rd",
    "sg:city":"Duncraig",
    "sg:classifiers":[
        {
            "category":"Retail",
            "subcategory":"Event Space",
            "type":"Services"
        }
    ],
    "sg:phone":"+61 8 9447 7400",
    "sg:postcode":"6023",
    "sg:province":"WA",
    "sg:tags":[
        "venue",
        "reception",
        "wedding"
    ],
    "wof:name":"The Carine",
    "wof:placetype":"venue"
},
  "geometry": {"coordinates":[115.788009644,-31.8456459045],"type":"Point"}
}