{
  "type": "Feature",
  "properties": {
    "addr:full":"13 Winbourne Rd Brookvale NSW 2100",
    "addr:housenumber":"13",
    "addr:postcode":"2100",
    "addr:street":"Winbourne Rd",
    "iso:country":"AU",
    "sg:address":"13 Winbourne Rd",
    "sg:city":"Brookvale",
    "sg:classifiers":[
        {
            "category":"Shopping",
            "subcategory":"Optical Goods",
            "type":"Retail Goods"
        }
    ],
    "sg:phone":"+61 2 9938 3244",
    "sg:postcode":"2100",
    "sg:province":"NSW",
    "sg:tags":[
        "supply"
    ],
    "wof:name":"Tasco Binoculars",
    "wof:placetype":"venue"
},
  "geometry": {"coordinates":[151.278106689,-33.7628288269],"type":"Point"}
}