{
  "type": "Feature",
  "properties": {
    "addr:full":"2B, 20- 22 Fleming St Aitkenvale QLD 4814",
    "addr:housenumber":"2b;22",
    "addr:postcode":"4814",
    "addr:street":"20;Fleming St",
    "iso:country":"AU",
    "sg:address":"2B, 20- 22 Fleming St",
    "sg:city":"Aitkenvale",
    "sg:classifiers":[
        {
            "category":"Home & Garden",
            "subcategory":"Garden Supply",
            "type":"Retail Goods"
        }
    ],
    "sg:phone":"+61 7 4728 3957",
    "sg:postcode":"4814",
    "sg:province":"QLD",
    "sg:tags":[
        "equipment",
        "hydroponics"
    ],
    "wof:name":"NTH QLD Hydroponic Supplies",
    "wof:placetype":"venue"
},
  "geometry": {"coordinates":[146.76942399999999,-19.293003],"type":"Point"}
}