{
  "type": "Feature",
  "properties": {
    "addr:full":"2/ 6 Queens Ave McMahons Point NSW 2060",
    "addr:housenumber":"/ 6",
    "addr:postcode":"2060",
    "addr:street":"Queens Ave",
    "iso:country":"AU",
    "sg:address":"2/ 6 Queens Ave",
    "sg:city":"McMahons Point",
    "sg:classifiers":[
        {
            "category":"Organizations",
            "subcategory":"Professional Association",
            "type":"Services"
        }
    ],
    "sg:phone":"+61 2 9929 3236",
    "sg:postcode":"2060",
    "sg:province":"NSW",
    "sg:tags":[
        "web",
        "internet"
    ],
    "wof:name":"Abfab Web Design",
    "wof:placetype":"venue"
},
  "geometry": {"coordinates":[151.202835083,-33.8450889587],"type":"Point"}
}