{
  "type": "Feature",
  "properties": {
    "addr:full":"4/ 6 Graham Rd Clayton South VIC 3169",
    "addr:housenumber":"/ 6",
    "addr:postcode":"3169",
    "addr:street":"Graham Rd",
    "iso:country":"AU",
    "sg:address":"4/ 6 Graham Rd",
    "sg:city":"Clayton South",
    "sg:classifiers":[
        {
            "category":"Wholesale",
            "subcategory":"Auto Parts",
            "type":"Manufacturing & Wholesale Goods"
        }
    ],
    "sg:phone":"+61 3 9558 5722",
    "sg:postcode":"3169",
    "sg:province":"VIC",
    "sg:tags":[
        "recyclers"
    ],
    "wof:name":"Suba Bits",
    "wof:placetype":"venue"
},
  "geometry": {"coordinates":[145.13424682600001,-37.9524841309],"type":"Point"}
}