{
  "type": "Feature",
  "properties": {
    "addr:full":"615 Darling St Rozelle NSW 2039",
    "addr:housenumber":"615",
    "addr:postcode":"2039",
    "addr:street":"Darling St",
    "iso:country":"AU",
    "sg:address":"615 Darling St",
    "sg:city":"Rozelle",
    "sg:classifiers":[
        {
            "category":"Health Services",
            "subcategory":"Chiropractor",
            "type":"Services"
        }
    ],
    "sg:phone":"+61 2 9818 8517",
    "sg:postcode":"2039",
    "sg:province":"NSW",
    "wof:name":"Goodwin Mylene",
    "wof:placetype":"venue"
},
  "geometry": {"coordinates":[151.17129516599999,-33.8614311218],"type":"Point"}
}