{
  "type": "Feature",
  "properties": {
    "addr:full":"21 Vicary St Triabunna TAS 7190",
    "addr:housenumber":"21",
    "addr:postcode":"7190",
    "addr:street":"Vicary St",
    "iso:country":"AU",
    "sg:address":"21 Vicary St",
    "sg:city":"Triabunna",
    "sg:classifiers":[
        {
            "category":"Wholesale",
            "subcategory":"Hardware",
            "type":"Manufacturing & Wholesale Goods"
        }
    ],
    "sg:phone":"+61 3 6257 3117",
    "sg:postcode":"7190",
    "sg:province":"TAS",
    "wof:name":"East Coast Hardware",
    "wof:placetype":"venue"
},
  "geometry": {"coordinates":[147.91423,-42.507755],"type":"Point"}
}