{
  "type": "Feature",
  "properties": {
    "iso:country":"AU",
    "sg:address":"3/ 100 Campbell St",
    "sg:city":"Bowen Hills",
    "sg:classifiers":[
        {
            "category":"Real Estate",
            "subcategory":"Real Estate Services",
            "type":"Services"
        }
    ],
    "sg:phone":"+61 7 3257 4747",
    "sg:postcode":"4006",
    "sg:province":"QLD",
    "sg:tags":[
        "valuer"
    ],
    "wof:name":"Acval Eccleston & Fraser",
    "wof:placetype":"venue"
},
  "geometry": {"coordinates":[153.03204345699999,-27.4467792511],"type":"Point"}
}