{
  "type": "Feature",
  "properties": {
    "addr:full":"85 Pacific Hwy Gosford West NSW 2250",
    "addr:housenumber":"85",
    "addr:postcode":"2250",
    "addr:street":"Pacific Hwy",
    "iso:country":"AU",
    "sg:address":"85 Pacific Hwy",
    "sg:city":"Gosford West",
    "sg:classifiers":[
        {
            "category":"Building & Trades",
            "subcategory":"Construction",
            "type":"Services"
        }
    ],
    "sg:phone":"+61 2 4324 3868",
    "sg:postcode":"2250",
    "sg:province":"NSW",
    "sg:tags":[
        "scaffolding"
    ],
    "wof:name":"Kennards Scaffold Hire",
    "wof:placetype":"venue"
},
  "geometry": {"coordinates":[151.317993164,-33.4271965027],"type":"Point"}
}