{
  "type": "Feature",
  "properties": {
    "addr:full":"175 Kendal St Cowra NSW 2794",
    "addr:housenumber":"175",
    "addr:postcode":"2794",
    "addr:street":"Kendal St",
    "iso:country":"AU",
    "sg:address":"175 Kendal St",
    "sg:city":"Cowra",
    "sg:classifiers":[
        {
            "category":"Retail",
            "subcategory":"Auto Repair",
            "type":"Services"
        }
    ],
    "sg:phone":"+61 2 6342 1800",
    "sg:postcode":"2794",
    "sg:province":"NSW",
    "sg:tags":[
        "repairer",
        "motor",
        "engineer"
    ],
    "wof:name":"Holden",
    "wof:placetype":"venue"
},
  "geometry": {"coordinates":[148.69776916500001,-33.8355636597],"type":"Point"}
}