{
  "type": "Feature",
  "properties": {
    "addr:full":"Lvl 1/ 214 Parramatta Rd Burwood NSW 2134",
    "addr:housenumber":"/ 214",
    "addr:postcode":"2134",
    "addr:street":"Parramatta Rd",
    "iso:country":"AU",
    "sg:address":"Lvl 1/ 214 Parramatta Rd",
    "sg:city":"Burwood",
    "sg:classifiers":[
        {
            "category":"Building & Trades",
            "subcategory":"Cleaning & Sanitation",
            "type":"Services"
        }
    ],
    "sg:phone":"+61 2 9745 3111",
    "sg:postcode":"2134",
    "sg:province":"NSW",
    "sg:tags":[
        "industrial",
        "commercial",
        "contractor"
    ],
    "wof:name":"Help Cleaning Agency",
    "wof:placetype":"venue"
},
  "geometry": {"coordinates":[151.110717773,-33.8697395325],"type":"Point"}
}