{
  "type": "Feature",
  "properties": {
    "addr:full":"Main Rd Basket Range SA 5138",
    "addr:postcode":"5138",
    "addr:street":"Main Rd",
    "iso:country":"AU",
    "sg:address":"Main Rd",
    "sg:city":"Basket Range",
    "sg:classifiers":[
        {
            "category":"Farming",
            "subcategory":"Berry Farm",
            "type":"Manufacturing & Wholesale Goods"
        }
    ],
    "sg:phone":"+61 8 8390 3437",
    "sg:postcode":"5138",
    "sg:province":"SA",
    "sg:tags":[
        "fruit",
        "grower"
    ],
    "wof:name":"Musolino Kevin V",
    "wof:placetype":"venue"
},
  "geometry": {"coordinates":[138.77491760300001,-34.9364509583],"type":"Point"}
}