{
  "type": "Feature",
  "properties": {
    "addr:full":"689 The Horsley Drv Smithfield NSW 2164",
    "addr:housenumber":"689",
    "addr:postcode":"2164",
    "addr:street":"The Horsley Drv",
    "iso:country":"AU",
    "sg:address":"689 The Horsley Drv",
    "sg:city":"Smithfield",
    "sg:classifiers":[
        {
            "category":"Personal",
            "subcategory":"Beauty Salon",
            "type":"Services"
        }
    ],
    "sg:phone":"+61 2 9725 3500",
    "sg:postcode":"2164",
    "sg:province":"NSW",
    "wof:name":"Beauty Elixir The",
    "wof:placetype":"venue"
},
  "geometry": {"coordinates":[150.93940734899999,-33.8531913757],"type":"Point"}
}