{
  "type": "Feature",
  "properties": {
    "iso:country":"AU",
    "sg:address":"Lot 1 Lynam Rd",
    "sg:city":"Kirwan",
    "sg:classifiers":[
        {
            "category":"Home & Garden",
            "subcategory":"Garden Supply",
            "type":"Retail Goods"
        }
    ],
    "sg:phone":"+61 417 752 788",
    "sg:postcode":"4817",
    "sg:province":"QLD",
    "sg:tags":[
        "turf",
        "lawn"
    ],
    "wof:name":"Big Buffalo Turf Farm The",
    "wof:placetype":"venue"
},
  "geometry": {"coordinates":[146.689484,-19.326305],"type":"Point"}
}