{
  "type": "Feature",
  "properties": {
    "iso:country":"AU",
    "sg:address":"118 Darebin Rd",
    "sg:city":"Thornbury",
    "sg:classifiers":[
        {
            "category":"Utilities",
            "subcategory":"Electric",
            "type":"Services"
        }
    ],
    "sg:phone":"+61 3 9480 2839",
    "sg:postcode":"3071",
    "sg:province":"VIC",
    "sg:tags":[
        "electrical",
        "contractor"
    ],
    "wof:name":"Thornbury Electrical Services",
    "wof:placetype":"venue"
},
  "geometry": {"coordinates":[145.00804138199999,-37.7642784119],"type":"Point"}
}