{
  "type": "Feature",
  "properties": {
    "addr:full":"51 Henson Rd Salisbury QLD 4107",
    "addr:housenumber":"51",
    "addr:postcode":"4107",
    "addr:street":"Henson Rd",
    "iso:country":"AU",
    "sg:address":"51 Henson Rd",
    "sg:city":"Salisbury",
    "sg:classifiers":[
        {
            "category":"Building & Trades",
            "subcategory":"Landscaping Services",
            "type":"Services"
        }
    ],
    "sg:phone":"+61 7 3277 2262",
    "sg:postcode":"4107",
    "sg:province":"QLD",
    "sg:tags":[
        "firebreak",
        "clearing",
        "land",
        "contractor"
    ],
    "wof:name":"Richmere Pty Ltd Slashing Contractors",
    "wof:placetype":"venue"
},
  "geometry": {"coordinates":[153.02459716800001,-27.5516662598],"type":"Point"}
}