{
  "type": "Feature",
  "properties": {
    "addr:full":"PO Box 53 Coburg VIC 3058",
    "addr:postcode":"3058",
    "iso:country":"AU",
    "sg:address":"PO Box 53",
    "sg:city":"Coburg",
    "sg:classifiers":[
        {
            "category":"Bars & Pubs",
            "subcategory":"Nightclub",
            "type":"Food & Drink"
        }
    ],
    "sg:phone":"+61 406 541 158",
    "sg:postcode":"3058",
    "sg:province":"VIC",
    "sg:tags":[
        "discotheque"
    ],
    "wof:name":"Prime Promotions Pty Ltd",
    "wof:placetype":"venue"
},
  "geometry": {"coordinates":[144.97096252399999,-37.745677948],"type":"Point"}
}