{
  "type": "Feature",
  "properties": {
    "iso:country":"AU",
    "sg:address":"49 Putnam Ave",
    "sg:city":"Bendigo",
    "sg:classifiers":[
        {
            "category":"Social Services",
            "subcategory":"Retirement Home",
            "type":"Services"
        }
    ],
    "sg:phone":"+61 3 5441 5241",
    "sg:postcode":"3554",
    "sg:province":"VIC",
    "sg:tags":[
        "environmental",
        "consultant",
        "pollution"
    ],
    "wof:name":"Landserv Pty Ltd",
    "wof:placetype":"venue"
},
  "geometry": {"coordinates":[144.31011962900001,-36.7638206482],"type":"Point"}
}