{
  "type": "Feature",
  "properties": {
    "addr:full":"73 Walker St Dandenong VIC 3175",
    "addr:housenumber":"73",
    "addr:postcode":"3175",
    "addr:street":"Walker St",
    "iso:country":"AU",
    "sg:address":"73 Walker St",
    "sg:city":"Dandenong",
    "sg:classifiers":[
        {
            "category":"Professional",
            "subcategory":"Management & Consulting",
            "type":"Services"
        }
    ],
    "sg:phone":"+61 3 9794 9133",
    "sg:postcode":"3175",
    "sg:province":"VIC",
    "sg:tags":[
        "consultant",
        "migration"
    ],
    "wof:name":"A & K Fazal Company",
    "wof:placetype":"venue"
},
  "geometry": {"coordinates":[145.21412658700001,-37.9879837036],"type":"Point"}
}