{
  "type": "Feature",
  "properties": {
    "iso:country":"AU",
    "sg:address":"Shop 6 Richmond Marketplace",
    "sg:city":"Richmond",
    "sg:classifiers":[
        {
            "category":"Fast Food",
            "type":"Food & Drink"
        }
    ],
    "sg:phone":"+61 2 4578 2388",
    "sg:postcode":"2753",
    "sg:province":"NSW",
    "sg:tags":[
        "away",
        "take"
    ],
    "wof:name":"Sandwich Tower",
    "wof:placetype":"venue"
},
  "geometry": {"coordinates":[150.79023742699999,-33.6085472107],"type":"Point"}
}