{
  "type": "Feature",
  "properties": {
    "addr:full":"Unit 4/ 10 Paisley Drv Lawnton QLD 4501",
    "addr:housenumber":"10",
    "addr:postcode":"4501",
    "addr:street":"Paisley Drv",
    "iso:country":"AU",
    "sg:address":"Unit 4/ 10 Paisley Drv",
    "sg:city":"Lawnton",
    "sg:classifiers":[
        {
            "category":"Wholesale",
            "subcategory":"Toys & Hobbies",
            "type":"Manufacturing & Wholesale Goods"
        }
    ],
    "sg:phone":"+61 7 3205 8099",
    "sg:postcode":"4501",
    "sg:province":"QLD",
    "wof:name":"Greig Novelties South Pty Ltd",
    "wof:placetype":"venue"
},
  "geometry": {"coordinates":[152.988204956,-27.2830200195],"type":"Point"}
}