{
  "type": "Feature",
  "properties": {
    "addr:full":"15 Folkstone Rd Glen Waverley VIC 3150",
    "addr:housenumber":"15",
    "addr:postcode":"3150",
    "addr:street":"Folkstone Rd",
    "iso:country":"AU",
    "sg:address":"15 Folkstone Rd",
    "sg:city":"Glen Waverley",
    "sg:classifiers":[
        {
            "category":"Utilities",
            "subcategory":"Electric",
            "type":"Services"
        }
    ],
    "sg:phone":"+61 3 9803 0193",
    "sg:postcode":"3150",
    "sg:province":"VIC",
    "sg:tags":[
        "electrical",
        "contractor"
    ],
    "wof:name":"Sekula Electrics",
    "wof:placetype":"venue"
},
  "geometry": {"coordinates":[145.152175903,-37.8607330322],"type":"Point"}
}