{
  "type": "Feature",
  "properties": {
    "addr:full":"48 Mann St Gosford NSW 2250",
    "addr:housenumber":"48",
    "addr:postcode":"2250",
    "addr:street":"Mann St",
    "iso:country":"AU",
    "sg:address":"48 Mann St",
    "sg:city":"Gosford",
    "sg:classifiers":[
        {
            "category":"Professional",
            "subcategory":"Business Services",
            "type":"Services"
        }
    ],
    "sg:phone":"+61 2 4323 9211",
    "sg:postcode":"2250",
    "sg:province":"NSW",
    "sg:tags":[
        "drafting"
    ],
    "wof:name":"CopyShop Gosford",
    "wof:placetype":"venue"
},
  "geometry": {"coordinates":[151.34135437,-33.4285240173],"type":"Point"}
}