{
  "type": "Feature",
  "properties": {
    "addr:full":"115 George St Bathurst NSW 2795",
    "addr:housenumber":"115",
    "addr:postcode":"2795",
    "addr:street":"George St",
    "iso:country":"AU",
    "sg:address":"115 George St",
    "sg:city":"Bathurst",
    "sg:classifiers":[
        {
            "category":"Health Services",
            "subcategory":"Doctor",
            "type":"Services"
        }
    ],
    "sg:phone":"+61 2 6332 5355",
    "sg:postcode":"2795",
    "sg:province":"NSW",
    "sg:tags":[
        "medical",
        "practitioner"
    ],
    "wof:name":"George Street Medical Practice",
    "wof:placetype":"venue"
},
  "geometry": {"coordinates":[149.57844543499999,-33.4166908264],"type":"Point"}
}