{
  "type": "Feature",
  "properties": {
    "iso:country":"AU",
    "sg:address":"153 Mckinnon Rd",
    "sg:city":"McKinnon",
    "sg:classifiers":[
        {
            "category":"Real Estate",
            "subcategory":"Real Estate Agent",
            "type":"Services"
        }
    ],
    "sg:phone":"+61 3 9576 7599",
    "sg:postcode":"3204",
    "sg:province":"VIC",
    "wof:name":"Century 21 Wilson Pride",
    "wof:placetype":"venue"
},
  "geometry": {"coordinates":[145.03727699999999,-37.910774],"type":"Point"}
}