{
  "type": "Feature",
  "properties": {
    "addr:full":"4 Bolton Rd Huskisson NSW 2540",
    "addr:housenumber":"4",
    "addr:postcode":"2540",
    "addr:street":"Bolton Rd",
    "iso:country":"AU",
    "sg:address":"4 Bolton Rd",
    "sg:city":"Huskisson",
    "sg:classifiers":[
        {
            "category":"Wholesale",
            "subcategory":"Metals & Minerals",
            "type":"Manufacturing & Wholesale Goods"
        }
    ],
    "sg:phone":"+61 2 4441 7277",
    "sg:postcode":"2540",
    "sg:province":"NSW",
    "sg:tags":[
        "steel",
        "stainless",
        "product",
        "equipment"
    ],
    "wof:name":"Huskisson Plywood Plus",
    "wof:placetype":"venue"
},
  "geometry": {"coordinates":[150.66070556599999,-35.0288963318],"type":"Point"}
}