{
  "type": "Feature",
  "properties": {
    "addr:full":"20 Hudson Rd Albion QLD 4010",
    "addr:housenumber":"20",
    "addr:postcode":"4010",
    "addr:street":"Hudson Rd",
    "iso:country":"AU",
    "sg:address":"20 Hudson Rd",
    "sg:city":"Albion",
    "sg:classifiers":[
        {
            "category":"Shopping",
            "subcategory":"Antiques",
            "type":"Retail Goods"
        }
    ],
    "sg:phone":"+61 408 069 883",
    "sg:postcode":"4010",
    "sg:province":"QLD",
    "wof:name":"Northside Antiques",
    "wof:placetype":"venue"
},
  "geometry": {"coordinates":[153.04098510700001,-27.4318733215],"type":"Point"}
}