{
  "type": "Feature",
  "properties": {
    "addr:full":"42 Brompton St Alexandra Hills QLD 4161",
    "addr:housenumber":"42",
    "addr:postcode":"4161",
    "addr:street":"Brompton St",
    "iso:country":"AU",
    "sg:address":"42 Brompton St",
    "sg:city":"Alexandra Hills",
    "sg:classifiers":[
        {
            "category":"Retail",
            "subcategory":"Auto Repair",
            "type":"Services"
        }
    ],
    "sg:phone":"+61 7 3824 4340",
    "sg:postcode":"4161",
    "sg:province":"QLD",
    "sg:tags":[
        "beater",
        "painter",
        "panel"
    ],
    "wof:name":"Spot On Smash & Mechanical Repairs",
    "wof:placetype":"venue"
},
  "geometry": {"coordinates":[153.21763610799999,-27.5335483551],"type":"Point"}
}