{
  "type": "Feature",
  "properties": {
    "iso:country":"AU",
    "sg:address":"98 Murphy St",
    "sg:city":"Wangaratta",
    "sg:classifiers":[
        {
            "category":"Banks & Credit Unions",
            "subcategory":"Bank",
            "type":"Services"
        }
    ],
    "sg:phone":"+61 3 5721 9499",
    "sg:postcode":"3676",
    "sg:province":"VIC",
    "wof:name":"Bendigo Bank",
    "wof:placetype":"venue"
},
  "geometry": {"coordinates":[146.326324,-36.355785],"type":"Point"}
}