{
  "type": "Feature",
  "properties": {
    "iso:country":"AU",
    "sg:address":"14-20 Balaclava Rd St",
    "sg:city":"Kilda East",
    "sg:classifiers":[
        {
            "category":"Education",
            "subcategory":"School",
            "type":"Public Place"
        }
    ],
    "sg:phone":"+61 3 9522 8227",
    "sg:postcode":"3183",
    "sg:province":"VIC",
    "sg:tags":[
        "girl"
    ],
    "wof:name":"Beth Rivkah Ladies College",
    "wof:placetype":"venue"
},
  "geometry": {"coordinates":[145.00198364299999,-37.8696784973],"type":"Point"}
}