{
  "type": "Feature",
  "properties": {
    "addr:full":"Mudgee Rd Capertee NSW 2846",
    "addr:postcode":"2846",
    "addr:street":"Mudgee Rd",
    "iso:country":"AU",
    "sg:address":"Mudgee Rd",
    "sg:city":"Capertee",
    "sg:classifiers":[
        {
            "category":"Autos & Motor Vehicles",
            "subcategory":"Fuel & Gas Station",
            "type":"Retail Goods"
        }
    ],
    "sg:phone":"+61 2 6359 0127",
    "sg:postcode":"2846",
    "sg:province":"NSW",
    "wof:name":"Shell Roadhouse",
    "wof:placetype":"venue"
},
  "geometry": {"coordinates":[149.97105400000001,-32.80759],"type":"Point"}
}