{
  "type": "Feature",
  "properties": {
    "addr:full":"Stockland Caloundra 47 Bowman Rd Caloundra QLD 4551",
    "addr:housenumber":"47",
    "addr:postcode":"4551",
    "addr:street":"Bowman Rd",
    "iso:country":"AU",
    "sg:address":"Stockland Caloundra 47 Bowman Rd",
    "sg:city":"Caloundra",
    "sg:classifiers":[
        {
            "category":"Organizations",
            "subcategory":"Membership Organization",
            "type":"Services"
        }
    ],
    "sg:phone":"+61 7 5491 2402",
    "sg:postcode":"4551",
    "sg:province":"QLD",
    "sg:tags":[
        "support",
        "health",
        "organisation"
    ],
    "wof:name":"Caloundra Amcal Pharmacy",
    "wof:placetype":"venue"
},
  "geometry": {"coordinates":[153.12965393100001,-26.80078125],"type":"Point"}
}