{
  "type": "Feature",
  "properties": {
    "addr:full":"Lvl 2, 72- 74 Auburn Pde Camberwell VIC 3124",
    "addr:housenumber":"72 74",
    "addr:postcode":"3124",
    "addr:street":"Auburn Pde",
    "iso:country":"AU",
    "sg:address":"Lvl 2, 72- 74 Auburn Pde",
    "sg:city":"Camberwell",
    "sg:classifiers":[
        {
            "category":"Professional",
            "subcategory":"Computer Services",
            "type":"Services"
        }
    ],
    "sg:phone":"+61 3 9882 2060",
    "sg:postcode":"3124",
    "sg:province":"VIC",
    "sg:tags":[
        "consultant",
        "system"
    ],
    "wof:name":"McRae I T Pty Ltd",
    "wof:placetype":"venue"
},
  "geometry": {"coordinates":[145.04185485799999,-37.8387451172],"type":"Point"}
}