{
  "type": "Feature",
  "properties": {
    "addr:full":"33 Claremont Ave Greenacre NSW 2190",
    "addr:housenumber":"33",
    "addr:postcode":"2190",
    "addr:street":"Claremont Ave",
    "iso:country":"AU",
    "sg:address":"33 Claremont Ave",
    "sg:city":"Greenacre",
    "sg:classifiers":[
        {
            "category":"Wholesale",
            "subcategory":"Auto Parts",
            "type":"Manufacturing & Wholesale Goods"
        }
    ],
    "sg:phone":"+61 2 9790 2983",
    "sg:postcode":"2190",
    "sg:province":"NSW",
    "sg:tags":[
        "recyclers"
    ],
    "wof:name":"AAA All For Car",
    "wof:placetype":"venue"
},
  "geometry": {"coordinates":[151.03890999999999,-33.900787],"type":"Point"}
}