{
  "type": "Feature",
  "properties": {
    "addr:full":"9 Janice Ave Smithfield NSW 2164",
    "addr:housenumber":"9",
    "addr:postcode":"2164",
    "addr:street":"Janice Ave",
    "iso:country":"AU",
    "sg:address":"9 Janice Ave",
    "sg:city":"Smithfield",
    "sg:classifiers":[
        {
            "category":"Professional",
            "subcategory":"Employment Agencies",
            "type":"Services"
        }
    ],
    "sg:phone":"+61 404 049 262",
    "sg:postcode":"2164",
    "sg:province":"NSW",
    "sg:tags":[
        "entertainer",
        "agent"
    ],
    "wof:name":"Summit Entertainment",
    "wof:placetype":"venue"
},
  "geometry": {"coordinates":[150.93658447300001,-33.8548049927],"type":"Point"}
}