{
  "type": "Feature",
  "properties": {
    "addr:full":"381 Woolooware Rd Cronulla NSW 2230",
    "addr:housenumber":"381",
    "addr:postcode":"2230",
    "addr:street":"Woolooware Rd",
    "iso:country":"AU",
    "sg:address":"381 Woolooware Rd",
    "sg:city":"Cronulla",
    "sg:classifiers":[
        {
            "category":"Building & Trades",
            "subcategory":"Construction",
            "type":"Services"
        }
    ],
    "sg:phone":"+61 2 9544 0355",
    "sg:postcode":"2230",
    "sg:province":"NSW",
    "sg:tags":[
        "industrial",
        "commercial",
        "air conditioning"
    ],
    "wof:name":"A Aairden Service",
    "wof:placetype":"venue"
},
  "geometry": {"coordinates":[151.137207031,-34.0663948059],"type":"Point"}
}