{
  "type": "Feature",
  "properties": {
    "iso:country":"AU",
    "sg:address":"PO Box 3486",
    "sg:city":"Narellan",
    "sg:classifiers":[
        {
            "category":"Building & Trades",
            "subcategory":"Cleaning & Sanitation",
            "type":"Services"
        }
    ],
    "sg:phone":"+61 412 273 546",
    "sg:postcode":"2567",
    "sg:province":"NSW",
    "sg:tags":[
        "window"
    ],
    "wof:name":"Bright & Shiny Windows",
    "wof:placetype":"venue"
},
  "geometry": {"coordinates":[150.73526000999999,-34.0400390625],"type":"Point"}
}