{
  "type": "Feature",
  "properties": {
    "iso:country":"AU",
    "sg:address":"Commercial St",
    "sg:city":"Mt Gambier",
    "sg:classifiers":[
        {
            "category":"Autos & Motor Vehicles",
            "subcategory":"Fuel & Gas Station",
            "type":"Retail Goods"
        }
    ],
    "sg:phone":"+61 8 8725 3285",
    "sg:postcode":"5290",
    "sg:province":"SA",
    "wof:name":"BP Australia Limited",
    "wof:placetype":"venue"
},
  "geometry": {"coordinates":[140.78329500000001,-37.826321],"type":"Point"}
}