{
  "type": "Feature",
  "properties": {
    "addr:full":"Shp2 East Ballina Shpng Centre Links Ave East Ballina NSW 2478",
    "addr:postcode":"2478",
    "addr:street":"Links Ave",
    "iso:country":"AU",
    "sg:address":"Shp2 East Ballina Shpng Centre Links Ave",
    "sg:city":"East Ballina",
    "sg:classifiers":[
        {
            "category":"Communications",
            "subcategory":"Film & Video Production",
            "type":"Services"
        }
    ],
    "sg:phone":"+61 2 6681 1131",
    "sg:postcode":"2478",
    "sg:province":"NSW",
    "sg:tags":[
        "dvd",
        "library"
    ],
    "wof:name":"East Ballina Video",
    "wof:placetype":"venue"
},
  "geometry": {"coordinates":[153.584838867,-28.8580570221],"type":"Point"}
}