{
  "type": "Feature",
  "properties": {
    "iso:country":"AU",
    "sg:address":"43 Ferguson St",
    "sg:city":"Canowindra",
    "sg:classifiers":[
        {
            "category":"Autos & Motor Vehicles",
            "subcategory":"Fuel & Gas Station",
            "type":"Retail Goods"
        }
    ],
    "sg:phone":"+61 2 6344 1020",
    "sg:postcode":"2804",
    "sg:province":"NSW",
    "wof:name":"Burn B R & K S",
    "wof:placetype":"venue"
},
  "geometry": {"coordinates":[148.66473388700001,-33.5620803833],"type":"Point"}
}