{
  "type": "Feature",
  "properties": {
    "addr:full":"21 Stephen St Bunbury WA 6230",
    "addr:housenumber":"21",
    "addr:postcode":"6230",
    "addr:street":"Stephen St",
    "iso:country":"AU",
    "sg:address":"21 Stephen St",
    "sg:city":"Bunbury",
    "sg:classifiers":[
        {
            "category":"Shopping",
            "subcategory":"Jewelry",
            "type":"Retail Goods"
        }
    ],
    "sg:phone":"+61 8 9721 1929",
    "sg:postcode":"6230",
    "sg:province":"WA",
    "sg:tags":[
        "jeweller"
    ],
    "wof:name":"Goldsmiths Jewellers",
    "wof:placetype":"venue"
},
  "geometry": {"coordinates":[115.63762699999999,-33.326294],"type":"Point"}
}