{
  "type": "Feature",
  "properties": {
    "addr:full":"4 Kitchener Rd Tecoma VIC 3160",
    "addr:housenumber":"4",
    "addr:postcode":"3160",
    "addr:street":"Kitchener Rd",
    "iso:country":"AU",
    "sg:address":"4 Kitchener Rd",
    "sg:city":"Tecoma",
    "sg:classifiers":[
        {
            "category":"Professional",
            "subcategory":"Business Services",
            "type":"Services"
        }
    ],
    "sg:phone":"+61 3 9754 3618",
    "sg:postcode":"3160",
    "sg:province":"VIC",
    "sg:tags":[
        "drafting"
    ],
    "wof:name":"Aatech Mechanical Drafting",
    "wof:placetype":"venue"
},
  "geometry": {"coordinates":[145.34916687,-37.9039039612],"type":"Point"}
}