{
  "type": "Feature",
  "properties": {
    "iso:country":"AU",
    "sg:address":"124 Whitehall St",
    "sg:city":"Footscray",
    "sg:classifiers":[
        {
            "category":"Food & Beverages",
            "subcategory":"Fruits & Vegetables",
            "type":"Retail Goods"
        }
    ],
    "sg:phone":"+61 3 9687 3339",
    "sg:postcode":"3011",
    "sg:province":"VIC",
    "sg:tags":[
        "greengrocer",
        "fruiterer"
    ],
    "wof:name":"Bonney Produce Pty Ltd",
    "wof:placetype":"venue"
},
  "geometry": {"coordinates":[144.90260314899999,-37.808216095],"type":"Point"}
}