{
  "type": "Feature",
  "properties": {
    "addr:full":"Unit 8 Forest Glen Shopng Cntr Mons Rd Forest Glen QLD 4556",
    "addr:postcode":"4556",
    "addr:street":"Mons Rd",
    "iso:country":"AU",
    "sg:address":"Unit 8 Forest Glen Shopng Cntr Mons Rd",
    "sg:city":"Forest Glen",
    "sg:classifiers":[
        {
            "category":"Retail",
            "subcategory":"Auto Repair",
            "type":"Services"
        }
    ],
    "sg:phone":"+61 7 5445 6553",
    "sg:postcode":"4556",
    "sg:province":"QLD",
    "sg:tags":[
        "repairer",
        "motor",
        "engineer"
    ],
    "wof:name":"Motor Sports Developments",
    "wof:placetype":"venue"
},
  "geometry": {"coordinates":[153.009963989,-26.6886234283],"type":"Point"}
}