{
  "type": "Feature",
  "properties": {
    "iso:country":"AU",
    "sg:address":"111 McEvoy St",
    "sg:city":"Alexandria",
    "sg:classifiers":[
        {
            "category":"Home & Garden",
            "subcategory":"Carpets & Floor Coverings",
            "type":"Retail Goods"
        }
    ],
    "sg:phone":"+61 2 9310 2913",
    "sg:postcode":"2015",
    "sg:province":"NSW",
    "sg:tags":[
        "tile",
        "wall",
        "layer"
    ],
    "wof:name":"Goldhick Pty Ltd",
    "wof:placetype":"venue"
},
  "geometry": {"coordinates":[151.19841003400001,-33.9020347595],"type":"Point"}
}