{
  "type": "Feature",
  "properties": {
    "addr:full":"Yarrawonga Hospital 33 Piper St Yarrawonga VIC 3730",
    "addr:housenumber":"33",
    "addr:postcode":"3730",
    "addr:street":"Piper St",
    "iso:country":"AU",
    "sg:address":"Yarrawonga Hospital 33 Piper St",
    "sg:city":"Yarrawonga",
    "sg:classifiers":[
        {
            "category":"Health Services",
            "subcategory":"Doctor",
            "type":"Services"
        }
    ],
    "sg:phone":"+61 3 5743 8163",
    "sg:postcode":"3730",
    "sg:province":"VIC",
    "sg:tags":[
        "medical",
        "practitioner"
    ],
    "wof:name":"Gribbles Pathology (Vic) Pty Ltd",
    "wof:placetype":"venue"
},
  "geometry": {"coordinates":[146.00686645499999,-36.0111579895],"type":"Point"}
}