{
  "type": "Feature",
  "properties": {
    "addr:full":"13 Juliana Drv Carrum Downs VIC 3201",
    "addr:housenumber":"13",
    "addr:postcode":"3201",
    "addr:street":"Juliana Drv",
    "iso:country":"AU",
    "sg:address":"13 Juliana Drv",
    "sg:city":"Carrum Downs",
    "sg:classifiers":[
        {
            "category":"Retail",
            "subcategory":"Repair Shop",
            "type":"Services"
        }
    ],
    "sg:phone":"+61 3 9786 7578",
    "sg:postcode":"3201",
    "sg:province":"VIC",
    "sg:tags":[
        "machine",
        "repairs",
        "part",
        "dryer",
        "washing"
    ],
    "wof:name":"J & N McLauglin Appliance Service",
    "wof:placetype":"venue"
},
  "geometry": {"coordinates":[145.184326,-38.10894],"type":"Point"}
}