{
  "type": "Feature",
  "properties": {
    "iso:country":"AU",
    "sg:address":"87 Newman St",
    "sg:city":"Wangaratta",
    "sg:classifiers":[
        {
            "category":"Professional",
            "subcategory":"Art Services",
            "type":"Services"
        }
    ],
    "sg:phone":"+61 409 963 948",
    "sg:postcode":"3677",
    "sg:province":"VIC",
    "sg:tags":[
        "decorator",
        "painter"
    ],
    "wof:name":"David Phillips Painting",
    "wof:placetype":"venue"
},
  "geometry": {"coordinates":[146.30279540999999,-36.3653144836],"type":"Point"}
}