{
  "type": "Feature",
  "properties": {
    "iso:country":"AU",
    "sg:address":"Cnr Maitland Rd & Islington St",
    "sg:city":"Islington",
    "sg:classifiers":[
        {
            "category":"Autos & Motor Vehicles",
            "subcategory":"Automobile Sales",
            "type":"Retail Goods"
        }
    ],
    "sg:phone":"+61 2 4969 1708",
    "sg:postcode":"2296",
    "sg:province":"NSW",
    "sg:tags":[
        "car",
        "used"
    ],
    "wof:name":"Halyard Motors",
    "wof:placetype":"venue"
},
  "geometry": {"coordinates":[151.745697022,-32.9145393372],"type":"Point"}
}