{
  "type": "Feature",
  "properties": {
    "iso:country":"AU",
    "sg:address":"24 Prestige Drv",
    "sg:city":"Clayton South",
    "sg:classifiers":[
        {
            "category":"Building & Trades",
            "subcategory":"Construction",
            "type":"Services"
        }
    ],
    "sg:phone":"+61 3 9558 1277",
    "sg:postcode":"3169",
    "sg:province":"VIC",
    "sg:tags":[
        "contractor"
    ],
    "wof:name":"J.H.L. Design Group Pty Ltd",
    "wof:placetype":"venue"
},
  "geometry": {"coordinates":[145.12193298299999,-37.9431266785],"type":"Point"}
}