{
  "type": "Feature",
  "properties": {
    "addr:full":"Shop 2 Wynyard Centre Wynyard St Tumut NSW 2720",
    "addr:housenumber":"shop 2",
    "addr:postcode":"2720",
    "addr:street":"Wynyard Centre Wynyard St",
    "iso:country":"AU",
    "sg:address":"Shop 2 Wynyard Centre Wynyard St",
    "sg:city":"Tumut",
    "sg:classifiers":[
        {
            "category":"Shopping",
            "subcategory":"Computers & Home Electronics",
            "type":"Retail Goods"
        }
    ],
    "sg:phone":"+61 2 6947 4661",
    "sg:postcode":"2720",
    "sg:province":"NSW",
    "sg:tags":[
        "hardware",
        "equipment"
    ],
    "wof:name":"Tims Computer Service",
    "wof:placetype":"venue"
},
  "geometry": {"coordinates":[148.22384600000001,-35.301125],"type":"Point"}
}