{
  "type": "Feature",
  "properties": {
    "iso:country":"AU",
    "sg:address":"82 Queen St",
    "sg:city":"Barraba",
    "sg:classifiers":[
        {
            "category":"Travel",
            "subcategory":"Hotels & Motels",
            "type":"Entertainment"
        }
    ],
    "sg:phone":"+61 2 6782 1004",
    "sg:postcode":"2347",
    "sg:province":"NSW",
    "sg:tags":[
        "pub"
    ],
    "wof:name":"Victoria Hotel",
    "wof:placetype":"venue"
},
  "geometry": {"coordinates":[150.610397339,-30.380399704],"type":"Point"}
}