{
  "type": "Feature",
  "properties": {
    "iso:country":"AU",
    "sg:address":"11 Mary St",
    "sg:city":"Jesmond",
    "sg:classifiers":[
        {
            "category":"Personal",
            "subcategory":"Massage",
            "type":"Services"
        }
    ],
    "sg:phone":"+61 2 4956 4044",
    "sg:postcode":"2299",
    "sg:province":"NSW",
    "sg:tags":[
        "therapy"
    ],
    "wof:name":"Groves' Total Approach",
    "wof:placetype":"venue"
},
  "geometry": {"coordinates":[151.69917297399999,-32.9030342102],"type":"Point"}
}