{
  "type": "Feature",
  "properties": {
    "addr:full":"146 Glenholm St Mitchelton QLD 4053",
    "addr:housenumber":"146",
    "addr:postcode":"4053",
    "addr:street":"Glenholm St",
    "iso:country":"AU",
    "sg:address":"146 Glenholm St",
    "sg:city":"Mitchelton",
    "sg:classifiers":[
        {
            "category":"Professional",
            "subcategory":"Art Services",
            "type":"Services"
        }
    ],
    "sg:phone":"+61 413 717 759",
    "sg:postcode":"4053",
    "sg:province":"QLD",
    "sg:tags":[
        "decorator",
        "painter"
    ],
    "wof:name":"Fitzpatrick Peter",
    "wof:placetype":"venue"
},
  "geometry": {"coordinates":[152.97280883799999,-27.4044208527],"type":"Point"}
}