{
  "type": "Feature",
  "properties": {
    "iso:country":"AU",
    "sg:address":"178 Anzac Pde",
    "sg:city":"Kensington",
    "sg:classifiers":[
        {
            "category":"Health Services",
            "subcategory":"Optometrist",
            "type":"Services"
        }
    ],
    "sg:phone":"+61 2 9697 9044",
    "sg:postcode":"2033",
    "sg:province":"NSW",
    "wof:name":"Michael Michael",
    "wof:placetype":"venue"
},
  "geometry": {"coordinates":[151.223587,-33.909851],"type":"Point"}
}