{
  "type": "Feature",
  "properties": {
    "iso:country":"AU",
    "sg:address":"PO Box 7010",
    "sg:city":"Dandenong",
    "sg:classifiers":[
        {
            "category":"Professional",
            "type":"Services"
        }
    ],
    "sg:phone":"+61 425 265 037",
    "sg:postcode":"3175",
    "sg:province":"VIC",
    "sg:tags":[
        "transport"
    ],
    "wof:name":"A To Z Couriers, Taxi Trucks & Furniture Removals",
    "wof:placetype":"venue"
},
  "geometry": {"coordinates":[145.21023559599999,-37.9872703552],"type":"Point"}
}