{
  "type": "Feature",
  "properties": {
    "addr:full":"8 Helen Kob Drv Braeside VIC 3195",
    "addr:housenumber":"8",
    "addr:postcode":"3195",
    "addr:street":"Helen Kob Drv",
    "iso:country":"AU",
    "sg:address":"8 Helen Kob Drv",
    "sg:city":"Braeside",
    "sg:classifiers":[
        {
            "category":"Real Estate",
            "subcategory":"Real Estate Operator",
            "type":"Services"
        }
    ],
    "sg:phone":"+61 3 9580 5577",
    "sg:postcode":"3195",
    "sg:province":"VIC",
    "sg:tags":[
        "building",
        "consultant",
        "management"
    ],
    "wof:name":"Pritchard Pty Ltd",
    "wof:placetype":"venue"
},
  "geometry": {"coordinates":[145.111419678,-38.0094566345],"type":"Point"}
}