{
  "type": "Feature",
  "properties": {
    "addr:full":"188 Merrylands Rd Merrylands NSW 2160",
    "addr:housenumber":"188",
    "addr:postcode":"2160",
    "addr:street":"Merrylands Rd",
    "iso:country":"AU",
    "sg:address":"188 Merrylands Rd",
    "sg:city":"Merrylands",
    "sg:classifiers":[
        {
            "category":"Food & Beverages",
            "subcategory":"Bakery",
            "type":"Retail Goods"
        }
    ],
    "sg:phone":"+61 2 9637 8978",
    "sg:postcode":"2160",
    "sg:province":"NSW",
    "sg:tags":[
        "baker"
    ],
    "wof:name":"Phat K Y Hot Bread",
    "wof:placetype":"venue"
},
  "geometry": {"coordinates":[150.989776611,-33.8366088867],"type":"Point"}
}