{
  "type": "Feature",
  "properties": {
    "addr:full":"135 Maitland Rd Mayfield NSW 2304",
    "addr:housenumber":"135",
    "addr:postcode":"2304",
    "addr:street":"Maitland Rd",
    "iso:country":"AU",
    "sg:address":"135 Maitland Rd",
    "sg:city":"Mayfield",
    "sg:classifiers":[
        {
            "category":"Food & Beverages",
            "subcategory":"Bakery",
            "type":"Retail Goods"
        }
    ],
    "sg:phone":"+61 2 4967 5963",
    "sg:postcode":"2304",
    "sg:province":"NSW",
    "sg:tags":[
        "baker"
    ],
    "wof:name":"Mayfield Hot Bread",
    "wof:placetype":"venue"
},
  "geometry": {"coordinates":[151.738204956,-32.8983840942],"type":"Point"}
}