{
  "type": "Feature",
  "properties": {
    "addr:full":"505 Main Rd Montrose TAS 7010",
    "addr:housenumber":"505",
    "addr:postcode":"7010",
    "addr:street":"Main Rd",
    "iso:country":"AU",
    "sg:address":"505 Main Rd",
    "sg:city":"Montrose",
    "sg:classifiers":[
        {
            "category":"Autos & Motor Vehicles",
            "subcategory":"Auto Supplies",
            "type":"Retail Goods"
        }
    ],
    "sg:phone":"+61 3 6273 2871",
    "sg:postcode":"7010",
    "sg:province":"TAS",
    "sg:tags":[
        "part",
        "cycles",
        "accessory"
    ],
    "wof:name":"Tas Scooters",
    "wof:placetype":"venue"
},
  "geometry": {"coordinates":[147.267211914,-42.8268547058],"type":"Point"}
}