{
  "type": "Feature",
  "properties": {
    "addr:full":"167 Hein Rd Buccan QLD 4207",
    "addr:housenumber":"167",
    "addr:postcode":"4207",
    "addr:street":"Hein Rd",
    "iso:country":"AU",
    "sg:address":"167 Hein Rd",
    "sg:city":"Buccan",
    "sg:classifiers":[
        {
            "category":"Utilities",
            "subcategory":"Water",
            "type":"Services"
        }
    ],
    "sg:phone":"+61 417 641 642",
    "sg:postcode":"4207",
    "sg:province":"QLD",
    "sg:tags":[
        "cartage"
    ],
    "wof:name":"Larry Allen",
    "wof:placetype":"venue"
},
  "geometry": {"coordinates":[153.13255310100001,-27.7481708527],"type":"Point"}
}