{
  "type": "Feature",
  "properties": {
    "iso:country":"AU",
    "sg:address":"131 Brodie Drv",
    "sg:city":"Coffs Harbour",
    "sg:classifiers":[
        {
            "category":"Building & Trades",
            "subcategory":"Construction",
            "type":"Services"
        }
    ],
    "sg:phone":"+61 2 6652 1750",
    "sg:postcode":"2450",
    "sg:province":"NSW",
    "sg:tags":[
        "contractor"
    ],
    "wof:name":"Ryan P & A Pty Ltd",
    "wof:placetype":"venue"
},
  "geometry": {"coordinates":[153.134399,-30.295837],"type":"Point"}
}