{
  "type": "Feature",
  "properties": {
    "iso:country":"AU",
    "sg:address":"21 Campana Ave",
    "sg:city":"Edgeworth",
    "sg:classifiers":[
        {
            "category":"Utilities",
            "subcategory":"Telephone",
            "type":"Services"
        }
    ],
    "sg:phone":"+61 2 4958 8999",
    "sg:postcode":"2285",
    "sg:province":"NSW",
    "sg:tags":[
        "installation",
        "system",
        "maintenance"
    ],
    "wof:name":"Data North Pty Ltd",
    "wof:placetype":"venue"
},
  "geometry": {"coordinates":[151.62611389200001,-32.9199142456],"type":"Point"}
}