{
  "type": "Feature",
  "properties": {
    "iso:country":"AU",
    "sg:address":"77 Grant St",
    "sg:city":"Port Macquarie",
    "sg:classifiers":[
        {
            "category":"Professional",
            "subcategory":"Art Services",
            "type":"Services"
        }
    ],
    "sg:phone":"+61 2 6584 0583",
    "sg:postcode":"2444",
    "sg:province":"NSW",
    "sg:tags":[
        "graphic",
        "designer"
    ],
    "sg:website":"http://www.abwerx.com",
    "wof:name":"AB Werx",
    "wof:placetype":"venue"
},
  "geometry": {"coordinates":[152.91456600000001,-31.430601],"type":"Point"}
}