{
  "type": "Feature",
  "properties": {
    "addr:full":"35 Wylie St Toowoomba QLD 4350",
    "addr:housenumber":"35",
    "addr:postcode":"4350",
    "addr:street":"Wylie St",
    "iso:country":"AU",
    "sg:address":"35 Wylie St",
    "sg:city":"Toowoomba",
    "sg:classifiers":[
        {
            "category":"Retail",
            "subcategory":"Auto Repair",
            "type":"Services"
        }
    ],
    "sg:phone":"+61 7 4659 9711",
    "sg:postcode":"4350",
    "sg:province":"QLD",
    "sg:tags":[
        "gas",
        "conversion",
        "natural",
        "lp",
        "vehicle"
    ],
    "wof:name":"Paramount Automotive & Performance",
    "wof:placetype":"venue"
},
  "geometry": {"coordinates":[151.949814,-27.567495],"type":"Point"}
}