{
  "type": "Feature",
  "properties": {
    "addr:full":"140 Macquarie Rd Springwood NSW 2777",
    "addr:housenumber":"140",
    "addr:postcode":"2777",
    "addr:street":"Macquarie Rd",
    "iso:country":"AU",
    "sg:address":"140 Macquarie Rd",
    "sg:city":"Springwood",
    "sg:classifiers":[
        {
            "category":"Food & Beverages",
            "subcategory":"Bakery",
            "type":"Retail Goods"
        }
    ],
    "sg:phone":"+61 2 4751 2394",
    "sg:postcode":"2777",
    "sg:province":"NSW",
    "sg:tags":[
        "cake",
        "shop",
        "pastry"
    ],
    "wof:name":"Springwood Cakes",
    "wof:placetype":"venue"
},
  "geometry": {"coordinates":[150.566848755,-33.6991348267],"type":"Point"}
}