{
  "type": "Feature",
  "properties": {
    "iso:country":"AU",
    "sg:address":"Shp 20 The Cosmopolitan Cntr Knox",
    "sg:city":"Double Bay",
    "sg:classifiers":[
        {
            "category":"Shopping",
            "subcategory":"Clothing, Apparel, & Fashions",
            "type":"Retail Goods"
        }
    ],
    "sg:phone":"+61 2 9327 4167",
    "sg:postcode":"2028",
    "sg:province":"NSW",
    "sg:tags":[
        "lady",
        "wear"
    ],
    "wof:name":"Papoucci",
    "wof:placetype":"venue"
},
  "geometry": {"coordinates":[151.243087769,-33.8790588379],"type":"Point"}
}