{
  "type": "Feature",
  "properties": {
    "addr:full":"174 Tannery La Mandurang VIC 3551",
    "addr:housenumber":"174",
    "addr:postcode":"3551",
    "addr:street":"Tannery La Mandurang",
    "iso:country":"AU",
    "sg:address":"174 Tannery La",
    "sg:city":"Mandurang",
    "sg:classifiers":[
        {
            "category":"Farming",
            "subcategory":"Vineyard",
            "type":"Manufacturing & Wholesale Goods"
        }
    ],
    "sg:phone":"+61 3 5439 3227",
    "sg:postcode":"3551",
    "sg:province":"VIC",
    "sg:tags":[
        "winery"
    ],
    "wof:name":"Tannery Lane Vineyard",
    "wof:placetype":"venue"
},
  "geometry": {"coordinates":[144.309249878,-36.8147277832],"type":"Point"}
}