{
  "type": "Feature",
  "properties": {
    "iso:country":"AU",
    "sg:address":"5 Friend St",
    "sg:city":"Mont Albert North",
    "sg:classifiers":[
        {
            "category":"Education",
            "subcategory":"Kindergarten",
            "type":"Public Place"
        }
    ],
    "sg:phone":"+61 3 9857 6583",
    "sg:postcode":"3129",
    "sg:province":"VIC",
    "sg:tags":[
        "pre-schools"
    ],
    "wof:name":"Friend Street Kindergarten",
    "wof:placetype":"venue"
},
  "geometry": {"coordinates":[145.10562133799999,-37.8001441956],"type":"Point"}
}