{
  "type": "Feature",
  "properties": {
    "addr:full":"Sd3/ 311 Macdonnell Rd Clontarf QLD 4019",
    "addr:housenumber":"sd3 / 311",
    "addr:postcode":"4019",
    "addr:street":"Macdonnell Rd",
    "iso:country":"AU",
    "sg:address":"Sd3/ 311 Macdonnell Rd",
    "sg:city":"Clontarf",
    "sg:classifiers":[
        {
            "category":"Retail",
            "subcategory":"Auto Repair",
            "type":"Services"
        }
    ],
    "sg:phone":"+61 7 3283 4311",
    "sg:postcode":"4019",
    "sg:province":"QLD",
    "sg:tags":[
        "repairer",
        "motor",
        "engineer"
    ],
    "wof:name":"Tp Automotive Engineering",
    "wof:placetype":"venue"
},
  "geometry": {"coordinates":[153.08277893100001,-27.2339515686],"type":"Point"}
}