{
  "type": "Feature",
  "properties": {
    "addr:full":"1 Gawler River Rd Two Wells SA 5501",
    "addr:housenumber":"1",
    "addr:postcode":"5501",
    "addr:street":"Gawler River Rd",
    "iso:country":"AU",
    "sg:address":"1 Gawler River Rd",
    "sg:city":"Two Wells",
    "sg:classifiers":[
        {
            "category":"Building & Trades",
            "subcategory":"Construction",
            "type":"Services"
        }
    ],
    "sg:phone":"+61 419 037 159",
    "sg:postcode":"5501",
    "sg:province":"SA",
    "sg:tags":[
        "concrete",
        "contractor"
    ],
    "wof:name":"Whiting Mark",
    "wof:placetype":"venue"
},
  "geometry": {"coordinates":[138.54458600000001,-34.625031],"type":"Point"}
}