{
  "type": "Feature",
  "properties": {
    "iso:country":"AU",
    "sg:address":"37 Main North Rd",
    "sg:city":"Clare",
    "sg:classifiers":[
        {
            "category":"Building & Trades",
            "subcategory":"Construction",
            "type":"Services"
        }
    ],
    "sg:phone":"+61 8 8842 1166",
    "sg:postcode":"5453",
    "sg:province":"SA",
    "sg:tags":[
        "brick",
        "paving"
    ],
    "wof:name":"Mid North Pave & Landscape",
    "wof:placetype":"venue"
},
  "geometry": {"coordinates":[138.61163300000001,-33.833015],"type":"Point"}
}