{
  "type": "Feature",
  "properties": {
    "addr:full":"2/ 11 Christine Pl Capalaba QLD 4157",
    "addr:housenumber":"/ 11",
    "addr:postcode":"4157",
    "addr:street":"Christine Pl",
    "iso:country":"AU",
    "sg:address":"2/ 11 Christine Pl",
    "sg:city":"Capalaba",
    "sg:classifiers":[
        {
            "category":"Autos & Motor Vehicles",
            "subcategory":"Auto Supplies",
            "type":"Retail Goods"
        }
    ],
    "sg:phone":"+61 7 3390 3933",
    "sg:postcode":"4157",
    "sg:province":"QLD",
    "sg:tags":[
        "garage",
        "equipment"
    ],
    "wof:name":"Precision Automotive Equipment",
    "wof:placetype":"venue"
},
  "geometry": {"coordinates":[153.20510864299999,-27.532037735],"type":"Point"}
}