{
  "type": "Feature",
  "properties": {
    "addr:full":"5 Clarendon Crt Mooroolbark VIC 3138",
    "addr:housenumber":"5",
    "addr:postcode":"3138",
    "addr:street":"Clarendon Crt",
    "iso:country":"AU",
    "sg:address":"5 Clarendon Crt",
    "sg:city":"Mooroolbark",
    "sg:classifiers":[
        {
            "category":"Arts & Performance",
            "subcategory":"Music",
            "type":"Entertainment"
        }
    ],
    "sg:phone":"+61 3 9726 8856",
    "sg:postcode":"3138",
    "sg:province":"VIC",
    "sg:tags":[
        "mobile",
        "jockey",
        "disc"
    ],
    "wof:name":"Digital Disc Drive",
    "wof:placetype":"venue"
},
  "geometry": {"coordinates":[145.32937622099999,-37.7840805054],"type":"Point"}
}