{
  "type": "Feature",
  "properties": {
    "iso:country":"AU",
    "sg:address":"Bay 4 19 Orchard Rd",
    "sg:city":"Brookvale",
    "sg:classifiers":[
        {
            "category":"Professional",
            "subcategory":"Detective & Security Services",
            "type":"Services"
        }
    ],
    "sg:phone":"+61 408 218 519",
    "sg:postcode":"2100",
    "sg:province":"NSW",
    "sg:tags":[
        "protective",
        "rustproofing"
    ],
    "wof:name":"Rustemul Pty Ltd",
    "wof:placetype":"venue"
},
  "geometry": {"coordinates":[151.272537231,-33.765171051],"type":"Point"}
}