{
  "type": "Feature",
  "properties": {
    "iso:country":"AU",
    "sg:address":"210 Drummond St (South)",
    "sg:city":"Ballarat",
    "sg:classifiers":[
        {
            "category":"Health Services",
            "subcategory":"Health Practitioner",
            "type":"Services"
        }
    ],
    "sg:phone":"+61 412 326 755",
    "sg:postcode":"3350",
    "sg:province":"VIC",
    "sg:tags":[
        "psychologist"
    ],
    "wof:name":"Gerry Egan",
    "wof:placetype":"venue"
},
  "geometry": {"coordinates":[143.846329,-37.565956],"type":"Point"}
}