{
  "type": "Feature",
  "properties": {
    "addr:full":"35 Rowlins Rd Gerringong NSW 2534",
    "addr:housenumber":"35",
    "addr:postcode":"2534",
    "addr:street":"Rowlins Rd",
    "iso:country":"AU",
    "sg:address":"35 Rowlins Rd",
    "sg:city":"Gerringong",
    "sg:classifiers":[
        {
            "category":"Professional",
            "type":"Services"
        }
    ],
    "sg:phone":"+61 2 4234 2077",
    "sg:postcode":"2534",
    "sg:province":"NSW",
    "sg:tags":[
        "spray",
        "painting"
    ],
    "wof:name":"Gerringong Smash Repairs",
    "wof:placetype":"venue"
},
  "geometry": {"coordinates":[150.82128906200001,-34.7420387268],"type":"Point"}
}