{
  "type": "Feature",
  "properties": {
    "iso:country":"AU",
    "sg:address":"PO Box 194",
    "sg:city":"Sanderson",
    "sg:classifiers":[
        {
            "category":"Shopping",
            "subcategory":"Musical Instruments",
            "type":"Retail Goods"
        }
    ],
    "sg:phone":"+61 8 8932 1496",
    "sg:postcode":"0812",
    "sg:province":"NT",
    "sg:tags":[
        "musician",
        "agent"
    ],
    "wof:name":"Ambush",
    "wof:placetype":"venue"
},
  "geometry": {"coordinates":[130.898911,-12.3905],"type":"Point"}
}