{
  "type": "Feature",
  "properties": {
    "addr:full":"Nicklin Way Minyama QLD 4575",
    "addr:postcode":"4575",
    "addr:street":"Nicklin",
    "iso:country":"AU",
    "sg:address":"Nicklin Way",
    "sg:city":"Minyama",
    "sg:classifiers":[
        {
            "category":"Professional",
            "subcategory":"Art Services",
            "type":"Services"
        }
    ],
    "sg:phone":"+61 7 5444 7932",
    "sg:postcode":"4575",
    "sg:province":"QLD",
    "sg:tags":[
        "interior",
        "decorator"
    ],
    "sg:website":"http://www.decorinteriors.com.au",
    "wof:name":"Decor Interiors",
    "wof:placetype":"venue"
},
  "geometry": {"coordinates":[153.122726,-26.700253],"type":"Point"}
}