{
  "type": "Feature",
  "properties": {
    "addr:full":"Shops 1 & 2, 7 Day Markets Cambridge Pde Manly QLD 4179",
    "addr:housenumber":"shops 1 &;7",
    "addr:postcode":"4179",
    "addr:street":"Cambridge Pde",
    "iso:country":"AU",
    "sg:address":"Shops 1 & 2, 7 Day Markets Cambridge Pde",
    "sg:city":"Manly",
    "sg:classifiers":[
        {
            "category":"Cafe",
            "type":"Food & Drink"
        }
    ],
    "sg:phone":"+61 7 3893 1093",
    "sg:postcode":"4179",
    "sg:province":"QLD",
    "wof:name":"Manly Village Deli Cafe",
    "wof:placetype":"venue"
},
  "geometry": {"coordinates":[153.18580627399999,-27.4542274475],"type":"Point"}
}