{
  "type": "Feature",
  "properties": {
    "addr:full":"31- 33 Benalla Shepparton VIC 3630",
    "addr:housenumber":"33",
    "addr:postcode":"3630",
    "addr:street":"Benalla",
    "iso:country":"AU",
    "sg:address":"31- 33",
    "sg:city":"Benalla Shepparton",
    "sg:classifiers":[
        {
            "category":"Manufacturing",
            "subcategory":"Metals",
            "type":"Manufacturing & Wholesale Goods"
        }
    ],
    "sg:phone":"+61 3 5831 3534",
    "sg:postcode":"3630",
    "sg:province":"VIC",
    "sg:tags":[
        "sheet",
        "worker"
    ],
    "wof:name":"CME Steel - Con Pty Ltd",
    "wof:placetype":"venue"
},
  "geometry": {"coordinates":[145.416091919,-36.3836212158],"type":"Point"}
}