{
  "type": "Feature",
  "properties": {
    "addr:full":"35 Geils Crt Deakin ACT 2600",
    "addr:housenumber":"35",
    "addr:postcode":"2600",
    "addr:street":"Geils Crt",
    "iso:country":"AU",
    "sg:address":"35 Geils Crt",
    "sg:city":"Deakin",
    "sg:classifiers":[
        {
            "category":"Professional",
            "subcategory":"Accounting & Tax Preparation",
            "type":"Services"
        }
    ],
    "sg:phone":"+61 2 6282 9696",
    "sg:postcode":"2600",
    "sg:province":"ACT",
    "sg:tags":[
        "accountant",
        "auditor"
    ],
    "wof:name":"Williams Rick",
    "wof:placetype":"venue"
},
  "geometry": {"coordinates":[149.09710693400001,-35.3157043457],"type":"Point"}
}