{
  "type": "Feature",
  "properties": {
    "addr:full":"355 South Pine Rd Enoggera QLD 4051",
    "addr:housenumber":"355",
    "addr:postcode":"4051",
    "addr:street":"South Pine Rd",
    "iso:country":"AU",
    "sg:address":"355 South Pine Rd",
    "sg:city":"Enoggera",
    "sg:classifiers":[
        {
            "category":"Building & Trades",
            "subcategory":"Landscaping Services",
            "type":"Services"
        }
    ],
    "sg:phone":"+61 405 648 827",
    "sg:postcode":"4051",
    "sg:province":"QLD",
    "sg:tags":[
        "designer",
        "landscape",
        "contractor"
    ],
    "wof:name":"Team Landscape",
    "wof:placetype":"venue"
},
  "geometry": {"coordinates":[152.992355347,-27.4118156433],"type":"Point"}
}