{
  "type": "Feature",
  "properties": {
    "addr:full":"15 Short St Redlynch QLD 4870",
    "addr:housenumber":"15",
    "addr:postcode":"4870",
    "addr:street":"Short St",
    "iso:country":"AU",
    "sg:address":"15 Short St",
    "sg:city":"Redlynch",
    "sg:classifiers":[
        {
            "category":"Social Services",
            "subcategory":"Retirement Home",
            "type":"Services"
        }
    ],
    "sg:phone":"+61 7 4039 9100",
    "sg:postcode":"4870",
    "sg:province":"QLD",
    "sg:tags":[
        "village"
    ],
    "wof:name":"Glenmead Village",
    "wof:placetype":"venue"
},
  "geometry": {"coordinates":[145.69729614299999,-16.889257431],"type":"Point"}
}