{
  "type": "Feature",
  "properties": {
    "iso:country":"AU",
    "sg:address":"Stockton St",
    "sg:city":"Nelson Bay",
    "sg:classifiers":[
        {
            "category":"Travel",
            "subcategory":"Travel Agent",
            "type":"Entertainment"
        }
    ],
    "sg:phone":"+61 2 4981 2277",
    "sg:postcode":"2315",
    "sg:province":"NSW",
    "sg:tags":[
        "consultant"
    ],
    "wof:name":"Bay World Travel",
    "wof:placetype":"venue"
},
  "geometry": {"coordinates":[152.14329499999999,-32.722809],"type":"Point"}
}