{
  "type": "Feature",
  "properties": {
    "addr:full":"Hannans Rd Riverwood NSW 2210",
    "addr:postcode":"2210",
    "addr:street":"Hannans Rd",
    "iso:country":"AU",
    "sg:address":"Hannans Rd",
    "sg:city":"Riverwood",
    "sg:classifiers":[
        {
            "category":"Education",
            "subcategory":"School",
            "type":"Public Place"
        }
    ],
    "sg:phone":"+61 2 9153 8170",
    "sg:postcode":"2210",
    "sg:province":"NSW",
    "sg:tags":[
        "state",
        "-",
        "nsw"
    ],
    "wof:name":"Hannans Road Public School",
    "wof:placetype":"venue"
},
  "geometry": {"coordinates":[151.05363500000001,-33.945404],"type":"Point"}
}