{
  "type": "Feature",
  "properties": {
    "iso:country":"AU",
    "sg:address":"U 3/ 66 Rundle St",
    "sg:city":"Kent Town",
    "sg:classifiers":[
        {
            "category":"Professional",
            "subcategory":"Engineering",
            "type":"Services"
        }
    ],
    "sg:phone":"+61 8 8362 8860",
    "sg:postcode":"5067",
    "sg:province":"SA",
    "sg:tags":[
        "consulting",
        "engineer"
    ],
    "wof:name":"Bryant Concepts Pty Ltd",
    "wof:placetype":"venue"
},
  "geometry": {"coordinates":[138.620925903,-34.921546936],"type":"Point"}
}