{
  "type": "Feature",
  "properties": {
    "addr:full":"273a Mill Point Rd South Perth WA 6151",
    "addr:housenumber":"273a",
    "addr:postcode":"6151",
    "addr:street":"Mill Point Rd",
    "iso:country":"AU",
    "sg:address":"273a Mill Point Rd",
    "sg:city":"South Perth",
    "sg:classifiers":[
        {
            "category":"Food & Beverages",
            "subcategory":"Meat & Fish",
            "type":"Retail Goods"
        }
    ],
    "sg:phone":"+61 8 9367 6324",
    "sg:postcode":"6151",
    "sg:province":"WA",
    "sg:tags":[
        "seafood"
    ],
    "wof:name":"Mill Point Fish Supply",
    "wof:placetype":"venue"
},
  "geometry": {"coordinates":[115.85623200000001,-31.975563],"type":"Point"}
}