{
  "type": "Feature",
  "properties": {
    "iso:country":"AU",
    "sg:address":"Main Rd",
    "sg:city":"Harrietville",
    "sg:classifiers":[
        {
            "category":"Sports & Exercise",
            "subcategory":"Ski Slope",
            "type":"Entertainment"
        }
    ],
    "sg:phone":"+61 1800 467 669",
    "sg:postcode":"3741",
    "sg:province":"VIC",
    "sg:tags":[
        "equipment",
        "hire",
        "retail",
        "snow"
    ],
    "wof:name":"Hoys A-Frame Ski Hire",
    "wof:placetype":"venue"
},
  "geometry": {"coordinates":[147.06204199999999,-36.895329],"type":"Point"}
}