{
  "type": "Feature",
  "properties": {
    "addr:full":"29/ 195 Prospect Hwy Seven Hills NSW 2147",
    "addr:housenumber":"29 / 195",
    "addr:postcode":"2147",
    "addr:street":"Prospect Hwy",
    "iso:country":"AU",
    "sg:address":"29/ 195 Prospect Hwy",
    "sg:city":"Seven Hills",
    "sg:classifiers":[
        {
            "category":"Transit Center",
            "subcategory":"Freight",
            "type":"Transportation"
        }
    ],
    "sg:phone":"+61 2 9620 8777",
    "sg:postcode":"2147",
    "sg:province":"NSW",
    "sg:tags":[
        "forklift",
        "truck"
    ],
    "wof:name":"M & E Forklifts Pty Ltd",
    "wof:placetype":"venue"
},
  "geometry": {"coordinates":[150.938156128,-33.771572113],"type":"Point"}
}