{
  "type": "Feature",
  "properties": {
    "addr:full":"134 Langford St North Melbourne VIC 3051",
    "addr:housenumber":"134",
    "addr:postcode":"3051",
    "addr:street":"Langford St",
    "iso:country":"AU",
    "sg:address":"134 Langford St",
    "sg:city":"North Melbourne",
    "sg:classifiers":[
        {
            "category":"Home & Garden",
            "subcategory":"Hardware",
            "type":"Retail Goods"
        }
    ],
    "sg:phone":"+61 3 9329 8500",
    "sg:postcode":"3051",
    "sg:province":"VIC",
    "sg:tags":[
        "generating",
        "set",
        "generator"
    ],
    "wof:name":"Event Power",
    "wof:placetype":"venue"
},
  "geometry": {"coordinates":[144.93690490700001,-37.7960395813],"type":"Point"}
}