{
  "type": "Feature",
  "properties": {
    "addr:full":"PO Box 77 Seddon VIC 3011",
    "addr:postcode":"3011",
    "iso:country":"AU",
    "sg:address":"PO Box 77",
    "sg:city":"Seddon",
    "sg:classifiers":[
        {
            "category":"Professional",
            "subcategory":"Employment Agencies",
            "type":"Services"
        }
    ],
    "sg:phone":"+61 411 786 376",
    "sg:postcode":"3011",
    "sg:province":"VIC",
    "sg:tags":[
        "entertainer",
        "agent"
    ],
    "wof:name":"Magic2",
    "wof:placetype":"venue"
},
  "geometry": {"coordinates":[144.89004516599999,-37.8029098511],"type":"Point"}
}