{
  "type": "Feature",
  "properties": {
    "addr:full":"82 Argyle St South Windsor NSW 2756",
    "addr:housenumber":"82",
    "addr:postcode":"2756",
    "addr:street":"Argyle St",
    "iso:country":"AU",
    "sg:address":"82 Argyle St",
    "sg:city":"South Windsor",
    "sg:classifiers":[
        {
            "category":"Manufacturing",
            "subcategory":"Tools & Machinery",
            "type":"Manufacturing & Wholesale Goods"
        }
    ],
    "sg:phone":"+61 2 4577 2988",
    "sg:postcode":"2756",
    "sg:province":"NSW",
    "sg:tags":[
        "small",
        "engineer"
    ],
    "wof:name":"Twin Engineering Pty Ltd",
    "wof:placetype":"venue"
},
  "geometry": {"coordinates":[150.81367492699999,-33.620716095],"type":"Point"}
}