{
  "type": "Feature",
  "properties": {
    "iso:country":"AU",
    "sg:address":"106 West High St",
    "sg:city":"Coffs Harbour",
    "sg:classifiers":[
        {
            "category":"Health Services",
            "subcategory":"Health Practitioner",
            "type":"Services"
        }
    ],
    "sg:phone":"+61 2 6651 1549",
    "sg:postcode":"2450",
    "sg:province":"NSW",
    "sg:tags":[
        "homoeopath"
    ],
    "wof:name":"Northcoast Allergy Prevention Clinic",
    "wof:placetype":"venue"
},
  "geometry": {"coordinates":[153.10938999999999,-30.295637],"type":"Point"}
}