{
  "type": "Feature",
  "properties": {
    "iso:country":"AU",
    "sg:address":"102a May St St",
    "sg:city":"Peters",
    "sg:classifiers":[
        {
            "category":"Professional",
            "subcategory":"Art Services",
            "type":"Services"
        }
    ],
    "sg:phone":"+61 2 9519 9081",
    "sg:postcode":"2044",
    "sg:province":"NSW",
    "sg:tags":[
        "picture",
        "frame",
        "framing"
    ],
    "wof:name":"Art & Framing Company",
    "wof:placetype":"venue"
},
  "geometry": {"coordinates":[151.176865,-33.909966],"type":"Point"}
}