{
  "type": "Feature",
  "properties": {
    "addr:full":"198 High St Hillston NSW 2675",
    "addr:housenumber":"198",
    "addr:postcode":"2675",
    "addr:street":"High St",
    "iso:country":"AU",
    "sg:address":"198 High St",
    "sg:city":"Hillston",
    "sg:classifiers":[
        {
            "category":"Retail",
            "subcategory":"Auto Repair",
            "type":"Services"
        }
    ],
    "sg:phone":"+61 2 6967 2647",
    "sg:postcode":"2675",
    "sg:province":"NSW",
    "sg:tags":[
        "repairer",
        "motor",
        "engineer"
    ],
    "wof:name":"Moore's Motors",
    "wof:placetype":"venue"
},
  "geometry": {"coordinates":[145.53733825699999,-33.4816551208],"type":"Point"}
}