{
  "type": "Feature",
  "properties": {
    "addr:full":"51 Henderson Rd Rowville VIC 3178",
    "addr:housenumber":"51",
    "addr:postcode":"3178",
    "addr:street":"Henderson Rd",
    "iso:country":"AU",
    "sg:address":"51 Henderson Rd",
    "sg:city":"Rowville",
    "sg:classifiers":[
        {
            "category":"Manufacturing",
            "subcategory":"Tools & Machinery",
            "type":"Manufacturing & Wholesale Goods"
        }
    ],
    "sg:phone":"+61 3 9764 0150",
    "sg:postcode":"3178",
    "sg:province":"VIC",
    "sg:tags":[
        "manufactured",
        "specially",
        "designed"
    ],
    "wof:name":"Centreline Engineering Pty Ltd",
    "wof:placetype":"venue"
},
  "geometry": {"coordinates":[145.245727539,-37.9054069519],"type":"Point"}
}