{
  "type": "Feature",
  "properties": {
    "addr:full":"Ste3/ 189 Ocean View Rd Ettalong Beach NSW 2257",
    "addr:housenumber":"189",
    "addr:postcode":"2257",
    "addr:street":"Ocean View Rd",
    "iso:country":"AU",
    "sg:address":"Ste3/ 189 Ocean View Rd",
    "sg:city":"Ettalong Beach",
    "sg:classifiers":[
        {
            "category":"Cafe",
            "type":"Food & Drink"
        }
    ],
    "sg:phone":"+61 2 4344 1233",
    "sg:postcode":"2257",
    "sg:province":"NSW",
    "wof:name":"Red Saffire Exotic Interiors & Cafe",
    "wof:placetype":"venue"
},
  "geometry": {"coordinates":[151.339019775,-33.514087677],"type":"Point"}
}