{
  "type": "Feature",
  "properties": {
    "iso:country":"AU",
    "sg:address":"51 Brunswick St",
    "sg:city":"Fitzroy",
    "sg:classifiers":[
        {
            "category":"Travel",
            "subcategory":"Hotels & Motels",
            "type":"Entertainment"
        }
    ],
    "sg:phone":"+61 3 9419 7180",
    "sg:postcode":"3065",
    "sg:province":"VIC",
    "sg:tags":[
        "accommodation"
    ],
    "wof:name":"Rob Roy Hotel",
    "wof:placetype":"venue"
},
  "geometry": {"coordinates":[144.97706604000001,-37.805644989],"type":"Point"}
}