{
  "type": "Feature",
  "properties": {
    "iso:country":"AU",
    "sg:address":"17 Napoleon St",
    "sg:city":"Cottesloe",
    "sg:classifiers":[
        {
            "category":"Food & Beverages",
            "subcategory":"Specialty",
            "type":"Retail Goods"
        }
    ],
    "sg:phone":"+61 8 9286 3133",
    "sg:postcode":"6011",
    "sg:province":"WA",
    "sg:tags":[
        "product",
        "health"
    ],
    "wof:name":"The Well Within",
    "wof:placetype":"venue"
},
  "geometry": {"coordinates":[115.76193237299999,-31.9980430603],"type":"Point"}
}