{
  "type": "Feature",
  "properties": {
    "addr:full":"2/ 97 Commercial St Merbein VIC 3505",
    "addr:housenumber":"/ 97",
    "addr:postcode":"3505",
    "addr:street":"Commercial St",
    "iso:country":"AU",
    "sg:address":"2/ 97 Commercial St",
    "sg:city":"Merbein",
    "sg:classifiers":[
        {
            "category":"Professional",
            "subcategory":"Employment Agencies",
            "type":"Services"
        }
    ],
    "sg:phone":"+61 3 5025 3344",
    "sg:postcode":"3505",
    "sg:province":"VIC",
    "wof:name":"MADEC Jobs Australia",
    "wof:placetype":"venue"
},
  "geometry": {"coordinates":[142.060546875,-34.167766571],"type":"Point"}
}