{
  "type": "Feature",
  "properties": {
    "addr:full":"Shop 1, 140- 146 Eleventh St Mildura VIC 3500",
    "addr:housenumber":"shop 1;146",
    "addr:postcode":"140;3500",
    "addr:street":"Eleventh St",
    "iso:country":"AU",
    "sg:address":"Shop 1, 140- 146 Eleventh St",
    "sg:city":"Mildura",
    "sg:classifiers":[
        {
            "category":"Home & Garden",
            "subcategory":"Furniture",
            "type":"Retail Goods"
        }
    ],
    "sg:phone":"+61 3 5021 1390",
    "sg:postcode":"3500",
    "sg:province":"VIC",
    "sg:tags":[
        "business"
    ],
    "wof:name":"Mildura Auctions Warehouse",
    "wof:placetype":"venue"
},
  "geometry": {"coordinates":[142.16567993199999,-34.1962127686],"type":"Point"}
}