{
  "type": "Feature",
  "properties": {
    "addr:full":"PO Box 208 Woollahra NSW 1350",
    "addr:postcode":"1350",
    "iso:country":"AU",
    "sg:address":"PO Box 208",
    "sg:city":"Woollahra",
    "sg:classifiers":[
        {
            "category":"Shopping",
            "subcategory":"Luggage & Leather Goods",
            "type":"Retail Goods"
        }
    ],
    "sg:phone":"+61 411 852 367",
    "sg:postcode":"1350",
    "sg:province":"NSW",
    "sg:tags":[
        "reconditioning"
    ],
    "wof:name":"Professional Australian Leather - Woollahra",
    "wof:placetype":"venue"
},
  "geometry": {"coordinates":[151.23716735799999,-33.8884391785],"type":"Point"}
}