{
  "type": "Feature",
  "properties": {
    "iso:country":"AU",
    "sg:address":"42 Kamarooka St",
    "sg:city":"Barooga",
    "sg:classifiers":[
        {
            "category":"Travel",
            "subcategory":"Hotels & Motels",
            "type":"Entertainment"
        }
    ],
    "sg:phone":"+61 3 5873 4244",
    "sg:postcode":"3644",
    "sg:province":"NSW",
    "wof:name":"High-Noon Motel Barooga",
    "wof:placetype":"venue"
},
  "geometry": {"coordinates":[145.69671630900001,-35.9064331055],"type":"Point"}
}