{
  "type": "Feature",
  "properties": {
    "iso:country":"AU",
    "sg:address":"Sunshine Pde",
    "sg:city":"Sunshine",
    "sg:classifiers":[
        {
            "category":"Recreation",
            "subcategory":"Sailing Club",
            "type":"Entertainment"
        }
    ],
    "sg:phone":"+61 2 4970 5118",
    "sg:postcode":"2264",
    "sg:province":"NSW",
    "sg:tags":[
        "yacht"
    ],
    "wof:name":"South Lake Macquarie Amateur Sailing Club",
    "wof:placetype":"venue"
},
  "geometry": {"coordinates":[151.562637,-33.114002],"type":"Point"}
}