{
  "type": "Feature",
  "properties": {
    "addr:full":"Unit 9/ 60 Kremzow Brendale QLD 4500",
    "addr:housenumber":"60",
    "addr:postcode":"4500",
    "addr:street":"Kremzow",
    "iso:country":"AU",
    "sg:address":"Unit 9/ 60 Kremzow",
    "sg:city":"Brendale",
    "sg:classifiers":[
        {
            "category":"Home & Garden",
            "subcategory":"Carpets & Floor Coverings",
            "type":"Retail Goods"
        }
    ],
    "sg:phone":"+61 7 3881 1000",
    "sg:postcode":"4500",
    "sg:province":"QLD",
    "wof:name":"Kenbrock Flooring",
    "wof:placetype":"venue"
},
  "geometry": {"coordinates":[152.981964111,-27.3172607422],"type":"Point"}
}