{
  "type": "Feature",
  "properties": {
    "addr:full":"142 Victoria Rd Parramatta NSW 2150",
    "addr:housenumber":"142",
    "addr:postcode":"2150",
    "addr:street":"Victoria Rd",
    "iso:country":"AU",
    "sg:address":"142 Victoria Rd",
    "sg:city":"Parramatta",
    "sg:classifiers":[
        {
            "category":"Fast Food",
            "type":"Food & Drink"
        }
    ],
    "sg:phone":"+61 2 9630 3777",
    "sg:postcode":"2150",
    "sg:province":"NSW",
    "sg:tags":[
        "away",
        "take"
    ],
    "wof:name":"Take Away Food",
    "wof:placetype":"venue"
},
  "geometry": {"coordinates":[151.046417236,-33.7399711609],"type":"Point"}
}