{
  "type": "Feature",
  "properties": {
    "addr:full":"Suite 9, 126 Egan St Kalgoorlie WA 6430",
    "addr:housenumber":"126",
    "addr:postcode":"6430",
    "addr:street":"Egan St",
    "iso:country":"AU",
    "sg:address":"Suite 9, 126 Egan St",
    "sg:city":"Kalgoorlie",
    "sg:classifiers":[
        {
            "category":"Health Services",
            "subcategory":"Doctor",
            "type":"Services"
        }
    ],
    "sg:phone":"+61 8 9021 5044",
    "sg:postcode":"6430",
    "sg:province":"WA",
    "sg:tags":[
        "medical",
        "practitioner"
    ],
    "wof:name":"Imaging The South",
    "wof:placetype":"venue"
},
  "geometry": {"coordinates":[121.47038268999999,-30.751083374],"type":"Point"}
}