{
  "type": "Feature",
  "properties": {
    "addr:full":"71 - 75 Griffiths Rd Lambton NSW 2299",
    "addr:housenumber":"75",
    "addr:postcode":"2299",
    "addr:street":"Griffiths Rd",
    "iso:country":"AU",
    "sg:address":"71 - 75 Griffiths Rd",
    "sg:city":"Lambton",
    "sg:classifiers":[
        {
            "category":"Social Services",
            "subcategory":"Adult Care",
            "type":"Services"
        }
    ],
    "sg:phone":"+61 2 4952 2730",
    "sg:postcode":"2299",
    "sg:province":"NSW",
    "sg:tags":[
        "towing"
    ],
    "wof:name":"Steve Koulis Smash Repairs",
    "wof:placetype":"venue"
},
  "geometry": {"coordinates":[151.72456359899999,-32.9148597717],"type":"Point"}
}