{
  "type": "Feature",
  "properties": {
    "addr:full":"18 Power St North Rockhampton QLD 4701",
    "addr:housenumber":"18",
    "addr:postcode":"4701",
    "addr:street":"Power St North",
    "iso:country":"AU",
    "sg:address":"18 Power St",
    "sg:city":"North Rockhampton",
    "sg:classifiers":[
        {
            "category":"Commercial Area",
            "type":"Public Place"
        }
    ],
    "sg:phone":"+61 7 4927 8911",
    "sg:postcode":"4701",
    "sg:province":"QLD",
    "sg:tags":[
        "heavy",
        "carrier"
    ],
    "wof:name":"Rocky's Own Transport Co",
    "wof:placetype":"venue"
},
  "geometry": {"coordinates":[150.506469727,-23.345954895],"type":"Point"}
}