{
  "type": "Feature",
  "properties": {
    "addr:full":"17 Bathurst Pl Macquarie ACT 2614",
    "addr:housenumber":"17",
    "addr:postcode":"2614",
    "addr:street":"Bathurst Pl",
    "iso:country":"AU",
    "sg:address":"17 Bathurst Pl",
    "sg:city":"Macquarie",
    "sg:classifiers":[
        {
            "category":"Education",
            "subcategory":"Music School",
            "type":"Public Place"
        }
    ],
    "sg:phone":"+61 2 6251 1716",
    "sg:postcode":"2614",
    "sg:province":"ACT",
    "sg:tags":[
        "teacher"
    ],
    "wof:name":"Macquarie Music",
    "wof:placetype":"venue"
},
  "geometry": {"coordinates":[149.05531310999999,-35.2538490295],"type":"Point"}
}