{
  "type": "Feature",
  "properties": {
    "addr:full":"35 Derby Rd Maryborough VIC 3465",
    "addr:housenumber":"35",
    "addr:postcode":"3465",
    "addr:street":"Derby Rd",
    "iso:country":"AU",
    "sg:address":"35 Derby Rd",
    "sg:city":"Maryborough",
    "sg:classifiers":[
        {
            "category":"Professional",
            "subcategory":"Computer Services",
            "type":"Services"
        }
    ],
    "sg:phone":"+61 3 5461 4052",
    "sg:postcode":"3465",
    "sg:province":"VIC",
    "sg:tags":[
        "package",
        "software"
    ],
    "wof:name":"Aware Supplies",
    "wof:placetype":"venue"
},
  "geometry": {"coordinates":[143.730102539,-37.0521202087],"type":"Point"}
}