{
  "type": "Feature",
  "properties": {
    "addr:full":"1 Glenrowan Drv Tallai QLD 4213",
    "addr:housenumber":"1",
    "addr:postcode":"4213",
    "addr:street":"Glenrowan Drv",
    "iso:country":"AU",
    "sg:address":"1 Glenrowan Drv",
    "sg:city":"Tallai",
    "sg:classifiers":[
        {
            "category":"Shopping",
            "subcategory":"Discount & Variety Stores",
            "type":"Retail Goods"
        }
    ],
    "sg:phone":"+61 7 5559 1088",
    "sg:postcode":"4213",
    "sg:province":"QLD",
    "sg:tags":[
        "shop",
        "adult"
    ],
    "wof:name":"EPA Trading Pty Ltd",
    "wof:placetype":"venue"
},
  "geometry": {"coordinates":[153.320114136,-28.0496730804],"type":"Point"}
}