{
  "type": "Feature",
  "properties": {
    "addr:full":"319 Milton Rd Milton QLD 4064",
    "addr:housenumber":"319",
    "addr:postcode":"4064",
    "addr:street":"Milton Rd",
    "iso:country":"AU",
    "sg:address":"319 Milton Rd",
    "sg:city":"Milton",
    "sg:classifiers":[
        {
            "category":"Health Services",
            "subcategory":"Medical Lab",
            "type":"Services"
        }
    ],
    "sg:phone":"+61 7 3368 3688",
    "sg:postcode":"4064",
    "sg:province":"QLD",
    "sg:tags":[
        "laboratory",
        "dental"
    ],
    "wof:name":"Hansen Dental Laboratory Services",
    "wof:placetype":"venue"
},
  "geometry": {"coordinates":[152.99996948200001,-27.4703598022],"type":"Point"}
}