{
  "type": "Feature",
  "properties": {
    "addr:full":"85 Sydney Rd Manly NSW 2095",
    "addr:housenumber":"85",
    "addr:postcode":"2095",
    "addr:street":"Sydney Rd",
    "iso:country":"AU",
    "sg:address":"85 Sydney Rd",
    "sg:city":"Manly",
    "sg:classifiers":[
        {
            "category":"Building & Trades",
            "subcategory":"Pest Control",
            "type":"Services"
        }
    ],
    "sg:phone":"+61 2 9907 0900",
    "sg:postcode":"2095",
    "sg:province":"NSW",
    "sg:website":"http://www.manlywarringahpest.com.au",
    "wof:name":"Manly-Warringah Pest Control",
    "wof:placetype":"venue"
},
  "geometry": {"coordinates":[151.28126525900001,-33.7963485718],"type":"Point"}
}