{
  "type": "Feature",
  "properties": {
    "iso:country":"AU",
    "sg:address":"1047 Ryans La",
    "sg:city":"Melton",
    "sg:classifiers":[
        {
            "category":"Building & Trades",
            "subcategory":"Construction",
            "type":"Services"
        }
    ],
    "sg:phone":"+61 3 9746 6507",
    "sg:postcode":"3337",
    "sg:province":"VIC",
    "sg:tags":[
        "contractor"
    ],
    "wof:name":"Elite Home Constructions Development Pty Ltd",
    "wof:placetype":"venue"
},
  "geometry": {"coordinates":[144.61882,-37.660393],"type":"Point"}
}