{
  "type": "Feature",
  "properties": {
    "addr:full":"919 Londonberry Rd Londonderry NSW 2753",
    "addr:housenumber":"919",
    "addr:postcode":"2753",
    "addr:street":"Londonberry Rd",
    "iso:country":"AU",
    "sg:address":"919 Londonberry Rd",
    "sg:city":"Londonderry",
    "sg:classifiers":[
        {
            "category":"Building & Trades",
            "subcategory":"Pest Control",
            "type":"Services"
        }
    ],
    "sg:phone":"+61 2 4724 4900",
    "sg:postcode":"2753",
    "sg:province":"NSW",
    "sg:tags":[
        "technical",
        "consultant"
    ],
    "sg:website":"http://www.testsafe.com.au",
    "wof:name":"Testsafe Australia",
    "wof:placetype":"venue"
},
  "geometry": {"coordinates":[150.72882080100001,-33.6830978394],"type":"Point"}
}