{
  "type": "Feature",
  "properties": {
    "addr:full":"22 Aldershot Rd Lonsdale SA 5160",
    "addr:housenumber":"22",
    "addr:postcode":"5160",
    "addr:street":"Aldershot Rd",
    "iso:country":"AU",
    "sg:address":"22 Aldershot Rd",
    "sg:city":"Lonsdale",
    "sg:classifiers":[
        {
            "category":"Communications",
            "subcategory":"Film & Video Production",
            "type":"Services"
        }
    ],
    "sg:phone":"+61 1800 888 123",
    "sg:postcode":"5160",
    "sg:province":"SA",
    "sg:tags":[
        "strip",
        "weather",
        "seal"
    ],
    "wof:name":"Raven Products Pty Ltd",
    "wof:placetype":"venue"
},
  "geometry": {"coordinates":[138.50709533700001,-35.1061668396],"type":"Point"}
}