{
  "type": "Feature",
  "properties": {
    "iso:country":"AU",
    "sg:address":"116 - 118 Bundall Rd",
    "sg:city":"Bundall",
    "sg:classifiers":[
        {
            "category":"Home & Garden",
            "subcategory":"Furniture",
            "type":"Retail Goods"
        }
    ],
    "sg:phone":"+61 7 5570 1299",
    "sg:postcode":"4217",
    "sg:province":"QLD",
    "sg:tags":[
        "outdoor"
    ],
    "wof:name":"Barbeques Galore",
    "wof:placetype":"venue"
},
  "geometry": {"coordinates":[153.41375732399999,-28.0035686493],"type":"Point"}
}