{
  "type": "Feature",
  "properties": {
    "iso:country":"AU",
    "sg:address":"PO Box 34",
    "sg:city":"Koolunga",
    "sg:classifiers":[
        {
            "category":"Education",
            "subcategory":"School",
            "type":"Public Place"
        }
    ],
    "sg:phone":"+61 8 8846 6052",
    "sg:postcode":"5464",
    "sg:province":"SA",
    "sg:tags":[
        "state",
        "except",
        "nsw"
    ],
    "wof:name":"Koolunga Primary School",
    "wof:placetype":"venue"
},
  "geometry": {"coordinates":[138.33387756400001,-33.5851898193],"type":"Point"}
}