{
  "type": "Feature",
  "properties": {
    "addr:full":"18 Ross St Newstead QLD 4006",
    "addr:housenumber":"18",
    "addr:postcode":"4006",
    "addr:street":"Ross St",
    "iso:country":"AU",
    "sg:address":"18 Ross St",
    "sg:city":"Newstead",
    "sg:classifiers":[
        {
            "category":"Autos & Motor Vehicles",
            "subcategory":"Automobile Sales",
            "type":"Retail Goods"
        }
    ],
    "sg:phone":"+61 7 3852 3822",
    "sg:postcode":"4006",
    "sg:province":"QLD",
    "sg:tags":[
        "car",
        "used"
    ],
    "wof:name":"Adness Jim Quality Used Cars",
    "wof:placetype":"venue"
},
  "geometry": {"coordinates":[153.042205811,-27.4436855316],"type":"Point"}
}