{
  "type": "Feature",
  "properties": {
    "iso:country":"AU",
    "sg:address":"Suite 20, Level 16 329 Pitt St",
    "sg:city":"Sydney",
    "sg:classifiers":[
        {
            "category":"Banks & Credit Unions",
            "subcategory":"Financial Services",
            "type":"Services"
        }
    ],
    "sg:phone":"+61 2 9286 3566",
    "sg:postcode":"2000",
    "sg:province":"NSW",
    "sg:tags":[
        "financier"
    ],
    "wof:name":"Australian Capital Solution Pty Ltd",
    "wof:placetype":"venue"
},
  "geometry": {"coordinates":[151.207855225,-33.874294281],"type":"Point"}
}