{
  "type": "Feature",
  "properties": {
    "addr:full":"7 Spencer Ave Kirwan QLD 4817",
    "addr:housenumber":"7",
    "addr:postcode":"4817",
    "addr:street":"Spencer Ave",
    "iso:country":"AU",
    "sg:address":"7 Spencer Ave",
    "sg:city":"Kirwan",
    "sg:classifiers":[
        {
            "category":"Freight",
            "type":"Transportation"
        }
    ],
    "sg:phone":"+61 417 329 801",
    "sg:postcode":"4817",
    "sg:province":"QLD",
    "sg:tags":[
        "cargo",
        "container"
    ],
    "wof:name":"Spot On Container Services",
    "wof:placetype":"venue"
},
  "geometry": {"coordinates":[146.720642,-19.295225],"type":"Point"}
}