{
  "type": "Feature",
  "properties": {
    "addr:full":"112 Princes Hwy Figtree NSW 2525",
    "addr:housenumber":"112",
    "addr:postcode":"2525",
    "addr:street":"Princes Hwy",
    "iso:country":"AU",
    "sg:address":"112 Princes Hwy",
    "sg:city":"Figtree",
    "sg:classifiers":[
        {
            "category":"Retail",
            "subcategory":"Auto Repair",
            "type":"Services"
        }
    ],
    "sg:phone":"+61 2 4272 3999",
    "sg:postcode":"2525",
    "sg:province":"NSW",
    "sg:tags":[
        "clutch",
        "brake"
    ],
    "wof:name":"Figtree Brake & Clutch",
    "wof:placetype":"venue"
},
  "geometry": {"coordinates":[150.86375427199999,-34.4333686829],"type":"Point"}
}