{
  "type": "Feature",
  "properties": {
    "iso:country":"AU",
    "sg:address":"Unit 1, 45 Flinders St",
    "sg:city":"Lawson",
    "sg:classifiers":[
        {
            "category":"Retail",
            "subcategory":"Auto Repair",
            "type":"Services"
        }
    ],
    "sg:phone":"+61 2 4759 2103",
    "sg:postcode":"2783",
    "sg:province":"NSW",
    "sg:tags":[
        "wheel",
        "balancing",
        "alignment"
    ],
    "wof:name":"Mark Harrison Automotive Services",
    "wof:placetype":"venue"
},
  "geometry": {"coordinates":[150.442230225,-33.7259635925],"type":"Point"}
}