{
  "type": "Feature",
  "properties": {
    "addr:full":"38 Princes Hwy Mogo NSW 2536",
    "addr:housenumber":"38",
    "addr:postcode":"2536",
    "addr:street":"Princes Hwy",
    "iso:country":"AU",
    "sg:address":"38 Princes Hwy",
    "sg:city":"Mogo",
    "sg:classifiers":[
        {
            "category":"Ice Cream",
            "type":"Food & Drink"
        }
    ],
    "sg:phone":"+61 2 4474 0190",
    "sg:postcode":"2536",
    "sg:province":"NSW",
    "sg:tags":[
        "retail"
    ],
    "wof:name":"Mogo Ice Creamery The",
    "wof:placetype":"venue"
},
  "geometry": {"coordinates":[150.145355225,-35.7735748291],"type":"Point"}
}