{
  "type": "Feature",
  "properties": {
    "addr:full":"Unit 1/ 11 Robertson Pl Penrith NSW 2750",
    "addr:housenumber":"11",
    "addr:postcode":"2750",
    "addr:street":"Robertson Pl",
    "iso:country":"AU",
    "sg:address":"Unit 1/ 11 Robertson Pl",
    "sg:city":"Penrith",
    "sg:classifiers":[
        {
            "category":"Arts & Performance",
            "subcategory":"Dance",
            "type":"Entertainment"
        }
    ],
    "sg:phone":"+61 2 4722 6348",
    "sg:postcode":"2750",
    "sg:province":"NSW",
    "sg:tags":[
        "theatrical",
        "ballet",
        "tuition"
    ],
    "wof:name":"Penrith Premier Dance & Performing Arts",
    "wof:placetype":"venue"
},
  "geometry": {"coordinates":[150.68260192899999,-33.76820755],"type":"Point"}
}