{
  "type": "Feature",
  "properties": {
    "addr:full":"30 Futura Rd Keysborough VIC 3173",
    "addr:housenumber":"30",
    "addr:postcode":"3173",
    "addr:street":"Futura Rd",
    "iso:country":"AU",
    "sg:address":"30 Futura Rd",
    "sg:city":"Keysborough",
    "sg:classifiers":[
        {
            "category":"Professional",
            "subcategory":"Detective & Security Services",
            "type":"Services"
        }
    ],
    "sg:phone":"+61 3 9798 4944",
    "sg:postcode":"3173",
    "sg:province":"VIC",
    "sg:tags":[
        "protective",
        "rustproofing"
    ],
    "wof:name":"AVS Rustlac",
    "wof:placetype":"venue"
},
  "geometry": {"coordinates":[145.18894958499999,-37.9861831665],"type":"Point"}
}