{
  "type": "Feature",
  "properties": {
    "addr:full":"2 Gracechurch Crs Leeming WA 6149",
    "addr:housenumber":"2",
    "addr:postcode":"6149",
    "addr:street":"Gracechurch Crs",
    "iso:country":"AU",
    "sg:address":"2 Gracechurch Crs",
    "sg:city":"Leeming",
    "sg:classifiers":[
        {
            "category":"Health Services",
            "subcategory":"Health Practitioner",
            "type":"Services"
        }
    ],
    "sg:phone":"+61 8 9332 9599",
    "sg:postcode":"6149",
    "sg:province":"WA",
    "sg:tags":[
        "pathologist",
        "speech"
    ],
    "wof:name":"Williams Sally",
    "wof:placetype":"venue"
},
  "geometry": {"coordinates":[115.858841,-32.078442],"type":"Point"}
}