{
  "type": "Feature",
  "properties": {
    "addr:full":"19 Wonga Rd Liverpool NSW 2170",
    "addr:housenumber":"19",
    "addr:postcode":"2170",
    "addr:street":"Wonga Rd",
    "iso:country":"AU",
    "sg:address":"19 Wonga Rd",
    "sg:city":"Liverpool",
    "sg:classifiers":[
        {
            "category":"Utilities",
            "subcategory":"Water",
            "type":"Services"
        }
    ],
    "sg:phone":"+61 1300 734 180",
    "sg:postcode":"2170",
    "sg:province":"NSW",
    "sg:tags":[
        "hot",
        "system"
    ],
    "wof:name":"Best Hot Water Services",
    "wof:placetype":"venue"
},
  "geometry": {"coordinates":[150.903808594,-33.9319915771],"type":"Point"}
}