{
  "type": "Feature",
  "properties": {
    "addr:full":"422 High St Northcote VIC 3070",
    "addr:housenumber":"422",
    "addr:postcode":"3070",
    "addr:street":"High St",
    "iso:country":"AU",
    "sg:address":"422 High St",
    "sg:city":"Northcote",
    "sg:classifiers":[
        {
            "category":"Building & Trades",
            "subcategory":"Plumbing",
            "type":"Services"
        }
    ],
    "sg:phone":"+61 3 9444 6181",
    "sg:postcode":"3070",
    "sg:province":"VIC",
    "sg:tags":[
        "plumber",
        "gasfitters"
    ],
    "wof:name":"JMB Drain Cleaning",
    "wof:placetype":"venue"
},
  "geometry": {"coordinates":[144.999359,-37.767342],"type":"Point"}
}