{
  "type": "Feature",
  "properties": {
    "iso:country":"AU",
    "sg:address":"30 Burke Rd",
    "sg:city":"Malvern East",
    "sg:classifiers":[
        {
            "category":"Health Services",
            "subcategory":"Health Practitioner",
            "type":"Services"
        }
    ],
    "sg:phone":"+61 3 9882 2443",
    "sg:postcode":"3145",
    "sg:province":"VIC",
    "sg:tags":[
        "psychologist"
    ],
    "wof:name":"Mindset Psychology",
    "wof:placetype":"venue"
},
  "geometry": {"coordinates":[145.04838562,-37.8757705688],"type":"Point"}
}