{
  "type": "Feature",
  "properties": {
    "iso:country":"AU",
    "sg:address":"7a Bessemer St",
    "sg:city":"Blacktown",
    "sg:classifiers":[
        {
            "category":"Building & Trades",
            "subcategory":"Construction",
            "type":"Services"
        }
    ],
    "sg:phone":"+61 1800 211 800",
    "sg:postcode":"2148",
    "sg:province":"NSW",
    "sg:tags":[
        "home",
        "air conditioning"
    ],
    "wof:name":"Bradway Engineering Pty Ltd",
    "wof:placetype":"venue"
},
  "geometry": {"coordinates":[150.90757751500001,-33.7570877075],"type":"Point"}
}