{
  "type": "Feature",
  "properties": {
    "addr:full":"Regal Crt Montmorency VIC 3094",
    "addr:postcode":"3094",
    "addr:street":"Regal Crt",
    "iso:country":"AU",
    "sg:address":"Regal Crt",
    "sg:city":"Montmorency",
    "sg:classifiers":[
        {
            "category":"Professional",
            "subcategory":"Accounting & Tax Preparation",
            "type":"Services"
        }
    ],
    "sg:phone":"+61 3 9439 8022",
    "sg:postcode":"3094",
    "sg:province":"VIC",
    "sg:tags":[
        "accountant",
        "auditor"
    ],
    "wof:name":"Brasier G L",
    "wof:placetype":"venue"
},
  "geometry": {"coordinates":[145.12945556599999,-37.7141075134],"type":"Point"}
}