{
  "type": "Feature",
  "properties": {
    "addr:full":"6 / 23 Terminus St Castle Hill NSW 2154",
    "addr:housenumber":"/ 23",
    "addr:postcode":"2154",
    "addr:street":"Terminus St",
    "iso:country":"AU",
    "sg:address":"6 / 23 Terminus St",
    "sg:city":"Castle Hill",
    "sg:classifiers":[
        {
            "category":"Shopping",
            "subcategory":"Stationery & Office Supplies",
            "type":"Retail Goods"
        }
    ],
    "sg:phone":"+61 2 9659 9779",
    "sg:postcode":"2154",
    "sg:province":"NSW",
    "sg:tags":[
        "equipment",
        "facsimile"
    ],
    "wof:name":"Castle Hill Business Machines",
    "wof:placetype":"venue"
},
  "geometry": {"coordinates":[151.005493164,-33.7344970703],"type":"Point"}
}