{
  "type": "Feature",
  "properties": {
    "addr:full":"Suite 35/ 24 Cavenagh St Darwin NT 0800",
    "addr:housenumber":"35 / 24",
    "addr:postcode":"nt 0800",
    "addr:street":"Cavenagh St",
    "iso:country":"AU",
    "sg:address":"Suite 35/ 24 Cavenagh St",
    "sg:city":"Darwin",
    "sg:classifiers":[
        {
            "category":"Banks & Credit Unions",
            "subcategory":"Investment Brokerage",
            "type":"Services"
        }
    ],
    "sg:phone":"+61 8 8981 6966",
    "sg:postcode":"0800",
    "sg:province":"NT",
    "sg:tags":[
        "debt",
        "collection"
    ],
    "wof:name":"A.B.I. Debt Collection",
    "wof:placetype":"venue"
},
  "geometry": {"coordinates":[130.843475342,-12.4625444412],"type":"Point"}
}