{
  "type": "Feature",
  "properties": {
    "addr:full":"79 Dean St Narara NSW 2250",
    "addr:housenumber":"79",
    "addr:postcode":"2250",
    "addr:street":"Dean St",
    "iso:country":"AU",
    "sg:address":"79 Dean St",
    "sg:city":"Narara",
    "sg:classifiers":[
        {
            "category":"Building & Trades",
            "subcategory":"Landscaping Services",
            "type":"Services"
        }
    ],
    "sg:phone":"+61 419 694 082",
    "sg:postcode":"2250",
    "sg:province":"NSW",
    "sg:tags":[
        "machinery",
        "road"
    ],
    "wof:name":"Gavenlock J D & J M Pty Ltd",
    "wof:placetype":"venue"
},
  "geometry": {"coordinates":[151.28549194300001,-33.4364013672],"type":"Point"}
}