{
  "type": "Feature",
  "properties": {
    "iso:country":"AU",
    "sg:address":"5 Riviera Crt",
    "sg:city":"Reservoir",
    "sg:classifiers":[
        {
            "category":"Building & Trades",
            "subcategory":"Construction",
            "type":"Services"
        }
    ],
    "sg:phone":"+61 3 9357 2861",
    "sg:postcode":"3073",
    "sg:province":"VIC",
    "sg:tags":[
        "concrete",
        "contractor"
    ],
    "wof:name":"Baccari Concrete Constructions Pty Ltd",
    "wof:placetype":"venue"
},
  "geometry": {"coordinates":[144.97950744600001,-37.694316864],"type":"Point"}
}