{
  "type": "Feature",
  "properties": {
    "addr:full":"4 Iluka St Black Rock VIC 3193",
    "addr:housenumber":"4",
    "addr:postcode":"3193",
    "addr:street":"Iluka St",
    "iso:country":"AU",
    "sg:address":"4 Iluka St",
    "sg:city":"Black Rock",
    "sg:classifiers":[
        {
            "category":"Building & Trades",
            "subcategory":"Construction",
            "type":"Services"
        }
    ],
    "sg:phone":"+61 3 9598 8221",
    "sg:postcode":"3193",
    "sg:province":"VIC",
    "sg:tags":[
        "contractor"
    ],
    "wof:name":"Map Developments Pty Ltd",
    "wof:placetype":"venue"
},
  "geometry": {"coordinates":[145.025878906,-37.9728965759],"type":"Point"}
}