{
  "type": "Feature",
  "properties": {
    "iso:country":"AU",
    "sg:address":"221 Peel St",
    "sg:city":"Tamworth",
    "sg:classifiers":[
        {
            "category":"Insurance",
            "subcategory":"Hazard Insurance",
            "type":"Services"
        }
    ],
    "sg:phone":"+61 2 6761 2344",
    "sg:postcode":"2340",
    "sg:province":"NSW",
    "sg:tags":[
        "loss",
        "adjuster",
        "assessor"
    ],
    "wof:name":"GAB Robins",
    "wof:placetype":"venue"
},
  "geometry": {"coordinates":[150.927124023,-31.0879077911],"type":"Point"}
}