{
  "type": "Feature",
  "properties": {
    "addr:full":"457 Mt Crosby Rd Anstead QLD 4070",
    "addr:housenumber":"457",
    "addr:postcode":"4070",
    "addr:street":"Mt Crosby Rd",
    "iso:country":"AU",
    "sg:address":"457 Mt Crosby Rd",
    "sg:city":"Anstead",
    "sg:classifiers":[
        {
            "category":"Education",
            "subcategory":"Kindergarten",
            "type":"Public Place"
        }
    ],
    "sg:phone":"+61 7 3202 5098",
    "sg:postcode":"4070",
    "sg:province":"QLD",
    "sg:tags":[
        "pre-schools"
    ],
    "wof:name":"Young Einstein Discovery Pre-School",
    "wof:placetype":"venue"
},
  "geometry": {"coordinates":[152.865402222,-27.5429573059],"type":"Point"}
}