{
  "type": "Feature",
  "properties": {
    "addr:full":"195 Sunnyside Drv Camden NSW 2570",
    "addr:housenumber":"195",
    "addr:postcode":"2570",
    "addr:street":"Sunnyside Drv",
    "iso:country":"AU",
    "sg:address":"195 Sunnyside Drv",
    "sg:city":"Camden",
    "sg:classifiers":[
        {
            "category":"Building & Trades",
            "subcategory":"Construction",
            "type":"Services"
        }
    ],
    "sg:phone":"+61 2 4655 8686",
    "sg:postcode":"2570",
    "sg:province":"NSW",
    "sg:tags":[
        "contractor"
    ],
    "wof:name":"Ebeling Constructions Pty Ltd",
    "wof:placetype":"venue"
},
  "geometry": {"coordinates":[150.67579650900001,-34.0297012329],"type":"Point"}
}