{
  "type": "Feature",
  "properties": {
    "addr:full":"84 Colburn Ave Victoria Point QLD 4165",
    "addr:housenumber":"84",
    "addr:postcode":"4165",
    "addr:street":"Colburn Ave",
    "iso:country":"AU",
    "sg:address":"84 Colburn Ave",
    "sg:city":"Victoria Point",
    "sg:classifiers":[
        {
            "category":"Building & Trades",
            "subcategory":"Construction",
            "type":"Services"
        }
    ],
    "sg:phone":"+61 7 3820 6645",
    "sg:postcode":"4165",
    "sg:province":"QLD",
    "sg:tags":[
        "plasterboard",
        "plasterer",
        "fixer"
    ],
    "wof:name":"Gary Jorgensen Plasterers",
    "wof:placetype":"venue"
},
  "geometry": {"coordinates":[153.30697631800001,-27.5859870911],"type":"Point"}
}