{
  "type": "Feature",
  "properties": {
    "iso:country":"AU",
    "sg:address":"3/2 Park Ave",
    "sg:city":"Coffs Harbour",
    "sg:classifiers":[
        {
            "category":"Food & Beverages",
            "subcategory":"Bakery",
            "type":"Retail Goods"
        }
    ],
    "sg:phone":"+61 2 6651 7555",
    "sg:postcode":"2450",
    "sg:province":"NSW",
    "sg:tags":[
        "cake",
        "shop",
        "pastry"
    ],
    "wof:name":"Cheesecake Shop The",
    "wof:placetype":"venue"
},
  "geometry": {"coordinates":[153.113266,-30.297417],"type":"Point"}
}