{
  "type": "Feature",
  "properties": {
    "addr:full":"49 Tradelink Rd Hillcrest QLD 4118",
    "addr:housenumber":"49",
    "addr:postcode":"4118",
    "addr:street":"Tradelink Rd",
    "iso:country":"AU",
    "sg:address":"49 Tradelink Rd",
    "sg:city":"Hillcrest",
    "sg:classifiers":[
        {
            "category":"Sports & Exercise",
            "subcategory":"Gym",
            "type":"Entertainment"
        }
    ],
    "sg:phone":"+61 7 3800 2788",
    "sg:postcode":"4118",
    "sg:province":"QLD",
    "sg:tags":[
        "health",
        "fitness"
    ],
    "wof:name":"GymCare Australia Pty Ltd",
    "wof:placetype":"venue"
},
  "geometry": {"coordinates":[153.03401184099999,-27.664812088],"type":"Point"}
}