{
  "type": "Feature",
  "properties": {
    "iso:country":"AU",
    "sg:address":"52 York St",
    "sg:city":"Launceston",
    "sg:classifiers":[
        {
            "category":"Health Services",
            "subcategory":"Dentist",
            "type":"Services"
        }
    ],
    "sg:phone":"+61 3 6334 0788",
    "sg:postcode":"7250",
    "sg:province":"TAS",
    "wof:name":"Leith Philip R",
    "wof:placetype":"venue"
},
  "geometry": {"coordinates":[147.14375305199999,-41.4354324341],"type":"Point"}
}