{
  "type": "Feature",
  "properties": {
    "iso:country":"AU",
    "sg:address":"Centreway, 44 Wingara Ave",
    "sg:city":"Keilor East",
    "sg:classifiers":[
        {
            "category":"Sports & Exercise",
            "subcategory":"Gym",
            "type":"Entertainment"
        }
    ],
    "sg:phone":"+61 3 9336 1600",
    "sg:postcode":"3033",
    "sg:province":"VIC",
    "sg:tags":[
        "health",
        "fitness"
    ],
    "wof:name":"Curves Keilor East",
    "wof:placetype":"venue"
},
  "geometry": {"coordinates":[144.867386,-37.733101],"type":"Point"}
}