{
  "type": "Feature",
  "properties": {
    "addr:full":"134 Old Geelong Rd Hoppers Crossing VIC 3029",
    "addr:housenumber":"134",
    "addr:postcode":"3029",
    "addr:street":"Old Geelong Rd",
    "iso:country":"AU",
    "sg:address":"134 Old Geelong Rd",
    "sg:city":"Hoppers Crossing",
    "sg:classifiers":[
        {
            "category":"Retail",
            "subcategory":"Auto Repair",
            "type":"Services"
        }
    ],
    "sg:phone":"+61 3 9749 4799",
    "sg:postcode":"3029",
    "sg:province":"VIC",
    "sg:tags":[
        "camper-trailers",
        "caravan",
        "servicing"
    ],
    "wof:name":"A & K Caravans Repairs",
    "wof:placetype":"venue"
},
  "geometry": {"coordinates":[144.711884,-37.877625],"type":"Point"}
}