{
  "type": "Feature",
  "properties": {
    "addr:full":"12 Treen St Balga WA 6061",
    "addr:housenumber":"12",
    "addr:postcode":"6061",
    "addr:street":"Treen St",
    "iso:country":"AU",
    "sg:address":"12 Treen St",
    "sg:city":"Balga",
    "sg:classifiers":[
        {
            "category":"Professional",
            "subcategory":"Accounting & Tax Preparation",
            "type":"Services"
        }
    ],
    "sg:phone":"+61 8 9343 1311",
    "sg:postcode":"6061",
    "sg:province":"WA",
    "sg:tags":[
        "consultant",
        "taxation"
    ],
    "wof:name":"Lindzay Baldsing & Associates Pty Ltd",
    "wof:placetype":"venue"
},
  "geometry": {"coordinates":[115.82563018800001,-31.8461818695],"type":"Point"}
}