{
  "type": "Feature",
  "properties": {
    "addr:full":"71 Learjet Drv Caboolture QLD 4510",
    "addr:housenumber":"71",
    "addr:postcode":"4510",
    "addr:street":"Learjet Drv",
    "iso:country":"AU",
    "sg:address":"71 Learjet Drv",
    "sg:city":"Caboolture",
    "sg:classifiers":[
        {
            "category":"Manufacturing",
            "subcategory":"Tools & Machinery",
            "type":"Manufacturing & Wholesale Goods"
        }
    ],
    "sg:phone":"+61 1300 738 520",
    "sg:postcode":"4510",
    "sg:province":"QLD",
    "sg:tags":[
        "earth",
        "excavating",
        "moving",
        "equipment"
    ],
    "wof:name":"Trackplus Sales & Rental",
    "wof:placetype":"venue"
},
  "geometry": {"coordinates":[152.97685200000001,-27.082794],"type":"Point"}
}