{
  "type": "Feature",
  "properties": {
    "addr:full":"130 Launceston St Lyons ACT 2606",
    "addr:housenumber":"130",
    "addr:postcode":"2606",
    "addr:street":"Launceston St",
    "iso:country":"AU",
    "sg:address":"130 Launceston St",
    "sg:city":"Lyons",
    "sg:classifiers":[
        {
            "category":"Building & Trades",
            "subcategory":"Construction",
            "type":"Services"
        }
    ],
    "sg:phone":"+61 2 6281 4136",
    "sg:postcode":"2606",
    "sg:province":"ACT",
    "sg:tags":[
        "contractor"
    ],
    "wof:name":"ABC Constructions",
    "wof:placetype":"venue"
},
  "geometry": {"coordinates":[149.07398986800001,-35.345199585],"type":"Point"}
}