{
  "type": "Feature",
  "properties": {
    "addr:full":"93 Goulburn St West Hobart TAS 7000",
    "addr:housenumber":"93",
    "addr:postcode":"7000",
    "addr:street":"Goulburn St",
    "iso:country":"AU",
    "sg:address":"93 Goulburn St",
    "sg:city":"West Hobart",
    "sg:classifiers":[
        {
            "category":"Fast Food",
            "type":"Food & Drink"
        }
    ],
    "sg:phone":"+61 3 6234 2155",
    "sg:postcode":"7000",
    "sg:province":"TAS",
    "sg:tags":[
        "away",
        "take"
    ],
    "wof:name":"Jean-Pascal Patisserie",
    "wof:placetype":"venue"
},
  "geometry": {"coordinates":[147.319259644,-42.8865776062],"type":"Point"}
}