{
  "type": "Feature",
  "properties": {
    "iso:country":"AU",
    "sg:address":"Shp 10/ 2185 Point Nepean Rd",
    "sg:city":"Rye",
    "sg:classifiers":[
        {
            "category":"Personal",
            "subcategory":"Beauty Salon",
            "type":"Services"
        }
    ],
    "sg:phone":"+61 3 5985 3639",
    "sg:postcode":"3941",
    "sg:province":"VIC",
    "wof:name":"Purrfect Wax",
    "wof:placetype":"venue"
},
  "geometry": {"coordinates":[144.82960510300001,-38.3711700439],"type":"Point"}
}