{
  "type": "Feature",
  "properties": {
    "iso:country":"AU",
    "sg:address":"129 Smart St",
    "sg:city":"Fairfield",
    "sg:classifiers":[
        {
            "category":"Personal",
            "type":"Services"
        }
    ],
    "sg:phone":"+61 2 9724 0770",
    "sg:postcode":"2165",
    "sg:province":"NSW",
    "sg:tags":[
        "reducing",
        "treatment",
        "weight"
    ],
    "wof:name":"Donaldson Norma",
    "wof:placetype":"venue"
},
  "geometry": {"coordinates":[150.948654175,-33.8644714355],"type":"Point"}
}