{
  "type": "Feature",
  "properties": {
    "addr:full":"1451 Sandgate Rd Nundah QLD 4012",
    "addr:housenumber":"1451",
    "addr:postcode":"4012",
    "addr:street":"Sandgate Rd",
    "iso:country":"AU",
    "sg:address":"1451 Sandgate Rd",
    "sg:city":"Nundah",
    "sg:classifiers":[
        {
            "category":"Professional",
            "subcategory":"Accounting & Tax Preparation",
            "type":"Services"
        }
    ],
    "sg:phone":"+61 7 3266 4122",
    "sg:postcode":"4012",
    "sg:province":"QLD",
    "sg:tags":[
        "consultant",
        "taxation"
    ],
    "wof:name":"H&R Block",
    "wof:placetype":"venue"
},
  "geometry": {"coordinates":[153.05943298299999,-27.3977603912],"type":"Point"}
}