{
  "type": "Feature",
  "properties": {
    "addr:full":"Shp 4/ 10 West Market St Richmond NSW 2753",
    "addr:housenumber":"/ 10",
    "addr:postcode":"2753",
    "addr:street":"West Market St",
    "iso:country":"AU",
    "sg:address":"Shp 4/ 10 West Market St",
    "sg:city":"Richmond",
    "sg:classifiers":[
        {
            "category":"Shopping",
            "subcategory":"Baby Store",
            "type":"Retail Goods"
        }
    ],
    "sg:phone":"+61 2 4588 5560",
    "sg:postcode":"2753",
    "sg:province":"NSW",
    "sg:tags":[
        "children's",
        "wear"
    ],
    "wof:name":"The Kids Cupboard",
    "wof:placetype":"venue"
},
  "geometry": {"coordinates":[150.75091552699999,-33.59608078],"type":"Point"}
}