{
  "type": "Feature",
  "properties": {
    "addr:full":"13 Casserly Crs Salisbury Heights SA 5109",
    "addr:housenumber":"13",
    "addr:postcode":"5109",
    "addr:street":"Casserly Crs",
    "iso:country":"AU",
    "sg:address":"13 Casserly Crs",
    "sg:city":"Salisbury Heights",
    "sg:classifiers":[
        {
            "category":"Professional",
            "subcategory":"Art Services",
            "type":"Services"
        }
    ],
    "sg:phone":"+61 8 8250 5489",
    "sg:postcode":"5109",
    "sg:province":"SA",
    "sg:tags":[
        "decorator",
        "painter"
    ],
    "wof:name":"Ellis Kevin P",
    "wof:placetype":"venue"
},
  "geometry": {"coordinates":[138.67491149899999,-34.7659492493],"type":"Point"}
}