{
  "type": "Feature",
  "properties": {
    "addr:full":"5 Wunda Rd Concord West NSW 2138",
    "addr:housenumber":"5",
    "addr:postcode":"2138",
    "addr:street":"Wunda Rd",
    "iso:country":"AU",
    "sg:address":"5 Wunda Rd",
    "sg:city":"Concord West",
    "sg:classifiers":[
        {
            "category":"Real Estate",
            "subcategory":"Real Estate Operator",
            "type":"Services"
        }
    ],
    "sg:phone":"+61 414 736 393",
    "sg:postcode":"2138",
    "sg:province":"NSW",
    "sg:tags":[
        "concrete",
        "pumping"
    ],
    "wof:name":"Quick Concrete Pumping",
    "wof:placetype":"venue"
},
  "geometry": {"coordinates":[151.08888244600001,-33.8450012207],"type":"Point"}
}