{
  "type": "Feature",
  "properties": {
    "addr:full":"31 Market St Sydney NSW 2000",
    "addr:housenumber":"31",
    "addr:postcode":"2000",
    "addr:street":"Market St",
    "iso:country":"AU",
    "sg:address":"31 Market St",
    "sg:city":"Sydney",
    "sg:classifiers":[
        {
            "category":"Shopping",
            "subcategory":"Clothing, Apparel, & Fashions",
            "type":"Retail Goods"
        }
    ],
    "sg:phone":"+61 2 9262 9551",
    "sg:postcode":"2000",
    "sg:province":"NSW",
    "sg:tags":[
        "menswear"
    ],
    "wof:name":"Val Parks Fine Clothing For Men",
    "wof:placetype":"venue"
},
  "geometry": {"coordinates":[151.204620361,-33.8726501465],"type":"Point"}
}