{
  "type": "Feature",
  "properties": {
    "addr:full":"Dysons La Ulverstone TAS 7315",
    "addr:postcode":"7315",
    "iso:country":"AU",
    "sg:address":"Dysons La",
    "sg:city":"Ulverstone",
    "sg:classifiers":[
        {
            "category":"Building & Trades",
            "subcategory":"Construction",
            "type":"Services"
        }
    ],
    "sg:phone":"+61 3 6425 9557",
    "sg:postcode":"7315",
    "sg:province":"TAS",
    "sg:tags":[
        "contractor"
    ],
    "wof:name":"Jerzyk C J & T M",
    "wof:placetype":"venue"
},
  "geometry": {"coordinates":[146.18980407699999,-41.1594619751],"type":"Point"}
}