{
  "type": "Feature",
  "properties": {
    "addr:full":"43 Reiby St Ulverstone TAS 7315",
    "addr:housenumber":"43",
    "addr:postcode":"7315",
    "addr:street":"Reiby St",
    "iso:country":"AU",
    "sg:address":"43 Reiby St",
    "sg:city":"Ulverstone",
    "sg:classifiers":[
        {
            "category":"Cafe",
            "type":"Food & Drink"
        }
    ],
    "sg:phone":"+61 3 6425 7222",
    "sg:postcode":"7315",
    "sg:province":"TAS",
    "wof:name":"Smileys Coffee Lounge",
    "wof:placetype":"venue"
},
  "geometry": {"coordinates":[146.17193603499999,-41.1571846008],"type":"Point"}
}