{
  "type": "Feature",
  "properties": {
    "addr:full":"7 Cottonwood Pl O&#039;Connor WA 6163",
    "addr:housenumber":"7",
    "addr:postcode":"6163",
    "addr:street":"Cottonwood Pl O &",
    "iso:country":"AU",
    "sg:address":"7 Cottonwood Pl",
    "sg:city":"O&#039;Connor",
    "sg:classifiers":[
        {
            "category":"Shopping",
            "subcategory":"Mobile Phones",
            "type":"Retail Goods"
        }
    ],
    "sg:phone":"+61 413 833 188",
    "sg:postcode":"6163",
    "sg:province":"WA",
    "sg:tags":[
        "telephone",
        "accessory"
    ],
    "wof:name":"In communication",
    "wof:placetype":"venue"
},
  "geometry": {"coordinates":[115.802353,-32.063557],"type":"Point"}
}