{
  "type": "Feature",
  "properties": {
    "iso:country":"AU",
    "sg:address":"2- 6 Randolf Crt",
    "sg:city":"Templestowe Lower",
    "sg:classifiers":[
        {
            "category":"Home & Garden",
            "subcategory":"Furniture",
            "type":"Retail Goods"
        }
    ],
    "sg:phone":"+61 3 9852 3266",
    "sg:postcode":"3107",
    "sg:province":"VIC",
    "sg:tags":[
        "repair",
        "restoration"
    ],
    "wof:name":"Furniture Service Bureau Kew Pty Ltd",
    "wof:placetype":"venue"
},
  "geometry": {"coordinates":[145.11143493599999,-37.7583999634],"type":"Point"}
}