{
  "type": "Feature",
  "properties": {
    "addr:full":"Chifley Rd Lithgow NSW 2790",
    "addr:postcode":"2790",
    "addr:street":"Chifley Rd",
    "iso:country":"AU",
    "sg:address":"Chifley Rd",
    "sg:city":"Lithgow",
    "sg:classifiers":[
        {
            "category":"Utilities",
            "subcategory":"Water",
            "type":"Services"
        }
    ],
    "sg:phone":"+61 2 6351 3174",
    "sg:postcode":"2790",
    "sg:province":"NSW",
    "sg:tags":[
        "hot",
        "system"
    ],
    "wof:name":"R & K Gas Supplies",
    "wof:placetype":"venue"
},
  "geometry": {"coordinates":[150.16595459000001,-33.4791183472],"type":"Point"}
}