{
  "type": "Feature",
  "properties": {
    "iso:country":"AU",
    "sg:address":"125 Albert Rd",
    "sg:city":"Moonah",
    "sg:classifiers":[
        {
            "category":"Home & Garden",
            "subcategory":"Building Materials",
            "type":"Retail Goods"
        }
    ],
    "sg:phone":"+61 3 6278 8887",
    "sg:postcode":"7009",
    "sg:province":"TAS",
    "sg:tags":[
        "shutter",
        "roller",
        "grille"
    ],
    "wof:name":"Taylor Screens",
    "wof:placetype":"venue"
},
  "geometry": {"coordinates":[147.309356689,-42.8488121033],"type":"Point"}
}