{
  "type": "Feature",
  "properties": {
    "iso:country":"AU",
    "sg:address":"29 Hawkins Pl",
    "sg:city":"Emerald",
    "sg:classifiers":[
        {
            "category":"Professional",
            "type":"Services"
        }
    ],
    "sg:phone":"+61 7 4982 2301",
    "sg:postcode":"4720",
    "sg:province":"QLD",
    "sg:tags":[
        "courier"
    ],
    "wof:name":"Emerald Couriers",
    "wof:placetype":"venue"
},
  "geometry": {"coordinates":[148.154144,-23.533913],"type":"Point"}
}