{
  "type": "Feature",
  "properties": {
    "addr:full":"51 Bosworth St Richmond NSW 2753",
    "addr:housenumber":"51",
    "addr:postcode":"2753",
    "addr:street":"Bosworth St",
    "iso:country":"AU",
    "sg:address":"51 Bosworth St",
    "sg:city":"Richmond",
    "sg:classifiers":[
        {
            "category":"Travel",
            "subcategory":"Hotels & Motels",
            "type":"Entertainment"
        }
    ],
    "sg:phone":"+61 2 4578 0520",
    "sg:postcode":"2753",
    "sg:province":"NSW",
    "wof:name":"The New Inn Motel",
    "wof:placetype":"venue"
},
  "geometry": {"coordinates":[150.74621582,-33.5977058411],"type":"Point"}
}