{
  "type": "Feature",
  "properties": {
    "iso:country":"AU",
    "sg:address":"667 Boundary Rd",
    "sg:city":"Richlands",
    "sg:classifiers":[
        {
            "category":"Manufacturing",
            "subcategory":"Tools & Machinery",
            "type":"Manufacturing & Wholesale Goods"
        }
    ],
    "sg:phone":"+61 7 3375 1431",
    "sg:postcode":"4077",
    "sg:province":"QLD",
    "sg:tags":[
        "fastener",
        "industrial"
    ],
    "wof:name":"Hydranut Pty Ltd",
    "wof:placetype":"venue"
},
  "geometry": {"coordinates":[152.95504760700001,-27.5783576965],"type":"Point"}
}