{
  "type": "Feature",
  "properties": {
    "iso:country":"AU",
    "sg:address":"43 Regent St",
    "sg:city":"Regents Park",
    "sg:classifiers":[
        {
            "category":"Education",
            "subcategory":"School",
            "type":"Public Place"
        }
    ],
    "sg:phone":"+61 2 9644 9083",
    "sg:postcode":"2143",
    "sg:province":"NSW",
    "wof:name":"St Peter Chanel Primary School",
    "wof:placetype":"venue"
},
  "geometry": {"coordinates":[151.02687072800001,-33.8796958923],"type":"Point"}
}