{
  "type": "Feature",
  "properties": {
    "iso:country":"AU",
    "sg:address":"6 Lake Vista Crs",
    "sg:city":"Forster",
    "sg:classifiers":[
        {
            "category":"Home & Garden",
            "subcategory":"Carpets & Floor Coverings",
            "type":"Retail Goods"
        }
    ],
    "sg:phone":"+61 2 6554 8316",
    "sg:postcode":"2428",
    "sg:province":"NSW",
    "sg:tags":[
        "tile",
        "wall",
        "layer"
    ],
    "wof:name":"Goodwin Phil",
    "wof:placetype":"venue"
},
  "geometry": {"coordinates":[152.513397,-32.18219],"type":"Point"}
}