{
  "type": "Feature",
  "properties": {
    "addr:full":"46 Williamson Rd Maribyrnong VIC 3032",
    "addr:housenumber":"46",
    "addr:postcode":"3032",
    "addr:street":"Williamson Rd",
    "iso:country":"AU",
    "sg:address":"46 Williamson Rd",
    "sg:city":"Maribyrnong",
    "sg:classifiers":[
        {
            "category":"Health Services",
            "subcategory":"Health Practitioner",
            "type":"Services"
        }
    ],
    "sg:phone":"+61 3 9318 7080",
    "sg:postcode":"3032",
    "sg:province":"VIC",
    "sg:tags":[
        "acupuncture"
    ],
    "wof:name":"A. Acupuncture & Chiropractic Centres",
    "wof:placetype":"venue"
},
  "geometry": {"coordinates":[144.87927199999999,-37.774605],"type":"Point"}
}