{
  "type": "Feature",
  "properties": {
    "addr:full":"42 Mearns St Fairfield QLD 4103",
    "addr:housenumber":"42",
    "addr:postcode":"4103",
    "addr:street":"Mearns St",
    "iso:country":"AU",
    "sg:address":"42 Mearns St",
    "sg:city":"Fairfield",
    "sg:classifiers":[
        {
            "category":"Sports & Exercise",
            "subcategory":"Race Track",
            "type":"Entertainment"
        }
    ],
    "sg:phone":"+61 7 3844 8507",
    "sg:postcode":"4103",
    "sg:province":"QLD",
    "sg:tags":[
        "club",
        "racing",
        "motor"
    ],
    "wof:name":"Australian Karting Assn (Qld) Inc.",
    "wof:placetype":"venue"
},
  "geometry": {"coordinates":[153.027435303,-27.5068397522],"type":"Point"}
}