{
  "type": "Feature",
  "properties": {
    "addr:full":"12 Luisa Ave Dandenong South VIC 3175",
    "addr:housenumber":"12",
    "addr:postcode":"3175",
    "addr:street":"Luisa Ave",
    "iso:country":"AU",
    "sg:address":"12 Luisa Ave",
    "sg:city":"Dandenong South",
    "sg:classifiers":[
        {
            "category":"Wholesale",
            "subcategory":"Painting Supplies",
            "type":"Manufacturing & Wholesale Goods"
        }
    ],
    "sg:phone":"+61 3 9768 2600",
    "sg:postcode":"3175",
    "sg:province":"VIC",
    "sg:tags":[
        "product",
        "polyurethane"
    ],
    "wof:name":"Hetin Foam Industries Pty Ltd",
    "wof:placetype":"venue"
},
  "geometry": {"coordinates":[145.203582764,-38.0352554321],"type":"Point"}
}