{
  "type": "Feature",
  "properties": {
    "iso:country":"AU",
    "sg:address":"22 Livingstone St",
    "sg:city":"Ivanhoe",
    "sg:classifiers":[
        {
            "category":"Health Services",
            "subcategory":"Doctor",
            "type":"Services"
        }
    ],
    "sg:phone":"+61 3 9499 1245",
    "sg:postcode":"3079",
    "sg:province":"VIC",
    "sg:tags":[
        "medical",
        "practitioner"
    ],
    "wof:name":"Adami Catherine Dr",
    "wof:placetype":"venue"
},
  "geometry": {"coordinates":[145.040405273,-37.7677154541],"type":"Point"}
}