{
  "type": "Feature",
  "properties": {
    "addr:full":"245 Warrigal Rd Cheltenham VIC 3192",
    "addr:housenumber":"245",
    "addr:postcode":"3192",
    "addr:street":"Warrigal Rd",
    "iso:country":"AU",
    "sg:address":"245 Warrigal Rd",
    "sg:city":"Cheltenham",
    "sg:classifiers":[
        {
            "category":"Retail",
            "subcategory":"Car Wash",
            "type":"Services"
        }
    ],
    "sg:phone":"+61 419 159 679",
    "sg:postcode":"3192",
    "sg:province":"VIC",
    "sg:tags":[
        "truck",
        "cleaning"
    ],
    "wof:name":"Original Detailing",
    "wof:placetype":"venue"
},
  "geometry": {"coordinates":[145.074295044,-37.9657211304],"type":"Point"}
}