{
  "type": "Feature",
  "properties": {
    "addr:full":"Moseley Drv Boambee NSW 2450",
    "addr:postcode":"2450",
    "addr:street":"Moseley Drv",
    "iso:country":"AU",
    "sg:address":"Moseley Drv",
    "sg:city":"Boambee",
    "sg:classifiers":[
        {
            "category":"Building & Trades",
            "subcategory":"Construction",
            "type":"Services"
        }
    ],
    "sg:phone":"+61 2 6658 4036",
    "sg:postcode":"2450",
    "sg:province":"NSW",
    "sg:tags":[
        "builder",
        "designer",
        "room",
        "cool"
    ],
    "wof:name":"Coolrite Coolroom Manufacturing",
    "wof:placetype":"venue"
},
  "geometry": {"coordinates":[153.07916299999999,-30.346451],"type":"Point"}
}