{
  "type": "Feature",
  "properties": {
    "addr:full":"Cnr Kingsway & Kiora Rd Miranda NSW 2228",
    "addr:postcode":"2228",
    "addr:street":"Cnr Kingsway & Kiora Rd",
    "iso:country":"AU",
    "sg:address":"Cnr Kingsway & Kiora Rd",
    "sg:city":"Miranda",
    "sg:classifiers":[
        {
            "category":"Shopping",
            "subcategory":"Crafts & Fabrics",
            "type":"Retail Goods"
        }
    ],
    "sg:phone":"+61 2 9525 5797",
    "sg:postcode":"2228",
    "sg:province":"NSW",
    "sg:tags":[
        "supply"
    ],
    "wof:name":"Vaggs Hobbies",
    "wof:placetype":"venue"
},
  "geometry": {"coordinates":[151.10328674300001,-34.0342102051],"type":"Point"}
}