{
  "type": "Feature",
  "properties": {
    "iso:country":"AU",
    "sg:address":"Man O Ross Hotel 35 Church St",
    "sg:city":"Ross",
    "sg:classifiers":[
        {
            "category":"Food & Beverages",
            "subcategory":"Liquor & Beverages",
            "type":"Retail Goods"
        }
    ],
    "sg:phone":"+61 3 6381 5445",
    "sg:postcode":"7209",
    "sg:province":"TAS",
    "sg:tags":[
        "store"
    ],
    "wof:name":"Liquorwise",
    "wof:placetype":"venue"
},
  "geometry": {"coordinates":[147.492371,-42.030636],"type":"Point"}
}