{
  "type": "Feature",
  "properties": {
    "addr:full":"7 Edward St Shepparton VIC 3630",
    "addr:housenumber":"7",
    "addr:postcode":"3630",
    "addr:street":"Edward St",
    "iso:country":"AU",
    "sg:address":"7 Edward St",
    "sg:city":"Shepparton",
    "sg:classifiers":[
        {
            "category":"Personal",
            "subcategory":"Massage",
            "type":"Services"
        }
    ],
    "sg:phone":"+61 3 5821 8300",
    "sg:postcode":"3630",
    "sg:province":"VIC",
    "sg:tags":[
        "therapy"
    ],
    "wof:name":"Black David R",
    "wof:placetype":"venue"
},
  "geometry": {"coordinates":[145.40237426799999,-36.3781852722],"type":"Point"}
}