{
  "type": "Feature",
  "properties": {
    "addr:full":"113- 115 Toorak Rd South Yarra VIC 3141",
    "addr:housenumber":"113 115",
    "addr:postcode":"3141",
    "addr:street":"Toorak Rd",
    "iso:country":"AU",
    "sg:address":"113- 115 Toorak Rd",
    "sg:city":"South Yarra",
    "sg:classifiers":[
        {
            "category":"Food & Beverages",
            "subcategory":"Liquor & Beverages",
            "type":"Retail Goods"
        }
    ],
    "sg:phone":"+61 3 9465 5155",
    "sg:postcode":"3141",
    "sg:province":"VIC",
    "sg:tags":[
        "store"
    ],
    "wof:name":"Cheeers",
    "wof:placetype":"venue"
},
  "geometry": {"coordinates":[144.990402222,-37.8386878967],"type":"Point"}
}