{
  "type": "Feature",
  "properties": {
    "addr:full":"305 Railway Rd Koo Wee Rup VIC 3981",
    "addr:housenumber":"305",
    "addr:postcode":"3981",
    "addr:street":"Railway Rd",
    "iso:country":"AU",
    "sg:address":"305 Railway Rd",
    "sg:city":"Koo Wee Rup",
    "sg:classifiers":[
        {
            "category":"Farming",
            "subcategory":"Farm",
            "type":"Manufacturing & Wholesale Goods"
        }
    ],
    "sg:phone":"+61 3 5997 1337",
    "sg:postcode":"3981",
    "sg:province":"VIC",
    "sg:tags":[
        "farmer"
    ],
    "wof:name":"Jeffery W P",
    "wof:placetype":"venue"
},
  "geometry": {"coordinates":[145.452224731,-38.1937522888],"type":"Point"}
}