{
  "type": "Feature",
  "properties": {
    "addr:full":"39 Irvine St Bayswater WA 6053",
    "addr:housenumber":"39",
    "addr:postcode":"6053",
    "addr:street":"Irvine St",
    "iso:country":"AU",
    "sg:address":"39 Irvine St",
    "sg:city":"Bayswater",
    "sg:classifiers":[
        {
            "category":"Autos & Motor Vehicles",
            "subcategory":"Automobile Sales",
            "type":"Retail Goods"
        }
    ],
    "sg:phone":"+61 8 9371 1515",
    "sg:postcode":"6053",
    "sg:province":"WA",
    "sg:tags":[
        "car",
        "used"
    ],
    "wof:name":"Great Eastern Auto's",
    "wof:placetype":"venue"
},
  "geometry": {"coordinates":[115.92079925500001,-31.9100437164],"type":"Point"}
}