{
  "type": "Feature",
  "properties": {
    "addr:full":"Suite 3 44 King St East Maitland NSW 2323",
    "addr:housenumber":"44",
    "addr:postcode":"2323",
    "addr:street":"King St",
    "iso:country":"AU",
    "sg:address":"Suite 3 44 King St",
    "sg:city":"East Maitland",
    "sg:classifiers":[
        {
            "category":"Health Services",
            "subcategory":"Doctor",
            "type":"Services"
        }
    ],
    "sg:phone":"+61 2 4933 9949",
    "sg:postcode":"2323",
    "sg:province":"NSW",
    "sg:tags":[
        "occupational",
        "safety"
    ],
    "wof:name":"Safety & Forensic Engineering Pty Ltd",
    "wof:placetype":"venue"
},
  "geometry": {"coordinates":[151.58851623499999,-32.748790741],"type":"Point"}
}