{
  "type": "Feature",
  "properties": {
    "addr:full":"Unit 1, 3 Myrtle St Botany NSW 2019",
    "addr:housenumber":"3",
    "addr:postcode":"2019",
    "addr:street":"Myrtle St",
    "iso:country":"AU",
    "sg:address":"Unit 1, 3 Myrtle St",
    "sg:city":"Botany",
    "sg:classifiers":[
        {
            "category":"Building & Trades",
            "subcategory":"Equipment Rental",
            "type":"Services"
        }
    ],
    "sg:phone":"+61 2 9666 8894",
    "sg:postcode":"2019",
    "sg:province":"NSW",
    "sg:tags":[
        "supply",
        "catering"
    ],
    "wof:name":"Catering Wholesalers P/L",
    "wof:placetype":"venue"
},
  "geometry": {"coordinates":[151.20234680199999,-33.9405860901],"type":"Point"}
}