{
  "type": "Feature",
  "properties": {
    "addr:full":"Cnr Mowbray Rd & Sydney St Chatswood NSW 2067",
    "addr:postcode":"2067",
    "addr:street":"Cnr Mowbray Rd & Sydney St",
    "iso:country":"AU",
    "sg:address":"Cnr Mowbray Rd & Sydney St",
    "sg:city":"Chatswood",
    "sg:classifiers":[
        {
            "category":"Arts & Performance",
            "subcategory":"Dance",
            "type":"Entertainment"
        }
    ],
    "sg:phone":"+61 2 9419 6984",
    "sg:postcode":"2067",
    "sg:province":"NSW",
    "sg:tags":[
        "theatrical",
        "ballet",
        "tuition"
    ],
    "wof:name":"Elizabeth McGirr School Of Ballet",
    "wof:placetype":"venue"
},
  "geometry": {"coordinates":[151.18669128400001,-33.8017120361],"type":"Point"}
}