{
  "type": "Feature",
  "properties": {
    "addr:full":"536 David St Albury NSW 2640",
    "addr:housenumber":"536",
    "addr:postcode":"2640",
    "addr:street":"David St",
    "iso:country":"AU",
    "sg:address":"536 David St",
    "sg:city":"Albury",
    "sg:classifiers":[
        {
            "category":"Education",
            "subcategory":"Music School",
            "type":"Public Place"
        }
    ],
    "sg:phone":"+61 2 6041 6644",
    "sg:postcode":"2640",
    "sg:province":"NSW",
    "sg:tags":[
        "choir",
        "bands",
        "orchestra"
    ],
    "wof:name":"Round Midnight Music",
    "wof:placetype":"venue"
},
  "geometry": {"coordinates":[146.921142578,-36.0799102783],"type":"Point"}
}