{
  "type": "Feature",
  "properties": {
    "addr:full":"16 Fisher Ave Pennant Hills NSW 2120",
    "addr:housenumber":"16",
    "addr:postcode":"2120",
    "addr:street":"Fisher Ave",
    "iso:country":"AU",
    "sg:address":"16 Fisher Ave",
    "sg:city":"Pennant Hills",
    "sg:classifiers":[
        {
            "category":"Health Services",
            "subcategory":"Doctor",
            "type":"Services"
        }
    ],
    "sg:phone":"+61 2 9980 9909",
    "sg:postcode":"2120",
    "sg:province":"NSW",
    "sg:tags":[
        "podiatrist"
    ],
    "wof:name":"Anderson Ann",
    "wof:placetype":"venue"
},
  "geometry": {"coordinates":[151.06906127900001,-33.7382316589],"type":"Point"}
}