{
  "type": "Feature",
  "properties": {
    "iso:country":"AU",
    "sg:address":"1509 Botany Rd",
    "sg:city":"Botany",
    "sg:classifiers":[
        {
            "category":"Banks & Credit Unions",
            "subcategory":"Investment Brokerage",
            "type":"Services"
        }
    ],
    "sg:phone":"+61 2 9316 8701",
    "sg:postcode":"2019",
    "sg:province":"NSW",
    "sg:tags":[
        "radiator",
        "motor"
    ],
    "wof:name":"Botany Auto Panel Beating & Radiators Pty Ltd",
    "wof:placetype":"venue"
},
  "geometry": {"coordinates":[151.197341919,-33.9493522644],"type":"Point"}
}