{
  "type": "Feature",
  "properties": {
    "addr:full":"82 Prospect Rd Prospect SA 5082",
    "addr:housenumber":"82",
    "addr:postcode":"5082",
    "addr:street":"Prospect Rd",
    "iso:country":"AU",
    "sg:address":"82 Prospect Rd",
    "sg:city":"Prospect",
    "sg:classifiers":[
        {
            "category":"Mining & Drilling",
            "type":"Manufacturing & Wholesale Goods"
        }
    ],
    "sg:phone":"+61 8 8269 7188",
    "sg:postcode":"5082",
    "sg:province":"SA",
    "sg:tags":[
        "geologist"
    ],
    "wof:name":"Teale & Associates Pty Ltd",
    "wof:placetype":"venue"
},
  "geometry": {"coordinates":[138.594024658,-34.8896217346],"type":"Point"}
}