{
  "type": "Feature",
  "properties": {
    "addr:full":"509 St Kilda Rd Melbourne VIC 3000",
    "addr:housenumber":"509",
    "addr:postcode":"3000",
    "addr:street":"St Kilda Rd",
    "iso:country":"AU",
    "sg:address":"509 St Kilda Rd",
    "sg:city":"Melbourne",
    "sg:classifiers":[
        {
            "category":"Banks & Credit Unions",
            "subcategory":"Investment Brokerage",
            "type":"Services"
        }
    ],
    "sg:phone":"+61 1300 659 659",
    "sg:postcode":"3000",
    "sg:province":"VIC",
    "wof:name":"Navigator",
    "wof:placetype":"venue"
},
  "geometry": {"coordinates":[144.97865295400001,-37.8435707092],"type":"Point"}
}