{
  "type": "Feature",
  "properties": {
    "addr:full":"Anzac Pde Gwabegar NSW 2356",
    "addr:postcode":"2356",
    "addr:street":"Anzac",
    "iso:country":"AU",
    "sg:address":"Anzac Pde",
    "sg:city":"Gwabegar",
    "sg:classifiers":[
        {
            "category":"Government",
            "subcategory":"Post Office",
            "type":"Public Place"
        }
    ],
    "sg:phone":"+61 2 6843 6250",
    "sg:postcode":"2356",
    "sg:province":"NSW",
    "sg:tags":[
        "postal"
    ],
    "wof:name":"Australia Post",
    "wof:placetype":"venue"
},
  "geometry": {"coordinates":[148.97166442899999,-30.6091766357],"type":"Point"}
}