{
  "type": "Feature",
  "properties": {
    "addr:full":"GPO Box 2692 Brisbane QLD 4001",
    "addr:postcode":"4001",
    "iso:country":"AU",
    "sg:address":"GPO Box 2692",
    "sg:city":"Brisbane",
    "sg:classifiers":[
        {
            "category":"Professional",
            "subcategory":"Business Services",
            "type":"Services"
        }
    ],
    "sg:phone":"+61 7 3821 3018",
    "sg:postcode":"4001",
    "sg:province":"QLD",
    "sg:tags":[
        "broker"
    ],
    "wof:name":"Peter Davison Business Broker",
    "wof:placetype":"venue"
},
  "geometry": {"coordinates":[152.88862609899999,-27.5975971222],"type":"Point"}
}