{
  "type": "Feature",
  "properties": {
    "addr:full":"19 Castles Pl Melba ACT 2615",
    "addr:housenumber":"19",
    "addr:postcode":"2615",
    "addr:street":"Castles Pl Melba",
    "iso:country":"AU",
    "sg:address":"19 Castles Pl",
    "sg:city":"Melba",
    "sg:classifiers":[
        {
            "category":"Professional",
            "subcategory":"Computer Services",
            "type":"Services"
        }
    ],
    "sg:phone":"+61 2 6258 1061",
    "sg:postcode":"2615",
    "sg:province":"ACT",
    "sg:tags":[
        "repairs",
        "upgrade",
        "equipment"
    ],
    "wof:name":"Bytech Computer Services",
    "wof:placetype":"venue"
},
  "geometry": {"coordinates":[149.050613403,-35.2071151733],"type":"Point"}
}