{
  "type": "Feature",
  "properties": {
    "addr:full":"189 Springvale Rd Springvale VIC 3171",
    "addr:housenumber":"189",
    "addr:postcode":"3171",
    "addr:street":"Springvale Rd",
    "iso:country":"AU",
    "sg:address":"189 Springvale Rd",
    "sg:city":"Springvale",
    "sg:classifiers":[
        {
            "category":"Real Estate",
            "subcategory":"Architect",
            "type":"Services"
        }
    ],
    "sg:phone":"+61 3 9548 1807",
    "sg:postcode":"3171",
    "sg:province":"VIC",
    "sg:tags":[
        "building",
        "designer"
    ],
    "wof:name":"GNC & Associates",
    "wof:placetype":"venue"
},
  "geometry": {"coordinates":[145.153640747,-37.9457778931],"type":"Point"}
}