{
  "type": "Feature",
  "properties": {
    "addr:full":"113 Neptune St Maryborough QLD 4650",
    "addr:housenumber":"113",
    "addr:postcode":"4650",
    "addr:street":"Neptune St",
    "iso:country":"AU",
    "sg:address":"113 Neptune St",
    "sg:city":"Maryborough",
    "sg:classifiers":[
        {
            "category":"Retail",
            "subcategory":"Storage",
            "type":"Services"
        }
    ],
    "sg:phone":"+61 427 232 325",
    "sg:postcode":"4650",
    "sg:province":"QLD",
    "sg:tags":[
        "removal",
        "furniture"
    ],
    "wof:name":"Maryborough Self Storage",
    "wof:placetype":"venue"
},
  "geometry": {"coordinates":[152.68635599999999,-25.524019],"type":"Point"}
}