{
  "type": "Feature",
  "properties": {
    "addr:full":"Shop Ap14 Smith St Mall Darwin NT 0800",
    "addr:housenumber":"ap14",
    "addr:postcode":"nt 0800",
    "addr:street":"Smith St Mall",
    "iso:country":"AU",
    "sg:address":"Shop Ap14 Smith St Mall",
    "sg:city":"Darwin",
    "sg:classifiers":[
        {
            "category":"Shopping",
            "subcategory":"Music",
            "type":"Retail Goods"
        }
    ],
    "sg:phone":"+61 8 8981 7136",
    "sg:postcode":"0800",
    "sg:province":"NT",
    "sg:tags":[
        "store"
    ],
    "wof:name":"Leading Edge Music",
    "wof:placetype":"venue"
},
  "geometry": {"coordinates":[130.84231567399999,-12.4620399475],"type":"Point"}
}