{
  "type": "Feature",
  "properties": {
    "addr:full":"Morningside Central Shopping Centre Shop 10, 25 Junction Rd Morningside QLD 4170",
    "addr:housenumber":"shop 10 25",
    "addr:postcode":"4170",
    "addr:street":"Junction Rd",
    "iso:country":"AU",
    "sg:address":"Morningside Central Shopping Centre Shop 10, 25 Junction Rd",
    "sg:city":"Morningside",
    "sg:classifiers":[
        {
            "category":"Cafe",
            "type":"Food & Drink"
        }
    ],
    "sg:phone":"+61 7 3399 1772",
    "sg:postcode":"4170",
    "sg:province":"QLD",
    "wof:name":"Morningside Florist & Cafe",
    "wof:placetype":"venue"
},
  "geometry": {"coordinates":[153.07882690400001,-27.4668121338],"type":"Point"}
}