{
  "type": "Feature",
  "properties": {
    "iso:country":"AU",
    "sg:address":"Suite 3/ 307 Condamine St",
    "sg:city":"Manly Vale",
    "sg:classifiers":[
        {
            "category":"Health Services",
            "subcategory":"Chiropractor",
            "type":"Services"
        }
    ],
    "sg:phone":"+61 2 9907 7139",
    "sg:postcode":"2093",
    "sg:province":"NSW",
    "wof:name":"Windsham Ross",
    "wof:placetype":"venue"
},
  "geometry": {"coordinates":[151.26695251500001,-33.784526825],"type":"Point"}
}