{
  "type": "Feature",
  "properties": {
    "addr:full":"77 Racecourse Rd Ascot QLD 4007",
    "addr:housenumber":"77",
    "addr:postcode":"4007",
    "addr:street":"Racecourse Rd",
    "iso:country":"AU",
    "sg:address":"77 Racecourse Rd",
    "sg:city":"Ascot",
    "sg:classifiers":[
        {
            "category":"Food & Beverages",
            "subcategory":"Liquor & Beverages",
            "type":"Retail Goods"
        }
    ],
    "sg:phone":"+61 7 3868 2421",
    "sg:postcode":"4007",
    "sg:province":"QLD",
    "sg:tags":[
        "store"
    ],
    "wof:name":"The Grape Liquor Market",
    "wof:placetype":"venue"
},
  "geometry": {"coordinates":[153.06500199999999,-27.435863],"type":"Point"}
}