{
  "type": "Feature",
  "properties": {
    "addr:full":"66 Moore St Liverpool NSW 2170",
    "addr:housenumber":"66",
    "addr:postcode":"2170",
    "addr:street":"Moore St",
    "iso:country":"AU",
    "sg:address":"66 Moore St",
    "sg:city":"Liverpool",
    "sg:classifiers":[
        {
            "category":"Personal",
            "subcategory":"Beauty Salon",
            "type":"Services"
        }
    ],
    "sg:phone":"+61 2 9822 5746",
    "sg:postcode":"2170",
    "sg:province":"NSW",
    "sg:tags":[
        "hairdresser"
    ],
    "wof:name":"Try Africa Look Salon",
    "wof:placetype":"venue"
},
  "geometry": {"coordinates":[150.92425537099999,-33.9226913452],"type":"Point"}
}