{
  "type": "Feature",
  "properties": {
    "addr:full":"218 Swensons Rd Mt Crosby QLD 4306",
    "addr:housenumber":"218",
    "addr:postcode":"4306",
    "addr:street":"Swensons Rd",
    "iso:country":"AU",
    "sg:address":"218 Swensons Rd",
    "sg:city":"Mt Crosby",
    "sg:classifiers":[
        {
            "category":"Personal",
            "type":"Services"
        }
    ],
    "sg:phone":"+61 7 3013 3115",
    "sg:postcode":"4306",
    "sg:province":"QLD",
    "sg:tags":[
        "reducing",
        "treatment",
        "weight"
    ],
    "wof:name":"Independent Herbalife Distributor",
    "wof:placetype":"venue"
},
  "geometry": {"coordinates":[152.8334198,-27.520275116],"type":"Point"}
}