{
  "type": "Feature",
  "properties": {
    "addr:full":"5 Thuringowa Drv Kirwan QLD 4817",
    "addr:housenumber":"5",
    "addr:postcode":"4817",
    "addr:street":"Thuringowa Drv",
    "iso:country":"AU",
    "sg:address":"5 Thuringowa Drv",
    "sg:city":"Kirwan",
    "sg:classifiers":[
        {
            "category":"Health Services",
            "subcategory":"Doctor",
            "type":"Services"
        }
    ],
    "sg:phone":"+61 7 4773 6133",
    "sg:postcode":"4817",
    "sg:province":"QLD",
    "sg:tags":[
        "medical",
        "practitioner"
    ],
    "wof:name":"Fleming Fiona Dr",
    "wof:placetype":"venue"
},
  "geometry": {"coordinates":[146.72877500000001,-19.316439],"type":"Point"}
}