{
  "type": "Feature",
  "properties": {
    "addr:full":"Suite 6 / 147 Ward St North Adelaide SA 5006",
    "addr:housenumber":"/ 147",
    "addr:postcode":"5006",
    "addr:street":"Ward St",
    "iso:country":"AU",
    "sg:address":"Suite 6 / 147 Ward St",
    "sg:city":"North Adelaide",
    "sg:classifiers":[
        {
            "category":"Health Services",
            "subcategory":"Doctor",
            "type":"Services"
        }
    ],
    "sg:phone":"+61 8 8267 5480",
    "sg:postcode":"5006",
    "sg:province":"SA",
    "sg:tags":[
        "medical",
        "practitioner"
    ],
    "wof:name":"Bennett C Kim Dr",
    "wof:placetype":"venue"
},
  "geometry": {"coordinates":[138.59573364299999,-34.9090194702],"type":"Point"}
}