{
  "type": "Feature",
  "properties": {
    "iso:country":"AU",
    "sg:address":"16 Church St",
    "sg:city":"Benalla",
    "sg:classifiers":[
        {
            "category":"Retail",
            "subcategory":"Veterinary Services",
            "type":"Services"
        }
    ],
    "sg:phone":"+61 3 5762 2788",
    "sg:postcode":"3672",
    "sg:province":"VIC",
    "sg:tags":[
        "surgeon"
    ],
    "wof:name":"Benalla Veterinary Clinic",
    "wof:placetype":"venue"
},
  "geometry": {"coordinates":[145.981934,-36.550056],"type":"Point"}
}