{
  "type": "Feature",
  "properties": {
    "addr:full":"7 Hume Rd Smithfield NSW 2164",
    "addr:housenumber":"7",
    "addr:postcode":"2164",
    "addr:street":"Hume Rd",
    "iso:country":"AU",
    "sg:address":"7 Hume Rd",
    "sg:city":"Smithfield",
    "sg:classifiers":[
        {
            "category":"Manufacturing",
            "subcategory":"Motor Vehicles & Parts",
            "type":"Manufacturing & Wholesale Goods"
        }
    ],
    "sg:phone":"+61 1300 796 900",
    "sg:postcode":"2164",
    "sg:province":"NSW",
    "sg:tags":[
        "engine",
        "equipment",
        "diesel"
    ],
    "sg:website":"http://www.hatz.com.au",
    "wof:name":"Hatz Diesel Australia",
    "wof:placetype":"venue"
},
  "geometry": {"coordinates":[150.93055725100001,-33.8359985352],"type":"Point"}
}