{
  "type": "Feature",
  "properties": {
    "iso:country":"AU",
    "sg:address":"34 Hagman St",
    "sg:city":"Stafford Heights",
    "sg:classifiers":[
        {
            "category":"Utilities",
            "subcategory":"Telephone",
            "type":"Services"
        }
    ],
    "sg:phone":"+61 1300 655 625",
    "sg:postcode":"4053",
    "sg:province":"QLD",
    "sg:tags":[
        "equipment",
        "system"
    ],
    "wof:name":"PhoneControl Call Accounting",
    "wof:placetype":"venue"
},
  "geometry": {"coordinates":[152.999603272,-27.3944797516],"type":"Point"}
}