{
  "type": "Feature",
  "properties": {
    "addr:full":"9 Trafalgar St Enmore NSW 2042",
    "addr:housenumber":"9",
    "addr:postcode":"2042",
    "addr:street":"Trafalgar St",
    "iso:country":"AU",
    "sg:address":"9 Trafalgar St",
    "sg:city":"Enmore",
    "sg:classifiers":[
        {
            "category":"Shopping",
            "subcategory":"Musical Instruments",
            "type":"Retail Goods"
        }
    ],
    "sg:phone":"+61 2 9517 2836",
    "sg:postcode":"2042",
    "sg:province":"NSW",
    "sg:tags":[
        "musician",
        "agent"
    ],
    "wof:name":"Henrich Glenn & Ann",
    "wof:placetype":"venue"
},
  "geometry": {"coordinates":[151.173203,-33.896626],"type":"Point"}
}