{
  "type": "Feature",
  "properties": {
    "iso:country":"AU",
    "sg:address":"124 Percival Rd",
    "sg:city":"Stanmore",
    "sg:classifiers":[
        {
            "category":"Manufacturing",
            "subcategory":"Food",
            "type":"Manufacturing & Wholesale Goods"
        }
    ],
    "sg:phone":"+61 2 9569 5898",
    "sg:postcode":"2048",
    "sg:province":"NSW",
    "sg:tags":[
        "function",
        "catering"
    ],
    "wof:name":"Made in Stanmore",
    "wof:placetype":"venue"
},
  "geometry": {"coordinates":[151.164124,-33.893581],"type":"Point"}
}