{
  "type": "Feature",
  "properties": {
    "addr:full":"3093 Albany Hwy Armadale WA 6112",
    "addr:housenumber":"3093",
    "addr:postcode":"6112",
    "addr:street":"Albany Hwy",
    "iso:country":"AU",
    "sg:address":"3093 Albany Hwy",
    "sg:city":"Armadale",
    "sg:classifiers":[
        {
            "category":"Shopping",
            "subcategory":"Pets & Pet Supplies",
            "type":"Retail Goods"
        }
    ],
    "sg:phone":"+61 8 9399 7746",
    "sg:postcode":"6112",
    "sg:province":"WA",
    "sg:tags":[
        "equipment",
        "ceramic"
    ],
    "wof:name":"Mals Hobby Ceramics",
    "wof:placetype":"venue"
},
  "geometry": {"coordinates":[116.02610015899999,-32.1607437134],"type":"Point"}
}