{
  "type": "Feature",
  "properties": {
    "iso:country":"AU",
    "sg:address":"Factory 5 9 Phoenix Crt",
    "sg:city":"Braeside",
    "sg:classifiers":[
        {
            "category":"Utilities",
            "subcategory":"Electric",
            "type":"Services"
        }
    ],
    "sg:phone":"+61 3 9590 9066",
    "sg:postcode":"3195",
    "sg:province":"VIC",
    "sg:tags":[
        "electrical",
        "contractor"
    ],
    "wof:name":"South Eastern Electrics",
    "wof:placetype":"venue"
},
  "geometry": {"coordinates":[145.11204528799999,-38.0024452209],"type":"Point"}
}