{
  "type": "Feature",
  "properties": {
    "addr:full":"Cnr Eighteenth & Tapio St Renmark SA 5341",
    "addr:postcode":"5341",
    "addr:street":"Cnr;St",
    "iso:country":"AU",
    "sg:address":"Cnr Eighteenth & Tapio St",
    "sg:city":"Renmark",
    "sg:classifiers":[
        {
            "category":"Home & Garden",
            "subcategory":"Building Materials",
            "type":"Retail Goods"
        }
    ],
    "sg:phone":"+61 8 8586 4266",
    "sg:postcode":"5341",
    "sg:province":"SA",
    "sg:tags":[
        "secondhand"
    ],
    "wof:name":"Riverland Salvage",
    "wof:placetype":"venue"
},
  "geometry": {"coordinates":[140.74551391599999,-34.1753616333],"type":"Point"}
}