{
  "type": "Feature",
  "properties": {
    "addr:full":"Wellington Rd Mulgrave VIC 3170",
    "addr:postcode":"3170",
    "addr:street":"Wellington Rd",
    "iso:country":"AU",
    "sg:address":"Wellington Rd",
    "sg:city":"Mulgrave",
    "sg:classifiers":[
        {
            "category":"Farming",
            "subcategory":"Fish & Marine Products",
            "type":"Manufacturing & Wholesale Goods"
        }
    ],
    "sg:phone":"+61 2 4920 1649",
    "sg:postcode":"3170",
    "sg:province":"VIC",
    "sg:tags":[
        "chemical",
        "supplier"
    ],
    "wof:name":"Swift And Company Limited",
    "wof:placetype":"venue"
},
  "geometry": {"coordinates":[145.165924072,-37.9197616577],"type":"Point"}
}