{
  "type": "Feature",
  "properties": {
    "iso:country":"AU",
    "sg:address":"Unit 3, 17 Donegal Rd",
    "sg:city":"Lonsdale",
    "sg:classifiers":[
        {
            "category":"Manufacturing",
            "subcategory":"Metals",
            "type":"Manufacturing & Wholesale Goods"
        }
    ],
    "sg:phone":"+61 8 8326 6160",
    "sg:postcode":"5160",
    "sg:province":"SA",
    "sg:tags":[
        "steel",
        "fabricator",
        "mfrs"
    ],
    "wof:name":"Structurally Sound Engineering",
    "wof:placetype":"venue"
},
  "geometry": {"coordinates":[138.493896484,-35.1180839539],"type":"Point"}
}