{
  "type": "Feature",
  "properties": {
    "addr:full":"1435 Sydney Rd Fawkner VIC 3060",
    "addr:housenumber":"1435",
    "addr:postcode":"3060",
    "addr:street":"Sydney Rd",
    "iso:country":"AU",
    "sg:address":"1435 Sydney Rd",
    "sg:city":"Fawkner",
    "sg:classifiers":[
        {
            "category":"Travel",
            "subcategory":"Hotels & Motels",
            "type":"Entertainment"
        }
    ],
    "sg:phone":"+61 3 9359 1666",
    "sg:postcode":"3060",
    "sg:province":"VIC",
    "sg:tags":[
        "pub"
    ],
    "wof:name":"Meadow Inn Hotel",
    "wof:placetype":"venue"
},
  "geometry": {"coordinates":[144.969406128,-37.7048110962],"type":"Point"}
}