{
  "type": "Feature",
  "properties": {
    "addr:full":"shop 7 eastwood Arcade 183-185 Rowe St Eastwood NSW 2122",
    "addr:housenumber":"shop 7;183-185",
    "addr:postcode":"2122",
    "addr:street":"Eastwood Arcade;Rowe St",
    "iso:country":"AU",
    "sg:address":"shop 7 eastwood Arcade 183-185 Rowe St",
    "sg:city":"Eastwood",
    "sg:classifiers":[
        {
            "category":"Food & Beverages",
            "subcategory":"Bakery",
            "type":"Retail Goods"
        }
    ],
    "sg:phone":"+61 2 9804 0168",
    "sg:postcode":"2122",
    "sg:province":"NSW",
    "sg:tags":[
        "baker"
    ],
    "wof:name":"Tai Baan Bakery",
    "wof:placetype":"venue"
},
  "geometry": {"coordinates":[151.079711914,-33.7917556763],"type":"Point"}
}