{
  "type": "Feature",
  "properties": {
    "addr:full":"174A James St Toowoomba QLD 4350",
    "addr:housenumber":"174a",
    "addr:postcode":"4350",
    "addr:street":"James St",
    "iso:country":"AU",
    "sg:address":"174A James St",
    "sg:city":"Toowoomba",
    "sg:classifiers":[
        {
            "category":"Retail",
            "subcategory":"Auto Rental",
            "type":"Services"
        }
    ],
    "sg:phone":"+61 13 27 27",
    "sg:postcode":"4350",
    "sg:province":"QLD",
    "sg:tags":[
        "bus",
        "truck"
    ],
    "wof:name":"Budget",
    "wof:placetype":"venue"
},
  "geometry": {"coordinates":[151.94996599999999,-27.568565],"type":"Point"}
}