{
  "type": "Feature",
  "properties": {
    "iso:country":"AU",
    "sg:address":"Unit 6/ 13 Crown St",
    "sg:city":"South Geelong",
    "sg:classifiers":[
        {
            "category":"Retail",
            "subcategory":"Auto Repair",
            "type":"Services"
        }
    ],
    "sg:phone":"+61 3 5229 9183",
    "sg:postcode":"3220",
    "sg:province":"VIC",
    "sg:tags":[
        "repairer",
        "motor",
        "engineer"
    ],
    "wof:name":"Morts Motorsports",
    "wof:placetype":"venue"
},
  "geometry": {"coordinates":[144.36596700000001,-38.168488],"type":"Point"}
}