{
  "type": "Feature",
  "properties": {
    "addr:full":"497 Kingston Rd Kingston QLD 4114",
    "addr:housenumber":"497",
    "addr:postcode":"4114",
    "addr:street":"Kingston Rd",
    "iso:country":"AU",
    "sg:address":"497 Kingston Rd",
    "sg:city":"Kingston",
    "sg:classifiers":[
        {
            "category":"Fast Food",
            "type":"Food & Drink"
        }
    ],
    "sg:phone":"+61 7 3808 5505",
    "sg:postcode":"4114",
    "sg:province":"QLD",
    "sg:tags":[
        "away",
        "take"
    ],
    "wof:name":"Big Dad's Pies Kingston",
    "wof:placetype":"venue"
},
  "geometry": {"coordinates":[153.11807250999999,-27.6617622375],"type":"Point"}
}