{
  "type": "Feature",
  "properties": {
    "addr:full":"34 Alison Ave Warrnambool VIC 3280",
    "addr:housenumber":"34",
    "addr:postcode":"3280",
    "addr:street":"Alison Ave",
    "iso:country":"AU",
    "sg:address":"34 Alison Ave",
    "sg:city":"Warrnambool",
    "sg:classifiers":[
        {
            "category":"Education",
            "subcategory":"Music School",
            "type":"Public Place"
        }
    ],
    "sg:phone":"+61 3 5561 4281",
    "sg:postcode":"3280",
    "sg:province":"VIC",
    "sg:tags":[
        "singing",
        "teacher"
    ],
    "wof:name":"Elizabeth Mckay",
    "wof:placetype":"venue"
},
  "geometry": {"coordinates":[142.50680542000001,-38.3887214661],"type":"Point"}
}