{
  "type": "Feature",
  "properties": {
    "iso:country":"AU",
    "sg:address":"132 Mains Rd",
    "sg:city":"Sunnybank",
    "sg:classifiers":[
        {
            "category":"Health Services",
            "subcategory":"Dentist",
            "type":"Services"
        }
    ],
    "sg:phone":"+61 7 3344 6088",
    "sg:postcode":"4109",
    "sg:province":"QLD",
    "wof:name":"Wan Pui Lee Tnay",
    "wof:placetype":"venue"
},
  "geometry": {"coordinates":[153.062057495,-27.5815105438],"type":"Point"}
}