{
  "type": "Feature",
  "properties": {
    "addr:full":"82 Balo St Moree NSW 2400",
    "addr:housenumber":"82",
    "addr:postcode":"2400",
    "addr:street":"Balo St",
    "iso:country":"AU",
    "sg:address":"82 Balo St",
    "sg:city":"Moree",
    "sg:classifiers":[
        {
            "category":"Shopping",
            "subcategory":"Music",
            "type":"Retail Goods"
        }
    ],
    "sg:phone":"+61 2 6752 9542",
    "sg:postcode":"2400",
    "sg:province":"NSW",
    "sg:tags":[
        "instrument",
        "musical"
    ],
    "wof:name":"Harvey Norman Music",
    "wof:placetype":"venue"
},
  "geometry": {"coordinates":[149.84175109899999,-29.4646663666],"type":"Point"}
}