{
  "type": "Feature",
  "properties": {
    "iso:country":"AU",
    "sg:address":"Donaldson St",
    "sg:city":"Griffith",
    "sg:classifiers":[
        {
            "category":"Wholesale",
            "subcategory":"Machinery & Supplies",
            "type":"Manufacturing & Wholesale Goods"
        }
    ],
    "sg:phone":"+61 2 6962 3866",
    "sg:postcode":"2680",
    "sg:province":"NSW",
    "sg:tags":[
        "agricultural"
    ],
    "wof:name":"Mitchell Agricultural Parts",
    "wof:placetype":"venue"
},
  "geometry": {"coordinates":[146.071228,-34.291637],"type":"Point"}
}