{
  "type": "Feature",
  "properties": {
    "addr:full":"122 Bluebell La Murrumbateman NSW 2582",
    "addr:housenumber":"122",
    "addr:postcode":"2582",
    "addr:street":"Bluebell La",
    "iso:country":"AU",
    "sg:address":"122 Bluebell La",
    "sg:city":"Murrumbateman",
    "sg:classifiers":[
        {
            "category":"Farming",
            "subcategory":"Vineyard",
            "type":"Manufacturing & Wholesale Goods"
        }
    ],
    "sg:phone":"+61 2 6227 5999",
    "sg:postcode":"2582",
    "sg:province":"NSW",
    "sg:tags":[
        "winery"
    ],
    "wof:name":"Jeir Creek Wines",
    "wof:placetype":"venue"
},
  "geometry": {"coordinates":[149.02450561500001,-35.0288162231],"type":"Point"}
}