{
  "type": "Feature",
  "properties": {
    "addr:full":"382 Barrenjoey Rd Newport Beach NSW 2106",
    "addr:housenumber":"382",
    "addr:postcode":"2106",
    "addr:street":"Barrenjoey Rd",
    "iso:country":"AU",
    "sg:address":"382 Barrenjoey Rd",
    "sg:city":"Newport Beach",
    "sg:classifiers":[
        {
            "category":"Real Estate",
            "subcategory":"Real Estate Agent",
            "type":"Services"
        }
    ],
    "sg:phone":"+61 2 9997 8044",
    "sg:postcode":"2106",
    "sg:province":"NSW",
    "wof:name":"Violet Real Estate",
    "wof:placetype":"venue"
},
  "geometry": {"coordinates":[151.32154846200001,-33.6544036865],"type":"Point"}
}