{
  "type": "Feature",
  "properties": {
    "addr:full":"181 Chaple St Prahran VIC 3181",
    "addr:housenumber":"181",
    "addr:postcode":"3181",
    "addr:street":"Chaple St",
    "iso:country":"AU",
    "sg:address":"181 Chaple St",
    "sg:city":"Prahran",
    "sg:classifiers":[
        {
            "category":"Personal",
            "subcategory":"Beauty Salon",
            "type":"Services"
        }
    ],
    "sg:phone":"+61 413 376 103",
    "sg:postcode":"3181",
    "sg:province":"VIC",
    "sg:tags":[
        "hairdresser"
    ],
    "wof:name":"Gorgeous Fx",
    "wof:placetype":"venue"
},
  "geometry": {"coordinates":[144.993209839,-37.8516807556],"type":"Point"}
}