{
  "type": "Feature",
  "properties": {
    "addr:full":"388 Shute Harbour Rd Airlie Beach QLD 4802",
    "addr:housenumber":"388",
    "addr:postcode":"4802",
    "addr:street":"Shute Harbour Rd",
    "iso:country":"AU",
    "sg:address":"388 Shute Harbour Rd",
    "sg:city":"Airlie Beach",
    "sg:classifiers":[
        {
            "category":"Real Estate",
            "subcategory":"Real Estate Agent",
            "type":"Services"
        }
    ],
    "sg:phone":"+61 7 4948 8500",
    "sg:postcode":"4802",
    "sg:province":"QLD",
    "wof:name":"Ray White Whitsunday",
    "wof:placetype":"venue"
},
  "geometry": {"coordinates":[148.719406128,-20.2692432404],"type":"Point"}
}