{
  "type": "Feature",
  "properties": {
    "addr:full":"U2/ 39 Enterprise St Cleveland QLD 4163",
    "addr:housenumber":"39",
    "addr:postcode":"4163",
    "addr:street":"U2 /;Enterprise St",
    "iso:country":"AU",
    "sg:address":"U2/ 39 Enterprise St",
    "sg:city":"Cleveland",
    "sg:classifiers":[
        {
            "category":"Professional",
            "subcategory":"Printing & Photocopies",
            "type":"Services"
        }
    ],
    "sg:phone":"+61 7 3286 1833",
    "sg:postcode":"4163",
    "sg:province":"QLD",
    "sg:tags":[
        "publishing",
        "desktop"
    ],
    "wof:name":"Collins Media",
    "wof:placetype":"venue"
},
  "geometry": {"coordinates":[153.26713562,-27.5282821655],"type":"Point"}
}