{
  "type": "Feature",
  "properties": {
    "addr:full":"25 Homestead St Marsden QLD 4132",
    "addr:housenumber":"25",
    "addr:postcode":"4132",
    "addr:street":"Homestead St",
    "iso:country":"AU",
    "sg:address":"25 Homestead St",
    "sg:city":"Marsden",
    "sg:classifiers":[
        {
            "category":"Education",
            "subcategory":"Music School",
            "type":"Public Place"
        }
    ],
    "sg:phone":"+61 7 3200 8223",
    "sg:postcode":"4132",
    "sg:province":"QLD",
    "sg:tags":[
        "teacher"
    ],
    "wof:name":"A1 Drum Tuition",
    "wof:placetype":"venue"
},
  "geometry": {"coordinates":[153.10443115199999,-27.6762084961],"type":"Point"}
}