{
  "type": "Feature",
  "properties": {
    "addr:full":"610 Ballarat Rd Ardeer VIC 3022",
    "addr:housenumber":"610",
    "addr:postcode":"3022",
    "addr:street":"Ballarat Rd",
    "iso:country":"AU",
    "sg:address":"610 Ballarat Rd",
    "sg:city":"Ardeer",
    "sg:classifiers":[
        {
            "category":"Travel",
            "subcategory":"Hotels & Motels",
            "type":"Entertainment"
        }
    ],
    "sg:phone":"+61 3 9363 3262",
    "sg:postcode":"3022",
    "sg:province":"VIC",
    "wof:name":"West City Cabin Park & Motel",
    "wof:placetype":"venue"
},
  "geometry": {"coordinates":[144.803665,-37.773586],"type":"Point"}
}