{
  "type": "Feature",
  "properties": {
    "addr:full":"William St Southport QLD 4215",
    "addr:postcode":"4215",
    "addr:street":"William St",
    "iso:country":"AU",
    "sg:address":"William St",
    "sg:city":"Southport",
    "sg:classifiers":[
        {
            "category":"Health Services",
            "subcategory":"Health Practitioner",
            "type":"Services"
        }
    ],
    "sg:phone":"+61 7 5531 0602",
    "sg:postcode":"4215",
    "sg:province":"QLD",
    "sg:tags":[
        "psychotherapist"
    ],
    "wof:name":"Barnao Elizabeth",
    "wof:placetype":"venue"
},
  "geometry": {"coordinates":[153.40408325199999,-27.9598178864],"type":"Point"}
}