{
  "type": "Feature",
  "properties": {
    "iso:country":"AU",
    "sg:address":"6b Drabsch St",
    "sg:city":"Loxton",
    "sg:classifiers":[
        {
            "category":"Home & Garden",
            "subcategory":"Building Materials",
            "type":"Retail Goods"
        }
    ],
    "sg:phone":"+61 8 8584 7507",
    "sg:postcode":"5333",
    "sg:province":"SA",
    "sg:tags":[
        "shutter",
        "roller",
        "grille"
    ],
    "wof:name":"C.C Blinds",
    "wof:placetype":"venue"
},
  "geometry": {"coordinates":[140.56971740700001,-34.4513816833],"type":"Point"}
}