{
  "type": "Feature",
  "properties": {
    "addr:full":"Hamilton Rd Haven VIC 3401",
    "addr:postcode":"3401",
    "addr:street":"Hamilton Rd",
    "iso:country":"AU",
    "sg:address":"Hamilton Rd",
    "sg:city":"Haven",
    "sg:classifiers":[
        {
            "category":"Commercial Area",
            "type":"Public Place"
        }
    ],
    "sg:phone":"+61 3 5382 1251",
    "sg:postcode":"3401",
    "sg:province":"VIC",
    "sg:tags":[
        "heavy",
        "carrier"
    ],
    "wof:name":"Ryans Freighters",
    "wof:placetype":"venue"
},
  "geometry": {"coordinates":[142.20924377399999,-36.7177848816],"type":"Point"}
}