{
  "type": "Feature",
  "properties": {
    "addr:full":"PO Box 4131 Richmond East VIC 3121",
    "addr:postcode":"3121",
    "iso:country":"AU",
    "sg:address":"PO Box 4131",
    "sg:city":"Richmond East",
    "sg:classifiers":[
        {
            "category":"Professional",
            "subcategory":"Computer Services",
            "type":"Services"
        }
    ],
    "sg:phone":"+61 3 9429 7280",
    "sg:postcode":"3121",
    "sg:province":"VIC",
    "sg:tags":[
        "consultant",
        "system"
    ],
    "wof:name":"Job Express Pty. Limited",
    "wof:placetype":"venue"
},
  "geometry": {"coordinates":[145.00813293499999,-37.8220596313],"type":"Point"}
}