{
  "type": "Feature",
  "properties": {
    "iso:country":"AU",
    "sg:address":"52 Lords Pl",
    "sg:city":"Orange",
    "sg:classifiers":[
        {
            "category":"Building & Trades",
            "subcategory":"Construction",
            "type":"Services"
        }
    ],
    "sg:phone":"+61 2 6362 0700",
    "sg:postcode":"2800",
    "sg:province":"NSW",
    "sg:tags":[
        "fencing",
        "contractor"
    ],
    "wof:name":"A1 Absolutely Fencing",
    "wof:placetype":"venue"
},
  "geometry": {"coordinates":[149.10069274899999,-33.2853965759],"type":"Point"}
}