{
  "type": "Feature",
  "properties": {
    "iso:country":"AU",
    "sg:address":"32 High St",
    "sg:city":"Bendigo",
    "sg:classifiers":[
        {
            "category":"Shopping",
            "subcategory":"Music",
            "type":"Retail Goods"
        }
    ],
    "sg:phone":"+61 3 5443 4111",
    "sg:postcode":"3550",
    "sg:province":"VIC",
    "sg:tags":[
        "store"
    ],
    "wof:name":"Discography Music & Books",
    "wof:placetype":"venue"
},
  "geometry": {"coordinates":[144.27804565400001,-36.7598876953],"type":"Point"}
}