{
  "type": "Feature",
  "properties": {
    "addr:full":"752a Springvale Rd Mulgrave VIC 3170",
    "addr:housenumber":"752a",
    "addr:postcode":"3170",
    "addr:street":"Springvale Rd",
    "iso:country":"AU",
    "sg:address":"752a Springvale Rd",
    "sg:city":"Mulgrave",
    "sg:classifiers":[
        {
            "category":"Retail",
            "subcategory":"Auto Repair",
            "type":"Services"
        }
    ],
    "sg:phone":"+61 3 9561 1744",
    "sg:postcode":"3170",
    "sg:province":"VIC",
    "sg:tags":[
        "clutch",
        "brake"
    ],
    "wof:name":"ABS",
    "wof:placetype":"venue"
},
  "geometry": {"coordinates":[145.158294678,-37.9227905273],"type":"Point"}
}