{
  "type": "Feature",
  "properties": {
    "addr:full":"699 Doncaster Rd Doncaster VIC 3108",
    "addr:housenumber":"699",
    "addr:postcode":"3108",
    "addr:street":"Doncaster Rd",
    "iso:country":"AU",
    "sg:address":"699 Doncaster Rd",
    "sg:city":"Doncaster",
    "sg:classifiers":[
        {
            "category":"Arts & Performance",
            "subcategory":"Art Gallery",
            "type":"Entertainment"
        }
    ],
    "sg:phone":"+61 3 9840 9367",
    "sg:postcode":"3108",
    "sg:province":"VIC",
    "wof:name":"Manningham Gallery",
    "wof:placetype":"venue"
},
  "geometry": {"coordinates":[145.13247680699999,-37.7870521545],"type":"Point"}
}