{
  "type": "Feature",
  "properties": {
    "addr:full":"3B, 525 Lytton Rd Morningside QLD 4170",
    "addr:housenumber":"3b 525",
    "addr:postcode":"4170",
    "addr:street":"Lytton Rd",
    "iso:country":"AU",
    "sg:address":"3B, 525 Lytton Rd",
    "sg:city":"Morningside",
    "sg:classifiers":[
        {
            "category":"Professional",
            "subcategory":"Employment Agencies",
            "type":"Services"
        }
    ],
    "sg:phone":"+61 7 3899 3444",
    "sg:postcode":"4170",
    "sg:province":"QLD",
    "wof:name":"Humanity",
    "wof:placetype":"venue"
},
  "geometry": {"coordinates":[153.098266602,-27.4569225311],"type":"Point"}
}