{
  "type": "Feature",
  "properties": {
    "addr:full":"unit 3 10 Production Pl Penrith South NSW 2750",
    "addr:housenumber":"10",
    "addr:postcode":"2750",
    "addr:street":"Production Pl",
    "iso:country":"AU",
    "sg:address":"unit 3 10 Production Pl",
    "sg:city":"Penrith South",
    "sg:classifiers":[
        {
            "category":"Food & Beverages",
            "subcategory":"Specialty",
            "type":"Retail Goods"
        }
    ],
    "sg:phone":"+61 1800 605 040",
    "sg:postcode":"2750",
    "sg:province":"NSW",
    "sg:tags":[
        "solvent"
    ],
    "wof:name":"Sydney Solvents Pty Ltd",
    "wof:placetype":"venue"
},
  "geometry": {"coordinates":[150.684524536,-33.7688751221],"type":"Point"}
}