{
  "type": "Feature",
  "properties": {
    "addr:full":"Unit 2, 6-8 Industrial Rd Unanderra NSW 2526",
    "addr:housenumber":"6-8",
    "addr:postcode":"2526",
    "addr:street":"Industrial Rd",
    "iso:country":"AU",
    "sg:address":"Unit 2, 6-8 Industrial Rd",
    "sg:city":"Unanderra",
    "sg:classifiers":[
        {
            "category":"Building & Trades",
            "subcategory":"Cleaning & Sanitation",
            "type":"Services"
        }
    ],
    "sg:phone":"+61 2 4283 4079",
    "sg:postcode":"2526",
    "sg:province":"NSW",
    "sg:tags":[
        "washroom",
        "toilet",
        "equipment"
    ],
    "sg:website":"http://www.sanokil.com.au",
    "wof:name":"Sanokil",
    "wof:placetype":"venue"
},
  "geometry": {"coordinates":[150.84829711899999,-34.4563407898],"type":"Point"}
}