{
  "type": "Feature",
  "properties": {
    "addr:full":"Unit 3/ 10 Boag Pl Morley WA 6062",
    "addr:housenumber":"10",
    "addr:postcode":"6062",
    "addr:street":"Boag Pl",
    "iso:country":"AU",
    "sg:address":"Unit 3/ 10 Boag Pl",
    "sg:city":"Morley",
    "sg:classifiers":[
        {
            "category":"Banks & Credit Unions",
            "subcategory":"Investment Brokerage",
            "type":"Services"
        }
    ],
    "sg:phone":"+61 8 9275 6955",
    "sg:postcode":"6062",
    "sg:province":"WA",
    "sg:tags":[
        "equipment",
        "spray",
        "painting",
        "supply"
    ],
    "wof:name":"Westcoast Automotive Supplies",
    "wof:placetype":"venue"
},
  "geometry": {"coordinates":[115.89421081499999,-31.8985843658],"type":"Point"}
}