{
  "type": "Feature",
  "properties": {
    "addr:full":"121 Fairfield Rd Guildford NSW 2161",
    "addr:housenumber":"121",
    "addr:postcode":"2161",
    "addr:street":"Fairfield Rd",
    "iso:country":"AU",
    "sg:address":"121 Fairfield Rd",
    "sg:city":"Guildford",
    "sg:classifiers":[
        {
            "category":"Fast Food",
            "type":"Food & Drink"
        }
    ],
    "sg:phone":"+61 2 9681 4303",
    "sg:postcode":"2161",
    "sg:province":"NSW",
    "sg:tags":[
        "away",
        "take"
    ],
    "wof:name":"Gum Wah Chinese Restauarant",
    "wof:placetype":"venue"
},
  "geometry": {"coordinates":[150.96127319300001,-33.8495635986],"type":"Point"}
}