{
  "type": "Feature",
  "properties": {
    "addr:full":"99 Racecourse Rd Ascot QLD 4007",
    "addr:housenumber":"99",
    "addr:postcode":"4007",
    "addr:street":"Racecourse Rd",
    "iso:country":"AU",
    "sg:address":"99 Racecourse Rd",
    "sg:city":"Ascot",
    "sg:classifiers":[
        {
            "category":"Shopping",
            "subcategory":"Mobile Phones",
            "type":"Retail Goods"
        }
    ],
    "sg:phone":"+61 7 3268 5755",
    "sg:postcode":"4007",
    "sg:province":"QLD",
    "sg:tags":[
        "telephone",
        "accessory"
    ],
    "wof:name":"Mobile Central",
    "wof:placetype":"venue"
},
  "geometry": {"coordinates":[153.065414,-27.433243],"type":"Point"}
}