{
  "type": "Feature",
  "properties": {
    "iso:country":"AU",
    "sg:address":"Ridley Rd",
    "sg:city":"Wattle Grove",
    "sg:classifiers":[
        {
            "category":"Commercial Area",
            "type":"Public Place"
        }
    ],
    "sg:phone":"+61 8 9453 6327",
    "sg:postcode":"6107",
    "sg:province":"WA",
    "sg:tags":[
        "heavy",
        "carrier"
    ],
    "wof:name":"Nickisson R J",
    "wof:placetype":"venue"
},
  "geometry": {"coordinates":[116.01978302000001,-32.0054740906],"type":"Point"}
}