{
  "type": "Feature",
  "properties": {
    "iso:country":"AU",
    "sg:address":"40 Waratah St",
    "sg:city":"Katoomba",
    "sg:classifiers":[
        {
            "category":"Professional",
            "subcategory":"Art Services",
            "type":"Services"
        }
    ],
    "sg:phone":"+61 2 4782 9022",
    "sg:postcode":"2780",
    "sg:province":"NSW",
    "sg:tags":[
        "picture",
        "frame",
        "framing"
    ],
    "wof:name":"Christopher Lines Picture Framing",
    "wof:placetype":"venue"
},
  "geometry": {"coordinates":[150.31190490700001,-33.7174873352],"type":"Point"}
}