{
  "type": "Feature",
  "properties": {
    "addr:full":"10b Torrens Rd Caboolture QLD 4510",
    "addr:housenumber":"10b",
    "addr:postcode":"4510",
    "addr:street":"Torrens Rd",
    "iso:country":"AU",
    "sg:address":"10b Torrens Rd",
    "sg:city":"Caboolture",
    "sg:classifiers":[
        {
            "category":"Education",
            "subcategory":"Kindergarten",
            "type":"Public Place"
        }
    ],
    "sg:phone":"+61 7 5495 2766",
    "sg:postcode":"4510",
    "sg:province":"QLD",
    "sg:tags":[
        "pre-schools"
    ],
    "wof:name":"Lady Gowrie Caboolture Family Day Care",
    "wof:placetype":"venue"
},
  "geometry": {"coordinates":[152.947723,-27.097292],"type":"Point"}
}