{
  "type": "Feature",
  "properties": {
    "addr:full":"82 Yambil St Griffith NSW 2680",
    "addr:housenumber":"82",
    "addr:postcode":"2680",
    "addr:street":"Yambil St",
    "iso:country":"AU",
    "sg:address":"82 Yambil St",
    "sg:city":"Griffith",
    "sg:classifiers":[
        {
            "category":"Professional",
            "subcategory":"Accounting & Tax Preparation",
            "type":"Services"
        }
    ],
    "sg:phone":"+61 2 6962 6333",
    "sg:postcode":"2680",
    "sg:province":"NSW",
    "sg:tags":[
        "consultant",
        "taxation"
    ],
    "wof:name":"Del Gigante T",
    "wof:placetype":"venue"
},
  "geometry": {"coordinates":[146.05166600000001,-34.290134],"type":"Point"}
}