{
  "type": "Feature",
  "properties": {
    "addr:full":"194 Churchill Rd Prospect SA 5082",
    "addr:housenumber":"194",
    "addr:postcode":"5082",
    "addr:street":"Churchill Rd",
    "iso:country":"AU",
    "sg:address":"194 Churchill Rd",
    "sg:city":"Prospect",
    "sg:classifiers":[
        {
            "category":"Building & Trades",
            "subcategory":"Construction",
            "type":"Services"
        }
    ],
    "sg:phone":"+61 8 8344 8454",
    "sg:postcode":"5082",
    "sg:province":"SA",
    "sg:tags":[
        "equipment",
        "system",
        "automation"
    ],
    "wof:name":"J R & R T Walker",
    "wof:placetype":"venue"
},
  "geometry": {"coordinates":[138.58448791500001,-34.8821182251],"type":"Point"}
}