{
  "type": "Feature",
  "properties": {
    "addr:full":"7 Seville St Fairfield NSW 2165",
    "addr:housenumber":"7",
    "addr:postcode":"2165",
    "addr:street":"Seville St",
    "iso:country":"AU",
    "sg:address":"7 Seville St",
    "sg:city":"Fairfield",
    "sg:classifiers":[
        {
            "category":"Manufacturing",
            "subcategory":"Rubber & Plastics",
            "type":"Manufacturing & Wholesale Goods"
        }
    ],
    "sg:phone":"+61 2 9755 9500",
    "sg:postcode":"2165",
    "sg:province":"NSW",
    "sg:tags":[
        "moulders"
    ],
    "wof:name":"Low Volume Plastics Pty Ltd",
    "wof:placetype":"venue"
},
  "geometry": {"coordinates":[150.98243713400001,-33.8734588623],"type":"Point"}
}