{
  "type": "Feature",
  "properties": {
    "addr:full":"116 Main St Croydon VIC 3136",
    "addr:housenumber":"116",
    "addr:postcode":"3136",
    "addr:street":"Main St",
    "iso:country":"AU",
    "sg:address":"116 Main St",
    "sg:city":"Croydon",
    "sg:classifiers":[
        {
            "category":"Professional",
            "subcategory":"Advertising",
            "type":"Services"
        }
    ],
    "sg:phone":"+61 3 9725 1432",
    "sg:postcode":"3136",
    "sg:province":"VIC",
    "sg:tags":[
        "balloon",
        "novelty"
    ],
    "wof:name":"Balloon & Party Specialists",
    "wof:placetype":"venue"
},
  "geometry": {"coordinates":[145.28082275400001,-37.7980651855],"type":"Point"}
}