{
  "type": "Feature",
  "properties": {
    "addr:full":"520 Tingal Rd Wynnum North QLD 4178",
    "addr:housenumber":"520",
    "addr:postcode":"4178",
    "addr:street":"Tingal Rd",
    "iso:country":"AU",
    "sg:address":"520 Tingal Rd",
    "sg:city":"Wynnum North",
    "sg:classifiers":[
        {
            "category":"Sports & Exercise",
            "subcategory":"Gym",
            "type":"Entertainment"
        }
    ],
    "sg:phone":"+61 7 3393 3234",
    "sg:postcode":"4178",
    "sg:province":"QLD",
    "sg:tags":[
        "personal",
        "trainer",
        "fitness"
    ],
    "wof:name":"Move &#039;n&#039; Improve Personal Training",
    "wof:placetype":"venue"
},
  "geometry": {"coordinates":[153.164352417,-27.4290618896],"type":"Point"}
}