{
  "type": "Feature",
  "properties": {
    "iso:country":"AU",
    "sg:address":"195c Waterloo Rd",
    "sg:city":"Greenacre",
    "sg:classifiers":[
        {
            "category":"Health Services",
            "subcategory":"Optometrist",
            "type":"Services"
        }
    ],
    "sg:phone":"+61 2 9750 2111",
    "sg:postcode":"2190",
    "sg:province":"NSW",
    "wof:name":"Eyecare Plus Optometrists",
    "wof:placetype":"venue"
},
  "geometry": {"coordinates":[151.058777,-33.898621],"type":"Point"}
}