{
  "type": "Feature",
  "properties": {
    "iso:country":"AU",
    "sg:address":"169 Lyons Rd",
    "sg:city":"Drummoyne",
    "sg:classifiers":[
        {
            "category":"Health Services",
            "subcategory":"Chiropractor",
            "type":"Services"
        }
    ],
    "sg:phone":"+61 2 9819 6182",
    "sg:postcode":"2047",
    "sg:province":"NSW",
    "wof:name":"Molino Paul",
    "wof:placetype":"venue"
},
  "geometry": {"coordinates":[151.147141,-33.856079],"type":"Point"}
}