{
  "type": "Feature",
  "properties": {
    "addr:full":"3 Kellaway St Fannie Bay NT 0820",
    "addr:housenumber":"3",
    "addr:postcode":"nt 0820",
    "addr:street":"Kellaway St",
    "iso:country":"AU",
    "sg:address":"3 Kellaway St",
    "sg:city":"Fannie Bay",
    "sg:classifiers":[
        {
            "category":"Travel",
            "subcategory":"Hotels & Motels",
            "type":"Entertainment"
        }
    ],
    "sg:phone":"+61 8 8981 4055",
    "sg:postcode":"0820",
    "sg:province":"NT",
    "sg:tags":[
        "accommodation"
    ],
    "wof:name":"Capricornia Motel",
    "wof:placetype":"venue"
},
  "geometry": {"coordinates":[130.838012695,-12.4319267273],"type":"Point"}
}