{
  "type": "Feature",
  "properties": {
    "iso:country":"AU",
    "sg:address":"96 St James Rd",
    "sg:city":"Rosanna",
    "sg:classifiers":[
        {
            "category":"Food & Beverages",
            "subcategory":"Groceries & Convenience Stores",
            "type":"Retail Goods"
        }
    ],
    "sg:phone":"+61 3 9457 1386",
    "sg:postcode":"3084",
    "sg:province":"VIC",
    "wof:name":"Mica Mini Mart",
    "wof:placetype":"venue"
},
  "geometry": {"coordinates":[145.073120117,-37.748210907],"type":"Point"}
}