{
  "type": "Feature",
  "properties": {
    "addr:full":"41 Denison Pde Mango Hill QLD 4509",
    "addr:housenumber":"41",
    "addr:postcode":"4509",
    "addr:street":"Denison Pde",
    "iso:country":"AU",
    "sg:address":"41 Denison Pde",
    "sg:city":"Mango Hill",
    "sg:classifiers":[
        {
            "category":"Professional",
            "subcategory":"Computer Services",
            "type":"Services"
        }
    ],
    "sg:phone":"+61 7 3886 1491",
    "sg:postcode":"4509",
    "sg:province":"QLD",
    "sg:tags":[
        "tele-communications",
        "consultant"
    ],
    "wof:name":"Recognition Solutions",
    "wof:placetype":"venue"
},
  "geometry": {"coordinates":[153.01841735799999,-27.2271099091],"type":"Point"}
}