{
  "type": "Feature",
  "properties": {
    "addr:full":"105 William St Bathurst NSW 2795",
    "addr:housenumber":"105",
    "addr:postcode":"2795",
    "addr:street":"William St",
    "iso:country":"AU",
    "sg:address":"105 William St",
    "sg:city":"Bathurst",
    "sg:classifiers":[
        {
            "category":"Retail",
            "subcategory":"Event Space",
            "type":"Services"
        }
    ],
    "sg:phone":"+61 2 6333 6162",
    "sg:postcode":"2795",
    "sg:province":"NSW",
    "sg:tags":[
        "venue",
        "reception",
        "wedding"
    ],
    "wof:name":"Bathurst Memorial Entertainment Centre",
    "wof:placetype":"venue"
},
  "geometry": {"coordinates":[149.55354309099999,-33.5437316895],"type":"Point"}
}