{
  "type": "Feature",
  "properties": {
    "iso:country":"AU",
    "sg:address":"18 Phillip St",
    "sg:city":"Bonnie Doon",
    "sg:classifiers":[
        {
            "category":"Cafe",
            "type":"Food & Drink"
        }
    ],
    "sg:phone":"+61 3 5778 7251",
    "sg:postcode":"3720",
    "sg:province":"VIC",
    "wof:name":"Melz Eatery",
    "wof:placetype":"venue"
},
  "geometry": {"coordinates":[145.85398864699999,-37.0249824524],"type":"Point"}
}