{
  "type": "Feature",
  "properties": {
    "iso:country":"AU",
    "sg:address":"Unit 2, 16 Bonnal Rd",
    "sg:city":"Erina",
    "sg:classifiers":[
        {
            "category":"Professional",
            "subcategory":"Detective & Security Services",
            "type":"Services"
        }
    ],
    "sg:phone":"+61 2 4367 6551",
    "sg:postcode":"2250",
    "sg:province":"NSW",
    "sg:tags":[
        "protective",
        "rustproofing"
    ],
    "wof:name":"Rust-Busters",
    "wof:placetype":"venue"
},
  "geometry": {"coordinates":[151.38359069800001,-33.4351806641],"type":"Point"}
}