{
  "type": "Feature",
  "properties": {
    "addr:full":"6 Railway St Southport QLD 4215",
    "addr:housenumber":"6",
    "addr:postcode":"4215",
    "addr:street":"Railway St",
    "iso:country":"AU",
    "sg:address":"6 Railway St",
    "sg:city":"Southport",
    "sg:classifiers":[
        {
            "category":"Health Services",
            "subcategory":"Dentist",
            "type":"Services"
        }
    ],
    "sg:phone":"+61 7 5531 2053",
    "sg:postcode":"4215",
    "sg:province":"QLD",
    "wof:name":"Railway Street Dental Surgery",
    "wof:placetype":"venue"
},
  "geometry": {"coordinates":[153.412185669,-27.9624996185],"type":"Point"}
}