{
  "type": "Feature",
  "properties": {
    "addr:full":"Level 1 764 Pittwater Rd Brookvale NSW 2100",
    "addr:housenumber":"764",
    "addr:postcode":"2100",
    "addr:street":"Pittwater Rd",
    "iso:country":"AU",
    "sg:address":"Level 1 764 Pittwater Rd",
    "sg:city":"Brookvale",
    "sg:classifiers":[
        {
            "category":"Farming",
            "subcategory":"Fish & Marine Products",
            "type":"Manufacturing & Wholesale Goods"
        }
    ],
    "sg:phone":"+61 2 9905 9999",
    "sg:postcode":"2100",
    "sg:province":"NSW",
    "sg:tags":[
        "wholesaler",
        "mfrs",
        "swimwear"
    ],
    "wof:name":"Berzelli Irene Swimwear",
    "wof:placetype":"venue"
},
  "geometry": {"coordinates":[151.27682495100001,-33.761302948],"type":"Point"}
}