{
  "type": "Feature",
  "properties": {
    "iso:country":"AU",
    "sg:address":"12 Camelot St",
    "sg:city":"Carine",
    "sg:classifiers":[
        {
            "category":"Arts & Performance",
            "subcategory":"Music",
            "type":"Entertainment"
        }
    ],
    "sg:phone":"+61 8 9246 3338",
    "sg:postcode":"6020",
    "sg:province":"WA",
    "sg:tags":[
        "mobile",
        "jockey",
        "disc"
    ],
    "wof:name":"Tip Top Sound",
    "wof:placetype":"venue"
},
  "geometry": {"coordinates":[115.79499054,-31.8539981842],"type":"Point"}
}