{
  "type": "Feature",
  "properties": {
    "addr:full":"163 Pelham St Carlton VIC 3053",
    "addr:housenumber":"163",
    "addr:postcode":"3053",
    "addr:street":"Pelham St",
    "iso:country":"AU",
    "sg:address":"163 Pelham St",
    "sg:city":"Carlton",
    "sg:classifiers":[
        {
            "category":"Real Estate",
            "subcategory":"Architect",
            "type":"Services"
        }
    ],
    "sg:phone":"+61 3 9349 5677",
    "sg:postcode":"3053",
    "sg:province":"VIC",
    "wof:name":"Gunn Graeme Architects Pty Ltd",
    "wof:placetype":"venue"
},
  "geometry": {"coordinates":[144.96136474599999,-37.8023529053],"type":"Point"}
}