{
  "type": "Feature",
  "properties": {
    "addr:full":"17 Wellbank St Concord NSW 2137",
    "addr:housenumber":"17",
    "addr:postcode":"2137",
    "addr:street":"Wellbank St",
    "iso:country":"AU",
    "sg:address":"17 Wellbank St",
    "sg:city":"Concord",
    "sg:classifiers":[
        {
            "category":"Health Services",
            "subcategory":"Health Practitioner",
            "type":"Services"
        }
    ],
    "sg:phone":"+61 2 9743 1174",
    "sg:postcode":"2137",
    "sg:province":"NSW",
    "sg:tags":[
        "physiotherapist"
    ],
    "wof:name":"Concord Physiotherapy",
    "wof:placetype":"venue"
},
  "geometry": {"coordinates":[151.10264587399999,-33.8559684753],"type":"Point"}
}