{
  "type": "Feature",
  "properties": {
    "addr:full":"193 Phillip Hwy Elizabeth South SA 5112",
    "addr:housenumber":"193",
    "addr:postcode":"5112",
    "addr:street":"Phillip Hwy",
    "iso:country":"AU",
    "sg:address":"193 Phillip Hwy",
    "sg:city":"Elizabeth South",
    "sg:classifiers":[
        {
            "category":"Professional",
            "subcategory":"Engineering",
            "type":"Services"
        }
    ],
    "sg:phone":"+61 8 8287 2144",
    "sg:postcode":"5112",
    "sg:province":"SA",
    "sg:tags":[
        "precision",
        "engineer"
    ],
    "wof:name":"Levett Engineering Pty Ltd",
    "wof:placetype":"venue"
},
  "geometry": {"coordinates":[138.66314697300001,-34.7315444946],"type":"Point"}
}