{
  "type": "Feature",
  "properties": {
    "addr:full":"35 Narellar Crs Bonnyrigg NSW 2177",
    "addr:housenumber":"35",
    "addr:postcode":"2177",
    "addr:street":"Narellar Crs",
    "iso:country":"AU",
    "sg:address":"35 Narellar Crs",
    "sg:city":"Bonnyrigg",
    "sg:classifiers":[
        {
            "category":"Building & Trades",
            "subcategory":"Construction",
            "type":"Services"
        }
    ],
    "sg:phone":"+61 2 9610 9667",
    "sg:postcode":"2177",
    "sg:province":"NSW",
    "sg:tags":[
        "concrete",
        "contractor"
    ],
    "wof:name":"Barillaro Concrete Contractors",
    "wof:placetype":"venue"
},
  "geometry": {"coordinates":[150.88322448700001,-33.8972702026],"type":"Point"}
}