{
  "type": "Feature",
  "properties": {
    "iso:country":"AU",
    "sg:address":"14 Grantham Pde",
    "sg:city":"St Albans",
    "sg:classifiers":[
        {
            "category":"Professional",
            "subcategory":"Computer Services",
            "type":"Services"
        }
    ],
    "sg:phone":"+61 3 9382 9333",
    "sg:postcode":"3021",
    "sg:province":"VIC",
    "sg:tags":[
        "repairs",
        "upgrade",
        "equipment"
    ],
    "wof:name":"NT IT Onsite Computer Support",
    "wof:placetype":"venue"
},
  "geometry": {"coordinates":[144.820526,-37.748028],"type":"Point"}
}