{
  "type": "Feature",
  "properties": {
    "addr:full":"Suite 34/ 34 Queens Rd Melbourne VIC 3000",
    "addr:housenumber":"34 / 34",
    "addr:postcode":"3000",
    "addr:street":"Queens Rd",
    "iso:country":"AU",
    "sg:address":"Suite 34/ 34 Queens Rd",
    "sg:city":"Melbourne",
    "sg:classifiers":[
        {
            "category":"Shopping",
            "subcategory":"Computers & Home Electronics",
            "type":"Retail Goods"
        }
    ],
    "sg:phone":"+61 3 9820 0584",
    "sg:postcode":"3000",
    "sg:province":"VIC",
    "sg:tags":[
        "equipment",
        "multimedia"
    ],
    "wof:name":"Chroma Lab Pty Ltd",
    "wof:placetype":"venue"
},
  "geometry": {"coordinates":[144.97622680699999,-37.8440322876],"type":"Point"}
}