{
  "type": "Feature",
  "properties": {
    "iso:country":"AU",
    "sg:address":"49 Chatswood Drv",
    "sg:city":"Anglesea",
    "sg:classifiers":[
        {
            "category":"Professional",
            "subcategory":"Art Services",
            "type":"Services"
        }
    ],
    "sg:phone":"+61 3 5263 2180",
    "sg:postcode":"3230",
    "sg:province":"VIC",
    "sg:tags":[
        "decorator",
        "painter"
    ],
    "wof:name":"Coastal Painting Services Pty Ltd",
    "wof:placetype":"venue"
},
  "geometry": {"coordinates":[144.175201,-38.402863],"type":"Point"}
}