{
  "type": "Feature",
  "properties": {
    "addr:full":"PO Box 18 Nicholson VIC 3882",
    "addr:postcode":"3882",
    "iso:country":"AU",
    "sg:address":"PO Box 18",
    "sg:city":"Nicholson",
    "sg:classifiers":[
        {
            "category":"Retail",
            "subcategory":"Auto Rental",
            "type":"Services"
        }
    ],
    "sg:phone":"+61 417 106 563",
    "sg:postcode":"3882",
    "sg:province":"VIC",
    "sg:tags":[
        "bus",
        "truck"
    ],
    "wof:name":"East Gippsland Tilt Tray Service",
    "wof:placetype":"venue"
},
  "geometry": {"coordinates":[147.74586486800001,-37.809551239],"type":"Point"}
}