{
  "type": "Feature",
  "properties": {
    "addr:full":"196 Ballarat Rd Creswick VIC 3363",
    "addr:housenumber":"196",
    "addr:postcode":"3363",
    "addr:street":"Ballarat Rd",
    "iso:country":"AU",
    "sg:address":"196 Ballarat Rd",
    "sg:city":"Creswick",
    "sg:classifiers":[
        {
            "category":"Building & Trades",
            "subcategory":"Construction",
            "type":"Services"
        }
    ],
    "sg:phone":"+61 3 5345 2729",
    "sg:postcode":"3363",
    "sg:province":"VIC",
    "sg:tags":[
        "earth",
        "excavating",
        "moving",
        "contractor"
    ],
    "wof:name":"Deckers Earthworks Etc.",
    "wof:placetype":"venue"
},
  "geometry": {"coordinates":[143.892410278,-37.435382843],"type":"Point"}
}