{
  "type": "Feature",
  "properties": {
    "iso:country":"AU",
    "sg:address":"Grey St",
    "sg:city":"Kalbarri",
    "sg:classifiers":[
        {
            "category":"Travel",
            "subcategory":"Hotels & Motels",
            "type":"Entertainment"
        }
    ],
    "sg:phone":"+61 8 9937 1000",
    "sg:postcode":"6536",
    "sg:province":"WA",
    "sg:tags":[
        "accommodation"
    ],
    "wof:name":"Kalbarri Motor Hotel",
    "wof:placetype":"venue"
},
  "geometry": {"coordinates":[114.161521912,-27.7110099792],"type":"Point"}
}