{
  "type": "Feature",
  "properties": {
    "addr:full":"2/ 274 Beatty Rd Archerfield QLD 4108",
    "addr:housenumber":"/ 274",
    "addr:postcode":"4108",
    "addr:street":"Beatty Rd",
    "iso:country":"AU",
    "sg:address":"2/ 274 Beatty Rd",
    "sg:city":"Archerfield",
    "sg:classifiers":[
        {
            "category":"Banks & Credit Unions",
            "subcategory":"Investment Brokerage",
            "type":"Services"
        }
    ],
    "sg:phone":"+61 7 3216 7744",
    "sg:postcode":"4108",
    "sg:province":"QLD",
    "sg:tags":[
        "mechanical",
        "oil",
        "seal"
    ],
    "wof:name":"James Walker Australia Pty Ltd",
    "wof:placetype":"venue"
},
  "geometry": {"coordinates":[153.015182495,-27.5676860809],"type":"Point"}
}