{
  "type": "Feature",
  "properties": {
    "iso:country":"AU",
    "sg:address":"321 Downside St",
    "sg:city":"Albury",
    "sg:classifiers":[
        {
            "category":"Retail",
            "subcategory":"Repair Shop",
            "type":"Services"
        }
    ],
    "sg:phone":"+61 2 6021 6107",
    "sg:postcode":"2640",
    "sg:province":"NSW",
    "sg:tags":[
        "repairing",
        "piano",
        "tuning"
    ],
    "wof:name":"Ashley Ken",
    "wof:placetype":"venue"
},
  "geometry": {"coordinates":[146.930130005,-36.0825653076],"type":"Point"}
}