{
  "type": "Feature",
  "properties": {
    "iso:country":"AU",
    "sg:address":"117 Ryedale Rd",
    "sg:city":"West Ryde",
    "sg:classifiers":[
        {
            "category":"Arena",
            "subcategory":"Sports Club",
            "type":"Entertainment"
        }
    ],
    "sg:phone":"+61 2 9807 2444",
    "sg:postcode":"2114",
    "sg:province":"NSW",
    "sg:tags":[
        "league",
        "rugby"
    ],
    "wof:name":"Ryde Eastwood Leagues Club",
    "wof:placetype":"venue"
},
  "geometry": {"coordinates":[151.091598511,-33.8057060242],"type":"Point"}
}