{
  "type": "Feature",
  "properties": {
    "addr:full":"PO Box 1332 Golden Grove SA 5125",
    "addr:postcode":"5125",
    "iso:country":"AU",
    "sg:address":"PO Box 1332",
    "sg:city":"Golden Grove",
    "sg:classifiers":[
        {
            "category":"Retail",
            "subcategory":"Auto Repair",
            "type":"Services"
        }
    ],
    "sg:phone":"+61 412 661 372",
    "sg:postcode":"5125",
    "sg:province":"SA",
    "sg:tags":[
        "beater",
        "painter",
        "panel"
    ],
    "wof:name":"Ducofix Northeast",
    "wof:placetype":"venue"
},
  "geometry": {"coordinates":[138.72293099999999,-34.779251],"type":"Point"}
}