{
  "type": "Feature",
  "properties": {
    "addr:full":"Rear 8 Station St Bayswater VIC 3153",
    "addr:housenumber":"8",
    "addr:postcode":"3153",
    "addr:street":"Station St",
    "iso:country":"AU",
    "sg:address":"Rear 8 Station St",
    "sg:city":"Bayswater",
    "sg:classifiers":[
        {
            "category":"Health Services",
            "subcategory":"Medical Lab",
            "type":"Services"
        }
    ],
    "sg:phone":"+61 3 9720 1897",
    "sg:postcode":"3153",
    "sg:province":"VIC",
    "sg:tags":[
        "laboratory",
        "dental"
    ],
    "wof:name":"Sier Kevin Denture Clinic",
    "wof:placetype":"venue"
},
  "geometry": {"coordinates":[145.26649475100001,-37.8412437439],"type":"Point"}
}