{
  "type": "Feature",
  "properties": {
    "addr:full":"Shp 13 1 Princess St St Albans VIC 3021",
    "addr:housenumber":"1",
    "addr:postcode":"3021",
    "addr:street":"Princess St",
    "iso:country":"AU",
    "sg:address":"Shp 13 1 Princess St",
    "sg:city":"St Albans",
    "sg:classifiers":[
        {
            "category":"Communications",
            "subcategory":"Film & Video Production",
            "type":"Services"
        }
    ],
    "sg:phone":"+61 3 9366 5298",
    "sg:postcode":"3021",
    "sg:province":"VIC",
    "sg:tags":[
        "dvd",
        "library"
    ],
    "wof:name":"Kayham Video",
    "wof:placetype":"venue"
},
  "geometry": {"coordinates":[144.801727,-37.745296],"type":"Point"}
}