{
  "type": "Feature",
  "properties": {
    "iso:country":"AU",
    "sg:address":"43 Camellia Crs",
    "sg:city":"Norlane",
    "sg:classifiers":[
        {
            "category":"Personal",
            "type":"Services"
        }
    ],
    "sg:phone":"+61 3 5275 0971",
    "sg:postcode":"3214",
    "sg:province":"VIC",
    "sg:tags":[
        "reducing",
        "treatment",
        "weight"
    ],
    "wof:name":"The Weight Works",
    "wof:placetype":"venue"
},
  "geometry": {"coordinates":[144.34771728499999,-38.0885391235],"type":"Point"}
}