{
  "type": "Feature",
  "properties": {
    "addr:full":"PO Box 516 Beaudesert QLD 4285",
    "addr:postcode":"4285",
    "iso:country":"AU",
    "sg:address":"PO Box 516",
    "sg:city":"Beaudesert",
    "sg:classifiers":[
        {
            "category":"Professional",
            "subcategory":"Engineering",
            "type":"Services"
        }
    ],
    "sg:phone":"+61 7 5543 1633",
    "sg:postcode":"4285",
    "sg:province":"QLD",
    "sg:tags":[
        "engineer"
    ],
    "wof:name":"Labrador Engineering",
    "wof:placetype":"venue"
},
  "geometry": {"coordinates":[152.984634,-27.948097],"type":"Point"}
}