{
  "type": "Feature",
  "properties": {
    "addr:full":"72- 80 Belgravia St Belmont WA 6104",
    "addr:housenumber":"80",
    "addr:postcode":"6104",
    "addr:street":"Belgravia St",
    "iso:country":"AU",
    "sg:address":"72- 80 Belgravia St",
    "sg:city":"Belmont",
    "sg:classifiers":[
        {
            "category":"Professional",
            "type":"Services"
        }
    ],
    "sg:phone":"+61 1800 266 066",
    "sg:postcode":"6104",
    "sg:province":"WA",
    "sg:tags":[
        "shop",
        "fitting"
    ],
    "wof:name":"Cooling Brothers Glass Company Pty Ltd",
    "wof:placetype":"venue"
},
  "geometry": {"coordinates":[115.928077698,-31.9484081268],"type":"Point"}
}