{
  "type": "Feature",
  "properties": {
    "addr:full":"31 Erin St Toowoomba QLD 4350",
    "addr:housenumber":"31",
    "addr:postcode":"4350",
    "addr:street":"Erin St",
    "iso:country":"AU",
    "sg:address":"31 Erin St",
    "sg:city":"Toowoomba",
    "sg:classifiers":[
        {
            "category":"Building & Trades",
            "subcategory":"Plumbing",
            "type":"Services"
        }
    ],
    "sg:phone":"+61 7 4633 4343",
    "sg:postcode":"4350",
    "sg:province":"QLD",
    "sg:tags":[
        "pump",
        "repairer"
    ],
    "wof:name":"A1 Divining & Drilling Services",
    "wof:placetype":"venue"
},
  "geometry": {"coordinates":[151.92614699999999,-27.541952],"type":"Point"}
}