{
  "type": "Feature",
  "properties": {
    "addr:full":"56 Gomms Rd Somerville VIC 3912",
    "addr:housenumber":"56",
    "addr:postcode":"3912",
    "addr:street":"Gomms Rd",
    "iso:country":"AU",
    "sg:address":"56 Gomms Rd",
    "sg:city":"Somerville",
    "sg:classifiers":[
        {
            "category":"Building & Trades",
            "subcategory":"Plumbing",
            "type":"Services"
        }
    ],
    "sg:phone":"+61 3 5977 7459",
    "sg:postcode":"3912",
    "sg:province":"VIC",
    "sg:tags":[
        "plumber",
        "gasfitters"
    ],
    "wof:name":"A & A Vanhoof",
    "wof:placetype":"venue"
},
  "geometry": {"coordinates":[145.16633605999999,-38.2166175842],"type":"Point"}
}