{
  "type": "Feature",
  "properties": {
    "addr:full":"1213 Botany Rd Mascot NSW 2020",
    "addr:housenumber":"1213",
    "addr:postcode":"2020",
    "addr:street":"Botany Rd",
    "iso:country":"AU",
    "sg:address":"1213 Botany Rd",
    "sg:city":"Mascot",
    "sg:classifiers":[
        {
            "category":"Food & Beverages",
            "subcategory":"Bakery",
            "type":"Retail Goods"
        }
    ],
    "sg:phone":"+61 2 9667 0300",
    "sg:postcode":"2020",
    "sg:province":"NSW",
    "sg:tags":[
        "cake",
        "shop",
        "pastry"
    ],
    "wof:name":"Athenaiko Cake Shop",
    "wof:placetype":"venue"
},
  "geometry": {"coordinates":[151.19427490199999,-33.9319000244],"type":"Point"}
}