{
  "type": "Feature",
  "properties": {
    "addr:full":"125- 127 Raglan St Waterloo NSW 2017",
    "addr:housenumber":"127",
    "addr:postcode":"2017",
    "addr:street":"Raglan St",
    "iso:country":"AU",
    "sg:address":"125- 127 Raglan St",
    "sg:city":"Waterloo",
    "sg:classifiers":[
        {
            "category":"Food & Beverages",
            "subcategory":"Supermarket",
            "type":"Retail Goods"
        }
    ],
    "sg:phone":"+61 2 9318 1754",
    "sg:postcode":"2017",
    "sg:province":"NSW",
    "sg:tags":[
        "grocery",
        "store"
    ],
    "wof:name":"Waterloo Mixed Business",
    "wof:placetype":"venue"
},
  "geometry": {"coordinates":[151.19984435999999,-33.8965301514],"type":"Point"}
}