{
  "type": "Feature",
  "properties": {
    "addr:full":"Lvl3/ 61-63 Market St Sydney NSW 2000",
    "addr:housenumber":"61-63",
    "addr:postcode":"2000",
    "addr:street":"Market St",
    "iso:country":"AU",
    "sg:address":"Lvl3/ 61-63 Market St",
    "sg:city":"Sydney",
    "sg:classifiers":[
        {
            "category":"Retail",
            "subcategory":"Repair Shop",
            "type":"Services"
        }
    ],
    "sg:phone":"+61 2 9261 3550",
    "sg:postcode":"2000",
    "sg:province":"NSW",
    "sg:tags":[
        "mending",
        "clothing",
        "alteration"
    ],
    "wof:name":"Sew Special",
    "wof:placetype":"venue"
},
  "geometry": {"coordinates":[151.209182739,-33.8718948364],"type":"Point"}
}