{
  "type": "Feature",
  "properties": {
    "iso:country":"AU",
    "sg:address":"PO Box 127",
    "sg:city":"Earlwood",
    "sg:classifiers":[
        {
            "category":"Manufacturing",
            "subcategory":"Jewelry",
            "type":"Manufacturing & Wholesale Goods"
        }
    ],
    "sg:phone":"+61 2 9150 8585",
    "sg:postcode":"2206",
    "sg:province":"NSW",
    "sg:tags":[
        "designer",
        "jewellery"
    ],
    "wof:name":"Penelope Ellen Jewellery",
    "wof:placetype":"venue"
},
  "geometry": {"coordinates":[151.124939,-33.926922],"type":"Point"}
}