{
  "type": "Feature",
  "properties": {
    "iso:country":"AU",
    "sg:address":"Level 3, 345 Ann St",
    "sg:city":"Brisbane",
    "sg:classifiers":[
        {
            "category":"Personal",
            "subcategory":"Beauty Salon",
            "type":"Services"
        }
    ],
    "sg:phone":"+61 1300 304 247",
    "sg:postcode":"4000",
    "sg:province":"QLD",
    "sg:tags":[
        "hair",
        "treatment",
        "replacement"
    ],
    "wof:name":"Ashley & Martin",
    "wof:placetype":"venue"
},
  "geometry": {"coordinates":[153.02874755900001,-27.4644145966],"type":"Point"}
}