{
  "type": "Feature",
  "properties": {
    "addr:full":"Aspley Village Medical Centre 605 Robinson Rd Aspley QLD 4034",
    "addr:housenumber":"605",
    "addr:postcode":"4034",
    "addr:street":"Robinson Rd",
    "iso:country":"AU",
    "sg:address":"Aspley Village Medical Centre 605 Robinson Rd",
    "sg:city":"Aspley",
    "sg:classifiers":[
        {
            "category":"Health Services",
            "subcategory":"Doctor",
            "type":"Services"
        }
    ],
    "sg:phone":"+61 7 3862 8099",
    "sg:postcode":"4034",
    "sg:province":"QLD",
    "sg:tags":[
        "medical",
        "practitioner"
    ],
    "wof:name":"Price, Kathryn",
    "wof:placetype":"venue"
},
  "geometry": {"coordinates":[153.02392599999999,-27.364723],"type":"Point"}
}