{
  "type": "Feature",
  "properties": {
    "iso:country":"AU",
    "sg:address":"21 Discovery Crs",
    "sg:city":"Port Kennedy",
    "sg:classifiers":[
        {
            "category":"Retail",
            "subcategory":"Repair Shop",
            "type":"Services"
        }
    ],
    "sg:phone":"+61 8 9524 6252",
    "sg:postcode":"6172",
    "sg:province":"WA",
    "sg:tags":[
        "machine",
        "repairs",
        "part",
        "dryer",
        "washing"
    ],
    "wof:name":"Endeavour Appliance Services",
    "wof:placetype":"venue"
},
  "geometry": {"coordinates":[115.749763,-32.371109],"type":"Point"}
}