{
  "type": "Feature",
  "properties": {
    "iso:country":"AU",
    "sg:address":"500 Churchill Rd",
    "sg:city":"Kilburn",
    "sg:classifiers":[
        {
            "category":"Utilities",
            "subcategory":"Refuse",
            "type":"Services"
        }
    ],
    "sg:phone":"+61 8 8260 2122",
    "sg:postcode":"5084",
    "sg:province":"SA",
    "sg:tags":[
        "disposal",
        "reduction",
        "waste"
    ],
    "wof:name":"Veolia Environmental Services",
    "wof:placetype":"venue"
},
  "geometry": {"coordinates":[138.58297729500001,-34.8552246094],"type":"Point"}
}