{
  "type": "Feature",
  "properties": {
    "addr:full":"Compton Crt Maleny QLD 4552",
    "addr:postcode":"4552",
    "addr:street":"Compton Crt",
    "iso:country":"AU",
    "sg:address":"Compton Crt",
    "sg:city":"Maleny",
    "sg:classifiers":[
        {
            "category":"Personal",
            "subcategory":"Beauty Salon",
            "type":"Services"
        }
    ],
    "sg:phone":"+61 7 5494 2866",
    "sg:postcode":"4552",
    "sg:province":"QLD",
    "sg:tags":[
        "hairdresser"
    ],
    "wof:name":"Mostyn Ross Hairdressing",
    "wof:placetype":"venue"
},
  "geometry": {"coordinates":[152.84934997600001,-26.7581195831],"type":"Point"}
}