{
  "type": "Feature",
  "properties": {
    "addr:full":"12 Charlton Crt Stuart Park NT 0820",
    "addr:housenumber":"12",
    "addr:postcode":"0820",
    "addr:street":"Charlton Crt",
    "iso:country":"AU",
    "sg:address":"12 Charlton Crt",
    "sg:city":"Stuart Park",
    "sg:classifiers":[
        {
            "category":"Professional",
            "subcategory":"Printing & Photocopies",
            "type":"Services"
        }
    ],
    "sg:phone":"+61 8 8941 2122",
    "sg:postcode":"0820",
    "sg:province":"NT",
    "sg:tags":[
        "screen",
        "printer"
    ],
    "wof:name":"Stickers and Stuff",
    "wof:placetype":"venue"
},
  "geometry": {"coordinates":[130.85943603499999,-12.4316959381],"type":"Point"}
}