{
  "type": "Feature",
  "properties": {
    "iso:country":"AU",
    "sg:address":"346 Blaxcell St",
    "sg:city":"Granville",
    "sg:classifiers":[
        {
            "category":"Autos & Motor Vehicles",
            "subcategory":"Recreational Vehicle Sales",
            "type":"Retail Goods"
        }
    ],
    "sg:phone":"+61 2 9632 1956",
    "sg:postcode":"2142",
    "sg:province":"NSW",
    "sg:tags":[
        "confectionery"
    ],
    "wof:name":"Crystal Candies",
    "wof:placetype":"venue"
},
  "geometry": {"coordinates":[151.00726318400001,-33.8569908142],"type":"Point"}
}