{
  "type": "Feature",
  "properties": {
    "addr:full":"97 Kenilworth St Warwick QLD 4370",
    "addr:housenumber":"97",
    "addr:postcode":"4370",
    "addr:street":"Kenilworth St",
    "iso:country":"AU",
    "sg:address":"97 Kenilworth St",
    "sg:city":"Warwick",
    "sg:classifiers":[
        {
            "category":"Government",
            "subcategory":"Department Of Motor Vehicles",
            "type":"Public Place"
        }
    ],
    "sg:phone":"+61 7 4661 7513",
    "sg:postcode":"4370",
    "sg:province":"QLD",
    "sg:tags":[
        "tank",
        "cleaning"
    ],
    "wof:name":"Darling Downs Septic Service Specialists",
    "wof:placetype":"venue"
},
  "geometry": {"coordinates":[152.03700256400001,-28.2408351898],"type":"Point"}
}