{
  "type": "Feature",
  "properties": {
    "addr:full":"Shop 1, 76 George St Bathurst NSW 2795",
    "addr:housenumber":"shop;76",
    "addr:postcode":"2795",
    "addr:street":"George St",
    "iso:country":"AU",
    "sg:address":"Shop 1, 76 George St",
    "sg:city":"Bathurst",
    "sg:classifiers":[
        {
            "category":"Home & Garden",
            "subcategory":"Carpets & Floor Coverings",
            "type":"Retail Goods"
        }
    ],
    "sg:phone":"+61 2 6332 6750",
    "sg:postcode":"2795",
    "sg:province":"NSW",
    "sg:tags":[
        "layer",
        "planner"
    ],
    "wof:name":"Bathurst Independent Floors",
    "wof:placetype":"venue"
},
  "geometry": {"coordinates":[149.57847595199999,-33.4166641235],"type":"Point"}
}