{
  "type": "Feature",
  "properties": {
    "addr:full":"Linfield Station Pacific Hwy Lindfield NSW 2070",
    "addr:postcode":"2070",
    "addr:street":"Pacific Hwy",
    "iso:country":"AU",
    "sg:address":"Linfield Station Pacific Hwy",
    "sg:city":"Lindfield",
    "sg:classifiers":[
        {
            "category":"Personal",
            "subcategory":"Shoe Repair & Shine",
            "type":"Services"
        }
    ],
    "sg:phone":"+61 2 9416 6981",
    "sg:postcode":"2070",
    "sg:province":"NSW",
    "sg:tags":[
        "footwear"
    ],
    "wof:name":"Lindfield Shoe Repair",
    "wof:placetype":"venue"
},
  "geometry": {"coordinates":[151.16868591299999,-33.7751808167],"type":"Point"}
}