{
  "type": "Feature",
  "properties": {
    "addr:full":"103 Beatrice St Cheltenham VIC 3192",
    "addr:housenumber":"103",
    "addr:postcode":"3192",
    "addr:street":"Beatrice St",
    "iso:country":"AU",
    "sg:address":"103 Beatrice St",
    "sg:city":"Cheltenham",
    "sg:classifiers":[
        {
            "category":"Building & Trades",
            "subcategory":"Plumbing",
            "type":"Services"
        }
    ],
    "sg:phone":"+61 3 9584 2743",
    "sg:postcode":"3192",
    "sg:province":"VIC",
    "sg:tags":[
        "plumber",
        "gasfitters"
    ],
    "wof:name":"Williams D E & R A Pty Ltd",
    "wof:placetype":"venue"
},
  "geometry": {"coordinates":[145.08396911599999,-37.962310791],"type":"Point"}
}