{
  "type": "Feature",
  "properties": {
    "iso:country":"AU",
    "sg:address":"898 North Rd",
    "sg:city":"Bentleigh East",
    "sg:classifiers":[
        {
            "category":"Fast Food",
            "type":"Food & Drink"
        }
    ],
    "sg:phone":"+61 3 9570 4683",
    "sg:postcode":"3165",
    "sg:province":"VIC",
    "sg:tags":[
        "away",
        "take"
    ],
    "wof:name":"Pizza World",
    "wof:placetype":"venue"
},
  "geometry": {"coordinates":[145.06123352,-37.9067420959],"type":"Point"}
}