{
  "type": "Feature",
  "properties": {
    "addr:full":"44 Maroochy Spring Drv Dulong QLD 4560",
    "addr:housenumber":"44",
    "addr:postcode":"4560",
    "addr:street":"Maroochy Spring Drv",
    "iso:country":"AU",
    "sg:address":"44 Maroochy Spring Drv",
    "sg:city":"Dulong",
    "sg:classifiers":[
        {
            "category":"Building & Trades",
            "subcategory":"Construction",
            "type":"Services"
        }
    ],
    "sg:phone":"+61 411 648 760",
    "sg:postcode":"4560",
    "sg:province":"QLD",
    "sg:tags":[
        "contractor"
    ],
    "wof:name":"Schuckmann Design",
    "wof:placetype":"venue"
},
  "geometry": {"coordinates":[152.89094543499999,-26.6287269592],"type":"Point"}
}