{
  "type": "Feature",
  "properties": {
    "addr:full":"Shop 4, 232 Nepean Hwy Edithvale VIC 3196",
    "addr:housenumber":"shop 4 232",
    "addr:postcode":"3196",
    "addr:street":"Nepean Hwy",
    "iso:country":"AU",
    "sg:address":"Shop 4, 232 Nepean Hwy",
    "sg:city":"Edithvale",
    "sg:classifiers":[
        {
            "category":"Home & Garden",
            "subcategory":"Garden Supply",
            "type":"Retail Goods"
        }
    ],
    "sg:phone":"+61 3 9783 3006",
    "sg:postcode":"3196",
    "sg:province":"VIC",
    "sg:tags":[
        "equipment",
        "hydroponics"
    ],
    "wof:name":"Brew N&#039;Grow",
    "wof:placetype":"venue"
},
  "geometry": {"coordinates":[145.106964111,-38.0362205505],"type":"Point"}
}