{
  "type": "Feature",
  "properties": {
    "iso:country":"AU",
    "sg:address":"33 Compton St",
    "sg:city":"Adelaide",
    "sg:classifiers":[
        {
            "category":"Professional",
            "subcategory":"Accounting & Tax Preparation",
            "type":"Services"
        }
    ],
    "sg:phone":"+61 8 8212 7922",
    "sg:postcode":"5000",
    "sg:province":"SA",
    "sg:tags":[
        "accountant",
        "auditor"
    ],
    "wof:name":"Ma Victor",
    "wof:placetype":"venue"
},
  "geometry": {"coordinates":[138.596633911,-34.9315643311],"type":"Point"}
}