{
  "type": "Feature",
  "properties": {
    "addr:full":"13 Melaleuca Drv Upwey VIC 3158",
    "addr:housenumber":"13",
    "addr:postcode":"3158",
    "addr:street":"Melaleuca Drv",
    "iso:country":"AU",
    "sg:address":"13 Melaleuca Drv",
    "sg:city":"Upwey",
    "sg:classifiers":[
        {
            "category":"Retail",
            "subcategory":"Storage",
            "type":"Services"
        }
    ],
    "sg:phone":"+61 3 9754 5364",
    "sg:postcode":"3158",
    "sg:province":"VIC",
    "sg:tags":[
        "removal",
        "furniture"
    ],
    "wof:name":"Hare G J & A M",
    "wof:placetype":"venue"
},
  "geometry": {"coordinates":[145.325073242,-37.917755127],"type":"Point"}
}