{
  "type": "Feature",
  "properties": {
    "iso:country":"AU",
    "sg:address":"5/20- 24 Anne St",
    "sg:city":"St Marys",
    "sg:classifiers":[
        {
            "category":"Building & Trades",
            "subcategory":"Construction",
            "type":"Services"
        }
    ],
    "sg:phone":"+61 2 9833 8811",
    "sg:postcode":"2760",
    "sg:province":"NSW",
    "sg:tags":[
        "scaffolding"
    ],
    "wof:name":"Superior D.G.A. Hire Pty Ltd",
    "wof:placetype":"venue"
},
  "geometry": {"coordinates":[150.77171325699999,-33.7508773804],"type":"Point"}
}