{
  "type": "Feature",
  "properties": {
    "addr:full":"45- 79 Breakfast Creek Rd Newstead QLD 4006",
    "addr:housenumber":"79",
    "addr:postcode":"4006",
    "addr:street":"Breakfast Creek Rd",
    "iso:country":"AU",
    "sg:address":"45- 79 Breakfast Creek Rd",
    "sg:city":"Newstead",
    "sg:classifiers":[
        {
            "category":"Autos & Motor Vehicles",
            "subcategory":"Automobile Sales",
            "type":"Retail Goods"
        }
    ],
    "sg:phone":"+61 7 3364 1700",
    "sg:postcode":"4006",
    "sg:province":"QLD",
    "sg:tags":[
        "car",
        "new"
    ],
    "wof:name":"Austral Honda Landrover, Volkswagen",
    "wof:placetype":"venue"
},
  "geometry": {"coordinates":[153.042724609,-27.4474124908],"type":"Point"}
}