{
  "type": "Feature",
  "properties": {
    "addr:full":"Level 1/ 102 Gawler Pl Adelaide SA 5000",
    "addr:housenumber":"/ 102",
    "addr:postcode":"5000",
    "addr:street":"Gawler Pl",
    "iso:country":"AU",
    "sg:address":"Level 1/ 102 Gawler Pl",
    "sg:city":"Adelaide",
    "sg:classifiers":[
        {
            "category":"Health Services",
            "subcategory":"Health Practitioner",
            "type":"Services"
        }
    ],
    "sg:phone":"+61 8 8223 2456",
    "sg:postcode":"5000",
    "sg:province":"SA",
    "sg:tags":[
        "herbalist"
    ],
    "wof:name":"Chelsea Prescott",
    "wof:placetype":"venue"
},
  "geometry": {"coordinates":[138.60218810999999,-34.9248695374],"type":"Point"}
}