{
  "type": "Feature",
  "properties": {
    "addr:full":"Unit 3 /29 Export Drive Molendinar Molendinar QLD 4214",
    "addr:housenumber":"29",
    "addr:postcode":"4214",
    "addr:street":"Export Drive",
    "iso:country":"AU",
    "sg:address":"Unit 3",
    "sg:city":"/29 Export Drive Molendinar Molendinar",
    "sg:classifiers":[
        {
            "category":"Professional",
            "subcategory":"Detective & Security Services",
            "type":"Services"
        }
    ],
    "sg:phone":"+61 7 5563 1409",
    "sg:postcode":"4214",
    "sg:province":"QLD",
    "sg:tags":[
        "consultant",
        "system"
    ],
    "wof:name":"C-cure Systems",
    "wof:placetype":"venue"
},
  "geometry": {"coordinates":[153.360031128,-27.967376709],"type":"Point"}
}