{
  "type": "Feature",
  "properties": {
    "addr:full":"Level 1/ 190 Queen St Melbourne VIC 3000",
    "addr:housenumber":"/ 190",
    "addr:postcode":"3000",
    "addr:street":"Queen St",
    "iso:country":"AU",
    "sg:address":"Level 1/ 190 Queen St",
    "sg:city":"Melbourne",
    "sg:classifiers":[
        {
            "category":"Social Services",
            "subcategory":"Retirement Home",
            "type":"Services"
        }
    ],
    "sg:phone":"+61 3 8641 6400",
    "sg:postcode":"3000",
    "sg:province":"VIC",
    "sg:tags":[
        "environmental",
        "consultant",
        "pollution"
    ],
    "wof:name":"Net Balance Management Group Pty Ltd",
    "wof:placetype":"venue"
},
  "geometry": {"coordinates":[144.96046447800001,-37.8140258789],"type":"Point"}
}