{
  "type": "Feature",
  "properties": {
    "addr:full":"Simonds Rd Leongatha VIC 3953",
    "addr:postcode":"3953",
    "addr:street":"Simonds Rd",
    "iso:country":"AU",
    "sg:address":"Simonds Rd",
    "sg:city":"Leongatha",
    "sg:classifiers":[
        {
            "category":"Professional",
            "type":"Services"
        }
    ],
    "sg:phone":"+61 3 5662 2284",
    "sg:postcode":"3953",
    "sg:province":"VIC",
    "sg:tags":[
        "transport"
    ],
    "wof:name":"Findlay R J & R H",
    "wof:placetype":"venue"
},
  "geometry": {"coordinates":[145.94703674300001,-38.4758605957],"type":"Point"}
}