{
  "type": "Feature",
  "properties": {
    "iso:country":"AU",
    "sg:address":"140 Marsh St",
    "sg:city":"Armidale",
    "sg:classifiers":[
        {
            "category":"Health Services",
            "subcategory":"Dentist",
            "type":"Services"
        }
    ],
    "sg:phone":"+61 2 6772 3522",
    "sg:postcode":"2350",
    "sg:province":"NSW",
    "wof:name":"Dewhurst Dental",
    "wof:placetype":"venue"
},
  "geometry": {"coordinates":[151.666305542,-30.5218219757],"type":"Point"}
}