{
  "type": "Feature",
  "properties": {
    "iso:country":"AU",
    "sg:address":"11 Young St",
    "sg:city":"Adelaide",
    "sg:classifiers":[
        {
            "category":"Travel",
            "subcategory":"Travel Agent",
            "type":"Entertainment"
        }
    ],
    "sg:phone":"+61 8 8212 7833",
    "sg:postcode":"5000",
    "sg:province":"SA",
    "sg:tags":[
        "consultant"
    ],
    "sg:website":"http://www.kirratours.com",
    "wof:name":"Kirra Tours",
    "wof:placetype":"venue"
},
  "geometry": {"coordinates":[138.59585571299999,-34.9262008667],"type":"Point"}
}