{
  "type": "Feature",
  "properties": {
    "addr:full":"336 Oxley Drv Runaway Bay QLD 4216",
    "addr:housenumber":"336",
    "addr:postcode":"4216",
    "addr:street":"Oxley Drv",
    "iso:country":"AU",
    "sg:address":"336 Oxley Drv",
    "sg:city":"Runaway Bay",
    "sg:classifiers":[
        {
            "category":"Social Services",
            "subcategory":"Child Care",
            "type":"Services"
        }
    ],
    "sg:phone":"+61 7 5537 9160",
    "sg:postcode":"4216",
    "sg:province":"QLD",
    "wof:name":"Kids World Runaway Bay",
    "wof:placetype":"venue"
},
  "geometry": {"coordinates":[153.38763427699999,-27.9213638306],"type":"Point"}
}