{
  "type": "Feature",
  "properties": {
    "iso:country":"AU",
    "sg:address":"Showroom 4 Flint Crt",
    "sg:city":"Varsity Lakes",
    "sg:classifiers":[
        {
            "category":"Home & Garden",
            "subcategory":"Carpets & Floor Coverings",
            "type":"Retail Goods"
        }
    ],
    "sg:phone":"+61 7 5522 0882",
    "sg:postcode":"4226",
    "sg:province":"QLD",
    "sg:tags":[
        "wood"
    ],
    "wof:name":"Ablaze Installations & Maintenance",
    "wof:placetype":"venue"
},
  "geometry": {"coordinates":[153.41226196299999,-28.1006584167],"type":"Point"}
}