{
  "type": "Feature",
  "properties": {
    "addr:full":"1275 Viveash Rd Swan View WA 6056",
    "addr:postcode":"1275;6056",
    "addr:street":"Viveash Rd",
    "iso:country":"AU",
    "sg:address":"1275 Viveash Rd",
    "sg:city":"Swan View",
    "sg:classifiers":[
        {
            "category":"Autos & Motor Vehicles",
            "subcategory":"Auto Supplies",
            "type":"Retail Goods"
        }
    ],
    "sg:phone":"+61 8 9255 1013",
    "sg:postcode":"6056",
    "sg:province":"WA",
    "sg:tags":[
        "camper-trailers",
        "caravan",
        "equipment"
    ],
    "wof:name":"Camp-Let (Aust) W.A.",
    "wof:placetype":"venue"
},
  "geometry": {"coordinates":[116.058570862,-31.8737754822],"type":"Point"}
}