{
  "type": "Feature",
  "properties": {
    "addr:full":"34 Victoria St Victor Harbor SA 5211",
    "addr:housenumber":"34",
    "addr:postcode":"5211",
    "addr:street":"Victoria St",
    "iso:country":"AU",
    "sg:address":"34 Victoria St",
    "sg:city":"Victor Harbor",
    "sg:classifiers":[
        {
            "category":"Professional",
            "subcategory":"Accounting & Tax Preparation",
            "type":"Services"
        }
    ],
    "sg:phone":"+61 8 8552 2822",
    "sg:postcode":"5211",
    "sg:province":"SA",
    "sg:tags":[
        "accountant",
        "auditor"
    ],
    "wof:name":"Price Michael & Co",
    "wof:placetype":"venue"
},
  "geometry": {"coordinates":[138.62001037600001,-35.5563316345],"type":"Point"}
}