{
  "type": "Feature",
  "properties": {
    "iso:country":"AU",
    "sg:address":"PO Box 6019",
    "sg:city":"Tweed Heads South",
    "sg:classifiers":[
        {
            "category":"Organizations",
            "subcategory":"Professional Association",
            "type":"Services"
        }
    ],
    "sg:phone":"+61 7 5513 1139",
    "sg:postcode":"2486",
    "sg:province":"NSW",
    "sg:tags":[
        "web",
        "internet"
    ],
    "wof:name":"Designs That Shine",
    "wof:placetype":"venue"
},
  "geometry": {"coordinates":[153.54444885300001,-28.2044506073],"type":"Point"}
}