{
  "type": "Feature",
  "properties": {
    "iso:country":"AU",
    "sg:address":"70 Mallard Rd",
    "sg:city":"King River",
    "sg:classifiers":[
        {
            "category":"Professional",
            "type":"Services"
        }
    ],
    "sg:phone":"+61 8 9844 3066",
    "sg:postcode":"6330",
    "sg:province":"WA",
    "sg:tags":[
        "transport"
    ],
    "wof:name":"Southern Regional Transport Pty Ltd",
    "wof:placetype":"venue"
},
  "geometry": {"coordinates":[117.890167236,-34.9554901123],"type":"Point"}
}