{
  "type": "Feature",
  "properties": {
    "addr:full":"18 Margaret St Palmwoods QLD 4555",
    "addr:housenumber":"18",
    "addr:postcode":"4555",
    "addr:street":"Margaret St",
    "iso:country":"AU",
    "sg:address":"18 Margaret St",
    "sg:city":"Palmwoods",
    "sg:classifiers":[
        {
            "category":"Health Services",
            "subcategory":"Optometrist",
            "type":"Services"
        }
    ],
    "sg:phone":"+61 7 5457 3333",
    "sg:postcode":"4555",
    "sg:province":"QLD",
    "wof:name":"Eye C U",
    "wof:placetype":"venue"
},
  "geometry": {"coordinates":[152.956207275,-26.6875400543],"type":"Point"}
}