{
  "type": "Feature",
  "properties": {
    "addr:full":"Lot 253 Bussell Hwy Carbunup River WA 6280",
    "addr:postcode":"6280",
    "addr:street":"Bussell Hwy Carbunup",
    "iso:country":"AU",
    "sg:address":"Lot 253 Bussell Hwy",
    "sg:city":"Carbunup River",
    "sg:classifiers":[
        {
            "category":"Farming",
            "subcategory":"Farm & Veterinary Services",
            "type":"Manufacturing & Wholesale Goods"
        }
    ],
    "sg:phone":"+61 8 9755 1166",
    "sg:postcode":"6280",
    "sg:province":"WA",
    "sg:tags":[
        "contracting"
    ],
    "wof:name":"Riverace Pty Ltd",
    "wof:placetype":"venue"
},
  "geometry": {"coordinates":[115.258460998,-33.6647262573],"type":"Point"}
}