{
  "type": "Feature",
  "properties": {
    "addr:full":"102 Valda St Blacktown NSW 2148",
    "addr:housenumber":"102",
    "addr:postcode":"2148",
    "addr:street":"Valda St",
    "iso:country":"AU",
    "sg:address":"102 Valda St",
    "sg:city":"Blacktown",
    "sg:classifiers":[
        {
            "category":"Home & Garden",
            "subcategory":"Carpets & Floor Coverings",
            "type":"Retail Goods"
        }
    ],
    "sg:phone":"+61 2 8807 4271",
    "sg:postcode":"2148",
    "sg:province":"NSW",
    "wof:name":"Schmick Tiling",
    "wof:placetype":"venue"
},
  "geometry": {"coordinates":[150.90467834500001,-33.781085968],"type":"Point"}
}