{
  "type": "Feature",
  "properties": {
    "iso:country":"AU",
    "sg:address":"34 Macleay St",
    "sg:city":"Bradbury",
    "sg:classifiers":[
        {
            "category":"Utilities",
            "subcategory":"Water",
            "type":"Services"
        }
    ],
    "sg:phone":"+61 2 4625 4744",
    "sg:postcode":"2560",
    "sg:province":"NSW",
    "sg:tags":[
        "hot",
        "system"
    ],
    "wof:name":"Alliband Electrical Services",
    "wof:placetype":"venue"
},
  "geometry": {"coordinates":[150.814987183,-34.0864143372],"type":"Point"}
}