{
  "type": "Feature",
  "properties": {
    "addr:full":"251 Hay St East Perth WA 6004",
    "addr:housenumber":"251",
    "addr:postcode":"6004",
    "addr:street":"Hay St East",
    "iso:country":"AU",
    "sg:address":"251 Hay St",
    "sg:city":"East Perth",
    "sg:classifiers":[
        {
            "category":"Professional",
            "subcategory":"Business Services",
            "type":"Services"
        }
    ],
    "sg:phone":"+61 1800 622 464",
    "sg:postcode":"6004",
    "sg:province":"WA",
    "sg:tags":[
        "broker"
    ],
    "wof:name":"Champion Settlements",
    "wof:placetype":"venue"
},
  "geometry": {"coordinates":[115.871101379,-31.9582824707],"type":"Point"}
}