{
  "type": "Feature",
  "properties": {
    "iso:country":"AU",
    "sg:address":"2/ 4",
    "sg:city":"Aluminium Cl Edgeworth",
    "sg:classifiers":[
        {
            "category":"Professional",
            "type":"Services"
        }
    ],
    "sg:phone":"+61 2 4958 3222",
    "sg:postcode":"2285",
    "sg:province":"NSW",
    "sg:tags":[
        "spray",
        "painting"
    ],
    "wof:name":"O&#039;Connor Steve Smash Repairs",
    "wof:placetype":"venue"
},
  "geometry": {"coordinates":[151.612884522,-32.9235305786],"type":"Point"}
}