{
  "type": "Feature",
  "properties": {
    "addr:full":"185 Ingham Rd West End (Townsville) QLD 4810",
    "addr:housenumber":"185",
    "addr:postcode":"4810",
    "addr:street":"Ingham Rd",
    "iso:country":"AU",
    "sg:address":"185 Ingham Rd",
    "sg:city":"West End (Townsville)",
    "sg:classifiers":[
        {
            "category":"Personal",
            "subcategory":"Tanning Parlor",
            "type":"Services"
        }
    ],
    "sg:phone":"+61 7 4721 3422",
    "sg:postcode":"4810",
    "sg:province":"QLD",
    "sg:tags":[
        "solarium"
    ],
    "wof:name":"Affordable Beauty",
    "wof:placetype":"venue"
},
  "geometry": {"coordinates":[146.78804,-19.26671],"type":"Point"}
}