{
  "type": "Feature",
  "properties": {
    "addr:full":"16 Dutton St Walkerston QLD 4751",
    "addr:housenumber":"16",
    "addr:postcode":"4751",
    "addr:street":"Dutton St",
    "iso:country":"AU",
    "sg:address":"16 Dutton St",
    "sg:city":"Walkerston",
    "sg:classifiers":[
        {
            "category":"Real Estate",
            "subcategory":"Real Estate Agent",
            "type":"Services"
        }
    ],
    "sg:phone":"+61 7 4959 2777",
    "sg:postcode":"4751",
    "sg:province":"QLD",
    "wof:name":"Borg's Real Estate",
    "wof:placetype":"venue"
},
  "geometry": {"coordinates":[149.06564299999999,-21.160563],"type":"Point"}
}