{
  "type": "Feature",
  "properties": {
    "iso:country":"AU",
    "sg:address":"Kennedy Creek Rd",
    "sg:city":"Kennedy",
    "sg:classifiers":[
        {
            "category":"Education",
            "subcategory":"School",
            "type":"Public Place"
        }
    ],
    "sg:phone":"+61 7 4066 0136",
    "sg:postcode":"4816",
    "sg:province":"QLD",
    "sg:tags":[
        "state",
        "except",
        "nsw"
    ],
    "wof:name":"Kennedy Primary School",
    "wof:placetype":"venue"
},
  "geometry": {"coordinates":[145.956406,-18.205683],"type":"Point"}
}