{
  "type": "Feature",
  "properties": {
    "addr:full":"Tully Gorge Rd Tully QLD 4854",
    "addr:postcode":"4854",
    "addr:street":"Gorge Rd",
    "iso:country":"AU",
    "sg:address":"Tully Gorge Rd",
    "sg:city":"Tully",
    "sg:classifiers":[
        {
            "category":"Home & Garden",
            "subcategory":"Carpets & Floor Coverings",
            "type":"Retail Goods"
        }
    ],
    "sg:phone":"+61 7 4068 1510",
    "sg:postcode":"4854",
    "sg:province":"QLD",
    "sg:tags":[
        "banana",
        "grower"
    ],
    "wof:name":"GJ Flegler Pty Ltd",
    "wof:placetype":"venue"
},
  "geometry": {"coordinates":[145.992095947,-18.0052108765],"type":"Point"}
}