{
  "type": "Feature",
  "properties": {
    "iso:country":"AU",
    "sg:address":"16 Foster St",
    "sg:city":"Tenambit",
    "sg:classifiers":[
        {
            "category":"Professional",
            "subcategory":"Engineering",
            "type":"Services"
        }
    ],
    "sg:phone":"+61 2 4933 5864",
    "sg:postcode":"2323",
    "sg:province":"NSW",
    "sg:tags":[
        "building",
        "prefabricated",
        "transportable",
        "industrial",
        "commercial"
    ],
    "wof:name":"Tolsaf Pty Ltd",
    "wof:placetype":"venue"
},
  "geometry": {"coordinates":[151.60650634800001,-32.7452812195],"type":"Point"}
}