{
  "type": "Feature",
  "properties": {
    "iso:country":"AU",
    "sg:address":"12 Byte St",
    "sg:city":"Yatala",
    "sg:classifiers":[
        {
            "category":"Wholesale",
            "subcategory":"Machinery & Supplies",
            "type":"Manufacturing & Wholesale Goods"
        }
    ],
    "sg:phone":"+61 7 3382 6600",
    "sg:postcode":"4207",
    "sg:province":"QLD",
    "sg:tags":[
        "equipment",
        "hydraulic"
    ],
    "wof:name":"Express Hydraulics",
    "wof:placetype":"venue"
},
  "geometry": {"coordinates":[153.23162841800001,-27.7578773499],"type":"Point"}
}