{
  "type": "Feature",
  "properties": {
    "iso:country":"AU",
    "sg:address":"20 Wright St",
    "sg:city":"Glenbrook",
    "sg:classifiers":[
        {
            "category":"Military Area",
            "subcategory":"Army Base",
            "type":"Public Place"
        }
    ],
    "sg:phone":"+61 414 391 234",
    "sg:postcode":"2773",
    "sg:province":"NSW",
    "sg:tags":[
        "concrete",
        "slab",
        "floor"
    ],
    "wof:name":"Calcrete Pty Ltd",
    "wof:placetype":"venue"
},
  "geometry": {"coordinates":[150.618484497,-33.7713661194],"type":"Point"}
}