{
  "type": "Feature",
  "properties": {
    "addr:full":"135 South West Hwy Serpentine WA 6125",
    "addr:housenumber":"135",
    "addr:postcode":"6125",
    "addr:street":"South West Hwy",
    "iso:country":"AU",
    "sg:address":"135 South West Hwy",
    "sg:city":"Serpentine",
    "sg:classifiers":[
        {
            "category":"Autos & Motor Vehicles",
            "subcategory":"Fuel & Gas Station",
            "type":"Retail Goods"
        }
    ],
    "sg:phone":"+61 8 9525 2202",
    "sg:postcode":"6125",
    "sg:province":"WA",
    "wof:name":"Shell Co Of Aust Ltd The",
    "wof:placetype":"venue"
},
  "geometry": {"coordinates":[115.99292755099999,-32.3608512878],"type":"Point"}
}