{
  "type": "Feature",
  "properties": {
    "iso:country":"AU",
    "sg:address":"3545 Frankston Flinder Rd",
    "sg:city":"Merricks",
    "sg:classifiers":[
        {
            "category":"Airport",
            "subcategory":"General Aviation",
            "type":"Transportation"
        }
    ],
    "sg:phone":"+61 428 542 126",
    "sg:postcode":"3916",
    "sg:province":"VIC",
    "sg:tags":[
        "helicopter"
    ],
    "wof:name":"Hawkeye Helicopters",
    "wof:placetype":"venue"
},
  "geometry": {"coordinates":[145.08360290499999,-38.3973808289],"type":"Point"}
}