{
  "type": "Feature",
  "properties": {
    "iso:country":"AU",
    "sg:address":"3 / 73 Leopold St",
    "sg:city":"South Yarra",
    "sg:classifiers":[
        {
            "category":"Building & Trades",
            "subcategory":"Construction",
            "type":"Services"
        }
    ],
    "sg:phone":"+61 3 9820 3371",
    "sg:postcode":"3141",
    "sg:province":"VIC",
    "sg:tags":[
        "waterproofing",
        "contractor"
    ],
    "wof:name":"National Waterproofing & Industrial Flooring Pty Ltd",
    "wof:placetype":"venue"
},
  "geometry": {"coordinates":[144.982788086,-37.8361549377],"type":"Point"}
}