{
  "type": "Feature",
  "properties": {
    "iso:country":"AU",
    "sg:address":"70 East Esp",
    "sg:city":"St Albans",
    "sg:classifiers":[
        {
            "category":"Building & Trades",
            "subcategory":"Landscaping Services",
            "type":"Services"
        }
    ],
    "sg:phone":"+61 3 9366 1682",
    "sg:postcode":"3021",
    "sg:province":"VIC",
    "sg:tags":[
        "consultant"
    ],
    "wof:name":"Econo Building Contractors",
    "wof:placetype":"venue"
},
  "geometry": {"coordinates":[144.795975,-37.734512],"type":"Point"}
}