{
  "type": "Feature",
  "properties": {
    "addr:full":"Unit 5/ 707 Forest Rd Peakhurst NSW 2210",
    "addr:housenumber":"/ 707",
    "addr:postcode":"2210",
    "addr:street":"Forest Rd",
    "iso:country":"AU",
    "sg:address":"Unit 5/ 707 Forest Rd",
    "sg:city":"Peakhurst",
    "sg:classifiers":[
        {
            "category":"Government",
            "subcategory":"Post Office",
            "type":"Public Place"
        }
    ],
    "sg:phone":"+61 2 8338 8188",
    "sg:postcode":"2210",
    "sg:province":"NSW",
    "sg:tags":[
        "postal"
    ],
    "wof:name":"Trade Envelopes",
    "wof:placetype":"venue"
},
  "geometry": {"coordinates":[151.06202697800001,-33.9599838257],"type":"Point"}
}