{
  "type": "Feature",
  "properties": {
    "iso:country":"AU",
    "sg:address":"2 Malloy St",
    "sg:city":"Rochester",
    "sg:classifiers":[
        {
            "category":"Professional",
            "subcategory":"Engineering",
            "type":"Services"
        }
    ],
    "sg:phone":"+61 3 5484 1746",
    "sg:postcode":"3561",
    "sg:province":"VIC",
    "sg:tags":[
        "engineer"
    ],
    "wof:name":"Paul Evan's Welding",
    "wof:placetype":"venue"
},
  "geometry": {"coordinates":[144.698318481,-36.3600311279],"type":"Point"}
}