{
  "type": "Feature",
  "properties": {
    "addr:full":"184 Hugh St Currajong QLD 4812",
    "addr:housenumber":"184",
    "addr:postcode":"4812",
    "addr:street":"Hugh St",
    "iso:country":"AU",
    "sg:address":"184 Hugh St",
    "sg:city":"Currajong",
    "sg:classifiers":[
        {
            "category":"Industrial Area",
            "type":"Public Place"
        }
    ],
    "sg:phone":"+61 7 4725 8166",
    "sg:postcode":"4812",
    "sg:province":"QLD",
    "sg:tags":[
        "protective",
        "clothing"
    ],
    "wof:name":"Totally Workwear",
    "wof:placetype":"venue"
},
  "geometry": {"coordinates":[146.78218100000001,-19.274635],"type":"Point"}
}