{
  "type": "Feature",
  "properties": {
    "iso:country":"AU",
    "sg:address":"184 Hugh St",
    "sg:city":"Currajong",
    "sg:classifiers":[
        {
            "category":"Industrial Area",
            "type":"Public Place"
        }
    ],
    "sg:phone":"+61 7 4725 8166",
    "sg:postcode":"4812",
    "sg:province":"QLD",
    "sg:tags":[
        "protective",
        "clothing"
    ],
    "wof:name":"Totally Workwear",
    "wof:placetype":"venue"
},
  "geometry": {"coordinates":[146.782181,-19.274635],"type":"Point"}
}