{
  "type": "Feature",
  "properties": {
    "addr:full":"Shop 2, 1525 Warrego Hwy Blacksoil QLD 4306",
    "addr:housenumber":"shop 2",
    "addr:postcode":"1525;4306",
    "addr:street":"Warrego Hwy",
    "iso:country":"AU",
    "sg:address":"Shop 2, 1525 Warrego Hwy",
    "sg:city":"Blacksoil",
    "sg:classifiers":[
        {
            "category":"Food & Beverages",
            "subcategory":"Liquor & Beverages",
            "type":"Retail Goods"
        }
    ],
    "sg:phone":"+61 7 3813 0451",
    "sg:postcode":"4306",
    "sg:province":"QLD",
    "sg:tags":[
        "store"
    ],
    "wof:name":"Liquor Legends",
    "wof:placetype":"venue"
},
  "geometry": {"coordinates":[152.70289611800001,-27.5754718781],"type":"Point"}
}