{
  "type": "Feature",
  "properties": {
    "addr:full":"Level 9, 12 - 14 Marine Pde Southport QLD 4215",
    "addr:housenumber":"12 14",
    "addr:postcode":"4215",
    "addr:street":"Marine Pde",
    "iso:country":"AU",
    "sg:address":"Level 9, 12 - 14 Marine Pde",
    "sg:city":"Southport",
    "sg:classifiers":[
        {
            "category":"Building & Trades",
            "subcategory":"Construction",
            "type":"Services"
        }
    ],
    "sg:phone":"+61 1300 850 075",
    "sg:postcode":"4215",
    "sg:province":"QLD",
    "sg:tags":[
        "home",
        "air conditioning"
    ],
    "wof:name":"Coolcraft Engineering",
    "wof:placetype":"venue"
},
  "geometry": {"coordinates":[153.41734314000001,-27.9712867737],"type":"Point"}
}