{
  "type": "Feature",
  "properties": {
    "addr:full":"145 Walker St Sebastopol VIC 3356",
    "addr:housenumber":"145",
    "addr:postcode":"3356",
    "addr:street":"Walker St",
    "iso:country":"AU",
    "sg:address":"145 Walker St",
    "sg:city":"Sebastopol",
    "sg:classifiers":[
        {
            "category":"Building & Trades",
            "subcategory":"Cleaning & Sanitation",
            "type":"Services"
        }
    ],
    "sg:phone":"+61 407 860 131",
    "sg:postcode":"3356",
    "sg:province":"VIC",
    "sg:tags":[
        "industrial",
        "commercial",
        "contractor"
    ],
    "wof:name":"Rowe I J & M J Pty Ltd",
    "wof:placetype":"venue"
},
  "geometry": {"coordinates":[143.83470199999999,-37.595444],"type":"Point"}
}