{
  "type": "Feature",
  "properties": {
    "addr:full":"57 Bourke St Tamworth NSW 2340",
    "addr:housenumber":"57",
    "addr:postcode":"2340",
    "addr:street":"Bourke St",
    "iso:country":"AU",
    "sg:address":"57 Bourke St",
    "sg:city":"Tamworth",
    "sg:classifiers":[
        {
            "category":"Education",
            "subcategory":"School",
            "type":"Public Place"
        }
    ],
    "sg:phone":"+61 2 6761 3781",
    "sg:postcode":"2340",
    "sg:province":"NSW",
    "sg:tags":[
        "boy"
    ],
    "wof:name":"William Cowper School",
    "wof:placetype":"venue"
},
  "geometry": {"coordinates":[150.937225342,-31.0822372437],"type":"Point"}
}