{
  "type": "Feature",
  "properties": {
    "iso:country":"AU",
    "sg:address":"Cnr Taylor & Tor Sts",
    "sg:city":"Toowoomba",
    "sg:classifiers":[
        {
            "category":"Retail",
            "subcategory":"Auto Repair",
            "type":"Services"
        }
    ],
    "sg:phone":"+61 7 4634 1801",
    "sg:postcode":"4350",
    "sg:province":"QLD",
    "sg:tags":[
        "repairer",
        "motor",
        "engineer"
    ],
    "wof:name":"Shell Auto Care",
    "wof:placetype":"venue"
},
  "geometry": {"coordinates":[151.927353,-27.564123],"type":"Point"}
}