{
  "type": "Feature",
  "properties": {
    "addr:full":"15 Lapis Crs Bardwell Valley NSW 2207",
    "addr:housenumber":"15",
    "addr:postcode":"2207",
    "addr:street":"Lapis Crs",
    "iso:country":"AU",
    "sg:address":"15 Lapis Crs",
    "sg:city":"Bardwell Valley",
    "sg:classifiers":[
        {
            "category":"Arena",
            "subcategory":"Indoor Arena",
            "type":"Entertainment"
        }
    ],
    "sg:phone":"+61 2 9567 9986",
    "sg:postcode":"2207",
    "sg:province":"NSW",
    "sg:tags":[
        "modelmakers"
    ],
    "wof:name":"Architectural Models Nsw T/as Matrix Models",
    "wof:placetype":"venue"
},
  "geometry": {"coordinates":[151.13298,-33.937119],"type":"Point"}
}