{
  "type": "Feature",
  "properties": {
    "addr:full":"18 Porter Ave Highton VIC 3216",
    "addr:housenumber":"18",
    "addr:postcode":"3216",
    "addr:street":"Porter Ave",
    "iso:country":"AU",
    "sg:address":"18 Porter Ave",
    "sg:city":"Highton",
    "sg:classifiers":[
        {
            "category":"Fast Food",
            "type":"Food & Drink"
        }
    ],
    "sg:phone":"+61 3 5243 0511",
    "sg:postcode":"3216",
    "sg:province":"VIC",
    "sg:tags":[
        "away",
        "take"
    ],
    "wof:name":"Bo Bo's Fish And Chips",
    "wof:placetype":"venue"
},
  "geometry": {"coordinates":[144.31752014200001,-38.1809501648],"type":"Point"}
}