{
  "type": "Feature",
  "properties": {
    "iso:country":"AU",
    "sg:address":"250 Mann St",
    "sg:city":"Armidale",
    "sg:classifiers":[
        {
            "category":"Professional",
            "subcategory":"Detective & Security Services",
            "type":"Services"
        }
    ],
    "sg:phone":"+61 2 6772 9377",
    "sg:postcode":"2350",
    "sg:province":"NSW",
    "sg:tags":[
        "equipment",
        "window",
        "doors"
    ],
    "wof:name":"New England Glass & Aluminium",
    "wof:placetype":"venue"
},
  "geometry": {"coordinates":[151.64262390100001,-30.5147209167],"type":"Point"}
}