{
  "type": "Feature",
  "properties": {
    "iso:country":"AU",
    "sg:address":"125 Bolsover St",
    "sg:city":"Rockhampton",
    "sg:classifiers":[
        {
            "category":"Health Services",
            "subcategory":"Dentist",
            "type":"Services"
        }
    ],
    "sg:phone":"+61 7 4927 2569",
    "sg:postcode":"4700",
    "sg:province":"QLD",
    "wof:name":"Daniels Carl",
    "wof:placetype":"venue"
},
  "geometry": {"coordinates":[150.51922607399999,-23.3880443573],"type":"Point"}
}