{
  "type": "Feature",
  "properties": {
    "addr:full":"640 Newcastle St West Perth WA 6005",
    "addr:housenumber":"640",
    "addr:postcode":"6005",
    "addr:street":"Newcastle St",
    "iso:country":"AU",
    "sg:address":"640 Newcastle St",
    "sg:city":"West Perth",
    "sg:classifiers":[
        {
            "category":"Retail",
            "subcategory":"Auto Rental",
            "type":"Services"
        }
    ],
    "sg:phone":"+61 8 9227 7111",
    "sg:postcode":"6005",
    "sg:province":"WA",
    "sg:tags":[
        "car",
        "hire",
        "minibus"
    ],
    "sg:website":"http://www.m2000car.com.au",
    "wof:name":"M2000 Car Rental",
    "wof:placetype":"venue"
},
  "geometry": {"coordinates":[115.843772888,-31.93816185],"type":"Point"}
}