{
  "type": "Feature",
  "properties": {
    "addr:full":"21 Nullamanna Rd Camp Mountain QLD 4520",
    "addr:housenumber":"21",
    "addr:postcode":"4520",
    "addr:street":"Nullamanna Rd",
    "iso:country":"AU",
    "sg:address":"21 Nullamanna Rd",
    "sg:city":"Camp Mountain",
    "sg:classifiers":[
        {
            "category":"Professional",
            "subcategory":"Computer Services",
            "type":"Services"
        }
    ],
    "sg:phone":"+61 7 3289 2426",
    "sg:postcode":"4520",
    "sg:province":"QLD",
    "sg:tags":[
        "equipment",
        "networking",
        "installation"
    ],
    "wof:name":"Skye Systems Pty Ltd",
    "wof:placetype":"venue"
},
  "geometry": {"coordinates":[152.88188199999999,-27.400801],"type":"Point"}
}