{
  "type": "Feature",
  "properties": {
    "addr:full":"1577a Ferntree Gully Rd Knoxfield VIC 3180",
    "addr:housenumber":"1577a",
    "addr:postcode":"3180",
    "addr:street":"Ferntree Gully Rd",
    "iso:country":"AU",
    "sg:address":"1577a Ferntree Gully Rd",
    "sg:city":"Knoxfield",
    "sg:classifiers":[
        {
            "category":"Personal",
            "subcategory":"Nail Salon",
            "type":"Services"
        }
    ],
    "sg:phone":"+61 3 9763 3002",
    "sg:postcode":"3180",
    "sg:province":"VIC",
    "sg:tags":[
        "artificial"
    ],
    "wof:name":"Just Claws",
    "wof:placetype":"venue"
},
  "geometry": {"coordinates":[145.24957275400001,-37.8948936462],"type":"Point"}
}