{
  "type": "Feature",
  "properties": {
    "addr:full":"257 Montague Rd Ingle Farm SA 5098",
    "addr:housenumber":"257",
    "addr:postcode":"5098",
    "addr:street":"Montague Rd",
    "iso:country":"AU",
    "sg:address":"257 Montague Rd",
    "sg:city":"Ingle Farm",
    "sg:classifiers":[
        {
            "category":"Retail",
            "subcategory":"Self-service Laundry",
            "type":"Services"
        }
    ],
    "sg:phone":"+61 8 8396 4252",
    "sg:postcode":"5098",
    "sg:province":"SA",
    "wof:name":"Ingle Farm Laundry",
    "wof:placetype":"venue"
},
  "geometry": {"coordinates":[138.651123047,-34.8289299011],"type":"Point"}
}