{
  "type": "Feature",
  "properties": {
    "iso:country":"AU",
    "sg:address":"2/ 82 Batesford Rd",
    "sg:city":"Chadstone",
    "sg:classifiers":[
        {
            "category":"Retail",
            "subcategory":"Repair Shop",
            "type":"Services"
        }
    ],
    "sg:phone":"+61 3 9807 6480",
    "sg:postcode":"3148",
    "sg:province":"VIC",
    "sg:tags":[
        "mending",
        "clothing",
        "alteration"
    ],
    "wof:name":"Lilian Fashion Alterations",
    "wof:placetype":"venue"
},
  "geometry": {"coordinates":[145.10044860799999,-37.8751182556],"type":"Point"}
}