{
  "type": "Feature",
  "properties": {
    "iso:country":"AU",
    "sg:address":"230 Darling St",
    "sg:city":"Balmain",
    "sg:classifiers":[
        {
            "category":"Real Estate",
            "subcategory":"Real Estate Agent",
            "type":"Services"
        }
    ],
    "sg:phone":"+61 2 9818 7192",
    "sg:postcode":"2041",
    "sg:province":"NSW",
    "wof:name":"Raine & Horne Balmain",
    "wof:placetype":"venue"
},
  "geometry": {"coordinates":[151.18469200000001,-33.858402],"type":"Point"}
}