{
  "type": "Feature",
  "properties": {
    "addr:full":"9 Gleniffer Rd Bellingen NSW 2454",
    "addr:housenumber":"9",
    "addr:postcode":"2454",
    "addr:street":"Gleniffer Rd",
    "iso:country":"AU",
    "sg:address":"9 Gleniffer Rd",
    "sg:city":"Bellingen",
    "sg:classifiers":[
        {
            "category":"Wholesale",
            "subcategory":"Medical Equipment & Supplies",
            "type":"Manufacturing & Wholesale Goods"
        }
    ],
    "sg:phone":"+61 2 6655 0155",
    "sg:postcode":"2454",
    "sg:province":"NSW",
    "sg:tags":[
        "aid",
        "care",
        "health",
        "home"
    ],
    "wof:name":"Galaxy Easy Access Baths",
    "wof:placetype":"venue"
},
  "geometry": {"coordinates":[152.884918,-30.437769],"type":"Point"}
}