{
  "type": "Feature",
  "properties": {
    "addr:full":"Atkin St Henley Beach SA 5022",
    "addr:postcode":"5022",
    "addr:street":"Atkin St",
    "iso:country":"AU",
    "sg:address":"Atkin St",
    "sg:city":"Henley Beach",
    "sg:classifiers":[
        {
            "category":"Education",
            "subcategory":"Special Training",
            "type":"Public Place"
        }
    ],
    "sg:phone":"+61 8 8353 3710",
    "sg:postcode":"5022",
    "sg:province":"SA",
    "sg:tags":[
        "school",
        "art"
    ],
    "wof:name":"Henley & Grange Arts Society Incorporated",
    "wof:placetype":"venue"
},
  "geometry": {"coordinates":[138.49790954599999,-34.9207000732],"type":"Point"}
}