{
  "type": "Feature",
  "properties": {
    "iso:country":"AU",
    "sg:address":"10 Sidnell St",
    "sg:city":"Geebung",
    "sg:classifiers":[
        {
            "category":"Home & Garden",
            "subcategory":"Building Materials",
            "type":"Retail Goods"
        }
    ],
    "sg:phone":"+61 416 270 215",
    "sg:postcode":"4034",
    "sg:province":"QLD",
    "sg:tags":[
        "lawn",
        "cutting",
        "maintenance"
    ],
    "wof:name":"Geebung Mowing & Maintenance Services",
    "wof:placetype":"venue"
},
  "geometry": {"coordinates":[153.044037,-27.374693],"type":"Point"}
}