{
  "type": "Feature",
  "properties": {
    "iso:country":"AU",
    "sg:address":"PO Box 1136",
    "sg:city":"Howard Springs",
    "sg:classifiers":[
        {
            "category":"Home & Garden",
            "subcategory":"Carpets & Floor Coverings",
            "type":"Retail Goods"
        }
    ],
    "sg:phone":"+61 417 896 013",
    "sg:postcode":"0835",
    "sg:province":"NT",
    "wof:name":"Territory Commercial Floors",
    "wof:placetype":"venue"
},
  "geometry": {"coordinates":[131.045792,-12.49626],"type":"Point"}
}