{
  "type": "Feature",
  "properties": {
    "addr:full":"4 Moric Ave Blaxland NSW 2774",
    "addr:housenumber":"4",
    "addr:postcode":"2774",
    "addr:street":"Moric Ave",
    "iso:country":"AU",
    "sg:address":"4 Moric Ave",
    "sg:city":"Blaxland",
    "sg:classifiers":[
        {
            "category":"Home & Garden",
            "subcategory":"Building Materials",
            "type":"Retail Goods"
        }
    ],
    "sg:phone":"+61 418 647 851",
    "sg:postcode":"2774",
    "sg:province":"NSW",
    "sg:tags":[
        "lawn",
        "cutting",
        "maintenance"
    ],
    "wof:name":"Mirage Lawns Gardens",
    "wof:placetype":"venue"
},
  "geometry": {"coordinates":[150.633834839,-33.7300453186],"type":"Point"}
}