{
  "type": "Feature",
  "properties": {
    "addr:full":"20 Gannet St Mt Eliza VIC 3930",
    "addr:housenumber":"20",
    "addr:postcode":"3930",
    "addr:street":"Gannet St",
    "iso:country":"AU",
    "sg:address":"20 Gannet St",
    "sg:city":"Mt Eliza",
    "sg:classifiers":[
        {
            "category":"Professional",
            "subcategory":"Art Services",
            "type":"Services"
        }
    ],
    "sg:phone":"+61 418 982 387",
    "sg:postcode":"3930",
    "sg:province":"VIC",
    "sg:tags":[
        "decorator",
        "painter"
    ],
    "wof:name":"Picaso Master Painting Contractors",
    "wof:placetype":"venue"
},
  "geometry": {"coordinates":[145.08168029800001,-38.2001228333],"type":"Point"}
}