{
  "type": "Feature",
  "properties": {
    "addr:full":"4 Stennett Rd Ingleburn NSW 2565",
    "addr:housenumber":"4",
    "addr:postcode":"2565",
    "addr:street":"Stennett Rd",
    "iso:country":"AU",
    "sg:address":"4 Stennett Rd",
    "sg:city":"Ingleburn",
    "sg:classifiers":[
        {
            "category":"Taxi",
            "type":"Transportation"
        }
    ],
    "sg:phone":"+61 2 9933 3300",
    "sg:postcode":"2565",
    "sg:province":"NSW",
    "sg:tags":[
        "truck"
    ],
    "wof:name":"TWT Couriers & Transport Systems",
    "wof:placetype":"venue"
},
  "geometry": {"coordinates":[150.855377197,-34.0002326965],"type":"Point"}
}