{
  "type": "Feature",
  "properties": {
    "addr:full":"5 Toulon Drv Lower Templestowe VIC 3107",
    "addr:housenumber":"5",
    "addr:postcode":"3107",
    "addr:street":"Toulon Drv Lower",
    "iso:country":"AU",
    "sg:address":"5 Toulon Drv",
    "sg:city":"Lower Templestowe",
    "sg:classifiers":[
        {
            "category":"Home & Garden",
            "subcategory":"Carpets & Floor Coverings",
            "type":"Retail Goods"
        }
    ],
    "sg:phone":"+61 403 236 820",
    "sg:postcode":"3107",
    "sg:province":"VIC",
    "sg:tags":[
        "tile",
        "wall",
        "layer"
    ],
    "wof:name":"Tiling Artist",
    "wof:placetype":"venue"
},
  "geometry": {"coordinates":[145.12994384800001,-37.7682914734],"type":"Point"}
}