{
  "type": "Feature",
  "properties": {
    "iso:country":"AU",
    "sg:address":"364- 366 Canterbury Rd",
    "sg:city":"Canterbury",
    "sg:classifiers":[
        {
            "category":"Retail",
            "subcategory":"Auto Repair",
            "type":"Services"
        }
    ],
    "sg:phone":"+61 2 9787 6833",
    "sg:postcode":"2193",
    "sg:province":"NSW",
    "sg:tags":[
        "beater",
        "painter",
        "panel"
    ],
    "wof:name":"Kenwell Auto Repair Centre",
    "wof:placetype":"venue"
},
  "geometry": {"coordinates":[151.126556,-33.9067],"type":"Point"}
}