{
  "type": "Feature",
  "properties": {
    "iso:country":"AU",
    "sg:address":"6 Bruce St",
    "sg:city":"Box Hill",
    "sg:classifiers":[
        {
            "category":"Health Services",
            "subcategory":"Health Practitioner",
            "type":"Services"
        }
    ],
    "sg:phone":"+61 3 9890 0781",
    "sg:postcode":"3128",
    "sg:province":"VIC",
    "sg:tags":[
        "dietitian"
    ],
    "wof:name":"Cocks Gabrielle",
    "wof:placetype":"venue"
},
  "geometry": {"coordinates":[145.122192383,-37.8170166016],"type":"Point"}
}