{
  "type": "Feature",
  "properties": {
    "iso:country":"AU",
    "sg:address":"2 Oak St",
    "sg:city":"Evans Head",
    "sg:classifiers":[
        {
            "category":"Shopping",
            "subcategory":"Clothing, Apparel, & Fashions",
            "type":"Retail Goods"
        }
    ],
    "sg:phone":"+61 2 6682 6066",
    "sg:postcode":"2473",
    "sg:province":"NSW",
    "sg:tags":[
        "lady",
        "wear"
    ],
    "wof:name":"Inne's On Oak",
    "wof:placetype":"venue"
},
  "geometry": {"coordinates":[153.43104553200001,-29.1180591583],"type":"Point"}
}