{
  "type": "Feature",
  "properties": {
    "addr:full":"90 Keppel St Bathurst NSW 2795",
    "addr:housenumber":"90",
    "addr:postcode":"2795",
    "addr:street":"Keppel St",
    "iso:country":"AU",
    "sg:address":"90 Keppel St",
    "sg:city":"Bathurst",
    "sg:classifiers":[
        {
            "category":"Utilities",
            "subcategory":"Telephone",
            "type":"Services"
        }
    ],
    "sg:phone":"+61 2 6332 4123",
    "sg:postcode":"2795",
    "sg:province":"NSW",
    "sg:tags":[
        "equipment",
        "system"
    ],
    "wof:name":"Internet Express",
    "wof:placetype":"venue"
},
  "geometry": {"coordinates":[149.57904052699999,-33.4215621948],"type":"Point"}
}