{
  "type": "Feature",
  "properties": {
    "iso:country":"AU",
    "sg:address":"59 Hanson Rd",
    "sg:city":"Gladstone",
    "sg:classifiers":[
        {
            "category":"Professional",
            "subcategory":"Art Services",
            "type":"Services"
        }
    ],
    "sg:phone":"+61 400 811 387",
    "sg:postcode":"4680",
    "sg:province":"QLD",
    "sg:tags":[
        "interior",
        "decorator"
    ],
    "wof:name":"Concept Design & Interiors",
    "wof:placetype":"venue"
},
  "geometry": {"coordinates":[151.24769592300001,-23.8412265778],"type":"Point"}
}