{
  "type": "Feature",
  "properties": {
    "iso:country":"AU",
    "sg:address":"49 Elizabeth St",
    "sg:city":"Launceston",
    "sg:classifiers":[
        {
            "category":"Building & Trades",
            "subcategory":"Landscaping Services",
            "type":"Services"
        }
    ],
    "sg:phone":"+61 3 6337 7000",
    "sg:postcode":"7250",
    "sg:province":"TAS",
    "sg:tags":[
        "grazier"
    ],
    "wof:name":"Connorville Station Pty Ltd",
    "wof:placetype":"venue"
},
  "geometry": {"coordinates":[147.13899230999999,-41.440574646],"type":"Point"}
}