{
  "type": "Feature",
  "properties": {
    "iso:country":"AU",
    "sg:address":"138 Murray St",
    "sg:city":"Colac",
    "sg:classifiers":[
        {
            "category":"Professional",
            "subcategory":"Art Services",
            "type":"Services"
        }
    ],
    "sg:phone":"+61 3 5231 3511",
    "sg:postcode":"3250",
    "sg:province":"VIC",
    "sg:tags":[
        "picture",
        "frame",
        "framing"
    ],
    "wof:name":"Colac Picture Framing",
    "wof:placetype":"venue"
},
  "geometry": {"coordinates":[143.58696,-38.339806],"type":"Point"}
}