{
  "type": "Feature",
  "properties": {
    "addr:full":"Suite 4, Level 3, 3974 Pacific Hwy Loganholme QLD 4129",
    "addr:housenumber":"3974",
    "addr:postcode":"4129",
    "addr:street":"Pacific Hwy",
    "iso:country":"AU",
    "sg:address":"Suite 4, Level 3, 3974 Pacific Hwy",
    "sg:city":"Loganholme",
    "sg:classifiers":[
        {
            "category":"Building & Trades",
            "subcategory":"Construction",
            "type":"Services"
        }
    ],
    "sg:phone":"+61 7 3801 9600",
    "sg:postcode":"4129",
    "sg:province":"QLD",
    "sg:tags":[
        "earth",
        "excavating",
        "moving",
        "contractor"
    ],
    "wof:name":"Lantrak",
    "wof:placetype":"venue"
},
  "geometry": {"coordinates":[153.17984008799999,-27.6705970764],"type":"Point"}
}