{
  "type": "Feature",
  "properties": {
    "addr:full":"PO Box 167 W Westcourt QLD 4870",
    "addr:postcode":"4870",
    "iso:country":"AU",
    "sg:address":"PO Box 167",
    "sg:city":"W Westcourt",
    "sg:classifiers":[
        {
            "category":"Real Estate",
            "subcategory":"Real Estate Agent",
            "type":"Services"
        }
    ],
    "sg:phone":"+61 1300 882 500",
    "sg:postcode":"4870",
    "sg:province":"QLD",
    "wof:name":"Australian Private Realty North QLD",
    "wof:placetype":"venue"
},
  "geometry": {"coordinates":[145.75128173799999,-16.9316501617],"type":"Point"}
}