{
  "type": "Feature",
  "properties": {
    "addr:full":"1/ 14 Tang St Coconut Grove NT 0810",
    "addr:housenumber":"/ 14",
    "addr:postcode":"0810",
    "addr:street":"Tang St",
    "iso:country":"AU",
    "sg:address":"1/ 14 Tang St",
    "sg:city":"Coconut Grove",
    "sg:classifiers":[
        {
            "category":"Shopping",
            "subcategory":"Bridal",
            "type":"Retail Goods"
        }
    ],
    "sg:phone":"+61 8 8985 6000",
    "sg:postcode":"0810",
    "sg:province":"NT",
    "sg:tags":[
        "hire",
        "wear"
    ],
    "wof:name":"La Sposa Bridal Boutique",
    "wof:placetype":"venue"
},
  "geometry": {"coordinates":[130.85482788100001,-12.3995952606],"type":"Point"}
}