{
  "type": "Feature",
  "properties": {
    "iso:country":"AU",
    "sg:address":"8 Kent St",
    "sg:city":"Rockingham",
    "sg:classifiers":[
        {
            "category":"Food & Beverages",
            "subcategory":"Bakery",
            "type":"Retail Goods"
        }
    ],
    "sg:phone":"+61 8 9527 1880",
    "sg:postcode":"6168",
    "sg:province":"WA",
    "sg:tags":[
        "baker"
    ],
    "wof:name":"Rockingham Beach Bakery",
    "wof:placetype":"venue"
},
  "geometry": {"coordinates":[115.730476,-32.276241],"type":"Point"}
}