{
  "type": "Feature",
  "properties": {
    "addr:full":"246 Stanbrough Rd Gumdale QLD 4154",
    "addr:housenumber":"246",
    "addr:postcode":"4154",
    "addr:street":"Stanbrough Rd",
    "iso:country":"AU",
    "sg:address":"246 Stanbrough Rd",
    "sg:city":"Gumdale",
    "sg:classifiers":[
        {
            "category":"Building & Trades",
            "subcategory":"Construction",
            "type":"Services"
        }
    ],
    "sg:phone":"+61 7 3890 2055",
    "sg:postcode":"4154",
    "sg:province":"QLD",
    "sg:tags":[
        "renovation",
        "alterations",
        "extension",
        "contractor"
    ],
    "wof:name":"Ian Kenyon Constructions Pty Ltd",
    "wof:placetype":"venue"
},
  "geometry": {"coordinates":[153.13949585,-27.4969100952],"type":"Point"}
}