{
  "type": "Feature",
  "properties": {
    "addr:full":"Suite 2 / 116 Rowe St Eastwood NSW 2122",
    "addr:housenumber":"/ 116",
    "addr:postcode":"2122",
    "addr:street":"Rowe St",
    "iso:country":"AU",
    "sg:address":"Suite 2 / 116 Rowe St",
    "sg:city":"Eastwood",
    "sg:classifiers":[
        {
            "category":"Building & Trades",
            "subcategory":"Construction",
            "type":"Services"
        }
    ],
    "sg:phone":"+61 2 9858 3737",
    "sg:postcode":"2122",
    "sg:province":"NSW",
    "sg:tags":[
        "contractor"
    ],
    "wof:name":"Metrovic Constructions",
    "wof:placetype":"venue"
},
  "geometry": {"coordinates":[151.0831604,-33.7912940979],"type":"Point"}
}