{
  "type": "Feature",
  "properties": {
    "addr:full":"Findon Ave Seaton SA 5023",
    "addr:postcode":"5023",
    "addr:street":"Findon Ave",
    "iso:country":"AU",
    "sg:address":"Findon Ave",
    "sg:city":"Seaton",
    "sg:classifiers":[
        {
            "category":"Social Services",
            "subcategory":"Child Care",
            "type":"Services"
        }
    ],
    "sg:phone":"+61 8 8347 1176",
    "sg:postcode":"5023",
    "sg:province":"SA",
    "wof:name":"Seaton Kids Care",
    "wof:placetype":"venue"
},
  "geometry": {"coordinates":[138.51454162600001,-34.8936309814],"type":"Point"}
}