{
  "type": "Feature",
  "properties": {
    "iso:country":"AU",
    "sg:address":"Factory 7/ 3 Hi-Tech Pl",
    "sg:city":"Rowville",
    "sg:classifiers":[
        {
            "category":"Retail",
            "subcategory":"Auto Repair",
            "type":"Services"
        }
    ],
    "sg:phone":"+61 3 9763 7898",
    "sg:postcode":"3178",
    "sg:province":"VIC",
    "sg:tags":[
        "transmission",
        "automotive",
        "car"
    ],
    "wof:name":"EKM Automatics",
    "wof:placetype":"venue"
},
  "geometry": {"coordinates":[145.244873047,-37.9106254578],"type":"Point"}
}