{
  "type": "Feature",
  "properties": {
    "iso:country":"AU",
    "sg:address":"156 Main St",
    "sg:city":"Pakenham",
    "sg:classifiers":[
        {
            "category":"Shopping",
            "subcategory":"Computers & Home Electronics",
            "type":"Retail Goods"
        }
    ],
    "sg:phone":"+61 3 5941 5081",
    "sg:postcode":"3810",
    "sg:province":"VIC",
    "sg:tags":[
        "small",
        "equipment",
        "business"
    ],
    "wof:name":"G B A Computers",
    "wof:placetype":"venue"
},
  "geometry": {"coordinates":[145.483063,-38.078632],"type":"Point"}
}