{
  "type": "Feature",
  "properties": {
    "addr:full":"138 Baillie St Horsham VIC 3400",
    "addr:housenumber":"138",
    "addr:postcode":"3400",
    "addr:street":"Baillie St",
    "iso:country":"AU",
    "sg:address":"138 Baillie St",
    "sg:city":"Horsham",
    "sg:classifiers":[
        {
            "category":"Train Station",
            "subcategory":"Rail",
            "type":"Transportation"
        }
    ],
    "sg:phone":"+61 3 5382 2811",
    "sg:postcode":"3400",
    "sg:province":"VIC",
    "sg:tags":[
        "goat",
        "farmer"
    ],
    "wof:name":"Sylvania Park Mohair Farm",
    "wof:placetype":"venue"
},
  "geometry": {"coordinates":[142.201248169,-36.7116012573],"type":"Point"}
}