{
  "type": "Feature",
  "properties": {
    "addr:full":"5 Chantilly St Mt Waverley VIC 3149",
    "addr:housenumber":"5",
    "addr:postcode":"3149",
    "addr:street":"Chantilly St Mt",
    "iso:country":"AU",
    "sg:address":"5 Chantilly St",
    "sg:city":"Mt Waverley",
    "sg:classifiers":[
        {
            "category":"Sports & Exercise",
            "subcategory":"Sports Center",
            "type":"Entertainment"
        }
    ],
    "sg:phone":"+61 3 9515 7312",
    "sg:postcode":"3149",
    "sg:province":"VIC",
    "sg:tags":[
        "coach",
        "tennis"
    ],
    "wof:name":"Roffey J A",
    "wof:placetype":"venue"
},
  "geometry": {"coordinates":[145.117675781,-37.8947029114],"type":"Point"}
}