{
  "type": "Feature",
  "properties": {
    "iso:country":"AU",
    "sg:address":"26 Silkes Rd",
    "sg:city":"Paradise",
    "sg:classifiers":[
        {
            "category":"Communications",
            "subcategory":"Film & Video Production",
            "type":"Services"
        }
    ],
    "sg:phone":"+61 8 8337 3545",
    "sg:postcode":"5075",
    "sg:province":"SA",
    "sg:tags":[
        "dvd",
        "library"
    ],
    "wof:name":"AustCom Trading Pty Ltd",
    "wof:placetype":"venue"
},
  "geometry": {"coordinates":[138.682983398,-34.8726730347],"type":"Point"}
}