{
  "type": "Feature",
  "properties": {
    "addr:full":"242- 244 Yarra St Warrandyte VIC 3113",
    "addr:housenumber":"244",
    "addr:postcode":"3113",
    "addr:street":"Yarra St",
    "iso:country":"AU",
    "sg:address":"242- 244 Yarra St",
    "sg:city":"Warrandyte",
    "sg:classifiers":[
        {
            "category":"Arts & Performance",
            "subcategory":"Art Gallery",
            "type":"Entertainment"
        }
    ],
    "sg:phone":"+61 3 9844 2642",
    "sg:postcode":"3113",
    "sg:province":"VIC",
    "wof:name":"The Bridge Gallery",
    "wof:placetype":"venue"
},
  "geometry": {"coordinates":[145.22410583499999,-37.7369155884],"type":"Point"}
}