{
  "type": "Feature",
  "properties": {
    "addr:full":"2 George St Scottsdale TAS 7260",
    "addr:housenumber":"2",
    "addr:postcode":"7260",
    "addr:street":"George St",
    "iso:country":"AU",
    "sg:address":"2 George St",
    "sg:city":"Scottsdale",
    "sg:classifiers":[
        {
            "category":"Autos & Motor Vehicles",
            "subcategory":"Fuel & Gas Station",
            "type":"Retail Goods"
        }
    ],
    "sg:phone":"+61 3 6352 2805",
    "sg:postcode":"7260",
    "sg:province":"TAS",
    "wof:name":"Shell Pineview Service Station",
    "wof:placetype":"venue"
},
  "geometry": {"coordinates":[147.51878400000001,-41.159279],"type":"Point"}
}