{
  "type": "Feature",
  "properties": {
    "iso:country":"AU",
    "sg:address":"312 Marrickville Rd",
    "sg:city":"Marrickville",
    "sg:classifiers":[
        {
            "category":"Health Services",
            "subcategory":"Doctor",
            "type":"Services"
        }
    ],
    "sg:phone":"+61 2 9569 7222",
    "sg:postcode":"2204",
    "sg:province":"NSW",
    "sg:tags":[
        "medical",
        "practitioner"
    ],
    "wof:name":"Garber Mervyn Dr",
    "wof:placetype":"venue"
},
  "geometry": {"coordinates":[151.155639648,-33.910320282],"type":"Point"}
}