{
  "type": "Feature",
  "properties": {
    "iso:country":"AU",
    "sg:address":"175 Glenroy Rd",
    "sg:city":"Glenroy",
    "sg:classifiers":[
        {
            "category":"Professional",
            "subcategory":"Employment Agencies",
            "type":"Services"
        }
    ],
    "sg:phone":"+61 3 9306 5444",
    "sg:postcode":"3046",
    "sg:province":"VIC",
    "wof:name":"A.M.E.S. Employment Services",
    "wof:placetype":"venue"
},
  "geometry": {"coordinates":[144.919525147,-37.7057571411],"type":"Point"}
}