{
  "type": "Feature",
  "properties": {
    "addr:full":"29 Bedford St Queanbeyan NSW 2620",
    "addr:housenumber":"29",
    "addr:postcode":"2620",
    "addr:street":"Bedford St",
    "iso:country":"AU",
    "sg:address":"29 Bedford St",
    "sg:city":"Queanbeyan",
    "sg:classifiers":[
        {
            "category":"Shopping",
            "subcategory":"Clothing, Apparel, & Fashions",
            "type":"Retail Goods"
        }
    ],
    "sg:phone":"+61 2 6284 2060",
    "sg:postcode":"2620",
    "sg:province":"NSW",
    "sg:tags":[
        "uniform"
    ],
    "wof:name":"First Impressions",
    "wof:placetype":"venue"
},
  "geometry": {"coordinates":[149.20413207999999,-35.3516807556],"type":"Point"}
}