{
  "type": "Feature",
  "properties": {
    "addr:full":"7 Falvey Crs Goodna QLD 4300",
    "addr:housenumber":"7",
    "addr:postcode":"4300",
    "addr:street":"Falvey Crs",
    "iso:country":"AU",
    "sg:address":"7 Falvey Crs",
    "sg:city":"Goodna",
    "sg:classifiers":[
        {
            "category":"Retail",
            "subcategory":"Auto Rental",
            "type":"Services"
        }
    ],
    "sg:phone":"+61 7 3848 0044",
    "sg:postcode":"4300",
    "sg:province":"QLD",
    "sg:tags":[
        "camper-trailers",
        "caravan",
        "hire"
    ],
    "wof:name":"Kool Cat Caravan & Camper & Trailer Hire & Sales",
    "wof:placetype":"venue"
},
  "geometry": {"coordinates":[152.782546997,-27.6645088196],"type":"Point"}
}