{
  "type": "Feature",
  "properties": {
    "addr:full":"60 May Rd Narraweena NSW 2099",
    "addr:housenumber":"60",
    "addr:postcode":"2099",
    "addr:street":"May Rd",
    "iso:country":"AU",
    "sg:address":"60 May Rd",
    "sg:city":"Narraweena",
    "sg:classifiers":[
        {
            "category":"Fast Food",
            "type":"Food & Drink"
        }
    ],
    "sg:phone":"+61 2 9984 1777",
    "sg:postcode":"2099",
    "sg:province":"NSW",
    "sg:tags":[
        "away",
        "take"
    ],
    "wof:name":"Narraweena Pizza, Pida & Kebab House",
    "wof:placetype":"venue"
},
  "geometry": {"coordinates":[151.27580261200001,-33.7553329468],"type":"Point"}
}