{
  "type": "Feature",
  "properties": {
    "addr:full":"16 Henry St Paralowie SA 5108",
    "addr:housenumber":"16",
    "addr:postcode":"5108",
    "addr:street":"Henry St",
    "iso:country":"AU",
    "sg:address":"16 Henry St",
    "sg:city":"Paralowie",
    "sg:classifiers":[
        {
            "category":"Personal",
            "subcategory":"Beauty Salon",
            "type":"Services"
        }
    ],
    "sg:phone":"+61 8 8280 5078",
    "sg:postcode":"5108",
    "sg:province":"SA",
    "sg:tags":[
        "hairdresser"
    ],
    "wof:name":"Chizell Hair",
    "wof:placetype":"venue"
},
  "geometry": {"coordinates":[138.593826294,-34.7595977783],"type":"Point"}
}