{
  "type": "Feature",
  "properties": {
    "addr:full":"Bellenden Rd Euramo QLD 4854",
    "addr:postcode":"4854",
    "addr:street":"Bellenden Rd",
    "iso:country":"AU",
    "sg:address":"Bellenden Rd",
    "sg:city":"Euramo",
    "sg:classifiers":[
        {
            "category":"Farming",
            "subcategory":"Farm",
            "type":"Manufacturing & Wholesale Goods"
        }
    ],
    "sg:phone":"+61 7 4066 5525",
    "sg:postcode":"4854",
    "sg:province":"QLD",
    "sg:tags":[
        "farmer"
    ],
    "wof:name":"Jackson P W & V J",
    "wof:placetype":"venue"
},
  "geometry": {"coordinates":[145.90293884299999,-18.0355682373],"type":"Point"}
}