{
  "type": "Feature",
  "properties": {
    "addr:full":"suite 15 50 stanley St East Sydney NSW 2010",
    "addr:housenumber":"50",
    "addr:postcode":"2010",
    "addr:street":"Stanley St East",
    "iso:country":"AU",
    "sg:address":"suite 15 50 stanley St",
    "sg:city":"East Sydney",
    "sg:classifiers":[
        {
            "category":"Professional",
            "subcategory":"Art Services",
            "type":"Services"
        }
    ],
    "sg:phone":"+61 404 803 735",
    "sg:postcode":"2010",
    "sg:province":"NSW",
    "sg:tags":[
        "graphic",
        "designer"
    ],
    "wof:name":"Creative Tank",
    "wof:placetype":"venue"
},
  "geometry": {"coordinates":[151.214569092,-33.8755378723],"type":"Point"}
}