{
  "type": "Feature",
  "properties": {
    "iso:country":"AU",
    "sg:address":"33 Parke Rd",
    "sg:city":"Gooseberry Hill",
    "sg:classifiers":[
        {
            "category":"Professional",
            "subcategory":"Management & Consulting",
            "type":"Services"
        }
    ],
    "sg:phone":"+61 8 9293 2719",
    "sg:postcode":"6076",
    "sg:province":"WA",
    "sg:tags":[
        "consultant",
        "educational"
    ],
    "wof:name":"Kirton & Durack Consultancy",
    "wof:placetype":"venue"
},
  "geometry": {"coordinates":[116.047798157,-31.964176178],"type":"Point"}
}