{
  "type": "Feature",
  "properties": {
    "addr:full":"66 Bryants Rd Loganholme QLD 4129",
    "addr:housenumber":"66",
    "addr:postcode":"4129",
    "addr:street":"Bryants Rd",
    "iso:country":"AU",
    "sg:address":"66 Bryants Rd",
    "sg:city":"Loganholme",
    "sg:classifiers":[
        {
            "category":"Health Services",
            "subcategory":"Doctor",
            "type":"Services"
        }
    ],
    "sg:phone":"+61 7 3801 2233",
    "sg:postcode":"4129",
    "sg:province":"QLD",
    "sg:tags":[
        "medical",
        "practitioner"
    ],
    "wof:name":"Miros Michael",
    "wof:placetype":"venue"
},
  "geometry": {"coordinates":[153.17645263700001,-27.6626434326],"type":"Point"}
}