{
  "type": "Feature",
  "properties": {
    "iso:country":"AU",
    "sg:address":"6 Ryelane St",
    "sg:city":"Maddington",
    "sg:classifiers":[
        {
            "category":"Professional",
            "type":"Services"
        }
    ],
    "sg:phone":"+61 8 9493 3324",
    "sg:postcode":"6109",
    "sg:province":"WA",
    "sg:tags":[
        "coating",
        "powder"
    ],
    "wof:name":"Prestige Powdercoaters (WA) Pty Ltd",
    "wof:placetype":"venue"
},
  "geometry": {"coordinates":[115.990097046,-32.0435142517],"type":"Point"}
}