{
  "type": "Feature",
  "properties": {
    "addr:full":"Beaumont Rd Smithfield Plains SA 5114",
    "addr:postcode":"5114",
    "addr:street":"Beaumont Rd",
    "iso:country":"AU",
    "sg:address":"Beaumont Rd",
    "sg:city":"Smithfield Plains",
    "sg:classifiers":[
        {
            "category":"Education",
            "subcategory":"School",
            "type":"Public Place"
        }
    ],
    "sg:phone":"+61 8 8254 6555",
    "sg:postcode":"5114",
    "sg:province":"SA",
    "sg:tags":[
        "state",
        "except",
        "nsw"
    ],
    "wof:name":"Smithfield Plains High School",
    "wof:placetype":"venue"
},
  "geometry": {"coordinates":[138.675323486,-34.6791343689],"type":"Point"}
}