{
  "type": "Feature",
  "properties": {
    "addr:full":"14 Richings Drv Youngtown TAS 7249",
    "addr:housenumber":"14",
    "addr:postcode":"7249",
    "addr:street":"Richings Drv",
    "iso:country":"AU",
    "sg:address":"14 Richings Drv",
    "sg:city":"Youngtown",
    "sg:classifiers":[
        {
            "category":"Professional",
            "subcategory":"Accounting & Tax Preparation",
            "type":"Services"
        }
    ],
    "sg:phone":"+61 3 6344 6157",
    "sg:postcode":"7249",
    "sg:province":"TAS",
    "sg:tags":[
        "bookkeeping"
    ],
    "wof:name":"Busy Bookkeeping Launceston",
    "wof:placetype":"venue"
},
  "geometry": {"coordinates":[147.183349609,-41.4812507629],"type":"Point"}
}