{
  "type": "Feature",
  "properties": {
    "iso:country":"AU",
    "sg:address":"10 Prices Rd",
    "sg:city":"Gladysdale",
    "sg:classifiers":[
        {
            "category":"Farming",
            "subcategory":"Vineyard",
            "type":"Manufacturing & Wholesale Goods"
        }
    ],
    "sg:phone":"+61 3 5966 6257",
    "sg:postcode":"3797",
    "sg:province":"VIC",
    "sg:tags":[
        "winery"
    ],
    "wof:name":"Peggies",
    "wof:placetype":"venue"
},
  "geometry": {"coordinates":[145.643234253,-37.8409881592],"type":"Point"}
}