{
  "type": "Feature",
  "properties": {
    "iso:country":"AU",
    "sg:address":"18 Moondarra Crs",
    "sg:city":"Mooloolaba",
    "sg:classifiers":[
        {
            "category":"Professional",
            "subcategory":"Art Services",
            "type":"Services"
        }
    ],
    "sg:phone":"+61 7 5478 2307",
    "sg:postcode":"4557",
    "sg:province":"QLD",
    "sg:tags":[
        "artist"
    ],
    "wof:name":"Pearson John N",
    "wof:placetype":"venue"
},
  "geometry": {"coordinates":[153.117797852,-26.6837902069],"type":"Point"}
}