{
  "type": "Feature",
  "properties": {
    "iso:country":"AU",
    "sg:address":"Shp5/ 41 Denham St",
    "sg:city":"Townsville City",
    "sg:classifiers":[
        {
            "category":"Cafe",
            "type":"Food & Drink"
        }
    ],
    "sg:phone":"+61 7 4772 5200",
    "sg:postcode":"4810",
    "sg:province":"QLD",
    "wof:name":"Twisted Melon",
    "wof:placetype":"venue"
},
  "geometry": {"coordinates":[146.817139,-19.256939],"type":"Point"}
}