{
  "type": "Feature",
  "properties": {
    "addr:full":"1 Binghi Bridgecarind Rd Carinda NSW 2831",
    "addr:housenumber":"1",
    "addr:postcode":"2831",
    "addr:street":"Binghi Bridgecarind Rd",
    "iso:country":"AU",
    "sg:address":"1 Binghi Bridgecarind Rd",
    "sg:city":"Carinda",
    "sg:classifiers":[
        {
            "category":"Manufacturing",
            "subcategory":"Textiles",
            "type":"Manufacturing & Wholesale Goods"
        }
    ],
    "sg:phone":"+61 2 6790 3000",
    "sg:postcode":"2831",
    "sg:province":"NSW",
    "sg:tags":[
        "cotton"
    ],
    "wof:name":"Namoi Cotton Co-Operative Ltd",
    "wof:placetype":"venue"
},
  "geometry": {"coordinates":[147.69046020499999,-30.4611091614],"type":"Point"}
}