{
  "type": "Feature",
  "properties": {
    "iso:country":"AU",
    "sg:address":"48 Hillside Pl",
    "sg:city":"Bullsbrook",
    "sg:classifiers":[
        {
            "category":"Utilities",
            "subcategory":"Water",
            "type":"Services"
        }
    ],
    "sg:phone":"+61 8 9571 0037",
    "sg:postcode":"6084",
    "sg:province":"WA",
    "sg:tags":[
        "cartage"
    ],
    "wof:name":"Bullsbrook & Chittering Water Tankers",
    "wof:placetype":"venue"
},
  "geometry": {"coordinates":[116.068450928,-31.6562538147],"type":"Point"}
}