{
  "type": "Feature",
  "properties": {
    "addr:full":"12 Horizon Drv Beenleigh QLD 4207",
    "addr:housenumber":"12",
    "addr:postcode":"4207",
    "addr:street":"Horizon Drv",
    "iso:country":"AU",
    "sg:address":"12 Horizon Drv",
    "sg:city":"Beenleigh",
    "sg:classifiers":[
        {
            "category":"Manufacturing",
            "subcategory":"Metals",
            "type":"Manufacturing & Wholesale Goods"
        }
    ],
    "sg:phone":"+61 7 3804 6488",
    "sg:postcode":"4207",
    "sg:province":"QLD",
    "sg:tags":[
        "steel",
        "fabricator",
        "mfrs"
    ],
    "wof:name":"Efab Structual Pty Ltd",
    "wof:placetype":"venue"
},
  "geometry": {"coordinates":[153.183151245,-27.7141208649],"type":"Point"}
}