{
  "type": "Feature",
  "properties": {
    "addr:full":"Shp 16 Old Prospect Rd Pemulwuy NSW 2145",
    "addr:housenumber":"16",
    "addr:postcode":"2145",
    "addr:street":"Old Prospect Rd",
    "iso:country":"AU",
    "sg:address":"Shp 16 Old Prospect Rd",
    "sg:city":"Pemulwuy",
    "sg:classifiers":[
        {
            "category":"Shopping",
            "subcategory":"Mobile Phones",
            "type":"Retail Goods"
        }
    ],
    "sg:phone":"+61 2 9631 0255",
    "sg:postcode":"2145",
    "sg:province":"NSW",
    "sg:tags":[
        "telephone",
        "accessory"
    ],
    "wof:name":"Phone Avenue",
    "wof:placetype":"venue"
},
  "geometry": {"coordinates":[150.966796875,-33.8174629211],"type":"Point"}
}