{
  "type": "Feature",
  "properties": {
    "addr:full":"3 Windhaven Crt Warragul VIC 3820",
    "addr:housenumber":"3",
    "addr:postcode":"3820",
    "addr:street":"Windhaven Crt",
    "iso:country":"AU",
    "sg:address":"3 Windhaven Crt",
    "sg:city":"Warragul",
    "sg:classifiers":[
        {
            "category":"Home & Garden",
            "subcategory":"Household Appliances",
            "type":"Retail Goods"
        }
    ],
    "sg:phone":"+61 3 5622 3004",
    "sg:postcode":"3820",
    "sg:province":"VIC",
    "sg:tags":[
        "heating",
        "system"
    ],
    "wof:name":"Warragul Heating & Cooling",
    "wof:placetype":"venue"
},
  "geometry": {"coordinates":[145.93562299999999,-38.141499],"type":"Point"}
}