{
  "type": "Feature",
  "properties": {
    "iso:country":"AU",
    "sg:address":"24 charleskurz Drv",
    "sg:city":"Worongary",
    "sg:classifiers":[
        {
            "category":"Retail",
            "subcategory":"Event Space",
            "type":"Services"
        }
    ],
    "sg:phone":"+61 7 5530 2366",
    "sg:postcode":"4213",
    "sg:province":"QLD",
    "sg:tags":[
        "venue",
        "reception",
        "wedding"
    ],
    "wof:name":"Angela Sully Enterprises",
    "wof:placetype":"venue"
},
  "geometry": {"coordinates":[153.33042907699999,-28.0556106567],"type":"Point"}
}