{
  "type": "Feature",
  "properties": {
    "addr:full":"63 Golf Links Rd Barwon Heads VIC 3227",
    "addr:housenumber":"63",
    "addr:postcode":"3227",
    "addr:street":"Golf Links Rd",
    "iso:country":"AU",
    "sg:address":"63 Golf Links Rd",
    "sg:city":"Barwon Heads",
    "sg:classifiers":[
        {
            "category":"Sports & Exercise",
            "subcategory":"Gym",
            "type":"Entertainment"
        }
    ],
    "sg:phone":"+61 3 5254 1015",
    "sg:postcode":"3227",
    "sg:province":"VIC",
    "sg:tags":[
        "health",
        "fitness"
    ],
    "wof:name":"C-Change Training Studio",
    "wof:placetype":"venue"
},
  "geometry": {"coordinates":[144.48819,-38.275669],"type":"Point"}
}