{
  "type": "Feature",
  "properties": {
    "iso:country":"AU",
    "sg:address":"Level 2/ 182 Bay Tce",
    "sg:city":"Wynnum",
    "sg:classifiers":[
        {
            "category":"Personal",
            "type":"Services"
        }
    ],
    "sg:phone":"+61 7 3393 4194",
    "sg:postcode":"4178",
    "sg:province":"QLD",
    "sg:tags":[
        "reducing",
        "treatment",
        "weight"
    ],
    "wof:name":"Curves Wynnum/Manly",
    "wof:placetype":"venue"
},
  "geometry": {"coordinates":[153.17579650900001,-27.4457054138],"type":"Point"}
}