{
  "type": "Feature",
  "properties": {
    "addr:full":"Fcty1/18- 20 Rhur St Dandenong South VIC 3164",
    "addr:housenumber":"20",
    "addr:postcode":"3164",
    "addr:street":"Rhur St",
    "iso:country":"AU",
    "sg:address":"Fcty1/18- 20 Rhur St",
    "sg:city":"Dandenong South",
    "sg:classifiers":[
        {
            "category":"Farming",
            "subcategory":"Farm & Veterinary Services",
            "type":"Manufacturing & Wholesale Goods"
        }
    ],
    "sg:phone":"+61 3 9793 3006",
    "sg:postcode":"3164",
    "sg:province":"VIC",
    "sg:tags":[
        "seedsman"
    ],
    "wof:name":"Westranell Horticultral Solutions",
    "wof:placetype":"venue"
},
  "geometry": {"coordinates":[145.208084106,-38.0088310242],"type":"Point"}
}