{
  "type": "Feature",
  "properties": {
    "iso:country":"AU",
    "sg:address":"8 Lushington Drv",
    "sg:city":"Padbury",
    "sg:classifiers":[
        {
            "category":"Professional",
            "subcategory":"Accounting & Tax Preparation",
            "type":"Services"
        }
    ],
    "sg:phone":"+61 8 9401 6274",
    "sg:postcode":"6025",
    "sg:province":"WA",
    "sg:tags":[
        "accountant",
        "auditor"
    ],
    "wof:name":"Fisher M L & Associates",
    "wof:placetype":"venue"
},
  "geometry": {"coordinates":[115.759658813,-31.811674118],"type":"Point"}
}