{
  "type": "Feature",
  "properties": {
    "addr:full":"Shop 6 164 Baroona Rd Rosalie QLD 4064",
    "addr:housenumber":"shop 6",
    "addr:postcode":"164;4064",
    "addr:street":"Baroona Rd",
    "iso:country":"AU",
    "sg:address":"Shop 6 164 Baroona Rd",
    "sg:city":"Rosalie",
    "sg:classifiers":[
        {
            "category":"Restaurant",
            "type":"Food & Drink"
        }
    ],
    "sg:phone":"+61 7 3369 0877",
    "sg:postcode":"4064",
    "sg:province":"QLD",
    "wof:name":"Bali Grill",
    "wof:placetype":"venue"
},
  "geometry": {"coordinates":[152.99676513700001,-27.4662799835],"type":"Point"}
}