{
  "type": "Feature",
  "properties": {
    "addr:full":"25 Moore St Coburg VIC 3058",
    "addr:housenumber":"25",
    "addr:postcode":"3058",
    "addr:street":"Moore St",
    "iso:country":"AU",
    "sg:address":"25 Moore St",
    "sg:city":"Coburg",
    "sg:classifiers":[
        {
            "category":"Banks & Credit Unions",
            "subcategory":"Bureau De Change",
            "type":"Services"
        }
    ],
    "sg:phone":"+61 408 006 690",
    "sg:postcode":"3058",
    "sg:province":"VIC",
    "sg:tags":[
        "archaeology"
    ],
    "wof:name":"Landskape Heritage Management",
    "wof:placetype":"venue"
},
  "geometry": {"coordinates":[144.96665954599999,-37.7537727356],"type":"Point"}
}