{
  "type": "Feature",
  "properties": {
    "addr:full":"Suite 6 / Ground Floor, 12 Cato St Hawthorn East VIC 3123",
    "addr:housenumber":"12",
    "addr:postcode":"3123",
    "addr:street":"/;Cato St",
    "iso:country":"AU",
    "sg:address":"Suite 6 / Ground Floor, 12 Cato St",
    "sg:city":"Hawthorn East",
    "sg:classifiers":[
        {
            "category":"Shopping",
            "subcategory":"Computers & Home Electronics",
            "type":"Retail Goods"
        }
    ],
    "sg:phone":"+61 3 9821 0055",
    "sg:postcode":"3123",
    "sg:province":"VIC",
    "sg:tags":[
        "wholesaler",
        "equipment",
        "electronic",
        "mfrs"
    ],
    "wof:name":"Vcomm Pty Ltd",
    "wof:placetype":"venue"
},
  "geometry": {"coordinates":[145.04281616200001,-37.84324646],"type":"Point"}
}