{
  "type": "Feature",
  "properties": {
    "iso:country":"AU",
    "sg:address":"Hedges Rd",
    "sg:city":"Narembeen East",
    "sg:classifiers":[
        {
            "category":"Farming",
            "subcategory":"Farm",
            "type":"Manufacturing & Wholesale Goods"
        }
    ],
    "sg:phone":"+61 8 9061 8014",
    "sg:postcode":"6369",
    "sg:province":"WA",
    "sg:tags":[
        "farmer"
    ],
    "wof:name":"Hunter D M & H S",
    "wof:placetype":"venue"
},
  "geometry": {"coordinates":[118.39566000000001,-32.090343],"type":"Point"}
}