{
  "type": "Feature",
  "properties": {
    "addr:full":"Factory 2, 67 Lara Way Campbellfield VIC 3061",
    "addr:housenumber":"67",
    "addr:postcode":"3061",
    "addr:street":"Lara Way",
    "iso:country":"AU",
    "sg:address":"Factory 2, 67",
    "sg:city":"Lara Way Campbellfield",
    "sg:classifiers":[
        {
            "category":"Communications",
            "subcategory":"Film & Video Production",
            "type":"Services"
        }
    ],
    "sg:phone":"+61 3 9357 6866",
    "sg:postcode":"3061",
    "sg:province":"VIC",
    "sg:tags":[
        "fan",
        "blower"
    ],
    "wof:name":"Skelley Electrical",
    "wof:placetype":"venue"
},
  "geometry": {"coordinates":[144.96827697800001,-37.6638298035],"type":"Point"}
}