{
  "type": "Feature",
  "properties": {
    "iso:country":"AU",
    "sg:address":"Unit 6/ 35 King Rd",
    "sg:city":"Hornsby",
    "sg:classifiers":[
        {
            "category":"Banks & Credit Unions",
            "subcategory":"Investment Brokerage",
            "type":"Services"
        }
    ],
    "sg:phone":"+61 2 9477 4111",
    "sg:postcode":"2077",
    "sg:province":"NSW",
    "sg:tags":[
        "directory",
        "notice",
        "board"
    ],
    "wof:name":"Assignment Signs & Engraving",
    "wof:placetype":"venue"
},
  "geometry": {"coordinates":[151.11230468799999,-33.698638916],"type":"Point"}
}