{
  "type": "Feature",
  "properties": {
    "iso:country":"AU",
    "sg:address":"28 Park Ave",
    "sg:city":"Woodville North",
    "sg:classifiers":[
        {
            "category":"Manufacturing",
            "subcategory":"Glass & Minerals",
            "type":"Manufacturing & Wholesale Goods"
        }
    ],
    "sg:phone":"+61 8 8348 9200",
    "sg:postcode":"5012",
    "sg:province":"SA",
    "sg:tags":[
        "mfrg",
        "processing"
    ],
    "wof:name":"DMS Glass",
    "wof:placetype":"venue"
},
  "geometry": {"coordinates":[138.53970336899999,-34.8599433899],"type":"Point"}
}