{
  "type": "Feature",
  "properties": {
    "addr:full":"Middle Brighton 94 Church Brighton VIC 3186",
    "addr:housenumber":"94",
    "addr:postcode":"3186",
    "addr:street":"Church",
    "iso:country":"AU",
    "sg:address":"Middle Brighton 94",
    "sg:city":"Church Brighton",
    "sg:classifiers":[
        {
            "category":"Banks & Credit Unions",
            "subcategory":"Bank",
            "type":"Services"
        }
    ],
    "sg:phone":"+61 13 20 32",
    "sg:postcode":"3186",
    "sg:province":"VIC",
    "wof:name":"Westpac",
    "wof:placetype":"venue"
},
  "geometry": {"coordinates":[144.99707031200001,-37.8837509155],"type":"Point"}
}