{
  "type": "Feature",
  "properties": {
    "iso:country":"AU",
    "sg:address":"PO Box 284",
    "sg:city":"Balaclava",
    "sg:classifiers":[
        {
            "category":"Social Services",
            "type":"Services"
        }
    ],
    "sg:phone":"+61 402 069 366",
    "sg:postcode":"3183",
    "sg:province":"VIC",
    "sg:tags":[
        "domestic",
        "help"
    ],
    "wof:name":"Domestica Household Management",
    "wof:placetype":"venue"
},
  "geometry": {"coordinates":[144.996017456,-37.8690795898],"type":"Point"}
}