{
  "type": "Feature",
  "properties": {
    "addr:full":"227 Princes Hwy Corrimal NSW 2518",
    "addr:housenumber":"227",
    "addr:postcode":"2518",
    "addr:street":"Princes Hwy",
    "iso:country":"AU",
    "sg:address":"227 Princes Hwy",
    "sg:city":"Corrimal",
    "sg:classifiers":[
        {
            "category":"Ice Cream",
            "type":"Food & Drink"
        }
    ],
    "sg:phone":"+61 2 4285 3323",
    "sg:postcode":"2518",
    "sg:province":"NSW",
    "sg:tags":[
        "specialised",
        "fitting",
        "lady",
        "wear"
    ],
    "wof:name":"Curvaceous Babes",
    "wof:placetype":"venue"
},
  "geometry": {"coordinates":[150.895645,-34.372875],"type":"Point"}
}