{
  "type": "Feature",
  "properties": {
    "iso:country":"AU",
    "sg:address":"11 Smith St",
    "sg:city":"Chatswood",
    "sg:classifiers":[
        {
            "category":"Manufacturing",
            "subcategory":"Tools & Machinery",
            "type":"Manufacturing & Wholesale Goods"
        }
    ],
    "sg:phone":"+61 2 9417 6197",
    "sg:postcode":"2067",
    "sg:province":"NSW",
    "sg:tags":[
        "supplier",
        "diamond"
    ],
    "wof:name":"Quality Diamond Plated Products Pty Ltd",
    "wof:placetype":"venue"
},
  "geometry": {"coordinates":[151.1978302,-33.7866706848],"type":"Point"}
}