{
  "type": "Feature",
  "properties": {
    "addr:full":"Unit 6, 19 Ashton St Labrador QLD 4215",
    "addr:housenumber":"19",
    "addr:postcode":"4215",
    "addr:street":"Ashton St",
    "iso:country":"AU",
    "sg:address":"Unit 6, 19 Ashton St",
    "sg:city":"Labrador",
    "sg:classifiers":[
        {
            "category":"Retail",
            "subcategory":"Auto Repair",
            "type":"Services"
        }
    ],
    "sg:phone":"+61 7 5537 7377",
    "sg:postcode":"4215",
    "sg:province":"QLD",
    "sg:tags":[
        "transmission",
        "automotive",
        "car"
    ],
    "wof:name":"Trade Exchange Transmissions",
    "wof:placetype":"venue"
},
  "geometry": {"coordinates":[153.39828491200001,-27.9366073608],"type":"Point"}
}