{
  "type": "Feature",
  "properties": {
    "addr:full":"Level 1, 509 St Kilda Rd Melbourne VIC 3004",
    "addr:housenumber":"509",
    "addr:postcode":"3004",
    "addr:street":"St Kilda Rd",
    "iso:country":"AU",
    "sg:address":"Level 1, 509 St Kilda Rd",
    "sg:city":"Melbourne",
    "sg:classifiers":[
        {
            "category":"Banks & Credit Unions",
            "subcategory":"Financial Services",
            "type":"Services"
        }
    ],
    "sg:phone":"+61 3 9863 1200",
    "sg:postcode":"3004",
    "sg:province":"VIC",
    "sg:tags":[
        "planning"
    ],
    "sg:website":"http://www.fpa.asn.au",
    "wof:name":"Meritum Financial Group Pty Ltd",
    "wof:placetype":"venue"
},
  "geometry": {"coordinates":[144.97865295400001,-37.8435707092],"type":"Point"}
}