{
  "type": "Feature",
  "properties": {
    "addr:full":"576 Bengeo Rd Lemana Junction TAS 7304",
    "addr:housenumber":"576",
    "addr:postcode":"7304",
    "addr:street":"Bengeo Rd",
    "iso:country":"AU",
    "sg:address":"576 Bengeo Rd",
    "sg:city":"Lemana Junction",
    "sg:classifiers":[
        {
            "category":"Farming",
            "subcategory":"Farm",
            "type":"Manufacturing & Wholesale Goods"
        }
    ],
    "sg:phone":"+61 3 6362 2403",
    "sg:postcode":"7304",
    "sg:province":"TAS",
    "sg:tags":[
        "farmer"
    ],
    "wof:name":"Leonard K W C",
    "wof:placetype":"venue"
},
  "geometry": {"coordinates":[146.589676,-41.524525],"type":"Point"}
}