{
  "type": "Feature",
  "properties": {
    "iso:country":"AU",
    "sg:address":"Unit 23 8 Gray St",
    "sg:city":"Kilkenny",
    "sg:classifiers":[
        {
            "category":"Manufacturing",
            "subcategory":"Apparel",
            "type":"Manufacturing & Wholesale Goods"
        }
    ],
    "sg:phone":"+61 8 8268 1846",
    "sg:postcode":"5009",
    "sg:province":"SA",
    "sg:tags":[
        "makers-up",
        "clothing"
    ],
    "wof:name":"Australian Fine Clothing Pty Ltd",
    "wof:placetype":"venue"
},
  "geometry": {"coordinates":[138.55232238799999,-34.8746185303],"type":"Point"}
}