{
  "type": "Feature",
  "properties": {
    "addr:full":"171 Werin St Tewantin QLD 4565",
    "addr:housenumber":"171",
    "addr:postcode":"4565",
    "addr:street":"Werin St",
    "iso:country":"AU",
    "sg:address":"171 Werin St",
    "sg:city":"Tewantin",
    "sg:classifiers":[
        {
            "category":"Shopping",
            "type":"Retail Goods"
        }
    ],
    "sg:phone":"+61 437 471 383",
    "sg:postcode":"4565",
    "sg:province":"QLD",
    "sg:tags":[
        "equipment",
        "safety",
        "accessory"
    ],
    "wof:name":"Pedro's Tag & Test",
    "wof:placetype":"venue"
},
  "geometry": {"coordinates":[153.03465270999999,-26.3796253204],"type":"Point"}
}