{
  "type": "Feature",
  "properties": {
    "iso:country":"AU",
    "sg:address":"Camp St",
    "sg:city":"Grenfell",
    "sg:classifiers":[
        {
            "category":"Government",
            "subcategory":"Fire Station",
            "type":"Public Place"
        }
    ],
    "sg:phone":"+61 2 6343 1054",
    "sg:postcode":"2810",
    "sg:province":"NSW",
    "sg:tags":[
        "brigade"
    ],
    "wof:name":"Fire Brigades-NSW",
    "wof:placetype":"venue"
},
  "geometry": {"coordinates":[148.15370178200001,-33.8942642212],"type":"Point"}
}