{
  "type": "Feature",
  "properties": {
    "addr:full":"179 A Sunshine Rd West Footscray VIC 3012",
    "addr:housenumber":"179 a",
    "addr:postcode":"3012",
    "addr:street":"Sunshine Rd",
    "iso:country":"AU",
    "sg:address":"179 A Sunshine Rd",
    "sg:city":"West Footscray",
    "sg:classifiers":[
        {
            "category":"Fast Food",
            "type":"Food & Drink"
        }
    ],
    "sg:phone":"+61 3 9314 1881",
    "sg:postcode":"3012",
    "sg:province":"VIC",
    "sg:tags":[
        "away",
        "take"
    ],
    "wof:name":"Pony Express Pizza & Pasta",
    "wof:placetype":"venue"
},
  "geometry": {"coordinates":[144.88096618599999,-37.8019485474],"type":"Point"}
}