{
  "type": "Feature",
  "properties": {
    "addr:full":"4 Hannah Crt Highfields QLD 4352",
    "addr:housenumber":"4",
    "addr:postcode":"4352",
    "addr:street":"Hannah Crt",
    "iso:country":"AU",
    "sg:address":"4 Hannah Crt",
    "sg:city":"Highfields",
    "sg:classifiers":[
        {
            "category":"Building & Trades",
            "subcategory":"Construction",
            "type":"Services"
        }
    ],
    "sg:phone":"+61 419 712 415",
    "sg:postcode":"4352",
    "sg:province":"QLD",
    "sg:tags":[
        "earth",
        "excavating",
        "moving",
        "contractor"
    ],
    "wof:name":"Kahler's Bobcat Hire",
    "wof:placetype":"venue"
},
  "geometry": {"coordinates":[151.945526,-27.473219],"type":"Point"}
}