{
  "type": "Feature",
  "properties": {
    "addr:full":"382 Bridge Rd Richmond VIC 3121",
    "addr:housenumber":"382",
    "addr:postcode":"3121",
    "addr:street":"Bridge Rd",
    "iso:country":"AU",
    "sg:address":"382 Bridge Rd",
    "sg:city":"Richmond",
    "sg:classifiers":[
        {
            "category":"Fast Food",
            "type":"Food & Drink"
        }
    ],
    "sg:phone":"+61 3 9428 7318",
    "sg:postcode":"3121",
    "sg:province":"VIC",
    "sg:tags":[
        "away",
        "take"
    ],
    "wof:name":"Fillings Deli & Take-Away Foods",
    "wof:placetype":"venue"
},
  "geometry": {"coordinates":[145.00422668499999,-37.8191871643],"type":"Point"}
}