{
  "type": "Feature",
  "properties": {
    "addr:full":"Unit 3 / 42 Currumbin Creek Rd Currumbin QLD 4223",
    "addr:housenumber":"42",
    "addr:postcode":"4223",
    "addr:street":"Currumbin Creek Rd",
    "iso:country":"AU",
    "sg:address":"Unit 3 / 42 Currumbin Creek Rd",
    "sg:city":"Currumbin",
    "sg:classifiers":[
        {
            "category":"Shopping",
            "subcategory":"Clothing, Apparel, & Fashions",
            "type":"Retail Goods"
        }
    ],
    "sg:phone":"+61 7 5534 4266",
    "sg:postcode":"4223",
    "sg:province":"QLD",
    "sg:tags":[
        "sportswear"
    ],
    "wof:name":"The Grind",
    "wof:placetype":"venue"
},
  "geometry": {"coordinates":[153.47242736800001,-28.1432781219],"type":"Point"}
}