{
  "type": "Feature",
  "properties": {
    "addr:full":"1045 Frankston Flinders Rd Somerville VIC 3912",
    "addr:housenumber":"1045",
    "addr:postcode":"3912",
    "addr:street":"Frankston Flinders Rd",
    "iso:country":"AU",
    "sg:address":"1045 Frankston Flinders Rd",
    "sg:city":"Somerville",
    "sg:classifiers":[
        {
            "category":"Retail",
            "subcategory":"Auto Repair",
            "type":"Services"
        }
    ],
    "sg:phone":"+61 3 5977 5218",
    "sg:postcode":"3912",
    "sg:province":"VIC",
    "sg:tags":[
        "repairer",
        "motor",
        "engineer"
    ],
    "wof:name":"S.A.B. Motors Somerville Pty Ltd",
    "wof:placetype":"venue"
},
  "geometry": {"coordinates":[145.17506408700001,-38.2227783203],"type":"Point"}
}