{
  "type": "Feature",
  "properties": {
    "iso:country":"AU",
    "sg:address":"5 Cruise Crt",
    "sg:city":"Bundaberg",
    "sg:classifiers":[
        {
            "category":"Professional",
            "subcategory":"Computer Services",
            "type":"Services"
        }
    ],
    "sg:phone":"+61 429 319 701",
    "sg:postcode":"4670",
    "sg:province":"QLD",
    "sg:tags":[
        "consultant",
        "system"
    ],
    "wof:name":"Ontrack International Pty Ltd",
    "wof:placetype":"venue"
},
  "geometry": {"coordinates":[152.30592346200001,-24.8940238953],"type":"Point"}
}