{
  "type": "Feature",
  "properties": {
    "iso:country":"AU",
    "sg:address":"21/ 937 Marion Rd",
    "sg:city":"Mitchell Park",
    "sg:classifiers":[
        {
            "category":"Home & Garden",
            "subcategory":"Hardware",
            "type":"Retail Goods"
        }
    ],
    "sg:phone":"+61 8 8358 4100",
    "sg:postcode":"5043",
    "sg:province":"SA",
    "sg:tags":[
        "compressor",
        "air"
    ],
    "wof:name":"Calair Pipe Systems (SSA)",
    "wof:placetype":"venue"
},
  "geometry": {"coordinates":[138.558731,-35.013737],"type":"Point"}
}