{
  "type": "Feature",
  "properties": {
    "addr:full":"184 Huntingdale Rd Oakleigh East VIC 3166",
    "addr:housenumber":"184",
    "addr:postcode":"3166",
    "addr:street":"Huntingdale Rd",
    "iso:country":"AU",
    "sg:address":"184 Huntingdale Rd",
    "sg:city":"Oakleigh East",
    "sg:classifiers":[
        {
            "category":"Health Services",
            "subcategory":"Doctor",
            "type":"Services"
        }
    ],
    "sg:phone":"+61 3 9544 7167",
    "sg:postcode":"3166",
    "sg:province":"VIC",
    "sg:tags":[
        "medical",
        "practitioner"
    ],
    "wof:name":"Dr Danny Beebe",
    "wof:placetype":"venue"
},
  "geometry": {"coordinates":[145.105834961,-37.8993988037],"type":"Point"}
}