{
  "type": "Feature",
  "properties": {
    "addr:full":"2 Nesbitt St Wagga Wagga NSW 2650",
    "addr:housenumber":"2",
    "addr:postcode":"2650",
    "addr:street":"Nesbitt St",
    "iso:country":"AU",
    "sg:address":"2 Nesbitt St",
    "sg:city":"Wagga Wagga",
    "sg:classifiers":[
        {
            "category":"Retail",
            "subcategory":"Auto Rental",
            "type":"Services"
        }
    ],
    "sg:phone":"+61 13 61 39",
    "sg:postcode":"2650",
    "sg:province":"NSW",
    "sg:tags":[
        "bus",
        "truck"
    ],
    "wof:name":"Thrifty",
    "wof:placetype":"venue"
},
  "geometry": {"coordinates":[147.384002686,-35.1211547852],"type":"Point"}
}