{
  "type": "Feature",
  "properties": {
    "addr:full":"Shop 80 Westfield Shpng Cntr Doncaster VIC 3108",
    "addr:housenumber":"shop 80",
    "addr:postcode":"3108",
    "addr:street":"Westfield Shpng",
    "iso:country":"AU",
    "sg:address":"Shop 80 Westfield Shpng Cntr",
    "sg:city":"Doncaster",
    "sg:classifiers":[
        {
            "category":"Food & Beverages",
            "subcategory":"Specialty",
            "type":"Retail Goods"
        }
    ],
    "sg:phone":"+61 3 9848 7411",
    "sg:postcode":"3108",
    "sg:province":"VIC",
    "sg:tags":[
        "product",
        "health"
    ],
    "wof:name":"GNC Live Well",
    "wof:placetype":"venue"
},
  "geometry": {"coordinates":[145.12586975100001,-37.7822265625],"type":"Point"}
}