{
  "type": "Feature",
  "properties": {
    "iso:country":"AU",
    "sg:address":"143 Macquarie St",
    "sg:city":"Sydney",
    "sg:classifiers":[
        {
            "category":"Insurance",
            "subcategory":"Hazard Insurance",
            "type":"Services"
        }
    ],
    "sg:phone":"+61 13 31 30",
    "sg:postcode":"2000",
    "sg:province":"NSW",
    "sg:tags":[
        "fire",
        "accident",
        "marine"
    ],
    "wof:name":"Over 50's Insurance Agency",
    "wof:placetype":"venue"
},
  "geometry": {"coordinates":[151.21257019000001,-33.8646697998],"type":"Point"}
}