{
  "type": "Feature",
  "properties": {
    "iso:country":"AU",
    "sg:address":"Suite 8, 10 McCourt St",
    "sg:city":"West Leederville",
    "sg:classifiers":[
        {
            "category":"Health Services",
            "subcategory":"Doctor",
            "type":"Services"
        }
    ],
    "sg:phone":"+61 8 9388 1334",
    "sg:postcode":"6007",
    "sg:province":"WA",
    "sg:tags":[
        "medical",
        "practitioner"
    ],
    "wof:name":"Lamont Amanda Dr",
    "wof:placetype":"venue"
},
  "geometry": {"coordinates":[115.827850342,-31.9428043365],"type":"Point"}
}