{
  "type": "Feature",
  "properties": {
    "addr:full":"2 Cantwell Rd Narre Warren North VIC 3804",
    "addr:housenumber":"2",
    "addr:postcode":"3804",
    "addr:street":"Cantwell Rd",
    "iso:country":"AU",
    "sg:address":"2 Cantwell Rd",
    "sg:city":"Narre Warren North",
    "sg:classifiers":[
        {
            "category":"Manufacturing",
            "subcategory":"Tools & Machinery",
            "type":"Manufacturing & Wholesale Goods"
        }
    ],
    "sg:phone":"+61 3 9796 9505",
    "sg:postcode":"3804",
    "sg:province":"VIC",
    "sg:tags":[
        "earth",
        "excavating",
        "moving",
        "equipment"
    ],
    "wof:name":"John Tilley",
    "wof:placetype":"venue"
},
  "geometry": {"coordinates":[145.320480347,-37.9895820618],"type":"Point"}
}