{
  "type": "Feature",
  "properties": {
    "addr:full":"6 Nickson Crt Ringwood North VIC 3134",
    "addr:housenumber":"6",
    "addr:postcode":"3134",
    "addr:street":"Nickson Crt",
    "iso:country":"AU",
    "sg:address":"6 Nickson Crt",
    "sg:city":"Ringwood North",
    "sg:classifiers":[
        {
            "category":"Professional",
            "subcategory":"Accounting & Tax Preparation",
            "type":"Services"
        }
    ],
    "sg:phone":"+61 3 9879 9581",
    "sg:postcode":"3134",
    "sg:province":"VIC",
    "sg:tags":[
        "accountant",
        "auditor"
    ],
    "wof:name":"Ball, Stuart & Associates",
    "wof:placetype":"venue"
},
  "geometry": {"coordinates":[145.24095153799999,-37.7807006836],"type":"Point"}
}