{
  "type": "Feature",
  "properties": {
    "addr:full":"19 Callistemon Drv Hoppers Crossing VIC 3029",
    "addr:housenumber":"19",
    "addr:postcode":"3029",
    "addr:street":"Callistemon Drv",
    "iso:country":"AU",
    "sg:address":"19 Callistemon Drv",
    "sg:city":"Hoppers Crossing",
    "sg:classifiers":[
        {
            "category":"Shopping",
            "subcategory":"Computers & Home Electronics",
            "type":"Retail Goods"
        }
    ],
    "sg:phone":"+61 3 9749 5366",
    "sg:postcode":"3029",
    "sg:province":"VIC",
    "sg:tags":[
        "hardware",
        "equipment"
    ],
    "wof:name":"Dilithium Computing Pty Ltd",
    "wof:placetype":"venue"
},
  "geometry": {"coordinates":[144.67733799999999,-37.8592],"type":"Point"}
}