{
  "type": "Feature",
  "properties": {
    "addr:full":"206 Liverpool Rd Ashfield NSW 2131",
    "addr:housenumber":"206",
    "addr:postcode":"2131",
    "addr:street":"Liverpool Rd",
    "iso:country":"AU",
    "sg:address":"206 Liverpool Rd",
    "sg:city":"Ashfield",
    "sg:classifiers":[
        {
            "category":"Health Services",
            "subcategory":"Doctor",
            "type":"Services"
        }
    ],
    "sg:phone":"+61 2 9797 2222",
    "sg:postcode":"2131",
    "sg:province":"NSW",
    "sg:tags":[
        "medical",
        "practitioner"
    ],
    "wof:name":"Bennelong X-Ray",
    "wof:placetype":"venue"
},
  "geometry": {"coordinates":[151.125762939,-33.8895950317],"type":"Point"}
}