{
  "type": "Feature",
  "properties": {
    "addr:full":"37 Koroit St Warrnambool VIC 3280",
    "addr:housenumber":"37",
    "addr:postcode":"3280",
    "addr:street":"Koroit St",
    "iso:country":"AU",
    "sg:address":"37 Koroit St",
    "sg:city":"Warrnambool",
    "sg:classifiers":[
        {
            "category":"Health Services",
            "subcategory":"Health Practitioner",
            "type":"Services"
        }
    ],
    "sg:phone":"+61 3 5561 6150",
    "sg:postcode":"3280",
    "sg:province":"VIC",
    "sg:tags":[
        "osteopath"
    ],
    "wof:name":"Southwest Osteopathy",
    "wof:placetype":"venue"
},
  "geometry": {"coordinates":[142.489624023,-38.3863945007],"type":"Point"}
}