{
  "type": "Feature",
  "properties": {
    "addr:full":"432 Hemmant-Tingalpa Rd Hemmant QLD 4174",
    "addr:housenumber":"432",
    "addr:postcode":"4174",
    "addr:street":"Hemmant-Tingalpa Rd",
    "iso:country":"AU",
    "sg:address":"432 Hemmant-Tingalpa Rd",
    "sg:city":"Hemmant",
    "sg:classifiers":[
        {
            "category":"Building & Trades",
            "subcategory":"Plumbing",
            "type":"Services"
        }
    ],
    "sg:phone":"+61 7 3390 8576",
    "sg:postcode":"4174",
    "sg:province":"QLD",
    "sg:tags":[
        "plumber",
        "gasfitters"
    ],
    "wof:name":"N R Grice Plumbing & Drainage",
    "wof:placetype":"venue"
},
  "geometry": {"coordinates":[153.16294860799999,-27.4504547119],"type":"Point"}
}