{
  "type": "Feature",
  "properties": {
    "addr:full":"124 Fitzmaurice St Wagga Wagga NSW 2650",
    "addr:housenumber":"124",
    "addr:postcode":"2650",
    "addr:street":"Fitzmaurice St",
    "iso:country":"AU",
    "sg:address":"124 Fitzmaurice St",
    "sg:city":"Wagga Wagga",
    "sg:classifiers":[
        {
            "category":"Professional",
            "subcategory":"Art Services",
            "type":"Services"
        }
    ],
    "sg:phone":"+61 2 6931 8944",
    "sg:postcode":"2650",
    "sg:province":"NSW",
    "sg:tags":[
        "interior",
        "decorator"
    ],
    "wof:name":"Tigger Hall",
    "wof:placetype":"venue"
},
  "geometry": {"coordinates":[147.368896484,-35.1043891907],"type":"Point"}
}