{
  "type": "Feature",
  "properties": {
    "iso:country":"AU",
    "sg:address":"31 Church St",
    "sg:city":"Glen Innes",
    "sg:classifiers":[
        {
            "category":"Personal",
            "subcategory":"Beauty Salon",
            "type":"Services"
        }
    ],
    "sg:phone":"+61 2 6732 4569",
    "sg:postcode":"2370",
    "sg:province":"NSW",
    "sg:tags":[
        "hairdresser"
    ],
    "wof:name":"Debs Hairstyles",
    "wof:placetype":"venue"
},
  "geometry": {"coordinates":[151.733352661,-29.7349205017],"type":"Point"}
}