{
  "type": "Feature",
  "properties": {
    "iso:country":"AU",
    "sg:address":"14 Aberfoyle Pl",
    "sg:city":"Grasmere",
    "sg:classifiers":[
        {
            "category":"Donuts",
            "subcategory":"None",
            "type":"Food & Drink"
        }
    ],
    "sg:phone":"+61 2 4655 1113",
    "sg:postcode":"2570",
    "sg:province":"NSW",
    "sg:tags":[
        "die",
        "engraver",
        "sinker"
    ],
    "wof:name":"Alsa Die Sinking Pty Ltd",
    "wof:placetype":"venue"
},
  "geometry": {"coordinates":[150.666305542,-34.0519943237],"type":"Point"}
}