{
  "type": "Feature",
  "properties": {
    "addr:full":"5 Jacaranda St East Ipswich QLD 4305",
    "addr:housenumber":"5",
    "addr:postcode":"4305",
    "addr:street":"Jacaranda St East",
    "iso:country":"AU",
    "sg:address":"5 Jacaranda St",
    "sg:city":"East Ipswich",
    "sg:classifiers":[
        {
            "category":"Social Services",
            "subcategory":"Job Training",
            "type":"Services"
        }
    ],
    "sg:phone":"+61 7 3282 7133",
    "sg:postcode":"4305",
    "sg:province":"QLD",
    "sg:tags":[
        "hire",
        "computer",
        "leasing"
    ],
    "wof:name":"Mr Rental",
    "wof:placetype":"venue"
},
  "geometry": {"coordinates":[152.77345275900001,-27.60638237],"type":"Point"}
}