{
  "type": "Feature",
  "properties": {
    "addr:full":"33 Locke St Raglan NSW 2795",
    "addr:housenumber":"33",
    "addr:postcode":"2795",
    "addr:street":"Locke St",
    "iso:country":"AU",
    "sg:address":"33 Locke St",
    "sg:city":"Raglan",
    "sg:classifiers":[
        {
            "category":"Home & Garden",
            "subcategory":"Building Materials",
            "type":"Retail Goods"
        }
    ],
    "sg:phone":"+61 2 6337 3656",
    "sg:postcode":"2795",
    "sg:province":"NSW",
    "sg:tags":[
        "tile",
        "roofing"
    ],
    "wof:name":"Lloyd Hyde Rooftiler",
    "wof:placetype":"venue"
},
  "geometry": {"coordinates":[149.64982605,-33.4262695312],"type":"Point"}
}