{
  "type": "Feature",
  "properties": {
    "addr:full":"Shp 9/ 191 Big Muster Drv Dinner Plain VIC 3898",
    "addr:housenumber":"/ 191",
    "addr:postcode":"3898",
    "addr:street":"Big Muster Drv",
    "iso:country":"AU",
    "sg:address":"Shp 9/ 191 Big Muster Drv",
    "sg:city":"Dinner Plain",
    "sg:classifiers":[
        {
            "category":"Restaurant",
            "type":"Food & Drink"
        }
    ],
    "sg:phone":"+61 3 5159 6799",
    "sg:postcode":"3898",
    "sg:province":"VIC",
    "wof:name":"Cilantro Restaurant & Bar",
    "wof:placetype":"venue"
},
  "geometry": {"coordinates":[147.238845825,-37.0218963623],"type":"Point"}
}