{
  "type": "Feature",
  "properties": {
    "iso:country":"AU",
    "sg:address":"1/ 68 Markham St",
    "sg:city":"Armidale",
    "sg:classifiers":[
        {
            "category":"Organizations",
            "subcategory":"Membership Organization",
            "type":"Services"
        }
    ],
    "sg:phone":"+61 427 037 774",
    "sg:postcode":"2350",
    "sg:province":"NSW",
    "sg:tags":[
        "support",
        "health",
        "organisation"
    ],
    "wof:name":"My Health Australia",
    "wof:placetype":"venue"
},
  "geometry": {"coordinates":[151.651947022,-30.5304374695],"type":"Point"}
}