{
  "type": "Feature",
  "properties": {
    "iso:country":"AU",
    "sg:address":"13 Attwood Crt",
    "sg:city":"Shepparton",
    "sg:classifiers":[
        {
            "category":"Health Services",
            "subcategory":"Health Practitioner",
            "type":"Services"
        }
    ],
    "sg:phone":"+61 3 5831 4975",
    "sg:postcode":"3630",
    "sg:province":"VIC",
    "sg:tags":[
        "naturopath"
    ],
    "wof:name":"Wayne Uhe",
    "wof:placetype":"venue"
},
  "geometry": {"coordinates":[145.41290283199999,-36.3596076965],"type":"Point"}
}