{
  "type": "Feature",
  "properties": {
    "iso:country":"AU",
    "sg:address":"PO Box 1064",
    "sg:city":"Mildura",
    "sg:classifiers":[
        {
            "category":"Government",
            "subcategory":"Customs House",
            "type":"Public Place"
        }
    ],
    "sg:phone":"+61 3 5023 6312",
    "sg:postcode":"3502",
    "sg:province":"VIC",
    "sg:tags":[
        "title",
        "management",
        "stratum"
    ],
    "wof:name":"Ivy Kirwin",
    "wof:placetype":"venue"
},
  "geometry": {"coordinates":[142.165557861,-34.184551239],"type":"Point"}
}