{
  "type": "Feature",
  "properties": {
    "addr:full":"53- 57 Sydney Rd Coburg VIC 3058",
    "addr:housenumber":"57",
    "addr:postcode":"3058",
    "addr:street":"Sydney Rd",
    "iso:country":"AU",
    "sg:address":"53- 57 Sydney Rd",
    "sg:city":"Coburg",
    "sg:classifiers":[
        {
            "category":"Utilities",
            "subcategory":"Electric",
            "type":"Services"
        }
    ],
    "sg:phone":"+61 3 9386 1907",
    "sg:postcode":"3058",
    "sg:province":"VIC",
    "sg:tags":[
        "electrical",
        "contractor"
    ],
    "wof:name":"Gore Pty Ltd",
    "wof:placetype":"venue"
},
  "geometry": {"coordinates":[144.964233398,-37.75390625],"type":"Point"}
}