{
  "type": "Feature",
  "properties": {
    "iso:country":"AU",
    "sg:address":"71 Cranford Ave",
    "sg:city":"Brentwood",
    "sg:classifiers":[
        {
            "category":"Autos & Motor Vehicles",
            "subcategory":"Fuel & Gas Station",
            "type":"Retail Goods"
        }
    ],
    "sg:phone":"+61 8 9364 3436",
    "sg:postcode":"6153",
    "sg:province":"WA",
    "wof:name":"Shell Co Of Aust Ltd The",
    "wof:placetype":"venue"
},
  "geometry": {"coordinates":[115.856712,-32.041134],"type":"Point"}
}