{
  "type": "Feature",
  "properties": {
    "iso:country":"AU",
    "sg:address":"Unit 3/ 18 Egmont Rd",
    "sg:city":"Henderson",
    "sg:classifiers":[
        {
            "category":"Utilities",
            "subcategory":"Electric",
            "type":"Services"
        }
    ],
    "sg:phone":"+61 8 9437 1553",
    "sg:postcode":"6166",
    "sg:province":"WA",
    "sg:tags":[
        "electrical",
        "contractor"
    ],
    "wof:name":"Cotek Electrical Services",
    "wof:placetype":"venue"
},
  "geometry": {"coordinates":[115.773407,-32.153152],"type":"Point"}
}