{
  "type": "Feature",
  "properties": {
    "addr:full":"99 Grattan St Carlton VIC 3053",
    "addr:housenumber":"99",
    "addr:postcode":"3053",
    "addr:street":"Grattan St",
    "iso:country":"AU",
    "sg:address":"99 Grattan St",
    "sg:city":"Carlton",
    "sg:classifiers":[
        {
            "category":"Health Services",
            "subcategory":"Optometrist",
            "type":"Services"
        }
    ],
    "sg:phone":"+61 3 9349 3919",
    "sg:postcode":"3053",
    "sg:province":"VIC",
    "wof:name":"Maritz Alison",
    "wof:placetype":"venue"
},
  "geometry": {"coordinates":[144.966430664,-37.8008117676],"type":"Point"}
}