{
  "type": "Feature",
  "properties": {
    "addr:full":"165 Pitt Town Rd Kenthurst NSW 2156",
    "addr:housenumber":"165",
    "addr:postcode":"2156",
    "addr:street":"Pitt Town Rd",
    "iso:country":"AU",
    "sg:address":"165 Pitt Town Rd",
    "sg:city":"Kenthurst",
    "sg:classifiers":[
        {
            "category":"Farming",
            "subcategory":"Nursery",
            "type":"Manufacturing & Wholesale Goods"
        }
    ],
    "sg:phone":"+61 2 9654 9255",
    "sg:postcode":"2156",
    "sg:province":"NSW",
    "wof:name":"Shaw Plants Pty Ltd",
    "wof:placetype":"venue"
},
  "geometry": {"coordinates":[150.97416687,-33.6559104919],"type":"Point"}
}