{
  "type": "Feature",
  "properties": {
    "addr:full":"Shop 20, 282 Collins St Melbourne VIC 3000",
    "addr:housenumber":"shop 20 282",
    "addr:postcode":"3000",
    "addr:street":"Collins St",
    "iso:country":"AU",
    "sg:address":"Shop 20, 282 Collins St",
    "sg:city":"Melbourne",
    "sg:classifiers":[
        {
            "category":"Personal",
            "subcategory":"Beauty Salon",
            "type":"Services"
        }
    ],
    "sg:phone":"+61 3 9650 8599",
    "sg:postcode":"3000",
    "sg:province":"VIC",
    "wof:name":"Skin Deep Beauty Therapy",
    "wof:placetype":"venue"
},
  "geometry": {"coordinates":[144.964767456,-37.8158721924],"type":"Point"}
}