{
  "type": "Feature",
  "properties": {
    "addr:full":"Factory 3 269 Deadhorse La Mansfield VIC 3722",
    "addr:housenumber":"269",
    "addr:postcode":"3722",
    "addr:street":"Deadhorse La",
    "iso:country":"AU",
    "sg:address":"Factory 3 269 Deadhorse La",
    "sg:city":"Mansfield",
    "sg:classifiers":[
        {
            "category":"Professional",
            "subcategory":"Engineering",
            "type":"Services"
        }
    ],
    "sg:phone":"+61 3 5775 3287",
    "sg:postcode":"3722",
    "sg:province":"VIC",
    "sg:tags":[
        "engineer"
    ],
    "wof:name":"D U B Fabrications",
    "wof:placetype":"venue"
},
  "geometry": {"coordinates":[146.09686279300001,-37.0440139771],"type":"Point"}
}