{
  "type": "Feature",
  "properties": {
    "addr:full":"2121 Point Nepean Rd Rye VIC 3941",
    "addr:housenumber":"2121",
    "addr:postcode":"3941",
    "addr:street":"Point Nepean Rd",
    "iso:country":"AU",
    "sg:address":"2121 Point Nepean Rd",
    "sg:city":"Rye",
    "sg:classifiers":[
        {
            "category":"Travel",
            "subcategory":"Travel Agent",
            "type":"Entertainment"
        }
    ],
    "sg:phone":"+61 1800 354 352",
    "sg:postcode":"3941",
    "sg:province":"VIC",
    "sg:tags":[
        "consultant"
    ],
    "wof:name":"O&#039;Shannessys Quality Tours",
    "wof:placetype":"venue"
},
  "geometry": {"coordinates":[144.83190918,-38.3711395264],"type":"Point"}
}