{
  "type": "Feature",
  "properties": {
    "addr:full":"8 Hull Crt Lonsdale SA 5160",
    "addr:housenumber":"8",
    "addr:postcode":"5160",
    "addr:street":"Hull Crt",
    "iso:country":"AU",
    "sg:address":"8 Hull Crt",
    "sg:city":"Lonsdale",
    "sg:classifiers":[
        {
            "category":"Wholesale",
            "subcategory":"Machinery & Supplies",
            "type":"Manufacturing & Wholesale Goods"
        }
    ],
    "sg:phone":"+61 8 8326 3303",
    "sg:postcode":"5160",
    "sg:province":"SA",
    "wof:name":"Artec Engineering",
    "wof:placetype":"venue"
},
  "geometry": {"coordinates":[138.49949645999999,-35.1147537231],"type":"Point"}
}