{
  "type": "Feature",
  "properties": {
    "addr:full":"Unit 1/ 10 Lampton Ave Derwent Park TAS 7009",
    "addr:housenumber":"10",
    "addr:postcode":"7009",
    "addr:street":"Lampton Ave",
    "iso:country":"AU",
    "sg:address":"Unit 1/ 10 Lampton Ave",
    "sg:city":"Derwent Park",
    "sg:classifiers":[
        {
            "category":"Retail",
            "subcategory":"Storage",
            "type":"Services"
        }
    ],
    "sg:phone":"+61 3 6273 5577",
    "sg:postcode":"7009",
    "sg:province":"TAS",
    "sg:tags":[
        "shelving",
        "system"
    ],
    "wof:name":"Complete Storage Systems Pty Ltd",
    "wof:placetype":"venue"
},
  "geometry": {"coordinates":[147.291915894,-42.8348693848],"type":"Point"}
}