{
  "type": "Feature",
  "properties": {
    "addr:full":"Queen Elizabeth Drv Dysart QLD 4745",
    "addr:postcode":"4745",
    "addr:street":"Elizabeth Drv",
    "iso:country":"AU",
    "sg:address":"Queen Elizabeth Drv",
    "sg:city":"Dysart",
    "sg:classifiers":[
        {
            "category":"Health Services",
            "subcategory":"Optometrist",
            "type":"Services"
        }
    ],
    "sg:phone":"+61 7 4941 8562",
    "sg:postcode":"4745",
    "sg:province":"QLD",
    "wof:name":"Central Highlands Optical",
    "wof:placetype":"venue"
},
  "geometry": {"coordinates":[148.34866299999999,-22.590349],"type":"Point"}
}