{
  "type": "Feature",
  "properties": {
    "addr:full":"96 Mollison St Kyneton VIC 3444",
    "addr:housenumber":"96",
    "addr:postcode":"3444",
    "addr:street":"Mollison St",
    "iso:country":"AU",
    "sg:address":"96 Mollison St",
    "sg:city":"Kyneton",
    "sg:classifiers":[
        {
            "category":"Real Estate",
            "subcategory":"Architect",
            "type":"Services"
        }
    ],
    "sg:phone":"+61 3 5422 6955",
    "sg:postcode":"3444",
    "sg:province":"VIC",
    "sg:tags":[
        "building",
        "designer"
    ],
    "wof:name":"Arciworx Design",
    "wof:placetype":"venue"
},
  "geometry": {"coordinates":[144.45347595199999,-37.2487030029],"type":"Point"}
}