{
  "type": "Feature",
  "properties": {
    "addr:full":"3 Ninth St Wingfield SA 5013",
    "addr:housenumber":"3",
    "addr:postcode":"5013",
    "addr:street":"Ninth St",
    "iso:country":"AU",
    "sg:address":"3 Ninth St",
    "sg:city":"Wingfield",
    "sg:classifiers":[
        {
            "category":"Manufacturing",
            "subcategory":"Metals",
            "type":"Manufacturing & Wholesale Goods"
        }
    ],
    "sg:phone":"+61 8 8244 6777",
    "sg:postcode":"5013",
    "sg:province":"SA",
    "sg:tags":[
        "steel",
        "fabricator",
        "mfrs"
    ],
    "wof:name":"Adelaide Steel Fabrications Pty Ltd",
    "wof:placetype":"venue"
},
  "geometry": {"coordinates":[138.55619812,-34.8381881714],"type":"Point"}
}