{
  "type": "Feature",
  "properties": {
    "addr:full":"9 Marryat Crt Hamilton Hill WA 6163",
    "addr:housenumber":"9",
    "addr:postcode":"6163",
    "addr:street":"Marryat Crt",
    "iso:country":"AU",
    "sg:address":"9 Marryat Crt",
    "sg:city":"Hamilton Hill",
    "sg:classifiers":[
        {
            "category":"Home & Garden",
            "subcategory":"Carpets & Floor Coverings",
            "type":"Retail Goods"
        }
    ],
    "sg:phone":"+61 8 9434 1629",
    "sg:postcode":"6163",
    "sg:province":"WA",
    "sg:tags":[
        "mat",
        "matting"
    ],
    "wof:name":"ABS Group",
    "wof:placetype":"venue"
},
  "geometry": {"coordinates":[115.77797700000001,-32.087627],"type":"Point"}
}