{
  "type": "Feature",
  "properties": {
    "addr:full":"43 Forge St Blacktown NSW 2148",
    "addr:housenumber":"43",
    "addr:postcode":"2148",
    "addr:street":"Forge St",
    "iso:country":"AU",
    "sg:address":"43 Forge St",
    "sg:city":"Blacktown",
    "sg:classifiers":[
        {
            "category":"Retail",
            "subcategory":"Auto Repair",
            "type":"Services"
        }
    ],
    "sg:phone":"+61 2 9671 7904",
    "sg:postcode":"2148",
    "sg:province":"NSW",
    "sg:tags":[
        "transmission",
        "automotive",
        "car"
    ],
    "wof:name":"J & V R Transmissions",
    "wof:placetype":"venue"
},
  "geometry": {"coordinates":[150.910400391,-33.753276825],"type":"Point"}
}