{
  "type": "Feature",
  "properties": {
    "addr:full":"14 Laughton St Chisholm ACT 2905",
    "addr:housenumber":"14",
    "addr:postcode":"2905",
    "addr:street":"Laughton St",
    "iso:country":"AU",
    "sg:address":"14 Laughton St",
    "sg:city":"Chisholm",
    "sg:classifiers":[
        {
            "category":"Structure",
            "subcategory":"Office Building",
            "type":"Public Place"
        }
    ],
    "sg:phone":"+61 418 633 201",
    "sg:postcode":"2905",
    "sg:province":"ACT",
    "sg:tags":[
        "slater",
        "tiler",
        "roof"
    ],
    "wof:name":"Hutchings Roofing Pty Ltd",
    "wof:placetype":"venue"
},
  "geometry": {"coordinates":[149.12387085,-35.4203109741],"type":"Point"}
}