{
  "type": "Feature",
  "properties": {
    "addr:full":"5 Province St Boondall QLD 4034",
    "addr:housenumber":"5",
    "addr:postcode":"4034",
    "addr:street":"Province St",
    "iso:country":"AU",
    "sg:address":"5 Province St",
    "sg:city":"Boondall",
    "sg:classifiers":[
        {
            "category":"Professional",
            "subcategory":"Art Services",
            "type":"Services"
        }
    ],
    "sg:phone":"+61 7 3265 2469",
    "sg:postcode":"4034",
    "sg:province":"QLD",
    "sg:tags":[
        "picture",
        "frame",
        "framing"
    ],
    "wof:name":"Five Star Framing",
    "wof:placetype":"venue"
},
  "geometry": {"coordinates":[153.057175,-27.353806],"type":"Point"}
}