{
  "type": "Feature",
  "properties": {
    "iso:country":"AU",
    "sg:address":"5 Montgomery St",
    "sg:city":"Miranda",
    "sg:classifiers":[
        {
            "category":"Sports & Exercise",
            "subcategory":"Sports Center",
            "type":"Entertainment"
        }
    ],
    "sg:phone":"+61 431 738 765",
    "sg:postcode":"2228",
    "sg:province":"NSW",
    "sg:tags":[
        "ground"
    ],
    "wof:name":"Sk8 Schools Australia",
    "wof:placetype":"venue"
},
  "geometry": {"coordinates":[151.10801696799999,-34.0324783325],"type":"Point"}
}