{
  "type": "Feature",
  "properties": {
    "addr:full":"116 Hammond Ave East Wagga Wagga NSW 2650",
    "addr:housenumber":"116",
    "addr:postcode":"2650",
    "addr:street":"Hammond Ave East",
    "iso:country":"AU",
    "sg:address":"116 Hammond Ave",
    "sg:city":"East Wagga Wagga",
    "sg:classifiers":[
        {
            "category":"Autos & Motor Vehicles",
            "subcategory":"Auto Supplies",
            "type":"Retail Goods"
        }
    ],
    "sg:phone":"+61 2 6921 7580",
    "sg:postcode":"2650",
    "sg:province":"NSW",
    "sg:tags":[
        "battery",
        "automotive"
    ],
    "wof:name":"Saddler Motors",
    "wof:placetype":"venue"
},
  "geometry": {"coordinates":[147.391113281,-35.1257705688],"type":"Point"}
}