{
  "type": "Feature",
  "properties": {
    "addr:full":"3 Waverley Ave Edwardstown SA 5039",
    "addr:housenumber":"3",
    "addr:postcode":"5039",
    "addr:street":"Waverley Ave",
    "iso:country":"AU",
    "sg:address":"3 Waverley Ave",
    "sg:city":"Edwardstown",
    "sg:classifiers":[
        {
            "category":"Professional",
            "subcategory":"Engineering",
            "type":"Services"
        }
    ],
    "sg:phone":"+61 8 8276 3644",
    "sg:postcode":"5039",
    "sg:province":"SA",
    "sg:tags":[
        "manufacturing",
        "engineer"
    ],
    "wof:name":"Flight Bros Pty Ltd",
    "wof:placetype":"venue"
},
  "geometry": {"coordinates":[138.57029724099999,-34.9850311279],"type":"Point"}
}