{
  "type": "Feature",
  "properties": {
    "iso:country":"AU",
    "sg:address":"Woodvale Shopping Village Shop 16 923 Whitfords Ave",
    "sg:city":"Woodvale",
    "sg:classifiers":[
        {
            "category":"Professional",
            "subcategory":"Art Services",
            "type":"Services"
        }
    ],
    "sg:phone":"+61 8 9309 9330",
    "sg:postcode":"6026",
    "sg:province":"WA",
    "sg:tags":[
        "picture",
        "frame",
        "framing"
    ],
    "wof:name":"Woodvale Art Framers",
    "wof:placetype":"venue"
},
  "geometry": {"coordinates":[115.808532715,-31.785654068],"type":"Point"}
}