{
  "type": "Feature",
  "properties": {
    "addr:full":"245 Fitzgerald St Northam WA 6401",
    "addr:housenumber":"245",
    "addr:postcode":"6401",
    "addr:street":"Fitzgerald St",
    "iso:country":"AU",
    "sg:address":"245 Fitzgerald St",
    "sg:city":"Northam",
    "sg:classifiers":[
        {
            "category":"Building & Trades",
            "subcategory":"Locksmith",
            "type":"Services"
        }
    ],
    "sg:phone":"+61 8 9622 8883",
    "sg:postcode":"6401",
    "sg:province":"WA",
    "sg:tags":[
        "lock"
    ],
    "wof:name":"Avon Locks & Keys",
    "wof:placetype":"venue"
},
  "geometry": {"coordinates":[116.670051575,-31.6552028656],"type":"Point"}
}