{
  "type": "Feature",
  "properties": {
    "iso:country":"AU",
    "sg:address":"Bonville St",
    "sg:city":"Urunga",
    "sg:classifiers":[
        {
            "category":"Communications",
            "subcategory":"News Services",
            "type":"Services"
        }
    ],
    "sg:phone":"+61 2 6655 5426",
    "sg:postcode":"2455",
    "sg:province":"NSW",
    "sg:tags":[
        "information",
        "tourist",
        "attractions"
    ],
    "wof:name":"Odal-Berree Tours",
    "wof:placetype":"venue"
},
  "geometry": {"coordinates":[153.020508,-30.498142],"type":"Point"}
}