{
  "type": "Feature",
  "properties": {
    "iso:country":"AU",
    "sg:address":"PO Box 265",
    "sg:city":"Boronia",
    "sg:classifiers":[
        {
            "category":"Building & Trades",
            "subcategory":"Plumbing",
            "type":"Services"
        }
    ],
    "sg:phone":"+61 411 460 656",
    "sg:postcode":"3155",
    "sg:province":"VIC",
    "sg:tags":[
        "plumber",
        "gasfitters"
    ],
    "wof:name":"C J B Plumbing",
    "wof:placetype":"venue"
},
  "geometry": {"coordinates":[145.28416442899999,-37.8538093567],"type":"Point"}
}