{
  "type": "Feature",
  "properties": {
    "iso:country":"AU",
    "sg:address":"11 Hewitt St",
    "sg:city":"Moura",
    "sg:classifiers":[
        {
            "category":"Education",
            "subcategory":"Special Training",
            "type":"Public Place"
        }
    ],
    "sg:phone":"+61 7 4997 3473",
    "sg:postcode":"4718",
    "sg:province":"QLD",
    "sg:tags":[
        "tuition-educational"
    ],
    "wof:name":"Moura Reading & Writing Centre",
    "wof:placetype":"venue"
},
  "geometry": {"coordinates":[149.97059631400001,-24.5725498199],"type":"Point"}
}