{
  "type": "Feature",
  "properties": {
    "addr:full":"50 Belgravia St Belmont WA 6104",
    "addr:housenumber":"50",
    "addr:postcode":"6104",
    "addr:street":"Belgravia St",
    "iso:country":"AU",
    "sg:address":"50 Belgravia St",
    "sg:city":"Belmont",
    "sg:classifiers":[
        {
            "category":"Professional",
            "subcategory":"Printing & Photocopies",
            "type":"Services"
        }
    ],
    "sg:phone":"+61 8 9479 6600",
    "sg:postcode":"6104",
    "sg:province":"WA",
    "sg:tags":[
        "photocopier"
    ],
    "wof:name":"Konica Minolta Business Solutions",
    "wof:placetype":"venue"
},
  "geometry": {"coordinates":[115.926048279,-31.9466724396],"type":"Point"}
}