{
  "type": "Feature",
  "properties": {
    "iso:country":"AU",
    "sg:address":"Cnr Seymour & Market Sts",
    "sg:city":"Ringwood",
    "sg:classifiers":[
        {
            "category":"Health Services",
            "subcategory":"Health Practitioner",
            "type":"Services"
        }
    ],
    "sg:phone":"+61 3 9876 0888",
    "sg:postcode":"3134",
    "sg:province":"VIC",
    "sg:tags":[
        "physiotherapist"
    ],
    "wof:name":"In Touch Physiotherapy",
    "wof:placetype":"venue"
},
  "geometry": {"coordinates":[145.227172852,-37.8150177002],"type":"Point"}
}