{
  "type": "Feature",
  "properties": {
    "addr:full":"50 Assembly Drv Tullamarine VIC 3043",
    "addr:housenumber":"50",
    "addr:postcode":"3043",
    "addr:street":"Assembly Drv",
    "iso:country":"AU",
    "sg:address":"50 Assembly Drv",
    "sg:city":"Tullamarine",
    "sg:classifiers":[
        {
            "category":"Retail",
            "subcategory":"Storage",
            "type":"Services"
        }
    ],
    "sg:phone":"+61 3 9335 2733",
    "sg:postcode":"3043",
    "sg:province":"VIC",
    "wof:name":"Link Air Bond",
    "wof:placetype":"venue"
},
  "geometry": {"coordinates":[144.86607360799999,-37.7074546814],"type":"Point"}
}