{
  "type": "Feature",
  "properties": {
    "addr:full":"22 Andrew Thomson Drv McGraths Hill NSW 2756",
    "addr:housenumber":"22",
    "addr:postcode":"2756",
    "addr:street":"Andrew Thomson Drv",
    "iso:country":"AU",
    "sg:address":"22 Andrew Thomson Drv",
    "sg:city":"McGraths Hill",
    "sg:classifiers":[
        {
            "category":"Shopping",
            "subcategory":"Bicycles & Sporting Goods",
            "type":"Retail Goods"
        }
    ],
    "sg:phone":"+61 2 4577 5135",
    "sg:postcode":"2756",
    "sg:province":"NSW",
    "sg:tags":[
        "synthetic",
        "surface"
    ],
    "wof:name":"Playpave Sporting Systems",
    "wof:placetype":"venue"
},
  "geometry": {"coordinates":[150.83732605,-33.6184158325],"type":"Point"}
}