{
  "type": "Feature",
  "properties": {
    "addr:full":"325 Springvale Rd Glen Waverley VIC 3150",
    "addr:housenumber":"325",
    "addr:postcode":"3150",
    "addr:street":"Springvale Rd",
    "iso:country":"AU",
    "sg:address":"325 Springvale Rd",
    "sg:city":"Glen Waverley",
    "sg:classifiers":[
        {
            "category":"Health Services",
            "subcategory":"Doctor",
            "type":"Services"
        }
    ],
    "sg:phone":"+61 3 9561 5858",
    "sg:postcode":"3150",
    "sg:province":"VIC",
    "sg:tags":[
        "medical",
        "practitioner"
    ],
    "wof:name":"Tan W O",
    "wof:placetype":"venue"
},
  "geometry": {"coordinates":[145.16494750999999,-37.8830795288],"type":"Point"}
}