{
  "type": "Feature",
  "properties": {
    "addr:full":"149 Church St Brighton VIC 3186",
    "addr:housenumber":"149",
    "addr:postcode":"3186",
    "addr:street":"Church St",
    "iso:country":"AU",
    "sg:address":"149 Church St",
    "sg:city":"Brighton",
    "sg:classifiers":[
        {
            "category":"Health Services",
            "subcategory":"Health Practitioner",
            "type":"Services"
        }
    ],
    "sg:phone":"+61 3 9591 0540",
    "sg:postcode":"3186",
    "sg:province":"VIC",
    "sg:tags":[
        "psychologist"
    ],
    "wof:name":"Milburn J D",
    "wof:placetype":"venue"
},
  "geometry": {"coordinates":[144.996917725,-37.9159393311],"type":"Point"}
}