{
  "type": "Feature",
  "properties": {
    "iso:country":"AU",
    "sg:address":"Shop 9/ 120 Anderson St",
    "sg:city":"Manunda",
    "sg:classifiers":[
        {
            "category":"Home & Garden",
            "subcategory":"Furniture",
            "type":"Retail Goods"
        }
    ],
    "sg:phone":"+61 7 4053 6969",
    "sg:postcode":"4870",
    "sg:province":"QLD",
    "sg:tags":[
        "repair",
        "restoration"
    ],
    "wof:name":"Robert Allwood",
    "wof:placetype":"venue"
},
  "geometry": {"coordinates":[145.742874145,-16.91664505],"type":"Point"}
}