{
  "type": "Feature",
  "properties": {
    "iso:country":"AU",
    "sg:address":"831 High St",
    "sg:city":"Thornbury",
    "sg:classifiers":[
        {
            "category":"Professional",
            "subcategory":"Accounting & Tax Preparation",
            "type":"Services"
        }
    ],
    "sg:phone":"+61 3 9484 5000",
    "sg:postcode":"3071",
    "sg:province":"VIC",
    "sg:tags":[
        "accountant",
        "auditor"
    ],
    "wof:name":"Nicholson Partners",
    "wof:placetype":"venue"
},
  "geometry": {"coordinates":[145.00097656200001,-37.7554092407],"type":"Point"}
}