{
  "type": "Feature",
  "properties": {
    "addr:full":"Level 1/ 50 Yeo St Neutral Bay NSW 2089",
    "addr:housenumber":"/ 50",
    "addr:postcode":"2089",
    "addr:street":"Yeo St",
    "iso:country":"AU",
    "sg:address":"Level 1/ 50 Yeo St",
    "sg:city":"Neutral Bay",
    "sg:classifiers":[
        {
            "category":"Professional",
            "subcategory":"Art Services",
            "type":"Services"
        }
    ],
    "sg:phone":"+61 2 9953 1494",
    "sg:postcode":"2089",
    "sg:province":"NSW",
    "sg:tags":[
        "graphic",
        "designer"
    ],
    "wof:name":"Workhouse Visual Communications Pty Ltd The",
    "wof:placetype":"venue"
},
  "geometry": {"coordinates":[151.22288513199999,-33.8322486877],"type":"Point"}
}