{
  "type": "Feature",
  "properties": {
    "addr:full":"305 Wingham Rd Taree NSW 2430",
    "addr:housenumber":"305",
    "addr:postcode":"2430",
    "addr:street":"Wingham Rd",
    "iso:country":"AU",
    "sg:address":"305 Wingham Rd",
    "sg:city":"Taree",
    "sg:classifiers":[
        {
            "category":"Building & Trades",
            "subcategory":"Construction",
            "type":"Services"
        }
    ],
    "sg:phone":"+61 2 6552 6545",
    "sg:postcode":"2430",
    "sg:province":"NSW",
    "sg:tags":[
        "polishing",
        "sanding",
        "floor"
    ],
    "wof:name":"Taree Timber Floors",
    "wof:placetype":"venue"
},
  "geometry": {"coordinates":[152.442474,-31.886267],"type":"Point"}
}