{
  "type": "Feature",
  "properties": {
    "addr:full":"17 Clay Gully Crt Bendigo VIC 3550",
    "addr:housenumber":"17",
    "addr:postcode":"3550",
    "addr:street":"Clay Gully Crt",
    "iso:country":"AU",
    "sg:address":"17 Clay Gully Crt",
    "sg:city":"Bendigo",
    "sg:classifiers":[
        {
            "category":"Professional",
            "subcategory":"Testing Lab",
            "type":"Services"
        }
    ],
    "sg:phone":"+61 409 709 423",
    "sg:postcode":"3550",
    "sg:province":"VIC",
    "sg:tags":[
        "inspection"
    ],
    "wof:name":"Elecwise Pty Ltd",
    "wof:placetype":"venue"
},
  "geometry": {"coordinates":[144.22819519000001,-36.7526702881],"type":"Point"}
}