{
  "type": "Feature",
  "properties": {
    "iso:country":"AU",
    "sg:address":"24 Nelson St",
    "sg:city":"Port Noarlunga South",
    "sg:classifiers":[
        {
            "category":"Building & Trades",
            "subcategory":"Construction",
            "type":"Services"
        }
    ],
    "sg:phone":"+61 8 8327 4530",
    "sg:postcode":"5167",
    "sg:province":"SA",
    "sg:tags":[
        "renovation",
        "alterations",
        "extension",
        "contractor"
    ],
    "wof:name":"Craig Hurrell Builder",
    "wof:placetype":"venue"
},
  "geometry": {"coordinates":[138.472412109,-35.1657066345],"type":"Point"}
}