{
  "type": "Feature",
  "properties": {
    "iso:country":"AU",
    "sg:address":"160 Sir Donald Bradman Drv",
    "sg:city":"Hilton",
    "sg:classifiers":[
        {
            "category":"Personal",
            "subcategory":"Beauty Salon",
            "type":"Services"
        }
    ],
    "sg:phone":"+61 8 8234 9747",
    "sg:postcode":"5033",
    "sg:province":"SA",
    "sg:tags":[
        "hairdresser"
    ],
    "wof:name":"Aqua Hair",
    "wof:placetype":"venue"
},
  "geometry": {"coordinates":[138.562225342,-34.9320259094],"type":"Point"}
}