{
  "type": "Feature",
  "properties": {
    "iso:country":"AU",
    "sg:address":"PO Box 4153",
    "sg:city":"Penrith Plaza",
    "sg:classifiers":[
        {
            "category":"Building & Trades",
            "subcategory":"Construction",
            "type":"Services"
        }
    ],
    "sg:phone":"+61 2 4735 5998",
    "sg:postcode":"2750",
    "sg:province":"NSW",
    "sg:tags":[
        "earth",
        "excavating",
        "moving",
        "contractor"
    ],
    "wof:name":"Shepherd Group Services Pty Ltd",
    "wof:placetype":"venue"
},
  "geometry": {"coordinates":[150.692337036,-33.7511901855],"type":"Point"}
}