{
  "type": "Feature",
  "properties": {
    "iso:country":"AU",
    "sg:address":"Redcliffe Pde",
    "sg:city":"Redcliffe",
    "sg:classifiers":[
        {
            "category":"Real Estate",
            "subcategory":"Real Estate Agent",
            "type":"Services"
        }
    ],
    "sg:phone":"+61 7 3284 3000",
    "sg:postcode":"4020",
    "sg:province":"QLD",
    "wof:name":"RE/MAX Alliance Realty",
    "wof:placetype":"venue"
},
  "geometry": {"coordinates":[153.107224,-27.22217],"type":"Point"}
}