{
  "type": "Feature",
  "properties": {
    "addr:full":"Euston Ave Irymple VIC 3498",
    "addr:postcode":"3498",
    "addr:street":"Euston Ave",
    "iso:country":"AU",
    "sg:address":"Euston Ave",
    "sg:city":"Irymple",
    "sg:classifiers":[
        {
            "category":"Farming",
            "subcategory":"Berry Farm",
            "type":"Manufacturing & Wholesale Goods"
        }
    ],
    "sg:phone":"+61 3 5024 5723",
    "sg:postcode":"3498",
    "sg:province":"VIC",
    "sg:tags":[
        "fruit",
        "grower"
    ],
    "wof:name":"Balog S & K",
    "wof:placetype":"venue"
},
  "geometry": {"coordinates":[142.154953003,-34.2563514709],"type":"Point"}
}