{
  "type": "Feature",
  "properties": {
    "addr:full":"Fitzroy St Binalong NSW 2584",
    "addr:postcode":"2584",
    "addr:street":"Fitzroy St",
    "iso:country":"AU",
    "sg:address":"Fitzroy St",
    "sg:city":"Binalong",
    "sg:classifiers":[
        {
            "category":"Food & Beverages",
            "subcategory":"Groceries & Convenience Stores",
            "type":"Retail Goods"
        }
    ],
    "sg:phone":"+61 2 6227 4309",
    "sg:postcode":"2584",
    "sg:province":"NSW",
    "wof:name":"Binalong General Store",
    "wof:placetype":"venue"
},
  "geometry": {"coordinates":[148.632736206,-34.6686096191],"type":"Point"}
}