{
  "type": "Feature",
  "properties": {
    "addr:full":"81a Lockhart St Como WA 6152",
    "addr:housenumber":"81a",
    "addr:postcode":"6152",
    "addr:street":"Lockhart St",
    "iso:country":"AU",
    "sg:address":"81a Lockhart St",
    "sg:city":"Como",
    "sg:classifiers":[
        {
            "category":"Health Services",
            "subcategory":"Health Practitioner",
            "type":"Services"
        }
    ],
    "sg:phone":"+61 8 9313 2113",
    "sg:postcode":"6152",
    "sg:province":"WA",
    "sg:tags":[
        "pathologist",
        "speech"
    ],
    "wof:name":"Kilov Andrea",
    "wof:placetype":"venue"
},
  "geometry": {"coordinates":[115.859047,-32.004299],"type":"Point"}
}