{
  "type": "Feature",
  "properties": {
    "addr:full":"60 Aberfeldy St Kenmore QLD 4069",
    "addr:housenumber":"60",
    "addr:postcode":"4069",
    "addr:street":"Aberfeldy St",
    "iso:country":"AU",
    "sg:address":"60 Aberfeldy St",
    "sg:city":"Kenmore",
    "sg:classifiers":[
        {
            "category":"Education",
            "subcategory":"School",
            "type":"Public Place"
        }
    ],
    "sg:phone":"+61 7 3327 1555",
    "sg:postcode":"4069",
    "sg:province":"QLD",
    "sg:tags":[
        "state",
        "except",
        "nsw"
    ],
    "wof:name":"Kenmore High",
    "wof:placetype":"venue"
},
  "geometry": {"coordinates":[152.92956543,-27.5083675385],"type":"Point"}
}