{
  "type": "Feature",
  "properties": {
    "addr:full":"9 Power Rd Gympie QLD 4570",
    "addr:housenumber":"9",
    "addr:postcode":"4570",
    "addr:street":"Power Rd",
    "iso:country":"AU",
    "sg:address":"9 Power Rd",
    "sg:city":"Gympie",
    "sg:classifiers":[
        {
            "category":"Retail",
            "subcategory":"Event Space",
            "type":"Services"
        }
    ],
    "sg:phone":"+61 7 5482 3107",
    "sg:postcode":"4570",
    "sg:province":"QLD",
    "sg:tags":[
        "venue",
        "reception",
        "wedding"
    ],
    "wof:name":"Gunabul Homestead Weddings & Restaurant",
    "wof:placetype":"venue"
},
  "geometry": {"coordinates":[152.65911865199999,-26.2029380798],"type":"Point"}
}