{
  "type": "Feature",
  "properties": {
    "iso:country":"AU",
    "sg:address":"Shop 1, 20- 22 Woodriss St",
    "sg:city":"Penrith",
    "sg:classifiers":[
        {
            "category":"Personal",
            "subcategory":"Beauty Salon",
            "type":"Services"
        }
    ],
    "sg:phone":"+61 2 4731 3036",
    "sg:postcode":"2750",
    "sg:province":"NSW",
    "sg:tags":[
        "hairdresser"
    ],
    "wof:name":"Captive Hair Studio",
    "wof:placetype":"venue"
},
  "geometry": {"coordinates":[150.69810485799999,-33.754650116],"type":"Point"}
}