{
  "type": "Feature",
  "properties": {
    "addr:full":"Unit 1/ 166 James St Toowoomba QLD 4350",
    "addr:housenumber":"/ 166",
    "addr:postcode":"4350",
    "addr:street":"James St",
    "iso:country":"AU",
    "sg:address":"Unit 1/ 166 James St",
    "sg:city":"Toowoomba",
    "sg:classifiers":[
        {
            "category":"Wholesale",
            "subcategory":"Machinery & Supplies",
            "type":"Manufacturing & Wholesale Goods"
        }
    ],
    "sg:phone":"+61 7 4638 5899",
    "sg:postcode":"4350",
    "sg:province":"QLD",
    "sg:tags":[
        "equipment",
        "hydraulic"
    ],
    "wof:name":"Enzed",
    "wof:placetype":"venue"
},
  "geometry": {"coordinates":[151.95109600000001,-27.568693],"type":"Point"}
}