{
  "type": "Feature",
  "properties": {
    "addr:full":"Shop2/ 720 Main Rd Edgeworth NSW 2285",
    "addr:housenumber":"720",
    "addr:postcode":"2285",
    "addr:street":"Main Rd",
    "iso:country":"AU",
    "sg:address":"Shop2/ 720 Main Rd",
    "sg:city":"Edgeworth",
    "sg:classifiers":[
        {
            "category":"Shopping",
            "subcategory":"Clothing, Apparel, & Fashions",
            "type":"Retail Goods"
        }
    ],
    "sg:phone":"+61 2 4965 8088",
    "sg:postcode":"2285",
    "sg:province":"NSW",
    "sg:tags":[
        "lingerie",
        "hosiery",
        "sleepwear"
    ],
    "wof:name":"Bare Coverage",
    "wof:placetype":"venue"
},
  "geometry": {"coordinates":[151.62396240199999,-32.9445037842],"type":"Point"}
}