{
  "type": "Feature",
  "properties": {
    "addr:full":"20 Frenchs Forest Rd Frenchs Forest NSW 2086",
    "addr:housenumber":"20",
    "addr:postcode":"2086",
    "addr:street":"Frenchs Forest Rd",
    "iso:country":"AU",
    "sg:address":"20 Frenchs Forest Rd",
    "sg:city":"Frenchs Forest",
    "sg:classifiers":[
        {
            "category":"Fast Food",
            "type":"Food & Drink"
        }
    ],
    "sg:phone":"+61 2 9451 5946",
    "sg:postcode":"2086",
    "sg:province":"NSW",
    "sg:tags":[
        "away",
        "take"
    ],
    "wof:name":"Bills Take Away",
    "wof:placetype":"venue"
},
  "geometry": {"coordinates":[151.24392700199999,-33.7510871887],"type":"Point"}
}