{
  "type": "Feature",
  "properties": {
    "addr:full":"Unit 3, 59 Kapara Rd Gillman SA 5013",
    "addr:housenumber":"59",
    "addr:postcode":"5013",
    "addr:street":"Kapara Rd",
    "iso:country":"AU",
    "sg:address":"Unit 3, 59 Kapara Rd",
    "sg:city":"Gillman",
    "sg:classifiers":[
        {
            "category":"Wholesale",
            "subcategory":"Machinery & Supplies",
            "type":"Manufacturing & Wholesale Goods"
        }
    ],
    "sg:phone":"+61 8 8347 7100",
    "sg:postcode":"5013",
    "sg:province":"SA",
    "sg:tags":[
        "distributor",
        "crane",
        "mfrs"
    ],
    "wof:name":"JDN Monocrane",
    "wof:placetype":"venue"
},
  "geometry": {"coordinates":[138.53669738799999,-34.8397789001],"type":"Point"}
}