{
  "type": "Feature",
  "properties": {
    "iso:country":"AU",
    "sg:address":"1b Colstoun Rd",
    "sg:city":"Ashfield",
    "sg:classifiers":[
        {
            "category":"Fast Food",
            "type":"Food & Drink"
        }
    ],
    "sg:phone":"+61 8 9378 4355",
    "sg:postcode":"6054",
    "sg:province":"WA",
    "sg:tags":[
        "away",
        "take"
    ],
    "wof:name":"Pasta Viva",
    "wof:placetype":"venue"
},
  "geometry": {"coordinates":[115.935821533,-31.9138450623],"type":"Point"}
}