{
  "type": "Feature",
  "properties": {
    "addr:full":"Shop 4/ 7 Hallam Rd Hallam VIC 3803",
    "addr:housenumber":"shop 4 / 7",
    "addr:postcode":"3803",
    "addr:street":"Hallam Rd",
    "iso:country":"AU",
    "sg:address":"Shop 4/ 7 Hallam Rd",
    "sg:city":"Hallam",
    "sg:classifiers":[
        {
            "category":"Fast Food",
            "type":"Food & Drink"
        }
    ],
    "sg:phone":"+61 3 9703 2212",
    "sg:postcode":"3803",
    "sg:province":"VIC",
    "sg:tags":[
        "away",
        "take"
    ],
    "wof:name":"Jessies Pizza",
    "wof:placetype":"venue"
},
  "geometry": {"coordinates":[145.27302551299999,-38.0072021484],"type":"Point"}
}