{
  "type": "Feature",
  "properties": {
    "addr:full":"6 Marker St Enfield SA 5085",
    "addr:housenumber":"6",
    "addr:postcode":"5085",
    "addr:street":"Marker St",
    "iso:country":"AU",
    "sg:address":"6 Marker St",
    "sg:city":"Enfield",
    "sg:classifiers":[
        {
            "category":"Shopping",
            "subcategory":"Pets & Pet Supplies",
            "type":"Retail Goods"
        }
    ],
    "sg:phone":"+61 8 8262 4698",
    "sg:postcode":"5085",
    "sg:province":"SA",
    "sg:tags":[
        "dog"
    ],
    "wof:name":"D.O.G.S. Importers & Distributors",
    "wof:placetype":"venue"
},
  "geometry": {"coordinates":[138.60690307600001,-34.8498878479],"type":"Point"}
}