{
  "type": "Feature",
  "properties": {
    "iso:country":"AU",
    "sg:address":"61 Addison Ave",
    "sg:city":"East Roseville",
    "sg:classifiers":[
        {
            "category":"Health Services",
            "subcategory":"Dentist",
            "type":"Services"
        }
    ],
    "sg:phone":"+61 2 9417 1974",
    "sg:postcode":"2069",
    "sg:province":"NSW",
    "wof:name":"Der Tateossian John",
    "wof:placetype":"venue"
},
  "geometry": {"coordinates":[151.193603516,-33.7799415588],"type":"Point"}
}