{
  "type": "Feature",
  "properties": {
    "iso:country":"AU",
    "sg:address":"Moggill-Burkin Rd",
    "sg:city":"Bellbowrie",
    "sg:classifiers":[
        {
            "category":"Government",
            "subcategory":"Post Office",
            "type":"Public Place"
        }
    ],
    "sg:phone":"+61 7 3202 7206",
    "sg:postcode":"4070",
    "sg:province":"QLD",
    "sg:tags":[
        "postal"
    ],
    "wof:name":"Bellbowrie Post Office",
    "wof:placetype":"venue"
},
  "geometry": {"coordinates":[152.886627197,-27.5625247955],"type":"Point"}
}