{
  "type": "Feature",
  "properties": {
    "iso:country":"AU",
    "sg:address":"10 Lockheed St",
    "sg:city":"Tamworth",
    "sg:classifiers":[
        {
            "category":"Food & Beverages",
            "subcategory":"Bakery",
            "type":"Retail Goods"
        }
    ],
    "sg:phone":"+61 2 6765 7288",
    "sg:postcode":"2340",
    "sg:province":"NSW",
    "sg:tags":[
        "baker"
    ],
    "wof:name":"Buttercup",
    "wof:placetype":"venue"
},
  "geometry": {"coordinates":[150.90965270999999,-31.0905284882],"type":"Point"}
}