{
  "type": "Feature",
  "properties": {
    "addr:full":"Lake St Murtoa VIC 3390",
    "addr:postcode":"3390",
    "addr:street":"Lake St",
    "iso:country":"AU",
    "sg:address":"Lake St",
    "sg:city":"Murtoa",
    "sg:classifiers":[
        {
            "category":"Arena",
            "subcategory":"Sports Club",
            "type":"Entertainment"
        }
    ],
    "sg:phone":"+61 3 5385 2695",
    "sg:postcode":"3390",
    "sg:province":"VIC",
    "sg:tags":[
        "australian",
        "football",
        "rule"
    ],
    "wof:name":"Minyip- Murtoa Football Club",
    "wof:placetype":"venue"
},
  "geometry": {"coordinates":[142.46649169899999,-36.6192932129],"type":"Point"}
}