{
  "type": "Feature",
  "properties": {
    "addr:full":"Holland Park Specialist Cntr 1000 Logan Rd Holland Park QLD 4121",
    "addr:housenumber":"1000",
    "addr:postcode":"4121",
    "addr:street":"Logan Rd",
    "iso:country":"AU",
    "sg:address":"Holland Park Specialist Cntr 1000 Logan Rd",
    "sg:city":"Holland Park",
    "sg:classifiers":[
        {
            "category":"Health Services",
            "subcategory":"Doctor",
            "type":"Services"
        }
    ],
    "sg:phone":"+61 7 3846 2500",
    "sg:postcode":"4121",
    "sg:province":"QLD",
    "sg:tags":[
        "medical",
        "practitioner"
    ],
    "wof:name":"Duffy Peter B",
    "wof:placetype":"venue"
},
  "geometry": {"coordinates":[153.06245422399999,-27.5199394226],"type":"Point"}
}