{
  "type": "Feature",
  "properties": {
    "addr:full":"40 Jamieson St Wentworth Falls NSW 2782",
    "addr:housenumber":"40",
    "addr:postcode":"2782",
    "addr:street":"Jamieson St",
    "iso:country":"AU",
    "sg:address":"40 Jamieson St",
    "sg:city":"Wentworth Falls",
    "sg:classifiers":[
        {
            "category":"Building & Trades",
            "subcategory":"Landscaping Services",
            "type":"Services"
        }
    ],
    "sg:phone":"+61 2 4757 2511",
    "sg:postcode":"2782",
    "sg:province":"NSW",
    "sg:tags":[
        "designer",
        "landscape",
        "contractor"
    ],
    "wof:name":"Arthur Lathouris",
    "wof:placetype":"venue"
},
  "geometry": {"coordinates":[150.37591552699999,-33.7218742371],"type":"Point"}
}