{
  "type": "Feature",
  "properties": {
    "addr:full":"Henbury Ave Kandos NSW 2848",
    "addr:postcode":"2848",
    "addr:street":"Henbury Ave",
    "iso:country":"AU",
    "sg:address":"Henbury Ave",
    "sg:city":"Kandos",
    "sg:classifiers":[
        {
            "category":"Sports & Exercise",
            "subcategory":"Golf",
            "type":"Entertainment"
        }
    ],
    "sg:phone":"+61 2 6379 4101",
    "sg:postcode":"2848",
    "sg:province":"NSW",
    "sg:tags":[
        "club"
    ],
    "wof:name":"Henbury Golf Club",
    "wof:placetype":"venue"
},
  "geometry": {"coordinates":[149.97129799999999,-32.85537],"type":"Point"}
}