{
  "type": "Feature",
  "properties": {
    "iso:country":"AU",
    "sg:address":"Cnr Spring Gully Rd & Retreat Rd",
    "sg:city":"Spring Gully",
    "sg:classifiers":[
        {
            "category":"Travel",
            "subcategory":"Hotels & Motels",
            "type":"Entertainment"
        }
    ],
    "sg:phone":"+61 3 5443 7219",
    "sg:postcode":"3550",
    "sg:province":"VIC",
    "sg:tags":[
        "accommodation"
    ],
    "wof:name":"One Tree Hill Hotel Pty Ltd",
    "wof:placetype":"venue"
},
  "geometry": {"coordinates":[144.28666687,-36.7981376648],"type":"Point"}
}