{
  "type": "Feature",
  "properties": {
    "iso:country":"AU",
    "sg:address":"100 Bridge St",
    "sg:city":"Picton",
    "sg:classifiers":[
        {
            "category":"Wholesale",
            "subcategory":"Machinery & Supplies",
            "type":"Manufacturing & Wholesale Goods"
        }
    ],
    "sg:phone":"+61 2 4677 2877",
    "sg:postcode":"2571",
    "sg:province":"NSW",
    "sg:tags":[
        "machine",
        "tool",
        "engineer"
    ],
    "wof:name":"Epic Industries Pty Ltd",
    "wof:placetype":"venue"
},
  "geometry": {"coordinates":[150.59918212900001,-34.1936759949],"type":"Point"}
}