{
  "type": "Feature",
  "properties": {
    "iso:country":"AU",
    "sg:address":"21 Hammer St",
    "sg:city":"Bendigo",
    "sg:classifiers":[
        {
            "category":"Building & Trades",
            "subcategory":"Construction",
            "type":"Services"
        }
    ],
    "sg:phone":"+61 3 5441 6542",
    "sg:postcode":"3539",
    "sg:province":"VIC",
    "sg:tags":[
        "welding"
    ],
    "wof:name":"Rob Pierce Engineering",
    "wof:placetype":"venue"
},
  "geometry": {"coordinates":[144.29315185600001,-36.7751197815],"type":"Point"}
}