{
  "type": "Feature",
  "properties": {
    "addr:full":"JAC/ICTE, Joyce Ackroyd Building, University of Qu Lucia QLD 4067",
    "addr:postcode":"4067",
    "iso:country":"AU",
    "sg:address":"JAC/ICTE, Joyce Ackroyd Building, University of Qu",
    "sg:city":"Lucia",
    "sg:classifiers":[
        {
            "category":"Education",
            "subcategory":"University",
            "type":"Public Place"
        }
    ],
    "sg:phone":"+61 7 3876 0422",
    "sg:postcode":"4067",
    "sg:province":"QLD",
    "sg:tags":[
        "educational",
        "organisation",
        "cultural"
    ],
    "wof:name":"Jikei Australia Centre",
    "wof:placetype":"venue"
},
  "geometry": {"coordinates":[153.004516602,-27.4940605164],"type":"Point"}
}