{
  "type": "Feature",
  "properties": {
    "addr:full":"10 Ridgeland St Woongarrah NSW 2259",
    "addr:housenumber":"10",
    "addr:postcode":"2259",
    "addr:street":"Ridgeland St",
    "iso:country":"AU",
    "sg:address":"10 Ridgeland St",
    "sg:city":"Woongarrah",
    "sg:classifiers":[
        {
            "category":"Health Services",
            "subcategory":"Chiropractor",
            "type":"Services"
        }
    ],
    "sg:phone":"+61 2 4393 9127",
    "sg:postcode":"2259",
    "sg:province":"NSW",
    "wof:name":"Gibbons Ellis Chiropractor",
    "wof:placetype":"venue"
},
  "geometry": {"coordinates":[151.472564697,-33.2433929443],"type":"Point"}
}