{
  "type": "Feature",
  "properties": {
    "iso:country":"AU",
    "sg:address":"7 Whyalla St",
    "sg:city":"Fyshwick",
    "sg:classifiers":[
        {
            "category":"Utilities",
            "subcategory":"Fuel Oil & Lpg",
            "type":"Services"
        }
    ],
    "sg:phone":"+61 2 6280 5118",
    "sg:postcode":"2609",
    "sg:province":"ACT",
    "sg:tags":[
        "merchant"
    ],
    "wof:name":"Woodstock Firewood",
    "wof:placetype":"venue"
},
  "geometry": {"coordinates":[149.17239379899999,-35.3342018127],"type":"Point"}
}