{
  "type": "Feature",
  "properties": {
    "iso:country":"AU",
    "sg:address":"Manning Drv",
    "sg:city":"Noble Park North",
    "sg:classifiers":[
        {
            "category":"Education",
            "subcategory":"School",
            "type":"Public Place"
        }
    ],
    "sg:phone":"+61 3 9795 8100",
    "sg:postcode":"3174",
    "sg:province":"VIC",
    "sg:tags":[
        "co-educational"
    ],
    "wof:name":"Nazareth College",
    "wof:placetype":"venue"
},
  "geometry": {"coordinates":[145.19305419899999,-37.9410743713],"type":"Point"}
}