{
  "type": "Feature",
  "properties": {
    "iso:country":"AU",
    "sg:address":"225B Settlement Rd",
    "sg:city":"Thomastown",
    "sg:classifiers":[
        {
            "category":"Building & Trades",
            "subcategory":"Construction",
            "type":"Services"
        }
    ],
    "sg:phone":"+61 3 9464 3319",
    "sg:postcode":"3074",
    "sg:province":"VIC",
    "sg:tags":[
        "contractor"
    ],
    "wof:name":"GJ Gardner Homes Pty Ltd",
    "wof:placetype":"venue"
},
  "geometry": {"coordinates":[145.032272339,-37.6938018799],"type":"Point"}
}