{
  "type": "Feature",
  "properties": {
    "addr:full":"Shop 40 Menai Marketplace Allison Crs Menai NSW 2234",
    "addr:housenumber":"shop 40",
    "addr:postcode":"2234",
    "addr:street":"Allison Crs",
    "iso:country":"AU",
    "sg:address":"Shop 40 Menai Marketplace Allison Crs",
    "sg:city":"Menai",
    "sg:classifiers":[
        {
            "category":"Real Estate",
            "subcategory":"Real Estate Agent",
            "type":"Services"
        }
    ],
    "sg:phone":"+61 2 9543 2111",
    "sg:postcode":"2234",
    "sg:province":"NSW",
    "wof:name":"Century 21 Menai Real Estate",
    "wof:placetype":"venue"
},
  "geometry": {"coordinates":[151.043869019,-34.0201339722],"type":"Point"}
}