{
  "type": "Feature",
  "properties": {
    "iso:country":"AU",
    "sg:address":"56 Bridge St",
    "sg:city":"Bendigo",
    "sg:classifiers":[
        {
            "category":"Manufacturing",
            "subcategory":"Tools & Machinery",
            "type":"Manufacturing & Wholesale Goods"
        }
    ],
    "sg:phone":"+61 407 472 775",
    "sg:postcode":"3539",
    "sg:province":"VIC",
    "sg:tags":[
        "earth",
        "excavating",
        "moving",
        "equipment"
    ],
    "wof:name":"Sherlock's Soil Works",
    "wof:placetype":"venue"
},
  "geometry": {"coordinates":[144.284485,-36.751534],"type":"Point"}
}