{
  "type": "Feature",
  "properties": {
    "addr:full":"Shop 7, 107 Alfred St Narraweena NSW 2099",
    "addr:housenumber":"shop 7 107",
    "addr:postcode":"2099",
    "addr:street":"Alfred St",
    "iso:country":"AU",
    "sg:address":"Shop 7, 107 Alfred St",
    "sg:city":"Narraweena",
    "sg:classifiers":[
        {
            "category":"Real Estate",
            "subcategory":"Real Estate Agent",
            "type":"Services"
        }
    ],
    "sg:phone":"+61 2 9972 3600",
    "sg:postcode":"2099",
    "sg:province":"NSW",
    "wof:name":"Nationwide Realty Narraweena",
    "wof:placetype":"venue"
},
  "geometry": {"coordinates":[151.274780273,-33.7501716614],"type":"Point"}
}