{
  "type": "Feature",
  "properties": {
    "iso:country":"AU",
    "sg:address":"449 Draper St",
    "sg:city":"Cairns",
    "sg:classifiers":[
        {
            "category":"Health Services",
            "subcategory":"Health Practitioner",
            "type":"Services"
        }
    ],
    "sg:phone":"+61 7 4031 2100",
    "sg:postcode":"4870",
    "sg:province":"QLD",
    "sg:tags":[
        "alternative"
    ],
    "wof:name":"Annette Donnan Acupuncture & Massage Therapy",
    "wof:placetype":"venue"
},
  "geometry": {"coordinates":[145.760040283,-16.9166374207],"type":"Point"}
}