{
  "type": "Feature",
  "properties": {
    "iso:country":"AU",
    "sg:address":"680 Huon Rd",
    "sg:city":"Fern Tree",
    "sg:classifiers":[
        {
            "category":"Travel",
            "subcategory":"Hotels & Motels",
            "type":"Entertainment"
        }
    ],
    "sg:phone":"+61 3 6239 1171",
    "sg:postcode":"7054",
    "sg:province":"TAS",
    "sg:tags":[
        "accommodation"
    ],
    "wof:name":"Fern Tree Tavern",
    "wof:placetype":"venue"
},
  "geometry": {"coordinates":[147.26010099999999,-42.922398],"type":"Point"}
}