{
  "type": "Feature",
  "properties": {
    "addr:full":"Springwood Plaza Chambers 15 Dennis Road Springwood QLD 4127",
    "addr:housenumber":"15",
    "addr:postcode":"4127",
    "addr:street":"Dennis Road",
    "iso:country":"AU",
    "sg:address":"Springwood Plaza Chambers 15 Dennis Road",
    "sg:city":"Springwood",
    "sg:classifiers":[
        {
            "category":"Education",
            "subcategory":"Music School",
            "type":"Public Place"
        }
    ],
    "sg:phone":"+61 7 3808 7282",
    "sg:postcode":"4127",
    "sg:province":"QLD",
    "sg:tags":[
        "teacher"
    ],
    "wof:name":"Forte School Of Music",
    "wof:placetype":"venue"
},
  "geometry": {"coordinates":[153.129074097,-27.620721817],"type":"Point"}
}