{
  "type": "Feature",
  "properties": {
    "addr:full":"462 Forrest Rd Brookdale WA 6112",
    "addr:housenumber":"462",
    "addr:postcode":"6112",
    "addr:street":"Forrest Rd",
    "iso:country":"AU",
    "sg:address":"462 Forrest Rd",
    "sg:city":"Brookdale",
    "sg:classifiers":[
        {
            "category":"Communications",
            "subcategory":"News Services",
            "type":"Services"
        }
    ],
    "sg:phone":"+61 8 9498 2009",
    "sg:postcode":"6112",
    "sg:province":"WA",
    "sg:tags":[
        "information",
        "tourist",
        "attractions"
    ],
    "wof:name":"Oz Tour Coachlines",
    "wof:placetype":"venue"
},
  "geometry": {"coordinates":[115.973121643,-32.1649703979],"type":"Point"}
}