{
  "type": "Feature",
  "properties": {
    "addr:full":"967 Pittwater Rd Collaroy NSW 2097",
    "addr:housenumber":"967",
    "addr:postcode":"2097",
    "addr:street":"Pittwater Rd",
    "iso:country":"AU",
    "sg:address":"967 Pittwater Rd",
    "sg:city":"Collaroy",
    "sg:classifiers":[
        {
            "category":"Professional",
            "subcategory":"Management & Consulting",
            "type":"Services"
        }
    ],
    "sg:phone":"+61 412 327 277",
    "sg:postcode":"2097",
    "sg:province":"NSW",
    "sg:tags":[
        "consultant"
    ],
    "wof:name":"Sedane Pty Ltd",
    "wof:placetype":"venue"
},
  "geometry": {"coordinates":[151.30137634299999,-33.7318534851],"type":"Point"}
}