{
  "type": "Feature",
  "properties": {
    "addr:full":"Shop 24 The Bentley Centre Albany Hwy Bentley WA 6102",
    "addr:housenumber":"shop 24",
    "addr:postcode":"6102",
    "addr:street":"The;Albany Hwy",
    "iso:country":"AU",
    "sg:address":"Shop 24 The Bentley Centre Albany Hwy",
    "sg:city":"Bentley",
    "sg:classifiers":[
        {
            "category":"Shopping",
            "subcategory":"Clothing, Apparel, & Fashions",
            "type":"Retail Goods"
        }
    ],
    "sg:phone":"+61 8 9358 0366",
    "sg:postcode":"6102",
    "sg:province":"WA",
    "sg:tags":[
        "lady",
        "wear"
    ],
    "wof:name":"Miller's Fashion Club",
    "wof:placetype":"venue"
},
  "geometry": {"coordinates":[115.919067383,-32.0019493103],"type":"Point"}
}