{
  "type": "Feature",
  "properties": {
    "addr:full":"Level 2/ 754 George St Haymarket NSW 2000",
    "addr:housenumber":"/ 754",
    "addr:postcode":"2000",
    "addr:street":"George St",
    "iso:country":"AU",
    "sg:address":"Level 2/ 754 George St",
    "sg:city":"Haymarket",
    "sg:classifiers":[
        {
            "category":"Personal",
            "subcategory":"Massage",
            "type":"Services"
        }
    ],
    "sg:phone":"+61 2 9281 1868",
    "sg:postcode":"2000",
    "sg:province":"NSW",
    "sg:tags":[
        "therapy"
    ],
    "wof:name":"Golden Touch",
    "wof:placetype":"venue"
},
  "geometry": {"coordinates":[151.205368042,-33.8800621033],"type":"Point"}
}