{
  "type": "Feature",
  "properties": {
    "iso:country":"AU",
    "sg:address":"5 Stewart Ave",
    "sg:city":"Glenelg North",
    "sg:classifiers":[
        {
            "category":"Health Services",
            "subcategory":"Dentist",
            "type":"Services"
        }
    ],
    "sg:phone":"+61 8 8295 7735",
    "sg:postcode":"5045",
    "sg:province":"SA",
    "sg:tags":[
        "dental",
        "prosthetist"
    ],
    "wof:name":"Herriman J M",
    "wof:placetype":"venue"
},
  "geometry": {"coordinates":[138.526093,-34.972908],"type":"Point"}
}