{
  "type": "Feature",
  "properties": {
    "addr:full":"19 Oliver St Harbord NSW 2096",
    "addr:housenumber":"19",
    "addr:postcode":"2096",
    "addr:street":"Oliver St",
    "iso:country":"AU",
    "sg:address":"19 Oliver St",
    "sg:city":"Harbord",
    "sg:classifiers":[
        {
            "category":"Autos & Motor Vehicles",
            "subcategory":"Automobile Sales",
            "type":"Retail Goods"
        }
    ],
    "sg:phone":"+61 2 9938 4900",
    "sg:postcode":"2096",
    "sg:province":"NSW",
    "sg:tags":[
        "car",
        "used"
    ],
    "wof:name":"Pittwater Auto Sales",
    "wof:placetype":"venue"
},
  "geometry": {"coordinates":[151.283737183,-33.7781486511],"type":"Point"}
}