{
  "type": "Feature",
  "properties": {
    "addr:full":"81 Myall St Merrylands NSW 2160",
    "addr:housenumber":"81",
    "addr:postcode":"2160",
    "addr:street":"Myall St",
    "iso:country":"AU",
    "sg:address":"81 Myall St",
    "sg:city":"Merrylands",
    "sg:classifiers":[
        {
            "category":"Real Estate",
            "subcategory":"Real Estate Operator",
            "type":"Services"
        }
    ],
    "sg:phone":"+61 418 468 237",
    "sg:postcode":"2160",
    "sg:province":"NSW",
    "sg:tags":[
        "concrete",
        "pumping"
    ],
    "wof:name":"Autocrete Concrete Pumping",
    "wof:placetype":"venue"
},
  "geometry": {"coordinates":[150.984375,-33.8433036804],"type":"Point"}
}