{
  "type": "Feature",
  "properties": {
    "addr:full":"108 Rozelle Ave Melrose Park SA 5039",
    "addr:housenumber":"108",
    "addr:postcode":"5039",
    "addr:street":"Rozelle Ave",
    "iso:country":"AU",
    "sg:address":"108 Rozelle Ave",
    "sg:city":"Melrose Park",
    "sg:classifiers":[
        {
            "category":"Building & Trades",
            "subcategory":"Plumbing",
            "type":"Services"
        }
    ],
    "sg:phone":"+61 412 858 286",
    "sg:postcode":"5039",
    "sg:province":"SA",
    "sg:tags":[
        "plumber",
        "gasfitters"
    ],
    "wof:name":"Elite Plumbing Maintenance Pty Ltd",
    "wof:placetype":"venue"
},
  "geometry": {"coordinates":[138.57606506400001,-34.9838981628],"type":"Point"}
}