{
  "type": "Feature",
  "properties": {
    "iso:country":"AU",
    "sg:address":"PO Box 653",
    "sg:city":"Wonthaggi",
    "sg:classifiers":[
        {
            "category":"Retail",
            "subcategory":"Driving School",
            "type":"Services"
        }
    ],
    "sg:phone":"+61 3 5672 5646",
    "sg:postcode":"3995",
    "sg:province":"VIC",
    "wof:name":"Bass Coast Driving School",
    "wof:placetype":"venue"
},
  "geometry": {"coordinates":[145.59446700000001,-38.605721],"type":"Point"}
}