{
  "type": "Feature",
  "properties": {
    "addr:full":"Cnr 51 Hallam South Rd & Star Cres Hallam VIC 3803",
    "addr:housenumber":"51",
    "addr:postcode":"3803",
    "addr:street":"Cnr;South Rd & Star Cres",
    "iso:country":"AU",
    "sg:address":"Cnr 51 Hallam South Rd & Star Cres",
    "sg:city":"Hallam",
    "sg:classifiers":[
        {
            "category":"Shopping",
            "subcategory":"Party Supplies",
            "type":"Retail Goods"
        }
    ],
    "sg:phone":"+61 3 9796 5588",
    "sg:postcode":"3803",
    "sg:province":"VIC",
    "sg:tags":[
        "children's"
    ],
    "wof:name":"Koolkids (Aust) Indoor Playground & Cafe",
    "wof:placetype":"venue"
},
  "geometry": {"coordinates":[145.271606445,-38.0135612488],"type":"Point"}
}