{
  "type": "Feature",
  "properties": {
    "addr:full":"12 Power Rd Southside Gympie QLD 4570",
    "addr:housenumber":"12",
    "addr:postcode":"4570",
    "addr:street":"Power Rd",
    "iso:country":"AU",
    "sg:address":"12 Power Rd",
    "sg:city":"Southside Gympie",
    "sg:classifiers":[
        {
            "category":"Building & Trades",
            "subcategory":"Plumbing",
            "type":"Services"
        }
    ],
    "sg:phone":"+61 418 738 744",
    "sg:postcode":"4570",
    "sg:province":"QLD",
    "sg:tags":[
        "plumber",
        "gasfitters"
    ],
    "wof:name":"Bothams Tim TJB Plumbing Service Pty Ltd",
    "wof:placetype":"venue"
},
  "geometry": {"coordinates":[152.65965270999999,-26.2032985687],"type":"Point"}
}