{
  "type": "Feature",
  "properties": {
    "addr:full":"Unit 1, 196 Campbell St Belmont WA 6104",
    "addr:housenumber":"196",
    "addr:postcode":"6104",
    "addr:street":"Campbell St",
    "iso:country":"AU",
    "sg:address":"Unit 1, 196 Campbell St",
    "sg:city":"Belmont",
    "sg:classifiers":[
        {
            "category":"Utilities",
            "subcategory":"Electric",
            "type":"Services"
        }
    ],
    "sg:phone":"+61 8 9477 4063",
    "sg:postcode":"6104",
    "sg:province":"WA",
    "sg:tags":[
        "electrical",
        "contractor"
    ],
    "wof:name":"Aurora Electrical Services",
    "wof:placetype":"venue"
},
  "geometry": {"coordinates":[115.925888062,-31.9556121826],"type":"Point"}
}