{
  "type": "Feature",
  "properties": {
    "addr:full":"2nd Floor, Gilhooley&#039;s Bldg 124 Albert St Brisbane QLD 4000",
    "addr:housenumber":"124",
    "addr:postcode":"4000",
    "addr:street":"S;Albert St",
    "iso:country":"AU",
    "sg:address":"2nd Floor, Gilhooley&#039;s Bldg 124 Albert St",
    "sg:city":"Brisbane",
    "sg:classifiers":[
        {
            "category":"Personal",
            "subcategory":"Massage",
            "type":"Services"
        }
    ],
    "sg:phone":"+61 7 3221 6373",
    "sg:postcode":"4000",
    "sg:province":"QLD",
    "sg:tags":[
        "therapy"
    ],
    "wof:name":"Brisbane Body Therapy",
    "wof:placetype":"venue"
},
  "geometry": {"coordinates":[153.02711486800001,-27.4717235565],"type":"Point"}
}