{
  "type": "Feature",
  "properties": {
    "iso:country":"AU",
    "sg:address":"89 Mandurah Tce",
    "sg:city":"Mandurah",
    "sg:classifiers":[
        {
            "category":"Real Estate",
            "subcategory":"Real Estate Agent",
            "type":"Services"
        }
    ],
    "sg:phone":"+61 8 9535 7277",
    "sg:postcode":"6210",
    "sg:province":"WA",
    "sg:website":"http://www.mandurahestateagency.com.au",
    "wof:name":"Mandurah Estate Agency",
    "wof:placetype":"venue"
},
  "geometry": {"coordinates":[115.721977,-32.526653],"type":"Point"}
}