{
  "type": "Feature",
  "properties": {
    "addr:full":"The Hermitage, 340 Old Northern Rd Castle Hill NSW 2154",
    "addr:housenumber":"340",
    "addr:postcode":"2154",
    "addr:street":"Old Northern Rd",
    "iso:country":"AU",
    "sg:address":"The Hermitage, 340 Old Northern Rd",
    "sg:city":"Castle Hill",
    "sg:classifiers":[
        {
            "category":"Retail",
            "subcategory":"Funeral Services",
            "type":"Services"
        }
    ],
    "sg:phone":"+61 2 9659 0900",
    "sg:postcode":"2154",
    "sg:province":"NSW",
    "sg:tags":[
        "director"
    ],
    "wof:name":"Hills Family Funerals",
    "wof:placetype":"venue"
},
  "geometry": {"coordinates":[151.01614379899999,-33.7312507629],"type":"Point"}
}