{
  "type": "Feature",
  "properties": {
    "iso:country":"AU",
    "sg:address":"88 Ricketts Rd",
    "sg:city":"Mt Waverley",
    "sg:classifiers":[
        {
            "category":"Real Estate",
            "subcategory":"Real Estate Services",
            "type":"Services"
        }
    ],
    "sg:phone":"+61 3 9535 8599",
    "sg:postcode":"3149",
    "sg:province":"VIC",
    "sg:tags":[
        "consultant",
        "property"
    ],
    "wof:name":"Ford Investment Group",
    "wof:placetype":"venue"
},
  "geometry": {"coordinates":[145.130783081,-37.8948364258],"type":"Point"}
}