{
  "type": "Feature",
  "properties": {
    "addr:full":"1 Fisher St Tusmore SA 5065",
    "addr:housenumber":"1",
    "addr:postcode":"5065",
    "addr:street":"Fisher St",
    "iso:country":"AU",
    "sg:address":"1 Fisher St",
    "sg:city":"Tusmore",
    "sg:classifiers":[
        {
            "category":"Government",
            "subcategory":"City Hall",
            "type":"Public Place"
        }
    ],
    "sg:phone":"+61 8 8361 2296",
    "sg:postcode":"5065",
    "sg:province":"SA",
    "wof:name":"United Eastern Masonic Association Incorporated",
    "wof:placetype":"venue"
},
  "geometry": {"coordinates":[138.64300537099999,-34.9375915527],"type":"Point"}
}