{
  "type": "Feature",
  "properties": {
    "iso:country":"AU",
    "sg:address":"32 Teton Crt",
    "sg:city":"Highett",
    "sg:classifiers":[
        {
            "category":"Manufacturing",
            "subcategory":"Motor Vehicles & Parts",
            "type":"Manufacturing & Wholesale Goods"
        }
    ],
    "sg:phone":"+61 3 9555 9333",
    "sg:postcode":"3190",
    "sg:province":"VIC",
    "sg:tags":[
        "replacement"
    ],
    "wof:name":"Sbaru Parts",
    "wof:placetype":"venue"
},
  "geometry": {"coordinates":[145.053833008,-37.9469223022],"type":"Point"}
}