{
  "type": "Feature",
  "properties": {
    "addr:full":"49 Georges River Rd Croydon Park NSW 2133",
    "addr:housenumber":"49",
    "addr:postcode":"2133",
    "addr:street":"Georges River Rd",
    "iso:country":"AU",
    "sg:address":"49 Georges River Rd",
    "sg:city":"Croydon Park",
    "sg:classifiers":[
        {
            "category":"Health Services",
            "subcategory":"Dentist",
            "type":"Services"
        }
    ],
    "sg:phone":"+61 2 9798 8483",
    "sg:postcode":"2133",
    "sg:province":"NSW",
    "wof:name":"Croydon Park Dental Centre",
    "wof:placetype":"venue"
},
  "geometry": {"coordinates":[151.10931396500001,-33.8952522278],"type":"Point"}
}