{
  "type": "Feature",
  "properties": {
    "addr:full":"Unit 3/ 123 Link Rd Victoria Point QLD 4165",
    "addr:housenumber":"/ 123",
    "addr:postcode":"4165",
    "addr:street":"Link Rd",
    "iso:country":"AU",
    "sg:address":"Unit 3/ 123 Link Rd",
    "sg:city":"Victoria Point",
    "sg:classifiers":[
        {
            "category":"Real Estate",
            "subcategory":"Surveying",
            "type":"Services"
        }
    ],
    "sg:phone":"+61 1300 362 094",
    "sg:postcode":"4165",
    "sg:province":"QLD",
    "sg:tags":[
        "surveyor",
        "land"
    ],
    "wof:name":"Statewide Survey Group Pty Ltd",
    "wof:placetype":"venue"
},
  "geometry": {"coordinates":[153.294723511,-27.5859031677],"type":"Point"}
}