{
  "type": "Feature",
  "properties": {
    "iso:country":"AU",
    "sg:address":"25 Manning St",
    "sg:city":"Tuncurry",
    "sg:classifiers":[
        {
            "category":"Professional",
            "subcategory":"Computer Services",
            "type":"Services"
        }
    ],
    "sg:phone":"+61 2 6555 7959",
    "sg:postcode":"2428",
    "sg:province":"NSW",
    "sg:tags":[
        "repairs",
        "upgrade",
        "equipment"
    ],
    "wof:name":"The Copy Place",
    "wof:placetype":"venue"
},
  "geometry": {"coordinates":[152.498962,-32.173714],"type":"Point"}
}