{
  "type": "Feature",
  "properties": {
    "iso:country":"AU",
    "sg:address":"PO Box 439",
    "sg:city":"Northbridge Pte Boxes",
    "sg:classifiers":[
        {
            "category":"Education",
            "subcategory":"Special Training",
            "type":"Public Place"
        }
    ],
    "sg:phone":"+61 8 9227 6066",
    "sg:postcode":"6865",
    "sg:province":"WA",
    "sg:tags":[
        "instruction",
        "display",
        "parachuting"
    ],
    "wof:name":"Perth Tandem Centre",
    "wof:placetype":"venue"
},
  "geometry": {"coordinates":[115.857391357,-31.946969986],"type":"Point"}
}