{
  "type": "Feature",
  "properties": {
    "iso:country":"AU",
    "sg:address":"381 Anzac Ave",
    "sg:city":"Kippa-Ring",
    "sg:classifiers":[
        {
            "category":"Shopping",
            "subcategory":"Pets & Pet Supplies",
            "type":"Retail Goods"
        }
    ],
    "sg:phone":"+61 7 3284 2421",
    "sg:postcode":"4021",
    "sg:province":"QLD",
    "sg:tags":[
        "food"
    ],
    "wof:name":"K.R. Petcare Pty Ltd",
    "wof:placetype":"venue"
},
  "geometry": {"coordinates":[153.077835,-27.219578],"type":"Point"}
}