{
  "type": "Feature",
  "properties": {
    "iso:country":"AU",
    "sg:address":"2 Innovation Parkway (Cnr Kawana Way)",
    "sg:city":"Warana",
    "sg:classifiers":[
        {
            "category":"Structure",
            "subcategory":"Office Building",
            "type":"Public Place"
        }
    ],
    "sg:phone":"+61 7 5413 9200",
    "sg:postcode":"4575",
    "sg:province":"QLD",
    "sg:tags":[
        "serviced"
    ],
    "sg:website":"http://www.regatta1.com.au",
    "wof:name":"Regatta 1 Business Centre",
    "wof:placetype":"venue"
},
  "geometry": {"coordinates":[153.12170399999999,-26.731689],"type":"Point"}
}