{
  "type": "Feature",
  "properties": {
    "addr:full":"Fcty 7/ 7 Commerical Crt Tullamarine VIC 3043",
    "addr:housenumber":"/ 7",
    "addr:postcode":"3043",
    "addr:street":"Commerical Crt",
    "iso:country":"AU",
    "sg:address":"Fcty 7/ 7 Commerical Crt",
    "sg:city":"Tullamarine",
    "sg:classifiers":[
        {
            "category":"Building & Trades",
            "subcategory":"Construction",
            "type":"Services"
        }
    ],
    "sg:phone":"+61 3 9335 2223",
    "sg:postcode":"3043",
    "sg:province":"VIC",
    "sg:tags":[
        "home",
        "air conditioning"
    ],
    "wof:name":"CPM Mist",
    "wof:placetype":"venue"
},
  "geometry": {"coordinates":[144.857254028,-37.7083625793],"type":"Point"}
}