{
  "type": "Feature",
  "properties": {
    "iso:country":"AU",
    "sg:address":"30 Bell St",
    "sg:city":"Ormiston",
    "sg:classifiers":[
        {
            "category":"Retail",
            "subcategory":"Auto Repair",
            "type":"Services"
        }
    ],
    "sg:phone":"+61 412 074 456",
    "sg:postcode":"4160",
    "sg:province":"QLD",
    "sg:tags":[
        "repairer",
        "motor",
        "engineer"
    ],
    "wof:name":"Mobi-Lube",
    "wof:placetype":"venue"
},
  "geometry": {"coordinates":[153.249343872,-27.5209655762],"type":"Point"}
}