{
  "type": "Feature",
  "properties": {
    "iso:country":"AU",
    "sg:address":"504 South Arm Rd",
    "sg:city":"Bowraville",
    "sg:classifiers":[
        {
            "category":"Farming",
            "subcategory":"Poultry Farm",
            "type":"Manufacturing & Wholesale Goods"
        }
    ],
    "sg:phone":"+61 2 6564 8480",
    "sg:postcode":"2449",
    "sg:province":"NSW",
    "sg:tags":[
        "farmer"
    ],
    "wof:name":"Dave's Farmyard Poultry",
    "wof:placetype":"venue"
},
  "geometry": {"coordinates":[152.805634,-30.659897],"type":"Point"}
}