{
  "type": "Feature",
  "properties": {
    "addr:full":"14 Campbell Rd Albany WA 6330",
    "addr:housenumber":"14",
    "addr:postcode":"6330",
    "addr:street":"Campbell Rd",
    "iso:country":"AU",
    "sg:address":"14 Campbell Rd",
    "sg:city":"Albany",
    "sg:classifiers":[
        {
            "category":"Health Services",
            "subcategory":"Dentist",
            "type":"Services"
        }
    ],
    "sg:phone":"+61 8 9842 5595",
    "sg:postcode":"6330",
    "sg:province":"WA",
    "sg:tags":[
        "dental",
        "prosthetist"
    ],
    "wof:name":"Star Denture Clinic",
    "wof:placetype":"venue"
},
  "geometry": {"coordinates":[117.893508911,-35.0162506104],"type":"Point"}
}