{
  "type": "Feature",
  "properties": {
    "addr:full":"PO Box 5122 Wodonga VIC 3690",
    "addr:postcode":"3690",
    "iso:country":"AU",
    "sg:address":"PO Box 5122",
    "sg:city":"Wodonga",
    "sg:classifiers":[
        {
            "category":"Insurance",
            "subcategory":"Insurance Agent",
            "type":"Services"
        }
    ],
    "sg:phone":"+61 418 690 877",
    "sg:postcode":"3690",
    "sg:province":"VIC",
    "wof:name":"Pastel Pty Ltd (Paul Venables)",
    "wof:placetype":"venue"
},
  "geometry": {"coordinates":[146.84840393100001,-36.1168785095],"type":"Point"}
}