{
  "type": "Feature",
  "properties": {
    "iso:country":"AU",
    "sg:address":"57 Sellwood St",
    "sg:city":"Brighton-le-Sands",
    "sg:classifiers":[
        {
            "category":"Building & Trades",
            "subcategory":"Construction",
            "type":"Services"
        }
    ],
    "sg:phone":"+61 439 985 843",
    "sg:postcode":"2216",
    "sg:province":"NSW",
    "sg:tags":[
        "contractor"
    ],
    "wof:name":"AAA Building, Carpentary & Maintenance",
    "wof:placetype":"venue"
},
  "geometry": {"coordinates":[151.152954,-33.955154],"type":"Point"}
}