{
  "type": "Feature",
  "properties": {
    "addr:full":"10 Kyamba Crt Bayswater North VIC 3153",
    "addr:housenumber":"10",
    "addr:postcode":"3153",
    "addr:street":"Kyamba Crt",
    "iso:country":"AU",
    "sg:address":"10 Kyamba Crt",
    "sg:city":"Bayswater North",
    "sg:classifiers":[
        {
            "category":"Organizations",
            "subcategory":"Community Association",
            "type":"Services"
        }
    ],
    "sg:phone":"+61 3 9725 6015",
    "sg:postcode":"3153",
    "sg:province":"VIC",
    "sg:tags":[
        "shiatsu",
        "therapy"
    ],
    "wof:name":"Mary Ingram",
    "wof:placetype":"venue"
},
  "geometry": {"coordinates":[145.27272033700001,-37.8198814392],"type":"Point"}
}