{
  "type": "Feature",
  "properties": {
    "addr:full":"74 Dorset Rd Croydon VIC 3136",
    "addr:housenumber":"74",
    "addr:postcode":"3136",
    "addr:street":"Dorset Rd",
    "iso:country":"AU",
    "sg:address":"74 Dorset Rd",
    "sg:city":"Croydon",
    "sg:classifiers":[
        {
            "category":"Building & Trades",
            "subcategory":"Landscaping Services",
            "type":"Services"
        }
    ],
    "sg:phone":"+61 3 9727 3279",
    "sg:postcode":"3136",
    "sg:province":"VIC",
    "sg:tags":[
        "gardener"
    ],
    "wof:name":"Garden Magic Property Services",
    "wof:placetype":"venue"
},
  "geometry": {"coordinates":[145.29394531200001,-37.7773513794],"type":"Point"}
}