{
  "type": "Feature",
  "properties": {
    "addr:full":"59 Woodigee St Currumbin QLD 4223",
    "addr:housenumber":"59",
    "addr:postcode":"4223",
    "addr:street":"Woodigee St",
    "iso:country":"AU",
    "sg:address":"59 Woodigee St",
    "sg:city":"Currumbin",
    "sg:classifiers":[
        {
            "category":"Home & Garden",
            "subcategory":"Carpets & Floor Coverings",
            "type":"Retail Goods"
        }
    ],
    "sg:phone":"+61 422 060 794",
    "sg:postcode":"4223",
    "sg:province":"QLD",
    "wof:name":"Around Town Flooring",
    "wof:placetype":"venue"
},
  "geometry": {"coordinates":[153.48696899399999,-28.1323833466],"type":"Point"}
}