{
  "type": "Feature",
  "properties": {
    "addr:full":"67 Tucker Rd Bentleigh VIC 3204",
    "addr:housenumber":"67",
    "addr:postcode":"3204",
    "addr:street":"Tucker Rd",
    "iso:country":"AU",
    "sg:address":"67 Tucker Rd",
    "sg:city":"Bentleigh",
    "sg:classifiers":[
        {
            "category":"Building & Trades",
            "subcategory":"Locksmith",
            "type":"Services"
        }
    ],
    "sg:phone":"+61 412 306 039",
    "sg:postcode":"3204",
    "sg:province":"VIC",
    "sg:tags":[
        "lock"
    ],
    "wof:name":"Doctor Lock Locksmiths",
    "wof:placetype":"venue"
},
  "geometry": {"coordinates":[145.04913300000001,-37.928799],"type":"Point"}
}