{
  "type": "Feature",
  "properties": {
    "addr:full":"12 Lawes St Hamilton QLD 4007",
    "addr:housenumber":"12",
    "addr:postcode":"4007",
    "addr:street":"Lawes St",
    "iso:country":"AU",
    "sg:address":"12 Lawes St",
    "sg:city":"Hamilton",
    "sg:classifiers":[
        {
            "category":"Parking",
            "subcategory":"Garage",
            "type":"Transportation"
        }
    ],
    "sg:phone":"+61 7 3268 6801",
    "sg:postcode":"4007",
    "sg:province":"QLD",
    "sg:tags":[
        "radiographer"
    ],
    "wof:name":"Redcliffe Radiology",
    "wof:placetype":"venue"
},
  "geometry": {"coordinates":[153.05886799999999,-27.436113],"type":"Point"}
}