{
  "type": "Feature",
  "properties": {
    "iso:country":"AU",
    "sg:address":"Blackall St",
    "sg:city":"Woombye",
    "sg:classifiers":[
        {
            "category":"Food & Beverages",
            "subcategory":"Bakery",
            "type":"Retail Goods"
        }
    ],
    "sg:phone":"+61 7 5442 1344",
    "sg:postcode":"4559",
    "sg:province":"QLD",
    "sg:tags":[
        "baker"
    ],
    "wof:name":"Woombye Bakery & Cafe",
    "wof:placetype":"venue"
},
  "geometry": {"coordinates":[152.968582153,-26.6607170105],"type":"Point"}
}