{
  "type": "Feature",
  "properties": {
    "iso:country":"AU",
    "sg:address":"38 Marshall Rd",
    "sg:city":"High Wycombe",
    "sg:classifiers":[
        {
            "category":"Recreation",
            "subcategory":"Fishing",
            "type":"Entertainment"
        }
    ],
    "sg:phone":"+61 8 9454 4449",
    "sg:postcode":"6057",
    "sg:province":"WA",
    "sg:tags":[
        "tackle"
    ],
    "wof:name":"Fish Mate",
    "wof:placetype":"venue"
},
  "geometry": {"coordinates":[115.994018555,-31.941400528],"type":"Point"}
}