{
  "type": "Feature",
  "properties": {
    "addr:full":"4 Rankine St Strathalbyn SA 5255",
    "addr:housenumber":"4",
    "addr:postcode":"5255",
    "addr:street":"Rankine St",
    "iso:country":"AU",
    "sg:address":"4 Rankine St",
    "sg:city":"Strathalbyn",
    "sg:classifiers":[
        {
            "category":"Health Services",
            "subcategory":"Health Practitioner",
            "type":"Services"
        }
    ],
    "sg:phone":"+61 8 8536 2933",
    "sg:postcode":"5255",
    "sg:province":"SA",
    "sg:tags":[
        "naturopath"
    ],
    "wof:name":"Sara Rooney BHSc., ND., MATMS",
    "wof:placetype":"venue"
},
  "geometry": {"coordinates":[138.892745972,-35.2599601746],"type":"Point"}
}