{
  "type": "Feature",
  "properties": {
    "addr:full":"19 Dalmahoy St Bairnsdale VIC 3875",
    "addr:housenumber":"19",
    "addr:postcode":"3875",
    "addr:street":"Dalmahoy St",
    "iso:country":"AU",
    "sg:address":"19 Dalmahoy St",
    "sg:city":"Bairnsdale",
    "sg:classifiers":[
        {
            "category":"Manufacturing",
            "subcategory":"Food",
            "type":"Manufacturing & Wholesale Goods"
        }
    ],
    "sg:phone":"+61 3 5150 1132",
    "sg:postcode":"3875",
    "sg:province":"VIC",
    "sg:tags":[
        "function",
        "catering"
    ],
    "wof:name":"Jacqui's Catering at the Heritage",
    "wof:placetype":"venue"
},
  "geometry": {"coordinates":[147.63142395,-37.8286514282],"type":"Point"}
}