{
  "type": "Feature",
  "properties": {
    "addr:full":"Shop 1/ 56 Harley St Strathdale VIC 3550",
    "addr:housenumber":"shop 1 / 56",
    "addr:postcode":"3550",
    "addr:street":"Harley St",
    "iso:country":"AU",
    "sg:address":"Shop 1/ 56 Harley St",
    "sg:city":"Strathdale",
    "sg:classifiers":[
        {
            "category":"Building & Trades",
            "subcategory":"Construction",
            "type":"Services"
        }
    ],
    "sg:phone":"+61 3 5441 6233",
    "sg:postcode":"3550",
    "sg:province":"VIC",
    "sg:tags":[
        "repair",
        "maintenance",
        "contractor"
    ],
    "wof:name":"Arryleen Building Services",
    "wof:placetype":"venue"
},
  "geometry": {"coordinates":[144.31671142600001,-36.7724952698],"type":"Point"}
}