{
  "type": "Feature",
  "properties": {
    "iso:country":"AU",
    "sg:address":"61- 63 Clow St",
    "sg:city":"Dandenong",
    "sg:classifiers":[
        {
            "category":"Building & Trades",
            "subcategory":"Construction",
            "type":"Services"
        }
    ],
    "sg:phone":"+61 3 9792 4200",
    "sg:postcode":"3175",
    "sg:province":"VIC",
    "sg:tags":[
        "pool",
        "swimming"
    ],
    "wof:name":"B. Kilworth",
    "wof:placetype":"venue"
},
  "geometry": {"coordinates":[145.21995544399999,-37.9853439331],"type":"Point"}
}