{
  "type": "Feature",
  "properties": {
    "addr:full":"69 Malcom Rd Braeside VIC 3195",
    "addr:housenumber":"69",
    "addr:postcode":"3195",
    "addr:street":"Malcom Rd",
    "iso:country":"AU",
    "sg:address":"69 Malcom Rd",
    "sg:city":"Braeside",
    "sg:phone":"+61 3 9587 9488",
    "sg:postcode":"3195",
    "sg:province":"VIC",
    "wof:name":"Micro Fresh Filters (Aust) Pty Ltd",
    "wof:placetype":"venue"
},
  "geometry": {"coordinates":[145.110031128,-37.9943771362],"type":"Point"}
}