{
  "type": "Feature",
  "properties": {
    "iso:country":"AU",
    "sg:address":"Nirimba St",
    "sg:city":"Manly West",
    "sg:classifiers":[
        {
            "category":"Professional",
            "subcategory":"Management & Consulting",
            "type":"Services"
        }
    ],
    "sg:phone":"+61 7 3893 2833",
    "sg:postcode":"4179",
    "sg:province":"QLD",
    "sg:tags":[
        "consultant",
        "educational"
    ],
    "wof:name":"Motivational Media Assemblies Australia Ltd",
    "wof:placetype":"venue"
},
  "geometry": {"coordinates":[153.16586303700001,-27.4639892578],"type":"Point"}
}