{
  "type": "Feature",
  "properties": {
    "iso:country":"AU",
    "sg:address":"1947 Malvern Rd",
    "sg:city":"Malvern East",
    "sg:classifiers":[
        {
            "category":"Building & Trades",
            "subcategory":"Construction",
            "type":"Services"
        }
    ],
    "sg:phone":"+61 3 9885 3599",
    "sg:postcode":"3145",
    "sg:province":"VIC",
    "sg:tags":[
        "earth",
        "excavating",
        "moving",
        "contractor"
    ],
    "wof:name":"Foster Bros",
    "wof:placetype":"venue"
},
  "geometry": {"coordinates":[145.06134033199999,-37.8698883057],"type":"Point"}
}