{
  "type": "Feature",
  "properties": {
    "addr:full":"10 McFall St Botany NSW 2019",
    "addr:housenumber":"10",
    "addr:postcode":"2019",
    "addr:street":"Mcfall St",
    "iso:country":"AU",
    "sg:address":"10 McFall St",
    "sg:city":"Botany",
    "sg:classifiers":[
        {
            "category":"Structure",
            "subcategory":"Building",
            "type":"Public Place"
        }
    ],
    "sg:phone":"+61 2 9666 7844",
    "sg:postcode":"2019",
    "sg:province":"NSW",
    "sg:tags":[
        "sail",
        "shade"
    ],
    "wof:name":"Leisure Structures Pty Ltd",
    "wof:placetype":"venue"
},
  "geometry": {"coordinates":[151.19145202600001,-33.9454154968],"type":"Point"}
}