{
  "type": "Feature",
  "properties": {
    "addr:full":"113 Union St South Lismore NSW 2480",
    "addr:housenumber":"113",
    "addr:postcode":"2480",
    "addr:street":"Union St South",
    "iso:country":"AU",
    "sg:address":"113 Union St",
    "sg:city":"South Lismore",
    "sg:classifiers":[
        {
            "category":"Autos & Motor Vehicles",
            "subcategory":"Fuel & Gas Station",
            "type":"Retail Goods"
        }
    ],
    "sg:phone":"+61 2 6622 4227",
    "sg:postcode":"2480",
    "sg:province":"NSW",
    "wof:name":"Liberty",
    "wof:placetype":"venue"
},
  "geometry": {"coordinates":[153.26763915999999,-28.8111438751],"type":"Point"}
}