{
  "type": "Feature",
  "properties": {
    "addr:full":"85 Grose St Parramatta NSW 2150",
    "addr:housenumber":"85",
    "addr:postcode":"2150",
    "addr:street":"Grose St",
    "iso:country":"AU",
    "sg:address":"85 Grose St",
    "sg:city":"Parramatta",
    "sg:classifiers":[
        {
            "category":"Professional",
            "type":"Services"
        }
    ],
    "sg:phone":"+61 2 9890 2777",
    "sg:postcode":"2150",
    "sg:province":"NSW",
    "sg:tags":[
        "mail",
        "contractor"
    ],
    "sg:website":"http://www.apmail.com.au",
    "wof:name":"A P Mail Management",
    "wof:placetype":"venue"
},
  "geometry": {"coordinates":[151.01316833499999,-33.8077468872],"type":"Point"}
}