{
  "type": "Feature",
  "properties": {
    "addr:full":"Easter Ave Bilinga QLD 4225",
    "addr:postcode":"4225",
    "addr:street":"Easter Ave",
    "iso:country":"AU",
    "sg:address":"Easter Ave",
    "sg:city":"Bilinga",
    "sg:classifiers":[
        {
            "category":"Travel",
            "subcategory":"Hotels & Motels",
            "type":"Entertainment"
        }
    ],
    "sg:phone":"+61 7 5536 8650",
    "sg:postcode":"4225",
    "sg:province":"QLD",
    "sg:tags":[
        "pub"
    ],
    "wof:name":"Fish Liquor",
    "wof:placetype":"venue"
},
  "geometry": {"coordinates":[153.51159668,-28.1624946594],"type":"Point"}
}