{
  "type": "Feature",
  "properties": {
    "addr:full":"17 Abbotsleigh St Thornlands QLD 4164",
    "addr:housenumber":"17",
    "addr:postcode":"4164",
    "addr:street":"Abbotsleigh St",
    "iso:country":"AU",
    "sg:address":"17 Abbotsleigh St",
    "sg:city":"Thornlands",
    "sg:classifiers":[
        {
            "category":"Professional",
            "subcategory":"Business Services",
            "type":"Services"
        }
    ],
    "sg:phone":"+61 7 3286 3873",
    "sg:postcode":"4164",
    "sg:province":"QLD",
    "sg:tags":[
        "drafting"
    ],
    "wof:name":"Magnic Drafting Service",
    "wof:placetype":"venue"
},
  "geometry": {"coordinates":[153.260665894,-27.5525569916],"type":"Point"}
}