{
  "type": "Feature",
  "properties": {
    "iso:country":"AU",
    "sg:address":"7 Oxford St",
    "sg:city":"Forbes",
    "sg:classifiers":[
        {
            "category":"Retail",
            "subcategory":"Auto Rental",
            "type":"Services"
        }
    ],
    "sg:phone":"+61 2 6852 2244",
    "sg:postcode":"2871",
    "sg:province":"NSW",
    "sg:tags":[
        "car",
        "hire",
        "minibus"
    ],
    "wof:name":"Thrifty",
    "wof:placetype":"venue"
},
  "geometry": {"coordinates":[148.011536,-33.38052],"type":"Point"}
}