{
  "type": "Feature",
  "properties": {
    "iso:country":"AU",
    "sg:address":"436 Henley Beach Rd",
    "sg:city":"Lockleys",
    "sg:classifiers":[
        {
            "category":"Personal",
            "type":"Services"
        }
    ],
    "sg:phone":"+61 8 8443 7998",
    "sg:postcode":"5032",
    "sg:province":"SA",
    "sg:tags":[
        "gift"
    ],
    "wof:name":"Georgies Gift Baskets & Flowers",
    "wof:placetype":"venue"
},
  "geometry": {"coordinates":[138.52934265100001,-34.9258728027],"type":"Point"}
}