{
  "type": "Feature",
  "properties": {
    "addr:full":"239 McIntosh Creek Rd Gympie QLD 4570",
    "addr:housenumber":"239",
    "addr:postcode":"4570",
    "addr:street":"Mcintosh Creek Rd",
    "iso:country":"AU",
    "sg:address":"239 McIntosh Creek Rd",
    "sg:city":"Gympie",
    "sg:classifiers":[
        {
            "category":"Military Area",
            "subcategory":"Army Base",
            "type":"Public Place"
        }
    ],
    "sg:phone":"+61 7 5482 6470",
    "sg:postcode":"4570",
    "sg:province":"QLD",
    "sg:tags":[
        "concrete",
        "slab",
        "floor"
    ],
    "wof:name":"Rob Schluter",
    "wof:placetype":"venue"
},
  "geometry": {"coordinates":[152.66517639200001,-26.2344799042],"type":"Point"}
}