{
  "type": "Feature",
  "properties": {
    "iso:country":"AU",
    "sg:address":"33 Peel St",
    "sg:city":"South Ballarat",
    "sg:classifiers":[
        {
            "category":"Professional",
            "subcategory":"Employment Agencies",
            "type":"Services"
        }
    ],
    "sg:phone":"+61 1300 137 425",
    "sg:postcode":"3350",
    "sg:province":"VIC",
    "sg:tags":[
        "provider",
        "internet"
    ],
    "wof:name":"Chariot",
    "wof:placetype":"venue"
},
  "geometry": {"coordinates":[143.863693,-37.564285],"type":"Point"}
}