{
  "type": "Feature",
  "properties": {
    "iso:country":"AU",
    "sg:address":"2 Havelock St",
    "sg:city":"West Perth",
    "sg:classifiers":[
        {
            "category":"Cafe",
            "type":"Food & Drink"
        }
    ],
    "sg:phone":"+61 8 9321 3865",
    "sg:postcode":"6005",
    "sg:province":"WA",
    "wof:name":"Cafe Dumas",
    "wof:placetype":"venue"
},
  "geometry": {"coordinates":[115.84291076700001,-31.9529209137],"type":"Point"}
}