{
  "type": "Feature",
  "properties": {
    "addr:full":"Unit 1, 20 Henderson Rd Knoxfield VIC 3180",
    "addr:housenumber":"20",
    "addr:postcode":"3180",
    "addr:street":"Henderson Rd",
    "iso:country":"AU",
    "sg:address":"Unit 1, 20 Henderson Rd",
    "sg:city":"Knoxfield",
    "sg:classifiers":[
        {
            "category":"Wholesale",
            "subcategory":"Construction Materials",
            "type":"Manufacturing & Wholesale Goods"
        }
    ],
    "sg:phone":"+61 1300 302 852",
    "sg:postcode":"3180",
    "sg:province":"VIC",
    "sg:tags":[
        "wholesaler",
        "lighting",
        "mfrs",
        "accessory"
    ],
    "wof:name":"Specialised Lamp Supplies",
    "wof:placetype":"venue"
},
  "geometry": {"coordinates":[145.24809265100001,-37.9012908936],"type":"Point"}
}