{
  "type": "Feature",
  "properties": {
    "addr:full":"8a Henty St Reservoir VIC 3073",
    "addr:housenumber":"8a",
    "addr:postcode":"3073",
    "addr:street":"Henty St",
    "iso:country":"AU",
    "sg:address":"8a Henty St",
    "sg:city":"Reservoir",
    "sg:classifiers":[
        {
            "category":"Wholesale",
            "subcategory":"Machinery & Supplies",
            "type":"Manufacturing & Wholesale Goods"
        }
    ],
    "sg:phone":"+61 412 054 989",
    "sg:postcode":"3073",
    "sg:province":"VIC",
    "sg:tags":[
        "equipment",
        "hydraulic"
    ],
    "wof:name":"Hydraulics Network",
    "wof:placetype":"venue"
},
  "geometry": {"coordinates":[145.00050354000001,-37.7189712524],"type":"Point"}
}