{
  "type": "Feature",
  "properties": {
    "iso:country":"AU",
    "sg:address":"5 Rada Rd",
    "sg:city":"Kettering",
    "sg:classifiers":[
        {
            "category":"Train Station",
            "subcategory":"Rail",
            "type":"Transportation"
        }
    ],
    "sg:phone":"+61 3 6267 4980",
    "sg:postcode":"7155",
    "sg:province":"TAS",
    "sg:tags":[
        "marine",
        "engineer"
    ],
    "wof:name":"D-Entrecasteaux Marine Electrics",
    "wof:placetype":"venue"
},
  "geometry": {"coordinates":[147.245040894,-43.1278152466],"type":"Point"}
}