{
  "type": "Feature",
  "properties": {
    "addr:full":"PO Box 170 Wavell Heights North QLD 4012",
    "addr:postcode":"4012",
    "iso:country":"AU",
    "sg:address":"PO Box 170",
    "sg:city":"Wavell Heights North",
    "sg:classifiers":[
        {
            "category":"Shopping",
            "subcategory":"Antiques",
            "type":"Retail Goods"
        }
    ],
    "sg:phone":"+61 409 342 489",
    "sg:postcode":"4012",
    "sg:province":"QLD",
    "wof:name":"Kleptomania:Modern Age Icons",
    "wof:placetype":"venue"
},
  "geometry": {"coordinates":[153.04986572300001,-27.389749527],"type":"Point"}
}