{
  "type": "Feature",
  "properties": {
    "iso:country":"AU",
    "sg:address":"116 Beach Rd",
    "sg:city":"Batemans Bay",
    "sg:classifiers":[
        {
            "category":"Education",
            "subcategory":"Special Training",
            "type":"Public Place"
        }
    ],
    "sg:phone":"+61 2 4472 8028",
    "sg:postcode":"2536",
    "sg:province":"NSW",
    "sg:tags":[
        "tuition-educational"
    ],
    "wof:name":"In2ition",
    "wof:placetype":"venue"
},
  "geometry": {"coordinates":[150.18948364299999,-35.716583252],"type":"Point"}
}