{
  "type": "Feature",
  "properties": {
    "iso:country":"AU",
    "sg:address":"Shop 4, 509- 511 South Rd",
    "sg:city":"Ashford",
    "sg:classifiers":[
        {
            "category":"Professional",
            "subcategory":"Computer Services",
            "type":"Services"
        }
    ],
    "sg:phone":"+61 8 8351 1600",
    "sg:postcode":"5035",
    "sg:province":"SA",
    "sg:tags":[
        "package",
        "software"
    ],
    "wof:name":"RD Computer Services Pty Ltd",
    "wof:placetype":"venue"
},
  "geometry": {"coordinates":[138.571731567,-34.947353363],"type":"Point"}
}