{
  "type": "Feature",
  "properties": {
    "addr:full":"9/ 22 Loganlea Rd Waterford QLD 4133",
    "addr:housenumber":"/ 22",
    "addr:postcode":"4133",
    "addr:street":"Loganlea Rd",
    "iso:country":"AU",
    "sg:address":"9/ 22 Loganlea Rd",
    "sg:city":"Waterford",
    "sg:classifiers":[
        {
            "category":"Personal",
            "subcategory":"Beauty Salon",
            "type":"Services"
        }
    ],
    "sg:phone":"+61 7 3200 7575",
    "sg:postcode":"4133",
    "sg:province":"QLD",
    "wof:name":"Harlequins Beauty Salon",
    "wof:placetype":"venue"
},
  "geometry": {"coordinates":[153.13609314000001,-27.6916847229],"type":"Point"}
}