{
  "type": "Feature",
  "properties": {
    "addr:full":"266 Marrickville Rd Marrickville NSW 2204",
    "addr:housenumber":"266",
    "addr:postcode":"2204",
    "addr:street":"Marrickville Rd",
    "iso:country":"AU",
    "sg:address":"266 Marrickville Rd",
    "sg:city":"Marrickville",
    "sg:classifiers":[
        {
            "category":"Fast Food",
            "type":"Food & Drink"
        }
    ],
    "sg:phone":"+61 2 9569 2034",
    "sg:postcode":"2204",
    "sg:province":"NSW",
    "sg:tags":[
        "away",
        "take"
    ],
    "wof:name":"Classic Milk Bar",
    "wof:placetype":"venue"
},
  "geometry": {"coordinates":[151.15742492699999,-33.911151886],"type":"Point"}
}