{
  "type": "Feature",
  "properties": {
    "addr:full":"500 Chapel St South Yarra VIC 3141",
    "addr:housenumber":"500",
    "addr:postcode":"3141",
    "addr:street":"Chapel St",
    "iso:country":"AU",
    "sg:address":"500 Chapel St",
    "sg:city":"South Yarra",
    "sg:classifiers":[
        {
            "category":"Shopping",
            "subcategory":"Shoes",
            "type":"Retail Goods"
        }
    ],
    "sg:phone":"+61 3 9824 2800",
    "sg:postcode":"3141",
    "sg:province":"VIC",
    "sg:tags":[
        "footwear"
    ],
    "wof:name":"Ghetto Sport & Street",
    "wof:placetype":"venue"
},
  "geometry": {"coordinates":[144.995269775,-37.8420410156],"type":"Point"}
}