{
  "type": "Feature",
  "properties": {
    "addr:full":"59 Main Rd Perth TAS 7300",
    "addr:housenumber":"59",
    "addr:postcode":"7300",
    "addr:street":"Main Rd",
    "iso:country":"AU",
    "sg:address":"59 Main Rd",
    "sg:city":"Perth",
    "sg:classifiers":[
        {
            "category":"Communications",
            "subcategory":"Film & Video Production",
            "type":"Services"
        }
    ],
    "sg:phone":"+61 3 6398 2635",
    "sg:postcode":"7300",
    "sg:province":"TAS",
    "sg:tags":[
        "dvd",
        "library"
    ],
    "wof:name":"Perth Video Library",
    "wof:placetype":"venue"
},
  "geometry": {"coordinates":[147.17364499999999,-41.575863],"type":"Point"}
}