{
  "type": "Feature",
  "properties": {
    "iso:country":"AU",
    "sg:address":"18 Midas Rd",
    "sg:city":"Malaga",
    "sg:classifiers":[
        {
            "category":"Wholesale",
            "subcategory":"Auto Parts",
            "type":"Manufacturing & Wholesale Goods"
        }
    ],
    "sg:phone":"+61 8 9249 6263",
    "sg:postcode":"6090",
    "sg:province":"WA",
    "sg:tags":[
        "recyclers"
    ],
    "wof:name":"Stuttgart Parts (Australia) Pty Ltd",
    "wof:placetype":"venue"
},
  "geometry": {"coordinates":[115.89186859100001,-31.8595428467],"type":"Point"}
}