{
  "type": "Feature",
  "properties": {
    "addr:full":"Level 10, 15 William St Melbourne VIC 3000",
    "addr:housenumber":"15",
    "addr:postcode":"3000",
    "addr:street":"William St",
    "iso:country":"AU",
    "sg:address":"Level 10, 15 William St",
    "sg:city":"Melbourne",
    "sg:classifiers":[
        {
            "category":"Insurance",
            "subcategory":"Insurance Agent",
            "type":"Services"
        }
    ],
    "sg:phone":"+61 1800 687 620",
    "sg:postcode":"3000",
    "sg:province":"VIC",
    "sg:tags":[
        "broker"
    ],
    "wof:name":"Guardian Financial Planning",
    "wof:placetype":"venue"
},
  "geometry": {"coordinates":[144.959472656,-37.8187637329],"type":"Point"}
}