{
  "type": "Feature",
  "properties": {
    "addr:full":"711 Chester Crt Manunda QLD 4870",
    "addr:housenumber":"711",
    "addr:postcode":"4870",
    "addr:street":"Chester Crt",
    "iso:country":"AU",
    "sg:address":"711 Chester Crt",
    "sg:city":"Manunda",
    "sg:classifiers":[
        {
            "category":"Travel",
            "subcategory":"Hotels & Motels",
            "type":"Entertainment"
        }
    ],
    "sg:phone":"+61 7 4053 2587",
    "sg:postcode":"4870",
    "sg:province":"QLD",
    "sg:tags":[
        "accommodation"
    ],
    "wof:name":"Good Hotel",
    "wof:placetype":"venue"
},
  "geometry": {"coordinates":[145.742263794,-16.9292373657],"type":"Point"}
}