{
  "type": "Feature",
  "properties": {
    "iso:country":"AU",
    "sg:address":"Shop 1 451 Pacific Hwy",
    "sg:city":"Gosford",
    "sg:classifiers":[
        {
            "category":"Banks & Credit Unions",
            "subcategory":"Investment Brokerage",
            "type":"Services"
        }
    ],
    "sg:phone":"+61 2 4323 7468",
    "sg:postcode":"2250",
    "sg:province":"NSW",
    "sg:tags":[
        "share",
        "broker",
        "stock"
    ],
    "wof:name":"Bridges Personal Investment Services",
    "wof:placetype":"venue"
},
  "geometry": {"coordinates":[151.34707641599999,-33.4107284546],"type":"Point"}
}