{
  "type": "Feature",
  "properties": {
    "addr:full":"Level 3/ 73 York St Sydney NSW 2000",
    "addr:housenumber":"/ 73",
    "addr:postcode":"2000",
    "addr:street":"York St",
    "iso:country":"AU",
    "sg:address":"Level 3/ 73 York St",
    "sg:city":"Sydney",
    "sg:classifiers":[
        {
            "category":"Real Estate",
            "subcategory":"Architect",
            "type":"Services"
        }
    ],
    "sg:phone":"+61 2 8299 4600",
    "sg:postcode":"2000",
    "sg:province":"NSW",
    "sg:tags":[
        "building",
        "designer"
    ],
    "wof:name":"Silver Thomas Hanley Pty Ltd",
    "wof:placetype":"venue"
},
  "geometry": {"coordinates":[151.204879761,-33.8697547913],"type":"Point"}
}