{
  "type": "Feature",
  "properties": {
    "addr:full":"49 Bowen St Goondiwindi QLD 4390",
    "addr:housenumber":"49",
    "addr:postcode":"4390",
    "addr:street":"Bowen St",
    "iso:country":"AU",
    "sg:address":"49 Bowen St",
    "sg:city":"Goondiwindi",
    "sg:classifiers":[
        {
            "category":"Health Services",
            "subcategory":"Doctor",
            "type":"Services"
        }
    ],
    "sg:phone":"+61 7 4671 1444",
    "sg:postcode":"4390",
    "sg:province":"QLD",
    "sg:tags":[
        "medical",
        "practitioner"
    ],
    "wof:name":"Thompson, Ian",
    "wof:placetype":"venue"
},
  "geometry": {"coordinates":[150.30702209500001,-28.5480632782],"type":"Point"}
}