{
  "type": "Feature",
  "properties": {
    "addr:full":"33 Stanley St Wodonga NSW 3690",
    "addr:housenumber":"33",
    "addr:postcode":"3690",
    "addr:street":"Stanley St",
    "iso:country":"AU",
    "sg:address":"33 Stanley St",
    "sg:city":"Wodonga",
    "sg:classifiers":[
        {
            "category":"Banks & Credit Unions",
            "subcategory":"Financial Services",
            "type":"Services"
        }
    ],
    "sg:phone":"+61 2 6056 2229",
    "sg:postcode":"3690",
    "sg:province":"NSW",
    "sg:tags":[
        "annuity",
        "rollover",
        "superannuation",
        "consultant"
    ],
    "wof:name":"Maximum Wealth Strategies",
    "wof:placetype":"venue"
},
  "geometry": {"coordinates":[146.88124084500001,-36.1234130859],"type":"Point"}
}