{
  "type": "Feature",
  "properties": {
    "iso:country":"AU",
    "sg:address":"1428 Stuart Hwy",
    "sg:city":"Winnellie",
    "sg:classifiers":[
        {
            "category":"Retail",
            "subcategory":"Storage",
            "type":"Services"
        }
    ],
    "sg:phone":"+61 8 8984 3300",
    "sg:postcode":"0820",
    "sg:province":"NT",
    "sg:tags":[
        "cold"
    ],
    "wof:name":"Darwin Coldstores",
    "wof:placetype":"venue"
},
  "geometry": {"coordinates":[130.895629883,-12.4259672165],"type":"Point"}
}