{
  "type": "Feature",
  "properties": {
    "addr:full":"11 Reymond St Forbes NSW 2871",
    "addr:housenumber":"11",
    "addr:postcode":"2871",
    "addr:street":"Reymond St",
    "iso:country":"AU",
    "sg:address":"11 Reymond St",
    "sg:city":"Forbes",
    "sg:classifiers":[
        {
            "category":"Building & Trades",
            "subcategory":"Construction",
            "type":"Services"
        }
    ],
    "sg:phone":"+61 2 6851 1583",
    "sg:postcode":"2871",
    "sg:province":"NSW",
    "sg:tags":[
        "contractor"
    ],
    "wof:name":"Redfern D M & H L",
    "wof:placetype":"venue"
},
  "geometry": {"coordinates":[148.00904800000001,-33.402481],"type":"Point"}
}