{
  "type": "Feature",
  "properties": {
    "iso:country":"AU",
    "sg:address":"4 Rhadgodia Crt",
    "sg:city":"Heathridge",
    "sg:classifiers":[
        {
            "category":"Building & Trades",
            "subcategory":"Cleaning & Sanitation",
            "type":"Services"
        }
    ],
    "sg:phone":"+61 8 9401 9149",
    "sg:postcode":"6027",
    "sg:province":"WA",
    "sg:tags":[
        "window"
    ],
    "wof:name":"Flash Window Cleaning",
    "wof:placetype":"venue"
},
  "geometry": {"coordinates":[115.75643158,-31.7618465424],"type":"Point"}
}