{
  "type": "Feature",
  "properties": {
    "addr:full":"9/ 469 Nudgee Rd Eagle Farm QLD 4009",
    "addr:housenumber":"/ 469",
    "addr:postcode":"4009",
    "addr:street":"Nudgee Rd",
    "iso:country":"AU",
    "sg:address":"9/ 469 Nudgee Rd",
    "sg:city":"Eagle Farm",
    "sg:classifiers":[
        {
            "category":"Professional",
            "subcategory":"Printing & Photocopies",
            "type":"Services"
        }
    ],
    "sg:phone":"+61 7 3868 3881",
    "sg:postcode":"4009",
    "sg:province":"QLD",
    "sg:tags":[
        "photocopying"
    ],
    "wof:name":"Copy Specialists Group-Eagle Farm",
    "wof:placetype":"venue"
},
  "geometry": {"coordinates":[153.07489013700001,-27.4122428894],"type":"Point"}
}