{
  "type": "Feature",
  "properties": {
    "addr:full":"5 Mount Nathan Rd Mt Nathan QLD 4211",
    "addr:housenumber":"5",
    "addr:postcode":"4211",
    "addr:street":"Mount Nathan Rd;Nathan",
    "iso:country":"AU",
    "sg:address":"5 Mount Nathan Rd",
    "sg:city":"Mt Nathan",
    "sg:classifiers":[
        {
            "category":"Building & Trades",
            "subcategory":"Construction",
            "type":"Services"
        }
    ],
    "sg:phone":"+61 417 786 909",
    "sg:postcode":"4211",
    "sg:province":"QLD",
    "sg:tags":[
        "earth",
        "excavating",
        "moving",
        "contractor"
    ],
    "wof:name":"Leamon Kev Earthmoving",
    "wof:placetype":"venue"
},
  "geometry": {"coordinates":[153.29934692399999,-27.9999217987],"type":"Point"}
}