{
  "type": "Feature",
  "properties": {
    "addr:full":"Shop 2, Wyee Shopping Village Wyee Rd Wyee NSW 2259",
    "addr:housenumber":"shop 2",
    "addr:postcode":"2259",
    "addr:street":"Wyee;Wyee Rd",
    "iso:country":"AU",
    "sg:address":"Shop 2, Wyee Shopping Village Wyee Rd",
    "sg:city":"Wyee",
    "sg:classifiers":[
        {
            "category":"Health Services",
            "subcategory":"Doctor",
            "type":"Services"
        }
    ],
    "sg:phone":"+61 2 4357 1333",
    "sg:postcode":"2259",
    "sg:province":"NSW",
    "sg:tags":[
        "medical",
        "practitioner"
    ],
    "wof:name":"Tristar Medical Group",
    "wof:placetype":"venue"
},
  "geometry": {"coordinates":[151.48173523,-33.1759262085],"type":"Point"}
}