{
  "type": "Feature",
  "properties": {
    "addr:full":"21 Franklin St Wangaratta VIC 3677",
    "addr:housenumber":"21",
    "addr:postcode":"3677",
    "addr:street":"Franklin St",
    "iso:country":"AU",
    "sg:address":"21 Franklin St",
    "sg:city":"Wangaratta",
    "sg:classifiers":[
        {
            "category":"Retail",
            "subcategory":"Driving School",
            "type":"Services"
        }
    ],
    "sg:phone":"+61 3 5721 5601",
    "sg:postcode":"3677",
    "sg:province":"VIC",
    "wof:name":"Pat. Kilroy's Driving School",
    "wof:placetype":"venue"
},
  "geometry": {"coordinates":[146.29719543499999,-36.3475723267],"type":"Point"}
}