{
  "type": "Feature",
  "properties": {
    "addr:full":"300 Huntingdale Rd Huntingdale VIC 3166",
    "addr:housenumber":"300",
    "addr:postcode":"3166",
    "addr:street":"Huntingdale Rd",
    "iso:country":"AU",
    "sg:address":"300 Huntingdale Rd",
    "sg:city":"Huntingdale",
    "sg:classifiers":[
        {
            "category":"Education",
            "subcategory":"University",
            "type":"Public Place"
        }
    ],
    "sg:phone":"+61 3 9535 7020",
    "sg:postcode":"3166",
    "sg:province":"VIC",
    "sg:tags":[
        "educational",
        "organisation",
        "cultural"
    ],
    "wof:name":"Victorian Orff Schulwerk Association",
    "wof:placetype":"venue"
},
  "geometry": {"coordinates":[145.10377502399999,-37.9103469849],"type":"Point"}
}