{
  "type": "Feature",
  "properties": {
    "iso:country":"AU",
    "sg:address":"76 Moselle Drv",
    "sg:city":"Thornlands",
    "sg:phone":"+61 412 378 805",
    "sg:postcode":"4164",
    "sg:province":"QLD",
    "wof:name":"On The Spot Filter Clean - Bayside",
    "wof:placetype":"venue"
},
  "geometry": {"coordinates":[153.257247925,-27.5626296997],"type":"Point"}
}