{
  "type": "Feature",
  "properties": {
    "addr:full":"Suite 16, The Gateway Buiding 111 Davy St Booragoon WA 6154",
    "addr:housenumber":"111",
    "addr:postcode":"6154",
    "addr:street":"Davy St",
    "iso:country":"AU",
    "sg:address":"Suite 16, The Gateway Buiding 111 Davy St",
    "sg:city":"Booragoon",
    "sg:classifiers":[
        {
            "category":"Shopping",
            "subcategory":"Optical Goods",
            "type":"Retail Goods"
        }
    ],
    "sg:phone":"+61 8 9315 1245",
    "sg:postcode":"6154",
    "sg:province":"WA",
    "sg:tags":[
        "dispenser",
        "prescription"
    ],
    "wof:name":"The Optical Superstore",
    "wof:placetype":"venue"
},
  "geometry": {"coordinates":[115.829582,-32.033611],"type":"Point"}
}