{
  "type": "Feature",
  "properties": {
    "addr:full":"49 Guy St Warwick QLD 4370",
    "addr:housenumber":"49",
    "addr:postcode":"4370",
    "addr:street":"Guy St",
    "iso:country":"AU",
    "sg:address":"49 Guy St",
    "sg:city":"Warwick",
    "sg:classifiers":[
        {
            "category":"Home & Garden",
            "subcategory":"Carpets & Floor Coverings",
            "type":"Retail Goods"
        }
    ],
    "sg:phone":"+61 7 4661 7050",
    "sg:postcode":"4370",
    "sg:province":"QLD",
    "sg:tags":[
        "mattress"
    ],
    "wof:name":"Beds &#039;R Us",
    "wof:placetype":"venue"
},
  "geometry": {"coordinates":[152.03016662600001,-28.2156658173],"type":"Point"}
}