{
  "type": "Feature",
  "properties": {
    "addr:full":"11 Wattle St North Rockhampton QLD 4701",
    "addr:housenumber":"11",
    "addr:postcode":"4701",
    "addr:street":"Wattle St North",
    "iso:country":"AU",
    "sg:address":"11 Wattle St",
    "sg:city":"North Rockhampton",
    "sg:classifiers":[
        {
            "category":"Building & Trades",
            "subcategory":"Construction",
            "type":"Services"
        }
    ],
    "sg:phone":"+61 7 4927 5470",
    "sg:postcode":"4701",
    "sg:province":"QLD",
    "sg:tags":[
        "bitumen",
        "paving",
        "asphalt"
    ],
    "wof:name":"Bitumen Surfacing",
    "wof:placetype":"venue"
},
  "geometry": {"coordinates":[150.50253295900001,-23.3600902557],"type":"Point"}
}