{
  "type": "Feature",
  "properties": {
    "iso:country":"AU",
    "sg:address":"35 Webb St",
    "sg:city":"Narre Warren",
    "sg:classifiers":[
        {
            "category":"Fast Food",
            "type":"Food & Drink"
        }
    ],
    "sg:phone":"+61 3 9704 9917",
    "sg:postcode":"3805",
    "sg:province":"VIC",
    "sg:tags":[
        "away",
        "take"
    ],
    "wof:name":"Webb St Fish & Chip Shop",
    "wof:placetype":"venue"
},
  "geometry": {"coordinates":[145.304855,-38.025723],"type":"Point"}
}