{
  "type": "Feature",
  "properties": {
    "addr:full":"187 Great Eastern Hwy Belmont WA 6104",
    "addr:housenumber":"187",
    "addr:postcode":"6104",
    "addr:street":"Great Eastern Hwy",
    "iso:country":"AU",
    "sg:address":"187 Great Eastern Hwy",
    "sg:city":"Belmont",
    "sg:classifiers":[
        {
            "category":"Building & Trades",
            "subcategory":"Construction",
            "type":"Services"
        }
    ],
    "sg:phone":"+61 8 9475 6930",
    "sg:postcode":"6104",
    "sg:province":"WA",
    "sg:tags":[
        "earth",
        "excavating",
        "moving",
        "contractor"
    ],
    "wof:name":"FRL Contracting Pty Ltd",
    "wof:placetype":"venue"
},
  "geometry": {"coordinates":[115.919921875,-31.9457015991],"type":"Point"}
}