{
  "type": "Feature",
  "properties": {
    "addr:full":"Shop 6, 53 Grange Rd Welland SA 5007",
    "addr:housenumber":"shop;53",
    "addr:postcode":"5007",
    "addr:street":"Grange Rd",
    "iso:country":"AU",
    "sg:address":"Shop 6, 53 Grange Rd",
    "sg:city":"Welland",
    "sg:classifiers":[
        {
            "category":"Communications",
            "subcategory":"Film & Video Production",
            "type":"Services"
        }
    ],
    "sg:phone":"+61 8 8340 0411",
    "sg:postcode":"5007",
    "sg:province":"SA",
    "sg:tags":[
        "dvd",
        "library"
    ],
    "wof:name":"Blockbuster",
    "wof:placetype":"venue"
},
  "geometry": {"coordinates":[138.560546875,-34.9039154053],"type":"Point"}
}