{
  "type": "Feature",
  "properties": {
    "addr:full":"1 Beattie St Kallangur QLD 4503",
    "addr:housenumber":"1",
    "addr:postcode":"4503",
    "addr:street":"Beattie St",
    "iso:country":"AU",
    "sg:address":"1 Beattie St",
    "sg:city":"Kallangur",
    "sg:classifiers":[
        {
            "category":"Professional",
            "subcategory":"Art Services",
            "type":"Services"
        }
    ],
    "sg:phone":"+61 408 744 995",
    "sg:postcode":"4503",
    "sg:province":"QLD",
    "sg:tags":[
        "decorator",
        "painter"
    ],
    "wof:name":"QLD Textures Specialised Coating",
    "wof:placetype":"venue"
},
  "geometry": {"coordinates":[152.981765747,-27.2584342957],"type":"Point"}
}