{
  "type": "Feature",
  "properties": {
    "iso:country":"AU",
    "sg:address":"9 Forge St",
    "sg:city":"Welshpool",
    "sg:classifiers":[
        {
            "category":"Bars & Pubs",
            "subcategory":"Champagne Bar",
            "type":"Food & Drink"
        }
    ],
    "sg:phone":"+61 8 9356 1797",
    "sg:postcode":"6106",
    "sg:province":"WA",
    "sg:tags":[
        "lintel",
        "arch"
    ],
    "wof:name":"D & L Lintels",
    "wof:placetype":"venue"
},
  "geometry": {"coordinates":[115.93321228000001,-31.98960495],"type":"Point"}
}