{
  "type": "Feature",
  "properties": {
    "iso:country":"AU",
    "sg:address":"39a Wright St",
    "sg:city":"Adelaide",
    "sg:classifiers":[
        {
            "category":"Real Estate",
            "subcategory":"Architect",
            "type":"Services"
        }
    ],
    "sg:phone":"+61 413 380 518",
    "sg:postcode":"5000",
    "sg:province":"SA",
    "wof:name":"DC Studios",
    "wof:placetype":"venue"
},
  "geometry": {"coordinates":[138.59861755399999,-34.931728363],"type":"Point"}
}