{
  "type": "Feature",
  "properties": {
    "addr:full":"167 North Rd Gardenvale VIC 3185",
    "addr:housenumber":"167",
    "addr:postcode":"3185",
    "addr:street":"North Rd",
    "iso:country":"AU",
    "sg:address":"167 North Rd",
    "sg:city":"Gardenvale",
    "sg:classifiers":[
        {
            "category":"Retail",
            "subcategory":"Veterinary Services",
            "type":"Services"
        }
    ],
    "sg:phone":"+61 3 9596 4804",
    "sg:postcode":"3185",
    "sg:province":"VIC",
    "sg:tags":[
        "surgeon"
    ],
    "wof:name":"North Road Veterinary Centre",
    "wof:placetype":"venue"
},
  "geometry": {"coordinates":[145.00755310100001,-37.8997917175],"type":"Point"}
}