{
  "type": "Feature",
  "properties": {
    "iso:country":"AU",
    "sg:address":"51 Druitt St",
    "sg:city":"Sydney",
    "sg:classifiers":[
        {
            "category":"Cafe",
            "type":"Food & Drink"
        }
    ],
    "sg:phone":"+61 2 9264 6370",
    "sg:postcode":"2000",
    "sg:province":"NSW",
    "wof:name":"PJ&#039;S Gourmet Cafe",
    "wof:placetype":"venue"
},
  "geometry": {"coordinates":[151.20497131400001,-33.8729438782],"type":"Point"}
}