{
  "type": "Feature",
  "properties": {
    "addr:full":"Kiosk 3 Centro Box Hill South 1 Main St Box Hill VIC 3128",
    "addr:housenumber":"1",
    "addr:postcode":"3128",
    "addr:street":"Hill South;Main St",
    "iso:country":"AU",
    "sg:address":"Kiosk 3 Centro Box Hill South 1 Main St",
    "sg:city":"Box Hill",
    "sg:classifiers":[
        {
            "category":"Building & Trades",
            "subcategory":"Locksmith",
            "type":"Services"
        }
    ],
    "sg:phone":"+61 3 9890 6370",
    "sg:postcode":"3128",
    "sg:province":"VIC",
    "sg:tags":[
        "lock"
    ],
    "wof:name":"Mister Minit",
    "wof:placetype":"venue"
},
  "geometry": {"coordinates":[145.12326049800001,-37.819278717],"type":"Point"}
}