{
  "type": "Feature",
  "properties": {
    "iso:country":"AU",
    "sg:address":"20- 22 Tikalara St",
    "sg:city":"Regency Park",
    "sg:classifiers":[
        {
            "category":"Shopping",
            "subcategory":"Stationery & Office Supplies",
            "type":"Retail Goods"
        }
    ],
    "sg:phone":"+61 1300 479 727",
    "sg:postcode":"5010",
    "sg:province":"SA",
    "sg:tags":[
        "packaging",
        "material"
    ],
    "wof:name":"Integrated Packaging",
    "wof:placetype":"venue"
},
  "geometry": {"coordinates":[138.573684692,-34.8693351746],"type":"Point"}
}