{
  "type": "Feature",
  "properties": {
    "iso:country":"AU",
    "sg:address":"271 Wardell Rd",
    "sg:city":"Marrickville",
    "sg:classifiers":[
        {
            "category":"Retail",
            "subcategory":"Auto Repair",
            "type":"Services"
        }
    ],
    "sg:phone":"+61 2 9558 1257",
    "sg:postcode":"2204",
    "sg:province":"NSW",
    "sg:tags":[
        "repairer",
        "motor",
        "engineer"
    ],
    "wof:name":"M.P. Automotive Mechanics",
    "wof:placetype":"venue"
},
  "geometry": {"coordinates":[151.144974,-33.907101],"type":"Point"}
}