{
  "type": "Feature",
  "properties": {
    "addr:full":"139 Gotha St Fortitude Valley QLD 4006",
    "addr:housenumber":"139",
    "addr:postcode":"4006",
    "addr:street":"Gotha St",
    "iso:country":"AU",
    "sg:address":"139 Gotha St",
    "sg:city":"Fortitude Valley",
    "sg:classifiers":[
        {
            "category":"Professional",
            "subcategory":"Art Services",
            "type":"Services"
        }
    ],
    "sg:phone":"+61 7 3854 1633",
    "sg:postcode":"4006",
    "sg:province":"QLD",
    "sg:tags":[
        "graphic",
        "designer"
    ],
    "wof:name":"JSA Design",
    "wof:placetype":"venue"
},
  "geometry": {"coordinates":[153.02981567399999,-27.4580459595],"type":"Point"}
}