{
  "type": "Feature",
  "properties": {
    "iso:country":"AU",
    "sg:address":"44a Robertson St",
    "sg:city":"Naracoorte",
    "sg:classifiers":[
        {
            "category":"Health Services",
            "subcategory":"Dentist",
            "type":"Services"
        }
    ],
    "sg:phone":"+61 8 8762 1449",
    "sg:postcode":"5271",
    "sg:province":"SA",
    "wof:name":"Lewis S Dr",
    "wof:placetype":"venue"
},
  "geometry": {"coordinates":[140.74437,-36.956188],"type":"Point"}
}