{
  "type": "Feature",
  "properties": {
    "addr:full":"Unit 4/ 6 Mary St Como WA 6152",
    "addr:housenumber":"6",
    "addr:postcode":"6152",
    "addr:street":"Mary St",
    "iso:country":"AU",
    "sg:address":"Unit 4/ 6 Mary St",
    "sg:city":"Como",
    "sg:classifiers":[
        {
            "category":"Building & Trades",
            "subcategory":"Cleaning & Sanitation",
            "type":"Services"
        }
    ],
    "sg:phone":"+61 8 9368 0177",
    "sg:postcode":"6152",
    "sg:province":"WA",
    "sg:tags":[
        "industrial",
        "commercial",
        "contractor"
    ],
    "wof:name":"Cleansing Wave",
    "wof:placetype":"venue"
},
  "geometry": {"coordinates":[115.85745199999999,-31.993006],"type":"Point"}
}