{
  "type": "Feature",
  "properties": {
    "iso:country":"AU",
    "sg:address":"Suite 9/ 214 Bay St",
    "sg:city":"Brighton",
    "sg:classifiers":[
        {
            "category":"School Buses",
            "type":"Transportation"
        }
    ],
    "sg:phone":"+61 3 9592 5161",
    "sg:postcode":"3186",
    "sg:province":"VIC",
    "sg:tags":[
        "nanny"
    ],
    "wof:name":"Abracadabra Brighton Domestic Agencies",
    "wof:placetype":"venue"
},
  "geometry": {"coordinates":[145.01660156200001,-37.9175796509],"type":"Point"}
}