{
  "type": "Feature",
  "properties": {
    "iso:country":"AU",
    "sg:address":"36 Reid St",
    "sg:city":"Ardeer",
    "sg:classifiers":[
        {
            "category":"Building & Trades",
            "subcategory":"Construction",
            "type":"Services"
        }
    ],
    "sg:phone":"+61 419 102 064",
    "sg:postcode":"3022",
    "sg:province":"VIC",
    "sg:tags":[
        "concrete",
        "contractor"
    ],
    "wof:name":"Deer Park Concreting Co Pty Ltd",
    "wof:placetype":"venue"
},
  "geometry": {"coordinates":[144.804626,-37.770016],"type":"Point"}
}