{
  "type": "Feature",
  "properties": {
    "iso:country":"AU",
    "sg:address":"PO Box 21",
    "sg:city":"Cambooya",
    "sg:classifiers":[
        {
            "category":"Commercial Area",
            "type":"Public Place"
        }
    ],
    "sg:phone":"+61 428 449 940",
    "sg:postcode":"4358",
    "sg:province":"QLD",
    "sg:tags":[
        "heavy",
        "carrier"
    ],
    "wof:name":"Darby Harvesting & Haulage",
    "wof:placetype":"venue"
},
  "geometry": {"coordinates":[151.873627,-27.708389],"type":"Point"}
}