{
  "type": "Feature",
  "properties": {
    "addr:full":"128- 130 Hume St Goulburn NSW 2580",
    "addr:housenumber":"128 130",
    "addr:postcode":"2580",
    "addr:street":"Hume St",
    "iso:country":"AU",
    "sg:address":"128- 130 Hume St",
    "sg:city":"Goulburn",
    "sg:classifiers":[
        {
            "category":"Retail",
            "subcategory":"Auto Repair",
            "type":"Services"
        }
    ],
    "sg:phone":"+61 2 4821 1266",
    "sg:postcode":"2580",
    "sg:province":"NSW",
    "sg:tags":[
        "repairer",
        "motor",
        "engineer"
    ],
    "wof:name":"Southern Ford",
    "wof:placetype":"venue"
},
  "geometry": {"coordinates":[149.696655273,-34.7691078186],"type":"Point"}
}