{
  "type": "Feature",
  "properties": {
    "addr:full":"120 Egan St Kalgoorlie WA 6430",
    "addr:housenumber":"120",
    "addr:postcode":"6430",
    "addr:street":"Egan St",
    "iso:country":"AU",
    "sg:address":"120 Egan St",
    "sg:city":"Kalgoorlie",
    "sg:classifiers":[
        {
            "category":"Banks & Credit Unions",
            "subcategory":"Financial Services",
            "type":"Services"
        }
    ],
    "sg:phone":"+61 8 9021 6444",
    "sg:postcode":"6430",
    "sg:province":"WA",
    "sg:tags":[
        "loan",
        "finance",
        "mortgage"
    ],
    "wof:name":"Goldfields Credit Union",
    "wof:placetype":"venue"
},
  "geometry": {"coordinates":[121.470336914,-30.751121521],"type":"Point"}
}