{
  "type": "Feature",
  "properties": {
    "addr:full":"1262 Toorak Rd Burwood VIC 3125",
    "addr:housenumber":"1262",
    "addr:postcode":"3125",
    "addr:street":"Toorak Rd",
    "iso:country":"AU",
    "sg:address":"1262 Toorak Rd",
    "sg:city":"Burwood",
    "sg:classifiers":[
        {
            "category":"Education",
            "subcategory":"Special Training",
            "type":"Public Place"
        }
    ],
    "sg:phone":"+61 3 9889 1772",
    "sg:postcode":"3125",
    "sg:province":"VIC",
    "sg:tags":[
        "development"
    ],
    "wof:name":"Future Impact",
    "wof:placetype":"venue"
},
  "geometry": {"coordinates":[145.08395385700001,-37.8491783142],"type":"Point"}
}