{
  "type": "Feature",
  "properties": {
    "addr:full":"32/ 1 St Heliers St Abbotsford VIC 3067",
    "addr:housenumber":"32 / 1",
    "addr:postcode":"3067",
    "addr:street":"St Heliers St",
    "iso:country":"AU",
    "sg:address":"32/ 1 St Heliers St",
    "sg:city":"Abbotsford",
    "sg:classifiers":[
        {
            "category":"Building & Trades",
            "subcategory":"Construction",
            "type":"Services"
        }
    ],
    "sg:phone":"+61 3 9419 5550",
    "sg:postcode":"3067",
    "sg:province":"VIC",
    "sg:tags":[
        "contractor"
    ],
    "wof:name":"Bruce Cook & Associates Pty Ltd",
    "wof:placetype":"venue"
},
  "geometry": {"coordinates":[145.00331115700001,-37.8020477295],"type":"Point"}
}