{
  "type": "Feature",
  "properties": {
    "addr:full":"13 Commercial St Merbein VIC 3505",
    "addr:housenumber":"13",
    "addr:postcode":"3505",
    "addr:street":"Commercial St",
    "iso:country":"AU",
    "sg:address":"13 Commercial St",
    "sg:city":"Merbein",
    "sg:classifiers":[
        {
            "category":"Professional",
            "subcategory":"Engineering",
            "type":"Services"
        }
    ],
    "sg:phone":"+61 409 979 665",
    "sg:postcode":"3505",
    "sg:province":"VIC",
    "sg:tags":[
        "engineer"
    ],
    "wof:name":"Bob Impey",
    "wof:placetype":"venue"
},
  "geometry": {"coordinates":[142.052001953,-34.168056488],"type":"Point"}
}