{
  "type": "Feature",
  "properties": {
    "iso:country":"AU",
    "sg:address":"Main Rd",
    "sg:city":"Lady Barron",
    "sg:classifiers":[
        {
            "category":"Wholesale",
            "subcategory":"Seafood",
            "type":"Manufacturing & Wholesale Goods"
        }
    ],
    "sg:phone":"+61 3 6359 3604",
    "sg:postcode":"7255",
    "sg:province":"TAS",
    "sg:tags":[
        "fish"
    ],
    "wof:name":"Stavrinos Enterprises Seafoods",
    "wof:placetype":"venue"
},
  "geometry": {"coordinates":[148.23942565900001,-40.2100982666],"type":"Point"}
}