{
  "type": "Feature",
  "properties": {
    "iso:country":"AU",
    "sg:address":"40 Bennett St",
    "sg:city":"Fitzroy North",
    "sg:classifiers":[
        {
            "category":"Professional",
            "subcategory":"Accounting & Tax Preparation",
            "type":"Services"
        }
    ],
    "sg:phone":"+61 3 9486 8882",
    "sg:postcode":"3068",
    "sg:province":"VIC",
    "sg:tags":[
        "accountant",
        "auditor"
    ],
    "wof:name":"Account Ability",
    "wof:placetype":"venue"
},
  "geometry": {"coordinates":[144.98806762699999,-37.7826042175],"type":"Point"}
}