{
  "type": "Feature",
  "properties": {
    "iso:country":"AU",
    "sg:address":"22 Econo Pl",
    "sg:city":"Silverdale",
    "sg:classifiers":[
        {
            "category":"Retail",
            "subcategory":"Auto Repair",
            "type":"Services"
        }
    ],
    "sg:phone":"+61 2 4774 0700",
    "sg:postcode":"2752",
    "sg:province":"NSW",
    "sg:tags":[
        "repairer",
        "motor",
        "engineer"
    ],
    "wof:name":"Silverdale Automotive",
    "wof:placetype":"venue"
},
  "geometry": {"coordinates":[150.61465454099999,-33.8923454285],"type":"Point"}
}