{
  "type": "Feature",
  "properties": {
    "iso:country":"AU",
    "sg:address":"33 Coolatai Crs",
    "sg:city":"Bossley Park",
    "sg:classifiers":[
        {
            "category":"Building & Trades",
            "subcategory":"Cleaning & Sanitation",
            "type":"Services"
        }
    ],
    "sg:phone":"+61 2 9610 3040",
    "sg:postcode":"2176",
    "sg:province":"NSW",
    "sg:tags":[
        "grease",
        "trap"
    ],
    "wof:name":"Hills District Domestic Grease Trap Cleaning",
    "wof:placetype":"venue"
},
  "geometry": {"coordinates":[150.88375854500001,-33.859828949],"type":"Point"}
}