{
  "type": "Feature",
  "properties": {
    "addr:full":"60 Hurstbridge Rd Diamond Creek VIC 3089",
    "addr:housenumber":"60",
    "addr:postcode":"3089",
    "addr:street":"Hurstbridge Rd",
    "iso:country":"AU",
    "sg:address":"60 Hurstbridge Rd",
    "sg:city":"Diamond Creek",
    "sg:classifiers":[
        {
            "category":"Personal",
            "subcategory":"Beauty Salon",
            "type":"Services"
        }
    ],
    "sg:phone":"+61 3 9438 2537",
    "sg:postcode":"3089",
    "sg:province":"VIC",
    "sg:tags":[
        "hairdresser"
    ],
    "wof:name":"Chic Hair Studio",
    "wof:placetype":"venue"
},
  "geometry": {"coordinates":[145.15799000000001,-37.674252],"type":"Point"}
}