{
  "type": "Feature",
  "properties": {
    "addr:full":"401 Banna Ave Griffith NSW 2680",
    "addr:housenumber":"401",
    "addr:postcode":"2680",
    "addr:street":"Banna Ave",
    "iso:country":"AU",
    "sg:address":"401 Banna Ave",
    "sg:city":"Griffith",
    "sg:classifiers":[
        {
            "category":"Shopping",
            "subcategory":"Clothing, Apparel, & Fashions",
            "type":"Retail Goods"
        }
    ],
    "sg:phone":"+61 2 6962 6577",
    "sg:postcode":"2680",
    "sg:province":"NSW",
    "sg:tags":[
        "lingerie",
        "hosiery",
        "sleepwear"
    ],
    "wof:name":"Moreens For Lingerie",
    "wof:placetype":"venue"
},
  "geometry": {"coordinates":[146.04246499999999,-34.287224],"type":"Point"}
}