{
  "type": "Feature",
  "properties": {
    "iso:country":"AU",
    "sg:address":"136 Goondoon St",
    "sg:city":"Gladstone",
    "sg:classifiers":[
        {
            "category":"Fast Food",
            "type":"Food & Drink"
        }
    ],
    "sg:phone":"+61 7 4972 4141",
    "sg:postcode":"4680",
    "sg:province":"QLD",
    "sg:tags":[
        "away",
        "take"
    ],
    "wof:name":"Green Pepper Coffee Shop",
    "wof:placetype":"venue"
},
  "geometry": {"coordinates":[151.25672912600001,-23.8444633484],"type":"Point"}
}