{
  "type": "Feature",
  "properties": {
    "addr:full":"11-12 / 169 South Creek Rd Cromer NSW 2099",
    "addr:housenumber":"11-12 / 169",
    "addr:postcode":"2099",
    "addr:street":"South Creek Rd",
    "iso:country":"AU",
    "sg:address":"11-12 / 169 South Creek Rd",
    "sg:city":"Cromer",
    "sg:classifiers":[
        {
            "category":"Wholesale",
            "subcategory":"Furniture",
            "type":"Manufacturing & Wholesale Goods"
        }
    ],
    "sg:phone":"+61 1300 309 889",
    "sg:postcode":"2099",
    "sg:province":"NSW",
    "sg:tags":[
        "wholesaler",
        "mfrs"
    ],
    "wof:name":"Instyle Seating",
    "wof:placetype":"venue"
},
  "geometry": {"coordinates":[151.28599548299999,-33.7391014099],"type":"Point"}
}