{
  "type": "Feature",
  "properties": {
    "addr:full":"15 Torwood Ave Glen Waverley VIC 3150",
    "addr:housenumber":"15",
    "addr:postcode":"3150",
    "addr:street":"Torwood Ave",
    "iso:country":"AU",
    "sg:address":"15 Torwood Ave",
    "sg:city":"Glen Waverley",
    "sg:classifiers":[
        {
            "category":"Utilities",
            "subcategory":"Electric",
            "type":"Services"
        }
    ],
    "sg:phone":"+61 417 324 390",
    "sg:postcode":"3150",
    "sg:province":"VIC",
    "sg:tags":[
        "electrical",
        "contractor"
    ],
    "wof:name":"Paull Newman Electrics Pty Ltd",
    "wof:placetype":"venue"
},
  "geometry": {"coordinates":[145.18685913100001,-37.879108429],"type":"Point"}
}