{
  "type": "Feature",
  "properties": {
    "addr:full":"13 Pascoe Ave Strathmore VIC 3041",
    "addr:housenumber":"13",
    "addr:postcode":"3041",
    "addr:street":"Pascoe Ave",
    "iso:country":"AU",
    "sg:address":"13 Pascoe Ave",
    "sg:city":"Strathmore",
    "sg:classifiers":[
        {
            "category":"Retail",
            "subcategory":"Auto Repair",
            "type":"Services"
        }
    ],
    "sg:phone":"+61 3 9379 5264",
    "sg:postcode":"3041",
    "sg:province":"VIC",
    "sg:tags":[
        "repairer",
        "motor",
        "engineer"
    ],
    "wof:name":"V.B. Automotive Services",
    "wof:placetype":"venue"
},
  "geometry": {"coordinates":[144.92796325699999,-37.742351532],"type":"Point"}
}