{
  "type": "Feature",
  "properties": {
    "iso:country":"AU",
    "sg:address":"10 Bayonet Head Rd",
    "sg:city":"Bayonet Head",
    "sg:classifiers":[
        {
            "category":"Building & Trades",
            "subcategory":"Landscaping Services",
            "type":"Services"
        }
    ],
    "sg:phone":"+61 8 9844 8598",
    "sg:postcode":"6330",
    "sg:province":"WA",
    "sg:tags":[
        "designer",
        "landscape",
        "contractor"
    ],
    "wof:name":"Gardenwest",
    "wof:placetype":"venue"
},
  "geometry": {"coordinates":[117.922523498,-34.9814910889],"type":"Point"}
}