{
  "type": "Feature",
  "properties": {
    "addr:full":"Shop 1a, 3 Raymond Rd Springwood NSW 2777",
    "addr:housenumber":"shop 1a 3",
    "addr:postcode":"2777",
    "addr:street":"Raymond Rd",
    "iso:country":"AU",
    "sg:address":"Shop 1a, 3 Raymond Rd",
    "sg:city":"Springwood",
    "sg:classifiers":[
        {
            "category":"Communications",
            "subcategory":"Film & Video Production",
            "type":"Services"
        }
    ],
    "sg:phone":"+61 2 4751 7555",
    "sg:postcode":"2777",
    "sg:province":"NSW",
    "sg:tags":[
        "dvd",
        "library"
    ],
    "wof:name":"Blockbuster",
    "wof:placetype":"venue"
},
  "geometry": {"coordinates":[150.56771850600001,-33.7006187439],"type":"Point"}
}