{
  "type": "Feature",
  "properties": {
    "addr:full":"46 Challis St Newport VIC 3015",
    "addr:housenumber":"46",
    "addr:postcode":"3015",
    "addr:street":"Challis St",
    "iso:country":"AU",
    "sg:address":"46 Challis St",
    "sg:city":"Newport",
    "sg:classifiers":[
        {
            "category":"Shopping",
            "subcategory":"Crafts & Fabrics",
            "type":"Retail Goods"
        }
    ],
    "sg:phone":"+61 3 9398 0151",
    "sg:postcode":"3015",
    "sg:province":"VIC",
    "sg:tags":[
        "supply"
    ],
    "wof:name":"Dutch Folk Art & Woodcraft",
    "wof:placetype":"venue"
},
  "geometry": {"coordinates":[144.87289428700001,-37.8458976746],"type":"Point"}
}