{
  "type": "Feature",
  "properties": {
    "addr:full":"Panorama Ave Bathurst NSW 2795",
    "addr:postcode":"2795",
    "addr:street":"Panorama Ave",
    "iso:country":"AU",
    "sg:address":"Panorama Ave",
    "sg:city":"Bathurst",
    "sg:classifiers":[
        {
            "category":"Real Estate",
            "subcategory":"Surveying",
            "type":"Services"
        }
    ],
    "sg:phone":"+61 2 6332 8123",
    "sg:postcode":"2795",
    "sg:province":"NSW",
    "sg:tags":[
        "map",
        "mapping"
    ],
    "wof:name":"Land And Property Information",
    "wof:placetype":"venue"
},
  "geometry": {"coordinates":[149.56178283700001,-33.4393157959],"type":"Point"}
}