{
  "type": "Feature",
  "properties": {
    "addr:full":"136 High St Hastings VIC 3915",
    "addr:housenumber":"136",
    "addr:postcode":"3915",
    "addr:street":"High St",
    "iso:country":"AU",
    "sg:address":"136 High St",
    "sg:city":"Hastings",
    "sg:classifiers":[
        {
            "category":"Home & Garden",
            "subcategory":"Garden Supply",
            "type":"Retail Goods"
        }
    ],
    "sg:phone":"+61 3 5979 1588",
    "sg:postcode":"3915",
    "sg:province":"VIC",
    "sg:tags":[
        "equipment"
    ],
    "wof:name":"Raes Mitre 10 Gardener",
    "wof:placetype":"venue"
},
  "geometry": {"coordinates":[145.18490600600001,-38.3075790405],"type":"Point"}
}