{
  "type": "Feature",
  "properties": {
    "iso:country":"AU",
    "sg:address":"33 Heeley St",
    "sg:city":"Paddington",
    "sg:classifiers":[
        {
            "category":"Social Services",
            "subcategory":"Child Care",
            "type":"Services"
        }
    ],
    "sg:phone":"+61 2 9331 2621",
    "sg:postcode":"2021",
    "sg:province":"NSW",
    "wof:name":"SDN Children's Services",
    "wof:placetype":"venue"
},
  "geometry": {"coordinates":[151.22795105,-33.8829994202],"type":"Point"}
}