{
  "type": "Feature",
  "properties": {
    "addr:full":"Level 11, 89 York St Sydney NSW 2000",
    "addr:housenumber":"89",
    "addr:postcode":"2000",
    "addr:street":"York St",
    "iso:country":"AU",
    "sg:address":"Level 11, 89 York St",
    "sg:city":"Sydney",
    "sg:classifiers":[
        {
            "category":"Organizations",
            "subcategory":"Professional Association",
            "type":"Services"
        }
    ],
    "sg:phone":"+61 2 8297 3877",
    "sg:postcode":"2000",
    "sg:province":"NSW",
    "sg:tags":[
        "organisation",
        "business"
    ],
    "wof:name":"AWARD Australasian Writers & Art Directors Association",
    "wof:placetype":"venue"
},
  "geometry": {"coordinates":[151.20599365199999,-33.8694534302],"type":"Point"}
}