{
  "type": "Feature",
  "properties": {
    "addr:full":"479 Ocean Dr Laurieton NSW 2443",
    "addr:housenumber":"479",
    "addr:postcode":"2443",
    "addr:street":"Ocean Dr Laurieton",
    "iso:country":"AU",
    "sg:address":"479 Ocean Dr",
    "sg:city":"Laurieton",
    "sg:classifiers":[
        {
            "category":"Personal",
            "subcategory":"Massage",
            "type":"Services"
        }
    ],
    "sg:phone":"+61 2 6559 6867",
    "sg:postcode":"2443",
    "sg:province":"NSW",
    "sg:tags":[
        "therapy"
    ],
    "wof:name":"Heavenly Hands Massage & Beauty",
    "wof:placetype":"venue"
},
  "geometry": {"coordinates":[152.819794,-31.639519],"type":"Point"}
}