{
  "type": "Feature",
  "properties": {
    "iso:country":"AU",
    "sg:address":"The Lock Up, 301 Main St",
    "sg:city":"Kangaroo Point",
    "sg:classifiers":[
        {
            "category":"Real Estate",
            "subcategory":"Architect",
            "type":"Services"
        }
    ],
    "sg:phone":"+61 7 3392 1066",
    "sg:postcode":"4169",
    "sg:province":"QLD",
    "wof:name":"Spencer Robin Architects Pty Ltd",
    "wof:placetype":"venue"
},
  "geometry": {"coordinates":[153.03520202600001,-27.4710998535],"type":"Point"}
}