{
  "type": "Feature",
  "properties": {
    "addr:full":"193 Murray St Hobart TAS 7000",
    "addr:housenumber":"193",
    "addr:postcode":"7000",
    "addr:street":"Murray St",
    "iso:country":"AU",
    "sg:address":"193 Murray St",
    "sg:city":"Hobart",
    "sg:classifiers":[
        {
            "category":"Professional",
            "subcategory":"Accounting & Tax Preparation",
            "type":"Services"
        }
    ],
    "sg:phone":"+61 3 6234 3088",
    "sg:postcode":"7000",
    "sg:province":"TAS",
    "sg:tags":[
        "consultant",
        "taxation"
    ],
    "wof:name":"Accounting & Financial Services",
    "wof:placetype":"venue"
},
  "geometry": {"coordinates":[147.31993102999999,-42.8795661926],"type":"Point"}
}