{
  "type": "Feature",
  "properties": {
    "addr:full":"44 Mitchell St Mt Pleasant WA 6153",
    "addr:housenumber":"44",
    "addr:postcode":"6153",
    "addr:street":"Mitchell St",
    "iso:country":"AU",
    "sg:address":"44 Mitchell St",
    "sg:city":"Mt Pleasant",
    "sg:classifiers":[
        {
            "category":"Building & Trades",
            "subcategory":"Landscaping Services",
            "type":"Services"
        }
    ],
    "sg:phone":"+61 8 9364 6542",
    "sg:postcode":"6153",
    "sg:province":"WA",
    "sg:tags":[
        "stump",
        "tree",
        "felling",
        "removal"
    ],
    "wof:name":"Dependable Tree Services",
    "wof:placetype":"venue"
},
  "geometry": {"coordinates":[115.841667,-32.019909],"type":"Point"}
}