{
  "type": "Feature",
  "properties": {
    "addr:full":"586 Main North Road Gepps Cross SA 5094",
    "addr:housenumber":"586",
    "addr:postcode":"5094",
    "addr:street":"Main North Road",
    "iso:country":"AU",
    "sg:address":"586 Main North Road",
    "sg:city":"Gepps Cross",
    "sg:classifiers":[
        {
            "category":"Autos & Motor Vehicles",
            "subcategory":"Auto Supplies",
            "type":"Retail Goods"
        }
    ],
    "sg:phone":"+61 8 8359 0888",
    "sg:postcode":"5094",
    "sg:province":"SA",
    "sg:tags":[
        "camper-trailers",
        "caravan",
        "equipment"
    ],
    "sg:website":"http://www.adelaidecaravanspecialists.com.au",
    "wof:name":"Adelaide Caravan Specialists",
    "wof:placetype":"venue"
},
  "geometry": {"coordinates":[138.604415894,-34.8418693542],"type":"Point"}
}