{
  "type": "Feature",
  "properties": {
    "addr:full":"PO Box 248 Currumbin QLD 4223",
    "addr:postcode":"4223",
    "iso:country":"AU",
    "sg:address":"PO Box 248",
    "sg:city":"Currumbin",
    "sg:classifiers":[
        {
            "category":"Travel",
            "subcategory":"Travel Agent",
            "type":"Entertainment"
        }
    ],
    "sg:phone":"+61 7 5598 7333",
    "sg:postcode":"4223",
    "sg:province":"QLD",
    "sg:tags":[
        "tour",
        "holiday",
        "adventure"
    ],
    "wof:name":"Himalayan Envpro Adventures",
    "wof:placetype":"venue"
},
  "geometry": {"coordinates":[153.47454834000001,-28.1377792358],"type":"Point"}
}