{
  "type": "Feature",
  "properties": {
    "addr:full":"80 Oldaker St Devonport TAS 7310",
    "addr:housenumber":"80",
    "addr:postcode":"7310",
    "addr:street":"Oldaker St",
    "iso:country":"AU",
    "sg:address":"80 Oldaker St",
    "sg:city":"Devonport",
    "sg:classifiers":[
        {
            "category":"Organizations",
            "subcategory":"Labor Organization",
            "type":"Services"
        }
    ],
    "sg:phone":"+61 3 6424 6885",
    "sg:postcode":"7310",
    "sg:province":"TAS",
    "sg:tags":[
        "union"
    ],
    "wof:name":"Health and Community Services Union",
    "wof:placetype":"venue"
},
  "geometry": {"coordinates":[146.35211181599999,-41.1753845215],"type":"Point"}
}