{
  "type": "Feature",
  "properties": {
    "addr:full":"20 Henderson St Fremantle WA 6160",
    "addr:housenumber":"20",
    "addr:postcode":"6160",
    "addr:street":"Henderson St",
    "iso:country":"AU",
    "sg:address":"20 Henderson St",
    "sg:city":"Fremantle",
    "sg:classifiers":[
        {
            "category":"Shopping",
            "subcategory":"Crafts & Fabrics",
            "type":"Retail Goods"
        }
    ],
    "sg:phone":"+61 8 9335 8323",
    "sg:postcode":"6160",
    "sg:province":"WA",
    "sg:tags":[
        "supply"
    ],
    "wof:name":"Beads and Bangles",
    "wof:placetype":"venue"
},
  "geometry": {"coordinates":[115.74936700000001,-32.055622],"type":"Point"}
}