{
  "type": "Feature",
  "properties": {
    "addr:full":"30 Frankston Gardens Drv Carrum Downs VIC 3201",
    "addr:housenumber":"30",
    "addr:postcode":"3201",
    "addr:street":"Frankston Gardens Drv",
    "iso:country":"AU",
    "sg:address":"30 Frankston Gardens Drv",
    "sg:city":"Carrum Downs",
    "sg:classifiers":[
        {
            "category":"Banks & Credit Unions",
            "subcategory":"Investment Brokerage",
            "type":"Services"
        }
    ],
    "sg:phone":"+61 3 9770 4184",
    "sg:postcode":"3201",
    "sg:province":"VIC",
    "sg:tags":[
        "shutter",
        "louvre"
    ],
    "wof:name":"LouvreTec",
    "wof:placetype":"venue"
},
  "geometry": {"coordinates":[145.162048,-38.104343],"type":"Point"}
}