{
  "type": "Feature",
  "properties": {
    "addr:full":"28 Newton Rd Wetherill Park NSW 2164",
    "addr:housenumber":"28",
    "addr:postcode":"2164",
    "addr:street":"Newton Rd",
    "iso:country":"AU",
    "sg:address":"28 Newton Rd",
    "sg:city":"Wetherill Park",
    "sg:classifiers":[
        {
            "category":"Shopping",
            "subcategory":"Stationery & Office Supplies",
            "type":"Retail Goods"
        }
    ],
    "sg:phone":"+61 2 9612 1800",
    "sg:postcode":"2164",
    "sg:province":"NSW",
    "sg:tags":[
        "packaging",
        "material"
    ],
    "wof:name":"Mark Colin Packaging",
    "wof:placetype":"venue"
},
  "geometry": {"coordinates":[150.8934021,-33.8419189453],"type":"Point"}
}