{
  "type": "Feature",
  "properties": {
    "addr:full":"Suite 6b/ 197 Days Rd Grange QLD 4051",
    "addr:housenumber":"suite 6b / 197",
    "addr:postcode":"4051",
    "addr:street":"Days Rd",
    "iso:country":"AU",
    "sg:address":"Suite 6b/ 197 Days Rd",
    "sg:city":"Grange",
    "sg:classifiers":[
        {
            "category":"Health Services",
            "subcategory":"Health Practitioner",
            "type":"Services"
        }
    ],
    "sg:phone":"+61 7 3356 7737",
    "sg:postcode":"4051",
    "sg:province":"QLD",
    "sg:tags":[
        "physiotherapist"
    ],
    "wof:name":"Box Robyn Dr",
    "wof:placetype":"venue"
},
  "geometry": {"coordinates":[153.01451110799999,-27.4258174896],"type":"Point"}
}