{
  "type": "Feature",
  "properties": {
    "iso:country":"AU",
    "sg:address":"PO Box 619",
    "sg:city":"Nelson Bay",
    "sg:classifiers":[
        {
            "category":"Retail",
            "subcategory":"Auto Rental",
            "type":"Services"
        }
    ],
    "sg:phone":"+61 2 4984 7766",
    "sg:postcode":"2315",
    "sg:province":"NSW",
    "sg:tags":[
        "chauffeur",
        "car",
        "hire",
        "driven",
        "limousine"
    ],
    "wof:name":"Nelson Bay Limousines",
    "wof:placetype":"venue"
},
  "geometry": {"coordinates":[152.14331100000001,-32.72279],"type":"Point"}
}