{
  "type": "Feature",
  "properties": {
    "addr:full":"Unit 5, 750- 752 Pittwater Rd Brookvale NSW 2100",
    "addr:housenumber":"750 752",
    "addr:postcode":"2100",
    "addr:street":"Pittwater Rd",
    "iso:country":"AU",
    "sg:address":"Unit 5, 750- 752 Pittwater Rd",
    "sg:city":"Brookvale",
    "sg:classifiers":[
        {
            "category":"Retail",
            "subcategory":"Auto Repair",
            "type":"Services"
        }
    ],
    "sg:phone":"+61 2 9905 4914",
    "sg:postcode":"2100",
    "sg:province":"NSW",
    "sg:tags":[
        "automotive",
        "air conditioning"
    ],
    "wof:name":"Henshaw Auto Electrical Service Pty Ltd",
    "wof:placetype":"venue"
},
  "geometry": {"coordinates":[151.2762146,-33.761390686],"type":"Point"}
}