{
  "type": "Feature",
  "properties": {
    "iso:country":"AU",
    "sg:address":"U5/ 10 Prosperity Pl",
    "sg:city":"Geebung",
    "sg:classifiers":[
        {
            "category":"Shopping Center",
            "type":"Public Place"
        }
    ],
    "sg:phone":"+61 7 3216 5477",
    "sg:postcode":"4034",
    "sg:province":"QLD",
    "sg:tags":[
        "riveting",
        "equipment",
        "rivet"
    ],
    "wof:name":"G W Fasteners",
    "wof:placetype":"venue"
},
  "geometry": {"coordinates":[153.047653,-27.365622],"type":"Point"}
}