{
  "type": "Feature",
  "properties": {
    "addr:full":"James Rd Beachmere QLD 4510",
    "addr:postcode":"4510",
    "addr:street":"James Rd",
    "iso:country":"AU",
    "sg:address":"James Rd",
    "sg:city":"Beachmere",
    "sg:classifiers":[
        {
            "category":"Education",
            "subcategory":"School",
            "type":"Public Place"
        }
    ],
    "sg:phone":"+61 7 5496 8088",
    "sg:postcode":"4510",
    "sg:province":"QLD",
    "sg:tags":[
        "state",
        "except",
        "nsw"
    ],
    "wof:name":"Beachmere Preschool",
    "wof:placetype":"venue"
},
  "geometry": {"coordinates":[153.04899599999999,-27.129835],"type":"Point"}
}