{
  "type": "Feature",
  "properties": {
    "addr:full":"14 Florence St West Perth WA 6005",
    "addr:housenumber":"14",
    "addr:postcode":"6005",
    "addr:street":"Florence St",
    "iso:country":"AU",
    "sg:address":"14 Florence St",
    "sg:city":"West Perth",
    "sg:classifiers":[
        {
            "category":"Professional",
            "subcategory":"Printing & Photocopies",
            "type":"Services"
        }
    ],
    "sg:phone":"+61 8 9328 6855",
    "sg:postcode":"6005",
    "sg:province":"WA",
    "sg:tags":[
        "plaque"
    ],
    "wof:name":"Sheridan's Engraving",
    "wof:placetype":"venue"
},
  "geometry": {"coordinates":[115.850738525,-31.9385051727],"type":"Point"}
}