{
  "type": "Feature",
  "properties": {
    "addr:full":"PO Box 811 Rye VIC 3941",
    "addr:postcode":"3941",
    "iso:country":"AU",
    "sg:address":"PO Box 811",
    "sg:city":"Rye",
    "sg:classifiers":[
        {
            "category":"Banks & Credit Unions",
            "subcategory":"Bank",
            "type":"Services"
        }
    ],
    "sg:phone":"+61 429 300 262",
    "sg:postcode":"3941",
    "sg:province":"VIC",
    "sg:tags":[
        "broker",
        "mortgage"
    ],
    "wof:name":"Success Mortgages Pty Ltd",
    "wof:placetype":"venue"
},
  "geometry": {"coordinates":[144.820755005,-38.3701400757],"type":"Point"}
}