{
  "type": "Feature",
  "properties": {
    "addr:full":"358- 362 Orrong Rd Caulfield North VIC 3161",
    "addr:housenumber":"358 362",
    "addr:postcode":"3161",
    "addr:street":"Orrong Rd",
    "iso:country":"AU",
    "sg:address":"358- 362 Orrong Rd",
    "sg:city":"Caulfield North",
    "sg:classifiers":[
        {
            "category":"Food & Beverages",
            "subcategory":"Supermarket",
            "type":"Retail Goods"
        }
    ],
    "sg:phone":"+61 3 9527 5888",
    "sg:postcode":"3161",
    "sg:province":"VIC",
    "sg:tags":[
        "grocery",
        "store"
    ],
    "wof:name":"Alma Village Supermarket",
    "wof:placetype":"venue"
},
  "geometry": {"coordinates":[145.01017761200001,-37.8630561829],"type":"Point"}
}