{
  "type": "Feature",
  "properties": {
    "addr:full":"1055 Mira Rd (South) Darwin River NT 0822",
    "addr:housenumber":"1055",
    "addr:postcode":"0822",
    "addr:street":"Mira Rd South Darwin",
    "iso:country":"AU",
    "sg:address":"1055 Mira Rd (South)",
    "sg:city":"Darwin River",
    "sg:classifiers":[
        {
            "category":"Home & Garden",
            "subcategory":"Garden Supply",
            "type":"Retail Goods"
        }
    ],
    "sg:phone":"+61 8 8988 6266",
    "sg:postcode":"0822",
    "sg:province":"NT",
    "sg:tags":[
        "equipment"
    ],
    "wof:name":"Shuker Farm",
    "wof:placetype":"venue"
},
  "geometry": {"coordinates":[130.94931,-12.73486],"type":"Point"}
}