{
  "type": "Feature",
  "properties": {
    "iso:country":"AU",
    "sg:address":"635 Mt Alexander Rd",
    "sg:city":"Moonee Ponds",
    "sg:classifiers":[
        {
            "category":"Personal",
            "subcategory":"Beauty Salon",
            "type":"Services"
        }
    ],
    "sg:phone":"+61 3 9375 1869",
    "sg:postcode":"3039",
    "sg:province":"VIC",
    "sg:tags":[
        "hairdresser"
    ],
    "wof:name":"Brunettes, Blondes & Redheads",
    "wof:placetype":"venue"
},
  "geometry": {"coordinates":[144.924652,-37.767036],"type":"Point"}
}