{
  "type": "Feature",
  "properties": {
    "addr:full":"Lvl 9, Northpoint Cnr Miller St & Pacific Hwy North Sydney NSW 2060",
    "addr:postcode":"2060",
    "addr:street":"Miller St & Pacific Hwy",
    "iso:country":"AU",
    "sg:address":"Lvl 9, Northpoint Cnr Miller St & Pacific Hwy",
    "sg:city":"North Sydney",
    "sg:classifiers":[
        {
            "category":"Education",
            "subcategory":"Junior College",
            "type":"Public Place"
        }
    ],
    "sg:phone":"+61 2 9955 1122",
    "sg:postcode":"2060",
    "sg:province":"NSW",
    "sg:tags":[
        "business"
    ],
    "wof:name":"Billy Blue Schools",
    "wof:placetype":"venue"
},
  "geometry": {"coordinates":[151.20669555699999,-33.8396720886],"type":"Point"}
}