{
  "type": "Feature",
  "properties": {
    "addr:full":"1013 Raglan Pde Warrnambool VIC 3280",
    "addr:housenumber":"1013",
    "addr:postcode":"3280",
    "addr:street":"Raglan Pde",
    "iso:country":"AU",
    "sg:address":"1013 Raglan Pde",
    "sg:city":"Warrnambool",
    "sg:classifiers":[
        {
            "category":"Retail",
            "subcategory":"Auto Repair",
            "type":"Services"
        }
    ],
    "sg:phone":"+61 3 5561 3415",
    "sg:postcode":"3280",
    "sg:province":"VIC",
    "sg:tags":[
        "repairer",
        "motor",
        "engineer"
    ],
    "wof:name":"Passlow Ford",
    "wof:placetype":"venue"
},
  "geometry": {"coordinates":[142.467697144,-38.3694229126],"type":"Point"}
}