{
  "type": "Feature",
  "properties": {
    "addr:full":"Cnr Investigator Drv & Nolan St Unanderra NSW 2526",
    "addr:postcode":"2526",
    "addr:street":"Cnr Investigator Drv & Nolan St",
    "iso:country":"AU",
    "sg:address":"Cnr Investigator Drv & Nolan St",
    "sg:city":"Unanderra",
    "sg:classifiers":[
        {
            "category":"Retail",
            "subcategory":"Auto Repair",
            "type":"Services"
        }
    ],
    "sg:phone":"+61 411 561 045",
    "sg:postcode":"2526",
    "sg:province":"NSW",
    "sg:tags":[
        "repairer",
        "motor",
        "engineer"
    ],
    "wof:name":"Mark Hamilton",
    "wof:placetype":"venue"
},
  "geometry": {"coordinates":[150.84164428700001,-34.4627075195],"type":"Point"}
}