{
  "type": "Feature",
  "properties": {
    "iso:country":"AU",
    "sg:address":"PO Box 3120",
    "sg:city":"Mandurah",
    "sg:classifiers":[
        {
            "category":"Building & Trades",
            "subcategory":"Pest Control",
            "type":"Services"
        }
    ],
    "sg:phone":"+61 8 9581 2202",
    "sg:postcode":"6210",
    "sg:province":"WA",
    "wof:name":"Pest Guard WA",
    "wof:placetype":"venue"
},
  "geometry": {"coordinates":[115.784737,-32.509258],"type":"Point"}
}