{
  "type": "Feature",
  "properties": {
    "iso:country":"AU",
    "sg:address":"Shop 4 109 Palmerin St",
    "sg:city":"Warwick",
    "sg:classifiers":[
        {
            "category":"Food & Beverages",
            "subcategory":"Specialty",
            "type":"Retail Goods"
        }
    ],
    "sg:phone":"+61 7 4661 3813",
    "sg:postcode":"4370",
    "sg:province":"QLD",
    "sg:tags":[
        "product",
        "health"
    ],
    "wof:name":"Go Vita Health & Nutrition Centre",
    "wof:placetype":"venue"
},
  "geometry": {"coordinates":[152.03233337399999,-28.2169780731],"type":"Point"}
}