{
  "type": "Feature",
  "properties": {
    "iso:country":"AU",
    "sg:address":"2/ 2 Ryan Crt",
    "sg:city":"Cowes",
    "sg:classifiers":[
        {
            "category":"Building & Trades",
            "subcategory":"Construction",
            "type":"Services"
        }
    ],
    "sg:phone":"+61 3 5952 2572",
    "sg:postcode":"3922",
    "sg:province":"VIC",
    "sg:tags":[
        "home",
        "air conditioning"
    ],
    "wof:name":"Island Air",
    "wof:placetype":"venue"
},
  "geometry": {"coordinates":[145.201171875,-38.4580116272],"type":"Point"}
}