{
  "type": "Feature",
  "properties": {
    "addr:full":"513- 517 Pacific Hwy Mt Colah NSW 2079",
    "addr:housenumber":"513 517",
    "addr:postcode":"2079",
    "addr:street":"Pacific Hwy Mt Colah",
    "iso:country":"AU",
    "sg:address":"513- 517 Pacific Hwy",
    "sg:city":"Mt Colah",
    "sg:classifiers":[
        {
            "category":"Fast Food",
            "type":"Food & Drink"
        }
    ],
    "sg:phone":"+61 2 9476 8711",
    "sg:postcode":"2079",
    "sg:province":"NSW",
    "sg:tags":[
        "away",
        "take"
    ],
    "wof:name":"McDonald's Family Restaurants",
    "wof:placetype":"venue"
},
  "geometry": {"coordinates":[151.111618042,-33.6781806946],"type":"Point"}
}