{
  "type": "Feature",
  "properties": {
    "addr:full":"Level 1/ 295 Ann St Brisbane QLD 4001",
    "addr:housenumber":"/ 295",
    "addr:postcode":"4001",
    "addr:street":"Ann St",
    "iso:country":"AU",
    "sg:address":"Level 1/ 295 Ann St",
    "sg:city":"Brisbane",
    "sg:classifiers":[
        {
            "category":"Education",
            "subcategory":"Dance Studio",
            "type":"Public Place"
        }
    ],
    "sg:phone":"+61 7 3229 0350",
    "sg:postcode":"4001",
    "sg:province":"QLD",
    "sg:tags":[
        "instruction",
        "language"
    ],
    "wof:name":"Australian College Of English",
    "wof:placetype":"venue"
},
  "geometry": {"coordinates":[153.02713012699999,-27.4657001495],"type":"Point"}
}