{
  "type": "Feature",
  "properties": {
    "iso:country":"AU",
    "sg:address":"27 Gladys Crs",
    "sg:city":"Athelstone",
    "sg:classifiers":[
        {
            "category":"Building & Trades",
            "subcategory":"Landscaping Services",
            "type":"Services"
        }
    ],
    "sg:phone":"+61 8 8337 7020",
    "sg:postcode":"5076",
    "sg:province":"SA",
    "sg:tags":[
        "gardener"
    ],
    "wof:name":"Tandarnya Landscaping",
    "wof:placetype":"venue"
},
  "geometry": {"coordinates":[138.69761657699999,-34.8679542542],"type":"Point"}
}