{
  "type": "Feature",
  "properties": {
    "iso:country":"AU",
    "sg:address":"PO Box 267",
    "sg:city":"Mitchell",
    "sg:classifiers":[
        {
            "category":"Shopping",
            "subcategory":"Stationery & Office Supplies",
            "type":"Retail Goods"
        }
    ],
    "sg:phone":"+61 2 6299 7830",
    "sg:postcode":"2795",
    "sg:province":"NSW",
    "sg:tags":[
        "equipment",
        "facsimile"
    ],
    "wof:name":"Geoff Howe Business Machines",
    "wof:placetype":"venue"
},
  "geometry": {"coordinates":[149.55674743599999,-33.4224586487],"type":"Point"}
}