{
  "type": "Feature",
  "properties": {
    "addr:full":"PO Box 1217 Manly NSW 1655",
    "addr:postcode":"1655",
    "iso:country":"AU",
    "sg:address":"PO Box 1217",
    "sg:city":"Manly",
    "sg:classifiers":[
        {
            "category":"Personal",
            "subcategory":"Beauty Salon",
            "type":"Services"
        }
    ],
    "sg:phone":"+61 422 053 264",
    "sg:postcode":"1655",
    "sg:province":"NSW",
    "sg:tags":[
        "hairdresser"
    ],
    "wof:name":"African Braiding Extensions",
    "wof:placetype":"venue"
},
  "geometry": {"coordinates":[151.216308594,-33.876449585],"type":"Point"}
}