{
  "type": "Feature",
  "properties": {
    "iso:country":"AU",
    "sg:address":"Unit 1, 3 Veronica St",
    "sg:city":"Capalaba",
    "sg:classifiers":[
        {
            "category":"Shopping",
            "subcategory":"Computers & Home Electronics",
            "type":"Retail Goods"
        }
    ],
    "sg:phone":"+61 7 3245 3399",
    "sg:postcode":"4157",
    "sg:province":"QLD",
    "sg:tags":[
        "small",
        "equipment",
        "business"
    ],
    "wof:name":"Cyberpack Internet",
    "wof:placetype":"venue"
},
  "geometry": {"coordinates":[153.19844055199999,-27.5286502838],"type":"Point"}
}