{
  "type": "Feature",
  "properties": {
    "iso:country":"AU",
    "sg:address":"51b Karnak Rd",
    "sg:city":"Ashburton",
    "sg:classifiers":[
        {
            "category":"Professional",
            "subcategory":"Accounting & Tax Preparation",
            "type":"Services"
        }
    ],
    "sg:phone":"+61 3 9885 9746",
    "sg:postcode":"3147",
    "sg:province":"VIC",
    "sg:tags":[
        "accountant",
        "auditor"
    ],
    "wof:name":"Emmett & Co",
    "wof:placetype":"venue"
},
  "geometry": {"coordinates":[145.07327270499999,-37.8735313416],"type":"Point"}
}