{
  "type": "Feature",
  "properties": {
    "iso:country":"AU",
    "sg:address":"Lvl 1/ 82 Waterloo Rd",
    "sg:city":"North Ryde",
    "sg:classifiers":[
        {
            "category":"Insurance",
            "subcategory":"Hazard Insurance",
            "type":"Services"
        }
    ],
    "sg:phone":"+61 2 9889 2800",
    "sg:postcode":"2113",
    "sg:province":"NSW",
    "sg:tags":[
        "loss",
        "adjuster",
        "assessor"
    ],
    "wof:name":"Technical Assessing Pty Ltd",
    "wof:placetype":"venue"
},
  "geometry": {"coordinates":[151.12413024899999,-33.7821388245],"type":"Point"}
}