{
  "type": "Feature",
  "properties": {
    "addr:full":"3 Saltash Ave City Beach WA 6015",
    "addr:housenumber":"3",
    "addr:postcode":"6015",
    "addr:street":"Saltash Ave",
    "iso:country":"AU",
    "sg:address":"3 Saltash Ave",
    "sg:city":"City Beach",
    "sg:classifiers":[
        {
            "category":"Real Estate",
            "subcategory":"Architect",
            "type":"Services"
        }
    ],
    "sg:phone":"+61 8 9385 9867",
    "sg:postcode":"6015",
    "sg:province":"WA",
    "wof:name":"Waldron Kenneth",
    "wof:placetype":"venue"
},
  "geometry": {"coordinates":[115.760322571,-31.9502086639],"type":"Point"}
}