{
  "type": "Feature",
  "properties": {
    "addr:full":"PO Box 703 Stawell VIC 3380",
    "addr:postcode":"3380",
    "iso:country":"AU",
    "sg:address":"PO Box 703",
    "sg:city":"Stawell",
    "sg:classifiers":[
        {
            "category":"Building & Trades",
            "subcategory":"Construction",
            "type":"Services"
        }
    ],
    "sg:phone":"+61 437 103 845",
    "sg:postcode":"3380",
    "sg:province":"VIC",
    "sg:tags":[
        "earth",
        "excavating",
        "moving",
        "contractor"
    ],
    "wof:name":"S R Nicholls Excavation",
    "wof:placetype":"venue"
},
  "geometry": {"coordinates":[142.765625,-37.0643806458],"type":"Point"}
}