{
  "type": "Feature",
  "properties": {
    "addr:full":"Mary St Leichhardt NSW 2040",
    "addr:postcode":"2040",
    "addr:street":"Mary St",
    "iso:country":"AU",
    "sg:address":"Mary St",
    "sg:city":"Leichhardt",
    "sg:classifiers":[
        {
            "category":"Sports & Exercise",
            "subcategory":"Gym",
            "type":"Entertainment"
        }
    ],
    "sg:phone":"+61 2 9555 8344",
    "sg:postcode":"2040",
    "sg:province":"NSW",
    "sg:tags":[
        "health",
        "fitness"
    ],
    "wof:name":"Leichhardt Park Aquatic Centre",
    "wof:placetype":"venue"
},
  "geometry": {"coordinates":[151.155304,-33.872768],"type":"Point"}
}