{
  "type": "Feature",
  "properties": {
    "iso:country":"AU",
    "sg:address":"392 Yanyula Drv",
    "sg:city":"Anula",
    "sg:classifiers":[
        {
            "category":"Food & Beverages",
            "subcategory":"Supermarket",
            "type":"Retail Goods"
        }
    ],
    "sg:phone":"+61 8 8927 3391",
    "sg:postcode":"0812",
    "sg:province":"NT",
    "sg:tags":[
        "grocery",
        "store"
    ],
    "wof:name":"Anula Supermarket",
    "wof:placetype":"venue"
},
  "geometry": {"coordinates":[130.88528400000001,-12.388785],"type":"Point"}
}