{
  "type": "Feature",
  "properties": {
    "addr:full":"2 Finniss St Gawler SA 5118",
    "addr:housenumber":"2",
    "addr:postcode":"5118",
    "addr:street":"Finniss St",
    "iso:country":"AU",
    "sg:address":"2 Finniss St",
    "sg:city":"Gawler",
    "sg:classifiers":[
        {
            "category":"Professional",
            "subcategory":"Accounting & Tax Preparation",
            "type":"Services"
        }
    ],
    "sg:phone":"+61 8 8522 6064",
    "sg:postcode":"5118",
    "sg:province":"SA",
    "sg:tags":[
        "accountant",
        "auditor"
    ],
    "wof:name":"Jacob K F",
    "wof:placetype":"venue"
},
  "geometry": {"coordinates":[138.743774,-34.597855],"type":"Point"}
}