{
  "type": "Feature",
  "properties": {
    "addr:full":"28 Papagni Ave Newton SA 5074",
    "addr:housenumber":"28",
    "addr:postcode":"5074",
    "addr:street":"Papagni Ave",
    "iso:country":"AU",
    "sg:address":"28 Papagni Ave",
    "sg:city":"Newton",
    "sg:classifiers":[
        {
            "category":"Manufacturing",
            "subcategory":"Retail Goods",
            "type":"Manufacturing & Wholesale Goods"
        }
    ],
    "sg:phone":"+61 8 8365 9300",
    "sg:postcode":"5074",
    "sg:province":"SA",
    "sg:tags":[
        "merchant",
        "pump",
        "mfrs"
    ],
    "wof:name":"Newton Irrigation and Landscape Supplies",
    "wof:placetype":"venue"
},
  "geometry": {"coordinates":[138.684036255,-34.8791618347],"type":"Point"}
}