{
  "type": "Feature",
  "properties": {
    "addr:full":"71 Bosanquet Ave Prospect SA 5082",
    "addr:housenumber":"71",
    "addr:postcode":"5082",
    "addr:street":"Bosanquet Ave",
    "iso:country":"AU",
    "sg:address":"71 Bosanquet Ave",
    "sg:city":"Prospect",
    "sg:classifiers":[
        {
            "category":"Professional",
            "subcategory":"Art Services",
            "type":"Services"
        }
    ],
    "sg:phone":"+61 8 8269 2097",
    "sg:postcode":"5082",
    "sg:province":"SA",
    "sg:tags":[
        "work",
        "metal"
    ],
    "wof:name":"Gerry McMahon",
    "wof:placetype":"venue"
},
  "geometry": {"coordinates":[138.586868286,-34.8832550049],"type":"Point"}
}