{
  "type": "Feature",
  "properties": {
    "addr:full":"2 Coxen St Hughes ACT 2605",
    "addr:housenumber":"2",
    "addr:postcode":"2605",
    "addr:street":"Coxen St",
    "iso:country":"AU",
    "sg:address":"2 Coxen St",
    "sg:city":"Hughes",
    "sg:classifiers":[
        {
            "category":"Autos & Motor Vehicles",
            "subcategory":"Automobile Sales",
            "type":"Retail Goods"
        }
    ],
    "sg:phone":"+61 414 219 732",
    "sg:postcode":"2605",
    "sg:province":"ACT",
    "sg:tags":[
        "equipment",
        "trailer"
    ],
    "wof:name":"Affordable Trailer Repairs",
    "wof:placetype":"venue"
},
  "geometry": {"coordinates":[149.089355469,-35.3330955505],"type":"Point"}
}