{
  "type": "Feature",
  "properties": {
    "addr:full":"21 Marine Pde Arcadia QLD 4819",
    "addr:housenumber":"21",
    "addr:postcode":"4819",
    "addr:street":"Marine Pde",
    "iso:country":"AU",
    "sg:address":"21 Marine Pde",
    "sg:city":"Arcadia",
    "sg:classifiers":[
        {
            "category":"Real Estate",
            "subcategory":"Real Estate Agent",
            "type":"Services"
        }
    ],
    "sg:phone":"+61 7 4778 5077",
    "sg:postcode":"4819",
    "sg:province":"QLD",
    "wof:name":"Magnetic Island First National Real Estate",
    "wof:placetype":"venue"
},
  "geometry": {"coordinates":[146.863495,-19.151482],"type":"Point"}
}