{
  "type": "Feature",
  "properties": {
    "addr:full":"1c Spine St Sumner Park QLD 4074",
    "addr:postcode":"4074",
    "addr:street":"Spine St",
    "iso:country":"AU",
    "sg:address":"1c Spine St",
    "sg:city":"Sumner Park",
    "sg:classifiers":[
        {
            "category":"Banks & Credit Unions",
            "subcategory":"Atm",
            "type":"Services"
        }
    ],
    "sg:phone":"+61 7 3376 9980",
    "sg:postcode":"4074",
    "sg:province":"QLD",
    "sg:tags":[
        "reconditioners",
        "drum",
        "manufacturers"
    ],
    "wof:name":"Container Specialists",
    "wof:placetype":"venue"
},
  "geometry": {"coordinates":[152.937576294,-27.5686130524],"type":"Point"}
}