{
  "type": "Feature",
  "properties": {
    "iso:country":"AU",
    "sg:address":"10 Denis St St",
    "sg:city":"Marys",
    "sg:classifiers":[
        {
            "category":"Home & Garden",
            "subcategory":"Building Materials",
            "type":"Retail Goods"
        }
    ],
    "sg:phone":"+61 8 8357 5797",
    "sg:postcode":"5042",
    "sg:province":"SA",
    "sg:tags":[
        "secondhand"
    ],
    "wof:name":"Cutloose Demolition & Salvage Yard",
    "wof:placetype":"venue"
},
  "geometry": {"coordinates":[138.577682,-34.997433],"type":"Point"}
}