{
  "type": "Feature",
  "properties": {
    "addr:full":"Golden Beach Medical Centre 34 Landsborough Pde Golden Beach QLD 4551",
    "addr:housenumber":"34",
    "addr:postcode":"4551",
    "addr:street":"Landsborough Pde",
    "iso:country":"AU",
    "sg:address":"Golden Beach Medical Centre 34 Landsborough Pde",
    "sg:city":"Golden Beach",
    "sg:classifiers":[
        {
            "category":"Health Services",
            "subcategory":"Medical Lab",
            "type":"Services"
        }
    ],
    "sg:phone":"+61 7 5437 3820",
    "sg:postcode":"4551",
    "sg:province":"QLD",
    "sg:tags":[
        "laboratory",
        "pathology"
    ],
    "wof:name":"Gribbles Pathology",
    "wof:placetype":"venue"
},
  "geometry": {"coordinates":[153.119995117,-26.8202533722],"type":"Point"}
}