{
  "type": "Feature",
  "properties": {
    "addr:full":"Pacific Hwy Gordon NSW 2072",
    "addr:postcode":"2072",
    "addr:street":"Pacific Hwy",
    "iso:country":"AU",
    "sg:address":"Pacific Hwy",
    "sg:city":"Gordon",
    "sg:classifiers":[
        {
            "category":"Autos & Motor Vehicles",
            "subcategory":"Automobile Sales",
            "type":"Retail Goods"
        }
    ],
    "sg:phone":"+61 1300 307 720",
    "sg:postcode":"2072",
    "sg:province":"NSW",
    "sg:tags":[
        "car",
        "new"
    ],
    "wof:name":"Australian Vehicle Consultants Pty Ltd",
    "wof:placetype":"venue"
},
  "geometry": {"coordinates":[151.15333557100001,-33.7575912476],"type":"Point"}
}