{
  "type": "Feature",
  "properties": {
    "iso:country":"AU",
    "sg:address":"16 Cronulla St",
    "sg:city":"Cronulla",
    "sg:classifiers":[
        {
            "category":"Arena",
            "subcategory":"Sports Club",
            "type":"Entertainment"
        }
    ],
    "sg:phone":"+61 2 9523 2768",
    "sg:postcode":"2230",
    "sg:province":"NSW",
    "sg:tags":[
        "defence",
        "supply",
        "self",
        "instruction",
        "martial art"
    ],
    "sg:website":"http://www.kineticmartialarts.com.au",
    "wof:name":"Kinetic Martial Arts",
    "wof:placetype":"venue"
},
  "geometry": {"coordinates":[151.14971923799999,-34.0517120361],"type":"Point"}
}