{
  "type": "Feature",
  "properties": {
    "addr:full":"139 Union St South Lismore NSW 2480",
    "addr:housenumber":"139",
    "addr:postcode":"2480",
    "addr:street":"Union St South",
    "iso:country":"AU",
    "sg:address":"139 Union St",
    "sg:city":"South Lismore",
    "sg:classifiers":[
        {
            "category":"Wholesale",
            "subcategory":"Metals & Minerals",
            "type":"Manufacturing & Wholesale Goods"
        }
    ],
    "sg:phone":"+61 2 6622 6911",
    "sg:postcode":"2480",
    "sg:province":"NSW",
    "sg:tags":[
        "steel",
        "merchant"
    ],
    "wof:name":"Steel Boss",
    "wof:placetype":"venue"
},
  "geometry": {"coordinates":[153.26658630399999,-28.8132648468],"type":"Point"}
}