{
  "type": "Feature",
  "properties": {
    "addr:full":"Shop 11, Lismore Square Shopping Centre, McKenzie Lismore NSW 2480",
    "addr:housenumber":"shop 11",
    "addr:postcode":"2480",
    "addr:street":"Lismore Square",
    "iso:country":"AU",
    "sg:address":"Shop 11, Lismore Square Shopping Centre, McKenzie",
    "sg:city":"Lismore",
    "sg:classifiers":[
        {
            "category":"Banks & Credit Unions",
            "subcategory":"Bank",
            "type":"Services"
        }
    ],
    "sg:phone":"+61 2 6622 0499",
    "sg:postcode":"2480",
    "sg:province":"NSW",
    "wof:name":"Suncorp",
    "wof:placetype":"venue"
},
  "geometry": {"coordinates":[153.28732299800001,-28.8110523224],"type":"Point"}
}