{
  "type": "Feature",
  "properties": {
    "addr:full":"PO Box CP 1102 Mildura VIC 3501",
    "addr:postcode":"3501",
    "iso:country":"AU",
    "sg:address":"PO Box CP 1102",
    "sg:city":"Mildura",
    "sg:classifiers":[
        {
            "category":"Building & Trades",
            "subcategory":"Pest Control",
            "type":"Services"
        }
    ],
    "sg:phone":"+61 418 583 580",
    "sg:postcode":"3501",
    "sg:province":"VIC",
    "wof:name":"Pestban",
    "wof:placetype":"venue"
},
  "geometry": {"coordinates":[142.161712647,-34.186050415],"type":"Point"}
}