{
  "type": "Feature",
  "properties": {
    "iso:country":"AU",
    "sg:address":"6 George Rd",
    "sg:city":"Salamander Bay",
    "sg:classifiers":[
        {
            "category":"Manufacturing",
            "subcategory":"Rubber & Plastics",
            "type":"Manufacturing & Wholesale Goods"
        }
    ],
    "sg:phone":"+61 2 4982 0094",
    "sg:postcode":"2317",
    "sg:province":"NSW",
    "sg:tags":[
        "moulders"
    ],
    "wof:name":"Deeps Engineering-Plastics Division",
    "wof:placetype":"venue"
},
  "geometry": {"coordinates":[152.074982,-32.726585],"type":"Point"}
}