{
  "type": "Feature",
  "properties": {
    "addr:full":"Blackbutt Rd Port Macquarie NSW 2444",
    "addr:postcode":"2444",
    "addr:street":"Blackbutt Rd",
    "iso:country":"AU",
    "sg:address":"Blackbutt Rd",
    "sg:city":"Port Macquarie",
    "sg:classifiers":[
        {
            "category":"Shopping",
            "subcategory":"Pets & Pet Supplies",
            "type":"Retail Goods"
        }
    ],
    "sg:phone":"+61 2 6581 4224",
    "sg:postcode":"2444",
    "sg:province":"NSW",
    "sg:tags":[
        "food"
    ],
    "wof:name":"Port Pet Warehouse",
    "wof:placetype":"venue"
},
  "geometry": {"coordinates":[152.888779,-31.449608],"type":"Point"}
}