{
  "type": "Feature",
  "properties": {
    "addr:full":"Suite 303, 60 Park St Cnr Elizabeth St Sydney NSW 2000",
    "addr:housenumber":"60",
    "addr:postcode":"2000",
    "addr:street":"Park St Cnr Elizabeth St",
    "iso:country":"AU",
    "sg:address":"Suite 303, 60 Park St Cnr Elizabeth St",
    "sg:city":"Sydney",
    "sg:classifiers":[
        {
            "category":"Health Services",
            "subcategory":"Dentist",
            "type":"Services"
        }
    ],
    "sg:phone":"+61 2 9264 1592",
    "sg:postcode":"2000",
    "sg:province":"NSW",
    "wof:name":"A.A.A. City Smile",
    "wof:placetype":"venue"
},
  "geometry": {"coordinates":[151.210327148,-33.8695907593],"type":"Point"}
}