{
  "type": "Feature",
  "properties": {
    "addr:full":"20 Corporate Drv Heatherton VIC 3202",
    "addr:housenumber":"20",
    "addr:postcode":"3202",
    "addr:street":"Corporate Drv",
    "iso:country":"AU",
    "sg:address":"20 Corporate Drv",
    "sg:city":"Heatherton",
    "sg:phone":"+61 1300 760 306",
    "sg:postcode":"3202",
    "sg:province":"VIC",
    "wof:name":"South East Water Priority Plumbing",
    "wof:placetype":"venue"
},
  "geometry": {"coordinates":[145.077957,-37.950066],"type":"Point"}
}