{
  "type": "Feature",
  "properties": {
    "addr:full":"Level 1 146 High St Wodonga VIC 3690",
    "addr:housenumber":"146",
    "addr:postcode":"3690",
    "addr:street":"High St",
    "iso:country":"AU",
    "sg:address":"Level 1 146 High St",
    "sg:city":"Wodonga",
    "sg:classifiers":[
        {
            "category":"Professional",
            "subcategory":"Employment Agencies",
            "type":"Services"
        }
    ],
    "sg:phone":"+61 2 6056 5977",
    "sg:postcode":"3690",
    "sg:province":"VIC",
    "wof:name":"Strategic Skills Development",
    "wof:placetype":"venue"
},
  "geometry": {"coordinates":[146.88825988799999,-36.120929718],"type":"Point"}
}