{
  "type": "Feature",
  "properties": {
    "iso:country":"AU",
    "sg:address":"2/ 22 Alliance Ave",
    "sg:city":"Morisset",
    "sg:classifiers":[
        {
            "category":"Sports & Exercise",
            "subcategory":"Ski Resort",
            "type":"Entertainment"
        }
    ],
    "sg:phone":"+61 2 4973 6000",
    "sg:postcode":"2264",
    "sg:province":"NSW",
    "sg:tags":[
        "propelled",
        "jet"
    ],
    "wof:name":"Lake & Valley Leisure Craft",
    "wof:placetype":"venue"
},
  "geometry": {"coordinates":[151.473557,-33.115704],"type":"Point"}
}