{
  "type": "Feature",
  "properties": {
    "addr:full":"58 Seymour St Traralgon VIC 3844",
    "addr:housenumber":"58",
    "addr:postcode":"3844",
    "addr:street":"Seymour St",
    "iso:country":"AU",
    "sg:address":"58 Seymour St",
    "sg:city":"Traralgon",
    "sg:classifiers":[
        {
            "category":"Real Estate",
            "subcategory":"Real Estate Agent",
            "type":"Services"
        }
    ],
    "sg:phone":"+61 3 5175 8888",
    "sg:postcode":"3844",
    "sg:province":"VIC",
    "wof:name":"Ray White-Traralgon Bill McMahon Real Estate",
    "wof:placetype":"venue"
},
  "geometry": {"coordinates":[146.53717040999999,-38.1962471008],"type":"Point"}
}