{
  "type": "Feature",
  "properties": {
    "addr:full":"Cnr Warren St & Wagga Rd Lavington NSW 2641",
    "addr:postcode":"2641",
    "addr:street":"Cnr Warren St & Wagga Rd",
    "iso:country":"AU",
    "sg:address":"Cnr Warren St & Wagga Rd",
    "sg:city":"Lavington",
    "sg:classifiers":[
        {
            "category":"Social Services",
            "subcategory":"Retirement Home",
            "type":"Services"
        }
    ],
    "sg:phone":"+61 2 6040 8844",
    "sg:postcode":"2641",
    "sg:province":"NSW",
    "sg:tags":[
        "village"
    ],
    "wof:name":"Lavington Lodge",
    "wof:placetype":"venue"
},
  "geometry": {"coordinates":[146.95475769000001,-36.0423355103],"type":"Point"}
}