{
  "type": "Feature",
  "properties": {
    "addr:full":"257 Hobart Rd Kings Meadows TAS 7249",
    "addr:housenumber":"257",
    "addr:postcode":"7249",
    "addr:street":"Hobart Rd",
    "iso:country":"AU",
    "sg:address":"257 Hobart Rd",
    "sg:city":"Kings Meadows",
    "sg:classifiers":[
        {
            "category":"Home & Garden",
            "subcategory":"Carpets & Floor Coverings",
            "type":"Retail Goods"
        }
    ],
    "sg:phone":"+61 3 6344 9555",
    "sg:postcode":"7249",
    "sg:province":"TAS",
    "sg:tags":[
        "wood"
    ],
    "wof:name":"Kings Carpet Choice",
    "wof:placetype":"venue"
},
  "geometry": {"coordinates":[147.165252686,-41.4764556885],"type":"Point"}
}