{
  "type": "Feature",
  "properties": {
    "iso:country":"AU",
    "sg:address":"25 Wellington St",
    "sg:city":"Virginia",
    "sg:classifiers":[
        {
            "category":"Building & Trades",
            "subcategory":"Plumbing",
            "type":"Services"
        }
    ],
    "sg:phone":"+61 408 455 896",
    "sg:postcode":"4014",
    "sg:province":"QLD",
    "sg:tags":[
        "plumber",
        "gasfitters"
    ],
    "wof:name":"Peter Bowman",
    "wof:placetype":"venue"
},
  "geometry": {"coordinates":[153.065643311,-27.3811264038],"type":"Point"}
}