{
  "type": "Feature",
  "properties": {
    "iso:country":"AU",
    "sg:address":"87 John St",
    "sg:city":"Singleton",
    "sg:classifiers":[
        {
            "category":"Shopping",
            "subcategory":"Jewelry",
            "type":"Retail Goods"
        }
    ],
    "sg:phone":"+61 2 6572 1681",
    "sg:postcode":"2330",
    "sg:province":"NSW",
    "sg:tags":[
        "jeweller"
    ],
    "wof:name":"Coulston R",
    "wof:placetype":"venue"
},
  "geometry": {"coordinates":[151.16626,-32.56638],"type":"Point"}
}