{
  "type": "Feature",
  "properties": {
    "addr:full":"U1/ 248 Rockingham Rd Spearwood WA 6163",
    "addr:housenumber":"248",
    "addr:postcode":"6163",
    "addr:street":"U1 /;Rockingham Rd",
    "iso:country":"AU",
    "sg:address":"U1/ 248 Rockingham Rd",
    "sg:city":"Spearwood",
    "sg:classifiers":[
        {
            "category":"Shopping",
            "subcategory":"Pawn Shop",
            "type":"Retail Goods"
        }
    ],
    "sg:phone":"+61 8 9434 3144",
    "sg:postcode":"6163",
    "sg:province":"WA",
    "sg:tags":[
        "pawnbroker"
    ],
    "wof:name":"Cash Converters Phoenix Park",
    "wof:placetype":"venue"
},
  "geometry": {"coordinates":[115.782898,-32.109447],"type":"Point"}
}