{
  "type": "Feature",
  "properties": {
    "iso:country":"AU",
    "sg:address":"PO Box 1704",
    "sg:city":"Applecross",
    "sg:classifiers":[
        {
            "category":"Professional",
            "subcategory":"Management & Consulting",
            "type":"Services"
        }
    ],
    "sg:phone":"+61 8 9330 1359",
    "sg:postcode":"6153",
    "sg:province":"WA",
    "sg:tags":[
        "consultant",
        "relocation"
    ],
    "wof:name":"Executive Step Int Relocations",
    "wof:placetype":"venue"
},
  "geometry": {"coordinates":[115.834808,-32.010342],"type":"Point"}
}