{
  "type": "Feature",
  "properties": {
    "addr:full":"28 Service St Bairnsdale VIC 3875",
    "addr:housenumber":"28",
    "addr:postcode":"3875",
    "addr:street":"Service St",
    "iso:country":"AU",
    "sg:address":"28 Service St",
    "sg:city":"Bairnsdale",
    "sg:classifiers":[
        {
            "category":"Professional",
            "subcategory":"Accounting & Tax Preparation",
            "type":"Services"
        }
    ],
    "sg:phone":"+61 3 5152 3766",
    "sg:postcode":"3875",
    "sg:province":"VIC",
    "sg:tags":[
        "consultant",
        "taxation"
    ],
    "wof:name":"H&R Block",
    "wof:placetype":"venue"
},
  "geometry": {"coordinates":[147.62895202600001,-37.8256492615],"type":"Point"}
}