{
  "type": "Feature",
  "properties": {
    "addr:full":"36 Marmong St Marmong Point NSW 2284",
    "addr:housenumber":"36",
    "addr:postcode":"2284",
    "addr:street":"Marmong St",
    "iso:country":"AU",
    "sg:address":"36 Marmong St",
    "sg:city":"Marmong Point",
    "sg:classifiers":[
        {
            "category":"Home & Garden",
            "subcategory":"Carpets & Floor Coverings",
            "type":"Retail Goods"
        }
    ],
    "sg:phone":"+61 409 688 723",
    "sg:postcode":"2284",
    "sg:province":"NSW",
    "sg:tags":[
        "layer",
        "planner"
    ],
    "wof:name":"Camps Carpet Laying",
    "wof:placetype":"venue"
},
  "geometry": {"coordinates":[151.61793518100001,-32.9810333252],"type":"Point"}
}