{
  "type": "Feature",
  "properties": {
    "addr:full":"4/ 59 Boyd St Tweed Heads NSW 2485",
    "addr:housenumber":"/ 59",
    "addr:postcode":"2485",
    "addr:street":"Boyd St",
    "iso:country":"AU",
    "sg:address":"4/ 59 Boyd St",
    "sg:city":"Tweed Heads",
    "sg:classifiers":[
        {
            "category":"Shopping",
            "subcategory":"Beauty & Cosmetics",
            "type":"Retail Goods"
        }
    ],
    "sg:phone":"+61 1800 074 416",
    "sg:postcode":"2485",
    "sg:province":"NSW",
    "sg:tags":[
        "equipment",
        "salon",
        "supply"
    ],
    "wof:name":"Shaz",
    "wof:placetype":"venue"
},
  "geometry": {"coordinates":[153.53921508799999,-28.1804447174],"type":"Point"}
}