{
  "type": "Feature",
  "properties": {
    "addr:full":"199 Fison Ave Eagle Farm QLD 4009",
    "addr:housenumber":"199",
    "addr:postcode":"4009",
    "addr:street":"Fison Ave",
    "iso:country":"AU",
    "sg:address":"199 Fison Ave",
    "sg:city":"Eagle Farm",
    "sg:classifiers":[
        {
            "category":"Fast Food",
            "type":"Food & Drink"
        }
    ],
    "sg:phone":"+61 7 3268 4094",
    "sg:postcode":"4009",
    "sg:province":"QLD",
    "sg:tags":[
        "away",
        "take"
    ],
    "wof:name":"Fison Ave Takeaway",
    "wof:placetype":"venue"
},
  "geometry": {"coordinates":[153.092453003,-27.4366359711],"type":"Point"}
}