{
  "type": "Feature",
  "properties": {
    "addr:full":"Suite 2 39A Davies St Frankston VIC 3199",
    "addr:housenumber":"39a",
    "addr:postcode":"3199",
    "addr:street":"Davies St",
    "iso:country":"AU",
    "sg:address":"Suite 2 39A Davies St",
    "sg:city":"Frankston",
    "sg:classifiers":[
        {
            "category":"Insurance",
            "subcategory":"Insurance Agent",
            "type":"Services"
        }
    ],
    "sg:phone":"+61 3 9783 3166",
    "sg:postcode":"3199",
    "sg:province":"VIC",
    "sg:tags":[
        "underwriter",
        "life"
    ],
    "wof:name":"Gary J Wake Pty Ltd",
    "wof:placetype":"venue"
},
  "geometry": {"coordinates":[144.833084106,-37.8669548035],"type":"Point"}
}