{
  "type": "Feature",
  "properties": {
    "addr:full":"77 Mulgrave St South Launceston TAS 7249",
    "addr:housenumber":"77",
    "addr:postcode":"7249",
    "addr:street":"Mulgrave St",
    "iso:country":"AU",
    "sg:address":"77 Mulgrave St",
    "sg:city":"South Launceston",
    "sg:classifiers":[
        {
            "category":"Professional",
            "subcategory":"Accounting & Tax Preparation",
            "type":"Services"
        }
    ],
    "sg:phone":"+61 3 6343 7964",
    "sg:postcode":"7249",
    "sg:province":"TAS",
    "sg:tags":[
        "bookkeeping"
    ],
    "wof:name":"M&E Devlin",
    "wof:placetype":"venue"
},
  "geometry": {"coordinates":[147.14947509800001,-41.4522972107],"type":"Point"}
}