{
  "type": "Feature",
  "properties": {
    "iso:country":"AU",
    "sg:address":"35 Tuart Drv",
    "sg:city":"Baldivis",
    "sg:classifiers":[
        {
            "category":"Professional",
            "subcategory":"Computer Services",
            "type":"Services"
        }
    ],
    "sg:phone":"+61 8 9524 3502",
    "sg:postcode":"6171",
    "sg:province":"WA",
    "sg:tags":[
        "repairs",
        "upgrade",
        "equipment"
    ],
    "wof:name":"IT Services Pty Ltd",
    "wof:placetype":"venue"
},
  "geometry": {"coordinates":[115.800987,-32.369705],"type":"Point"}
}