{
  "type": "Feature",
  "properties": {
    "addr:full":"26 Dixon St Mt Druitt NSW 2770",
    "addr:housenumber":"26",
    "addr:postcode":"2770",
    "addr:street":"Dixon St Mt",
    "iso:country":"AU",
    "sg:address":"26 Dixon St",
    "sg:city":"Mt Druitt",
    "sg:classifiers":[
        {
            "category":"Professional",
            "subcategory":"Art Services",
            "type":"Services"
        }
    ],
    "sg:phone":"+61 410 405 040",
    "sg:postcode":"2770",
    "sg:province":"NSW",
    "sg:tags":[
        "decorator",
        "painter"
    ],
    "wof:name":"Proharts Painting",
    "wof:placetype":"venue"
},
  "geometry": {"coordinates":[150.822143555,-33.773311615],"type":"Point"}
}