{
  "type": "Feature",
  "properties": {
    "iso:country":"AU",
    "sg:address":"8/ 21 Barnhill Rd",
    "sg:city":"Terrigal",
    "sg:classifiers":[
        {
            "category":"Professional",
            "subcategory":"Art Services",
            "type":"Services"
        }
    ],
    "sg:phone":"+61 2 4384 7722",
    "sg:postcode":"2260",
    "sg:province":"NSW",
    "sg:tags":[
        "graphic",
        "designer"
    ],
    "wof:name":"Copp This Graphics",
    "wof:placetype":"venue"
},
  "geometry": {"coordinates":[151.441589,-33.444969],"type":"Point"}
}