{
  "type": "Feature",
  "properties": {
    "addr:full":"Lot 112 Zipfs Rd Alberton QLD 4207",
    "addr:postcode":"4207",
    "addr:street":"Zipfs Rd",
    "iso:country":"AU",
    "sg:address":"Lot 112 Zipfs Rd",
    "sg:city":"Alberton",
    "sg:classifiers":[
        {
            "category":"Home & Garden",
            "subcategory":"Garden Supply",
            "type":"Retail Goods"
        }
    ],
    "sg:phone":"+61 408 756 616",
    "sg:postcode":"4207",
    "sg:province":"QLD",
    "sg:tags":[
        "landscape"
    ],
    "wof:name":"Alberton Soils",
    "wof:placetype":"venue"
},
  "geometry": {"coordinates":[153.27107238799999,-27.7117004395],"type":"Point"}
}