{
  "type": "Feature",
  "properties": {
    "iso:country":"AU",
    "sg:address":"60 Molesworth St",
    "sg:city":"Lismore",
    "sg:classifiers":[
        {
            "category":"Shopping",
            "subcategory":"Clothing, Apparel, & Fashions",
            "type":"Retail Goods"
        }
    ],
    "sg:phone":"+61 2 6621 4478",
    "sg:postcode":"2480",
    "sg:province":"NSW",
    "sg:tags":[
        "lady",
        "wear"
    ],
    "wof:name":"No Rules",
    "wof:placetype":"venue"
},
  "geometry": {"coordinates":[153.276977539,-28.8073711395],"type":"Point"}
}