{
  "type": "Feature",
  "properties": {
    "addr:full":"Shop 8, The Mall Station St Seymour VIC 3660",
    "addr:housenumber":"shop 8",
    "addr:postcode":"3660",
    "addr:street":"The Mall Station St",
    "iso:country":"AU",
    "sg:address":"Shop 8, The Mall Station St",
    "sg:city":"Seymour",
    "sg:classifiers":[
        {
            "category":"Shopping",
            "subcategory":"Optical Goods",
            "type":"Retail Goods"
        }
    ],
    "sg:phone":"+61 3 5792 4053",
    "sg:postcode":"3660",
    "sg:province":"VIC",
    "sg:tags":[
        "dispenser",
        "prescription"
    ],
    "wof:name":"The Spectacle Site",
    "wof:placetype":"venue"
},
  "geometry": {"coordinates":[145.14187622099999,-37.0221672058],"type":"Point"}
}