{
  "type": "Feature",
  "properties": {
    "iso:country":"AU",
    "sg:address":"145 Canning Hwy",
    "sg:city":"South Perth",
    "sg:classifiers":[
        {
            "category":"Government",
            "subcategory":"Fire Station",
            "type":"Public Place"
        }
    ],
    "sg:phone":"+61 8 9368 0333",
    "sg:postcode":"6151",
    "sg:province":"WA",
    "sg:tags":[
        "equipment",
        "protection",
        "consultant"
    ],
    "wof:name":"Fire Design & Commissioning",
    "wof:placetype":"venue"
},
  "geometry": {"coordinates":[115.87545,-31.982792],"type":"Point"}
}