{
  "type": "Feature",
  "properties": {
    "addr:full":"36-38 Peck St Hamilton VIC 3300",
    "addr:housenumber":"36-38",
    "addr:postcode":"3300",
    "addr:street":"Peck St",
    "iso:country":"AU",
    "sg:address":"36-38 Peck St",
    "sg:city":"Hamilton",
    "sg:classifiers":[
        {
            "category":"Wholesale",
            "subcategory":"Machinery & Supplies",
            "type":"Manufacturing & Wholesale Goods"
        }
    ],
    "sg:phone":"+61 3 5571 2435",
    "sg:postcode":"3300",
    "sg:province":"VIC",
    "sg:tags":[
        "agricultural"
    ],
    "wof:name":"Moose Engineering",
    "wof:placetype":"venue"
},
  "geometry": {"coordinates":[142.00462341299999,-37.7258605957],"type":"Point"}
}