{
  "type": "Feature",
  "properties": {
    "addr:full":"48 Overlord Pl Acacia Ridge QLD 4110",
    "addr:housenumber":"48",
    "addr:postcode":"4110",
    "addr:street":"Overlord Pl",
    "iso:country":"AU",
    "sg:address":"48 Overlord Pl",
    "sg:city":"Acacia Ridge",
    "sg:classifiers":[
        {
            "category":"Food & Beverages",
            "subcategory":"Fruits & Vegetables",
            "type":"Retail Goods"
        }
    ],
    "sg:phone":"+61 7 3273 8334",
    "sg:postcode":"4110",
    "sg:province":"QLD",
    "sg:tags":[
        "wholesale"
    ],
    "wof:name":"Field Cuisine",
    "wof:placetype":"venue"
},
  "geometry": {"coordinates":[153.03781127900001,-27.5956821442],"type":"Point"}
}