{
  "type": "Feature",
  "properties": {
    "iso:country":"AU",
    "sg:address":"92 Hargreaves St",
    "sg:city":"Castlemaine",
    "sg:classifiers":[
        {
            "category":"Utilities",
            "subcategory":"Electric",
            "type":"Services"
        }
    ],
    "sg:phone":"+61 3 5472 2184",
    "sg:postcode":"3450",
    "sg:province":"VIC",
    "sg:tags":[
        "electrical",
        "contractor"
    ],
    "wof:name":"Lyons Pat",
    "wof:placetype":"venue"
},
  "geometry": {"coordinates":[144.220092773,-37.0627098083],"type":"Point"}
}