{
  "type": "Feature",
  "properties": {
    "addr:full":"Shop 1/ 920 Main Rd Hurstbridge VIC 3099",
    "addr:housenumber":"shop 1 / 920",
    "addr:postcode":"3099",
    "addr:street":"Main Rd",
    "iso:country":"AU",
    "sg:address":"Shop 1/ 920 Main Rd",
    "sg:city":"Hurstbridge",
    "sg:classifiers":[
        {
            "category":"Shopping",
            "subcategory":"Clothing, Apparel, & Fashions",
            "type":"Retail Goods"
        }
    ],
    "sg:phone":"+61 3 9718 2564",
    "sg:postcode":"3099",
    "sg:province":"VIC",
    "sg:tags":[
        "menswear"
    ],
    "wof:name":"Workin&#039; Clobber",
    "wof:placetype":"venue"
},
  "geometry": {"coordinates":[145.195114136,-37.637336731],"type":"Point"}
}