{
  "type": "Feature",
  "properties": {
    "iso:country":"AU",
    "sg:address":"983A North Rd",
    "sg:city":"Murrumbeena",
    "sg:classifiers":[
        {
            "category":"Arts & Performance",
            "subcategory":"Art Gallery",
            "type":"Entertainment"
        }
    ],
    "sg:phone":"+61 3 9570 6266",
    "sg:postcode":"3163",
    "sg:province":"VIC",
    "wof:name":"Innovative Art",
    "wof:placetype":"venue"
},
  "geometry": {"coordinates":[145.06838989299999,-37.9072647095],"type":"Point"}
}