{
  "type": "Feature",
  "properties": {
    "addr:full":"253-255 High St Ashburton VIC 3147",
    "addr:housenumber":"253-255",
    "addr:postcode":"3147",
    "addr:street":"High St",
    "iso:country":"AU",
    "sg:address":"253-255 High St",
    "sg:city":"Ashburton",
    "sg:classifiers":[
        {
            "category":"Shopping",
            "subcategory":"Clothing, Apparel, & Fashions",
            "type":"Retail Goods"
        }
    ],
    "sg:phone":"+61 3 9885 1650",
    "sg:postcode":"3147",
    "sg:province":"VIC",
    "sg:tags":[
        "lady",
        "wear"
    ],
    "wof:name":"Easy Going Pty Ltd",
    "wof:placetype":"venue"
},
  "geometry": {"coordinates":[145.07919311500001,-37.8632202148],"type":"Point"}
}