{
  "type": "Feature",
  "properties": {
    "addr:full":"230 Forge Creek Rd Bairnsdale VIC 3875",
    "addr:housenumber":"230",
    "addr:postcode":"3875",
    "addr:street":"Forge Creek Rd",
    "iso:country":"AU",
    "sg:address":"230 Forge Creek Rd",
    "sg:city":"Bairnsdale",
    "sg:classifiers":[
        {
            "category":"Building & Trades",
            "subcategory":"Plumbing",
            "type":"Services"
        }
    ],
    "sg:phone":"+61 3 5153 0183",
    "sg:postcode":"3875",
    "sg:province":"VIC",
    "sg:tags":[
        "plumber",
        "gasfitters"
    ],
    "wof:name":"D.M.B Plumber & Gasfitter",
    "wof:placetype":"venue"
},
  "geometry": {"coordinates":[147.65878295900001,-37.8985557556],"type":"Point"}
}