{
  "type": "Feature",
  "properties": {
    "addr:full":"2 Tonkin St Cronulla NSW 2230",
    "addr:housenumber":"2",
    "addr:postcode":"2230",
    "addr:street":"Tonkin St",
    "iso:country":"AU",
    "sg:address":"2 Tonkin St",
    "sg:city":"Cronulla",
    "sg:classifiers":[
        {
            "category":"Recreation",
            "subcategory":"Marina",
            "type":"Entertainment"
        }
    ],
    "sg:phone":"+61 2 9544 0888",
    "sg:postcode":"2230",
    "sg:province":"NSW",
    "wof:name":"Cronulla Marina",
    "wof:placetype":"venue"
},
  "geometry": {"coordinates":[151.15080261200001,-34.0550842285],"type":"Point"}
}