{
  "type": "Feature",
  "properties": {
    "iso:country":"AU",
    "sg:address":"25 Buckley St",
    "sg:city":"Cockburn Central",
    "sg:classifiers":[
        {
            "category":"Building & Trades",
            "subcategory":"Plumbing",
            "type":"Services"
        }
    ],
    "sg:phone":"+61 8 9414 7651",
    "sg:postcode":"6164",
    "sg:province":"WA",
    "sg:tags":[
        "pipe",
        "fabricator"
    ],
    "wof:name":"Wilsons Pipe Fabrication",
    "wof:placetype":"venue"
},
  "geometry": {"coordinates":[115.84317,-32.120068],"type":"Point"}
}