{
  "type": "Feature",
  "properties": {
    "addr:full":"Unit 4, 165 Old Pacific Hwy Oxenford QLD 4210",
    "addr:housenumber":"165",
    "addr:postcode":"4210",
    "addr:street":"Old Pacific Hwy",
    "iso:country":"AU",
    "sg:address":"Unit 4, 165 Old Pacific Hwy",
    "sg:city":"Oxenford",
    "sg:classifiers":[
        {
            "category":"Home & Garden",
            "subcategory":"Building Materials",
            "type":"Retail Goods"
        }
    ],
    "sg:phone":"+61 7 5573 4837",
    "sg:postcode":"4210",
    "sg:province":"QLD",
    "sg:tags":[
        "anti-corrosive",
        "composition",
        "flooring"
    ],
    "wof:name":"Southeast Floors",
    "wof:placetype":"venue"
},
  "geometry": {"coordinates":[153.31350707999999,-27.8899726868],"type":"Point"}
}