{
  "type": "Feature",
  "properties": {
    "addr:full":"14 Warringah St North Balgowlah NSW 2093",
    "addr:housenumber":"14",
    "addr:postcode":"2093",
    "addr:street":"Warringah St",
    "iso:country":"AU",
    "sg:address":"14 Warringah St",
    "sg:city":"North Balgowlah",
    "sg:classifiers":[
        {
            "category":"Food & Beverages",
            "subcategory":"Specialty",
            "type":"Retail Goods"
        }
    ],
    "sg:phone":"+61 1300 301 738",
    "sg:postcode":"2093",
    "sg:province":"NSW",
    "sg:tags":[
        "product",
        "health"
    ],
    "wof:name":"Juice Plus",
    "wof:placetype":"venue"
},
  "geometry": {"coordinates":[151.24986267099999,-33.7833747864],"type":"Point"}
}