{
  "type": "Feature",
  "properties": {
    "iso:country":"AU",
    "sg:address":"7 Painter Pl",
    "sg:city":"Palmerston",
    "sg:classifiers":[
        {
            "category":"Professional",
            "subcategory":"Secretarial Services",
            "type":"Services"
        }
    ],
    "sg:phone":"+61 2 6241 7700",
    "sg:postcode":"2913",
    "sg:province":"ACT",
    "sg:tags":[
        "typing"
    ],
    "wof:name":"Canberra Secretarial Services",
    "wof:placetype":"venue"
},
  "geometry": {"coordinates":[149.121002197,-35.1885528564],"type":"Point"}
}