{
  "type": "Feature",
  "properties": {
    "addr:full":"139 Church St Wollongong NSW 2500",
    "addr:housenumber":"139",
    "addr:postcode":"2500",
    "addr:street":"Church St",
    "iso:country":"AU",
    "sg:address":"139 Church St",
    "sg:city":"Wollongong",
    "sg:classifiers":[
        {
            "category":"Personal",
            "subcategory":"Beauty Salon",
            "type":"Services"
        }
    ],
    "sg:phone":"+61 410 698 604",
    "sg:postcode":"2500",
    "sg:province":"NSW",
    "wof:name":"Making Faces",
    "wof:placetype":"venue"
},
  "geometry": {"coordinates":[150.89447000000001,-34.429798],"type":"Point"}
}