{
  "type": "Feature",
  "properties": {
    "addr:full":"16 Ferry St Hunters Hill NSW 2110",
    "addr:housenumber":"16",
    "addr:postcode":"2110",
    "addr:street":"Ferry St",
    "iso:country":"AU",
    "sg:address":"16 Ferry St",
    "sg:city":"Hunters Hill",
    "sg:classifiers":[
        {
            "category":"Real Estate",
            "subcategory":"Real Estate Agent",
            "type":"Services"
        }
    ],
    "sg:phone":"+61 2 9816 3622",
    "sg:postcode":"2110",
    "sg:province":"NSW",
    "wof:name":"Century 21 Maureen Smith Real Estate",
    "wof:placetype":"venue"
},
  "geometry": {"coordinates":[151.15562439000001,-33.8369636536],"type":"Point"}
}