{
  "type": "Feature",
  "properties": {
    "addr:full":"23 Lansdowne St East Melbourne VIC 3002",
    "addr:housenumber":"23",
    "addr:postcode":"3002",
    "addr:street":"Lansdowne St",
    "iso:country":"AU",
    "sg:address":"23 Lansdowne St",
    "sg:city":"East Melbourne",
    "sg:classifiers":[
        {
            "category":"Fast Food",
            "type":"Food & Drink"
        }
    ],
    "sg:phone":"+61 3 9662 1014",
    "sg:postcode":"3002",
    "sg:province":"VIC",
    "sg:tags":[
        "away",
        "take"
    ],
    "wof:name":"Cafe Lansdowne",
    "wof:placetype":"venue"
},
  "geometry": {"coordinates":[144.97828674300001,-37.8090171814],"type":"Point"}
}