{
  "type": "Feature",
  "properties": {
    "addr:full":"59 Greenbank Rd Stratford QLD 4870",
    "addr:housenumber":"59",
    "addr:postcode":"4870",
    "addr:street":"Greenbank Rd",
    "iso:country":"AU",
    "sg:address":"59 Greenbank Rd",
    "sg:city":"Stratford",
    "sg:classifiers":[
        {
            "category":"Building & Trades",
            "subcategory":"Equipment Rental",
            "type":"Services"
        }
    ],
    "sg:phone":"+61 408 772 035",
    "sg:postcode":"4870",
    "sg:province":"QLD",
    "sg:tags":[
        "platform",
        "hire",
        "work",
        "elevating"
    ],
    "wof:name":"Crossy's Crane Hire",
    "wof:placetype":"venue"
},
  "geometry": {"coordinates":[145.73915100100001,-16.8692989349],"type":"Point"}
}