{
  "type": "Feature",
  "properties": {
    "iso:country":"AU",
    "sg:address":"Shop 1 134 Thompson Ave",
    "sg:city":"Cowes",
    "sg:classifiers":[
        {
            "category":"Personal",
            "subcategory":"Beauty Salon",
            "type":"Services"
        }
    ],
    "sg:phone":"+61 3 5952 1258",
    "sg:postcode":"3922",
    "sg:province":"VIC",
    "sg:tags":[
        "hairdresser"
    ],
    "wof:name":"Cowes Hairdressing and Waxing",
    "wof:placetype":"venue"
},
  "geometry": {"coordinates":[145.23880004899999,-38.4540100098],"type":"Point"}
}