{
  "type": "Feature",
  "properties": {
    "iso:country":"AU",
    "sg:address":"46 Through St",
    "sg:city":"South Grafton",
    "sg:classifiers":[
        {
            "category":"Home & Garden",
            "subcategory":"Household Appliances",
            "type":"Retail Goods"
        }
    ],
    "sg:phone":"+61 2 6642 6722",
    "sg:postcode":"2460",
    "sg:province":"NSW",
    "sg:tags":[
        "equipment",
        "gas"
    ],
    "wof:name":"Clarence Valley Gas",
    "wof:placetype":"venue"
},
  "geometry": {"coordinates":[152.93870544399999,-29.7029781342],"type":"Point"}
}