{
  "type": "Feature",
  "properties": {
    "addr:full":"283 Trower Rd Casuarina NT 0810",
    "addr:housenumber":"283",
    "addr:postcode":"nt 0810",
    "addr:street":"Trower Rd",
    "iso:country":"AU",
    "sg:address":"283 Trower Rd",
    "sg:city":"Casuarina",
    "sg:classifiers":[
        {
            "category":"Shopping",
            "subcategory":"Computers & Home Electronics",
            "type":"Retail Goods"
        }
    ],
    "sg:phone":"+61 8 8928 0890",
    "sg:postcode":"0810",
    "sg:province":"NT",
    "sg:tags":[
        "equipment",
        "part",
        "electronic"
    ],
    "wof:name":"Dick Smith Electronics",
    "wof:placetype":"venue"
},
  "geometry": {"coordinates":[130.883666992,-12.3722572327],"type":"Point"}
}