{
  "type": "Feature",
  "properties": {
    "addr:full":"23 Cuthbert Crs Vincent QLD 4814",
    "addr:housenumber":"23",
    "addr:postcode":"4814",
    "addr:street":"Cuthbert Crs Vincent",
    "iso:country":"AU",
    "sg:address":"23 Cuthbert Crs",
    "sg:city":"Vincent",
    "sg:classifiers":[
        {
            "category":"Building & Trades",
            "subcategory":"Construction",
            "type":"Services"
        }
    ],
    "sg:phone":"+61 419 041 150",
    "sg:postcode":"4814",
    "sg:province":"QLD",
    "sg:tags":[
        "concrete",
        "contractor"
    ],
    "wof:name":"Readyset Concrete",
    "wof:placetype":"venue"
},
  "geometry": {"coordinates":[146.76797500000001,-19.28476],"type":"Point"}
}