{
  "type": "Feature",
  "properties": {
    "addr:full":"178 Old Maryborough Rd Gympie QLD 4570",
    "addr:housenumber":"178",
    "addr:postcode":"4570",
    "addr:street":"Old Maryborough Rd",
    "iso:country":"AU",
    "sg:address":"178 Old Maryborough Rd",
    "sg:city":"Gympie",
    "sg:classifiers":[
        {
            "category":"Commercial Area",
            "type":"Public Place"
        }
    ],
    "sg:phone":"+61 7 5482 3702",
    "sg:postcode":"4570",
    "sg:province":"QLD",
    "sg:tags":[
        "heavy",
        "carrier"
    ],
    "wof:name":"Smillie's Truck and Crane Hire",
    "wof:placetype":"venue"
},
  "geometry": {"coordinates":[152.671585083,-26.1740016937],"type":"Point"}
}