{
  "type": "Feature",
  "properties": {
    "addr:full":"6 Ashton Ave Chester Hill NSW 2162",
    "addr:housenumber":"6",
    "addr:postcode":"2162",
    "addr:street":"Ashton Ave",
    "iso:country":"AU",
    "sg:address":"6 Ashton Ave",
    "sg:city":"Chester Hill",
    "sg:classifiers":[
        {
            "category":"Professional",
            "subcategory":"Engineering",
            "type":"Services"
        }
    ],
    "sg:phone":"+61 2 9743 7039",
    "sg:postcode":"2162",
    "sg:province":"NSW",
    "sg:tags":[
        "electronic",
        "engineer"
    ],
    "wof:name":"Unitec Australia Pty Ltd",
    "wof:placetype":"venue"
},
  "geometry": {"coordinates":[150.996856689,-33.8773117065],"type":"Point"}
}