{
  "type": "Feature",
  "properties": {
    "iso:country":"AU",
    "sg:address":"PO Box 2262",
    "sg:city":"Tuggeranong",
    "sg:classifiers":[
        {
            "category":"Professional",
            "type":"Services"
        }
    ],
    "sg:phone":"+61 412 624 710",
    "sg:postcode":"2900",
    "sg:province":"ACT",
    "sg:tags":[
        "transport"
    ],
    "wof:name":"JDT Tilt Tray Service",
    "wof:placetype":"venue"
},
  "geometry": {"coordinates":[149.065795898,-35.4151611328],"type":"Point"}
}