{
  "type": "Feature",
  "properties": {
    "iso:country":"AU",
    "sg:address":"Shop 204 Warringah Mall Pittwater Rd",
    "sg:city":"Brookvale",
    "sg:classifiers":[
        {
            "category":"Shopping",
            "subcategory":"Shoes",
            "type":"Retail Goods"
        }
    ],
    "sg:phone":"+61 2 9939 5081",
    "sg:postcode":"2100",
    "sg:province":"NSW",
    "sg:tags":[
        "footwear"
    ],
    "wof:name":"Nine West Australia",
    "wof:placetype":"venue"
},
  "geometry": {"coordinates":[151.27305602999999,-33.7611312866],"type":"Point"}
}