{
  "type": "Feature",
  "properties": {
    "addr:full":"2 Commerce St Salisbury QLD 4107",
    "addr:housenumber":"2",
    "addr:postcode":"4107",
    "addr:street":"Commerce St",
    "iso:country":"AU",
    "sg:address":"2 Commerce St",
    "sg:city":"Salisbury",
    "sg:classifiers":[
        {
            "category":"Home & Garden",
            "subcategory":"Hardware",
            "type":"Retail Goods"
        }
    ],
    "sg:phone":"+61 7 3277 1241",
    "sg:postcode":"4107",
    "sg:province":"QLD",
    "sg:tags":[
        "woodworking",
        "machinery"
    ],
    "wof:name":"Wattle Products",
    "wof:placetype":"venue"
},
  "geometry": {"coordinates":[153.02972412099999,-27.5428256989],"type":"Point"}
}