{
  "type": "Feature",
  "properties": {
    "addr:full":"87 Waples Rd Unanderra NSW 2526",
    "addr:housenumber":"87",
    "addr:postcode":"2526",
    "addr:street":"Waples Rd",
    "iso:country":"AU",
    "sg:address":"87 Waples Rd",
    "sg:city":"Unanderra",
    "sg:classifiers":[
        {
            "category":"Building & Trades",
            "subcategory":"Plumbing",
            "type":"Services"
        }
    ],
    "sg:phone":"+61 2 4271 3116",
    "sg:postcode":"2526",
    "sg:province":"NSW",
    "sg:tags":[
        "plumber",
        "gasfitters"
    ],
    "wof:name":"Farmborough Plumbing",
    "wof:placetype":"venue"
},
  "geometry": {"coordinates":[150.830474853,-34.4559326172],"type":"Point"}
}