{
  "type": "Feature",
  "properties": {
    "addr:full":"18 Holmes Drv Beaconsfield QLD 4740",
    "addr:housenumber":"18",
    "addr:postcode":"4740",
    "addr:street":"Holmes Drv",
    "iso:country":"AU",
    "sg:address":"18 Holmes Drv",
    "sg:city":"Beaconsfield",
    "sg:classifiers":[
        {
            "category":"Home & Garden",
            "subcategory":"Carpets & Floor Coverings",
            "type":"Retail Goods"
        }
    ],
    "sg:phone":"+61 7 4942 4128",
    "sg:postcode":"4740",
    "sg:province":"QLD",
    "sg:tags":[
        "layer",
        "planner"
    ],
    "wof:name":"Julyan CM & DB",
    "wof:placetype":"venue"
},
  "geometry": {"coordinates":[149.16490200000001,-21.102417],"type":"Point"}
}