{
  "type": "Feature",
  "properties": {
    "addr:full":"220 River St Ballina NSW 2478",
    "addr:housenumber":"220",
    "addr:postcode":"2478",
    "addr:street":"River St",
    "iso:country":"AU",
    "sg:address":"220 River St",
    "sg:city":"Ballina",
    "sg:classifiers":[
        {
            "category":"Fast Food",
            "type":"Food & Drink"
        }
    ],
    "sg:phone":"+61 2 6686 6336",
    "sg:postcode":"2478",
    "sg:province":"NSW",
    "sg:tags":[
        "away",
        "take"
    ],
    "wof:name":"Raamon's Dial-A-Pizza",
    "wof:placetype":"venue"
},
  "geometry": {"coordinates":[153.557662964,-28.8694648743],"type":"Point"}
}