{
  "type": "Feature",
  "properties": {
    "addr:full":"28 Greenhill Rd Goodwood SA 5034",
    "addr:housenumber":"28",
    "addr:postcode":"5034",
    "addr:street":"Greenhill Rd",
    "iso:country":"AU",
    "sg:address":"28 Greenhill Rd",
    "sg:city":"Goodwood",
    "sg:classifiers":[
        {
            "category":"Professional",
            "subcategory":"Management & Consulting",
            "type":"Services"
        }
    ],
    "sg:phone":"+61 413 755 153",
    "sg:postcode":"5034",
    "sg:province":"SA",
    "sg:tags":[
        "consultant"
    ],
    "wof:name":"Food & Hospitality Solutions",
    "wof:placetype":"venue"
},
  "geometry": {"coordinates":[138.58840942399999,-34.9421005249],"type":"Point"}
}