{
  "type": "Feature",
  "properties": {
    "addr:full":"71 South Rd Hindmarsh SA 5007",
    "addr:housenumber":"71",
    "addr:postcode":"5007",
    "addr:street":"South Rd",
    "iso:country":"AU",
    "sg:address":"71 South Rd",
    "sg:city":"Hindmarsh",
    "sg:classifiers":[
        {
            "category":"Building & Trades",
            "subcategory":"Equipment Rental",
            "type":"Services"
        }
    ],
    "sg:phone":"+61 8 8346 4553",
    "sg:postcode":"5007",
    "sg:province":"SA",
    "sg:tags":[
        "demolition",
        "contractor"
    ],
    "wof:name":"S A Demolition & Salvage Pty Ltd",
    "wof:placetype":"venue"
},
  "geometry": {"coordinates":[138.56562805199999,-34.9065284729],"type":"Point"}
}