{
  "type": "Feature",
  "properties": {
    "addr:full":"Lvl 1, 37B Alexandra St Hunters Hill NSW 2110",
    "addr:housenumber":"37b",
    "addr:postcode":"2110",
    "addr:street":"Alexandra St",
    "iso:country":"AU",
    "sg:address":"Lvl 1, 37B Alexandra St",
    "sg:city":"Hunters Hill",
    "sg:classifiers":[
        {
            "category":"Professional",
            "subcategory":"Business Services",
            "type":"Services"
        }
    ],
    "sg:phone":"+61 2 9879 5567",
    "sg:postcode":"2110",
    "sg:province":"NSW",
    "sg:tags":[
        "broker"
    ],
    "wof:name":"Dunross Business Services Pty Ltd",
    "wof:placetype":"venue"
},
  "geometry": {"coordinates":[151.15565490700001,-33.8351478577],"type":"Point"}
}