{
  "type": "Feature",
  "properties": {
    "addr:full":"21 Boundary St Kalgoorlie WA 6430",
    "addr:housenumber":"21",
    "addr:postcode":"6430",
    "addr:street":"Boundary St",
    "iso:country":"AU",
    "sg:address":"21 Boundary St",
    "sg:city":"Kalgoorlie",
    "sg:classifiers":[
        {
            "category":"Communications",
            "type":"Services"
        }
    ],
    "sg:phone":"+61 8 9021 8177",
    "sg:postcode":"6430",
    "sg:province":"WA",
    "sg:tags":[
        "public",
        "system",
        "address"
    ],
    "wof:name":"Rentkal",
    "wof:placetype":"venue"
},
  "geometry": {"coordinates":[121.476387024,-30.7567768097],"type":"Point"}
}