{
  "type": "Feature",
  "properties": {
    "addr:full":"110 Casino St South Lismore NSW 2480",
    "addr:housenumber":"110",
    "addr:postcode":"2480",
    "addr:street":"Casino St South",
    "iso:country":"AU",
    "sg:address":"110 Casino St",
    "sg:city":"South Lismore",
    "sg:classifiers":[
        {
            "category":"Home & Garden",
            "subcategory":"Carpets & Floor Coverings",
            "type":"Retail Goods"
        }
    ],
    "sg:phone":"+61 2 6621 4333",
    "sg:postcode":"2480",
    "sg:province":"NSW",
    "sg:tags":[
        "mat",
        "matting"
    ],
    "wof:name":"Dennys Upholstery",
    "wof:placetype":"venue"
},
  "geometry": {"coordinates":[153.26046752900001,-28.8078308105],"type":"Point"}
}