{
  "type": "Feature",
  "properties": {
    "addr:full":"95 South Lake Drv South Lake WA 6164",
    "addr:housenumber":"95",
    "addr:postcode":"6164",
    "addr:street":"South Lake Drv",
    "iso:country":"AU",
    "sg:address":"95 South Lake Drv",
    "sg:city":"South Lake",
    "sg:classifiers":[
        {
            "category":"Building & Trades",
            "subcategory":"Construction",
            "type":"Services"
        }
    ],
    "sg:phone":"+61 422 648 889",
    "sg:postcode":"6164",
    "sg:province":"WA",
    "sg:tags":[
        "fencing",
        "contractor"
    ],
    "wof:name":"Rapid Fencing",
    "wof:placetype":"venue"
},
  "geometry": {"coordinates":[115.844688,-32.107506],"type":"Point"}
}