{
  "type": "Feature",
  "properties": {
    "addr:full":"3/ 6 Kennedy St Kingston ACT 2604",
    "addr:housenumber":"/ 6",
    "addr:postcode":"2604",
    "addr:street":"Kennedy St",
    "iso:country":"AU",
    "sg:address":"3/ 6 Kennedy St",
    "sg:city":"Kingston",
    "sg:classifiers":[
        {
            "category":"Social Services",
            "subcategory":"Retirement Home",
            "type":"Services"
        }
    ],
    "sg:phone":"+61 2 6260 6200",
    "sg:postcode":"2604",
    "sg:province":"ACT",
    "sg:tags":[
        "environmental",
        "consultant",
        "pollution"
    ],
    "wof:name":"DASCEM Holdings Pty Limited",
    "wof:placetype":"venue"
},
  "geometry": {"coordinates":[149.14024352999999,-35.3164176941],"type":"Point"}
}