{
  "type": "Feature",
  "properties": {
    "addr:full":"Shp8/ 56 Kalang Rd Elanora Heights NSW 2101",
    "addr:postcode":"2101",
    "addr:street":"Kalang Rd",
    "iso:country":"AU",
    "sg:address":"Shp8/ 56 Kalang Rd",
    "sg:city":"Elanora Heights",
    "sg:classifiers":[
        {
            "category":"Personal",
            "subcategory":"Barber",
            "type":"Services"
        }
    ],
    "sg:phone":"+61 2 9913 8887",
    "sg:postcode":"2101",
    "sg:province":"NSW",
    "wof:name":"Svetlana's Barber Shop",
    "wof:placetype":"venue"
},
  "geometry": {"coordinates":[151.27981600000001,-33.695778],"type":"Point"}
}