{
  "type": "Feature",
  "properties": {
    "iso:country":"AU",
    "sg:address":"42 Neil St",
    "sg:city":"Toowoomba",
    "sg:classifiers":[
        {
            "category":"Education",
            "subcategory":"Special Training",
            "type":"Public Place"
        }
    ],
    "sg:phone":"+61 7 4688 9300",
    "sg:postcode":"4350",
    "sg:province":"QLD",
    "sg:tags":[
        "development"
    ],
    "wof:name":"Centacare Employment",
    "wof:placetype":"venue"
},
  "geometry": {"coordinates":[151.955765,-27.56082],"type":"Point"}
}