{
  "type": "Feature",
  "properties": {
    "addr:full":"37 Samuel St Smithfield SA 5114",
    "addr:housenumber":"37",
    "addr:postcode":"5114",
    "addr:street":"Samuel St",
    "iso:country":"AU",
    "sg:address":"37 Samuel St",
    "sg:city":"Smithfield",
    "sg:classifiers":[
        {
            "category":"Retail",
            "subcategory":"Storage",
            "type":"Services"
        }
    ],
    "sg:phone":"+61 8 8284 1089",
    "sg:postcode":"5114",
    "sg:province":"SA",
    "sg:tags":[
        "removal",
        "furniture"
    ],
    "wof:name":"J.W. Removals",
    "wof:placetype":"venue"
},
  "geometry": {"coordinates":[138.68598938,-34.6782951355],"type":"Point"}
}