{
  "type": "Feature",
  "properties": {
    "addr:full":"67 Hampton St Bridgetown WA 6255",
    "addr:housenumber":"67",
    "addr:postcode":"6255",
    "addr:street":"Hampton St",
    "iso:country":"AU",
    "sg:address":"67 Hampton St",
    "sg:city":"Bridgetown",
    "sg:classifiers":[
        {
            "category":"Autos & Motor Vehicles",
            "subcategory":"Fuel & Gas Station",
            "type":"Retail Goods"
        }
    ],
    "sg:phone":"+61 8 9761 1377",
    "sg:postcode":"6255",
    "sg:province":"WA",
    "wof:name":"Caltex",
    "wof:placetype":"venue"
},
  "geometry": {"coordinates":[116.13703918500001,-33.9578285217],"type":"Point"}
}