{
  "type": "Feature",
  "properties": {
    "addr:full":"3 Carawa Drv Reservoir VIC 3073",
    "addr:housenumber":"3",
    "addr:postcode":"3073",
    "addr:street":"Carawa Drv",
    "iso:country":"AU",
    "sg:address":"3 Carawa Drv",
    "sg:city":"Reservoir",
    "sg:classifiers":[
        {
            "category":"Farming",
            "subcategory":"Farm & Veterinary Services",
            "type":"Manufacturing & Wholesale Goods"
        }
    ],
    "sg:phone":"+61 3 9462 0340",
    "sg:postcode":"3073",
    "sg:province":"VIC",
    "sg:tags":[
        "seedsman"
    ],
    "wof:name":"Advanced Seeds & Packaging Pty Ltd",
    "wof:placetype":"venue"
},
  "geometry": {"coordinates":[144.978607178,-37.7205123901],"type":"Point"}
}