{
  "type": "Feature",
  "properties": {
    "addr:full":"K Mart Entrance Shop 70, Bazaar St Robina Town Centre QLD 4230",
    "addr:housenumber":"70",
    "addr:postcode":"4230",
    "addr:street":"Bazaar St",
    "iso:country":"AU",
    "sg:address":"K Mart Entrance Shop 70, Bazaar St",
    "sg:city":"Robina Town Centre",
    "sg:classifiers":[
        {
            "category":"Real Estate",
            "subcategory":"Real Estate Agent",
            "type":"Services"
        }
    ],
    "sg:phone":"+61 7 5562 1411",
    "sg:postcode":"4230",
    "sg:province":"QLD",
    "wof:name":"L J Hooker",
    "wof:placetype":"venue"
},
  "geometry": {"coordinates":[153.38531494099999,-28.0774707794],"type":"Point"}
}