{
  "type": "Feature",
  "properties": {
    "addr:full":"PO Box 438 Miami QLD 4220",
    "addr:postcode":"4220",
    "iso:country":"AU",
    "sg:address":"PO Box 438",
    "sg:city":"Miami",
    "sg:classifiers":[
        {
            "category":"Utilities",
            "subcategory":"Sewage",
            "type":"Services"
        }
    ],
    "sg:phone":"+61 7 5576 7049",
    "sg:postcode":"4220",
    "sg:province":"QLD",
    "sg:tags":[
        "arboriculturist"
    ],
    "wof:name":"Terra Ark",
    "wof:placetype":"venue"
},
  "geometry": {"coordinates":[153.443893433,-28.07264328],"type":"Point"}
}