{
  "type": "Feature",
  "properties": {
    "addr:full":"25 Mill Rd Busselton WA 6280",
    "addr:housenumber":"25",
    "addr:postcode":"6280",
    "addr:street":"Mill Rd",
    "iso:country":"AU",
    "sg:address":"25 Mill Rd",
    "sg:city":"Busselton",
    "sg:classifiers":[
        {
            "category":"Health Services",
            "subcategory":"Dentist",
            "type":"Services"
        }
    ],
    "sg:phone":"+61 8 9754 3800",
    "sg:postcode":"6280",
    "sg:province":"WA",
    "wof:name":"Busselton Government Dental Clinic",
    "wof:placetype":"venue"
},
  "geometry": {"coordinates":[115.321739197,-33.6534690857],"type":"Point"}
}