{
  "type": "Feature",
  "properties": {
    "addr:full":"Yea Rd Tallarook VIC 3659",
    "addr:postcode":"3659",
    "addr:street":"Yea Rd",
    "iso:country":"AU",
    "sg:address":"Yea Rd",
    "sg:city":"Tallarook",
    "sg:classifiers":[
        {
            "category":"Home & Garden",
            "subcategory":"Building Materials",
            "type":"Retail Goods"
        }
    ],
    "sg:phone":"+61 3 5792 1269",
    "sg:postcode":"3659",
    "sg:province":"VIC",
    "sg:tags":[
        "concrete",
        "gutter",
        "kerb"
    ],
    "wof:name":"Les Bell Contracting",
    "wof:placetype":"venue"
},
  "geometry": {"coordinates":[145.100631714,-37.0982894897],"type":"Point"}
}