{
  "type": "Feature",
  "properties": {
    "iso:country":"AU",
    "sg:address":"Shop 10A Brandon Park Shopping Centre Springvale R",
    "sg:city":"Wheelers Hill",
    "sg:classifiers":[
        {
            "category":"Travel",
            "subcategory":"Travel Agent",
            "type":"Entertainment"
        }
    ],
    "sg:phone":"+61 13 18 66",
    "sg:postcode":"3150",
    "sg:province":"VIC",
    "sg:tags":[
        "consultant"
    ],
    "wof:name":"Flight Centre",
    "wof:placetype":"venue"
},
  "geometry": {"coordinates":[145.16229248100001,-37.9005088806],"type":"Point"}
}