{
  "type": "Feature",
  "properties": {
    "iso:country":"AU",
    "sg:address":"Shop 19",
    "sg:city":"Hibiscus Shopping Town, Leanyer",
    "sg:classifiers":[
        {
            "category":"Shopping",
            "subcategory":"Optical Goods",
            "type":"Retail Goods"
        }
    ],
    "sg:phone":"+61 8 8927 5139",
    "sg:postcode":"0812",
    "sg:province":"NT",
    "sg:tags":[
        "supply"
    ],
    "wof:name":"Territory Optical Service",
    "wof:placetype":"venue"
},
  "geometry": {"coordinates":[130.89193700000001,-12.37749],"type":"Point"}
}