{
  "type": "Feature",
  "properties": {
    "iso:country":"AU",
    "sg:address":"772 Beaudesert Rd",
    "sg:city":"Coopers Plains",
    "sg:classifiers":[
        {
            "category":"Home & Garden",
            "subcategory":"Home Furnishings",
            "type":"Retail Goods"
        }
    ],
    "sg:phone":"+61 7 3890 2758",
    "sg:postcode":"4108",
    "sg:province":"QLD",
    "sg:tags":[
        "shower",
        "screen"
    ],
    "wof:name":"Showermate Showerscreens",
    "wof:placetype":"venue"
},
  "geometry": {"coordinates":[153.020996094,-27.5585575104],"type":"Point"}
}