{
  "type": "Feature",
  "properties": {
    "iso:country":"AU",
    "sg:address":"61 Watson St",
    "sg:city":"Molong",
    "sg:classifiers":[
        {
            "category":"Wholesale",
            "subcategory":"Machinery & Supplies",
            "type":"Manufacturing & Wholesale Goods"
        }
    ],
    "sg:phone":"+61 2 6366 9494",
    "sg:postcode":"2866",
    "sg:province":"NSW",
    "sg:tags":[
        "equipment",
        "welding"
    ],
    "wof:name":"Nelco Trading",
    "wof:placetype":"venue"
},
  "geometry": {"coordinates":[148.86888099999999,-33.092079],"type":"Point"}
}