{
  "type": "Feature",
  "properties": {
    "addr:full":"55 Jerrabomberra Ave Narrabundah ACT 2604",
    "addr:housenumber":"55",
    "addr:postcode":"2604",
    "addr:street":"Jerrabomberra Ave",
    "iso:country":"AU",
    "sg:address":"55 Jerrabomberra Ave",
    "sg:city":"Narrabundah",
    "sg:classifiers":[
        {
            "category":"Travel",
            "subcategory":"Hotels & Motels",
            "type":"Entertainment"
        }
    ],
    "sg:phone":"+61 2 6295 3322",
    "sg:postcode":"2604",
    "sg:province":"ACT",
    "wof:name":"Garden City Motel",
    "wof:placetype":"venue"
},
  "geometry": {"coordinates":[149.14808654800001,-35.3354110718],"type":"Point"}
}