{
  "type": "Feature",
  "properties": {
    "addr:full":"1 Haugh Pl Oxley ACT 2903",
    "addr:housenumber":"1",
    "addr:postcode":"2903",
    "addr:street":"Haugh Pl",
    "iso:country":"AU",
    "sg:address":"1 Haugh Pl",
    "sg:city":"Oxley",
    "sg:classifiers":[
        {
            "category":"Utilities",
            "subcategory":"Electric",
            "type":"Services"
        }
    ],
    "sg:phone":"+61 419 464 062",
    "sg:postcode":"2903",
    "sg:province":"ACT",
    "sg:tags":[
        "electrical",
        "contractor"
    ],
    "wof:name":"Sovereign All Trades",
    "wof:placetype":"venue"
},
  "geometry": {"coordinates":[149.07435607900001,-35.4102554321],"type":"Point"}
}