{
  "type": "Feature",
  "properties": {
    "addr:full":"147 Crockford St Northgate QLD 4013",
    "addr:housenumber":"147",
    "addr:postcode":"4013",
    "addr:street":"Crockford St",
    "iso:country":"AU",
    "sg:address":"147 Crockford St",
    "sg:city":"Northgate",
    "sg:classifiers":[
        {
            "category":"Wholesale",
            "subcategory":"Scrap",
            "type":"Manufacturing & Wholesale Goods"
        }
    ],
    "sg:phone":"+61 7 3260 6300",
    "sg:postcode":"4013",
    "sg:province":"QLD",
    "sg:tags":[
        "merchant",
        "metal"
    ],
    "wof:name":"The Recycling Warehouse",
    "wof:placetype":"venue"
},
  "geometry": {"coordinates":[153.06671142600001,-27.3862419128],"type":"Point"}
}