{
  "type": "Feature",
  "properties": {
    "addr:full":"5 Nicol St McLaren Vale SA 5171",
    "addr:housenumber":"5",
    "addr:postcode":"5171",
    "addr:street":"Nicol St",
    "iso:country":"AU",
    "sg:address":"5 Nicol St",
    "sg:city":"McLaren Vale",
    "sg:classifiers":[
        {
            "category":"Retail",
            "subcategory":"Auto Repair",
            "type":"Services"
        }
    ],
    "sg:phone":"+61 8 8323 9669",
    "sg:postcode":"5171",
    "sg:province":"SA",
    "sg:tags":[
        "body",
        "motor",
        "trimmer"
    ],
    "wof:name":"McLaren Vale Vehicle And Marine Upholstery",
    "wof:placetype":"venue"
},
  "geometry": {"coordinates":[138.54411315900001,-35.2181549072],"type":"Point"}
}