{
  "type": "Feature",
  "properties": {
    "addr:full":"55 Kew St Welshpool WA 6106",
    "addr:housenumber":"55",
    "addr:postcode":"6106",
    "addr:street":"Kew St",
    "iso:country":"AU",
    "sg:address":"55 Kew St",
    "sg:city":"Welshpool",
    "sg:classifiers":[
        {
            "category":"Professional",
            "subcategory":"Engineering",
            "type":"Services"
        }
    ],
    "sg:phone":"+61 8 9362 2555",
    "sg:postcode":"6106",
    "sg:province":"WA",
    "sg:tags":[
        "manufacturing",
        "engineer"
    ],
    "wof:name":"Furlan Engineering",
    "wof:placetype":"venue"
},
  "geometry": {"coordinates":[115.933029175,-31.9839897156],"type":"Point"}
}