{
  "type": "Feature",
  "properties": {
    "addr:full":"Level 1 / 420 William St West Melbourne VIC 3003",
    "addr:housenumber":"/ 420",
    "addr:postcode":"3003",
    "addr:street":"William St",
    "iso:country":"AU",
    "sg:address":"Level 1 / 420 William St",
    "sg:city":"West Melbourne",
    "sg:classifiers":[
        {
            "category":"Banks & Credit Unions",
            "subcategory":"Financial Services",
            "type":"Services"
        }
    ],
    "sg:phone":"+61 3 9329 1299",
    "sg:postcode":"3003",
    "sg:province":"VIC",
    "sg:tags":[
        "loan",
        "finance",
        "mortgage"
    ],
    "wof:name":"Secide Pty Ltd",
    "wof:placetype":"venue"
},
  "geometry": {"coordinates":[144.954956055,-37.8082389832],"type":"Point"}
}