{
  "type": "Feature",
  "properties": {
    "iso:country":"AU",
    "sg:address":"26 Furness Ave",
    "sg:city":"Edwardstown",
    "sg:phone":"+61 8 8277 5777",
    "sg:postcode":"5039",
    "sg:province":"SA",
    "wof:name":"Aquamate",
    "wof:placetype":"venue"
},
  "geometry": {"coordinates":[138.572067261,-34.9833946228],"type":"Point"}
}