{
  "type": "Feature",
  "properties": {
    "addr:full":"429 High St Melton VIC 3337",
    "addr:housenumber":"429",
    "addr:postcode":"3337",
    "addr:street":"High St",
    "iso:country":"AU",
    "sg:address":"429 High St",
    "sg:city":"Melton",
    "sg:classifiers":[
        {
            "category":"Professional",
            "subcategory":"Computer Services",
            "type":"Services"
        }
    ],
    "sg:phone":"+61 3 9747 8011",
    "sg:postcode":"3337",
    "sg:province":"VIC",
    "sg:tags":[
        "repairs",
        "upgrade",
        "equipment"
    ],
    "wof:name":"Hurricane Computers Pty Ltd",
    "wof:placetype":"venue"
},
  "geometry": {"coordinates":[144.58189400000001,-37.683289],"type":"Point"}
}