{
  "type": "Feature",
  "properties": {
    "iso:country":"AU",
    "sg:address":"Shop 6, 180 Pascoe Rd",
    "sg:city":"Ormeau",
    "sg:classifiers":[
        {
            "category":"Health Services",
            "subcategory":"Doctor",
            "type":"Services"
        }
    ],
    "sg:phone":"+61 7 5547 5111",
    "sg:postcode":"4208",
    "sg:province":"QLD",
    "sg:tags":[
        "medical",
        "practitioner"
    ],
    "wof:name":"Ormeau Queensland Medical Centres",
    "wof:placetype":"venue"
},
  "geometry": {"coordinates":[153.24598693900001,-27.7633705139],"type":"Point"}
}