{
  "type": "Feature",
  "properties": {
    "iso:country":"AU",
    "sg:address":"75 Arthur St St",
    "sg:city":"Albans",
    "sg:classifiers":[
        {
            "category":"Health Services",
            "subcategory":"Health Practitioner",
            "type":"Services"
        }
    ],
    "sg:phone":"+61 3 9366 5444",
    "sg:postcode":"3021",
    "sg:province":"VIC",
    "sg:tags":[
        "hypnotherapy"
    ],
    "wof:name":"Saratchandran K.P. Dr.",
    "wof:placetype":"venue"
},
  "geometry": {"coordinates":[144.809036,-37.73085],"type":"Point"}
}