{
  "type": "Feature",
  "properties": {
    "addr:full":"45 Tweeddale Rd Applecross WA 6153",
    "addr:housenumber":"45",
    "addr:postcode":"6153",
    "addr:street":"Tweeddale Rd",
    "iso:country":"AU",
    "sg:address":"45 Tweeddale Rd",
    "sg:city":"Applecross",
    "sg:classifiers":[
        {
            "category":"Social Services",
            "subcategory":"Child Care",
            "type":"Services"
        }
    ],
    "sg:phone":"+61 8 9316 2995",
    "sg:postcode":"6153",
    "sg:province":"WA",
    "sg:tags":[
        "equipment",
        "identification"
    ],
    "wof:name":"Armada Photo ID Centre",
    "wof:placetype":"venue"
},
  "geometry": {"coordinates":[115.842461,-32.009472],"type":"Point"}
}