{
  "type": "Feature",
  "properties": {
    "addr:full":"Shop 4/ 300 Main Rd Cardiff NSW 2285",
    "addr:housenumber":"shop 4 / 300",
    "addr:postcode":"2285",
    "addr:street":"Main Rd",
    "iso:country":"AU",
    "sg:address":"Shop 4/ 300 Main Rd",
    "sg:city":"Cardiff",
    "sg:classifiers":[
        {
            "category":"Bars & Pubs",
            "subcategory":"Nightclub",
            "type":"Food & Drink"
        }
    ],
    "sg:phone":"+61 2 4954 2556",
    "sg:postcode":"2285",
    "sg:province":"NSW",
    "sg:tags":[
        "karaoke"
    ],
    "wof:name":"Karaoke Hunter",
    "wof:placetype":"venue"
},
  "geometry": {"coordinates":[151.65945434599999,-32.9398345947],"type":"Point"}
}