{
  "type": "Feature",
  "properties": {
    "iso:country":"AU",
    "sg:address":"127 Orchard Rd",
    "sg:city":"Chester Hill",
    "sg:classifiers":[
        {
            "category":"Retail",
            "subcategory":"Storage",
            "type":"Services"
        }
    ],
    "sg:phone":"+61 2 9743 9022",
    "sg:postcode":"2162",
    "sg:province":"NSW",
    "sg:tags":[
        "shelving",
        "system"
    ],
    "wof:name":"Modern Storage Corporation",
    "wof:placetype":"venue"
},
  "geometry": {"coordinates":[150.99667358400001,-33.8866386414],"type":"Point"}
}