{
  "type": "Feature",
  "properties": {
    "addr:full":"83- 85 Five Islands Rd Cringila NSW 2502",
    "addr:housenumber":"85",
    "addr:postcode":"2502",
    "addr:street":"Five Islands Rd",
    "iso:country":"AU",
    "sg:address":"83- 85 Five Islands Rd",
    "sg:city":"Cringila",
    "sg:classifiers":[
        {
            "category":"Utilities",
            "subcategory":"Recycling",
            "type":"Services"
        }
    ],
    "sg:phone":"+61 2 4276 2814",
    "sg:postcode":"2502",
    "sg:province":"NSW",
    "wof:name":"Steel City Metals",
    "wof:placetype":"venue"
},
  "geometry": {"coordinates":[150.88189700000001,-34.470642],"type":"Point"}
}