{
  "type": "Feature",
  "properties": {
    "addr:full":"12 Mountainview Drv Woongarrah NSW 2259",
    "addr:housenumber":"12",
    "addr:postcode":"2259",
    "addr:street":"Mountainview Drv",
    "iso:country":"AU",
    "sg:address":"12 Mountainview Drv",
    "sg:city":"Woongarrah",
    "sg:classifiers":[
        {
            "category":"Arts & Performance",
            "subcategory":"Music",
            "type":"Entertainment"
        }
    ],
    "sg:phone":"+61 402 257 782",
    "sg:postcode":"2259",
    "sg:province":"NSW",
    "sg:tags":[
        "mobile",
        "jockey",
        "disc"
    ],
    "sg:website":"http://www.xtremepartyz.com",
    "wof:name":"Xtreme Partyz",
    "wof:placetype":"venue"
},
  "geometry": {"coordinates":[151.48338317899999,-33.2486305237],"type":"Point"}
}