{
  "type": "Feature",
  "properties": {
    "iso:country":"AU",
    "sg:address":"20 Tyers St",
    "sg:city":"Stratford",
    "sg:classifiers":[
        {
            "category":"Shopping",
            "subcategory":"Antiques",
            "type":"Retail Goods"
        }
    ],
    "sg:phone":"+61 3 5145 6352",
    "sg:postcode":"3862",
    "sg:province":"VIC",
    "sg:tags":[
        "restoration",
        "reproduction"
    ],
    "wof:name":"Avon River Antiques & Cottage Furniture",
    "wof:placetype":"venue"
},
  "geometry": {"coordinates":[147.07966613799999,-37.9687538147],"type":"Point"}
}