{
  "type": "Feature",
  "properties": {
    "iso:country":"AU",
    "sg:address":"4/ 127 Creek St",
    "sg:city":"Brisbane",
    "sg:classifiers":[
        {
            "category":"Banks & Credit Unions",
            "subcategory":"Financial Services",
            "type":"Services"
        }
    ],
    "sg:phone":"+61 7 3218 3281",
    "sg:postcode":"4000",
    "sg:province":"QLD",
    "sg:tags":[
        "advisory",
        "planning",
        "retirement"
    ],
    "wof:name":"Philip Mason-Cox",
    "wof:placetype":"venue"
},
  "geometry": {"coordinates":[153.027709961,-27.4658489227],"type":"Point"}
}