{
  "type": "Feature",
  "properties": {
    "iso:country":"AU",
    "sg:address":"44 Stirling Rd",
    "sg:city":"Port Augusta",
    "sg:classifiers":[
        {
            "category":"Autos & Motor Vehicles",
            "subcategory":"Fuel & Gas Station",
            "type":"Retail Goods"
        }
    ],
    "sg:phone":"+61 8 8642 4255",
    "sg:postcode":"5700",
    "sg:province":"SA",
    "wof:name":"Mobil Davenport Service Station",
    "wof:placetype":"venue"
},
  "geometry": {"coordinates":[137.771240234,-32.4988250732],"type":"Point"}
}