{
  "type": "Feature",
  "properties": {
    "addr:full":"Units 1-2 / 12 Princes Hwy Doveton VIC 3177",
    "addr:housenumber":"units 1-2 / 12",
    "addr:postcode":"3177",
    "addr:street":"Princes Hwy",
    "iso:country":"AU",
    "sg:address":"Units 1-2 / 12 Princes Hwy",
    "sg:city":"Doveton",
    "sg:classifiers":[
        {
            "category":"Home & Garden",
            "subcategory":"Carpets & Floor Coverings",
            "type":"Retail Goods"
        }
    ],
    "sg:phone":"+61 3 9706 9767",
    "sg:postcode":"3177",
    "sg:province":"VIC",
    "sg:tags":[
        "tile",
        "wall"
    ],
    "wof:name":"Slate Discounts Pty Ltd",
    "wof:placetype":"venue"
},
  "geometry": {"coordinates":[145.22967529300001,-38.0005683899],"type":"Point"}
}