{
  "type": "Feature",
  "properties": {
    "addr:full":"Lot 67 Magnesium Crs Narangba QLD 4504",
    "addr:postcode":"4504",
    "addr:street":"Magnesium Crs",
    "iso:country":"AU",
    "sg:address":"Lot 67 Magnesium Crs",
    "sg:city":"Narangba",
    "sg:classifiers":[
        {
            "category":"Health Services",
            "subcategory":"Nursing And Care Facility",
            "type":"Services"
        }
    ],
    "sg:phone":"+61 7 3204 1322",
    "sg:postcode":"4504",
    "sg:province":"QLD",
    "sg:tags":[
        "treatment",
        "preservation",
        "timber"
    ],
    "wof:name":"Coxs Timber Preservation (Aust) Pty Ltd",
    "wof:placetype":"venue"
},
  "geometry": {"coordinates":[152.99902343799999,-27.19947052],"type":"Point"}
}