{
  "type": "Feature",
  "properties": {
    "iso:country":"AU",
    "sg:address":"285 Doncaster Rd",
    "sg:city":"Balwyn North",
    "sg:classifiers":[
        {
            "category":"Personal",
            "subcategory":"Beauty Salon",
            "type":"Services"
        }
    ],
    "sg:phone":"+61 3 9857 5155",
    "sg:postcode":"3104",
    "sg:province":"VIC",
    "sg:tags":[
        "hairdresser"
    ],
    "wof:name":"Wardika Hairdressing",
    "wof:placetype":"venue"
},
  "geometry": {"coordinates":[145.093582153,-37.791721344],"type":"Point"}
}