{
  "type": "Feature",
  "properties": {
    "iso:country":"AU",
    "sg:address":"20 Thorne St",
    "sg:city":"Wynnum",
    "sg:classifiers":[
        {
            "category":"Structure",
            "subcategory":"Building",
            "type":"Public Place"
        }
    ],
    "sg:phone":"+61 7 3396 9245",
    "sg:postcode":"4178",
    "sg:province":"QLD",
    "sg:tags":[
        "sail",
        "shade"
    ],
    "wof:name":"Thorline Shade Structures",
    "wof:placetype":"venue"
},
  "geometry": {"coordinates":[153.16758727999999,-27.4394226074],"type":"Point"}
}