{
  "type": "Feature",
  "properties": {
    "addr:full":"Cnr Scarborough Beach Rd & Main St Osborne Park WA 6017",
    "addr:postcode":"6017",
    "addr:street":"Cnr Scarborough Beach Rd & Main St",
    "iso:country":"AU",
    "sg:address":"Cnr Scarborough Beach Rd & Main St",
    "sg:city":"Osborne Park",
    "sg:classifiers":[
        {
            "category":"Home & Garden",
            "subcategory":"Household Appliances",
            "type":"Retail Goods"
        }
    ],
    "sg:phone":"+61 8 9242 4751",
    "sg:postcode":"6017",
    "sg:province":"WA",
    "sg:tags":[
        "chemical",
        "equipment",
        "steam",
        "cleaning",
        "pressure"
    ],
    "wof:name":"Power Vac",
    "wof:placetype":"venue"
},
  "geometry": {"coordinates":[115.812896728,-31.9092235565],"type":"Point"}
}