{
  "type": "Feature",
  "properties": {
    "iso:country":"AU",
    "sg:address":"RMB 1365 Yarramalong Rd",
    "sg:city":"Yarramalong",
    "sg:classifiers":[
        {
            "category":"Retail",
            "subcategory":"Event Space",
            "type":"Services"
        }
    ],
    "sg:phone":"+61 2 4356 1066",
    "sg:postcode":"2259",
    "sg:province":"NSW",
    "sg:tags":[
        "venue",
        "reception",
        "wedding"
    ],
    "wof:name":"Yarramalong Manor",
    "wof:placetype":"venue"
},
  "geometry": {"coordinates":[151.299194336,-33.2348442078],"type":"Point"}
}