{
  "type": "Feature",
  "properties": {
    "addr:full":"Eighth St (Cnr Yambellup Ave) Harvey WA 6220",
    "addr:postcode":"6220",
    "addr:street":"Eighth St Cnr Yambellup Ave",
    "iso:country":"AU",
    "sg:address":"Eighth St (Cnr Yambellup Ave)",
    "sg:city":"Harvey",
    "sg:classifiers":[
        {
            "category":"Farming",
            "subcategory":"Farm",
            "type":"Manufacturing & Wholesale Goods"
        }
    ],
    "sg:phone":"+61 8 9729 1255",
    "sg:postcode":"6220",
    "sg:province":"WA",
    "sg:tags":[
        "farmer"
    ],
    "wof:name":"Morris R F",
    "wof:placetype":"venue"
},
  "geometry": {"coordinates":[115.867149,-33.071953],"type":"Point"}
}