{
  "type": "Feature",
  "properties": {
    "addr:full":"4/ 52 Riverside Rd Chipping Norton NSW 2170",
    "addr:housenumber":"/ 52",
    "addr:postcode":"2170",
    "addr:street":"Riverside Rd",
    "iso:country":"AU",
    "sg:address":"4/ 52 Riverside Rd",
    "sg:city":"Chipping Norton",
    "sg:classifiers":[
        {
            "category":"Retail",
            "subcategory":"Auto Repair",
            "type":"Services"
        }
    ],
    "sg:phone":"+61 2 9755 3375",
    "sg:postcode":"2170",
    "sg:province":"NSW",
    "sg:tags":[
        "beater",
        "painter",
        "panel"
    ],
    "wof:name":"Bang Motor Body Repairs",
    "wof:placetype":"venue"
},
  "geometry": {"coordinates":[150.968505859,-33.9211883545],"type":"Point"}
}