{
  "type": "Feature",
  "properties": {
    "iso:country":"AU",
    "sg:address":"PO Box 110",
    "sg:city":"Sylvania Heights",
    "sg:classifiers":[
        {
            "category":"Social Services",
            "type":"Services"
        }
    ],
    "sg:phone":"+61 1300 653 928",
    "sg:postcode":"2224",
    "sg:province":"NSW",
    "sg:tags":[
        "domestic",
        "help"
    ],
    "wof:name":"Care 4 Services Pty Ltd",
    "wof:placetype":"venue"
},
  "geometry": {"coordinates":[151.088165283,-34.0167808533],"type":"Point"}
}