{
  "type": "Feature",
  "properties": {
    "addr:full":"7 Randle St Surry Hills NSW 2010",
    "addr:housenumber":"7",
    "addr:postcode":"2010",
    "addr:street":"Randle St",
    "iso:country":"AU",
    "sg:address":"7 Randle St",
    "sg:city":"Surry Hills",
    "sg:classifiers":[
        {
            "category":"Bars & Pubs",
            "subcategory":"Nightclub",
            "type":"Food & Drink"
        }
    ],
    "sg:phone":"+61 2 9281 9000",
    "sg:postcode":"2010",
    "sg:province":"NSW",
    "sg:tags":[
        "karaoke"
    ],
    "wof:name":"Ding Dong Deng",
    "wof:placetype":"venue"
},
  "geometry": {"coordinates":[151.20770263700001,-33.8850440979],"type":"Point"}
}