{
  "type": "Feature",
  "properties": {
    "iso:country":"AU",
    "sg:address":"Monaco St",
    "sg:city":"Holland Park West",
    "sg:classifiers":[
        {
            "category":"Education",
            "subcategory":"School",
            "type":"Public Place"
        }
    ],
    "sg:phone":"+61 7 3349 5624",
    "sg:postcode":"4121",
    "sg:province":"QLD",
    "sg:tags":[
        "state",
        "except",
        "nsw"
    ],
    "wof:name":"Marshall Road Preschool",
    "wof:placetype":"venue"
},
  "geometry": {"coordinates":[153.05796814000001,-27.5274944305],"type":"Point"}
}