{
  "type": "Feature",
  "properties": {
    "iso:country":"AU",
    "sg:address":"2 Caramut Rd",
    "sg:city":"Ringwood East",
    "sg:classifiers":[
        {
            "category":"Wholesale",
            "subcategory":"Painting Supplies",
            "type":"Manufacturing & Wholesale Goods"
        }
    ],
    "sg:phone":"+61 3 8802 0382",
    "sg:postcode":"3135",
    "sg:province":"VIC",
    "sg:tags":[
        "product",
        "cleaning"
    ],
    "wof:name":"Flow Master",
    "wof:placetype":"venue"
},
  "geometry": {"coordinates":[145.257324219,-37.8005027771],"type":"Point"}
}