{
  "type": "Feature",
  "properties": {
    "addr:full":"65- 73 Dawson Hwy Moura QLD 4718",
    "addr:housenumber":"73",
    "addr:postcode":"4718",
    "addr:street":"Dawson Hwy",
    "iso:country":"AU",
    "sg:address":"65- 73 Dawson Hwy",
    "sg:city":"Moura",
    "sg:classifiers":[
        {
            "category":"Travel",
            "subcategory":"Hotels & Motels",
            "type":"Entertainment"
        }
    ],
    "sg:phone":"+61 7 4997 1588",
    "sg:postcode":"4718",
    "sg:province":"QLD",
    "wof:name":"Moura Motel & Restaurant",
    "wof:placetype":"venue"
},
  "geometry": {"coordinates":[149.97622680699999,-24.5654411316],"type":"Point"}
}