{
  "type": "Feature",
  "properties": {
    "iso:country":"AU",
    "sg:address":"7/ 714 Princes Hwy",
    "sg:city":"Kogarah",
    "sg:classifiers":[
        {
            "category":"Organizations",
            "subcategory":"Professional Association",
            "type":"Services"
        }
    ],
    "sg:phone":"+61 2 9587 3047",
    "sg:postcode":"2217",
    "sg:province":"NSW",
    "sg:tags":[
        "web",
        "internet"
    ],
    "wof:name":"Integration Online Services",
    "wof:placetype":"venue"
},
  "geometry": {"coordinates":[151.137665,-33.962601],"type":"Point"}
}