{
  "type": "Feature",
  "properties": {
    "addr:full":"388 Crown St Wollongong NSW 2500",
    "addr:housenumber":"388",
    "addr:postcode":"2500",
    "addr:street":"Crown St",
    "iso:country":"AU",
    "sg:address":"388 Crown St",
    "sg:city":"Wollongong",
    "sg:classifiers":[
        {
            "category":"Shopping",
            "subcategory":"Crafts & Fabrics",
            "type":"Retail Goods"
        }
    ],
    "sg:phone":"+61 2 4228 5488",
    "sg:postcode":"2500",
    "sg:province":"NSW",
    "sg:tags":[
        "merchant",
        "cork"
    ],
    "wof:name":"Better Floors Pty Ltd",
    "wof:placetype":"venue"
},
  "geometry": {"coordinates":[150.876892,-34.425823],"type":"Point"}
}