{
  "type": "Feature",
  "properties": {
    "addr:full":"119- 121 Rowe St Eastwood NSW 2122",
    "addr:housenumber":"121",
    "addr:postcode":"2122",
    "addr:street":"Rowe St",
    "iso:country":"AU",
    "sg:address":"119- 121 Rowe St",
    "sg:city":"Eastwood",
    "sg:classifiers":[
        {
            "category":"Shopping",
            "subcategory":"Clothing, Apparel, & Fashions",
            "type":"Retail Goods"
        }
    ],
    "sg:phone":"+61 2 9874 6743",
    "sg:postcode":"2122",
    "sg:province":"NSW",
    "sg:tags":[
        "recycled",
        "clothing"
    ],
    "wof:name":"After-a-Fashion",
    "wof:placetype":"venue"
},
  "geometry": {"coordinates":[151.07579040499999,-33.7929344177],"type":"Point"}
}