{
  "type": "Feature",
  "properties": {
    "iso:country":"AU",
    "sg:address":"28c Hull St",
    "sg:city":"Glenorchy",
    "sg:classifiers":[
        {
            "category":"Home & Garden",
            "subcategory":"Furniture",
            "type":"Retail Goods"
        }
    ],
    "sg:phone":"+61 408 389 238",
    "sg:postcode":"7010",
    "sg:province":"TAS",
    "sg:tags":[
        "repair",
        "restoration"
    ],
    "wof:name":"Kruse Furniture Restorations",
    "wof:placetype":"venue"
},
  "geometry": {"coordinates":[147.26502990700001,-42.8327217102],"type":"Point"}
}