{
  "type": "Feature",
  "properties": {
    "addr:full":"25 Beaumont Ave Wyoming NSW 2250",
    "addr:housenumber":"25",
    "addr:postcode":"2250",
    "addr:street":"Beaumont Ave",
    "iso:country":"AU",
    "sg:address":"25 Beaumont Ave",
    "sg:city":"Wyoming",
    "sg:classifiers":[
        {
            "category":"Professional",
            "subcategory":"Computer Services",
            "type":"Services"
        }
    ],
    "sg:phone":"+61 2 4323 7149",
    "sg:postcode":"2250",
    "sg:province":"NSW",
    "sg:tags":[
        "package",
        "software"
    ],
    "wof:name":"Prestwood Australia Pty Ltd",
    "wof:placetype":"venue"
},
  "geometry": {"coordinates":[151.35887145999999,-33.41065979],"type":"Point"}
}