{
  "type": "Feature",
  "properties": {
    "iso:country":"AU",
    "sg:address":"27 Torrens St",
    "sg:city":"Braddon",
    "sg:classifiers":[
        {
            "category":"Banks & Credit Unions",
            "subcategory":"Investment Brokerage",
            "type":"Services"
        }
    ],
    "sg:phone":"+61 2 6247 0099",
    "sg:postcode":"2612",
    "sg:province":"ACT",
    "wof:name":"Barnett Lilley & Associates Pty Ltd",
    "wof:placetype":"venue"
},
  "geometry": {"coordinates":[149.13404846200001,-35.2727661133],"type":"Point"}
}