{
  "type": "Feature",
  "properties": {
    "iso:country":"AU",
    "sg:address":"100 Seiferts Rd",
    "sg:city":"Bondoola",
    "sg:classifiers":[
        {
            "category":"Professional",
            "subcategory":"Engineering",
            "type":"Services"
        }
    ],
    "sg:phone":"+61 7 4938 3338",
    "sg:postcode":"4702",
    "sg:province":"QLD",
    "sg:tags":[
        "engineer"
    ],
    "wof:name":"Infin-Tech Pty Ltd",
    "wof:placetype":"venue"
},
  "geometry": {"coordinates":[150.67536926299999,-23.1696491241],"type":"Point"}
}