{
  "type": "Feature",
  "properties": {
    "iso:country":"AU",
    "sg:address":"457 Clayton Rd",
    "sg:city":"Clayton South",
    "sg:classifiers":[
        {
            "category":"Building & Trades",
            "subcategory":"Landscaping Services",
            "type":"Services"
        }
    ],
    "sg:phone":"+61 3 9515 8492",
    "sg:postcode":"3169",
    "sg:province":"VIC",
    "sg:tags":[
        "gardener"
    ],
    "wof:name":"Hall N & C",
    "wof:placetype":"venue"
},
  "geometry": {"coordinates":[145.11752319300001,-37.9354171753],"type":"Point"}
}