{
  "type": "Feature",
  "properties": {
    "iso:country":"AU",
    "sg:address":"15 Railway Pde",
    "sg:city":"Darra",
    "sg:classifiers":[
        {
            "category":"Shopping",
            "subcategory":"Clothing, Apparel, & Fashions",
            "type":"Retail Goods"
        }
    ],
    "sg:phone":"+61 7 3375 1376",
    "sg:postcode":"4076",
    "sg:province":"QLD",
    "sg:tags":[
        "accessory"
    ],
    "wof:name":"Marygold Fashion",
    "wof:placetype":"venue"
},
  "geometry": {"coordinates":[152.952026367,-27.5663948059],"type":"Point"}
}