{
  "type": "Feature",
  "properties": {
    "addr:full":"1/ 14 Shepherd St Darwin NT 0800",
    "addr:housenumber":"/ 14",
    "addr:postcode":"nt 0800",
    "addr:street":"Shepherd St",
    "iso:country":"AU",
    "sg:address":"1/ 14 Shepherd St",
    "sg:city":"Darwin",
    "sg:classifiers":[
        {
            "category":"Health Services",
            "subcategory":"Health Practitioner",
            "type":"Services"
        }
    ],
    "sg:phone":"+61 8 8981 5392",
    "sg:postcode":"0800",
    "sg:province":"NT",
    "sg:tags":[
        "psychologist"
    ],
    "wof:name":"Cindy Wall",
    "wof:placetype":"venue"
},
  "geometry": {"coordinates":[130.84063720699999,-12.4577980042],"type":"Point"}
}