{
  "type": "Feature",
  "properties": {
    "iso:country":"AU",
    "sg:address":"Ste2/ 779 Albany Hwy",
    "sg:city":"East Victoria Park",
    "sg:classifiers":[
        {
            "category":"Health Services",
            "subcategory":"Doctor",
            "type":"Services"
        }
    ],
    "sg:phone":"+61 8 9355 2005",
    "sg:postcode":"6101",
    "sg:province":"WA",
    "sg:tags":[
        "medical",
        "practitioner"
    ],
    "wof:name":"East Victoria Park Medical Centre",
    "wof:placetype":"venue"
},
  "geometry": {"coordinates":[115.902633667,-31.9841060638],"type":"Point"}
}