{
  "type": "Feature",
  "properties": {
    "iso:country":"AU",
    "sg:address":"63 Commercial St",
    "sg:city":"East Mt Gambier",
    "sg:classifiers":[
        {
            "category":"Shopping",
            "subcategory":"Clothing, Apparel, & Fashions",
            "type":"Retail Goods"
        }
    ],
    "sg:phone":"+61 8 8725 0455",
    "sg:postcode":"5290",
    "sg:province":"SA",
    "sg:tags":[
        "menswear"
    ],
    "wof:name":"Thwaites Mensland",
    "wof:placetype":"venue"
},
  "geometry": {"coordinates":[140.78315699999999,-37.829063],"type":"Point"}
}