{
  "type": "Feature",
  "properties": {
    "addr:full":"Shop 28 Valley Plaza Wilson Rd Green Valley NSW 2168",
    "addr:housenumber":"shop 28",
    "addr:postcode":"2168",
    "addr:street":"Valley Plaza Wilson Rd",
    "iso:country":"AU",
    "sg:address":"Shop 28 Valley Plaza Wilson Rd",
    "sg:city":"Green Valley",
    "sg:classifiers":[
        {
            "category":"Food & Beverages",
            "subcategory":"Meat & Fish",
            "type":"Retail Goods"
        }
    ],
    "sg:phone":"+61 2 9826 9487",
    "sg:postcode":"2168",
    "sg:province":"NSW",
    "sg:tags":[
        "seafood"
    ],
    "wof:name":"Golden Shell Seafood",
    "wof:placetype":"venue"
},
  "geometry": {"coordinates":[150.86651611299999,-33.9027328491],"type":"Point"}
}