{
  "type": "Feature",
  "properties": {
    "addr:full":"1 Harley Rd Avalon NSW 2107",
    "addr:housenumber":"1",
    "addr:postcode":"2107",
    "addr:street":"Harley Rd",
    "iso:country":"AU",
    "sg:address":"1 Harley Rd",
    "sg:city":"Avalon",
    "sg:classifiers":[
        {
            "category":"Health Services",
            "subcategory":"Health Practitioner",
            "type":"Services"
        }
    ],
    "sg:phone":"+61 2 9918 7201",
    "sg:postcode":"2107",
    "sg:province":"NSW",
    "sg:tags":[
        "physiotherapist"
    ],
    "wof:name":"Lapin Susie. Peninsula Physiotherapy",
    "wof:placetype":"venue"
},
  "geometry": {"coordinates":[151.33702087399999,-33.630355835],"type":"Point"}
}