{
  "type": "Feature",
  "properties": {
    "iso:country":"AU",
    "sg:address":"85 Isabella St",
    "sg:city":"Wingham",
    "sg:classifiers":[
        {
            "category":"Shopping",
            "subcategory":"Clothing, Apparel, & Fashions",
            "type":"Retail Goods"
        }
    ],
    "sg:phone":"+61 2 6553 0142",
    "sg:postcode":"2429",
    "sg:province":"NSW",
    "sg:tags":[
        "lady",
        "wear"
    ],
    "wof:name":"Ashlea Road",
    "wof:placetype":"venue"
},
  "geometry": {"coordinates":[152.373672,-31.868797],"type":"Point"}
}