{
  "type": "Feature",
  "properties": {
    "addr:full":"PO Box 902 Redcliffe QLD 4020",
    "addr:postcode":"4020",
    "iso:country":"AU",
    "sg:address":"PO Box 902",
    "sg:city":"Redcliffe",
    "sg:classifiers":[
        {
            "category":"Shopping",
            "subcategory":"Bicycles & Sporting Goods",
            "type":"Retail Goods"
        }
    ],
    "sg:phone":"+61 7 3284 7554",
    "sg:postcode":"4020",
    "sg:province":"QLD",
    "sg:tags":[
        "chemical",
        "equipment",
        "pool",
        "swimming"
    ],
    "wof:name":"Expert Pool Care",
    "wof:placetype":"venue"
},
  "geometry": {"coordinates":[153.107224,-27.22217],"type":"Point"}
}