{
  "type": "Feature",
  "properties": {
    "iso:country":"AU",
    "sg:address":"91 Arabella St",
    "sg:city":"Longueville",
    "sg:classifiers":[
        {
            "category":"Building & Trades",
            "subcategory":"Landscaping Services",
            "type":"Services"
        }
    ],
    "sg:phone":"+61 418 224 992",
    "sg:postcode":"2066",
    "sg:province":"NSW",
    "sg:tags":[
        "consultant"
    ],
    "wof:name":"Senjet Pty Ltd",
    "wof:placetype":"venue"
},
  "geometry": {"coordinates":[151.168136597,-33.8318557739],"type":"Point"}
}