{
  "type": "Feature",
  "properties": {
    "iso:country":"AU",
    "sg:address":"27 Simla Rd",
    "sg:city":"West Ryde",
    "sg:classifiers":[
        {
            "category":"Building & Trades",
            "subcategory":"Plumbing",
            "type":"Services"
        }
    ],
    "sg:phone":"+61 2 9874 1937",
    "sg:postcode":"2114",
    "sg:province":"NSW",
    "sg:tags":[
        "plumber",
        "gasfitters"
    ],
    "wof:name":"Southeron R.J.",
    "wof:placetype":"venue"
},
  "geometry": {"coordinates":[151.08314514200001,-33.8017921448],"type":"Point"}
}