{
  "type": "Feature",
  "properties": {
    "iso:country":"AU",
    "sg:address":"73 Thompson St",
    "sg:city":"Earlwood",
    "sg:classifiers":[
        {
            "category":"Professional",
            "subcategory":"Printing & Photocopies",
            "type":"Services"
        }
    ],
    "sg:phone":"+61 2 9718 1239",
    "sg:postcode":"2206",
    "sg:province":"NSW",
    "sg:tags":[
        "trophy"
    ],
    "wof:name":"Mayfair Trophies",
    "wof:placetype":"venue"
},
  "geometry": {"coordinates":[151.12290999999999,-33.921844],"type":"Point"}
}