{
  "type": "Feature",
  "properties": {
    "addr:full":"76 Smith St Kempsey NSW 2440",
    "addr:housenumber":"76",
    "addr:postcode":"2440",
    "addr:street":"Smith St",
    "iso:country":"AU",
    "sg:address":"76 Smith St",
    "sg:city":"Kempsey",
    "sg:classifiers":[
        {
            "category":"Autos & Motor Vehicles",
            "subcategory":"Auto Supplies",
            "type":"Retail Goods"
        }
    ],
    "sg:phone":"+61 2 6562 7089",
    "sg:postcode":"2440",
    "sg:province":"NSW",
    "sg:tags":[
        "accessory"
    ],
    "wof:name":"Col's Motorcycles",
    "wof:placetype":"venue"
},
  "geometry": {"coordinates":[152.84245300000001,-31.077646],"type":"Point"}
}