{
  "type": "Feature",
  "properties": {
    "addr:full":"13 Dawson St Strathalbyn SA 5255",
    "addr:housenumber":"13",
    "addr:postcode":"5255",
    "addr:street":"Dawson St",
    "iso:country":"AU",
    "sg:address":"13 Dawson St",
    "sg:city":"Strathalbyn",
    "sg:classifiers":[
        {
            "category":"Personal",
            "subcategory":"Beauty Salon",
            "type":"Services"
        }
    ],
    "sg:phone":"+61 8 8536 2540",
    "sg:postcode":"5255",
    "sg:province":"SA",
    "sg:tags":[
        "hairdresser"
    ],
    "wof:name":"Hair Fashions Strathalbyn",
    "wof:placetype":"venue"
},
  "geometry": {"coordinates":[138.891067505,-35.2597541809],"type":"Point"}
}