{
  "type": "Feature",
  "properties": {
    "iso:country":"AU",
    "sg:address":"27 Harold St",
    "sg:city":"Wendouree",
    "sg:classifiers":[
        {
            "category":"Fast Food",
            "type":"Food & Drink"
        }
    ],
    "sg:phone":"+61 3 5339 5125",
    "sg:postcode":"3355",
    "sg:province":"VIC",
    "sg:tags":[
        "away",
        "take"
    ],
    "wof:name":"Goh Sing Chinese Take Away Food & Catering Service",
    "wof:placetype":"venue"
},
  "geometry": {"coordinates":[143.83165,-37.530224],"type":"Point"}
}