{
  "type": "Feature",
  "properties": {
    "addr:full":"190 High St Wodonga VIC 3690",
    "addr:housenumber":"190",
    "addr:postcode":"3690",
    "addr:street":"High St",
    "iso:country":"AU",
    "sg:address":"190 High St",
    "sg:city":"Wodonga",
    "sg:classifiers":[
        {
            "category":"Food & Beverages",
            "subcategory":"Liquor & Beverages",
            "type":"Retail Goods"
        }
    ],
    "sg:phone":"+61 2 6056 2544",
    "sg:postcode":"3690",
    "sg:province":"VIC",
    "sg:tags":[
        "store"
    ],
    "wof:name":"Liquorland",
    "wof:placetype":"venue"
},
  "geometry": {"coordinates":[146.88829040499999,-36.1233062744],"type":"Point"}
}