{
  "type": "Feature",
  "properties": {
    "addr:full":"Lot 1 Bower Rd Normanville SA 5204",
    "addr:postcode":"5204",
    "addr:street":"Bower Rd",
    "iso:country":"AU",
    "sg:address":"Lot 1 Bower Rd",
    "sg:city":"Normanville",
    "sg:classifiers":[
        {
            "category":"Farming",
            "subcategory":"Vineyard",
            "type":"Manufacturing & Wholesale Goods"
        }
    ],
    "sg:phone":"+61 8 8558 3595",
    "sg:postcode":"5204",
    "sg:province":"SA",
    "sg:tags":[
        "winery"
    ],
    "wof:name":"Trafford Hill Winery",
    "wof:placetype":"venue"
},
  "geometry": {"coordinates":[138.332489014,-35.4458351135],"type":"Point"}
}