{
  "type": "Feature",
  "properties": {
    "addr:full":"55 Lancaster Ave Cecil Hills NSW 2171",
    "addr:housenumber":"55",
    "addr:postcode":"2171",
    "addr:street":"Lancaster Ave Cecil",
    "iso:country":"AU",
    "sg:address":"55 Lancaster Ave",
    "sg:city":"Cecil Hills",
    "sg:classifiers":[
        {
            "category":"Building & Trades",
            "subcategory":"Construction",
            "type":"Services"
        }
    ],
    "sg:phone":"+61 418 273 478",
    "sg:postcode":"2171",
    "sg:province":"NSW",
    "sg:tags":[
        "concrete",
        "contractor"
    ],
    "wof:name":"West City Concrete",
    "wof:placetype":"venue"
},
  "geometry": {"coordinates":[150.847900391,-33.8824729919],"type":"Point"}
}