{
  "type": "Feature",
  "properties": {
    "iso:country":"AU",
    "sg:address":"11 Graham Rd",
    "sg:city":"Clayton South",
    "sg:classifiers":[
        {
            "category":"Retail",
            "subcategory":"Storage",
            "type":"Services"
        }
    ],
    "sg:phone":"+61 3 9546 5916",
    "sg:postcode":"3169",
    "sg:province":"VIC",
    "sg:tags":[
        "shelving",
        "system"
    ],
    "wof:name":"MQT Metal Industry Pty Ltd",
    "wof:placetype":"venue"
},
  "geometry": {"coordinates":[145.13479614299999,-37.9522819519],"type":"Point"}
}