{
  "type": "Feature",
  "properties": {
    "addr:full":"40 Tamar St Launceston TAS 7250",
    "addr:housenumber":"40",
    "addr:postcode":"7250",
    "addr:street":"Tamar St",
    "iso:country":"AU",
    "sg:address":"40 Tamar St",
    "sg:city":"Launceston",
    "sg:classifiers":[
        {
            "category":"Farming",
            "subcategory":"Farm & Veterinary Services",
            "type":"Manufacturing & Wholesale Goods"
        }
    ],
    "sg:phone":"+61 3 6334 1033",
    "sg:postcode":"7250",
    "sg:province":"TAS",
    "sg:tags":[
        "agricultural",
        "advisory"
    ],
    "wof:name":"Armstrong Agricultural Services",
    "wof:placetype":"venue"
},
  "geometry": {"coordinates":[147.140716553,-41.4327888489],"type":"Point"}
}