{
  "type": "Feature",
  "properties": {
    "iso:country":"AU",
    "sg:address":"64 Casuarina Rd",
    "sg:city":"Alfords Point",
    "sg:classifiers":[
        {
            "category":"Professional",
            "subcategory":"Computer Services",
            "type":"Services"
        }
    ],
    "sg:phone":"+61 418 409 128",
    "sg:postcode":"2234",
    "sg:province":"NSW",
    "sg:tags":[
        "consultant",
        "system"
    ],
    "wof:name":"Arthur Klioufis Computer Services",
    "wof:placetype":"venue"
},
  "geometry": {"coordinates":[151.02458190900001,-33.9821281433],"type":"Point"}
}