{
  "type": "Feature",
  "properties": {
    "addr:full":"99 Second Ave Marsden QLD 4132",
    "addr:housenumber":"99",
    "addr:postcode":"4132",
    "addr:street":"Second Ave",
    "iso:country":"AU",
    "sg:address":"99 Second Ave",
    "sg:city":"Marsden",
    "sg:classifiers":[
        {
            "category":"Building & Trades",
            "subcategory":"Construction",
            "type":"Services"
        }
    ],
    "sg:phone":"+61 7 3803 4505",
    "sg:postcode":"4132",
    "sg:province":"QLD",
    "sg:tags":[
        "plasterboard",
        "plasterer",
        "fixer"
    ],
    "wof:name":"Gee-Jay Plasterers",
    "wof:placetype":"venue"
},
  "geometry": {"coordinates":[153.09526062,-27.6687469482],"type":"Point"}
}