{
  "type": "Feature",
  "properties": {
    "addr:full":"21 Tintern Crt Frankston VIC 3199",
    "addr:housenumber":"21",
    "addr:postcode":"3199",
    "addr:street":"Tintern Crt",
    "iso:country":"AU",
    "sg:address":"21 Tintern Crt",
    "sg:city":"Frankston",
    "sg:classifiers":[
        {
            "category":"Building & Trades",
            "subcategory":"Plumbing",
            "type":"Services"
        }
    ],
    "sg:phone":"+61 3 5971 1494",
    "sg:postcode":"3199",
    "sg:province":"VIC",
    "sg:tags":[
        "plumber",
        "gasfitters"
    ],
    "wof:name":"Brodie's Plumbing & Gas Service",
    "wof:placetype":"venue"
},
  "geometry": {"coordinates":[145.141479492,-38.1818313599],"type":"Point"}
}