{
  "type": "Feature",
  "properties": {
    "addr:full":"36 Tiral St Charlestown NSW 2290",
    "addr:housenumber":"36",
    "addr:postcode":"2290",
    "addr:street":"Tiral St",
    "iso:country":"AU",
    "sg:address":"36 Tiral St",
    "sg:city":"Charlestown",
    "sg:classifiers":[
        {
            "category":"Utilities",
            "subcategory":"Electric",
            "type":"Services"
        }
    ],
    "sg:phone":"+61 2 4943 5117",
    "sg:postcode":"2290",
    "sg:province":"NSW",
    "sg:tags":[
        "electrical",
        "contractor"
    ],
    "wof:name":"Macchia Electrical",
    "wof:placetype":"venue"
},
  "geometry": {"coordinates":[151.69915771500001,-32.9705238342],"type":"Point"}
}