{
  "type": "Feature",
  "properties": {
    "addr:full":"6 Henry St Pakenham VIC 3810",
    "addr:housenumber":"6",
    "addr:postcode":"3810",
    "addr:street":"Henry St",
    "iso:country":"AU",
    "sg:address":"6 Henry St",
    "sg:city":"Pakenham",
    "sg:classifiers":[
        {
            "category":"Organizations",
            "subcategory":"Community Association",
            "type":"Services"
        }
    ],
    "sg:phone":"+61 3 5940 2885",
    "sg:postcode":"3810",
    "sg:province":"VIC",
    "sg:tags":[
        "organisation",
        "family",
        "welfare"
    ],
    "wof:name":"UnitingCare Connections",
    "wof:placetype":"venue"
},
  "geometry": {"coordinates":[145.48121599999999,-38.072849],"type":"Point"}
}