{
  "type": "Feature",
  "properties": {
    "iso:country":"AU",
    "sg:address":"Cnr Knuckey & Cavenagh Sts",
    "sg:city":"Darwin",
    "sg:classifiers":[
        {
            "category":"Health Services",
            "subcategory":"Health Practitioner",
            "type":"Services"
        }
    ],
    "sg:phone":"+61 409 090 885",
    "sg:postcode":"0800",
    "sg:province":"NT",
    "sg:tags":[
        "naturopath"
    ],
    "wof:name":"Elevated",
    "wof:placetype":"venue"
},
  "geometry": {"coordinates":[130.84257507300001,-12.4620265961],"type":"Point"}
}