{
  "type": "Feature",
  "properties": {
    "addr:full":"4/ 19 Watland St Springwood QLD 4127",
    "addr:housenumber":"/ 19",
    "addr:postcode":"4127",
    "addr:street":"Watland St",
    "iso:country":"AU",
    "sg:address":"4/ 19 Watland St",
    "sg:city":"Springwood",
    "sg:classifiers":[
        {
            "category":"Retail",
            "subcategory":"Repair Shop",
            "type":"Services"
        }
    ],
    "sg:phone":"+61 7 3209 1832",
    "sg:postcode":"4127",
    "sg:province":"QLD",
    "sg:tags":[
        "maintenance",
        "pool",
        "swimming"
    ],
    "wof:name":"Logan Pump Shop",
    "wof:placetype":"venue"
},
  "geometry": {"coordinates":[153.13148498499999,-27.6249580383],"type":"Point"}
}