{
  "type": "Feature",
  "properties": {
    "addr:full":"53 High St Casino NSW 2470",
    "addr:housenumber":"53",
    "addr:postcode":"2470",
    "addr:street":"High St",
    "iso:country":"AU",
    "sg:address":"53 High St",
    "sg:city":"Casino",
    "sg:classifiers":[
        {
            "category":"Retail",
            "subcategory":"Repair Shop",
            "type":"Services"
        }
    ],
    "sg:phone":"+61 1300 650 251",
    "sg:postcode":"2470",
    "sg:province":"NSW",
    "sg:tags":[
        "restorer",
        "repairer",
        "carpet"
    ],
    "wof:name":"Stainbusters Northern Rivers",
    "wof:placetype":"venue"
},
  "geometry": {"coordinates":[153.03782653799999,-28.8513088226],"type":"Point"}
}