{
  "type": "Feature",
  "properties": {
    "iso:country":"AU",
    "sg:address":"Shop 1, 3 Dower St",
    "sg:city":"Mandurah",
    "sg:classifiers":[
        {
            "category":"Shopping",
            "subcategory":"Clothing, Apparel, & Fashions",
            "type":"Retail Goods"
        }
    ],
    "sg:phone":"+61 8 9535 1029",
    "sg:postcode":"6210",
    "sg:province":"WA",
    "sg:tags":[
        "lady",
        "wear"
    ],
    "wof:name":"Occasions",
    "wof:placetype":"venue"
},
  "geometry": {"coordinates":[115.738731,-32.536064],"type":"Point"}
}