{
  "type": "Feature",
  "properties": {
    "addr:full":"221 Burwood Rd Burwood NSW 2134",
    "addr:housenumber":"221",
    "addr:postcode":"2134",
    "addr:street":"Burwood Rd",
    "iso:country":"AU",
    "sg:address":"221 Burwood Rd",
    "sg:city":"Burwood",
    "sg:classifiers":[
        {
            "category":"Health Services",
            "subcategory":"Nursing And Care Facility",
            "type":"Services"
        }
    ],
    "sg:phone":"+61 2 9744 2237",
    "sg:postcode":"2134",
    "sg:province":"NSW",
    "sg:tags":[
        "home"
    ],
    "wof:name":"Laureldene Nursing Home",
    "wof:placetype":"venue"
},
  "geometry": {"coordinates":[151.10191345199999,-33.8856391907],"type":"Point"}
}