{
  "type": "Feature",
  "properties": {
    "addr:full":"7 Haven Crt Mitcham VIC 3132",
    "addr:housenumber":"7",
    "addr:postcode":"3132",
    "addr:street":"Haven Crt",
    "iso:country":"AU",
    "sg:address":"7 Haven Crt",
    "sg:city":"Mitcham",
    "sg:classifiers":[
        {
            "category":"Professional",
            "subcategory":"Art Services",
            "type":"Services"
        }
    ],
    "sg:phone":"+61 3 9872 3237",
    "sg:postcode":"3132",
    "sg:province":"VIC",
    "sg:tags":[
        "decorator",
        "painter"
    ],
    "wof:name":"Advanced Painting",
    "wof:placetype":"venue"
},
  "geometry": {"coordinates":[145.20419311500001,-37.8278121948],"type":"Point"}
}