{
  "type": "Feature",
  "properties": {
    "iso:country":"AU",
    "sg:address":"87/ 91 Arundle Rd",
    "sg:city":"Horsley Park",
    "sg:classifiers":[
        {
            "category":"Wholesale",
            "subcategory":"Plants",
            "type":"Manufacturing & Wholesale Goods"
        }
    ],
    "sg:phone":"+61 2 9746 0313",
    "sg:postcode":"2164",
    "sg:province":"NSW",
    "sg:tags":[
        "florist"
    ],
    "wof:name":"Horsley Park Flowers",
    "wof:placetype":"venue"
},
  "geometry": {"coordinates":[150.99064636200001,-33.8988075256],"type":"Point"}
}