{
  "type": "Feature",
  "properties": {
    "addr:full":"Unit 5/ 8 Phipps Cl Deakin ACT 2600",
    "addr:housenumber":"8",
    "addr:postcode":"2600",
    "addr:street":"Phipps Cl Deakin",
    "iso:country":"AU",
    "sg:address":"Unit 5/ 8 Phipps Cl",
    "sg:city":"Deakin",
    "sg:classifiers":[
        {
            "category":"Banks & Credit Unions",
            "subcategory":"Financial Services",
            "type":"Services"
        }
    ],
    "sg:phone":"+61 2 6162 4100",
    "sg:postcode":"2600",
    "sg:province":"ACT",
    "sg:tags":[
        "advisory",
        "planning",
        "retirement"
    ],
    "wof:name":"Wybrow & Associates",
    "wof:placetype":"venue"
},
  "geometry": {"coordinates":[149.09472656200001,-35.3256378174],"type":"Point"}
}