{
  "type": "Feature",
  "properties": {
    "addr:full":"70 Cunnington St Bundaberg QLD 4670",
    "addr:housenumber":"70",
    "addr:postcode":"4670",
    "addr:street":"Cunnington St",
    "iso:country":"AU",
    "sg:address":"70 Cunnington St",
    "sg:city":"Bundaberg",
    "sg:classifiers":[
        {
            "category":"Utilities",
            "subcategory":"Electric",
            "type":"Services"
        }
    ],
    "sg:phone":"+61 7 4152 8874",
    "sg:postcode":"4670",
    "sg:province":"QLD",
    "sg:tags":[
        "electrical",
        "contractor"
    ],
    "wof:name":"Adrian Van Der Walt",
    "wof:placetype":"venue"
},
  "geometry": {"coordinates":[152.38432312,-24.8570632935],"type":"Point"}
}