{
  "type": "Feature",
  "properties": {
    "addr:full":"3/ 694 Mowbray Rd Lane Cove NSW 2066",
    "addr:housenumber":"/ 694",
    "addr:postcode":"2066",
    "addr:street":"Mowbray Rd",
    "iso:country":"AU",
    "sg:address":"3/ 694 Mowbray Rd",
    "sg:city":"Lane Cove",
    "sg:classifiers":[
        {
            "category":"Banks & Credit Unions",
            "subcategory":"Investment Brokerage",
            "type":"Services"
        }
    ],
    "sg:phone":"+61 2 9427 6791",
    "sg:postcode":"2066",
    "sg:province":"NSW",
    "sg:tags":[
        "radiator",
        "motor"
    ],
    "wof:name":"Lane Cove Radiators",
    "wof:placetype":"venue"
},
  "geometry": {"coordinates":[151.15042114299999,-33.8039016724],"type":"Point"}
}