{
  "type": "Feature",
  "properties": {
    "iso:country":"AU",
    "sg:address":"413 Chapel St",
    "sg:city":"South Yarra",
    "sg:classifiers":[
        {
            "category":"Shopping",
            "subcategory":"Clothing, Apparel, & Fashions",
            "type":"Retail Goods"
        }
    ],
    "sg:phone":"+61 3 9826 5797",
    "sg:postcode":"3141",
    "sg:province":"VIC",
    "sg:tags":[
        "jean"
    ],
    "wof:name":"The Work",
    "wof:placetype":"venue"
},
  "geometry": {"coordinates":[144.994338989,-37.8449630737],"type":"Point"}
}