{
  "type": "Feature",
  "properties": {
    "addr:full":"Suite 2, MVB, 90 Mona Vale Rd Mona Vale NSW 2103",
    "addr:housenumber":"90",
    "addr:postcode":"2103",
    "addr:street":"Mvb;Mona Vale Rd",
    "iso:country":"AU",
    "sg:address":"Suite 2, MVB, 90 Mona Vale Rd",
    "sg:city":"Mona Vale",
    "sg:classifiers":[
        {
            "category":"Social Services",
            "subcategory":"Adult Care",
            "type":"Services"
        }
    ],
    "sg:phone":"+61 1300 760 225",
    "sg:postcode":"2103",
    "sg:province":"NSW",
    "sg:tags":[
        "advocate"
    ],
    "wof:name":"Mediate Today Pty Ltd",
    "wof:placetype":"venue"
},
  "geometry": {"coordinates":[151.28941345199999,-33.6761665344],"type":"Point"}
}