{
  "type": "Feature",
  "properties": {
    "iso:country":"AU",
    "sg:address":"26 Oliver St",
    "sg:city":"Wooloowin",
    "sg:classifiers":[
        {
            "category":"Education",
            "subcategory":"Special Training",
            "type":"Public Place"
        }
    ],
    "sg:phone":"+61 7 3862 1340",
    "sg:postcode":"4030",
    "sg:province":"QLD",
    "sg:tags":[
        "development"
    ],
    "wof:name":"Bks Management Services Pty Ltd",
    "wof:placetype":"venue"
},
  "geometry": {"coordinates":[153.04274000000001,-27.424923],"type":"Point"}
}