{
  "type": "Feature",
  "properties": {
    "addr:full":"Shop 5, Railway Walk South Hampton VIC 3188",
    "addr:housenumber":"shop 5",
    "addr:postcode":"3188",
    "addr:street":"Railway Walk",
    "iso:country":"AU",
    "sg:address":"Shop 5, Railway Walk South",
    "sg:city":"Hampton",
    "sg:classifiers":[
        {
            "category":"Health Services",
            "subcategory":"Dentist",
            "type":"Services"
        }
    ],
    "sg:phone":"+61 3 9521 6093",
    "sg:postcode":"3188",
    "sg:province":"VIC",
    "sg:tags":[
        "dental",
        "prosthetist"
    ],
    "wof:name":"Antony P. Edwards",
    "wof:placetype":"venue"
},
  "geometry": {"coordinates":[144.999923706,-37.9374160767],"type":"Point"}
}