{
  "type": "Feature",
  "properties": {
    "addr:full":"Kiosk 20 Bayside Shopng Cntr 16 Veet St Frankston VIC 3199",
    "addr:housenumber":"16",
    "addr:postcode":"3199",
    "addr:street":"Veet St",
    "iso:country":"AU",
    "sg:address":"Kiosk 20 Bayside Shopng Cntr 16 Veet St",
    "sg:city":"Frankston",
    "sg:classifiers":[
        {
            "category":"Food & Beverages",
            "subcategory":"Bakery",
            "type":"Retail Goods"
        }
    ],
    "sg:phone":"+61 3 9781 1225",
    "sg:postcode":"3199",
    "sg:province":"VIC",
    "sg:tags":[
        "cake",
        "shop",
        "pastry"
    ],
    "wof:name":"Michels Patisserie",
    "wof:placetype":"venue"
},
  "geometry": {"coordinates":[144.77655029300001,-37.895236969],"type":"Point"}
}