{
  "type": "Feature",
  "properties": {
    "iso:country":"AU",
    "sg:address":"573 Gardners Rd",
    "sg:city":"Mascot",
    "sg:classifiers":[
        {
            "category":"Real Estate",
            "subcategory":"Real Estate Agent",
            "type":"Services"
        }
    ],
    "sg:phone":"+61 2 9669 1477",
    "sg:postcode":"2020",
    "sg:province":"NSW",
    "sg:tags":[
        "handyman's",
        "equipment",
        "hire",
        "builders",
        "contractor"
    ],
    "wof:name":"Wreckair Hire",
    "wof:placetype":"venue"
},
  "geometry": {"coordinates":[151.19467163100001,-33.9213027954],"type":"Point"}
}