{
  "type": "Feature",
  "properties": {
    "iso:country":"AU",
    "sg:address":"6 Lawson St",
    "sg:city":"Byron Bay",
    "sg:classifiers":[
        {
            "category":"Health Services",
            "subcategory":"Doctor",
            "type":"Services"
        }
    ],
    "sg:phone":"+61 2 6685 6206",
    "sg:postcode":"2481",
    "sg:province":"NSW",
    "sg:tags":[
        "medical",
        "practitioner"
    ],
    "wof:name":"Simpson R",
    "wof:placetype":"venue"
},
  "geometry": {"coordinates":[153.61297607399999,-28.642414093],"type":"Point"}
}