{
  "type": "Feature",
  "properties": {
    "addr:full":"10 Harper St Harvey WA 6220",
    "addr:housenumber":"10",
    "addr:postcode":"6220",
    "addr:street":"Harper St",
    "iso:country":"AU",
    "sg:address":"10 Harper St",
    "sg:city":"Harvey",
    "sg:classifiers":[
        {
            "category":"Recreation",
            "subcategory":"Amusement Park",
            "type":"Entertainment"
        }
    ],
    "sg:phone":"+61 8 9729 1631",
    "sg:postcode":"6220",
    "sg:province":"WA",
    "wof:name":"Panetta's Amusements",
    "wof:placetype":"venue"
},
  "geometry": {"coordinates":[115.897858,-33.079914],"type":"Point"}
}