{
  "type": "Feature",
  "properties": {
    "addr:full":"33 Valley Pde Glen Iris VIC 3146",
    "addr:housenumber":"33",
    "addr:postcode":"3146",
    "addr:street":"Valley Pde",
    "iso:country":"AU",
    "sg:address":"33 Valley Pde",
    "sg:city":"Glen Iris",
    "sg:classifiers":[
        {
            "category":"Professional",
            "subcategory":"Accounting & Tax Preparation",
            "type":"Services"
        }
    ],
    "sg:phone":"+61 3 9889 6656",
    "sg:postcode":"3146",
    "sg:province":"VIC",
    "sg:tags":[
        "accountant",
        "auditor"
    ],
    "wof:name":"Monthly Accounting Services",
    "wof:placetype":"venue"
},
  "geometry": {"coordinates":[145.060714722,-37.8513526917],"type":"Point"}
}