{
  "type": "Feature",
  "properties": {
    "iso:country":"AU",
    "sg:address":"McLeish Rd",
    "sg:city":"Lake Eacham",
    "sg:classifiers":[
        {
            "category":"Professional",
            "subcategory":"Engineering",
            "type":"Services"
        }
    ],
    "sg:phone":"+61 7 4095 3723",
    "sg:postcode":"4872",
    "sg:province":"QLD",
    "sg:tags":[
        "consulting",
        "engineer"
    ],
    "wof:name":"Perkowicz W.S. & Associates Pty Ltd",
    "wof:placetype":"venue"
},
  "geometry": {"coordinates":[145.622146606,-17.2955703735],"type":"Point"}
}