{
  "type": "Feature",
  "properties": {
    "addr:full":"Shop 6, Springfield Shopping Centre 1 Main St Springfield Lakes QLD 4300",
    "addr:housenumber":"shop 6;1",
    "addr:postcode":"4300",
    "addr:street":"Springfield Shopping;Main St",
    "iso:country":"AU",
    "sg:address":"Shop 6, Springfield Shopping Centre 1 Main St",
    "sg:city":"Springfield Lakes",
    "sg:classifiers":[
        {
            "category":"Shopping",
            "subcategory":"Mobile Phones",
            "type":"Retail Goods"
        }
    ],
    "sg:phone":"+61 7 3818 7333",
    "sg:postcode":"4300",
    "sg:province":"QLD",
    "sg:tags":[
        "telephone",
        "accessory"
    ],
    "wof:name":"Vodafone",
    "wof:placetype":"venue"
},
  "geometry": {"coordinates":[152.91279602,-27.6702804565],"type":"Point"}
}