{
  "type": "Feature",
  "properties": {
    "addr:full":"4 Supply Crt Kellyville NSW 2155",
    "addr:postcode":"2155",
    "addr:street":"Crt",
    "iso:country":"AU",
    "sg:address":"4 Supply Crt",
    "sg:city":"Kellyville",
    "sg:classifiers":[
        {
            "category":"Professional",
            "subcategory":"Computer Services",
            "type":"Services"
        }
    ],
    "sg:phone":"+61 2 9629 6355",
    "sg:postcode":"2155",
    "sg:province":"NSW",
    "sg:tags":[
        "consultant",
        "system"
    ],
    "wof:name":"Doug Allen & Associates Pty Ltd",
    "wof:placetype":"venue"
},
  "geometry": {"coordinates":[150.96466064399999,-33.7012939453],"type":"Point"}
}