{
  "type": "Feature",
  "properties": {
    "addr:full":"41 Florence St Mentone VIC 3194",
    "addr:housenumber":"41",
    "addr:postcode":"3194",
    "addr:street":"Florence St",
    "iso:country":"AU",
    "sg:address":"41 Florence St",
    "sg:city":"Mentone",
    "sg:classifiers":[
        {
            "category":"Real Estate",
            "subcategory":"Real Estate Agent",
            "type":"Services"
        }
    ],
    "sg:phone":"+61 3 9585 1777",
    "sg:postcode":"3194",
    "sg:province":"VIC",
    "wof:name":"Frances Shingleton Real Estate",
    "wof:placetype":"venue"
},
  "geometry": {"coordinates":[145.063262939,-37.9824943542],"type":"Point"}
}