{
  "type": "Feature",
  "properties": {
    "addr:full":"18 Glenway Rd Hallett Cove SA 5158",
    "addr:housenumber":"18",
    "addr:postcode":"5158",
    "addr:street":"Glenway Rd",
    "iso:country":"AU",
    "sg:address":"18 Glenway Rd",
    "sg:city":"Hallett Cove",
    "sg:classifiers":[
        {
            "category":"Food & Beverages",
            "subcategory":"Specialty",
            "type":"Retail Goods"
        }
    ],
    "sg:phone":"+61 8 8322 8602",
    "sg:postcode":"5158",
    "sg:province":"SA",
    "sg:tags":[
        "product",
        "health"
    ],
    "wof:name":"Ramedica Australia Pty Ltd",
    "wof:placetype":"venue"
},
  "geometry": {"coordinates":[138.518066406,-35.0661087036],"type":"Point"}
}