{
  "type": "Feature",
  "properties": {
    "addr:full":"14 Mason Drv Braeside VIC 3195",
    "addr:housenumber":"14",
    "addr:postcode":"3195",
    "addr:street":"Mason Drv",
    "iso:country":"AU",
    "sg:address":"14 Mason Drv",
    "sg:city":"Braeside",
    "sg:classifiers":[
        {
            "category":"Home & Garden",
            "subcategory":"Building Materials",
            "type":"Retail Goods"
        }
    ],
    "sg:phone":"+61 3 9587 6021",
    "sg:postcode":"3195",
    "sg:province":"VIC",
    "sg:tags":[
        "balustrading"
    ],
    "wof:name":"sga Glazing Contractors",
    "wof:placetype":"venue"
},
  "geometry": {"coordinates":[145.110305786,-37.9991722107],"type":"Point"}
}