{
  "type": "Feature",
  "properties": {
    "addr:full":"28 Norrish St Tambellup WA 6320",
    "addr:housenumber":"28",
    "addr:postcode":"6320",
    "addr:street":"Norrish St",
    "iso:country":"AU",
    "sg:address":"28 Norrish St",
    "sg:city":"Tambellup",
    "sg:classifiers":[
        {
            "category":"Food & Beverages",
            "subcategory":"Supermarket",
            "type":"Retail Goods"
        }
    ],
    "sg:phone":"+61 8 9825 1007",
    "sg:postcode":"6320",
    "sg:province":"WA",
    "sg:tags":[
        "grocery",
        "store"
    ],
    "wof:name":"Tambellup Settler's Mart",
    "wof:placetype":"venue"
},
  "geometry": {"coordinates":[117.642082214,-34.0453224182],"type":"Point"}
}