{
  "type": "Feature",
  "properties": {
    "addr:full":"42 Hastings River Drv Port Macquarie NSW 2444",
    "addr:housenumber":"42",
    "addr:postcode":"2444",
    "addr:street":"Hastings River Drv",
    "iso:country":"AU",
    "sg:address":"42 Hastings River Drv",
    "sg:city":"Port Macquarie",
    "sg:classifiers":[
        {
            "category":"Organizations",
            "subcategory":"Community Association",
            "type":"Services"
        }
    ],
    "sg:phone":"+61 2 6584 1241",
    "sg:postcode":"2444",
    "sg:province":"NSW",
    "sg:tags":[
        "organisation",
        "family",
        "welfare"
    ],
    "wof:name":"UnitingCare Burnside Family Support Centre",
    "wof:placetype":"venue"
},
  "geometry": {"coordinates":[152.892258,-31.432247],"type":"Point"}
}