{
  "type": "Feature",
  "properties": {
    "addr:full":"Shed 3/ 18B Goggs St Toowoomba QLD 4350",
    "addr:housenumber":"3 / 18b",
    "addr:postcode":"4350",
    "addr:street":"Goggs St",
    "iso:country":"AU",
    "sg:address":"Shed 3/ 18B Goggs St",
    "sg:city":"Toowoomba",
    "sg:classifiers":[
        {
            "category":"Autos & Motor Vehicles",
            "subcategory":"Auto Supplies",
            "type":"Retail Goods"
        }
    ],
    "sg:phone":"+61 7 4613 0313",
    "sg:postcode":"4350",
    "sg:province":"QLD",
    "sg:tags":[
        "part",
        "cycles",
        "accessory"
    ],
    "wof:name":"Mayhem Chopperworks Australia",
    "wof:placetype":"venue"
},
  "geometry": {"coordinates":[151.94528199999999,-27.566341],"type":"Point"}
}