{
  "type": "Feature",
  "properties": {
    "addr:full":"Shed 2 Lot 24 Cooper St Chinchilla QLD 4413",
    "addr:housenumber":"2 lot 24",
    "addr:postcode":"4413",
    "addr:street":"Cooper St",
    "iso:country":"AU",
    "sg:address":"Shed 2 Lot 24 Cooper St",
    "sg:city":"Chinchilla",
    "sg:classifiers":[
        {
            "category":"Retail",
            "subcategory":"Auto Repair",
            "type":"Services"
        }
    ],
    "sg:phone":"+61 7 4669 1333",
    "sg:postcode":"4413",
    "sg:province":"QLD",
    "sg:tags":[
        "repairer",
        "motor",
        "engineer"
    ],
    "wof:name":"Car Line Mechanical Repairs",
    "wof:placetype":"venue"
},
  "geometry": {"coordinates":[150.64198303200001,-26.7521724701],"type":"Point"}
}