{
  "type": "Feature",
  "properties": {
    "iso:country":"AU",
    "sg:address":"24 Henry St",
    "sg:city":"Rockingham",
    "sg:classifiers":[
        {
            "category":"Utilities",
            "subcategory":"Electric",
            "type":"Services"
        }
    ],
    "sg:phone":"+61 413 714 550",
    "sg:postcode":"6168",
    "sg:province":"WA",
    "sg:tags":[
        "electrical",
        "contractor"
    ],
    "wof:name":"Torain Electrics",
    "wof:placetype":"venue"
},
  "geometry": {"coordinates":[115.754204,-32.289803],"type":"Point"}
}