{
  "type": "Feature",
  "properties": {
    "iso:country":"AU",
    "sg:address":"37 Onkara Crt",
    "sg:city":"Eltham",
    "sg:classifiers":[
        {
            "category":"Building & Trades",
            "subcategory":"Construction",
            "type":"Services"
        }
    ],
    "sg:phone":"+61 3 9439 9846",
    "sg:postcode":"3095",
    "sg:province":"VIC",
    "sg:tags":[
        "concrete",
        "contractor"
    ],
    "wof:name":"Bulleen Paving Co Pty Ltd",
    "wof:placetype":"venue"
},
  "geometry": {"coordinates":[145.17071533199999,-37.7100448608],"type":"Point"}
}