{
  "type": "Feature",
  "properties": {
    "iso:country":"AU",
    "sg:address":"PO Box 2049",
    "sg:city":"Gateshead Delivery Cntr",
    "sg:classifiers":[
        {
            "category":"Professional",
            "subcategory":"Employment Agencies",
            "type":"Services"
        }
    ],
    "sg:phone":"+61 2 4957 0047",
    "sg:postcode":"2290",
    "sg:province":"NSW",
    "sg:tags":[
        "occupational",
        "therapist"
    ],
    "wof:name":"Gai Lovell Paediatric Occupational Therapy",
    "wof:placetype":"venue"
},
  "geometry": {"coordinates":[151.699386597,-32.9838905334],"type":"Point"}
}