{
  "type": "Feature",
  "properties": {
    "addr:full":"Shp 2/ 24 Riverview St North Richmond NSW 2754",
    "addr:housenumber":"/ 24",
    "addr:postcode":"2754",
    "addr:street":"Riverview St",
    "iso:country":"AU",
    "sg:address":"Shp 2/ 24 Riverview St",
    "sg:city":"North Richmond",
    "sg:classifiers":[
        {
            "category":"Personal",
            "subcategory":"Tanning Parlor",
            "type":"Services"
        }
    ],
    "sg:phone":"+61 2 4571 4774",
    "sg:postcode":"2754",
    "sg:province":"NSW",
    "sg:tags":[
        "solarium"
    ],
    "wof:name":"Chic Hair Design",
    "wof:placetype":"venue"
},
  "geometry": {"coordinates":[150.71966552699999,-33.5814476013],"type":"Point"}
}