{
  "type": "Feature",
  "properties": {
    "iso:country":"AU",
    "sg:address":"65 Armentieres St",
    "sg:city":"Kedron",
    "sg:classifiers":[
        {
            "category":"Social Services",
            "subcategory":"Retirement Home",
            "type":"Services"
        }
    ],
    "sg:phone":"+61 7 3357 6310",
    "sg:postcode":"4031",
    "sg:province":"QLD",
    "sg:tags":[
        "life",
        "coaching"
    ],
    "wof:name":"Manfred Luck",
    "wof:placetype":"venue"
},
  "geometry": {"coordinates":[153.02778599999999,-27.406626],"type":"Point"}
}