{
  "type": "Feature",
  "properties": {
    "addr:full":"North Road Medical Cntr 409 North Rd Caulfield East VIC 3145",
    "addr:housenumber":"409",
    "addr:postcode":"3145",
    "addr:street":"North;North Rd",
    "iso:country":"AU",
    "sg:address":"North Road Medical Cntr 409 North Rd",
    "sg:city":"Caulfield East",
    "sg:classifiers":[
        {
            "category":"Health Services",
            "subcategory":"Health Practitioner",
            "type":"Services"
        }
    ],
    "sg:phone":"+61 3 9576 9311",
    "sg:postcode":"3145",
    "sg:province":"VIC",
    "sg:tags":[
        "psychologist"
    ],
    "wof:name":"Levy Betty Dr",
    "wof:placetype":"venue"
},
  "geometry": {"coordinates":[145.03416442899999,-37.9030303955],"type":"Point"}
}