{
  "type": "Feature",
  "properties": {
    "addr:full":"18-20 Ross St Parramatta NSW 2150",
    "addr:housenumber":"18-20",
    "addr:postcode":"2150",
    "addr:street":"Ross St",
    "iso:country":"AU",
    "sg:address":"18-20 Ross St",
    "sg:city":"Parramatta",
    "sg:classifiers":[
        {
            "category":"Social Services",
            "type":"Services"
        }
    ],
    "sg:phone":"+61 2 9890 1988",
    "sg:postcode":"2150",
    "sg:province":"NSW",
    "sg:tags":[
        "domestic",
        "help"
    ],
    "wof:name":"Home Care Service Of N.S.W.",
    "wof:placetype":"venue"
},
  "geometry": {"coordinates":[151.0572052,-33.7738418579],"type":"Point"}
}