{
  "type": "Feature",
  "properties": {
    "addr:full":"566 Chittering Rd Bullsbrook WA 6084",
    "addr:housenumber":"566",
    "addr:postcode":"6084",
    "addr:street":"Chittering Rd",
    "iso:country":"AU",
    "sg:address":"566 Chittering Rd",
    "sg:city":"Bullsbrook",
    "sg:classifiers":[
        {
            "category":"Mining & Drilling",
            "type":"Manufacturing & Wholesale Goods"
        }
    ],
    "sg:phone":"+61 427 539 674",
    "sg:postcode":"6084",
    "sg:province":"WA",
    "sg:tags":[
        "boring",
        "contractor"
    ],
    "wof:name":"Paz Drilling Services",
    "wof:placetype":"venue"
},
  "geometry": {"coordinates":[116.03237915,-31.6675739288],"type":"Point"}
}