{
  "type": "Feature",
  "properties": {
    "addr:full":"170 Hardgrave Rd West End (Brisbane) QLD 4101",
    "addr:housenumber":"170",
    "addr:postcode":"4101",
    "addr:street":"Hardgrave Rd",
    "iso:country":"AU",
    "sg:address":"170 Hardgrave Rd",
    "sg:city":"West End (Brisbane)",
    "sg:classifiers":[
        {
            "category":"Cafe",
            "type":"Food & Drink"
        }
    ],
    "sg:phone":"+61 7 3844 1163",
    "sg:postcode":"4101",
    "sg:province":"QLD",
    "wof:name":"Lefkas Greek Taverna",
    "wof:placetype":"venue"
},
  "geometry": {"coordinates":[153.00633239699999,-27.4863262177],"type":"Point"}
}