{
  "type": "Feature",
  "properties": {
    "iso:country":"AU",
    "sg:address":"Unit 1, 16 Ledgar Rd",
    "sg:city":"Balcatta",
    "sg:classifiers":[
        {
            "category":"Building & Trades",
            "subcategory":"Equipment Rental",
            "type":"Services"
        }
    ],
    "sg:phone":"+61 8 9345 3499",
    "sg:postcode":"6021",
    "sg:province":"WA",
    "sg:tags":[
        "saw"
    ],
    "wof:name":"Carbide Tool Industries Pty Ltd",
    "wof:placetype":"venue"
},
  "geometry": {"coordinates":[115.80342865,-31.8649215698],"type":"Point"}
}