{
  "type": "Feature",
  "properties": {
    "iso:country":"AU",
    "sg:address":"Shop 3/ 90 Aumuller St",
    "sg:city":"Portsmith",
    "sg:classifiers":[
        {
            "category":"Building & Trades",
            "subcategory":"Construction",
            "type":"Services"
        }
    ],
    "sg:phone":"+61 7 4035 5333",
    "sg:postcode":"4870",
    "sg:province":"QLD",
    "sg:tags":[
        "ceiling"
    ],
    "wof:name":"Interline Plasterers P/L",
    "wof:placetype":"venue"
},
  "geometry": {"coordinates":[145.76614379899999,-16.9400596619],"type":"Point"}
}