{
  "type": "Feature",
  "properties": {
    "addr:full":"247 Main Rd Willunga SA 5172",
    "addr:housenumber":"247",
    "addr:postcode":"5172",
    "addr:street":"Main Rd",
    "iso:country":"AU",
    "sg:address":"247 Main Rd",
    "sg:city":"Willunga",
    "sg:classifiers":[
        {
            "category":"Education",
            "subcategory":"School",
            "type":"Public Place"
        }
    ],
    "sg:phone":"+61 8 8556 2234",
    "sg:postcode":"5172",
    "sg:province":"SA",
    "sg:tags":[
        "state",
        "except",
        "nsw"
    ],
    "wof:name":"Willunga (OSHC)",
    "wof:placetype":"venue"
},
  "geometry": {"coordinates":[138.54986572300001,-35.2235603333],"type":"Point"}
}