{
  "type": "Feature",
  "properties": {
    "iso:country":"AU",
    "sg:address":"Suite 3 50 Assembly Drv",
    "sg:city":"Tullamarine",
    "sg:classifiers":[
        {
            "category":"Professional",
            "subcategory":"Computer Services",
            "type":"Services"
        }
    ],
    "sg:phone":"+61 3 9338 2271",
    "sg:postcode":"3043",
    "sg:province":"VIC",
    "sg:tags":[
        "package",
        "software"
    ],
    "wof:name":"Eagle Developments International Pty Ltd",
    "wof:placetype":"venue"
},
  "geometry": {"coordinates":[144.86607360799999,-37.7074546814],"type":"Point"}
}