{
  "type": "Feature",
  "properties": {
    "iso:country":"AU",
    "sg:address":"Unit 9, 100 Bundall Rd Bundall Ctr (Behind Westpac)",
    "sg:city":"Bundall",
    "sg:classifiers":[
        {
            "category":"Retail",
            "subcategory":"Repair Shop",
            "type":"Services"
        }
    ],
    "sg:phone":"+61 7 5538 4533",
    "sg:postcode":"4217",
    "sg:province":"QLD",
    "sg:tags":[
        "mending",
        "clothing",
        "alteration"
    ],
    "wof:name":"Bambos Clothing Alteration & Repair Specialists",
    "wof:placetype":"venue"
},
  "geometry": {"coordinates":[153.41302490199999,-28.0049571991],"type":"Point"}
}