{
  "type": "Feature",
  "properties": {
    "addr:full":"200 Mirrabooka Ave Alexander Heights WA 6064",
    "addr:housenumber":"200",
    "addr:postcode":"6064",
    "addr:street":"Mirrabooka Ave",
    "iso:country":"AU",
    "sg:address":"200 Mirrabooka Ave",
    "sg:city":"Alexander Heights",
    "sg:classifiers":[
        {
            "category":"Autos & Motor Vehicles",
            "subcategory":"Fuel & Gas Station",
            "type":"Retail Goods"
        }
    ],
    "sg:phone":"+61 8 9343 4422",
    "sg:postcode":"6064",
    "sg:province":"WA",
    "wof:name":"Gull Petroleum (WA) Pty Ltd",
    "wof:placetype":"venue"
},
  "geometry": {"coordinates":[115.852577209,-31.8299236298],"type":"Point"}
}