{
  "type": "Feature",
  "properties": {
    "iso:country":"AU",
    "sg:address":"Mackenzie Rd",
    "sg:city":"West Melbourne",
    "sg:classifiers":[
        {
            "category":"Ferry Terminal",
            "type":"Transportation"
        }
    ],
    "sg:phone":"+61 3 8387 1900",
    "sg:postcode":"3003",
    "sg:province":"VIC",
    "sg:tags":[
        "bulk",
        "storage",
        "liquid"
    ],
    "wof:name":"Terminals Pty Ltd",
    "wof:placetype":"venue"
},
  "geometry": {"coordinates":[144.93093872099999,-37.8105697632],"type":"Point"}
}