{
  "type": "Feature",
  "properties": {
    "iso:country":"AU",
    "sg:address":"70 Lakelands Drv",
    "sg:city":"Gnangara",
    "sg:classifiers":[
        {
            "category":"Mining & Drilling",
            "type":"Manufacturing & Wholesale Goods"
        }
    ],
    "sg:phone":"+61 8 9306 2733",
    "sg:postcode":"6065",
    "sg:province":"WA",
    "sg:tags":[
        "boring",
        "contractor"
    ],
    "wof:name":"Westoz Drilling Company Pty Ltd",
    "wof:placetype":"venue"
},
  "geometry": {"coordinates":[115.85220336899999,-31.7832756042],"type":"Point"}
}