{
  "type": "Feature",
  "properties": {
    "addr:full":"73 Veterans Pde Collaroy Plateau NSW 2097",
    "addr:housenumber":"73",
    "addr:postcode":"2097",
    "addr:street":"Veterans Pde",
    "iso:country":"AU",
    "sg:address":"73 Veterans Pde",
    "sg:city":"Collaroy Plateau",
    "sg:classifiers":[
        {
            "category":"Health Services",
            "subcategory":"Doctor",
            "type":"Services"
        }
    ],
    "sg:phone":"+61 2 9971 8222",
    "sg:postcode":"2097",
    "sg:province":"NSW",
    "sg:tags":[
        "medical",
        "practitioner"
    ],
    "wof:name":"Wai C W",
    "wof:placetype":"venue"
},
  "geometry": {"coordinates":[151.28684997600001,-33.7264938354],"type":"Point"}
}