{
  "type": "Feature",
  "properties": {
    "addr:full":"U1/ 23 Brookhollow Ave Baulkham Hills NSW 2153",
    "addr:housenumber":"23",
    "addr:postcode":"2153",
    "addr:street":"U1 /;Brookhollow Ave",
    "iso:country":"AU",
    "sg:address":"U1/ 23 Brookhollow Ave",
    "sg:city":"Baulkham Hills",
    "sg:classifiers":[
        {
            "category":"Sports & Exercise",
            "subcategory":"Gym",
            "type":"Entertainment"
        }
    ],
    "sg:phone":"+61 2 9680 3050",
    "sg:postcode":"2153",
    "sg:province":"NSW",
    "sg:tags":[
        "health",
        "fitness"
    ],
    "wof:name":"Livit Lifestyles",
    "wof:placetype":"venue"
},
  "geometry": {"coordinates":[150.96900939899999,-33.7330932617],"type":"Point"}
}