{
  "type": "Feature",
  "properties": {
    "iso:country":"AU",
    "sg:address":"580 Anzac Ave",
    "sg:city":"Drayton",
    "sg:classifiers":[
        {
            "category":"Building & Trades",
            "subcategory":"Construction",
            "type":"Services"
        }
    ],
    "sg:phone":"+61 7 4614 0077",
    "sg:postcode":"4350",
    "sg:province":"QLD",
    "sg:tags":[
        "welding"
    ],
    "wof:name":"Sub-Arc",
    "wof:placetype":"venue"
},
  "geometry": {"coordinates":[151.89849899999999,-27.603933],"type":"Point"}
}