{
  "type": "Feature",
  "properties": {
    "addr:full":"93 Booralie Rd Terrey Hills NSW 2084",
    "addr:housenumber":"93",
    "addr:postcode":"2084",
    "addr:street":"Booralie Rd",
    "iso:country":"AU",
    "sg:address":"93 Booralie Rd",
    "sg:city":"Terrey Hills",
    "sg:classifiers":[
        {
            "category":"Utilities",
            "subcategory":"Fuel Oil & Lpg",
            "type":"Services"
        }
    ],
    "sg:phone":"+61 2 9450 0257",
    "sg:postcode":"2084",
    "sg:province":"NSW",
    "sg:tags":[
        "merchant"
    ],
    "wof:name":"Down Under Firewood",
    "wof:placetype":"venue"
},
  "geometry": {"coordinates":[151.21580505399999,-33.6783905029],"type":"Point"}
}