{
  "type": "Feature",
  "properties": {
    "addr:full":"Unit 2/ 9 Oxleigh Drv Malaga WA 6090",
    "addr:housenumber":"9",
    "addr:postcode":"6090",
    "addr:street":"Oxleigh Drv",
    "iso:country":"AU",
    "sg:address":"Unit 2/ 9 Oxleigh Drv",
    "sg:city":"Malaga",
    "sg:classifiers":[
        {
            "category":"Wholesale",
            "subcategory":"Farm Supplies",
            "type":"Manufacturing & Wholesale Goods"
        }
    ],
    "sg:phone":"+61 8 9249 9599",
    "sg:postcode":"6090",
    "sg:province":"WA",
    "sg:tags":[
        "equipment"
    ],
    "wof:name":"Prestige Communications",
    "wof:placetype":"venue"
},
  "geometry": {"coordinates":[115.885856628,-31.8523578644],"type":"Point"}
}