{
  "type": "Feature",
  "properties": {
    "iso:country":"AU",
    "sg:address":"16 Chalder St",
    "sg:city":"Marrickville",
    "sg:classifiers":[
        {
            "category":"Building & Trades",
            "subcategory":"Equipment Rental",
            "type":"Services"
        }
    ],
    "sg:phone":"+61 2 9792 6129",
    "sg:postcode":"2204",
    "sg:province":"NSW",
    "sg:tags":[
        "party",
        "hire"
    ],
    "wof:name":"A Essential Coverings",
    "wof:placetype":"venue"
},
  "geometry": {"coordinates":[151.164124,-33.907585],"type":"Point"}
}