{
  "type": "Feature",
  "properties": {
    "addr:full":"93 Orsmond St Hindmarsh SA 5007",
    "addr:housenumber":"93",
    "addr:postcode":"5007",
    "addr:street":"Orsmond St",
    "iso:country":"AU",
    "sg:address":"93 Orsmond St",
    "sg:city":"Hindmarsh",
    "sg:classifiers":[
        {
            "category":"Professional",
            "subcategory":"Computer Services",
            "type":"Services"
        }
    ],
    "sg:phone":"+61 1300 367 686",
    "sg:postcode":"5007",
    "sg:province":"SA",
    "sg:tags":[
        "equipment",
        "networking",
        "installation"
    ],
    "wof:name":"Emerson Network Power",
    "wof:placetype":"venue"
},
  "geometry": {"coordinates":[138.56634521500001,-34.9033432007],"type":"Point"}
}