{
  "type": "Feature",
  "properties": {
    "addr:full":"30 Queen St Harrisville QLD 4307",
    "addr:housenumber":"30",
    "addr:postcode":"4307",
    "addr:street":"Queen St",
    "iso:country":"AU",
    "sg:address":"30 Queen St",
    "sg:city":"Harrisville",
    "sg:classifiers":[
        {
            "category":"Personal",
            "subcategory":"Massage",
            "type":"Services"
        }
    ],
    "sg:phone":"+61 7 5467 1999",
    "sg:postcode":"4307",
    "sg:province":"QLD",
    "sg:tags":[
        "therapy"
    ],
    "wof:name":"Body Wishez",
    "wof:placetype":"venue"
},
  "geometry": {"coordinates":[152.668167114,-27.8112983704],"type":"Point"}
}