{
  "type": "Feature",
  "properties": {
    "addr:full":"55 Caloundra Rd Caloundra QLD 4551",
    "addr:housenumber":"55",
    "addr:postcode":"4551",
    "addr:street":"Caloundra Rd",
    "iso:country":"AU",
    "sg:address":"55 Caloundra Rd",
    "sg:city":"Caloundra",
    "sg:classifiers":[
        {
            "category":"Home & Garden",
            "subcategory":"Furniture",
            "type":"Retail Goods"
        }
    ],
    "sg:phone":"+61 7 5491 9633",
    "sg:postcode":"4551",
    "sg:province":"QLD",
    "sg:tags":[
        "outdoor"
    ],
    "wof:name":"HotSpring Portable Spas",
    "wof:placetype":"venue"
},
  "geometry": {"coordinates":[153.107055664,-26.794927597],"type":"Point"}
}