{
  "type": "Feature",
  "properties": {
    "iso:country":"AU",
    "sg:address":"439 Chapel St",
    "sg:city":"South Yarra",
    "sg:classifiers":[
        {
            "category":"Health Services",
            "subcategory":"Optometrist",
            "type":"Services"
        }
    ],
    "sg:phone":"+61 3 9827 1089",
    "sg:postcode":"3141",
    "sg:province":"VIC",
    "wof:name":"Howden Olga",
    "wof:placetype":"venue"
},
  "geometry": {"coordinates":[144.99449157699999,-37.8442459106],"type":"Point"}
}