{
  "type": "Feature",
  "properties": {
    "addr:full":"\"Ackworth\"4970 Illawarra Hwy Robertson NSW 2577",
    "addr:postcode":"4970;2577",
    "addr:street":"Illawarra Hwy",
    "iso:country":"AU",
    "sg:address":"\"Ackworth\"4970 Illawarra Hwy",
    "sg:city":"Robertson",
    "sg:classifiers":[
        {
            "category":"Shopping",
            "type":"Retail Goods"
        }
    ],
    "sg:phone":"+61 2 4885 1329",
    "sg:postcode":"2577",
    "sg:province":"NSW",
    "sg:tags":[
        "agent",
        "stock"
    ],
    "wof:name":"Mackey R J Real Estate Stock & Station Agents",
    "wof:placetype":"venue"
},
  "geometry": {"coordinates":[150.572509766,-34.5898475647],"type":"Point"}
}