{
  "type": "Feature",
  "properties": {
    "addr:full":"564 Marrickville Rd Dulwich Hill NSW 2203",
    "addr:housenumber":"564",
    "addr:postcode":"2203",
    "addr:street":"Marrickville Rd",
    "iso:country":"AU",
    "sg:address":"564 Marrickville Rd",
    "sg:city":"Dulwich Hill",
    "sg:classifiers":[
        {
            "category":"Real Estate",
            "subcategory":"Real Estate Agent",
            "type":"Services"
        }
    ],
    "sg:phone":"+61 2 9564 3388",
    "sg:postcode":"2203",
    "sg:province":"NSW",
    "wof:name":"John Ness Realty",
    "wof:placetype":"venue"
},
  "geometry": {"coordinates":[151.14260899999999,-33.903698],"type":"Point"}
}