{
  "type": "Feature",
  "properties": {
    "iso:country":"AU",
    "sg:address":"8 Welder Rd",
    "sg:city":"Seven Hills",
    "sg:classifiers":[
        {
            "category":"Shopping",
            "subcategory":"Stationery & Office Supplies",
            "type":"Retail Goods"
        }
    ],
    "sg:phone":"+61 2 9674 2222",
    "sg:postcode":"2147",
    "sg:province":"NSW",
    "sg:tags":[
        "packaging",
        "material"
    ],
    "wof:name":"ITT Jetpak",
    "wof:placetype":"venue"
},
  "geometry": {"coordinates":[150.957763672,-33.7697563171],"type":"Point"}
}