{
  "type": "Feature",
  "properties": {
    "iso:country":"AU",
    "sg:address":"48b Archibald St",
    "sg:city":"Dalby",
    "sg:classifiers":[
        {
            "category":"Health Services",
            "subcategory":"Dentist",
            "type":"Services"
        }
    ],
    "sg:phone":"+61 7 4662 5630",
    "sg:postcode":"4405",
    "sg:province":"QLD",
    "wof:name":"Renner M Paul",
    "wof:placetype":"venue"
},
  "geometry": {"coordinates":[151.26371765100001,-27.1807060242],"type":"Point"}
}