{
  "type": "Feature",
  "properties": {
    "iso:country":"AU",
    "sg:address":"13 Elliott Ave",
    "sg:city":"Gulfview Heights",
    "sg:classifiers":[
        {
            "category":"Home & Garden",
            "subcategory":"Building Materials",
            "type":"Retail Goods"
        }
    ],
    "sg:phone":"+61 417 866 396",
    "sg:postcode":"5096",
    "sg:province":"SA",
    "sg:tags":[
        "lawn",
        "cutting",
        "maintenance"
    ],
    "wof:name":"Cutting Edge",
    "wof:placetype":"venue"
},
  "geometry": {"coordinates":[138.66531372099999,-34.7915115356],"type":"Point"}
}