{
  "type": "Feature",
  "properties": {
    "iso:country":"AU",
    "sg:address":"Ste 5-6, 116 Brookes St",
    "sg:city":"Fortitude Valley",
    "sg:classifiers":[
        {
            "category":"Professional",
            "subcategory":"Computer Services",
            "type":"Services"
        }
    ],
    "sg:phone":"+61 1300 855 225",
    "sg:postcode":"4006",
    "sg:province":"QLD",
    "sg:tags":[
        "tele-communications",
        "consultant"
    ],
    "wof:name":"Avoncore Direct",
    "wof:placetype":"venue"
},
  "geometry": {"coordinates":[153.03884887699999,-27.4540042877],"type":"Point"}
}