{
  "type": "Feature",
  "properties": {
    "addr:full":"17 Downs St Ipswich QLD 4305",
    "addr:housenumber":"17",
    "addr:postcode":"4305",
    "addr:street":"Downs St",
    "iso:country":"AU",
    "sg:address":"17 Downs St",
    "sg:city":"Ipswich",
    "sg:classifiers":[
        {
            "category":"Health Services",
            "subcategory":"Optometrist",
            "type":"Services"
        }
    ],
    "sg:phone":"+61 7 3281 0822",
    "sg:postcode":"4305",
    "sg:province":"QLD",
    "wof:name":"New Look Eyewear",
    "wof:placetype":"venue"
},
  "geometry": {"coordinates":[152.760421753,-27.6067123413],"type":"Point"}
}