{
  "type": "Feature",
  "properties": {
    "addr:full":"993 Bells Line Of Road Kurrajong Hills NSW 2758",
    "addr:housenumber":"993",
    "addr:postcode":"2758",
    "addr:street":"Bells Line Of Road",
    "iso:country":"AU",
    "sg:address":"993 Bells Line Of Road",
    "sg:city":"Kurrajong Hills",
    "sg:classifiers":[
        {
            "category":"Retail",
            "subcategory":"Event Space",
            "type":"Services"
        }
    ],
    "sg:phone":"+61 2 4567 7711",
    "sg:postcode":"2758",
    "sg:province":"NSW",
    "sg:tags":[
        "venue",
        "reception",
        "wedding"
    ],
    "wof:name":"Loxley On Bellbird Hill",
    "wof:placetype":"venue"
},
  "geometry": {"coordinates":[150.642486572,-33.5418128967],"type":"Point"}
}