{
  "type": "Feature",
  "properties": {
    "addr:full":"7 Stockholm Ave Hassall Grove NSW 2761",
    "addr:housenumber":"7",
    "addr:postcode":"2761",
    "addr:street":"Stockholm Ave",
    "iso:country":"AU",
    "sg:address":"7 Stockholm Ave",
    "sg:city":"Hassall Grove",
    "sg:classifiers":[
        {
            "category":"Professional",
            "subcategory":"Business Services",
            "type":"Services"
        }
    ],
    "sg:phone":"+61 410 067 404",
    "sg:postcode":"2761",
    "sg:province":"NSW",
    "sg:tags":[
        "exporter"
    ],
    "wof:name":"ABESHO International Pty Ltd",
    "wof:placetype":"venue"
},
  "geometry": {"coordinates":[150.83345,-33.730175],"type":"Point"}
}