{
  "type": "Feature",
  "properties": {
    "addr:full":"140 Victoria St Potts Point NSW 2011",
    "addr:housenumber":"140",
    "addr:postcode":"2011",
    "addr:street":"Victoria St",
    "iso:country":"AU",
    "sg:address":"140 Victoria St",
    "sg:city":"Potts Point",
    "sg:classifiers":[
        {
            "category":"Cafe",
            "type":"Food & Drink"
        }
    ],
    "sg:phone":"+61 2 9356 3206",
    "sg:postcode":"2011",
    "sg:province":"NSW",
    "wof:name":"One Forty Cafe Artiste",
    "wof:placetype":"venue"
},
  "geometry": {"coordinates":[151.22267150900001,-33.8732910156],"type":"Point"}
}