{
  "type": "Feature",
  "properties": {
    "iso:country":"AU",
    "sg:address":"Shp2/ 1 Manning St",
    "sg:city":"Kingswood",
    "sg:classifiers":[
        {
            "category":"Food & Beverages",
            "subcategory":"Groceries & Convenience Stores",
            "type":"Retail Goods"
        }
    ],
    "sg:phone":"+61 2 4736 6975",
    "sg:postcode":"2747",
    "sg:province":"NSW",
    "wof:name":"Manning Convenience Store",
    "wof:placetype":"venue"
},
  "geometry": {"coordinates":[150.725708008,-33.7638778687],"type":"Point"}
}