{
  "type": "Feature",
  "properties": {
    "addr:full":"128 Glen Osmond Rd Parkside SA 5063",
    "addr:housenumber":"128",
    "addr:postcode":"5063",
    "addr:street":"Glen Osmond Rd",
    "iso:country":"AU",
    "sg:address":"128 Glen Osmond Rd",
    "sg:city":"Parkside",
    "sg:classifiers":[
        {
            "category":"Professional",
            "type":"Services"
        }
    ],
    "sg:phone":"+61 8 8373 5707",
    "sg:postcode":"5063",
    "sg:province":"SA",
    "sg:tags":[
        "shop",
        "fitting"
    ],
    "wof:name":"B.E. Building Services P/L",
    "wof:placetype":"venue"
},
  "geometry": {"coordinates":[138.623504639,-34.9454803467],"type":"Point"}
}