{
  "type": "Feature",
  "properties": {
    "addr:full":"Cnr Thornborough Rd & Quarry Way Mandurah WA 6210",
    "addr:postcode":"6210",
    "addr:street":"Cnr Thornborough Rd & Quarry Way",
    "iso:country":"AU",
    "sg:address":"Cnr Thornborough Rd & Quarry Way",
    "sg:city":"Mandurah",
    "sg:classifiers":[
        {
            "category":"Home & Garden",
            "subcategory":"Building Materials",
            "type":"Retail Goods"
        }
    ],
    "sg:phone":"+61 8 9581 7890",
    "sg:postcode":"6210",
    "sg:province":"WA",
    "sg:tags":[
        "fitting",
        "door"
    ],
    "wof:name":"Mandurah Roller Door Centre",
    "wof:placetype":"venue"
},
  "geometry": {"coordinates":[115.752792,-32.512474],"type":"Point"}
}