{
  "type": "Feature",
  "properties": {
    "iso:country":"AU",
    "sg:address":"2807 Gold Coast Hwy",
    "sg:city":"Surfers Paradise",
    "sg:classifiers":[
        {
            "category":"Retail",
            "subcategory":"Event Space",
            "type":"Services"
        }
    ],
    "sg:phone":"+61 7 5592 9900",
    "sg:postcode":"4217",
    "sg:province":"QLD",
    "sg:tags":[
        "function",
        "organiser"
    ],
    "wof:name":"Crowne Plaza",
    "wof:placetype":"venue"
},
  "geometry": {"coordinates":[153.429595947,-28.0181503296],"type":"Point"}
}