{
  "type": "Feature",
  "properties": {
    "addr:full":"25 Jacaranda Ave Woodridge QLD 4114",
    "addr:housenumber":"25",
    "addr:postcode":"4114",
    "addr:street":"Jacaranda Ave",
    "iso:country":"AU",
    "sg:address":"25 Jacaranda Ave",
    "sg:city":"Woodridge",
    "sg:classifiers":[
        {
            "category":"Education",
            "subcategory":"School",
            "type":"Public Place"
        }
    ],
    "sg:phone":"+61 7 3209 4755",
    "sg:postcode":"4114",
    "sg:province":"QLD",
    "wof:name":"Burragah Aboriginal & Islander Pre-School",
    "wof:placetype":"venue"
},
  "geometry": {"coordinates":[153.10578918499999,-27.6437549591],"type":"Point"}
}