{
  "type": "Feature",
  "properties": {
    "addr:full":"Level 9, 111 St Georges Tce Perth WA 6000",
    "addr:housenumber":"111",
    "addr:postcode":"6000",
    "addr:street":"St Georges Tce",
    "iso:country":"AU",
    "sg:address":"Level 9, 111 St Georges Tce",
    "sg:city":"Perth",
    "sg:classifiers":[
        {
            "category":"Professional",
            "subcategory":"Management & Consulting",
            "type":"Services"
        }
    ],
    "sg:phone":"+61 8 9323 0222",
    "sg:postcode":"6000",
    "sg:province":"WA",
    "sg:tags":[
        "consultant"
    ],
    "wof:name":"Hudson",
    "wof:placetype":"venue"
},
  "geometry": {"coordinates":[115.856330872,-31.9547386169],"type":"Point"}
}