{
  "type": "Feature",
  "properties": {
    "addr:full":"Crossing Rd Mylor SA 5153",
    "addr:postcode":"5153",
    "addr:street":"Crossing Rd",
    "iso:country":"AU",
    "sg:address":"Crossing Rd",
    "sg:city":"Mylor",
    "sg:classifiers":[
        {
            "category":"Building & Trades",
            "subcategory":"Plumbing",
            "type":"Services"
        }
    ],
    "sg:phone":"+61 8 8388 5627",
    "sg:postcode":"5153",
    "sg:province":"SA",
    "sg:tags":[
        "plumber",
        "gasfitters"
    ],
    "wof:name":"W.C. Plumbing Services",
    "wof:placetype":"venue"
},
  "geometry": {"coordinates":[138.751342773,-35.0622940063],"type":"Point"}
}