{
  "type": "Feature",
  "properties": {
    "iso:country":"AU",
    "sg:address":"Factory 1/ 3 Luisa Ave",
    "sg:city":"Dandenong",
    "sg:classifiers":[
        {
            "category":"Arena",
            "subcategory":"Indoor Arena",
            "type":"Entertainment"
        }
    ],
    "sg:phone":"+61 3 9768 2593",
    "sg:postcode":"3175",
    "sg:province":"VIC",
    "sg:tags":[
        "modelmakers"
    ],
    "wof:name":"Cameron Patternmakers P/L",
    "wof:placetype":"venue"
},
  "geometry": {"coordinates":[145.20449829099999,-38.0355834961],"type":"Point"}
}