{
  "type": "Feature",
  "properties": {
    "addr:full":"102 Coleman Rd Wantirna VIC 3152",
    "addr:housenumber":"102",
    "addr:postcode":"3152",
    "addr:street":"Coleman Rd",
    "iso:country":"AU",
    "sg:address":"102 Coleman Rd",
    "sg:city":"Wantirna",
    "sg:classifiers":[
        {
            "category":"Professional",
            "subcategory":"Computer Services",
            "type":"Services"
        }
    ],
    "sg:phone":"+61 3 9038 9338",
    "sg:postcode":"3152",
    "sg:province":"VIC",
    "sg:tags":[
        "repairs",
        "upgrade",
        "equipment"
    ],
    "wof:name":"Excellence IT",
    "wof:placetype":"venue"
},
  "geometry": {"coordinates":[145.25250244099999,-37.8612861633],"type":"Point"}
}