{
  "type": "Feature",
  "properties": {
    "iso:country":"AU",
    "sg:address":"71 Firebrace St",
    "sg:city":"Horsham",
    "sg:classifiers":[
        {
            "category":"Shopping",
            "subcategory":"Music",
            "type":"Retail Goods"
        }
    ],
    "sg:phone":"+61 3 5381 0866",
    "sg:postcode":"3400",
    "sg:province":"VIC",
    "sg:tags":[
        "store"
    ],
    "wof:name":"Bellcourt Books",
    "wof:placetype":"venue"
},
  "geometry": {"coordinates":[142.199905395,-36.7151260376],"type":"Point"}
}