{
  "type": "Feature",
  "properties": {
    "addr:full":"Suite 1, Cerina House 4 Mapleton Rd Nambour QLD 4560",
    "addr:housenumber":"4",
    "addr:postcode":"4560",
    "addr:street":"Mapleton Rd",
    "iso:country":"AU",
    "sg:address":"Suite 1, Cerina House 4 Mapleton Rd",
    "sg:city":"Nambour",
    "sg:classifiers":[
        {
            "category":"Health Services",
            "subcategory":"Doctor",
            "type":"Services"
        }
    ],
    "sg:phone":"+61 7 5476 2977",
    "sg:postcode":"4560",
    "sg:province":"QLD",
    "sg:tags":[
        "medical",
        "practitioner"
    ],
    "wof:name":"Moir Medical Services",
    "wof:placetype":"venue"
},
  "geometry": {"coordinates":[152.95228576700001,-26.6207561493],"type":"Point"}
}