{
  "type": "Feature",
  "properties": {
    "iso:country":"AU",
    "sg:address":"Unit 2, 111 Industrial Rd",
    "sg:city":"Oak Flats",
    "sg:classifiers":[
        {
            "category":"Retail",
            "subcategory":"Auto Repair",
            "type":"Services"
        }
    ],
    "sg:phone":"+61 2 4256 0966",
    "sg:postcode":"2529",
    "sg:province":"NSW",
    "sg:tags":[
        "repairer",
        "motor",
        "engineer"
    ],
    "wof:name":"Workshop On Wheels Mechanics",
    "wof:placetype":"venue"
},
  "geometry": {"coordinates":[150.80984497099999,-34.5668373108],"type":"Point"}
}