{
  "type": "Feature",
  "properties": {
    "iso:country":"AU",
    "sg:address":"203 Cornelia Rd",
    "sg:city":"Toongabbie",
    "sg:classifiers":[
        {
            "category":"Professional",
            "subcategory":"Engineering",
            "type":"Services"
        }
    ],
    "sg:phone":"+61 2 9636 3828",
    "sg:postcode":"2146",
    "sg:province":"NSW",
    "sg:tags":[
        "electronic",
        "engineer"
    ],
    "sg:website":"http://www.realtimedesigns.com.au",
    "wof:name":"Real Time Designs Pty Ltd",
    "wof:placetype":"venue"
},
  "geometry": {"coordinates":[150.93130493199999,-33.7948532104],"type":"Point"}
}