{
  "type": "Feature",
  "properties": {
    "addr:full":"Fcty11/ 37 Blanck St Ormeau QLD 4208",
    "addr:postcode":"4208",
    "addr:street":"Blanck St",
    "iso:country":"AU",
    "sg:address":"Fcty11/ 37 Blanck St",
    "sg:city":"Ormeau",
    "sg:classifiers":[
        {
            "category":"Manufacturing",
            "subcategory":"Metals",
            "type":"Manufacturing & Wholesale Goods"
        }
    ],
    "sg:phone":"+61 7 5549 2711",
    "sg:postcode":"4208",
    "sg:province":"QLD",
    "sg:tags":[
        "sheet",
        "worker"
    ],
    "wof:name":"Freehand Sheet Metal",
    "wof:placetype":"venue"
},
  "geometry": {"coordinates":[153.25552368199999,-27.7821331024],"type":"Point"}
}