{
  "type": "Feature",
  "properties": {
    "addr:full":"6 Arcoona Rd Salisbury Plain SA 5109",
    "addr:housenumber":"6",
    "addr:postcode":"5109",
    "addr:street":"Arcoona Rd",
    "iso:country":"AU",
    "sg:address":"6 Arcoona Rd",
    "sg:city":"Salisbury Plain",
    "sg:classifiers":[
        {
            "category":"Manufacturing",
            "subcategory":"Motor Vehicles & Parts",
            "type":"Manufacturing & Wholesale Goods"
        }
    ],
    "sg:phone":"+61 8 8250 8848",
    "sg:postcode":"5109",
    "sg:province":"SA",
    "sg:tags":[
        "replacement"
    ],
    "wof:name":"Natrad",
    "wof:placetype":"venue"
},
  "geometry": {"coordinates":[138.660644531,-34.7721252441],"type":"Point"}
}