{
  "type": "Feature",
  "properties": {
    "addr:full":"81 Lloyd St Moe VIC 3825",
    "addr:housenumber":"81",
    "addr:postcode":"3825",
    "addr:street":"Lloyd St",
    "iso:country":"AU",
    "sg:address":"81 Lloyd St",
    "sg:city":"Moe",
    "sg:classifiers":[
        {
            "category":"Autos & Motor Vehicles",
            "subcategory":"Fuel & Gas Station",
            "type":"Retail Goods"
        }
    ],
    "sg:phone":"+61 3 5127 3130",
    "sg:postcode":"3825",
    "sg:province":"VIC",
    "wof:name":"Mobil Oil Australia Pty Ltd",
    "wof:placetype":"venue"
},
  "geometry": {"coordinates":[146.25740099999999,-38.177952],"type":"Point"}
}