{
  "type": "Feature",
  "properties": {
    "addr:full":"39 Meckiff St Mt Gravatt QLD 4122",
    "addr:housenumber":"39",
    "addr:postcode":"4122",
    "addr:street":"Meckiff St",
    "iso:country":"AU",
    "sg:address":"39 Meckiff St",
    "sg:city":"Mt Gravatt",
    "sg:classifiers":[
        {
            "category":"Utilities",
            "subcategory":"Electric",
            "type":"Services"
        }
    ],
    "sg:phone":"+61 7 3849 6971",
    "sg:postcode":"4122",
    "sg:province":"QLD",
    "sg:tags":[
        "electrical",
        "contractor"
    ],
    "wof:name":"Inf Electrical",
    "wof:placetype":"venue"
},
  "geometry": {"coordinates":[153.07130432100001,-27.5546302795],"type":"Point"}
}