{
  "type": "Feature",
  "properties": {
    "addr:full":"37 Taunton Drv Cheltenham VIC 3192",
    "addr:housenumber":"37",
    "addr:postcode":"3192",
    "addr:street":"Taunton Drv",
    "iso:country":"AU",
    "sg:address":"37 Taunton Drv",
    "sg:city":"Cheltenham",
    "sg:classifiers":[
        {
            "category":"Wholesale",
            "subcategory":"Construction Materials",
            "type":"Manufacturing & Wholesale Goods"
        }
    ],
    "sg:phone":"+61 3 9584 9038",
    "sg:postcode":"3192",
    "sg:province":"VIC",
    "sg:tags":[
        "wholesaler",
        "lighting",
        "mfrs",
        "accessory"
    ],
    "wof:name":"Matrix Innovations Pty Ltd",
    "wof:placetype":"venue"
},
  "geometry": {"coordinates":[145.08445739699999,-37.9722557068],"type":"Point"}
}