{
  "type": "Feature",
  "properties": {
    "addr:full":"Iris Pl Fitzgibbon QLD 4018",
    "addr:postcode":"4018",
    "addr:street":"Pl",
    "iso:country":"AU",
    "sg:address":"Iris Pl",
    "sg:city":"Fitzgibbon",
    "sg:classifiers":[
        {
            "category":"Shopping",
            "subcategory":"Baby Store",
            "type":"Retail Goods"
        }
    ],
    "sg:phone":"+61 7 3862 7325",
    "sg:postcode":"4018",
    "sg:province":"QLD",
    "sg:tags":[
        "children's",
        "wear"
    ],
    "wof:name":"Mini Minors",
    "wof:placetype":"venue"
},
  "geometry": {"coordinates":[153.03453099999999,-27.345734],"type":"Point"}
}