{
  "type": "Feature",
  "properties": {
    "iso:country":"AU",
    "sg:address":"91 Tabilban St",
    "sg:city":"Burleigh Heads",
    "sg:classifiers":[
        {
            "category":"Shopping",
            "subcategory":"Musical Instruments",
            "type":"Retail Goods"
        }
    ],
    "sg:phone":"+61 7 5535 7155",
    "sg:postcode":"4220",
    "sg:province":"QLD",
    "sg:tags":[
        "musician",
        "agent"
    ],
    "wof:name":"Topline Entertainment",
    "wof:placetype":"venue"
},
  "geometry": {"coordinates":[153.44480895999999,-28.096654892],"type":"Point"}
}