{
  "type": "Feature",
  "properties": {
    "addr:full":"62 David Rd Geraldton WA 6530",
    "addr:housenumber":"62",
    "addr:postcode":"6530",
    "addr:street":"David Rd",
    "iso:country":"AU",
    "sg:address":"62 David Rd",
    "sg:city":"Geraldton",
    "sg:classifiers":[
        {
            "category":"Building & Trades",
            "subcategory":"Cleaning & Sanitation",
            "type":"Services"
        }
    ],
    "sg:phone":"+61 8 9938 1188",
    "sg:postcode":"6530",
    "sg:province":"WA",
    "sg:tags":[
        "industrial",
        "commercial",
        "contractor"
    ],
    "wof:name":"Midwest Cleaning Service",
    "wof:placetype":"venue"
},
  "geometry": {"coordinates":[114.64481353799999,-28.7017192841],"type":"Point"}
}