{
  "type": "Feature",
  "properties": {
    "addr:full":"45b Gilbert St Latrobe TAS 7307",
    "addr:housenumber":"45b",
    "addr:postcode":"7307",
    "addr:street":"Gilbert St",
    "iso:country":"AU",
    "sg:address":"45b Gilbert St",
    "sg:city":"Latrobe",
    "sg:classifiers":[
        {
            "category":"Health Services",
            "subcategory":"Doctor",
            "type":"Services"
        }
    ],
    "sg:phone":"+61 3 6426 1141",
    "sg:postcode":"7307",
    "sg:province":"TAS",
    "sg:tags":[
        "medical",
        "practitioner"
    ],
    "wof:name":"Morris S",
    "wof:placetype":"venue"
},
  "geometry": {"coordinates":[146.411438,-41.235672],"type":"Point"}
}