{
  "type": "Feature",
  "properties": {
    "addr:full":"Unit 10/ 5 Deakin St Brendale QLD 4500",
    "addr:housenumber":"/ 5",
    "addr:postcode":"4500",
    "addr:street":"Deakin St",
    "iso:country":"AU",
    "sg:address":"Unit 10/ 5 Deakin St",
    "sg:city":"Brendale",
    "sg:classifiers":[
        {
            "category":"Home & Garden",
            "subcategory":"Building Materials",
            "type":"Retail Goods"
        }
    ],
    "sg:phone":"+61 7 3205 1123",
    "sg:postcode":"4500",
    "sg:province":"QLD",
    "sg:tags":[
        "shutter",
        "roller",
        "grille"
    ],
    "wof:name":"Link Controls",
    "wof:placetype":"venue"
},
  "geometry": {"coordinates":[152.99154663100001,-27.3227043152],"type":"Point"}
}