{
  "type": "Feature",
  "properties": {
    "addr:full":"55 Whiteside Rd Clayton South VIC 3169",
    "addr:housenumber":"55",
    "addr:postcode":"3169",
    "addr:street":"Whiteside Rd",
    "iso:country":"AU",
    "sg:address":"55 Whiteside Rd",
    "sg:city":"Clayton South",
    "sg:classifiers":[
        {
            "category":"Retail",
            "subcategory":"Auto Repair",
            "type":"Services"
        }
    ],
    "sg:phone":"+61 3 9545 5944",
    "sg:postcode":"3169",
    "sg:province":"VIC",
    "sg:tags":[
        "beater",
        "painter",
        "panel"
    ],
    "wof:name":"Bodypro Accident Repairs",
    "wof:placetype":"venue"
},
  "geometry": {"coordinates":[145.12274169899999,-37.9384307861],"type":"Point"}
}