{
  "type": "Feature",
  "properties": {
    "addr:full":"54, 2-10 Quarry Master Drv Pyrmont NSW 2009",
    "addr:housenumber":"2-10",
    "addr:postcode":"2009",
    "addr:street":"54;Quarry Master Drv",
    "iso:country":"AU",
    "sg:address":"54, 2-10 Quarry Master Drv",
    "sg:city":"Pyrmont",
    "sg:classifiers":[
        {
            "category":"Professional",
            "subcategory":"Printing & Photocopies",
            "type":"Services"
        }
    ],
    "sg:phone":"+61 2 9571 7839",
    "sg:postcode":"2009",
    "sg:province":"NSW",
    "sg:tags":[
        "publishing",
        "desktop"
    ],
    "wof:name":"YSIT Graphics",
    "wof:placetype":"venue"
},
  "geometry": {"coordinates":[151.18739318900001,-33.8759078979],"type":"Point"}
}