{
  "type": "Feature",
  "properties": {
    "iso:country":"AU",
    "sg:address":"81 Newcastle St",
    "sg:city":"Fyshwick",
    "sg:classifiers":[
        {
            "category":"Autos & Motor Vehicles",
            "subcategory":"Automobile Sales",
            "type":"Retail Goods"
        }
    ],
    "sg:phone":"+61 2 6239 2030",
    "sg:postcode":"2609",
    "sg:province":"ACT",
    "sg:tags":[
        "car",
        "used"
    ],
    "wof:name":"Kembla Car Sales",
    "wof:placetype":"venue"
},
  "geometry": {"coordinates":[149.17518615700001,-35.3268737793],"type":"Point"}
}