{
  "type": "Feature",
  "properties": {
    "addr:full":"Cnr Pound & Reserve Sts Grafton NSW 2460",
    "addr:postcode":"2460",
    "iso:country":"AU",
    "sg:address":"Cnr Pound & Reserve Sts",
    "sg:city":"Grafton",
    "sg:classifiers":[
        {
            "category":"Travel",
            "subcategory":"Hotels & Motels",
            "type":"Entertainment"
        }
    ],
    "sg:phone":"+61 2 6643 5823",
    "sg:postcode":"2460",
    "sg:province":"NSW",
    "wof:name":"Welcome Inn Grafton",
    "wof:placetype":"venue"
},
  "geometry": {"coordinates":[152.93728637699999,-29.6911125183],"type":"Point"}
}