{
  "type": "Feature",
  "properties": {
    "addr:full":"U8/ 14 Halley Rd Balcatta WA 6021",
    "addr:housenumber":"14",
    "addr:postcode":"6021",
    "addr:street":"U8 /;Halley Rd",
    "iso:country":"AU",
    "sg:address":"U8/ 14 Halley Rd",
    "sg:city":"Balcatta",
    "sg:classifiers":[
        {
            "category":"Shopping",
            "subcategory":"Gifts & Souvenirs",
            "type":"Retail Goods"
        }
    ],
    "sg:phone":"+61 8 9207 2911",
    "sg:postcode":"6021",
    "sg:province":"WA",
    "sg:tags":[
        "shop",
        "supply"
    ],
    "wof:name":"Jairon Trading Company",
    "wof:placetype":"venue"
},
  "geometry": {"coordinates":[115.825950623,-31.8616733551],"type":"Point"}
}