{
  "type": "Feature",
  "properties": {
    "addr:full":"PO Box 813 Merbein VIC 3505",
    "addr:postcode":"3505",
    "iso:country":"AU",
    "sg:address":"PO Box 813",
    "sg:city":"Merbein",
    "sg:classifiers":[
        {
            "category":"Utilities",
            "subcategory":"Refuse",
            "type":"Services"
        }
    ],
    "sg:phone":"+61 429 172 422",
    "sg:postcode":"3505",
    "sg:province":"VIC",
    "sg:tags":[
        "remover",
        "rubbish"
    ],
    "wof:name":"Sunnycat Bobcat & Tipper Hire",
    "wof:placetype":"venue"
},
  "geometry": {"coordinates":[142.05857849099999,-34.1675605774],"type":"Point"}
}