{
  "type": "Feature",
  "properties": {
    "addr:full":"Burrier Rd Burrier NSW 2540",
    "addr:postcode":"2540",
    "addr:street":"Burrier Rd",
    "iso:country":"AU",
    "sg:address":"Burrier Rd",
    "sg:city":"Burrier",
    "sg:classifiers":[
        {
            "category":"Health Services",
            "subcategory":"Health Practitioner",
            "type":"Services"
        }
    ],
    "sg:phone":"+61 2 4422 4819",
    "sg:postcode":"2540",
    "sg:province":"NSW",
    "sg:tags":[
        "homoeopath"
    ],
    "wof:name":"Keeli Cambourne",
    "wof:placetype":"venue"
},
  "geometry": {"coordinates":[150.46202087399999,-34.8834762573],"type":"Point"}
}