{
  "type": "Feature",
  "properties": {
    "addr:full":"Suite 3A 255 Pacific Hwy North Sydney NSW 2060",
    "addr:housenumber":"255",
    "addr:postcode":"2060",
    "addr:street":"Pacific Hwy",
    "iso:country":"AU",
    "sg:address":"Suite 3A 255 Pacific Hwy",
    "sg:city":"North Sydney",
    "sg:classifiers":[
        {
            "category":"Education",
            "subcategory":"Special Training",
            "type":"Public Place"
        }
    ],
    "sg:phone":"+61 2 9957 5544",
    "sg:postcode":"2060",
    "sg:province":"NSW",
    "sg:tags":[
        "development"
    ],
    "wof:name":"Carlton Communicators",
    "wof:placetype":"venue"
},
  "geometry": {"coordinates":[151.20506286599999,-33.8341789246],"type":"Point"}
}