{
  "type": "Feature",
  "properties": {
    "addr:full":"64 Ashmore Rd Bundall QLD 4217",
    "addr:housenumber":"64",
    "addr:postcode":"4217",
    "addr:street":"Ashmore Rd",
    "iso:country":"AU",
    "sg:address":"64 Ashmore Rd",
    "sg:city":"Bundall",
    "sg:classifiers":[
        {
            "category":"Health Services",
            "subcategory":"Dentist",
            "type":"Services"
        }
    ],
    "sg:phone":"+61 7 5531 6599",
    "sg:postcode":"4217",
    "sg:province":"QLD",
    "wof:name":"de Leeuw B.D.S.",
    "wof:placetype":"venue"
},
  "geometry": {"coordinates":[153.40603637699999,-28.0105419159],"type":"Point"}
}