{
  "type": "Feature",
  "properties": {
    "addr:full":"72 Bay St Botany NSW 2019",
    "addr:housenumber":"72",
    "addr:postcode":"2019",
    "addr:street":"Bay St",
    "iso:country":"AU",
    "sg:address":"72 Bay St",
    "sg:city":"Botany",
    "sg:classifiers":[
        {
            "category":"Professional",
            "type":"Services"
        }
    ],
    "sg:phone":"+61 2 9700 1511",
    "sg:postcode":"2019",
    "sg:province":"NSW",
    "sg:tags":[
        "coating",
        "powder"
    ],
    "wof:name":"A-1 Powder Coating Services",
    "wof:placetype":"venue"
},
  "geometry": {"coordinates":[151.20143127399999,-33.9422073364],"type":"Point"}
}