{
  "type": "Feature",
  "properties": {
    "addr:full":"16/ 20 Bogong St Riverhills QLD 4074",
    "addr:housenumber":"16 / 20",
    "addr:postcode":"4074",
    "addr:street":"Bogong St",
    "iso:country":"AU",
    "sg:address":"16/ 20 Bogong St",
    "sg:city":"Riverhills",
    "sg:classifiers":[
        {
            "category":"Professional",
            "subcategory":"Accounting & Tax Preparation",
            "type":"Services"
        }
    ],
    "sg:phone":"+61 7 3279 2366",
    "sg:postcode":"4074",
    "sg:province":"QLD",
    "sg:tags":[
        "accountant",
        "auditor"
    ],
    "wof:name":"Less Stress Tax Time",
    "wof:placetype":"venue"
},
  "geometry": {"coordinates":[152.911941528,-27.5592193604],"type":"Point"}
}