{
  "type": "Feature",
  "properties": {
    "addr:full":"345 Borella Rd Albury NSW 2640",
    "addr:housenumber":"345",
    "addr:postcode":"2640",
    "addr:street":"Borella Rd",
    "iso:country":"AU",
    "sg:address":"345 Borella Rd",
    "sg:city":"Albury",
    "sg:classifiers":[
        {
            "category":"Building & Trades",
            "subcategory":"Construction",
            "type":"Services"
        }
    ],
    "sg:phone":"+61 412 691 877",
    "sg:postcode":"2640",
    "sg:province":"NSW",
    "sg:tags":[
        "contractor"
    ],
    "wof:name":"Mick Plunkett",
    "wof:placetype":"venue"
},
  "geometry": {"coordinates":[146.92874145499999,-36.0765075684],"type":"Point"}
}