{
  "type": "Feature",
  "properties": {
    "iso:country":"AU",
    "sg:address":"PO Box 137",
    "sg:city":"Darling Heights",
    "sg:classifiers":[
        {
            "category":"Education",
            "subcategory":"Special Training",
            "type":"Public Place"
        }
    ],
    "sg:phone":"+61 7 4696 3379",
    "sg:postcode":"4350",
    "sg:province":"QLD",
    "sg:tags":[
        "development"
    ],
    "wof:name":"Merganza People Development",
    "wof:placetype":"venue"
},
  "geometry": {"coordinates":[151.875641,-27.55761],"type":"Point"}
}