{
  "type": "Feature",
  "properties": {
    "iso:country":"AU",
    "sg:address":"Rakow Street (PO Box 984",
    "sg:city":", Broken Hill) Broken Hill",
    "sg:classifiers":[
        {
            "category":"Organizations",
            "subcategory":"Non-profit Organization",
            "type":"Services"
        }
    ],
    "sg:phone":"+61 8 8087 3919",
    "sg:postcode":"2880",
    "sg:province":"NSW",
    "sg:tags":[
        "support",
        "disability",
        "organisation"
    ],
    "wof:name":"Silverlea Community Centre",
    "wof:placetype":"venue"
},
  "geometry": {"coordinates":[141.442260742,-31.9588432312],"type":"Point"}
}