{
  "type": "Feature",
  "properties": {
    "addr:full":"60 Anstey Ave Reservoir VIC 3073",
    "addr:housenumber":"60",
    "addr:postcode":"3073",
    "addr:street":"Anstey Ave",
    "iso:country":"AU",
    "sg:address":"60 Anstey Ave",
    "sg:city":"Reservoir",
    "sg:classifiers":[
        {
            "category":"Retail",
            "subcategory":"Storage",
            "type":"Services"
        }
    ],
    "sg:phone":"+61 3 9402 0268",
    "sg:postcode":"3073",
    "sg:province":"VIC",
    "sg:tags":[
        "removal",
        "furniture"
    ],
    "wof:name":"MGC Transport/Removals Pty Ltd",
    "wof:placetype":"venue"
},
  "geometry": {"coordinates":[144.981033325,-37.6926040649],"type":"Point"}
}