{
  "type": "Feature",
  "properties": {
    "iso:country":"AU",
    "sg:address":"4 Neil St",
    "sg:city":"Mannum",
    "sg:classifiers":[
        {
            "category":"Manufacturing",
            "subcategory":"Glass & Minerals",
            "type":"Manufacturing & Wholesale Goods"
        }
    ],
    "sg:phone":"+61 8 8569 2262",
    "sg:postcode":"5238",
    "sg:province":"SA",
    "sg:tags":[
        "earth"
    ],
    "wof:name":"Mannum Minerals",
    "wof:placetype":"venue"
},
  "geometry": {"coordinates":[139.29957580600001,-34.913356781],"type":"Point"}
}