{
  "type": "Feature",
  "properties": {
    "iso:country":"AU",
    "sg:address":"14 Cricklewood Ave",
    "sg:city":"Frankston",
    "sg:classifiers":[
        {
            "category":"Professional",
            "subcategory":"Art Services",
            "type":"Services"
        }
    ],
    "sg:phone":"+61 419 565 806",
    "sg:postcode":"3199",
    "sg:province":"VIC",
    "sg:tags":[
        "decorator",
        "painter"
    ],
    "wof:name":"J C F Painting Service",
    "wof:placetype":"venue"
},
  "geometry": {"coordinates":[145.13168335,-38.1367340088],"type":"Point"}
}