{
  "type": "Feature",
  "properties": {
    "addr:full":"PO Box 6062 South Windsor NSW 2756",
    "addr:postcode":"2756",
    "iso:country":"AU",
    "sg:address":"PO Box 6062",
    "sg:city":"South Windsor",
    "sg:classifiers":[
        {
            "category":"Utilities",
            "type":"Services"
        }
    ],
    "sg:phone":"+61 417 411 290",
    "sg:postcode":"2756",
    "sg:province":"NSW",
    "sg:tags":[
        "refrigeration",
        "industrial",
        "commercial",
        "retail"
    ],
    "wof:name":"Macquarie Towns Refrigeration",
    "wof:placetype":"venue"
},
  "geometry": {"coordinates":[150.804412842,-33.621761322],"type":"Point"}
}