{
  "type": "Feature",
  "properties": {
    "addr:full":"Maroubra PCYC 26a Bunnerong Rd Daceyville NSW 2032",
    "addr:housenumber":"26a",
    "addr:postcode":"2032",
    "addr:street":"Pcyc;Bunnerong Rd",
    "iso:country":"AU",
    "sg:address":"Maroubra PCYC 26a Bunnerong Rd",
    "sg:city":"Daceyville",
    "sg:classifiers":[
        {
            "category":"Recreation",
            "type":"Entertainment"
        }
    ],
    "sg:phone":"+61 2 9371 6572",
    "sg:postcode":"2032",
    "sg:province":"NSW",
    "sg:tags":[
        "children's",
        "play",
        "programme"
    ],
    "wof:name":"GymbaROO",
    "wof:placetype":"venue"
},
  "geometry": {"coordinates":[151.228973389,-33.9284172058],"type":"Point"}
}