{
  "type": "Feature",
  "properties": {
    "addr:full":"Shop 4/ 537 Malvern Rd Toorak VIC 3142",
    "addr:housenumber":"shop 4 / 537",
    "addr:postcode":"3142",
    "addr:street":"Malvern Rd",
    "iso:country":"AU",
    "sg:address":"Shop 4/ 537 Malvern Rd",
    "sg:city":"Toorak",
    "sg:classifiers":[
        {
            "category":"Shopping",
            "subcategory":"Clothing, Apparel, & Fashions",
            "type":"Retail Goods"
        }
    ],
    "sg:phone":"+61 3 9826 4034",
    "sg:postcode":"3142",
    "sg:province":"VIC",
    "sg:tags":[
        "lady",
        "wear"
    ],
    "wof:name":"Panada Boutique",
    "wof:placetype":"venue"
},
  "geometry": {"coordinates":[145.004272461,-37.8480911255],"type":"Point"}
}