{
  "type": "Feature",
  "properties": {
    "addr:full":"75 Noosa Drv Noosa Heads QLD 4567",
    "addr:housenumber":"75",
    "addr:postcode":"4567",
    "addr:street":"Noosa Drv",
    "iso:country":"AU",
    "sg:address":"75 Noosa Drv",
    "sg:city":"Noosa Heads",
    "sg:classifiers":[
        {
            "category":"Personal",
            "subcategory":"Beauty Salon",
            "type":"Services"
        }
    ],
    "sg:phone":"+61 7 5447 3263",
    "sg:postcode":"4567",
    "sg:province":"QLD",
    "sg:tags":[
        "hairdresser"
    ],
    "wof:name":"Anne Marie Wall Hairdressers",
    "wof:placetype":"venue"
},
  "geometry": {"coordinates":[153.089675903,-26.3930435181],"type":"Point"}
}