{
  "type": "Feature",
  "properties": {
    "addr:full":"114 Parry St Charleville QLD 4470",
    "addr:housenumber":"114",
    "addr:postcode":"4470",
    "addr:street":"Parry St",
    "iso:country":"AU",
    "sg:address":"114 Parry St",
    "sg:city":"Charleville",
    "sg:classifiers":[
        {
            "category":"Home & Garden",
            "subcategory":"Building Materials",
            "type":"Retail Goods"
        }
    ],
    "sg:phone":"+61 7 4654 1140",
    "sg:postcode":"4470",
    "sg:province":"QLD",
    "sg:tags":[
        "supply"
    ],
    "wof:name":"Tower Hardware",
    "wof:placetype":"venue"
},
  "geometry": {"coordinates":[146.249237061,-26.4011745453],"type":"Point"}
}