{
  "type": "Feature",
  "properties": {
    "addr:full":"247 - 249 Morayfield Rd Morayfield QLD 4506",
    "addr:housenumber":"249",
    "addr:postcode":"4506",
    "addr:street":"Morayfield Rd",
    "iso:country":"AU",
    "sg:address":"247 - 249 Morayfield Rd",
    "sg:city":"Morayfield",
    "sg:classifiers":[
        {
            "category":"Autos & Motor Vehicles",
            "subcategory":"Automobile Sales",
            "type":"Retail Goods"
        }
    ],
    "sg:phone":"+61 7 5498 5800",
    "sg:postcode":"4506",
    "sg:province":"QLD",
    "sg:tags":[
        "car",
        "new"
    ],
    "wof:name":"Keystar Subaru",
    "wof:placetype":"venue"
},
  "geometry": {"coordinates":[152.95149230999999,-27.1123218536],"type":"Point"}
}