{
  "type": "Feature",
  "properties": {
    "addr:full":"Unit 8a Louise Ave Ingleburn NSW 2565",
    "addr:housenumber":"unit 8a",
    "addr:postcode":"2565",
    "addr:street":"Louise Ave",
    "iso:country":"AU",
    "sg:address":"Unit 8a Louise Ave",
    "sg:city":"Ingleburn",
    "sg:classifiers":[
        {
            "category":"Retail",
            "subcategory":"Auto Repair",
            "type":"Services"
        }
    ],
    "sg:phone":"+61 407 664 040",
    "sg:postcode":"2565",
    "sg:province":"NSW",
    "sg:tags":[
        "electrical"
    ],
    "wof:name":"Ingleburn Auto Electrical",
    "wof:placetype":"venue"
},
  "geometry": {"coordinates":[150.865966797,-33.9953231812],"type":"Point"}
}