{
  "type": "Feature",
  "properties": {
    "addr:full":"Unit 262/ 4 Potter St Waterloo NSW 2017",
    "addr:housenumber":"/ 4",
    "addr:postcode":"2017",
    "addr:street":"Potter St",
    "iso:country":"AU",
    "sg:address":"Unit 262/ 4 Potter St",
    "sg:city":"Waterloo",
    "sg:classifiers":[
        {
            "category":"Personal",
            "subcategory":"Beauty Salon",
            "type":"Services"
        }
    ],
    "sg:phone":"+61 2 8399 1376",
    "sg:postcode":"2017",
    "sg:province":"NSW",
    "sg:tags":[
        "hairdresser"
    ],
    "wof:name":"Hair On Potter",
    "wof:placetype":"venue"
},
  "geometry": {"coordinates":[151.212493897,-33.8994445801],"type":"Point"}
}