{
  "type": "Feature",
  "properties": {
    "iso:country":"AU",
    "sg:address":"1/ 20 Clarke St",
    "sg:city":"Crows Nest",
    "sg:classifiers":[
        {
            "category":"Health Services",
            "subcategory":"Health Practitioner",
            "type":"Services"
        }
    ],
    "sg:phone":"+61 2 9437 5510",
    "sg:postcode":"2065",
    "sg:province":"NSW",
    "sg:tags":[
        "alternative"
    ],
    "wof:name":"Chiara College Of Metaphysics The",
    "wof:placetype":"venue"
},
  "geometry": {"coordinates":[151.20074462900001,-33.8240318298],"type":"Point"}
}