{
  "type": "Feature",
  "properties": {
    "addr:full":"Aldis Rd Calen QLD 4798",
    "addr:postcode":"4798",
    "addr:street":"Aldis Rd",
    "iso:country":"AU",
    "sg:address":"Aldis Rd",
    "sg:city":"Calen",
    "sg:classifiers":[
        {
            "category":"Farming",
            "subcategory":"Farm",
            "type":"Manufacturing & Wholesale Goods"
        }
    ],
    "sg:phone":"+61 7 4958 7882",
    "sg:postcode":"4798",
    "sg:province":"QLD",
    "sg:tags":[
        "farmer"
    ],
    "wof:name":"Birkett R G & Sons",
    "wof:placetype":"venue"
},
  "geometry": {"coordinates":[148.765258789,-20.8608818054],"type":"Point"}
}