{
  "type": "Feature",
  "properties": {
    "addr:full":"1455 South Rd Bedford Park SA 5042",
    "addr:housenumber":"1455",
    "addr:postcode":"5042",
    "addr:street":"South Rd",
    "iso:country":"AU",
    "sg:address":"1455 South Rd",
    "sg:city":"Bedford Park",
    "sg:classifiers":[
        {
            "category":"Health Services",
            "subcategory":"Doctor",
            "type":"Services"
        }
    ],
    "sg:phone":"+61 8 8277 6344",
    "sg:postcode":"5042",
    "sg:province":"SA",
    "sg:tags":[
        "medical",
        "practitioner"
    ],
    "wof:name":"Henschke Philip Dr",
    "wof:placetype":"venue"
},
  "geometry": {"coordinates":[138.57600400000001,-35.010464],"type":"Point"}
}