{
  "type": "Feature",
  "properties": {
    "addr:full":"2 Cedar Pl Bellingen NSW 2454",
    "addr:housenumber":"2",
    "addr:postcode":"2454",
    "addr:street":"Cedar Pl",
    "iso:country":"AU",
    "sg:address":"2 Cedar Pl",
    "sg:city":"Bellingen",
    "sg:classifiers":[
        {
            "category":"Building & Trades",
            "subcategory":"Landscaping Services",
            "type":"Services"
        }
    ],
    "sg:phone":"+61 2 6655 9179",
    "sg:postcode":"2454",
    "sg:province":"NSW",
    "sg:tags":[
        "designer",
        "landscape",
        "contractor"
    ],
    "wof:name":"Superb-en-forests",
    "wof:placetype":"venue"
},
  "geometry": {"coordinates":[152.900925,-30.442793],"type":"Point"}
}