{
  "type": "Feature",
  "properties": {
    "addr:full":"43 Redan St Mosman NSW 2088",
    "addr:housenumber":"43",
    "addr:postcode":"2088",
    "addr:street":"Redan St",
    "iso:country":"AU",
    "sg:address":"43 Redan St",
    "sg:city":"Mosman",
    "sg:classifiers":[
        {
            "category":"Real Estate",
            "subcategory":"Architect",
            "type":"Services"
        }
    ],
    "sg:phone":"+61 2 9968 1387",
    "sg:postcode":"2088",
    "sg:province":"NSW",
    "wof:name":"Wisden Architects",
    "wof:placetype":"venue"
},
  "geometry": {"coordinates":[151.24667358400001,-33.8265609741],"type":"Point"}
}