{
  "type": "Feature",
  "properties": {
    "addr:full":"10 Murrell St Glenroy VIC 3046",
    "addr:housenumber":"10",
    "addr:postcode":"3046",
    "addr:street":"Murrell St",
    "iso:country":"AU",
    "sg:address":"10 Murrell St",
    "sg:city":"Glenroy",
    "sg:classifiers":[
        {
            "category":"Education",
            "subcategory":"Kindergarten",
            "type":"Public Place"
        }
    ],
    "sg:phone":"+61 3 9306 9767",
    "sg:postcode":"3046",
    "sg:province":"VIC",
    "sg:tags":[
        "pre-schools"
    ],
    "wof:name":"Glenroy Memorial Pre-school",
    "wof:placetype":"venue"
},
  "geometry": {"coordinates":[144.920379639,-37.7041397095],"type":"Point"}
}