{
  "type": "Feature",
  "properties": {
    "addr:full":"10 Shirley Crt Alice Springs NT 0870",
    "addr:housenumber":"10",
    "addr:postcode":"nt 0870",
    "addr:street":"Shirley Crt",
    "iso:country":"AU",
    "sg:address":"10 Shirley Crt",
    "sg:city":"Alice Springs",
    "sg:classifiers":[
        {
            "category":"Mining & Drilling",
            "type":"Manufacturing & Wholesale Goods"
        }
    ],
    "sg:phone":"+61 8 8952 2353",
    "sg:postcode":"0870",
    "sg:province":"NT",
    "sg:tags":[
        "equipment",
        "quarrying",
        "supply"
    ],
    "wof:name":"Hirex Services",
    "wof:placetype":"venue"
},
  "geometry": {"coordinates":[133.86268615700001,-23.6928138733],"type":"Point"}
}