{
  "type": "Feature",
  "properties": {
    "iso:country":"AU",
    "sg:address":"10 Kimberly Rd",
    "sg:city":"Dandenong",
    "sg:classifiers":[
        {
            "category":"Professional",
            "type":"Services"
        }
    ],
    "sg:phone":"+61 3 9544 2288",
    "sg:postcode":"3175",
    "sg:province":"VIC",
    "sg:tags":[
        "control",
        "equipment",
        "traffic"
    ],
    "wof:name":"Flexitec Rubber Surfaces",
    "wof:placetype":"venue"
},
  "geometry": {"coordinates":[145.203567505,-38.0312538147],"type":"Point"}
}