{
  "type": "Feature",
  "properties": {
    "iso:country":"AU",
    "sg:address":"Ste29/ 17 Ogilvie Rd",
    "sg:city":"Mt Pleasant",
    "sg:classifiers":[
        {
            "category":"Social Services",
            "subcategory":"Retirement Home",
            "type":"Services"
        }
    ],
    "sg:phone":"+61 8 9316 1444",
    "sg:postcode":"6153",
    "sg:province":"WA",
    "sg:tags":[
        "environmental",
        "consultant",
        "pollution"
    ],
    "wof:name":"Green Vision Wa Pty Ltd",
    "wof:placetype":"venue"
},
  "geometry": {"coordinates":[115.848511,-32.013691],"type":"Point"}
}