{
  "type": "Feature",
  "properties": {
    "addr:full":"47 Kokoda St Darra QLD 4076",
    "addr:housenumber":"47",
    "addr:postcode":"4076",
    "addr:street":"Kokoda St",
    "iso:country":"AU",
    "sg:address":"47 Kokoda St",
    "sg:city":"Darra",
    "sg:classifiers":[
        {
            "category":"Government",
            "subcategory":"City Hall",
            "type":"Public Place"
        }
    ],
    "sg:phone":"+61 7 3271 1387",
    "sg:postcode":"4076",
    "sg:province":"QLD",
    "wof:name":"Better Centenary Village Alliance Community Hall",
    "wof:placetype":"venue"
},
  "geometry": {"coordinates":[152.94107055699999,-27.5768413544],"type":"Point"}
}