{
  "type": "Feature",
  "properties": {
    "addr:full":"North West Hospital 137 Flockton St Everton Park QLD 4053",
    "addr:housenumber":"137",
    "addr:postcode":"4053",
    "addr:street":"Flockton St",
    "iso:country":"AU",
    "sg:address":"North West Hospital 137 Flockton St",
    "sg:city":"Everton Park",
    "sg:classifiers":[
        {
            "category":"Health Services",
            "subcategory":"Doctor",
            "type":"Services"
        }
    ],
    "sg:phone":"+61 7 3353 5011",
    "sg:postcode":"4053",
    "sg:province":"QLD",
    "sg:tags":[
        "medical",
        "practitioner"
    ],
    "wof:name":"Queensland Diagnostic Imaging",
    "wof:placetype":"venue"
},
  "geometry": {"coordinates":[152.991790772,-27.3943729401],"type":"Point"}
}