{
  "type": "Feature",
  "properties": {
    "addr:full":"PO Box 3108 Mt Druitt Village NSW 2770",
    "addr:postcode":"2770",
    "addr:street":"Druitt",
    "iso:country":"AU",
    "sg:address":"PO Box 3108",
    "sg:city":"Mt Druitt Village",
    "sg:classifiers":[
        {
            "category":"Professional",
            "subcategory":"Detective & Security Services",
            "type":"Services"
        }
    ],
    "sg:phone":"+61 1300 781 232",
    "sg:postcode":"2770",
    "sg:province":"NSW",
    "sg:tags":[
        "consultant",
        "system"
    ],
    "wof:name":"On Guard Security Services Pty Ltd",
    "wof:placetype":"venue"
},
  "geometry": {"coordinates":[150.81158447300001,-33.7720489502],"type":"Point"}
}