{
  "type": "Feature",
  "properties": {
    "addr:full":"61 Harold St Stafford QLD 4053",
    "addr:housenumber":"61",
    "addr:postcode":"4053",
    "addr:street":"Harold St",
    "iso:country":"AU",
    "sg:address":"61 Harold St",
    "sg:city":"Stafford",
    "sg:classifiers":[
        {
            "category":"Personal",
            "subcategory":"Massage",
            "type":"Services"
        }
    ],
    "sg:phone":"+61 7 3352 7741",
    "sg:postcode":"4053",
    "sg:province":"QLD",
    "sg:tags":[
        "therapy"
    ],
    "wof:name":"Luke Sheedy",
    "wof:placetype":"venue"
},
  "geometry": {"coordinates":[153.01008605999999,-27.408285141],"type":"Point"}
}