{
  "type": "Feature",
  "properties": {
    "addr:full":"604 Springvale Rd Mulgrave VIC 3170",
    "addr:housenumber":"604",
    "addr:postcode":"3170",
    "addr:street":"Springvale Rd",
    "iso:country":"AU",
    "sg:address":"604 Springvale Rd",
    "sg:city":"Mulgrave",
    "sg:classifiers":[
        {
            "category":"Professional",
            "subcategory":"Art Services",
            "type":"Services"
        }
    ],
    "sg:phone":"+61 3 9560 6729",
    "sg:postcode":"3170",
    "sg:province":"VIC",
    "sg:tags":[
        "graphic",
        "designer"
    ],
    "wof:name":"Mulgrave Graphic Studios",
    "wof:placetype":"venue"
},
  "geometry": {"coordinates":[145.160354614,-37.9109764099],"type":"Point"}
}