{
  "type": "Feature",
  "properties": {
    "iso:country":"AU",
    "sg:address":"27A Jindalee Rd",
    "sg:city":"Port Macquarie",
    "sg:classifiers":[
        {
            "category":"Retail",
            "subcategory":"Auto Repair",
            "type":"Services"
        }
    ],
    "sg:phone":"+61 2 6581 0691",
    "sg:postcode":"2444",
    "sg:province":"NSW",
    "sg:tags":[
        "muffler",
        "exhaust",
        "system"
    ],
    "wof:name":"A1 Exhausts",
    "wof:placetype":"venue"
},
  "geometry": {"coordinates":[152.88459800000001,-31.450867],"type":"Point"}
}