{
  "type": "Feature",
  "properties": {
    "iso:country":"AU",
    "sg:address":"Kiosk 11/ 620 Terrigal Drv",
    "sg:city":"Erina",
    "sg:classifiers":[
        {
            "category":"Retail",
            "subcategory":"Repair Shop",
            "type":"Services"
        }
    ],
    "sg:phone":"+61 2 4365 6558",
    "sg:postcode":"2250",
    "sg:province":"NSW",
    "sg:tags":[
        "mending",
        "clothing",
        "alteration"
    ],
    "wof:name":"Citywide Clothing Alterations",
    "wof:placetype":"venue"
},
  "geometry": {"coordinates":[151.43223571799999,-33.4395332336],"type":"Point"}
}