{
  "type": "Feature",
  "properties": {
    "addr:full":"Shp2/ Mayne St (CnrHerbertSt) Gulgong NSW 2852",
    "addr:postcode":"2852",
    "iso:country":"AU",
    "sg:address":"Shp2/ Mayne St (CnrHerbertSt)",
    "sg:city":"Gulgong",
    "sg:classifiers":[
        {
            "category":"Shopping",
            "subcategory":"Department Store",
            "type":"Retail Goods"
        }
    ],
    "sg:phone":"+61 2 6374 2670",
    "sg:postcode":"2852",
    "sg:province":"NSW",
    "wof:name":"Merchant The",
    "wof:placetype":"venue"
},
  "geometry": {"coordinates":[149.52946499999999,-32.36298],"type":"Point"}
}