{
  "type": "Feature",
  "properties": {
    "iso:country":"AU",
    "sg:address":"34 Campbell St",
    "sg:city":"Port Fairy",
    "sg:classifiers":[
        {
            "category":"Professional",
            "type":"Services"
        }
    ],
    "sg:phone":"+61 408 387 851",
    "sg:postcode":"3284",
    "sg:province":"VIC",
    "sg:tags":[
        "courier"
    ],
    "wof:name":"Fiona's Freight",
    "wof:placetype":"venue"
},
  "geometry": {"coordinates":[142.236053467,-38.3873825073],"type":"Point"}
}