{
  "type": "Feature",
  "properties": {
    "addr:full":"123 Vaughan St Shepparton VIC 3630",
    "addr:housenumber":"123",
    "addr:postcode":"3630",
    "addr:street":"Vaughan St",
    "iso:country":"AU",
    "sg:address":"123 Vaughan St",
    "sg:city":"Shepparton",
    "sg:classifiers":[
        {
            "category":"Farming",
            "subcategory":"Dairy Farm",
            "type":"Manufacturing & Wholesale Goods"
        }
    ],
    "sg:phone":"+61 3 5821 9733",
    "sg:postcode":"3630",
    "sg:province":"VIC",
    "sg:tags":[
        "wholesaler",
        "product",
        "mfrs"
    ],
    "wof:name":"Dairy Farmers",
    "wof:placetype":"venue"
},
  "geometry": {"coordinates":[145.40890502900001,-36.3843955994],"type":"Point"}
}