{
  "type": "Feature",
  "properties": {
    "addr:full":"19 Main St Hervey Bay QLD 4655",
    "addr:housenumber":"19",
    "addr:postcode":"4655",
    "addr:street":"Main St",
    "iso:country":"AU",
    "sg:address":"19 Main St",
    "sg:city":"Hervey Bay",
    "sg:classifiers":[
        {
            "category":"Real Estate",
            "subcategory":"Real Estate Agent",
            "type":"Services"
        }
    ],
    "sg:phone":"+61 7 4194 3444",
    "sg:postcode":"4655",
    "sg:province":"QLD",
    "wof:name":"Re/max",
    "wof:placetype":"venue"
},
  "geometry": {"coordinates":[152.83749399999999,-25.290672],"type":"Point"}
}