{
  "type": "Feature",
  "properties": {
    "addr:full":"Office upwey Upwey VIC 3158",
    "addr:postcode":"3158",
    "iso:country":"AU",
    "sg:address":"Office upwey",
    "sg:city":"Upwey",
    "sg:classifiers":[
        {
            "category":"Arena",
            "subcategory":"Sports Club",
            "type":"Entertainment"
        }
    ],
    "sg:phone":"+61 3 9754 5659",
    "sg:postcode":"3158",
    "sg:province":"VIC",
    "sg:tags":[
        "defence",
        "supply",
        "self",
        "instruction",
        "martial art"
    ],
    "wof:name":"Kendo Dojos Australia",
    "wof:placetype":"venue"
},
  "geometry": {"coordinates":[145.32827758799999,-37.9063911438],"type":"Point"}
}