{
  "type": "Feature",
  "properties": {
    "addr:full":"20 McAdam St Maffra VIC 3860",
    "addr:housenumber":"20",
    "addr:postcode":"3860",
    "addr:street":"Mcadam St",
    "iso:country":"AU",
    "sg:address":"20 McAdam St",
    "sg:city":"Maffra",
    "sg:classifiers":[
        {
            "category":"Building & Trades",
            "subcategory":"Plumbing",
            "type":"Services"
        }
    ],
    "sg:phone":"+61 3 5147 2206",
    "sg:postcode":"3860",
    "sg:province":"VIC",
    "sg:tags":[
        "plumber",
        "gasfitters"
    ],
    "wof:name":"Medew G J",
    "wof:placetype":"venue"
},
  "geometry": {"coordinates":[146.987182617,-37.9694709778],"type":"Point"}
}