{
  "type": "Feature",
  "properties": {
    "addr:full":"PO Box 3023 Newstead QLD 4006",
    "addr:postcode":"4006",
    "iso:country":"AU",
    "sg:address":"PO Box 3023",
    "sg:city":"Newstead",
    "sg:classifiers":[
        {
            "category":"Professional",
            "subcategory":"Detective & Security Services",
            "type":"Services"
        }
    ],
    "sg:phone":"+61 412 350 579",
    "sg:postcode":"4006",
    "sg:province":"QLD",
    "sg:tags":[
        "guard",
        "patrol"
    ],
    "wof:name":"Python Security Service",
    "wof:placetype":"venue"
},
  "geometry": {"coordinates":[153.04527282699999,-27.4538993835],"type":"Point"}
}