{
  "type": "Feature",
  "properties": {
    "addr:full":"452 McClelland Drv Langwarrin VIC 3910",
    "addr:housenumber":"452",
    "addr:postcode":"3910",
    "addr:street":"Mcclelland Drv",
    "iso:country":"AU",
    "sg:address":"452 McClelland Drv",
    "sg:city":"Langwarrin",
    "sg:classifiers":[
        {
            "category":"Social Services",
            "subcategory":"Child Care",
            "type":"Services"
        }
    ],
    "sg:phone":"+61 3 9789 8786",
    "sg:postcode":"3910",
    "sg:province":"VIC",
    "wof:name":"Tiddlywinks Child Care",
    "wof:placetype":"venue"
},
  "geometry": {"coordinates":[145.172607422,-38.151966095],"type":"Point"}
}