{
  "type": "Feature",
  "properties": {
    "addr:full":"125 Vimiera Rd Eastwood NSW 2122",
    "addr:housenumber":"125",
    "addr:postcode":"2122",
    "addr:street":"Vimiera Rd",
    "iso:country":"AU",
    "sg:address":"125 Vimiera Rd",
    "sg:city":"Eastwood",
    "sg:classifiers":[
        {
            "category":"Education",
            "subcategory":"Kindergarten",
            "type":"Public Place"
        }
    ],
    "sg:phone":"+61 2 9876 3834",
    "sg:postcode":"2122",
    "sg:province":"NSW",
    "sg:tags":[
        "pre-schools"
    ],
    "wof:name":"Christopher Robin Pre-School",
    "wof:placetype":"venue"
},
  "geometry": {"coordinates":[151.095092773,-33.7790565491],"type":"Point"}
}