{
  "type": "Feature",
  "properties": {
    "iso:country":"AU",
    "sg:address":"496 Geelong Rd",
    "sg:city":"Tottenham",
    "sg:classifiers":[
        {
            "category":"Retail",
            "subcategory":"Auto Repair",
            "type":"Services"
        }
    ],
    "sg:phone":"+61 3 9314 6704",
    "sg:postcode":"3012",
    "sg:province":"VIC",
    "sg:tags":[
        "repairer",
        "motor",
        "engineer"
    ],
    "wof:name":"One &#039;O&#039; Nine Autos",
    "wof:placetype":"venue"
},
  "geometry": {"coordinates":[144.86029052699999,-37.8133163452],"type":"Point"}
}