{
  "type": "Feature",
  "properties": {
    "iso:country":"AU",
    "sg:address":"266 Dowling St",
    "sg:city":"Dungog",
    "sg:classifiers":[
        {
            "category":"Personal",
            "subcategory":"Beauty Salon",
            "type":"Services"
        }
    ],
    "sg:phone":"+61 2 4992 2292",
    "sg:postcode":"2420",
    "sg:province":"NSW",
    "sg:tags":[
        "hairdresser"
    ],
    "wof:name":"Hairlooms Hair & Beauty",
    "wof:placetype":"venue"
},
  "geometry": {"coordinates":[151.757919,-32.399651],"type":"Point"}
}