{
  "type": "Feature",
  "properties": {
    "addr:full":"Unit 5/ 6 Stanton Rd Seven Hills NSW 2147",
    "addr:housenumber":"6",
    "addr:postcode":"2147",
    "addr:street":"Stanton Rd",
    "iso:country":"AU",
    "sg:address":"Unit 5/ 6 Stanton Rd",
    "sg:city":"Seven Hills",
    "sg:classifiers":[
        {
            "category":"Manufacturing",
            "subcategory":"Rubber & Plastics",
            "type":"Manufacturing & Wholesale Goods"
        }
    ],
    "sg:phone":"+61 2 9674 5711",
    "sg:postcode":"2147",
    "sg:province":"NSW",
    "sg:tags":[
        "moulders"
    ],
    "wof:name":"Viscount Plastics (NSW) Pty Ltd",
    "wof:placetype":"venue"
},
  "geometry": {"coordinates":[150.949676514,-33.7701454163],"type":"Point"}
}