{
  "type": "Feature",
  "properties": {
    "addr:full":"Ste5a/ 13 Walkers Rd Nunawading VIC 3131",
    "addr:housenumber":"13",
    "addr:postcode":"3131",
    "addr:street":"Walkers Rd",
    "iso:country":"AU",
    "sg:address":"Ste5a/ 13 Walkers Rd",
    "sg:city":"Nunawading",
    "sg:classifiers":[
        {
            "category":"Professional",
            "subcategory":"Employment Agencies",
            "type":"Services"
        }
    ],
    "sg:phone":"+61 3 9878 8426",
    "sg:postcode":"3131",
    "sg:province":"VIC",
    "wof:name":"Australian Recruiting Pty Ltd",
    "wof:placetype":"venue"
},
  "geometry": {"coordinates":[145.17788696299999,-37.8197517395],"type":"Point"}
}