{
  "type": "Feature",
  "properties": {
    "addr:full":"151 Myrtle St Myrtleford VIC 3737",
    "addr:housenumber":"151",
    "addr:postcode":"3737",
    "addr:street":"Myrtle St",
    "iso:country":"AU",
    "sg:address":"151 Myrtle St",
    "sg:city":"Myrtleford",
    "sg:classifiers":[
        {
            "category":"Professional",
            "subcategory":"Accounting & Tax Preparation",
            "type":"Services"
        }
    ],
    "sg:phone":"+61 3 5752 1544",
    "sg:postcode":"3737",
    "sg:province":"VIC",
    "sg:tags":[
        "consultant",
        "taxation"
    ],
    "wof:name":"Paynter & Parmesan",
    "wof:placetype":"venue"
},
  "geometry": {"coordinates":[146.72410583499999,-36.5607528687],"type":"Point"}
}