{
  "type": "Feature",
  "properties": {
    "addr:full":"25 Blaxland Rd Campbelltown NSW 2560",
    "addr:housenumber":"25",
    "addr:postcode":"2560",
    "addr:street":"Blaxland Rd",
    "iso:country":"AU",
    "sg:address":"25 Blaxland Rd",
    "sg:city":"Campbelltown",
    "sg:classifiers":[
        {
            "category":"Retail",
            "subcategory":"Auto Rental",
            "type":"Services"
        }
    ],
    "sg:phone":"+61 2 4645 6800",
    "sg:postcode":"2560",
    "sg:province":"NSW",
    "sg:tags":[
        "bus",
        "truck"
    ],
    "wof:name":"Budget",
    "wof:placetype":"venue"
},
  "geometry": {"coordinates":[150.81582641599999,-34.0579872131],"type":"Point"}
}