{
  "type": "Feature",
  "properties": {
    "addr:full":"70 Henry St Traralgon VIC 3844",
    "addr:housenumber":"70",
    "addr:postcode":"3844",
    "addr:street":"Henry St",
    "iso:country":"AU",
    "sg:address":"70 Henry St",
    "sg:city":"Traralgon",
    "sg:classifiers":[
        {
            "category":"Travel",
            "subcategory":"Hostel",
            "type":"Entertainment"
        }
    ],
    "sg:phone":"+61 3 5176 1411",
    "sg:postcode":"3844",
    "sg:province":"VIC",
    "sg:tags":[
        "home"
    ],
    "wof:name":"Glenwood Assisted Living",
    "wof:placetype":"venue"
},
  "geometry": {"coordinates":[146.523193359,-38.1970672607],"type":"Point"}
}