{
  "type": "Feature",
  "properties": {
    "iso:country":"AU",
    "sg:address":"Cnr Walker & King Sts",
    "sg:city":"Lancelin",
    "sg:classifiers":[
        {
            "category":"Autos & Motor Vehicles",
            "subcategory":"Auto Supplies",
            "type":"Retail Goods"
        }
    ],
    "sg:phone":"+61 8 9655 1367",
    "sg:postcode":"6044",
    "sg:province":"WA",
    "sg:tags":[
        "tyre"
    ],
    "wof:name":"Lancelin Tyres Tools & Batteries",
    "wof:placetype":"venue"
},
  "geometry": {"coordinates":[115.33255004900001,-31.0215492249],"type":"Point"}
}