{
  "type": "Feature",
  "properties": {
    "addr:full":"1A-D, 10-18 Jacka Blv St Kilda VIC 3182",
    "addr:housenumber":"1a-d 10-18",
    "addr:postcode":"3182",
    "addr:street":"Jacka Blv",
    "iso:country":"AU",
    "sg:address":"1A-D, 10-18 Jacka Blv",
    "sg:city":"St Kilda",
    "sg:classifiers":[
        {
            "category":"Restaurant",
            "type":"Food & Drink"
        }
    ],
    "sg:phone":"+61 3 8598 9055",
    "sg:postcode":"3182",
    "sg:province":"VIC",
    "sg:website":"http://www.amello.com.au",
    "wof:name":"Amello",
    "wof:placetype":"venue"
},
  "geometry": {"coordinates":[144.97381591800001,-37.8663711548],"type":"Point"}
}