{
  "type": "Feature",
  "properties": {
    "iso:country":"AU",
    "sg:address":"1 Rodwell Pl",
    "sg:city":"Bunbury",
    "sg:classifiers":[
        {
            "category":"Professional",
            "subcategory":"Art Services",
            "type":"Services"
        }
    ],
    "sg:phone":"+61 8 9721 8496",
    "sg:postcode":"6230",
    "sg:province":"WA",
    "sg:tags":[
        "decorator",
        "painter"
    ],
    "wof:name":"L W Parker",
    "wof:placetype":"venue"
},
  "geometry": {"coordinates":[115.65522799999999,-33.332905],"type":"Point"}
}