{
  "type": "Feature",
  "properties": {
    "iso:country":"AU",
    "sg:address":"1 Gardiner St",
    "sg:city":"Moora",
    "sg:classifiers":[
        {
            "category":"Travel",
            "subcategory":"Hotels & Motels",
            "type":"Entertainment"
        }
    ],
    "sg:phone":"+61 8 9651 1177",
    "sg:postcode":"6510",
    "sg:province":"WA",
    "sg:tags":[
        "accommodation"
    ],
    "wof:name":"Moora Hotel",
    "wof:placetype":"venue"
},
  "geometry": {"coordinates":[116.01119199999999,-30.647465],"type":"Point"}
}