{
  "type": "Feature",
  "properties": {
    "addr:full":"10/24 Harry Chan Ave Darwin NT 0800",
    "addr:housenumber":"10 / 24",
    "addr:postcode":"nt 0800",
    "addr:street":"Harry Chan Ave",
    "iso:country":"AU",
    "sg:address":"10/24 Harry Chan Ave",
    "sg:city":"Darwin",
    "sg:classifiers":[
        {
            "category":"Building & Trades",
            "subcategory":"Cleaning & Sanitation",
            "type":"Services"
        }
    ],
    "sg:phone":"+61 414 490 109",
    "sg:postcode":"0800",
    "sg:province":"NT",
    "sg:tags":[
        "industrial",
        "commercial",
        "contractor"
    ],
    "wof:name":"MRL Cleaning Services",
    "wof:placetype":"venue"
},
  "geometry": {"coordinates":[130.8462677,-12.4644794464],"type":"Point"}
}