{
  "type": "Feature",
  "properties": {
    "addr:full":"PO Box 1125 Bega NSW 2550",
    "addr:postcode":"bega nsw 2550",
    "iso:country":"AU",
    "sg:address":"PO Box 1125",
    "sg:city":"Bega",
    "sg:classifiers":[
        {
            "category":"Professional",
            "subcategory":"Detective & Security Services",
            "type":"Services"
        }
    ],
    "sg:phone":"+61 2 6492 0165",
    "sg:postcode":"2550",
    "sg:province":"NSW",
    "sg:tags":[
        "alarm",
        "protection",
        "system",
        "machinery"
    ],
    "wof:name":"Kens Auto Electrics & Air Conditioning Mobile Workshop",
    "wof:placetype":"venue"
},
  "geometry": {"coordinates":[149.84138488799999,-36.6739883423],"type":"Point"}
}