{
  "type": "Feature",
  "properties": {
    "addr:full":"28 Eyre St Kingston ACT 2604",
    "addr:housenumber":"28",
    "addr:postcode":"2604",
    "addr:street":"Eyre St",
    "iso:country":"AU",
    "sg:address":"28 Eyre St",
    "sg:city":"Kingston",
    "sg:classifiers":[
        {
            "category":"Real Estate",
            "subcategory":"Surveying",
            "type":"Services"
        }
    ],
    "sg:phone":"+61 2 6239 4155",
    "sg:postcode":"2604",
    "sg:province":"ACT",
    "sg:tags":[
        "surveyor",
        "quantity"
    ],
    "wof:name":"Wilde & Woollard",
    "wof:placetype":"venue"
},
  "geometry": {"coordinates":[149.14178466800001,-35.3168525696],"type":"Point"}
}