{
  "type": "Feature",
  "properties": {
    "addr:full":"189 Brisbane Rd Mooloolaba QLD 4557",
    "addr:housenumber":"189",
    "addr:postcode":"4557",
    "addr:street":"Brisbane Rd",
    "iso:country":"AU",
    "sg:address":"189 Brisbane Rd",
    "sg:city":"Mooloolaba",
    "sg:classifiers":[
        {
            "category":"Structure",
            "subcategory":"Bridge",
            "type":"Public Place"
        }
    ],
    "sg:phone":"+61 7 5444 2577",
    "sg:postcode":"4557",
    "sg:province":"QLD",
    "sg:tags":[
        "chainsaw",
        "brushcutters"
    ],
    "wof:name":"Sunshine Coast Mowers",
    "wof:placetype":"venue"
},
  "geometry": {"coordinates":[153.115234375,-26.6933078766],"type":"Point"}
}