{
  "type": "Feature",
  "properties": {
    "addr:full":"Goolwa Rd Middleton SA 5213",
    "addr:postcode":"5213",
    "addr:street":"Goolwa Rd",
    "iso:country":"AU",
    "sg:address":"Goolwa Rd",
    "sg:city":"Middleton",
    "sg:classifiers":[
        {
            "category":"Travel",
            "subcategory":"Hotels & Motels",
            "type":"Entertainment"
        }
    ],
    "sg:phone":"+61 8 8554 3010",
    "sg:postcode":"5213",
    "sg:province":"SA",
    "sg:tags":[
        "accommodation"
    ],
    "wof:name":"Middleton Tavern",
    "wof:placetype":"venue"
},
  "geometry": {"coordinates":[138.70599365199999,-35.4847602844],"type":"Point"}
}