{
  "type": "Feature",
  "properties": {
    "iso:country":"AU",
    "sg:address":"St Stephen&#039;s Medical Centre Boat Harbour Drv",
    "sg:city":"Hervey Bay",
    "sg:classifiers":[
        {
            "category":"Health Services",
            "subcategory":"Doctor",
            "type":"Services"
        }
    ],
    "sg:phone":"+61 7 3737 4500",
    "sg:postcode":"4655",
    "sg:province":"QLD",
    "sg:tags":[
        "medical",
        "practitioner"
    ],
    "wof:name":"Durrant Simon",
    "wof:placetype":"venue"
},
  "geometry": {"coordinates":[152.836288,-25.287842],"type":"Point"}
}