{
  "type": "Feature",
  "properties": {
    "iso:country":"AU",
    "sg:address":"54 Benaroon Rd",
    "sg:city":"Lakemba",
    "sg:classifiers":[
        {
            "category":"Building & Trades",
            "subcategory":"Construction",
            "type":"Services"
        }
    ],
    "sg:phone":"+61 400 420 675",
    "sg:postcode":"2195",
    "sg:province":"NSW",
    "sg:tags":[
        "concrete",
        "contractor"
    ],
    "wof:name":"All Concrete Services",
    "wof:placetype":"venue"
},
  "geometry": {"coordinates":[151.079453,-33.91301],"type":"Point"}
}