{
  "type": "Feature",
  "properties": {
    "addr:full":"1080 Munetta Rd Pages Flat SA 5172",
    "addr:housenumber":"1080",
    "addr:postcode":"5172",
    "addr:street":"Munetta Rd",
    "iso:country":"AU",
    "sg:address":"1080 Munetta Rd",
    "sg:city":"Pages Flat",
    "sg:classifiers":[
        {
            "category":"Health Services",
            "subcategory":"Doctor",
            "type":"Services"
        }
    ],
    "sg:phone":"+61 8 8556 1166",
    "sg:postcode":"5172",
    "sg:province":"SA",
    "sg:tags":[
        "occupational",
        "safety"
    ],
    "wof:name":"CPR Safe - Ind",
    "wof:placetype":"venue"
},
  "geometry": {"coordinates":[138.56565856899999,-35.3335723877],"type":"Point"}
}