{
  "type": "Feature",
  "properties": {
    "iso:country":"AU",
    "sg:address":"9 Mark St",
    "sg:city":"Forster",
    "sg:classifiers":[
        {
            "category":"Health Services",
            "subcategory":"Chiropractor",
            "type":"Services"
        }
    ],
    "sg:phone":"+61 2 6557 6227",
    "sg:postcode":"2428",
    "sg:province":"NSW",
    "wof:name":"Helen Dempsey Chiropractor",
    "wof:placetype":"venue"
},
  "geometry": {"coordinates":[152.513336,-32.194138],"type":"Point"}
}