{
  "type": "Feature",
  "properties": {
    "addr:full":"Cnr Scotland & Princess Sts Bundaberg QLD 4670",
    "addr:postcode":"4670",
    "addr:street":"Cnr",
    "iso:country":"AU",
    "sg:address":"Cnr Scotland & Princess Sts",
    "sg:city":"Bundaberg",
    "sg:classifiers":[
        {
            "category":"Shopping",
            "subcategory":"Discount & Variety Stores",
            "type":"Retail Goods"
        }
    ],
    "sg:phone":"+61 7 4152 8546",
    "sg:postcode":"4670",
    "sg:province":"QLD",
    "sg:tags":[
        "shop",
        "adult"
    ],
    "wof:name":"Hidden Desire",
    "wof:placetype":"venue"
},
  "geometry": {"coordinates":[152.36166381800001,-24.8610191345],"type":"Point"}
}