{
  "type": "Feature",
  "properties": {
    "addr:full":"24 Tyalgum St Mudgeeraba QLD 4213",
    "addr:housenumber":"24",
    "addr:postcode":"4213",
    "addr:street":"Tyalgum St",
    "iso:country":"AU",
    "sg:address":"24 Tyalgum St",
    "sg:city":"Mudgeeraba",
    "sg:classifiers":[
        {
            "category":"Shopping",
            "subcategory":"Party Supplies",
            "type":"Retail Goods"
        }
    ],
    "sg:phone":"+61 7 5530 3572",
    "sg:postcode":"4213",
    "sg:province":"QLD",
    "sg:tags":[
        "children's"
    ],
    "wof:name":"Mudgeeraba Marionettes",
    "wof:placetype":"venue"
},
  "geometry": {"coordinates":[153.31800842300001,-28.0978221893],"type":"Point"}
}