{
  "type": "Feature",
  "properties": {
    "addr:full":"Level 14 222 Kings Way South Melbourne VIC 3205",
    "addr:housenumber":"222",
    "addr:postcode":"3205",
    "addr:street":"Kings Way",
    "iso:country":"AU",
    "sg:address":"Level 14 222 Kings Way",
    "sg:city":"South Melbourne",
    "sg:classifiers":[
        {
            "category":"Professional",
            "subcategory":"Engineering",
            "type":"Services"
        }
    ],
    "sg:phone":"+61 3 9686 8081",
    "sg:postcode":"3205",
    "sg:province":"VIC",
    "sg:tags":[
        "consulting",
        "engineer"
    ],
    "wof:name":"Aerostructures Australia",
    "wof:placetype":"venue"
},
  "geometry": {"coordinates":[144.96485899999999,-37.83083],"type":"Point"}
}