{
  "type": "Feature",
  "properties": {
    "addr:full":"Shop 1/ 170-2172 Jacobs Drv Sussex Inlet NSW 2540",
    "addr:housenumber":"shop 1 / 170-2172",
    "addr:postcode":"2540",
    "addr:street":"Jacobs Drv",
    "iso:country":"AU",
    "sg:address":"Shop 1/ 170-2172 Jacobs Drv",
    "sg:city":"Sussex Inlet",
    "sg:classifiers":[
        {
            "category":"Shopping",
            "subcategory":"Bicycles & Sporting Goods",
            "type":"Retail Goods"
        }
    ],
    "sg:phone":"+61 2 4441 1938",
    "sg:postcode":"2540",
    "sg:province":"NSW",
    "sg:tags":[
        "water",
        "equipment",
        "skiing"
    ],
    "wof:name":"Sun & Surf",
    "wof:placetype":"venue"
},
  "geometry": {"coordinates":[150.59942626899999,-35.1569900513],"type":"Point"}
}