{
  "type": "Feature",
  "properties": {
    "iso:country":"AU",
    "sg:address":"4 Rocksleigh Ave",
    "sg:city":"Tecoma",
    "sg:classifiers":[
        {
            "category":"Education",
            "subcategory":"Special Training",
            "type":"Public Place"
        }
    ],
    "sg:phone":"+61 3 9754 5926",
    "sg:postcode":"3160",
    "sg:province":"VIC",
    "sg:tags":[
        "drama",
        "tuition"
    ],
    "wof:name":"The Drama Craft Company",
    "wof:placetype":"venue"
},
  "geometry": {"coordinates":[145.347167969,-37.9078598022],"type":"Point"}
}