{
  "type": "Feature",
  "properties": {
    "addr:full":"Unit 3 Lot 3 Lukis Ave Richmond NSW 2753",
    "addr:housenumber":"lot 3",
    "addr:postcode":"2753",
    "addr:street":"Lukis Ave",
    "iso:country":"AU",
    "sg:address":"Unit 3 Lot 3 Lukis Ave",
    "sg:city":"Richmond",
    "sg:classifiers":[
        {
            "category":"Retail",
            "subcategory":"Auto Repair",
            "type":"Services"
        }
    ],
    "sg:phone":"+61 2 4588 5455",
    "sg:postcode":"2753",
    "sg:province":"NSW",
    "sg:tags":[
        "gas",
        "conversion",
        "natural",
        "lp",
        "vehicle"
    ],
    "wof:name":"Christie's Auto Services",
    "wof:placetype":"venue"
},
  "geometry": {"coordinates":[150.763275147,-33.6009674072],"type":"Point"}
}