{
  "type": "Feature",
  "properties": {
    "addr:full":"Tarlington Pde Bonnyrigg NSW 2177",
    "addr:postcode":"2177",
    "addr:street":"Pde",
    "iso:country":"AU",
    "sg:address":"Tarlington Pde",
    "sg:city":"Bonnyrigg",
    "sg:classifiers":[
        {
            "category":"Education",
            "subcategory":"School",
            "type":"Public Place"
        }
    ],
    "sg:phone":"+61 2 9610 1511",
    "sg:postcode":"2177",
    "sg:province":"NSW",
    "sg:tags":[
        "state",
        "-",
        "nsw"
    ],
    "wof:name":"Bonnyrigg Public School",
    "wof:placetype":"venue"
},
  "geometry": {"coordinates":[150.89239501899999,-33.8928375244],"type":"Point"}
}