{
  "type": "Feature",
  "properties": {
    "addr:full":"Cnr Sheppard St & Tapleys Hill Rd Hendon SA 5014",
    "addr:housenumber":"cnr",
    "addr:postcode":"5014",
    "addr:street":"Sheppard St & Tapleys Hill Rd",
    "iso:country":"AU",
    "sg:address":"Cnr Sheppard St & Tapleys Hill Rd",
    "sg:city":"Hendon",
    "sg:classifiers":[
        {
            "category":"Building & Trades",
            "subcategory":"Construction",
            "type":"Services"
        }
    ],
    "sg:phone":"+61 8 8241 2833",
    "sg:postcode":"5014",
    "sg:province":"SA",
    "sg:tags":[
        "equipment",
        "system",
        "automation"
    ],
    "wof:name":"Oakes Automation-Electrical Services",
    "wof:placetype":"venue"
},
  "geometry": {"coordinates":[138.513504028,-34.8695068359],"type":"Point"}
}