{
  "type": "Feature",
  "properties": {
    "iso:country":"AU",
    "sg:address":"61 Campbell St",
    "sg:city":"Bowen Hills",
    "sg:classifiers":[
        {
            "category":"Wholesale",
            "subcategory":"Painting Supplies",
            "type":"Manufacturing & Wholesale Goods"
        }
    ],
    "sg:phone":"+61 7 3253 6271",
    "sg:postcode":"4006",
    "sg:province":"QLD",
    "sg:tags":[
        "product",
        "cleaning"
    ],
    "wof:name":"Alliance Technology",
    "wof:placetype":"venue"
},
  "geometry": {"coordinates":[153.033325195,-27.4472351074],"type":"Point"}
}