{
  "type": "Feature",
  "properties": {
    "addr:full":"17 Durham St Carlton NSW 2218",
    "addr:housenumber":"17",
    "addr:postcode":"2218",
    "addr:street":"Durham St",
    "iso:country":"AU",
    "sg:address":"17 Durham St",
    "sg:city":"Carlton",
    "sg:classifiers":[
        {
            "category":"Home & Garden",
            "subcategory":"Furniture",
            "type":"Retail Goods"
        }
    ],
    "sg:phone":"+61 2 9553 9313",
    "sg:postcode":"2218",
    "sg:province":"NSW",
    "sg:tags":[
        "repair",
        "restoration"
    ],
    "wof:name":"Mark Rileys Upholstery",
    "wof:placetype":"venue"
},
  "geometry": {"coordinates":[151.117279,-33.965775],"type":"Point"}
}