{
  "type": "Feature",
  "properties": {
    "addr:full":"86 Port Stephens St Raymond Terrace NSW 2324",
    "addr:housenumber":"86",
    "addr:postcode":"2324",
    "addr:street":"Port Stephens St",
    "iso:country":"AU",
    "sg:address":"86 Port Stephens St",
    "sg:city":"Raymond Terrace",
    "sg:classifiers":[
        {
            "category":"Retail",
            "subcategory":"Self-service Laundry",
            "type":"Services"
        }
    ],
    "sg:phone":"+61 2 4987 3444",
    "sg:postcode":"2324",
    "sg:province":"NSW",
    "wof:name":"Raymond Terrace Laundrette",
    "wof:placetype":"venue"
},
  "geometry": {"coordinates":[151.74130249000001,-32.7618293762],"type":"Point"}
}