{
  "type": "Feature",
  "properties": {
    "addr:full":"49- 55 York St South Melbourne VIC 3205",
    "addr:housenumber":"55",
    "addr:postcode":"3205",
    "addr:street":"York St",
    "iso:country":"AU",
    "sg:address":"49- 55 York St",
    "sg:city":"South Melbourne",
    "sg:classifiers":[
        {
            "category":"Wholesale",
            "subcategory":"Construction Materials",
            "type":"Manufacturing & Wholesale Goods"
        }
    ],
    "sg:phone":"+61 3 9699 2844",
    "sg:postcode":"3205",
    "sg:province":"VIC",
    "sg:tags":[
        "wholesaler",
        "lighting",
        "mfrs",
        "accessory"
    ],
    "wof:name":"Lampada",
    "wof:placetype":"venue"
},
  "geometry": {"coordinates":[144.96154799999999,-37.830334],"type":"Point"}
}