{
  "type": "Feature",
  "properties": {
    "addr:full":"Unit 1, 24- 26 Isles Drv Coffs Harbour NSW 2450",
    "addr:housenumber":"24 26",
    "addr:postcode":"2450",
    "addr:street":"Isles Drv",
    "iso:country":"AU",
    "sg:address":"Unit 1, 24- 26 Isles Drv",
    "sg:city":"Coffs Harbour",
    "sg:classifiers":[
        {
            "category":"Building & Trades",
            "subcategory":"Construction",
            "type":"Services"
        }
    ],
    "sg:phone":"+61 2 6652 5366",
    "sg:postcode":"2450",
    "sg:province":"NSW",
    "sg:tags":[
        "builder",
        "designer",
        "room",
        "cool"
    ],
    "wof:name":"Allied Air Conditioning & Refrigeration Coffs Harbour Pty Ltd",
    "wof:placetype":"venue"
},
  "geometry": {"coordinates":[153.088257,-30.315748],"type":"Point"}
}