{
  "type": "Feature",
  "properties": {
    "addr:full":"352 Nudgee Rd Hendra QLD 4011",
    "addr:housenumber":"352",
    "addr:postcode":"4011",
    "addr:street":"Nudgee Rd",
    "iso:country":"AU",
    "sg:address":"352 Nudgee Rd",
    "sg:city":"Hendra",
    "sg:classifiers":[
        {
            "category":"Building & Trades",
            "subcategory":"Plumbing",
            "type":"Services"
        }
    ],
    "sg:phone":"+61 7 3268 2132",
    "sg:postcode":"4011",
    "sg:province":"QLD",
    "sg:tags":[
        "fitting",
        "hose",
        "supply"
    ],
    "wof:name":"Enzed",
    "wof:placetype":"venue"
},
  "geometry": {"coordinates":[153.073654,-27.41872],"type":"Point"}
}