{
  "type": "Feature",
  "properties": {
    "addr:full":"Millar Rd Yanakie VIC 3960",
    "addr:postcode":"3960",
    "addr:street":"Millar Rd",
    "iso:country":"AU",
    "sg:address":"Millar Rd",
    "sg:city":"Yanakie",
    "sg:classifiers":[
        {
            "category":"Farming",
            "subcategory":"Farm",
            "type":"Manufacturing & Wholesale Goods"
        }
    ],
    "sg:phone":"+61 3 5687 1204",
    "sg:postcode":"3960",
    "sg:province":"VIC",
    "sg:tags":[
        "farmer"
    ],
    "wof:name":"Truscott R & G",
    "wof:placetype":"venue"
},
  "geometry": {"coordinates":[146.20539855999999,-38.8112831116],"type":"Point"}
}