{
  "type": "Feature",
  "properties": {
    "iso:country":"AU",
    "sg:address":"50 Galeen Drv",
    "sg:city":"Burleigh Waters",
    "sg:classifiers":[
        {
            "category":"Shopping",
            "subcategory":"Beauty & Cosmetics",
            "type":"Retail Goods"
        }
    ],
    "sg:phone":"+61 7 5520 3146",
    "sg:postcode":"4220",
    "sg:province":"QLD",
    "wof:name":"House of eLidi",
    "wof:placetype":"venue"
},
  "geometry": {"coordinates":[153.43157959000001,-28.0789890289],"type":"Point"}
}