{
  "type": "Feature",
  "properties": {
    "addr:full":"60 Berkeley Rd Fountaindale NSW 2259",
    "addr:housenumber":"60",
    "addr:postcode":"2259",
    "addr:street":"Berkeley Rd",
    "iso:country":"AU",
    "sg:address":"60 Berkeley Rd",
    "sg:city":"Fountaindale",
    "sg:classifiers":[
        {
            "category":"Organizations",
            "subcategory":"Community Association",
            "type":"Services"
        }
    ],
    "sg:phone":"+61 2 4388 4588",
    "sg:postcode":"2259",
    "sg:province":"NSW",
    "sg:tags":[
        "organisation",
        "family",
        "welfare"
    ],
    "wof:name":"Salvation Army Selah Rehabilitation Centre",
    "wof:placetype":"venue"
},
  "geometry": {"coordinates":[151.42291259800001,-33.1819992065],"type":"Point"}
}