{
  "type": "Feature",
  "properties": {
    "iso:country":"AU",
    "sg:address":"5/ 38",
    "sg:city":"Irrigation Wy Griffith",
    "sg:classifiers":[
        {
            "category":"Wholesale",
            "subcategory":"Electrical",
            "type":"Manufacturing & Wholesale Goods"
        }
    ],
    "sg:phone":"+61 2 6964 6125",
    "sg:postcode":"2680",
    "sg:province":"NSW",
    "sg:tags":[
        "wholesaler"
    ],
    "wof:name":"Rexel Australia Electrical Supplies",
    "wof:placetype":"venue"
},
  "geometry": {"coordinates":[146.08497600000001,-34.302528],"type":"Point"}
}