{
  "type": "Feature",
  "properties": {
    "addr:full":"11 Josephine St Loganholme QLD 4129",
    "addr:housenumber":"11",
    "addr:postcode":"4129",
    "addr:street":"Josephine St",
    "iso:country":"AU",
    "sg:address":"11 Josephine St",
    "sg:city":"Loganholme",
    "sg:classifiers":[
        {
            "category":"Wholesale",
            "subcategory":"Home Furnishings",
            "type":"Manufacturing & Wholesale Goods"
        }
    ],
    "sg:phone":"+61 7 3806 4100",
    "sg:postcode":"4129",
    "sg:province":"QLD",
    "sg:tags":[
        "wholesaler",
        "mfrs",
        "manchester"
    ],
    "wof:name":"H Polesy & Co",
    "wof:placetype":"venue"
},
  "geometry": {"coordinates":[153.19554138199999,-27.6825523376],"type":"Point"}
}