{
  "type": "Feature",
  "properties": {
    "iso:country":"AU",
    "sg:address":"71 Barkly St",
    "sg:city":"St Kilda",
    "sg:classifiers":[
        {
            "category":"Health Services",
            "subcategory":"Health Practitioner",
            "type":"Services"
        }
    ],
    "sg:phone":"+61 3 9534 0795",
    "sg:postcode":"3182",
    "sg:province":"VIC",
    "sg:tags":[
        "psychotherapist"
    ],
    "wof:name":"Kairos Centre",
    "wof:placetype":"venue"
},
  "geometry": {"coordinates":[144.98204040499999,-37.8616676331],"type":"Point"}
}