{
  "type": "Feature",
  "properties": {
    "iso:country":"AU",
    "sg:address":"13 Halstead Pl",
    "sg:city":"Bomaderry",
    "sg:classifiers":[
        {
            "category":"Building & Trades",
            "subcategory":"Construction",
            "type":"Services"
        }
    ],
    "sg:phone":"+61 2 4448 6333",
    "sg:postcode":"2541",
    "sg:province":"NSW",
    "sg:tags":[
        "renovation",
        "alterations",
        "extension",
        "contractor"
    ],
    "wof:name":"GJ & CM Butler Building",
    "wof:placetype":"venue"
},
  "geometry": {"coordinates":[150.60618591299999,-34.833480835],"type":"Point"}
}