{
  "type": "Feature",
  "properties": {
    "addr:full":"Hibiscus Sports Complex 90 Klumpp Rd Upper Mt Gravatt QLD 4122",
    "addr:housenumber":"90",
    "addr:postcode":"4122",
    "addr:street":"Klumpp Rd Upper",
    "iso:country":"AU",
    "sg:address":"Hibiscus Sports Complex 90 Klumpp Rd",
    "sg:city":"Upper Mt Gravatt",
    "sg:classifiers":[
        {
            "category":"Health Services",
            "subcategory":"Health Practitioner",
            "type":"Services"
        }
    ],
    "sg:phone":"+61 7 3349 5733",
    "sg:postcode":"4122",
    "sg:province":"QLD",
    "sg:tags":[
        "physiotherapist"
    ],
    "wof:name":"Optima Sports Medicine",
    "wof:placetype":"venue"
},
  "geometry": {"coordinates":[153.07211303700001,-27.5519180298],"type":"Point"}
}