{
  "type": "Feature",
  "properties": {
    "iso:country":"AU",
    "sg:address":"43 Winstanley St",
    "sg:city":"Carina",
    "sg:classifiers":[
        {
            "category":"Professional",
            "subcategory":"Computer Services",
            "type":"Services"
        }
    ],
    "sg:phone":"+61 7 3901 6248",
    "sg:postcode":"4152",
    "sg:province":"QLD",
    "sg:tags":[
        "package",
        "software"
    ],
    "wof:name":"Idasoft",
    "wof:placetype":"venue"
},
  "geometry": {"coordinates":[153.08926391599999,-27.5037288666],"type":"Point"}
}