{
  "type": "Feature",
  "properties": {
    "iso:country":"AU",
    "sg:address":"21 Wardoo St",
    "sg:city":"Southport",
    "sg:classifiers":[
        {
            "category":"Building & Trades",
            "subcategory":"Construction",
            "type":"Services"
        }
    ],
    "sg:phone":"+61 418 743 684",
    "sg:postcode":"4215",
    "sg:province":"QLD",
    "sg:tags":[
        "joiner",
        "carpenter"
    ],
    "wof:name":"Ford J W",
    "wof:placetype":"venue"
},
  "geometry": {"coordinates":[153.394332886,-27.9913654327],"type":"Point"}
}