{
  "type": "Feature",
  "properties": {
    "addr:full":"86 Through St South Grafton NSW 2460",
    "addr:housenumber":"86",
    "addr:postcode":"2460",
    "addr:street":"Through St",
    "iso:country":"AU",
    "sg:address":"86 Through St",
    "sg:city":"South Grafton",
    "sg:classifiers":[
        {
            "category":"Health Services",
            "subcategory":"Doctor",
            "type":"Services"
        }
    ],
    "sg:phone":"+61 2 6643 4448",
    "sg:postcode":"2460",
    "sg:province":"NSW",
    "sg:tags":[
        "medical",
        "practitioner"
    ],
    "wof:name":"Southside Doctors Surgery",
    "wof:placetype":"venue"
},
  "geometry": {"coordinates":[152.93588256800001,-29.7015838623],"type":"Point"}
}