{
  "type": "Feature",
  "properties": {
    "iso:country":"AU",
    "sg:address":"PO Box 2412",
    "sg:city":"Broome",
    "sg:classifiers":[
        {
            "category":"Taxi",
            "type":"Transportation"
        }
    ],
    "sg:phone":"+61 8 9192 1133",
    "sg:postcode":"6725",
    "sg:province":"WA",
    "sg:tags":[
        "cab"
    ],
    "wof:name":"Broome Taxis",
    "wof:placetype":"venue"
},
  "geometry": {"coordinates":[122.677589416,-18.2141704559],"type":"Point"}
}