{
  "type": "Feature",
  "properties": {
    "addr:full":"Unit 3/ 12 Forge St Blacktown NSW 2148",
    "addr:housenumber":"12",
    "addr:postcode":"2148",
    "addr:street":"Forge St",
    "iso:country":"AU",
    "sg:address":"Unit 3/ 12 Forge St",
    "sg:city":"Blacktown",
    "sg:classifiers":[
        {
            "category":"Autos & Motor Vehicles",
            "subcategory":"Auto Supplies",
            "type":"Retail Goods"
        }
    ],
    "sg:phone":"+61 2 9621 7104",
    "sg:postcode":"2148",
    "sg:province":"NSW",
    "sg:tags":[
        "accessory"
    ],
    "wof:name":"Inner Active Manifold",
    "wof:placetype":"venue"
},
  "geometry": {"coordinates":[150.90951538100001,-33.7561264038],"type":"Point"}
}