{
  "type": "Feature",
  "properties": {
    "addr:full":"4/ 114 Fairfield St Fairfield NSW 2165",
    "addr:housenumber":"/ 114",
    "addr:postcode":"2165",
    "addr:street":"Fairfield St",
    "iso:country":"AU",
    "sg:address":"4/ 114 Fairfield St",
    "sg:city":"Fairfield",
    "sg:classifiers":[
        {
            "category":"Retail",
            "subcategory":"Repair Shop",
            "type":"Services"
        }
    ],
    "sg:phone":"+61 2 9681 1926",
    "sg:postcode":"2165",
    "sg:province":"NSW",
    "sg:tags":[
        "upholsterer"
    ],
    "wof:name":"Tru-Trim Upholstery Manufacturer",
    "wof:placetype":"venue"
},
  "geometry": {"coordinates":[150.970779419,-33.8683776855],"type":"Point"}
}