{
  "type": "Feature",
  "properties": {
    "iso:country":"AU",
    "sg:address":"25 Hughes St",
    "sg:city":"Yarraville",
    "sg:classifiers":[
        {
            "category":"Professional",
            "subcategory":"Employment Agencies",
            "type":"Services"
        }
    ],
    "sg:phone":"+61 439 448 123",
    "sg:postcode":"3013",
    "sg:province":"VIC",
    "sg:tags":[
        "entertainer",
        "agent"
    ],
    "wof:name":"Mac Brothers Entertainment",
    "wof:placetype":"venue"
},
  "geometry": {"coordinates":[144.890167236,-37.8233261108],"type":"Point"}
}