{
  "type": "Feature",
  "properties": {
    "addr:full":"46- 48 Redfern St Wetherill Park NSW 2164",
    "addr:housenumber":"48",
    "addr:postcode":"2164",
    "addr:street":"Redfern St",
    "iso:country":"AU",
    "sg:address":"46- 48 Redfern St",
    "sg:city":"Wetherill Park",
    "sg:classifiers":[
        {
            "category":"Wholesale",
            "subcategory":"Home Furnishings",
            "type":"Manufacturing & Wholesale Goods"
        }
    ],
    "sg:phone":"+61 2 9604 8082",
    "sg:postcode":"2164",
    "sg:province":"NSW",
    "sg:tags":[
        "wholesaler",
        "mfrs",
        "manchester"
    ],
    "wof:name":"Kingtex International Pty Ltd",
    "wof:placetype":"venue"
},
  "geometry": {"coordinates":[150.91299438499999,-33.8438453674],"type":"Point"}
}