{
  "type": "Feature",
  "properties": {
    "addr:full":"Cnr Waratah & Keenan Sts Mona Vale NSW 2103",
    "addr:postcode":"2103",
    "addr:street":"Cnr",
    "iso:country":"AU",
    "sg:address":"Cnr Waratah & Keenan Sts",
    "sg:city":"Mona Vale",
    "sg:classifiers":[
        {
            "category":"Food & Beverages",
            "subcategory":"Supermarket",
            "type":"Retail Goods"
        }
    ],
    "sg:phone":"+61 2 9997 4777",
    "sg:postcode":"2103",
    "sg:province":"NSW",
    "sg:tags":[
        "grocery",
        "store"
    ],
    "wof:name":"Woolworths Ltd",
    "wof:placetype":"venue"
},
  "geometry": {"coordinates":[151.30128479000001,-33.6764907837],"type":"Point"}
}