{
  "type": "Feature",
  "properties": {
    "iso:country":"AU",
    "sg:address":"2 Nile Rd",
    "sg:city":"Evandale",
    "sg:classifiers":[
        {
            "category":"Travel",
            "subcategory":"Hotels & Motels",
            "type":"Entertainment"
        }
    ],
    "sg:phone":"+61 3 6391 8381",
    "sg:postcode":"7212",
    "sg:province":"TAS",
    "sg:tags":[
        "accommodation"
    ],
    "wof:name":"Prince of Wales Hotel",
    "wof:placetype":"venue"
},
  "geometry": {"coordinates":[147.247971,-41.571655],"type":"Point"}
}