{
  "type": "Feature",
  "properties": {
    "addr:full":"Unit 1 / 48 Dellamarta Rd Wangara WA 6065",
    "addr:postcode":"6065",
    "addr:street":"48 Dellamarta Rd",
    "iso:country":"AU",
    "sg:address":"Unit 1 / 48 Dellamarta Rd",
    "sg:city":"Wangara",
    "sg:classifiers":[
        {
            "category":"Retail",
            "subcategory":"Auto Repair",
            "type":"Services"
        }
    ],
    "sg:phone":"+61 8 9409 6711",
    "sg:postcode":"6065",
    "sg:province":"WA",
    "sg:tags":[
        "repairer",
        "motor",
        "engineer"
    ],
    "wof:name":"Topline Auto Gas & Mechanical Repairs",
    "wof:placetype":"venue"
},
  "geometry": {"coordinates":[115.811096191,-31.7855949402],"type":"Point"}
}