{
  "type": "Feature",
  "properties": {
    "iso:country":"AU",
    "sg:address":"184 Pitt St",
    "sg:city":"Merrylands",
    "sg:classifiers":[
        {
            "category":"Organizations",
            "subcategory":"Professional Association",
            "type":"Services"
        }
    ],
    "sg:phone":"+61 2 9637 9691",
    "sg:postcode":"2160",
    "sg:province":"NSW",
    "sg:tags":[
        "organisation",
        "business"
    ],
    "wof:name":"Curtis C, Georgas T, Kokkinakis J",
    "wof:placetype":"venue"
},
  "geometry": {"coordinates":[150.99244689899999,-33.833404541],"type":"Point"}
}