{
  "type": "Feature",
  "properties": {
    "addr:full":"Level 7 Latrobe St Melbourne VIC 3000",
    "addr:postcode":"3000",
    "addr:street":"Latrobe St",
    "iso:country":"AU",
    "sg:address":"Level 7 Latrobe St",
    "sg:city":"Melbourne",
    "sg:classifiers":[
        {
            "category":"Health Services",
            "subcategory":"Health Practitioner",
            "type":"Services"
        }
    ],
    "sg:phone":"+61 3 9642 1166",
    "sg:postcode":"3000",
    "sg:province":"VIC",
    "sg:tags":[
        "psychologist"
    ],
    "wof:name":"Dianne Perrett-Abrahams",
    "wof:placetype":"venue"
},
  "geometry": {"coordinates":[144.97038269000001,-37.8077964783],"type":"Point"}
}