{
  "type": "Feature",
  "properties": {
    "addr:full":"Level 1, 2072 Logan Rd Mt Gravatt QLD 4122",
    "addr:housenumber":"2072",
    "addr:postcode":"4122",
    "addr:street":"Logan Rd",
    "iso:country":"AU",
    "sg:address":"Level 1, 2072 Logan Rd",
    "sg:city":"Mt Gravatt",
    "sg:classifiers":[
        {
            "category":"Professional",
            "subcategory":"Employment Agencies",
            "type":"Services"
        }
    ],
    "sg:phone":"+61 7 3349 3355",
    "sg:postcode":"4122",
    "sg:province":"QLD",
    "sg:tags":[
        "hire",
        "labour",
        "contractor"
    ],
    "wof:name":"Excel Recruitment",
    "wof:placetype":"venue"
},
  "geometry": {"coordinates":[153.081756592,-27.5601463318],"type":"Point"}
}