{
  "type": "Feature",
  "properties": {
    "iso:country":"AU",
    "sg:address":"70 Bailey St",
    "sg:city":"Clunes",
    "sg:classifiers":[
        {
            "category":"Museum",
            "type":"Entertainment"
        }
    ],
    "sg:phone":"+61 3 5345 3896",
    "sg:postcode":"3370",
    "sg:province":"VIC",
    "wof:name":"Bottle Museum The",
    "wof:placetype":"venue"
},
  "geometry": {"coordinates":[143.787475586,-37.2952804565],"type":"Point"}
}