{
  "type": "Feature",
  "properties": {
    "addr:full":"5 Coral Drv Jerrabomberra NSW 2619",
    "addr:housenumber":"5",
    "addr:postcode":"2619",
    "addr:street":"Coral Drv",
    "iso:country":"AU",
    "sg:address":"5 Coral Drv",
    "sg:city":"Jerrabomberra",
    "sg:classifiers":[
        {
            "category":"Education",
            "subcategory":"Kindergarten",
            "type":"Public Place"
        }
    ],
    "sg:phone":"+61 2 6299 9962",
    "sg:postcode":"2619",
    "sg:province":"NSW",
    "sg:tags":[
        "pre-schools"
    ],
    "wof:name":"Leap Frog",
    "wof:placetype":"venue"
},
  "geometry": {"coordinates":[149.199020386,-35.3867607117],"type":"Point"}
}