{
  "type": "Feature",
  "properties": {
    "iso:country":"AU",
    "sg:address":"Devon Ave",
    "sg:city":"Keilor East",
    "sg:classifiers":[
        {
            "category":"Social Services",
            "subcategory":"Child Care",
            "type":"Services"
        }
    ],
    "sg:phone":"+61 3 9337 2551",
    "sg:postcode":"3033",
    "sg:province":"VIC",
    "sg:tags":[
        "support",
        "health"
    ],
    "wof:name":"Maternal & Child Health Centres",
    "wof:placetype":"venue"
},
  "geometry": {"coordinates":[144.87329099999999,-37.750107],"type":"Point"}
}