{
  "type": "Feature",
  "properties": {
    "addr:full":"393a Macquarie Rd Warners Bay NSW 2282",
    "addr:housenumber":"393a",
    "addr:postcode":"2282",
    "addr:street":"Macquarie Rd",
    "iso:country":"AU",
    "sg:address":"393a Macquarie Rd",
    "sg:city":"Warners Bay",
    "sg:classifiers":[
        {
            "category":"Communications",
            "subcategory":"Film & Video Production",
            "type":"Services"
        }
    ],
    "sg:phone":"+61 2 4956 9255",
    "sg:postcode":"2282",
    "sg:province":"NSW",
    "sg:tags":[
        "dvd",
        "library"
    ],
    "wof:name":"Blockbuster",
    "wof:placetype":"venue"
},
  "geometry": {"coordinates":[151.65266418499999,-32.9658546448],"type":"Point"}
}