{
  "type": "Feature",
  "properties": {
    "iso:country":"AU",
    "sg:address":"7 Quigley Crs",
    "sg:city":"Churchill",
    "sg:classifiers":[
        {
            "category":"Home & Garden",
            "subcategory":"Building Materials",
            "type":"Retail Goods"
        }
    ],
    "sg:phone":"+61 3 5122 1645",
    "sg:postcode":"3842",
    "sg:province":"VIC",
    "sg:tags":[
        "lawn",
        "cutting",
        "maintenance"
    ],
    "wof:name":"Bruce's 4 Seasons Lawn Mowing & Gardening Services",
    "wof:placetype":"venue"
},
  "geometry": {"coordinates":[146.42181396500001,-38.3153915405],"type":"Point"}
}