{
  "type": "Feature",
  "properties": {
    "addr:full":"402 Brunswick St Fitzroy VIC 3065",
    "addr:housenumber":"402",
    "addr:postcode":"3065",
    "addr:street":"Brunswick St",
    "iso:country":"AU",
    "sg:address":"402 Brunswick St",
    "sg:city":"Fitzroy",
    "sg:classifiers":[
        {
            "category":"Food & Beverages",
            "subcategory":"Bakery",
            "type":"Retail Goods"
        }
    ],
    "sg:phone":"+61 3 9417 3166",
    "sg:postcode":"3065",
    "sg:province":"VIC",
    "sg:tags":[
        "baker"
    ],
    "wof:name":"Pane Provinciale",
    "wof:placetype":"venue"
},
  "geometry": {"coordinates":[144.979171753,-37.7951049805],"type":"Point"}
}