{
  "type": "Feature",
  "properties": {
    "iso:country":"AU",
    "sg:address":"1- 3 Alexandra Ave",
    "sg:city":"Hoppers Crossing",
    "sg:classifiers":[
        {
            "category":"Travel",
            "subcategory":"Travel Agent",
            "type":"Entertainment"
        }
    ],
    "sg:phone":"+61 3 8742 7431",
    "sg:postcode":"3029",
    "sg:province":"VIC",
    "sg:tags":[
        "consultant"
    ],
    "wof:name":"Anaysah Travel Centre",
    "wof:placetype":"venue"
},
  "geometry": {"coordinates":[144.706528,-37.851357],"type":"Point"}
}