{
  "type": "Feature",
  "properties": {
    "iso:country":"AU",
    "sg:address":"Lot 5 Neil Rd",
    "sg:city":"Mooloolah",
    "sg:classifiers":[
        {
            "category":"Building & Trades",
            "subcategory":"Construction",
            "type":"Services"
        }
    ],
    "sg:phone":"+61 408 151 161",
    "sg:postcode":"4553",
    "sg:province":"QLD",
    "sg:tags":[
        "fencing",
        "contractor"
    ],
    "wof:name":"Clearwater Glass Fencing and Balustrades",
    "wof:placetype":"venue"
},
  "geometry": {"coordinates":[152.96134900000001,-26.764187],"type":"Point"}
}