{
  "type": "Feature",
  "properties": {
    "addr:full":"15 Faulkner Ave Belmont WA 6984",
    "addr:housenumber":"15",
    "addr:postcode":"6984",
    "addr:street":"Faulkner Ave",
    "iso:country":"AU",
    "sg:address":"15 Faulkner Ave",
    "sg:city":"Belmont",
    "sg:classifiers":[
        {
            "category":"Retail",
            "subcategory":"Storage",
            "type":"Services"
        }
    ],
    "sg:phone":"+61 8 9277 4565",
    "sg:postcode":"6984",
    "sg:province":"WA",
    "wof:name":"Car Storage",
    "wof:placetype":"venue"
},
  "geometry": {"coordinates":[115.924538,-31.954494],"type":"Point"}
}