{
  "type": "Feature",
  "properties": {
    "addr:full":"116 Denmark St Kew VIC 3101",
    "addr:housenumber":"116",
    "addr:postcode":"3101",
    "addr:street":"Denmark St",
    "iso:country":"AU",
    "sg:address":"116 Denmark St",
    "sg:city":"Kew",
    "sg:classifiers":[
        {
            "category":"Autos & Motor Vehicles",
            "subcategory":"Automobile Sales",
            "type":"Retail Goods"
        }
    ],
    "sg:phone":"+61 3 9853 6669",
    "sg:postcode":"3101",
    "sg:province":"VIC",
    "sg:tags":[
        "car",
        "new"
    ],
    "wof:name":"3 Point",
    "wof:placetype":"venue"
},
  "geometry": {"coordinates":[145.02906799300001,-37.8079452515],"type":"Point"}
}