{
  "type": "Feature",
  "properties": {
    "addr:full":"22 Stewart Rd Ashgrove QLD 4060",
    "addr:housenumber":"22",
    "addr:postcode":"4060",
    "addr:street":"Stewart Rd",
    "iso:country":"AU",
    "sg:address":"22 Stewart Rd",
    "sg:city":"Ashgrove",
    "sg:classifiers":[
        {
            "category":"Health Services",
            "subcategory":"Health Practitioner",
            "type":"Services"
        }
    ],
    "sg:phone":"+61 7 3366 8977",
    "sg:postcode":"4060",
    "sg:province":"QLD",
    "sg:tags":[
        "alternative"
    ],
    "wof:name":"Brennan Paul",
    "wof:placetype":"venue"
},
  "geometry": {"coordinates":[152.991455078,-27.4446182251],"type":"Point"}
}