{
  "type": "Feature",
  "properties": {
    "addr:full":"8 Greeves St St Kilda VIC 3182",
    "addr:housenumber":"8",
    "addr:postcode":"3182",
    "addr:street":"Greeves St",
    "iso:country":"AU",
    "sg:address":"8 Greeves St St",
    "sg:city":"Kilda",
    "sg:classifiers":[
        {
            "category":"Shopping",
            "subcategory":"Stationery & Office Supplies",
            "type":"Retail Goods"
        }
    ],
    "sg:phone":"+61 3 9534 9031",
    "sg:postcode":"3182",
    "sg:province":"VIC",
    "sg:tags":[
        "packaging",
        "material"
    ],
    "wof:name":"Paramount Paper Merchants",
    "wof:placetype":"venue"
},
  "geometry": {"coordinates":[144.98362731899999,-37.8646087646],"type":"Point"}
}