{
  "type": "Feature",
  "properties": {
    "iso:country":"AU",
    "sg:address":"13 Vernon St",
    "sg:city":"Coffs Harbour",
    "sg:classifiers":[
        {
            "category":"Personal",
            "subcategory":"Beauty Salon",
            "type":"Services"
        }
    ],
    "sg:phone":"+61 2 6652 9753",
    "sg:postcode":"2450",
    "sg:province":"NSW",
    "wof:name":"Jan Youngs Beauty Gallerie",
    "wof:placetype":"venue"
},
  "geometry": {"coordinates":[153.117432,-30.297401],"type":"Point"}
}