{
  "type": "Feature",
  "properties": {
    "addr:full":"13 Vernon St Coffs Harbour NSW 2450",
    "addr:housenumber":"13",
    "addr:postcode":"2450",
    "addr:street":"Vernon St",
    "iso:country":"AU",
    "sg:address":"13 Vernon St",
    "sg:city":"Coffs Harbour",
    "sg:classifiers":[
        {
            "category":"Personal",
            "subcategory":"Beauty Salon",
            "type":"Services"
        }
    ],
    "sg:phone":"+61 2 6652 9753",
    "sg:postcode":"2450",
    "sg:province":"NSW",
    "wof:name":"Jan Youngs Beauty Gallerie",
    "wof:placetype":"venue"
},
  "geometry": {"coordinates":[153.11743200000001,-30.297401],"type":"Point"}
}