{
  "type": "Feature",
  "properties": {
    "iso:country":"AU",
    "sg:address":"Carnamah Rd",
    "sg:city":"Perenjori",
    "sg:classifiers":[
        {
            "category":"Farming",
            "subcategory":"Farm",
            "type":"Manufacturing & Wholesale Goods"
        }
    ],
    "sg:phone":"+61 8 9973 1087",
    "sg:postcode":"6620",
    "sg:province":"WA",
    "sg:tags":[
        "farmer"
    ],
    "wof:name":"James H G & J",
    "wof:placetype":"venue"
},
  "geometry": {"coordinates":[116.28842926,-29.443359375],"type":"Point"}
}