{
  "type": "Feature",
  "properties": {
    "iso:country":"AU",
    "sg:address":"12 Kawarren St",
    "sg:city":"Balwyn North",
    "sg:classifiers":[
        {
            "category":"Professional",
            "subcategory":"Secretarial Services",
            "type":"Services"
        }
    ],
    "sg:phone":"+61 3 9816 3887",
    "sg:postcode":"3104",
    "sg:province":"VIC",
    "sg:tags":[
        "typing"
    ],
    "wof:name":"Boroondara Secretarial Service",
    "wof:placetype":"venue"
},
  "geometry": {"coordinates":[145.09176635700001,-37.7857704163],"type":"Point"}
}