{
  "type": "Feature",
  "properties": {
    "iso:country":"AU",
    "sg:address":"77 Maitland Rd",
    "sg:city":"Mayfield",
    "sg:classifiers":[
        {
            "category":"Autos & Motor Vehicles",
            "subcategory":"Automobile Sales",
            "type":"Retail Goods"
        }
    ],
    "sg:phone":"+61 2 4967 1500",
    "sg:postcode":"2304",
    "sg:province":"NSW",
    "sg:tags":[
        "car",
        "used"
    ],
    "wof:name":"Mitsubishi Newcastle",
    "wof:placetype":"venue"
},
  "geometry": {"coordinates":[151.74168395999999,-32.9009284973],"type":"Point"}
}