{
  "type": "Feature",
  "properties": {
    "addr:full":"Cnr Okehampton Rd & Currie St Warnbro WA 6169",
    "addr:postcode":"6169",
    "addr:street":"Cnr Okehampton Rd & Currie St",
    "iso:country":"AU",
    "sg:address":"Cnr Okehampton Rd & Currie St",
    "sg:city":"Warnbro",
    "sg:classifiers":[
        {
            "category":"Sports & Exercise",
            "subcategory":"Gym",
            "type":"Entertainment"
        }
    ],
    "sg:phone":"+61 8 9593 6102",
    "sg:postcode":"6169",
    "sg:province":"WA",
    "sg:tags":[
        "health",
        "fitness"
    ],
    "wof:name":"Warnbro Community YMCA",
    "wof:placetype":"venue"
},
  "geometry": {"coordinates":[115.75861399999999,-32.331348],"type":"Point"}
}