{
  "type": "Feature",
  "properties": {
    "iso:country":"AU",
    "sg:address":"Lvl 1/ 86 Vulture St",
    "sg:city":"West End",
    "sg:classifiers":[
        {
            "category":"Professional",
            "subcategory":"Business Services",
            "type":"Services"
        }
    ],
    "sg:phone":"+61 7 3844 3029",
    "sg:postcode":"4101",
    "sg:province":"QLD",
    "sg:tags":[
        "drafting"
    ],
    "wof:name":"Plan B Drafting & Design",
    "wof:placetype":"venue"
},
  "geometry": {"coordinates":[153.012176514,-27.4808444977],"type":"Point"}
}