{
  "type": "Feature",
  "properties": {
    "iso:country":"AU",
    "sg:address":"288 Queen St",
    "sg:city":"Campbelltown",
    "sg:classifiers":[
        {
            "category":"Government",
            "subcategory":"Court House",
            "type":"Public Place"
        }
    ],
    "sg:phone":"+61 2 4627 2792",
    "sg:postcode":"2560",
    "sg:province":"NSW",
    "sg:tags":[
        "personal",
        "marriage",
        "family",
        "counselling"
    ],
    "wof:name":"Benevolent Society",
    "wof:placetype":"venue"
},
  "geometry": {"coordinates":[150.81192016599999,-34.069519043],"type":"Point"}
}