{
  "type": "Feature",
  "properties": {
    "addr:full":"19 Dellamarta Rd Wangara WA 6065",
    "addr:housenumber":"19",
    "addr:postcode":"6065",
    "addr:street":"Dellamarta Rd",
    "iso:country":"AU",
    "sg:address":"19 Dellamarta Rd",
    "sg:city":"Wangara",
    "sg:classifiers":[
        {
            "category":"Shopping",
            "subcategory":"Stationery & Office Supplies",
            "type":"Retail Goods"
        }
    ],
    "sg:phone":"+61 8 9409 6166",
    "sg:postcode":"6065",
    "sg:province":"WA",
    "sg:tags":[
        "packaging",
        "material"
    ],
    "wof:name":"Taldara Industries Pty Ltd",
    "wof:placetype":"venue"
},
  "geometry": {"coordinates":[115.817230225,-31.788772583],"type":"Point"}
}