{
  "type": "Feature",
  "properties": {
    "iso:country":"AU",
    "sg:address":"Lackey Rd",
    "sg:city":"Moss Vale",
    "sg:classifiers":[
        {
            "category":"Commercial Area",
            "type":"Public Place"
        }
    ],
    "sg:phone":"+61 2 4868 2568",
    "sg:postcode":"2577",
    "sg:province":"NSW",
    "sg:tags":[
        "heavy",
        "carrier"
    ],
    "wof:name":"Camtrac",
    "wof:placetype":"venue"
},
  "geometry": {"coordinates":[150.370803833,-34.5486869812],"type":"Point"}
}