{
  "type": "Feature",
  "properties": {
    "iso:country":"AU",
    "sg:address":"232 Mary St",
    "sg:city":"Wanneroo",
    "sg:classifiers":[
        {
            "category":"Farming",
            "subcategory":"Nursery",
            "type":"Manufacturing & Wholesale Goods"
        }
    ],
    "sg:phone":"+61 8 9306 1432",
    "sg:postcode":"6065",
    "sg:province":"WA",
    "wof:name":"Boogaard's Nurseries",
    "wof:placetype":"venue"
},
  "geometry": {"coordinates":[115.837173462,-31.7854156494],"type":"Point"}
}