{
  "type": "Feature",
  "properties": {
    "iso:country":"AU",
    "sg:address":"U 1, 9 Sundercombe St",
    "sg:city":"Osborne Park",
    "sg:classifiers":[
        {
            "category":"Manufacturing",
            "subcategory":"Furniture",
            "type":"Manufacturing & Wholesale Goods"
        }
    ],
    "sg:phone":"+61 8 9445 2677",
    "sg:postcode":"6017",
    "sg:province":"WA",
    "sg:tags":[
        "builder",
        "designer",
        "custom"
    ],
    "wof:name":"Western Cabinets",
    "wof:placetype":"venue"
},
  "geometry": {"coordinates":[115.81165313699999,-31.904592514],"type":"Point"}
}