{
  "type": "Feature",
  "properties": {
    "iso:country":"AU",
    "sg:address":"13 Pierce St",
    "sg:city":"Niagara Park",
    "sg:classifiers":[
        {
            "category":"Education",
            "subcategory":"Music School",
            "type":"Public Place"
        }
    ],
    "sg:phone":"+61 2 4329 4424",
    "sg:postcode":"2250",
    "sg:province":"NSW",
    "sg:tags":[
        "singing",
        "teacher"
    ],
    "wof:name":"Gail Beaman",
    "wof:placetype":"venue"
},
  "geometry": {"coordinates":[151.35661315900001,-33.3875236511],"type":"Point"}
}