{
  "type": "Feature",
  "properties": {
    "addr:full":"27 Mangrove La Taren Point NSW 2229",
    "addr:housenumber":"27",
    "addr:postcode":"2229",
    "addr:street":"Mangrove La",
    "iso:country":"AU",
    "sg:address":"27 Mangrove La",
    "sg:city":"Taren Point",
    "sg:classifiers":[
        {
            "category":"Industrial Area",
            "type":"Public Place"
        }
    ],
    "sg:phone":"+61 2 9526 0888",
    "sg:postcode":"2229",
    "sg:province":"NSW",
    "sg:tags":[
        "protective",
        "clothing"
    ],
    "wof:name":"Hi Craft Workwear",
    "wof:placetype":"venue"
},
  "geometry": {"coordinates":[151.13180542000001,-34.0243911743],"type":"Point"}
}