{
  "type": "Feature",
  "properties": {
    "iso:country":"AU",
    "sg:address":"Shop 1 West Street La",
    "sg:city":"Mt Isa",
    "sg:classifiers":[
        {
            "category":"Retail",
            "subcategory":"Repair Shop",
            "type":"Services"
        }
    ],
    "sg:phone":"+61 7 4743 2730",
    "sg:postcode":"4825",
    "sg:province":"QLD",
    "sg:tags":[
        "machine",
        "sewing"
    ],
    "wof:name":"Sewing Machine Centre",
    "wof:placetype":"venue"
},
  "geometry": {"coordinates":[139.490265,-20.727463],"type":"Point"}
}