{
  "type": "Feature",
  "properties": {
    "addr:full":"Lot 89 Meadow La Dardanup WA 6236",
    "addr:postcode":"6236",
    "addr:street":"Meadow La Dardanup",
    "iso:country":"AU",
    "sg:address":"Lot 89 Meadow La",
    "sg:city":"Dardanup",
    "sg:classifiers":[
        {
            "category":"Building & Trades",
            "subcategory":"Construction",
            "type":"Services"
        }
    ],
    "sg:phone":"+61 8 9728 0018",
    "sg:postcode":"6236",
    "sg:province":"WA",
    "sg:tags":[
        "fencing",
        "contractor"
    ],
    "wof:name":"G & G Prestige Paving",
    "wof:placetype":"venue"
},
  "geometry": {"coordinates":[115.716202,-33.398109],"type":"Point"}
}