{
  "type": "Feature",
  "properties": {
    "iso:country":"AU",
    "sg:address":"Studio 1/ 149 Chapel St",
    "sg:city":"St Kilda",
    "sg:classifiers":[
        {
            "category":"Professional",
            "subcategory":"Art Services",
            "type":"Services"
        }
    ],
    "sg:phone":"+61 3 9537 0608",
    "sg:postcode":"3182",
    "sg:province":"VIC",
    "sg:tags":[
        "graphic",
        "designer"
    ],
    "wof:name":"Hatch Creative Pty Ltd",
    "wof:placetype":"venue"
},
  "geometry": {"coordinates":[144.99026489299999,-37.867931366],"type":"Point"}
}