{
  "type": "Feature",
  "properties": {
    "addr:full":"48 Bell St Speers Point NSW 2284",
    "addr:housenumber":"48",
    "addr:postcode":"2284",
    "addr:street":"Bell St",
    "iso:country":"AU",
    "sg:address":"48 Bell St",
    "sg:city":"Speers Point",
    "sg:classifiers":[
        {
            "category":"Insurance",
            "subcategory":"Insurance Agent",
            "type":"Services"
        }
    ],
    "sg:phone":"+61 2 4950 8399",
    "sg:postcode":"2284",
    "sg:province":"NSW",
    "wof:name":"Elsleys Insurances Pty Ltd",
    "wof:placetype":"venue"
},
  "geometry": {"coordinates":[151.620483398,-32.9600067139],"type":"Point"}
}