{
  "type": "Feature",
  "properties": {
    "addr:full":"320 Walter Rd Morley WA 6062",
    "addr:housenumber":"320",
    "addr:postcode":"6062",
    "addr:street":"Walter Rd",
    "iso:country":"AU",
    "sg:address":"320 Walter Rd",
    "sg:city":"Morley",
    "sg:classifiers":[
        {
            "category":"Health Services",
            "subcategory":"Health Practitioner",
            "type":"Services"
        }
    ],
    "sg:phone":"+61 8 9276 8995",
    "sg:postcode":"6062",
    "sg:province":"WA",
    "sg:tags":[
        "psychologist"
    ],
    "wof:name":"Solomon Julia Dr",
    "wof:placetype":"venue"
},
  "geometry": {"coordinates":[115.894561768,-31.8756504059],"type":"Point"}
}