{
  "type": "Feature",
  "properties": {
    "addr:full":"266 Cleveland St Surry Hills NSW 2010",
    "addr:housenumber":"266",
    "addr:postcode":"2010",
    "addr:street":"Cleveland St",
    "iso:country":"AU",
    "sg:address":"266 Cleveland St",
    "sg:city":"Surry Hills",
    "sg:classifiers":[
        {
            "category":"Banks & Credit Unions",
            "subcategory":"Investment Brokerage",
            "type":"Services"
        }
    ],
    "sg:phone":"+61 2 9698 3175",
    "sg:postcode":"2010",
    "sg:province":"NSW",
    "wof:name":"Unigar Investments Pty Ltd",
    "wof:placetype":"venue"
},
  "geometry": {"coordinates":[151.20724487300001,-33.8899536133],"type":"Point"}
}