{
  "type": "Feature",
  "properties": {
    "addr:full":"324 High St Kew VIC 3101",
    "addr:housenumber":"324",
    "addr:postcode":"3101",
    "addr:street":"High St",
    "iso:country":"AU",
    "sg:address":"324 High St",
    "sg:city":"Kew",
    "sg:classifiers":[
        {
            "category":"Shopping",
            "subcategory":"Gifts & Souvenirs",
            "type":"Retail Goods"
        }
    ],
    "sg:phone":"+61 3 9853 7496",
    "sg:postcode":"3101",
    "sg:province":"VIC",
    "sg:tags":[
        "print",
        "poster",
        "pictures"
    ],
    "wof:name":"Bevelled Edge The",
    "wof:placetype":"venue"
},
  "geometry": {"coordinates":[145.036087036,-37.8050079346],"type":"Point"}
}