{
  "type": "Feature",
  "properties": {
    "addr:full":"439 Waterford Rd Ellen Grove QLD 4078",
    "addr:housenumber":"439",
    "addr:postcode":"4078",
    "addr:street":"Waterford Rd",
    "iso:country":"AU",
    "sg:address":"439 Waterford Rd",
    "sg:city":"Ellen Grove",
    "sg:classifiers":[
        {
            "category":"Retail",
            "subcategory":"Veterinary Services",
            "type":"Services"
        }
    ],
    "sg:phone":"+61 7 3271 1155",
    "sg:postcode":"4078",
    "sg:province":"QLD",
    "sg:tags":[
        "surgeon"
    ],
    "wof:name":"Dogtainers",
    "wof:placetype":"venue"
},
  "geometry": {"coordinates":[152.946975708,-27.6121177673],"type":"Point"}
}