{
  "type": "Feature",
  "properties": {
    "addr:full":"51 Garland Rd Bundanoon NSW 2578",
    "addr:housenumber":"51",
    "addr:postcode":"2578",
    "addr:street":"Garland Rd",
    "iso:country":"AU",
    "sg:address":"51 Garland Rd",
    "sg:city":"Bundanoon",
    "sg:classifiers":[
        {
            "category":"Building & Trades",
            "subcategory":"Pest Control",
            "type":"Services"
        }
    ],
    "sg:phone":"+61 2 4883 6472",
    "sg:postcode":"2578",
    "sg:province":"NSW",
    "sg:tags":[
        "breastfeeding",
        "support"
    ],
    "wof:name":"Australian Breastfeeding Association",
    "wof:placetype":"venue"
},
  "geometry": {"coordinates":[150.31422424300001,-34.6623420715],"type":"Point"}
}