{
  "type": "Feature",
  "properties": {
    "addr:full":"Sh 8A Harbourtown Shopng Cntr Cnr Gold Coast Hwy & Biggera Waters QLD 4216",
    "addr:postcode":"4216",
    "addr:street":"Sh 8A Harbourtown Shopng Cntr Cnr Gold Coast Hwy &",
    "iso:country":"AU",
    "sg:address":"Sh 8A Harbourtown Shopng Cntr Cnr Gold Coast Hwy &",
    "sg:city":"Biggera Waters",
    "sg:classifiers":[
        {
            "category":"Shopping",
            "subcategory":"Mobile Phones",
            "type":"Retail Goods"
        }
    ],
    "sg:phone":"+61 7 5537 6994",
    "sg:postcode":"4216",
    "sg:province":"QLD",
    "sg:tags":[
        "telephone",
        "accessory"
    ],
    "wof:name":"Coastline Mobile Phones",
    "wof:placetype":"venue"
},
  "geometry": {"coordinates":[153.35940551799999,-27.9258289337],"type":"Point"}
}