{
  "type": "Feature",
  "properties": {
    "addr:full":"10 Ferguson St Underwood QLD 4119",
    "addr:housenumber":"10",
    "addr:postcode":"4119",
    "addr:street":"Ferguson St",
    "iso:country":"AU",
    "sg:address":"10 Ferguson St",
    "sg:city":"Underwood",
    "sg:classifiers":[
        {
            "category":"Arts & Performance",
            "subcategory":"Music",
            "type":"Entertainment"
        }
    ],
    "sg:phone":"+61 7 3841 3067",
    "sg:postcode":"4119",
    "sg:province":"QLD",
    "sg:tags":[
        "hi-fi",
        "equipment"
    ],
    "wof:name":"Pioneer Electronics Australia Pty Ltd",
    "wof:placetype":"venue"
},
  "geometry": {"coordinates":[153.11442565900001,-27.6112594604],"type":"Point"}
}