{
  "type": "Feature",
  "properties": {
    "iso:country":"AU",
    "sg:address":"Shop Upper Hay 9, Carillon City Arcade, Hay St",
    "sg:city":"Perth",
    "sg:classifiers":[
        {
            "category":"Wholesale",
            "subcategory":"Medical Equipment & Supplies",
            "type":"Manufacturing & Wholesale Goods"
        }
    ],
    "sg:phone":"+61 8 9321 4999",
    "sg:postcode":"6000",
    "sg:province":"WA",
    "sg:tags":[
        "aids",
        "hearing"
    ],
    "wof:name":"Western Hearing Services",
    "wof:placetype":"venue"
},
  "geometry": {"coordinates":[115.852546692,-31.9546794891],"type":"Point"}
}