{
  "type": "Feature",
  "properties": {
    "addr:full":"16 Erskine Rd Taren Point NSW 2229",
    "addr:housenumber":"16",
    "addr:postcode":"2229",
    "addr:street":"Erskine Rd",
    "iso:country":"AU",
    "sg:address":"16 Erskine Rd",
    "sg:city":"Taren Point",
    "sg:classifiers":[
        {
            "category":"Mining & Drilling",
            "type":"Manufacturing & Wholesale Goods"
        }
    ],
    "sg:phone":"+61 2 9526 2044",
    "sg:postcode":"2229",
    "sg:province":"NSW",
    "sg:tags":[
        "equipment",
        "quarrying",
        "supply"
    ],
    "wof:name":"Australian & Overseas Alloys Pty Ltd",
    "wof:placetype":"venue"
},
  "geometry": {"coordinates":[151.12220764200001,-34.0256919861],"type":"Point"}
}