{
  "type": "Feature",
  "properties": {
    "addr:full":"Cunninyek Rd Mallan NSW 2739",
    "addr:postcode":"2739",
    "addr:street":"Cunninyek Rd",
    "iso:country":"AU",
    "sg:address":"Cunninyek Rd",
    "sg:city":"Mallan",
    "sg:classifiers":[
        {
            "category":"Education",
            "subcategory":"School",
            "type":"Public Place"
        }
    ],
    "sg:phone":"+61 3 5034 0539",
    "sg:postcode":"2739",
    "sg:province":"NSW",
    "sg:tags":[
        "state",
        "except",
        "nsw"
    ],
    "wof:name":"Mallan Primary School",
    "wof:placetype":"venue"
},
  "geometry": {"coordinates":[142.36715699999999,-33.97279],"type":"Point"}
}