{
  "type": "Feature",
  "properties": {
    "addr:full":"136 Mollison St Bendigo VIC 3550",
    "addr:housenumber":"136",
    "addr:postcode":"3550",
    "addr:street":"Mollison St",
    "iso:country":"AU",
    "sg:address":"136 Mollison St",
    "sg:city":"Bendigo",
    "sg:classifiers":[
        {
            "category":"Fast Food",
            "type":"Food & Drink"
        }
    ],
    "sg:phone":"+61 3 5444 4450",
    "sg:postcode":"3550",
    "sg:province":"VIC",
    "sg:tags":[
        "away",
        "take"
    ],
    "wof:name":"Piyawat Thai Restaurant",
    "wof:placetype":"venue"
},
  "geometry": {"coordinates":[144.283203125,-36.7629623413],"type":"Point"}
}