{
  "type": "Feature",
  "properties": {
    "addr:full":"Suite 8/ 555 Main St Mordialloc VIC 3195",
    "addr:housenumber":"/ 555",
    "addr:postcode":"3195",
    "addr:street":"Main St",
    "iso:country":"AU",
    "sg:address":"Suite 8/ 555 Main St",
    "sg:city":"Mordialloc",
    "sg:classifiers":[
        {
            "category":"Building & Trades",
            "subcategory":"Landscaping Services",
            "type":"Services"
        }
    ],
    "sg:phone":"+61 3 9587 5757",
    "sg:postcode":"3195",
    "sg:province":"VIC",
    "sg:tags":[
        "stump",
        "tree",
        "felling",
        "removal"
    ],
    "wof:name":"Total Tree Care",
    "wof:placetype":"venue"
},
  "geometry": {"coordinates":[145.08807373100001,-38.0080413818],"type":"Point"}
}