{
  "type": "Feature",
  "properties": {
    "addr:full":"1 Martin St Seaford VIC 3198",
    "addr:housenumber":"1",
    "addr:postcode":"3198",
    "addr:street":"Martin St",
    "iso:country":"AU",
    "sg:address":"1 Martin St",
    "sg:city":"Seaford",
    "sg:classifiers":[
        {
            "category":"Building & Trades",
            "subcategory":"Plumbing",
            "type":"Services"
        }
    ],
    "sg:phone":"+61 3 9786 5555",
    "sg:postcode":"3198",
    "sg:province":"VIC",
    "sg:tags":[
        "plumber",
        "gasfitters"
    ],
    "wof:name":"Flack Enterprises (Plumbing)",
    "wof:placetype":"venue"
},
  "geometry": {"coordinates":[145.13282775900001,-38.111743927],"type":"Point"}
}