{
  "type": "Feature",
  "properties": {
    "addr:full":"26-34 Dennis Rd Springwood QLD 4127",
    "addr:housenumber":"26-34",
    "addr:postcode":"4127",
    "addr:street":"Dennis Rd",
    "iso:country":"AU",
    "sg:address":"26-34 Dennis Rd",
    "sg:city":"Springwood",
    "sg:classifiers":[
        {
            "category":"Education",
            "subcategory":"School",
            "type":"Public Place"
        }
    ],
    "sg:phone":"+61 7 3290 9326",
    "sg:postcode":"4127",
    "sg:province":"QLD",
    "sg:tags":[
        "state",
        "except",
        "nsw"
    ],
    "wof:name":"Springwood Central Preschool",
    "wof:placetype":"venue"
},
  "geometry": {"coordinates":[153.13067626899999,-27.6186256409],"type":"Point"}
}