{
  "type": "Feature",
  "properties": {
    "iso:country":"AU",
    "sg:address":"128 Lydiard St",
    "sg:city":"Ballarat",
    "sg:classifiers":[
        {
            "category":"Travel",
            "subcategory":"Hotels & Motels",
            "type":"Entertainment"
        }
    ],
    "sg:phone":"+61 3 5331 3461",
    "sg:postcode":"3350",
    "sg:province":"VIC",
    "wof:name":"Reid's Guest House",
    "wof:placetype":"venue"
},
  "geometry": {"coordinates":[143.858475,-37.558952],"type":"Point"}
}