{
  "type": "Feature",
  "properties": {
    "addr:full":"PO Box 2523 Cheltenham VIC 3192",
    "addr:postcode":"3192",
    "iso:country":"AU",
    "sg:address":"PO Box 2523",
    "sg:city":"Cheltenham",
    "sg:classifiers":[
        {
            "category":"Professional",
            "subcategory":"Business Services",
            "type":"Services"
        }
    ],
    "sg:phone":"+61 3 9585 7955",
    "sg:postcode":"3192",
    "sg:province":"VIC",
    "sg:tags":[
        "management",
        "event"
    ],
    "wof:name":"Crest Management Pty Ltd",
    "wof:placetype":"venue"
},
  "geometry": {"coordinates":[145.073852539,-37.9676208496],"type":"Point"}
}