{
  "type": "Feature",
  "properties": {
    "addr:full":"251 Buckland Rd Nundah QLD 4012",
    "addr:housenumber":"251",
    "addr:postcode":"4012",
    "addr:street":"Buckland Rd",
    "iso:country":"AU",
    "sg:address":"251 Buckland Rd",
    "sg:city":"Nundah",
    "sg:classifiers":[
        {
            "category":"Building & Trades",
            "subcategory":"Construction",
            "type":"Services"
        }
    ],
    "sg:phone":"+61 407 164 015",
    "sg:postcode":"4012",
    "sg:province":"QLD",
    "sg:tags":[
        "concrete",
        "contractor"
    ],
    "wof:name":"S.R.C. Concreting",
    "wof:placetype":"venue"
},
  "geometry": {"coordinates":[153.050415039,-27.4018764496],"type":"Point"}
}