{
  "type": "Feature",
  "properties": {
    "addr:full":"506 Mulgrave Rd Cairns QLD 4870",
    "addr:housenumber":"506",
    "addr:postcode":"4870",
    "addr:street":"Mulgrave Rd",
    "iso:country":"AU",
    "sg:address":"506 Mulgrave Rd",
    "sg:city":"Cairns",
    "sg:classifiers":[
        {
            "category":"Banks & Credit Unions",
            "subcategory":"Financial Services",
            "type":"Services"
        }
    ],
    "sg:phone":"+61 7 4033 7333",
    "sg:postcode":"4870",
    "sg:province":"QLD",
    "sg:tags":[
        "loan",
        "finance",
        "mortgage"
    ],
    "wof:name":"Wizard Home Loans",
    "wof:placetype":"venue"
},
  "geometry": {"coordinates":[145.738815308,-16.942615509],"type":"Point"}
}