{
  "type": "Feature",
  "properties": {
    "addr:full":"74 Oxford St Darlinghurst NSW 2010",
    "addr:housenumber":"74",
    "addr:postcode":"2010",
    "addr:street":"Oxford St",
    "iso:country":"AU",
    "sg:address":"74 Oxford St",
    "sg:city":"Darlinghurst",
    "sg:classifiers":[
        {
            "category":"Shopping",
            "subcategory":"Clothing, Apparel, & Fashions",
            "type":"Retail Goods"
        }
    ],
    "sg:phone":"+61 2 9361 6182",
    "sg:postcode":"2010",
    "sg:province":"NSW",
    "sg:tags":[
        "menswear"
    ],
    "wof:name":"Axel",
    "wof:placetype":"venue"
},
  "geometry": {"coordinates":[151.21505737300001,-33.8788757324],"type":"Point"}
}