{
  "type": "Feature",
  "properties": {
    "addr:full":"7 Green St Doveton VIC 3177",
    "addr:housenumber":"7",
    "addr:postcode":"3177",
    "addr:street":"Green St",
    "iso:country":"AU",
    "sg:address":"7 Green St",
    "sg:city":"Doveton",
    "sg:classifiers":[
        {
            "category":"Utilities",
            "subcategory":"Electric",
            "type":"Services"
        }
    ],
    "sg:phone":"+61 3 9794 8031",
    "sg:postcode":"3177",
    "sg:province":"VIC",
    "sg:tags":[
        "electrical",
        "contractor"
    ],
    "wof:name":"A & J Food Machines Services",
    "wof:placetype":"venue"
},
  "geometry": {"coordinates":[145.23382568400001,-37.9987258911],"type":"Point"}
}