{
  "type": "Feature",
  "properties": {
    "addr:full":"480 Payneham Rd Glynde SA 5070",
    "addr:housenumber":"480",
    "addr:postcode":"5070",
    "addr:street":"Payneham Rd",
    "iso:country":"AU",
    "sg:address":"480 Payneham Rd",
    "sg:city":"Glynde",
    "sg:classifiers":[
        {
            "category":"Shopping",
            "subcategory":"Shoes",
            "type":"Retail Goods"
        }
    ],
    "sg:phone":"+61 8 8337 4025",
    "sg:postcode":"5070",
    "sg:province":"SA",
    "sg:tags":[
        "footwear"
    ],
    "wof:name":"Lisa's The Shoe Shop Glynde",
    "wof:placetype":"venue"
},
  "geometry": {"coordinates":[138.65512085,-34.8901290894],"type":"Point"}
}