{
  "type": "Feature",
  "properties": {
    "addr:full":"185 Melbourne St North Adelaide SA 5006",
    "addr:housenumber":"185",
    "addr:postcode":"5006",
    "addr:street":"Melbourne St",
    "iso:country":"AU",
    "sg:address":"185 Melbourne St",
    "sg:city":"North Adelaide",
    "sg:classifiers":[
        {
            "category":"Professional",
            "subcategory":"Management & Consulting",
            "type":"Services"
        }
    ],
    "sg:phone":"+61 8 8130 4100",
    "sg:postcode":"5006",
    "sg:province":"SA",
    "sg:tags":[
        "consultant"
    ],
    "wof:name":"Davidson Trahaire",
    "wof:placetype":"venue"
},
  "geometry": {"coordinates":[138.60499572800001,-34.9085044861],"type":"Point"}
}