{
  "type": "Feature",
  "properties": {
    "addr:full":"1st Floor, 4- 8 Angas St Kent Town SA 5067",
    "addr:housenumber":"8",
    "addr:postcode":"5067",
    "addr:street":"Angas St",
    "iso:country":"AU",
    "sg:address":"1st Floor, 4- 8 Angas St",
    "sg:city":"Kent Town",
    "sg:classifiers":[
        {
            "category":"Professional",
            "subcategory":"Computer Services",
            "type":"Services"
        }
    ],
    "sg:phone":"+61 8 8139 1111",
    "sg:postcode":"5067",
    "sg:province":"SA",
    "sg:tags":[
        "consultant",
        "system"
    ],
    "wof:name":"Edwards Marshall IT Solutions Pty Ltd",
    "wof:placetype":"venue"
},
  "geometry": {"coordinates":[138.62252807600001,-34.925819397],"type":"Point"}
}