{
  "type": "Feature",
  "properties": {
    "iso:country":"AU",
    "sg:address":"Goodchap St",
    "sg:city":"Tewantin",
    "sg:classifiers":[
        {
            "category":"Building & Trades",
            "subcategory":"Construction",
            "type":"Services"
        }
    ],
    "sg:phone":"+61 7 5442 4011",
    "sg:postcode":"4565",
    "sg:province":"QLD",
    "sg:tags":[
        "sun",
        "product",
        "protection"
    ],
    "wof:name":"Pacific Dreaming",
    "wof:placetype":"venue"
},
  "geometry": {"coordinates":[153.043426514,-26.3986968994],"type":"Point"}
}