{
  "type": "Feature",
  "properties": {
    "addr:full":"Shop 4 Catherine St Strathalbyn SA 5255",
    "addr:housenumber":"shop 4",
    "addr:postcode":"5255",
    "addr:street":"Catherine St",
    "iso:country":"AU",
    "sg:address":"Shop 4 Catherine St",
    "sg:city":"Strathalbyn",
    "sg:classifiers":[
        {
            "category":"Personal",
            "subcategory":"Beauty Salon",
            "type":"Services"
        }
    ],
    "sg:phone":"+61 8 8536 3414",
    "sg:postcode":"5255",
    "sg:province":"SA",
    "sg:tags":[
        "hairdresser"
    ],
    "wof:name":"Hair Raisers",
    "wof:placetype":"venue"
},
  "geometry": {"coordinates":[138.891555786,-35.2595748901],"type":"Point"}
}