{
  "type": "Feature",
  "properties": {
    "addr:full":"7 Corinda Rd Woonona NSW 2517",
    "addr:housenumber":"7",
    "addr:postcode":"2517",
    "addr:street":"Corinda Rd",
    "iso:country":"AU",
    "sg:address":"7 Corinda Rd",
    "sg:city":"Woonona",
    "sg:classifiers":[
        {
            "category":"Real Estate",
            "subcategory":"Architect",
            "type":"Services"
        }
    ],
    "sg:phone":"+61 412 086 410",
    "sg:postcode":"2517",
    "sg:province":"NSW",
    "wof:name":"Ixis Architects",
    "wof:placetype":"venue"
},
  "geometry": {"coordinates":[150.91786200000001,-34.351631],"type":"Point"}
}