{
  "type": "Feature",
  "properties": {
    "iso:country":"AU",
    "sg:address":"Un 1, 140 Gould Rd",
    "sg:city":"Eagle Vale",
    "sg:classifiers":[
        {
            "category":"Health Services",
            "subcategory":"Health Practitioner",
            "type":"Services"
        }
    ],
    "sg:phone":"+61 2 4628 5293",
    "sg:postcode":"2558",
    "sg:province":"NSW",
    "sg:tags":[
        "dietitian"
    ],
    "wof:name":"Healthy Body Image Enterprises",
    "wof:placetype":"venue"
},
  "geometry": {"coordinates":[150.82081604000001,-34.0367126465],"type":"Point"}
}