{
  "type": "Feature",
  "properties": {
    "iso:country":"AU",
    "sg:address":"356 Bell St",
    "sg:city":"Pascoe Vale",
    "sg:classifiers":[
        {
            "category":"Banks & Credit Unions",
            "subcategory":"Financial Services",
            "type":"Services"
        }
    ],
    "sg:phone":"+61 3 9350 1881",
    "sg:postcode":"3044",
    "sg:province":"VIC",
    "sg:tags":[
        "planning"
    ],
    "sg:website":"http://www.fpa.asn.au",
    "wof:name":"Garvan Financial Planning",
    "wof:placetype":"venue"
},
  "geometry": {"coordinates":[144.94432067899999,-37.7388801575],"type":"Point"}
}