{
  "type": "Feature",
  "properties": {
    "iso:country":"AU",
    "sg:address":"15 Armstrong St",
    "sg:city":"Geelong North",
    "sg:classifiers":[
        {
            "category":"Wholesale",
            "subcategory":"Metals & Minerals",
            "type":"Manufacturing & Wholesale Goods"
        }
    ],
    "sg:phone":"+61 3 5277 9049",
    "sg:postcode":"3215",
    "sg:province":"VIC",
    "sg:tags":[
        "steel",
        "stainless",
        "product",
        "equipment"
    ],
    "wof:name":"Lunn Sheet Metal & Mechanical Services",
    "wof:placetype":"venue"
},
  "geometry": {"coordinates":[144.34588623100001,-38.1098937988],"type":"Point"}
}