{
  "type": "Feature",
  "properties": {
    "addr:full":"74 Henley Beach Rd Mile End SA 5031",
    "addr:housenumber":"74",
    "addr:postcode":"5031",
    "addr:street":"Henley Beach Rd",
    "iso:country":"AU",
    "sg:address":"74 Henley Beach Rd",
    "sg:city":"Mile End",
    "sg:classifiers":[
        {
            "category":"Health Services",
            "subcategory":"Health Practitioner",
            "type":"Services"
        }
    ],
    "sg:phone":"+61 8 8354 3777",
    "sg:postcode":"5031",
    "sg:province":"SA",
    "sg:tags":[
        "physiotherapist"
    ],
    "wof:name":"PhysioEdge",
    "wof:placetype":"venue"
},
  "geometry": {"coordinates":[138.57379150400001,-34.9233398438],"type":"Point"}
}