{
  "type": "Feature",
  "properties": {
    "iso:country":"AU",
    "sg:address":"281 Pacific Hwy",
    "sg:city":"North Sydney",
    "sg:classifiers":[
        {
            "category":"Professional",
            "subcategory":"Computer Services",
            "type":"Services"
        }
    ],
    "sg:phone":"+61 1300 658 175",
    "sg:postcode":"2060",
    "sg:province":"NSW",
    "sg:tags":[
        "consultant",
        "system"
    ],
    "wof:name":"Inside Computing",
    "wof:placetype":"venue"
},
  "geometry": {"coordinates":[151.20457458499999,-33.832824707],"type":"Point"}
}