{
  "type": "Feature",
  "properties": {
    "addr:full":"Shop 75a Warringah Mall Old Pittwater Rd Brookvale NSW 2100",
    "addr:housenumber":"75a",
    "addr:postcode":"2100",
    "addr:street":"Warringah Mall Old Pittwater Rd",
    "iso:country":"AU",
    "sg:address":"Shop 75a Warringah Mall Old Pittwater Rd",
    "sg:city":"Brookvale",
    "sg:classifiers":[
        {
            "category":"Travel",
            "subcategory":"Travel Agent",
            "type":"Entertainment"
        }
    ],
    "sg:phone":"+61 2 9939 2044",
    "sg:postcode":"2100",
    "sg:province":"NSW",
    "sg:tags":[
        "consultant"
    ],
    "wof:name":"Harvey World Travel",
    "wof:placetype":"venue"
},
  "geometry": {"coordinates":[151.27171325699999,-33.7619056702],"type":"Point"}
}