{
  "type": "Feature",
  "properties": {
    "iso:country":"AU",
    "sg:address":"112 Murray St",
    "sg:city":"Hobart",
    "sg:classifiers":[
        {
            "category":"Bars & Pubs",
            "subcategory":"Nightclub",
            "type":"Food & Drink"
        }
    ],
    "sg:phone":"+61 3 6234 5112",
    "sg:postcode":"7000",
    "sg:province":"TAS",
    "sg:tags":[
        "discotheque"
    ],
    "wof:name":"Curlys Bar",
    "wof:placetype":"venue"
},
  "geometry": {"coordinates":[147.32496643100001,-42.8823890686],"type":"Point"}
}