{
  "type": "Feature",
  "properties": {
    "addr:full":"3 Kinta Crt Clifton Springs VIC 3222",
    "addr:housenumber":"3",
    "addr:postcode":"3222",
    "addr:street":"Kinta Crt",
    "iso:country":"AU",
    "sg:address":"3 Kinta Crt",
    "sg:city":"Clifton Springs",
    "sg:classifiers":[
        {
            "category":"Autos & Motor Vehicles",
            "subcategory":"Automobile Sales",
            "type":"Retail Goods"
        }
    ],
    "sg:phone":"+61 407 597 391",
    "sg:postcode":"3222",
    "sg:province":"VIC",
    "sg:tags":[
        "equipment",
        "trailer"
    ],
    "wof:name":"Muscle Head",
    "wof:placetype":"venue"
},
  "geometry": {"coordinates":[144.553055,-38.159996],"type":"Point"}
}