{
  "type": "Feature",
  "properties": {
    "iso:country":"AU",
    "sg:address":"Great Western Hwy",
    "sg:city":"Wentworthville",
    "sg:classifiers":[
        {
            "category":"Shopping",
            "subcategory":"Music",
            "type":"Retail Goods"
        }
    ],
    "sg:phone":"+61 2 9769 0091",
    "sg:postcode":"2145",
    "sg:province":"NSW",
    "sg:tags":[
        "store"
    ],
    "wof:name":"Pied Piper Music",
    "wof:placetype":"venue"
},
  "geometry": {"coordinates":[150.967926025,-33.8151016235],"type":"Point"}
}