{
  "type": "Feature",
  "properties": {
    "addr:full":"473 Warrigul Rd Moorabbin VIC 3189",
    "addr:housenumber":"473",
    "addr:postcode":"3189",
    "addr:street":"Warrigul Rd",
    "iso:country":"AU",
    "sg:address":"473 Warrigul Rd",
    "sg:city":"Moorabbin",
    "sg:classifiers":[
        {
            "category":"Utilities",
            "subcategory":"Natural Gas",
            "type":"Services"
        }
    ],
    "sg:phone":"+61 3 9555 0599",
    "sg:postcode":"3189",
    "sg:province":"VIC",
    "sg:tags":[
        "supplier"
    ],
    "wof:name":"McMillan Distributor Pty Ltd",
    "wof:placetype":"venue"
},
  "geometry": {"coordinates":[145.078125,-37.9452400208],"type":"Point"}
}