{
  "type": "Feature",
  "properties": {
    "addr:full":"30 Boundary St South Melbourne VIC 3205",
    "addr:housenumber":"30",
    "addr:postcode":"3205",
    "addr:street":"Boundary St",
    "iso:country":"AU",
    "sg:address":"30 Boundary St",
    "sg:city":"South Melbourne",
    "sg:classifiers":[
        {
            "category":"Professional",
            "subcategory":"Engineering",
            "type":"Services"
        }
    ],
    "sg:phone":"+61 3 9645 1200",
    "sg:postcode":"3205",
    "sg:province":"VIC",
    "sg:tags":[
        "consulting",
        "engineer"
    ],
    "wof:name":"Skendzic Enterprises Pty Ltd",
    "wof:placetype":"venue"
},
  "geometry": {"coordinates":[144.948395,-37.832664],"type":"Point"}
}