{
  "type": "Feature",
  "properties": {
    "addr:full":"15 Fifth St Minlaton SA 5575",
    "addr:housenumber":"15",
    "addr:postcode":"5575",
    "addr:street":"Fifth St",
    "iso:country":"AU",
    "sg:address":"15 Fifth St",
    "sg:city":"Minlaton",
    "sg:classifiers":[
        {
            "category":"Professional",
            "subcategory":"Accounting & Tax Preparation",
            "type":"Services"
        }
    ],
    "sg:phone":"+61 8 8853 2080",
    "sg:postcode":"5575",
    "sg:province":"SA",
    "sg:tags":[
        "consultant",
        "taxation"
    ],
    "wof:name":"Dean Withers & Associates Pty Ltd",
    "wof:placetype":"venue"
},
  "geometry": {"coordinates":[137.59519958499999,-34.7730293274],"type":"Point"}
}