{
  "type": "Feature",
  "properties": {
    "addr:full":"Shp 304 Sugarland Shoppingtown West Bundaberg QLD 4670",
    "addr:housenumber":"304;shoppingtown",
    "addr:postcode":"4670",
    "addr:street":"Sugarland",
    "iso:country":"AU",
    "sg:address":"Shp 304 Sugarland Shoppingtown",
    "sg:city":"West Bundaberg",
    "sg:classifiers":[
        {
            "category":"Shopping",
            "subcategory":"Clothing, Apparel, & Fashions",
            "type":"Retail Goods"
        }
    ],
    "sg:phone":"+61 7 4151 2450",
    "sg:postcode":"4670",
    "sg:province":"QLD",
    "sg:tags":[
        "jean"
    ],
    "wof:name":"Just Jeans",
    "wof:placetype":"venue"
},
  "geometry": {"coordinates":[152.34669494600001,-24.8670501709],"type":"Point"}
}