{
  "type": "Feature",
  "properties": {
    "addr:full":"Shop 5 24 Flushcombe Rd Blacktown NSW 2148",
    "addr:housenumber":"shop;24",
    "addr:postcode":"2148",
    "addr:street":"Flushcombe Rd",
    "iso:country":"AU",
    "sg:address":"Shop 5 24 Flushcombe Rd",
    "sg:city":"Blacktown",
    "sg:classifiers":[
        {
            "category":"Banks & Credit Unions",
            "subcategory":"Investment Brokerage",
            "type":"Services"
        }
    ],
    "sg:phone":"+61 2 9621 6921",
    "sg:postcode":"2148",
    "sg:province":"NSW",
    "sg:tags":[
        "finance",
        "broker"
    ],
    "wof:name":"No.1 Home Loans",
    "wof:placetype":"venue"
},
  "geometry": {"coordinates":[150.90861511200001,-33.7704925537],"type":"Point"}
}