{
  "type": "Feature",
  "properties": {
    "addr:full":"1 The Northern Rd Luddenham NSW 2745",
    "addr:housenumber":"1",
    "addr:postcode":"2745",
    "addr:street":"The Northern Rd",
    "iso:country":"AU",
    "sg:address":"1 The Northern Rd",
    "sg:city":"Luddenham",
    "sg:classifiers":[
        {
            "category":"Food & Beverages",
            "subcategory":"Bakery",
            "type":"Retail Goods"
        }
    ],
    "sg:phone":"+61 2 4773 4193",
    "sg:postcode":"2745",
    "sg:province":"NSW",
    "sg:tags":[
        "baker"
    ],
    "wof:name":"Al's Bakery",
    "wof:placetype":"venue"
},
  "geometry": {"coordinates":[150.701568603,-33.8966941833],"type":"Point"}
}