{
  "type": "Feature",
  "properties": {
    "iso:country":"AU",
    "sg:address":"33 Ellen St",
    "sg:city":"Wollongong",
    "sg:classifiers":[
        {
            "category":"Building & Trades",
            "subcategory":"Construction",
            "type":"Services"
        }
    ],
    "sg:phone":"+61 2 4225 1555",
    "sg:postcode":"2500",
    "sg:province":"NSW",
    "sg:tags":[
        "contractor"
    ],
    "wof:name":"Hotondo Homes Wollongong",
    "wof:placetype":"venue"
},
  "geometry": {"coordinates":[150.884247,-34.429836],"type":"Point"}
}