{
  "type": "Feature",
  "properties": {
    "addr:full":"99 Marion St Leichhardt NSW 2040",
    "addr:housenumber":"99",
    "addr:postcode":"2040",
    "addr:street":"Marion St",
    "iso:country":"AU",
    "sg:address":"99 Marion St",
    "sg:city":"Leichhardt",
    "sg:classifiers":[
        {
            "category":"Health Services",
            "subcategory":"Dentist",
            "type":"Services"
        }
    ],
    "sg:phone":"+61 2 9560 7885",
    "sg:postcode":"2040",
    "sg:province":"NSW",
    "sg:tags":[
        "technician",
        "dental"
    ],
    "wof:name":"R & C Dental Laboratory",
    "wof:placetype":"venue"
},
  "geometry": {"coordinates":[151.15237400000001,-33.883945],"type":"Point"}
}