{
  "type": "Feature",
  "properties": {
    "iso:country":"AU",
    "sg:address":"909 Rathdowne St",
    "sg:city":"Carlton North",
    "sg:classifiers":[
        {
            "category":"Personal",
            "subcategory":"Beauty Salon",
            "type":"Services"
        }
    ],
    "sg:phone":"+61 3 9380 8155",
    "sg:postcode":"3054",
    "sg:province":"VIC",
    "sg:tags":[
        "hairdresser"
    ],
    "wof:name":"Peroximity Hair & Beauty",
    "wof:placetype":"venue"
},
  "geometry": {"coordinates":[144.972732544,-37.7828979492],"type":"Point"}
}