{
  "type": "Feature",
  "properties": {
    "addr:full":"24 Shields St Cairns QLD 4870",
    "addr:housenumber":"24",
    "addr:postcode":"4870",
    "addr:street":"Shields St",
    "iso:country":"AU",
    "sg:address":"24 Shields St",
    "sg:city":"Cairns",
    "sg:classifiers":[
        {
            "category":"Bars & Pubs",
            "subcategory":"Nightclub",
            "type":"Food & Drink"
        }
    ],
    "sg:phone":"+61 7 4031 6304",
    "sg:postcode":"4870",
    "sg:province":"QLD",
    "sg:tags":[
        "discotheque"
    ],
    "wof:name":"The Wool Shed Char Grill & Saloon Bar",
    "wof:placetype":"venue"
},
  "geometry": {"coordinates":[145.775466919,-16.922504425],"type":"Point"}
}