{
  "type": "Feature",
  "properties": {
    "addr:full":"227 Lennox St Richmond VIC 3121",
    "addr:housenumber":"227",
    "addr:postcode":"3121",
    "addr:street":"Lennox St",
    "iso:country":"AU",
    "sg:address":"227 Lennox St",
    "sg:city":"Richmond",
    "sg:classifiers":[
        {
            "category":"Real Estate",
            "subcategory":"Architect",
            "type":"Services"
        }
    ],
    "sg:phone":"+61 3 9427 7535",
    "sg:postcode":"3121",
    "sg:province":"VIC",
    "wof:name":"Michael Wald Architect",
    "wof:placetype":"venue"
},
  "geometry": {"coordinates":[144.994338989,-37.8206634521],"type":"Point"}
}