{
  "type": "Feature",
  "properties": {
    "addr:full":"169 Birkdale Rd Birkdale QLD 4159",
    "addr:housenumber":"169",
    "addr:postcode":"4159",
    "addr:street":"Birkdale Rd",
    "iso:country":"AU",
    "sg:address":"169 Birkdale Rd",
    "sg:city":"Birkdale",
    "sg:classifiers":[
        {
            "category":"Personal",
            "subcategory":"Beauty Salon",
            "type":"Services"
        }
    ],
    "sg:phone":"+61 421 868 118",
    "sg:postcode":"4159",
    "sg:province":"QLD",
    "sg:tags":[
        "hairdresser"
    ],
    "wof:name":"BMH Mobile Hair Design",
    "wof:placetype":"venue"
},
  "geometry": {"coordinates":[153.21081543,-27.5005588531],"type":"Point"}
}