{
  "type": "Feature",
  "properties": {
    "iso:country":"AU",
    "sg:address":"1 Rochester Rd",
    "sg:city":"Canterbury",
    "sg:classifiers":[
        {
            "category":"Professional",
            "subcategory":"Art Services",
            "type":"Services"
        }
    ],
    "sg:phone":"+61 3 9888 5601",
    "sg:postcode":"3126",
    "sg:province":"VIC",
    "sg:tags":[
        "graphic",
        "designer"
    ],
    "wof:name":"David Bryant & Associates",
    "wof:placetype":"venue"
},
  "geometry": {"coordinates":[145.081207275,-37.8237533569],"type":"Point"}
}