{
  "type": "Feature",
  "properties": {
    "addr:full":"524 Guildford Rd Bayswater WA 6053",
    "addr:housenumber":"524",
    "addr:postcode":"6053",
    "addr:street":"Guildford Rd",
    "iso:country":"AU",
    "sg:address":"524 Guildford Rd",
    "sg:city":"Bayswater",
    "sg:classifiers":[
        {
            "category":"Professional",
            "subcategory":"Employment Agencies",
            "type":"Services"
        }
    ],
    "sg:phone":"+61 8 6278 4907",
    "sg:postcode":"6053",
    "sg:province":"WA",
    "sg:tags":[
        "hire",
        "labour",
        "contractor"
    ],
    "wof:name":"Yangwha Global Pty Ltd",
    "wof:placetype":"venue"
},
  "geometry": {"coordinates":[115.92133331300001,-31.9237918854],"type":"Point"}
}