{
  "type": "Feature",
  "properties": {
    "addr:full":"Main St Stawell VIC 3380",
    "addr:postcode":"3380",
    "addr:street":"Main St",
    "iso:country":"AU",
    "sg:address":"Main St",
    "sg:city":"Stawell",
    "sg:classifiers":[
        {
            "category":"Autos & Motor Vehicles",
            "subcategory":"Fuel & Gas Station",
            "type":"Retail Goods"
        }
    ],
    "sg:phone":"+61 3 5356 9330",
    "sg:postcode":"3380",
    "sg:province":"VIC",
    "wof:name":"BP Australia Limited",
    "wof:placetype":"venue"
},
  "geometry": {"coordinates":[142.783599853,-37.0541305542],"type":"Point"}
}