{
  "type": "Feature",
  "properties": {
    "iso:country":"AU",
    "sg:address":"11a Lampton Ave",
    "sg:city":"Derwent Park",
    "sg:classifiers":[
        {
            "category":"Government",
            "subcategory":"Fire Station",
            "type":"Public Place"
        }
    ],
    "sg:phone":"+61 3 6272 7077",
    "sg:postcode":"7009",
    "sg:province":"TAS",
    "sg:tags":[
        "equipment",
        "protection",
        "consultant"
    ],
    "wof:name":"Chubb Fire Safety",
    "wof:placetype":"venue"
},
  "geometry": {"coordinates":[147.28956604000001,-42.8355064392],"type":"Point"}
}