{
  "type": "Feature",
  "properties": {
    "iso:country":"AU",
    "sg:address":"792 Nubeena Rd",
    "sg:city":"Premaydena",
    "sg:classifiers":[
        {
            "category":"Home & Garden",
            "subcategory":"Building Materials",
            "type":"Retail Goods"
        }
    ],
    "sg:phone":"+61 3 6250 3555",
    "sg:postcode":"7185",
    "sg:province":"TAS",
    "sg:tags":[
        "merchant",
        "glass",
        "glazier"
    ],
    "wof:name":"Peninsula Glass & Glazing",
    "wof:placetype":"venue"
},
  "geometry": {"coordinates":[147.789246,-43.052937],"type":"Point"}
}