{
  "type": "Feature",
  "properties": {
    "iso:country":"AU",
    "sg:address":"8 Laurel St",
    "sg:city":"Korora",
    "sg:classifiers":[
        {
            "category":"Retail",
            "subcategory":"Car Wash",
            "type":"Services"
        }
    ],
    "sg:phone":"+61 2 6653 7248",
    "sg:postcode":"2450",
    "sg:province":"NSW",
    "sg:tags":[
        "bitumen",
        "spraying"
    ],
    "wof:name":"Bowen M & R Road Maintenance & Earthmoving",
    "wof:placetype":"venue"
},
  "geometry": {"coordinates":[153.135986,-30.256269],"type":"Point"}
}