{
  "type": "Feature",
  "properties": {
    "iso:country":"AU",
    "sg:address":"72 Percival Rd",
    "sg:city":"Smithfield",
    "sg:classifiers":[
        {
            "category":"Utilities",
            "subcategory":"Electric",
            "type":"Services"
        }
    ],
    "sg:phone":"+61 2 9729 0499",
    "sg:postcode":"2164",
    "sg:province":"NSW",
    "sg:tags":[
        "electrical",
        "contractor"
    ],
    "wof:name":"Elarmcom Electrical Services",
    "wof:placetype":"venue"
},
  "geometry": {"coordinates":[150.95039367699999,-33.8407058716],"type":"Point"}
}