{
  "type": "Feature",
  "properties": {
    "iso:country":"AU",
    "sg:address":"Greenhill Rd",
    "sg:city":"Uraidla",
    "sg:classifiers":[
        {
            "category":"Professional",
            "subcategory":"Engineering",
            "type":"Services"
        }
    ],
    "sg:phone":"+61 8 8390 3680",
    "sg:postcode":"5142",
    "sg:province":"SA",
    "sg:tags":[
        "electronic",
        "engineer"
    ],
    "wof:name":"Novacom Pty Ltd",
    "wof:placetype":"venue"
},
  "geometry": {"coordinates":[138.745865,-34.958366],"type":"Point"}
}