{
  "type": "Feature",
  "properties": {
    "addr:full":"U 3/ 7 Kara Crs Taylors Beach NSW 2316",
    "addr:housenumber":"7",
    "addr:postcode":"2316",
    "addr:street":"Kara Crs",
    "iso:country":"AU",
    "sg:address":"U 3/ 7 Kara Crs",
    "sg:city":"Taylors Beach",
    "sg:classifiers":[
        {
            "category":"Wholesale",
            "subcategory":"Non-durable Goods",
            "type":"Manufacturing & Wholesale Goods"
        }
    ],
    "sg:phone":"+61 2 4982 2601",
    "sg:postcode":"2316",
    "sg:province":"NSW",
    "sg:tags":[
        "wholesaler",
        "mfrs",
        "cosmetic"
    ],
    "wof:name":"Natural Choice Cosmetics",
    "wof:placetype":"venue"
},
  "geometry": {"coordinates":[152.06880200000001,-32.749008],"type":"Point"}
}