{
  "type": "Feature",
  "properties": {
    "addr:full":"Shop 2 100 King William Rd Hyde Park SA 5061",
    "addr:housenumber":"shop 2 100",
    "addr:postcode":"5061",
    "addr:street":"King William Rd",
    "iso:country":"AU",
    "sg:address":"Shop 2 100 King William Rd",
    "sg:city":"Hyde Park",
    "sg:classifiers":[
        {
            "category":"Personal",
            "subcategory":"Skin Care",
            "type":"Services"
        }
    ],
    "sg:phone":"+61 8 8373 4771",
    "sg:postcode":"5061",
    "sg:province":"SA",
    "sg:tags":[
        "treatment"
    ],
    "wof:name":"Natalie Of Hyde Park",
    "wof:placetype":"venue"
},
  "geometry": {"coordinates":[138.599700928,-34.9522399902],"type":"Point"}
}