{
  "type": "Feature",
  "properties": {
    "addr:full":"Shop 1, 485 Cabramatta Rd Cabramatta NSW 2166",
    "addr:housenumber":"shop 1 485",
    "addr:postcode":"2166",
    "addr:street":"Cabramatta Rd",
    "iso:country":"AU",
    "sg:address":"Shop 1, 485 Cabramatta Rd",
    "sg:city":"Cabramatta",
    "sg:classifiers":[
        {
            "category":"Food & Beverages",
            "subcategory":"Liquor & Beverages",
            "type":"Retail Goods"
        }
    ],
    "sg:phone":"+61 2 9610 5121",
    "sg:postcode":"2166",
    "sg:province":"NSW",
    "sg:tags":[
        "store"
    ],
    "wof:name":"BWS Liquor",
    "wof:placetype":"venue"
},
  "geometry": {"coordinates":[150.91215515100001,-33.8963661194],"type":"Point"}
}