{
  "type": "Feature",
  "properties": {
    "iso:country":"AU",
    "sg:address":"27 Crescent St",
    "sg:city":"Rozelle",
    "sg:classifiers":[
        {
            "category":"Building & Trades",
            "subcategory":"Construction",
            "type":"Services"
        }
    ],
    "sg:phone":"+61 2 9555 8338",
    "sg:postcode":"2039",
    "sg:province":"NSW",
    "sg:tags":[
        "contractor"
    ],
    "wof:name":"Braams Developments",
    "wof:placetype":"venue"
},
  "geometry": {"coordinates":[151.174957275,-33.8651046753],"type":"Point"}
}