{
  "type": "Feature",
  "properties": {
    "addr:full":"22 Maud St Newstead QLD 4006",
    "addr:housenumber":"22",
    "addr:postcode":"4006",
    "addr:street":"Maud St",
    "iso:country":"AU",
    "sg:address":"22 Maud St",
    "sg:city":"Newstead",
    "sg:classifiers":[
        {
            "category":"Building & Trades",
            "subcategory":"Equipment Rental",
            "type":"Services"
        }
    ],
    "sg:phone":"+61 7 3852 2757",
    "sg:postcode":"4006",
    "sg:province":"QLD",
    "sg:tags":[
        "party",
        "hire"
    ],
    "wof:name":"Skypak Lighting & Production Services Pty Ltd",
    "wof:placetype":"venue"
},
  "geometry": {"coordinates":[153.04481506400001,-27.4448299408],"type":"Point"}
}