{
  "type": "Feature",
  "properties": {
    "iso:country":"AU",
    "sg:address":"1220 Mair St",
    "sg:city":"Ballarat",
    "sg:classifiers":[
        {
            "category":"Health Services",
            "subcategory":"Health Practitioner",
            "type":"Services"
        }
    ],
    "sg:phone":"+61 3 5331 3066",
    "sg:postcode":"3350",
    "sg:province":"VIC",
    "sg:tags":[
        "physiotherapist"
    ],
    "wof:name":"Crocker A D",
    "wof:placetype":"venue"
},
  "geometry": {"coordinates":[143.842224,-37.557758],"type":"Point"}
}