{
  "type": "Feature",
  "properties": {
    "addr:full":"169 Musgrave Rd Coopers Plains QLD 4108",
    "addr:housenumber":"169",
    "addr:postcode":"4108",
    "addr:street":"Musgrave Rd",
    "iso:country":"AU",
    "sg:address":"169 Musgrave Rd",
    "sg:city":"Coopers Plains",
    "sg:classifiers":[
        {
            "category":"Transit Center",
            "subcategory":"Freight",
            "type":"Transportation"
        }
    ],
    "sg:phone":"+61 7 3277 9962",
    "sg:postcode":"4108",
    "sg:province":"QLD",
    "sg:tags":[
        "joint",
        "expansion"
    ],
    "wof:name":"Bellis Contracting Services",
    "wof:placetype":"venue"
},
  "geometry": {"coordinates":[153.030960083,-27.5620555878],"type":"Point"}
}