{
  "type": "Feature",
  "properties": {
    "addr:full":"9th Floor Suite 907 Manchester Unity Bldg Melbourne VIC 3000",
    "addr:postcode":"3000",
    "iso:country":"AU",
    "sg:address":"9th Floor Suite 907 Manchester Unity Bldg",
    "sg:city":"Melbourne",
    "sg:classifiers":[
        {
            "category":"Recreation",
            "subcategory":"Sailing Club",
            "type":"Entertainment"
        }
    ],
    "sg:phone":"+61 3 9650 1380",
    "sg:postcode":"3000",
    "sg:province":"VIC",
    "sg:tags":[
        "merchant",
        "diamond"
    ],
    "wof:name":"Superior Diamonds Pty Ltd",
    "wof:placetype":"venue"
},
  "geometry": {"coordinates":[144.97027587900001,-37.8145599365],"type":"Point"}
}