{
  "type": "Feature",
  "properties": {
    "iso:country":"AU",
    "sg:address":"Hicksons Rd",
    "sg:city":"Officer",
    "sg:classifiers":[
        {
            "category":"Wholesale",
            "subcategory":"Farm Supplies",
            "type":"Manufacturing & Wholesale Goods"
        }
    ],
    "sg:phone":"+61 3 5943 2255",
    "sg:postcode":"3809",
    "sg:province":"VIC",
    "sg:tags":[
        "feed",
        "supplement",
        "stock"
    ],
    "wof:name":"Hy Gain Feed Pty Ltd",
    "wof:placetype":"venue"
},
  "geometry": {"coordinates":[145.41043099999999,-38.067909],"type":"Point"}
}