{
  "type": "Feature",
  "properties": {
    "addr:full":"23 Beenong Rd Darlington WA 6070",
    "addr:housenumber":"23",
    "addr:postcode":"6070",
    "addr:street":"Beenong Rd",
    "iso:country":"AU",
    "sg:address":"23 Beenong Rd",
    "sg:city":"Darlington",
    "sg:classifiers":[
        {
            "category":"Building & Trades",
            "subcategory":"Plumbing",
            "type":"Services"
        }
    ],
    "sg:phone":"+61 8 9252 0111",
    "sg:postcode":"6070",
    "sg:province":"WA",
    "sg:tags":[
        "plumber",
        "gasfitters"
    ],
    "wof:name":"West Force Plumbing",
    "wof:placetype":"venue"
},
  "geometry": {"coordinates":[116.074913025,-31.9220695496],"type":"Point"}
}