{
  "type": "Feature",
  "properties": {
    "addr:full":"166 River St Ballina NSW 2478",
    "addr:housenumber":"166",
    "addr:postcode":"2478",
    "addr:street":"River St",
    "iso:country":"AU",
    "sg:address":"166 River St",
    "sg:city":"Ballina",
    "sg:classifiers":[
        {
            "category":"Retail",
            "subcategory":"Auto Repair",
            "type":"Services"
        }
    ],
    "sg:phone":"+61 2 6627 7999",
    "sg:postcode":"2478",
    "sg:province":"NSW",
    "sg:tags":[
        "repairer",
        "motor",
        "engineer"
    ],
    "wof:name":"Trevan Ford",
    "wof:placetype":"venue"
},
  "geometry": {"coordinates":[153.55990600600001,-28.8703727722],"type":"Point"}
}