{
  "type": "Feature",
  "properties": {
    "addr:full":"36 Old Cleveland Rd Capalaba QLD 4157",
    "addr:housenumber":"36",
    "addr:postcode":"4157",
    "addr:street":"Old Cleveland Rd",
    "iso:country":"AU",
    "sg:address":"36 Old Cleveland Rd",
    "sg:city":"Capalaba",
    "sg:classifiers":[
        {
            "category":"Health Services",
            "subcategory":"Doctor",
            "type":"Services"
        }
    ],
    "sg:phone":"+61 7 3843 8911",
    "sg:postcode":"4157",
    "sg:province":"QLD",
    "sg:tags":[
        "nurse",
        "nursing"
    ],
    "wof:name":"Code Blue Specialist Nurses Agency",
    "wof:placetype":"venue"
},
  "geometry": {"coordinates":[153.197555542,-27.5210933685],"type":"Point"}
}