{
  "type": "Feature",
  "properties": {
    "iso:country":"AU",
    "sg:address":"Shop 7/ 15 Pitt St",
    "sg:city":"Riverstone",
    "sg:classifiers":[
        {
            "category":"Shopping",
            "subcategory":"Computers & Home Electronics",
            "type":"Retail Goods"
        }
    ],
    "sg:phone":"+61 2 9838 1212",
    "sg:postcode":"2765",
    "sg:province":"NSW",
    "sg:tags":[
        "hardware",
        "equipment"
    ],
    "wof:name":"Z-Tronics Computer Services",
    "wof:placetype":"venue"
},
  "geometry": {"coordinates":[150.863113403,-33.6784172058],"type":"Point"}
}