{
  "type": "Feature",
  "properties": {
    "addr:full":"Lvl 1 16-18 Princes Hwy Dapto NSW 2530",
    "addr:housenumber":"16-18",
    "addr:postcode":"2530",
    "addr:street":"Princes Hwy",
    "iso:country":"AU",
    "sg:address":"Lvl 1 16-18 Princes Hwy",
    "sg:city":"Dapto",
    "sg:classifiers":[
        {
            "category":"Banks & Credit Unions",
            "subcategory":"Financial Services",
            "type":"Services"
        }
    ],
    "sg:phone":"+61 2 4261 2101",
    "sg:postcode":"2530",
    "sg:province":"NSW",
    "sg:tags":[
        "annuity",
        "rollover",
        "superannuation",
        "consultant"
    ],
    "wof:name":"Thurlings Financial Services",
    "wof:placetype":"venue"
},
  "geometry": {"coordinates":[150.81840515100001,-34.4924659729],"type":"Point"}
}