{
  "type": "Feature",
  "properties": {
    "iso:country":"AU",
    "sg:address":"20 Mowburra Pl",
    "sg:city":"Caloundra West",
    "sg:classifiers":[
        {
            "category":"Utilities",
            "subcategory":"Refuse",
            "type":"Services"
        }
    ],
    "sg:phone":"+61 7 5438 2866",
    "sg:postcode":"4551",
    "sg:province":"QLD",
    "sg:tags":[
        "remover",
        "rubbish"
    ],
    "wof:name":"Be Pro-Active",
    "wof:placetype":"venue"
},
  "geometry": {"coordinates":[153.091674805,-26.7945232391],"type":"Point"}
}