{
  "type": "Feature",
  "properties": {
    "iso:country":"AU",
    "sg:address":"10 Nardie Pl",
    "sg:city":"Hillman",
    "sg:classifiers":[
        {
            "category":"Building & Trades",
            "subcategory":"Construction",
            "type":"Services"
        }
    ],
    "sg:phone":"+61 8 9527 1862",
    "sg:postcode":"6168",
    "sg:province":"WA",
    "sg:tags":[
        "roof"
    ],
    "wof:name":"Marinich S & L Pty Ltd",
    "wof:placetype":"venue"
},
  "geometry": {"coordinates":[115.762047,-32.28495],"type":"Point"}
}