{
  "type": "Feature",
  "properties": {
    "addr:full":"19 Oxley St Bourke NSW 2840",
    "addr:housenumber":"19",
    "addr:postcode":"2840",
    "addr:street":"Oxley St",
    "iso:country":"AU",
    "sg:address":"19 Oxley St",
    "sg:city":"Bourke",
    "sg:classifiers":[
        {
            "category":"Banks & Credit Unions",
            "subcategory":"Bank",
            "type":"Services"
        }
    ],
    "sg:phone":"+61 13 20 32",
    "sg:postcode":"2840",
    "sg:province":"NSW",
    "wof:name":"Westpac",
    "wof:placetype":"venue"
},
  "geometry": {"coordinates":[145.93533300000001,-30.089634],"type":"Point"}
}