{
  "type": "Feature",
  "properties": {
    "iso:country":"AU",
    "sg:address":"4 Deacon Ave",
    "sg:city":"Richmond",
    "sg:classifiers":[
        {
            "category":"Professional",
            "subcategory":"Art Services",
            "type":"Services"
        }
    ],
    "sg:phone":"+61 8 8234 2045",
    "sg:postcode":"5033",
    "sg:province":"SA",
    "sg:tags":[
        "graphic",
        "designer"
    ],
    "wof:name":"Graphicmac",
    "wof:placetype":"venue"
},
  "geometry": {"coordinates":[138.56979370100001,-34.9382591248],"type":"Point"}
}