{
  "type": "Feature",
  "properties": {
    "addr:full":"17 Mickle St Dandenong VIC 3175",
    "addr:housenumber":"17",
    "addr:postcode":"3175",
    "addr:street":"Mickle St",
    "iso:country":"AU",
    "sg:address":"17 Mickle St",
    "sg:city":"Dandenong",
    "sg:classifiers":[
        {
            "category":"Manufacturing",
            "subcategory":"Rubber & Plastics",
            "type":"Manufacturing & Wholesale Goods"
        }
    ],
    "sg:phone":"+61 3 9706 5948",
    "sg:postcode":"3175",
    "sg:province":"VIC",
    "sg:tags":[
        "moulders"
    ],
    "wof:name":"L J Plastics Pty Ltd",
    "wof:placetype":"venue"
},
  "geometry": {"coordinates":[145.20503234899999,-38.0299797058],"type":"Point"}
}