{
  "type": "Feature",
  "properties": {
    "iso:country":"AU",
    "sg:address":"14 Chapman St",
    "sg:city":"Proserpine",
    "sg:classifiers":[
        {
            "category":"Health Services",
            "subcategory":"Dentist",
            "type":"Services"
        }
    ],
    "sg:phone":"+61 7 4945 1361",
    "sg:postcode":"4800",
    "sg:province":"QLD",
    "wof:name":"Helvig Steven",
    "wof:placetype":"venue"
},
  "geometry": {"coordinates":[148.583221436,-20.4005527496],"type":"Point"}
}