{
  "type": "Feature",
  "properties": {
    "addr:full":"Lot 343, Kintyre Cl Warnervale NSW 2259",
    "addr:housenumber":"343",
    "addr:postcode":"2259",
    "addr:street":"Kintyre Cl Warnervale",
    "iso:country":"AU",
    "sg:address":"Lot 343, Kintyre Cl",
    "sg:city":"Warnervale",
    "sg:classifiers":[
        {
            "category":"Building & Trades",
            "subcategory":"Construction",
            "type":"Services"
        }
    ],
    "sg:phone":"+61 2 4393 0217",
    "sg:postcode":"2259",
    "sg:province":"NSW",
    "sg:tags":[
        "contractor"
    ],
    "wof:name":"Mirvac Homes",
    "wof:placetype":"venue"
},
  "geometry": {"coordinates":[151.423217773,-33.2335090637],"type":"Point"}
}