{
  "type": "Feature",
  "properties": {
    "addr:full":"93 Cronulla St Cronulla NSW 2230",
    "addr:housenumber":"93",
    "addr:postcode":"2230",
    "addr:street":"Cronulla St",
    "iso:country":"AU",
    "sg:address":"93 Cronulla St",
    "sg:city":"Cronulla",
    "sg:classifiers":[
        {
            "category":"Deli",
            "type":"Food & Drink"
        }
    ],
    "sg:phone":"+61 2 9544 0339",
    "sg:postcode":"2230",
    "sg:province":"NSW",
    "sg:tags":[
        "delicatessen"
    ],
    "wof:name":"Rhonda's Place",
    "wof:placetype":"venue"
},
  "geometry": {"coordinates":[151.151885986,-34.0543632507],"type":"Point"}
}