{
  "type": "Feature",
  "properties": {
    "iso:country":"AU",
    "sg:address":"31 Old North Rd",
    "sg:city":"Clare",
    "sg:classifiers":[
        {
            "category":"Health Services",
            "subcategory":"Chiropractor",
            "type":"Services"
        }
    ],
    "sg:phone":"+61 8 8542 1930",
    "sg:postcode":"5453",
    "sg:province":"SA",
    "wof:name":"Quodling Nicole Dr",
    "wof:placetype":"venue"
},
  "geometry": {"coordinates":[138.611954,-33.832424],"type":"Point"}
}