{
  "type": "Feature",
  "properties": {
    "addr:full":"80 Glen Tower Drv Glen Waverley VIC 3150",
    "addr:housenumber":"80",
    "addr:postcode":"3150",
    "addr:street":"Glen Tower Drv",
    "iso:country":"AU",
    "sg:address":"80 Glen Tower Drv",
    "sg:city":"Glen Waverley",
    "sg:classifiers":[
        {
            "category":"Communications",
            "subcategory":"Film & Video Production",
            "type":"Services"
        }
    ],
    "sg:phone":"+61 3 9574 7776",
    "sg:postcode":"3150",
    "sg:province":"VIC",
    "sg:tags":[
        "print",
        "poster",
        "wholesale",
        "pictures"
    ],
    "wof:name":"Blue Angel Gallery",
    "wof:placetype":"venue"
},
  "geometry": {"coordinates":[145.18504333499999,-37.8785514832],"type":"Point"}
}