{
  "type": "Feature",
  "properties": {
    "iso:country":"AU",
    "sg:address":"4/ 49 Regentville Rd",
    "sg:city":"Penrith",
    "sg:classifiers":[
        {
            "category":"Autos & Motor Vehicles",
            "subcategory":"Auto Supplies",
            "type":"Retail Goods"
        }
    ],
    "sg:phone":"+61 2 4721 7472",
    "sg:postcode":"2750",
    "sg:province":"NSW",
    "sg:tags":[
        "part",
        "cycles",
        "accessory"
    ],
    "wof:name":"John Rabaud Motorcycles",
    "wof:placetype":"venue"
},
  "geometry": {"coordinates":[150.68312072800001,-33.7653541565],"type":"Point"}
}