{
  "type": "Feature",
  "properties": {
    "addr:full":"67 Nicholson Pde Cronulla NSW 2230",
    "addr:housenumber":"67",
    "addr:postcode":"2230",
    "addr:street":"Nicholson Pde",
    "iso:country":"AU",
    "sg:address":"67 Nicholson Pde",
    "sg:city":"Cronulla",
    "sg:classifiers":[
        {
            "category":"Professional",
            "type":"Services"
        }
    ],
    "sg:phone":"+61 2 9523 5725",
    "sg:postcode":"2230",
    "sg:province":"NSW",
    "sg:tags":[
        "valuer"
    ],
    "wof:name":"Heidenreich Rodney Valuations",
    "wof:placetype":"venue"
},
  "geometry": {"coordinates":[151.14874267600001,-34.0621833801],"type":"Point"}
}