{
  "type": "Feature",
  "properties": {
    "addr:full":"605 Canterbury Rd Surrey Hills VIC 3127",
    "addr:housenumber":"605",
    "addr:postcode":"3127",
    "addr:street":"Canterbury Rd",
    "iso:country":"AU",
    "sg:address":"605 Canterbury Rd",
    "sg:city":"Surrey Hills",
    "sg:classifiers":[
        {
            "category":"Retail",
            "subcategory":"Auto Repair",
            "type":"Services"
        }
    ],
    "sg:phone":"+61 3 9836 6511",
    "sg:postcode":"3127",
    "sg:province":"VIC",
    "sg:tags":[
        "body",
        "builder",
        "motor"
    ],
    "wof:name":"Surrey Panelcare Pty Ltd",
    "wof:placetype":"venue"
},
  "geometry": {"coordinates":[145.0965271,-37.8257255554],"type":"Point"}
}