{
  "type": "Feature",
  "properties": {
    "iso:country":"AU",
    "sg:address":"U3/ 5 Augusta St",
    "sg:city":"Willetton",
    "sg:classifiers":[
        {
            "category":"Retail",
            "subcategory":"Auto Repair",
            "type":"Services"
        }
    ],
    "sg:phone":"+61 8 9457 6621",
    "sg:postcode":"6155",
    "sg:province":"WA",
    "sg:tags":[
        "repairer",
        "motor",
        "engineer"
    ],
    "wof:name":"Vogels Auto Repairs",
    "wof:placetype":"venue"
},
  "geometry": {"coordinates":[115.87995100000001,-32.039791],"type":"Point"}
}