{
  "type": "Feature",
  "properties": {
    "addr:full":"137 Macquarie Rd Macquarie Hills NSW 2285",
    "addr:housenumber":"137",
    "addr:postcode":"2285",
    "addr:street":"Macquarie Rd",
    "iso:country":"AU",
    "sg:address":"137 Macquarie Rd",
    "sg:city":"Macquarie Hills",
    "sg:classifiers":[
        {
            "category":"Wholesale",
            "subcategory":"Machinery & Supplies",
            "type":"Manufacturing & Wholesale Goods"
        }
    ],
    "sg:phone":"+61 2 4954 2112",
    "sg:postcode":"2285",
    "sg:province":"NSW",
    "sg:tags":[
        "engineer"
    ],
    "wof:name":"Applied Advantage Pty Ltd",
    "wof:placetype":"venue"
},
  "geometry": {"coordinates":[151.65545654300001,-32.9542312622],"type":"Point"}
}