{
  "type": "Feature",
  "properties": {
    "addr:full":"67 Benjamin St Sunshine VIC 3020",
    "addr:housenumber":"67",
    "addr:postcode":"3020",
    "addr:street":"Benjamin St",
    "iso:country":"AU",
    "sg:address":"67 Benjamin St",
    "sg:city":"Sunshine",
    "sg:classifiers":[
        {
            "category":"Building & Trades",
            "subcategory":"Landscaping Services",
            "type":"Services"
        }
    ],
    "sg:phone":"+61 413 144 141",
    "sg:postcode":"3020",
    "sg:province":"VIC",
    "sg:tags":[
        "gardener"
    ],
    "wof:name":"Country Cuts Garden Service",
    "wof:placetype":"venue"
},
  "geometry": {"coordinates":[144.82908599999999,-37.793354],"type":"Point"}
}