{
  "type": "Feature",
  "properties": {
    "addr:full":"122 Ashgrove Ave Ashgrove QLD 4060",
    "addr:housenumber":"122",
    "addr:postcode":"4060",
    "addr:street":"Ashgrove Ave",
    "iso:country":"AU",
    "sg:address":"122 Ashgrove Ave",
    "sg:city":"Ashgrove",
    "sg:classifiers":[
        {
            "category":"Health Services",
            "subcategory":"Health Practitioner",
            "type":"Services"
        }
    ],
    "sg:phone":"+61 7 3366 5654",
    "sg:postcode":"4060",
    "sg:province":"QLD",
    "sg:tags":[
        "homoeopath"
    ],
    "wof:name":"Michele Graham",
    "wof:placetype":"venue"
},
  "geometry": {"coordinates":[152.99885559099999,-27.4383182526],"type":"Point"}
}