{
  "type": "Feature",
  "properties": {
    "addr:full":"Shop 106, The Junction Village Kenrick St The Junction NSW 2291",
    "addr:housenumber":"106",
    "addr:postcode":"2291",
    "addr:street":"Kenrick St",
    "iso:country":"AU",
    "sg:address":"Shop 106, The Junction Village Kenrick St",
    "sg:city":"The Junction",
    "sg:classifiers":[
        {
            "category":"Personal",
            "subcategory":"Hair Removal",
            "type":"Services"
        }
    ],
    "sg:phone":"+61 1300 366 310",
    "sg:postcode":"2291",
    "sg:province":"NSW",
    "wof:name":"Australian Laser Clinic",
    "wof:placetype":"venue"
},
  "geometry": {"coordinates":[151.75888061500001,-32.9374313354],"type":"Point"}
}