{
  "type": "Feature",
  "properties": {
    "addr:full":"6 Baker St Gunnedah NSW 2380",
    "addr:housenumber":"6",
    "addr:postcode":"2380",
    "addr:street":"Baker St",
    "iso:country":"AU",
    "sg:address":"6 Baker St",
    "sg:city":"Gunnedah",
    "sg:classifiers":[
        {
            "category":"Home & Garden",
            "subcategory":"Carpets & Floor Coverings",
            "type":"Retail Goods"
        }
    ],
    "sg:phone":"+61 2 6742 2762",
    "sg:postcode":"2380",
    "sg:province":"NSW",
    "sg:tags":[
        "layer",
        "planner"
    ],
    "wof:name":"Mark Stevens",
    "wof:placetype":"venue"
},
  "geometry": {"coordinates":[150.25747680699999,-30.9877338409],"type":"Point"}
}