{
  "type": "Feature",
  "properties": {
    "iso:country":"AU",
    "sg:address":"Suite 1/ 10 Nile St",
    "sg:city":"Coffs Harbour",
    "sg:classifiers":[
        {
            "category":"Professional",
            "subcategory":"Art Services",
            "type":"Services"
        }
    ],
    "sg:phone":"+61 2 6651 4405",
    "sg:postcode":"2450",
    "sg:province":"NSW",
    "sg:tags":[
        "interior",
        "designer"
    ],
    "wof:name":"Natural Habitat Interiors & Design",
    "wof:placetype":"venue"
},
  "geometry": {"coordinates":[153.135605,-30.306282],"type":"Point"}
}