{
  "type": "Feature",
  "properties": {
    "addr:full":"Shop 4 Highland Shopping Centr Target Hill Rd Greenwith SA 5125",
    "addr:housenumber":"shop 4",
    "addr:postcode":"5125",
    "addr:street":"Highland;Hill Rd",
    "iso:country":"AU",
    "sg:address":"Shop 4 Highland Shopping Centr Target Hill Rd",
    "sg:city":"Greenwith",
    "sg:classifiers":[
        {
            "category":"Real Estate",
            "subcategory":"Real Estate Agent",
            "type":"Services"
        }
    ],
    "sg:phone":"+61 8 8289 6660",
    "sg:postcode":"5125",
    "sg:province":"SA",
    "wof:name":"Hooker L.J. Greenwith",
    "wof:placetype":"venue"
},
  "geometry": {"coordinates":[138.714035,-34.772713],"type":"Point"}
}