{
  "type": "Feature",
  "properties": {
    "addr:full":"Rocky Point Kumrumja Pl Weipa QLD 4874",
    "addr:postcode":"4874",
    "addr:street":"Pl",
    "iso:country":"AU",
    "sg:address":"Rocky Point Kumrumja Pl",
    "sg:city":"Weipa",
    "sg:classifiers":[
        {
            "category":"Professional",
            "subcategory":"Management & Consulting",
            "type":"Services"
        }
    ],
    "sg:phone":"+61 7 4069 9066",
    "sg:postcode":"4874",
    "sg:province":"QLD",
    "sg:tags":[
        "consultant",
        "educational"
    ],
    "wof:name":"C.Y.I.F.E.T",
    "wof:placetype":"venue"
},
  "geometry": {"coordinates":[141.87167358400001,-12.6334495544],"type":"Point"}
}