{
  "type": "Feature",
  "properties": {
    "addr:full":"58 Terracotta Drv Nunawading VIC 3131",
    "addr:housenumber":"58",
    "addr:postcode":"3131",
    "addr:street":"Terracotta Drv",
    "iso:country":"AU",
    "sg:address":"58 Terracotta Drv",
    "sg:city":"Nunawading",
    "sg:classifiers":[
        {
            "category":"Building & Trades",
            "subcategory":"Construction",
            "type":"Services"
        }
    ],
    "sg:phone":"+61 3 9875 1000",
    "sg:postcode":"3131",
    "sg:province":"VIC",
    "sg:tags":[
        "industrial",
        "commercial",
        "air conditioning"
    ],
    "wof:name":"York Airconditioning & Heating",
    "wof:placetype":"venue"
},
  "geometry": {"coordinates":[145.165557861,-37.8214263916],"type":"Point"}
}