{
  "type": "Feature",
  "properties": {
    "addr:full":"786- 790 Glenferrie Rd Hawthorn VIC 3122",
    "addr:housenumber":"790",
    "addr:postcode":"3122",
    "addr:street":"Glenferrie Rd",
    "iso:country":"AU",
    "sg:address":"786- 790 Glenferrie Rd",
    "sg:city":"Hawthorn",
    "sg:classifiers":[
        {
            "category":"Home & Garden",
            "subcategory":"Carpets & Floor Coverings",
            "type":"Retail Goods"
        }
    ],
    "sg:phone":"+61 3 9818 0488",
    "sg:postcode":"3122",
    "sg:province":"VIC",
    "wof:name":"Halls Carpets",
    "wof:placetype":"venue"
},
  "geometry": {"coordinates":[145.03639221200001,-37.8179397583],"type":"Point"}
}