{
  "type": "Feature",
  "properties": {
    "iso:country":"AU",
    "sg:address":"Suite 7, 50- 54 Robinson St",
    "sg:city":"Dandenong",
    "sg:classifiers":[
        {
            "category":"Professional",
            "subcategory":"Employment Agencies",
            "type":"Services"
        }
    ],
    "sg:phone":"+61 3 9701 3170",
    "sg:postcode":"3175",
    "sg:province":"VIC",
    "sg:tags":[
        "hire",
        "labour",
        "contractor"
    ],
    "wof:name":"A Taranto",
    "wof:placetype":"venue"
},
  "geometry": {"coordinates":[145.211700439,-37.9842300415],"type":"Point"}
}