{
  "type": "Feature",
  "properties": {
    "addr:full":"23 High St Mansfield VIC 3722",
    "addr:housenumber":"23",
    "addr:postcode":"3722",
    "addr:street":"High St",
    "iso:country":"AU",
    "sg:address":"23 High St",
    "sg:city":"Mansfield",
    "sg:classifiers":[
        {
            "category":"Personal",
            "subcategory":"Hair Removal",
            "type":"Services"
        }
    ],
    "sg:phone":"+61 3 5775 1481",
    "sg:postcode":"3722",
    "sg:province":"VIC",
    "wof:name":"Beautif-Eye",
    "wof:placetype":"venue"
},
  "geometry": {"coordinates":[146.09107971200001,-37.0522842407],"type":"Point"}
}