{
  "type": "Feature",
  "properties": {
    "iso:country":"AU",
    "sg:address":"21 Inverness Ave",
    "sg:city":"Burwood",
    "sg:classifiers":[
        {
            "category":"Building & Trades",
            "subcategory":"Cleaning & Sanitation",
            "type":"Services"
        }
    ],
    "sg:phone":"+61 3 9889 8811",
    "sg:postcode":"3125",
    "sg:province":"VIC",
    "sg:tags":[
        "duct"
    ],
    "wof:name":"Enviro Duct Cleaning",
    "wof:placetype":"venue"
},
  "geometry": {"coordinates":[145.118606567,-37.8455657959],"type":"Point"}
}