{
  "type": "Feature",
  "properties": {
    "addr:full":"PO Box 655 Avalon Beach NSW 2107",
    "addr:postcode":"2107",
    "iso:country":"AU",
    "sg:address":"PO Box 655",
    "sg:city":"Avalon Beach",
    "sg:classifiers":[
        {
            "category":"Banks & Credit Unions",
            "subcategory":"Bank",
            "type":"Services"
        }
    ],
    "sg:phone":"+61 1300 888 839",
    "sg:postcode":"2107",
    "sg:province":"NSW",
    "sg:tags":[
        "broker",
        "mortgage"
    ],
    "wof:name":"Mortgage Gallery, The",
    "wof:placetype":"venue"
},
  "geometry": {"coordinates":[151.33059692399999,-33.6363182068],"type":"Point"}
}