{
  "type": "Feature",
  "properties": {
    "iso:country":"AU",
    "sg:address":"13/ 53 Casua Drv",
    "sg:city":"Stephens",
    "sg:classifiers":[
        {
            "category":"Wholesale",
            "subcategory":"Machinery & Supplies",
            "type":"Manufacturing & Wholesale Goods"
        }
    ],
    "sg:phone":"+61 7 5522 1744",
    "sg:postcode":"4227",
    "sg:province":"QLD",
    "sg:tags":[
        "equipment",
        "hydraulic"
    ],
    "wof:name":"Pirtek Fluid Systems",
    "wof:placetype":"venue"
},
  "geometry": {"coordinates":[153.40762329099999,-28.1016864777],"type":"Point"}
}