{
  "type": "Feature",
  "properties": {
    "iso:country":"AU",
    "sg:address":"2/ 159 Hardgrove Rd",
    "sg:city":"West End (Brisbane)",
    "sg:classifiers":[
        {
            "category":"Organizations",
            "subcategory":"Membership Organization",
            "type":"Services"
        }
    ],
    "sg:phone":"+61 7 3844 3810",
    "sg:postcode":"4101",
    "sg:province":"QLD",
    "sg:tags":[
        "club",
        "bridge"
    ],
    "wof:name":"Peter Munroe",
    "wof:placetype":"venue"
},
  "geometry": {"coordinates":[153.00616455100001,-27.485742569],"type":"Point"}
}