{
  "type": "Feature",
  "properties": {
    "iso:country":"AU",
    "sg:address":"32 Wellington St",
    "sg:city":"North Hobart",
    "sg:classifiers":[
        {
            "category":"Home & Garden",
            "subcategory":"Building Materials",
            "type":"Retail Goods"
        }
    ],
    "sg:phone":"+61 13 31 66",
    "sg:postcode":"7000",
    "sg:province":"TAS",
    "sg:tags":[
        "shutter",
        "roller",
        "grille"
    ],
    "wof:name":"Wormald",
    "wof:placetype":"venue"
},
  "geometry": {"coordinates":[147.31910705600001,-42.8710517883],"type":"Point"}
}