{
  "type": "Feature",
  "properties": {
    "addr:full":"Unit 2a 160 Beechboro Rd South Bayswater WA 6053",
    "addr:housenumber":"unit 2a",
    "addr:postcode":"160;6053",
    "addr:street":"Beechboro Rd South",
    "iso:country":"AU",
    "sg:address":"Unit 2a 160 Beechboro Rd South",
    "sg:city":"Bayswater",
    "sg:classifiers":[
        {
            "category":"Autos & Motor Vehicles",
            "subcategory":"Auto Supplies",
            "type":"Retail Goods"
        }
    ],
    "sg:phone":"+61 8 9272 8300",
    "sg:postcode":"6053",
    "sg:province":"WA",
    "sg:tags":[
        "part",
        "cycles",
        "accessory"
    ],
    "wof:name":"ATV Performance",
    "wof:placetype":"venue"
},
  "geometry": {"coordinates":[115.919029236,-31.901304245],"type":"Point"}
}