{
  "type": "Feature",
  "properties": {
    "addr:full":"414 Gardeners Rd Rosebery NSW 2018",
    "addr:housenumber":"414",
    "addr:postcode":"2018",
    "addr:street":"Gardeners Rd",
    "iso:country":"AU",
    "sg:address":"414 Gardeners Rd",
    "sg:city":"Rosebery",
    "sg:classifiers":[
        {
            "category":"Professional",
            "subcategory":"Engineering",
            "type":"Services"
        }
    ],
    "sg:phone":"+61 2 9669 5000",
    "sg:postcode":"2018",
    "sg:province":"NSW",
    "sg:tags":[
        "electronic",
        "engineer"
    ],
    "wof:name":"Corvette Technologies",
    "wof:placetype":"venue"
},
  "geometry": {"coordinates":[151.19926452600001,-33.9217033386],"type":"Point"}
}