{
  "type": "Feature",
  "properties": {
    "addr:full":"7 Balmoral Ave Strathmore VIC 3041",
    "addr:housenumber":"7",
    "addr:postcode":"3041",
    "addr:street":"Balmoral Ave",
    "iso:country":"AU",
    "sg:address":"7 Balmoral Ave",
    "sg:city":"Strathmore",
    "sg:classifiers":[
        {
            "category":"Home & Garden",
            "subcategory":"Building Materials",
            "type":"Retail Goods"
        }
    ],
    "sg:phone":"+61 407 511 861",
    "sg:postcode":"3041",
    "sg:province":"VIC",
    "sg:tags":[
        "lawn",
        "cutting",
        "maintenance"
    ],
    "wof:name":"Bryan's Home Maintenance",
    "wof:placetype":"venue"
},
  "geometry": {"coordinates":[144.91017150900001,-37.7368431091],"type":"Point"}
}