{
  "type": "Feature",
  "properties": {
    "addr:full":"48- 50 Snapper Island Drv Wonga Beach QLD 4873",
    "addr:housenumber":"50",
    "addr:postcode":"4873",
    "addr:street":"Snapper Island Drv",
    "iso:country":"AU",
    "sg:address":"48- 50 Snapper Island Drv",
    "sg:city":"Wonga Beach",
    "sg:classifiers":[
        {
            "category":"Social Services",
            "subcategory":"Child Care",
            "type":"Services"
        }
    ],
    "sg:phone":"+61 7 4098 7010",
    "sg:postcode":"4873",
    "sg:province":"QLD",
    "wof:name":"Wonga Beach Out of School Hours Care",
    "wof:placetype":"venue"
},
  "geometry": {"coordinates":[145.41192626899999,-16.3460216522],"type":"Point"}
}