{
  "type": "Feature",
  "properties": {
    "iso:country":"AU",
    "sg:address":"Golf Links Rd",
    "sg:city":"Woodenbong",
    "sg:classifiers":[
        {
            "category":"Sports & Exercise",
            "subcategory":"Golf",
            "type":"Entertainment"
        }
    ],
    "sg:phone":"+61 2 6635 1278",
    "sg:postcode":"2476",
    "sg:province":"NSW",
    "sg:tags":[
        "club"
    ],
    "wof:name":"Woodenbong & District Golf Club Ltd",
    "wof:placetype":"venue"
},
  "geometry": {"coordinates":[152.612792969,-28.3889503479],"type":"Point"}
}