{
  "type": "Feature",
  "properties": {
    "iso:country":"AU",
    "sg:address":"470 Church St",
    "sg:city":"North Parramatta",
    "sg:classifiers":[
        {
            "category":"Health Services",
            "subcategory":"Doctor",
            "type":"Services"
        }
    ],
    "sg:phone":"+61 2 9630 4555",
    "sg:postcode":"2151",
    "sg:province":"NSW",
    "sg:tags":[
        "podiatrist"
    ],
    "wof:name":"Jason Van Den Broek",
    "wof:placetype":"venue"
},
  "geometry": {"coordinates":[151.006057739,-33.8049621582],"type":"Point"}
}