{
  "type": "Feature",
  "properties": {
    "addr:full":"24 Hill St Murray Bridge SA 5253",
    "addr:housenumber":"24",
    "addr:postcode":"5253",
    "addr:street":"Hill St",
    "iso:country":"AU",
    "sg:address":"24 Hill St",
    "sg:city":"Murray Bridge",
    "sg:classifiers":[
        {
            "category":"Utilities",
            "type":"Services"
        }
    ],
    "sg:phone":"+61 8 8532 1611",
    "sg:postcode":"5253",
    "sg:province":"SA",
    "sg:tags":[
        "equipment",
        "towing"
    ],
    "wof:name":"Graham Edwards Crash Repairs",
    "wof:placetype":"venue"
},
  "geometry": {"coordinates":[139.27207946799999,-35.1298027039],"type":"Point"}
}