{
  "type": "Feature",
  "properties": {
    "addr:full":"Unit 7/ 3 King Edward Rd Osborne Park WA 6017",
    "addr:postcode":"6017",
    "addr:street":"King Edward Rd",
    "iso:country":"AU",
    "sg:address":"Unit 7/ 3 King Edward Rd",
    "sg:city":"Osborne Park",
    "sg:classifiers":[
        {
            "category":"Professional",
            "subcategory":"Employment Agencies",
            "type":"Services"
        }
    ],
    "sg:phone":"+61 8 9244 8988",
    "sg:postcode":"6017",
    "sg:province":"WA",
    "sg:tags":[
        "provider",
        "internet"
    ],
    "wof:name":"city NEX",
    "wof:placetype":"venue"
},
  "geometry": {"coordinates":[115.804450989,-31.9037075043],"type":"Point"}
}