{
  "type": "Feature",
  "properties": {
    "addr:full":"Shop 6 Bassendean Village Bassendean WA 6054",
    "addr:housenumber":"shop 6",
    "addr:postcode":"6054",
    "addr:street":"Bassendean Village",
    "iso:country":"AU",
    "sg:address":"Shop 6 Bassendean Village",
    "sg:city":"Bassendean",
    "sg:classifiers":[
        {
            "category":"Health Services",
            "subcategory":"Optometrist",
            "type":"Services"
        }
    ],
    "sg:phone":"+61 8 9377 2811",
    "sg:postcode":"6054",
    "sg:province":"WA",
    "wof:name":"Doyle Michael",
    "wof:placetype":"venue"
},
  "geometry": {"coordinates":[115.919090271,-31.9170017242],"type":"Point"}
}