{
  "type": "Feature",
  "properties": {
    "addr:full":"10 Cedar Crs Geraldton WA 6530",
    "addr:housenumber":"10",
    "addr:postcode":"6530",
    "addr:street":"Cedar Crs",
    "iso:country":"AU",
    "sg:address":"10 Cedar Crs",
    "sg:city":"Geraldton",
    "sg:classifiers":[
        {
            "category":"Building & Trades",
            "subcategory":"Construction",
            "type":"Services"
        }
    ],
    "sg:phone":"+61 429 108 424",
    "sg:postcode":"6530",
    "sg:province":"WA",
    "sg:tags":[
        "concrete",
        "contractor"
    ],
    "wof:name":"Peaker Steve & Anna",
    "wof:placetype":"venue"
},
  "geometry": {"coordinates":[114.64060974100001,-28.7494506836],"type":"Point"}
}