{
  "type": "Feature",
  "properties": {
    "addr:full":"6 Newport Crs Port Macquarie NSW 2444",
    "addr:housenumber":"6",
    "addr:postcode":"2444",
    "addr:street":"Newport Crs",
    "iso:country":"AU",
    "sg:address":"6 Newport Crs",
    "sg:city":"Port Macquarie",
    "sg:classifiers":[
        {
            "category":"Health Services",
            "subcategory":"Doctor",
            "type":"Services"
        }
    ],
    "sg:phone":"+61 2 6583 6644",
    "sg:postcode":"2444",
    "sg:province":"NSW",
    "sg:tags":[
        "medical",
        "practitioner"
    ],
    "wof:name":"Dunn Dr Robert H",
    "wof:placetype":"venue"
},
  "geometry": {"coordinates":[152.886932,-31.429293],"type":"Point"}
}