{
  "type": "Feature",
  "properties": {
    "addr:full":"19 Taragala St Cowra NSW 2794",
    "addr:housenumber":"19",
    "addr:postcode":"2794",
    "addr:street":"Taragala St",
    "iso:country":"AU",
    "sg:address":"19 Taragala St",
    "sg:city":"Cowra",
    "sg:classifiers":[
        {
            "category":"Retail",
            "subcategory":"Auto Repair",
            "type":"Services"
        }
    ],
    "sg:phone":"+61 2 6341 9600",
    "sg:postcode":"2794",
    "sg:province":"NSW",
    "sg:tags":[
        "body",
        "builder",
        "motor"
    ],
    "wof:name":"Uni-Lock Pty Ltd",
    "wof:placetype":"venue"
},
  "geometry": {"coordinates":[148.686889648,-33.8466491699],"type":"Point"}
}