{
  "type": "Feature",
  "properties": {
    "addr:full":"4 Nicholson St Hawthorn East VIC 3123",
    "addr:housenumber":"4",
    "addr:postcode":"3123",
    "addr:street":"Nicholson St",
    "iso:country":"AU",
    "sg:address":"4 Nicholson St",
    "sg:city":"Hawthorn East",
    "sg:classifiers":[
        {
            "category":"Professional",
            "subcategory":"Computer Services",
            "type":"Services"
        }
    ],
    "sg:phone":"+61 3 9882 9200",
    "sg:postcode":"3123",
    "sg:province":"VIC",
    "sg:tags":[
        "consultant",
        "system"
    ],
    "wof:name":"Gretal Consulting Pty Ltd",
    "wof:placetype":"venue"
},
  "geometry": {"coordinates":[145.05500793499999,-37.8235778809],"type":"Point"}
}