{
  "type": "Feature",
  "properties": {
    "iso:country":"AU",
    "sg:address":"171 LaTrobe St",
    "sg:city":"Melbourne",
    "sg:classifiers":[
        {
            "category":"Real Estate",
            "subcategory":"Real Estate Agent",
            "type":"Services"
        }
    ],
    "sg:phone":"+61 3 9272 4734",
    "sg:postcode":"3000",
    "sg:province":"VIC",
    "wof:name":"Property Path.com.au Pty Ltd",
    "wof:placetype":"venue"
},
  "geometry": {"coordinates":[144.96664428700001,-37.8088989258],"type":"Point"}
}