{
  "type": "Feature",
  "properties": {
    "addr:full":"170 North St Grafton NSW 2460",
    "addr:housenumber":"170",
    "addr:postcode":"2460",
    "addr:street":"North St",
    "iso:country":"AU",
    "sg:address":"170 North St",
    "sg:city":"Grafton",
    "sg:classifiers":[
        {
            "category":"Sports & Exercise",
            "subcategory":"Gym",
            "type":"Entertainment"
        }
    ],
    "sg:phone":"+61 2 6642 8055",
    "sg:postcode":"2460",
    "sg:province":"NSW",
    "sg:tags":[
        "health",
        "fitness"
    ],
    "wof:name":"Curves Grafton",
    "wof:placetype":"venue"
},
  "geometry": {"coordinates":[152.94747924800001,-29.6723918915],"type":"Point"}
}