{
  "type": "Feature",
  "properties": {
    "addr:full":"14 Linden St Box Hill South VIC 3128",
    "addr:housenumber":"14",
    "addr:postcode":"3128",
    "addr:street":"Linden St",
    "iso:country":"AU",
    "sg:address":"14 Linden St",
    "sg:city":"Box Hill South",
    "sg:classifiers":[
        {
            "category":"Manufacturing",
            "subcategory":"Leather Goods",
            "type":"Manufacturing & Wholesale Goods"
        }
    ],
    "sg:phone":"+61 3 9808 6214",
    "sg:postcode":"3128",
    "sg:province":"VIC",
    "sg:tags":[
        "wholesaler",
        "mfrs"
    ],
    "wof:name":"Jankov Leather Cutters",
    "wof:placetype":"venue"
},
  "geometry": {"coordinates":[145.12161254899999,-37.8378181458],"type":"Point"}
}