{
  "type": "Feature",
  "properties": {
    "addr:full":"29 Landsboro Ave Boondall QLD 4034",
    "addr:housenumber":"29",
    "addr:postcode":"4034",
    "addr:street":"Landsboro Ave",
    "iso:country":"AU",
    "sg:address":"29 Landsboro Ave",
    "sg:city":"Boondall",
    "sg:classifiers":[
        {
            "category":"Building & Trades",
            "subcategory":"Construction",
            "type":"Services"
        }
    ],
    "sg:phone":"+61 7 3865 4450",
    "sg:postcode":"4034",
    "sg:province":"QLD",
    "sg:tags":[
        "welding"
    ],
    "wof:name":"Clarke M A & W A",
    "wof:placetype":"venue"
},
  "geometry": {"coordinates":[153.06373600000001,-27.345432],"type":"Point"}
}