{
  "type": "Feature",
  "properties": {
    "addr:full":"Factory 2, 155 Donald St Brunswick East VIC 3057",
    "addr:housenumber":"155",
    "addr:postcode":"3057",
    "addr:street":"Donald St",
    "iso:country":"AU",
    "sg:address":"Factory 2, 155 Donald St",
    "sg:city":"Brunswick East",
    "sg:classifiers":[
        {
            "category":"Retail",
            "subcategory":"Auto Repair",
            "type":"Services"
        }
    ],
    "sg:phone":"+61 3 9384 1595",
    "sg:postcode":"3057",
    "sg:province":"VIC",
    "sg:tags":[
        "testing",
        "inspection",
        "motor",
        "vehicle"
    ],
    "wof:name":"A & M East Brunswick Auto Care",
    "wof:placetype":"venue"
},
  "geometry": {"coordinates":[144.97825622600001,-37.7590522766],"type":"Point"}
}