{
  "type": "Feature",
  "properties": {
    "addr:full":"PO Box 134 Maclean NSW 2463",
    "addr:postcode":"2463",
    "iso:country":"AU",
    "sg:address":"PO Box 134",
    "sg:city":"Maclean",
    "sg:classifiers":[
        {
            "category":"Building & Trades",
            "subcategory":"Construction",
            "type":"Services"
        }
    ],
    "sg:phone":"+61 2 6645 3079",
    "sg:postcode":"2463",
    "sg:province":"NSW",
    "sg:tags":[
        "tennis court",
        "repair"
    ],
    "wof:name":"Court Pro Services (Nth NSW)",
    "wof:placetype":"venue"
},
  "geometry": {"coordinates":[153.21983337399999,-29.4524097443],"type":"Point"}
}