{
  "type": "Feature",
  "properties": {
    "iso:country":"AU",
    "sg:address":"191 Colchester Rd",
    "sg:city":"Kilsyth",
    "sg:classifiers":[
        {
            "category":"Retail",
            "subcategory":"Driving School",
            "type":"Services"
        }
    ],
    "sg:phone":"+61 3 9723 9077",
    "sg:postcode":"3137",
    "sg:province":"VIC",
    "wof:name":"Paul Mont Driving School",
    "wof:placetype":"venue"
},
  "geometry": {"coordinates":[145.30331420900001,-37.8272590637],"type":"Point"}
}