{
  "type": "Feature",
  "properties": {
    "addr:full":"3 May Pl St Andrews NSW 2566",
    "addr:housenumber":"3",
    "addr:postcode":"2566",
    "addr:street":"May Pl",
    "iso:country":"AU",
    "sg:address":"3 May Pl St",
    "sg:city":"Andrews",
    "sg:classifiers":[
        {
            "category":"Building & Trades",
            "subcategory":"Pest Control",
            "type":"Services"
        }
    ],
    "sg:phone":"+61 2 9820 3499",
    "sg:postcode":"2566",
    "sg:province":"NSW",
    "wof:name":"Envirospray Pest Control",
    "wof:placetype":"venue"
},
  "geometry": {"coordinates":[150.829788208,-34.0280952454],"type":"Point"}
}