{
  "type": "Feature",
  "properties": {
    "iso:country":"AU",
    "sg:address":"66 Riverside Rd",
    "sg:city":"Chipping Norton",
    "sg:classifiers":[
        {
            "category":"Social Services",
            "subcategory":"Retirement Home",
            "type":"Services"
        }
    ],
    "sg:phone":"+61 2 9755 1593",
    "sg:postcode":"2170",
    "sg:province":"NSW",
    "sg:tags":[
        "environmental",
        "consultant",
        "pollution"
    ],
    "wof:name":"Ronnies Environmental Services Pty Ltd",
    "wof:placetype":"venue"
},
  "geometry": {"coordinates":[150.96839904800001,-33.919128418],"type":"Point"}
}