{
  "type": "Feature",
  "properties": {
    "addr:full":"14 Phillip St Mentone VIC 3194",
    "addr:housenumber":"14",
    "addr:postcode":"3194",
    "addr:street":"Phillip St",
    "iso:country":"AU",
    "sg:address":"14 Phillip St",
    "sg:city":"Mentone",
    "sg:classifiers":[
        {
            "category":"Building & Trades",
            "subcategory":"Construction",
            "type":"Services"
        }
    ],
    "sg:phone":"+61 3 9583 2038",
    "sg:postcode":"3194",
    "sg:province":"VIC",
    "sg:tags":[
        "fencing",
        "contractor"
    ],
    "wof:name":"Stone & Steel Traditional Fences",
    "wof:placetype":"venue"
},
  "geometry": {"coordinates":[145.06251525900001,-37.977432251],"type":"Point"}
}