{
  "type": "Feature",
  "properties": {
    "addr:full":"57 Federation Drv Bethania QLD 4205",
    "addr:housenumber":"57",
    "addr:postcode":"4205",
    "addr:street":"Federation Drv",
    "iso:country":"AU",
    "sg:address":"57 Federation Drv",
    "sg:city":"Bethania",
    "sg:classifiers":[
        {
            "category":"Professional",
            "subcategory":"Detective & Security Services",
            "type":"Services"
        }
    ],
    "sg:phone":"+61 7 3299 6660",
    "sg:postcode":"4205",
    "sg:province":"QLD",
    "sg:tags":[
        "equipment",
        "window",
        "doors"
    ],
    "wof:name":"Aussie Blinds",
    "wof:placetype":"venue"
},
  "geometry": {"coordinates":[153.15304565400001,-27.6838054657],"type":"Point"}
}