{
  "type": "Feature",
  "properties": {
    "addr:full":"40 Egerton St Silverwater NSW 2128",
    "addr:housenumber":"40",
    "addr:postcode":"2128",
    "addr:street":"Egerton St",
    "iso:country":"AU",
    "sg:address":"40 Egerton St",
    "sg:city":"Silverwater",
    "sg:classifiers":[
        {
            "category":"Transit Center",
            "subcategory":"Freight",
            "type":"Transportation"
        }
    ],
    "sg:phone":"+61 2 9748 2521",
    "sg:postcode":"2128",
    "sg:province":"NSW",
    "sg:tags":[
        "forklift",
        "truck"
    ],
    "wof:name":"Allforks Hire",
    "wof:placetype":"venue"
},
  "geometry": {"coordinates":[151.049072266,-33.8361206055],"type":"Point"}
}