{
  "type": "Feature",
  "properties": {
    "iso:country":"AU",
    "sg:address":"11- 13 Crescent Rd",
    "sg:city":"Camberwell",
    "sg:classifiers":[
        {
            "category":"Professional",
            "subcategory":"Accounting & Tax Preparation",
            "type":"Services"
        }
    ],
    "sg:phone":"+61 3 9889 3900",
    "sg:postcode":"3124",
    "sg:province":"VIC",
    "sg:tags":[
        "accountant",
        "auditor"
    ],
    "wof:name":"Susan M Constable & Associates",
    "wof:placetype":"venue"
},
  "geometry": {"coordinates":[145.063323975,-37.8358612061],"type":"Point"}
}