{
  "type": "Feature",
  "properties": {
    "addr:full":"298 Gardner Rd Rochedale QLD 4123",
    "addr:housenumber":"298",
    "addr:postcode":"4123",
    "addr:street":"Gardner Rd",
    "iso:country":"AU",
    "sg:address":"298 Gardner Rd",
    "sg:city":"Rochedale",
    "sg:classifiers":[
        {
            "category":"Building & Trades",
            "subcategory":"Construction",
            "type":"Services"
        }
    ],
    "sg:phone":"+61 7 3841 6811",
    "sg:postcode":"4123",
    "sg:province":"QLD",
    "sg:tags":[
        "earth",
        "excavating",
        "moving",
        "contractor"
    ],
    "wof:name":"S L Civil Contracting",
    "wof:placetype":"venue"
},
  "geometry": {"coordinates":[153.11508178700001,-27.5773162842],"type":"Point"}
}