{
  "type": "Feature",
  "properties": {
    "addr:full":"38 Bruce St Mt Waverley VIC 3149",
    "addr:housenumber":"38",
    "addr:postcode":"3149",
    "addr:street":"Bruce St Mt",
    "iso:country":"AU",
    "sg:address":"38 Bruce St",
    "sg:city":"Mt Waverley",
    "sg:classifiers":[
        {
            "category":"Professional",
            "subcategory":"Accounting & Tax Preparation",
            "type":"Services"
        }
    ],
    "sg:phone":"+61 3 9807 6665",
    "sg:postcode":"3149",
    "sg:province":"VIC",
    "sg:tags":[
        "distributor",
        "lock",
        "mfrs"
    ],
    "wof:name":"Access Control Codalok",
    "wof:placetype":"venue"
},
  "geometry": {"coordinates":[145.13397216800001,-37.8810768127],"type":"Point"}
}