{
  "type": "Feature",
  "properties": {
    "addr:full":"73 Brighton Rd Sandgate QLD 4017",
    "addr:housenumber":"73",
    "addr:postcode":"4017",
    "addr:street":"Brighton Rd",
    "iso:country":"AU",
    "sg:address":"73 Brighton Rd",
    "sg:city":"Sandgate",
    "sg:classifiers":[
        {
            "category":"Real Estate",
            "subcategory":"Real Estate Agent",
            "type":"Services"
        }
    ],
    "sg:phone":"+61 7 3269 1001",
    "sg:postcode":"4017",
    "sg:province":"QLD",
    "wof:name":"Decker Shirley Real Estate",
    "wof:placetype":"venue"
},
  "geometry": {"coordinates":[153.068893433,-27.3190898895],"type":"Point"}
}