{
  "type": "Feature",
  "properties": {
    "iso:country":"AU",
    "sg:address":"35 Rival St",
    "sg:city":"Kareela",
    "sg:classifiers":[
        {
            "category":"Manufacturing",
            "subcategory":"Building Materials",
            "type":"Manufacturing & Wholesale Goods"
        }
    ],
    "sg:phone":"+61 2 9528 7100",
    "sg:postcode":"2232",
    "sg:province":"NSW",
    "sg:tags":[
        "equipment",
        "handling"
    ],
    "wof:name":"A-Quip Material Handling",
    "wof:placetype":"venue"
},
  "geometry": {"coordinates":[151.07974243199999,-34.0132675171],"type":"Point"}
}