{
  "type": "Feature",
  "properties": {
    "addr:full":"10 Cabramatta Rd Woolooware NSW 2230",
    "addr:housenumber":"10",
    "addr:postcode":"2230",
    "addr:street":"Cabramatta Rd",
    "iso:country":"AU",
    "sg:address":"10 Cabramatta Rd",
    "sg:city":"Woolooware",
    "sg:classifiers":[
        {
            "category":"Social Services",
            "subcategory":"Child Care",
            "type":"Services"
        }
    ],
    "sg:phone":"+61 1300 289 963",
    "sg:postcode":"2230",
    "sg:province":"NSW",
    "sg:tags":[
        "equipment",
        "supply"
    ],
    "wof:name":"Buzzmeband",
    "wof:placetype":"venue"
},
  "geometry": {"coordinates":[151.13865661599999,-34.0509719849],"type":"Point"}
}