{
  "type": "Feature",
  "properties": {
    "iso:country":"AU",
    "sg:address":"Shop 254 Pitt St",
    "sg:city":"Merrylands",
    "sg:classifiers":[
        {
            "category":"Real Estate",
            "subcategory":"Real Estate Agent",
            "type":"Services"
        }
    ],
    "sg:phone":"+61 2 9897 0655",
    "sg:postcode":"2160",
    "sg:province":"NSW",
    "wof:name":"Elders Real Estate",
    "wof:placetype":"venue"
},
  "geometry": {"coordinates":[150.99159240700001,-33.8362579346],"type":"Point"}
}