{
  "type": "Feature",
  "properties": {
    "addr:full":"PO Box 13 Cundletown NSW 2430",
    "addr:postcode":"2430",
    "iso:country":"AU",
    "sg:address":"PO Box 13",
    "sg:city":"Cundletown",
    "sg:classifiers":[
        {
            "category":"Home & Garden",
            "subcategory":"Carpets & Floor Coverings",
            "type":"Retail Goods"
        }
    ],
    "sg:phone":"+61 428 536 092",
    "sg:postcode":"2430",
    "sg:province":"NSW",
    "sg:tags":[
        "tile",
        "wall",
        "layer"
    ],
    "wof:name":"Roger Else",
    "wof:placetype":"venue"
},
  "geometry": {"coordinates":[152.51597599999999,-31.897129],"type":"Point"}
}