{
  "type": "Feature",
  "properties": {
    "addr:full":"Shop 11 Village Walk 52-54 O&#039;Sullivan Rd Glen Waverley VIC 3150",
    "addr:housenumber":"shop 11;52-54 o",
    "addr:postcode":"3150",
    "addr:street":"Village Walk;Sullivan Rd",
    "iso:country":"AU",
    "sg:address":"Shop 11 Village Walk 52-54 O&#039;Sullivan Rd",
    "sg:city":"Glen Waverley",
    "sg:classifiers":[
        {
            "category":"Banks & Credit Unions",
            "subcategory":"Financial Services",
            "type":"Services"
        }
    ],
    "sg:phone":"+61 3 9886 8088",
    "sg:postcode":"3150",
    "sg:province":"VIC",
    "sg:tags":[
        "coin"
    ],
    "wof:name":"Golden Penny Numismatics",
    "wof:placetype":"venue"
},
  "geometry": {"coordinates":[145.16390991200001,-37.8784980774],"type":"Point"}
}