{
  "type": "Feature",
  "properties": {
    "iso:country":"AU",
    "sg:address":"Suite 14, 265- 271 Pennant Hills Rd",
    "sg:city":"Thornleigh",
    "sg:classifiers":[
        {
            "category":"Banks & Credit Unions",
            "subcategory":"Financial Services",
            "type":"Services"
        }
    ],
    "sg:phone":"+61 1300 880 103",
    "sg:postcode":"2120",
    "sg:province":"NSW",
    "sg:tags":[
        "loan",
        "finance",
        "mortgage"
    ],
    "wof:name":"Caprice Finance Of Australia Pty Ltd",
    "wof:placetype":"venue"
},
  "geometry": {"coordinates":[151.08076477,-33.7313575745],"type":"Point"}
}