{
  "type": "Feature",
  "properties": {
    "iso:country":"AU",
    "sg:address":"Shop 5",
    "sg:city":", Safeway Arcade Lakes Entrance",
    "sg:classifiers":[
        {
            "category":"Wholesale",
            "subcategory":"Seafood",
            "type":"Manufacturing & Wholesale Goods"
        }
    ],
    "sg:phone":"+61 3 5155 4344",
    "sg:postcode":"3909",
    "sg:province":"VIC",
    "sg:tags":[
        "fish"
    ],
    "wof:name":"Leftrade Omega 3",
    "wof:placetype":"venue"
},
  "geometry": {"coordinates":[148.00227355999999,-37.8771514893],"type":"Point"}
}