{
  "type": "Feature",
  "properties": {
    "iso:country":"AU",
    "sg:address":"60 Factory Rd",
    "sg:city":"Yannathan",
    "sg:classifiers":[
        {
            "category":"Farming",
            "subcategory":"Farm",
            "type":"Manufacturing & Wholesale Goods"
        }
    ],
    "sg:phone":"+61 3 5997 8261",
    "sg:postcode":"3981",
    "sg:province":"VIC",
    "sg:tags":[
        "farmer"
    ],
    "wof:name":"Gardiner R G",
    "wof:placetype":"venue"
},
  "geometry": {"coordinates":[145.64457702600001,-38.2354660034],"type":"Point"}
}