{
  "type": "Feature",
  "properties": {
    "iso:country":"AU",
    "sg:address":"16 Elm Park Drv",
    "sg:city":"Hoppers Crossing",
    "sg:classifiers":[
        {
            "category":"Professional",
            "type":"Services"
        }
    ],
    "sg:phone":"+61 3 8742 7703",
    "sg:postcode":"3029",
    "sg:province":"VIC",
    "sg:tags":[
        "transport"
    ],
    "wof:name":"Braye Transport",
    "wof:placetype":"venue"
},
  "geometry": {"coordinates":[144.720459,-37.870522],"type":"Point"}
}