{
  "type": "Feature",
  "properties": {
    "iso:country":"AU",
    "sg:address":"18 Hulme Drv",
    "sg:city":"Wangaratta",
    "sg:classifiers":[
        {
            "category":"Building & Trades",
            "subcategory":"Construction",
            "type":"Services"
        }
    ],
    "sg:phone":"+61 3 5721 4637",
    "sg:postcode":"3677",
    "sg:province":"VIC",
    "sg:tags":[
        "contractor"
    ],
    "wof:name":"Brownles Nominees Pty Ltd",
    "wof:placetype":"venue"
},
  "geometry": {"coordinates":[146.304595947,-36.3444709778],"type":"Point"}
}