{
  "type": "Feature",
  "properties": {
    "addr:full":"55 Wellington Rd Mt Barker SA 5251",
    "addr:housenumber":"55",
    "addr:postcode":"5251",
    "addr:street":"Wellington Rd",
    "iso:country":"AU",
    "sg:address":"55 Wellington Rd",
    "sg:city":"Mt Barker",
    "sg:classifiers":[
        {
            "category":"Retail",
            "subcategory":"Auto Repair",
            "type":"Services"
        }
    ],
    "sg:phone":"+61 8 8391 2877",
    "sg:postcode":"5251",
    "sg:province":"SA",
    "sg:tags":[
        "repairer",
        "motor",
        "engineer"
    ],
    "wof:name":"Automotive Doctor",
    "wof:placetype":"venue"
},
  "geometry": {"coordinates":[138.86575317399999,-35.0793304443],"type":"Point"}
}