{
  "type": "Feature",
  "properties": {
    "addr:full":"PO Box 1560 Busselton WA 6280",
    "addr:postcode":"6280",
    "iso:country":"AU",
    "sg:address":"PO Box 1560",
    "sg:city":"Busselton",
    "sg:classifiers":[
        {
            "category":"Home & Garden",
            "subcategory":"Carpets & Floor Coverings",
            "type":"Retail Goods"
        }
    ],
    "sg:phone":"+61 8 9753 1235",
    "sg:postcode":"6280",
    "sg:province":"WA",
    "sg:tags":[
        "wood"
    ],
    "wof:name":"Fine Timber Floors",
    "wof:placetype":"venue"
},
  "geometry": {"coordinates":[115.344818115,-33.652141571],"type":"Point"}
}