{
  "type": "Feature",
  "properties": {
    "addr:full":"9 Regnans Ave Endeavour Hills VIC 3802",
    "addr:housenumber":"9",
    "addr:postcode":"3802",
    "addr:street":"Regnans Ave",
    "iso:country":"AU",
    "sg:address":"9 Regnans Ave",
    "sg:city":"Endeavour Hills",
    "sg:classifiers":[
        {
            "category":"Shopping",
            "subcategory":"Computers & Home Electronics",
            "type":"Retail Goods"
        }
    ],
    "sg:phone":"+61 411 116 636",
    "sg:postcode":"3802",
    "sg:province":"VIC",
    "sg:tags":[
        "small",
        "equipment",
        "business"
    ],
    "wof:name":"Chalot Micro Systems",
    "wof:placetype":"venue"
},
  "geometry": {"coordinates":[145.240997314,-37.970539093],"type":"Point"}
}