{
  "type": "Feature",
  "properties": {
    "addr:full":"36 Henderson Rd Clayton North VIC 3168",
    "addr:housenumber":"36",
    "addr:postcode":"3168",
    "addr:street":"Henderson Rd",
    "iso:country":"AU",
    "sg:address":"36 Henderson Rd",
    "sg:city":"Clayton North",
    "sg:classifiers":[
        {
            "category":"Manufacturing",
            "subcategory":"Tools & Machinery",
            "type":"Manufacturing & Wholesale Goods"
        }
    ],
    "sg:phone":"+61 3 9562 2515",
    "sg:postcode":"3168",
    "sg:province":"VIC",
    "sg:tags":[
        "machine",
        "knife"
    ],
    "wof:name":"Blakeley W H Industrial Knives Pty Ltd",
    "wof:placetype":"venue"
},
  "geometry": {"coordinates":[145.144897461,-37.9135894775],"type":"Point"}
}