{
  "type": "Feature",
  "properties": {
    "addr:full":"Epping Drv Frenchs Forest NSW 2086",
    "addr:postcode":"2086",
    "addr:street":"Epping Drv",
    "iso:country":"AU",
    "sg:address":"Epping Drv",
    "sg:city":"Frenchs Forest",
    "sg:classifiers":[
        {
            "category":"Professional",
            "subcategory":"Art Services",
            "type":"Services"
        }
    ],
    "sg:phone":"+61 2 9452 1273",
    "sg:postcode":"2086",
    "sg:province":"NSW",
    "sg:tags":[
        "interior",
        "designer"
    ],
    "wof:name":"Greg Sadler Of Chatswood",
    "wof:placetype":"venue"
},
  "geometry": {"coordinates":[151.23263549800001,-33.7469444275],"type":"Point"}
}