{
  "type": "Feature",
  "properties": {
    "addr:full":"1 Steere St Bridgetown WA 6255",
    "addr:housenumber":"1",
    "addr:postcode":"6255",
    "addr:street":"Steere St",
    "iso:country":"AU",
    "sg:address":"1 Steere St",
    "sg:city":"Bridgetown",
    "sg:classifiers":[
        {
            "category":"Government",
            "subcategory":"Department Of Motor Vehicles",
            "type":"Public Place"
        }
    ],
    "sg:phone":"+61 8 9761 1555",
    "sg:postcode":"6255",
    "sg:province":"WA",
    "sg:tags":[
        "organisation",
        "local"
    ],
    "wof:name":"Bridgetown-Greenbushes Shire Of",
    "wof:placetype":"venue"
},
  "geometry": {"coordinates":[116.13749694800001,-33.9579925537],"type":"Point"}
}