{
  "type": "Feature",
  "properties": {
    "addr:full":"132 Hunter La Hornsby NSW 2077",
    "addr:housenumber":"132",
    "addr:postcode":"2077",
    "addr:street":"Hunter La",
    "iso:country":"AU",
    "sg:address":"132 Hunter La",
    "sg:city":"Hornsby",
    "sg:classifiers":[
        {
            "category":"Retail",
            "subcategory":"Auto Repair",
            "type":"Services"
        }
    ],
    "sg:phone":"+61 2 9477 7114",
    "sg:postcode":"2077",
    "sg:province":"NSW",
    "sg:tags":[
        "transmission",
        "automotive",
        "car"
    ],
    "sg:website":"http://www.boxdr.com.au",
    "wof:name":"Transmission Physician",
    "wof:placetype":"venue"
},
  "geometry": {"coordinates":[151.10096740700001,-33.6988945007],"type":"Point"}
}