{
  "type": "Feature",
  "properties": {
    "addr:full":"755 High St Armadale VIC 3143",
    "addr:housenumber":"755",
    "addr:postcode":"3143",
    "addr:street":"High St",
    "iso:country":"AU",
    "sg:address":"755 High St",
    "sg:city":"Armadale",
    "sg:classifiers":[
        {
            "category":"Shopping",
            "subcategory":"Antiques",
            "type":"Retail Goods"
        }
    ],
    "sg:phone":"+61 3 9500 0699",
    "sg:postcode":"3143",
    "sg:province":"VIC",
    "wof:name":"Brett Manley Antiques",
    "wof:placetype":"venue"
},
  "geometry": {"coordinates":[145.012939453,-37.8543395996],"type":"Point"}
}