{
  "type": "Feature",
  "properties": {
    "addr:full":"506 Glynburn Rd Burnside SA 5066",
    "addr:housenumber":"506",
    "addr:postcode":"5066",
    "addr:street":"Glynburn Rd",
    "iso:country":"AU",
    "sg:address":"506 Glynburn Rd",
    "sg:city":"Burnside",
    "sg:classifiers":[
        {
            "category":"Retail",
            "subcategory":"Veterinary Services",
            "type":"Services"
        }
    ],
    "sg:phone":"+61 8 8364 3308",
    "sg:postcode":"5066",
    "sg:province":"SA",
    "sg:tags":[
        "surgeon"
    ],
    "wof:name":"Burnside Veterinary Centre",
    "wof:placetype":"venue"
},
  "geometry": {"coordinates":[138.66026306099999,-34.9368743896],"type":"Point"}
}