{
  "type": "Feature",
  "properties": {
    "addr:full":"5 Paul Crt Jimboomba QLD 4280",
    "addr:housenumber":"5",
    "addr:postcode":"4280",
    "addr:street":"Paul Crt",
    "iso:country":"AU",
    "sg:address":"5 Paul Crt",
    "sg:city":"Jimboomba",
    "sg:classifiers":[
        {
            "category":"Home & Garden",
            "subcategory":"Building Materials",
            "type":"Retail Goods"
        }
    ],
    "sg:phone":"+61 7 5547 7441",
    "sg:postcode":"4280",
    "sg:province":"QLD",
    "sg:tags":[
        "supply"
    ],
    "wof:name":"Get Plastered Supplies",
    "wof:placetype":"venue"
},
  "geometry": {"coordinates":[153.03019699999999,-27.825426],"type":"Point"}
}