{
  "type": "Feature",
  "properties": {
    "iso:country":"AU",
    "sg:address":"Suite 56, Levwl 11, 88 Pitt St",
    "sg:city":"Sydney",
    "sg:classifiers":[
        {
            "category":"Banks & Credit Unions",
            "subcategory":"Financial Services",
            "type":"Services"
        }
    ],
    "sg:phone":"+61 2 9241 7002",
    "sg:postcode":"2000",
    "sg:province":"NSW",
    "sg:tags":[
        "planning"
    ],
    "wof:name":"Millennium Asset Management Ltd",
    "wof:placetype":"venue"
},
  "geometry": {"coordinates":[151.208694458,-33.8668785095],"type":"Point"}
}