{
  "type": "Feature",
  "properties": {
    "addr:full":"289 Flinders La Melbourne VIC 3000",
    "addr:housenumber":"289",
    "addr:postcode":"3000",
    "addr:street":"Flinders La",
    "iso:country":"AU",
    "sg:address":"289 Flinders La",
    "sg:city":"Melbourne",
    "sg:classifiers":[
        {
            "category":"Real Estate",
            "subcategory":"Architect",
            "type":"Services"
        }
    ],
    "sg:phone":"+61 3 9639 5838",
    "sg:postcode":"3000",
    "sg:province":"VIC",
    "wof:name":"Michael Rahill Architects",
    "wof:placetype":"venue"
},
  "geometry": {"coordinates":[144.96473693900001,-37.8172607422],"type":"Point"}
}