{
  "type": "Feature",
  "properties": {
    "iso:country":"AU",
    "sg:address":"32 Abbott Ave",
    "sg:city":"Sefton",
    "sg:classifiers":[
        {
            "category":"Education",
            "subcategory":"Dance Studio",
            "type":"Public Place"
        }
    ],
    "sg:phone":"+61 2 9786 7539",
    "sg:postcode":"2162",
    "sg:province":"NSW",
    "sg:tags":[
        "venue",
        "tuition"
    ],
    "wof:name":"esp. australia productions",
    "wof:placetype":"venue"
},
  "geometry": {"coordinates":[151.00875854500001,-33.877872467],"type":"Point"}
}