{
  "type": "Feature",
  "properties": {
    "addr:full":"40 Bonavista Crs Doonan QLD 4562",
    "addr:housenumber":"40",
    "addr:postcode":"4562",
    "addr:street":"Bonavista Crs",
    "iso:country":"AU",
    "sg:address":"40 Bonavista Crs",
    "sg:city":"Doonan",
    "sg:classifiers":[
        {
            "category":"Building & Trades",
            "subcategory":"Construction",
            "type":"Services"
        }
    ],
    "sg:phone":"+61 410 402 541",
    "sg:postcode":"4562",
    "sg:province":"QLD",
    "sg:tags":[
        "concrete",
        "paving"
    ],
    "wof:name":"Sidwell Concreting Pty Ltd",
    "wof:placetype":"venue"
},
  "geometry": {"coordinates":[153.00785827600001,-26.4438400269],"type":"Point"}
}