{
  "type": "Feature",
  "properties": {
    "addr:full":"Level 5, 431 - 439 King William St Adelaide SA 5000",
    "addr:housenumber":"431 439",
    "addr:postcode":"5000",
    "addr:street":"King William St",
    "iso:country":"AU",
    "sg:address":"Level 5, 431 - 439 King William St",
    "sg:city":"Adelaide",
    "sg:classifiers":[
        {
            "category":"Education",
            "subcategory":"Special Training",
            "type":"Public Place"
        }
    ],
    "sg:phone":"+61 8 8212 8533",
    "sg:postcode":"5000",
    "sg:province":"SA",
    "sg:tags":[
        "development"
    ],
    "wof:name":"Invisage",
    "wof:placetype":"venue"
},
  "geometry": {"coordinates":[138.60075378400001,-34.9353904724],"type":"Point"}
}