{
  "type": "Feature",
  "properties": {
    "iso:country":"AU",
    "sg:address":"Unit 5, 30 Clarke St",
    "sg:city":"South Melbourne",
    "sg:classifiers":[
        {
            "category":"Professional",
            "subcategory":"Employment Agencies",
            "type":"Services"
        }
    ],
    "sg:phone":"+61 3 9680 8666",
    "sg:postcode":"3205",
    "sg:province":"VIC",
    "sg:tags":[
        "broker",
        "custom"
    ],
    "wof:name":"Rocke E A Customs Services",
    "wof:placetype":"venue"
},
  "geometry": {"coordinates":[144.958603,-37.826054],"type":"Point"}
}