{
  "type": "Feature",
  "properties": {
    "addr:full":"Cnr Stamford & Moggil Rds Indooroopilly QLD 4068",
    "addr:postcode":"4068",
    "addr:street":"Cnr",
    "iso:country":"AU",
    "sg:address":"Cnr Stamford & Moggil Rds",
    "sg:city":"Indooroopilly",
    "sg:classifiers":[
        {
            "category":"Fast Food",
            "type":"Food & Drink"
        }
    ],
    "sg:phone":"+61 7 3378 7810",
    "sg:postcode":"4068",
    "sg:province":"QLD",
    "sg:tags":[
        "away",
        "take"
    ],
    "wof:name":"Red Rooster",
    "wof:placetype":"venue"
},
  "geometry": {"coordinates":[152.97383117699999,-27.4982738495],"type":"Point"}
}