{
  "type": "Feature",
  "properties": {
    "iso:country":"AU",
    "sg:address":"PO Box 6289",
    "sg:city":"Penrith",
    "sg:classifiers":[
        {
            "category":"Building & Trades",
            "subcategory":"Landscaping Services",
            "type":"Services"
        }
    ],
    "sg:phone":"+61 411 726 057",
    "sg:postcode":"2750",
    "sg:province":"NSW",
    "sg:tags":[
        "inspection"
    ],
    "wof:name":"M&C Saunders Carpentry",
    "wof:placetype":"venue"
},
  "geometry": {"coordinates":[150.698562622,-33.753818512],"type":"Point"}
}