{
  "type": "Feature",
  "properties": {
    "addr:full":"6/ 14 Atbara St West Kalgoorlie WA 6430",
    "addr:housenumber":"/ 14",
    "addr:postcode":"6430",
    "addr:street":"Atbara St West",
    "iso:country":"AU",
    "sg:address":"6/ 14 Atbara St",
    "sg:city":"West Kalgoorlie",
    "sg:classifiers":[
        {
            "category":"Utilities",
            "subcategory":"Telephone",
            "type":"Services"
        }
    ],
    "sg:phone":"+61 8 9021 6960",
    "sg:postcode":"6430",
    "sg:province":"WA",
    "sg:tags":[
        "installation",
        "system",
        "maintenance"
    ],
    "wof:name":"Goldfields Telephone Service",
    "wof:placetype":"venue"
},
  "geometry": {"coordinates":[121.440483093,-30.7883777618],"type":"Point"}
}