{
  "type": "Feature",
  "properties": {
    "addr:full":"4 Ernest Crt Portsea VIC 3944",
    "addr:housenumber":"4",
    "addr:postcode":"3944",
    "addr:street":"Ernest Crt",
    "iso:country":"AU",
    "sg:address":"4 Ernest Crt",
    "sg:city":"Portsea",
    "sg:classifiers":[
        {
            "category":"Sports & Exercise",
            "subcategory":"Sports Center",
            "type":"Entertainment"
        }
    ],
    "sg:phone":"+61 3 5984 5058",
    "sg:postcode":"3944",
    "sg:province":"VIC",
    "sg:tags":[
        "coach",
        "tennis"
    ],
    "wof:name":"Crozier Peter",
    "wof:placetype":"venue"
},
  "geometry": {"coordinates":[144.72161865199999,-38.3301582336],"type":"Point"}
}