{
  "type": "Feature",
  "properties": {
    "addr:full":"16 Queens Ave Caulfield East VIC 3145",
    "addr:housenumber":"16",
    "addr:postcode":"3145",
    "addr:street":"Queens Ave",
    "iso:country":"AU",
    "sg:address":"16 Queens Ave",
    "sg:city":"Caulfield East",
    "sg:classifiers":[
        {
            "category":"Building & Trades",
            "subcategory":"Landscaping Services",
            "type":"Services"
        }
    ],
    "sg:phone":"+61 3 9505 6363",
    "sg:postcode":"3145",
    "sg:province":"VIC",
    "sg:tags":[
        "designer",
        "landscape",
        "contractor"
    ],
    "wof:name":"Van Leeuwen Green Horticultural Services Pty Ltd",
    "wof:placetype":"venue"
},
  "geometry": {"coordinates":[145.04335022000001,-37.8854827881],"type":"Point"}
}