{
  "type": "Feature",
  "properties": {
    "addr:full":"124 Kent Rd Pascoe Vale VIC 3044",
    "addr:housenumber":"124",
    "addr:postcode":"3044",
    "addr:street":"Kent Rd",
    "iso:country":"AU",
    "sg:address":"124 Kent Rd",
    "sg:city":"Pascoe Vale",
    "sg:classifiers":[
        {
            "category":"Wholesale",
            "subcategory":"Medical Equipment & Supplies",
            "type":"Manufacturing & Wholesale Goods"
        }
    ],
    "sg:phone":"+61 1300 550 836",
    "sg:postcode":"3044",
    "sg:province":"VIC",
    "sg:tags":[
        "aids",
        "hearing"
    ],
    "wof:name":"Sound Advice Hearing Consultants",
    "wof:placetype":"venue"
},
  "geometry": {"coordinates":[144.939361572,-37.7198867798],"type":"Point"}
}