{
  "type": "Feature",
  "properties": {
    "iso:country":"AU",
    "sg:address":"28-30 Silkwood Rse",
    "sg:city":"Carrum Downs",
    "sg:classifiers":[
        {
            "category":"Building & Trades",
            "subcategory":"Plumbing",
            "type":"Services"
        }
    ],
    "sg:phone":"+61 3 9770 8416",
    "sg:postcode":"3201",
    "sg:province":"VIC",
    "sg:tags":[
        "plumber",
        "gasfitters"
    ],
    "wof:name":"Close Commercial Services",
    "wof:placetype":"venue"
},
  "geometry": {"coordinates":[145.163284,-38.101925],"type":"Point"}
}