{
  "type": "Feature",
  "properties": {
    "iso:country":"AU",
    "sg:address":"Cresser St",
    "sg:city":"Altona North",
    "sg:classifiers":[
        {
            "category":"Education",
            "subcategory":"School",
            "type":"Public Place"
        }
    ],
    "sg:phone":"+61 3 9391 4233",
    "sg:postcode":"3025",
    "sg:province":"VIC",
    "sg:tags":[
        "state",
        "except",
        "nsw"
    ],
    "wof:name":"Altona North Primary",
    "wof:placetype":"venue"
},
  "geometry": {"coordinates":[144.847916,-37.836636],"type":"Point"}
}