{
  "type": "Feature",
  "properties": {
    "addr:full":"795 New South Head Rd Rose Bay NSW 2029",
    "addr:housenumber":"795",
    "addr:postcode":"2029",
    "addr:street":"New South Head Rd",
    "iso:country":"AU",
    "sg:address":"795 New South Head Rd",
    "sg:city":"Rose Bay",
    "sg:classifiers":[
        {
            "category":"Personal",
            "subcategory":"Beauty Salon",
            "type":"Services"
        }
    ],
    "sg:phone":"+61 2 9371 5650",
    "sg:postcode":"2029",
    "sg:province":"NSW",
    "sg:tags":[
        "hairdresser"
    ],
    "wof:name":"John of Rose Bay",
    "wof:placetype":"venue"
},
  "geometry": {"coordinates":[151.26954650900001,-33.8699645996],"type":"Point"}
}