{
  "type": "Feature",
  "properties": {
    "iso:country":"AU",
    "sg:address":"169 Main St",
    "sg:city":"Bacchus Marsh",
    "sg:classifiers":[
        {
            "category":"Food & Beverages",
            "subcategory":"Bakery",
            "type":"Retail Goods"
        }
    ],
    "sg:phone":"+61 3 5367 4127",
    "sg:postcode":"3340",
    "sg:province":"VIC",
    "sg:tags":[
        "baker"
    ],
    "wof:name":"Sunflour Hotbread",
    "wof:placetype":"venue"
},
  "geometry": {"coordinates":[144.43902600000001,-37.676113],"type":"Point"}
}