{
  "type": "Feature",
  "properties": {
    "iso:country":"AU",
    "sg:address":"21- 39 Bundy Drv",
    "sg:city":"Melton South",
    "sg:classifiers":[
        {
            "category":"Autos & Motor Vehicles",
            "subcategory":"Automobile Sales",
            "type":"Retail Goods"
        }
    ],
    "sg:phone":"+61 3 9746 9244",
    "sg:postcode":"3338",
    "sg:province":"VIC",
    "sg:tags":[
        "equipment",
        "trailer"
    ],
    "wof:name":"Tag-A-Long Machinery Trailers Pty Ltd",
    "wof:placetype":"venue"
},
  "geometry": {"coordinates":[144.595245,-37.701923],"type":"Point"}
}