{
  "type": "Feature",
  "properties": {
    "addr:full":"21- 39 Bundy Drv Melton South VIC 3338",
    "addr:housenumber":"39",
    "addr:postcode":"3338",
    "addr:street":"Bundy Drv",
    "iso:country":"AU",
    "sg:address":"21- 39 Bundy Drv",
    "sg:city":"Melton South",
    "sg:classifiers":[
        {
            "category":"Autos & Motor Vehicles",
            "subcategory":"Automobile Sales",
            "type":"Retail Goods"
        }
    ],
    "sg:phone":"+61 3 9746 9244",
    "sg:postcode":"3338",
    "sg:province":"VIC",
    "sg:tags":[
        "equipment",
        "trailer"
    ],
    "wof:name":"Tag-A-Long Machinery Trailers Pty Ltd",
    "wof:placetype":"venue"
},
  "geometry": {"coordinates":[144.59524500000001,-37.701923],"type":"Point"}
}