{
  "type": "Feature",
  "properties": {
    "addr:full":"1/ 3 Machinery Drv Tweed Heads South NSW 2486",
    "addr:housenumber":"/ 3",
    "addr:postcode":"2486",
    "addr:street":"Machinery Drv",
    "iso:country":"AU",
    "sg:address":"1/ 3 Machinery Drv",
    "sg:city":"Tweed Heads South",
    "sg:classifiers":[
        {
            "category":"Shopping",
            "subcategory":"Crafts & Fabrics",
            "type":"Retail Goods"
        }
    ],
    "sg:phone":"+61 7 5524 4818",
    "sg:postcode":"2486",
    "sg:province":"NSW",
    "sg:tags":[
        "supply"
    ],
    "wof:name":"Coastal Art & Papercrafts",
    "wof:placetype":"venue"
},
  "geometry": {"coordinates":[153.542526245,-28.2027835846],"type":"Point"}
}