{
  "type": "Feature",
  "properties": {
    "addr:full":"Cnr Windsor & Boundary Rds Vineyard NSW 2765",
    "addr:postcode":"2765",
    "addr:street":"Cnr",
    "iso:country":"AU",
    "sg:address":"Cnr Windsor & Boundary Rds",
    "sg:city":"Vineyard",
    "sg:classifiers":[
        {
            "category":"Food & Beverages",
            "subcategory":"Liquor & Beverages",
            "type":"Retail Goods"
        }
    ],
    "sg:phone":"+61 2 9627 2281",
    "sg:postcode":"2765",
    "sg:province":"NSW",
    "sg:tags":[
        "store"
    ],
    "wof:name":"Liquor Stax Australia Pty Ltd",
    "wof:placetype":"venue"
},
  "geometry": {"coordinates":[150.86164855999999,-33.6487121582],"type":"Point"}
}