{
  "type": "Feature",
  "properties": {
    "addr:full":"Shed 3, 6 Combarton St Brendale QLD 4500",
    "addr:housenumber":"6",
    "addr:postcode":"4500",
    "addr:street":"Combarton St",
    "iso:country":"AU",
    "sg:address":"Shed 3, 6 Combarton St",
    "sg:city":"Brendale",
    "sg:classifiers":[
        {
            "category":"Wholesale",
            "subcategory":"Metals & Minerals",
            "type":"Manufacturing & Wholesale Goods"
        }
    ],
    "sg:phone":"+61 7 3205 2966",
    "sg:postcode":"4500",
    "sg:province":"QLD",
    "sg:tags":[
        "steel",
        "stainless",
        "product",
        "equipment"
    ],
    "wof:name":"A.I.G. All Industries Grating",
    "wof:placetype":"venue"
},
  "geometry": {"coordinates":[152.97499084500001,-27.3198318481],"type":"Point"}
}