{
  "type": "Feature",
  "properties": {
    "addr:full":"7 Mulloway Crt Sorrento WA 6020",
    "addr:housenumber":"7",
    "addr:postcode":"6020",
    "addr:street":"Mulloway Crt",
    "iso:country":"AU",
    "sg:address":"7 Mulloway Crt",
    "sg:city":"Sorrento",
    "sg:classifiers":[
        {
            "category":"Personal",
            "subcategory":"Beauty Salon",
            "type":"Services"
        }
    ],
    "sg:phone":"+61 8 9448 3198",
    "sg:postcode":"6020",
    "sg:province":"WA",
    "wof:name":"Cloud Nine Beauty Therapy",
    "wof:placetype":"venue"
},
  "geometry": {"coordinates":[115.75739288299999,-31.8193912506],"type":"Point"}
}