{
  "type": "Feature",
  "properties": {
    "addr:full":"146 Norton St Leichhardt NSW 2040",
    "addr:housenumber":"146",
    "addr:postcode":"2040",
    "addr:street":"Norton St",
    "iso:country":"AU",
    "sg:address":"146 Norton St",
    "sg:city":"Leichhardt",
    "sg:classifiers":[
        {
            "category":"Restaurant",
            "type":"Food & Drink"
        }
    ],
    "sg:phone":"+61 2 9569 1600",
    "sg:postcode":"2040",
    "sg:province":"NSW",
    "wof:name":"Addie Thai Restaurant",
    "wof:placetype":"venue"
},
  "geometry": {"coordinates":[151.156723,-33.882381],"type":"Point"}
}