{
  "type": "Feature",
  "properties": {
    "addr:full":"10A Field St Caulfield South VIC 3162",
    "addr:housenumber":"10a",
    "addr:postcode":"3162",
    "addr:street":"Field St",
    "iso:country":"AU",
    "sg:address":"10A Field St",
    "sg:city":"Caulfield South",
    "sg:classifiers":[
        {
            "category":"Education",
            "subcategory":"Special Training",
            "type":"Public Place"
        }
    ],
    "sg:phone":"+61 3 9569 2686",
    "sg:postcode":"3162",
    "sg:province":"VIC",
    "sg:tags":[
        "development"
    ],
    "wof:name":"TLC Training",
    "wof:placetype":"venue"
},
  "geometry": {"coordinates":[145.029785156,-37.8885955811],"type":"Point"}
}