{
  "type": "Feature",
  "properties": {
    "addr:full":"14 Turley St Raceview QLD 4305",
    "addr:housenumber":"14",
    "addr:postcode":"4305",
    "addr:street":"Turley St",
    "iso:country":"AU",
    "sg:address":"14 Turley St",
    "sg:city":"Raceview",
    "sg:classifiers":[
        {
            "category":"Retail",
            "subcategory":"Auto Repair",
            "type":"Services"
        }
    ],
    "sg:phone":"+61 7 3202 2177",
    "sg:postcode":"4305",
    "sg:province":"QLD",
    "sg:tags":[
        "beater",
        "painter",
        "panel"
    ],
    "wof:name":"Crisp Panel & Paint",
    "wof:placetype":"venue"
},
  "geometry": {"coordinates":[152.760055542,-27.6341209412],"type":"Point"}
}