{
  "type": "Feature",
  "properties": {
    "addr:full":"29 Jefferson Drv Marangaroo WA 6064",
    "addr:housenumber":"29",
    "addr:postcode":"6064",
    "addr:street":"Jefferson Drv Marangaroo",
    "iso:country":"AU",
    "sg:address":"29 Jefferson Drv",
    "sg:city":"Marangaroo",
    "sg:classifiers":[
        {
            "category":"Home & Garden",
            "subcategory":"Building Materials",
            "type":"Retail Goods"
        }
    ],
    "sg:phone":"+61 405 763 457",
    "sg:postcode":"6064",
    "sg:province":"WA",
    "sg:tags":[
        "plaster",
        "plasterboard",
        "supply"
    ],
    "wof:name":"Daz Plastering",
    "wof:placetype":"venue"
},
  "geometry": {"coordinates":[115.846557617,-31.8333320618],"type":"Point"}
}