{
  "type": "Feature",
  "properties": {
    "addr:full":"Shop 15/ 20 Bungan Mona Vale NSW 2103",
    "addr:housenumber":"shop 15 / 20",
    "addr:postcode":"2103",
    "addr:street":"Bungan",
    "iso:country":"AU",
    "sg:address":"Shop 15/ 20 Bungan",
    "sg:city":"Mona Vale",
    "sg:classifiers":[
        {
            "category":"Shopping",
            "subcategory":"Computers & Home Electronics",
            "type":"Retail Goods"
        }
    ],
    "sg:phone":"+61 2 9997 3666",
    "sg:postcode":"2103",
    "sg:province":"NSW",
    "sg:tags":[
        "hardware",
        "equipment"
    ],
    "wof:name":"H B Wireless",
    "wof:placetype":"venue"
},
  "geometry": {"coordinates":[151.301605225,-33.6777687073],"type":"Point"}
}