{
  "type": "Feature",
  "properties": {
    "iso:country":"AU",
    "sg:address":"3 Rowsell Crt",
    "sg:city":"Mt Warren Park",
    "sg:classifiers":[
        {
            "category":"Health Services",
            "subcategory":"Health Practitioner",
            "type":"Services"
        }
    ],
    "sg:phone":"+61 7 3805 4151",
    "sg:postcode":"4207",
    "sg:province":"QLD",
    "sg:tags":[
        "naturopath"
    ],
    "wof:name":"Dernedde Catherine",
    "wof:placetype":"venue"
},
  "geometry": {"coordinates":[153.20028686500001,-27.726266861],"type":"Point"}
}