{
  "type": "Feature",
  "properties": {
    "addr:full":"47 George St Granville NSW 2142",
    "addr:housenumber":"47",
    "addr:postcode":"2142",
    "addr:street":"George St",
    "iso:country":"AU",
    "sg:address":"47 George St",
    "sg:city":"Granville",
    "sg:classifiers":[
        {
            "category":"Wholesale",
            "subcategory":"Painting Supplies",
            "type":"Manufacturing & Wholesale Goods"
        }
    ],
    "sg:phone":"+61 2 9897 9600",
    "sg:postcode":"2142",
    "sg:province":"NSW",
    "sg:tags":[
        "product",
        "cleaning"
    ],
    "wof:name":"Applied Chemicals Pty Ltd",
    "wof:placetype":"venue"
},
  "geometry": {"coordinates":[151.01852417000001,-33.8322486877],"type":"Point"}
}