{
  "type": "Feature",
  "properties": {
    "iso:country":"AU",
    "sg:address":"5 Hereford St",
    "sg:city":"Richmond",
    "sg:classifiers":[
        {
            "category":"Government",
            "subcategory":"Fire Station",
            "type":"Public Place"
        }
    ],
    "sg:phone":"+61 412 744 441",
    "sg:postcode":"2753",
    "sg:province":"NSW",
    "sg:tags":[
        "equipment",
        "protection",
        "consultant"
    ],
    "wof:name":"Fire Training Services Pty Ltd",
    "wof:placetype":"venue"
},
  "geometry": {"coordinates":[150.74415588400001,-33.59998703],"type":"Point"}
}