{
  "type": "Feature",
  "properties": {
    "addr:full":"46 Old Bar Rd Old Bar NSW 2430",
    "addr:housenumber":"46",
    "addr:postcode":"2430",
    "addr:street":"Old Bar Rd",
    "iso:country":"AU",
    "sg:address":"46 Old Bar Rd",
    "sg:city":"Old Bar",
    "sg:classifiers":[
        {
            "category":"Health Services",
            "subcategory":"Doctor",
            "type":"Services"
        }
    ],
    "sg:phone":"+61 2 6553 7600",
    "sg:postcode":"2430",
    "sg:province":"NSW",
    "sg:tags":[
        "medical",
        "practitioner"
    ],
    "wof:name":"Old Bar Medical Centre & Skin Cancer Clinic",
    "wof:placetype":"venue"
},
  "geometry": {"coordinates":[152.57856799999999,-31.96715],"type":"Point"}
}