{
  "type": "Feature",
  "properties": {
    "addr:full":"18 Clementson St Broome WA 6725",
    "addr:housenumber":"18",
    "addr:postcode":"6725",
    "addr:street":"Clementson St",
    "iso:country":"AU",
    "sg:address":"18 Clementson St",
    "sg:city":"Broome",
    "sg:classifiers":[
        {
            "category":"Home & Garden",
            "subcategory":"Hardware",
            "type":"Retail Goods"
        }
    ],
    "sg:phone":"+61 8 9193 5982",
    "sg:postcode":"6725",
    "sg:province":"WA",
    "sg:tags":[
        "plumber",
        "supply"
    ],
    "wof:name":"Tradelink Plumbing Centres",
    "wof:placetype":"venue"
},
  "geometry": {"coordinates":[122.219848633,-17.9715805054],"type":"Point"}
}