{
  "type": "Feature",
  "properties": {
    "iso:country":"AU",
    "sg:address":"6 Emperor St",
    "sg:city":"Tin Can Bay",
    "sg:classifiers":[
        {
            "category":"Autos & Motor Vehicles",
            "subcategory":"Motorcycle Sales",
            "type":"Retail Goods"
        }
    ],
    "sg:phone":"+61 7 5488 0686",
    "sg:postcode":"4580",
    "sg:province":"QLD",
    "sg:tags":[
        "outboard"
    ],
    "wof:name":"R & D Marine",
    "wof:placetype":"venue"
},
  "geometry": {"coordinates":[153.008865356,-25.9062900543],"type":"Point"}
}