{
  "type": "Feature",
  "properties": {
    "addr:full":"14 Hurley St Canning Vale WA 6155",
    "addr:housenumber":"14",
    "addr:postcode":"6155",
    "addr:street":"Hurley St",
    "iso:country":"AU",
    "sg:address":"14 Hurley St",
    "sg:city":"Canning Vale",
    "sg:classifiers":[
        {
            "category":"Retail",
            "subcategory":"Storage",
            "type":"Services"
        }
    ],
    "sg:phone":"+61 8 9455 7122",
    "sg:postcode":"6155",
    "sg:province":"WA",
    "sg:tags":[
        "removal",
        "furniture"
    ],
    "wof:name":"Australian Vanlines",
    "wof:placetype":"venue"
},
  "geometry": {"coordinates":[115.908417,-32.059166],"type":"Point"}
}