{
  "type": "Feature",
  "properties": {
    "iso:country":"AU",
    "sg:address":"8 Negara Crs",
    "sg:city":"Goodwood",
    "sg:classifiers":[
        {
            "category":"Food & Beverages",
            "subcategory":"Meat & Fish",
            "type":"Retail Goods"
        }
    ],
    "sg:phone":"+61 3 6274 0222",
    "sg:postcode":"7010",
    "sg:province":"TAS",
    "sg:tags":[
        "aquaculture"
    ],
    "wof:name":"Plastic Fabrications Pty Ltd",
    "wof:placetype":"venue"
},
  "geometry": {"coordinates":[147.289505005,-42.8290596008],"type":"Point"}
}