{
  "type": "Feature",
  "properties": {
    "addr:full":"32 Mitchell St Bourke NSW 2840",
    "addr:housenumber":"32",
    "addr:postcode":"2840",
    "addr:street":"Mitchell St",
    "iso:country":"AU",
    "sg:address":"32 Mitchell St",
    "sg:city":"Bourke",
    "sg:classifiers":[
        {
            "category":"Travel",
            "subcategory":"Hotels & Motels",
            "type":"Entertainment"
        }
    ],
    "sg:phone":"+61 2 6872 2544",
    "sg:postcode":"2840",
    "sg:province":"NSW",
    "sg:tags":[
        "accommodation"
    ],
    "wof:name":"The Port Of Bourke Hotel",
    "wof:placetype":"venue"
},
  "geometry": {"coordinates":[145.935867,-30.088697],"type":"Point"}
}