{
  "type": "Feature",
  "properties": {
    "iso:country":"AU",
    "sg:address":"227 Place Rd",
    "sg:city":"Wonthella",
    "sg:classifiers":[
        {
            "category":"Retail",
            "subcategory":"Auto Repair",
            "type":"Services"
        }
    ],
    "sg:phone":"+61 8 9921 1999",
    "sg:postcode":"6530",
    "sg:province":"WA",
    "sg:tags":[
        "repairer",
        "motor",
        "engineer"
    ],
    "wof:name":"Autosense",
    "wof:placetype":"venue"
},
  "geometry": {"coordinates":[114.62792968799999,-28.7595348358],"type":"Point"}
}