{
  "type": "Feature",
  "properties": {
    "addr:full":"112 McLennan St Mooroopna VIC 3629",
    "addr:housenumber":"112",
    "addr:postcode":"3629",
    "addr:street":"Mclennan St",
    "iso:country":"AU",
    "sg:address":"112 McLennan St",
    "sg:city":"Mooroopna",
    "sg:classifiers":[
        {
            "category":"Banks & Credit Unions",
            "subcategory":"Financial Services",
            "type":"Services"
        }
    ],
    "sg:phone":"+61 3 5825 1999",
    "sg:postcode":"3629",
    "sg:province":"VIC",
    "sg:tags":[
        "loan",
        "finance",
        "mortgage"
    ],
    "wof:name":"Goulburn Murray Credit Union Co-Op Ltd",
    "wof:placetype":"venue"
},
  "geometry": {"coordinates":[145.35899352999999,-36.394443512],"type":"Point"}
}