{
  "type": "Feature",
  "properties": {
    "addr:full":"Unit 1, 203 Great Eastern Hwy Midland WA 6056",
    "addr:housenumber":"203",
    "addr:postcode":"6056",
    "addr:street":"Great Eastern Hwy",
    "iso:country":"AU",
    "sg:address":"Unit 1, 203 Great Eastern Hwy",
    "sg:city":"Midland",
    "sg:classifiers":[
        {
            "category":"Manufacturing",
            "subcategory":"Retail Goods",
            "type":"Manufacturing & Wholesale Goods"
        }
    ],
    "sg:phone":"+61 13 20 09",
    "sg:postcode":"6056",
    "sg:province":"WA",
    "sg:tags":[
        "merchant",
        "pump",
        "mfrs"
    ],
    "wof:name":"Hugall & Hoile",
    "wof:placetype":"venue"
},
  "geometry": {"coordinates":[116.009910584,-31.8910274506],"type":"Point"}
}