{
  "type": "Feature",
  "properties": {
    "iso:country":"AU",
    "sg:address":"26 Tod St",
    "sg:city":"Glenelg North",
    "sg:classifiers":[
        {
            "category":"Utilities",
            "subcategory":"Electric",
            "type":"Services"
        }
    ],
    "sg:phone":"+61 417 863 245",
    "sg:postcode":"5045",
    "sg:province":"SA",
    "sg:tags":[
        "electrical",
        "contractor"
    ],
    "wof:name":"Conroys Electrical Services",
    "wof:placetype":"venue"
},
  "geometry": {"coordinates":[138.515884,-34.970943],"type":"Point"}
}