{
  "type": "Feature",
  "properties": {
    "addr:full":"85 Gordon St Naracoorte SA 5271",
    "addr:housenumber":"85",
    "addr:postcode":"5271",
    "addr:street":"Gordon St",
    "iso:country":"AU",
    "sg:address":"85 Gordon St",
    "sg:city":"Naracoorte",
    "sg:classifiers":[
        {
            "category":"Manufacturing",
            "subcategory":"Food",
            "type":"Manufacturing & Wholesale Goods"
        }
    ],
    "sg:phone":"+61 8 8762 0700",
    "sg:postcode":"5271",
    "sg:province":"SA",
    "sg:tags":[
        "function",
        "catering"
    ],
    "wof:name":"Settlers Cafe & Function Rooms",
    "wof:placetype":"venue"
},
  "geometry": {"coordinates":[140.74203499999999,-36.960178],"type":"Point"}
}