{
  "type": "Feature",
  "properties": {
    "addr:full":"3 Foxgrove Pl Geraldton WA 6530",
    "addr:housenumber":"3",
    "addr:postcode":"6530",
    "addr:street":"Foxgrove Pl",
    "iso:country":"AU",
    "sg:address":"3 Foxgrove Pl",
    "sg:city":"Geraldton",
    "sg:classifiers":[
        {
            "category":"Utilities",
            "type":"Services"
        }
    ],
    "sg:phone":"+61 429 654 484",
    "sg:postcode":"6530",
    "sg:province":"WA",
    "sg:tags":[
        "refrigeration",
        "industrial",
        "commercial",
        "retail"
    ],
    "wof:name":"Batavia Coast Fridge Rentals",
    "wof:placetype":"venue"
},
  "geometry": {"coordinates":[114.64441680900001,-28.7547912598],"type":"Point"}
}