{
  "type": "Feature",
  "properties": {
    "iso:country":"AU",
    "sg:address":"3/ 17 Indy Crt",
    "sg:city":"Nerang",
    "sg:classifiers":[
        {
            "category":"Insurance",
            "subcategory":"Hazard Insurance",
            "type":"Services"
        }
    ],
    "sg:phone":"+61 1800 686 692",
    "sg:postcode":"4211",
    "sg:province":"QLD",
    "sg:tags":[
        "fire",
        "accident",
        "marine"
    ],
    "wof:name":"Glass Now",
    "wof:placetype":"venue"
},
  "geometry": {"coordinates":[153.34765625,-28.0116596222],"type":"Point"}
}