{
  "type": "Feature",
  "properties": {
    "iso:country":"AU",
    "sg:address":"24 Everist Rd",
    "sg:city":"Ocean Grove",
    "sg:classifiers":[
        {
            "category":"Professional",
            "subcategory":"Engineering",
            "type":"Services"
        }
    ],
    "sg:phone":"+61 3 5256 1929",
    "sg:postcode":"3226",
    "sg:province":"VIC",
    "sg:tags":[
        "engineer"
    ],
    "wof:name":"Bellarine Peninsula Engineering Pty Ltd",
    "wof:placetype":"venue"
},
  "geometry": {"coordinates":[144.54002399999999,-38.252747],"type":"Point"}
}