{
  "type": "Feature",
  "properties": {
    "iso:country":"AU",
    "sg:address":"Cnr Snow & Factory Rds",
    "sg:city":"Milawa",
    "sg:classifiers":[
        {
            "category":"Travel",
            "subcategory":"Hotels & Motels",
            "type":"Entertainment"
        }
    ],
    "sg:phone":"+61 3 5727 3208",
    "sg:postcode":"3678",
    "sg:province":"VIC",
    "sg:tags":[
        "accommodation"
    ],
    "wof:name":"Milawa Commercial Hotel",
    "wof:placetype":"venue"
},
  "geometry": {"coordinates":[146.44520568900001,-36.4511604309],"type":"Point"}
}