{
  "type": "Feature",
  "properties": {
    "addr:full":"13a/ Stanton Rd Seven Hills NSW 2147",
    "addr:housenumber":"13a /",
    "addr:postcode":"2147",
    "addr:street":"Stanton Rd",
    "iso:country":"AU",
    "sg:address":"13a/ Stanton Rd",
    "sg:city":"Seven Hills",
    "sg:classifiers":[
        {
            "category":"Wholesale",
            "subcategory":"Electrical",
            "type":"Manufacturing & Wholesale Goods"
        }
    ],
    "sg:phone":"+61 2 9620 8411",
    "sg:postcode":"2147",
    "sg:province":"NSW",
    "sg:tags":[
        "wholesaler",
        "mfrs",
        "accessory"
    ],
    "wof:name":"Cable Cage Systems",
    "wof:placetype":"venue"
},
  "geometry": {"coordinates":[150.941238403,-33.7741012573],"type":"Point"}
}