{
  "type": "Feature",
  "properties": {
    "addr:full":"196 Bridge St Muswellbrook NSW 2333",
    "addr:housenumber":"196",
    "addr:postcode":"2333",
    "addr:street":"Bridge St",
    "iso:country":"AU",
    "sg:address":"196 Bridge St",
    "sg:city":"Muswellbrook",
    "sg:classifiers":[
        {
            "category":"Health Services",
            "subcategory":"Health Practitioner",
            "type":"Services"
        }
    ],
    "sg:phone":"+61 2 6541 1884",
    "sg:postcode":"2333",
    "sg:province":"NSW",
    "sg:tags":[
        "hypnotherapy"
    ],
    "wof:name":"Total Health & Education Centre",
    "wof:placetype":"venue"
},
  "geometry": {"coordinates":[150.888504028,-32.2638778687],"type":"Point"}
}