{
  "type": "Feature",
  "properties": {
    "addr:full":"Room 202, 2nd Flr Sports House Wentworth Pk Sporti Ultimo NSW 2007",
    "addr:postcode":"2007",
    "addr:street":"Wentworth",
    "iso:country":"AU",
    "sg:address":"Room 202, 2nd Flr Sports House Wentworth Pk Sporti",
    "sg:city":"Ultimo",
    "sg:classifiers":[
        {
            "category":"Arena",
            "subcategory":"Sports Club",
            "type":"Entertainment"
        }
    ],
    "sg:phone":"+61 2 9660 4333",
    "sg:postcode":"2007",
    "sg:province":"NSW",
    "sg:tags":[
        "organisation",
        "sporting"
    ],
    "wof:name":"Sports Medicine Australia (NSW)",
    "wof:placetype":"venue"
},
  "geometry": {"coordinates":[151.19731140100001,-33.8817901611],"type":"Point"}
}