{
  "type": "Feature",
  "properties": {
    "addr:full":"2 Market St Melbourne VIC 3000",
    "addr:housenumber":"2",
    "addr:postcode":"3000",
    "addr:street":"Market St",
    "iso:country":"AU",
    "sg:address":"2 Market St",
    "sg:city":"Melbourne",
    "sg:classifiers":[
        {
            "category":"Professional",
            "subcategory":"Accounting & Tax Preparation",
            "type":"Services"
        }
    ],
    "sg:phone":"+61 3 9629 6455",
    "sg:postcode":"3000",
    "sg:province":"VIC",
    "sg:tags":[
        "accountant",
        "auditor"
    ],
    "wof:name":"Tudor & Company",
    "wof:placetype":"venue"
},
  "geometry": {"coordinates":[144.961303711,-37.8191947937],"type":"Point"}
}