{
  "type": "Feature",
  "properties": {
    "iso:country":"AU",
    "sg:address":"26b Bombala St",
    "sg:city":"Cooma",
    "sg:classifiers":[
        {
            "category":"Professional",
            "subcategory":"Employment Agencies",
            "type":"Services"
        }
    ],
    "sg:phone":"+61 2 6452 5555",
    "sg:postcode":"2630",
    "sg:province":"NSW",
    "sg:tags":[
        "provider",
        "internet"
    ],
    "wof:name":"Monaro It Computer Sales & Service",
    "wof:placetype":"venue"
},
  "geometry": {"coordinates":[149.126586914,-36.2339782715],"type":"Point"}
}