{
  "type": "Feature",
  "properties": {
    "addr:full":"13 Isabel St Maryborough QLD 4650",
    "addr:housenumber":"13",
    "addr:postcode":"4650",
    "addr:street":"Isabel St",
    "iso:country":"AU",
    "sg:address":"13 Isabel St",
    "sg:city":"Maryborough",
    "sg:classifiers":[
        {
            "category":"Shopping",
            "subcategory":"Crafts & Fabrics",
            "type":"Retail Goods"
        }
    ],
    "sg:phone":"+61 7 4123 1715",
    "sg:postcode":"4650",
    "sg:province":"QLD",
    "sg:tags":[
        "merchant",
        "cork"
    ],
    "wof:name":"Polley Enterprises Pty Ltd",
    "wof:placetype":"venue"
},
  "geometry": {"coordinates":[152.67896999999999,-25.547813],"type":"Point"}
}