{
  "type": "Feature",
  "properties": {
    "iso:country":"AU",
    "sg:address":"117 Clermont St",
    "sg:city":"Emerald",
    "sg:classifiers":[
        {
            "category":"Food & Beverages",
            "subcategory":"Bakery",
            "type":"Retail Goods"
        }
    ],
    "sg:phone":"+61 7 4982 1103",
    "sg:postcode":"4720",
    "sg:province":"QLD",
    "sg:tags":[
        "cake",
        "shop",
        "pastry"
    ],
    "wof:name":"Emerald Bakery",
    "wof:placetype":"venue"
},
  "geometry": {"coordinates":[148.157883,-23.525543],"type":"Point"}
}