{
  "type": "Feature",
  "properties": {
    "addr:full":"31 Mermaid Ave Maroubra NSW 2035",
    "addr:housenumber":"31",
    "addr:postcode":"2035",
    "addr:street":"Mermaid Ave",
    "iso:country":"AU",
    "sg:address":"31 Mermaid Ave",
    "sg:city":"Maroubra",
    "sg:classifiers":[
        {
            "category":"Professional",
            "subcategory":"Employment Agencies",
            "type":"Services"
        }
    ],
    "sg:phone":"+61 2 9314 2421",
    "sg:postcode":"2035",
    "sg:province":"NSW",
    "sg:tags":[
        "entertainer",
        "agent"
    ],
    "wof:name":"Tightly Packed",
    "wof:placetype":"venue"
},
  "geometry": {"coordinates":[151.258666992,-33.9384040833],"type":"Point"}
}