{
  "type": "Feature",
  "properties": {
    "addr:full":"845 Wynnum Rd Cannon Hill QLD 4170",
    "addr:housenumber":"845",
    "addr:postcode":"4170",
    "addr:street":"Wynnum Rd",
    "iso:country":"AU",
    "sg:address":"845 Wynnum Rd",
    "sg:city":"Cannon Hill",
    "sg:classifiers":[
        {
            "category":"Education",
            "subcategory":"School",
            "type":"Public Place"
        }
    ],
    "sg:phone":"+61 7 3902 3333",
    "sg:postcode":"4170",
    "sg:province":"QLD",
    "sg:tags":[
        "state",
        "except",
        "nsw"
    ],
    "wof:name":"Cannon Hill Primary",
    "wof:placetype":"venue"
},
  "geometry": {"coordinates":[153.07525634800001,-27.467004776],"type":"Point"}
}