{
  "type": "Feature",
  "properties": {
    "iso:country":"AU",
    "sg:address":"85 Hoffmans Rd",
    "sg:city":"Niddrie",
    "sg:classifiers":[
        {
            "category":"Professional",
            "subcategory":"Management & Consulting",
            "type":"Services"
        }
    ],
    "sg:phone":"+61 3 9337 4123",
    "sg:postcode":"3042",
    "sg:province":"VIC",
    "sg:tags":[
        "consultant",
        "business"
    ],
    "wof:name":"Knowledge Translation",
    "wof:placetype":"venue"
},
  "geometry": {"coordinates":[144.89117431599999,-37.7437362671],"type":"Point"}
}