{
  "type": "Feature",
  "properties": {
    "iso:country":"AU",
    "sg:address":"16 Tangara Rd",
    "sg:city":"Mt Nelson",
    "sg:classifiers":[
        {
            "category":"Building & Trades",
            "subcategory":"Cleaning & Sanitation",
            "type":"Services"
        }
    ],
    "sg:phone":"+61 3 6224 2057",
    "sg:postcode":"7007",
    "sg:province":"TAS",
    "sg:tags":[
        "industrial",
        "commercial",
        "contractor"
    ],
    "wof:name":"C & S Cleaning Services",
    "wof:placetype":"venue"
},
  "geometry": {"coordinates":[147.321655273,-42.9137077332],"type":"Point"}
}