{
  "type": "Feature",
  "properties": {
    "iso:country":"AU",
    "sg:address":"15 gardner Crt",
    "sg:city":"Toowoomba",
    "sg:classifiers":[
        {
            "category":"Autos & Motor Vehicles",
            "subcategory":"Auto Supplies",
            "type":"Retail Goods"
        }
    ],
    "sg:phone":"+61 1300 880 433",
    "sg:postcode":"4350",
    "sg:province":"QLD",
    "sg:tags":[
        "camper-trailers",
        "caravan",
        "equipment"
    ],
    "wof:name":"Venture Fifth Wheelers",
    "wof:placetype":"venue"
},
  "geometry": {"coordinates":[151.90422100000001,-27.547386],"type":"Point"}
}