{
  "type": "Feature",
  "properties": {
    "addr:full":"10 Hyde Crt Nerang QLD 4211",
    "addr:housenumber":"10",
    "addr:postcode":"4211",
    "addr:street":"Hyde Crt",
    "iso:country":"AU",
    "sg:address":"10 Hyde Crt",
    "sg:city":"Nerang",
    "sg:classifiers":[
        {
            "category":"Professional",
            "subcategory":"Testing Lab",
            "type":"Services"
        }
    ],
    "sg:phone":"+61 7 5502 1511",
    "sg:postcode":"4211",
    "sg:province":"QLD",
    "sg:tags":[
        "inspection"
    ],
    "wof:name":"Abba Pest Control",
    "wof:placetype":"venue"
},
  "geometry": {"coordinates":[153.336425781,-27.989440918],"type":"Point"}
}