{
  "type": "Feature",
  "properties": {
    "addr:full":"28 Crimea St Drysdale VIC 3222",
    "addr:housenumber":"28",
    "addr:postcode":"3222",
    "addr:street":"Crimea St",
    "iso:country":"AU",
    "sg:address":"28 Crimea St",
    "sg:city":"Drysdale",
    "sg:classifiers":[
        {
            "category":"Professional",
            "subcategory":"Accounting & Tax Preparation",
            "type":"Services"
        }
    ],
    "sg:phone":"+61 3 5253 2366",
    "sg:postcode":"3222",
    "sg:province":"VIC",
    "sg:tags":[
        "accountant",
        "auditor"
    ],
    "wof:name":"L J Warren Pty Ltd",
    "wof:placetype":"venue"
},
  "geometry": {"coordinates":[144.55943300000001,-38.177471],"type":"Point"}
}