{
  "type": "Feature",
  "properties": {
    "iso:country":"AU",
    "sg:address":"1st Floor 145a Balo St",
    "sg:city":"Moree",
    "sg:classifiers":[
        {
            "category":"Real Estate",
            "subcategory":"Real Estate Services",
            "type":"Services"
        }
    ],
    "sg:phone":"+61 2 6752 1966",
    "sg:postcode":"2400",
    "sg:province":"NSW",
    "sg:tags":[
        "valuer"
    ],
    "wof:name":"Taylor Byrne",
    "wof:placetype":"venue"
},
  "geometry": {"coordinates":[149.84144592300001,-29.4648113251],"type":"Point"}
}