{
  "type": "Feature",
  "properties": {
    "addr:full":"6 Gregory Crt Mt Ommaney QLD 4074",
    "addr:housenumber":"6",
    "addr:postcode":"4074",
    "addr:street":"Gregory Crt Mt Ommaney",
    "iso:country":"AU",
    "sg:address":"6 Gregory Crt",
    "sg:city":"Mt Ommaney",
    "sg:classifiers":[
        {
            "category":"Health Services",
            "subcategory":"Health Practitioner",
            "type":"Services"
        }
    ],
    "sg:phone":"+61 7 3279 1999",
    "sg:postcode":"4074",
    "sg:province":"QLD",
    "sg:tags":[
        "pathologist",
        "speech"
    ],
    "wof:name":"Price Lynne D",
    "wof:placetype":"venue"
},
  "geometry": {"coordinates":[152.93255615199999,-27.5402488708],"type":"Point"}
}