{
  "type": "Feature",
  "properties": {
    "iso:country":"AU",
    "sg:address":"267 Ingham Rd",
    "sg:city":"Garbutt",
    "sg:classifiers":[
        {
            "category":"Building & Trades",
            "subcategory":"Construction",
            "type":"Services"
        }
    ],
    "sg:phone":"+61 7 4779 2266",
    "sg:postcode":"4814",
    "sg:province":"QLD",
    "sg:tags":[
        "contractor"
    ],
    "wof:name":"Formset Pty Ltd",
    "wof:placetype":"venue"
},
  "geometry": {"coordinates":[146.777191,-19.265511],"type":"Point"}
}