{
  "type": "Feature",
  "properties": {
    "addr:full":"73 Warwick St Hobart TAS 7000",
    "addr:housenumber":"73",
    "addr:postcode":"7000",
    "addr:street":"Warwick St",
    "iso:country":"AU",
    "sg:address":"73 Warwick St",
    "sg:city":"Hobart",
    "sg:classifiers":[
        {
            "category":"Retail",
            "subcategory":"Auto Rental",
            "type":"Services"
        }
    ],
    "sg:phone":"+61 3 6231 3313",
    "sg:postcode":"7000",
    "sg:province":"TAS",
    "sg:tags":[
        "bus",
        "truck"
    ],
    "wof:name":"AAA Car Rentals Pty Ltd",
    "wof:placetype":"venue"
},
  "geometry": {"coordinates":[147.31951904300001,-42.8774452209],"type":"Point"}
}