{
  "type": "Feature",
  "properties": {
    "addr:full":"7- 11 Kapara Rd Gillman SA 5013",
    "addr:housenumber":"11",
    "addr:postcode":"5013",
    "addr:street":"7;Kapara Rd",
    "iso:country":"AU",
    "sg:address":"7- 11 Kapara Rd",
    "sg:city":"Gillman",
    "sg:classifiers":[
        {
            "category":"Professional",
            "type":"Services"
        }
    ],
    "sg:phone":"+61 8 8241 0988",
    "sg:postcode":"5013",
    "sg:province":"SA",
    "sg:tags":[
        "transport"
    ],
    "wof:name":"Scott's Transport Industries Pty Ltd",
    "wof:placetype":"venue"
},
  "geometry": {"coordinates":[138.530685425,-34.8375205994],"type":"Point"}
}