{
  "type": "Feature",
  "properties": {
    "addr:full":"3 Gardiner St Ingham QLD 4850",
    "addr:housenumber":"3",
    "addr:postcode":"4850",
    "addr:street":"Gardiner St",
    "iso:country":"AU",
    "sg:address":"3 Gardiner St",
    "sg:city":"Ingham",
    "sg:classifiers":[
        {
            "category":"Utilities",
            "type":"Services"
        }
    ],
    "sg:phone":"+61 7 4776 2625",
    "sg:postcode":"4850",
    "sg:province":"QLD",
    "sg:tags":[
        "refrigeration",
        "industrial",
        "commercial",
        "retail"
    ],
    "wof:name":"Jeff & Pitsi Lahtinen Electrical",
    "wof:placetype":"venue"
},
  "geometry": {"coordinates":[146.16146850600001,-18.645652771],"type":"Point"}
}