{
  "type": "Feature",
  "properties": {
    "addr:full":"570 Mt Alexander Rd Moonee Ponds VIC 3039",
    "addr:housenumber":"570",
    "addr:postcode":"3039",
    "addr:street":"Mt Alexander Rd",
    "iso:country":"AU",
    "sg:address":"570 Mt Alexander Rd",
    "sg:city":"Moonee Ponds",
    "sg:classifiers":[
        {
            "category":"Autos & Motor Vehicles",
            "subcategory":"Automobile Sales",
            "type":"Retail Goods"
        }
    ],
    "sg:phone":"+61 3 9326 2822",
    "sg:postcode":"3039",
    "sg:province":"VIC",
    "sg:tags":[
        "car",
        "new"
    ],
    "wof:name":"North City Daewoo",
    "wof:placetype":"venue"
},
  "geometry": {"coordinates":[144.9254,-37.769062],"type":"Point"}
}