{
  "type": "Feature",
  "properties": {
    "iso:country":"AU",
    "sg:address":"U 1/ 6",
    "sg:city":"National Cct Barton",
    "sg:classifiers":[
        {
            "category":"Fast Food",
            "type":"Food & Drink"
        }
    ],
    "sg:phone":"+61 2 6273 3253",
    "sg:postcode":"2600",
    "sg:province":"ACT",
    "sg:tags":[
        "away",
        "take"
    ],
    "wof:name":"Barton Food Bar",
    "wof:placetype":"venue"
},
  "geometry": {"coordinates":[149.133499145,-35.3084983826],"type":"Point"}
}