{
  "type": "Feature",
  "properties": {
    "iso:country":"AU",
    "sg:address":"Unit 5 6",
    "sg:city":"Woodlake Blv Durack",
    "sg:classifiers":[
        {
            "category":"Health Services",
            "subcategory":"Health Practitioner",
            "type":"Services"
        }
    ],
    "sg:phone":"+61 8 8931 2441",
    "sg:postcode":"0830",
    "sg:province":"NT",
    "sg:tags":[
        "naturopath"
    ],
    "wof:name":"Allyson Richards Top Shelf Herbals",
    "wof:placetype":"venue"
},
  "geometry": {"coordinates":[130.976028,-12.479567],"type":"Point"}
}