{
  "type": "Feature",
  "properties": {
    "iso:country":"AU",
    "sg:address":"4A Little St",
    "sg:city":"Dulwich Hill",
    "sg:classifiers":[
        {
            "category":"Building & Trades",
            "subcategory":"Construction",
            "type":"Services"
        }
    ],
    "sg:phone":"+61 2 9560 9894",
    "sg:postcode":"2203",
    "sg:province":"NSW",
    "sg:tags":[
        "joinery"
    ],
    "wof:name":"Benoit Midy & Francis Boutry",
    "wof:placetype":"venue"
},
  "geometry": {"coordinates":[151.14151,-33.898342],"type":"Point"}
}