{
  "type": "Feature",
  "properties": {
    "addr:full":"PO Box 75 Ourimbah NSW 2258",
    "addr:postcode":"2258",
    "iso:country":"AU",
    "sg:address":"PO Box 75",
    "sg:city":"Ourimbah",
    "sg:classifiers":[
        {
            "category":"Home & Garden",
            "subcategory":"Building Materials",
            "type":"Retail Goods"
        }
    ],
    "sg:phone":"+61 2 4372 1105",
    "sg:postcode":"2258",
    "sg:province":"NSW",
    "sg:tags":[
        "retaining",
        "wall"
    ],
    "wof:name":"Scape Constructions Pty Ltd",
    "wof:placetype":"venue"
},
  "geometry": {"coordinates":[151.369750977,-33.3518981934],"type":"Point"}
}