{
  "type": "Feature",
  "properties": {
    "addr:full":"Morayfield Rd Caboolture QLD 4510",
    "addr:postcode":"4510",
    "addr:street":"Morayfield Rd",
    "iso:country":"AU",
    "sg:address":"Morayfield Rd",
    "sg:city":"Caboolture",
    "sg:classifiers":[
        {
            "category":"Retail",
            "subcategory":"Auto Rental",
            "type":"Services"
        }
    ],
    "sg:phone":"+61 7 3865 1788",
    "sg:postcode":"4510",
    "sg:province":"QLD",
    "sg:tags":[
        "bus",
        "truck"
    ],
    "wof:name":"Avis",
    "wof:placetype":"venue"
},
  "geometry": {"coordinates":[152.95138499999999,-27.085728],"type":"Point"}
}