{
  "type": "Feature",
  "properties": {
    "addr:full":"26 Douglas St Milton QLD 4064",
    "addr:housenumber":"26",
    "addr:postcode":"4064",
    "addr:street":"Douglas St",
    "iso:country":"AU",
    "sg:address":"26 Douglas St",
    "sg:city":"Milton",
    "sg:classifiers":[
        {
            "category":"Home & Garden",
            "subcategory":"Home Furnishings",
            "type":"Retail Goods"
        }
    ],
    "sg:phone":"+61 7 3367 8300",
    "sg:postcode":"4064",
    "sg:province":"QLD",
    "sg:tags":[
        "candle"
    ],
    "wof:name":"Pellegrini & Coverall Books",
    "wof:placetype":"venue"
},
  "geometry": {"coordinates":[153.00404357900001,-27.4716758728],"type":"Point"}
}