{
  "type": "Feature",
  "properties": {
    "addr:full":"25 Wandearah Ave Avalon NSW 2107",
    "addr:housenumber":"25",
    "addr:postcode":"2107",
    "addr:street":"Wandearah Ave",
    "iso:country":"AU",
    "sg:address":"25 Wandearah Ave",
    "sg:city":"Avalon",
    "sg:classifiers":[
        {
            "category":"Professional",
            "subcategory":"Business Services",
            "type":"Services"
        }
    ],
    "sg:phone":"+61 2 9973 2343",
    "sg:postcode":"2107",
    "sg:province":"NSW",
    "sg:tags":[
        "drafting"
    ],
    "wof:name":"Ricks Drafting Pty Ltd",
    "wof:placetype":"venue"
},
  "geometry": {"coordinates":[151.32090759299999,-33.6237030029],"type":"Point"}
}