{
  "type": "Feature",
  "properties": {
    "iso:country":"AU",
    "sg:address":"Level 1 City Plz, 45 Wood St",
    "sg:city":"Mackay",
    "sg:classifiers":[
        {
            "category":"Professional",
            "subcategory":"Accounting & Tax Preparation",
            "type":"Services"
        }
    ],
    "sg:phone":"+61 7 4957 2231",
    "sg:postcode":"4740",
    "sg:province":"QLD",
    "sg:tags":[
        "consultant",
        "taxation"
    ],
    "wof:name":"S.H. Tait & Co",
    "wof:placetype":"venue"
},
  "geometry": {"coordinates":[149.185867,-21.142269],"type":"Point"}
}