{
  "type": "Feature",
  "properties": {
    "addr:full":"Level 13/ 77 Eagle St Brisbane QLD 4000",
    "addr:housenumber":"/ 77",
    "addr:postcode":"4000",
    "addr:street":"Eagle St",
    "iso:country":"AU",
    "sg:address":"Level 13/ 77 Eagle St",
    "sg:city":"Brisbane",
    "sg:classifiers":[
        {
            "category":"Real Estate",
            "subcategory":"Developer",
            "type":"Services"
        }
    ],
    "sg:phone":"+61 7 3221 8006",
    "sg:postcode":"4000",
    "sg:province":"QLD",
    "sg:tags":[
        "development"
    ],
    "wof:name":"Winten Qld Pty Ltd",
    "wof:placetype":"venue"
},
  "geometry": {"coordinates":[153.02992248499999,-27.4678497314],"type":"Point"}
}