{
  "type": "Feature",
  "properties": {
    "addr:full":"1 Denver St Bentleigh East VIC 3165",
    "addr:housenumber":"1",
    "addr:postcode":"3165",
    "addr:street":"Denver St",
    "iso:country":"AU",
    "sg:address":"1 Denver St",
    "sg:city":"Bentleigh East",
    "sg:classifiers":[
        {
            "category":"Building & Trades",
            "subcategory":"Construction",
            "type":"Services"
        }
    ],
    "sg:phone":"+61 3 9570 6764",
    "sg:postcode":"3165",
    "sg:province":"VIC",
    "sg:tags":[
        "stonework",
        "stone",
        "mason"
    ],
    "wof:name":"S & R Stonecraft Pty Ltd",
    "wof:placetype":"venue"
},
  "geometry": {"coordinates":[145.05706787099999,-37.9328918457],"type":"Point"}
}