{
  "type": "Feature",
  "properties": {
    "addr:full":"Cnr Clyde & Girling Sts Newcastle NSW 2300",
    "addr:postcode":"2300",
    "addr:street":"Cnr",
    "iso:country":"AU",
    "sg:address":"Cnr Clyde & Girling Sts",
    "sg:city":"Newcastle",
    "sg:classifiers":[
        {
            "category":"Professional",
            "subcategory":"Engineering",
            "type":"Services"
        }
    ],
    "sg:phone":"+61 1800 033 322",
    "sg:postcode":"2300",
    "sg:province":"NSW",
    "sg:tags":[
        "engineer"
    ],
    "wof:name":"Teterin Engineering Pty. Ltd.",
    "wof:placetype":"venue"
},
  "geometry": {"coordinates":[151.74153100000001,-32.91106],"type":"Point"}
}