{
  "type": "Feature",
  "properties": {
    "addr:full":"625 St Kilda Rd Windsor VIC 3181",
    "addr:housenumber":"625",
    "addr:postcode":"3181",
    "addr:street":"St Kilda Rd",
    "iso:country":"AU",
    "sg:address":"625 St Kilda Rd",
    "sg:city":"Windsor",
    "sg:classifiers":[
        {
            "category":"Education",
            "subcategory":"School",
            "type":"Public Place"
        }
    ],
    "sg:phone":"+61 3 8102 6200",
    "sg:postcode":"3181",
    "sg:province":"VIC",
    "sg:tags":[
        "co-educational"
    ],
    "wof:name":"Wesley College Prahran Preparatory School",
    "wof:placetype":"venue"
},
  "geometry": {"coordinates":[144.98223876899999,-37.8535690308],"type":"Point"}
}