{
  "type": "Feature",
  "properties": {
    "addr:full":"Shop 1, 695 Sandgate Rd Clayfield QLD 4011",
    "addr:housenumber":"shop 1 695",
    "addr:postcode":"4011",
    "addr:street":"Sandgate Rd",
    "iso:country":"AU",
    "sg:address":"Shop 1, 695 Sandgate Rd",
    "sg:city":"Clayfield",
    "sg:classifiers":[
        {
            "category":"Banks & Credit Unions",
            "subcategory":"Bank",
            "type":"Services"
        }
    ],
    "sg:phone":"+61 7 3265 7555",
    "sg:postcode":"4011",
    "sg:province":"QLD",
    "sg:tags":[
        "broker",
        "mortgage"
    ],
    "wof:name":"Mortgage Choice",
    "wof:placetype":"venue"
},
  "geometry": {"coordinates":[153.054565,-27.419502],"type":"Point"}
}