{
  "type": "Feature",
  "properties": {
    "addr:full":"100 Strickland St Bunbury WA 6230",
    "addr:housenumber":"100",
    "addr:postcode":"6230",
    "addr:street":"Strickland St",
    "iso:country":"AU",
    "sg:address":"100 Strickland St",
    "sg:city":"Bunbury",
    "sg:classifiers":[
        {
            "category":"Autos & Motor Vehicles",
            "subcategory":"Fuel & Gas Station",
            "type":"Retail Goods"
        }
    ],
    "sg:phone":"+61 8 9791 3678",
    "sg:postcode":"6230",
    "sg:province":"WA",
    "wof:name":"Shell Central",
    "wof:placetype":"venue"
},
  "geometry": {"coordinates":[115.65640999999999,-33.336094],"type":"Point"}
}