{
  "type": "Feature",
  "properties": {
    "iso:country":"AU",
    "sg:address":"11 Yatama Pl",
    "sg:city":"Tewantin",
    "sg:classifiers":[
        {
            "category":"Building & Trades",
            "subcategory":"Construction",
            "type":"Services"
        }
    ],
    "sg:phone":"+61 408 115 273",
    "sg:postcode":"4565",
    "sg:province":"QLD",
    "sg:tags":[
        "contractor"
    ],
    "wof:name":"Bryant D A & J M",
    "wof:placetype":"venue"
},
  "geometry": {"coordinates":[152.99571227999999,-26.3679237366],"type":"Point"}
}