{
  "type": "Feature",
  "properties": {
    "addr:full":"GPO Box 1277 Canberra City ACT 2601",
    "addr:postcode":"2601",
    "iso:country":"AU",
    "sg:address":"GPO Box 1277",
    "sg:city":"Canberra City",
    "sg:classifiers":[
        {
            "category":"Freight",
            "type":"Transportation"
        }
    ],
    "sg:phone":"+61 418 626 586",
    "sg:postcode":"2601",
    "sg:province":"ACT",
    "sg:tags":[
        "light",
        "carrier"
    ],
    "wof:name":"DPS Couriers",
    "wof:placetype":"venue"
},
  "geometry": {"coordinates":[149.13090515100001,-35.2801513672],"type":"Point"}
}