{
  "type": "Feature",
  "properties": {
    "iso:country":"AU",
    "sg:address":"161- 165 Horton Pde",
    "sg:city":"Maroochydore",
    "sg:classifiers":[
        {
            "category":"Professional",
            "subcategory":"Employment Agencies",
            "type":"Services"
        }
    ],
    "sg:phone":"+61 7 5451 0555",
    "sg:postcode":"4558",
    "sg:province":"QLD",
    "wof:name":"WorkDirections Australia",
    "wof:placetype":"venue"
},
  "geometry": {"coordinates":[153.090866089,-26.6541213989],"type":"Point"}
}