{
  "type": "Feature",
  "properties": {
    "addr:full":"686 Gympie Rd Chermside QLD 4032",
    "addr:housenumber":"686",
    "addr:postcode":"qld 4032",
    "addr:street":"Gympie Rd",
    "iso:country":"AU",
    "sg:address":"686 Gympie Rd",
    "sg:city":"Chermside",
    "sg:classifiers":[
        {
            "category":"Health Services",
            "subcategory":"Doctor",
            "type":"Services"
        }
    ],
    "sg:phone":"+61 7 3359 3011",
    "sg:postcode":"4032",
    "sg:province":"QLD",
    "sg:tags":[
        "medical",
        "practitioner"
    ],
    "wof:name":"Chermside Clinic Pty Ltd",
    "wof:placetype":"venue"
},
  "geometry": {"coordinates":[153.031113,-27.389549],"type":"Point"}
}