{
  "type": "Feature",
  "properties": {
    "addr:full":"PO Box 269 Frenchs Forest NSW 2086",
    "addr:postcode":"2086",
    "iso:country":"AU",
    "sg:address":"PO Box 269",
    "sg:city":"Frenchs Forest",
    "sg:classifiers":[
        {
            "category":"Retail",
            "subcategory":"Repair Shop",
            "type":"Services"
        }
    ],
    "sg:phone":"+61 2 9450 0788",
    "sg:postcode":"2086",
    "sg:province":"NSW",
    "sg:tags":[
        "maintenance",
        "pool",
        "swimming"
    ],
    "wof:name":"Wright Pools Pty Limited",
    "wof:placetype":"venue"
},
  "geometry": {"coordinates":[151.23475647000001,-33.7508201599],"type":"Point"}
}