{
  "type": "Feature",
  "properties": {
    "iso:country":"AU",
    "sg:address":"Level 6, 60 Albert Rd",
    "sg:city":"South Melbourne",
    "sg:classifiers":[
        {
            "category":"Banks & Credit Unions",
            "subcategory":"Investment Brokerage",
            "type":"Services"
        }
    ],
    "sg:phone":"+61 1800 006 216",
    "sg:postcode":"3205",
    "sg:province":"VIC",
    "wof:name":"Financial Services Partners",
    "wof:placetype":"venue"
},
  "geometry": {"coordinates":[144.971146,-37.834568],"type":"Point"}
}