{
  "type": "Feature",
  "properties": {
    "addr:full":"133b Lime Ave Mildura VIC 3500",
    "addr:housenumber":"133b",
    "addr:postcode":"3500",
    "addr:street":"Lime Ave",
    "iso:country":"AU",
    "sg:address":"133b Lime Ave",
    "sg:city":"Mildura",
    "sg:classifiers":[
        {
            "category":"Professional",
            "subcategory":"Engineering",
            "type":"Services"
        }
    ],
    "sg:phone":"+61 3 5051 6111",
    "sg:postcode":"3500",
    "sg:province":"VIC",
    "sg:tags":[
        "engineer"
    ],
    "wof:name":"EA Systems Pty Ltd",
    "wof:placetype":"venue"
},
  "geometry": {"coordinates":[142.15638732900001,-34.1865501404],"type":"Point"}
}