{
  "type": "Feature",
  "properties": {
    "addr:full":"11 Menzies St Dawesville WA 6210",
    "addr:housenumber":"11",
    "addr:postcode":"6210",
    "addr:street":"Menzies St",
    "iso:country":"AU",
    "sg:address":"11 Menzies St",
    "sg:city":"Dawesville",
    "sg:classifiers":[
        {
            "category":"Professional",
            "subcategory":"Business Services",
            "type":"Services"
        }
    ],
    "sg:phone":"+61 8 9582 3331",
    "sg:postcode":"6210",
    "sg:province":"WA",
    "sg:tags":[
        "consultant",
        "system"
    ],
    "wof:name":"Mandurah Business Support",
    "wof:placetype":"venue"
},
  "geometry": {"coordinates":[115.636482,-32.621746],"type":"Point"}
}