{
  "type": "Feature",
  "properties": {
    "addr:full":"449 Montville Rd Palmwoods QLD 4555",
    "addr:housenumber":"449",
    "addr:postcode":"4555",
    "addr:street":"Montville Rd",
    "iso:country":"AU",
    "sg:address":"449 Montville Rd",
    "sg:city":"Palmwoods",
    "sg:classifiers":[
        {
            "category":"Building & Trades",
            "subcategory":"Construction",
            "type":"Services"
        }
    ],
    "sg:phone":"+61 7 5445 9072",
    "sg:postcode":"4555",
    "sg:province":"QLD",
    "sg:tags":[
        "earth",
        "excavating",
        "moving",
        "contractor"
    ],
    "wof:name":"T & K Earthmoving",
    "wof:placetype":"venue"
},
  "geometry": {"coordinates":[152.956207275,-26.6875400543],"type":"Point"}
}