{
  "type": "Feature",
  "properties": {
    "addr:full":"Cnr Strangways St & Waddell Pl Curtin ACT 2605",
    "addr:postcode":"2605",
    "addr:street":"Cnr Strangways St & Waddell Pl Curtin",
    "iso:country":"AU",
    "sg:address":"Cnr Strangways St & Waddell Pl",
    "sg:city":"Curtin",
    "sg:classifiers":[
        {
            "category":"Manufacturing",
            "subcategory":"Motor Vehicles & Parts",
            "type":"Manufacturing & Wholesale Goods"
        }
    ],
    "sg:phone":"+61 2 6281 6192",
    "sg:postcode":"2605",
    "sg:province":"ACT",
    "sg:tags":[
        "replacement"
    ],
    "wof:name":"Canberra Driveshaft Centre",
    "wof:placetype":"venue"
},
  "geometry": {"coordinates":[149.08189392099999,-35.3246536255],"type":"Point"}
}