{
  "type": "Feature",
  "properties": {
    "addr:full":"Shop 5, 169 - 171 Anzac Pde Kensington NSW 2033",
    "addr:housenumber":"shop 5;171",
    "addr:postcode":"169;2033",
    "addr:street":"Anzac Pde",
    "iso:country":"AU",
    "sg:address":"Shop 5, 169 - 171 Anzac Pde",
    "sg:city":"Kensington",
    "sg:classifiers":[
        {
            "category":"Banks & Credit Unions",
            "subcategory":"Bank",
            "type":"Services"
        }
    ],
    "sg:phone":"+61 2 9697 3800",
    "sg:postcode":"2033",
    "sg:province":"NSW",
    "wof:name":"Bank of Queensland",
    "wof:placetype":"venue"
},
  "geometry": {"coordinates":[151.223343,-33.912174],"type":"Point"}
}