{
  "type": "Feature",
  "properties": {
    "iso:country":"AU",
    "sg:address":"74 Seabrook Rd",
    "sg:city":"Somerset",
    "sg:classifiers":[
        {
            "category":"Building & Trades",
            "subcategory":"Construction",
            "type":"Services"
        }
    ],
    "sg:phone":"+61 3 6435 1661",
    "sg:postcode":"7322",
    "sg:province":"TAS",
    "sg:tags":[
        "earth",
        "excavating",
        "moving",
        "contractor"
    ],
    "wof:name":"Bugg D W & J L",
    "wof:placetype":"venue"
},
  "geometry": {"coordinates":[145.806137,-41.045506],"type":"Point"}
}