{
  "type": "Feature",
  "properties": {
    "iso:country":"AU",
    "sg:address":"1 Hollywood Ave",
    "sg:city":"Bondi Junction",
    "sg:classifiers":[
        {
            "category":"Shopping",
            "subcategory":"Pawn Shop",
            "type":"Retail Goods"
        }
    ],
    "sg:phone":"+61 2 9369 4934",
    "sg:postcode":"2022",
    "sg:province":"NSW",
    "sg:tags":[
        "pawnbroker"
    ],
    "wof:name":"Goods For Cash",
    "wof:placetype":"venue"
},
  "geometry": {"coordinates":[151.25192260700001,-33.8930091858],"type":"Point"}
}