{
  "type": "Feature",
  "properties": {
    "addr:full":"71 Kenneth Rd Manly Vale NSW 2093",
    "addr:housenumber":"71",
    "addr:postcode":"2093",
    "addr:street":"Kenneth Rd",
    "iso:country":"AU",
    "sg:address":"71 Kenneth Rd",
    "sg:city":"Manly Vale",
    "sg:classifiers":[
        {
            "category":"Professional",
            "subcategory":"Printing & Photocopies",
            "type":"Services"
        }
    ],
    "sg:phone":"+61 2 9949 2217",
    "sg:postcode":"2093",
    "sg:province":"NSW",
    "sg:tags":[
        "plaque"
    ],
    "wof:name":"Perma Plaque",
    "wof:placetype":"venue"
},
  "geometry": {"coordinates":[151.26161193900001,-33.7859611511],"type":"Point"}
}