{
  "type": "Feature",
  "properties": {
    "iso:country":"AU",
    "sg:address":"6 Abbott Ave",
    "sg:city":"Morphett Vale",
    "sg:classifiers":[
        {
            "category":"Retail",
            "subcategory":"Driving School",
            "type":"Services"
        }
    ],
    "sg:phone":"+61 8 8326 6167",
    "sg:postcode":"5162",
    "sg:province":"SA",
    "wof:name":"5 Star Driver Training",
    "wof:placetype":"venue"
},
  "geometry": {"coordinates":[138.515167236,-35.1264228821],"type":"Point"}
}