{
  "type": "Feature",
  "properties": {
    "addr:full":"31 Poplar Pl Lugarno NSW 2210",
    "addr:housenumber":"31",
    "addr:postcode":"2210",
    "addr:street":"Poplar Pl",
    "iso:country":"AU",
    "sg:address":"31 Poplar Pl",
    "sg:city":"Lugarno",
    "sg:classifiers":[
        {
            "category":"Building & Trades",
            "subcategory":"Pest Control",
            "type":"Services"
        }
    ],
    "sg:phone":"+61 2 9534 8548",
    "sg:postcode":"2210",
    "sg:province":"NSW",
    "wof:name":"Thermal Solutions International",
    "wof:placetype":"venue"
},
  "geometry": {"coordinates":[151.04257200000001,-33.984127],"type":"Point"}
}