{
  "type": "Feature",
  "properties": {
    "iso:country":"AU",
    "sg:address":"127 Main St",
    "sg:city":"Lilydale",
    "sg:phone":"+61 3 9735 9204",
    "sg:postcode":"3140",
    "sg:province":"VIC",
    "wof:name":"One Stop Oils And Filters",
    "wof:placetype":"venue"
},
  "geometry": {"coordinates":[145.280715942,-37.7969894409],"type":"Point"}
}