{
  "type": "Feature",
  "properties": {
    "addr:full":"1 Thompson St Campbellfield VIC 3061",
    "addr:housenumber":"1",
    "addr:postcode":"3061",
    "addr:street":"Thompson St",
    "iso:country":"AU",
    "sg:address":"1 Thompson St",
    "sg:city":"Campbellfield",
    "sg:classifiers":[
        {
            "category":"Wholesale",
            "subcategory":"Painting Supplies",
            "type":"Manufacturing & Wholesale Goods"
        }
    ],
    "sg:phone":"+61 3 9359 5231",
    "sg:postcode":"3061",
    "sg:province":"VIC",
    "sg:tags":[
        "equipment",
        "spraying"
    ],
    "wof:name":"Spraychief Industries Pty Ltd",
    "wof:placetype":"venue"
},
  "geometry": {"coordinates":[144.956298828,-37.6851730347],"type":"Point"}
}