{
  "type": "Feature",
  "properties": {
    "addr:full":"118 Wellington St Mosman Park WA 6012",
    "addr:housenumber":"118",
    "addr:postcode":"6012",
    "addr:street":"Wellington St",
    "iso:country":"AU",
    "sg:address":"118 Wellington St",
    "sg:city":"Mosman Park",
    "sg:classifiers":[
        {
            "category":"Professional",
            "subcategory":"Art Services",
            "type":"Services"
        }
    ],
    "sg:phone":"+61 8 9384 4851",
    "sg:postcode":"6012",
    "sg:province":"WA",
    "sg:tags":[
        "interior",
        "decorator"
    ],
    "wof:name":"Design Co-Ordinates",
    "wof:placetype":"venue"
},
  "geometry": {"coordinates":[115.76862335200001,-32.0152740479],"type":"Point"}
}