{
  "type": "Feature",
  "properties": {
    "iso:country":"AU",
    "sg:address":"Suite 8/ 2 Warton Rd",
    "sg:city":"Huntingdale",
    "sg:classifiers":[
        {
            "category":"Health Services",
            "subcategory":"Health Practitioner",
            "type":"Services"
        }
    ],
    "sg:phone":"+61 8 9493 7070",
    "sg:postcode":"6110",
    "sg:province":"WA",
    "sg:tags":[
        "psychologist"
    ],
    "wof:name":"Bright Side Counselling",
    "wof:placetype":"venue"
},
  "geometry": {"coordinates":[115.953468323,-32.0815734863],"type":"Point"}
}