{
  "type": "Feature",
  "properties": {
    "iso:country":"AU",
    "sg:address":"22 Hayward Rd",
    "sg:city":"Ferntree Gully",
    "sg:classifiers":[
        {
            "category":"Retail",
            "subcategory":"Auto Repair",
            "type":"Services"
        }
    ],
    "sg:phone":"+61 3 9758 0620",
    "sg:postcode":"3156",
    "sg:province":"VIC",
    "sg:tags":[
        "repairer",
        "motor",
        "engineer"
    ],
    "wof:name":"Des & Gray's Automotive Services Pty Ltd",
    "wof:placetype":"venue"
},
  "geometry": {"coordinates":[145.26528930699999,-37.8810501099],"type":"Point"}
}