{
  "type": "Feature",
  "properties": {
    "addr:full":"41 Montagu St New Norfolk TAS 7140",
    "addr:housenumber":"41",
    "addr:postcode":"7140",
    "addr:street":"Montagu St",
    "iso:country":"AU",
    "sg:address":"41 Montagu St",
    "sg:city":"New Norfolk",
    "sg:classifiers":[
        {
            "category":"Personal",
            "subcategory":"Massage",
            "type":"Services"
        }
    ],
    "sg:phone":"+61 3 6261 4151",
    "sg:postcode":"7140",
    "sg:province":"TAS",
    "sg:tags":[
        "therapy"
    ],
    "wof:name":"Tony Kew's Australian Body-Tune Academy",
    "wof:placetype":"venue"
},
  "geometry": {"coordinates":[147.062546,-42.778389],"type":"Point"}
}