{
  "type": "Feature",
  "properties": {
    "addr:full":"PO Box 1270 Noosa Heads QLD 4567",
    "addr:postcode":"4567",
    "iso:country":"AU",
    "sg:address":"PO Box 1270",
    "sg:city":"Noosa Heads",
    "sg:classifiers":[
        {
            "category":"Building & Trades",
            "subcategory":"Construction",
            "type":"Services"
        }
    ],
    "sg:phone":"+61 7 5474 5706",
    "sg:postcode":"4567",
    "sg:province":"QLD",
    "sg:tags":[
        "contractor"
    ],
    "wof:name":"Ross Alan",
    "wof:placetype":"venue"
},
  "geometry": {"coordinates":[153.086105347,-26.3990192413],"type":"Point"}
}