{
  "type": "Feature",
  "properties": {
    "iso:country":"AU",
    "sg:address":"Prairie Vale Rd",
    "sg:city":"Wetherill Park",
    "sg:classifiers":[
        {
            "category":"Education",
            "subcategory":"School",
            "type":"Public Place"
        }
    ],
    "sg:phone":"+61 2 9725 5444",
    "sg:postcode":"2164",
    "sg:province":"NSW",
    "sg:tags":[
        "state",
        "-",
        "nsw"
    ],
    "wof:name":"Prairiewood High School",
    "wof:placetype":"venue"
},
  "geometry": {"coordinates":[150.90423584000001,-33.857624054],"type":"Point"}
}