{
  "type": "Feature",
  "properties": {
    "addr:full":"147 Soldiers Point Rd Soldiers Point NSW 2317",
    "addr:housenumber":"147",
    "addr:postcode":"2317",
    "addr:street":"Soldiers Point Rd",
    "iso:country":"AU",
    "sg:address":"147 Soldiers Point Rd",
    "sg:city":"Soldiers Point",
    "sg:classifiers":[
        {
            "category":"Personal",
            "subcategory":"Beauty Salon",
            "type":"Services"
        }
    ],
    "sg:phone":"+61 2 4916 0731",
    "sg:postcode":"2317",
    "sg:province":"NSW",
    "wof:name":"Shambhala Health & Beauty",
    "wof:placetype":"venue"
},
  "geometry": {"coordinates":[152.07202100000001,-32.712765],"type":"Point"}
}