{
  "type": "Feature",
  "properties": {
    "addr:full":"2/ 2 Pioneer Ave Thornleigh NSW 2120",
    "addr:housenumber":"/ 2",
    "addr:postcode":"2120",
    "addr:street":"Pioneer Ave",
    "iso:country":"AU",
    "sg:address":"2/ 2 Pioneer Ave",
    "sg:city":"Thornleigh",
    "sg:classifiers":[
        {
            "category":"Utilities",
            "subcategory":"Telephone",
            "type":"Services"
        }
    ],
    "sg:phone":"+61 2 9980 8222",
    "sg:postcode":"2120",
    "sg:province":"NSW",
    "sg:tags":[
        "accessory"
    ],
    "wof:name":"Applied Telephone Systems",
    "wof:placetype":"venue"
},
  "geometry": {"coordinates":[151.08355712900001,-33.7255058289],"type":"Point"}
}