{
  "type": "Feature",
  "properties": {
    "addr:full":"Unit 5, 2 Joule Pl Tuggerah NSW 2259",
    "addr:housenumber":"2",
    "addr:postcode":"2259",
    "addr:street":"Joule Pl",
    "iso:country":"AU",
    "sg:address":"Unit 5, 2 Joule Pl",
    "sg:city":"Tuggerah",
    "sg:classifiers":[
        {
            "category":"Social Services",
            "subcategory":"Child Care",
            "type":"Services"
        }
    ],
    "sg:phone":"+61 2 4351 9566",
    "sg:postcode":"2259",
    "sg:province":"NSW",
    "sg:tags":[
        "equipment",
        "identification"
    ],
    "wof:name":"Kegwrap",
    "wof:placetype":"venue"
},
  "geometry": {"coordinates":[151.417694092,-33.2984809875],"type":"Point"}
}