{
  "type": "Feature",
  "properties": {
    "iso:country":"AU",
    "sg:address":"3 Zenith Crt",
    "sg:city":"Regents Park",
    "sg:classifiers":[
        {
            "category":"Building & Trades",
            "subcategory":"Construction",
            "type":"Services"
        }
    ],
    "sg:phone":"+61 7 3800 5784",
    "sg:postcode":"4118",
    "sg:province":"QLD",
    "sg:tags":[
        "concrete",
        "paving"
    ],
    "wof:name":"Pinnacle Paving & Concrete",
    "wof:placetype":"venue"
},
  "geometry": {"coordinates":[153.04075622600001,-27.6815471649],"type":"Point"}
}