{
  "type": "Feature",
  "properties": {
    "iso:country":"AU",
    "sg:address":"50 Grobe Ave",
    "sg:city":"Narwee",
    "sg:classifiers":[
        {
            "category":"Professional",
            "subcategory":"Detective & Security Services",
            "type":"Services"
        }
    ],
    "sg:phone":"+61 2 9584 0247",
    "sg:postcode":"2209",
    "sg:province":"NSW",
    "sg:tags":[
        "guard",
        "patrol"
    ],
    "wof:name":"Live Protection",
    "wof:placetype":"venue"
},
  "geometry": {"coordinates":[151.067902,-33.942429],"type":"Point"}
}