{
  "type": "Feature",
  "properties": {
    "addr:full":"46 Punt Rd Cobram NSW 3644",
    "addr:housenumber":"46",
    "addr:postcode":"3644",
    "addr:street":"Punt Rd",
    "iso:country":"AU",
    "sg:address":"46 Punt Rd",
    "sg:city":"Cobram",
    "sg:classifiers":[
        {
            "category":"Personal",
            "subcategory":"Piercing",
            "type":"Services"
        }
    ],
    "sg:phone":"+61 3 5872 2810",
    "sg:postcode":"3644",
    "sg:province":"NSW",
    "sg:tags":[
        "body",
        "ear"
    ],
    "wof:name":"Harmonious Hair Design",
    "wof:placetype":"venue"
},
  "geometry": {"coordinates":[145.647094727,-35.9200820923],"type":"Point"}
}