{
  "type": "Feature",
  "properties": {
    "addr:full":"28 Drake St Osborne Park WA 6017",
    "addr:housenumber":"28",
    "addr:postcode":"6017",
    "addr:street":"Drake St",
    "iso:country":"AU",
    "sg:address":"28 Drake St",
    "sg:city":"Osborne Park",
    "sg:classifiers":[
        {
            "category":"Professional",
            "type":"Services"
        }
    ],
    "sg:phone":"+61 8 9443 3000",
    "sg:postcode":"6017",
    "sg:province":"WA",
    "sg:tags":[
        "spray",
        "painting"
    ],
    "wof:name":"Compleat Smash Repairs",
    "wof:placetype":"venue"
},
  "geometry": {"coordinates":[115.816299438,-31.9087600708],"type":"Point"}
}