{
  "type": "Feature",
  "properties": {
    "iso:country":"AU",
    "sg:address":"Unit 5/ 163 Prospect Hwy",
    "sg:city":"Seven Hills",
    "sg:classifiers":[
        {
            "category":"Retail",
            "subcategory":"Driving School",
            "type":"Services"
        }
    ],
    "sg:phone":"+61 1800 208 000",
    "sg:postcode":"2147",
    "sg:province":"NSW",
    "sg:tags":[
        "defensive",
        "advanced"
    ],
    "wof:name":"A. Sideways Action",
    "wof:placetype":"venue"
},
  "geometry": {"coordinates":[150.94151306099999,-33.7698440552],"type":"Point"}
}