{
  "type": "Feature",
  "properties": {
    "addr:full":"PO Box 26 Menangle NSW 2568",
    "addr:postcode":"2568",
    "iso:country":"AU",
    "sg:address":"PO Box 26",
    "sg:city":"Menangle",
    "sg:classifiers":[
        {
            "category":"Building & Trades",
            "subcategory":"Construction",
            "type":"Services"
        }
    ],
    "sg:phone":"+61 2 4633 8245",
    "sg:postcode":"2568",
    "sg:province":"NSW",
    "sg:tags":[
        "fencing",
        "contractor"
    ],
    "wof:name":"R & B Ferry Fencing Pty Ltd",
    "wof:placetype":"venue"
},
  "geometry": {"coordinates":[150.738647461,-34.1248168945],"type":"Point"}
}