{
  "type": "Feature",
  "properties": {
    "addr:full":"988 Logan Rd Holland Park QLD 4121",
    "addr:housenumber":"988",
    "addr:postcode":"4121",
    "addr:street":"Logan Rd",
    "iso:country":"AU",
    "sg:address":"988 Logan Rd",
    "sg:city":"Holland Park",
    "sg:classifiers":[
        {
            "category":"Manufacturing",
            "subcategory":"Jewelry",
            "type":"Manufacturing & Wholesale Goods"
        }
    ],
    "sg:phone":"+61 7 3847 9933",
    "sg:postcode":"4121",
    "sg:province":"QLD",
    "sg:tags":[
        "designer",
        "jewellery"
    ],
    "wof:name":"Stephen Dibb Jewellers",
    "wof:placetype":"venue"
},
  "geometry": {"coordinates":[153.062042236,-27.5196094513],"type":"Point"}
}