{
  "type": "Feature",
  "properties": {
    "iso:country":"AU",
    "sg:address":"27 Alice St",
    "sg:city":"Wellington Point",
    "sg:classifiers":[
        {
            "category":"Building & Trades",
            "subcategory":"Plumbing",
            "type":"Services"
        }
    ],
    "sg:phone":"+61 411 519 854",
    "sg:postcode":"4160",
    "sg:province":"QLD",
    "sg:tags":[
        "plumber",
        "gasfitters"
    ],
    "wof:name":"Wayne McDonald Plumbing Pty Ltd",
    "wof:placetype":"venue"
},
  "geometry": {"coordinates":[153.24232482900001,-27.4961833954],"type":"Point"}
}