{
  "type": "Feature",
  "properties": {
    "addr:full":"9 Apperly St Fitzroy North VIC 3068",
    "addr:housenumber":"9",
    "addr:postcode":"3068",
    "addr:street":"Apperly St",
    "iso:country":"AU",
    "sg:address":"9 Apperly St",
    "sg:city":"Fitzroy North",
    "sg:classifiers":[
        {
            "category":"Professional",
            "type":"Services"
        }
    ],
    "sg:phone":"+61 412 998 918",
    "sg:postcode":"3068",
    "sg:province":"VIC",
    "sg:tags":[
        "shop",
        "fitting"
    ],
    "wof:name":"Whittaker Contract Pty Ltd",
    "wof:placetype":"venue"
},
  "geometry": {"coordinates":[144.98617553700001,-37.7813262939],"type":"Point"}
}