{
  "type": "Feature",
  "properties": {
    "iso:country":"AU",
    "sg:address":"6 a Mount Joy Pde",
    "sg:city":"Lorne",
    "sg:classifiers":[
        {
            "category":"Restaurant",
            "type":"Food & Drink"
        }
    ],
    "sg:phone":"+61 3 5289 1808",
    "sg:postcode":"3232",
    "sg:province":"VIC",
    "wof:name":"Ba Ba Lu Bar",
    "wof:placetype":"venue"
},
  "geometry": {"coordinates":[143.97363300000001,-38.53577],"type":"Point"}
}