{
  "type": "Feature",
  "properties": {
    "iso:country":"AU",
    "sg:address":"Unit 4, 7 St James Pl",
    "sg:city":"Seven Hills",
    "sg:classifiers":[
        {
            "category":"Banks & Credit Unions",
            "subcategory":"Financial Services",
            "type":"Services"
        }
    ],
    "sg:phone":"+61 2 9674 8188",
    "sg:postcode":"2147",
    "sg:province":"NSW",
    "sg:tags":[
        "wholesaler",
        "pencil",
        "pen",
        "mfrs"
    ],
    "wof:name":"Capax (Australia) Pty Ltd",
    "wof:placetype":"venue"
},
  "geometry": {"coordinates":[150.952835083,-33.7744026184],"type":"Point"}
}