{
  "type": "Feature",
  "properties": {
    "iso:country":"AU",
    "sg:address":"19 Bondel Pl",
    "sg:city":"Mt Ommaney",
    "sg:classifiers":[
        {
            "category":"Shopping",
            "subcategory":"Gifts & Souvenirs",
            "type":"Retail Goods"
        }
    ],
    "sg:phone":"+61 7 3279 7533",
    "sg:postcode":"4074",
    "sg:province":"QLD",
    "sg:tags":[
        "shop",
        "supply"
    ],
    "wof:name":"Contact Enterprises Australia Pty Ltd",
    "wof:placetype":"venue"
},
  "geometry": {"coordinates":[152.93089294399999,-27.5455131531],"type":"Point"}
}