{
  "type": "Feature",
  "properties": {
    "addr:full":"6 Russell St Evandale TAS 7212",
    "addr:housenumber":"6",
    "addr:postcode":"7212",
    "addr:street":"Russell St",
    "iso:country":"AU",
    "sg:address":"6 Russell St",
    "sg:city":"Evandale",
    "sg:classifiers":[
        {
            "category":"Professional",
            "type":"Services"
        }
    ],
    "sg:phone":"+61 3 6391 9191",
    "sg:postcode":"7212",
    "sg:province":"TAS",
    "sg:tags":[
        "auctioneer"
    ],
    "wof:name":"Evandale Antiques",
    "wof:placetype":"venue"
},
  "geometry": {"coordinates":[147.25199900000001,-41.5784],"type":"Point"}
}