{
  "type": "Feature",
  "properties": {
    "addr:full":"597 Pittwater Rd North Dee Why NSW 2099",
    "addr:housenumber":"597",
    "addr:postcode":"2099",
    "addr:street":"Pittwater Rd North",
    "iso:country":"AU",
    "sg:address":"597 Pittwater Rd North",
    "sg:city":"Dee Why",
    "sg:classifiers":[
        {
            "category":"Home & Garden",
            "subcategory":"Building Materials",
            "type":"Retail Goods"
        }
    ],
    "sg:phone":"+61 411 143 308",
    "sg:postcode":"2099",
    "sg:province":"NSW",
    "sg:tags":[
        "lawn",
        "cutting",
        "maintenance"
    ],
    "wof:name":"Supreme Mowing",
    "wof:placetype":"venue"
},
  "geometry": {"coordinates":[151.287719727,-33.7516593933],"type":"Point"}
}