{
  "type": "Feature",
  "properties": {
    "addr:full":"30A Young St Preston VIC 3072",
    "addr:housenumber":"30a",
    "addr:postcode":"3072",
    "addr:street":"Young St",
    "iso:country":"AU",
    "sg:address":"30A Young St",
    "sg:city":"Preston",
    "sg:classifiers":[
        {
            "category":"Health Services",
            "subcategory":"Health Practitioner",
            "type":"Services"
        }
    ],
    "sg:phone":"+61 3 9484 9502",
    "sg:postcode":"3072",
    "sg:province":"VIC",
    "sg:tags":[
        "naturopath"
    ],
    "wof:name":"Cheryl O&#039;Neill",
    "wof:placetype":"venue"
},
  "geometry": {"coordinates":[145.00852966299999,-37.7473335266],"type":"Point"}
}