{
  "type": "Feature",
  "properties": {
    "iso:country":"AU",
    "sg:address":"102 Gosport St",
    "sg:city":"Hemmant",
    "sg:classifiers":[
        {
            "category":"Professional",
            "type":"Services"
        }
    ],
    "sg:phone":"+61 7 3348 3222",
    "sg:postcode":"4174",
    "sg:province":"QLD",
    "sg:tags":[
        "auctioneer"
    ],
    "wof:name":"WWA Australia Pty Ltd",
    "wof:placetype":"venue"
},
  "geometry": {"coordinates":[153.13446044899999,-27.4389877319],"type":"Point"}
}