{
  "type": "Feature",
  "properties": {
    "addr:full":"325 Bay St Port Melbourne VIC 3207",
    "addr:housenumber":"325",
    "addr:postcode":"3207",
    "addr:street":"Bay St",
    "iso:country":"AU",
    "sg:address":"325 Bay St",
    "sg:city":"Port Melbourne",
    "sg:classifiers":[
        {
            "category":"Real Estate",
            "subcategory":"Real Estate Agent",
            "type":"Services"
        }
    ],
    "sg:phone":"+61 3 9646 4444",
    "sg:postcode":"3207",
    "sg:province":"VIC",
    "wof:name":"Chisholm & Gamon Property",
    "wof:placetype":"venue"
},
  "geometry": {"coordinates":[144.94433599999999,-37.836193],"type":"Point"}
}