{
  "type": "Feature",
  "properties": {
    "iso:country":"AU",
    "sg:address":"69 Erin St",
    "sg:city":"Richmond",
    "sg:classifiers":[
        {
            "category":"Health Services",
            "subcategory":"Health Practitioner",
            "type":"Services"
        }
    ],
    "sg:phone":"+61 3 9429 1677",
    "sg:postcode":"3121",
    "sg:province":"VIC",
    "sg:tags":[
        "psychologist"
    ],
    "wof:name":"Beattie Laraine P",
    "wof:placetype":"venue"
},
  "geometry": {"coordinates":[144.993896484,-37.8165397644],"type":"Point"}
}