{
  "type": "Feature",
  "properties": {
    "iso:country":"AU",
    "sg:address":"80 Reid St",
    "sg:city":"Wangaratta",
    "sg:classifiers":[
        {
            "category":"Health Services",
            "subcategory":"Optometrist",
            "type":"Services"
        }
    ],
    "sg:phone":"+61 3 5721 9733",
    "sg:postcode":"3676",
    "sg:province":"VIC",
    "wof:name":"Wangaratta Eyecare",
    "wof:placetype":"venue"
},
  "geometry": {"coordinates":[146.32531700000001,-36.353848],"type":"Point"}
}