{
  "type": "Feature",
  "properties": {
    "iso:country":"AU",
    "sg:address":"38 Leeds Rd",
    "sg:city":"Mt Waverley",
    "sg:classifiers":[
        {
            "category":"Professional",
            "subcategory":"Art Services",
            "type":"Services"
        }
    ],
    "sg:phone":"+61 3 9803 4421",
    "sg:postcode":"3149",
    "sg:province":"VIC",
    "sg:tags":[
        "product",
        "industrial",
        "designer"
    ],
    "wof:name":"Design Dynamics Pty Ltd",
    "wof:placetype":"venue"
},
  "geometry": {"coordinates":[145.13804626500001,-37.8626861572],"type":"Point"}
}