{
  "type": "Feature",
  "properties": {
    "addr:full":"Unit 23/ 152 Melbourne St North Adelaide SA 5006",
    "addr:housenumber":"/ 152",
    "addr:postcode":"5006",
    "addr:street":"Melbourne St",
    "iso:country":"AU",
    "sg:address":"Unit 23/ 152 Melbourne St",
    "sg:city":"North Adelaide",
    "sg:classifiers":[
        {
            "category":"Health Services",
            "subcategory":"Doctor",
            "type":"Services"
        }
    ],
    "sg:phone":"+61 8 8367 0788",
    "sg:postcode":"5006",
    "sg:province":"SA",
    "sg:tags":[
        "medical",
        "practitioner"
    ],
    "wof:name":"Dr Nathan Francis",
    "wof:placetype":"venue"
},
  "geometry": {"coordinates":[138.60621643100001,-34.9075164795],"type":"Point"}
}