{
  "type": "Feature",
  "properties": {
    "iso:country":"AU",
    "sg:address":"Shop 6, 914 Military Rd",
    "sg:city":"Mosman",
    "sg:classifiers":[
        {
            "category":"Communications",
            "subcategory":"Film & Video Production",
            "type":"Services"
        }
    ],
    "sg:phone":"+61 2 9960 5040",
    "sg:postcode":"2088",
    "sg:province":"NSW",
    "sg:tags":[
        "linen",
        "good"
    ],
    "wof:name":"HouseHold Linens",
    "wof:placetype":"venue"
},
  "geometry": {"coordinates":[151.244384766,-33.8306999207],"type":"Point"}
}