{
  "type": "Feature",
  "properties": {
    "addr:full":"Unit 2, 73 Dobney Ave Wagga Wagga NSW 2650",
    "addr:housenumber":"73",
    "addr:postcode":"2650",
    "addr:street":"Dobney Ave",
    "iso:country":"AU",
    "sg:address":"Unit 2, 73 Dobney Ave",
    "sg:city":"Wagga Wagga",
    "sg:classifiers":[
        {
            "category":"Retail",
            "subcategory":"Auto Repair",
            "type":"Services"
        }
    ],
    "sg:phone":"+61 2 6925 5248",
    "sg:postcode":"2650",
    "sg:province":"NSW",
    "sg:tags":[
        "wheel",
        "balancing",
        "alignment"
    ],
    "wof:name":"Wagga Brake & Steering Specialists",
    "wof:placetype":"venue"
},
  "geometry": {"coordinates":[147.34104919399999,-35.1242179871],"type":"Point"}
}