{
  "type": "Feature",
  "properties": {
    "addr:full":"Pacific Hwy Herons Creek NSW 2443",
    "addr:postcode":"2443",
    "addr:street":"Pacific Hwy",
    "iso:country":"AU",
    "sg:address":"Pacific Hwy",
    "sg:city":"Herons Creek",
    "sg:classifiers":[
        {
            "category":"Food & Beverages",
            "subcategory":"Groceries & Convenience Stores",
            "type":"Retail Goods"
        }
    ],
    "sg:phone":"+61 2 6585 7121",
    "sg:postcode":"2443",
    "sg:province":"NSW",
    "sg:tags":[
        "merchant",
        "egg"
    ],
    "wof:name":"Bartlett Farms",
    "wof:placetype":"venue"
},
  "geometry": {"coordinates":[152.74023399999999,-31.561094],"type":"Point"}
}