{
  "type": "Feature",
  "properties": {
    "addr:full":"Shop 88 Station St Ferntree Gully VIC 3156",
    "addr:housenumber":"shop 88",
    "addr:postcode":"3156",
    "addr:street":"Station St",
    "iso:country":"AU",
    "sg:address":"Shop 88 Station St",
    "sg:city":"Ferntree Gully",
    "sg:classifiers":[
        {
            "category":"Professional",
            "subcategory":"Computer Services",
            "type":"Services"
        }
    ],
    "sg:phone":"+61 3 9758 9201",
    "sg:postcode":"3156",
    "sg:province":"VIC",
    "sg:tags":[
        "repairs",
        "upgrade",
        "equipment"
    ],
    "wof:name":"Amos Electronics",
    "wof:placetype":"venue"
},
  "geometry": {"coordinates":[145.29550170900001,-37.8828125],"type":"Point"}
}