{
  "type": "Feature",
  "properties": {
    "addr:full":"25 Sixteenth Ave West Hoxton NSW 2171",
    "addr:housenumber":"25",
    "addr:postcode":"2171",
    "addr:street":"Sixteenth Ave West",
    "iso:country":"AU",
    "sg:address":"25 Sixteenth Ave",
    "sg:city":"West Hoxton",
    "sg:classifiers":[
        {
            "category":"Retail",
            "subcategory":"Auto Repair",
            "type":"Services"
        }
    ],
    "sg:phone":"+61 2 9606 9570",
    "sg:postcode":"2171",
    "sg:province":"NSW",
    "sg:tags":[
        "repairer",
        "motor",
        "engineer"
    ],
    "wof:name":"Wynup Pty Ltd",
    "wof:placetype":"venue"
},
  "geometry": {"coordinates":[150.84849548299999,-33.9200706482],"type":"Point"}
}