{
  "type": "Feature",
  "properties": {
    "iso:country":"AU",
    "sg:address":"Shop 31, Westfield Shopng Cnt, 328-335 North Rocks Rd",
    "sg:city":"North Rocks",
    "sg:classifiers":[
        {
            "category":"Shopping",
            "subcategory":"Mobile Phones",
            "type":"Retail Goods"
        }
    ],
    "sg:phone":"+61 2 9873 3444",
    "sg:postcode":"2151",
    "sg:province":"NSW",
    "sg:tags":[
        "telephone",
        "accessory"
    ],
    "wof:name":"Vodafone North Rocks",
    "wof:placetype":"venue"
},
  "geometry": {"coordinates":[151.025222778,-33.7712783813],"type":"Point"}
}