{
  "type": "Feature",
  "properties": {
    "addr:full":"2 Nugent St Monbulk VIC 3793",
    "addr:housenumber":"2",
    "addr:postcode":"3793",
    "addr:street":"Nugent St",
    "iso:country":"AU",
    "sg:address":"2 Nugent St",
    "sg:city":"Monbulk",
    "sg:classifiers":[
        {
            "category":"Retail",
            "subcategory":"Veterinary Services",
            "type":"Services"
        }
    ],
    "sg:phone":"+61 3 9752 1001",
    "sg:postcode":"3793",
    "sg:province":"VIC",
    "sg:tags":[
        "surgeon"
    ],
    "wof:name":"Andrew Byrne",
    "wof:placetype":"venue"
},
  "geometry": {"coordinates":[145.408004761,-37.8763923645],"type":"Point"}
}