{
  "type": "Feature",
  "properties": {
    "iso:country":"AU",
    "sg:address":"487 Ebden St",
    "sg:city":"Albury",
    "sg:classifiers":[
        {
            "category":"Fast Food",
            "type":"Food & Drink"
        }
    ],
    "sg:phone":"+61 2 6021 4433",
    "sg:postcode":"2640",
    "sg:province":"NSW",
    "sg:tags":[
        "away",
        "take"
    ],
    "wof:name":"J T's Take Away",
    "wof:placetype":"venue"
},
  "geometry": {"coordinates":[146.90957641599999,-36.0885047913],"type":"Point"}
}