{
  "type": "Feature",
  "properties": {
    "addr:full":"18 Kane St Kingsley WA 6026",
    "addr:housenumber":"18",
    "addr:postcode":"6026",
    "addr:street":"Kane St",
    "iso:country":"AU",
    "sg:address":"18 Kane St",
    "sg:city":"Kingsley",
    "sg:classifiers":[
        {
            "category":"Building & Trades",
            "subcategory":"Construction",
            "type":"Services"
        }
    ],
    "sg:phone":"+61 427 989 416",
    "sg:postcode":"6026",
    "sg:province":"WA",
    "sg:tags":[
        "joiner",
        "carpenter"
    ],
    "wof:name":"T & G Carpentry",
    "wof:placetype":"venue"
},
  "geometry": {"coordinates":[115.802268982,-31.8187141418],"type":"Point"}
}