{
  "type": "Feature",
  "properties": {
    "addr:full":"23b Vermont St Nollamara WA 6061",
    "addr:housenumber":"23b",
    "addr:postcode":"6061",
    "addr:street":"Vermont St",
    "iso:country":"AU",
    "sg:address":"23b Vermont St",
    "sg:city":"Nollamara",
    "sg:classifiers":[
        {
            "category":"Professional",
            "subcategory":"Engineering",
            "type":"Services"
        }
    ],
    "sg:phone":"+61 8 9440 3147",
    "sg:postcode":"6061",
    "sg:province":"WA",
    "sg:tags":[
        "engineer"
    ],
    "wof:name":"Vortexian Technology",
    "wof:placetype":"venue"
},
  "geometry": {"coordinates":[115.835899353,-31.8793334961],"type":"Point"}
}