{
  "type": "Feature",
  "properties": {
    "iso:country":"AU",
    "sg:address":"PO Box 6050",
    "sg:city":"Linden Park",
    "sg:classifiers":[
        {
            "category":"Building & Trades",
            "subcategory":"Landscaping Services",
            "type":"Services"
        }
    ],
    "sg:phone":"+61 8 8261 0433",
    "sg:postcode":"5065",
    "sg:province":"SA",
    "sg:tags":[
        "designer",
        "landscape",
        "contractor"
    ],
    "wof:name":"Superior Gardens",
    "wof:placetype":"venue"
},
  "geometry": {"coordinates":[138.643844605,-34.9391708374],"type":"Point"}
}