{
  "type": "Feature",
  "properties": {
    "addr:full":"1 Glebe Rd Ipswich QLD 4305",
    "addr:housenumber":"1",
    "addr:postcode":"4305",
    "addr:street":"Glebe Rd",
    "iso:country":"AU",
    "sg:address":"1 Glebe Rd",
    "sg:city":"Ipswich",
    "sg:classifiers":[
        {
            "category":"Autos & Motor Vehicles",
            "subcategory":"Automobile Sales",
            "type":"Retail Goods"
        }
    ],
    "sg:phone":"+61 7 3812 5577",
    "sg:postcode":"4305",
    "sg:province":"QLD",
    "sg:tags":[
        "car",
        "used"
    ],
    "wof:name":"Just Nice Cars",
    "wof:placetype":"venue"
},
  "geometry": {"coordinates":[152.77134704599999,-27.6153430939],"type":"Point"}
}