{
  "type": "Feature",
  "properties": {
    "iso:country":"AU",
    "sg:address":"323 South Rd",
    "sg:city":"Croydon Park",
    "sg:classifiers":[
        {
            "category":"Personal",
            "subcategory":"Adult",
            "type":"Services"
        }
    ],
    "sg:phone":"+61 8 8340 2228",
    "sg:postcode":"5008",
    "sg:province":"SA",
    "sg:tags":[
        "product"
    ],
    "wof:name":"Liba Teez",
    "wof:placetype":"venue"
},
  "geometry": {"coordinates":[138.57170099999999,-34.878445],"type":"Point"}
}