{
  "type": "Feature",
  "properties": {
    "addr:full":"975 High St Reservoir VIC 3073",
    "addr:housenumber":"975",
    "addr:postcode":"3073",
    "addr:street":"High St",
    "iso:country":"AU",
    "sg:address":"975 High St",
    "sg:city":"Reservoir",
    "sg:classifiers":[
        {
            "category":"Health Services",
            "subcategory":"Doctor",
            "type":"Services"
        }
    ],
    "sg:phone":"+61 3 9470 1954",
    "sg:postcode":"3073",
    "sg:province":"VIC",
    "sg:tags":[
        "medical",
        "practitioner"
    ],
    "wof:name":"John Buchanan ,I A Swain & G Pearce & C Roy-Chowdhury",
    "wof:placetype":"venue"
},
  "geometry": {"coordinates":[145.008865356,-37.7079238892],"type":"Point"}
}