{
  "type": "Feature",
  "properties": {
    "iso:country":"AU",
    "sg:address":"1114 North East Rd",
    "sg:city":"St Agnes",
    "sg:classifiers":[
        {
            "category":"Shopping",
            "subcategory":"Crafts & Fabrics",
            "type":"Retail Goods"
        }
    ],
    "sg:phone":"+61 8 8263 1892",
    "sg:postcode":"5097",
    "sg:province":"SA",
    "sg:tags":[
        "supply"
    ],
    "wof:name":"Genesis Creations Silk & Fabric Painting",
    "wof:placetype":"venue"
},
  "geometry": {"coordinates":[138.70986938499999,-34.8242416382],"type":"Point"}
}