{
  "type": "Feature",
  "properties": {
    "addr:full":"1st fl Marian House 1002 Mair St Ballarat VIC 3350",
    "addr:housenumber":"1002",
    "addr:postcode":"3350",
    "addr:street":"Mair St",
    "iso:country":"AU",
    "sg:address":"1st fl Marian House 1002 Mair St",
    "sg:city":"Ballarat",
    "sg:classifiers":[
        {
            "category":"Health Services",
            "subcategory":"Doctor",
            "type":"Services"
        }
    ],
    "sg:phone":"+61 3 5331 2900",
    "sg:postcode":"3350",
    "sg:province":"VIC",
    "sg:tags":[
        "medical",
        "practitioner"
    ],
    "wof:name":"Zehnwirth H",
    "wof:placetype":"venue"
},
  "geometry": {"coordinates":[143.846146,-37.558479],"type":"Point"}
}