{
  "type": "Feature",
  "properties": {
    "addr:full":"West St Toowoomba QLD 4350",
    "addr:postcode":"4350",
    "addr:street":"West St",
    "iso:country":"AU",
    "sg:address":"West St",
    "sg:city":"Toowoomba",
    "sg:classifiers":[
        {
            "category":"Retail",
            "subcategory":"Event Space",
            "type":"Services"
        }
    ],
    "sg:phone":"+61 7 4631 2730",
    "sg:postcode":"4350",
    "sg:province":"QLD",
    "sg:tags":[
        "function",
        "organiser"
    ],
    "wof:name":"USQ Fast &#039;n&#039; Fresh Refectory",
    "wof:placetype":"venue"
},
  "geometry": {"coordinates":[151.94215399999999,-27.566767],"type":"Point"}
}