{
  "type": "Feature",
  "properties": {
    "iso:country":"AU",
    "sg:address":"56 Petken Drv",
    "sg:city":"Taree",
    "sg:classifiers":[
        {
            "category":"Building & Trades",
            "subcategory":"Construction",
            "type":"Services"
        }
    ],
    "sg:phone":"+61 2 6552 4260",
    "sg:postcode":"2430",
    "sg:province":"NSW",
    "sg:tags":[
        "plasterboard",
        "plasterer",
        "fixer"
    ],
    "wof:name":"Currie S G",
    "wof:placetype":"venue"
},
  "geometry": {"coordinates":[152.435867,-31.917685],"type":"Point"}
}