{
  "type": "Feature",
  "properties": {
    "addr:full":"251 New South Head Rd Edgecliff NSW 2027",
    "addr:housenumber":"251",
    "addr:postcode":"2027",
    "addr:street":"New South Head Rd",
    "iso:country":"AU",
    "sg:address":"251 New South Head Rd",
    "sg:city":"Edgecliff",
    "sg:classifiers":[
        {
            "category":"Food & Beverages",
            "subcategory":"Fruits & Vegetables",
            "type":"Retail Goods"
        }
    ],
    "sg:phone":"+61 2 9328 7782",
    "sg:postcode":"2027",
    "sg:province":"NSW",
    "sg:tags":[
        "greengrocer",
        "fruiterer"
    ],
    "wof:name":"Harris Farm Markets",
    "wof:placetype":"venue"
},
  "geometry": {"coordinates":[151.23695373499999,-33.8790054321],"type":"Point"}
}