{
  "type": "Feature",
  "properties": {
    "iso:country":"AU",
    "sg:address":"33 Portman St",
    "sg:city":"Oakleigh",
    "sg:classifiers":[
        {
            "category":"Health Services",
            "subcategory":"Optometrist",
            "type":"Services"
        }
    ],
    "sg:phone":"+61 3 9568 3442",
    "sg:postcode":"3166",
    "sg:province":"VIC",
    "wof:name":"Wakeling Stephen B",
    "wof:placetype":"venue"
},
  "geometry": {"coordinates":[145.09034729000001,-37.9000205994],"type":"Point"}
}