{
  "type": "Feature",
  "properties": {
    "addr:full":"30 Grahamvale Rd Shepparton VIC 3630",
    "addr:housenumber":"30",
    "addr:postcode":"3630",
    "addr:street":"Grahamvale Rd",
    "iso:country":"AU",
    "sg:address":"30 Grahamvale Rd",
    "sg:city":"Shepparton",
    "sg:classifiers":[
        {
            "category":"Utilities",
            "subcategory":"Electric",
            "type":"Services"
        }
    ],
    "sg:phone":"+61 418 575 928",
    "sg:postcode":"3630",
    "sg:province":"VIC",
    "sg:tags":[
        "electrical",
        "contractor"
    ],
    "wof:name":"Albert Qose",
    "wof:placetype":"venue"
},
  "geometry": {"coordinates":[145.432037353,-36.3625259399],"type":"Point"}
}