{
  "type": "Feature",
  "properties": {
    "addr:full":"7 Larbert Ave Wahroonga NSW 2076",
    "addr:housenumber":"7",
    "addr:postcode":"2076",
    "addr:street":"Larbert Ave",
    "iso:country":"AU",
    "sg:address":"7 Larbert Ave",
    "sg:city":"Wahroonga",
    "sg:classifiers":[
        {
            "category":"Real Estate",
            "subcategory":"Architect",
            "type":"Services"
        }
    ],
    "sg:phone":"+61 2 9489 1816",
    "sg:postcode":"2076",
    "sg:province":"NSW",
    "wof:name":"Shea Robert J & Associates",
    "wof:placetype":"venue"
},
  "geometry": {"coordinates":[151.12904357900001,-33.7200088501],"type":"Point"}
}