{
  "type": "Feature",
  "properties": {
    "iso:country":"AU",
    "sg:address":"1 Apollo Crt",
    "sg:city":"Victoria Point",
    "sg:classifiers":[
        {
            "category":"Real Estate",
            "subcategory":"Real Estate Agent",
            "type":"Services"
        }
    ],
    "sg:phone":"+61 418 841 878",
    "sg:postcode":"4165",
    "sg:province":"QLD",
    "sg:tags":[
        "handyman's",
        "equipment",
        "hire",
        "builders",
        "contractor"
    ],
    "wof:name":"Apollo Bobcats",
    "wof:placetype":"venue"
},
  "geometry": {"coordinates":[153.27398681599999,-27.5887451172],"type":"Point"}
}