{
  "type": "Feature",
  "properties": {
    "addr:full":"Shop 3/ 26 Hill St Emu Park QLD 4702",
    "addr:housenumber":"shop 3 / 26",
    "addr:postcode":"4702",
    "addr:street":"Hill St",
    "iso:country":"AU",
    "sg:address":"Shop 3/ 26 Hill St",
    "sg:city":"Emu Park",
    "sg:classifiers":[
        {
            "category":"Real Estate",
            "subcategory":"Real Estate Agent",
            "type":"Services"
        }
    ],
    "sg:phone":"+61 7 4938 8112",
    "sg:postcode":"4702",
    "sg:province":"QLD",
    "wof:name":"Lyn Solito Real Estate",
    "wof:placetype":"venue"
},
  "geometry": {"coordinates":[150.329147339,-23.4824829102],"type":"Point"}
}