{
  "type": "Feature",
  "properties": {
    "iso:country":"AU",
    "sg:address":"59 Burnett St",
    "sg:city":"Buderim",
    "sg:classifiers":[
        {
            "category":"Shopping",
            "subcategory":"Clothing, Apparel, & Fashions",
            "type":"Retail Goods"
        }
    ],
    "sg:phone":"+61 7 5456 2570",
    "sg:postcode":"4556",
    "sg:province":"QLD",
    "sg:tags":[
        "lady",
        "wear"
    ],
    "wof:name":"Kooshka",
    "wof:placetype":"venue"
},
  "geometry": {"coordinates":[153.04966735799999,-26.6869373322],"type":"Point"}
}