{
  "type": "Feature",
  "properties": {
    "addr:full":"258a Main Rd Toukley NSW 2263",
    "addr:housenumber":"258a",
    "addr:postcode":"2263",
    "addr:street":"Main Rd",
    "iso:country":"AU",
    "sg:address":"258a Main Rd",
    "sg:city":"Toukley",
    "sg:classifiers":[
        {
            "category":"Shopping",
            "subcategory":"Clothing, Apparel, & Fashions",
            "type":"Retail Goods"
        }
    ],
    "sg:phone":"+61 2 4396 9566",
    "sg:postcode":"2263",
    "sg:province":"NSW",
    "sg:tags":[
        "boutique"
    ],
    "wof:name":"C C's Boutique",
    "wof:placetype":"venue"
},
  "geometry": {"coordinates":[151.54331999999999,-33.26424],"type":"Point"}
}