{
  "type": "Feature",
  "properties": {
    "addr:full":"12 Crescent St Gatton QLD 4343",
    "addr:housenumber":"12",
    "addr:postcode":"4343",
    "addr:street":"Crescent St",
    "iso:country":"AU",
    "sg:address":"12 Crescent St",
    "sg:city":"Gatton",
    "sg:classifiers":[
        {
            "category":"Autos & Motor Vehicles",
            "subcategory":"Auto Supplies",
            "type":"Retail Goods"
        }
    ],
    "sg:phone":"+61 7 5462 2432",
    "sg:postcode":"4343",
    "sg:province":"QLD",
    "sg:tags":[
        "accessory"
    ],
    "wof:name":"Gatton Performance Centre",
    "wof:placetype":"venue"
},
  "geometry": {"coordinates":[152.27923584000001,-27.5558586121],"type":"Point"}
}