{
  "type": "Feature",
  "properties": {
    "addr:full":"Cnr Ditchingham Plce & Piggott Rd Australind WA 6233",
    "addr:postcode":"6233",
    "addr:street":"Cnr;Piggott Rd",
    "iso:country":"AU",
    "sg:address":"Cnr Ditchingham Plce & Piggott Rd",
    "sg:city":"Australind",
    "sg:classifiers":[
        {
            "category":"Professional",
            "subcategory":"Testing Lab",
            "type":"Services"
        }
    ],
    "sg:phone":"+61 8 9796 1188",
    "sg:postcode":"6233",
    "sg:province":"WA",
    "sg:tags":[
        "inspection"
    ],
    "wof:name":"NDT Site Services Pty Ltd",
    "wof:placetype":"venue"
},
  "geometry": {"coordinates":[115.744423,-33.279263],"type":"Point"}
}