{
  "type": "Feature",
  "properties": {
    "iso:country":"AU",
    "sg:address":"88- 90 Sylvan Rd",
    "sg:city":"Towong",
    "sg:classifiers":[
        {
            "category":"Banks & Credit Unions",
            "subcategory":"Bank",
            "type":"Services"
        }
    ],
    "sg:phone":"+61 1300 733 281",
    "sg:postcode":"3707",
    "sg:province":"NSW",
    "sg:tags":[
        "broker",
        "mortgage"
    ],
    "wof:name":"Sasama Finance Pty Ltd",
    "wof:placetype":"venue"
},
  "geometry": {"coordinates":[147.996017456,-36.124080658],"type":"Point"}
}