{
  "type": "Feature",
  "properties": {
    "addr:full":"17 Dampier St Warrane TAS 7018",
    "addr:housenumber":"17",
    "addr:postcode":"7018",
    "addr:street":"Dampier St",
    "iso:country":"AU",
    "sg:address":"17 Dampier St",
    "sg:city":"Warrane",
    "sg:classifiers":[
        {
            "category":"Fast Food",
            "type":"Food & Drink"
        }
    ],
    "sg:phone":"+61 3 6244 1729",
    "sg:postcode":"7018",
    "sg:province":"TAS",
    "sg:tags":[
        "away",
        "take"
    ],
    "wof:name":"Warrane Take Away",
    "wof:placetype":"venue"
},
  "geometry": {"coordinates":[147.381515503,-42.8572311401],"type":"Point"}
}