{
  "type": "Feature",
  "properties": {
    "addr:full":"Fountain Gate, Unit 4 Overland Drive Narre Warren VIC 3805",
    "addr:postcode":"3805",
    "addr:street":"Overland Drive",
    "iso:country":"AU",
    "sg:address":"Fountain Gate, Unit 4",
    "sg:city":"Overland Drive Narre Warren",
    "sg:classifiers":[
        {
            "category":"Recreation",
            "subcategory":"Fishing",
            "type":"Entertainment"
        }
    ],
    "sg:phone":"+61 3 9796 6677",
    "sg:postcode":"3805",
    "sg:province":"VIC",
    "sg:tags":[
        "tackle"
    ],
    "wof:name":"Got One",
    "wof:placetype":"venue"
},
  "geometry": {"coordinates":[145.30354299999999,-38.019981],"type":"Point"}
}