{
  "type": "Feature",
  "properties": {
    "addr:full":"36 Princess St Bundaberg QLD 4670",
    "addr:housenumber":"36",
    "addr:postcode":"4670",
    "addr:street":"Princess St",
    "iso:country":"AU",
    "sg:address":"36 Princess St",
    "sg:city":"Bundaberg",
    "sg:classifiers":[
        {
            "category":"Building & Trades",
            "subcategory":"Locksmith",
            "type":"Services"
        }
    ],
    "sg:phone":"+61 7 4153 6242",
    "sg:postcode":"4670",
    "sg:province":"QLD",
    "sg:tags":[
        "lock"
    ],
    "sg:website":"http://www.activelock.com.au",
    "wof:name":"Active Lock & Key",
    "wof:placetype":"venue"
},
  "geometry": {"coordinates":[152.36843872099999,-24.8599739075],"type":"Point"}
}