{
  "type": "Feature",
  "properties": {
    "addr:full":"12 Oxford Rd Strathfield NSW 2135",
    "addr:housenumber":"12",
    "addr:postcode":"2135",
    "addr:street":"Oxford Rd",
    "iso:country":"AU",
    "sg:address":"12 Oxford Rd",
    "sg:city":"Strathfield",
    "sg:classifiers":[
        {
            "category":"Government",
            "subcategory":"Court House",
            "type":"Public Place"
        }
    ],
    "sg:phone":"+61 2 9764 2700",
    "sg:postcode":"2135",
    "sg:province":"NSW",
    "sg:tags":[
        "personal",
        "marriage",
        "family",
        "counselling"
    ],
    "wof:name":"Strathfield Counselling",
    "wof:placetype":"venue"
},
  "geometry": {"coordinates":[151.08561706500001,-33.8746070862],"type":"Point"}
}