{
  "type": "Feature",
  "properties": {
    "addr:full":"PO Box 4048 Dandenong VIC 3175",
    "addr:postcode":"3175",
    "iso:country":"AU",
    "sg:address":"PO Box 4048",
    "sg:city":"Dandenong",
    "sg:classifiers":[
        {
            "category":"Wholesale",
            "subcategory":"Machinery & Supplies",
            "type":"Manufacturing & Wholesale Goods"
        }
    ],
    "sg:phone":"+61 3 9794 5088",
    "sg:postcode":"3175",
    "sg:province":"VIC",
    "sg:tags":[
        "equipment",
        "hydraulic"
    ],
    "wof:name":"Custom Fluidpower Pty Limited",
    "wof:placetype":"venue"
},
  "geometry": {"coordinates":[145.218215942,-37.9853210449],"type":"Point"}
}