{
  "type": "Feature",
  "properties": {
    "iso:country":"AU",
    "sg:address":"PO Box 2408",
    "sg:city":"Brookside Centre",
    "sg:classifiers":[
        {
            "category":"Organizations",
            "subcategory":"Professional Association",
            "type":"Services"
        }
    ],
    "sg:phone":"+61 7 3359 1155",
    "sg:postcode":"4053",
    "sg:province":"QLD",
    "sg:tags":[
        "web",
        "internet"
    ],
    "wof:name":"ITWEBX",
    "wof:placetype":"venue"
},
  "geometry": {"coordinates":[152.97911071799999,-27.4088497162],"type":"Point"}
}