{
  "type": "Feature",
  "properties": {
    "addr:full":"3 Inverness Crt Croydon VIC 3136",
    "addr:housenumber":"3",
    "addr:postcode":"3136",
    "addr:street":"Inverness Crt",
    "iso:country":"AU",
    "sg:address":"3 Inverness Crt",
    "sg:city":"Croydon",
    "sg:classifiers":[
        {
            "category":"Retail",
            "subcategory":"Auto Rental",
            "type":"Services"
        }
    ],
    "sg:phone":"+61 412 017 148",
    "sg:postcode":"3136",
    "sg:province":"VIC",
    "sg:tags":[
        "chauffeur",
        "car",
        "hire",
        "driven",
        "limousine"
    ],
    "wof:name":"King's Limousines",
    "wof:placetype":"venue"
},
  "geometry": {"coordinates":[145.26617431599999,-37.8025550842],"type":"Point"}
}