{
  "type": "Feature",
  "properties": {
    "addr:full":"62 Koonoona Ave Carramar NSW 2163",
    "addr:housenumber":"62",
    "addr:postcode":"2163",
    "addr:street":"Koonoona Ave",
    "iso:country":"AU",
    "sg:address":"62 Koonoona Ave",
    "sg:city":"Carramar",
    "sg:classifiers":[
        {
            "category":"Building & Trades",
            "subcategory":"Landscaping Services",
            "type":"Services"
        }
    ],
    "sg:phone":"+61 2 9754 1134",
    "sg:postcode":"2163",
    "sg:province":"NSW",
    "sg:tags":[
        "gardener"
    ],
    "wof:name":"Earth-Lee Landscaping & Gardening Service",
    "wof:placetype":"venue"
},
  "geometry": {"coordinates":[150.97001648,-33.8841094971],"type":"Point"}
}