{
  "type": "Feature",
  "properties": {
    "addr:full":"5 Elston Ave Denistone NSW 2114",
    "addr:housenumber":"5",
    "addr:postcode":"2114",
    "addr:street":"Elston Ave",
    "iso:country":"AU",
    "sg:address":"5 Elston Ave",
    "sg:city":"Denistone",
    "sg:classifiers":[
        {
            "category":"Professional",
            "subcategory":"Detective & Security Services",
            "type":"Services"
        }
    ],
    "sg:phone":"+61 2 9874 3700",
    "sg:postcode":"2114",
    "sg:province":"NSW",
    "sg:tags":[
        "consultant",
        "system"
    ],
    "wof:name":"Intelligent Electronic Security",
    "wof:placetype":"venue"
},
  "geometry": {"coordinates":[151.08982849099999,-33.7995109558],"type":"Point"}
}