{
  "type": "Feature",
  "properties": {
    "addr:full":"1/ 1 Pirie St Fyshwick ACT 2609",
    "addr:housenumber":"/ 1",
    "addr:postcode":"2609",
    "addr:street":"Pirie St",
    "iso:country":"AU",
    "sg:address":"1/ 1 Pirie St",
    "sg:city":"Fyshwick",
    "sg:classifiers":[
        {
            "category":"Organizations",
            "subcategory":"Professional Association",
            "type":"Services"
        }
    ],
    "sg:phone":"+61 2 6239 3923",
    "sg:postcode":"2609",
    "sg:province":"ACT",
    "sg:tags":[
        "organisation",
        "business"
    ],
    "wof:name":"National Publishers",
    "wof:placetype":"venue"
},
  "geometry": {"coordinates":[149.169189453,-35.3266029358],"type":"Point"}
}