{
  "type": "Feature",
  "properties": {
    "addr:full":"4 Sage Crt Langwarrin VIC 3910",
    "addr:housenumber":"4",
    "addr:postcode":"3910",
    "addr:street":"Sage Crt",
    "iso:country":"AU",
    "sg:address":"4 Sage Crt",
    "sg:city":"Langwarrin",
    "sg:classifiers":[
        {
            "category":"Building & Trades",
            "subcategory":"Construction",
            "type":"Services"
        }
    ],
    "sg:phone":"+61 3 9775 6505",
    "sg:postcode":"3910",
    "sg:province":"VIC",
    "sg:tags":[
        "concrete",
        "contractor"
    ],
    "wof:name":"Discount Concreting",
    "wof:placetype":"venue"
},
  "geometry": {"coordinates":[145.20390319800001,-38.1377220154],"type":"Point"}
}