{
  "type": "Feature",
  "properties": {
    "addr:full":"2 Milburn Gr St Kilda East VIC 3183",
    "addr:housenumber":"2",
    "addr:postcode":"3183",
    "addr:street":"Milburn Gr",
    "iso:country":"AU",
    "sg:address":"2 Milburn Gr",
    "sg:city":"St Kilda East",
    "sg:classifiers":[
        {
            "category":"Building & Trades",
            "subcategory":"Construction",
            "type":"Services"
        }
    ],
    "sg:phone":"+61 418 351 310",
    "sg:postcode":"3183",
    "sg:province":"VIC",
    "sg:tags":[
        "contractor"
    ],
    "wof:name":"MBD Constructions Pty Ltd",
    "wof:placetype":"venue"
},
  "geometry": {"coordinates":[145.00779724099999,-37.873714447],"type":"Point"}
}