{
  "type": "Feature",
  "properties": {
    "addr:full":"Unit 1/ 23 Rowood Rd Prospect NSW 2148",
    "addr:housenumber":"23",
    "addr:postcode":"2148",
    "addr:street":"Rowood Rd",
    "iso:country":"AU",
    "sg:address":"Unit 1/ 23 Rowood Rd",
    "sg:city":"Prospect",
    "sg:classifiers":[
        {
            "category":"Shopping",
            "subcategory":"Bicycles & Sporting Goods",
            "type":"Retail Goods"
        }
    ],
    "sg:phone":"+61 2 9688 0100",
    "sg:postcode":"2148",
    "sg:province":"NSW",
    "sg:tags":[
        "chemical",
        "equipment",
        "pool",
        "swimming"
    ],
    "wof:name":"Clearwater",
    "wof:placetype":"venue"
},
  "geometry": {"coordinates":[150.92219543499999,-33.8022727966],"type":"Point"}
}