{
  "type": "Feature",
  "properties": {
    "addr:full":"32 McCrossin St Uralla NSW 2358",
    "addr:housenumber":"32",
    "addr:postcode":"2358",
    "addr:street":"Mccrossin St",
    "iso:country":"AU",
    "sg:address":"32 McCrossin St",
    "sg:city":"Uralla",
    "sg:classifiers":[
        {
            "category":"Building & Trades",
            "subcategory":"Construction",
            "type":"Services"
        }
    ],
    "sg:phone":"+61 2 6778 4746",
    "sg:postcode":"2358",
    "sg:province":"NSW",
    "sg:tags":[
        "contractor"
    ],
    "wof:name":"McFarlane A C & L M Building Contractors",
    "wof:placetype":"venue"
},
  "geometry": {"coordinates":[151.51448059099999,-30.648317337],"type":"Point"}
}