{
  "type": "Feature",
  "properties": {
    "addr:full":"Cape Paterson Rd Wonthaggi VIC 3995",
    "addr:postcode":"3995",
    "addr:street":"Cape Paterson Rd",
    "iso:country":"AU",
    "sg:address":"Cape Paterson Rd",
    "sg:city":"Wonthaggi",
    "sg:classifiers":[
        {
            "category":"Autos & Motor Vehicles",
            "subcategory":"Auto Supplies",
            "type":"Retail Goods"
        }
    ],
    "sg:phone":"+61 3 5672 1297",
    "sg:postcode":"3995",
    "sg:province":"VIC",
    "sg:tags":[
        "part",
        "cycles",
        "accessory"
    ],
    "wof:name":"Hills Mower & Motorcycles",
    "wof:placetype":"venue"
},
  "geometry": {"coordinates":[145.60458399999999,-38.624264],"type":"Point"}
}