{
  "type": "Feature",
  "properties": {
    "addr:full":"PO Box 572 Spit Junction NSW 2088",
    "addr:postcode":"2088",
    "addr:street":"Spit",
    "iso:country":"AU",
    "sg:address":"PO Box 572",
    "sg:city":"Spit Junction",
    "sg:classifiers":[
        {
            "category":"Banks & Credit Unions",
            "subcategory":"Financial Services",
            "type":"Services"
        }
    ],
    "sg:phone":"+61 2 9968 2328",
    "sg:postcode":"2088",
    "sg:province":"NSW",
    "sg:tags":[
        "finance",
        "factoring"
    ],
    "wof:name":"Working Capital Finance Pty Ltd",
    "wof:placetype":"venue"
},
  "geometry": {"coordinates":[151.24139404300001,-33.8247413635],"type":"Point"}
}