{
  "type": "Feature",
  "properties": {
    "addr:full":"18 Tulloch Ave Melton VIC 3337",
    "addr:housenumber":"18",
    "addr:postcode":"3337",
    "addr:street":"Tulloch Ave",
    "iso:country":"AU",
    "sg:address":"18 Tulloch Ave",
    "sg:city":"Melton",
    "sg:classifiers":[
        {
            "category":"Building & Trades",
            "subcategory":"Construction",
            "type":"Services"
        }
    ],
    "sg:phone":"+61 3 9743 5299",
    "sg:postcode":"3337",
    "sg:province":"VIC",
    "sg:tags":[
        "fencing",
        "contractor"
    ],
    "wof:name":"Doors &#034;R&#034; Us",
    "wof:placetype":"venue"
},
  "geometry": {"coordinates":[144.59599299999999,-37.67522],"type":"Point"}
}