{
  "type": "Feature",
  "properties": {
    "addr:full":"Cnr Canning Hwy & South Tce Como WA 6152",
    "addr:postcode":"6152",
    "addr:street":"Canning Hwy & South Tce",
    "iso:country":"AU",
    "sg:address":"Cnr Canning Hwy & South Tce",
    "sg:city":"Como",
    "sg:classifiers":[
        {
            "category":"Travel",
            "subcategory":"Hotels & Motels",
            "type":"Entertainment"
        }
    ],
    "sg:phone":"+61 8 9367 6666",
    "sg:postcode":"6152",
    "sg:province":"WA",
    "sg:tags":[
        "accommodation"
    ],
    "wof:name":"Como Drive In Cellers",
    "wof:placetype":"venue"
},
  "geometry": {"coordinates":[115.86380800000001,-31.997253],"type":"Point"}
}