{
  "type": "Feature",
  "properties": {
    "addr:full":"8 Dameeli Ave Kirrawee NSW 2232",
    "addr:housenumber":"8",
    "addr:postcode":"2232",
    "addr:street":"Dameeli Ave",
    "iso:country":"AU",
    "sg:address":"8 Dameeli Ave",
    "sg:city":"Kirrawee",
    "sg:classifiers":[
        {
            "category":"Professional",
            "subcategory":"Engineering",
            "type":"Services"
        }
    ],
    "sg:phone":"+61 2 9545 3980",
    "sg:postcode":"2232",
    "sg:province":"NSW",
    "sg:tags":[
        "electrical",
        "engineer"
    ],
    "wof:name":"Ellbrook Engineering Services Pty Ltd",
    "wof:placetype":"venue"
},
  "geometry": {"coordinates":[151.07427978499999,-34.035369873],"type":"Point"}
}