{
  "type": "Feature",
  "properties": {
    "iso:country":"AU",
    "sg:address":"56 Logan Rd",
    "sg:city":"Woolloongabba",
    "sg:classifiers":[
        {
            "category":"Education",
            "subcategory":"Special Training",
            "type":"Public Place"
        }
    ],
    "sg:phone":"+61 7 3249 3370",
    "sg:postcode":"4102",
    "sg:province":"QLD",
    "sg:tags":[
        "development"
    ],
    "wof:name":"Forest Industries Industry Training Advisory Body Inc",
    "wof:placetype":"venue"
},
  "geometry": {"coordinates":[153.03871154800001,-27.4894733429],"type":"Point"}
}