{
  "type": "Feature",
  "properties": {
    "iso:country":"AU",
    "sg:address":"48 Lake Charm East Rd",
    "sg:city":"Lake Charm",
    "sg:classifiers":[
        {
            "category":"Autos & Motor Vehicles",
            "subcategory":"Auto Supplies",
            "type":"Retail Goods"
        }
    ],
    "sg:phone":"+61 3 5457 9408",
    "sg:postcode":"3581",
    "sg:province":"VIC",
    "sg:tags":[
        "part",
        "cycles",
        "accessory"
    ],
    "wof:name":"On Farm Motorcycle Services",
    "wof:placetype":"venue"
},
  "geometry": {"coordinates":[143.80990600600001,-35.6110343933],"type":"Point"}
}