{
  "type": "Feature",
  "properties": {
    "addr:full":"Suite 202, 2nd Floor Spring St Chatswood NSW 2067",
    "addr:postcode":"2067",
    "addr:street":"St",
    "iso:country":"AU",
    "sg:address":"Suite 202, 2nd Floor Spring St",
    "sg:city":"Chatswood",
    "sg:classifiers":[
        {
            "category":"Health Services",
            "subcategory":"Health Practitioner",
            "type":"Services"
        }
    ],
    "sg:phone":"+61 2 9948 7103",
    "sg:postcode":"2067",
    "sg:province":"NSW",
    "sg:tags":[
        "naturopath"
    ],
    "wof:name":"Barta Marianne",
    "wof:placetype":"venue"
},
  "geometry": {"coordinates":[151.18450927699999,-33.7961196899],"type":"Point"}
}