{
  "type": "Feature",
  "properties": {
    "addr:full":"9 Chalder St Marrickville NSW 2204",
    "addr:housenumber":"9",
    "addr:postcode":"2204",
    "addr:street":"Chalder St",
    "iso:country":"AU",
    "sg:address":"9 Chalder St",
    "sg:city":"Marrickville",
    "sg:classifiers":[
        {
            "category":"Manufacturing",
            "subcategory":"Metals",
            "type":"Manufacturing & Wholesale Goods"
        }
    ],
    "sg:phone":"+61 2 9557 1617",
    "sg:postcode":"2204",
    "sg:province":"NSW",
    "sg:tags":[
        "merchant"
    ],
    "wof:name":"Newton Scrap Metal",
    "wof:placetype":"venue"
},
  "geometry": {"coordinates":[151.16450499999999,-33.907509],"type":"Point"}
}