{
  "type": "Feature",
  "properties": {
    "addr:full":"6 Sutherland Rd Chatswood NSW 2067",
    "addr:housenumber":"6",
    "addr:postcode":"2067",
    "addr:street":"Sutherland Rd",
    "iso:country":"AU",
    "sg:address":"6 Sutherland Rd",
    "sg:city":"Chatswood",
    "sg:classifiers":[
        {
            "category":"Shopping",
            "subcategory":"Clothing, Apparel, & Fashions",
            "type":"Retail Goods"
        }
    ],
    "sg:phone":"+61 2 9419 3747",
    "sg:postcode":"2067",
    "sg:province":"NSW",
    "sg:tags":[
        "wholesaler",
        "children's",
        "mfrs",
        "wear"
    ],
    "wof:name":"Anne Von Bulow",
    "wof:placetype":"venue"
},
  "geometry": {"coordinates":[151.17898559599999,-33.8022880554],"type":"Point"}
}