{
  "type": "Feature",
  "properties": {
    "addr:full":"6/ 30 Leighton Pl Hornsby NSW 2077",
    "addr:housenumber":"/ 30",
    "addr:postcode":"2077",
    "addr:street":"Leighton Pl",
    "iso:country":"AU",
    "sg:address":"6/ 30 Leighton Pl",
    "sg:city":"Hornsby",
    "sg:classifiers":[
        {
            "category":"Professional",
            "type":"Services"
        }
    ],
    "sg:phone":"+61 2 9477 3762",
    "sg:postcode":"2077",
    "sg:province":"NSW",
    "sg:tags":[
        "shop",
        "fitting"
    ],
    "wof:name":"Channel Panel",
    "wof:placetype":"venue"
},
  "geometry": {"coordinates":[151.11622619600001,-33.6956710815],"type":"Point"}
}