{
  "type": "Feature",
  "properties": {
    "addr:full":"21 Rowland St Slacks Creek QLD 4127",
    "addr:housenumber":"21",
    "addr:postcode":"4127",
    "addr:street":"Rowland St",
    "iso:country":"AU",
    "sg:address":"21 Rowland St",
    "sg:city":"Slacks Creek",
    "sg:classifiers":[
        {
            "category":"Autos & Motor Vehicles",
            "subcategory":"Boat Sales",
            "type":"Retail Goods"
        }
    ],
    "sg:phone":"+61 7 3808 1988",
    "sg:postcode":"4127",
    "sg:province":"QLD",
    "sg:tags":[
        "equipment",
        "yacht"
    ],
    "wof:name":"Marine Safe Australia Pty Ltd",
    "wof:placetype":"venue"
},
  "geometry": {"coordinates":[153.126495361,-27.6306781769],"type":"Point"}
}