{
  "type": "Feature",
  "properties": {
    "addr:full":"5 Karina St Frankston South VIC 3199",
    "addr:housenumber":"5",
    "addr:postcode":"3199",
    "addr:street":"Karina St",
    "iso:country":"AU",
    "sg:address":"5 Karina St",
    "sg:city":"Frankston South",
    "sg:classifiers":[
        {
            "category":"Building & Trades",
            "subcategory":"Construction",
            "type":"Services"
        }
    ],
    "sg:phone":"+61 417 317 470",
    "sg:postcode":"3199",
    "sg:province":"VIC",
    "sg:tags":[
        "contractor"
    ],
    "wof:name":"G J S Constructions Pty Ltd",
    "wof:placetype":"venue"
},
  "geometry": {"coordinates":[145.11981201200001,-38.1776695251],"type":"Point"}
}