{
  "type": "Feature",
  "properties": {
    "addr:full":"10 Albert St Clarence Gardens SA 5039",
    "addr:housenumber":"10",
    "addr:postcode":"5039",
    "addr:street":"Albert St",
    "iso:country":"AU",
    "sg:address":"10 Albert St",
    "sg:city":"Clarence Gardens",
    "sg:classifiers":[
        {
            "category":"Wholesale",
            "subcategory":"Construction Materials",
            "type":"Manufacturing & Wholesale Goods"
        }
    ],
    "sg:phone":"+61 8 8351 4600",
    "sg:postcode":"5039",
    "sg:province":"SA",
    "sg:tags":[
        "lift"
    ],
    "wof:name":"Adelaide Lift Interiors",
    "wof:placetype":"venue"
},
  "geometry": {"coordinates":[138.57536315900001,-34.9750938416],"type":"Point"}
}