{
  "type": "Feature",
  "properties": {
    "addr:full":"57 Finucane Rd Capalaba QLD 4157",
    "addr:housenumber":"57",
    "addr:postcode":"4157",
    "addr:street":"Finucane Rd",
    "iso:country":"AU",
    "sg:address":"57 Finucane Rd",
    "sg:city":"Capalaba",
    "sg:classifiers":[
        {
            "category":"Government",
            "subcategory":"Court House",
            "type":"Public Place"
        }
    ],
    "sg:phone":"+61 7 3245 2500",
    "sg:postcode":"4157",
    "sg:province":"QLD",
    "sg:tags":[
        "personal",
        "marriage",
        "family",
        "counselling"
    ],
    "wof:name":"Care Point Counselling & Psychotherapy Services",
    "wof:placetype":"venue"
},
  "geometry": {"coordinates":[153.208084106,-27.5221252441],"type":"Point"}
}