{
  "type": "Feature",
  "properties": {
    "iso:country":"AU",
    "sg:address":"39a Gregory St",
    "sg:city":"North Ward",
    "sg:classifiers":[
        {
            "category":"Shopping",
            "subcategory":"Department Store",
            "type":"Retail Goods"
        }
    ],
    "sg:phone":"+61 7 4771 3236",
    "sg:postcode":"4810",
    "sg:province":"QLD",
    "wof:name":"Stan Short Clothing",
    "wof:placetype":"venue"
},
  "geometry": {"coordinates":[146.81358299999999,-19.251249],"type":"Point"}
}