{
  "type": "Feature",
  "properties": {
    "addr:full":"Lot 88 Benowa Drv Glen Forrest WA 6071",
    "addr:postcode":"6071",
    "addr:street":"Benowa Drv Glen",
    "iso:country":"AU",
    "sg:address":"Lot 88 Benowa Drv",
    "sg:city":"Glen Forrest",
    "sg:classifiers":[
        {
            "category":"Health Services",
            "subcategory":"Health Practitioner",
            "type":"Services"
        }
    ],
    "sg:phone":"+61 8 9298 9027",
    "sg:postcode":"6071",
    "sg:province":"WA",
    "sg:tags":[
        "technique",
        "alexander"
    ],
    "wof:name":"Paul Lawrence",
    "wof:placetype":"venue"
},
  "geometry": {"coordinates":[116.108413696,-31.9113731384],"type":"Point"}
}