{
  "type": "Feature",
  "properties": {
    "iso:country":"AU",
    "sg:address":"Milton Rd",
    "sg:city":"Milton",
    "sg:classifiers":[
        {
            "category":"Home & Garden",
            "subcategory":"Home Furnishings",
            "type":"Retail Goods"
        }
    ],
    "sg:phone":"+61 7 3367 2822",
    "sg:postcode":"4064",
    "sg:province":"QLD",
    "sg:tags":[
        "storage",
        "rack",
        "wine"
    ],
    "wof:name":"Milton Cellars",
    "wof:placetype":"venue"
},
  "geometry": {"coordinates":[153.0052948,-27.4686031342],"type":"Point"}
}