{
  "type": "Feature",
  "properties": {
    "iso:country":"AU",
    "sg:address":"Camp St",
    "sg:city":"Heathcote",
    "sg:classifiers":[
        {
            "category":"Education",
            "subcategory":"Kindergarten",
            "type":"Public Place"
        }
    ],
    "sg:phone":"+61 3 5433 2068",
    "sg:postcode":"3523",
    "sg:province":"VIC",
    "sg:tags":[
        "pre-schools"
    ],
    "wof:name":"Heathcote Pre-School",
    "wof:placetype":"venue"
},
  "geometry": {"coordinates":[144.70881700000001,-36.923504],"type":"Point"}
}