{
  "type": "Feature",
  "properties": {
    "addr:full":"Nash Rd Onkaparinga Hills SA 5163",
    "addr:postcode":"5163",
    "addr:street":"Nash Rd",
    "iso:country":"AU",
    "sg:address":"Nash Rd",
    "sg:city":"Onkaparinga Hills",
    "sg:classifiers":[
        {
            "category":"Social Services",
            "type":"Services"
        }
    ],
    "sg:phone":"+61 8 8383 6909",
    "sg:postcode":"5163",
    "sg:province":"SA",
    "sg:tags":[
        "disabled",
        "person",
        "equipment"
    ],
    "wof:name":"Modified Driving Solutions",
    "wof:placetype":"venue"
},
  "geometry": {"coordinates":[138.584075928,-35.1231994629],"type":"Point"}
}