{
  "type": "Feature",
  "properties": {
    "addr:full":"Suite 2/ 592 Dean St Albury NSW 2640",
    "addr:housenumber":"/ 592",
    "addr:postcode":"2640",
    "addr:street":"Dean St",
    "iso:country":"AU",
    "sg:address":"Suite 2/ 592 Dean St",
    "sg:city":"Albury",
    "sg:classifiers":[
        {
            "category":"Shopping",
            "subcategory":"Bridal",
            "type":"Retail Goods"
        }
    ],
    "sg:phone":"+61 2 6021 0777",
    "sg:postcode":"2640",
    "sg:province":"NSW",
    "sg:tags":[
        "hire",
        "wear"
    ],
    "wof:name":"To The Bride & Groom",
    "wof:placetype":"venue"
},
  "geometry": {"coordinates":[146.91526794399999,-36.0804824829],"type":"Point"}
}