{
  "type": "Feature",
  "properties": {
    "addr:full":"50 Marjorie St Pinelands NT 0829",
    "addr:housenumber":"50",
    "addr:postcode":"nt 0829",
    "addr:street":"Marjorie St",
    "iso:country":"AU",
    "sg:address":"50 Marjorie St",
    "sg:city":"Pinelands",
    "sg:classifiers":[
        {
            "category":"Professional",
            "type":"Services"
        }
    ],
    "sg:phone":"+61 8 8932 2994",
    "sg:postcode":"0829",
    "sg:province":"NT",
    "sg:tags":[
        "transport"
    ],
    "wof:name":"P & F Haulage Pty Ltd",
    "wof:placetype":"venue"
},
  "geometry": {"coordinates":[130.96832275400001,-12.4617395401],"type":"Point"}
}