{
  "type": "Feature",
  "properties": {
    "iso:country":"AU",
    "sg:address":"3 Paul St",
    "sg:city":"St Marys",
    "sg:classifiers":[
        {
            "category":"Transit Center",
            "subcategory":"Passenger",
            "type":"Transportation"
        }
    ],
    "sg:phone":"+61 8 8277 1044",
    "sg:postcode":"5042",
    "sg:province":"SA",
    "sg:tags":[
        "wood",
        "moulding",
        "plastic"
    ],
    "wof:name":"Plastic Products (Sth Aust)",
    "wof:placetype":"venue"
},
  "geometry": {"coordinates":[138.577347,-35.007504],"type":"Point"}
}