{
  "type": "Feature",
  "properties": {
    "addr:full":"18 Endurance Ave Queanbeyan ACT 2620",
    "addr:housenumber":"18",
    "addr:postcode":"2620",
    "addr:street":"Endurance Ave",
    "iso:country":"AU",
    "sg:address":"18 Endurance Ave",
    "sg:city":"Queanbeyan",
    "sg:classifiers":[
        {
            "category":"Retail",
            "subcategory":"Auto Repair",
            "type":"Services"
        }
    ],
    "sg:phone":"+61 2 6297 2137",
    "sg:postcode":"2620",
    "sg:province":"ACT",
    "sg:tags":[
        "testing",
        "inspection",
        "motor",
        "vehicle"
    ],
    "wof:name":"Ron Shepherd Mechanical Repairs",
    "wof:placetype":"venue"
},
  "geometry": {"coordinates":[149.246292114,-35.3407325745],"type":"Point"}
}