{
  "type": "Feature",
  "properties": {
    "iso:country":"AU",
    "sg:address":"11 1353 The Horsley Drv",
    "sg:city":"Wetherill Park",
    "sg:classifiers":[
        {
            "category":"Professional",
            "subcategory":"Engineering",
            "type":"Services"
        }
    ],
    "sg:phone":"+61 2 9756 6556",
    "sg:postcode":"2164",
    "sg:province":"NSW",
    "sg:tags":[
        "engineer"
    ],
    "wof:name":"Elite Engineering",
    "wof:placetype":"venue"
},
  "geometry": {"coordinates":[150.882125855,-33.8522949219],"type":"Point"}
}