{
  "type": "Feature",
  "properties": {
    "addr:full":"4/ 55 Orchard Rd Brookvale NSW 2100",
    "addr:housenumber":"/ 55",
    "addr:postcode":"2100",
    "addr:street":"Orchard Rd",
    "iso:country":"AU",
    "sg:address":"4/ 55 Orchard Rd",
    "sg:city":"Brookvale",
    "sg:classifiers":[
        {
            "category":"Home & Garden",
            "subcategory":"Furniture",
            "type":"Retail Goods"
        }
    ],
    "sg:phone":"+61 2 9971 9969",
    "sg:postcode":"2100",
    "sg:province":"NSW",
    "sg:tags":[
        "repair",
        "restoration"
    ],
    "wof:name":"RJ Scali Cabinet Maker",
    "wof:placetype":"venue"
},
  "geometry": {"coordinates":[151.27395629899999,-33.7653465271],"type":"Point"}
}