{
  "type": "Feature",
  "properties": {
    "addr:full":"67- 81 Maroondah Hwy Croydon VIC 3136",
    "addr:housenumber":"81",
    "addr:postcode":"3136",
    "addr:street":"Maroondah Hwy",
    "iso:country":"AU",
    "sg:address":"67- 81 Maroondah Hwy",
    "sg:city":"Croydon",
    "sg:classifiers":[
        {
            "category":"Social Services",
            "subcategory":"Retirement Home",
            "type":"Services"
        }
    ],
    "sg:phone":"+61 3 9723 2260",
    "sg:postcode":"3136",
    "sg:province":"VIC",
    "sg:tags":[
        "accommodation",
        "special"
    ],
    "wof:name":"Cherry Tree Lifestyle Serviced Apartments",
    "wof:placetype":"venue"
},
  "geometry": {"coordinates":[145.26654052699999,-37.7894515991],"type":"Point"}
}