{
  "type": "Feature",
  "properties": {
    "addr:full":"107 Eumundi-Noosa Rd Noosaville QLD 4566",
    "addr:housenumber":"107",
    "addr:postcode":"4566",
    "addr:street":"Eumundi-Noosa Rd",
    "iso:country":"AU",
    "sg:address":"107 Eumundi-Noosa Rd",
    "sg:city":"Noosaville",
    "sg:classifiers":[
        {
            "category":"Communications",
            "subcategory":"Film & Video Production",
            "type":"Services"
        }
    ],
    "sg:phone":"+61 7 5474 3117",
    "sg:postcode":"4566",
    "sg:province":"QLD",
    "sg:tags":[
        "made",
        "clothing",
        "custom"
    ],
    "wof:name":"Sarona",
    "wof:placetype":"venue"
},
  "geometry": {"coordinates":[153.04818725600001,-26.4085731506],"type":"Point"}
}