{
  "type": "Feature",
  "properties": {
    "iso:country":"AU",
    "sg:address":"31 Caloundra Rd",
    "sg:city":"Caloundra",
    "sg:classifiers":[
        {
            "category":"Real Estate",
            "subcategory":"Real Estate Agent",
            "type":"Services"
        }
    ],
    "sg:phone":"+61 7 5491 9566",
    "sg:postcode":"4551",
    "sg:province":"QLD",
    "sg:tags":[
        "handyman's",
        "equipment",
        "hire",
        "builders",
        "contractor"
    ],
    "wof:name":"CSP Hire Pty Ltd",
    "wof:placetype":"venue"
},
  "geometry": {"coordinates":[153.11184692399999,-26.7967090607],"type":"Point"}
}