{
  "type": "Feature",
  "properties": {
    "addr:full":"3 A Lucy St Elsternwick VIC 3185",
    "addr:housenumber":"3 a",
    "addr:postcode":"3185",
    "addr:street":"Lucy St",
    "iso:country":"AU",
    "sg:address":"3 A Lucy St",
    "sg:city":"Elsternwick",
    "sg:classifiers":[
        {
            "category":"Government",
            "subcategory":"Court House",
            "type":"Public Place"
        }
    ],
    "sg:phone":"+61 3 9505 0393",
    "sg:postcode":"3185",
    "sg:province":"VIC",
    "sg:tags":[
        "personal",
        "marriage",
        "family",
        "counselling"
    ],
    "wof:name":"Reddy Belinda",
    "wof:placetype":"venue"
},
  "geometry": {"coordinates":[145.00654602,-37.8968544006],"type":"Point"}
}