{
  "type": "Feature",
  "properties": {
    "addr:full":"PO Box 3102 Rhodes NSW 2138",
    "addr:postcode":"2138",
    "iso:country":"AU",
    "sg:address":"PO Box 3102",
    "sg:city":"Rhodes",
    "sg:classifiers":[
        {
            "category":"Health Services",
            "subcategory":"Doctor",
            "type":"Services"
        }
    ],
    "sg:phone":"+61 1800 789 098",
    "sg:postcode":"2138",
    "sg:province":"NSW",
    "sg:tags":[
        "occupational",
        "safety"
    ],
    "wof:name":"Solid Dynamics",
    "wof:placetype":"venue"
},
  "geometry": {"coordinates":[151.08953857399999,-33.8270492554],"type":"Point"}
}