{
  "type": "Feature",
  "properties": {
    "addr:full":"Shp19/ 508 Old Northern Rd Dural NSW 2158",
    "addr:housenumber":"508",
    "addr:postcode":"2158",
    "addr:street":"Old Northern Rd",
    "iso:country":"AU",
    "sg:address":"Shp19/ 508 Old Northern Rd",
    "sg:city":"Dural",
    "sg:classifiers":[
        {
            "category":"Building & Trades",
            "subcategory":"Locksmith",
            "type":"Services"
        }
    ],
    "sg:phone":"+61 2 9651 5600",
    "sg:postcode":"2158",
    "sg:province":"NSW",
    "sg:tags":[
        "lock"
    ],
    "wof:name":"Lockworx Pty Ltd",
    "wof:placetype":"venue"
},
  "geometry": {"coordinates":[151.02011108400001,-33.6936302185],"type":"Point"}
}