{
  "type": "Feature",
  "properties": {
    "addr:full":"Lot 656 Wetherall St Manjimup WA 6258",
    "addr:postcode":"6258",
    "addr:street":"Wetherall St",
    "iso:country":"AU",
    "sg:address":"Lot 656 Wetherall St",
    "sg:city":"Manjimup",
    "sg:classifiers":[
        {
            "category":"Home & Garden",
            "subcategory":"Building Materials",
            "type":"Retail Goods"
        }
    ],
    "sg:phone":"+61 8 9772 4888",
    "sg:postcode":"6258",
    "sg:province":"WA",
    "sg:tags":[
        "pre-mixed",
        "concrete"
    ],
    "wof:name":"Readymix",
    "wof:placetype":"venue"
},
  "geometry": {"coordinates":[116.14251709,-34.2514266968],"type":"Point"}
}