{
  "type": "Feature",
  "properties": {
    "iso:country":"AU",
    "sg:address":"Level 11, 180 Russell St",
    "sg:city":"Melbourne",
    "sg:classifiers":[
        {
            "category":"Real Estate",
            "subcategory":"Architect",
            "type":"Services"
        }
    ],
    "sg:phone":"+61 3 9654 0015",
    "sg:postcode":"3000",
    "sg:province":"VIC",
    "wof:name":"Elliott Peter Pty Ltd",
    "wof:placetype":"venue"
},
  "geometry": {"coordinates":[144.96794128400001,-37.8120498657],"type":"Point"}
}