{
  "type": "Feature",
  "properties": {
    "iso:country":"AU",
    "sg:address":"13 Martine Ave",
    "sg:city":"Camden",
    "sg:classifiers":[
        {
            "category":"Professional",
            "subcategory":"Computer Services",
            "type":"Services"
        }
    ],
    "sg:phone":"+61 2 4655 6792",
    "sg:postcode":"2570",
    "sg:province":"NSW",
    "sg:tags":[
        "consultant",
        "system"
    ],
    "wof:name":"Data Source Pty Ltd",
    "wof:placetype":"venue"
},
  "geometry": {"coordinates":[150.697998047,-34.0814933777],"type":"Point"}
}