{
  "type": "Feature",
  "properties": {
    "iso:country":"AU",
    "sg:address":"Ceramic Ave",
    "sg:city":"Raglan",
    "sg:classifiers":[
        {
            "category":"School Buses",
            "type":"Transportation"
        }
    ],
    "sg:phone":"+61 13 15 79",
    "sg:postcode":"2795",
    "sg:province":"NSW",
    "sg:tags":[
        "brick"
    ],
    "wof:name":"CSR PGH (Bricks & Pavers)",
    "wof:placetype":"venue"
},
  "geometry": {"coordinates":[149.66212463400001,-33.4193840027],"type":"Point"}
}