{
  "type": "Feature",
  "properties": {
    "addr:full":"69 Maroubra Rd Maroubra NSW 2035",
    "addr:housenumber":"69",
    "addr:postcode":"2035",
    "addr:street":"Maroubra Rd",
    "iso:country":"AU",
    "sg:address":"69 Maroubra Rd",
    "sg:city":"Maroubra",
    "sg:classifiers":[
        {
            "category":"Retail",
            "subcategory":"Repair Shop",
            "type":"Services"
        }
    ],
    "sg:phone":"+61 2 9349 1400",
    "sg:postcode":"2035",
    "sg:province":"NSW",
    "sg:tags":[
        "repairing",
        "piano",
        "tuning"
    ],
    "wof:name":"Davies Peter J Pty Ltd",
    "wof:placetype":"venue"
},
  "geometry": {"coordinates":[151.23204040499999,-33.9406776428],"type":"Point"}
}