{
  "type": "Feature",
  "properties": {
    "iso:country":"AU",
    "sg:address":"71 Mary St",
    "sg:city":"St Peters",
    "sg:classifiers":[
        {
            "category":"Professional",
            "subcategory":"Printing & Photocopies",
            "type":"Services"
        }
    ],
    "sg:phone":"+61 2 9550 1343",
    "sg:postcode":"2044",
    "sg:province":"NSW",
    "sg:tags":[
        "embroidery"
    ],
    "wof:name":"Karen Torrisi Beading Services",
    "wof:placetype":"venue"
},
  "geometry": {"coordinates":[151.17309599999999,-33.913795],"type":"Point"}
}