{
  "type": "Feature",
  "properties": {
    "iso:country":"AU",
    "sg:address":"13 Forest Ave",
    "sg:city":"Plainland",
    "sg:classifiers":[
        {
            "category":"Professional",
            "subcategory":"Computer Services",
            "type":"Services"
        }
    ],
    "sg:phone":"+61 7 5465 6752",
    "sg:postcode":"4341",
    "sg:province":"QLD",
    "sg:tags":[
        "consultant",
        "system"
    ],
    "wof:name":"TAJ Computer Support Pty Ltd",
    "wof:placetype":"venue"
},
  "geometry": {"coordinates":[152.41867065400001,-27.5541553497],"type":"Point"}
}