{
  "type": "Feature",
  "properties": {
    "addr:full":"Cnr Power Rd & Princes Hwy Doveton VIC 3177",
    "addr:postcode":"3177",
    "addr:street":"Power Rd & Princes Hwy",
    "iso:country":"AU",
    "sg:address":"Cnr Power Rd & Princes Hwy",
    "sg:city":"Doveton",
    "sg:classifiers":[
        {
            "category":"Autos & Motor Vehicles",
            "subcategory":"Fuel & Gas Station",
            "type":"Retail Goods"
        }
    ],
    "sg:phone":"+61 3 9792 5320",
    "sg:postcode":"3177",
    "sg:province":"VIC",
    "wof:name":"Ampol Doveton",
    "wof:placetype":"venue"
},
  "geometry": {"coordinates":[145.23960876500001,-37.9866104126],"type":"Point"}
}