{
  "type": "Feature",
  "properties": {
    "addr:full":"Cnr Howard and Ann Streets Nambour QLD 4560",
    "addr:postcode":"4560",
    "addr:street":"Cnr Howard",
    "iso:country":"AU",
    "sg:address":"Cnr Howard and Ann Streets",
    "sg:city":"Nambour",
    "sg:classifiers":[
        {
            "category":"Health Services",
            "subcategory":"Optometrist",
            "type":"Services"
        }
    ],
    "sg:phone":"+61 7 5444 1411",
    "sg:postcode":"4560",
    "sg:province":"QLD",
    "wof:name":"Absolute Vision",
    "wof:placetype":"venue"
},
  "geometry": {"coordinates":[152.972167969,-26.609369278],"type":"Point"}
}