{
  "type": "Feature",
  "properties": {
    "addr:full":"63 Darley St Newtown NSW 2042",
    "addr:housenumber":"63",
    "addr:postcode":"2042",
    "addr:street":"Darley St",
    "iso:country":"AU",
    "sg:address":"63 Darley St",
    "sg:city":"Newtown",
    "sg:classifiers":[
        {
            "category":"Home & Garden",
            "subcategory":"Garden Supply",
            "type":"Retail Goods"
        }
    ],
    "sg:phone":"+61 2 9519 9273",
    "sg:postcode":"2042",
    "sg:province":"NSW",
    "sg:tags":[
        "statuary",
        "fountains",
        "sundial"
    ],
    "wof:name":"Sundial Designs",
    "wof:placetype":"venue"
},
  "geometry": {"coordinates":[151.17842099999999,-33.906498],"type":"Point"}
}