{
  "type": "Feature",
  "properties": {
    "addr:full":"21 Gabagong Rd Horsfield Bay NSW 2256",
    "addr:housenumber":"21",
    "addr:postcode":"2256",
    "addr:street":"Gabagong Rd",
    "iso:country":"AU",
    "sg:address":"21 Gabagong Rd",
    "sg:city":"Horsfield Bay",
    "sg:classifiers":[
        {
            "category":"Health Services",
            "subcategory":"Health Practitioner",
            "type":"Services"
        }
    ],
    "sg:phone":"+61 414 868 185",
    "sg:postcode":"2256",
    "sg:province":"NSW",
    "sg:tags":[
        "naturopath"
    ],
    "wof:name":"Pirie Christina",
    "wof:placetype":"venue"
},
  "geometry": {"coordinates":[151.30390930199999,-33.4906082153],"type":"Point"}
}