{
  "type": "Feature",
  "properties": {
    "addr:full":"Unit 4-21 Lyell St Mittagong NSW 2575",
    "addr:postcode":"2575",
    "addr:street":"Lyell St",
    "iso:country":"AU",
    "sg:address":"Unit 4-21 Lyell St",
    "sg:city":"Mittagong",
    "sg:classifiers":[
        {
            "category":"Professional",
            "type":"Services"
        }
    ],
    "sg:phone":"+61 429 620 022",
    "sg:postcode":"2575",
    "sg:province":"NSW",
    "sg:tags":[
        "transport"
    ],
    "wof:name":"Highlander Transport Services",
    "wof:placetype":"venue"
},
  "geometry": {"coordinates":[150.42573547399999,-34.4485397339],"type":"Point"}
}