{
  "type": "Feature",
  "properties": {
    "iso:country":"AU",
    "sg:address":"PO Box 4044",
    "sg:city":"Mackay",
    "sg:classifiers":[
        {
            "category":"Professional",
            "subcategory":"Detective & Security Services",
            "type":"Services"
        }
    ],
    "sg:phone":"+61 413 776 180",
    "sg:postcode":"4740",
    "sg:province":"QLD",
    "sg:tags":[
        "investigator"
    ],
    "wof:name":"Precision Investigations",
    "wof:placetype":"venue"
},
  "geometry": {"coordinates":[149.111847,-21.15519],"type":"Point"}
}