{
  "type": "Feature",
  "properties": {
    "iso:country":"AU",
    "sg:address":"63 Melbourne Rd",
    "sg:city":"Mulwala",
    "sg:classifiers":[
        {
            "category":"Government",
            "subcategory":"Post Office",
            "type":"Public Place"
        }
    ],
    "sg:phone":"+61 3 5744 3118",
    "sg:postcode":"2647",
    "sg:province":"NSW",
    "sg:tags":[
        "postal"
    ],
    "wof:name":"Australia Post",
    "wof:placetype":"venue"
},
  "geometry": {"coordinates":[146.00701904300001,-35.9874687195],"type":"Point"}
}