{
  "type": "Feature",
  "properties": {
    "addr:full":"6 Whitney Crt Alexandra Hills QLD 4161",
    "addr:housenumber":"6",
    "addr:postcode":"4161",
    "addr:street":"Whitney Crt",
    "iso:country":"AU",
    "sg:address":"6 Whitney Crt",
    "sg:city":"Alexandra Hills",
    "sg:classifiers":[
        {
            "category":"Communications",
            "subcategory":"Film & Video Production",
            "type":"Services"
        }
    ],
    "sg:phone":"+61 7 3820 2570",
    "sg:postcode":"4161",
    "sg:province":"QLD",
    "sg:tags":[
        "equipment",
        "amplification",
        "music"
    ],
    "wof:name":"Steve's Pro Audio Hire",
    "wof:placetype":"venue"
},
  "geometry": {"coordinates":[153.22265625,-27.5423812866],"type":"Point"}
}