{
  "type": "Feature",
  "properties": {
    "iso:country":"AU",
    "sg:address":"GPO Box 2769",
    "sg:city":"Canberra",
    "sg:classifiers":[
        {
            "category":"Professional",
            "subcategory":"Detective & Security Services",
            "type":"Services"
        }
    ],
    "sg:phone":"+61 1300 138 769",
    "sg:postcode":"2601",
    "sg:province":"ACT",
    "sg:tags":[
        "consultant",
        "system"
    ],
    "wof:name":"Centurion Corporate Protection",
    "wof:placetype":"venue"
},
  "geometry": {"coordinates":[149.111816406,-35.2768592834],"type":"Point"}
}