{
  "type": "Feature",
  "properties": {
    "addr:full":"Copine Rd Mareeba QLD 4880",
    "addr:postcode":"4880",
    "addr:street":"Copine Rd",
    "iso:country":"AU",
    "sg:address":"Copine Rd",
    "sg:city":"Mareeba",
    "sg:classifiers":[
        {
            "category":"Home & Garden",
            "subcategory":"Household Appliances",
            "type":"Retail Goods"
        }
    ],
    "sg:phone":"+61 7 4092 3402",
    "sg:postcode":"4880",
    "sg:province":"QLD",
    "sg:tags":[
        "equipment",
        "gas"
    ],
    "wof:name":"Plumbgas",
    "wof:placetype":"venue"
},
  "geometry": {"coordinates":[145.42817688,-16.9616394043],"type":"Point"}
}