{
  "type": "Feature",
  "properties": {
    "iso:country":"AU",
    "sg:address":"26 Constitution Rd",
    "sg:city":"Ryde",
    "sg:classifiers":[
        {
            "category":"Home & Garden",
            "subcategory":"Building Materials",
            "type":"Retail Goods"
        }
    ],
    "sg:phone":"+61 2 9807 9188",
    "sg:postcode":"2112",
    "sg:province":"NSW",
    "sg:tags":[
        "merchant",
        "glass",
        "glazier"
    ],
    "wof:name":"Mercupond Australia",
    "wof:placetype":"venue"
},
  "geometry": {"coordinates":[151.093215942,-33.8168106079],"type":"Point"}
}