{
  "type": "Feature",
  "properties": {
    "iso:country":"AU",
    "sg:address":"11 Beek St",
    "sg:city":"Katamatite",
    "sg:classifiers":[
        {
            "category":"Food & Beverages",
            "subcategory":"Supermarket",
            "type":"Retail Goods"
        }
    ],
    "sg:phone":"+61 3 5865 1322",
    "sg:postcode":"3649",
    "sg:province":"VIC",
    "sg:tags":[
        "grocery",
        "store"
    ],
    "wof:name":"The Shop",
    "wof:placetype":"venue"
},
  "geometry": {"coordinates":[145.68736267099999,-36.0761184692],"type":"Point"}
}