{
  "type": "Feature",
  "properties": {
    "addr:full":"52 Victoria St Forest Hill QLD 4342",
    "addr:housenumber":"52",
    "addr:postcode":"4342",
    "addr:street":"Victoria St",
    "iso:country":"AU",
    "sg:address":"52 Victoria St",
    "sg:city":"Forest Hill",
    "sg:classifiers":[
        {
            "category":"Travel",
            "subcategory":"Hotels & Motels",
            "type":"Entertainment"
        }
    ],
    "sg:phone":"+61 7 5465 4201",
    "sg:postcode":"4342",
    "sg:province":"QLD",
    "sg:tags":[
        "accommodation"
    ],
    "wof:name":"Lockyer Hotel",
    "wof:placetype":"venue"
},
  "geometry": {"coordinates":[152.35699462900001,-27.5891609192],"type":"Point"}
}