{
  "type": "Feature",
  "properties": {
    "addr:full":"147 Bentinck St Bathurst NSW 2795",
    "addr:housenumber":"147",
    "addr:postcode":"2795",
    "addr:street":"Bentinck St",
    "iso:country":"AU",
    "sg:address":"147 Bentinck St",
    "sg:city":"Bathurst",
    "sg:classifiers":[
        {
            "category":"Health Services",
            "subcategory":"Doctor",
            "type":"Services"
        }
    ],
    "sg:phone":"+61 2 6331 9098",
    "sg:postcode":"2795",
    "sg:province":"NSW",
    "sg:tags":[
        "medical",
        "practitioner"
    ],
    "wof:name":"Parkin, Ray",
    "wof:placetype":"venue"
},
  "geometry": {"coordinates":[149.57835388199999,-33.4222373962],"type":"Point"}
}