{
  "type": "Feature",
  "properties": {
    "iso:country":"AU",
    "sg:address":"4 Woolpack St",
    "sg:city":"Camden",
    "sg:classifiers":[
        {
            "category":"Building & Trades",
            "subcategory":"Cleaning & Sanitation",
            "type":"Services"
        }
    ],
    "sg:phone":"+61 2 4658 1077",
    "sg:postcode":"2570",
    "sg:province":"NSW",
    "sg:tags":[
        "window"
    ],
    "wof:name":"Elderslie Cleaning Service",
    "wof:placetype":"venue"
},
  "geometry": {"coordinates":[150.71163940400001,-34.0556526184],"type":"Point"}
}