{
  "type": "Feature",
  "properties": {
    "addr:full":"3391 San Mateo Ave Koorlong VIC 3501",
    "addr:housenumber":"3391",
    "addr:postcode":"3501",
    "addr:street":"San Mateo Ave",
    "iso:country":"AU",
    "sg:address":"3391 San Mateo Ave",
    "sg:city":"Koorlong",
    "sg:classifiers":[
        {
            "category":"Farming",
            "subcategory":"Vineyard",
            "type":"Manufacturing & Wholesale Goods"
        }
    ],
    "sg:phone":"+61 3 5025 7154",
    "sg:postcode":"3501",
    "sg:province":"VIC",
    "sg:tags":[
        "winery"
    ],
    "wof:name":"Currans Family Wines",
    "wof:placetype":"venue"
},
  "geometry": {"coordinates":[142.09202575699999,-34.2516822815],"type":"Point"}
}