{
  "type": "Feature",
  "properties": {
    "iso:country":"AU",
    "sg:address":"7/ 25 Bailey Crs",
    "sg:city":"Southport",
    "sg:classifiers":[
        {
            "category":"Home & Garden",
            "subcategory":"Furniture",
            "type":"Retail Goods"
        }
    ],
    "sg:phone":"+61 7 5531 1949",
    "sg:postcode":"4215",
    "sg:province":"QLD",
    "sg:tags":[
        "repair",
        "restoration"
    ],
    "wof:name":"Schubert Restorations",
    "wof:placetype":"venue"
},
  "geometry": {"coordinates":[153.415557861,-27.9655303955],"type":"Point"}
}