{
  "type": "Feature",
  "properties": {
    "addr:full":"310 Timor St Warrnambool VIC 3280",
    "addr:housenumber":"310",
    "addr:postcode":"3280",
    "addr:street":"Timor St",
    "iso:country":"AU",
    "sg:address":"310 Timor St",
    "sg:city":"Warrnambool",
    "sg:classifiers":[
        {
            "category":"Health Services",
            "subcategory":"Health Practitioner",
            "type":"Services"
        }
    ],
    "sg:phone":"+61 3 5561 1601",
    "sg:postcode":"3280",
    "sg:province":"VIC",
    "sg:tags":[
        "psychologist"
    ],
    "wof:name":"Andrew Gray",
    "wof:placetype":"venue"
},
  "geometry": {"coordinates":[142.47364807100001,-38.3813591003],"type":"Point"}
}