{
  "type": "Feature",
  "properties": {
    "addr:full":"16 Glenburnie St Happy Valley SA 5159",
    "addr:housenumber":"16",
    "addr:postcode":"5159",
    "addr:street":"Glenburnie St",
    "iso:country":"AU",
    "sg:address":"16 Glenburnie St",
    "sg:city":"Happy Valley",
    "sg:classifiers":[
        {
            "category":"Building & Trades",
            "subcategory":"Cleaning & Sanitation",
            "type":"Services"
        }
    ],
    "sg:phone":"+61 8 8322 2339",
    "sg:postcode":"5159",
    "sg:province":"SA",
    "sg:tags":[
        "cleaner",
        "repairer",
        "roof"
    ],
    "wof:name":"D & S Roof Restoration",
    "wof:placetype":"venue"
},
  "geometry": {"coordinates":[138.554031372,-35.0785369873],"type":"Point"}
}