{
  "type": "Feature",
  "properties": {
    "iso:country":"AU",
    "sg:address":"7 St",
    "sg:city":"Peter&#039;s Cl Glengowrie",
    "sg:classifiers":[
        {
            "category":"Autos & Motor Vehicles",
            "subcategory":"Auto Supplies",
            "type":"Retail Goods"
        }
    ],
    "sg:phone":"+61 417 890 981",
    "sg:postcode":"5044",
    "sg:province":"SA",
    "sg:tags":[
        "part",
        "cycles",
        "accessory"
    ],
    "wof:name":"Steves Cycle Fabrications",
    "wof:placetype":"venue"
},
  "geometry": {"coordinates":[138.517715,-34.991901],"type":"Point"}
}