{
  "type": "Feature",
  "properties": {
    "addr:full":"Roberts St South Hedland WA 6722",
    "addr:postcode":"6722",
    "addr:street":"Roberts St South",
    "iso:country":"AU",
    "sg:address":"Roberts St",
    "sg:city":"South Hedland",
    "sg:classifiers":[
        {
            "category":"Education",
            "subcategory":"School",
            "type":"Public Place"
        }
    ],
    "sg:phone":"+61 8 9172 1244",
    "sg:postcode":"6722",
    "sg:province":"WA",
    "sg:tags":[
        "state",
        "except",
        "nsw"
    ],
    "wof:name":"Hedland Senior High School",
    "wof:placetype":"venue"
},
  "geometry": {"coordinates":[118.59754180900001,-20.4036159515],"type":"Point"}
}