{
  "type": "Feature",
  "properties": {
    "addr:full":"53-61 Chanter St Berrigan NSW 2712",
    "addr:housenumber":"53-61",
    "addr:postcode":"2712",
    "addr:street":"Chanter St",
    "iso:country":"AU",
    "sg:address":"53-61 Chanter St",
    "sg:city":"Berrigan",
    "sg:classifiers":[
        {
            "category":"Home & Garden",
            "subcategory":"Building Materials",
            "type":"Retail Goods"
        }
    ],
    "sg:phone":"+61 3 5885 2371",
    "sg:postcode":"2712",
    "sg:province":"NSW",
    "sg:tags":[
        "secondhand"
    ],
    "wof:name":"Paul's Demolition",
    "wof:placetype":"venue"
},
  "geometry": {"coordinates":[145.809204102,-35.6570281982],"type":"Point"}
}