{
  "type": "Feature",
  "properties": {
    "addr:full":"PO Box 67 Pymble NSW 2073",
    "addr:postcode":"2073",
    "iso:country":"AU",
    "sg:address":"PO Box 67",
    "sg:city":"Pymble",
    "sg:classifiers":[
        {
            "category":"Building & Trades",
            "subcategory":"Cleaning & Sanitation",
            "type":"Services"
        }
    ],
    "sg:phone":"+61 1800 817 547",
    "sg:postcode":"2073",
    "sg:province":"NSW",
    "sg:tags":[
        "cleaner",
        "repairer",
        "roof"
    ],
    "wof:name":"Resurrection Re-Roofing",
    "wof:placetype":"venue"
},
  "geometry": {"coordinates":[151.13749694800001,-33.7405281067],"type":"Point"}
}