{
  "type": "Feature",
  "properties": {
    "addr:full":"20 Main St Port Vincent SA 5581",
    "addr:housenumber":"20",
    "addr:postcode":"5581",
    "addr:street":"Main St",
    "iso:country":"AU",
    "sg:address":"20 Main St",
    "sg:city":"Port Vincent",
    "sg:classifiers":[
        {
            "category":"Government",
            "subcategory":"Post Office",
            "type":"Public Place"
        }
    ],
    "sg:phone":"+61 8 8853 7020",
    "sg:postcode":"5581",
    "sg:province":"SA",
    "sg:tags":[
        "postal"
    ],
    "wof:name":"Australia Post",
    "wof:placetype":"venue"
},
  "geometry": {"coordinates":[137.859375,-34.7790374756],"type":"Point"}
}