{
  "type": "Feature",
  "properties": {
    "addr:full":"Theta Therapeutic Centre 27 Norman St Clifton QLD 4361",
    "addr:housenumber":"27",
    "addr:postcode":"4361",
    "addr:street":"Norman St",
    "iso:country":"AU",
    "sg:address":"Theta Therapeutic Centre 27 Norman St",
    "sg:city":"Clifton",
    "sg:classifiers":[
        {
            "category":"Health Services",
            "subcategory":"Health Practitioner",
            "type":"Services"
        }
    ],
    "sg:phone":"+61 7 4697 3252",
    "sg:postcode":"4361",
    "sg:province":"QLD",
    "sg:tags":[
        "naturopath"
    ],
    "wof:name":"Bell Althea Rhyl",
    "wof:placetype":"venue"
},
  "geometry": {"coordinates":[151.91110229500001,-27.9283714294],"type":"Point"}
}