{
  "type": "Feature",
  "properties": {
    "iso:country":"AU",
    "sg:address":"2 Kendall St",
    "sg:city":"Sans Souci",
    "sg:classifiers":[
        {
            "category":"Building & Trades",
            "subcategory":"Construction",
            "type":"Services"
        }
    ],
    "sg:phone":"+61 418 472 384",
    "sg:postcode":"2219",
    "sg:province":"NSW",
    "sg:tags":[
        "contractor"
    ],
    "wof:name":"Williamson J & K",
    "wof:placetype":"venue"
},
  "geometry": {"coordinates":[151.12872300000001,-33.9981],"type":"Point"}
}