{
  "type": "Feature",
  "properties": {
    "iso:country":"AU",
    "sg:address":"21 Doblo Ave",
    "sg:city":"North Rockhampton",
    "sg:classifiers":[
        {
            "category":"Autos & Motor Vehicles",
            "subcategory":"Auto Supplies",
            "type":"Retail Goods"
        }
    ],
    "sg:phone":"+61 411 434 611",
    "sg:postcode":"4701",
    "sg:province":"QLD",
    "sg:tags":[
        "accessory"
    ],
    "wof:name":"Ultimate Racegear",
    "wof:placetype":"venue"
},
  "geometry": {"coordinates":[150.530807495,-23.3386230469],"type":"Point"}
}