{
  "type": "Feature",
  "properties": {
    "addr:full":"269 Stockleigh Rd Jimboomba QLD 4280",
    "addr:housenumber":"269",
    "addr:postcode":"4280",
    "addr:street":"Stockleigh Rd",
    "iso:country":"AU",
    "sg:address":"269 Stockleigh Rd",
    "sg:city":"Jimboomba",
    "sg:classifiers":[
        {
            "category":"Personal",
            "subcategory":"Beauty Salon",
            "type":"Services"
        }
    ],
    "sg:phone":"+61 415 773 083",
    "sg:postcode":"4280",
    "sg:province":"QLD",
    "wof:name":"Pink Pamper Beauty Clinic",
    "wof:placetype":"venue"
},
  "geometry": {"coordinates":[153.03758199999999,-27.791395],"type":"Point"}
}