{
  "type": "Feature",
  "properties": {
    "addr:full":"32 Crofton St Bundaberg QLD 4670",
    "addr:housenumber":"32",
    "addr:postcode":"4670",
    "addr:street":"Crofton St",
    "iso:country":"AU",
    "sg:address":"32 Crofton St",
    "sg:city":"Bundaberg",
    "sg:classifiers":[
        {
            "category":"Health Services",
            "subcategory":"Doctor",
            "type":"Services"
        }
    ],
    "sg:phone":"+61 7 4152 8133",
    "sg:postcode":"4670",
    "sg:province":"QLD",
    "sg:tags":[
        "medical",
        "practitioner"
    ],
    "wof:name":"Astara Cosmetic Skin Clinic",
    "wof:placetype":"venue"
},
  "geometry": {"coordinates":[152.34854125999999,-24.8700485229],"type":"Point"}
}