{
  "type": "Feature",
  "properties": {
    "addr:full":"89 Barnetts Rd Berowra Heights NSW 2082",
    "addr:housenumber":"89",
    "addr:postcode":"2082",
    "addr:street":"Barnetts Rd",
    "iso:country":"AU",
    "sg:address":"89 Barnetts Rd",
    "sg:city":"Berowra Heights",
    "sg:classifiers":[
        {
            "category":"Government",
            "subcategory":"Court House",
            "type":"Public Place"
        }
    ],
    "sg:phone":"+61 2 9456 0212",
    "sg:postcode":"2082",
    "sg:province":"NSW",
    "sg:tags":[
        "personal",
        "marriage",
        "family",
        "counselling"
    ],
    "wof:name":"Change 4 Life",
    "wof:placetype":"venue"
},
  "geometry": {"coordinates":[151.13168335,-33.6173400879],"type":"Point"}
}