{
  "type": "Feature",
  "properties": {
    "addr:full":"86 Coolgardie St Bentley WA 6102",
    "addr:housenumber":"86",
    "addr:postcode":"6102",
    "addr:street":"Coolgardie St",
    "iso:country":"AU",
    "sg:address":"86 Coolgardie St",
    "sg:city":"Bentley",
    "sg:classifiers":[
        {
            "category":"Professional",
            "subcategory":"Computer Services",
            "type":"Services"
        }
    ],
    "sg:phone":"+61 8 9458 3889",
    "sg:postcode":"6102",
    "sg:province":"WA",
    "sg:tags":[
        "package",
        "software"
    ],
    "wof:name":"Logical Developments",
    "wof:placetype":"venue"
},
  "geometry": {"coordinates":[115.915031433,-32.0035972595],"type":"Point"}
}