{
  "type": "Feature",
  "properties": {
    "addr:full":"19/ 23 Bolam St Garbutt QLD 4814",
    "addr:housenumber":"19 / 23",
    "addr:postcode":"4814",
    "addr:street":"Bolam St",
    "iso:country":"AU",
    "sg:address":"19/ 23 Bolam St",
    "sg:city":"Garbutt",
    "sg:classifiers":[
        {
            "category":"Building & Trades",
            "subcategory":"Equipment Rental",
            "type":"Services"
        }
    ],
    "sg:phone":"+61 7 4775 7148",
    "sg:postcode":"4814",
    "sg:province":"QLD",
    "sg:tags":[
        "demolition",
        "contractor"
    ],
    "wof:name":"ADM Demolitions N.Q.",
    "wof:placetype":"venue"
},
  "geometry": {"coordinates":[146.77024800000001,-19.265593],"type":"Point"}
}