{
  "type": "Feature",
  "properties": {
    "addr:full":"338 Cotham Rd Kew VIC 3101",
    "addr:housenumber":"338",
    "addr:postcode":"3101",
    "addr:street":"Cotham Rd",
    "iso:country":"AU",
    "sg:address":"338 Cotham Rd",
    "sg:city":"Kew",
    "sg:classifiers":[
        {
            "category":"Health Services",
            "subcategory":"Doctor",
            "type":"Services"
        }
    ],
    "sg:phone":"+61 3 9817 4077",
    "sg:postcode":"3101",
    "sg:province":"VIC",
    "sg:tags":[
        "medical",
        "practitioner"
    ],
    "wof:name":"Stelmach Dr Z & M",
    "wof:placetype":"venue"
},
  "geometry": {"coordinates":[145.05613708499999,-37.8098831177],"type":"Point"}
}