{
  "type": "Feature",
  "properties": {
    "iso:country":"AU",
    "sg:address":"437 Hume Hwy",
    "sg:city":"Casula",
    "sg:classifiers":[
        {
            "category":"Travel",
            "subcategory":"Hotels & Motels",
            "type":"Entertainment"
        }
    ],
    "sg:phone":"+61 2 9822 2777",
    "sg:postcode":"2170",
    "sg:province":"NSW",
    "wof:name":"Hotel Formule 1",
    "wof:placetype":"venue"
},
  "geometry": {"coordinates":[150.90060424800001,-33.9526557922],"type":"Point"}
}