{
  "type": "Feature",
  "properties": {
    "addr:full":"Unit 2/ 1 Parkinson La Kardinya WA 6163",
    "addr:housenumber":"1",
    "addr:postcode":"6163",
    "addr:street":"Parkinson La",
    "iso:country":"AU",
    "sg:address":"Unit 2/ 1 Parkinson La",
    "sg:city":"Kardinya",
    "sg:classifiers":[
        {
            "category":"Cafe",
            "type":"Food & Drink"
        }
    ],
    "sg:phone":"+61 8 9314 7340",
    "sg:postcode":"6163",
    "sg:province":"WA",
    "wof:name":"Parklane Cafe & Lunch Bar",
    "wof:placetype":"venue"
},
  "geometry": {"coordinates":[115.803741,-32.062214],"type":"Point"}
}