{
  "type": "Feature",
  "properties": {
    "addr:full":"9 Kenross Crt Wantirna VIC 3152",
    "addr:housenumber":"9",
    "addr:postcode":"3152",
    "addr:street":"Kenross Crt",
    "iso:country":"AU",
    "sg:address":"9 Kenross Crt",
    "sg:city":"Wantirna",
    "sg:classifiers":[
        {
            "category":"Building & Trades",
            "subcategory":"Construction",
            "type":"Services"
        }
    ],
    "sg:phone":"+61 3 9720 2929",
    "sg:postcode":"3152",
    "sg:province":"VIC",
    "sg:tags":[
        "plasterboard",
        "plasterer",
        "fixer"
    ],
    "wof:name":"Webb Royston C",
    "wof:placetype":"venue"
},
  "geometry": {"coordinates":[145.234985352,-37.8457374573],"type":"Point"}
}