{
  "type": "Feature",
  "properties": {
    "iso:country":"AU",
    "sg:address":"375 Great Eastern Hwy",
    "sg:city":"Redcliffe",
    "sg:classifiers":[
        {
            "category":"Travel",
            "subcategory":"Hotels & Motels",
            "type":"Entertainment"
        }
    ],
    "sg:phone":"+61 8 9277 7777",
    "sg:postcode":"6104",
    "sg:province":"WA",
    "wof:name":"Marracoonda Perth Airport Motel",
    "wof:placetype":"venue"
},
  "geometry": {"coordinates":[115.945457459,-31.9294281006],"type":"Point"}
}