{
  "type": "Feature",
  "properties": {
    "addr:full":"75 Bourke St Brewarrina NSW 2839",
    "addr:housenumber":"75",
    "addr:postcode":"2839",
    "addr:street":"Bourke St",
    "iso:country":"AU",
    "sg:address":"75 Bourke St",
    "sg:city":"Brewarrina",
    "sg:classifiers":[
        {
            "category":"Professional",
            "subcategory":"Business Services",
            "type":"Services"
        }
    ],
    "sg:phone":"+61 2 6839 2143",
    "sg:postcode":"2839",
    "sg:province":"NSW",
    "sg:tags":[
        "livestock",
        "transport"
    ],
    "wof:name":"Johnston Peter Transport",
    "wof:placetype":"venue"
},
  "geometry": {"coordinates":[146.86433400000001,-29.965244],"type":"Point"}
}