{
  "type": "Feature",
  "properties": {
    "iso:country":"AU",
    "sg:address":"PO Box 17",
    "sg:city":"Junortoun",
    "sg:classifiers":[
        {
            "category":"Utilities",
            "subcategory":"Electric",
            "type":"Services"
        }
    ],
    "sg:phone":"+61 419 599 129",
    "sg:postcode":"3551",
    "sg:province":"VIC",
    "sg:tags":[
        "electrical",
        "contractor"
    ],
    "wof:name":"Switched On Electrical Contracting",
    "wof:placetype":"venue"
},
  "geometry": {"coordinates":[144.35353088400001,-36.7720985413],"type":"Point"}
}