{
  "type": "Feature",
  "properties": {
    "addr:full":"8 Dunluce Crt View Bank VIC 3084",
    "addr:housenumber":"8",
    "addr:postcode":"3084",
    "addr:street":"Dunluce Crt View Bank",
    "iso:country":"AU",
    "sg:address":"8 Dunluce Crt",
    "sg:city":"View Bank",
    "sg:classifiers":[
        {
            "category":"Health Services",
            "subcategory":"Health Practitioner",
            "type":"Services"
        }
    ],
    "sg:phone":"+61 3 9459 0014",
    "sg:postcode":"3084",
    "sg:province":"VIC",
    "sg:tags":[
        "psychologist"
    ],
    "wof:name":"Danek Christine",
    "wof:placetype":"venue"
},
  "geometry": {"coordinates":[145.08763122600001,-37.7435379028],"type":"Point"}
}