{
  "type": "Feature",
  "properties": {
    "addr:full":"35 Felspar St Welshpool WA 6106",
    "addr:housenumber":"35",
    "addr:postcode":"6106",
    "addr:street":"Felspar St",
    "iso:country":"AU",
    "sg:address":"35 Felspar St",
    "sg:city":"Welshpool",
    "sg:classifiers":[
        {
            "category":"Wholesale",
            "subcategory":"Scrap",
            "type":"Manufacturing & Wholesale Goods"
        }
    ],
    "sg:phone":"+61 8 9451 6818",
    "sg:postcode":"6106",
    "sg:province":"WA",
    "sg:tags":[
        "merchant",
        "metal"
    ],
    "wof:name":"Allied Metal Recyclers",
    "wof:placetype":"venue"
},
  "geometry": {"coordinates":[115.972457886,-31.9986476898],"type":"Point"}
}