{
  "type": "Feature",
  "properties": {
    "iso:country":"AU",
    "sg:address":"217 Charters Towers Rd",
    "sg:city":"Hermit Park",
    "sg:classifiers":[
        {
            "category":"Home & Garden",
            "subcategory":"Carpets & Floor Coverings",
            "type":"Retail Goods"
        }
    ],
    "sg:phone":"+61 7 4725 2844",
    "sg:postcode":"4812",
    "sg:province":"QLD",
    "sg:tags":[
        "mattress"
    ],
    "wof:name":"JR'S Foam & Rubber Pty Ltd",
    "wof:placetype":"venue"
},
  "geometry": {"coordinates":[146.796982,-19.285492],"type":"Point"}
}