{
  "type": "Feature",
  "properties": {
    "iso:country":"AU",
    "sg:address":"PO Box 7173",
    "sg:city":"Mannering Park",
    "sg:classifiers":[
        {
            "category":"Professional",
            "subcategory":"Accounting & Tax Preparation",
            "type":"Services"
        }
    ],
    "sg:phone":"+61 434 676 983",
    "sg:postcode":"2259",
    "sg:province":"NSW",
    "sg:tags":[
        "bookkeeping"
    ],
    "wof:name":"In The Black Consulting",
    "wof:placetype":"venue"
},
  "geometry": {"coordinates":[151.5390625,-33.1730804443],"type":"Point"}
}