{
  "type": "Feature",
  "properties": {
    "iso:country":"AU",
    "sg:address":"107 Youralla Rd",
    "sg:city":"Highclere",
    "sg:classifiers":[
        {
            "category":"Manufacturing",
            "subcategory":"Musical Instruments",
            "type":"Manufacturing & Wholesale Goods"
        }
    ],
    "sg:phone":"+61 3 6435 7744",
    "sg:postcode":"7321",
    "sg:province":"TAS",
    "sg:tags":[
        "logging",
        "timber"
    ],
    "wof:name":"C.T.P. Logging",
    "wof:placetype":"venue"
},
  "geometry": {"coordinates":[145.818726,-41.196648],"type":"Point"}
}