{
  "type": "Feature",
  "properties": {
    "addr:full":"St Albans VIC 3021",
    "addr:postcode":"3021",
    "iso:country":"AU",
    "sg:address":"St",
    "sg:city":"Albans",
    "sg:classifiers":[
        {
            "category":"Building & Trades",
            "subcategory":"Cleaning & Sanitation",
            "type":"Services"
        }
    ],
    "sg:phone":"+61 3 9366 1548",
    "sg:postcode":"3021",
    "sg:province":"VIC",
    "sg:tags":[
        "chemical",
        "pressure",
        "steam",
        "contractor"
    ],
    "wof:name":"Golden Moonlight Cleaning",
    "wof:placetype":"venue"
},
  "geometry": {"coordinates":[144.800217,-37.744259],"type":"Point"}
}