{
  "type": "Feature",
  "properties": {
    "iso:country":"AU",
    "sg:address":"409 George St",
    "sg:city":"Waterloo",
    "sg:classifiers":[
        {
            "category":"Banks & Credit Unions",
            "subcategory":"Bureau De Change",
            "type":"Services"
        }
    ],
    "sg:phone":"+61 2 9310 1770",
    "sg:postcode":"2017",
    "sg:province":"NSW",
    "sg:tags":[
        "photography",
        "video",
        "school"
    ],
    "wof:name":"Mondo Digital Pty Ltd",
    "wof:placetype":"venue"
},
  "geometry": {"coordinates":[151.20326232900001,-33.9016876221],"type":"Point"}
}