{
  "type": "Feature",
  "properties": {
    "addr:full":"142 Sheridan St Gundagai NSW 2722",
    "addr:housenumber":"142",
    "addr:postcode":"2722",
    "addr:street":"Sheridan St",
    "iso:country":"AU",
    "sg:address":"142 Sheridan St",
    "sg:city":"Gundagai",
    "sg:classifiers":[
        {
            "category":"Cafe",
            "type":"Food & Drink"
        }
    ],
    "sg:phone":"+61 2 6944 1109",
    "sg:postcode":"2722",
    "sg:province":"NSW",
    "wof:name":"Niagra Cafe",
    "wof:placetype":"venue"
},
  "geometry": {"coordinates":[148.104614,-35.064178],"type":"Point"}
}