{
  "type": "Feature",
  "properties": {
    "iso:country":"AU",
    "sg:address":"29 Sir Laurence Drv",
    "sg:city":"Seaford",
    "sg:classifiers":[
        {
            "category":"Recreation",
            "subcategory":"Boat Charter",
            "type":"Entertainment"
        }
    ],
    "sg:phone":"+61 3 9785 1984",
    "sg:postcode":"3198",
    "sg:province":"VIC",
    "sg:tags":[
        "canopy",
        "motor"
    ],
    "wof:name":"Southern Motor Trimming Pty Ltd",
    "wof:placetype":"venue"
},
  "geometry": {"coordinates":[145.14276123100001,-38.1160240173],"type":"Point"}
}