{
  "type": "Feature",
  "properties": {
    "iso:country":"AU",
    "sg:address":"239 High St",
    "sg:city":"Hastings",
    "sg:classifiers":[
        {
            "category":"Social Services",
            "subcategory":"Child Care",
            "type":"Services"
        }
    ],
    "sg:phone":"+61 3 5979 2831",
    "sg:postcode":"3915",
    "sg:province":"VIC",
    "wof:name":"Fun 4 Kids Child Care & Early Learning Centre",
    "wof:placetype":"venue"
},
  "geometry": {"coordinates":[145.17291259800001,-38.3078422546],"type":"Point"}
}