{
  "type": "Feature",
  "properties": {
    "addr:full":"Shop 1/ 56 Landsborough Pde Golden Beach QLD 4551",
    "addr:housenumber":"shop 1 / 56",
    "addr:postcode":"4551",
    "addr:street":"Landsborough Pde",
    "iso:country":"AU",
    "sg:address":"Shop 1/ 56 Landsborough Pde",
    "sg:city":"Golden Beach",
    "sg:classifiers":[
        {
            "category":"Health Services",
            "subcategory":"Health Practitioner",
            "type":"Services"
        }
    ],
    "sg:phone":"+61 7 5492 3305",
    "sg:postcode":"4551",
    "sg:province":"QLD",
    "sg:tags":[
        "naturopath"
    ],
    "wof:name":"Suncoast Natural Therapies Clinic",
    "wof:placetype":"venue"
},
  "geometry": {"coordinates":[153.11993408199999,-26.8218784332],"type":"Point"}
}