{
  "type": "Feature",
  "properties": {
    "addr:full":"309 Main Rd East St Albans VIC 3021",
    "addr:housenumber":"309",
    "addr:postcode":"3021",
    "addr:street":"Main Rd East",
    "iso:country":"AU",
    "sg:address":"309 Main Rd East St",
    "sg:city":"Albans",
    "sg:classifiers":[
        {
            "category":"Health Services",
            "subcategory":"Doctor",
            "type":"Services"
        }
    ],
    "sg:phone":"+61 3 9367 8847",
    "sg:postcode":"3021",
    "sg:province":"VIC",
    "sg:tags":[
        "medical",
        "practitioner"
    ],
    "wof:name":"Hocking N W J",
    "wof:placetype":"venue"
},
  "geometry": {"coordinates":[144.80514500000001,-37.744972],"type":"Point"}
}