{
  "type": "Feature",
  "properties": {
    "iso:country":"AU",
    "sg:address":"Emerald Vale Rd",
    "sg:city":"Wynyard",
    "sg:classifiers":[
        {
            "category":"Building & Trades",
            "subcategory":"Construction",
            "type":"Services"
        }
    ],
    "sg:phone":"+61 419 567 952",
    "sg:postcode":"7325",
    "sg:province":"TAS",
    "sg:tags":[
        "earth",
        "excavating",
        "moving",
        "contractor"
    ],
    "wof:name":"Hage A K Excavations",
    "wof:placetype":"venue"
},
  "geometry": {"coordinates":[145.663666,-40.982605],"type":"Point"}
}