{
  "type": "Feature",
  "properties": {
    "addr:full":"26 Acland St St Kilda VIC 3182",
    "addr:housenumber":"26",
    "addr:postcode":"3182",
    "addr:street":"Acland St",
    "iso:country":"AU",
    "sg:address":"26 Acland St",
    "sg:city":"St Kilda",
    "sg:classifiers":[
        {
            "category":"Arts & Performance",
            "subcategory":"Art Gallery",
            "type":"Entertainment"
        }
    ],
    "sg:phone":"+61 3 9209 6794",
    "sg:postcode":"3182",
    "sg:province":"VIC",
    "wof:name":"Linden-St Kilda Centre for Contemporary Arts",
    "wof:placetype":"venue"
},
  "geometry": {"coordinates":[144.97465515100001,-37.8629074097],"type":"Point"}
}