{
  "type": "Feature",
  "properties": {
    "iso:country":"AU",
    "sg:address":"Jindabyne Rd",
    "sg:city":"Berridale",
    "sg:classifiers":[
        {
            "category":"Travel",
            "subcategory":"Hotels & Motels",
            "type":"Entertainment"
        }
    ],
    "sg:phone":"+61 2 6456 3209",
    "sg:postcode":"2628",
    "sg:province":"NSW",
    "sg:tags":[
        "accommodation"
    ],
    "wof:name":"Berridale Inn Hotel-Motel",
    "wof:placetype":"venue"
},
  "geometry": {"coordinates":[148.825897217,-36.3664627075],"type":"Point"}
}