{
  "type": "Feature",
  "properties": {
    "addr:full":"Shop 11/12 K Mart Plaza Cnr Marion & Simpson Sts Mt Isa QLD 4825",
    "addr:housenumber":"shop 11 / 12",
    "addr:postcode":"4825",
    "addr:street":"Cnr;Mt Isa",
    "iso:country":"AU",
    "sg:address":"Shop 11/12 K Mart Plaza Cnr Marion & Simpson Sts",
    "sg:city":"Mt Isa",
    "sg:classifiers":[
        {
            "category":"Shopping",
            "subcategory":"Clothing, Apparel, & Fashions",
            "type":"Retail Goods"
        }
    ],
    "sg:phone":"+61 7 4743 6625",
    "sg:postcode":"4825",
    "sg:province":"QLD",
    "sg:tags":[
        "lady",
        "wear"
    ],
    "wof:name":"Katies Fashions (Aust) Pty Ltd",
    "wof:placetype":"venue"
},
  "geometry": {"coordinates":[139.481979,-20.73167],"type":"Point"}
}