{
  "type": "Feature",
  "properties": {
    "addr:full":"2a Duke St Beulah Park SA 5067",
    "addr:housenumber":"2a",
    "addr:postcode":"5067",
    "addr:street":"Duke St",
    "iso:country":"AU",
    "sg:address":"2a Duke St",
    "sg:city":"Beulah Park",
    "sg:phone":"+61 1800 999 599",
    "sg:postcode":"5067",
    "sg:province":"SA",
    "wof:name":"Pioneer Water Tanks",
    "wof:placetype":"venue"
},
  "geometry": {"coordinates":[138.64564514200001,-34.9203872681],"type":"Point"}
}