{
  "type": "Feature",
  "properties": {
    "addr:full":"3819 Abergowrie Road Abergowrie QLD 4850",
    "addr:housenumber":"3819",
    "addr:postcode":"4850",
    "addr:street":"Abergowrie Road",
    "iso:country":"AU",
    "sg:address":"3819 Abergowrie Road",
    "sg:city":"Abergowrie",
    "sg:classifiers":[
        {
            "category":"Education",
            "subcategory":"School",
            "type":"Public Place"
        }
    ],
    "sg:phone":"+61 7 4777 4600",
    "sg:postcode":"4850",
    "sg:province":"QLD",
    "wof:name":"Abergowrie College",
    "wof:placetype":"venue"
},
  "geometry": {"coordinates":[146.07774352999999,-18.6248397827],"type":"Point"}
}