{
  "type": "Feature",
  "properties": {
    "addr:full":"Suite 3, 100 Dorcas St Southbank VIC 3006",
    "addr:housenumber":"100",
    "addr:postcode":"3006",
    "addr:street":"Dorcas St",
    "iso:country":"AU",
    "sg:address":"Suite 3, 100 Dorcas St",
    "sg:city":"Southbank",
    "sg:classifiers":[
        {
            "category":"Professional",
            "subcategory":"Engineering",
            "type":"Services"
        }
    ],
    "sg:phone":"+61 3 5223 3415",
    "sg:postcode":"3006",
    "sg:province":"VIC",
    "sg:tags":[
        "engineer"
    ],
    "wof:name":"Tomkinson Pty. Ltd.",
    "wof:placetype":"venue"
},
  "geometry": {"coordinates":[144.96600341800001,-37.8312988281],"type":"Point"}
}