{
  "type": "Feature",
  "properties": {
    "addr:full":"3/ 3 Hornsey St Rozelle NSW 2039",
    "addr:housenumber":"/ 3",
    "addr:postcode":"2039",
    "addr:street":"Hornsey St",
    "iso:country":"AU",
    "sg:address":"3/ 3 Hornsey St",
    "sg:city":"Rozelle",
    "sg:classifiers":[
        {
            "category":"Real Estate",
            "subcategory":"Architect",
            "type":"Services"
        }
    ],
    "sg:phone":"+61 2 9818 3941",
    "sg:postcode":"2039",
    "sg:province":"NSW",
    "sg:tags":[
        "house",
        "damp",
        "waterproofing",
        "repair"
    ],
    "wof:name":"Mouldbusters Ventilation",
    "wof:placetype":"venue"
},
  "geometry": {"coordinates":[151.175704956,-33.8677444458],"type":"Point"}
}