{
  "type": "Feature",
  "properties": {
    "iso:country":"AU",
    "sg:address":"43 Pickering St",
    "sg:city":"Enoggera",
    "sg:classifiers":[
        {
            "category":"Manufacturing",
            "subcategory":"Motor Vehicles & Parts",
            "type":"Manufacturing & Wholesale Goods"
        }
    ],
    "sg:phone":"+61 7 3855 3188",
    "sg:postcode":"4051",
    "sg:province":"QLD",
    "sg:tags":[
        "replacement"
    ],
    "wof:name":"Super Cheap Auto",
    "wof:placetype":"venue"
},
  "geometry": {"coordinates":[152.99641418499999,-27.4196529388],"type":"Point"}
}