{
  "type": "Feature",
  "properties": {
    "iso:country":"AU",
    "sg:address":"611 Great Northern Hwy",
    "sg:city":"Herne Hill",
    "sg:classifiers":[
        {
            "category":"Utilities",
            "subcategory":"Electric",
            "type":"Services"
        }
    ],
    "sg:phone":"+61 418 949 440",
    "sg:postcode":"6056",
    "sg:province":"WA",
    "sg:tags":[
        "electrical",
        "contractor"
    ],
    "wof:name":"J & T Electrical Contracting",
    "wof:placetype":"venue"
},
  "geometry": {"coordinates":[116.017021179,-31.8242969513],"type":"Point"}
}