{
  "type": "Feature",
  "properties": {
    "iso:country":"AU",
    "sg:address":"Shop 5a King Arcade King St",
    "sg:city":"Grafton",
    "sg:classifiers":[
        {
            "category":"Retail",
            "subcategory":"Laundry & Dry Cleaning",
            "type":"Services"
        }
    ],
    "sg:phone":"+61 2 6642 7744",
    "sg:postcode":"2460",
    "sg:province":"NSW",
    "sg:tags":[
        "manicurist"
    ],
    "wof:name":"Skin Care Connection",
    "wof:placetype":"venue"
},
  "geometry": {"coordinates":[152.93226623499999,-29.6902923584],"type":"Point"}
}