{
  "type": "Feature",
  "properties": {
    "iso:country":"AU",
    "sg:address":"Lot1 Wimpole Rd",
    "sg:city":"Bunyip North",
    "sg:classifiers":[
        {
            "category":"Utilities",
            "subcategory":"Electric",
            "type":"Services"
        }
    ],
    "sg:phone":"+61 3 5629 5975",
    "sg:postcode":"3815",
    "sg:province":"VIC",
    "sg:tags":[
        "electrical",
        "contractor"
    ],
    "wof:name":"Buzz Electrics Pty Ltd",
    "wof:placetype":"venue"
},
  "geometry": {"coordinates":[145.741257,-38.069218],"type":"Point"}
}