{
  "type": "Feature",
  "properties": {
    "addr:full":"22 Banksia St Burwood VIC 3125",
    "addr:housenumber":"22",
    "addr:postcode":"3125",
    "addr:street":"Banksia St",
    "iso:country":"AU",
    "sg:address":"22 Banksia St",
    "sg:city":"Burwood",
    "sg:classifiers":[
        {
            "category":"Communications",
            "type":"Services"
        }
    ],
    "sg:phone":"+61 3 9808 0388",
    "sg:postcode":"3125",
    "sg:province":"VIC",
    "sg:tags":[
        "public",
        "system",
        "address"
    ],
    "wof:name":"B.S. Sound P.A. Hire",
    "wof:placetype":"venue"
},
  "geometry": {"coordinates":[145.09950256400001,-37.8437767029],"type":"Point"}
}