{
  "type": "Feature",
  "properties": {
    "addr:full":"440 Burnley St Richmond VIC 3121",
    "addr:housenumber":"440",
    "addr:postcode":"3121",
    "addr:street":"Burnley St",
    "iso:country":"AU",
    "sg:address":"440 Burnley St",
    "sg:city":"Richmond",
    "sg:classifiers":[
        {
            "category":"Utilities",
            "subcategory":"Recycling",
            "type":"Services"
        }
    ],
    "sg:phone":"+61 3 9421 4472",
    "sg:postcode":"3121",
    "sg:province":"VIC",
    "wof:name":"DHR Waste Services",
    "wof:placetype":"venue"
},
  "geometry": {"coordinates":[145.006393433,-37.8290748596],"type":"Point"}
}