{
  "type": "Feature",
  "properties": {
    "iso:country":"AU",
    "sg:address":"19 Padauk Drv",
    "sg:city":"Nerang",
    "sg:classifiers":[
        {
            "category":"Building & Trades",
            "subcategory":"Pest Control",
            "type":"Services"
        }
    ],
    "sg:phone":"+61 7 5596 1727",
    "sg:postcode":"4211",
    "sg:province":"QLD",
    "wof:name":"A.S.A.P Pest Control",
    "wof:placetype":"venue"
},
  "geometry": {"coordinates":[153.304321289,-28.0078964233],"type":"Point"}
}