{
  "type": "Feature",
  "properties": {
    "addr:full":"48 Prospect Tce Bowen Hills QLD 4006",
    "addr:housenumber":"48",
    "addr:postcode":"4006",
    "addr:street":"Prospect Tce",
    "iso:country":"AU",
    "sg:address":"48 Prospect Tce",
    "sg:city":"Bowen Hills",
    "sg:classifiers":[
        {
            "category":"Wholesale",
            "subcategory":"Construction Materials",
            "type":"Manufacturing & Wholesale Goods"
        }
    ],
    "sg:phone":"+61 7 3252 9709",
    "sg:postcode":"4006",
    "sg:province":"QLD",
    "sg:tags":[
        "lift"
    ],
    "wof:name":"A & RMS Pty Ltd",
    "wof:placetype":"venue"
},
  "geometry": {"coordinates":[153.04318237300001,-27.448431015],"type":"Point"}
}