{
  "type": "Feature",
  "properties": {
    "addr:full":"Pechey Rd Swan View WA 6056",
    "addr:postcode":"6056",
    "addr:street":"Pechey Rd",
    "iso:country":"AU",
    "sg:address":"Pechey Rd",
    "sg:city":"Swan View",
    "sg:classifiers":[
        {
            "category":"Retail",
            "subcategory":"Driving School",
            "type":"Services"
        }
    ],
    "sg:phone":"+61 8 9294 1729",
    "sg:postcode":"6056",
    "sg:province":"WA",
    "wof:name":"Silverlock's Driving School",
    "wof:placetype":"venue"
},
  "geometry": {"coordinates":[116.060623169,-31.8855133057],"type":"Point"}
}