{
  "type": "Feature",
  "properties": {
    "addr:full":"78 Dalmahoy St Bairnsdale VIC 3875",
    "addr:housenumber":"78",
    "addr:postcode":"3875",
    "addr:street":"Dalmahoy St",
    "iso:country":"AU",
    "sg:address":"78 Dalmahoy St",
    "sg:city":"Bairnsdale",
    "sg:classifiers":[
        {
            "category":"Retail",
            "subcategory":"Laundry & Dry Cleaning",
            "type":"Services"
        }
    ],
    "sg:phone":"+61 3 5152 4508",
    "sg:postcode":"3875",
    "sg:province":"VIC",
    "wof:name":"Hammonds Drive In Dry Cleaners & Launderers",
    "wof:placetype":"venue"
},
  "geometry": {"coordinates":[147.62348938,-37.8301315308],"type":"Point"}
}