{
  "type": "Feature",
  "properties": {
    "iso:country":"AU",
    "sg:address":"White St",
    "sg:city":"Mukinbudin",
    "sg:classifiers":[
        {
            "category":"Education",
            "subcategory":"School",
            "type":"Public Place"
        }
    ],
    "sg:phone":"+61 8 9047 1053",
    "sg:postcode":"6479",
    "sg:province":"WA",
    "sg:tags":[
        "state",
        "except",
        "nsw"
    ],
    "wof:name":"Mukinbudin District High School",
    "wof:placetype":"venue"
},
  "geometry": {"coordinates":[118.208351135,-30.9184322357],"type":"Point"}
}