{
  "type": "Feature",
  "properties": {
    "addr:full":"16 Strathmore Crt Kanimbla QLD 4870",
    "addr:housenumber":"16",
    "addr:postcode":"4870",
    "addr:street":"Strathmore Crt",
    "iso:country":"AU",
    "sg:address":"16 Strathmore Crt",
    "sg:city":"Kanimbla",
    "sg:classifiers":[
        {
            "category":"Building & Trades",
            "subcategory":"Cleaning & Sanitation",
            "type":"Services"
        }
    ],
    "sg:phone":"+61 7 4054 1487",
    "sg:postcode":"4870",
    "sg:province":"QLD",
    "sg:tags":[
        "industrial",
        "commercial",
        "contractor"
    ],
    "wof:name":"Cairns Cleaning Services",
    "wof:placetype":"venue"
},
  "geometry": {"coordinates":[145.72604370100001,-16.9378242493],"type":"Point"}
}