{
  "type": "Feature",
  "properties": {
    "addr:full":"Unit 1, 110 David St Dandenong VIC 3175",
    "addr:housenumber":"110",
    "addr:postcode":"3175",
    "addr:street":"David St",
    "iso:country":"AU",
    "sg:address":"Unit 1, 110 David St",
    "sg:city":"Dandenong",
    "sg:classifiers":[
        {
            "category":"Health Services",
            "subcategory":"Doctor",
            "type":"Services"
        }
    ],
    "sg:phone":"+61 3 9791 3455",
    "sg:postcode":"3175",
    "sg:province":"VIC",
    "sg:tags":[
        "medical",
        "practitioner"
    ],
    "wof:name":"Fergin Peter Dr",
    "wof:placetype":"venue"
},
  "geometry": {"coordinates":[145.21879577600001,-37.9773521423],"type":"Point"}
}