{
  "type": "Feature",
  "properties": {
    "addr:full":"47/ 5 Ponderosa Pde Warriewood NSW 2102",
    "addr:housenumber":"47 / 5",
    "addr:postcode":"2102",
    "addr:street":"Ponderosa Pde",
    "iso:country":"AU",
    "sg:address":"47/ 5 Ponderosa Pde",
    "sg:city":"Warriewood",
    "sg:classifiers":[
        {
            "category":"Autos & Motor Vehicles",
            "subcategory":"Boat Sales",
            "type":"Retail Goods"
        }
    ],
    "sg:phone":"+61 1800 803 569",
    "sg:postcode":"2102",
    "sg:province":"NSW",
    "sg:tags":[
        "machine",
        "dishwashing"
    ],
    "wof:name":"All Norris Glass & Dishwasher Service",
    "wof:placetype":"venue"
},
  "geometry": {"coordinates":[151.28829999999999,-33.680737],"type":"Point"}
}