{
  "type": "Feature",
  "properties": {
    "addr:full":"14-16 Cnr of Bayshore & Banksia Drv Byron Bay NSW 2481",
    "addr:housenumber":"14-16",
    "addr:postcode":"2481",
    "addr:street":"Cnr Of;Drv",
    "iso:country":"AU",
    "sg:address":"14-16 Cnr of Bayshore & Banksia Drv",
    "sg:city":"Byron Bay",
    "sg:classifiers":[
        {
            "category":"Autos & Motor Vehicles",
            "subcategory":"Automobile Sales",
            "type":"Retail Goods"
        }
    ],
    "sg:phone":"+61 2 6680 7533",
    "sg:postcode":"2481",
    "sg:province":"NSW",
    "sg:tags":[
        "car",
        "used"
    ],
    "wof:name":"Byron Classic Cars",
    "wof:placetype":"venue"
},
  "geometry": {"coordinates":[153.58578491200001,-28.6378288269],"type":"Point"}
}