{
  "type": "Feature",
  "properties": {
    "iso:country":"AU",
    "sg:address":"76 Warwick Rd",
    "sg:city":"Ipswich",
    "sg:classifiers":[
        {
            "category":"Shopping",
            "subcategory":"Computers & Home Electronics",
            "type":"Retail Goods"
        }
    ],
    "sg:phone":"+61 7 3812 1989",
    "sg:postcode":"4305",
    "sg:province":"QLD",
    "sg:tags":[
        "hardware",
        "equipment"
    ],
    "wof:name":"Silkstone IT",
    "wof:placetype":"venue"
},
  "geometry": {"coordinates":[152.76039123499999,-27.6250553131],"type":"Point"}
}