{
  "type": "Feature",
  "properties": {
    "addr:full":"Unit 78 171 Flemington Rd North Melbourne VIC 3051",
    "addr:housenumber":"171",
    "addr:postcode":"3051",
    "addr:street":"Flemington Rd",
    "iso:country":"AU",
    "sg:address":"Unit 78 171 Flemington Rd",
    "sg:city":"North Melbourne",
    "sg:classifiers":[
        {
            "category":"Shopping",
            "subcategory":"Musical Instruments",
            "type":"Retail Goods"
        }
    ],
    "sg:phone":"+61 3 9328 8634",
    "sg:postcode":"3051",
    "sg:province":"VIC",
    "sg:tags":[
        "musician",
        "agent"
    ],
    "wof:name":"Ascot String Quartet",
    "wof:placetype":"venue"
},
  "geometry": {"coordinates":[144.94940185600001,-37.7955436707],"type":"Point"}
}