{
  "type": "Feature",
  "properties": {
    "addr:full":"110 Wood St Mackay QLD 4740",
    "addr:housenumber":"110",
    "addr:postcode":"4740",
    "addr:street":"Wood St",
    "iso:country":"AU",
    "sg:address":"110 Wood St",
    "sg:city":"Mackay",
    "sg:classifiers":[
        {
            "category":"Education",
            "subcategory":"Kindergarten",
            "type":"Public Place"
        }
    ],
    "sg:phone":"+61 7 4951 5920",
    "sg:postcode":"4740",
    "sg:province":"QLD",
    "sg:tags":[
        "pre-schools"
    ],
    "wof:name":"Creche & Kindergarten Association Of Queensland",
    "wof:placetype":"venue"
},
  "geometry": {"coordinates":[149.185394,-21.143511],"type":"Point"}
}