{
  "type": "Feature",
  "properties": {
    "iso:country":"AU",
    "sg:address":"12 Kalara Crt",
    "sg:city":"Carseldine",
    "sg:classifiers":[
        {
            "category":"Professional",
            "subcategory":"Business Services",
            "type":"Services"
        }
    ],
    "sg:phone":"+61 7 3263 3595",
    "sg:postcode":"4034",
    "sg:province":"QLD",
    "sg:tags":[
        "drafting"
    ],
    "wof:name":"Hislop P.F.",
    "wof:placetype":"venue"
},
  "geometry": {"coordinates":[153.023392,-27.346149],"type":"Point"}
}