{
  "type": "Feature",
  "properties": {
    "iso:country":"AU",
    "sg:address":"18 High St",
    "sg:city":"Wodonga",
    "sg:classifiers":[
        {
            "category":"Wholesale",
            "subcategory":"Painting Supplies",
            "type":"Manufacturing & Wholesale Goods"
        }
    ],
    "sg:phone":"+61 2 6056 1633",
    "sg:postcode":"3690",
    "sg:province":"VIC",
    "sg:tags":[
        "equipment",
        "spraying"
    ],
    "wof:name":"Flower Macklan Pty Ltd",
    "wof:placetype":"venue"
},
  "geometry": {"coordinates":[146.89358520499999,-36.1126327515],"type":"Point"}
}