{
  "type": "Feature",
  "properties": {
    "iso:country":"AU",
    "sg:address":"2/ 228 Ripley Rd",
    "sg:city":"Flinders View",
    "sg:classifiers":[
        {
            "category":"Health Services",
            "subcategory":"Health Practitioner",
            "type":"Services"
        }
    ],
    "sg:phone":"+61 7 3288 0455",
    "sg:postcode":"4305",
    "sg:province":"QLD",
    "sg:tags":[
        "physiotherapist"
    ],
    "wof:name":"Bertram Physiotherapy",
    "wof:placetype":"venue"
},
  "geometry": {"coordinates":[152.77456665,-27.6494464874],"type":"Point"}
}