{
  "type": "Feature",
  "properties": {
    "addr:full":"4 Darra Ave Darra QLD 4076",
    "addr:housenumber":"4",
    "addr:postcode":"4076",
    "addr:street":"Darra Ave",
    "iso:country":"AU",
    "sg:address":"4 Darra Ave",
    "sg:city":"Darra",
    "sg:classifiers":[
        {
            "category":"Building & Trades",
            "subcategory":"Plumbing",
            "type":"Services"
        }
    ],
    "sg:phone":"+61 7 3375 4900",
    "sg:postcode":"4076",
    "sg:province":"QLD",
    "sg:tags":[
        "plumber",
        "gasfitters"
    ],
    "wof:name":"Van Doorn G P & R A",
    "wof:placetype":"venue"
},
  "geometry": {"coordinates":[152.957763672,-27.5640296936],"type":"Point"}
}