{
  "type": "Feature",
  "properties": {
    "addr:full":"1/ 10 Grieve Cl Gosford West NSW 2250",
    "addr:housenumber":"/ 10",
    "addr:postcode":"2250",
    "addr:street":"Grieve Cl Gosford West",
    "iso:country":"AU",
    "sg:address":"1/ 10",
    "sg:city":"Grieve Cl Gosford West",
    "sg:classifiers":[
        {
            "category":"Autos & Motor Vehicles",
            "subcategory":"Fuel & Gas Station",
            "type":"Retail Goods"
        }
    ],
    "sg:phone":"+61 1800 028 283",
    "sg:postcode":"2250",
    "sg:province":"NSW",
    "sg:tags":[
        "petrol",
        "marketing",
        "pump",
        "equipment"
    ],
    "wof:name":"National Petroleum Equipment",
    "wof:placetype":"venue"
},
  "geometry": {"coordinates":[151.32734680199999,-33.4264717102],"type":"Point"}
}