{
  "type": "Feature",
  "properties": {
    "addr:full":"97 Joseph St Kingswood NSW 2747",
    "addr:housenumber":"97",
    "addr:postcode":"2747",
    "addr:street":"Joseph St",
    "iso:country":"AU",
    "sg:address":"97 Joseph St",
    "sg:city":"Kingswood",
    "sg:classifiers":[
        {
            "category":"Professional",
            "subcategory":"Art Services",
            "type":"Services"
        }
    ],
    "sg:phone":"+61 2 4731 2436",
    "sg:postcode":"2747",
    "sg:province":"NSW",
    "sg:tags":[
        "picture",
        "frame",
        "framing"
    ],
    "wof:name":"Rivermont Framing Gallery",
    "wof:placetype":"venue"
},
  "geometry": {"coordinates":[150.723098755,-33.7564086914],"type":"Point"}
}