{
  "type": "Feature",
  "properties": {
    "addr:full":"5 Mathews St Hope Valley SA 5090",
    "addr:housenumber":"5",
    "addr:postcode":"5090",
    "addr:street":"Mathews St",
    "iso:country":"AU",
    "sg:address":"5 Mathews St",
    "sg:city":"Hope Valley",
    "sg:classifiers":[
        {
            "category":"Professional",
            "subcategory":"Art Services",
            "type":"Services"
        }
    ],
    "sg:phone":"+61 8 8265 5480",
    "sg:postcode":"5090",
    "sg:province":"SA",
    "sg:tags":[
        "picture",
        "frame",
        "framing"
    ],
    "wof:name":"North East Custom Framing",
    "wof:placetype":"venue"
},
  "geometry": {"coordinates":[138.716674805,-34.8391227722],"type":"Point"}
}