{
  "type": "Feature",
  "properties": {
    "addr:full":"78 Harper St Ashmore QLD 4214",
    "addr:housenumber":"78",
    "addr:postcode":"4214",
    "addr:street":"Harper St",
    "iso:country":"AU",
    "sg:address":"78 Harper St",
    "sg:city":"Ashmore",
    "sg:classifiers":[
        {
            "category":"Wholesale",
            "subcategory":"Auto Parts",
            "type":"Manufacturing & Wholesale Goods"
        }
    ],
    "sg:phone":"+61 7 5527 8911",
    "sg:postcode":"4214",
    "sg:province":"QLD",
    "sg:tags":[
        "recyclers"
    ],
    "wof:name":"Hinterland 4X4 & Commercial Wreckers",
    "wof:placetype":"venue"
},
  "geometry": {"coordinates":[153.35839843799999,-27.9850311279],"type":"Point"}
}