{
  "type": "Feature",
  "properties": {
    "addr:full":"20 Stwal Crs Emerald QLD 4720",
    "addr:housenumber":"20",
    "addr:postcode":"4720",
    "addr:street":"Stwal Crs",
    "iso:country":"AU",
    "sg:address":"20 Stwal Crs",
    "sg:city":"Emerald",
    "sg:classifiers":[
        {
            "category":"Building & Trades",
            "subcategory":"Construction",
            "type":"Services"
        }
    ],
    "sg:phone":"+61 401 813 520",
    "sg:postcode":"4720",
    "sg:province":"QLD",
    "sg:tags":[
        "concrete",
        "contractor"
    ],
    "wof:name":"Shane Peel Concreting",
    "wof:placetype":"venue"
},
  "geometry": {"coordinates":[148.15815734899999,-23.5248699188],"type":"Point"}
}