{
  "type": "Feature",
  "properties": {
    "iso:country":"AU",
    "sg:address":"RMB 635 Little Jilliby Rd",
    "sg:city":"Jilliby",
    "sg:classifiers":[
        {
            "category":"Retail",
            "subcategory":"Veterinary Services",
            "type":"Services"
        }
    ],
    "sg:phone":"+61 2 4355 1428",
    "sg:postcode":"2259",
    "sg:province":"NSW",
    "sg:tags":[
        "surgeon"
    ],
    "wof:name":"Phillips Keith C BVSc",
    "wof:placetype":"venue"
},
  "geometry": {"coordinates":[151.35104370100001,-33.2360649109],"type":"Point"}
}