{
  "type": "Feature",
  "properties": {
    "addr:full":"Military Rd North Bondi NSW 2026",
    "addr:postcode":"2026",
    "addr:street":"Military Rd",
    "iso:country":"AU",
    "sg:address":"Military Rd",
    "sg:city":"North Bondi",
    "sg:classifiers":[
        {
            "category":"Retail",
            "subcategory":"Event Space",
            "type":"Services"
        }
    ],
    "sg:phone":"+61 2 9130 1981",
    "sg:postcode":"2026",
    "sg:province":"NSW",
    "sg:tags":[
        "function",
        "organiser"
    ],
    "wof:name":"Bondi Golf Club",
    "wof:placetype":"venue"
},
  "geometry": {"coordinates":[151.282546997,-33.8834991455],"type":"Point"}
}