{
  "type": "Feature",
  "properties": {
    "addr:full":"20 Lipton Drv Thomastown VIC 3074",
    "addr:housenumber":"20",
    "addr:postcode":"3074",
    "addr:street":"Lipton Drv",
    "iso:country":"AU",
    "sg:address":"20 Lipton Drv",
    "sg:city":"Thomastown",
    "sg:classifiers":[
        {
            "category":"Home & Garden",
            "subcategory":"Building Materials",
            "type":"Retail Goods"
        }
    ],
    "sg:phone":"+61 3 9469 5360",
    "sg:postcode":"3074",
    "sg:province":"VIC",
    "sg:tags":[
        "fitting",
        "door"
    ],
    "wof:name":"Lenwall Trading Co",
    "wof:placetype":"venue"
},
  "geometry": {"coordinates":[144.997970581,-37.6897315979],"type":"Point"}
}