{
  "type": "Feature",
  "properties": {
    "iso:country":"AU",
    "sg:address":"2 Kessell St",
    "sg:city":"Gladstone",
    "sg:classifiers":[
        {
            "category":"Retail",
            "subcategory":"Repair Shop",
            "type":"Services"
        }
    ],
    "sg:phone":"+61 7 4972 5654",
    "sg:postcode":"4680",
    "sg:province":"QLD",
    "sg:tags":[
        "machine",
        "repairs",
        "part",
        "dryer",
        "washing"
    ],
    "wof:name":"Flint Electrics",
    "wof:placetype":"venue"
},
  "geometry": {"coordinates":[151.257522583,-23.8542861938],"type":"Point"}
}