{
  "type": "Feature",
  "properties": {
    "iso:country":"AU",
    "sg:address":"PO Box 680",
    "sg:city":"Potts Point",
    "sg:classifiers":[
        {
            "category":"Education",
            "subcategory":"Special Training",
            "type":"Public Place"
        }
    ],
    "sg:phone":"+61 1800 679 288",
    "sg:postcode":"2011",
    "sg:province":"NSW",
    "sg:tags":[
        "development"
    ],
    "wof:name":"Ocean Training Systems",
    "wof:placetype":"venue"
},
  "geometry": {"coordinates":[151.222854614,-33.8715896606],"type":"Point"}
}