{
  "type": "Feature",
  "properties": {
    "addr:full":"243 Pyrmont St Pyrmont NSW 2009",
    "addr:housenumber":"243",
    "addr:postcode":"2009",
    "addr:street":"Pyrmont St",
    "iso:country":"AU",
    "sg:address":"243 Pyrmont St",
    "sg:city":"Pyrmont",
    "sg:classifiers":[
        {
            "category":"Professional",
            "subcategory":"Employment Agencies",
            "type":"Services"
        }
    ],
    "sg:phone":"+61 2 9518 8589",
    "sg:postcode":"2009",
    "sg:province":"NSW",
    "sg:tags":[
        "entertainer",
        "agent"
    ],
    "wof:name":"Millennium Entertainment International",
    "wof:placetype":"venue"
},
  "geometry": {"coordinates":[151.19711303700001,-33.8734931946],"type":"Point"}
}