{
  "type": "Feature",
  "properties": {
    "addr:full":"28 Albion St Kingsville VIC 3012",
    "addr:housenumber":"28",
    "addr:postcode":"3012",
    "addr:street":"Albion St",
    "iso:country":"AU",
    "sg:address":"28 Albion St",
    "sg:city":"Kingsville",
    "sg:classifiers":[
        {
            "category":"Professional",
            "subcategory":"Accounting & Tax Preparation",
            "type":"Services"
        }
    ],
    "sg:phone":"+61 3 9314 4685",
    "sg:postcode":"3012",
    "sg:province":"VIC",
    "sg:tags":[
        "consultant",
        "taxation"
    ],
    "wof:name":"Courtney John J",
    "wof:placetype":"venue"
},
  "geometry": {"coordinates":[144.87144470199999,-37.8111305237],"type":"Point"}
}