{
  "type": "Feature",
  "properties": {
    "addr:full":"50 Atherton Rd Oakleigh VIC 3166",
    "addr:housenumber":"50",
    "addr:postcode":"3166",
    "addr:street":"Atherton Rd",
    "iso:country":"AU",
    "sg:address":"50 Atherton Rd",
    "sg:city":"Oakleigh",
    "sg:classifiers":[
        {
            "category":"Shopping",
            "subcategory":"Clothing, Apparel, & Fashions",
            "type":"Retail Goods"
        }
    ],
    "sg:phone":"+61 3 9564 7379",
    "sg:postcode":"3166",
    "sg:province":"VIC",
    "sg:tags":[
        "recycled",
        "clothing"
    ],
    "wof:name":"The Salvation Army Family Stores",
    "wof:placetype":"venue"
},
  "geometry": {"coordinates":[145.091873169,-37.8990745544],"type":"Point"}
}