{
  "type": "Feature",
  "properties": {
    "iso:country":"AU",
    "sg:address":"Bay 22, 10 Bellbowrie Pk",
    "sg:city":"Port Macquarie",
    "sg:classifiers":[
        {
            "category":"Professional",
            "subcategory":"Art Services",
            "type":"Services"
        }
    ],
    "sg:phone":"+61 2 6583 9577",
    "sg:postcode":"2444",
    "sg:province":"NSW",
    "sg:tags":[
        "graphic",
        "designer"
    ],
    "wof:name":"Digital Design & Poster Studio",
    "wof:placetype":"venue"
},
  "geometry": {"coordinates":[152.886932,-31.429293],"type":"Point"}
}