{
  "type": "Feature",
  "properties": {
    "addr:full":"20 Victoria St Ballarat VIC 3350",
    "addr:housenumber":"20",
    "addr:postcode":"3350",
    "addr:street":"Victoria St",
    "iso:country":"AU",
    "sg:address":"20 Victoria St",
    "sg:city":"Ballarat",
    "sg:classifiers":[
        {
            "category":"Banks & Credit Unions",
            "subcategory":"Investment Brokerage",
            "type":"Services"
        }
    ],
    "sg:phone":"+61 3 5333 5858",
    "sg:postcode":"3350",
    "sg:province":"VIC",
    "sg:tags":[
        "finance",
        "broker"
    ],
    "wof:name":"Vehicle & Equipment Finance",
    "wof:placetype":"venue"
},
  "geometry": {"coordinates":[143.866623,-37.56287],"type":"Point"}
}