{
  "type": "Feature",
  "properties": {
    "addr:full":"371 Shepherds Hill Rd Blackwood SA 5051",
    "addr:housenumber":"371",
    "addr:postcode":"5051",
    "addr:street":"Shepherds Hill Rd",
    "iso:country":"AU",
    "sg:address":"371 Shepherds Hill Rd",
    "sg:city":"Blackwood",
    "sg:classifiers":[
        {
            "category":"Retail",
            "subcategory":"Auto Repair",
            "type":"Services"
        }
    ],
    "sg:phone":"+61 8 8278 1169",
    "sg:postcode":"5051",
    "sg:province":"SA",
    "sg:tags":[
        "repairer",
        "motor",
        "engineer"
    ],
    "wof:name":"Blackwood Brake & Clutch",
    "wof:placetype":"venue"
},
  "geometry": {"coordinates":[138.61552399999999,-35.02113],"type":"Point"}
}