{
  "type": "Feature",
  "properties": {
    "iso:country":"AU",
    "sg:address":"PO Box 316",
    "sg:city":"Belmont",
    "sg:classifiers":[
        {
            "category":"Personal",
            "type":"Services"
        }
    ],
    "sg:phone":"+61 432 373 608",
    "sg:postcode":"3216",
    "sg:province":"VIC",
    "sg:tags":[
        "reducing",
        "treatment",
        "weight"
    ],
    "wof:name":"Rebecca Dempster- Independent Herbalife Distributor",
    "wof:placetype":"venue"
},
  "geometry": {"coordinates":[144.34268188499999,-38.1750984192],"type":"Point"}
}