{
  "type": "Feature",
  "properties": {
    "addr:full":"90 Boyd St Austral NSW 2171",
    "addr:housenumber":"90",
    "addr:postcode":"2171",
    "addr:street":"Boyd St",
    "iso:country":"AU",
    "sg:address":"90 Boyd St",
    "sg:city":"Austral",
    "sg:classifiers":[
        {
            "category":"Mining & Drilling",
            "type":"Manufacturing & Wholesale Goods"
        }
    ],
    "sg:phone":"+61 418 776 650",
    "sg:postcode":"2171",
    "sg:province":"NSW",
    "sg:tags":[
        "boring",
        "contractor"
    ],
    "wof:name":"M Lakin",
    "wof:placetype":"venue"
},
  "geometry": {"coordinates":[150.79151916500001,-33.9309425354],"type":"Point"}
}