{
  "type": "Feature",
  "properties": {
    "addr:full":"14/ 229 Brisbane Rd Labrador QLD 4215",
    "addr:housenumber":"14 / 229",
    "addr:postcode":"4215",
    "addr:street":"Brisbane Rd",
    "iso:country":"AU",
    "sg:address":"14/ 229 Brisbane Rd",
    "sg:city":"Labrador",
    "sg:classifiers":[
        {
            "category":"Manufacturing",
            "subcategory":"Chemicals & Compounds",
            "type":"Manufacturing & Wholesale Goods"
        }
    ],
    "sg:phone":"+61 1300 852 655",
    "sg:postcode":"4215",
    "sg:province":"QLD",
    "sg:tags":[
        "industrial"
    ],
    "wof:name":"J & J Manufacturers-Private Label Chemicals",
    "wof:placetype":"venue"
},
  "geometry": {"coordinates":[153.40724182100001,-27.9381504059],"type":"Point"}
}