{
  "type": "Feature",
  "properties": {
    "iso:country":"AU",
    "sg:address":"7 Bridge St",
    "sg:city":"Northcote",
    "sg:classifiers":[
        {
            "category":"Building & Trades",
            "subcategory":"Construction",
            "type":"Services"
        }
    ],
    "sg:phone":"+61 425 747 189",
    "sg:postcode":"3070",
    "sg:province":"VIC",
    "sg:tags":[
        "polishing",
        "sanding",
        "floor"
    ],
    "wof:name":"Barclay Floor Sanding & Polishing",
    "wof:placetype":"venue"
},
  "geometry": {"coordinates":[144.99070699999999,-37.777477],"type":"Point"}
}