{
  "type": "Feature",
  "properties": {
    "iso:country":"AU",
    "sg:address":"537 Malvern Rd",
    "sg:city":"Toorak",
    "sg:classifiers":[
        {
            "category":"Banks & Credit Unions",
            "subcategory":"Financial Services",
            "type":"Services"
        }
    ],
    "sg:phone":"+61 3 9823 1497",
    "sg:postcode":"3142",
    "sg:province":"VIC",
    "sg:tags":[
        "financier"
    ],
    "wof:name":"Royal Enterprises",
    "wof:placetype":"venue"
},
  "geometry": {"coordinates":[145.004272461,-37.8480911255],"type":"Point"}
}