{
  "type": "Feature",
  "properties": {
    "addr:full":"Cnr Scarborough & Young Sts Southport QLD 4215",
    "addr:postcode":"4215",
    "addr:street":"Cnr",
    "iso:country":"AU",
    "sg:address":"Cnr Scarborough & Young Sts",
    "sg:city":"Southport",
    "sg:classifiers":[
        {
            "category":"Health Services",
            "subcategory":"Dentist",
            "type":"Services"
        }
    ],
    "sg:phone":"+61 7 5591 2661",
    "sg:postcode":"4215",
    "sg:province":"QLD",
    "wof:name":"Australia Fair Shopping Centre Dental Care",
    "wof:placetype":"venue"
},
  "geometry": {"coordinates":[153.413406372,-27.9661636353],"type":"Point"}
}