{
  "type": "Feature",
  "properties": {
    "addr:full":"Suite 2, Level 4, 11 The Boulevarde Strathfield NSW 2135",
    "addr:housenumber":"11",
    "addr:postcode":"2135",
    "addr:street":"The Boulevarde",
    "iso:country":"AU",
    "sg:address":"Suite 2, Level 4, 11 The Boulevarde",
    "sg:city":"Strathfield",
    "sg:classifiers":[
        {
            "category":"Professional",
            "subcategory":"Employment Agencies",
            "type":"Services"
        }
    ],
    "sg:phone":"+61 2 8746 0711",
    "sg:postcode":"2135",
    "sg:province":"NSW",
    "wof:name":"Job Futures",
    "wof:placetype":"venue"
},
  "geometry": {"coordinates":[151.09405517600001,-33.873210907],"type":"Point"}
}