{
  "type": "Feature",
  "properties": {
    "iso:country":"AU",
    "sg:address":"Shop 1 West St",
    "sg:city":"Bega North",
    "sg:classifiers":[
        {
            "category":"Building & Trades",
            "subcategory":"Electrical",
            "type":"Services"
        }
    ],
    "sg:phone":"+61 2 6492 0555",
    "sg:postcode":"2550",
    "sg:province":"NSW",
    "sg:tags":[
        "repair",
        "generator",
        "electric",
        "motor"
    ],
    "wof:name":"Michael's Auto Electrics & Motor Rewind",
    "wof:placetype":"venue"
},
  "geometry": {"coordinates":[149.82539367699999,-36.6628189087],"type":"Point"}
}