{
  "type": "Feature",
  "properties": {
    "addr:full":"19 Toxteth Rd Glebe NSW 2037",
    "addr:housenumber":"19",
    "addr:postcode":"2037",
    "addr:street":"Toxteth Rd",
    "iso:country":"AU",
    "sg:address":"19 Toxteth Rd",
    "sg:city":"Glebe",
    "sg:classifiers":[
        {
            "category":"Social Services",
            "subcategory":"Child Care",
            "type":"Services"
        }
    ],
    "sg:phone":"+61 2 9660 6001",
    "sg:postcode":"2037",
    "sg:province":"NSW",
    "wof:name":"Glebe Uniting Church Toxteth Road Kindergarten",
    "wof:placetype":"venue"
},
  "geometry": {"coordinates":[151.181716919,-33.8770904541],"type":"Point"}
}