{
  "type": "Feature",
  "properties": {
    "addr:full":"Cnr Swan & Burnley Sts Richmond VIC 3121",
    "addr:postcode":"3121",
    "addr:street":"Cnr",
    "iso:country":"AU",
    "sg:address":"Cnr Swan & Burnley Sts",
    "sg:city":"Richmond",
    "sg:classifiers":[
        {
            "category":"Wholesale",
            "subcategory":"Construction Materials",
            "type":"Manufacturing & Wholesale Goods"
        }
    ],
    "sg:phone":"+61 3 9428 3622",
    "sg:postcode":"3121",
    "sg:province":"VIC",
    "sg:tags":[
        "wholesaler",
        "equipment",
        "bathroom",
        "mfrs",
        "accessory"
    ],
    "wof:name":"A.Timber Mirror Centre",
    "wof:placetype":"venue"
},
  "geometry": {"coordinates":[144.99760437,-37.8256263733],"type":"Point"}
}