{
  "type": "Feature",
  "properties": {
    "iso:country":"AU",
    "sg:address":"72a Doncaster Rd",
    "sg:city":"Balwyn North",
    "sg:classifiers":[
        {
            "category":"Real Estate",
            "subcategory":"Real Estate Agent",
            "type":"Services"
        }
    ],
    "sg:phone":"+61 3 9859 9517",
    "sg:postcode":"3104",
    "sg:province":"VIC",
    "wof:name":"Eggers Robert Real Estate",
    "wof:placetype":"venue"
},
  "geometry": {"coordinates":[145.071502686,-37.7928733826],"type":"Point"}
}