{
  "type": "Feature",
  "properties": {
    "addr:full":"Lvl 1, 58 Norman St Gordonvale QLD 4865",
    "addr:housenumber":"58",
    "addr:postcode":"4865",
    "addr:street":"Norman St",
    "iso:country":"AU",
    "sg:address":"Lvl 1, 58 Norman St",
    "sg:city":"Gordonvale",
    "sg:classifiers":[
        {
            "category":"Professional",
            "subcategory":"Accounting & Tax Preparation",
            "type":"Services"
        }
    ],
    "sg:phone":"+61 7 4056 1583",
    "sg:postcode":"4865",
    "sg:province":"QLD",
    "sg:tags":[
        "accountant",
        "auditor"
    ],
    "wof:name":"Gary Wilkins CPA",
    "wof:placetype":"venue"
},
  "geometry": {"coordinates":[145.76878356899999,-17.1179885864],"type":"Point"}
}