{
  "type": "Feature",
  "properties": {
    "addr:full":"208 Lt Collins St Melbourne VIC 3000",
    "addr:housenumber":"208",
    "addr:postcode":"3000",
    "addr:street":"Lt Collins St",
    "iso:country":"AU",
    "sg:address":"208 Lt Collins St",
    "sg:city":"Melbourne",
    "sg:classifiers":[
        {
            "category":"Shopping",
            "subcategory":"Jewelry",
            "type":"Retail Goods"
        }
    ],
    "sg:phone":"+61 3 9654 1858",
    "sg:postcode":"3000",
    "sg:province":"VIC",
    "sg:tags":[
        "jeweller"
    ],
    "wof:name":"Rochis Opals",
    "wof:placetype":"venue"
},
  "geometry": {"coordinates":[144.96519470199999,-37.8157424927],"type":"Point"}
}