{
  "type": "Feature",
  "properties": {
    "addr:full":"PO Box 4 Williamstown VIC 3016",
    "addr:postcode":"3016",
    "iso:country":"AU",
    "sg:address":"PO Box 4",
    "sg:city":"Williamstown",
    "sg:classifiers":[
        {
            "category":"Government",
            "subcategory":"Customs House",
            "type":"Public Place"
        }
    ],
    "sg:phone":"+61 3 8310 8399",
    "sg:postcode":"3016",
    "sg:province":"VIC",
    "sg:tags":[
        "title",
        "management",
        "stratum"
    ],
    "wof:name":"Ace Body Corporate Management - Footscray/Williamstown",
    "wof:placetype":"venue"
},
  "geometry": {"coordinates":[144.902587891,-37.8615112305],"type":"Point"}
}