{
  "type": "Feature",
  "properties": {
    "addr:full":"351 Beardy St Armidale NSW 2350",
    "addr:housenumber":"351",
    "addr:postcode":"2350",
    "addr:street":"Beardy St",
    "iso:country":"AU",
    "sg:address":"351 Beardy St",
    "sg:city":"Armidale",
    "sg:classifiers":[
        {
            "category":"Banks & Credit Unions",
            "subcategory":"Investment Brokerage",
            "type":"Services"
        }
    ],
    "sg:phone":"+61 2 6771 2940",
    "sg:postcode":"2350",
    "sg:province":"NSW",
    "sg:tags":[
        "radiator",
        "motor"
    ],
    "wof:name":"I.C.E Radiator Repair Centres",
    "wof:placetype":"venue"
},
  "geometry": {"coordinates":[151.647613525,-30.508058548],"type":"Point"}
}