{
  "type": "Feature",
  "properties": {
    "iso:country":"AU",
    "sg:address":"11- 15 Douro St",
    "sg:city":"Geelong North",
    "sg:classifiers":[
        {
            "category":"Taxi",
            "type":"Transportation"
        }
    ],
    "sg:phone":"+61 3 5278 9456",
    "sg:postcode":"3215",
    "sg:province":"VIC",
    "sg:tags":[
        "cab"
    ],
    "wof:name":"Murrell Chauffeur Drive",
    "wof:placetype":"venue"
},
  "geometry": {"coordinates":[144.34776306099999,-38.1212882996],"type":"Point"}
}