{
  "type": "Feature",
  "properties": {
    "addr:full":"Claremont Arcade, Shop 8, ST Quentins Ave Claremont WA 6010",
    "addr:housenumber":"8",
    "addr:postcode":"6010",
    "addr:street":"St Quentins Ave",
    "iso:country":"AU",
    "sg:address":"Claremont Arcade, Shop 8, ST Quentins Ave",
    "sg:city":"Claremont",
    "sg:classifiers":[
        {
            "category":"Shopping",
            "subcategory":"Clothing, Apparel, & Fashions",
            "type":"Retail Goods"
        }
    ],
    "sg:phone":"+61 8 9384 1688",
    "sg:postcode":"6010",
    "sg:province":"WA",
    "sg:tags":[
        "lady",
        "wear"
    ],
    "wof:name":"Simona",
    "wof:placetype":"venue"
},
  "geometry": {"coordinates":[115.78109741199999,-31.9823303223],"type":"Point"}
}