{
  "type": "Feature",
  "properties": {
    "addr:full":"Shop 33 Livingston Marketplace Shopping Ctr Canning Vale WA 6155",
    "addr:housenumber":"shop 33",
    "addr:postcode":"6155",
    "addr:street":"Shopping Ctr",
    "iso:country":"AU",
    "sg:address":"Shop 33 Livingston Marketplace Shopping Ctr",
    "sg:city":"Canning Vale",
    "sg:classifiers":[
        {
            "category":"Health Services",
            "subcategory":"Optometrist",
            "type":"Services"
        }
    ],
    "sg:phone":"+61 8 9456 5560",
    "sg:postcode":"6155",
    "sg:province":"WA",
    "wof:name":"Livingston Optical",
    "wof:placetype":"venue"
},
  "geometry": {"coordinates":[115.92858099999999,-32.080261],"type":"Point"}
}