{
  "type": "Feature",
  "properties": {
    "addr:full":"6 Mernda Ave Ashburton VIC 3147",
    "addr:housenumber":"6",
    "addr:postcode":"3147",
    "addr:street":"Mernda Ave",
    "iso:country":"AU",
    "sg:address":"6 Mernda Ave",
    "sg:city":"Ashburton",
    "sg:classifiers":[
        {
            "category":"Banks & Credit Unions",
            "subcategory":"Financial Services",
            "type":"Services"
        }
    ],
    "sg:phone":"+61 3 9885 0289",
    "sg:postcode":"3147",
    "sg:province":"VIC",
    "sg:tags":[
        "planning"
    ],
    "wof:name":"Glenmar Financial Services",
    "wof:placetype":"venue"
},
  "geometry": {"coordinates":[145.09088134800001,-37.8623199463],"type":"Point"}
}