{
  "type": "Feature",
  "properties": {
    "iso:country":"AU",
    "sg:address":"26 Dover St",
    "sg:city":"Caulfield South",
    "sg:classifiers":[
        {
            "category":"Wholesale",
            "subcategory":"Drugs",
            "type":"Manufacturing & Wholesale Goods"
        }
    ],
    "sg:phone":"+61 3 9528 2615",
    "sg:postcode":"3162",
    "sg:province":"VIC",
    "sg:tags":[
        "wholesaler",
        "pharmaceutical",
        "product",
        "mfrs"
    ],
    "wof:name":"Redlands Veterinary Products",
    "wof:placetype":"venue"
},
  "geometry": {"coordinates":[145.02322387699999,-37.8953895569],"type":"Point"}
}