{
  "type": "Feature",
  "properties": {
    "addr:full":"76 Main St Alstonville NSW 2477",
    "addr:housenumber":"76",
    "addr:postcode":"2477",
    "addr:street":"Main St",
    "iso:country":"AU",
    "sg:address":"76 Main St",
    "sg:city":"Alstonville",
    "sg:classifiers":[
        {
            "category":"Personal",
            "subcategory":"Hair Removal",
            "type":"Services"
        }
    ],
    "sg:phone":"+61 2 6628 5877",
    "sg:postcode":"2477",
    "sg:province":"NSW",
    "wof:name":"Alstonville Rejuvenation Beauty & Skin Care Centre",
    "wof:placetype":"venue"
},
  "geometry": {"coordinates":[153.435943603,-28.8380184174],"type":"Point"}
}