{
  "type": "Feature",
  "properties": {
    "addr:full":"16a Prescott Crs Gawler Belt SA 5118",
    "addr:housenumber":"16a",
    "addr:postcode":"5118",
    "addr:street":"Prescott Crs",
    "iso:country":"AU",
    "sg:address":"16a Prescott Crs",
    "sg:city":"Gawler Belt",
    "sg:classifiers":[
        {
            "category":"Retail",
            "subcategory":"Auto Repair",
            "type":"Services"
        }
    ],
    "sg:phone":"+61 8 8522 4433",
    "sg:postcode":"5118",
    "sg:province":"SA",
    "sg:tags":[
        "beater",
        "painter",
        "panel"
    ],
    "wof:name":"David Adler Spray Painting",
    "wof:placetype":"venue"
},
  "geometry": {"coordinates":[138.73547400000001,-34.574772],"type":"Point"}
}