{
  "type": "Feature",
  "properties": {
    "iso:country":"AU",
    "sg:address":"69a Reynolds Rd",
    "sg:city":"Mt Pleasant",
    "sg:classifiers":[
        {
            "category":"Real Estate",
            "subcategory":"Real Estate Agent",
            "type":"Services"
        }
    ],
    "sg:phone":"+61 8 9364 3294",
    "sg:postcode":"6153",
    "sg:province":"WA",
    "wof:name":"Lister Estate Agency",
    "wof:placetype":"venue"
},
  "geometry": {"coordinates":[115.84863300000001,-32.025822],"type":"Point"}
}