{
  "type": "Feature",
  "properties": {
    "addr:full":"Parkes Rd Condobolin NSW 2877",
    "addr:postcode":"2877",
    "addr:street":"Parkes Rd",
    "iso:country":"AU",
    "sg:address":"Parkes Rd",
    "sg:city":"Condobolin",
    "sg:classifiers":[
        {
            "category":"Retail",
            "subcategory":"Auto Repair",
            "type":"Services"
        }
    ],
    "sg:phone":"+61 2 6895 2787",
    "sg:postcode":"2877",
    "sg:province":"NSW",
    "sg:tags":[
        "beater",
        "painter",
        "panel"
    ],
    "wof:name":"Bell Ian Smash Repairs",
    "wof:placetype":"venue"
},
  "geometry": {"coordinates":[147.15901199999999,-33.082634],"type":"Point"}
}