{
  "type": "Feature",
  "properties": {
    "addr:full":"102 Maryborough St Bundaberg QLD 4670",
    "addr:housenumber":"102",
    "addr:postcode":"4670",
    "addr:street":"Maryborough St",
    "iso:country":"AU",
    "sg:address":"102 Maryborough St",
    "sg:city":"Bundaberg",
    "sg:classifiers":[
        {
            "category":"Insurance",
            "subcategory":"Insurance Agent",
            "type":"Services"
        }
    ],
    "sg:phone":"+61 1300 766 866",
    "sg:postcode":"4670",
    "sg:province":"QLD",
    "sg:tags":[
        "broker"
    ],
    "wof:name":"Seamac Insurance Brokers Pty Ltd",
    "wof:placetype":"venue"
},
  "geometry": {"coordinates":[152.352783203,-24.8848152161],"type":"Point"}
}