{
  "type": "Feature",
  "properties": {
    "addr:full":"4/ 40 Reginald St Rocklea QLD 4106",
    "addr:housenumber":"/ 40",
    "addr:postcode":"4106",
    "addr:street":"Reginald St",
    "iso:country":"AU",
    "sg:address":"4/ 40 Reginald St",
    "sg:city":"Rocklea",
    "sg:classifiers":[
        {
            "category":"Professional",
            "type":"Services"
        }
    ],
    "sg:phone":"+61 7 3373 8840",
    "sg:postcode":"4106",
    "sg:province":"QLD",
    "sg:tags":[
        "transport"
    ],
    "wof:name":"Jarratt Transport",
    "wof:placetype":"venue"
},
  "geometry": {"coordinates":[152.996856689,-27.5629463196],"type":"Point"}
}