{
  "type": "Feature",
  "properties": {
    "iso:country":"AU",
    "sg:address":"336 Railway Pde",
    "sg:city":"Carlton",
    "sg:classifiers":[
        {
            "category":"Shopping",
            "subcategory":"Clothing, Apparel, & Fashions",
            "type":"Retail Goods"
        }
    ],
    "sg:phone":"+61 2 9553 7766",
    "sg:postcode":"2218",
    "sg:province":"NSW",
    "sg:tags":[
        "maternity",
        "wear"
    ],
    "wof:name":"Curves With Love",
    "wof:placetype":"venue"
},
  "geometry": {"coordinates":[151.12321499999999,-33.968887],"type":"Point"}
}