{
  "type": "Feature",
  "properties": {
    "iso:country":"AU",
    "sg:address":"942 Old Northern Rd",
    "sg:city":"Glenorie",
    "sg:classifiers":[
        {
            "category":"Home & Garden",
            "subcategory":"Home Furnishings",
            "type":"Retail Goods"
        }
    ],
    "sg:phone":"+61 2 9652 0552",
    "sg:postcode":"2157",
    "sg:province":"NSW",
    "sg:tags":[
        "candle"
    ],
    "wof:name":"Flametree",
    "wof:placetype":"venue"
},
  "geometry": {"coordinates":[151.00721740700001,-33.6010704041],"type":"Point"}
}