{
  "type": "Feature",
  "properties": {
    "iso:country":"AU",
    "sg:address":"67 Wanganella St",
    "sg:city":"Balgowlah",
    "sg:classifiers":[
        {
            "category":"Health Services",
            "subcategory":"Doctor",
            "type":"Services"
        }
    ],
    "sg:phone":"+61 2 9949 5855",
    "sg:postcode":"2093",
    "sg:province":"NSW",
    "sg:tags":[
        "medical",
        "practitioner"
    ],
    "wof:name":"Matthews Charles",
    "wof:placetype":"venue"
},
  "geometry": {"coordinates":[151.25785827600001,-33.7943496704],"type":"Point"}
}