{
  "type": "Feature",
  "properties": {
    "iso:country":"AU",
    "sg:address":"66 Lr Heidelberg Rd",
    "sg:city":"Ivanhoe",
    "sg:classifiers":[
        {
            "category":"Shopping",
            "subcategory":"Bicycles & Sporting Goods",
            "type":"Retail Goods"
        }
    ],
    "sg:phone":"+61 3 9497 3077",
    "sg:postcode":"3079",
    "sg:province":"VIC",
    "sg:tags":[
        "chemical",
        "equipment",
        "pool",
        "swimming"
    ],
    "wof:name":"Jeanie's Pool & Spa Shop",
    "wof:placetype":"venue"
},
  "geometry": {"coordinates":[145.04609680199999,-37.7719535828],"type":"Point"}
}