{
  "type": "Feature",
  "properties": {
    "addr:full":"5 Woodville La North Perth WA 6006",
    "addr:housenumber":"5",
    "addr:postcode":"6006",
    "addr:street":"Woodville La",
    "iso:country":"AU",
    "sg:address":"5 Woodville La",
    "sg:city":"North Perth",
    "sg:classifiers":[
        {
            "category":"Shopping",
            "subcategory":"Jewelry",
            "type":"Retail Goods"
        }
    ],
    "sg:phone":"+61 3 9328 5255",
    "sg:postcode":"6006",
    "sg:province":"WA",
    "sg:tags":[
        "jeweller"
    ],
    "wof:name":"Jewellery By Design",
    "wof:placetype":"venue"
},
  "geometry": {"coordinates":[115.857810974,-31.930316925],"type":"Point"}
}