{
  "type": "Feature",
  "properties": {
    "iso:country":"AU",
    "sg:address":"22 Tain St",
    "sg:city":"Applecross",
    "sg:classifiers":[
        {
            "category":"Building & Trades",
            "subcategory":"Construction",
            "type":"Services"
        }
    ],
    "sg:phone":"+61 8 9315 5881",
    "sg:postcode":"6153",
    "sg:province":"WA",
    "sg:tags":[
        "contractor"
    ],
    "wof:name":"Artistic Homes",
    "wof:placetype":"venue"
},
  "geometry": {"coordinates":[115.834862,-32.014877],"type":"Point"}
}