{
  "type": "Feature",
  "properties": {
    "iso:country":"AU",
    "sg:address":"208 Boneo Rd",
    "sg:city":"Rosebud",
    "sg:classifiers":[
        {
            "category":"Retail",
            "subcategory":"Storage",
            "type":"Services"
        }
    ],
    "sg:phone":"+61 3 5982 0411",
    "sg:postcode":"3939",
    "sg:province":"VIC",
    "wof:name":"Boat Storage-Peninsula Undercover",
    "wof:placetype":"venue"
},
  "geometry": {"coordinates":[144.88873290999999,-38.3814086914],"type":"Point"}
}