{
  "type": "Feature",
  "properties": {
    "addr:full":"2 Stuart St Manly NSW 2095",
    "addr:housenumber":"2",
    "addr:postcode":"2095",
    "addr:street":"Stuart St",
    "iso:country":"AU",
    "sg:address":"2 Stuart St",
    "sg:city":"Manly",
    "sg:classifiers":[
        {
            "category":"Professional",
            "subcategory":"Management & Consulting",
            "type":"Services"
        }
    ],
    "sg:phone":"+61 2 9977 1690",
    "sg:postcode":"2095",
    "sg:province":"NSW",
    "sg:tags":[
        "consultant",
        "industrial",
        "relation"
    ],
    "wof:name":"Roff David C",
    "wof:placetype":"venue"
},
  "geometry": {"coordinates":[151.28529357900001,-33.803981781],"type":"Point"}
}