{
  "type": "Feature",
  "properties": {
    "iso:country":"AU",
    "sg:address":"Shop 12, 216 Farnham Rd",
    "sg:city":"Shopping Village Quakers Hill",
    "sg:classifiers":[
        {
            "category":"Real Estate",
            "subcategory":"Real Estate Agent",
            "type":"Services"
        }
    ],
    "sg:phone":"+61 2 9626 3333",
    "sg:postcode":"2763",
    "sg:province":"NSW",
    "wof:name":"Costigan Hills Real Estate",
    "wof:placetype":"venue"
},
  "geometry": {"coordinates":[150.89570617699999,-33.7231521606],"type":"Point"}
}