{
  "type": "Feature",
  "properties": {
    "addr:full":"2387 Gold Coast Hwy Mermaid Beach QLD 4218",
    "addr:housenumber":"2387",
    "addr:postcode":"4218",
    "addr:street":"Gold Coast Hwy",
    "iso:country":"AU",
    "sg:address":"2387 Gold Coast Hwy",
    "sg:city":"Mermaid Beach",
    "sg:classifiers":[
        {
            "category":"Shopping",
            "subcategory":"Clothing, Apparel, & Fashions",
            "type":"Retail Goods"
        }
    ],
    "sg:phone":"+61 7 5572 2075",
    "sg:postcode":"4218",
    "sg:province":"QLD",
    "sg:tags":[
        "recycled",
        "clothing"
    ],
    "wof:name":"Change Gear Pre-Loved Fashions",
    "wof:placetype":"venue"
},
  "geometry": {"coordinates":[153.436309814,-28.0495510101],"type":"Point"}
}