{
  "type": "Feature",
  "properties": {
    "iso:country":"AU",
    "sg:address":"Bogangar Bowling Club, Cabarita Rd",
    "sg:city":"Bogangar",
    "sg:classifiers":[
        {
            "category":"Fast Food",
            "type":"Food & Drink"
        }
    ],
    "sg:phone":"+61 2 6676 1701",
    "sg:postcode":"2488",
    "sg:province":"NSW",
    "sg:tags":[
        "away",
        "take"
    ],
    "wof:name":"Bogangar Happy Valley",
    "wof:placetype":"venue"
},
  "geometry": {"coordinates":[153.564835,-28.332355],"type":"Point"}
}