{
  "type": "Feature",
  "properties": {
    "addr:full":"91 Scarborough St Southport QLD 4215",
    "addr:housenumber":"91",
    "addr:postcode":"4215",
    "addr:street":"Scarborough St",
    "iso:country":"AU",
    "sg:address":"91 Scarborough St",
    "sg:city":"Southport",
    "sg:classifiers":[
        {
            "category":"Parking",
            "type":"Transportation"
        }
    ],
    "sg:phone":"+61 7 5531 4625",
    "sg:postcode":"4215",
    "sg:province":"QLD",
    "wof:name":"Care Park",
    "wof:placetype":"venue"
},
  "geometry": {"coordinates":[153.41368102999999,-27.9663238525],"type":"Point"}
}