{
  "type": "Feature",
  "properties": {
    "addr:full":"Far Northern End Of Hanson Rd Wingfield SA 5013",
    "addr:postcode":"5013",
    "addr:street":"Hanson Rd",
    "iso:country":"AU",
    "sg:address":"Far Northern End Of Hanson Rd",
    "sg:city":"Wingfield",
    "sg:classifiers":[
        {
            "category":"Utilities",
            "subcategory":"Recycling",
            "type":"Services"
        }
    ],
    "sg:phone":"+61 8 8244 8156",
    "sg:postcode":"5013",
    "sg:province":"SA",
    "wof:name":"Adelaide Resource Recovery",
    "wof:placetype":"venue"
},
  "geometry": {"coordinates":[138.56442260700001,-34.8483886719],"type":"Point"}
}