{
  "type": "Feature",
  "properties": {
    "addr:full":"36 Main Rd Lobethal SA 5241",
    "addr:housenumber":"36",
    "addr:postcode":"5241",
    "addr:street":"Main Rd",
    "iso:country":"AU",
    "sg:address":"36 Main Rd",
    "sg:city":"Lobethal",
    "sg:classifiers":[
        {
            "category":"Organizations",
            "subcategory":"Community Association",
            "type":"Services"
        }
    ],
    "sg:phone":"+61 8 8389 6734",
    "sg:postcode":"5241",
    "sg:province":"SA",
    "sg:tags":[
        "club",
        "senior",
        "citizen"
    ],
    "wof:name":"Onkaparinga Senior Citizens Centre",
    "wof:placetype":"venue"
},
  "geometry": {"coordinates":[138.874603272,-34.9051475525],"type":"Point"}
}