{
  "type": "Feature",
  "properties": {
    "addr:full":"12 Grimsdyke Crt Molendinar QLD 4214",
    "addr:housenumber":"12",
    "addr:postcode":"4214",
    "addr:street":"Grimsdyke Crt",
    "iso:country":"AU",
    "sg:address":"12 Grimsdyke Crt",
    "sg:city":"Molendinar",
    "sg:classifiers":[
        {
            "category":"Building & Trades",
            "subcategory":"Plumbing",
            "type":"Services"
        }
    ],
    "sg:phone":"+61 7 5539 6918",
    "sg:postcode":"4214",
    "sg:province":"QLD",
    "sg:tags":[
        "plumber",
        "gasfitters"
    ],
    "wof:name":"Wizard Plumbing",
    "wof:placetype":"venue"
},
  "geometry": {"coordinates":[153.36305236800001,-27.9727458954],"type":"Point"}
}