{
  "type": "Feature",
  "properties": {
    "addr:full":"65 Princes Hwy Batemans Bay NSW 2536",
    "addr:housenumber":"65",
    "addr:postcode":"2536",
    "addr:street":"Princes Hwy",
    "iso:country":"AU",
    "sg:address":"65 Princes Hwy",
    "sg:city":"Batemans Bay",
    "sg:classifiers":[
        {
            "category":"Autos & Motor Vehicles",
            "subcategory":"Auto Supplies",
            "type":"Retail Goods"
        }
    ],
    "sg:phone":"+61 2 4472 5051",
    "sg:postcode":"2536",
    "sg:province":"NSW",
    "sg:tags":[
        "tyre"
    ],
    "wof:name":"Batemans Bay Tyres - Shortys",
    "wof:placetype":"venue"
},
  "geometry": {"coordinates":[150.17665100100001,-35.7177276611],"type":"Point"}
}