{
  "type": "Feature",
  "properties": {
    "addr:full":"27 - 29 Canberra Ave Dandenong South VIC 3175",
    "addr:housenumber":"29",
    "addr:postcode":"3175",
    "addr:street":"Canberra Ave",
    "iso:country":"AU",
    "sg:address":"27 - 29 Canberra Ave",
    "sg:city":"Dandenong South",
    "sg:classifiers":[
        {
            "category":"Social Services",
            "subcategory":"Child Care",
            "type":"Services"
        }
    ],
    "sg:phone":"+61 3 9791 2272",
    "sg:postcode":"3175",
    "sg:province":"VIC",
    "wof:name":"Canberra Avenue Child Care",
    "wof:placetype":"venue"
},
  "geometry": {"coordinates":[145.207687378,-37.9970016479],"type":"Point"}
}