{
  "type": "Feature",
  "properties": {
    "addr:full":"4/ 11 Aruma Cl Cardiff NSW 2285",
    "addr:housenumber":"/ 11",
    "addr:postcode":"2285",
    "addr:street":"Aruma Cl",
    "iso:country":"AU",
    "sg:address":"4/ 11",
    "sg:city":"Aruma Cl Cardiff",
    "sg:classifiers":[
        {
            "category":"Government",
            "subcategory":"Department Of Motor Vehicles",
            "type":"Public Place"
        }
    ],
    "sg:phone":"+61 2 4954 4422",
    "sg:postcode":"2285",
    "sg:province":"NSW",
    "sg:tags":[
        "wholesaler",
        "mfrs",
        "accessory"
    ],
    "wof:name":"Automotive Trade parts Centre",
    "wof:placetype":"venue"
},
  "geometry": {"coordinates":[151.63911438,-32.9419784546],"type":"Point"}
}