{
  "type": "Feature",
  "properties": {
    "addr:full":"Lot 4 301 Blackall Range Rd Woombye QLD 4559",
    "addr:housenumber":"301",
    "addr:postcode":"4559",
    "addr:street":"Blackall Range Rd",
    "iso:country":"AU",
    "sg:address":"Lot 4 301 Blackall Range Rd",
    "sg:city":"Woombye",
    "sg:classifiers":[
        {
            "category":"Building & Trades",
            "subcategory":"Construction",
            "type":"Services"
        }
    ],
    "sg:phone":"+61 7 5442 3303",
    "sg:postcode":"4559",
    "sg:province":"QLD",
    "sg:tags":[
        "earth",
        "excavating",
        "moving",
        "contractor"
    ],
    "wof:name":"Suncoast Diggers",
    "wof:placetype":"venue"
},
  "geometry": {"coordinates":[152.93748474099999,-26.6643848419],"type":"Point"}
}