{
  "type": "Feature",
  "properties": {
    "addr:full":"6 Mann St Mt Barker SA 5251",
    "addr:housenumber":"6",
    "addr:postcode":"5251",
    "addr:street":"Mann St Mt",
    "iso:country":"AU",
    "sg:address":"6 Mann St",
    "sg:city":"Mt Barker",
    "sg:classifiers":[
        {
            "category":"Banks & Credit Unions",
            "subcategory":"Investment Brokerage",
            "type":"Services"
        }
    ],
    "sg:phone":"+61 8 8391 5921",
    "sg:postcode":"5251",
    "sg:province":"SA",
    "sg:tags":[
        "finance",
        "broker"
    ],
    "wof:name":"Preferred Finance",
    "wof:placetype":"venue"
},
  "geometry": {"coordinates":[138.86166381800001,-35.0664863586],"type":"Point"}
}