{
  "type": "Feature",
  "properties": {
    "addr:full":"32 Sutton St Mandurah WA 6210",
    "addr:housenumber":"32",
    "addr:postcode":"6210",
    "addr:street":"Sutton St",
    "iso:country":"AU",
    "sg:address":"32 Sutton St",
    "sg:city":"Mandurah",
    "sg:classifiers":[
        {
            "category":"Organizations",
            "subcategory":"Professional Association",
            "type":"Services"
        }
    ],
    "sg:phone":"+61 8 9535 4338",
    "sg:postcode":"6210",
    "sg:province":"WA",
    "sg:tags":[
        "web",
        "internet"
    ],
    "sg:website":"http://www.jobtech.com.au",
    "wof:name":"Jobtech",
    "wof:placetype":"venue"
},
  "geometry": {"coordinates":[115.72277099999999,-32.530827],"type":"Point"}
}