{
  "type": "Feature",
  "properties": {
    "addr:full":"PO Box 539 Haberfield NSW 2045",
    "addr:postcode":"2045",
    "iso:country":"AU",
    "sg:address":"PO Box 539",
    "sg:city":"Haberfield",
    "sg:classifiers":[
        {
            "category":"Utilities",
            "subcategory":"Refuse",
            "type":"Services"
        }
    ],
    "sg:phone":"+61 425 220 946",
    "sg:postcode":"2045",
    "sg:province":"NSW",
    "sg:tags":[
        "remover",
        "rubbish"
    ],
    "wof:name":"What A Load Of Garbage",
    "wof:placetype":"venue"
},
  "geometry": {"coordinates":[151.13926699999999,-33.881031],"type":"Point"}
}