{
  "type": "Feature",
  "properties": {
    "iso:country":"AU",
    "sg:address":"PO Box 1652",
    "sg:city":"Coorparoo",
    "sg:classifiers":[
        {
            "category":"Professional",
            "subcategory":"Accounting & Tax Preparation",
            "type":"Services"
        }
    ],
    "sg:phone":"+61 409 547 574",
    "sg:postcode":"4151",
    "sg:province":"QLD",
    "sg:tags":[
        "bookkeeping"
    ],
    "wof:name":"On The Move Accounting Services",
    "wof:placetype":"venue"
},
  "geometry": {"coordinates":[153.061645508,-27.4981002808],"type":"Point"}
}