{
  "type": "Feature",
  "properties": {
    "addr:full":"356 Middleton Rd Albany WA 6330",
    "addr:housenumber":"356",
    "addr:postcode":"6330",
    "addr:street":"Middleton Rd",
    "iso:country":"AU",
    "sg:address":"356 Middleton Rd",
    "sg:city":"Albany",
    "sg:classifiers":[
        {
            "category":"Personal",
            "subcategory":"Beauty Salon",
            "type":"Services"
        }
    ],
    "sg:phone":"+61 8 9841 7677",
    "sg:postcode":"6330",
    "sg:province":"WA",
    "sg:tags":[
        "hairdresser"
    ],
    "wof:name":"Tangles Hair Studio",
    "wof:placetype":"venue"
},
  "geometry": {"coordinates":[117.88432312,-35.0201568604],"type":"Point"}
}