{
  "type": "Feature",
  "properties": {
    "addr:full":"Lot 32 Oyster Drv Cowell SA 5602",
    "addr:postcode":"5602",
    "addr:street":"Oyster Drv",
    "iso:country":"AU",
    "sg:address":"Lot 32 Oyster Drv",
    "sg:city":"Cowell",
    "sg:classifiers":[
        {
            "category":"Farming",
            "subcategory":"Fish & Marine Products",
            "type":"Manufacturing & Wholesale Goods"
        }
    ],
    "sg:phone":"+61 8 8629 2550",
    "sg:postcode":"5602",
    "sg:province":"SA",
    "sg:tags":[
        "supplier",
        "oyster",
        "farmer"
    ],
    "wof:name":"Oysters Amalgamated",
    "wof:placetype":"venue"
},
  "geometry": {"coordinates":[136.926636,-33.67585],"type":"Point"}
}