{
  "type": "Feature",
  "properties": {
    "iso:country":"AU",
    "sg:address":"Victor St",
    "sg:city":"Banyo",
    "sg:classifiers":[
        {
            "category":"Education",
            "subcategory":"School",
            "type":"Public Place"
        }
    ],
    "sg:phone":"+61 7 3621 7409",
    "sg:postcode":"4014",
    "sg:province":"QLD",
    "sg:tags":[
        "state",
        "except",
        "nsw"
    ],
    "wof:name":"Earnshaw State College Preschool",
    "wof:placetype":"venue"
},
  "geometry": {"coordinates":[153.079055786,-27.3755264282],"type":"Point"}
}