{
  "type": "Feature",
  "properties": {
    "addr:full":"Suite 12/ 14 Garden Blv Dingley VIC 3172",
    "addr:housenumber":"12 / 14",
    "addr:postcode":"3172",
    "addr:street":"Garden Blv",
    "iso:country":"AU",
    "sg:address":"Suite 12/ 14",
    "sg:city":"Garden Blv Dingley",
    "sg:classifiers":[
        {
            "category":"Banks & Credit Unions",
            "subcategory":"Financial Services",
            "type":"Services"
        }
    ],
    "sg:phone":"+61 3 9551 2822",
    "sg:postcode":"3172",
    "sg:province":"VIC",
    "sg:tags":[
        "annuity",
        "rollover",
        "superannuation",
        "consultant"
    ],
    "wof:name":"Focus Financial Planning Pty Ltd",
    "wof:placetype":"venue"
},
  "geometry": {"coordinates":[145.113967895,-37.9811019897],"type":"Point"}
}