{
  "type": "Feature",
  "properties": {
    "iso:country":"AU",
    "sg:address":"Government Rd",
    "sg:city":"Belalie",
    "sg:classifiers":[
        {
            "category":"Manufacturing",
            "subcategory":"Pottery",
            "type":"Manufacturing & Wholesale Goods"
        }
    ],
    "sg:phone":"+61 8 8665 2002",
    "sg:postcode":"5491",
    "sg:province":"SA",
    "wof:name":"Old Belalie Farm House",
    "wof:placetype":"venue"
},
  "geometry": {"coordinates":[138.652877808,-33.2207527161],"type":"Point"}
}