{
  "type": "Feature",
  "properties": {
    "addr:full":"Lvl8/ 10 Felix St Brisbane QLD 4000",
    "addr:postcode":"4000",
    "addr:street":"Felix St",
    "iso:country":"AU",
    "sg:address":"Lvl8/ 10 Felix St",
    "sg:city":"Brisbane",
    "sg:classifiers":[
        {
            "category":"Professional",
            "subcategory":"Management & Consulting",
            "type":"Services"
        }
    ],
    "sg:phone":"+61 7 3227 9500",
    "sg:postcode":"4000",
    "sg:province":"QLD",
    "sg:tags":[
        "consultant",
        "economic"
    ],
    "wof:name":"Synergies Economic Consulting Pty Ltd",
    "wof:placetype":"venue"
},
  "geometry": {"coordinates":[153.03036499000001,-27.4709243774],"type":"Point"}
}