{
  "type": "Feature",
  "properties": {
    "addr:full":"164 Bridge Rd Richmond VIC 3121",
    "addr:housenumber":"164",
    "addr:postcode":"3121",
    "addr:street":"Bridge Rd",
    "iso:country":"AU",
    "sg:address":"164 Bridge Rd",
    "sg:city":"Richmond",
    "sg:classifiers":[
        {
            "category":"Shopping",
            "subcategory":"Clothing, Apparel, & Fashions",
            "type":"Retail Goods"
        }
    ],
    "sg:phone":"+61 3 9428 6433",
    "sg:postcode":"3121",
    "sg:province":"VIC",
    "sg:tags":[
        "lady",
        "wear"
    ],
    "wof:name":"Roxanne Fashions",
    "wof:placetype":"venue"
},
  "geometry": {"coordinates":[144.995925903,-37.8183403015],"type":"Point"}
}