{
  "type": "Feature",
  "properties": {
    "iso:country":"AU",
    "sg:address":"8 Jarrett St",
    "sg:city":"Innaloo",
    "sg:classifiers":[
        {
            "category":"Social Services",
            "subcategory":"Retirement Home",
            "type":"Services"
        }
    ],
    "sg:phone":"+61 8 9242 8777",
    "sg:postcode":"6018",
    "sg:province":"WA",
    "sg:tags":[
        "environmental",
        "consultant",
        "pollution"
    ],
    "wof:name":"Acid Soil Water & Waste Management Pty Ltd",
    "wof:placetype":"venue"
},
  "geometry": {"coordinates":[115.78653717,-31.9122867584],"type":"Point"}
}