{
  "type": "Feature",
  "properties": {
    "addr:full":"8 Broadland Drv Launceston TAS 7250",
    "addr:housenumber":"8",
    "addr:postcode":"7250",
    "addr:street":"Broadland Drv",
    "iso:country":"AU",
    "sg:address":"8 Broadland Drv",
    "sg:city":"Launceston",
    "sg:classifiers":[
        {
            "category":"Professional",
            "subcategory":"Engineering",
            "type":"Services"
        }
    ],
    "sg:phone":"+61 3 6332 6988",
    "sg:postcode":"7250",
    "sg:province":"TAS",
    "sg:tags":[
        "electrical",
        "engineer"
    ],
    "wof:name":"C B & M Design Solutions Pty Ltd",
    "wof:placetype":"venue"
},
  "geometry": {"coordinates":[147.153808594,-41.4311752319],"type":"Point"}
}