{
  "type": "Feature",
  "properties": {
    "iso:country":"AU",
    "sg:address":"26 Melaleuca Ave",
    "sg:city":"Leeton",
    "sg:classifiers":[
        {
            "category":"Wholesale",
            "subcategory":"Machinery & Supplies",
            "type":"Manufacturing & Wholesale Goods"
        }
    ],
    "sg:phone":"+61 2 6953 3849",
    "sg:postcode":"2705",
    "sg:province":"NSW",
    "sg:tags":[
        "distributor",
        "crane",
        "mfrs"
    ],
    "wof:name":"Backsaver",
    "wof:placetype":"venue"
},
  "geometry": {"coordinates":[146.397537231,-34.5603218079],"type":"Point"}
}