{
  "type": "Feature",
  "properties": {
    "addr:full":"876 Beaudesert Rd Coopers Plains QLD 4108",
    "addr:housenumber":"876",
    "addr:postcode":"4108",
    "addr:street":"Beaudesert Rd",
    "iso:country":"AU",
    "sg:address":"876 Beaudesert Rd",
    "sg:city":"Coopers Plains",
    "sg:classifiers":[
        {
            "category":"Manufacturing",
            "subcategory":"Tools & Machinery",
            "type":"Manufacturing & Wholesale Goods"
        }
    ],
    "sg:phone":"+61 1800 214 910",
    "sg:postcode":"4108",
    "sg:province":"QLD",
    "sg:tags":[
        "earth",
        "excavating",
        "moving",
        "equipment"
    ],
    "sg:website":"http://www.xcmgcobra.com.au",
    "wof:name":"Alliance Major Plant Sales",
    "wof:placetype":"venue"
},
  "geometry": {"coordinates":[153.02285766599999,-27.5629253387],"type":"Point"}
}