{
  "type": "Feature",
  "properties": {
    "addr:full":"Cnr Wood & Greed Rds Kyabram VIC 3620",
    "addr:postcode":"3620",
    "addr:street":"Cnr",
    "iso:country":"AU",
    "sg:address":"Cnr Wood & Greed Rds",
    "sg:city":"Kyabram",
    "sg:classifiers":[
        {
            "category":"Professional",
            "subcategory":"Engineering",
            "type":"Services"
        }
    ],
    "sg:phone":"+61 3 5853 1045",
    "sg:postcode":"3620",
    "sg:province":"VIC",
    "sg:tags":[
        "engineer"
    ],
    "wof:name":"Brose Engineering Pty Ltd",
    "wof:placetype":"venue"
},
  "geometry": {"coordinates":[145.03465270999999,-36.3049201965],"type":"Point"}
}