{
  "type": "Feature",
  "properties": {
    "iso:country":"AU",
    "sg:address":"1st Floor, 264 Beamish St",
    "sg:city":"Campsie",
    "sg:classifiers":[
        {
            "category":"Health Services",
            "subcategory":"Dentist",
            "type":"Services"
        }
    ],
    "sg:phone":"+61 2 9787 3473",
    "sg:postcode":"2194",
    "sg:province":"NSW",
    "wof:name":"Liu Eric Dr",
    "wof:placetype":"venue"
},
  "geometry": {"coordinates":[151.103928,-33.913265],"type":"Point"}
}