{
  "type": "Feature",
  "properties": {
    "addr:full":"40 Malison St Wyoming NSW 2250",
    "addr:housenumber":"40",
    "addr:postcode":"2250",
    "addr:street":"Malison St",
    "iso:country":"AU",
    "sg:address":"40 Malison St",
    "sg:city":"Wyoming",
    "sg:classifiers":[
        {
            "category":"Professional",
            "subcategory":"Art Services",
            "type":"Services"
        }
    ],
    "sg:phone":"+61 2 4328 4334",
    "sg:postcode":"2250",
    "sg:province":"NSW",
    "sg:tags":[
        "graphic",
        "designer"
    ],
    "wof:name":"Adrian Bain",
    "wof:placetype":"venue"
},
  "geometry": {"coordinates":[151.360671997,-33.4031066895],"type":"Point"}
}