{
  "type": "Feature",
  "properties": {
    "addr:full":"6 Laffitte Rd Wingfield SA 5013",
    "addr:housenumber":"6",
    "addr:postcode":"5013",
    "addr:street":"Laffitte Rd",
    "iso:country":"AU",
    "sg:address":"6 Laffitte Rd",
    "sg:city":"Wingfield",
    "sg:classifiers":[
        {
            "category":"Utilities",
            "subcategory":"Water",
            "type":"Services"
        }
    ],
    "sg:phone":"+61 1300 724 516",
    "sg:postcode":"5013",
    "sg:province":"SA",
    "sg:tags":[
        "hot",
        "system"
    ],
    "wof:name":"Conergy Hot Water",
    "wof:placetype":"venue"
},
  "geometry": {"coordinates":[138.567993164,-34.8458137512],"type":"Point"}
}