{
  "type": "Feature",
  "properties": {
    "iso:country":"AU",
    "sg:address":"505 Ballarat Rd",
    "sg:city":"Sunshine",
    "sg:classifiers":[
        {
            "category":"Shopping",
            "subcategory":"Party Supplies",
            "type":"Retail Goods"
        }
    ],
    "sg:phone":"+61 3 9311 5799",
    "sg:postcode":"3020",
    "sg:province":"VIC",
    "sg:tags":[
        "children's"
    ],
    "wof:name":"AMF Bowling Centres",
    "wof:placetype":"venue"
},
  "geometry": {"coordinates":[144.82693499999999,-37.777229],"type":"Point"}
}