{
  "type": "Feature",
  "properties": {
    "addr:full":"20 Dickenson Rd Melville NSW 2320",
    "addr:housenumber":"20",
    "addr:postcode":"2320",
    "addr:street":"Dickenson Rd",
    "iso:country":"AU",
    "sg:address":"20 Dickenson Rd",
    "sg:city":"Melville",
    "sg:classifiers":[
        {
            "category":"Retail",
            "subcategory":"Auto Rental",
            "type":"Services"
        }
    ],
    "sg:phone":"+61 2 4930 6766",
    "sg:postcode":"2320",
    "sg:province":"NSW",
    "sg:tags":[
        "car",
        "wedding"
    ],
    "wof:name":"Luxury Link Limousines",
    "wof:placetype":"venue"
},
  "geometry": {"coordinates":[151.527877808,-32.6724014282],"type":"Point"}
}