{
  "type": "Feature",
  "properties": {
    "addr:full":"71a Railway Rd Blackburn VIC 3130",
    "addr:housenumber":"71a",
    "addr:postcode":"3130",
    "addr:street":"Railway Rd",
    "iso:country":"AU",
    "sg:address":"71a Railway Rd",
    "sg:city":"Blackburn",
    "sg:classifiers":[
        {
            "category":"Cafe",
            "type":"Food & Drink"
        }
    ],
    "sg:phone":"+61 3 9878 0757",
    "sg:postcode":"3130",
    "sg:province":"VIC",
    "wof:name":"Greek Bakehouse The",
    "wof:placetype":"venue"
},
  "geometry": {"coordinates":[145.153396606,-37.8193778992],"type":"Point"}
}