{
  "type": "Feature",
  "properties": {
    "addr:full":"16 Lewis St Port Lincoln SA 5606",
    "addr:housenumber":"16",
    "addr:postcode":"5606",
    "addr:street":"Lewis St",
    "iso:country":"AU",
    "sg:address":"16 Lewis St",
    "sg:city":"Port Lincoln",
    "sg:classifiers":[
        {
            "category":"Fast Food",
            "type":"Food & Drink"
        }
    ],
    "sg:phone":"+61 8 8682 3117",
    "sg:postcode":"5606",
    "sg:province":"SA",
    "sg:tags":[
        "away",
        "take"
    ],
    "wof:name":"Regal Chickens",
    "wof:placetype":"venue"
},
  "geometry": {"coordinates":[135.855682,-34.718624],"type":"Point"}
}