{
  "type": "Feature",
  "properties": {
    "addr:full":"Northpark Consulting Suites, Greenhills Rd Bundoora VIC 3083",
    "addr:postcode":"3083",
    "addr:street":"Greenhills Rd",
    "iso:country":"AU",
    "sg:address":"Northpark Consulting Suites, Greenhills Rd",
    "sg:city":"Bundoora",
    "sg:classifiers":[
        {
            "category":"Health Services",
            "subcategory":"Doctor",
            "type":"Services"
        }
    ],
    "sg:phone":"+61 3 9467 7611",
    "sg:postcode":"3083",
    "sg:province":"VIC",
    "sg:tags":[
        "medical",
        "practitioner"
    ],
    "wof:name":"Manolas Steve G. Surgeon",
    "wof:placetype":"venue"
},
  "geometry": {"coordinates":[145.06092834500001,-37.6916465759],"type":"Point"}
}