{
  "type": "Feature",
  "properties": {
    "addr:full":"6 Ward St Kinglake VIC 3763",
    "addr:housenumber":"6",
    "addr:postcode":"3763",
    "addr:street":"Ward St",
    "iso:country":"AU",
    "sg:address":"6 Ward St",
    "sg:city":"Kinglake",
    "sg:classifiers":[
        {
            "category":"Travel",
            "subcategory":"Travel Agent",
            "type":"Entertainment"
        }
    ],
    "sg:phone":"+61 3 5786 2004",
    "sg:postcode":"3763",
    "sg:province":"VIC",
    "sg:tags":[
        "tour",
        "holiday",
        "adventure"
    ],
    "wof:name":"Red Desert Tours & Catering",
    "wof:placetype":"venue"
},
  "geometry": {"coordinates":[145.335403442,-37.5283508301],"type":"Point"}
}