{
  "type": "Feature",
  "properties": {
    "addr:full":"Legge St Falmouth TAS 7215",
    "addr:postcode":"7215",
    "addr:street":"Legge St",
    "iso:country":"AU",
    "sg:address":"Legge St",
    "sg:city":"Falmouth",
    "sg:classifiers":[
        {
            "category":"Building & Trades",
            "subcategory":"Plumbing",
            "type":"Services"
        }
    ],
    "sg:phone":"+61 3 6372 5378",
    "sg:postcode":"7215",
    "sg:province":"TAS",
    "sg:tags":[
        "plumber",
        "gasfitters"
    ],
    "wof:name":"Child P J & H K",
    "wof:placetype":"venue"
},
  "geometry": {"coordinates":[148.27136200000001,-41.507877],"type":"Point"}
}