{
  "type": "Feature",
  "properties": {
    "addr:full":"83 McLennan St Mooroopna VIC 3629",
    "addr:housenumber":"83",
    "addr:postcode":"3629",
    "addr:street":"Mclennan St",
    "iso:country":"AU",
    "sg:address":"83 McLennan St",
    "sg:city":"Mooroopna",
    "sg:classifiers":[
        {
            "category":"Wholesale",
            "subcategory":"Medical Equipment & Supplies",
            "type":"Manufacturing & Wholesale Goods"
        }
    ],
    "sg:phone":"+61 3 5825 2144",
    "sg:postcode":"3629",
    "sg:province":"VIC",
    "sg:tags":[
        "aid",
        "care",
        "health",
        "home"
    ],
    "wof:name":"Campbell Barry & Lois",
    "wof:placetype":"venue"
},
  "geometry": {"coordinates":[145.35925293,-36.3950195312],"type":"Point"}
}