{
  "type": "Feature",
  "properties": {
    "addr:full":"74 1/2 Buckingham St Surry Hills NSW 2010",
    "addr:housenumber":"1 / 2",
    "addr:postcode":"2010",
    "addr:street":"74;Buckingham St",
    "iso:country":"AU",
    "sg:address":"74 1/2 Buckingham St",
    "sg:city":"Surry Hills",
    "sg:classifiers":[
        {
            "category":"Commercial Area",
            "type":"Public Place"
        }
    ],
    "sg:phone":"+61 2 9319 3382",
    "sg:postcode":"2010",
    "sg:province":"NSW",
    "sg:tags":[
        "clothing",
        "label"
    ],
    "wof:name":"Image Label Systems Australia Pty Ltd",
    "wof:placetype":"venue"
},
  "geometry": {"coordinates":[151.207519531,-33.88621521],"type":"Point"}
}