{
  "type": "Feature",
  "properties": {
    "addr:full":"38 Jupiter St Winston Hills NSW 2153",
    "addr:housenumber":"38",
    "addr:postcode":"2153",
    "addr:street":"Jupiter St",
    "iso:country":"AU",
    "sg:address":"38 Jupiter St",
    "sg:city":"Winston Hills",
    "sg:classifiers":[
        {
            "category":"Education",
            "subcategory":"Special Training",
            "type":"Public Place"
        }
    ],
    "sg:phone":"+61 2 9686 3311",
    "sg:postcode":"2153",
    "sg:province":"NSW",
    "sg:tags":[
        "development"
    ],
    "wof:name":"Barlow, Mannell & Associates",
    "wof:placetype":"venue"
},
  "geometry": {"coordinates":[150.975463867,-33.7737007141],"type":"Point"}
}