{
  "type": "Feature",
  "properties": {
    "addr:full":"28 Northern Rd Roma QLD 4455",
    "addr:housenumber":"28",
    "addr:postcode":"4455",
    "addr:street":"Northern Rd",
    "iso:country":"AU",
    "sg:address":"28 Northern Rd",
    "sg:city":"Roma",
    "sg:classifiers":[
        {
            "category":"Health Services",
            "subcategory":"Health Practitioner",
            "type":"Services"
        }
    ],
    "sg:phone":"+61 7 4622 5060",
    "sg:postcode":"4455",
    "sg:province":"QLD",
    "sg:tags":[
        "bowen",
        "therapy"
    ],
    "wof:name":"Erika Lister",
    "wof:placetype":"venue"
},
  "geometry": {"coordinates":[148.78672790499999,-26.5625705719],"type":"Point"}
}