{
  "type": "Feature",
  "properties": {
    "iso:country":"AU",
    "sg:address":"Wellington Rd",
    "sg:city":"Parkes",
    "sg:classifiers":[
        {
            "category":"Manufacturing",
            "subcategory":"Metals",
            "type":"Manufacturing & Wholesale Goods"
        }
    ],
    "sg:phone":"+61 1800 269 626",
    "sg:postcode":"2870",
    "sg:province":"NSW",
    "sg:tags":[
        "steel",
        "fabricator",
        "mfrs"
    ],
    "wof:name":"Bowman Promotions",
    "wof:placetype":"venue"
},
  "geometry": {"coordinates":[148.189346,-33.152714],"type":"Point"}
}