{
  "type": "Feature",
  "properties": {
    "iso:country":"AU",
    "sg:address":"21 Glenelg St",
    "sg:city":"Applecross",
    "sg:classifiers":[
        {
            "category":"Wholesale",
            "subcategory":"Machinery & Supplies",
            "type":"Manufacturing & Wholesale Goods"
        }
    ],
    "sg:phone":"+61 8 9315 9505",
    "sg:postcode":"6153",
    "sg:province":"WA",
    "sg:tags":[
        "equipment",
        "pneumatic"
    ],
    "wof:name":"Airdoc Mechanical Services",
    "wof:placetype":"venue"
},
  "geometry": {"coordinates":[115.838882,-32.011997],"type":"Point"}
}