{
  "type": "Feature",
  "properties": {
    "addr:full":"127 Victoria Rd Marrickville NSW 2204",
    "addr:housenumber":"127",
    "addr:postcode":"2204",
    "addr:street":"Victoria Rd",
    "iso:country":"AU",
    "sg:address":"127 Victoria Rd",
    "sg:city":"Marrickville",
    "sg:classifiers":[
        {
            "category":"Banks & Credit Unions",
            "subcategory":"Investment Brokerage",
            "type":"Services"
        }
    ],
    "sg:phone":"+61 2 9569 6327",
    "sg:postcode":"2204",
    "sg:province":"NSW",
    "wof:name":"Zhong Xing Investments Ltd",
    "wof:placetype":"venue"
},
  "geometry": {"coordinates":[151.16482500000001,-33.906223],"type":"Point"}
}