{
  "type": "Feature",
  "properties": {
    "addr:full":"54 - 58 London Rd Mile End SA 5031",
    "addr:housenumber":"58",
    "addr:postcode":"5031",
    "addr:street":"London Rd",
    "iso:country":"AU",
    "sg:address":"54 - 58 London Rd",
    "sg:city":"Mile End",
    "sg:classifiers":[
        {
            "category":"Wholesale",
            "subcategory":"Seafood",
            "type":"Manufacturing & Wholesale Goods"
        }
    ],
    "sg:phone":"+61 8 8351 8201",
    "sg:postcode":"5031",
    "sg:province":"SA",
    "sg:tags":[
        "fish"
    ],
    "wof:name":"Adelaide Fish Processors Pty Ltd",
    "wof:placetype":"venue"
},
  "geometry": {"coordinates":[138.57539367699999,-34.9373893738],"type":"Point"}
}