{
  "type": "Feature",
  "properties": {
    "addr:full":"10 Torquay Rd Pialba QLD 4655",
    "addr:housenumber":"10",
    "addr:postcode":"4655",
    "addr:street":"Torquay Rd",
    "iso:country":"AU",
    "sg:address":"10 Torquay Rd",
    "sg:city":"Pialba",
    "sg:classifiers":[
        {
            "category":"Professional",
            "subcategory":"Accounting & Tax Preparation",
            "type":"Services"
        }
    ],
    "sg:phone":"+61 7 4124 3838",
    "sg:postcode":"4655",
    "sg:province":"QLD",
    "sg:tags":[
        "accountant",
        "auditor"
    ],
    "wof:name":"Mangelsdorf R J",
    "wof:placetype":"venue"
},
  "geometry": {"coordinates":[152.84042400000001,-25.281567],"type":"Point"}
}