{
  "type": "Feature",
  "properties": {
    "addr:full":"27 Bringelly Ave Pendle Hill NSW 2145",
    "addr:housenumber":"27",
    "addr:postcode":"2145",
    "addr:street":"Bringelly Ave",
    "iso:country":"AU",
    "sg:address":"27 Bringelly Ave",
    "sg:city":"Pendle Hill",
    "sg:classifiers":[
        {
            "category":"Personal",
            "type":"Services"
        }
    ],
    "sg:phone":"+61 2 9757 2811",
    "sg:postcode":"2145",
    "sg:province":"NSW",
    "sg:tags":[
        "gift"
    ],
    "wof:name":"A Gift Worth Giving",
    "wof:placetype":"venue"
},
  "geometry": {"coordinates":[150.96134948700001,-33.8003158569],"type":"Point"}
}