{
  "type": "Feature",
  "properties": {
    "addr:full":"157 Anakie Rd Bell Post Hill VIC 3215",
    "addr:housenumber":"157",
    "addr:postcode":"3215",
    "addr:street":"Anakie Rd;Post Hill",
    "iso:country":"AU",
    "sg:address":"157 Anakie Rd",
    "sg:city":"Bell Post Hill",
    "sg:classifiers":[
        {
            "category":"Professional",
            "subcategory":"Art Services",
            "type":"Services"
        }
    ],
    "sg:phone":"+61 407 246 837",
    "sg:postcode":"3215",
    "sg:province":"VIC",
    "sg:tags":[
        "decorator",
        "painter"
    ],
    "wof:name":"040 Painter",
    "wof:placetype":"venue"
},
  "geometry": {"coordinates":[144.333053589,-38.1019706726],"type":"Point"}
}