{
  "type": "Feature",
  "properties": {
    "iso:country":"AU",
    "sg:address":"4 Larool Rd",
    "sg:city":"Terrey Hills",
    "sg:classifiers":[
        {
            "category":"Building & Trades",
            "subcategory":"Equipment Rental",
            "type":"Services"
        }
    ],
    "sg:phone":"+61 2 9486 3160",
    "sg:postcode":"2084",
    "sg:province":"NSW",
    "sg:tags":[
        "party",
        "hire"
    ],
    "wof:name":"Lease-A-Leaf Plant Party Hire",
    "wof:placetype":"venue"
},
  "geometry": {"coordinates":[151.21859741200001,-33.6876792908],"type":"Point"}
}