{
  "type": "Feature",
  "properties": {
    "addr:full":"1 A Loch St Cranbourne VIC 3977",
    "addr:housenumber":"1 a",
    "addr:postcode":"3977",
    "addr:street":"Loch St",
    "iso:country":"AU",
    "sg:address":"1 A Loch St",
    "sg:city":"Cranbourne",
    "sg:classifiers":[
        {
            "category":"Home & Garden",
            "subcategory":"Hardware",
            "type":"Retail Goods"
        }
    ],
    "sg:phone":"+61 3 5995 2722",
    "sg:postcode":"3977",
    "sg:province":"VIC",
    "sg:tags":[
        "tarpaulin"
    ],
    "wof:name":"Avtek Covers",
    "wof:placetype":"venue"
},
  "geometry": {"coordinates":[145.284133911,-38.1009101868],"type":"Point"}
}