{
  "type": "Feature",
  "properties": {
    "addr:full":"74 Sladden Rd Yarrawarrah NSW 2233",
    "addr:housenumber":"74",
    "addr:postcode":"2233",
    "addr:street":"Sladden Rd",
    "iso:country":"AU",
    "sg:address":"74 Sladden Rd",
    "sg:city":"Yarrawarrah",
    "sg:classifiers":[
        {
            "category":"Professional",
            "subcategory":"Computer Services",
            "type":"Services"
        }
    ],
    "sg:phone":"+61 2 9520 0340",
    "sg:postcode":"2233",
    "sg:province":"NSW",
    "sg:tags":[
        "consultant",
        "system"
    ],
    "wof:name":"Glotech Pty Ltd",
    "wof:placetype":"venue"
},
  "geometry": {"coordinates":[151.02500915499999,-34.057346344],"type":"Point"}
}