{
  "type": "Feature",
  "properties": {
    "addr:full":"18 Binalong Ave Allambie Heights NSW 2100",
    "addr:housenumber":"18",
    "addr:postcode":"2100",
    "addr:street":"Binalong Ave",
    "iso:country":"AU",
    "sg:address":"18 Binalong Ave",
    "sg:city":"Allambie Heights",
    "sg:classifiers":[
        {
            "category":"Building & Trades",
            "subcategory":"Construction",
            "type":"Services"
        }
    ],
    "sg:phone":"+61 2 9938 4013",
    "sg:postcode":"2100",
    "sg:province":"NSW",
    "sg:tags":[
        "contractor"
    ],
    "wof:name":"Readman Brent",
    "wof:placetype":"venue"
},
  "geometry": {"coordinates":[151.25689697300001,-33.774810791],"type":"Point"}
}