{
  "type": "Feature",
  "properties": {
    "addr:full":"Shop 174 - 175, Westfield Belconnen ACT 2617",
    "addr:housenumber":"175",
    "addr:postcode":"2617",
    "addr:street":"Westfield",
    "iso:country":"AU",
    "sg:address":"Shop 174 - 175, Westfield",
    "sg:city":"Belconnen",
    "sg:classifiers":[
        {
            "category":"Shopping",
            "subcategory":"Music",
            "type":"Retail Goods"
        }
    ],
    "sg:phone":"+61 1300 787 768",
    "sg:postcode":"2617",
    "sg:province":"ACT",
    "sg:tags":[
        "store"
    ],
    "wof:name":"The Music Shop",
    "wof:placetype":"venue"
},
  "geometry": {"coordinates":[149.06353759800001,-35.239730835],"type":"Point"}
}