{
  "type": "Feature",
  "properties": {
    "addr:full":"181a Swan St Richmond VIC 3121",
    "addr:housenumber":"181a",
    "addr:postcode":"3121",
    "addr:street":"Swan St",
    "iso:country":"AU",
    "sg:address":"181a Swan St",
    "sg:city":"Richmond",
    "sg:classifiers":[
        {
            "category":"Shopping",
            "subcategory":"Clothing, Apparel, & Fashions",
            "type":"Retail Goods"
        }
    ],
    "sg:phone":"+61 3 9428 3880",
    "sg:postcode":"3121",
    "sg:province":"VIC",
    "sg:tags":[
        "sportswear"
    ],
    "wof:name":"Xtremiteez",
    "wof:placetype":"venue"
},
  "geometry": {"coordinates":[144.99769592300001,-37.825504303],"type":"Point"}
}