{
  "type": "Feature",
  "properties": {
    "addr:full":"1059 Cambridge Rd Cambridge TAS 7170",
    "addr:housenumber":"1059",
    "addr:postcode":"7170",
    "addr:street":"Cambridge Rd",
    "iso:country":"AU",
    "sg:address":"1059 Cambridge Rd",
    "sg:city":"Cambridge",
    "sg:classifiers":[
        {
            "category":"Wholesale",
            "subcategory":"Machinery & Supplies",
            "type":"Manufacturing & Wholesale Goods"
        }
    ],
    "sg:phone":"+61 3 6216 1500",
    "sg:postcode":"7170",
    "sg:province":"TAS",
    "sg:tags":[
        "instrument",
        "scientific"
    ],
    "wof:name":"Imbros Pty Ltd",
    "wof:placetype":"venue"
},
  "geometry": {"coordinates":[147.448776245,-42.835308075],"type":"Point"}
}