{
  "type": "Feature",
  "properties": {
    "addr:full":"1/ 8 Kerr Rd Ingleburn NSW 2565",
    "addr:housenumber":"/ 8",
    "addr:postcode":"2565",
    "addr:street":"Kerr Rd",
    "iso:country":"AU",
    "sg:address":"1/ 8 Kerr Rd",
    "sg:city":"Ingleburn",
    "sg:phone":"+61 2 9618 6114",
    "sg:postcode":"2565",
    "sg:province":"NSW",
    "wof:name":"Moores Rotomold Pty Ltd",
    "wof:placetype":"venue"
},
  "geometry": {"coordinates":[150.86752319300001,-33.9926109314],"type":"Point"}
}