{
  "type": "Feature",
  "properties": {
    "addr:full":"8691 Westswan Rd Henley Brook WA 6055",
    "addr:housenumber":"8691",
    "addr:postcode":"6055",
    "addr:street":"Westswan Rd",
    "iso:country":"AU",
    "sg:address":"8691 Westswan Rd",
    "sg:city":"Henley Brook",
    "sg:classifiers":[
        {
            "category":"Farming",
            "subcategory":"Vineyard",
            "type":"Manufacturing & Wholesale Goods"
        }
    ],
    "sg:phone":"+61 8 9296 3444",
    "sg:postcode":"6055",
    "sg:province":"WA",
    "sg:tags":[
        "winery"
    ],
    "wof:name":"Chesters",
    "wof:placetype":"venue"
},
  "geometry": {"coordinates":[115.978256,-31.79565],"type":"Point"}
}