{
  "type": "Feature",
  "properties": {
    "iso:country":"AU",
    "sg:address":"Shp4/ 401 Main Rd",
    "sg:city":"Coromandel Valley",
    "sg:classifiers":[
        {
            "category":"Health Services",
            "subcategory":"Health Practitioner",
            "type":"Services"
        }
    ],
    "sg:phone":"+61 8 8178 0978",
    "sg:postcode":"5051",
    "sg:province":"SA",
    "sg:tags":[
        "physiotherapist"
    ],
    "wof:name":"Coromandel Physiotherapy Clinic",
    "wof:placetype":"venue"
},
  "geometry": {"coordinates":[138.622726,-35.043953],"type":"Point"}
}