{
  "type": "Feature",
  "properties": {
    "iso:country":"AU",
    "sg:address":"26 Hector St",
    "sg:city":"Osborne Park",
    "sg:classifiers":[
        {
            "category":"Professional",
            "subcategory":"Employment Agencies",
            "type":"Services"
        }
    ],
    "sg:phone":"+61 8 9244 8055",
    "sg:postcode":"6017",
    "sg:province":"WA",
    "sg:tags":[
        "hire",
        "labour",
        "contractor"
    ],
    "sg:website":"http://www.nr.com.au",
    "wof:name":"Nationwide Recruitment Services",
    "wof:placetype":"venue"
},
  "geometry": {"coordinates":[115.81407165500001,-31.8990840912],"type":"Point"}
}