{
  "type": "Feature",
  "properties": {
    "addr:full":"97 Uduc Rd Harvey WA 6220",
    "addr:housenumber":"97",
    "addr:postcode":"6220",
    "addr:street":"Uduc Rd",
    "iso:country":"AU",
    "sg:address":"97 Uduc Rd",
    "sg:city":"Harvey",
    "sg:classifiers":[
        {
            "category":"Restaurant",
            "type":"Food & Drink"
        }
    ],
    "sg:phone":"+61 8 9729 1321",
    "sg:postcode":"6220",
    "sg:province":"WA",
    "wof:name":"Bellas Seafood Restaurant",
    "wof:placetype":"venue"
},
  "geometry": {"coordinates":[115.89424099999999,-33.080242],"type":"Point"}
}