{
  "type": "Feature",
  "properties": {
    "addr:full":"Shp 2/ 243 Main Rd Blackwood SA 5051",
    "addr:housenumber":"/ 243",
    "addr:postcode":"5051",
    "addr:street":"Main Rd",
    "iso:country":"AU",
    "sg:address":"Shp 2/ 243 Main Rd",
    "sg:city":"Blackwood",
    "sg:classifiers":[
        {
            "category":"Shopping",
            "subcategory":"Clothing, Apparel, & Fashions",
            "type":"Retail Goods"
        }
    ],
    "sg:phone":"+61 8 8178 0910",
    "sg:postcode":"5051",
    "sg:province":"SA",
    "sg:tags":[
        "accessory"
    ],
    "wof:name":"Blonde Ambition",
    "wof:placetype":"venue"
},
  "geometry": {"coordinates":[138.616806,-35.020668],"type":"Point"}
}