{
  "type": "Feature",
  "properties": {
    "addr:full":"Deanmore Rd Scarborough WA 6019",
    "addr:postcode":"6019",
    "addr:street":"Deanmore Rd",
    "iso:country":"AU",
    "sg:address":"Deanmore Rd",
    "sg:city":"Scarborough",
    "sg:classifiers":[
        {
            "category":"Sports & Exercise",
            "subcategory":"Sports Center",
            "type":"Entertainment"
        }
    ],
    "sg:phone":"+61 400 087 991",
    "sg:postcode":"6019",
    "sg:province":"WA",
    "sg:tags":[
        "coach",
        "tennis"
    ],
    "wof:name":"Scarborough Tennis Centre",
    "wof:placetype":"venue"
},
  "geometry": {"coordinates":[115.76773071300001,-31.8963222504],"type":"Point"}
}