{
  "type": "Feature",
  "properties": {
    "iso:country":"AU",
    "sg:address":"New England Hwy",
    "sg:city":"Cambooya",
    "sg:classifiers":[
        {
            "category":"Retail",
            "subcategory":"Auto Repair",
            "type":"Services"
        }
    ],
    "sg:phone":"+61 7 4696 1900",
    "sg:postcode":"4358",
    "sg:province":"QLD",
    "sg:tags":[
        "automotive",
        "air conditioning"
    ],
    "wof:name":"Ejac Auto Centre",
    "wof:placetype":"venue"
},
  "geometry": {"coordinates":[151.90884399999999,-27.699844],"type":"Point"}
}