{
  "type": "Feature",
  "properties": {
    "addr:full":"59 Breed St Traralgon VIC 3844",
    "addr:housenumber":"59",
    "addr:postcode":"3844",
    "addr:street":"Breed St",
    "iso:country":"AU",
    "sg:address":"59 Breed St",
    "sg:city":"Traralgon",
    "sg:classifiers":[
        {
            "category":"Government",
            "subcategory":"Fire Station",
            "type":"Public Place"
        }
    ],
    "sg:phone":"+61 3 5176 1362",
    "sg:postcode":"3844",
    "sg:province":"VIC",
    "sg:tags":[
        "equipment",
        "protection",
        "consultant"
    ],
    "sg:website":"http://www.deanmac.com.au",
    "wof:name":"Deanmac Emergency Services",
    "wof:placetype":"venue"
},
  "geometry": {"coordinates":[146.53346252399999,-38.1936569214],"type":"Point"}
}