{
  "type": "Feature",
  "properties": {
    "addr:full":"2b- 4b Patrick St Hobart TAS 7000",
    "addr:housenumber":"4b",
    "addr:postcode":"7000",
    "addr:street":"Patrick St",
    "iso:country":"AU",
    "sg:address":"2b- 4b Patrick St",
    "sg:city":"Hobart",
    "sg:classifiers":[
        {
            "category":"Building & Trades",
            "subcategory":"Construction",
            "type":"Services"
        }
    ],
    "sg:phone":"+61 3 6231 0249",
    "sg:postcode":"7000",
    "sg:province":"TAS",
    "sg:tags":[
        "window",
        "timber"
    ],
    "wof:name":"Trimview Pty Ltd",
    "wof:placetype":"venue"
},
  "geometry": {"coordinates":[147.32505798299999,-42.8760108948],"type":"Point"}
}