{
  "type": "Feature",
  "properties": {
    "iso:country":"AU",
    "sg:address":"Shop 7, Napoleon Close, Napoleon St",
    "sg:city":"Cottesloe",
    "sg:classifiers":[
        {
            "category":"Personal",
            "subcategory":"Hair Removal",
            "type":"Services"
        }
    ],
    "sg:phone":"+61 8 9385 1427",
    "sg:postcode":"6011",
    "sg:province":"WA",
    "wof:name":"Monicas Electrolysis & Beauty Centre",
    "wof:placetype":"venue"
},
  "geometry": {"coordinates":[115.761978149,-31.9979095459],"type":"Point"}
}