{
  "type": "Feature",
  "properties": {
    "addr:full":"Shp4/ 192 George St Windsor NSW 2756",
    "addr:housenumber":"192",
    "addr:postcode":"2756",
    "addr:street":"George St",
    "iso:country":"AU",
    "sg:address":"Shp4/ 192 George St",
    "sg:city":"Windsor",
    "sg:classifiers":[
        {
            "category":"Fast Food",
            "type":"Food & Drink"
        }
    ],
    "sg:phone":"+61 2 4577 7227",
    "sg:postcode":"2756",
    "sg:province":"NSW",
    "sg:tags":[
        "away",
        "take"
    ],
    "wof:name":"Fooweys Flaming Chickens",
    "wof:placetype":"venue"
},
  "geometry": {"coordinates":[150.81704711899999,-33.6092720032],"type":"Point"}
}