{
  "type": "Feature",
  "properties": {
    "addr:full":"PO Box 290 Annerley QLD 4103",
    "addr:postcode":"4103",
    "iso:country":"AU",
    "sg:address":"PO Box 290",
    "sg:city":"Annerley",
    "sg:classifiers":[
        {
            "category":"Education",
            "subcategory":"Special Training",
            "type":"Public Place"
        }
    ],
    "sg:phone":"+61 7 3342 4563",
    "sg:postcode":"4103",
    "sg:province":"QLD",
    "sg:tags":[
        "tuition-educational"
    ],
    "wof:name":"Australian Training & Education Centre",
    "wof:placetype":"venue"
},
  "geometry": {"coordinates":[153.031784058,-27.5140094757],"type":"Point"}
}