{
  "type": "Feature",
  "properties": {
    "iso:country":"AU",
    "sg:address":"PO Box 530",
    "sg:city":"Sunnybank",
    "sg:classifiers":[
        {
            "category":"Professional",
            "type":"Services"
        }
    ],
    "sg:phone":"+61 7 3344 2090",
    "sg:postcode":"4109",
    "sg:province":"QLD",
    "sg:tags":[
        "valuer"
    ],
    "wof:name":"Valuations & Appraisals Services Australasia Pty Ltd",
    "wof:placetype":"venue"
},
  "geometry": {"coordinates":[153.061157227,-27.5790500641],"type":"Point"}
}