{
  "type": "Feature",
  "properties": {
    "addr:full":"207 Pacific Hwy St Leonards NSW 2065",
    "addr:housenumber":"207",
    "addr:postcode":"2065",
    "addr:street":"Pacific Hwy",
    "iso:country":"AU",
    "sg:address":"207 Pacific Hwy",
    "sg:city":"St Leonards",
    "sg:classifiers":[
        {
            "category":"Insurance",
            "subcategory":"Hazard Insurance",
            "type":"Services"
        }
    ],
    "sg:phone":"+61 13 72 00",
    "sg:postcode":"2065",
    "sg:province":"NSW",
    "sg:tags":[
        "motor",
        "vehicle"
    ],
    "wof:name":"Toyota Extra Care",
    "wof:placetype":"venue"
},
  "geometry": {"coordinates":[151.198944092,-33.8255500793],"type":"Point"}
}