{
  "type": "Feature",
  "properties": {
    "addr:full":"Mills Ave Moranbah QLD 4744",
    "addr:postcode":"4744",
    "addr:street":"Mills Ave",
    "iso:country":"AU",
    "sg:address":"Mills Ave",
    "sg:city":"Moranbah",
    "sg:classifiers":[
        {
            "category":"Autos & Motor Vehicles",
            "subcategory":"Auto Supplies",
            "type":"Retail Goods"
        }
    ],
    "sg:phone":"+61 7 4941 8144",
    "sg:postcode":"4744",
    "sg:province":"QLD",
    "sg:tags":[
        "tyre"
    ],
    "wof:name":"Coalfields Tyre Centre",
    "wof:placetype":"venue"
},
  "geometry": {"coordinates":[148.06712341299999,-21.9988174438],"type":"Point"}
}