{
  "type": "Feature",
  "properties": {
    "iso:country":"AU",
    "sg:address":"85 George St",
    "sg:city":"Brisbane",
    "sg:classifiers":[
        {
            "category":"Travel",
            "subcategory":"Hotels & Motels",
            "type":"Entertainment"
        }
    ],
    "sg:phone":"+61 7 3221 6511",
    "sg:postcode":"4000",
    "sg:province":"QLD",
    "sg:tags":[
        "accommodation"
    ],
    "wof:name":"Lands Office Tavern",
    "wof:placetype":"venue"
},
  "geometry": {"coordinates":[153.02581787099999,-27.4730300903],"type":"Point"}
}