{
  "type": "Feature",
  "properties": {
    "iso:country":"AU",
    "sg:address":"3 Dulhunty Ave",
    "sg:city":"Dubbo",
    "sg:classifiers":[
        {
            "category":"Professional",
            "subcategory":"Computer Services",
            "type":"Services"
        }
    ],
    "sg:phone":"+61 2 6882 0139",
    "sg:postcode":"2830",
    "sg:province":"NSW",
    "sg:tags":[
        "training"
    ],
    "wof:name":"Annette Priest Computing",
    "wof:placetype":"venue"
},
  "geometry": {"coordinates":[148.60479736299999,-32.2612495422],"type":"Point"}
}