{
  "type": "Feature",
  "properties": {
    "iso:country":"AU",
    "sg:address":"12 Battersea Rd",
    "sg:city":"Canning Vale",
    "sg:classifiers":[
        {
            "category":"Professional",
            "subcategory":"Computer Services",
            "type":"Services"
        }
    ],
    "sg:phone":"+61 8 9455 6842",
    "sg:postcode":"6155",
    "sg:province":"WA",
    "sg:tags":[
        "package",
        "software"
    ],
    "wof:name":"Laboratory Software",
    "wof:placetype":"venue"
},
  "geometry": {"coordinates":[115.904701,-32.096359],"type":"Point"}
}