{
  "type": "Feature",
  "properties": {
    "iso:country":"AU",
    "sg:address":"Boat Harbour Drv",
    "sg:city":"Torquay",
    "sg:classifiers":[
        {
            "category":"Food & Beverages",
            "subcategory":"Supermarket",
            "type":"Retail Goods"
        }
    ],
    "sg:phone":"+61 7 4125 2999",
    "sg:postcode":"4655",
    "sg:province":"QLD",
    "sg:tags":[
        "grocery",
        "store"
    ],
    "wof:name":"Torquay Heights Foodstore",
    "wof:placetype":"venue"
},
  "geometry": {"coordinates":[152.869263,-25.291925],"type":"Point"}
}