{
  "type": "Feature",
  "properties": {
    "addr:full":"Shop 7/ 1779 Pittwater Rd Mona Vale NSW 2103",
    "addr:housenumber":"shop 7 / 1779",
    "addr:postcode":"2103",
    "addr:street":"Pittwater Rd",
    "iso:country":"AU",
    "sg:address":"Shop 7/ 1779 Pittwater Rd",
    "sg:city":"Mona Vale",
    "sg:classifiers":[
        {
            "category":"Farming",
            "subcategory":"Fish & Marine Products",
            "type":"Manufacturing & Wholesale Goods"
        }
    ],
    "sg:phone":"+61 2 9999 3917",
    "sg:postcode":"2103",
    "sg:province":"NSW",
    "sg:tags":[
        "organic"
    ],
    "wof:name":"In The Raw Organics",
    "wof:placetype":"venue"
},
  "geometry": {"coordinates":[151.303497314,-33.6761131287],"type":"Point"}
}