{
  "type": "Feature",
  "properties": {
    "addr:full":"1/ 6 Pendry Crt Woodridge QLD 4114",
    "addr:housenumber":"/ 6",
    "addr:postcode":"4114",
    "addr:street":"Pendry Crt",
    "iso:country":"AU",
    "sg:address":"1/ 6 Pendry Crt",
    "sg:city":"Woodridge",
    "sg:classifiers":[
        {
            "category":"Retail",
            "subcategory":"Auto Repair",
            "type":"Services"
        }
    ],
    "sg:phone":"+61 7 3208 1471",
    "sg:postcode":"4114",
    "sg:province":"QLD",
    "sg:tags":[
        "beater",
        "painter",
        "panel"
    ],
    "wof:name":"Tonys Paint & Panel",
    "wof:placetype":"venue"
},
  "geometry": {"coordinates":[153.11390685999999,-27.6207065582],"type":"Point"}
}