{
  "type": "Feature",
  "properties": {
    "addr:full":"Unit 1 / 8 Rouse Rd Mandurah WA 6210",
    "addr:housenumber":"8",
    "addr:postcode":"6210",
    "addr:street":"Rouse Rd",
    "iso:country":"AU",
    "sg:address":"Unit 1 / 8 Rouse Rd",
    "sg:city":"Mandurah",
    "sg:classifiers":[
        {
            "category":"Building & Trades",
            "subcategory":"Plumbing",
            "type":"Services"
        }
    ],
    "sg:phone":"+61 8 9582 0567",
    "sg:postcode":"6210",
    "sg:province":"WA",
    "sg:tags":[
        "plumber",
        "gasfitters"
    ],
    "sg:website":"http://www.swansplumbing.com.au",
    "wof:name":"Swan's Complete Plumbing & Gas",
    "wof:placetype":"venue"
},
  "geometry": {"coordinates":[115.750229,-32.514404],"type":"Point"}
}