{
  "type": "Feature",
  "properties": {
    "iso:country":"AU",
    "sg:address":"273a High St",
    "sg:city":"Northcote",
    "sg:classifiers":[
        {
            "category":"Health Services",
            "subcategory":"Health Practitioner",
            "type":"Services"
        }
    ],
    "sg:phone":"+61 3 9489 4988",
    "sg:postcode":"3070",
    "sg:province":"VIC",
    "sg:tags":[
        "naturopath"
    ],
    "wof:name":"Northcote Natural Healing Centre",
    "wof:placetype":"venue"
},
  "geometry": {"coordinates":[144.998215,-37.77243],"type":"Point"}
}