{
  "type": "Feature",
  "properties": {
    "iso:country":"AU",
    "sg:address":"Unit 6, 43 Berrimah Rd",
    "sg:city":"Berrimah",
    "sg:classifiers":[
        {
            "category":"Communications",
            "type":"Services"
        }
    ],
    "sg:phone":"+61 1300 130 299",
    "sg:postcode":"0828",
    "sg:province":"NT",
    "sg:tags":[
        "equipment",
        "satellite"
    ],
    "wof:name":"Cando Antenna & Satellite Systems",
    "wof:placetype":"venue"
},
  "geometry": {"coordinates":[130.92344665499999,-12.4338197708],"type":"Point"}
}