{
  "type": "Feature",
  "properties": {
    "iso:country":"AU",
    "sg:address":"26 Bongalong St",
    "sg:city":"Naremburn",
    "sg:classifiers":[
        {
            "category":"Professional",
            "subcategory":"Business Services",
            "type":"Services"
        }
    ],
    "sg:phone":"+61 411 377 076",
    "sg:postcode":"2065",
    "sg:province":"NSW",
    "sg:tags":[
        "broker"
    ],
    "wof:name":"Emmconsult",
    "wof:placetype":"venue"
},
  "geometry": {"coordinates":[151.19825744600001,-33.8185272217],"type":"Point"}
}