{
  "type": "Feature",
  "properties": {
    "addr:full":"1/ 6 Glencoe St Bendigo VIC 3539",
    "addr:housenumber":"/ 6",
    "addr:postcode":"3539",
    "addr:street":"Glencoe St",
    "iso:country":"AU",
    "sg:address":"1/ 6 Glencoe St",
    "sg:city":"Bendigo",
    "sg:classifiers":[
        {
            "category":"Government",
            "subcategory":"Post Office",
            "type":"Public Place"
        }
    ],
    "sg:phone":"+61 409 180 113",
    "sg:postcode":"3539",
    "sg:province":"VIC",
    "sg:tags":[
        "horse",
        "dentist"
    ],
    "wof:name":"Campbell Paul",
    "wof:placetype":"venue"
},
  "geometry": {"coordinates":[144.296143,-36.76535],"type":"Point"}
}