{
  "type": "Feature",
  "properties": {
    "addr:full":"24 North St Mt Lawley WA 6050",
    "addr:housenumber":"24",
    "addr:postcode":"6050",
    "addr:street":"North St",
    "iso:country":"AU",
    "sg:address":"24 North St",
    "sg:city":"Mt Lawley",
    "sg:classifiers":[
        {
            "category":"Health Services",
            "subcategory":"Doctor",
            "type":"Services"
        }
    ],
    "sg:phone":"+61 8 9271 6394",
    "sg:postcode":"6050",
    "sg:province":"WA",
    "sg:tags":[
        "medical",
        "practitioner"
    ],
    "wof:name":"Antonas Nicholas A Dr",
    "wof:placetype":"venue"
},
  "geometry": {"coordinates":[115.87220764200001,-31.9250106812],"type":"Point"}
}