{
  "type": "Feature",
  "properties": {
    "addr:full":"6 Asher Crt null QLD 4210",
    "addr:housenumber":"6",
    "addr:postcode":"4210",
    "addr:street":"Asher Crt",
    "iso:country":"AU",
    "sg:address":"6 Asher Crt",
    "sg:city":"null",
    "sg:classifiers":[
        {
            "category":"Professional",
            "subcategory":"Engineering",
            "type":"Services"
        }
    ],
    "sg:phone":"+61 7 5529 7899",
    "sg:postcode":"4210",
    "sg:province":"QLD",
    "sg:tags":[
        "civil",
        "engineer"
    ],
    "wof:name":"Seovic Civil Engineering Pty Ltd",
    "wof:placetype":"venue"
},
  "geometry": {"coordinates":[153.271362305,-27.9029006958],"type":"Point"}
}