{
  "type": "Feature",
  "properties": {
    "addr:full":"519 Keilor Rd Essendon VIC 3040",
    "addr:housenumber":"519",
    "addr:postcode":"3040",
    "addr:street":"Keilor Rd",
    "iso:country":"AU",
    "sg:address":"519 Keilor Rd",
    "sg:city":"Essendon",
    "sg:classifiers":[
        {
            "category":"Home & Garden",
            "subcategory":"Household Appliances",
            "type":"Retail Goods"
        }
    ],
    "sg:phone":"+61 3 9379 7744",
    "sg:postcode":"3040",
    "sg:province":"VIC",
    "sg:tags":[
        "heating",
        "system"
    ],
    "wof:name":"Barbeque Fireplace",
    "wof:placetype":"venue"
},
  "geometry": {"coordinates":[144.90213012699999,-37.7412528992],"type":"Point"}
}