{
  "type": "Feature",
  "properties": {
    "iso:country":"AU",
    "sg:address":"353 Cambridge St",
    "sg:city":"Wembley",
    "sg:classifiers":[
        {
            "category":"Communications",
            "subcategory":"Film & Video Production",
            "type":"Services"
        }
    ],
    "sg:phone":"+61 8 9387 8033",
    "sg:postcode":"6014",
    "sg:province":"WA",
    "sg:tags":[
        "dvd",
        "library"
    ],
    "wof:name":"Video Ezy",
    "wof:placetype":"venue"
},
  "geometry": {"coordinates":[115.810539246,-31.9408855438],"type":"Point"}
}