{
  "type": "Feature",
  "properties": {
    "iso:country":"AU",
    "sg:address":"11 Bellevue Park Rd",
    "sg:city":"Bellevue Hill",
    "sg:classifiers":[
        {
            "category":"Shopping",
            "subcategory":"Music",
            "type":"Retail Goods"
        }
    ],
    "sg:phone":"+61 2 9387 7843",
    "sg:postcode":"2023",
    "sg:province":"NSW",
    "sg:tags":[
        "instrument",
        "musical"
    ],
    "wof:name":"Fiddlers Hire",
    "wof:placetype":"venue"
},
  "geometry": {"coordinates":[151.25944519000001,-33.8876724243],"type":"Point"}
}