{
  "type": "Feature",
  "properties": {
    "addr:full":"28 Frances St Merrylands NSW 2160",
    "addr:housenumber":"28",
    "addr:postcode":"2160",
    "addr:street":"Frances St",
    "iso:country":"AU",
    "sg:address":"28 Frances St",
    "sg:city":"Merrylands",
    "sg:classifiers":[
        {
            "category":"Retail",
            "subcategory":"Storage",
            "type":"Services"
        }
    ],
    "sg:phone":"+61 2 9613 0311",
    "sg:postcode":"2160",
    "sg:province":"NSW",
    "sg:tags":[
        "removal",
        "furniture"
    ],
    "wof:name":"Accent Removals",
    "wof:placetype":"venue"
},
  "geometry": {"coordinates":[150.97604370100001,-33.8242950439],"type":"Point"}
}