{
  "type": "Feature",
  "properties": {
    "iso:country":"AU",
    "sg:address":"PO Box 217",
    "sg:city":"Eudlo",
    "sg:classifiers":[
        {
            "category":"Building & Trades",
            "subcategory":"Plumbing",
            "type":"Services"
        }
    ],
    "sg:phone":"+61 7 5445 0055",
    "sg:postcode":"4554",
    "sg:province":"QLD",
    "sg:tags":[
        "plumber",
        "gasfitters"
    ],
    "wof:name":"Bakers Plumbing",
    "wof:placetype":"venue"
},
  "geometry": {"coordinates":[152.95811462399999,-26.7261600494],"type":"Point"}
}