{
  "type": "Feature",
  "properties": {
    "addr:full":"3 Coolibah St Dalby QLD 4405",
    "addr:housenumber":"3",
    "addr:postcode":"4405",
    "addr:street":"Coolibah St",
    "iso:country":"AU",
    "sg:address":"3 Coolibah St",
    "sg:city":"Dalby",
    "sg:classifiers":[
        {
            "category":"Wholesale",
            "subcategory":"Electrical",
            "type":"Manufacturing & Wholesale Goods"
        }
    ],
    "sg:phone":"+61 7 4662 5933",
    "sg:postcode":"4405",
    "sg:province":"QLD",
    "sg:tags":[
        "wholesaler"
    ],
    "wof:name":"Haymans Electrical",
    "wof:placetype":"venue"
},
  "geometry": {"coordinates":[151.26942443900001,-27.1787586212],"type":"Point"}
}