{
  "type": "Feature",
  "properties": {
    "addr:full":"2/30 Metro Court Gateshead NSW 2290",
    "addr:housenumber":"/ 30",
    "addr:postcode":"2290",
    "addr:street":"Metro Court",
    "iso:country":"AU",
    "sg:address":"2/30 Metro Court",
    "sg:city":"Gateshead",
    "sg:classifiers":[
        {
            "category":"Shopping",
            "subcategory":"Computers & Home Electronics",
            "type":"Retail Goods"
        }
    ],
    "sg:phone":"+61 2 4943 0400",
    "sg:postcode":"2290",
    "sg:province":"NSW",
    "sg:tags":[
        "hi-fi",
        "equipment"
    ],
    "wof:name":"Anderson Terry Hi Fi",
    "wof:placetype":"venue"
},
  "geometry": {"coordinates":[151.69720459000001,-32.9613761902],"type":"Point"}
}