{
  "type": "Feature",
  "properties": {
    "iso:country":"AU",
    "sg:address":"12 Leichhardt St",
    "sg:city":"North Ward",
    "sg:classifiers":[
        {
            "category":"Education",
            "subcategory":"Kindergarten",
            "type":"Public Place"
        }
    ],
    "sg:phone":"+61 7 4721 3983",
    "sg:postcode":"4810",
    "sg:province":"QLD",
    "sg:tags":[
        "pre-schools"
    ],
    "wof:name":"Mike Reynolds Early Childhood Centre The",
    "wof:placetype":"venue"
},
  "geometry": {"coordinates":[146.815735,-19.252226],"type":"Point"}
}