{
  "type": "Feature",
  "properties": {
    "addr:full":"115 Burdoo Drv Grovedale VIC 3216",
    "addr:housenumber":"115",
    "addr:postcode":"3216",
    "addr:street":"Burdoo Drv",
    "iso:country":"AU",
    "sg:address":"115 Burdoo Drv",
    "sg:city":"Grovedale",
    "sg:classifiers":[
        {
            "category":"Health Services",
            "subcategory":"Doctor",
            "type":"Services"
        }
    ],
    "sg:phone":"+61 3 5243 7260",
    "sg:postcode":"3216",
    "sg:province":"VIC",
    "sg:tags":[
        "medical",
        "practitioner"
    ],
    "wof:name":"Burdoo Drive Medical Clinic",
    "wof:placetype":"venue"
},
  "geometry": {"coordinates":[144.33062744099999,-38.2068443298],"type":"Point"}
}