{
  "type": "Feature",
  "properties": {
    "iso:country":"AU",
    "sg:address":"Colgate Professional Suite, 2nd Floor Adelaide Den",
    "sg:city":"Adelaide",
    "sg:classifiers":[
        {
            "category":"Health Services",
            "subcategory":"Dentist",
            "type":"Services"
        }
    ],
    "sg:phone":"+61 8 8303 3437",
    "sg:postcode":"5000",
    "sg:province":"SA",
    "wof:name":"Chen Sam Dr",
    "wof:placetype":"venue"
},
  "geometry": {"coordinates":[138.60780334500001,-34.9211273193],"type":"Point"}
}