{
  "type": "Feature",
  "properties": {
    "addr:full":"2 Slaney Pl Chermside West QLD 4032",
    "addr:housenumber":"2",
    "addr:postcode":"4032",
    "addr:street":"Slaney Pl",
    "iso:country":"AU",
    "sg:address":"2 Slaney Pl",
    "sg:city":"Chermside West",
    "sg:classifiers":[
        {
            "category":"Cafe",
            "type":"Food & Drink"
        }
    ],
    "sg:phone":"+61 7 3863 4400",
    "sg:postcode":"4032",
    "sg:province":"QLD",
    "wof:name":"Serendib Teas",
    "wof:placetype":"venue"
},
  "geometry": {"coordinates":[153.00266999999999,-27.374598],"type":"Point"}
}