{
  "type": "Feature",
  "properties": {
    "addr:full":"43 Salt St Concord NSW 2137",
    "addr:housenumber":"43",
    "addr:postcode":"2137",
    "addr:street":"Salt St",
    "iso:country":"AU",
    "sg:address":"43 Salt St",
    "sg:city":"Concord",
    "sg:classifiers":[
        {
            "category":"Professional",
            "subcategory":"Engineering",
            "type":"Services"
        }
    ],
    "sg:phone":"+61 2 9743 5266",
    "sg:postcode":"2137",
    "sg:province":"NSW",
    "sg:tags":[
        "engineer",
        "structural"
    ],
    "wof:name":"Astroc Structural Engineering",
    "wof:placetype":"venue"
},
  "geometry": {"coordinates":[151.11260986299999,-33.8555412292],"type":"Point"}
}