{
  "type": "Feature",
  "properties": {
    "addr:full":"Warrego Hwy Blacksoil QLD 4306",
    "addr:postcode":"4306",
    "addr:street":"Warrego Hwy",
    "iso:country":"AU",
    "sg:address":"Warrego Hwy",
    "sg:city":"Blacksoil",
    "sg:classifiers":[
        {
            "category":"Shopping",
            "type":"Retail Goods"
        }
    ],
    "sg:phone":"+61 7 3201 8366",
    "sg:postcode":"4306",
    "sg:province":"QLD",
    "sg:tags":[
        "produce",
        "grain"
    ],
    "wof:name":"Stocks Produce Qld",
    "wof:placetype":"venue"
},
  "geometry": {"coordinates":[152.70121765100001,-27.576171875],"type":"Point"}
}