{
  "type": "Feature",
  "properties": {
    "addr:full":"51 Lancaster St Ingleburn NSW 2565",
    "addr:housenumber":"51",
    "addr:postcode":"2565",
    "addr:street":"Lancaster St",
    "iso:country":"AU",
    "sg:address":"51 Lancaster St",
    "sg:city":"Ingleburn",
    "sg:classifiers":[
        {
            "category":"Home & Garden",
            "subcategory":"Building Materials",
            "type":"Retail Goods"
        }
    ],
    "sg:phone":"+61 2 9605 1955",
    "sg:postcode":"2565",
    "sg:province":"NSW",
    "sg:tags":[
        "concrete",
        "gutter",
        "kerb"
    ],
    "wof:name":"South West Kerbing Pty Limited",
    "wof:placetype":"venue"
},
  "geometry": {"coordinates":[150.858078003,-33.9981918335],"type":"Point"}
}