{
  "type": "Feature",
  "properties": {
    "addr:full":"10 Fifty Rd Baldivis WA 6171",
    "addr:housenumber":"10",
    "addr:postcode":"6171",
    "addr:street":"Fifty Rd",
    "iso:country":"AU",
    "sg:address":"10 Fifty Rd",
    "sg:city":"Baldivis",
    "sg:classifiers":[
        {
            "category":"Farming",
            "subcategory":"Farm & Veterinary Services",
            "type":"Manufacturing & Wholesale Goods"
        }
    ],
    "sg:phone":"+61 8 9524 1441",
    "sg:postcode":"6171",
    "sg:province":"WA",
    "sg:tags":[
        "irrigation",
        "reticulation",
        "system"
    ],
    "wof:name":"Poly Pipe Traders",
    "wof:placetype":"venue"
},
  "geometry": {"coordinates":[115.80587800000001,-32.322636],"type":"Point"}
}