{
  "type": "Feature",
  "properties": {
    "addr:full":"634 Glenhuntly Rd Caulfield VIC 3162",
    "addr:housenumber":"634",
    "addr:postcode":"3162",
    "addr:street":"Glenhuntly Rd",
    "iso:country":"AU",
    "sg:address":"634 Glenhuntly Rd",
    "sg:city":"Caulfield",
    "sg:classifiers":[
        {
            "category":"Personal",
            "subcategory":"Beauty Salon",
            "type":"Services"
        }
    ],
    "sg:phone":"+61 3 9528 5963",
    "sg:postcode":"3162",
    "sg:province":"VIC",
    "sg:tags":[
        "hairdresser"
    ],
    "wof:name":"European Touch Hair Beauty",
    "wof:placetype":"venue"
},
  "geometry": {"coordinates":[145.01573181099999,-37.8862342834],"type":"Point"}
}