{
  "type": "Feature",
  "properties": {
    "addr:full":"26 Carter St Homebush Bay NSW 2127",
    "addr:housenumber":"26",
    "addr:postcode":"2127",
    "addr:street":"Carter St Homebush",
    "iso:country":"AU",
    "sg:address":"26 Carter St",
    "sg:city":"Homebush Bay",
    "sg:classifiers":[
        {
            "category":"Building & Trades",
            "subcategory":"Construction",
            "type":"Services"
        }
    ],
    "sg:phone":"+61 2 9737 8855",
    "sg:postcode":"2127",
    "sg:province":"NSW",
    "sg:tags":[
        "course",
        "golf",
        "equipment"
    ],
    "wof:name":"Club Car",
    "wof:placetype":"venue"
},
  "geometry": {"coordinates":[151.06187439000001,-33.8524208069],"type":"Point"}
}