{
  "type": "Feature",
  "properties": {
    "addr:full":"PO Box 4805 Toowoomba East QLD 4350",
    "addr:postcode":"4350",
    "iso:country":"AU",
    "sg:address":"PO Box 4805",
    "sg:city":"Toowoomba East",
    "sg:classifiers":[
        {
            "category":"Retail",
            "subcategory":"Storage",
            "type":"Services"
        }
    ],
    "sg:phone":"+61 7 4633 1103",
    "sg:postcode":"4350",
    "sg:province":"QLD",
    "wof:name":"Master Storage",
    "wof:placetype":"venue"
},
  "geometry": {"coordinates":[151.868683,-27.564619],"type":"Point"}
}