{
  "type": "Feature",
  "properties": {
    "addr:full":"Falls Rd Falls Creek NSW 2540",
    "addr:postcode":"2540",
    "addr:street":"Falls Rd",
    "iso:country":"AU",
    "sg:address":"Falls Rd",
    "sg:city":"Falls Creek",
    "sg:classifiers":[
        {
            "category":"Recreation",
            "type":"Entertainment"
        }
    ],
    "sg:phone":"+61 2 4447 8320",
    "sg:postcode":"2540",
    "sg:province":"NSW",
    "sg:tags":[
        "supply",
        "outdoor",
        "adventure",
        "activity"
    ],
    "wof:name":"Valhalla Horse Riding & Farm Holidays",
    "wof:placetype":"venue"
},
  "geometry": {"coordinates":[150.59523010300001,-34.9718360901],"type":"Point"}
}