{
  "type": "Feature",
  "properties": {
    "iso:country":"AU",
    "sg:address":"Suite 1/ 120 Upper Heidelberg Rd",
    "sg:city":"Ivanhoe",
    "sg:classifiers":[
        {
            "category":"Personal",
            "subcategory":"Skin Care",
            "type":"Services"
        }
    ],
    "sg:phone":"+61 3 9497 2922",
    "sg:postcode":"3079",
    "sg:province":"VIC",
    "sg:tags":[
        "treatment"
    ],
    "wof:name":"A.A.Advanced Skin Therapy",
    "wof:placetype":"venue"
},
  "geometry": {"coordinates":[145.042144775,-37.7691650391],"type":"Point"}
}