{
  "type": "Feature",
  "properties": {
    "addr:full":"74 Fairview Ave Newtown VIC 3220",
    "addr:housenumber":"74",
    "addr:postcode":"3220",
    "addr:street":"Fairview Ave",
    "iso:country":"AU",
    "sg:address":"74 Fairview Ave",
    "sg:city":"Newtown",
    "sg:classifiers":[
        {
            "category":"Farming",
            "subcategory":"Nursery",
            "type":"Manufacturing & Wholesale Goods"
        }
    ],
    "sg:phone":"+61 3 5221 7968",
    "sg:postcode":"3220",
    "sg:province":"VIC",
    "wof:name":"The Olive Tree Man",
    "wof:placetype":"venue"
},
  "geometry": {"coordinates":[144.33880600000001,-38.154549],"type":"Point"}
}