{
  "type": "Feature",
  "properties": {
    "addr:full":"8 Inverness St Malaga WA 6090",
    "addr:housenumber":"8",
    "addr:postcode":"6090",
    "addr:street":"Inverness St",
    "iso:country":"AU",
    "sg:address":"8 Inverness St",
    "sg:city":"Malaga",
    "sg:classifiers":[
        {
            "category":"Retail",
            "subcategory":"Auto Repair",
            "type":"Services"
        }
    ],
    "sg:phone":"+61 8 9249 6299",
    "sg:postcode":"6090",
    "sg:province":"WA",
    "sg:tags":[
        "beater",
        "painter",
        "panel"
    ],
    "wof:name":"Jack's Panel Beating",
    "wof:placetype":"venue"
},
  "geometry": {"coordinates":[115.88362121599999,-31.8552837372],"type":"Point"}
}