{
  "type": "Feature",
  "properties": {
    "addr:full":"132 Hammond Ave Wagga Wagga NSW 2650",
    "addr:housenumber":"132",
    "addr:postcode":"2650",
    "addr:street":"Hammond Ave",
    "iso:country":"AU",
    "sg:address":"132 Hammond Ave",
    "sg:city":"Wagga Wagga",
    "sg:classifiers":[
        {
            "category":"Manufacturing",
            "subcategory":"Motor Vehicles & Parts",
            "type":"Manufacturing & Wholesale Goods"
        }
    ],
    "sg:phone":"+61 2 6921 6044",
    "sg:postcode":"2650",
    "sg:province":"NSW",
    "sg:tags":[
        "engine",
        "equipment",
        "diesel"
    ],
    "wof:name":"R.W. International Parts Pty Ltd",
    "wof:placetype":"venue"
},
  "geometry": {"coordinates":[147.396484375,-35.1228141785],"type":"Point"}
}