{
  "type": "Feature",
  "properties": {
    "iso:country":"AU",
    "sg:address":"Rm2/ Dennistoun Ave",
    "sg:city":"Guildford",
    "sg:classifiers":[
        {
            "category":"Professional",
            "type":"Services"
        }
    ],
    "sg:phone":"+61 2 9892 2090",
    "sg:postcode":"2161",
    "sg:province":"NSW",
    "sg:tags":[
        "buyer",
        "merchant",
        "wool"
    ],
    "wof:name":"Wooltrade Australia Pty Ltd",
    "wof:placetype":"venue"
},
  "geometry": {"coordinates":[150.976104736,-33.8566932678],"type":"Point"}
}