{
  "type": "Feature",
  "properties": {
    "iso:country":"AU",
    "sg:address":"13 Tedder Ave",
    "sg:city":"Main Beach",
    "sg:classifiers":[
        {
            "category":"Professional",
            "subcategory":"Art Services",
            "type":"Services"
        }
    ],
    "sg:phone":"+61 7 5527 1856",
    "sg:postcode":"4217",
    "sg:province":"QLD",
    "sg:tags":[
        "interior",
        "decorator"
    ],
    "wof:name":"Indeco Design",
    "wof:placetype":"venue"
},
  "geometry": {"coordinates":[153.424926758,-27.9803066254],"type":"Point"}
}