{
  "type": "Feature",
  "properties": {
    "addr:full":"2 Epsom Rd Alexandria NSW 2015",
    "addr:housenumber":"2",
    "addr:postcode":"2015",
    "addr:street":"Epsom Rd",
    "iso:country":"AU",
    "sg:address":"2 Epsom Rd",
    "sg:city":"Alexandria",
    "sg:classifiers":[
        {
            "category":"Professional",
            "subcategory":"Art Services",
            "type":"Services"
        }
    ],
    "sg:phone":"+61 2 9697 2008",
    "sg:postcode":"2015",
    "sg:province":"NSW",
    "sg:tags":[
        "picture",
        "frame",
        "framing"
    ],
    "wof:name":"Master Framing",
    "wof:placetype":"venue"
},
  "geometry": {"coordinates":[151.20291137699999,-33.9101104736],"type":"Point"}
}