{
  "type": "Feature",
  "properties": {
    "addr:full":"7 Gleneden Crt The Gap QLD 4061",
    "addr:housenumber":"7",
    "addr:postcode":"4061",
    "addr:street":"Gleneden Crt",
    "iso:country":"AU",
    "sg:address":"7 Gleneden Crt",
    "sg:city":"The Gap",
    "sg:classifiers":[
        {
            "category":"Government",
            "subcategory":"Post Office",
            "type":"Public Place"
        }
    ],
    "sg:phone":"+61 7 3300 5252",
    "sg:postcode":"4061",
    "sg:province":"QLD",
    "sg:tags":[
        "house",
        "doll"
    ],
    "wof:name":"National Original Doll Artists Association Of Australia (Inc)",
    "wof:placetype":"venue"
},
  "geometry": {"coordinates":[152.934616089,-27.4406661987],"type":"Point"}
}