{
  "type": "Feature",
  "properties": {
    "addr:full":"15b Holt St Eagle Farm QLD 4009",
    "addr:housenumber":"15b",
    "addr:postcode":"4009",
    "addr:street":"Holt St",
    "iso:country":"AU",
    "sg:address":"15b Holt St",
    "sg:city":"Eagle Farm",
    "sg:classifiers":[
        {
            "category":"Banks & Credit Unions",
            "subcategory":"Atm",
            "type":"Services"
        }
    ],
    "sg:phone":"+61 7 3268 4358",
    "sg:postcode":"4009",
    "sg:province":"QLD",
    "sg:tags":[
        "reconditioners",
        "drum",
        "manufacturers"
    ],
    "wof:name":"Visy Industrial Packaging",
    "wof:placetype":"venue"
},
  "geometry": {"coordinates":[153.10188293499999,-27.4291534424],"type":"Point"}
}