{
  "type": "Feature",
  "properties": {
    "iso:country":"AU",
    "sg:address":"252 Jenkins Ave",
    "sg:city":"Whyalla Stuart",
    "sg:classifiers":[
        {
            "category":"Building & Trades",
            "subcategory":"Landscaping Services",
            "type":"Services"
        }
    ],
    "sg:phone":"+61 8 8649 1891",
    "sg:postcode":"5608",
    "sg:province":"SA",
    "sg:tags":[
        "control",
        "weed"
    ],
    "wof:name":"Household Pest & Weed Control",
    "wof:placetype":"venue"
},
  "geometry": {"coordinates":[137.52177399999999,-33.018345],"type":"Point"}
}