{
  "type": "Feature",
  "properties": {
    "iso:country":"AU",
    "sg:address":"100 Beveridge St",
    "sg:city":"Swan Hill",
    "sg:classifiers":[
        {
            "category":"Social Services",
            "subcategory":"Child Care",
            "type":"Services"
        }
    ],
    "sg:phone":"+61 3 5033 2859",
    "sg:postcode":"3585",
    "sg:province":"VIC",
    "wof:name":"Little Tykes Day Care",
    "wof:placetype":"venue"
},
  "geometry": {"coordinates":[143.55770899999999,-35.3381],"type":"Point"}
}