{
  "type": "Feature",
  "properties": {
    "iso:country":"AU",
    "sg:address":"Shp 1/ 19 Arabin St",
    "sg:city":"Keilor",
    "sg:classifiers":[
        {
            "category":"Personal",
            "subcategory":"Massage",
            "type":"Services"
        }
    ],
    "sg:phone":"+61 3 9331 7707",
    "sg:postcode":"3036",
    "sg:province":"VIC",
    "sg:tags":[
        "therapy"
    ],
    "wof:name":"Get Well Body Therapy",
    "wof:placetype":"venue"
},
  "geometry": {"coordinates":[144.835983,-37.718761],"type":"Point"}
}