{
  "type": "Feature",
  "properties": {
    "addr:full":"2 Seven Hills Rd Seven Hills NSW 2147",
    "addr:housenumber":"2",
    "addr:postcode":"2147",
    "addr:street":"Seven Hills Rd",
    "iso:country":"AU",
    "sg:address":"2 Seven Hills Rd",
    "sg:city":"Seven Hills",
    "sg:classifiers":[
        {
            "category":"Utilities",
            "subcategory":"Electric",
            "type":"Services"
        }
    ],
    "sg:phone":"+61 414 539 454",
    "sg:postcode":"2147",
    "sg:province":"NSW",
    "sg:tags":[
        "electrical",
        "contractor"
    ],
    "wof:name":"GFK Electrical",
    "wof:placetype":"venue"
},
  "geometry": {"coordinates":[150.94430542000001,-33.7672271729],"type":"Point"}
}