{
  "type": "Feature",
  "properties": {
    "iso:country":"AU",
    "sg:address":"Level 4, 316 Adelaide St",
    "sg:city":"Brisbane",
    "sg:classifiers":[
        {
            "category":"Transit Center",
            "subcategory":"Freight",
            "type":"Transportation"
        }
    ],
    "sg:phone":"+61 7 3237 7377",
    "sg:postcode":"4000",
    "sg:province":"QLD",
    "sg:tags":[
        "agent",
        "shipping"
    ],
    "wof:name":"Evergreen Marine Australia Pty Ltd",
    "wof:placetype":"venue"
},
  "geometry": {"coordinates":[153.029205322,-27.4650058746],"type":"Point"}
}