{
  "type": "Feature",
  "properties": {
    "addr:full":"23 Bardolph St Bonython ACT 2905",
    "addr:housenumber":"23",
    "addr:postcode":"2905",
    "addr:street":"Bardolph St",
    "iso:country":"AU",
    "sg:address":"23 Bardolph St",
    "sg:city":"Bonython",
    "sg:classifiers":[
        {
            "category":"Professional",
            "subcategory":"Management & Consulting",
            "type":"Services"
        }
    ],
    "sg:phone":"+61 2 6293 1760",
    "sg:postcode":"2905",
    "sg:province":"ACT",
    "sg:tags":[
        "consultant",
        "educational"
    ],
    "wof:name":"Home Education Network, Canberra",
    "wof:placetype":"venue"
},
  "geometry": {"coordinates":[149.086227417,-35.4325256348],"type":"Point"}
}