{
  "type": "Feature",
  "properties": {
    "iso:country":"AU",
    "sg:address":"GPO Box 733",
    "sg:city":"Hobart",
    "sg:classifiers":[
        {
            "category":"Professional",
            "subcategory":"Management & Consulting",
            "type":"Services"
        }
    ],
    "sg:phone":"+61 3 6224 9949",
    "sg:postcode":"7001",
    "sg:province":"TAS",
    "sg:tags":[
        "consultant"
    ],
    "wof:name":"T D T Logic",
    "wof:placetype":"venue"
},
  "geometry": {"coordinates":[147.51083374000001,-42.8352508545],"type":"Point"}
}