{
  "type": "Feature",
  "properties": {
    "addr:full":"63 Princess Rd Claremont WA 6010",
    "addr:housenumber":"63",
    "addr:postcode":"6010",
    "addr:street":"Princess Rd",
    "iso:country":"AU",
    "sg:address":"63 Princess Rd",
    "sg:city":"Claremont",
    "sg:classifiers":[
        {
            "category":"Social Services",
            "subcategory":"Job Training",
            "type":"Services"
        }
    ],
    "sg:phone":"+61 8 9384 9920",
    "sg:postcode":"6010",
    "sg:province":"WA",
    "sg:tags":[
        "sport"
    ],
    "wof:name":"Kidz &#039;n Sport",
    "wof:placetype":"venue"
},
  "geometry": {"coordinates":[115.787437439,-31.9862747192],"type":"Point"}
}