{
  "type": "Feature",
  "properties": {
    "iso:country":"AU",
    "sg:address":"Southwest Sports Centre, Hay Park, Bussell Hwy",
    "sg:city":"Bunbury",
    "sg:classifiers":[
        {
            "category":"Personal",
            "subcategory":"Beauty Salon",
            "type":"Services"
        }
    ],
    "sg:phone":"+61 8 9795 5777",
    "sg:postcode":"6230",
    "sg:province":"WA",
    "wof:name":"Smooth Synergy",
    "wof:placetype":"venue"
},
  "geometry": {"coordinates":[115.645798,-33.379936],"type":"Point"}
}