{
  "type": "Feature",
  "properties": {
    "addr:full":"200 Rooks Rd Nunawading VIC 3131",
    "addr:housenumber":"200",
    "addr:postcode":"3131",
    "addr:street":"Rooks Rd",
    "iso:country":"AU",
    "sg:address":"200 Rooks Rd",
    "sg:city":"Nunawading",
    "sg:classifiers":[
        {
            "category":"Education",
            "subcategory":"Dance Studio",
            "type":"Public Place"
        }
    ],
    "sg:phone":"+61 3 9874 8711",
    "sg:postcode":"3131",
    "sg:province":"VIC",
    "sg:tags":[
        "venue",
        "tuition"
    ],
    "wof:name":"MarShere Dance Studios",
    "wof:placetype":"venue"
},
  "geometry": {"coordinates":[145.187210083,-37.8321037292],"type":"Point"}
}