{
  "type": "Feature",
  "properties": {
    "addr:full":"30 Algona St Bilgola Plateau NSW 2107",
    "addr:housenumber":"30",
    "addr:postcode":"2107",
    "addr:street":"Algona St",
    "iso:country":"AU",
    "sg:address":"30 Algona St",
    "sg:city":"Bilgola Plateau",
    "sg:classifiers":[
        {
            "category":"Personal",
            "subcategory":"Massage",
            "type":"Services"
        }
    ],
    "sg:phone":"+61 2 9973 1173",
    "sg:postcode":"2107",
    "sg:province":"NSW",
    "sg:tags":[
        "therapy"
    ],
    "wof:name":"Lance Glynis",
    "wof:placetype":"venue"
},
  "geometry": {"coordinates":[151.311447144,-33.6499671936],"type":"Point"}
}