{
  "type": "Feature",
  "properties": {
    "addr:full":"70 Battery Rd Beaconsfield TAS 7270",
    "addr:housenumber":"70",
    "addr:postcode":"7270",
    "addr:street":"Battery Rd",
    "iso:country":"AU",
    "sg:address":"70 Battery Rd",
    "sg:city":"Beaconsfield",
    "sg:classifiers":[
        {
            "category":"Home & Garden",
            "subcategory":"Building Materials",
            "type":"Retail Goods"
        }
    ],
    "sg:phone":"+61 418 364 442",
    "sg:postcode":"7270",
    "sg:province":"TAS",
    "sg:tags":[
        "lawn",
        "cutting",
        "maintenance"
    ],
    "wof:name":"Time for Todd",
    "wof:placetype":"venue"
},
  "geometry": {"coordinates":[146.8331604,-41.203327179],"type":"Point"}
}