{
  "type": "Feature",
  "properties": {
    "addr:full":"1 Arcadia St Warilla NSW 2528",
    "addr:housenumber":"1",
    "addr:postcode":"2528",
    "addr:street":"Arcadia St",
    "iso:country":"AU",
    "sg:address":"1 Arcadia St",
    "sg:city":"Warilla",
    "sg:classifiers":[
        {
            "category":"Social Services",
            "subcategory":"Adult Care",
            "type":"Services"
        }
    ],
    "sg:phone":"+61 2 4297 0999",
    "sg:postcode":"2528",
    "sg:province":"NSW",
    "sg:tags":[
        "aged"
    ],
    "wof:name":"Warrigal Care",
    "wof:placetype":"venue"
},
  "geometry": {"coordinates":[150.86297607399999,-34.552986145],"type":"Point"}
}