{
  "type": "Feature",
  "properties": {
    "iso:country":"AU",
    "sg:address":"73 Bentinck St",
    "sg:city":"Portland",
    "sg:classifiers":[
        {
            "category":"Shopping",
            "subcategory":"Luggage & Leather Goods",
            "type":"Retail Goods"
        }
    ],
    "sg:phone":"+61 3 5523 6990",
    "sg:postcode":"3305",
    "sg:province":"VIC",
    "wof:name":"Lineker Leather",
    "wof:placetype":"venue"
},
  "geometry": {"coordinates":[141.60606384299999,-38.3491744995],"type":"Point"}
}