{
  "type": "Feature",
  "properties": {
    "iso:country":"AU",
    "sg:address":"2 Wey St",
    "sg:city":"Blackwater",
    "sg:classifiers":[
        {
            "category":"Retail",
            "subcategory":"Car Wash",
            "type":"Services"
        }
    ],
    "sg:phone":"+61 7 4982 7977",
    "sg:postcode":"4717",
    "sg:province":"QLD",
    "sg:tags":[
        "merchant",
        "oil",
        "refiner"
    ],
    "wof:name":"Techenomics Pty Ltd",
    "wof:placetype":"venue"
},
  "geometry": {"coordinates":[148.87953200000001,-23.583178],"type":"Point"}
}