{
  "type": "Feature",
  "properties": {
    "addr:full":"Shop 1, 12 Victoria St Coburg VIC 3058",
    "addr:housenumber":"shop;12",
    "addr:postcode":"3058",
    "addr:street":"Victoria St",
    "iso:country":"AU",
    "sg:address":"Shop 1, 12 Victoria St",
    "sg:city":"Coburg",
    "sg:classifiers":[
        {
            "category":"Food & Beverages",
            "subcategory":"Specialty",
            "type":"Retail Goods"
        }
    ],
    "sg:phone":"+61 3 9354 8519",
    "sg:postcode":"3058",
    "sg:province":"VIC",
    "sg:tags":[
        "product",
        "health"
    ],
    "wof:name":"The Original Fruit and Nut Wholesalers",
    "wof:placetype":"venue"
},
  "geometry": {"coordinates":[144.965866089,-37.7429924011],"type":"Point"}
}