{
  "type": "Feature",
  "properties": {
    "iso:country":"AU",
    "sg:address":"58 Hesse St",
    "sg:city":"Queenscliff",
    "sg:classifiers":[
        {
            "category":"Personal",
            "subcategory":"Day Spa",
            "type":"Services"
        }
    ],
    "sg:phone":"+61 3 5258 4738",
    "sg:postcode":"3225",
    "sg:province":"VIC",
    "wof:name":"Hepburn Queenscliff",
    "wof:placetype":"venue"
},
  "geometry": {"coordinates":[144.660767,-38.267677],"type":"Point"}
}