{
  "type": "Feature",
  "properties": {
    "addr:full":"147 Queen Cleveland QLD 4163",
    "addr:housenumber":"147",
    "addr:postcode":"4163",
    "addr:street":"Queen",
    "iso:country":"AU",
    "sg:address":"147 Queen",
    "sg:city":"Cleveland",
    "sg:classifiers":[
        {
            "category":"Health Services",
            "subcategory":"Optometrist",
            "type":"Services"
        }
    ],
    "sg:phone":"+61 7 3286 5000",
    "sg:postcode":"4163",
    "sg:province":"QLD",
    "wof:name":"Angelos Nick",
    "wof:placetype":"venue"
},
  "geometry": {"coordinates":[153.26495361299999,-27.5279884338],"type":"Point"}
}