{
  "type": "Feature",
  "properties": {
    "addr:full":"14 Burgess St Raceview QLD 4305",
    "addr:housenumber":"14",
    "addr:postcode":"4305",
    "addr:street":"Burgess St",
    "iso:country":"AU",
    "sg:address":"14 Burgess St",
    "sg:city":"Raceview",
    "sg:classifiers":[
        {
            "category":"Donuts",
            "subcategory":"None",
            "type":"Food & Drink"
        }
    ],
    "sg:phone":"+61 417 754 553",
    "sg:postcode":"4305",
    "sg:province":"QLD",
    "sg:tags":[
        "die",
        "engraver",
        "sinker"
    ],
    "wof:name":"J & D Computerised Engraving Services",
    "wof:placetype":"venue"
},
  "geometry": {"coordinates":[152.783294678,-27.6424293518],"type":"Point"}
}