{
  "type": "Feature",
  "properties": {
    "iso:country":"AU",
    "sg:address":"334 Henley Beach Rd",
    "sg:city":"Lockleys",
    "sg:classifiers":[
        {
            "category":"Building & Trades",
            "subcategory":"Landscaping Services",
            "type":"Services"
        }
    ],
    "sg:phone":"+61 8 8234 2270",
    "sg:postcode":"5032",
    "sg:province":"SA",
    "sg:tags":[
        "designer",
        "landscape",
        "contractor"
    ],
    "wof:name":"Lockleys Garden Centre",
    "wof:placetype":"venue"
},
  "geometry": {"coordinates":[138.53890991200001,-34.9267616272],"type":"Point"}
}