{
  "type": "Feature",
  "properties": {
    "iso:country":"AU",
    "sg:address":"2 Yarrara Rd",
    "sg:city":"Pymble",
    "sg:classifiers":[
        {
            "category":"Manufacturing",
            "subcategory":"Textiles",
            "type":"Manufacturing & Wholesale Goods"
        }
    ],
    "sg:phone":"+61 2 9449 6157",
    "sg:postcode":"2073",
    "sg:province":"NSW",
    "sg:tags":[
        "wholesaler",
        "knitwear",
        "mfrs"
    ],
    "wof:name":"Large Sun Pty Ltd",
    "wof:placetype":"venue"
},
  "geometry": {"coordinates":[151.13442993199999,-33.7541351318],"type":"Point"}
}