{
  "type": "Feature",
  "properties": {
    "addr:full":"2 Tyson St South Grafton NSW 2460",
    "addr:housenumber":"2",
    "addr:postcode":"2460",
    "addr:street":"Tyson St",
    "iso:country":"AU",
    "sg:address":"2 Tyson St",
    "sg:city":"South Grafton",
    "sg:classifiers":[
        {
            "category":"Manufacturing",
            "subcategory":"Tools & Machinery",
            "type":"Manufacturing & Wholesale Goods"
        }
    ],
    "sg:phone":"+61 2 6642 8211",
    "sg:postcode":"2460",
    "sg:province":"NSW",
    "sg:tags":[
        "earth",
        "excavating",
        "moving",
        "equipment"
    ],
    "wof:name":"WesTrac",
    "wof:placetype":"venue"
},
  "geometry": {"coordinates":[152.946502686,-29.7236194611],"type":"Point"}
}