{
  "type": "Feature",
  "properties": {
    "addr:full":"Unit 14, 112 Ashford Ave Milperra NSW 2214",
    "addr:housenumber":"112",
    "addr:postcode":"2214",
    "addr:street":"Ashford Ave",
    "iso:country":"AU",
    "sg:address":"Unit 14, 112 Ashford Ave",
    "sg:city":"Milperra",
    "sg:classifiers":[
        {
            "category":"Wholesale",
            "subcategory":"Electrical",
            "type":"Manufacturing & Wholesale Goods"
        }
    ],
    "sg:phone":"+61 2 9792 1293",
    "sg:postcode":"2214",
    "sg:province":"NSW",
    "sg:tags":[
        "control",
        "equipment",
        "switch"
    ],
    "wof:name":"Artisan Switchboards Pty Ltd",
    "wof:placetype":"venue"
},
  "geometry": {"coordinates":[150.989182,-33.937435],"type":"Point"}
}