{
  "type": "Feature",
  "properties": {
    "addr:full":"47 Park Rd Milton QLD 4064",
    "addr:housenumber":"47",
    "addr:postcode":"4064",
    "addr:street":"Park Rd",
    "iso:country":"AU",
    "sg:address":"47 Park Rd",
    "sg:city":"Milton",
    "sg:classifiers":[
        {
            "category":"Health Services",
            "subcategory":"Health Practitioner",
            "type":"Services"
        }
    ],
    "sg:phone":"+61 7 3816 0064",
    "sg:postcode":"4064",
    "sg:province":"QLD",
    "sg:tags":[
        "psychologist"
    ],
    "wof:name":"Australian Psychological Society College of Clinical Psychologists",
    "wof:placetype":"venue"
},
  "geometry": {"coordinates":[153.00486755399999,-27.4717788696],"type":"Point"}
}