{
  "type": "Feature",
  "properties": {
    "iso:country":"AU",
    "sg:address":"449A Main Rd",
    "sg:city":"Coromandel Valley",
    "sg:classifiers":[
        {
            "category":"Building & Trades",
            "subcategory":"Landscaping Services",
            "type":"Services"
        }
    ],
    "sg:phone":"+61 438 701 582",
    "sg:postcode":"5051",
    "sg:province":"SA",
    "sg:tags":[
        "designer",
        "landscape",
        "contractor"
    ],
    "wof:name":"Michael Wright Landscaping",
    "wof:placetype":"venue"
},
  "geometry": {"coordinates":[138.61998,-35.050404],"type":"Point"}
}