{
  "type": "Feature",
  "properties": {
    "addr:full":"4/1 Terminus St Castle Hill NSW 2154",
    "addr:housenumber":"/ 1",
    "addr:postcode":"2154",
    "addr:street":"Terminus St",
    "iso:country":"AU",
    "sg:address":"4/1 Terminus St",
    "sg:city":"Castle Hill",
    "sg:classifiers":[
        {
            "category":"Health Services",
            "subcategory":"Health Practitioner",
            "type":"Services"
        }
    ],
    "sg:phone":"+61 2 9634 7788",
    "sg:postcode":"2154",
    "sg:province":"NSW",
    "sg:tags":[
        "physiotherapist"
    ],
    "wof:name":"Dessen Michael",
    "wof:placetype":"venue"
},
  "geometry": {"coordinates":[151.00689697300001,-33.7331581116],"type":"Point"}
}