{
  "type": "Feature",
  "properties": {
    "iso:country":"AU",
    "sg:address":"Thorpdale St",
    "sg:city":"Thorpdale",
    "sg:classifiers":[
        {
            "category":"Farming",
            "subcategory":"Farm",
            "type":"Manufacturing & Wholesale Goods"
        }
    ],
    "sg:phone":"+61 3 5634 6231",
    "sg:postcode":"3835",
    "sg:province":"VIC",
    "sg:tags":[
        "farmer"
    ],
    "wof:name":"Manley J G",
    "wof:placetype":"venue"
},
  "geometry": {"coordinates":[146.17465200000001,-38.305519],"type":"Point"}
}