{
  "type": "Feature",
  "properties": {
    "addr:full":"Shop 16 Winthrop Vlge Winthrop WA 6150",
    "addr:housenumber":"shop 16",
    "addr:postcode":"6150",
    "addr:street":"Winthrop Vlge",
    "iso:country":"AU",
    "sg:address":"Shop 16",
    "sg:city":"Winthrop Vlge Winthrop",
    "sg:classifiers":[
        {
            "category":"Retail",
            "subcategory":"Veterinary Services",
            "type":"Services"
        }
    ],
    "sg:phone":"+61 8 9310 5222",
    "sg:postcode":"6150",
    "sg:province":"WA",
    "sg:tags":[
        "surgeon"
    ],
    "wof:name":"Winthrup Vet",
    "wof:placetype":"venue"
},
  "geometry": {"coordinates":[115.82534,-32.047928],"type":"Point"}
}