{
  "type": "Feature",
  "properties": {
    "addr:full":"Channel Hwy Woodbridge TAS 7162",
    "addr:postcode":"7162",
    "addr:street":"Channel Hwy",
    "iso:country":"AU",
    "sg:address":"Channel Hwy",
    "sg:city":"Woodbridge",
    "sg:classifiers":[
        {
            "category":"Government",
            "subcategory":"Post Office",
            "type":"Public Place"
        }
    ],
    "sg:phone":"+61 3 6267 4630",
    "sg:postcode":"7162",
    "sg:province":"TAS",
    "sg:tags":[
        "postal"
    ],
    "wof:name":"Australia Post Offices",
    "wof:placetype":"venue"
},
  "geometry": {"coordinates":[147.238815308,-43.1600036621],"type":"Point"}
}