{
  "type": "Feature",
  "properties": {
    "iso:country":"AU",
    "sg:address":"463 Swanston St",
    "sg:city":"Melbourne",
    "sg:classifiers":[
        {
            "category":"Cafe",
            "type":"Food & Drink"
        }
    ],
    "sg:phone":"+61 3 9663 6519",
    "sg:postcode":"3000",
    "sg:province":"VIC",
    "wof:name":"Cafe Mimo",
    "wof:placetype":"venue"
},
  "geometry": {"coordinates":[144.96267700199999,-37.8073997498],"type":"Point"}
}