{
  "type": "Feature",
  "properties": {
    "iso:country":"AU",
    "sg:address":"274A Brunswick St",
    "sg:city":"Fitzroy",
    "sg:classifiers":[
        {
            "category":"Personal",
            "subcategory":"Beauty Salon",
            "type":"Services"
        }
    ],
    "sg:phone":"+61 3 9419 1414",
    "sg:postcode":"3065",
    "sg:province":"VIC",
    "wof:name":"Your Indulgence Skin Clinic",
    "wof:placetype":"venue"
},
  "geometry": {"coordinates":[144.97846984899999,-37.7991943359],"type":"Point"}
}