{
  "type": "Feature",
  "properties": {
    "iso:country":"AU",
    "sg:address":"25 Maud St",
    "sg:city":"Geelong",
    "sg:classifiers":[
        {
            "category":"Health Services",
            "subcategory":"Health Practitioner",
            "type":"Services"
        }
    ],
    "sg:phone":"+61 3 5229 8260",
    "sg:postcode":"3220",
    "sg:province":"VIC",
    "sg:tags":[
        "naturopath"
    ],
    "wof:name":"Neil Walker",
    "wof:placetype":"venue"
},
  "geometry": {"coordinates":[144.35415599999999,-38.15337],"type":"Point"}
}