{
  "type": "Feature",
  "properties": {
    "addr:full":"159 Jasper Rd (Next to Bentleigh Library) Bentleigh VIC 3204",
    "addr:housenumber":"159",
    "addr:postcode":"3204",
    "addr:street":"Jasper Rd Next",
    "iso:country":"AU",
    "sg:address":"159 Jasper Rd",
    "sg:city":"(Next to Bentleigh Library) Bentleigh",
    "sg:classifiers":[
        {
            "category":"Health Services",
            "subcategory":"Dentist",
            "type":"Services"
        }
    ],
    "sg:phone":"+61 3 9563 9559",
    "sg:postcode":"3204",
    "sg:province":"VIC",
    "wof:name":"Helena Waks Dr",
    "wof:placetype":"venue"
},
  "geometry": {"coordinates":[145.041428,-37.919212],"type":"Point"}
}