{
  "type": "Feature",
  "properties": {
    "iso:country":"AU",
    "sg:address":"19 Inverloch Rd",
    "sg:city":"Kongwak",
    "sg:classifiers":[
        {
            "category":"Retail",
            "subcategory":"Laundry & Dry Cleaning",
            "type":"Services"
        }
    ],
    "sg:phone":"+61 428 515 616",
    "sg:postcode":"3951",
    "sg:province":"VIC",
    "sg:tags":[
        "truck",
        "tip",
        "contractor"
    ],
    "wof:name":"Webster C A",
    "wof:placetype":"venue"
},
  "geometry": {"coordinates":[145.71116638199999,-38.5147094727],"type":"Point"}
}