{
  "type": "Feature",
  "properties": {
    "addr:full":"1395 Logan Rd Mt Gravatt QLD 4122",
    "addr:housenumber":"1395",
    "addr:postcode":"4122",
    "addr:street":"Logan Rd",
    "iso:country":"AU",
    "sg:address":"1395 Logan Rd",
    "sg:city":"Mt Gravatt",
    "sg:classifiers":[
        {
            "category":"Health Services",
            "subcategory":"Dentist",
            "type":"Services"
        }
    ],
    "sg:phone":"+61 7 3349 2261",
    "sg:postcode":"4122",
    "sg:province":"QLD",
    "wof:name":"Culwick Andrew",
    "wof:placetype":"venue"
},
  "geometry": {"coordinates":[153.07940673799999,-27.5386886597],"type":"Point"}
}