{
  "type": "Feature",
  "properties": {
    "addr:full":"Shop 4, 1459 Point Nepean Rd Rosebud VIC 3939",
    "addr:housenumber":"shop 4 1459",
    "addr:postcode":"3939",
    "addr:street":"Nepean Rd",
    "iso:country":"AU",
    "sg:address":"Shop 4, 1459 Point Nepean Rd",
    "sg:city":"Rosebud",
    "sg:classifiers":[
        {
            "category":"Shopping",
            "subcategory":"Pets & Pet Supplies",
            "type":"Retail Goods"
        }
    ],
    "sg:phone":"+61 3 5986 5288",
    "sg:postcode":"3939",
    "sg:province":"VIC",
    "sg:tags":[
        "food"
    ],
    "wof:name":"Healthy Hounds",
    "wof:placetype":"venue"
},
  "geometry": {"coordinates":[144.88931274399999,-38.3601531982],"type":"Point"}
}