{
  "type": "Feature",
  "properties": {
    "addr:full":"Unit 29/2- 8 Gray St Kilkenny SA 5009",
    "addr:housenumber":"/ 2 8",
    "addr:postcode":"5009",
    "addr:street":"Gray St",
    "iso:country":"AU",
    "sg:address":"Unit 29/2- 8 Gray St",
    "sg:city":"Kilkenny",
    "sg:classifiers":[
        {
            "category":"Professional",
            "subcategory":"Engineering",
            "type":"Services"
        }
    ],
    "sg:phone":"+61 8 8243 2300",
    "sg:postcode":"5009",
    "sg:province":"SA",
    "sg:tags":[
        "manufacturing",
        "engineer"
    ],
    "wof:name":"Winmec Engineering",
    "wof:placetype":"venue"
},
  "geometry": {"coordinates":[138.55232238799999,-34.8746185303],"type":"Point"}
}