{
  "type": "Feature",
  "properties": {
    "iso:country":"AU",
    "sg:address":"Suite 4, 41 Glenhuntly Rd",
    "sg:city":"Elwood",
    "sg:classifiers":[
        {
            "category":"Organizations",
            "subcategory":"Professional Association",
            "type":"Services"
        }
    ],
    "sg:phone":"+61 3 9531 4703",
    "sg:postcode":"3184",
    "sg:province":"VIC",
    "sg:tags":[
        "organisation",
        "business"
    ],
    "wof:name":"Federation Of Wall & Ceiling Contractors Of Australia & New Zealand",
    "wof:placetype":"venue"
},
  "geometry": {"coordinates":[144.99261474599999,-37.8833045959],"type":"Point"}
}