{
  "type": "Feature",
  "properties": {
    "iso:country":"AU",
    "sg:address":"33 Dome Rd",
    "sg:city":"Dorrigo",
    "sg:classifiers":[
        {
            "category":"Professional",
            "subcategory":"Engineering",
            "type":"Services"
        }
    ],
    "sg:phone":"+61 2 6657 1720",
    "sg:postcode":"2453",
    "sg:province":"NSW",
    "sg:tags":[
        "engineer",
        "mechanical"
    ],
    "wof:name":"Pelena Energy",
    "wof:placetype":"venue"
},
  "geometry": {"coordinates":[152.72019958499999,-30.3557796478],"type":"Point"}
}