{
  "type": "Feature",
  "properties": {
    "addr:full":"123 Dalley St Mullumbimby NSW 2482",
    "addr:housenumber":"123",
    "addr:postcode":"2482",
    "addr:street":"Dalley St",
    "iso:country":"AU",
    "sg:address":"123 Dalley St",
    "sg:city":"Mullumbimby",
    "sg:classifiers":[
        {
            "category":"Health Services",
            "subcategory":"Doctor",
            "type":"Services"
        }
    ],
    "sg:phone":"+61 2 6684 2300",
    "sg:postcode":"2482",
    "sg:province":"NSW",
    "sg:tags":[
        "medical",
        "practitioner"
    ],
    "wof:name":"Taylor G",
    "wof:placetype":"venue"
},
  "geometry": {"coordinates":[153.49916076700001,-28.5550346375],"type":"Point"}
}