{
  "type": "Feature",
  "properties": {
    "addr:full":"5- 7 King William Rd Unley SA 5061",
    "addr:housenumber":"7",
    "addr:postcode":"5061",
    "addr:street":"King William Rd",
    "iso:country":"AU",
    "sg:address":"5- 7 King William Rd",
    "sg:city":"Unley",
    "sg:classifiers":[
        {
            "category":"Banks & Credit Unions",
            "subcategory":"Financial Services",
            "type":"Services"
        }
    ],
    "sg:phone":"+61 8 8373 6109",
    "sg:postcode":"5061",
    "sg:province":"SA",
    "sg:tags":[
        "planning"
    ],
    "wof:name":"Genesys Wealth Advisers",
    "wof:placetype":"venue"
},
  "geometry": {"coordinates":[138.600372314,-34.9422073364],"type":"Point"}
}