{
  "type": "Feature",
  "properties": {
    "addr:full":"6 Malmo St Maffra VIC 3860",
    "addr:housenumber":"6",
    "addr:postcode":"3860",
    "addr:street":"Malmo St",
    "iso:country":"AU",
    "sg:address":"6 Malmo St",
    "sg:city":"Maffra",
    "sg:classifiers":[
        {
            "category":"Government",
            "subcategory":"Post Office",
            "type":"Public Place"
        }
    ],
    "sg:phone":"+61 3 5141 1882",
    "sg:postcode":"3860",
    "sg:province":"VIC",
    "sg:tags":[
        "silo"
    ],
    "wof:name":"Vic Silos",
    "wof:placetype":"venue"
},
  "geometry": {"coordinates":[146.996856689,-37.9710655212],"type":"Point"}
}