{
  "type": "Feature",
  "properties": {
    "iso:country":"AU",
    "sg:address":"PO Box 1607",
    "sg:city":"Fremantle Private Boxes",
    "sg:classifiers":[
        {
            "category":"Autos & Motor Vehicles",
            "subcategory":"Boat Sales",
            "type":"Retail Goods"
        }
    ],
    "sg:phone":"+61 408 866 292",
    "sg:postcode":"6959",
    "sg:province":"WA",
    "sg:tags":[
        "equipment",
        "yacht"
    ],
    "wof:name":"All Marine Services",
    "wof:placetype":"venue"
},
  "geometry": {"coordinates":[115.974151611,-32.0679168701],"type":"Point"}
}