{
  "type": "Feature",
  "properties": {
    "iso:country":"AU",
    "sg:address":"32 Douglas Pde",
    "sg:city":"Williamstown",
    "sg:classifiers":[
        {
            "category":"Food & Beverages",
            "subcategory":"Bakery",
            "type":"Retail Goods"
        }
    ],
    "sg:phone":"+61 3 9397 1718",
    "sg:postcode":"3016",
    "sg:province":"VIC",
    "sg:tags":[
        "baker"
    ],
    "wof:name":"Bakers Delight Ltd",
    "wof:placetype":"venue"
},
  "geometry": {"coordinates":[144.89805602999999,-37.8579025269],"type":"Point"}
}