{
  "type": "Feature",
  "properties": {
    "iso:country":"AU",
    "sg:address":"30 West Brooke Pde",
    "sg:city":"Gorokan",
    "sg:classifiers":[
        {
            "category":"Building & Trades",
            "subcategory":"Plumbing",
            "type":"Services"
        }
    ],
    "sg:phone":"+61 2 4393 9076",
    "sg:postcode":"2263",
    "sg:province":"NSW",
    "sg:tags":[
        "drainers"
    ],
    "wof:name":"Boomers Plumbing Services",
    "wof:placetype":"venue"
},
  "geometry": {"coordinates":[151.503555,-33.254799],"type":"Point"}
}