{
  "type": "Feature",
  "properties": {
    "addr:full":"319 Thomas St Dandenong VIC 3175",
    "addr:housenumber":"319",
    "addr:postcode":"3175",
    "addr:street":"Thomas St",
    "iso:country":"AU",
    "sg:address":"319 Thomas St",
    "sg:city":"Dandenong",
    "sg:classifiers":[
        {
            "category":"Health Services",
            "subcategory":"Dentist",
            "type":"Services"
        }
    ],
    "sg:phone":"+61 3 9791 4030",
    "sg:postcode":"3175",
    "sg:province":"VIC",
    "wof:name":"Jayasinghe RB Dr",
    "wof:placetype":"venue"
},
  "geometry": {"coordinates":[145.21221923799999,-37.9849319458],"type":"Point"}
}