{
  "type": "Feature",
  "properties": {
    "iso:country":"AU",
    "sg:address":"Suite 3, Level 2, 19- 31 Pitt St",
    "sg:city":"Sydney",
    "sg:classifiers":[
        {
            "category":"Organizations",
            "subcategory":"Professional Association",
            "type":"Services"
        }
    ],
    "sg:phone":"+61 1800 816 997",
    "sg:postcode":"2000",
    "sg:province":"NSW",
    "sg:tags":[
        "web",
        "internet"
    ],
    "wof:name":"Hitwise",
    "wof:placetype":"venue"
},
  "geometry": {"coordinates":[151.20899963400001,-33.8620986938],"type":"Point"}
}