{
  "type": "Feature",
  "properties": {
    "iso:country":"AU",
    "sg:address":"16 Sale St",
    "sg:city":"Orange",
    "sg:classifiers":[
        {
            "category":"Professional",
            "subcategory":"Accounting & Tax Preparation",
            "type":"Services"
        }
    ],
    "sg:phone":"+61 2 6362 2870",
    "sg:postcode":"2800",
    "sg:province":"NSW",
    "sg:tags":[
        "consultant",
        "taxation"
    ],
    "wof:name":"Broadleys Financial Services",
    "wof:placetype":"venue"
},
  "geometry": {"coordinates":[149.09648132300001,-33.2826652527],"type":"Point"}
}