{
  "type": "Feature",
  "properties": {
    "addr:full":"High Central Rd Macleay Island QLD 4184",
    "addr:postcode":"4184",
    "addr:street":"Central Rd",
    "iso:country":"AU",
    "sg:address":"High Central Rd",
    "sg:city":"Macleay Island",
    "sg:classifiers":[
        {
            "category":"Organizations",
            "subcategory":"Community Association",
            "type":"Services"
        }
    ],
    "sg:phone":"+61 7 3409 5613",
    "sg:postcode":"4184",
    "sg:province":"QLD",
    "sg:tags":[
        "organisation",
        "family",
        "welfare"
    ],
    "wof:name":"Bay Islands Community Services Inc",
    "wof:placetype":"venue"
},
  "geometry": {"coordinates":[153.35679626500001,-27.6148738861],"type":"Point"}
}