{
  "type": "Feature",
  "properties": {
    "addr:full":"25 Morialta Rd Rostrevor SA 5073",
    "addr:housenumber":"25",
    "addr:postcode":"5073",
    "addr:street":"Morialta Rd",
    "iso:country":"AU",
    "sg:address":"25 Morialta Rd",
    "sg:city":"Rostrevor",
    "sg:classifiers":[
        {
            "category":"Retail",
            "subcategory":"Auto Repair",
            "type":"Services"
        }
    ],
    "sg:phone":"+61 8 8337 5758",
    "sg:postcode":"5073",
    "sg:province":"SA",
    "sg:tags":[
        "beater",
        "painter",
        "panel"
    ],
    "wof:name":"Varricchios Crash Repairs",
    "wof:placetype":"venue"
},
  "geometry": {"coordinates":[138.67889404300001,-34.9008331299],"type":"Point"}
}