{
  "type": "Feature",
  "properties": {
    "addr:full":"Lvl 1, Shop 1150, 120-200 Rosamond Rd, Highpoint Entertainment Complex Maribyrnong VIC 3032",
    "addr:housenumber":"shop 1150",
    "addr:postcode":"120-200;3032",
    "addr:street":"Rosamond Rd",
    "iso:country":"AU",
    "sg:address":"Lvl 1, Shop 1150, 120-200 Rosamond Rd, Highpoint Entertainment Complex",
    "sg:city":"Maribyrnong",
    "sg:classifiers":[
        {
            "category":"Cafe",
            "type":"Food & Drink"
        }
    ],
    "sg:phone":"+61 3 9317 4170",
    "sg:postcode":"3032",
    "sg:province":"VIC",
    "wof:name":"Loco Express Cafe",
    "wof:placetype":"venue"
},
  "geometry": {"coordinates":[144.886414,-37.771812],"type":"Point"}
}