{
  "type": "Feature",
  "properties": {
    "addr:full":"Cnr Elgin & Tarwin Sts Morwell VIC 3840",
    "addr:postcode":"3840",
    "addr:street":"Cnr",
    "iso:country":"AU",
    "sg:address":"Cnr Elgin & Tarwin Sts",
    "sg:city":"Morwell",
    "sg:classifiers":[
        {
            "category":"Real Estate",
            "subcategory":"Real Estate Agent",
            "type":"Services"
        }
    ],
    "sg:phone":"+61 3 5135 3336",
    "sg:postcode":"3840",
    "sg:province":"VIC",
    "wof:name":"Ross Maddaluno Real Estate Pty Ltd",
    "wof:placetype":"venue"
},
  "geometry": {"coordinates":[146.399093628,-38.2399291992],"type":"Point"}
}