{
  "type": "Feature",
  "properties": {
    "addr:full":"375 St Georges Rd Fitzroy North VIC 3068",
    "addr:housenumber":"375",
    "addr:postcode":"3068",
    "addr:street":"St Georges Rd",
    "iso:country":"AU",
    "sg:address":"375 St Georges Rd",
    "sg:city":"Fitzroy North",
    "sg:classifiers":[
        {
            "category":"Shopping",
            "subcategory":"Stationery & Office Supplies",
            "type":"Retail Goods"
        }
    ],
    "sg:phone":"+61 3 9489 2911",
    "sg:postcode":"3068",
    "sg:province":"VIC",
    "sg:tags":[
        "equipment",
        "display",
        "exhibition"
    ],
    "wof:name":"Visibility Event Signage",
    "wof:placetype":"venue"
},
  "geometry": {"coordinates":[144.98756408700001,-37.778755188],"type":"Point"}
}