{
  "type": "Feature",
  "properties": {
    "addr:full":"Jacaranda Crs Margaret River WA 6285",
    "addr:postcode":"6285",
    "addr:street":"Jacaranda Crs",
    "iso:country":"AU",
    "sg:address":"Jacaranda Crs",
    "sg:city":"Margaret River",
    "sg:classifiers":[
        {
            "category":"Home & Garden",
            "subcategory":"Carpets & Floor Coverings",
            "type":"Retail Goods"
        }
    ],
    "sg:phone":"+61 417 998 644",
    "sg:postcode":"6285",
    "sg:province":"WA",
    "sg:tags":[
        "tile",
        "wall",
        "layer"
    ],
    "wof:name":"Cape To Cape Contracting WA Pty Ltd",
    "wof:placetype":"venue"
},
  "geometry": {"coordinates":[115.073486328,-33.9533615112],"type":"Point"}
}