{
  "type": "Feature",
  "properties": {
    "iso:country":"AU",
    "sg:address":"11 Maritana Ave",
    "sg:city":"Regent",
    "sg:classifiers":[
        {
            "category":"Building & Trades",
            "subcategory":"Landscaping Services",
            "type":"Services"
        }
    ],
    "sg:phone":"+61 417 035 759",
    "sg:postcode":"3073",
    "sg:province":"VIC",
    "sg:tags":[
        "designer",
        "landscape",
        "contractor"
    ],
    "wof:name":"JC Landscaping",
    "wof:placetype":"venue"
},
  "geometry": {"coordinates":[144.99740600600001,-37.7286758423],"type":"Point"}
}