{
  "type": "Feature",
  "properties": {
    "addr:full":"110 Green St Lockhart NSW 2656",
    "addr:housenumber":"110",
    "addr:postcode":"2656",
    "addr:street":"Green St",
    "iso:country":"AU",
    "sg:address":"110 Green St",
    "sg:city":"Lockhart",
    "sg:classifiers":[
        {
            "category":"Personal",
            "subcategory":"Beauty Salon",
            "type":"Services"
        }
    ],
    "sg:phone":"+61 2 6920 5397",
    "sg:postcode":"2656",
    "sg:province":"NSW",
    "sg:tags":[
        "hairdresser"
    ],
    "wof:name":"Lorrett's Hairdressing",
    "wof:placetype":"venue"
},
  "geometry": {"coordinates":[146.718093872,-35.2211608887],"type":"Point"}
}