{
  "type": "Feature",
  "properties": {
    "addr:full":"102 Pyramid St Emu Plains NSW 2750",
    "addr:housenumber":"102",
    "addr:postcode":"2750",
    "addr:street":"Pyramid St",
    "iso:country":"AU",
    "sg:address":"102 Pyramid St",
    "sg:city":"Emu Plains",
    "sg:classifiers":[
        {
            "category":"Home & Garden",
            "subcategory":"Building Materials",
            "type":"Retail Goods"
        }
    ],
    "sg:phone":"+61 416 089 957",
    "sg:postcode":"2750",
    "sg:province":"NSW",
    "sg:tags":[
        "lawn",
        "cutting",
        "maintenance"
    ],
    "wof:name":"Wayne's All Round Lawn & Garden Care",
    "wof:placetype":"venue"
},
  "geometry": {"coordinates":[150.65135192899999,-33.7498931885],"type":"Point"}
}