{
  "type": "Feature",
  "properties": {
    "iso:country":"AU",
    "sg:address":"23 Summerset Drv",
    "sg:city":"Buderim",
    "sg:classifiers":[
        {
            "category":"Manufacturing",
            "subcategory":"Aerospace",
            "type":"Manufacturing & Wholesale Goods"
        }
    ],
    "sg:phone":"+61 7 5476 8282",
    "sg:postcode":"4556",
    "sg:province":"QLD",
    "sg:tags":[
        "equipment",
        "aircraft",
        "maintenance"
    ],
    "wof:name":"Aerowatt",
    "wof:placetype":"venue"
},
  "geometry": {"coordinates":[153.059356689,-26.6697254181],"type":"Point"}
}