{
  "type": "Feature",
  "properties": {
    "iso:country":"AU",
    "sg:address":"42 Victoria St",
    "sg:city":"Taree",
    "sg:classifiers":[
        {
            "category":"Travel",
            "subcategory":"Hotels & Motels",
            "type":"Entertainment"
        }
    ],
    "sg:phone":"+61 2 6552 2877",
    "sg:postcode":"2430",
    "sg:province":"NSW",
    "wof:name":"Midlands Motel",
    "wof:placetype":"venue"
},
  "geometry": {"coordinates":[152.46740700000001,-31.909676],"type":"Point"}
}