{
  "type": "Feature",
  "properties": {
    "addr:full":"24a Aitken St Gisborne VIC 3437",
    "addr:housenumber":"24a",
    "addr:postcode":"3437",
    "addr:street":"Aitken St",
    "iso:country":"AU",
    "sg:address":"24a Aitken St",
    "sg:city":"Gisborne",
    "sg:classifiers":[
        {
            "category":"Shopping",
            "subcategory":"Jewelry",
            "type":"Retail Goods"
        }
    ],
    "sg:phone":"+61 409 408 270",
    "sg:postcode":"3437",
    "sg:province":"VIC",
    "sg:tags":[
        "jeweller"
    ],
    "wof:name":"Berge Jewellery",
    "wof:placetype":"venue"
},
  "geometry": {"coordinates":[144.590866089,-37.487449646],"type":"Point"}
}