{
  "type": "Feature",
  "properties": {
    "iso:country":"AU",
    "sg:address":"35 Pillinger Drv",
    "sg:city":"Fern Tree",
    "sg:classifiers":[
        {
            "category":"Mining & Drilling",
            "type":"Manufacturing & Wholesale Goods"
        }
    ],
    "sg:phone":"+61 3 6239 1688",
    "sg:postcode":"7054",
    "sg:province":"TAS",
    "sg:tags":[
        "geologist"
    ],
    "wof:name":"Corbett K D Consultant Geologist",
    "wof:placetype":"venue"
},
  "geometry": {"coordinates":[147.261368,-42.917698],"type":"Point"}
}