{
  "type": "Feature",
  "properties": {
    "addr:full":"41 Myerick St Mandurah WA 6210",
    "addr:housenumber":"41",
    "addr:postcode":"6210",
    "addr:street":"Myerick St",
    "iso:country":"AU",
    "sg:address":"41 Myerick St",
    "sg:city":"Mandurah",
    "sg:classifiers":[
        {
            "category":"Building & Trades",
            "subcategory":"Landscaping Services",
            "type":"Services"
        }
    ],
    "sg:phone":"+61 8 9535 8361",
    "sg:postcode":"6210",
    "sg:province":"WA",
    "sg:tags":[
        "gardener"
    ],
    "wof:name":"Reliable Landscape & Garden Service",
    "wof:placetype":"venue"
},
  "geometry": {"coordinates":[115.737938,-32.521187],"type":"Point"}
}