{
  "type": "Feature",
  "properties": {
    "iso:country":"AU",
    "sg:address":"10 McCourt Rd",
    "sg:city":"Moss Vale",
    "sg:classifiers":[
        {
            "category":"Home & Garden",
            "subcategory":"Hardware",
            "type":"Retail Goods"
        }
    ],
    "sg:phone":"+61 2 4868 3311",
    "sg:postcode":"2577",
    "sg:province":"NSW",
    "sg:tags":[
        "supply",
        "maker",
        "cabinet"
    ],
    "wof:name":"Unika (Aust) Pty Ltd",
    "wof:placetype":"venue"
},
  "geometry": {"coordinates":[150.37905883799999,-34.534198761],"type":"Point"}
}