{
  "type": "Feature",
  "properties": {
    "addr:full":"36 Bickley St Naval Base WA 6165",
    "addr:housenumber":"36",
    "addr:postcode":"6165",
    "addr:street":"Bickley St",
    "iso:country":"AU",
    "sg:address":"36 Bickley St",
    "sg:city":"Naval Base",
    "sg:classifiers":[
        {
            "category":"Professional",
            "type":"Services"
        }
    ],
    "sg:phone":"+61 8 9410 0183",
    "sg:postcode":"6165",
    "sg:province":"WA",
    "sg:tags":[
        "transport"
    ],
    "wof:name":"Oz Makman",
    "wof:placetype":"venue"
},
  "geometry": {"coordinates":[115.78357699999999,-32.204895],"type":"Point"}
}