{
  "type": "Feature",
  "properties": {
    "addr:full":"26a Morgan St Dubbo NSW 2830",
    "addr:housenumber":"26a",
    "addr:postcode":"2830",
    "addr:street":"Morgan St",
    "iso:country":"AU",
    "sg:address":"26a Morgan St",
    "sg:city":"Dubbo",
    "sg:classifiers":[
        {
            "category":"Building & Trades",
            "subcategory":"Equipment Rental",
            "type":"Services"
        }
    ],
    "sg:phone":"+61 2 6884 1612",
    "sg:postcode":"2830",
    "sg:province":"NSW",
    "sg:tags":[
        "repairing",
        "changing",
        "retreading",
        "tyre"
    ],
    "wof:name":"Garaquip Sales & Service Dubbo",
    "wof:placetype":"venue"
},
  "geometry": {"coordinates":[148.61802673299999,-32.2379226685],"type":"Point"}
}