{
  "type": "Feature",
  "properties": {
    "addr:full":"449 Willoughby Rd Willoughby NSW 2068",
    "addr:housenumber":"449",
    "addr:postcode":"2068",
    "addr:street":"Willoughby Rd",
    "iso:country":"AU",
    "sg:address":"449 Willoughby Rd",
    "sg:city":"Willoughby",
    "sg:classifiers":[
        {
            "category":"Utilities",
            "subcategory":"Electric",
            "type":"Services"
        }
    ],
    "sg:phone":"+61 2 9958 1043",
    "sg:postcode":"2068",
    "sg:province":"NSW",
    "sg:tags":[
        "electrical",
        "contractor"
    ],
    "wof:name":"Rotric Pty Ltd",
    "wof:placetype":"venue"
},
  "geometry": {"coordinates":[151.199676514,-33.8096237183],"type":"Point"}
}