{
  "type": "Feature",
  "properties": {
    "addr:full":"McDonnell St Naracoorte SA 5271",
    "addr:postcode":"5271",
    "addr:street":"Mcdonnell St",
    "iso:country":"AU",
    "sg:address":"McDonnell St",
    "sg:city":"Naracoorte",
    "sg:classifiers":[
        {
            "category":"Museum",
            "type":"Entertainment"
        }
    ],
    "sg:phone":"+61 8 8762 1518",
    "sg:postcode":"5271",
    "sg:province":"SA",
    "wof:name":"The Sheeps Back Wool Museum",
    "wof:placetype":"venue"
},
  "geometry": {"coordinates":[140.73114000000001,-36.954624],"type":"Point"}
}