{
  "type": "Feature",
  "properties": {
    "addr:full":"Fcty 3/ 23 Premier Cct Warana QLD 4575",
    "addr:housenumber":"/ 23",
    "addr:postcode":"4575",
    "iso:country":"AU",
    "sg:address":"Fcty 3/ 23 Premier Cct",
    "sg:city":"Warana",
    "sg:classifiers":[
        {
            "category":"Organizations",
            "subcategory":"Community Association",
            "type":"Services"
        }
    ],
    "sg:phone":"+61 7 5493 2966",
    "sg:postcode":"4575",
    "sg:province":"QLD",
    "sg:tags":[
        "equipment",
        "system",
        "vacuum"
    ],
    "wof:name":"Greystone Vacuums",
    "wof:placetype":"venue"
},
  "geometry": {"coordinates":[153.13076799999999,-26.719839],"type":"Point"}
}