{
  "type": "Feature",
  "properties": {
    "addr:full":"15 Champion Drv Kelmscott WA 6111",
    "addr:housenumber":"15",
    "addr:postcode":"6111",
    "addr:street":"Champion Drv",
    "iso:country":"AU",
    "sg:address":"15 Champion Drv",
    "sg:city":"Kelmscott",
    "sg:classifiers":[
        {
            "category":"Manufacturing",
            "subcategory":"Wood Products",
            "type":"Manufacturing & Wholesale Goods"
        }
    ],
    "sg:phone":"+61 8 9497 9777",
    "sg:postcode":"6111",
    "sg:province":"WA",
    "sg:tags":[
        "polisher",
        "french"
    ],
    "wof:name":"Moore K N French Polishing Services",
    "wof:placetype":"venue"
},
  "geometry": {"coordinates":[116.008201599,-32.1359596252],"type":"Point"}
}