{
  "type": "Feature",
  "properties": {
    "addr:full":"25 Prince St Grafton NSW 2460",
    "addr:housenumber":"25",
    "addr:postcode":"2460",
    "addr:street":"Prince St",
    "iso:country":"AU",
    "sg:address":"25 Prince St",
    "sg:city":"Grafton",
    "sg:classifiers":[
        {
            "category":"Real Estate",
            "subcategory":"Real Estate Agent",
            "type":"Services"
        }
    ],
    "sg:phone":"+61 2 6642 3844",
    "sg:postcode":"2460",
    "sg:province":"NSW",
    "wof:name":"Ray White Real Estate",
    "wof:placetype":"venue"
},
  "geometry": {"coordinates":[152.93261718799999,-29.6918792725],"type":"Point"}
}