{
  "type": "Feature",
  "properties": {
    "iso:country":"AU",
    "sg:address":"Units 6-7, 123 Coreen Ave",
    "sg:city":"Penrith",
    "sg:classifiers":[
        {
            "category":"Autos & Motor Vehicles",
            "subcategory":"Automobile Sales",
            "type":"Retail Goods"
        }
    ],
    "sg:phone":"+61 2 4732 3211",
    "sg:postcode":"2750",
    "sg:province":"NSW",
    "sg:tags":[
        "car",
        "used"
    ],
    "wof:name":"Nepean Classic Cars",
    "wof:placetype":"venue"
},
  "geometry": {"coordinates":[150.70085144000001,-33.744972229],"type":"Point"}
}