{
  "type": "Feature",
  "properties": {
    "iso:country":"AU",
    "sg:address":"112 Wattletree Rd",
    "sg:city":"Bunyip",
    "sg:classifiers":[
        {
            "category":"Professional",
            "subcategory":"Computer Services",
            "type":"Services"
        }
    ],
    "sg:phone":"+61 1800 633 282",
    "sg:postcode":"3815",
    "sg:province":"VIC",
    "sg:tags":[
        "equipment",
        "networking",
        "installation"
    ],
    "wof:name":"Data Networks Pty Ltd",
    "wof:placetype":"venue"
},
  "geometry": {"coordinates":[145.732147,-38.090237],"type":"Point"}
}