{
  "type": "Feature",
  "properties": {
    "iso:country":"AU",
    "sg:address":"47 Robert St",
    "sg:city":"Labrador",
    "sg:classifiers":[
        {
            "category":"Professional",
            "subcategory":"Art Services",
            "type":"Services"
        }
    ],
    "sg:phone":"+61 411 472 370",
    "sg:postcode":"4215",
    "sg:province":"QLD",
    "sg:tags":[
        "graphic",
        "designer"
    ],
    "wof:name":"Platopod Design",
    "wof:placetype":"venue"
},
  "geometry": {"coordinates":[153.40452575699999,-27.9526138306],"type":"Point"}
}