{
  "type": "Feature",
  "properties": {
    "addr:full":"77 Vines Rd Hamlyn Heights VIC 3215",
    "addr:housenumber":"77",
    "addr:postcode":"3215",
    "addr:street":"Vines Rd",
    "iso:country":"AU",
    "sg:address":"77 Vines Rd",
    "sg:city":"Hamlyn Heights",
    "sg:classifiers":[
        {
            "category":"Personal",
            "subcategory":"Beauty Salon",
            "type":"Services"
        }
    ],
    "sg:phone":"+61 3 5277 9835",
    "sg:postcode":"3215",
    "sg:province":"VIC",
    "sg:tags":[
        "hairdresser"
    ],
    "wof:name":"Biancas Hair Studio",
    "wof:placetype":"venue"
},
  "geometry": {"coordinates":[144.328323364,-38.1214408875],"type":"Point"}
}