{
  "type": "Feature",
  "properties": {
    "iso:country":"AU",
    "sg:address":"87 Maygar St",
    "sg:city":"Grange",
    "sg:classifiers":[
        {
            "category":"Building & Trades",
            "subcategory":"Cleaning & Sanitation",
            "type":"Services"
        }
    ],
    "sg:phone":"+61 7 3886 1080",
    "sg:postcode":"4051",
    "sg:province":"QLD",
    "sg:tags":[
        "cleaner",
        "repairer",
        "roof"
    ],
    "wof:name":"Armourshield Roof Restoration",
    "wof:placetype":"venue"
},
  "geometry": {"coordinates":[153.02470398,-27.4270553589],"type":"Point"}
}