{
  "type": "Feature",
  "properties": {
    "addr:full":"Unit 8, 2 Kendall St Wodonga VIC 3690",
    "addr:housenumber":"2",
    "addr:postcode":"3690",
    "addr:street":"Kendall St",
    "iso:country":"AU",
    "sg:address":"Unit 8, 2 Kendall St",
    "sg:city":"Wodonga",
    "sg:classifiers":[
        {
            "category":"Retail",
            "subcategory":"Auto Repair",
            "type":"Services"
        }
    ],
    "sg:phone":"+61 2 6024 4289",
    "sg:postcode":"3690",
    "sg:province":"VIC",
    "sg:tags":[
        "beater",
        "painter",
        "panel"
    ],
    "wof:name":"Graeme Wild Auto Body Repairs",
    "wof:placetype":"venue"
},
  "geometry": {"coordinates":[146.90122985799999,-36.1210136414],"type":"Point"}
}