{
  "type": "Feature",
  "properties": {
    "addr:full":"2/ 5 Breene Pl Morningside QLD 4170",
    "addr:housenumber":"/ 5",
    "addr:postcode":"4170",
    "addr:street":"Breene Pl",
    "iso:country":"AU",
    "sg:address":"2/ 5 Breene Pl",
    "sg:city":"Morningside",
    "sg:classifiers":[
        {
            "category":"Wholesale",
            "subcategory":"Electrical",
            "type":"Manufacturing & Wholesale Goods"
        }
    ],
    "sg:phone":"+61 7 3899 1322",
    "sg:postcode":"4170",
    "sg:province":"QLD",
    "sg:tags":[
        "control",
        "equipment",
        "switch"
    ],
    "wof:name":"WEIDMULLER",
    "wof:placetype":"venue"
},
  "geometry": {"coordinates":[153.08489990199999,-27.4573879242],"type":"Point"}
}