{
  "type": "Feature",
  "properties": {
    "addr:full":"Unit 2/ 23 Denison St Wollongong NSW 2500",
    "addr:housenumber":"23",
    "addr:postcode":"2500",
    "addr:street":"Denison St",
    "iso:country":"AU",
    "sg:address":"Unit 2/ 23 Denison St",
    "sg:city":"Wollongong",
    "sg:classifiers":[
        {
            "category":"Wholesale",
            "subcategory":"Medical Equipment & Supplies",
            "type":"Manufacturing & Wholesale Goods"
        }
    ],
    "sg:phone":"+61 2 4227 4315",
    "sg:postcode":"2500",
    "sg:province":"NSW",
    "sg:tags":[
        "aid",
        "care",
        "health",
        "home"
    ],
    "wof:name":"Aids for Independent Daily Living",
    "wof:placetype":"venue"
},
  "geometry": {"coordinates":[150.88841199999999,-34.422913],"type":"Point"}
}