{
  "type": "Feature",
  "properties": {
    "iso:country":"AU",
    "sg:address":"33 Bambery St",
    "sg:city":"Fingal Head",
    "sg:classifiers":[
        {
            "category":"Organizations",
            "subcategory":"Professional Association",
            "type":"Services"
        }
    ],
    "sg:phone":"+61 7 5523 1588",
    "sg:postcode":"2487",
    "sg:province":"NSW",
    "sg:tags":[
        "organisation",
        "business"
    ],
    "wof:name":"Australian Wood Panels Association The",
    "wof:placetype":"venue"
},
  "geometry": {"coordinates":[153.56455993599999,-28.2022361755],"type":"Point"}
}