{
  "type": "Feature",
  "properties": {
    "addr:full":"190 Enoggera Rd Newmarket QLD 4051",
    "addr:housenumber":"190",
    "addr:postcode":"4051",
    "addr:street":"Enoggera Rd",
    "iso:country":"AU",
    "sg:address":"190 Enoggera Rd",
    "sg:city":"Newmarket",
    "sg:classifiers":[
        {
            "category":"Fast Food",
            "type":"Food & Drink"
        }
    ],
    "sg:phone":"+61 7 3356 3555",
    "sg:postcode":"4051",
    "sg:province":"QLD",
    "sg:tags":[
        "away",
        "take"
    ],
    "wof:name":"Suzie Wong Asian Fast Food",
    "wof:placetype":"venue"
},
  "geometry": {"coordinates":[153.006256103,-27.4362106323],"type":"Point"}
}