{
  "type": "Feature",
  "properties": {
    "addr:full":"21 Cook St Busselton WA 6280",
    "addr:housenumber":"21",
    "addr:postcode":"6280",
    "addr:street":"Cook St",
    "iso:country":"AU",
    "sg:address":"21 Cook St",
    "sg:city":"Busselton",
    "sg:classifiers":[
        {
            "category":"Wholesale",
            "subcategory":"Machinery & Supplies",
            "type":"Manufacturing & Wholesale Goods"
        }
    ],
    "sg:phone":"+61 8 9754 4420",
    "sg:postcode":"6280",
    "sg:province":"WA",
    "sg:tags":[
        "agricultural"
    ],
    "wof:name":"Russell Chinnery's Mechanical Services",
    "wof:placetype":"venue"
},
  "geometry": {"coordinates":[115.34403228799999,-33.6668815613],"type":"Point"}
}