{
  "type": "Feature",
  "properties": {
    "iso:country":"AU",
    "sg:address":"16 Raymond Rd",
    "sg:city":"Laverton North",
    "sg:classifiers":[
        {
            "category":"Home & Garden",
            "subcategory":"Garden Supply",
            "type":"Retail Goods"
        }
    ],
    "sg:phone":"+61 3 9931 0177",
    "sg:postcode":"3026",
    "sg:province":"VIC",
    "sg:tags":[
        "fertilizer"
    ],
    "wof:name":"Campbells Fertiliser Australasia Pty Ltd",
    "wof:placetype":"venue"
},
  "geometry": {"coordinates":[144.807465,-37.81834],"type":"Point"}
}