{
  "type": "Feature",
  "properties": {
    "addr:full":"Suite 37/ 11 Preston St Como WA 6152",
    "addr:housenumber":"37 / 11",
    "addr:postcode":"6152",
    "addr:street":"Preston St",
    "iso:country":"AU",
    "sg:address":"Suite 37/ 11 Preston St",
    "sg:city":"Como",
    "sg:classifiers":[
        {
            "category":"Building & Trades",
            "subcategory":"Construction",
            "type":"Services"
        }
    ],
    "sg:phone":"+61 8 9367 8633",
    "sg:postcode":"6152",
    "sg:province":"WA",
    "sg:tags":[
        "contractor"
    ],
    "wof:name":"Ernest Guillaume Homes",
    "wof:placetype":"venue"
},
  "geometry": {"coordinates":[115.85768899999999,-31.993877],"type":"Point"}
}