{
  "type": "Feature",
  "properties": {
    "iso:country":"AU",
    "sg:address":"Level 3, 169 Macquarie St",
    "sg:city":"Parramatta",
    "sg:classifiers":[
        {
            "category":"Professional",
            "subcategory":"Computer Services",
            "type":"Services"
        }
    ],
    "sg:phone":"+61 2 9806 0888",
    "sg:postcode":"2150",
    "sg:province":"NSW",
    "sg:tags":[
        "training"
    ],
    "wof:name":"Camets Education",
    "wof:placetype":"venue"
},
  "geometry": {"coordinates":[151.02076721200001,-33.8530006409],"type":"Point"}
}