{
  "type": "Feature",
  "properties": {
    "iso:country":"AU",
    "sg:address":"551 Burwood Rd",
    "sg:city":"Hawthorn",
    "sg:classifiers":[
        {
            "category":"Retail",
            "subcategory":"Car Wash",
            "type":"Services"
        }
    ],
    "sg:phone":"+61 3 9818 4000",
    "sg:postcode":"3122",
    "sg:province":"VIC",
    "sg:tags":[
        "wholesaler",
        "apron",
        "mfrs"
    ],
    "wof:name":"Beven Australia",
    "wof:placetype":"venue"
},
  "geometry": {"coordinates":[145.04237365700001,-37.8232765198],"type":"Point"}
}