{
  "type": "Feature",
  "properties": {
    "addr:full":"1 Worsfold St Everton Park QLD 4053",
    "addr:housenumber":"1",
    "addr:postcode":"4053",
    "addr:street":"Worsfold St",
    "iso:country":"AU",
    "sg:address":"1 Worsfold St",
    "sg:city":"Everton Park",
    "sg:classifiers":[
        {
            "category":"Retail",
            "subcategory":"Repair Shop",
            "type":"Services"
        }
    ],
    "sg:phone":"+61 7 3855 9005",
    "sg:postcode":"4053",
    "sg:province":"QLD",
    "sg:tags":[
        "maintenance",
        "pool",
        "swimming"
    ],
    "wof:name":"Brisbanes Pool Pump Specialists",
    "wof:placetype":"venue"
},
  "geometry": {"coordinates":[152.978118897,-27.3996372223],"type":"Point"}
}