{
  "type": "Feature",
  "properties": {
    "addr:full":"8 Kingfisher Way St Clair NSW 2759",
    "addr:housenumber":"8",
    "addr:postcode":"2759",
    "addr:street":"Kingfisher Way",
    "iso:country":"AU",
    "sg:address":"8 Kingfisher Way",
    "sg:city":"St Clair",
    "sg:classifiers":[
        {
            "category":"Home & Garden",
            "subcategory":"Building Materials",
            "type":"Retail Goods"
        }
    ],
    "sg:phone":"+61 2 9670 2847",
    "sg:postcode":"2759",
    "sg:province":"NSW",
    "sg:tags":[
        "merchant",
        "glass",
        "glazier"
    ],
    "wof:name":"K & M Window Repair Service",
    "wof:placetype":"venue"
},
  "geometry": {"coordinates":[150.796676636,-33.7973213196],"type":"Point"}
}