{
  "type": "Feature",
  "properties": {
    "addr:full":"Chadstone Shopping Centre Dandenong Rd Chadstone VIC 3148",
    "addr:postcode":"3148",
    "addr:street":"Dandenong Rd",
    "iso:country":"AU",
    "sg:address":"Chadstone Shopping Centre Dandenong Rd",
    "sg:city":"Chadstone",
    "sg:classifiers":[
        {
            "category":"Professional",
            "subcategory":"Computer Services",
            "type":"Services"
        }
    ],
    "sg:phone":"+61 3 9563 2666",
    "sg:postcode":"3148",
    "sg:province":"VIC",
    "sg:tags":[
        "package",
        "software"
    ],
    "wof:name":"Electronics Boutique Australia",
    "wof:placetype":"venue"
},
  "geometry": {"coordinates":[145.079589844,-37.8796424866],"type":"Point"}
}