{
  "type": "Feature",
  "properties": {
    "iso:country":"AU",
    "sg:address":"2/ 125 Elder St",
    "sg:city":"Lambton",
    "sg:classifiers":[
        {
            "category":"Real Estate",
            "subcategory":"Real Estate Services",
            "type":"Services"
        }
    ],
    "sg:phone":"+61 2 4952 3744",
    "sg:postcode":"2299",
    "sg:province":"NSW",
    "sg:tags":[
        "valuer"
    ],
    "wof:name":"Elders Real Estate",
    "wof:placetype":"venue"
},
  "geometry": {"coordinates":[151.70687866200001,-32.9114646912],"type":"Point"}
}