{
  "type": "Feature",
  "properties": {
    "iso:country":"AU",
    "sg:address":"114 Mount St",
    "sg:city":"Coogee",
    "sg:classifiers":[
        {
            "category":"Professional",
            "subcategory":"Art Services",
            "type":"Services"
        }
    ],
    "sg:phone":"+61 2 8004 6850",
    "sg:postcode":"2034",
    "sg:province":"NSW",
    "sg:tags":[
        "picture",
        "frame",
        "framing"
    ],
    "sg:website":"http://www.abodepicturehanging.com.au",
    "wof:name":"Abode Picturehanging",
    "wof:placetype":"venue"
},
  "geometry": {"coordinates":[151.25114440900001,-33.9233779907],"type":"Point"}
}