{
  "type": "Feature",
  "properties": {
    "iso:country":"AU",
    "sg:address":"1297 Nepean Hwy",
    "sg:city":"Cheltenham",
    "sg:classifiers":[
        {
            "category":"Arena",
            "subcategory":"Horse Racetrack",
            "type":"Entertainment"
        }
    ],
    "sg:phone":"+61 3 9585 5622",
    "sg:postcode":"3192",
    "sg:province":"VIC",
    "sg:tags":[
        "retail",
        "swimwear"
    ],
    "wof:name":"Swimwear Galore",
    "wof:placetype":"venue"
},
  "geometry": {"coordinates":[145.057983398,-37.9652557373],"type":"Point"}
}