{
  "type": "Feature",
  "properties": {
    "addr:full":"164 Liverpool Rd Enfield NSW 2136",
    "addr:housenumber":"164",
    "addr:postcode":"2136",
    "addr:street":"Liverpool Rd",
    "iso:country":"AU",
    "sg:address":"164 Liverpool Rd",
    "sg:city":"Enfield",
    "sg:classifiers":[
        {
            "category":"Communications",
            "subcategory":"Film & Video Production",
            "type":"Services"
        }
    ],
    "sg:phone":"+61 2 9744 7777",
    "sg:postcode":"2136",
    "sg:province":"NSW",
    "sg:tags":[
        "television",
        "system",
        "circuit",
        "closed"
    ],
    "wof:name":"Lamba Audio Visual Lighting Group",
    "wof:placetype":"venue"
},
  "geometry": {"coordinates":[151.097579956,-33.8870353699],"type":"Point"}
}