{
  "type": "Feature",
  "properties": {
    "iso:country":"AU",
    "sg:address":"Crows Nest Plaza 103 Willoughby Rd",
    "sg:city":"Crows Nest",
    "sg:classifiers":[
        {
            "category":"Banks & Credit Unions",
            "subcategory":"Investment Brokerage",
            "type":"Services"
        }
    ],
    "sg:phone":"+61 2 9906 8666",
    "sg:postcode":"2065",
    "sg:province":"NSW",
    "wof:name":"Crows Nest Plaza Management",
    "wof:placetype":"venue"
},
  "geometry": {"coordinates":[151.20106506400001,-33.8236198425],"type":"Point"}
}