{
  "type": "Feature",
  "properties": {
    "addr:full":"PO Box 195 Magill SA 5072",
    "addr:postcode":"5072",
    "iso:country":"AU",
    "sg:address":"PO Box 195",
    "sg:city":"Magill",
    "sg:classifiers":[
        {
            "category":"Health Services",
            "subcategory":"Health Practitioner",
            "type":"Services"
        }
    ],
    "sg:phone":"+61 8 8331 7450",
    "sg:postcode":"5072",
    "sg:province":"SA",
    "sg:tags":[
        "psychologist"
    ],
    "wof:name":"Lebedev Lena A",
    "wof:placetype":"venue"
},
  "geometry": {"coordinates":[138.67552185100001,-34.9059104919],"type":"Point"}
}