{
  "type": "Feature",
  "properties": {
    "iso:country":"AU",
    "sg:address":"510 Great Northern Hwy",
    "sg:city":"Middle Swan",
    "sg:classifiers":[
        {
            "category":"Arts & Performance",
            "subcategory":"Art Gallery",
            "type":"Entertainment"
        }
    ],
    "sg:phone":"+61 8 9250 8838",
    "sg:postcode":"6056",
    "sg:province":"WA",
    "wof:name":"Taylors Studio",
    "wof:placetype":"venue"
},
  "geometry": {"coordinates":[116.015007019,-31.850435257],"type":"Point"}
}