{
  "type": "Feature",
  "properties": {
    "addr:full":"24 Leyland St Garbutt QLD 4814",
    "addr:housenumber":"24",
    "addr:postcode":"4814",
    "addr:street":"Leyland St",
    "iso:country":"AU",
    "sg:address":"24 Leyland St",
    "sg:city":"Garbutt",
    "sg:classifiers":[
        {
            "category":"Personal",
            "subcategory":"Tattoo Parlor",
            "type":"Services"
        }
    ],
    "sg:phone":"+61 7 4725 2799",
    "sg:postcode":"4814",
    "sg:province":"QLD",
    "sg:tags":[
        "resume"
    ],
    "wof:name":"Representative Business Services",
    "wof:placetype":"venue"
},
  "geometry": {"coordinates":[146.766006,-19.271639],"type":"Point"}
}