{
  "type": "Feature",
  "properties": {
    "addr:full":"PO Box 122 Emu Plains NSW 2750",
    "addr:postcode":"2750",
    "iso:country":"AU",
    "sg:address":"PO Box 122",
    "sg:city":"Emu Plains",
    "sg:classifiers":[
        {
            "category":"Building & Trades",
            "subcategory":"Equipment Rental",
            "type":"Services"
        }
    ],
    "sg:phone":"+61 2 4735 6099",
    "sg:postcode":"2750",
    "sg:province":"NSW",
    "sg:tags":[
        "builder",
        "contractor"
    ],
    "wof:name":"Bouman Cranes Pty Ltd",
    "wof:placetype":"venue"
},
  "geometry": {"coordinates":[150.65957641599999,-33.7534790039],"type":"Point"}
}