{
  "type": "Feature",
  "properties": {
    "iso:country":"AU",
    "sg:address":"1/ 470 Bridge Rd",
    "sg:city":"Mackay",
    "sg:classifiers":[
        {
            "category":"Shopping",
            "type":"Retail Goods"
        }
    ],
    "sg:phone":"+61 7 4953 2191",
    "sg:postcode":"4740",
    "sg:province":"QLD",
    "sg:tags":[
        "supply",
        "religious",
        "church"
    ],
    "wof:name":"Christian Bookworld",
    "wof:placetype":"venue"
},
  "geometry": {"coordinates":[149.15621899999999,-21.145452],"type":"Point"}
}