{
  "type": "Feature",
  "properties": {
    "addr:full":"362 Church St Parramatta NSW 2150",
    "addr:housenumber":"362",
    "addr:postcode":"2150",
    "addr:street":"Church St",
    "iso:country":"AU",
    "sg:address":"362 Church St",
    "sg:city":"Parramatta",
    "sg:classifiers":[
        {
            "category":"Shopping",
            "subcategory":"Mobile Phones",
            "type":"Retail Goods"
        }
    ],
    "sg:phone":"+61 2 9890 2440",
    "sg:postcode":"2150",
    "sg:province":"NSW",
    "sg:tags":[
        "telephone",
        "accessory"
    ],
    "wof:name":"A OK Communications",
    "wof:placetype":"venue"
},
  "geometry": {"coordinates":[151.005371094,-33.8092918396],"type":"Point"}
}