{
  "type": "Feature",
  "properties": {
    "addr:full":"Lvl 4/ 345 George St Sydney NSW 2000",
    "addr:housenumber":"/ 345",
    "addr:postcode":"2000",
    "addr:street":"George St",
    "iso:country":"AU",
    "sg:address":"Lvl 4/ 345 George St",
    "sg:city":"Sydney",
    "sg:classifiers":[
        {
            "category":"Real Estate",
            "subcategory":"Real Estate Services",
            "type":"Services"
        }
    ],
    "sg:phone":"+61 2 9249 3708",
    "sg:postcode":"2000",
    "sg:province":"NSW",
    "sg:tags":[
        "consultant",
        "property"
    ],
    "wof:name":"Commercial Property Consulting Pty Limited",
    "wof:placetype":"venue"
},
  "geometry": {"coordinates":[151.20689392099999,-33.8677902222],"type":"Point"}
}