{
  "type": "Feature",
  "properties": {
    "addr:full":"Lvl 1/ 88 Albert Rd South Melbourne VIC 3205",
    "addr:housenumber":"/ 88",
    "addr:postcode":"3205",
    "addr:street":"Albert Rd",
    "iso:country":"AU",
    "sg:address":"Lvl 1/ 88 Albert Rd",
    "sg:city":"South Melbourne",
    "sg:classifiers":[
        {
            "category":"Professional",
            "subcategory":"Employment Agencies",
            "type":"Services"
        }
    ],
    "sg:phone":"+61 3 9697 1800",
    "sg:postcode":"3205",
    "sg:province":"VIC",
    "wof:name":"MNJ Personnel Pty Ltd",
    "wof:placetype":"venue"
},
  "geometry": {"coordinates":[144.97035199999999,-37.835487],"type":"Point"}
}