{
  "type": "Feature",
  "properties": {
    "addr:full":"17 Union Rd Dandenong VIC 3175",
    "addr:housenumber":"17",
    "addr:postcode":"3175",
    "addr:street":"Union Rd",
    "iso:country":"AU",
    "sg:address":"17 Union Rd",
    "sg:city":"Dandenong",
    "sg:classifiers":[
        {
            "category":"Manufacturing",
            "subcategory":"Rubber & Plastics",
            "type":"Manufacturing & Wholesale Goods"
        }
    ],
    "sg:phone":"+61 3 9794 0777",
    "sg:postcode":"3175",
    "sg:province":"VIC",
    "sg:tags":[
        "wholesaler",
        "product",
        "mfrs"
    ],
    "wof:name":"FMP Plastic Injection Moulders Pty Ltd",
    "wof:placetype":"venue"
},
  "geometry": {"coordinates":[145.20344543499999,-38.0075836182],"type":"Point"}
}