{
  "type": "Feature",
  "properties": {
    "addr:full":"10 Lynda Crt Aspendale Gardens VIC 3195",
    "addr:housenumber":"10",
    "addr:postcode":"3195",
    "addr:street":"Lynda Crt",
    "iso:country":"AU",
    "sg:address":"10 Lynda Crt",
    "sg:city":"Aspendale Gardens",
    "sg:classifiers":[
        {
            "category":"Utilities",
            "subcategory":"Electric",
            "type":"Services"
        }
    ],
    "sg:phone":"+61 408 587 068",
    "sg:postcode":"3195",
    "sg:province":"VIC",
    "sg:tags":[
        "electrical",
        "contractor"
    ],
    "wof:name":"Wewire Electrical",
    "wof:placetype":"venue"
},
  "geometry": {"coordinates":[145.11228942899999,-38.0203590393],"type":"Point"}
}