{
  "type": "Feature",
  "properties": {
    "addr:full":"86 Brisbane St Ipswich QLD 4305",
    "addr:housenumber":"86",
    "addr:postcode":"4305",
    "addr:street":"Brisbane St",
    "iso:country":"AU",
    "sg:address":"86 Brisbane St",
    "sg:city":"Ipswich",
    "sg:classifiers":[
        {
            "category":"Professional",
            "subcategory":"Art Services",
            "type":"Services"
        }
    ],
    "sg:phone":"+61 7 3281 1989",
    "sg:postcode":"4305",
    "sg:province":"QLD",
    "sg:tags":[
        "picture",
        "frame",
        "framing"
    ],
    "wof:name":"Whiteheads Of Ipswich",
    "wof:placetype":"venue"
},
  "geometry": {"coordinates":[152.76043701200001,-27.6146011353],"type":"Point"}
}