{
  "type": "Feature",
  "properties": {
    "iso:country":"AU",
    "sg:address":"98 Toohey Rd",
    "sg:city":"Wellers Hill",
    "sg:classifiers":[
        {
            "category":"Building & Trades",
            "subcategory":"Construction",
            "type":"Services"
        }
    ],
    "sg:phone":"+61 7 3255 8340",
    "sg:postcode":"4121",
    "sg:province":"QLD",
    "sg:tags":[
        "contractor"
    ],
    "wof:name":"Kevin Hessey Homes",
    "wof:placetype":"venue"
},
  "geometry": {"coordinates":[153.04675293,-27.5231342316],"type":"Point"}
}