{
  "type": "Feature",
  "properties": {
    "addr:full":"8 Northcott St Queanbeyan ACT 2620",
    "addr:housenumber":"8",
    "addr:postcode":"2620",
    "addr:street":"Northcott St",
    "iso:country":"AU",
    "sg:address":"8 Northcott St",
    "sg:city":"Queanbeyan",
    "sg:classifiers":[
        {
            "category":"Professional",
            "subcategory":"Accounting & Tax Preparation",
            "type":"Services"
        }
    ],
    "sg:phone":"+61 418 450 126",
    "sg:postcode":"2620",
    "sg:province":"ACT",
    "sg:tags":[
        "bookkeeping"
    ],
    "wof:name":"Keep It Simple For Small Business",
    "wof:placetype":"venue"
},
  "geometry": {"coordinates":[149.21734619099999,-35.3491706848],"type":"Point"}
}