{
  "type": "Feature",
  "properties": {
    "iso:country":"AU",
    "sg:address":"Beach Rd",
    "sg:city":"Christies Beach",
    "sg:classifiers":[
        {
            "category":"Education",
            "subcategory":"School",
            "type":"Public Place"
        }
    ],
    "sg:phone":"+61 8 8384 8288",
    "sg:postcode":"5165",
    "sg:province":"SA",
    "sg:tags":[
        "state",
        "except",
        "nsw"
    ],
    "wof:name":"Bowden Brompton Community School",
    "wof:placetype":"venue"
},
  "geometry": {"coordinates":[138.47825622600001,-35.1390686035],"type":"Point"}
}