{
  "type": "Feature",
  "properties": {
    "addr:full":"U2/ 6 Henzell Rd Caboolture QLD 4510",
    "addr:postcode":"4510",
    "addr:street":"U2 / 6 Henzell Rd",
    "iso:country":"AU",
    "sg:address":"U2/ 6 Henzell Rd",
    "sg:city":"Caboolture",
    "sg:classifiers":[
        {
            "category":"Professional",
            "subcategory":"Printing & Photocopies",
            "type":"Services"
        }
    ],
    "sg:phone":"+61 7 5495 3862",
    "sg:postcode":"4510",
    "sg:province":"QLD",
    "sg:tags":[
        "screen",
        "printer"
    ],
    "wof:name":"Caboolture Screen Printers",
    "wof:placetype":"venue"
},
  "geometry": {"coordinates":[152.95047,-27.076733],"type":"Point"}
}