{
  "type": "Feature",
  "properties": {
    "iso:country":"AU",
    "sg:address":"53 Bultje St",
    "sg:city":"Dubbo",
    "sg:classifiers":[
        {
            "category":"Health Services",
            "subcategory":"Doctor",
            "type":"Services"
        }
    ],
    "sg:phone":"+61 2 6882 8655",
    "sg:postcode":"2830",
    "sg:province":"NSW",
    "sg:tags":[
        "medical",
        "practitioner"
    ],
    "wof:name":"Kavanagh Diane",
    "wof:placetype":"venue"
},
  "geometry": {"coordinates":[148.60505676299999,-32.2517433167],"type":"Point"}
}