{
  "type": "Feature",
  "properties": {
    "addr:full":"127 North West Arm Rd Grays Point NSW 2232",
    "addr:housenumber":"127",
    "addr:postcode":"2232",
    "addr:street":"North West Arm Rd",
    "iso:country":"AU",
    "sg:address":"127 North West Arm Rd",
    "sg:city":"Grays Point",
    "sg:classifiers":[
        {
            "category":"Professional",
            "subcategory":"Secretarial Services",
            "type":"Services"
        }
    ],
    "sg:phone":"+61 2 9545 3324",
    "sg:postcode":"2232",
    "sg:province":"NSW",
    "sg:tags":[
        "typing"
    ],
    "wof:name":"Compu-Sec 2000 Computer & Secretarial Services",
    "wof:placetype":"venue"
},
  "geometry": {"coordinates":[151.07635498100001,-34.048160553],"type":"Point"}
}