{
  "type": "Feature",
  "properties": {
    "addr:full":"Suite 4 , 6 Langmore La Berwick VIC 3806",
    "addr:housenumber":"6",
    "addr:postcode":"3806",
    "addr:street":"Langmore La",
    "iso:country":"AU",
    "sg:address":"Suite 4 , 6 Langmore La",
    "sg:city":"Berwick",
    "sg:classifiers":[
        {
            "category":"Health Services",
            "subcategory":"Doctor",
            "type":"Services"
        }
    ],
    "sg:phone":"+61 3 9796 2548",
    "sg:postcode":"3806",
    "sg:province":"VIC",
    "sg:tags":[
        "medical",
        "practitioner"
    ],
    "wof:name":"Pullar Michael",
    "wof:placetype":"venue"
},
  "geometry": {"coordinates":[145.344207764,-38.0331382751],"type":"Point"}
}