{
  "type": "Feature",
  "properties": {
    "iso:country":"AU",
    "sg:address":"196 Union Rd",
    "sg:city":"Surrey Hills",
    "sg:classifiers":[
        {
            "category":"Government",
            "subcategory":"Court House",
            "type":"Public Place"
        }
    ],
    "sg:phone":"+61 3 9888 4737",
    "sg:postcode":"3127",
    "sg:province":"VIC",
    "sg:tags":[
        "personal",
        "marriage",
        "family",
        "counselling"
    ],
    "wof:name":"Oak House The",
    "wof:placetype":"venue"
},
  "geometry": {"coordinates":[145.09808349599999,-37.8206062317],"type":"Point"}
}