{
  "type": "Feature",
  "properties": {
    "addr:full":"9b Pepper St Falcon WA 6210",
    "addr:housenumber":"9b",
    "addr:postcode":"6210",
    "addr:street":"Pepper St",
    "iso:country":"AU",
    "sg:address":"9b Pepper St",
    "sg:city":"Falcon",
    "sg:classifiers":[
        {
            "category":"Utilities",
            "subcategory":"Water",
            "type":"Services"
        }
    ],
    "sg:phone":"+61 8 9534 5976",
    "sg:postcode":"6210",
    "sg:province":"WA",
    "sg:tags":[
        "equipment",
        "treatment"
    ],
    "wof:name":"Lobb Engineering Pty Ltd",
    "wof:placetype":"venue"
},
  "geometry": {"coordinates":[115.643494,-32.589199],"type":"Point"}
}