{
  "type": "Feature",
  "properties": {
    "addr:full":"148 Queen St Woollahra NSW 2025",
    "addr:housenumber":"148",
    "addr:postcode":"2025",
    "addr:street":"Queen St",
    "iso:country":"AU",
    "sg:address":"148 Queen St",
    "sg:city":"Woollahra",
    "sg:classifiers":[
        {
            "category":"Food & Beverages",
            "subcategory":"Groceries & Convenience Stores",
            "type":"Retail Goods"
        }
    ],
    "sg:phone":"+61 2 9363 3604",
    "sg:postcode":"2025",
    "sg:province":"NSW",
    "wof:name":"The Brothers Foodstores",
    "wof:placetype":"venue"
},
  "geometry": {"coordinates":[151.238372803,-33.8880805969],"type":"Point"}
}