{
  "type": "Feature",
  "properties": {
    "iso:country":"AU",
    "sg:address":"18 - 20 Palmer Crt",
    "sg:city":"Mt Waverley",
    "sg:classifiers":[
        {
            "category":"Manufacturing",
            "subcategory":"Building Materials",
            "type":"Manufacturing & Wholesale Goods"
        }
    ],
    "sg:phone":"+61 3 9565 6400",
    "sg:postcode":"3149",
    "sg:province":"VIC",
    "sg:tags":[
        "equipment",
        "handling"
    ],
    "wof:name":"NKC Conveyors Australia Pty Ltd",
    "wof:placetype":"venue"
},
  "geometry": {"coordinates":[145.126419067,-37.8945159912],"type":"Point"}
}