{
  "type": "Feature",
  "properties": {
    "iso:country":"AU",
    "sg:address":"Cnr Foskew Rd & Gould Rd",
    "sg:city":"Narngulu",
    "sg:classifiers":[
        {
            "category":"Cafe",
            "type":"Food & Drink"
        }
    ],
    "sg:phone":"+61 8 9923 3779",
    "sg:postcode":"6532",
    "sg:province":"WA",
    "wof:name":"Joannes Narngulu Lunchbar",
    "wof:placetype":"venue"
},
  "geometry": {"coordinates":[114.173919678,-27.703868866],"type":"Point"}
}