{
  "type": "Feature",
  "properties": {
    "addr:full":"200 Ballarat Rd Hamilton VIC 3300",
    "addr:housenumber":"200",
    "addr:postcode":"3300",
    "addr:street":"Ballarat Rd",
    "iso:country":"AU",
    "sg:address":"200 Ballarat Rd",
    "sg:city":"Hamilton",
    "sg:classifiers":[
        {
            "category":"Education",
            "subcategory":"University",
            "type":"Public Place"
        }
    ],
    "sg:phone":"+61 3 9925 2000",
    "sg:postcode":"3300",
    "sg:province":"VIC",
    "sg:tags":[
        "college",
        "tertiary"
    ],
    "wof:name":"RMIT University",
    "wof:placetype":"venue"
},
  "geometry": {"coordinates":[142.04884338400001,-37.7435150146],"type":"Point"}
}