{
  "type": "Feature",
  "properties": {
    "addr:full":"Melbourne Rd Kialla VIC 3631",
    "addr:postcode":"3631",
    "addr:street":"Melbourne Rd",
    "iso:country":"AU",
    "sg:address":"Melbourne Rd",
    "sg:city":"Kialla",
    "sg:classifiers":[
        {
            "category":"Wholesale",
            "subcategory":"Auto Parts",
            "type":"Manufacturing & Wholesale Goods"
        }
    ],
    "sg:phone":"+61 3 5823 1911",
    "sg:postcode":"3631",
    "sg:province":"VIC",
    "sg:tags":[
        "recyclers"
    ],
    "wof:name":"Central Victorian Auto Parts",
    "wof:placetype":"venue"
},
  "geometry": {"coordinates":[145.389572144,-36.4276161194],"type":"Point"}
}