{
  "type": "Feature",
  "properties": {
    "addr:full":"Commercial Ste 1-8 Kellicar La Macarthur Square NSW 2560",
    "addr:postcode":"2560",
    "addr:street":"Square",
    "iso:country":"AU",
    "sg:address":"Commercial Ste 1-8 Kellicar La",
    "sg:city":"Macarthur Square",
    "sg:classifiers":[
        {
            "category":"Insurance",
            "subcategory":"Insurance Agent",
            "type":"Services"
        }
    ],
    "sg:phone":"+61 2 4627 2111",
    "sg:postcode":"2560",
    "sg:province":"NSW",
    "sg:tags":[
        "broker"
    ],
    "wof:name":"Davies Brookes Pty Ltd",
    "wof:placetype":"venue"
},
  "geometry": {"coordinates":[150.81483459500001,-34.0658035278],"type":"Point"}
}