{
  "type": "Feature",
  "properties": {
    "addr:full":"569 Keilor Rd Niddrie VIC 3042",
    "addr:housenumber":"569",
    "addr:postcode":"3042",
    "addr:street":"Keilor Rd",
    "iso:country":"AU",
    "sg:address":"569 Keilor Rd",
    "sg:city":"Niddrie",
    "sg:classifiers":[
        {
            "category":"Retail",
            "subcategory":"Auto Rental",
            "type":"Services"
        }
    ],
    "sg:phone":"+61 3 9337 8000",
    "sg:postcode":"3042",
    "sg:province":"VIC",
    "sg:tags":[
        "chauffeur",
        "car",
        "hire",
        "driven",
        "limousine"
    ],
    "wof:name":"www WeddingCars pty ltd",
    "wof:placetype":"venue"
},
  "geometry": {"coordinates":[144.881515503,-37.7333984375],"type":"Point"}
}