{
  "type": "Feature",
  "properties": {
    "addr:full":"1565 Barrabool Rd Gnarwarre VIC 3221",
    "addr:housenumber":"1565",
    "addr:postcode":"3221",
    "addr:street":"Barrabool Rd",
    "iso:country":"AU",
    "sg:address":"1565 Barrabool Rd",
    "sg:city":"Gnarwarre",
    "sg:classifiers":[
        {
            "category":"Real Estate",
            "subcategory":"Architect",
            "type":"Services"
        }
    ],
    "sg:phone":"+61 3 5265 6121",
    "sg:postcode":"3221",
    "sg:province":"VIC",
    "sg:tags":[
        "house",
        "damp",
        "waterproofing",
        "repair"
    ],
    "wof:name":"BW Group P/L",
    "wof:placetype":"venue"
},
  "geometry": {"coordinates":[144.16076699999999,-38.168728],"type":"Point"}
}