{
  "type": "Feature",
  "properties": {
    "iso:country":"AU",
    "sg:address":"425 Kiewa St",
    "sg:city":"Albury",
    "sg:classifiers":[
        {
            "category":"Home & Garden",
            "subcategory":"Hardware",
            "type":"Retail Goods"
        }
    ],
    "sg:phone":"+61 2 6021 5699",
    "sg:postcode":"2640",
    "sg:province":"NSW",
    "sg:tags":[
        "repair",
        "tool",
        "power"
    ],
    "wof:name":"Gasweld Tool Centre",
    "wof:placetype":"venue"
},
  "geometry": {"coordinates":[146.917205811,-36.0713615417],"type":"Point"}
}