{
  "type": "Feature",
  "properties": {
    "addr:full":"142 Avoca St Randwick NSW 2031",
    "addr:housenumber":"142",
    "addr:postcode":"2031",
    "addr:street":"Avoca St",
    "iso:country":"AU",
    "sg:address":"142 Avoca St",
    "sg:city":"Randwick",
    "sg:classifiers":[
        {
            "category":"Restaurant",
            "type":"Food & Drink"
        }
    ],
    "sg:phone":"+61 2 9326 4122",
    "sg:postcode":"2031",
    "sg:province":"NSW",
    "wof:name":"Cedars Valley Lebanese Restaurant",
    "wof:placetype":"venue"
},
  "geometry": {"coordinates":[151.241744995,-33.913646698],"type":"Point"}
}