{
  "type": "Feature",
  "properties": {
    "addr:full":"Elizabeth St Moe VIC 3825",
    "addr:postcode":"3825",
    "addr:street":"Elizabeth St",
    "iso:country":"AU",
    "sg:address":"Elizabeth St",
    "sg:city":"Moe",
    "sg:classifiers":[
        {
            "category":"Education",
            "subcategory":"School",
            "type":"Public Place"
        }
    ],
    "sg:phone":"+61 3 5127 2607",
    "sg:postcode":"3825",
    "sg:province":"VIC",
    "sg:tags":[
        "state",
        "except",
        "nsw"
    ],
    "wof:name":"Moe Primary School",
    "wof:placetype":"venue"
},
  "geometry": {"coordinates":[146.252487,-38.188469],"type":"Point"}
}