{
  "type": "Feature",
  "properties": {
    "addr:full":"Level 1 660 Doncaster Rd Doncaster VIC 3108",
    "addr:housenumber":"660",
    "addr:postcode":"3108",
    "addr:street":"Doncaster Rd",
    "iso:country":"AU",
    "sg:address":"Level 1 660 Doncaster Rd",
    "sg:city":"Doncaster",
    "sg:classifiers":[
        {
            "category":"Manufacturing",
            "subcategory":"Tools & Machinery",
            "type":"Manufacturing & Wholesale Goods"
        }
    ],
    "sg:phone":"+61 1800 645 045",
    "sg:postcode":"3108",
    "sg:province":"VIC",
    "sg:tags":[
        "wholesaler",
        "lingerie",
        "mfrs",
        "sleepwear"
    ],
    "wof:name":"The Berlei Group",
    "wof:placetype":"venue"
},
  "geometry": {"coordinates":[145.12843322800001,-37.7875328064],"type":"Point"}
}