{
  "type": "Feature",
  "properties": {
    "addr:full":"16-20 Claremont St South Yarra VIC 3141",
    "addr:housenumber":"16-20",
    "addr:postcode":"3141",
    "addr:street":"Claremont St",
    "iso:country":"AU",
    "sg:address":"16-20 Claremont St",
    "sg:city":"South Yarra",
    "sg:classifiers":[
        {
            "category":"Travel",
            "subcategory":"Hotels & Motels",
            "type":"Entertainment"
        }
    ],
    "sg:phone":"+61 3 9703 1148",
    "sg:postcode":"3141",
    "sg:province":"VIC",
    "sg:tags":[
        "accommodation"
    ],
    "wof:name":"ALH Group",
    "wof:placetype":"venue"
},
  "geometry": {"coordinates":[144.993942261,-37.8380050659],"type":"Point"}
}