{
  "type": "Feature",
  "properties": {
    "iso:country":"AU",
    "sg:address":"7/ 49 Downs St",
    "sg:city":"North Ipswich",
    "sg:classifiers":[
        {
            "category":"Shopping",
            "type":"Retail Goods"
        }
    ],
    "sg:phone":"+61 7 3281 1450",
    "sg:postcode":"4305",
    "sg:province":"QLD",
    "sg:tags":[
        "new age",
        "product"
    ],
    "wof:name":"Mystical Vibrations",
    "wof:placetype":"venue"
},
  "geometry": {"coordinates":[152.761627197,-27.603723526],"type":"Point"}
}