{
  "type": "Feature",
  "properties": {
    "iso:country":"AU",
    "sg:address":"9/ 369 Glebe Point Rd",
    "sg:city":"Glebe Point",
    "sg:classifiers":[
        {
            "category":"Real Estate",
            "subcategory":"Real Estate Agent",
            "type":"Services"
        }
    ],
    "sg:phone":"+61 408 472 507",
    "sg:postcode":"2037",
    "sg:province":"NSW",
    "wof:name":"Richard Ware Real Estate",
    "wof:placetype":"venue"
},
  "geometry": {"coordinates":[151.184249878,-33.8760681152],"type":"Point"}
}