{
  "type": "Feature",
  "properties": {
    "addr:full":"42 Forest St Woodend VIC 3442",
    "addr:housenumber":"42",
    "addr:postcode":"3442",
    "addr:street":"Forest St",
    "iso:country":"AU",
    "sg:address":"42 Forest St",
    "sg:city":"Woodend",
    "sg:classifiers":[
        {
            "category":"Education",
            "subcategory":"University",
            "type":"Public Place"
        }
    ],
    "sg:phone":"+61 3 5427 3361",
    "sg:postcode":"3442",
    "sg:province":"VIC",
    "sg:tags":[
        "educational",
        "organisation",
        "cultural"
    ],
    "wof:name":"Woodend & District Heritage Society",
    "wof:placetype":"venue"
},
  "geometry": {"coordinates":[144.526321411,-37.3546600342],"type":"Point"}
}