{
  "type": "Feature",
  "properties": {
    "addr:full":"5 Warneford St South Hobart TAS 7004",
    "addr:housenumber":"5",
    "addr:postcode":"7004",
    "addr:street":"Warneford St",
    "iso:country":"AU",
    "sg:address":"5 Warneford St",
    "sg:city":"South Hobart",
    "sg:classifiers":[
        {
            "category":"Health Services",
            "subcategory":"Doctor",
            "type":"Services"
        }
    ],
    "sg:phone":"+61 3 6231 0385",
    "sg:postcode":"7004",
    "sg:province":"TAS",
    "sg:tags":[
        "medical",
        "practitioner"
    ],
    "wof:name":"Moore Philip J",
    "wof:placetype":"venue"
},
  "geometry": {"coordinates":[147.32043457,-42.8895835876],"type":"Point"}
}