{
  "type": "Feature",
  "properties": {
    "iso:country":"AU",
    "sg:address":"L1/ 224 Hutt St",
    "sg:city":"Adelaide",
    "sg:classifiers":[
        {
            "category":"Sports & Exercise",
            "subcategory":"Gym",
            "type":"Entertainment"
        }
    ],
    "sg:phone":"+61 8 8227 0722",
    "sg:postcode":"5000",
    "sg:province":"SA",
    "sg:tags":[
        "personal",
        "trainer",
        "fitness"
    ],
    "wof:name":"Life Personal Trainers",
    "wof:placetype":"venue"
},
  "geometry": {"coordinates":[138.61265564000001,-34.9331588745],"type":"Point"}
}