{
  "type": "Feature",
  "properties": {
    "iso:country":"AU",
    "sg:address":"134 Blues Point Rd",
    "sg:city":"McMahons Point",
    "sg:classifiers":[
        {
            "category":"Shopping",
            "subcategory":"Clothing, Apparel, & Fashions",
            "type":"Retail Goods"
        }
    ],
    "sg:phone":"+61 2 9954 1188",
    "sg:postcode":"2060",
    "sg:province":"NSW",
    "sg:tags":[
        "lady",
        "wear"
    ],
    "wof:name":"Moore & More",
    "wof:placetype":"venue"
},
  "geometry": {"coordinates":[151.20408630399999,-33.8446884155],"type":"Point"}
}