{
  "type": "Feature",
  "properties": {
    "iso:country":"AU",
    "sg:address":"Yorketown Rd",
    "sg:city":"Brentwood",
    "sg:classifiers":[
        {
            "category":"Building & Trades",
            "subcategory":"Construction",
            "type":"Services"
        }
    ],
    "sg:phone":"+61 8 8853 4226",
    "sg:postcode":"5575",
    "sg:province":"SA",
    "sg:tags":[
        "renovation",
        "alterations",
        "extension",
        "contractor"
    ],
    "wof:name":"Johnson I M & C A",
    "wof:placetype":"venue"
},
  "geometry": {"coordinates":[137.49659729000001,-34.864151001],"type":"Point"}
}