{
  "type": "Feature",
  "properties": {
    "addr:full":"161 Princes Hwy Corrimal NSW 2518",
    "addr:housenumber":"161",
    "addr:postcode":"2518",
    "addr:street":"Princes Hwy",
    "iso:country":"AU",
    "sg:address":"161 Princes Hwy",
    "sg:city":"Corrimal",
    "sg:classifiers":[
        {
            "category":"Health Services",
            "subcategory":"Doctor",
            "type":"Services"
        }
    ],
    "sg:phone":"+61 2 4284 1888",
    "sg:postcode":"2518",
    "sg:province":"NSW",
    "sg:tags":[
        "medical",
        "practitioner"
    ],
    "wof:name":"Komora K Dr",
    "wof:placetype":"venue"
},
  "geometry": {"coordinates":[150.896545,-34.373909],"type":"Point"}
}