{
  "type": "Feature",
  "properties": {
    "iso:country":"AU",
    "sg:address":"39b High St",
    "sg:city":"Burnside",
    "sg:classifiers":[
        {
            "category":"Insurance",
            "subcategory":"Insurance Agent",
            "type":"Services"
        }
    ],
    "sg:phone":"+61 8 8364 1311",
    "sg:postcode":"5066",
    "sg:province":"SA",
    "sg:tags":[
        "broker"
    ],
    "wof:name":"Clayton A R & Associates",
    "wof:placetype":"venue"
},
  "geometry": {"coordinates":[138.665252686,-34.9361000061],"type":"Point"}
}