{
  "type": "Feature",
  "properties": {
    "iso:country":"AU",
    "sg:address":"58 Welington St",
    "sg:city":"Virginia",
    "sg:phone":"+61 410 114 474",
    "sg:postcode":"4014",
    "sg:province":"QLD",
    "wof:name":"Micks Tank Installations",
    "wof:placetype":"venue"
},
  "geometry": {"coordinates":[153.069458008,-27.3782272339],"type":"Point"}
}