{
  "type": "Feature",
  "properties": {
    "addr:full":"1080 Mate St North Albury NSW 2640",
    "addr:postcode":"1080;2640",
    "addr:street":"Mate St North",
    "iso:country":"AU",
    "sg:address":"1080 Mate St",
    "sg:city":"North Albury",
    "sg:classifiers":[
        {
            "category":"Personal",
            "subcategory":"Beauty Salon",
            "type":"Services"
        }
    ],
    "sg:phone":"+61 2 6040 7114",
    "sg:postcode":"2640",
    "sg:province":"NSW",
    "wof:name":"Setaro Haircutters For Ladies",
    "wof:placetype":"venue"
},
  "geometry": {"coordinates":[146.933425903,-36.0541763306],"type":"Point"}
}