{
  "type": "Feature",
  "properties": {
    "addr:full":"PO Box 351 Mildura Centre Plaza VIC 3500",
    "addr:postcode":"3500",
    "iso:country":"AU",
    "sg:address":"PO Box 351",
    "sg:city":"Mildura Centre Plaza",
    "sg:classifiers":[
        {
            "category":"Home & Garden",
            "subcategory":"Carpets & Floor Coverings",
            "type":"Retail Goods"
        }
    ],
    "sg:phone":"+61 417 390 087",
    "sg:postcode":"3500",
    "sg:province":"VIC",
    "sg:tags":[
        "tile",
        "wall",
        "layer"
    ],
    "wof:name":"Dedman Jack",
    "wof:placetype":"venue"
},
  "geometry": {"coordinates":[142.154098511,-34.2107391357],"type":"Point"}
}