{
  "type": "Feature",
  "properties": {
    "addr:full":"3 Dover St Wilston QLD 4051",
    "addr:housenumber":"3",
    "addr:postcode":"4051",
    "addr:street":"Dover St",
    "iso:country":"AU",
    "sg:address":"3 Dover St",
    "sg:city":"Wilston",
    "sg:classifiers":[
        {
            "category":"Building & Trades",
            "subcategory":"Plumbing",
            "type":"Services"
        }
    ],
    "sg:phone":"+61 7 3856 4786",
    "sg:postcode":"4051",
    "sg:province":"QLD",
    "sg:tags":[
        "plumber",
        "gasfitters"
    ],
    "wof:name":"Bowes Plumbing",
    "wof:placetype":"venue"
},
  "geometry": {"coordinates":[153.015335083,-27.4346847534],"type":"Point"}
}