{
  "type": "Feature",
  "properties": {
    "iso:country":"AU",
    "sg:address":"19 Wrights Rd",
    "sg:city":"Kellyville",
    "sg:classifiers":[
        {
            "category":"Building & Trades",
            "subcategory":"Construction",
            "type":"Services"
        }
    ],
    "sg:phone":"+61 415 628 991",
    "sg:postcode":"2153",
    "sg:province":"NSW",
    "sg:tags":[
        "contractor"
    ],
    "wof:name":"SGC Rural Contracting",
    "wof:placetype":"venue"
},
  "geometry": {"coordinates":[150.96461486800001,-33.7169723511],"type":"Point"}
}