{
  "type": "Feature",
  "properties": {
    "iso:country":"AU",
    "sg:address":"Unit 1, 84-90 Lakewood Blv",
    "sg:city":"Braeside",
    "sg:classifiers":[
        {
            "category":"Shopping",
            "subcategory":"Computers & Home Electronics",
            "type":"Retail Goods"
        }
    ],
    "sg:phone":"+61 3 9590 9196",
    "sg:postcode":"3195",
    "sg:province":"VIC",
    "sg:tags":[
        "wholesaler",
        "equipment",
        "electronic",
        "mfrs"
    ],
    "wof:name":"Cole Innovation & Design Pty Ltd",
    "wof:placetype":"venue"
},
  "geometry": {"coordinates":[145.11581420900001,-38.0014953613],"type":"Point"}
}