{
  "type": "Feature",
  "properties": {
    "addr:full":"80 Wedge St Epping VIC 3076",
    "addr:housenumber":"80",
    "addr:postcode":"3076",
    "addr:street":"Wedge St",
    "iso:country":"AU",
    "sg:address":"80 Wedge St",
    "sg:city":"Epping",
    "sg:classifiers":[
        {
            "category":"Retail",
            "subcategory":"Auto Repair",
            "type":"Services"
        }
    ],
    "sg:phone":"+61 3 9401 1108",
    "sg:postcode":"3076",
    "sg:province":"VIC",
    "sg:tags":[
        "repairer",
        "motor",
        "engineer"
    ],
    "wof:name":"Horman Service Centre",
    "wof:placetype":"venue"
},
  "geometry": {"coordinates":[145.02212524399999,-37.6503105164],"type":"Point"}
}