{
  "type": "Feature",
  "properties": {
    "addr:full":"484- 486 Geelong Rd West Footscray VIC 3012",
    "addr:housenumber":"486",
    "addr:postcode":"3012",
    "addr:street":"Geelong Rd",
    "iso:country":"AU",
    "sg:address":"484- 486 Geelong Rd",
    "sg:city":"West Footscray",
    "sg:classifiers":[
        {
            "category":"Autos & Motor Vehicles",
            "subcategory":"Automobile Sales",
            "type":"Retail Goods"
        }
    ],
    "sg:phone":"+61 3 9315 2000",
    "sg:postcode":"3012",
    "sg:province":"VIC",
    "sg:tags":[
        "car",
        "used"
    ],
    "wof:name":"Racecourse Motor Co",
    "wof:placetype":"venue"
},
  "geometry": {"coordinates":[144.86154174800001,-37.8129692078],"type":"Point"}
}