{
  "type": "Feature",
  "properties": {
    "iso:country":"AU",
    "sg:address":"219 Winterfold Rd",
    "sg:city":"Coolbellup",
    "sg:classifiers":[
        {
            "category":"Social Services",
            "subcategory":"Child Care",
            "type":"Services"
        }
    ],
    "sg:phone":"+61 8 9337 2455",
    "sg:postcode":"6163",
    "sg:province":"WA",
    "wof:name":"Meerilinga Early learning Centre",
    "wof:placetype":"venue"
},
  "geometry": {"coordinates":[115.804169,-32.07457],"type":"Point"}
}