{
  "type": "Feature",
  "properties": {
    "addr:full":"22 Ralph Black Drv North Wollongong NSW 2500",
    "addr:housenumber":"22",
    "addr:postcode":"2500",
    "addr:street":"Ralph Black Drv North",
    "iso:country":"AU",
    "sg:address":"22 Ralph Black Drv",
    "sg:city":"North Wollongong",
    "sg:classifiers":[
        {
            "category":"Professional",
            "subcategory":"Art Services",
            "type":"Services"
        }
    ],
    "sg:phone":"+61 2 4226 9422",
    "sg:postcode":"2500",
    "sg:province":"NSW",
    "sg:tags":[
        "graphic",
        "designer"
    ],
    "wof:name":"South Coast Graphics Printers",
    "wof:placetype":"venue"
},
  "geometry": {"coordinates":[150.89318800000001,-34.408127],"type":"Point"}
}