{
  "type": "Feature",
  "properties": {
    "addr:full":"131 Paisley St Footscray VIC 3011",
    "addr:housenumber":"131",
    "addr:postcode":"3011",
    "addr:street":"Paisley St",
    "iso:country":"AU",
    "sg:address":"131 Paisley St",
    "sg:city":"Footscray",
    "sg:classifiers":[
        {
            "category":"Professional",
            "subcategory":"Accounting & Tax Preparation",
            "type":"Services"
        }
    ],
    "sg:phone":"+61 3 9687 7591",
    "sg:postcode":"3011",
    "sg:province":"VIC",
    "sg:tags":[
        "consultant",
        "taxation"
    ],
    "wof:name":"City Taxation Services",
    "wof:placetype":"venue"
},
  "geometry": {"coordinates":[144.893112183,-37.8002586365],"type":"Point"}
}