{
  "type": "Feature",
  "properties": {
    "addr:full":"Woodbine St Warracknabeal VIC 3393",
    "addr:postcode":"3393",
    "addr:street":"Woodbine St",
    "iso:country":"AU",
    "sg:address":"Woodbine St",
    "sg:city":"Warracknabeal",
    "sg:classifiers":[
        {
            "category":"Education",
            "subcategory":"School",
            "type":"Public Place"
        }
    ],
    "sg:phone":"+61 3 5398 2564",
    "sg:postcode":"3393",
    "sg:province":"VIC",
    "sg:tags":[
        "state",
        "except",
        "nsw"
    ],
    "wof:name":"Warracknabeal Special Development School",
    "wof:placetype":"venue"
},
  "geometry": {"coordinates":[142.38713073700001,-36.2491493225],"type":"Point"}
}