{
  "type": "Feature",
  "properties": {
    "addr:full":"2 Leswell St Woollahra NSW 2025",
    "addr:housenumber":"2",
    "addr:postcode":"2025",
    "addr:street":"Leswell St",
    "iso:country":"AU",
    "sg:address":"2 Leswell St",
    "sg:city":"Woollahra",
    "sg:classifiers":[
        {
            "category":"Professional",
            "subcategory":"Accounting & Tax Preparation",
            "type":"Services"
        }
    ],
    "sg:phone":"+61 2 9389 0511",
    "sg:postcode":"2025",
    "sg:province":"NSW",
    "sg:tags":[
        "accountant",
        "auditor"
    ],
    "wof:name":"Nurmi John Arthur",
    "wof:placetype":"venue"
},
  "geometry": {"coordinates":[151.24473571799999,-33.8902664185],"type":"Point"}
}