{
  "type": "Feature",
  "properties": {
    "iso:country":"AU",
    "sg:address":"PO Box 218",
    "sg:city":"Coldstream",
    "sg:classifiers":[
        {
            "category":"Professional",
            "subcategory":"Secretarial Services",
            "type":"Services"
        }
    ],
    "sg:phone":"+61 3 9739 1559",
    "sg:postcode":"3770",
    "sg:province":"VIC",
    "sg:tags":[
        "typing"
    ],
    "wof:name":"Gottsche K R",
    "wof:placetype":"venue"
},
  "geometry": {"coordinates":[145.378525,-37.724941],"type":"Point"}
}