{
  "type": "Feature",
  "properties": {
    "addr:full":"Unit 1/ 12 Keates Rd Armadale WA 6112",
    "addr:housenumber":"12",
    "addr:postcode":"6112",
    "addr:street":"Keates Rd",
    "iso:country":"AU",
    "sg:address":"Unit 1/ 12 Keates Rd",
    "sg:city":"Armadale",
    "sg:classifiers":[
        {
            "category":"Home & Garden",
            "subcategory":"Hardware",
            "type":"Retail Goods"
        }
    ],
    "sg:phone":"+61 8 9525 5992",
    "sg:postcode":"6112",
    "sg:province":"WA",
    "sg:tags":[
        "product",
        "treatment",
        "floor"
    ],
    "wof:name":"Leeder Cleaning Services.",
    "wof:placetype":"venue"
},
  "geometry": {"coordinates":[116.012809753,-32.1712722778],"type":"Point"}
}