{
  "type": "Feature",
  "properties": {
    "addr:full":"92-96 Hannan Street Kalgoorlie WA 6430",
    "addr:housenumber":"92-96",
    "addr:postcode":"6430",
    "addr:street":"Hannan Street",
    "iso:country":"AU",
    "sg:address":"92-96 Hannan Street",
    "sg:city":"Kalgoorlie",
    "sg:classifiers":[
        {
            "category":"Real Estate",
            "subcategory":"Real Estate Agent",
            "type":"Services"
        }
    ],
    "sg:phone":"+61 8 9021 2488",
    "sg:postcode":"6430",
    "sg:province":"WA",
    "wof:name":"Wades First National",
    "wof:placetype":"venue"
},
  "geometry": {"coordinates":[121.467727661,-30.7516136169],"type":"Point"}
}