{
  "type": "Feature",
  "properties": {
    "addr:full":"30 Hastings St Wauchope NSW 2446",
    "addr:housenumber":"30",
    "addr:postcode":"2446",
    "addr:street":"Hastings St",
    "iso:country":"AU",
    "sg:address":"30 Hastings St",
    "sg:city":"Wauchope",
    "sg:classifiers":[
        {
            "category":"Health Services",
            "subcategory":"Health Practitioner",
            "type":"Services"
        }
    ],
    "sg:phone":"+61 2 6586 4290",
    "sg:postcode":"2446",
    "sg:province":"NSW",
    "sg:tags":[
        "alternative"
    ],
    "wof:name":"Essential Being",
    "wof:placetype":"venue"
},
  "geometry": {"coordinates":[152.73287999999999,-31.45524],"type":"Point"}
}