{
  "type": "Feature",
  "properties": {
    "addr:full":"120 Kahibah Rd Kahibah NSW 2290",
    "addr:housenumber":"120",
    "addr:postcode":"2290",
    "addr:street":"Kahibah Rd",
    "iso:country":"AU",
    "sg:address":"120 Kahibah Rd",
    "sg:city":"Kahibah",
    "sg:classifiers":[
        {
            "category":"Utilities",
            "type":"Services"
        }
    ],
    "sg:phone":"+61 2 4942 1785",
    "sg:postcode":"2290",
    "sg:province":"NSW",
    "sg:tags":[
        "refrigeration",
        "industrial",
        "commercial",
        "retail"
    ],
    "wof:name":"All Areas Fridge Seals",
    "wof:placetype":"venue"
},
  "geometry": {"coordinates":[151.70588684099999,-32.9648246765],"type":"Point"}
}