{
  "type": "Feature",
  "properties": {
    "addr:full":"292 Hoddle St Abbotsford VIC 3067",
    "addr:housenumber":"292",
    "addr:postcode":"3067",
    "addr:street":"Hoddle St",
    "iso:country":"AU",
    "sg:address":"292 Hoddle St",
    "sg:city":"Abbotsford",
    "sg:classifiers":[
        {
            "category":"Utilities",
            "subcategory":"Electric",
            "type":"Services"
        }
    ],
    "sg:phone":"+61 3 9001 3000",
    "sg:postcode":"3067",
    "sg:province":"VIC",
    "sg:tags":[
        "electrical",
        "contractor"
    ],
    "wof:name":"Nuvo Electrics",
    "wof:placetype":"venue"
},
  "geometry": {"coordinates":[144.99356079099999,-37.7975845337],"type":"Point"}
}