{
  "type": "Feature",
  "properties": {
    "iso:country":"AU",
    "sg:address":"565 Keilor Rd",
    "sg:city":"Niddrie",
    "sg:classifiers":[
        {
            "category":"Shopping",
            "subcategory":"Bicycles & Sporting Goods",
            "type":"Retail Goods"
        }
    ],
    "sg:phone":"+61 3 9374 2299",
    "sg:postcode":"3042",
    "sg:province":"VIC",
    "sg:tags":[
        "chemical",
        "equipment",
        "pool",
        "swimming"
    ],
    "wof:name":"A Balint Zoltans Automatic Pool Cleaner",
    "wof:placetype":"venue"
},
  "geometry": {"coordinates":[144.88183593799999,-37.7335205078],"type":"Point"}
}