{
  "type": "Feature",
  "properties": {
    "addr:full":"Unit 2/ 54 Kremzow Rd Brendale QLD 4500",
    "addr:housenumber":"54",
    "addr:postcode":"4500",
    "addr:street":"Kremzow Rd",
    "iso:country":"AU",
    "sg:address":"Unit 2/ 54 Kremzow Rd",
    "sg:city":"Brendale",
    "sg:classifiers":[
        {
            "category":"Wholesale",
            "subcategory":"Apparel",
            "type":"Manufacturing & Wholesale Goods"
        }
    ],
    "sg:phone":"+61 7 3889 7022",
    "sg:postcode":"4500",
    "sg:province":"QLD",
    "sg:tags":[
        "wholesaler",
        "mfrs",
        "uniform"
    ],
    "wof:name":"SSA Sports Suits Australia",
    "wof:placetype":"venue"
},
  "geometry": {"coordinates":[152.98260498100001,-27.3173408508],"type":"Point"}
}