{
  "type": "Feature",
  "properties": {
    "iso:country":"AU",
    "sg:address":"293 Abercrombie St",
    "sg:city":"Chippendale",
    "sg:classifiers":[
        {
            "category":"Wholesale",
            "subcategory":"Apparel",
            "type":"Manufacturing & Wholesale Goods"
        }
    ],
    "sg:phone":"+61 2 9698 5700",
    "sg:postcode":"2008",
    "sg:province":"NSW",
    "sg:tags":[
        "wholesaler",
        "mfrs",
        "dress"
    ],
    "wof:name":"Whiteline",
    "wof:placetype":"venue"
},
  "geometry": {"coordinates":[151.19424438499999,-33.8915023804],"type":"Point"}
}