{
  "type": "Feature",
  "properties": {
    "iso:country":"AU",
    "sg:address":"137 Hobart Rd",
    "sg:city":"Kings Meadows",
    "sg:classifiers":[
        {
            "category":"Wholesale",
            "subcategory":"Medical Equipment & Supplies",
            "type":"Manufacturing & Wholesale Goods"
        }
    ],
    "sg:phone":"+61 1800 201 509",
    "sg:postcode":"7249",
    "sg:province":"TAS",
    "sg:tags":[
        "aids",
        "hearing"
    ],
    "wof:name":"Steven Hooper",
    "wof:placetype":"venue"
},
  "geometry": {"coordinates":[147.16033935600001,-41.4671096802],"type":"Point"}
}