{
  "type": "Feature",
  "properties": {
    "iso:country":"AU",
    "sg:address":"375 St Georges Rd",
    "sg:city":"Thornbury",
    "sg:classifiers":[
        {
            "category":"Fast Food",
            "type":"Food & Drink"
        }
    ],
    "sg:phone":"+61 3 9484 3750",
    "sg:postcode":"3071",
    "sg:province":"VIC",
    "sg:tags":[
        "away",
        "take"
    ],
    "wof:name":"Flamingo's Halal Pizza & Pasta",
    "wof:placetype":"venue"
},
  "geometry": {"coordinates":[144.992919922,-37.7588348389],"type":"Point"}
}