{
  "type": "Feature",
  "properties": {
    "iso:country":"AU",
    "sg:address":"Suite 7/ 37 High St",
    "sg:city":"Yackandandah",
    "sg:classifiers":[
        {
            "category":"Building & Trades",
            "subcategory":"Construction",
            "type":"Services"
        }
    ],
    "sg:phone":"+61 2 6027 1084",
    "sg:postcode":"3749",
    "sg:province":"VIC",
    "sg:tags":[
        "contractor"
    ],
    "wof:name":"Altered Dimensions",
    "wof:placetype":"venue"
},
  "geometry": {"coordinates":[146.83815000000001,-36.312782],"type":"Point"}
}