{
  "type": "Feature",
  "properties": {
    "addr:full":"Suite 105 3 Chester St Oakleigh VIC 3166",
    "addr:housenumber":"3",
    "addr:postcode":"3166",
    "addr:street":"Chester St",
    "iso:country":"AU",
    "sg:address":"Suite 105 3 Chester St",
    "sg:city":"Oakleigh",
    "sg:classifiers":[
        {
            "category":"Banks & Credit Unions",
            "subcategory":"Financial Services",
            "type":"Services"
        }
    ],
    "sg:phone":"+61 3 9530 4740",
    "sg:postcode":"3166",
    "sg:province":"VIC",
    "sg:tags":[
        "planning"
    ],
    "wof:name":"Count Wealth Accountants",
    "wof:placetype":"venue"
},
  "geometry": {"coordinates":[145.087646484,-37.8990859985],"type":"Point"}
}