{
  "type": "Feature",
  "properties": {
    "addr:full":"PO Box 582 Stepney SA 5069",
    "addr:postcode":"5069",
    "iso:country":"AU",
    "sg:address":"PO Box 582",
    "sg:city":"Stepney",
    "sg:classifiers":[
        {
            "category":"Building & Trades",
            "subcategory":"Landscaping Services",
            "type":"Services"
        }
    ],
    "sg:phone":"+61 419 627 372",
    "sg:postcode":"5069",
    "sg:province":"SA",
    "sg:tags":[
        "gardener"
    ],
    "wof:name":"Neighbour Labour",
    "wof:placetype":"venue"
},
  "geometry": {"coordinates":[138.626785278,-34.9107894897],"type":"Point"}
}