{
  "type": "Feature",
  "properties": {
    "addr:full":"27 Lyndhurst St Richmond VIC 3121",
    "addr:housenumber":"27",
    "addr:postcode":"3121",
    "addr:street":"Lyndhurst St",
    "iso:country":"AU",
    "sg:address":"27 Lyndhurst St",
    "sg:city":"Richmond",
    "sg:classifiers":[
        {
            "category":"Professional",
            "subcategory":"Management & Consulting",
            "type":"Services"
        }
    ],
    "sg:phone":"+61 413 592 287",
    "sg:postcode":"3121",
    "sg:province":"VIC",
    "sg:tags":[
        "consultant",
        "business"
    ],
    "wof:name":"Dimou Dimitria",
    "wof:placetype":"venue"
},
  "geometry": {"coordinates":[145.00071716299999,-37.819896698],"type":"Point"}
}