{
  "type": "Feature",
  "properties": {
    "addr:full":"The Basement, 3 Wetherill St Leichhardt NSW 2040",
    "addr:housenumber":"3",
    "addr:postcode":"2040",
    "addr:street":"Wetherill St",
    "iso:country":"AU",
    "sg:address":"The Basement, 3 Wetherill St",
    "sg:city":"Leichhardt",
    "sg:classifiers":[
        {
            "category":"Health Services",
            "subcategory":"Health Practitioner",
            "type":"Services"
        }
    ],
    "sg:phone":"+61 1300 784 724",
    "sg:postcode":"2040",
    "sg:province":"NSW",
    "sg:tags":[
        "physiotherapist"
    ],
    "wof:name":"Bounce Rehab",
    "wof:placetype":"venue"
},
  "geometry": {"coordinates":[151.15728799999999,-33.882999],"type":"Point"}
}