{
  "type": "Feature",
  "properties": {
    "addr:full":"64 Stacey St Bankstown NSW 2200",
    "addr:housenumber":"64",
    "addr:postcode":"2200",
    "addr:street":"Stacey St",
    "iso:country":"AU",
    "sg:address":"64 Stacey St",
    "sg:city":"Bankstown",
    "sg:classifiers":[
        {
            "category":"Government",
            "subcategory":"Fire Station",
            "type":"Public Place"
        }
    ],
    "sg:phone":"+61 2 9796 8123",
    "sg:postcode":"2200",
    "sg:province":"NSW",
    "sg:tags":[
        "equipment",
        "protection",
        "consultant"
    ],
    "wof:name":"R. B. Maher Electric Pty Ltd",
    "wof:placetype":"venue"
},
  "geometry": {"coordinates":[151.040131,-33.906914],"type":"Point"}
}