{
  "type": "Feature",
  "properties": {
    "iso:country":"AU",
    "sg:address":"1199 Riverway Drv",
    "sg:city":"Rasmussen",
    "sg:classifiers":[
        {
            "category":"Health Services",
            "subcategory":"Dentist",
            "type":"Services"
        }
    ],
    "sg:phone":"+61 7 4789 2288",
    "sg:postcode":"4815",
    "sg:province":"QLD",
    "wof:name":"Townsville Family Dental",
    "wof:placetype":"venue"
},
  "geometry": {"coordinates":[146.731674,-19.363941],"type":"Point"}
}