{
  "type": "Feature",
  "properties": {
    "iso:country":"AU",
    "sg:address":"Crn Toona Way & Bottlebrush Drv",
    "sg:city":"Glenning Valley",
    "sg:classifiers":[
        {
            "category":"Education",
            "subcategory":"Kindergarten",
            "type":"Public Place"
        }
    ],
    "sg:phone":"+61 2 4389 1788",
    "sg:postcode":"2261",
    "sg:province":"NSW",
    "sg:tags":[
        "pre-schools"
    ],
    "wof:name":"Glenning Valley Child Care Centre",
    "wof:placetype":"venue"
},
  "geometry": {"coordinates":[151.428574,-33.334492],"type":"Point"}
}