{
  "type": "Feature",
  "properties": {
    "addr:full":"Nalinga Rd Violet Town VIC 3669",
    "addr:postcode":"3669",
    "addr:street":"Nalinga Rd",
    "iso:country":"AU",
    "sg:address":"Nalinga Rd",
    "sg:city":"Violet Town",
    "sg:classifiers":[
        {
            "category":"Farming",
            "subcategory":"Farm",
            "type":"Manufacturing & Wholesale Goods"
        }
    ],
    "sg:phone":"+61 3 5798 1440",
    "sg:postcode":"3669",
    "sg:province":"VIC",
    "sg:tags":[
        "farmer"
    ],
    "wof:name":"Sloan M B",
    "wof:placetype":"venue"
},
  "geometry": {"coordinates":[145.80406189000001,-36.6087913513],"type":"Point"}
}