{
  "type": "Feature",
  "properties": {
    "addr:full":"20 Princeton Ave Adamstown Heights NSW 2289",
    "addr:housenumber":"20",
    "addr:postcode":"2289",
    "addr:street":"Princeton Ave Adamstown",
    "iso:country":"AU",
    "sg:address":"20 Princeton Ave",
    "sg:city":"Adamstown Heights",
    "sg:classifiers":[
        {
            "category":"Building & Trades",
            "subcategory":"Plumbing",
            "type":"Services"
        }
    ],
    "sg:phone":"+61 2 4952 5031",
    "sg:postcode":"2289",
    "sg:province":"NSW",
    "sg:tags":[
        "consultant"
    ],
    "wof:name":"Crosland Bill",
    "wof:placetype":"venue"
},
  "geometry": {"coordinates":[151.707687378,-32.9416923523],"type":"Point"}
}