{
  "type": "Feature",
  "properties": {
    "addr:full":"Esprit/Grace Bros Lvl 1 Penrith Plaza Henry St Penrith NSW 2750",
    "addr:postcode":"2750",
    "addr:street":"Henry St",
    "iso:country":"AU",
    "sg:address":"Esprit/Grace Bros Lvl 1 Penrith Plaza Henry St",
    "sg:city":"Penrith",
    "sg:classifiers":[
        {
            "category":"Shopping",
            "subcategory":"Clothing, Apparel, & Fashions",
            "type":"Retail Goods"
        }
    ],
    "sg:phone":"+61 2 4721 4331",
    "sg:postcode":"2750",
    "sg:province":"NSW",
    "sg:tags":[
        "lady",
        "wear"
    ],
    "wof:name":"Esprit Retail Pty Ltd",
    "wof:placetype":"venue"
},
  "geometry": {"coordinates":[150.68374633799999,-33.7659645081],"type":"Point"}
}