{
  "type": "Feature",
  "properties": {
    "addr:full":"46 Victoria Pde Coochiemudlo Island QLD 4184",
    "addr:housenumber":"46",
    "addr:postcode":"4184",
    "addr:street":"Victoria Pde",
    "iso:country":"AU",
    "sg:address":"46 Victoria Pde",
    "sg:city":"Coochiemudlo Island",
    "sg:classifiers":[
        {
            "category":"Real Estate",
            "subcategory":"Real Estate Services",
            "type":"Services"
        }
    ],
    "sg:phone":"+61 7 3207 8207",
    "sg:postcode":"4184",
    "sg:province":"QLD",
    "sg:tags":[
        "house",
        "hire",
        "boat"
    ],
    "wof:name":"Coochie Boat Hire",
    "wof:placetype":"venue"
},
  "geometry": {"coordinates":[153.33456420900001,-27.5737857819],"type":"Point"}
}