{
  "type": "Feature",
  "properties": {
    "addr:full":"6 Roslyn Pl Cherrybrook NSW 2126",
    "addr:housenumber":"6",
    "addr:postcode":"2126",
    "addr:street":"Roslyn Pl",
    "iso:country":"AU",
    "sg:address":"6 Roslyn Pl",
    "sg:city":"Cherrybrook",
    "sg:classifiers":[
        {
            "category":"Banks & Credit Unions",
            "subcategory":"Atm",
            "type":"Services"
        }
    ],
    "sg:phone":"+61 2 9899 8264",
    "sg:postcode":"2126",
    "sg:province":"NSW",
    "sg:tags":[
        "detector",
        "gas"
    ],
    "wof:name":"Mine Instrument Services Pty Ltd",
    "wof:placetype":"venue"
},
  "geometry": {"coordinates":[151.03309631400001,-33.7296028137],"type":"Point"}
}