{
  "type": "Feature",
  "properties": {
    "iso:country":"AU",
    "sg:address":"119 Plenty Rd",
    "sg:city":"Bundoora",
    "sg:classifiers":[
        {
            "category":"Health Services",
            "subcategory":"Doctor",
            "type":"Services"
        }
    ],
    "sg:phone":"+61 3 9466 8466",
    "sg:postcode":"3083",
    "sg:province":"VIC",
    "sg:tags":[
        "medical",
        "practitioner"
    ],
    "wof:name":"Elliott Ross",
    "wof:placetype":"venue"
},
  "geometry": {"coordinates":[145.06149292000001,-37.6930427551],"type":"Point"}
}