{
  "type": "Feature",
  "properties": {
    "iso:country":"AU",
    "sg:address":"15 Byron St",
    "sg:city":"Bangalow",
    "sg:classifiers":[
        {
            "category":"Personal",
            "subcategory":"Beauty Salon",
            "type":"Services"
        }
    ],
    "sg:phone":"+61 2 6687 1888",
    "sg:postcode":"2479",
    "sg:province":"NSW",
    "sg:tags":[
        "hairdresser"
    ],
    "wof:name":"Bangalow Hairdressing",
    "wof:placetype":"venue"
},
  "geometry": {"coordinates":[153.52339172399999,-28.6864871979],"type":"Point"}
}