{
  "type": "Feature",
  "properties": {
    "iso:country":"AU",
    "sg:address":"432a Old Northern Rd",
    "sg:city":"Glenhaven",
    "sg:classifiers":[
        {
            "category":"Personal",
            "subcategory":"Massage",
            "type":"Services"
        }
    ],
    "sg:phone":"+61 2 9899 6977",
    "sg:postcode":"2156",
    "sg:province":"NSW",
    "sg:tags":[
        "therapy"
    ],
    "wof:name":"Inner Harmony & Health",
    "wof:placetype":"venue"
},
  "geometry": {"coordinates":[151.01100158700001,-33.7087135315],"type":"Point"}
}