{
  "type": "Feature",
  "properties": {
    "addr:full":"Cnr Bougainville & Luxford Rds Lethbridge Park NSW 2770",
    "addr:postcode":"2770",
    "addr:street":"Cnr Bougainville & Luxford Rds",
    "iso:country":"AU",
    "sg:address":"Cnr Bougainville & Luxford Rds",
    "sg:city":"Lethbridge Park",
    "sg:classifiers":[
        {
            "category":"Food & Beverages",
            "subcategory":"Groceries & Convenience Stores",
            "type":"Retail Goods"
        }
    ],
    "sg:phone":"+61 2 9628 1756",
    "sg:postcode":"2770",
    "sg:province":"NSW",
    "wof:name":"Shell Select",
    "wof:placetype":"venue"
},
  "geometry": {"coordinates":[150.798370361,-33.7363815308],"type":"Point"}
}