{
  "type": "Feature",
  "properties": {
    "addr:full":"PO Box 116 Prahran VIC 8802",
    "addr:postcode":"8802",
    "iso:country":"AU",
    "sg:address":"PO Box 116",
    "sg:city":"Prahran",
    "sg:classifiers":[
        {
            "category":"Building & Trades",
            "subcategory":"Landscaping Services",
            "type":"Services"
        }
    ],
    "sg:phone":"+61 3 9533 7553",
    "sg:postcode":"8802",
    "sg:province":"VIC",
    "sg:tags":[
        "inspection"
    ],
    "wof:name":"Astra Building Services Pty Ltd",
    "wof:placetype":"venue"
},
  "geometry": {"coordinates":[144.99342346200001,-37.8513412476],"type":"Point"}
}