{
  "type": "Feature",
  "properties": {
    "addr:full":"Park Rd Goulburn NSW 2580",
    "addr:postcode":"2580",
    "addr:street":"Park Rd",
    "iso:country":"AU",
    "sg:address":"Park Rd",
    "sg:city":"Goulburn",
    "sg:classifiers":[
        {
            "category":"Education",
            "subcategory":"School",
            "type":"Public Place"
        }
    ],
    "sg:phone":"+61 2 4821 4007",
    "sg:postcode":"2580",
    "sg:province":"NSW",
    "sg:tags":[
        "state",
        "-",
        "nsw"
    ],
    "wof:name":"East Goulburn Primary School",
    "wof:placetype":"venue"
},
  "geometry": {"coordinates":[149.72091674800001,-34.7591209412],"type":"Point"}
}