{
  "type": "Feature",
  "properties": {
    "addr:full":"3/ 129 Smith St Darwin NT 0800",
    "addr:housenumber":"/ 129",
    "addr:postcode":"nt 0800",
    "addr:street":"Smith St",
    "iso:country":"AU",
    "sg:address":"3/ 129 Smith St",
    "sg:city":"Darwin",
    "sg:classifiers":[
        {
            "category":"Government",
            "subcategory":"Court House",
            "type":"Public Place"
        }
    ],
    "sg:phone":"+61 8 8941 5350",
    "sg:postcode":"0800",
    "sg:province":"NT",
    "sg:tags":[
        "personal",
        "marriage",
        "family",
        "counselling"
    ],
    "wof:name":"Dianne Knox",
    "wof:placetype":"venue"
},
  "geometry": {"coordinates":[130.835739136,-12.4570541382],"type":"Point"}
}