{
  "type": "Feature",
  "properties": {
    "iso:country":"AU",
    "sg:address":"278 Manns Rd",
    "sg:city":"Gosford West",
    "sg:classifiers":[
        {
            "category":"Coffee & Tea",
            "type":"Food & Drink"
        }
    ],
    "sg:phone":"+61 2 4324 4300",
    "sg:postcode":"2250",
    "sg:province":"NSW",
    "sg:tags":[
        "kayak",
        "canoe"
    ],
    "wof:name":"Power &#039;N Paddle Marine Sports",
    "wof:placetype":"venue"
},
  "geometry": {"coordinates":[151.319412231,-33.4244918823],"type":"Point"}
}