{
  "type": "Feature",
  "properties": {
    "iso:country":"AU",
    "sg:address":"801 Glenferrie Rd",
    "sg:city":"Hawthorn",
    "sg:classifiers":[
        {
            "category":"Wholesale",
            "subcategory":"Drugs",
            "type":"Manufacturing & Wholesale Goods"
        }
    ],
    "sg:phone":"+61 3 9854 9800",
    "sg:postcode":"3122",
    "sg:province":"VIC",
    "sg:tags":[
        "wholesaler",
        "pharmaceutical",
        "product",
        "mfrs"
    ],
    "wof:name":"AMGEN Australia Pty Ltd",
    "wof:placetype":"venue"
},
  "geometry": {"coordinates":[145.03642273,-37.8159408569],"type":"Point"}
}