{
  "type": "Feature",
  "properties": {
    "addr:full":"Suite 3B, 2 Central Ave Moorabbin VIC 3189",
    "addr:housenumber":"suite 3b 2",
    "addr:postcode":"3189",
    "addr:street":"Central Ave",
    "iso:country":"AU",
    "sg:address":"Suite 3B, 2 Central Ave",
    "sg:city":"Moorabbin",
    "sg:classifiers":[
        {
            "category":"Banks & Credit Unions",
            "subcategory":"Financial Services",
            "type":"Services"
        }
    ],
    "sg:phone":"+61 3 9555 3488",
    "sg:postcode":"3189",
    "sg:province":"VIC",
    "sg:tags":[
        "annuity",
        "rollover",
        "superannuation",
        "consultant"
    ],
    "wof:name":"Corporate Superannuation Services Pty Ltd",
    "wof:placetype":"venue"
},
  "geometry": {"coordinates":[145.03834533700001,-37.9351806641],"type":"Point"}
}