{
  "type": "Feature",
  "properties": {
    "addr:full":"Unit 10/ 5 Goddard St Rockingham WA 6168",
    "addr:housenumber":"/ 5",
    "addr:postcode":"6168",
    "addr:street":"Goddard St",
    "iso:country":"AU",
    "sg:address":"Unit 10/ 5 Goddard St",
    "sg:city":"Rockingham",
    "sg:classifiers":[
        {
            "category":"Insurance",
            "subcategory":"Life Insurance",
            "type":"Services"
        }
    ],
    "sg:phone":"+61 8 9592 1844",
    "sg:postcode":"6168",
    "sg:province":"WA",
    "wof:name":"Westshore Financial Services",
    "wof:placetype":"venue"
},
  "geometry": {"coordinates":[115.742142,-32.287094],"type":"Point"}
}