{
  "type": "Feature",
  "properties": {
    "addr:full":"75 Rundle Rd Salisbury South SA 5106",
    "addr:housenumber":"75",
    "addr:postcode":"5106",
    "addr:street":"Rundle Rd",
    "iso:country":"AU",
    "sg:address":"75 Rundle Rd",
    "sg:city":"Salisbury South",
    "sg:classifiers":[
        {
            "category":"Wholesale",
            "subcategory":"Machinery & Supplies",
            "type":"Manufacturing & Wholesale Goods"
        }
    ],
    "sg:phone":"+61 8 8281 1677",
    "sg:postcode":"5106",
    "sg:province":"SA",
    "sg:tags":[
        "equipment",
        "pneumatic"
    ],
    "wof:name":"Mobile Compressed Air",
    "wof:placetype":"venue"
},
  "geometry": {"coordinates":[138.64460800000001,-34.786102],"type":"Point"}
}