{
  "type": "Feature",
  "properties": {
    "addr:full":"Cnr Gold Coast Hwy & Eighth Ave Palm Beach QLD 4221",
    "addr:postcode":"4221",
    "addr:street":"Gold Coast Hwy & Eighth Ave",
    "iso:country":"AU",
    "sg:address":"Cnr Gold Coast Hwy & Eighth Ave",
    "sg:city":"Palm Beach",
    "sg:classifiers":[
        {
            "category":"Food & Beverages",
            "subcategory":"Supermarket",
            "type":"Retail Goods"
        }
    ],
    "sg:phone":"+61 7 5534 2108",
    "sg:postcode":"4221",
    "sg:province":"QLD",
    "sg:tags":[
        "grocery",
        "store"
    ],
    "wof:name":"Quix Food Stores",
    "wof:placetype":"venue"
},
  "geometry": {"coordinates":[153.472824097,-28.1213474274],"type":"Point"}
}