{
  "type": "Feature",
  "properties": {
    "addr:full":"3 Geneva Rd Alphington VIC 3078",
    "addr:housenumber":"3",
    "addr:postcode":"3078",
    "addr:street":"Geneva Rd",
    "iso:country":"AU",
    "sg:address":"3 Geneva Rd",
    "sg:city":"Alphington",
    "sg:classifiers":[
        {
            "category":"Real Estate",
            "subcategory":"Architect",
            "type":"Services"
        }
    ],
    "sg:phone":"+61 3 9497 4764",
    "sg:postcode":"3078",
    "sg:province":"VIC",
    "wof:name":"BHY Architects",
    "wof:placetype":"venue"
},
  "geometry": {"coordinates":[145.03421020499999,-37.7846794128],"type":"Point"}
}