{
  "type": "Feature",
  "properties": {
    "addr:full":"47 Church St Bega NSW 2550",
    "addr:housenumber":"47",
    "addr:postcode":"2550",
    "addr:street":"Church St",
    "iso:country":"AU",
    "sg:address":"47 Church St",
    "sg:city":"Bega",
    "sg:classifiers":[
        {
            "category":"Arts & Performance",
            "subcategory":"Art Gallery",
            "type":"Entertainment"
        }
    ],
    "sg:phone":"+61 2 6492 5322",
    "sg:postcode":"2550",
    "sg:province":"NSW",
    "wof:name":"Spiral Gallery",
    "wof:placetype":"venue"
},
  "geometry": {"coordinates":[149.84193420400001,-36.6735954285],"type":"Point"}
}