{
  "type": "Feature",
  "properties": {
    "addr:full":"1 Croydon Rd Woodridge QLD 4114",
    "addr:housenumber":"1",
    "addr:postcode":"4114",
    "addr:street":"Croydon Rd",
    "iso:country":"AU",
    "sg:address":"1 Croydon Rd",
    "sg:city":"Woodridge",
    "sg:classifiers":[
        {
            "category":"Professional",
            "subcategory":"Accounting & Tax Preparation",
            "type":"Services"
        }
    ],
    "sg:phone":"+61 7 3209 4388",
    "sg:postcode":"4114",
    "sg:province":"QLD",
    "sg:tags":[
        "consultant",
        "taxation"
    ],
    "wof:name":"Roger Ryan",
    "wof:placetype":"venue"
},
  "geometry": {"coordinates":[153.104125977,-27.6375770569],"type":"Point"}
}