{
  "type": "Feature",
  "properties": {
    "addr:full":"Suite 1/ 15 Albert Ave Broadbeach QLD 4218",
    "addr:housenumber":"15",
    "addr:postcode":"4218",
    "addr:street":"Albert Ave",
    "iso:country":"AU",
    "sg:address":"Suite 1/ 15 Albert Ave",
    "sg:city":"Broadbeach",
    "sg:classifiers":[
        {
            "category":"Building & Trades",
            "subcategory":"Construction",
            "type":"Services"
        }
    ],
    "sg:phone":"+61 7 5504 5589",
    "sg:postcode":"4218",
    "sg:province":"QLD",
    "sg:tags":[
        "contractor"
    ],
    "wof:name":"Shoreline Constructions & Developments Pty Ltd",
    "wof:placetype":"venue"
},
  "geometry": {"coordinates":[153.432174683,-28.0280647278],"type":"Point"}
}