{
  "type": "Feature",
  "properties": {
    "iso:country":"AU",
    "sg:address":"323 Darling St",
    "sg:city":"Balmain",
    "sg:classifiers":[
        {
            "category":"Professional",
            "subcategory":"Accounting & Tax Preparation",
            "type":"Services"
        }
    ],
    "sg:phone":"+61 2 9810 2333",
    "sg:postcode":"2041",
    "sg:province":"NSW",
    "sg:tags":[
        "accountant",
        "auditor"
    ],
    "wof:name":"Sydney Accounting",
    "wof:placetype":"venue"
},
  "geometry": {"coordinates":[151.179565,-33.856647],"type":"Point"}
}