{
  "type": "Feature",
  "properties": {
    "addr:full":"9 Chapel Rd Moorabbin VIC 3189",
    "addr:housenumber":"9",
    "addr:postcode":"3189",
    "addr:street":"Chapel Rd",
    "iso:country":"AU",
    "sg:address":"9 Chapel Rd",
    "sg:city":"Moorabbin",
    "sg:classifiers":[
        {
            "category":"Professional",
            "subcategory":"Computer Services",
            "type":"Services"
        }
    ],
    "sg:phone":"+61 3 9555 4321",
    "sg:postcode":"3189",
    "sg:province":"VIC",
    "sg:tags":[
        "equipment",
        "networking",
        "installation"
    ],
    "wof:name":"Total Computer Maintenance",
    "wof:placetype":"venue"
},
  "geometry": {"coordinates":[145.04728698700001,-37.945148468],"type":"Point"}
}