{
  "type": "Feature",
  "properties": {
    "addr:full":"11-13 Havelock Ave Coogee NSW 2034",
    "addr:housenumber":"11-13",
    "addr:postcode":"2034",
    "addr:street":"Havelock Ave",
    "iso:country":"AU",
    "sg:address":"11-13 Havelock Ave",
    "sg:city":"Coogee",
    "sg:classifiers":[
        {
            "category":"Personal",
            "subcategory":"Beauty Salon",
            "type":"Services"
        }
    ],
    "sg:phone":"+61 2 9665 1951",
    "sg:postcode":"2034",
    "sg:province":"NSW",
    "wof:name":"Access To Beauty",
    "wof:placetype":"venue"
},
  "geometry": {"coordinates":[151.255615234,-33.9242935181],"type":"Point"}
}