{
  "type": "Feature",
  "properties": {
    "iso:country":"AU",
    "sg:address":"Unit 1/ 18 Bradley St",
    "sg:city":"Randwick",
    "sg:classifiers":[
        {
            "category":"Food & Beverages",
            "subcategory":"Fruits & Vegetables",
            "type":"Retail Goods"
        }
    ],
    "sg:phone":"+61 414 498 501",
    "sg:postcode":"2031",
    "sg:province":"NSW",
    "sg:tags":[
        "consultant",
        "catering"
    ],
    "wof:name":"Z - events",
    "wof:placetype":"venue"
},
  "geometry": {"coordinates":[151.23617553700001,-33.9138526917],"type":"Point"}
}