{
  "type": "Feature",
  "properties": {
    "addr:full":"Flinders St East Townsville QLD 4810",
    "addr:postcode":"4810",
    "addr:street":"Flinders St East",
    "iso:country":"AU",
    "sg:address":"Flinders St East",
    "sg:city":"Townsville",
    "sg:classifiers":[
        {
            "category":"Travel",
            "subcategory":"Hotels & Motels",
            "type":"Entertainment"
        }
    ],
    "sg:phone":"+61 7 4771 3428",
    "sg:postcode":"4810",
    "sg:province":"QLD",
    "sg:tags":[
        "pub"
    ],
    "wof:name":"Molly Malones Irish Pub",
    "wof:placetype":"venue"
},
  "geometry": {"coordinates":[146.80641199999999,-19.268761],"type":"Point"}
}