{
  "type": "Feature",
  "properties": {
    "addr:full":"52 Juers St Kingston QLD 4114",
    "addr:housenumber":"52",
    "addr:postcode":"4114",
    "addr:street":"Juers St",
    "iso:country":"AU",
    "sg:address":"52 Juers St",
    "sg:city":"Kingston",
    "sg:classifiers":[
        {
            "category":"Food & Beverages",
            "subcategory":"Groceries & Convenience Stores",
            "type":"Retail Goods"
        }
    ],
    "sg:phone":"+61 7 3208 7851",
    "sg:postcode":"4114",
    "sg:province":"QLD",
    "wof:name":"Family Fare Kingston",
    "wof:placetype":"venue"
},
  "geometry": {"coordinates":[153.10963439899999,-27.6591587067],"type":"Point"}
}