{
  "type": "Feature",
  "properties": {
    "addr:full":"Rmb 8027/ Friends Rd Rosedale VIC 3847",
    "addr:housenumber":"8027 /",
    "addr:postcode":"3847",
    "addr:street":"Friends Rd",
    "iso:country":"AU",
    "sg:address":"Rmb 8027/ Friends Rd",
    "sg:city":"Rosedale",
    "sg:classifiers":[
        {
            "category":"Utilities",
            "subcategory":"Electric",
            "type":"Services"
        }
    ],
    "sg:phone":"+61 419 302 235",
    "sg:postcode":"3847",
    "sg:province":"VIC",
    "sg:tags":[
        "electrical",
        "contractor"
    ],
    "wof:name":"Gilmore Electrical",
    "wof:placetype":"venue"
},
  "geometry": {"coordinates":[146.775024414,-38.1612663269],"type":"Point"}
}