{
  "type": "Feature",
  "properties": {
    "addr:full":"308 Keilor Rd Niddrie VIC 3042",
    "addr:housenumber":"308",
    "addr:postcode":"3042",
    "addr:street":"Keilor Rd",
    "iso:country":"AU",
    "sg:address":"308 Keilor Rd",
    "sg:city":"Niddrie",
    "sg:classifiers":[
        {
            "category":"Communications",
            "subcategory":"Film & Video Production",
            "type":"Services"
        }
    ],
    "sg:phone":"+61 3 9379 6489",
    "sg:postcode":"3042",
    "sg:province":"VIC",
    "sg:tags":[
        "dvd",
        "library"
    ],
    "wof:name":"Blockbuster",
    "wof:placetype":"venue"
},
  "geometry": {"coordinates":[144.894134522,-37.7378616333],"type":"Point"}
}