{
  "type": "Feature",
  "properties": {
    "addr:full":"67 Swanston St Melbourne VIC 3000",
    "addr:housenumber":"67",
    "addr:postcode":"3000",
    "addr:street":"Swanston St",
    "iso:country":"AU",
    "sg:address":"67 Swanston St",
    "sg:city":"Melbourne",
    "sg:classifiers":[
        {
            "category":"Travel",
            "subcategory":"Hotels & Motels",
            "type":"Entertainment"
        }
    ],
    "sg:phone":"+61 3 9654 7011",
    "sg:postcode":"3000",
    "sg:province":"VIC",
    "wof:name":"City Square Motel",
    "wof:placetype":"venue"
},
  "geometry": {"coordinates":[144.96664428700001,-37.8160858154],"type":"Point"}
}