{
  "type": "Feature",
  "properties": {
    "addr:full":"Level 8 500 Queen St Brisbane QLD 4000",
    "addr:housenumber":"500",
    "addr:postcode":"4000",
    "addr:street":"Queen St",
    "iso:country":"AU",
    "sg:address":"Level 8 500 Queen St",
    "sg:city":"Brisbane",
    "sg:classifiers":[
        {
            "category":"Real Estate",
            "subcategory":"Architect",
            "type":"Services"
        }
    ],
    "sg:phone":"+61 7 3831 8144",
    "sg:postcode":"4000",
    "sg:province":"QLD",
    "wof:name":"Woodhead",
    "wof:placetype":"venue"
},
  "geometry": {"coordinates":[153.031524658,-27.4635791779],"type":"Point"}
}