{
  "type": "Feature",
  "properties": {
    "addr:full":"19 Walhallow St Hawker ACT 2614",
    "addr:housenumber":"19",
    "addr:postcode":"2614",
    "addr:street":"Walhallow St",
    "iso:country":"AU",
    "sg:address":"19 Walhallow St",
    "sg:city":"Hawker",
    "sg:classifiers":[
        {
            "category":"Sports & Exercise",
            "subcategory":"Sports Center",
            "type":"Entertainment"
        }
    ],
    "sg:phone":"+61 2 6254 2336",
    "sg:postcode":"2614",
    "sg:province":"ACT",
    "sg:tags":[
        "coach",
        "tennis"
    ],
    "wof:name":"Hawker Tennis Centre",
    "wof:placetype":"venue"
},
  "geometry": {"coordinates":[149.03977966299999,-35.2432022095],"type":"Point"}
}