{
  "type": "Feature",
  "properties": {
    "addr:full":"112 Balmain St Richmond VIC 3121",
    "addr:housenumber":"112",
    "addr:postcode":"3121",
    "addr:street":"Balmain St",
    "iso:country":"AU",
    "sg:address":"112 Balmain St",
    "sg:city":"Richmond",
    "sg:classifiers":[
        {
            "category":"Real Estate",
            "subcategory":"Architect",
            "type":"Services"
        }
    ],
    "sg:phone":"+61 3 9429 4780",
    "sg:postcode":"3121",
    "sg:province":"VIC",
    "wof:name":"Interlandi Mantesso Architects",
    "wof:placetype":"venue"
},
  "geometry": {"coordinates":[144.99574279800001,-37.8303565979],"type":"Point"}
}