{
  "type": "Feature",
  "properties": {
    "addr:full":"35 Catalina Drv Tullamarine VIC 3043",
    "addr:housenumber":"35",
    "addr:postcode":"3043",
    "addr:street":"Catalina Drv",
    "iso:country":"AU",
    "sg:address":"35 Catalina Drv",
    "sg:city":"Tullamarine",
    "sg:classifiers":[
        {
            "category":"Parking",
            "type":"Transportation"
        }
    ],
    "sg:phone":"+61 3 8346 6677",
    "sg:postcode":"3043",
    "sg:province":"VIC",
    "wof:name":"Pink Elephant Airport Parking",
    "wof:placetype":"venue"
},
  "geometry": {"coordinates":[144.87933349599999,-37.6889343262],"type":"Point"}
}