{
  "type": "Feature",
  "properties": {
    "addr:full":"71 Mitchell Ave Northam WA 6401",
    "addr:housenumber":"71",
    "addr:postcode":"6401",
    "addr:street":"Mitchell Ave",
    "iso:country":"AU",
    "sg:address":"71 Mitchell Ave",
    "sg:city":"Northam",
    "sg:classifiers":[
        {
            "category":"Wholesale",
            "subcategory":"Machinery & Supplies",
            "type":"Manufacturing & Wholesale Goods"
        }
    ],
    "sg:phone":"+61 8 9622 1577",
    "sg:postcode":"6401",
    "sg:province":"WA",
    "sg:tags":[
        "agricultural"
    ],
    "wof:name":"Holtfreters Engineers",
    "wof:placetype":"venue"
},
  "geometry": {"coordinates":[116.657180786,-31.6594676971],"type":"Point"}
}