{
  "type": "Feature",
  "properties": {
    "iso:country":"AU",
    "sg:address":"Erindale Plaza, 370 F Kensington Rd",
    "sg:city":"Erindale",
    "sg:classifiers":[
        {
            "category":"Health Services",
            "subcategory":"Dentist",
            "type":"Services"
        }
    ],
    "sg:phone":"+61 8 8331 7030",
    "sg:postcode":"5066",
    "sg:province":"SA",
    "wof:name":"Bob Zeibarts, Dr",
    "wof:placetype":"venue"
},
  "geometry": {"coordinates":[138.66673278799999,-34.9256439209],"type":"Point"}
}