{
  "type": "Feature",
  "properties": {
    "addr:full":"Level 1, 243 Edward St Brisbane QLD 4000",
    "addr:housenumber":"243",
    "addr:postcode":"4000",
    "addr:street":"Edward St",
    "iso:country":"AU",
    "sg:address":"Level 1, 243 Edward St",
    "sg:city":"Brisbane",
    "sg:classifiers":[
        {
            "category":"Wholesale",
            "subcategory":"Medical Equipment & Supplies",
            "type":"Manufacturing & Wholesale Goods"
        }
    ],
    "sg:phone":"+61 1800 057 220",
    "sg:postcode":"4000",
    "sg:province":"QLD",
    "sg:tags":[
        "aids",
        "hearing"
    ],
    "wof:name":"Audio Clinic Queensland",
    "wof:placetype":"venue"
},
  "geometry": {"coordinates":[153.026580811,-27.4677467346],"type":"Point"}
}