{
  "type": "Feature",
  "properties": {
    "addr:full":"114 Munro Rd Queanbeyan NSW 2620",
    "addr:housenumber":"114",
    "addr:postcode":"2620",
    "addr:street":"Munro Rd",
    "iso:country":"AU",
    "sg:address":"114 Munro Rd",
    "sg:city":"Queanbeyan",
    "sg:classifiers":[
        {
            "category":"Building & Trades",
            "subcategory":"Construction",
            "type":"Services"
        }
    ],
    "sg:phone":"+61 2 6297 4444",
    "sg:postcode":"2620",
    "sg:province":"NSW",
    "sg:tags":[
        "home",
        "air conditioning"
    ],
    "wof:name":"Munro Refrigeration & Air Conditioning",
    "wof:placetype":"venue"
},
  "geometry": {"coordinates":[149.214309692,-35.3531112671],"type":"Point"}
}