{
  "type": "Feature",
  "properties": {
    "addr:full":"Unit 1, 17- 19 Gould St South Strathfield NSW 2136",
    "addr:housenumber":"17 19",
    "addr:postcode":"2136",
    "addr:street":"Gould St South",
    "iso:country":"AU",
    "sg:address":"Unit 1, 17- 19 Gould St",
    "sg:city":"South Strathfield",
    "sg:classifiers":[
        {
            "category":"Professional",
            "subcategory":"Detective & Security Services",
            "type":"Services"
        }
    ],
    "sg:phone":"+61 2 9742 5233",
    "sg:postcode":"2136",
    "sg:province":"NSW",
    "sg:tags":[
        "consultant",
        "system"
    ],
    "wof:name":"Came",
    "wof:placetype":"venue"
},
  "geometry": {"coordinates":[151.07220459000001,-33.8885765076],"type":"Point"}
}