{
  "type": "Feature",
  "properties": {
    "iso:country":"AU",
    "sg:address":"162 Sanctuary Drv",
    "sg:city":"Mt Cotton",
    "sg:classifiers":[
        {
            "category":"Utilities",
            "subcategory":"Electric",
            "type":"Services"
        }
    ],
    "sg:phone":"+61 7 3206 6698",
    "sg:postcode":"4165",
    "sg:province":"QLD",
    "sg:tags":[
        "electrical",
        "contractor"
    ],
    "wof:name":"Optical Communications & Electrical Services P/L",
    "wof:placetype":"venue"
},
  "geometry": {"coordinates":[153.24708557100001,-27.6314697266],"type":"Point"}
}