{
  "type": "Feature",
  "properties": {
    "addr:full":"Pyrenees Hwy Amphitheatre VIC 3468",
    "addr:postcode":"3468",
    "addr:street":"Pyrenees Hwy",
    "iso:country":"AU",
    "sg:address":"Pyrenees Hwy",
    "sg:city":"Amphitheatre",
    "sg:classifiers":[
        {
            "category":"Travel",
            "subcategory":"Hotels & Motels",
            "type":"Entertainment"
        }
    ],
    "sg:phone":"+61 3 5466 2212",
    "sg:postcode":"3468",
    "sg:province":"VIC",
    "sg:tags":[
        "accommodation"
    ],
    "wof:name":"Amphitheatre Hotel",
    "wof:placetype":"venue"
},
  "geometry": {"coordinates":[143.40916442899999,-37.1773948669],"type":"Point"}
}