{
  "type": "Feature",
  "properties": {
    "addr:full":"772 High St Epping VIC 3076",
    "addr:housenumber":"772",
    "addr:postcode":"3076",
    "addr:street":"High St",
    "iso:country":"AU",
    "sg:address":"772 High St",
    "sg:city":"Epping",
    "sg:classifiers":[
        {
            "category":"Professional",
            "subcategory":"Employment Agencies",
            "type":"Services"
        }
    ],
    "sg:phone":"+61 3 9401 5000",
    "sg:postcode":"3076",
    "sg:province":"VIC",
    "sg:tags":[
        "hire",
        "labour",
        "contractor"
    ],
    "sg:website":"http://www.mclabour.com.au",
    "wof:name":"MC Labour Services",
    "wof:placetype":"venue"
},
  "geometry": {"coordinates":[145.014404297,-37.8548049927],"type":"Point"}
}