{
  "type": "Feature",
  "properties": {
    "addr:full":"PO Box 116 Cheltenham VIC 3192",
    "addr:postcode":"3192",
    "iso:country":"AU",
    "sg:address":"PO Box 116",
    "sg:city":"Cheltenham",
    "sg:classifiers":[
        {
            "category":"Real Estate",
            "subcategory":"Architect",
            "type":"Services"
        }
    ],
    "sg:phone":"+61 417 336 770",
    "sg:postcode":"3192",
    "sg:province":"VIC",
    "wof:name":"Anderson Wonnacot",
    "wof:placetype":"venue"
},
  "geometry": {"coordinates":[145.073852539,-37.9676208496],"type":"Point"}
}