{
  "type": "Feature",
  "properties": {
    "iso:country":"AU",
    "sg:address":"12 Troy's Rd. M/S 1436",
    "sg:city":"Toowoomba",
    "sg:classifiers":[
        {
            "category":"Building & Trades",
            "subcategory":"Construction",
            "type":"Services"
        }
    ],
    "sg:phone":"+61 7 4630 4397",
    "sg:postcode":"4350",
    "sg:province":"QLD",
    "sg:tags":[
        "excavation",
        "foundation"
    ],
    "wof:name":"Bellert's Bobcat Service",
    "wof:placetype":"venue"
},
  "geometry": {"coordinates":[151.954697,-27.539413],"type":"Point"}
}