{
  "type": "Feature",
  "properties": {
    "iso:country":"AU",
    "sg:address":"84- 92 Chapel St",
    "sg:city":"Marrickville",
    "sg:classifiers":[
        {
            "category":"Wholesale",
            "subcategory":"Furniture",
            "type":"Manufacturing & Wholesale Goods"
        }
    ],
    "sg:phone":"+61 2 9572 8877",
    "sg:postcode":"2204",
    "sg:province":"NSW",
    "sg:tags":[
        "wholesaler",
        "mfrs"
    ],
    "wof:name":"Matt Blatt Furniture",
    "wof:placetype":"venue"
},
  "geometry": {"coordinates":[151.163315,-33.906281],"type":"Point"}
}