{
  "type": "Feature",
  "properties": {
    "addr:full":"69 Helms St Newcomb VIC 3219",
    "addr:housenumber":"69",
    "addr:postcode":"3219",
    "addr:street":"Helms St",
    "iso:country":"AU",
    "sg:address":"69 Helms St",
    "sg:city":"Newcomb",
    "sg:classifiers":[
        {
            "category":"Building & Trades",
            "subcategory":"Construction",
            "type":"Services"
        }
    ],
    "sg:phone":"+61 3 5248 4185",
    "sg:postcode":"3219",
    "sg:province":"VIC",
    "sg:tags":[
        "industrial",
        "commercial",
        "air conditioning"
    ],
    "wof:name":"Eastside Refrigeration & Airconditioning",
    "wof:placetype":"venue"
},
  "geometry": {"coordinates":[144.39984130900001,-38.1676902771],"type":"Point"}
}