{
  "type": "Feature",
  "properties": {
    "iso:country":"AU",
    "sg:address":"1 Beavis St",
    "sg:city":"Elsternwick",
    "sg:classifiers":[
        {
            "category":"Arena",
            "subcategory":"Sports Club",
            "type":"Entertainment"
        }
    ],
    "sg:phone":"+61 3 9857 7619",
    "sg:postcode":"3185",
    "sg:province":"VIC",
    "sg:tags":[
        "defence",
        "supply",
        "self",
        "instruction",
        "martial art"
    ],
    "wof:name":"Shotokan JKA Alliance",
    "wof:placetype":"venue"
},
  "geometry": {"coordinates":[145.00729370100001,-37.8849525452],"type":"Point"}
}