{
  "type": "Feature",
  "properties": {
    "addr:full":"7/ 20 Ireland St Burwood VIC 3125",
    "addr:housenumber":"/ 20",
    "addr:postcode":"3125",
    "addr:street":"Ireland St",
    "iso:country":"AU",
    "sg:address":"7/ 20 Ireland St",
    "sg:city":"Burwood",
    "sg:classifiers":[
        {
            "category":"Health Services",
            "subcategory":"Health Practitioner",
            "type":"Services"
        }
    ],
    "sg:phone":"+61 418 381 542",
    "sg:postcode":"3125",
    "sg:province":"VIC",
    "sg:tags":[
        "acupuncture"
    ],
    "wof:name":"Rob Daniyela",
    "wof:placetype":"venue"
},
  "geometry": {"coordinates":[145.105865478,-37.853225708],"type":"Point"}
}