{
  "type": "Feature",
  "properties": {
    "addr:full":"985 Arthurs Creek Rd Arthurs Creek VIC 3099",
    "addr:housenumber":"985",
    "addr:postcode":"3099",
    "addr:street":"Arthurs Creek Rd",
    "iso:country":"AU",
    "sg:address":"985 Arthurs Creek Rd",
    "sg:city":"Arthurs Creek",
    "sg:classifiers":[
        {
            "category":"Taxi",
            "type":"Transportation"
        }
    ],
    "sg:phone":"+61 3 9714 8755",
    "sg:postcode":"3099",
    "sg:province":"VIC",
    "sg:tags":[
        "truck"
    ],
    "wof:name":"Triwite Transport Services",
    "wof:placetype":"venue"
},
  "geometry": {"coordinates":[145.19483947800001,-37.5766639709],"type":"Point"}
}