{
  "type": "Feature",
  "properties": {
    "addr:full":"PO Box 8252 Woolloongabba QLD 4102",
    "addr:postcode":"4102",
    "iso:country":"AU",
    "sg:address":"PO Box 8252",
    "sg:city":"Woolloongabba",
    "sg:classifiers":[
        {
            "category":"Building & Trades",
            "subcategory":"Construction",
            "type":"Services"
        }
    ],
    "sg:phone":"+61 7 3891 1262",
    "sg:postcode":"4102",
    "sg:province":"QLD",
    "sg:tags":[
        "contractor"
    ],
    "wof:name":"Bryant The Builder",
    "wof:placetype":"venue"
},
  "geometry": {"coordinates":[153.035842895,-27.4891109467],"type":"Point"}
}