{
  "type": "Feature",
  "properties": {
    "iso:country":"AU",
    "sg:address":"43 First Ave",
    "sg:city":"Kilkenny",
    "sg:classifiers":[
        {
            "category":"Shopping",
            "subcategory":"Stationery & Office Supplies",
            "type":"Retail Goods"
        }
    ],
    "sg:phone":"+61 8 8347 7071",
    "sg:postcode":"5009",
    "sg:province":"SA",
    "sg:tags":[
        "packaging",
        "material"
    ],
    "wof:name":"Metropak Australia",
    "wof:placetype":"venue"
},
  "geometry": {"coordinates":[138.55474853499999,-34.8721961975],"type":"Point"}
}