{
  "type": "Feature",
  "properties": {
    "iso:country":"AU",
    "sg:address":"135 Bussell Hwy",
    "sg:city":"Margaret River",
    "sg:classifiers":[
        {
            "category":"Retail",
            "subcategory":"Storage",
            "type":"Services"
        }
    ],
    "sg:phone":"+61 8 9757 2122",
    "sg:postcode":"6285",
    "sg:province":"WA",
    "wof:name":"Margaret River Self Storage",
    "wof:placetype":"venue"
},
  "geometry": {"coordinates":[115.073753357,-33.9520378113],"type":"Point"}
}