{
  "type": "Feature",
  "properties": {
    "iso:country":"AU",
    "sg:address":"100 Sunnyholt Rd",
    "sg:city":"Blacktown",
    "sg:classifiers":[
        {
            "category":"Retail",
            "subcategory":"Auto Repair",
            "type":"Services"
        }
    ],
    "sg:phone":"+61 2 9621 6708",
    "sg:postcode":"2148",
    "sg:province":"NSW",
    "sg:tags":[
        "beater",
        "painter",
        "panel"
    ],
    "wof:name":"Rod Bowen Prestige Smash Repairs",
    "wof:placetype":"venue"
},
  "geometry": {"coordinates":[150.91148376500001,-33.7718162537],"type":"Point"}
}