{
  "type": "Feature",
  "properties": {
    "addr:full":"111 Bray St Coffs Harbour NSW 2450",
    "addr:housenumber":"111",
    "addr:postcode":"2450",
    "addr:street":"Bray St",
    "iso:country":"AU",
    "sg:address":"111 Bray St",
    "sg:city":"Coffs Harbour",
    "sg:classifiers":[
        {
            "category":"Professional",
            "subcategory":"Accounting & Tax Preparation",
            "type":"Services"
        }
    ],
    "sg:phone":"+61 408 669 284",
    "sg:postcode":"2450",
    "sg:province":"NSW",
    "sg:tags":[
        "bookkeeping"
    ],
    "wof:name":"Triple One Bookkeeping",
    "wof:placetype":"venue"
},
  "geometry": {"coordinates":[153.11601257300001,-30.2818660736],"type":"Point"}
}