{
  "type": "Feature",
  "properties": {
    "addr:full":"444 Brunswick St Fortitude Valley QLD 4006",
    "addr:housenumber":"444",
    "addr:postcode":"4006",
    "addr:street":"Brunswick St",
    "iso:country":"AU",
    "sg:address":"444 Brunswick St",
    "sg:city":"Fortitude Valley",
    "sg:classifiers":[
        {
            "category":"Fast Food",
            "type":"Food & Drink"
        }
    ],
    "sg:phone":"+61 7 3252 4832",
    "sg:postcode":"4006",
    "sg:province":"QLD",
    "sg:tags":[
        "away",
        "take"
    ],
    "wof:name":"444 Snack Bar",
    "wof:placetype":"venue"
},
  "geometry": {"coordinates":[153.03741455100001,-27.4601802826],"type":"Point"}
}