{
  "type": "Feature",
  "properties": {
    "addr:full":"7 Thompson Ave Cowes VIC 3922",
    "addr:housenumber":"7",
    "addr:postcode":"3922",
    "addr:street":"Thompson Ave",
    "iso:country":"AU",
    "sg:address":"7 Thompson Ave",
    "sg:city":"Cowes",
    "sg:classifiers":[
        {
            "category":"Restaurant",
            "type":"Food & Drink"
        }
    ],
    "sg:phone":"+61 3 5952 3017",
    "sg:postcode":"3922",
    "sg:province":"VIC",
    "sg:tags":[
        "pizza"
    ],
    "wof:name":"Jeronimos Pizza",
    "wof:placetype":"venue"
},
  "geometry": {"coordinates":[145.23916625999999,-38.4484176636],"type":"Point"}
}