{
  "type": "Feature",
  "properties": {
    "addr:full":"6 Molloy St Toowoomba QLD 4350",
    "addr:housenumber":"6",
    "addr:postcode":"4350",
    "addr:street":"Molloy St",
    "iso:country":"AU",
    "sg:address":"6 Molloy St",
    "sg:city":"Toowoomba",
    "sg:classifiers":[
        {
            "category":"Wholesale",
            "subcategory":"Machinery & Supplies",
            "type":"Manufacturing & Wholesale Goods"
        }
    ],
    "sg:phone":"+61 7 4634 9153",
    "sg:postcode":"4350",
    "sg:province":"QLD",
    "sg:tags":[
        "agricultural"
    ],
    "wof:name":"Seris (Qld) Pty Ltd",
    "wof:placetype":"venue"
},
  "geometry": {"coordinates":[151.89793399999999,-27.555464],"type":"Point"}
}