{
  "type": "Feature",
  "properties": {
    "addr:full":"24 Coghlan Rd Subiaco WA 6008",
    "addr:housenumber":"24",
    "addr:postcode":"6008",
    "addr:street":"Coghlan Rd",
    "iso:country":"AU",
    "sg:address":"24 Coghlan Rd",
    "sg:city":"Subiaco",
    "sg:classifiers":[
        {
            "category":"Health Services",
            "subcategory":"Doctor",
            "type":"Services"
        }
    ],
    "sg:phone":"+61 8 9388 1223",
    "sg:postcode":"6008",
    "sg:province":"WA",
    "sg:tags":[
        "medical",
        "practitioner"
    ],
    "wof:name":"Read P J",
    "wof:placetype":"venue"
},
  "geometry": {"coordinates":[115.83310699499999,-31.9468421936],"type":"Point"}
}