{
  "type": "Feature",
  "properties": {
    "iso:country":"AU",
    "sg:address":"Shop 5, Williams Sq",
    "sg:city":"Warragul",
    "sg:classifiers":[
        {
            "category":"Personal",
            "subcategory":"Beauty Salon",
            "type":"Services"
        }
    ],
    "sg:phone":"+61 3 5623 2535",
    "sg:postcode":"3820",
    "sg:province":"VIC",
    "sg:tags":[
        "hairdresser"
    ],
    "wof:name":"Philip Johns Hairdressing",
    "wof:placetype":"venue"
},
  "geometry": {"coordinates":[145.93211400000001,-38.163219],"type":"Point"}
}