{
  "type": "Feature",
  "properties": {
    "addr:full":"596 Goodwood Rd Daw Park SA 5041",
    "addr:housenumber":"596",
    "addr:postcode":"5041",
    "addr:street":"Goodwood Rd",
    "iso:country":"AU",
    "sg:address":"596 Goodwood Rd",
    "sg:city":"Daw Park",
    "sg:classifiers":[
        {
            "category":"Professional",
            "subcategory":"Accounting & Tax Preparation",
            "type":"Services"
        }
    ],
    "sg:phone":"+61 8 8374 3188",
    "sg:postcode":"5041",
    "sg:province":"SA",
    "sg:tags":[
        "accountant",
        "auditor"
    ],
    "wof:name":"H&R Block",
    "wof:placetype":"venue"
},
  "geometry": {"coordinates":[138.59196499999999,-34.982399],"type":"Point"}
}