{
  "type": "Feature",
  "properties": {
    "addr:full":"7 Springvale Rd Springvale VIC 3171",
    "addr:housenumber":"7",
    "addr:postcode":"3171",
    "addr:street":"Springvale Rd",
    "iso:country":"AU",
    "sg:address":"7 Springvale Rd",
    "sg:city":"Springvale",
    "sg:classifiers":[
        {
            "category":"Structure",
            "subcategory":"Bridge",
            "type":"Public Place"
        }
    ],
    "sg:phone":"+61 3 9547 8912",
    "sg:postcode":"3171",
    "sg:province":"VIC",
    "sg:tags":[
        "chainsaw",
        "brushcutters"
    ],
    "wof:name":"Springvale Mowers & Chainsaws Pty Ltd",
    "wof:placetype":"venue"
},
  "geometry": {"coordinates":[145.155975342,-37.9334945679],"type":"Point"}
}