{
  "type": "Feature",
  "properties": {
    "addr:full":"179 Burns Rd Turramurra NSW 2074",
    "addr:housenumber":"179",
    "addr:postcode":"2074",
    "addr:street":"Burns Rd",
    "iso:country":"AU",
    "sg:address":"179 Burns Rd",
    "sg:city":"Turramurra",
    "sg:classifiers":[
        {
            "category":"Building & Trades",
            "subcategory":"Construction",
            "type":"Services"
        }
    ],
    "sg:phone":"+61 2 9440 1173",
    "sg:postcode":"2074",
    "sg:province":"NSW",
    "sg:tags":[
        "contractor"
    ],
    "wof:name":"QS Building Economics Pty Ltd",
    "wof:placetype":"venue"
},
  "geometry": {"coordinates":[151.14112854000001,-33.7198905945],"type":"Point"}
}