{
  "type": "Feature",
  "properties": {
    "addr:full":"95 Samford Rd Alderley QLD 4051",
    "addr:housenumber":"95",
    "addr:postcode":"4051",
    "addr:street":"Samford Rd",
    "iso:country":"AU",
    "sg:address":"95 Samford Rd",
    "sg:city":"Alderley",
    "sg:classifiers":[
        {
            "category":"Personal",
            "subcategory":"Tattoo Parlor",
            "type":"Services"
        }
    ],
    "sg:phone":"+61 7 3352 3799",
    "sg:postcode":"4051",
    "sg:province":"QLD",
    "sg:tags":[
        "tattooing"
    ],
    "wof:name":"Trader Tims Tattooing",
    "wof:placetype":"venue"
},
  "geometry": {"coordinates":[152.99624633799999,-27.4236354828],"type":"Point"}
}