{
  "type": "Feature",
  "properties": {
    "addr:full":"Unit 8/ 26 Longstaff Rd Bayswater VIC 3153",
    "addr:housenumber":"26",
    "addr:postcode":"3153",
    "addr:street":"Longstaff Rd",
    "iso:country":"AU",
    "sg:address":"Unit 8/ 26 Longstaff Rd",
    "sg:city":"Bayswater",
    "sg:classifiers":[
        {
            "category":"Home & Garden",
            "subcategory":"Carpets & Floor Coverings",
            "type":"Retail Goods"
        }
    ],
    "sg:phone":"+61 3 9738 0770",
    "sg:postcode":"3153",
    "sg:province":"VIC",
    "wof:name":"SP&M Building Products",
    "wof:placetype":"venue"
},
  "geometry": {"coordinates":[145.283447266,-37.8355674744],"type":"Point"}
}