{
  "type": "Feature",
  "properties": {
    "addr:full":"90 Boas Ave Joondalup WA 6027",
    "addr:housenumber":"90",
    "addr:postcode":"6027",
    "addr:street":"Boas Ave",
    "iso:country":"AU",
    "sg:address":"90 Boas Ave",
    "sg:city":"Joondalup",
    "sg:classifiers":[
        {
            "category":"Social Services",
            "subcategory":"Child Care",
            "type":"Services"
        }
    ],
    "sg:phone":"+61 8 9301 8222",
    "sg:postcode":"6027",
    "sg:province":"WA",
    "wof:name":"Community Vision Inc.",
    "wof:placetype":"venue"
},
  "geometry": {"coordinates":[115.770233154,-31.7429542542],"type":"Point"}
}