{
  "type": "Feature",
  "properties": {
    "addr:full":"Meissners Rd Biloela QLD 4715",
    "addr:postcode":"4715",
    "addr:street":"Meissners Rd",
    "iso:country":"AU",
    "sg:address":"Meissners Rd",
    "sg:city":"Biloela",
    "sg:classifiers":[
        {
            "category":"Farming",
            "subcategory":"Farm",
            "type":"Manufacturing & Wholesale Goods"
        }
    ],
    "sg:phone":"+61 7 4992 1615",
    "sg:postcode":"4715",
    "sg:province":"QLD",
    "sg:tags":[
        "farmer"
    ],
    "wof:name":"Bauer Farming Co",
    "wof:placetype":"venue"
},
  "geometry": {"coordinates":[150.50238037099999,-24.4170150757],"type":"Point"}
}