{
  "type": "Feature",
  "properties": {
    "iso:country":"AU",
    "sg:address":"PO Box 2859",
    "sg:city":"Burleigh",
    "sg:classifiers":[
        {
            "category":"Home & Garden",
            "subcategory":"Hardware",
            "type":"Retail Goods"
        }
    ],
    "sg:phone":"+61 7 5507 7922",
    "sg:postcode":"4220",
    "sg:province":"QLD",
    "sg:tags":[
        "product",
        "treatment",
        "floor"
    ],
    "wof:name":"WetGrip Pty Ltd",
    "wof:placetype":"venue"
},
  "geometry": {"coordinates":[153.432662964,-28.0981998444],"type":"Point"}
}