{
  "type": "Feature",
  "properties": {
    "addr:full":"374 Moreland Rd Brunswick West VIC 3055",
    "addr:housenumber":"374",
    "addr:postcode":"3055",
    "addr:street":"Moreland Rd",
    "iso:country":"AU",
    "sg:address":"374 Moreland Rd",
    "sg:city":"Brunswick West",
    "sg:classifiers":[
        {
            "category":"Professional",
            "subcategory":"Accounting & Tax Preparation",
            "type":"Services"
        }
    ],
    "sg:phone":"+61 3 9386 6061",
    "sg:postcode":"3055",
    "sg:province":"VIC",
    "sg:tags":[
        "accountant",
        "auditor"
    ],
    "wof:name":"Tax Time Accounts",
    "wof:placetype":"venue"
},
  "geometry": {"coordinates":[144.93797302199999,-37.7524681091],"type":"Point"}
}