{
  "type": "Feature",
  "properties": {
    "iso:country":"AU",
    "sg:address":"Cnr Princess Hwy & Progress St,",
    "sg:city":"Doveton",
    "sg:classifiers":[
        {
            "category":"Structure",
            "subcategory":"Bridge",
            "type":"Public Place"
        }
    ],
    "sg:phone":"+61 3 9793 3177",
    "sg:postcode":"3177",
    "sg:province":"VIC",
    "sg:tags":[
        "chainsaw",
        "brushcutters"
    ],
    "sg:website":"http://www.powerquip.com.au",
    "wof:name":"Powerquip Mower & Chainsaw Centre",
    "wof:placetype":"venue"
},
  "geometry": {"coordinates":[145.236526489,-38.0028533936],"type":"Point"}
}