{
  "type": "Feature",
  "properties": {
    "addr:full":"3/ 36 Myrtle Gr Reservoir VIC 3073",
    "addr:housenumber":"/ 36",
    "addr:postcode":"3073",
    "addr:street":"Myrtle Gr",
    "iso:country":"AU",
    "sg:address":"3/ 36 Myrtle Gr",
    "sg:city":"Reservoir",
    "sg:classifiers":[
        {
            "category":"Professional",
            "subcategory":"Accounting & Tax Preparation",
            "type":"Services"
        }
    ],
    "sg:phone":"+61 3 9478 8903",
    "sg:postcode":"3073",
    "sg:province":"VIC",
    "sg:tags":[
        "consultant",
        "taxation"
    ],
    "wof:name":"Arval Taxation Services",
    "wof:placetype":"venue"
},
  "geometry": {"coordinates":[144.99891662600001,-37.7282371521],"type":"Point"}
}