{
  "type": "Feature",
  "properties": {
    "iso:country":"AU",
    "sg:address":"Lot 3 Melrose Rd",
    "sg:city":"Mudgee",
    "sg:classifiers":[
        {
            "category":"Building & Trades",
            "subcategory":"Construction",
            "type":"Services"
        }
    ],
    "sg:phone":"+61 418 212 262",
    "sg:postcode":"2850",
    "sg:province":"NSW",
    "sg:tags":[
        "concrete",
        "contractor"
    ],
    "wof:name":"Jaycee's Concretors",
    "wof:placetype":"venue"
},
  "geometry": {"coordinates":[149.674316,-32.6394],"type":"Point"}
}