{
  "type": "Feature",
  "properties": {
    "addr:full":"15 Viewtech Pl Rowville VIC 3178",
    "addr:housenumber":"15",
    "addr:postcode":"3178",
    "addr:street":"Viewtech Pl",
    "iso:country":"AU",
    "sg:address":"15 Viewtech Pl",
    "sg:city":"Rowville",
    "sg:classifiers":[
        {
            "category":"Wholesale",
            "subcategory":"Machinery & Supplies",
            "type":"Manufacturing & Wholesale Goods"
        }
    ],
    "sg:phone":"+61 3 9755 8277",
    "sg:postcode":"3178",
    "sg:province":"VIC",
    "sg:tags":[
        "equipment",
        "hydraulic"
    ],
    "wof:name":"Shinn Fu Australia Pty Ltd",
    "wof:placetype":"venue"
},
  "geometry": {"coordinates":[145.22268676799999,-37.9293785095],"type":"Point"}
}