{
  "type": "Feature",
  "properties": {
    "addr:full":"Shop 1042E Centro Galleria, Dewar St Morley WA 6062",
    "addr:housenumber":"1042e centro",
    "addr:postcode":"6062",
    "addr:street":"Dewar St",
    "iso:country":"AU",
    "sg:address":"Shop 1042E Centro Galleria, Dewar St",
    "sg:city":"Morley",
    "sg:classifiers":[
        {
            "category":"Wholesale",
            "subcategory":"Medical Equipment & Supplies",
            "type":"Manufacturing & Wholesale Goods"
        }
    ],
    "sg:phone":"+61 8 9275 5077",
    "sg:postcode":"6062",
    "sg:province":"WA",
    "sg:tags":[
        "aids",
        "hearing"
    ],
    "wof:name":"Australian Hearing",
    "wof:placetype":"venue"
},
  "geometry": {"coordinates":[115.901657105,-31.8994007111],"type":"Point"}
}