{
  "type": "Feature",
  "properties": {
    "addr:full":"Cnr River Rd & Gladstone St, Gympie QLD 4570",
    "addr:postcode":"4570",
    "addr:street":"Cnr River Rd & Gladstone St",
    "iso:country":"AU",
    "sg:address":"Cnr River Rd",
    "sg:city":"& Gladstone St, Gympie",
    "sg:classifiers":[
        {
            "category":"Banks & Credit Unions",
            "subcategory":"Financial Services",
            "type":"Services"
        }
    ],
    "sg:phone":"+61 7 5482 2468",
    "sg:postcode":"4570",
    "sg:province":"QLD",
    "sg:tags":[
        "planning"
    ],
    "wof:name":"AMP Financial Planning Pty Ltd",
    "wof:placetype":"venue"
},
  "geometry": {"coordinates":[152.66029357900001,-26.1905937195],"type":"Point"}
}