{
  "type": "Feature",
  "properties": {
    "iso:country":"AU",
    "sg:address":"Brisbane Rd",
    "sg:city":"Mooloolaba",
    "sg:classifiers":[
        {
            "category":"Autos & Motor Vehicles",
            "subcategory":"Fuel & Gas Station",
            "type":"Retail Goods"
        }
    ],
    "sg:phone":"+61 7 5444 4266",
    "sg:postcode":"4557",
    "sg:province":"QLD",
    "wof:name":"Shell Mooloolaba Self Serve",
    "wof:placetype":"venue"
},
  "geometry": {"coordinates":[153.117797852,-26.6837902069],"type":"Point"}
}