{
  "type": "Feature",
  "properties": {
    "iso:country":"AU",
    "sg:address":"Cnr Nicklin Way & Bellara Drv",
    "sg:city":"Currimundi",
    "sg:classifiers":[
        {
            "category":"Health Services",
            "subcategory":"Dentist",
            "type":"Services"
        }
    ],
    "sg:phone":"+61 7 5491 9177",
    "sg:postcode":"4551",
    "sg:province":"QLD",
    "wof:name":"Martin Steve",
    "wof:placetype":"venue"
},
  "geometry": {"coordinates":[153.12217712399999,-26.7688045502],"type":"Point"}
}