{
  "type": "Feature",
  "properties": {
    "addr:full":"(Cnr Kirkham Rd) Dandenong VIC 3175",
    "addr:postcode":"3175",
    "addr:street":"Cnr Kirkham Rd",
    "iso:country":"AU",
    "sg:address":"(Cnr Kirkham Rd)",
    "sg:city":"Dandenong",
    "sg:classifiers":[
        {
            "category":"Freight",
            "type":"Transportation"
        }
    ],
    "sg:phone":"+61 3 9793 6410",
    "sg:postcode":"3175",
    "sg:province":"VIC",
    "sg:tags":[
        "transport",
        "refrigerated"
    ],
    "wof:name":"Express Refrigerated Cold Storage & Distribution",
    "wof:placetype":"venue"
},
  "geometry": {"coordinates":[145.21873474099999,-37.9987411499],"type":"Point"}
}