{
  "type": "Feature",
  "properties": {
    "addr:full":"43 Prince St Busselton WA 6280",
    "addr:housenumber":"43",
    "addr:postcode":"6280",
    "addr:street":"Prince St",
    "iso:country":"AU",
    "sg:address":"43 Prince St",
    "sg:city":"Busselton",
    "sg:classifiers":[
        {
            "category":"Retail",
            "subcategory":"Laundry & Dry Cleaning",
            "type":"Services"
        }
    ],
    "sg:phone":"+61 8 9752 1113",
    "sg:postcode":"6280",
    "sg:province":"WA",
    "wof:name":"Busselton Dry Cleaners",
    "wof:placetype":"venue"
},
  "geometry": {"coordinates":[115.344932556,-33.6509017944],"type":"Point"}
}