{
  "type": "Feature",
  "properties": {
    "addr:full":"Bold St Laurieton NSW 2443",
    "addr:postcode":"2443",
    "addr:street":"Bold St",
    "iso:country":"AU",
    "sg:address":"Bold St",
    "sg:city":"Laurieton",
    "sg:classifiers":[
        {
            "category":"Education",
            "subcategory":"School",
            "type":"Public Place"
        }
    ],
    "sg:phone":"+61 2 6559 9084",
    "sg:postcode":"2443",
    "sg:province":"NSW",
    "sg:tags":[
        "state",
        "-",
        "nsw"
    ],
    "wof:name":"Laurieton Public School",
    "wof:placetype":"venue"
},
  "geometry": {"coordinates":[152.79672199999999,-31.648775],"type":"Point"}
}