{
  "type": "Feature",
  "properties": {
    "addr:full":"382- 392 Wagga Rd Lavington NSW 2641",
    "addr:housenumber":"392",
    "addr:postcode":"2641",
    "addr:street":"Wagga Rd",
    "iso:country":"AU",
    "sg:address":"382- 392 Wagga Rd",
    "sg:city":"Lavington",
    "sg:classifiers":[
        {
            "category":"Wholesale",
            "subcategory":"Metals & Minerals",
            "type":"Manufacturing & Wholesale Goods"
        }
    ],
    "sg:phone":"+61 2 6025 2322",
    "sg:postcode":"2641",
    "sg:province":"NSW",
    "sg:tags":[
        "steel",
        "merchant"
    ],
    "wof:name":"Grants Mitre 10",
    "wof:placetype":"venue"
},
  "geometry": {"coordinates":[146.94329834000001,-36.0453948975],"type":"Point"}
}