{
  "type": "Feature",
  "properties": {
    "iso:country":"AU",
    "sg:address":"Fingerboard Rd",
    "sg:city":"Yambuk",
    "sg:classifiers":[
        {
            "category":"Building & Trades",
            "subcategory":"Landscaping Services",
            "type":"Services"
        }
    ],
    "sg:phone":"+61 3 5568 4341",
    "sg:postcode":"3285",
    "sg:province":"VIC",
    "sg:tags":[
        "grazier"
    ],
    "wof:name":"Watts B L & C H",
    "wof:placetype":"venue"
},
  "geometry": {"coordinates":[142.071075439,-38.3123397827],"type":"Point"}
}