{
  "type": "Feature",
  "properties": {
    "iso:country":"AU",
    "sg:address":"36 Prior St",
    "sg:city":"Albany",
    "sg:classifiers":[
        {
            "category":"Home & Garden",
            "subcategory":"Building Materials",
            "type":"Retail Goods"
        }
    ],
    "sg:phone":"+61 8 9842 2457",
    "sg:postcode":"6330",
    "sg:province":"WA",
    "sg:tags":[
        "merchant",
        "glass",
        "glazier"
    ],
    "wof:name":"Novada Glass & Aluminium",
    "wof:placetype":"venue"
},
  "geometry": {"coordinates":[117.886390686,-35.0158233643],"type":"Point"}
}