{
  "type": "Feature",
  "properties": {
    "iso:country":"AU",
    "sg:address":"102 Canterbury Rd",
    "sg:city":"Middle Park",
    "sg:classifiers":[
        {
            "category":"Travel",
            "subcategory":"Hotels & Motels",
            "type":"Entertainment"
        }
    ],
    "sg:phone":"+61 3 9690 1958",
    "sg:postcode":"3206",
    "sg:province":"VIC",
    "sg:tags":[
        "pub"
    ],
    "wof:name":"Gunn Island",
    "wof:placetype":"venue"
},
  "geometry": {"coordinates":[144.96519499999999,-37.849895],"type":"Point"}
}