{
  "type": "Feature",
  "properties": {
    "addr:full":"151 Victoria Pde Fitzroy VIC 3065",
    "addr:housenumber":"151",
    "addr:postcode":"3065",
    "addr:street":"Victoria Pde",
    "iso:country":"AU",
    "sg:address":"151 Victoria Pde",
    "sg:city":"Fitzroy",
    "sg:classifiers":[
        {
            "category":"Autos & Motor Vehicles",
            "subcategory":"Fuel & Gas Station",
            "type":"Retail Goods"
        }
    ],
    "sg:phone":"+61 3 9417 6747",
    "sg:postcode":"3065",
    "sg:province":"VIC",
    "wof:name":"Liberty Fitzroy",
    "wof:placetype":"venue"
},
  "geometry": {"coordinates":[144.97976684599999,-37.8083229065],"type":"Point"}
}