{
  "type": "Feature",
  "properties": {
    "addr:full":"1/ 1 First Ave Eastwood NSW 2122",
    "addr:housenumber":"/ 1",
    "addr:postcode":"2122",
    "addr:street":"First Ave",
    "iso:country":"AU",
    "sg:address":"1/ 1 First Ave",
    "sg:city":"Eastwood",
    "sg:classifiers":[
        {
            "category":"Banks & Credit Unions",
            "subcategory":"Financial Services",
            "type":"Services"
        }
    ],
    "sg:phone":"+61 2 8819 6741",
    "sg:postcode":"2122",
    "sg:province":"NSW",
    "sg:tags":[
        "financier"
    ],
    "wof:name":"Leasecorp Australia",
    "wof:placetype":"venue"
},
  "geometry": {"coordinates":[151.08311462399999,-33.7923660278],"type":"Point"}
}