{
  "type": "Feature",
  "properties": {
    "addr:full":"8 Mazepa Ave Penrith South NSW 2750",
    "addr:housenumber":"8",
    "addr:postcode":"2750",
    "addr:street":"Mazepa Ave",
    "iso:country":"AU",
    "sg:address":"8 Mazepa Ave",
    "sg:city":"Penrith South",
    "sg:classifiers":[
        {
            "category":"Building & Trades",
            "subcategory":"Construction",
            "type":"Services"
        }
    ],
    "sg:phone":"+61 2 4736 2297",
    "sg:postcode":"2750",
    "sg:province":"NSW",
    "sg:tags":[
        "brick",
        "paving"
    ],
    "wof:name":"Pauls Paving",
    "wof:placetype":"venue"
},
  "geometry": {"coordinates":[150.709518433,-33.7687416077],"type":"Point"}
}