{
  "type": "Feature",
  "properties": {
    "iso:country":"AU",
    "sg:address":"Langford Rd",
    "sg:city":"Sorrento",
    "sg:classifiers":[
        {
            "category":"Sports & Exercise",
            "subcategory":"Golf",
            "type":"Entertainment"
        }
    ],
    "sg:phone":"+61 3 5984 2226",
    "sg:postcode":"3943",
    "sg:province":"VIC",
    "sg:tags":[
        "club"
    ],
    "wof:name":"Sorrento Golf Club",
    "wof:placetype":"venue"
},
  "geometry": {"coordinates":[144.73619079599999,-38.3290023804],"type":"Point"}
}