{
  "type": "Feature",
  "properties": {
    "addr:full":"1/ 10 Westmoreland Rd Minto NSW 2566",
    "addr:housenumber":"/ 10",
    "addr:postcode":"2566",
    "addr:street":"Westmoreland Rd",
    "iso:country":"AU",
    "sg:address":"1/ 10 Westmoreland Rd",
    "sg:city":"Minto",
    "sg:classifiers":[
        {
            "category":"Health Services",
            "subcategory":"Health Practitioner",
            "type":"Services"
        }
    ],
    "sg:phone":"+61 2 9603 6024",
    "sg:postcode":"2566",
    "sg:province":"NSW",
    "sg:tags":[
        "homoeopath"
    ],
    "wof:name":"Tariq Chaudhry",
    "wof:placetype":"venue"
},
  "geometry": {"coordinates":[150.84387207,-34.0422782898],"type":"Point"}
}