{
  "type": "Feature",
  "properties": {
    "iso:country":"AU",
    "sg:address":"59 Mulgrave Rd",
    "sg:city":"Westcourt",
    "sg:classifiers":[
        {
            "category":"Autos & Motor Vehicles",
            "subcategory":"Automobile Sales",
            "type":"Retail Goods"
        }
    ],
    "sg:phone":"+61 7 4051 5527",
    "sg:postcode":"4870",
    "sg:province":"QLD",
    "sg:tags":[
        "car",
        "used"
    ],
    "wof:name":"Alfies Used Cars",
    "wof:placetype":"venue"
},
  "geometry": {"coordinates":[145.75392150900001,-16.9355697632],"type":"Point"}
}