{
  "type": "Feature",
  "properties": {
    "iso:country":"AU",
    "sg:address":"52 Oxford St",
    "sg:city":"Paddington",
    "sg:classifiers":[
        {
            "category":"Shopping",
            "subcategory":"Clothing, Apparel, & Fashions",
            "type":"Retail Goods"
        }
    ],
    "sg:phone":"+61 2 9358 1155",
    "sg:postcode":"2021",
    "sg:province":"NSW",
    "sg:tags":[
        "lady",
        "wear"
    ],
    "wof:name":"Goldy Fashion House Pty Ltd",
    "wof:placetype":"venue"
},
  "geometry": {"coordinates":[151.220504761,-33.8826332092],"type":"Point"}
}