{
  "type": "Feature",
  "properties": {
    "iso:country":"AU",
    "sg:address":"18 Barton Drv",
    "sg:city":"Baranduda",
    "sg:classifiers":[
        {
            "category":"Professional",
            "subcategory":"Management & Consulting",
            "type":"Services"
        }
    ],
    "sg:phone":"+61 412 399 239",
    "sg:postcode":"3691",
    "sg:province":"VIC",
    "sg:tags":[
        "consultant"
    ],
    "wof:name":"Bartlett N R Consulting",
    "wof:placetype":"venue"
},
  "geometry": {"coordinates":[146.95492553700001,-36.2022743225],"type":"Point"}
}