{
  "type": "Feature",
  "properties": {
    "addr:full":"102 Pitt St Nowra NSW 2541",
    "addr:housenumber":"102",
    "addr:postcode":"2541",
    "addr:street":"Pitt St",
    "iso:country":"AU",
    "sg:address":"102 Pitt St",
    "sg:city":"Nowra",
    "sg:classifiers":[
        {
            "category":"Professional",
            "subcategory":"Employment Agencies",
            "type":"Services"
        }
    ],
    "sg:phone":"+61 2 4423 3337",
    "sg:postcode":"2541",
    "sg:province":"NSW",
    "wof:name":"Workplace Shoalhaven",
    "wof:placetype":"venue"
},
  "geometry": {"coordinates":[150.569824219,-34.8582992554],"type":"Point"}
}