{
  "type": "Feature",
  "properties": {
    "iso:country":"AU",
    "sg:address":"15 Aquarius Ave",
    "sg:city":"Torquay",
    "sg:classifiers":[
        {
            "category":"Home & Garden",
            "subcategory":"Building Materials",
            "type":"Retail Goods"
        }
    ],
    "sg:phone":"+61 3 5261 3025",
    "sg:postcode":"3228",
    "sg:province":"VIC",
    "sg:tags":[
        "lawn",
        "cutting",
        "maintenance"
    ],
    "wof:name":"Garden Harmony",
    "wof:placetype":"venue"
},
  "geometry": {"coordinates":[144.327454,-38.297363],"type":"Point"}
}