{
  "type": "Feature",
  "properties": {
    "iso:country":"AU",
    "sg:address":"12 Somerleigh Rd",
    "sg:city":"Laverton North",
    "sg:classifiers":[
        {
            "category":"Building & Trades",
            "subcategory":"Equipment Rental",
            "type":"Services"
        }
    ],
    "sg:phone":"+61 417 315 840",
    "sg:postcode":"3026",
    "sg:province":"VIC",
    "sg:tags":[
        "demolition",
        "contractor"
    ],
    "wof:name":"Martian Demolitions Pty Ltd",
    "wof:placetype":"venue"
},
  "geometry": {"coordinates":[144.814346,-37.816952],"type":"Point"}
}