{
  "type": "Feature",
  "properties": {
    "addr:full":"985 Fairfield Rd Yeerongpilly QLD 4105",
    "addr:housenumber":"985",
    "addr:postcode":"4105",
    "addr:street":"Fairfield Rd",
    "iso:country":"AU",
    "sg:address":"985 Fairfield Rd",
    "sg:city":"Yeerongpilly",
    "sg:classifiers":[
        {
            "category":"Retail",
            "subcategory":"Storage",
            "type":"Services"
        }
    ],
    "sg:phone":"+61 7 3892 7966",
    "sg:postcode":"4105",
    "sg:province":"QLD",
    "wof:name":"AAA.SKR",
    "wof:placetype":"venue"
},
  "geometry": {"coordinates":[153.01133727999999,-27.5384998322],"type":"Point"}
}