{
  "type": "Feature",
  "properties": {
    "addr:full":"8 O'Connell Ave Matraville NSW 2036",
    "addr:housenumber":"8",
    "addr:postcode":"2036",
    "addr:street":"O'Connell Ave",
    "iso:country":"AU",
    "sg:address":"8 O'Connell Ave",
    "sg:city":"Matraville",
    "sg:classifiers":[
        {
            "category":"Retail",
            "subcategory":"Driving School",
            "type":"Services"
        }
    ],
    "sg:phone":"+61 2 9661 7613",
    "sg:postcode":"2036",
    "sg:province":"NSW",
    "wof:name":"Matraville Driving School",
    "wof:placetype":"venue"
},
  "geometry": {"coordinates":[151.239334106,-33.9522094727],"type":"Point"}
}