{
  "type": "Feature",
  "properties": {
    "addr:full":"Shp2/ 14 Bay St Byron Bay NSW 2481",
    "addr:housenumber":"14",
    "addr:postcode":"2481",
    "addr:street":"Bay St",
    "iso:country":"AU",
    "sg:address":"Shp2/ 14 Bay St",
    "sg:city":"Byron Bay",
    "sg:classifiers":[
        {
            "category":"Personal",
            "subcategory":"Massage",
            "type":"Services"
        }
    ],
    "sg:phone":"+61 2 6680 9887",
    "sg:postcode":"2481",
    "sg:province":"NSW",
    "sg:tags":[
        "therapy"
    ],
    "wof:name":"Feel Good Massage Lounge",
    "wof:placetype":"venue"
},
  "geometry": {"coordinates":[153.61424255399999,-28.6415405273],"type":"Point"}
}