{
  "type": "Feature",
  "properties": {
    "iso:country":"AU",
    "sg:address":"PO Box 577E",
    "sg:city":"Earlville",
    "sg:classifiers":[
        {
            "category":"Organizations",
            "subcategory":"Membership Organization",
            "type":"Services"
        }
    ],
    "sg:phone":"+61 7 4057 6029",
    "sg:postcode":"4870",
    "sg:province":"QLD",
    "sg:tags":[
        "club",
        "car"
    ],
    "wof:name":"Far North Queensland Restorers Club Inc",
    "wof:placetype":"venue"
},
  "geometry": {"coordinates":[145.736206055,-16.9474105835],"type":"Point"}
}