{
  "type": "Feature",
  "properties": {
    "addr:full":"Yetti Rd Cockatoo Valley SA 5351",
    "addr:postcode":"5351",
    "addr:street":"Yetti Rd",
    "iso:country":"AU",
    "sg:address":"Yetti Rd",
    "sg:city":"Cockatoo Valley",
    "sg:classifiers":[
        {
            "category":"Farming",
            "subcategory":"Farm",
            "type":"Manufacturing & Wholesale Goods"
        }
    ],
    "sg:phone":"+61 8 8524 6392",
    "sg:postcode":"5351",
    "sg:province":"SA",
    "sg:tags":[
        "farmer"
    ],
    "wof:name":"Pain R K & R H",
    "wof:placetype":"venue"
},
  "geometry": {"coordinates":[138.85304260300001,-34.632686615],"type":"Point"}
}