{
  "type": "Feature",
  "properties": {
    "iso:country":"AU",
    "sg:address":"Factory 14 39 East St",
    "sg:city":"Daylesford",
    "sg:classifiers":[
        {
            "category":"Manufacturing",
            "subcategory":"Furniture",
            "type":"Manufacturing & Wholesale Goods"
        }
    ],
    "sg:phone":"+61 3 5348 4288",
    "sg:postcode":"3460",
    "sg:province":"VIC",
    "sg:tags":[
        "builder",
        "designer",
        "custom"
    ],
    "wof:name":"Pentland Furniture Company",
    "wof:placetype":"venue"
},
  "geometry": {"coordinates":[144.154953003,-37.3469772339],"type":"Point"}
}