{
  "type": "Feature",
  "properties": {
    "addr:full":"Waterwheel Rd Bedfordale WA 6112",
    "addr:postcode":"6112",
    "addr:street":"Waterwheel Rd",
    "iso:country":"AU",
    "sg:address":"Waterwheel Rd",
    "sg:city":"Bedfordale",
    "sg:classifiers":[
        {
            "category":"Government",
            "subcategory":"Fire Station",
            "type":"Public Place"
        }
    ],
    "sg:phone":"+61 8 9497 2536",
    "sg:postcode":"6112",
    "sg:province":"WA",
    "sg:tags":[
        "brigade"
    ],
    "wof:name":"Bedfordale Volunteer Bush Fire Brigade",
    "wof:placetype":"venue"
},
  "geometry": {"coordinates":[116.067123413,-32.1687507629],"type":"Point"}
}