{
  "type": "Feature",
  "properties": {
    "addr:full":"55 Burgundy St Heidelberg VIC 3084",
    "addr:housenumber":"55",
    "addr:postcode":"3084",
    "addr:street":"Burgundy St",
    "iso:country":"AU",
    "sg:address":"55 Burgundy St",
    "sg:city":"Heidelberg",
    "sg:classifiers":[
        {
            "category":"Shopping",
            "subcategory":"Clothing, Apparel, & Fashions",
            "type":"Retail Goods"
        }
    ],
    "sg:phone":"+61 3 9455 0860",
    "sg:postcode":"3084",
    "sg:province":"VIC",
    "sg:tags":[
        "menswear"
    ],
    "wof:name":"The Knitwear Gallery",
    "wof:placetype":"venue"
},
  "geometry": {"coordinates":[145.06831359899999,-37.7565574646],"type":"Point"}
}