{
  "type": "Feature",
  "properties": {
    "addr:full":"Shop 11-14, 25-29 Dumaresq St Campbelltown NSW 2560",
    "addr:housenumber":"11-14 25-29",
    "addr:postcode":"2560",
    "addr:street":"Dumaresq St",
    "iso:country":"AU",
    "sg:address":"Shop 11-14, 25-29 Dumaresq St",
    "sg:city":"Campbelltown",
    "sg:classifiers":[
        {
            "category":"Wholesale",
            "subcategory":"Stationery",
            "type":"Manufacturing & Wholesale Goods"
        }
    ],
    "sg:phone":"+61 2 4625 2600",
    "sg:postcode":"2560",
    "sg:province":"NSW",
    "sg:tags":[
        "mfrg"
    ],
    "wof:name":"Reliable Stationery & Office Supplies Pty Ltd",
    "wof:placetype":"venue"
},
  "geometry": {"coordinates":[150.81246948200001,-34.0675849915],"type":"Point"}
}