{
  "type": "Feature",
  "properties": {
    "addr:full":"269 Creek Rd Mt Gravatt QLD 4122",
    "addr:housenumber":"269",
    "addr:postcode":"4122",
    "addr:street":"Creek Rd",
    "iso:country":"AU",
    "sg:address":"269 Creek Rd",
    "sg:city":"Mt Gravatt",
    "sg:classifiers":[
        {
            "category":"Retail",
            "subcategory":"Event Space",
            "type":"Services"
        }
    ],
    "sg:phone":"+61 7 3821 1153",
    "sg:postcode":"4122",
    "sg:province":"QLD",
    "sg:tags":[
        "function",
        "organiser"
    ],
    "wof:name":"Greek Orthodox Community Of Mt Gravatt",
    "wof:placetype":"venue"
},
  "geometry": {"coordinates":[153.09146118199999,-27.533618927],"type":"Point"}
}