{
  "type": "Feature",
  "properties": {
    "addr:full":"Clift St Heddon Greta NSW 2321",
    "addr:postcode":"2321",
    "addr:street":"Clift St",
    "iso:country":"AU",
    "sg:address":"Clift St",
    "sg:city":"Heddon Greta",
    "sg:classifiers":[
        {
            "category":"Retail",
            "subcategory":"Event Space",
            "type":"Services"
        }
    ],
    "sg:phone":"+61 2 4937 1224",
    "sg:postcode":"2321",
    "sg:province":"NSW",
    "sg:tags":[
        "venue",
        "reception",
        "wedding"
    ],
    "wof:name":"Kurri Golf Club",
    "wof:placetype":"venue"
},
  "geometry": {"coordinates":[151.51173400900001,-32.8055076599],"type":"Point"}
}