{
  "type": "Feature",
  "properties": {
    "addr:full":"Unit 1/ 765 Old South Head Rd Vaucluse NSW 2030",
    "addr:housenumber":"/ 765",
    "addr:postcode":"2030",
    "addr:street":"Old South Head Rd",
    "iso:country":"AU",
    "sg:address":"Unit 1/ 765 Old South Head Rd",
    "sg:city":"Vaucluse",
    "sg:classifiers":[
        {
            "category":"Professional",
            "subcategory":"Employment Agencies",
            "type":"Services"
        }
    ],
    "sg:phone":"+61 2 9337 4640",
    "sg:postcode":"2030",
    "sg:province":"NSW",
    "sg:tags":[
        "hire",
        "labour",
        "contractor"
    ],
    "wof:name":"A.S MANPOWER",
    "wof:placetype":"venue"
},
  "geometry": {"coordinates":[151.28248596200001,-33.8572769165],"type":"Point"}
}