{
  "type": "Feature",
  "properties": {
    "addr:full":"Shop 4 Boulevarde Shopng Cntr Broome WA 6725",
    "addr:housenumber":"shop 4",
    "addr:postcode":"6725",
    "addr:street":"Boulevarde Shopng Cntr",
    "iso:country":"AU",
    "sg:address":"Shop 4 Boulevarde Shopng Cntr",
    "sg:city":"Broome",
    "sg:classifiers":[
        {
            "category":"Health Services",
            "subcategory":"Optometrist",
            "type":"Services"
        }
    ],
    "sg:phone":"+61 8 9192 3444",
    "sg:postcode":"6725",
    "sg:province":"WA",
    "wof:name":"OPSM",
    "wof:placetype":"venue"
},
  "geometry": {"coordinates":[122.243087769,-17.9566612244],"type":"Point"}
}