{
  "type": "Feature",
  "properties": {
    "addr:full":"32 Arunta St Tarragindi QLD 4121",
    "addr:housenumber":"32",
    "addr:postcode":"4121",
    "addr:street":"Arunta St",
    "iso:country":"AU",
    "sg:address":"32 Arunta St",
    "sg:city":"Tarragindi",
    "sg:classifiers":[
        {
            "category":"Professional",
            "subcategory":"Employment Agencies",
            "type":"Services"
        }
    ],
    "sg:phone":"+61 7 3397 8522",
    "sg:postcode":"4121",
    "sg:province":"QLD",
    "wof:name":"Direct Care Resources",
    "wof:placetype":"venue"
},
  "geometry": {"coordinates":[153.05447387699999,-27.5293731689],"type":"Point"}
}