{
  "type": "Feature",
  "properties": {
    "addr:full":"PO Box 224 Swan Hill VIC 3585",
    "addr:postcode":"3585",
    "iso:country":"AU",
    "sg:address":"PO Box 224",
    "sg:city":"Swan Hill",
    "sg:classifiers":[
        {
            "category":"Building & Trades",
            "subcategory":"Landscaping Services",
            "type":"Services"
        }
    ],
    "sg:phone":"+61 407 322 647",
    "sg:postcode":"3585",
    "sg:province":"VIC",
    "sg:tags":[
        "designer",
        "landscape",
        "contractor"
    ],
    "wof:name":"Heritage Contractors",
    "wof:placetype":"venue"
},
  "geometry": {"coordinates":[143.561554,-35.340969],"type":"Point"}
}