{
  "type": "Feature",
  "properties": {
    "addr:full":"148 Acland St St Kilda VIC 3182",
    "addr:housenumber":"148",
    "addr:postcode":"3182",
    "addr:street":"Acland St",
    "iso:country":"AU",
    "sg:address":"148 Acland St",
    "sg:city":"St Kilda",
    "sg:classifiers":[
        {
            "category":"Shopping",
            "subcategory":"Clothing, Apparel, & Fashions",
            "type":"Retail Goods"
        }
    ],
    "sg:phone":"+61 3 9534 9351",
    "sg:postcode":"3182",
    "sg:province":"VIC",
    "sg:tags":[
        "boutique"
    ],
    "wof:name":"Seagulls Boutique",
    "wof:placetype":"venue"
},
  "geometry": {"coordinates":[144.98023986800001,-37.8688163757],"type":"Point"}
}