{
  "type": "Feature",
  "properties": {
    "iso:country":"AU",
    "sg:address":"16 Lochlarney St",
    "sg:city":"Beenleigh",
    "sg:classifiers":[
        {
            "category":"Manufacturing",
            "subcategory":"Glass & Minerals",
            "type":"Manufacturing & Wholesale Goods"
        }
    ],
    "sg:phone":"+61 7 3382 0499",
    "sg:postcode":"4207",
    "sg:province":"QLD",
    "sg:tags":[
        "merchant",
        "granite",
        "marble"
    ],
    "wof:name":"Contemporary Marble & Granite",
    "wof:placetype":"venue"
},
  "geometry": {"coordinates":[153.185348511,-27.7125320435],"type":"Point"}
}