{
  "type": "Feature",
  "properties": {
    "addr:full":"Shop 1, Griffin Plaza Yambil St Griffith NSW 2680",
    "addr:housenumber":"shop 1",
    "addr:postcode":"2680",
    "addr:street":"Griffin Plaza Yambil St",
    "iso:country":"AU",
    "sg:address":"Shop 1, Griffin Plaza Yambil St",
    "sg:city":"Griffith",
    "sg:classifiers":[
        {
            "category":"Utilities",
            "subcategory":"Telephone",
            "type":"Services"
        }
    ],
    "sg:phone":"+61 2 6964 5644",
    "sg:postcode":"2680",
    "sg:province":"NSW",
    "sg:tags":[
        "accessory"
    ],
    "wof:name":"Telstra Shop Griffith",
    "wof:placetype":"venue"
},
  "geometry": {"coordinates":[146.04849200000001,-34.289597],"type":"Point"}
}