{
  "type": "Feature",
  "properties": {
    "iso:country":"AU",
    "sg:address":"205 Grote St",
    "sg:city":"Adelaide",
    "sg:classifiers":[
        {
            "category":"Food & Beverages",
            "subcategory":"Liquor & Beverages",
            "type":"Retail Goods"
        }
    ],
    "sg:phone":"+61 8 8112 4200",
    "sg:postcode":"5000",
    "sg:province":"SA",
    "sg:tags":[
        "merchant",
        "spirit",
        "wine"
    ],
    "wof:name":"Samuel Smith & Son Pty Ltd",
    "wof:placetype":"venue"
},
  "geometry": {"coordinates":[138.591873169,-34.9292373657],"type":"Point"}
}