{
  "type": "Feature",
  "properties": {
    "addr:full":"3 Wadkins Crt Parkwood QLD 4214",
    "addr:housenumber":"3",
    "addr:postcode":"4214",
    "addr:street":"Wadkins Crt",
    "iso:country":"AU",
    "sg:address":"3 Wadkins Crt",
    "sg:city":"Parkwood",
    "sg:classifiers":[
        {
            "category":"Professional",
            "type":"Services"
        }
    ],
    "sg:phone":"+61 1300 799 645",
    "sg:postcode":"4214",
    "sg:province":"QLD",
    "sg:tags":[
        "message",
        "answering",
        "telephone"
    ],
    "wof:name":"On Hold Business Plus Pty Ltd",
    "wof:placetype":"venue"
},
  "geometry": {"coordinates":[153.36361694300001,-27.9597816467],"type":"Point"}
}