{
  "type": "Feature",
  "properties": {
    "addr:full":"47 Alver Rd Doubleview WA 6018",
    "addr:housenumber":"47",
    "addr:postcode":"6018",
    "addr:street":"Alver Rd",
    "iso:country":"AU",
    "sg:address":"47 Alver Rd",
    "sg:city":"Doubleview",
    "sg:classifiers":[
        {
            "category":"Retail",
            "subcategory":"Laundry & Dry Cleaning",
            "type":"Services"
        }
    ],
    "sg:phone":"+61 411 735 960",
    "sg:postcode":"6018",
    "sg:province":"WA",
    "sg:tags":[
        "equipment",
        "supply"
    ],
    "wof:name":"Allwest Commercial Laundry Equipment",
    "wof:placetype":"venue"
},
  "geometry": {"coordinates":[115.786010742,-31.9059715271],"type":"Point"}
}