{
  "type": "Feature",
  "properties": {
    "addr:full":"Suite 3 240 New South Head Rd Edgecliff NSW 2027",
    "addr:housenumber":"240",
    "addr:postcode":"2027",
    "addr:street":"New South Head Rd",
    "iso:country":"AU",
    "sg:address":"Suite 3 240 New South Head Rd",
    "sg:city":"Edgecliff",
    "sg:classifiers":[
        {
            "category":"Building & Trades",
            "subcategory":"Construction",
            "type":"Services"
        }
    ],
    "sg:phone":"+61 2 9328 3800",
    "sg:postcode":"2027",
    "sg:province":"NSW",
    "sg:tags":[
        "renovation",
        "alterations",
        "extension",
        "contractor"
    ],
    "wof:name":"Residential Constructive",
    "wof:placetype":"venue"
},
  "geometry": {"coordinates":[151.238525391,-33.8790779114],"type":"Point"}
}