{
  "type": "Feature",
  "properties": {
    "iso:country":"AU",
    "sg:address":"62 Sydenham Rd",
    "sg:city":"Norwood",
    "sg:classifiers":[
        {
            "category":"Personal",
            "type":"Services"
        }
    ],
    "sg:phone":"+61 8 8362 4885",
    "sg:postcode":"5067",
    "sg:province":"SA",
    "sg:tags":[
        "gift"
    ],
    "wof:name":"The Basement Online",
    "wof:placetype":"venue"
},
  "geometry": {"coordinates":[138.62765502900001,-34.920375824],"type":"Point"}
}