{
  "type": "Feature",
  "properties": {
    "addr:full":"18 Stirling Crs Surrey Hills VIC 3127",
    "addr:housenumber":"18",
    "addr:postcode":"3127",
    "addr:street":"Stirling Crs",
    "iso:country":"AU",
    "sg:address":"18 Stirling Crs",
    "sg:city":"Surrey Hills",
    "sg:classifiers":[
        {
            "category":"Shopping",
            "subcategory":"Computers & Home Electronics",
            "type":"Retail Goods"
        }
    ],
    "sg:phone":"+61 3 9836 2566",
    "sg:postcode":"3127",
    "sg:province":"VIC",
    "sg:tags":[
        "wholesaler",
        "mfrs",
        "part",
        "electronic"
    ],
    "wof:name":"Consulaust International Pty Ltd",
    "wof:placetype":"venue"
},
  "geometry": {"coordinates":[145.09730529800001,-37.8255195618],"type":"Point"}
}