{
  "type": "Feature",
  "properties": {
    "addr:full":"21 King St Caboolture QLD 4510",
    "addr:housenumber":"21",
    "addr:postcode":"4510",
    "addr:street":"King St",
    "iso:country":"AU",
    "sg:address":"21 King St",
    "sg:city":"Caboolture",
    "sg:classifiers":[
        {
            "category":"Banks & Credit Unions",
            "subcategory":"Bank",
            "type":"Services"
        }
    ],
    "sg:phone":"+61 7 5495 1037",
    "sg:postcode":"4510",
    "sg:province":"QLD",
    "wof:name":"Commonwealth Bank Of Australia",
    "wof:placetype":"venue"
},
  "geometry": {"coordinates":[152.952316,-27.084681],"type":"Point"}
}