{
  "type": "Feature",
  "properties": {
    "addr:full":"5 Daniel St Nambour QLD 4560",
    "addr:housenumber":"5",
    "addr:postcode":"4560",
    "addr:street":"Daniel St",
    "iso:country":"AU",
    "sg:address":"5 Daniel St",
    "sg:city":"Nambour",
    "sg:classifiers":[
        {
            "category":"Organizations",
            "subcategory":"Non-profit Organization",
            "type":"Services"
        }
    ],
    "sg:phone":"+61 7 5441 6600",
    "sg:postcode":"4560",
    "sg:province":"QLD",
    "sg:tags":[
        "support",
        "disability",
        "organisation"
    ],
    "wof:name":"Sunshine Coast Link Family Scheme",
    "wof:placetype":"venue"
},
  "geometry": {"coordinates":[152.933303833,-26.6501312256],"type":"Point"}
}