{
  "type": "Feature",
  "properties": {
    "addr:full":"62 Yass St Gunning NSW 2581",
    "addr:housenumber":"62",
    "addr:postcode":"2581",
    "addr:street":"Yass St",
    "iso:country":"AU",
    "sg:address":"62 Yass St",
    "sg:city":"Gunning",
    "sg:classifiers":[
        {
            "category":"Cafe",
            "type":"Food & Drink"
        }
    ],
    "sg:phone":"+61 2 4845 1250",
    "sg:postcode":"2581",
    "sg:province":"NSW",
    "wof:name":"Merino Cafe",
    "wof:placetype":"venue"
},
  "geometry": {"coordinates":[149.265457153,-34.7829475403],"type":"Point"}
}