{
  "type": "Feature",
  "properties": {
    "addr:full":"90 Wantirna Rd Ringwood VIC 3134",
    "addr:housenumber":"90",
    "addr:postcode":"3134",
    "addr:street":"Wantirna Rd",
    "iso:country":"AU",
    "sg:address":"90 Wantirna Rd",
    "sg:city":"Ringwood",
    "sg:classifiers":[
        {
            "category":"Retail",
            "subcategory":"Repair Shop",
            "type":"Services"
        }
    ],
    "sg:phone":"+61 3 9879 2493",
    "sg:postcode":"3134",
    "sg:province":"VIC",
    "sg:tags":[
        "upholsterer"
    ],
    "wof:name":"Ringwood Restoration",
    "wof:placetype":"venue"
},
  "geometry": {"coordinates":[145.22715759299999,-37.8251304626],"type":"Point"}
}