{
  "type": "Feature",
  "properties": {
    "iso:country":"AU",
    "sg:address":"211 Peel St",
    "sg:city":"Tamworth",
    "sg:classifiers":[
        {
            "category":"Retail",
            "subcategory":"Event Space",
            "type":"Services"
        }
    ],
    "sg:phone":"+61 2 6766 2442",
    "sg:postcode":"2340",
    "sg:province":"NSW",
    "sg:tags":[
        "venue",
        "reception",
        "wedding"
    ],
    "wof:name":"The Albert",
    "wof:placetype":"venue"
},
  "geometry": {"coordinates":[150.926803589,-31.0875740051],"type":"Point"}
}