{
  "type": "Feature",
  "properties": {
    "addr:full":"45 Kurrajong St Dorrigo NSW 2453",
    "addr:housenumber":"45",
    "addr:postcode":"2453",
    "addr:street":"Kurrajong St",
    "iso:country":"AU",
    "sg:address":"45 Kurrajong St",
    "sg:city":"Dorrigo",
    "sg:classifiers":[
        {
            "category":"Building & Trades",
            "subcategory":"Construction",
            "type":"Services"
        }
    ],
    "sg:phone":"+61 2 6657 2585",
    "sg:postcode":"2453",
    "sg:province":"NSW",
    "sg:tags":[
        "contractor"
    ],
    "wof:name":"Francis Bros",
    "wof:placetype":"venue"
},
  "geometry": {"coordinates":[152.71484375,-30.3377628326],"type":"Point"}
}