{
  "type": "Feature",
  "properties": {
    "addr:full":"Ouyen Hwy Pinnaroo SA 5304",
    "addr:postcode":"5304",
    "addr:street":"Ouyen Hwy",
    "iso:country":"AU",
    "sg:address":"Ouyen Hwy",
    "sg:city":"Pinnaroo",
    "sg:classifiers":[
        {
            "category":"Restaurant",
            "type":"Food & Drink"
        }
    ],
    "sg:phone":"+61 8 8577 8488",
    "sg:postcode":"5304",
    "sg:province":"SA",
    "sg:tags":[
        "roadhouse"
    ],
    "wof:name":"Mobil Pinnaroo",
    "wof:placetype":"venue"
},
  "geometry": {"coordinates":[140.872512817,-35.304599762],"type":"Point"}
}