{
  "type": "Feature",
  "properties": {
    "addr:full":"297 Montacute Rd Newton SA 5074",
    "addr:housenumber":"297",
    "addr:postcode":"5074",
    "addr:street":"Montacute Rd",
    "iso:country":"AU",
    "sg:address":"297 Montacute Rd",
    "sg:city":"Newton",
    "sg:classifiers":[
        {
            "category":"Restaurant",
            "type":"Food & Drink"
        }
    ],
    "sg:phone":"+61 8 8336 8716",
    "sg:postcode":"5074",
    "sg:province":"SA",
    "wof:name":"Chinese Garden Restaurant",
    "wof:placetype":"venue"
},
  "geometry": {"coordinates":[138.69015502900001,-34.8867454529],"type":"Point"}
}