{
  "type": "Feature",
  "properties": {
    "iso:country":"AU",
    "sg:address":"105 Budgewoi Rd",
    "sg:city":"Noraville",
    "sg:classifiers":[
        {
            "category":"Banks & Credit Unions",
            "subcategory":"Bank",
            "type":"Services"
        }
    ],
    "sg:phone":"+61 416 273 254",
    "sg:postcode":"2263",
    "sg:province":"NSW",
    "sg:tags":[
        "concrete",
        "reinforcement"
    ],
    "wof:name":"Leaity Mike Reinforcing Pty Ltd",
    "wof:placetype":"venue"
},
  "geometry": {"coordinates":[151.560715,-33.261581],"type":"Point"}
}