{
  "type": "Feature",
  "properties": {
    "addr:full":"Ste 3/ 29 Ord St West Perth WA 6005",
    "addr:housenumber":"29",
    "addr:postcode":"6005",
    "addr:street":"Ord St",
    "iso:country":"AU",
    "sg:address":"Ste 3/ 29 Ord St",
    "sg:city":"West Perth",
    "sg:classifiers":[
        {
            "category":"Banks & Credit Unions",
            "subcategory":"Atm",
            "type":"Services"
        }
    ],
    "sg:phone":"+61 8 9321 7101",
    "sg:postcode":"6005",
    "sg:province":"WA",
    "sg:tags":[
        "premium",
        "insurance",
        "finance"
    ],
    "wof:name":"Pacific Premium Funding",
    "wof:placetype":"venue"
},
  "geometry": {"coordinates":[115.84082031200001,-31.9507198334],"type":"Point"}
}