{
  "type": "Feature",
  "properties": {
    "addr:full":"1b Marine Pde Merimbula NSW 2548",
    "addr:housenumber":"1b",
    "addr:postcode":"2548",
    "addr:street":"Marine Pde",
    "iso:country":"AU",
    "sg:address":"1b Marine Pde",
    "sg:city":"Merimbula",
    "sg:classifiers":[
        {
            "category":"Recreation",
            "subcategory":"Fishing",
            "type":"Entertainment"
        }
    ],
    "sg:phone":"+61 2 6495 2171",
    "sg:postcode":"2548",
    "sg:province":"NSW",
    "sg:tags":[
        "bait"
    ],
    "wof:name":"Cycle &#039;N&#039; Surf",
    "wof:placetype":"venue"
},
  "geometry": {"coordinates":[149.914825439,-36.8957710266],"type":"Point"}
}