{
  "type": "Feature",
  "properties": {
    "iso:country":"AU",
    "sg:address":"130 Herring Rd",
    "sg:city":"North Ryde",
    "sg:classifiers":[
        {
            "category":"Education",
            "subcategory":"University",
            "type":"Public Place"
        }
    ],
    "sg:phone":"+61 2 9856 1000",
    "sg:postcode":"2113",
    "sg:province":"NSW",
    "sg:tags":[
        "college",
        "tertiary"
    ],
    "wof:name":"Dunmore Lang College",
    "wof:placetype":"venue"
},
  "geometry": {"coordinates":[151.11604309099999,-33.7789993286],"type":"Point"}
}