{
  "type": "Feature",
  "properties": {
    "iso:country":"AU",
    "sg:address":"Suite 11 / 84 Wises Rd",
    "sg:city":"Maroochydore",
    "sg:classifiers":[
        {
            "category":"Shopping",
            "subcategory":"News",
            "type":"Retail Goods"
        }
    ],
    "sg:phone":"+61 7 5443 1824",
    "sg:postcode":"4558",
    "sg:province":"QLD",
    "sg:tags":[
        "magazine",
        "periodical"
    ],
    "wof:name":"Sunshine Coast Community & Tourism Guide",
    "wof:placetype":"venue"
},
  "geometry": {"coordinates":[153.08360290499999,-26.6710605621],"type":"Point"}
}