{
  "type": "Feature",
  "properties": {
    "addr:full":"25 Beaconsfield Rd Rooty Hill NSW 2766",
    "addr:housenumber":"25",
    "addr:postcode":"2766",
    "addr:street":"Beaconsfield Rd",
    "iso:country":"AU",
    "sg:address":"25 Beaconsfield Rd",
    "sg:city":"Rooty Hill",
    "sg:classifiers":[
        {
            "category":"Building & Trades",
            "subcategory":"Construction",
            "type":"Services"
        }
    ],
    "sg:phone":"+61 2 9625 9793",
    "sg:postcode":"2766",
    "sg:province":"NSW",
    "sg:tags":[
        "polishing",
        "sanding",
        "floor"
    ],
    "wof:name":"E & E Impieri Floor Sanding Specialist",
    "wof:placetype":"venue"
},
  "geometry": {"coordinates":[150.84417724599999,-33.7835769653],"type":"Point"}
}