{
  "type": "Feature",
  "properties": {
    "iso:country":"AU",
    "sg:address":"2 Freeling St",
    "sg:city":"Naracoorte",
    "sg:classifiers":[
        {
            "category":"Building & Trades",
            "subcategory":"Plumbing",
            "type":"Services"
        }
    ],
    "sg:phone":"+61 8 8762 1310",
    "sg:postcode":"5271",
    "sg:province":"SA",
    "sg:tags":[
        "plumber",
        "gasfitters"
    ],
    "wof:name":"Grarock Pty Ltd M R & H",
    "wof:placetype":"venue"
},
  "geometry": {"coordinates":[140.73083500000001,-36.953453],"type":"Point"}
}