{
  "type": "Feature",
  "properties": {
    "iso:country":"AU",
    "sg:address":"4A/ 1 Hampden Rd",
    "sg:city":"Artarmon",
    "sg:classifiers":[
        {
            "category":"Government",
            "subcategory":"Court House",
            "type":"Public Place"
        }
    ],
    "sg:phone":"+61 2 9412 4436",
    "sg:postcode":"2064",
    "sg:province":"NSW",
    "sg:tags":[
        "personal",
        "marriage",
        "family",
        "counselling"
    ],
    "wof:name":"Anne Penny Woods",
    "wof:placetype":"venue"
},
  "geometry": {"coordinates":[151.188720703,-33.8125762939],"type":"Point"}
}