{
  "type": "Feature",
  "properties": {
    "addr:full":"Suite 303, 12 Cato St Hawthorn East VIC 3123",
    "addr:housenumber":"12",
    "addr:postcode":"3123",
    "addr:street":"Cato St",
    "iso:country":"AU",
    "sg:address":"Suite 303, 12 Cato St",
    "sg:city":"Hawthorn East",
    "sg:classifiers":[
        {
            "category":"Health Services",
            "subcategory":"Doctor",
            "type":"Services"
        }
    ],
    "sg:phone":"+61 3 9832 2260",
    "sg:postcode":"3123",
    "sg:province":"VIC",
    "sg:tags":[
        "medical",
        "practitioner"
    ],
    "wof:name":"Corcoran Susan",
    "wof:placetype":"venue"
},
  "geometry": {"coordinates":[145.04281616200001,-37.84324646],"type":"Point"}
}