{
  "type": "Feature",
  "properties": {
    "addr:full":"23 Mindaribba Ave Rouse Hill NSW 2155",
    "addr:housenumber":"23",
    "addr:postcode":"2155",
    "addr:street":"Mindaribba Ave",
    "iso:country":"AU",
    "sg:address":"23 Mindaribba Ave",
    "sg:city":"Rouse Hill",
    "sg:classifiers":[
        {
            "category":"Shopping",
            "subcategory":"Computers & Home Electronics",
            "type":"Retail Goods"
        }
    ],
    "sg:phone":"+61 2 9629 4413",
    "sg:postcode":"2155",
    "sg:province":"NSW",
    "sg:tags":[
        "equipment",
        "supply"
    ],
    "wof:name":"Repro Media Systems",
    "wof:placetype":"venue"
},
  "geometry": {"coordinates":[150.93003845199999,-33.6785163879],"type":"Point"}
}