{
  "type": "Feature",
  "properties": {
    "addr:full":"650 Port Rd Beverley SA 5009",
    "addr:housenumber":"650",
    "addr:postcode":"5009",
    "addr:street":"Port Rd",
    "iso:country":"AU",
    "sg:address":"650 Port Rd",
    "sg:city":"Beverley",
    "sg:classifiers":[
        {
            "category":"Retail",
            "subcategory":"Auto Repair",
            "type":"Services"
        }
    ],
    "sg:phone":"+61 8 8345 5866",
    "sg:postcode":"5009",
    "sg:province":"SA",
    "sg:tags":[
        "wheel",
        "balancing",
        "alignment"
    ],
    "wof:name":"Auto Steering & Wheel Alignment Specialists",
    "wof:placetype":"venue"
},
  "geometry": {"coordinates":[138.54925537099999,-34.8905487061],"type":"Point"}
}