{
  "type": "Feature",
  "properties": {
    "addr:full":"Hooker Rd Nyora VIC 3987",
    "addr:postcode":"3987",
    "addr:street":"Hooker Rd",
    "iso:country":"AU",
    "sg:address":"Hooker Rd",
    "sg:city":"Nyora",
    "sg:classifiers":[
        {
            "category":"Manufacturing",
            "subcategory":"Paper Products",
            "type":"Manufacturing & Wholesale Goods"
        }
    ],
    "sg:phone":"+61 3 5659 0090",
    "sg:postcode":"3987",
    "sg:province":"VIC",
    "sg:tags":[
        "sawdust",
        "supplier",
        "shaving"
    ],
    "wof:name":"T G S Sand & Soil",
    "wof:placetype":"venue"
},
  "geometry": {"coordinates":[145.62190246599999,-38.3186149597],"type":"Point"}
}