{
  "type": "Feature",
  "properties": {
    "addr:full":"364 Clarendon St South Melbourne VIC 3205",
    "addr:housenumber":"364",
    "addr:postcode":"3205",
    "addr:street":"Clarendon St",
    "iso:country":"AU",
    "sg:address":"364 Clarendon St",
    "sg:city":"South Melbourne",
    "sg:classifiers":[
        {
            "category":"Retail",
            "subcategory":"Event Space",
            "type":"Services"
        }
    ],
    "sg:phone":"+61 3 9690 0995",
    "sg:postcode":"3205",
    "sg:province":"VIC",
    "sg:tags":[
        "function",
        "organiser"
    ],
    "wof:name":"Limerick Hotel",
    "wof:placetype":"venue"
},
  "geometry": {"coordinates":[144.962051,-37.83585],"type":"Point"}
}