{
  "type": "Feature",
  "properties": {
    "iso:country":"AU",
    "sg:address":"558a Pennant Hills Rd",
    "sg:city":"West Pennant Hills",
    "sg:classifiers":[
        {
            "category":"Fast Food",
            "type":"Food & Drink"
        }
    ],
    "sg:phone":"+61 2 9484 3409",
    "sg:postcode":"2125",
    "sg:province":"NSW",
    "sg:tags":[
        "away",
        "take"
    ],
    "wof:name":"West Pennant Hills Pizzeria",
    "wof:placetype":"venue"
},
  "geometry": {"coordinates":[151.04745483400001,-33.7538948059],"type":"Point"}
}