{
  "type": "Feature",
  "properties": {
    "addr:full":"52 Cleary St Hamilton NSW 2303",
    "addr:housenumber":"52",
    "addr:postcode":"2303",
    "addr:street":"Cleary St",
    "iso:country":"AU",
    "sg:address":"52 Cleary St",
    "sg:city":"Hamilton",
    "sg:classifiers":[
        {
            "category":"Restaurant",
            "type":"Food & Drink"
        }
    ],
    "sg:phone":"+61 2 4965 3648",
    "sg:postcode":"2303",
    "sg:province":"NSW",
    "wof:name":"Bistro Tartine",
    "wof:placetype":"venue"
},
  "geometry": {"coordinates":[151.74783300000001,-32.920738],"type":"Point"}
}