{
  "type": "Feature",
  "properties": {
    "addr:full":"24 Faithful St Wangaratta VIC 3677",
    "addr:housenumber":"24",
    "addr:postcode":"3677",
    "addr:street":"Faithful St",
    "iso:country":"AU",
    "sg:address":"24 Faithful St",
    "sg:city":"Wangaratta",
    "sg:classifiers":[
        {
            "category":"Fast Food",
            "type":"Food & Drink"
        }
    ],
    "sg:phone":"+61 3 5721 7458",
    "sg:postcode":"3677",
    "sg:province":"VIC",
    "sg:tags":[
        "away",
        "take"
    ],
    "wof:name":"Chicken Time",
    "wof:placetype":"venue"
},
  "geometry": {"coordinates":[146.32850647000001,-36.3536567688],"type":"Point"}
}