{
  "type": "Feature",
  "properties": {
    "addr:full":"14 Gray Ave Mt Warrigal NSW 2528",
    "addr:housenumber":"14",
    "addr:postcode":"2528",
    "addr:street":"Gray Ave Mt Warrigal",
    "iso:country":"AU",
    "sg:address":"14 Gray Ave",
    "sg:city":"Mt Warrigal",
    "sg:classifiers":[
        {
            "category":"Professional",
            "subcategory":"Computer Services",
            "type":"Services"
        }
    ],
    "sg:phone":"+61 2 4297 8033",
    "sg:postcode":"2528",
    "sg:province":"NSW",
    "sg:tags":[
        "repairs",
        "upgrade",
        "equipment"
    ],
    "wof:name":"Colt Computers",
    "wof:placetype":"venue"
},
  "geometry": {"coordinates":[150.83920288100001,-34.5510597229],"type":"Point"}
}