{
  "type": "Feature",
  "properties": {
    "iso:country":"AU",
    "sg:address":"32 Macaranga St",
    "sg:city":"Marsden",
    "sg:classifiers":[
        {
            "category":"Building & Trades",
            "subcategory":"Construction",
            "type":"Services"
        }
    ],
    "sg:phone":"+61 7 3388 4377",
    "sg:postcode":"4132",
    "sg:province":"QLD",
    "sg:tags":[
        "plasterboard",
        "plasterer",
        "fixer"
    ],
    "wof:name":"Lets Get Plastered",
    "wof:placetype":"venue"
},
  "geometry": {"coordinates":[153.11085510300001,-27.6782932281],"type":"Point"}
}