{
  "type": "Feature",
  "properties": {
    "addr:full":"Shop 2/ 130 Elizabeth Drv Liverpool NSW 2170",
    "addr:housenumber":"shop 2 / 130",
    "addr:postcode":"2170",
    "addr:street":"Elizabeth Drv",
    "iso:country":"AU",
    "sg:address":"Shop 2/ 130 Elizabeth Drv",
    "sg:city":"Liverpool",
    "sg:classifiers":[
        {
            "category":"Fast Food",
            "type":"Food & Drink"
        }
    ],
    "sg:phone":"+61 2 9601 2939",
    "sg:postcode":"2170",
    "sg:province":"NSW",
    "sg:tags":[
        "away",
        "take"
    ],
    "wof:name":"4 Seasons Charcoal Chicken & Takeaway",
    "wof:placetype":"venue"
},
  "geometry": {"coordinates":[150.91119384800001,-33.9167480469],"type":"Point"}
}