{
  "type": "Feature",
  "properties": {
    "addr:full":"39 Gueudecourt Ave Earlwood NSW 2206",
    "addr:housenumber":"39",
    "addr:postcode":"2206",
    "addr:street":"Gueudecourt Ave",
    "iso:country":"AU",
    "sg:address":"39 Gueudecourt Ave",
    "sg:city":"Earlwood",
    "sg:classifiers":[
        {
            "category":"Building & Trades",
            "subcategory":"Construction",
            "type":"Services"
        }
    ],
    "sg:phone":"+61 2 9559 2546",
    "sg:postcode":"2206",
    "sg:province":"NSW",
    "sg:tags":[
        "contractor"
    ],
    "wof:name":"Boland A J",
    "wof:placetype":"venue"
},
  "geometry": {"coordinates":[151.12756300000001,-33.921181],"type":"Point"}
}