{
  "type": "Feature",
  "properties": {
    "addr:full":"210 Clarinda St Parkes NSW 2870",
    "addr:housenumber":"210",
    "addr:postcode":"2870",
    "addr:street":"Clarinda St",
    "iso:country":"AU",
    "sg:address":"210 Clarinda St",
    "sg:city":"Parkes",
    "sg:classifiers":[
        {
            "category":"Fast Food",
            "type":"Food & Drink"
        }
    ],
    "sg:phone":"+61 2 6862 4233",
    "sg:postcode":"2870",
    "sg:province":"NSW",
    "sg:tags":[
        "away",
        "take"
    ],
    "wof:name":"Hong Loch Chinese Restaurant",
    "wof:placetype":"venue"
},
  "geometry": {"coordinates":[148.17482000000001,-33.13707],"type":"Point"}
}