{
  "type": "Feature",
  "properties": {
    "addr:full":"Unit 1/ 4 Dean Pl Penrith NSW 2750",
    "addr:housenumber":"4",
    "addr:postcode":"2750",
    "addr:street":"Dean Pl",
    "iso:country":"AU",
    "sg:address":"Unit 1/ 4 Dean Pl",
    "sg:city":"Penrith",
    "sg:classifiers":[
        {
            "category":"Retail",
            "subcategory":"Auto Repair",
            "type":"Services"
        }
    ],
    "sg:phone":"+61 2 4722 3426",
    "sg:postcode":"2750",
    "sg:province":"NSW",
    "sg:tags":[
        "repairer",
        "motor",
        "engineer"
    ],
    "wof:name":"Castlereagh Car Clinic",
    "wof:placetype":"venue"
},
  "geometry": {"coordinates":[150.914596558,-33.7365951538],"type":"Point"}
}