{
  "type": "Feature",
  "properties": {
    "iso:country":"AU",
    "sg:address":"Level 1,Mudgeeraba Professional Centre Swan Lane",
    "sg:city":"Mudgeeraba",
    "sg:classifiers":[
        {
            "category":"Real Estate",
            "subcategory":"Real Estate Agent",
            "type":"Services"
        }
    ],
    "sg:phone":"+61 407 676 668",
    "sg:postcode":"4213",
    "sg:province":"QLD",
    "wof:name":"David Brown Real Estate",
    "wof:placetype":"venue"
},
  "geometry": {"coordinates":[153.36517334000001,-28.0766716003],"type":"Point"}
}