{
  "type": "Feature",
  "properties": {
    "iso:country":"AU",
    "sg:address":"6 Bridgnorth St",
    "sg:city":"Carindale",
    "sg:classifiers":[
        {
            "category":"Retail",
            "subcategory":"Driving School",
            "type":"Services"
        }
    ],
    "sg:phone":"+61 7 3395 3431",
    "sg:postcode":"4152",
    "sg:province":"QLD",
    "wof:name":"Omega Driving School",
    "wof:placetype":"venue"
},
  "geometry": {"coordinates":[153.108810425,-27.5020484924],"type":"Point"}
}