{
  "type": "Feature",
  "properties": {
    "addr:full":"21 Beacon Ave Beacon Hill NSW 2100",
    "addr:housenumber":"21",
    "addr:postcode":"2100",
    "addr:street":"Beacon Ave",
    "iso:country":"AU",
    "sg:address":"21 Beacon Ave",
    "sg:city":"Beacon Hill",
    "sg:classifiers":[
        {
            "category":"Building & Trades",
            "subcategory":"Plumbing",
            "type":"Services"
        }
    ],
    "sg:phone":"+61 2 9939 6659",
    "sg:postcode":"2100",
    "sg:province":"NSW",
    "sg:tags":[
        "plumber",
        "gasfitters"
    ],
    "wof:name":"A Baker Neil & Craig",
    "wof:placetype":"venue"
},
  "geometry": {"coordinates":[151.265548706,-33.7594490051],"type":"Point"}
}