{
  "type": "Feature",
  "properties": {
    "addr:full":"31 Watton St Werribee VIC 3030",
    "addr:housenumber":"31",
    "addr:postcode":"3030",
    "addr:street":"Watton St",
    "iso:country":"AU",
    "sg:address":"31 Watton St",
    "sg:city":"Werribee",
    "sg:classifiers":[
        {
            "category":"Manufacturing",
            "subcategory":"Motor Vehicles & Parts",
            "type":"Manufacturing & Wholesale Goods"
        }
    ],
    "sg:phone":"+61 3 9731 0644",
    "sg:postcode":"3030",
    "sg:province":"VIC",
    "sg:tags":[
        "replacement"
    ],
    "wof:name":"All Things Auto",
    "wof:placetype":"venue"
},
  "geometry": {"coordinates":[144.66304,-37.900528],"type":"Point"}
}