{
  "type": "Feature",
  "properties": {
    "iso:country":"AU",
    "sg:address":"14 Wordsworth St",
    "sg:city":"Strathpine",
    "sg:classifiers":[
        {
            "category":"Building & Trades",
            "subcategory":"Plumbing",
            "type":"Services"
        }
    ],
    "sg:phone":"+61 418 796 459",
    "sg:postcode":"4500",
    "sg:province":"QLD",
    "sg:tags":[
        "plumber",
        "gasfitters"
    ],
    "wof:name":"Darryl Robinsons Plumbing",
    "wof:placetype":"venue"
},
  "geometry": {"coordinates":[152.995635986,-27.2917366028],"type":"Point"}
}