{
  "type": "Feature",
  "properties": {
    "addr:full":"Wellness Centre, Cnr Cutbush & Stafford Rds Everton Park QLD 4053",
    "addr:postcode":"4053",
    "addr:street":"Cnr",
    "iso:country":"AU",
    "sg:address":"Wellness Centre, Cnr Cutbush & Stafford Rds",
    "sg:city":"Everton Park",
    "sg:classifiers":[
        {
            "category":"Personal",
            "subcategory":"Massage",
            "type":"Services"
        }
    ],
    "sg:phone":"+61 410 216 243",
    "sg:postcode":"4053",
    "sg:province":"QLD",
    "sg:tags":[
        "therapy"
    ],
    "sg:website":"http://www.atms.com.au",
    "wof:name":"Thyme For Aromatherapy",
    "wof:placetype":"venue"
},
  "geometry": {"coordinates":[152.99330139200001,-27.4070491791],"type":"Point"}
}