{
  "type": "Feature",
  "properties": {
    "iso:country":"AU",
    "sg:address":"419 Black Hills Rd",
    "sg:city":"Westbury",
    "sg:classifiers":[
        {
            "category":"Farming",
            "subcategory":"Farm",
            "type":"Manufacturing & Wholesale Goods"
        }
    ],
    "sg:phone":"+61 3 6397 3007",
    "sg:postcode":"7303",
    "sg:province":"TAS",
    "sg:tags":[
        "farmer"
    ],
    "wof:name":"Classic Park Alpaca Stud",
    "wof:placetype":"venue"
},
  "geometry": {"coordinates":[146.884369,-41.570625],"type":"Point"}
}