{
  "type": "Feature",
  "properties": {
    "addr:full":"127 Regent St Chippendale NSW 2008",
    "addr:housenumber":"127",
    "addr:postcode":"2008",
    "addr:street":"Regent St",
    "iso:country":"AU",
    "sg:address":"127 Regent St",
    "sg:city":"Chippendale",
    "sg:classifiers":[
        {
            "category":"Personal",
            "subcategory":"Adult",
            "type":"Services"
        }
    ],
    "sg:phone":"+61 2 8399 1680",
    "sg:postcode":"2008",
    "sg:province":"NSW",
    "sg:tags":[
        "vic",
        "except",
        "state",
        "escort",
        "social",
        "qld"
    ],
    "wof:name":"127 Asia House",
    "wof:placetype":"venue"
},
  "geometry": {"coordinates":[151.20132446299999,-33.8880081177],"type":"Point"}
}