{
  "type": "Feature",
  "properties": {
    "addr:full":"PO Box 438 Ballina NSW 2478",
    "addr:postcode":"2478",
    "iso:country":"AU",
    "sg:address":"PO Box 438",
    "sg:city":"Ballina",
    "sg:classifiers":[
        {
            "category":"Personal",
            "subcategory":"Tattoo Parlor",
            "type":"Services"
        }
    ],
    "sg:phone":"+61 2 6686 3441",
    "sg:postcode":"2478",
    "sg:province":"NSW",
    "sg:tags":[
        "resume"
    ],
    "wof:name":"Winning Edge Promotions",
    "wof:placetype":"venue"
},
  "geometry": {"coordinates":[153.554962158,-28.8678798676],"type":"Point"}
}