{
  "type": "Feature",
  "properties": {
    "addr:full":"Lawrence St Harbord NSW 2096",
    "addr:postcode":"2096",
    "addr:street":"Lawrence St",
    "iso:country":"AU",
    "sg:address":"Lawrence St",
    "sg:city":"Harbord",
    "sg:classifiers":[
        {
            "category":"Shopping",
            "subcategory":"Clothing, Apparel, & Fashions",
            "type":"Retail Goods"
        }
    ],
    "sg:phone":"+61 2 9905 0790",
    "sg:postcode":"2096",
    "sg:province":"NSW",
    "sg:tags":[
        "lady",
        "wear"
    ],
    "wof:name":"Splice Fashion & Living",
    "wof:placetype":"venue"
},
  "geometry": {"coordinates":[151.28363037099999,-33.7787742615],"type":"Point"}
}