{
  "type": "Feature",
  "properties": {
    "addr:full":"Shop 55, Castletown Shopping World, Woolcock St Pimlico QLD 4812",
    "addr:housenumber":"shop 55",
    "addr:postcode":"4812",
    "addr:street":"Castletown Shopping;Woolcock St",
    "iso:country":"AU",
    "sg:address":"Shop 55, Castletown Shopping World, Woolcock St",
    "sg:city":"Pimlico",
    "sg:classifiers":[
        {
            "category":"Banks & Credit Unions",
            "subcategory":"Bank",
            "type":"Services"
        }
    ],
    "sg:phone":"+61 7 4760 1000",
    "sg:postcode":"4812",
    "sg:province":"QLD",
    "wof:name":"Bank of Queensland",
    "wof:placetype":"venue"
},
  "geometry": {"coordinates":[146.79057299999999,-19.270943],"type":"Point"}
}