{
  "type": "Feature",
  "properties": {
    "addr:full":"2110 Glenelg Hwy Lake Bolac VIC 3351",
    "addr:housenumber":"2110",
    "addr:postcode":"3351",
    "addr:street":"Glenelg Hwy",
    "iso:country":"AU",
    "sg:address":"2110 Glenelg Hwy",
    "sg:city":"Lake Bolac",
    "sg:classifiers":[
        {
            "category":"Banks & Credit Unions",
            "subcategory":"Bank",
            "type":"Services"
        }
    ],
    "sg:phone":"+61 3 5350 2374",
    "sg:postcode":"3351",
    "sg:province":"VIC",
    "wof:name":"Bendigo Community Bank",
    "wof:placetype":"venue"
},
  "geometry": {"coordinates":[142.84167500000001,-37.711517],"type":"Point"}
}