{
  "type": "Feature",
  "properties": {
    "addr:full":"Ste 3/ 106 Main St Blacktown NSW 2148",
    "addr:housenumber":"/ 106",
    "addr:postcode":"2148",
    "addr:street":"Main St",
    "iso:country":"AU",
    "sg:address":"Ste 3/ 106 Main St",
    "sg:city":"Blacktown",
    "sg:classifiers":[
        {
            "category":"Health Services",
            "subcategory":"Dentist",
            "type":"Services"
        }
    ],
    "sg:phone":"+61 2 9676 1122",
    "sg:postcode":"2148",
    "sg:province":"NSW",
    "wof:name":"Sanati Shahriar Dr",
    "wof:placetype":"venue"
},
  "geometry": {"coordinates":[150.91014099099999,-33.7709770203],"type":"Point"}
}