{
  "type": "Feature",
  "properties": {
    "addr:full":"16 Opal Pl Bossley Park NSW 2176",
    "addr:housenumber":"16",
    "addr:postcode":"2176",
    "addr:street":"Opal Pl",
    "iso:country":"AU",
    "sg:address":"16 Opal Pl",
    "sg:city":"Bossley Park",
    "sg:classifiers":[
        {
            "category":"Building & Trades",
            "subcategory":"Construction",
            "type":"Services"
        }
    ],
    "sg:phone":"+61 414 496 235",
    "sg:postcode":"2176",
    "sg:province":"NSW",
    "sg:tags":[
        "joiner",
        "carpenter"
    ],
    "wof:name":"GS Building Solutions",
    "wof:placetype":"venue"
},
  "geometry": {"coordinates":[150.88554382300001,-33.8586349487],"type":"Point"}
}