{
  "type": "Feature",
  "properties": {
    "iso:country":"AU",
    "sg:address":"11 Devonshire Rd",
    "sg:city":"Sunshine",
    "sg:classifiers":[
        {
            "category":"Personal",
            "subcategory":"Beauty Salon",
            "type":"Services"
        }
    ],
    "sg:phone":"+61 3 9312 6563",
    "sg:postcode":"3020",
    "sg:province":"VIC",
    "sg:tags":[
        "hairdresser"
    ],
    "wof:name":"Vina Hair Studio",
    "wof:placetype":"venue"
},
  "geometry": {"coordinates":[144.831909,-37.784695],"type":"Point"}
}