{
  "type": "Feature",
  "properties": {
    "iso:country":"AU",
    "sg:address":"PO Box 125",
    "sg:city":"Kalamunda",
    "sg:classifiers":[
        {
            "category":"Utilities",
            "subcategory":"Electric",
            "type":"Services"
        }
    ],
    "sg:phone":"+61 414 267 168",
    "sg:postcode":"6926",
    "sg:province":"WA",
    "sg:tags":[
        "electrical",
        "contractor"
    ],
    "wof:name":"AAA Glens Electrical",
    "wof:placetype":"venue"
},
  "geometry": {"coordinates":[116.057312012,-31.9702205658],"type":"Point"}
}