{
  "type": "Feature",
  "properties": {
    "addr:full":"166 Gilbert Rd Preston West VIC 3072",
    "addr:housenumber":"166",
    "addr:postcode":"3072",
    "addr:street":"Gilbert Rd",
    "iso:country":"AU",
    "sg:address":"166 Gilbert Rd",
    "sg:city":"Preston West",
    "sg:classifiers":[
        {
            "category":"Health Services",
            "subcategory":"Health Practitioner",
            "type":"Services"
        }
    ],
    "sg:phone":"+61 3 9480 0938",
    "sg:postcode":"3072",
    "sg:province":"VIC",
    "sg:tags":[
        "acupuncture"
    ],
    "wof:name":"Giuliani Carlo",
    "wof:placetype":"venue"
},
  "geometry": {"coordinates":[144.989105225,-37.7455406189],"type":"Point"}
}