{
  "type": "Feature",
  "properties": {
    "addr:full":"PO Box 171 Glen Forrest WA 6071",
    "addr:postcode":"6071",
    "addr:street":"Glen",
    "iso:country":"AU",
    "sg:address":"PO Box 171",
    "sg:city":"Glen Forrest",
    "sg:classifiers":[
        {
            "category":"Train Station",
            "subcategory":"Rail",
            "type":"Transportation"
        }
    ],
    "sg:phone":"+61 419 959 025",
    "sg:postcode":"6071",
    "sg:province":"WA",
    "sg:tags":[
        "consultant"
    ],
    "wof:name":"MRP Group",
    "wof:placetype":"venue"
},
  "geometry": {"coordinates":[116.104270935,-31.9034500122],"type":"Point"}
}