{
  "type": "Feature",
  "properties": {
    "iso:country":"AU",
    "sg:address":"Shp 10/ 30 Wiluna St",
    "sg:city":"Yokine",
    "sg:classifiers":[
        {
            "category":"Food & Beverages",
            "subcategory":"Bakery",
            "type":"Retail Goods"
        }
    ],
    "sg:phone":"+61 8 9443 8831",
    "sg:postcode":"6060",
    "sg:province":"WA",
    "sg:tags":[
        "cake",
        "shop",
        "pastry"
    ],
    "wof:name":"Delish Patisserie",
    "wof:placetype":"venue"
},
  "geometry": {"coordinates":[115.84844207800001,-31.9113674164],"type":"Point"}
}