{
  "type": "Feature",
  "properties": {
    "iso:country":"AU",
    "sg:address":"24 Reid St",
    "sg:city":"Wodonga",
    "sg:classifiers":[
        {
            "category":"Retail",
            "subcategory":"Auto Repair",
            "type":"Services"
        }
    ],
    "sg:phone":"+61 2 6024 6911",
    "sg:postcode":"3690",
    "sg:province":"VIC",
    "sg:tags":[
        "repairer",
        "motor",
        "engineer"
    ],
    "wof:name":"Collishaws Service Centre",
    "wof:placetype":"venue"
},
  "geometry": {"coordinates":[146.89427185100001,-36.1232070923],"type":"Point"}
}