{
  "type": "Feature",
  "properties": {
    "iso:country":"AU",
    "sg:address":"363 Settlement Rd",
    "sg:city":"Thomastown",
    "sg:classifiers":[
        {
            "category":"Retail",
            "subcategory":"Auto Repair",
            "type":"Services"
        }
    ],
    "sg:phone":"+61 3 9465 1999",
    "sg:postcode":"3074",
    "sg:province":"VIC",
    "sg:tags":[
        "beater",
        "painter",
        "panel"
    ],
    "wof:name":"Northern Smash Repairs (Vic Proprietory Ltd)",
    "wof:placetype":"venue"
},
  "geometry": {"coordinates":[145.018432617,-37.688583374],"type":"Point"}
}