{
  "type": "Feature",
  "properties": {
    "addr:full":"38 Coleman Rd Wantirna South VIC 3152",
    "addr:housenumber":"38",
    "addr:postcode":"3152",
    "addr:street":"Coleman Rd",
    "iso:country":"AU",
    "sg:address":"38 Coleman Rd",
    "sg:city":"Wantirna South",
    "sg:classifiers":[
        {
            "category":"Building & Trades",
            "subcategory":"Plumbing",
            "type":"Services"
        }
    ],
    "sg:phone":"+61 3 9801 3524",
    "sg:postcode":"3152",
    "sg:province":"VIC",
    "sg:tags":[
        "plumber",
        "gasfitters"
    ],
    "wof:name":"Lancad Pty Ltd",
    "wof:placetype":"venue"
},
  "geometry": {"coordinates":[145.24703979500001,-37.8629798889],"type":"Point"}
}