{
  "type": "Feature",
  "properties": {
    "addr:full":"249c Grange Rd Findon SA 5023",
    "addr:housenumber":"249c",
    "addr:postcode":"5023",
    "addr:street":"Grange Rd",
    "iso:country":"AU",
    "sg:address":"249c Grange Rd",
    "sg:city":"Findon",
    "sg:classifiers":[
        {
            "category":"Personal",
            "subcategory":"Beauty Salon",
            "type":"Services"
        }
    ],
    "sg:phone":"+61 8 8268 1999",
    "sg:postcode":"5023",
    "sg:province":"SA",
    "wof:name":"Everlasting Beauty",
    "wof:placetype":"venue"
},
  "geometry": {"coordinates":[138.53851318400001,-34.9050445557],"type":"Point"}
}