{
  "type": "Feature",
  "properties": {
    "iso:country":"AU",
    "sg:address":"218 Princes Hwy",
    "sg:city":"Hallam",
    "sg:classifiers":[
        {
            "category":"Travel",
            "subcategory":"Hotels & Motels",
            "type":"Entertainment"
        }
    ],
    "sg:phone":"+61 3 9703 1255",
    "sg:postcode":"3803",
    "sg:province":"VIC",
    "wof:name":"Abode Thomas Lodge Motel Hallam",
    "wof:placetype":"venue"
},
  "geometry": {"coordinates":[145.27561950699999,-38.0071296692],"type":"Point"}
}