{
  "type": "Feature",
  "properties": {
    "iso:country":"AU",
    "sg:address":"Cnr Thomas & Cummings Rds",
    "sg:city":"Oakford",
    "sg:classifiers":[
        {
            "category":"Wholesale",
            "subcategory":"Farm Supplies",
            "type":"Manufacturing & Wholesale Goods"
        }
    ],
    "sg:phone":"+61 8 9419 5598",
    "sg:postcode":"6121",
    "sg:province":"WA",
    "sg:tags":[
        "equipment"
    ],
    "wof:name":"Oakford Agricultural & Garden Supplies",
    "wof:placetype":"venue"
},
  "geometry": {"coordinates":[115.968086243,-32.2070503235],"type":"Point"}
}