{
  "type": "Feature",
  "properties": {
    "addr:full":"14 Gatwick Rd Croydon VIC 3136",
    "addr:housenumber":"14",
    "addr:postcode":"3136",
    "addr:street":"Gatwick Rd",
    "iso:country":"AU",
    "sg:address":"14 Gatwick Rd",
    "sg:city":"Croydon",
    "sg:classifiers":[
        {
            "category":"Sports & Exercise",
            "subcategory":"Sports Center",
            "type":"Entertainment"
        }
    ],
    "sg:phone":"+61 3 9729 0988",
    "sg:postcode":"3136",
    "sg:province":"VIC",
    "sg:tags":[
        "ground"
    ],
    "wof:name":"Action Indoor Sports Stadiums",
    "wof:placetype":"venue"
},
  "geometry": {"coordinates":[145.297409058,-37.8192825317],"type":"Point"}
}