{
  "type": "Feature",
  "properties": {
    "addr:full":"23 Walker St South Windsor NSW 2756",
    "addr:housenumber":"23",
    "addr:postcode":"2756",
    "addr:street":"Walker St",
    "iso:country":"AU",
    "sg:address":"23 Walker St",
    "sg:city":"South Windsor",
    "sg:classifiers":[
        {
            "category":"School Buses",
            "type":"Transportation"
        }
    ],
    "sg:phone":"+61 2 4577 6100",
    "sg:postcode":"2756",
    "sg:province":"NSW",
    "sg:tags":[
        "brick"
    ],
    "wof:name":"Timbercrete Sydney",
    "wof:placetype":"venue"
},
  "geometry": {"coordinates":[150.80963134800001,-33.6244087219],"type":"Point"}
}