{
  "type": "Feature",
  "properties": {
    "addr:full":"21- 25 Scott St Toowoomba QLD 4350",
    "addr:housenumber":"25",
    "addr:postcode":"4350",
    "addr:street":"Scott St",
    "iso:country":"AU",
    "sg:address":"21- 25 Scott St",
    "sg:city":"Toowoomba",
    "sg:classifiers":[
        {
            "category":"Organizations",
            "subcategory":"Non-profit Organization",
            "type":"Services"
        }
    ],
    "sg:phone":"+61 7 4688 9400",
    "sg:postcode":"4350",
    "sg:province":"QLD",
    "sg:tags":[
        "support",
        "disability",
        "organisation"
    ],
    "wof:name":"Cerebral Palsy League of Queensland",
    "wof:placetype":"venue"
},
  "geometry": {"coordinates":[151.97155799999999,-27.565481],"type":"Point"}
}