{
  "type": "Feature",
  "properties": {
    "iso:country":"AU",
    "sg:address":"452 William St",
    "sg:city":"Perth",
    "sg:classifiers":[
        {
            "category":"Arts & Performance",
            "subcategory":"Art Gallery",
            "type":"Entertainment"
        }
    ],
    "sg:phone":"+61 8 9227 1077",
    "sg:postcode":"6000",
    "sg:province":"WA",
    "wof:name":"The Church Gallery",
    "wof:placetype":"venue"
},
  "geometry": {"coordinates":[115.85664367699999,-31.9540653229],"type":"Point"}
}