{
  "type": "Feature",
  "properties": {
    "iso:country":"AU",
    "sg:address":"28 Carbon Crt",
    "sg:city":"Osborne Park",
    "sg:classifiers":[
        {
            "category":"Home & Garden",
            "subcategory":"Carpets & Floor Coverings",
            "type":"Retail Goods"
        }
    ],
    "sg:phone":"+61 8 9445 3666",
    "sg:postcode":"6017",
    "sg:province":"WA",
    "wof:name":"Armstrong World Industries (Australia) Pty Ltd",
    "wof:placetype":"venue"
},
  "geometry": {"coordinates":[115.805023193,-31.9024200439],"type":"Point"}
}