{
  "type": "Feature",
  "properties": {
    "iso:country":"AU",
    "sg:address":"23- 25 Egan St",
    "sg:city":"Newtown",
    "sg:classifiers":[
        {
            "category":"Retail",
            "subcategory":"Auto Repair",
            "type":"Services"
        }
    ],
    "sg:phone":"+61 2 9557 2672",
    "sg:postcode":"2042",
    "sg:province":"NSW",
    "sg:tags":[
        "beater",
        "painter",
        "panel"
    ],
    "wof:name":"Joe Darman Smash Repairs",
    "wof:placetype":"venue"
},
  "geometry": {"coordinates":[151.181808,-33.893562],"type":"Point"}
}