{
  "type": "Feature",
  "properties": {
    "iso:country":"AU",
    "sg:address":"Harbour Town Wellington St",
    "sg:city":"Perth",
    "sg:classifiers":[
        {
            "category":"Shopping",
            "subcategory":"Clothing, Apparel, & Fashions",
            "type":"Retail Goods"
        }
    ],
    "sg:phone":"+61 8 9324 3244",
    "sg:postcode":"6000",
    "sg:province":"WA",
    "sg:tags":[
        "maternity",
        "wear"
    ],
    "wof:name":"Maternity Girl",
    "wof:placetype":"venue"
},
  "geometry": {"coordinates":[115.85492706300001,-31.9502372742],"type":"Point"}
}