{
  "type": "Feature",
  "properties": {
    "addr:full":"23 Roebig St Aspley QLD 4034",
    "addr:housenumber":"23",
    "addr:postcode":"4034",
    "addr:street":"Roebig St",
    "iso:country":"AU",
    "sg:address":"23 Roebig St",
    "sg:city":"Aspley",
    "sg:classifiers":[
        {
            "category":"Real Estate",
            "subcategory":"Real Estate Services",
            "type":"Services"
        }
    ],
    "sg:phone":"+61 7 3263 9988",
    "sg:postcode":"4034",
    "sg:province":"QLD",
    "sg:tags":[
        "consultant",
        "property"
    ],
    "wof:name":"Jap Kenny Properties Pty Ltd",
    "wof:placetype":"venue"
},
  "geometry": {"coordinates":[153.00367700000001,-27.373413],"type":"Point"}
}