{
  "type": "Feature",
  "properties": {
    "addr:full":"Murton St Broken Hill NSW 2880",
    "addr:postcode":"2880",
    "addr:street":"Murton St",
    "iso:country":"AU",
    "sg:address":"Murton St",
    "sg:city":"Broken Hill",
    "sg:classifiers":[
        {
            "category":"Education",
            "subcategory":"School",
            "type":"Public Place"
        }
    ],
    "sg:phone":"+61 8 8088 1055",
    "sg:postcode":"2880",
    "sg:province":"NSW",
    "sg:tags":[
        "state",
        "-",
        "nsw"
    ],
    "wof:name":"Willyama High School",
    "wof:placetype":"venue"
},
  "geometry": {"coordinates":[141.47697448700001,-31.9445953369],"type":"Point"}
}