{
  "type": "Feature",
  "properties": {
    "addr:full":"Cnr Sandgate Rd & Railway Pde Clayfield QLD 4011",
    "addr:postcode":"4011",
    "addr:street":"Cnr Sandgate Rd & Railway Pde",
    "iso:country":"AU",
    "sg:address":"Cnr Sandgate Rd & Railway Pde",
    "sg:city":"Clayfield",
    "sg:classifiers":[
        {
            "category":"Fast Food",
            "type":"Food & Drink"
        }
    ],
    "sg:phone":"+61 7 3256 2299",
    "sg:postcode":"4011",
    "sg:province":"QLD",
    "sg:tags":[
        "away",
        "take"
    ],
    "wof:name":"Tomato Brothers Cafe Ristorante",
    "wof:placetype":"venue"
},
  "geometry": {"coordinates":[153.05898999999999,-27.412111],"type":"Point"}
}