{
  "type": "Feature",
  "properties": {
    "addr:full":"21/ 70-72 Captain Cook Drv Caringbah NSW 2229",
    "addr:housenumber":"21 / 70-72",
    "addr:postcode":"2229",
    "addr:street":"Captain Cook Drv",
    "iso:country":"AU",
    "sg:address":"21/ 70-72 Captain Cook Drv",
    "sg:city":"Caringbah",
    "sg:classifiers":[
        {
            "category":"Manufacturing",
            "subcategory":"Food",
            "type":"Manufacturing & Wholesale Goods"
        }
    ],
    "sg:phone":"+61 2 9544 0283",
    "sg:postcode":"2229",
    "sg:province":"NSW",
    "sg:tags":[
        "function",
        "catering"
    ],
    "wof:name":"Feast Caterers",
    "wof:placetype":"venue"
},
  "geometry": {"coordinates":[151.123703003,-34.0326194763],"type":"Point"}
}