{
  "type": "Feature",
  "properties": {
    "iso:country":"AU",
    "sg:address":"4 Lookes Ave",
    "sg:city":"Balmain East",
    "sg:classifiers":[
        {
            "category":"Professional",
            "subcategory":"Management & Consulting",
            "type":"Services"
        }
    ],
    "sg:phone":"+61 2 9810 6701",
    "sg:postcode":"2041",
    "sg:province":"NSW",
    "sg:tags":[
        "consultant"
    ],
    "wof:name":"Mayo Group Pty Ltd The",
    "wof:placetype":"venue"
},
  "geometry": {"coordinates":[151.19358800000001,-33.85667],"type":"Point"}
}