{
  "type": "Feature",
  "properties": {
    "addr:full":"175 McCullough St Sunnybank QLD 4109",
    "addr:housenumber":"175",
    "addr:postcode":"4109",
    "addr:street":"Mccullough St",
    "iso:country":"AU",
    "sg:address":"175 McCullough St",
    "sg:city":"Sunnybank",
    "sg:classifiers":[
        {
            "category":"Arts & Performance",
            "subcategory":"Music",
            "type":"Entertainment"
        }
    ],
    "sg:phone":"+61 419 781 032",
    "sg:postcode":"4109",
    "sg:province":"QLD",
    "sg:tags":[
        "mobile",
        "jockey",
        "disc"
    ],
    "wof:name":"Daniel Bardell",
    "wof:placetype":"venue"
},
  "geometry": {"coordinates":[153.05609130900001,-27.5709018707],"type":"Point"}
}