{
  "type": "Feature",
  "properties": {
    "addr:full":"21 Ontario Ave St Clair NSW 2759",
    "addr:housenumber":"21",
    "addr:postcode":"2759",
    "addr:street":"Ontario Ave St",
    "iso:country":"AU",
    "sg:address":"21 Ontario Ave",
    "sg:city":"St Clair",
    "sg:classifiers":[
        {
            "category":"Government",
            "subcategory":"Post Office",
            "type":"Public Place"
        }
    ],
    "sg:phone":"+61 2 9834 5042",
    "sg:postcode":"2759",
    "sg:province":"NSW",
    "sg:tags":[
        "box",
        "mail"
    ],
    "wof:name":"Discount Clotheslines",
    "wof:placetype":"venue"
},
  "geometry": {"coordinates":[150.773727417,-33.7999801636],"type":"Point"}
}