{
  "type": "Feature",
  "properties": {
    "addr:full":"Gardeners Rd Rosebery NSW 2018",
    "addr:postcode":"2018",
    "addr:street":"Gardeners Rd",
    "iso:country":"AU",
    "sg:address":"Gardeners Rd",
    "sg:city":"Rosebery",
    "sg:classifiers":[
        {
            "category":"Education",
            "subcategory":"School",
            "type":"Public Place"
        }
    ],
    "sg:phone":"+61 2 9667 2193",
    "sg:postcode":"2018",
    "sg:province":"NSW",
    "sg:tags":[
        "state",
        "-",
        "nsw"
    ],
    "wof:name":"Gardeners Road Primary School",
    "wof:placetype":"venue"
},
  "geometry": {"coordinates":[151.201004028,-33.9220924377],"type":"Point"}
}