{
  "type": "Feature",
  "properties": {
    "iso:country":"AU",
    "sg:address":"10 Quail Crt",
    "sg:city":"Traralgon",
    "sg:classifiers":[
        {
            "category":"Utilities",
            "subcategory":"Electric",
            "type":"Services"
        }
    ],
    "sg:phone":"+61 3 5174 3541",
    "sg:postcode":"3844",
    "sg:province":"VIC",
    "sg:tags":[
        "electrical",
        "contractor"
    ],
    "wof:name":"John Rhimes Electrical",
    "wof:placetype":"venue"
},
  "geometry": {"coordinates":[146.50793457,-38.1951026917],"type":"Point"}
}