{
  "type": "Feature",
  "properties": {
    "addr:full":"Maxwell St Penrith South NSW 2750",
    "addr:postcode":"2750",
    "addr:street":"Maxwell St",
    "iso:country":"AU",
    "sg:address":"Maxwell St",
    "sg:city":"Penrith South",
    "sg:classifiers":[
        {
            "category":"Fast Food",
            "type":"Food & Drink"
        }
    ],
    "sg:phone":"+61 2 4732 3846",
    "sg:postcode":"2750",
    "sg:province":"NSW",
    "sg:tags":[
        "away",
        "take"
    ],
    "wof:name":"South Lands Pizza Pasta & Ribs",
    "wof:placetype":"venue"
},
  "geometry": {"coordinates":[150.68772888199999,-33.7720794678],"type":"Point"}
}