{
  "type": "Feature",
  "properties": {
    "addr:full":"Tasman Hse, Marcus Clarke St Canberra City ACT 2601",
    "addr:postcode":"2601",
    "addr:street":"Marcus Clarke St",
    "iso:country":"AU",
    "sg:address":"Tasman Hse, Marcus Clarke St",
    "sg:city":"Canberra City",
    "sg:classifiers":[
        {
            "category":"Fast Food",
            "type":"Food & Drink"
        }
    ],
    "sg:phone":"+61 2 6249 6784",
    "sg:postcode":"2601",
    "sg:province":"ACT",
    "sg:tags":[
        "away",
        "take"
    ],
    "wof:name":"Shalimar Indian Restaurant",
    "wof:placetype":"venue"
},
  "geometry": {"coordinates":[149.126052856,-35.2788696289],"type":"Point"}
}