{
  "type": "Feature",
  "properties": {
    "addr:full":"160 Stawell St Burnley VIC 3121",
    "addr:housenumber":"160",
    "addr:postcode":"3121",
    "addr:street":"Stawell St",
    "iso:country":"AU",
    "sg:address":"160 Stawell St",
    "sg:city":"Burnley",
    "sg:classifiers":[
        {
            "category":"Building & Trades",
            "subcategory":"Landscaping Services",
            "type":"Services"
        }
    ],
    "sg:phone":"+61 3 9428 5420",
    "sg:postcode":"3121",
    "sg:province":"VIC",
    "sg:tags":[
        "stump",
        "tree",
        "felling",
        "removal"
    ],
    "wof:name":"A All About Trees",
    "wof:placetype":"venue"
},
  "geometry": {"coordinates":[145.00895690900001,-37.8290176392],"type":"Point"}
}