{
  "type": "Feature",
  "properties": {
    "addr:full":"Unit 4 1 Male St Brighton VIC 3186",
    "addr:housenumber":"1",
    "addr:postcode":"3186",
    "addr:street":"Male St",
    "iso:country":"AU",
    "sg:address":"Unit 4 1 Male St",
    "sg:city":"Brighton",
    "sg:classifiers":[
        {
            "category":"Professional",
            "subcategory":"Accounting & Tax Preparation",
            "type":"Services"
        }
    ],
    "sg:phone":"+61 3 9592 3958",
    "sg:postcode":"3186",
    "sg:province":"VIC",
    "sg:tags":[
        "accountant",
        "auditor"
    ],
    "wof:name":"Wormington Peter",
    "wof:placetype":"venue"
},
  "geometry": {"coordinates":[144.99571227999999,-37.9164543152],"type":"Point"}
}