{
  "type": "Feature",
  "properties": {
    "addr:full":"Coopers Ave Leabrook SA 5068",
    "addr:postcode":"5068",
    "addr:street":"Coopers Ave",
    "iso:country":"AU",
    "sg:address":"Coopers Ave",
    "sg:city":"Leabrook",
    "sg:classifiers":[
        {
            "category":"Social Services",
            "subcategory":"Retirement Home",
            "type":"Services"
        }
    ],
    "sg:phone":"+61 8 8364 4844",
    "sg:postcode":"5068",
    "sg:province":"SA",
    "sg:tags":[
        "village"
    ],
    "wof:name":"On Statenborough",
    "wof:placetype":"venue"
},
  "geometry": {"coordinates":[138.658859253,-34.9260292053],"type":"Point"}
}