{
  "type": "Feature",
  "properties": {
    "addr:full":"PO Box 301 Narrabeen NSW 2101",
    "addr:postcode":"2101",
    "iso:country":"AU",
    "sg:address":"PO Box 301",
    "sg:city":"Narrabeen",
    "sg:classifiers":[
        {
            "category":"Building & Trades",
            "subcategory":"Plumbing",
            "type":"Services"
        }
    ],
    "sg:phone":"+61 1300 965 343",
    "sg:postcode":"2101",
    "sg:province":"NSW",
    "sg:tags":[
        "plumber",
        "gasfitters"
    ],
    "wof:name":"Wolfie's Plumbing & Electrical Services",
    "wof:placetype":"venue"
},
  "geometry": {"coordinates":[151.298416,-33.720211],"type":"Point"}
}