{
  "type": "Feature",
  "properties": {
    "addr:full":"2 Mews Rd Fremantle WA 6160",
    "addr:housenumber":"2",
    "addr:postcode":"6160",
    "addr:street":"Mews Rd",
    "iso:country":"AU",
    "sg:address":"2 Mews Rd",
    "sg:city":"Fremantle",
    "sg:classifiers":[
        {
            "category":"Real Estate",
            "subcategory":"Developer",
            "type":"Services"
        }
    ],
    "sg:phone":"+61 8 9335 6674",
    "sg:postcode":"6160",
    "sg:province":"WA",
    "sg:tags":[
        "development"
    ],
    "wof:name":"CCI Group",
    "wof:placetype":"venue"
},
  "geometry": {"coordinates":[115.747818,-32.060242],"type":"Point"}
}