{
  "type": "Feature",
  "properties": {
    "iso:country":"AU",
    "sg:address":"16a Florence Rd",
    "sg:city":"Surrey Hills",
    "sg:classifiers":[
        {
            "category":"Government",
            "subcategory":"Customs House",
            "type":"Public Place"
        }
    ],
    "sg:phone":"+61 3 9899 1256",
    "sg:postcode":"3127",
    "sg:province":"VIC",
    "sg:tags":[
        "title",
        "management",
        "stratum"
    ],
    "wof:name":"Sterling Management Services",
    "wof:placetype":"venue"
},
  "geometry": {"coordinates":[145.102386475,-37.8279457092],"type":"Point"}
}