{
  "type": "Feature",
  "properties": {
    "addr:full":"Back Springfield Rd Bundaberg QLD 4670",
    "addr:postcode":"4670",
    "addr:street":"Springfield Rd",
    "iso:country":"AU",
    "sg:address":"Back Springfield Rd",
    "sg:city":"Bundaberg",
    "sg:classifiers":[
        {
            "category":"Commercial Area",
            "type":"Public Place"
        }
    ],
    "sg:phone":"+61 7 4155 6264",
    "sg:postcode":"4670",
    "sg:province":"QLD",
    "sg:tags":[
        "heavy",
        "carrier"
    ],
    "wof:name":"Bonato L & K",
    "wof:placetype":"venue"
},
  "geometry": {"coordinates":[152.43324279800001,-24.8864898682],"type":"Point"}
}