{
  "type": "Feature",
  "properties": {
    "iso:country":"AU",
    "sg:address":"282 High St",
    "sg:city":"Northcote",
    "sg:classifiers":[
        {
            "category":"Health Services",
            "subcategory":"Doctor",
            "type":"Services"
        }
    ],
    "sg:phone":"+61 3 9489 3852",
    "sg:postcode":"3070",
    "sg:province":"VIC",
    "sg:tags":[
        "medical",
        "practitioner"
    ],
    "wof:name":"Guarrella G",
    "wof:placetype":"venue"
},
  "geometry": {"coordinates":[144.998657,-37.771919],"type":"Point"}
}