{
  "type": "Feature",
  "properties": {
    "iso:country":"AU",
    "sg:address":"Adelaide Markets Shed J, J4 Burma Rd",
    "sg:city":"Pooraka",
    "sg:classifiers":[
        {
            "category":"Farming",
            "subcategory":"Fish & Marine Products",
            "type":"Manufacturing & Wholesale Goods"
        }
    ],
    "sg:phone":"+61 8 8260 4500",
    "sg:postcode":"5095",
    "sg:province":"SA",
    "sg:tags":[
        "organic"
    ],
    "wof:name":"Eco- Farms Pty Ltd",
    "wof:placetype":"venue"
},
  "geometry": {"coordinates":[138.61016845699999,-34.8336982727],"type":"Point"}
}