{
  "type": "Feature",
  "properties": {
    "iso:country":"AU",
    "sg:address":"44 Lascelles Ave",
    "sg:city":"Warradale",
    "sg:classifiers":[
        {
            "category":"Social Services",
            "subcategory":"Job Training",
            "type":"Services"
        }
    ],
    "sg:phone":"+61 8 8377 0660",
    "sg:postcode":"5046",
    "sg:province":"SA",
    "sg:tags":[
        "sport"
    ],
    "wof:name":"Balance For Health Personal Training",
    "wof:placetype":"venue"
},
  "geometry": {"coordinates":[138.532639,-35.014328],"type":"Point"}
}