{
  "type": "Feature",
  "properties": {
    "addr:full":"Shp7/ 25 South Steyne St Manly NSW 2095",
    "addr:housenumber":"25",
    "addr:postcode":"2095",
    "addr:street":"South Steyne St",
    "iso:country":"AU",
    "sg:address":"Shp7/ 25 South Steyne St",
    "sg:city":"Manly",
    "sg:classifiers":[
        {
            "category":"Food & Beverages",
            "subcategory":"Groceries & Convenience Stores",
            "type":"Retail Goods"
        }
    ],
    "sg:phone":"+61 2 9977 0041",
    "sg:postcode":"2095",
    "sg:province":"NSW",
    "wof:name":"Beachside Convenience",
    "wof:placetype":"venue"
},
  "geometry": {"coordinates":[151.28965759299999,-33.7995262146],"type":"Point"}
}