{
  "type": "Feature",
  "properties": {
    "addr:full":"18 Herald Ave Willetton WA 6155",
    "addr:housenumber":"18",
    "addr:postcode":"6155",
    "addr:street":"Herald Ave",
    "iso:country":"AU",
    "sg:address":"18 Herald Ave",
    "sg:city":"Willetton",
    "sg:classifiers":[
        {
            "category":"Government",
            "subcategory":"Customs House",
            "type":"Public Place"
        }
    ],
    "sg:phone":"+61 8 9457 6963",
    "sg:postcode":"6155",
    "sg:province":"WA",
    "sg:tags":[
        "title",
        "management",
        "stratum"
    ],
    "wof:name":"Independent Strata Services",
    "wof:placetype":"venue"
},
  "geometry": {"coordinates":[115.888451,-32.040482],"type":"Point"}
}