{
  "type": "Feature",
  "properties": {
    "addr:full":"11 Fifth St Wingfield SA 5013",
    "addr:housenumber":"11",
    "addr:postcode":"5013",
    "addr:street":"Fifth St",
    "iso:country":"AU",
    "sg:address":"11 Fifth St",
    "sg:city":"Wingfield",
    "sg:classifiers":[
        {
            "category":"Retail",
            "subcategory":"Auto Repair",
            "type":"Services"
        }
    ],
    "sg:phone":"+61 8 8347 4277",
    "sg:postcode":"5013",
    "sg:province":"SA",
    "sg:tags":[
        "repairer",
        "motor",
        "engineer"
    ],
    "wof:name":"A & J Motor Repairs",
    "wof:placetype":"venue"
},
  "geometry": {"coordinates":[138.547927856,-34.8473510742],"type":"Point"}
}