{
  "type": "Feature",
  "properties": {
    "addr:full":"26 Shirley St St Albans VIC 3021",
    "addr:housenumber":"26",
    "addr:postcode":"3021",
    "addr:street":"Shirley St",
    "iso:country":"AU",
    "sg:address":"26 Shirley St",
    "sg:city":"St Albans",
    "sg:classifiers":[
        {
            "category":"Retail",
            "subcategory":"Auto Repair",
            "type":"Services"
        }
    ],
    "sg:phone":"+61 3 9366 5333",
    "sg:postcode":"3021",
    "sg:province":"VIC",
    "sg:tags":[
        "repairer",
        "motor",
        "engineer"
    ],
    "wof:name":"A-One Performance Centre",
    "wof:placetype":"venue"
},
  "geometry": {"coordinates":[144.79029800000001,-37.736588],"type":"Point"}
}