{
  "type": "Feature",
  "properties": {
    "addr:full":"18 Realm St Arncliffe NSW 2205",
    "addr:housenumber":"18",
    "addr:postcode":"2205",
    "addr:street":"Realm St",
    "iso:country":"AU",
    "sg:address":"18 Realm St",
    "sg:city":"Arncliffe",
    "sg:classifiers":[
        {
            "category":"Professional",
            "subcategory":"Art Services",
            "type":"Services"
        }
    ],
    "sg:phone":"+61 2 9567 6511",
    "sg:postcode":"2205",
    "sg:province":"NSW",
    "sg:tags":[
        "graphic",
        "designer"
    ],
    "wof:name":"Marksman Design Group The",
    "wof:placetype":"venue"
},
  "geometry": {"coordinates":[151.13961800000001,-33.933331],"type":"Point"}
}