{
  "type": "Feature",
  "properties": {
    "iso:country":"AU",
    "sg:address":"28 Rigby St",
    "sg:city":"St Leonards",
    "sg:classifiers":[
        {
            "category":"Building & Trades",
            "subcategory":"Plumbing",
            "type":"Services"
        }
    ],
    "sg:phone":"+61 408 554 043",
    "sg:postcode":"3223",
    "sg:province":"VIC",
    "sg:tags":[
        "plumber",
        "gasfitters"
    ],
    "wof:name":"Bellarine Plumbing Services",
    "wof:placetype":"venue"
},
  "geometry": {"coordinates":[144.70953399999999,-38.173225],"type":"Point"}
}