{
  "type": "Feature",
  "properties": {
    "addr:full":"Queen St Goulburn NSW 2580",
    "addr:postcode":"2580",
    "addr:street":"Queen St",
    "iso:country":"AU",
    "sg:address":"Queen St",
    "sg:city":"Goulburn",
    "sg:classifiers":[
        {
            "category":"Fast Food",
            "type":"Food & Drink"
        }
    ],
    "sg:phone":"+61 2 4821 3153",
    "sg:postcode":"2580",
    "sg:province":"NSW",
    "sg:tags":[
        "away",
        "take"
    ],
    "wof:name":"Isys Takeaway",
    "wof:placetype":"venue"
},
  "geometry": {"coordinates":[149.73425293,-34.7301139832],"type":"Point"}
}