{
  "type": "Feature",
  "properties": {
    "addr:full":"2/ 36 Kularoo Drv Forster NSW 2428",
    "addr:housenumber":"/ 36",
    "addr:postcode":"2428",
    "addr:street":"Kularoo Drv",
    "iso:country":"AU",
    "sg:address":"2/ 36 Kularoo Drv",
    "sg:city":"Forster",
    "sg:classifiers":[
        {
            "category":"Retail",
            "subcategory":"Auto Repair",
            "type":"Services"
        }
    ],
    "sg:phone":"+61 2 6554 8625",
    "sg:postcode":"2428",
    "sg:province":"NSW",
    "sg:tags":[
        "repairer",
        "motor",
        "engineer"
    ],
    "wof:name":"Joe's Auto Service Centre",
    "wof:placetype":"venue"
},
  "geometry": {"coordinates":[152.51805100000001,-32.197163],"type":"Point"}
}