{
  "type": "Feature",
  "properties": {
    "iso:country":"AU",
    "sg:address":"PO Box 2890",
    "sg:city":"Geraldton",
    "sg:classifiers":[
        {
            "category":"Cafe",
            "type":"Food & Drink"
        }
    ],
    "sg:phone":"+61 8 9921 1443",
    "sg:postcode":"6530",
    "sg:province":"WA",
    "wof:name":"Hard Ware Cafe",
    "wof:placetype":"venue"
},
  "geometry": {"coordinates":[114.64060974100001,-28.7494506836],"type":"Point"}
}