{
  "type": "Feature",
  "properties": {
    "addr:full":"Cave Hill Garden Estate, Factory 17 Beresford Rd Lilydale VIC 3140",
    "addr:housenumber":"17",
    "addr:postcode":"3140",
    "addr:street":"Beresford Rd",
    "iso:country":"AU",
    "sg:address":"Cave Hill Garden Estate, Factory 17 Beresford Rd",
    "sg:city":"Lilydale",
    "sg:classifiers":[
        {
            "category":"Professional",
            "subcategory":"Engineering",
            "type":"Services"
        }
    ],
    "sg:phone":"+61 3 9739 7322",
    "sg:postcode":"3140",
    "sg:province":"VIC",
    "sg:tags":[
        "engineer"
    ],
    "wof:name":"Lilydale Engineering Pty Ltd",
    "wof:placetype":"venue"
},
  "geometry": {"coordinates":[145.33859252900001,-37.7497406006],"type":"Point"}
}