{
  "type": "Feature",
  "properties": {
    "iso:country":"AU",
    "sg:address":"28 Allen St",
    "sg:city":"Caloundra",
    "sg:classifiers":[
        {
            "category":"Building & Trades",
            "subcategory":"Construction",
            "type":"Services"
        }
    ],
    "sg:phone":"+61 407 957 617",
    "sg:postcode":"4551",
    "sg:province":"QLD",
    "sg:tags":[
        "rendering",
        "cement"
    ],
    "wof:name":"Emblem Enterprises Solid Plastering",
    "wof:placetype":"venue"
},
  "geometry": {"coordinates":[153.132369995,-26.7920665741],"type":"Point"}
}