{
  "type": "Feature",
  "properties": {
    "iso:country":"AU",
    "sg:address":"124 Norton St",
    "sg:city":"Leichhardt",
    "sg:classifiers":[
        {
            "category":"Health Services",
            "subcategory":"Optometrist",
            "type":"Services"
        }
    ],
    "sg:phone":"+61 2 9550 0512",
    "sg:postcode":"2040",
    "sg:province":"NSW",
    "wof:name":"Pepper Lee J",
    "wof:placetype":"venue"
},
  "geometry": {"coordinates":[151.156876,-33.883633],"type":"Point"}
}