{
  "type": "Feature",
  "properties": {
    "addr:full":"6 Arabin St Keilor VIC 3036",
    "addr:housenumber":"6",
    "addr:postcode":"3036",
    "addr:street":"Arabin St",
    "iso:country":"AU",
    "sg:address":"6 Arabin St",
    "sg:city":"Keilor",
    "sg:classifiers":[
        {
            "category":"Building & Trades",
            "subcategory":"Cleaning & Sanitation",
            "type":"Services"
        }
    ],
    "sg:phone":"+61 3 9331 6336",
    "sg:postcode":"3036",
    "sg:province":"VIC",
    "sg:tags":[
        "cleaner",
        "repairer",
        "roof"
    ],
    "wof:name":"Allsub Plumbing & Maintenance",
    "wof:placetype":"venue"
},
  "geometry": {"coordinates":[144.83448799999999,-37.720806],"type":"Point"}
}