{
  "type": "Feature",
  "properties": {
    "addr:full":"660a South Rd Moorabbin VIC 3189",
    "addr:housenumber":"660a",
    "addr:postcode":"3189",
    "addr:street":"South Rd",
    "iso:country":"AU",
    "sg:address":"660a South Rd",
    "sg:city":"Moorabbin",
    "sg:classifiers":[
        {
            "category":"Personal",
            "subcategory":"Skin Care",
            "type":"Services"
        }
    ],
    "sg:phone":"+61 3 9555 1533",
    "sg:postcode":"3189",
    "sg:province":"VIC",
    "sg:tags":[
        "hair",
        "product"
    ],
    "wof:name":"M & U Imports Pty Ltd",
    "wof:placetype":"venue"
},
  "geometry": {"coordinates":[145.07183837900001,-37.9378318787],"type":"Point"}
}