{
  "type": "Feature",
  "properties": {
    "addr:full":"Shop 7, 285 Henley Beach Rd Brooklyn Park SA 5032",
    "addr:housenumber":"shop 7 285",
    "addr:postcode":"5032",
    "addr:street":"Henley Beach Rd",
    "iso:country":"AU",
    "sg:address":"Shop 7, 285 Henley Beach Rd",
    "sg:city":"Brooklyn Park",
    "sg:classifiers":[
        {
            "category":"Food & Beverages",
            "subcategory":"Bakery",
            "type":"Retail Goods"
        }
    ],
    "sg:phone":"+61 8 8234 9666",
    "sg:postcode":"5032",
    "sg:province":"SA",
    "sg:tags":[
        "baker"
    ],
    "wof:name":"Gumleaf Bakery",
    "wof:placetype":"venue"
},
  "geometry": {"coordinates":[138.54917907699999,-34.9248733521],"type":"Point"}
}