{
  "type": "Feature",
  "properties": {
    "addr:full":"605 Waterdale Rd Heidelberg West VIC 3081",
    "addr:housenumber":"605",
    "addr:postcode":"3081",
    "addr:street":"Waterdale Rd",
    "iso:country":"AU",
    "sg:address":"605 Waterdale Rd",
    "sg:city":"Heidelberg West",
    "sg:classifiers":[
        {
            "category":"Structure",
            "subcategory":"Building",
            "type":"Public Place"
        }
    ],
    "sg:phone":"+61 3 9457 3633",
    "sg:postcode":"3081",
    "sg:province":"VIC",
    "sg:tags":[
        "sail",
        "shade"
    ],
    "wof:name":"A. Intouch Shade Sails",
    "wof:placetype":"venue"
},
  "geometry": {"coordinates":[145.049026489,-37.7341842651],"type":"Point"}
}