{
  "type": "Feature",
  "properties": {
    "addr:full":"48- 86 Powell St Bendigo VIC 3550",
    "addr:housenumber":"86",
    "addr:postcode":"3550",
    "addr:street":"Powell St",
    "iso:country":"AU",
    "sg:address":"48- 86 Powell St",
    "sg:city":"Bendigo",
    "sg:classifiers":[
        {
            "category":"Manufacturing",
            "subcategory":"Rubber & Plastics",
            "type":"Manufacturing & Wholesale Goods"
        }
    ],
    "sg:phone":"+61 3 5442 1066",
    "sg:postcode":"3550",
    "sg:province":"VIC",
    "sg:tags":[
        "wholesaler",
        "product",
        "mfrs"
    ],
    "wof:name":"Empire Rubber",
    "wof:placetype":"venue"
},
  "geometry": {"coordinates":[144.30572509800001,-36.7417984009],"type":"Point"}
}