{
  "type": "Feature",
  "properties": {
    "addr:full":"PO Box 225 Red Hill South VIC 3937",
    "addr:postcode":"3937",
    "iso:country":"AU",
    "sg:address":"PO Box 225",
    "sg:city":"Red Hill South",
    "sg:classifiers":[
        {
            "category":"Utilities",
            "type":"Services"
        }
    ],
    "sg:phone":"+61 3 5983 1765",
    "sg:postcode":"3937",
    "sg:province":"VIC",
    "sg:tags":[
        "refrigeration",
        "industrial",
        "commercial",
        "retail"
    ],
    "wof:name":"Red Hill Refrigeration",
    "wof:placetype":"venue"
},
  "geometry": {"coordinates":[145.043655395,-38.3980789185],"type":"Point"}
}