{
  "type": "Feature",
  "properties": {
    "addr:full":"4 Park Pl Caloundra QLD 4551",
    "addr:housenumber":"4",
    "addr:postcode":"4551",
    "addr:street":"Park Pl",
    "iso:country":"AU",
    "sg:address":"4 Park Pl",
    "sg:city":"Caloundra",
    "sg:classifiers":[
        {
            "category":"Retail",
            "subcategory":"Auto Rental",
            "type":"Services"
        }
    ],
    "sg:phone":"+61 7 5491 2444",
    "sg:postcode":"4551",
    "sg:province":"QLD",
    "sg:tags":[
        "car",
        "hire",
        "minibus"
    ],
    "wof:name":"Trusty Car Rental",
    "wof:placetype":"venue"
},
  "geometry": {"coordinates":[153.123443603,-26.8055267334],"type":"Point"}
}