{
  "type": "Feature",
  "properties": {
    "iso:country":"AU",
    "sg:address":"4/ 112 Egerton St",
    "sg:city":"Emerald",
    "sg:classifiers":[
        {
            "category":"Health Services",
            "subcategory":"Dentist",
            "type":"Services"
        }
    ],
    "sg:phone":"+61 428 585 408",
    "sg:postcode":"4720",
    "sg:province":"QLD",
    "sg:tags":[
        "dental",
        "prosthetist"
    ],
    "wof:name":"Rick Lawson",
    "wof:placetype":"venue"
},
  "geometry": {"coordinates":[148.158401,-23.524153],"type":"Point"}
}