{
  "type": "Feature",
  "properties": {
    "addr:full":"Doncaster Rd Doncaster VIC 3108",
    "addr:postcode":"3108",
    "addr:street":"Doncaster Rd",
    "iso:country":"AU",
    "sg:address":"Doncaster Rd",
    "sg:city":"Doncaster",
    "sg:classifiers":[
        {
            "category":"Professional",
            "subcategory":"Employment Agencies",
            "type":"Services"
        }
    ],
    "sg:phone":"+61 412 162 797",
    "sg:postcode":"3108",
    "sg:province":"VIC",
    "sg:tags":[
        "provider",
        "internet"
    ],
    "wof:name":"Skybiz",
    "wof:placetype":"venue"
},
  "geometry": {"coordinates":[145.12384033199999,-37.7874450684],"type":"Point"}
}