{
  "type": "Feature",
  "properties": {
    "iso:country":"AU",
    "sg:address":"Lawsons Rd",
    "sg:city":"Macedon",
    "sg:classifiers":[
        {
            "category":"Education",
            "subcategory":"School",
            "type":"Public Place"
        }
    ],
    "sg:phone":"+61 3 5426 1751",
    "sg:postcode":"3440",
    "sg:province":"VIC",
    "sg:tags":[
        "co-educational"
    ],
    "wof:name":"Macedon Grammar School",
    "wof:placetype":"venue"
},
  "geometry": {"coordinates":[144.554855347,-37.4477157593],"type":"Point"}
}