{
  "type": "Feature",
  "properties": {
    "addr:full":"1072 South Rd Edwardstown SA 5039",
    "addr:housenumber":"1072",
    "addr:postcode":"5039",
    "addr:street":"South Rd",
    "iso:country":"AU",
    "sg:address":"1072 South Rd",
    "sg:city":"Edwardstown",
    "sg:classifiers":[
        {
            "category":"Military Area",
            "subcategory":"Army Base",
            "type":"Public Place"
        }
    ],
    "sg:phone":"+61 8 8277 4244",
    "sg:postcode":"5039",
    "sg:province":"SA",
    "sg:tags":[
        "wholesaler",
        "clutch",
        "brake",
        "mfrs",
        "equipment"
    ],
    "wof:name":"Hawk Brake",
    "wof:placetype":"venue"
},
  "geometry": {"coordinates":[138.574386597,-34.9890365601],"type":"Point"}
}