{
  "type": "Feature",
  "properties": {
    "iso:country":"AU",
    "sg:address":"46-48 Prince St",
    "sg:city":"Grafton",
    "sg:classifiers":[
        {
            "category":"Health Services",
            "subcategory":"Health Practitioner",
            "type":"Services"
        }
    ],
    "sg:phone":"+61 2 6643 5035",
    "sg:postcode":"2460",
    "sg:province":"NSW",
    "sg:tags":[
        "naturopath"
    ],
    "wof:name":"Clinic Of Complementary Natural Therapies",
    "wof:placetype":"venue"
},
  "geometry": {"coordinates":[152.933883667,-29.6907539368],"type":"Point"}
}