{
  "type": "Feature",
  "properties": {
    "addr:full":"79 Drummond Rd Shepparton VIC 3630",
    "addr:housenumber":"79",
    "addr:postcode":"3630",
    "addr:street":"Drummond Rd",
    "iso:country":"AU",
    "sg:address":"79 Drummond Rd",
    "sg:city":"Shepparton",
    "sg:classifiers":[
        {
            "category":"Home & Garden",
            "subcategory":"Building Materials",
            "type":"Retail Goods"
        }
    ],
    "sg:phone":"+61 3 5831 3377",
    "sg:postcode":"3630",
    "sg:province":"VIC",
    "sg:tags":[
        "supply"
    ],
    "wof:name":"Samo's Roof Trusses",
    "wof:placetype":"venue"
},
  "geometry": {"coordinates":[145.42315673799999,-36.3738174438],"type":"Point"}
}