{
  "type": "Feature",
  "properties": {
    "addr:full":"Shed 4/ 591 Grand Junction Rd Gepps Cross SA 5094",
    "addr:housenumber":"4 / 591",
    "addr:postcode":"5094",
    "addr:street":"Grand Junction Rd",
    "iso:country":"AU",
    "sg:address":"Shed 4/ 591 Grand Junction Rd",
    "sg:city":"Gepps Cross",
    "sg:classifiers":[
        {
            "category":"Commercial Area",
            "type":"Public Place"
        }
    ],
    "sg:phone":"+61 8 8625 2774",
    "sg:postcode":"5094",
    "sg:province":"SA",
    "sg:tags":[
        "heavy",
        "carrier"
    ],
    "wof:name":"Genrich Transport Pty Ltd",
    "wof:placetype":"venue"
},
  "geometry": {"coordinates":[138.59600830100001,-34.8481445312],"type":"Point"}
}