{
  "type": "Feature",
  "properties": {
    "addr:full":"Cnr Belfast St & Dallas Drv Broadmeadows VIC 3047",
    "addr:postcode":"3047",
    "addr:street":"Cnr Belfast St & Dallas Drv",
    "iso:country":"AU",
    "sg:address":"Cnr Belfast St & Dallas Drv",
    "sg:city":"Broadmeadows",
    "sg:classifiers":[
        {
            "category":"Farming",
            "subcategory":"Nursery",
            "type":"Manufacturing & Wholesale Goods"
        }
    ],
    "sg:phone":"+61 3 9309 5111",
    "sg:postcode":"3047",
    "sg:province":"VIC",
    "wof:name":"Brite Plants",
    "wof:placetype":"venue"
},
  "geometry": {"coordinates":[144.930343628,-37.6787147522],"type":"Point"}
}