{
  "type": "Feature",
  "properties": {
    "iso:country":"AU",
    "sg:address":"75 Lyons Rd",
    "sg:city":"Drummoyne",
    "sg:classifiers":[
        {
            "category":"Personal",
            "subcategory":"Beauty Salon",
            "type":"Services"
        }
    ],
    "sg:phone":"+61 2 9719 2299",
    "sg:postcode":"2047",
    "sg:province":"NSW",
    "sg:tags":[
        "hairdresser"
    ],
    "wof:name":"Senso Hair & Skin",
    "wof:placetype":"venue"
},
  "geometry": {"coordinates":[151.15173300000001,-33.853073],"type":"Point"}
}