{
  "type": "Feature",
  "properties": {
    "iso:country":"AU",
    "sg:address":"Westfield Shopng Cntr Shp137/ Cowper St",
    "sg:city":"Warrawong",
    "sg:classifiers":[
        {
            "category":"Shopping",
            "subcategory":"Clothing, Apparel, & Fashions",
            "type":"Retail Goods"
        }
    ],
    "sg:phone":"+61 2 4276 4088",
    "sg:postcode":"2502",
    "sg:province":"NSW",
    "sg:tags":[
        "lady",
        "wear"
    ],
    "wof:name":"Popular Simply The Best",
    "wof:placetype":"venue"
},
  "geometry": {"coordinates":[150.887589,-34.485378],"type":"Point"}
}