{
  "type": "Feature",
  "properties": {
    "iso:country":"AU",
    "sg:address":"266 Melbourne St",
    "sg:city":"North Adelaide",
    "sg:classifiers":[
        {
            "category":"Health Services",
            "subcategory":"Doctor",
            "type":"Services"
        }
    ],
    "sg:phone":"+61 8 8361 7088",
    "sg:postcode":"5006",
    "sg:province":"SA",
    "sg:tags":[
        "medical",
        "practitioner"
    ],
    "wof:name":"Hague W M",
    "wof:placetype":"venue"
},
  "geometry": {"coordinates":[138.602493286,-34.9095344543],"type":"Point"}
}