{
  "type": "Feature",
  "properties": {
    "addr:full":"12 Milverton Ave Karrinyup WA 6018",
    "addr:housenumber":"12",
    "addr:postcode":"6018",
    "addr:street":"Milverton Ave",
    "iso:country":"AU",
    "sg:address":"12 Milverton Ave",
    "sg:city":"Karrinyup",
    "sg:classifiers":[
        {
            "category":"Health Services",
            "subcategory":"Health Practitioner",
            "type":"Services"
        }
    ],
    "sg:phone":"+61 409 080 324",
    "sg:postcode":"6018",
    "sg:province":"WA",
    "sg:tags":[
        "pathologist",
        "speech"
    ],
    "wof:name":"Freedom Of Speech For Kids",
    "wof:placetype":"venue"
},
  "geometry": {"coordinates":[115.77432251,-31.859752655],"type":"Point"}
}