{
  "type": "Feature",
  "properties": {
    "iso:country":"AU",
    "sg:address":"296 Elizabeth St",
    "sg:city":"North Hobart",
    "sg:classifiers":[
        {
            "category":"Building & Trades",
            "subcategory":"Construction",
            "type":"Services"
        }
    ],
    "sg:phone":"+61 3 6234 2200",
    "sg:postcode":"7000",
    "sg:province":"TAS",
    "sg:tags":[
        "contractor"
    ],
    "sg:website":"http://www.cunic.com.au",
    "wof:name":"Cunic Constructions Pty Ltd",
    "wof:placetype":"venue"
},
  "geometry": {"coordinates":[147.31829834000001,-42.8765563965],"type":"Point"}
}