{
  "type": "Feature",
  "properties": {
    "addr:full":"2/ 1147 South Pine Rd Arana Hills QLD 4054",
    "addr:housenumber":"/ 1147",
    "addr:postcode":"4054",
    "addr:street":"South Pine Rd",
    "iso:country":"AU",
    "sg:address":"2/ 1147 South Pine Rd",
    "sg:city":"Arana Hills",
    "sg:classifiers":[
        {
            "category":"Professional",
            "subcategory":"Printing & Photocopies",
            "type":"Services"
        }
    ],
    "sg:phone":"+61 7 3851 0045",
    "sg:postcode":"4054",
    "sg:province":"QLD",
    "sg:tags":[
        "screen",
        "printer"
    ],
    "wof:name":"Top Cat Screen Printers",
    "wof:placetype":"venue"
},
  "geometry": {"coordinates":[152.96168518100001,-27.3889255524],"type":"Point"}
}