{
  "type": "Feature",
  "properties": {
    "addr:full":"40 Ernest St Safety Bay WA 6169",
    "addr:housenumber":"40",
    "addr:postcode":"6169",
    "addr:street":"Ernest St",
    "iso:country":"AU",
    "sg:address":"40 Ernest St",
    "sg:city":"Safety Bay",
    "sg:classifiers":[
        {
            "category":"Professional",
            "subcategory":"Art Services",
            "type":"Services"
        }
    ],
    "sg:phone":"+61 8 9527 5762",
    "sg:postcode":"6169",
    "sg:province":"WA",
    "sg:tags":[
        "decorator",
        "painter"
    ],
    "wof:name":"Eikhoudt A J",
    "wof:placetype":"venue"
},
  "geometry": {"coordinates":[115.733177,-32.306358],"type":"Point"}
}