{
  "type": "Feature",
  "properties": {
    "iso:country":"AU",
    "sg:address":"1 Evans Rd",
    "sg:city":"Toukley",
    "sg:classifiers":[
        {
            "category":"Social Services",
            "subcategory":"Retirement Home",
            "type":"Services"
        }
    ],
    "sg:phone":"+61 2 4396 5533",
    "sg:postcode":"2263",
    "sg:province":"NSW",
    "sg:tags":[
        "village"
    ],
    "wof:name":"Heritage Estate The",
    "wof:placetype":"venue"
},
  "geometry": {"coordinates":[151.549622,-33.266621],"type":"Point"}
}