{
  "type": "Feature",
  "properties": {
    "addr:full":"105 Tucks Rd Main Ridge VIC 3928",
    "addr:housenumber":"105",
    "addr:postcode":"3928",
    "addr:street":"Tucks Rd",
    "iso:country":"AU",
    "sg:address":"105 Tucks Rd",
    "sg:city":"Main Ridge",
    "sg:classifiers":[
        {
            "category":"Farming",
            "subcategory":"Vineyard",
            "type":"Manufacturing & Wholesale Goods"
        }
    ],
    "sg:phone":"+61 3 5989 6500",
    "sg:postcode":"3928",
    "sg:province":"VIC",
    "sg:tags":[
        "winery"
    ],
    "wof:name":"Yrsas Vineyard Pty Ltd",
    "wof:placetype":"venue"
},
  "geometry": {"coordinates":[144.99568176299999,-38.3878364563],"type":"Point"}
}