{
  "type": "Feature",
  "properties": {
    "addr:full":"Barrier St Fyshwick ACT 2609",
    "addr:postcode":"2609",
    "addr:street":"Barrier St",
    "iso:country":"AU",
    "sg:address":"Barrier St",
    "sg:city":"Fyshwick",
    "sg:classifiers":[
        {
            "category":"Personal",
            "subcategory":"Beauty Salon",
            "type":"Services"
        }
    ],
    "sg:phone":"+61 2 6280 6049",
    "sg:postcode":"2609",
    "sg:province":"ACT",
    "sg:tags":[
        "hairdresser"
    ],
    "wof:name":"TG's Hair Studio",
    "wof:placetype":"venue"
},
  "geometry": {"coordinates":[149.17539977999999,-35.3303222656],"type":"Point"}
}