{
  "type": "Feature",
  "properties": {
    "addr:full":"Shop 12 / 58 Southside Drv Hillarys WA 6025",
    "addr:housenumber":"shop 12 / 58",
    "addr:postcode":"6025",
    "addr:street":"Southside Drv",
    "iso:country":"AU",
    "sg:address":"Shop 12 / 58 Southside Drv",
    "sg:city":"Hillarys",
    "sg:classifiers":[
        {
            "category":"Personal",
            "subcategory":"Beauty Salon",
            "type":"Services"
        }
    ],
    "sg:phone":"+61 8 9447 1129",
    "sg:postcode":"6025",
    "sg:province":"WA",
    "sg:tags":[
        "hairdresser"
    ],
    "wof:name":"The Salon @ Hillarys",
    "wof:placetype":"venue"
},
  "geometry": {"coordinates":[115.741966248,-31.8239994049],"type":"Point"}
}