{
  "type": "Feature",
  "properties": {
    "addr:full":"5 Forrest St Nannup WA 6275",
    "addr:housenumber":"5",
    "addr:postcode":"6275",
    "addr:street":"Forrest St",
    "iso:country":"AU",
    "sg:address":"5 Forrest St",
    "sg:city":"Nannup",
    "sg:classifiers":[
        {
            "category":"Building & Trades",
            "subcategory":"Construction",
            "type":"Services"
        }
    ],
    "sg:phone":"+61 8 9756 3046",
    "sg:postcode":"6275",
    "sg:province":"WA",
    "sg:tags":[
        "contractor"
    ],
    "wof:name":"Warren Blackwood Construction",
    "wof:placetype":"venue"
},
  "geometry": {"coordinates":[115.764572144,-33.9778022766],"type":"Point"}
}