{
  "type": "Feature",
  "properties": {
    "iso:country":"AU",
    "sg:address":"Shop 7A, 87 King St",
    "sg:city":"Warners Bay",
    "sg:classifiers":[
        {
            "category":"Banks & Credit Unions",
            "subcategory":"Financial Services",
            "type":"Services"
        }
    ],
    "sg:phone":"+61 2 4947 4999",
    "sg:postcode":"2282",
    "sg:province":"NSW",
    "sg:tags":[
        "loan",
        "finance",
        "mortgage"
    ],
    "wof:name":"Plan B Finance Brokers Pty Ltd",
    "wof:placetype":"venue"
},
  "geometry": {"coordinates":[151.647827148,-32.9743347168],"type":"Point"}
}