{
  "type": "Feature",
  "properties": {
    "addr:full":"5 Adderley Crt Point Cook VIC 3030",
    "addr:housenumber":"5",
    "addr:postcode":"3030",
    "addr:street":"Adderley Crt",
    "iso:country":"AU",
    "sg:address":"5 Adderley Crt",
    "sg:city":"Point Cook",
    "sg:classifiers":[
        {
            "category":"Arena",
            "subcategory":"Sports Club",
            "type":"Entertainment"
        }
    ],
    "sg:phone":"+61 3 9395 4088",
    "sg:postcode":"3030",
    "sg:province":"VIC",
    "sg:tags":[
        "defence",
        "supply",
        "self",
        "instruction",
        "martial art"
    ],
    "wof:name":"Dave Franklin Martial Arts",
    "wof:placetype":"venue"
},
  "geometry": {"coordinates":[144.748627,-37.877365],"type":"Point"}
}