{
  "type": "Feature",
  "properties": {
    "addr:full":"1875 Bulga Rd Marlee NSW 2429",
    "addr:housenumber":"1875",
    "addr:postcode":"2429",
    "addr:street":"Bulga Rd",
    "iso:country":"AU",
    "sg:address":"1875 Bulga Rd",
    "sg:city":"Marlee",
    "sg:classifiers":[
        {
            "category":"Professional",
            "subcategory":"Business Services",
            "type":"Services"
        }
    ],
    "sg:phone":"+61 2 6550 5244",
    "sg:postcode":"2429",
    "sg:province":"NSW",
    "sg:tags":[
        "drafting"
    ],
    "wof:name":"Brenden Summerfield",
    "wof:placetype":"venue"
},
  "geometry": {"coordinates":[152.30201721200001,-31.756816864],"type":"Point"}
}