{
  "type": "Feature",
  "properties": {
    "addr:full":"18 Waterloo Ave Woy Woy NSW 2256",
    "addr:housenumber":"18",
    "addr:postcode":"2256",
    "addr:street":"Waterloo Ave",
    "iso:country":"AU",
    "sg:address":"18 Waterloo Ave",
    "sg:city":"Woy Woy",
    "sg:classifiers":[
        {
            "category":"Building & Trades",
            "subcategory":"Construction",
            "type":"Services"
        }
    ],
    "sg:phone":"+61 2 4342 3539",
    "sg:postcode":"2256",
    "sg:province":"NSW",
    "sg:tags":[
        "earth",
        "excavating",
        "moving",
        "contractor"
    ],
    "wof:name":"Plowright Brian",
    "wof:placetype":"venue"
},
  "geometry": {"coordinates":[151.32290649399999,-33.5047836304],"type":"Point"}
}