{
  "type": "Feature",
  "properties": {
    "iso:country":"AU",
    "sg:address":"285 Clarence St",
    "sg:city":"Sydney",
    "sg:classifiers":[
        {
            "category":"Shopping",
            "subcategory":"Event Tickets",
            "type":"Retail Goods"
        }
    ],
    "sg:phone":"+61 2 9209 8101",
    "sg:postcode":"2000",
    "sg:province":"NSW",
    "sg:tags":[
        "machine",
        "issuing"
    ],
    "wof:name":"Softix Pty Ltd",
    "wof:placetype":"venue"
},
  "geometry": {"coordinates":[151.205535889,-33.8726844788],"type":"Point"}
}