{
  "type": "Feature",
  "properties": {
    "iso:country":"AU",
    "sg:address":"Corner Of Hospital Road & Ruby Street Suite 3 / 31 Ruby St",
    "sg:city":"Emerald",
    "sg:classifiers":[
        {
            "category":"Professional",
            "subcategory":"Engineering",
            "type":"Services"
        }
    ],
    "sg:phone":"+61 7 4982 3689",
    "sg:postcode":"4720",
    "sg:province":"QLD",
    "sg:tags":[
        "civil",
        "engineer"
    ],
    "wof:name":"Golding Contractors Pty Ltd",
    "wof:placetype":"venue"
},
  "geometry": {"coordinates":[148.158264,-23.524223],"type":"Point"}
}