{
  "type": "Feature",
  "properties": {
    "addr:full":"25 Boston St Clayfield QLD 4011",
    "addr:housenumber":"25",
    "addr:postcode":"4011",
    "addr:street":"Boston St",
    "iso:country":"AU",
    "sg:address":"25 Boston St",
    "sg:city":"Clayfield",
    "sg:classifiers":[
        {
            "category":"Shopping",
            "subcategory":"Gifts & Souvenirs",
            "type":"Retail Goods"
        }
    ],
    "sg:phone":"+61 7 3262 6411",
    "sg:postcode":"4011",
    "sg:province":"QLD",
    "sg:tags":[
        "shop",
        "supply"
    ],
    "wof:name":"Australia Greetings",
    "wof:placetype":"venue"
},
  "geometry": {"coordinates":[153.058594,-27.421474],"type":"Point"}
}