{
  "type": "Feature",
  "properties": {
    "addr:full":"9 Effingham St South Launceston TAS 7249",
    "addr:housenumber":"9",
    "addr:postcode":"7249",
    "addr:street":"Effingham St",
    "iso:country":"AU",
    "sg:address":"9 Effingham St",
    "sg:city":"South Launceston",
    "sg:classifiers":[
        {
            "category":"Building & Trades",
            "subcategory":"Construction",
            "type":"Services"
        }
    ],
    "sg:phone":"+61 3 6343 1685",
    "sg:postcode":"7249",
    "sg:province":"TAS",
    "sg:tags":[
        "contractor"
    ],
    "wof:name":"Whatley P R",
    "wof:placetype":"venue"
},
  "geometry": {"coordinates":[147.152435303,-41.4539070129],"type":"Point"}
}