{
  "type": "Feature",
  "properties": {
    "addr:full":"287 Bay Rd Cheltenham VIC 3192",
    "addr:housenumber":"287",
    "addr:postcode":"3192",
    "addr:street":"Bay Rd",
    "iso:country":"AU",
    "sg:address":"287 Bay Rd",
    "sg:city":"Cheltenham",
    "sg:classifiers":[
        {
            "category":"Ferry Terminal",
            "type":"Transportation"
        }
    ],
    "sg:phone":"+61 3 9553 5624",
    "sg:postcode":"3192",
    "sg:province":"VIC",
    "sg:tags":[
        "mixing",
        "concrete",
        "vibrator",
        "equipment"
    ],
    "wof:name":"Dinmac Solutions Pty Ltd",
    "wof:placetype":"venue"
},
  "geometry": {"coordinates":[145.07063293499999,-37.9512825012],"type":"Point"}
}