{
  "type": "Feature",
  "properties": {
    "addr:full":"11 Tullamarine Park Drv Tullamarine VIC 3043",
    "addr:housenumber":"11",
    "addr:postcode":"3043",
    "addr:street":"Tullamarine Park Drv",
    "iso:country":"AU",
    "sg:address":"11 Tullamarine Park Drv",
    "sg:city":"Tullamarine",
    "sg:classifiers":[
        {
            "category":"Building & Trades",
            "subcategory":"Construction",
            "type":"Services"
        }
    ],
    "sg:phone":"+61 3 9330 2655",
    "sg:postcode":"3043",
    "sg:province":"VIC",
    "sg:tags":[
        "earth",
        "excavating",
        "moving",
        "contractor"
    ],
    "wof:name":"Weldit Pty Ltd",
    "wof:placetype":"venue"
},
  "geometry": {"coordinates":[144.86256408700001,-37.7142715454],"type":"Point"}
}