{
  "type": "Feature",
  "properties": {
    "addr:full":"218 York St Albany WA 6330",
    "addr:housenumber":"218",
    "addr:postcode":"6330",
    "addr:street":"York St",
    "iso:country":"AU",
    "sg:address":"218 York St",
    "sg:city":"Albany",
    "sg:classifiers":[
        {
            "category":"Personal",
            "subcategory":"Beauty Salon",
            "type":"Services"
        }
    ],
    "sg:phone":"+61 8 9841 4665",
    "sg:postcode":"6330",
    "sg:province":"WA",
    "sg:tags":[
        "hairdresser"
    ],
    "wof:name":"Albany Hot Lox Hair & Beauty",
    "wof:placetype":"venue"
},
  "geometry": {"coordinates":[117.883781433,-35.0236587524],"type":"Point"}
}