{
  "type": "Feature",
  "properties": {
    "iso:country":"AU",
    "sg:address":"2/ 5 Aurora Pl",
    "sg:city":"Queanbeyan",
    "sg:classifiers":[
        {
            "category":"Manufacturing",
            "subcategory":"Furniture",
            "type":"Manufacturing & Wholesale Goods"
        }
    ],
    "sg:phone":"+61 2 6297 8200",
    "sg:postcode":"2620",
    "sg:province":"ACT",
    "sg:tags":[
        "builder",
        "designer",
        "custom"
    ],
    "wof:name":"Dunstone Design",
    "wof:placetype":"venue"
},
  "geometry": {"coordinates":[149.249069214,-35.3372802734],"type":"Point"}
}