{
  "type": "Feature",
  "properties": {
    "addr:full":"111 Shorehaven Drv Noosaville QLD 4566",
    "addr:housenumber":"111",
    "addr:postcode":"4566",
    "addr:street":"Shorehaven Drv",
    "iso:country":"AU",
    "sg:address":"111 Shorehaven Drv",
    "sg:city":"Noosaville",
    "sg:classifiers":[
        {
            "category":"Building & Trades",
            "subcategory":"Construction",
            "type":"Services"
        }
    ],
    "sg:phone":"+61 7 5474 1538",
    "sg:postcode":"4566",
    "sg:province":"QLD",
    "sg:tags":[
        "concrete",
        "contractor"
    ],
    "wof:name":"Fielden Concreting",
    "wof:placetype":"venue"
},
  "geometry": {"coordinates":[153.05490112300001,-26.4039058685],"type":"Point"}
}