{
  "type": "Feature",
  "properties": {
    "iso:country":"AU",
    "sg:address":"Unit 2- 4 Bellingham St",
    "sg:city":"Narellan",
    "sg:classifiers":[
        {
            "category":"Building & Trades",
            "subcategory":"Construction",
            "type":"Services"
        }
    ],
    "sg:phone":"+61 412 409 632",
    "sg:postcode":"2567",
    "sg:province":"NSW",
    "sg:tags":[
        "insulation",
        "contractor"
    ],
    "wof:name":"Cosy Inslulation Pty Ltd",
    "wof:placetype":"venue"
},
  "geometry": {"coordinates":[150.73127746599999,-34.0374107361],"type":"Point"}
}