{
  "type": "Feature",
  "properties": {
    "addr:full":"6/ 111 Jersey Rd Woollahra NSW 2025",
    "addr:housenumber":"/ 111",
    "addr:postcode":"2025",
    "addr:street":"Jersey Rd",
    "iso:country":"AU",
    "sg:address":"6/ 111 Jersey Rd",
    "sg:city":"Woollahra",
    "sg:classifiers":[
        {
            "category":"Real Estate",
            "subcategory":"Architect",
            "type":"Services"
        }
    ],
    "sg:phone":"+61 2 9363 3455",
    "sg:postcode":"2025",
    "sg:province":"NSW",
    "wof:name":"de la Vega Architects Pty Ltd",
    "wof:placetype":"venue"
},
  "geometry": {"coordinates":[151.23695373499999,-33.886051178],"type":"Point"}
}