{
  "type": "Feature",
  "properties": {
    "iso:country":"AU",
    "sg:address":"131- 133 Mann St",
    "sg:city":"Gosford",
    "sg:classifiers":[
        {
            "category":"Real Estate",
            "subcategory":"Real Estate Agent",
            "type":"Services"
        }
    ],
    "sg:phone":"+61 2 4324 1011",
    "sg:postcode":"2250",
    "sg:province":"NSW",
    "wof:name":"Real Estate, The House Of",
    "wof:placetype":"venue"
},
  "geometry": {"coordinates":[151.34213256800001,-33.4263343811],"type":"Point"}
}