{
  "type": "Feature",
  "properties": {
    "addr:full":"33-39 Huntingdale Drv Greenbank QLD 4124",
    "addr:housenumber":"33-39",
    "addr:postcode":"4124",
    "addr:street":"Huntingdale Drv",
    "iso:country":"AU",
    "sg:address":"33-39 Huntingdale Drv",
    "sg:city":"Greenbank",
    "sg:classifiers":[
        {
            "category":"Professional",
            "type":"Services"
        }
    ],
    "sg:phone":"+61 7 3297 5408",
    "sg:postcode":"4124",
    "sg:province":"QLD",
    "sg:tags":[
        "transport"
    ],
    "wof:name":"Cumner Transport Services Pty Ltd",
    "wof:placetype":"venue"
},
  "geometry": {"coordinates":[153.00794982900001,-27.6940631866],"type":"Point"}
}