{
  "type": "Feature",
  "properties": {
    "iso:country":"AU",
    "sg:address":"2457 Warburton Hwy",
    "sg:city":"Yarra Junction",
    "sg:classifiers":[
        {
            "category":"Utilities",
            "subcategory":"Mobile Phone",
            "type":"Services"
        }
    ],
    "sg:phone":"+61 3 5967 2667",
    "sg:postcode":"3797",
    "sg:province":"VIC",
    "sg:tags":[
        "repair",
        "telephone"
    ],
    "wof:name":"Polktronics",
    "wof:placetype":"venue"
},
  "geometry": {"coordinates":[145.60633850100001,-37.7797431946],"type":"Point"}
}