{
  "type": "Feature",
  "properties": {
    "iso:country":"AU",
    "sg:address":"PO Box 569",
    "sg:city":"Marrickville",
    "sg:classifiers":[
        {
            "category":"Banks & Credit Unions",
            "subcategory":"Investment Brokerage",
            "type":"Services"
        }
    ],
    "sg:phone":"+61 408 885 613",
    "sg:postcode":"1475",
    "sg:province":"NSW",
    "sg:tags":[
        "shutter",
        "louvre"
    ],
    "wof:name":"Universal Building Services",
    "wof:placetype":"venue"
},
  "geometry": {"coordinates":[151.15719604500001,-33.9109191895],"type":"Point"}
}