{
  "type": "Feature",
  "properties": {
    "addr:full":"108 Mt Crosby Rd Tivoli QLD 4305",
    "addr:housenumber":"108",
    "addr:postcode":"4305",
    "addr:street":"Mt Crosby Rd",
    "iso:country":"AU",
    "sg:address":"108 Mt Crosby Rd",
    "sg:city":"Tivoli",
    "sg:classifiers":[
        {
            "category":"Education",
            "subcategory":"School",
            "type":"Public Place"
        }
    ],
    "sg:phone":"+61 7 3813 7444",
    "sg:postcode":"4305",
    "sg:province":"QLD",
    "sg:tags":[
        "state",
        "except",
        "nsw"
    ],
    "wof:name":"Tivoli Primary",
    "wof:placetype":"venue"
},
  "geometry": {"coordinates":[152.77784729000001,-27.5835971832],"type":"Point"}
}