{
  "type": "Feature",
  "properties": {
    "iso:country":"AU",
    "sg:address":"61 Acanthas Rd",
    "sg:city":"Willetton",
    "sg:classifiers":[
        {
            "category":"Professional",
            "subcategory":"Art Services",
            "type":"Services"
        }
    ],
    "sg:phone":"+61 8 9457 8107",
    "sg:postcode":"6155",
    "sg:province":"WA",
    "sg:tags":[
        "interior",
        "designer"
    ],
    "wof:name":"Diana Scott CAD Designs",
    "wof:placetype":"venue"
},
  "geometry": {"coordinates":[115.88041699999999,-32.043415],"type":"Point"}
}