{
  "type": "Feature",
  "properties": {
    "iso:country":"AU",
    "sg:address":"Cnr Anzac Pde & York St",
    "sg:city":"Teralba",
    "sg:classifiers":[
        {
            "category":"Building & Trades",
            "subcategory":"Equipment Rental",
            "type":"Services"
        }
    ],
    "sg:phone":"+61 2 4958 8497",
    "sg:postcode":"2284",
    "sg:province":"NSW",
    "sg:tags":[
        "party",
        "hire"
    ],
    "wof:name":"Cupids Corner Wedding Hire & Event Designs",
    "wof:placetype":"venue"
},
  "geometry": {"coordinates":[151.604614258,-32.9632911682],"type":"Point"}
}