{
  "type": "Feature",
  "properties": {
    "addr:full":"Shop 1 730 Logan Rd Greenslopes QLD 4120",
    "addr:housenumber":"shop 1 730",
    "addr:postcode":"4120",
    "addr:street":"Logan Rd",
    "iso:country":"AU",
    "sg:address":"Shop 1 730 Logan Rd",
    "sg:city":"Greenslopes",
    "sg:classifiers":[
        {
            "category":"Utilities",
            "subcategory":"Electric",
            "type":"Services"
        }
    ],
    "sg:phone":"+61 7 3397 2769",
    "sg:postcode":"4120",
    "sg:province":"QLD",
    "sg:tags":[
        "electrical",
        "contractor"
    ],
    "wof:name":"Nu-Tech Electrical",
    "wof:placetype":"venue"
},
  "geometry": {"coordinates":[153.05364990199999,-27.5126495361],"type":"Point"}
}