{
  "type": "Feature",
  "properties": {
    "addr:full":"Thinraathin St Pormpuraaw QLD 4871",
    "addr:postcode":"4871",
    "iso:country":"AU",
    "sg:address":"Thinraathin St",
    "sg:city":"Pormpuraaw",
    "sg:classifiers":[
        {
            "category":"Government",
            "subcategory":"Department Of Motor Vehicles",
            "type":"Public Place"
        }
    ],
    "sg:phone":"+61 7 4060 4600",
    "sg:postcode":"4871",
    "sg:province":"QLD",
    "sg:tags":[
        "organisation",
        "local"
    ],
    "wof:name":"Pormpuraaw Community Council",
    "wof:placetype":"venue"
},
  "geometry": {"coordinates":[141.618652344,-14.8990688324],"type":"Point"}
}