{
  "type": "Feature",
  "properties": {
    "addr:full":"51 Manning St Tuncurry NSW 2428",
    "addr:housenumber":"51",
    "addr:postcode":"2428",
    "addr:street":"Manning St",
    "iso:country":"AU",
    "sg:address":"51 Manning St",
    "sg:city":"Tuncurry",
    "sg:classifiers":[
        {
            "category":"Social Services",
            "subcategory":"Child Care",
            "type":"Services"
        }
    ],
    "sg:phone":"+61 2 6555 3266",
    "sg:postcode":"2428",
    "sg:province":"NSW",
    "wof:name":"Dolphins Child Care Centre",
    "wof:placetype":"venue"
},
  "geometry": {"coordinates":[152.49899300000001,-32.171551],"type":"Point"}
}