{
  "type": "Feature",
  "properties": {
    "addr:full":"39 Martin Pl Sydney NSW 2000",
    "addr:housenumber":"39",
    "addr:postcode":"2000",
    "addr:street":"Martin Pl",
    "iso:country":"AU",
    "sg:address":"39 Martin Pl",
    "sg:city":"Sydney",
    "sg:classifiers":[
        {
            "category":"Building & Trades",
            "subcategory":"Locksmith",
            "type":"Services"
        }
    ],
    "sg:phone":"+61 2 9223 6393",
    "sg:postcode":"2000",
    "sg:province":"NSW",
    "sg:tags":[
        "lock"
    ],
    "wof:name":"O'Brien Locks Doors & Security",
    "wof:placetype":"venue"
},
  "geometry": {"coordinates":[151.20993042000001,-33.8678016663],"type":"Point"}
}