{
  "type": "Feature",
  "properties": {
    "iso:country":"AU",
    "sg:address":"123 Forest Rd",
    "sg:city":"Hurstville",
    "sg:classifiers":[
        {
            "category":"Professional",
            "subcategory":"Accounting & Tax Preparation",
            "type":"Services"
        }
    ],
    "sg:phone":"+61 2 9585 0688",
    "sg:postcode":"2220",
    "sg:province":"NSW",
    "sg:tags":[
        "consultant",
        "taxation"
    ],
    "wof:name":"Karamihas E & Co",
    "wof:placetype":"venue"
},
  "geometry": {"coordinates":[151.103683472,-33.9674530029],"type":"Point"}
}