{
  "type": "Feature",
  "properties": {
    "addr:full":"Watson Rd Acacia Ridge QLD 4110",
    "addr:postcode":"4110",
    "addr:street":"Watson Rd",
    "iso:country":"AU",
    "sg:address":"Watson Rd",
    "sg:city":"Acacia Ridge",
    "sg:classifiers":[
        {
            "category":"Utilities",
            "subcategory":"Refuse",
            "type":"Services"
        }
    ],
    "sg:phone":"+61 7 3272 3377",
    "sg:postcode":"4110",
    "sg:province":"QLD",
    "sg:tags":[
        "disposal",
        "reduction",
        "waste"
    ],
    "wof:name":"Metro Skips",
    "wof:placetype":"venue"
},
  "geometry": {"coordinates":[153.01942443900001,-27.5888938904],"type":"Point"}
}