{
  "type": "Feature",
  "properties": {
    "iso:country":"AU",
    "sg:address":"9 Rainbow Valley Rd",
    "sg:city":"Park Orchards",
    "sg:classifiers":[
        {
            "category":"Building & Trades",
            "subcategory":"Construction",
            "type":"Services"
        }
    ],
    "sg:phone":"+61 3 9876 5945",
    "sg:postcode":"3114",
    "sg:province":"VIC",
    "sg:tags":[
        "fencing",
        "contractor"
    ],
    "wof:name":"Carlile Fencing Pty Ltd",
    "wof:placetype":"venue"
},
  "geometry": {"coordinates":[145.20185852,-37.7791595459],"type":"Point"}
}