{
  "type": "Feature",
  "properties": {
    "addr:full":"Level 2 211 La Trobe St Melbourne VIC 3000",
    "addr:housenumber":"211",
    "addr:postcode":"3000",
    "addr:street":"La Trobe St",
    "iso:country":"AU",
    "sg:address":"Level 2 211 La Trobe St",
    "sg:city":"Melbourne",
    "sg:classifiers":[
        {
            "category":"Manufacturing",
            "subcategory":"Jewelry",
            "type":"Manufacturing & Wholesale Goods"
        }
    ],
    "sg:phone":"+61 3 9660 6571",
    "sg:postcode":"3000",
    "sg:province":"VIC",
    "sg:tags":[
        "mfrg",
        "jeweller"
    ],
    "wof:name":"Eiko Australia Pty Ltd",
    "wof:placetype":"venue"
},
  "geometry": {"coordinates":[144.963424683,-37.8098258972],"type":"Point"}
}