{
  "type": "Feature",
  "properties": {
    "iso:country":"AU",
    "sg:address":"4 Evans St",
    "sg:city":"Peakhurst",
    "sg:classifiers":[
        {
            "category":"Commercial Area",
            "type":"Public Place"
        }
    ],
    "sg:phone":"+61 2 9533 1557",
    "sg:postcode":"2210",
    "sg:province":"NSW",
    "sg:tags":[
        "heavy",
        "carrier"
    ],
    "wof:name":"Newson T & J A Transport Pty Ltd",
    "wof:placetype":"venue"
},
  "geometry": {"coordinates":[151.049149,-33.964752],"type":"Point"}
}