{
  "type": "Feature",
  "properties": {
    "addr:full":"Unit 2/ 81 Guthrie St Osborne Park WA 6017",
    "addr:postcode":"6017",
    "addr:street":"Guthrie St",
    "iso:country":"AU",
    "sg:address":"Unit 2/ 81 Guthrie St",
    "sg:city":"Osborne Park",
    "sg:classifiers":[
        {
            "category":"Shopping",
            "type":"Retail Goods"
        }
    ],
    "sg:phone":"+61 8 9244 4566",
    "sg:postcode":"6017",
    "sg:province":"WA",
    "sg:tags":[
        "equipment",
        "safety",
        "accessory"
    ],
    "wof:name":"Access Unlimited International Pty Ltd",
    "wof:placetype":"venue"
},
  "geometry": {"coordinates":[115.81636047400001,-31.9063625336],"type":"Point"}
}