{
  "type": "Feature",
  "properties": {
    "iso:country":"AU",
    "sg:address":"Cnr Woodroffe Ave & Broadarrow Cct",
    "sg:city":"Palmerston",
    "sg:classifiers":[
        {
            "category":"Education",
            "subcategory":"School",
            "type":"Public Place"
        }
    ],
    "sg:phone":"+61 8 8932 2338",
    "sg:postcode":"0830",
    "sg:province":"NT",
    "sg:tags":[
        "state",
        "except",
        "nsw"
    ],
    "wof:name":"Woodroffe Pre-School",
    "wof:placetype":"venue"
},
  "geometry": {"coordinates":[130.98126199999999,-12.501301],"type":"Point"}
}