{
  "type": "Feature",
  "properties": {
    "iso:country":"AU",
    "sg:address":"120 Edward St",
    "sg:city":"Brisbane",
    "sg:classifiers":[
        {
            "category":"Personal",
            "subcategory":"Beauty Salon",
            "type":"Services"
        }
    ],
    "sg:phone":"+61 7 3012 7448",
    "sg:postcode":"4000",
    "sg:province":"QLD",
    "wof:name":"The Skin Management Centre",
    "wof:placetype":"venue"
},
  "geometry": {"coordinates":[153.02850341800001,-27.4700927734],"type":"Point"}
}