{
  "type": "Feature",
  "properties": {
    "addr:full":"Ste1/ 314 Childs Rd Mill Park VIC 3082",
    "addr:housenumber":"314",
    "addr:postcode":"3082",
    "addr:street":"Childs Rd",
    "iso:country":"AU",
    "sg:address":"Ste1/ 314 Childs Rd",
    "sg:city":"Mill Park",
    "sg:classifiers":[
        {
            "category":"Personal",
            "subcategory":"Beauty Salon",
            "type":"Services"
        }
    ],
    "sg:phone":"+61 3 9436 5900",
    "sg:postcode":"3082",
    "sg:province":"VIC",
    "sg:tags":[
        "hairdresser"
    ],
    "wof:name":"Marsu Hair Studio",
    "wof:placetype":"venue"
},
  "geometry": {"coordinates":[145.061813355,-37.6672286987],"type":"Point"}
}