{
  "type": "Feature",
  "properties": {
    "addr:full":"14 Nepean Hwy Mentone VIC 3194",
    "addr:housenumber":"14",
    "addr:postcode":"3194",
    "addr:street":"Nepean Hwy",
    "iso:country":"AU",
    "sg:address":"14 Nepean Hwy",
    "sg:city":"Mentone",
    "sg:classifiers":[
        {
            "category":"Manufacturing",
            "subcategory":"Motor Vehicles & Parts",
            "type":"Manufacturing & Wholesale Goods"
        }
    ],
    "sg:phone":"+61 3 9585 0077",
    "sg:postcode":"3194",
    "sg:province":"VIC",
    "sg:tags":[
        "replacement"
    ],
    "wof:name":"Autobarn Pty Ltd",
    "wof:placetype":"venue"
},
  "geometry": {"coordinates":[145.06549072300001,-37.9758682251],"type":"Point"}
}