{
  "type": "Feature",
  "properties": {
    "addr:full":"221 Wollaston Rd Warrnambool VIC 3280",
    "addr:housenumber":"221",
    "addr:postcode":"3280",
    "addr:street":"Wollaston Rd",
    "iso:country":"AU",
    "sg:address":"221 Wollaston Rd",
    "sg:city":"Warrnambool",
    "sg:classifiers":[
        {
            "category":"Building & Trades",
            "subcategory":"Plumbing",
            "type":"Services"
        }
    ],
    "sg:phone":"+61 418 528 549",
    "sg:postcode":"3280",
    "sg:province":"VIC",
    "sg:tags":[
        "pump",
        "repairer"
    ],
    "wof:name":"Kavanagh's Fuel & Pump Repairs",
    "wof:placetype":"venue"
},
  "geometry": {"coordinates":[142.47938537600001,-38.3532829285],"type":"Point"}
}