{
  "type": "Feature",
  "properties": {
    "addr:full":"1/ 5 Victoria Rd Parramatta NSW 2150",
    "addr:housenumber":"/ 5",
    "addr:postcode":"2150",
    "addr:street":"Victoria Rd",
    "iso:country":"AU",
    "sg:address":"1/ 5 Victoria Rd",
    "sg:city":"Parramatta",
    "sg:classifiers":[
        {
            "category":"Personal",
            "type":"Services"
        }
    ],
    "sg:phone":"+61 2 9683 6551",
    "sg:postcode":"2150",
    "sg:province":"NSW",
    "sg:tags":[
        "nappy"
    ],
    "wof:name":"B J's Laundry Service",
    "wof:placetype":"venue"
},
  "geometry": {"coordinates":[151.06280517600001,-33.7376365662],"type":"Point"}
}