{
  "type": "Feature",
  "properties": {
    "addr:full":"Kawana Waters Shopping World Pt Cartwright Drv Kawana Waters QLD 4575",
    "addr:postcode":"4575",
    "addr:street":"Cartwright Drv",
    "iso:country":"AU",
    "sg:address":"Kawana Waters Shopping World Pt Cartwright Drv",
    "sg:city":"Kawana Waters",
    "sg:classifiers":[
        {
            "category":"Shopping",
            "subcategory":"Department Store",
            "type":"Retail Goods"
        }
    ],
    "sg:phone":"+61 7 5478 3599",
    "sg:postcode":"4575",
    "sg:province":"QLD",
    "wof:name":"Chain Reaction",
    "wof:placetype":"venue"
},
  "geometry": {"coordinates":[153.128647,-26.702805],"type":"Point"}
}