{
  "type": "Feature",
  "properties": {
    "addr:full":"45 Michelmore St Paget QLD 4740",
    "addr:housenumber":"45",
    "addr:postcode":"4740",
    "addr:street":"Michelmore St",
    "iso:country":"AU",
    "sg:address":"45 Michelmore St",
    "sg:city":"Paget",
    "sg:classifiers":[
        {
            "category":"Professional",
            "subcategory":"Engineering",
            "type":"Services"
        }
    ],
    "sg:phone":"+61 7 4952 5554",
    "sg:postcode":"4740",
    "sg:province":"QLD",
    "sg:tags":[
        "engineer"
    ],
    "wof:name":"Melco Engineering Pty. Ltd.",
    "wof:placetype":"venue"
},
  "geometry": {"coordinates":[149.16661099999999,-21.181351],"type":"Point"}
}