{
  "type": "Feature",
  "properties": {
    "addr:full":"Shop 7 Macquarie Pl Cnr Macquarie St & Elizabeth Drv Liverpool NSW 2170",
    "addr:housenumber":"shop 7",
    "addr:postcode":"2170",
    "addr:street":"Macquarie Pl Cnr Macquarie St & Elizabeth Drv",
    "iso:country":"AU",
    "sg:address":"Shop 7 Macquarie Pl Cnr Macquarie St & Elizabeth Drv",
    "sg:city":"Liverpool",
    "sg:classifiers":[
        {
            "category":"Shopping",
            "subcategory":"Mobile Phones",
            "type":"Retail Goods"
        }
    ],
    "sg:phone":"+61 2 9602 7555",
    "sg:postcode":"2170",
    "sg:province":"NSW",
    "sg:tags":[
        "telephone",
        "accessory"
    ],
    "wof:name":"Ryda Telecommunications",
    "wof:placetype":"venue"
},
  "geometry": {"coordinates":[150.91822814899999,-33.9286499023],"type":"Point"}
}