{
  "type": "Feature",
  "properties": {
    "addr:full":"1383 Mount Dandenong Tourist Rd Mt Dandenong VIC 3767",
    "addr:housenumber":"1383",
    "addr:postcode":"3767",
    "addr:street":"Mount Dandenong Tourist Rd",
    "iso:country":"AU",
    "sg:address":"1383 Mount Dandenong Tourist Rd",
    "sg:city":"Mt Dandenong",
    "sg:classifiers":[
        {
            "category":"Travel",
            "subcategory":"Hotels & Motels",
            "type":"Entertainment"
        }
    ],
    "sg:phone":"+61 3 9751 1103",
    "sg:postcode":"3767",
    "sg:province":"VIC",
    "sg:tags":[
        "accommodation"
    ],
    "wof:name":"AAA Five Star Linden Gardens",
    "wof:placetype":"venue"
},
  "geometry": {"coordinates":[145.35589599599999,-37.8335609436],"type":"Point"}
}