{
  "type": "Feature",
  "properties": {
    "addr:full":"27 Garfield St South Launceston TAS 7249",
    "addr:housenumber":"27",
    "addr:postcode":"7249",
    "addr:street":"Garfield St",
    "iso:country":"AU",
    "sg:address":"27 Garfield St",
    "sg:city":"South Launceston",
    "sg:classifiers":[
        {
            "category":"Autos & Motor Vehicles",
            "subcategory":"Auto Supplies",
            "type":"Retail Goods"
        }
    ],
    "sg:phone":"+61 407 866 086",
    "sg:postcode":"7249",
    "sg:province":"TAS",
    "sg:tags":[
        "accessory"
    ],
    "wof:name":"Auto-Motif",
    "wof:placetype":"venue"
},
  "geometry": {"coordinates":[147.14483642600001,-41.4502220154],"type":"Point"}
}