{
  "type": "Feature",
  "properties": {
    "addr:full":"24 Samuel St Mona Vale NSW 2103",
    "addr:housenumber":"24",
    "addr:postcode":"2103",
    "addr:street":"Samuel St",
    "iso:country":"AU",
    "sg:address":"24 Samuel St",
    "sg:city":"Mona Vale",
    "sg:classifiers":[
        {
            "category":"Building & Trades",
            "subcategory":"Construction",
            "type":"Services"
        }
    ],
    "sg:phone":"+61 2 9999 4776",
    "sg:postcode":"2103",
    "sg:province":"NSW",
    "sg:tags":[
        "earth",
        "excavating",
        "moving",
        "contractor"
    ],
    "wof:name":"Hendmet Enterprises Pty Ltd",
    "wof:placetype":"venue"
},
  "geometry": {"coordinates":[151.290283203,-33.6736183167],"type":"Point"}
}