{
  "type": "Feature",
  "properties": {
    "iso:country":"AU",
    "sg:address":"Unit 3/ 21 Spring Park Rd",
    "sg:city":"Midland",
    "sg:classifiers":[
        {
            "category":"Banks & Credit Unions",
            "subcategory":"Financial Services",
            "type":"Services"
        }
    ],
    "sg:phone":"+61 8 9250 2956",
    "sg:postcode":"6056",
    "sg:province":"WA",
    "sg:tags":[
        "settlement",
        "nt",
        "agent",
        "wa"
    ],
    "wof:name":"Woodbridge Settlements",
    "wof:placetype":"venue"
},
  "geometry": {"coordinates":[116.00173950200001,-31.8882369995],"type":"Point"}
}