{
  "type": "Feature",
  "properties": {
    "iso:country":"AU",
    "sg:address":"Mudge St",
    "sg:city":"Sea Lake",
    "sg:classifiers":[
        {
            "category":"Education",
            "subcategory":"Kindergarten",
            "type":"Public Place"
        }
    ],
    "sg:phone":"+61 3 5070 1387",
    "sg:postcode":"3533",
    "sg:province":"VIC",
    "sg:tags":[
        "pre-schools"
    ],
    "wof:name":"Sea Lake Pre-School Centre",
    "wof:placetype":"venue"
},
  "geometry": {"coordinates":[142.85339400000001,-35.504719],"type":"Point"}
}