{
  "type": "Feature",
  "properties": {
    "addr:full":"69 George St East Fremantle WA 6158",
    "addr:housenumber":"69",
    "addr:postcode":"6158",
    "addr:street":"George St",
    "iso:country":"AU",
    "sg:address":"69 George St",
    "sg:city":"East Fremantle",
    "sg:classifiers":[
        {
            "category":"Shopping",
            "subcategory":"Stationery & Office Supplies",
            "type":"Retail Goods"
        }
    ],
    "sg:phone":"+61 8 9319 3630",
    "sg:postcode":"6158",
    "sg:province":"WA",
    "sg:tags":[
        "equipment",
        "display",
        "exhibition"
    ],
    "wof:name":"Creative Spaces",
    "wof:placetype":"venue"
},
  "geometry": {"coordinates":[115.760948,-32.043987],"type":"Point"}
}