{
  "type": "Feature",
  "properties": {
    "addr:full":"328 Moama St Hay NSW 2711",
    "addr:housenumber":"328",
    "addr:postcode":"2711",
    "addr:street":"Moama St",
    "iso:country":"AU",
    "sg:address":"328 Moama St",
    "sg:city":"Hay",
    "sg:classifiers":[
        {
            "category":"Farming",
            "subcategory":"Vineyard",
            "type":"Manufacturing & Wholesale Goods"
        }
    ],
    "sg:phone":"+61 2 6993 1480",
    "sg:postcode":"2711",
    "sg:province":"NSW",
    "sg:tags":[
        "winery"
    ],
    "wof:name":"Ruberto's Cellars",
    "wof:placetype":"venue"
},
  "geometry": {"coordinates":[144.84576415999999,-34.5201263428],"type":"Point"}
}