{
  "type": "Feature",
  "properties": {
    "addr:full":"267 Darling St Dubbo NSW 2830",
    "addr:housenumber":"267",
    "addr:postcode":"2830",
    "addr:street":"Darling St",
    "iso:country":"AU",
    "sg:address":"267 Darling St",
    "sg:city":"Dubbo",
    "sg:classifiers":[
        {
            "category":"Personal",
            "subcategory":"Massage",
            "type":"Services"
        }
    ],
    "sg:phone":"+61 2 6882 0053",
    "sg:postcode":"2830",
    "sg:province":"NSW",
    "sg:tags":[
        "therapy"
    ],
    "wof:name":"Dubbo (Wellbeing) Clinic",
    "wof:placetype":"venue"
},
  "geometry": {"coordinates":[148.60513305699999,-32.2557258606],"type":"Point"}
}