{
  "type": "Feature",
  "properties": {
    "addr:full":"5 Belfree Drv Green Fields SA 5107",
    "addr:housenumber":"5",
    "addr:postcode":"5107",
    "addr:street":"Belfree Drv Green",
    "iso:country":"AU",
    "sg:address":"5 Belfree Drv",
    "sg:city":"Green Fields",
    "sg:classifiers":[
        {
            "category":"Professional",
            "subcategory":"Engineering",
            "type":"Services"
        }
    ],
    "sg:phone":"+61 8 8250 0540",
    "sg:postcode":"5107",
    "sg:province":"SA",
    "sg:tags":[
        "engineer"
    ],
    "sg:website":"http://www.ritewayengineering.com.au",
    "wof:name":"Riteway Engineering & Manufacturing Pty Ltd",
    "wof:placetype":"venue"
},
  "geometry": {"coordinates":[138.60435485799999,-34.7950019836],"type":"Point"}
}