{
  "type": "Feature",
  "properties": {
    "addr:full":"48 Delta Ave Taroona TAS 7053",
    "addr:housenumber":"48",
    "addr:postcode":"7053",
    "addr:street":"Delta Ave",
    "iso:country":"AU",
    "sg:address":"48 Delta Ave",
    "sg:city":"Taroona",
    "sg:classifiers":[
        {
            "category":"Professional",
            "subcategory":"Business Services",
            "type":"Services"
        }
    ],
    "sg:phone":"+61 3 6227 8380",
    "sg:postcode":"7053",
    "sg:province":"TAS",
    "sg:tags":[
        "small",
        "advisory"
    ],
    "sg:website":"http://www.commercetas.com.au",
    "wof:name":"Commerce Tasmania",
    "wof:placetype":"venue"
},
  "geometry": {"coordinates":[147.352463,-42.934975],"type":"Point"}
}