{
  "type": "Feature",
  "properties": {
    "addr:full":"146 Princes Hwy Corrimal NSW 2518",
    "addr:housenumber":"146",
    "addr:postcode":"2518",
    "addr:street":"Princes Hwy",
    "iso:country":"AU",
    "sg:address":"146 Princes Hwy",
    "sg:city":"Corrimal",
    "sg:classifiers":[
        {
            "category":"Retail",
            "subcategory":"Auto Repair",
            "type":"Services"
        }
    ],
    "sg:phone":"+61 2 4284 6540",
    "sg:postcode":"2518",
    "sg:province":"NSW",
    "sg:tags":[
        "repairer",
        "motor",
        "engineer"
    ],
    "wof:name":"Arches Automotive Repairs",
    "wof:placetype":"venue"
},
  "geometry": {"coordinates":[150.89653000000001,-34.374001],"type":"Point"}
}