{
  "type": "Feature",
  "properties": {
    "iso:country":"AU",
    "sg:address":"106 Stuart Hwy",
    "sg:city":"Adelaide River",
    "sg:classifiers":[
        {
            "category":"Travel",
            "subcategory":"Hotels & Motels",
            "type":"Entertainment"
        }
    ],
    "sg:phone":"+61 8 8976 7047",
    "sg:postcode":"0846",
    "sg:province":"NT",
    "wof:name":"Adelaide River Inn",
    "wof:placetype":"venue"
},
  "geometry": {"coordinates":[131.106002808,-13.2389125824],"type":"Point"}
}