{
  "type": "Feature",
  "properties": {
    "addr:full":"279A Yarra Rd Wonga Park VIC 3115",
    "addr:housenumber":"279a",
    "addr:postcode":"3115",
    "addr:street":"Yarra Rd",
    "iso:country":"AU",
    "sg:address":"279A Yarra Rd",
    "sg:city":"Wonga Park",
    "sg:classifiers":[
        {
            "category":"Transit Center",
            "subcategory":"Passenger",
            "type":"Transportation"
        }
    ],
    "sg:phone":"+61 3 9894 1998",
    "sg:postcode":"3115",
    "sg:province":"VIC",
    "sg:tags":[
        "wood",
        "moulding",
        "plastic"
    ],
    "wof:name":"Advanced Moulding Fabricators Pty Ltd",
    "wof:placetype":"venue"
},
  "geometry": {"coordinates":[145.27081298799999,-37.7375144958],"type":"Point"}
}