{
  "type": "Feature",
  "properties": {
    "iso:country":"AU",
    "sg:address":"Box 59 Woodbine St",
    "sg:city":"North Balgowlah 2093 North Balgowlah",
    "sg:classifiers":[
        {
            "category":"Professional",
            "subcategory":"Employment Agencies",
            "type":"Services"
        }
    ],
    "sg:phone":"+61 2 9907 1622",
    "sg:postcode":"2093",
    "sg:province":"NSW",
    "sg:tags":[
        "entertainer",
        "agent"
    ],
    "wof:name":"Swinging Sixties Band",
    "wof:placetype":"venue"
},
  "geometry": {"coordinates":[151.248657227,-33.7857208252],"type":"Point"}
}