{
  "type": "Feature",
  "properties": {
    "addr:full":"85 Nelson St Wallsend NSW 2287",
    "addr:housenumber":"85",
    "addr:postcode":"2287",
    "addr:street":"Nelson St",
    "iso:country":"AU",
    "sg:address":"85 Nelson St",
    "sg:city":"Wallsend",
    "sg:classifiers":[
        {
            "category":"Personal",
            "subcategory":"Beauty Salon",
            "type":"Services"
        }
    ],
    "sg:phone":"+61 2 4951 6857",
    "sg:postcode":"2287",
    "sg:province":"NSW",
    "sg:tags":[
        "hairdresser"
    ],
    "wof:name":"Warrens Hairdressing",
    "wof:placetype":"venue"
},
  "geometry": {"coordinates":[151.66937255900001,-32.9021835327],"type":"Point"}
}