{
  "type": "Feature",
  "properties": {
    "addr:full":"Cnr Russell St & Old Bathurst Rd Emu Plains NSW 2750",
    "addr:postcode":"2750",
    "addr:street":"Cnr Russell St & Old Bathurst Rd",
    "iso:country":"AU",
    "sg:address":"Cnr Russell St & Old Bathurst Rd",
    "sg:city":"Emu Plains",
    "sg:classifiers":[
        {
            "category":"Food & Beverages",
            "subcategory":"Groceries & Convenience Stores",
            "type":"Retail Goods"
        }
    ],
    "sg:phone":"+61 2 4735 5358",
    "sg:postcode":"2750",
    "sg:province":"NSW",
    "wof:name":"Quix Food Stores",
    "wof:placetype":"venue"
},
  "geometry": {"coordinates":[150.65354919399999,-33.7524490356],"type":"Point"}
}