{
  "type": "Feature",
  "properties": {
    "addr:full":"29 Fullers Rd Glenhaven NSW 2156",
    "addr:housenumber":"29",
    "addr:postcode":"2156",
    "addr:street":"Fullers Rd",
    "iso:country":"AU",
    "sg:address":"29 Fullers Rd",
    "sg:city":"Glenhaven",
    "sg:classifiers":[
        {
            "category":"Professional",
            "subcategory":"Computer Services",
            "type":"Services"
        }
    ],
    "sg:phone":"+61 2 9699 8800",
    "sg:postcode":"2156",
    "sg:province":"NSW",
    "sg:tags":[
        "package",
        "software"
    ],
    "wof:name":"Cyber Commerce",
    "wof:placetype":"venue"
},
  "geometry": {"coordinates":[151.00819397000001,-33.7066383362],"type":"Point"}
}