{
  "type": "Feature",
  "properties": {
    "addr:full":"21 Wason St Ulladulla NSW 2539",
    "addr:housenumber":"21",
    "addr:postcode":"2539",
    "addr:street":"Wason St",
    "iso:country":"AU",
    "sg:address":"21 Wason St",
    "sg:city":"Ulladulla",
    "sg:classifiers":[
        {
            "category":"Health Services",
            "subcategory":"Dentist",
            "type":"Services"
        }
    ],
    "sg:phone":"+61 2 4455 1604",
    "sg:postcode":"2539",
    "sg:province":"NSW",
    "wof:name":"Brodie Grant E",
    "wof:placetype":"venue"
},
  "geometry": {"coordinates":[150.474334717,-35.3582229614],"type":"Point"}
}