{
  "type": "Feature",
  "properties": {
    "addr:full":"18 Thames St West Wollongong NSW 2500",
    "addr:housenumber":"18",
    "addr:postcode":"2500",
    "addr:street":"Thames St West",
    "iso:country":"AU",
    "sg:address":"18 Thames St",
    "sg:city":"West Wollongong",
    "sg:classifiers":[
        {
            "category":"Building & Trades",
            "subcategory":"Plumbing",
            "type":"Services"
        }
    ],
    "sg:phone":"+61 2 4227 3614",
    "sg:postcode":"2500",
    "sg:province":"NSW",
    "sg:tags":[
        "plumber",
        "gasfitters"
    ],
    "wof:name":"Figtree Plumbing",
    "wof:placetype":"venue"
},
  "geometry": {"coordinates":[150.864227,-34.432327],"type":"Point"}
}