{
  "type": "Feature",
  "properties": {
    "addr:full":"135 Abbott St Cairns QLD 4870",
    "addr:housenumber":"135",
    "addr:postcode":"4870",
    "addr:street":"Abbott St",
    "iso:country":"AU",
    "sg:address":"135 Abbott St",
    "sg:city":"Cairns",
    "sg:classifiers":[
        {
            "category":"Organizations",
            "subcategory":"Professional Association",
            "type":"Services"
        }
    ],
    "sg:phone":"+61 7 4046 4700",
    "sg:postcode":"4870",
    "sg:province":"QLD",
    "sg:tags":[
        "web",
        "internet"
    ],
    "wof:name":"Mangoville New Media",
    "wof:placetype":"venue"
},
  "geometry": {"coordinates":[145.778762817,-16.9237232208],"type":"Point"}
}