{
  "type": "Feature",
  "properties": {
    "addr:full":"20 Nicholsdale Rd Camberwell VIC 3124",
    "addr:housenumber":"20",
    "addr:postcode":"3124",
    "addr:street":"Nicholsdale Rd",
    "iso:country":"AU",
    "sg:address":"20 Nicholsdale Rd",
    "sg:city":"Camberwell",
    "sg:classifiers":[
        {
            "category":"Building & Trades",
            "subcategory":"Construction",
            "type":"Services"
        }
    ],
    "sg:phone":"+61 419 307 700",
    "sg:postcode":"3124",
    "sg:province":"VIC",
    "sg:tags":[
        "joiner",
        "carpenter"
    ],
    "wof:name":"Wood Worx Pty Ltd",
    "wof:placetype":"venue"
},
  "geometry": {"coordinates":[145.09092712399999,-37.8367996216],"type":"Point"}
}