{
  "type": "Feature",
  "properties": {
    "addr:full":"67 North St Rockhampton QLD 4700",
    "addr:housenumber":"67",
    "addr:postcode":"4700",
    "addr:street":"North St",
    "iso:country":"AU",
    "sg:address":"67 North St",
    "sg:city":"Rockhampton",
    "sg:classifiers":[
        {
            "category":"Health Services",
            "subcategory":"Doctor",
            "type":"Services"
        }
    ],
    "sg:phone":"+61 7 4921 1621",
    "sg:postcode":"4700",
    "sg:province":"QLD",
    "sg:tags":[
        "occupational",
        "safety"
    ],
    "wof:name":"Occupational Medic & Training Services",
    "wof:placetype":"venue"
},
  "geometry": {"coordinates":[150.49534606899999,-23.3775672913],"type":"Point"}
}