{
  "type": "Feature",
  "properties": {
    "iso:country":"AU",
    "sg:address":"U3/ 50 James St",
    "sg:city":"Yeppoon",
    "sg:classifiers":[
        {
            "category":"Fast Food",
            "type":"Food & Drink"
        }
    ],
    "sg:phone":"+61 7 4939 4384",
    "sg:postcode":"4703",
    "sg:province":"QLD",
    "sg:tags":[
        "away",
        "take"
    ],
    "wof:name":"Svendsens Takeaway",
    "wof:placetype":"venue"
},
  "geometry": {"coordinates":[150.74432373100001,-23.128446579],"type":"Point"}
}