{
  "type": "Feature",
  "properties": {
    "addr:full":"Murtho Rd Paringa SA 5340",
    "addr:postcode":"5340",
    "addr:street":"Murtho Rd",
    "iso:country":"AU",
    "sg:address":"Murtho Rd",
    "sg:city":"Paringa",
    "sg:classifiers":[
        {
            "category":"Farming",
            "subcategory":"Orchard",
            "type":"Manufacturing & Wholesale Goods"
        }
    ],
    "sg:phone":"+61 8 8595 8019",
    "sg:postcode":"5340",
    "sg:province":"SA",
    "sg:tags":[
        "citrus",
        "fruit",
        "grower"
    ],
    "wof:name":"Jermacans V",
    "wof:placetype":"venue"
},
  "geometry": {"coordinates":[140.78306579599999,-34.1810417175],"type":"Point"}
}