{
  "type": "Feature",
  "properties": {
    "addr:full":"Old Inn Rd Bulahdelah NSW 2423",
    "addr:postcode":"2423",
    "addr:street":"Rd",
    "iso:country":"AU",
    "sg:address":"Old Inn Rd",
    "sg:city":"Bulahdelah",
    "sg:classifiers":[
        {
            "category":"Building & Trades",
            "subcategory":"Construction",
            "type":"Services"
        }
    ],
    "sg:phone":"+61 2 4997 4698",
    "sg:postcode":"2423",
    "sg:province":"NSW",
    "sg:tags":[
        "roof"
    ],
    "wof:name":"Grimson G H",
    "wof:placetype":"venue"
},
  "geometry": {"coordinates":[152.168564,-32.391987],"type":"Point"}
}