{
  "type": "Feature",
  "properties": {
    "addr:full":"22 Amour Ave Maroubra NSW 2035",
    "addr:housenumber":"22",
    "addr:postcode":"2035",
    "addr:street":"Amour Ave",
    "iso:country":"AU",
    "sg:address":"22 Amour Ave",
    "sg:city":"Maroubra",
    "sg:classifiers":[
        {
            "category":"Health Services",
            "subcategory":"Health Practitioner",
            "type":"Services"
        }
    ],
    "sg:phone":"+61 2 9344 5038",
    "sg:postcode":"2035",
    "sg:province":"NSW",
    "sg:tags":[
        "acupuncture"
    ],
    "wof:name":"Acupuncture Centre",
    "wof:placetype":"venue"
},
  "geometry": {"coordinates":[151.25163269000001,-33.9392852783],"type":"Point"}
}