{
  "type": "Feature",
  "properties": {
    "addr:full":"1/ 56 Young St Frankston VIC 3199",
    "addr:housenumber":"/ 56",
    "addr:postcode":"3199",
    "addr:street":"Young St",
    "iso:country":"AU",
    "sg:address":"1/ 56 Young St",
    "sg:city":"Frankston",
    "sg:classifiers":[
        {
            "category":"Shopping",
            "subcategory":"Clothing, Apparel, & Fashions",
            "type":"Retail Goods"
        }
    ],
    "sg:phone":"+61 3 9781 2250",
    "sg:postcode":"3199",
    "sg:province":"VIC",
    "sg:tags":[
        "menswear"
    ],
    "wof:name":"Aussie Best Clothing",
    "wof:placetype":"venue"
},
  "geometry": {"coordinates":[144.97837829599999,-37.8064880371],"type":"Point"}
}