{
  "type": "Feature",
  "properties": {
    "addr:full":"Galston Rd Galston NSW 2159",
    "addr:postcode":"2159",
    "addr:street":"Galston Rd",
    "iso:country":"AU",
    "sg:address":"Galston Rd",
    "sg:city":"Galston",
    "sg:classifiers":[
        {
            "category":"Education",
            "subcategory":"University",
            "type":"Public Place"
        }
    ],
    "sg:phone":"+61 2 9651 5194",
    "sg:postcode":"2159",
    "sg:province":"NSW",
    "sg:tags":[
        "educational",
        "organisation",
        "cultural"
    ],
    "wof:name":"Girl Guides Asscn (NSW)",
    "wof:placetype":"venue"
},
  "geometry": {"coordinates":[151.045043945,-33.6528701782],"type":"Point"}
}