{
  "type": "Feature",
  "properties": {
    "iso:country":"AU",
    "sg:address":"Level 4, 107 Phillip St",
    "sg:city":"Parramatta",
    "sg:classifiers":[
        {
            "category":"Home & Garden",
            "subcategory":"Building Materials",
            "type":"Retail Goods"
        }
    ],
    "sg:phone":"+61 2 9849 7400",
    "sg:postcode":"2150",
    "sg:province":"NSW",
    "sg:tags":[
        "pre-mixed",
        "concrete"
    ],
    "sg:website":"http://www.metromix.com.au",
    "wof:name":"Metromix Concrete Pty Ltd",
    "wof:placetype":"venue"
},
  "geometry": {"coordinates":[151.211227417,-33.8666000366],"type":"Point"}
}