{
  "type": "Feature",
  "properties": {
    "iso:country":"AU",
    "sg:address":"Upstairs, 87a Beaumont St",
    "sg:city":"Hamilton",
    "sg:classifiers":[
        {
            "category":"Personal",
            "subcategory":"Beauty Salon",
            "type":"Services"
        }
    ],
    "sg:phone":"+61 2 4969 4422",
    "sg:postcode":"2303",
    "sg:province":"NSW",
    "sg:tags":[
        "hairdresser"
    ],
    "wof:name":"Anera Hair Studio",
    "wof:placetype":"venue"
},
  "geometry": {"coordinates":[151.74733000000001,-32.922569],"type":"Point"}
}