{
  "type": "Feature",
  "properties": {
    "addr:full":"103 Grant St Alexandra VIC 3714",
    "addr:housenumber":"103",
    "addr:postcode":"3714",
    "addr:street":"Grant St",
    "iso:country":"AU",
    "sg:address":"103 Grant St",
    "sg:city":"Alexandra",
    "sg:classifiers":[
        {
            "category":"Home & Garden",
            "subcategory":"Garden Supply",
            "type":"Retail Goods"
        }
    ],
    "sg:phone":"+61 3 5772 2536",
    "sg:postcode":"3714",
    "sg:province":"VIC",
    "sg:tags":[
        "equipment"
    ],
    "wof:name":"Alexandra Garden Centre",
    "wof:placetype":"venue"
},
  "geometry": {"coordinates":[145.70960998499999,-37.1917953491],"type":"Point"}
}