{
  "type": "Feature",
  "properties": {
    "iso:country":"AU",
    "sg:address":"188 Railway Pde",
    "sg:city":"Warrimoo",
    "sg:classifiers":[
        {
            "category":"Manufacturing",
            "subcategory":"Metals",
            "type":"Manufacturing & Wholesale Goods"
        }
    ],
    "sg:phone":"+61 2 4753 6974",
    "sg:postcode":"2774",
    "sg:province":"NSW",
    "sg:tags":[
        "steel",
        "fabricator",
        "mfrs"
    ],
    "wof:name":"Simcon Constructions Pty Ltd",
    "wof:placetype":"venue"
},
  "geometry": {"coordinates":[150.604812622,-33.732635498],"type":"Point"}
}