{
  "type": "Feature",
  "properties": {
    "addr:full":"Shop 12, Thornton Shopping Centre, Taylor Avenue Thornton NSW 2322",
    "addr:housenumber":"shop 12",
    "addr:postcode":"2322",
    "addr:street":"Thornton Shopping;Taylor Avenue",
    "iso:country":"AU",
    "sg:address":"Shop 12, Thornton Shopping Centre, Taylor Avenue",
    "sg:city":"Thornton",
    "sg:classifiers":[
        {
            "category":"Fast Food",
            "type":"Food & Drink"
        }
    ],
    "sg:phone":"+61 2 4966 5966",
    "sg:postcode":"2322",
    "sg:province":"NSW",
    "sg:tags":[
        "away",
        "take"
    ],
    "wof:name":"Thornton Take Away",
    "wof:placetype":"venue"
},
  "geometry": {"coordinates":[151.64039611800001,-32.7781906128],"type":"Point"}
}