{
  "type": "Feature",
  "properties": {
    "addr:full":"70 Northcott Drv Kotara NSW 2289",
    "addr:housenumber":"70",
    "addr:postcode":"2289",
    "addr:street":"Northcott Drv",
    "iso:country":"AU",
    "sg:address":"70 Northcott Drv",
    "sg:city":"Kotara",
    "sg:classifiers":[
        {
            "category":"Health Services",
            "subcategory":"Doctor",
            "type":"Services"
        }
    ],
    "sg:phone":"+61 2 4956 1164",
    "sg:postcode":"2289",
    "sg:province":"NSW",
    "sg:tags":[
        "medical",
        "practitioner"
    ],
    "wof:name":"Nikoletatos K Dr",
    "wof:placetype":"venue"
},
  "geometry": {"coordinates":[151.71266174300001,-32.9407463074],"type":"Point"}
}