{
  "type": "Feature",
  "properties": {
    "addr:full":"136 Industrial Rd Oak Flats NSW 2529",
    "addr:housenumber":"136",
    "addr:postcode":"2529",
    "addr:street":"Industrial Rd",
    "iso:country":"AU",
    "sg:address":"136 Industrial Rd",
    "sg:city":"Oak Flats",
    "sg:classifiers":[
        {
            "category":"Building & Trades",
            "subcategory":"Landscaping Services",
            "type":"Services"
        }
    ],
    "sg:phone":"+61 418 603 466",
    "sg:postcode":"2529",
    "sg:province":"NSW",
    "sg:tags":[
        "designer",
        "landscape",
        "contractor"
    ],
    "wof:name":"Your Backyard D.I.Y. Centre",
    "wof:placetype":"venue"
},
  "geometry": {"coordinates":[150.80711364699999,-34.5655822754],"type":"Point"}
}