{
  "type": "Feature",
  "properties": {
    "iso:country":"AU",
    "sg:address":"2 Moore Rd, Cnr Mathews Ave",
    "sg:city":"Airport West",
    "sg:classifiers":[
        {
            "category":"Retail",
            "subcategory":"Auto Rental",
            "type":"Services"
        }
    ],
    "sg:phone":"+61 3 9299 5555",
    "sg:postcode":"3042",
    "sg:province":"VIC",
    "sg:tags":[
        "car",
        "hire",
        "minibus"
    ],
    "wof:name":"Budget Rent A Car",
    "wof:placetype":"venue"
},
  "geometry": {"coordinates":[144.89193725600001,-37.7168807983],"type":"Point"}
}