{
  "type": "Feature",
  "properties": {
    "addr:full":"152 Mitchell St Northcote VIC 3070",
    "addr:housenumber":"152",
    "addr:postcode":"3070",
    "addr:street":"Mitchell St",
    "iso:country":"AU",
    "sg:address":"152 Mitchell St",
    "sg:city":"Northcote",
    "sg:classifiers":[
        {
            "category":"Shopping",
            "subcategory":"Stationery & Office Supplies",
            "type":"Retail Goods"
        }
    ],
    "sg:phone":"+61 3 9486 1190",
    "sg:postcode":"3070",
    "sg:province":"VIC",
    "sg:tags":[
        "partition"
    ],
    "wof:name":"Demountable Office Partitions",
    "wof:placetype":"venue"
},
  "geometry": {"coordinates":[145.009064,-37.773388],"type":"Point"}
}