{
  "type": "Feature",
  "properties": {
    "iso:country":"AU",
    "sg:address":"9 Albion St",
    "sg:city":"Waverley",
    "sg:classifiers":[
        {
            "category":"Restaurant",
            "type":"Food & Drink"
        }
    ],
    "sg:phone":"+61 2 9389 6687",
    "sg:postcode":"2024",
    "sg:province":"NSW",
    "wof:name":"Chow King",
    "wof:placetype":"venue"
},
  "geometry": {"coordinates":[151.25468444800001,-33.9026565552],"type":"Point"}
}