{
  "type": "Feature",
  "properties": {
    "iso:country":"AU",
    "sg:address":"83 A Fitzroy St",
    "sg:city":"St Kilda",
    "sg:classifiers":[
        {
            "category":"Fast Food",
            "type":"Food & Drink"
        }
    ],
    "sg:phone":"+61 3 9534 5700",
    "sg:postcode":"3182",
    "sg:province":"VIC",
    "sg:tags":[
        "away",
        "take"
    ],
    "wof:name":"Skwidz",
    "wof:placetype":"venue"
},
  "geometry": {"coordinates":[144.97958374000001,-37.858455658],"type":"Point"}
}