{
  "type": "Feature",
  "properties": {
    "addr:full":"137 Franklin St Eltham VIC 3095",
    "addr:housenumber":"137",
    "addr:postcode":"3095",
    "addr:street":"Franklin St",
    "iso:country":"AU",
    "sg:address":"137 Franklin St",
    "sg:city":"Eltham",
    "sg:classifiers":[
        {
            "category":"Building & Trades",
            "subcategory":"Pest Control",
            "type":"Services"
        }
    ],
    "sg:phone":"+61 3 9431 4765",
    "sg:postcode":"3095",
    "sg:province":"VIC",
    "sg:tags":[
        "technical",
        "consultant"
    ],
    "wof:name":"Carew Creative Solutions",
    "wof:placetype":"venue"
},
  "geometry": {"coordinates":[145.15345764200001,-37.7224197388],"type":"Point"}
}