{
  "type": "Feature",
  "properties": {
    "addr:full":"16 Strathwyn St Brendale QLD 4500",
    "addr:housenumber":"16",
    "addr:postcode":"4500",
    "addr:street":"Strathwyn St",
    "iso:country":"AU",
    "sg:address":"16 Strathwyn St",
    "sg:city":"Brendale",
    "sg:classifiers":[
        {
            "category":"Retail",
            "subcategory":"Storage",
            "type":"Services"
        }
    ],
    "sg:phone":"+61 7 3205 1166",
    "sg:postcode":"4500",
    "sg:province":"QLD",
    "sg:tags":[
        "removal",
        "furniture"
    ],
    "wof:name":"Elite Self Storage Strathpine Pty Ltd",
    "wof:placetype":"venue"
},
  "geometry": {"coordinates":[152.97877502399999,-27.32056427],"type":"Point"}
}