{
  "type": "Feature",
  "properties": {
    "addr:full":"PO Box 4033 Wagstaffe NSW 2257",
    "addr:postcode":"2257",
    "iso:country":"AU",
    "sg:address":"PO Box 4033",
    "sg:city":"Wagstaffe",
    "sg:classifiers":[
        {
            "category":"Real Estate",
            "subcategory":"Architect",
            "type":"Services"
        }
    ],
    "sg:phone":"+61 2 4360 1731",
    "sg:postcode":"2257",
    "sg:province":"NSW",
    "sg:tags":[
        "building",
        "designer"
    ],
    "wof:name":"Keelty Design",
    "wof:placetype":"venue"
},
  "geometry": {"coordinates":[151.36143493599999,-33.523891449],"type":"Point"}
}