{
  "type": "Feature",
  "properties": {
    "addr:full":"Chapman Shopping Cntr Chapman ACT 2611",
    "addr:postcode":"2611",
    "iso:country":"AU",
    "sg:address":"Chapman Shopping Cntr",
    "sg:city":"Chapman",
    "sg:classifiers":[
        {
            "category":"Shopping",
            "subcategory":"Bicycles & Sporting Goods",
            "type":"Retail Goods"
        }
    ],
    "sg:phone":"+61 2 6288 4226",
    "sg:postcode":"2611",
    "sg:province":"ACT",
    "sg:tags":[
        "chemical",
        "equipment",
        "pool",
        "swimming"
    ],
    "wof:name":"Cool Pools Of Canberra",
    "wof:placetype":"venue"
},
  "geometry": {"coordinates":[149.04080200199999,-35.3561630249],"type":"Point"}
}