{
  "type": "Feature",
  "properties": {
    "addr:full":"71 Bourke Rd Clarinda VIC 3169",
    "addr:housenumber":"71",
    "addr:postcode":"3169",
    "addr:street":"Bourke Rd",
    "iso:country":"AU",
    "sg:address":"71 Bourke Rd",
    "sg:city":"Clarinda",
    "sg:classifiers":[
        {
            "category":"Social Services",
            "subcategory":"Retirement Home",
            "type":"Services"
        }
    ],
    "sg:phone":"+61 3 9551 2293",
    "sg:postcode":"3169",
    "sg:province":"VIC",
    "sg:tags":[
        "village"
    ],
    "wof:name":"Clarinda Retirement Village",
    "wof:placetype":"venue"
},
  "geometry": {"coordinates":[145.10292053200001,-37.9411048889],"type":"Point"}
}