{
  "type": "Feature",
  "properties": {
    "addr:full":"Cnr Burwood Hwy & Middleborough Rd Burwood East VIC 3151",
    "addr:postcode":"3151",
    "addr:street":"Burwood Hwy & Middleborough Rd",
    "iso:country":"AU",
    "sg:address":"Cnr Burwood Hwy & Middleborough Rd",
    "sg:city":"Burwood East",
    "sg:classifiers":[
        {
            "category":"Travel",
            "subcategory":"Travel Agent",
            "type":"Entertainment"
        }
    ],
    "sg:phone":"+61 3 9808 1177",
    "sg:postcode":"3151",
    "sg:province":"VIC",
    "sg:tags":[
        "consultant"
    ],
    "wof:name":"East Burwood Travel Pty Ltd",
    "wof:placetype":"venue"
},
  "geometry": {"coordinates":[145.15136718799999,-37.8526496887],"type":"Point"}
}