{
  "type": "Feature",
  "properties": {
    "addr:full":"Suite 6, 301- 303 Albany Hwy Victoria Park WA 6100",
    "addr:housenumber":"301 303",
    "addr:postcode":"6100",
    "addr:street":"Albany Hwy Victoria",
    "iso:country":"AU",
    "sg:address":"Suite 6, 301- 303 Albany Hwy",
    "sg:city":"Victoria Park",
    "sg:classifiers":[
        {
            "category":"Personal",
            "type":"Services"
        }
    ],
    "sg:phone":"+61 408 777 622",
    "sg:postcode":"6100",
    "sg:province":"WA",
    "sg:tags":[
        "wallpapering",
        "wallcovering"
    ],
    "wof:name":"Admire Painting Services",
    "wof:placetype":"venue"
},
  "geometry": {"coordinates":[115.895690918,-31.9726352692],"type":"Point"}
}