{
  "type": "Feature",
  "properties": {
    "iso:country":"AU",
    "sg:address":"1 B Mccoll St",
    "sg:city":"Walkerston",
    "sg:classifiers":[
        {
            "category":"Shopping",
            "subcategory":"Party Supplies",
            "type":"Retail Goods"
        }
    ],
    "sg:phone":"+61 7 4959 2973",
    "sg:postcode":"4751",
    "sg:province":"QLD",
    "sg:tags":[
        "children's"
    ],
    "wof:name":"Magical Balloon Man",
    "wof:placetype":"venue"
},
  "geometry": {"coordinates":[149.064911,-21.158766],"type":"Point"}
}