{
  "type": "Feature",
  "properties": {
    "addr:full":"9 Peacock St Leichhardt QLD 4305",
    "addr:housenumber":"9",
    "addr:postcode":"4305",
    "addr:street":"Peacock St",
    "iso:country":"AU",
    "sg:address":"9 Peacock St",
    "sg:city":"Leichhardt",
    "sg:classifiers":[
        {
            "category":"Building & Trades",
            "subcategory":"Construction",
            "type":"Services"
        }
    ],
    "sg:phone":"+61 419 643 670",
    "sg:postcode":"4305",
    "sg:province":"QLD",
    "sg:tags":[
        "welding"
    ],
    "wof:name":"TAC Welding & Fabrication",
    "wof:placetype":"venue"
},
  "geometry": {"coordinates":[152.736328125,-27.6303825378],"type":"Point"}
}