{
  "type": "Feature",
  "properties": {
    "iso:country":"AU",
    "sg:address":"5 Cook Ave",
    "sg:city":"Hillarys",
    "sg:classifiers":[
        {
            "category":"Professional",
            "subcategory":"Computer Services",
            "type":"Services"
        }
    ],
    "sg:phone":"+61 8 9403 2882",
    "sg:postcode":"6025",
    "sg:province":"WA",
    "sg:tags":[
        "repairs",
        "upgrade",
        "equipment"
    ],
    "wof:name":"Computer Shop The",
    "wof:placetype":"venue"
},
  "geometry": {"coordinates":[115.752403259,-31.8021297455],"type":"Point"}
}