{
  "type": "Feature",
  "properties": {
    "addr:full":"U20/ 16 Henley Rd Homebush West NSW 2140",
    "addr:postcode":"2140",
    "addr:street":"/ 16 Henley Rd",
    "iso:country":"AU",
    "sg:address":"U20/ 16 Henley Rd",
    "sg:city":"Homebush West",
    "sg:classifiers":[
        {
            "category":"Real Estate",
            "subcategory":"Real Estate Agent",
            "type":"Services"
        }
    ],
    "sg:phone":"+61 2 9764 1866",
    "sg:postcode":"2140",
    "sg:province":"NSW",
    "wof:name":"Highgate Real Estate",
    "wof:placetype":"venue"
},
  "geometry": {"coordinates":[151.069824219,-33.8663330078],"type":"Point"}
}