{
  "type": "Feature",
  "properties": {
    "addr:full":"9 Central Ave Nowra South NSW 2541",
    "addr:housenumber":"9",
    "addr:postcode":"2541",
    "addr:street":"Central Ave",
    "iso:country":"AU",
    "sg:address":"9 Central Ave",
    "sg:city":"Nowra South",
    "sg:classifiers":[
        {
            "category":"Utilities",
            "subcategory":"Recycling",
            "type":"Services"
        }
    ],
    "sg:phone":"+61 2 4423 7300",
    "sg:postcode":"2541",
    "sg:province":"NSW",
    "wof:name":"South Coast Resources Pty Ltd",
    "wof:placetype":"venue"
},
  "geometry": {"coordinates":[150.59437560999999,-34.9131011963],"type":"Point"}
}