{
  "type": "Feature",
  "properties": {
    "addr:full":"2/26- 30 Kayleigh Drv Maroochydore QLD 4558",
    "addr:housenumber":"/;30",
    "addr:postcode":"4558",
    "addr:street":"26;Kayleigh Drv",
    "iso:country":"AU",
    "sg:address":"2/26- 30 Kayleigh Drv",
    "sg:city":"Maroochydore",
    "sg:classifiers":[
        {
            "category":"Autos & Motor Vehicles",
            "subcategory":"Auto Supplies",
            "type":"Retail Goods"
        }
    ],
    "sg:phone":"+61 7 5443 1022",
    "sg:postcode":"4558",
    "sg:province":"QLD",
    "sg:tags":[
        "paint",
        "automotive"
    ],
    "wof:name":"Discount Automotive Paints",
    "wof:placetype":"venue"
},
  "geometry": {"coordinates":[153.08920288100001,-26.6696777344],"type":"Point"}
}