{
  "type": "Feature",
  "properties": {
    "addr:full":"25 Coolaroo Crs Jindalee QLD 4074",
    "addr:housenumber":"25",
    "addr:postcode":"4074",
    "addr:street":"Coolaroo Crs",
    "iso:country":"AU",
    "sg:address":"25 Coolaroo Crs",
    "sg:city":"Jindalee",
    "sg:classifiers":[
        {
            "category":"Education",
            "subcategory":"Special Training",
            "type":"Public Place"
        }
    ],
    "sg:phone":"+61 7 3376 1576",
    "sg:postcode":"4074",
    "sg:province":"QLD",
    "sg:tags":[
        "development"
    ],
    "wof:name":"Personal Best Systems",
    "wof:placetype":"venue"
},
  "geometry": {"coordinates":[152.942230225,-27.5386600494],"type":"Point"}
}