{
  "type": "Feature",
  "properties": {
    "iso:country":"AU",
    "sg:address":"4 Fonts Pl",
    "sg:city":"Embleton",
    "sg:classifiers":[
        {
            "category":"Building & Trades",
            "subcategory":"Construction",
            "type":"Services"
        }
    ],
    "sg:phone":"+61 8 6278 3750",
    "sg:postcode":"6062",
    "sg:province":"WA",
    "sg:tags":[
        "joinery"
    ],
    "wof:name":"Swisswood Carpentry Joinery Pty Ltd",
    "wof:placetype":"venue"
},
  "geometry": {"coordinates":[115.922828674,-31.8960075378],"type":"Point"}
}