{
  "type": "Feature",
  "properties": {
    "addr:full":"Lot 1 Gnangara Drv Waikiki WA 6169",
    "addr:postcode":"6169",
    "addr:street":"Gnangara Drv",
    "iso:country":"AU",
    "sg:address":"Lot 1 Gnangara Drv",
    "sg:city":"Waikiki",
    "sg:classifiers":[
        {
            "category":"Autos & Motor Vehicles",
            "subcategory":"Fuel & Gas Station",
            "type":"Retail Goods"
        }
    ],
    "sg:phone":"+61 8 9592 8088",
    "sg:postcode":"6169",
    "sg:province":"WA",
    "wof:name":"Shell Select Waikiki",
    "wof:placetype":"venue"
},
  "geometry": {"coordinates":[115.753258,-32.315292],"type":"Point"}
}