{
  "type": "Feature",
  "properties": {
    "addr:full":"Shed 2/ 8 Winton St Dalby QLD 4405",
    "addr:housenumber":"2 / 8",
    "addr:postcode":"4405",
    "addr:street":"Winton St",
    "iso:country":"AU",
    "sg:address":"Shed 2/ 8 Winton St",
    "sg:city":"Dalby",
    "sg:classifiers":[
        {
            "category":"Professional",
            "type":"Services"
        }
    ],
    "sg:phone":"+61 7 4662 1622",
    "sg:postcode":"4405",
    "sg:province":"QLD",
    "sg:tags":[
        "control",
        "equipment",
        "traffic"
    ],
    "wof:name":"Western Downs Traffic Control",
    "wof:placetype":"venue"
},
  "geometry": {"coordinates":[151.278244019,-27.1986675262],"type":"Point"}
}