{
  "type": "Feature",
  "properties": {
    "addr:full":"156 Allan St Kyabram VIC 3620",
    "addr:housenumber":"156",
    "addr:postcode":"3620",
    "addr:street":"Allan St",
    "iso:country":"AU",
    "sg:address":"156 Allan St",
    "sg:city":"Kyabram",
    "sg:classifiers":[
        {
            "category":"Shopping",
            "subcategory":"Clothing, Apparel, & Fashions",
            "type":"Retail Goods"
        }
    ],
    "sg:phone":"+61 3 5852 2911",
    "sg:postcode":"3620",
    "sg:province":"VIC",
    "sg:tags":[
        "lady",
        "wear"
    ],
    "wof:name":"Fashion Girl Pty Ltd",
    "wof:placetype":"venue"
},
  "geometry": {"coordinates":[145.04579162600001,-36.3135795593],"type":"Point"}
}