{
  "type": "Feature",
  "properties": {
    "iso:country":"AU",
    "sg:address":"25 Fernbrook Pl",
    "sg:city":"Castle Hill",
    "sg:classifiers":[
        {
            "category":"Real Estate",
            "subcategory":"Architect",
            "type":"Services"
        }
    ],
    "sg:phone":"+61 2 8850 3502",
    "sg:postcode":"2154",
    "sg:province":"NSW",
    "sg:tags":[
        "building",
        "designer"
    ],
    "wof:name":"Consulting Drafting Services",
    "wof:placetype":"venue"
},
  "geometry": {"coordinates":[151.023834228,-33.7122421265],"type":"Point"}
}