{
  "type": "Feature",
  "properties": {
    "addr:full":"6/ 935 Station St Box Hill North VIC 3129",
    "addr:housenumber":"/ 935",
    "addr:postcode":"3129",
    "addr:street":"Station St",
    "iso:country":"AU",
    "sg:address":"6/ 935 Station St",
    "sg:city":"Box Hill North",
    "sg:classifiers":[
        {
            "category":"Banks & Credit Unions",
            "subcategory":"Bank",
            "type":"Services"
        }
    ],
    "sg:phone":"+61 3 9899 0300",
    "sg:postcode":"3129",
    "sg:province":"VIC",
    "sg:tags":[
        "broker",
        "mortgage"
    ],
    "wof:name":"Smartline Home Loans (Victoria)",
    "wof:placetype":"venue"
},
  "geometry": {"coordinates":[145.12661743199999,-37.802116394],"type":"Point"}
}