{
  "type": "Feature",
  "properties": {
    "iso:country":"AU",
    "sg:address":"8 Hedlund St",
    "sg:city":"Revesby",
    "sg:classifiers":[
        {
            "category":"Organizations",
            "subcategory":"Non-profit Organization",
            "type":"Services"
        }
    ],
    "sg:phone":"+61 2 9774 1692",
    "sg:postcode":"2212",
    "sg:province":"NSW",
    "sg:tags":[
        "support",
        "disability",
        "organisation"
    ],
    "wof:name":"Bankstown East Hills Handicapped Association",
    "wof:placetype":"venue"
},
  "geometry": {"coordinates":[151.01507599999999,-33.95446],"type":"Point"}
}