{
  "type": "Feature",
  "properties": {
    "addr:full":"Nicholson Pde Cronulla NSW 2230",
    "addr:postcode":"2230",
    "addr:street":"Nicholson",
    "iso:country":"AU",
    "sg:address":"Nicholson Pde",
    "sg:city":"Cronulla",
    "sg:classifiers":[
        {
            "category":"Cafe",
            "type":"Food & Drink"
        }
    ],
    "sg:phone":"+61 2 9544 3805",
    "sg:postcode":"2230",
    "sg:province":"NSW",
    "wof:name":"Gunnamatta Park Cafe",
    "wof:placetype":"venue"
},
  "geometry": {"coordinates":[151.15304565400001,-34.0569114685],"type":"Point"}
}