{
  "type": "Feature",
  "properties": {
    "addr:full":"1 Bourke St Essendon VIC 3040",
    "addr:housenumber":"1",
    "addr:postcode":"3040",
    "addr:street":"Bourke St",
    "iso:country":"AU",
    "sg:address":"1 Bourke St",
    "sg:city":"Essendon",
    "sg:classifiers":[
        {
            "category":"Building & Trades",
            "subcategory":"Plumbing",
            "type":"Services"
        }
    ],
    "sg:phone":"+61 3 9331 2168",
    "sg:postcode":"3040",
    "sg:province":"VIC",
    "sg:tags":[
        "plumber",
        "gasfitters"
    ],
    "wof:name":"Rosehill Road Plumbing",
    "wof:placetype":"venue"
},
  "geometry": {"coordinates":[144.886276245,-37.7537956238],"type":"Point"}
}