{
  "type": "Feature",
  "properties": {
    "addr:full":"29 Clarence St Geelong West VIC 3218",
    "addr:housenumber":"29",
    "addr:postcode":"3218",
    "addr:street":"Clarence St",
    "iso:country":"AU",
    "sg:address":"29 Clarence St",
    "sg:city":"Geelong West",
    "sg:classifiers":[
        {
            "category":"Government",
            "subcategory":"Court House",
            "type":"Public Place"
        }
    ],
    "sg:phone":"+61 3 5222 6969",
    "sg:postcode":"3218",
    "sg:province":"VIC",
    "sg:tags":[
        "personal",
        "marriage",
        "family",
        "counselling"
    ],
    "wof:name":"Sanctuary Conuselling Centre",
    "wof:placetype":"venue"
},
  "geometry": {"coordinates":[144.345703125,-38.1395645142],"type":"Point"}
}