{
  "type": "Feature",
  "properties": {
    "iso:country":"AU",
    "sg:address":"1-3 Lennox St",
    "sg:city":"Moorabbin",
    "sg:classifiers":[
        {
            "category":"Shopping",
            "type":"Retail Goods"
        }
    ],
    "sg:phone":"+61 3 9553 2884",
    "sg:postcode":"3189",
    "sg:province":"VIC",
    "sg:tags":[
        "product",
        "plastic"
    ],
    "wof:name":"J & C Plastics Recycling",
    "wof:placetype":"venue"
},
  "geometry": {"coordinates":[145.06570434599999,-37.9422187805],"type":"Point"}
}