{
  "type": "Feature",
  "properties": {
    "addr:full":"Cnr Upper Lyndale St & Roselea Rd Shailer Park QLD 4128",
    "addr:postcode":"4128",
    "addr:street":"Cnr Upper Lyndale St & Roselea Rd",
    "iso:country":"AU",
    "sg:address":"Cnr Upper Lyndale St & Roselea Rd",
    "sg:city":"Shailer Park",
    "sg:classifiers":[
        {
            "category":"Fast Food",
            "type":"Food & Drink"
        }
    ],
    "sg:phone":"+61 7 3801 4833",
    "sg:postcode":"4128",
    "sg:province":"QLD",
    "sg:tags":[
        "away",
        "take"
    ],
    "wof:name":"Greenery Cafe Chinese & Thai Takeaway",
    "wof:placetype":"venue"
},
  "geometry": {"coordinates":[153.17251586899999,-27.6437072754],"type":"Point"}
}