{
  "type": "Feature",
  "properties": {
    "addr:full":"Unit 11/ 45 Bassett St West Mona Vale NSW 2103",
    "addr:housenumber":"/ 45",
    "addr:postcode":"2103",
    "addr:street":"Bassett St West",
    "iso:country":"AU",
    "sg:address":"Unit 11/ 45 Bassett St",
    "sg:city":"West Mona Vale",
    "sg:classifiers":[
        {
            "category":"Manufacturing",
            "subcategory":"Tools & Machinery",
            "type":"Manufacturing & Wholesale Goods"
        }
    ],
    "sg:phone":"+61 2 9729 3400",
    "sg:postcode":"2103",
    "sg:province":"NSW",
    "wof:name":"Proto Professional Tools (U.S.A)",
    "wof:placetype":"venue"
},
  "geometry": {"coordinates":[151.31048584000001,-33.6736297607],"type":"Point"}
}