{
  "type": "Feature",
  "properties": {
    "iso:country":"AU",
    "sg:address":"11B Viking Crt",
    "sg:city":"Cheltenham",
    "sg:classifiers":[
        {
            "category":"Professional",
            "subcategory":"Engineering",
            "type":"Services"
        }
    ],
    "sg:phone":"+61 3 9553 7142",
    "sg:postcode":"3192",
    "sg:province":"VIC",
    "sg:tags":[
        "engineer"
    ],
    "wof:name":"L.M Hitchcock Marine General Engineering Pty Ltd",
    "wof:placetype":"venue"
},
  "geometry": {"coordinates":[145.06803894000001,-37.95104599],"type":"Point"}
}