{
  "type": "Feature",
  "properties": {
    "addr:full":"PO Box 61 Irymple VIC 3498",
    "addr:postcode":"3498",
    "iso:country":"AU",
    "sg:address":"PO Box 61",
    "sg:city":"Irymple",
    "sg:classifiers":[
        {
            "category":"Home & Garden",
            "subcategory":"Building Materials",
            "type":"Retail Goods"
        }
    ],
    "sg:phone":"+61 419 186 773",
    "sg:postcode":"3498",
    "sg:province":"VIC",
    "sg:tags":[
        "fencing"
    ],
    "wof:name":"I.M. Fencing",
    "wof:placetype":"venue"
},
  "geometry": {"coordinates":[142.17286682100001,-34.2372512817],"type":"Point"}
}