{
  "type": "Feature",
  "properties": {
    "addr:full":"Endeavour House 1 Franklin St Manuka ACT 2603",
    "addr:housenumber":"1",
    "addr:postcode":"2603",
    "addr:street":"Franklin St",
    "iso:country":"AU",
    "sg:address":"Endeavour House 1 Franklin St",
    "sg:city":"Manuka",
    "sg:classifiers":[
        {
            "category":"Organizations",
            "subcategory":"Professional Association",
            "type":"Services"
        }
    ],
    "sg:phone":"+61 2 6239 6999",
    "sg:postcode":"2603",
    "sg:province":"ACT",
    "sg:tags":[
        "web",
        "internet"
    ],
    "wof:name":"Roar",
    "wof:placetype":"venue"
},
  "geometry": {"coordinates":[149.13177490199999,-35.3430557251],"type":"Point"}
}