{
  "type": "Feature",
  "properties": {
    "addr:full":"57 McDonald Rd Windsor QLD 4030",
    "addr:housenumber":"57",
    "addr:postcode":"4030",
    "addr:street":"Mcdonald Rd",
    "iso:country":"AU",
    "sg:address":"57 McDonald Rd",
    "sg:city":"Windsor",
    "sg:classifiers":[
        {
            "category":"Real Estate",
            "subcategory":"Real Estate Agent",
            "type":"Services"
        }
    ],
    "sg:phone":"+61 7 3357 7877",
    "sg:postcode":"4030",
    "sg:province":"QLD",
    "sg:tags":[
        "handyman's",
        "equipment",
        "hire",
        "builders",
        "contractor"
    ],
    "wof:name":"Brisbane Scaffold Hire Pty Limited",
    "wof:placetype":"venue"
},
  "geometry": {"coordinates":[153.03866600000001,-27.431984],"type":"Point"}
}