{
  "type": "Feature",
  "properties": {
    "addr:full":"6 Waddikee Rd Lonsdale SA 5160",
    "addr:housenumber":"6",
    "addr:postcode":"5160",
    "addr:street":"Waddikee Rd",
    "iso:country":"AU",
    "sg:address":"6 Waddikee Rd",
    "sg:city":"Lonsdale",
    "sg:classifiers":[
        {
            "category":"Communications",
            "subcategory":"Film & Video Production",
            "type":"Services"
        }
    ],
    "sg:phone":"+61 8 8384 4331",
    "sg:postcode":"5160",
    "sg:province":"SA",
    "sg:tags":[
        "plating",
        "silver"
    ],
    "wof:name":"A Class Metal Finishers Pty Ltd",
    "wof:placetype":"venue"
},
  "geometry": {"coordinates":[138.498214722,-35.1103401184],"type":"Point"}
}