{
  "type": "Feature",
  "properties": {
    "addr:full":"Suite 7,47 51 Baan Baan St Dapto NSW 2530",
    "addr:housenumber":"7,47 51",
    "addr:postcode":"2530",
    "addr:street":"Baan Baan St",
    "iso:country":"AU",
    "sg:address":"Suite 7,47 51 Baan Baan St",
    "sg:city":"Dapto",
    "sg:classifiers":[
        {
            "category":"Health Services",
            "subcategory":"Optometrist",
            "type":"Services"
        }
    ],
    "sg:phone":"+61 2 4261 8855",
    "sg:postcode":"2530",
    "sg:province":"NSW",
    "wof:name":"Malinda Halley Optometrists",
    "wof:placetype":"venue"
},
  "geometry": {"coordinates":[150.79600524899999,-34.4933280945],"type":"Point"}
}