{
  "type": "Feature",
  "properties": {
    "addr:full":"Shop 105 Trinity Arcade Perth WA 6000",
    "addr:housenumber":"105",
    "addr:postcode":"6000",
    "addr:street":"Trinity Arcade",
    "iso:country":"AU",
    "sg:address":"Shop 105 Trinity Arcade",
    "sg:city":"Perth",
    "sg:classifiers":[
        {
            "category":"Donuts",
            "subcategory":"None",
            "type":"Food & Drink"
        }
    ],
    "sg:phone":"+61 8 9322 4572",
    "sg:postcode":"6000",
    "sg:province":"WA",
    "sg:tags":[
        "die",
        "engraver",
        "sinker"
    ],
    "wof:name":"Jon's Shoe Repair",
    "wof:placetype":"venue"
},
  "geometry": {"coordinates":[115.880432129,-31.9612197876],"type":"Point"}
}