{
  "type": "Feature",
  "properties": {
    "iso:country":"AU",
    "sg:address":"24 Comport St",
    "sg:city":"Portsmith",
    "sg:classifiers":[
        {
            "category":"Retail",
            "subcategory":"Storage",
            "type":"Services"
        }
    ],
    "sg:phone":"+61 7 4051 6000",
    "sg:postcode":"4870",
    "sg:province":"QLD",
    "sg:tags":[
        "cold"
    ],
    "wof:name":"Harbourside Cold Stores",
    "wof:placetype":"venue"
},
  "geometry": {"coordinates":[145.77229309099999,-16.9378623962],"type":"Point"}
}