{
  "type": "Feature",
  "properties": {
    "iso:country":"AU",
    "sg:address":"15 A Brighton Rd",
    "sg:city":"St Kilda",
    "sg:classifiers":[
        {
            "category":"Retail",
            "subcategory":"Storage",
            "type":"Services"
        }
    ],
    "sg:phone":"+61 3 9537 2081",
    "sg:postcode":"3182",
    "sg:province":"VIC",
    "sg:tags":[
        "equipment",
        "computer",
        "secondhand"
    ],
    "wof:name":"Notebooks Galore",
    "wof:placetype":"venue"
},
  "geometry": {"coordinates":[144.986984253,-37.8682136536],"type":"Point"}
}