{
  "type": "Feature",
  "properties": {
    "addr:full":"4 Fingal Rd Fingal Head NSW 2487",
    "addr:housenumber":"4",
    "addr:postcode":"2487",
    "addr:street":"Fingal Rd",
    "iso:country":"AU",
    "sg:address":"4 Fingal Rd",
    "sg:city":"Fingal Head",
    "sg:classifiers":[
        {
            "category":"Building & Trades",
            "subcategory":"Construction",
            "type":"Services"
        }
    ],
    "sg:phone":"+61 7 5523 0911",
    "sg:postcode":"2487",
    "sg:province":"NSW",
    "sg:tags":[
        "concrete",
        "contractor"
    ],
    "wof:name":"Lion Concrete Constructions",
    "wof:placetype":"venue"
},
  "geometry": {"coordinates":[153.55770874000001,-28.2245903015],"type":"Point"}
}