{
  "type": "Feature",
  "properties": {
    "addr:full":"1420 Frankston- Flinders Rd Tyabb VIC 3913",
    "addr:housenumber":"1420",
    "addr:postcode":"3913",
    "addr:street":"Frankston Flinders Rd",
    "iso:country":"AU",
    "sg:address":"1420 Frankston- Flinders Rd",
    "sg:city":"Tyabb",
    "sg:classifiers":[
        {
            "category":"Manufacturing",
            "subcategory":"Wood Products",
            "type":"Manufacturing & Wholesale Goods"
        }
    ],
    "sg:phone":"+61 3 5977 4331",
    "sg:postcode":"3913",
    "sg:province":"VIC",
    "sg:tags":[
        "machinist"
    ],
    "wof:name":"Peninsula Wood Machining",
    "wof:placetype":"venue"
},
  "geometry": {"coordinates":[145.19036865199999,-38.252040863],"type":"Point"}
}