{
  "type": "Feature",
  "properties": {
    "iso:country":"AU",
    "sg:address":"70 Albert St",
    "sg:city":"Berry",
    "sg:classifiers":[
        {
            "category":"Shopping",
            "subcategory":"Crafts & Fabrics",
            "type":"Retail Goods"
        }
    ],
    "sg:phone":"+61 2 4464 3387",
    "sg:postcode":"2535",
    "sg:province":"NSW",
    "sg:tags":[
        "supply"
    ],
    "wof:name":"Berry Patchwork Shop The",
    "wof:placetype":"venue"
},
  "geometry": {"coordinates":[150.697753906,-34.7747573853],"type":"Point"}
}