{
  "type": "Feature",
  "properties": {
    "iso:country":"AU",
    "sg:address":"24 Evans Ave",
    "sg:city":"North Mackay",
    "sg:classifiers":[
        {
            "category":"Shopping",
            "subcategory":"Gifts & Souvenirs",
            "type":"Retail Goods"
        }
    ],
    "sg:phone":"+61 7 4957 2022",
    "sg:postcode":"4740",
    "sg:province":"QLD",
    "sg:tags":[
        "print",
        "poster",
        "pictures"
    ],
    "wof:name":"T J Picture Framing",
    "wof:placetype":"venue"
},
  "geometry": {"coordinates":[149.183456,-21.120647],"type":"Point"}
}