{
  "type": "Feature",
  "properties": {
    "addr:full":"65 Norrie Ave Whyalla SA 5600",
    "addr:housenumber":"65",
    "addr:postcode":"5600",
    "addr:street":"Norrie Ave",
    "iso:country":"AU",
    "sg:address":"65 Norrie Ave",
    "sg:city":"Whyalla",
    "sg:classifiers":[
        {
            "category":"Health Services",
            "subcategory":"Doctor",
            "type":"Services"
        }
    ],
    "sg:phone":"+61 8 8645 8564",
    "sg:postcode":"5600",
    "sg:province":"SA",
    "sg:tags":[
        "medical",
        "practitioner"
    ],
    "wof:name":"Patel Dr. M.",
    "wof:placetype":"venue"
},
  "geometry": {"coordinates":[137.55204800000001,-33.037663],"type":"Point"}
}