{
  "type": "Feature",
  "properties": {
    "iso:country":"AU",
    "sg:address":"Lvl 1 111 Queensbridge St",
    "sg:city":"Southbank",
    "sg:classifiers":[
        {
            "category":"Professional",
            "subcategory":"Art Services",
            "type":"Services"
        }
    ],
    "sg:phone":"+61 3 9682 1468",
    "sg:postcode":"3006",
    "sg:province":"VIC",
    "sg:tags":[
        "interior",
        "designer"
    ],
    "wof:name":"Thomson Lilley Design Pty Ltd",
    "wof:placetype":"venue"
},
  "geometry": {"coordinates":[144.96052551299999,-37.8249740601],"type":"Point"}
}