{
  "type": "Feature",
  "properties": {
    "iso:country":"AU",
    "sg:address":"Keppel Bay Business Centre 69 Queen St",
    "sg:city":"Yeppoon",
    "sg:classifiers":[
        {
            "category":"Professional",
            "subcategory":"Accounting & Tax Preparation",
            "type":"Services"
        }
    ],
    "sg:phone":"+61 7 4924 9100",
    "sg:postcode":"4703",
    "sg:province":"QLD",
    "sg:tags":[
        "accountant",
        "auditor"
    ],
    "wof:name":"Kennas Financial Services Pty Ltd",
    "wof:placetype":"venue"
},
  "geometry": {"coordinates":[150.74093627900001,-23.1294078827],"type":"Point"}
}