{
  "type": "Feature",
  "properties": {
    "addr:full":"71- 83 Blackall Range Rd Nambour QLD 4560",
    "addr:housenumber":"83",
    "addr:postcode":"4560",
    "addr:street":"Blackall Range Rd",
    "iso:country":"AU",
    "sg:address":"71- 83 Blackall Range Rd",
    "sg:city":"Nambour",
    "sg:classifiers":[
        {
            "category":"Farming",
            "subcategory":"Nursery",
            "type":"Manufacturing & Wholesale Goods"
        }
    ],
    "sg:phone":"+61 7 5442 1611",
    "sg:postcode":"4560",
    "sg:province":"QLD",
    "wof:name":"Birdwood Nursery",
    "wof:placetype":"venue"
},
  "geometry": {"coordinates":[152.954315186,-26.6210021973],"type":"Point"}
}