{
  "type": "Feature",
  "properties": {
    "addr:full":"24 Chase Rd Turramurra NSW 2074",
    "addr:housenumber":"24",
    "addr:postcode":"2074",
    "addr:street":"Chase Rd",
    "iso:country":"AU",
    "sg:address":"24 Chase Rd",
    "sg:city":"Turramurra",
    "sg:classifiers":[
        {
            "category":"Health Services",
            "subcategory":"Doctor",
            "type":"Services"
        }
    ],
    "sg:phone":"+61 2 9489 2228",
    "sg:postcode":"2074",
    "sg:province":"NSW",
    "sg:tags":[
        "medical",
        "practitioner"
    ],
    "wof:name":"Douglas Godfrey",
    "wof:placetype":"venue"
},
  "geometry": {"coordinates":[151.129196167,-33.7326011658],"type":"Point"}
}