{
  "type": "Feature",
  "properties": {
    "addr:full":"2-4 Verran Tce Port Lincoln SA 5606",
    "addr:housenumber":"2-4",
    "addr:postcode":"5606",
    "addr:street":"Verran Tce",
    "iso:country":"AU",
    "sg:address":"2-4 Verran Tce",
    "sg:city":"Port Lincoln",
    "sg:classifiers":[
        {
            "category":"Autos & Motor Vehicles",
            "subcategory":"Auto Supplies",
            "type":"Retail Goods"
        }
    ],
    "sg:phone":"+61 8 8683 4555",
    "sg:postcode":"5606",
    "sg:province":"SA",
    "sg:tags":[
        "part",
        "cycles",
        "accessory"
    ],
    "wof:name":"Pointer Motorcycles",
    "wof:placetype":"venue"
},
  "geometry": {"coordinates":[135.85185200000001,-34.740231],"type":"Point"}
}