{
  "type": "Feature",
  "properties": {
    "iso:country":"AU",
    "sg:address":"94 Ford St",
    "sg:city":"Beechworth",
    "sg:classifiers":[
        {
            "category":"Communications",
            "subcategory":"News Services",
            "type":"Services"
        }
    ],
    "sg:phone":"+61 3 5728 8066",
    "sg:postcode":"3747",
    "sg:province":"VIC",
    "sg:tags":[
        "information",
        "tourist",
        "attractions"
    ],
    "wof:name":"Beechworth Historic Court House",
    "wof:placetype":"venue"
},
  "geometry": {"coordinates":[146.68815599999999,-36.358704],"type":"Point"}
}