{
  "type": "Feature",
  "properties": {
    "addr:full":"58 Lawson Ave Frankston VIC 3199",
    "addr:housenumber":"58",
    "addr:postcode":"3199",
    "addr:street":"Lawson Ave",
    "iso:country":"AU",
    "sg:address":"58 Lawson Ave",
    "sg:city":"Frankston",
    "sg:classifiers":[
        {
            "category":"Building & Trades",
            "subcategory":"Cleaning & Sanitation",
            "type":"Services"
        }
    ],
    "sg:phone":"+61 3 9783 9866",
    "sg:postcode":"3199",
    "sg:province":"VIC",
    "sg:tags":[
        "industrial",
        "commercial",
        "contractor"
    ],
    "wof:name":"Brenthom General Cleaning",
    "wof:placetype":"venue"
},
  "geometry": {"coordinates":[145.13165283199999,-38.1698722839],"type":"Point"}
}