{
  "type": "Feature",
  "properties": {
    "iso:country":"AU",
    "sg:address":"U3/ 140 Meakin Rd",
    "sg:city":"Kingston",
    "sg:classifiers":[
        {
            "category":"Manufacturing",
            "subcategory":"Furniture",
            "type":"Manufacturing & Wholesale Goods"
        }
    ],
    "sg:phone":"+61 7 3290 0962",
    "sg:postcode":"4114",
    "sg:province":"QLD",
    "sg:tags":[
        "builder",
        "designer",
        "custom"
    ],
    "wof:name":"CTC (Custom Timber Cutting)",
    "wof:placetype":"venue"
},
  "geometry": {"coordinates":[153.134857178,-27.6531009674],"type":"Point"}
}