{
  "type": "Feature",
  "properties": {
    "iso:country":"AU",
    "sg:address":"A + I Hall Station St",
    "sg:city":"Bangalow",
    "sg:classifiers":[
        {
            "category":"Shopping",
            "subcategory":"Discount & Variety Stores",
            "type":"Retail Goods"
        }
    ],
    "sg:phone":"+61 2 6687 2799",
    "sg:postcode":"2479",
    "sg:province":"NSW",
    "sg:tags":[
        "information",
        "cooking",
        "class"
    ],
    "wof:name":"Bangalow Cooking School",
    "wof:placetype":"venue"
},
  "geometry": {"coordinates":[153.52442932100001,-28.6849784851],"type":"Point"}
}