{
  "type": "Feature",
  "properties": {
    "addr:full":"PO Box 6987 Shepparton VIC 3630",
    "addr:postcode":"3630",
    "iso:country":"AU",
    "sg:address":"PO Box 6987",
    "sg:city":"Shepparton",
    "sg:classifiers":[
        {
            "category":"Communications",
            "type":"Services"
        }
    ],
    "sg:phone":"+61 403 688 666",
    "sg:postcode":"3630",
    "sg:province":"VIC",
    "sg:tags":[
        "antenna"
    ],
    "wof:name":"Jason's TV",
    "wof:placetype":"venue"
},
  "geometry": {"coordinates":[145.40072631800001,-36.381980896],"type":"Point"}
}