{
  "type": "Feature",
  "properties": {
    "iso:country":"AU",
    "sg:address":"172 South Creek Rd",
    "sg:city":"Dee Why",
    "sg:classifiers":[
        {
            "category":"Building & Trades",
            "subcategory":"Construction",
            "type":"Services"
        }
    ],
    "sg:phone":"+61 2 9981 3772",
    "sg:postcode":"2099",
    "sg:province":"NSW",
    "sg:tags":[
        "welding"
    ],
    "wof:name":"C & G Structural Steelwork",
    "wof:placetype":"venue"
},
  "geometry": {"coordinates":[151.279907227,-33.7345733643],"type":"Point"}
}