{
  "type": "Feature",
  "properties": {
    "addr:full":"8 Ferncraft Ave Malvern East VIC 3145",
    "addr:housenumber":"8",
    "addr:postcode":"3145",
    "addr:street":"Ferncraft Ave",
    "iso:country":"AU",
    "sg:address":"8 Ferncraft Ave",
    "sg:city":"Malvern East",
    "sg:classifiers":[
        {
            "category":"Professional",
            "subcategory":"Accounting & Tax Preparation",
            "type":"Services"
        }
    ],
    "sg:phone":"+61 3 9885 5276",
    "sg:postcode":"3145",
    "sg:province":"VIC",
    "sg:tags":[
        "accountant",
        "auditor"
    ],
    "wof:name":"Burman R A W",
    "wof:placetype":"venue"
},
  "geometry": {"coordinates":[145.05726623499999,-37.8667907715],"type":"Point"}
}