{
  "type": "Feature",
  "properties": {
    "addr:full":"732 Merrylands Rd Greystanes NSW 2145",
    "addr:housenumber":"732",
    "addr:postcode":"2145",
    "addr:street":"Merrylands Rd",
    "iso:country":"AU",
    "sg:address":"732 Merrylands Rd",
    "sg:city":"Greystanes",
    "sg:classifiers":[
        {
            "category":"Government",
            "subcategory":"City Hall",
            "type":"Public Place"
        }
    ],
    "sg:phone":"+61 2 9631 4832",
    "sg:postcode":"2145",
    "sg:province":"NSW",
    "wof:name":"Greystanes Community Centre",
    "wof:placetype":"venue"
},
  "geometry": {"coordinates":[150.94432067899999,-33.829158783],"type":"Point"}
}