{
  "type": "Feature",
  "properties": {
    "iso:country":"AU",
    "sg:address":"31 Brockley St",
    "sg:city":"Wodonga",
    "sg:classifiers":[
        {
            "category":"Train Station",
            "subcategory":"Light Rail",
            "type":"Transportation"
        }
    ],
    "sg:phone":"+61 2 6056 6455",
    "sg:postcode":"3690",
    "sg:province":"VIC",
    "sg:tags":[
        "equipment",
        "energy",
        "solar"
    ],
    "wof:name":"Zane Solar Centre - Wodonga",
    "wof:placetype":"venue"
},
  "geometry": {"coordinates":[146.89097595199999,-36.1290397644],"type":"Point"}
}