{
  "type": "Feature",
  "properties": {
    "iso:country":"AU",
    "sg:address":"19 Main St",
    "sg:city":"Lithgow",
    "sg:classifiers":[
        {
            "category":"Retail",
            "subcategory":"Repair Shop",
            "type":"Services"
        }
    ],
    "sg:phone":"+61 2 6353 1108",
    "sg:postcode":"2790",
    "sg:province":"NSW",
    "sg:tags":[
        "upholsterer"
    ],
    "wof:name":"LS Upholstery",
    "wof:placetype":"venue"
},
  "geometry": {"coordinates":[150.154495239,-33.4822273254],"type":"Point"}
}