{
  "type": "Feature",
  "properties": {
    "addr:full":"105 Baxter-Tooradin Rd Baxter VIC 3911",
    "addr:housenumber":"105",
    "addr:postcode":"3911",
    "addr:street":"Baxter-Tooradin Rd",
    "iso:country":"AU",
    "sg:address":"105 Baxter-Tooradin Rd",
    "sg:city":"Baxter",
    "sg:classifiers":[
        {
            "category":"Health Services",
            "subcategory":"Dentist",
            "type":"Services"
        }
    ],
    "sg:phone":"+61 3 5971 4666",
    "sg:postcode":"3911",
    "sg:province":"VIC",
    "wof:name":"Grant D T Dr & Associates",
    "wof:placetype":"venue"
},
  "geometry": {"coordinates":[145.159469605,-38.1956977844],"type":"Point"}
}