{
  "type": "Feature",
  "properties": {
    "addr:full":"38 Cormie Ave Wee Waa NSW 2388",
    "addr:housenumber":"38",
    "addr:postcode":"2388",
    "addr:street":"Cormie Ave",
    "iso:country":"AU",
    "sg:address":"38 Cormie Ave",
    "sg:city":"Wee Waa",
    "sg:classifiers":[
        {
            "category":"Professional",
            "subcategory":"Engineering",
            "type":"Services"
        }
    ],
    "sg:phone":"+61 2 6795 4058",
    "sg:postcode":"2388",
    "sg:province":"NSW",
    "sg:tags":[
        "engineer",
        "mechanical"
    ],
    "wof:name":"Humphries G J & C H",
    "wof:placetype":"venue"
},
  "geometry": {"coordinates":[149.443756103,-30.2185211182],"type":"Point"}
}