{
  "type": "Feature",
  "properties": {
    "addr:full":"128C Ware St Fairfield NSW 2165",
    "addr:housenumber":"128c",
    "addr:postcode":"2165",
    "addr:street":"Ware St",
    "iso:country":"AU",
    "sg:address":"128C Ware St",
    "sg:city":"Fairfield",
    "sg:classifiers":[
        {
            "category":"Utilities",
            "subcategory":"Mobile Phone",
            "type":"Services"
        }
    ],
    "sg:phone":"+61 2 9724 9709",
    "sg:postcode":"2165",
    "sg:province":"NSW",
    "sg:tags":[
        "repair",
        "telephone"
    ],
    "wof:name":"Antz Mobile Station",
    "wof:placetype":"venue"
},
  "geometry": {"coordinates":[150.95429992699999,-33.8692474365],"type":"Point"}
}