{
  "type": "Feature",
  "properties": {
    "iso:country":"AU",
    "sg:address":"7/ 20 Lawson Crs",
    "sg:city":"Coffs Harbour",
    "sg:classifiers":[
        {
            "category":"Shopping",
            "subcategory":"Gifts & Souvenirs",
            "type":"Retail Goods"
        }
    ],
    "sg:phone":"+61 2 6651 3457",
    "sg:postcode":"2450",
    "sg:province":"NSW",
    "sg:tags":[
        "print",
        "poster",
        "pictures"
    ],
    "wof:name":"Coffs Interior Prints",
    "wof:placetype":"venue"
},
  "geometry": {"coordinates":[153.11515800000001,-30.29701],"type":"Point"}
}