{
  "type": "Feature",
  "properties": {
    "addr:full":"626- 628 Bell St Preston VIC 3072",
    "addr:housenumber":"626 628",
    "addr:postcode":"3072",
    "addr:street":"Bell St",
    "iso:country":"AU",
    "sg:address":"626- 628 Bell St",
    "sg:city":"Preston",
    "sg:classifiers":[
        {
            "category":"Building & Trades",
            "subcategory":"Equipment Rental",
            "type":"Services"
        }
    ],
    "sg:phone":"+61 1800 227 788",
    "sg:postcode":"3072",
    "sg:province":"VIC",
    "sg:tags":[
        "fitness"
    ],
    "wof:name":"Fitness Choice",
    "wof:placetype":"venue"
},
  "geometry": {"coordinates":[144.988891602,-37.7434997559],"type":"Point"}
}