{
  "type": "Feature",
  "properties": {
    "addr:full":"Shop 3 & 4 Centre Mall Merimbula NSW 2548",
    "addr:housenumber":"shop 3 & 4",
    "addr:postcode":"2548",
    "addr:street":"Centre Mall",
    "iso:country":"AU",
    "sg:address":"Shop 3 & 4 Centre Mall",
    "sg:city":"Merimbula",
    "sg:classifiers":[
        {
            "category":"Cafe",
            "type":"Food & Drink"
        }
    ],
    "sg:phone":"+61 2 6495 3933",
    "sg:postcode":"2548",
    "sg:province":"NSW",
    "wof:name":"Palm Cove Cafe",
    "wof:placetype":"venue"
},
  "geometry": {"coordinates":[149.908401489,-36.8878707886],"type":"Point"}
}