{
  "type": "Feature",
  "properties": {
    "iso:country":"AU",
    "sg:address":"182 Craword St",
    "sg:city":"Queanbeyan",
    "sg:classifiers":[
        {
            "category":"Personal",
            "subcategory":"Beauty Salon",
            "type":"Services"
        }
    ],
    "sg:phone":"+61 2 6299 0630",
    "sg:postcode":"2620",
    "sg:province":"ACT",
    "wof:name":"Your Natural Beauty",
    "wof:placetype":"venue"
},
  "geometry": {"coordinates":[149.23301696799999,-35.3511962891],"type":"Point"}
}