{
  "type": "Feature",
  "properties": {
    "iso:country":"AU",
    "sg:address":"57-75 Industrial Ave",
    "sg:city":"Toowoomba",
    "sg:classifiers":[
        {
            "category":"Transit Center",
            "subcategory":"Freight",
            "type":"Transportation"
        }
    ],
    "sg:phone":"+61 1300 458 789",
    "sg:postcode":"4350",
    "sg:province":"QLD",
    "sg:tags":[
        "equipment",
        "transport",
        "road",
        "vehicle"
    ],
    "sg:website":"http://www.thedaveygroup.com.au",
    "wof:name":"Lusty Low Loaders",
    "wof:placetype":"venue"
},
  "geometry": {"coordinates":[151.906464,-27.541845],"type":"Point"}
}