{
  "type": "Feature",
  "properties": {
    "iso:country":"AU",
    "sg:address":"2918 Barton Hwy",
    "sg:city":"Murrumbateman",
    "sg:classifiers":[
        {
            "category":"Farming",
            "subcategory":"Vineyard",
            "type":"Manufacturing & Wholesale Goods"
        }
    ],
    "sg:phone":"+61 407 913 912",
    "sg:postcode":"2582",
    "sg:province":"ACT",
    "sg:tags":[
        "winery"
    ],
    "wof:name":"Kyeema Wine",
    "wof:placetype":"venue"
},
  "geometry": {"coordinates":[148.97966003400001,-34.9092636108],"type":"Point"}
}