{
  "type": "Feature",
  "properties": {
    "addr:full":"272 William St Northbridge WA 6003",
    "addr:housenumber":"272",
    "addr:postcode":"6003",
    "addr:street":"William St",
    "iso:country":"AU",
    "sg:address":"272 William St",
    "sg:city":"Northbridge",
    "sg:classifiers":[
        {
            "category":"Shopping",
            "subcategory":"Mobile Phones",
            "type":"Retail Goods"
        }
    ],
    "sg:phone":"+61 8 9328 1889",
    "sg:postcode":"6003",
    "sg:province":"WA",
    "sg:tags":[
        "telephone",
        "accessory"
    ],
    "wof:name":"Pacific Com Pty Ltd",
    "wof:placetype":"venue"
},
  "geometry": {"coordinates":[115.860458374,-31.947479248],"type":"Point"}
}