{
  "type": "Feature",
  "properties": {
    "addr:full":"Shop 60 Nowra Fair Nowra NSW 2541",
    "addr:housenumber":"shop 60",
    "addr:postcode":"2541",
    "iso:country":"AU",
    "sg:address":"Shop 60",
    "sg:city":"Nowra Fair Nowra",
    "sg:classifiers":[
        {
            "category":"Fast Food",
            "type":"Food & Drink"
        }
    ],
    "sg:phone":"+61 2 4423 2833",
    "sg:postcode":"2541",
    "sg:province":"NSW",
    "sg:tags":[
        "away",
        "take"
    ],
    "wof:name":"Nowra Charcoal Chickens",
    "wof:placetype":"venue"
},
  "geometry": {"coordinates":[150.59387207,-34.8777999878],"type":"Point"}
}