{
  "type": "Feature",
  "properties": {
    "addr:full":"11 Ian Crs Chester Hill NSW 2162",
    "addr:housenumber":"11",
    "addr:postcode":"2162",
    "addr:street":"Ian Crs",
    "iso:country":"AU",
    "sg:address":"11 Ian Crs",
    "sg:city":"Chester Hill",
    "sg:classifiers":[
        {
            "category":"Building & Trades",
            "subcategory":"Landscaping Services",
            "type":"Services"
        }
    ],
    "sg:phone":"+61 416 552 723",
    "sg:postcode":"2162",
    "sg:province":"NSW",
    "sg:tags":[
        "stump",
        "tree",
        "felling",
        "removal"
    ],
    "wof:name":"Payless Tree Service",
    "wof:placetype":"venue"
},
  "geometry": {"coordinates":[151.00013732900001,-33.8829994202],"type":"Point"}
}