{
  "type": "Feature",
  "properties": {
    "iso:country":"AU",
    "sg:address":"14- 18 Racecourse Rd",
    "sg:city":"Williamstown",
    "sg:classifiers":[
        {
            "category":"Manufacturing",
            "subcategory":"Wood Products",
            "type":"Manufacturing & Wholesale Goods"
        }
    ],
    "sg:phone":"+61 3 9399 1385",
    "sg:postcode":"3016",
    "sg:province":"VIC",
    "sg:tags":[
        "pallet",
        "platform"
    ],
    "wof:name":"Westend Pallets (Aust.) Pty. Ltd.",
    "wof:placetype":"venue"
},
  "geometry": {"coordinates":[144.85313415499999,-37.8528213501],"type":"Point"}
}