{
  "type": "Feature",
  "properties": {
    "iso:country":"AU",
    "sg:address":"179 Marine Pde",
    "sg:city":"Kingston SE",
    "sg:classifiers":[
        {
            "category":"Fast Food",
            "type":"Food & Drink"
        }
    ],
    "sg:phone":"+61 8 8767 2388",
    "sg:postcode":"5275",
    "sg:province":"SA",
    "sg:tags":[
        "away",
        "take"
    ],
    "wof:name":"Wyomi Beach Store",
    "wof:placetype":"venue"
},
  "geometry": {"coordinates":[139.85011299999999,-36.827244],"type":"Point"}
}