{
  "type": "Feature",
  "properties": {
    "iso:country":"AU",
    "sg:address":"36 Meenan St",
    "sg:city":"Garbutt",
    "sg:classifiers":[
        {
            "category":"Personal",
            "subcategory":"Beauty Salon",
            "type":"Services"
        }
    ],
    "sg:phone":"+61 7 4779 9292",
    "sg:postcode":"4814",
    "sg:province":"QLD",
    "sg:tags":[
        "hairdresser"
    ],
    "wof:name":"The Hair Base",
    "wof:placetype":"venue"
},
  "geometry": {"coordinates":[146.775024,-19.260374],"type":"Point"}
}