{
  "type": "Feature",
  "properties": {
    "iso:country":"AU",
    "sg:address":"100A Creek Rd",
    "sg:city":"Birkdale",
    "sg:classifiers":[
        {
            "category":"Sports & Exercise",
            "subcategory":"Golf",
            "type":"Entertainment"
        }
    ],
    "sg:phone":"+61 7 3207 2452",
    "sg:postcode":"4159",
    "sg:province":"QLD",
    "sg:tags":[
        "club"
    ],
    "wof:name":"Howeston Golf Course",
    "wof:placetype":"venue"
},
  "geometry": {"coordinates":[153.199615478,-27.5001049042],"type":"Point"}
}