{
  "type": "Feature",
  "properties": {
    "addr:full":"32 Marsden St Boorowa NSW 2586",
    "addr:housenumber":"32",
    "addr:postcode":"2586",
    "addr:street":"Marsden St",
    "iso:country":"AU",
    "sg:address":"32 Marsden St",
    "sg:city":"Boorowa",
    "sg:classifiers":[
        {
            "category":"Banks & Credit Unions",
            "subcategory":"Bank",
            "type":"Services"
        }
    ],
    "sg:phone":"+61 2 6385 3277",
    "sg:postcode":"2586",
    "sg:province":"NSW",
    "wof:name":"Bendigo Community Bank",
    "wof:placetype":"venue"
},
  "geometry": {"coordinates":[148.71629333499999,-34.4378051758],"type":"Point"}
}