{
  "type": "Feature",
  "properties": {
    "iso:country":"AU",
    "sg:address":"576 Queen St",
    "sg:city":"Brisbane",
    "sg:classifiers":[
        {
            "category":"Retail",
            "subcategory":"Auto Rental",
            "type":"Services"
        }
    ],
    "sg:phone":"+61 7 3839 4355",
    "sg:postcode":"4000",
    "sg:province":"QLD",
    "sg:tags":[
        "car",
        "hire",
        "minibus"
    ],
    "wof:name":"Delta Car & Truck Rentals",
    "wof:placetype":"venue"
},
  "geometry": {"coordinates":[153.03103637699999,-27.4621124268],"type":"Point"}
}