{
  "type": "Feature",
  "properties": {
    "addr:full":"216 Burgundy St Heidelberg VIC 3084",
    "addr:housenumber":"216",
    "addr:postcode":"3084",
    "addr:street":"Burgundy St",
    "iso:country":"AU",
    "sg:address":"216 Burgundy St",
    "sg:city":"Heidelberg",
    "sg:classifiers":[
        {
            "category":"Health Services",
            "subcategory":"Doctor",
            "type":"Services"
        }
    ],
    "sg:phone":"+61 3 9496 5034",
    "sg:postcode":"3084",
    "sg:province":"VIC",
    "sg:tags":[
        "medical",
        "practitioner"
    ],
    "wof:name":"Warringal Echodoppler Clinic",
    "wof:placetype":"venue"
},
  "geometry": {"coordinates":[145.060668945,-37.755115509],"type":"Point"}
}