{
  "type": "Feature",
  "properties": {
    "addr:full":"275 Johnston St Abbotsford VIC 3067",
    "addr:housenumber":"275",
    "addr:postcode":"3067",
    "addr:street":"Johnston St",
    "iso:country":"AU",
    "sg:address":"275 Johnston St",
    "sg:city":"Abbotsford",
    "sg:classifiers":[
        {
            "category":"Professional",
            "subcategory":"Engineering",
            "type":"Services"
        }
    ],
    "sg:phone":"+61 3 9415 1800",
    "sg:postcode":"3067",
    "sg:province":"VIC",
    "sg:tags":[
        "consulting",
        "engineer"
    ],
    "wof:name":"Terenyi R & Associates Pty Ltd",
    "wof:placetype":"venue"
},
  "geometry": {"coordinates":[144.995727539,-37.8002166748],"type":"Point"}
}