{
  "type": "Feature",
  "properties": {
    "addr:full":"162 Maroondah Hwy Croydon VIC 3136",
    "addr:housenumber":"162",
    "addr:postcode":"3136",
    "addr:street":"Maroondah Hwy",
    "iso:country":"AU",
    "sg:address":"162 Maroondah Hwy",
    "sg:city":"Croydon",
    "sg:classifiers":[
        {
            "category":"Health Services",
            "subcategory":"Doctor",
            "type":"Services"
        }
    ],
    "sg:phone":"+61 3 9725 6785",
    "sg:postcode":"3136",
    "sg:province":"VIC",
    "sg:tags":[
        "medical",
        "practitioner"
    ],
    "wof:name":"Bailey Kit A",
    "wof:placetype":"venue"
},
  "geometry": {"coordinates":[145.27589416500001,-37.7867851257],"type":"Point"}
}