{
  "type": "Feature",
  "properties": {
    "addr:full":"Ste 10/ 170 George St Liverpool NSW 2170",
    "addr:housenumber":"/ 170",
    "addr:postcode":"2170",
    "addr:street":"George St",
    "iso:country":"AU",
    "sg:address":"Ste 10/ 170 George St",
    "sg:city":"Liverpool",
    "sg:classifiers":[
        {
            "category":"Health Services",
            "subcategory":"Health Practitioner",
            "type":"Services"
        }
    ],
    "sg:phone":"+61 2 9734 0095",
    "sg:postcode":"2170",
    "sg:province":"NSW",
    "sg:tags":[
        "psychologist"
    ],
    "wof:name":"Prana Consulting",
    "wof:placetype":"venue"
},
  "geometry": {"coordinates":[150.92457580600001,-33.9236106873],"type":"Point"}
}