{
  "type": "Feature",
  "properties": {
    "addr:full":"101 Balnarring Rd Balnarring VIC 3926",
    "addr:housenumber":"101",
    "addr:postcode":"3926",
    "addr:street":"Balnarring Rd",
    "iso:country":"AU",
    "sg:address":"101 Balnarring Rd",
    "sg:city":"Balnarring",
    "sg:classifiers":[
        {
            "category":"Farming",
            "subcategory":"Vineyard",
            "type":"Manufacturing & Wholesale Goods"
        }
    ],
    "sg:phone":"+61 3 5931 3000",
    "sg:postcode":"3926",
    "sg:province":"VIC",
    "sg:tags":[
        "winery"
    ],
    "wof:name":"Hurley Vineyard",
    "wof:placetype":"venue"
},
  "geometry": {"coordinates":[145.11322021500001,-38.3594856262],"type":"Point"}
}