{
  "type": "Feature",
  "properties": {
    "addr:full":"Shop 2/ 1a Para Rd Tanunda SA 5352",
    "addr:housenumber":"shop 2 / 1a",
    "addr:postcode":"5352",
    "addr:street":"Para Rd",
    "iso:country":"AU",
    "sg:address":"Shop 2/ 1a Para Rd",
    "sg:city":"Tanunda",
    "sg:classifiers":[
        {
            "category":"Banks & Credit Unions",
            "subcategory":"Investment Brokerage",
            "type":"Services"
        }
    ],
    "sg:phone":"+61 8 8563 0075",
    "sg:postcode":"5352",
    "sg:province":"SA",
    "sg:tags":[
        "radiator",
        "motor"
    ],
    "wof:name":"Barossa Radiators",
    "wof:placetype":"venue"
},
  "geometry": {"coordinates":[138.974319458,-34.5114746094],"type":"Point"}
}