{
  "type": "Feature",
  "properties": {
    "iso:country":"AU",
    "sg:address":"8 St Helena Market Pl",
    "sg:city":"Greensborough",
    "sg:classifiers":[
        {
            "category":"Health Services",
            "subcategory":"Optometrist",
            "type":"Services"
        }
    ],
    "sg:phone":"+61 3 9438 5333",
    "sg:postcode":"3088",
    "sg:province":"VIC",
    "wof:name":"Diamond Valley Optical",
    "wof:placetype":"venue"
},
  "geometry": {"coordinates":[145.10830688499999,-37.6998214722],"type":"Point"}
}