{
  "type": "Feature",
  "properties": {
    "iso:country":"AU",
    "sg:address":"PO Box 111",
    "sg:city":"Pyrmont",
    "sg:classifiers":[
        {
            "category":"Banks & Credit Unions",
            "subcategory":"Bank",
            "type":"Services"
        }
    ],
    "sg:phone":"+61 2 9571 7206",
    "sg:postcode":"2009",
    "sg:province":"NSW",
    "sg:tags":[
        "broker",
        "mortgage"
    ],
    "wof:name":"Ability Finance Pty Ltd",
    "wof:placetype":"venue"
},
  "geometry": {"coordinates":[151.19543457,-33.8708190918],"type":"Point"}
}