{
  "type": "Feature",
  "properties": {
    "addr:full":"49 Jubilee St Lismore NSW 2480",
    "addr:housenumber":"49",
    "addr:postcode":"2480",
    "addr:street":"Jubilee St",
    "iso:country":"AU",
    "sg:address":"49 Jubilee St",
    "sg:city":"Lismore",
    "sg:classifiers":[
        {
            "category":"Home & Garden",
            "subcategory":"Building Materials",
            "type":"Retail Goods"
        }
    ],
    "sg:phone":"+61 2 6621 2274",
    "sg:postcode":"2480",
    "sg:province":"NSW",
    "sg:tags":[
        "merchant",
        "glass",
        "glazier"
    ],
    "wof:name":"Dayal Singh Joinery",
    "wof:placetype":"venue"
},
  "geometry": {"coordinates":[153.290557861,-28.80610466],"type":"Point"}
}