{
  "type": "Feature",
  "properties": {
    "addr:full":"30 Nioka St Brookfield QLD 4069",
    "addr:housenumber":"30",
    "addr:postcode":"4069",
    "addr:street":"Nioka St",
    "iso:country":"AU",
    "sg:address":"30 Nioka St",
    "sg:city":"Brookfield",
    "sg:classifiers":[
        {
            "category":"Real Estate",
            "subcategory":"Architect",
            "type":"Services"
        }
    ],
    "sg:phone":"+61 7 3374 1422",
    "sg:postcode":"4069",
    "sg:province":"QLD",
    "wof:name":"Payne Robin Building Designer",
    "wof:placetype":"venue"
},
  "geometry": {"coordinates":[152.908035278,-27.5042495728],"type":"Point"}
}