{
  "type": "Feature",
  "properties": {
    "addr:full":"88 Percy St Wellington NSW 2820",
    "addr:housenumber":"88",
    "addr:postcode":"2820",
    "addr:street":"Percy St",
    "iso:country":"AU",
    "sg:address":"88 Percy St",
    "sg:city":"Wellington",
    "sg:classifiers":[
        {
            "category":"Retail",
            "subcategory":"Funeral Services",
            "type":"Services"
        }
    ],
    "sg:phone":"+61 2 6845 1946",
    "sg:postcode":"2820",
    "sg:province":"NSW",
    "sg:tags":[
        "director"
    ],
    "wof:name":"H Logue & Sons",
    "wof:placetype":"venue"
},
  "geometry": {"coordinates":[148.943069458,-32.5527191162],"type":"Point"}
}