{
  "type": "Feature",
  "properties": {
    "addr:full":"90 Coopers Rd Foster VIC 3960",
    "addr:housenumber":"90",
    "addr:postcode":"3960",
    "addr:street":"Coopers Rd",
    "iso:country":"AU",
    "sg:address":"90 Coopers Rd",
    "sg:city":"Foster",
    "sg:classifiers":[
        {
            "category":"Banks & Credit Unions",
            "subcategory":"Bureau De Change",
            "type":"Services"
        }
    ],
    "sg:phone":"+61 3 5682 1288",
    "sg:postcode":"3960",
    "sg:province":"VIC",
    "sg:tags":[
        "repairs",
        "part",
        "appliance",
        "electrical"
    ],
    "wof:name":"Prom Appliances",
    "wof:placetype":"venue"
},
  "geometry": {"coordinates":[146.19635009800001,-38.6512527466],"type":"Point"}
}