{
  "type": "Feature",
  "properties": {
    "addr:full":"7th Floor, 38 Gawler Pl Adelaide SA 5000",
    "addr:housenumber":"38",
    "addr:postcode":"5000",
    "addr:street":"Gawler Pl",
    "iso:country":"AU",
    "sg:address":"7th Floor, 38 Gawler Pl",
    "sg:city":"Adelaide",
    "sg:classifiers":[
        {
            "category":"Personal",
            "type":"Services"
        }
    ],
    "sg:phone":"+61 8 8232 0844",
    "sg:postcode":"5000",
    "sg:province":"SA",
    "sg:tags":[
        "reducing",
        "treatment",
        "weight"
    ],
    "wof:name":"South Australian Weight Watchers Assoc Inc",
    "wof:placetype":"venue"
},
  "geometry": {"coordinates":[138.602050781,-34.9232330322],"type":"Point"}
}