{
  "type": "Feature",
  "properties": {
    "iso:country":"AU",
    "sg:address":"PO Box 949",
    "sg:city":"Smithfield (Cairns)",
    "sg:classifiers":[
        {
            "category":"Building & Trades",
            "subcategory":"Landscaping Services",
            "type":"Services"
        }
    ],
    "sg:phone":"+61 418 727 834",
    "sg:postcode":"4878",
    "sg:province":"QLD",
    "sg:tags":[
        "gardener"
    ],
    "wof:name":"CJ's Gardening Maintenance",
    "wof:placetype":"venue"
},
  "geometry": {"coordinates":[145.68907165499999,-16.83852005],"type":"Point"}
}