{
  "type": "Feature",
  "properties": {
    "addr:full":"127 Kangaroo Point Rd Kangaroo Point NSW 2224",
    "addr:housenumber":"127",
    "addr:postcode":"2224",
    "addr:street":"Kangaroo Point Rd",
    "iso:country":"AU",
    "sg:address":"127 Kangaroo Point Rd",
    "sg:city":"Kangaroo Point",
    "sg:classifiers":[
        {
            "category":"Real Estate",
            "subcategory":"Architect",
            "type":"Services"
        }
    ],
    "sg:phone":"+61 404 022 985",
    "sg:postcode":"2224",
    "sg:province":"NSW",
    "sg:tags":[
        "building",
        "designer"
    ],
    "wof:name":"Archispot",
    "wof:placetype":"venue"
},
  "geometry": {"coordinates":[151.09605407699999,-34.0044822693],"type":"Point"}
}