{
  "type": "Feature",
  "properties": {
    "addr:full":"116 Diment Rd Salisbury North SA 5108",
    "addr:housenumber":"116",
    "addr:postcode":"5108",
    "addr:street":"Diment Rd",
    "iso:country":"AU",
    "sg:address":"116 Diment Rd",
    "sg:city":"Salisbury North",
    "sg:classifiers":[
        {
            "category":"Communications",
            "subcategory":"Film & Video Production",
            "type":"Services"
        }
    ],
    "sg:phone":"+61 8 8281 0797",
    "sg:postcode":"5108",
    "sg:province":"SA",
    "sg:tags":[
        "dvd",
        "library"
    ],
    "wof:name":"Network Video",
    "wof:placetype":"venue"
},
  "geometry": {"coordinates":[138.62652587900001,-34.740196228],"type":"Point"}
}