{
  "type": "Feature",
  "properties": {
    "addr:full":"331 Forest Rd Bexley NSW 2207",
    "addr:housenumber":"331",
    "addr:postcode":"2207",
    "addr:street":"Forest Rd",
    "iso:country":"AU",
    "sg:address":"331 Forest Rd",
    "sg:city":"Bexley",
    "sg:classifiers":[
        {
            "category":"Personal",
            "subcategory":"Beauty Salon",
            "type":"Services"
        }
    ],
    "sg:phone":"+61 2 9599 3859",
    "sg:postcode":"2207",
    "sg:province":"NSW",
    "sg:tags":[
        "hairdresser"
    ],
    "wof:name":"M Beauty Liscious",
    "wof:placetype":"venue"
},
  "geometry": {"coordinates":[151.124573,-33.951611],"type":"Point"}
}