{
  "type": "Feature",
  "properties": {
    "iso:country":"AU",
    "sg:address":"6 Jennifer Crt",
    "sg:city":"Avondale Heights",
    "sg:classifiers":[
        {
            "category":"Education",
            "subcategory":"Music School",
            "type":"Public Place"
        }
    ],
    "sg:phone":"+61 3 9318 4339",
    "sg:postcode":"3034",
    "sg:province":"VIC",
    "sg:tags":[
        "teacher"
    ],
    "wof:name":"Shell P C & M J",
    "wof:placetype":"venue"
},
  "geometry": {"coordinates":[144.85981799999999,-37.772812],"type":"Point"}
}