{
  "type": "Feature",
  "properties": {
    "iso:country":"AU",
    "sg:address":"42 Dense St",
    "sg:city":"Lake Heights",
    "sg:classifiers":[
        {
            "category":"Home & Garden",
            "subcategory":"Carpets & Floor Coverings",
            "type":"Retail Goods"
        }
    ],
    "sg:phone":"+61 2 4274 4555",
    "sg:postcode":"2502",
    "sg:province":"NSW",
    "sg:tags":[
        "tile",
        "wall",
        "layer"
    ],
    "wof:name":"South Coast Flooring",
    "wof:placetype":"venue"
},
  "geometry": {"coordinates":[150.87307699999999,-34.487419],"type":"Point"}
}