{
  "type": "Feature",
  "properties": {
    "iso:country":"AU",
    "sg:address":"14 Robertson Ave",
    "sg:city":"Margate",
    "sg:classifiers":[
        {
            "category":"Building & Trades",
            "subcategory":"Pest Control",
            "type":"Services"
        }
    ],
    "sg:phone":"+61 7 3885 3932",
    "sg:postcode":"4019",
    "sg:province":"QLD",
    "wof:name":"Aussie Mozzie Pest Control",
    "wof:placetype":"venue"
},
  "geometry": {"coordinates":[153.111053467,-27.2398815155],"type":"Point"}
}