{
  "type": "Feature",
  "properties": {
    "addr:full":"Prospect St Lowood QLD 4311",
    "addr:postcode":"4311",
    "addr:street":"Prospect St",
    "iso:country":"AU",
    "sg:address":"Prospect St",
    "sg:city":"Lowood",
    "sg:classifiers":[
        {
            "category":"Education",
            "subcategory":"School",
            "type":"Public Place"
        }
    ],
    "sg:phone":"+61 7 5427 8333",
    "sg:postcode":"4311",
    "sg:province":"QLD",
    "sg:tags":[
        "state",
        "except",
        "nsw"
    ],
    "wof:name":"Lowood High School",
    "wof:placetype":"venue"
},
  "geometry": {"coordinates":[152.58598327600001,-27.4684333801],"type":"Point"}
}