{
  "type": "Feature",
  "properties": {
    "iso:country":"AU",
    "sg:address":"Shop 3/ 68- 70 Essington Lewis Ave",
    "sg:city":"Whyalla",
    "sg:classifiers":[
        {
            "category":"Personal",
            "subcategory":"Piercing",
            "type":"Services"
        }
    ],
    "sg:phone":"+61 8 8645 3735",
    "sg:postcode":"5600",
    "sg:province":"SA",
    "sg:tags":[
        "body",
        "ear"
    ],
    "wof:name":"Skin Deep Body Piercing",
    "wof:placetype":"venue"
},
  "geometry": {"coordinates":[137.57489,-33.035671],"type":"Point"}
}