{
  "type": "Feature",
  "properties": {
    "iso:country":"AU",
    "sg:address":"67 Little Fyans St",
    "sg:city":"South Geelong",
    "sg:classifiers":[
        {
            "category":"Structure",
            "subcategory":"Building",
            "type":"Public Place"
        }
    ],
    "sg:phone":"+61 3 5244 4121",
    "sg:postcode":"3220",
    "sg:province":"VIC",
    "sg:tags":[
        "sail",
        "shade"
    ],
    "wof:name":"Geelong Shade Structures",
    "wof:placetype":"venue"
},
  "geometry": {"coordinates":[144.36012299999999,-38.164406],"type":"Point"}
}