{
  "type": "Feature",
  "properties": {
    "iso:country":"AU",
    "sg:address":"28 Southern Cross Drv",
    "sg:city":"Ballina",
    "sg:classifiers":[
        {
            "category":"Retail",
            "subcategory":"Auto Repair",
            "type":"Services"
        }
    ],
    "sg:phone":"+61 2 6686 9666",
    "sg:postcode":"2478",
    "sg:province":"NSW",
    "sg:tags":[
        "repairer",
        "motor",
        "engineer"
    ],
    "wof:name":"European Automotive",
    "wof:placetype":"venue"
},
  "geometry": {"coordinates":[153.55494689899999,-28.8486785889],"type":"Point"}
}