{
  "type": "Feature",
  "properties": {
    "addr:full":"Watergardens Shopping Centre Keilor-Melton Hwy Taylors Lakes VIC 3038",
    "addr:postcode":"3038",
    "addr:street":"Keilor-Melton Hwy",
    "iso:country":"AU",
    "sg:address":"Watergardens Shopping Centre Keilor-Melton Hwy",
    "sg:city":"Taylors Lakes",
    "sg:classifiers":[
        {
            "category":"Shopping",
            "subcategory":"Computers & Home Electronics",
            "type":"Retail Goods"
        }
    ],
    "sg:phone":"+61 3 9449 0193",
    "sg:postcode":"3038",
    "sg:province":"VIC",
    "sg:tags":[
        "equipment",
        "part",
        "electronic"
    ],
    "wof:name":"Tandy Electronics",
    "wof:placetype":"venue"
},
  "geometry": {"coordinates":[144.77757299999999,-37.698952],"type":"Point"}
}