{
  "type": "Feature",
  "properties": {
    "addr:full":"8 William St Portsmith QLD 4870",
    "addr:housenumber":"8",
    "addr:postcode":"4870",
    "addr:street":"William St Portsmith",
    "iso:country":"AU",
    "sg:address":"8 William St",
    "sg:city":"Portsmith",
    "sg:classifiers":[
        {
            "category":"Building & Trades",
            "subcategory":"Construction",
            "type":"Services"
        }
    ],
    "sg:phone":"+61 7 4035 5029",
    "sg:postcode":"4870",
    "sg:province":"QLD",
    "sg:tags":[
        "scaffolding"
    ],
    "sg:website":"http://www.rijcon.com",
    "wof:name":"Rijcon Construction Pty Ltd",
    "wof:placetype":"venue"
},
  "geometry": {"coordinates":[145.75921630900001,-16.9421482086],"type":"Point"}
}