{
  "type": "Feature",
  "properties": {
    "iso:country":"AU",
    "sg:address":"488 Bourke St",
    "sg:city":"Melbourne",
    "sg:classifiers":[
        {
            "category":"Cafe",
            "type":"Food & Drink"
        }
    ],
    "sg:phone":"+61 3 9670 3322",
    "sg:postcode":"3000",
    "sg:province":"VIC",
    "wof:name":"Cafe Euro Food and Wine Bar",
    "wof:placetype":"venue"
},
  "geometry": {"coordinates":[144.959182739,-37.8152656555],"type":"Point"}
}