{
  "type": "Feature",
  "properties": {
    "iso:country":"AU",
    "sg:address":"75 Greygums Rd",
    "sg:city":"Mt Pleasant",
    "sg:classifiers":[
        {
            "category":"Professional",
            "subcategory":"Business Services",
            "type":"Services"
        }
    ],
    "sg:phone":"+61 2 4730 3991",
    "sg:postcode":"2749",
    "sg:province":"NSW",
    "sg:tags":[
        "drafting"
    ],
    "wof:name":"Menaka Kulatunge (Building Design & Drafting)",
    "wof:placetype":"venue"
},
  "geometry": {"coordinates":[150.712127686,-33.7326698303],"type":"Point"}
}