{
  "type": "Feature",
  "properties": {
    "iso:country":"AU",
    "sg:address":"187 Campbell St",
    "sg:city":"Belmont",
    "sg:classifiers":[
        {
            "category":"Professional",
            "type":"Services"
        }
    ],
    "sg:phone":"+61 8 9478 2404",
    "sg:postcode":"6104",
    "sg:province":"WA",
    "sg:tags":[
        "spray",
        "painting"
    ],
    "wof:name":"Mirage Spraypainters & Panel Beaters",
    "wof:placetype":"venue"
},
  "geometry": {"coordinates":[115.92579650899999,-31.9553108215],"type":"Point"}
}