{
  "type": "Feature",
  "properties": {
    "iso:country":"AU",
    "sg:address":"13 Cornish St",
    "sg:city":"Glenelg North",
    "sg:classifiers":[
        {
            "category":"Utilities",
            "subcategory":"Electric",
            "type":"Services"
        }
    ],
    "sg:phone":"+61 418 836 351",
    "sg:postcode":"5045",
    "sg:province":"SA",
    "sg:tags":[
        "electrical",
        "contractor"
    ],
    "wof:name":"Contect Electrical",
    "wof:placetype":"venue"
},
  "geometry": {"coordinates":[138.518951,-34.969608],"type":"Point"}
}