{
  "type": "Feature",
  "properties": {
    "addr:full":"92 Davy St Taradale VIC 3447",
    "addr:housenumber":"92",
    "addr:postcode":"3447",
    "addr:street":"Davy St",
    "iso:country":"AU",
    "sg:address":"92 Davy St",
    "sg:city":"Taradale",
    "sg:classifiers":[
        {
            "category":"Building & Trades",
            "subcategory":"Construction",
            "type":"Services"
        }
    ],
    "sg:phone":"+61 3 5423 2246",
    "sg:postcode":"3447",
    "sg:province":"VIC",
    "sg:tags":[
        "fencing",
        "contractor"
    ],
    "wof:name":"Densmore Robert",
    "wof:placetype":"venue"
},
  "geometry": {"coordinates":[144.345413208,-37.1362991333],"type":"Point"}
}