{
  "type": "Feature",
  "properties": {
    "addr:full":"U1/ 1 Craftsman Ave Berkeley Vale NSW 2261",
    "addr:housenumber":"1",
    "addr:postcode":"2261",
    "addr:street":"U1 /;Craftsman Ave",
    "iso:country":"AU",
    "sg:address":"U1/ 1 Craftsman Ave",
    "sg:city":"Berkeley Vale",
    "sg:classifiers":[
        {
            "category":"Manufacturing",
            "subcategory":"Metals",
            "type":"Manufacturing & Wholesale Goods"
        }
    ],
    "sg:phone":"+61 2 4389 8722",
    "sg:postcode":"2261",
    "sg:province":"NSW",
    "sg:tags":[
        "steel",
        "fabricator",
        "mfrs"
    ],
    "wof:name":"Jpb Welding",
    "wof:placetype":"venue"
},
  "geometry": {"coordinates":[151.42482000000001,-33.326824],"type":"Point"}
}