{
  "type": "Feature",
  "properties": {
    "iso:country":"AU",
    "sg:address":"12 Linacre Rd",
    "sg:city":"Hampton",
    "sg:classifiers":[
        {
            "category":"Health Services",
            "subcategory":"Doctor",
            "type":"Services"
        }
    ],
    "sg:phone":"+61 3 9598 9666",
    "sg:postcode":"3188",
    "sg:province":"VIC",
    "sg:tags":[
        "medical",
        "practitioner"
    ],
    "wof:name":"Lang D Andrew",
    "wof:placetype":"venue"
},
  "geometry": {"coordinates":[145.00286865199999,-37.9422340393],"type":"Point"}
}