{
  "type": "Feature",
  "properties": {
    "addr:full":"1 Lisle Crt West Pennant Hills NSW 2125",
    "addr:housenumber":"1",
    "addr:postcode":"2125",
    "addr:street":"Lisle Crt",
    "iso:country":"AU",
    "sg:address":"1 Lisle Crt",
    "sg:city":"West Pennant Hills",
    "sg:classifiers":[
        {
            "category":"Real Estate",
            "subcategory":"Architect",
            "type":"Services"
        }
    ],
    "sg:phone":"+61 2 9871 3977",
    "sg:postcode":"2125",
    "sg:province":"NSW",
    "sg:tags":[
        "building",
        "designer"
    ],
    "wof:name":"Paul Meyer Design Pty Ltd",
    "wof:placetype":"venue"
},
  "geometry": {"coordinates":[151.043502808,-33.7572174072],"type":"Point"}
}