{
  "type": "Feature",
  "properties": {
    "addr:full":"13 Skene St Stawell VIC 3380",
    "addr:housenumber":"13",
    "addr:postcode":"3380",
    "addr:street":"Skene St",
    "iso:country":"AU",
    "sg:address":"13 Skene St",
    "sg:city":"Stawell",
    "sg:classifiers":[
        {
            "category":"Education",
            "subcategory":"School",
            "type":"Public Place"
        }
    ],
    "sg:phone":"+61 3 5358 2448",
    "sg:postcode":"3380",
    "sg:province":"VIC",
    "sg:tags":[
        "state",
        "except",
        "nsw"
    ],
    "wof:name":"Skene Street School",
    "wof:placetype":"venue"
},
  "geometry": {"coordinates":[142.783859253,-37.0578193665],"type":"Point"}
}