{
  "type": "Feature",
  "properties": {
    "addr:full":"183 Tynte St North Adelaide SA 5006",
    "addr:housenumber":"183",
    "addr:postcode":"5006",
    "addr:street":"Tynte St",
    "iso:country":"AU",
    "sg:address":"183 Tynte St",
    "sg:city":"North Adelaide",
    "sg:classifiers":[
        {
            "category":"Health Services",
            "subcategory":"Doctor",
            "type":"Services"
        }
    ],
    "sg:phone":"+61 8 8239 0399",
    "sg:postcode":"5006",
    "sg:province":"SA",
    "sg:tags":[
        "medical",
        "practitioner"
    ],
    "wof:name":"In Shape Cosmetic Surgery",
    "wof:placetype":"venue"
},
  "geometry": {"coordinates":[138.593460083,-34.9066581726],"type":"Point"}
}