{
  "type": "Feature",
  "properties": {
    "addr:full":"355 Erindale Rd Warwick WA 6024",
    "addr:housenumber":"355",
    "addr:postcode":"6024",
    "addr:street":"Erindale Rd",
    "iso:country":"AU",
    "sg:address":"355 Erindale Rd",
    "sg:city":"Warwick",
    "sg:classifiers":[
        {
            "category":"Education",
            "subcategory":"School",
            "type":"Public Place"
        }
    ],
    "sg:phone":"+61 8 9342 7422",
    "sg:postcode":"6024",
    "sg:province":"WA",
    "sg:tags":[
        "state",
        "except",
        "nsw"
    ],
    "wof:name":"Warwick Senior High School",
    "wof:placetype":"venue"
},
  "geometry": {"coordinates":[115.814018249,-31.8381023407],"type":"Point"}
}