{
  "type": "Feature",
  "properties": {
    "addr:full":"11 / 46 Douglas St Milton QLD 4064",
    "addr:housenumber":"11 / 46",
    "addr:postcode":"4064",
    "addr:street":"Douglas St",
    "iso:country":"AU",
    "sg:address":"11 / 46 Douglas St",
    "sg:city":"Milton",
    "sg:classifiers":[
        {
            "category":"Building & Trades",
            "subcategory":"Construction",
            "type":"Services"
        }
    ],
    "sg:phone":"+61 1300 783 356",
    "sg:postcode":"4064",
    "sg:province":"QLD",
    "sg:tags":[
        "renovation",
        "alterations",
        "extension",
        "contractor"
    ],
    "wof:name":"Steelform Structures",
    "wof:placetype":"venue"
},
  "geometry": {"coordinates":[153.003509522,-27.4718666077],"type":"Point"}
}