{
  "type": "Feature",
  "properties": {
    "addr:full":"Shp 17/ 6 Stradbroke St Redland Bay QLD 4165",
    "addr:housenumber":"17 / 6",
    "addr:postcode":"4165",
    "addr:street":"Stradbroke St",
    "iso:country":"AU",
    "sg:address":"Shp 17/ 6 Stradbroke St",
    "sg:city":"Redland Bay",
    "sg:classifiers":[
        {
            "category":"Fast Food",
            "type":"Food & Drink"
        }
    ],
    "sg:phone":"+61 7 3829 1222",
    "sg:postcode":"4165",
    "sg:province":"QLD",
    "sg:tags":[
        "away",
        "take"
    ],
    "wof:name":"Wok's To Eat",
    "wof:placetype":"venue"
},
  "geometry": {"coordinates":[153.30258178700001,-27.6126728058],"type":"Point"}
}