{
  "type": "Feature",
  "properties": {
    "addr:full":"132 Opal St Emerald QLD 4720",
    "addr:housenumber":"132",
    "addr:postcode":"4720",
    "addr:street":"Opal St",
    "iso:country":"AU",
    "sg:address":"132 Opal St",
    "sg:city":"Emerald",
    "sg:classifiers":[
        {
            "category":"Personal",
            "subcategory":"Massage",
            "type":"Services"
        }
    ],
    "sg:phone":"+61 7 4982 2541",
    "sg:postcode":"4720",
    "sg:province":"QLD",
    "sg:tags":[
        "therapy"
    ],
    "wof:name":"Greenfields Natural Health Clinic",
    "wof:placetype":"venue"
},
  "geometry": {"coordinates":[148.16357400000001,-23.526735],"type":"Point"}
}