{
  "type": "Feature",
  "properties": {
    "addr:full":"Shp 1 Strathfield Plz The Boulevarde Strathfield NSW 2135",
    "addr:housenumber":"1",
    "addr:postcode":"2135",
    "addr:street":"Strathfield Plz The Boulevarde",
    "iso:country":"AU",
    "sg:address":"Shp 1 Strathfield Plz The Boulevarde",
    "sg:city":"Strathfield",
    "sg:classifiers":[
        {
            "category":"Health Services",
            "subcategory":"Optometrist",
            "type":"Services"
        }
    ],
    "sg:phone":"+61 2 9763 2309",
    "sg:postcode":"2135",
    "sg:province":"NSW",
    "wof:name":"Philip Wendy, Ton Linda",
    "wof:placetype":"venue"
},
  "geometry": {"coordinates":[151.09259033199999,-33.8811225891],"type":"Point"}
}