{
  "type": "Feature",
  "properties": {
    "addr:full":"435- 439 High St Golden Square VIC 3555",
    "addr:housenumber":"435 439",
    "addr:postcode":"3555",
    "addr:street":"High St",
    "iso:country":"AU",
    "sg:address":"435- 439 High St",
    "sg:city":"Golden Square",
    "sg:classifiers":[
        {
            "category":"Military Area",
            "subcategory":"Air Force Base",
            "type":"Public Place"
        }
    ],
    "sg:phone":"+61 1800 420 145",
    "sg:postcode":"3555",
    "sg:province":"VIC",
    "sg:tags":[
        "water",
        "distilled"
    ],
    "wof:name":"Distilled Water Suppliers",
    "wof:placetype":"venue"
},
  "geometry": {"coordinates":[144.25448608400001,-36.7757835388],"type":"Point"}
}