{
  "type": "Feature",
  "properties": {
    "addr:full":"42B O&#039;Sullivan&#039;s Beach Rd Lonsdale SA 5160",
    "addr:housenumber":"42b",
    "addr:postcode":"5160",
    "addr:street":"O &;S Beach Rd",
    "iso:country":"AU",
    "sg:address":"42B O&#039;Sullivan&#039;s Beach Rd",
    "sg:city":"Lonsdale",
    "sg:classifiers":[
        {
            "category":"Government",
            "subcategory":"Department Of Motor Vehicles",
            "type":"Public Place"
        }
    ],
    "sg:phone":"+61 8 8326 2254",
    "sg:postcode":"5160",
    "sg:province":"SA",
    "sg:tags":[
        "wholesaler",
        "mfrs",
        "accessory"
    ],
    "wof:name":"Specialized Vehicle Enhancements",
    "wof:placetype":"venue"
},
  "geometry": {"coordinates":[138.50083923299999,-35.1063804626],"type":"Point"}
}