{
  "type": "Feature",
  "properties": {
    "addr:full":"2 Oakglen Rd Wyoming NSW 2250",
    "addr:housenumber":"2",
    "addr:postcode":"2250",
    "addr:street":"Oakglen Rd",
    "iso:country":"AU",
    "sg:address":"2 Oakglen Rd",
    "sg:city":"Wyoming",
    "sg:classifiers":[
        {
            "category":"Building & Trades",
            "subcategory":"Pest Control",
            "type":"Services"
        }
    ],
    "sg:phone":"+61 2 4324 2726",
    "sg:postcode":"2250",
    "sg:province":"NSW",
    "wof:name":"Dunn-Well Pest Control",
    "wof:placetype":"venue"
},
  "geometry": {"coordinates":[151.355636597,-33.4152374268],"type":"Point"}
}