{
  "type": "Feature",
  "properties": {
    "iso:country":"AU",
    "sg:address":"420 Mt Dandenong Rd",
    "sg:city":"Croydon",
    "sg:classifiers":[
        {
            "category":"Shopping",
            "subcategory":"Stationery & Office Supplies",
            "type":"Retail Goods"
        }
    ],
    "sg:phone":"+61 3 9725 5433",
    "sg:postcode":"3136",
    "sg:province":"VIC",
    "sg:tags":[
        "pencil",
        "pen",
        "repair"
    ],
    "wof:name":"HLB (Australia) Pty Ltd",
    "wof:placetype":"venue"
},
  "geometry": {"coordinates":[145.30384826700001,-37.8014526367],"type":"Point"}
}