{
  "type": "Feature",
  "properties": {
    "addr:full":"7 Beach Rd Snug TAS 7054",
    "addr:housenumber":"7",
    "addr:postcode":"7054",
    "addr:street":"Beach Rd",
    "iso:country":"AU",
    "sg:address":"7 Beach Rd",
    "sg:city":"Snug",
    "sg:classifiers":[
        {
            "category":"Health Services",
            "subcategory":"Doctor",
            "type":"Services"
        }
    ],
    "sg:phone":"+61 3 6267 9221",
    "sg:postcode":"7054",
    "sg:province":"TAS",
    "sg:tags":[
        "medical",
        "practitioner"
    ],
    "wof:name":"Ridgers Michael",
    "wof:placetype":"venue"
},
  "geometry": {"coordinates":[147.25680500000001,-43.065788],"type":"Point"}
}