{
  "type": "Feature",
  "properties": {
    "iso:country":"AU",
    "sg:address":"600 Waverley Rd",
    "sg:city":"Malvern East",
    "sg:classifiers":[
        {
            "category":"Utilities",
            "subcategory":"Electric",
            "type":"Services"
        }
    ],
    "sg:phone":"+61 3 9568 7759",
    "sg:postcode":"3145",
    "sg:province":"VIC",
    "sg:tags":[
        "tube",
        "lamps",
        "globe"
    ],
    "wof:name":"Chadstone Lighting",
    "wof:placetype":"venue"
},
  "geometry": {"coordinates":[145.078735352,-37.878704071],"type":"Point"}
}