{
  "type": "Feature",
  "properties": {
    "addr:full":"Suite 3a, 1 Forbes Rd Northbridge WA 6003",
    "addr:housenumber":"1",
    "addr:postcode":"6003",
    "addr:street":"Forbes Rd",
    "iso:country":"AU",
    "sg:address":"Suite 3a, 1 Forbes Rd",
    "sg:city":"Northbridge",
    "sg:classifiers":[
        {
            "category":"Health Services",
            "subcategory":"Health Practitioner",
            "type":"Services"
        }
    ],
    "sg:phone":"+61 8 9228 3018",
    "sg:postcode":"6003",
    "sg:province":"WA",
    "sg:tags":[
        "naturopath"
    ],
    "wof:name":"Body Care Traditional Chinese Natural Therapy",
    "wof:placetype":"venue"
},
  "geometry": {"coordinates":[115.859931946,-31.9437656403],"type":"Point"}
}