{
  "type": "Feature",
  "properties": {
    "addr:full":"Factory 3 14 Indy Crt Nerang QLD 4211",
    "addr:housenumber":"14",
    "addr:postcode":"4211",
    "addr:street":"Indy Crt",
    "iso:country":"AU",
    "sg:address":"Factory 3 14 Indy Crt",
    "sg:city":"Nerang",
    "sg:classifiers":[
        {
            "category":"Home & Garden",
            "subcategory":"Building Materials",
            "type":"Retail Goods"
        }
    ],
    "sg:phone":"+61 411 754 020",
    "sg:postcode":"4211",
    "sg:province":"QLD",
    "sg:tags":[
        "fencing"
    ],
    "wof:name":"Brushwood Polynesian Fencing",
    "wof:placetype":"venue"
},
  "geometry": {"coordinates":[153.348052978,-28.0104598999],"type":"Point"}
}