{
  "type": "Feature",
  "properties": {
    "iso:country":"AU",
    "sg:address":"Unit 13 Studio 2 Fitzgerald Ave",
    "sg:city":"Springwood",
    "sg:classifiers":[
        {
            "category":"Home & Garden",
            "subcategory":"Building Materials",
            "type":"Retail Goods"
        }
    ],
    "sg:phone":"+61 7 3208 1744",
    "sg:postcode":"4127",
    "sg:province":"QLD",
    "sg:tags":[
        "skylight"
    ],
    "wof:name":"Litedome Skylights",
    "wof:placetype":"venue"
},
  "geometry": {"coordinates":[153.126220703,-27.6121501923],"type":"Point"}
}