{
  "type": "Feature",
  "properties": {
    "iso:country":"AU",
    "sg:address":"Cottage Grove 150 Reynell Rd",
    "sg:city":"Woodcroft",
    "sg:classifiers":[
        {
            "category":"Health Services",
            "subcategory":"Nursing And Care Facility",
            "type":"Services"
        }
    ],
    "sg:phone":"+61 8 8322 6322",
    "sg:postcode":"5162",
    "sg:province":"SA",
    "sg:tags":[
        "home"
    ],
    "wof:name":"Eldercare Incorporated",
    "wof:placetype":"venue"
},
  "geometry": {"coordinates":[138.55929565400001,-35.0931015015],"type":"Point"}
}