{
  "type": "Feature",
  "properties": {
    "iso:country":"AU",
    "sg:address":"25 Preston St",
    "sg:city":"Como",
    "sg:classifiers":[
        {
            "category":"Real Estate",
            "subcategory":"Real Estate Agent",
            "type":"Services"
        }
    ],
    "sg:phone":"+61 8 9474 1440",
    "sg:postcode":"6152",
    "sg:province":"WA",
    "wof:name":"South Perth Apartments",
    "wof:placetype":"venue"
},
  "geometry": {"coordinates":[115.85923,-31.993877],"type":"Point"}
}