{
  "type": "Feature",
  "properties": {
    "iso:country":"AU",
    "sg:address":"Ste5/ 233 Cardigan St",
    "sg:city":"Carlton",
    "sg:classifiers":[
        {
            "category":"Real Estate",
            "subcategory":"Surveying",
            "type":"Services"
        }
    ],
    "sg:phone":"+61 3 9347 6556",
    "sg:postcode":"3053",
    "sg:province":"VIC",
    "sg:tags":[
        "building",
        "surveyor"
    ],
    "wof:name":"Approval Systems Pty Ltd",
    "wof:placetype":"venue"
},
  "geometry": {"coordinates":[144.96885681099999,-37.799282074],"type":"Point"}
}