{
  "type": "Feature",
  "properties": {
    "addr:full":"147 Loganlea Rd Meadowbrook QLD 4131",
    "addr:housenumber":"147",
    "addr:postcode":"4131",
    "addr:street":"Loganlea Rd",
    "iso:country":"AU",
    "sg:address":"147 Loganlea Rd",
    "sg:city":"Meadowbrook",
    "sg:classifiers":[
        {
            "category":"Professional",
            "subcategory":"Management & Consulting",
            "type":"Services"
        }
    ],
    "sg:phone":"+61 7 3200 2896",
    "sg:postcode":"4131",
    "sg:province":"QLD",
    "sg:tags":[
        "consultant"
    ],
    "wof:name":"Lifeback Systems",
    "wof:placetype":"venue"
},
  "geometry": {"coordinates":[153.13911438,-27.668554306],"type":"Point"}
}