{
  "type": "Feature",
  "properties": {
    "iso:country":"AU",
    "sg:address":"24 Pigeon St",
    "sg:city":"Werribee",
    "sg:classifiers":[
        {
            "category":"Banks & Credit Unions",
            "subcategory":"Financial Services",
            "type":"Services"
        }
    ],
    "sg:phone":"+61 3 9741 0148",
    "sg:postcode":"3030",
    "sg:province":"VIC",
    "sg:tags":[
        "annuity",
        "rollover",
        "superannuation",
        "consultant"
    ],
    "wof:name":"Emjay Insurance Agency",
    "wof:placetype":"venue"
},
  "geometry": {"coordinates":[144.66752600000001,-37.887756],"type":"Point"}
}