{
  "type": "Feature",
  "properties": {
    "addr:full":"2 Risby St Ulverstone TAS 7315",
    "addr:housenumber":"2",
    "addr:postcode":"7315",
    "addr:street":"Risby St",
    "iso:country":"AU",
    "sg:address":"2 Risby St",
    "sg:city":"Ulverstone",
    "sg:classifiers":[
        {
            "category":"Autos & Motor Vehicles",
            "subcategory":"Fuel & Gas Station",
            "type":"Retail Goods"
        }
    ],
    "sg:phone":"+61 3 6425 1824",
    "sg:postcode":"7315",
    "sg:province":"TAS",
    "wof:name":"Shell Four Ways Service Station",
    "wof:placetype":"venue"
},
  "geometry": {"coordinates":[146.17578125,-41.1580238342],"type":"Point"}
}