{
  "type": "Feature",
  "properties": {
    "addr:full":"61 Warraba Rd North Narrabeen NSW 2101",
    "addr:housenumber":"61",
    "addr:postcode":"2101",
    "addr:street":"Warraba Rd",
    "iso:country":"AU",
    "sg:address":"61 Warraba Rd",
    "sg:city":"North Narrabeen",
    "sg:classifiers":[
        {
            "category":"Retail",
            "subcategory":"Storage",
            "type":"Services"
        }
    ],
    "sg:phone":"+61 2 9913 8430",
    "sg:postcode":"2101",
    "sg:province":"NSW",
    "sg:tags":[
        "removal",
        "furniture"
    ],
    "wof:name":"Flash Removals",
    "wof:placetype":"venue"
},
  "geometry": {"coordinates":[151.29231300000001,-33.698696],"type":"Point"}
}