{
  "type": "Feature",
  "properties": {
    "iso:country":"AU",
    "sg:address":"Lot4/ Otterys Scrub Rd",
    "sg:city":"Walmer",
    "sg:classifiers":[
        {
            "category":"Building & Trades",
            "subcategory":"Landscaping Services",
            "type":"Services"
        }
    ],
    "sg:phone":"+61 3 5475 1928",
    "sg:postcode":"3463",
    "sg:province":"VIC",
    "sg:tags":[
        "stump",
        "tree",
        "felling",
        "removal"
    ],
    "wof:name":"Stump Man Sales & Service",
    "wof:placetype":"venue"
},
  "geometry": {"coordinates":[144.18066406200001,-36.9942359924],"type":"Point"}
}