{
  "type": "Feature",
  "properties": {
    "iso:country":"AU",
    "sg:address":"59 Albany Hwy",
    "sg:city":"Victoria Park",
    "sg:classifiers":[
        {
            "category":"Shopping",
            "subcategory":"Party Supplies",
            "type":"Retail Goods"
        }
    ],
    "sg:phone":"+61 8 9229 8900",
    "sg:postcode":"6100",
    "sg:province":"WA",
    "sg:tags":[
        "selling",
        "plan"
    ],
    "wof:name":"Nutrimetics",
    "wof:placetype":"venue"
},
  "geometry": {"coordinates":[115.893478394,-31.9712867737],"type":"Point"}
}