{
  "type": "Feature",
  "properties": {
    "addr:full":"568 Castra Rd Ulverstone TAS 7315",
    "addr:housenumber":"568",
    "addr:postcode":"7315",
    "addr:street":"Castra Rd",
    "iso:country":"AU",
    "sg:address":"568 Castra Rd",
    "sg:city":"Ulverstone",
    "sg:classifiers":[
        {
            "category":"Retail",
            "subcategory":"Repair Shop",
            "type":"Services"
        }
    ],
    "sg:phone":"+61 3 6425 9658",
    "sg:postcode":"7315",
    "sg:province":"TAS",
    "sg:tags":[
        "upholsterer"
    ],
    "wof:name":"E-Trim Upholstery",
    "wof:placetype":"venue"
},
  "geometry": {"coordinates":[146.175018311,-41.2117080688],"type":"Point"}
}