{
  "type": "Feature",
  "properties": {
    "addr:full":"PO Box 685 Innaloo WA 6918",
    "addr:postcode":"6918",
    "iso:country":"AU",
    "sg:address":"PO Box 685",
    "sg:city":"Innaloo",
    "sg:classifiers":[
        {
            "category":"Building & Trades",
            "subcategory":"Construction",
            "type":"Services"
        }
    ],
    "sg:phone":"+61 417 779 580",
    "sg:postcode":"6918",
    "sg:province":"WA",
    "sg:tags":[
        "bitumen",
        "paving",
        "asphalt"
    ],
    "wof:name":"Stirling Asphalt",
    "wof:placetype":"venue"
},
  "geometry": {"coordinates":[115.79221344,-31.888710022],"type":"Point"}
}