{
  "type": "Feature",
  "properties": {
    "addr:full":"577 Glen Huntly Rd Elsternwick VIC 3185",
    "addr:housenumber":"577",
    "addr:postcode":"3185",
    "addr:street":"Glen Huntly Rd",
    "iso:country":"AU",
    "sg:address":"577 Glen Huntly Rd",
    "sg:city":"Elsternwick",
    "sg:classifiers":[
        {
            "category":"Personal",
            "subcategory":"Massage",
            "type":"Services"
        }
    ],
    "sg:phone":"+61 3 9772 8632",
    "sg:postcode":"3185",
    "sg:province":"VIC",
    "sg:tags":[
        "therapy"
    ],
    "wof:name":"Being In Harmony Naturopathic Clinic",
    "wof:placetype":"venue"
},
  "geometry": {"coordinates":[145.013183594,-37.8856620789],"type":"Point"}
}