{
  "type": "Feature",
  "properties": {
    "iso:country":"AU",
    "sg:address":"Stokes Rd",
    "sg:city":"Quorn",
    "sg:classifiers":[
        {
            "category":"Education",
            "subcategory":"School",
            "type":"Public Place"
        }
    ],
    "sg:phone":"+61 8 8648 6101",
    "sg:postcode":"5433",
    "sg:province":"SA",
    "sg:tags":[
        "state",
        "except",
        "nsw"
    ],
    "wof:name":"Quorn Area School",
    "wof:placetype":"venue"
},
  "geometry": {"coordinates":[138.035842895,-32.3476867676],"type":"Point"}
}