{
  "type": "Feature",
  "properties": {
    "addr:full":"28 Loftus St Nambucca Heads NSW 2448",
    "addr:housenumber":"28",
    "addr:postcode":"2448",
    "addr:street":"Loftus St",
    "iso:country":"AU",
    "sg:address":"28 Loftus St",
    "sg:city":"Nambucca Heads",
    "sg:classifiers":[
        {
            "category":"Professional",
            "subcategory":"Art Services",
            "type":"Services"
        }
    ],
    "sg:phone":"+61 2 6568 6614",
    "sg:postcode":"2448",
    "sg:province":"NSW",
    "sg:tags":[
        "caricaturist",
        "cartoonist"
    ],
    "wof:name":"Gonad Man Pty Limited",
    "wof:placetype":"venue"
},
  "geometry": {"coordinates":[153.003311,-30.639894],"type":"Point"}
}