{
  "type": "Feature",
  "properties": {
    "addr:full":"2/ 12 Adrian St Welshpool WA 6106",
    "addr:housenumber":"/ 12",
    "addr:postcode":"6106",
    "addr:street":"Adrian St",
    "iso:country":"AU",
    "sg:address":"2/ 12 Adrian St",
    "sg:city":"Welshpool",
    "sg:classifiers":[
        {
            "category":"Structure",
            "subcategory":"Factory",
            "type":"Public Place"
        }
    ],
    "sg:phone":"+61 8 9362 6800",
    "sg:postcode":"6106",
    "sg:province":"WA",
    "sg:tags":[
        "seating",
        "system"
    ],
    "wof:name":"ISRI Seats Perth",
    "wof:placetype":"venue"
},
  "geometry": {"coordinates":[115.918418884,-31.9947967529],"type":"Point"}
}