{
  "type": "Feature",
  "properties": {
    "addr:full":"Unit 3 5 Coghill Drv Currumbin QLD 4223",
    "addr:housenumber":"5",
    "addr:postcode":"4223",
    "addr:street":"Coghill Drv",
    "iso:country":"AU",
    "sg:address":"Unit 3 5 Coghill Drv",
    "sg:city":"Currumbin",
    "sg:classifiers":[
        {
            "category":"Autos & Motor Vehicles",
            "subcategory":"Auto Supplies",
            "type":"Retail Goods"
        }
    ],
    "sg:phone":"+61 7 5534 7300",
    "sg:postcode":"4223",
    "sg:province":"QLD",
    "sg:tags":[
        "part",
        "cycles",
        "accessory"
    ],
    "wof:name":"Currumbin Motor Cycle Salvage",
    "wof:placetype":"venue"
},
  "geometry": {"coordinates":[153.474487305,-28.150592804],"type":"Point"}
}