{
  "type": "Feature",
  "properties": {
    "addr:full":"21 Higginbotham Rd Gladesville NSW 2111",
    "addr:housenumber":"21",
    "addr:postcode":"2111",
    "addr:street":"Higginbotham Rd",
    "iso:country":"AU",
    "sg:address":"21 Higginbotham Rd",
    "sg:city":"Gladesville",
    "sg:classifiers":[
        {
            "category":"Arts & Performance",
            "subcategory":"Theater",
            "type":"Entertainment"
        }
    ],
    "sg:phone":"+61 2 9809 4444",
    "sg:postcode":"2111",
    "sg:province":"NSW",
    "sg:tags":[
        "theatrical",
        "supply"
    ],
    "wof:name":"Theatricks Productions Pty Ltd",
    "wof:placetype":"venue"
},
  "geometry": {"coordinates":[151.124923706,-33.8177833557],"type":"Point"}
}