{
  "type": "Feature",
  "properties": {
    "addr:full":"266 Green St Ulladulla NSW 2539",
    "addr:housenumber":"266",
    "addr:postcode":"2539",
    "addr:street":"Green St",
    "iso:country":"AU",
    "sg:address":"266 Green St",
    "sg:city":"Ulladulla",
    "sg:classifiers":[
        {
            "category":"Real Estate",
            "subcategory":"Surveying",
            "type":"Services"
        }
    ],
    "sg:phone":"+61 2 4454 2137",
    "sg:postcode":"2539",
    "sg:province":"NSW",
    "sg:tags":[
        "surveyor",
        "land"
    ],
    "wof:name":"Beasley G A",
    "wof:placetype":"venue"
},
  "geometry": {"coordinates":[150.472091675,-35.3569068909],"type":"Point"}
}