{
  "type": "Feature",
  "properties": {
    "addr:full":"32- 36 Sunderland St Moonah TAS 7009",
    "addr:housenumber":"36",
    "addr:postcode":"7009",
    "addr:street":"Sunderland St",
    "iso:country":"AU",
    "sg:address":"32- 36 Sunderland St",
    "sg:city":"Moonah",
    "sg:classifiers":[
        {
            "category":"Shopping",
            "subcategory":"Stationery & Office Supplies",
            "type":"Retail Goods"
        }
    ],
    "sg:phone":"+61 3 6272 3366",
    "sg:postcode":"7009",
    "sg:province":"TAS",
    "sg:tags":[
        "packaging",
        "material"
    ],
    "wof:name":"Protect-A-Clean Pty Ltd",
    "wof:placetype":"venue"
},
  "geometry": {"coordinates":[147.29478454599999,-42.8432006836],"type":"Point"}
}