{
  "type": "Feature",
  "properties": {
    "iso:country":"AU",
    "sg:address":"Lvl 1/ 5 Raglan St",
    "sg:city":"South Melbourne",
    "sg:classifiers":[
        {
            "category":"Real Estate",
            "subcategory":"Architect",
            "type":"Services"
        }
    ],
    "sg:phone":"+61 3 9686 1899",
    "sg:postcode":"3205",
    "sg:province":"VIC",
    "wof:name":"Artillery Architecture & Interior Design Aust",
    "wof:placetype":"venue"
},
  "geometry": {"coordinates":[144.966614,-37.836403],"type":"Point"}
}