{
  "type": "Feature",
  "properties": {
    "addr:full":"Lvl 1/ 5 Raglan St South Melbourne VIC 3205",
    "addr:housenumber":"/ 5",
    "addr:postcode":"3205",
    "addr:street":"Raglan St",
    "iso:country":"AU",
    "sg:address":"Lvl 1/ 5 Raglan St",
    "sg:city":"South Melbourne",
    "sg:classifiers":[
        {
            "category":"Real Estate",
            "subcategory":"Architect",
            "type":"Services"
        }
    ],
    "sg:phone":"+61 3 9686 1899",
    "sg:postcode":"3205",
    "sg:province":"VIC",
    "wof:name":"Artillery Architecture & Interior Design Aust",
    "wof:placetype":"venue"
},
  "geometry": {"coordinates":[144.96661399999999,-37.836403],"type":"Point"}
}