{
  "type": "Feature",
  "properties": {
    "addr:full":"18 Hammer Crt Hoppers Crossing VIC 3029",
    "addr:housenumber":"18",
    "addr:postcode":"3029",
    "addr:street":"Hammer Crt",
    "iso:country":"AU",
    "sg:address":"18 Hammer Crt",
    "sg:city":"Hoppers Crossing",
    "sg:classifiers":[
        {
            "category":"Government",
            "subcategory":"Police Station",
            "type":"Public Place"
        }
    ],
    "sg:phone":"+61 3 9974 6770",
    "sg:postcode":"3029",
    "sg:province":"VIC",
    "sg:tags":[
        "steering",
        "power"
    ],
    "wof:name":"Pedders Suspension",
    "wof:placetype":"venue"
},
  "geometry": {"coordinates":[144.72418200000001,-37.872868],"type":"Point"}
}