{
  "type": "Feature",
  "properties": {
    "addr:full":"85 Warwick St Toowoomba QLD 4350",
    "addr:housenumber":"85",
    "addr:postcode":"4350",
    "addr:street":"Warwick St",
    "iso:country":"AU",
    "sg:address":"85 Warwick St",
    "sg:city":"Toowoomba",
    "sg:classifiers":[
        {
            "category":"Food & Beverages",
            "subcategory":"Bakery",
            "type":"Retail Goods"
        }
    ],
    "sg:phone":"+61 1800 076 205",
    "sg:postcode":"4350",
    "sg:province":"QLD",
    "sg:tags":[
        "baker"
    ],
    "wof:name":"Homestyle Bake Pty Ltd",
    "wof:placetype":"venue"
},
  "geometry": {"coordinates":[151.92546100000001,-27.575254],"type":"Point"}
}