{
  "type": "Feature",
  "properties": {
    "addr:full":"Suite 208/413- 415 Sussex St Sydney NSW 2000",
    "addr:housenumber":"/ 413 415",
    "addr:postcode":"2000",
    "addr:street":"Sussex St",
    "iso:country":"AU",
    "sg:address":"Suite 208/413- 415 Sussex St",
    "sg:city":"Sydney",
    "sg:classifiers":[
        {
            "category":"Travel",
            "subcategory":"Travel Agent",
            "type":"Entertainment"
        }
    ],
    "sg:phone":"+61 2 9211 6833",
    "sg:postcode":"2000",
    "sg:province":"NSW",
    "sg:tags":[
        "consultant"
    ],
    "wof:name":"Sunny World Travel Pty Ltd",
    "wof:placetype":"venue"
},
  "geometry": {"coordinates":[151.20469665499999,-33.8788375854],"type":"Point"}
}