{
  "type": "Feature",
  "properties": {
    "iso:country":"AU",
    "sg:address":"903 Nepean Hwy",
    "sg:city":"Mornington",
    "sg:classifiers":[
        {
            "category":"Manufacturing",
            "subcategory":"Motor Vehicles & Parts",
            "type":"Manufacturing & Wholesale Goods"
        }
    ],
    "sg:phone":"+61 3 5975 9699",
    "sg:postcode":"3931",
    "sg:province":"VIC",
    "sg:tags":[
        "replacement"
    ],
    "wof:name":"Burson Automotive Pty Ltd",
    "wof:placetype":"venue"
},
  "geometry": {"coordinates":[145.04722595199999,-38.2273674011],"type":"Point"}
}