{
  "type": "Feature",
  "properties": {
    "addr:full":"Shop: 14 258 Springvale Rd Springvale VIC 3171",
    "addr:housenumber":"shop 14 258",
    "addr:postcode":"3171",
    "addr:street":"Springvale Rd",
    "iso:country":"AU",
    "sg:address":"Shop: 14 258 Springvale Rd",
    "sg:city":"Springvale",
    "sg:classifiers":[
        {
            "category":"Shopping",
            "subcategory":"Jewelry",
            "type":"Retail Goods"
        }
    ],
    "sg:phone":"+61 3 9548 3210",
    "sg:postcode":"3171",
    "sg:province":"VIC",
    "sg:tags":[
        "jeweller"
    ],
    "wof:name":"Tin Phat",
    "wof:placetype":"venue"
},
  "geometry": {"coordinates":[145.152267456,-37.9509735107],"type":"Point"}
}