{
  "type": "Feature",
  "properties": {
    "iso:country":"AU",
    "sg:address":"33 Main St",
    "sg:city":"Wooli",
    "sg:classifiers":[
        {
            "category":"Retail",
            "subcategory":"Auto Repair",
            "type":"Services"
        }
    ],
    "sg:phone":"+61 2 6649 7898",
    "sg:postcode":"2462",
    "sg:province":"NSW",
    "sg:tags":[
        "repairer",
        "motor",
        "engineer"
    ],
    "wof:name":"Wooli Auto Port",
    "wof:placetype":"venue"
},
  "geometry": {"coordinates":[153.265533447,-29.8696975708],"type":"Point"}
}