{
  "type": "Feature",
  "properties": {
    "addr:full":"Level 1/ 235 Whitehorse Rd Balwyn VIC 3103",
    "addr:housenumber":"/ 235",
    "addr:postcode":"3103",
    "addr:street":"Whitehorse Rd",
    "iso:country":"AU",
    "sg:address":"Level 1/ 235 Whitehorse Rd",
    "sg:city":"Balwyn",
    "sg:classifiers":[
        {
            "category":"Personal",
            "subcategory":"Massage",
            "type":"Services"
        }
    ],
    "sg:phone":"+61 3 9816 8322",
    "sg:postcode":"3103",
    "sg:province":"VIC",
    "sg:tags":[
        "therapy"
    ],
    "wof:name":"Re-fresh Skin & Body",
    "wof:placetype":"venue"
},
  "geometry": {"coordinates":[145.07574462900001,-37.8120193481],"type":"Point"}
}