{
  "type": "Feature",
  "properties": {
    "addr:full":"241 Tamborine- Oxenford Rd Oxenford QLD 4210",
    "addr:housenumber":"241",
    "addr:postcode":"4210",
    "addr:street":"Tamborine Oxenford Rd",
    "iso:country":"AU",
    "sg:address":"241 Tamborine- Oxenford Rd",
    "sg:city":"Oxenford",
    "sg:classifiers":[
        {
            "category":"Building & Trades",
            "subcategory":"Equipment Rental",
            "type":"Services"
        }
    ],
    "sg:phone":"+61 7 5580 6499",
    "sg:postcode":"4210",
    "sg:province":"QLD",
    "sg:tags":[
        "demolition",
        "contractor"
    ],
    "wof:name":"North End Skip Hire-Landfill",
    "wof:placetype":"venue"
},
  "geometry": {"coordinates":[153.295684814,-27.9020900726],"type":"Point"}
}