{
  "type": "Feature",
  "properties": {
    "addr:full":"Cnr Morphett & Sturt Rds Marion SA 5043",
    "addr:postcode":"5043",
    "addr:street":"Cnr",
    "iso:country":"AU",
    "sg:address":"Cnr Morphett & Sturt Rds",
    "sg:city":"Marion",
    "sg:classifiers":[
        {
            "category":"Fast Food",
            "type":"Food & Drink"
        }
    ],
    "sg:phone":"+61 8 8298 8500",
    "sg:postcode":"5043",
    "sg:province":"SA",
    "sg:tags":[
        "away",
        "take"
    ],
    "wof:name":"Pizza Hut Delivery",
    "wof:placetype":"venue"
},
  "geometry": {"coordinates":[138.54098500000001,-35.018211],"type":"Point"}
}