{
  "type": "Feature",
  "properties": {
    "addr:full":"14 Dawson St Sale VIC 3850",
    "addr:housenumber":"14",
    "addr:postcode":"3850",
    "addr:street":"Dawson St",
    "iso:country":"AU",
    "sg:address":"14 Dawson St",
    "sg:city":"Sale",
    "sg:classifiers":[
        {
            "category":"Building & Trades",
            "subcategory":"Plumbing",
            "type":"Services"
        }
    ],
    "sg:phone":"+61 3 5144 1769",
    "sg:postcode":"3850",
    "sg:province":"VIC",
    "sg:tags":[
        "fitting",
        "hose",
        "supply"
    ],
    "wof:name":"Hydeng",
    "wof:placetype":"venue"
},
  "geometry": {"coordinates":[147.09223938,-38.1011352539],"type":"Point"}
}