{
  "type": "Feature",
  "properties": {
    "iso:country":"AU",
    "sg:address":"9 Nylander St",
    "sg:city":"Parap",
    "sg:classifiers":[
        {
            "category":"Utilities",
            "subcategory":"Water",
            "type":"Services"
        }
    ],
    "sg:phone":"+61 8 8924 9700",
    "sg:postcode":"0820",
    "sg:province":"NT",
    "sg:tags":[
        "hot",
        "system"
    ],
    "wof:name":"Combined Electrical",
    "wof:placetype":"venue"
},
  "geometry": {"coordinates":[130.839233398,-12.4385251999],"type":"Point"}
}