{
  "type": "Feature",
  "properties": {
    "addr:full":"Lot 7 Coalfields Hwy Darkan WA 6392",
    "addr:postcode":"6392",
    "addr:street":"Coalfields Hwy",
    "iso:country":"AU",
    "sg:address":"Lot 7 Coalfields Hwy",
    "sg:city":"Darkan",
    "sg:classifiers":[
        {
            "category":"Professional",
            "subcategory":"Engineering",
            "type":"Services"
        }
    ],
    "sg:phone":"+61 8 9736 1360",
    "sg:postcode":"6392",
    "sg:province":"WA",
    "sg:tags":[
        "engineer"
    ],
    "wof:name":"Cole Equipment",
    "wof:placetype":"venue"
},
  "geometry": {"coordinates":[116.74449157700001,-33.3353614807],"type":"Point"}
}