{
  "type": "Feature",
  "properties": {
    "iso:country":"AU",
    "sg:address":"17 Ridgehill Crt",
    "sg:city":"Ellenbrook",
    "sg:classifiers":[
        {
            "category":"Building & Trades",
            "subcategory":"Plumbing",
            "type":"Services"
        }
    ],
    "sg:phone":"+61 448 879 299",
    "sg:postcode":"6069",
    "sg:province":"WA",
    "sg:tags":[
        "plumber",
        "gasfitters"
    ],
    "wof:name":"Schmickford Plumbing & Gas",
    "wof:placetype":"venue"
},
  "geometry": {"coordinates":[115.977050781,-31.7851161957],"type":"Point"}
}