{
  "type": "Feature",
  "properties": {
    "iso:country":"AU",
    "sg:address":"3/ 63 Blaxland Rd",
    "sg:city":"Campbelltown",
    "sg:classifiers":[
        {
            "category":"Autos & Motor Vehicles",
            "subcategory":"Automobile Sales",
            "type":"Retail Goods"
        }
    ],
    "sg:phone":"+61 2 4628 6900",
    "sg:postcode":"2560",
    "sg:province":"NSW",
    "sg:tags":[
        "equipment",
        "trailer"
    ],
    "wof:name":"Willex Trailer Axle Sales",
    "wof:placetype":"venue"
},
  "geometry": {"coordinates":[150.810302734,-34.061542511],"type":"Point"}
}