{
  "type": "Feature",
  "properties": {
    "addr:full":"27 Cradle Rd Diggers Rest VIC 3427",
    "addr:housenumber":"27",
    "addr:postcode":"3427",
    "addr:street":"Cradle Rd",
    "iso:country":"AU",
    "sg:address":"27 Cradle Rd",
    "sg:city":"Diggers Rest",
    "sg:classifiers":[
        {
            "category":"Fast Food",
            "type":"Food & Drink"
        }
    ],
    "sg:phone":"+61 3 9740 1955",
    "sg:postcode":"3427",
    "sg:province":"VIC",
    "sg:tags":[
        "away",
        "take"
    ],
    "wof:name":"Diggers Take-Away",
    "wof:placetype":"venue"
},
  "geometry": {"coordinates":[144.713058472,-37.6222953796],"type":"Point"}
}