{
  "type": "Feature",
  "properties": {
    "iso:country":"AU",
    "sg:address":"Koojedda Rd",
    "sg:city":"Bakers Hill",
    "sg:classifiers":[
        {
            "category":"Building & Trades",
            "subcategory":"Construction",
            "type":"Services"
        }
    ],
    "sg:phone":"+61 8 9574 1124",
    "sg:postcode":"6562",
    "sg:province":"WA",
    "sg:tags":[
        "welding"
    ],
    "wof:name":"Carnegie R A Contracting",
    "wof:placetype":"venue"
},
  "geometry": {"coordinates":[116.44651,-31.749367],"type":"Point"}
}