{
  "type": "Feature",
  "properties": {
    "iso:country":"AU",
    "sg:address":"99 High St",
    "sg:city":"East Maitland",
    "sg:classifiers":[
        {
            "category":"Food & Beverages",
            "subcategory":"Fruits & Vegetables",
            "type":"Retail Goods"
        }
    ],
    "sg:phone":"+61 2 4933 1131",
    "sg:postcode":"2323",
    "sg:province":"NSW",
    "sg:tags":[
        "greengrocer",
        "fruiterer"
    ],
    "wof:name":"McKimms Fruit Market",
    "wof:placetype":"venue"
},
  "geometry": {"coordinates":[151.58996582,-32.7509727478],"type":"Point"}
}