{
  "type": "Feature",
  "properties": {
    "iso:country":"AU",
    "sg:address":"Manthorpe St",
    "sg:city":"Dry Creek",
    "sg:classifiers":[
        {
            "category":"Transit Center",
            "subcategory":"Freight",
            "type":"Transportation"
        }
    ],
    "sg:phone":"+61 8 8405 7600",
    "sg:postcode":"5094",
    "sg:province":"SA",
    "sg:tags":[
        "equipment",
        "transport",
        "road",
        "vehicle"
    ],
    "wof:name":"Southern Cross Trailers",
    "wof:placetype":"venue"
},
  "geometry": {"coordinates":[138.589447022,-34.8372955322],"type":"Point"}
}