{
  "type": "Feature",
  "properties": {
    "iso:country":"AU",
    "sg:address":"12 Robinson St",
    "sg:city":"Carnarvon",
    "sg:classifiers":[
        {
            "category":"Travel",
            "subcategory":"Travel Agent",
            "type":"Entertainment"
        }
    ],
    "sg:phone":"+61 8 9941 1007",
    "sg:postcode":"6701",
    "sg:province":"WA",
    "sg:tags":[
        "consultant"
    ],
    "wof:name":"Jetset",
    "wof:placetype":"venue"
},
  "geometry": {"coordinates":[113.656051636,-24.8852844238],"type":"Point"}
}