{
  "type": "Feature",
  "properties": {
    "addr:full":"37 Etna St Gosford NSW 2250",
    "addr:housenumber":"37",
    "addr:postcode":"2250",
    "addr:street":"Etna St",
    "iso:country":"AU",
    "sg:address":"37 Etna St",
    "sg:city":"Gosford",
    "sg:classifiers":[
        {
            "category":"Health Services",
            "subcategory":"Dentist",
            "type":"Services"
        }
    ],
    "sg:phone":"+61 2 4323 2828",
    "sg:postcode":"2250",
    "sg:province":"NSW",
    "wof:name":"Low, Charles R",
    "wof:placetype":"venue"
},
  "geometry": {"coordinates":[151.344482422,-33.4192848206],"type":"Point"}
}