{
  "type": "Feature",
  "properties": {
    "addr:full":"291 Burwood Rd Hawthorn VIC 3122",
    "addr:housenumber":"291",
    "addr:postcode":"3122",
    "addr:street":"Burwood Rd",
    "iso:country":"AU",
    "sg:address":"291 Burwood Rd",
    "sg:city":"Hawthorn",
    "sg:classifiers":[
        {
            "category":"Banks & Credit Unions",
            "subcategory":"Financial Services",
            "type":"Services"
        }
    ],
    "sg:phone":"+61 3 9810 0700",
    "sg:postcode":"3122",
    "sg:province":"VIC",
    "sg:tags":[
        "planning"
    ],
    "wof:name":"Count Wealth Accountants",
    "wof:placetype":"venue"
},
  "geometry": {"coordinates":[145.03260803200001,-37.8221549988],"type":"Point"}
}