{
  "type": "Feature",
  "properties": {
    "iso:country":"AU",
    "sg:address":"10 Wilson St",
    "sg:city":"Royal Park",
    "sg:classifiers":[
        {
            "category":"Professional",
            "type":"Services"
        }
    ],
    "sg:phone":"+61 8 8241 2727",
    "sg:postcode":"5014",
    "sg:province":"SA",
    "sg:tags":[
        "shop",
        "fitting"
    ],
    "wof:name":"Five Star Cabinets Australia Pty Ltd",
    "wof:placetype":"venue"
},
  "geometry": {"coordinates":[138.507354736,-34.8680114746],"type":"Point"}
}