{
  "type": "Feature",
  "properties": {
    "addr:full":"\"Maison La Plage\" 5 Hastings St Noosa Heads QLD 4567",
    "addr:housenumber":"5",
    "addr:postcode":"4567",
    "addr:street":"Hastings St",
    "iso:country":"AU",
    "sg:address":"\"Maison La Plage\" 5 Hastings St",
    "sg:city":"Noosa Heads",
    "sg:classifiers":[
        {
            "category":"Shopping",
            "subcategory":"Jewelry",
            "type":"Retail Goods"
        }
    ],
    "sg:phone":"+61 7 5473 5277",
    "sg:postcode":"4567",
    "sg:province":"QLD",
    "sg:tags":[
        "jeweller"
    ],
    "wof:name":"Up & Up North",
    "wof:placetype":"venue"
},
  "geometry": {"coordinates":[153.087356567,-26.3860435486],"type":"Point"}
}