{
  "type": "Feature",
  "properties": {
    "addr:full":"Unit 2/ 17 Westside Drv Laverton North VIC 3026",
    "addr:housenumber":"17",
    "addr:postcode":"3026",
    "addr:street":"Westside Drv",
    "iso:country":"AU",
    "sg:address":"Unit 2/ 17 Westside Drv",
    "sg:city":"Laverton North",
    "sg:classifiers":[
        {
            "category":"Building & Trades",
            "subcategory":"Equipment Rental",
            "type":"Services"
        }
    ],
    "sg:phone":"+61 3 9318 9988",
    "sg:postcode":"3026",
    "sg:province":"VIC",
    "sg:tags":[
        "wool",
        "processing"
    ],
    "wof:name":"Andar Tool & Press Ltd",
    "wof:placetype":"venue"
},
  "geometry": {"coordinates":[144.82261700000001,-37.818504],"type":"Point"}
}