{
  "type": "Feature",
  "properties": {
    "iso:country":"AU",
    "sg:address":"6A First Ave",
    "sg:city":"Caloundra",
    "sg:classifiers":[
        {
            "category":"Health Services",
            "subcategory":"Health Practitioner",
            "type":"Services"
        }
    ],
    "sg:phone":"+61 7 5491 7277",
    "sg:postcode":"4551",
    "sg:province":"QLD",
    "sg:tags":[
        "osteopath"
    ],
    "wof:name":"Naylor Tom Dr",
    "wof:placetype":"venue"
},
  "geometry": {"coordinates":[153.123657227,-26.8034286499],"type":"Point"}
}