{
  "type": "Feature",
  "properties": {
    "iso:country":"AU",
    "sg:address":"Station St",
    "sg:city":"Colbinabbin",
    "sg:classifiers":[
        {
            "category":"Home & Garden",
            "subcategory":"Garden Supply",
            "type":"Retail Goods"
        }
    ],
    "sg:phone":"+61 3 5432 9303",
    "sg:postcode":"3559",
    "sg:province":"VIC",
    "sg:tags":[
        "fertilizer"
    ],
    "wof:name":"Colbinabbin Fertilisers Pty Ltd",
    "wof:placetype":"venue"
},
  "geometry": {"coordinates":[144.79421997099999,-36.5883331299],"type":"Point"}
}