{
  "type": "Feature",
  "properties": {
    "addr:full":"Showgrounds Cecil St Benalla VIC 3672",
    "addr:postcode":"3672",
    "addr:street":"Cecil St",
    "iso:country":"AU",
    "sg:address":"Showgrounds Cecil St",
    "sg:city":"Benalla",
    "sg:classifiers":[
        {
            "category":"Arena",
            "subcategory":"Sports Club",
            "type":"Entertainment"
        }
    ],
    "sg:phone":"+61 3 5762 1645",
    "sg:postcode":"3672",
    "sg:province":"VIC",
    "sg:tags":[
        "australian",
        "football",
        "rule"
    ],
    "wof:name":"Benalla Saints Sports Club Inc",
    "wof:placetype":"venue"
},
  "geometry": {"coordinates":[145.977036,-36.558769],"type":"Point"}
}