{
  "type": "Feature",
  "properties": {
    "addr:full":"369 Edward St Wagga Wagga NSW 2650",
    "addr:housenumber":"369",
    "addr:postcode":"2650",
    "addr:street":"Edward St",
    "iso:country":"AU",
    "sg:address":"369 Edward St",
    "sg:city":"Wagga Wagga",
    "sg:classifiers":[
        {
            "category":"Autos & Motor Vehicles",
            "subcategory":"Automobile Sales",
            "type":"Retail Goods"
        }
    ],
    "sg:phone":"+61 2 6925 3988",
    "sg:postcode":"2650",
    "sg:province":"NSW",
    "sg:tags":[
        "car",
        "used"
    ],
    "wof:name":"Wagga Car Sales",
    "wof:placetype":"venue"
},
  "geometry": {"coordinates":[147.348556519,-35.1158103943],"type":"Point"}
}