{
  "type": "Feature",
  "properties": {
    "iso:country":"AU",
    "sg:address":"2- 6 Rathdowne St",
    "sg:city":"Carlton",
    "sg:classifiers":[
        {
            "category":"Autos & Motor Vehicles",
            "subcategory":"Fuel & Gas Station",
            "type":"Retail Goods"
        }
    ],
    "sg:phone":"+61 3 9347 4930",
    "sg:postcode":"3053",
    "sg:province":"VIC",
    "wof:name":"BP Australia Pty Ltd",
    "wof:placetype":"venue"
},
  "geometry": {"coordinates":[144.970245361,-37.800403595],"type":"Point"}
}