{
  "type": "Feature",
  "properties": {
    "addr:full":"14/ 16 Bosworth St Richmond NSW 2753",
    "addr:housenumber":"14 / 16",
    "addr:postcode":"2753",
    "addr:street":"Bosworth St",
    "iso:country":"AU",
    "sg:address":"14/ 16 Bosworth St",
    "sg:city":"Richmond",
    "sg:classifiers":[
        {
            "category":"Professional",
            "subcategory":"Computer Services",
            "type":"Services"
        }
    ],
    "sg:phone":"+61 2 4588 5633",
    "sg:postcode":"2753",
    "sg:province":"NSW",
    "sg:tags":[
        "tele-communications",
        "consultant"
    ],
    "wof:name":"Pacific Research Pty Ltd",
    "wof:placetype":"venue"
},
  "geometry": {"coordinates":[150.74801635700001,-33.5950622559],"type":"Point"}
}