{
  "type": "Feature",
  "properties": {
    "addr:full":"7 Westgate St Wacol QLD 4076",
    "addr:housenumber":"7",
    "addr:postcode":"4076",
    "addr:street":"Westgate St",
    "iso:country":"AU",
    "sg:address":"7 Westgate St",
    "sg:city":"Wacol",
    "sg:classifiers":[
        {
            "category":"Shopping",
            "type":"Retail Goods"
        }
    ],
    "sg:phone":"+61 7 3271 6789",
    "sg:postcode":"4076",
    "sg:province":"QLD",
    "sg:tags":[
        "equipment",
        "safety",
        "accessory"
    ],
    "wof:name":"Independent Welding Supplies",
    "wof:placetype":"venue"
},
  "geometry": {"coordinates":[152.93414306599999,-27.5905761719],"type":"Point"}
}