{
  "type": "Feature",
  "properties": {
    "addr:full":"29 Winton Road Joondalup WA 6027",
    "addr:housenumber":"29",
    "addr:postcode":"6027",
    "addr:street":"Winton Road",
    "iso:country":"AU",
    "sg:address":"29 Winton Road",
    "sg:city":"Joondalup",
    "sg:classifiers":[
        {
            "category":"Professional",
            "subcategory":"Art Services",
            "type":"Services"
        }
    ],
    "sg:phone":"+61 8 9300 2011",
    "sg:postcode":"6027",
    "sg:province":"WA",
    "sg:tags":[
        "graphic",
        "designer"
    ],
    "wof:name":"The Printing Factory",
    "wof:placetype":"venue"
},
  "geometry": {"coordinates":[115.762573242,-31.7507286072],"type":"Point"}
}