{
  "type": "Feature",
  "properties": {
    "iso:country":"AU",
    "sg:address":"11 Forsyth St",
    "sg:city":"O'Connor",
    "sg:classifiers":[
        {
            "category":"Autos & Motor Vehicles",
            "subcategory":"Boat Sales",
            "type":"Retail Goods"
        }
    ],
    "sg:phone":"+61 8 9314 3055",
    "sg:postcode":"6163",
    "sg:province":"WA",
    "sg:tags":[
        "equipment",
        "yacht"
    ],
    "wof:name":"RMS Engines",
    "wof:placetype":"venue"
},
  "geometry": {"coordinates":[115.793083,-32.054981],"type":"Point"}
}