{
  "type": "Feature",
  "properties": {
    "addr:full":"13 Crusade Ave Padstow NSW 2211",
    "addr:housenumber":"13",
    "addr:postcode":"2211",
    "addr:street":"Crusade Ave",
    "iso:country":"AU",
    "sg:address":"13 Crusade Ave",
    "sg:city":"Padstow",
    "sg:classifiers":[
        {
            "category":"Education",
            "subcategory":"Kindergarten",
            "type":"Public Place"
        }
    ],
    "sg:phone":"+61 2 9773 6762",
    "sg:postcode":"2211",
    "sg:province":"NSW",
    "sg:tags":[
        "pre-schools"
    ],
    "wof:name":"Friendly Faces Childcare",
    "wof:placetype":"venue"
},
  "geometry": {"coordinates":[151.029449,-33.952686],"type":"Point"}
}