{
  "type": "Feature",
  "properties": {
    "iso:country":"AU",
    "sg:address":"30 Mabel St",
    "sg:city":"Georgetown",
    "sg:classifiers":[
        {
            "category":"Professional",
            "subcategory":"Art Services",
            "type":"Services"
        }
    ],
    "sg:phone":"+61 2 4968 2345",
    "sg:postcode":"2298",
    "sg:province":"NSW",
    "sg:tags":[
        "graphic",
        "designer"
    ],
    "wof:name":"Reprobyte",
    "wof:placetype":"venue"
},
  "geometry": {"coordinates":[151.732955933,-32.907371521],"type":"Point"}
}