{
  "type": "Feature",
  "properties": {
    "addr:full":"2 Moody Crt Roxburgh Park VIC 3064",
    "addr:housenumber":"2",
    "addr:postcode":"3064",
    "addr:street":"Moody Crt",
    "iso:country":"AU",
    "sg:address":"2 Moody Crt",
    "sg:city":"Roxburgh Park",
    "sg:classifiers":[
        {
            "category":"Home & Garden",
            "subcategory":"Building Materials",
            "type":"Retail Goods"
        }
    ],
    "sg:phone":"+61 3 9305 2775",
    "sg:postcode":"3064",
    "sg:province":"VIC",
    "sg:tags":[
        "lawn",
        "cutting",
        "maintenance"
    ],
    "wof:name":"Kunos Mowing",
    "wof:placetype":"venue"
},
  "geometry": {"coordinates":[144.929443359,-37.6363334656],"type":"Point"}
}