{
  "type": "Feature",
  "properties": {
    "addr:full":"30 Hamilton St Cannington WA 6107",
    "addr:housenumber":"30",
    "addr:postcode":"6107",
    "addr:street":"Hamilton St",
    "iso:country":"AU",
    "sg:address":"30 Hamilton St",
    "sg:city":"Cannington",
    "sg:classifiers":[
        {
            "category":"Building & Trades",
            "subcategory":"Construction",
            "type":"Services"
        }
    ],
    "sg:phone":"+61 13 63 70",
    "sg:postcode":"6107",
    "sg:province":"WA",
    "sg:tags":[
        "window",
        "tinting"
    ],
    "wof:name":"Sol Ace",
    "wof:placetype":"venue"
},
  "geometry": {"coordinates":[115.92672729500001,-32.010799408],"type":"Point"}
}