{
  "type": "Feature",
  "properties": {
    "addr:full":"150 Forest Rd Hurstville NSW 2220",
    "addr:housenumber":"150",
    "addr:postcode":"2220",
    "addr:street":"Forest Rd",
    "iso:country":"AU",
    "sg:address":"150 Forest Rd",
    "sg:city":"Hurstville",
    "sg:classifiers":[
        {
            "category":"Professional",
            "subcategory":"Computer Services",
            "type":"Services"
        }
    ],
    "sg:phone":"+61 2 9586 0678",
    "sg:postcode":"2220",
    "sg:province":"NSW",
    "sg:tags":[
        "consultant",
        "system"
    ],
    "wof:name":"Auswanda Technology",
    "wof:placetype":"venue"
},
  "geometry": {"coordinates":[151.10345459000001,-33.9673309326],"type":"Point"}
}