{
  "type": "Feature",
  "properties": {
    "iso:country":"AU",
    "sg:address":"30 Miller St",
    "sg:city":"Unley",
    "sg:classifiers":[
        {
            "category":"Travel",
            "subcategory":"Travel Agent",
            "type":"Entertainment"
        }
    ],
    "sg:phone":"+61 428 603 303",
    "sg:postcode":"5061",
    "sg:province":"SA",
    "sg:tags":[
        "tour",
        "holiday",
        "adventure"
    ],
    "wof:name":"Team Merlin",
    "wof:placetype":"venue"
},
  "geometry": {"coordinates":[138.601287842,-34.9430541992],"type":"Point"}
}