{
  "type": "Feature",
  "properties": {
    "addr:full":"148 Parker St Cootamundra NSW 2590",
    "addr:housenumber":"148",
    "addr:postcode":"2590",
    "addr:street":"Parker St",
    "iso:country":"AU",
    "sg:address":"148 Parker St",
    "sg:city":"Cootamundra",
    "sg:classifiers":[
        {
            "category":"Personal",
            "type":"Services"
        }
    ],
    "sg:phone":"+61 2 6942 2992",
    "sg:postcode":"2590",
    "sg:province":"NSW",
    "sg:tags":[
        "career",
        "counselling"
    ],
    "wof:name":"Wagga Wagga Compact",
    "wof:placetype":"venue"
},
  "geometry": {"coordinates":[148.02195739699999,-34.641078949],"type":"Point"}
}