{
  "type": "Feature",
  "properties": {
    "addr:full":"341 Lygon St Brunswick East VIC 3057",
    "addr:housenumber":"341",
    "addr:postcode":"3057",
    "addr:street":"Lygon St",
    "iso:country":"AU",
    "sg:address":"341 Lygon St",
    "sg:city":"Brunswick East",
    "sg:classifiers":[
        {
            "category":"Autos & Motor Vehicles",
            "subcategory":"Auto Supplies",
            "type":"Retail Goods"
        }
    ],
    "sg:phone":"+61 3 9388 9334",
    "sg:postcode":"3057",
    "sg:province":"VIC",
    "sg:tags":[
        "tyre"
    ],
    "wof:name":"One Stop Wheels & Tyres",
    "wof:placetype":"venue"
},
  "geometry": {"coordinates":[144.972198486,-37.7680130005],"type":"Point"}
}