{
  "type": "Feature",
  "properties": {
    "addr:full":"755 Anzac Pde Maroubra Junction NSW 2035",
    "addr:housenumber":"755",
    "addr:postcode":"2035",
    "addr:street":"Anzac Pde",
    "iso:country":"AU",
    "sg:address":"755 Anzac Pde",
    "sg:city":"Maroubra Junction",
    "sg:classifiers":[
        {
            "category":"Banks & Credit Unions",
            "subcategory":"Bank",
            "type":"Services"
        }
    ],
    "sg:phone":"+61 2 9349 2644",
    "sg:postcode":"2035",
    "sg:province":"NSW",
    "wof:name":"St. George Bank Home Loan Centre",
    "wof:placetype":"venue"
},
  "geometry": {"coordinates":[151.23898315400001,-33.9414749146],"type":"Point"}
}