{
  "type": "Feature",
  "properties": {
    "addr:full":"21 Gladstone Park Drv Gladstone Park VIC 3043",
    "addr:housenumber":"21",
    "addr:postcode":"3043",
    "addr:street":"Gladstone Park Drv",
    "iso:country":"AU",
    "sg:address":"21 Gladstone Park Drv",
    "sg:city":"Gladstone Park",
    "sg:classifiers":[
        {
            "category":"Personal",
            "subcategory":"Beauty Salon",
            "type":"Services"
        }
    ],
    "sg:phone":"+61 3 9330 0884",
    "sg:postcode":"3043",
    "sg:province":"VIC",
    "wof:name":"Sheer Indulgence",
    "wof:placetype":"venue"
},
  "geometry": {"coordinates":[144.883865356,-37.688999176],"type":"Point"}
}