{
  "type": "Feature",
  "properties": {
    "addr:full":"Fairy Hole Rd Yass NSW 2582",
    "addr:postcode":"2582",
    "addr:street":"Hole Rd",
    "iso:country":"AU",
    "sg:address":"Fairy Hole Rd",
    "sg:city":"Yass",
    "sg:classifiers":[
        {
            "category":"Farming",
            "subcategory":"Vineyard",
            "type":"Manufacturing & Wholesale Goods"
        }
    ],
    "sg:phone":"+61 2 6226 2427",
    "sg:postcode":"2582",
    "sg:province":"NSW",
    "sg:tags":[
        "winery"
    ],
    "wof:name":"Benfield Estate",
    "wof:placetype":"venue"
},
  "geometry": {"coordinates":[148.91374206500001,-34.7969398499],"type":"Point"}
}