{
  "type": "Feature",
  "properties": {
    "addr:full":"21-23 May Ave Rossmore NSW 2171",
    "addr:housenumber":"21-23",
    "addr:postcode":"2171",
    "addr:street":"May Ave",
    "iso:country":"AU",
    "sg:address":"21-23 May Ave",
    "sg:city":"Rossmore",
    "sg:classifiers":[
        {
            "category":"Food & Beverages",
            "subcategory":"Fruits & Vegetables",
            "type":"Retail Goods"
        }
    ],
    "sg:phone":"+61 415 847 756",
    "sg:postcode":"2171",
    "sg:province":"NSW",
    "sg:tags":[
        "grower"
    ],
    "wof:name":"G&J Produce",
    "wof:placetype":"venue"
},
  "geometry": {"coordinates":[151.05445861800001,-33.92603302],"type":"Point"}
}