{
  "type": "Feature",
  "properties": {
    "addr:full":"Unit 1, 21 Boree St Ulladulla NSW 2539",
    "addr:housenumber":"21",
    "addr:postcode":"2539",
    "addr:street":"Boree St",
    "iso:country":"AU",
    "sg:address":"Unit 1, 21 Boree St",
    "sg:city":"Ulladulla",
    "sg:classifiers":[
        {
            "category":"Health Services",
            "subcategory":"Dentist",
            "type":"Services"
        }
    ],
    "sg:phone":"+61 2 4455 1640",
    "sg:postcode":"2539",
    "sg:province":"NSW",
    "wof:name":"Moon John Dr",
    "wof:placetype":"venue"
},
  "geometry": {"coordinates":[150.47244262699999,-35.3597373962],"type":"Point"}
}