{
  "type": "Feature",
  "properties": {
    "addr:full":"Shop 149A Westfield Shpng Twn 967 North East Rd Modbury SA 5092",
    "addr:housenumber":"149a;967",
    "addr:postcode":"5092",
    "addr:street":"Westfield Shpng;North East Rd",
    "iso:country":"AU",
    "sg:address":"Shop 149A Westfield Shpng Twn 967 North East Rd",
    "sg:city":"Modbury",
    "sg:classifiers":[
        {
            "category":"Banks & Credit Unions",
            "subcategory":"Bureau De Change",
            "type":"Services"
        }
    ],
    "sg:phone":"+61 1800 637 642",
    "sg:postcode":"5092",
    "sg:province":"SA",
    "sg:tags":[
        "currency",
        "exchange",
        "foreign"
    ],
    "wof:name":"Travelex",
    "wof:placetype":"venue"
},
  "geometry": {"coordinates":[138.685623169,-34.8315315247],"type":"Point"}
}