{
  "type": "Feature",
  "properties": {
    "addr:full":"Suite 5, Level 2 The Forum 26 Orchid Ave Surfers Paradise QLD 4217",
    "addr:housenumber":"the;26",
    "addr:postcode":"4217",
    "addr:street":"Forum;Orchid Ave",
    "iso:country":"AU",
    "sg:address":"Suite 5, Level 2 The Forum 26 Orchid Ave",
    "sg:city":"Surfers Paradise",
    "sg:classifiers":[
        {
            "category":"Manufacturing",
            "subcategory":"Leather Goods",
            "type":"Manufacturing & Wholesale Goods"
        }
    ],
    "sg:phone":"+61 7 5526 7522",
    "sg:postcode":"4217",
    "sg:province":"QLD",
    "sg:tags":[
        "wholesaler",
        "mfrs"
    ],
    "wof:name":"Bags Of Oz",
    "wof:placetype":"venue"
},
  "geometry": {"coordinates":[153.429397583,-28.0001296997],"type":"Point"}
}