{
  "type": "Feature",
  "properties": {
    "addr:full":"Unit 3/ 60 Berwick St Fortitude Valley QLD 4006",
    "addr:housenumber":"60",
    "addr:postcode":"4006",
    "addr:street":"Berwick St",
    "iso:country":"AU",
    "sg:address":"Unit 3/ 60 Berwick St",
    "sg:city":"Fortitude Valley",
    "sg:classifiers":[
        {
            "category":"Professional",
            "subcategory":"Employment Agencies",
            "type":"Services"
        }
    ],
    "sg:phone":"+61 7 3257 1755",
    "sg:postcode":"4006",
    "sg:province":"QLD",
    "sg:tags":[
        "provider",
        "internet"
    ],
    "wof:name":"Whoo Studios",
    "wof:placetype":"venue"
},
  "geometry": {"coordinates":[153.03715515100001,-27.4585895538],"type":"Point"}
}