{
  "type": "Feature",
  "properties": {
    "addr:full":"30 Kent St Raymond Terrace NSW 2324",
    "addr:housenumber":"30",
    "addr:postcode":"2324",
    "addr:street":"Kent St",
    "iso:country":"AU",
    "sg:address":"30 Kent St",
    "sg:city":"Raymond Terrace",
    "sg:classifiers":[
        {
            "category":"Utilities",
            "subcategory":"Fuel Oil & Lpg",
            "type":"Services"
        }
    ],
    "sg:phone":"+61 2 4987 6029",
    "sg:postcode":"2324",
    "sg:province":"NSW",
    "sg:tags":[
        "combustion",
        "engineer"
    ],
    "wof:name":"Brown Combustion Consultants",
    "wof:placetype":"venue"
},
  "geometry": {"coordinates":[151.73832702600001,-32.7715568542],"type":"Point"}
}