{
  "type": "Feature",
  "properties": {
    "addr:full":"37 Boundary Rd Mordialloc VIC 3195",
    "addr:housenumber":"37",
    "addr:postcode":"3195",
    "addr:street":"Boundary Rd",
    "iso:country":"AU",
    "sg:address":"37 Boundary Rd",
    "sg:city":"Mordialloc",
    "sg:classifiers":[
        {
            "category":"Building & Trades",
            "subcategory":"Construction",
            "type":"Services"
        }
    ],
    "sg:phone":"+61 439 822 262",
    "sg:postcode":"3195",
    "sg:province":"VIC",
    "sg:tags":[
        "contractor"
    ],
    "wof:name":"Jubb Constructions Pty. Ltd.",
    "wof:placetype":"venue"
},
  "geometry": {"coordinates":[145.10354614299999,-38.007900238],"type":"Point"}
}