{
  "type": "Feature",
  "properties": {
    "addr:full":"16 Ballina St Kelvin Grove QLD 4059",
    "addr:housenumber":"16",
    "addr:postcode":"4059",
    "addr:street":"Ballina St",
    "iso:country":"AU",
    "sg:address":"16 Ballina St",
    "sg:city":"Kelvin Grove",
    "sg:classifiers":[
        {
            "category":"Professional",
            "subcategory":"Accounting & Tax Preparation",
            "type":"Services"
        }
    ],
    "sg:phone":"+61 7 3356 6377",
    "sg:postcode":"4059",
    "sg:province":"QLD",
    "sg:tags":[
        "accountant",
        "auditor"
    ],
    "wof:name":"Davidsons-DEM",
    "wof:placetype":"venue"
},
  "geometry": {"coordinates":[153.012405395,-27.4475364685],"type":"Point"}
}