{
  "type": "Feature",
  "properties": {
    "iso:country":"AU",
    "sg:address":"45 Murray St",
    "sg:city":"Hobart",
    "sg:classifiers":[
        {
            "category":"Professional",
            "subcategory":"Computer Services",
            "type":"Services"
        }
    ],
    "sg:phone":"+61 3 6230 4086",
    "sg:postcode":"7000",
    "sg:province":"TAS",
    "sg:tags":[
        "training"
    ],
    "wof:name":"Anntec",
    "wof:placetype":"venue"
},
  "geometry": {"coordinates":[147.32699585,-42.883102417],"type":"Point"}
}