{
  "type": "Feature",
  "properties": {
    "addr:full":"45 Nagle St Wagga Wagga NSW 2650",
    "addr:housenumber":"45",
    "addr:postcode":"2650",
    "addr:street":"Nagle St",
    "iso:country":"AU",
    "sg:address":"45 Nagle St",
    "sg:city":"Wagga Wagga",
    "sg:classifiers":[
        {
            "category":"Building & Trades",
            "subcategory":"Equipment Rental",
            "type":"Services"
        }
    ],
    "sg:phone":"+61 2 6921 4863",
    "sg:postcode":"2650",
    "sg:province":"NSW",
    "sg:tags":[
        "supply",
        "catering"
    ],
    "wof:name":"Dalco Confectionery Wholesalers",
    "wof:placetype":"venue"
},
  "geometry": {"coordinates":[147.38406372099999,-35.1243400574],"type":"Point"}
}