{
  "type": "Feature",
  "properties": {
    "iso:country":"AU",
    "sg:address":"Cnr South Milton St & Boundary Rd",
    "sg:city":"Mackay",
    "sg:classifiers":[
        {
            "category":"Sports & Exercise",
            "subcategory":"Sports Center",
            "type":"Entertainment"
        }
    ],
    "sg:phone":"+61 7 4952 1522",
    "sg:postcode":"4740",
    "sg:province":"QLD",
    "sg:tags":[
        "ground"
    ],
    "wof:name":"The Past Brothers Rugby League Football Club Inc",
    "wof:placetype":"venue"
},
  "geometry": {"coordinates":[149.17291299999999,-21.177038],"type":"Point"}
}