{
  "type": "Feature",
  "properties": {
    "iso:country":"AU",
    "sg:address":"3 Eucalyptus Drv",
    "sg:city":"Wellington",
    "sg:classifiers":[
        {
            "category":"Building & Trades",
            "subcategory":"Construction",
            "type":"Services"
        }
    ],
    "sg:phone":"+61 2 6845 1247",
    "sg:postcode":"2820",
    "sg:province":"NSW",
    "sg:tags":[
        "contractor"
    ],
    "wof:name":"Burke David Building",
    "wof:placetype":"venue"
},
  "geometry": {"coordinates":[148.931762695,-32.5386352539],"type":"Point"}
}