{
  "type": "Feature",
  "properties": {
    "addr:full":"12 Beardmore Pl St George QLD 4487",
    "addr:housenumber":"12",
    "addr:postcode":"4487",
    "addr:street":"Beardmore Pl",
    "iso:country":"AU",
    "sg:address":"12 Beardmore Pl St",
    "sg:city":"George",
    "sg:classifiers":[
        {
            "category":"Retail",
            "subcategory":"Auto Repair",
            "type":"Services"
        }
    ],
    "sg:phone":"+61 7 4625 3663",
    "sg:postcode":"4487",
    "sg:province":"QLD",
    "sg:tags":[
        "repairer",
        "motor",
        "engineer"
    ],
    "wof:name":"St George Suspension Centre",
    "wof:placetype":"venue"
},
  "geometry": {"coordinates":[148.57966613799999,-28.0355091095],"type":"Point"}
}