{
  "type": "Feature",
  "properties": {
    "iso:country":"AU",
    "sg:address":"Shop 1/ 43 Coronation Ave",
    "sg:city":"Nambour",
    "sg:classifiers":[
        {
            "category":"Building & Trades",
            "subcategory":"Equipment Rental",
            "type":"Services"
        }
    ],
    "sg:phone":"+61 7 5476 0284",
    "sg:postcode":"4560",
    "sg:province":"QLD",
    "sg:tags":[
        "party",
        "hire"
    ],
    "wof:name":"Nambour Party Hire",
    "wof:placetype":"venue"
},
  "geometry": {"coordinates":[152.964233398,-26.6209697723],"type":"Point"}
}