{
  "type": "Feature",
  "properties": {
    "addr:full":"2 Duranbah Drv Woollamia NSW 2540",
    "addr:housenumber":"2",
    "addr:postcode":"2540",
    "addr:street":"Duranbah Drv",
    "iso:country":"AU",
    "sg:address":"2 Duranbah Drv",
    "sg:city":"Woollamia",
    "sg:classifiers":[
        {
            "category":"Autos & Motor Vehicles",
            "subcategory":"Boat Sales",
            "type":"Retail Goods"
        }
    ],
    "sg:phone":"+61 2 4441 6994",
    "sg:postcode":"2540",
    "sg:province":"NSW",
    "sg:tags":[
        "builder",
        "yacht",
        "repairer"
    ],
    "wof:name":"Jarkan Pty Ltd",
    "wof:placetype":"venue"
},
  "geometry": {"coordinates":[150.66113281200001,-35.0283241272],"type":"Point"}
}