{
  "type": "Feature",
  "properties": {
    "addr:full":"O'Hallaran Pk Cnr Lake Albert & Kooringal Rds Wagga Wagga NSW 2650",
    "addr:postcode":"2650",
    "addr:street":"O'Hallaran;Cnr",
    "iso:country":"AU",
    "sg:address":"O'Hallaran Pk Cnr Lake Albert & Kooringal Rds",
    "sg:city":"Wagga Wagga",
    "sg:classifiers":[
        {
            "category":"Social Services",
            "subcategory":"Child Care",
            "type":"Services"
        }
    ],
    "sg:phone":"+61 2 6922 5434",
    "sg:postcode":"2650",
    "sg:province":"NSW",
    "wof:name":"Kooringal Casual Childcare Centre",
    "wof:placetype":"venue"
},
  "geometry": {"coordinates":[147.38154602,-35.1629066467],"type":"Point"}
}