{
  "type": "Feature",
  "properties": {
    "iso:country":"AU",
    "sg:address":"70 Gardeners Rd",
    "sg:city":"Kingsford",
    "sg:classifiers":[
        {
            "category":"Retail",
            "subcategory":"Veterinary Services",
            "type":"Services"
        }
    ],
    "sg:phone":"+61 2 9662 6703",
    "sg:postcode":"2032",
    "sg:province":"NSW",
    "sg:tags":[
        "surgeon"
    ],
    "wof:name":"Animal Medical Services - Kingsford Veterinary Hospital",
    "wof:placetype":"venue"
},
  "geometry": {"coordinates":[151.221801758,-33.9256706238],"type":"Point"}
}