{
  "type": "Feature",
  "properties": {
    "addr:full":"812 Port Rd Woodville South SA 5011",
    "addr:housenumber":"812",
    "addr:postcode":"5011",
    "addr:street":"Port Rd",
    "iso:country":"AU",
    "sg:address":"812 Port Rd",
    "sg:city":"Woodville South",
    "sg:classifiers":[
        {
            "category":"Retail",
            "subcategory":"Auto Repair",
            "type":"Services"
        }
    ],
    "sg:phone":"+61 8 8445 9077",
    "sg:postcode":"5011",
    "sg:province":"SA",
    "sg:tags":[
        "repairer",
        "motor",
        "engineer"
    ],
    "wof:name":"Big Bill's Workshop",
    "wof:placetype":"venue"
},
  "geometry": {"coordinates":[138.53805542000001,-34.8831558228],"type":"Point"}
}