{
  "type": "Feature",
  "properties": {
    "addr:full":"26 Barossa Ave Vermont South VIC 3133",
    "addr:housenumber":"26",
    "addr:postcode":"3133",
    "addr:street":"Barossa Ave",
    "iso:country":"AU",
    "sg:address":"26 Barossa Ave",
    "sg:city":"Vermont South",
    "sg:classifiers":[
        {
            "category":"Home & Garden",
            "subcategory":"Garden Supply",
            "type":"Retail Goods"
        }
    ],
    "sg:phone":"+61 3 9837 5331",
    "sg:postcode":"3133",
    "sg:province":"VIC",
    "sg:tags":[
        "statuary",
        "fountains",
        "sundial"
    ],
    "wof:name":"Old Melbourne Statues",
    "wof:placetype":"venue"
},
  "geometry": {"coordinates":[145.19400024399999,-37.8558921814],"type":"Point"}
}