{
  "type": "Feature",
  "properties": {
    "addr:full":"11 Douglas St Earlwood NSW 2206",
    "addr:housenumber":"11",
    "addr:postcode":"2206",
    "addr:street":"Douglas St",
    "iso:country":"AU",
    "sg:address":"11 Douglas St",
    "sg:city":"Earlwood",
    "sg:classifiers":[
        {
            "category":"Transit Center",
            "subcategory":"Freight",
            "type":"Transportation"
        }
    ],
    "sg:phone":"+61 2 9150 5220",
    "sg:postcode":"2206",
    "sg:province":"NSW",
    "sg:tags":[
        "forklift",
        "truck"
    ],
    "wof:name":"Able John Forklift Service",
    "wof:placetype":"venue"
},
  "geometry": {"coordinates":[151.110794,-33.933899],"type":"Point"}
}