{
  "type": "Feature",
  "properties": {
    "addr:full":"51 Don Heads Rd Devonport TAS 7310",
    "addr:housenumber":"51",
    "addr:postcode":"7310",
    "addr:street":"Don Heads Rd",
    "iso:country":"AU",
    "sg:address":"51 Don Heads Rd",
    "sg:city":"Devonport",
    "sg:classifiers":[
        {
            "category":"Farming",
            "subcategory":"Nursery",
            "type":"Manufacturing & Wholesale Goods"
        }
    ],
    "sg:phone":"+61 3 6424 8796",
    "sg:postcode":"7310",
    "sg:province":"TAS",
    "wof:name":"Hills Transplants Pty Ltd",
    "wof:placetype":"venue"
},
  "geometry": {"coordinates":[146.32395935100001,-41.1674804688],"type":"Point"}
}