{
  "type": "Feature",
  "properties": {
    "addr:full":"Rear 246 Railway Pde Kogarah NSW 2217",
    "addr:housenumber":"246",
    "addr:postcode":"2217",
    "addr:street":"Railway Pde",
    "iso:country":"AU",
    "sg:address":"Rear 246 Railway Pde",
    "sg:city":"Kogarah",
    "sg:classifiers":[
        {
            "category":"Retail",
            "subcategory":"Auto Repair",
            "type":"Services"
        }
    ],
    "sg:phone":"+61 2 9553 8612",
    "sg:postcode":"2217",
    "sg:province":"NSW",
    "sg:tags":[
        "repairer",
        "motor",
        "engineer"
    ],
    "wof:name":"N & G Mechanical Repairs",
    "wof:placetype":"venue"
},
  "geometry": {"coordinates":[151.12884500000001,-33.967613],"type":"Point"}
}