{
  "type": "Feature",
  "properties": {
    "iso:country":"AU",
    "sg:address":"1/ 9 Corrigan Crs",
    "sg:city":"Batehaven",
    "sg:classifiers":[
        {
            "category":"Health Services",
            "subcategory":"Doctor",
            "type":"Services"
        }
    ],
    "sg:phone":"+61 2 4472 4422",
    "sg:postcode":"2536",
    "sg:province":"NSW",
    "sg:tags":[
        "medical",
        "practitioner"
    ],
    "wof:name":"Ward Adrian",
    "wof:placetype":"venue"
},
  "geometry": {"coordinates":[150.19996643100001,-35.7324409485],"type":"Point"}
}