{
  "type": "Feature",
  "properties": {
    "addr:full":"159 Manifold St Camperdown VIC 3260",
    "addr:housenumber":"159",
    "addr:postcode":"3260",
    "addr:street":"Manifold St",
    "iso:country":"AU",
    "sg:address":"159 Manifold St",
    "sg:city":"Camperdown",
    "sg:classifiers":[
        {
            "category":"Organizations",
            "subcategory":"Professional Association",
            "type":"Services"
        }
    ],
    "sg:phone":"+61 3 5593 2684",
    "sg:postcode":"3260",
    "sg:province":"VIC",
    "sg:tags":[
        "organisation",
        "business"
    ],
    "wof:name":"Otway Division Of General Practice",
    "wof:placetype":"venue"
},
  "geometry": {"coordinates":[143.147415161,-38.2331428528],"type":"Point"}
}