{
  "type": "Feature",
  "properties": {
    "addr:full":"Shop 3, Eagle St Pier Brisbane QLD 4000",
    "addr:housenumber":"shop 3",
    "addr:postcode":"4000",
    "addr:street":"Eagle St Pier",
    "iso:country":"AU",
    "sg:address":"Shop 3, Eagle St Pier",
    "sg:city":"Brisbane",
    "sg:classifiers":[
        {
            "category":"Manufacturing",
            "subcategory":"Food",
            "type":"Manufacturing & Wholesale Goods"
        }
    ],
    "sg:phone":"+61 7 3225 9100",
    "sg:postcode":"4000",
    "sg:province":"QLD",
    "sg:tags":[
        "function",
        "catering"
    ],
    "sg:website":"http://www.boutiquevenues.com.au",
    "wof:name":"Gourmet en Counter",
    "wof:placetype":"venue"
},
  "geometry": {"coordinates":[153.030426025,-27.4693126678],"type":"Point"}
}