{
  "type": "Feature",
  "properties": {
    "addr:full":"Sunnybank Specialist Centre McCullough St Sunnybank QLD 4109",
    "addr:postcode":"4109",
    "addr:street":"Mccullough St",
    "iso:country":"AU",
    "sg:address":"Sunnybank Specialist Centre McCullough St",
    "sg:city":"Sunnybank",
    "sg:classifiers":[
        {
            "category":"Health Services",
            "subcategory":"Doctor",
            "type":"Services"
        }
    ],
    "sg:phone":"+61 7 3830 0788",
    "sg:postcode":"4109",
    "sg:province":"QLD",
    "sg:tags":[
        "medical",
        "practitioner"
    ],
    "wof:name":"Hinsch Roger Dr",
    "wof:placetype":"venue"
},
  "geometry": {"coordinates":[153.06271362300001,-27.5717849731],"type":"Point"}
}