{
  "type": "Feature",
  "properties": {
    "iso:country":"AU",
    "sg:address":"547 Wyndham St",
    "sg:city":"Shepparton",
    "sg:classifiers":[
        {
            "category":"Personal",
            "subcategory":"Massage",
            "type":"Services"
        }
    ],
    "sg:phone":"+61 419 318 258",
    "sg:postcode":"3630",
    "sg:province":"VIC",
    "sg:tags":[
        "therapy"
    ],
    "wof:name":"Calming Touch Massage Therapy",
    "wof:placetype":"venue"
},
  "geometry": {"coordinates":[145.397094727,-36.3929328918],"type":"Point"}
}