{
  "type": "Feature",
  "properties": {
    "addr:full":"Pacific Hwy Chinderah NSW 2487",
    "addr:postcode":"2487",
    "addr:street":"Pacific Hwy",
    "iso:country":"AU",
    "sg:address":"Pacific Hwy",
    "sg:city":"Chinderah",
    "sg:classifiers":[
        {
            "category":"Travel",
            "subcategory":"Hotels & Motels",
            "type":"Entertainment"
        }
    ],
    "sg:phone":"+61 2 6674 1137",
    "sg:postcode":"2487",
    "sg:province":"NSW",
    "sg:tags":[
        "accommodation"
    ],
    "wof:name":"Chinderah Tavern",
    "wof:placetype":"venue"
},
  "geometry": {"coordinates":[153.552978516,-28.2445335388],"type":"Point"}
}