{
  "type": "Feature",
  "properties": {
    "addr:full":"357 Main Rd Granton TAS 7030",
    "addr:housenumber":"357",
    "addr:postcode":"7030",
    "addr:street":"Main Rd",
    "iso:country":"AU",
    "sg:address":"357 Main Rd",
    "sg:city":"Granton",
    "sg:classifiers":[
        {
            "category":"Building & Trades",
            "subcategory":"Plumbing",
            "type":"Services"
        }
    ],
    "sg:phone":"+61 3 6249 2314",
    "sg:postcode":"7030",
    "sg:province":"TAS",
    "sg:tags":[
        "plumber",
        "gasfitters"
    ],
    "wof:name":"Barrow Robert",
    "wof:placetype":"venue"
},
  "geometry": {"coordinates":[147.24020385700001,-42.7611274719],"type":"Point"}
}