{
  "type": "Feature",
  "properties": {
    "iso:country":"AU",
    "sg:address":"9- 11",
    "sg:city":"Endeavour Way Braeside",
    "sg:classifiers":[
        {
            "category":"Wholesale",
            "subcategory":"Furniture",
            "type":"Manufacturing & Wholesale Goods"
        }
    ],
    "sg:phone":"+61 3 9587 5544",
    "sg:postcode":"3195",
    "sg:province":"VIC",
    "sg:tags":[
        "wholesaler",
        "mfrs"
    ],
    "wof:name":"Rehau Pty Ltd",
    "wof:placetype":"venue"
},
  "geometry": {"coordinates":[145.116577148,-38.0027542114],"type":"Point"}
}