{
  "type": "Feature",
  "properties": {
    "addr:full":"2040 Logan Rd Upper Mt Gravatt QLD 4122",
    "addr:housenumber":"2040",
    "addr:postcode":"4122",
    "addr:street":"Logan Rd Upper",
    "iso:country":"AU",
    "sg:address":"2040 Logan Rd",
    "sg:city":"Upper Mt Gravatt",
    "sg:classifiers":[
        {
            "category":"Shopping",
            "subcategory":"Pawn Shop",
            "type":"Retail Goods"
        }
    ],
    "sg:phone":"+61 7 3349 7655",
    "sg:postcode":"4122",
    "sg:province":"QLD",
    "sg:tags":[
        "pawnbroker"
    ],
    "wof:name":"Moneywise",
    "wof:placetype":"venue"
},
  "geometry": {"coordinates":[153.08111572300001,-27.5593795776],"type":"Point"}
}