{
  "type": "Feature",
  "properties": {
    "addr:full":"17 Concord Pl Caboolture QLD 4510",
    "addr:housenumber":"17",
    "addr:postcode":"4510",
    "addr:street":"Concord Pl",
    "iso:country":"AU",
    "sg:address":"17 Concord Pl",
    "sg:city":"Caboolture",
    "sg:classifiers":[
        {
            "category":"Manufacturing",
            "subcategory":"Metals",
            "type":"Manufacturing & Wholesale Goods"
        }
    ],
    "sg:phone":"+61 7 5499 3055",
    "sg:postcode":"4510",
    "sg:province":"QLD",
    "sg:tags":[
        "sheet",
        "worker"
    ],
    "wof:name":"Colonial Roofing Supply Co",
    "wof:placetype":"venue"
},
  "geometry": {"coordinates":[152.979477,-27.081364],"type":"Point"}
}