{
  "type": "Feature",
  "properties": {
    "addr:full":"285 Mulgrave Rd Cairns QLD 4870",
    "addr:housenumber":"285",
    "addr:postcode":"4870",
    "addr:street":"Mulgrave Rd",
    "iso:country":"AU",
    "sg:address":"285 Mulgrave Rd",
    "sg:city":"Cairns",
    "sg:classifiers":[
        {
            "category":"Food & Beverages",
            "subcategory":"Liquor & Beverages",
            "type":"Retail Goods"
        }
    ],
    "sg:phone":"+61 7 4051 4104",
    "sg:postcode":"4870",
    "sg:province":"QLD",
    "sg:tags":[
        "store"
    ],
    "wof:name":"Mulgrave Road Bottleshop",
    "wof:placetype":"venue"
},
  "geometry": {"coordinates":[145.74333190900001,-16.9400482178],"type":"Point"}
}