{
  "type": "Feature",
  "properties": {
    "iso:country":"AU",
    "sg:address":"PO Box 85",
    "sg:city":"Mulwala",
    "sg:classifiers":[
        {
            "category":"Building & Trades",
            "subcategory":"Construction",
            "type":"Services"
        }
    ],
    "sg:phone":"+61 418 579 988",
    "sg:postcode":"2647",
    "sg:province":"NSW",
    "sg:tags":[
        "contractor"
    ],
    "wof:name":"Riches Homes & Improvements",
    "wof:placetype":"venue"
},
  "geometry": {"coordinates":[145.94569397000001,-35.9083900452],"type":"Point"}
}