{
  "type": "Feature",
  "properties": {
    "iso:country":"AU",
    "sg:address":"22 Aster Ave",
    "sg:city":"Carrum Downs",
    "sg:classifiers":[
        {
            "category":"Building & Trades",
            "subcategory":"Construction",
            "type":"Services"
        }
    ],
    "sg:phone":"+61 3 9770 8046",
    "sg:postcode":"3201",
    "sg:province":"VIC",
    "sg:tags":[
        "road",
        "contractor"
    ],
    "wof:name":"Civilmech Pty Ltd",
    "wof:placetype":"venue"
},
  "geometry": {"coordinates":[145.16203300000001,-38.101841],"type":"Point"}
}