{
  "type": "Feature",
  "properties": {
    "addr:full":"Suite 4 458- 460 Swanston St Carlton VIC 3053",
    "addr:housenumber":"458 460",
    "addr:postcode":"3053",
    "addr:street":"Swanston St",
    "iso:country":"AU",
    "sg:address":"Suite 4 458- 460 Swanston St",
    "sg:city":"Carlton",
    "sg:classifiers":[
        {
            "category":"Health Services",
            "subcategory":"Doctor",
            "type":"Services"
        }
    ],
    "sg:phone":"+61 3 9349 7800",
    "sg:postcode":"3053",
    "sg:province":"VIC",
    "sg:tags":[
        "medical",
        "practitioner"
    ],
    "wof:name":"Rural Workforce Agency Victoria Ltd",
    "wof:placetype":"venue"
},
  "geometry": {"coordinates":[144.963134766,-37.8061523438],"type":"Point"}
}