{
  "type": "Feature",
  "properties": {
    "addr:full":"Dobney Ave Wagga Wagga NSW 2650",
    "addr:postcode":"2650",
    "addr:street":"Dobney Ave",
    "iso:country":"AU",
    "sg:address":"Dobney Ave",
    "sg:city":"Wagga Wagga",
    "sg:classifiers":[
        {
            "category":"Wholesale",
            "subcategory":"Metals & Minerals",
            "type":"Manufacturing & Wholesale Goods"
        }
    ],
    "sg:phone":"+61 2 6925 3199",
    "sg:postcode":"2650",
    "sg:province":"NSW",
    "sg:tags":[
        "steel",
        "merchant"
    ],
    "wof:name":"Smorgon Steelmark Metals",
    "wof:placetype":"venue"
},
  "geometry": {"coordinates":[147.34246826200001,-35.1230659485],"type":"Point"}
}