{
  "type": "Feature",
  "properties": {
    "addr:full":"Shop 83 , Epping Plaza Epping VIC 3076",
    "addr:housenumber":"shop 83",
    "addr:postcode":"3076",
    "addr:street":"Epping Plaza",
    "iso:country":"AU",
    "sg:address":"Shop 83",
    "sg:city":", Epping Plaza Epping",
    "sg:classifiers":[
        {
            "category":"Shopping",
            "subcategory":"Clothing, Apparel, & Fashions",
            "type":"Retail Goods"
        }
    ],
    "sg:phone":"+61 3 9408 6415",
    "sg:postcode":"3076",
    "sg:province":"VIC",
    "sg:tags":[
        "hire",
        "men's",
        "wear",
        "formal"
    ],
    "wof:name":"Ferrari Formal Hire",
    "wof:placetype":"venue"
},
  "geometry": {"coordinates":[145.02682495100001,-37.6337509155],"type":"Point"}
}