{
  "type": "Feature",
  "properties": {
    "addr:full":"Nuwarra Rd Moorebank NSW 2170",
    "addr:postcode":"2170",
    "addr:street":"Nuwarra Rd",
    "iso:country":"AU",
    "sg:address":"Nuwarra Rd",
    "sg:city":"Moorebank",
    "sg:classifiers":[
        {
            "category":"School Buses",
            "type":"Transportation"
        }
    ],
    "sg:phone":"+61 1300 309 718",
    "sg:postcode":"2170",
    "sg:province":"NSW",
    "sg:tags":[
        "brick"
    ],
    "wof:name":"Boral Bricks",
    "wof:placetype":"venue"
},
  "geometry": {"coordinates":[150.947433472,-33.9445953369],"type":"Point"}
}