{
  "type": "Feature",
  "properties": {
    "addr:full":"6 Thistle Crt Delahey VIC 3037",
    "addr:housenumber":"6",
    "addr:postcode":"3037",
    "addr:street":"Thistle Crt",
    "iso:country":"AU",
    "sg:address":"6 Thistle Crt",
    "sg:city":"Delahey",
    "sg:classifiers":[
        {
            "category":"Professional",
            "subcategory":"Art Services",
            "type":"Services"
        }
    ],
    "sg:phone":"+61 425 739 210",
    "sg:postcode":"3037",
    "sg:province":"VIC",
    "sg:tags":[
        "graphic",
        "designer"
    ],
    "wof:name":"Donnel Cruz",
    "wof:placetype":"venue"
},
  "geometry": {"coordinates":[144.768845,-37.724583],"type":"Point"}
}