{
  "type": "Feature",
  "properties": {
    "addr:full":"811 Edward St Marong VIC 3515",
    "addr:housenumber":"811",
    "addr:postcode":"3515",
    "addr:street":"Edward St",
    "iso:country":"AU",
    "sg:address":"811 Edward St",
    "sg:city":"Marong",
    "sg:classifiers":[
        {
            "category":"Farming",
            "subcategory":"Vineyard",
            "type":"Manufacturing & Wholesale Goods"
        }
    ],
    "sg:phone":"+61 3 5435 2473",
    "sg:postcode":"3515",
    "sg:province":"VIC",
    "sg:tags":[
        "winery"
    ],
    "wof:name":"Marong Vineyard",
    "wof:placetype":"venue"
},
  "geometry": {"coordinates":[144.135132,-36.769997],"type":"Point"}
}