{
  "type": "Feature",
  "properties": {
    "addr:full":"Byrne Rd Wudinna SA 5652",
    "addr:postcode":"5652",
    "addr:street":"Byrne Rd",
    "iso:country":"AU",
    "sg:address":"Byrne Rd",
    "sg:city":"Wudinna",
    "sg:classifiers":[
        {
            "category":"Freight",
            "type":"Transportation"
        }
    ],
    "sg:phone":"+61 8 8680 2326",
    "sg:postcode":"5652",
    "sg:province":"SA",
    "sg:tags":[
        "light",
        "carrier"
    ],
    "wof:name":"Heath Transport",
    "wof:placetype":"venue"
},
  "geometry": {"coordinates":[135.46098327600001,-33.0521621704],"type":"Point"}
}