{
  "type": "Feature",
  "properties": {
    "addr:full":"Main St Strathmerton VIC 3641",
    "addr:postcode":"3641",
    "addr:street":"Main St",
    "iso:country":"AU",
    "sg:address":"Main St",
    "sg:city":"Strathmerton",
    "sg:classifiers":[
        {
            "category":"Personal",
            "subcategory":"Beauty Salon",
            "type":"Services"
        }
    ],
    "sg:phone":"+61 3 5874 5502",
    "sg:postcode":"3641",
    "sg:province":"VIC",
    "sg:tags":[
        "hairdresser"
    ],
    "wof:name":"Freckles Hair Design",
    "wof:placetype":"venue"
},
  "geometry": {"coordinates":[145.47651672399999,-35.9254798889],"type":"Point"}
}