{
  "type": "Feature",
  "properties": {
    "addr:full":"57 Morrice St Lane Cove NSW 2066",
    "addr:housenumber":"57",
    "addr:postcode":"2066",
    "addr:street":"Morrice St",
    "iso:country":"AU",
    "sg:address":"57 Morrice St",
    "sg:city":"Lane Cove",
    "sg:classifiers":[
        {
            "category":"Health Services",
            "subcategory":"Health Practitioner",
            "type":"Services"
        }
    ],
    "sg:phone":"+61 2 9428 4812",
    "sg:postcode":"2066",
    "sg:province":"NSW",
    "sg:tags":[
        "dietitian"
    ],
    "wof:name":"Thompson Susan",
    "wof:placetype":"venue"
},
  "geometry": {"coordinates":[151.16673278799999,-33.8180084229],"type":"Point"}
}