{
  "type": "Feature",
  "properties": {
    "addr:full":"2 First Ave Forestville SA 5035",
    "addr:housenumber":"2",
    "addr:postcode":"5035",
    "addr:street":"First Ave",
    "iso:country":"AU",
    "sg:address":"2 First Ave",
    "sg:city":"Forestville",
    "sg:classifiers":[
        {
            "category":"Manufacturing",
            "subcategory":"Metals",
            "type":"Manufacturing & Wholesale Goods"
        }
    ],
    "sg:phone":"+61 8 8293 2486",
    "sg:postcode":"5035",
    "sg:province":"SA",
    "sg:tags":[
        "steel",
        "fabricator",
        "mfrs"
    ],
    "wof:name":"Dunks Pty Ltd",
    "wof:placetype":"venue"
},
  "geometry": {"coordinates":[138.57977294899999,-34.9492721558],"type":"Point"}
}