{
  "type": "Feature",
  "properties": {
    "iso:country":"AU",
    "sg:address":"76 Melbourne Rd",
    "sg:city":"Riverstone",
    "sg:classifiers":[
        {
            "category":"Professional",
            "subcategory":"Engineering",
            "type":"Services"
        }
    ],
    "sg:phone":"+61 2 9627 9300",
    "sg:postcode":"2765",
    "sg:province":"NSW",
    "sg:tags":[
        "engineer"
    ],
    "wof:name":"Dunning Industries Pty Ltd",
    "wof:placetype":"venue"
},
  "geometry": {"coordinates":[150.860839844,-33.6618499756],"type":"Point"}
}