{
  "type": "Feature",
  "properties": {
    "addr:full":"67 Ashworth Ave Belrose NSW 2085",
    "addr:housenumber":"67",
    "addr:postcode":"2085",
    "addr:street":"Ashworth Ave",
    "iso:country":"AU",
    "sg:address":"67 Ashworth Ave",
    "sg:city":"Belrose",
    "sg:classifiers":[
        {
            "category":"Building & Trades",
            "subcategory":"Landscaping Services",
            "type":"Services"
        }
    ],
    "sg:phone":"+61 418 688 353",
    "sg:postcode":"2085",
    "sg:province":"NSW",
    "sg:tags":[
        "gardener"
    ],
    "wof:name":"Barrenjoey Garden Care",
    "wof:placetype":"venue"
},
  "geometry": {"coordinates":[151.201629639,-33.736618042],"type":"Point"}
}