{
  "type": "Feature",
  "properties": {
    "addr:full":"38a Edwardes St Reservoir VIC 3073",
    "addr:housenumber":"38a",
    "addr:postcode":"3073",
    "addr:street":"Edwardes St",
    "iso:country":"AU",
    "sg:address":"38a Edwardes St",
    "sg:city":"Reservoir",
    "sg:classifiers":[
        {
            "category":"Personal",
            "subcategory":"Shoe Repair & Shine",
            "type":"Services"
        }
    ],
    "sg:phone":"+61 3 9462 3138",
    "sg:postcode":"3073",
    "sg:province":"VIC",
    "sg:tags":[
        "footwear"
    ],
    "wof:name":"Frank Condello Shoe Repairs",
    "wof:placetype":"venue"
},
  "geometry": {"coordinates":[145.00488281200001,-37.715965271],"type":"Point"}
}