{
  "type": "Feature",
  "properties": {
    "iso:country":"AU",
    "sg:address":"58 Dalmeny Ave",
    "sg:city":"Rosebery",
    "sg:classifiers":[
        {
            "category":"Professional",
            "subcategory":"Accounting & Tax Preparation",
            "type":"Services"
        }
    ],
    "sg:phone":"+61 2 9662 8349",
    "sg:postcode":"2018",
    "sg:province":"NSW",
    "sg:tags":[
        "accountant",
        "auditor"
    ],
    "wof:name":"Anthony George & Co",
    "wof:placetype":"venue"
},
  "geometry": {"coordinates":[151.20755004899999,-33.9179344177],"type":"Point"}
}