{
  "type": "Feature",
  "properties": {
    "iso:country":"AU",
    "sg:address":"128 East Barrack St",
    "sg:city":"Merredin",
    "sg:classifiers":[
        {
            "category":"Retail",
            "subcategory":"Auto Repair",
            "type":"Services"
        }
    ],
    "sg:phone":"+61 8 9041 1720",
    "sg:postcode":"6415",
    "sg:province":"WA",
    "sg:tags":[
        "repairer",
        "motor",
        "engineer"
    ],
    "wof:name":"Holmes Motors & Engineering",
    "wof:placetype":"venue"
},
  "geometry": {"coordinates":[118.27908325200001,-31.481962204],"type":"Point"}
}