{
  "type": "Feature",
  "properties": {
    "addr:full":"8/ 28 Gladstonbury Ave Unanderra NSW 2526",
    "addr:housenumber":"/ 28",
    "addr:postcode":"2526",
    "addr:street":"Gladstonbury Ave",
    "iso:country":"AU",
    "sg:address":"8/ 28 Gladstonbury Ave",
    "sg:city":"Unanderra",
    "sg:classifiers":[
        {
            "category":"Retail",
            "subcategory":"Auto Repair",
            "type":"Services"
        }
    ],
    "sg:phone":"+61 411 484 771",
    "sg:postcode":"2526",
    "sg:province":"NSW",
    "sg:tags":[
        "electrical"
    ],
    "wof:name":"Supreme Auto Electrics & Air Pty Ltd",
    "wof:placetype":"venue"
},
  "geometry": {"coordinates":[150.85505676299999,-34.4598388672],"type":"Point"}
}