{
  "type": "Feature",
  "properties": {
    "addr:full":"PO Box 2079 Howrah TAS 7018",
    "addr:postcode":"7018",
    "iso:country":"AU",
    "sg:address":"PO Box 2079",
    "sg:city":"Howrah",
    "sg:classifiers":[
        {
            "category":"Building & Trades",
            "subcategory":"Cleaning & Sanitation",
            "type":"Services"
        }
    ],
    "sg:phone":"+61 412 872 483",
    "sg:postcode":"7018",
    "sg:province":"TAS",
    "sg:tags":[
        "cleaner",
        "repairer",
        "roof"
    ],
    "wof:name":"Heath Stanton",
    "wof:placetype":"venue"
},
  "geometry": {"coordinates":[147.40835571299999,-42.8798789978],"type":"Point"}
}