{
  "type": "Feature",
  "properties": {
    "addr:full":"Shop 262 Whitford City Shopping Centre Hillarys WA 6025",
    "addr:housenumber":"262",
    "addr:postcode":"6025",
    "iso:country":"AU",
    "sg:address":"Shop 262",
    "sg:city":"Whitford City Shopping Centre Hillarys",
    "sg:classifiers":[
        {
            "category":"Personal",
            "subcategory":"Beauty Salon",
            "type":"Services"
        }
    ],
    "sg:phone":"+61 8 9402 5899",
    "sg:postcode":"6025",
    "sg:province":"WA",
    "sg:tags":[
        "hairdresser"
    ],
    "wof:name":"Maurice Meade",
    "wof:placetype":"venue"
},
  "geometry": {"coordinates":[115.74561309800001,-31.8076992035],"type":"Point"}
}