{
  "type": "Feature",
  "properties": {
    "addr:full":"Shops 1 & 2, 237 Grange Rd Findon SA 5023",
    "addr:housenumber":"shops 1 & 2 237",
    "addr:postcode":"5023",
    "addr:street":"Grange Rd",
    "iso:country":"AU",
    "sg:address":"Shops 1 & 2, 237 Grange Rd",
    "sg:city":"Findon",
    "sg:classifiers":[
        {
            "category":"Shopping",
            "subcategory":"Computers & Home Electronics",
            "type":"Retail Goods"
        }
    ],
    "sg:phone":"+61 8 8244 7260",
    "sg:postcode":"5023",
    "sg:province":"SA",
    "sg:tags":[
        "hardware",
        "equipment"
    ],
    "wof:name":"Global Computers",
    "wof:placetype":"venue"
},
  "geometry": {"coordinates":[138.54020690900001,-34.9049606323],"type":"Point"}
}