{
  "type": "Feature",
  "properties": {
    "iso:country":"AU",
    "sg:address":"59 Wallace St",
    "sg:city":"Beaconsfield",
    "sg:classifiers":[
        {
            "category":"Personal",
            "subcategory":"Beauty Salon",
            "type":"Services"
        }
    ],
    "sg:phone":"+61 3 9707 4000",
    "sg:postcode":"3807",
    "sg:province":"VIC",
    "sg:tags":[
        "hairdresser"
    ],
    "wof:name":"Hair Movement",
    "wof:placetype":"venue"
},
  "geometry": {"coordinates":[145.37031555199999,-38.0474586487],"type":"Point"}
}