{
  "type": "Feature",
  "properties": {
    "iso:country":"AU",
    "sg:address":"12 Hakea Crs",
    "sg:city":"Galston",
    "sg:classifiers":[
        {
            "category":"Utilities",
            "subcategory":"Electric",
            "type":"Services"
        }
    ],
    "sg:phone":"+61 411 643 994",
    "sg:postcode":"2159",
    "sg:province":"NSW",
    "sg:tags":[
        "electrical",
        "contractor"
    ],
    "wof:name":"ADSA Electrical Services",
    "wof:placetype":"venue"
},
  "geometry": {"coordinates":[151.045013428,-33.6529197693],"type":"Point"}
}