{
  "type": "Feature",
  "properties": {
    "addr:full":"Cedar Court 374 Burke Rd Camberwell VIC 3124",
    "addr:housenumber":"374",
    "addr:postcode":"3124",
    "addr:street":"Cedar;Burke Rd",
    "iso:country":"AU",
    "sg:address":"Cedar Court 374 Burke Rd",
    "sg:city":"Camberwell",
    "sg:classifiers":[
        {
            "category":"Health Services",
            "subcategory":"Doctor",
            "type":"Services"
        }
    ],
    "sg:phone":"+61 3 9805 4154",
    "sg:postcode":"3124",
    "sg:province":"VIC",
    "sg:tags":[
        "medical",
        "practitioner"
    ],
    "wof:name":"Heathershaw Katie",
    "wof:placetype":"venue"
},
  "geometry": {"coordinates":[145.05398559599999,-37.8463783264],"type":"Point"}
}