{
  "type": "Feature",
  "properties": {
    "iso:country":"AU",
    "sg:address":"18 Yates St",
    "sg:city":"Nelly Bay",
    "sg:classifiers":[
        {
            "category":"Professional",
            "subcategory":"Art Services",
            "type":"Services"
        }
    ],
    "sg:phone":"+61 7 4778 5351",
    "sg:postcode":"4819",
    "sg:province":"QLD",
    "sg:tags":[
        "graphic",
        "designer"
    ],
    "wof:name":"Identity Marketing & Design",
    "wof:placetype":"venue"
},
  "geometry": {"coordinates":[146.84652700000001,-19.161341],"type":"Point"}
}