{
  "type": "Feature",
  "properties": {
    "addr:full":"10 Sargood St Toorak VIC 3142",
    "addr:housenumber":"10",
    "addr:postcode":"3142",
    "addr:street":"Sargood St",
    "iso:country":"AU",
    "sg:address":"10 Sargood St",
    "sg:city":"Toorak",
    "sg:classifiers":[
        {
            "category":"Travel",
            "subcategory":"Travel Agent",
            "type":"Entertainment"
        }
    ],
    "sg:phone":"+61 3 9827 5846",
    "sg:postcode":"3142",
    "sg:province":"VIC",
    "sg:tags":[
        "consultant"
    ],
    "wof:name":"Ingall Travel Group Pty Ltd",
    "wof:placetype":"venue"
},
  "geometry": {"coordinates":[145.01370239299999,-37.84633255],"type":"Point"}
}