{
  "type": "Feature",
  "properties": {
    "iso:country":"AU",
    "sg:address":"4 Synett Crt",
    "sg:city":"Seaview Downs",
    "sg:classifiers":[
        {
            "category":"Arts & Performance",
            "subcategory":"Dance",
            "type":"Entertainment"
        }
    ],
    "sg:phone":"+61 8 8296 2332",
    "sg:postcode":"5049",
    "sg:province":"SA",
    "sg:tags":[
        "theatrical",
        "ballet",
        "tuition"
    ],
    "wof:name":"Cecchetti Society Of Aust (S.A. Branch)",
    "wof:placetype":"venue"
},
  "geometry": {"coordinates":[138.534256,-35.036419],"type":"Point"}
}