{
  "type": "Feature",
  "properties": {
    "addr:full":"Lot 1 Dynon Rd Flemington VIC 3031",
    "addr:postcode":"3031",
    "addr:street":"Dynon Rd",
    "iso:country":"AU",
    "sg:address":"Lot 1 Dynon Rd",
    "sg:city":"Flemington",
    "sg:classifiers":[
        {
            "category":"Taxi",
            "type":"Transportation"
        }
    ],
    "sg:phone":"+61 3 9372 1844",
    "sg:postcode":"3031",
    "sg:province":"VIC",
    "sg:tags":[
        "truck"
    ],
    "wof:name":"Macs Transport Services",
    "wof:placetype":"venue"
},
  "geometry": {"coordinates":[144.91864000000001,-37.801907],"type":"Point"}
}