{
  "type": "Feature",
  "properties": {
    "addr:full":"PO Box 866 Bulimba QLD 4171",
    "addr:postcode":"4171",
    "iso:country":"AU",
    "sg:address":"PO Box 866",
    "sg:city":"Bulimba",
    "sg:classifiers":[
        {
            "category":"Building & Trades",
            "subcategory":"Construction",
            "type":"Services"
        }
    ],
    "sg:phone":"+61 7 3899 7333",
    "sg:postcode":"4171",
    "sg:province":"QLD",
    "sg:tags":[
        "contractor"
    ],
    "sg:website":"http://www.evermorehomes.com.au",
    "wof:name":"Evermore Properties",
    "wof:placetype":"venue"
},
  "geometry": {"coordinates":[153.05502319300001,-27.4508533478],"type":"Point"}
}