{
  "type": "Feature",
  "properties": {
    "addr:full":"PO Box 366 Ballina NSW 2478",
    "addr:postcode":"2478",
    "iso:country":"AU",
    "sg:address":"PO Box 366",
    "sg:city":"Ballina",
    "sg:classifiers":[
        {
            "category":"Building & Trades",
            "subcategory":"Construction",
            "type":"Services"
        }
    ],
    "sg:phone":"+61 2 6681 3887",
    "sg:postcode":"2478",
    "sg:province":"NSW",
    "sg:tags":[
        "pool",
        "swimming"
    ],
    "wof:name":"North East Pool Professionals",
    "wof:placetype":"venue"
},
  "geometry": {"coordinates":[153.554962158,-28.8678798676],"type":"Point"}
}