{
  "type": "Feature",
  "properties": {
    "addr:full":"12- 16 Kesters Rd Para Hills West SA 5096",
    "addr:housenumber":"16",
    "addr:postcode":"5096",
    "addr:street":"Kesters Rd Para Hills West",
    "iso:country":"AU",
    "sg:address":"12- 16 Kesters Rd",
    "sg:city":"Para Hills West",
    "sg:classifiers":[
        {
            "category":"Professional",
            "type":"Services"
        }
    ],
    "sg:phone":"+61 8 8281 4924",
    "sg:postcode":"5096",
    "sg:province":"SA",
    "sg:tags":[
        "coating",
        "powder"
    ],
    "wof:name":"Adelaide Powder Coaters",
    "wof:placetype":"venue"
},
  "geometry": {"coordinates":[138.646316528,-34.7984085083],"type":"Point"}
}