{
  "type": "Feature",
  "properties": {
    "iso:country":"AU",
    "sg:address":"16 Herbert St",
    "sg:city":"Artarmon",
    "sg:classifiers":[
        {
            "category":"Building & Trades",
            "subcategory":"Equipment Rental",
            "type":"Services"
        }
    ],
    "sg:phone":"+61 2 9439 3477",
    "sg:postcode":"2064",
    "sg:province":"NSW",
    "sg:tags":[
        "renting",
        "trailer"
    ],
    "wof:name":"Kennards Trailer Hire",
    "wof:placetype":"venue"
},
  "geometry": {"coordinates":[151.19023132300001,-33.8155212402],"type":"Point"}
}