{
  "type": "Feature",
  "properties": {
    "addr:full":"7 Hayden Crt Myaree WA 6154",
    "addr:housenumber":"7",
    "addr:postcode":"6154",
    "addr:street":"Hayden Crt",
    "iso:country":"AU",
    "sg:address":"7 Hayden Crt",
    "sg:city":"Myaree",
    "sg:classifiers":[
        {
            "category":"Retail",
            "subcategory":"Auto Repair",
            "type":"Services"
        }
    ],
    "sg:phone":"+61 8 9330 3822",
    "sg:postcode":"6154",
    "sg:province":"WA",
    "sg:tags":[
        "repairer",
        "motor",
        "engineer"
    ],
    "wof:name":"De Rosa Auto Repairs",
    "wof:placetype":"venue"
},
  "geometry": {"coordinates":[115.81791699999999,-32.044853],"type":"Point"}
}