{
  "type": "Feature",
  "properties": {
    "iso:country":"AU",
    "sg:address":"5 Wheatstone Drv",
    "sg:city":"Morley",
    "sg:classifiers":[
        {
            "category":"Professional",
            "subcategory":"Art Services",
            "type":"Services"
        }
    ],
    "sg:phone":"+61 411 645 038",
    "sg:postcode":"6062",
    "sg:province":"WA",
    "sg:tags":[
        "decorator",
        "painter"
    ],
    "wof:name":"Glatz H",
    "wof:placetype":"venue"
},
  "geometry": {"coordinates":[115.92579650899999,-31.88489151],"type":"Point"}
}