{
  "type": "Feature",
  "properties": {
    "iso:country":"AU",
    "sg:address":"7 Abbott St",
    "sg:city":"Bellerive",
    "sg:classifiers":[
        {
            "category":"Health Services",
            "subcategory":"Health Practitioner",
            "type":"Services"
        }
    ],
    "sg:phone":"+61 3 6244 2928",
    "sg:postcode":"7018",
    "sg:province":"TAS",
    "sg:tags":[
        "physiotherapist"
    ],
    "wof:name":"Clarence Hydrotherapy Physiotherapy Centre",
    "wof:placetype":"venue"
},
  "geometry": {"coordinates":[147.36555480999999,-42.8804244995],"type":"Point"}
}