{
  "type": "Feature",
  "properties": {
    "iso:country":"AU",
    "sg:address":"222B MacArthur Ave",
    "sg:city":"Hamilton",
    "sg:classifiers":[
        {
            "category":"Freight",
            "type":"Transportation"
        }
    ],
    "sg:phone":"+61 7 3268 9400",
    "sg:postcode":"4007",
    "sg:province":"QLD",
    "sg:tags":[
        "car",
        "carrier",
        "transporting"
    ],
    "wof:name":"Toll AutoLogistics",
    "wof:placetype":"venue"
},
  "geometry": {"coordinates":[153.064606,-27.4375],"type":"Point"}
}