{
  "type": "Feature",
  "properties": {
    "addr:full":"111 Carlisle St Balaclava VIC 3183",
    "addr:housenumber":"111",
    "addr:postcode":"3183",
    "addr:street":"Carlisle St",
    "iso:country":"AU",
    "sg:address":"111 Carlisle St",
    "sg:city":"Balaclava",
    "sg:classifiers":[
        {
            "category":"Health Services",
            "subcategory":"Clinic",
            "type":"Services"
        }
    ],
    "sg:phone":"+61 417 564 372",
    "sg:postcode":"3183",
    "sg:province":"VIC",
    "sg:tags":[
        "aromatherapy"
    ],
    "wof:name":"Therabees",
    "wof:placetype":"venue"
},
  "geometry": {"coordinates":[144.990631103,-37.8684921265],"type":"Point"}
}