{
  "type": "Feature",
  "properties": {
    "iso:country":"AU",
    "sg:address":"Beerwah Pde",
    "sg:city":"Beerwah",
    "sg:classifiers":[
        {
            "category":"Autos & Motor Vehicles",
            "subcategory":"Fuel & Gas Station",
            "type":"Retail Goods"
        }
    ],
    "sg:phone":"+61 7 5494 6304",
    "sg:postcode":"4519",
    "sg:province":"QLD",
    "wof:name":"BP Australia Limited",
    "wof:placetype":"venue"
},
  "geometry": {"coordinates":[152.95895400000001,-26.857759],"type":"Point"}
}