{
  "type": "Feature",
  "properties": {
    "addr:full":"13 Aitchander Rd Ryde NSW 2112",
    "addr:housenumber":"13",
    "addr:postcode":"2112",
    "addr:street":"Aitchander Rd",
    "iso:country":"AU",
    "sg:address":"13 Aitchander Rd",
    "sg:city":"Ryde",
    "sg:classifiers":[
        {
            "category":"Home & Garden",
            "subcategory":"Carpets & Floor Coverings",
            "type":"Retail Goods"
        }
    ],
    "sg:phone":"+61 2 9808 4244",
    "sg:postcode":"2112",
    "sg:province":"NSW",
    "sg:tags":[
        "tile",
        "wall",
        "layer"
    ],
    "wof:name":"Hajj G & S Tiling Company",
    "wof:placetype":"venue"
},
  "geometry": {"coordinates":[151.116790772,-33.8118667603],"type":"Point"}
}