{
  "type": "Feature",
  "properties": {
    "addr:full":"4 Schofield Crt Geelong North VIC 3215",
    "addr:housenumber":"4",
    "addr:postcode":"3215",
    "addr:street":"Schofield Crt",
    "iso:country":"AU",
    "sg:address":"4 Schofield Crt",
    "sg:city":"Geelong North",
    "sg:classifiers":[
        {
            "category":"Organizations",
            "subcategory":"Professional Association",
            "type":"Services"
        }
    ],
    "sg:phone":"+61 3 5272 2400",
    "sg:postcode":"3215",
    "sg:province":"VIC",
    "sg:tags":[
        "web",
        "internet"
    ],
    "wof:name":"Totalcare ITS",
    "wof:placetype":"venue"
},
  "geometry": {"coordinates":[144.32986450199999,-38.1096153259],"type":"Point"}
}