{
  "type": "Feature",
  "properties": {
    "iso:country":"AU",
    "sg:address":"40 Playne St",
    "sg:city":"Frankston",
    "sg:classifiers":[
        {
            "category":"Health Services",
            "subcategory":"Doctor",
            "type":"Services"
        }
    ],
    "sg:phone":"+61 3 9781 4999",
    "sg:postcode":"3199",
    "sg:province":"VIC",
    "sg:tags":[
        "medical",
        "practitioner"
    ],
    "wof:name":"Yeap Y Dr",
    "wof:placetype":"venue"
},
  "geometry": {"coordinates":[145.122512817,-38.1451225281],"type":"Point"}
}