{
  "type": "Feature",
  "properties": {
    "addr:full":"160 Portrush Rd Trinity Gardens SA 5068",
    "addr:housenumber":"160",
    "addr:postcode":"5068",
    "addr:street":"Portrush Rd",
    "iso:country":"AU",
    "sg:address":"160 Portrush Rd",
    "sg:city":"Trinity Gardens",
    "sg:classifiers":[
        {
            "category":"Education",
            "subcategory":"School",
            "type":"Public Place"
        }
    ],
    "sg:phone":"+61 8 8431 4170",
    "sg:postcode":"5068",
    "sg:province":"SA",
    "sg:tags":[
        "state",
        "except",
        "nsw"
    ],
    "wof:name":"Trinity Gardens Primary and Preschool",
    "wof:placetype":"venue"
},
  "geometry": {"coordinates":[138.64030456500001,-34.9084205627],"type":"Point"}
}