{
  "type": "Feature",
  "properties": {
    "addr:full":"74 Bridport St Albert Park VIC 3206",
    "addr:housenumber":"74",
    "addr:postcode":"3206",
    "addr:street":"Bridport St",
    "iso:country":"AU",
    "sg:address":"74 Bridport St",
    "sg:city":"Albert Park",
    "sg:classifiers":[
        {
            "category":"Real Estate",
            "subcategory":"Architect",
            "type":"Services"
        }
    ],
    "sg:phone":"+61 3 9686 6086",
    "sg:postcode":"3206",
    "sg:province":"VIC",
    "wof:name":"Whiting A & I",
    "wof:placetype":"venue"
},
  "geometry": {"coordinates":[144.95777899999999,-37.83997],"type":"Point"}
}