{
  "type": "Feature",
  "properties": {
    "iso:country":"AU",
    "sg:address":"Level 2/ 370 Pitt St",
    "sg:city":"Sydney",
    "sg:classifiers":[
        {
            "category":"Banks & Credit Unions",
            "subcategory":"Investment Brokerage",
            "type":"Services"
        }
    ],
    "sg:phone":"+61 2 9285 2800",
    "sg:postcode":"2000",
    "sg:province":"NSW",
    "sg:tags":[
        "debt",
        "collection"
    ],
    "wof:name":"Forster Mercantile Collections Pty Ltd",
    "wof:placetype":"venue"
},
  "geometry": {"coordinates":[151.207794189,-33.8773345947],"type":"Point"}
}