{
  "type": "Feature",
  "properties": {
    "iso:country":"AU",
    "sg:address":"108 Myers Creek Rd",
    "sg:city":"Healesville",
    "sg:classifiers":[
        {
            "category":"Building & Trades",
            "subcategory":"Landscaping Services",
            "type":"Services"
        }
    ],
    "sg:phone":"+61 3 5962 6176",
    "sg:postcode":"3777",
    "sg:province":"VIC",
    "sg:tags":[
        "stump",
        "tree",
        "felling",
        "removal"
    ],
    "wof:name":"Imberger Helmut-Tree Garden Services",
    "wof:placetype":"venue"
},
  "geometry": {"coordinates":[145.52276599999999,-37.636658],"type":"Point"}
}