{
  "type": "Feature",
  "properties": {
    "iso:country":"AU",
    "sg:address":"29-35 Pine Rd",
    "sg:city":"Shepparton",
    "sg:classifiers":[
        {
            "category":"Health Services",
            "subcategory":"Nursing And Care Facility",
            "type":"Services"
        }
    ],
    "sg:phone":"+61 3 5821 0255",
    "sg:postcode":"3630",
    "sg:province":"VIC",
    "sg:tags":[
        "home"
    ],
    "wof:name":"Shepparton Aged Care",
    "wof:placetype":"venue"
},
  "geometry": {"coordinates":[145.40794372600001,-36.3573265076],"type":"Point"}
}