{
  "type": "Feature",
  "properties": {
    "iso:country":"AU",
    "sg:address":"242 Bourbong St",
    "sg:city":"Bundaberg",
    "sg:classifiers":[
        {
            "category":"Travel",
            "subcategory":"Hotels & Motels",
            "type":"Entertainment"
        }
    ],
    "sg:phone":"+61 7 4152 9922",
    "sg:postcode":"4670",
    "sg:province":"QLD",
    "wof:name":"Chalet Motor Inn.",
    "wof:placetype":"venue"
},
  "geometry": {"coordinates":[152.34117126500001,-24.8684101105],"type":"Point"}
}