{
  "type": "Feature",
  "properties": {
    "addr:full":"Forrest Ave Kirwan QLD 4817",
    "addr:postcode":"4817",
    "addr:street":"Forrest Ave",
    "iso:country":"AU",
    "sg:address":"Forrest Ave",
    "sg:city":"Kirwan",
    "sg:classifiers":[
        {
            "category":"Fast Food",
            "type":"Food & Drink"
        }
    ],
    "sg:phone":"+61 7 4773 2416",
    "sg:postcode":"4817",
    "sg:province":"QLD",
    "sg:tags":[
        "away",
        "take"
    ],
    "wof:name":"La Cucina",
    "wof:placetype":"venue"
},
  "geometry": {"coordinates":[146.74285900000001,-19.309418],"type":"Point"}
}