{
  "type": "Feature",
  "properties": {
    "addr:full":"6 Burns St North Fremantle WA 6159",
    "addr:housenumber":"6",
    "addr:postcode":"6159",
    "addr:street":"Burns St",
    "iso:country":"AU",
    "sg:address":"6 Burns St",
    "sg:city":"North Fremantle",
    "sg:classifiers":[
        {
            "category":"Home & Garden",
            "subcategory":"Carpets & Floor Coverings",
            "type":"Retail Goods"
        }
    ],
    "sg:phone":"+61 8 9335 5339",
    "sg:postcode":"6159",
    "sg:province":"WA",
    "sg:tags":[
        "flooring",
        "parquet"
    ],
    "wof:name":"Noosa Design",
    "wof:placetype":"venue"
},
  "geometry": {"coordinates":[115.75380699999999,-32.035412],"type":"Point"}
}