{
  "type": "Feature",
  "properties": {
    "addr:full":"67 Kallista Rd Rochedale South QLD 4123",
    "addr:housenumber":"67",
    "addr:postcode":"4123",
    "addr:street":"Kallista Rd",
    "iso:country":"AU",
    "sg:address":"67 Kallista Rd",
    "sg:city":"Rochedale South",
    "sg:classifiers":[
        {
            "category":"Shopping",
            "subcategory":"Musical Instruments",
            "type":"Retail Goods"
        }
    ],
    "sg:phone":"+61 412 002 802",
    "sg:postcode":"4123",
    "sg:province":"QLD",
    "sg:tags":[
        "musician",
        "agent"
    ],
    "wof:name":"Lonsdale Karen",
    "wof:placetype":"venue"
},
  "geometry": {"coordinates":[153.142700195,-27.597902298],"type":"Point"}
}