{
  "type": "Feature",
  "properties": {
    "iso:country":"AU",
    "sg:address":"26 Carolina Pde",
    "sg:city":"Forest Lake",
    "sg:classifiers":[
        {
            "category":"Government",
            "subcategory":"Fire Station",
            "type":"Public Place"
        }
    ],
    "sg:phone":"+61 7 3879 8766",
    "sg:postcode":"4078",
    "sg:province":"QLD",
    "sg:tags":[
        "spring",
        "shock",
        "absorbers",
        "suspension"
    ],
    "wof:name":"Powerdown Australia Pty Ltd",
    "wof:placetype":"venue"
},
  "geometry": {"coordinates":[152.97866821299999,-27.6229934692],"type":"Point"}
}