{
  "type": "Feature",
  "properties": {
    "addr:full":"15 Hartington St Elsternwick VIC 3185",
    "addr:housenumber":"15",
    "addr:postcode":"3185",
    "addr:street":"Hartington St",
    "iso:country":"AU",
    "sg:address":"15 Hartington St",
    "sg:city":"Elsternwick",
    "sg:classifiers":[
        {
            "category":"Professional",
            "subcategory":"Computer Services",
            "type":"Services"
        }
    ],
    "sg:phone":"+61 3 9524 3165",
    "sg:postcode":"3185",
    "sg:province":"VIC",
    "sg:tags":[
        "package",
        "software"
    ],
    "wof:name":"Vaxacom Information Systems",
    "wof:placetype":"venue"
},
  "geometry": {"coordinates":[145.01100158700001,-37.8911132812],"type":"Point"}
}