{
  "type": "Feature",
  "properties": {
    "addr:full":"Suite 26, 56 - 62 Chandos St St Leonards NSW 2065",
    "addr:housenumber":"56 62",
    "addr:postcode":"2065",
    "addr:street":"Chandos St",
    "iso:country":"AU",
    "sg:address":"Suite 26, 56 - 62 Chandos St St",
    "sg:city":"Leonards",
    "sg:classifiers":[
        {
            "category":"Building & Trades",
            "subcategory":"Construction",
            "type":"Services"
        }
    ],
    "sg:phone":"+61 2 9966 5095",
    "sg:postcode":"2065",
    "sg:province":"NSW",
    "sg:tags":[
        "window",
        "tinting"
    ],
    "wof:name":"Sun-Gard St Leonards",
    "wof:placetype":"venue"
},
  "geometry": {"coordinates":[151.19790649399999,-33.8218841553],"type":"Point"}
}