{
  "type": "Feature",
  "properties": {
    "addr:full":"178 Pratten St Warwick QLD 4370",
    "addr:housenumber":"178",
    "addr:postcode":"4370",
    "addr:street":"Pratten St",
    "iso:country":"AU",
    "sg:address":"178 Pratten St",
    "sg:city":"Warwick",
    "sg:classifiers":[
        {
            "category":"Education",
            "subcategory":"Music School",
            "type":"Public Place"
        }
    ],
    "sg:phone":"+61 418 723 943",
    "sg:postcode":"4370",
    "sg:province":"QLD",
    "sg:tags":[
        "choir",
        "bands",
        "orchestra"
    ],
    "wof:name":"Jim Kelly",
    "wof:placetype":"venue"
},
  "geometry": {"coordinates":[152.00958251899999,-28.2193489075],"type":"Point"}
}