{
  "type": "Feature",
  "properties": {
    "addr:full":"224 Mountain Ridge Rd Greenbank QLD 4124",
    "addr:housenumber":"224",
    "addr:postcode":"4124",
    "addr:street":"Mountain Ridge Rd",
    "iso:country":"AU",
    "sg:address":"224 Mountain Ridge Rd",
    "sg:city":"Greenbank",
    "sg:classifiers":[
        {
            "category":"Home & Garden",
            "subcategory":"Garden Supply",
            "type":"Retail Goods"
        }
    ],
    "sg:phone":"+61 7 3200 0642",
    "sg:postcode":"4124",
    "sg:province":"QLD",
    "sg:tags":[
        "turf",
        "lawn"
    ],
    "wof:name":"Hanworth Blue Couch",
    "wof:placetype":"venue"
},
  "geometry": {"coordinates":[152.968582153,-27.788028717],"type":"Point"}
}