{
  "type": "Feature",
  "properties": {
    "addr:full":"47 James St Burleigh Heads QLD 4220",
    "addr:housenumber":"47",
    "addr:postcode":"4220",
    "addr:street":"James St",
    "iso:country":"AU",
    "sg:address":"47 James St",
    "sg:city":"Burleigh Heads",
    "sg:classifiers":[
        {
            "category":"Shopping",
            "subcategory":"Beauty & Cosmetics",
            "type":"Retail Goods"
        }
    ],
    "sg:phone":"+61 7 5576 1433",
    "sg:postcode":"4220",
    "sg:province":"QLD",
    "wof:name":"Barbarellas Discount Cosmetics",
    "wof:placetype":"venue"
},
  "geometry": {"coordinates":[153.45013427699999,-28.0890731812],"type":"Point"}
}