{
  "type": "Feature",
  "properties": {
    "iso:country":"AU",
    "sg:address":"4 Lurline St",
    "sg:city":"Cranbourne",
    "sg:classifiers":[
        {
            "category":"Fast Food",
            "type":"Food & Drink"
        }
    ],
    "sg:phone":"+61 3 5996 2029",
    "sg:postcode":"3977",
    "sg:province":"VIC",
    "sg:tags":[
        "away",
        "take"
    ],
    "wof:name":"Silver Mermaid Fish & Chips",
    "wof:placetype":"venue"
},
  "geometry": {"coordinates":[145.27496337900001,-38.1117973328],"type":"Point"}
}