{
  "type": "Feature",
  "properties": {
    "addr:full":"1a Ross St Glenbrook NSW 2773",
    "addr:housenumber":"1a",
    "addr:postcode":"2773",
    "addr:street":"Ross St",
    "iso:country":"AU",
    "sg:address":"1a Ross St",
    "sg:city":"Glenbrook",
    "sg:classifiers":[
        {
            "category":"Education",
            "subcategory":"Special Training",
            "type":"Public Place"
        }
    ],
    "sg:phone":"+61 2 4739 3152",
    "sg:postcode":"2773",
    "sg:province":"NSW",
    "sg:tags":[
        "development"
    ],
    "wof:name":"Blue Mountains Rocksports",
    "wof:placetype":"venue"
},
  "geometry": {"coordinates":[150.622116089,-33.7654724121],"type":"Point"}
}