{
  "type": "Feature",
  "properties": {
    "addr:full":"32 Mickle St Dandenong South VIC 3175",
    "addr:housenumber":"32",
    "addr:postcode":"3175",
    "addr:street":"Mickle St",
    "iso:country":"AU",
    "sg:address":"32 Mickle St",
    "sg:city":"Dandenong South",
    "sg:phone":"+61 3 9768 2228",
    "sg:postcode":"3175",
    "sg:province":"VIC",
    "wof:name":"DSD Tanks Pty Ltd",
    "wof:placetype":"venue"
},
  "geometry": {"coordinates":[145.20619201700001,-38.0303535461],"type":"Point"}
}