{
  "type": "Feature",
  "properties": {
    "addr:full":"Lot 48 Pier Haven Lamb Island QLD 4184",
    "addr:postcode":"4184",
    "addr:street":"Pier",
    "iso:country":"AU",
    "sg:address":"Lot 48",
    "sg:city":"Pier Haven Lamb Island",
    "sg:classifiers":[
        {
            "category":"Home & Garden",
            "subcategory":"Building Materials",
            "type":"Retail Goods"
        }
    ],
    "sg:phone":"+61 418 733 842",
    "sg:postcode":"4184",
    "sg:province":"QLD",
    "sg:tags":[
        "concrete",
        "panel",
        "pre-cast"
    ],
    "wof:name":"All Tilt Panels",
    "wof:placetype":"venue"
},
  "geometry": {"coordinates":[153.37440490700001,-27.6273365021],"type":"Point"}
}