{
  "type": "Feature",
  "properties": {
    "iso:country":"AU",
    "sg:address":"322 Grange Rd",
    "sg:city":"Findon",
    "sg:classifiers":[
        {
            "category":"Home & Garden",
            "subcategory":"Carpets & Floor Coverings",
            "type":"Retail Goods"
        }
    ],
    "sg:phone":"+61 8 8353 3355",
    "sg:postcode":"5023",
    "sg:province":"SA",
    "sg:tags":[
        "tile",
        "wall"
    ],
    "wof:name":"Solomons Flooring",
    "wof:placetype":"venue"
},
  "geometry": {"coordinates":[138.53041076700001,-34.9057235718],"type":"Point"}
}