{
  "type": "Feature",
  "properties": {
    "addr:full":"226a Leichardt St Spring Hill QLD 4000",
    "addr:housenumber":"226a",
    "addr:postcode":"4000",
    "addr:street":"Leichardt St",
    "iso:country":"AU",
    "sg:address":"226a Leichardt St",
    "sg:city":"Spring Hill",
    "sg:classifiers":[
        {
            "category":"Fast Food",
            "type":"Food & Drink"
        }
    ],
    "sg:phone":"+61 7 3831 0308",
    "sg:postcode":"4000",
    "sg:province":"QLD",
    "sg:tags":[
        "away",
        "take"
    ],
    "wof:name":"Dill & Sage Cafe",
    "wof:placetype":"venue"
},
  "geometry": {"coordinates":[153.02655029300001,-27.4616088867],"type":"Point"}
}