{
  "type": "Feature",
  "properties": {
    "iso:country":"AU",
    "sg:address":"56 Landsborough Pde",
    "sg:city":"Golden Beach",
    "sg:classifiers":[
        {
            "category":"Health Services",
            "subcategory":"Doctor",
            "type":"Services"
        }
    ],
    "sg:phone":"+61 7 5491 6244",
    "sg:postcode":"4551",
    "sg:province":"QLD",
    "sg:tags":[
        "podiatrist"
    ],
    "wof:name":"Adam Glascock Podiatry",
    "wof:placetype":"venue"
},
  "geometry": {"coordinates":[153.11993408199999,-26.8218784332],"type":"Point"}
}