{
  "type": "Feature",
  "properties": {
    "iso:country":"AU",
    "sg:address":"Lot 50 Wogolin Rd",
    "sg:city":"Wickepin",
    "sg:classifiers":[
        {
            "category":"Building & Trades",
            "subcategory":"Cleaning & Sanitation",
            "type":"Services"
        }
    ],
    "sg:phone":"+61 429 920 013",
    "sg:postcode":"6370",
    "sg:province":"WA",
    "sg:tags":[
        "abrasive",
        "blasting"
    ],
    "wof:name":"Wickepin Sand Blasting & Spray Painting",
    "wof:placetype":"venue"
},
  "geometry": {"coordinates":[117.501617,-32.781673],"type":"Point"}
}