{
  "type": "Feature",
  "properties": {
    "addr:full":"68B Lockheed St Raby NSW 2566",
    "addr:housenumber":"68b",
    "addr:postcode":"2566",
    "addr:street":"Lockheed St",
    "iso:country":"AU",
    "sg:address":"68B Lockheed St",
    "sg:city":"Raby",
    "sg:classifiers":[
        {
            "category":"Organizations",
            "subcategory":"Professional Association",
            "type":"Services"
        }
    ],
    "sg:phone":"+61 2 9820 8584",
    "sg:postcode":"2566",
    "sg:province":"NSW",
    "sg:tags":[
        "web",
        "internet"
    ],
    "wof:name":"Taipan Internet Services",
    "wof:placetype":"venue"
},
  "geometry": {"coordinates":[150.82225036599999,-34.0287857056],"type":"Point"}
}