{
  "type": "Feature",
  "properties": {
    "addr:full":"49 Lawnton Pocket Rd Lawnton QLD 4501",
    "addr:housenumber":"49",
    "addr:postcode":"4501",
    "addr:street":"Pocket Rd",
    "iso:country":"AU",
    "sg:address":"49 Lawnton Pocket Rd",
    "sg:city":"Lawnton",
    "sg:classifiers":[
        {
            "category":"Retail",
            "subcategory":"Auto Repair",
            "type":"Services"
        }
    ],
    "sg:phone":"+61 7 3285 4058",
    "sg:postcode":"4501",
    "sg:province":"QLD",
    "sg:tags":[
        "body",
        "builder",
        "motor"
    ],
    "wof:name":"Strathpine Crash Repairs",
    "wof:placetype":"venue"
},
  "geometry": {"coordinates":[152.99302673299999,-27.2821903229],"type":"Point"}
}