{
  "type": "Feature",
  "properties": {
    "addr:full":"10 Brendan Drv Nerang QLD 4211",
    "addr:housenumber":"10",
    "addr:postcode":"4211",
    "addr:street":"Brendan Drv",
    "iso:country":"AU",
    "sg:address":"10 Brendan Drv",
    "sg:city":"Nerang",
    "sg:classifiers":[
        {
            "category":"Building & Trades",
            "subcategory":"Equipment Rental",
            "type":"Services"
        }
    ],
    "sg:phone":"+61 7 5596 3099",
    "sg:postcode":"4211",
    "sg:province":"QLD",
    "sg:tags":[
        "supply",
        "catering"
    ],
    "wof:name":"Queensland Commercial Cooking Equipment",
    "wof:placetype":"venue"
},
  "geometry": {"coordinates":[153.34100341800001,-27.9981746674],"type":"Point"}
}