{
  "type": "Feature",
  "properties": {
    "iso:country":"AU",
    "sg:address":"287 Springvale Rd",
    "sg:city":"Springvale",
    "sg:classifiers":[
        {
            "category":"Real Estate",
            "subcategory":"Real Estate Agent",
            "type":"Services"
        }
    ],
    "sg:phone":"+61 3 9546 8211",
    "sg:postcode":"3171",
    "sg:province":"VIC",
    "wof:name":"A.E. McDonald Real Estate",
    "wof:placetype":"venue"
},
  "geometry": {"coordinates":[145.15292358400001,-37.9499893188],"type":"Point"}
}