{
  "type": "Feature",
  "properties": {
    "iso:country":"AU",
    "sg:address":"42-52 Liddiard Rd",
    "sg:city":"Traralgon",
    "sg:classifiers":[
        {
            "category":"Education",
            "subcategory":"Special Training",
            "type":"Public Place"
        }
    ],
    "sg:phone":"+61 3 5174 6629",
    "sg:postcode":"3844",
    "sg:province":"VIC",
    "sg:tags":[
        "drama",
        "speech",
        "speaking",
        "tuition"
    ],
    "wof:name":"Trinity College London",
    "wof:placetype":"venue"
},
  "geometry": {"coordinates":[146.550125122,-38.2100830078],"type":"Point"}
}