{
  "type": "Feature",
  "properties": {
    "iso:country":"AU",
    "sg:address":"23 White St",
    "sg:city":"Emerald",
    "sg:classifiers":[
        {
            "category":"Health Services",
            "subcategory":"Health Practitioner",
            "type":"Services"
        }
    ],
    "sg:phone":"+61 7 4987 7717",
    "sg:postcode":"4720",
    "sg:province":"QLD",
    "sg:tags":[
        "acupuncture"
    ],
    "wof:name":"Emerald Acupuncture",
    "wof:placetype":"venue"
},
  "geometry": {"coordinates":[148.157745,-23.534561],"type":"Point"}
}