{
  "type": "Feature",
  "properties": {
    "iso:country":"AU",
    "sg:address":"Ruthven St",
    "sg:city":"Toowoomba",
    "sg:classifiers":[
        {
            "category":"Building & Trades",
            "subcategory":"Landscaping Services",
            "type":"Services"
        }
    ],
    "sg:phone":"+61 7 4637 9163",
    "sg:postcode":"4350",
    "sg:province":"QLD",
    "sg:tags":[
        "stump",
        "tree",
        "felling",
        "removal"
    ],
    "wof:name":"Garys Mobile Tree Services",
    "wof:placetype":"venue"
},
  "geometry": {"coordinates":[151.95190400000001,-27.569506],"type":"Point"}
}