{
  "type": "Feature",
  "properties": {
    "addr:full":"U1/ 2 Industry Drv Tweed Heads South NSW 2486",
    "addr:housenumber":"2",
    "addr:postcode":"2486",
    "addr:street":"U1 /;Industry Drv",
    "iso:country":"AU",
    "sg:address":"U1/ 2 Industry Drv",
    "sg:city":"Tweed Heads South",
    "sg:classifiers":[
        {
            "category":"Retail",
            "subcategory":"Auto Repair",
            "type":"Services"
        }
    ],
    "sg:phone":"+61 7 5524 5010",
    "sg:postcode":"2486",
    "sg:province":"NSW",
    "sg:tags":[
        "repairer",
        "motor",
        "engineer"
    ],
    "wof:name":"Automotive Technical Services",
    "wof:placetype":"venue"
},
  "geometry": {"coordinates":[153.54142761200001,-28.2004966736],"type":"Point"}
}