{
  "type": "Feature",
  "properties": {
    "iso:country":"AU",
    "sg:address":"25 Barnes St",
    "sg:city":"Cootamundra",
    "sg:classifiers":[
        {
            "category":"Organizations",
            "subcategory":"Non-profit Organization",
            "type":"Services"
        }
    ],
    "sg:phone":"+61 2 6942 4353",
    "sg:postcode":"2590",
    "sg:province":"NSW",
    "sg:tags":[
        "support",
        "disability",
        "organisation"
    ],
    "wof:name":"Elouera Industries",
    "wof:placetype":"venue"
},
  "geometry": {"coordinates":[148.03692626899999,-34.6321907043],"type":"Point"}
}