{
  "type": "Feature",
  "properties": {
    "addr:full":"4 Bridge St Sebastopol VIC 3356",
    "addr:housenumber":"4",
    "addr:postcode":"3356",
    "addr:street":"Bridge St",
    "iso:country":"AU",
    "sg:address":"4 Bridge St",
    "sg:city":"Sebastopol",
    "sg:classifiers":[
        {
            "category":"Personal",
            "subcategory":"Beauty Salon",
            "type":"Services"
        }
    ],
    "sg:phone":"+61 3 5335 6155",
    "sg:postcode":"3356",
    "sg:province":"VIC",
    "sg:tags":[
        "hairdresser"
    ],
    "wof:name":"Jan Wills Hairdressing",
    "wof:placetype":"venue"
},
  "geometry": {"coordinates":[143.84227000000001,-37.599037],"type":"Point"}
}