{
  "type": "Feature",
  "properties": {
    "addr:full":"24 Beach St Kwinana WA 6167",
    "addr:housenumber":"24",
    "addr:postcode":"6167",
    "addr:street":"Beach St",
    "iso:country":"AU",
    "sg:address":"24 Beach St",
    "sg:city":"Kwinana",
    "sg:classifiers":[
        {
            "category":"Home & Garden",
            "subcategory":"Garden Supply",
            "type":"Retail Goods"
        }
    ],
    "sg:phone":"+61 8 9439 1688",
    "sg:postcode":"6167",
    "sg:province":"WA",
    "sg:tags":[
        "fertilizer"
    ],
    "wof:name":"Baileys Fertilisers",
    "wof:placetype":"venue"
},
  "geometry": {"coordinates":[115.776642,-32.243465],"type":"Point"}
}