{
  "type": "Feature",
  "properties": {
    "addr:full":"162 Princes Hwy Nowra NSW 2541",
    "addr:housenumber":"162",
    "addr:postcode":"2541",
    "addr:street":"Princes Hwy",
    "iso:country":"AU",
    "sg:address":"162 Princes Hwy",
    "sg:city":"Nowra",
    "sg:classifiers":[
        {
            "category":"Building & Trades",
            "subcategory":"Construction",
            "type":"Services"
        }
    ],
    "sg:phone":"+61 2 4423 6166",
    "sg:postcode":"2541",
    "sg:province":"NSW",
    "sg:tags":[
        "polishing",
        "sanding",
        "floor"
    ],
    "wof:name":"Independent Floors",
    "wof:placetype":"venue"
},
  "geometry": {"coordinates":[150.603683472,-34.9138374329],"type":"Point"}
}