{
  "type": "Feature",
  "properties": {
    "addr:full":"Strelitzia Ave Forrestfield WA 6058",
    "addr:postcode":"6058",
    "addr:street":"Strelitzia Ave",
    "iso:country":"AU",
    "sg:address":"Strelitzia Ave",
    "sg:city":"Forrestfield",
    "sg:classifiers":[
        {
            "category":"Communications",
            "subcategory":"Film & Video Production",
            "type":"Services"
        }
    ],
    "sg:phone":"+61 8 9359 0909",
    "sg:postcode":"6058",
    "sg:province":"WA",
    "sg:tags":[
        "dvd",
        "library"
    ],
    "wof:name":"Video Ezy",
    "wof:placetype":"venue"
},
  "geometry": {"coordinates":[116.005363464,-31.9813594818],"type":"Point"}
}