{
  "type": "Feature",
  "properties": {
    "addr:full":"Cnr Pitt & Liverpool St Sydney NSW 2000",
    "addr:postcode":"2000",
    "addr:street":"Cnr;St",
    "iso:country":"AU",
    "sg:address":"Cnr Pitt & Liverpool St",
    "sg:city":"Sydney",
    "sg:classifiers":[
        {
            "category":"Restaurant",
            "type":"Food & Drink"
        }
    ],
    "sg:phone":"+61 2 9262 9525",
    "sg:postcode":"2000",
    "sg:province":"NSW",
    "sg:website":"http://www.macchiato.com.au",
    "wof:name":"Macchiato Restaurant",
    "wof:placetype":"venue"
},
  "geometry": {"coordinates":[151.20826721200001,-33.8694496155],"type":"Point"}
}