{
  "type": "Feature",
  "properties": {
    "addr:full":"Smith St Maitland NSW 2320",
    "addr:postcode":"2320",
    "addr:street":"Smith St",
    "iso:country":"AU",
    "sg:address":"Smith St",
    "sg:city":"Maitland",
    "sg:classifiers":[
        {
            "category":"Utilities",
            "type":"Services"
        }
    ],
    "sg:phone":"+61 2 4933 3230",
    "sg:postcode":"2320",
    "sg:province":"NSW",
    "sg:tags":[
        "equipment",
        "towing"
    ],
    "wof:name":"Super Kote",
    "wof:placetype":"venue"
},
  "geometry": {"coordinates":[151.561157227,-32.7395019531],"type":"Point"}
}