{
  "type": "Feature",
  "properties": {
    "iso:country":"AU",
    "sg:address":"28 Doran Pl",
    "sg:city":"Tumbi Umbi",
    "sg:classifiers":[
        {
            "category":"Structure",
            "subcategory":"Office Building",
            "type":"Public Place"
        }
    ],
    "sg:phone":"+61 2 4389 4314",
    "sg:postcode":"2261",
    "sg:province":"NSW",
    "sg:tags":[
        "fire",
        "window",
        "door"
    ],
    "wof:name":"DRC Doors and Building",
    "wof:placetype":"venue"
},
  "geometry": {"coordinates":[151.450897,-33.3675],"type":"Point"}
}