{
  "type": "Feature",
  "properties": {
    "iso:country":"AU",
    "sg:address":"55 Enterprise Drv",
    "sg:city":"Beresfield",
    "sg:classifiers":[
        {
            "category":"Manufacturing",
            "subcategory":"Wood Products",
            "type":"Manufacturing & Wholesale Goods"
        }
    ],
    "sg:phone":"+61 2 4964 4422",
    "sg:postcode":"2322",
    "sg:province":"NSW",
    "sg:tags":[
        "pallet",
        "platform"
    ],
    "wof:name":"Chep Australia",
    "wof:placetype":"venue"
},
  "geometry": {"coordinates":[151.64141845699999,-32.8102340698],"type":"Point"}
}