{
  "type": "Feature",
  "properties": {
    "addr:full":"330 Kiewa St Albury NSW 2640",
    "addr:housenumber":"330",
    "addr:postcode":"2640",
    "addr:street":"Kiewa St",
    "iso:country":"AU",
    "sg:address":"330 Kiewa St",
    "sg:city":"Albury",
    "sg:classifiers":[
        {
            "category":"Social Services",
            "subcategory":"Adult Care",
            "type":"Services"
        }
    ],
    "sg:phone":"+61 2 6041 6929",
    "sg:postcode":"2640",
    "sg:province":"NSW",
    "sg:tags":[
        "towing"
    ],
    "wof:name":"Aldonga Dent Doctor",
    "wof:placetype":"venue"
},
  "geometry": {"coordinates":[146.91598510700001,-36.0797805786],"type":"Point"}
}