{
  "type": "Feature",
  "properties": {
    "addr:full":"1 Cordelia St Dalby QLD 4405",
    "addr:housenumber":"1",
    "addr:postcode":"4405",
    "addr:street":"Cordelia St",
    "iso:country":"AU",
    "sg:address":"1 Cordelia St",
    "sg:city":"Dalby",
    "sg:classifiers":[
        {
            "category":"Retail",
            "subcategory":"Storage",
            "type":"Services"
        }
    ],
    "sg:phone":"+61 7 4669 6183",
    "sg:postcode":"4405",
    "sg:province":"QLD",
    "wof:name":"Dalby Removals & Storage",
    "wof:placetype":"venue"
},
  "geometry": {"coordinates":[151.273681641,-27.1841831207],"type":"Point"}
}