{
  "type": "Feature",
  "properties": {
    "addr:full":"Level 1, Shop 6 Mcfarlane St Merrylands NSW 2160",
    "addr:housenumber":"shop 6",
    "addr:postcode":"2160",
    "addr:street":"Mcfarlane St",
    "iso:country":"AU",
    "sg:address":"Level 1, Shop 6 Mcfarlane St",
    "sg:city":"Merrylands",
    "sg:classifiers":[
        {
            "category":"Professional",
            "subcategory":"Lawyer & Legal Services",
            "type":"Services"
        }
    ],
    "sg:phone":"+61 2 9637 5011",
    "sg:postcode":"2160",
    "sg:province":"NSW",
    "sg:tags":[
        "wills",
        "probate",
        "estate"
    ],
    "wof:name":"Prestige Solicitors & Associates",
    "wof:placetype":"venue"
},
  "geometry": {"coordinates":[150.991455078,-33.8358879089],"type":"Point"}
}