{
  "type": "Feature",
  "properties": {
    "iso:country":"AU",
    "sg:address":"Suite 1, 537",
    "sg:city":"Kingsway Miranda",
    "sg:classifiers":[
        {
            "category":"Education",
            "subcategory":"Special Training",
            "type":"Public Place"
        }
    ],
    "sg:phone":"+61 2 9540 5067",
    "sg:postcode":"2228",
    "sg:province":"NSW",
    "sg:tags":[
        "tuition-educational"
    ],
    "wof:name":"Kip McGrath Education Centres",
    "wof:placetype":"venue"
},
  "geometry": {"coordinates":[151.103713989,-34.0341148376],"type":"Point"}
}