{
  "type": "Feature",
  "properties": {
    "addr:full":"99 Beaumont St Hamilton NSW 2303",
    "addr:housenumber":"99",
    "addr:postcode":"2303",
    "addr:street":"Beaumont St",
    "iso:country":"AU",
    "sg:address":"99 Beaumont St",
    "sg:city":"Hamilton",
    "sg:classifiers":[
        {
            "category":"Shopping",
            "subcategory":"Clothing, Apparel, & Fashions",
            "type":"Retail Goods"
        }
    ],
    "sg:phone":"+61 2 4961 5125",
    "sg:postcode":"2303",
    "sg:province":"NSW",
    "sg:tags":[
        "boutique"
    ],
    "wof:name":"Irene's Boutique",
    "wof:placetype":"venue"
},
  "geometry": {"coordinates":[151.74728400000001,-32.922798],"type":"Point"}
}