{
  "type": "Feature",
  "properties": {
    "iso:country":"AU",
    "sg:address":"214 Baylis St",
    "sg:city":"Wagga Wagga",
    "sg:classifiers":[
        {
            "category":"Health Services",
            "subcategory":"Dentist",
            "type":"Services"
        }
    ],
    "sg:phone":"+61 2 6921 5272",
    "sg:postcode":"2650",
    "sg:province":"NSW",
    "sg:tags":[
        "dental",
        "prosthetist"
    ],
    "wof:name":"Denture & Mouthguard Clinic",
    "wof:placetype":"venue"
},
  "geometry": {"coordinates":[147.37014770499999,-35.1110115051],"type":"Point"}
}