{
  "type": "Feature",
  "properties": {
    "iso:country":"AU",
    "sg:address":"121a Victoria St",
    "sg:city":"Eaglehawk",
    "sg:classifiers":[
        {
            "category":"Manufacturing",
            "subcategory":"Building Materials",
            "type":"Manufacturing & Wholesale Goods"
        }
    ],
    "sg:phone":"+61 3 5446 9322",
    "sg:postcode":"3556",
    "sg:province":"VIC",
    "sg:tags":[
        "concrete",
        "product"
    ],
    "wof:name":"Skinners Pty Ltd",
    "wof:placetype":"venue"
},
  "geometry": {"coordinates":[144.25006103499999,-36.7241172791],"type":"Point"}
}