{
  "type": "Feature",
  "properties": {
    "iso:country":"AU",
    "sg:address":"17 Falmouth St",
    "sg:city":"Hawthorn",
    "sg:classifiers":[
        {
            "category":"Real Estate",
            "subcategory":"Architect",
            "type":"Services"
        }
    ],
    "sg:phone":"+61 3 9818 5030",
    "sg:postcode":"3122",
    "sg:province":"VIC",
    "wof:name":"John Collins Architects",
    "wof:placetype":"venue"
},
  "geometry": {"coordinates":[145.04168701200001,-37.8200111389],"type":"Point"}
}