{
  "type": "Feature",
  "properties": {
    "addr:full":"112 Hotham St Traralgon VIC 3844",
    "addr:housenumber":"112",
    "addr:postcode":"3844",
    "addr:street":"Hotham St",
    "iso:country":"AU",
    "sg:address":"112 Hotham St",
    "sg:city":"Traralgon",
    "sg:classifiers":[
        {
            "category":"Shopping",
            "subcategory":"Clothing, Apparel, & Fashions",
            "type":"Retail Goods"
        }
    ],
    "sg:phone":"+61 3 5174 0333",
    "sg:postcode":"3844",
    "sg:province":"VIC",
    "sg:tags":[
        "lady",
        "wear"
    ],
    "wof:name":"Bloomfields Fashion House",
    "wof:placetype":"venue"
},
  "geometry": {"coordinates":[146.53451538100001,-38.196975708],"type":"Point"}
}