{
  "type": "Feature",
  "properties": {
    "addr:full":"Shp1/ 8 Simms Rd Greensborough VIC 3088",
    "addr:housenumber":"8",
    "addr:postcode":"3088",
    "addr:street":"Simms Rd",
    "iso:country":"AU",
    "sg:address":"Shp1/ 8 Simms Rd",
    "sg:city":"Greensborough",
    "sg:classifiers":[
        {
            "category":"Fast Food",
            "type":"Food & Drink"
        }
    ],
    "sg:phone":"+61 3 9435 6886",
    "sg:postcode":"3088",
    "sg:province":"VIC",
    "sg:tags":[
        "away",
        "take"
    ],
    "wof:name":"Chappys Cafe & Take Away",
    "wof:placetype":"venue"
},
  "geometry": {"coordinates":[145.11392211899999,-37.7119636536],"type":"Point"}
}