{
  "type": "Feature",
  "properties": {
    "iso:country":"AU",
    "sg:address":"475 Pacific Hwy",
    "sg:city":"Wyoming",
    "sg:classifiers":[
        {
            "category":"Fast Food",
            "type":"Food & Drink"
        }
    ],
    "sg:phone":"+61 2 4329 1839",
    "sg:postcode":"2250",
    "sg:province":"NSW",
    "sg:tags":[
        "away",
        "take"
    ],
    "wof:name":"Thai Arees Restaurant",
    "wof:placetype":"venue"
},
  "geometry": {"coordinates":[151.35078430199999,-33.4083480835],"type":"Point"}
}