{
  "type": "Feature",
  "properties": {
    "iso:country":"AU",
    "sg:address":"7 Hutchinson St",
    "sg:city":"Mt Barker",
    "sg:classifiers":[
        {
            "category":"Utilities",
            "subcategory":"Natural Gas",
            "type":"Services"
        }
    ],
    "sg:phone":"+61 8 8391 5156",
    "sg:postcode":"5251",
    "sg:province":"SA",
    "sg:tags":[
        "consultant",
        "resource"
    ],
    "wof:name":"Fatchen Environmental Pty Ltd",
    "wof:placetype":"venue"
},
  "geometry": {"coordinates":[138.85809326200001,-35.0636444092],"type":"Point"}
}