{
  "type": "Feature",
  "properties": {
    "addr:full":"10 Coolibah Drv Kununurra WA 6743",
    "addr:housenumber":"10",
    "addr:postcode":"6743",
    "addr:street":"Coolibah Drv",
    "iso:country":"AU",
    "sg:address":"10 Coolibah Drv",
    "sg:city":"Kununurra",
    "sg:classifiers":[
        {
            "category":"Real Estate",
            "subcategory":"Surveying",
            "type":"Services"
        }
    ],
    "sg:phone":"+61 8 9168 1479",
    "sg:postcode":"6743",
    "sg:province":"WA",
    "sg:tags":[
        "surveyor",
        "land"
    ],
    "wof:name":"Johnson Warren F",
    "wof:placetype":"venue"
},
  "geometry": {"coordinates":[128.73927307100001,-15.7720890045],"type":"Point"}
}