{
  "type": "Feature",
  "properties": {
    "addr:full":"40 McKell Ave Sunbury VIC 3429",
    "addr:housenumber":"40",
    "addr:postcode":"3429",
    "addr:street":"Mckell Ave",
    "iso:country":"AU",
    "sg:address":"40 McKell Ave",
    "sg:city":"Sunbury",
    "sg:classifiers":[
        {
            "category":"Health Services",
            "subcategory":"Doctor",
            "type":"Services"
        }
    ],
    "sg:phone":"+61 3 9744 7511",
    "sg:postcode":"3429",
    "sg:province":"VIC",
    "sg:tags":[
        "medical",
        "practitioner"
    ],
    "wof:name":"McKell Ave Medical Centre",
    "wof:placetype":"venue"
},
  "geometry": {"coordinates":[144.725708008,-37.5738601685],"type":"Point"}
}