{
  "type": "Feature",
  "properties": {
    "addr:full":"22 Binnie St Tara QLD 4421",
    "addr:housenumber":"22",
    "addr:postcode":"4421",
    "addr:street":"Binnie St",
    "iso:country":"AU",
    "sg:address":"22 Binnie St",
    "sg:city":"Tara",
    "sg:classifiers":[
        {
            "category":"Education",
            "subcategory":"School",
            "type":"Public Place"
        }
    ],
    "sg:phone":"+61 7 4678 7333",
    "sg:postcode":"4421",
    "sg:province":"QLD",
    "sg:tags":[
        "state",
        "except",
        "nsw"
    ],
    "wof:name":"Tara Shire State College Primary",
    "wof:placetype":"venue"
},
  "geometry": {"coordinates":[150.45916748100001,-27.2796535492],"type":"Point"}
}