{
  "type": "Feature",
  "properties": {
    "iso:country":"AU",
    "sg:address":"7/ 131 Scott St",
    "sg:city":"Bungalow",
    "sg:classifiers":[
        {
            "category":"Shopping",
            "subcategory":"Computers & Home Electronics",
            "type":"Retail Goods"
        }
    ],
    "sg:phone":"+61 7 4041 3366",
    "sg:postcode":"4870",
    "sg:province":"QLD",
    "sg:tags":[
        "equipment",
        "supply"
    ],
    "wof:name":"Coral Coast Cartridges",
    "wof:placetype":"venue"
},
  "geometry": {"coordinates":[145.75796508799999,-16.9358654022],"type":"Point"}
}