{
  "type": "Feature",
  "properties": {
    "addr:full":"U13b/ 4 Homepride Ave Warwick Farm NSW 2170",
    "addr:postcode":"2170",
    "addr:street":"Homepride Ave",
    "iso:country":"AU",
    "sg:address":"U13b/ 4 Homepride Ave",
    "sg:city":"Warwick Farm",
    "sg:classifiers":[
        {
            "category":"Home & Garden",
            "subcategory":"Building Materials",
            "type":"Retail Goods"
        }
    ],
    "sg:phone":"+61 2 9600 6199",
    "sg:postcode":"2170",
    "sg:province":"NSW",
    "sg:tags":[
        "merchant",
        "glass",
        "glazier"
    ],
    "sg:website":"http://www.nlglass.com",
    "wof:name":"Nl Glass Splashbacks",
    "wof:placetype":"venue"
},
  "geometry": {"coordinates":[150.92451477,-33.9140663147],"type":"Point"}
}