{
  "type": "Feature",
  "properties": {
    "iso:country":"AU",
    "sg:address":"379 City Rd",
    "sg:city":"South Melbourne",
    "sg:classifiers":[
        {
            "category":"Retail",
            "subcategory":"Auto Repair",
            "type":"Services"
        }
    ],
    "sg:phone":"+61 3 9696 1744",
    "sg:postcode":"3205",
    "sg:province":"VIC",
    "sg:tags":[
        "repairer",
        "motor",
        "engineer"
    ],
    "wof:name":"UltraTune#",
    "wof:placetype":"venue"
},
  "geometry": {"coordinates":[144.955994,-37.829212],"type":"Point"}
}