{
  "type": "Feature",
  "properties": {
    "addr:full":"22A Hillcrest St Tempe NSW 2044",
    "addr:housenumber":"22a",
    "addr:postcode":"2044",
    "addr:street":"Hillcrest St",
    "iso:country":"AU",
    "sg:address":"22A Hillcrest St",
    "sg:city":"Tempe",
    "sg:classifiers":[
        {
            "category":"Education",
            "subcategory":"Special Training",
            "type":"Public Place"
        }
    ],
    "sg:phone":"+61 2 9558 3332",
    "sg:postcode":"2044",
    "sg:province":"NSW",
    "sg:tags":[
        "development"
    ],
    "wof:name":"Kriskindl Education Centre",
    "wof:placetype":"venue"
},
  "geometry": {"coordinates":[151.16160600000001,-33.918217],"type":"Point"}
}