{
  "type": "Feature",
  "properties": {
    "addr:full":"86 Duncan St Maroubra NSW 2035",
    "addr:housenumber":"86",
    "addr:postcode":"2035",
    "addr:street":"Duncan St",
    "iso:country":"AU",
    "sg:address":"86 Duncan St",
    "sg:city":"Maroubra",
    "sg:classifiers":[
        {
            "category":"Health Services",
            "subcategory":"Health Practitioner",
            "type":"Services"
        }
    ],
    "sg:phone":"+61 2 9349 5700",
    "sg:postcode":"2035",
    "sg:province":"NSW",
    "sg:tags":[
        "pathologist",
        "speech"
    ],
    "wof:name":"Petersen Louise",
    "wof:placetype":"venue"
},
  "geometry": {"coordinates":[151.255203247,-33.9439811707],"type":"Point"}
}