{
  "type": "Feature",
  "properties": {
    "addr:full":"7 Beltana Rd Pialligo ACT 2609",
    "addr:housenumber":"7",
    "addr:postcode":"2609",
    "addr:street":"Beltana Rd",
    "iso:country":"AU",
    "sg:address":"7 Beltana Rd",
    "sg:city":"Pialligo",
    "sg:classifiers":[
        {
            "category":"Farming",
            "subcategory":"Livestock Farm",
            "type":"Manufacturing & Wholesale Goods"
        }
    ],
    "sg:phone":"+61 2 6247 6217",
    "sg:postcode":"2609",
    "sg:province":"ACT",
    "sg:tags":[
        "agistment"
    ],
    "wof:name":"Hayshed The",
    "wof:placetype":"venue"
},
  "geometry": {"coordinates":[149.18113708499999,-35.3072738647],"type":"Point"}
}