{
  "type": "Feature",
  "properties": {
    "iso:country":"AU",
    "sg:address":"Cnr Preston & Wondall Rds",
    "sg:city":"Wynnum West",
    "sg:classifiers":[
        {
            "category":"Retail",
            "subcategory":"Auto Repair",
            "type":"Services"
        }
    ],
    "sg:phone":"+61 7 3348 3844",
    "sg:postcode":"4178",
    "sg:province":"QLD",
    "sg:tags":[
        "testing",
        "inspection",
        "motor",
        "vehicle"
    ],
    "wof:name":"Daniel's Mechanical",
    "wof:placetype":"venue"
},
  "geometry": {"coordinates":[153.15931701700001,-27.4532337189],"type":"Point"}
}