{
  "type": "Feature",
  "properties": {
    "addr:full":"34 Phillip St Parramatta NSW 2150",
    "addr:housenumber":"34",
    "addr:postcode":"2150",
    "addr:street":"Phillip St",
    "iso:country":"AU",
    "sg:address":"34 Phillip St",
    "sg:city":"Parramatta",
    "sg:classifiers":[
        {
            "category":"Food & Beverages",
            "subcategory":"Specialty",
            "type":"Retail Goods"
        }
    ],
    "sg:phone":"+61 2 9635 3011",
    "sg:postcode":"2150",
    "sg:province":"NSW",
    "sg:tags":[
        "product",
        "health"
    ],
    "wof:name":"Forever Living Products Aust Pty Ltd",
    "wof:placetype":"venue"
},
  "geometry": {"coordinates":[150.964935303,-33.8514900208],"type":"Point"}
}