{
  "type": "Feature",
  "properties": {
    "iso:country":"AU",
    "sg:address":"Lot1/ Munbura Rd",
    "sg:city":"Munbura",
    "sg:classifiers":[
        {
            "category":"Retail",
            "subcategory":"Auto Repair",
            "type":"Services"
        }
    ],
    "sg:phone":"+61 7 4956 5042",
    "sg:postcode":"4741",
    "sg:province":"QLD",
    "sg:tags":[
        "repairer",
        "motor",
        "engineer"
    ],
    "wof:name":"T W Mcroberts",
    "wof:placetype":"venue"
},
  "geometry": {"coordinates":[149.12164300000001,-21.37553],"type":"Point"}
}