{
  "type": "Feature",
  "properties": {
    "iso:country":"AU",
    "sg:address":"PO Box 7197",
    "sg:city":"Garbutt Business Centre",
    "sg:classifiers":[
        {
            "category":"Professional",
            "subcategory":"Art Services",
            "type":"Services"
        }
    ],
    "sg:phone":"+61 7 4774 7125",
    "sg:postcode":"4814",
    "sg:province":"QLD",
    "sg:tags":[
        "decorator",
        "painter"
    ],
    "wof:name":"Haydon Mann",
    "wof:placetype":"venue"
},
  "geometry": {"coordinates":[146.762527,-19.292179],"type":"Point"}
}