{
  "type": "Feature",
  "properties": {
    "addr:full":"88 Gidley St Molong NSW 2866",
    "addr:housenumber":"88",
    "addr:postcode":"2866",
    "addr:street":"Gidley St",
    "iso:country":"AU",
    "sg:address":"88 Gidley St",
    "sg:city":"Molong",
    "sg:classifiers":[
        {
            "category":"Museum",
            "subcategory":"Art Museum",
            "type":"Entertainment"
        }
    ],
    "sg:phone":"+61 2 6366 8657",
    "sg:postcode":"2866",
    "sg:province":"NSW",
    "sg:tags":[
        "antique",
        "fine",
        "valuer"
    ],
    "wof:name":"C J Crowe",
    "wof:placetype":"venue"
},
  "geometry": {"coordinates":[148.866974,-33.100563],"type":"Point"}
}