{
  "type": "Feature",
  "properties": {
    "iso:country":"AU",
    "sg:address":"71 Wattletree Rd",
    "sg:city":"Hurstbridge",
    "sg:classifiers":[
        {
            "category":"Building & Trades",
            "subcategory":"Construction",
            "type":"Services"
        }
    ],
    "sg:phone":"+61 412 541 423",
    "sg:postcode":"3099",
    "sg:province":"VIC",
    "sg:tags":[
        "earth",
        "excavating",
        "moving",
        "contractor"
    ],
    "wof:name":"Down To Earth Landscapes",
    "wof:placetype":"venue"
},
  "geometry": {"coordinates":[145.18548584000001,-37.6296386719],"type":"Point"}
}