{
  "type": "Feature",
  "properties": {
    "addr:full":"Unit 3 & 4/ 2 Harford St Penrith NSW 2750",
    "addr:housenumber":"&;/ 2",
    "addr:postcode":"2750",
    "addr:street":"Harford St",
    "iso:country":"AU",
    "sg:address":"Unit 3 & 4/ 2 Harford St",
    "sg:city":"Penrith",
    "sg:classifiers":[
        {
            "category":"Home & Garden",
            "subcategory":"Building Materials",
            "type":"Retail Goods"
        }
    ],
    "sg:phone":"+61 2 4731 1533",
    "sg:postcode":"2750",
    "sg:province":"NSW",
    "sg:tags":[
        "roofing"
    ],
    "wof:name":"Jay Jay Building Supplies",
    "wof:placetype":"venue"
},
  "geometry": {"coordinates":[150.68580627399999,-33.7649536133],"type":"Point"}
}