{
  "type": "Feature",
  "properties": {
    "iso:country":"AU",
    "sg:address":"2nd Floor 160 Scarborough St",
    "sg:city":"Southport",
    "sg:classifiers":[
        {
            "category":"Arena",
            "subcategory":"Sports Club",
            "type":"Entertainment"
        }
    ],
    "sg:phone":"+61 414 345 177",
    "sg:postcode":"4215",
    "sg:province":"QLD",
    "sg:tags":[
        "defence",
        "supply",
        "self",
        "instruction",
        "martial art"
    ],
    "wof:name":"Wing Chun Kung Fu",
    "wof:placetype":"venue"
},
  "geometry": {"coordinates":[153.41067504899999,-27.9627609253],"type":"Point"}
}