{
  "type": "Feature",
  "properties": {
    "addr:full":"7 Latrobe St Warragul VIC 3820",
    "addr:housenumber":"7",
    "addr:postcode":"3820",
    "addr:street":"Latrobe St",
    "iso:country":"AU",
    "sg:address":"7 Latrobe St",
    "sg:city":"Warragul",
    "sg:classifiers":[
        {
            "category":"Professional",
            "subcategory":"Printing & Photocopies",
            "type":"Services"
        }
    ],
    "sg:phone":"+61 3 5623 6644",
    "sg:postcode":"3820",
    "sg:province":"VIC",
    "sg:tags":[
        "photocopying"
    ],
    "wof:name":"RMI Print Pty. Ltd.",
    "wof:placetype":"venue"
},
  "geometry": {"coordinates":[145.92266799999999,-38.15836],"type":"Point"}
}