{
  "type": "Feature",
  "properties": {
    "iso:country":"AU",
    "sg:address":"46 Swift Ave",
    "sg:city":"Dulwich",
    "sg:classifiers":[
        {
            "category":"Health Services",
            "subcategory":"Health Practitioner",
            "type":"Services"
        }
    ],
    "sg:phone":"+61 8 8332 0577",
    "sg:postcode":"5065",
    "sg:province":"SA",
    "sg:tags":[
        "pathologist",
        "speech"
    ],
    "wof:name":"Dodd Beverley",
    "wof:placetype":"venue"
},
  "geometry": {"coordinates":[138.629180908,-34.9361610413],"type":"Point"}
}