{
  "type": "Feature",
  "properties": {
    "iso:country":"AU",
    "sg:address":"Brooke St",
    "sg:city":"Woodend",
    "sg:classifiers":[
        {
            "category":"Health Services",
            "subcategory":"Doctor",
            "type":"Services"
        }
    ],
    "sg:phone":"+61 3 5427 1002",
    "sg:postcode":"3442",
    "sg:province":"VIC",
    "sg:tags":[
        "medical",
        "practitioner"
    ],
    "wof:name":"Atkins C",
    "wof:placetype":"venue"
},
  "geometry": {"coordinates":[144.53111267099999,-37.3595542908],"type":"Point"}
}