{
  "type": "Feature",
  "properties": {
    "iso:country":"AU",
    "sg:address":"Deakin Ave",
    "sg:city":"Mildura",
    "sg:classifiers":[
        {
            "category":"Personal",
            "subcategory":"Massage",
            "type":"Services"
        }
    ],
    "sg:phone":"+61 3 5022 1337",
    "sg:postcode":"3500",
    "sg:province":"VIC",
    "sg:tags":[
        "therapy"
    ],
    "wof:name":"Rest Assured Massage Centre",
    "wof:placetype":"venue"
},
  "geometry": {"coordinates":[142.143112183,-34.2014122009],"type":"Point"}
}