{
  "type": "Feature",
  "properties": {
    "addr:full":"16 Henry St St George QLD 4487",
    "addr:housenumber":"16",
    "addr:postcode":"4487",
    "addr:street":"Henry St",
    "iso:country":"AU",
    "sg:address":"16 Henry St",
    "sg:city":"St George",
    "sg:classifiers":[
        {
            "category":"Cafe",
            "type":"Food & Drink"
        }
    ],
    "sg:phone":"+61 7 4625 3707",
    "sg:postcode":"4487",
    "sg:province":"QLD",
    "wof:name":"Food Basket",
    "wof:placetype":"venue"
},
  "geometry": {"coordinates":[148.582427978,-28.0370101929],"type":"Point"}
}