{
  "type": "Feature",
  "properties": {
    "iso:country":"AU",
    "sg:address":"33 Ashley Ave",
    "sg:city":"Quinns Rocks",
    "sg:classifiers":[
        {
            "category":"Food & Beverages",
            "subcategory":"Fruits & Vegetables",
            "type":"Retail Goods"
        }
    ],
    "sg:phone":"+61 8 9305 2535",
    "sg:postcode":"6030",
    "sg:province":"WA",
    "sg:tags":[
        "consultant",
        "catering"
    ],
    "wof:name":"True Blue Aussie Hot Dogs",
    "wof:placetype":"venue"
},
  "geometry": {"coordinates":[115.692832947,-31.6658725739],"type":"Point"}
}