{
  "type": "Feature",
  "properties": {
    "addr:full":"93 Separation St Bell Park VIC 3215",
    "addr:housenumber":"93",
    "addr:postcode":"3215",
    "addr:street":"Separation St",
    "iso:country":"AU",
    "sg:address":"93 Separation St",
    "sg:city":"Bell Park",
    "sg:classifiers":[
        {
            "category":"Retail",
            "subcategory":"Event Space",
            "type":"Services"
        }
    ],
    "sg:phone":"+61 3 5278 2596",
    "sg:postcode":"3215",
    "sg:province":"VIC",
    "sg:tags":[
        "venue",
        "reception",
        "wedding"
    ],
    "wof:name":"Australian Croatian Association Geelong",
    "wof:placetype":"venue"
},
  "geometry": {"coordinates":[144.34165954599999,-38.110710144],"type":"Point"}
}