{
  "type": "Feature",
  "properties": {
    "addr:full":"28 Rowlands St Slacks Creek QLD 4127",
    "addr:housenumber":"28",
    "addr:postcode":"4127",
    "addr:street":"Rowlands St",
    "iso:country":"AU",
    "sg:address":"28 Rowlands St",
    "sg:city":"Slacks Creek",
    "sg:classifiers":[
        {
            "category":"Retail",
            "subcategory":"Laundry & Dry Cleaning",
            "type":"Services"
        }
    ],
    "sg:phone":"+61 7 3352 5732",
    "sg:postcode":"4127",
    "sg:province":"QLD",
    "wof:name":"Logan City Commercial Laundry",
    "wof:placetype":"venue"
},
  "geometry": {"coordinates":[153.12677001899999,-27.6306552887],"type":"Point"}
}