{
  "type": "Feature",
  "properties": {
    "addr:full":"34 Cottenham Ave Kensington NSW 2033",
    "addr:housenumber":"34",
    "addr:postcode":"2033",
    "addr:street":"Cottenham Ave",
    "iso:country":"AU",
    "sg:address":"34 Cottenham Ave",
    "sg:city":"Kensington",
    "sg:classifiers":[
        {
            "category":"Utilities",
            "subcategory":"Refuse",
            "type":"Services"
        }
    ],
    "sg:phone":"+61 2 9663 4976",
    "sg:postcode":"2033",
    "sg:province":"NSW",
    "sg:tags":[
        "remover",
        "rubbish"
    ],
    "wof:name":"Land -E-Scape Property Maintenance",
    "wof:placetype":"venue"
},
  "geometry": {"coordinates":[151.22160299999999,-33.916153],"type":"Point"}
}