{
  "type": "Feature",
  "properties": {
    "addr:full":"Ommaney Rd Brunswick Junction WA 6224",
    "addr:postcode":"6224",
    "addr:street":"Ommaney Rd",
    "iso:country":"AU",
    "sg:address":"Ommaney Rd",
    "sg:city":"Brunswick Junction",
    "sg:classifiers":[
        {
            "category":"Farming",
            "subcategory":"Dairy Farm",
            "type":"Manufacturing & Wholesale Goods"
        }
    ],
    "sg:phone":"+61 8 9726 8777",
    "sg:postcode":"6224",
    "sg:province":"WA",
    "sg:tags":[
        "wholesaler",
        "product",
        "mfrs"
    ],
    "wof:name":"Peters Creameries (WA) Pty Ltd",
    "wof:placetype":"venue"
},
  "geometry": {"coordinates":[115.839691,-33.252106],"type":"Point"}
}