{
  "type": "Feature",
  "properties": {
    "iso:country":"AU",
    "sg:address":"1a/ 195 Murray St",
    "sg:city":"Tanunda",
    "sg:classifiers":[
        {
            "category":"Autos & Motor Vehicles",
            "subcategory":"Automobile Sales",
            "type":"Retail Goods"
        }
    ],
    "sg:phone":"+61 8 8563 2996",
    "sg:postcode":"5352",
    "sg:province":"SA",
    "sg:tags":[
        "car",
        "used"
    ],
    "wof:name":"Barossa Moteur Industrie",
    "wof:placetype":"venue"
},
  "geometry": {"coordinates":[138.96992492699999,-34.5165634155],"type":"Point"}
}