{
  "type": "Feature",
  "properties": {
    "addr:full":"Westfield Bondi Junction, Level 4 Car Park, Westfield Mall Bondi Junction NSW 2022",
    "addr:postcode":"2022",
    "iso:country":"AU",
    "sg:address":"Westfield Bondi Junction, Level 4 Car Park, Westfield Mall",
    "sg:city":"Bondi Junction",
    "sg:classifiers":[
        {
            "category":"Retail",
            "subcategory":"Car Wash",
            "type":"Services"
        }
    ],
    "sg:phone":"+61 2 9387 6280",
    "sg:postcode":"2022",
    "sg:province":"NSW",
    "sg:tags":[
        "truck",
        "cleaning"
    ],
    "wof:name":"Enviro Car Care",
    "wof:placetype":"venue"
},
  "geometry": {"coordinates":[151.253463745,-33.8911018372],"type":"Point"}
}