{
  "type": "Feature",
  "properties": {
    "addr:full":"639a Hay St Mall Perth WA 6000",
    "addr:housenumber":"639a",
    "addr:postcode":"6000",
    "addr:street":"Hay St Mall",
    "iso:country":"AU",
    "sg:address":"639a Hay St",
    "sg:city":"Mall Perth",
    "sg:classifiers":[
        {
            "category":"Banks & Credit Unions",
            "subcategory":"Bureau De Change",
            "type":"Services"
        }
    ],
    "sg:phone":"+61 8 9221 1261",
    "sg:postcode":"6000",
    "sg:province":"WA",
    "sg:tags":[
        "currency",
        "exchange",
        "foreign"
    ],
    "wof:name":"Nationwide Foreign Exchange",
    "wof:placetype":"venue"
},
  "geometry": {"coordinates":[115.855262756,-31.953119278],"type":"Point"}
}