{
  "type": "Feature",
  "properties": {
    "addr:full":"16 Weaver Pl Woronora Heights NSW 2233",
    "addr:housenumber":"16",
    "addr:postcode":"2233",
    "addr:street":"Weaver Pl",
    "iso:country":"AU",
    "sg:address":"16 Weaver Pl",
    "sg:city":"Woronora Heights",
    "sg:classifiers":[
        {
            "category":"Building & Trades",
            "subcategory":"Cleaning & Sanitation",
            "type":"Services"
        }
    ],
    "sg:phone":"+61 417 016 002",
    "sg:postcode":"2233",
    "sg:province":"NSW",
    "sg:tags":[
        "chemical",
        "pressure",
        "steam",
        "contractor"
    ],
    "wof:name":"Home Care 2000 Clad Clean",
    "wof:placetype":"venue"
},
  "geometry": {"coordinates":[151.02494812,-34.0355949402],"type":"Point"}
}