{
  "type": "Feature",
  "properties": {
    "addr:full":"720 Sydney Rd Brunswick VIC 3056",
    "addr:housenumber":"720",
    "addr:postcode":"3056",
    "addr:street":"Sydney Rd",
    "iso:country":"AU",
    "sg:address":"720 Sydney Rd",
    "sg:city":"Brunswick",
    "sg:classifiers":[
        {
            "category":"Shopping",
            "type":"Retail Goods"
        }
    ],
    "sg:phone":"+61 3 9383 4341",
    "sg:postcode":"3056",
    "sg:province":"VIC",
    "sg:tags":[
        "repair",
        "travel"
    ],
    "wof:name":"Noah Luggage",
    "wof:placetype":"venue"
},
  "geometry": {"coordinates":[144.963378906,-37.7604408264],"type":"Point"}
}