{
  "type": "Feature",
  "properties": {
    "iso:country":"AU",
    "sg:address":"1 Ti Tree Pl",
    "sg:city":"Byron Bay",
    "sg:classifiers":[
        {
            "category":"Coffee & Tea",
            "type":"Food & Drink"
        }
    ],
    "sg:phone":"+61 2 6685 6403",
    "sg:postcode":"2481",
    "sg:province":"NSW",
    "sg:tags":[
        "kayak",
        "canoe"
    ],
    "wof:name":"Kayaks At Byron Bay",
    "wof:placetype":"venue"
},
  "geometry": {"coordinates":[153.58653259299999,-28.6346874237],"type":"Point"}
}