{
  "type": "Feature",
  "properties": {
    "addr:full":"Shop 13 Stafford City Shopping Centre, 400 Stafford Rd Stafford QLD 4053",
    "addr:housenumber":"shop 13;400",
    "addr:postcode":"4053",
    "addr:street":"Stafford City;Stafford Rd",
    "iso:country":"AU",
    "sg:address":"Shop 13 Stafford City Shopping Centre, 400 Stafford Rd",
    "sg:city":"Stafford",
    "sg:classifiers":[
        {
            "category":"Shopping",
            "subcategory":"Mobile Phones",
            "type":"Retail Goods"
        }
    ],
    "sg:phone":"+61 7 3352 7033",
    "sg:postcode":"4053",
    "sg:province":"QLD",
    "sg:tags":[
        "telephone",
        "accessory"
    ],
    "wof:name":"Telstra Shop",
    "wof:placetype":"venue"
},
  "geometry": {"coordinates":[153.011474609,-27.4099388123],"type":"Point"}
}