{
  "type": "Feature",
  "properties": {
    "addr:full":"1570 Wester Hwy Rockbank VIC 3335",
    "addr:postcode":"1570;3335",
    "addr:street":"Wester Hwy",
    "iso:country":"AU",
    "sg:address":"1570 Wester Hwy",
    "sg:city":"Rockbank",
    "sg:classifiers":[
        {
            "category":"Utilities",
            "subcategory":"Refuse",
            "type":"Services"
        }
    ],
    "sg:phone":"+61 412 004 003",
    "sg:postcode":"3335",
    "sg:province":"VIC",
    "sg:tags":[
        "remover",
        "rubbish"
    ],
    "wof:name":"Gary's Car Removals",
    "wof:placetype":"venue"
},
  "geometry": {"coordinates":[144.704025,-37.746319],"type":"Point"}
}