{
  "type": "Feature",
  "properties": {
    "iso:country":"AU",
    "sg:address":"8 Macarthur St",
    "sg:city":"Cottesloe",
    "sg:classifiers":[
        {
            "category":"Travel",
            "subcategory":"Hotels & Motels",
            "type":"Entertainment"
        }
    ],
    "sg:phone":"+61 8 9284 2555",
    "sg:postcode":"6011",
    "sg:province":"WA",
    "wof:name":"Cottesloe Waters",
    "wof:placetype":"venue"
},
  "geometry": {"coordinates":[115.752670288,-32.0112724304],"type":"Point"}
}