{
  "type": "Feature",
  "properties": {
    "addr:full":"634 King St Newtown NSW 2042",
    "addr:housenumber":"634",
    "addr:postcode":"2042",
    "addr:street":"King St",
    "iso:country":"AU",
    "sg:address":"634 King St",
    "sg:city":"Newtown",
    "sg:classifiers":[
        {
            "category":"Ice Cream",
            "type":"Food & Drink"
        }
    ],
    "sg:phone":"+61 2 9516 3146",
    "sg:postcode":"2042",
    "sg:province":"NSW",
    "sg:tags":[
        "specialised",
        "fitting",
        "lady",
        "wear"
    ],
    "wof:name":"Varivi Indian Fashion",
    "wof:placetype":"venue"
},
  "geometry": {"coordinates":[151.18090799999999,-33.905254],"type":"Point"}
}