{
  "type": "Feature",
  "properties": {
    "iso:country":"AU",
    "sg:address":"50 Morley St",
    "sg:city":"Coorparoo",
    "sg:classifiers":[
        {
            "category":"Home & Garden",
            "subcategory":"Building Materials",
            "type":"Retail Goods"
        }
    ],
    "sg:phone":"+61 7 3394 1234",
    "sg:postcode":"4151",
    "sg:province":"QLD",
    "sg:tags":[
        "plaster",
        "plasterboard",
        "supply"
    ],
    "wof:name":"Plaster quip",
    "wof:placetype":"venue"
},
  "geometry": {"coordinates":[153.052368164,-27.4918727875],"type":"Point"}
}