{
  "type": "Feature",
  "properties": {
    "addr:full":"U4/ 2 Travers St Coconut Grove NT 0810",
    "addr:housenumber":"2",
    "addr:postcode":"0810",
    "addr:street":"U4 /;Travers St",
    "iso:country":"AU",
    "sg:address":"U4/ 2 Travers St",
    "sg:city":"Coconut Grove",
    "sg:classifiers":[
        {
            "category":"Metro Station",
            "type":"Transportation"
        }
    ],
    "sg:phone":"+61 8 8985 3300",
    "sg:postcode":"0810",
    "sg:province":"NT",
    "sg:tags":[
        "consultant",
        "marine"
    ],
    "wof:name":"Brian White & Associates",
    "wof:placetype":"venue"
},
  "geometry": {"coordinates":[130.85255432100001,-12.4012441635],"type":"Point"}
}