{
  "type": "Feature",
  "properties": {
    "addr:full":"PO Box 1737 Castle Hill NSW 1765",
    "addr:postcode":"1765",
    "iso:country":"AU",
    "sg:address":"PO Box 1737",
    "sg:city":"Castle Hill",
    "sg:classifiers":[
        {
            "category":"Communications",
            "subcategory":"Film & Video Production",
            "type":"Services"
        }
    ],
    "sg:phone":"+61 2 9571 5222",
    "sg:postcode":"1765",
    "sg:province":"NSW",
    "sg:tags":[
        "information",
        "recorded",
        "telephone"
    ],
    "wof:name":"Telads (NSW) Pty Ltd",
    "wof:placetype":"venue"
},
  "geometry": {"coordinates":[151.01724200000001,-33.730858],"type":"Point"}
}