{
  "type": "Feature",
  "properties": {
    "iso:country":"AU",
    "sg:address":"377 Gardeners Rd",
    "sg:city":"Mascot",
    "sg:classifiers":[
        {
            "category":"Real Estate",
            "subcategory":"Real Estate Agent",
            "type":"Services"
        }
    ],
    "sg:phone":"+61 2 9669 6066",
    "sg:postcode":"1460",
    "sg:province":"NSW",
    "wof:name":"Firmstone First National",
    "wof:placetype":"venue"
},
  "geometry": {"coordinates":[151.203399658,-33.9225349426],"type":"Point"}
}