{
  "type": "Feature",
  "properties": {
    "addr:full":"75 Perkins St South Townsville QLD 4810",
    "addr:housenumber":"75",
    "addr:postcode":"4810",
    "addr:street":"Perkins St",
    "iso:country":"AU",
    "sg:address":"75 Perkins St",
    "sg:city":"South Townsville",
    "sg:classifiers":[
        {
            "category":"Wholesale",
            "subcategory":"Toys & Hobbies",
            "type":"Manufacturing & Wholesale Goods"
        }
    ],
    "sg:phone":"+61 7 4772 3264",
    "sg:postcode":"4810",
    "sg:province":"QLD",
    "wof:name":"Dick Yuen Agencies",
    "wof:placetype":"venue"
},
  "geometry": {"coordinates":[146.820694,-19.269415],"type":"Point"}
}