{
  "type": "Feature",
  "properties": {
    "addr:full":"17 Yuille St Frankston VIC 3199",
    "addr:housenumber":"17",
    "addr:postcode":"3199",
    "addr:street":"Yuille St",
    "iso:country":"AU",
    "sg:address":"17 Yuille St",
    "sg:city":"Frankston",
    "sg:classifiers":[
        {
            "category":"Health Services",
            "subcategory":"Doctor",
            "type":"Services"
        }
    ],
    "sg:phone":"+61 3 9781 5888",
    "sg:postcode":"3199",
    "sg:province":"VIC",
    "sg:tags":[
        "medical",
        "practitioner"
    ],
    "wof:name":"Ross David A.",
    "wof:placetype":"venue"
},
  "geometry": {"coordinates":[145.00064086899999,-37.9271507263],"type":"Point"}
}