{
  "type": "Feature",
  "properties": {
    "iso:country":"AU",
    "sg:address":"PO Box 4162",
    "sg:city":"Richmond East",
    "sg:classifiers":[
        {
            "category":"Education",
            "subcategory":"Music School",
            "type":"Public Place"
        }
    ],
    "sg:phone":"+61 3 9527 8644",
    "sg:postcode":"3121",
    "sg:province":"VIC",
    "sg:tags":[
        "choir",
        "bands",
        "orchestra"
    ],
    "wof:name":"Entertainment Store",
    "wof:placetype":"venue"
},
  "geometry": {"coordinates":[145.00813293499999,-37.8220596313],"type":"Point"}
}