{
  "type": "Feature",
  "properties": {
    "iso:country":"AU",
    "sg:address":"Level 1, 31 Ventnor Ave",
    "sg:city":"West Perth",
    "sg:classifiers":[
        {
            "category":"Professional",
            "subcategory":"Detective & Security Services",
            "type":"Services"
        }
    ],
    "sg:phone":"+61 1300 365 766",
    "sg:postcode":"6005",
    "sg:province":"WA",
    "sg:tags":[
        "identification",
        "system"
    ],
    "wof:name":"Imaje Coding Technology Pty Ltd",
    "wof:placetype":"venue"
},
  "geometry": {"coordinates":[115.838027954,-31.9493923187],"type":"Point"}
}