{
  "type": "Feature",
  "properties": {
    "addr:full":"89 Vincent St Cessnock NSW 2325",
    "addr:housenumber":"89",
    "addr:postcode":"2325",
    "addr:street":"Vincent St",
    "iso:country":"AU",
    "sg:address":"89 Vincent St",
    "sg:city":"Cessnock",
    "sg:classifiers":[
        {
            "category":"Personal",
            "subcategory":"Beauty Salon",
            "type":"Services"
        }
    ],
    "sg:phone":"+61 2 4991 4247",
    "sg:postcode":"2325",
    "sg:province":"NSW",
    "sg:tags":[
        "hairdresser"
    ],
    "wof:name":"Fuse Gallery Hair Skin Body",
    "wof:placetype":"venue"
},
  "geometry": {"coordinates":[151.35618591299999,-32.8346977234],"type":"Point"}
}