{
  "type": "Feature",
  "properties": {
    "iso:country":"AU",
    "sg:address":"PO Box 3023",
    "sg:city":"Rowville",
    "sg:classifiers":[
        {
            "category":"Food & Beverages",
            "subcategory":"Specialty",
            "type":"Retail Goods"
        }
    ],
    "sg:phone":"+61 3 9701 8891",
    "sg:postcode":"3178",
    "sg:province":"VIC",
    "sg:tags":[
        "ice",
        "supply"
    ],
    "wof:name":"Ice Occasions, Ice Sculptures",
    "wof:placetype":"venue"
},
  "geometry": {"coordinates":[145.24317932100001,-37.9258804321],"type":"Point"}
}