{
  "type": "Feature",
  "properties": {
    "addr:full":"Cnr Lytton Rd & Taylor St Bulimba QLD 4171",
    "addr:postcode":"4171",
    "addr:street":"Cnr Lytton Rd & Taylor St",
    "iso:country":"AU",
    "sg:address":"Cnr Lytton Rd & Taylor St",
    "sg:city":"Bulimba",
    "sg:classifiers":[
        {
            "category":"Shopping",
            "subcategory":"Stationery & Office Supplies",
            "type":"Retail Goods"
        }
    ],
    "sg:phone":"+61 7 3217 9177",
    "sg:postcode":"4171",
    "sg:province":"QLD",
    "sg:tags":[
        "equipment",
        "display",
        "exhibition"
    ],
    "wof:name":"Foremost Plastics Pty Ltd",
    "wof:placetype":"venue"
},
  "geometry": {"coordinates":[153.06297302199999,-27.4514217377],"type":"Point"}
}