{
  "type": "Feature",
  "properties": {
    "iso:country":"AU",
    "sg:address":"734 Pittwater Rd",
    "sg:city":"Brookvale",
    "sg:classifiers":[
        {
            "category":"Retail",
            "subcategory":"Veterinary Services",
            "type":"Services"
        }
    ],
    "sg:phone":"+61 2 9939 1321",
    "sg:postcode":"2100",
    "sg:province":"NSW",
    "sg:tags":[
        "surgeon"
    ],
    "wof:name":"Brookvale Veterinary Clinic",
    "wof:placetype":"venue"
},
  "geometry": {"coordinates":[151.27395629899999,-33.7610359192],"type":"Point"}
}