{
  "type": "Feature",
  "properties": {
    "addr:full":"6 Marrion St Coburg VIC 3058",
    "addr:housenumber":"6",
    "addr:postcode":"3058",
    "addr:street":"Marrion St",
    "iso:country":"AU",
    "sg:address":"6 Marrion St",
    "sg:city":"Coburg",
    "sg:classifiers":[
        {
            "category":"Building & Trades",
            "subcategory":"Construction",
            "type":"Services"
        }
    ],
    "sg:phone":"+61 3 9350 3525",
    "sg:postcode":"3058",
    "sg:province":"VIC",
    "sg:tags":[
        "contractor"
    ],
    "wof:name":"Michielin Brothers Construction",
    "wof:placetype":"venue"
},
  "geometry": {"coordinates":[144.95062255900001,-37.7308273315],"type":"Point"}
}