{
  "type": "Feature",
  "properties": {
    "iso:country":"AU",
    "sg:address":"27 Morgan St",
    "sg:city":"Cannington",
    "sg:classifiers":[
        {
            "category":"Retail",
            "subcategory":"Auto Repair",
            "type":"Services"
        }
    ],
    "sg:phone":"+61 8 9358 1500",
    "sg:postcode":"6107",
    "sg:province":"WA",
    "sg:tags":[
        "recapping",
        "repairing",
        "retreading",
        "tyre"
    ],
    "wof:name":"Allround Tyres",
    "wof:placetype":"venue"
},
  "geometry": {"coordinates":[115.948486328,-32.0211334229],"type":"Point"}
}