{
  "type": "Feature",
  "properties": {
    "iso:country":"AU",
    "sg:address":"Shp5/ 36 Musgrave Ave",
    "sg:city":"Chirn Park",
    "sg:classifiers":[
        {
            "category":"Manufacturing",
            "subcategory":"Jewelry",
            "type":"Manufacturing & Wholesale Goods"
        }
    ],
    "sg:phone":"+61 7 5527 1652",
    "sg:postcode":"4215",
    "sg:province":"QLD",
    "sg:tags":[
        "mfrg",
        "jeweller"
    ],
    "wof:name":"Chirn Park Jewellers",
    "wof:placetype":"venue"
},
  "geometry": {"coordinates":[153.40106201200001,-27.9561634064],"type":"Point"}
}