{
  "type": "Feature",
  "properties": {
    "addr:full":"4 Nicholson St Altona Meadows VIC 3028",
    "addr:housenumber":"4",
    "addr:postcode":"3028",
    "addr:street":"Nicholson St",
    "iso:country":"AU",
    "sg:address":"4 Nicholson St",
    "sg:city":"Altona Meadows",
    "sg:classifiers":[
        {
            "category":"Professional",
            "subcategory":"Computer Services",
            "type":"Services"
        }
    ],
    "sg:phone":"+61 412 186 410",
    "sg:postcode":"3028",
    "sg:province":"VIC",
    "sg:tags":[
        "repairs",
        "upgrade",
        "equipment"
    ],
    "wof:name":"Asrats",
    "wof:placetype":"venue"
},
  "geometry": {"coordinates":[144.77929700000001,-37.865906],"type":"Point"}
}