{
  "type": "Feature",
  "properties": {
    "addr:full":"79 Wilpena Ave Vale Park SA 5081",
    "addr:housenumber":"79",
    "addr:postcode":"5081",
    "addr:street":"Wilpena Ave Vale",
    "iso:country":"AU",
    "sg:address":"79 Wilpena Ave",
    "sg:city":"Vale Park",
    "sg:classifiers":[
        {
            "category":"Manufacturing",
            "subcategory":"Signs",
            "type":"Manufacturing & Wholesale Goods"
        }
    ],
    "sg:phone":"+61 8 8362 4359",
    "sg:postcode":"5081",
    "sg:province":"SA",
    "sg:tags":[
        "traffic",
        "safety"
    ],
    "wof:name":"Safetyman Pty Ltd",
    "wof:placetype":"venue"
},
  "geometry": {"coordinates":[138.62950134299999,-34.8850669861],"type":"Point"}
}