{
  "type": "Feature",
  "properties": {
    "addr:full":"Shp9 / 9 The Strand Dee Why NSW 2099",
    "addr:housenumber":"9",
    "addr:postcode":"2099",
    "addr:street":"The Strand",
    "iso:country":"AU",
    "sg:address":"Shp9",
    "sg:city":"/ 9 The Strand Dee Why",
    "sg:classifiers":[
        {
            "category":"Fast Food",
            "type":"Food & Drink"
        }
    ],
    "sg:phone":"+61 2 9984 1702",
    "sg:postcode":"2099",
    "sg:province":"NSW",
    "sg:tags":[
        "away",
        "take"
    ],
    "wof:name":"Slyce Pizza Cafe",
    "wof:placetype":"venue"
},
  "geometry": {"coordinates":[151.296142578,-33.7549781799],"type":"Point"}
}