{
  "type": "Feature",
  "properties": {
    "iso:country":"AU",
    "sg:address":"Creamy Rd",
    "sg:city":"Tyntynder South",
    "sg:classifiers":[
        {
            "category":"Farming",
            "subcategory":"Dairy Farm",
            "type":"Manufacturing & Wholesale Goods"
        }
    ],
    "sg:phone":"+61 3 5032 3577",
    "sg:postcode":"3586",
    "sg:province":"VIC",
    "wof:name":"Hastings Jones Pty Ltd",
    "wof:placetype":"venue"
},
  "geometry": {"coordinates":[143.517410278,-35.273979187],"type":"Point"}
}