{
  "type": "Feature",
  "properties": {
    "addr:full":"98 Military Rd Semaphore South SA 5019",
    "addr:housenumber":"98",
    "addr:postcode":"5019",
    "addr:street":"Military Rd",
    "iso:country":"AU",
    "sg:address":"98 Military Rd",
    "sg:city":"Semaphore South",
    "sg:classifiers":[
        {
            "category":"Health Services",
            "subcategory":"Nursing And Care Facility",
            "type":"Services"
        }
    ],
    "sg:phone":"+61 8 8449 8251",
    "sg:postcode":"5019",
    "sg:province":"SA",
    "sg:tags":[
        "home"
    ],
    "wof:name":"Kooluna Nursing Home",
    "wof:placetype":"venue"
},
  "geometry": {"coordinates":[138.481765747,-34.8449211121],"type":"Point"}
}