{
  "type": "Feature",
  "properties": {
    "addr:full":"143 Leura La Hamilton VIC 3300",
    "addr:housenumber":"143",
    "addr:postcode":"3300",
    "addr:street":"Leura La",
    "iso:country":"AU",
    "sg:address":"143 Leura La",
    "sg:city":"Hamilton",
    "sg:classifiers":[
        {
            "category":"Farming",
            "subcategory":"Farm & Veterinary Services",
            "type":"Manufacturing & Wholesale Goods"
        }
    ],
    "sg:phone":"+61 3 5571 1176",
    "sg:postcode":"3300",
    "sg:province":"VIC",
    "sg:tags":[
        "shearing",
        "contractor"
    ],
    "wof:name":"Action Shear Pty Ltd",
    "wof:placetype":"venue"
},
  "geometry": {"coordinates":[142.04737854000001,-37.7204551697],"type":"Point"}
}