{
  "type": "Feature",
  "properties": {
    "iso:country":"AU",
    "sg:address":"174 Bay St",
    "sg:city":"Brighton",
    "sg:classifiers":[
        {
            "category":"Personal",
            "subcategory":"Massage",
            "type":"Services"
        }
    ],
    "sg:phone":"+61 3 9596 6610",
    "sg:postcode":"3186",
    "sg:province":"VIC",
    "sg:tags":[
        "therapy"
    ],
    "wof:name":"Sally Creek",
    "wof:placetype":"venue"
},
  "geometry": {"coordinates":[144.998245239,-37.9050636292],"type":"Point"}
}