{
  "type": "Feature",
  "properties": {
    "addr:full":"51 Cavan Rd Cavan SA 5094",
    "addr:housenumber":"51",
    "addr:postcode":"5094",
    "addr:street":"Cavan Rd",
    "iso:country":"AU",
    "sg:address":"51 Cavan Rd",
    "sg:city":"Cavan",
    "sg:classifiers":[
        {
            "category":"Manufacturing",
            "subcategory":"Metals",
            "type":"Manufacturing & Wholesale Goods"
        }
    ],
    "sg:phone":"+61 8 8368 1160",
    "sg:postcode":"5094",
    "sg:province":"SA",
    "sg:tags":[
        "sheet",
        "worker"
    ],
    "wof:name":"Fielders Australia",
    "wof:placetype":"venue"
},
  "geometry": {"coordinates":[138.58888244600001,-34.8436851501],"type":"Point"}
}