{
  "type": "Feature",
  "properties": {
    "iso:country":"AU",
    "sg:address":"79- 85 Pacific Hwy",
    "sg:city":"Tweed Heads",
    "sg:classifiers":[
        {
            "category":"Fast Food",
            "type":"Food & Drink"
        }
    ],
    "sg:phone":"+61 7 5569 4255",
    "sg:postcode":"2485",
    "sg:province":"NSW",
    "sg:tags":[
        "away",
        "take"
    ],
    "wof:name":"Dominos Pizza",
    "wof:placetype":"venue"
},
  "geometry": {"coordinates":[153.54066467300001,-28.179693222],"type":"Point"}
}