{
  "type": "Feature",
  "properties": {
    "addr:full":"54 Bourke St Dubbo NSW 2830",
    "addr:housenumber":"54",
    "addr:postcode":"2830",
    "addr:street":"Bourke St",
    "iso:country":"AU",
    "sg:address":"54 Bourke St",
    "sg:city":"Dubbo",
    "sg:classifiers":[
        {
            "category":"Retail",
            "subcategory":"Car Wash",
            "type":"Services"
        }
    ],
    "sg:phone":"+61 2 6884 9959",
    "sg:postcode":"2830",
    "sg:province":"NSW",
    "sg:tags":[
        "truck",
        "cleaning"
    ],
    "wof:name":"Orana Car Care",
    "wof:placetype":"venue"
},
  "geometry": {"coordinates":[148.610595703,-32.2385025024],"type":"Point"}
}