{
  "type": "Feature",
  "properties": {
    "iso:country":"AU",
    "sg:address":"6 Easton Pl",
    "sg:city":"East Ballina",
    "sg:classifiers":[
        {
            "category":"Travel",
            "subcategory":"Hotels & Motels",
            "type":"Entertainment"
        }
    ],
    "sg:phone":"+61 2 6686 2426",
    "sg:postcode":"2478",
    "sg:province":"NSW",
    "wof:name":"Ballina's Leisure-Lee Holiday Apartments",
    "wof:placetype":"venue"
},
  "geometry": {"coordinates":[153.59291076700001,-28.800037384],"type":"Point"}
}