{
  "type": "Feature",
  "properties": {
    "iso:country":"AU",
    "sg:address":"760 Menangle Rd",
    "sg:city":"Douglas Park",
    "sg:classifiers":[
        {
            "category":"Utilities",
            "subcategory":"Electric",
            "type":"Services"
        }
    ],
    "sg:phone":"+61 2 4632 7411",
    "sg:postcode":"2569",
    "sg:province":"NSW",
    "sg:tags":[
        "electrical",
        "contractor"
    ],
    "wof:name":"Bush Electrics Pty Ltd",
    "wof:placetype":"venue"
},
  "geometry": {"coordinates":[150.70864868199999,-34.1716041565],"type":"Point"}
}