{
  "type": "Feature",
  "properties": {
    "iso:country":"AU",
    "sg:address":"1350 Pittwater Rd",
    "sg:city":"Narrabeen",
    "sg:classifiers":[
        {
            "category":"Real Estate",
            "subcategory":"Real Estate Agent",
            "type":"Services"
        }
    ],
    "sg:phone":"+61 2 9970 7921",
    "sg:postcode":"2101",
    "sg:province":"NSW",
    "wof:name":"Ray White Real Estate",
    "wof:placetype":"venue"
},
  "geometry": {"coordinates":[151.29718,-33.715351],"type":"Point"}
}