{
  "type": "Feature",
  "properties": {
    "iso:country":"AU",
    "sg:address":"Level 3, 63 Exibition St",
    "sg:city":"Melbourne",
    "sg:classifiers":[
        {
            "category":"Banks & Credit Unions",
            "subcategory":"Investment Brokerage",
            "type":"Services"
        }
    ],
    "sg:phone":"+61 3 9223 4902",
    "sg:postcode":"3000",
    "sg:province":"VIC",
    "sg:tags":[
        "debt",
        "collection"
    ],
    "wof:name":"Accounts Control Management Services Pty Ltd",
    "wof:placetype":"venue"
},
  "geometry": {"coordinates":[144.97154235799999,-37.8145370483],"type":"Point"}
}