{
  "type": "Feature",
  "properties": {
    "iso:country":"AU",
    "sg:address":"30 High St",
    "sg:city":"Yackandandah",
    "sg:classifiers":[
        {
            "category":"Travel",
            "subcategory":"Hotels & Motels",
            "type":"Entertainment"
        }
    ],
    "sg:phone":"+61 2 6027 1493",
    "sg:postcode":"3749",
    "sg:province":"VIC",
    "sg:tags":[
        "accommodation"
    ],
    "wof:name":"Yackandandah Star Hotel & Haig Room Restaurant",
    "wof:placetype":"venue"
},
  "geometry": {"coordinates":[146.83812,-36.313038],"type":"Point"}
}