{
  "type": "Feature",
  "properties": {
    "iso:country":"AU",
    "sg:address":"965- 967 Pacific Hwy",
    "sg:city":"Pymble",
    "sg:classifiers":[
        {
            "category":"Insurance",
            "subcategory":"Insurance Agent",
            "type":"Services"
        }
    ],
    "sg:phone":"+61 2 9488 8300",
    "sg:postcode":"2073",
    "sg:province":"NSW",
    "sg:tags":[
        "broker"
    ],
    "wof:name":"Watkins Taylor Stone",
    "wof:placetype":"venue"
},
  "geometry": {"coordinates":[151.14361572300001,-33.7455482483],"type":"Point"}
}