{
  "type": "Feature",
  "properties": {
    "iso:country":"AU",
    "sg:address":"433 Kent St",
    "sg:city":"Sydney",
    "sg:classifiers":[
        {
            "category":"Travel",
            "subcategory":"Hotels & Motels",
            "type":"Entertainment"
        }
    ],
    "sg:phone":"+61 1800 224 584",
    "sg:postcode":"2000",
    "sg:province":"NSW",
    "sg:tags":[
        "accommodation"
    ],
    "wof:name":"Pacific International Consolidated Pty Ltd",
    "wof:placetype":"venue"
},
  "geometry": {"coordinates":[151.204833984,-33.8717765808],"type":"Point"}
}