{
  "type": "Feature",
  "properties": {
    "addr:full":"50 Belgrave-Hallam Rd Belgrave VIC 3160",
    "addr:housenumber":"50",
    "addr:postcode":"3160",
    "addr:street":"Belgrave-Hallam Rd",
    "iso:country":"AU",
    "sg:address":"50 Belgrave-Hallam Rd",
    "sg:city":"Belgrave",
    "sg:classifiers":[
        {
            "category":"Landmark",
            "subcategory":"Scenic View",
            "type":"Public Place"
        }
    ],
    "sg:phone":"+61 3 9754 2810",
    "sg:postcode":"3160",
    "sg:province":"VIC",
    "sg:tags":[
        "staircase",
        "handrail"
    ],
    "wof:name":"Matco Handrails Pty Ltd",
    "wof:placetype":"venue"
},
  "geometry": {"coordinates":[145.353683472,-37.9174461365],"type":"Point"}
}