{
  "type": "Feature",
  "properties": {
    "iso:country":"AU",
    "sg:address":"251 Mona Drv",
    "sg:city":"Jimboomba",
    "sg:classifiers":[
        {
            "category":"Home & Garden",
            "subcategory":"Building Materials",
            "type":"Retail Goods"
        }
    ],
    "sg:phone":"+61 7 5547 8101",
    "sg:postcode":"4280",
    "sg:province":"QLD",
    "sg:tags":[
        "balustrading"
    ],
    "wof:name":"CJ's Lattice & Building Services",
    "wof:placetype":"venue"
},
  "geometry": {"coordinates":[153.07316599999999,-27.848648],"type":"Point"}
}