{
  "type": "Feature",
  "properties": {
    "iso:country":"AU",
    "sg:address":"8 Holberry St",
    "sg:city":"Broadmeadows",
    "sg:classifiers":[
        {
            "category":"Building & Trades",
            "subcategory":"Construction",
            "type":"Services"
        }
    ],
    "sg:phone":"+61 3 9309 5187",
    "sg:postcode":"3047",
    "sg:province":"VIC",
    "sg:tags":[
        "management"
    ],
    "wof:name":"Barbosa Bros & Partners",
    "wof:placetype":"venue"
},
  "geometry": {"coordinates":[144.930252075,-37.6912612915],"type":"Point"}
}