{
  "type": "Feature",
  "properties": {
    "iso:country":"AU",
    "sg:address":"9 Redfern Rd",
    "sg:city":"Minto",
    "sg:classifiers":[
        {
            "category":"Sports & Exercise",
            "subcategory":"Sports Center",
            "type":"Entertainment"
        }
    ],
    "sg:phone":"+61 2 9820 1377",
    "sg:postcode":"2566",
    "sg:province":"NSW",
    "sg:tags":[
        "ground"
    ],
    "wof:name":"Macarthur Basketball Association",
    "wof:placetype":"venue"
},
  "geometry": {"coordinates":[150.84472656200001,-34.0282745361],"type":"Point"}
}