{
  "type": "Feature",
  "properties": {
    "addr:full":"Parkyn Pde Mooloolaba QLD 4557",
    "addr:postcode":"4557",
    "addr:street":"Parkyn",
    "iso:country":"AU",
    "sg:address":"Parkyn Pde",
    "sg:city":"Mooloolaba",
    "sg:classifiers":[
        {
            "category":"Wholesale",
            "subcategory":"Seafood",
            "type":"Manufacturing & Wholesale Goods"
        }
    ],
    "sg:phone":"+61 7 5444 1351",
    "sg:postcode":"4557",
    "sg:province":"QLD",
    "sg:tags":[
        "fish"
    ],
    "wof:name":"Browns Slipway (QLD) Pty Ltd",
    "wof:placetype":"venue"
},
  "geometry": {"coordinates":[153.122924805,-26.6829833984],"type":"Point"}
}