{
  "type": "Feature",
  "properties": {
    "addr:full":"Wetherall St Manjimup WA 6258",
    "addr:postcode":"6258",
    "addr:street":"St",
    "iso:country":"AU",
    "sg:address":"Wetherall St",
    "sg:city":"Manjimup",
    "sg:classifiers":[
        {
            "category":"Parking",
            "subcategory":"Lot",
            "type":"Transportation"
        }
    ],
    "sg:phone":"+61 8 9771 2666",
    "sg:postcode":"6258",
    "sg:province":"WA",
    "sg:tags":[
        "vegetable",
        "packing",
        "fruit",
        "pack"
    ],
    "wof:name":"Manjimup Vegetable Export Growers",
    "wof:placetype":"venue"
},
  "geometry": {"coordinates":[116.143226623,-34.2521820068],"type":"Point"}
}