{
  "type": "Feature",
  "properties": {
    "addr:full":"4 Lindsay Ave Nunawading VIC 3131",
    "addr:housenumber":"4",
    "addr:postcode":"3131",
    "addr:street":"Lindsay Ave",
    "iso:country":"AU",
    "sg:address":"4 Lindsay Ave",
    "sg:city":"Nunawading",
    "sg:classifiers":[
        {
            "category":"Manufacturing",
            "subcategory":"Paper Products",
            "type":"Manufacturing & Wholesale Goods"
        }
    ],
    "sg:phone":"+61 3 9894 1311",
    "sg:postcode":"3131",
    "sg:province":"VIC",
    "sg:tags":[
        "disposable"
    ],
    "wof:name":"Pacific Paper Supplies",
    "wof:placetype":"venue"
},
  "geometry": {"coordinates":[145.177612305,-37.8106269836],"type":"Point"}
}