{
  "type": "Feature",
  "properties": {
    "iso:country":"AU",
    "sg:address":"Shop 5, 350 Taylors Road",
    "sg:city":"Delahey Delahey",
    "sg:classifiers":[
        {
            "category":"Real Estate",
            "subcategory":"Real Estate Agent",
            "type":"Services"
        }
    ],
    "sg:phone":"+61 3 9364 6900",
    "sg:postcode":"3037",
    "sg:province":"VIC",
    "wof:name":"Taylors Real Estate Agents Pty Ltd",
    "wof:placetype":"venue"
},
  "geometry": {"coordinates":[144.770325,-37.726089],"type":"Point"}
}