{
  "type": "Feature",
  "properties": {
    "addr:full":"8 Basilio Crt Ayr QLD 4807",
    "addr:housenumber":"8",
    "addr:postcode":"4807",
    "addr:street":"Basilio Crt",
    "iso:country":"AU",
    "sg:address":"8 Basilio Crt",
    "sg:city":"Ayr",
    "sg:classifiers":[
        {
            "category":"Building & Trades",
            "subcategory":"Construction",
            "type":"Services"
        }
    ],
    "sg:phone":"+61 7 4783 4975",
    "sg:postcode":"4807",
    "sg:province":"QLD",
    "sg:tags":[
        "contractor"
    ],
    "wof:name":"Ayr Building Company",
    "wof:placetype":"venue"
},
  "geometry": {"coordinates":[147.420974731,-19.5444984436],"type":"Point"}
}