{
  "type": "Feature",
  "properties": {
    "addr:full":"158 Craig Rd Devon Meadows VIC 3977",
    "addr:housenumber":"158",
    "addr:postcode":"3977",
    "addr:street":"Craig Rd",
    "iso:country":"AU",
    "sg:address":"158 Craig Rd",
    "sg:city":"Devon Meadows",
    "sg:classifiers":[
        {
            "category":"Building & Trades",
            "subcategory":"Construction",
            "type":"Services"
        }
    ],
    "sg:phone":"+61 3 5998 2735",
    "sg:postcode":"3977",
    "sg:province":"VIC",
    "sg:tags":[
        "plasterboard",
        "plasterer",
        "fixer"
    ],
    "wof:name":"Cullinane C J & G A",
    "wof:placetype":"venue"
},
  "geometry": {"coordinates":[145.28744506800001,-38.1737480164],"type":"Point"}
}