{
  "type": "Feature",
  "properties": {
    "addr:full":"Lvl 4/ 300 Adelaide St Brisbane QLD 4000",
    "addr:housenumber":"/ 300",
    "addr:postcode":"4000",
    "addr:street":"Adelaide St",
    "iso:country":"AU",
    "sg:address":"Lvl 4/ 300 Adelaide St",
    "sg:city":"Brisbane",
    "sg:classifiers":[
        {
            "category":"Professional",
            "subcategory":"Computer Services",
            "type":"Services"
        }
    ],
    "sg:phone":"+61 7 3246 0000",
    "sg:postcode":"4000",
    "sg:province":"QLD",
    "sg:tags":[
        "tele-communications",
        "consultant"
    ],
    "wof:name":"Communications Design & Management Pty Limited",
    "wof:placetype":"venue"
},
  "geometry": {"coordinates":[153.029098511,-27.4650878906],"type":"Point"}
}