{
  "type": "Feature",
  "properties": {
    "addr:full":"4 Kaycee Pl Yatala QLD 4207",
    "addr:housenumber":"4",
    "addr:postcode":"4207",
    "addr:street":"Kaycee Pl",
    "iso:country":"AU",
    "sg:address":"4 Kaycee Pl",
    "sg:city":"Yatala",
    "sg:classifiers":[
        {
            "category":"Autos & Motor Vehicles",
            "subcategory":"Auto Supplies",
            "type":"Retail Goods"
        }
    ],
    "sg:phone":"+61 7 3807 1100",
    "sg:postcode":"4207",
    "sg:province":"QLD",
    "sg:tags":[
        "equipment",
        "part",
        "truck"
    ],
    "wof:name":"Yatala Truck Parts",
    "wof:placetype":"venue"
},
  "geometry": {"coordinates":[153.22425842300001,-27.7338752747],"type":"Point"}
}