{
  "type": "Feature",
  "properties": {
    "addr:full":"14 Melville Ave Strathfield NSW 2135",
    "addr:housenumber":"14",
    "addr:postcode":"2135",
    "addr:street":"Melville Ave",
    "iso:country":"AU",
    "sg:address":"14 Melville Ave",
    "sg:city":"Strathfield",
    "sg:classifiers":[
        {
            "category":"Professional",
            "subcategory":"Employment Agencies",
            "type":"Services"
        }
    ],
    "sg:phone":"+61 412 625 248",
    "sg:postcode":"2135",
    "sg:province":"NSW",
    "wof:name":"Clarity Corporation",
    "wof:placetype":"venue"
},
  "geometry": {"coordinates":[151.07026672399999,-33.8777923584],"type":"Point"}
}