{
  "type": "Feature",
  "properties": {
    "addr:full":"Unit 3, 1 Blaydon St Kings Meadows TAS 7249",
    "addr:housenumber":"1",
    "addr:postcode":"7249",
    "addr:street":"Blaydon St",
    "iso:country":"AU",
    "sg:address":"Unit 3, 1 Blaydon St",
    "sg:city":"Kings Meadows",
    "sg:classifiers":[
        {
            "category":"Education",
            "subcategory":"Special Training",
            "type":"Public Place"
        }
    ],
    "sg:phone":"+61 1300 739 320",
    "sg:postcode":"7249",
    "sg:province":"TAS",
    "sg:tags":[
        "development"
    ],
    "wof:name":"State Enterprise Training",
    "wof:placetype":"venue"
},
  "geometry": {"coordinates":[147.16026306099999,-41.468460083],"type":"Point"}
}