{
  "type": "Feature",
  "properties": {
    "addr:full":"PO Box 373 Erindale Centre ACT 2903",
    "addr:postcode":"2903",
    "iso:country":"AU",
    "sg:address":"PO Box 373",
    "sg:city":"Erindale Centre",
    "sg:classifiers":[
        {
            "category":"Home & Garden",
            "subcategory":"Building Materials",
            "type":"Retail Goods"
        }
    ],
    "sg:phone":"+61 404 289 534",
    "sg:postcode":"2903",
    "sg:province":"ACT",
    "sg:tags":[
        "concrete",
        "gutter",
        "kerb"
    ],
    "wof:name":"Kurvy Kurb",
    "wof:placetype":"venue"
},
  "geometry": {"coordinates":[149.097213745,-35.403011322],"type":"Point"}
}