{
  "type": "Feature",
  "properties": {
    "addr:full":"Shop 2 17 Hanson St Corryong NSW 3707",
    "addr:housenumber":"shop;17",
    "addr:postcode":"3707",
    "addr:street":"Hanson St",
    "iso:country":"AU",
    "sg:address":"Shop 2 17 Hanson St",
    "sg:city":"Corryong",
    "sg:classifiers":[
        {
            "category":"Shopping",
            "subcategory":"Clothing, Apparel, & Fashions",
            "type":"Retail Goods"
        }
    ],
    "sg:phone":"+61 2 6076 1343",
    "sg:postcode":"3707",
    "sg:province":"NSW",
    "sg:tags":[
        "lady",
        "wear"
    ],
    "wof:name":"Rubys Clothing",
    "wof:placetype":"venue"
},
  "geometry": {"coordinates":[147.90594482399999,-36.1953239441],"type":"Point"}
}