{
  "type": "Feature",
  "properties": {
    "iso:country":"AU",
    "sg:address":"1 Rathdown St",
    "sg:city":"Carlton",
    "sg:classifiers":[
        {
            "category":"Building & Trades",
            "subcategory":"Construction",
            "type":"Services"
        }
    ],
    "sg:phone":"+61 3 9635 5112",
    "sg:postcode":"3053",
    "sg:province":"VIC",
    "sg:tags":[
        "sun",
        "product",
        "protection"
    ],
    "wof:name":"Cancer Council Retail Services",
    "wof:placetype":"venue"
},
  "geometry": {"coordinates":[144.96864318900001,-37.8072471619],"type":"Point"}
}