{
  "type": "Feature",
  "properties": {
    "iso:country":"AU",
    "sg:address":"Cnr Milton & Heinrich Sts",
    "sg:city":"Mackay",
    "sg:classifiers":[
        {
            "category":"Social Services",
            "subcategory":"Job Training",
            "type":"Services"
        }
    ],
    "sg:phone":"+61 7 4952 2799",
    "sg:postcode":"4740",
    "sg:province":"QLD",
    "sg:tags":[
        "hire",
        "computer",
        "leasing"
    ],
    "wof:name":"Kennedy Amplifier Hire Service",
    "wof:placetype":"venue"
},
  "geometry": {"coordinates":[149.17506399999999,-21.161919],"type":"Point"}
}