{
  "type": "Feature",
  "properties": {
    "iso:country":"AU",
    "sg:address":"27 Adelaide Rd",
    "sg:city":"Gawler",
    "sg:classifiers":[
        {
            "category":"Health Services",
            "subcategory":"Doctor",
            "type":"Services"
        }
    ],
    "sg:phone":"+61 8 8522 5555",
    "sg:postcode":"5118",
    "sg:province":"SA",
    "sg:tags":[
        "medical",
        "practitioner"
    ],
    "wof:name":"Graham Frank Dr",
    "wof:placetype":"venue"
},
  "geometry": {"coordinates":[138.744858,-34.606064],"type":"Point"}
}