{
  "type": "Feature",
  "properties": {
    "addr:full":"22 Myers Ave Innisfail QLD 4860",
    "addr:housenumber":"22",
    "addr:postcode":"4860",
    "addr:street":"Myers Ave",
    "iso:country":"AU",
    "sg:address":"22 Myers Ave",
    "sg:city":"Innisfail",
    "sg:classifiers":[
        {
            "category":"Real Estate",
            "subcategory":"Real Estate Agent",
            "type":"Services"
        }
    ],
    "sg:phone":"+61 7 4064 2344",
    "sg:postcode":"4860",
    "sg:province":"QLD",
    "sg:tags":[
        "steel",
        "foundry",
        "iron"
    ],
    "wof:name":"Northern Iron & Brass Foundary Pty Ltd",
    "wof:placetype":"venue"
},
  "geometry": {"coordinates":[146.01133727999999,-17.575553894],"type":"Point"}
}