{
  "type": "Feature",
  "properties": {
    "addr:full":"Shop 9/ 36 George St Moe VIC 3825",
    "addr:housenumber":"shop 9 / 36",
    "addr:postcode":"3825",
    "addr:street":"George St",
    "iso:country":"AU",
    "sg:address":"Shop 9/ 36 George St",
    "sg:city":"Moe",
    "sg:classifiers":[
        {
            "category":"Shopping",
            "subcategory":"Antiques",
            "type":"Retail Goods"
        }
    ],
    "sg:phone":"+61 402 699 766",
    "sg:postcode":"3825",
    "sg:province":"VIC",
    "wof:name":"Old World Charm",
    "wof:placetype":"venue"
},
  "geometry": {"coordinates":[146.26190199999999,-38.176151],"type":"Point"}
}