{
  "type": "Feature",
  "properties": {
    "addr:full":"11- 15 Douro St Geelong North VIC 3215",
    "addr:housenumber":"15",
    "addr:postcode":"3215",
    "addr:street":"Douro St",
    "iso:country":"AU",
    "sg:address":"11- 15 Douro St",
    "sg:city":"Geelong North",
    "sg:classifiers":[
        {
            "category":"Taxi",
            "type":"Transportation"
        }
    ],
    "sg:phone":"+61 13 22 27",
    "sg:postcode":"3215",
    "sg:province":"VIC",
    "sg:tags":[
        "cab"
    ],
    "wof:name":"Torquay Taxi Service",
    "wof:placetype":"venue"
},
  "geometry": {"coordinates":[144.34776306099999,-38.1212882996],"type":"Point"}
}