{
  "type": "Feature",
  "properties": {
    "addr:full":"245 Brisbane St Ipswich QLD 4305",
    "addr:housenumber":"245",
    "addr:postcode":"4305",
    "addr:street":"Brisbane St",
    "iso:country":"AU",
    "sg:address":"245 Brisbane St",
    "sg:city":"Ipswich",
    "sg:classifiers":[
        {
            "category":"Professional",
            "subcategory":"Accounting & Tax Preparation",
            "type":"Services"
        }
    ],
    "sg:phone":"+61 7 3812 0227",
    "sg:postcode":"4305",
    "sg:province":"QLD",
    "sg:tags":[
        "consultant",
        "taxation"
    ],
    "wof:name":"Fastax (Australia) Pty Ltd",
    "wof:placetype":"venue"
},
  "geometry": {"coordinates":[152.75471496599999,-27.614528656],"type":"Point"}
}