{
  "type": "Feature",
  "properties": {
    "iso:country":"AU",
    "sg:address":"2 Koolinda Ave",
    "sg:city":"Point Clare",
    "sg:classifiers":[
        {
            "category":"Banks & Credit Unions",
            "subcategory":"Bank",
            "type":"Services"
        }
    ],
    "sg:phone":"+61 2 4322 9288",
    "sg:postcode":"2250",
    "sg:province":"NSW",
    "sg:tags":[
        "broker",
        "mortgage"
    ],
    "wof:name":"Clarity Finance Pty Ltd",
    "wof:placetype":"venue"
},
  "geometry": {"coordinates":[151.32220459000001,-33.4374809265],"type":"Point"}
}