{
  "type": "Feature",
  "properties": {
    "addr:full":"31 Second Ave Maroochydore QLD 4558",
    "addr:housenumber":"31",
    "addr:postcode":"4558",
    "addr:street":"Second Ave",
    "iso:country":"AU",
    "sg:address":"31 Second Ave",
    "sg:city":"Maroochydore",
    "sg:classifiers":[
        {
            "category":"Health Services",
            "subcategory":"Doctor",
            "type":"Services"
        }
    ],
    "sg:phone":"+61 7 5492 5188",
    "sg:postcode":"4558",
    "sg:province":"QLD",
    "sg:tags":[
        "medical",
        "practitioner"
    ],
    "wof:name":"Herd, C L J",
    "wof:placetype":"venue"
},
  "geometry": {"coordinates":[153.09536743199999,-26.6574878693],"type":"Point"}
}