{
  "type": "Feature",
  "properties": {
    "addr:full":"1071 Old Princes Hwy Engadine NSW 2233",
    "addr:housenumber":"1071",
    "addr:postcode":"2233",
    "addr:street":"Old Princes Hwy",
    "iso:country":"AU",
    "sg:address":"1071 Old Princes Hwy",
    "sg:city":"Engadine",
    "sg:classifiers":[
        {
            "category":"Real Estate",
            "subcategory":"Real Estate Agent",
            "type":"Services"
        }
    ],
    "sg:phone":"+61 2 9520 4477",
    "sg:postcode":"2233",
    "sg:province":"NSW",
    "wof:name":"L J Hooker",
    "wof:placetype":"venue"
},
  "geometry": {"coordinates":[151.01263427699999,-34.065536499],"type":"Point"}
}