{
  "type": "Feature",
  "properties": {
    "addr:full":"Buchanan St Murwillumbah NSW 2484",
    "addr:postcode":"2484",
    "addr:street":"Buchanan St",
    "iso:country":"AU",
    "sg:address":"Buchanan St",
    "sg:city":"Murwillumbah",
    "sg:classifiers":[
        {
            "category":"Professional",
            "subcategory":"Engineering",
            "type":"Services"
        }
    ],
    "sg:phone":"+61 2 6672 2327",
    "sg:postcode":"2484",
    "sg:province":"NSW",
    "sg:tags":[
        "engineer"
    ],
    "wof:name":"Hayes Steel",
    "wof:placetype":"venue"
},
  "geometry": {"coordinates":[153.40852355999999,-28.3339633942],"type":"Point"}
}