{
  "type": "Feature",
  "properties": {
    "iso:country":"AU",
    "sg:address":"848 North Rd",
    "sg:city":"Bentleigh East",
    "sg:classifiers":[
        {
            "category":"Autos & Motor Vehicles",
            "subcategory":"Automobile Sales",
            "type":"Retail Goods"
        }
    ],
    "sg:phone":"+61 3 9570 5800",
    "sg:postcode":"3165",
    "sg:province":"VIC",
    "sg:tags":[
        "car",
        "used"
    ],
    "wof:name":"Collits Motor Cars Pty Ltd",
    "wof:placetype":"venue"
},
  "geometry": {"coordinates":[145.06028747600001,-37.9066734314],"type":"Point"}
}