{
  "type": "Feature",
  "properties": {
    "iso:country":"AU",
    "sg:address":"Gallaghers La",
    "sg:city":"Maldon",
    "sg:classifiers":[
        {
            "category":"Farming",
            "subcategory":"Vineyard",
            "type":"Manufacturing & Wholesale Goods"
        }
    ],
    "sg:phone":"+61 3 5435 7427",
    "sg:postcode":"3463",
    "sg:province":"VIC",
    "sg:tags":[
        "winery"
    ],
    "wof:name":"Grange Hill Vineyard",
    "wof:placetype":"venue"
},
  "geometry": {"coordinates":[143.977249145,-36.8858261108],"type":"Point"}
}