{
  "type": "Feature",
  "properties": {
    "addr:full":"McKebery St Coleraine VIC 3315",
    "addr:postcode":"3315",
    "addr:street":"St",
    "iso:country":"AU",
    "sg:address":"McKebery St",
    "sg:city":"Coleraine",
    "sg:classifiers":[
        {
            "category":"Health Services",
            "subcategory":"Dentist",
            "type":"Services"
        }
    ],
    "sg:phone":"+61 3 5553 2024",
    "sg:postcode":"3315",
    "sg:province":"VIC",
    "wof:name":"Halloran T N",
    "wof:placetype":"venue"
},
  "geometry": {"coordinates":[141.691482544,-37.6041564941],"type":"Point"}
}