{
  "type": "Feature",
  "properties": {
    "iso:country":"AU",
    "sg:address":"176 McIntyre Rd",
    "sg:city":"Sunshine North",
    "sg:classifiers":[
        {
            "category":"Home & Garden",
            "subcategory":"Building Materials",
            "type":"Retail Goods"
        }
    ],
    "sg:phone":"+61 3 9311 0380",
    "sg:postcode":"3020",
    "sg:province":"VIC",
    "sg:tags":[
        "balustrading"
    ],
    "wof:name":"McIntyre Steel Industries",
    "wof:placetype":"venue"
},
  "geometry": {"coordinates":[144.83230599999999,-37.758392],"type":"Point"}
}