{
  "type": "Feature",
  "properties": {
    "addr:full":"69 Saints Rd Salisbury Plain SA 5109",
    "addr:housenumber":"69",
    "addr:postcode":"5109",
    "addr:street":"Saints Rd",
    "iso:country":"AU",
    "sg:address":"69 Saints Rd",
    "sg:city":"Salisbury Plain",
    "sg:classifiers":[
        {
            "category":"Professional",
            "subcategory":"Detective & Security Services",
            "type":"Services"
        }
    ],
    "sg:phone":"+61 1300 780 773",
    "sg:postcode":"5109",
    "sg:province":"SA",
    "sg:tags":[
        "equipment",
        "window",
        "doors"
    ],
    "wof:name":"All Trend Security Doors",
    "wof:placetype":"venue"
},
  "geometry": {"coordinates":[138.665817261,-34.764175415],"type":"Point"}
}