{
  "type": "Feature",
  "properties": {
    "addr:full":"638 Barkly St Footscray West VIC 3012",
    "addr:housenumber":"638",
    "addr:postcode":"3012",
    "addr:street":"Barkly St",
    "iso:country":"AU",
    "sg:address":"638 Barkly St",
    "sg:city":"Footscray West",
    "sg:classifiers":[
        {
            "category":"Food & Beverages",
            "subcategory":"Groceries & Convenience Stores",
            "type":"Retail Goods"
        }
    ],
    "sg:phone":"+61 3 9689 7375",
    "sg:postcode":"3012",
    "sg:province":"VIC",
    "wof:name":"Vinh Nam Grocery",
    "wof:placetype":"venue"
},
  "geometry": {"coordinates":[144.87266540499999,-37.7967147827],"type":"Point"}
}