{
  "type": "Feature",
  "properties": {
    "addr:full":"12 Watsonia Rd Gooseberry Hill WA 6076",
    "addr:housenumber":"12",
    "addr:postcode":"6076",
    "addr:street":"Watsonia Rd",
    "iso:country":"AU",
    "sg:address":"12 Watsonia Rd",
    "sg:city":"Gooseberry Hill",
    "sg:classifiers":[
        {
            "category":"Building & Trades",
            "subcategory":"Landscaping Services",
            "type":"Services"
        }
    ],
    "sg:phone":"+61 8 9454 6076",
    "sg:postcode":"6076",
    "sg:province":"WA",
    "sg:tags":[
        "gardener"
    ],
    "wof:name":"Mulcha Man",
    "wof:placetype":"venue"
},
  "geometry": {"coordinates":[116.034187317,-31.9566383362],"type":"Point"}
}