{
  "type": "Feature",
  "properties": {
    "addr:full":"15 Benari Crt Grovedale VIC 3216",
    "addr:housenumber":"15",
    "addr:postcode":"3216",
    "addr:street":"Benari Crt",
    "iso:country":"AU",
    "sg:address":"15 Benari Crt",
    "sg:city":"Grovedale",
    "sg:classifiers":[
        {
            "category":"Retail",
            "subcategory":"Driving School",
            "type":"Services"
        }
    ],
    "sg:phone":"+61 3 5241 2210",
    "sg:postcode":"3216",
    "sg:province":"VIC",
    "wof:name":"Nelson Driver Tuition",
    "wof:placetype":"venue"
},
  "geometry": {"coordinates":[144.3253479,-38.2023048401],"type":"Point"}
}