{
  "type": "Feature",
  "properties": {
    "addr:full":"Gibb St Harvey WA 6220",
    "addr:postcode":"6220",
    "addr:street":"Gibb St",
    "iso:country":"AU",
    "sg:address":"Gibb St",
    "sg:city":"Harvey",
    "sg:classifiers":[
        {
            "category":"Education",
            "subcategory":"Kindergarten",
            "type":"Public Place"
        }
    ],
    "sg:phone":"+61 8 9729 1212",
    "sg:postcode":"6220",
    "sg:province":"WA",
    "sg:tags":[
        "pre-schools"
    ],
    "wof:name":"Harvey Primary School",
    "wof:placetype":"venue"
},
  "geometry": {"coordinates":[115.896317,-33.078842],"type":"Point"}
}