{
  "type": "Feature",
  "properties": {
    "iso:country":"AU",
    "sg:address":"433 On Logan Rd",
    "sg:city":"Stones Corner",
    "sg:classifiers":[
        {
            "category":"Building & Trades",
            "subcategory":"Equipment Rental",
            "type":"Services"
        }
    ],
    "sg:phone":"+61 7 3397 9522",
    "sg:postcode":"4120",
    "sg:province":"QLD",
    "sg:tags":[
        "supply",
        "catering"
    ],
    "wof:name":"Oppenheimer Pty Ltd",
    "wof:placetype":"venue"
},
  "geometry": {"coordinates":[153.046386719,-27.5012874603],"type":"Point"}
}