{
  "type": "Feature",
  "properties": {
    "addr:full":"12 Rowan St Bendigo VIC 3539",
    "addr:housenumber":"12",
    "addr:postcode":"3539",
    "addr:street":"Rowan St",
    "iso:country":"AU",
    "sg:address":"12 Rowan St",
    "sg:city":"Bendigo",
    "sg:classifiers":[
        {
            "category":"Health Services",
            "subcategory":"Doctor",
            "type":"Services"
        }
    ],
    "sg:phone":"+61 3 9898 0122",
    "sg:postcode":"3539",
    "sg:province":"VIC",
    "sg:tags":[
        "medical",
        "practitioner"
    ],
    "wof:name":"Grigg Prof. Michael J",
    "wof:placetype":"venue"
},
  "geometry": {"coordinates":[144.274857,-36.757156],"type":"Point"}
}