{
  "type": "Feature",
  "properties": {
    "addr:full":"107 Junction Rd Moorebank NSW 2170",
    "addr:housenumber":"107",
    "addr:postcode":"2170",
    "addr:street":"Junction Rd",
    "iso:country":"AU",
    "sg:address":"107 Junction Rd",
    "sg:city":"Moorebank",
    "sg:classifiers":[
        {
            "category":"Social Services",
            "subcategory":"Adult Care",
            "type":"Services"
        }
    ],
    "sg:phone":"+61 2 9602 5522",
    "sg:postcode":"2170",
    "sg:province":"NSW",
    "sg:tags":[
        "towing"
    ],
    "wof:name":"J & D Smash Repairs",
    "wof:placetype":"venue"
},
  "geometry": {"coordinates":[150.941009522,-33.9385299683],"type":"Point"}
}