{
  "type": "Feature",
  "properties": {
    "addr:full":"86-90 Abbott St Oonoonba QLD 4811",
    "addr:housenumber":"86-90",
    "addr:postcode":"4811",
    "addr:street":"Abbott St",
    "iso:country":"AU",
    "sg:address":"86-90 Abbott St",
    "sg:city":"Oonoonba",
    "sg:classifiers":[
        {
            "category":"Travel",
            "subcategory":"Hotels & Motels",
            "type":"Entertainment"
        }
    ],
    "sg:phone":"+61 7 4778 2533",
    "sg:postcode":"4811",
    "sg:province":"QLD",
    "wof:name":"Fairfield Waters Motel",
    "wof:placetype":"venue"
},
  "geometry": {"coordinates":[146.81930500000001,-19.302488],"type":"Point"}
}