{
  "type": "Feature",
  "properties": {
    "iso:country":"AU",
    "sg:address":"1265 Nepean Hwy",
    "sg:city":"Cheltenham",
    "sg:classifiers":[
        {
            "category":"Professional",
            "subcategory":"Engineering",
            "type":"Services"
        }
    ],
    "sg:phone":"+61 3 9581 6600",
    "sg:postcode":"3192",
    "sg:province":"VIC",
    "sg:tags":[
        "consulting",
        "engineer"
    ],
    "wof:name":"Asia Pacific Consultants Pty Ltd",
    "wof:placetype":"venue"
},
  "geometry": {"coordinates":[145.05566406200001,-37.9620666504],"type":"Point"}
}