{
  "type": "Feature",
  "properties": {
    "iso:country":"AU",
    "sg:address":"80 Marion St",
    "sg:city":"Unley",
    "sg:classifiers":[
        {
            "category":"Wholesale",
            "subcategory":"Machinery & Supplies",
            "type":"Manufacturing & Wholesale Goods"
        }
    ],
    "sg:phone":"+61 8 8271 0088",
    "sg:postcode":"5061",
    "sg:province":"SA",
    "sg:tags":[
        "equipment",
        "laboratory"
    ],
    "wof:name":"Medos Co Pty Ltd",
    "wof:placetype":"venue"
},
  "geometry": {"coordinates":[138.607666016,-34.9482116699],"type":"Point"}
}