{
  "type": "Feature",
  "properties": {
    "addr:full":"174 Portrush Rd Trinity Gardens SA 5068",
    "addr:housenumber":"174",
    "addr:postcode":"5068",
    "addr:street":"Portrush Rd",
    "iso:country":"AU",
    "sg:address":"174 Portrush Rd",
    "sg:city":"Trinity Gardens",
    "sg:classifiers":[
        {
            "category":"Banks & Credit Unions",
            "subcategory":"Bureau De Change",
            "type":"Services"
        }
    ],
    "sg:phone":"+61 8 8331 0466",
    "sg:postcode":"5068",
    "sg:province":"SA",
    "sg:tags":[
        "gas",
        "natural",
        "lp",
        "equipment"
    ],
    "wof:name":"Autogas Cylinder Retest Station",
    "wof:placetype":"venue"
},
  "geometry": {"coordinates":[138.640457153,-34.9103851318],"type":"Point"}
}