{
  "type": "Feature",
  "properties": {
    "iso:country":"AU",
    "sg:address":"Formby Rd",
    "sg:city":"Devonport",
    "sg:classifiers":[
        {
            "category":"Organizations",
            "subcategory":"Membership Organization",
            "type":"Services"
        }
    ],
    "sg:phone":"+61 3 6424 1507",
    "sg:postcode":"7310",
    "sg:province":"TAS",
    "sg:tags":[
        "railway"
    ],
    "wof:name":"Tasrail",
    "wof:placetype":"venue"
},
  "geometry": {"coordinates":[146.36207580600001,-41.1776046753],"type":"Point"}
}