{
  "type": "Feature",
  "properties": {
    "iso:country":"AU",
    "sg:address":"Unit 9/ 19 John St",
    "sg:city":"Bentley",
    "sg:classifiers":[
        {
            "category":"Home & Garden",
            "subcategory":"Hardware",
            "type":"Retail Goods"
        }
    ],
    "sg:phone":"+61 8 9458 9290",
    "sg:postcode":"6102",
    "sg:province":"WA",
    "sg:tags":[
        "trolley",
        "truck",
        "hand"
    ],
    "wof:name":"Statewide Trolley Repairs Pty Ltd",
    "wof:placetype":"venue"
},
  "geometry": {"coordinates":[115.92030334499999,-32.0004348755],"type":"Point"}
}