{
  "type": "Feature",
  "properties": {
    "addr:full":"454 Nicholson St Fitzroy North VIC 3068",
    "addr:housenumber":"454",
    "addr:postcode":"3068",
    "addr:street":"Nicholson St",
    "iso:country":"AU",
    "sg:address":"454 Nicholson St",
    "sg:city":"Fitzroy North",
    "sg:classifiers":[
        {
            "category":"Restaurant",
            "type":"Food & Drink"
        }
    ],
    "sg:phone":"+61 3 9482 7447",
    "sg:postcode":"3068",
    "sg:province":"VIC",
    "wof:name":"El Gaucho",
    "wof:placetype":"venue"
},
  "geometry": {"coordinates":[144.976730347,-37.7890625],"type":"Point"}
}