{
  "type": "Feature",
  "properties": {
    "addr:full":"13 Titan Drv Carrum Downs VIC 3201",
    "addr:housenumber":"13",
    "addr:postcode":"3201",
    "addr:street":"Titan Drv",
    "iso:country":"AU",
    "sg:address":"13 Titan Drv",
    "sg:city":"Carrum Downs",
    "sg:classifiers":[
        {
            "category":"Building & Trades",
            "subcategory":"Construction",
            "type":"Services"
        }
    ],
    "sg:phone":"+61 3 9775 1028",
    "sg:postcode":"3201",
    "sg:province":"VIC",
    "sg:tags":[
        "concrete",
        "contractor"
    ],
    "wof:name":"BFD Concreting",
    "wof:placetype":"venue"
},
  "geometry": {"coordinates":[145.166687,-38.102676],"type":"Point"}
}