{
  "type": "Feature",
  "properties": {
    "addr:full":"Units 2 & 3, 195 Five Islands Rd Cringila NSW 2502",
    "addr:housenumber":"units 2 & 3 195",
    "addr:postcode":"2502",
    "addr:street":"Five Islands Rd",
    "iso:country":"AU",
    "sg:address":"Units 2 & 3, 195 Five Islands Rd",
    "sg:city":"Cringila",
    "sg:classifiers":[
        {
            "category":"Retail",
            "subcategory":"Auto Repair",
            "type":"Services"
        }
    ],
    "sg:phone":"+61 2 4274 3500",
    "sg:postcode":"2502",
    "sg:province":"NSW",
    "sg:tags":[
        "sport",
        "motor"
    ],
    "wof:name":"Wild 1 Motorsport Products Pty Ltd",
    "wof:placetype":"venue"
},
  "geometry": {"coordinates":[150.872803,-34.46587],"type":"Point"}
}