{
  "type": "Feature",
  "properties": {
    "addr:full":"131 Kirkland Ave Coorparoo QLD 4151",
    "addr:housenumber":"131",
    "addr:postcode":"4151",
    "addr:street":"Kirkland Ave",
    "iso:country":"AU",
    "sg:address":"131 Kirkland Ave",
    "sg:city":"Coorparoo",
    "sg:classifiers":[
        {
            "category":"Personal",
            "subcategory":"Beauty Salon",
            "type":"Services"
        }
    ],
    "sg:phone":"+61 7 3324 2000",
    "sg:postcode":"4151",
    "sg:province":"QLD",
    "wof:name":"Ultra Suite Beauty Therapy",
    "wof:placetype":"venue"
},
  "geometry": {"coordinates":[153.05250549300001,-27.500371933],"type":"Point"}
}