{
  "type": "Feature",
  "properties": {
    "iso:country":"AU",
    "sg:address":"Bldg 4 731- 735 Deception Bay Rd",
    "sg:city":"Rothwell",
    "sg:classifiers":[
        {
            "category":"Sports & Exercise",
            "subcategory":"Gym",
            "type":"Entertainment"
        }
    ],
    "sg:phone":"+61 7 3204 9300",
    "sg:postcode":"4022",
    "sg:province":"QLD",
    "sg:tags":[
        "health",
        "fitness"
    ],
    "wof:name":"Genesis Fitness Club Rothwell",
    "wof:placetype":"venue"
},
  "geometry": {"coordinates":[153.047302,-27.21434],"type":"Point"}
}