{
  "type": "Feature",
  "properties": {
    "addr:full":"St Marys SA 5042",
    "addr:postcode":"5042",
    "iso:country":"AU",
    "sg:address":"St",
    "sg:city":"Marys",
    "sg:classifiers":[
        {
            "category":"Personal",
            "subcategory":"Massage",
            "type":"Services"
        }
    ],
    "sg:phone":"+61 8 8299 0536",
    "sg:postcode":"5042",
    "sg:province":"SA",
    "sg:tags":[
        "therapy"
    ],
    "wof:name":"Green Roseanne",
    "wof:placetype":"venue"
},
  "geometry": {"coordinates":[138.57913199999999,-35.000019],"type":"Point"}
}