{
  "type": "Feature",
  "properties": {
    "addr:full":"Johns Rd Woodstock QLD 4816",
    "addr:postcode":"4816",
    "addr:street":"Johns Rd",
    "iso:country":"AU",
    "sg:address":"Johns Rd",
    "sg:city":"Woodstock",
    "sg:classifiers":[
        {
            "category":"Farming",
            "subcategory":"Farm",
            "type":"Manufacturing & Wholesale Goods"
        }
    ],
    "sg:phone":"+61 7 4778 8741",
    "sg:postcode":"4816",
    "sg:province":"QLD",
    "sg:tags":[
        "farmer"
    ],
    "wof:name":"Cavill J & J",
    "wof:placetype":"venue"
},
  "geometry": {"coordinates":[146.83656300000001,-19.60158],"type":"Point"}
}