{
  "type": "Feature",
  "properties": {
    "addr:full":"223 Comur St Yass ACT 2582",
    "addr:housenumber":"223",
    "addr:postcode":"2582",
    "addr:street":"Comur St",
    "iso:country":"AU",
    "sg:address":"223 Comur St",
    "sg:city":"Yass",
    "sg:classifiers":[
        {
            "category":"Retail",
            "subcategory":"Auto Repair",
            "type":"Services"
        }
    ],
    "sg:phone":"+61 2 6226 3555",
    "sg:postcode":"2582",
    "sg:province":"ACT",
    "sg:tags":[
        "repairer",
        "motor",
        "engineer"
    ],
    "wof:name":"Maher Automotive",
    "wof:placetype":"venue"
},
  "geometry": {"coordinates":[148.915527344,-34.846736908],"type":"Point"}
}