{
  "type": "Feature",
  "properties": {
    "addr:full":"225 Great Eastern Hwy Belmont WA 6104",
    "addr:housenumber":"225",
    "addr:postcode":"6104",
    "addr:street":"Great Eastern Hwy",
    "iso:country":"AU",
    "sg:address":"225 Great Eastern Hwy",
    "sg:city":"Belmont",
    "sg:classifiers":[
        {
            "category":"Retail",
            "subcategory":"Auto Repair",
            "type":"Services"
        }
    ],
    "sg:phone":"+61 8 9477 0777",
    "sg:postcode":"6104",
    "sg:province":"WA",
    "sg:tags":[
        "bus",
        "truck"
    ],
    "sg:website":"http://www.majormotors.com.au",
    "wof:name":"Major Motors Pty Ltd",
    "wof:placetype":"venue"
},
  "geometry": {"coordinates":[115.924232483,-31.942861557],"type":"Point"}
}