{
  "type": "Feature",
  "properties": {
    "addr:full":"Shop 45, Pines Shopng Cntre Guineas Creek Rd Elanora QLD 4221",
    "addr:housenumber":"shop 45",
    "addr:postcode":"4221",
    "addr:street":"Cntre Guineas Creek Rd",
    "iso:country":"AU",
    "sg:address":"Shop 45, Pines Shopng Cntre Guineas Creek Rd",
    "sg:city":"Elanora",
    "sg:classifiers":[
        {
            "category":"Shopping",
            "subcategory":"Music",
            "type":"Retail Goods"
        }
    ],
    "sg:phone":"+61 7 5534 2159",
    "sg:postcode":"4221",
    "sg:province":"QLD",
    "sg:tags":[
        "store"
    ],
    "wof:name":"Recorded Music Group",
    "wof:placetype":"venue"
},
  "geometry": {"coordinates":[153.454177856,-28.1367073059],"type":"Point"}
}