{
  "type": "Feature",
  "properties": {
    "addr:full":"3/ 566 Nurigong St Albury NSW 2640",
    "addr:housenumber":"/ 566",
    "addr:postcode":"2640",
    "addr:street":"Nurigong St",
    "iso:country":"AU",
    "sg:address":"3/ 566 Nurigong St",
    "sg:city":"Albury",
    "sg:classifiers":[
        {
            "category":"Home & Garden",
            "subcategory":"Hardware",
            "type":"Retail Goods"
        }
    ],
    "sg:phone":"+61 2 6021 7744",
    "sg:postcode":"2640",
    "sg:province":"NSW",
    "sg:tags":[
        "nut",
        "bolt"
    ],
    "wof:name":"Coventry Fasteners",
    "wof:placetype":"venue"
},
  "geometry": {"coordinates":[146.91281127900001,-36.0907478333],"type":"Point"}
}