{
  "type": "Feature",
  "properties": {
    "iso:country":"AU",
    "sg:address":"96 Kosciusko Rd",
    "sg:city":"Thurgoona",
    "sg:classifiers":[
        {
            "category":"Building & Trades",
            "subcategory":"Construction",
            "type":"Services"
        }
    ],
    "sg:phone":"+61 2 6043 1253",
    "sg:postcode":"2640",
    "sg:province":"NSW",
    "sg:tags":[
        "contractor"
    ],
    "wof:name":"Burt Geoff",
    "wof:placetype":"venue"
},
  "geometry": {"coordinates":[146.98797607399999,-36.0504074097],"type":"Point"}
}