{
  "type": "Feature",
  "properties": {
    "iso:country":"AU",
    "sg:address":"605 Zillmere Rd",
    "sg:city":"Zillmere",
    "sg:classifiers":[
        {
            "category":"Retail",
            "subcategory":"Auto Repair",
            "type":"Services"
        }
    ],
    "sg:phone":"+61 13 19 05",
    "sg:postcode":"4034",
    "sg:province":"QLD",
    "sg:tags":[
        "testing",
        "inspection",
        "motor",
        "vehicle"
    ],
    "wof:name":"RACQ Vehicle Inspections",
    "wof:placetype":"venue"
},
  "geometry": {"coordinates":[153.02655,-27.357462],"type":"Point"}
}