{
  "type": "Feature",
  "properties": {
    "addr:full":"6 Kurrajong Ave Leeton NSW 2705",
    "addr:housenumber":"6",
    "addr:postcode":"2705",
    "addr:street":"Kurrajong Ave",
    "iso:country":"AU",
    "sg:address":"6 Kurrajong Ave",
    "sg:city":"Leeton",
    "sg:classifiers":[
        {
            "category":"Shopping",
            "subcategory":"Clothing, Apparel, & Fashions",
            "type":"Retail Goods"
        }
    ],
    "sg:phone":"+61 2 6953 4698",
    "sg:postcode":"2705",
    "sg:province":"NSW",
    "sg:tags":[
        "recycled",
        "clothing"
    ],
    "wof:name":"Salvation Army Leeton Red Shield Family Store",
    "wof:placetype":"venue"
},
  "geometry": {"coordinates":[146.40603637699999,-34.5520935059],"type":"Point"}
}