{
  "type": "Feature",
  "properties": {
    "addr:full":"17 Zilla Crt Dandenong VIC 3175",
    "addr:housenumber":"17",
    "addr:postcode":"3175",
    "addr:street":"Zilla Crt",
    "iso:country":"AU",
    "sg:address":"17 Zilla Crt",
    "sg:city":"Dandenong",
    "sg:classifiers":[
        {
            "category":"Bars & Pubs",
            "subcategory":"Gay Bar",
            "type":"Food & Drink"
        }
    ],
    "sg:phone":"+61 3 9792 4030",
    "sg:postcode":"3175",
    "sg:province":"VIC",
    "sg:tags":[
        "plywood",
        "veneer"
    ],
    "wof:name":"The Plystore",
    "wof:placetype":"venue"
},
  "geometry": {"coordinates":[145.20982360799999,-38.0120277405],"type":"Point"}
}