{
  "type": "Feature",
  "properties": {
    "iso:country":"AU",
    "sg:address":"4 Sabre St",
    "sg:city":"Raby",
    "sg:classifiers":[
        {
            "category":"Building & Trades",
            "subcategory":"Construction",
            "type":"Services"
        }
    ],
    "sg:phone":"+61 410 766 472",
    "sg:postcode":"2566",
    "sg:province":"NSW",
    "sg:tags":[
        "spouting",
        "guttering"
    ],
    "wof:name":"Supreme Fascia & Guttering",
    "wof:placetype":"venue"
},
  "geometry": {"coordinates":[150.813796997,-34.0213623047],"type":"Point"}
}