{
  "type": "Feature",
  "properties": {
    "iso:country":"AU",
    "sg:address":"25 Yallourn St",
    "sg:city":"Fyshwick",
    "sg:classifiers":[
        {
            "category":"Professional",
            "subcategory":"Employment Agencies",
            "type":"Services"
        }
    ],
    "sg:phone":"+61 2 6280 0347",
    "sg:postcode":"2609",
    "sg:province":"ACT",
    "sg:tags":[
        "provider",
        "internet"
    ],
    "wof:name":"Memex Technology Pty Ltd",
    "wof:placetype":"venue"
},
  "geometry": {"coordinates":[149.17257690400001,-35.331993103],"type":"Point"}
}