{
  "type": "Feature",
  "properties": {
    "addr:full":"30 Powlett St Kilmore VIC 3764",
    "addr:housenumber":"30",
    "addr:postcode":"3764",
    "addr:street":"Powlett St",
    "iso:country":"AU",
    "sg:address":"30 Powlett St",
    "sg:city":"Kilmore",
    "sg:classifiers":[
        {
            "category":"Health Services",
            "subcategory":"Chiropractor",
            "type":"Services"
        }
    ],
    "sg:phone":"+61 3 5782 2278",
    "sg:postcode":"3764",
    "sg:province":"VIC",
    "wof:name":"Terrett Robert Grahame",
    "wof:placetype":"venue"
},
  "geometry": {"coordinates":[144.95179748499999,-37.2989311218],"type":"Point"}
}