{
  "type": "Feature",
  "properties": {
    "iso:country":"AU",
    "sg:address":"Wallenjoe Rd",
    "sg:city":"Huntly",
    "sg:classifiers":[
        {
            "category":"Farming",
            "subcategory":"Vineyard",
            "type":"Manufacturing & Wholesale Goods"
        }
    ],
    "sg:phone":"+61 3 5448 8111",
    "sg:postcode":"3551",
    "sg:province":"VIC",
    "sg:tags":[
        "saleyards"
    ],
    "wof:name":"Bendigo Livestock Exchange",
    "wof:placetype":"venue"
},
  "geometry": {"coordinates":[144.30511474599999,-36.6665992737],"type":"Point"}
}