{
  "type": "Feature",
  "properties": {
    "addr:full":"181 Lake Rd Port Macquarie NSW 2444",
    "addr:housenumber":"181",
    "addr:postcode":"2444",
    "addr:street":"Lake Rd",
    "iso:country":"AU",
    "sg:address":"181 Lake Rd",
    "sg:city":"Port Macquarie",
    "sg:classifiers":[
        {
            "category":"Home & Garden",
            "subcategory":"Carpets & Floor Coverings",
            "type":"Retail Goods"
        }
    ],
    "sg:phone":"+61 2 6581 3200",
    "sg:postcode":"2444",
    "sg:province":"NSW",
    "sg:tags":[
        "tile",
        "wall"
    ],
    "sg:website":"http://www.tileswithstyle.com.au",
    "wof:name":"Tiles With Style",
    "wof:placetype":"venue"
},
  "geometry": {"coordinates":[152.892044,-31.44891],"type":"Point"}
}