{
  "type": "Feature",
  "properties": {
    "iso:country":"AU",
    "sg:address":"Short St",
    "sg:city":"Mt Isa",
    "sg:classifiers":[
        {
            "category":"Education",
            "subcategory":"School",
            "type":"Public Place"
        }
    ],
    "sg:phone":"+61 7 4743 3014",
    "sg:postcode":"4825",
    "sg:province":"QLD",
    "wof:name":"St Kieran's Primary",
    "wof:placetype":"venue"
},
  "geometry": {"coordinates":[139.500244,-20.71352],"type":"Point"}
}