{
  "type": "Feature",
  "properties": {
    "iso:country":"AU",
    "sg:address":"3/ 1420 Anzac Ave",
    "sg:city":"Kallangur",
    "sg:classifiers":[
        {
            "category":"Health Services",
            "subcategory":"Dentist",
            "type":"Services"
        }
    ],
    "sg:phone":"+61 7 3204 4777",
    "sg:postcode":"4503",
    "sg:province":"QLD",
    "wof:name":"Thomson, Monica",
    "wof:placetype":"venue"
},
  "geometry": {"coordinates":[152.994140625,-27.2502307892],"type":"Point"}
}