{
  "type": "Feature",
  "properties": {
    "addr:full":"46 Burleigh Rd Melton VIC 3337",
    "addr:housenumber":"46",
    "addr:postcode":"3337",
    "addr:street":"Burleigh Rd",
    "iso:country":"AU",
    "sg:address":"46 Burleigh Rd",
    "sg:city":"Melton",
    "sg:classifiers":[
        {
            "category":"Fast Food",
            "type":"Food & Drink"
        }
    ],
    "sg:phone":"+61 3 9743 7940",
    "sg:postcode":"3337",
    "sg:province":"VIC",
    "sg:tags":[
        "away",
        "take"
    ],
    "wof:name":"Burleigh Fish Shop",
    "wof:placetype":"venue"
},
  "geometry": {"coordinates":[144.58424400000001,-37.675419],"type":"Point"}
}