{
  "type": "Feature",
  "properties": {
    "iso:country":"AU",
    "sg:address":"77 Dukes Hwy",
    "sg:city":"Bordertown",
    "sg:classifiers":[
        {
            "category":"Freight",
            "type":"Transportation"
        }
    ],
    "sg:phone":"+61 8 8752 0022",
    "sg:postcode":"5268",
    "sg:province":"SA",
    "sg:tags":[
        "transport",
        "refrigerated"
    ],
    "wof:name":"Tartiara Transport Pty Ltd",
    "wof:placetype":"venue"
},
  "geometry": {"coordinates":[140.733505,-36.284271],"type":"Point"}
}