{
  "type": "Feature",
  "properties": {
    "iso:country":"AU",
    "sg:address":"Suite 2, 41 Sturt St",
    "sg:city":"Townsville",
    "sg:classifiers":[
        {
            "category":"Insurance",
            "subcategory":"Hazard Insurance",
            "type":"Services"
        }
    ],
    "sg:phone":"+61 7 4772 4099",
    "sg:postcode":"4810",
    "sg:province":"QLD",
    "sg:tags":[
        "motor",
        "vehicle"
    ],
    "wof:name":"Jardine Lloyd Thompson Pty Ltd",
    "wof:placetype":"venue"
},
  "geometry": {"coordinates":[146.814606,-19.260921],"type":"Point"}
}