{
  "type": "Feature",
  "properties": {
    "addr:full":"435 Chapel St South Yarra VIC 3141",
    "addr:housenumber":"435",
    "addr:postcode":"3141",
    "addr:street":"Chapel St",
    "iso:country":"AU",
    "sg:address":"435 Chapel St",
    "sg:city":"South Yarra",
    "sg:classifiers":[
        {
            "category":"Manufacturing",
            "subcategory":"Leather Goods",
            "type":"Manufacturing & Wholesale Goods"
        }
    ],
    "sg:phone":"+61 3 9824 1819",
    "sg:postcode":"3141",
    "sg:province":"VIC",
    "sg:tags":[
        "wholesaler",
        "mfrs",
        "clothing"
    ],
    "wof:name":"Oris Quality Leathers",
    "wof:placetype":"venue"
},
  "geometry": {"coordinates":[144.99447631800001,-37.8443260193],"type":"Point"}
}