{
  "type": "Feature",
  "properties": {
    "addr:full":"11 Erceg Rd Yangebup WA 6164",
    "addr:housenumber":"11",
    "addr:postcode":"6164",
    "addr:street":"Erceg Rd",
    "iso:country":"AU",
    "sg:address":"11 Erceg Rd",
    "sg:city":"Yangebup",
    "sg:phone":"+61 8 9418 8566",
    "sg:postcode":"6164",
    "sg:province":"WA",
    "wof:name":"Diverse Tank Engineering Pty Ltd",
    "wof:placetype":"venue"
},
  "geometry": {"coordinates":[115.796959,-32.120754],"type":"Point"}
}