{
  "type": "Feature",
  "properties": {
    "addr:full":"253- 255 Hannon St Kalgoorlie WA 6430",
    "addr:housenumber":"255",
    "addr:postcode":"6430",
    "addr:street":"Hannon St",
    "iso:country":"AU",
    "sg:address":"253- 255 Hannon St",
    "sg:city":"Kalgoorlie",
    "sg:classifiers":[
        {
            "category":"Shopping",
            "subcategory":"Clothing, Apparel, & Fashions",
            "type":"Retail Goods"
        }
    ],
    "sg:phone":"+61 8 9021 6685",
    "sg:postcode":"6430",
    "sg:province":"WA",
    "sg:tags":[
        "jean"
    ],
    "wof:name":"JeansWest",
    "wof:placetype":"venue"
},
  "geometry": {"coordinates":[121.46939086899999,-30.7501144409],"type":"Point"}
}