{
  "type": "Feature",
  "properties": {
    "addr:full":"205 Balaclava Rd Shepparton VIC 3630",
    "addr:housenumber":"205",
    "addr:postcode":"3630",
    "addr:street":"Balaclava Rd",
    "iso:country":"AU",
    "sg:address":"205 Balaclava Rd",
    "sg:city":"Shepparton",
    "sg:classifiers":[
        {
            "category":"Social Services",
            "subcategory":"Child Care",
            "type":"Services"
        }
    ],
    "sg:phone":"+61 3 5821 9188",
    "sg:postcode":"3630",
    "sg:province":"VIC",
    "wof:name":"ABC Learning Centres",
    "wof:placetype":"venue"
},
  "geometry": {"coordinates":[145.414138794,-36.3680839539],"type":"Point"}
}