{
  "type": "Feature",
  "properties": {
    "addr:full":"349 Frome St Moree NSW 2400",
    "addr:housenumber":"349",
    "addr:postcode":"2400",
    "addr:street":"Frome St",
    "iso:country":"AU",
    "sg:address":"349 Frome St",
    "sg:city":"Moree",
    "sg:classifiers":[
        {
            "category":"Shopping",
            "type":"Retail Goods"
        }
    ],
    "sg:phone":"+61 2 6752 1133",
    "sg:postcode":"2400",
    "sg:province":"NSW",
    "sg:tags":[
        "agent",
        "stock"
    ],
    "wof:name":"Landmark Operations Limited",
    "wof:placetype":"venue"
},
  "geometry": {"coordinates":[149.84283447300001,-29.4744415283],"type":"Point"}
}