{
  "type": "Feature",
  "properties": {
    "iso:country":"AU",
    "sg:address":"60- 64 West St",
    "sg:city":"Mt Isa",
    "sg:classifiers":[
        {
            "category":"Education",
            "subcategory":"Kindergarten",
            "type":"Public Place"
        }
    ],
    "sg:phone":"+61 7 4743 6311",
    "sg:postcode":"4825",
    "sg:province":"QLD",
    "sg:tags":[
        "pre-schools"
    ],
    "wof:name":"Captain Kid Child Care Centre.",
    "wof:placetype":"venue"
},
  "geometry": {"coordinates":[139.491486,-20.721146],"type":"Point"}
}