{
  "type": "Feature",
  "properties": {
    "iso:country":"AU",
    "sg:address":"Lvl6 / 273",
    "sg:city":"Adelaide Tce Perth",
    "sg:classifiers":[
        {
            "category":"Professional",
            "subcategory":"Employment Agencies",
            "type":"Services"
        }
    ],
    "sg:phone":"+61 13 19 17",
    "sg:postcode":"6000",
    "sg:province":"WA",
    "sg:tags":[
        "provider",
        "internet"
    ],
    "wof:name":"iiNet Ltd",
    "wof:placetype":"venue"
},
  "geometry": {"coordinates":[115.87789917000001,-31.9620685577],"type":"Point"}
}