{
  "type": "Feature",
  "properties": {
    "addr:full":"33 Lincoln St Minto NSW 2566",
    "addr:housenumber":"33",
    "addr:postcode":"2566",
    "addr:street":"Lincoln St",
    "iso:country":"AU",
    "sg:address":"33 Lincoln St",
    "sg:city":"Minto",
    "sg:classifiers":[
        {
            "category":"Home & Garden",
            "subcategory":"Building Materials",
            "type":"Retail Goods"
        }
    ],
    "sg:phone":"+61 2 9824 6218",
    "sg:postcode":"2566",
    "sg:province":"NSW",
    "sg:tags":[
        "insect",
        "screen"
    ],
    "wof:name":"P R W Window Services",
    "wof:placetype":"venue"
},
  "geometry": {"coordinates":[150.841796875,-34.0247688293],"type":"Point"}
}