{
  "type": "Feature",
  "properties": {
    "addr:full":"U 32/ 52 Bay St Rockdale NSW 2216",
    "addr:housenumber":"32 / 52",
    "addr:postcode":"2216",
    "addr:street":"Bay St",
    "iso:country":"AU",
    "sg:address":"U 32/ 52 Bay St",
    "sg:city":"Rockdale",
    "sg:classifiers":[
        {
            "category":"Professional",
            "subcategory":"Detective & Security Services",
            "type":"Services"
        }
    ],
    "sg:phone":"+61 2 9599 6123",
    "sg:postcode":"2216",
    "sg:province":"NSW",
    "sg:tags":[
        "consultant",
        "system"
    ],
    "wof:name":"Executive Protective Services Pty Ltd",
    "wof:placetype":"venue"
},
  "geometry": {"coordinates":[151.13870199999999,-33.953186],"type":"Point"}
}