{
  "type": "Feature",
  "properties": {
    "addr:full":"73 Edgar St Heywood VIC 3304",
    "addr:housenumber":"73",
    "addr:postcode":"3304",
    "addr:street":"Edgar St",
    "iso:country":"AU",
    "sg:address":"73 Edgar St",
    "sg:city":"Heywood",
    "sg:classifiers":[
        {
            "category":"Food & Beverages",
            "subcategory":"Groceries & Convenience Stores",
            "type":"Retail Goods"
        }
    ],
    "sg:phone":"+61 3 5527 1781",
    "sg:postcode":"3304",
    "sg:province":"VIC",
    "wof:name":"Hollyrock Milk Bar & Takeaway",
    "wof:placetype":"venue"
},
  "geometry": {"coordinates":[141.62997436500001,-38.1305198669],"type":"Point"}
}