{
  "type": "Feature",
  "properties": {
    "iso:country":"AU",
    "sg:address":"3/ 52 Albert Rd",
    "sg:city":"South Melbourne",
    "sg:classifiers":[
        {
            "category":"Banks & Credit Unions",
            "subcategory":"Investment Brokerage",
            "type":"Services"
        }
    ],
    "sg:phone":"+61 1800 467 444",
    "sg:postcode":"3205",
    "sg:province":"VIC",
    "wof:name":"Insight Investment Corporation",
    "wof:placetype":"venue"
},
  "geometry": {"coordinates":[144.97122200000001,-37.834442],"type":"Point"}
}