{
  "type": "Feature",
  "properties": {
    "addr:full":"25 Illawong Crs Terranora NSW 2486",
    "addr:housenumber":"25",
    "addr:postcode":"2486",
    "addr:street":"Illawong Crs",
    "iso:country":"AU",
    "sg:address":"25 Illawong Crs",
    "sg:city":"Terranora",
    "sg:classifiers":[
        {
            "category":"Professional",
            "subcategory":"Business Services",
            "type":"Services"
        }
    ],
    "sg:phone":"+61 7 5590 4555",
    "sg:postcode":"2486",
    "sg:province":"NSW",
    "sg:tags":[
        "broker"
    ],
    "wof:name":"East Coast Business Sales",
    "wof:placetype":"venue"
},
  "geometry": {"coordinates":[153.49336242699999,-28.2410202026],"type":"Point"}
}