{
  "type": "Feature",
  "properties": {
    "addr:full":"Units 9-11 2 Pyrmont Bridge Rd Pyrmont NSW 2009",
    "addr:housenumber":"2",
    "addr:postcode":"2009",
    "addr:street":"Pyrmont Bridge Rd",
    "iso:country":"AU",
    "sg:address":"Units 9-11 2 Pyrmont Bridge Rd",
    "sg:city":"Pyrmont",
    "sg:classifiers":[
        {
            "category":"Shopping",
            "subcategory":"Clothing, Apparel, & Fashions",
            "type":"Retail Goods"
        }
    ],
    "sg:phone":"+61 2 8586 0444",
    "sg:postcode":"2009",
    "sg:province":"NSW",
    "sg:tags":[
        "lady",
        "wear"
    ],
    "wof:name":"Esprit Retail Pty Ltd",
    "wof:placetype":"venue"
},
  "geometry": {"coordinates":[151.197174072,-33.8698501587],"type":"Point"}
}