{
  "type": "Feature",
  "properties": {
    "addr:full":"67 Westminster Rd Gladesville NSW 2111",
    "addr:housenumber":"67",
    "addr:postcode":"2111",
    "addr:street":"Westminster Rd",
    "iso:country":"AU",
    "sg:address":"67 Westminster Rd",
    "sg:city":"Gladesville",
    "sg:classifiers":[
        {
            "category":"Professional",
            "subcategory":"Computer Services",
            "type":"Services"
        }
    ],
    "sg:phone":"+61 2 9879 3683",
    "sg:postcode":"2111",
    "sg:province":"NSW",
    "sg:tags":[
        "package",
        "software"
    ],
    "wof:name":"Payfast",
    "wof:placetype":"venue"
},
  "geometry": {"coordinates":[151.13127136200001,-33.8184127808],"type":"Point"}
}