{
  "type": "Feature",
  "properties": {
    "iso:country":"AU",
    "sg:address":"Level 1/234- 236 Cowper St",
    "sg:city":"Warrawong",
    "sg:classifiers":[
        {
            "category":"Personal",
            "subcategory":"Beauty Salon",
            "type":"Services"
        }
    ],
    "sg:phone":"+61 2 4274 5674",
    "sg:postcode":"2502",
    "sg:province":"NSW",
    "sg:tags":[
        "hairdresser"
    ],
    "wof:name":"Suave Hair & Beauty",
    "wof:placetype":"venue"
},
  "geometry": {"coordinates":[150.88755800000001,-34.484859],"type":"Point"}
}