{
  "type": "Feature",
  "properties": {
    "addr:full":"Matthews St Parkes NSW 2870",
    "addr:postcode":"2870",
    "addr:street":"Matthews St",
    "iso:country":"AU",
    "sg:address":"Matthews St",
    "sg:city":"Parkes",
    "sg:classifiers":[
        {
            "category":"Building & Trades",
            "subcategory":"Construction",
            "type":"Services"
        }
    ],
    "sg:phone":"+61 2 6862 4655",
    "sg:postcode":"2870",
    "sg:province":"NSW",
    "sg:tags":[
        "earth",
        "excavating",
        "moving",
        "contractor"
    ],
    "wof:name":"Parkes Ready Mixed Concrete Pty Ltd",
    "wof:placetype":"venue"
},
  "geometry": {"coordinates":[148.16253699999999,-33.148876],"type":"Point"}
}