{
  "type": "Feature",
  "properties": {
    "iso:country":"AU",
    "sg:address":"12 Stuart Rd",
    "sg:city":"Dulwich",
    "sg:classifiers":[
        {
            "category":"Government",
            "subcategory":"Court House",
            "type":"Public Place"
        }
    ],
    "sg:phone":"+61 408 839 426",
    "sg:postcode":"5065",
    "sg:province":"SA",
    "sg:tags":[
        "personal",
        "marriage",
        "family",
        "counselling"
    ],
    "wof:name":"A. Ros. Yuen",
    "wof:placetype":"venue"
},
  "geometry": {"coordinates":[138.631515503,-34.9355239868],"type":"Point"}
}