{
  "type": "Feature",
  "properties": {
    "addr:full":"315 Cleveland- Redland Bay Rd Thornlands QLD 4164",
    "addr:housenumber":"315",
    "addr:postcode":"4164",
    "addr:street":"Cleveland Redland Bay Rd",
    "iso:country":"AU",
    "sg:address":"315 Cleveland- Redland Bay Rd",
    "sg:city":"Thornlands",
    "sg:classifiers":[
        {
            "category":"Wholesale",
            "subcategory":"Plants",
            "type":"Manufacturing & Wholesale Goods"
        }
    ],
    "sg:phone":"+61 7 3820 7492",
    "sg:postcode":"4164",
    "sg:province":"QLD",
    "sg:tags":[
        "florist"
    ],
    "wof:name":"Kahlon Fresh Flowers",
    "wof:placetype":"venue"
},
  "geometry": {"coordinates":[153.26756286599999,-27.5599155426],"type":"Point"}
}