{
  "type": "Feature",
  "properties": {
    "addr:full":"469 Cabramatta Rd Cabramatta NSW 2166",
    "addr:housenumber":"469",
    "addr:postcode":"2166",
    "addr:street":"Cabramatta Rd",
    "iso:country":"AU",
    "sg:address":"469 Cabramatta Rd",
    "sg:city":"Cabramatta",
    "sg:classifiers":[
        {
            "category":"Food & Beverages",
            "subcategory":"Supermarket",
            "type":"Retail Goods"
        }
    ],
    "sg:phone":"+61 2 9610 4432",
    "sg:postcode":"2166",
    "sg:province":"NSW",
    "sg:tags":[
        "grocery",
        "store"
    ],
    "wof:name":"Welcome Mart",
    "wof:placetype":"venue"
},
  "geometry": {"coordinates":[150.912567139,-33.8966598511],"type":"Point"}
}