{
  "type": "Feature",
  "properties": {
    "addr:full":"26 Dewer Ave Ridgehaven SA 5097",
    "addr:housenumber":"26",
    "addr:postcode":"5097",
    "addr:street":"Dewer Ave",
    "iso:country":"AU",
    "sg:address":"26 Dewer Ave",
    "sg:city":"Ridgehaven",
    "sg:classifiers":[
        {
            "category":"Building & Trades",
            "subcategory":"Construction",
            "type":"Services"
        }
    ],
    "sg:phone":"+61 8 8264 6264",
    "sg:postcode":"5097",
    "sg:province":"SA",
    "sg:tags":[
        "joinery"
    ],
    "wof:name":"Bell R A & A L",
    "wof:placetype":"venue"
},
  "geometry": {"coordinates":[138.697555542,-34.8251800537],"type":"Point"}
}