{
  "type": "Feature",
  "properties": {
    "iso:country":"AU",
    "sg:address":"3 Duggan Crt",
    "sg:city":"Kardinya",
    "sg:classifiers":[
        {
            "category":"Building & Trades",
            "subcategory":"Plumbing",
            "type":"Services"
        }
    ],
    "sg:phone":"+61 403 573 360",
    "sg:postcode":"6163",
    "sg:province":"WA",
    "sg:tags":[
        "plumber",
        "gasfitters"
    ],
    "wof:name":"Equator Plumbing Pty. Ltd.",
    "wof:placetype":"venue"
},
  "geometry": {"coordinates":[115.819061,-32.072083],"type":"Point"}
}