{
  "type": "Feature",
  "properties": {
    "iso:country":"AU",
    "sg:address":"32 Duncan St",
    "sg:city":"Murtoa",
    "sg:classifiers":[
        {
            "category":"Building & Trades",
            "subcategory":"Construction",
            "type":"Services"
        }
    ],
    "sg:phone":"+61 417 030 025",
    "sg:postcode":"3390",
    "sg:province":"VIC",
    "sg:tags":[
        "concrete",
        "contractor"
    ],
    "wof:name":"Briggs A T",
    "wof:placetype":"venue"
},
  "geometry": {"coordinates":[142.467849731,-36.618598938],"type":"Point"}
}