{
  "type": "Feature",
  "properties": {
    "addr:full":"PO Box 229 Bentleigh East VIC 3165",
    "addr:postcode":"3165",
    "iso:country":"AU",
    "sg:address":"PO Box 229",
    "sg:city":"Bentleigh East",
    "sg:classifiers":[
        {
            "category":"Building & Trades",
            "subcategory":"Plumbing",
            "type":"Services"
        }
    ],
    "sg:phone":"+61 3 9579 7105",
    "sg:postcode":"3165",
    "sg:province":"VIC",
    "sg:tags":[
        "plumber",
        "gasfitters"
    ],
    "wof:name":"K D Plumbing",
    "wof:placetype":"venue"
},
  "geometry": {"coordinates":[145.06695556599999,-37.9222412109],"type":"Point"}
}