{
  "type": "Feature",
  "properties": {
    "iso:country":"AU",
    "sg:address":"50 Freer St",
    "sg:city":"Shearwater",
    "sg:classifiers":[
        {
            "category":"Wholesale",
            "subcategory":"Machinery & Supplies",
            "type":"Manufacturing & Wholesale Goods"
        }
    ],
    "sg:phone":"+61 418 811 171",
    "sg:postcode":"7307",
    "sg:province":"TAS",
    "sg:tags":[
        "process",
        "instrument",
        "control"
    ],
    "wof:name":"Tasmanian Process Instruments Pty Ltd",
    "wof:placetype":"venue"
},
  "geometry": {"coordinates":[146.541153,-41.156109],"type":"Point"}
}