{
  "type": "Feature",
  "properties": {
    "addr:full":"2504 Benalla-Tatong Rd Tatong VIC 3673",
    "addr:housenumber":"2504",
    "addr:postcode":"3673",
    "addr:street":"Benalla-Tatong Rd",
    "iso:country":"AU",
    "sg:address":"2504 Benalla-Tatong Rd",
    "sg:city":"Tatong",
    "sg:classifiers":[
        {
            "category":"Building & Trades",
            "subcategory":"Construction",
            "type":"Services"
        }
    ],
    "sg:phone":"+61 3 5767 2161",
    "sg:postcode":"3673",
    "sg:province":"VIC",
    "sg:tags":[
        "industrial",
        "commercial",
        "air conditioning"
    ],
    "wof:name":"Anthony Cairncross",
    "wof:placetype":"venue"
},
  "geometry": {"coordinates":[146.10725400000001,-36.729607],"type":"Point"}
}