{
  "type": "Feature",
  "properties": {
    "addr:full":"5 Whyte Crt Wodonga VIC 3690",
    "addr:housenumber":"5",
    "addr:postcode":"3690",
    "addr:street":"Whyte Crt",
    "iso:country":"AU",
    "sg:address":"5 Whyte Crt",
    "sg:city":"Wodonga",
    "sg:classifiers":[
        {
            "category":"Home & Garden",
            "subcategory":"Garden Supply",
            "type":"Retail Goods"
        }
    ],
    "sg:phone":"+61 2 6056 3449",
    "sg:postcode":"3690",
    "sg:province":"VIC",
    "sg:tags":[
        "fertilizer"
    ],
    "wof:name":"Jenkins Fertilisers & Limes",
    "wof:placetype":"venue"
},
  "geometry": {"coordinates":[146.897613525,-36.1187858582],"type":"Point"}
}