{
  "type": "Feature",
  "properties": {
    "addr:full":"3 Snapper Rd Huskisson NSW 2540",
    "addr:housenumber":"3",
    "addr:postcode":"2540",
    "addr:street":"Snapper Rd",
    "iso:country":"AU",
    "sg:address":"3 Snapper Rd",
    "sg:city":"Huskisson",
    "sg:classifiers":[
        {
            "category":"Retail",
            "subcategory":"Auto Repair",
            "type":"Services"
        }
    ],
    "sg:phone":"+61 2 4441 7755",
    "sg:postcode":"2540",
    "sg:province":"NSW",
    "sg:tags":[
        "repairer",
        "motor",
        "engineer"
    ],
    "wof:name":"Steve Purse Automotive",
    "wof:placetype":"venue"
},
  "geometry": {"coordinates":[150.65936279300001,-35.0293655396],"type":"Point"}
}