{
  "type": "Feature",
  "properties": {
    "addr:full":"120 Geelong Rd Torquay VIC 3228",
    "addr:housenumber":"120",
    "addr:postcode":"3228",
    "addr:street":"Geelong Rd",
    "iso:country":"AU",
    "sg:address":"120 Geelong Rd",
    "sg:city":"Torquay",
    "sg:classifiers":[
        {
            "category":"Retail",
            "subcategory":"Veterinary Services",
            "type":"Services"
        }
    ],
    "sg:phone":"+61 3 5261 6486",
    "sg:postcode":"3228",
    "sg:province":"VIC",
    "sg:tags":[
        "surgeon"
    ],
    "wof:name":"Trembath, Fleur Dr",
    "wof:placetype":"venue"
},
  "geometry": {"coordinates":[144.31796299999999,-38.325581],"type":"Point"}
}