{
  "type": "Feature",
  "properties": {
    "addr:full":"Lvl 1/ 21 Waterloo Rd Collingwood VIC 3066",
    "addr:housenumber":"/ 21",
    "addr:postcode":"3066",
    "addr:street":"Waterloo Rd",
    "iso:country":"AU",
    "sg:address":"Lvl 1/ 21 Waterloo Rd",
    "sg:city":"Collingwood",
    "sg:classifiers":[
        {
            "category":"Building & Trades",
            "subcategory":"Construction",
            "type":"Services"
        }
    ],
    "sg:phone":"+61 3 9417 3225",
    "sg:postcode":"3066",
    "sg:province":"VIC",
    "sg:tags":[
        "contractor"
    ],
    "wof:name":"Kubic Pty Ltd",
    "wof:placetype":"venue"
},
  "geometry": {"coordinates":[144.98793029800001,-37.8064117432],"type":"Point"}
}