{
  "type": "Feature",
  "properties": {
    "addr:full":"136 Bridge Rd Glebe NSW 2037",
    "addr:housenumber":"136",
    "addr:postcode":"2037",
    "addr:street":"Bridge Rd",
    "iso:country":"AU",
    "sg:address":"136 Bridge Rd",
    "sg:city":"Glebe",
    "sg:classifiers":[
        {
            "category":"Travel",
            "subcategory":"Travel Agent",
            "type":"Entertainment"
        }
    ],
    "sg:phone":"+61 2 9552 2852",
    "sg:postcode":"2037",
    "sg:province":"NSW",
    "sg:tags":[
        "consultant"
    ],
    "wof:name":"Cycling For Softies-France",
    "wof:placetype":"venue"
},
  "geometry": {"coordinates":[151.18783569300001,-33.8794708252],"type":"Point"}
}