{
  "type": "Feature",
  "properties": {
    "addr:full":"Unit 1, 19 Penny Pl Arndell Park NSW 2148",
    "addr:housenumber":"19",
    "addr:postcode":"2148",
    "addr:street":"Penny Pl",
    "iso:country":"AU",
    "sg:address":"Unit 1, 19 Penny Pl",
    "sg:city":"Arndell Park",
    "sg:classifiers":[
        {
            "category":"Building & Trades",
            "subcategory":"Plumbing",
            "type":"Services"
        }
    ],
    "sg:phone":"+61 2 9621 1960",
    "sg:postcode":"2148",
    "sg:province":"NSW",
    "sg:tags":[
        "plumber",
        "gasfitters"
    ],
    "wof:name":"Chips Plumbing Pty Ltd",
    "wof:placetype":"venue"
},
  "geometry": {"coordinates":[150.893875122,-33.7959785461],"type":"Point"}
}