{
  "type": "Feature",
  "properties": {
    "addr:full":"182 - 184 Springwood Rd Springwood QLD 4127",
    "addr:housenumber":"184",
    "addr:postcode":"4127",
    "addr:street":"Springwood Rd",
    "iso:country":"AU",
    "sg:address":"182 - 184 Springwood Rd",
    "sg:city":"Springwood",
    "sg:classifiers":[
        {
            "category":"Social Services",
            "subcategory":"Child Care",
            "type":"Services"
        }
    ],
    "sg:phone":"+61 1800 232 282",
    "sg:postcode":"4127",
    "sg:province":"QLD",
    "sg:website":"http://www.sunkids.com.au",
    "wof:name":"Sunkids",
    "wof:placetype":"venue"
},
  "geometry": {"coordinates":[153.13421630900001,-27.6108112335],"type":"Point"}
}