{
  "type": "Feature",
  "properties": {
    "addr:full":"145 Timor St Warrnambool VIC 3280",
    "addr:housenumber":"145",
    "addr:postcode":"3280",
    "addr:street":"Timor St",
    "iso:country":"AU",
    "sg:address":"145 Timor St",
    "sg:city":"Warrnambool",
    "sg:classifiers":[
        {
            "category":"Ice Cream",
            "type":"Food & Drink"
        }
    ],
    "sg:phone":"+61 3 5562 5201",
    "sg:postcode":"3280",
    "sg:province":"VIC",
    "sg:tags":[
        "retail"
    ],
    "wof:name":"Warrnambool Ice Creamery",
    "wof:placetype":"venue"
},
  "geometry": {"coordinates":[142.483551025,-38.3860626221],"type":"Point"}
}