{
  "type": "Feature",
  "properties": {
    "addr:full":"121 Carthage St Tamworth NSW 2340",
    "addr:housenumber":"121",
    "addr:postcode":"2340",
    "addr:street":"Carthage St",
    "iso:country":"AU",
    "sg:address":"121 Carthage St",
    "sg:city":"Tamworth",
    "sg:classifiers":[
        {
            "category":"Insurance",
            "subcategory":"Hazard Insurance",
            "type":"Services"
        }
    ],
    "sg:phone":"+61 2 6766 6377",
    "sg:postcode":"2340",
    "sg:province":"NSW",
    "sg:tags":[
        "loss",
        "adjuster",
        "assessor"
    ],
    "wof:name":"Freemans Australia",
    "wof:placetype":"venue"
},
  "geometry": {"coordinates":[150.935623169,-31.0902309418],"type":"Point"}
}