{
  "type": "Feature",
  "properties": {
    "addr:full":"3 Della Torre Rd Moe VIC 3825",
    "addr:housenumber":"3",
    "addr:postcode":"3825",
    "addr:street":"Della Torre Rd",
    "iso:country":"AU",
    "sg:address":"3 Della Torre Rd",
    "sg:city":"Moe",
    "sg:classifiers":[
        {
            "category":"Retail",
            "subcategory":"Auto Repair",
            "type":"Services"
        }
    ],
    "sg:phone":"+61 3 5127 8726",
    "sg:postcode":"3825",
    "sg:province":"VIC",
    "sg:tags":[
        "clutch",
        "brake"
    ],
    "wof:name":"Moe Brake & Clutch Service",
    "wof:placetype":"venue"
},
  "geometry": {"coordinates":[146.26127600000001,-38.16798],"type":"Point"}
}