{
  "type": "Feature",
  "properties": {
    "addr:full":"5 Carcoola St Nollamara WA 6061",
    "addr:housenumber":"5",
    "addr:postcode":"6061",
    "addr:street":"Carcoola St",
    "iso:country":"AU",
    "sg:address":"5 Carcoola St",
    "sg:city":"Nollamara",
    "sg:classifiers":[
        {
            "category":"Social Services",
            "subcategory":"Child Care",
            "type":"Services"
        }
    ],
    "sg:phone":"+61 8 9349 1891",
    "sg:postcode":"6061",
    "sg:province":"WA",
    "wof:name":"Child Health Services",
    "wof:placetype":"venue"
},
  "geometry": {"coordinates":[115.84237670900001,-31.88032341],"type":"Point"}
}