{
  "type": "Feature",
  "properties": {
    "addr:full":"416 Oxford St Mall Bondi Junction NSW 2022",
    "addr:housenumber":"416",
    "addr:postcode":"2022",
    "addr:street":"Oxford St Mall",
    "iso:country":"AU",
    "sg:address":"416 Oxford St",
    "sg:city":"Mall Bondi Junction",
    "sg:classifiers":[
        {
            "category":"Health Services",
            "subcategory":"Doctor",
            "type":"Services"
        }
    ],
    "sg:phone":"+61 2 9369 3383",
    "sg:postcode":"2022",
    "sg:province":"NSW",
    "sg:tags":[
        "podiatrist"
    ],
    "wof:name":"Jedynak Ted",
    "wof:placetype":"venue"
},
  "geometry": {"coordinates":[151.24818420400001,-33.8917884827],"type":"Point"}
}