{
  "type": "Feature",
  "properties": {
    "addr:full":"23 Doncaster East Rd Mitcham VIC 3132",
    "addr:housenumber":"23",
    "addr:postcode":"3132",
    "addr:street":"Doncaster East Rd",
    "iso:country":"AU",
    "sg:address":"23 Doncaster East Rd",
    "sg:city":"Mitcham",
    "sg:classifiers":[
        {
            "category":"Health Services",
            "subcategory":"Doctor",
            "type":"Services"
        }
    ],
    "sg:phone":"+61 3 9899 1200",
    "sg:postcode":"3132",
    "sg:province":"VIC",
    "sg:tags":[
        "medical",
        "practitioner"
    ],
    "wof:name":"Capell William D",
    "wof:placetype":"venue"
},
  "geometry": {"coordinates":[145.194122314,-37.8100738525],"type":"Point"}
}