{
  "type": "Feature",
  "properties": {
    "iso:country":"AU",
    "sg:address":"67 Pilkington St",
    "sg:city":"Garbutt",
    "sg:classifiers":[
        {
            "category":"Building & Trades",
            "subcategory":"Locksmith",
            "type":"Services"
        }
    ],
    "sg:phone":"+61 400 757 207",
    "sg:postcode":"4814",
    "sg:province":"QLD",
    "sg:tags":[
        "lock"
    ],
    "wof:name":"Jim Roberts Locksmiths",
    "wof:placetype":"venue"
},
  "geometry": {"coordinates":[146.76982100000001,-19.271948],"type":"Point"}
}