{
  "type": "Feature",
  "properties": {
    "addr:full":"PO Box 731 North Lakes QLD 4509",
    "addr:postcode":"4509",
    "iso:country":"AU",
    "sg:address":"PO Box 731",
    "sg:city":"North Lakes",
    "sg:classifiers":[
        {
            "category":"Professional",
            "type":"Services"
        }
    ],
    "sg:phone":"+61 7 3482 2619",
    "sg:postcode":"4509",
    "sg:province":"QLD",
    "sg:tags":[
        "shop",
        "fitting"
    ],
    "wof:name":"Comprehensive Building Solutions",
    "wof:placetype":"venue"
},
  "geometry": {"coordinates":[153.01353454599999,-27.2243404388],"type":"Point"}
}