{
  "type": "Feature",
  "properties": {
    "addr:full":"98 Abbotsford St West Melbourne VIC 3003",
    "addr:housenumber":"98",
    "addr:postcode":"3003",
    "addr:street":"Abbotsford St",
    "iso:country":"AU",
    "sg:address":"98 Abbotsford St",
    "sg:city":"West Melbourne",
    "sg:classifiers":[
        {
            "category":"Professional",
            "subcategory":"Employment Agencies",
            "type":"Services"
        }
    ],
    "sg:phone":"+61 3 9326 6658",
    "sg:postcode":"3003",
    "sg:province":"VIC",
    "wof:name":"W.I.S.E. Employment",
    "wof:placetype":"venue"
},
  "geometry": {"coordinates":[144.94515991200001,-37.8054542542],"type":"Point"}
}