{
  "type": "Feature",
  "properties": {
    "iso:country":"AU",
    "sg:address":"Factory 5/ 23 Peel St",
    "sg:city":"Eltham",
    "sg:classifiers":[
        {
            "category":"Retail",
            "subcategory":"Auto Repair",
            "type":"Services"
        }
    ],
    "sg:phone":"+61 412 815 734",
    "sg:postcode":"3095",
    "sg:province":"VIC",
    "sg:tags":[
        "electrical"
    ],
    "wof:name":"Eltham Auto Electrical",
    "wof:placetype":"venue"
},
  "geometry": {"coordinates":[145.140426636,-37.7200012207],"type":"Point"}
}