{
  "type": "Feature",
  "properties": {
    "addr:full":"8 Nabillia Ave Seaford VIC 3198",
    "addr:housenumber":"8",
    "addr:postcode":"3198",
    "addr:street":"Nabillia Ave",
    "iso:country":"AU",
    "sg:address":"8 Nabillia Ave",
    "sg:city":"Seaford",
    "sg:classifiers":[
        {
            "category":"Building & Trades",
            "subcategory":"Construction",
            "type":"Services"
        }
    ],
    "sg:phone":"+61 419 112 155",
    "sg:postcode":"3198",
    "sg:province":"VIC",
    "sg:tags":[
        "repairing",
        "window"
    ],
    "wof:name":"A Help in a Hurry",
    "wof:placetype":"venue"
},
  "geometry": {"coordinates":[145.12954711899999,-38.0885162354],"type":"Point"}
}