{
  "type": "Feature",
  "properties": {
    "iso:country":"AU",
    "sg:address":"Suite 4, 72A Great North Rd",
    "sg:city":"Five Dock",
    "sg:classifiers":[
        {
            "category":"Professional",
            "subcategory":"Engineering",
            "type":"Services"
        }
    ],
    "sg:phone":"+61 2 9713 5351",
    "sg:postcode":"2046",
    "sg:province":"NSW",
    "sg:tags":[
        "consulting",
        "engineer"
    ],
    "wof:name":"Elevator Management Services",
    "wof:placetype":"venue"
},
  "geometry": {"coordinates":[151.12956199999999,-33.869602],"type":"Point"}
}