{
  "type": "Feature",
  "properties": {
    "iso:country":"AU",
    "sg:address":"13 Erskine Rd",
    "sg:city":"Taren Point",
    "sg:classifiers":[
        {
            "category":"Home & Garden",
            "subcategory":"Garden Supply",
            "type":"Retail Goods"
        }
    ],
    "sg:phone":"+61 2 9525 3299",
    "sg:postcode":"2229",
    "sg:province":"NSW",
    "sg:tags":[
        "landscape"
    ],
    "wof:name":"Bransons Building Materials",
    "wof:placetype":"venue"
},
  "geometry": {"coordinates":[151.12197875999999,-34.0252532959],"type":"Point"}
}