{
  "type": "Feature",
  "properties": {
    "addr:full":"13 Finlayson St Lane Cove NSW 2066",
    "addr:housenumber":"13",
    "addr:postcode":"2066",
    "addr:street":"Finlayson St",
    "iso:country":"AU",
    "sg:address":"13 Finlayson St",
    "sg:city":"Lane Cove",
    "sg:classifiers":[
        {
            "category":"Building & Trades",
            "subcategory":"Cleaning & Sanitation",
            "type":"Services"
        }
    ],
    "sg:phone":"+61 2 9427 2802",
    "sg:postcode":"2066",
    "sg:province":"NSW",
    "sg:tags":[
        "grease",
        "trap"
    ],
    "wof:name":"Able Liquid Waste Pty Ltd",
    "wof:placetype":"venue"
},
  "geometry": {"coordinates":[151.167678833,-33.8133125305],"type":"Point"}
}