{
  "type": "Feature",
  "properties": {
    "addr:full":"RMB 4637 Millards Rd Heywood VIC 3304",
    "addr:postcode":"3304",
    "addr:street":"Millards Rd",
    "iso:country":"AU",
    "sg:address":"RMB 4637 Millards Rd",
    "sg:city":"Heywood",
    "sg:classifiers":[
        {
            "category":"Shopping",
            "subcategory":"Pets & Pet Supplies",
            "type":"Retail Goods"
        }
    ],
    "sg:phone":"+61 408 527 232",
    "sg:postcode":"3304",
    "sg:province":"VIC",
    "sg:tags":[
        "food"
    ],
    "wof:name":"Southwest Pet Foods",
    "wof:placetype":"venue"
},
  "geometry": {"coordinates":[141.81350707999999,-38.1152763367],"type":"Point"}
}