{
  "type": "Feature",
  "properties": {
    "addr:full":"99 Argyle St Fitzroy VIC 3065",
    "addr:housenumber":"99",
    "addr:postcode":"3065",
    "addr:street":"Argyle St",
    "iso:country":"AU",
    "sg:address":"99 Argyle St",
    "sg:city":"Fitzroy",
    "sg:classifiers":[
        {
            "category":"Real Estate",
            "subcategory":"Architect",
            "type":"Services"
        }
    ],
    "sg:phone":"+61 3 9419 2836",
    "sg:postcode":"3065",
    "sg:province":"VIC",
    "wof:name":"Dance S J",
    "wof:placetype":"venue"
},
  "geometry": {"coordinates":[144.97874450699999,-37.7973937988],"type":"Point"}
}