{
  "type": "Feature",
  "properties": {
    "iso:country":"AU",
    "sg:address":"Stuart Hwy",
    "sg:city":"Batchelor",
    "sg:classifiers":[
        {
            "category":"Farming",
            "subcategory":"Farm",
            "type":"Manufacturing & Wholesale Goods"
        }
    ],
    "sg:phone":"+61 8 8976 0072",
    "sg:postcode":"0845",
    "sg:province":"NT",
    "sg:tags":[
        "farmer"
    ],
    "wof:name":"Coomalie Farm",
    "wof:placetype":"venue"
},
  "geometry": {"coordinates":[131.105102539,-13.0708379745],"type":"Point"}
}