{
  "type": "Feature",
  "properties": {
    "addr:full":"38 Illawarra St Everton Hills QLD 4053",
    "addr:housenumber":"38",
    "addr:postcode":"4053",
    "addr:street":"Illawarra St",
    "iso:country":"AU",
    "sg:address":"38 Illawarra St",
    "sg:city":"Everton Hills",
    "sg:classifiers":[
        {
            "category":"Taxi",
            "type":"Transportation"
        }
    ],
    "sg:phone":"+61 7 3855 3838",
    "sg:postcode":"4053",
    "sg:province":"QLD",
    "sg:tags":[
        "cab"
    ],
    "wof:name":"Gardners",
    "wof:placetype":"venue"
},
  "geometry": {"coordinates":[152.977493286,-27.3969745636],"type":"Point"}
}