{
  "type": "Feature",
  "properties": {
    "iso:country":"AU",
    "sg:address":"119 Magellan St",
    "sg:city":"Lismore",
    "sg:classifiers":[
        {
            "category":"Shopping",
            "subcategory":"Music",
            "type":"Retail Goods"
        }
    ],
    "sg:phone":"+61 2 6621 2606",
    "sg:postcode":"2480",
    "sg:province":"NSW",
    "sg:tags":[
        "instrument",
        "musical"
    ],
    "wof:name":"Instrumental As Anything",
    "wof:placetype":"venue"
},
  "geometry": {"coordinates":[153.27871704099999,-28.8104000092],"type":"Point"}
}