{
  "type": "Feature",
  "properties": {
    "addr:full":"456 Brighton Rd Brighton SA 5048",
    "addr:housenumber":"456",
    "addr:postcode":"5048",
    "addr:street":"Brighton Rd",
    "iso:country":"AU",
    "sg:address":"456 Brighton Rd",
    "sg:city":"Brighton",
    "sg:classifiers":[
        {
            "category":"Real Estate",
            "subcategory":"Real Estate Agent",
            "type":"Services"
        }
    ],
    "sg:phone":"+61 8 8298 6999",
    "sg:postcode":"5048",
    "sg:province":"SA",
    "wof:name":"Century 21 Associates Brighton",
    "wof:placetype":"venue"
},
  "geometry": {"coordinates":[138.52323899999999,-35.018246],"type":"Point"}
}