{
  "type": "Feature",
  "properties": {
    "iso:country":"AU",
    "sg:address":"2c Rofe St",
    "sg:city":"Leichhardt",
    "sg:classifiers":[
        {
            "category":"Manufacturing",
            "subcategory":"Tools & Machinery",
            "type":"Manufacturing & Wholesale Goods"
        }
    ],
    "sg:phone":"+61 2 9569 2445",
    "sg:postcode":"2040",
    "sg:province":"NSW",
    "sg:tags":[
        "reconditioners"
    ],
    "wof:name":"Davidson Machine Tools",
    "wof:placetype":"venue"
},
  "geometry": {"coordinates":[151.155304,-33.887753],"type":"Point"}
}