{
  "type": "Feature",
  "properties": {
    "addr:full":"71- 73 Lithgow St St Leonards NSW 2065",
    "addr:housenumber":"73",
    "addr:postcode":"2065",
    "addr:street":"Lithgow St",
    "iso:country":"AU",
    "sg:address":"71- 73 Lithgow St",
    "sg:city":"St Leonards",
    "sg:classifiers":[
        {
            "category":"Health Services",
            "subcategory":"Dentist",
            "type":"Services"
        }
    ],
    "sg:phone":"+61 2 8436 9900",
    "sg:postcode":"2065",
    "sg:province":"NSW",
    "wof:name":"Australian Dental Association (NSW Branch) Ltd The",
    "wof:placetype":"venue"
},
  "geometry": {"coordinates":[151.194915772,-33.8241119385],"type":"Point"}
}