{
  "type": "Feature",
  "properties": {
    "addr:full":"40 Lake Rd Stawell VIC 3380",
    "addr:housenumber":"40",
    "addr:postcode":"3380",
    "addr:street":"Lake Rd",
    "iso:country":"AU",
    "sg:address":"40 Lake Rd",
    "sg:city":"Stawell",
    "sg:classifiers":[
        {
            "category":"Wholesale",
            "subcategory":"Machinery & Supplies",
            "type":"Manufacturing & Wholesale Goods"
        }
    ],
    "sg:phone":"+61 3 5358 2857",
    "sg:postcode":"3380",
    "sg:province":"VIC",
    "sg:tags":[
        "equipment",
        "hydraulic"
    ],
    "wof:name":"Wimmera Hydraulics",
    "wof:placetype":"venue"
},
  "geometry": {"coordinates":[142.76414489699999,-37.0565986633],"type":"Point"}
}