{
  "type": "Feature",
  "properties": {
    "addr:full":"Factory 2, 90 Clarke St Kilmore VIC 3764",
    "addr:housenumber":"90",
    "addr:postcode":"3764",
    "addr:street":"Clarke St",
    "iso:country":"AU",
    "sg:address":"Factory 2, 90 Clarke St",
    "sg:city":"Kilmore",
    "sg:classifiers":[
        {
            "category":"Banks & Credit Unions",
            "subcategory":"Investment Brokerage",
            "type":"Services"
        }
    ],
    "sg:phone":"+61 3 5781 0531",
    "sg:postcode":"3764",
    "sg:province":"VIC",
    "sg:tags":[
        "radiator",
        "motor"
    ],
    "wof:name":"Radiators- R - Us",
    "wof:placetype":"venue"
},
  "geometry": {"coordinates":[144.95579528799999,-37.2875709534],"type":"Point"}
}