{
  "type": "Feature",
  "properties": {
    "iso:country":"AU",
    "sg:address":"93 Gardiner St",
    "sg:city":"Moora",
    "sg:classifiers":[
        {
            "category":"Home & Garden",
            "subcategory":"Hardware",
            "type":"Retail Goods"
        }
    ],
    "sg:phone":"+61 8 9651 1012",
    "sg:postcode":"6510",
    "sg:province":"WA",
    "sg:tags":[
        "tarpaulin"
    ],
    "wof:name":"Moora Sports",
    "wof:placetype":"venue"
},
  "geometry": {"coordinates":[116.009117,-30.638836],"type":"Point"}
}