{
  "type": "Feature",
  "properties": {
    "addr:full":"16 Porrende St Narellan NSW 2567",
    "addr:housenumber":"16",
    "addr:postcode":"2567",
    "addr:street":"Porrende St",
    "iso:country":"AU",
    "sg:address":"16 Porrende St",
    "sg:city":"Narellan",
    "sg:classifiers":[
        {
            "category":"Manufacturing",
            "subcategory":"Metals",
            "type":"Manufacturing & Wholesale Goods"
        }
    ],
    "sg:phone":"+61 2 4647 0100",
    "sg:postcode":"2567",
    "sg:province":"NSW",
    "sg:tags":[
        "sheet",
        "worker"
    ],
    "wof:name":"Comfrig Sheetmetal",
    "wof:placetype":"venue"
},
  "geometry": {"coordinates":[150.729125977,-34.0325126648],"type":"Point"}
}