{
  "type": "Feature",
  "properties": {
    "addr:full":"1 Loudoun Rd Dalby QLD 4405",
    "addr:housenumber":"1",
    "addr:postcode":"4405",
    "addr:street":"Loudoun Rd",
    "iso:country":"AU",
    "sg:address":"1 Loudoun Rd",
    "sg:city":"Dalby",
    "sg:classifiers":[
        {
            "category":"Utilities",
            "subcategory":"Natural Gas",
            "type":"Services"
        }
    ],
    "sg:phone":"+61 13 21 80",
    "sg:postcode":"4405",
    "sg:province":"QLD",
    "sg:tags":[
        "supplier"
    ],
    "wof:name":"Kleenheat Gas",
    "wof:placetype":"venue"
},
  "geometry": {"coordinates":[151.248443603,-27.1860980988],"type":"Point"}
}