{
  "type": "Feature",
  "properties": {
    "addr:full":"PO Box 1183 Gosford NSW 2250",
    "addr:postcode":"2250",
    "iso:country":"AU",
    "sg:address":"PO Box 1183",
    "sg:city":"Gosford",
    "sg:classifiers":[
        {
            "category":"Arena",
            "subcategory":"Sports Club",
            "type":"Entertainment"
        }
    ],
    "sg:phone":"+61 2 4363 2028",
    "sg:postcode":"2250",
    "sg:province":"NSW",
    "sg:tags":[
        "tour",
        "holiday"
    ],
    "wof:name":"Central Coast Bushworks",
    "wof:placetype":"venue"
},
  "geometry": {"coordinates":[151.34249877900001,-33.4237213135],"type":"Point"}
}