{
  "type": "Feature",
  "properties": {
    "addr:full":"26 Deane St Charters Towers QLD 4820",
    "addr:housenumber":"26",
    "addr:postcode":"4820",
    "addr:street":"Deane St",
    "iso:country":"AU",
    "sg:address":"26 Deane St",
    "sg:city":"Charters Towers",
    "sg:classifiers":[
        {
            "category":"Building & Trades",
            "subcategory":"Construction",
            "type":"Services"
        }
    ],
    "sg:phone":"+61 7 4787 4021",
    "sg:postcode":"4820",
    "sg:province":"QLD",
    "sg:tags":[
        "polishing",
        "sanding",
        "floor"
    ],
    "wof:name":"Heritage Floors",
    "wof:placetype":"venue"
},
  "geometry": {"coordinates":[146.258636,-20.075752],"type":"Point"}
}