{
  "type": "Feature",
  "properties": {
    "addr:full":"Newell Hwy Gilgandra NSW 2827",
    "addr:postcode":"2827",
    "addr:street":"Newell Hwy",
    "iso:country":"AU",
    "sg:address":"Newell Hwy",
    "sg:city":"Gilgandra",
    "sg:classifiers":[
        {
            "category":"Travel",
            "subcategory":"Hotels & Motels",
            "type":"Entertainment"
        }
    ],
    "sg:phone":"+61 2 6847 1271",
    "sg:postcode":"2827",
    "sg:province":"NSW",
    "wof:name":"Bungalow Motel",
    "wof:placetype":"venue"
},
  "geometry": {"coordinates":[148.66531372099999,-31.7130661011],"type":"Point"}
}