{
  "type": "Feature",
  "properties": {
    "addr:full":"131 High St Prahran VIC 3181",
    "addr:housenumber":"131",
    "addr:postcode":"3181",
    "addr:street":"High St",
    "iso:country":"AU",
    "sg:address":"131 High St",
    "sg:city":"Prahran",
    "sg:classifiers":[
        {
            "category":"Personal",
            "subcategory":"Massage",
            "type":"Services"
        }
    ],
    "sg:phone":"+61 3 9510 3555",
    "sg:postcode":"3181",
    "sg:province":"VIC",
    "sg:tags":[
        "therapy"
    ],
    "wof:name":"The Sports Injury Repair Centre",
    "wof:placetype":"venue"
},
  "geometry": {"coordinates":[144.991333008,-37.8514251709],"type":"Point"}
}