{
  "type": "Feature",
  "properties": {
    "addr:full":"27 Meeks Rd Marrickville NSW 1475",
    "addr:housenumber":"27",
    "addr:postcode":"1475",
    "addr:street":"Meeks Rd",
    "iso:country":"AU",
    "sg:address":"27 Meeks Rd",
    "sg:city":"Marrickville",
    "sg:classifiers":[
        {
            "category":"Manufacturing",
            "subcategory":"Furniture",
            "type":"Manufacturing & Wholesale Goods"
        }
    ],
    "sg:phone":"+61 402 028 707",
    "sg:postcode":"1475",
    "sg:province":"NSW",
    "sg:tags":[
        "builder",
        "designer",
        "custom"
    ],
    "wof:name":"Bibliotheque",
    "wof:placetype":"venue"
},
  "geometry": {"coordinates":[151.162277222,-33.9113311768],"type":"Point"}
}