{
  "type": "Feature",
  "properties": {
    "iso:country":"AU",
    "sg:address":"PO Box 4008",
    "sg:city":"Rockhampton",
    "sg:classifiers":[
        {
            "category":"Building & Trades",
            "subcategory":"Construction",
            "type":"Services"
        }
    ],
    "sg:phone":"+61 419 786 060",
    "sg:postcode":"4700",
    "sg:province":"QLD",
    "sg:tags":[
        "concrete",
        "contractor"
    ],
    "wof:name":"Cosmetic Concrete",
    "wof:placetype":"venue"
},
  "geometry": {"coordinates":[150.50942993199999,-23.4106502533],"type":"Point"}
}