{
  "type": "Feature",
  "properties": {
    "iso:country":"AU",
    "sg:address":"2- 12 Newspaper Pl",
    "sg:city":"Maroochydore",
    "sg:classifiers":[
        {
            "category":"Professional",
            "subcategory":"Art Services",
            "type":"Services"
        }
    ],
    "sg:phone":"+61 7 5479 1155",
    "sg:postcode":"4558",
    "sg:province":"QLD",
    "sg:tags":[
        "picture",
        "frame",
        "framing"
    ],
    "wof:name":"Art Madd",
    "wof:placetype":"venue"
},
  "geometry": {"coordinates":[153.091705322,-26.667804718],"type":"Point"}
}