{
  "type": "Feature",
  "properties": {
    "addr:full":"Broadford Crs Macleod VIC 3085",
    "addr:postcode":"3085",
    "addr:street":"Broadford Crs",
    "iso:country":"AU",
    "sg:address":"Broadford Crs",
    "sg:city":"Macleod",
    "sg:classifiers":[
        {
            "category":"Social Services",
            "subcategory":"Retirement Home",
            "type":"Services"
        }
    ],
    "sg:phone":"+61 3 9434 4555",
    "sg:postcode":"3085",
    "sg:province":"VIC",
    "sg:tags":[
        "village"
    ],
    "wof:name":"Macleod Village",
    "wof:placetype":"venue"
},
  "geometry": {"coordinates":[145.07305908199999,-37.7228889465],"type":"Point"}
}