{
  "type": "Feature",
  "properties": {
    "addr:full":"143 Charlotte St Brisbane QLD 4000",
    "addr:housenumber":"143",
    "addr:postcode":"4000",
    "addr:street":"Charlotte St",
    "iso:country":"AU",
    "sg:address":"143 Charlotte St",
    "sg:city":"Brisbane",
    "sg:classifiers":[
        {
            "category":"Professional",
            "subcategory":"Business Services",
            "type":"Services"
        }
    ],
    "sg:phone":"+61 7 3211 7710",
    "sg:postcode":"4000",
    "sg:province":"QLD",
    "sg:tags":[
        "record",
        "management",
        "storage"
    ],
    "sg:website":"http://www.dataimagegroup.com.au",
    "wof:name":"The Data Image Group",
    "wof:placetype":"venue"
},
  "geometry": {"coordinates":[153.02775573700001,-27.4705581665],"type":"Point"}
}