{
  "type": "Feature",
  "properties": {
    "iso:country":"AU",
    "sg:address":"PO Box 6105",
    "sg:city":"East Perth",
    "sg:classifiers":[
        {
            "category":"Building & Trades",
            "subcategory":"Construction",
            "type":"Services"
        }
    ],
    "sg:phone":"+61 411 209 350",
    "sg:postcode":"6892",
    "sg:province":"WA",
    "sg:tags":[
        "bitumen",
        "paving",
        "asphalt"
    ],
    "wof:name":"Harpave Bitumen",
    "wof:placetype":"venue"
},
  "geometry": {"coordinates":[115.87187194800001,-31.9584293365],"type":"Point"}
}