{
  "type": "Feature",
  "properties": {
    "iso:country":"AU",
    "sg:address":"Shop 2002 Knox City Shopng Cntr, 425 Burwood Hwy",
    "sg:city":"Wantirna South",
    "sg:classifiers":[
        {
            "category":"Wholesale",
            "subcategory":"Apparel",
            "type":"Manufacturing & Wholesale Goods"
        }
    ],
    "sg:phone":"+61 3 9801 9311",
    "sg:postcode":"3152",
    "sg:province":"VIC",
    "sg:tags":[
        "wholesaler",
        "mfrs",
        "dress"
    ],
    "wof:name":"Ravish",
    "wof:placetype":"venue"
},
  "geometry": {"coordinates":[145.23806762699999,-37.8702659607],"type":"Point"}
}