{
  "type": "Feature",
  "properties": {
    "addr:full":"Factory 2 / 14 Attercliffe St Coburg North VIC 3058",
    "addr:housenumber":"/ 14",
    "addr:postcode":"3058",
    "addr:street":"Attercliffe St",
    "iso:country":"AU",
    "sg:address":"Factory 2 / 14 Attercliffe St",
    "sg:city":"Coburg North",
    "sg:classifiers":[
        {
            "category":"Manufacturing",
            "subcategory":"Furniture",
            "type":"Manufacturing & Wholesale Goods"
        }
    ],
    "sg:phone":"+61 3 9354 5712",
    "sg:postcode":"3058",
    "sg:province":"VIC",
    "sg:tags":[
        "builder",
        "designer",
        "custom"
    ],
    "wof:name":"Gamma Doura",
    "wof:placetype":"venue"
},
  "geometry": {"coordinates":[144.94662475600001,-37.7290802002],"type":"Point"}
}