{
  "type": "Feature",
  "properties": {
    "addr:full":"63 Lewisham Rd Windsor VIC 3181",
    "addr:housenumber":"63",
    "addr:postcode":"3181",
    "addr:street":"Lewisham Rd",
    "iso:country":"AU",
    "sg:address":"63 Lewisham Rd",
    "sg:city":"Windsor",
    "sg:classifiers":[
        {
            "category":"Professional",
            "subcategory":"Art Services",
            "type":"Services"
        }
    ],
    "sg:phone":"+61 3 9533 6842",
    "sg:postcode":"3181",
    "sg:province":"VIC",
    "sg:tags":[
        "interior",
        "decorator"
    ],
    "wof:name":"Phillip Chester Design Pty Ltd",
    "wof:placetype":"venue"
},
  "geometry": {"coordinates":[144.99937439000001,-37.8536949158],"type":"Point"}
}