{
  "type": "Feature",
  "properties": {
    "addr:full":"Shop 7, Portside Wharf, 39 Hercules St Hamilton QLD 4007",
    "addr:housenumber":"shop 7;39",
    "addr:postcode":"4007",
    "addr:street":"Portside Wharf;Hercules St",
    "iso:country":"AU",
    "sg:address":"Shop 7, Portside Wharf, 39 Hercules St",
    "sg:city":"Hamilton",
    "sg:classifiers":[
        {
            "category":"Personal",
            "subcategory":"Beauty Salon",
            "type":"Services"
        }
    ],
    "sg:phone":"+61 7 3868 2500",
    "sg:postcode":"4007",
    "sg:province":"QLD",
    "sg:website":"http://www.hamilton.ellabache.com.au",
    "wof:name":"Ella Bache Hamilton At Portside",
    "wof:placetype":"venue"
},
  "geometry": {"coordinates":[153.068085,-27.439047],"type":"Point"}
}