{
  "type": "Feature",
  "properties": {
    "addr:full":"8 Moonbi St Brendale QLD 4500",
    "addr:housenumber":"8",
    "addr:postcode":"4500",
    "addr:street":"Moonbi St",
    "iso:country":"AU",
    "sg:address":"8 Moonbi St",
    "sg:city":"Brendale",
    "sg:classifiers":[
        {
            "category":"Wholesale",
            "subcategory":"Machinery & Supplies",
            "type":"Manufacturing & Wholesale Goods"
        }
    ],
    "sg:phone":"+61 7 3881 0202",
    "sg:postcode":"4500",
    "sg:province":"QLD",
    "sg:tags":[
        "equipment",
        "hydraulic"
    ],
    "sg:website":"http://www.pacific-hyd.com.au",
    "wof:name":"Pacific Hydraulics",
    "wof:placetype":"venue"
},
  "geometry": {"coordinates":[152.98934936500001,-27.322347641],"type":"Point"}
}