{
  "type": "Feature",
  "properties": {
    "addr:full":"Cnr Napper Rd & Greenacre Drv Arundel QLD 4214",
    "addr:postcode":"4214",
    "addr:street":"Cnr Napper Rd & Greenacre Drv",
    "iso:country":"AU",
    "sg:address":"Cnr Napper Rd & Greenacre Drv",
    "sg:city":"Arundel",
    "sg:classifiers":[
        {
            "category":"Education",
            "subcategory":"Kindergarten",
            "type":"Public Place"
        }
    ],
    "sg:phone":"+61 7 5594 0377",
    "sg:postcode":"4214",
    "sg:province":"QLD",
    "sg:tags":[
        "pre-schools"
    ],
    "wof:name":"Sunkids",
    "wof:placetype":"venue"
},
  "geometry": {"coordinates":[153.34703064000001,-27.9485607147],"type":"Point"}
}