{
  "type": "Feature",
  "properties": {
    "addr:full":"5 Watkins St West Wallsend NSW 2286",
    "addr:housenumber":"5",
    "addr:postcode":"2286",
    "addr:street":"Watkins St",
    "iso:country":"AU",
    "sg:address":"5 Watkins St",
    "sg:city":"West Wallsend",
    "sg:classifiers":[
        {
            "category":"Shopping",
            "subcategory":"Music",
            "type":"Retail Goods"
        }
    ],
    "sg:phone":"+61 2 4953 2465",
    "sg:postcode":"2286",
    "sg:province":"NSW",
    "sg:tags":[
        "instrument",
        "musical"
    ],
    "wof:name":"Curran Peter J",
    "wof:placetype":"venue"
},
  "geometry": {"coordinates":[151.58189392099999,-32.9080657959],"type":"Point"}
}