{
  "type": "Feature",
  "properties": {
    "addr:full":"2/ 401 Francis St Brooklyn VIC 3025",
    "addr:housenumber":"/ 401",
    "addr:postcode":"3025",
    "addr:street":"Francis St",
    "iso:country":"AU",
    "sg:address":"2/ 401 Francis St",
    "sg:city":"Brooklyn",
    "sg:classifiers":[
        {
            "category":"Government",
            "subcategory":"Fire Station",
            "type":"Public Place"
        }
    ],
    "sg:phone":"+61 3 9318 9717",
    "sg:postcode":"3025",
    "sg:province":"VIC",
    "sg:tags":[
        "equipment",
        "protection",
        "consultant"
    ],
    "wof:name":"AAA Passive Fire Services",
    "wof:placetype":"venue"
},
  "geometry": {"coordinates":[144.85699500000001,-37.817497],"type":"Point"}
}