{
  "type": "Feature",
  "properties": {
    "addr:full":"31 Whittell Crs Florey ACT 2615",
    "addr:housenumber":"31",
    "addr:postcode":"2615",
    "addr:street":"Whittell Crs",
    "iso:country":"AU",
    "sg:address":"31 Whittell Crs",
    "sg:city":"Florey",
    "sg:classifiers":[
        {
            "category":"Organizations",
            "subcategory":"Professional Association",
            "type":"Services"
        }
    ],
    "sg:phone":"+61 2 6259 0619",
    "sg:postcode":"2615",
    "sg:province":"ACT",
    "sg:tags":[
        "web",
        "internet"
    ],
    "wof:name":"dodt.com Studios",
    "wof:placetype":"venue"
},
  "geometry": {"coordinates":[149.05523681599999,-35.2267799377],"type":"Point"}
}