{
  "type": "Feature",
  "properties": {
    "iso:country":"AU",
    "sg:address":"67a Matthews Ave",
    "sg:city":"Airport West",
    "sg:classifiers":[
        {
            "category":"Wholesale",
            "subcategory":"Home Furnishings",
            "type":"Manufacturing & Wholesale Goods"
        }
    ],
    "sg:phone":"+61 3 9338 3834",
    "sg:postcode":"3042",
    "sg:province":"VIC",
    "sg:tags":[
        "wholesaler",
        "bedding",
        "mfrs",
        "bed"
    ],
    "wof:name":"Bed Factory The",
    "wof:placetype":"venue"
},
  "geometry": {"coordinates":[144.89048767099999,-37.7261695862],"type":"Point"}
}