{
  "type": "Feature",
  "properties": {
    "addr:full":"Main Rd St Andrews VIC 3761",
    "addr:postcode":"3761",
    "addr:street":"Main Rd",
    "iso:country":"AU",
    "sg:address":"Main Rd",
    "sg:city":"St Andrews",
    "sg:classifiers":[
        {
            "category":"Building & Trades",
            "subcategory":"Construction",
            "type":"Services"
        }
    ],
    "sg:phone":"+61 418 321 630",
    "sg:postcode":"3761",
    "sg:province":"VIC",
    "sg:tags":[
        "plasterboard",
        "plasterer",
        "fixer"
    ],
    "wof:name":"Universal Plaster Co",
    "wof:placetype":"venue"
},
  "geometry": {"coordinates":[145.28773498499999,-37.5787086487],"type":"Point"}
}