{
  "type": "Feature",
  "properties": {
    "addr:full":"90 Cadogan St Carindale QLD 4152",
    "addr:housenumber":"90",
    "addr:postcode":"4152",
    "addr:street":"Cadogan St",
    "iso:country":"AU",
    "sg:address":"90 Cadogan St",
    "sg:city":"Carindale",
    "sg:classifiers":[
        {
            "category":"Manufacturing",
            "subcategory":"Glass & Minerals",
            "type":"Manufacturing & Wholesale Goods"
        }
    ],
    "sg:phone":"+61 7 3399 7551",
    "sg:postcode":"4152",
    "sg:province":"QLD",
    "sg:tags":[
        "repair",
        "fibreglass",
        "product"
    ],
    "wof:name":"Bathware Repairs",
    "wof:placetype":"venue"
},
  "geometry": {"coordinates":[153.11654663100001,-27.4975719452],"type":"Point"}
}