{
  "type": "Feature",
  "properties": {
    "addr:full":"147a Stawell Rd Horsham VIC 3400",
    "addr:housenumber":"147a",
    "addr:postcode":"3400",
    "addr:street":"Stawell Rd",
    "iso:country":"AU",
    "sg:address":"147a Stawell Rd",
    "sg:city":"Horsham",
    "sg:classifiers":[
        {
            "category":"Shopping",
            "subcategory":"Computers & Home Electronics",
            "type":"Retail Goods"
        }
    ],
    "sg:phone":"+61 3 5381 0199",
    "sg:postcode":"3400",
    "sg:province":"VIC",
    "sg:tags":[
        "equipment",
        "multimedia"
    ],
    "wof:name":"Mpmedia Solutions",
    "wof:placetype":"venue"
},
  "geometry": {"coordinates":[142.21286010700001,-36.7392463684],"type":"Point"}
}