{
  "type": "Feature",
  "properties": {
    "addr:full":"13 Chapel St Lynbrook VIC 3975",
    "addr:housenumber":"13",
    "addr:postcode":"3975",
    "addr:street":"Chapel St",
    "iso:country":"AU",
    "sg:address":"13 Chapel St",
    "sg:city":"Lynbrook",
    "sg:classifiers":[
        {
            "category":"Building & Trades",
            "subcategory":"Construction",
            "type":"Services"
        }
    ],
    "sg:phone":"+61 3 8788 4350",
    "sg:postcode":"3975",
    "sg:province":"VIC",
    "sg:tags":[
        "fencing",
        "contractor"
    ],
    "wof:name":"ARC Fences",
    "wof:placetype":"venue"
},
  "geometry": {"coordinates":[145.24969482399999,-38.0401191711],"type":"Point"}
}