{
  "type": "Feature",
  "properties": {
    "addr:full":"PO Box 2477 Fortitude Valley Bus Centr QLD 4006",
    "addr:postcode":"4006",
    "iso:country":"AU",
    "sg:address":"PO Box 2477",
    "sg:city":"Fortitude Valley Bus Centr",
    "sg:classifiers":[
        {
            "category":"Organizations",
            "subcategory":"Professional Association",
            "type":"Services"
        }
    ],
    "sg:phone":"+61 7 3257 3927",
    "sg:postcode":"4006",
    "sg:province":"QLD",
    "sg:tags":[
        "organisation",
        "business"
    ],
    "wof:name":"Queensland Resident Accommodation Managers Association",
    "wof:placetype":"venue"
},
  "geometry": {"coordinates":[153.039672852,-27.4558525085],"type":"Point"}
}