{
  "type": "Feature",
  "properties": {
    "addr:full":"21 Vale St North Melbourne VIC 3051",
    "addr:housenumber":"21",
    "addr:postcode":"3051",
    "addr:street":"Vale St",
    "iso:country":"AU",
    "sg:address":"21 Vale St",
    "sg:city":"North Melbourne",
    "sg:classifiers":[
        {
            "category":"Organizations",
            "subcategory":"Professional Association",
            "type":"Services"
        }
    ],
    "sg:phone":"+61 3 9696 5190",
    "sg:postcode":"3051",
    "sg:province":"VIC",
    "sg:tags":[
        "organisation",
        "business"
    ],
    "wof:name":"Society Of Automotive Engineers Australasia",
    "wof:placetype":"venue"
},
  "geometry": {"coordinates":[144.953399658,-37.7998733521],"type":"Point"}
}