{
  "type": "Feature",
  "properties": {
    "iso:country":"AU",
    "sg:address":"4 Basil St",
    "sg:city":"Dromana",
    "sg:classifiers":[
        {
            "category":"Building & Trades",
            "subcategory":"Cleaning & Sanitation",
            "type":"Services"
        }
    ],
    "sg:phone":"+61 3 5981 4226",
    "sg:postcode":"3936",
    "sg:province":"VIC",
    "sg:tags":[
        "window"
    ],
    "wof:name":"Coastline Window Cleaning Services",
    "wof:placetype":"venue"
},
  "geometry": {"coordinates":[144.97364807100001,-38.3378143311],"type":"Point"}
}