{
  "type": "Feature",
  "properties": {
    "addr:full":"116 Fryers St Shepparton VIC 3630",
    "addr:housenumber":"116",
    "addr:postcode":"3630",
    "addr:street":"Fryers St",
    "iso:country":"AU",
    "sg:address":"116 Fryers St",
    "sg:city":"Shepparton",
    "sg:classifiers":[
        {
            "category":"Fast Food",
            "type":"Food & Drink"
        }
    ],
    "sg:phone":"+61 3 5821 8102",
    "sg:postcode":"3630",
    "sg:province":"VIC",
    "sg:tags":[
        "away",
        "take"
    ],
    "wof:name":"Star Bowl Restaurant",
    "wof:placetype":"venue"
},
  "geometry": {"coordinates":[145.402801514,-36.3796081543],"type":"Point"}
}