{
  "type": "Feature",
  "properties": {
    "addr:full":"46 Jonson St Byron Bay NSW 2481",
    "addr:housenumber":"46",
    "addr:postcode":"2481",
    "addr:street":"Jonson St",
    "iso:country":"AU",
    "sg:address":"46 Jonson St",
    "sg:city":"Byron Bay",
    "sg:classifiers":[
        {
            "category":"Shopping",
            "subcategory":"Clothing, Apparel, & Fashions",
            "type":"Retail Goods"
        }
    ],
    "sg:phone":"+61 401 374 930",
    "sg:postcode":"2481",
    "sg:province":"NSW",
    "sg:tags":[
        "lady",
        "wear"
    ],
    "wof:name":"Stoked Byron",
    "wof:placetype":"venue"
},
  "geometry": {"coordinates":[153.61285400400001,-28.6479625702],"type":"Point"}
}