{
  "type": "Feature",
  "properties": {
    "iso:country":"AU",
    "sg:address":"102 Bathurst St",
    "sg:city":"Condobolin",
    "sg:classifiers":[
        {
            "category":"Fast Food",
            "type":"Food & Drink"
        }
    ],
    "sg:phone":"+61 2 6895 3736",
    "sg:postcode":"2877",
    "sg:province":"NSW",
    "sg:tags":[
        "away",
        "take"
    ],
    "wof:name":"Yetties Takeaway",
    "wof:placetype":"venue"
},
  "geometry": {"coordinates":[147.146591,-33.088184],"type":"Point"}
}