{
  "type": "Feature",
  "properties": {
    "iso:country":"AU",
    "sg:address":"5 Trevor St",
    "sg:city":"Beachmere",
    "sg:classifiers":[
        {
            "category":"Building & Trades",
            "subcategory":"Landscaping Services",
            "type":"Services"
        }
    ],
    "sg:phone":"+61 7 5496 8015",
    "sg:postcode":"4510",
    "sg:province":"QLD",
    "sg:tags":[
        "designer",
        "landscape",
        "contractor"
    ],
    "wof:name":"Jock Garden Edging",
    "wof:placetype":"venue"
},
  "geometry": {"coordinates":[153.049026,-27.137318],"type":"Point"}
}