{
  "type": "Feature",
  "properties": {
    "addr:full":"Unit 2 53 Landells Rd Pascoe Vale VIC 3044",
    "addr:housenumber":"53",
    "addr:postcode":"3044",
    "addr:street":"Landells Rd",
    "iso:country":"AU",
    "sg:address":"Unit 2 53 Landells Rd",
    "sg:city":"Pascoe Vale",
    "sg:classifiers":[
        {
            "category":"Food & Beverages",
            "subcategory":"Specialty",
            "type":"Retail Goods"
        }
    ],
    "sg:phone":"+61 3 9354 2131",
    "sg:postcode":"3044",
    "sg:province":"VIC",
    "sg:tags":[
        "product",
        "health"
    ],
    "wof:name":"Mission Nutrition",
    "wof:placetype":"venue"
},
  "geometry": {"coordinates":[144.94271850600001,-37.7274131775],"type":"Point"}
}