{
  "type": "Feature",
  "properties": {
    "addr:full":"Lot 2 Goulburn Valley Hwy Numurkah VIC 3636",
    "addr:postcode":"3636",
    "addr:street":"Valley Hwy",
    "iso:country":"AU",
    "sg:address":"Lot 2 Goulburn Valley Hwy",
    "sg:city":"Numurkah",
    "sg:classifiers":[
        {
            "category":"Professional",
            "type":"Services"
        }
    ],
    "sg:phone":"+61 3 5862 2622",
    "sg:postcode":"3636",
    "sg:province":"VIC",
    "sg:tags":[
        "transport"
    ],
    "wof:name":"Embridge Crest Pty Ltd",
    "wof:placetype":"venue"
},
  "geometry": {"coordinates":[145.43177795400001,-36.0883102417],"type":"Point"}
}