{
  "type": "Feature",
  "properties": {
    "addr:full":"Level 2 Suite 16 Wesley Medical Centre 40 Chasely Auchenflower QLD 4066",
    "addr:housenumber":"40",
    "addr:postcode":"4066",
    "addr:street":"Chasely",
    "iso:country":"AU",
    "sg:address":"Level 2 Suite 16 Wesley Medical Centre 40 Chasely",
    "sg:city":"Auchenflower",
    "sg:classifiers":[
        {
            "category":"Professional",
            "subcategory":"Management & Consulting",
            "type":"Services"
        }
    ],
    "sg:phone":"+61 414 883 463",
    "sg:postcode":"4066",
    "sg:province":"QLD",
    "sg:tags":[
        "consultant",
        "educational"
    ],
    "wof:name":"John Worthington",
    "wof:placetype":"venue"
},
  "geometry": {"coordinates":[152.997955322,-27.4771118164],"type":"Point"}
}