{
  "type": "Feature",
  "properties": {
    "addr:full":"Shp 3/ 206 Princess Hwy Pakenham VIC 3810",
    "addr:housenumber":"/ 206",
    "addr:postcode":"3810",
    "addr:street":"Princess Hwy",
    "iso:country":"AU",
    "sg:address":"Shp 3/ 206 Princess Hwy",
    "sg:city":"Pakenham",
    "sg:classifiers":[
        {
            "category":"Autos & Motor Vehicles",
            "subcategory":"Auto Supplies",
            "type":"Retail Goods"
        }
    ],
    "sg:phone":"+61 3 5940 1364",
    "sg:postcode":"3810",
    "sg:province":"VIC",
    "sg:tags":[
        "battery",
        "automotive"
    ],
    "wof:name":"Battery Zone",
    "wof:placetype":"venue"
},
  "geometry": {"coordinates":[145.46679700000001,-38.065388],"type":"Point"}
}