{
  "type": "Feature",
  "properties": {
    "iso:country":"AU",
    "sg:address":"Shop 140, Karrinyup Shopping Centre, Karrinyup Rd",
    "sg:city":"Karrinyup",
    "sg:classifiers":[
        {
            "category":"Shopping",
            "subcategory":"Clothing, Apparel, & Fashions",
            "type":"Retail Goods"
        }
    ],
    "sg:phone":"+61 8 9446 8297",
    "sg:postcode":"6018",
    "sg:province":"WA",
    "sg:tags":[
        "jean"
    ],
    "wof:name":"Westco Jeans Pty Ltd",
    "wof:placetype":"venue"
},
  "geometry": {"coordinates":[115.77133178699999,-31.8735256195],"type":"Point"}
}