{
  "type": "Feature",
  "properties": {
    "iso:country":"AU",
    "sg:address":"32 Bruce St",
    "sg:city":"Mallacoota",
    "sg:classifiers":[
        {
            "category":"Travel",
            "subcategory":"Hotels & Motels",
            "type":"Entertainment"
        }
    ],
    "sg:phone":"+61 3 5158 0223",
    "sg:postcode":"3892",
    "sg:province":"VIC",
    "wof:name":"Golden Chain Grevillea Grove Luxury Apartments",
    "wof:placetype":"venue"
},
  "geometry": {"coordinates":[149.75448608400001,-37.5575447083],"type":"Point"}
}