{
  "type": "Feature",
  "properties": {
    "addr:full":"14 Brewster St Mittagong NSW 2575",
    "addr:housenumber":"14",
    "addr:postcode":"2575",
    "addr:street":"Brewster St",
    "iso:country":"AU",
    "sg:address":"14 Brewster St",
    "sg:city":"Mittagong",
    "sg:classifiers":[
        {
            "category":"Building & Trades",
            "subcategory":"Construction",
            "type":"Services"
        }
    ],
    "sg:phone":"+61 2 4871 2072",
    "sg:postcode":"2575",
    "sg:province":"NSW",
    "sg:tags":[
        "ceiling"
    ],
    "wof:name":"Armstrong David Plastering",
    "wof:placetype":"venue"
},
  "geometry": {"coordinates":[150.438400269,-34.4521179199],"type":"Point"}
}