{
  "type": "Feature",
  "properties": {
    "addr:full":"Unit 3 244- 254 Horsley Rd Milperra NSW 2214",
    "addr:housenumber":"244 254",
    "addr:postcode":"2214",
    "addr:street":"Horsley Rd",
    "iso:country":"AU",
    "sg:address":"Unit 3 244- 254 Horsley Rd",
    "sg:city":"Milperra",
    "sg:classifiers":[
        {
            "category":"Education",
            "subcategory":"Dance Studio",
            "type":"Public Place"
        }
    ],
    "sg:phone":"+61 2 9771 5462",
    "sg:postcode":"2214",
    "sg:province":"NSW",
    "sg:tags":[
        "venue",
        "tuition"
    ],
    "wof:name":"Dance Studio",
    "wof:placetype":"venue"
},
  "geometry": {"coordinates":[150.994049072,-33.9435501099],"type":"Point"}
}