{
  "type": "Feature",
  "properties": {
    "addr:full":"52 Nebo Rd Mackay QLD 4740",
    "addr:housenumber":"52",
    "addr:postcode":"4740",
    "addr:street":"Nebo Rd",
    "iso:country":"AU",
    "sg:address":"52 Nebo Rd",
    "sg:city":"Mackay",
    "sg:classifiers":[
        {
            "category":"Travel",
            "subcategory":"Hotels & Motels",
            "type":"Entertainment"
        }
    ],
    "sg:phone":"+61 7 4951 2699",
    "sg:postcode":"4740",
    "sg:province":"QLD",
    "wof:name":"Alara Motor Inn",
    "wof:placetype":"venue"
},
  "geometry": {"coordinates":[149.16970800000001,-21.150141],"type":"Point"}
}