{
  "type": "Feature",
  "properties": {
    "addr:full":"2 / 9 Rouse Rd Mandurah WA 6210",
    "addr:housenumber":"/ 9",
    "addr:postcode":"6210",
    "addr:street":"Rouse Rd",
    "iso:country":"AU",
    "sg:address":"2 / 9 Rouse Rd",
    "sg:city":"Mandurah",
    "sg:classifiers":[
        {
            "category":"Structure",
            "subcategory":"Building",
            "type":"Public Place"
        }
    ],
    "sg:phone":"+61 8 9581 9788",
    "sg:postcode":"6210",
    "sg:province":"WA",
    "sg:tags":[
        "sail",
        "shade"
    ],
    "wof:name":"Avalon Sail Co.",
    "wof:placetype":"venue"
},
  "geometry": {"coordinates":[115.75007600000001,-32.51466],"type":"Point"}
}