{
  "type": "Feature",
  "properties": {
    "iso:country":"AU",
    "sg:address":"2 / 9 Rouse Rd",
    "sg:city":"Mandurah",
    "sg:classifiers":[
        {
            "category":"Structure",
            "subcategory":"Building",
            "type":"Public Place"
        }
    ],
    "sg:phone":"+61 8 9581 9788",
    "sg:postcode":"6210",
    "sg:province":"WA",
    "sg:tags":[
        "sail",
        "shade"
    ],
    "wof:name":"Avalon Sail Co.",
    "wof:placetype":"venue"
},
  "geometry": {"coordinates":[115.750076,-32.51466],"type":"Point"}
}