{
  "type": "Feature",
  "properties": {
    "addr:full":"3 Carolyn St Silverwater NSW 2128",
    "addr:housenumber":"3",
    "addr:postcode":"2128",
    "addr:street":"Carolyn St",
    "iso:country":"AU",
    "sg:address":"3 Carolyn St",
    "sg:city":"Silverwater",
    "sg:classifiers":[
        {
            "category":"Manufacturing",
            "subcategory":"Metals",
            "type":"Manufacturing & Wholesale Goods"
        }
    ],
    "sg:phone":"+61 2 9648 3334",
    "sg:postcode":"2128",
    "sg:province":"NSW",
    "sg:tags":[
        "steel",
        "fabricator",
        "mfrs"
    ],
    "wof:name":"Active Metalwork Systems",
    "wof:placetype":"venue"
},
  "geometry": {"coordinates":[151.04539489699999,-33.8327598572],"type":"Point"}
}