{
  "type": "Feature",
  "properties": {
    "iso:country":"AU",
    "sg:address":"4/ 355 Mann St",
    "sg:city":"Gosford",
    "sg:classifiers":[
        {
            "category":"Professional",
            "subcategory":"Computer Services",
            "type":"Services"
        }
    ],
    "sg:phone":"+61 2 4322 3302",
    "sg:postcode":"2250",
    "sg:province":"NSW",
    "sg:tags":[
        "package",
        "software"
    ],
    "wof:name":"Transactive Systems Pty Ltd",
    "wof:placetype":"venue"
},
  "geometry": {"coordinates":[151.34381103499999,-33.4180603027],"type":"Point"}
}