{
  "type": "Feature",
  "properties": {
    "iso:country":"AU",
    "sg:address":"245 Springvale Rd",
    "sg:city":"Glen Waverley",
    "sg:classifiers":[
        {
            "category":"Real Estate",
            "subcategory":"Real Estate Agent",
            "type":"Services"
        }
    ],
    "sg:phone":"+61 3 9802 5522",
    "sg:postcode":"3150",
    "sg:province":"VIC",
    "wof:name":"N.R. Reid & Co",
    "wof:placetype":"venue"
},
  "geometry": {"coordinates":[145.16575622600001,-37.8787460327],"type":"Point"}
}