{
  "type": "Feature",
  "properties": {
    "addr:full":"268 Boorowa St Cootamundra NSW 2590",
    "addr:housenumber":"268",
    "addr:postcode":"2590",
    "addr:street":"Boorowa St",
    "iso:country":"AU",
    "sg:address":"268 Boorowa St",
    "sg:city":"Cootamundra",
    "sg:classifiers":[
        {
            "category":"Banks & Credit Unions",
            "subcategory":"Bank",
            "type":"Services"
        }
    ],
    "sg:phone":"+61 1300 654 255",
    "sg:postcode":"2590",
    "sg:province":"NSW",
    "sg:tags":[
        "society"
    ],
    "wof:name":"South West Slopes Credit Union",
    "wof:placetype":"venue"
},
  "geometry": {"coordinates":[148.02609252900001,-34.6400413513],"type":"Point"}
}