{
  "type": "Feature",
  "properties": {
    "iso:country":"AU",
    "sg:address":"106 George St",
    "sg:city":"Redfern",
    "sg:classifiers":[
        {
            "category":"Travel",
            "subcategory":"Hotels & Motels",
            "type":"Entertainment"
        }
    ],
    "sg:phone":"+61 2 9690 0610",
    "sg:postcode":"2016",
    "sg:province":"NSW",
    "sg:tags":[
        "pub"
    ],
    "wof:name":"Mr Mary's Hotel",
    "wof:placetype":"venue"
},
  "geometry": {"coordinates":[151.20199585,-33.8926811218],"type":"Point"}
}