{
  "type": "Feature",
  "properties": {
    "addr:full":"Old Pimba Rd Woomera SA 5720",
    "addr:postcode":"5720",
    "addr:street":"Pimba Rd",
    "iso:country":"AU",
    "sg:address":"Old Pimba Rd",
    "sg:city":"Woomera",
    "sg:classifiers":[
        {
            "category":"Professional",
            "subcategory":"Computer Services",
            "type":"Services"
        }
    ],
    "sg:phone":"+61 8 8673 7029",
    "sg:postcode":"5720",
    "sg:province":"SA",
    "sg:tags":[
        "equipment",
        "networking",
        "installation"
    ],
    "wof:name":"Outback Electronics",
    "wof:placetype":"venue"
},
  "geometry": {"coordinates":[136.815719605,-31.2004337311],"type":"Point"}
}