{
  "type": "Feature",
  "properties": {
    "addr:full":"146 Mount Dandenong Rd Croydon VIC 3136",
    "addr:housenumber":"146",
    "addr:postcode":"3136",
    "addr:street":"Mount Dandenong Rd",
    "iso:country":"AU",
    "sg:address":"146 Mount Dandenong Rd",
    "sg:city":"Croydon",
    "sg:classifiers":[
        {
            "category":"Communications",
            "subcategory":"Film & Video Production",
            "type":"Services"
        }
    ],
    "sg:phone":"+61 3 9723 0822",
    "sg:postcode":"3136",
    "sg:province":"VIC",
    "sg:tags":[
        "fan",
        "blower"
    ],
    "wof:name":"Airco Industrial Fans Pty Ltd",
    "wof:placetype":"venue"
},
  "geometry": {"coordinates":[145.27789306599999,-37.7998313904],"type":"Point"}
}