{
  "type": "Feature",
  "properties": {
    "addr:full":"2/ 19 Argyle Rd Kew VIC 3101",
    "addr:housenumber":"/ 19",
    "addr:postcode":"3101",
    "addr:street":"Argyle Rd",
    "iso:country":"AU",
    "sg:address":"2/ 19 Argyle Rd",
    "sg:city":"Kew",
    "sg:classifiers":[
        {
            "category":"Health Services",
            "subcategory":"Health Practitioner",
            "type":"Services"
        }
    ],
    "sg:phone":"+61 3 9817 5474",
    "sg:postcode":"3101",
    "sg:province":"VIC",
    "sg:tags":[
        "naturopath"
    ],
    "wof:name":"Emma Wright ND",
    "wof:placetype":"venue"
},
  "geometry": {"coordinates":[145.05137634299999,-37.8032150269],"type":"Point"}
}