{
  "type": "Feature",
  "properties": {
    "addr:full":"7 Westlink Crt Altona VIC 3018",
    "addr:housenumber":"7",
    "addr:postcode":"3018",
    "addr:street":"Westlink Crt",
    "iso:country":"AU",
    "sg:address":"7 Westlink Crt",
    "sg:city":"Altona",
    "sg:classifiers":[
        {
            "category":"Real Estate",
            "subcategory":"Architect",
            "type":"Services"
        }
    ],
    "sg:phone":"+61 3 9931 5333",
    "sg:postcode":"3018",
    "sg:province":"VIC",
    "sg:tags":[
        "building",
        "designer"
    ],
    "wof:name":"Fourth Edition Pty Ltd",
    "wof:placetype":"venue"
},
  "geometry": {"coordinates":[144.78843689000001,-37.8564071655],"type":"Point"}
}