{
  "type": "Feature",
  "properties": {
    "iso:country":"AU",
    "sg:address":"37 High St",
    "sg:city":"New Norfolk",
    "sg:classifiers":[
        {
            "category":"Shopping",
            "subcategory":"Clothing, Apparel, & Fashions",
            "type":"Retail Goods"
        }
    ],
    "sg:phone":"+61 3 6261 2224",
    "sg:postcode":"7140",
    "sg:province":"TAS",
    "sg:tags":[
        "menswear"
    ],
    "wof:name":"Ron Williams",
    "wof:placetype":"venue"
},
  "geometry": {"coordinates":[147.06315599999999,-42.780983],"type":"Point"}
}