{
  "type": "Feature",
  "properties": {
    "addr:full":"26 Parsons St Rozelle NSW 2039",
    "addr:housenumber":"26",
    "addr:postcode":"2039",
    "addr:street":"Parsons St",
    "iso:country":"AU",
    "sg:address":"26 Parsons St",
    "sg:city":"Rozelle",
    "sg:classifiers":[
        {
            "category":"Home & Garden",
            "subcategory":"Household Appliances",
            "type":"Retail Goods"
        }
    ],
    "sg:phone":"+61 2 9810 6066",
    "sg:postcode":"2039",
    "sg:province":"NSW",
    "sg:tags":[
        "equipment",
        "gas"
    ],
    "sg:website":"http://www.chippendalerestorations.com.au",
    "wof:name":"Chippendale Restorations",
    "wof:placetype":"venue"
},
  "geometry": {"coordinates":[151.175582886,-33.8656234741],"type":"Point"}
}