{
  "type": "Feature",
  "properties": {
    "addr:full":"Shop 2/ 840 Lower North East Rd Dernancourt SA 5075",
    "addr:housenumber":"shop 2 / 840",
    "addr:postcode":"5075",
    "addr:street":"Lower North East Rd",
    "iso:country":"AU",
    "sg:address":"Shop 2/ 840 Lower North East Rd",
    "sg:city":"Dernancourt",
    "sg:classifiers":[
        {
            "category":"Government",
            "subcategory":"Post Office",
            "type":"Public Place"
        }
    ],
    "sg:phone":"+61 8 8337 3611",
    "sg:postcode":"5075",
    "sg:province":"SA",
    "sg:tags":[
        "postal"
    ],
    "wof:name":"Australia Post",
    "wof:placetype":"venue"
},
  "geometry": {"coordinates":[138.68261718799999,-34.8618927002],"type":"Point"}
}