{
  "type": "Feature",
  "properties": {
    "addr:full":"Bicentennial Drv Sunshine Beach QLD 4567",
    "addr:postcode":"4567",
    "addr:street":"Bicentennial Drv",
    "iso:country":"AU",
    "sg:address":"Bicentennial Drv",
    "sg:city":"Sunshine Beach",
    "sg:classifiers":[
        {
            "category":"Government",
            "subcategory":"City Hall",
            "type":"Public Place"
        }
    ],
    "sg:phone":"+61 7 5447 1177",
    "sg:postcode":"4567",
    "sg:province":"QLD",
    "wof:name":"Bicentennial Community Centre",
    "wof:placetype":"venue"
},
  "geometry": {"coordinates":[153.10113525400001,-26.4035205841],"type":"Point"}
}