{
  "type": "Feature",
  "properties": {
    "addr:full":"5 Railway Pde Darra QLD 4076",
    "addr:housenumber":"5",
    "addr:postcode":"4076",
    "addr:street":"Railway Pde",
    "iso:country":"AU",
    "sg:address":"5 Railway Pde",
    "sg:city":"Darra",
    "sg:classifiers":[
        {
            "category":"Retail",
            "subcategory":"Funeral Services",
            "type":"Services"
        }
    ],
    "sg:phone":"+61 7 3375 6788",
    "sg:postcode":"4076",
    "sg:province":"QLD",
    "sg:tags":[
        "director"
    ],
    "wof:name":"George Hartnett Funerals",
    "wof:placetype":"venue"
},
  "geometry": {"coordinates":[152.95185852,-27.5664196014],"type":"Point"}
}