{
  "type": "Feature",
  "properties": {
    "iso:country":"AU",
    "sg:address":"41 The Concord St",
    "sg:city":"Bundoora",
    "sg:classifiers":[
        {
            "category":"Retail",
            "subcategory":"Auto Repair",
            "type":"Services"
        }
    ],
    "sg:phone":"+61 3 9467 1464",
    "sg:postcode":"3083",
    "sg:province":"VIC",
    "sg:tags":[
        "repairer",
        "motor",
        "engineer"
    ],
    "wof:name":"Watsonia Garage",
    "wof:placetype":"venue"
},
  "geometry": {"coordinates":[145.06947326700001,-37.7011451721],"type":"Point"}
}