{
  "type": "Feature",
  "properties": {
    "addr:full":"3/ 9 Advance Pl Sunrise Estate QLD 4567",
    "addr:housenumber":"/ 9",
    "addr:postcode":"4567",
    "iso:country":"AU",
    "sg:address":"3/ 9 Advance Pl",
    "sg:city":"Sunrise Estate",
    "sg:classifiers":[
        {
            "category":"Personal",
            "subcategory":"Massage",
            "type":"Services"
        }
    ],
    "sg:phone":"+61 7 5455 3620",
    "sg:postcode":"4567",
    "sg:province":"QLD",
    "sg:tags":[
        "therapy"
    ],
    "wof:name":"BodyWhealth-Kirstine Cairns",
    "wof:placetype":"venue"
},
  "geometry": {"coordinates":[153.10198974599999,-26.4096069336],"type":"Point"}
}