{
  "type": "Feature",
  "properties": {
    "addr:full":"1 Church St Kallista VIC 3791",
    "addr:housenumber":"1",
    "addr:postcode":"3791",
    "addr:street":"Church St",
    "iso:country":"AU",
    "sg:address":"1 Church St",
    "sg:city":"Kallista",
    "sg:classifiers":[
        {
            "category":"Health Services",
            "subcategory":"Doctor",
            "type":"Services"
        }
    ],
    "sg:phone":"+61 3 9755 1990",
    "sg:postcode":"3791",
    "sg:province":"VIC",
    "sg:tags":[
        "medical",
        "practitioner"
    ],
    "wof:name":"Kallista Medical Centre",
    "wof:placetype":"venue"
},
  "geometry": {"coordinates":[145.37020874000001,-37.8842086792],"type":"Point"}
}