{
  "type": "Feature",
  "properties": {
    "iso:country":"AU",
    "sg:address":"27 Louee St",
    "sg:city":"Rylstone",
    "sg:classifiers":[
        {
            "category":"Taxi",
            "type":"Transportation"
        }
    ],
    "sg:phone":"+61 410 437 912",
    "sg:postcode":"2849",
    "sg:province":"NSW",
    "sg:tags":[
        "cab"
    ],
    "wof:name":"Rylstone District Hire Car",
    "wof:placetype":"venue"
},
  "geometry": {"coordinates":[149.970795,-32.799782],"type":"Point"}
}