{
  "type": "Feature",
  "properties": {
    "iso:country":"AU",
    "sg:address":"17 Madden St",
    "sg:city":"Aitkenvale",
    "sg:classifiers":[
        {
            "category":"Home & Garden",
            "subcategory":"Hardware",
            "type":"Retail Goods"
        }
    ],
    "sg:phone":"+61 7 4728 5833",
    "sg:postcode":"4814",
    "sg:province":"QLD",
    "sg:tags":[
        "supply",
        "maker",
        "cabinet"
    ],
    "wof:name":"Finn's Panel Solution",
    "wof:placetype":"venue"
},
  "geometry": {"coordinates":[146.76980599999999,-19.292683],"type":"Point"}
}