{
  "type": "Feature",
  "properties": {
    "iso:country":"AU",
    "sg:address":"9- 13 Canterbury Rd",
    "sg:city":"Blackburn South",
    "sg:classifiers":[
        {
            "category":"Retail",
            "subcategory":"Auto Repair",
            "type":"Services"
        }
    ],
    "sg:phone":"+61 3 9898 4498",
    "sg:postcode":"3130",
    "sg:province":"VIC",
    "sg:tags":[
        "electrical"
    ],
    "wof:name":"Pace Auto Electrics Pty. Ltd.",
    "wof:placetype":"venue"
},
  "geometry": {"coordinates":[145.137283325,-37.8303184509],"type":"Point"}
}