{
  "type": "Feature",
  "properties": {
    "addr:full":"17 Beechboro Rd Bayswater WA 6053",
    "addr:housenumber":"17",
    "addr:postcode":"6053",
    "addr:street":"Beechboro Rd",
    "iso:country":"AU",
    "sg:address":"17 Beechboro Rd",
    "sg:city":"Bayswater",
    "sg:classifiers":[
        {
            "category":"Personal",
            "subcategory":"Beauty Salon",
            "type":"Services"
        }
    ],
    "sg:phone":"+61 8 9271 4302",
    "sg:postcode":"6053",
    "sg:province":"WA",
    "sg:tags":[
        "hairdresser"
    ],
    "wof:name":"Head Address For Hair",
    "wof:placetype":"venue"
},
  "geometry": {"coordinates":[115.91358184800001,-31.9157657623],"type":"Point"}
}