{
  "type": "Feature",
  "properties": {
    "iso:country":"AU",
    "sg:address":"1/ 3",
    "sg:city":"Sahra Gr Carrum Downs",
    "sg:classifiers":[
        {
            "category":"Real Estate",
            "subcategory":"Architect",
            "type":"Services"
        }
    ],
    "sg:phone":"+61 3 9770 8155",
    "sg:postcode":"3201",
    "sg:province":"VIC",
    "sg:tags":[
        "wholesaler",
        "mfrs",
        "wool",
        "knitting",
        "accessory"
    ],
    "wof:name":"Morgan R & D",
    "wof:placetype":"venue"
},
  "geometry": {"coordinates":[145.162933,-38.103436],"type":"Point"}
}