{
  "type": "Feature",
  "properties": {
    "addr:full":"56 Princes Hwy Fairy Meadow NSW 2519",
    "addr:housenumber":"56",
    "addr:postcode":"2519",
    "addr:street":"Princes Hwy",
    "iso:country":"AU",
    "sg:address":"56 Princes Hwy",
    "sg:city":"Fairy Meadow",
    "sg:classifiers":[
        {
            "category":"Personal",
            "subcategory":"Tanning Parlor",
            "type":"Services"
        }
    ],
    "sg:phone":"+61 2 4284 8805",
    "sg:postcode":"2519",
    "sg:province":"NSW",
    "sg:tags":[
        "solarium"
    ],
    "wof:name":"A Complete Indulgence Hair & Beauty Salon",
    "wof:placetype":"venue"
},
  "geometry": {"coordinates":[150.893494,-34.391685],"type":"Point"}
}