{
  "type": "Feature",
  "properties": {
    "iso:country":"AU",
    "sg:address":"9 James Ruse Drv",
    "sg:city":"Clyde",
    "sg:classifiers":[
        {
            "category":"Retail",
            "subcategory":"Car Wash",
            "type":"Services"
        }
    ],
    "sg:phone":"+61 2 9637 1722",
    "sg:postcode":"2142",
    "sg:province":"NSW",
    "sg:tags":[
        "truck",
        "cleaning"
    ],
    "wof:name":"Infinity Auto Pty Ltd",
    "wof:placetype":"venue"
},
  "geometry": {"coordinates":[151.01937866200001,-33.8325157166],"type":"Point"}
}