{
  "type": "Feature",
  "properties": {
    "addr:full":"63 Bay St Port Melbourne VIC 3207",
    "addr:housenumber":"63",
    "addr:postcode":"3207",
    "addr:street":"Bay St",
    "iso:country":"AU",
    "sg:address":"63 Bay St",
    "sg:city":"Port Melbourne",
    "sg:classifiers":[
        {
            "category":"Food & Beverages",
            "subcategory":"Bakery",
            "type":"Retail Goods"
        }
    ],
    "sg:phone":"+61 3 9681 8699",
    "sg:postcode":"3207",
    "sg:province":"VIC",
    "sg:tags":[
        "cake",
        "shop",
        "pastry"
    ],
    "wof:name":"Portofino",
    "wof:placetype":"venue"
},
  "geometry": {"coordinates":[144.939438,-37.841499],"type":"Point"}
}