{
  "type": "Feature",
  "properties": {
    "addr:full":"P.O.Box 1084 Thornbury VIC 3071",
    "addr:housenumber":"1084",
    "addr:postcode":"p.o.box;3071",
    "iso:country":"AU",
    "sg:address":"P.O.Box 1084",
    "sg:city":"Thornbury",
    "sg:classifiers":[
        {
            "category":"Building & Trades",
            "subcategory":"Construction",
            "type":"Services"
        }
    ],
    "sg:phone":"+61 412 374 495",
    "sg:postcode":"3071",
    "sg:province":"VIC",
    "sg:tags":[
        "contractor"
    ],
    "wof:name":"Three Js Maintenance",
    "wof:placetype":"venue"
},
  "geometry": {"coordinates":[145.00572204599999,-37.7584495544],"type":"Point"}
}