{
  "type": "Feature",
  "properties": {
    "iso:country":"AU",
    "sg:address":"166 Victoria St",
    "sg:city":"Footscray",
    "sg:classifiers":[
        {
            "category":"Food & Beverages",
            "subcategory":"Groceries & Convenience Stores",
            "type":"Retail Goods"
        }
    ],
    "sg:phone":"+61 3 9687 3694",
    "sg:postcode":"3011",
    "sg:province":"VIC",
    "wof:name":"Wazan B & N",
    "wof:placetype":"venue"
},
  "geometry": {"coordinates":[144.89183044399999,-37.8054771423],"type":"Point"}
}