{
  "type": "Feature",
  "properties": {
    "addr:full":"Unit 2/237 Montague Rd (Cnr Musgrave Rd) South Brisbane QLD 4101",
    "addr:housenumber":"/ 237",
    "addr:postcode":"4101",
    "addr:street":"Montague Rd Cnr Musgrave Rd",
    "iso:country":"AU",
    "sg:address":"Unit 2/237 Montague Rd (Cnr Musgrave Rd)",
    "sg:city":"South Brisbane",
    "sg:classifiers":[
        {
            "category":"Real Estate",
            "subcategory":"Real Estate Services",
            "type":"Services"
        }
    ],
    "sg:phone":"+61 7 3844 9104",
    "sg:postcode":"4101",
    "sg:province":"QLD",
    "sg:tags":[
        "consultant",
        "property"
    ],
    "wof:name":"Aries Projects & Property",
    "wof:placetype":"venue"
},
  "geometry": {"coordinates":[153.007354736,-27.4773330688],"type":"Point"}
}