{
  "type": "Feature",
  "properties": {
    "iso:country":"AU",
    "sg:address":"218 grange Rd",
    "sg:city":"Fairfield",
    "sg:classifiers":[
        {
            "category":"Building & Trades",
            "subcategory":"Construction",
            "type":"Services"
        }
    ],
    "sg:phone":"+61 3 9499 6166",
    "sg:postcode":"3078",
    "sg:province":"VIC",
    "sg:tags":[
        "stonework",
        "stone",
        "mason"
    ],
    "wof:name":"Rock On Grange",
    "wof:placetype":"venue"
},
  "geometry": {"coordinates":[145.02719116200001,-37.7665519714],"type":"Point"}
}