{
  "type": "Feature",
  "properties": {
    "addr:full":"28 Berry Rd St Leonards NSW 2065",
    "addr:housenumber":"28",
    "addr:postcode":"2065",
    "addr:street":"Berry Rd",
    "iso:country":"AU",
    "sg:address":"28 Berry Rd St",
    "sg:city":"Leonards",
    "sg:classifiers":[
        {
            "category":"Professional",
            "subcategory":"Engineering",
            "type":"Services"
        }
    ],
    "sg:phone":"+61 408 677 171",
    "sg:postcode":"2065",
    "sg:province":"NSW",
    "sg:tags":[
        "consulting",
        "engineer"
    ],
    "wof:name":"John Nixon Engineering Pty Ltd",
    "wof:placetype":"venue"
},
  "geometry": {"coordinates":[151.192092895,-33.8267097473],"type":"Point"}
}