{
  "type": "Feature",
  "properties": {
    "addr:full":"Factory 4/ 12 Greenway Drv Tweed Heads NSW 2485",
    "addr:housenumber":"/ 12",
    "addr:postcode":"2485",
    "addr:street":"Greenway Drv",
    "iso:country":"AU",
    "sg:address":"Factory 4/ 12 Greenway Drv",
    "sg:city":"Tweed Heads",
    "sg:classifiers":[
        {
            "category":"Wholesale",
            "subcategory":"Apparel",
            "type":"Manufacturing & Wholesale Goods"
        }
    ],
    "sg:phone":"+61 7 5524 9411",
    "sg:postcode":"2485",
    "sg:province":"NSW",
    "sg:tags":[
        "wholesaler",
        "mfrs",
        "uniform"
    ],
    "wof:name":"Retro Chef",
    "wof:placetype":"venue"
},
  "geometry": {"coordinates":[153.54066467300001,-28.179693222],"type":"Point"}
}