{
  "type": "Feature",
  "properties": {
    "addr:full":"1 Weald Crt Frankston VIC 3199",
    "addr:housenumber":"1",
    "addr:postcode":"3199",
    "addr:street":"Weald Crt",
    "iso:country":"AU",
    "sg:address":"1 Weald Crt",
    "sg:city":"Frankston",
    "sg:classifiers":[
        {
            "category":"Building & Trades",
            "subcategory":"Cleaning & Sanitation",
            "type":"Services"
        }
    ],
    "sg:phone":"+61 425 775 111",
    "sg:postcode":"3199",
    "sg:province":"VIC",
    "sg:tags":[
        "chemical",
        "pressure",
        "steam",
        "contractor"
    ],
    "wof:name":"PSS & Co Cleaning Services",
    "wof:placetype":"venue"
},
  "geometry": {"coordinates":[145.16142273,-38.1589202881],"type":"Point"}
}