{
  "type": "Feature",
  "properties": {
    "addr:full":"U3/ 17 Rivergate Pl Murarrie QLD 4172",
    "addr:postcode":"4172",
    "addr:street":"U3 / 17;Pl",
    "iso:country":"AU",
    "sg:address":"U3/ 17 Rivergate Pl",
    "sg:city":"Murarrie",
    "sg:classifiers":[
        {
            "category":"Utilities",
            "subcategory":"Electric",
            "type":"Services"
        }
    ],
    "sg:phone":"+61 7 3390 8155",
    "sg:postcode":"4172",
    "sg:province":"QLD",
    "sg:tags":[
        "electrical",
        "contractor"
    ],
    "wof:name":"Met Services",
    "wof:placetype":"venue"
},
  "geometry": {"coordinates":[153.10523986800001,-27.4467258453],"type":"Point"}
}