{
  "type": "Feature",
  "properties": {
    "addr:full":"78 Elder St Alice Springs NT 0871",
    "addr:housenumber":"78",
    "addr:postcode":"nt 0871",
    "addr:street":"Elder St",
    "iso:country":"AU",
    "sg:address":"78 Elder St",
    "sg:city":"Alice Springs",
    "sg:classifiers":[
        {
            "category":"Manufacturing",
            "subcategory":"Metals",
            "type":"Manufacturing & Wholesale Goods"
        }
    ],
    "sg:phone":"+61 8 8953 2700",
    "sg:postcode":"0871",
    "sg:province":"NT",
    "sg:tags":[
        "steel",
        "fabricator",
        "mfrs"
    ],
    "wof:name":"Sno's Welding",
    "wof:placetype":"venue"
},
  "geometry": {"coordinates":[133.86280822800001,-23.6945171356],"type":"Point"}
}