{
  "type": "Feature",
  "properties": {
    "addr:full":"Cnr Beckett & Hamilton Rds McDowall QLD 4053",
    "addr:postcode":"4053",
    "iso:country":"AU",
    "sg:address":"Cnr Beckett & Hamilton Rds",
    "sg:city":"McDowall",
    "sg:classifiers":[
        {
            "category":"Education",
            "subcategory":"Kindergarten",
            "type":"Public Place"
        }
    ],
    "sg:phone":"+61 7 3353 5511",
    "sg:postcode":"4053",
    "sg:province":"QLD",
    "sg:tags":[
        "pre-schools"
    ],
    "wof:name":"McDowall Village Childcare",
    "wof:placetype":"venue"
},
  "geometry": {"coordinates":[152.98594665499999,-27.3844203949],"type":"Point"}
}