{
  "type": "Feature",
  "properties": {
    "addr:full":"167 High St Prahran VIC 3181",
    "addr:housenumber":"167",
    "addr:postcode":"3181",
    "addr:street":"High St",
    "iso:country":"AU",
    "sg:address":"167 High St",
    "sg:city":"Prahran",
    "sg:classifiers":[
        {
            "category":"Shopping",
            "subcategory":"Clothing, Apparel, & Fashions",
            "type":"Retail Goods"
        }
    ],
    "sg:phone":"+61 3 9533 7010",
    "sg:postcode":"3181",
    "sg:province":"VIC",
    "sg:tags":[
        "lingerie",
        "hosiery",
        "sleepwear"
    ],
    "wof:name":"Panties & Pearls",
    "wof:placetype":"venue"
},
  "geometry": {"coordinates":[144.99366760300001,-37.8517379761],"type":"Point"}
}