{
  "type": "Feature",
  "properties": {
    "addr:full":"24 Wohling Drv Kimba SA 5641",
    "addr:housenumber":"24",
    "addr:postcode":"5641",
    "addr:street":"Wohling Drv",
    "iso:country":"AU",
    "sg:address":"24 Wohling Drv",
    "sg:city":"Kimba",
    "sg:classifiers":[
        {
            "category":"Personal",
            "subcategory":"Beauty Salon",
            "type":"Services"
        }
    ],
    "sg:phone":"+61 8 8627 2497",
    "sg:postcode":"5641",
    "sg:province":"SA",
    "sg:tags":[
        "hairdresser"
    ],
    "wof:name":"Kimba Hair & Beauty",
    "wof:placetype":"venue"
},
  "geometry": {"coordinates":[136.41424560600001,-33.141242981],"type":"Point"}
}