{
  "type": "Feature",
  "properties": {
    "addr:full":"\"Glenbrook\" Duri NSW 2344",
    "addr:postcode":"2344",
    "iso:country":"AU",
    "sg:address":"\"Glenbrook\"",
    "sg:city":"Duri",
    "sg:classifiers":[
        {
            "category":"Building & Trades",
            "subcategory":"Construction",
            "type":"Services"
        }
    ],
    "sg:phone":"+61 2 6768 0013",
    "sg:postcode":"2344",
    "sg:province":"NSW",
    "sg:tags":[
        "fencing",
        "contractor"
    ],
    "wof:name":"S & N Walters Fencing",
    "wof:placetype":"venue"
},
  "geometry": {"coordinates":[150.85104370100001,-31.2228603363],"type":"Point"}
}