{
  "type": "Feature",
  "properties": {
    "iso:country":"AU",
    "sg:address":"43 Faraday St",
    "sg:city":"West Hobart",
    "sg:classifiers":[
        {
            "category":"Retail",
            "subcategory":"Driving School",
            "type":"Services"
        }
    ],
    "sg:phone":"+61 421 707 754",
    "sg:postcode":"7000",
    "sg:province":"TAS",
    "wof:name":"Alan Greenlees",
    "wof:placetype":"venue"
},
  "geometry": {"coordinates":[147.31152343799999,-42.8864440918],"type":"Point"}
}