{
  "type": "Feature",
  "properties": {
    "iso:country":"AU",
    "sg:address":"209 Darley Rd",
    "sg:city":"Randwick",
    "sg:classifiers":[
        {
            "category":"Building & Trades",
            "subcategory":"Construction",
            "type":"Services"
        }
    ],
    "sg:phone":"+61 415 245 289",
    "sg:postcode":"2031",
    "sg:province":"NSW",
    "sg:tags":[
        "stonework",
        "stone",
        "mason"
    ],
    "wof:name":"JJ's Stone Ceiling",
    "wof:placetype":"venue"
},
  "geometry": {"coordinates":[151.24806213400001,-33.903377533],"type":"Point"}
}