{
  "type": "Feature",
  "properties": {
    "iso:country":"AU",
    "sg:address":"Cnr William & Rocket Sts",
    "sg:city":"Bathurst",
    "sg:classifiers":[
        {
            "category":"Utilities",
            "subcategory":"Electric",
            "type":"Services"
        }
    ],
    "sg:phone":"+61 2 6331 1831",
    "sg:postcode":"2795",
    "sg:province":"NSW",
    "sg:tags":[
        "tube",
        "lamps",
        "globe"
    ],
    "wof:name":"Bathurst Bright Idea Lighting",
    "wof:placetype":"venue"
},
  "geometry": {"coordinates":[149.57989501899999,-33.4317169189],"type":"Point"}
}