{
  "type": "Feature",
  "properties": {
    "iso:country":"AU",
    "sg:address":"Riverside Drv",
    "sg:city":"Wooli",
    "sg:classifiers":[
        {
            "category":"Food & Beverages",
            "subcategory":"Meat & Fish",
            "type":"Retail Goods"
        }
    ],
    "sg:phone":"+61 2 6649 7537",
    "sg:postcode":"2462",
    "sg:province":"NSW",
    "sg:tags":[
        "seafood"
    ],
    "wof:name":"Wooli Oyster Supply",
    "wof:placetype":"venue"
},
  "geometry": {"coordinates":[153.26565551799999,-29.8684005737],"type":"Point"}
}