{
  "type": "Feature",
  "properties": {
    "addr:full":"Suite 3 50 Palm Beach Rd Palm Beach NSW 2108",
    "addr:housenumber":"50",
    "addr:postcode":"2108",
    "addr:street":"Palm Beach Rd",
    "iso:country":"AU",
    "sg:address":"Suite 3 50 Palm Beach Rd",
    "sg:city":"Palm Beach",
    "sg:classifiers":[
        {
            "category":"Communications",
            "subcategory":"News Services",
            "type":"Services"
        }
    ],
    "sg:phone":"+61 2 9974 1096",
    "sg:postcode":"2108",
    "sg:province":"NSW",
    "sg:tags":[
        "information",
        "tourist",
        "attractions"
    ],
    "wof:name":"Palm Beach Experience The",
    "wof:placetype":"venue"
},
  "geometry": {"coordinates":[151.32083129899999,-33.5952224731],"type":"Point"}
}