{
  "type": "Feature",
  "properties": {
    "iso:country":"AU",
    "sg:address":"16a Riviera Crt",
    "sg:city":"Pasadena",
    "sg:classifiers":[
        {
            "category":"Health Services",
            "subcategory":"Health Practitioner",
            "type":"Services"
        }
    ],
    "sg:phone":"+61 8 8277 0824",
    "sg:postcode":"5042",
    "sg:province":"SA",
    "sg:tags":[
        "homoeopath"
    ],
    "wof:name":"Adelaide Homeopathic Clinic",
    "wof:placetype":"venue"
},
  "geometry": {"coordinates":[138.593887,-35.01268],"type":"Point"}
}