{
  "type": "Feature",
  "properties": {
    "addr:full":"Hewlett Packard St Reynella SA 5161",
    "addr:postcode":"5161",
    "addr:street":"St",
    "iso:country":"AU",
    "sg:address":"Hewlett Packard St",
    "sg:city":"Reynella",
    "sg:classifiers":[
        {
            "category":"Education",
            "subcategory":"School",
            "type":"Public Place"
        }
    ],
    "sg:phone":"+61 8 8381 8466",
    "sg:postcode":"5161",
    "sg:province":"SA",
    "sg:tags":[
        "state",
        "except",
        "nsw"
    ],
    "wof:name":"Reynella East High",
    "wof:placetype":"venue"
},
  "geometry": {"coordinates":[138.556732178,-35.0921516418],"type":"Point"}
}