{
  "type": "Feature",
  "properties": {
    "addr:full":"Level 2 The Regent 167 Queen St Mall Brisbane QLD 4000",
    "addr:housenumber":"167",
    "addr:postcode":"4000",
    "addr:street":"Queen St Mall",
    "iso:country":"AU",
    "sg:address":"Level 2 The Regent 167 Queen St",
    "sg:city":"Mall Brisbane",
    "sg:classifiers":[
        {
            "category":"Health Services",
            "subcategory":"Dentist",
            "type":"Services"
        }
    ],
    "sg:phone":"+61 7 3221 8225",
    "sg:postcode":"4000",
    "sg:province":"QLD",
    "wof:name":"Bennett Clive",
    "wof:placetype":"venue"
},
  "geometry": {"coordinates":[153.0262146,-27.4690570831],"type":"Point"}
}