{
  "type": "Feature",
  "properties": {
    "addr:full":"76 Topping St Sale VIC 3850",
    "addr:housenumber":"76",
    "addr:postcode":"3850",
    "addr:street":"Topping St",
    "iso:country":"AU",
    "sg:address":"76 Topping St",
    "sg:city":"Sale",
    "sg:classifiers":[
        {
            "category":"Professional",
            "subcategory":"Art Services",
            "type":"Services"
        }
    ],
    "sg:phone":"+61 3 5144 3977",
    "sg:postcode":"3850",
    "sg:province":"VIC",
    "sg:tags":[
        "interior",
        "decorator"
    ],
    "wof:name":"Fraser G & B A",
    "wof:placetype":"venue"
},
  "geometry": {"coordinates":[147.05268859899999,-38.1044082642],"type":"Point"}
}