{
  "type": "Feature",
  "properties": {
    "addr:full":"\"Hillgrove\" Knobles Rd Wirlinga NSW 2640",
    "addr:postcode":"2640",
    "addr:street":"Knobles Rd",
    "iso:country":"AU",
    "sg:address":"\"Hillgrove\" Knobles Rd",
    "sg:city":"Wirlinga",
    "sg:classifiers":[
        {
            "category":"Building & Trades",
            "subcategory":"Construction",
            "type":"Services"
        }
    ],
    "sg:phone":"+61 407 211 235",
    "sg:postcode":"2640",
    "sg:province":"NSW",
    "sg:tags":[
        "contractor"
    ],
    "wof:name":"Craig Scott Building & Design",
    "wof:placetype":"venue"
},
  "geometry": {"coordinates":[147.04620361299999,-36.0647354126],"type":"Point"}
}