{
  "type": "Feature",
  "properties": {
    "iso:country":"AU",
    "sg:address":"1 Scarborough Drv",
    "sg:city":"Patterson Lakes",
    "sg:classifiers":[
        {
            "category":"Professional",
            "subcategory":"Management & Consulting",
            "type":"Services"
        }
    ],
    "sg:phone":"+61 3 9773 3974",
    "sg:postcode":"3197",
    "sg:province":"VIC",
    "sg:tags":[
        "consultant"
    ],
    "wof:name":"Greetham Management Services Pty Ltd",
    "wof:placetype":"venue"
},
  "geometry": {"coordinates":[145.14031982399999,-38.0685653687],"type":"Point"}
}