{
  "type": "Feature",
  "properties": {
    "addr:full":"Telstra Bldg, 2A/ 242 Exhibition St Melbourne VIC 3000",
    "addr:housenumber":"2a / 242",
    "addr:postcode":"3000",
    "addr:street":"Exhibition St",
    "iso:country":"AU",
    "sg:address":"Telstra Bldg, 2A/ 242 Exhibition St",
    "sg:city":"Melbourne",
    "sg:classifiers":[
        {
            "category":"Health Services",
            "subcategory":"Optometrist",
            "type":"Services"
        }
    ],
    "sg:phone":"+61 3 9639 0187",
    "sg:postcode":"3000",
    "sg:province":"VIC",
    "wof:name":"Nou Vogue Eyeware",
    "wof:placetype":"venue"
},
  "geometry": {"coordinates":[144.96978759800001,-37.810005188],"type":"Point"}
}