{
  "type": "Feature",
  "properties": {
    "addr:full":"38d Grigor St Caloundra QLD 4551",
    "addr:housenumber":"38d",
    "addr:postcode":"4551",
    "addr:street":"Grigor St",
    "iso:country":"AU",
    "sg:address":"38d Grigor St",
    "sg:city":"Caloundra",
    "sg:classifiers":[
        {
            "category":"Manufacturing",
            "subcategory":"Signs",
            "type":"Manufacturing & Wholesale Goods"
        }
    ],
    "sg:phone":"+61 7 5492 6100",
    "sg:postcode":"4551",
    "sg:province":"QLD",
    "sg:tags":[
        "traffic",
        "safety"
    ],
    "wof:name":"Impact Screenprints",
    "wof:placetype":"venue"
},
  "geometry": {"coordinates":[153.13682556099999,-26.791721344],"type":"Point"}
}