{
  "type": "Feature",
  "properties": {
    "addr:full":"5 Tea Tree Crs Sinnamon Park QLD 4073",
    "addr:housenumber":"5",
    "addr:postcode":"4073",
    "addr:street":"Tea Tree Crs",
    "iso:country":"AU",
    "sg:address":"5 Tea Tree Crs",
    "sg:city":"Sinnamon Park",
    "sg:classifiers":[
        {
            "category":"Health Services",
            "subcategory":"Health Practitioner",
            "type":"Services"
        }
    ],
    "sg:phone":"+61 406 724 752",
    "sg:postcode":"4073",
    "sg:province":"QLD",
    "sg:tags":[
        "pathologist",
        "speech"
    ],
    "wof:name":"Mawson Peta",
    "wof:placetype":"venue"
},
  "geometry": {"coordinates":[152.95300293,-27.5454502106],"type":"Point"}
}