{
  "type": "Feature",
  "properties": {
    "addr:full":"34-36 McIntyre Rd Sunshine VIC 3020",
    "addr:housenumber":"34-36",
    "addr:postcode":"3020",
    "addr:street":"Mcintyre Rd",
    "iso:country":"AU",
    "sg:address":"34-36 McIntyre Rd",
    "sg:city":"Sunshine",
    "sg:classifiers":[
        {
            "category":"Autos & Motor Vehicles",
            "subcategory":"Auto Supplies",
            "type":"Retail Goods"
        }
    ],
    "sg:phone":"+61 3 9364 9761",
    "sg:postcode":"3020",
    "sg:province":"VIC",
    "sg:tags":[
        "tyre"
    ],
    "wof:name":"Sunshine Tyrepower",
    "wof:placetype":"venue"
},
  "geometry": {"coordinates":[144.82948300000001,-37.773823],"type":"Point"}
}