{
  "type": "Feature",
  "properties": {
    "addr:full":"11 Lenehans La Noosaville QLD 4566",
    "addr:housenumber":"11",
    "addr:postcode":"4566",
    "addr:street":"Lenehans La",
    "iso:country":"AU",
    "sg:address":"11 Lenehans La",
    "sg:city":"Noosaville",
    "sg:classifiers":[
        {
            "category":"Manufacturing",
            "subcategory":"Tools & Machinery",
            "type":"Manufacturing & Wholesale Goods"
        }
    ],
    "sg:phone":"+61 7 5471 1242",
    "sg:postcode":"4566",
    "sg:province":"QLD",
    "sg:tags":[
        "earth",
        "excavating",
        "moving",
        "equipment"
    ],
    "wof:name":"Andrew Corns Pandanus",
    "wof:placetype":"venue"
},
  "geometry": {"coordinates":[153.05047607399999,-26.4029693604],"type":"Point"}
}