{
  "type": "Feature",
  "properties": {
    "iso:country":"AU",
    "sg:address":"U2/ 66 Greville St",
    "sg:city":"Prahran",
    "sg:classifiers":[
        {
            "category":"Manufacturing",
            "subcategory":"Printing",
            "type":"Manufacturing & Wholesale Goods"
        }
    ],
    "sg:phone":"+61 3 9510 4555",
    "sg:postcode":"3181",
    "sg:province":"VIC",
    "sg:tags":[
        "wholesaler",
        "mfrs",
        "greeting",
        "card"
    ],
    "wof:name":"Flaming Rhino Design Pty Ltd",
    "wof:placetype":"venue"
},
  "geometry": {"coordinates":[144.991897583,-37.8564491272],"type":"Point"}
}