{
  "type": "Feature",
  "properties": {
    "addr:full":"6 Station St Wentworth Falls NSW 2782",
    "addr:housenumber":"6",
    "addr:postcode":"2782",
    "addr:street":"Station St",
    "iso:country":"AU",
    "sg:address":"6 Station St",
    "sg:city":"Wentworth Falls",
    "sg:classifiers":[
        {
            "category":"Deli",
            "type":"Food & Drink"
        }
    ],
    "sg:phone":"+61 2 4757 1429",
    "sg:postcode":"2782",
    "sg:province":"NSW",
    "sg:tags":[
        "delicatessen"
    ],
    "wof:name":"Wentworth Falls Deli",
    "wof:placetype":"venue"
},
  "geometry": {"coordinates":[150.37579345699999,-33.7102165222],"type":"Point"}
}