{
  "type": "Feature",
  "properties": {
    "iso:country":"AU",
    "sg:address":"PO Box 27",
    "sg:city":"Lara",
    "sg:classifiers":[
        {
            "category":"Wholesale",
            "subcategory":"Fruits & Vegetables",
            "type":"Manufacturing & Wholesale Goods"
        }
    ],
    "sg:phone":"+61 3 5282 4745",
    "sg:postcode":"3212",
    "sg:province":"VIC",
    "sg:tags":[
        "produce",
        "grain"
    ],
    "wof:name":"J R Grains Pty Ltd",
    "wof:placetype":"venue"
},
  "geometry": {"coordinates":[144.39659118599999,-38.0215110779],"type":"Point"}
}