{
  "type": "Feature",
  "properties": {
    "addr:full":"12/ 640 Albany Creek Rd Albany Creek QLD 4035",
    "addr:housenumber":"12 / 640",
    "addr:postcode":"4035",
    "addr:street":"Albany Creek Rd",
    "iso:country":"AU",
    "sg:address":"12/ 640 Albany Creek Rd",
    "sg:city":"Albany Creek",
    "sg:classifiers":[
        {
            "category":"Health Services",
            "subcategory":"Doctor",
            "type":"Services"
        }
    ],
    "sg:phone":"+61 7 3325 1244",
    "sg:postcode":"4035",
    "sg:province":"QLD",
    "sg:tags":[
        "medical",
        "practitioner"
    ],
    "wof:name":"Skin Screen Skin Cancer Clinic",
    "wof:placetype":"venue"
},
  "geometry": {"coordinates":[152.966095,-27.345373],"type":"Point"}
}