{
  "type": "Feature",
  "properties": {
    "addr:full":"5/ 440 Elizabeth St Melbourne VIC 3000",
    "addr:housenumber":"/ 440",
    "addr:postcode":"3000",
    "addr:street":"Elizabeth St",
    "iso:country":"AU",
    "sg:address":"5/ 440 Elizabeth St",
    "sg:city":"Melbourne",
    "sg:classifiers":[
        {
            "category":"Shopping",
            "subcategory":"Mobile Phones",
            "type":"Retail Goods"
        }
    ],
    "sg:phone":"+61 3 9654 6440",
    "sg:postcode":"3000",
    "sg:province":"VIC",
    "sg:tags":[
        "telephone",
        "accessory"
    ],
    "wof:name":"Excel Force Communications",
    "wof:placetype":"venue"
},
  "geometry": {"coordinates":[144.960662842,-37.808391571],"type":"Point"}
}