{
  "type": "Feature",
  "properties": {
    "addr:full":"1541 Komine East Rd Injune QLD 4454",
    "addr:housenumber":"1541",
    "addr:postcode":"4454",
    "addr:street":"East Rd",
    "iso:country":"AU",
    "sg:address":"1541 Komine East Rd",
    "sg:city":"Injune",
    "sg:classifiers":[
        {
            "category":"Building & Trades",
            "subcategory":"Landscaping Services",
            "type":"Services"
        }
    ],
    "sg:phone":"+61 7 4626 1207",
    "sg:postcode":"4454",
    "sg:province":"QLD",
    "sg:tags":[
        "grazier"
    ],
    "wof:name":"Guthrie S R & J M",
    "wof:placetype":"venue"
},
  "geometry": {"coordinates":[148.523147583,-25.9173851013],"type":"Point"}
}