{
  "type": "Feature",
  "properties": {
    "addr:full":"332 Montague St Albert Park VIC 3206",
    "addr:housenumber":"332",
    "addr:postcode":"3206",
    "addr:street":"Montague St",
    "iso:country":"AU",
    "sg:address":"332 Montague St",
    "sg:city":"Albert Park",
    "sg:classifiers":[
        {
            "category":"Real Estate",
            "subcategory":"Real Estate Agent",
            "type":"Services"
        }
    ],
    "sg:phone":"+61 3 9690 5366",
    "sg:postcode":"3206",
    "sg:province":"VIC",
    "wof:name":"Hocking Stuart Albert Park",
    "wof:placetype":"venue"
},
  "geometry": {"coordinates":[144.95545999999999,-37.840508],"type":"Point"}
}