{
  "type": "Feature",
  "properties": {
    "addr:full":"312 Avoca Drv Avoca Beach NSW 2251",
    "addr:housenumber":"312",
    "addr:postcode":"2251",
    "addr:street":"Avoca Drv",
    "iso:country":"AU",
    "sg:address":"312 Avoca Drv",
    "sg:city":"Avoca Beach",
    "sg:classifiers":[
        {
            "category":"Education",
            "subcategory":"Kindergarten",
            "type":"Public Place"
        }
    ],
    "sg:phone":"+61 2 4381 1554",
    "sg:postcode":"2251",
    "sg:province":"NSW",
    "sg:tags":[
        "pre-schools"
    ],
    "wof:name":"Hillside Preschool/Daycare Centre Avoca Beach",
    "wof:placetype":"venue"
},
  "geometry": {"coordinates":[151.41868591299999,-33.4663124084],"type":"Point"}
}