{
  "type": "Feature",
  "properties": {
    "iso:country":"AU",
    "sg:address":"11 Civic Pl",
    "sg:city":"Ringwood",
    "sg:classifiers":[
        {
            "category":"Banks & Credit Unions",
            "subcategory":"Bank",
            "type":"Services"
        }
    ],
    "sg:phone":"+61 3 9879 2201",
    "sg:postcode":"3134",
    "sg:province":"VIC",
    "sg:tags":[
        "society"
    ],
    "wof:name":"Maroondah Credit Union Ltd",
    "wof:placetype":"venue"
},
  "geometry": {"coordinates":[145.229370117,-37.8145751953],"type":"Point"}
}