{
  "type": "Feature",
  "properties": {
    "addr:full":"130 Wigram Rd Glebe NSW 2037",
    "addr:housenumber":"130",
    "addr:postcode":"2037",
    "addr:street":"Wigram Rd",
    "iso:country":"AU",
    "sg:address":"130 Wigram Rd",
    "sg:city":"Glebe",
    "sg:classifiers":[
        {
            "category":"Wholesale",
            "subcategory":"Music Publishers",
            "type":"Manufacturing & Wholesale Goods"
        }
    ],
    "sg:phone":"+61 2 9552 4020",
    "sg:postcode":"2037",
    "sg:province":"NSW",
    "sg:tags":[
        "wholesaler",
        "dvd",
        "mfrs",
        "cd"
    ],
    "wof:name":"Tall Poppies Records Ltd",
    "wof:placetype":"venue"
},
  "geometry": {"coordinates":[151.17741394000001,-33.8815994263],"type":"Point"}
}