{
  "type": "Feature",
  "properties": {
    "addr:full":"Unit 2, 5 Roxburgh Ave Lonsdale SA 5160",
    "addr:housenumber":"5",
    "addr:postcode":"5160",
    "addr:street":"Roxburgh Ave",
    "iso:country":"AU",
    "sg:address":"Unit 2, 5 Roxburgh Ave",
    "sg:city":"Lonsdale",
    "sg:classifiers":[
        {
            "category":"Retail",
            "subcategory":"Auto Repair",
            "type":"Services"
        }
    ],
    "sg:phone":"+61 403 026 218",
    "sg:postcode":"5160",
    "sg:province":"SA",
    "sg:tags":[
        "automotive",
        "air conditioning"
    ],
    "wof:name":"H & S Car Company",
    "wof:placetype":"venue"
},
  "geometry": {"coordinates":[138.49598693900001,-35.1173706055],"type":"Point"}
}