{
  "type": "Feature",
  "properties": {
    "addr:full":"1062 Doncaster Rd Doncaster East VIC 3109",
    "addr:housenumber":"1062",
    "addr:postcode":"3109",
    "addr:street":"Doncaster Rd",
    "iso:country":"AU",
    "sg:address":"1062 Doncaster Rd",
    "sg:city":"Doncaster East",
    "sg:classifiers":[
        {
            "category":"Health Services",
            "subcategory":"Dentist",
            "type":"Services"
        }
    ],
    "sg:phone":"+61 3 9841 6655",
    "sg:postcode":"3109",
    "sg:province":"VIC",
    "sg:tags":[
        "technician",
        "dental"
    ],
    "wof:name":"Malcolm Parkinson Dental Technician & Prosthetist",
    "wof:placetype":"venue"
},
  "geometry": {"coordinates":[145.16606140100001,-37.7897949219],"type":"Point"}
}