{
  "type": "Feature",
  "properties": {
    "addr:full":"Cnr High St & Watts Rd Hastings VIC 3915",
    "addr:postcode":"3915",
    "addr:street":"High St & Watts Rd",
    "iso:country":"AU",
    "sg:address":"Cnr High St & Watts Rd",
    "sg:city":"Hastings",
    "sg:classifiers":[
        {
            "category":"Food & Beverages",
            "subcategory":"Groceries & Convenience Stores",
            "type":"Retail Goods"
        }
    ],
    "sg:phone":"+61 3 5979 2945",
    "sg:postcode":"3915",
    "sg:province":"VIC",
    "wof:name":"Ampol",
    "wof:placetype":"venue"
},
  "geometry": {"coordinates":[145.191329956,-38.3077087402],"type":"Point"}
}