{
  "type": "Feature",
  "properties": {
    "addr:full":"2 O'Keefe Crt Garbutt QLD 4814",
    "addr:housenumber":"2",
    "addr:postcode":"4814",
    "addr:street":"O'Keefe Crt",
    "iso:country":"AU",
    "sg:address":"2 O'Keefe Crt",
    "sg:city":"Garbutt",
    "sg:classifiers":[
        {
            "category":"Retail",
            "subcategory":"Auto Repair",
            "type":"Services"
        }
    ],
    "sg:phone":"+61 7 4779 1934",
    "sg:postcode":"4814",
    "sg:province":"QLD",
    "sg:tags":[
        "repairer",
        "motor",
        "engineer"
    ],
    "wof:name":"Townsville Mechanical Services",
    "wof:placetype":"venue"
},
  "geometry": {"coordinates":[146.76315299999999,-19.27743],"type":"Point"}
}