{
  "type": "Feature",
  "properties": {
    "addr:full":"Shop 2, 346 Pakington St Newtown VIC 3220",
    "addr:housenumber":"shop 2",
    "addr:postcode":"346;3220",
    "addr:street":"Pakington St",
    "iso:country":"AU",
    "sg:address":"Shop 2, 346 Pakington St",
    "sg:city":"Newtown",
    "sg:classifiers":[
        {
            "category":"Personal",
            "subcategory":"Tanning Parlor",
            "type":"Services"
        }
    ],
    "sg:phone":"+61 3 5221 9059",
    "sg:postcode":"3220",
    "sg:province":"VIC",
    "sg:tags":[
        "solarium"
    ],
    "wof:name":"Malibu Tan",
    "wof:placetype":"venue"
},
  "geometry": {"coordinates":[144.34524500000001,-38.157829],"type":"Point"}
}