{
  "type": "Feature",
  "properties": {
    "addr:full":"22 Martin Rd Sorrento WA 6020",
    "addr:housenumber":"22",
    "addr:postcode":"6020",
    "addr:street":"Martin Rd",
    "iso:country":"AU",
    "sg:address":"22 Martin Rd",
    "sg:city":"Sorrento",
    "sg:classifiers":[
        {
            "category":"Professional",
            "subcategory":"Art Services",
            "type":"Services"
        }
    ],
    "sg:phone":"+61 8 9447 8048",
    "sg:postcode":"6020",
    "sg:province":"WA",
    "sg:tags":[
        "decorator",
        "painter"
    ],
    "wof:name":"Color My World Painters & Decorators",
    "wof:placetype":"venue"
},
  "geometry": {"coordinates":[115.75743866000001,-31.8309307098],"type":"Point"}
}