{
  "type": "Feature",
  "properties": {
    "addr:full":"Shop 1a Railway Tce Alice Springs NT 0870",
    "addr:housenumber":"shop 1a",
    "addr:postcode":"nt 0870",
    "addr:street":"Railway Tce",
    "iso:country":"AU",
    "sg:address":"Shop 1a Railway Tce",
    "sg:city":"Alice Springs",
    "sg:classifiers":[
        {
            "category":"Organizations",
            "subcategory":"Non-profit Organization",
            "type":"Services"
        }
    ],
    "sg:phone":"+61 8 8953 1422",
    "sg:postcode":"0870",
    "sg:province":"NT",
    "sg:tags":[
        "support",
        "disability",
        "organisation"
    ],
    "wof:name":"Disability Advocacy Service",
    "wof:placetype":"venue"
},
  "geometry": {"coordinates":[133.87809753400001,-23.6997280121],"type":"Point"}
}