{
  "type": "Feature",
  "properties": {
    "iso:country":"AU",
    "sg:address":"8 Hidden Valley Drv",
    "sg:city":"Eatons Hill",
    "sg:classifiers":[
        {
            "category":"Building & Trades",
            "subcategory":"Construction",
            "type":"Services"
        }
    ],
    "sg:phone":"+61 7 3325 2001",
    "sg:postcode":"4037",
    "sg:province":"QLD",
    "sg:tags":[
        "renovation",
        "alterations",
        "extension",
        "contractor"
    ],
    "wof:name":"Fraser Renovations Pty Ltd",
    "wof:placetype":"venue"
},
  "geometry": {"coordinates":[152.937897,-27.343719],"type":"Point"}
}