{
  "type": "Feature",
  "properties": {
    "iso:country":"AU",
    "sg:address":"2/ 30 Greenlinks Ave",
    "sg:city":"Coffs Harbour",
    "sg:classifiers":[
        {
            "category":"Building & Trades",
            "subcategory":"Pest Control",
            "type":"Services"
        }
    ],
    "sg:phone":"+61 2 6651 1714",
    "sg:postcode":"2450",
    "sg:province":"NSW",
    "wof:name":"Mals Environmental Pest Management",
    "wof:placetype":"venue"
},
  "geometry": {"coordinates":[153.109131,-30.305401],"type":"Point"}
}