{
  "type": "Feature",
  "properties": {
    "iso:country":"AU",
    "sg:address":"Greystanes Rd",
    "sg:city":"South Wentworthville",
    "sg:classifiers":[
        {
            "category":"Home & Garden",
            "subcategory":"Building Materials",
            "type":"Retail Goods"
        }
    ],
    "sg:phone":"+61 2 9688 9500",
    "sg:postcode":"2145",
    "sg:province":"NSW",
    "sg:tags":[
        "supply"
    ],
    "wof:name":"Blue Circle Southern Cement Ltd",
    "wof:placetype":"venue"
},
  "geometry": {"coordinates":[150.934356689,-33.8159675598],"type":"Point"}
}