{
  "type": "Feature",
  "properties": {
    "addr:full":"33 Grove Ave Marleston SA 5033",
    "addr:housenumber":"33",
    "addr:postcode":"5033",
    "addr:street":"Grove Ave",
    "iso:country":"AU",
    "sg:address":"33 Grove Ave",
    "sg:city":"Marleston",
    "sg:classifiers":[
        {
            "category":"Government",
            "subcategory":"Fire Station",
            "type":"Public Place"
        }
    ],
    "sg:phone":"+61 8 8371 4555",
    "sg:postcode":"5033",
    "sg:province":"SA",
    "sg:tags":[
        "equipment",
        "protection",
        "consultant"
    ],
    "wof:name":"Complete Fire Services P/L",
    "wof:placetype":"venue"
},
  "geometry": {"coordinates":[138.562744141,-34.9459114075],"type":"Point"}
}