{
  "type": "Feature",
  "properties": {
    "iso:country":"AU",
    "sg:address":"12 Nickson St",
    "sg:city":"Bundoora",
    "sg:classifiers":[
        {
            "category":"Education",
            "subcategory":"Special Training",
            "type":"Public Place"
        }
    ],
    "sg:phone":"+61 3 9467 3543",
    "sg:postcode":"3083",
    "sg:province":"VIC",
    "sg:tags":[
        "tuition-educational"
    ],
    "wof:name":"Minova Tutoring",
    "wof:placetype":"venue"
},
  "geometry": {"coordinates":[145.057296753,-37.6967086792],"type":"Point"}
}