{
  "type": "Feature",
  "properties": {
    "addr:full":"U 3/ 96 Glenayr Ave Bondi Beach NSW 2026",
    "addr:housenumber":"96",
    "addr:postcode":"2026",
    "addr:street":"Glenayr Ave",
    "iso:country":"AU",
    "sg:address":"U 3/ 96 Glenayr Ave",
    "sg:city":"Bondi Beach",
    "sg:classifiers":[
        {
            "category":"Building & Trades",
            "subcategory":"Cleaning & Sanitation",
            "type":"Services"
        }
    ],
    "sg:phone":"+61 2 9130 4930",
    "sg:postcode":"2026",
    "sg:province":"NSW",
    "sg:tags":[
        "industrial",
        "commercial",
        "contractor"
    ],
    "wof:name":"NRG Cleaners Pty Ltd",
    "wof:placetype":"venue"
},
  "geometry": {"coordinates":[151.27355957,-33.8859138489],"type":"Point"}
}