{
  "type": "Feature",
  "properties": {
    "addr:full":"Unit 5, 465 Victoria St Wetherill Park NSW 2164",
    "addr:housenumber":"465",
    "addr:postcode":"2164",
    "addr:street":"Victoria St",
    "iso:country":"AU",
    "sg:address":"Unit 5, 465 Victoria St",
    "sg:city":"Wetherill Park",
    "sg:classifiers":[
        {
            "category":"Retail",
            "subcategory":"Auto Repair",
            "type":"Services"
        }
    ],
    "sg:phone":"+61 2 9725 5011",
    "sg:postcode":"2164",
    "sg:province":"NSW",
    "sg:tags":[
        "electrical"
    ],
    "wof:name":"Prestige Auto Electrical",
    "wof:placetype":"venue"
},
  "geometry": {"coordinates":[150.888946533,-33.844039917],"type":"Point"}
}