{
  "type": "Feature",
  "properties": {
    "iso:country":"AU",
    "sg:address":"448 Cleveland St",
    "sg:city":"Surry Hills",
    "sg:classifiers":[
        {
            "category":"Shopping",
            "subcategory":"Stationery & Office Supplies",
            "type":"Retail Goods"
        }
    ],
    "sg:phone":"+61 2 9698 5534",
    "sg:postcode":"2010",
    "sg:province":"NSW",
    "sg:tags":[
        "screen",
        "printing"
    ],
    "wof:name":"Live With Passion Marketing",
    "wof:placetype":"venue"
},
  "geometry": {"coordinates":[151.21292114299999,-33.8914337158],"type":"Point"}
}