{
  "type": "Feature",
  "properties": {
    "addr:full":"19 Hobart Rd Kings Meadows TAS 7249",
    "addr:housenumber":"19",
    "addr:postcode":"7249",
    "addr:street":"Hobart Rd",
    "iso:country":"AU",
    "sg:address":"19 Hobart Rd",
    "sg:city":"Kings Meadows",
    "sg:classifiers":[
        {
            "category":"Retail",
            "subcategory":"Laundry & Dry Cleaning",
            "type":"Services"
        }
    ],
    "sg:phone":"+61 3 6344 5822",
    "sg:postcode":"7249",
    "sg:province":"TAS",
    "wof:name":"Launceston Linen Service",
    "wof:placetype":"venue"
},
  "geometry": {"coordinates":[147.15553283700001,-41.4599990845],"type":"Point"}
}