{
  "type": "Feature",
  "properties": {
    "addr:full":"449 Swanston St Melbourne VIC 3000",
    "addr:housenumber":"449",
    "addr:postcode":"3000",
    "addr:street":"Swanston St",
    "iso:country":"AU",
    "sg:address":"449 Swanston St",
    "sg:city":"Melbourne",
    "sg:classifiers":[
        {
            "category":"Cafe",
            "type":"Food & Drink"
        }
    ],
    "sg:phone":"+61 3 9663 3700",
    "sg:postcode":"3000",
    "sg:province":"VIC",
    "wof:name":"Gloria Jean's Coffees",
    "wof:placetype":"venue"
},
  "geometry": {"coordinates":[144.96287536599999,-37.8078765869],"type":"Point"}
}