{
  "type": "Feature",
  "properties": {
    "addr:full":"288 Welshpool Rd Welshpool WA 6106",
    "addr:housenumber":"288",
    "addr:postcode":"6106",
    "addr:street":"Welshpool Rd",
    "iso:country":"AU",
    "sg:address":"288 Welshpool Rd",
    "sg:city":"Welshpool",
    "sg:classifiers":[
        {
            "category":"Manufacturing",
            "subcategory":"Motor Vehicles & Parts",
            "type":"Manufacturing & Wholesale Goods"
        }
    ],
    "sg:phone":"+61 8 9451 9166",
    "sg:postcode":"6106",
    "sg:province":"WA",
    "sg:tags":[
        "engine",
        "equipment",
        "diesel"
    ],
    "wof:name":"Lombardini Engines",
    "wof:placetype":"venue"
},
  "geometry": {"coordinates":[115.97386169400001,-32.0032348633],"type":"Point"}
}