{
  "type": "Feature",
  "properties": {
    "iso:country":"AU",
    "sg:address":"141 Flemington Rd",
    "sg:city":"Mitchell",
    "sg:classifiers":[
        {
            "category":"Home & Garden",
            "subcategory":"Carpets & Floor Coverings",
            "type":"Retail Goods"
        }
    ],
    "sg:phone":"+61 2 6241 5666",
    "sg:postcode":"2911",
    "sg:province":"ACT",
    "sg:tags":[
        "wood"
    ],
    "wof:name":"Carpet One",
    "wof:placetype":"venue"
},
  "geometry": {"coordinates":[149.13864135700001,-35.2152290344],"type":"Point"}
}