{
  "type": "Feature",
  "properties": {
    "addr:full":"45 Quayle St Battery Point TAS 7004",
    "addr:housenumber":"45",
    "addr:postcode":"7004",
    "addr:street":"Quayle St",
    "iso:country":"AU",
    "sg:address":"45 Quayle St",
    "sg:city":"Battery Point",
    "sg:classifiers":[
        {
            "category":"Education",
            "subcategory":"Music School",
            "type":"Public Place"
        }
    ],
    "sg:phone":"+61 3 6224 8060",
    "sg:postcode":"7004",
    "sg:province":"TAS",
    "sg:tags":[
        "teacher"
    ],
    "wof:name":"Susan King",
    "wof:placetype":"venue"
},
  "geometry": {"coordinates":[147.328201294,-42.892364502],"type":"Point"}
}