{
  "type": "Feature",
  "properties": {
    "addr:full":"20 New St Woombye QLD 4559",
    "addr:housenumber":"20",
    "addr:postcode":"4559",
    "addr:street":"New St",
    "iso:country":"AU",
    "sg:address":"20 New St",
    "sg:city":"Woombye",
    "sg:classifiers":[
        {
            "category":"Building & Trades",
            "subcategory":"Construction",
            "type":"Services"
        }
    ],
    "sg:phone":"+61 411 138 081",
    "sg:postcode":"4559",
    "sg:province":"QLD",
    "sg:tags":[
        "contractor"
    ],
    "wof:name":"Kilby G M & Y M",
    "wof:placetype":"venue"
},
  "geometry": {"coordinates":[152.964553833,-26.6631832123],"type":"Point"}
}