{
  "type": "Feature",
  "properties": {
    "addr:full":"20 Vivian St Inverell NSW 2360",
    "addr:housenumber":"20",
    "addr:postcode":"2360",
    "addr:street":"Vivian St",
    "iso:country":"AU",
    "sg:address":"20 Vivian St",
    "sg:city":"Inverell",
    "sg:classifiers":[
        {
            "category":"Shopping",
            "subcategory":"Discount & Variety Stores",
            "type":"Retail Goods"
        }
    ],
    "sg:phone":"+61 2 6722 3002",
    "sg:postcode":"2360",
    "sg:province":"NSW",
    "sg:tags":[
        "shop",
        "adult"
    ],
    "wof:name":"S.S.A.O.",
    "wof:placetype":"venue"
},
  "geometry": {"coordinates":[151.11424255399999,-29.7753486633],"type":"Point"}
}