{
  "type": "Feature",
  "properties": {
    "iso:country":"AU",
    "sg:address":"35 Sale St",
    "sg:city":"Orange",
    "sg:classifiers":[
        {
            "category":"Education",
            "subcategory":"Junior College",
            "type":"Public Place"
        }
    ],
    "sg:phone":"+61 2 6362 8572",
    "sg:postcode":"2800",
    "sg:province":"NSW",
    "sg:tags":[
        "wholesaler",
        "school",
        "mfrs",
        "uniform"
    ],
    "wof:name":"Orange Clothing Company",
    "wof:placetype":"venue"
},
  "geometry": {"coordinates":[149.095947266,-33.2837791443],"type":"Point"}
}