{
  "type": "Feature",
  "properties": {
    "iso:country":"AU",
    "sg:address":"24 Oxley St",
    "sg:city":"Taree",
    "sg:classifiers":[
        {
            "category":"Professional",
            "subcategory":"Engineering",
            "type":"Services"
        }
    ],
    "sg:phone":"+61 2 6551 6888",
    "sg:postcode":"2430",
    "sg:province":"NSW",
    "sg:tags":[
        "building",
        "cladding",
        "industrial",
        "commercial"
    ],
    "wof:name":"Ranbuild",
    "wof:placetype":"venue"
},
  "geometry": {"coordinates":[152.476944,-31.90304],"type":"Point"}
}