{
  "type": "Feature",
  "properties": {
    "iso:country":"AU",
    "sg:address":"763 South Rd",
    "sg:city":"Black Forest",
    "sg:classifiers":[
        {
            "category":"Professional",
            "type":"Services"
        }
    ],
    "sg:phone":"+61 8 8371 1077",
    "sg:postcode":"5035",
    "sg:province":"SA",
    "sg:tags":[
        "packaging",
        "filling",
        "assembling"
    ],
    "wof:name":"Orana",
    "wof:placetype":"venue"
},
  "geometry": {"coordinates":[138.57310485799999,-34.9651031494],"type":"Point"}
}