{
  "type": "Feature",
  "properties": {
    "addr:full":"6/ 37 Technology Drv Warana QLD 4575",
    "addr:housenumber":"/ 37",
    "addr:postcode":"4575",
    "addr:street":"Technology Drv",
    "iso:country":"AU",
    "sg:address":"6/ 37 Technology Drv",
    "sg:city":"Warana",
    "sg:classifiers":[
        {
            "category":"Professional",
            "subcategory":"Detective & Security Services",
            "type":"Services"
        }
    ],
    "sg:phone":"+61 7 5493 6266",
    "sg:postcode":"4575",
    "sg:province":"QLD",
    "sg:tags":[
        "equipment",
        "window",
        "doors"
    ],
    "wof:name":"Shade & Security",
    "wof:placetype":"venue"
},
  "geometry": {"coordinates":[153.12750199999999,-26.724863],"type":"Point"}
}