{
  "type": "Feature",
  "properties": {
    "addr:full":"105 Seventh Ave Joslin SA 5070",
    "addr:housenumber":"105",
    "addr:postcode":"5070",
    "addr:street":"Seventh Ave",
    "iso:country":"AU",
    "sg:address":"105 Seventh Ave",
    "sg:city":"Joslin",
    "sg:classifiers":[
        {
            "category":"Organizations",
            "subcategory":"Community Association",
            "type":"Services"
        }
    ],
    "sg:phone":"+61 8 8362 6917",
    "sg:postcode":"5070",
    "sg:province":"SA",
    "sg:tags":[
        "international",
        "organisation",
        "relation",
        "aid"
    ],
    "wof:name":"Indianaid Incorporated",
    "wof:placetype":"venue"
},
  "geometry": {"coordinates":[138.624908447,-34.9000816345],"type":"Point"}
}