{
  "type": "Feature",
  "properties": {
    "iso:country":"AU",
    "sg:address":"15 Snapdragon St",
    "sg:city":"Toowoomba",
    "sg:classifiers":[
        {
            "category":"Professional",
            "subcategory":"Art Services",
            "type":"Services"
        }
    ],
    "sg:phone":"+61 7 4687 6232",
    "sg:postcode":"4350",
    "sg:province":"QLD",
    "sg:tags":[
        "decorator",
        "painter"
    ],
    "wof:name":"Carlish Trevor",
    "wof:placetype":"venue"
},
  "geometry": {"coordinates":[151.96756,-27.597956],"type":"Point"}
}