{
  "type": "Feature",
  "properties": {
    "addr:full":"7 Hallett Pl Kambah ACT 2902",
    "addr:housenumber":"7",
    "addr:postcode":"2902",
    "addr:street":"Hallett Pl",
    "iso:country":"AU",
    "sg:address":"7 Hallett Pl",
    "sg:city":"Kambah",
    "sg:classifiers":[
        {
            "category":"Utilities",
            "subcategory":"Electric",
            "type":"Services"
        }
    ],
    "sg:phone":"+61 410 625 879",
    "sg:postcode":"2902",
    "sg:province":"ACT",
    "sg:tags":[
        "electrical",
        "contractor"
    ],
    "wof:name":"Bob Dawes Electrical",
    "wof:placetype":"venue"
},
  "geometry": {"coordinates":[149.06182861299999,-35.3765449524],"type":"Point"}
}