{
  "type": "Feature",
  "properties": {
    "iso:country":"AU",
    "sg:address":"133 Great Western Hwy",
    "sg:city":"Blaxland",
    "sg:classifiers":[
        {
            "category":"Sports & Exercise",
            "subcategory":"Gym",
            "type":"Entertainment"
        }
    ],
    "sg:phone":"+61 2 4727 7710",
    "sg:postcode":"2774",
    "sg:province":"NSW",
    "sg:tags":[
        "health",
        "fitness"
    ],
    "wof:name":"Blue Mountains Pilates Studio",
    "wof:placetype":"venue"
},
  "geometry": {"coordinates":[150.612258911,-33.7458343506],"type":"Point"}
}