{
  "type": "Feature",
  "properties": {
    "addr:full":"1 Horn St Sunbury VIC 3429",
    "addr:housenumber":"1",
    "addr:postcode":"3429",
    "addr:street":"Horn St",
    "iso:country":"AU",
    "sg:address":"1 Horn St",
    "sg:city":"Sunbury",
    "sg:classifiers":[
        {
            "category":"Retail",
            "subcategory":"Auto Rental",
            "type":"Services"
        }
    ],
    "sg:phone":"+61 3 9299 5556",
    "sg:postcode":"3429",
    "sg:province":"VIC",
    "sg:tags":[
        "bus",
        "truck"
    ],
    "wof:name":"Budget Truck Rental",
    "wof:placetype":"venue"
},
  "geometry": {"coordinates":[144.728424072,-37.5758628845],"type":"Point"}
}