{
  "type": "Feature",
  "properties": {
    "addr:full":"Unit 3/ 13 Horizon Dr Beenleigh QLD 4207",
    "addr:housenumber":"13",
    "addr:postcode":"4207",
    "addr:street":"Horizon Dr",
    "iso:country":"AU",
    "sg:address":"Unit 3/ 13 Horizon Dr",
    "sg:city":"Beenleigh",
    "sg:classifiers":[
        {
            "category":"Home & Garden",
            "subcategory":"Building Materials",
            "type":"Retail Goods"
        }
    ],
    "sg:phone":"+61 7 3807 1237",
    "sg:postcode":"4207",
    "sg:province":"QLD",
    "sg:tags":[
        "merchant",
        "glass",
        "glazier"
    ],
    "wof:name":"ELF Insulated Glass Products",
    "wof:placetype":"venue"
},
  "geometry": {"coordinates":[153.182983398,-27.715877533],"type":"Point"}
}