{
  "type": "Feature",
  "properties": {
    "addr:full":"127 George St Launceston TAS 7250",
    "addr:housenumber":"127",
    "addr:postcode":"7250",
    "addr:street":"George St",
    "iso:country":"AU",
    "sg:address":"127 George St",
    "sg:city":"Launceston",
    "sg:classifiers":[
        {
            "category":"Personal",
            "subcategory":"Beauty Salon",
            "type":"Services"
        }
    ],
    "sg:phone":"+61 3 6334 8774",
    "sg:postcode":"7250",
    "sg:province":"TAS",
    "sg:website":"http://www.romanbath.com.au",
    "wof:name":"Aquarius Beauty Clinic",
    "wof:placetype":"venue"
},
  "geometry": {"coordinates":[147.14207458499999,-41.4380760193],"type":"Point"}
}