{
  "type": "Feature",
  "properties": {
    "addr:full":"8A Springvale Rd Aspendale Gardens VIC 3195",
    "addr:housenumber":"8a",
    "addr:postcode":"3195",
    "addr:street":"Springvale Rd",
    "iso:country":"AU",
    "sg:address":"8A Springvale Rd",
    "sg:city":"Aspendale Gardens",
    "sg:classifiers":[
        {
            "category":"Health Services",
            "subcategory":"Dentist",
            "type":"Services"
        }
    ],
    "sg:phone":"+61 3 9773 8688",
    "sg:postcode":"3195",
    "sg:province":"VIC",
    "wof:name":"Jaffrey Craig Dr",
    "wof:placetype":"venue"
},
  "geometry": {"coordinates":[145.132125855,-38.0261535645],"type":"Point"}
}