{
  "type": "Feature",
  "properties": {
    "iso:country":"AU",
    "sg:address":"Ground Floor, 12 Central Rd",
    "sg:city":"Miranda",
    "sg:classifiers":[
        {
            "category":"Health Services",
            "subcategory":"Doctor",
            "type":"Services"
        }
    ],
    "sg:phone":"+61 2 9540 1200",
    "sg:postcode":"2228",
    "sg:province":"NSW",
    "sg:tags":[
        "medical",
        "practitioner"
    ],
    "wof:name":"Saad George Dr",
    "wof:placetype":"venue"
},
  "geometry": {"coordinates":[151.10081481899999,-34.0329360962],"type":"Point"}
}