{
  "type": "Feature",
  "properties": {
    "iso:country":"AU",
    "sg:address":"39- 53 Shettleston St",
    "sg:city":"Rocklea",
    "sg:classifiers":[
        {
            "category":"Shopping",
            "subcategory":"Stationery & Office Supplies",
            "type":"Retail Goods"
        }
    ],
    "sg:phone":"+61 7 3268 4366",
    "sg:postcode":"4106",
    "sg:province":"QLD",
    "sg:tags":[
        "packaging",
        "material"
    ],
    "wof:name":"Containers Flexibles Pty Ltd",
    "wof:placetype":"venue"
},
  "geometry": {"coordinates":[153.00050354000001,-27.5627288818],"type":"Point"}
}