{
  "type": "Feature",
  "properties": {
    "addr:full":"WCM House 65 Hill St Roseville NSW 2069",
    "addr:housenumber":"65",
    "addr:postcode":"2069",
    "addr:street":"Hill St",
    "iso:country":"AU",
    "sg:address":"WCM House 65 Hill St",
    "sg:city":"Roseville",
    "sg:classifiers":[
        {
            "category":"Professional",
            "subcategory":"Accounting & Tax Preparation",
            "type":"Services"
        }
    ],
    "sg:phone":"+61 2 9880 9101",
    "sg:postcode":"2069",
    "sg:province":"NSW",
    "sg:tags":[
        "accountant",
        "auditor"
    ],
    "sg:website":"http://www.thetaxbase.com.au",
    "wof:name":"The Tax Base Pty Limited",
    "wof:placetype":"venue"
},
  "geometry": {"coordinates":[151.17730712900001,-33.7837486267],"type":"Point"}
}