{
  "type": "Feature",
  "properties": {
    "addr:full":"12 Numidia St Currumbin Waters QLD 4223",
    "addr:housenumber":"12",
    "addr:postcode":"4223",
    "addr:street":"Numidia St",
    "iso:country":"AU",
    "sg:address":"12 Numidia St",
    "sg:city":"Currumbin Waters",
    "sg:classifiers":[
        {
            "category":"Building & Trades",
            "subcategory":"Construction",
            "type":"Services"
        }
    ],
    "sg:phone":"+61 402 916 856",
    "sg:postcode":"4223",
    "sg:province":"QLD",
    "sg:tags":[
        "window",
        "aluminium"
    ],
    "wof:name":"S & T Installations",
    "wof:placetype":"venue"
},
  "geometry": {"coordinates":[153.460494995,-28.1396980286],"type":"Point"}
}