{
  "type": "Feature",
  "properties": {
    "iso:country":"AU",
    "sg:address":"13 McAlister St",
    "sg:city":"Darlington Point",
    "sg:classifiers":[
        {
            "category":"Building & Trades",
            "subcategory":"Landscaping Services",
            "type":"Services"
        }
    ],
    "sg:phone":"+61 2 6968 4205",
    "sg:postcode":"2706",
    "sg:province":"NSW",
    "sg:tags":[
        "grazier"
    ],
    "wof:name":"Dunvarleigh Pastoral Company",
    "wof:placetype":"venue"
},
  "geometry": {"coordinates":[145.99697875999999,-34.5707321167],"type":"Point"}
}