{
  "type": "Feature",
  "properties": {
    "iso:country":"AU",
    "sg:address":"26 Beech Rd",
    "sg:city":"Kingsley",
    "sg:classifiers":[
        {
            "category":"Government",
            "subcategory":"Post Office",
            "type":"Public Place"
        }
    ],
    "sg:phone":"+61 8 9309 4258",
    "sg:postcode":"6026",
    "sg:province":"WA",
    "sg:tags":[
        "house",
        "doll"
    ],
    "wof:name":"Darling Dolls & Bears",
    "wof:placetype":"venue"
},
  "geometry": {"coordinates":[115.795448303,-31.8190765381],"type":"Point"}
}