{
  "type": "Feature",
  "properties": {
    "iso:country":"AU",
    "sg:address":"210 Shellharbour Rd",
    "sg:city":"Warrawong",
    "sg:classifiers":[
        {
            "category":"Health Services",
            "subcategory":"Doctor",
            "type":"Services"
        }
    ],
    "sg:phone":"+61 2 4276 9800",
    "sg:postcode":"2502",
    "sg:province":"NSW",
    "sg:tags":[
        "occupational",
        "safety"
    ],
    "wof:name":"Guardian Training Services Pty Ltd",
    "wof:placetype":"venue"
},
  "geometry": {"coordinates":[150.89155600000001,-34.496338],"type":"Point"}
}