{
  "type": "Feature",
  "properties": {
    "addr:full":"18 Donaldson St Wyong North NSW 2259",
    "addr:housenumber":"18",
    "addr:postcode":"2259",
    "addr:street":"Donaldson St",
    "iso:country":"AU",
    "sg:address":"18 Donaldson St",
    "sg:city":"Wyong North",
    "sg:classifiers":[
        {
            "category":"Home & Garden",
            "subcategory":"Building Materials",
            "type":"Retail Goods"
        }
    ],
    "sg:phone":"+61 2 4351 2616",
    "sg:postcode":"2259",
    "sg:province":"NSW",
    "sg:tags":[
        "wall",
        "frame",
        "truss",
        "roof"
    ],
    "wof:name":"Heyden Frame & Truss",
    "wof:placetype":"venue"
},
  "geometry": {"coordinates":[151.44340515100001,-33.2667579651],"type":"Point"}
}