{
  "type": "Feature",
  "properties": {
    "addr:full":"PO Box 2761 Nerang East QLD 4211",
    "addr:postcode":"4211",
    "iso:country":"AU",
    "sg:address":"PO Box 2761",
    "sg:city":"Nerang East",
    "sg:classifiers":[
        {
            "category":"Building & Trades",
            "subcategory":"Construction",
            "type":"Services"
        }
    ],
    "sg:phone":"+61 13 15 46",
    "sg:postcode":"4211",
    "sg:province":"QLD",
    "sg:tags":[
        "brick",
        "paving"
    ],
    "wof:name":"Jim's Paving",
    "wof:placetype":"venue"
},
  "geometry": {"coordinates":[153.3359375,-27.9926815033],"type":"Point"}
}