{
  "type": "Feature",
  "properties": {
    "addr:full":"149 Longwarry- Drouin Rd Longwarry VIC 3816",
    "addr:housenumber":"149",
    "addr:postcode":"3816",
    "addr:street":"Longwarry Drouin Rd",
    "iso:country":"AU",
    "sg:address":"149 Longwarry- Drouin Rd",
    "sg:city":"Longwarry",
    "sg:classifiers":[
        {
            "category":"Building & Trades",
            "subcategory":"Construction",
            "type":"Services"
        }
    ],
    "sg:phone":"+61 3 5629 9472",
    "sg:postcode":"3816",
    "sg:province":"VIC",
    "sg:tags":[
        "fencing",
        "contractor"
    ],
    "wof:name":"Alby Fencing",
    "wof:placetype":"venue"
},
  "geometry": {"coordinates":[145.785538,-38.107128],"type":"Point"}
}