{
  "type": "Feature",
  "properties": {
    "addr:full":"43 Heaths Rd Hoppers Crossing VIC 3029",
    "addr:housenumber":"43",
    "addr:postcode":"3029",
    "addr:street":"Heaths Rd",
    "iso:country":"AU",
    "sg:address":"43 Heaths Rd",
    "sg:city":"Hoppers Crossing",
    "sg:classifiers":[
        {
            "category":"Autos & Motor Vehicles",
            "subcategory":"Auto Supplies",
            "type":"Retail Goods"
        }
    ],
    "sg:phone":"+61 3 9748 7022",
    "sg:postcode":"3029",
    "sg:province":"VIC",
    "sg:tags":[
        "wheel",
        "automotive",
        "rim"
    ],
    "wof:name":"Bob Jane T-Marts",
    "wof:placetype":"venue"
},
  "geometry": {"coordinates":[144.702347,-37.879684],"type":"Point"}
}