{
  "type": "Feature",
  "properties": {
    "iso:country":"AU",
    "sg:address":"Factory 5, 9 Peel St",
    "sg:city":"Eltham",
    "sg:classifiers":[
        {
            "category":"Manufacturing",
            "subcategory":"Furniture",
            "type":"Manufacturing & Wholesale Goods"
        }
    ],
    "sg:phone":"+61 3 9431 6550",
    "sg:postcode":"3095",
    "sg:province":"VIC",
    "sg:tags":[
        "builder",
        "designer",
        "custom"
    ],
    "wof:name":"Soul Of The Tree",
    "wof:placetype":"venue"
},
  "geometry": {"coordinates":[145.138961792,-37.7198600769],"type":"Point"}
}