{
  "type": "Feature",
  "properties": {
    "addr:full":"1/ 6 Auster Crt Glass House Mountains QLD 4518",
    "addr:housenumber":"/ 6",
    "addr:postcode":"4518",
    "addr:street":"Auster Crt",
    "iso:country":"AU",
    "sg:address":"1/ 6 Auster Crt",
    "sg:city":"Glass House Mountains",
    "sg:classifiers":[
        {
            "category":"Retail",
            "subcategory":"Storage",
            "type":"Services"
        }
    ],
    "sg:phone":"+61 7 5493 0404",
    "sg:postcode":"4518",
    "sg:province":"QLD",
    "sg:tags":[
        "removal",
        "furniture"
    ],
    "wof:name":"Blue Cube Removals & Storage",
    "wof:placetype":"venue"
},
  "geometry": {"coordinates":[152.95967102,-26.8700523376],"type":"Point"}
}