{
  "type": "Feature",
  "properties": {
    "addr:full":"85 Dunsborough Lakes Drv Dunsborough WA 6281",
    "addr:housenumber":"85",
    "addr:postcode":"6281",
    "addr:street":"Dunsborough Lakes Drv",
    "iso:country":"AU",
    "sg:address":"85 Dunsborough Lakes Drv",
    "sg:city":"Dunsborough",
    "sg:classifiers":[
        {
            "category":"Manufacturing",
            "subcategory":"Food",
            "type":"Manufacturing & Wholesale Goods"
        }
    ],
    "sg:phone":"+61 8 9755 3812",
    "sg:postcode":"6281",
    "sg:province":"WA",
    "sg:tags":[
        "function",
        "catering"
    ],
    "wof:name":"Olsen's Catering",
    "wof:placetype":"venue"
},
  "geometry": {"coordinates":[115.09992981000001,-33.6282348633],"type":"Point"}
}