{
  "type": "Feature",
  "properties": {
    "addr:full":"32 Tulkara St Manly West QLD 4179",
    "addr:housenumber":"32",
    "addr:postcode":"4179",
    "addr:street":"Tulkara St",
    "iso:country":"AU",
    "sg:address":"32 Tulkara St",
    "sg:city":"Manly West",
    "sg:classifiers":[
        {
            "category":"Personal",
            "subcategory":"Beauty Salon",
            "type":"Services"
        }
    ],
    "sg:phone":"+61 7 3396 2962",
    "sg:postcode":"4179",
    "sg:province":"QLD",
    "sg:tags":[
        "hairdresser"
    ],
    "wof:name":"Jazz Hair Studio",
    "wof:placetype":"venue"
},
  "geometry": {"coordinates":[153.16543579099999,-27.4652023315],"type":"Point"}
}