{
  "type": "Feature",
  "properties": {
    "addr:full":"Cnr Graham & Mackenzie Sts Ayr QLD 4807",
    "addr:postcode":"4807",
    "addr:street":"Cnr;Sts",
    "iso:country":"AU",
    "sg:address":"Cnr Graham & Mackenzie Sts",
    "sg:city":"Ayr",
    "sg:classifiers":[
        {
            "category":"Autos & Motor Vehicles",
            "subcategory":"Boat Sales",
            "type":"Retail Goods"
        }
    ],
    "sg:phone":"+61 7 4783 2342",
    "sg:postcode":"4807",
    "sg:province":"QLD",
    "sg:tags":[
        "equipment",
        "yacht"
    ],
    "wof:name":"Jarvis G S & Sons",
    "wof:placetype":"venue"
},
  "geometry": {"coordinates":[147.40640258799999,-19.5728187561],"type":"Point"}
}