{
  "type": "Feature",
  "properties": {
    "addr:full":"125 Barker St Casino NSW 2470",
    "addr:housenumber":"125",
    "addr:postcode":"2470",
    "addr:street":"Barker St",
    "iso:country":"AU",
    "sg:address":"125 Barker St",
    "sg:city":"Casino",
    "sg:classifiers":[
        {
            "category":"Health Services",
            "subcategory":"Health Practitioner",
            "type":"Services"
        }
    ],
    "sg:phone":"+61 2 6662 2848",
    "sg:postcode":"2470",
    "sg:province":"NSW",
    "sg:tags":[
        "psychotherapist"
    ],
    "wof:name":"Upper Clarence Counselling",
    "wof:placetype":"venue"
},
  "geometry": {"coordinates":[153.04751586899999,-28.8649787903],"type":"Point"}
}