{
  "type": "Feature",
  "properties": {
    "addr:full":"Level 6 90 Mount St North Sydney NSW 1522",
    "addr:housenumber":"90",
    "addr:postcode":"1522",
    "addr:street":"Mount St",
    "iso:country":"AU",
    "sg:address":"Level 6 90 Mount St",
    "sg:city":"North Sydney",
    "sg:classifiers":[
        {
            "category":"Home & Garden",
            "subcategory":"Hardware",
            "type":"Retail Goods"
        }
    ],
    "sg:phone":"+61 1800 640 611",
    "sg:postcode":"1522",
    "sg:province":"NSW",
    "sg:tags":[
        "compressor",
        "air"
    ],
    "wof:name":"Kaeser Compressors",
    "wof:placetype":"venue"
},
  "geometry": {"coordinates":[151.20843505900001,-33.8389015198],"type":"Point"}
}