{
  "type": "Feature",
  "properties": {
    "iso:country":"AU",
    "sg:address":"58 Beerburn Rd",
    "sg:city":"Caboolture",
    "sg:classifiers":[
        {
            "category":"Farming",
            "subcategory":"Farm & Veterinary Services",
            "type":"Manufacturing & Wholesale Goods"
        }
    ],
    "sg:phone":"+61 7 5499 4690",
    "sg:postcode":"4510",
    "sg:province":"QLD",
    "sg:tags":[
        "irrigation",
        "reticulation",
        "system"
    ],
    "wof:name":"Water Specialists Australia",
    "wof:placetype":"venue"
},
  "geometry": {"coordinates":[152.950424,-27.076593],"type":"Point"}
}