{
  "type": "Feature",
  "properties": {
    "addr:full":"76 Porter St Gwelup WA 6018",
    "addr:housenumber":"76",
    "addr:postcode":"6018",
    "addr:street":"Porter St",
    "iso:country":"AU",
    "sg:address":"76 Porter St",
    "sg:city":"Gwelup",
    "sg:classifiers":[
        {
            "category":"Building & Trades",
            "subcategory":"Plumbing",
            "type":"Services"
        }
    ],
    "sg:phone":"+61 8 9445 1600",
    "sg:postcode":"6018",
    "sg:province":"WA",
    "sg:tags":[
        "equipment",
        "valves"
    ],
    "wof:name":"Palvalve Pacific Pty Ltd",
    "wof:placetype":"venue"
},
  "geometry": {"coordinates":[115.796707153,-31.8703193665],"type":"Point"}
}