{
  "type": "Feature",
  "properties": {
    "addr:full":"Melbourne Hotel, Edmondstone St West End QLD 4101",
    "addr:postcode":"4101",
    "addr:street":"St",
    "iso:country":"AU",
    "sg:address":"Melbourne Hotel, Edmondstone St",
    "sg:city":"West End",
    "sg:classifiers":[
        {
            "category":"Food & Beverages",
            "subcategory":"Liquor & Beverages",
            "type":"Retail Goods"
        }
    ],
    "sg:phone":"+61 7 3844 1571",
    "sg:postcode":"4101",
    "sg:province":"QLD",
    "sg:tags":[
        "store"
    ],
    "wof:name":"Liquor King",
    "wof:placetype":"venue"
},
  "geometry": {"coordinates":[153.015426636,-27.4791622162],"type":"Point"}
}