{
  "type": "Feature",
  "properties": {
    "iso:country":"AU",
    "sg:address":"363 Lonsdale St",
    "sg:city":"Dandenong",
    "sg:classifiers":[
        {
            "category":"Personal",
            "subcategory":"Tanning Parlor",
            "type":"Services"
        }
    ],
    "sg:phone":"+61 3 9793 0001",
    "sg:postcode":"3175",
    "sg:province":"VIC",
    "sg:tags":[
        "solarium"
    ],
    "wof:name":"Tan & Beauty Pty Ltd",
    "wof:placetype":"venue"
},
  "geometry": {"coordinates":[145.213821411,-37.9850692749],"type":"Point"}
}