{
  "type": "Feature",
  "properties": {
    "addr:full":"10- 12 Cannan St South Townsville QLD 4810",
    "addr:housenumber":"12",
    "addr:postcode":"4810",
    "addr:street":"Cannan St",
    "iso:country":"AU",
    "sg:address":"10- 12 Cannan St",
    "sg:city":"South Townsville",
    "sg:classifiers":[
        {
            "category":"Autos & Motor Vehicles",
            "subcategory":"Auto Supplies",
            "type":"Retail Goods"
        }
    ],
    "sg:phone":"+61 7 4789 7303",
    "sg:postcode":"4810",
    "sg:province":"QLD",
    "sg:tags":[
        "part",
        "cycles",
        "accessory"
    ],
    "wof:name":"Bravo Distribution Pty Ltd",
    "wof:placetype":"venue"
},
  "geometry": {"coordinates":[146.82873499999999,-19.262833],"type":"Point"}
}