{
  "type": "Feature",
  "properties": {
    "addr:full":"72 Guthrie St Osborne Park WA 6017",
    "addr:housenumber":"72",
    "addr:postcode":"6017",
    "addr:street":"Guthrie St",
    "iso:country":"AU",
    "sg:address":"72 Guthrie St",
    "sg:city":"Osborne Park",
    "sg:classifiers":[
        {
            "category":"Wholesale",
            "subcategory":"Auto Parts",
            "type":"Manufacturing & Wholesale Goods"
        }
    ],
    "sg:phone":"+61 8 9242 7221",
    "sg:postcode":"6017",
    "sg:province":"WA",
    "sg:tags":[
        "transmission",
        "automotive",
        "truck"
    ],
    "wof:name":"Automatic Transmissions R Us",
    "wof:placetype":"venue"
},
  "geometry": {"coordinates":[115.815109253,-31.9055557251],"type":"Point"}
}