{
  "type": "Feature",
  "properties": {
    "addr:full":"Lot 9036/ New England Hwy Muswellbrook NSW 2333",
    "addr:housenumber":"9036",
    "addr:postcode":"2333",
    "addr:street":"New England Hwy",
    "iso:country":"AU",
    "sg:address":"Lot 9036/ New England Hwy",
    "sg:city":"Muswellbrook",
    "sg:classifiers":[
        {
            "category":"Building & Trades",
            "subcategory":"Landscaping Services",
            "type":"Services"
        }
    ],
    "sg:phone":"+61 2 6543 2814",
    "sg:postcode":"2333",
    "sg:province":"NSW",
    "sg:tags":[
        "grazier"
    ],
    "wof:name":"Perram H C",
    "wof:placetype":"venue"
},
  "geometry": {"coordinates":[150.88752746599999,-32.268901825],"type":"Point"}
}