{
  "type": "Feature",
  "properties": {
    "iso:country":"AU",
    "sg:address":"173 Great Eastern Hwy",
    "sg:city":"Midland",
    "sg:classifiers":[
        {
            "category":"Building & Trades",
            "subcategory":"Construction",
            "type":"Services"
        }
    ],
    "sg:phone":"+61 8 9250 1883",
    "sg:postcode":"6056",
    "sg:province":"WA",
    "sg:tags":[
        "window",
        "tinting"
    ],
    "wof:name":"Instant Tint",
    "wof:placetype":"venue"
},
  "geometry": {"coordinates":[116.00969696,-31.8909912109],"type":"Point"}
}