{
  "type": "Feature",
  "properties": {
    "addr:full":"13 Collier Rd Morley WA 6062",
    "addr:housenumber":"13",
    "addr:postcode":"6062",
    "addr:street":"Collier Rd",
    "iso:country":"AU",
    "sg:address":"13 Collier Rd",
    "sg:city":"Morley",
    "sg:classifiers":[
        {
            "category":"Professional",
            "subcategory":"Accounting & Tax Preparation",
            "type":"Services"
        }
    ],
    "sg:phone":"+61 8 9276 1650",
    "sg:postcode":"6062",
    "sg:province":"WA",
    "sg:tags":[
        "consultant",
        "taxation"
    ],
    "wof:name":"A.J. Thornett & Associates",
    "wof:placetype":"venue"
},
  "geometry": {"coordinates":[115.902587891,-31.8955135345],"type":"Point"}
}