{
  "type": "Feature",
  "properties": {
    "iso:country":"AU",
    "sg:address":"15 Billing St",
    "sg:city":"Mt Waverley",
    "sg:classifiers":[
        {
            "category":"Home & Garden",
            "subcategory":"Building Materials",
            "type":"Retail Goods"
        }
    ],
    "sg:phone":"+61 412 135 307",
    "sg:postcode":"3149",
    "sg:province":"VIC",
    "sg:tags":[
        "lawn",
        "cutting",
        "maintenance"
    ],
    "wof:name":"P & L Allen & Daughters",
    "wof:placetype":"venue"
},
  "geometry": {"coordinates":[145.11816406200001,-37.8785552979],"type":"Point"}
}