{
  "type": "Feature",
  "properties": {
    "addr:full":"20 Liston St Burwood VIC 3125",
    "addr:housenumber":"20",
    "addr:postcode":"3125",
    "addr:street":"Liston St",
    "iso:country":"AU",
    "sg:address":"20 Liston St",
    "sg:city":"Burwood",
    "sg:classifiers":[
        {
            "category":"Professional",
            "subcategory":"Employment Agencies",
            "type":"Services"
        }
    ],
    "sg:phone":"+61 3 9809 1099",
    "sg:postcode":"3125",
    "sg:province":"VIC",
    "wof:name":"Pharm Hands",
    "wof:placetype":"venue"
},
  "geometry": {"coordinates":[145.08714294399999,-37.8589935303],"type":"Point"}
}