{
  "type": "Feature",
  "properties": {
    "addr:full":"99 Grendon St North Mackay QLD 4740",
    "addr:housenumber":"99",
    "addr:postcode":"4740",
    "addr:street":"Grendon St",
    "iso:country":"AU",
    "sg:address":"99 Grendon St",
    "sg:city":"North Mackay",
    "sg:classifiers":[
        {
            "category":"Transit Center",
            "subcategory":"Freight",
            "type":"Transportation"
        }
    ],
    "sg:phone":"+61 7 4953 3160",
    "sg:postcode":"4740",
    "sg:province":"QLD",
    "sg:tags":[
        "honey",
        "merchant"
    ],
    "wof:name":"Whitsunday Honey",
    "wof:placetype":"venue"
},
  "geometry": {"coordinates":[149.19000199999999,-21.115887],"type":"Point"}
}