{
  "type": "Feature",
  "properties": {
    "addr:full":"160 Central, 811 Hay St Perth WA 6000",
    "addr:housenumber":"160",
    "addr:postcode":"6000",
    "addr:street":"Central 811 Hay St",
    "iso:country":"AU",
    "sg:address":"160 Central, 811 Hay St",
    "sg:city":"Perth",
    "sg:classifiers":[
        {
            "category":"Food & Beverages",
            "subcategory":"Bakery",
            "type":"Retail Goods"
        }
    ],
    "sg:phone":"+61 8 9226 1300",
    "sg:postcode":"6000",
    "sg:province":"WA",
    "sg:tags":[
        "cake",
        "shop",
        "pastry"
    ],
    "wof:name":"Miss Maud Swedish Pastry Houses",
    "wof:placetype":"venue"
},
  "geometry": {"coordinates":[115.854820252,-31.9529857635],"type":"Point"}
}