{
  "type": "Feature",
  "properties": {
    "iso:country":"AU",
    "sg:address":"648 High St",
    "sg:city":"Reservoir",
    "sg:classifiers":[
        {
            "category":"Government",
            "subcategory":"Court House",
            "type":"Public Place"
        }
    ],
    "sg:phone":"+61 3 8650 6200",
    "sg:postcode":"3073",
    "sg:province":"VIC",
    "sg:tags":[
        "personal",
        "marriage",
        "family",
        "counselling"
    ],
    "wof:name":"LifeWorks Relationship Counselling & Education Services",
    "wof:placetype":"venue"
},
  "geometry": {"coordinates":[145.00743102999999,-37.7181243896],"type":"Point"}
}