{
  "type": "Feature",
  "properties": {
    "addr:full":"20 Glassman Drv Yatala QLD 4207",
    "addr:housenumber":"20",
    "addr:postcode":"4207",
    "addr:street":"Glassman Drv",
    "iso:country":"AU",
    "sg:address":"20 Glassman Drv",
    "sg:city":"Yatala",
    "sg:classifiers":[
        {
            "category":"Home & Garden",
            "subcategory":"Building Materials",
            "type":"Retail Goods"
        }
    ],
    "sg:phone":"+61 1800 199 932",
    "sg:postcode":"4207",
    "sg:province":"QLD",
    "sg:tags":[
        "balustrading"
    ],
    "wof:name":"Absolute Glass Products Pty Ltd",
    "wof:placetype":"venue"
},
  "geometry": {"coordinates":[153.15643310600001,-27.7015972137],"type":"Point"}
}