{
  "type": "Feature",
  "properties": {
    "iso:country":"AU",
    "sg:address":"PO Box 4007",
    "sg:city":"Mandurah North",
    "sg:classifiers":[
        {
            "category":"Recreation",
            "subcategory":"Boat Charter",
            "type":"Entertainment"
        }
    ],
    "sg:phone":"+61 1800 601 588",
    "sg:postcode":"6210",
    "sg:province":"WA",
    "wof:name":"Rock Island Charters",
    "wof:placetype":"venue"
},
  "geometry": {"coordinates":[115.784447,-32.510052],"type":"Point"}
}