{
  "type": "Feature",
  "properties": {
    "iso:country":"AU",
    "sg:address":"148 Archer St",
    "sg:city":"Rockhampton",
    "sg:classifiers":[
        {
            "category":"Education",
            "subcategory":"Kindergarten",
            "type":"Public Place"
        }
    ],
    "sg:phone":"+61 7 4927 6877",
    "sg:postcode":"4700",
    "sg:province":"QLD",
    "sg:tags":[
        "pre-schools"
    ],
    "wof:name":"Archer Street Child Care Centre",
    "wof:placetype":"venue"
},
  "geometry": {"coordinates":[150.49603271500001,-23.3841991425],"type":"Point"}
}