{
  "type": "Feature",
  "properties": {
    "iso:country":"AU",
    "sg:address":"200 Gayndah Rd",
    "sg:city":"Maryborough",
    "sg:classifiers":[
        {
            "category":"Organizations",
            "subcategory":"Membership Organization",
            "type":"Services"
        }
    ],
    "sg:phone":"+61 7 4123 2211",
    "sg:postcode":"4650",
    "sg:province":"QLD",
    "sg:tags":[
        "club",
        "car"
    ],
    "wof:name":"Fraser Coast Historic Vehicle Club Inc",
    "wof:placetype":"venue"
},
  "geometry": {"coordinates":[152.66871599999999,-25.517176],"type":"Point"}
}