{
  "type": "Feature",
  "properties": {
    "addr:full":"706 / 220 Collins St Melbourne VIC 3000",
    "addr:housenumber":"706 / 220",
    "addr:postcode":"3000",
    "addr:street":"Collins St",
    "iso:country":"AU",
    "sg:address":"706 / 220 Collins St",
    "sg:city":"Melbourne",
    "sg:classifiers":[
        {
            "category":"Organizations",
            "subcategory":"Professional Association",
            "type":"Services"
        }
    ],
    "sg:phone":"+61 438 568 394",
    "sg:postcode":"3000",
    "sg:province":"VIC",
    "sg:tags":[
        "web",
        "internet"
    ],
    "wof:name":"Ausmedia Network",
    "wof:placetype":"venue"
},
  "geometry": {"coordinates":[144.96635437,-37.815410614],"type":"Point"}
}