{
  "type": "Feature",
  "properties": {
    "iso:country":"AU",
    "sg:address":"2 Cecil Pl",
    "sg:city":"Prahran",
    "sg:classifiers":[
        {
            "category":"Personal",
            "subcategory":"Massage",
            "type":"Services"
        }
    ],
    "sg:phone":"+61 418 724 958",
    "sg:postcode":"3181",
    "sg:province":"VIC",
    "sg:tags":[
        "therapy"
    ],
    "wof:name":"Tania Curtis",
    "wof:placetype":"venue"
},
  "geometry": {"coordinates":[144.99447631800001,-37.8503494263],"type":"Point"}
}