{
  "type": "Feature",
  "properties": {
    "addr:full":"PO Box 786 Manly NSW 1655",
    "addr:postcode":"1655",
    "iso:country":"AU",
    "sg:address":"PO Box 786",
    "sg:city":"Manly",
    "sg:classifiers":[
        {
            "category":"Professional",
            "subcategory":"Computer Services",
            "type":"Services"
        }
    ],
    "sg:phone":"+61 1300 662 626",
    "sg:postcode":"1655",
    "sg:province":"NSW",
    "sg:tags":[
        "package",
        "software"
    ],
    "wof:name":"Interacct Software Pty Ltd",
    "wof:placetype":"venue"
},
  "geometry": {"coordinates":[151.288040161,-33.7971382141],"type":"Point"}
}