{
  "type": "Feature",
  "properties": {
    "iso:country":"AU",
    "sg:address":"Unit 5/ 1 McRoyle St",
    "sg:city":"Wacol",
    "sg:classifiers":[
        {
            "category":"Banks & Credit Unions",
            "subcategory":"Bureau De Change",
            "type":"Services"
        }
    ],
    "sg:phone":"+61 7 3271 5199",
    "sg:postcode":"4076",
    "sg:province":"QLD",
    "sg:tags":[
        "gas",
        "natural",
        "lp",
        "equipment"
    ],
    "wof:name":"Carole Park Automotive Services",
    "wof:placetype":"venue"
},
  "geometry": {"coordinates":[152.936737061,-27.5976467133],"type":"Point"}
}