{
  "type": "Feature",
  "properties": {
    "iso:country":"AU",
    "sg:address":"145 Beach St",
    "sg:city":"Frankston",
    "sg:classifiers":[
        {
            "category":"Personal",
            "type":"Services"
        }
    ],
    "sg:phone":"+61 3 9770 0777",
    "sg:postcode":"3199",
    "sg:province":"VIC",
    "sg:tags":[
        "nappy"
    ],
    "wof:name":"Nappyland",
    "wof:placetype":"venue"
},
  "geometry": {"coordinates":[144.92715454099999,-37.8395576477],"type":"Point"}
}