{
  "type": "Feature",
  "properties": {
    "addr:full":"57 Main St Pakenham VIC 3810",
    "addr:housenumber":"57",
    "addr:postcode":"3810",
    "addr:street":"Main St",
    "iso:country":"AU",
    "sg:address":"57 Main St",
    "sg:city":"Pakenham",
    "sg:classifiers":[
        {
            "category":"Social Services",
            "subcategory":"Child Care",
            "type":"Services"
        }
    ],
    "sg:phone":"+61 3 5940 2466",
    "sg:postcode":"3810",
    "sg:province":"VIC",
    "wof:name":"Future Kids",
    "wof:placetype":"venue"
},
  "geometry": {"coordinates":[145.48028600000001,-38.076416],"type":"Point"}
}