{
  "type": "Feature",
  "properties": {
    "iso:country":"AU",
    "sg:address":"Unit 3/ 35 Machinery Drv",
    "sg:city":"Tweed Heads South",
    "sg:classifiers":[
        {
            "category":"Wholesale",
            "subcategory":"Metals & Minerals",
            "type":"Manufacturing & Wholesale Goods"
        }
    ],
    "sg:phone":"+61 407 231 028",
    "sg:postcode":"2486",
    "sg:province":"NSW",
    "sg:tags":[
        "steel",
        "stainless",
        "product",
        "equipment"
    ],
    "wof:name":"Strictly Stainless",
    "wof:placetype":"venue"
},
  "geometry": {"coordinates":[153.542892456,-28.2038803101],"type":"Point"}
}