{
  "type": "Feature",
  "properties": {
    "addr:full":"38 Nelson St Stepney SA 5069",
    "addr:housenumber":"38",
    "addr:postcode":"5069",
    "addr:street":"Nelson St",
    "iso:country":"AU",
    "sg:address":"38 Nelson St",
    "sg:city":"Stepney",
    "sg:classifiers":[
        {
            "category":"Wholesale",
            "subcategory":"Painting Supplies",
            "type":"Manufacturing & Wholesale Goods"
        }
    ],
    "sg:phone":"+61 8 8362 6817",
    "sg:postcode":"5069",
    "sg:province":"SA",
    "sg:tags":[
        "product",
        "cleaning"
    ],
    "wof:name":"Friendly Cleaning Supplies",
    "wof:placetype":"venue"
},
  "geometry": {"coordinates":[138.62884521500001,-34.9111061096],"type":"Point"}
}