{
  "type": "Feature",
  "properties": {
    "addr:full":"60 Elphin Rd Launceston TAS 7250",
    "addr:housenumber":"60",
    "addr:postcode":"7250",
    "addr:street":"Elphin Rd",
    "iso:country":"AU",
    "sg:address":"60 Elphin Rd",
    "sg:city":"Launceston",
    "sg:classifiers":[
        {
            "category":"Health Services",
            "subcategory":"Chiropractor",
            "type":"Services"
        }
    ],
    "sg:phone":"+61 3 6331 3411",
    "sg:postcode":"7250",
    "sg:province":"TAS",
    "wof:name":"Tamar Chiropractic",
    "wof:placetype":"venue"
},
  "geometry": {"coordinates":[147.151733398,-41.4333076477],"type":"Point"}
}