{
  "type": "Feature",
  "properties": {
    "iso:country":"AU",
    "sg:address":"12 Vereker St",
    "sg:city":"Humpty Doo",
    "sg:classifiers":[
        {
            "category":"Real Estate",
            "subcategory":"Real Estate Agent",
            "type":"Services"
        }
    ],
    "sg:phone":"+61 8 8988 2343",
    "sg:postcode":"0836",
    "sg:province":"NT",
    "wof:name":"Litchfield Realty",
    "wof:placetype":"venue"
},
  "geometry": {"coordinates":[131.10025,-12.57369],"type":"Point"}
}