{
  "type": "Feature",
  "properties": {
    "addr:full":"Level 2/ 68 Alfred St Milsons Point NSW 2061",
    "addr:housenumber":"/ 68",
    "addr:postcode":"2061",
    "addr:street":"Alfred St",
    "iso:country":"AU",
    "sg:address":"Level 2/ 68 Alfred St",
    "sg:city":"Milsons Point",
    "sg:classifiers":[
        {
            "category":"Professional",
            "subcategory":"Art Services",
            "type":"Services"
        }
    ],
    "sg:phone":"+61 2 9492 1900",
    "sg:postcode":"2061",
    "sg:province":"NSW",
    "sg:tags":[
        "graphic",
        "designer"
    ],
    "wof:name":"The Gallery",
    "wof:placetype":"venue"
},
  "geometry": {"coordinates":[151.21127319300001,-33.8465003967],"type":"Point"}
}