{
  "type": "Feature",
  "properties": {
    "addr:full":"U 6/ 3 Dewar St Mission Beach QLD 4852",
    "addr:housenumber":"3",
    "addr:postcode":"4852",
    "addr:street":"Dewar St",
    "iso:country":"AU",
    "sg:address":"U 6/ 3 Dewar St",
    "sg:city":"Mission Beach",
    "sg:classifiers":[
        {
            "category":"Farming",
            "subcategory":"Vineyard",
            "type":"Manufacturing & Wholesale Goods"
        }
    ],
    "sg:phone":"+61 7 4088 6888",
    "sg:postcode":"4852",
    "sg:province":"QLD",
    "sg:tags":[
        "winery"
    ],
    "wof:name":"Paradise Estate Wines",
    "wof:placetype":"venue"
},
  "geometry": {"coordinates":[146.09048461899999,-17.8704109192],"type":"Point"}
}