{
  "type": "Feature",
  "properties": {
    "iso:country":"AU",
    "sg:address":"131 Victoria Rd",
    "sg:city":"Lilydale",
    "sg:classifiers":[
        {
            "category":"Building & Trades",
            "subcategory":"Construction",
            "type":"Services"
        }
    ],
    "sg:phone":"+61 448 520 528",
    "sg:postcode":"3140",
    "sg:province":"VIC",
    "sg:tags":[
        "fencing",
        "contractor"
    ],
    "wof:name":"Stevens Fencing",
    "wof:placetype":"venue"
},
  "geometry": {"coordinates":[145.33663940400001,-37.7472953796],"type":"Point"}
}