{
  "type": "Feature",
  "properties": {
    "iso:country":"AU",
    "sg:address":"9 Viscount Drv",
    "sg:city":"Doncaster",
    "sg:classifiers":[
        {
            "category":"Shopping",
            "subcategory":"Stationery & Office Supplies",
            "type":"Retail Goods"
        }
    ],
    "sg:phone":"+61 3 9848 4346",
    "sg:postcode":"3108",
    "sg:province":"VIC",
    "sg:tags":[
        "equipment",
        "facsimile"
    ],
    "wof:name":"Mr Fax Pty Ltd",
    "wof:placetype":"venue"
},
  "geometry": {"coordinates":[145.13008117699999,-37.7725982666],"type":"Point"}
}