{
  "type": "Feature",
  "properties": {
    "iso:country":"AU",
    "sg:address":"467 Greenwattle St",
    "sg:city":"Toowoomba",
    "sg:classifiers":[
        {
            "category":"Retail",
            "subcategory":"Auto Repair",
            "type":"Services"
        }
    ],
    "sg:phone":"+61 7 4634 0500",
    "sg:postcode":"4350",
    "sg:province":"QLD",
    "sg:tags":[
        "bus",
        "truck"
    ],
    "wof:name":"Bromac Panel & Paint",
    "wof:placetype":"venue"
},
  "geometry": {"coordinates":[151.91423,-27.569923],"type":"Point"}
}