{
  "type": "Feature",
  "properties": {
    "iso:country":"AU",
    "sg:address":"Level 2, Hoyts Regent 167",
    "sg:city":"Queen Street Mall Brisbane",
    "sg:classifiers":[
        {
            "category":"Health Services",
            "subcategory":"Dentist",
            "type":"Services"
        }
    ],
    "sg:phone":"+61 7 3221 8225",
    "sg:postcode":"4000",
    "sg:province":"QLD",
    "sg:website":"http://www.cosmeticdentistry.com.au",
    "wof:name":"Bennett Clive",
    "wof:placetype":"venue"
},
  "geometry": {"coordinates":[153.01336669899999,-27.4614105225],"type":"Point"}
}