{
  "type": "Feature",
  "properties": {
    "iso:country":"AU",
    "sg:address":"PO Box 158",
    "sg:city":"Mt Macedon",
    "sg:classifiers":[
        {
            "category":"Professional",
            "type":"Services"
        }
    ],
    "sg:phone":"+61 3 5426 4204",
    "sg:postcode":"3441",
    "sg:province":"VIC",
    "sg:tags":[
        "forwarding",
        "agent",
        "transport"
    ],
    "wof:name":"M P S Transport Pty Ltd",
    "wof:placetype":"venue"
},
  "geometry": {"coordinates":[144.59248352,-37.389881134],"type":"Point"}
}