{
  "type": "Feature",
  "properties": {
    "iso:country":"AU",
    "sg:address":"Holt Pl",
    "sg:city":"Holt",
    "sg:classifiers":[
        {
            "category":"Food & Beverages",
            "subcategory":"Liquor & Beverages",
            "type":"Retail Goods"
        }
    ],
    "sg:phone":"+61 2 6254 4694",
    "sg:postcode":"2615",
    "sg:province":"ACT",
    "sg:tags":[
        "store"
    ],
    "wof:name":"Local Liquor",
    "wof:placetype":"venue"
},
  "geometry": {"coordinates":[149.01193237300001,-35.2249565125],"type":"Point"}
}