{
  "type": "Feature",
  "properties": {
    "addr:full":"609 Gilbert Rd Preston VIC 3072",
    "addr:housenumber":"609",
    "addr:postcode":"3072",
    "addr:street":"Gilbert Rd",
    "iso:country":"AU",
    "sg:address":"609 Gilbert Rd",
    "sg:city":"Preston",
    "sg:classifiers":[
        {
            "category":"Fast Food",
            "type":"Food & Drink"
        }
    ],
    "sg:phone":"+61 3 9478 5937",
    "sg:postcode":"3072",
    "sg:province":"VIC",
    "sg:tags":[
        "away",
        "take"
    ],
    "wof:name":"Moon Palace Take Away Chinese Food",
    "wof:placetype":"venue"
},
  "geometry": {"coordinates":[144.99139404300001,-37.7287483215],"type":"Point"}
}