{
  "type": "Feature",
  "properties": {
    "iso:country":"AU",
    "sg:address":"76 York St",
    "sg:city":"Launceston",
    "sg:classifiers":[
        {
            "category":"Professional",
            "subcategory":"Accounting & Tax Preparation",
            "type":"Services"
        }
    ],
    "sg:phone":"+61 3 6333 0311",
    "sg:postcode":"7250",
    "sg:province":"TAS",
    "sg:tags":[
        "accountant",
        "auditor"
    ],
    "wof:name":"Cindy Evans",
    "wof:placetype":"venue"
},
  "geometry": {"coordinates":[147.14187622099999,-41.4371261597],"type":"Point"}
}