{
  "type": "Feature",
  "properties": {
    "iso:country":"AU",
    "sg:address":"198 Kelly St",
    "sg:city":"Scone",
    "sg:classifiers":[
        {
            "category":"Farming",
            "subcategory":"Crops",
            "type":"Manufacturing & Wholesale Goods"
        }
    ],
    "sg:phone":"+61 2 6545 1211",
    "sg:postcode":"2337",
    "sg:province":"NSW",
    "sg:tags":[
        "warehousing"
    ],
    "wof:name":"Scone Mini Storage Pty Ltd",
    "wof:placetype":"venue"
},
  "geometry": {"coordinates":[150.86756897000001,-32.0517082214],"type":"Point"}
}