{
  "type": "Feature",
  "properties": {
    "iso:country":"AU",
    "sg:address":"3 Cheddar St",
    "sg:city":"Blakehurst",
    "sg:classifiers":[
        {
            "category":"Health Services",
            "subcategory":"Doctor",
            "type":"Services"
        }
    ],
    "sg:phone":"+61 2 9546 1200",
    "sg:postcode":"2221",
    "sg:province":"NSW",
    "sg:tags":[
        "podiatrist"
    ],
    "wof:name":"Birchall B E",
    "wof:placetype":"venue"
},
  "geometry": {"coordinates":[151.111495972,-33.9806671143],"type":"Point"}
}