{
  "type": "Feature",
  "properties": {
    "addr:full":"140 High St Willoughby NSW 2068",
    "addr:housenumber":"140",
    "addr:postcode":"2068",
    "addr:street":"High St",
    "iso:country":"AU",
    "sg:address":"140 High St",
    "sg:city":"Willoughby",
    "sg:classifiers":[
        {
            "category":"Building & Trades",
            "subcategory":"Pest Control",
            "type":"Services"
        }
    ],
    "sg:phone":"+61 2 9967 2050",
    "sg:postcode":"2068",
    "sg:province":"NSW",
    "wof:name":"Pest Inspection Services Pty Ltd",
    "wof:placetype":"venue"
},
  "geometry": {"coordinates":[151.20191955600001,-33.7992630005],"type":"Point"}
}