{
  "type": "Feature",
  "properties": {
    "iso:country":"AU",
    "sg:address":"131 Stirling Hwy",
    "sg:city":"Nedlands",
    "sg:classifiers":[
        {
            "category":"Restaurant",
            "type":"Food & Drink"
        }
    ],
    "sg:phone":"+61 8 9386 5886",
    "sg:postcode":"6009",
    "sg:province":"WA",
    "wof:name":"Chez Pierre",
    "wof:placetype":"venue"
},
  "geometry": {"coordinates":[115.79789,-31.97998],"type":"Point"}
}