{
  "type": "Feature",
  "properties": {
    "addr:full":"4 Club Crt Mansfield VIC 3722",
    "addr:housenumber":"4",
    "addr:postcode":"3722",
    "addr:street":"Club Crt",
    "iso:country":"AU",
    "sg:address":"4 Club Crt",
    "sg:city":"Mansfield",
    "sg:classifiers":[
        {
            "category":"Banks & Credit Unions",
            "subcategory":"Bureau De Change",
            "type":"Services"
        }
    ],
    "sg:phone":"+61 3 5779 1091",
    "sg:postcode":"3722",
    "sg:province":"VIC",
    "sg:tags":[
        "repairs",
        "part",
        "appliance",
        "electrical"
    ],
    "wof:name":"Michael Saville",
    "wof:placetype":"venue"
},
  "geometry": {"coordinates":[146.07304382300001,-37.0516777039],"type":"Point"}
}