{
  "type": "Feature",
  "properties": {
    "addr:full":"533 Princes Hwy Kirrawee NSW 2232",
    "addr:housenumber":"533",
    "addr:postcode":"2232",
    "addr:street":"Princes Hwy",
    "iso:country":"AU",
    "sg:address":"533 Princes Hwy",
    "sg:city":"Kirrawee",
    "sg:classifiers":[
        {
            "category":"Professional",
            "subcategory":"Engineering",
            "type":"Services"
        }
    ],
    "sg:phone":"+61 2 9542 5250",
    "sg:postcode":"2232",
    "sg:province":"NSW",
    "sg:tags":[
        "engineer",
        "mechanical"
    ],
    "wof:name":"Ali Mechanical Workshop",
    "wof:placetype":"venue"
},
  "geometry": {"coordinates":[151.07652282699999,-34.0316162109],"type":"Point"}
}