{
  "type": "Feature",
  "properties": {
    "addr:full":"PO Box 2087 Woonona East NSW 2517",
    "addr:postcode":"2517",
    "iso:country":"AU",
    "sg:address":"PO Box 2087",
    "sg:city":"Woonona East",
    "sg:classifiers":[
        {
            "category":"Real Estate",
            "subcategory":"Real Estate Services",
            "type":"Services"
        }
    ],
    "sg:phone":"+61 428 423 232",
    "sg:postcode":"2517",
    "sg:province":"NSW",
    "sg:tags":[
        "valuer"
    ],
    "wof:name":"Bergmeier Murray",
    "wof:placetype":"venue"
},
  "geometry": {"coordinates":[150.91416899999999,-34.349152],"type":"Point"}
}