{
  "type": "Feature",
  "properties": {
    "addr:full":"Showroom 2/ 12 Leda Blv Morayfield QLD 4506",
    "addr:housenumber":"/ 12",
    "addr:postcode":"4506",
    "addr:street":"Leda Blv",
    "iso:country":"AU",
    "sg:address":"Showroom 2/ 12",
    "sg:city":"Leda Blv Morayfield",
    "sg:classifiers":[
        {
            "category":"Building & Trades",
            "subcategory":"Construction",
            "type":"Services"
        }
    ],
    "sg:phone":"+61 7 5495 3530",
    "sg:postcode":"4506",
    "sg:province":"QLD",
    "sg:tags":[
        "home",
        "air conditioning"
    ],
    "wof:name":"T & L Air Conditioning",
    "wof:placetype":"venue"
},
  "geometry": {"coordinates":[152.94900512699999,-27.10414505],"type":"Point"}
}