{
  "type": "Feature",
  "properties": {
    "addr:full":"1 Glenferrie Rd Malvern VIC 3144",
    "addr:housenumber":"1",
    "addr:postcode":"3144",
    "addr:street":"Glenferrie Rd",
    "iso:country":"AU",
    "sg:address":"1 Glenferrie Rd",
    "sg:city":"Malvern",
    "sg:classifiers":[
        {
            "category":"Building & Trades",
            "subcategory":"Construction",
            "type":"Services"
        }
    ],
    "sg:phone":"+61 3 9508 7144",
    "sg:postcode":"3144",
    "sg:province":"VIC",
    "sg:tags":[
        "bitumen",
        "paving",
        "asphalt"
    ],
    "wof:name":"Boral Asphalt",
    "wof:placetype":"venue"
},
  "geometry": {"coordinates":[145.027542114,-37.8660202026],"type":"Point"}
}