{
  "type": "Feature",
  "properties": {
    "addr:full":"76 Richmond Ave Colonel Light Gardens SA 5041",
    "addr:housenumber":"76",
    "addr:postcode":"5041",
    "addr:street":"Richmond Ave",
    "iso:country":"AU",
    "sg:address":"76 Richmond Ave",
    "sg:city":"Colonel Light Gardens",
    "sg:classifiers":[
        {
            "category":"Personal",
            "subcategory":"Beauty Salon",
            "type":"Services"
        }
    ],
    "sg:phone":"+61 8 8276 1693",
    "sg:postcode":"5041",
    "sg:province":"SA",
    "sg:tags":[
        "hairdresser"
    ],
    "wof:name":"Ann Kubilius Salon",
    "wof:placetype":"venue"
},
  "geometry": {"coordinates":[138.584137,-34.981651],"type":"Point"}
}