{
  "type": "Feature",
  "properties": {
    "addr:full":"Berry Rd Gidgegannup WA 6083",
    "addr:postcode":"6083",
    "addr:street":"Berry Rd",
    "iso:country":"AU",
    "sg:address":"Berry Rd",
    "sg:city":"Gidgegannup",
    "sg:classifiers":[
        {
            "category":"Real Estate",
            "subcategory":"Surveying",
            "type":"Services"
        }
    ],
    "sg:phone":"+61 8 9572 9991",
    "sg:postcode":"6083",
    "sg:province":"WA",
    "sg:tags":[
        "surveyor",
        "land"
    ],
    "wof:name":"Land & Engineering Surveys",
    "wof:placetype":"venue"
},
  "geometry": {"coordinates":[116.219802856,-31.737487793],"type":"Point"}
}