{
  "type": "Feature",
  "properties": {
    "iso:country":"AU",
    "sg:address":"Factory 2 40 Kylta Rd",
    "sg:city":"Heidelberg West",
    "sg:classifiers":[
        {
            "category":"Retail",
            "subcategory":"Auto Repair",
            "type":"Services"
        }
    ],
    "sg:phone":"+61 3 9458 4022",
    "sg:postcode":"3081",
    "sg:province":"VIC",
    "sg:tags":[
        "testing",
        "inspection",
        "motor",
        "vehicle"
    ],
    "wof:name":"West Heidelberg Motors Pty Ltd",
    "wof:placetype":"venue"
},
  "geometry": {"coordinates":[145.044754028,-37.7332382202],"type":"Point"}
}