{
  "type": "Feature",
  "properties": {
    "addr:full":"48 Woodlands Drv Blackmans Bay TAS 7052",
    "addr:housenumber":"48",
    "addr:postcode":"7052",
    "addr:street":"Woodlands Drv",
    "iso:country":"AU",
    "sg:address":"48 Woodlands Drv",
    "sg:city":"Blackmans Bay",
    "sg:classifiers":[
        {
            "category":"Building & Trades",
            "subcategory":"Landscaping Services",
            "type":"Services"
        }
    ],
    "sg:phone":"+61 3 6229 5481",
    "sg:postcode":"7052",
    "sg:province":"TAS",
    "sg:tags":[
        "stump",
        "tree",
        "felling",
        "removal"
    ],
    "wof:name":"Stump Busters",
    "wof:placetype":"venue"
},
  "geometry": {"coordinates":[147.31286600000001,-43.003853],"type":"Point"}
}