{
  "type": "Feature",
  "properties": {
    "addr:full":"212 Silverwater Rd Silverwater NSW 2128",
    "addr:housenumber":"212",
    "addr:postcode":"2128",
    "addr:street":"Silverwater Rd",
    "iso:country":"AU",
    "sg:address":"212 Silverwater Rd",
    "sg:city":"Silverwater",
    "sg:classifiers":[
        {
            "category":"Utilities",
            "subcategory":"Water",
            "type":"Services"
        }
    ],
    "sg:phone":"+61 2 9748 8800",
    "sg:postcode":"2128",
    "sg:province":"NSW",
    "sg:tags":[
        "equipment",
        "treatment"
    ],
    "wof:name":"Ozone Pollution Technology",
    "wof:placetype":"venue"
},
  "geometry": {"coordinates":[151.05064392099999,-33.8269462585],"type":"Point"}
}