{
  "type": "Feature",
  "properties": {
    "iso:country":"AU",
    "sg:address":"161 East St",
    "sg:city":"Rockhampton",
    "sg:classifiers":[
        {
            "category":"Organizations",
            "subcategory":"Professional Association",
            "type":"Services"
        }
    ],
    "sg:phone":"+61 7 4922 2922",
    "sg:postcode":"4700",
    "sg:province":"QLD",
    "sg:tags":[
        "web",
        "internet"
    ],
    "wof:name":"All-Biz-Art",
    "wof:placetype":"venue"
},
  "geometry": {"coordinates":[150.52143859899999,-23.3893432617],"type":"Point"}
}