{
  "type": "Feature",
  "properties": {
    "addr:full":"32 Camms Rd Kayena TAS 7270",
    "addr:housenumber":"32",
    "addr:postcode":"7270",
    "addr:street":"Camms Rd",
    "iso:country":"AU",
    "sg:address":"32 Camms Rd",
    "sg:city":"Kayena",
    "sg:classifiers":[
        {
            "category":"Utilities",
            "subcategory":"Electric",
            "type":"Services"
        }
    ],
    "sg:phone":"+61 3 6394 7476",
    "sg:postcode":"7270",
    "sg:province":"TAS",
    "sg:tags":[
        "electrical",
        "contractor"
    ],
    "wof:name":"Prolec",
    "wof:placetype":"venue"
},
  "geometry": {"coordinates":[146.90525817899999,-41.1993751526],"type":"Point"}
}