{
  "type": "Feature",
  "properties": {
    "iso:country":"AU",
    "sg:address":"25 Nardoo St",
    "sg:city":"Wagga Wagga",
    "sg:classifiers":[
        {
            "category":"Utilities",
            "subcategory":"Electric",
            "type":"Services"
        }
    ],
    "sg:phone":"+61 408 693 656",
    "sg:postcode":"2650",
    "sg:province":"NSW",
    "sg:tags":[
        "electrical",
        "contractor"
    ],
    "wof:name":"Breasley John Electrical",
    "wof:placetype":"venue"
},
  "geometry": {"coordinates":[147.33897399899999,-35.1308059692],"type":"Point"}
}