{
  "type": "Feature",
  "properties": {
    "addr:full":"112 Albany Rd Currajong QLD 4812",
    "addr:housenumber":"112",
    "addr:postcode":"4812",
    "addr:street":"Albany Rd",
    "iso:country":"AU",
    "sg:address":"112 Albany Rd",
    "sg:city":"Currajong",
    "sg:classifiers":[
        {
            "category":"Building & Trades",
            "subcategory":"Construction",
            "type":"Services"
        }
    ],
    "sg:phone":"+61 7 4771 2333",
    "sg:postcode":"4812",
    "sg:province":"QLD",
    "sg:tags":[
        "contractor"
    ],
    "wof:name":"Edwards Phil",
    "wof:placetype":"venue"
},
  "geometry": {"coordinates":[146.78767400000001,-19.273468],"type":"Point"}
}