{
  "type": "Feature",
  "properties": {
    "addr:full":"13 Ashley Park Drv Chelsea Heights VIC 3196",
    "addr:housenumber":"13",
    "addr:postcode":"3196",
    "addr:street":"Ashley Park Drv",
    "iso:country":"AU",
    "sg:address":"13 Ashley Park Drv",
    "sg:city":"Chelsea Heights",
    "sg:classifiers":[
        {
            "category":"Autos & Motor Vehicles",
            "subcategory":"Boat Sales",
            "type":"Retail Goods"
        }
    ],
    "sg:phone":"+61 3 9483 8576",
    "sg:postcode":"3196",
    "sg:province":"VIC",
    "sg:tags":[
        "equipment",
        "yacht"
    ],
    "wof:name":"Marine Wholesale",
    "wof:placetype":"venue"
},
  "geometry": {"coordinates":[145.13836669899999,-38.0385437012],"type":"Point"}
}