{
  "type": "Feature",
  "properties": {
    "addr:full":"29 Albion St Surry Hills NSW 2010",
    "addr:housenumber":"29",
    "addr:postcode":"2010",
    "addr:street":"Albion St",
    "iso:country":"AU",
    "sg:address":"29 Albion St",
    "sg:city":"Surry Hills",
    "sg:classifiers":[
        {
            "category":"Professional",
            "subcategory":"Detective & Security Services",
            "type":"Services"
        }
    ],
    "sg:phone":"+61 419 243 403",
    "sg:postcode":"2010",
    "sg:province":"NSW",
    "sg:tags":[
        "investigator"
    ],
    "wof:name":"Spy Vs Spy Investigations",
    "wof:placetype":"venue"
},
  "geometry": {"coordinates":[151.210006714,-33.8823547363],"type":"Point"}
}