{
  "type": "Feature",
  "properties": {
    "addr:full":"8 Mandara Drv Wurtulla QLD 4575",
    "addr:housenumber":"8",
    "addr:postcode":"4575",
    "addr:street":"Mandara Drv",
    "iso:country":"AU",
    "sg:address":"8 Mandara Drv",
    "sg:city":"Wurtulla",
    "sg:classifiers":[
        {
            "category":"Education",
            "subcategory":"Special Training",
            "type":"Public Place"
        }
    ],
    "sg:phone":"+61 7 5493 1834",
    "sg:postcode":"4575",
    "sg:province":"QLD",
    "sg:tags":[
        "drama",
        "speech",
        "speaking",
        "tuition"
    ],
    "wof:name":"Bimrose Daphne, BA.LGSM.",
    "wof:placetype":"venue"
},
  "geometry": {"coordinates":[153.12501499999999,-26.761072],"type":"Point"}
}