{
  "type": "Feature",
  "properties": {
    "addr:full":"94 Capitol Drv Mt Ommaney QLD 4074",
    "addr:postcode":"4074",
    "addr:street":"Capitol Drv Mt Ommaney",
    "iso:country":"AU",
    "sg:address":"94 Capitol Drv",
    "sg:city":"Mt Ommaney",
    "sg:classifiers":[
        {
            "category":"Education",
            "subcategory":"School",
            "type":"Public Place"
        }
    ],
    "sg:phone":"+61 7 3717 6888",
    "sg:postcode":"4074",
    "sg:province":"QLD",
    "sg:tags":[
        "state",
        "except",
        "nsw"
    ],
    "wof:name":"Mt Ommaney Special School",
    "wof:placetype":"venue"
},
  "geometry": {"coordinates":[152.94078064000001,-27.5424575806],"type":"Point"}
}