{
  "type": "Feature",
  "properties": {
    "iso:country":"AU",
    "sg:address":"Shop 1184 Bay City Plaza, 95 Malop St",
    "sg:city":"Geelong",
    "sg:classifiers":[
        {
            "category":"Personal",
            "subcategory":"Piercing",
            "type":"Services"
        }
    ],
    "sg:phone":"+61 3 5221 5688",
    "sg:postcode":"3220",
    "sg:province":"VIC",
    "sg:tags":[
        "body",
        "ear"
    ],
    "wof:name":"HairHouse Warehouse",
    "wof:placetype":"venue"
},
  "geometry": {"coordinates":[144.36213699999999,-38.147438],"type":"Point"}
}