{
  "type": "Feature",
  "properties": {
    "iso:country":"AU",
    "sg:address":"19 Cunningham Drv",
    "sg:city":"Mill Park",
    "sg:classifiers":[
        {
            "category":"Professional",
            "subcategory":"Computer Services",
            "type":"Services"
        }
    ],
    "sg:phone":"+61 402 311 990",
    "sg:postcode":"3082",
    "sg:province":"VIC",
    "sg:tags":[
        "repairs",
        "upgrade",
        "equipment"
    ],
    "wof:name":"JT PC Solutions",
    "wof:placetype":"venue"
},
  "geometry": {"coordinates":[145.063262939,-37.6614990234],"type":"Point"}
}