{
  "type": "Feature",
  "properties": {
    "addr:full":"PO Box 4032 Robina Town Centre QLD 4230",
    "addr:postcode":"4230",
    "iso:country":"AU",
    "sg:address":"PO Box 4032",
    "sg:city":"Robina Town Centre",
    "sg:classifiers":[
        {
            "category":"Professional",
            "subcategory":"Employment Agencies",
            "type":"Services"
        }
    ],
    "sg:phone":"+61 422 207 722",
    "sg:postcode":"4230",
    "sg:province":"QLD",
    "sg:tags":[
        "hire",
        "labour",
        "contractor"
    ],
    "wof:name":"Worklink Solutions",
    "wof:placetype":"venue"
},
  "geometry": {"coordinates":[153.38531494099999,-28.0774707794],"type":"Point"}
}