{
  "type": "Feature",
  "properties": {
    "addr:full":"240 Ballarat Rd Braybrook VIC 3019",
    "addr:housenumber":"240",
    "addr:postcode":"3019",
    "addr:street":"Ballarat Rd",
    "iso:country":"AU",
    "sg:address":"240 Ballarat Rd",
    "sg:city":"Braybrook",
    "sg:classifiers":[
        {
            "category":"Wholesale",
            "subcategory":"Home Furnishings",
            "type":"Manufacturing & Wholesale Goods"
        }
    ],
    "sg:phone":"+61 3 9318 1211",
    "sg:postcode":"3019",
    "sg:province":"VIC",
    "sg:tags":[
        "wholesaler",
        "bedding",
        "mfrs",
        "bed"
    ],
    "wof:name":"Chiropedic Bedding Pty Ltd",
    "wof:placetype":"venue"
},
  "geometry": {"coordinates":[144.86195373499999,-37.7805976868],"type":"Point"}
}