{
  "type": "Feature",
  "properties": {
    "addr:full":"17 Michael St Brunswick VIC 3056",
    "addr:housenumber":"17",
    "addr:postcode":"3056",
    "addr:street":"Michael St",
    "iso:country":"AU",
    "sg:address":"17 Michael St",
    "sg:city":"Brunswick",
    "sg:classifiers":[
        {
            "category":"Utilities",
            "type":"Services"
        }
    ],
    "sg:phone":"+61 3 9387 4626",
    "sg:postcode":"3056",
    "sg:province":"VIC",
    "sg:tags":[
        "refrigeration",
        "industrial",
        "commercial",
        "retail"
    ],
    "wof:name":"Cedar Refrigeration & Catering Equipment Pty Ltd",
    "wof:placetype":"venue"
},
  "geometry": {"coordinates":[144.959640503,-37.7727165222],"type":"Point"}
}