{
  "type": "Feature",
  "properties": {
    "addr:full":"Level 1/ 51 York Rd Penrith NSW 2750",
    "addr:housenumber":"/ 51",
    "addr:postcode":"2750",
    "addr:street":"York Rd",
    "iso:country":"AU",
    "sg:address":"Level 1/ 51 York Rd",
    "sg:city":"Penrith",
    "sg:classifiers":[
        {
            "category":"Shopping",
            "subcategory":"Crafts & Fabrics",
            "type":"Retail Goods"
        }
    ],
    "sg:phone":"+61 2 4722 5650",
    "sg:postcode":"2750",
    "sg:province":"NSW",
    "sg:tags":[
        "supply"
    ],
    "wof:name":"2 Bead Or Not 2 Bead",
    "wof:placetype":"venue"
},
  "geometry": {"coordinates":[150.98336792000001,-33.859752655],"type":"Point"}
}