{
  "type": "Feature",
  "properties": {
    "addr:full":"29 Hunter Ave St Ives NSW 2075",
    "addr:housenumber":"29",
    "addr:postcode":"2075",
    "addr:street":"Hunter Ave",
    "iso:country":"AU",
    "sg:address":"29 Hunter Ave St",
    "sg:city":"Ives",
    "sg:classifiers":[
        {
            "category":"Professional",
            "subcategory":"Engineering",
            "type":"Services"
        }
    ],
    "sg:phone":"+61 2 9440 0120",
    "sg:postcode":"2075",
    "sg:province":"NSW",
    "sg:tags":[
        "consulting",
        "engineer"
    ],
    "wof:name":"Walker Knox Associates Pty Ltd",
    "wof:placetype":"venue"
},
  "geometry": {"coordinates":[151.17100524899999,-33.7425041199],"type":"Point"}
}