{
  "type": "Feature",
  "properties": {
    "addr:full":"Shop 19, 45 Plenty Rd Bundoora VIC 3083",
    "addr:housenumber":"shop 19 45",
    "addr:postcode":"3083",
    "addr:street":"Plenty Rd",
    "iso:country":"AU",
    "sg:address":"Shop 19, 45 Plenty Rd",
    "sg:city":"Bundoora",
    "sg:classifiers":[
        {
            "category":"Fast Food",
            "type":"Food & Drink"
        }
    ],
    "sg:phone":"+61 3 9466 8033",
    "sg:postcode":"3083",
    "sg:province":"VIC",
    "sg:tags":[
        "away",
        "take"
    ],
    "wof:name":"Sammy's Charcoal Chicken",
    "wof:placetype":"venue"
},
  "geometry": {"coordinates":[145.058517456,-37.6962165833],"type":"Point"}
}