{
  "type": "Feature",
  "properties": {
    "addr:full":"120 Para Rd Montmorency VIC 3094",
    "addr:housenumber":"120",
    "addr:postcode":"3094",
    "addr:street":"Para Rd",
    "iso:country":"AU",
    "sg:address":"120 Para Rd",
    "sg:city":"Montmorency",
    "sg:classifiers":[
        {
            "category":"Banks & Credit Unions",
            "subcategory":"Investment Brokerage",
            "type":"Services"
        }
    ],
    "sg:phone":"+61 3 9434 2024",
    "sg:postcode":"3094",
    "sg:province":"VIC",
    "sg:tags":[
        "radiator",
        "motor"
    ],
    "wof:name":"Diamond Valley Radiator Centre Pty Ltd",
    "wof:placetype":"venue"
},
  "geometry": {"coordinates":[145.11537170400001,-37.7142944336],"type":"Point"}
}