{
  "type": "Feature",
  "properties": {
    "addr:full":"1, 46 Burns Bay Rd Lane Cove NSW 2066",
    "addr:housenumber":"46",
    "addr:postcode":"2066",
    "addr:street":"1;Bay Rd",
    "iso:country":"AU",
    "sg:address":"1, 46 Burns Bay Rd",
    "sg:city":"Lane Cove",
    "sg:classifiers":[
        {
            "category":"Health Services",
            "subcategory":"Chiropractor",
            "type":"Services"
        }
    ],
    "sg:phone":"+61 2 9428 4033",
    "sg:postcode":"2066",
    "sg:province":"NSW",
    "wof:name":"Uren Mark, Chin Irene &+ Allport Gillian",
    "wof:placetype":"venue"
},
  "geometry": {"coordinates":[151.167404175,-33.8146743774],"type":"Point"}
}