{
  "type": "Feature",
  "properties": {
    "iso:country":"AU",
    "sg:address":"U3/ 17 Boniface St",
    "sg:city":"Archerfield",
    "sg:classifiers":[
        {
            "category":"Manufacturing",
            "subcategory":"Metals",
            "type":"Manufacturing & Wholesale Goods"
        }
    ],
    "sg:phone":"+61 7 3272 9292",
    "sg:postcode":"4108",
    "sg:province":"QLD",
    "sg:tags":[
        "steel",
        "fabricator",
        "mfrs"
    ],
    "wof:name":"Bexley Steel",
    "wof:placetype":"venue"
},
  "geometry": {"coordinates":[153.02044677699999,-27.5599937439],"type":"Point"}
}