{
  "type": "Feature",
  "properties": {
    "addr:full":"105b Scarborough St Southport QLD 4215",
    "addr:housenumber":"105b",
    "addr:postcode":"4215",
    "addr:street":"Scarborough St",
    "iso:country":"AU",
    "sg:address":"105b Scarborough St",
    "sg:city":"Southport",
    "sg:classifiers":[
        {
            "category":"Professional",
            "subcategory":"Management & Consulting",
            "type":"Services"
        }
    ],
    "sg:phone":"+61 7 5531 3387",
    "sg:postcode":"4215",
    "sg:province":"QLD",
    "sg:tags":[
        "consultant",
        "business"
    ],
    "wof:name":"Big Picture Management Pty Ltd",
    "wof:placetype":"venue"
},
  "geometry": {"coordinates":[153.41346740700001,-27.9660072327],"type":"Point"}
}