{
  "type": "Feature",
  "properties": {
    "addr:full":"18 Somerton Park Drv Campbellfield VIC 3061",
    "addr:housenumber":"18",
    "addr:postcode":"3061",
    "addr:street":"Somerton Park Drv",
    "iso:country":"AU",
    "sg:address":"18 Somerton Park Drv",
    "sg:city":"Campbellfield",
    "sg:classifiers":[
        {
            "category":"Utilities",
            "subcategory":"Refuse",
            "type":"Services"
        }
    ],
    "sg:phone":"+61 3 9308 9833",
    "sg:postcode":"3061",
    "sg:province":"VIC",
    "sg:tags":[
        "disposal",
        "reduction",
        "waste"
    ],
    "wof:name":"Campbellfield Recycling Station",
    "wof:placetype":"venue"
},
  "geometry": {"coordinates":[144.946731567,-37.6457748413],"type":"Point"}
}