{
  "type": "Feature",
  "properties": {
    "addr:full":"2 / 172 Elliott Rd Scarborough WA 6019",
    "addr:housenumber":"/ 172",
    "addr:postcode":"6019",
    "addr:street":"Elliott Rd",
    "iso:country":"AU",
    "sg:address":"2 / 172 Elliott Rd",
    "sg:city":"Scarborough",
    "sg:classifiers":[
        {
            "category":"Building & Trades",
            "subcategory":"Landscaping Services",
            "type":"Services"
        }
    ],
    "sg:phone":"+61 8 9245 9508",
    "sg:postcode":"6019",
    "sg:province":"WA",
    "sg:tags":[
        "designer",
        "landscape",
        "contractor"
    ],
    "wof:name":"Repave Spray-On Paving",
    "wof:placetype":"venue"
},
  "geometry": {"coordinates":[115.761451721,-31.8868923187],"type":"Point"}
}