{
  "type": "Feature",
  "properties": {
    "iso:country":"AU",
    "sg:address":"13 Robinson St",
    "sg:city":"Murchison",
    "sg:classifiers":[
        {
            "category":"Shopping",
            "subcategory":"Antiques",
            "type":"Retail Goods"
        }
    ],
    "sg:phone":"+61 3 5826 2401",
    "sg:postcode":"3610",
    "sg:province":"VIC",
    "wof:name":"Betty Maslin",
    "wof:placetype":"venue"
},
  "geometry": {"coordinates":[145.218307495,-36.6183738708],"type":"Point"}
}