{
  "type": "Feature",
  "properties": {
    "iso:country":"AU",
    "sg:address":"Melbourne Rd",
    "sg:city":"Shepparton South",
    "sg:classifiers":[
        {
            "category":"Professional",
            "subcategory":"Art Services",
            "type":"Services"
        }
    ],
    "sg:phone":"+61 3 5820 3150",
    "sg:postcode":"3630",
    "sg:province":"VIC",
    "sg:tags":[
        "graphic",
        "designer"
    ],
    "wof:name":"Marketing Solutions",
    "wof:placetype":"venue"
},
  "geometry": {"coordinates":[145.390136719,-36.4269676208],"type":"Point"}
}