{
  "type": "Feature",
  "properties": {
    "iso:country":"AU",
    "sg:address":"Shp1/ 177-219 Mitchell Rd",
    "sg:city":"Erskineville",
    "sg:classifiers":[
        {
            "category":"Cafe",
            "type":"Food & Drink"
        }
    ],
    "sg:phone":"+61 2 9519 2000",
    "sg:postcode":"2043",
    "sg:province":"NSW",
    "wof:name":"Noemi's Cafe",
    "wof:placetype":"venue"
},
  "geometry": {"coordinates":[151.187683,-33.906681],"type":"Point"}
}