{
  "type": "Feature",
  "properties": {
    "iso:country":"AU",
    "sg:address":"Shop 31 NTU Casuarina Campus",
    "sg:city":"Casuarina",
    "sg:classifiers":[
        {
            "category":"Food & Beverages",
            "subcategory":"Specialty",
            "type":"Retail Goods"
        }
    ],
    "sg:phone":"+61 8 8946 7736",
    "sg:postcode":"0810",
    "sg:province":"NT",
    "sg:tags":[
        "product",
        "health"
    ],
    "wof:name":"Planet Organic Darwin Wholefoods",
    "wof:placetype":"venue"
},
  "geometry": {"coordinates":[130.858886719,-12.3764762878],"type":"Point"}
}