{
  "type": "Feature",
  "properties": {
    "addr:full":"PO Box 351 Balgowlah NSW 2093",
    "addr:postcode":"2093",
    "iso:country":"AU",
    "sg:address":"PO Box 351",
    "sg:city":"Balgowlah",
    "sg:classifiers":[
        {
            "category":"Building & Trades",
            "subcategory":"Plumbing",
            "type":"Services"
        }
    ],
    "sg:phone":"+61 409 126 518",
    "sg:postcode":"2093",
    "sg:province":"NSW",
    "sg:tags":[
        "repair",
        "appliance",
        "system",
        "heating"
    ],
    "wof:name":"Sydney Heating & Cooling Pty Ltd",
    "wof:placetype":"venue"
},
  "geometry": {"coordinates":[151.26158142099999,-33.7939300537],"type":"Point"}
}