{
  "type": "Feature",
  "properties": {
    "iso:country":"AU",
    "sg:address":"112 Balmain St",
    "sg:city":"Richmond",
    "sg:classifiers":[
        {
            "category":"Building & Trades",
            "subcategory":"Construction",
            "type":"Services"
        }
    ],
    "sg:phone":"+61 3 8420 8200",
    "sg:postcode":"3121",
    "sg:province":"VIC",
    "sg:tags":[
        "management"
    ],
    "sg:website":"http://www.baracon.com.au",
    "wof:name":"Baracon Group Pty Ltd",
    "wof:placetype":"venue"
},
  "geometry": {"coordinates":[144.99574279800001,-37.8303565979],"type":"Point"}
}