{
  "type": "Feature",
  "properties": {
    "iso:country":"AU",
    "sg:address":"19 Kearns Crs",
    "sg:city":"Ardross",
    "sg:classifiers":[
        {
            "category":"Retail",
            "subcategory":"Laundry & Dry Cleaning",
            "type":"Services"
        }
    ],
    "sg:phone":"+61 8 9364 8392",
    "sg:postcode":"6153",
    "sg:province":"WA",
    "wof:name":"Ardross Drycleaners",
    "wof:placetype":"venue"
},
  "geometry": {"coordinates":[115.835518,-32.020561],"type":"Point"}
}