{
  "type": "Feature",
  "properties": {
    "addr:full":"3056 Grabben Gullen Rd Grabben Gullen NSW 2583",
    "addr:housenumber":"3056",
    "addr:postcode":"2583",
    "addr:street":"Grabben Gullen Rd",
    "iso:country":"AU",
    "sg:address":"3056 Grabben Gullen Rd",
    "sg:city":"Grabben Gullen",
    "sg:classifiers":[
        {
            "category":"Retail",
            "subcategory":"Laundry & Dry Cleaning",
            "type":"Services"
        }
    ],
    "sg:phone":"+61 2 4836 7360",
    "sg:postcode":"2583",
    "sg:province":"NSW",
    "sg:tags":[
        "breeder",
        "alpaca",
        "llama"
    ],
    "wof:name":"Tapitalee Alpacas",
    "wof:placetype":"venue"
},
  "geometry": {"coordinates":[149.42434692399999,-34.4936103821],"type":"Point"}
}