{
  "type": "Feature",
  "properties": {
    "addr:full":"36 Gipps Rd Greystanes NSW 2145",
    "addr:housenumber":"36",
    "addr:postcode":"2145",
    "addr:street":"Gipps Rd",
    "iso:country":"AU",
    "sg:address":"36 Gipps Rd",
    "sg:city":"Greystanes",
    "sg:classifiers":[
        {
            "category":"Sports & Exercise",
            "subcategory":"Gym",
            "type":"Entertainment"
        }
    ],
    "sg:phone":"+61 2 9720 0260",
    "sg:postcode":"2145",
    "sg:province":"NSW",
    "sg:tags":[
        "meditation"
    ],
    "wof:name":"Haim, J",
    "wof:placetype":"venue"
},
  "geometry": {"coordinates":[150.928222656,-33.8300361633],"type":"Point"}
}