{
  "type": "Feature",
  "properties": {
    "addr:full":"Jungari St Davenport SA 5700",
    "addr:postcode":"5700",
    "addr:street":"St",
    "iso:country":"AU",
    "sg:address":"Jungari St",
    "sg:city":"Davenport",
    "sg:classifiers":[
        {
            "category":"Food & Beverages",
            "subcategory":"Groceries & Convenience Stores",
            "type":"Retail Goods"
        }
    ],
    "sg:phone":"+61 8 8964 1965",
    "sg:postcode":"5700",
    "sg:province":"SA",
    "wof:name":"Mirnirri Aboriginal Corporation",
    "wof:placetype":"venue"
},
  "geometry": {"coordinates":[137.77377319300001,-32.4899940491],"type":"Point"}
}