{
  "type": "Feature",
  "properties": {
    "addr:full":"55 Alacrity Pl Henderson WA 6166",
    "addr:housenumber":"55",
    "addr:postcode":"6166",
    "addr:street":"Alacrity Pl",
    "iso:country":"AU",
    "sg:address":"55 Alacrity Pl",
    "sg:city":"Henderson",
    "sg:classifiers":[
        {
            "category":"Sports & Exercise",
            "subcategory":"Athletic Track",
            "type":"Entertainment"
        }
    ],
    "sg:phone":"+61 8 9437 1155",
    "sg:postcode":"6166",
    "sg:province":"WA",
    "sg:tags":[
        "industrial",
        "ceramic",
        "scientific"
    ],
    "wof:name":"Rojan Advanced Ceramics Pty Ltd",
    "wof:placetype":"venue"
},
  "geometry": {"coordinates":[115.77658099999999,-32.165684],"type":"Point"}
}