{
  "type": "Feature",
  "properties": {
    "addr:full":"236 Gooch St Thornbury VIC 3071",
    "addr:housenumber":"236",
    "addr:postcode":"3071",
    "addr:street":"Gooch St",
    "iso:country":"AU",
    "sg:address":"236 Gooch St",
    "sg:city":"Thornbury",
    "sg:classifiers":[
        {
            "category":"Shopping",
            "subcategory":"Baby Store",
            "type":"Retail Goods"
        }
    ],
    "sg:phone":"+61 3 9495 1911",
    "sg:postcode":"3071",
    "sg:province":"VIC",
    "sg:tags":[
        "wear"
    ],
    "wof:name":"Delicate Elegance Aust.",
    "wof:placetype":"venue"
},
  "geometry": {"coordinates":[145.018432617,-37.7599029541],"type":"Point"}
}