{
  "type": "Feature",
  "properties": {
    "addr:full":"Agnes St Bundaberg QLD 4670",
    "addr:postcode":"4670",
    "addr:street":"Agnes St",
    "iso:country":"AU",
    "sg:address":"Agnes St",
    "sg:city":"Bundaberg",
    "sg:classifiers":[
        {
            "category":"Autos & Motor Vehicles",
            "subcategory":"Boat Sales",
            "type":"Retail Goods"
        }
    ],
    "sg:phone":"+61 7 4151 8112",
    "sg:postcode":"4670",
    "sg:province":"QLD",
    "sg:tags":[
        "builder",
        "yacht",
        "repairer"
    ],
    "wof:name":"Bundaberg Slipway",
    "wof:placetype":"venue"
},
  "geometry": {"coordinates":[152.348342895,-24.8612728119],"type":"Point"}
}