{
  "type": "Feature",
  "properties": {
    "addr:full":"Cnr Somerville & Paramount Rds Footscray VIC 3011",
    "addr:postcode":"3011",
    "addr:street":"Cnr",
    "iso:country":"AU",
    "sg:address":"Cnr Somerville & Paramount Rds",
    "sg:city":"Footscray",
    "sg:classifiers":[
        {
            "category":"Transit Center",
            "subcategory":"Freight",
            "type":"Transportation"
        }
    ],
    "sg:phone":"+61 3 9315 1300",
    "sg:postcode":"3011",
    "sg:province":"VIC",
    "sg:tags":[
        "agent",
        "shipping"
    ],
    "wof:name":"Export Freight Services",
    "wof:placetype":"venue"
},
  "geometry": {"coordinates":[144.860794067,-37.8102302551],"type":"Point"}
}