{
  "type": "Feature",
  "properties": {
    "iso:country":"AU",
    "sg:address":"139 Middle Rd",
    "sg:city":"Hillcrest",
    "sg:classifiers":[
        {
            "category":"Organizations",
            "subcategory":"Non-profit Organization",
            "type":"Services"
        }
    ],
    "sg:phone":"+61 7 3333 1525",
    "sg:postcode":"4118",
    "sg:province":"QLD",
    "sg:tags":[
        "support",
        "disability",
        "organisation"
    ],
    "wof:name":"Alpha Community Services",
    "wof:placetype":"venue"
},
  "geometry": {"coordinates":[153.02073669399999,-27.6789073944],"type":"Point"}
}