{
  "type": "Feature",
  "properties": {
    "iso:country":"AU",
    "sg:address":"4/ 4 Hawke Drv",
    "sg:city":"Woolgoolga",
    "sg:classifiers":[
        {
            "category":"Manufacturing",
            "subcategory":"Glass & Minerals",
            "type":"Manufacturing & Wholesale Goods"
        }
    ],
    "sg:phone":"+61 2 6654 7698",
    "sg:postcode":"2456",
    "sg:province":"NSW",
    "sg:tags":[
        "fabricator",
        "fibreglass"
    ],
    "wof:name":"Mitchos Fibreglass",
    "wof:placetype":"venue"
},
  "geometry": {"coordinates":[153.192123,-30.121971],"type":"Point"}
}