{
  "type": "Feature",
  "properties": {
    "iso:country":"AU",
    "sg:address":"75 Vineyard Rd",
    "sg:city":"Sunbury",
    "sg:classifiers":[
        {
            "category":"Arts & Performance",
            "subcategory":"Dance",
            "type":"Entertainment"
        }
    ],
    "sg:phone":"+61 3 9744 2162",
    "sg:postcode":"3429",
    "sg:province":"VIC",
    "sg:tags":[
        "theatrical",
        "ballet",
        "tuition"
    ],
    "wof:name":"Flash Dance Performing Arts",
    "wof:placetype":"venue"
},
  "geometry": {"coordinates":[144.71580505399999,-37.5878448486],"type":"Point"}
}