{
  "type": "Feature",
  "properties": {
    "addr:full":"766 High St Epping VIC 3076",
    "addr:housenumber":"766",
    "addr:postcode":"3076",
    "addr:street":"High St",
    "iso:country":"AU",
    "sg:address":"766 High St",
    "sg:city":"Epping",
    "sg:classifiers":[
        {
            "category":"Food & Beverages",
            "subcategory":"Bakery",
            "type":"Retail Goods"
        }
    ],
    "sg:phone":"+61 3 9408 5322",
    "sg:postcode":"3076",
    "sg:province":"VIC",
    "sg:tags":[
        "cake",
        "shop",
        "pastry"
    ],
    "wof:name":"Cheesecake Shop The",
    "wof:placetype":"venue"
},
  "geometry": {"coordinates":[145.01434326200001,-37.8547973633],"type":"Point"}
}