{
  "type": "Feature",
  "properties": {
    "iso:country":"AU",
    "sg:address":"Park Beach Home Base, 252 Pacific Hwy",
    "sg:city":"Coffs Harbour",
    "sg:classifiers":[
        {
            "category":"Shopping",
            "subcategory":"Mobile Phones",
            "type":"Retail Goods"
        }
    ],
    "sg:phone":"+61 13 17 60",
    "sg:postcode":"2450",
    "sg:province":"NSW",
    "sg:tags":[
        "telephone",
        "accessory"
    ],
    "wof:name":"Battery World",
    "wof:placetype":"venue"
},
  "geometry": {"coordinates":[153.09063699999999,-30.318195],"type":"Point"}
}