{
  "type": "Feature",
  "properties": {
    "iso:country":"AU",
    "sg:address":"Bruce Hwy",
    "sg:city":"Mt Ossa",
    "sg:classifiers":[
        {
            "category":"Wholesale",
            "subcategory":"Farm Supplies",
            "type":"Manufacturing & Wholesale Goods"
        }
    ],
    "sg:phone":"+61 7 4958 8001",
    "sg:postcode":"4741",
    "sg:province":"QLD",
    "sg:tags":[
        "equipment"
    ],
    "wof:name":"Mt Ossa Rural",
    "wof:placetype":"venue"
},
  "geometry": {"coordinates":[148.825699,-20.953524],"type":"Point"}
}