{
  "type": "Feature",
  "properties": {
    "iso:country":"AU",
    "sg:address":"39 Albemarle St",
    "sg:city":"Doubleview",
    "sg:classifiers":[
        {
            "category":"Professional",
            "subcategory":"Art Services",
            "type":"Services"
        }
    ],
    "sg:phone":"+61 8 9341 1591",
    "sg:postcode":"6018",
    "sg:province":"WA",
    "sg:tags":[
        "interior",
        "designer"
    ],
    "sg:website":"http://www.lifestyledesign.net.au",
    "wof:name":"Felicia For Lifestyle Design",
    "wof:placetype":"venue"
},
  "geometry": {"coordinates":[115.776222229,-31.9041862488],"type":"Point"}
}