{
  "type": "Feature",
  "properties": {
    "iso:country":"AU",
    "sg:address":"7 Travers St",
    "sg:city":"Coconut Grove",
    "sg:classifiers":[
        {
            "category":"Industrial Area",
            "type":"Public Place"
        }
    ],
    "sg:phone":"+61 8 8948 1600",
    "sg:postcode":"0810",
    "sg:province":"NT",
    "sg:tags":[
        "rural",
        "shed"
    ],
    "wof:name":"NAC",
    "wof:placetype":"venue"
},
  "geometry": {"coordinates":[130.853393555,-12.4009752274],"type":"Point"}
}