{
  "type": "Feature",
  "properties": {
    "iso:country":"AU",
    "sg:address":"18 Roslyn St",
    "sg:city":"Lane Cove",
    "sg:classifiers":[
        {
            "category":"Professional",
            "subcategory":"Management & Consulting",
            "type":"Services"
        }
    ],
    "sg:phone":"+61 2 9418 8994",
    "sg:postcode":"2066",
    "sg:province":"NSW",
    "sg:tags":[
        "consultant"
    ],
    "wof:name":"Asset Evaluation Pty Limited (AEL)",
    "wof:placetype":"venue"
},
  "geometry": {"coordinates":[151.169433594,-33.8083267212],"type":"Point"}
}