{
  "type": "Feature",
  "properties": {
    "iso:country":"AU",
    "sg:address":"959 Heatherton Rd",
    "sg:city":"Springvale",
    "sg:classifiers":[
        {
            "category":"Education",
            "subcategory":"School",
            "type":"Public Place"
        }
    ],
    "sg:phone":"+61 3 9546 7562",
    "sg:postcode":"3171",
    "sg:province":"VIC",
    "sg:tags":[
        "state",
        "except",
        "nsw"
    ],
    "wof:name":"Heatherhill Primary",
    "wof:placetype":"venue"
},
  "geometry": {"coordinates":[145.15823364299999,-37.9629936218],"type":"Point"}
}