{
  "type": "Feature",
  "properties": {
    "addr:full":"7 Nailor St Hay NSW 2711",
    "addr:housenumber":"7",
    "addr:postcode":"2711",
    "addr:street":"Nailor St",
    "iso:country":"AU",
    "sg:address":"7 Nailor St",
    "sg:city":"Hay",
    "sg:classifiers":[
        {
            "category":"Travel",
            "subcategory":"Hotels & Motels",
            "type":"Entertainment"
        }
    ],
    "sg:phone":"+61 2 6993 1031",
    "sg:postcode":"2711",
    "sg:province":"NSW",
    "sg:tags":[
        "accommodation"
    ],
    "wof:name":"South Hay Hotel",
    "wof:placetype":"venue"
},
  "geometry": {"coordinates":[144.843185425,-34.5199317932],"type":"Point"}
}