{
  "type": "Feature",
  "properties": {
    "iso:country":"AU",
    "sg:address":"39 Salisbury Rd",
    "sg:city":"Ashwood",
    "sg:classifiers":[
        {
            "category":"Building & Trades",
            "subcategory":"Construction",
            "type":"Services"
        }
    ],
    "sg:phone":"+61 413 811 771",
    "sg:postcode":"3147",
    "sg:province":"VIC",
    "sg:tags":[
        "fencing",
        "contractor"
    ],
    "wof:name":"Reliable Fencing",
    "wof:placetype":"venue"
},
  "geometry": {"coordinates":[145.10440063499999,-37.8722343445],"type":"Point"}
}