{
  "type": "Feature",
  "properties": {
    "addr:full":"60 Pollards La Drummond VIC 3461",
    "addr:housenumber":"60",
    "addr:postcode":"3461",
    "addr:street":"Pollards La Drummond",
    "iso:country":"AU",
    "sg:address":"60 Pollards La",
    "sg:city":"Drummond",
    "sg:classifiers":[
        {
            "category":"Farming",
            "subcategory":"Vineyard",
            "type":"Manufacturing & Wholesale Goods"
        }
    ],
    "sg:phone":"+61 3 5423 9225",
    "sg:postcode":"3461",
    "sg:province":"VIC",
    "sg:tags":[
        "winery"
    ],
    "wof:name":"Cloudscape Wines",
    "wof:placetype":"venue"
},
  "geometry": {"coordinates":[144.311203003,-37.2658576965],"type":"Point"}
}