{
  "type": "Feature",
  "properties": {
    "addr:full":"136 Woodend Rd Woodend QLD 4305",
    "addr:housenumber":"136",
    "addr:postcode":"4305",
    "addr:street":"Woodend Rd",
    "iso:country":"AU",
    "sg:address":"136 Woodend Rd",
    "sg:city":"Woodend",
    "sg:classifiers":[
        {
            "category":"Professional",
            "subcategory":"Business Services",
            "type":"Services"
        }
    ],
    "sg:phone":"+61 7 3812 3443",
    "sg:postcode":"4305",
    "sg:province":"QLD",
    "sg:tags":[
        "drafting"
    ],
    "wof:name":"King Architectural Engineering",
    "wof:placetype":"venue"
},
  "geometry": {"coordinates":[152.772613525,-27.6145114899],"type":"Point"}
}