{
  "type": "Feature",
  "properties": {
    "iso:country":"AU",
    "sg:address":"Cnr Mulgrave & Milden Sts",
    "sg:city":"Gin Gin",
    "sg:classifiers":[
        {
            "category":"Farming",
            "subcategory":"Vineyard",
            "type":"Manufacturing & Wholesale Goods"
        }
    ],
    "sg:phone":"+61 7 4157 2871",
    "sg:postcode":"4671",
    "sg:province":"QLD",
    "sg:tags":[
        "winery"
    ],
    "wof:name":"The Winetasting Centre",
    "wof:placetype":"venue"
},
  "geometry": {"coordinates":[151.959869,-24.993271],"type":"Point"}
}