{
  "type": "Feature",
  "properties": {
    "iso:country":"AU",
    "sg:address":"45 Lt Boundary Rd",
    "sg:city":"Laverton North",
    "sg:classifiers":[
        {
            "category":"Professional",
            "subcategory":"Engineering",
            "type":"Services"
        }
    ],
    "sg:phone":"+61 3 9314 2511",
    "sg:postcode":"3026",
    "sg:province":"VIC",
    "sg:tags":[
        "engineer"
    ],
    "wof:name":"Maker F A Holdings Pty Ltd",
    "wof:placetype":"venue"
},
  "geometry": {"coordinates":[144.78787199999999,-37.813656],"type":"Point"}
}