{
  "type": "Feature",
  "properties": {
    "iso:country":"AU",
    "sg:address":"94 Curlewis St",
    "sg:city":"Swan Hill",
    "sg:classifiers":[
        {
            "category":"Food & Beverages",
            "subcategory":"Specialty",
            "type":"Retail Goods"
        }
    ],
    "sg:phone":"+61 3 5032 2432",
    "sg:postcode":"3585",
    "sg:province":"VIC",
    "sg:tags":[
        "ice",
        "supply"
    ],
    "wof:name":"Northern Ice Supplies",
    "wof:placetype":"venue"
},
  "geometry": {"coordinates":[143.559845,-35.335461],"type":"Point"}
}