{
  "type": "Feature",
  "properties": {
    "iso:country":"AU",
    "sg:address":"Shastar Rd",
    "sg:city":"Lesmurdie",
    "sg:classifiers":[
        {
            "category":"Professional",
            "subcategory":"Computer Services",
            "type":"Services"
        }
    ],
    "sg:phone":"+61 8 9291 0600",
    "sg:postcode":"6076",
    "sg:province":"WA",
    "sg:tags":[
        "package",
        "software"
    ],
    "wof:name":"MacWare",
    "wof:placetype":"venue"
},
  "geometry": {"coordinates":[116.04801178,-32.0154800415],"type":"Point"}
}