{
  "type": "Feature",
  "properties": {
    "addr:full":"58 Brunnel Rd Seaford VIC 3198",
    "addr:housenumber":"58",
    "addr:postcode":"3198",
    "addr:street":"Brunnel Rd",
    "iso:country":"AU",
    "sg:address":"58 Brunnel Rd",
    "sg:city":"Seaford",
    "sg:classifiers":[
        {
            "category":"Home & Garden",
            "subcategory":"Building Materials",
            "type":"Retail Goods"
        }
    ],
    "sg:phone":"+61 3 9570 4570",
    "sg:postcode":"3198",
    "sg:province":"VIC",
    "sg:tags":[
        "skylight"
    ],
    "wof:name":"Southern Skylights",
    "wof:placetype":"venue"
},
  "geometry": {"coordinates":[145.14813232399999,-38.1008453369],"type":"Point"}
}