{
  "type": "Feature",
  "properties": {
    "iso:country":"AU",
    "sg:address":"Factory 1a/ 1 Grace St",
    "sg:city":"Cranbourne",
    "sg:classifiers":[
        {
            "category":"Retail",
            "subcategory":"Auto Repair",
            "type":"Services"
        }
    ],
    "sg:phone":"+61 3 5995 0255",
    "sg:postcode":"3977",
    "sg:province":"VIC",
    "sg:tags":[
        "beater",
        "painter",
        "panel"
    ],
    "wof:name":"South Eastern Smash Repairs",
    "wof:placetype":"venue"
},
  "geometry": {"coordinates":[145.28236389200001,-38.1042671204],"type":"Point"}
}