{
  "type": "Feature",
  "properties": {
    "addr:full":"11 Swaffham Rd Minto NSW 2566",
    "addr:housenumber":"11",
    "addr:postcode":"2566",
    "addr:street":"Swaffham Rd",
    "iso:country":"AU",
    "sg:address":"11 Swaffham Rd",
    "sg:city":"Minto",
    "sg:classifiers":[
        {
            "category":"Manufacturing",
            "subcategory":"Paper Products",
            "type":"Manufacturing & Wholesale Goods"
        }
    ],
    "sg:phone":"+61 2 9820 1188",
    "sg:postcode":"2566",
    "sg:province":"NSW",
    "sg:tags":[
        "bag"
    ],
    "wof:name":"Wholesale Packaging Pty Ltd",
    "wof:placetype":"venue"
},
  "geometry": {"coordinates":[150.83108520499999,-34.0352401733],"type":"Point"}
}