{
  "type": "Feature",
  "properties": {
    "addr:full":"Tongyan Loh St Christmas Island WA 6798",
    "addr:postcode":"6798",
    "addr:street":"Loh St",
    "iso:country":"AU",
    "sg:address":"Tongyan Loh St",
    "sg:city":"Christmas Island",
    "sg:classifiers":[
        {
            "category":"Food & Beverages",
            "subcategory":"Groceries & Convenience Stores",
            "type":"Retail Goods"
        }
    ],
    "sg:phone":"+61 8 9164 8172",
    "sg:postcode":"6798",
    "sg:province":"WA",
    "wof:name":"Boong Trading",
    "wof:placetype":"venue"
},
  "geometry": {"coordinates":[105.600143,-10.48692],"type":"Point"}
}