{
  "type": "Feature",
  "properties": {
    "addr:full":"50 Queen St Molong NSW 2866",
    "addr:housenumber":"50",
    "addr:postcode":"2866",
    "addr:street":"Queen St",
    "iso:country":"AU",
    "sg:address":"50 Queen St",
    "sg:city":"Molong",
    "sg:classifiers":[
        {
            "category":"Manufacturing",
            "subcategory":"Metals",
            "type":"Manufacturing & Wholesale Goods"
        }
    ],
    "sg:phone":"+61 414 958 182",
    "sg:postcode":"2866",
    "sg:province":"NSW",
    "sg:tags":[
        "fabricator",
        "aluminium"
    ],
    "wof:name":"John Hale",
    "wof:placetype":"venue"
},
  "geometry": {"coordinates":[148.853714,-33.091309],"type":"Point"}
}