{
  "type": "Feature",
  "properties": {
    "iso:country":"AU",
    "sg:address":"168 Blacks Rd",
    "sg:city":"Flagstaff Hill",
    "sg:classifiers":[
        {
            "category":"Building & Trades",
            "subcategory":"Plumbing",
            "type":"Services"
        }
    ],
    "sg:phone":"+61 8 8358 6644",
    "sg:postcode":"5159",
    "sg:province":"SA",
    "sg:tags":[
        "plumber",
        "gasfitters"
    ],
    "wof:name":"M & J Maintenance Plumbing Pty Ltd",
    "wof:placetype":"venue"
},
  "geometry": {"coordinates":[138.59642028799999,-35.0551872253],"type":"Point"}
}