{
  "type": "Feature",
  "properties": {
    "iso:country":"AU",
    "sg:address":"PO Box 334",
    "sg:city":"Richmond",
    "sg:classifiers":[
        {
            "category":"Building & Trades",
            "subcategory":"Construction",
            "type":"Services"
        }
    ],
    "sg:phone":"+61 424 140 776",
    "sg:postcode":"2753",
    "sg:province":"NSW",
    "sg:tags":[
        "management"
    ],
    "wof:name":"Innovate Project Solutions Pty Ltd",
    "wof:placetype":"venue"
},
  "geometry": {"coordinates":[150.752410889,-33.5984802246],"type":"Point"}
}