{
  "type": "Feature",
  "properties": {
    "addr:full":"1/ 66 Junction Rd Clayfield QLD 4011",
    "addr:housenumber":"/ 66",
    "addr:postcode":"4011",
    "addr:street":"Junction Rd",
    "iso:country":"AU",
    "sg:address":"1/ 66 Junction Rd",
    "sg:city":"Clayfield",
    "sg:classifiers":[
        {
            "category":"Professional",
            "subcategory":"Employment Agencies",
            "type":"Services"
        }
    ],
    "sg:phone":"+61 7 3262 9980",
    "sg:postcode":"4011",
    "sg:province":"QLD",
    "sg:tags":[
        "entertainer",
        "agent"
    ],
    "wof:name":"The Blood Idols",
    "wof:placetype":"venue"
},
  "geometry": {"coordinates":[153.06075999999999,-27.416386],"type":"Point"}
}