{
  "type": "Feature",
  "properties": {
    "addr:full":"8 Penny Lane St Ulladulla NSW 2539",
    "addr:housenumber":"8",
    "addr:postcode":"2539",
    "addr:street":"Penny Lane St",
    "iso:country":"AU",
    "sg:address":"8 Penny Lane St",
    "sg:city":"Ulladulla",
    "sg:classifiers":[
        {
            "category":"Building & Trades",
            "subcategory":"Construction",
            "type":"Services"
        }
    ],
    "sg:phone":"+61 2 4455 4512",
    "sg:postcode":"2539",
    "sg:province":"NSW",
    "sg:tags":[
        "concrete",
        "contractor"
    ],
    "wof:name":"P J & D A Monaghan",
    "wof:placetype":"venue"
},
  "geometry": {"coordinates":[150.460403442,-35.35414505],"type":"Point"}
}