{
  "type": "Feature",
  "properties": {
    "addr:full":"10 Kenrose St Carina QLD 4152",
    "addr:housenumber":"10",
    "addr:postcode":"4152",
    "addr:street":"Kenrose St",
    "iso:country":"AU",
    "sg:address":"10 Kenrose St",
    "sg:city":"Carina",
    "sg:classifiers":[
        {
            "category":"Personal",
            "subcategory":"Beauty Salon",
            "type":"Services"
        }
    ],
    "sg:phone":"+61 7 3398 1777",
    "sg:postcode":"4152",
    "sg:province":"QLD",
    "sg:tags":[
        "hairdresser"
    ],
    "wof:name":"Hair Beauty & Body",
    "wof:placetype":"venue"
},
  "geometry": {"coordinates":[153.09783935600001,-27.4861869812],"type":"Point"}
}