{
  "type": "Feature",
  "properties": {
    "iso:country":"AU",
    "sg:address":"8 Matthew Smillie Drv",
    "sg:city":"Nairne",
    "sg:classifiers":[
        {
            "category":"Building & Trades",
            "subcategory":"Construction",
            "type":"Services"
        }
    ],
    "sg:phone":"+61 412 825 508",
    "sg:postcode":"5252",
    "sg:province":"SA",
    "sg:tags":[
        "polishing",
        "sanding",
        "floor"
    ],
    "wof:name":"Dingle A C",
    "wof:placetype":"venue"
},
  "geometry": {"coordinates":[138.91403198200001,-35.0421218872],"type":"Point"}
}