{
  "type": "Feature",
  "properties": {
    "addr:full":"Cnr Perry & Mortimer Sts Mudgee NSW 2850",
    "addr:postcode":"2850",
    "addr:street":"Cnr",
    "iso:country":"AU",
    "sg:address":"Cnr Perry & Mortimer Sts",
    "sg:city":"Mudgee",
    "sg:classifiers":[
        {
            "category":"Home & Garden",
            "subcategory":"Carpets & Floor Coverings",
            "type":"Retail Goods"
        }
    ],
    "sg:phone":"+61 2 6372 6655",
    "sg:postcode":"2850",
    "sg:province":"NSW",
    "sg:tags":[
        "tile",
        "wall"
    ],
    "wof:name":"Mudgee Tile Centre",
    "wof:placetype":"venue"
},
  "geometry": {"coordinates":[149.584564,-32.599251],"type":"Point"}
}