{
  "type": "Feature",
  "properties": {
    "addr:full":"113 Bridge St Port Macquarie NSW 2444",
    "addr:housenumber":"113",
    "addr:postcode":"2444",
    "addr:street":"Bridge St",
    "iso:country":"AU",
    "sg:address":"113 Bridge St",
    "sg:city":"Port Macquarie",
    "sg:classifiers":[
        {
            "category":"Personal",
            "subcategory":"Massage",
            "type":"Services"
        }
    ],
    "sg:phone":"+61 2 6584 0027",
    "sg:postcode":"2444",
    "sg:province":"NSW",
    "sg:tags":[
        "therapy"
    ],
    "wof:name":"Perfect Scents Aromatherapy",
    "wof:placetype":"venue"
},
  "geometry": {"coordinates":[152.904663,-31.433231],"type":"Point"}
}