{
  "type": "Feature",
  "properties": {
    "iso:country":"AU",
    "sg:address":"6/ 8 Redemptora Rd",
    "sg:city":"Henderson",
    "sg:classifiers":[
        {
            "category":"Government",
            "subcategory":"Fire Station",
            "type":"Public Place"
        }
    ],
    "sg:phone":"+61 8 9410 0144",
    "sg:postcode":"6166",
    "sg:province":"WA",
    "sg:tags":[
        "equipment",
        "protection",
        "consultant"
    ],
    "wof:name":"Marine Plant Systems Pty Ltd",
    "wof:placetype":"venue"
},
  "geometry": {"coordinates":[115.772743,-32.154297],"type":"Point"}
}