{
  "type": "Feature",
  "properties": {
    "addr:full":"62 Tumut St Adelong NSW 2729",
    "addr:housenumber":"62",
    "addr:postcode":"2729",
    "addr:street":"Tumut St",
    "iso:country":"AU",
    "sg:address":"62 Tumut St",
    "sg:city":"Adelong",
    "sg:classifiers":[
        {
            "category":"Banks & Credit Unions",
            "subcategory":"Bank",
            "type":"Services"
        }
    ],
    "sg:phone":"+61 2 6946 2922",
    "sg:postcode":"2729",
    "sg:province":"NSW",
    "wof:name":"Bendigo Community Bank",
    "wof:placetype":"venue"
},
  "geometry": {"coordinates":[148.06405599999999,-35.307884],"type":"Point"}
}