{
  "type": "Feature",
  "properties": {
    "addr:full":"Shp2/ 26 Tedder Ave Main Beach QLD 4217",
    "addr:housenumber":"26",
    "addr:postcode":"4217",
    "addr:street":"Tedder Ave",
    "iso:country":"AU",
    "sg:address":"Shp2/ 26 Tedder Ave",
    "sg:city":"Main Beach",
    "sg:classifiers":[
        {
            "category":"Shopping",
            "subcategory":"Baby Store",
            "type":"Retail Goods"
        }
    ],
    "sg:phone":"+61 7 5503 1030",
    "sg:postcode":"4217",
    "sg:province":"QLD",
    "sg:tags":[
        "children's",
        "wear"
    ],
    "wof:name":"Bebetique",
    "wof:placetype":"venue"
},
  "geometry": {"coordinates":[153.42489624000001,-27.97864151],"type":"Point"}
}