{
  "type": "Feature",
  "properties": {
    "addr:full":"Suite 3 Level 1 1 Transvaal Ave Double Bay NSW 2028",
    "addr:housenumber":"1",
    "addr:postcode":"2028",
    "addr:street":"Transvaal Ave",
    "iso:country":"AU",
    "sg:address":"Suite 3 Level 1 1 Transvaal Ave",
    "sg:city":"Double Bay",
    "sg:classifiers":[
        {
            "category":"Banks & Credit Unions",
            "subcategory":"Investment Brokerage",
            "type":"Services"
        }
    ],
    "sg:phone":"+61 2 9326 2732",
    "sg:postcode":"2028",
    "sg:province":"NSW",
    "wof:name":"Tasman Asset Management Limited",
    "wof:placetype":"venue"
},
  "geometry": {"coordinates":[151.243972778,-33.8765411377],"type":"Point"}
}