{
  "type": "Feature",
  "properties": {
    "addr:full":"4 Cook St West Perth WA 6005",
    "addr:housenumber":"4",
    "addr:postcode":"6005",
    "addr:street":"Cook St",
    "iso:country":"AU",
    "sg:address":"4 Cook St",
    "sg:city":"West Perth",
    "sg:classifiers":[
        {
            "category":"Social Services",
            "subcategory":"Retirement Home",
            "type":"Services"
        }
    ],
    "sg:phone":"+61 8 9226 3177",
    "sg:postcode":"6005",
    "sg:province":"WA",
    "sg:tags":[
        "environmental",
        "consultant",
        "pollution"
    ],
    "wof:name":"M.B.S Environmental",
    "wof:placetype":"venue"
},
  "geometry": {"coordinates":[115.840049744,-31.9472885132],"type":"Point"}
}