{
  "type": "Feature",
  "properties": {
    "addr:full":"11 James St Maitland NSW 2320",
    "addr:housenumber":"11",
    "addr:postcode":"2320",
    "addr:street":"James St",
    "iso:country":"AU",
    "sg:address":"11 James St",
    "sg:city":"Maitland",
    "sg:classifiers":[
        {
            "category":"Retail",
            "subcategory":"Storage",
            "type":"Services"
        }
    ],
    "sg:phone":"+61 2 4933 3587",
    "sg:postcode":"2320",
    "sg:province":"NSW",
    "wof:name":"Extra Space Mini Storage",
    "wof:placetype":"venue"
},
  "geometry": {"coordinates":[151.58819580100001,-32.699508667],"type":"Point"}
}