{
  "type": "Feature",
  "properties": {
    "addr:full":"Clunes Rd Clunes NSW 2480",
    "addr:postcode":"2480",
    "addr:street":"Clunes Rd",
    "iso:country":"AU",
    "sg:address":"Clunes Rd",
    "sg:city":"Clunes",
    "sg:classifiers":[
        {
            "category":"Home & Garden",
            "subcategory":"Building Materials",
            "type":"Retail Goods"
        }
    ],
    "sg:phone":"+61 2 6629 1482",
    "sg:postcode":"2480",
    "sg:province":"NSW",
    "sg:tags":[
        "tile",
        "roofing"
    ],
    "wof:name":"Coronakes Philip",
    "wof:placetype":"venue"
},
  "geometry": {"coordinates":[153.34684753400001,-28.7626209259],"type":"Point"}
}