{
  "type": "Feature",
  "properties": {
    "addr:full":"401 Robina Town Centre Drv Robina QLD 4226",
    "addr:housenumber":"401",
    "addr:postcode":"4226",
    "addr:street":"Robina Town Centre Drv",
    "iso:country":"AU",
    "sg:address":"401 Robina Town Centre Drv",
    "sg:city":"Robina",
    "sg:classifiers":[
        {
            "category":"Fast Food",
            "type":"Food & Drink"
        }
    ],
    "sg:phone":"+61 7 5578 9524",
    "sg:postcode":"4226",
    "sg:province":"QLD",
    "sg:tags":[
        "away",
        "take"
    ],
    "wof:name":"Seafood Affair",
    "wof:placetype":"venue"
},
  "geometry": {"coordinates":[153.38783264200001,-28.0696353912],"type":"Point"}
}