{
  "type": "Feature",
  "properties": {
    "addr:full":"Unit 1/59- 63 Mooringe Ave Plympton North SA 5037",
    "addr:housenumber":"63",
    "addr:postcode":"5037",
    "addr:street":"Mooringe Ave",
    "iso:country":"AU",
    "sg:address":"Unit 1/59- 63 Mooringe Ave",
    "sg:city":"Plympton North",
    "sg:classifiers":[
        {
            "category":"Wholesale",
            "subcategory":"Painting Supplies",
            "type":"Manufacturing & Wholesale Goods"
        }
    ],
    "sg:phone":"+61 8 8293 2020",
    "sg:postcode":"5037",
    "sg:province":"SA",
    "sg:tags":[
        "product",
        "cleaning"
    ],
    "wof:name":"Agar Cleaning Systems Pty Ltd",
    "wof:placetype":"venue"
},
  "geometry": {"coordinates":[138.54681396500001,-34.9602432251],"type":"Point"}
}