{
  "type": "Feature",
  "properties": {
    "addr:full":"Castle St Castle Hill Prvte Bxs NSW 1765",
    "addr:postcode":"1765",
    "addr:street":"Castle St",
    "iso:country":"AU",
    "sg:address":"Castle St",
    "sg:city":"Castle Hill Prvte Bxs",
    "sg:classifiers":[
        {
            "category":"Cafe",
            "type":"Food & Drink"
        }
    ],
    "sg:phone":"+61 2 9659 3900",
    "sg:postcode":"1765",
    "sg:province":"NSW",
    "wof:name":"Orchid Hill Bakery Cafe",
    "wof:placetype":"venue"
},
  "geometry": {"coordinates":[151.01724200000001,-33.730858],"type":"Point"}
}