{
  "type": "Feature",
  "properties": {
    "iso:country":"AU",
    "sg:address":"Suite 1, 6 Dellamarta Rd",
    "sg:city":"Wangara",
    "sg:classifiers":[
        {
            "category":"Education",
            "subcategory":"Music School",
            "type":"Public Place"
        }
    ],
    "sg:phone":"+61 8 9409 8070",
    "sg:postcode":"6065",
    "sg:province":"WA",
    "sg:tags":[
        "teacher"
    ],
    "wof:name":"W.A.G.T. School Of Music",
    "wof:placetype":"venue"
},
  "geometry": {"coordinates":[115.81477356000001,-31.7891311646],"type":"Point"}
}