{
  "type": "Feature",
  "properties": {
    "iso:country":"AU",
    "sg:address":"51 Nyah St",
    "sg:city":"Swan Hill",
    "sg:classifiers":[
        {
            "category":"Retail",
            "subcategory":"Auto Repair",
            "type":"Services"
        }
    ],
    "sg:phone":"+61 3 5032 3729",
    "sg:postcode":"3585",
    "sg:province":"VIC",
    "sg:tags":[
        "wheel",
        "balancing",
        "alignment"
    ],
    "wof:name":"Bridgestone Tyre Centres",
    "wof:placetype":"venue"
},
  "geometry": {"coordinates":[143.55517599999999,-35.330837],"type":"Point"}
}