{
  "type": "Feature",
  "properties": {
    "addr:full":"PO Box 2542 Bendigo VIC 3554",
    "addr:postcode":"3554",
    "iso:country":"AU",
    "sg:address":"PO Box 2542",
    "sg:city":"Bendigo",
    "sg:classifiers":[
        {
            "category":"Building & Trades",
            "subcategory":"Plumbing",
            "type":"Services"
        }
    ],
    "sg:phone":"+61 3 5442 7887",
    "sg:postcode":"3554",
    "sg:province":"VIC",
    "sg:tags":[
        "plumber",
        "gasfitters"
    ],
    "wof:name":"Morley Peter",
    "wof:placetype":"venue"
},
  "geometry": {"coordinates":[144.28007507300001,-36.7584915161],"type":"Point"}
}