{
  "type": "Feature",
  "properties": {
    "iso:country":"AU",
    "sg:address":"2 Kimmins Pl",
    "sg:city":"Figtree",
    "sg:classifiers":[
        {
            "category":"Building & Trades",
            "subcategory":"Plumbing",
            "type":"Services"
        }
    ],
    "sg:phone":"+61 407 422 244",
    "sg:postcode":"2525",
    "sg:province":"NSW",
    "sg:tags":[
        "plumber",
        "gasfitters"
    ],
    "wof:name":"Mountford Plumbing Services",
    "wof:placetype":"venue"
},
  "geometry": {"coordinates":[150.84559631400001,-34.4302940369],"type":"Point"}
}