{
  "type": "Feature",
  "properties": {
    "addr:full":"1710 Burwood Hwy Belgrave VIC 3160",
    "addr:housenumber":"1710",
    "addr:postcode":"3160",
    "addr:street":"Burwood Hwy",
    "iso:country":"AU",
    "sg:address":"1710 Burwood Hwy",
    "sg:city":"Belgrave",
    "sg:classifiers":[
        {
            "category":"Cafe",
            "type":"Food & Drink"
        }
    ],
    "sg:phone":"+61 3 9754 4988",
    "sg:postcode":"3160",
    "sg:province":"VIC",
    "wof:name":"Queen Of Tarts Cafes",
    "wof:placetype":"venue"
},
  "geometry": {"coordinates":[145.35513305699999,-37.9085655212],"type":"Point"}
}