{
  "type": "Feature",
  "properties": {
    "addr:full":"1263 Sydney Rd Fawkner VIC 3060",
    "addr:housenumber":"1263",
    "addr:postcode":"3060",
    "addr:street":"Sydney Rd",
    "iso:country":"AU",
    "sg:address":"1263 Sydney Rd",
    "sg:city":"Fawkner",
    "sg:classifiers":[
        {
            "category":"Autos & Motor Vehicles",
            "subcategory":"Automobile Sales",
            "type":"Retail Goods"
        }
    ],
    "sg:phone":"+61 3 9359 1333",
    "sg:postcode":"3060",
    "sg:province":"VIC",
    "sg:tags":[
        "car",
        "new"
    ],
    "wof:name":"Mantello Holden",
    "wof:placetype":"venue"
},
  "geometry": {"coordinates":[144.95994567899999,-37.7026176453],"type":"Point"}
}