{
  "type": "Feature",
  "properties": {
    "iso:country":"AU",
    "sg:address":"204 Homer St",
    "sg:city":"Earlwood",
    "sg:classifiers":[
        {
            "category":"Fast Food",
            "type":"Food & Drink"
        }
    ],
    "sg:phone":"+61 2 9558 4293",
    "sg:postcode":"2206",
    "sg:province":"NSW",
    "sg:tags":[
        "away",
        "take"
    ],
    "wof:name":"Earlwood Chinese Take-Away Food Centre",
    "wof:placetype":"venue"
},
  "geometry": {"coordinates":[151.12333699999999,-33.928047],"type":"Point"}
}