{
  "type": "Feature",
  "properties": {
    "addr:full":"21 Anfield St Glenorchy TAS 7010",
    "addr:housenumber":"21",
    "addr:postcode":"7010",
    "addr:street":"Anfield St",
    "iso:country":"AU",
    "sg:address":"21 Anfield St",
    "sg:city":"Glenorchy",
    "sg:classifiers":[
        {
            "category":"Professional",
            "subcategory":"Art Services",
            "type":"Services"
        }
    ],
    "sg:phone":"+61 3 6272 2222",
    "sg:postcode":"7010",
    "sg:province":"TAS",
    "sg:tags":[
        "decorator",
        "painter"
    ],
    "wof:name":"Danny Malone",
    "wof:placetype":"venue"
},
  "geometry": {"coordinates":[147.27828979500001,-42.8281593323],"type":"Point"}
}