{
  "type": "Feature",
  "properties": {
    "iso:country":"AU",
    "sg:address":"39 Warren Ave",
    "sg:city":"Bankstown",
    "sg:classifiers":[
        {
            "category":"Building & Trades",
            "subcategory":"Pest Control",
            "type":"Services"
        }
    ],
    "sg:phone":"+61 1300 241 500",
    "sg:postcode":"2200",
    "sg:province":"NSW",
    "wof:name":"A Fumapest Service",
    "wof:placetype":"venue"
},
  "geometry": {"coordinates":[151.03613300000001,-33.932632],"type":"Point"}
}