{
  "type": "Feature",
  "properties": {
    "addr:full":"28 Medina St Moorooka QLD 4105",
    "addr:housenumber":"28",
    "addr:postcode":"4105",
    "addr:street":"Medina St",
    "iso:country":"AU",
    "sg:address":"28 Medina St",
    "sg:city":"Moorooka",
    "sg:classifiers":[
        {
            "category":"Shopping",
            "subcategory":"Jewelry",
            "type":"Retail Goods"
        }
    ],
    "sg:phone":"+61 7 3700 6210",
    "sg:postcode":"4105",
    "sg:province":"QLD",
    "sg:tags":[
        "jeweller"
    ],
    "wof:name":"World of Glass",
    "wof:placetype":"venue"
},
  "geometry": {"coordinates":[153.027175903,-27.537153244],"type":"Point"}
}