{
  "type": "Feature",
  "properties": {
    "addr:full":"PO Box 438 Dromana VIC 3936",
    "addr:postcode":"3936",
    "iso:country":"AU",
    "sg:address":"PO Box 438",
    "sg:city":"Dromana",
    "sg:classifiers":[
        {
            "category":"Building & Trades",
            "subcategory":"Construction",
            "type":"Services"
        }
    ],
    "sg:phone":"+61 3 5989 7088",
    "sg:postcode":"3936",
    "sg:province":"VIC",
    "sg:tags":[
        "contractor"
    ],
    "wof:name":"Construction By Law",
    "wof:placetype":"venue"
},
  "geometry": {"coordinates":[144.964447022,-38.3328781128],"type":"Point"}
}