{
  "type": "Feature",
  "properties": {
    "addr:full":"Unit 4, 9 Hayden Crt Myaree WA 6154",
    "addr:housenumber":"9",
    "addr:postcode":"6154",
    "addr:street":"Hayden Crt",
    "iso:country":"AU",
    "sg:address":"Unit 4, 9 Hayden Crt",
    "sg:city":"Myaree",
    "sg:classifiers":[
        {
            "category":"Wholesale",
            "subcategory":"Electrical",
            "type":"Manufacturing & Wholesale Goods"
        }
    ],
    "sg:phone":"+61 8 9317 2060",
    "sg:postcode":"6154",
    "sg:province":"WA",
    "sg:tags":[
        "wholesaler",
        "mfrs",
        "accessory"
    ],
    "wof:name":"Tatlan Industries Pty Ltd",
    "wof:placetype":"venue"
},
  "geometry": {"coordinates":[115.81739,-32.044849],"type":"Point"}
}