{
  "type": "Feature",
  "properties": {
    "addr:full":"Shop 1 62 Mount Barker Rd Stirling SA 5152",
    "addr:housenumber":"shop;62",
    "addr:postcode":"5152",
    "addr:street":"Mount Barker Rd",
    "iso:country":"AU",
    "sg:address":"Shop 1 62 Mount Barker Rd",
    "sg:city":"Stirling",
    "sg:classifiers":[
        {
            "category":"Real Estate",
            "subcategory":"Real Estate Agent",
            "type":"Services"
        }
    ],
    "sg:phone":"+61 8 8339 6333",
    "sg:postcode":"5152",
    "sg:province":"SA",
    "wof:name":"Brock Harcourts",
    "wof:placetype":"venue"
},
  "geometry": {"coordinates":[138.72201538100001,-35.0079650879],"type":"Point"}
}