{
  "type": "Feature",
  "properties": {
    "addr:full":"58 Oxford St Burwood NSW 2134",
    "addr:housenumber":"58",
    "addr:postcode":"2134",
    "addr:street":"Oxford St",
    "iso:country":"AU",
    "sg:address":"58 Oxford St",
    "sg:city":"Burwood",
    "sg:classifiers":[
        {
            "category":"Professional",
            "subcategory":"Business Services",
            "type":"Services"
        }
    ],
    "sg:phone":"+61 2 9744 1590",
    "sg:postcode":"2134",
    "sg:province":"NSW",
    "sg:tags":[
        "exporter"
    ],
    "wof:name":"Choice & W International Trading Pty Ltd",
    "wof:placetype":"venue"
},
  "geometry": {"coordinates":[151.09771728499999,-33.8786735535],"type":"Point"}
}