{
  "type": "Feature",
  "properties": {
    "iso:country":"AU",
    "sg:address":"21 Molesworth St",
    "sg:city":"Lismore",
    "sg:classifiers":[
        {
            "category":"Banks & Credit Unions",
            "subcategory":"Bank",
            "type":"Services"
        }
    ],
    "sg:phone":"+61 2 6621 2553",
    "sg:postcode":"2480",
    "sg:province":"NSW",
    "sg:tags":[
        "broker",
        "mortgage"
    ],
    "wof:name":"R.F.N. Regional Finance Network Pty Ltd",
    "wof:placetype":"venue"
},
  "geometry": {"coordinates":[153.277175903,-28.8070812225],"type":"Point"}
}