{
  "type": "Feature",
  "properties": {
    "addr:full":"8/ 66 Pritchard Rd Virginia QLD 4014",
    "addr:housenumber":"/ 66",
    "addr:postcode":"4014",
    "addr:street":"Pritchard Rd",
    "iso:country":"AU",
    "sg:address":"8/ 66 Pritchard Rd",
    "sg:city":"Virginia",
    "sg:classifiers":[
        {
            "category":"Autos & Motor Vehicles",
            "subcategory":"Auto Supplies",
            "type":"Retail Goods"
        }
    ],
    "sg:phone":"+61 7 3265 2666",
    "sg:postcode":"4014",
    "sg:province":"QLD",
    "sg:tags":[
        "transmission",
        "equipment",
        "power"
    ],
    "wof:name":"Statewide Bearings",
    "wof:placetype":"venue"
},
  "geometry": {"coordinates":[153.058029175,-27.3740100861],"type":"Point"}
}