{
  "type": "Feature",
  "properties": {
    "addr:full":"28 Simon St Blackburn North VIC 3130",
    "addr:housenumber":"28",
    "addr:postcode":"3130",
    "addr:street":"Simon St",
    "iso:country":"AU",
    "sg:address":"28 Simon St",
    "sg:city":"Blackburn North",
    "sg:classifiers":[
        {
            "category":"Shopping",
            "subcategory":"Party Supplies",
            "type":"Retail Goods"
        }
    ],
    "sg:phone":"+61 3 9878 6511",
    "sg:postcode":"3130",
    "sg:province":"VIC",
    "sg:tags":[
        "children's"
    ],
    "wof:name":"Abracadabra Magic .com.au",
    "wof:placetype":"venue"
},
  "geometry": {"coordinates":[145.157272339,-37.8025741577],"type":"Point"}
}