{
  "type": "Feature",
  "properties": {
    "iso:country":"AU",
    "sg:address":"PO Box 636",
    "sg:city":"Redcliffe",
    "sg:classifiers":[
        {
            "category":"Retail",
            "subcategory":"Driving School",
            "type":"Services"
        }
    ],
    "sg:phone":"+61 7 3284 4066",
    "sg:postcode":"4020",
    "sg:province":"QLD",
    "wof:name":"Billabong Off Road Driver Training Centre",
    "wof:placetype":"venue"
},
  "geometry": {"coordinates":[153.107224,-27.22217],"type":"Point"}
}