{
  "type": "Feature",
  "properties": {
    "addr:full":"Unit 9/ 8 Apollo St Warriewood NSW 2102",
    "addr:housenumber":"8",
    "addr:postcode":"2102",
    "addr:street":"Apollo St",
    "iso:country":"AU",
    "sg:address":"Unit 9/ 8 Apollo St",
    "sg:city":"Warriewood",
    "sg:classifiers":[
        {
            "category":"Autos & Motor Vehicles",
            "subcategory":"Auto Supplies",
            "type":"Retail Goods"
        }
    ],
    "sg:phone":"+61 2 9999 5444",
    "sg:postcode":"2102",
    "sg:province":"NSW",
    "sg:tags":[
        "paint",
        "automotive"
    ],
    "wof:name":"Automotive Touch-Up Technology Pty Ltd",
    "wof:placetype":"venue"
},
  "geometry": {"coordinates":[151.289276,-33.67944],"type":"Point"}
}