{
  "type": "Feature",
  "properties": {
    "iso:country":"AU",
    "sg:address":"4 Burgess St",
    "sg:city":"Tullamarine",
    "sg:classifiers":[
        {
            "category":"Home & Garden",
            "subcategory":"Kitchen Supply",
            "type":"Retail Goods"
        }
    ],
    "sg:phone":"+61 419 330 004",
    "sg:postcode":"3043",
    "sg:province":"VIC",
    "sg:tags":[
        "traffic",
        "equipment",
        "safety",
        "road"
    ],
    "wof:name":"Crash Guardrail Installations Pty Ltd",
    "wof:placetype":"venue"
},
  "geometry": {"coordinates":[144.87257385300001,-37.7001113892],"type":"Point"}
}