{
  "type": "Feature",
  "properties": {
    "addr:full":"10 Mount St North Sydney NSW 2060",
    "addr:housenumber":"10",
    "addr:postcode":"2060",
    "addr:street":"Mount St",
    "iso:country":"AU",
    "sg:address":"10 Mount St",
    "sg:city":"North Sydney",
    "sg:classifiers":[
        {
            "category":"Real Estate",
            "subcategory":"Developer",
            "type":"Services"
        }
    ],
    "sg:phone":"+61 412 246 248",
    "sg:postcode":"2060",
    "sg:province":"NSW",
    "sg:tags":[
        "development"
    ],
    "wof:name":"Nebkahn Pty Ltd",
    "wof:placetype":"venue"
},
  "geometry": {"coordinates":[151.20492553700001,-33.8383979797],"type":"Point"}
}