{
  "type": "Feature",
  "properties": {
    "addr:full":"71 Lyttleton St East Launceston TAS 7250",
    "addr:housenumber":"71",
    "addr:postcode":"7250",
    "addr:street":"Lyttleton St East",
    "iso:country":"AU",
    "sg:address":"71 Lyttleton St",
    "sg:city":"East Launceston",
    "sg:classifiers":[
        {
            "category":"Farming",
            "subcategory":"Farm & Veterinary Services",
            "type":"Manufacturing & Wholesale Goods"
        }
    ],
    "sg:phone":"+61 3 6331 0849",
    "sg:postcode":"7250",
    "sg:province":"TAS",
    "sg:tags":[
        "agricultural",
        "advisory"
    ],
    "wof:name":"Smart Viticulture",
    "wof:placetype":"venue"
},
  "geometry": {"coordinates":[147.150146484,-41.4385566711],"type":"Point"}
}