{
  "type": "Feature",
  "properties": {
    "addr:full":"Shop 7 2 Star Rd Bright VIC 3741",
    "addr:housenumber":"shop;2",
    "addr:postcode":"3741",
    "addr:street":"Star Rd",
    "iso:country":"AU",
    "sg:address":"Shop 7 2 Star Rd",
    "sg:city":"Bright",
    "sg:classifiers":[
        {
            "category":"Professional",
            "subcategory":"Printing & Photocopies",
            "type":"Services"
        }
    ],
    "sg:phone":"+61 3 5755 1102",
    "sg:postcode":"3741",
    "sg:province":"VIC",
    "sg:tags":[
        "trophy"
    ],
    "wof:name":"Jackaroo Blue",
    "wof:placetype":"venue"
},
  "geometry": {"coordinates":[146.95954900000001,-36.727173],"type":"Point"}
}