{
  "type": "Feature",
  "properties": {
    "iso:country":"AU",
    "sg:address":"111 Wollombi Rd",
    "sg:city":"Cessnock",
    "sg:classifiers":[
        {
            "category":"Home & Garden",
            "subcategory":"Carpets & Floor Coverings",
            "type":"Retail Goods"
        }
    ],
    "sg:phone":"+61 2 4990 8522",
    "sg:postcode":"2325",
    "sg:province":"NSW",
    "sg:tags":[
        "tile",
        "wall"
    ],
    "wof:name":"Tile Mania",
    "wof:placetype":"venue"
},
  "geometry": {"coordinates":[151.35336303700001,-32.8333282471],"type":"Point"}
}