{
  "type": "Feature",
  "properties": {
    "addr:full":"106 Enterprise St Kunda Park QLD 4556",
    "addr:housenumber":"106",
    "addr:postcode":"4556",
    "addr:street":"Enterprise St",
    "iso:country":"AU",
    "sg:address":"106 Enterprise St",
    "sg:city":"Kunda Park",
    "sg:classifiers":[
        {
            "category":"Professional",
            "subcategory":"Testing Lab",
            "type":"Services"
        }
    ],
    "sg:phone":"+61 419 747 377",
    "sg:postcode":"4556",
    "sg:province":"QLD",
    "sg:tags":[
        "inspection"
    ],
    "wof:name":"Pipeline Accreditation Services",
    "wof:placetype":"venue"
},
  "geometry": {"coordinates":[153.02961730999999,-26.6667938232],"type":"Point"}
}