{
  "type": "Feature",
  "properties": {
    "addr:full":"6 Boron St Narangba QLD 4504",
    "addr:housenumber":"6",
    "addr:postcode":"4504",
    "addr:street":"Boron St",
    "iso:country":"AU",
    "sg:address":"6 Boron St",
    "sg:city":"Narangba",
    "sg:classifiers":[
        {
            "category":"Home & Garden",
            "subcategory":"Building Materials",
            "type":"Retail Goods"
        }
    ],
    "sg:phone":"+61 7 3888 2468",
    "sg:postcode":"4504",
    "sg:province":"QLD",
    "sg:tags":[
        "supply"
    ],
    "wof:name":"Northside Mini Mix Pty Ltd",
    "wof:placetype":"venue"
},
  "geometry": {"coordinates":[152.98690795900001,-27.2016525269],"type":"Point"}
}