{
  "type": "Feature",
  "properties": {
    "addr:full":"25 Sonder Crs Bakewell NT 0832",
    "addr:housenumber":"25",
    "addr:postcode":"nt 0832",
    "addr:street":"Sonder Crs",
    "iso:country":"AU",
    "sg:address":"25 Sonder Crs",
    "sg:city":"Bakewell",
    "sg:classifiers":[
        {
            "category":"Real Estate",
            "subcategory":"Real Estate Agent",
            "type":"Services"
        }
    ],
    "sg:phone":"+61 8 8932 2698",
    "sg:postcode":"0832",
    "sg:province":"NT",
    "sg:tags":[
        "handyman's",
        "equipment",
        "hire",
        "builders",
        "contractor"
    ],
    "wof:name":"Raemac Grader Hire",
    "wof:placetype":"venue"
},
  "geometry": {"coordinates":[130.99290500000001,-12.49577],"type":"Point"}
}