{
  "type": "Feature",
  "properties": {
    "addr:full":"Unit 3/ 9 Mercer La Joondalup WA 6027",
    "addr:housenumber":"9",
    "addr:postcode":"6027",
    "addr:street":"Mercer La",
    "iso:country":"AU",
    "sg:address":"Unit 3/ 9 Mercer La",
    "sg:city":"Joondalup",
    "sg:classifiers":[
        {
            "category":"Home & Garden",
            "subcategory":"Building Materials",
            "type":"Retail Goods"
        }
    ],
    "sg:phone":"+61 8 9300 0841",
    "sg:postcode":"6027",
    "sg:province":"WA",
    "sg:tags":[
        "fitting",
        "door"
    ],
    "wof:name":"Door Stop",
    "wof:placetype":"venue"
},
  "geometry": {"coordinates":[115.761421204,-31.7433567047],"type":"Point"}
}