{
  "type": "Feature",
  "properties": {
    "addr:full":"28 Marshall St Goondiwindi QLD 4390",
    "addr:housenumber":"28",
    "addr:postcode":"4390",
    "addr:street":"Marshall St",
    "iso:country":"AU",
    "sg:address":"28 Marshall St",
    "sg:city":"Goondiwindi",
    "sg:classifiers":[
        {
            "category":"Autos & Motor Vehicles",
            "subcategory":"Auto Supplies",
            "type":"Retail Goods"
        }
    ],
    "sg:phone":"+61 7 4671 1177",
    "sg:postcode":"4390",
    "sg:province":"QLD",
    "sg:tags":[
        "tyre"
    ],
    "wof:name":"Goondiwindi Tyrepower",
    "wof:placetype":"venue"
},
  "geometry": {"coordinates":[150.30371093799999,-28.5465488434],"type":"Point"}
}