{
  "type": "Feature",
  "properties": {
    "addr:full":"71 Simpson Drv Bilambil Heights NSW 2486",
    "addr:housenumber":"71",
    "addr:postcode":"2486",
    "addr:street":"Simpson Drv",
    "iso:country":"AU",
    "sg:address":"71 Simpson Drv",
    "sg:city":"Bilambil Heights",
    "sg:classifiers":[
        {
            "category":"Food & Beverages",
            "subcategory":"Liquor & Beverages",
            "type":"Retail Goods"
        }
    ],
    "sg:phone":"+61 7 5590 7229",
    "sg:postcode":"2486",
    "sg:province":"NSW",
    "sg:tags":[
        "store"
    ],
    "wof:name":"Bilambil Cellars",
    "wof:placetype":"venue"
},
  "geometry": {"coordinates":[153.48507690400001,-28.2156867981],"type":"Point"}
}