{
  "type": "Feature",
  "properties": {
    "iso:country":"AU",
    "sg:address":"PO Box 140",
    "sg:city":"Yarragon",
    "sg:classifiers":[
        {
            "category":"Professional",
            "type":"Services"
        }
    ],
    "sg:phone":"+61 3 5634 2753",
    "sg:postcode":"3823",
    "sg:province":"VIC",
    "sg:tags":[
        "transport"
    ],
    "wof:name":"Parkinsons Refrigerated Transport",
    "wof:placetype":"venue"
},
  "geometry": {"coordinates":[146.084976,-38.184219],"type":"Point"}
}