{
  "type": "Feature",
  "properties": {
    "addr:full":"45 Moreland St Footscray VIC 3011",
    "addr:housenumber":"45",
    "addr:postcode":"3011",
    "addr:street":"Moreland St",
    "iso:country":"AU",
    "sg:address":"45 Moreland St",
    "sg:city":"Footscray",
    "sg:classifiers":[
        {
            "category":"Cinema",
            "subcategory":"Movie Theater",
            "type":"Entertainment"
        }
    ],
    "sg:phone":"+61 3 9689 5677",
    "sg:postcode":"3011",
    "sg:province":"VIC",
    "wof:name":"Footscray Community Arts Centre",
    "wof:placetype":"venue"
},
  "geometry": {"coordinates":[144.90682983400001,-37.8033447266],"type":"Point"}
}