{
  "type": "Feature",
  "properties": {
    "iso:country":"AU",
    "sg:address":"436 Barry Rd",
    "sg:city":"Broadmeadows",
    "sg:classifiers":[
        {
            "category":"Wholesale",
            "subcategory":"Furniture",
            "type":"Manufacturing & Wholesale Goods"
        }
    ],
    "sg:phone":"+61 3 9309 5664",
    "sg:postcode":"3047",
    "sg:province":"VIC",
    "sg:tags":[
        "wholesaler",
        "mfrs"
    ],
    "wof:name":"Rana Furniture Pty Ltd",
    "wof:placetype":"venue"
},
  "geometry": {"coordinates":[144.938964844,-37.6655273438],"type":"Point"}
}