{
  "type": "Feature",
  "properties": {
    "iso:country":"AU",
    "sg:address":"10-14 Hunter St",
    "sg:city":"Parramatta",
    "sg:classifiers":[
        {
            "category":"Professional",
            "subcategory":"Employment Agencies",
            "type":"Services"
        }
    ],
    "sg:phone":"+61 2 9635 8011",
    "sg:postcode":"2150",
    "sg:province":"NSW",
    "wof:name":"Prime Appointments Pty Ltd",
    "wof:placetype":"venue"
},
  "geometry": {"coordinates":[151.03512573200001,-33.8424835205],"type":"Point"}
}