{
  "type": "Feature",
  "properties": {
    "addr:full":"2/ 56 Ewing St Bentley WA 6102",
    "addr:housenumber":"/ 56",
    "addr:postcode":"6102",
    "addr:street":"Ewing St",
    "iso:country":"AU",
    "sg:address":"2/ 56 Ewing St",
    "sg:city":"Bentley",
    "sg:classifiers":[
        {
            "category":"Professional",
            "subcategory":"Printing & Photocopies",
            "type":"Services"
        }
    ],
    "sg:phone":"+61 8 9258 7066",
    "sg:postcode":"6102",
    "sg:province":"WA",
    "sg:tags":[
        "equipment",
        "plan"
    ],
    "wof:name":"Digital Documents",
    "wof:placetype":"venue"
},
  "geometry": {"coordinates":[115.92658996599999,-31.9990901947],"type":"Point"}
}