{
  "type": "Feature",
  "properties": {
    "iso:country":"AU",
    "sg:address":"62 Glenview Rd",
    "sg:city":"Palmview",
    "sg:classifiers":[
        {
            "category":"Retail",
            "subcategory":"Storage",
            "type":"Services"
        }
    ],
    "sg:phone":"+61 1800 851 135",
    "sg:postcode":"4553",
    "sg:province":"QLD",
    "sg:tags":[
        "removal",
        "furniture"
    ],
    "sg:website":"http://www.abberkade.com.au",
    "wof:name":"Abberkade Furniture Removals & Storage.",
    "wof:placetype":"venue"
},
  "geometry": {"coordinates":[153.04188500000001,-26.760193],"type":"Point"}
}