{
  "type": "Feature",
  "properties": {
    "addr:full":"10 Mason St Reservoir VIC 3073",
    "addr:housenumber":"10",
    "addr:postcode":"3073",
    "addr:street":"Mason St",
    "iso:country":"AU",
    "sg:address":"10 Mason St",
    "sg:city":"Reservoir",
    "sg:classifiers":[
        {
            "category":"Personal",
            "subcategory":"Massage",
            "type":"Services"
        }
    ],
    "sg:phone":"+61 417 136 427",
    "sg:postcode":"3073",
    "sg:province":"VIC",
    "sg:tags":[
        "therapy"
    ],
    "wof:name":"Tranquil Mind & Body",
    "wof:placetype":"venue"
},
  "geometry": {"coordinates":[145.01040649399999,-37.7283058167],"type":"Point"}
}