{
  "type": "Feature",
  "properties": {
    "addr:full":"93- 97 Seventh St Mildura VIC 3502",
    "addr:housenumber":"97",
    "addr:postcode":"3502",
    "addr:street":"Seventh St",
    "iso:country":"AU",
    "sg:address":"93- 97 Seventh St",
    "sg:city":"Mildura",
    "sg:classifiers":[
        {
            "category":"Autos & Motor Vehicles",
            "subcategory":"Auto Supplies",
            "type":"Retail Goods"
        }
    ],
    "sg:phone":"+61 3 5022 1814",
    "sg:postcode":"3502",
    "sg:province":"VIC",
    "sg:tags":[
        "accessory"
    ],
    "wof:name":"Autopro",
    "wof:placetype":"venue"
},
  "geometry": {"coordinates":[142.153244019,-34.1758880615],"type":"Point"}
}