{
  "type": "Feature",
  "properties": {
    "addr:full":"2nd Floor Suite 1, 36 Mitchell St Darwin NT 0800",
    "addr:housenumber":"36",
    "addr:postcode":"nt 0800",
    "addr:street":"Mitchell St",
    "iso:country":"AU",
    "sg:address":"2nd Floor Suite 1, 36 Mitchell St",
    "sg:city":"Darwin",
    "sg:classifiers":[
        {
            "category":"Professional",
            "subcategory":"Employment Agencies",
            "type":"Services"
        }
    ],
    "sg:phone":"+61 1300 728 151",
    "sg:postcode":"0800",
    "sg:province":"NT",
    "sg:tags":[
        "occupational",
        "therapist"
    ],
    "wof:name":"Maximus Solutions Australia Health",
    "wof:placetype":"venue"
},
  "geometry": {"coordinates":[130.841186523,-12.4641962051],"type":"Point"}
}