{
  "type": "Feature",
  "properties": {
    "addr:full":"14 Woolnough Rd Exeter SA 5019",
    "addr:housenumber":"14",
    "addr:postcode":"5019",
    "addr:street":"Woolnough Rd",
    "iso:country":"AU",
    "sg:address":"14 Woolnough Rd",
    "sg:city":"Exeter",
    "sg:classifiers":[
        {
            "category":"Health Services",
            "subcategory":"Doctor",
            "type":"Services"
        }
    ],
    "sg:phone":"+61 8 8449 6233",
    "sg:postcode":"5019",
    "sg:province":"SA",
    "sg:tags":[
        "medical",
        "practitioner"
    ],
    "wof:name":"James Clive M Dr",
    "wof:placetype":"venue"
},
  "geometry": {"coordinates":[138.489181519,-34.8389854431],"type":"Point"}
}