{
  "type": "Feature",
  "properties": {
    "addr:full":"458 Oceana Drv Howrah TAS 7018",
    "addr:housenumber":"458",
    "addr:postcode":"7018",
    "addr:street":"Oceana Drv",
    "iso:country":"AU",
    "sg:address":"458 Oceana Drv",
    "sg:city":"Howrah",
    "sg:classifiers":[
        {
            "category":"Structure",
            "subcategory":"Tunnel",
            "type":"Public Place"
        }
    ],
    "sg:phone":"+61 3 6247 1011",
    "sg:postcode":"7018",
    "sg:province":"TAS",
    "sg:tags":[
        "cleaner",
        "industrial",
        "vacuum"
    ],
    "wof:name":"Aussie Vac",
    "wof:placetype":"venue"
},
  "geometry": {"coordinates":[147.41197204599999,-42.8878250122],"type":"Point"}
}