{
  "type": "Feature",
  "properties": {
    "addr:full":"48-50 Scrivener St Warwick Farm NSW 2170",
    "addr:housenumber":"48-50",
    "addr:postcode":"2170",
    "addr:street":"Scrivener St",
    "iso:country":"AU",
    "sg:address":"48-50 Scrivener St",
    "sg:city":"Warwick Farm",
    "sg:classifiers":[
        {
            "category":"Professional",
            "subcategory":"Engineering",
            "type":"Services"
        }
    ],
    "sg:phone":"+61 2 9601 2022",
    "sg:postcode":"2170",
    "sg:province":"NSW",
    "sg:tags":[
        "manufacturing",
        "engineer"
    ],
    "wof:name":"A A Hydrological Services",
    "wof:placetype":"venue"
},
  "geometry": {"coordinates":[150.938232422,-33.9173316956],"type":"Point"}
}