{
  "type": "Feature",
  "properties": {
    "iso:country":"AU",
    "sg:address":"Un 3/ 294 New Cleveland Rd",
    "sg:city":"Tingalpa",
    "sg:classifiers":[
        {
            "category":"Retail",
            "subcategory":"Auto Repair",
            "type":"Services"
        }
    ],
    "sg:phone":"+61 7 3390 7222",
    "sg:postcode":"4173",
    "sg:province":"QLD",
    "sg:tags":[
        "camper-trailers",
        "caravan",
        "servicing"
    ],
    "wof:name":"Big Sky Caravan Repair",
    "wof:placetype":"venue"
},
  "geometry": {"coordinates":[153.14021301299999,-27.4795417786],"type":"Point"}
}