{
  "type": "Feature",
  "properties": {
    "addr:full":"683 Barrenjoey Rd Avalon NSW 2107",
    "addr:housenumber":"683",
    "addr:postcode":"2107",
    "addr:street":"Barrenjoey Rd",
    "iso:country":"AU",
    "sg:address":"683 Barrenjoey Rd",
    "sg:city":"Avalon",
    "sg:classifiers":[
        {
            "category":"Real Estate",
            "subcategory":"Real Estate Agent",
            "type":"Services"
        }
    ],
    "sg:phone":"+61 2 9918 7000",
    "sg:postcode":"2107",
    "sg:province":"NSW",
    "wof:name":"Delmege Residential",
    "wof:placetype":"venue"
},
  "geometry": {"coordinates":[151.33006286599999,-33.637096405],"type":"Point"}
}