{
  "type": "Feature",
  "properties": {
    "addr:full":"U2/ 27 Kyle St Rutherford NSW 2320",
    "addr:housenumber":"27",
    "addr:postcode":"2320",
    "addr:street":"U2 /;Kyle St",
    "iso:country":"AU",
    "sg:address":"U2/ 27 Kyle St",
    "sg:city":"Rutherford",
    "sg:classifiers":[
        {
            "category":"Professional",
            "subcategory":"Engineering",
            "type":"Services"
        }
    ],
    "sg:phone":"+61 2 4931 9233",
    "sg:postcode":"2320",
    "sg:province":"NSW",
    "sg:tags":[
        "engineer"
    ],
    "wof:name":"Oceanmaster Engineering",
    "wof:placetype":"venue"
},
  "geometry": {"coordinates":[151.497802734,-32.708782196],"type":"Point"}
}