{
  "type": "Feature",
  "properties": {
    "iso:country":"AU",
    "sg:address":"97-99 Kennedy Drv",
    "sg:city":"Tweed Heads",
    "sg:classifiers":[
        {
            "category":"Food & Beverages",
            "subcategory":"Liquor & Beverages",
            "type":"Retail Goods"
        }
    ],
    "sg:phone":"+61 7 5536 8400",
    "sg:postcode":"2485",
    "sg:province":"NSW",
    "sg:tags":[
        "store"
    ],
    "wof:name":"The Bay Boozatorium",
    "wof:placetype":"venue"
},
  "geometry": {"coordinates":[153.52030944800001,-28.1877975464],"type":"Point"}
}