{
  "type": "Feature",
  "properties": {
    "iso:country":"AU",
    "sg:address":"144 Sackville St",
    "sg:city":"Fairfield",
    "sg:classifiers":[
        {
            "category":"Professional",
            "subcategory":"Engineering",
            "type":"Services"
        }
    ],
    "sg:phone":"+61 2 9727 0566",
    "sg:postcode":"2165",
    "sg:province":"NSW",
    "sg:tags":[
        "building",
        "prefabricated",
        "transportable",
        "industrial",
        "commercial"
    ],
    "wof:name":"Designed Building Systems",
    "wof:placetype":"venue"
},
  "geometry": {"coordinates":[150.948974609,-33.8675346375],"type":"Point"}
}