{
  "type": "Feature",
  "properties": {
    "addr:full":"34 Old Hawkesbury Rd McGraths Hill NSW 2756",
    "addr:housenumber":"34",
    "addr:postcode":"2756",
    "addr:street":"Old Hawkesbury Rd",
    "iso:country":"AU",
    "sg:address":"34 Old Hawkesbury Rd",
    "sg:city":"McGraths Hill",
    "sg:classifiers":[
        {
            "category":"Professional",
            "subcategory":"Printing & Photocopies",
            "type":"Services"
        }
    ],
    "sg:phone":"+61 2 4577 3044",
    "sg:postcode":"2756",
    "sg:province":"NSW",
    "sg:tags":[
        "trophy"
    ],
    "wof:name":"Garry Hudson's Unique Signs & Engraving",
    "wof:placetype":"venue"
},
  "geometry": {"coordinates":[150.841598511,-33.6165885925],"type":"Point"}
}