{
  "type": "Feature",
  "properties": {
    "addr:full":"28 Punari St Currajong QLD 4812",
    "addr:housenumber":"28",
    "addr:postcode":"4812",
    "addr:street":"Punari St",
    "iso:country":"AU",
    "sg:address":"28 Punari St",
    "sg:city":"Currajong",
    "sg:classifiers":[
        {
            "category":"Retail",
            "subcategory":"Car Wash",
            "type":"Services"
        }
    ],
    "sg:phone":"+61 417 255 009",
    "sg:postcode":"4812",
    "sg:province":"QLD",
    "sg:tags":[
        "truck",
        "cleaning"
    ],
    "wof:name":"Mother Hubbards Car Detailing",
    "wof:placetype":"venue"
},
  "geometry": {"coordinates":[146.77496300000001,-19.273598],"type":"Point"}
}