{
  "type": "Feature",
  "properties": {
    "iso:country":"AU",
    "sg:address":"16 Creek St",
    "sg:city":"Walkerston",
    "sg:classifiers":[
        {
            "category":"Farming",
            "subcategory":"Farm",
            "type":"Manufacturing & Wholesale Goods"
        }
    ],
    "sg:phone":"+61 7 4959 2386",
    "sg:postcode":"4751",
    "sg:province":"QLD",
    "sg:tags":[
        "farmer"
    ],
    "wof:name":"Goltz G F & G M",
    "wof:placetype":"venue"
},
  "geometry": {"coordinates":[149.06578099999999,-21.161066],"type":"Point"}
}