{
  "type": "Feature",
  "properties": {
    "addr:full":"Metro On Beckett Cnr Beckett Rd & Saturn Crs Bridgeman Downs QLD 4035",
    "addr:postcode":"4035",
    "addr:street":"Cnr Beckett Rd & Saturn Crs",
    "iso:country":"AU",
    "sg:address":"Metro On Beckett Cnr Beckett Rd & Saturn Crs",
    "sg:city":"Bridgeman Downs",
    "sg:classifiers":[
        {
            "category":"Real Estate",
            "subcategory":"Real Estate Agent",
            "type":"Services"
        }
    ],
    "sg:phone":"+61 7 3353 7600",
    "sg:postcode":"4035",
    "sg:province":"QLD",
    "wof:name":"Ray White Bridgeman Downs",
    "wof:placetype":"venue"
},
  "geometry": {"coordinates":[152.99160800000001,-27.364845],"type":"Point"}
}