{
  "type": "Feature",
  "properties": {
    "addr:full":"1/ 208 Canterbury Rd Canterbury VIC 3126",
    "addr:housenumber":"/ 208",
    "addr:postcode":"3126",
    "addr:street":"Canterbury Rd",
    "iso:country":"AU",
    "sg:address":"1/ 208 Canterbury Rd",
    "sg:city":"Canterbury",
    "sg:classifiers":[
        {
            "category":"Organizations",
            "subcategory":"Community Association",
            "type":"Services"
        }
    ],
    "sg:phone":"+61 3 9880 7005",
    "sg:postcode":"3126",
    "sg:province":"VIC",
    "sg:tags":[
        "shiatsu",
        "therapy"
    ],
    "wof:name":"Canterbury Stress Management Centre",
    "wof:placetype":"venue"
},
  "geometry": {"coordinates":[145.083084106,-37.8243598938],"type":"Point"}
}