{
  "type": "Feature",
  "properties": {
    "addr:full":"65 Sydney St Kilmore VIC 3764",
    "addr:housenumber":"65",
    "addr:postcode":"3764",
    "addr:street":"Sydney St",
    "iso:country":"AU",
    "sg:address":"65 Sydney St",
    "sg:city":"Kilmore",
    "sg:classifiers":[
        {
            "category":"Fast Food",
            "type":"Food & Drink"
        }
    ],
    "sg:phone":"+61 3 5781 0178",
    "sg:postcode":"3764",
    "sg:province":"VIC",
    "sg:tags":[
        "away",
        "take"
    ],
    "wof:name":"Kemp's Bakery",
    "wof:placetype":"venue"
},
  "geometry": {"coordinates":[144.95065307600001,-37.2911682129],"type":"Point"}
}