{
  "type": "Feature",
  "properties": {
    "iso:country":"AU",
    "sg:address":"U1/ 10 Malland St",
    "sg:city":"Myaree",
    "sg:classifiers":[
        {
            "category":"Retail",
            "subcategory":"Auto Repair",
            "type":"Services"
        }
    ],
    "sg:phone":"+61 8 9317 3025",
    "sg:postcode":"6154",
    "sg:province":"WA",
    "sg:tags":[
        "repairer",
        "motor",
        "engineer"
    ],
    "wof:name":"ANG Automotive",
    "wof:placetype":"venue"
},
  "geometry": {"coordinates":[115.822151,-32.04071],"type":"Point"}
}