{
  "type": "Feature",
  "properties": {
    "addr:full":"53 Victoria St Melbourne VIC 3000",
    "addr:housenumber":"53",
    "addr:postcode":"3000",
    "addr:street":"Victoria St",
    "iso:country":"AU",
    "sg:address":"53 Victoria St",
    "sg:city":"Melbourne",
    "sg:classifiers":[
        {
            "category":"Education",
            "subcategory":"Music School",
            "type":"Public Place"
        }
    ],
    "sg:phone":"+61 3 9662 2959",
    "sg:postcode":"3000",
    "sg:province":"VIC",
    "sg:tags":[
        "teacher"
    ],
    "wof:name":"Melbourne Music Academy",
    "wof:placetype":"venue"
},
  "geometry": {"coordinates":[144.96206665,-37.8066864014],"type":"Point"}
}