{
  "type": "Feature",
  "properties": {
    "addr:full":"74 Maryborough St Walkervale QLD 4670",
    "addr:housenumber":"74",
    "addr:postcode":"4670",
    "addr:street":"Maryborough St",
    "iso:country":"AU",
    "sg:address":"74 Maryborough St",
    "sg:city":"Walkervale",
    "sg:classifiers":[
        {
            "category":"Insurance",
            "subcategory":"Insurance Agent",
            "type":"Services"
        }
    ],
    "sg:phone":"+61 7 4152 2096",
    "sg:postcode":"4670",
    "sg:province":"QLD",
    "wof:name":"Ben Amos",
    "wof:placetype":"venue"
},
  "geometry": {"coordinates":[152.35179138199999,-24.881778717],"type":"Point"}
}