{
  "type": "Feature",
  "properties": {
    "addr:full":"281 Barrenjoey Rd Newport NSW 2106",
    "addr:housenumber":"281",
    "addr:postcode":"2106",
    "addr:street":"Barrenjoey Rd",
    "iso:country":"AU",
    "sg:address":"281 Barrenjoey Rd",
    "sg:city":"Newport",
    "sg:classifiers":[
        {
            "category":"Health Services",
            "subcategory":"Chiropractor",
            "type":"Services"
        }
    ],
    "sg:phone":"+61 2 9997 1033",
    "sg:postcode":"2106",
    "sg:province":"NSW",
    "wof:name":"Newport Chiropractic",
    "wof:placetype":"venue"
},
  "geometry": {"coordinates":[151.31703185999999,-33.6589813232],"type":"Point"}
}