{
  "type": "Feature",
  "properties": {
    "iso:country":"AU",
    "sg:address":"14-16 45 Sinclair St",
    "sg:city":"Ocean Grove",
    "sg:classifiers":[
        {
            "category":"Retail",
            "subcategory":"Storage",
            "type":"Services"
        }
    ],
    "sg:phone":"+61 3 5256 2992",
    "sg:postcode":"3226",
    "sg:province":"VIC",
    "sg:tags":[
        "removal",
        "furniture"
    ],
    "wof:name":"Bellarine Self Storage",
    "wof:placetype":"venue"
},
  "geometry": {"coordinates":[144.539337,-38.250698],"type":"Point"}
}