{
  "type": "Feature",
  "properties": {
    "addr:full":"30 Old Wolvi Rd Gympie QLD 4570",
    "addr:housenumber":"30",
    "addr:postcode":"4570",
    "addr:street":"Old Wolvi Rd",
    "iso:country":"AU",
    "sg:address":"30 Old Wolvi Rd",
    "sg:city":"Gympie",
    "sg:classifiers":[
        {
            "category":"Manufacturing",
            "subcategory":"Lumber",
            "type":"Manufacturing & Wholesale Goods"
        }
    ],
    "sg:phone":"+61 7 5482 2943",
    "sg:postcode":"4570",
    "sg:province":"QLD",
    "sg:tags":[
        "sawmillers"
    ],
    "wof:name":"Robertson Bros Sawmills Pty Ltd",
    "wof:placetype":"venue"
},
  "geometry": {"coordinates":[152.685058594,-26.171962738],"type":"Point"}
}