{
  "type": "Feature",
  "properties": {
    "addr:full":"Baringa Orthopaedic Centre 31 Mackays Rd Coffs Harbour NSW 2450",
    "addr:housenumber":"31",
    "addr:postcode":"2450",
    "addr:street":"Mackays Rd",
    "iso:country":"AU",
    "sg:address":"Baringa Orthopaedic Centre 31 Mackays Rd",
    "sg:city":"Coffs Harbour",
    "sg:classifiers":[
        {
            "category":"Health Services",
            "subcategory":"Doctor",
            "type":"Services"
        }
    ],
    "sg:phone":"+61 2 6652 4977",
    "sg:postcode":"2450",
    "sg:province":"NSW",
    "sg:tags":[
        "medical",
        "practitioner"
    ],
    "wof:name":"Marshall Darrin",
    "wof:placetype":"venue"
},
  "geometry": {"coordinates":[153.10337799999999,-30.274244],"type":"Point"}
}