{
  "type": "Feature",
  "properties": {
    "addr:full":"10/ 1751 Pittwater Rd Mona Vale NSW 2103",
    "addr:housenumber":"10 / 1751",
    "addr:postcode":"2103",
    "addr:street":"Pittwater Rd",
    "iso:country":"AU",
    "sg:address":"10/ 1751 Pittwater Rd",
    "sg:city":"Mona Vale",
    "sg:classifiers":[
        {
            "category":"Shopping",
            "subcategory":"Music",
            "type":"Retail Goods"
        }
    ],
    "sg:phone":"+61 2 9999 0748",
    "sg:postcode":"2103",
    "sg:province":"NSW",
    "sg:tags":[
        "instrument",
        "musical"
    ],
    "wof:name":"The Music Lounge",
    "wof:placetype":"venue"
},
  "geometry": {"coordinates":[151.30325317399999,-33.6782684326],"type":"Point"}
}