{
  "type": "Feature",
  "properties": {
    "addr:full":"18 Rodney Rd Geelong North VIC 3215",
    "addr:housenumber":"18",
    "addr:postcode":"3215",
    "addr:street":"Rodney Rd",
    "iso:country":"AU",
    "sg:address":"18 Rodney Rd",
    "sg:city":"Geelong North",
    "sg:classifiers":[
        {
            "category":"Commercial Area",
            "type":"Public Place"
        }
    ],
    "sg:phone":"+61 3 5272 2655",
    "sg:postcode":"3215",
    "sg:province":"VIC",
    "sg:tags":[
        "heavy",
        "carrier"
    ],
    "wof:name":"Corio Towing",
    "wof:placetype":"venue"
},
  "geometry": {"coordinates":[144.351287842,-38.11536026],"type":"Point"}
}