{
  "type": "Feature",
  "properties": {
    "iso:country":"AU",
    "sg:address":"49- 51 Wing St",
    "sg:city":"Wingfield",
    "sg:classifiers":[
        {
            "category":"Wholesale",
            "subcategory":"Metals & Minerals",
            "type":"Manufacturing & Wholesale Goods"
        }
    ],
    "sg:phone":"+61 8 8272 0199",
    "sg:postcode":"5013",
    "sg:province":"SA",
    "sg:tags":[
        "steel",
        "stainless",
        "product",
        "equipment"
    ],
    "wof:name":"Adlingtons Australia",
    "wof:placetype":"venue"
},
  "geometry": {"coordinates":[138.56402587900001,-34.8366508484],"type":"Point"}
}