{
  "type": "Feature",
  "properties": {
    "iso:country":"AU",
    "sg:address":"1 Cleve Crt",
    "sg:city":"Howrah",
    "sg:classifiers":[
        {
            "category":"Home & Garden",
            "subcategory":"Building Materials",
            "type":"Retail Goods"
        }
    ],
    "sg:phone":"+61 3 6247 8734",
    "sg:postcode":"7018",
    "sg:province":"TAS",
    "sg:tags":[
        "concrete",
        "gutter",
        "kerb"
    ],
    "wof:name":"Peter & Jenny Lawrence",
    "wof:placetype":"venue"
},
  "geometry": {"coordinates":[147.40951538100001,-42.8921394348],"type":"Point"}
}