{
  "type": "Feature",
  "properties": {
    "iso:country":"AU",
    "sg:address":"9 Yennora Ave",
    "sg:city":"Yennora",
    "sg:classifiers":[
        {
            "category":"Manufacturing",
            "subcategory":"Motor Vehicles & Parts",
            "type":"Manufacturing & Wholesale Goods"
        }
    ],
    "sg:phone":"+61 2 9892 1686",
    "sg:postcode":"2161",
    "sg:province":"NSW",
    "sg:tags":[
        "replacement"
    ],
    "wof:name":"Chevparts",
    "wof:placetype":"venue"
},
  "geometry": {"coordinates":[150.971435547,-33.8615875244],"type":"Point"}
}