{
  "type": "Feature",
  "properties": {
    "addr:full":"404 Main Rd West St Albans VIC 3021",
    "addr:housenumber":"404",
    "addr:postcode":"3021",
    "addr:street":"Main Rd",
    "iso:country":"AU",
    "sg:address":"404 Main Rd West St",
    "sg:city":"Albans",
    "sg:classifiers":[
        {
            "category":"Health Services",
            "subcategory":"Chiropractor",
            "type":"Services"
        }
    ],
    "sg:phone":"+61 3 9364 4444",
    "sg:postcode":"3021",
    "sg:province":"VIC",
    "wof:name":"Drinkwater John S",
    "wof:placetype":"venue"
},
  "geometry": {"coordinates":[144.76396199999999,-37.740376],"type":"Point"}
}