{
  "type": "Feature",
  "properties": {
    "addr:full":"PO Box 3278 Malaga DC WA 6945",
    "addr:postcode":"6945",
    "iso:country":"AU",
    "sg:address":"PO Box 3278",
    "sg:city":"Malaga DC",
    "sg:classifiers":[
        {
            "category":"Education",
            "subcategory":"Music School",
            "type":"Public Place"
        }
    ],
    "sg:phone":"+61 8 9451 5415",
    "sg:postcode":"6945",
    "sg:province":"WA",
    "sg:tags":[
        "choir",
        "bands",
        "orchestra"
    ],
    "wof:name":"Daren Reid & The Soul City Groove",
    "wof:placetype":"venue"
},
  "geometry": {"coordinates":[115.914466858,-31.8515300751],"type":"Point"}
}