{
  "type": "Feature",
  "properties": {
    "iso:country":"AU",
    "sg:address":"346 Oxford St",
    "sg:city":"Paddington",
    "sg:classifiers":[
        {
            "category":"Shopping",
            "subcategory":"Clothing, Apparel, & Fashions",
            "type":"Retail Goods"
        }
    ],
    "sg:phone":"+61 2 9360 3414",
    "sg:postcode":"2021",
    "sg:province":"NSW",
    "sg:tags":[
        "jean"
    ],
    "wof:name":"General Pants Co Pty Ltd",
    "wof:placetype":"venue"
},
  "geometry": {"coordinates":[151.22932434099999,-33.8862113953],"type":"Point"}
}