{
  "type": "Feature",
  "properties": {
    "addr:full":"Unit 1, 42 Essington St Mitchell ACT 2911",
    "addr:housenumber":"42",
    "addr:postcode":"2911",
    "addr:street":"Essington St",
    "iso:country":"AU",
    "sg:address":"Unit 1, 42 Essington St",
    "sg:city":"Mitchell",
    "sg:classifiers":[
        {
            "category":"Building & Trades",
            "subcategory":"Construction",
            "type":"Services"
        }
    ],
    "sg:phone":"+61 2 6242 4100",
    "sg:postcode":"2911",
    "sg:province":"ACT",
    "sg:tags":[
        "joinery"
    ],
    "wof:name":"Clockwork Kitchens",
    "wof:placetype":"venue"
},
  "geometry": {"coordinates":[149.14210510300001,-35.2105751038],"type":"Point"}
}