{
  "type": "Feature",
  "properties": {
    "addr:full":"25 Henry St Nanango QLD 4615",
    "addr:housenumber":"25",
    "addr:postcode":"4615",
    "addr:street":"Henry St",
    "iso:country":"AU",
    "sg:address":"25 Henry St",
    "sg:city":"Nanango",
    "sg:classifiers":[
        {
            "category":"Autos & Motor Vehicles",
            "subcategory":"Automobile Sales",
            "type":"Retail Goods"
        }
    ],
    "sg:phone":"+61 7 4163 1304",
    "sg:postcode":"4615",
    "sg:province":"QLD",
    "sg:tags":[
        "car",
        "used"
    ],
    "wof:name":"Alexander's Garage",
    "wof:placetype":"venue"
},
  "geometry": {"coordinates":[152.00108337399999,-26.6724739075],"type":"Point"}
}