{
  "type": "Feature",
  "properties": {
    "addr:full":"199 Milleara Rd Keilor East VIC 3033",
    "addr:housenumber":"199",
    "addr:postcode":"3033",
    "addr:street":"Milleara Rd",
    "iso:country":"AU",
    "sg:address":"199 Milleara Rd",
    "sg:city":"Keilor East",
    "sg:classifiers":[
        {
            "category":"Real Estate",
            "subcategory":"Architect",
            "type":"Services"
        }
    ],
    "sg:phone":"+61 3 9337 0910",
    "sg:postcode":"3033",
    "sg:province":"VIC",
    "sg:tags":[
        "building",
        "designer"
    ],
    "wof:name":"Magdalani J & E",
    "wof:placetype":"venue"
},
  "geometry": {"coordinates":[144.86265599999999,-37.745888],"type":"Point"}
}