{
  "type": "Feature",
  "properties": {
    "addr:full":"1/ 62 Brunel Rd Seaford VIC 3198",
    "addr:housenumber":"/ 62",
    "addr:postcode":"3198",
    "addr:street":"Brunel Rd",
    "iso:country":"AU",
    "sg:address":"1/ 62 Brunel Rd",
    "sg:city":"Seaford",
    "sg:classifiers":[
        {
            "category":"Shopping",
            "subcategory":"Bicycles & Sporting Goods",
            "type":"Retail Goods"
        }
    ],
    "sg:phone":"+61 3 9782 5575",
    "sg:postcode":"3198",
    "sg:province":"VIC",
    "sg:tags":[
        "dance",
        "accessory",
        "wear",
        "supply"
    ],
    "wof:name":"Krystals Sequins & Beads",
    "wof:placetype":"venue"
},
  "geometry": {"coordinates":[145.14930725100001,-38.1009521484],"type":"Point"}
}