{
  "type": "Feature",
  "properties": {
    "iso:country":"AU",
    "sg:address":"663- 665 Ruthven St",
    "sg:city":"Toowoomba",
    "sg:classifiers":[
        {
            "category":"Home & Garden",
            "subcategory":"Furniture",
            "type":"Retail Goods"
        }
    ],
    "sg:phone":"+61 7 4638 4211",
    "sg:postcode":"4350",
    "sg:province":"QLD",
    "sg:tags":[
        "outdoor"
    ],
    "wof:name":"Barbeques Galore",
    "wof:placetype":"venue"
},
  "geometry": {"coordinates":[151.951431,-27.571609],"type":"Point"}
}