{
  "type": "Feature",
  "properties": {
    "addr:full":"663- 665 Ruthven St Toowoomba QLD 4350",
    "addr:housenumber":"665",
    "addr:postcode":"4350",
    "addr:street":"Ruthven St",
    "iso:country":"AU",
    "sg:address":"663- 665 Ruthven St",
    "sg:city":"Toowoomba",
    "sg:classifiers":[
        {
            "category":"Home & Garden",
            "subcategory":"Furniture",
            "type":"Retail Goods"
        }
    ],
    "sg:phone":"+61 7 4638 4211",
    "sg:postcode":"4350",
    "sg:province":"QLD",
    "sg:tags":[
        "outdoor"
    ],
    "wof:name":"Barbeques Galore",
    "wof:placetype":"venue"
},
  "geometry": {"coordinates":[151.95143100000001,-27.571609],"type":"Point"}
}