{
  "type": "Feature",
  "properties": {
    "addr:full":"47- 49 Wallsend Rd Sandgate NSW 2304",
    "addr:housenumber":"49",
    "addr:postcode":"2304",
    "addr:street":"Wallsend Rd",
    "iso:country":"AU",
    "sg:address":"47- 49 Wallsend Rd",
    "sg:city":"Sandgate",
    "sg:classifiers":[
        {
            "category":"Building & Trades",
            "subcategory":"Construction",
            "type":"Services"
        }
    ],
    "sg:phone":"+61 2 4968 3600",
    "sg:postcode":"2304",
    "sg:province":"NSW",
    "sg:tags":[
        "monumental",
        "mason"
    ],
    "wof:name":"Edstein Creative Stone",
    "wof:placetype":"venue"
},
  "geometry": {"coordinates":[151.705566406,-32.8723144531],"type":"Point"}
}