{
  "type": "Feature",
  "properties": {
    "addr:full":"88 Ring St Inverell NSW 2360",
    "addr:housenumber":"88",
    "addr:postcode":"2360",
    "addr:street":"Ring St",
    "iso:country":"AU",
    "sg:address":"88 Ring St",
    "sg:city":"Inverell",
    "sg:classifiers":[
        {
            "category":"Retail",
            "subcategory":"Repair Shop",
            "type":"Services"
        }
    ],
    "sg:phone":"+61 2 6722 2118",
    "sg:postcode":"2360",
    "sg:province":"NSW",
    "sg:tags":[
        "machine",
        "sewing"
    ],
    "wof:name":"Carol's Fabric & Sewing Centre",
    "wof:placetype":"venue"
},
  "geometry": {"coordinates":[151.10737609899999,-29.7638206482],"type":"Point"}
}