{
  "type": "Feature",
  "properties": {
    "addr:full":"Unit 5, 9 Pearson Way Osborne Park WA 6017",
    "addr:housenumber":"9",
    "addr:postcode":"6017",
    "addr:street":"Pearson Way",
    "iso:country":"AU",
    "sg:address":"Unit 5, 9",
    "sg:city":"Pearson Way Osborne Park",
    "sg:classifiers":[
        {
            "category":"Home & Garden",
            "subcategory":"Hardware",
            "type":"Retail Goods"
        }
    ],
    "sg:phone":"+61 8 9344 7255",
    "sg:postcode":"6017",
    "sg:province":"WA",
    "sg:tags":[
        "part",
        "air conditioning"
    ],
    "wof:name":"Active Refrigeration & Airconditioning",
    "wof:placetype":"venue"
},
  "geometry": {"coordinates":[115.802009583,-31.9081878662],"type":"Point"}
}