{
  "type": "Feature",
  "properties": {
    "iso:country":"AU",
    "sg:address":"Shop 11, The Pavillion Green St",
    "sg:city":"Ulladulla",
    "sg:classifiers":[
        {
            "category":"Personal",
            "subcategory":"Massage",
            "type":"Services"
        }
    ],
    "sg:phone":"+61 412 034 038",
    "sg:postcode":"2539",
    "sg:province":"NSW",
    "sg:tags":[
        "therapy"
    ],
    "wof:name":"Lynette Templeman",
    "wof:placetype":"venue"
},
  "geometry": {"coordinates":[150.47366332999999,-35.3569717407],"type":"Point"}
}