{
  "type": "Feature",
  "properties": {
    "addr:full":"Glen Stuart Rd Woodforde SA 5072",
    "addr:postcode":"5072",
    "addr:street":"Stuart Rd",
    "iso:country":"AU",
    "sg:address":"Glen Stuart Rd",
    "sg:city":"Woodforde",
    "sg:classifiers":[
        {
            "category":"Education",
            "subcategory":"School",
            "type":"Public Place"
        }
    ],
    "sg:phone":"+61 8 8364 8200",
    "sg:postcode":"5072",
    "sg:province":"SA",
    "sg:tags":[
        "boy"
    ],
    "wof:name":"Rostrevor College",
    "wof:placetype":"venue"
},
  "geometry": {"coordinates":[138.68426513700001,-34.9014167786],"type":"Point"}
}