{
  "type": "Feature",
  "properties": {
    "addr:full":"242 Zillmere Rd Zillmere QLD 4034",
    "addr:housenumber":"242",
    "addr:postcode":"4034",
    "addr:street":"Zillmere Rd",
    "iso:country":"AU",
    "sg:address":"242 Zillmere Rd",
    "sg:city":"Zillmere",
    "sg:classifiers":[
        {
            "category":"Retail",
            "subcategory":"Auto Repair",
            "type":"Services"
        }
    ],
    "sg:phone":"+61 7 3865 3218",
    "sg:postcode":"4034",
    "sg:province":"QLD",
    "sg:tags":[
        "repairer",
        "motor",
        "engineer"
    ],
    "wof:name":"Plus Four Brake & Clutch Service",
    "wof:placetype":"venue"
},
  "geometry": {"coordinates":[153.048889,-27.361118],"type":"Point"}
}