{
  "type": "Feature",
  "properties": {
    "iso:country":"AU",
    "sg:address":"464 Marrickville Rd",
    "sg:city":"Dulwich Hill",
    "sg:classifiers":[
        {
            "category":"Personal",
            "subcategory":"Beauty Salon",
            "type":"Services"
        }
    ],
    "sg:phone":"+61 2 9569 2417",
    "sg:postcode":"2203",
    "sg:province":"NSW",
    "sg:tags":[
        "hairdresser"
    ],
    "wof:name":"Sias Ladies' Hairdresser",
    "wof:placetype":"venue"
},
  "geometry": {"coordinates":[151.143585,-33.904259],"type":"Point"}
}