{
  "type": "Feature",
  "properties": {
    "iso:country":"AU",
    "sg:address":"2/15- 17 Blackburn Rd",
    "sg:city":"Maddington",
    "sg:classifiers":[
        {
            "category":"Personal",
            "type":"Services"
        }
    ],
    "sg:phone":"+61 8 9452 1033",
    "sg:postcode":"6109",
    "sg:province":"WA",
    "sg:tags":[
        "career",
        "counselling"
    ],
    "wof:name":"Mission Employment",
    "wof:placetype":"venue"
},
  "geometry": {"coordinates":[115.979820252,-32.0518608093],"type":"Point"}
}