{
  "type": "Feature",
  "properties": {
    "iso:country":"AU",
    "sg:address":"47 A Nathan Drv",
    "sg:city":"Campbellfield",
    "sg:classifiers":[
        {
            "category":"Wholesale",
            "subcategory":"Construction Materials",
            "type":"Manufacturing & Wholesale Goods"
        }
    ],
    "sg:phone":"+61 3 9303 7903",
    "sg:postcode":"3061",
    "sg:province":"VIC",
    "sg:tags":[
        "wholesaler",
        "lighting",
        "mfrs",
        "accessory"
    ],
    "wof:name":"Napier Lighting Co Pty Ltd",
    "wof:placetype":"venue"
},
  "geometry": {"coordinates":[144.94154357900001,-37.6500091553],"type":"Point"}
}