{
  "type": "Feature",
  "properties": {
    "iso:country":"AU",
    "sg:address":"85 High St",
    "sg:city":"Melton",
    "sg:classifiers":[
        {
            "category":"Retail",
            "subcategory":"Auto Repair",
            "type":"Services"
        }
    ],
    "sg:phone":"+61 3 9747 8464",
    "sg:postcode":"3337",
    "sg:province":"VIC",
    "sg:tags":[
        "repairer",
        "motor",
        "engineer"
    ],
    "wof:name":"Universal Automotive",
    "wof:placetype":"venue"
},
  "geometry": {"coordinates":[144.60403400000001,-37.691086],"type":"Point"}
}