{
  "type": "Feature",
  "properties": {
    "iso:country":"AU",
    "sg:address":"8 Brigalow Crt",
    "sg:city":"Murrumba Downs",
    "sg:classifiers":[
        {
            "category":"Utilities",
            "subcategory":"Electric",
            "type":"Services"
        }
    ],
    "sg:phone":"+61 418 788 748",
    "sg:postcode":"4503",
    "sg:province":"QLD",
    "sg:tags":[
        "electrical",
        "contractor"
    ],
    "wof:name":"Intelect Pty Ltd",
    "wof:placetype":"venue"
},
  "geometry": {"coordinates":[153.000442505,-27.259141922],"type":"Point"}
}