{
  "type": "Feature",
  "properties": {
    "addr:full":"Royal North Shore Level 4, Pacific Hwy St Leonards NSW 2065",
    "addr:postcode":"2065",
    "addr:street":"Pacific Hwy",
    "iso:country":"AU",
    "sg:address":"Royal North Shore Level 4, Pacific Hwy",
    "sg:city":"St Leonards",
    "sg:classifiers":[
        {
            "category":"Health Services",
            "subcategory":"Medical Lab",
            "type":"Services"
        }
    ],
    "sg:phone":"+61 2 9926 6066",
    "sg:postcode":"2065",
    "sg:province":"NSW",
    "sg:tags":[
        "laboratory",
        "pathology"
    ],
    "wof:name":"PaLMS# Pathology",
    "wof:placetype":"venue"
},
  "geometry": {"coordinates":[151.19776916500001,-33.8244247437],"type":"Point"}
}