{
  "type": "Feature",
  "properties": {
    "addr:full":"35 Ormond St Paddington NSW 2021",
    "addr:housenumber":"35",
    "addr:postcode":"2021",
    "addr:street":"Ormond St",
    "iso:country":"AU",
    "sg:address":"35 Ormond St",
    "sg:city":"Paddington",
    "sg:classifiers":[
        {
            "category":"Travel",
            "subcategory":"Travel Agent",
            "type":"Entertainment"
        }
    ],
    "sg:phone":"+61 2 9460 8888",
    "sg:postcode":"2021",
    "sg:province":"NSW",
    "sg:tags":[
        "consultant"
    ],
    "wof:name":"Explore Ireland",
    "wof:placetype":"venue"
},
  "geometry": {"coordinates":[151.22694397000001,-33.8836975098],"type":"Point"}
}