{
  "type": "Feature",
  "properties": {
    "addr:full":"PO Box 151 Hay NSW 2711",
    "addr:postcode":"2711",
    "iso:country":"AU",
    "sg:address":"PO Box 151",
    "sg:city":"Hay",
    "sg:classifiers":[
        {
            "category":"Farming",
            "subcategory":"Farm & Veterinary Services",
            "type":"Manufacturing & Wholesale Goods"
        }
    ],
    "sg:phone":"+61 2 6993 3160",
    "sg:postcode":"2711",
    "sg:province":"NSW",
    "sg:tags":[
        "irrigation",
        "reticulation",
        "system"
    ],
    "wof:name":"Riverina Poly Irrigation",
    "wof:placetype":"venue"
},
  "geometry": {"coordinates":[144.843948364,-34.5069885254],"type":"Point"}
}