{
  "type": "Feature",
  "properties": {
    "addr:full":"1683 Tamborine-Oxenford Rd Eagle Heights QLD 4271",
    "addr:housenumber":"1683",
    "addr:postcode":"4271",
    "addr:street":"Tamborine-Oxenford Rd",
    "iso:country":"AU",
    "sg:address":"1683 Tamborine-Oxenford Rd",
    "sg:city":"Eagle Heights",
    "sg:classifiers":[
        {
            "category":"Travel",
            "subcategory":"Hotels & Motels",
            "type":"Entertainment"
        }
    ],
    "sg:phone":"+61 7 5545 3103",
    "sg:postcode":"4271",
    "sg:province":"QLD",
    "sg:tags":[
        "accommodation"
    ],
    "wof:name":"Eagle Heights Mountain Resort",
    "wof:placetype":"venue"
},
  "geometry": {"coordinates":[153.20550537099999,-27.8990516663],"type":"Point"}
}