{
  "type": "Feature",
  "properties": {
    "iso:country":"AU",
    "sg:address":"145 Boundary Rd",
    "sg:city":"North Melbourne",
    "sg:classifiers":[
        {
            "category":"Shopping",
            "subcategory":"Clothing, Apparel, & Fashions",
            "type":"Retail Goods"
        }
    ],
    "sg:phone":"+61 3 9329 4955",
    "sg:postcode":"3051",
    "sg:province":"VIC",
    "sg:tags":[
        "lady",
        "wear"
    ],
    "wof:name":"Krishna International",
    "wof:placetype":"venue"
},
  "geometry": {"coordinates":[144.93960571299999,-37.7905349731],"type":"Point"}
}