{
  "type": "Feature",
  "properties": {
    "addr:full":"23 Roberts Rd Greenbank QLD 4124",
    "addr:housenumber":"23",
    "addr:postcode":"4124",
    "addr:street":"Roberts Rd",
    "iso:country":"AU",
    "sg:address":"23 Roberts Rd",
    "sg:city":"Greenbank",
    "sg:classifiers":[
        {
            "category":"Home & Garden",
            "subcategory":"Garden Supply",
            "type":"Retail Goods"
        }
    ],
    "sg:phone":"+61 7 3200 0563",
    "sg:postcode":"4124",
    "sg:province":"QLD",
    "sg:tags":[
        "turf",
        "lawn"
    ],
    "wof:name":"Bell's Turf",
    "wof:placetype":"venue"
},
  "geometry": {"coordinates":[152.94778442399999,-27.727848053],"type":"Point"}
}