{
  "type": "Feature",
  "properties": {
    "addr:full":"412 Thompson Rd North Geelong VIC 3215",
    "addr:housenumber":"412",
    "addr:postcode":"3215",
    "addr:street":"Thompson Rd",
    "iso:country":"AU",
    "sg:address":"412 Thompson Rd",
    "sg:city":"North Geelong",
    "sg:classifiers":[
        {
            "category":"Autos & Motor Vehicles",
            "subcategory":"Auto Supplies",
            "type":"Retail Goods"
        }
    ],
    "sg:phone":"+61 3 5277 9009",
    "sg:postcode":"3215",
    "sg:province":"VIC",
    "sg:tags":[
        "battery",
        "automotive"
    ],
    "wof:name":"Bay City Batteries",
    "wof:placetype":"venue"
},
  "geometry": {"coordinates":[144.34611511200001,-38.0975189209],"type":"Point"}
}