{
  "type": "Feature",
  "properties": {
    "addr:full":"Level 5 Central Plaza One 345 Queen St Brisbane QLD 4000",
    "addr:housenumber":"345",
    "addr:postcode":"4000",
    "addr:street":"Queen St",
    "iso:country":"AU",
    "sg:address":"Level 5 Central Plaza One 345 Queen St",
    "sg:city":"Brisbane",
    "sg:classifiers":[
        {
            "category":"Organizations",
            "subcategory":"Community Association",
            "type":"Services"
        }
    ],
    "sg:phone":"+61 7 3229 8627",
    "sg:postcode":"4000",
    "sg:province":"QLD",
    "sg:tags":[
        "registered",
        "trustee",
        "bankruptcy"
    ],
    "wof:name":"Knights Insolvency Administration",
    "wof:placetype":"venue"
},
  "geometry": {"coordinates":[153.02925109899999,-27.4667034149],"type":"Point"}
}