{
  "type": "Feature",
  "properties": {
    "addr:full":"Rear 27 Lyttleton St Castlemaine VIC 3450",
    "addr:housenumber":"27",
    "addr:postcode":"3450",
    "addr:street":"Lyttleton St",
    "iso:country":"AU",
    "sg:address":"Rear 27 Lyttleton St",
    "sg:city":"Castlemaine",
    "sg:classifiers":[
        {
            "category":"Train Station",
            "subcategory":"Light Rail",
            "type":"Transportation"
        }
    ],
    "sg:phone":"+61 3 5470 5890",
    "sg:postcode":"3450",
    "sg:province":"VIC",
    "sg:tags":[
        "equipment",
        "energy",
        "solar"
    ],
    "wof:name":"Solar Bloke The",
    "wof:placetype":"venue"
},
  "geometry": {"coordinates":[144.21879577600001,-37.064453125],"type":"Point"}
}