{
  "type": "Feature",
  "properties": {
    "iso:country":"AU",
    "sg:address":"May St",
    "sg:city":"Parkes",
    "sg:classifiers":[
        {
            "category":"Travel",
            "subcategory":"Hotels & Motels",
            "type":"Entertainment"
        }
    ],
    "sg:phone":"+61 2 6862 1553",
    "sg:postcode":"2870",
    "sg:province":"NSW",
    "sg:tags":[
        "accommodation"
    ],
    "wof:name":"Bushmans Tavern The",
    "wof:placetype":"venue"
},
  "geometry": {"coordinates":[148.173401,-33.141605],"type":"Point"}
}