{
  "type": "Feature",
  "properties": {
    "addr:full":"6 Reeve St Mt Martha VIC 3934",
    "addr:housenumber":"6",
    "addr:postcode":"3934",
    "addr:street":"Reeve St Mt Martha",
    "iso:country":"AU",
    "sg:address":"6 Reeve St",
    "sg:city":"Mt Martha",
    "sg:classifiers":[
        {
            "category":"Health Services",
            "subcategory":"Health Practitioner",
            "type":"Services"
        }
    ],
    "sg:phone":"+61 3 5974 2053",
    "sg:postcode":"3934",
    "sg:province":"VIC",
    "sg:tags":[
        "osteopath"
    ],
    "wof:name":"Mt Martha Osteopathy",
    "wof:placetype":"venue"
},
  "geometry": {"coordinates":[145.01846313499999,-38.2683486938],"type":"Point"}
}