{
  "type": "Feature",
  "properties": {
    "iso:country":"AU",
    "sg:address":"31 Pendlebury Rd",
    "sg:city":"Cardiff",
    "sg:classifiers":[
        {
            "category":"Wholesale",
            "subcategory":"Auto Parts",
            "type":"Manufacturing & Wholesale Goods"
        }
    ],
    "sg:phone":"+61 2 4956 5582",
    "sg:postcode":"2285",
    "sg:province":"NSW",
    "sg:tags":[
        "recyclers"
    ],
    "wof:name":"Commodore Shop Cardiff",
    "wof:placetype":"venue"
},
  "geometry": {"coordinates":[151.65397644000001,-32.9461784363],"type":"Point"}
}