{
  "type": "Feature",
  "properties": {
    "addr:full":"527 Glenferrie Rd Hawthorn VIC 3122",
    "addr:housenumber":"527",
    "addr:postcode":"3122",
    "addr:street":"Glenferrie Rd",
    "iso:country":"AU",
    "sg:address":"527 Glenferrie Rd",
    "sg:city":"Hawthorn",
    "sg:classifiers":[
        {
            "category":"Health Services",
            "subcategory":"Health Practitioner",
            "type":"Services"
        }
    ],
    "sg:phone":"+61 3 9818 8244",
    "sg:postcode":"3122",
    "sg:province":"VIC",
    "sg:tags":[
        "psychologist"
    ],
    "wof:name":"Elliott Raymond",
    "wof:placetype":"venue"
},
  "geometry": {"coordinates":[145.03382873499999,-37.8298492432],"type":"Point"}
}