{
  "type": "Feature",
  "properties": {
    "addr:full":"342 High St Echuca VIC 3564",
    "addr:housenumber":"342",
    "addr:postcode":"3564",
    "addr:street":"High St",
    "iso:country":"AU",
    "sg:address":"342 High St",
    "sg:city":"Echuca",
    "sg:classifiers":[
        {
            "category":"Health Services",
            "subcategory":"Health Practitioner",
            "type":"Services"
        }
    ],
    "sg:phone":"+61 3 5480 1655",
    "sg:postcode":"3564",
    "sg:province":"VIC",
    "sg:tags":[
        "physiotherapist"
    ],
    "wof:name":"Rich River Physiotherapy & Acupuncture Clinic",
    "wof:placetype":"venue"
},
  "geometry": {"coordinates":[144.75296020499999,-36.147895813],"type":"Point"}
}