{
  "type": "Feature",
  "properties": {
    "addr:full":"18 Julie St Beenleigh QLD 4207",
    "addr:housenumber":"18",
    "addr:postcode":"4207",
    "addr:street":"Julie St",
    "iso:country":"AU",
    "sg:address":"18 Julie St",
    "sg:city":"Beenleigh",
    "sg:classifiers":[
        {
            "category":"Building & Trades",
            "subcategory":"Construction",
            "type":"Services"
        }
    ],
    "sg:phone":"+61 412 789 533",
    "sg:postcode":"4207",
    "sg:province":"QLD",
    "sg:tags":[
        "joiner",
        "carpenter"
    ],
    "wof:name":"Farraher J & K",
    "wof:placetype":"venue"
},
  "geometry": {"coordinates":[153.189697266,-27.7233428955],"type":"Point"}
}