{
  "type": "Feature",
  "properties": {
    "addr:full":"18 Greenhill Rd Wayville SA 5034",
    "addr:housenumber":"18",
    "addr:postcode":"5034",
    "addr:street":"Greenhill Rd",
    "iso:country":"AU",
    "sg:address":"18 Greenhill Rd",
    "sg:city":"Wayville",
    "sg:classifiers":[
        {
            "category":"Insurance",
            "subcategory":"Hazard Insurance",
            "type":"Services"
        }
    ],
    "sg:phone":"+61 8 8357 9262",
    "sg:postcode":"5034",
    "sg:province":"SA",
    "sg:tags":[
        "fire",
        "accident",
        "marine"
    ],
    "wof:name":"Combined Insurance Co Of Aust",
    "wof:placetype":"venue"
},
  "geometry": {"coordinates":[138.58653259299999,-34.9421920776],"type":"Point"}
}