{
  "type": "Feature",
  "properties": {
    "addr:full":"Suite 20/ 809 Pacific Hwy Chatswood NSW 2067",
    "addr:housenumber":"20 / 809",
    "addr:postcode":"2067",
    "addr:street":"Pacific Hwy",
    "iso:country":"AU",
    "sg:address":"Suite 20/ 809 Pacific Hwy",
    "sg:city":"Chatswood",
    "sg:classifiers":[
        {
            "category":"Professional",
            "subcategory":"Engineering",
            "type":"Services"
        }
    ],
    "sg:phone":"+61 2 9410 4100",
    "sg:postcode":"2067",
    "sg:province":"NSW",
    "sg:tags":[
        "consulting",
        "engineer"
    ],
    "wof:name":"Masson Wilson Twiney Pty Ltd",
    "wof:placetype":"venue"
},
  "geometry": {"coordinates":[151.17814636200001,-33.7961883545],"type":"Point"}
}