{
  "type": "Feature",
  "properties": {
    "iso:country":"AU",
    "sg:address":"Menai Homemaker Cntr 778 Old Illawarra Rd",
    "sg:city":"Menai",
    "sg:classifiers":[
        {
            "category":"Fast Food",
            "type":"Food & Drink"
        }
    ],
    "sg:phone":"+61 2 9481 1111",
    "sg:postcode":"2234",
    "sg:province":"NSW",
    "sg:tags":[
        "away",
        "take"
    ],
    "wof:name":"Pizza Hut",
    "wof:placetype":"venue"
},
  "geometry": {"coordinates":[151.010253906,-34.0181503296],"type":"Point"}
}