{
  "type": "Feature",
  "properties": {
    "iso:country":"AU",
    "sg:address":"Unit 1/ 11 Wentworth Ave",
    "sg:city":"Nelson Bay",
    "sg:classifiers":[
        {
            "category":"Home & Garden",
            "subcategory":"Building Materials",
            "type":"Retail Goods"
        }
    ],
    "sg:phone":"+61 411 110 896",
    "sg:postcode":"2315",
    "sg:province":"NSW",
    "sg:tags":[
        "lawn",
        "cutting",
        "maintenance"
    ],
    "wof:name":"B.R. Lawn & Garden Care",
    "wof:placetype":"venue"
},
  "geometry": {"coordinates":[152.152573,-32.724316],"type":"Point"}
}