{
  "type": "Feature",
  "properties": {
    "iso:country":"AU",
    "sg:address":"52 Burgess St",
    "sg:city":"Bicheno",
    "sg:classifiers":[
        {
            "category":"Fast Food",
            "type":"Food & Drink"
        }
    ],
    "sg:phone":"+61 3 6375 1280",
    "sg:postcode":"7215",
    "sg:province":"TAS",
    "sg:tags":[
        "away",
        "take"
    ],
    "wof:name":"Bicheno Caravan Park & Take Away Food",
    "wof:placetype":"venue"
},
  "geometry": {"coordinates":[148.303391,-41.877682],"type":"Point"}
}