{
  "type": "Feature",
  "properties": {
    "iso:country":"AU",
    "sg:address":"\"Chirnside Park\" Watton St",
    "sg:city":"Werribee",
    "sg:classifiers":[
        {
            "category":"Arena",
            "subcategory":"Sports Club",
            "type":"Entertainment"
        }
    ],
    "sg:phone":"+61 3 9741 6688",
    "sg:postcode":"3030",
    "sg:province":"VIC",
    "sg:tags":[
        "australian",
        "football",
        "rule"
    ],
    "wof:name":"Werribee Football, Cricket & Sports Club",
    "wof:placetype":"venue"
},
  "geometry": {"coordinates":[144.660446,-37.90163],"type":"Point"}
}