{
  "type": "Feature",
  "properties": {
    "addr:full":"Shop 4 Hanson St Freeling SA 5372",
    "addr:housenumber":"shop 4",
    "addr:postcode":"5372",
    "addr:street":"Hanson St",
    "iso:country":"AU",
    "sg:address":"Shop 4 Hanson St",
    "sg:city":"Freeling",
    "sg:classifiers":[
        {
            "category":"Personal",
            "subcategory":"Beauty Salon",
            "type":"Services"
        }
    ],
    "sg:phone":"+61 8 8525 2278",
    "sg:postcode":"5372",
    "sg:province":"SA",
    "sg:tags":[
        "hairdresser"
    ],
    "wof:name":"Freeling Hair Fashions",
    "wof:placetype":"venue"
},
  "geometry": {"coordinates":[138.809082031,-34.4545974731],"type":"Point"}
}