{
  "type": "Feature",
  "properties": {
    "addr:full":"Davis Pl Grenfell NSW 2810",
    "addr:postcode":"2810",
    "addr:street":"Pl",
    "iso:country":"AU",
    "sg:address":"Davis Pl",
    "sg:city":"Grenfell",
    "sg:classifiers":[
        {
            "category":"Retail",
            "subcategory":"Storage",
            "type":"Services"
        }
    ],
    "sg:phone":"+61 2 6343 1110",
    "sg:postcode":"2810",
    "sg:province":"NSW",
    "wof:name":"Grenfell Self Storage",
    "wof:placetype":"venue"
},
  "geometry": {"coordinates":[148.15081787099999,-33.9004745483],"type":"Point"}
}