{
  "type": "Feature",
  "properties": {
    "iso:country":"AU",
    "sg:address":"Shop 2, 54 Normanby St",
    "sg:city":"Yeppoon",
    "sg:classifiers":[
        {
            "category":"Personal",
            "subcategory":"Massage",
            "type":"Services"
        }
    ],
    "sg:phone":"+61 7 4922 2722",
    "sg:postcode":"4703",
    "sg:province":"QLD",
    "sg:tags":[
        "therapy"
    ],
    "wof:name":"Frank Pottinger",
    "wof:placetype":"venue"
},
  "geometry": {"coordinates":[150.74343872099999,-23.12733078],"type":"Point"}
}