{
  "type": "Feature",
  "properties": {
    "addr:full":"57 MacGregor St Fairfield VIC 3078",
    "addr:housenumber":"57",
    "addr:postcode":"3078",
    "addr:street":"Macgregor St",
    "iso:country":"AU",
    "sg:address":"57 MacGregor St",
    "sg:city":"Fairfield",
    "sg:classifiers":[
        {
            "category":"Professional",
            "subcategory":"Accounting & Tax Preparation",
            "type":"Services"
        }
    ],
    "sg:phone":"+61 3 9482 1409",
    "sg:postcode":"3078",
    "sg:province":"VIC",
    "sg:tags":[
        "bookkeeping"
    ],
    "wof:name":"B 2 B Management Services",
    "wof:placetype":"venue"
},
  "geometry": {"coordinates":[145.022094727,-37.7702636719],"type":"Point"}
}