{
  "type": "Feature",
  "properties": {
    "addr:full":"Shop 9/Wynnum Plaza 2021 Wynnum Rd Wynnum West QLD 4178",
    "addr:housenumber":"shop 9 / wynnum;2021",
    "addr:postcode":"4178",
    "addr:street":"Wynnum Rd",
    "iso:country":"AU",
    "sg:address":"Shop 9/Wynnum Plaza 2021 Wynnum Rd",
    "sg:city":"Wynnum West",
    "sg:classifiers":[
        {
            "category":"Food & Beverages",
            "subcategory":"Specialty",
            "type":"Retail Goods"
        }
    ],
    "sg:phone":"+61 7 3393 4955",
    "sg:postcode":"4178",
    "sg:province":"QLD",
    "sg:tags":[
        "product",
        "health"
    ],
    "wof:name":"Wynnum Plaza Health Foods",
    "wof:placetype":"venue"
},
  "geometry": {"coordinates":[153.15374755900001,-27.4566802979],"type":"Point"}
}