{
  "type": "Feature",
  "properties": {
    "iso:country":"AU",
    "sg:address":"14 Lucas St",
    "sg:city":"Kingston",
    "sg:classifiers":[
        {
            "category":"Home & Garden",
            "subcategory":"Building Materials",
            "type":"Retail Goods"
        }
    ],
    "sg:phone":"+61 419 594 900",
    "sg:postcode":"7050",
    "sg:province":"TAS",
    "sg:tags":[
        "lawn",
        "cutting",
        "maintenance"
    ],
    "wof:name":"Four Seasons Lawn & Garden Services",
    "wof:placetype":"venue"
},
  "geometry": {"coordinates":[147.30830399999999,-42.983379],"type":"Point"}
}