{
  "type": "Feature",
  "properties": {
    "iso:country":"AU",
    "sg:address":"8 Scarborough St",
    "sg:city":"Southport",
    "sg:classifiers":[
        {
            "category":"Real Estate",
            "subcategory":"Real Estate Agent",
            "type":"Services"
        }
    ],
    "sg:phone":"+61 7 5532 3600",
    "sg:postcode":"4215",
    "sg:province":"QLD",
    "sg:website":"http://www.dohertyleesrealestate.com.au",
    "wof:name":"Doherty Lees Real Estate",
    "wof:placetype":"venue"
},
  "geometry": {"coordinates":[153.41531372099999,-27.9723854065],"type":"Point"}
}