{
  "type": "Feature",
  "properties": {
    "addr:full":"14 Ceratonia St Sunnybank Hills QLD 4109",
    "addr:housenumber":"14",
    "addr:postcode":"4109",
    "addr:street":"Ceratonia St",
    "iso:country":"AU",
    "sg:address":"14 Ceratonia St",
    "sg:city":"Sunnybank Hills",
    "sg:classifiers":[
        {
            "category":"Professional",
            "subcategory":"Computer Services",
            "type":"Services"
        }
    ],
    "sg:phone":"+61 7 3423 7733",
    "sg:postcode":"4109",
    "sg:province":"QLD",
    "sg:tags":[
        "repairs",
        "upgrade",
        "equipment"
    ],
    "wof:name":"Simmons Solutions",
    "wof:placetype":"venue"
},
  "geometry": {"coordinates":[153.04997253400001,-27.5901546478],"type":"Point"}
}