{
  "type": "Feature",
  "properties": {
    "addr:full":"4 Lady Game Dr Killara NSW 2071",
    "addr:housenumber":"4",
    "addr:postcode":"2071",
    "addr:street":"Lady Game Dr",
    "iso:country":"AU",
    "sg:address":"4 Lady Game Dr",
    "sg:city":"Killara",
    "sg:classifiers":[
        {
            "category":"Shopping",
            "subcategory":"Musical Instruments",
            "type":"Retail Goods"
        }
    ],
    "sg:phone":"+61 2 9416 4834",
    "sg:postcode":"2071",
    "sg:province":"NSW",
    "sg:tags":[
        "case"
    ],
    "wof:name":"JAFLAC Roadcases & Racks",
    "wof:placetype":"venue"
},
  "geometry": {"coordinates":[151.14848327600001,-33.7750663757],"type":"Point"}
}