{
  "type": "Feature",
  "properties": {
    "iso:country":"AU",
    "sg:address":"Homepride Ave",
    "sg:city":"Liverpool",
    "sg:classifiers":[
        {
            "category":"Food & Beverages",
            "subcategory":"Bakery",
            "type":"Retail Goods"
        }
    ],
    "sg:phone":"+61 2 9821 5888",
    "sg:postcode":"2170",
    "sg:province":"NSW",
    "sg:tags":[
        "baker"
    ],
    "wof:name":"Buttercup Bakeries",
    "wof:placetype":"venue"
},
  "geometry": {"coordinates":[150.92466735799999,-33.9140396118],"type":"Point"}
}