{
  "type": "Feature",
  "properties": {
    "addr:full":"1291 Albany Hwy Cannington WA 6107",
    "addr:housenumber":"1291",
    "addr:postcode":"6107",
    "addr:street":"Albany Hwy",
    "iso:country":"AU",
    "sg:address":"1291 Albany Hwy",
    "sg:city":"Cannington",
    "sg:classifiers":[
        {
            "category":"Communications",
            "subcategory":"Film & Video Production",
            "type":"Services"
        }
    ],
    "sg:phone":"+61 8 9451 4211",
    "sg:postcode":"6107",
    "sg:province":"WA",
    "sg:tags":[
        "fan",
        "blower"
    ],
    "wof:name":"Cannington Fans",
    "wof:placetype":"venue"
},
  "geometry": {"coordinates":[115.929000855,-32.014793396],"type":"Point"}
}