{
  "type": "Feature",
  "properties": {
    "addr:full":"Unit 5/488 Walter Rd (Cnr of Beechboro Rd) Bayswater WA 6053",
    "addr:housenumber":"/ 488",
    "addr:postcode":"6053",
    "addr:street":"Walter Rd Cnr;Beechboro Rd",
    "iso:country":"AU",
    "sg:address":"Unit 5/488 Walter Rd (Cnr of Beechboro Rd)",
    "sg:city":"Bayswater",
    "sg:classifiers":[
        {
            "category":"Health Services",
            "subcategory":"Doctor",
            "type":"Services"
        }
    ],
    "sg:phone":"+61 8 9279 9980",
    "sg:postcode":"6053",
    "sg:province":"WA",
    "sg:tags":[
        "medical",
        "practitioner"
    ],
    "wof:name":"Cooper Kathryn Dr",
    "wof:placetype":"venue"
},
  "geometry": {"coordinates":[115.918243408,-31.8946151733],"type":"Point"}
}