{
  "type": "Feature",
  "properties": {
    "iso:country":"AU",
    "sg:address":"Suite 3/ 138 Pitt Water Rd",
    "sg:city":"Boronia Park",
    "sg:classifiers":[
        {
            "category":"Professional",
            "subcategory":"Accounting & Tax Preparation",
            "type":"Services"
        }
    ],
    "sg:phone":"+61 2 9816 2033",
    "sg:postcode":"2111",
    "sg:province":"NSW",
    "sg:tags":[
        "consultant",
        "taxation"
    ],
    "wof:name":"Heming F L & Co",
    "wof:placetype":"venue"
},
  "geometry": {"coordinates":[151.13420105,-33.8219223022],"type":"Point"}
}