{
  "type": "Feature",
  "properties": {
    "addr:full":"49 Paradise Ave Miami QLD 4220",
    "addr:housenumber":"49",
    "addr:postcode":"4220",
    "addr:street":"Paradise Ave",
    "iso:country":"AU",
    "sg:address":"49 Paradise Ave",
    "sg:city":"Miami",
    "sg:phone":"+61 7 5526 1777",
    "sg:postcode":"4220",
    "sg:province":"QLD",
    "wof:name":"Gold Coast Window Tinting",
    "wof:placetype":"venue"
},
  "geometry": {"coordinates":[153.43467712399999,-28.0647296906],"type":"Point"}
}