{
  "type": "Feature",
  "properties": {
    "iso:country":"AU",
    "sg:address":"290 Brookfield Ave",
    "sg:city":"Broken Hill",
    "sg:classifiers":[
        {
            "category":"Autos & Motor Vehicles",
            "subcategory":"Auto Supplies",
            "type":"Retail Goods"
        }
    ],
    "sg:phone":"+61 8 8088 2906",
    "sg:postcode":"2880",
    "sg:province":"NSW",
    "sg:tags":[
        "battery",
        "automotive"
    ],
    "wof:name":"Century Batteries",
    "wof:placetype":"venue"
},
  "geometry": {"coordinates":[141.442428589,-31.9582862854],"type":"Point"}
}