{
  "type": "Feature",
  "properties": {
    "iso:country":"AU",
    "sg:address":"30 Regina St",
    "sg:city":"Kilsyth",
    "sg:classifiers":[
        {
            "category":"Building & Trades",
            "subcategory":"Cleaning & Sanitation",
            "type":"Services"
        }
    ],
    "sg:phone":"+61 3 9728 5516",
    "sg:postcode":"3137",
    "sg:province":"VIC",
    "sg:tags":[
        "duct"
    ],
    "wof:name":"Air Duct Specialized Cleaning Services",
    "wof:placetype":"venue"
},
  "geometry": {"coordinates":[145.32989501899999,-37.8034477234],"type":"Point"}
}