{
  "type": "Feature",
  "properties": {
    "iso:country":"AU",
    "sg:address":"15 Masson Crt",
    "sg:city":"Bakewell",
    "sg:classifiers":[
        {
            "category":"Retail",
            "subcategory":"Auto Repair",
            "type":"Services"
        }
    ],
    "sg:phone":"+61 400 205 525",
    "sg:postcode":"0832",
    "sg:province":"NT",
    "sg:tags":[
        "repairer",
        "motor",
        "engineer"
    ],
    "wof:name":"Alliance Mobile Automotive",
    "wof:placetype":"venue"
},
  "geometry": {"coordinates":[130.996964,-12.4949],"type":"Point"}
}