{
  "type": "Feature",
  "properties": {
    "iso:country":"AU",
    "sg:address":"10 Medusa St",
    "sg:city":"Bendigo",
    "sg:classifiers":[
        {
            "category":"Building & Trades",
            "subcategory":"Construction",
            "type":"Services"
        }
    ],
    "sg:phone":"+61 3 5439 4949",
    "sg:postcode":"3550",
    "sg:province":"VIC",
    "sg:tags":[
        "contractor"
    ],
    "wof:name":"Beazley Reuben Builder",
    "wof:placetype":"venue"
},
  "geometry": {"coordinates":[144.338912964,-36.7975311279],"type":"Point"}
}