{
  "type": "Feature",
  "properties": {
    "addr:full":"62 South St Rydalmere NSW 2116",
    "addr:housenumber":"62",
    "addr:postcode":"2116",
    "addr:street":"South St",
    "iso:country":"AU",
    "sg:address":"62 South St",
    "sg:city":"Rydalmere",
    "sg:classifiers":[
        {
            "category":"Banks & Credit Unions",
            "subcategory":"Investment Brokerage",
            "type":"Services"
        }
    ],
    "sg:phone":"+61 2 9638 0320",
    "sg:postcode":"2116",
    "sg:province":"NSW",
    "sg:tags":[
        "shutter",
        "louvre"
    ],
    "wof:name":"Crystal Twig Pty Ltd",
    "wof:placetype":"venue"
},
  "geometry": {"coordinates":[151.01072692899999,-33.8346633911],"type":"Point"}
}