{
  "type": "Feature",
  "properties": {
    "addr:full":"33 Stretton Pl Wyndham Vale VIC 3024",
    "addr:housenumber":"33",
    "addr:postcode":"3024",
    "addr:street":"Pl",
    "iso:country":"AU",
    "sg:address":"33 Stretton Pl",
    "sg:city":"Wyndham Vale",
    "sg:classifiers":[
        {
            "category":"Building & Trades",
            "subcategory":"Construction",
            "type":"Services"
        }
    ],
    "sg:phone":"+61 419 001 040",
    "sg:postcode":"3024",
    "sg:province":"VIC",
    "sg:tags":[
        "plasterboard",
        "plasterer",
        "fixer"
    ],
    "wof:name":"Hollywood for Hire",
    "wof:placetype":"venue"
},
  "geometry": {"coordinates":[144.618134,-37.879269],"type":"Point"}
}