{
  "type": "Feature",
  "properties": {
    "iso:country":"AU",
    "sg:address":"Level 2- 85 Queen St",
    "sg:city":"Melbourne",
    "sg:classifiers":[
        {
            "category":"Personal",
            "subcategory":"Massage",
            "type":"Services"
        }
    ],
    "sg:phone":"+61 1300 138 872",
    "sg:postcode":"3000",
    "sg:province":"VIC",
    "sg:tags":[
        "therapy"
    ],
    "wof:name":"Australian Association of Massage Therapists",
    "wof:placetype":"venue"
},
  "geometry": {"coordinates":[144.96124267600001,-37.816532135],"type":"Point"}
}