{
  "type": "Feature",
  "properties": {
    "addr:full":"8 Helena St Lilyfield NSW 2040",
    "addr:housenumber":"8",
    "addr:postcode":"2040",
    "addr:street":"Helena St",
    "iso:country":"AU",
    "sg:address":"8 Helena St",
    "sg:city":"Lilyfield",
    "sg:classifiers":[
        {
            "category":"Professional",
            "subcategory":"Computer Services",
            "type":"Services"
        }
    ],
    "sg:phone":"+61 2 9086 9098",
    "sg:postcode":"2040",
    "sg:province":"NSW",
    "sg:tags":[
        "tele-communications",
        "consultant"
    ],
    "wof:name":"Tektel",
    "wof:placetype":"venue"
},
  "geometry": {"coordinates":[151.16128499999999,-33.871651],"type":"Point"}
}