{
  "type": "Feature",
  "properties": {
    "iso:country":"AU",
    "sg:address":"Unit 2 12- 16 Ferndell St",
    "sg:city":"Granville",
    "sg:classifiers":[
        {
            "category":"Shopping",
            "subcategory":"Computers & Home Electronics",
            "type":"Retail Goods"
        }
    ],
    "sg:phone":"+61 2 9632 3666",
    "sg:postcode":"2142",
    "sg:province":"NSW",
    "sg:tags":[
        "equipment",
        "supply"
    ],
    "wof:name":"A. Zebra",
    "wof:placetype":"venue"
},
  "geometry": {"coordinates":[151.008636475,-33.8654785156],"type":"Point"}
}