{
  "type": "Feature",
  "properties": {
    "addr:full":"191 Lyons Rd Drummoyne NSW 2047",
    "addr:housenumber":"191",
    "addr:postcode":"2047",
    "addr:street":"Lyons Rd",
    "iso:country":"AU",
    "sg:address":"191 Lyons Rd",
    "sg:city":"Drummoyne",
    "sg:classifiers":[
        {
            "category":"Autos & Motor Vehicles",
            "subcategory":"Fuel & Gas Station",
            "type":"Retail Goods"
        }
    ],
    "sg:phone":"+61 2 9713 7265",
    "sg:postcode":"2047",
    "sg:province":"NSW",
    "wof:name":"Ampol",
    "wof:placetype":"venue"
},
  "geometry": {"coordinates":[151.145996,-33.856861],"type":"Point"}
}