{
  "type": "Feature",
  "properties": {
    "addr:full":"4/ 53 Metroplex Ave Murarrie QLD 4172",
    "addr:housenumber":"/ 53",
    "addr:postcode":"4172",
    "addr:street":"Metroplex Ave",
    "iso:country":"AU",
    "sg:address":"4/ 53 Metroplex Ave",
    "sg:city":"Murarrie",
    "sg:classifiers":[
        {
            "category":"Wholesale",
            "subcategory":"Apparel",
            "type":"Manufacturing & Wholesale Goods"
        }
    ],
    "sg:phone":"+61 7 3395 7200",
    "sg:postcode":"4172",
    "sg:province":"QLD",
    "sg:tags":[
        "wholesaler",
        "mfrs",
        "uniform"
    ],
    "wof:name":"Promo Gear",
    "wof:placetype":"venue"
},
  "geometry": {"coordinates":[153.09857177699999,-27.4497947693],"type":"Point"}
}