{
  "type": "Feature",
  "properties": {
    "addr:full":"36 Container St Tingalpa QLD 4173",
    "addr:postcode":"4173",
    "addr:street":"St",
    "iso:country":"AU",
    "sg:address":"36 Container St",
    "sg:city":"Tingalpa",
    "sg:classifiers":[
        {
            "category":"Shopping",
            "subcategory":"Stationery & Office Supplies",
            "type":"Retail Goods"
        }
    ],
    "sg:phone":"+61 7 3890 1890",
    "sg:postcode":"4173",
    "sg:province":"QLD",
    "sg:tags":[
        "packaging",
        "material"
    ],
    "wof:name":"Allpak Systems",
    "wof:placetype":"venue"
},
  "geometry": {"coordinates":[153.10911560100001,-27.4747123718],"type":"Point"}
}