{
  "type": "Feature",
  "properties": {
    "addr:full":"100 Brighton Rd Elsternwick VIC 3185",
    "addr:housenumber":"100",
    "addr:postcode":"3185",
    "addr:street":"Brighton Rd",
    "iso:country":"AU",
    "sg:address":"100 Brighton Rd",
    "sg:city":"Elsternwick",
    "sg:classifiers":[
        {
            "category":"Health Services",
            "subcategory":"Doctor",
            "type":"Services"
        }
    ],
    "sg:phone":"+61 3 9525 6200",
    "sg:postcode":"3185",
    "sg:province":"VIC",
    "sg:tags":[
        "medical",
        "practitioner"
    ],
    "wof:name":"Tass Tasiopoulos Dr",
    "wof:placetype":"venue"
},
  "geometry": {"coordinates":[144.99403381400001,-37.8784294128],"type":"Point"}
}