{
  "type": "Feature",
  "properties": {
    "addr:full":"1 Howard St Sebastopol VIC 3356",
    "addr:housenumber":"1",
    "addr:postcode":"3356",
    "addr:street":"Howard St",
    "iso:country":"AU",
    "sg:address":"1 Howard St",
    "sg:city":"Sebastopol",
    "sg:classifiers":[
        {
            "category":"Organizations",
            "subcategory":"Non-profit Organization",
            "type":"Services"
        }
    ],
    "sg:phone":"+61 3 5335 5634",
    "sg:postcode":"3356",
    "sg:province":"VIC",
    "sg:tags":[
        "support",
        "disability",
        "organisation"
    ],
    "wof:name":"Wynalla House",
    "wof:placetype":"venue"
},
  "geometry": {"coordinates":[143.83154300000001,-37.606556],"type":"Point"}
}