{
  "type": "Feature",
  "properties": {
    "iso:country":"AU",
    "sg:address":"Lot 4 Powter St",
    "sg:city":"Parkes",
    "sg:classifiers":[
        {
            "category":"Retail",
            "subcategory":"Auto Repair",
            "type":"Services"
        }
    ],
    "sg:phone":"+61 2 6862 1756",
    "sg:postcode":"2870",
    "sg:province":"NSW",
    "sg:tags":[
        "muffler",
        "exhaust",
        "system"
    ],
    "wof:name":"Custom Flow Exhaust",
    "wof:placetype":"venue"
},
  "geometry": {"coordinates":[148.16494800000001,-33.145214],"type":"Point"}
}