{
  "type": "Feature",
  "properties": {
    "addr:full":"2 Richard St The Entrance NSW 2261",
    "addr:housenumber":"2",
    "addr:postcode":"2261",
    "addr:street":"Richard St The",
    "iso:country":"AU",
    "sg:address":"2 Richard St",
    "sg:city":"The Entrance",
    "sg:classifiers":[
        {
            "category":"Building & Trades",
            "subcategory":"Construction",
            "type":"Services"
        }
    ],
    "sg:phone":"+61 2 4332 1279",
    "sg:postcode":"2261",
    "sg:province":"NSW",
    "sg:tags":[
        "fencing",
        "contractor"
    ],
    "wof:name":"TS Fencing Creations",
    "wof:placetype":"venue"
},
  "geometry": {"coordinates":[151.50071700000001,-33.349842],"type":"Point"}
}