{
  "type": "Feature",
  "properties": {
    "addr:full":"PO Box 8185 Glenmore Park NSW 2745",
    "addr:postcode":"2745",
    "iso:country":"AU",
    "sg:address":"PO Box 8185",
    "sg:city":"Glenmore Park",
    "sg:classifiers":[
        {
            "category":"Utilities",
            "subcategory":"Electric",
            "type":"Services"
        }
    ],
    "sg:phone":"+61 2 4733 4632",
    "sg:postcode":"2745",
    "sg:province":"NSW",
    "sg:tags":[
        "electrical",
        "contractor"
    ],
    "wof:name":"Champion Electrical Services",
    "wof:placetype":"venue"
},
  "geometry": {"coordinates":[150.67874145499999,-33.7848701477],"type":"Point"}
}