{
  "type": "Feature",
  "properties": {
    "iso:country":"AU",
    "sg:address":"31 Nevin Drv",
    "sg:city":"Thomastown",
    "sg:classifiers":[
        {
            "category":"Shopping",
            "subcategory":"Mobile Phones",
            "type":"Retail Goods"
        }
    ],
    "sg:phone":"+61 3 9464 2001",
    "sg:postcode":"3074",
    "sg:province":"VIC",
    "sg:tags":[
        "wholesaler",
        "mfrs",
        "electrical",
        "switchboard"
    ],
    "wof:name":"Pericsons Pty Ltd Custom Switchboards",
    "wof:placetype":"venue"
},
  "geometry": {"coordinates":[145.033325195,-37.6957626343],"type":"Point"}
}