{
  "type": "Feature",
  "properties": {
    "addr:full":"Shp3B/ 1569 Burwood Hwy Tecoma VIC 3160",
    "addr:housenumber":"1569",
    "addr:postcode":"3160",
    "addr:street":"Burwood Hwy",
    "iso:country":"AU",
    "sg:address":"Shp3B/ 1569 Burwood Hwy",
    "sg:city":"Tecoma",
    "sg:classifiers":[
        {
            "category":"Professional",
            "subcategory":"Accounting & Tax Preparation",
            "type":"Services"
        }
    ],
    "sg:phone":"+61 3 9752 5150",
    "sg:postcode":"3160",
    "sg:province":"VIC",
    "sg:tags":[
        "accountant",
        "auditor"
    ],
    "wof:name":"Peter Maxwell & Co",
    "wof:placetype":"venue"
},
  "geometry": {"coordinates":[145.34585571299999,-37.9068756104],"type":"Point"}
}