{
  "type": "Feature",
  "properties": {
    "addr:full":"Shop AM3, Cnr James & Doggett Strts Fortitude Valley QLD 4006",
    "addr:postcode":"4006",
    "addr:street":"Cnr James &",
    "iso:country":"AU",
    "sg:address":"Shop AM3, Cnr James & Doggett Strts",
    "sg:city":"Fortitude Valley",
    "sg:classifiers":[
        {
            "category":"Food & Beverages",
            "subcategory":"Specialty",
            "type":"Retail Goods"
        }
    ],
    "sg:phone":"+61 7 3852 5212",
    "sg:postcode":"4006",
    "sg:province":"QLD",
    "sg:tags":[
        "product",
        "health"
    ],
    "wof:name":"Vitality Stores",
    "wof:placetype":"venue"
},
  "geometry": {"coordinates":[153.040725708,-27.4566936493],"type":"Point"}
}