{
  "type": "Feature",
  "properties": {
    "iso:country":"AU",
    "sg:address":"7 Killara Rd",
    "sg:city":"Coldstream",
    "sg:classifiers":[
        {
            "category":"Retail",
            "subcategory":"Storage",
            "type":"Services"
        }
    ],
    "sg:phone":"+61 3 9739 0789",
    "sg:postcode":"3770",
    "sg:province":"VIC",
    "sg:tags":[
        "removal",
        "furniture"
    ],
    "wof:name":"Eagle Removals",
    "wof:placetype":"venue"
},
  "geometry": {"coordinates":[145.38180500000001,-37.7244],"type":"Point"}
}