{
  "type": "Feature",
  "properties": {
    "iso:country":"AU",
    "sg:address":"150 Blackmans Creek Rd",
    "sg:city":"Hartley",
    "sg:classifiers":[
        {
            "category":"Building & Trades",
            "subcategory":"Plumbing",
            "type":"Services"
        }
    ],
    "sg:phone":"+61 2 6355 2251",
    "sg:postcode":"2790",
    "sg:province":"NSW",
    "sg:tags":[
        "plumber",
        "gasfitters"
    ],
    "wof:name":"Mick Linhart Plumbing Services",
    "wof:placetype":"venue"
},
  "geometry": {"coordinates":[150.174224853,-33.5306816101],"type":"Point"}
}