{
  "type": "Feature",
  "properties": {
    "iso:country":"AU",
    "sg:address":"19 Bridge St",
    "sg:city":"Lismore",
    "sg:classifiers":[
        {
            "category":"Communications",
            "type":"Services"
        }
    ],
    "sg:phone":"+61 2 6621 7720",
    "sg:postcode":"2480",
    "sg:province":"NSW",
    "sg:tags":[
        "equipment",
        "radio"
    ],
    "wof:name":"Robs Mobile Communications",
    "wof:placetype":"venue"
},
  "geometry": {"coordinates":[153.27554321299999,-28.804605484],"type":"Point"}
}