{
  "type": "Feature",
  "properties": {
    "addr:full":"Paroo St Renmark SA 5341",
    "addr:postcode":"5341",
    "addr:street":"Paroo St",
    "iso:country":"AU",
    "sg:address":"Paroo St",
    "sg:city":"Renmark",
    "sg:classifiers":[
        {
            "category":"Farming",
            "subcategory":"Berry Farm",
            "type":"Manufacturing & Wholesale Goods"
        }
    ],
    "sg:phone":"+61 8 8595 3379",
    "sg:postcode":"5341",
    "sg:province":"SA",
    "sg:tags":[
        "fruit",
        "grower"
    ],
    "wof:name":"Ivanovic S R",
    "wof:placetype":"venue"
},
  "geometry": {"coordinates":[140.72833251899999,-34.1450538635],"type":"Point"}
}