{
  "type": "Feature",
  "properties": {
    "iso:country":"AU",
    "sg:address":"43 Coode Rd",
    "sg:city":"West Melbourne",
    "sg:classifiers":[
        {
            "category":"Freight",
            "type":"Transportation"
        }
    ],
    "sg:phone":"+61 3 9689 6311",
    "sg:postcode":"3003",
    "sg:province":"VIC",
    "sg:tags":[
        "cargo",
        "container"
    ],
    "wof:name":"Logistics Link Pty Ltd",
    "wof:placetype":"venue"
},
  "geometry": {"coordinates":[144.91607665999999,-37.8092460632],"type":"Point"}
}