{
  "type": "Feature",
  "properties": {
    "addr:full":"Suite 604/ 220 Pacific Hwy North Sydney NSW 2060",
    "addr:housenumber":"/ 220",
    "addr:postcode":"2060",
    "addr:street":"Pacific Hwy",
    "iso:country":"AU",
    "sg:address":"Suite 604/ 220 Pacific Hwy",
    "sg:city":"North Sydney",
    "sg:classifiers":[
        {
            "category":"Education",
            "subcategory":"Special Training",
            "type":"Public Place"
        }
    ],
    "sg:phone":"+61 2 9231 4591",
    "sg:postcode":"2060",
    "sg:province":"NSW",
    "sg:tags":[
        "development"
    ],
    "wof:name":"Twenty Twenty Learning",
    "wof:placetype":"venue"
},
  "geometry": {"coordinates":[151.20223999000001,-33.8299942017],"type":"Point"}
}