{
  "type": "Feature",
  "properties": {
    "iso:country":"AU",
    "sg:address":"168 Corio St",
    "sg:city":"Shepparton",
    "sg:classifiers":[
        {
            "category":"Professional",
            "subcategory":"Employment Agencies",
            "type":"Services"
        }
    ],
    "sg:phone":"+61 3 5822 2115",
    "sg:postcode":"3630",
    "sg:province":"VIC",
    "wof:name":"VECCI Shepparton",
    "wof:placetype":"venue"
},
  "geometry": {"coordinates":[145.40321350100001,-36.3809776306],"type":"Point"}
}