{
  "type": "Feature",
  "properties": {
    "addr:full":"32 Stirling Ave Cranbourne VIC 3977",
    "addr:housenumber":"32",
    "addr:postcode":"3977",
    "addr:street":"Stirling Ave",
    "iso:country":"AU",
    "sg:address":"32 Stirling Ave",
    "sg:city":"Cranbourne",
    "sg:classifiers":[
        {
            "category":"Health Services",
            "subcategory":"Doctor",
            "type":"Services"
        }
    ],
    "sg:phone":"+61 3 5995 7777",
    "sg:postcode":"3977",
    "sg:province":"VIC",
    "sg:tags":[
        "medical",
        "practitioner"
    ],
    "wof:name":"Wong Simon Dr",
    "wof:placetype":"venue"
},
  "geometry": {"coordinates":[145.267974853,-38.0694046021],"type":"Point"}
}