{
  "type": "Feature",
  "properties": {
    "iso:country":"AU",
    "sg:address":"Lvl1/ 47 Waymouth St",
    "sg:city":"Adelaide",
    "sg:classifiers":[
        {
            "category":"Education",
            "subcategory":"Dance Studio",
            "type":"Public Place"
        }
    ],
    "sg:phone":"+61 8 8410 5222",
    "sg:postcode":"5000",
    "sg:province":"SA",
    "sg:tags":[
        "instruction",
        "language"
    ],
    "wof:name":"South Australian College Of English",
    "wof:placetype":"venue"
},
  "geometry": {"coordinates":[138.59902954099999,-34.9259376526],"type":"Point"}
}