{
  "type": "Feature",
  "properties": {
    "addr:full":"8 Budgen St Moil NT 0810",
    "addr:housenumber":"8",
    "addr:postcode":"nt 0810",
    "addr:street":"Budgen St",
    "iso:country":"AU",
    "sg:address":"8 Budgen St",
    "sg:city":"Moil",
    "sg:classifiers":[
        {
            "category":"Health Services",
            "subcategory":"Doctor",
            "type":"Services"
        }
    ],
    "sg:phone":"+61 8 8945 1211",
    "sg:postcode":"0810",
    "sg:province":"NT",
    "sg:tags":[
        "medical",
        "practitioner"
    ],
    "wof:name":"Sirima Tilakaratne",
    "wof:placetype":"venue"
},
  "geometry": {"coordinates":[130.882614136,-12.3904180527],"type":"Point"}
}