{
  "type": "Feature",
  "properties": {
    "addr:full":"700 Lutwyche Rd Kedron QLD 4031",
    "addr:housenumber":"700",
    "addr:postcode":"4031",
    "addr:street":"Lutwyche Rd",
    "iso:country":"AU",
    "sg:address":"700 Lutwyche Rd",
    "sg:city":"Kedron",
    "sg:classifiers":[
        {
            "category":"Travel",
            "subcategory":"Hotels & Motels",
            "type":"Entertainment"
        }
    ],
    "sg:phone":"+61 1800 066 882",
    "sg:postcode":"4031",
    "sg:province":"QLD",
    "wof:name":"Kedron on the Brook",
    "wof:placetype":"venue"
},
  "geometry": {"coordinates":[153.035797,-27.415167],"type":"Point"}
}