{
  "type": "Feature",
  "properties": {
    "iso:country":"AU",
    "sg:address":"132 Mersey Rd",
    "sg:city":"Badgerys Creek",
    "sg:classifiers":[
        {
            "category":"Real Estate",
            "subcategory":"Real Estate Agent",
            "type":"Services"
        }
    ],
    "sg:phone":"+61 2 4774 9677",
    "sg:postcode":"2171",
    "sg:province":"NSW",
    "wof:name":"Harrington Park Industrial Real Estate",
    "wof:placetype":"venue"
},
  "geometry": {"coordinates":[150.846237183,-33.9284286499],"type":"Point"}
}