{
  "type": "Feature",
  "properties": {
    "addr:full":"U53/ 9 Hoyle Av Castle Hill NSW 2154",
    "addr:postcode":"2154",
    "addr:street":"/;Hoyle Av",
    "iso:country":"AU",
    "sg:address":"U53/ 9",
    "sg:city":"Hoyle Av Castle Hill",
    "sg:classifiers":[
        {
            "category":"Utilities",
            "subcategory":"Fuel Oil & Lpg",
            "type":"Services"
        }
    ],
    "sg:phone":"+61 1300 724 585",
    "sg:postcode":"2154",
    "sg:province":"NSW",
    "sg:tags":[
        "tungsten",
        "product",
        "carbide"
    ],
    "wof:name":"Taegutec Australia Pty Ltd",
    "wof:placetype":"venue"
},
  "geometry": {"coordinates":[150.98312377900001,-33.7314720154],"type":"Point"}
}