{
  "type": "Feature",
  "properties": {
    "addr:full":"192 William St Clemton Park NSW 2206",
    "addr:housenumber":"192",
    "addr:postcode":"2206",
    "addr:street":"William St",
    "iso:country":"AU",
    "sg:address":"192 William St",
    "sg:city":"Clemton Park",
    "sg:classifiers":[
        {
            "category":"Autos & Motor Vehicles",
            "subcategory":"Fuel & Gas Station",
            "type":"Retail Goods"
        }
    ],
    "sg:phone":"+61 2 9718 5649",
    "sg:postcode":"2206",
    "sg:province":"NSW",
    "wof:name":"Earlwood Service Centre",
    "wof:placetype":"venue"
},
  "geometry": {"coordinates":[151.11050399999999,-33.927593],"type":"Point"}
}