{
  "type": "Feature",
  "properties": {
    "iso:country":"AU",
    "sg:address":"35 Main North Rd",
    "sg:city":"Clare",
    "sg:classifiers":[
        {
            "category":"Restaurant",
            "type":"Food & Drink"
        }
    ],
    "sg:phone":"+61 8 8842 2848",
    "sg:postcode":"5453",
    "sg:province":"SA",
    "sg:tags":[
        "roadhouse"
    ],
    "wof:name":"Caltex Roadhouse",
    "wof:placetype":"venue"
},
  "geometry": {"coordinates":[138.61163300000001,-33.833019],"type":"Point"}
}