{
  "type": "Feature",
  "properties": {
    "addr:full":"188 Brighton St Richmond VIC 3121",
    "addr:housenumber":"188",
    "addr:postcode":"3121",
    "addr:street":"Brighton St",
    "iso:country":"AU",
    "sg:address":"188 Brighton St",
    "sg:city":"Richmond",
    "sg:classifiers":[
        {
            "category":"Real Estate",
            "subcategory":"Architect",
            "type":"Services"
        }
    ],
    "sg:phone":"+61 3 9427 7688",
    "sg:postcode":"3121",
    "sg:province":"VIC",
    "wof:name":"Atley Lawrence",
    "wof:placetype":"venue"
},
  "geometry": {"coordinates":[144.99807739299999,-37.8328819275],"type":"Point"}
}