{
  "type": "Feature",
  "properties": {
    "addr:full":"U 7/ 2 Apollo Crt Blackburn VIC 3130",
    "addr:housenumber":"2",
    "addr:postcode":"3130",
    "addr:street":"Apollo Crt",
    "iso:country":"AU",
    "sg:address":"U 7/ 2 Apollo Crt",
    "sg:city":"Blackburn",
    "sg:classifiers":[
        {
            "category":"Professional",
            "subcategory":"Art Services",
            "type":"Services"
        }
    ],
    "sg:phone":"+61 3 9894 7225",
    "sg:postcode":"3130",
    "sg:province":"VIC",
    "sg:tags":[
        "graphic",
        "designer"
    ],
    "wof:name":"Image Bound Pty Ltd",
    "wof:placetype":"venue"
},
  "geometry": {"coordinates":[145.16297912600001,-37.8197441101],"type":"Point"}
}