{
  "type": "Feature",
  "properties": {
    "addr:full":"335 South Dowling St Darlinghurst NSW 2010",
    "addr:housenumber":"335",
    "addr:postcode":"2010",
    "addr:street":"South Dowling St",
    "iso:country":"AU",
    "sg:address":"335 South Dowling St",
    "sg:city":"Darlinghurst",
    "sg:classifiers":[
        {
            "category":"Arts & Performance",
            "subcategory":"Art Gallery",
            "type":"Entertainment"
        }
    ],
    "sg:phone":"+61 2 9331 4988",
    "sg:postcode":"2010",
    "sg:province":"NSW",
    "wof:name":"Charles Hewitt Gallery & Framing Showroom",
    "wof:placetype":"venue"
},
  "geometry": {"coordinates":[151.21873474099999,-33.8823242188],"type":"Point"}
}