{
  "type": "Feature",
  "properties": {
    "iso:country":"AU",
    "sg:address":"134 Terralong St",
    "sg:city":"Kiama",
    "sg:classifiers":[
        {
            "category":"Professional",
            "subcategory":"Art Services",
            "type":"Services"
        }
    ],
    "sg:phone":"+61 2 4232 3166",
    "sg:postcode":"2533",
    "sg:province":"NSW",
    "sg:tags":[
        "picture",
        "frame",
        "framing"
    ],
    "wof:name":"Terralong Gallery",
    "wof:placetype":"venue"
},
  "geometry": {"coordinates":[150.851028442,-34.6682357788],"type":"Point"}
}