{
  "type": "Feature",
  "properties": {
    "iso:country":"AU",
    "sg:address":"Gellie St",
    "sg:city":"Camperdown",
    "sg:classifiers":[
        {
            "category":"Military Area",
            "subcategory":"Army Base",
            "type":"Public Place"
        }
    ],
    "sg:phone":"+61 3 5593 2700",
    "sg:postcode":"3260",
    "sg:province":"VIC",
    "sg:tags":[
        "concrete",
        "slab",
        "floor"
    ],
    "wof:name":"Camperdown Pre-Mix Concrete",
    "wof:placetype":"venue"
},
  "geometry": {"coordinates":[143.14503479000001,-38.2254600525],"type":"Point"}
}