{
  "type": "Feature",
  "properties": {
    "addr:full":"540 Beach Rd Denhams Beach NSW 2536",
    "addr:housenumber":"540",
    "addr:postcode":"2536",
    "addr:street":"Beach Rd",
    "iso:country":"AU",
    "sg:address":"540 Beach Rd",
    "sg:city":"Denhams Beach",
    "sg:classifiers":[
        {
            "category":"Organizations",
            "subcategory":"Non-profit Organization",
            "type":"Services"
        }
    ],
    "sg:phone":"+61 2 4472 1020",
    "sg:postcode":"2536",
    "sg:province":"NSW",
    "sg:tags":[
        "support",
        "disability",
        "organisation"
    ],
    "wof:name":"South Coast Additional Needs Learning & Consultancy Centre",
    "wof:placetype":"venue"
},
  "geometry": {"coordinates":[150.21063232399999,-35.7499504089],"type":"Point"}
}