{
  "type": "Feature",
  "properties": {
    "addr:full":"Shop 5 210 Albert St Sebastopol VIC 3356",
    "addr:housenumber":"shop 5 210",
    "addr:postcode":"3356",
    "addr:street":"Albert St",
    "iso:country":"AU",
    "sg:address":"Shop 5 210 Albert St",
    "sg:city":"Sebastopol",
    "sg:classifiers":[
        {
            "category":"Food & Beverages",
            "subcategory":"Supermarket",
            "type":"Retail Goods"
        }
    ],
    "sg:phone":"+61 3 5335 9267",
    "sg:postcode":"3356",
    "sg:province":"VIC",
    "sg:tags":[
        "grocery",
        "store"
    ],
    "wof:name":"Franklins No Frills",
    "wof:placetype":"venue"
},
  "geometry": {"coordinates":[143.84089700000001,-37.599442],"type":"Point"}
}