{
  "type": "Feature",
  "properties": {
    "addr:full":"5 Mary Gilmore Crt Burleigh Heads QLD 4220",
    "addr:housenumber":"5",
    "addr:postcode":"4220",
    "addr:street":"Mary Gilmore Crt",
    "iso:country":"AU",
    "sg:address":"5 Mary Gilmore Crt",
    "sg:city":"Burleigh Heads",
    "sg:classifiers":[
        {
            "category":"Professional",
            "subcategory":"Accounting & Tax Preparation",
            "type":"Services"
        }
    ],
    "sg:phone":"+61 7 5535 5614",
    "sg:postcode":"4220",
    "sg:province":"QLD",
    "sg:tags":[
        "accountant",
        "auditor"
    ],
    "wof:name":"Derek Smith",
    "wof:placetype":"venue"
},
  "geometry": {"coordinates":[153.429763794,-28.110080719],"type":"Point"}
}