{
  "type": "Feature",
  "properties": {
    "iso:country":"AU",
    "sg:address":"1/ 277 Sir Donald Bradman Drv",
    "sg:city":"Cowandilla",
    "sg:classifiers":[
        {
            "category":"Professional",
            "subcategory":"Printing & Photocopies",
            "type":"Services"
        }
    ],
    "sg:phone":"+61 8 8234 6500",
    "sg:postcode":"5033",
    "sg:province":"SA",
    "sg:tags":[
        "photocopier"
    ],
    "wof:name":"Xerox Business Centre",
    "wof:placetype":"venue"
},
  "geometry": {"coordinates":[138.553009033,-34.9329223633],"type":"Point"}
}