{
  "type": "Feature",
  "properties": {
    "addr:full":"2/ 177 Power St Hawthorn VIC 3122",
    "addr:housenumber":"/ 177",
    "addr:postcode":"3122",
    "addr:street":"Power St",
    "iso:country":"AU",
    "sg:address":"2/ 177 Power St",
    "sg:city":"Hawthorn",
    "sg:classifiers":[
        {
            "category":"Wholesale",
            "subcategory":"Scrap",
            "type":"Manufacturing & Wholesale Goods"
        }
    ],
    "sg:phone":"+61 433 660 363",
    "sg:postcode":"3122",
    "sg:province":"VIC",
    "sg:tags":[
        "merchant",
        "metal"
    ],
    "wof:name":"Hansko Metals",
    "wof:placetype":"venue"
},
  "geometry": {"coordinates":[145.02560424800001,-37.8265991211],"type":"Point"}
}