{
  "type": "Feature",
  "properties": {
    "addr:full":"PO Box 64 Lugarno NSW 2210",
    "addr:postcode":"2210",
    "iso:country":"AU",
    "sg:address":"PO Box 64",
    "sg:city":"Lugarno",
    "sg:classifiers":[
        {
            "category":"Organizations",
            "subcategory":"Community Association",
            "type":"Services"
        }
    ],
    "sg:phone":"+61 2 9153 9747",
    "sg:postcode":"2210",
    "sg:province":"NSW",
    "sg:tags":[
        "registered",
        "trustee",
        "bankruptcy"
    ],
    "wof:name":"Alternate Debt Relief",
    "wof:placetype":"venue"
},
  "geometry": {"coordinates":[151.04788199999999,-33.975929],"type":"Point"}
}