{
  "type": "Feature",
  "properties": {
    "addr:full":"30 Phillip St St Marys NSW 2760",
    "addr:housenumber":"30",
    "addr:postcode":"2760",
    "addr:street":"Phillip St",
    "iso:country":"AU",
    "sg:address":"30 Phillip St",
    "sg:city":"St Marys",
    "sg:classifiers":[
        {
            "category":"Health Services",
            "subcategory":"Chiropractor",
            "type":"Services"
        }
    ],
    "sg:phone":"+61 2 9673 2851",
    "sg:postcode":"2760",
    "sg:province":"NSW",
    "wof:name":"A Family Chiropractor",
    "wof:placetype":"venue"
},
  "geometry": {"coordinates":[150.777267456,-33.7642173767],"type":"Point"}
}