{
  "type": "Feature",
  "properties": {
    "iso:country":"AU",
    "sg:address":"Shop 3/ 1 Bells Rd",
    "sg:city":"Oatlands",
    "sg:classifiers":[
        {
            "category":"Personal",
            "subcategory":"Beauty Salon",
            "type":"Services"
        }
    ],
    "sg:phone":"+61 2 9638 4395",
    "sg:postcode":"2117",
    "sg:province":"NSW",
    "sg:tags":[
        "hairdresser"
    ],
    "wof:name":"Oatlands Hair",
    "wof:placetype":"venue"
},
  "geometry": {"coordinates":[151.03114318900001,-33.8025665283],"type":"Point"}
}