{
  "type": "Feature",
  "properties": {
    "addr:full":"5/ 56 Prindiville Drv Wangara WA 6065",
    "addr:housenumber":"/ 56",
    "addr:postcode":"6065",
    "addr:street":"Prindiville Drv",
    "iso:country":"AU",
    "sg:address":"5/ 56 Prindiville Drv",
    "sg:city":"Wangara",
    "sg:classifiers":[
        {
            "category":"Professional",
            "subcategory":"Art Services",
            "type":"Services"
        }
    ],
    "sg:phone":"+61 8 9309 6990",
    "sg:postcode":"6065",
    "sg:province":"WA",
    "sg:tags":[
        "graphic",
        "designer"
    ],
    "wof:name":"Multi Grafix",
    "wof:placetype":"venue"
},
  "geometry": {"coordinates":[115.82611846899999,-31.791519165],"type":"Point"}
}