{
  "type": "Feature",
  "properties": {
    "addr:full":"1 Montega St Iluka WA 6028",
    "addr:housenumber":"1",
    "addr:postcode":"6028",
    "addr:street":"Montega St",
    "iso:country":"AU",
    "sg:address":"1 Montega St",
    "sg:city":"Iluka",
    "sg:classifiers":[
        {
            "category":"Building & Trades",
            "subcategory":"Construction",
            "type":"Services"
        }
    ],
    "sg:phone":"+61 417 962 676",
    "sg:postcode":"6028",
    "sg:province":"WA",
    "sg:tags":[
        "brick",
        "paving"
    ],
    "wof:name":"Total Outdoor Creations",
    "wof:placetype":"venue"
},
  "geometry": {"coordinates":[115.727149963,-31.7405147552],"type":"Point"}
}