{
  "type": "Feature",
  "properties": {
    "addr:full":"Unit4 37 Rushdale St Knoxfield VIC 3180",
    "addr:housenumber":"37",
    "addr:postcode":"3180",
    "addr:street":"Rushdale St",
    "iso:country":"AU",
    "sg:address":"Unit4 37 Rushdale St",
    "sg:city":"Knoxfield",
    "sg:classifiers":[
        {
            "category":"Recreation",
            "type":"Entertainment"
        }
    ],
    "sg:phone":"+61 3 9764 9769",
    "sg:postcode":"3180",
    "sg:province":"VIC",
    "sg:tags":[
        "supply",
        "outdoor",
        "adventure",
        "activity"
    ],
    "wof:name":"Panther Soterion Pty Ltd",
    "wof:placetype":"venue"
},
  "geometry": {"coordinates":[145.25547790499999,-37.8941612244],"type":"Point"}
}