{
  "type": "Feature",
  "properties": {
    "iso:country":"AU",
    "sg:address":"2a Burraneer Ave",
    "sg:city":"St Ives",
    "sg:classifiers":[
        {
            "category":"Education",
            "subcategory":"Kindergarten",
            "type":"Public Place"
        }
    ],
    "sg:phone":"+61 2 9449 3110",
    "sg:postcode":"2075",
    "sg:province":"NSW",
    "sg:tags":[
        "pre-schools"
    ],
    "wof:name":"St Ives Barra-Brui Pre-School",
    "wof:placetype":"venue"
},
  "geometry": {"coordinates":[151.16827392600001,-33.7446975708],"type":"Point"}
}