{
  "type": "Feature",
  "properties": {
    "addr:full":"Unit 3 738 Hodge St Albury NSW 2640",
    "addr:housenumber":"738",
    "addr:postcode":"2640",
    "addr:street":"Hodge St",
    "iso:country":"AU",
    "sg:address":"Unit 3 738 Hodge St",
    "sg:city":"Albury",
    "sg:classifiers":[
        {
            "category":"Building & Trades",
            "subcategory":"Construction",
            "type":"Services"
        }
    ],
    "sg:phone":"+61 2 6025 5657",
    "sg:postcode":"2640",
    "sg:province":"NSW",
    "sg:tags":[
        "contractor"
    ],
    "wof:name":"Koenig Dieter",
    "wof:placetype":"venue"
},
  "geometry": {"coordinates":[146.90765380900001,-36.0622520447],"type":"Point"}
}