{
  "type": "Feature",
  "properties": {
    "addr:full":"6708 Mt Lindesay Hwy Gleneagle QLD 4285",
    "addr:housenumber":"6708",
    "addr:postcode":"4285",
    "addr:street":"Mt Lindesay Hwy",
    "iso:country":"AU",
    "sg:address":"6708 Mt Lindesay Hwy",
    "sg:city":"Gleneagle",
    "sg:classifiers":[
        {
            "category":"Retail",
            "subcategory":"Event Space",
            "type":"Services"
        }
    ],
    "sg:phone":"+61 7 5541 4366",
    "sg:postcode":"4285",
    "sg:province":"QLD",
    "sg:tags":[
        "venue",
        "reception",
        "wedding"
    ],
    "wof:name":"Gleneagle Gables",
    "wof:placetype":"venue"
},
  "geometry": {"coordinates":[152.99316400000001,-27.95965],"type":"Point"}
}