{
  "type": "Feature",
  "properties": {
    "iso:country":"AU",
    "sg:address":"32 Upper Havelock St",
    "sg:city":"Smithton",
    "sg:classifiers":[
        {
            "category":"Structure",
            "subcategory":"Bridge",
            "type":"Public Place"
        }
    ],
    "sg:phone":"+61 3 6452 2624",
    "sg:postcode":"7330",
    "sg:province":"TAS",
    "sg:tags":[
        "chainsaw",
        "brushcutters"
    ],
    "wof:name":"Smithton Mowers Forest & Garden",
    "wof:placetype":"venue"
},
  "geometry": {"coordinates":[145.12539699999999,-40.845936],"type":"Point"}
}