{
  "type": "Feature",
  "properties": {
    "addr:full":"1585 Main North Rd Brahma Lodge SA 5109",
    "addr:housenumber":"1585",
    "addr:postcode":"5109",
    "addr:street":"Main North Rd",
    "iso:country":"AU",
    "sg:address":"1585 Main North Rd",
    "sg:city":"Brahma Lodge",
    "sg:classifiers":[
        {
            "category":"Retail",
            "subcategory":"Auto Repair",
            "type":"Services"
        }
    ],
    "sg:phone":"+61 8 8250 3712",
    "sg:postcode":"5109",
    "sg:province":"SA",
    "sg:tags":[
        "muffler",
        "exhaust",
        "system"
    ],
    "wof:name":"Carline Mufflers",
    "wof:placetype":"venue"
},
  "geometry": {"coordinates":[138.660446167,-34.7767868042],"type":"Point"}
}