{
  "type": "Feature",
  "properties": {
    "iso:country":"AU",
    "sg:address":"\"Athlone\" 516 Cow Flat Rd",
    "sg:city":"Georges Plains",
    "sg:classifiers":[
        {
            "category":"Utilities",
            "subcategory":"Cable",
            "type":"Services"
        }
    ],
    "sg:phone":"+61 2 6337 2338",
    "sg:postcode":"2795",
    "sg:province":"NSW",
    "sg:tags":[
        "agricultural",
        "aerial"
    ],
    "wof:name":"Bathurst Agricultural Aviation Pty Ltd",
    "wof:placetype":"venue"
},
  "geometry": {"coordinates":[149.524734497,-33.5625190735],"type":"Point"}
}