{
  "type": "Feature",
  "properties": {
    "addr:full":"156 Barkly St Carlton VIC 3053",
    "addr:housenumber":"156",
    "addr:postcode":"3053",
    "addr:street":"Barkly St",
    "iso:country":"AU",
    "sg:address":"156 Barkly St",
    "sg:city":"Carlton",
    "sg:classifiers":[
        {
            "category":"Health Services",
            "subcategory":"Health Practitioner",
            "type":"Services"
        }
    ],
    "sg:phone":"+61 3 9348 1488",
    "sg:postcode":"3053",
    "sg:province":"VIC",
    "sg:tags":[
        "psychotherapist"
    ],
    "wof:name":"Kantor Anne",
    "wof:placetype":"venue"
},
  "geometry": {"coordinates":[144.97064209000001,-37.8001976013],"type":"Point"}
}