{
  "type": "Feature",
  "properties": {
    "addr:full":"114b Arthur St Wellington NSW 2820",
    "addr:housenumber":"114b",
    "addr:postcode":"2820",
    "addr:street":"Arthur St",
    "iso:country":"AU",
    "sg:address":"114b Arthur St",
    "sg:city":"Wellington",
    "sg:classifiers":[
        {
            "category":"Food & Beverages",
            "subcategory":"Supermarket",
            "type":"Retail Goods"
        }
    ],
    "sg:phone":"+61 2 6845 3035",
    "sg:postcode":"2820",
    "sg:province":"NSW",
    "sg:tags":[
        "grocery",
        "store"
    ],
    "wof:name":"School Shop",
    "wof:placetype":"venue"
},
  "geometry": {"coordinates":[148.946807861,-32.5450592041],"type":"Point"}
}