{
  "type": "Feature",
  "properties": {
    "addr:full":"3A 280 Newmarket Rd Wilston QLD 4051",
    "addr:housenumber":"3a 280",
    "addr:postcode":"4051",
    "addr:street":"Newmarket Rd",
    "iso:country":"AU",
    "sg:address":"3A 280 Newmarket Rd",
    "sg:city":"Wilston",
    "sg:classifiers":[
        {
            "category":"Home & Garden",
            "subcategory":"Building Materials",
            "type":"Retail Goods"
        }
    ],
    "sg:phone":"+61 7 3857 2121",
    "sg:postcode":"4051",
    "sg:province":"QLD",
    "sg:tags":[
        "ventilating",
        "equipment",
        "system"
    ],
    "wof:name":"Tufftek Building Products Pty Ltd",
    "wof:placetype":"venue"
},
  "geometry": {"coordinates":[153.01531982399999,-27.4359073639],"type":"Point"}
}