{
  "type": "Feature",
  "properties": {
    "iso:country":"AU",
    "sg:address":"24 High St",
    "sg:city":"Charlton",
    "sg:classifiers":[
        {
            "category":"Shopping",
            "subcategory":"Clothing, Apparel, & Fashions",
            "type":"Retail Goods"
        }
    ],
    "sg:phone":"+61 3 5491 1870",
    "sg:postcode":"3525",
    "sg:province":"VIC",
    "sg:tags":[
        "menswear"
    ],
    "wof:name":"Mensland",
    "wof:placetype":"venue"
},
  "geometry": {"coordinates":[143.34887699999999,-36.268173],"type":"Point"}
}