{
  "type": "Feature",
  "properties": {
    "addr:full":"Rear, 21 Toorak Rd South Yarra VIC 3141",
    "addr:housenumber":"21",
    "addr:postcode":"3141",
    "addr:street":"Toorak Rd",
    "iso:country":"AU",
    "sg:address":"Rear, 21 Toorak Rd",
    "sg:city":"South Yarra",
    "sg:classifiers":[
        {
            "category":"Professional",
            "subcategory":"Art Services",
            "type":"Services"
        }
    ],
    "sg:phone":"+61 3 9866 2043",
    "sg:postcode":"3141",
    "sg:province":"VIC",
    "sg:tags":[
        "graphic",
        "designer"
    ],
    "wof:name":"Veign Design",
    "wof:placetype":"venue"
},
  "geometry": {"coordinates":[144.98695373499999,-37.8382339478],"type":"Point"}
}