{
  "type": "Feature",
  "properties": {
    "addr:full":"157 Fenaughty St Kyabram VIC 3620",
    "addr:housenumber":"157",
    "addr:postcode":"3620",
    "addr:street":"Fenaughty St",
    "iso:country":"AU",
    "sg:address":"157 Fenaughty St",
    "sg:city":"Kyabram",
    "sg:classifiers":[
        {
            "category":"Banks & Credit Unions",
            "subcategory":"Bank",
            "type":"Services"
        }
    ],
    "sg:phone":"+61 3 5852 3344",
    "sg:postcode":"3620",
    "sg:province":"VIC",
    "sg:tags":[
        "broker",
        "mortgage"
    ],
    "wof:name":"Banksia Financial Group",
    "wof:placetype":"venue"
},
  "geometry": {"coordinates":[145.04689025900001,-36.3144683838],"type":"Point"}
}