{
  "type": "Feature",
  "properties": {
    "iso:country":"AU",
    "sg:address":"Shop 17, Woodville Park Shopping Centre Warringa C",
    "sg:city":"Hoppers Crossing",
    "sg:classifiers":[
        {
            "category":"Personal",
            "subcategory":"Beauty Salon",
            "type":"Services"
        }
    ],
    "sg:phone":"+61 3 9749 4237",
    "sg:postcode":"3029",
    "sg:province":"VIC",
    "sg:tags":[
        "hairdresser"
    ],
    "wof:name":"Cutting Edge Hairdressing, Williamstown & Woodville",
    "wof:placetype":"venue"
},
  "geometry": {"coordinates":[144.689606,-37.880165],"type":"Point"}
}