{
  "type": "Feature",
  "properties": {
    "iso:country":"AU",
    "sg:address":"192 Koroit St",
    "sg:city":"Warrnambool",
    "sg:classifiers":[
        {
            "category":"Banks & Credit Unions",
            "subcategory":"Investment Brokerage",
            "type":"Services"
        }
    ],
    "sg:phone":"+61 3 5561 5180",
    "sg:postcode":"3280",
    "sg:province":"VIC",
    "wof:name":"Ambleside Financial Planning",
    "wof:placetype":"venue"
},
  "geometry": {"coordinates":[142.47958374000001,-38.3816223145],"type":"Point"}
}