{
  "type": "Feature",
  "properties": {
    "addr:full":"9 Millhouse Rd Longley TAS 7150",
    "addr:housenumber":"9",
    "addr:postcode":"7150",
    "addr:street":"Millhouse Rd",
    "iso:country":"AU",
    "sg:address":"9 Millhouse Rd",
    "sg:city":"Longley",
    "sg:classifiers":[
        {
            "category":"Utilities",
            "subcategory":"Water",
            "type":"Services"
        }
    ],
    "sg:phone":"+61 3 6239 6461",
    "sg:postcode":"7150",
    "sg:province":"TAS",
    "sg:tags":[
        "cartage"
    ],
    "wof:name":"Wellington Water Cartage",
    "wof:placetype":"venue"
},
  "geometry": {"coordinates":[147.19563293499999,-42.9704093933],"type":"Point"}
}