{
  "type": "Feature",
  "properties": {
    "addr:full":"298b Railway Pde Cannington WA 6107",
    "addr:housenumber":"298b",
    "addr:postcode":"6107",
    "addr:street":"Railway Pde",
    "iso:country":"AU",
    "sg:address":"298b Railway Pde",
    "sg:city":"Cannington",
    "sg:classifiers":[
        {
            "category":"Food & Beverages",
            "subcategory":"Groceries & Convenience Stores",
            "type":"Retail Goods"
        }
    ],
    "sg:phone":"+61 8 9458 7536",
    "sg:postcode":"6107",
    "sg:province":"WA",
    "wof:name":"Cannington General Store",
    "wof:placetype":"venue"
},
  "geometry": {"coordinates":[115.949867248,-32.0173568726],"type":"Point"}
}