{
  "type": "Feature",
  "properties": {
    "iso:country":"AU",
    "sg:address":"142 Koornang Rd",
    "sg:city":"Carnegie",
    "sg:classifiers":[
        {
            "category":"Retail",
            "subcategory":"Self-service Laundry",
            "type":"Services"
        }
    ],
    "sg:phone":"+61 3 9569 7823",
    "sg:postcode":"3163",
    "sg:province":"VIC",
    "wof:name":"Koornang Road Coin Laundrette",
    "wof:placetype":"venue"
},
  "geometry": {"coordinates":[145.05731201200001,-37.8888168335],"type":"Point"}
}