{
  "type": "Feature",
  "properties": {
    "iso:country":"AU",
    "sg:address":"298A Grange Rd",
    "sg:city":"Flinders Park",
    "sg:classifiers":[
        {
            "category":"Wholesale",
            "subcategory":"Home Furnishings",
            "type":"Manufacturing & Wholesale Goods"
        }
    ],
    "sg:phone":"+61 8 8351 8183",
    "sg:postcode":"5025",
    "sg:province":"SA",
    "sg:tags":[
        "wholesaler",
        "curtain",
        "mfrs"
    ],
    "wof:name":"Julan Soft Furnishings",
    "wof:placetype":"venue"
},
  "geometry": {"coordinates":[138.53326415999999,-34.9054527283],"type":"Point"}
}