{
  "type": "Feature",
  "properties": {
    "iso:country":"AU",
    "sg:address":"Lot 6 Evans St",
    "sg:city":"Inverell",
    "sg:classifiers":[
        {
            "category":"Retail",
            "subcategory":"Repair Shop",
            "type":"Services"
        }
    ],
    "sg:phone":"+61 2 6721 0389",
    "sg:postcode":"2360",
    "sg:province":"NSW",
    "sg:tags":[
        "leadlights"
    ],
    "wof:name":"Hills Leadlights",
    "wof:placetype":"venue"
},
  "geometry": {"coordinates":[151.11991882300001,-29.7709674835],"type":"Point"}
}