{
  "type": "Feature",
  "properties": {
    "addr:full":"5 Greg Jabs Crt Garbutt QLD 4814",
    "addr:housenumber":"5",
    "addr:postcode":"4814",
    "addr:street":"Greg Jabs Crt",
    "iso:country":"AU",
    "sg:address":"5 Greg Jabs Crt",
    "sg:city":"Garbutt",
    "sg:classifiers":[
        {
            "category":"Government",
            "subcategory":"Department Of Motor Vehicles",
            "type":"Public Place"
        }
    ],
    "sg:phone":"+61 7 4775 7227",
    "sg:postcode":"4814",
    "sg:province":"QLD",
    "sg:tags":[
        "wholesaler",
        "mfrs",
        "accessory"
    ],
    "wof:name":"Suparax Roof Racks",
    "wof:placetype":"venue"
},
  "geometry": {"coordinates":[146.75563,-19.273949],"type":"Point"}
}