{
  "type": "Feature",
  "properties": {
    "addr:full":"14 Kennedy Ave Wagga Wagga NSW 2650",
    "addr:housenumber":"14",
    "addr:postcode":"2650",
    "addr:street":"Kennedy Ave",
    "iso:country":"AU",
    "sg:address":"14 Kennedy Ave",
    "sg:city":"Wagga Wagga",
    "sg:classifiers":[
        {
            "category":"Professional",
            "subcategory":"Management & Consulting",
            "type":"Services"
        }
    ],
    "sg:phone":"+61 2 6922 3429",
    "sg:postcode":"2650",
    "sg:province":"NSW",
    "sg:tags":[
        "consultant",
        "business"
    ],
    "wof:name":"Business Thinking Systems",
    "wof:placetype":"venue"
},
  "geometry": {"coordinates":[147.37017822300001,-35.1491203308],"type":"Point"}
}