{
  "type": "Feature",
  "properties": {
    "iso:country":"AU",
    "sg:address":"213 Condamine St",
    "sg:city":"Balgowlah",
    "sg:classifiers":[
        {
            "category":"Retail",
            "subcategory":"Repair Shop",
            "type":"Services"
        }
    ],
    "sg:phone":"+61 2 9948 5639",
    "sg:postcode":"2093",
    "sg:province":"NSW",
    "sg:tags":[
        "machine",
        "sewing"
    ],
    "wof:name":"A.M. Industrial Sewing Machines Pty Ltd",
    "wof:placetype":"venue"
},
  "geometry": {"coordinates":[151.26510620100001,-33.7923851013],"type":"Point"}
}