{
  "type": "Feature",
  "properties": {
    "addr:full":"22 Nile St Port Adelaide SA 5015",
    "addr:housenumber":"22",
    "addr:postcode":"5015",
    "addr:street":"Nile St",
    "iso:country":"AU",
    "sg:address":"22 Nile St",
    "sg:city":"Port Adelaide",
    "sg:classifiers":[
        {
            "category":"Professional",
            "subcategory":"Accounting & Tax Preparation",
            "type":"Services"
        }
    ],
    "sg:phone":"+61 8 8447 2088",
    "sg:postcode":"5015",
    "sg:province":"SA",
    "sg:tags":[
        "accountant",
        "auditor"
    ],
    "wof:name":"Panou Nitsa",
    "wof:placetype":"venue"
},
  "geometry": {"coordinates":[138.50198364299999,-34.8444404602],"type":"Point"}
}