{
  "type": "Feature",
  "properties": {
    "iso:country":"AU",
    "sg:address":"U3, 42",
    "sg:city":"Quarry Way Mandurah",
    "sg:classifiers":[
        {
            "category":"Social Services",
            "subcategory":"Adult Care",
            "type":"Services"
        }
    ],
    "sg:phone":"+61 416 031 170",
    "sg:postcode":"6210",
    "sg:province":"WA",
    "sg:tags":[
        "towing"
    ],
    "wof:name":"Mandurah Auto Recovery",
    "wof:placetype":"venue"
},
  "geometry": {"coordinates":[115.75340300000001,-32.514648],"type":"Point"}
}