{
  "type": "Feature",
  "properties": {
    "addr:full":"3/ 205 Merrylands Rd Merrylands NSW 2160",
    "addr:housenumber":"/ 205",
    "addr:postcode":"2160",
    "addr:street":"Merrylands Rd",
    "iso:country":"AU",
    "sg:address":"3/ 205 Merrylands Rd",
    "sg:city":"Merrylands",
    "sg:classifiers":[
        {
            "category":"Health Services",
            "subcategory":"Optometrist",
            "type":"Services"
        }
    ],
    "sg:phone":"+61 2 9637 7965",
    "sg:postcode":"2160",
    "sg:province":"NSW",
    "wof:name":"Novo Marcel",
    "wof:placetype":"venue"
},
  "geometry": {"coordinates":[150.98907470699999,-33.836151123],"type":"Point"}
}