{
  "type": "Feature",
  "properties": {
    "addr:full":"16 Strong St Warrnambool VIC 3280",
    "addr:housenumber":"16",
    "addr:postcode":"3280",
    "addr:street":"Strong St",
    "iso:country":"AU",
    "sg:address":"16 Strong St",
    "sg:city":"Warrnambool",
    "sg:classifiers":[
        {
            "category":"Building & Trades",
            "subcategory":"Construction",
            "type":"Services"
        }
    ],
    "sg:phone":"+61 408 529 733",
    "sg:postcode":"3280",
    "sg:province":"VIC",
    "sg:tags":[
        "scaffolding"
    ],
    "wof:name":"West Vic Scaffolding",
    "wof:placetype":"venue"
},
  "geometry": {"coordinates":[142.458984375,-38.3768348694],"type":"Point"}
}