{
  "type": "Feature",
  "properties": {
    "iso:country":"AU",
    "sg:address":"26 William St",
    "sg:city":"Devonport",
    "sg:classifiers":[
        {
            "category":"Health Services",
            "subcategory":"Doctor",
            "type":"Services"
        }
    ],
    "sg:phone":"+61 3 6424 8182",
    "sg:postcode":"7310",
    "sg:province":"TAS",
    "sg:tags":[
        "podiatrist"
    ],
    "wof:name":"Devonport Podiatry Clinic",
    "wof:placetype":"venue"
},
  "geometry": {"coordinates":[146.3487854,-41.187084198],"type":"Point"}
}