{
  "type": "Feature",
  "properties": {
    "iso:country":"AU",
    "sg:address":"Gannons Rd",
    "sg:city":"Caringbah",
    "sg:classifiers":[
        {
            "category":"Government",
            "subcategory":"City Hall",
            "type":"Public Place"
        }
    ],
    "sg:phone":"+61 2 9710 0682",
    "sg:postcode":"2229",
    "sg:province":"NSW",
    "wof:name":"Port Hacking Community Centre",
    "wof:placetype":"venue"
},
  "geometry": {"coordinates":[151.13302612300001,-34.0451545715],"type":"Point"}
}