{
  "type": "Feature",
  "properties": {
    "addr:full":"6/ 109 President St Welshpool WA 6106",
    "addr:housenumber":"/ 109",
    "addr:postcode":"6106",
    "addr:street":"President St",
    "iso:country":"AU",
    "sg:address":"6/ 109 President St",
    "sg:city":"Welshpool",
    "sg:classifiers":[
        {
            "category":"Building & Trades",
            "subcategory":"Construction",
            "type":"Services"
        }
    ],
    "sg:phone":"+61 8 9470 6462",
    "sg:postcode":"6106",
    "sg:province":"WA",
    "sg:tags":[
        "welding"
    ],
    "wof:name":"NTK Cast Iron Welding",
    "wof:placetype":"venue"
},
  "geometry": {"coordinates":[115.930358887,-31.9834747314],"type":"Point"}
}