{
  "type": "Feature",
  "properties": {
    "addr:full":"Lvl 10/ 140 Queen St Melbourne VIC 3000",
    "addr:housenumber":"/ 140",
    "addr:postcode":"3000",
    "addr:street":"Queen St",
    "iso:country":"AU",
    "sg:address":"Lvl 10/ 140 Queen St",
    "sg:city":"Melbourne",
    "sg:classifiers":[
        {
            "category":"Education",
            "subcategory":"University",
            "type":"Public Place"
        }
    ],
    "sg:phone":"+61 3 9670 7801",
    "sg:postcode":"3000",
    "sg:province":"VIC",
    "sg:tags":[
        "educational",
        "organisation",
        "cultural"
    ],
    "wof:name":"Nova Institute Of Technology",
    "wof:placetype":"venue"
},
  "geometry": {"coordinates":[144.961013794,-37.8153076172],"type":"Point"}
}