{
  "type": "Feature",
  "properties": {
    "addr:full":"Eagles La Koraleigh NSW 2735",
    "addr:postcode":"2735",
    "addr:street":"Eagles La Koraleigh",
    "iso:country":"AU",
    "sg:address":"Eagles La",
    "sg:city":"Koraleigh",
    "sg:classifiers":[
        {
            "category":"Utilities",
            "subcategory":"Natural Gas",
            "type":"Services"
        }
    ],
    "sg:phone":"+61 3 5030 2659",
    "sg:postcode":"2735",
    "sg:province":"NSW",
    "sg:tags":[
        "supplier"
    ],
    "wof:name":"Nyah District Gas Supplies Pty Ltd",
    "wof:placetype":"venue"
},
  "geometry": {"coordinates":[143.429993,-35.157566],"type":"Point"}
}