{
  "type": "Feature",
  "properties": {
    "iso:country":"AU",
    "sg:address":"16 Hertford St",
    "sg:city":"Upper Mt Gravatt",
    "sg:classifiers":[
        {
            "category":"Shopping",
            "type":"Retail Goods"
        }
    ],
    "sg:phone":"+61 7 3219 4173",
    "sg:postcode":"4122",
    "sg:province":"QLD",
    "sg:tags":[
        "supply",
        "religious",
        "church"
    ],
    "wof:name":"JCNME",
    "wof:placetype":"venue"
},
  "geometry": {"coordinates":[153.07992553700001,-27.5509586334],"type":"Point"}
}