{
  "type": "Feature",
  "properties": {
    "iso:country":"AU",
    "sg:address":"22 Tyne St",
    "sg:city":"Carlton",
    "sg:classifiers":[
        {
            "category":"Professional",
            "subcategory":"Art Services",
            "type":"Services"
        }
    ],
    "sg:phone":"+61 3 9349 1013",
    "sg:postcode":"3053",
    "sg:province":"VIC",
    "sg:tags":[
        "graphic",
        "designer"
    ],
    "wof:name":"Grafico",
    "wof:placetype":"venue"
},
  "geometry": {"coordinates":[144.96661376899999,-37.7977752686],"type":"Point"}
}