{
  "type": "Feature",
  "properties": {
    "iso:country":"AU",
    "sg:address":"34 Widgee Ave",
    "sg:city":"Banora Point",
    "sg:classifiers":[
        {
            "category":"Military Area",
            "subcategory":"Army Base",
            "type":"Public Place"
        }
    ],
    "sg:phone":"+61 7 5523 9802",
    "sg:postcode":"2486",
    "sg:province":"NSW",
    "sg:tags":[
        "concrete",
        "slab",
        "floor"
    ],
    "wof:name":"Green's Concrete Construction",
    "wof:placetype":"venue"
},
  "geometry": {"coordinates":[153.54461669899999,-28.2185306549],"type":"Point"}
}