{
  "type": "Feature",
  "properties": {
    "iso:country":"AU",
    "sg:address":"100 King St",
    "sg:city":"Newtown",
    "sg:classifiers":[
        {
            "category":"Food & Beverages",
            "subcategory":"Groceries & Convenience Stores",
            "type":"Retail Goods"
        }
    ],
    "sg:phone":"+61 2 9516 1421",
    "sg:postcode":"2042",
    "sg:province":"NSW",
    "wof:name":"Newtown Convenience Store",
    "wof:placetype":"venue"
},
  "geometry": {"coordinates":[151.184387,-33.893234],"type":"Point"}
}