{
  "type": "Feature",
  "properties": {
    "iso:country":"AU",
    "sg:address":"PO Box 111",
    "sg:city":"Cobbitty",
    "sg:classifiers":[
        {
            "category":"Building & Trades",
            "subcategory":"Construction",
            "type":"Services"
        }
    ],
    "sg:phone":"+61 1300 788 363",
    "sg:postcode":"2570",
    "sg:province":"NSW",
    "sg:tags":[
        "contractor"
    ],
    "wof:name":"GHI Solutions",
    "wof:placetype":"venue"
},
  "geometry": {"coordinates":[150.687255859,-34.0154190063],"type":"Point"}
}