{
  "type": "Feature",
  "properties": {
    "addr:full":"80 Fullarton Rd Norwood SA 5067",
    "addr:housenumber":"80",
    "addr:postcode":"5067",
    "addr:street":"Fullarton Rd",
    "iso:country":"AU",
    "sg:address":"80 Fullarton Rd",
    "sg:city":"Norwood",
    "sg:classifiers":[
        {
            "category":"Health Services",
            "subcategory":"Nursing And Care Facility",
            "type":"Services"
        }
    ],
    "sg:phone":"+61 8 8362 6500",
    "sg:postcode":"5067",
    "sg:province":"SA",
    "sg:tags":[
        "home"
    ],
    "sg:website":"http://www.padmanhealthcare.com.au",
    "wof:name":"Padman Health Care",
    "wof:placetype":"venue"
},
  "geometry": {"coordinates":[138.62348938,-34.9235115051],"type":"Point"}
}