{
  "type": "Feature",
  "properties": {
    "addr:full":"56 Fitchett St Garran ACT 2605",
    "addr:housenumber":"56",
    "addr:postcode":"2605",
    "addr:street":"Fitchett St",
    "iso:country":"AU",
    "sg:address":"56 Fitchett St",
    "sg:city":"Garran",
    "sg:classifiers":[
        {
            "category":"Real Estate",
            "subcategory":"Architect",
            "type":"Services"
        }
    ],
    "sg:phone":"+61 2 6281 2864",
    "sg:postcode":"2605",
    "sg:province":"ACT",
    "wof:name":"Stuart Davies Architect Pty Ltd",
    "wof:placetype":"venue"
},
  "geometry": {"coordinates":[149.09886169399999,-35.3404006958],"type":"Point"}
}