{
  "type": "Feature",
  "properties": {
    "addr:full":"1 Flemington Rd North Melbourne VIC 3051",
    "addr:housenumber":"1",
    "addr:postcode":"3051",
    "addr:street":"Flemington Rd",
    "iso:country":"AU",
    "sg:address":"1 Flemington Rd",
    "sg:city":"North Melbourne",
    "sg:classifiers":[
        {
            "category":"Travel",
            "subcategory":"Hotels & Motels",
            "type":"Entertainment"
        }
    ],
    "sg:phone":"+61 3 9329 6942",
    "sg:postcode":"3051",
    "sg:province":"VIC",
    "sg:tags":[
        "pub"
    ],
    "wof:name":"Turf Club Bar & Cafe",
    "wof:placetype":"venue"
},
  "geometry": {"coordinates":[144.95648193400001,-37.8011817932],"type":"Point"}
}