{
  "type": "Feature",
  "properties": {
    "iso:country":"AU",
    "sg:address":"20 Kurrajong Rd St",
    "sg:city":"Marys",
    "sg:classifiers":[
        {
            "category":"Retail",
            "subcategory":"Auto Repair",
            "type":"Services"
        }
    ],
    "sg:phone":"+61 2 9833 4855",
    "sg:postcode":"2760",
    "sg:province":"NSW",
    "sg:tags":[
        "beater",
        "painter",
        "panel"
    ],
    "wof:name":"Frank Costa Spray Painting/Smash Repairs",
    "wof:placetype":"venue"
},
  "geometry": {"coordinates":[150.78436279300001,-33.7607955933],"type":"Point"}
}