{
  "type": "Feature",
  "properties": {
    "addr:full":"Suite 1 Windich House 58 Windich St Esperance WA 6450",
    "addr:housenumber":"58",
    "addr:postcode":"6450",
    "addr:street":"Windich St",
    "iso:country":"AU",
    "sg:address":"Suite 1 Windich House 58 Windich St",
    "sg:city":"Esperance",
    "sg:classifiers":[
        {
            "category":"Banks & Credit Unions",
            "subcategory":"Financial Services",
            "type":"Services"
        }
    ],
    "sg:phone":"+61 8 9071 5833",
    "sg:postcode":"6450",
    "sg:province":"WA",
    "sg:tags":[
        "planning"
    ],
    "wof:name":"Hudson & Co",
    "wof:placetype":"venue"
},
  "geometry": {"coordinates":[121.89457702599999,-33.856388092],"type":"Point"}
}