{
  "type": "Feature",
  "properties": {
    "addr:full":"Level 1 Suite 8, 42 Parkside Crs Campbelltown NSW 2560",
    "addr:housenumber":"42",
    "addr:postcode":"2560",
    "addr:street":"Parkside Crs",
    "iso:country":"AU",
    "sg:address":"Level 1 Suite 8, 42 Parkside Crs",
    "sg:city":"Campbelltown",
    "sg:classifiers":[
        {
            "category":"Health Services",
            "subcategory":"Health Practitioner",
            "type":"Services"
        }
    ],
    "sg:phone":"+61 2 4620 4511",
    "sg:postcode":"2560",
    "sg:province":"NSW",
    "sg:tags":[
        "physiotherapist"
    ],
    "wof:name":"Park Central Physiotherapy",
    "wof:placetype":"venue"
},
  "geometry": {"coordinates":[150.81658935600001,-34.0640983582],"type":"Point"}
}