{
  "type": "Feature",
  "properties": {
    "iso:country":"AU",
    "sg:address":"Brisbane Square, 244-266 George St",
    "sg:city":"Brisbane",
    "sg:classifiers":[
        {
            "category":"Travel",
            "subcategory":"Travel Agent",
            "type":"Entertainment"
        }
    ],
    "sg:phone":"+61 7 3210 0460",
    "sg:postcode":"4000",
    "sg:province":"QLD",
    "sg:tags":[
        "consultant"
    ],
    "wof:name":"Escape Travel",
    "wof:placetype":"venue"
},
  "geometry": {"coordinates":[153.022415161,-27.4699668884],"type":"Point"}
}