{
  "type": "Feature",
  "properties": {
    "addr:full":"Cnr Beach Rd & Campbell Pde Bondi Beach NSW 2026",
    "addr:postcode":"2026",
    "addr:street":"Cnr Beach Rd & Campbell Pde",
    "iso:country":"AU",
    "sg:address":"Cnr Beach Rd & Campbell Pde",
    "sg:city":"Bondi Beach",
    "sg:classifiers":[
        {
            "category":"Retail",
            "subcategory":"Event Space",
            "type":"Services"
        }
    ],
    "sg:phone":"+61 2 9365 5666",
    "sg:postcode":"2026",
    "sg:province":"NSW",
    "sg:tags":[
        "venue",
        "reception",
        "wedding"
    ],
    "wof:name":"Swiss-Grand Resort & Spa",
    "wof:placetype":"venue"
},
  "geometry": {"coordinates":[151.27653503400001,-33.8891868591],"type":"Point"}
}