{
  "type": "Feature",
  "properties": {
    "iso:country":"AU",
    "sg:address":"770 Waverley Rd",
    "sg:city":"Mt Waverley",
    "sg:classifiers":[
        {
            "category":"Home & Garden",
            "subcategory":"Building Materials",
            "type":"Retail Goods"
        }
    ],
    "sg:phone":"+61 3 9562 5464",
    "sg:postcode":"3149",
    "sg:province":"VIC",
    "sg:tags":[
        "merchant",
        "glass",
        "glazier"
    ],
    "wof:name":"A. Aaablet Glass",
    "wof:placetype":"venue"
},
  "geometry": {"coordinates":[145.16891479500001,-37.8895072937],"type":"Point"}
}