{
  "type": "Feature",
  "properties": {
    "addr:full":"Level 7 99 William St Melbourne VIC 3000",
    "addr:housenumber":"99",
    "addr:postcode":"3000",
    "addr:street":"William St",
    "iso:country":"AU",
    "sg:address":"Level 7 99 William St",
    "sg:city":"Melbourne",
    "sg:classifiers":[
        {
            "category":"Professional",
            "subcategory":"Computer Services",
            "type":"Services"
        }
    ],
    "sg:phone":"+61 3 9914 2100",
    "sg:postcode":"3000",
    "sg:province":"VIC",
    "sg:tags":[
        "tele-communications",
        "consultant"
    ],
    "wof:name":"Ethan Direct",
    "wof:placetype":"venue"
},
  "geometry": {"coordinates":[144.96864318900001,-37.8105506897],"type":"Point"}
}