{
  "type": "Feature",
  "properties": {
    "addr:full":"70 Crestwood Drv Baulkham Hills NSW 2153",
    "addr:housenumber":"70",
    "addr:postcode":"2153",
    "addr:street":"Crestwood Drv",
    "iso:country":"AU",
    "sg:address":"70 Crestwood Drv",
    "sg:city":"Baulkham Hills",
    "sg:classifiers":[
        {
            "category":"Professional",
            "subcategory":"Art Services",
            "type":"Services"
        }
    ],
    "sg:phone":"+61 2 9624 2836",
    "sg:postcode":"2153",
    "sg:province":"NSW",
    "sg:tags":[
        "decorator",
        "painter"
    ],
    "wof:name":"Aria Painting & Improvements",
    "wof:placetype":"venue"
},
  "geometry": {"coordinates":[150.96856689399999,-33.7405319214],"type":"Point"}
}