{
  "type": "Feature",
  "properties": {
    "iso:country":"AU",
    "sg:address":"Shop 6 Walnut St",
    "sg:city":"Whittlesea",
    "sg:classifiers":[
        {
            "category":"Personal",
            "subcategory":"Beauty Salon",
            "type":"Services"
        }
    ],
    "sg:phone":"+61 3 9716 2900",
    "sg:postcode":"3757",
    "sg:province":"VIC",
    "wof:name":"Beauty On Walnut",
    "wof:placetype":"venue"
},
  "geometry": {"coordinates":[145.11930799999999,-37.512177],"type":"Point"}
}