{
  "type": "Feature",
  "properties": {
    "addr:full":"36 Hanson Rd Gladstone QLD 4680",
    "addr:housenumber":"36",
    "addr:postcode":"4680",
    "addr:street":"Hanson Rd",
    "iso:country":"AU",
    "sg:address":"36 Hanson Rd",
    "sg:city":"Gladstone",
    "sg:classifiers":[
        {
            "category":"Wholesale",
            "subcategory":"Home Furnishings",
            "type":"Manufacturing & Wholesale Goods"
        }
    ],
    "sg:phone":"+61 7 4972 2191",
    "sg:postcode":"4680",
    "sg:province":"QLD",
    "wof:name":"Simply Solid Timber Furniture",
    "wof:placetype":"venue"
},
  "geometry": {"coordinates":[151.21072387699999,-23.8458175659],"type":"Point"}
}