{
  "type": "Feature",
  "properties": {
    "addr:full":"516 Dorset Rd Croydon South VIC 3136",
    "addr:housenumber":"516",
    "addr:postcode":"3136",
    "addr:street":"Dorset Rd",
    "iso:country":"AU",
    "sg:address":"516 Dorset Rd",
    "sg:city":"Croydon South",
    "sg:classifiers":[
        {
            "category":"Health Services",
            "subcategory":"Doctor",
            "type":"Services"
        }
    ],
    "sg:phone":"+61 3 9725 1866",
    "sg:postcode":"3136",
    "sg:province":"VIC",
    "sg:tags":[
        "medical",
        "practitioner"
    ],
    "wof:name":"Vanderzeil Johann Dr",
    "wof:placetype":"venue"
},
  "geometry": {"coordinates":[145.28741455100001,-37.8164863586],"type":"Point"}
}