{
  "type": "Feature",
  "properties": {
    "addr:full":"152a Waterloo Rd Greenacre NSW 2190",
    "addr:housenumber":"152a",
    "addr:postcode":"2190",
    "addr:street":"Waterloo Rd",
    "iso:country":"AU",
    "sg:address":"152a Waterloo Rd",
    "sg:city":"Greenacre",
    "sg:classifiers":[
        {
            "category":"Health Services",
            "subcategory":"Dentist",
            "type":"Services"
        }
    ],
    "sg:phone":"+61 2 9759 6033",
    "sg:postcode":"2190",
    "sg:province":"NSW",
    "wof:name":"Bagdon V G",
    "wof:placetype":"venue"
},
  "geometry": {"coordinates":[151.05822800000001,-33.901901],"type":"Point"}
}