{
  "type": "Feature",
  "properties": {
    "addr:full":"Suite 304 Lvl 3/185 San Clinic Fox Valley Rd Wahroonga NSW 2076",
    "addr:housenumber":"/ 185",
    "addr:postcode":"2076",
    "addr:street":"Fox Valley Rd",
    "iso:country":"AU",
    "sg:address":"Suite 304 Lvl 3/185 San Clinic Fox Valley Rd",
    "sg:city":"Wahroonga",
    "sg:classifiers":[
        {
            "category":"Health Services",
            "subcategory":"Doctor",
            "type":"Services"
        }
    ],
    "sg:phone":"+61 2 9680 3585",
    "sg:postcode":"2076",
    "sg:province":"NSW",
    "sg:tags":[
        "medical",
        "practitioner"
    ],
    "wof:name":"Butler Donald L",
    "wof:placetype":"venue"
},
  "geometry": {"coordinates":[151.11871337900001,-33.727645874],"type":"Point"}
}