{
  "type": "Feature",
  "properties": {
    "iso:country":"AU",
    "sg:address":"22 Briggs St",
    "sg:city":"Camperdown",
    "sg:classifiers":[
        {
            "category":"Manufacturing",
            "subcategory":"Chemicals & Compounds",
            "type":"Manufacturing & Wholesale Goods"
        }
    ],
    "sg:phone":"+61 2 9519 7614",
    "sg:postcode":"2050",
    "sg:province":"NSW",
    "sg:tags":[
        "electroplating"
    ],
    "wof:name":"Armen Plating Pty Ltd",
    "wof:placetype":"venue"
},
  "geometry": {"coordinates":[151.178436,-33.887894],"type":"Point"}
}