{
  "type": "Feature",
  "properties": {
    "iso:country":"AU",
    "sg:address":"PO Box 1148",
    "sg:city":"West Perth",
    "sg:classifiers":[
        {
            "category":"Professional",
            "type":"Services"
        }
    ],
    "sg:phone":"+61 418 922 900",
    "sg:postcode":"6872",
    "sg:province":"WA",
    "sg:tags":[
        "quality",
        "assurance"
    ],
    "wof:name":"MTS Business Development And Training Group",
    "wof:placetype":"venue"
},
  "geometry": {"coordinates":[115.84382600000001,-31.95055],"type":"Point"}
}