{
  "type": "Feature",
  "properties": {
    "addr:full":"Lot4/ Steinohrts Rd Dalby QLD 4405",
    "addr:postcode":"4405",
    "addr:street":"Steinohrts Rd",
    "iso:country":"AU",
    "sg:address":"Lot4/ Steinohrts Rd",
    "sg:city":"Dalby",
    "sg:classifiers":[
        {
            "category":"Building & Trades",
            "subcategory":"Plumbing",
            "type":"Services"
        }
    ],
    "sg:phone":"+61 7 4668 1959",
    "sg:postcode":"4405",
    "sg:province":"QLD",
    "sg:tags":[
        "plumber",
        "gasfitters"
    ],
    "wof:name":"Exon Plumbing",
    "wof:placetype":"venue"
},
  "geometry": {"coordinates":[151.257415772,-27.1783504486],"type":"Point"}
}