{
  "type": "Feature",
  "properties": {
    "addr:full":"605 Burwood Hwy Knoxfield VIC 3180",
    "addr:housenumber":"605",
    "addr:postcode":"3180",
    "addr:street":"Burwood Hwy",
    "iso:country":"AU",
    "sg:address":"605 Burwood Hwy",
    "sg:city":"Knoxfield",
    "sg:classifiers":[
        {
            "category":"Manufacturing",
            "subcategory":"Tools & Machinery",
            "type":"Manufacturing & Wholesale Goods"
        }
    ],
    "sg:phone":"+61 3 9887 4691",
    "sg:postcode":"3180",
    "sg:province":"VIC",
    "sg:tags":[
        "toolmaker"
    ],
    "wof:name":"The Toolroom Pty Ltd",
    "wof:placetype":"venue"
},
  "geometry": {"coordinates":[145.2525177,-37.8741722107],"type":"Point"}
}