{
  "type": "Feature",
  "properties": {
    "addr:full":"15 Seaside Pde North Shore VIC 3214",
    "addr:housenumber":"15",
    "addr:postcode":"3214",
    "addr:street":"Seaside Pde",
    "iso:country":"AU",
    "sg:address":"15 Seaside Pde",
    "sg:city":"North Shore",
    "sg:classifiers":[
        {
            "category":"Manufacturing",
            "subcategory":"Metals",
            "type":"Manufacturing & Wholesale Goods"
        }
    ],
    "sg:phone":"+61 3 5272 1172",
    "sg:postcode":"3214",
    "sg:province":"VIC",
    "sg:tags":[
        "steel",
        "fabricator",
        "mfrs"
    ],
    "wof:name":"Weldfab Applications",
    "wof:placetype":"venue"
},
  "geometry": {"coordinates":[144.36871337900001,-38.0954856873],"type":"Point"}
}