{
  "type": "Feature",
  "properties": {
    "iso:country":"AU",
    "sg:address":"60 McIntyre St",
    "sg:city":"Goondiwindi",
    "sg:classifiers":[
        {
            "category":"Farming",
            "subcategory":"Farm & Veterinary Services",
            "type":"Manufacturing & Wholesale Goods"
        }
    ],
    "sg:phone":"+61 7 4671 2326",
    "sg:postcode":"4390",
    "sg:province":"QLD",
    "sg:tags":[
        "contracting"
    ],
    "wof:name":"Israelite Cotton Picking",
    "wof:placetype":"venue"
},
  "geometry": {"coordinates":[150.311645508,-28.5518741608],"type":"Point"}
}