{
  "type": "Feature",
  "properties": {
    "addr:full":"62- 66 Parfitt Rd Wangaratta VIC 3677",
    "addr:housenumber":"66",
    "addr:postcode":"3677",
    "addr:street":"Parfitt Rd",
    "iso:country":"AU",
    "sg:address":"62- 66 Parfitt Rd",
    "sg:city":"Wangaratta",
    "sg:classifiers":[
        {
            "category":"Autos & Motor Vehicles",
            "subcategory":"Automobile Sales",
            "type":"Retail Goods"
        }
    ],
    "sg:phone":"+61 3 5721 4428",
    "sg:postcode":"3677",
    "sg:province":"VIC",
    "sg:tags":[
        "car",
        "used"
    ],
    "wof:name":"Heffernan Ford",
    "wof:placetype":"venue"
},
  "geometry": {"coordinates":[146.33624267600001,-36.3480262756],"type":"Point"}
}