{
  "type": "Feature",
  "properties": {
    "iso:country":"AU",
    "sg:address":"James Ruse Drv (Cnr River Rd West)",
    "sg:city":"Camellia",
    "sg:phone":"+61 2 9635 1705",
    "sg:postcode":"2142",
    "sg:province":"NSW",
    "wof:name":"Holmwood Highgate",
    "wof:placetype":"venue"
},
  "geometry": {"coordinates":[151.02204895,-33.8186683655],"type":"Point"}
}