{
  "type": "Feature",
  "properties": {
    "addr:full":"10 / 105 Lord St East Perth WA 6004",
    "addr:housenumber":"10 / 105",
    "addr:postcode":"6004",
    "addr:street":"Lord St East",
    "iso:country":"AU",
    "sg:address":"10 / 105 Lord St",
    "sg:city":"East Perth",
    "sg:classifiers":[
        {
            "category":"Professional",
            "subcategory":"Employment Agencies",
            "type":"Services"
        }
    ],
    "sg:phone":"+61 8 9221 7477",
    "sg:postcode":"6004",
    "sg:province":"WA",
    "wof:name":"Sure Personnel",
    "wof:placetype":"venue"
},
  "geometry": {"coordinates":[115.86759948700001,-31.9521503448],"type":"Point"}
}