{
  "type": "Feature",
  "properties": {
    "addr:full":"67 Sutherland Rd Armadale VIC 3143",
    "addr:housenumber":"67",
    "addr:postcode":"3143",
    "addr:street":"Sutherland Rd",
    "iso:country":"AU",
    "sg:address":"67 Sutherland Rd",
    "sg:city":"Armadale",
    "sg:classifiers":[
        {
            "category":"Organizations",
            "subcategory":"Non-profit Organization",
            "type":"Services"
        }
    ],
    "sg:phone":"+61 3 9509 4266",
    "sg:postcode":"3143",
    "sg:province":"VIC",
    "sg:tags":[
        "support",
        "disability",
        "organisation"
    ],
    "wof:name":"Gawith Villa Inc",
    "wof:placetype":"venue"
},
  "geometry": {"coordinates":[145.01724243199999,-37.8559150696],"type":"Point"}
}