{
  "type": "Feature",
  "properties": {
    "addr:full":"Nineteenth St Warragamba NSW 2752",
    "addr:postcode":"2752",
    "addr:street":"Nineteenth St",
    "iso:country":"AU",
    "sg:address":"Nineteenth St",
    "sg:city":"Warragamba",
    "sg:classifiers":[
        {
            "category":"Building & Trades",
            "subcategory":"Construction",
            "type":"Services"
        }
    ],
    "sg:phone":"+61 419 601 226",
    "sg:postcode":"2752",
    "sg:province":"NSW",
    "sg:tags":[
        "contractor"
    ],
    "wof:name":"Shephard A J",
    "wof:placetype":"venue"
},
  "geometry": {"coordinates":[150.603393555,-33.8911170959],"type":"Point"}
}