{
  "type": "Feature",
  "properties": {
    "iso:country":"AU",
    "sg:address":"2/ 169 Grange Rd",
    "sg:city":"Fairfield",
    "sg:classifiers":[
        {
            "category":"Home & Garden",
            "subcategory":"Carpets & Floor Coverings",
            "type":"Retail Goods"
        }
    ],
    "sg:phone":"+61 3 9499 5991",
    "sg:postcode":"3078",
    "sg:province":"VIC",
    "sg:tags":[
        "mat",
        "matting"
    ],
    "wof:name":"Bardwell Safety Matting",
    "wof:placetype":"venue"
},
  "geometry": {"coordinates":[145.02667236299999,-37.7694892883],"type":"Point"}
}