{
  "type": "Feature",
  "properties": {
    "addr:full":"8 Bridge Rd Rochester VIC 3561",
    "addr:housenumber":"8",
    "addr:postcode":"3561",
    "addr:street":"Bridge Rd",
    "iso:country":"AU",
    "sg:address":"8 Bridge Rd",
    "sg:city":"Rochester",
    "sg:classifiers":[
        {
            "category":"Social Services",
            "subcategory":"Child Care",
            "type":"Services"
        }
    ],
    "sg:phone":"+61 3 5484 3303",
    "sg:postcode":"3561",
    "sg:province":"VIC",
    "sg:tags":[
        "breeding",
        "artificial"
    ],
    "wof:name":"Wellbred Genetics",
    "wof:placetype":"venue"
},
  "geometry": {"coordinates":[144.698318481,-36.3600311279],"type":"Point"}
}