{
  "type": "Feature",
  "properties": {
    "iso:country":"AU",
    "sg:address":"22 Tone Rd",
    "sg:city":"Wangaratta",
    "sg:classifiers":[
        {
            "category":"Shopping",
            "subcategory":"Crafts & Fabrics",
            "type":"Retail Goods"
        }
    ],
    "sg:phone":"+61 3 5721 8900",
    "sg:postcode":"3677",
    "sg:province":"VIC",
    "sg:tags":[
        "merchant",
        "cork"
    ],
    "wof:name":"Aggenbachs Carpet Choice",
    "wof:placetype":"venue"
},
  "geometry": {"coordinates":[146.31121826200001,-36.3599128723],"type":"Point"}
}