{
  "type": "Feature",
  "properties": {
    "addr:full":"19 Day St Lansvale NSW 2166",
    "addr:housenumber":"19",
    "addr:postcode":"2166",
    "addr:street":"Day St",
    "iso:country":"AU",
    "sg:address":"19 Day St",
    "sg:city":"Lansvale",
    "sg:classifiers":[
        {
            "category":"Wholesale",
            "subcategory":"Auto Parts",
            "type":"Manufacturing & Wholesale Goods"
        }
    ],
    "sg:phone":"+61 2 9727 5846",
    "sg:postcode":"2166",
    "sg:province":"NSW",
    "sg:tags":[
        "recyclers"
    ],
    "wof:name":"JR Sunrise Pty Ltd",
    "wof:placetype":"venue"
},
  "geometry": {"coordinates":[150.964233398,-33.8953361511],"type":"Point"}
}