{
  "type": "Feature",
  "properties": {
    "addr:full":"Ste 2/ 7 Price St Nerang QLD 4211",
    "addr:housenumber":"7",
    "addr:postcode":"4211",
    "addr:street":"Price St",
    "iso:country":"AU",
    "sg:address":"Ste 2/ 7 Price St",
    "sg:city":"Nerang",
    "sg:classifiers":[
        {
            "category":"Health Services",
            "subcategory":"Health Practitioner",
            "type":"Services"
        }
    ],
    "sg:phone":"+61 7 5502 1382",
    "sg:postcode":"4211",
    "sg:province":"QLD",
    "sg:tags":[
        "acupuncture"
    ],
    "wof:name":"Springwell - Acupuncture, Massage & Chinese Medicine",
    "wof:placetype":"venue"
},
  "geometry": {"coordinates":[153.33692932100001,-27.9884319305],"type":"Point"}
}