{
  "type": "Feature",
  "properties": {
    "iso:country":"AU",
    "sg:address":"23 Blaczland Drv",
    "sg:city":"Dandenong North",
    "sg:classifiers":[
        {
            "category":"Building & Trades",
            "subcategory":"Landscaping Services",
            "type":"Services"
        }
    ],
    "sg:phone":"+61 3 9790 6628",
    "sg:postcode":"3175",
    "sg:province":"VIC",
    "sg:tags":[
        "stump",
        "tree",
        "felling",
        "removal"
    ],
    "wof:name":"Ariel Tree Services",
    "wof:placetype":"venue"
},
  "geometry": {"coordinates":[145.20497131400001,-37.9407920837],"type":"Point"}
}