{
  "type": "Feature",
  "properties": {
    "addr:full":"U1/ 2 Kinwal Crt Moorabbin VIC 3189",
    "addr:postcode":"3189",
    "addr:street":"U1 / 2 Kinwal Crt",
    "iso:country":"AU",
    "sg:address":"U1/ 2 Kinwal Crt",
    "sg:city":"Moorabbin",
    "sg:classifiers":[
        {
            "category":"Wholesale",
            "subcategory":"Chemicals & Plastics",
            "type":"Manufacturing & Wholesale Goods"
        }
    ],
    "sg:phone":"+61 3 9553 2777",
    "sg:postcode":"3189",
    "sg:province":"VIC",
    "sg:tags":[
        "bag"
    ],
    "wof:name":"Cerberus Plastics",
    "wof:placetype":"venue"
},
  "geometry": {"coordinates":[145.052825928,-37.9441642761],"type":"Point"}
}