{
  "type": "Feature",
  "properties": {
    "addr:full":"Grey Gum St Tuncurry NSW 2428",
    "addr:postcode":"2428",
    "addr:street":"Gum St",
    "iso:country":"AU",
    "sg:address":"Grey Gum St",
    "sg:city":"Tuncurry",
    "sg:classifiers":[
        {
            "category":"Home & Garden",
            "subcategory":"Building Materials",
            "type":"Retail Goods"
        }
    ],
    "sg:phone":"+61 2 6554 7572",
    "sg:postcode":"2428",
    "sg:province":"NSW",
    "sg:tags":[
        "pre-mixed",
        "concrete"
    ],
    "wof:name":"Boral Country-Concrete & Quarries",
    "wof:placetype":"venue"
},
  "geometry": {"coordinates":[152.49374399999999,-32.16589],"type":"Point"}
}