{
  "type": "Feature",
  "properties": {
    "iso:country":"AU",
    "sg:address":"49 Railway Rd",
    "sg:city":"Blackburn",
    "sg:classifiers":[
        {
            "category":"Professional",
            "subcategory":"Engineering",
            "type":"Services"
        }
    ],
    "sg:phone":"+61 3 9894 2010",
    "sg:postcode":"3130",
    "sg:province":"VIC",
    "sg:tags":[
        "consulting",
        "engineer"
    ],
    "wof:name":"Mendis ,Hannah & Associates",
    "wof:placetype":"venue"
},
  "geometry": {"coordinates":[145.15187072800001,-37.819694519],"type":"Point"}
}