{
  "type": "Feature",
  "properties": {
    "addr:full":"Unit 7/Paddington Central 107 Latrobe Terrace Paddington QLD 4064",
    "addr:housenumber":"107",
    "addr:postcode":"4064",
    "addr:street":"Latrobe Terrace",
    "iso:country":"AU",
    "sg:address":"Unit 7/Paddington Central 107",
    "sg:city":"Latrobe Terrace Paddington",
    "sg:classifiers":[
        {
            "category":"Internet Cafe",
            "subcategory":"None",
            "type":"Food & Drink"
        }
    ],
    "sg:phone":"+61 7 3369 9077",
    "sg:postcode":"4064",
    "sg:province":"QLD",
    "wof:name":"Computer Cafe The",
    "wof:placetype":"venue"
},
  "geometry": {"coordinates":[152.997756958,-27.4589214325],"type":"Point"}
}