{
  "type": "Feature",
  "properties": {
    "iso:country":"AU",
    "sg:address":"29 Chetwynd St",
    "sg:city":"Loganholme",
    "sg:classifiers":[
        {
            "category":"Home & Garden",
            "subcategory":"Building Materials",
            "type":"Retail Goods"
        }
    ],
    "sg:phone":"+61 7 3801 1630",
    "sg:postcode":"4129",
    "sg:province":"QLD",
    "sg:tags":[
        "fencing"
    ],
    "wof:name":"Fenceforce Loganholme",
    "wof:placetype":"venue"
},
  "geometry": {"coordinates":[153.19004821799999,-27.6790790558],"type":"Point"}
}