{
  "type": "Feature",
  "properties": {
    "addr:full":"194 Abbotsford Rd Bowen Hills QLD 4006",
    "addr:housenumber":"194",
    "addr:postcode":"4006",
    "addr:street":"Abbotsford Rd",
    "iso:country":"AU",
    "sg:address":"194 Abbotsford Rd",
    "sg:city":"Bowen Hills",
    "sg:classifiers":[
        {
            "category":"Retail",
            "subcategory":"Auto Rental",
            "type":"Services"
        }
    ],
    "sg:phone":"+61 7 3252 7400",
    "sg:postcode":"4006",
    "sg:province":"QLD",
    "sg:tags":[
        "car",
        "hire",
        "minibus"
    ],
    "wof:name":"Scotty Car Rentals",
    "wof:placetype":"venue"
},
  "geometry": {"coordinates":[153.040939331,-27.4371376038],"type":"Point"}
}