{
  "type": "Feature",
  "properties": {
    "addr:full":"123 High St Stanthorpe QLD 4380",
    "addr:housenumber":"123",
    "addr:postcode":"4380",
    "addr:street":"High St",
    "iso:country":"AU",
    "sg:address":"123 High St",
    "sg:city":"Stanthorpe",
    "sg:classifiers":[
        {
            "category":"Fast Food",
            "type":"Food & Drink"
        }
    ],
    "sg:phone":"+61 7 4681 3355",
    "sg:postcode":"4380",
    "sg:province":"QLD",
    "sg:tags":[
        "away",
        "take"
    ],
    "wof:name":"Red Rooster Stanthorpe",
    "wof:placetype":"venue"
},
  "geometry": {"coordinates":[151.936554,-28.653929],"type":"Point"}
}