{
  "type": "Feature",
  "properties": {
    "addr:full":"96 Bourke St Woolloomooloo NSW 2011",
    "addr:housenumber":"96",
    "addr:postcode":"2011",
    "addr:street":"Bourke St",
    "iso:country":"AU",
    "sg:address":"96 Bourke St",
    "sg:city":"Woolloomooloo",
    "sg:classifiers":[
        {
            "category":"Professional",
            "subcategory":"Art Services",
            "type":"Services"
        }
    ],
    "sg:phone":"+61 2 9331 0122",
    "sg:postcode":"2011",
    "sg:province":"NSW",
    "sg:tags":[
        "interior",
        "designer"
    ],
    "wof:name":"Barnett Garth Interior Design",
    "wof:placetype":"venue"
},
  "geometry": {"coordinates":[151.218673706,-33.8725242615],"type":"Point"}
}