{
  "type": "Feature",
  "properties": {
    "iso:country":"AU",
    "sg:address":"65 Pacific Hwy",
    "sg:city":"Sandgate",
    "sg:classifiers":[
        {
            "category":"Autos & Motor Vehicles",
            "subcategory":"Automobile Sales",
            "type":"Retail Goods"
        }
    ],
    "sg:phone":"+61 2 4960 2262",
    "sg:postcode":"2304",
    "sg:province":"NSW",
    "sg:tags":[
        "car",
        "used"
    ],
    "wof:name":"Parador Pty Ltd",
    "wof:placetype":"venue"
},
  "geometry": {"coordinates":[151.70443725600001,-32.8602600098],"type":"Point"}
}