{
  "type": "Feature",
  "properties": {
    "addr:full":"6 Bonegilla Rd Griffith NSW 2680",
    "addr:housenumber":"6",
    "addr:postcode":"2680",
    "addr:street":"Bonegilla Rd",
    "iso:country":"AU",
    "sg:address":"6 Bonegilla Rd",
    "sg:city":"Griffith",
    "sg:classifiers":[
        {
            "category":"Wholesale",
            "subcategory":"Painting Supplies",
            "type":"Manufacturing & Wholesale Goods"
        }
    ],
    "sg:phone":"+61 2 6962 6455",
    "sg:postcode":"2680",
    "sg:province":"NSW",
    "sg:tags":[
        "product",
        "cleaning"
    ],
    "wof:name":"Axi-Kem Pty Ltd",
    "wof:placetype":"venue"
},
  "geometry": {"coordinates":[146.053406,-34.289764],"type":"Point"}
}