{
  "type": "Feature",
  "properties": {
    "addr:full":"36 Radford Rd Reservoir VIC 3073",
    "addr:housenumber":"36",
    "addr:postcode":"3073",
    "addr:street":"Radford Rd",
    "iso:country":"AU",
    "sg:address":"36 Radford Rd",
    "sg:city":"Reservoir",
    "sg:classifiers":[
        {
            "category":"Manufacturing",
            "subcategory":"Glass & Minerals",
            "type":"Manufacturing & Wholesale Goods"
        }
    ],
    "sg:phone":"+61 3 9462 1531",
    "sg:postcode":"3073",
    "sg:province":"VIC",
    "sg:tags":[
        "merchant",
        "granite",
        "marble"
    ],
    "wof:name":"Jotomi Pty Ltd",
    "wof:placetype":"venue"
},
  "geometry": {"coordinates":[144.98286438,-37.7097511292],"type":"Point"}
}