{
  "type": "Feature",
  "properties": {
    "addr:full":"Cnr Water & Upward Sts Cairns QLD 4870",
    "addr:postcode":"4870",
    "iso:country":"AU",
    "sg:address":"Cnr Water & Upward Sts",
    "sg:city":"Cairns",
    "sg:classifiers":[
        {
            "category":"Education",
            "subcategory":"Kindergarten",
            "type":"Public Place"
        }
    ],
    "sg:phone":"+61 7 4031 2983",
    "sg:postcode":"4870",
    "sg:province":"QLD",
    "sg:tags":[
        "pre-schools"
    ],
    "wof:name":"Water Street Occasional Child Care",
    "wof:placetype":"venue"
},
  "geometry": {"coordinates":[145.76023864699999,-16.9230518341],"type":"Point"}
}