{
  "type": "Feature",
  "properties": {
    "addr:full":"146 Drayton St Dalby QLD 4405",
    "addr:housenumber":"146",
    "addr:postcode":"4405",
    "addr:street":"Drayton St",
    "iso:country":"AU",
    "sg:address":"146 Drayton St",
    "sg:city":"Dalby",
    "sg:classifiers":[
        {
            "category":"Cafe",
            "type":"Food & Drink"
        }
    ],
    "sg:phone":"+61 7 4662 4841",
    "sg:postcode":"4405",
    "sg:province":"QLD",
    "wof:name":"Racecourse Star Cafe",
    "wof:placetype":"venue"
},
  "geometry": {"coordinates":[151.272018433,-27.192697525],"type":"Point"}
}