{
  "type": "Feature",
  "properties": {
    "iso:country":"AU",
    "sg:address":"336 Anakie Rd",
    "sg:city":"Norlane",
    "sg:classifiers":[
        {
            "category":"Recreation",
            "type":"Entertainment"
        }
    ],
    "sg:phone":"+61 447 796 300",
    "sg:postcode":"3214",
    "sg:province":"VIC",
    "sg:tags":[
        "hire",
        "tour",
        "motor",
        "cycle"
    ],
    "wof:name":"Mates On Bikes - MOB",
    "wof:placetype":"venue"
},
  "geometry": {"coordinates":[144.33644104000001,-38.0863418579],"type":"Point"}
}