{
  "type": "Feature",
  "properties": {
    "iso:country":"AU",
    "sg:address":"449 Springvale Rd",
    "sg:city":"Glen Waverley",
    "sg:classifiers":[
        {
            "category":"Professional",
            "subcategory":"Accounting & Tax Preparation",
            "type":"Services"
        }
    ],
    "sg:phone":"+61 3 9562 0178",
    "sg:postcode":"3150",
    "sg:province":"VIC",
    "sg:tags":[
        "accountant",
        "auditor"
    ],
    "wof:name":"Garbellini Alan G",
    "wof:placetype":"venue"
},
  "geometry": {"coordinates":[145.16285705600001,-37.8946228027],"type":"Point"}
}