{
  "type": "Feature",
  "properties": {
    "addr:full":"165 Drysdale St Ayr QLD 4807",
    "addr:housenumber":"165",
    "addr:postcode":"4807",
    "addr:street":"Drysdale St",
    "iso:country":"AU",
    "sg:address":"165 Drysdale St",
    "sg:city":"Ayr",
    "sg:classifiers":[
        {
            "category":"Professional",
            "subcategory":"Detective & Security Services",
            "type":"Services"
        }
    ],
    "sg:phone":"+61 7 4783 2300",
    "sg:postcode":"4807",
    "sg:province":"QLD",
    "sg:tags":[
        "equipment",
        "window",
        "doors"
    ],
    "wof:name":"Bob Gould Fabrications",
    "wof:placetype":"venue"
},
  "geometry": {"coordinates":[147.40040588400001,-19.5811424255],"type":"Point"}
}