{
  "type": "Feature",
  "properties": {
    "addr:full":"Shed 2/ 19 Lindsay Rd Lonsdale SA 5160",
    "addr:housenumber":"2 / 19",
    "addr:postcode":"5160",
    "addr:street":"Lindsay Rd",
    "iso:country":"AU",
    "sg:address":"Shed 2/ 19 Lindsay Rd",
    "sg:city":"Lonsdale",
    "sg:classifiers":[
        {
            "category":"Manufacturing",
            "subcategory":"Tools & Machinery",
            "type":"Manufacturing & Wholesale Goods"
        }
    ],
    "sg:phone":"+61 8 8322 5833",
    "sg:postcode":"5160",
    "sg:province":"SA",
    "sg:tags":[
        "toolmaker"
    ],
    "wof:name":"Waterhouse General Machining",
    "wof:placetype":"venue"
},
  "geometry": {"coordinates":[138.503295898,-35.1026878357],"type":"Point"}
}