{
  "type": "Feature",
  "properties": {
    "addr:full":"Level 1/ 533 Hay St Perth WA 6000",
    "addr:housenumber":"/ 533",
    "addr:postcode":"6000",
    "addr:street":"Hay St",
    "iso:country":"AU",
    "sg:address":"Level 1/ 533 Hay St",
    "sg:city":"Perth",
    "sg:classifiers":[
        {
            "category":"Professional",
            "subcategory":"Accounting & Tax Preparation",
            "type":"Services"
        }
    ],
    "sg:phone":"+61 8 9221 7444",
    "sg:postcode":"6000",
    "sg:province":"WA",
    "sg:tags":[
        "consultant",
        "taxation"
    ],
    "wof:name":"ZB Accounting and Taxation Service",
    "wof:placetype":"venue"
},
  "geometry": {"coordinates":[115.855529785,-31.9532012939],"type":"Point"}
}