{
  "type": "Feature",
  "properties": {
    "addr:full":"35 Clyde St Parkside SA 5063",
    "addr:housenumber":"35",
    "addr:postcode":"5063",
    "addr:street":"Clyde St",
    "iso:country":"AU",
    "sg:address":"35 Clyde St",
    "sg:city":"Parkside",
    "sg:classifiers":[
        {
            "category":"Health Services",
            "subcategory":"Health Practitioner",
            "type":"Services"
        }
    ],
    "sg:phone":"+61 8 8272 5800",
    "sg:postcode":"5063",
    "sg:province":"SA",
    "sg:tags":[
        "acupuncture"
    ],
    "wof:name":"Morrissey, Anne Marie",
    "wof:placetype":"venue"
},
  "geometry": {"coordinates":[138.607711792,-34.943397522],"type":"Point"}
}