{
  "type": "Feature",
  "properties": {
    "addr:full":"Shop 1, 621 Wynnum Rd Morningside QLD 4170",
    "addr:housenumber":"shop 1",
    "addr:postcode":"621;4170",
    "addr:street":"Wynnum Rd",
    "iso:country":"AU",
    "sg:address":"Shop 1, 621 Wynnum Rd",
    "sg:city":"Morningside",
    "sg:classifiers":[
        {
            "category":"Health Services",
            "subcategory":"Dentist",
            "type":"Services"
        }
    ],
    "sg:phone":"+61 7 3399 7756",
    "sg:postcode":"4170",
    "sg:province":"QLD",
    "wof:name":"Morningside 621 Dental Surgery",
    "wof:placetype":"venue"
},
  "geometry": {"coordinates":[153.071777344,-27.4680747986],"type":"Point"}
}