{
  "type": "Feature",
  "properties": {
    "iso:country":"AU",
    "sg:address":"Unit 3 / 6 99 Moore St",
    "sg:city":"Leichhardt",
    "sg:classifiers":[
        {
            "category":"Professional",
            "type":"Services"
        }
    ],
    "sg:phone":"+61 411 333 911",
    "sg:postcode":"2040",
    "sg:province":"NSW",
    "sg:tags":[
        "packaging",
        "filling",
        "assembling"
    ],
    "wof:name":"Automatic Filing Services",
    "wof:placetype":"venue"
},
  "geometry": {"coordinates":[151.161057,-33.878403],"type":"Point"}
}