{
  "type": "Feature",
  "properties": {
    "iso:country":"AU",
    "sg:address":"1359 Sandgate Rd",
    "sg:city":"Nundah",
    "sg:classifiers":[
        {
            "category":"Health Services",
            "subcategory":"Health Practitioner",
            "type":"Services"
        }
    ],
    "sg:phone":"+61 7 3256 6156",
    "sg:postcode":"4012",
    "sg:province":"QLD",
    "sg:tags":[
        "osteopath"
    ],
    "wof:name":"Osteocare",
    "wof:placetype":"venue"
},
  "geometry": {"coordinates":[153.05914306599999,-27.3996105194],"type":"Point"}
}