{
  "type": "Feature",
  "properties": {
    "iso:country":"AU",
    "sg:address":"113a Hampden Rd",
    "sg:city":"Battery Point",
    "sg:classifiers":[
        {
            "category":"Shopping",
            "subcategory":"Antiques",
            "type":"Retail Goods"
        }
    ],
    "sg:phone":"+61 3 6223 1156",
    "sg:postcode":"7004",
    "sg:province":"TAS",
    "wof:name":"St Georges Antiques",
    "wof:placetype":"venue"
},
  "geometry": {"coordinates":[147.33076477,-42.889251709],"type":"Point"}
}