{
  "type": "Feature",
  "properties": {
    "iso:country":"AU",
    "sg:address":"322 Ruthven St",
    "sg:city":"Toowoomba",
    "sg:classifiers":[
        {
            "category":"Personal",
            "subcategory":"Beauty Salon",
            "type":"Services"
        }
    ],
    "sg:phone":"+61 7 4632 0066",
    "sg:postcode":"4350",
    "sg:province":"QLD",
    "sg:tags":[
        "hairdresser"
    ],
    "wof:name":"Bladez Hair Design",
    "wof:placetype":"venue"
},
  "geometry": {"coordinates":[151.956512,-27.568443],"type":"Point"}
}