{
  "type": "Feature",
  "properties": {
    "addr:full":"Plenty Rd Mernda VIC 3754",
    "addr:postcode":"3754",
    "addr:street":"Plenty Rd",
    "iso:country":"AU",
    "sg:address":"Plenty Rd",
    "sg:city":"Mernda",
    "sg:classifiers":[
        {
            "category":"Travel",
            "subcategory":"Hotels & Motels",
            "type":"Entertainment"
        }
    ],
    "sg:phone":"+61 3 9717 3404",
    "sg:postcode":"3754",
    "sg:province":"VIC",
    "sg:tags":[
        "accommodation"
    ],
    "wof:name":"Bridge Inn Hotel Mernda",
    "wof:placetype":"venue"
},
  "geometry": {"coordinates":[145.1026,-37.589851],"type":"Point"}
}