{
  "type": "Feature",
  "properties": {
    "addr:full":"250 Childs Rd Mill Park VIC 3082",
    "addr:housenumber":"250",
    "addr:postcode":"3082",
    "addr:street":"Childs Rd",
    "iso:country":"AU",
    "sg:address":"250 Childs Rd",
    "sg:city":"Mill Park",
    "sg:classifiers":[
        {
            "category":"Personal",
            "subcategory":"Massage",
            "type":"Services"
        }
    ],
    "sg:phone":"+61 425 718 230",
    "sg:postcode":"3082",
    "sg:province":"VIC",
    "sg:tags":[
        "therapy"
    ],
    "wof:name":"Moyez R. Hashim",
    "wof:placetype":"venue"
},
  "geometry": {"coordinates":[145.065063477,-37.6641693115],"type":"Point"}
}