{
  "type": "Feature",
  "properties": {
    "addr:full":"35 Macquarie Ave Campbelltown NSW 2560",
    "addr:housenumber":"35",
    "addr:postcode":"2560",
    "addr:street":"Macquarie Ave",
    "iso:country":"AU",
    "sg:address":"35 Macquarie Ave",
    "sg:city":"Campbelltown",
    "sg:classifiers":[
        {
            "category":"Building & Trades",
            "subcategory":"Cleaning & Sanitation",
            "type":"Services"
        }
    ],
    "sg:phone":"+61 2 4628 9662",
    "sg:postcode":"2560",
    "sg:province":"NSW",
    "sg:tags":[
        "chemical",
        "pressure",
        "steam",
        "contractor"
    ],
    "wof:name":"A & L Whealy Clean",
    "wof:placetype":"venue"
},
  "geometry": {"coordinates":[150.824584961,-34.0708808899],"type":"Point"}
}