{
  "type": "Feature",
  "properties": {
    "addr:full":"Shop 7 & 8, 7 Railwasy Tce Rockingham WA 6168",
    "addr:housenumber":"shop 7 &;7",
    "addr:postcode":"6168",
    "addr:street":"Railwasy Tce",
    "iso:country":"AU",
    "sg:address":"Shop 7",
    "sg:city":"& 8, 7 Railwasy Tce Rockingham",
    "sg:classifiers":[
        {
            "category":"Banks & Credit Unions",
            "subcategory":"Investment Brokerage",
            "type":"Services"
        }
    ],
    "sg:phone":"+61 8 9592 1161",
    "sg:postcode":"6168",
    "sg:province":"WA",
    "sg:tags":[
        "management",
        "property"
    ],
    "wof:name":"Wentworth Real Estate & Property Management",
    "wof:placetype":"venue"
},
  "geometry": {"coordinates":[115.757622,-32.250061],"type":"Point"}
}