{
  "type": "Feature",
  "properties": {
    "iso:country":"AU",
    "sg:address":"18 Netherplace Drv",
    "sg:city":"Frankston",
    "sg:classifiers":[
        {
            "category":"Social Services",
            "subcategory":"Retirement Home",
            "type":"Services"
        }
    ],
    "sg:phone":"+61 3 9781 5922",
    "sg:postcode":"3199",
    "sg:province":"VIC",
    "sg:tags":[
        "accommodation",
        "special"
    ],
    "wof:name":"Acacia Place",
    "wof:placetype":"venue"
},
  "geometry": {"coordinates":[145.144454956,-38.1676063538],"type":"Point"}
}