{
  "type": "Feature",
  "properties": {
    "iso:country":"AU",
    "sg:address":"PO Box 638",
    "sg:city":"West Ryde",
    "sg:classifiers":[
        {
            "category":"Building & Trades",
            "subcategory":"Construction",
            "type":"Services"
        }
    ],
    "sg:phone":"+61 410 343 233",
    "sg:postcode":"1685",
    "sg:province":"NSW",
    "sg:tags":[
        "contractor"
    ],
    "wof:name":"Masterbuild Constructions",
    "wof:placetype":"venue"
},
  "geometry": {"coordinates":[151.0887146,-33.8077087402],"type":"Point"}
}