{
  "type": "Feature",
  "properties": {
    "addr:full":"16 Christina Pl Kareela NSW 2232",
    "addr:housenumber":"16",
    "addr:postcode":"2232",
    "addr:street":"Christina Pl",
    "iso:country":"AU",
    "sg:address":"16 Christina Pl",
    "sg:city":"Kareela",
    "sg:classifiers":[
        {
            "category":"Building & Trades",
            "subcategory":"Plumbing",
            "type":"Services"
        }
    ],
    "sg:phone":"+61 2 9528 7694",
    "sg:postcode":"2232",
    "sg:province":"NSW",
    "sg:tags":[
        "plumber",
        "gasfitters"
    ],
    "wof:name":"Stones Plumbing Service Pty Ltd",
    "wof:placetype":"venue"
},
  "geometry": {"coordinates":[151.08454895,-34.0157623291],"type":"Point"}
}