{
  "type": "Feature",
  "properties": {
    "iso:country":"AU",
    "sg:address":"96 Clavering Rd",
    "sg:city":"Bayswater",
    "sg:classifiers":[
        {
            "category":"Shopping",
            "subcategory":"Pets & Pet Supplies",
            "type":"Retail Goods"
        }
    ],
    "sg:phone":"+61 8 9271 6628",
    "sg:postcode":"6053",
    "sg:province":"WA",
    "sg:tags":[
        "shop",
        "supplier"
    ],
    "wof:name":"Aviary Makers",
    "wof:placetype":"venue"
},
  "geometry": {"coordinates":[115.91734314,-31.9125518799],"type":"Point"}
}