{
  "type": "Feature",
  "properties": {
    "addr:full":"1 Antonio Crt Newton SA 5074",
    "addr:postcode":"5074",
    "addr:street":"Antonio Crt",
    "iso:country":"AU",
    "sg:address":"1 Antonio Crt",
    "sg:city":"Newton",
    "sg:classifiers":[
        {
            "category":"Mining & Drilling",
            "type":"Manufacturing & Wholesale Goods"
        }
    ],
    "sg:phone":"+61 419 828 012",
    "sg:postcode":"5074",
    "sg:province":"SA",
    "sg:tags":[
        "boring",
        "contractor"
    ],
    "wof:name":"Gas-Tech Pty Ltd",
    "wof:placetype":"venue"
},
  "geometry": {"coordinates":[138.68661499000001,-34.8802337646],"type":"Point"}
}