{
  "type": "Feature",
  "properties": {
    "iso:country":"AU",
    "sg:address":"14 Prince St",
    "sg:city":"Busselton",
    "sg:classifiers":[
        {
            "category":"Professional",
            "subcategory":"Accounting & Tax Preparation",
            "type":"Services"
        }
    ],
    "sg:phone":"+61 8 9752 1022",
    "sg:postcode":"6280",
    "sg:province":"WA",
    "sg:tags":[
        "consultant",
        "taxation"
    ],
    "wof:name":"Hanlon Davies",
    "wof:placetype":"venue"
},
  "geometry": {"coordinates":[115.34323120099999,-33.6515007019],"type":"Point"}
}