{
  "type": "Feature",
  "properties": {
    "iso:country":"AU",
    "sg:address":"342 Railway Pde",
    "sg:city":"Carlton",
    "sg:classifiers":[
        {
            "category":"Shopping",
            "subcategory":"Baby Store",
            "type":"Retail Goods"
        }
    ],
    "sg:phone":"+61 2 9587 1394",
    "sg:postcode":"2218",
    "sg:province":"NSW",
    "sg:tags":[
        "wear"
    ],
    "wof:name":"Thoughtful Trinkets",
    "wof:placetype":"venue"
},
  "geometry": {"coordinates":[151.121964,-33.969112],"type":"Point"}
}