{
  "type": "Feature",
  "properties": {
    "addr:full":"Shp 1 Strathfield Plz The Boulevard Strathfield NSW 2135",
    "addr:housenumber":"1",
    "addr:postcode":"2135",
    "addr:street":"Strathfield Plz The Boulevard",
    "iso:country":"AU",
    "sg:address":"Shp 1",
    "sg:city":"Strathfield Plz The Boulevard Strathfield",
    "sg:classifiers":[
        {
            "category":"Shopping",
            "subcategory":"Optical Goods",
            "type":"Retail Goods"
        }
    ],
    "sg:phone":"+61 2 9746 1472",
    "sg:postcode":"2135",
    "sg:province":"NSW",
    "sg:tags":[
        "dispenser",
        "prescription"
    ],
    "wof:name":"OPSM Pty Ltd",
    "wof:placetype":"venue"
},
  "geometry": {"coordinates":[151.093215942,-33.8769721985],"type":"Point"}
}