{
  "type": "Feature",
  "properties": {
    "iso:country":"AU",
    "sg:address":"PO Box 253",
    "sg:city":"Quirindi",
    "sg:classifiers":[
        {
            "category":"Professional",
            "subcategory":"Detective & Security Services",
            "type":"Services"
        }
    ],
    "sg:phone":"+61 418 424 803",
    "sg:postcode":"2343",
    "sg:province":"NSW",
    "sg:tags":[
        "consultant",
        "system"
    ],
    "wof:name":"C.O.G.S. Security Pty Ltd",
    "wof:placetype":"venue"
},
  "geometry": {"coordinates":[150.67579650900001,-31.5191898346],"type":"Point"}
}