{
  "type": "Feature",
  "properties": {
    "addr:full":"Cnr Old Northern Rd Shop 6, 2 Chinook St Everton Hills QLD 4053",
    "addr:housenumber":"6 2",
    "addr:postcode":"4053",
    "addr:street":"Cnr Old Northern Rd Shop;Chinook St",
    "iso:country":"AU",
    "sg:address":"Cnr Old Northern Rd Shop 6, 2 Chinook St",
    "sg:city":"Everton Hills",
    "sg:classifiers":[
        {
            "category":"Education",
            "subcategory":"Special Training",
            "type":"Public Place"
        }
    ],
    "sg:phone":"+61 7 3353 0462",
    "sg:postcode":"4053",
    "sg:province":"QLD",
    "sg:tags":[
        "tuition-educational"
    ],
    "wof:name":"Fruition Tuition",
    "wof:placetype":"venue"
},
  "geometry": {"coordinates":[152.98324585,-27.3834896088],"type":"Point"}
}