{
  "type": "Feature",
  "properties": {
    "addr:full":"Unit 2/ 3 Bearing St Seven Hills NSW 2147",
    "addr:postcode":"2147",
    "addr:street":"Bearing St",
    "iso:country":"AU",
    "sg:address":"Unit 2/ 3 Bearing St",
    "sg:city":"Seven Hills",
    "sg:classifiers":[
        {
            "category":"Building & Trades",
            "subcategory":"Construction",
            "type":"Services"
        }
    ],
    "sg:phone":"+61 2 9624 1688",
    "sg:postcode":"2147",
    "sg:province":"NSW",
    "sg:tags":[
        "contractor"
    ],
    "wof:name":"Morelli Constructions Pty Ltd",
    "wof:placetype":"venue"
},
  "geometry": {"coordinates":[150.95774841299999,-33.774597168],"type":"Point"}
}