{
  "type": "Feature",
  "properties": {
    "addr:full":"11 Campbell St Blacktown NSW 2148",
    "addr:housenumber":"11",
    "addr:postcode":"2148",
    "addr:street":"Campbell St",
    "iso:country":"AU",
    "sg:address":"11 Campbell St",
    "sg:city":"Blacktown",
    "sg:classifiers":[
        {
            "category":"Personal",
            "type":"Services"
        }
    ],
    "sg:phone":"+61 2 9671 7333",
    "sg:postcode":"2148",
    "sg:province":"NSW",
    "sg:tags":[
        "reducing",
        "treatment",
        "weight"
    ],
    "wof:name":"Jenny Craig Weight Loss Centres Pty Ltd",
    "wof:placetype":"venue"
},
  "geometry": {"coordinates":[150.90936279300001,-33.7709083557],"type":"Point"}
}