{
  "type": "Feature",
  "properties": {
    "addr:full":"PMB 213 Alice Springs 0871 Alice Springs NT 0870",
    "addr:postcode":"0871;nt 0870",
    "iso:country":"AU",
    "sg:address":"PMB 213 Alice Springs 0871",
    "sg:city":"Alice Springs",
    "sg:classifiers":[
        {
            "category":"Education",
            "subcategory":"School",
            "type":"Public Place"
        }
    ],
    "sg:phone":"+61 8 8956 8779",
    "sg:postcode":"0870",
    "sg:province":"NT",
    "sg:tags":[
        "state",
        "except",
        "nsw"
    ],
    "wof:name":"Laramba School",
    "wof:placetype":"venue"
},
  "geometry": {"coordinates":[133.88088989299999,-23.7003593445],"type":"Point"}
}