{
  "type": "Feature",
  "properties": {
    "iso:country":"AU",
    "sg:address":"122 Hardware St",
    "sg:city":"Melbourne",
    "sg:classifiers":[
        {
            "category":"Real Estate",
            "subcategory":"Real Estate Agent",
            "type":"Services"
        }
    ],
    "sg:phone":"+61 3 9670 3330",
    "sg:postcode":"3000",
    "sg:province":"VIC",
    "wof:name":"Ray White City Residential",
    "wof:placetype":"venue"
},
  "geometry": {"coordinates":[144.96063232399999,-37.811958313],"type":"Point"}
}