{
  "type": "Feature",
  "properties": {
    "iso:country":"AU",
    "sg:address":"Bagot Rd",
    "sg:city":"Ludmilla",
    "sg:classifiers":[
        {
            "category":"Education",
            "subcategory":"School",
            "type":"Public Place"
        }
    ],
    "sg:phone":"+61 8 8999 3236",
    "sg:postcode":"0820",
    "sg:province":"NT",
    "sg:tags":[
        "state",
        "except",
        "nsw"
    ],
    "wof:name":"Ludmilla Pre-School",
    "wof:placetype":"venue"
},
  "geometry": {"coordinates":[130.85609435999999,-12.4076986313],"type":"Point"}
}