{
  "type": "Feature",
  "properties": {
    "addr:full":"Shop 3 Stewart Cnr & Stewart Drv Cannonvale QLD 4802",
    "addr:housenumber":"shop 3",
    "addr:postcode":"4802",
    "addr:street":"Stewart Cnr & Stewart Drv",
    "iso:country":"AU",
    "sg:address":"Shop 3 Stewart Cnr & Stewart Drv",
    "sg:city":"Cannonvale",
    "sg:classifiers":[
        {
            "category":"Shopping",
            "subcategory":"Computers & Home Electronics",
            "type":"Retail Goods"
        }
    ],
    "sg:phone":"+61 7 4946 6068",
    "sg:postcode":"4802",
    "sg:province":"QLD",
    "sg:tags":[
        "hardware",
        "equipment"
    ],
    "wof:name":"Dateline Computers",
    "wof:placetype":"venue"
},
  "geometry": {"coordinates":[148.69442749000001,-20.2729816437],"type":"Point"}
}