{
  "type": "Feature",
  "properties": {
    "iso:country":"AU",
    "sg:address":"Upper Lvl, Kippa Ring Shopping Centre, Anzac Ave",
    "sg:city":"Kippa-Ring",
    "sg:classifiers":[
        {
            "category":"Education",
            "subcategory":"Vocational School",
            "type":"Public Place"
        }
    ],
    "sg:phone":"+61 7 3883 3444",
    "sg:postcode":"4021",
    "sg:province":"QLD",
    "sg:tags":[
        "cake",
        "decorating",
        "decorator"
    ],
    "wof:name":"Make It & Bake It",
    "wof:placetype":"venue"
},
  "geometry": {"coordinates":[153.07788099999999,-27.219027],"type":"Point"}
}