{
  "type": "Feature",
  "properties": {
    "addr:full":"25 Dawson St Brunswick VIC 3056",
    "addr:housenumber":"25",
    "addr:postcode":"3056",
    "addr:street":"Dawson St",
    "iso:country":"AU",
    "sg:address":"25 Dawson St",
    "sg:city":"Brunswick",
    "sg:classifiers":[
        {
            "category":"Manufacturing",
            "subcategory":"Textiles",
            "type":"Manufacturing & Wholesale Goods"
        }
    ],
    "sg:phone":"+61 3 9925 9120",
    "sg:postcode":"3056",
    "sg:province":"VIC",
    "sg:tags":[
        "agent"
    ],
    "wof:name":"RMIT Textile Testing Services",
    "wof:placetype":"venue"
},
  "geometry": {"coordinates":[144.95611572300001,-37.7709579468],"type":"Point"}
}