{
  "type": "Feature",
  "properties": {
    "iso:country":"AU",
    "sg:address":"116 South Rd",
    "sg:city":"Brighton East",
    "sg:classifiers":[
        {
            "category":"Building & Trades",
            "subcategory":"Landscaping Services",
            "type":"Services"
        }
    ],
    "sg:phone":"+61 3 9557 9811",
    "sg:postcode":"3187",
    "sg:province":"VIC",
    "sg:tags":[
        "stump",
        "tree",
        "felling",
        "removal"
    ],
    "wof:name":"Jaspers Tree Services",
    "wof:placetype":"venue"
},
  "geometry": {"coordinates":[145.006515503,-37.9297866821],"type":"Point"}
}