{
  "type": "Feature",
  "properties": {
    "addr:full":"88 Darkes Rd Kembla Grange NSW 2526",
    "addr:housenumber":"88",
    "addr:postcode":"2526",
    "addr:street":"Darkes Rd",
    "iso:country":"AU",
    "sg:address":"88 Darkes Rd",
    "sg:city":"Kembla Grange",
    "sg:classifiers":[
        {
            "category":"Building & Trades",
            "subcategory":"Landscaping Services",
            "type":"Services"
        }
    ],
    "sg:phone":"+61 2 4261 6666",
    "sg:postcode":"2526",
    "sg:province":"NSW",
    "sg:tags":[
        "gardener"
    ],
    "wof:name":"Landform Gardens",
    "wof:placetype":"venue"
},
  "geometry": {"coordinates":[150.79385375999999,-34.4792556763],"type":"Point"}
}