{
  "type": "Feature",
  "properties": {
    "addr:full":"40 King St Gloucester NSW 2422",
    "addr:housenumber":"40",
    "addr:postcode":"2422",
    "addr:street":"King St",
    "iso:country":"AU",
    "sg:address":"40 King St",
    "sg:city":"Gloucester",
    "sg:classifiers":[
        {
            "category":"Government",
            "subcategory":"Fire Station",
            "type":"Public Place"
        }
    ],
    "sg:phone":"+61 2 6558 1703",
    "sg:postcode":"2422",
    "sg:province":"NSW",
    "sg:tags":[
        "brigade"
    ],
    "wof:name":"Fire Brigades-NSW",
    "wof:placetype":"venue"
},
  "geometry": {"coordinates":[151.96023559599999,-32.0082206726],"type":"Point"}
}