{
  "type": "Feature",
  "properties": {
    "addr:full":"21 Sharon Crs Kelso QLD 4815",
    "addr:housenumber":"21",
    "addr:postcode":"4815",
    "addr:street":"Sharon Crs",
    "iso:country":"AU",
    "sg:address":"21 Sharon Crs",
    "sg:city":"Kelso",
    "sg:classifiers":[
        {
            "category":"Building & Trades",
            "subcategory":"Construction",
            "type":"Services"
        }
    ],
    "sg:phone":"+61 422 231 845",
    "sg:postcode":"4815",
    "sg:province":"QLD",
    "sg:tags":[
        "plasterboard",
        "plasterer",
        "fixer"
    ],
    "wof:name":"Razz Plastering",
    "wof:placetype":"venue"
},
  "geometry": {"coordinates":[146.73034699999999,-19.379589],"type":"Point"}
}