{
  "type": "Feature",
  "properties": {
    "iso:country":"AU",
    "sg:address":"Albany Hwy",
    "sg:city":"Albany",
    "sg:classifiers":[
        {
            "category":"Professional",
            "type":"Services"
        }
    ],
    "sg:phone":"+61 8 9841 8641",
    "sg:postcode":"6330",
    "sg:province":"WA",
    "sg:tags":[
        "transport"
    ],
    "wof:name":"Stirling Freight Express",
    "wof:placetype":"venue"
},
  "geometry": {"coordinates":[117.84877014200001,-34.9826087952],"type":"Point"}
}