{
  "type": "Feature",
  "properties": {
    "addr:full":"13 Glen Drv Eaglemont VIC 3084",
    "addr:housenumber":"13",
    "addr:postcode":"3084",
    "addr:street":"Glen Drv",
    "iso:country":"AU",
    "sg:address":"13 Glen Drv",
    "sg:city":"Eaglemont",
    "sg:classifiers":[
        {
            "category":"Health Services",
            "subcategory":"Clinic",
            "type":"Services"
        }
    ],
    "sg:phone":"+61 417 564 372",
    "sg:postcode":"3084",
    "sg:province":"VIC",
    "sg:tags":[
        "aromatherapy"
    ],
    "wof:name":"Habron Bell Tracey",
    "wof:placetype":"venue"
},
  "geometry": {"coordinates":[145.06109619099999,-37.7669258118],"type":"Point"}
}