{
  "type": "Feature",
  "properties": {
    "addr:full":"2 Hume Rd Laverton North VIC 3026",
    "addr:housenumber":"2",
    "addr:postcode":"3026",
    "addr:street":"Hume Rd",
    "iso:country":"AU",
    "sg:address":"2 Hume Rd",
    "sg:city":"Laverton North",
    "sg:classifiers":[
        {
            "category":"Building & Trades",
            "subcategory":"Cleaning & Sanitation",
            "type":"Services"
        }
    ],
    "sg:phone":"+61 3 9369 6711",
    "sg:postcode":"3026",
    "sg:province":"VIC",
    "sg:tags":[
        "abrasive",
        "blasting"
    ],
    "wof:name":"McElligott Partners Pty Ltd",
    "wof:placetype":"venue"
},
  "geometry": {"coordinates":[144.796494,-37.828777],"type":"Point"}
}