{
  "type": "Feature",
  "properties": {
    "addr:full":"3 Marie Drv Wodonga VIC 3690",
    "addr:housenumber":"3",
    "addr:postcode":"3690",
    "addr:street":"Marie Drv",
    "iso:country":"AU",
    "sg:address":"3 Marie Drv",
    "sg:city":"Wodonga",
    "sg:classifiers":[
        {
            "category":"Building & Trades",
            "subcategory":"Cleaning & Sanitation",
            "type":"Services"
        }
    ],
    "sg:phone":"+61 2 6056 1602",
    "sg:postcode":"3690",
    "sg:province":"VIC",
    "sg:tags":[
        "industrial",
        "commercial",
        "contractor"
    ],
    "wof:name":"Olympic Power Cleaning",
    "wof:placetype":"venue"
},
  "geometry": {"coordinates":[146.881317139,-36.1146774292],"type":"Point"}
}