{
  "type": "Feature",
  "properties": {
    "iso:country":"AU",
    "sg:address":"90 Crawford St",
    "sg:city":"Bulahdelah",
    "sg:classifiers":[
        {
            "category":"Real Estate",
            "subcategory":"Real Estate Services",
            "type":"Services"
        }
    ],
    "sg:phone":"+61 2 4997 4380",
    "sg:postcode":"2423",
    "sg:province":"NSW",
    "sg:tags":[
        "house",
        "hire",
        "boat"
    ],
    "wof:name":"Luxury Houseboat Hire",
    "wof:placetype":"venue"
},
  "geometry": {"coordinates":[152.210556,-32.402489],"type":"Point"}
}