{
  "type": "Feature",
  "properties": {
    "addr:full":"46 Stevens Rd Julatten QLD 4871",
    "addr:housenumber":"46",
    "addr:postcode":"4871",
    "addr:street":"Stevens Rd",
    "iso:country":"AU",
    "sg:address":"46 Stevens Rd",
    "sg:city":"Julatten",
    "sg:classifiers":[
        {
            "category":"Farming",
            "subcategory":"Nursery",
            "type":"Manufacturing & Wholesale Goods"
        }
    ],
    "sg:phone":"+61 7 4094 1590",
    "sg:postcode":"4871",
    "sg:province":"QLD",
    "wof:name":"TNQ Palms Nursery",
    "wof:placetype":"venue"
},
  "geometry": {"coordinates":[145.36331176799999,-16.6208648682],"type":"Point"}
}