{
  "type": "Feature",
  "properties": {
    "iso:country":"AU",
    "sg:address":"PO Box 7008",
    "sg:city":"Eaton",
    "sg:classifiers":[
        {
            "category":"Retail",
            "subcategory":"Event Space",
            "type":"Services"
        }
    ],
    "sg:phone":"+61 8 9725 2999",
    "sg:postcode":"6232",
    "sg:province":"WA",
    "sg:tags":[
        "venue",
        "reception",
        "wedding"
    ],
    "wof:name":"All Seasons Sanctuary Golf Resort",
    "wof:placetype":"venue"
},
  "geometry": {"coordinates":[115.715233,-33.323139],"type":"Point"}
}