{
  "type": "Feature",
  "properties": {
    "addr:full":"41 Riley St Tenterfield NSW 2372",
    "addr:housenumber":"41",
    "addr:postcode":"2372",
    "addr:street":"Riley St",
    "iso:country":"AU",
    "sg:address":"41 Riley St",
    "sg:city":"Tenterfield",
    "sg:classifiers":[
        {
            "category":"Building & Trades",
            "subcategory":"Construction",
            "type":"Services"
        }
    ],
    "sg:phone":"+61 2 6736 3055",
    "sg:postcode":"2372",
    "sg:province":"NSW",
    "sg:tags":[
        "earth",
        "excavating",
        "moving",
        "contractor"
    ],
    "wof:name":"Sebs Bobcat & Tipper Hire",
    "wof:placetype":"venue"
},
  "geometry": {"coordinates":[152.01451110799999,-29.0427284241],"type":"Point"}
}