{
  "type": "Feature",
  "properties": {
    "addr:full":"10/80- 82 Pitt St Parramatta NSW 2150",
    "addr:housenumber":"10 / 80 82",
    "addr:postcode":"2150",
    "addr:street":"Pitt St",
    "iso:country":"AU",
    "sg:address":"10/80- 82 Pitt St",
    "sg:city":"Parramatta",
    "sg:classifiers":[
        {
            "category":"Professional",
            "subcategory":"Business Services",
            "type":"Services"
        }
    ],
    "sg:phone":"+61 412 388 237",
    "sg:postcode":"2150",
    "sg:province":"NSW",
    "sg:tags":[
        "drafting"
    ],
    "wof:name":"Precision Drafting Studios",
    "wof:placetype":"venue"
},
  "geometry": {"coordinates":[150.99412536599999,-33.8276901245],"type":"Point"}
}