{
  "type": "Feature",
  "properties": {
    "iso:country":"AU",
    "sg:address":"71 Burswood Rd",
    "sg:city":"Burswood",
    "sg:classifiers":[
        {
            "category":"Personal",
            "subcategory":"Adult",
            "type":"Services"
        }
    ],
    "sg:phone":"+61 8 9473 8937",
    "sg:postcode":"6100",
    "sg:province":"WA",
    "sg:tags":[
        "product"
    ],
    "wof:name":"Private Interludes",
    "wof:placetype":"venue"
},
  "geometry": {"coordinates":[115.893608093,-31.9676742554],"type":"Point"}
}