{
  "type": "Feature",
  "properties": {
    "addr:full":"11 Buchan Pl Kings Langley NSW 2147",
    "addr:housenumber":"11",
    "addr:postcode":"2147",
    "addr:street":"Buchan Pl",
    "iso:country":"AU",
    "sg:address":"11 Buchan Pl",
    "sg:city":"Kings Langley",
    "sg:classifiers":[
        {
            "category":"Professional",
            "subcategory":"Business Services",
            "type":"Services"
        }
    ],
    "sg:phone":"+61 2 9620 4559",
    "sg:postcode":"2147",
    "sg:province":"NSW",
    "sg:tags":[
        "consultant",
        "promoter",
        "entertainment"
    ],
    "wof:name":"R-Series",
    "wof:placetype":"venue"
},
  "geometry": {"coordinates":[150.93606567399999,-33.7483253479],"type":"Point"}
}