{
  "type": "Feature",
  "properties": {
    "iso:country":"AU",
    "sg:address":"4 Hamilton St",
    "sg:city":"Riverstone",
    "sg:classifiers":[
        {
            "category":"Building & Trades",
            "subcategory":"Construction",
            "type":"Services"
        }
    ],
    "sg:phone":"+61 2 9627 9110",
    "sg:postcode":"2765",
    "sg:province":"NSW",
    "sg:tags":[
        "welding"
    ],
    "wof:name":"S & W V Welding",
    "wof:placetype":"venue"
},
  "geometry": {"coordinates":[150.87037658700001,-33.6742897034],"type":"Point"}
}