{
  "type": "Feature",
  "properties": {
    "iso:country":"AU",
    "sg:address":"119 North Rd",
    "sg:city":"Denistone East",
    "sg:classifiers":[
        {
            "category":"Food & Beverages",
            "subcategory":"Supermarket",
            "type":"Retail Goods"
        }
    ],
    "sg:phone":"+61 2 9878 2420",
    "sg:postcode":"2112",
    "sg:province":"NSW",
    "sg:tags":[
        "grocery",
        "store"
    ],
    "wof:name":"IGA Xpress",
    "wof:placetype":"venue"
},
  "geometry": {"coordinates":[151.10240173299999,-33.7949104309],"type":"Point"}
}