{
  "type": "Feature",
  "properties": {
    "iso:country":"AU",
    "sg:address":"Shop 3, 44 Hampden Rd",
    "sg:city":"Artarmon",
    "sg:classifiers":[
        {
            "category":"Real Estate",
            "subcategory":"Real Estate Agent",
            "type":"Services"
        }
    ],
    "sg:phone":"+61 2 9411 7788",
    "sg:postcode":"2064",
    "sg:province":"NSW",
    "wof:name":"Laing & Simmons Artarmon",
    "wof:placetype":"venue"
},
  "geometry": {"coordinates":[151.18576049800001,-33.8096580505],"type":"Point"}
}