{
  "type": "Feature",
  "properties": {
    "iso:country":"AU",
    "sg:address":"1936 Hume Hwy",
    "sg:city":"Campbellfield",
    "sg:classifiers":[
        {
            "category":"Farming",
            "subcategory":"Farm & Veterinary Services",
            "type":"Manufacturing & Wholesale Goods"
        }
    ],
    "sg:phone":"+61 3 9357 0677",
    "sg:postcode":"3061",
    "sg:province":"VIC",
    "sg:tags":[
        "irrigation",
        "reticulation",
        "system"
    ],
    "wof:name":"Reece Pty Ltd",
    "wof:placetype":"venue"
},
  "geometry": {"coordinates":[144.95390319800001,-37.6563034058],"type":"Point"}
}