{
  "type": "Feature",
  "properties": {
    "addr:full":"11 Knox St St Marys NSW 2760",
    "addr:housenumber":"11",
    "addr:postcode":"2760",
    "addr:street":"Knox St",
    "iso:country":"AU",
    "sg:address":"11 Knox St St",
    "sg:city":"Marys",
    "sg:classifiers":[
        {
            "category":"Building & Trades",
            "subcategory":"Construction",
            "type":"Services"
        }
    ],
    "sg:phone":"+61 2 9623 6003",
    "sg:postcode":"2760",
    "sg:province":"NSW",
    "sg:tags":[
        "joiner",
        "carpenter"
    ],
    "wof:name":"Teague S",
    "wof:placetype":"venue"
},
  "geometry": {"coordinates":[150.779693603,-33.7743148804],"type":"Point"}
}