{
  "type": "Feature",
  "properties": {
    "addr:full":"Ste9/ 365 Kingsway Caringbah NSW 2229",
    "addr:housenumber":"365",
    "addr:postcode":"2229",
    "addr:street":"Kingsway",
    "iso:country":"AU",
    "sg:address":"Ste9/ 365 Kingsway",
    "sg:city":"Caringbah",
    "sg:classifiers":[
        {
            "category":"Banks & Credit Unions",
            "subcategory":"Financial Services",
            "type":"Services"
        }
    ],
    "sg:phone":"+61 2 9540 3411",
    "sg:postcode":"2229",
    "sg:province":"NSW",
    "sg:tags":[
        "loan",
        "finance",
        "mortgage"
    ],
    "wof:name":"Mortgage House Of Australia",
    "wof:placetype":"venue"
},
  "geometry": {"coordinates":[151.12371826200001,-34.0435028076],"type":"Point"}
}