{
  "type": "Feature",
  "properties": {
    "iso:country":"AU",
    "sg:address":"Cnr Carinya Ave & Charles Hockett Dr",
    "sg:city":"St Marys",
    "sg:classifiers":[
        {
            "category":"Wholesale",
            "subcategory":"Medical Equipment & Supplies",
            "type":"Manufacturing & Wholesale Goods"
        }
    ],
    "sg:phone":"+61 2 9623 1891",
    "sg:postcode":"2760",
    "sg:province":"NSW",
    "sg:tags":[
        "aids",
        "hearing"
    ],
    "wof:name":"Allens' Hearing and Specialists St Marys",
    "wof:placetype":"venue"
},
  "geometry": {"coordinates":[150.773635864,-33.7623748779],"type":"Point"}
}