{
  "type": "Feature",
  "properties": {
    "addr:full":"132 Nicholson St Footscray VIC 3011",
    "addr:housenumber":"132",
    "addr:postcode":"3011",
    "addr:street":"Nicholson St",
    "iso:country":"AU",
    "sg:address":"132 Nicholson St",
    "sg:city":"Footscray",
    "sg:classifiers":[
        {
            "category":"Personal",
            "subcategory":"Beauty Salon",
            "type":"Services"
        }
    ],
    "sg:phone":"+61 3 9687 7729",
    "sg:postcode":"3011",
    "sg:province":"VIC",
    "wof:name":"Tuyet Phong Phuong Mai",
    "wof:placetype":"venue"
},
  "geometry": {"coordinates":[144.89906310999999,-37.8016204834],"type":"Point"}
}