{
  "type": "Feature",
  "properties": {
    "iso:country":"AU",
    "sg:address":"U 15/ 45 Ladner St",
    "sg:city":"O'Connor",
    "sg:classifiers":[
        {
            "category":"Shopping",
            "subcategory":"Musical Instruments",
            "type":"Retail Goods"
        }
    ],
    "sg:phone":"+61 8 9331 8700",
    "sg:postcode":"6163",
    "sg:province":"WA",
    "sg:tags":[
        "musician",
        "agent"
    ],
    "wof:name":"Latin Music",
    "wof:placetype":"venue"
},
  "geometry": {"coordinates":[115.798851,-32.063877],"type":"Point"}
}