{
  "type": "Feature",
  "properties": {
    "addr:full":"PO Box 1533 Gosford NSW 2250",
    "addr:postcode":"2250",
    "iso:country":"AU",
    "sg:address":"PO Box 1533",
    "sg:city":"Gosford",
    "sg:classifiers":[
        {
            "category":"Farming",
            "subcategory":"Farm & Veterinary Services",
            "type":"Manufacturing & Wholesale Goods"
        }
    ],
    "sg:phone":"+61 418 437 411",
    "sg:postcode":"2250",
    "sg:province":"NSW",
    "sg:tags":[
        "irrigation",
        "reticulation",
        "system"
    ],
    "wof:name":"Outdoors Australia",
    "wof:placetype":"venue"
},
  "geometry": {"coordinates":[151.34249877900001,-33.4237213135],"type":"Point"}
}