{
  "type": "Feature",
  "properties": {
    "addr:full":"111 Alexander La Harrisville QLD 4307",
    "addr:housenumber":"111",
    "addr:postcode":"4307",
    "addr:street":"Alexander La",
    "iso:country":"AU",
    "sg:address":"111 Alexander La",
    "sg:city":"Harrisville",
    "sg:classifiers":[
        {
            "category":"Professional",
            "subcategory":"Business Services",
            "type":"Services"
        }
    ],
    "sg:phone":"+61 408 150 782",
    "sg:postcode":"4307",
    "sg:province":"QLD",
    "sg:tags":[
        "livestock",
        "transport"
    ],
    "wof:name":"W D Livestock Transport",
    "wof:placetype":"venue"
},
  "geometry": {"coordinates":[152.659545898,-27.7984447479],"type":"Point"}
}