{
  "type": "Feature",
  "properties": {
    "iso:country":"AU",
    "sg:address":"606A Croobyar Rd",
    "sg:city":"Milton",
    "sg:classifiers":[
        {
            "category":"Building & Trades",
            "subcategory":"Construction",
            "type":"Services"
        }
    ],
    "sg:phone":"+61 2 4455 7794",
    "sg:postcode":"2538",
    "sg:province":"NSW",
    "sg:tags":[
        "repair",
        "maintenance",
        "contractor"
    ],
    "wof:name":"Green Smart Design & Construction",
    "wof:placetype":"venue"
},
  "geometry": {"coordinates":[150.382247925,-35.3188476562],"type":"Point"}
}