{
  "type": "Feature",
  "properties": {
    "addr:full":"18 Sevenoakes Ave Croydon VIC 3136",
    "addr:housenumber":"18",
    "addr:postcode":"3136",
    "addr:street":"Sevenoakes Ave",
    "iso:country":"AU",
    "sg:address":"18 Sevenoakes Ave",
    "sg:city":"Croydon",
    "sg:classifiers":[
        {
            "category":"Professional",
            "subcategory":"Art Services",
            "type":"Services"
        }
    ],
    "sg:phone":"+61 412 322 431",
    "sg:postcode":"3136",
    "sg:province":"VIC",
    "sg:tags":[
        "decorator",
        "painter"
    ],
    "wof:name":"Cotter Painting",
    "wof:placetype":"venue"
},
  "geometry": {"coordinates":[145.27424621599999,-37.7848243713],"type":"Point"}
}