{
  "type": "Feature",
  "properties": {
    "addr:full":"Suite 301/ 16 Cotham Rd Kew VIC 3101",
    "addr:housenumber":"/ 16",
    "addr:postcode":"3101",
    "addr:street":"Cotham Rd",
    "iso:country":"AU",
    "sg:address":"Suite 301/ 16 Cotham Rd",
    "sg:city":"Kew",
    "sg:classifiers":[
        {
            "category":"Education",
            "subcategory":"Special Training",
            "type":"Public Place"
        }
    ],
    "sg:phone":"+61 3 9857 0001",
    "sg:postcode":"3101",
    "sg:province":"VIC",
    "sg:tags":[
        "tuition-educational"
    ],
    "wof:name":"The Hunchback of Notre Dame ? - Training & Educational Services",
    "wof:placetype":"venue"
},
  "geometry": {"coordinates":[145.03109741200001,-37.8070259094],"type":"Point"}
}