{
  "type": "Feature",
  "properties": {
    "addr:full":"28 Tallowwood Ave Cherrybrook NSW 2126",
    "addr:housenumber":"28",
    "addr:postcode":"2126",
    "addr:street":"Tallowwood Ave",
    "iso:country":"AU",
    "sg:address":"28 Tallowwood Ave",
    "sg:city":"Cherrybrook",
    "sg:classifiers":[
        {
            "category":"Sports & Exercise",
            "subcategory":"Sports Center",
            "type":"Entertainment"
        }
    ],
    "sg:phone":"+61 2 9484 7691",
    "sg:postcode":"2126",
    "sg:province":"NSW",
    "sg:tags":[
        "coach",
        "tennis"
    ],
    "wof:name":"VAETS Tennis School",
    "wof:placetype":"venue"
},
  "geometry": {"coordinates":[151.04434204099999,-33.7264862061],"type":"Point"}
}