{
  "type": "Feature",
  "properties": {
    "iso:country":"AU",
    "sg:address":"175 Murray St",
    "sg:city":"Tanunda",
    "sg:classifiers":[
        {
            "category":"Autos & Motor Vehicles",
            "subcategory":"Automobile Sales",
            "type":"Retail Goods"
        }
    ],
    "sg:phone":"+61 8 8563 2188",
    "sg:postcode":"5352",
    "sg:province":"SA",
    "sg:tags":[
        "car",
        "used"
    ],
    "wof:name":"Barossa Valley Toyota",
    "wof:placetype":"venue"
},
  "geometry": {"coordinates":[138.96926879899999,-34.5170783997],"type":"Point"}
}