{
  "type": "Feature",
  "properties": {
    "addr:full":"63 Ridge St Gordon NSW 2072",
    "addr:housenumber":"63",
    "addr:postcode":"2072",
    "addr:street":"Ridge St",
    "iso:country":"AU",
    "sg:address":"63 Ridge St",
    "sg:city":"Gordon",
    "sg:classifiers":[
        {
            "category":"Building & Trades",
            "subcategory":"Plumbing",
            "type":"Services"
        }
    ],
    "sg:phone":"+61 2 9498 3995",
    "sg:postcode":"2072",
    "sg:province":"NSW",
    "sg:tags":[
        "plumber",
        "gasfitters"
    ],
    "wof:name":"Bird R M",
    "wof:placetype":"venue"
},
  "geometry": {"coordinates":[151.144989014,-33.7537498474],"type":"Point"}
}