{
  "type": "Feature",
  "properties": {
    "addr:full":"269 Inkerman St St Kilda VIC 3182",
    "addr:housenumber":"269",
    "addr:postcode":"3182",
    "addr:street":"Inkerman St",
    "iso:country":"AU",
    "sg:address":"269 Inkerman St",
    "sg:city":"St Kilda",
    "sg:classifiers":[
        {
            "category":"Health Services",
            "subcategory":"Health Practitioner",
            "type":"Services"
        }
    ],
    "sg:phone":"+61 3 9525 3569",
    "sg:postcode":"3182",
    "sg:province":"VIC",
    "sg:tags":[
        "naturopath"
    ],
    "wof:name":"In Focus",
    "wof:placetype":"venue"
},
  "geometry": {"coordinates":[144.99278259299999,-37.8656578064],"type":"Point"}
}