{
  "type": "Feature",
  "properties": {
    "addr:full":"3 Holder Ave Richmond SA 5033",
    "addr:housenumber":"3",
    "addr:postcode":"5033",
    "addr:street":"Holder Ave",
    "iso:country":"AU",
    "sg:address":"3 Holder Ave",
    "sg:city":"Richmond",
    "sg:classifiers":[
        {
            "category":"Building & Trades",
            "subcategory":"Pest Control",
            "type":"Services"
        }
    ],
    "sg:phone":"+61 8 8159 8603",
    "sg:postcode":"5033",
    "sg:province":"SA",
    "sg:tags":[
        "technical",
        "consultant"
    ],
    "wof:name":"Tech-Man",
    "wof:placetype":"venue"
},
  "geometry": {"coordinates":[138.56654357900001,-34.9416809082],"type":"Point"}
}