{
  "type": "Feature",
  "properties": {
    "addr:full":"198 Lt Collins St Melbourne VIC 3000",
    "addr:housenumber":"198",
    "addr:postcode":"3000",
    "addr:street":"Lt Collins St",
    "iso:country":"AU",
    "sg:address":"198 Lt Collins St",
    "sg:city":"Melbourne",
    "sg:classifiers":[
        {
            "category":"Cafe",
            "type":"Food & Drink"
        }
    ],
    "sg:phone":"+61 3 9654 5074",
    "sg:postcode":"3000",
    "sg:province":"VIC",
    "wof:name":"Stellini Bar",
    "wof:placetype":"venue"
},
  "geometry": {"coordinates":[144.970611572,-37.8142967224],"type":"Point"}
}