{
  "type": "Feature",
  "properties": {
    "addr:full":"17 Edwardes St Black Hill VIC 3350",
    "addr:housenumber":"17",
    "addr:postcode":"3350",
    "addr:street":"Edwardes St",
    "iso:country":"AU",
    "sg:address":"17 Edwardes St",
    "sg:city":"Black Hill",
    "sg:classifiers":[
        {
            "category":"Farming",
            "subcategory":"Dairy Farm",
            "type":"Manufacturing & Wholesale Goods"
        }
    ],
    "sg:phone":"+61 3 5331 1238",
    "sg:postcode":"3350",
    "sg:province":"VIC",
    "wof:name":"Powell J & P",
    "wof:placetype":"venue"
},
  "geometry": {"coordinates":[143.87148999999999,-37.54847],"type":"Point"}
}