{
  "type": "Feature",
  "properties": {
    "iso:country":"AU",
    "sg:address":"23 Macrossan St",
    "sg:city":"Port Douglas",
    "sg:classifiers":[
        {
            "category":"Communications",
            "subcategory":"News Services",
            "type":"Services"
        }
    ],
    "sg:phone":"+61 7 4099 5599",
    "sg:postcode":"4877",
    "sg:province":"QLD",
    "sg:tags":[
        "information",
        "tourist",
        "attractions"
    ],
    "wof:name":"Port Douglas Tourist Information Centre",
    "wof:placetype":"venue"
},
  "geometry": {"coordinates":[145.46771240199999,-16.4851856232],"type":"Point"}
}