{
  "type": "Feature",
  "properties": {
    "addr:full":"Suite4 Level2/ 402 Chapel Rd Bankstown NSW 2200",
    "addr:housenumber":"402",
    "addr:postcode":"2200",
    "addr:street":"Chapel Rd",
    "iso:country":"AU",
    "sg:address":"Suite4 Level2/ 402 Chapel Rd",
    "sg:city":"Bankstown",
    "sg:classifiers":[
        {
            "category":"Government",
            "subcategory":"Court House",
            "type":"Public Place"
        }
    ],
    "sg:phone":"+61 2 9708 2088",
    "sg:postcode":"2200",
    "sg:province":"NSW",
    "sg:tags":[
        "personal",
        "marriage",
        "family",
        "counselling"
    ],
    "wof:name":"Lifecare Counselling & Family Services",
    "wof:placetype":"venue"
},
  "geometry": {"coordinates":[151.033646,-33.915459],"type":"Point"}
}