{
  "type": "Feature",
  "properties": {
    "iso:country":"AU",
    "sg:address":"Factory 2 21-29 Railway Ave",
    "sg:city":"Huntingdale",
    "sg:classifiers":[
        {
            "category":"Autos & Motor Vehicles",
            "subcategory":"Auto Supplies",
            "type":"Retail Goods"
        }
    ],
    "sg:phone":"+61 3 9563 0661",
    "sg:postcode":"3166",
    "sg:province":"VIC",
    "sg:tags":[
        "transmission",
        "equipment",
        "power"
    ],
    "wof:name":"Motion Solutions Australia Pty Ltd",
    "wof:placetype":"venue"
},
  "geometry": {"coordinates":[145.10096740700001,-37.9088134766],"type":"Point"}
}