{
  "type": "Feature",
  "properties": {
    "addr:full":"50 William St Cowra NSW 2794",
    "addr:housenumber":"50",
    "addr:postcode":"2794",
    "addr:street":"William St",
    "iso:country":"AU",
    "sg:address":"50 William St",
    "sg:city":"Cowra",
    "sg:classifiers":[
        {
            "category":"Manufacturing",
            "subcategory":"Retail Goods",
            "type":"Manufacturing & Wholesale Goods"
        }
    ],
    "sg:phone":"+61 2 6341 2222",
    "sg:postcode":"2794",
    "sg:province":"NSW",
    "sg:tags":[
        "merchant",
        "pump",
        "mfrs"
    ],
    "wof:name":"Pumpmaster",
    "wof:placetype":"venue"
},
  "geometry": {"coordinates":[148.675338745,-33.8351593018],"type":"Point"}
}