{
  "type": "Feature",
  "properties": {
    "addr:full":"2/ 234 North St Albury NSW 2640",
    "addr:housenumber":"/ 234",
    "addr:postcode":"2640",
    "addr:street":"North St",
    "iso:country":"AU",
    "sg:address":"2/ 234 North St",
    "sg:city":"Albury",
    "sg:classifiers":[
        {
            "category":"Building & Trades",
            "subcategory":"Cleaning & Sanitation",
            "type":"Services"
        }
    ],
    "sg:phone":"+61 2 6041 4688",
    "sg:postcode":"2640",
    "sg:province":"NSW",
    "sg:tags":[
        "abrasive",
        "blasting"
    ],
    "wof:name":"Murray Fab Engineering",
    "wof:placetype":"venue"
},
  "geometry": {"coordinates":[146.94129943900001,-36.0698890686],"type":"Point"}
}