{
  "type": "Feature",
  "properties": {
    "addr:full":"1 c Browns Pde Wendouree VIC 3355",
    "addr:housenumber":"1",
    "addr:postcode":"3355",
    "addr:street":"C Browns Pde",
    "iso:country":"AU",
    "sg:address":"1 c Browns Pde",
    "sg:city":"Wendouree",
    "sg:classifiers":[
        {
            "category":"Health Services",
            "subcategory":"Health Practitioner",
            "type":"Services"
        }
    ],
    "sg:phone":"+61 3 5338 1818",
    "sg:postcode":"3355",
    "sg:province":"VIC",
    "sg:tags":[
        "alternative"
    ],
    "wof:name":"Remedial Massage Therapist",
    "wof:placetype":"venue"
},
  "geometry": {"coordinates":[143.83807400000001,-37.536674],"type":"Point"}
}