{
  "type": "Feature",
  "properties": {
    "addr:full":"U12/ 12 Glenmore Rd Paddington NSW 2021",
    "addr:housenumber":"12",
    "addr:postcode":"2021",
    "addr:street":"/;Glenmore Rd",
    "iso:country":"AU",
    "sg:address":"U12/ 12 Glenmore Rd",
    "sg:city":"Paddington",
    "sg:classifiers":[
        {
            "category":"Shopping",
            "subcategory":"Clothing, Apparel, & Fashions",
            "type":"Retail Goods"
        }
    ],
    "sg:phone":"+61 2 9357 3308",
    "sg:postcode":"2021",
    "sg:province":"NSW",
    "sg:tags":[
        "lady",
        "wear"
    ],
    "wof:name":"Milich & Morton Pty Ltd",
    "wof:placetype":"venue"
},
  "geometry": {"coordinates":[151.222366333,-33.8835067749],"type":"Point"}
}