{
  "type": "Feature",
  "properties": {
    "iso:country":"AU",
    "sg:address":"Shop 3/ 41 Wason St",
    "sg:city":"Milton",
    "sg:classifiers":[
        {
            "category":"Shopping",
            "subcategory":"Clothing, Apparel, & Fashions",
            "type":"Retail Goods"
        }
    ],
    "sg:phone":"+61 2 4455 5264",
    "sg:postcode":"2538",
    "sg:province":"NSW",
    "sg:tags":[
        "menswear"
    ],
    "wof:name":"Milton Clothes Line The",
    "wof:placetype":"venue"
},
  "geometry": {"coordinates":[150.435745239,-35.3164596558],"type":"Point"}
}