{
  "type": "Feature",
  "properties": {
    "addr:full":"55 Sherington Rd Greenwood WA 6024",
    "addr:housenumber":"55",
    "addr:postcode":"6024",
    "addr:street":"Sherington Rd",
    "iso:country":"AU",
    "sg:address":"55 Sherington Rd",
    "sg:city":"Greenwood",
    "sg:classifiers":[
        {
            "category":"Building & Trades",
            "subcategory":"Construction",
            "type":"Services"
        }
    ],
    "sg:phone":"+61 8 9343 0300",
    "sg:postcode":"6024",
    "sg:province":"WA",
    "sg:tags":[
        "earth",
        "excavating",
        "moving",
        "contractor"
    ],
    "wof:name":"Mako Mini Diggas",
    "wof:placetype":"venue"
},
  "geometry": {"coordinates":[115.810111999,-31.8257846832],"type":"Point"}
}