{
  "type": "Feature",
  "properties": {
    "addr:full":"5/ 278 Mann St Gosford NSW 2250",
    "addr:housenumber":"/ 278",
    "addr:postcode":"2250",
    "addr:street":"Mann St",
    "iso:country":"AU",
    "sg:address":"5/ 278 Mann St",
    "sg:city":"Gosford",
    "sg:classifiers":[
        {
            "category":"Health Services",
            "subcategory":"Health Practitioner",
            "type":"Services"
        }
    ],
    "sg:phone":"+61 2 4323 2262",
    "sg:postcode":"2250",
    "sg:province":"NSW",
    "sg:tags":[
        "alternative"
    ],
    "wof:name":"Gibson, Wendy G",
    "wof:placetype":"venue"
},
  "geometry": {"coordinates":[151.34271240199999,-33.4219055176],"type":"Point"}
}