{
  "type": "Feature",
  "properties": {
    "addr:full":"PO Box 7140 McMahons Point NSW 2060",
    "addr:postcode":"2060",
    "iso:country":"AU",
    "sg:address":"PO Box 7140",
    "sg:city":"McMahons Point",
    "sg:classifiers":[
        {
            "category":"Manufacturing",
            "subcategory":"Apparel",
            "type":"Manufacturing & Wholesale Goods"
        }
    ],
    "sg:phone":"+61 2 9922 6884",
    "sg:postcode":"2060",
    "sg:province":"NSW",
    "sg:tags":[
        "wholesaler",
        "mfrs",
        "footwear"
    ],
    "wof:name":"Jack Hinton Shoes International Pty Ltd",
    "wof:placetype":"venue"
},
  "geometry": {"coordinates":[151.20399475100001,-33.8462905884],"type":"Point"}
}