{
  "type": "Feature",
  "properties": {
    "addr:full":"23 River Crs Cypress Gardens QLD 4218",
    "addr:housenumber":"23",
    "addr:postcode":"4218",
    "addr:street":"River Crs Cypress Gardens",
    "iso:country":"AU",
    "sg:address":"23 River Crs",
    "sg:city":"Cypress Gardens",
    "sg:classifiers":[
        {
            "category":"Real Estate",
            "subcategory":"Architect",
            "type":"Services"
        }
    ],
    "sg:phone":"+61 7 5594 1111",
    "sg:postcode":"4218",
    "sg:province":"QLD",
    "wof:name":"Giles William",
    "wof:placetype":"venue"
},
  "geometry": {"coordinates":[153.403106689,-28.0322399139],"type":"Point"}
}