{
  "type": "Feature",
  "properties": {
    "addr:full":"27- 31 White St Dubbo NSW 2830",
    "addr:housenumber":"31",
    "addr:postcode":"2830",
    "addr:street":"White St",
    "iso:country":"AU",
    "sg:address":"27- 31 White St",
    "sg:city":"Dubbo",
    "sg:classifiers":[
        {
            "category":"Commercial Area",
            "type":"Public Place"
        }
    ],
    "sg:phone":"+61 2 6882 2613",
    "sg:postcode":"2830",
    "sg:province":"NSW",
    "sg:tags":[
        "heavy",
        "carrier"
    ],
    "wof:name":"Dawsons Removals & Storage Pty Ltd",
    "wof:placetype":"venue"
},
  "geometry": {"coordinates":[148.61857605,-32.2432518005],"type":"Point"}
}