{
  "type": "Feature",
  "properties": {
    "addr:full":"131a Parramatta Rd Homebush NSW 2140",
    "addr:housenumber":"131a",
    "addr:postcode":"2140",
    "addr:street":"Parramatta Rd",
    "iso:country":"AU",
    "sg:address":"131a Parramatta Rd",
    "sg:city":"Homebush",
    "sg:classifiers":[
        {
            "category":"Autos & Motor Vehicles",
            "subcategory":"Automobile Sales",
            "type":"Retail Goods"
        }
    ],
    "sg:phone":"+61 2 9746 7933",
    "sg:postcode":"2140",
    "sg:province":"NSW",
    "sg:tags":[
        "car",
        "used"
    ],
    "wof:name":"Dave Lahood Motors",
    "wof:placetype":"venue"
},
  "geometry": {"coordinates":[151.081832886,-33.8635559082],"type":"Point"}
}