{
  "type": "Feature",
  "properties": {
    "iso:country":"AU",
    "sg:address":"1126 Canterbury Rd",
    "sg:city":"Roselands",
    "sg:classifiers":[
        {
            "category":"Manufacturing",
            "subcategory":"Tools & Machinery",
            "type":"Manufacturing & Wholesale Goods"
        }
    ],
    "sg:phone":"+61 2 9759 8833",
    "sg:postcode":"2196",
    "sg:province":"NSW",
    "wof:name":"Omer Tools Pty Ltd",
    "wof:placetype":"venue"
},
  "geometry": {"coordinates":[151.069229,-33.930241],"type":"Point"}
}