{
  "type": "Feature",
  "properties": {
    "addr:full":"7/ 16 Bourke St Wollongong NSW 2500",
    "addr:housenumber":"/ 16",
    "addr:postcode":"2500",
    "addr:street":"Bourke St",
    "iso:country":"AU",
    "sg:address":"7/ 16 Bourke St",
    "sg:city":"Wollongong",
    "sg:classifiers":[
        {
            "category":"Arena",
            "subcategory":"Sports Club",
            "type":"Entertainment"
        }
    ],
    "sg:phone":"+61 2 4226 6313",
    "sg:postcode":"2500",
    "sg:province":"NSW",
    "sg:tags":[
        "defence",
        "supply",
        "self",
        "instruction",
        "martial art"
    ],
    "wof:name":"Budokai",
    "wof:placetype":"venue"
},
  "geometry": {"coordinates":[150.89807099999999,-34.414555],"type":"Point"}
}