{
  "type": "Feature",
  "properties": {
    "addr:full":"Shop 45 Minchinbury Hometown Great Western Hwy Minchinbury NSW 2770",
    "addr:housenumber":"shop 45",
    "addr:postcode":"2770",
    "addr:street":"Great Western Hwy",
    "iso:country":"AU",
    "sg:address":"Shop 45 Minchinbury Hometown Great Western Hwy",
    "sg:city":"Minchinbury",
    "sg:classifiers":[
        {
            "category":"Shopping",
            "subcategory":"Bicycles & Sporting Goods",
            "type":"Retail Goods"
        }
    ],
    "sg:phone":"+61 2 9677 1137",
    "sg:postcode":"2770",
    "sg:province":"NSW",
    "sg:tags":[
        "chemical",
        "equipment",
        "pool",
        "swimming"
    ],
    "wof:name":"Swimart Pool & Spa Services",
    "wof:placetype":"venue"
},
  "geometry": {"coordinates":[150.82574462900001,-33.7820320129],"type":"Point"}
}