{
  "type": "Feature",
  "properties": {
    "iso:country":"AU",
    "sg:address":"61 Wharf St",
    "sg:city":"Forster",
    "sg:classifiers":[
        {
            "category":"Fast Food",
            "type":"Food & Drink"
        }
    ],
    "sg:phone":"+61 2 6554 6595",
    "sg:postcode":"2428",
    "sg:province":"NSW",
    "sg:tags":[
        "away",
        "take"
    ],
    "wof:name":"Chung Wa Chinese Restaurant",
    "wof:placetype":"venue"
},
  "geometry": {"coordinates":[152.511536,-32.180313],"type":"Point"}
}