{
  "type": "Feature",
  "properties": {
    "addr:full":"56 Renver Rd Clayton VIC 3168",
    "addr:housenumber":"56",
    "addr:postcode":"3168",
    "addr:street":"Renver Rd",
    "iso:country":"AU",
    "sg:address":"56 Renver Rd",
    "sg:city":"Clayton",
    "sg:classifiers":[
        {
            "category":"Shopping",
            "subcategory":"Computers & Home Electronics",
            "type":"Retail Goods"
        }
    ],
    "sg:phone":"+61 3 9562 8559",
    "sg:postcode":"3168",
    "sg:province":"VIC",
    "sg:tags":[
        "equipment",
        "part",
        "electronic"
    ],
    "wof:name":"Rockby Electronics Pty Ltd",
    "wof:placetype":"venue"
},
  "geometry": {"coordinates":[145.142776489,-37.9218826294],"type":"Point"}
}