{
  "type": "Feature",
  "properties": {
    "iso:country":"AU",
    "sg:address":"5 Pitt St",
    "sg:city":"Brunswick",
    "sg:classifiers":[
        {
            "category":"Utilities",
            "subcategory":"Electric",
            "type":"Services"
        }
    ],
    "sg:phone":"+61 415 490 234",
    "sg:postcode":"3056",
    "sg:province":"VIC",
    "sg:tags":[
        "electrical",
        "contractor"
    ],
    "wof:name":"Abbot Mike",
    "wof:placetype":"venue"
},
  "geometry": {"coordinates":[144.970703125,-37.7711410522],"type":"Point"}
}