{
  "type": "Feature",
  "properties": {
    "addr:full":"Benz Cellars 111A Spring St Reservoir VIC 3073",
    "addr:housenumber":"111a",
    "addr:postcode":"3073",
    "addr:street":"Spring St",
    "iso:country":"AU",
    "sg:address":"Benz Cellars 111A Spring St",
    "sg:city":"Reservoir",
    "sg:classifiers":[
        {
            "category":"Food & Beverages",
            "subcategory":"Liquor & Beverages",
            "type":"Retail Goods"
        }
    ],
    "sg:phone":"+61 3 9470 1347",
    "sg:postcode":"3073",
    "sg:province":"VIC",
    "sg:tags":[
        "store"
    ],
    "wof:name":"Cheeers",
    "wof:placetype":"venue"
},
  "geometry": {"coordinates":[145.00718689000001,-37.7149772644],"type":"Point"}
}