{
  "type": "Feature",
  "properties": {
    "iso:country":"AU",
    "sg:address":"22 Pearl St",
    "sg:city":"Wivenhoe",
    "sg:classifiers":[
        {
            "category":"Wholesale",
            "subcategory":"Painting Supplies",
            "type":"Manufacturing & Wholesale Goods"
        }
    ],
    "sg:phone":"+61 3 6431 9627",
    "sg:postcode":"7320",
    "sg:province":"TAS",
    "sg:tags":[
        "product",
        "cleaning"
    ],
    "wof:name":"Hunters Products (TAS) Pty Ltd",
    "wof:placetype":"venue"
},
  "geometry": {"coordinates":[145.929337,-41.06905],"type":"Point"}
}