{
  "type": "Feature",
  "properties": {
    "iso:country":"AU",
    "sg:address":"16 Grant St",
    "sg:city":"Ashgrove",
    "sg:classifiers":[
        {
            "category":"Professional",
            "subcategory":"Business Services",
            "type":"Services"
        }
    ],
    "sg:phone":"+61 7 3366 3344",
    "sg:postcode":"4060",
    "sg:province":"QLD",
    "sg:tags":[
        "drafting"
    ],
    "wof:name":"Fryer David",
    "wof:placetype":"venue"
},
  "geometry": {"coordinates":[152.99772644000001,-27.4428482056],"type":"Point"}
}