{
  "type": "Feature",
  "properties": {
    "addr:full":"86 Astor Tce Brisbane QLD 4000",
    "addr:housenumber":"86",
    "addr:postcode":"4000",
    "addr:street":"Astor Tce",
    "iso:country":"AU",
    "sg:address":"86 Astor Tce",
    "sg:city":"Brisbane",
    "sg:classifiers":[
        {
            "category":"Social Services",
            "subcategory":"Child Care",
            "type":"Services"
        }
    ],
    "sg:phone":"+61 7 3832 1219",
    "sg:postcode":"4000",
    "sg:province":"QLD",
    "wof:name":"Brisbane City Child Care",
    "wof:placetype":"venue"
},
  "geometry": {"coordinates":[153.02682495100001,-27.4631061554],"type":"Point"}
}