{
  "type": "Feature",
  "properties": {
    "addr:full":"9 Wills Crt Mooroolbark VIC 3138",
    "addr:housenumber":"9",
    "addr:postcode":"3138",
    "addr:street":"Wills Crt",
    "iso:country":"AU",
    "sg:address":"9 Wills Crt",
    "sg:city":"Mooroolbark",
    "sg:classifiers":[
        {
            "category":"Building & Trades",
            "subcategory":"Construction",
            "type":"Services"
        }
    ],
    "sg:phone":"+61 407 358 520",
    "sg:postcode":"3138",
    "sg:province":"VIC",
    "sg:tags":[
        "renovation",
        "alterations",
        "extension",
        "contractor"
    ],
    "wof:name":"J.E & I.M Groves",
    "wof:placetype":"venue"
},
  "geometry": {"coordinates":[145.338180542,-37.7797355652],"type":"Point"}
}