{
  "type": "Feature",
  "properties": {
    "iso:country":"AU",
    "sg:address":"PO Box 10",
    "sg:city":"West Lakes",
    "sg:classifiers":[
        {
            "category":"Conference Center",
            "type":"Public Place"
        }
    ],
    "sg:phone":"+61 8 8440 6666",
    "sg:postcode":"5021",
    "sg:province":"SA",
    "sg:tags":[
        "venue",
        "convention"
    ],
    "wof:name":"Adelaide Football Club \"The Crows Shed\"",
    "wof:placetype":"venue"
},
  "geometry": {"coordinates":[138.49456787099999,-34.8725700378],"type":"Point"}
}