{
  "type": "Feature",
  "properties": {
    "addr:full":"193 Stud Rd Wantirna VIC 3152",
    "addr:housenumber":"193",
    "addr:postcode":"3152",
    "addr:street":"Stud Rd",
    "iso:country":"AU",
    "sg:address":"193 Stud Rd",
    "sg:city":"Wantirna",
    "sg:classifiers":[
        {
            "category":"Food & Beverages",
            "subcategory":"Supermarket",
            "type":"Retail Goods"
        }
    ],
    "sg:phone":"+61 3 9801 2152",
    "sg:postcode":"3152",
    "sg:province":"VIC",
    "sg:tags":[
        "grocery",
        "store"
    ],
    "wof:name":"Studfield Lic Supermarket",
    "wof:placetype":"venue"
},
  "geometry": {"coordinates":[145.24081420900001,-37.859210968],"type":"Point"}
}