{
  "type": "Feature",
  "properties": {
    "addr:full":"247 Hammond Rd Dandenong VIC 3175",
    "addr:housenumber":"247",
    "addr:postcode":"3175",
    "addr:street":"Hammond Rd",
    "iso:country":"AU",
    "sg:address":"247 Hammond Rd",
    "sg:city":"Dandenong",
    "sg:classifiers":[
        {
            "category":"Retail",
            "subcategory":"Storage",
            "type":"Services"
        }
    ],
    "sg:phone":"+61 3 9791 9040",
    "sg:postcode":"3175",
    "sg:province":"VIC",
    "wof:name":"A Best Value Self Storage",
    "wof:placetype":"venue"
},
  "geometry": {"coordinates":[145.206634522,-38.0099563599],"type":"Point"}
}