{
  "type": "Feature",
  "properties": {
    "iso:country":"AU",
    "sg:address":"PO Box 310",
    "sg:city":"Albert Park",
    "sg:classifiers":[
        {
            "category":"Sports & Exercise",
            "subcategory":"Gym",
            "type":"Entertainment"
        }
    ],
    "sg:phone":"+61 413 838 320",
    "sg:postcode":"3206",
    "sg:province":"VIC",
    "sg:tags":[
        "health",
        "fitness"
    ],
    "wof:name":"U & I Personal & Corporate Fitness Services",
    "wof:placetype":"venue"
},
  "geometry": {"coordinates":[144.951111,-37.844269],"type":"Point"}
}