{
  "type": "Feature",
  "properties": {
    "iso:country":"AU",
    "sg:address":"27 Dunstan Rd",
    "sg:city":"Avonsleigh",
    "sg:classifiers":[
        {
            "category":"Autos & Motor Vehicles",
            "subcategory":"Boat Sales",
            "type":"Retail Goods"
        }
    ],
    "sg:phone":"+61 3 5968 5014",
    "sg:postcode":"3782",
    "sg:province":"VIC",
    "sg:tags":[
        "equipment",
        "yacht"
    ],
    "wof:name":"Anchor Right",
    "wof:placetype":"venue"
},
  "geometry": {"coordinates":[145.47503699999999,-37.925655],"type":"Point"}
}