{
  "type": "Feature",
  "properties": {
    "addr:full":"9 May St Fitzroy North VIC 3068",
    "addr:housenumber":"9",
    "addr:postcode":"3068",
    "addr:street":"May St",
    "iso:country":"AU",
    "sg:address":"9 May St",
    "sg:city":"Fitzroy North",
    "sg:classifiers":[
        {
            "category":"Health Services",
            "subcategory":"Health Practitioner",
            "type":"Services"
        }
    ],
    "sg:phone":"+61 3 9482 4005",
    "sg:postcode":"3068",
    "sg:province":"VIC",
    "sg:tags":[
        "psychologist"
    ],
    "wof:name":"Port Phillip Psychology",
    "wof:placetype":"venue"
},
  "geometry": {"coordinates":[144.98385620100001,-37.7756538391],"type":"Point"}
}