{
  "type": "Feature",
  "properties": {
    "addr:full":"40 Meyer Ave Wangan QLD 4871",
    "addr:housenumber":"40",
    "addr:postcode":"4871",
    "addr:street":"Meyer Ave",
    "iso:country":"AU",
    "sg:address":"40 Meyer Ave",
    "sg:city":"Wangan",
    "sg:classifiers":[
        {
            "category":"Food & Beverages",
            "subcategory":"Bakery",
            "type":"Retail Goods"
        }
    ],
    "sg:phone":"+61 7 4064 2572",
    "sg:postcode":"4871",
    "sg:province":"QLD",
    "sg:tags":[
        "baker"
    ],
    "wof:name":"Wangan Bakery",
    "wof:placetype":"venue"
},
  "geometry": {"coordinates":[146.009277344,-17.5766048431],"type":"Point"}
}