{
  "type": "Feature",
  "properties": {
    "iso:country":"AU",
    "sg:address":"1 Greenfield Rd",
    "sg:city":"Seaview Downs",
    "sg:classifiers":[
        {
            "category":"Arts & Performance",
            "subcategory":"Dance",
            "type":"Entertainment"
        }
    ],
    "sg:phone":"+61 8 8298 1594",
    "sg:postcode":"5049",
    "sg:province":"SA",
    "sg:tags":[
        "theatrical",
        "ballet",
        "tuition"
    ],
    "wof:name":"Pierrot School Of Ballet & Dance",
    "wof:placetype":"venue"
},
  "geometry": {"coordinates":[138.538071,-35.04063],"type":"Point"}
}