{
  "type": "Feature",
  "properties": {
    "iso:country":"AU",
    "sg:address":"Unit 12/ 25 Prince St",
    "sg:city":"Randwick",
    "sg:classifiers":[
        {
            "category":"Utilities",
            "subcategory":"Electric",
            "type":"Services"
        }
    ],
    "sg:phone":"+61 414 659 109",
    "sg:postcode":"2031",
    "sg:province":"NSW",
    "sg:tags":[
        "electrical",
        "contractor"
    ],
    "wof:name":"Eircom Technologies",
    "wof:placetype":"venue"
},
  "geometry": {"coordinates":[151.236602783,-33.9095001221],"type":"Point"}
}