{
  "type": "Feature",
  "properties": {
    "addr:full":"11 Ferguson Rd Moonta SA 5558",
    "addr:housenumber":"11",
    "addr:postcode":"5558",
    "addr:street":"Ferguson Rd",
    "iso:country":"AU",
    "sg:address":"11 Ferguson Rd",
    "sg:city":"Moonta",
    "sg:classifiers":[
        {
            "category":"Home & Garden",
            "subcategory":"Building Materials",
            "type":"Retail Goods"
        }
    ],
    "sg:phone":"+61 8 8825 3711",
    "sg:postcode":"5558",
    "sg:province":"SA",
    "sg:tags":[
        "pre-mixed",
        "concrete"
    ],
    "wof:name":"Peninsula Concrete",
    "wof:placetype":"venue"
},
  "geometry": {"coordinates":[137.59422302199999,-34.0556755066],"type":"Point"}
}