{
  "type": "Feature",
  "properties": {
    "addr:full":"244 Macquarie St Liverpool NSW 2170",
    "addr:housenumber":"244",
    "addr:postcode":"2170",
    "addr:street":"Macquarie St",
    "iso:country":"AU",
    "sg:address":"244 Macquarie St",
    "sg:city":"Liverpool",
    "sg:classifiers":[
        {
            "category":"Shopping",
            "subcategory":"Shoes",
            "type":"Retail Goods"
        }
    ],
    "sg:phone":"+61 2 9602 0239",
    "sg:postcode":"2170",
    "sg:province":"NSW",
    "sg:tags":[
        "footwear"
    ],
    "wof:name":"Payless Shoes Pty Limited",
    "wof:placetype":"venue"
},
  "geometry": {"coordinates":[150.92378234899999,-33.9231071472],"type":"Point"}
}