{
  "type": "Feature",
  "properties": {
    "iso:country":"AU",
    "sg:address":"6 High St",
    "sg:city":"Willunga",
    "sg:classifiers":[
        {
            "category":"Professional",
            "subcategory":"Employment Agencies",
            "type":"Services"
        }
    ],
    "sg:phone":"+61 8 8556 4311",
    "sg:postcode":"5172",
    "sg:province":"SA",
    "sg:tags":[
        "provider",
        "internet"
    ],
    "wof:name":"Intertech.Net.Au",
    "wof:placetype":"venue"
},
  "geometry": {"coordinates":[138.55462646500001,-35.2722129822],"type":"Point"}
}