{
  "type": "Feature",
  "properties": {
    "addr:full":"Level 1, 4 Avoca St South Yarra VIC 3141",
    "addr:housenumber":"4",
    "addr:postcode":"3141",
    "addr:street":"Avoca St",
    "iso:country":"AU",
    "sg:address":"Level 1, 4 Avoca St",
    "sg:city":"South Yarra",
    "sg:classifiers":[
        {
            "category":"Professional",
            "subcategory":"Management & Consulting",
            "type":"Services"
        }
    ],
    "sg:phone":"+61 3 9866 8977",
    "sg:postcode":"3141",
    "sg:province":"VIC",
    "sg:tags":[
        "consultant",
        "migration"
    ],
    "wof:name":"All Immigration Services",
    "wof:placetype":"venue"
},
  "geometry": {"coordinates":[144.989303589,-37.8383102417],"type":"Point"}
}