{
  "type": "Feature",
  "properties": {
    "addr:full":"Shop 11/ 4 Gibson Way Noosaville QLD 4566",
    "addr:housenumber":"shop 11 / 4",
    "addr:postcode":"4566",
    "addr:street":"Gibson Way",
    "iso:country":"AU",
    "sg:address":"Shop 11/ 4",
    "sg:city":"Gibson Way Noosaville",
    "sg:classifiers":[
        {
            "category":"Shopping",
            "subcategory":"Clothing, Apparel, & Fashions",
            "type":"Retail Goods"
        }
    ],
    "sg:phone":"+61 7 5474 1200",
    "sg:postcode":"4566",
    "sg:province":"QLD",
    "sg:tags":[
        "lady",
        "wear"
    ],
    "wof:name":"Youth Culture",
    "wof:placetype":"venue"
},
  "geometry": {"coordinates":[153.056884766,-26.4013824463],"type":"Point"}
}