{
  "type": "Feature",
  "properties": {
    "iso:country":"AU",
    "sg:address":"19 Waterloo St",
    "sg:city":"Wandoan",
    "sg:classifiers":[
        {
            "category":"Education",
            "subcategory":"Kindergarten",
            "type":"Public Place"
        }
    ],
    "sg:phone":"+61 7 4627 4102",
    "sg:postcode":"4419",
    "sg:province":"QLD",
    "sg:tags":[
        "pre-schools"
    ],
    "wof:name":"Wandoan Kindergarten",
    "wof:placetype":"venue"
},
  "geometry": {"coordinates":[149.96131897000001,-26.1181201935],"type":"Point"}
}