{
  "type": "Feature",
  "properties": {
    "iso:country":"AU",
    "sg:address":"11 Foundry Rd",
    "sg:city":"Seven Hills",
    "sg:classifiers":[
        {
            "category":"Wholesale",
            "subcategory":"Painting Supplies",
            "type":"Manufacturing & Wholesale Goods"
        }
    ],
    "sg:phone":"+61 2 9674 6635",
    "sg:postcode":"2147",
    "sg:province":"NSW",
    "sg:tags":[
        "product",
        "cleaning"
    ],
    "wof:name":"Merzo Vac Pty Ltd",
    "wof:placetype":"venue"
},
  "geometry": {"coordinates":[150.95614624000001,-33.7674980164],"type":"Point"}
}