{
  "type": "Feature",
  "properties": {
    "iso:country":"AU",
    "sg:address":"52 Myer St",
    "sg:city":"Lakes Entrance",
    "sg:classifiers":[
        {
            "category":"Cinema",
            "subcategory":"Movie Theater",
            "type":"Entertainment"
        }
    ],
    "sg:phone":"+61 3 5155 1941",
    "sg:postcode":"3909",
    "sg:province":"VIC",
    "wof:name":"Lakes Squash & Movie Theatre",
    "wof:placetype":"venue"
},
  "geometry": {"coordinates":[147.99452209500001,-37.8763046265],"type":"Point"}
}