{
  "type": "Feature",
  "properties": {
    "iso:country":"AU",
    "sg:address":"66-72 Leader St",
    "sg:city":"Forestville",
    "sg:classifiers":[
        {
            "category":"Arts & Performance",
            "subcategory":"Music",
            "type":"Entertainment"
        }
    ],
    "sg:phone":"+61 1800 333 562",
    "sg:postcode":"5035",
    "sg:province":"SA",
    "sg:tags":[
        "mobile",
        "jockey",
        "disc"
    ],
    "wof:name":"DJ/MC Bootcamp School",
    "wof:placetype":"venue"
},
  "geometry": {"coordinates":[138.58274841299999,-34.9487762451],"type":"Point"}
}