{
  "type": "Feature",
  "properties": {
    "addr:full":"Eagle St Brisbane QLD 4000",
    "addr:postcode":"4000",
    "addr:street":"Eagle St",
    "iso:country":"AU",
    "sg:address":"Eagle St",
    "sg:city":"Brisbane",
    "sg:classifiers":[
        {
            "category":"Shopping",
            "subcategory":"Crafts & Fabrics",
            "type":"Retail Goods"
        }
    ],
    "sg:phone":"+61 7 3014 6448",
    "sg:postcode":"4000",
    "sg:province":"QLD",
    "sg:tags":[
        "supply"
    ],
    "wof:name":"Mosaics 4 U",
    "wof:placetype":"venue"
},
  "geometry": {"coordinates":[153.03030395499999,-27.4660606384],"type":"Point"}
}