{
  "type": "Feature",
  "properties": {
    "addr:full":"32 Rock St Scarborough QLD 4020",
    "addr:housenumber":"32",
    "addr:postcode":"4020",
    "addr:street":"Rock St",
    "iso:country":"AU",
    "sg:address":"32 Rock St",
    "sg:city":"Scarborough",
    "sg:classifiers":[
        {
            "category":"Autos & Motor Vehicles",
            "subcategory":"Boat Sales",
            "type":"Retail Goods"
        }
    ],
    "sg:phone":"+61 7 3203 5333",
    "sg:postcode":"4020",
    "sg:province":"QLD",
    "sg:tags":[
        "equipment",
        "yacht"
    ],
    "wof:name":"Galliers Hardware",
    "wof:placetype":"venue"
},
  "geometry": {"coordinates":[153.11230499999999,-27.197563],"type":"Point"}
}