{
  "type": "Feature",
  "properties": {
    "iso:country":"AU",
    "sg:address":"15 Moore St",
    "sg:city":"Boat Harbour",
    "sg:classifiers":[
        {
            "category":"Home & Garden",
            "subcategory":"Building Materials",
            "type":"Retail Goods"
        }
    ],
    "sg:phone":"+61 417 553 877",
    "sg:postcode":"7321",
    "sg:province":"TAS",
    "sg:tags":[
        "lawn",
        "cutting",
        "maintenance"
    ],
    "wof:name":"1st Class Lawn Mowing Service",
    "wof:placetype":"venue"
},
  "geometry": {"coordinates":[145.61587499999999,-40.928707],"type":"Point"}
}