{
  "type": "Feature",
  "properties": {
    "addr:full":"Suite 1 Grd Flr 38 Chandos St St Leonards NSW 2065",
    "addr:postcode":"2065",
    "addr:street":"Grd;Chandos St",
    "iso:country":"AU",
    "sg:address":"Suite 1 Grd Flr 38 Chandos St St",
    "sg:city":"Leonards",
    "sg:classifiers":[
        {
            "category":"Organizations",
            "subcategory":"Professional Association",
            "type":"Services"
        }
    ],
    "sg:phone":"+61 1300 668 399",
    "sg:postcode":"2065",
    "sg:province":"NSW",
    "sg:tags":[
        "web",
        "internet"
    ],
    "wof:name":"Net Starter",
    "wof:placetype":"venue"
},
  "geometry": {"coordinates":[151.19671630900001,-33.8218841553],"type":"Point"}
}