{
  "type": "Feature",
  "properties": {
    "iso:country":"AU",
    "sg:address":"Shp 28, Dalby Shopng World, Cunningham St",
    "sg:city":"Dalby",
    "sg:classifiers":[
        {
            "category":"Education",
            "subcategory":"School",
            "type":"Public Place"
        }
    ],
    "sg:phone":"+61 7 4662 2293",
    "sg:postcode":"4405",
    "sg:province":"QLD",
    "sg:tags":[
        "supply"
    ],
    "wof:name":"Cunningham Street News",
    "wof:placetype":"venue"
},
  "geometry": {"coordinates":[151.26278686500001,-27.1840324402],"type":"Point"}
}