{
  "type": "Feature",
  "properties": {
    "iso:country":"AU",
    "sg:address":"1 Spring St",
    "sg:city":"Chatswood",
    "sg:classifiers":[
        {
            "category":"Insurance",
            "subcategory":"Hazard Insurance",
            "type":"Services"
        }
    ],
    "sg:phone":"+61 13 21 32",
    "sg:postcode":"2057",
    "sg:province":"NSW",
    "sg:tags":[
        "motor",
        "vehicle"
    ],
    "wof:name":"NRMA Insurance",
    "wof:placetype":"venue"
},
  "geometry": {"coordinates":[151.185196,-33.797199],"type":"Point"}
}