{
  "type": "Feature",
  "properties": {
    "iso:country":"AU",
    "sg:address":"160 Long Rd",
    "sg:city":"Eagle Heights",
    "sg:classifiers":[
        {
            "category":"Retail",
            "subcategory":"Event Space",
            "type":"Services"
        }
    ],
    "sg:phone":"+61 7 5545 1044",
    "sg:postcode":"4271",
    "sg:province":"QLD",
    "sg:tags":[
        "venue",
        "reception",
        "wedding"
    ],
    "wof:name":"Bungunyah Manor",
    "wof:placetype":"venue"
},
  "geometry": {"coordinates":[153.20048523,-27.9265899658],"type":"Point"}
}