{
  "type": "Feature",
  "properties": {
    "iso:country":"AU",
    "sg:address":"322 Portrush Rd",
    "sg:city":"Marryatville",
    "sg:classifiers":[
        {
            "category":"Education",
            "subcategory":"Kindergarten",
            "type":"Public Place"
        }
    ],
    "sg:phone":"+61 8 8331 2509",
    "sg:postcode":"5068",
    "sg:province":"SA",
    "sg:tags":[
        "pre-schools"
    ],
    "wof:name":"Babthorpe Montessori Preschool",
    "wof:placetype":"venue"
},
  "geometry": {"coordinates":[138.64187622099999,-34.92993927],"type":"Point"}
}