{
  "type": "Feature",
  "properties": {
    "iso:country":"AU",
    "sg:address":"Suite: 1, Level: 1 414 Victoria Ave",
    "sg:city":"Chatswood",
    "sg:classifiers":[
        {
            "category":"Professional",
            "subcategory":"Accounting & Tax Preparation",
            "type":"Services"
        }
    ],
    "sg:phone":"+61 2 9419 8339",
    "sg:postcode":"2067",
    "sg:province":"NSW",
    "sg:tags":[
        "accountant",
        "auditor"
    ],
    "wof:name":"Chats Accountants & Advisors",
    "wof:placetype":"venue"
},
  "geometry": {"coordinates":[151.18208313,-33.7966651917],"type":"Point"}
}