{
  "type": "Feature",
  "properties": {
    "addr:full":"Unit 1/ 14 Bannick Crt Canning Vale WA 6155",
    "addr:postcode":"6155",
    "addr:street":"14 Bannick Crt",
    "iso:country":"AU",
    "sg:address":"Unit 1/ 14 Bannick Crt",
    "sg:city":"Canning Vale",
    "sg:classifiers":[
        {
            "category":"Utilities",
            "subcategory":"Electric",
            "type":"Services"
        }
    ],
    "sg:phone":"+61 8 9455 4465",
    "sg:postcode":"6155",
    "sg:province":"WA",
    "sg:tags":[
        "electrical",
        "contractor"
    ],
    "wof:name":"Electrical Mining Services",
    "wof:placetype":"venue"
},
  "geometry": {"coordinates":[115.924049,-32.063305],"type":"Point"}
}