{
  "type": "Feature",
  "properties": {
    "iso:country":"AU",
    "sg:address":"Unit 15 36- 38 Tikilara St",
    "sg:city":"Regency Park",
    "sg:classifiers":[
        {
            "category":"Manufacturing",
            "subcategory":"Tools & Machinery",
            "type":"Manufacturing & Wholesale Goods"
        }
    ],
    "sg:phone":"+61 411 665 881",
    "sg:postcode":"5010",
    "sg:province":"SA",
    "wof:name":"Ellis Tools",
    "wof:placetype":"venue"
},
  "geometry": {"coordinates":[138.57322692899999,-34.8674468994],"type":"Point"}
}