{
  "type": "Feature",
  "properties": {
    "iso:country":"AU",
    "sg:address":"4/ 5 Collingwood St",
    "sg:city":"Osborne Park",
    "sg:classifiers":[
        {
            "category":"Real Estate",
            "subcategory":"Real Estate Agent",
            "type":"Services"
        }
    ],
    "sg:phone":"+61 8 9446 4377",
    "sg:postcode":"6017",
    "sg:province":"WA",
    "sg:tags":[
        "export"
    ],
    "wof:name":"Kimseed International Pty Ltd",
    "wof:placetype":"venue"
},
  "geometry": {"coordinates":[115.816612244,-31.9042224884],"type":"Point"}
}