{
  "type": "Feature",
  "properties": {
    "addr:full":"50 East St Harden NSW 2587",
    "addr:housenumber":"50",
    "addr:postcode":"2587",
    "addr:street":"East St",
    "iso:country":"AU",
    "sg:address":"50 East St",
    "sg:city":"Harden",
    "sg:classifiers":[
        {
            "category":"Farming",
            "subcategory":"Farm & Veterinary Services",
            "type":"Manufacturing & Wholesale Goods"
        }
    ],
    "sg:phone":"+61 2 6386 2430",
    "sg:postcode":"2587",
    "sg:province":"NSW",
    "sg:tags":[
        "agricultural",
        "advisory"
    ],
    "wof:name":"Wright A J",
    "wof:placetype":"venue"
},
  "geometry": {"coordinates":[148.36582946799999,-34.5587234497],"type":"Point"}
}