{
  "type": "Feature",
  "properties": {
    "addr:full":"19 Badminton Rd Croydon NSW 2132",
    "addr:housenumber":"19",
    "addr:postcode":"2132",
    "addr:street":"Badminton Rd",
    "iso:country":"AU",
    "sg:address":"19 Badminton Rd",
    "sg:city":"Croydon",
    "sg:classifiers":[
        {
            "category":"Health Services",
            "subcategory":"Nursing And Care Facility",
            "type":"Services"
        }
    ],
    "sg:phone":"+61 2 9744 7484",
    "sg:postcode":"2132",
    "sg:province":"NSW",
    "sg:tags":[
        "home"
    ],
    "wof:name":"Newhaven Nursing Home",
    "wof:placetype":"venue"
},
  "geometry": {"coordinates":[151.10716247600001,-33.8875732422],"type":"Point"}
}