{
  "type": "Feature",
  "properties": {
    "iso:country":"AU",
    "sg:address":"6e Louise Ave",
    "sg:city":"Ingleburn",
    "sg:classifiers":[
        {
            "category":"Manufacturing",
            "subcategory":"Metals",
            "type":"Manufacturing & Wholesale Goods"
        }
    ],
    "sg:phone":"+61 418 110 485",
    "sg:postcode":"2565",
    "sg:province":"NSW",
    "sg:tags":[
        "steel",
        "fabricator",
        "mfrs"
    ],
    "wof:name":"Forward Fabrications Pty Ltd",
    "wof:placetype":"venue"
},
  "geometry": {"coordinates":[150.86593627900001,-33.9953041077],"type":"Point"}
}