{
  "type": "Feature",
  "properties": {
    "addr:full":"Shop 4 & 5 Donellan Place, 21 Campbell St Blacktown NSW 2148",
    "addr:housenumber":"shop 4 & 5;21",
    "addr:postcode":"2148",
    "addr:street":"Donellan Place;Campbell St",
    "iso:country":"AU",
    "sg:address":"Shop 4 & 5 Donellan Place, 21 Campbell St",
    "sg:city":"Blacktown",
    "sg:classifiers":[
        {
            "category":"Professional",
            "subcategory":"Management & Consulting",
            "type":"Services"
        }
    ],
    "sg:phone":"+61 2 9678 9733",
    "sg:postcode":"2148",
    "sg:province":"NSW",
    "sg:tags":[
        "consultant",
        "business"
    ],
    "wof:name":"Blacktown BEC#",
    "wof:placetype":"venue"
},
  "geometry": {"coordinates":[150.90927124000001,-33.7714271545],"type":"Point"}
}