{
  "type": "Feature",
  "properties": {
    "iso:country":"AU",
    "sg:address":"82 Hastings Rd",
    "sg:city":"Terrigal",
    "sg:classifiers":[
        {
            "category":"Personal",
            "subcategory":"Massage",
            "type":"Services"
        }
    ],
    "sg:phone":"+61 417 230 842",
    "sg:postcode":"2260",
    "sg:province":"NSW",
    "sg:tags":[
        "therapy"
    ],
    "wof:name":"Bernadette Leiser",
    "wof:placetype":"venue"
},
  "geometry": {"coordinates":[151.432297,-33.436001],"type":"Point"}
}