{
  "type": "Feature",
  "properties": {
    "iso:country":"AU",
    "sg:address":"Cnr Pinjarra Rd & Sutton St",
    "sg:city":"Mandurah",
    "sg:classifiers":[
        {
            "category":"Building & Trades",
            "subcategory":"Locksmith",
            "type":"Services"
        }
    ],
    "sg:phone":"+61 8 9535 5951",
    "sg:postcode":"6210",
    "sg:province":"WA",
    "sg:tags":[
        "lock"
    ],
    "wof:name":"Mandurah Lock & Key",
    "wof:placetype":"venue"
},
  "geometry": {"coordinates":[115.762833,-32.540085],"type":"Point"}
}