{
  "type": "Feature",
  "properties": {
    "addr:full":"296 Coode St Bedford WA 6052",
    "addr:housenumber":"296",
    "addr:postcode":"6052",
    "addr:street":"Coode St",
    "iso:country":"AU",
    "sg:address":"296 Coode St",
    "sg:city":"Bedford",
    "sg:classifiers":[
        {
            "category":"Farming",
            "subcategory":"Farm & Veterinary Services",
            "type":"Manufacturing & Wholesale Goods"
        }
    ],
    "sg:phone":"+61 8 9276 1849",
    "sg:postcode":"6052",
    "sg:province":"WA",
    "sg:tags":[
        "worm"
    ],
    "wof:name":"Bedford Earth Worms Fertilizer",
    "wof:placetype":"venue"
},
  "geometry": {"coordinates":[115.900650024,-31.9093952179],"type":"Point"}
}