{
  "type": "Feature",
  "properties": {
    "addr:full":"PO Box 117 Miller NSW 2168",
    "addr:postcode":"2168",
    "iso:country":"AU",
    "sg:address":"PO Box 117",
    "sg:city":"Miller",
    "sg:classifiers":[
        {
            "category":"Personal",
            "type":"Services"
        }
    ],
    "sg:phone":"+61 2 9467 5367",
    "sg:postcode":"2168",
    "sg:province":"NSW",
    "sg:tags":[
        "reducing",
        "treatment",
        "weight"
    ],
    "wof:name":"Herbalife Narellan",
    "wof:placetype":"venue"
},
  "geometry": {"coordinates":[150.88563537600001,-33.9202804565],"type":"Point"}
}