{
  "type": "Feature",
  "properties": {
    "iso:country":"AU",
    "sg:address":"64 Darlinghurst Rd",
    "sg:city":"Kings Cross",
    "sg:classifiers":[
        {
            "category":"Travel",
            "subcategory":"Hotels & Motels",
            "type":"Entertainment"
        }
    ],
    "sg:phone":"+61 2 9358 5977",
    "sg:postcode":"2011",
    "sg:province":"NSW",
    "sg:tags":[
        "accommodation"
    ],
    "wof:name":"Alice's Tudor Private Hotel",
    "wof:placetype":"venue"
},
  "geometry": {"coordinates":[151.222732544,-33.8747634888],"type":"Point"}
}