{
  "type": "Feature",
  "properties": {
    "iso:country":"AU",
    "sg:address":"15 Pike St",
    "sg:city":"Camperdown",
    "sg:classifiers":[
        {
            "category":"Health Services",
            "subcategory":"Chiropractor",
            "type":"Services"
        }
    ],
    "sg:phone":"+61 3 5593 3220",
    "sg:postcode":"3260",
    "sg:province":"VIC",
    "wof:name":"McIlveen Ross Dr",
    "wof:placetype":"venue"
},
  "geometry": {"coordinates":[143.14768981899999,-38.2317085266],"type":"Point"}
}