{
  "type": "Feature",
  "properties": {
    "addr:full":"1117 Burwood Hwy Ferntree Gully VIC 3156",
    "addr:housenumber":"1117",
    "addr:postcode":"3156",
    "addr:street":"Burwood Hwy",
    "iso:country":"AU",
    "sg:address":"1117 Burwood Hwy",
    "sg:city":"Ferntree Gully",
    "sg:classifiers":[
        {
            "category":"Food & Beverages",
            "subcategory":"Bakery",
            "type":"Retail Goods"
        }
    ],
    "sg:phone":"+61 3 9753 5000",
    "sg:postcode":"3156",
    "sg:province":"VIC",
    "sg:tags":[
        "cake",
        "shop",
        "pastry"
    ],
    "wof:name":"Cheesecake Shop The",
    "wof:placetype":"venue"
},
  "geometry": {"coordinates":[145.29646301299999,-37.8883628845],"type":"Point"}
}