{
  "type": "Feature",
  "properties": {
    "addr:full":"Obi La Maleny QLD 4552",
    "addr:postcode":"4552",
    "addr:street":"La Maleny",
    "iso:country":"AU",
    "sg:address":"Obi La",
    "sg:city":"Maleny",
    "sg:classifiers":[
        {
            "category":"Shopping",
            "subcategory":"Computers & Home Electronics",
            "type":"Retail Goods"
        }
    ],
    "sg:phone":"+61 7 5494 2563",
    "sg:postcode":"4552",
    "sg:province":"QLD",
    "sg:tags":[
        "equipment",
        "supply"
    ],
    "wof:name":"Green Office Australia",
    "wof:placetype":"venue"
},
  "geometry": {"coordinates":[152.86558532699999,-26.7556495667],"type":"Point"}
}