{
  "type": "Feature",
  "properties": {
    "addr:full":"Cnr Golflinks & Frankston-Flinders Rds Frankston VIC 3199",
    "addr:postcode":"3199",
    "addr:street":"Cnr",
    "iso:country":"AU",
    "sg:address":"Cnr Golflinks & Frankston-Flinders Rds",
    "sg:city":"Frankston",
    "sg:classifiers":[
        {
            "category":"Autos & Motor Vehicles",
            "subcategory":"Fuel & Gas Station",
            "type":"Retail Goods"
        }
    ],
    "sg:phone":"+61 3 9783 4446",
    "sg:postcode":"3199",
    "sg:province":"VIC",
    "wof:name":"BP Australia Pty Ltd",
    "wof:placetype":"venue"
},
  "geometry": {"coordinates":[145.14096069300001,-38.1831169128],"type":"Point"}
}