{
  "type": "Feature",
  "properties": {
    "addr:full":"Unit 5/ 20 Elmsfield Rd Midvale WA 6056",
    "addr:postcode":"6056",
    "addr:street":"20 Elmsfield Rd",
    "iso:country":"AU",
    "sg:address":"Unit 5/ 20 Elmsfield Rd",
    "sg:city":"Midvale",
    "sg:classifiers":[
        {
            "category":"Building & Trades",
            "subcategory":"Construction",
            "type":"Services"
        }
    ],
    "sg:phone":"+61 8 9257 1541",
    "sg:postcode":"6056",
    "sg:province":"WA",
    "sg:tags":[
        "welding"
    ],
    "wof:name":"Studweld International",
    "wof:placetype":"venue"
},
  "geometry": {"coordinates":[116.03504180900001,-31.8914775848],"type":"Point"}
}