{
  "type": "Feature",
  "properties": {
    "addr:full":"35 Boulter St Berrimah NT 0828",
    "addr:housenumber":"35",
    "addr:postcode":"nt 0828",
    "addr:street":"Boulter St",
    "iso:country":"AU",
    "sg:address":"35 Boulter St",
    "sg:city":"Berrimah",
    "sg:classifiers":[
        {
            "category":"Home & Garden",
            "subcategory":"Garden Supply",
            "type":"Retail Goods"
        }
    ],
    "sg:phone":"+61 8 8947 4458",
    "sg:postcode":"0828",
    "sg:province":"NT",
    "sg:tags":[
        "equipment"
    ],
    "wof:name":"Marrara Garden Centre",
    "wof:placetype":"venue"
},
  "geometry": {"coordinates":[130.91583251899999,-12.4136428833],"type":"Point"}
}