{
  "type": "Feature",
  "properties": {
    "iso:country":"AU",
    "sg:address":"28 Diamond Drv",
    "sg:city":"Ocean Reef",
    "sg:classifiers":[
        {
            "category":"Professional",
            "subcategory":"Art Services",
            "type":"Services"
        }
    ],
    "sg:phone":"+61 404 036 455",
    "sg:postcode":"6027",
    "sg:province":"WA",
    "sg:tags":[
        "graphic",
        "designer"
    ],
    "wof:name":"Xsight Graphic Design",
    "wof:placetype":"venue"
},
  "geometry": {"coordinates":[115.736930847,-31.7682781219],"type":"Point"}
}