{
  "type": "Feature",
  "properties": {
    "addr:full":"Unit 4/ 182 Winton Rd Joondalup WA 6027",
    "addr:housenumber":"/ 182",
    "addr:postcode":"6027",
    "addr:street":"Winton Rd",
    "iso:country":"AU",
    "sg:address":"Unit 4/ 182 Winton Rd",
    "sg:city":"Joondalup",
    "sg:classifiers":[
        {
            "category":"Home & Garden",
            "subcategory":"Carpets & Floor Coverings",
            "type":"Retail Goods"
        }
    ],
    "sg:phone":"+61 8 9300 0076",
    "sg:postcode":"6027",
    "sg:province":"WA",
    "sg:tags":[
        "tile",
        "wall"
    ],
    "wof:name":"Harmony Tiles",
    "wof:placetype":"venue"
},
  "geometry": {"coordinates":[115.76249694800001,-31.7436466217],"type":"Point"}
}