{
  "type": "Feature",
  "properties": {
    "addr:full":"Unit 11 / 11 McKay Gardns Turner ACT 2612",
    "addr:housenumber":"/ 11",
    "addr:postcode":"2612",
    "addr:street":"Mckay Gardns",
    "iso:country":"AU",
    "sg:address":"Unit 11",
    "sg:city":"/ 11 McKay Gardns Turner",
    "sg:classifiers":[
        {
            "category":"Health Services",
            "subcategory":"Health Practitioner",
            "type":"Services"
        }
    ],
    "sg:phone":"+61 2 6247 5710",
    "sg:postcode":"2612",
    "sg:province":"ACT",
    "sg:tags":[
        "psychologist"
    ],
    "wof:name":"Peters Merilyn",
    "wof:placetype":"venue"
},
  "geometry": {"coordinates":[149.126556397,-35.2747383118],"type":"Point"}
}