{
  "type": "Feature",
  "properties": {
    "addr:full":"32 Moonee St Coffs Harbour NSW 2450",
    "addr:housenumber":"32",
    "addr:postcode":"2450",
    "addr:street":"Moonee St",
    "iso:country":"AU",
    "sg:address":"32 Moonee St",
    "sg:city":"Coffs Harbour",
    "sg:classifiers":[
        {
            "category":"Building & Trades",
            "subcategory":"Construction",
            "type":"Services"
        }
    ],
    "sg:phone":"+61 2 6650 3300",
    "sg:postcode":"2450",
    "sg:province":"NSW",
    "sg:tags":[
        "contractor"
    ],
    "wof:name":"Hibbards",
    "wof:placetype":"venue"
},
  "geometry": {"coordinates":[153.11262500000001,-30.296818],"type":"Point"}
}