{
  "type": "Feature",
  "properties": {
    "addr:full":"69 Lance Crs Greystanes NSW 2145",
    "addr:housenumber":"69",
    "addr:postcode":"2145",
    "addr:street":"Lance Crs",
    "iso:country":"AU",
    "sg:address":"69 Lance Crs",
    "sg:city":"Greystanes",
    "sg:classifiers":[
        {
            "category":"Home & Garden",
            "subcategory":"Carpets & Floor Coverings",
            "type":"Retail Goods"
        }
    ],
    "sg:phone":"+61 2 9636 5176",
    "sg:postcode":"2145",
    "sg:province":"NSW",
    "sg:tags":[
        "tile",
        "wall",
        "layer"
    ],
    "wof:name":"L. & R. Fenech Tiling",
    "wof:placetype":"venue"
},
  "geometry": {"coordinates":[150.94769287099999,-33.8190307617],"type":"Point"}
}