{
  "type": "Feature",
  "properties": {
    "iso:country":"AU",
    "sg:address":"Shed 1/ 76 Winnellie Rd",
    "sg:city":"Winnellie",
    "sg:classifiers":[
        {
            "category":"Retail",
            "subcategory":"Auto Repair",
            "type":"Services"
        }
    ],
    "sg:phone":"+61 8 8947 0910",
    "sg:postcode":"0820",
    "sg:province":"NT",
    "sg:tags":[
        "body",
        "motor",
        "trimmer"
    ],
    "wof:name":"All Car Upholstery",
    "wof:placetype":"venue"
},
  "geometry": {"coordinates":[130.87971496599999,-12.4267578125],"type":"Point"}
}