{
  "type": "Feature",
  "properties": {
    "addr:full":"PO Box 217 Churchill VIC 3842",
    "addr:postcode":"3842",
    "iso:country":"AU",
    "sg:address":"PO Box 217",
    "sg:city":"Churchill",
    "sg:classifiers":[
        {
            "category":"Building & Trades",
            "subcategory":"Plumbing",
            "type":"Services"
        }
    ],
    "sg:phone":"+61 3 5122 2543",
    "sg:postcode":"3842",
    "sg:province":"VIC",
    "sg:tags":[
        "plumber",
        "gasfitters"
    ],
    "wof:name":"Grisotto Plumbing Pty Ltd",
    "wof:placetype":"venue"
},
  "geometry": {"coordinates":[146.42181396500001,-38.3153915405],"type":"Point"}
}