{
  "type": "Feature",
  "properties": {
    "addr:full":"99 Forbes St Woolloomooloo NSW 2011",
    "addr:housenumber":"99",
    "addr:postcode":"2011",
    "addr:street":"Forbes St",
    "iso:country":"AU",
    "sg:address":"99 Forbes St",
    "sg:city":"Woolloomooloo",
    "sg:classifiers":[
        {
            "category":"Real Estate",
            "subcategory":"Real Estate Agent",
            "type":"Services"
        }
    ],
    "sg:phone":"+61 2 9357 9200",
    "sg:postcode":"2011",
    "sg:province":"NSW",
    "wof:name":"Mirvac Real Estate Pty Ltd",
    "wof:placetype":"venue"
},
  "geometry": {"coordinates":[151.21942138700001,-33.87292099],"type":"Point"}
}