{
  "type": "Feature",
  "properties": {
    "iso:country":"AU",
    "sg:address":"Shop 6 Huon Central Main Rd",
    "sg:city":"Huonville",
    "sg:classifiers":[
        {
            "category":"Personal",
            "subcategory":"Skin Care",
            "type":"Services"
        }
    ],
    "sg:phone":"+61 3 6264 1314",
    "sg:postcode":"7109",
    "sg:province":"TAS",
    "sg:tags":[
        "hair",
        "product"
    ],
    "wof:name":"Nix Hair Studio",
    "wof:placetype":"venue"
},
  "geometry": {"coordinates":[147.03529357900001,-43.0090560913],"type":"Point"}
}