{
  "type": "Feature",
  "properties": {
    "addr:full":"150 Park Ave Kotara NSW 2289",
    "addr:housenumber":"150",
    "addr:postcode":"2289",
    "addr:street":"Park Ave",
    "iso:country":"AU",
    "sg:address":"150 Park Ave",
    "sg:city":"Kotara",
    "sg:classifiers":[
        {
            "category":"Autos & Motor Vehicles",
            "subcategory":"Automobile Sales",
            "type":"Retail Goods"
        }
    ],
    "sg:phone":"+61 2 4956 2111",
    "sg:postcode":"2289",
    "sg:province":"NSW",
    "sg:tags":[
        "car",
        "used"
    ],
    "wof:name":"Valley Auction Group",
    "wof:placetype":"venue"
},
  "geometry": {"coordinates":[151.69534301799999,-32.9431152344],"type":"Point"}
}