{
  "type": "Feature",
  "properties": {
    "iso:country":"AU",
    "sg:address":"95- 99 Bridge Rd",
    "sg:city":"Glebe",
    "sg:classifiers":[
        {
            "category":"Home & Garden",
            "subcategory":"Carpets & Floor Coverings",
            "type":"Retail Goods"
        }
    ],
    "sg:phone":"+61 2 9692 8822",
    "sg:postcode":"2037",
    "sg:province":"NSW",
    "wof:name":"Whitecliffe Imports",
    "wof:placetype":"venue"
},
  "geometry": {"coordinates":[151.18853759800001,-33.8786659241],"type":"Point"}
}