{
  "type": "Feature",
  "properties": {
    "addr:full":"364 Main North Rd Blair Athol SA 5084",
    "addr:housenumber":"364",
    "addr:postcode":"5084",
    "addr:street":"Main North Rd",
    "iso:country":"AU",
    "sg:address":"364 Main North Rd",
    "sg:city":"Blair Athol",
    "sg:classifiers":[
        {
            "category":"Retail",
            "subcategory":"Funeral Services",
            "type":"Services"
        }
    ],
    "sg:phone":"+61 8 8293 2121",
    "sg:postcode":"5084",
    "sg:province":"SA",
    "sg:tags":[
        "director"
    ],
    "wof:name":"Affordable Funerals",
    "wof:placetype":"venue"
},
  "geometry": {"coordinates":[138.60113525400001,-34.8652381897],"type":"Point"}
}