{
  "type": "Feature",
  "properties": {
    "addr:full":"81 Cantrell St Yagoona NSW 2199",
    "addr:housenumber":"81",
    "addr:postcode":"2199",
    "addr:street":"Cantrell St",
    "iso:country":"AU",
    "sg:address":"81 Cantrell St",
    "sg:city":"Yagoona",
    "sg:classifiers":[
        {
            "category":"Building & Trades",
            "subcategory":"Construction",
            "type":"Services"
        }
    ],
    "sg:phone":"+61 416 217 537",
    "sg:postcode":"2199",
    "sg:province":"NSW",
    "sg:tags":[
        "rendering",
        "cement"
    ],
    "wof:name":"M & S Superior Renda",
    "wof:placetype":"venue"
},
  "geometry": {"coordinates":[151.0121,-33.911949],"type":"Point"}
}