{
  "type": "Feature",
  "properties": {
    "iso:country":"AU",
    "sg:address":"1 Avoca St",
    "sg:city":"Yagoona",
    "sg:classifiers":[
        {
            "category":"Wholesale",
            "subcategory":"Office Equipment",
            "type":"Manufacturing & Wholesale Goods"
        }
    ],
    "sg:phone":"+61 2 9793 2444",
    "sg:postcode":"2199",
    "sg:province":"NSW",
    "sg:tags":[
        "nail",
        "nailing"
    ],
    "wof:name":"Ray White Nailgun Repairs",
    "wof:placetype":"venue"
},
  "geometry": {"coordinates":[151.03185999999999,-33.907124],"type":"Point"}
}