{
  "type": "Feature",
  "properties": {
    "addr:full":"6 Buch Ave Epping VIC 3076",
    "addr:housenumber":"6",
    "addr:postcode":"3076",
    "addr:street":"Buch Ave",
    "iso:country":"AU",
    "sg:address":"6 Buch Ave",
    "sg:city":"Epping",
    "sg:classifiers":[
        {
            "category":"Retail",
            "subcategory":"Auto Repair",
            "type":"Services"
        }
    ],
    "sg:phone":"+61 3 9408 4988",
    "sg:postcode":"3076",
    "sg:province":"VIC",
    "sg:tags":[
        "beater",
        "painter",
        "panel"
    ],
    "wof:name":"Brotex Panels",
    "wof:placetype":"venue"
},
  "geometry": {"coordinates":[145.02494812,-37.6597633362],"type":"Point"}
}