{
  "type": "Feature",
  "properties": {
    "addr:full":"Cnr Montague Rd & Fairleigh Ave Modbury SA 5092",
    "addr:postcode":"5092",
    "addr:street":"Cnr Montague Rd & Fairleigh Ave",
    "iso:country":"AU",
    "sg:address":"Cnr Montague Rd & Fairleigh Ave",
    "sg:city":"Modbury",
    "sg:classifiers":[
        {
            "category":"Government",
            "subcategory":"City Hall",
            "type":"Public Place"
        }
    ],
    "sg:phone":"+61 8 8263 5622",
    "sg:postcode":"5092",
    "sg:province":"SA",
    "wof:name":"YMCA",
    "wof:placetype":"venue"
},
  "geometry": {"coordinates":[138.688720703,-34.8280334473],"type":"Point"}
}