{
  "type": "Feature",
  "properties": {
    "addr:full":"10 Belvedere Ave Castle Hill NSW 2154",
    "addr:housenumber":"10",
    "addr:postcode":"2154",
    "addr:street":"Belvedere Ave",
    "iso:country":"AU",
    "sg:address":"10 Belvedere Ave",
    "sg:city":"Castle Hill",
    "sg:classifiers":[
        {
            "category":"Professional",
            "subcategory":"Detective & Security Services",
            "type":"Services"
        }
    ],
    "sg:phone":"+61 2 9894 0647",
    "sg:postcode":"2154",
    "sg:province":"NSW",
    "sg:tags":[
        "domestic",
        "alarm",
        "commercial",
        "burglar"
    ],
    "wof:name":"Aries Security & Communications",
    "wof:placetype":"venue"
},
  "geometry": {"coordinates":[150.99316406200001,-33.72681427],"type":"Point"}
}