{
  "type": "Feature",
  "properties": {
    "iso:country":"AU",
    "sg:address":"18 Talbot St",
    "sg:city":"Fingal",
    "sg:classifiers":[
        {
            "category":"Cafe",
            "type":"Food & Drink"
        }
    ],
    "sg:phone":"+61 3 6374 2285",
    "sg:postcode":"7214",
    "sg:province":"TAS",
    "wof:name":"Mayfield Manor",
    "wof:placetype":"venue"
},
  "geometry": {"coordinates":[147.970673,-41.638248],"type":"Point"}
}