{
  "type": "Feature",
  "properties": {
    "addr:full":"11 Festival Crs Kidman Park SA 5025",
    "addr:housenumber":"11",
    "addr:postcode":"5025",
    "addr:street":"Festival Crs",
    "iso:country":"AU",
    "sg:address":"11 Festival Crs",
    "sg:city":"Kidman Park",
    "sg:classifiers":[
        {
            "category":"Shopping",
            "subcategory":"Party Supplies",
            "type":"Retail Goods"
        }
    ],
    "sg:phone":"+61 8 8234 5671",
    "sg:postcode":"5025",
    "sg:province":"SA",
    "sg:tags":[
        "children's"
    ],
    "wof:name":"Wedding World",
    "wof:placetype":"venue"
},
  "geometry": {"coordinates":[138.527740478,-34.9134407043],"type":"Point"}
}