{
  "type": "Feature",
  "properties": {
    "addr:full":"12 Kahala Rd Kallangur QLD 4503",
    "addr:housenumber":"12",
    "addr:postcode":"4503",
    "addr:street":"Kahala Rd",
    "iso:country":"AU",
    "sg:address":"12 Kahala Rd",
    "sg:city":"Kallangur",
    "sg:classifiers":[
        {
            "category":"Building & Trades",
            "subcategory":"Equipment Rental",
            "type":"Services"
        }
    ],
    "sg:phone":"+61 7 3204 4533",
    "sg:postcode":"4503",
    "sg:province":"QLD",
    "sg:tags":[
        "crane",
        "hire"
    ],
    "wof:name":"Colliers Crane Hire",
    "wof:placetype":"venue"
},
  "geometry": {"coordinates":[153.001663208,-27.2465591431],"type":"Point"}
}