{
  "type": "Feature",
  "properties": {
    "addr:full":"338 Parramatta Rd Burwood NSW 2134",
    "addr:housenumber":"338",
    "addr:postcode":"2134",
    "addr:street":"Parramatta Rd",
    "iso:country":"AU",
    "sg:address":"338 Parramatta Rd",
    "sg:city":"Burwood",
    "sg:classifiers":[
        {
            "category":"Retail",
            "subcategory":"Auto Repair",
            "type":"Services"
        }
    ],
    "sg:phone":"+61 2 9715 1011",
    "sg:postcode":"2134",
    "sg:province":"NSW",
    "sg:tags":[
        "body",
        "motor",
        "trimmer"
    ],
    "wof:name":"To The Max Auto Trim",
    "wof:placetype":"venue"
},
  "geometry": {"coordinates":[151.10601806599999,-33.8691444397],"type":"Point"}
}