{
  "type": "Feature",
  "properties": {
    "iso:country":"AU",
    "sg:address":"4 Amanda Ave",
    "sg:city":"Rasmussen",
    "sg:classifiers":[
        {
            "category":"Home & Garden",
            "subcategory":"Building Materials",
            "type":"Retail Goods"
        }
    ],
    "sg:phone":"+61 7 4773 3399",
    "sg:postcode":"4815",
    "sg:province":"QLD",
    "sg:tags":[
        "merchant",
        "glass",
        "glazier"
    ],
    "wof:name":"Norms Fixit Service",
    "wof:placetype":"venue"
},
  "geometry": {"coordinates":[146.72189299999999,-19.344879],"type":"Point"}
}