{
  "type": "Feature",
  "properties": {
    "addr:full":"Shop 3 Venture Plaza 290 Hargraves Mall Bendigo VIC 3550",
    "addr:housenumber":"shop 3;290",
    "addr:postcode":"3550",
    "addr:street":"Venture Plaza;Mall",
    "iso:country":"AU",
    "sg:address":"Shop 3 Venture Plaza 290",
    "sg:city":"Hargraves Mall Bendigo",
    "sg:classifiers":[
        {
            "category":"Personal",
            "subcategory":"Beauty Salon",
            "type":"Services"
        }
    ],
    "sg:phone":"+61 3 5441 3642",
    "sg:postcode":"3550",
    "sg:province":"VIC",
    "sg:tags":[
        "hairdresser"
    ],
    "wof:name":"Price Attack",
    "wof:placetype":"venue"
},
  "geometry": {"coordinates":[144.279907227,-36.7600898743],"type":"Point"}
}