{
  "type": "Feature",
  "properties": {
    "addr:full":"16 Gale St Aspendale VIC 3195",
    "addr:housenumber":"16",
    "addr:postcode":"3195",
    "addr:street":"Gale St",
    "iso:country":"AU",
    "sg:address":"16 Gale St",
    "sg:city":"Aspendale",
    "sg:classifiers":[
        {
            "category":"Utilities",
            "subcategory":"Electric",
            "type":"Services"
        }
    ],
    "sg:phone":"+61 3 9587 6979",
    "sg:postcode":"3195",
    "sg:province":"VIC",
    "sg:tags":[
        "electrical",
        "contractor"
    ],
    "wof:name":"Bentleigh Electrical Contractors",
    "wof:placetype":"venue"
},
  "geometry": {"coordinates":[145.09922790499999,-38.0178184509],"type":"Point"}
}