{
  "type": "Feature",
  "properties": {
    "iso:country":"AU",
    "sg:address":"Shop K020 Northland Shopping Centre, 2-50 Murray R",
    "sg:city":"Preston East",
    "sg:classifiers":[
        {
            "category":"Banks & Credit Unions",
            "subcategory":"Financial Services",
            "type":"Services"
        }
    ],
    "sg:phone":"+61 3 9471 1587",
    "sg:postcode":"3072",
    "sg:province":"VIC",
    "sg:tags":[
        "loan",
        "finance",
        "mortgage"
    ],
    "wof:name":"CUA Northland",
    "wof:placetype":"venue"
},
  "geometry": {"coordinates":[145.02931213400001,-37.740650177],"type":"Point"}
}