{
  "type": "Feature",
  "properties": {
    "iso:country":"AU",
    "sg:address":"4/ 166a The Entrance Rd",
    "sg:city":"Erina",
    "sg:classifiers":[
        {
            "category":"Wholesale",
            "subcategory":"Construction Materials",
            "type":"Manufacturing & Wholesale Goods"
        }
    ],
    "sg:phone":"+61 2 4365 3701",
    "sg:postcode":"2250",
    "sg:province":"NSW",
    "sg:tags":[
        "wholesaler",
        "lighting",
        "mfrs",
        "accessory"
    ],
    "wof:name":"Vaughan Grahame W Pty Ltd",
    "wof:placetype":"venue"
},
  "geometry": {"coordinates":[151.384674072,-33.4362068176],"type":"Point"}
}