{
  "type": "Feature",
  "properties": {
    "iso:country":"AU",
    "sg:address":"88 Hawdon St",
    "sg:city":"Heidelberg",
    "sg:classifiers":[
        {
            "category":"Personal",
            "subcategory":"Nail Salon",
            "type":"Services"
        }
    ],
    "sg:phone":"+61 3 9455 1997",
    "sg:postcode":"3084",
    "sg:province":"VIC",
    "sg:tags":[
        "artificial"
    ],
    "wof:name":"Touch Red Nail Design",
    "wof:placetype":"venue"
},
  "geometry": {"coordinates":[145.064697266,-37.7565612793],"type":"Point"}
}