{
  "type": "Feature",
  "properties": {
    "addr:full":"Homebush Rd Mackay QLD 4740",
    "addr:postcode":"4740",
    "addr:street":"Homebush Rd",
    "iso:country":"AU",
    "sg:address":"Homebush Rd",
    "sg:city":"Mackay",
    "sg:classifiers":[
        {
            "category":"Farming",
            "subcategory":"Farm",
            "type":"Manufacturing & Wholesale Goods"
        }
    ],
    "sg:phone":"+61 7 4959 5238",
    "sg:postcode":"4740",
    "sg:province":"QLD",
    "sg:tags":[
        "farmer"
    ],
    "wof:name":"Johnson A C & M J",
    "wof:placetype":"venue"
},
  "geometry": {"coordinates":[149.134109,-21.239737],"type":"Point"}
}