{
  "type": "Feature",
  "properties": {
    "addr:full":"Shop 31 Kardinya Park S/C 15 South St Kardinya WA 6163",
    "addr:housenumber":"shop 31;15",
    "addr:postcode":"6163",
    "addr:street":"Park S / C;South St",
    "iso:country":"AU",
    "sg:address":"Shop 31 Kardinya Park S/C 15 South St",
    "sg:city":"Kardinya",
    "sg:classifiers":[
        {
            "category":"Cafe",
            "type":"Food & Drink"
        }
    ],
    "sg:phone":"+61 8 9337 5954",
    "sg:postcode":"6163",
    "sg:province":"WA",
    "wof:name":"Aroma Cafe",
    "wof:placetype":"venue"
},
  "geometry": {"coordinates":[115.817657,-32.068405],"type":"Point"}
}