{
  "type": "Feature",
  "properties": {
    "iso:country":"AU",
    "sg:address":"3 Blanche Ave",
    "sg:city":"Parkdale",
    "sg:classifiers":[
        {
            "category":"Health Services",
            "subcategory":"Health Practitioner",
            "type":"Services"
        }
    ],
    "sg:phone":"+61 3 9587 7785",
    "sg:postcode":"3195",
    "sg:province":"VIC",
    "sg:tags":[
        "homoeopath"
    ],
    "wof:name":"Goodfield Mary",
    "wof:placetype":"venue"
},
  "geometry": {"coordinates":[145.08009338400001,-37.9930458069],"type":"Point"}
}