{
  "type": "Feature",
  "properties": {
    "addr:full":"741 Burwood Hwy Ferntree Gully VIC 3156",
    "addr:housenumber":"741",
    "addr:postcode":"3156",
    "addr:street":"Burwood Hwy",
    "iso:country":"AU",
    "sg:address":"741 Burwood Hwy",
    "sg:city":"Ferntree Gully",
    "sg:classifiers":[
        {
            "category":"Health Services",
            "subcategory":"Dentist",
            "type":"Services"
        }
    ],
    "sg:phone":"+61 3 9758 5641",
    "sg:postcode":"3156",
    "sg:province":"VIC",
    "wof:name":"Dobson Dental",
    "wof:placetype":"venue"
},
  "geometry": {"coordinates":[145.26762390100001,-37.8790206909],"type":"Point"}
}