{
  "type": "Feature",
  "properties": {
    "addr:full":"RMB 168 Fifty Rd Baldivis WA 6171",
    "addr:postcode":"6171",
    "addr:street":"Fifty Rd",
    "iso:country":"AU",
    "sg:address":"RMB 168 Fifty Rd",
    "sg:city":"Baldivis",
    "sg:classifiers":[
        {
            "category":"Home & Garden",
            "subcategory":"Garden Supply",
            "type":"Retail Goods"
        }
    ],
    "sg:phone":"+61 8 9524 1183",
    "sg:postcode":"6171",
    "sg:province":"WA",
    "sg:tags":[
        "landscape"
    ],
    "wof:name":"Janeast Landscape Supplies",
    "wof:placetype":"venue"
},
  "geometry": {"coordinates":[115.808891,-32.308529],"type":"Point"}
}