{
  "type": "Feature",
  "properties": {
    "addr:full":"1 Main North Rd Smithfield SA 5114",
    "addr:housenumber":"1",
    "addr:postcode":"5114",
    "addr:street":"Main North Rd",
    "iso:country":"AU",
    "sg:address":"1 Main North Rd",
    "sg:city":"Smithfield",
    "sg:classifiers":[
        {
            "category":"Food & Beverages",
            "subcategory":"Liquor & Beverages",
            "type":"Retail Goods"
        }
    ],
    "sg:phone":"+61 8 8254 6011",
    "sg:postcode":"5114",
    "sg:province":"SA",
    "sg:tags":[
        "store"
    ],
    "wof:name":"Liquor Marketing Group - S.A. Pty Ltd Sip'N Save",
    "wof:placetype":"venue"
},
  "geometry": {"coordinates":[138.69258117699999,-34.6843757629],"type":"Point"}
}