{
  "type": "Feature",
  "properties": {
    "iso:country":"AU",
    "sg:address":"Lvl2/ 95 Victoria St",
    "sg:city":"Fitzroy",
    "sg:classifiers":[
        {
            "category":"Bars & Pubs",
            "subcategory":"Dive Bar",
            "type":"Food & Drink"
        }
    ],
    "sg:phone":"+61 3 9416 3725",
    "sg:postcode":"3065",
    "sg:province":"VIC",
    "sg:tags":[
        "knitwear",
        "retail"
    ],
    "wof:name":"Fibre Red",
    "wof:placetype":"venue"
},
  "geometry": {"coordinates":[144.977584839,-37.7988243103],"type":"Point"}
}