{
  "type": "Feature",
  "properties": {
    "addr:full":"33 Quondola St Pambula NSW 2549",
    "addr:housenumber":"33",
    "addr:postcode":"2549",
    "addr:street":"Quondola St",
    "iso:country":"AU",
    "sg:address":"33 Quondola St",
    "sg:city":"Pambula",
    "sg:classifiers":[
        {
            "category":"Industrial Area",
            "type":"Public Place"
        }
    ],
    "sg:phone":"+61 2 6495 6038",
    "sg:postcode":"2549",
    "sg:province":"NSW",
    "sg:tags":[
        "protective",
        "clothing"
    ],
    "wof:name":"McPhersons Emporium",
    "wof:placetype":"venue"
},
  "geometry": {"coordinates":[149.87448120100001,-36.929775238],"type":"Point"}
}