{
  "type": "Feature",
  "properties": {
    "addr:full":"10 Norman St Highgate Hill QLD 4101",
    "addr:housenumber":"10",
    "addr:postcode":"4101",
    "addr:street":"Norman St",
    "iso:country":"AU",
    "sg:address":"10 Norman St",
    "sg:city":"Highgate Hill",
    "sg:classifiers":[
        {
            "category":"Building & Trades",
            "subcategory":"Landscaping Services",
            "type":"Services"
        }
    ],
    "sg:phone":"+61 412 558 368",
    "sg:postcode":"4101",
    "sg:province":"QLD",
    "sg:tags":[
        "designer",
        "landscape",
        "contractor"
    ],
    "wof:name":"botanical# bliss#",
    "wof:placetype":"venue"
},
  "geometry": {"coordinates":[153.045822144,-27.4866447449],"type":"Point"}
}