{
  "type": "Feature",
  "properties": {
    "addr:full":"Goulburn Valley Hwy Seymour VIC 3660",
    "addr:postcode":"3660",
    "addr:street":"Valley Hwy",
    "iso:country":"AU",
    "sg:address":"Goulburn Valley Hwy",
    "sg:city":"Seymour",
    "sg:classifiers":[
        {
            "category":"Building & Trades",
            "subcategory":"Landscaping Services",
            "type":"Services"
        }
    ],
    "sg:phone":"+61 3 5792 2416",
    "sg:postcode":"3660",
    "sg:province":"VIC",
    "sg:tags":[
        "grazier"
    ],
    "wof:name":"Castle Coombe Pastoral Co Pty Ltd",
    "wof:placetype":"venue"
},
  "geometry": {"coordinates":[145.14630126899999,-37.0033226013],"type":"Point"}
}