{
  "type": "Feature",
  "properties": {
    "addr:full":"9 Main St Atherton QLD 4883",
    "addr:housenumber":"9",
    "addr:postcode":"4883",
    "addr:street":"Main St",
    "iso:country":"AU",
    "sg:address":"9 Main St",
    "sg:city":"Atherton",
    "sg:classifiers":[
        {
            "category":"Shopping",
            "subcategory":"Crafts & Fabrics",
            "type":"Retail Goods"
        }
    ],
    "sg:phone":"+61 7 4091 3205",
    "sg:postcode":"4883",
    "sg:province":"QLD",
    "sg:tags":[
        "material",
        "dress"
    ],
    "wof:name":"Lookout Stores",
    "wof:placetype":"venue"
},
  "geometry": {"coordinates":[145.476852417,-17.2638473511],"type":"Point"}
}