{
  "type": "Feature",
  "properties": {
    "iso:country":"AU",
    "sg:address":"Suite 17 173 Waverley Rd",
    "sg:city":"Malvern East",
    "sg:classifiers":[
        {
            "category":"Real Estate",
            "subcategory":"Real Estate Services",
            "type":"Services"
        }
    ],
    "sg:phone":"+61 411 605 755",
    "sg:postcode":"3145",
    "sg:province":"VIC",
    "sg:tags":[
        "consultant",
        "property"
    ],
    "wof:name":"Westcor Property Consultants Pty Ltd",
    "wof:placetype":"venue"
},
  "geometry": {"coordinates":[145.05067443900001,-37.8760910034],"type":"Point"}
}