{
  "type": "Feature",
  "properties": {
    "iso:country":"AU",
    "sg:address":"Albatross Rd",
    "sg:city":"Nowra",
    "sg:classifiers":[
        {
            "category":"Building & Trades",
            "subcategory":"Construction",
            "type":"Services"
        }
    ],
    "sg:phone":"+61 2 4428 4400",
    "sg:postcode":"2541",
    "sg:province":"NSW",
    "sg:tags":[
        "contractor"
    ],
    "wof:name":"Serco Sodexho Defence Services",
    "wof:placetype":"venue"
},
  "geometry": {"coordinates":[150.59963989299999,-34.8875160217],"type":"Point"}
}