{
  "type": "Feature",
  "properties": {
    "addr:full":"1/ 64 Servern St Box Hill North VIC 3129",
    "addr:housenumber":"/ 64",
    "addr:postcode":"3129",
    "addr:street":"Servern St",
    "iso:country":"AU",
    "sg:address":"1/ 64 Servern St",
    "sg:city":"Box Hill North",
    "sg:classifiers":[
        {
            "category":"Education",
            "subcategory":"Special Training",
            "type":"Public Place"
        }
    ],
    "sg:phone":"+61 3 9897 3412",
    "sg:postcode":"3129",
    "sg:province":"VIC",
    "sg:tags":[
        "development"
    ],
    "wof:name":"Turnbull Ronald W",
    "wof:placetype":"venue"
},
  "geometry": {"coordinates":[145.12388610799999,-37.8122520447],"type":"Point"}
}