{
  "type": "Feature",
  "properties": {
    "iso:country":"AU",
    "sg:address":"21 Boorara Ave",
    "sg:city":"Oatley",
    "sg:classifiers":[
        {
            "category":"Professional",
            "subcategory":"Management & Consulting",
            "type":"Services"
        }
    ],
    "sg:phone":"+61 2 9586 4255",
    "sg:postcode":"2223",
    "sg:province":"NSW",
    "sg:tags":[
        "consultant"
    ],
    "wof:name":"Planning & Review Consultants",
    "wof:placetype":"venue"
},
  "geometry": {"coordinates":[151.07496643100001,-33.9868927002],"type":"Point"}
}