{
  "type": "Feature",
  "properties": {
    "iso:country":"AU",
    "sg:address":"33 Normanhurst Rd",
    "sg:city":"Normanhurst",
    "sg:classifiers":[
        {
            "category":"Health Services",
            "subcategory":"Dentist",
            "type":"Services"
        }
    ],
    "sg:phone":"+61 2 9489 1220",
    "sg:postcode":"2076",
    "sg:province":"NSW",
    "wof:name":"Normanhurst Dental Surgery",
    "wof:placetype":"venue"
},
  "geometry": {"coordinates":[151.09713745100001,-33.7213516235],"type":"Point"}
}