{
  "type": "Feature",
  "properties": {
    "addr:full":"PO Box 192 Grange QLD 4051",
    "addr:postcode":"4051",
    "iso:country":"AU",
    "sg:address":"PO Box 192",
    "sg:city":"Grange",
    "sg:classifiers":[
        {
            "category":"Health Services",
            "subcategory":"Health Practitioner",
            "type":"Services"
        }
    ],
    "sg:phone":"+61 7 3856 5428",
    "sg:postcode":"4051",
    "sg:province":"QLD",
    "sg:tags":[
        "physiotherapist"
    ],
    "wof:name":"Weston Helen",
    "wof:placetype":"venue"
},
  "geometry": {"coordinates":[153.01556396500001,-27.4260807037],"type":"Point"}
}