{
  "type": "Feature",
  "properties": {
    "addr:full":"67 Smith St Darwin NT 0800",
    "addr:housenumber":"67",
    "addr:postcode":"nt 0800",
    "addr:street":"Smith St",
    "iso:country":"AU",
    "sg:address":"67 Smith St",
    "sg:city":"Darwin",
    "sg:classifiers":[
        {
            "category":"Shopping",
            "subcategory":"Stationery & Office Supplies",
            "type":"Retail Goods"
        }
    ],
    "sg:phone":"+61 8 8981 7544",
    "sg:postcode":"0800",
    "sg:province":"NT",
    "sg:tags":[
        "merchant",
        "paper"
    ],
    "wof:name":"Copytime",
    "wof:placetype":"venue"
},
  "geometry": {"coordinates":[130.840133667,-12.4617023468],"type":"Point"}
}