{
  "type": "Feature",
  "properties": {
    "addr:full":"55 Fitzroy St Nanango QLD 4615",
    "addr:housenumber":"55",
    "addr:postcode":"4615",
    "addr:street":"Fitzroy St",
    "iso:country":"AU",
    "sg:address":"55 Fitzroy St",
    "sg:city":"Nanango",
    "sg:classifiers":[
        {
            "category":"Travel",
            "subcategory":"Hotels & Motels",
            "type":"Entertainment"
        }
    ],
    "sg:phone":"+61 7 4163 1100",
    "sg:postcode":"4615",
    "sg:province":"QLD",
    "wof:name":"Fitzroy Motel Nanango",
    "wof:placetype":"venue"
},
  "geometry": {"coordinates":[152.000076294,-26.6699085236],"type":"Point"}
}