{
  "type": "Feature",
  "properties": {
    "addr:full":"172 New St Brighton VIC 3186",
    "addr:housenumber":"172",
    "addr:postcode":"3186",
    "addr:street":"New St",
    "iso:country":"AU",
    "sg:address":"172 New St",
    "sg:city":"Brighton",
    "sg:classifiers":[
        {
            "category":"Building & Trades",
            "subcategory":"Construction",
            "type":"Services"
        }
    ],
    "sg:phone":"+61 3 9553 8500",
    "sg:postcode":"3186",
    "sg:province":"VIC",
    "sg:tags":[
        "contractor"
    ],
    "wof:name":"Rosden Builders Pty Ltd",
    "wof:placetype":"venue"
},
  "geometry": {"coordinates":[144.99223327600001,-37.9153404236],"type":"Point"}
}