{
  "type": "Feature",
  "properties": {
    "addr:full":"32 Craven St Clayfield QLD 4011",
    "addr:housenumber":"32",
    "addr:postcode":"4011",
    "addr:street":"Craven St",
    "iso:country":"AU",
    "sg:address":"32 Craven St",
    "sg:city":"Clayfield",
    "sg:classifiers":[
        {
            "category":"Professional",
            "subcategory":"Computer Services",
            "type":"Services"
        }
    ],
    "sg:phone":"+61 419 786 519",
    "sg:postcode":"4011",
    "sg:province":"QLD",
    "sg:tags":[
        "consultant",
        "system"
    ],
    "wof:name":"Pegasus Computer Services",
    "wof:placetype":"venue"
},
  "geometry": {"coordinates":[153.056793,-27.426092],"type":"Point"}
}