{
  "type": "Feature",
  "properties": {
    "addr:full":"Shop 7/ 100 Goondoon St Gladstone QLD 4680",
    "addr:housenumber":"shop 7 / 100",
    "addr:postcode":"4680",
    "addr:street":"Goondoon St",
    "iso:country":"AU",
    "sg:address":"Shop 7/ 100 Goondoon St",
    "sg:city":"Gladstone",
    "sg:classifiers":[
        {
            "category":"Shopping",
            "subcategory":"Bridal",
            "type":"Retail Goods"
        }
    ],
    "sg:phone":"+61 7 4972 4603",
    "sg:postcode":"4680",
    "sg:province":"QLD",
    "sg:tags":[
        "hire",
        "wear"
    ],
    "wof:name":"Gladstone Bridal",
    "wof:placetype":"venue"
},
  "geometry": {"coordinates":[151.25570678700001,-23.8427944183],"type":"Point"}
}