{
  "type": "Feature",
  "properties": {
    "iso:country":"AU",
    "sg:address":"Myocum Rd",
    "sg:city":"Ewingsdale",
    "sg:classifiers":[
        {
            "category":"Farming",
            "subcategory":"Nursery",
            "type":"Manufacturing & Wholesale Goods"
        }
    ],
    "sg:phone":"+61 2 6684 7332",
    "sg:postcode":"2481",
    "sg:province":"NSW",
    "wof:name":"Cape Nursery",
    "wof:placetype":"venue"
},
  "geometry": {"coordinates":[153.54722595199999,-28.6355171204],"type":"Point"}
}