{
  "type": "Feature",
  "properties": {
    "addr:full":"139 Camberwell Rd Hawthorn VIC 3122",
    "addr:housenumber":"139",
    "addr:postcode":"3122",
    "addr:street":"Camberwell Rd",
    "iso:country":"AU",
    "sg:address":"139 Camberwell Rd",
    "sg:city":"Hawthorn",
    "sg:classifiers":[
        {
            "category":"Retail",
            "subcategory":"Auto Repair",
            "type":"Services"
        }
    ],
    "sg:phone":"+61 3 9882 3600",
    "sg:postcode":"3122",
    "sg:province":"VIC",
    "sg:tags":[
        "repairer",
        "motor",
        "engineer"
    ],
    "wof:name":"Bilia Volvo",
    "wof:placetype":"venue"
},
  "geometry": {"coordinates":[145.05401611299999,-37.8287734985],"type":"Point"}
}