{
  "type": "Feature",
  "properties": {
    "addr:full":"36 Bosci Rd Ingleburn NSW 2565",
    "addr:housenumber":"36",
    "addr:postcode":"2565",
    "addr:street":"Bosci Rd",
    "iso:country":"AU",
    "sg:address":"36 Bosci Rd",
    "sg:city":"Ingleburn",
    "sg:classifiers":[
        {
            "category":"Manufacturing",
            "subcategory":"Wood Products",
            "type":"Manufacturing & Wholesale Goods"
        }
    ],
    "sg:phone":"+61 411 552 836",
    "sg:postcode":"2565",
    "sg:province":"NSW",
    "sg:tags":[
        "pallet",
        "platform"
    ],
    "wof:name":"Edwards Pallet Pty Ltd",
    "wof:placetype":"venue"
},
  "geometry": {"coordinates":[150.85546875,-33.9981918335],"type":"Point"}
}