{
  "type": "Feature",
  "properties": {
    "addr:full":"8b Stephen St East Devonport TAS 7310",
    "addr:housenumber":"8b",
    "addr:postcode":"7310",
    "addr:street":"Stephen St East",
    "iso:country":"AU",
    "sg:address":"8b Stephen St",
    "sg:city":"East Devonport",
    "sg:classifiers":[
        {
            "category":"Manufacturing",
            "subcategory":"Glass & Minerals",
            "type":"Manufacturing & Wholesale Goods"
        }
    ],
    "sg:phone":"+61 3 6427 0733",
    "sg:postcode":"7310",
    "sg:province":"TAS",
    "sg:tags":[
        "repair",
        "fibreglass",
        "product"
    ],
    "wof:name":"Tasmanian Fibreglass Products",
    "wof:placetype":"venue"
},
  "geometry": {"coordinates":[146.370635986,-41.1820526123],"type":"Point"}
}