{
  "type": "Feature",
  "properties": {
    "addr:full":"Lvl 1, 12 Inovation Pkwy, Kawana Central Business Kawana Waters QLD 4575",
    "addr:housenumber":"12",
    "addr:postcode":"4575",
    "addr:street":"Inovation Pkwy",
    "iso:country":"AU",
    "sg:address":"Lvl 1, 12 Inovation Pkwy, Kawana Central Business",
    "sg:city":"Kawana Waters",
    "sg:classifiers":[
        {
            "category":"Professional",
            "subcategory":"Engineering",
            "type":"Services"
        }
    ],
    "sg:phone":"+61 7 3218 2222",
    "sg:postcode":"4575",
    "sg:province":"QLD",
    "sg:tags":[
        "consulting",
        "engineer"
    ],
    "sg:website":"http://www.pbworld.com",
    "wof:name":"Parsons Brinckerhoff",
    "wof:placetype":"venue"
},
  "geometry": {"coordinates":[153.12910500000001,-26.73616],"type":"Point"}
}