{
  "type": "Feature",
  "properties": {
    "addr:full":"81 Pacific Hwy Charlestown NSW 2290",
    "addr:housenumber":"81",
    "addr:postcode":"2290",
    "addr:street":"Pacific Hwy",
    "iso:country":"AU",
    "sg:address":"81 Pacific Hwy",
    "sg:city":"Charlestown",
    "sg:classifiers":[
        {
            "category":"Building & Trades",
            "subcategory":"Equipment Rental",
            "type":"Services"
        }
    ],
    "sg:phone":"+61 2 4943 8000",
    "sg:postcode":"2290",
    "sg:province":"NSW",
    "sg:tags":[
        "renting",
        "trailer"
    ],
    "wof:name":"Dennis Smith Rentals",
    "wof:placetype":"venue"
},
  "geometry": {"coordinates":[151.69212341299999,-32.9784584045],"type":"Point"}
}