{
  "type": "Feature",
  "properties": {
    "addr:full":"32 Gipps St Collingwood VIC 3066",
    "addr:housenumber":"32",
    "addr:postcode":"3066",
    "addr:street":"Gipps St",
    "iso:country":"AU",
    "sg:address":"32 Gipps St",
    "sg:city":"Collingwood",
    "sg:classifiers":[
        {
            "category":"Manufacturing",
            "subcategory":"Furniture",
            "type":"Manufacturing & Wholesale Goods"
        }
    ],
    "sg:phone":"+61 3 9417 5377",
    "sg:postcode":"3066",
    "sg:province":"VIC",
    "sg:tags":[
        "builder",
        "designer",
        "custom"
    ],
    "wof:name":"Nicholas Dattner & Co",
    "wof:placetype":"venue"
},
  "geometry": {"coordinates":[144.98773193400001,-37.8043937683],"type":"Point"}
}