{
  "type": "Feature",
  "properties": {
    "addr:full":"26 Junction Rd Burleigh QLD 4220",
    "addr:housenumber":"26",
    "addr:postcode":"4220",
    "addr:street":"Junction Rd",
    "iso:country":"AU",
    "sg:address":"26 Junction Rd",
    "sg:city":"Burleigh",
    "sg:classifiers":[
        {
            "category":"Wholesale",
            "subcategory":"Home Furnishings",
            "type":"Manufacturing & Wholesale Goods"
        }
    ],
    "sg:phone":"+61 7 5593 7391",
    "sg:postcode":"4220",
    "sg:province":"QLD",
    "sg:tags":[
        "wholesaler",
        "bedding",
        "mfrs",
        "bed"
    ],
    "wof:name":"Qualitysleep",
    "wof:placetype":"venue"
},
  "geometry": {"coordinates":[153.425292969,-28.1052932739],"type":"Point"}
}