{
  "type": "Feature",
  "properties": {
    "addr:full":"31 Bowerbird Ave Hervey Bay QLD 4655",
    "addr:housenumber":"31",
    "addr:postcode":"4655",
    "addr:street":"Bowerbird Ave",
    "iso:country":"AU",
    "sg:address":"31 Bowerbird Ave",
    "sg:city":"Hervey Bay",
    "sg:classifiers":[
        {
            "category":"Retail",
            "subcategory":"Driving School",
            "type":"Services"
        }
    ],
    "sg:phone":"+61 7 4124 6789",
    "sg:postcode":"4655",
    "sg:province":"QLD",
    "wof:name":"Gails Drive Safe",
    "wof:placetype":"venue"
},
  "geometry": {"coordinates":[152.817093,-25.282478],"type":"Point"}
}