{
  "type": "Feature",
  "properties": {
    "iso:country":"AU",
    "sg:address":"13 Vanessa Blv",
    "sg:city":"Springwood",
    "sg:classifiers":[
        {
            "category":"Personal",
            "subcategory":"Massage",
            "type":"Services"
        }
    ],
    "sg:phone":"+61 7 3208 2066",
    "sg:postcode":"4127",
    "sg:province":"QLD",
    "sg:tags":[
        "therapy"
    ],
    "wof:name":"Springwood Sports Health",
    "wof:placetype":"venue"
},
  "geometry": {"coordinates":[153.12632751500001,-27.6155986786],"type":"Point"}
}