{
  "type": "Feature",
  "properties": {
    "iso:country":"AU",
    "sg:address":"236 Main North Rd",
    "sg:city":"Smithfield",
    "sg:classifiers":[
        {
            "category":"Autos & Motor Vehicles",
            "subcategory":"Fuel & Gas Station",
            "type":"Retail Goods"
        }
    ],
    "sg:phone":"+61 8 8254 6078",
    "sg:postcode":"5114",
    "sg:province":"SA",
    "wof:name":"BP Smithfield",
    "wof:placetype":"venue"
},
  "geometry": {"coordinates":[138.68783569300001,-34.6919021606],"type":"Point"}
}