{
  "type": "Feature",
  "properties": {
    "iso:country":"AU",
    "sg:address":"282 Dorset Rd",
    "sg:city":"Boronia",
    "sg:classifiers":[
        {
            "category":"Health Services",
            "subcategory":"Doctor",
            "type":"Services"
        }
    ],
    "sg:phone":"+61 3 9762 6049",
    "sg:postcode":"3155",
    "sg:province":"VIC",
    "sg:tags":[
        "medical",
        "practitioner"
    ],
    "wof:name":"Dorset Consultant Centre",
    "wof:placetype":"venue"
},
  "geometry": {"coordinates":[145.286010742,-37.8581848145],"type":"Point"}
}