{
  "type": "Feature",
  "properties": {
    "addr:full":"12 Gladys Ave Frenchs Forest NSW 2086",
    "addr:housenumber":"12",
    "addr:postcode":"2086",
    "addr:street":"Gladys Ave",
    "iso:country":"AU",
    "sg:address":"12 Gladys Ave",
    "sg:city":"Frenchs Forest",
    "sg:classifiers":[
        {
            "category":"Professional",
            "subcategory":"Management & Consulting",
            "type":"Services"
        }
    ],
    "sg:phone":"+61 2 9453 5409",
    "sg:postcode":"2086",
    "sg:province":"NSW",
    "sg:tags":[
        "consultant",
        "business"
    ],
    "wof:name":"Tomathol Corporate Advirsory",
    "wof:placetype":"venue"
},
  "geometry": {"coordinates":[151.231567383,-33.7491836548],"type":"Point"}
}