{
  "type": "Feature",
  "properties": {
    "addr:full":"PO Box 24 Koo Wee Rup VIC 3981",
    "addr:postcode":"3981",
    "iso:country":"AU",
    "sg:address":"PO Box 24",
    "sg:city":"Koo Wee Rup",
    "sg:classifiers":[
        {
            "category":"Professional",
            "subcategory":"Detective & Security Services",
            "type":"Services"
        }
    ],
    "sg:phone":"+61 3 5997 7188",
    "sg:postcode":"3981",
    "sg:province":"VIC",
    "sg:tags":[
        "guard",
        "patrol"
    ],
    "wof:name":"Gotcha Security",
    "wof:placetype":"venue"
},
  "geometry": {"coordinates":[145.49127197300001,-38.1991386414],"type":"Point"}
}