{
  "type": "Feature",
  "properties": {
    "iso:country":"AU",
    "sg:address":"3/ 1219 Upper Ross River Rd",
    "sg:city":"Rasmussen",
    "sg:classifiers":[
        {
            "category":"Shopping",
            "subcategory":"Clothing, Apparel, & Fashions",
            "type":"Retail Goods"
        }
    ],
    "sg:phone":"+61 7 4774 0824",
    "sg:postcode":"4815",
    "sg:province":"QLD",
    "sg:tags":[
        "recycled",
        "clothing"
    ],
    "wof:name":"Lifeline North Queensland",
    "wof:placetype":"venue"
},
  "geometry": {"coordinates":[146.731674,-19.364012],"type":"Point"}
}