{
  "type": "Feature",
  "properties": {
    "addr:full":"63 Groundwater Rd Gympie QLD 4570",
    "addr:housenumber":"63",
    "addr:postcode":"4570",
    "addr:street":"Groundwater Rd",
    "iso:country":"AU",
    "sg:address":"63 Groundwater Rd",
    "sg:city":"Gympie",
    "sg:classifiers":[
        {
            "category":"Building & Trades",
            "subcategory":"Construction",
            "type":"Services"
        }
    ],
    "sg:phone":"+61 7 5482 5874",
    "sg:postcode":"4570",
    "sg:province":"QLD",
    "sg:tags":[
        "earth",
        "excavating",
        "moving",
        "contractor"
    ],
    "wof:name":"Milne D & P A",
    "wof:placetype":"venue"
},
  "geometry": {"coordinates":[152.664993286,-26.22149086],"type":"Point"}
}