{
  "type": "Feature",
  "properties": {
    "iso:country":"AU",
    "sg:address":"2/ 10 Elbow St",
    "sg:city":"Coffs Harbour",
    "sg:classifiers":[
        {
            "category":"Health Services",
            "subcategory":"Chiropractor",
            "type":"Services"
        }
    ],
    "sg:phone":"+61 2 6652 3923",
    "sg:postcode":"2450",
    "sg:province":"NSW",
    "wof:name":"Vandenberg John",
    "wof:placetype":"venue"
},
  "geometry": {"coordinates":[153.115143,-30.294008],"type":"Point"}
}