{
  "type": "Feature",
  "properties": {
    "addr:full":"Doodenaning Rd Cunderdin WA 6407",
    "addr:postcode":"6407",
    "addr:street":"Doodenaning Rd",
    "iso:country":"AU",
    "sg:address":"Doodenaning Rd",
    "sg:city":"Cunderdin",
    "sg:classifiers":[
        {
            "category":"Farming",
            "subcategory":"Farm",
            "type":"Manufacturing & Wholesale Goods"
        }
    ],
    "sg:phone":"+61 8 9641 7045",
    "sg:postcode":"6407",
    "sg:province":"WA",
    "sg:tags":[
        "farmer"
    ],
    "wof:name":"Carter R L & W R",
    "wof:placetype":"venue"
},
  "geometry": {"coordinates":[117.236473084,-31.6515808105],"type":"Point"}
}