{
  "type": "Feature",
  "properties": {
    "addr:full":"Maidstone Rd Kersbrook SA 5231",
    "addr:postcode":"5231",
    "addr:street":"Maidstone Rd",
    "iso:country":"AU",
    "sg:address":"Maidstone Rd",
    "sg:city":"Kersbrook",
    "sg:classifiers":[
        {
            "category":"Farming",
            "subcategory":"Livestock Farm",
            "type":"Manufacturing & Wholesale Goods"
        }
    ],
    "sg:phone":"+61 8 8389 3357",
    "sg:postcode":"5231",
    "sg:province":"SA",
    "sg:tags":[
        "agistment"
    ],
    "wof:name":"Treuendorf Stables",
    "wof:placetype":"venue"
},
  "geometry": {"coordinates":[138.85140991200001,-34.7907142639],"type":"Point"}
}