{
  "type": "Feature",
  "properties": {
    "addr:full":"Shop 3/ 219 Unley Rd Malvern SA 5061",
    "addr:housenumber":"shop 3 / 219",
    "addr:postcode":"5061",
    "addr:street":"Unley Rd",
    "iso:country":"AU",
    "sg:address":"Shop 3/ 219 Unley Rd",
    "sg:city":"Malvern",
    "sg:classifiers":[
        {
            "category":"Shopping",
            "subcategory":"Clothing, Apparel, & Fashions",
            "type":"Retail Goods"
        }
    ],
    "sg:phone":"+61 8 8357 3977",
    "sg:postcode":"5061",
    "sg:province":"SA",
    "sg:tags":[
        "lady",
        "wear"
    ],
    "wof:name":"Venus Designs",
    "wof:placetype":"venue"
},
  "geometry": {"coordinates":[138.608154297,-34.9565925598],"type":"Point"}
}