{
  "type": "Feature",
  "properties": {
    "addr:full":"167 Canterbury Rd Kilsyth VIC 3137",
    "addr:housenumber":"167",
    "addr:postcode":"3137",
    "addr:street":"Canterbury Rd",
    "iso:country":"AU",
    "sg:address":"167 Canterbury Rd",
    "sg:city":"Kilsyth",
    "sg:classifiers":[
        {
            "category":"Home & Garden",
            "subcategory":"Garden Supply",
            "type":"Retail Goods"
        }
    ],
    "sg:phone":"+61 3 9761 4340",
    "sg:postcode":"3137",
    "sg:province":"VIC",
    "sg:tags":[
        "statuary",
        "fountains",
        "sundial"
    ],
    "wof:name":"Wholesale Pottery",
    "wof:placetype":"venue"
},
  "geometry": {"coordinates":[145.30549621599999,-37.8210372925],"type":"Point"}
}