{
  "type": "Feature",
  "properties": {
    "addr:full":"67 Laycock St Cranebrook NSW 2749",
    "addr:housenumber":"67",
    "addr:postcode":"2749",
    "addr:street":"Laycock St",
    "iso:country":"AU",
    "sg:address":"67 Laycock St",
    "sg:city":"Cranebrook",
    "sg:classifiers":[
        {
            "category":"Building & Trades",
            "subcategory":"Construction",
            "type":"Services"
        }
    ],
    "sg:phone":"+61 410 633 538",
    "sg:postcode":"2749",
    "sg:province":"NSW",
    "sg:tags":[
        "spouting",
        "guttering"
    ],
    "wof:name":"Walkers Fascia & Guttering",
    "wof:placetype":"venue"
},
  "geometry": {"coordinates":[150.706939697,-33.7218971252],"type":"Point"}
}