{
  "type": "Feature",
  "properties": {
    "addr:full":"504 Princes Hwy Rockdale NSW 2216",
    "addr:housenumber":"504",
    "addr:postcode":"2216",
    "addr:street":"Princes Hwy",
    "iso:country":"AU",
    "sg:address":"504 Princes Hwy",
    "sg:city":"Rockdale",
    "sg:classifiers":[
        {
            "category":"Personal",
            "subcategory":"Beauty Salon",
            "type":"Services"
        }
    ],
    "sg:phone":"+61 2 9556 2112",
    "sg:postcode":"2216",
    "sg:province":"NSW",
    "sg:tags":[
        "hairdresser"
    ],
    "wof:name":"New York Hair Studio",
    "wof:placetype":"venue"
},
  "geometry": {"coordinates":[151.137924,-33.95245],"type":"Point"}
}