{
  "type": "Feature",
  "properties": {
    "iso:country":"AU",
    "sg:address":"Factory 11, 354 - 356 Reserve Rd",
    "sg:city":"Cheltenham",
    "sg:classifiers":[
        {
            "category":"Building & Trades",
            "subcategory":"Cleaning & Sanitation",
            "type":"Services"
        }
    ],
    "sg:phone":"+61 3 9585 0765",
    "sg:postcode":"3192",
    "sg:province":"VIC",
    "sg:tags":[
        "asbestos",
        "treatment",
        "removal"
    ],
    "wof:name":"Cobra Contracting Services Pty Ltd",
    "wof:placetype":"venue"
},
  "geometry": {"coordinates":[145.03831481899999,-37.9592514038],"type":"Point"}
}