{
  "type": "Feature",
  "properties": {
    "addr:full":"144 Eldridge Rd Bankstown NSW 2200",
    "addr:housenumber":"144",
    "addr:postcode":"2200",
    "addr:street":"Eldridge Rd",
    "iso:country":"AU",
    "sg:address":"144 Eldridge Rd",
    "sg:city":"Bankstown",
    "sg:classifiers":[
        {
            "category":"Cafe",
            "type":"Food & Drink"
        }
    ],
    "sg:phone":"+61 2 9790 5420",
    "sg:postcode":"2200",
    "sg:province":"NSW",
    "wof:name":"Eldridge Cafe",
    "wof:placetype":"venue"
},
  "geometry": {"coordinates":[151.01516699999999,-33.931503],"type":"Point"}
}