{
  "type": "Feature",
  "properties": {
    "addr:full":"862- 868 Old Princes Hwy Sutherland NSW 2232",
    "addr:housenumber":"868",
    "addr:postcode":"2232",
    "addr:street":"Old Princes Hwy",
    "iso:country":"AU",
    "sg:address":"862- 868 Old Princes Hwy",
    "sg:city":"Sutherland",
    "sg:classifiers":[
        {
            "category":"Professional",
            "subcategory":"Employment Agencies",
            "type":"Services"
        }
    ],
    "sg:phone":"+61 2 9542 3011",
    "sg:postcode":"2232",
    "sg:province":"NSW",
    "sg:tags":[
        "hire",
        "labour",
        "contractor"
    ],
    "wof:name":"SouthTech",
    "wof:placetype":"venue"
},
  "geometry": {"coordinates":[151.05593872099999,-34.0343780518],"type":"Point"}
}