{
  "type": "Feature",
  "properties": {
    "addr:full":"University Of Sydney, Level 3, Wentworth Bldg , City Rd Chippendale NSW 2008",
    "addr:housenumber":"3",
    "addr:postcode":"2008",
    "addr:street":"Wentworth;City Rd",
    "iso:country":"AU",
    "sg:address":"University Of Sydney, Level 3, Wentworth Bldg , City Rd",
    "sg:city":"Chippendale",
    "sg:classifiers":[
        {
            "category":"Health Services",
            "subcategory":"Dentist",
            "type":"Services"
        }
    ],
    "sg:phone":"+61 2 9692 8900",
    "sg:postcode":"2008",
    "sg:province":"NSW",
    "wof:name":"Coroneos Marouli",
    "wof:placetype":"venue"
},
  "geometry": {"coordinates":[151.19358825699999,-33.8871803284],"type":"Point"}
}