{
  "type": "Feature",
  "properties": {
    "iso:country":"AU",
    "sg:address":"10 Newdegate St",
    "sg:city":"Deakin",
    "sg:classifiers":[
        {
            "category":"Health Services",
            "subcategory":"Medical Lab",
            "type":"Services"
        }
    ],
    "sg:phone":"+61 2 6285 4066",
    "sg:postcode":"2600",
    "sg:province":"ACT",
    "sg:tags":[
        "laboratory",
        "dental"
    ],
    "wof:name":"Judy Hay",
    "wof:placetype":"venue"
},
  "geometry": {"coordinates":[149.09945678700001,-35.3167190552],"type":"Point"}
}