{
  "type": "Feature",
  "properties": {
    "addr:full":"6 Warburton Rd Valley View SA 5093",
    "addr:housenumber":"6",
    "addr:postcode":"5093",
    "addr:street":"Warburton Rd",
    "iso:country":"AU",
    "sg:address":"6 Warburton Rd",
    "sg:city":"Valley View",
    "sg:classifiers":[
        {
            "category":"Building & Trades",
            "subcategory":"Construction",
            "type":"Services"
        }
    ],
    "sg:phone":"+61 8 8395 2330",
    "sg:postcode":"5093",
    "sg:province":"SA",
    "sg:tags":[
        "roof"
    ],
    "wof:name":"Darren Fraser Roof Plumber",
    "wof:placetype":"venue"
},
  "geometry": {"coordinates":[138.66131591800001,-34.8352012634],"type":"Point"}
}