{
  "type": "Feature",
  "properties": {
    "addr:full":"167 High St Kew VIC 3101",
    "addr:housenumber":"167",
    "addr:postcode":"3101",
    "addr:street":"High St",
    "iso:country":"AU",
    "sg:address":"167 High St",
    "sg:city":"Kew",
    "sg:classifiers":[
        {
            "category":"Education",
            "subcategory":"School",
            "type":"Public Place"
        }
    ],
    "sg:phone":"+61 3 9853 5829",
    "sg:postcode":"3101",
    "sg:province":"VIC",
    "sg:tags":[
        "supply"
    ],
    "wof:name":"Pages Bookshop",
    "wof:placetype":"venue"
},
  "geometry": {"coordinates":[145.03083801299999,-37.8066291809],"type":"Point"}
}