{
  "type": "Feature",
  "properties": {
    "addr:full":"36 Allen St South Townsville QLD 4810",
    "addr:housenumber":"36",
    "addr:postcode":"4810",
    "addr:street":"Allen St",
    "iso:country":"AU",
    "sg:address":"36 Allen St",
    "sg:city":"South Townsville",
    "sg:classifiers":[
        {
            "category":"Retail",
            "subcategory":"Auto Repair",
            "type":"Services"
        }
    ],
    "sg:phone":"+61 7 4771 3630",
    "sg:postcode":"4810",
    "sg:province":"QLD",
    "sg:tags":[
        "repairer",
        "motor",
        "engineer"
    ],
    "wof:name":"Mitsu Serv",
    "wof:placetype":"venue"
},
  "geometry": {"coordinates":[146.82652300000001,-19.264133],"type":"Point"}
}