{
  "type": "Feature",
  "properties": {
    "iso:country":"AU",
    "sg:address":"4353 Huon Hwy",
    "sg:city":"Port Huon",
    "sg:classifiers":[
        {
            "category":"Farming",
            "subcategory":"Fish & Marine Products",
            "type":"Manufacturing & Wholesale Goods"
        }
    ],
    "sg:phone":"+61 3 6297 1449",
    "sg:postcode":"7116",
    "sg:province":"TAS",
    "sg:tags":[
        "production",
        "seafood",
        "processing"
    ],
    "wof:name":"Huon Valley Seafoods Pty Ltd",
    "wof:placetype":"venue"
},
  "geometry": {"coordinates":[146.97770690900001,-43.1585083008],"type":"Point"}
}