{
  "type": "Feature",
  "properties": {
    "iso:country":"AU",
    "sg:address":"Shop 1/ 58 Anderson St",
    "sg:city":"Yarraville",
    "sg:classifiers":[
        {
            "category":"Personal",
            "subcategory":"Beauty Salon",
            "type":"Services"
        }
    ],
    "sg:phone":"+61 3 9314 1777",
    "sg:postcode":"3013",
    "sg:province":"VIC",
    "sg:tags":[
        "hairdresser"
    ],
    "wof:name":"Tina Brandi",
    "wof:placetype":"venue"
},
  "geometry": {"coordinates":[144.88890075699999,-37.8163032532],"type":"Point"}
}