{
  "type": "Feature",
  "properties": {
    "iso:country":"AU",
    "sg:address":"15 Sanford Rd",
    "sg:city":"Albany",
    "sg:phone":"+61 8 9841 2341",
    "sg:postcode":"6330",
    "sg:province":"WA",
    "wof:name":"Hawkins H R & N A",
    "wof:placetype":"venue"
},
  "geometry": {"coordinates":[117.87978363000001,-35.0167427063],"type":"Point"}
}