{
  "type": "Feature",
  "properties": {
    "iso:country":"AU",
    "sg:address":"67 Rickard Rd",
    "sg:city":"Bankstown",
    "sg:classifiers":[
        {
            "category":"Health Services",
            "subcategory":"Doctor",
            "type":"Services"
        }
    ],
    "sg:phone":"+61 2 9790 0024",
    "sg:postcode":"2200",
    "sg:province":"NSW",
    "sg:tags":[
        "medical",
        "practitioner"
    ],
    "wof:name":"Lim William",
    "wof:placetype":"venue"
},
  "geometry": {"coordinates":[151.033768,-33.914249],"type":"Point"}
}