{
  "type": "Feature",
  "properties": {
    "iso:country":"AU",
    "sg:address":"218a Crawford St",
    "sg:city":"Queanbeyan",
    "sg:classifiers":[
        {
            "category":"Health Services",
            "subcategory":"Health Practitioner",
            "type":"Services"
        }
    ],
    "sg:phone":"+61 2 6297 0299",
    "sg:postcode":"2620",
    "sg:province":"NSW",
    "sg:tags":[
        "alternative"
    ],
    "wof:name":"Queanbeyan's Mystical Magic",
    "wof:placetype":"venue"
},
  "geometry": {"coordinates":[149.23377990700001,-35.3522911072],"type":"Point"}
}