{
  "type": "Feature",
  "properties": {
    "addr:full":"7 Melrose St Condobolin NSW 2877",
    "addr:housenumber":"7",
    "addr:postcode":"2877",
    "addr:street":"Melrose St",
    "iso:country":"AU",
    "sg:address":"7 Melrose St",
    "sg:city":"Condobolin",
    "sg:classifiers":[
        {
            "category":"Organizations",
            "subcategory":"Community Association",
            "type":"Services"
        }
    ],
    "sg:phone":"+61 2 6895 3883",
    "sg:postcode":"2877",
    "sg:province":"NSW",
    "sg:tags":[
        "organisation",
        "family",
        "welfare"
    ],
    "wof:name":"Home Care Service Of NSW",
    "wof:placetype":"venue"
},
  "geometry": {"coordinates":[147.145386,-33.086975],"type":"Point"}
}