{
  "type": "Feature",
  "properties": {
    "iso:country":"AU",
    "sg:address":"27- 31 Barry St",
    "sg:city":"South Yarra",
    "sg:classifiers":[
        {
            "category":"Retail",
            "subcategory":"Event Space",
            "type":"Services"
        }
    ],
    "sg:phone":"+61 3 9555 8640",
    "sg:postcode":"3141",
    "sg:province":"VIC",
    "sg:tags":[
        "venue",
        "reception",
        "wedding"
    ],
    "wof:name":"Metropol Receptions",
    "wof:placetype":"venue"
},
  "geometry": {"coordinates":[144.99305725100001,-37.8449020386],"type":"Point"}
}