{
  "type": "Feature",
  "properties": {
    "addr:full":"59 Hansford Rd Coombabah QLD 4216",
    "addr:housenumber":"59",
    "addr:postcode":"4216",
    "addr:street":"Hansford Rd",
    "iso:country":"AU",
    "sg:address":"59 Hansford Rd",
    "sg:city":"Coombabah",
    "sg:classifiers":[
        {
            "category":"Manufacturing",
            "subcategory":"Musical Instruments",
            "type":"Manufacturing & Wholesale Goods"
        }
    ],
    "sg:phone":"+61 7 5577 2227",
    "sg:postcode":"4216",
    "sg:province":"QLD",
    "sg:tags":[
        "repair",
        "maker"
    ],
    "wof:name":"Rock &#039;N&#039; Roll Repairs",
    "wof:placetype":"venue"
},
  "geometry": {"coordinates":[153.382156372,-27.8992862701],"type":"Point"}
}