{
  "type": "Feature",
  "properties": {
    "addr:full":"6 Walker St Coburg VIC 3058",
    "addr:housenumber":"6",
    "addr:postcode":"3058",
    "addr:street":"Walker St",
    "iso:country":"AU",
    "sg:address":"6 Walker St",
    "sg:city":"Coburg",
    "sg:classifiers":[
        {
            "category":"Wholesale",
            "subcategory":"Medical Equipment & Supplies",
            "type":"Manufacturing & Wholesale Goods"
        }
    ],
    "sg:phone":"+61 405 687 345",
    "sg:postcode":"3058",
    "sg:province":"VIC",
    "sg:tags":[
        "plastering"
    ],
    "wof:name":"Bonnici Plastering",
    "wof:placetype":"venue"
},
  "geometry": {"coordinates":[144.964279175,-37.7451553345],"type":"Point"}
}