{
  "type": "Feature",
  "properties": {
    "iso:country":"AU",
    "sg:address":"142 Prospect Rd",
    "sg:city":"Prospect",
    "sg:classifiers":[
        {
            "category":"Health Services",
            "subcategory":"Dentist",
            "type":"Services"
        }
    ],
    "sg:phone":"+61 8 8344 4022",
    "sg:postcode":"5082",
    "sg:province":"SA",
    "wof:name":"Haddad-Ferraro Dianne Dr",
    "wof:placetype":"venue"
},
  "geometry": {"coordinates":[138.59373474099999,-34.8852272034],"type":"Point"}
}