{
  "type": "Feature",
  "properties": {
    "iso:country":"AU",
    "sg:address":"173 Margaret St",
    "sg:city":"Toowoomba",
    "sg:classifiers":[
        {
            "category":"Fast Food",
            "type":"Food & Drink"
        }
    ],
    "sg:phone":"+61 7 4632 2997",
    "sg:postcode":"4350",
    "sg:province":"QLD",
    "sg:tags":[
        "away",
        "take"
    ],
    "wof:name":"La Pizzaiola",
    "wof:placetype":"venue"
},
  "geometry": {"coordinates":[151.954407,-27.561003],"type":"Point"}
}