{
  "type": "Feature",
  "properties": {
    "addr:full":"1 Ryecroft Rd Darlington WA 6070",
    "addr:housenumber":"1",
    "addr:postcode":"6070",
    "addr:street":"Ryecroft Rd",
    "iso:country":"AU",
    "sg:address":"1 Ryecroft Rd",
    "sg:city":"Darlington",
    "sg:classifiers":[
        {
            "category":"Social Services",
            "subcategory":"Child Care",
            "type":"Services"
        }
    ],
    "sg:phone":"+61 8 9299 8687",
    "sg:postcode":"6070",
    "sg:province":"WA",
    "wof:name":"Hills Outside School Care Association (Inc)",
    "wof:placetype":"venue"
},
  "geometry": {"coordinates":[116.08708190900001,-31.9208316803],"type":"Point"}
}