{
  "type": "Feature",
  "properties": {
    "addr:full":"Shop B21d, Harbour Town, Cnr Oxley Ave & East Coast Hwy Biggera Waters QLD 4216",
    "addr:housenumber":"b21d",
    "addr:postcode":"4216",
    "addr:street":"Harbour Town Cnr Oxley Ave &;Hwy",
    "iso:country":"AU",
    "sg:address":"Shop B21d, Harbour Town, Cnr Oxley Ave & East Coast Hwy",
    "sg:city":"Biggera Waters",
    "sg:classifiers":[
        {
            "category":"Shopping",
            "type":"Retail Goods"
        }
    ],
    "sg:phone":"+61 7 5500 5039",
    "sg:postcode":"4216",
    "sg:province":"QLD",
    "sg:tags":[
        "clearance",
        "factory",
        "outlet"
    ],
    "wof:name":"Givoni",
    "wof:placetype":"venue"
},
  "geometry": {"coordinates":[153.400558472,-27.9347896576],"type":"Point"}
}