{
  "type": "Feature",
  "properties": {
    "addr:full":"55 Dunmore St Wentworthville NSW 2145",
    "addr:housenumber":"55",
    "addr:postcode":"2145",
    "addr:street":"Dunmore St",
    "iso:country":"AU",
    "sg:address":"55 Dunmore St",
    "sg:city":"Wentworthville",
    "sg:classifiers":[
        {
            "category":"Personal",
            "subcategory":"Beauty Salon",
            "type":"Services"
        }
    ],
    "sg:phone":"+61 2 9896 0433",
    "sg:postcode":"2145",
    "sg:province":"NSW",
    "wof:name":"Vive la Beaute",
    "wof:placetype":"venue"
},
  "geometry": {"coordinates":[150.97074890100001,-33.8074302673],"type":"Point"}
}