{
  "type": "Feature",
  "properties": {
    "iso:country":"AU",
    "sg:address":"Cnr Newnham & Wishart Rds",
    "sg:city":"Upper Mt Gravatt",
    "sg:classifiers":[
        {
            "category":"Real Estate",
            "subcategory":"Real Estate Agent",
            "type":"Services"
        }
    ],
    "sg:phone":"+61 7 3349 5333",
    "sg:postcode":"4122",
    "sg:province":"QLD",
    "wof:name":"Raine & Horne Upper Mt Gravatt",
    "wof:placetype":"venue"
},
  "geometry": {"coordinates":[153.094284058,-27.5322532654],"type":"Point"}
}