{
  "type": "Feature",
  "properties": {
    "addr:full":"390 South St O'Connor WA 6163",
    "addr:housenumber":"390",
    "addr:postcode":"6163",
    "addr:street":"South St",
    "iso:country":"AU",
    "sg:address":"390 South St",
    "sg:city":"O'Connor",
    "sg:classifiers":[
        {
            "category":"Fast Food",
            "type":"Food & Drink"
        }
    ],
    "sg:phone":"+61 8 9337 9000",
    "sg:postcode":"6163",
    "sg:province":"WA",
    "sg:tags":[
        "away",
        "take"
    ],
    "wof:name":"McDonald's Family Restaurants",
    "wof:placetype":"venue"
},
  "geometry": {"coordinates":[115.800392,-32.065014],"type":"Point"}
}