{
  "type": "Feature",
  "properties": {
    "addr:full":"Lot 22 Hoburd Drv Woodend VIC 3442",
    "addr:postcode":"3442",
    "addr:street":"Hoburd Drv",
    "iso:country":"AU",
    "sg:address":"Lot 22 Hoburd Drv",
    "sg:city":"Woodend",
    "sg:classifiers":[
        {
            "category":"Manufacturing",
            "subcategory":"Metals",
            "type":"Manufacturing & Wholesale Goods"
        }
    ],
    "sg:phone":"+61 3 5427 3701",
    "sg:postcode":"3442",
    "sg:province":"VIC",
    "sg:tags":[
        "sheet",
        "worker"
    ],
    "wof:name":"Tullamarine Sheet Metal Pty Ltd",
    "wof:placetype":"venue"
},
  "geometry": {"coordinates":[144.50070190400001,-37.3683052063],"type":"Point"}
}