{
  "type": "Feature",
  "properties": {
    "iso:country":"AU",
    "sg:address":"151 Carrington St",
    "sg:city":"Hilton",
    "sg:classifiers":[
        {
            "category":"Autos & Motor Vehicles",
            "subcategory":"Fuel & Gas Station",
            "type":"Retail Goods"
        }
    ],
    "sg:phone":"+61 8 9335 5233",
    "sg:postcode":"6163",
    "sg:province":"WA",
    "wof:name":"Wesco Hilton",
    "wof:placetype":"venue"
},
  "geometry": {"coordinates":[115.779633,-32.064415],"type":"Point"}
}