{
  "type": "Feature",
  "properties": {
    "addr:full":"17 Titan Drv Carrum Downs VIC 3201",
    "addr:housenumber":"17",
    "addr:postcode":"3201",
    "addr:street":"Titan Drv",
    "iso:country":"AU",
    "sg:address":"17 Titan Drv",
    "sg:city":"Carrum Downs",
    "sg:classifiers":[
        {
            "category":"Professional",
            "subcategory":"Engineering",
            "type":"Services"
        }
    ],
    "sg:phone":"+61 3 9776 8193",
    "sg:postcode":"3201",
    "sg:province":"VIC",
    "sg:tags":[
        "engineer"
    ],
    "wof:name":"Gray E & H Welding Pty Ltd",
    "wof:placetype":"venue"
},
  "geometry": {"coordinates":[145.16679400000001,-38.102161],"type":"Point"}
}