{
  "type": "Feature",
  "properties": {
    "addr:full":"Level 6 75 King St Sydney NSW 2000",
    "addr:housenumber":"75",
    "addr:postcode":"2000",
    "addr:street":"King St",
    "iso:country":"AU",
    "sg:address":"Level 6 75 King St",
    "sg:city":"Sydney",
    "sg:classifiers":[
        {
            "category":"Professional",
            "subcategory":"Employment Agencies",
            "type":"Services"
        }
    ],
    "sg:phone":"+61 2 9290 3944",
    "sg:postcode":"2000",
    "sg:province":"NSW",
    "sg:tags":[
        "hire",
        "labour",
        "contractor"
    ],
    "wof:name":"Parker Peacock International",
    "wof:placetype":"venue"
},
  "geometry": {"coordinates":[151.206756592,-33.8688278198],"type":"Point"}
}