{
  "type": "Feature",
  "properties": {
    "addr:full":"7 Starkey St Forestville NSW 2087",
    "addr:housenumber":"7",
    "addr:postcode":"2087",
    "addr:street":"Starkey St",
    "iso:country":"AU",
    "sg:address":"7 Starkey St",
    "sg:city":"Forestville",
    "sg:classifiers":[
        {
            "category":"Health Services",
            "subcategory":"Dentist",
            "type":"Services"
        }
    ],
    "sg:phone":"+61 2 9452 2033",
    "sg:postcode":"2087",
    "sg:province":"NSW",
    "wof:name":"Northside Orthodontics",
    "wof:placetype":"venue"
},
  "geometry": {"coordinates":[151.21661376899999,-33.7620735168],"type":"Point"}
}