{
  "type": "Feature",
  "properties": {
    "addr:full":"U 4/ 38 Auburn St Wollongong NSW 2500",
    "addr:postcode":"2500",
    "addr:street":"Auburn St",
    "iso:country":"AU",
    "sg:address":"U 4/ 38 Auburn St",
    "sg:city":"Wollongong",
    "sg:classifiers":[
        {
            "category":"Professional",
            "subcategory":"Engineering",
            "type":"Services"
        }
    ],
    "sg:phone":"+61 2 4228 7673",
    "sg:postcode":"2500",
    "sg:province":"NSW",
    "sg:tags":[
        "consulting",
        "engineer"
    ],
    "wof:name":"Nebo Mechanical Engineers",
    "wof:placetype":"venue"
},
  "geometry": {"coordinates":[150.88883999999999,-34.429577],"type":"Point"}
}