{
  "type": "Feature",
  "properties": {
    "addr:full":"22 High St Terang VIC 3264",
    "addr:housenumber":"22",
    "addr:postcode":"3264",
    "addr:street":"High St",
    "iso:country":"AU",
    "sg:address":"22 High St",
    "sg:city":"Terang",
    "sg:classifiers":[
        {
            "category":"Shopping",
            "subcategory":"Crafts & Fabrics",
            "type":"Retail Goods"
        }
    ],
    "sg:phone":"+61 3 5592 1984",
    "sg:postcode":"3264",
    "sg:province":"VIC",
    "sg:tags":[
        "supply"
    ],
    "wof:name":"Terang Cottage Craft",
    "wof:placetype":"venue"
},
  "geometry": {"coordinates":[142.9193573,-38.2410240173],"type":"Point"}
}