{
  "type": "Feature",
  "properties": {
    "iso:country":"AU",
    "sg:address":"121 Ipswich St",
    "sg:city":"Esk",
    "sg:classifiers":[
        {
            "category":"Travel",
            "subcategory":"Hotels & Motels",
            "type":"Entertainment"
        }
    ],
    "sg:phone":"+61 7 5424 1141",
    "sg:postcode":"4312",
    "sg:province":"QLD",
    "sg:tags":[
        "accommodation"
    ],
    "wof:name":"Esk Grand Hotel",
    "wof:placetype":"venue"
},
  "geometry": {"coordinates":[152.423995972,-27.2422008514],"type":"Point"}
}