{
  "type": "Feature",
  "properties": {
    "iso:country":"AU",
    "sg:address":"Suite 3/ 79 High St",
    "sg:city":"Belmont",
    "sg:classifiers":[
        {
            "category":"Utilities",
            "subcategory":"Telephone",
            "type":"Services"
        }
    ],
    "sg:phone":"+61 3 5249 8800",
    "sg:postcode":"3216",
    "sg:province":"VIC",
    "sg:tags":[
        "equipment",
        "system"
    ],
    "wof:name":"Tekworx Telecommunications",
    "wof:placetype":"venue"
},
  "geometry": {"coordinates":[144.346832275,-38.1714096069],"type":"Point"}
}