{
  "type": "Feature",
  "properties": {
    "addr:full":"82- 86 East St Narrandera NSW 2700",
    "addr:housenumber":"86",
    "addr:postcode":"2700",
    "addr:street":"East St",
    "iso:country":"AU",
    "sg:address":"82- 86 East St",
    "sg:city":"Narrandera",
    "sg:classifiers":[
        {
            "category":"Professional",
            "subcategory":"Accounting & Tax Preparation",
            "type":"Services"
        }
    ],
    "sg:phone":"+61 2 6959 1661",
    "sg:postcode":"2700",
    "sg:province":"NSW",
    "sg:tags":[
        "consultant",
        "taxation"
    ],
    "wof:name":"Auswild & Broad Pty Ltd",
    "wof:placetype":"venue"
},
  "geometry": {"coordinates":[146.55331420900001,-34.7448348999],"type":"Point"}
}