{
  "type": "Feature",
  "properties": {
    "iso:country":"AU",
    "sg:address":"Shp6/ 676 Pittwater Rd",
    "sg:city":"Brookvale",
    "sg:classifiers":[
        {
            "category":"Food & Beverages",
            "subcategory":"Groceries & Convenience Stores",
            "type":"Retail Goods"
        }
    ],
    "sg:phone":"+61 2 9905 9388",
    "sg:postcode":"2100",
    "sg:province":"NSW",
    "wof:name":"Warringah Asian Food Mart",
    "wof:placetype":"venue"
},
  "geometry": {"coordinates":[151.27180480999999,-33.7626876831],"type":"Point"}
}