{
  "type": "Feature",
  "properties": {
    "addr:full":"Suite 5, 54 Melbourne St North Adelaide SA 5006",
    "addr:housenumber":"54",
    "addr:postcode":"5006",
    "addr:street":"Melbourne St",
    "iso:country":"AU",
    "sg:address":"Suite 5, 54 Melbourne St",
    "sg:city":"North Adelaide",
    "sg:classifiers":[
        {
            "category":"Health Services",
            "subcategory":"Health Practitioner",
            "type":"Services"
        }
    ],
    "sg:phone":"+61 8 8267 4968",
    "sg:postcode":"5006",
    "sg:province":"SA",
    "sg:tags":[
        "dietitian"
    ],
    "wof:name":"Body Temple Health & Weight Loss Clinic",
    "wof:placetype":"venue"
},
  "geometry": {"coordinates":[138.608886719,-34.9060554504],"type":"Point"}
}