{
  "type": "Feature",
  "properties": {
    "addr:full":"Percy St Warwick QLD 4370",
    "addr:postcode":"4370",
    "addr:street":"Percy St",
    "iso:country":"AU",
    "sg:address":"Percy St",
    "sg:city":"Warwick",
    "sg:classifiers":[
        {
            "category":"Health Services",
            "subcategory":"Health Practitioner",
            "type":"Services"
        }
    ],
    "sg:phone":"+61 429 641 785",
    "sg:postcode":"4370",
    "sg:province":"QLD",
    "sg:tags":[
        "alternative"
    ],
    "wof:name":"Lesley Allison-Peterson",
    "wof:placetype":"venue"
},
  "geometry": {"coordinates":[152.03395080600001,-28.2184772491],"type":"Point"}
}