{
  "type": "Feature",
  "properties": {
    "iso:country":"AU",
    "sg:address":"24 Anzac Pde",
    "sg:city":"Yeppoon",
    "sg:classifiers":[
        {
            "category":"Food & Beverages",
            "subcategory":"Meat & Fish",
            "type":"Retail Goods"
        }
    ],
    "sg:phone":"+61 7 4939 2233",
    "sg:postcode":"4703",
    "sg:province":"QLD",
    "sg:tags":[
        "seafood"
    ],
    "wof:name":"Seagulls Seafood & Takeaways",
    "wof:placetype":"venue"
},
  "geometry": {"coordinates":[150.74928283700001,-23.1313552856],"type":"Point"}
}