{
  "type": "Feature",
  "properties": {
    "addr:full":"Shop 10 West Place Shopping Cntr Churchill VIC 3842",
    "addr:housenumber":"shop 10",
    "addr:postcode":"3842",
    "addr:street":"West Place Shopping Cntr",
    "iso:country":"AU",
    "sg:address":"Shop 10 West Place Shopping Cntr",
    "sg:city":"Churchill",
    "sg:classifiers":[
        {
            "category":"Fast Food",
            "type":"Food & Drink"
        }
    ],
    "sg:phone":"+61 3 5122 1101",
    "sg:postcode":"3842",
    "sg:province":"VIC",
    "sg:tags":[
        "away",
        "take"
    ],
    "wof:name":"Churchill Fish & Chip Shop",
    "wof:placetype":"venue"
},
  "geometry": {"coordinates":[146.42007446299999,-38.3140296936],"type":"Point"}
}