{
  "type": "Feature",
  "properties": {
    "addr:full":"Jumbuk Rd Yinnar VIC 3869",
    "addr:postcode":"3869",
    "addr:street":"Jumbuk Rd",
    "iso:country":"AU",
    "sg:address":"Jumbuk Rd",
    "sg:city":"Yinnar",
    "sg:classifiers":[
        {
            "category":"Farming",
            "subcategory":"Farm",
            "type":"Manufacturing & Wholesale Goods"
        }
    ],
    "sg:phone":"+61 3 5163 1421",
    "sg:postcode":"3869",
    "sg:province":"VIC",
    "sg:tags":[
        "farmer"
    ],
    "wof:name":"Quigley K & J",
    "wof:placetype":"venue"
},
  "geometry": {"coordinates":[146.32810974099999,-38.3223114014],"type":"Point"}
}