{
  "type": "Feature",
  "properties": {
    "addr:full":"PO Box 6116 Maroochydore BC QLD 4558",
    "addr:postcode":"qld 4558",
    "iso:country":"AU",
    "sg:address":"PO Box 6116",
    "sg:city":"Maroochydore BC",
    "sg:classifiers":[
        {
            "category":"Shopping",
            "subcategory":"Stationery & Office Supplies",
            "type":"Retail Goods"
        }
    ],
    "sg:phone":"+61 412 066 789",
    "sg:postcode":"4558",
    "sg:province":"QLD",
    "sg:tags":[
        "partition"
    ],
    "wof:name":"Q Wet Area Partitions",
    "wof:placetype":"venue"
},
  "geometry": {"coordinates":[153.07473754899999,-26.6551475525],"type":"Point"}
}