{
  "type": "Feature",
  "properties": {
    "addr:full":"Lot 1, Enterprise St Boyne Island QLD 4680",
    "addr:postcode":"4680",
    "addr:street":"Enterprise St",
    "iso:country":"AU",
    "sg:address":"Lot 1, Enterprise St",
    "sg:city":"Boyne Island",
    "sg:classifiers":[
        {
            "category":"Professional",
            "subcategory":"Engineering",
            "type":"Services"
        }
    ],
    "sg:phone":"+61 7 4973 9805",
    "sg:postcode":"4680",
    "sg:province":"QLD",
    "sg:tags":[
        "building",
        "prefabricated",
        "transportable",
        "industrial",
        "commercial"
    ],
    "wof:name":"Ausco Building Systems",
    "wof:placetype":"venue"
},
  "geometry": {"coordinates":[151.328521728,-23.9621677399],"type":"Point"}
}