{
  "type": "Feature",
  "properties": {
    "iso:country":"AU",
    "sg:address":"7- 9 Strong St",
    "sg:city":"Geelong South",
    "sg:classifiers":[
        {
            "category":"Home & Garden",
            "subcategory":"Building Materials",
            "type":"Retail Goods"
        }
    ],
    "sg:phone":"+61 3 5222 4500",
    "sg:postcode":"3220",
    "sg:province":"VIC",
    "sg:tags":[
        "plaster",
        "plasterboard",
        "supply"
    ],
    "wof:name":"All Plaster Supplies Pty Ltd",
    "wof:placetype":"venue"
},
  "geometry": {"coordinates":[144.36424299999999,-38.162483],"type":"Point"}
}