{
  "type": "Feature",
  "properties": {
    "addr:full":"9 Oaktree Drv Monbulk VIC 3793",
    "addr:housenumber":"9",
    "addr:postcode":"3793",
    "addr:street":"Oaktree Drv",
    "iso:country":"AU",
    "sg:address":"9 Oaktree Drv",
    "sg:city":"Monbulk",
    "sg:classifiers":[
        {
            "category":"Professional",
            "subcategory":"Computer Services",
            "type":"Services"
        }
    ],
    "sg:phone":"+61 3 9752 1811",
    "sg:postcode":"3793",
    "sg:province":"VIC",
    "sg:tags":[
        "consultant",
        "system"
    ],
    "wof:name":"Open Concepts Pty Ltd",
    "wof:placetype":"venue"
},
  "geometry": {"coordinates":[145.43556213400001,-37.8954658508],"type":"Point"}
}