{
  "type": "Feature",
  "properties": {
    "iso:country":"AU",
    "sg:address":"Ste 1001,Lvl 10, 117 York St",
    "sg:city":"Sydney",
    "sg:classifiers":[
        {
            "category":"Insurance",
            "subcategory":"Hazard Insurance",
            "type":"Services"
        }
    ],
    "sg:phone":"+61 2 8262 5800",
    "sg:postcode":"2000",
    "sg:province":"NSW",
    "sg:tags":[
        "fire",
        "accident",
        "marine"
    ],
    "wof:name":"Thomas Miller (Australasia) Pty Ltd",
    "wof:placetype":"venue"
},
  "geometry": {"coordinates":[151.20619201700001,-33.8712844849],"type":"Point"}
}