{
  "type": "Feature",
  "properties": {
    "addr:full":"Unit 2 - 2B Parker St Footscray VIC 3011",
    "addr:housenumber":"2b",
    "addr:postcode":"3011",
    "addr:street":"Parker St",
    "iso:country":"AU",
    "sg:address":"Unit 2 - 2B Parker St",
    "sg:city":"Footscray",
    "sg:classifiers":[
        {
            "category":"Social Services",
            "subcategory":"Retirement Home",
            "type":"Services"
        }
    ],
    "sg:phone":"+61 3 9689 6440",
    "sg:postcode":"3011",
    "sg:province":"VIC",
    "sg:tags":[
        "environmental",
        "consultant",
        "pollution"
    ],
    "wof:name":"ESP Environmental & Safety Professionals",
    "wof:placetype":"venue"
},
  "geometry": {"coordinates":[144.903076172,-37.8068885803],"type":"Point"}
}