{
  "type": "Feature",
  "properties": {
    "iso:country":"AU",
    "sg:address":"46 Kirra Pl",
    "sg:city":"Carindale",
    "sg:classifiers":[
        {
            "category":"Retail",
            "subcategory":"Repair Shop",
            "type":"Services"
        }
    ],
    "sg:phone":"+61 7 3420 5145",
    "sg:postcode":"4152",
    "sg:province":"QLD",
    "sg:tags":[
        "mending",
        "clothing",
        "alteration"
    ],
    "wof:name":"Needle N Pins",
    "wof:placetype":"venue"
},
  "geometry": {"coordinates":[153.11799621599999,-27.5302524567],"type":"Point"}
}