{
  "type": "Feature",
  "properties": {
    "iso:country":"AU",
    "sg:address":"2- 10 Kewdale Rd",
    "sg:city":"Welshpool",
    "sg:classifiers":[
        {
            "category":"Train Station",
            "subcategory":"Light Rail",
            "type":"Transportation"
        }
    ],
    "sg:phone":"+61 1800 133 322",
    "sg:postcode":"6106",
    "sg:province":"WA",
    "sg:tags":[
        "equipment",
        "energy",
        "solar"
    ],
    "wof:name":"Solar Sales",
    "wof:placetype":"venue"
},
  "geometry": {"coordinates":[115.954971313,-31.9840068817],"type":"Point"}
}