{
  "type": "Feature",
  "properties": {
    "addr:full":"45- 47 Topham Rd Smeaton Grange NSW 2567",
    "addr:housenumber":"47",
    "addr:postcode":"2567",
    "addr:street":"Topham Rd",
    "iso:country":"AU",
    "sg:address":"45- 47 Topham Rd",
    "sg:city":"Smeaton Grange",
    "sg:classifiers":[
        {
            "category":"Building & Trades",
            "subcategory":"Construction",
            "type":"Services"
        }
    ],
    "sg:phone":"+61 2 4648 5635",
    "sg:postcode":"2567",
    "sg:province":"NSW",
    "sg:tags":[
        "contractor"
    ],
    "wof:name":"Coenen Constructions",
    "wof:placetype":"venue"
},
  "geometry": {"coordinates":[150.75627136200001,-34.0367164612],"type":"Point"}
}