{
  "type": "Feature",
  "properties": {
    "addr:full":"1 Morilla St Tamworth NSW 2340",
    "addr:housenumber":"1",
    "addr:postcode":"2340",
    "addr:street":"Morilla St",
    "iso:country":"AU",
    "sg:address":"1 Morilla St",
    "sg:city":"Tamworth",
    "sg:classifiers":[
        {
            "category":"Commercial Area",
            "type":"Public Place"
        }
    ],
    "sg:phone":"+61 2 6762 1460",
    "sg:postcode":"2340",
    "sg:province":"NSW",
    "sg:tags":[
        "heavy",
        "carrier"
    ],
    "wof:name":"McCulloch Bulk Haulage Pty Ltd",
    "wof:placetype":"venue"
},
  "geometry": {"coordinates":[150.85197448700001,-31.0773468018],"type":"Point"}
}