{
  "type": "Feature",
  "properties": {
    "addr:full":"33 Piddington St St Johns Wood QLD 4060",
    "addr:housenumber":"33",
    "addr:postcode":"4060",
    "addr:street":"Piddington St",
    "iso:country":"AU",
    "sg:address":"33 Piddington St St",
    "sg:city":"Johns Wood",
    "sg:classifiers":[
        {
            "category":"Real Estate",
            "subcategory":"Architect",
            "type":"Services"
        }
    ],
    "sg:phone":"+61 7 3366 4621",
    "sg:postcode":"4060",
    "sg:province":"QLD",
    "wof:name":"Moorhouse Architects",
    "wof:placetype":"venue"
},
  "geometry": {"coordinates":[152.971633911,-27.4460430145],"type":"Point"}
}