{
  "type": "Feature",
  "properties": {
    "addr:full":"Church St Coolah NSW 2843",
    "addr:postcode":"2843",
    "addr:street":"Church St",
    "iso:country":"AU",
    "sg:address":"Church St",
    "sg:city":"Coolah",
    "sg:classifiers":[
        {
            "category":"Education",
            "subcategory":"School",
            "type":"Public Place"
        }
    ],
    "sg:phone":"+61 2 6377 1132",
    "sg:postcode":"2843",
    "sg:province":"NSW",
    "wof:name":"Sacred Heart School",
    "wof:placetype":"venue"
},
  "geometry": {"coordinates":[149.711197,-31.825365],"type":"Point"}
}