{
  "type": "Feature",
  "properties": {
    "iso:country":"AU",
    "sg:address":"24 Goulburn St",
    "sg:city":"Crookwell",
    "sg:classifiers":[
        {
            "category":"Home & Garden",
            "subcategory":"Garden Supply",
            "type":"Retail Goods"
        }
    ],
    "sg:phone":"+61 2 4832 1609",
    "sg:postcode":"2583",
    "sg:province":"NSW",
    "sg:tags":[
        "equipment"
    ],
    "wof:name":"Crookwell Hire",
    "wof:placetype":"venue"
},
  "geometry": {"coordinates":[149.475265503,-34.4623756409],"type":"Point"}
}