{
  "type": "Feature",
  "properties": {
    "iso:country":"AU",
    "sg:address":"Shop 6 Seagulls Shoping Cntr",
    "sg:city":"Slade Point",
    "sg:classifiers":[
        {
            "category":"Food & Beverages",
            "subcategory":"Fruits & Vegetables",
            "type":"Retail Goods"
        }
    ],
    "sg:phone":"+61 7 4955 0255",
    "sg:postcode":"4740",
    "sg:province":"QLD",
    "sg:tags":[
        "greengrocer",
        "fruiterer"
    ],
    "wof:name":"Slade Point Fruit & Vegetables",
    "wof:placetype":"venue"
},
  "geometry": {"coordinates":[149.214203,-21.076981],"type":"Point"}
}