{
  "type": "Feature",
  "properties": {
    "iso:country":"AU",
    "sg:address":"10- 14 Mansbridge Drv",
    "sg:city":"Coffs Harbour",
    "sg:classifiers":[
        {
            "category":"Home & Garden",
            "subcategory":"Building Materials",
            "type":"Retail Goods"
        }
    ],
    "sg:phone":"+61 13 21 36",
    "sg:postcode":"2450",
    "sg:province":"NSW",
    "sg:tags":[
        "laminate",
        "laminated",
        "panel"
    ],
    "wof:name":"Laminex Group The",
    "wof:placetype":"venue"
},
  "geometry": {"coordinates":[153.09198,-30.312441],"type":"Point"}
}