{
  "type": "Feature",
  "properties": {
    "addr:full":"Shop 58 A Golden Grove Village The Golden Way Golden SA 5125",
    "addr:housenumber":"shop 58 a",
    "addr:postcode":"5125",
    "addr:street":"Golden Grove Village The Golden Way",
    "iso:country":"AU",
    "sg:address":"Shop 58",
    "sg:city":"A Golden Grove Village The Golden Way Golden",
    "sg:classifiers":[
        {
            "category":"Shopping",
            "type":"Retail Goods"
        }
    ],
    "sg:phone":"+61 8 8288 7988",
    "sg:postcode":"5125",
    "sg:province":"SA",
    "sg:tags":[
        "repair",
        "travel"
    ],
    "wof:name":"Strandbags Group Pty Limited",
    "wof:placetype":"venue"
},
  "geometry": {"coordinates":[138.715958,-34.775261],"type":"Point"}
}