{
  "type": "Feature",
  "properties": {
    "iso:country":"AU",
    "sg:address":"2A/ 256 Bannister Rd",
    "sg:city":"Canning Vale",
    "sg:classifiers":[
        {
            "category":"Shopping",
            "subcategory":"Clothing, Apparel, & Fashions",
            "type":"Retail Goods"
        }
    ],
    "sg:phone":"+61 8 9455 7374",
    "sg:postcode":"6155",
    "sg:province":"WA",
    "sg:tags":[
        "recycled",
        "clothing"
    ],
    "wof:name":"Salvation Army Family Stores",
    "wof:placetype":"venue"
},
  "geometry": {"coordinates":[115.891724,-32.070789],"type":"Point"}
}