{
  "type": "Feature",
  "properties": {
    "addr:full":"36 Head St Traralgon VIC 3844",
    "addr:housenumber":"36",
    "addr:postcode":"3844",
    "addr:street":"Head St",
    "iso:country":"AU",
    "sg:address":"36 Head St",
    "sg:city":"Traralgon",
    "sg:classifiers":[
        {
            "category":"Professional",
            "subcategory":"Detective & Security Services",
            "type":"Services"
        }
    ],
    "sg:phone":"+61 1300 555 814",
    "sg:postcode":"3844",
    "sg:province":"VIC",
    "sg:tags":[
        "consultant",
        "system"
    ],
    "wof:name":"Jadak Security",
    "wof:placetype":"venue"
},
  "geometry": {"coordinates":[146.55490112300001,-38.1932907104],"type":"Point"}
}