{
  "type": "Feature",
  "properties": {
    "addr:full":"Shop 6, 77 Macquarie Rd Ingleburn NSW 2565",
    "addr:housenumber":"shop;77",
    "addr:postcode":"2565",
    "addr:street":"Macquarie Rd",
    "iso:country":"AU",
    "sg:address":"Shop 6, 77 Macquarie Rd",
    "sg:city":"Ingleburn",
    "sg:classifiers":[
        {
            "category":"Banks & Credit Unions",
            "subcategory":"Financial Services",
            "type":"Services"
        }
    ],
    "sg:phone":"+61 2 9829 1789",
    "sg:postcode":"2565",
    "sg:province":"NSW",
    "sg:tags":[
        "loan",
        "finance",
        "mortgage"
    ],
    "wof:name":"RAMS Home Loans",
    "wof:placetype":"venue"
},
  "geometry": {"coordinates":[150.867843628,-33.9958763123],"type":"Point"}
}