{
  "type": "Feature",
  "properties": {
    "addr:full":"70 Botanic Rd Warrnambool VIC 3280",
    "addr:housenumber":"70",
    "addr:postcode":"3280",
    "addr:street":"Botanic Rd",
    "iso:country":"AU",
    "sg:address":"70 Botanic Rd",
    "sg:city":"Warrnambool",
    "sg:classifiers":[
        {
            "category":"Education",
            "subcategory":"School",
            "type":"Public Place"
        }
    ],
    "sg:phone":"+61 3 5561 1343",
    "sg:postcode":"3280",
    "sg:province":"VIC",
    "sg:tags":[
        "co-educational"
    ],
    "wof:name":"St Josephs Primary School",
    "wof:placetype":"venue"
},
  "geometry": {"coordinates":[142.485107422,-38.3726882935],"type":"Point"}
}