{
  "type": "Feature",
  "properties": {
    "iso:country":"AU",
    "sg:address":"U1/ 70 Rushdale St",
    "sg:city":"Knoxfield",
    "sg:classifiers":[
        {
            "category":"Professional",
            "subcategory":"Testing Lab",
            "type":"Services"
        }
    ],
    "sg:phone":"+61 3 9763 3079",
    "sg:postcode":"3180",
    "sg:province":"VIC",
    "sg:tags":[
        "inspection"
    ],
    "sg:website":"http://www.compeng.com.au",
    "wof:name":"Compliance Engineering",
    "wof:placetype":"venue"
},
  "geometry": {"coordinates":[145.255126953,-37.8938941956],"type":"Point"}
}