{
  "type": "Feature",
  "properties": {
    "iso:country":"AU",
    "sg:address":"19 Ann St",
    "sg:city":"Point Lonsdale",
    "sg:classifiers":[
        {
            "category":"Professional",
            "subcategory":"Management & Consulting",
            "type":"Services"
        }
    ],
    "sg:phone":"+61 3 5258 4205",
    "sg:postcode":"3225",
    "sg:province":"VIC",
    "sg:tags":[
        "consultant"
    ],
    "wof:name":"Pierce Jacqueline & Associates",
    "wof:placetype":"venue"
},
  "geometry": {"coordinates":[144.617737,-38.272396],"type":"Point"}
}