{
  "type": "Feature",
  "properties": {
    "addr:full":"16 Brooklyn St Burwood NSW 2134",
    "addr:housenumber":"16",
    "addr:postcode":"2134",
    "addr:street":"Brooklyn St",
    "iso:country":"AU",
    "sg:address":"16 Brooklyn St",
    "sg:city":"Burwood",
    "sg:classifiers":[
        {
            "category":"Professional",
            "subcategory":"Detective & Security Services",
            "type":"Services"
        }
    ],
    "sg:phone":"+61 400 250 241",
    "sg:postcode":"2134",
    "sg:province":"NSW",
    "sg:tags":[
        "equipment",
        "window",
        "doors"
    ],
    "wof:name":"Terry Middleton",
    "wof:placetype":"venue"
},
  "geometry": {"coordinates":[151.10862731899999,-33.8794517517],"type":"Point"}
}