{
  "type": "Feature",
  "properties": {
    "iso:country":"AU",
    "sg:address":"28/ 7 Bungan St",
    "sg:city":"Mona Vale",
    "sg:classifiers":[
        {
            "category":"Sports & Exercise",
            "subcategory":"Gym",
            "type":"Entertainment"
        }
    ],
    "sg:phone":"+61 2 9999 4753",
    "sg:postcode":"2103",
    "sg:province":"NSW",
    "sg:tags":[
        "pilate",
        "method"
    ],
    "wof:name":"Pilates NY Mona Vale",
    "wof:placetype":"venue"
},
  "geometry": {"coordinates":[151.30232238799999,-33.6768341064],"type":"Point"}
}