{
  "type": "Feature",
  "properties": {
    "addr:full":"59 Russell St Toowoomba QLD 4350",
    "addr:housenumber":"59",
    "addr:postcode":"4350",
    "addr:street":"Russell St",
    "iso:country":"AU",
    "sg:address":"59 Russell St",
    "sg:city":"Toowoomba",
    "sg:classifiers":[
        {
            "category":"Travel",
            "subcategory":"Hotels & Motels",
            "type":"Entertainment"
        }
    ],
    "sg:phone":"+61 7 4639 2706",
    "sg:postcode":"4350",
    "sg:province":"QLD",
    "sg:tags":[
        "accommodation"
    ],
    "wof:name":"National Hotel",
    "wof:placetype":"venue"
},
  "geometry": {"coordinates":[151.95242300000001,-27.558804],"type":"Point"}
}