{
  "type": "Feature",
  "properties": {
    "addr:full":"Suite 1, 907 Canning Hwy Applecross WA 6153",
    "addr:housenumber":"907",
    "addr:postcode":"6153",
    "addr:street":"Canning Hwy",
    "iso:country":"AU",
    "sg:address":"Suite 1, 907 Canning Hwy",
    "sg:city":"Applecross",
    "sg:classifiers":[
        {
            "category":"Banks & Credit Unions",
            "subcategory":"Financial Services",
            "type":"Services"
        }
    ],
    "sg:phone":"+61 8 9316 7000",
    "sg:postcode":"6153",
    "sg:province":"WA",
    "sg:tags":[
        "planning"
    ],
    "wof:name":"Associated Planners Financial Services Limited",
    "wof:placetype":"venue"
},
  "geometry": {"coordinates":[115.849762,-32.012585],"type":"Point"}
}