{
  "type": "Feature",
  "properties": {
    "iso:country":"AU",
    "sg:address":"Un 24/42- 46 Wattle Rd",
    "sg:city":"Brookvale",
    "sg:classifiers":[
        {
            "category":"Shopping",
            "type":"Retail Goods"
        }
    ],
    "sg:phone":"+61 2 9907 1133",
    "sg:postcode":"2100",
    "sg:province":"NSW",
    "sg:tags":[
        "equipment",
        "safety",
        "accessory"
    ],
    "wof:name":"Universal Safety Supplies",
    "wof:placetype":"venue"
},
  "geometry": {"coordinates":[151.27487182600001,-33.7677192688],"type":"Point"}
}