{
  "type": "Feature",
  "properties": {
    "iso:country":"AU",
    "sg:address":"5 Deans Rd",
    "sg:city":"Upwey",
    "sg:classifiers":[
        {
            "category":"Professional",
            "subcategory":"Computer Services",
            "type":"Services"
        }
    ],
    "sg:phone":"+61 3 9754 3876",
    "sg:postcode":"3158",
    "sg:province":"VIC",
    "sg:tags":[
        "tele-communications",
        "consultant"
    ],
    "wof:name":"Siera Communications",
    "wof:placetype":"venue"
},
  "geometry": {"coordinates":[145.328735352,-37.9110183716],"type":"Point"}
}