{
  "type": "Feature",
  "properties": {
    "addr:full":"1370 Stevens St Mundaring WA 6073",
    "addr:housenumber":"1370",
    "addr:postcode":"6073",
    "addr:street":"Stevens St",
    "iso:country":"AU",
    "sg:address":"1370 Stevens St",
    "sg:city":"Mundaring",
    "sg:classifiers":[
        {
            "category":"Professional",
            "type":"Services"
        }
    ],
    "sg:phone":"+61 400 098 801",
    "sg:postcode":"6073",
    "sg:province":"WA",
    "sg:tags":[
        "courier"
    ],
    "wof:name":"Worldwide Express",
    "wof:placetype":"venue"
},
  "geometry": {"coordinates":[116.176177978,-31.8958110809],"type":"Point"}
}