{
  "type": "Feature",
  "properties": {
    "iso:country":"AU",
    "sg:address":"332 Gorge Rd",
    "sg:city":"Athelstone",
    "sg:classifiers":[
        {
            "category":"Health Services",
            "subcategory":"Dentist",
            "type":"Services"
        }
    ],
    "sg:phone":"+61 8 8336 3011",
    "sg:postcode":"5076",
    "sg:province":"SA",
    "wof:name":"Li Peter K Dr",
    "wof:placetype":"venue"
},
  "geometry": {"coordinates":[138.70466613799999,-34.8693237305],"type":"Point"}
}