{
  "type": "Feature",
  "properties": {
    "iso:country":"AU",
    "sg:address":"20 Spring St",
    "sg:city":"Bondi Junction",
    "sg:classifiers":[
        {
            "category":"Health Services",
            "subcategory":"Dentist",
            "type":"Services"
        }
    ],
    "sg:phone":"+61 2 9389 0391",
    "sg:postcode":"2022",
    "sg:province":"NSW",
    "sg:tags":[
        "dental",
        "prosthetist"
    ],
    "wof:name":"Bondi Junction Denture Clinic",
    "wof:placetype":"venue"
},
  "geometry": {"coordinates":[151.24615478499999,-33.8919906616],"type":"Point"}
}