{
  "type": "Feature",
  "properties": {
    "addr:full":"South St Bridport TAS 7262",
    "addr:postcode":"7262",
    "addr:street":"South St",
    "iso:country":"AU",
    "sg:address":"South St",
    "sg:city":"Bridport",
    "sg:classifiers":[
        {
            "category":"Education",
            "subcategory":"School",
            "type":"Public Place"
        }
    ],
    "sg:phone":"+61 3 6356 1226",
    "sg:postcode":"7262",
    "sg:province":"TAS",
    "sg:tags":[
        "state",
        "except",
        "nsw"
    ],
    "wof:name":"Bridport Primary School",
    "wof:placetype":"venue"
},
  "geometry": {"coordinates":[147.39021299999999,-41.003887],"type":"Point"}
}