{
  "type": "Feature",
  "properties": {
    "addr:full":"Elanora Drv Rockingham WA 6168",
    "addr:postcode":"6168",
    "addr:street":"Elanora Drv",
    "iso:country":"AU",
    "sg:address":"Elanora Drv",
    "sg:city":"Rockingham",
    "sg:classifiers":[
        {
            "category":"Organizations",
            "subcategory":"Non-profit Organization",
            "type":"Services"
        }
    ],
    "sg:phone":"+61 8 9527 3142",
    "sg:postcode":"6168",
    "sg:province":"WA",
    "sg:tags":[
        "environmental",
        "organisation",
        "conservation"
    ],
    "wof:name":"Men Of The Trees",
    "wof:placetype":"venue"
},
  "geometry": {"coordinates":[115.762878,-32.294498],"type":"Point"}
}