{
  "type": "Feature",
  "properties": {
    "iso:country":"AU",
    "sg:address":"Morpung Ave",
    "sg:city":"Irymple",
    "sg:classifiers":[
        {
            "category":"Building & Trades",
            "subcategory":"Construction",
            "type":"Services"
        }
    ],
    "sg:phone":"+61 3 5024 5773",
    "sg:postcode":"3498",
    "sg:province":"VIC",
    "sg:tags":[
        "pool",
        "swimming"
    ],
    "wof:name":"Clarke B D & J L",
    "wof:placetype":"venue"
},
  "geometry": {"coordinates":[142.18576049800001,-34.2393913269],"type":"Point"}
}