{
  "type": "Feature",
  "properties": {
    "addr:full":"27/ 231 Brisbane Rd Labrador QLD 4215",
    "addr:housenumber":"27 / 231",
    "addr:postcode":"4215",
    "addr:street":"Brisbane Rd",
    "iso:country":"AU",
    "sg:address":"27/ 231 Brisbane Rd",
    "sg:city":"Labrador",
    "sg:classifiers":[
        {
            "category":"Manufacturing",
            "subcategory":"Watercraft",
            "type":"Manufacturing & Wholesale Goods"
        }
    ],
    "sg:phone":"+61 7 5537 7433",
    "sg:postcode":"4215",
    "sg:province":"QLD",
    "sg:tags":[
        "sail",
        "marine",
        "maker"
    ],
    "wof:name":"Quantum Sails Qld",
    "wof:placetype":"venue"
},
  "geometry": {"coordinates":[153.40724182100001,-27.9381504059],"type":"Point"}
}