{
  "type": "Feature",
  "properties": {
    "iso:country":"AU",
    "sg:address":"McEwan Ave",
    "sg:city":"Winston Hills",
    "sg:classifiers":[
        {
            "category":"Professional",
            "subcategory":"Accounting & Tax Preparation",
            "type":"Services"
        }
    ],
    "sg:phone":"+61 2 9639 8485",
    "sg:postcode":"2153",
    "sg:province":"NSW",
    "sg:tags":[
        "accountant",
        "auditor"
    ],
    "wof:name":"Norris W F",
    "wof:placetype":"venue"
},
  "geometry": {"coordinates":[150.990234375,-33.77942276],"type":"Point"}
}