{
  "type": "Feature",
  "properties": {
    "addr:full":"628 Maryborough-Biggenden Rd Maryborough QLD 4650",
    "addr:housenumber":"628",
    "addr:postcode":"4650",
    "addr:street":"Maryborough-Biggenden Rd",
    "iso:country":"AU",
    "sg:address":"628 Maryborough-Biggenden Rd",
    "sg:city":"Maryborough",
    "sg:classifiers":[
        {
            "category":"Retail",
            "subcategory":"Car Wash",
            "type":"Services"
        }
    ],
    "sg:phone":"+61 7 4121 2053",
    "sg:postcode":"4650",
    "sg:province":"QLD",
    "sg:tags":[
        "bitumen",
        "spraying"
    ],
    "wof:name":"Heritage Dingo Digga",
    "wof:placetype":"venue"
},
  "geometry": {"coordinates":[152.658051,-25.513645],"type":"Point"}
}