{
  "type": "Feature",
  "properties": {
    "addr:full":"6/ 67 Jacaranda Ave Bradbury NSW 2560",
    "addr:housenumber":"/ 67",
    "addr:postcode":"2560",
    "addr:street":"Jacaranda Ave",
    "iso:country":"AU",
    "sg:address":"6/ 67 Jacaranda Ave",
    "sg:city":"Bradbury",
    "sg:classifiers":[
        {
            "category":"Health Services",
            "subcategory":"Dentist",
            "type":"Services"
        }
    ],
    "sg:phone":"+61 2 4628 2151",
    "sg:postcode":"2560",
    "sg:province":"NSW",
    "wof:name":"Bradbury Dental Surgery",
    "wof:placetype":"venue"
},
  "geometry": {"coordinates":[150.81422424300001,-34.0842628479],"type":"Point"}
}