{
  "type": "Feature",
  "properties": {
    "addr:full":"Bldg 2, 175 Varsity Pde Varsity Lakes QLD 4226",
    "addr:housenumber":"175",
    "addr:postcode":"4226",
    "addr:street":"Varsity Pde",
    "iso:country":"AU",
    "sg:address":"Bldg 2, 175 Varsity Pde",
    "sg:city":"Varsity Lakes",
    "sg:classifiers":[
        {
            "category":"Professional",
            "subcategory":"Management & Consulting",
            "type":"Services"
        }
    ],
    "sg:phone":"+61 7 5553 6060",
    "sg:postcode":"4226",
    "sg:province":"QLD",
    "sg:tags":[
        "consultant"
    ],
    "wof:name":"Pacific Training & Development",
    "wof:placetype":"venue"
},
  "geometry": {"coordinates":[153.41175842300001,-28.0792102814],"type":"Point"}
}