{
  "type": "Feature",
  "properties": {
    "addr:full":"9 Hawdon St Moruya NSW 2537",
    "addr:housenumber":"9",
    "addr:postcode":"2537",
    "addr:street":"Hawdon St",
    "iso:country":"AU",
    "sg:address":"9 Hawdon St",
    "sg:city":"Moruya",
    "sg:classifiers":[
        {
            "category":"Professional",
            "subcategory":"Art Services",
            "type":"Services"
        }
    ],
    "sg:phone":"+61 408 976 291",
    "sg:postcode":"2537",
    "sg:province":"NSW",
    "sg:tags":[
        "decorator",
        "painter"
    ],
    "wof:name":"O&#039;Connor Tony",
    "wof:placetype":"venue"
},
  "geometry": {"coordinates":[150.068450928,-35.9054870605],"type":"Point"}
}