{
  "type": "Feature",
  "properties": {
    "addr:full":"Shp 1/ 118 Main St Proserpine QLD 4800",
    "addr:housenumber":"/ 118",
    "addr:postcode":"4800",
    "addr:street":"Main St",
    "iso:country":"AU",
    "sg:address":"Shp 1/ 118 Main St",
    "sg:city":"Proserpine",
    "sg:classifiers":[
        {
            "category":"Real Estate",
            "subcategory":"Real Estate Agent",
            "type":"Services"
        }
    ],
    "sg:phone":"+61 7 4945 1400",
    "sg:postcode":"4800",
    "sg:province":"QLD",
    "wof:name":"Harcourts Proserpine Whitsunday",
    "wof:placetype":"venue"
},
  "geometry": {"coordinates":[148.58514404300001,-20.4020843506],"type":"Point"}
}