{
  "type": "Feature",
  "properties": {
    "iso:country":"AU",
    "sg:address":"Brickworks Crt",
    "sg:city":"Glenella",
    "sg:classifiers":[
        {
            "category":"Professional",
            "subcategory":"Detective & Security Services",
            "type":"Services"
        }
    ],
    "sg:phone":"+61 7 4969 2525",
    "sg:postcode":"4740",
    "sg:province":"QLD",
    "sg:tags":[
        "equipment",
        "window",
        "doors"
    ],
    "wof:name":"Porters",
    "wof:placetype":"venue"
},
  "geometry": {"coordinates":[149.14892599999999,-21.131191],"type":"Point"}
}