{
  "type": "Feature",
  "properties": {
    "iso:country":"AU",
    "sg:address":"59 First Ave",
    "sg:city":"Cockatoo",
    "sg:classifiers":[
        {
            "category":"Organizations",
            "subcategory":"Community Association",
            "type":"Services"
        }
    ],
    "sg:phone":"+61 3 5968 9380",
    "sg:postcode":"3781",
    "sg:province":"VIC",
    "sg:tags":[
        "shiatsu",
        "therapy"
    ],
    "wof:name":"Shiatsu For You",
    "wof:placetype":"venue"
},
  "geometry": {"coordinates":[145.486298,-37.941631],"type":"Point"}
}