{
  "type": "Feature",
  "properties": {
    "addr:full":"36 Mann St Invermay TAS 7248",
    "addr:housenumber":"36",
    "addr:postcode":"7248",
    "addr:street":"Mann St",
    "iso:country":"AU",
    "sg:address":"36 Mann St",
    "sg:city":"Invermay",
    "sg:classifiers":[
        {
            "category":"Insurance",
            "subcategory":"Hazard Insurance",
            "type":"Services"
        }
    ],
    "sg:phone":"+61 409 546 637",
    "sg:postcode":"7248",
    "sg:province":"TAS",
    "sg:tags":[
        "fire",
        "accident",
        "marine"
    ],
    "wof:name":"Aardvark Cleaning & Restoration Services",
    "wof:placetype":"venue"
},
  "geometry": {"coordinates":[147.13705444300001,-41.4149551392],"type":"Point"}
}