{
  "type": "Feature",
  "properties": {
    "addr:full":"Suite 22 22/ 25 Walters Drv Osborne Park WA 6017",
    "addr:housenumber":"22 / 25",
    "addr:postcode":"6017",
    "addr:street":"Walters Drv",
    "iso:country":"AU",
    "sg:address":"Suite 22 22/ 25 Walters Drv",
    "sg:city":"Osborne Park",
    "sg:classifiers":[
        {
            "category":"Health Services",
            "subcategory":"Health Practitioner",
            "type":"Services"
        }
    ],
    "sg:phone":"+61 8 9244 8345",
    "sg:postcode":"6017",
    "sg:province":"WA",
    "sg:tags":[
        "pathologist",
        "speech"
    ],
    "wof:name":"Viva Speech Pathology",
    "wof:placetype":"venue"
},
  "geometry": {"coordinates":[115.80911254900001,-31.9092922211],"type":"Point"}
}