{
  "type": "Feature",
  "properties": {
    "iso:country":"AU",
    "sg:address":"59 Liverpool St",
    "sg:city":"Hobart",
    "sg:classifiers":[
        {
            "category":"Personal",
            "type":"Services"
        }
    ],
    "sg:phone":"+61 3 6236 9769",
    "sg:postcode":"7000",
    "sg:province":"TAS",
    "sg:tags":[
        "gift"
    ],
    "wof:name":"Hampers By Jeffersons",
    "wof:placetype":"venue"
},
  "geometry": {"coordinates":[147.32791137699999,-42.8804016113],"type":"Point"}
}