{
  "type": "Feature",
  "properties": {
    "addr:full":"YMCA Mannington St Acacia Ridge QLD 4110",
    "addr:postcode":"4110",
    "addr:street":"Mannington St",
    "iso:country":"AU",
    "sg:address":"YMCA Mannington St",
    "sg:city":"Acacia Ridge",
    "sg:classifiers":[
        {
            "category":"Arena",
            "subcategory":"Sports Club",
            "type":"Entertainment"
        }
    ],
    "sg:phone":"+61 410 608 571",
    "sg:postcode":"4110",
    "sg:province":"QLD",
    "sg:tags":[
        "defence",
        "supply",
        "self",
        "instruction",
        "martial art"
    ],
    "wof:name":"Australian Freestyle Tae Kwon Do Academy",
    "wof:placetype":"venue"
},
  "geometry": {"coordinates":[153.025924683,-27.5849018097],"type":"Point"}
}