{
  "type": "Feature",
  "properties": {
    "addr:full":"7 Fairlie St Yarraville VIC 3013",
    "addr:housenumber":"7",
    "addr:postcode":"3013",
    "addr:street":"Fairlie St",
    "iso:country":"AU",
    "sg:address":"7 Fairlie St",
    "sg:city":"Yarraville",
    "sg:classifiers":[
        {
            "category":"Professional",
            "subcategory":"Art Services",
            "type":"Services"
        }
    ],
    "sg:phone":"+61 412 239 894",
    "sg:postcode":"3013",
    "sg:province":"VIC",
    "sg:tags":[
        "decorator",
        "painter"
    ],
    "wof:name":"Imperial Painting Service",
    "wof:placetype":"venue"
},
  "geometry": {"coordinates":[144.89385986299999,-37.8118667603],"type":"Point"}
}