{
  "type": "Feature",
  "properties": {
    "addr:full":"6 Norfolk St Blackwood SA 5051",
    "addr:housenumber":"6",
    "addr:postcode":"5051",
    "addr:street":"Norfolk St",
    "iso:country":"AU",
    "sg:address":"6 Norfolk St",
    "sg:city":"Blackwood",
    "sg:classifiers":[
        {
            "category":"Professional",
            "subcategory":"Computer Services",
            "type":"Services"
        }
    ],
    "sg:phone":"+61 8 8278 6320",
    "sg:postcode":"5051",
    "sg:province":"SA",
    "sg:tags":[
        "consultant",
        "system"
    ],
    "wof:name":"MJ & PD Horn",
    "wof:placetype":"venue"
},
  "geometry": {"coordinates":[138.61799600000001,-35.008793],"type":"Point"}
}