{
  "type": "Feature",
  "properties": {
    "iso:country":"AU",
    "sg:address":"2135 Frankston Flinders Rd",
    "sg:city":"Hastings",
    "sg:classifiers":[
        {
            "category":"Home & Garden",
            "subcategory":"Kitchen Supply",
            "type":"Retail Goods"
        }
    ],
    "sg:phone":"+61 3 5979 2050",
    "sg:postcode":"3915",
    "sg:province":"VIC",
    "sg:tags":[
        "sharpening"
    ],
    "wof:name":"Leading Edge Saws Tools And Cutters",
    "wof:placetype":"venue"
},
  "geometry": {"coordinates":[145.18377685600001,-38.3118972778],"type":"Point"}
}