{
  "type": "Feature",
  "properties": {
    "addr:full":"12 Waratah St Mona Vale NSW 2103",
    "addr:housenumber":"12",
    "addr:postcode":"2103",
    "addr:street":"Waratah St",
    "iso:country":"AU",
    "sg:address":"12 Waratah St",
    "sg:city":"Mona Vale",
    "sg:classifiers":[
        {
            "category":"Real Estate",
            "subcategory":"Real Estate Agent",
            "type":"Services"
        }
    ],
    "sg:phone":"+61 2 9997 4444",
    "sg:postcode":"2103",
    "sg:province":"NSW",
    "wof:name":"Hardys",
    "wof:placetype":"venue"
},
  "geometry": {"coordinates":[151.30258178700001,-33.6775474548],"type":"Point"}
}