{
  "type": "Feature",
  "properties": {
    "iso:country":"AU",
    "sg:address":"Buckland Rd",
    "sg:city":"Beechworth",
    "sg:classifiers":[
        {
            "category":"Farming",
            "subcategory":"Orchard",
            "type":"Manufacturing & Wholesale Goods"
        }
    ],
    "sg:phone":"+61 3 5728 1748",
    "sg:postcode":"3747",
    "sg:province":"VIC",
    "sg:tags":[
        "pear",
        "apple",
        "grower"
    ],
    "wof:name":"Christesen J",
    "wof:placetype":"venue"
},
  "geometry": {"coordinates":[146.681976,-36.365589],"type":"Point"}
}