{
  "type": "Feature",
  "properties": {
    "addr:full":"Cnr McFarlane & Treves Sts Merrylands NSW 2160",
    "addr:postcode":"2160",
    "addr:street":"Cnr",
    "iso:country":"AU",
    "sg:address":"Cnr McFarlane & Treves Sts",
    "sg:city":"Merrylands",
    "sg:classifiers":[
        {
            "category":"Retail",
            "subcategory":"Car Wash",
            "type":"Services"
        }
    ],
    "sg:phone":"+61 2 9897 7506",
    "sg:postcode":"2160",
    "sg:province":"NSW",
    "sg:tags":[
        "truck",
        "cleaning"
    ],
    "wof:name":"Carlovers Carwash Limited",
    "wof:placetype":"venue"
},
  "geometry": {"coordinates":[150.98890685999999,-33.8352241516],"type":"Point"}
}