{
  "type": "Feature",
  "properties": {
    "addr:full":"Unit 13/ 32 Wyllie St Bundaberg QLD 4670",
    "addr:housenumber":"/ 32",
    "addr:postcode":"4670",
    "addr:street":"Wyllie St",
    "iso:country":"AU",
    "sg:address":"Unit 13/ 32 Wyllie St",
    "sg:city":"Bundaberg",
    "sg:classifiers":[
        {
            "category":"Autos & Motor Vehicles",
            "subcategory":"Auto Supplies",
            "type":"Retail Goods"
        }
    ],
    "sg:phone":"+61 407 148 303",
    "sg:postcode":"4670",
    "sg:province":"QLD",
    "sg:tags":[
        "battery",
        "automotive"
    ],
    "wof:name":"Super Start Batteries",
    "wof:placetype":"venue"
},
  "geometry": {"coordinates":[152.36026000999999,-24.9009609222],"type":"Point"}
}