{
  "type": "Feature",
  "properties": {
    "iso:country":"AU",
    "sg:address":"15 Price St",
    "sg:city":"Southport",
    "sg:classifiers":[
        {
            "category":"Retail",
            "subcategory":"Auto Repair",
            "type":"Services"
        }
    ],
    "sg:phone":"+61 7 5532 4585",
    "sg:postcode":"4215",
    "sg:province":"QLD",
    "sg:tags":[
        "repairer",
        "motor",
        "engineer"
    ],
    "wof:name":"Falkiner Automotive Services",
    "wof:placetype":"venue"
},
  "geometry": {"coordinates":[153.40403747600001,-27.9662322998],"type":"Point"}
}