{
  "type": "Feature",
  "properties": {
    "addr:full":"19 Bombala St Cooma NSW 2630",
    "addr:housenumber":"19",
    "addr:postcode":"2630",
    "addr:street":"Bombala St",
    "iso:country":"AU",
    "sg:address":"19 Bombala St",
    "sg:city":"Cooma",
    "sg:classifiers":[
        {
            "category":"Personal",
            "subcategory":"Skin Care",
            "type":"Services"
        }
    ],
    "sg:phone":"+61 2 6452 7700",
    "sg:postcode":"2630",
    "sg:province":"NSW",
    "sg:tags":[
        "treatment"
    ],
    "wof:name":"Country Skin Reflections",
    "wof:placetype":"venue"
},
  "geometry": {"coordinates":[149.126586914,-36.2339782715],"type":"Point"}
}