{
  "type": "Feature",
  "properties": {
    "iso:country":"AU",
    "sg:address":"16 Swift St",
    "sg:city":"Aberfoyle Park",
    "sg:classifiers":[
        {
            "category":"Professional",
            "subcategory":"Printing & Photocopies",
            "type":"Services"
        }
    ],
    "sg:phone":"+61 8 8270 4358",
    "sg:postcode":"5159",
    "sg:province":"SA",
    "sg:tags":[
        "publishing",
        "desktop"
    ],
    "wof:name":"Barry Ryan",
    "wof:placetype":"venue"
},
  "geometry": {"coordinates":[138.59257507300001,-35.0658340454],"type":"Point"}
}