{
  "type": "Feature",
  "properties": {
    "iso:country":"AU",
    "sg:address":"165 Augusta Rd",
    "sg:city":"Lenah Valley",
    "sg:classifiers":[
        {
            "category":"Arts & Performance",
            "subcategory":"Music",
            "type":"Entertainment"
        }
    ],
    "sg:phone":"+61 439 386 776",
    "sg:postcode":"7008",
    "sg:province":"TAS",
    "sg:tags":[
        "mobile",
        "jockey",
        "disc"
    ],
    "wof:name":"Evolution Productions",
    "wof:placetype":"venue"
},
  "geometry": {"coordinates":[147.28953552199999,-42.8627967834],"type":"Point"}
}