{
  "type": "Feature",
  "properties": {
    "addr:full":"8/ 37 Veronica St Capalaba QLD 4157",
    "addr:housenumber":"/ 37",
    "addr:postcode":"4157",
    "addr:street":"Veronica St",
    "iso:country":"AU",
    "sg:address":"8/ 37 Veronica St",
    "sg:city":"Capalaba",
    "sg:classifiers":[
        {
            "category":"Shopping",
            "subcategory":"Party Supplies",
            "type":"Retail Goods"
        }
    ],
    "sg:phone":"+61 7 3823 1004",
    "sg:postcode":"4157",
    "sg:province":"QLD",
    "sg:tags":[
        "equipment",
        "metal",
        "spraying"
    ],
    "wof:name":"Mssa-Interweld",
    "wof:placetype":"venue"
},
  "geometry": {"coordinates":[153.19696044899999,-27.5266647339],"type":"Point"}
}