{
  "type": "Feature",
  "properties": {
    "addr:full":"Davy Robinson Drv Moorebank NSW 2170",
    "addr:postcode":"2170",
    "addr:street":"Robinson Drv",
    "iso:country":"AU",
    "sg:address":"Davy Robinson Drv",
    "sg:city":"Moorebank",
    "sg:classifiers":[
        {
            "category":"Utilities",
            "subcategory":"Sewage",
            "type":"Services"
        }
    ],
    "sg:phone":"+61 2 9600 7758",
    "sg:postcode":"2170",
    "sg:province":"NSW",
    "sg:tags":[
        "water",
        "waste",
        "treatment"
    ],
    "wof:name":"Leichhardt Engineering Workshops",
    "wof:placetype":"venue"
},
  "geometry": {"coordinates":[150.96890258799999,-33.929359436],"type":"Point"}
}