{
  "type": "Feature",
  "properties": {
    "addr:full":"Shop 11 Stones Corner Plaza 357 Logan Rd Stones Corner QLD 4120",
    "addr:housenumber":"shop 11;357",
    "addr:postcode":"4120",
    "addr:street":"Corner;Logan Rd",
    "iso:country":"AU",
    "sg:address":"Shop 11 Stones Corner Plaza 357 Logan Rd",
    "sg:city":"Stones Corner",
    "sg:classifiers":[
        {
            "category":"Personal",
            "subcategory":"Beauty Salon",
            "type":"Services"
        }
    ],
    "sg:phone":"+61 7 3397 1338",
    "sg:postcode":"4120",
    "sg:province":"QLD",
    "sg:tags":[
        "hairdresser"
    ],
    "wof:name":"L.A. Sweeney's",
    "wof:placetype":"venue"
},
  "geometry": {"coordinates":[153.04481506400001,-27.4992179871],"type":"Point"}
}