{
  "type": "Feature",
  "properties": {
    "addr:full":"87 Undola Rd Helensburgh NSW 2508",
    "addr:housenumber":"87",
    "addr:postcode":"2508",
    "addr:street":"Undola Rd",
    "iso:country":"AU",
    "sg:address":"87 Undola Rd",
    "sg:city":"Helensburgh",
    "sg:classifiers":[
        {
            "category":"Building & Trades",
            "subcategory":"Construction",
            "type":"Services"
        }
    ],
    "sg:phone":"+61 418 291 297",
    "sg:postcode":"2508",
    "sg:province":"NSW",
    "sg:tags":[
        "spouting",
        "guttering"
    ],
    "wof:name":"Ians Roof Plumbing Service",
    "wof:placetype":"venue"
},
  "geometry": {"coordinates":[150.983475,-34.199738],"type":"Point"}
}