{
  "type": "Feature",
  "properties": {
    "addr:full":"30 Craighill Rd St Georges SA 5064",
    "addr:housenumber":"30",
    "addr:postcode":"5064",
    "addr:street":"Craighill Rd",
    "iso:country":"AU",
    "sg:address":"30 Craighill Rd St",
    "sg:city":"Georges",
    "sg:classifiers":[
        {
            "category":"Government",
            "subcategory":"Court House",
            "type":"Public Place"
        }
    ],
    "sg:phone":"+61 432 995 470",
    "sg:postcode":"5064",
    "sg:province":"SA",
    "sg:tags":[
        "personal",
        "marriage",
        "family",
        "counselling"
    ],
    "wof:name":"Belle McCaleb",
    "wof:placetype":"venue"
},
  "geometry": {"coordinates":[138.648727417,-34.9529876709],"type":"Point"}
}