{
  "type": "Feature",
  "properties": {
    "iso:country":"AU",
    "sg:address":"413 High St",
    "sg:city":"Melton",
    "sg:classifiers":[
        {
            "category":"Sports & Exercise",
            "subcategory":"Gym",
            "type":"Entertainment"
        }
    ],
    "sg:phone":"+61 3 9743 3119",
    "sg:postcode":"3337",
    "sg:province":"VIC",
    "sg:tags":[
        "personal",
        "trainer",
        "fitness"
    ],
    "wof:name":"Fernwood",
    "wof:placetype":"venue"
},
  "geometry": {"coordinates":[144.579239,-37.683643],"type":"Point"}
}