{
  "type": "Feature",
  "properties": {
    "iso:country":"AU",
    "sg:address":"Shp5/ 86 King George Pde",
    "sg:city":"Forster",
    "sg:classifiers":[
        {
            "category":"Personal",
            "subcategory":"Beauty Salon",
            "type":"Services"
        }
    ],
    "sg:phone":"+61 2 6554 7422",
    "sg:postcode":"2428",
    "sg:province":"NSW",
    "sg:tags":[
        "hairdresser"
    ],
    "wof:name":"Sunshine Hair Salon",
    "wof:placetype":"venue"
},
  "geometry": {"coordinates":[152.520554,-32.215382],"type":"Point"}
}