{
  "type": "Feature",
  "properties": {
    "addr:full":"293 Liverpool St Hobart TAS 7000",
    "addr:housenumber":"293",
    "addr:postcode":"7000",
    "addr:street":"Liverpool St",
    "iso:country":"AU",
    "sg:address":"293 Liverpool St",
    "sg:city":"Hobart",
    "sg:classifiers":[
        {
            "category":"Retail",
            "subcategory":"Auto Repair",
            "type":"Services"
        }
    ],
    "sg:phone":"+61 3 6234 8818",
    "sg:postcode":"7000",
    "sg:province":"TAS",
    "sg:tags":[
        "testing",
        "inspection",
        "motor",
        "vehicle"
    ],
    "wof:name":"Autotechnik",
    "wof:placetype":"venue"
},
  "geometry": {"coordinates":[147.32148742699999,-42.8863258362],"type":"Point"}
}