{
  "type": "Feature",
  "properties": {
    "addr:full":"Mackay & Cusack Sts Wangaratta VIC 3677",
    "addr:postcode":"3677",
    "iso:country":"AU",
    "sg:address":"Mackay & Cusack Sts",
    "sg:city":"Wangaratta",
    "sg:classifiers":[
        {
            "category":"Travel",
            "subcategory":"Hotels & Motels",
            "type":"Entertainment"
        }
    ],
    "sg:phone":"+61 3 5721 7444",
    "sg:postcode":"3677",
    "sg:province":"VIC",
    "wof:name":"Hermitage Motor Inn",
    "wof:placetype":"venue"
},
  "geometry": {"coordinates":[146.31903076200001,-36.3571357727],"type":"Point"}
}