{
  "type": "Feature",
  "properties": {
    "addr:full":"1357 Gympie Rd Aspley QLD 4034",
    "addr:housenumber":"1357",
    "addr:postcode":"4034",
    "addr:street":"Gympie Rd",
    "iso:country":"AU",
    "sg:address":"1357 Gympie Rd",
    "sg:city":"Aspley",
    "sg:classifiers":[
        {
            "category":"Restaurant",
            "type":"Food & Drink"
        }
    ],
    "sg:phone":"+61 7 3263 4509",
    "sg:postcode":"4034",
    "sg:province":"QLD",
    "wof:name":"Antenna Blu Pizza Restaurant",
    "wof:placetype":"venue"
},
  "geometry": {"coordinates":[153.017426,-27.362474],"type":"Point"}
}