{
  "type": "Feature",
  "properties": {
    "addr:full":"290 Clarinda St Parkes NSW 2870",
    "addr:housenumber":"290",
    "addr:postcode":"2870",
    "addr:street":"Clarinda St",
    "iso:country":"AU",
    "sg:address":"290 Clarinda St",
    "sg:city":"Parkes",
    "sg:classifiers":[
        {
            "category":"Shopping",
            "subcategory":"Clothing, Apparel, & Fashions",
            "type":"Retail Goods"
        }
    ],
    "sg:phone":"+61 2 6862 1549",
    "sg:postcode":"2870",
    "sg:province":"NSW",
    "sg:tags":[
        "jean"
    ],
    "wof:name":"Just Jeans Pty Ltd",
    "wof:placetype":"venue"
},
  "geometry": {"coordinates":[148.17425499999999,-33.134552],"type":"Point"}
}