{
  "type": "Feature",
  "properties": {
    "iso:country":"AU",
    "sg:address":"PO Box 112",
    "sg:city":"Lower Plenty",
    "sg:classifiers":[
        {
            "category":"Building & Trades",
            "subcategory":"Plumbing",
            "type":"Services"
        }
    ],
    "sg:phone":"+61 411 551 882",
    "sg:postcode":"3093",
    "sg:province":"VIC",
    "sg:tags":[
        "plumber",
        "gasfitters"
    ],
    "wof:name":"Mark Hatton Plumbing & Construction",
    "wof:placetype":"venue"
},
  "geometry": {"coordinates":[145.11796569800001,-37.7384605408],"type":"Point"}
}