{
  "type": "Feature",
  "properties": {
    "addr:full":"77 Middle Harbour Rd Lindfield NSW 2070",
    "addr:housenumber":"77",
    "addr:postcode":"2070",
    "addr:street":"Middle Harbour Rd",
    "iso:country":"AU",
    "sg:address":"77 Middle Harbour Rd",
    "sg:city":"Lindfield",
    "sg:classifiers":[
        {
            "category":"Utilities",
            "subcategory":"Electric",
            "type":"Services"
        }
    ],
    "sg:phone":"+61 418 613 294",
    "sg:postcode":"2070",
    "sg:province":"NSW",
    "sg:tags":[
        "electrical",
        "contractor"
    ],
    "wof:name":"Energy Electrical Services Pty. Ltd.",
    "wof:placetype":"venue"
},
  "geometry": {"coordinates":[151.17784118599999,-33.7747459412],"type":"Point"}
}