{
  "type": "Feature",
  "properties": {
    "iso:country":"AU",
    "sg:address":"24 High St",
    "sg:city":"Yamba",
    "sg:classifiers":[
        {
            "category":"Personal",
            "subcategory":"Massage",
            "type":"Services"
        }
    ],
    "sg:phone":"+61 2 6646 3480",
    "sg:postcode":"2464",
    "sg:province":"NSW",
    "sg:tags":[
        "therapy"
    ],
    "wof:name":"Yamba Natural Therapies",
    "wof:placetype":"venue"
},
  "geometry": {"coordinates":[153.36253356899999,-29.4350605011],"type":"Point"}
}