{
  "type": "Feature",
  "properties": {
    "iso:country":"AU",
    "sg:address":"Haig St",
    "sg:city":"Heidelberg Heights",
    "sg:classifiers":[
        {
            "category":"Education",
            "subcategory":"School",
            "type":"Public Place"
        }
    ],
    "sg:phone":"+61 3 9457 1678",
    "sg:postcode":"3081",
    "sg:province":"VIC",
    "sg:tags":[
        "state",
        "except",
        "nsw"
    ],
    "wof:name":"Haig St Primary School",
    "wof:placetype":"venue"
},
  "geometry": {"coordinates":[145.05218505900001,-37.7459335327],"type":"Point"}
}