{
  "type": "Feature",
  "properties": {
    "addr:full":"25 Oaktree Rd Croydon VIC 3136",
    "addr:housenumber":"25",
    "addr:postcode":"3136",
    "addr:street":"Oaktree Rd",
    "iso:country":"AU",
    "sg:address":"25 Oaktree Rd",
    "sg:city":"Croydon",
    "sg:classifiers":[
        {
            "category":"Professional",
            "subcategory":"Computer Services",
            "type":"Services"
        }
    ],
    "sg:phone":"+61 3 9725 6675",
    "sg:postcode":"3136",
    "sg:province":"VIC",
    "sg:tags":[
        "consultant",
        "system"
    ],
    "wof:name":"Programmed Teaching Services",
    "wof:placetype":"venue"
},
  "geometry": {"coordinates":[145.28294372600001,-37.7805671692],"type":"Point"}
}