{
  "type": "Feature",
  "properties": {
    "addr:full":"52 Clapham Rd Sefton NSW 2162",
    "addr:housenumber":"52",
    "addr:postcode":"2162",
    "addr:street":"Clapham Rd",
    "iso:country":"AU",
    "sg:address":"52 Clapham Rd",
    "sg:city":"Sefton",
    "sg:classifiers":[
        {
            "category":"Professional",
            "subcategory":"Art Services",
            "type":"Services"
        }
    ],
    "sg:phone":"+61 2 9738 5200",
    "sg:postcode":"2162",
    "sg:province":"NSW",
    "sg:tags":[
        "graphic",
        "designer"
    ],
    "wof:name":"Innovative Response",
    "wof:placetype":"venue"
},
  "geometry": {"coordinates":[151.01368713400001,-33.8837966919],"type":"Point"}
}