{
  "type": "Feature",
  "properties": {
    "addr:full":"78 Maple St Goondi Bend Innisfail QLD 4860",
    "addr:housenumber":"78",
    "addr:postcode":"4860",
    "addr:street":"Maple St Goondi Bend",
    "iso:country":"AU",
    "sg:address":"78 Maple St Goondi Bend",
    "sg:city":"Innisfail",
    "sg:classifiers":[
        {
            "category":"Education",
            "subcategory":"School",
            "type":"Public Place"
        }
    ],
    "sg:phone":"+61 7 4061 1067",
    "sg:postcode":"4860",
    "sg:province":"QLD",
    "sg:tags":[
        "state",
        "except",
        "nsw"
    ],
    "wof:name":"Goondi Primary School",
    "wof:placetype":"venue"
},
  "geometry": {"coordinates":[146.009674072,-17.5240802765],"type":"Point"}
}