{
  "type": "Feature",
  "properties": {
    "addr:full":"30 Wheeler St Belmont WA 6104",
    "addr:housenumber":"30",
    "addr:postcode":"6104",
    "addr:street":"Wheeler St",
    "iso:country":"AU",
    "sg:address":"30 Wheeler St",
    "sg:city":"Belmont",
    "sg:classifiers":[
        {
            "category":"Shopping",
            "subcategory":"Computers & Home Electronics",
            "type":"Retail Goods"
        }
    ],
    "sg:phone":"+61 8 9262 9091",
    "sg:postcode":"6104",
    "sg:province":"WA",
    "sg:tags":[
        "equipment",
        "supply"
    ],
    "wof:name":"Print Solutions Group",
    "wof:placetype":"venue"
},
  "geometry": {"coordinates":[115.92691803,-31.9477787018],"type":"Point"}
}