{
  "type": "Feature",
  "properties": {
    "addr:full":"250 Ballarat Rd Braybrook VIC 3019",
    "addr:housenumber":"250",
    "addr:postcode":"3019",
    "addr:street":"Ballarat Rd",
    "iso:country":"AU",
    "sg:address":"250 Ballarat Rd",
    "sg:city":"Braybrook",
    "sg:classifiers":[
        {
            "category":"Retail",
            "subcategory":"Auto Rental",
            "type":"Services"
        }
    ],
    "sg:phone":"+61 3 9318 4766",
    "sg:postcode":"3019",
    "sg:province":"VIC",
    "sg:tags":[
        "bus",
        "truck"
    ],
    "wof:name":"Sargent",
    "wof:placetype":"venue"
},
  "geometry": {"coordinates":[144.860565186,-37.7803916931],"type":"Point"}
}