{
  "type": "Feature",
  "properties": {
    "iso:country":"AU",
    "sg:address":"480 Corinella Rd",
    "sg:city":"Corinella",
    "sg:classifiers":[
        {
            "category":"Home & Garden",
            "subcategory":"Garden Supply",
            "type":"Retail Goods"
        }
    ],
    "sg:phone":"+61 3 5678 0803",
    "sg:postcode":"3984",
    "sg:province":"VIC",
    "sg:tags":[
        "equipment",
        "hydroponics"
    ],
    "wof:name":"Peter Doyle Consultancy",
    "wof:placetype":"venue"
},
  "geometry": {"coordinates":[145.44847106899999,-38.4242591858],"type":"Point"}
}