{
  "type": "Feature",
  "properties": {
    "addr:full":"Shp 26/ Mountain Gate Shopping Centre Ferntree Gully VIC 3156",
    "addr:housenumber":"26 /",
    "addr:postcode":"3156",
    "iso:country":"AU",
    "sg:address":"Shp 26/ Mountain Gate Shopping Centre",
    "sg:city":"Ferntree Gully",
    "sg:classifiers":[
        {
            "category":"Health Services",
            "subcategory":"Health Practitioner",
            "type":"Services"
        }
    ],
    "sg:phone":"+61 3 9753 6111",
    "sg:postcode":"3156",
    "sg:province":"VIC",
    "sg:tags":[
        "physiotherapist"
    ],
    "wof:name":"Ferntree Gully Spinal & Sport Physiotherapy Clinic",
    "wof:placetype":"venue"
},
  "geometry": {"coordinates":[145.276245117,-37.88722229],"type":"Point"}
}