{
  "type": "Feature",
  "properties": {
    "addr:full":"131 Kinghorn La Nyah VIC 3594",
    "addr:housenumber":"131",
    "addr:postcode":"3594",
    "addr:street":"Kinghorn La Nyah",
    "iso:country":"AU",
    "sg:address":"131 Kinghorn La",
    "sg:city":"Nyah",
    "sg:classifiers":[
        {
            "category":"Farming",
            "subcategory":"Farm & Veterinary Services",
            "type":"Manufacturing & Wholesale Goods"
        }
    ],
    "sg:phone":"+61 3 5030 2175",
    "sg:postcode":"3594",
    "sg:province":"VIC",
    "sg:tags":[
        "worm"
    ],
    "wof:name":"Nyah Native Worm Farm",
    "wof:placetype":"venue"
},
  "geometry": {"coordinates":[143.36224365199999,-35.1525802612],"type":"Point"}
}