{
  "type": "Feature",
  "properties": {
    "iso:country":"AU",
    "sg:address":"5/ 101 North St",
    "sg:city":"Toowoomba",
    "sg:classifiers":[
        {
            "category":"Military Area",
            "subcategory":"Air Force Base",
            "type":"Public Place"
        }
    ],
    "sg:phone":"+61 418 716 774",
    "sg:postcode":"4350",
    "sg:province":"QLD",
    "sg:tags":[
        "equipment",
        "climbing",
        "venue",
        "rock"
    ],
    "wof:name":"Phil Box",
    "wof:placetype":"venue"
},
  "geometry": {"coordinates":[151.92880199999999,-27.538321],"type":"Point"}
}