{
  "type": "Feature",
  "properties": {
    "iso:country":"AU",
    "sg:address":"Lot K Stebonheath Rd",
    "sg:city":"Munno Para Downs",
    "sg:classifiers":[
        {
            "category":"Retail",
            "subcategory":"Auto Rental",
            "type":"Services"
        }
    ],
    "sg:phone":"+61 8 8254 1111",
    "sg:postcode":"5115",
    "sg:province":"SA",
    "sg:tags":[
        "chauffeur",
        "car",
        "hire",
        "driven",
        "limousine"
    ],
    "wof:name":"Unique Hire Cars",
    "wof:placetype":"venue"
},
  "geometry": {"coordinates":[138.686676025,-34.6463012695],"type":"Point"}
}