{
  "type": "Feature",
  "properties": {
    "iso:country":"AU",
    "sg:address":"8 Victor Ave",
    "sg:city":"Glenella",
    "sg:classifiers":[
        {
            "category":"Building & Trades",
            "subcategory":"Construction",
            "type":"Services"
        }
    ],
    "sg:phone":"+61 7 4942 9077",
    "sg:postcode":"4740",
    "sg:province":"QLD",
    "sg:tags":[
        "contractor"
    ],
    "wof:name":"Craftsman Homes",
    "wof:placetype":"venue"
},
  "geometry": {"coordinates":[149.154449,-21.13018],"type":"Point"}
}