{
  "type": "Feature",
  "properties": {
    "addr:full":"50 McBean St Yeppoon QLD 4703",
    "addr:housenumber":"50",
    "addr:postcode":"4703",
    "addr:street":"Mcbean St",
    "iso:country":"AU",
    "sg:address":"50 McBean St",
    "sg:city":"Yeppoon",
    "sg:classifiers":[
        {
            "category":"Commercial Area",
            "type":"Public Place"
        }
    ],
    "sg:phone":"+61 7 4939 2220",
    "sg:postcode":"4703",
    "sg:province":"QLD",
    "sg:tags":[
        "heavy",
        "carrier"
    ],
    "wof:name":"Zielke's Transport",
    "wof:placetype":"venue"
},
  "geometry": {"coordinates":[150.733444214,-23.1396083832],"type":"Point"}
}