{
  "type": "Feature",
  "properties": {
    "addr:full":"Fosters Rd White Rock QLD 4868",
    "addr:postcode":"4868",
    "addr:street":"Fosters Rd",
    "iso:country":"AU",
    "sg:address":"Fosters Rd",
    "sg:city":"White Rock",
    "sg:classifiers":[
        {
            "category":"Farming",
            "subcategory":"Farm",
            "type":"Manufacturing & Wholesale Goods"
        }
    ],
    "sg:phone":"+61 7 4036 2287",
    "sg:postcode":"4868",
    "sg:province":"QLD",
    "sg:tags":[
        "farmer"
    ],
    "wof:name":"Pezzutti W G",
    "wof:placetype":"venue"
},
  "geometry": {"coordinates":[145.74192810100001,-16.987531662],"type":"Point"}
}