{
  "type": "Feature",
  "properties": {
    "addr:full":"461 Scarborough Beach Rd Osborne Park WA 6017",
    "addr:housenumber":"461",
    "addr:postcode":"6017",
    "addr:street":"Scarborough Beach Rd",
    "iso:country":"AU",
    "sg:address":"461 Scarborough Beach Rd",
    "sg:city":"Osborne Park",
    "sg:classifiers":[
        {
            "category":"Social Services",
            "subcategory":"Adult Care",
            "type":"Services"
        }
    ],
    "sg:phone":"+61 8 9492 8920",
    "sg:postcode":"6017",
    "sg:province":"WA",
    "sg:tags":[
        "aged"
    ],
    "sg:website":"http://www.comfortkeepers.com.au",
    "wof:name":"Comfort Keepers",
    "wof:placetype":"venue"
},
  "geometry": {"coordinates":[115.80834197999999,-31.9056968689],"type":"Point"}
}