{
  "type": "Feature",
  "properties": {
    "iso:country":"AU",
    "sg:address":"8/ 119 Horton St",
    "sg:city":"Port Macquarie",
    "sg:classifiers":[
        {
            "category":"Shopping",
            "subcategory":"Crafts & Fabrics",
            "type":"Retail Goods"
        }
    ],
    "sg:phone":"+61 2 6583 7820",
    "sg:postcode":"2444",
    "sg:province":"NSW",
    "sg:tags":[
        "wool",
        "knitting",
        "accessory"
    ],
    "wof:name":"Port Macquarie Wool World",
    "wof:placetype":"venue"
},
  "geometry": {"coordinates":[152.908264,-31.432211],"type":"Point"}
}