{
  "type": "Feature",
  "properties": {
    "addr:full":"21 Eastbank St Collaroy NSW 2097",
    "addr:housenumber":"21",
    "addr:postcode":"2097",
    "addr:street":"Eastbank St",
    "iso:country":"AU",
    "sg:address":"21 Eastbank St",
    "sg:city":"Collaroy",
    "sg:classifiers":[
        {
            "category":"Health Services",
            "subcategory":"Nursing And Care Facility",
            "type":"Services"
        }
    ],
    "sg:phone":"+61 2 9982 9211",
    "sg:postcode":"2097",
    "sg:province":"NSW",
    "sg:tags":[
        "home"
    ],
    "wof:name":"Elizabeth Jenkins Nursing Home",
    "wof:placetype":"venue"
},
  "geometry": {"coordinates":[151.301315308,-33.7335281372],"type":"Point"}
}