{
  "type": "Feature",
  "properties": {
    "addr:full":"Railway Station Dukes Hwy Tintinara SA 5266",
    "addr:postcode":"5266",
    "addr:street":"Dukes Hwy",
    "iso:country":"AU",
    "sg:address":"Railway Station Dukes Hwy",
    "sg:city":"Tintinara",
    "sg:classifiers":[
        {
            "category":"Communications",
            "subcategory":"News Services",
            "type":"Services"
        }
    ],
    "sg:phone":"+61 8 8757 2220",
    "sg:postcode":"5266",
    "sg:province":"SA",
    "sg:tags":[
        "information",
        "tourist",
        "attractions"
    ],
    "wof:name":"Heart of the Park-Information & Craft",
    "wof:placetype":"venue"
},
  "geometry": {"coordinates":[140.056015,-35.88382],"type":"Point"}
}