{
  "type": "Feature",
  "properties": {
    "addr:full":"Crn Station Sts & St Georges Rd Norlane VIC 3214",
    "addr:postcode":"3214",
    "addr:street":"Crn Station;St Georges Rd",
    "iso:country":"AU",
    "sg:address":"Crn Station Sts & St Georges Rd",
    "sg:city":"Norlane",
    "sg:classifiers":[
        {
            "category":"Building & Trades",
            "subcategory":"Construction",
            "type":"Services"
        }
    ],
    "sg:phone":"+61 3 5275 6666",
    "sg:postcode":"3214",
    "sg:province":"VIC",
    "sg:tags":[
        "scaffolding"
    ],
    "wof:name":"Bay Hire",
    "wof:placetype":"venue"
},
  "geometry": {"coordinates":[144.35798645,-38.0840873718],"type":"Point"}
}