{
  "type": "Feature",
  "properties": {
    "iso:country":"AU",
    "sg:address":"12 Station St",
    "sg:city":"Wentworthville",
    "sg:classifiers":[
        {
            "category":"Travel",
            "subcategory":"Travel Agent",
            "type":"Entertainment"
        }
    ],
    "sg:phone":"+61 2 9631 4333",
    "sg:postcode":"2145",
    "sg:province":"NSW",
    "sg:tags":[
        "consultant"
    ],
    "wof:name":"A & J Travel Centre",
    "wof:placetype":"venue"
},
  "geometry": {"coordinates":[150.97239685100001,-33.8076553345],"type":"Point"}
}