{
  "type": "Feature",
  "properties": {
    "addr:full":"3 Ninda St Rosny TAS 7018",
    "addr:housenumber":"3",
    "addr:postcode":"7018",
    "addr:street":"Ninda St",
    "iso:country":"AU",
    "sg:address":"3 Ninda St",
    "sg:city":"Rosny",
    "sg:classifiers":[
        {
            "category":"Museum",
            "subcategory":"Art Museum",
            "type":"Entertainment"
        }
    ],
    "sg:phone":"+61 1800 808 197",
    "sg:postcode":"7018",
    "sg:province":"TAS",
    "sg:tags":[
        "antique",
        "fine",
        "valuer"
    ],
    "wof:name":"Harold Ogilvie A.M.",
    "wof:placetype":"venue"
},
  "geometry": {"coordinates":[147.35377502399999,-42.871006012],"type":"Point"}
}