{
  "type": "Feature",
  "properties": {
    "addr:full":"94 Springs Rd Clayton South VIC 3169",
    "addr:housenumber":"94",
    "addr:postcode":"3169",
    "addr:street":"Springs Rd",
    "iso:country":"AU",
    "sg:address":"94 Springs Rd",
    "sg:city":"Clayton South",
    "sg:classifiers":[
        {
            "category":"Health Services",
            "subcategory":"Nursing And Care Facility",
            "type":"Services"
        }
    ],
    "sg:phone":"+61 3 9552 4100",
    "sg:postcode":"3169",
    "sg:province":"VIC",
    "sg:tags":[
        "home"
    ],
    "wof:name":"Fronditha Care Inc",
    "wof:placetype":"venue"
},
  "geometry": {"coordinates":[145.10801696799999,-37.9362564087],"type":"Point"}
}