{
  "type": "Feature",
  "properties": {
    "addr:full":"Level 4, 313 Latrobe St Melbourne VIC 3000",
    "addr:housenumber":"313",
    "addr:postcode":"3000",
    "addr:street":"Latrobe St",
    "iso:country":"AU",
    "sg:address":"Level 4, 313 Latrobe St",
    "sg:city":"Melbourne",
    "sg:classifiers":[
        {
            "category":"Professional",
            "subcategory":"Accounting & Tax Preparation",
            "type":"Services"
        }
    ],
    "sg:phone":"+61 3 9642 8000",
    "sg:postcode":"3000",
    "sg:province":"VIC",
    "sg:tags":[
        "consultant",
        "taxation"
    ],
    "wof:name":"Anderson M V & Co",
    "wof:placetype":"venue"
},
  "geometry": {"coordinates":[144.96002197300001,-37.8108406067],"type":"Point"}
}