{
  "type": "Feature",
  "properties": {
    "addr:full":"Newell Hwy Gilgandra NSW 2827",
    "addr:postcode":"2827",
    "addr:street":"Newell Hwy",
    "iso:country":"AU",
    "sg:address":"Newell Hwy",
    "sg:city":"Gilgandra",
    "sg:classifiers":[
        {
            "category":"Autos & Motor Vehicles",
            "subcategory":"Fuel & Gas Station",
            "type":"Retail Goods"
        }
    ],
    "sg:phone":"+61 2 6847 2988",
    "sg:postcode":"2827",
    "sg:province":"NSW",
    "wof:name":"Shell Gilgandra Truck Port",
    "wof:placetype":"venue"
},
  "geometry": {"coordinates":[148.66531372099999,-31.7130661011],"type":"Point"}
}