{
  "type": "Feature",
  "properties": {
    "addr:full":"72 Stephensons Rd Mt Waverley VIC 3149",
    "addr:housenumber":"72",
    "addr:postcode":"3149",
    "addr:street":"Stephensons Rd",
    "iso:country":"AU",
    "sg:address":"72 Stephensons Rd",
    "sg:city":"Mt Waverley",
    "sg:classifiers":[
        {
            "category":"Health Services",
            "subcategory":"Health Practitioner",
            "type":"Services"
        }
    ],
    "sg:phone":"+61 3 9803 7755",
    "sg:postcode":"3149",
    "sg:province":"VIC",
    "sg:tags":[
        "physiotherapist"
    ],
    "wof:name":"Vincent Susan",
    "wof:placetype":"venue"
},
  "geometry": {"coordinates":[145.13128662099999,-37.8643417358],"type":"Point"}
}