{
  "type": "Feature",
  "properties": {
    "iso:country":"AU",
    "sg:address":"125 Orchardleigh St",
    "sg:city":"Old Guildford",
    "sg:classifiers":[
        {
            "category":"Autos & Motor Vehicles",
            "subcategory":"Fuel & Gas Station",
            "type":"Retail Goods"
        }
    ],
    "sg:phone":"+61 2 9632 7200",
    "sg:postcode":"2161",
    "sg:province":"NSW",
    "wof:name":"Astron Service Station",
    "wof:placetype":"venue"
},
  "geometry": {"coordinates":[150.98521423299999,-33.866558075],"type":"Point"}
}