{
  "type": "Feature",
  "properties": {
    "addr:full":"Morrell St Mooroopna VIC 3629",
    "addr:postcode":"3629",
    "addr:street":"Morrell St",
    "iso:country":"AU",
    "sg:address":"Morrell St",
    "sg:city":"Mooroopna",
    "sg:classifiers":[
        {
            "category":"Social Services",
            "subcategory":"Child Care",
            "type":"Services"
        }
    ],
    "sg:phone":"+61 3 5825 2371",
    "sg:postcode":"3629",
    "sg:province":"VIC",
    "sg:tags":[
        "support",
        "health"
    ],
    "wof:name":"Maternal & Child Health Centres",
    "wof:placetype":"venue"
},
  "geometry": {"coordinates":[145.35922241200001,-36.3936347961],"type":"Point"}
}