{
  "type": "Feature",
  "properties": {
    "addr:full":"92b Longueville Rd Lane Cove NSW 2066",
    "addr:housenumber":"92b",
    "addr:postcode":"2066",
    "addr:street":"Longueville Rd",
    "iso:country":"AU",
    "sg:address":"92b Longueville Rd",
    "sg:city":"Lane Cove",
    "sg:classifiers":[
        {
            "category":"Restaurant",
            "type":"Food & Drink"
        }
    ],
    "sg:phone":"+61 2 9427 7882",
    "sg:postcode":"2066",
    "sg:province":"NSW",
    "wof:name":"Darling Thai",
    "wof:placetype":"venue"
},
  "geometry": {"coordinates":[151.17007446299999,-33.8141021729],"type":"Point"}
}