{
  "type": "Feature",
  "properties": {
    "iso:country":"AU",
    "sg:address":"Waroo Rd",
    "sg:city":"Yass",
    "sg:classifiers":[
        {
            "category":"Building & Trades",
            "subcategory":"Construction",
            "type":"Services"
        }
    ],
    "sg:phone":"+61 2 6226 2422",
    "sg:postcode":"2582",
    "sg:province":"NSW",
    "sg:tags":[
        "welding"
    ],
    "wof:name":"B & V Engineering",
    "wof:placetype":"venue"
},
  "geometry": {"coordinates":[148.916870117,-34.8486747742],"type":"Point"}
}