{
  "type": "Feature",
  "properties": {
    "iso:country":"AU",
    "sg:address":"Shop 4, 28 Thurecht Pde",
    "sg:city":"Scarborough",
    "sg:classifiers":[
        {
            "category":"Recreation",
            "subcategory":"Fishing",
            "type":"Entertainment"
        }
    ],
    "sg:phone":"+61 7 3880 3312",
    "sg:postcode":"4020",
    "sg:province":"QLD",
    "sg:tags":[
        "trip"
    ],
    "wof:name":"Reel Easy Charters",
    "wof:placetype":"venue"
},
  "geometry": {"coordinates":[153.10495,-27.195406],"type":"Point"}
}