{
  "type": "Feature",
  "properties": {
    "iso:country":"AU",
    "sg:address":"712 - 714 Burwood Hwy",
    "sg:city":"Knox",
    "sg:classifiers":[
        {
            "category":"Home & Garden",
            "subcategory":"Carpets & Floor Coverings",
            "type":"Retail Goods"
        }
    ],
    "sg:phone":"+61 3 9758 9600",
    "sg:postcode":"3180",
    "sg:province":"VIC",
    "sg:tags":[
        "mattress"
    ],
    "wof:name":"Forty Winks",
    "wof:placetype":"venue"
},
  "geometry": {"coordinates":[145.26405334500001,-37.8785095215],"type":"Point"}
}