{
  "type": "Feature",
  "properties": {
    "iso:country":"AU",
    "sg:address":"Lot 102 / 3 Ridgeland St",
    "sg:city":"Woongarrah",
    "sg:classifiers":[
        {
            "category":"Building & Trades",
            "subcategory":"Construction",
            "type":"Services"
        }
    ],
    "sg:phone":"+61 2 4393 3300",
    "sg:postcode":"2259",
    "sg:province":"NSW",
    "sg:tags":[
        "contractor"
    ],
    "wof:name":"Westminster Homes Pty Ltd",
    "wof:placetype":"venue"
},
  "geometry": {"coordinates":[151.47265625,-33.2436637878],"type":"Point"}
}