{
  "type": "Feature",
  "properties": {
    "addr:full":"123 Burwood Rd Burwood NSW 2134",
    "addr:housenumber":"123",
    "addr:postcode":"2134",
    "addr:street":"Burwood Rd",
    "iso:country":"AU",
    "sg:address":"123 Burwood Rd",
    "sg:city":"Burwood",
    "sg:classifiers":[
        {
            "category":"Food & Beverages",
            "subcategory":"Supermarket",
            "type":"Retail Goods"
        }
    ],
    "sg:phone":"+61 2 9745 5788",
    "sg:postcode":"2134",
    "sg:province":"NSW",
    "sg:tags":[
        "grocery",
        "store"
    ],
    "wof:name":"Top Mart Supermarket",
    "wof:placetype":"venue"
},
  "geometry": {"coordinates":[151.10372924800001,-33.8763923645],"type":"Point"}
}