{
  "type": "Feature",
  "properties": {
    "addr:full":"33 Shop 3 Progress Rd Burpengary QLD 4505",
    "addr:housenumber":"33 shop 3",
    "addr:postcode":"4505",
    "addr:street":"Progress Rd",
    "iso:country":"AU",
    "sg:address":"33 Shop 3 Progress Rd",
    "sg:city":"Burpengary",
    "sg:classifiers":[
        {
            "category":"Health Services",
            "subcategory":"Health Practitioner",
            "type":"Services"
        }
    ],
    "sg:phone":"+61 7 3888 0409",
    "sg:postcode":"4505",
    "sg:province":"QLD",
    "sg:tags":[
        "physiotherapist"
    ],
    "wof:name":"Cunningham Michael",
    "wof:placetype":"venue"
},
  "geometry": {"coordinates":[152.969436645,-27.1624736786],"type":"Point"}
}