{
  "type": "Feature",
  "properties": {
    "addr:full":"PO Box 437 Busselton WA 6280",
    "addr:postcode":"6280",
    "iso:country":"AU",
    "sg:address":"PO Box 437",
    "sg:city":"Busselton",
    "sg:classifiers":[
        {
            "category":"Farming",
            "subcategory":"Farm",
            "type":"Manufacturing & Wholesale Goods"
        }
    ],
    "sg:phone":"+61 8 9753 2173",
    "sg:postcode":"6280",
    "sg:province":"WA",
    "sg:tags":[
        "farmer"
    ],
    "wof:name":"Forrest K M & D E",
    "wof:placetype":"venue"
},
  "geometry": {"coordinates":[115.344818115,-33.652141571],"type":"Point"}
}