{
  "type": "Feature",
  "properties": {
    "addr:full":"23 Elliott St Hawthorne QLD 4171",
    "addr:housenumber":"23",
    "addr:postcode":"4171",
    "addr:street":"Elliott St",
    "iso:country":"AU",
    "sg:address":"23 Elliott St",
    "sg:city":"Hawthorne",
    "sg:classifiers":[
        {
            "category":"Education",
            "subcategory":"Special Training",
            "type":"Public Place"
        }
    ],
    "sg:phone":"+61 7 3899 4311",
    "sg:postcode":"4171",
    "sg:province":"QLD",
    "sg:tags":[
        "development"
    ],
    "wof:name":"Construction & Property Services Industry Skills Council",
    "wof:placetype":"venue"
},
  "geometry": {"coordinates":[153.059494019,-27.4598255157],"type":"Point"}
}