{
  "type": "Feature",
  "properties": {
    "iso:country":"AU",
    "sg:address":"PO Box 778",
    "sg:city":"Berwick",
    "sg:classifiers":[
        {
            "category":"Building & Trades",
            "subcategory":"Construction",
            "type":"Services"
        }
    ],
    "sg:phone":"+61 3 8786 5454",
    "sg:postcode":"3806",
    "sg:province":"VIC",
    "sg:tags":[
        "plasterboard",
        "plasterer",
        "fixer"
    ],
    "wof:name":"Glenndale Plaster",
    "wof:placetype":"venue"
},
  "geometry": {"coordinates":[145.34732055699999,-38.0306282043],"type":"Point"}
}