{
  "type": "Feature",
  "properties": {
    "addr:full":"Shop G1 Acland Court Shopng Cn Acland St St Kilda VIC 3182",
    "addr:postcode":"3182",
    "addr:street":"Acland;Shopng;Acland St",
    "iso:country":"AU",
    "sg:address":"Shop G1 Acland Court Shopng Cn Acland St",
    "sg:city":"St Kilda",
    "sg:classifiers":[
        {
            "category":"Cafe",
            "type":"Food & Drink"
        }
    ],
    "sg:phone":"+61 3 8598 9031",
    "sg:postcode":"3182",
    "sg:province":"VIC",
    "wof:name":"Gloria Jean's Coffees",
    "wof:placetype":"venue"
},
  "geometry": {"coordinates":[144.973342895,-37.8617668152],"type":"Point"}
}