{
  "type": "Feature",
  "properties": {
    "iso:country":"AU",
    "sg:address":"16 Vale St",
    "sg:city":"Nagambie",
    "sg:classifiers":[
        {
            "category":"Education",
            "subcategory":"Kindergarten",
            "type":"Public Place"
        }
    ],
    "sg:phone":"+61 3 5794 2410",
    "sg:postcode":"3608",
    "sg:province":"VIC",
    "sg:tags":[
        "pre-schools"
    ],
    "wof:name":"Nagambie Pre-School Centre",
    "wof:placetype":"venue"
},
  "geometry": {"coordinates":[145.15733337399999,-36.7822570801],"type":"Point"}
}