{
  "type": "Feature",
  "properties": {
    "iso:country":"AU",
    "sg:address":"110 Rozelle St",
    "sg:city":"Melrose Park",
    "sg:classifiers":[
        {
            "category":"Building & Trades",
            "subcategory":"Plumbing",
            "type":"Services"
        }
    ],
    "sg:phone":"+61 8 8374 0774",
    "sg:postcode":"5039",
    "sg:province":"SA",
    "sg:tags":[
        "plumber",
        "gasfitters"
    ],
    "wof:name":"Elite Plumbing Services Pty Ltd",
    "wof:placetype":"venue"
},
  "geometry": {"coordinates":[138.57583618199999,-34.9839096069],"type":"Point"}
}