{
  "type": "Feature",
  "properties": {
    "iso:country":"AU",
    "sg:address":"91 Mooney St",
    "sg:city":"Gulliver",
    "sg:classifiers":[
        {
            "category":"Building & Trades",
            "subcategory":"Construction",
            "type":"Services"
        }
    ],
    "sg:phone":"+61 7 4779 3187",
    "sg:postcode":"4812",
    "sg:province":"QLD",
    "sg:tags":[
        "contractor"
    ],
    "wof:name":"Doyle Built Homes",
    "wof:placetype":"venue"
},
  "geometry": {"coordinates":[146.771393,-19.283154],"type":"Point"}
}