{
  "type": "Feature",
  "properties": {
    "iso:country":"AU",
    "sg:address":"U 3/ 4 Day Rd",
    "sg:city":"East Rockingham",
    "sg:classifiers":[
        {
            "category":"Building & Trades",
            "subcategory":"Construction",
            "type":"Services"
        }
    ],
    "sg:phone":"+61 8 9529 2144",
    "sg:postcode":"6168",
    "sg:province":"WA",
    "sg:tags":[
        "fencing",
        "contractor"
    ],
    "wof:name":"Crazy Pedros Rockingham",
    "wof:placetype":"venue"
},
  "geometry": {"coordinates":[115.775963,-32.274212],"type":"Point"}
}