{
  "type": "Feature",
  "properties": {
    "addr:full":"26 Neich Rd Glenorie NSW 2157",
    "addr:housenumber":"26",
    "addr:postcode":"2157",
    "addr:street":"Neich Rd",
    "iso:country":"AU",
    "sg:address":"26 Neich Rd",
    "sg:city":"Glenorie",
    "sg:classifiers":[
        {
            "category":"Banks & Credit Unions",
            "subcategory":"Bureau De Change",
            "type":"Services"
        }
    ],
    "sg:phone":"+61 2 9652 1990",
    "sg:postcode":"2157",
    "sg:province":"NSW",
    "sg:tags":[
        "repairs",
        "part",
        "appliance",
        "electrical"
    ],
    "wof:name":"Statewide Appliance Repairs & Electrical",
    "wof:placetype":"venue"
},
  "geometry": {"coordinates":[150.970214844,-33.5910987854],"type":"Point"}
}