{
  "type": "Feature",
  "properties": {
    "addr:full":"3 Bennison St Croydon VIC 3136",
    "addr:housenumber":"3",
    "addr:postcode":"3136",
    "addr:street":"Bennison St",
    "iso:country":"AU",
    "sg:address":"3 Bennison St",
    "sg:city":"Croydon",
    "sg:classifiers":[
        {
            "category":"Building & Trades",
            "subcategory":"Construction",
            "type":"Services"
        }
    ],
    "sg:phone":"+61 417 561 906",
    "sg:postcode":"3136",
    "sg:province":"VIC",
    "sg:tags":[
        "roof"
    ],
    "wof:name":"Quest Roofing Pty Ltd",
    "wof:placetype":"venue"
},
  "geometry": {"coordinates":[145.29377746599999,-37.8004417419],"type":"Point"}
}