{
  "type": "Feature",
  "properties": {
    "addr:full":"3 Maranoa Rd Kingston TAS 7050",
    "addr:housenumber":"3",
    "addr:postcode":"7050",
    "addr:street":"Maranoa Rd",
    "iso:country":"AU",
    "sg:address":"3 Maranoa Rd",
    "sg:city":"Kingston",
    "sg:classifiers":[
        {
            "category":"Building & Trades",
            "subcategory":"Construction",
            "type":"Services"
        }
    ],
    "sg:phone":"+61 3 6229 3809",
    "sg:postcode":"7050",
    "sg:province":"TAS",
    "sg:tags":[
        "contractor"
    ],
    "wof:name":"NSV Builders",
    "wof:placetype":"venue"
},
  "geometry": {"coordinates":[147.30639600000001,-42.976597],"type":"Point"}
}