{
  "type": "Feature",
  "properties": {
    "iso:country":"AU",
    "sg:address":"21 Gretel Gr",
    "sg:city":"Melton",
    "sg:classifiers":[
        {
            "category":"Utilities",
            "subcategory":"Electric",
            "type":"Services"
        }
    ],
    "sg:phone":"+61 437 366 322",
    "sg:postcode":"3337",
    "sg:province":"VIC",
    "sg:tags":[
        "electrical",
        "contractor"
    ],
    "wof:name":"Electricool",
    "wof:placetype":"venue"
},
  "geometry": {"coordinates":[144.57991000000001,-37.690907],"type":"Point"}
}