{
  "type": "Feature",
  "properties": {
    "addr:full":"Machinery Drv Tweed Heads NSW 2485",
    "addr:postcode":"2485",
    "addr:street":"Machinery Drv",
    "iso:country":"AU",
    "sg:address":"Machinery Drv",
    "sg:city":"Tweed Heads",
    "sg:classifiers":[
        {
            "category":"Home & Garden",
            "subcategory":"Building Materials",
            "type":"Retail Goods"
        }
    ],
    "sg:phone":"+61 7 5524 4671",
    "sg:postcode":"2485",
    "sg:province":"NSW",
    "sg:tags":[
        "pre-mixed",
        "concrete"
    ],
    "wof:name":"Readymix",
    "wof:placetype":"venue"
},
  "geometry": {"coordinates":[153.54057312,-28.2025260925],"type":"Point"}
}