{
  "type": "Feature",
  "properties": {
    "addr:full":"4 Powdrill Rd Lurnea NSW 2170",
    "addr:housenumber":"4",
    "addr:postcode":"2170",
    "addr:street":"Powdrill Rd",
    "iso:country":"AU",
    "sg:address":"4 Powdrill Rd",
    "sg:city":"Lurnea",
    "sg:classifiers":[
        {
            "category":"Professional",
            "type":"Services"
        }
    ],
    "sg:phone":"+61 2 9608 2888",
    "sg:postcode":"2170",
    "sg:province":"NSW",
    "sg:tags":[
        "shop",
        "fitting"
    ],
    "wof:name":"Cottle J.R. Pty Ltd",
    "wof:placetype":"venue"
},
  "geometry": {"coordinates":[150.88923645,-33.9344863892],"type":"Point"}
}