{
  "type": "Feature",
  "properties": {
    "addr:full":"105 Tooradin - Station Rd Tooradin VIC 3980",
    "addr:housenumber":"105",
    "addr:postcode":"3980",
    "addr:street":"Tooradin Station Rd",
    "iso:country":"AU",
    "sg:address":"105 Tooradin - Station Rd",
    "sg:city":"Tooradin",
    "sg:classifiers":[
        {
            "category":"Building & Trades",
            "subcategory":"Plumbing",
            "type":"Services"
        }
    ],
    "sg:phone":"+61 418 322 851",
    "sg:postcode":"3980",
    "sg:province":"VIC",
    "sg:tags":[
        "plumber",
        "gasfitters"
    ],
    "wof:name":"Hull J D",
    "wof:placetype":"venue"
},
  "geometry": {"coordinates":[145.378463745,-38.2124023438],"type":"Point"}
}