{
  "type": "Feature",
  "properties": {
    "addr:full":"Hume Hwy Warwick Farm NSW 2170",
    "addr:postcode":"2170",
    "addr:street":"Hume Hwy",
    "iso:country":"AU",
    "sg:address":"Hume Hwy",
    "sg:city":"Warwick Farm",
    "sg:classifiers":[
        {
            "category":"Retail",
            "subcategory":"Event Space",
            "type":"Services"
        }
    ],
    "sg:phone":"+61 2 9663 8500",
    "sg:postcode":"2170",
    "sg:province":"NSW",
    "sg:tags":[
        "venue",
        "reception",
        "wedding"
    ],
    "wof:name":"Australian Jockey Club",
    "wof:placetype":"venue"
},
  "geometry": {"coordinates":[150.93775939899999,-33.9115333557],"type":"Point"}
}