{
  "type": "Feature",
  "properties": {
    "addr:full":"49 Knowles Ave North Bondi NSW 2026",
    "addr:housenumber":"49",
    "addr:postcode":"2026",
    "addr:street":"Knowles Ave",
    "iso:country":"AU",
    "sg:address":"49 Knowles Ave",
    "sg:city":"North Bondi",
    "sg:classifiers":[
        {
            "category":"Health Services",
            "subcategory":"Health Practitioner",
            "type":"Services"
        }
    ],
    "sg:phone":"+61 2 9130 6866",
    "sg:postcode":"2026",
    "sg:province":"NSW",
    "sg:tags":[
        "dietitian"
    ],
    "wof:name":"Stern Rosie",
    "wof:placetype":"venue"
},
  "geometry": {"coordinates":[151.278808594,-33.8837661743],"type":"Point"}
}