{
  "type": "Feature",
  "properties": {
    "iso:country":"AU",
    "sg:address":"32 Gourla Rd",
    "sg:city":"Hillside",
    "sg:classifiers":[
        {
            "category":"Home & Garden",
            "subcategory":"Carpets & Floor Coverings",
            "type":"Retail Goods"
        }
    ],
    "sg:phone":"+61 403 017 884",
    "sg:postcode":"3037",
    "sg:province":"VIC",
    "sg:tags":[
        "tile",
        "wall"
    ],
    "wof:name":"Chirphin Tiling",
    "wof:placetype":"venue"
},
  "geometry": {"coordinates":[144.75900300000001,-37.695461],"type":"Point"}
}