{
  "type": "Feature",
  "properties": {
    "addr:full":"PO Box 1001 Maiden Gully VIC 3551",
    "addr:postcode":"3551",
    "iso:country":"AU",
    "sg:address":"PO Box 1001",
    "sg:city":"Maiden Gully",
    "sg:classifiers":[
        {
            "category":"Education",
            "subcategory":"Special Training",
            "type":"Public Place"
        }
    ],
    "sg:phone":"+61 3 5449 6100",
    "sg:postcode":"3551",
    "sg:province":"VIC",
    "sg:tags":[
        "development"
    ],
    "wof:name":"T & D Insight",
    "wof:placetype":"venue"
},
  "geometry": {"coordinates":[144.206756592,-36.7423210144],"type":"Point"}
}