{
  "type": "Feature",
  "properties": {
    "iso:country":"AU",
    "sg:address":"2B Thistle St",
    "sg:city":"Bendigo",
    "sg:classifiers":[
        {
            "category":"Retail",
            "subcategory":"Auto Repair",
            "type":"Services"
        }
    ],
    "sg:phone":"+61 3 5444 1975",
    "sg:postcode":"3550",
    "sg:province":"VIC",
    "sg:tags":[
        "engine",
        "reconditioning"
    ],
    "wof:name":"Motafit",
    "wof:placetype":"venue"
},
  "geometry": {"coordinates":[144.268707275,-36.771900177],"type":"Point"}
}