{
  "type": "Feature",
  "properties": {
    "iso:country":"AU",
    "sg:address":"200 Bourke St",
    "sg:city":"Melbourne",
    "sg:classifiers":[
        {
            "category":"Fast Food",
            "type":"Food & Drink"
        }
    ],
    "sg:phone":"+61 3 9663 8638",
    "sg:postcode":"3000",
    "sg:province":"VIC",
    "sg:tags":[
        "away",
        "take"
    ],
    "wof:name":"Gold Star Noodle House",
    "wof:placetype":"venue"
},
  "geometry": {"coordinates":[144.96723938,-37.812915802],"type":"Point"}
}