{
  "type": "Feature",
  "properties": {
    "addr:full":"24 Lynbrea Ave Beecroft NSW 2119",
    "addr:housenumber":"24",
    "addr:postcode":"2119",
    "addr:street":"Lynbrea Ave",
    "iso:country":"AU",
    "sg:address":"24 Lynbrea Ave",
    "sg:city":"Beecroft",
    "sg:classifiers":[
        {
            "category":"Professional",
            "subcategory":"Computer Services",
            "type":"Services"
        }
    ],
    "sg:phone":"+61 2 9869 0778",
    "sg:postcode":"2119",
    "sg:province":"NSW",
    "sg:tags":[
        "consultant",
        "system"
    ],
    "wof:name":"Bitech Pty Ltd",
    "wof:placetype":"venue"
},
  "geometry": {"coordinates":[151.05770874000001,-33.758354187],"type":"Point"}
}