{
  "type": "Feature",
  "properties": {
    "addr:full":"49 Jacaranda Drv Mooloolaba QLD 4557",
    "addr:housenumber":"49",
    "addr:postcode":"4557",
    "addr:street":"Jacaranda Drv",
    "iso:country":"AU",
    "sg:address":"49 Jacaranda Drv",
    "sg:city":"Mooloolaba",
    "sg:classifiers":[
        {
            "category":"Professional",
            "subcategory":"Engineering",
            "type":"Services"
        }
    ],
    "sg:phone":"+61 7 5444 8722",
    "sg:postcode":"4557",
    "sg:province":"QLD",
    "sg:tags":[
        "consulting",
        "engineer"
    ],
    "wof:name":"Don White & Associates",
    "wof:placetype":"venue"
},
  "geometry": {"coordinates":[153.10264587399999,-26.6790752411],"type":"Point"}
}