{
  "type": "Feature",
  "properties": {
    "addr:full":"118 Williamson Rd Morayfield QLD 4506",
    "addr:housenumber":"118",
    "addr:postcode":"4506",
    "addr:street":"Williamson Rd",
    "iso:country":"AU",
    "sg:address":"118 Williamson Rd",
    "sg:city":"Morayfield",
    "sg:classifiers":[
        {
            "category":"Professional",
            "subcategory":"Accounting & Tax Preparation",
            "type":"Services"
        }
    ],
    "sg:phone":"+61 7 5497 9788",
    "sg:postcode":"4506",
    "sg:province":"QLD",
    "sg:tags":[
        "bookkeeping"
    ],
    "wof:name":"Abacus Bookkeeping Centre",
    "wof:placetype":"venue"
},
  "geometry": {"coordinates":[152.91702270499999,-27.1498203278],"type":"Point"}
}