{
  "type": "Feature",
  "properties": {
    "addr:full":"Shed 4 13 Brian Rd Lonsdale SA 5160",
    "addr:housenumber":"13",
    "addr:postcode":"5160",
    "addr:street":"Brian Rd",
    "iso:country":"AU",
    "sg:address":"Shed 4 13 Brian Rd",
    "sg:city":"Lonsdale",
    "sg:classifiers":[
        {
            "category":"Retail",
            "subcategory":"Repair Shop",
            "type":"Services"
        }
    ],
    "sg:phone":"+61 8 8387 6363",
    "sg:postcode":"5160",
    "sg:province":"SA",
    "sg:tags":[
        "upholsterer"
    ],
    "wof:name":"Down South Motor Trimmers",
    "wof:placetype":"venue"
},
  "geometry": {"coordinates":[138.50590515100001,-35.1009902954],"type":"Point"}
}