{
  "type": "Feature",
  "properties": {
    "iso:country":"AU",
    "sg:address":"15 Montague St",
    "sg:city":"Launceston",
    "sg:classifiers":[
        {
            "category":"Building & Trades",
            "subcategory":"Construction",
            "type":"Services"
        }
    ],
    "sg:phone":"+61 1800 808 379",
    "sg:postcode":"7250",
    "sg:province":"TAS",
    "sg:tags":[
        "insulation",
        "contractor"
    ],
    "wof:name":"Tasman Insulation Pty Ltd",
    "wof:placetype":"venue"
},
  "geometry": {"coordinates":[147.12872314399999,-41.4269332886],"type":"Point"}
}