{
  "type": "Feature",
  "properties": {
    "addr:full":"7 Jordan St Cobram NSW 3644",
    "addr:housenumber":"7",
    "addr:postcode":"3644",
    "addr:street":"Jordan St",
    "iso:country":"AU",
    "sg:address":"7 Jordan St",
    "sg:city":"Cobram",
    "sg:classifiers":[
        {
            "category":"Utilities",
            "subcategory":"Electric",
            "type":"Services"
        }
    ],
    "sg:phone":"+61 427 070 177",
    "sg:postcode":"3644",
    "sg:province":"NSW",
    "sg:tags":[
        "electrical",
        "contractor"
    ],
    "wof:name":"RMX Electrics",
    "wof:placetype":"venue"
},
  "geometry": {"coordinates":[145.64486694300001,-35.9190483093],"type":"Point"}
}