{
  "type": "Feature",
  "properties": {
    "iso:country":"AU",
    "sg:address":"20 Baroona Rd",
    "sg:city":"Church Point",
    "sg:classifiers":[
        {
            "category":"Retail",
            "subcategory":"Auto Rental",
            "type":"Services"
        }
    ],
    "sg:phone":"+61 1800 634 283",
    "sg:postcode":"2105",
    "sg:province":"NSW",
    "sg:tags":[
        "home",
        "hire",
        "motor",
        "campervans"
    ],
    "wof:name":"Campahomes",
    "wof:placetype":"venue"
},
  "geometry": {"coordinates":[151.285645,-33.64896],"type":"Point"}
}