{
  "type": "Feature",
  "properties": {
    "addr:full":"Level 2/ 168 Day St Sydney NSW 2000",
    "addr:housenumber":"/ 168",
    "addr:postcode":"2000",
    "addr:street":"Day St",
    "iso:country":"AU",
    "sg:address":"Level 2/ 168 Day St",
    "sg:city":"Sydney",
    "sg:classifiers":[
        {
            "category":"Professional",
            "subcategory":"Computer Services",
            "type":"Services"
        }
    ],
    "sg:phone":"+61 2 9264 0688",
    "sg:postcode":"2000",
    "sg:province":"NSW",
    "sg:tags":[
        "consultant",
        "system"
    ],
    "wof:name":"Bossa Pty Ltd",
    "wof:placetype":"venue"
},
  "geometry": {"coordinates":[151.20370483400001,-33.8749427795],"type":"Point"}
}