{
  "type": "Feature",
  "properties": {
    "addr:full":"26 Moonga Rd Toorak VIC 3142",
    "addr:housenumber":"26",
    "addr:postcode":"3142",
    "addr:street":"Moonga Rd",
    "iso:country":"AU",
    "sg:address":"26 Moonga Rd",
    "sg:city":"Toorak",
    "sg:classifiers":[
        {
            "category":"Professional",
            "subcategory":"Computer Services",
            "type":"Services"
        }
    ],
    "sg:phone":"+61 3 9863 7555",
    "sg:postcode":"3142",
    "sg:province":"VIC",
    "sg:tags":[
        "package",
        "software"
    ],
    "wof:name":"Evaluation Solutions P/L",
    "wof:placetype":"venue"
},
  "geometry": {"coordinates":[145.027435303,-37.8395729065],"type":"Point"}
}