{
  "type": "Feature",
  "properties": {
    "addr:full":"7 Essex St Dandenong North VIC 3175",
    "addr:housenumber":"7",
    "addr:postcode":"3175",
    "addr:street":"Essex St",
    "iso:country":"AU",
    "sg:address":"7 Essex St",
    "sg:city":"Dandenong North",
    "sg:classifiers":[
        {
            "category":"Building & Trades",
            "subcategory":"Cleaning & Sanitation",
            "type":"Services"
        }
    ],
    "sg:phone":"+61 3 9795 3065",
    "sg:postcode":"3175",
    "sg:province":"VIC",
    "sg:tags":[
        "sweeping",
        "machine"
    ],
    "wof:name":"Floor Care Australia",
    "wof:placetype":"venue"
},
  "geometry": {"coordinates":[145.22569274899999,-37.9523506165],"type":"Point"}
}