{
  "type": "Feature",
  "properties": {
    "addr:full":"Factory 22, 29 Kirkham Rd Keysborough VIC 3173",
    "addr:housenumber":"29",
    "addr:postcode":"3173",
    "addr:street":"Kirkham Rd",
    "iso:country":"AU",
    "sg:address":"Factory 22, 29 Kirkham Rd",
    "sg:city":"Keysborough",
    "sg:classifiers":[
        {
            "category":"Building & Trades",
            "subcategory":"Construction",
            "type":"Services"
        }
    ],
    "sg:phone":"+61 3 9701 8170",
    "sg:postcode":"3173",
    "sg:province":"VIC",
    "sg:tags":[
        "pool",
        "swimming"
    ],
    "wof:name":"Pacific Blue Pools Pebbling",
    "wof:placetype":"venue"
},
  "geometry": {"coordinates":[145.18510437,-37.9956130981],"type":"Point"}
}