{
  "type": "Feature",
  "properties": {
    "iso:country":"AU",
    "sg:address":"Shop 6/ 142 Beamish St",
    "sg:city":"Campsie",
    "sg:classifiers":[
        {
            "category":"Food & Beverages",
            "subcategory":"Specialty",
            "type":"Retail Goods"
        }
    ],
    "sg:phone":"+61 2 9787 6043",
    "sg:postcode":"2194",
    "sg:province":"NSW",
    "sg:tags":[
        "product",
        "health"
    ],
    "wof:name":"Golden Waratah",
    "wof:placetype":"venue"
},
  "geometry": {"coordinates":[151.103165,-33.908756],"type":"Point"}
}