{
  "type": "Feature",
  "properties": {
    "addr:full":"37 Frinton St Mt Gravatt QLD 4122",
    "addr:housenumber":"37",
    "addr:postcode":"4122",
    "addr:street":"Frinton St",
    "iso:country":"AU",
    "sg:address":"37 Frinton St",
    "sg:city":"Mt Gravatt",
    "sg:classifiers":[
        {
            "category":"Building & Trades",
            "subcategory":"Construction",
            "type":"Services"
        }
    ],
    "sg:phone":"+61 7 3283 3252",
    "sg:postcode":"4122",
    "sg:province":"QLD",
    "sg:tags":[
        "repair",
        "maintenance",
        "contractor"
    ],
    "wof:name":"Man With A Hammer",
    "wof:placetype":"venue"
},
  "geometry": {"coordinates":[153.100952148,-27.5528316498],"type":"Point"}
}