{
  "type": "Feature",
  "properties": {
    "addr:full":"Unit 11/ 160 Balcatta Rd Balcatta WA 6021",
    "addr:housenumber":"/ 160",
    "addr:postcode":"6021",
    "addr:street":"Balcatta Rd",
    "iso:country":"AU",
    "sg:address":"Unit 11/ 160 Balcatta Rd",
    "sg:city":"Balcatta",
    "sg:classifiers":[
        {
            "category":"Manufacturing",
            "subcategory":"Paper Products",
            "type":"Manufacturing & Wholesale Goods"
        }
    ],
    "sg:phone":"+61 8 9240 8000",
    "sg:postcode":"6021",
    "sg:province":"WA",
    "sg:tags":[
        "wholesaler",
        "toilet",
        "mfrs"
    ],
    "wof:name":"Bathroom Paper Supplies Australia",
    "wof:placetype":"venue"
},
  "geometry": {"coordinates":[115.816642761,-31.8623046875],"type":"Point"}
}