{
  "type": "Feature",
  "properties": {
    "addr:full":"46 Tully St St Helens TAS 7216",
    "addr:housenumber":"46",
    "addr:postcode":"7216",
    "addr:street":"Tully St",
    "iso:country":"AU",
    "sg:address":"46 Tully St",
    "sg:city":"St Helens",
    "sg:classifiers":[
        {
            "category":"Retail",
            "subcategory":"Funeral Services",
            "type":"Services"
        }
    ],
    "sg:phone":"+61 3 6376 1153",
    "sg:postcode":"7216",
    "sg:province":"TAS",
    "sg:tags":[
        "director"
    ],
    "wof:name":"Harris Funerals",
    "wof:placetype":"venue"
},
  "geometry": {"coordinates":[148.248322,-41.318188],"type":"Point"}
}