{
  "type": "Feature",
  "properties": {
    "addr:full":"349 Moray St South Melbourne VIC 3205",
    "addr:housenumber":"349",
    "addr:postcode":"3205",
    "addr:street":"Moray St",
    "iso:country":"AU",
    "sg:address":"349 Moray St",
    "sg:city":"South Melbourne",
    "sg:classifiers":[
        {
            "category":"Professional",
            "subcategory":"Art Services",
            "type":"Services"
        }
    ],
    "sg:phone":"+61 3 9690 2411",
    "sg:postcode":"3205",
    "sg:province":"VIC",
    "sg:tags":[
        "graphic",
        "designer"
    ],
    "wof:name":"Pang Design",
    "wof:placetype":"venue"
},
  "geometry": {"coordinates":[144.96545399999999,-37.837109],"type":"Point"}
}