{
  "type": "Feature",
  "properties": {
    "addr:full":"10 Bullock Drv Oakford WA 6121",
    "addr:housenumber":"10",
    "addr:postcode":"6121",
    "addr:street":"Bullock Drv",
    "iso:country":"AU",
    "sg:address":"10 Bullock Drv",
    "sg:city":"Oakford",
    "sg:classifiers":[
        {
            "category":"Professional",
            "type":"Services"
        }
    ],
    "sg:phone":"+61 8 9525 0109",
    "sg:postcode":"6121",
    "sg:province":"WA",
    "sg:tags":[
        "transport"
    ],
    "wof:name":"C.T.S. Low Loaders",
    "wof:placetype":"venue"
},
  "geometry": {"coordinates":[115.972816467,-32.2294120789],"type":"Point"}
}