{
  "type": "Feature",
  "properties": {
    "addr:full":"PO Box 111 Wentworthville NSW 2145",
    "addr:postcode":"2145",
    "iso:country":"AU",
    "sg:address":"PO Box 111",
    "sg:city":"Wentworthville",
    "sg:classifiers":[
        {
            "category":"Professional",
            "subcategory":"Management & Consulting",
            "type":"Services"
        }
    ],
    "sg:phone":"+61 2 9631 8200",
    "sg:postcode":"2145",
    "sg:province":"NSW",
    "sg:tags":[
        "consultant",
        "business"
    ],
    "wof:name":"Strategic Business Planning Services Pty Ltd",
    "wof:placetype":"venue"
},
  "geometry": {"coordinates":[150.97215270999999,-33.8030815125],"type":"Point"}
}