{
  "type": "Feature",
  "properties": {
    "addr:full":"Gnangara Rd Landsdale WA 6065",
    "addr:postcode":"6065",
    "addr:street":"Gnangara Rd",
    "iso:country":"AU",
    "sg:address":"Gnangara Rd",
    "sg:city":"Landsdale",
    "sg:classifiers":[
        {
            "category":"Utilities",
            "subcategory":"Fuel Oil & Lpg",
            "type":"Services"
        }
    ],
    "sg:phone":"+61 8 9247 1711",
    "sg:postcode":"6065",
    "sg:province":"WA",
    "sg:tags":[
        "merchant"
    ],
    "wof:name":"Gnangara Road Firewood Co",
    "wof:placetype":"venue"
},
  "geometry": {"coordinates":[115.857971191,-31.7969818115],"type":"Point"}
}