{
  "type": "Feature",
  "properties": {
    "iso:country":"AU",
    "sg:address":"874 Victoria Rd",
    "sg:city":"Ryde",
    "sg:classifiers":[
        {
            "category":"Professional",
            "subcategory":"Accounting & Tax Preparation",
            "type":"Services"
        }
    ],
    "sg:phone":"+61 2 9807 8585",
    "sg:postcode":"2112",
    "sg:province":"NSW",
    "sg:tags":[
        "consultant",
        "taxation"
    ],
    "wof:name":"P M Taxation Specialists",
    "wof:placetype":"venue"
},
  "geometry": {"coordinates":[151.09649658199999,-33.8138961792],"type":"Point"}
}