{
  "type": "Feature",
  "properties": {
    "addr:full":"U1/ 9 Cessna St Marcoola QLD 4564",
    "addr:housenumber":"9",
    "addr:postcode":"4564",
    "addr:street":"U1 /;Cessna St",
    "iso:country":"AU",
    "sg:address":"U1/ 9 Cessna St",
    "sg:city":"Marcoola",
    "sg:classifiers":[
        {
            "category":"Wholesale",
            "subcategory":"Non-durable Goods",
            "type":"Manufacturing & Wholesale Goods"
        }
    ],
    "sg:phone":"+61 7 5448 8106",
    "sg:postcode":"4564",
    "sg:province":"QLD",
    "sg:tags":[
        "wholesaler",
        "mfrs",
        "cosmetic"
    ],
    "wof:name":"Nana May's Magic Hands Pty Ltd",
    "wof:placetype":"venue"
},
  "geometry": {"coordinates":[153.08392334000001,-26.6074752808],"type":"Point"}
}