{
  "type": "Feature",
  "properties": {
    "iso:country":"AU",
    "sg:address":"220 Leicester St",
    "sg:city":"Carlton",
    "sg:classifiers":[
        {
            "category":"Education",
            "subcategory":"University",
            "type":"Public Place"
        }
    ],
    "sg:phone":"+61 3 9347 3428",
    "sg:postcode":"3053",
    "sg:province":"VIC",
    "sg:tags":[
        "college",
        "tertiary"
    ],
    "wof:name":"Graduate House",
    "wof:placetype":"venue"
},
  "geometry": {"coordinates":[144.961135864,-37.8002738953],"type":"Point"}
}