{
  "type": "Feature",
  "properties": {
    "addr:full":"36 Collins St Hobart TAS 7000",
    "addr:housenumber":"36",
    "addr:postcode":"7000",
    "addr:street":"Collins St",
    "iso:country":"AU",
    "sg:address":"36 Collins St",
    "sg:city":"Hobart",
    "sg:classifiers":[
        {
            "category":"Health Services",
            "subcategory":"Doctor",
            "type":"Services"
        }
    ],
    "sg:phone":"+61 3 6231 9225",
    "sg:postcode":"7000",
    "sg:province":"TAS",
    "sg:tags":[
        "medical",
        "practitioner"
    ],
    "wof:name":"Reid Steve",
    "wof:placetype":"venue"
},
  "geometry": {"coordinates":[147.33169555699999,-42.8801383972],"type":"Point"}
}