{
  "type": "Feature",
  "properties": {
    "iso:country":"AU",
    "sg:address":"42 Bangs St",
    "sg:city":"Prahran",
    "sg:classifiers":[
        {
            "category":"Retail",
            "subcategory":"Auto Repair",
            "type":"Services"
        }
    ],
    "sg:phone":"+61 3 9510 4159",
    "sg:postcode":"3181",
    "sg:province":"VIC",
    "sg:tags":[
        "repairer",
        "motor",
        "engineer"
    ],
    "wof:name":"Zeds Automotive",
    "wof:placetype":"venue"
},
  "geometry": {"coordinates":[144.99656677199999,-37.8505325317],"type":"Point"}
}