{
  "type": "Feature",
  "properties": {
    "addr:full":"Cnr Yaamba Rd & Main St North Rockhampton QLD 4701",
    "addr:postcode":"4701",
    "addr:street":"Cnr Yaamba Rd & Main St North",
    "iso:country":"AU",
    "sg:address":"Cnr Yaamba Rd & Main St",
    "sg:city":"North Rockhampton",
    "sg:classifiers":[
        {
            "category":"Travel",
            "subcategory":"Hotels & Motels",
            "type":"Entertainment"
        }
    ],
    "sg:phone":"+61 7 4928 2222",
    "sg:postcode":"4701",
    "sg:province":"QLD",
    "wof:name":"Ambassador Motel",
    "wof:placetype":"venue"
},
  "geometry": {"coordinates":[150.52438354500001,-23.3512802124],"type":"Point"}
}