{
  "type": "Feature",
  "properties": {
    "iso:country":"AU",
    "sg:address":"Cnr Erindale & Beach Rds",
    "sg:city":"Warwick",
    "sg:classifiers":[
        {
            "category":"Health Services",
            "subcategory":"Optometrist",
            "type":"Services"
        }
    ],
    "sg:phone":"+61 8 9246 5588",
    "sg:postcode":"6024",
    "sg:province":"WA",
    "wof:name":"OPSM Pty Ltd",
    "wof:placetype":"venue"
},
  "geometry": {"coordinates":[115.813056946,-31.8445892334],"type":"Point"}
}