{
  "type": "Feature",
  "properties": {
    "addr:full":"Level 1, 441 St Kilda Rd Melbourne VIC 3004",
    "addr:housenumber":"441",
    "addr:postcode":"3004",
    "addr:street":"St Kilda Rd",
    "iso:country":"AU",
    "sg:address":"Level 1, 441 St Kilda Rd",
    "sg:city":"Melbourne",
    "sg:classifiers":[
        {
            "category":"Professional",
            "subcategory":"Employment Agencies",
            "type":"Services"
        }
    ],
    "sg:phone":"+61 3 9868 4000",
    "sg:postcode":"3004",
    "sg:province":"VIC",
    "sg:tags":[
        "provider",
        "internet"
    ],
    "wof:name":"Netstar Australia Pty Ltd",
    "wof:placetype":"venue"
},
  "geometry": {"coordinates":[144.976119995,-37.8387718201],"type":"Point"}
}