{
  "type": "Feature",
  "properties": {
    "iso:country":"AU",
    "sg:address":"20 Wing Pde",
    "sg:city":"Newington",
    "sg:classifiers":[
        {
            "category":"Building & Trades",
            "subcategory":"Locksmith",
            "type":"Services"
        }
    ],
    "sg:phone":"+61 414 352 506",
    "sg:postcode":"2127",
    "sg:province":"NSW",
    "sg:tags":[
        "lock"
    ],
    "wof:name":"Locomotion Pty Ltd",
    "wof:placetype":"venue"
},
  "geometry": {"coordinates":[151.05464172399999,-33.8392715454],"type":"Point"}
}