{
  "type": "Feature",
  "properties": {
    "iso:country":"AU",
    "sg:address":"12 Pinari Crt",
    "sg:city":"Mountain Creek",
    "sg:classifiers":[
        {
            "category":"Banks & Credit Unions",
            "subcategory":"Bank",
            "type":"Services"
        }
    ],
    "sg:phone":"+61 7 5444 4940",
    "sg:postcode":"4557",
    "sg:province":"QLD",
    "sg:tags":[
        "broker",
        "mortgage"
    ],
    "wof:name":"Smartline Oakley Family",
    "wof:placetype":"venue"
},
  "geometry": {"coordinates":[153.08990478499999,-26.6998138428],"type":"Point"}
}