{
  "type": "Feature",
  "properties": {
    "iso:country":"AU",
    "sg:address":"Unit 7, 88 Magowar Rd",
    "sg:city":"Girraween",
    "sg:classifiers":[
        {
            "category":"Autos & Motor Vehicles",
            "subcategory":"Auto Supplies",
            "type":"Retail Goods"
        }
    ],
    "sg:phone":"+61 1800 133 396",
    "sg:postcode":"2145",
    "sg:province":"NSW",
    "sg:tags":[
        "equipment",
        "part",
        "truck"
    ],
    "sg:website":"http://www.vernonandvazey.com.au",
    "wof:name":"Vernon & Vazey truck parts PL",
    "wof:placetype":"venue"
},
  "geometry": {"coordinates":[150.944747925,-33.8019485474],"type":"Point"}
}