{
  "type": "Feature",
  "properties": {
    "iso:country":"AU",
    "sg:address":"326 Balwyn Rd",
    "sg:city":"Balwyn North",
    "sg:classifiers":[
        {
            "category":"Utilities",
            "subcategory":"Natural Gas",
            "type":"Services"
        }
    ],
    "sg:phone":"+61 412 378 792",
    "sg:postcode":"3104",
    "sg:province":"VIC",
    "sg:tags":[
        "solid",
        "plasterer"
    ],
    "wof:name":"Mosaico Constructions",
    "wof:placetype":"venue"
},
  "geometry": {"coordinates":[145.085494995,-37.7921485901],"type":"Point"}
}