{
  "type": "Feature",
  "properties": {
    "iso:country":"AU",
    "sg:address":"9 Binalong Ave",
    "sg:city":"Georges Hall",
    "sg:classifiers":[
        {
            "category":"Education",
            "subcategory":"Special Training",
            "type":"Public Place"
        }
    ],
    "sg:phone":"+61 2 9727 6775",
    "sg:postcode":"2198",
    "sg:province":"NSW",
    "sg:tags":[
        "school",
        "art"
    ],
    "wof:name":"John A Bradley",
    "wof:placetype":"venue"
},
  "geometry": {"coordinates":[150.990494,-33.903461],"type":"Point"}
}