{
  "type": "Feature",
  "properties": {
    "addr:full":"11 Dansu Crt Hallam VIC 3803",
    "addr:housenumber":"11",
    "addr:postcode":"3803",
    "addr:street":"Dansu Crt",
    "iso:country":"AU",
    "sg:address":"11 Dansu Crt",
    "sg:city":"Hallam",
    "sg:classifiers":[
        {
            "category":"Manufacturing",
            "subcategory":"Motor Vehicles & Parts",
            "type":"Manufacturing & Wholesale Goods"
        }
    ],
    "sg:phone":"+61 3 9796 4044",
    "sg:postcode":"3803",
    "sg:province":"VIC",
    "sg:tags":[
        "replacement"
    ],
    "wof:name":"Dayco Pacific Pty Ltd",
    "wof:placetype":"venue"
},
  "geometry": {"coordinates":[145.25390625,-38.0071182251],"type":"Point"}
}