{
  "type": "Feature",
  "properties": {
    "addr:full":"Unit 9/ 14 - 17 Hogan Crt Pakenham VIC 3810",
    "addr:housenumber":"17",
    "addr:postcode":"3810",
    "addr:street":"Hogan Crt",
    "iso:country":"AU",
    "sg:address":"Unit 9/ 14 - 17 Hogan Crt",
    "sg:city":"Pakenham",
    "sg:classifiers":[
        {
            "category":"Transit Center",
            "subcategory":"Freight",
            "type":"Transportation"
        }
    ],
    "sg:phone":"+61 3 5940 0444",
    "sg:postcode":"3810",
    "sg:province":"VIC",
    "sg:tags":[
        "forklift",
        "truck"
    ],
    "wof:name":"Pakenham Forklift Services",
    "wof:placetype":"venue"
},
  "geometry": {"coordinates":[145.49745200000001,-38.084824],"type":"Point"}
}