{
  "type": "Feature",
  "properties": {
    "addr:full":"Shed 2/ 263 Anderson Drv Beresfield NSW 2322",
    "addr:housenumber":"2 / 263",
    "addr:postcode":"2322",
    "addr:street":"Anderson Drv",
    "iso:country":"AU",
    "sg:address":"Shed 2/ 263 Anderson Drv",
    "sg:city":"Beresfield",
    "sg:classifiers":[
        {
            "category":"Professional",
            "type":"Services"
        }
    ],
    "sg:phone":"+61 2 4966 0500",
    "sg:postcode":"2322",
    "sg:province":"NSW",
    "sg:tags":[
        "spray",
        "painting"
    ],
    "wof:name":"N J Smash",
    "wof:placetype":"venue"
},
  "geometry": {"coordinates":[151.64457702600001,-32.7990036011],"type":"Point"}
}