{
  "type": "Feature",
  "properties": {
    "addr:full":"Cnr Gold Coast Springbrook & Boomerang Rds Mudgeeraba QLD 4213",
    "addr:postcode":"4213",
    "iso:country":"AU",
    "sg:address":"Cnr Gold Coast Springbrook & Boomerang Rds",
    "sg:city":"Mudgeeraba",
    "sg:classifiers":[
        {
            "category":"Retail",
            "subcategory":"Event Space",
            "type":"Services"
        }
    ],
    "sg:phone":"+61 7 5530 4151",
    "sg:postcode":"4213",
    "sg:province":"QLD",
    "sg:tags":[
        "venue",
        "reception",
        "wedding"
    ],
    "wof:name":"Ecostudio Fellini",
    "wof:placetype":"venue"
},
  "geometry": {"coordinates":[153.36294555699999,-28.0808849335],"type":"Point"}
}