{
  "type": "Feature",
  "properties": {
    "addr:full":"Shop 1/ 171 Main South Rd Morphett Vale SA 5162",
    "addr:housenumber":"shop 1 / 171",
    "addr:postcode":"5162",
    "addr:street":"Main South Rd",
    "iso:country":"AU",
    "sg:address":"Shop 1/ 171 Main South Rd",
    "sg:city":"Morphett Vale",
    "sg:classifiers":[
        {
            "category":"Real Estate",
            "subcategory":"Real Estate Agent",
            "type":"Services"
        }
    ],
    "sg:phone":"+61 8 8186 0657",
    "sg:postcode":"5162",
    "sg:province":"SA",
    "wof:name":"Hooker L.J. Morphett Vale",
    "wof:placetype":"venue"
},
  "geometry": {"coordinates":[138.522903442,-35.1201248169],"type":"Point"}
}