{
  "type": "Feature",
  "properties": {
    "addr:full":"Suite 104, Level 5, 24 Albert Rd Melbourne VIC 3000",
    "addr:housenumber":"24",
    "addr:postcode":"3000",
    "addr:street":"104;Albert Rd",
    "iso:country":"AU",
    "sg:address":"Suite 104, Level 5, 24 Albert Rd",
    "sg:city":"Melbourne",
    "sg:classifiers":[
        {
            "category":"Banks & Credit Unions",
            "subcategory":"Investment Brokerage",
            "type":"Services"
        }
    ],
    "sg:phone":"+61 3 8695 4740",
    "sg:postcode":"3000",
    "sg:province":"VIC",
    "sg:tags":[
        "debt",
        "collection"
    ],
    "wof:name":"Kemps Collections",
    "wof:placetype":"venue"
},
  "geometry": {"coordinates":[144.971557617,-37.8332595825],"type":"Point"}
}