{
  "type": "Feature",
  "properties": {
    "addr:full":"44 Townsend Rd Whittington VIC 3219",
    "addr:housenumber":"44",
    "addr:postcode":"3219",
    "addr:street":"Townsend Rd",
    "iso:country":"AU",
    "sg:address":"44 Townsend Rd",
    "sg:city":"Whittington",
    "sg:classifiers":[
        {
            "category":"Professional",
            "subcategory":"Computer Services",
            "type":"Services"
        }
    ],
    "sg:phone":"+61 400 311 386",
    "sg:postcode":"3219",
    "sg:province":"VIC",
    "sg:tags":[
        "repairs",
        "upgrade",
        "equipment"
    ],
    "wof:name":"Nathan Lewis",
    "wof:placetype":"venue"
},
  "geometry": {"coordinates":[144.387176514,-38.1809425354],"type":"Point"}
}