{
  "type": "Feature",
  "properties": {
    "addr:full":"6 Cornell Pl Hampton Park VIC 3976",
    "addr:housenumber":"6",
    "addr:postcode":"3976",
    "addr:street":"Cornell Pl Hampton",
    "iso:country":"AU",
    "sg:address":"6 Cornell Pl",
    "sg:city":"Hampton Park",
    "sg:classifiers":[
        {
            "category":"Professional",
            "type":"Services"
        }
    ],
    "sg:phone":"+61 3 9799 7219",
    "sg:postcode":"3976",
    "sg:province":"VIC",
    "sg:tags":[
        "transport"
    ],
    "wof:name":"IFT Removals",
    "wof:placetype":"venue"
},
  "geometry": {"coordinates":[145.28251648,-38.0408935547],"type":"Point"}
}