{
  "type": "Feature",
  "properties": {
    "iso:country":"AU",
    "sg:address":"Westfield Shopping Centre, Cnr Campbell & Northumb",
    "sg:city":"Liverpool",
    "sg:classifiers":[
        {
            "category":"Food & Beverages",
            "subcategory":"Liquor & Beverages",
            "type":"Retail Goods"
        }
    ],
    "sg:phone":"+61 2 9602 4488",
    "sg:postcode":"2170",
    "sg:province":"NSW",
    "sg:tags":[
        "store"
    ],
    "wof:name":"Woolworths Liquor",
    "wof:placetype":"venue"
},
  "geometry": {"coordinates":[150.922073364,-33.9245681763],"type":"Point"}
}