{
  "type": "Feature",
  "properties": {
    "addr:full":"12c Farley St Derwent Park TAS 7009",
    "addr:housenumber":"12c",
    "addr:postcode":"7009",
    "addr:street":"Farley St",
    "iso:country":"AU",
    "sg:address":"12c Farley St",
    "sg:city":"Derwent Park",
    "sg:classifiers":[
        {
            "category":"Commercial Area",
            "type":"Public Place"
        }
    ],
    "sg:phone":"+61 3 6273 8011",
    "sg:postcode":"7009",
    "sg:province":"TAS",
    "sg:tags":[
        "heavy",
        "carrier"
    ],
    "wof:name":"East Coast Freight",
    "wof:placetype":"venue"
},
  "geometry": {"coordinates":[147.287277222,-42.8338851929],"type":"Point"}
}