{
  "type": "Feature",
  "properties": {
    "iso:country":"AU",
    "sg:address":"PO Box 614",
    "sg:city":"Woy Woy",
    "sg:classifiers":[
        {
            "category":"Recreation",
            "type":"Entertainment"
        }
    ],
    "sg:phone":"+61 2 4341 3906",
    "sg:postcode":"2256",
    "sg:province":"NSW",
    "sg:tags":[
        "supply",
        "outdoor",
        "adventure",
        "activity"
    ],
    "wof:name":"The Bicycle Store Pty Ltd",
    "wof:placetype":"venue"
},
  "geometry": {"coordinates":[151.32435607900001,-33.4853668213],"type":"Point"}
}