{
  "type": "Feature",
  "properties": {
    "addr:full":"300 South Pine Rd Brendale QLD 4500",
    "addr:housenumber":"300",
    "addr:postcode":"4500",
    "addr:street":"South Pine Rd",
    "iso:country":"AU",
    "sg:address":"300 South Pine Rd",
    "sg:city":"Brendale",
    "sg:classifiers":[
        {
            "category":"Professional",
            "subcategory":"Employment Agencies",
            "type":"Services"
        }
    ],
    "sg:phone":"+61 7 3204 3399",
    "sg:postcode":"4500",
    "sg:province":"QLD",
    "sg:tags":[
        "hire",
        "labour",
        "contractor"
    ],
    "wof:name":"Biga Apprenticeships",
    "wof:placetype":"venue"
},
  "geometry": {"coordinates":[152.98733520499999,-27.3244857788],"type":"Point"}
}