{
  "type": "Feature",
  "properties": {
    "iso:country":"AU",
    "sg:address":"Unit 9b- 69 Sir Donald Bradman Drv",
    "sg:city":"Hilton",
    "sg:classifiers":[
        {
            "category":"Building & Trades",
            "subcategory":"Cleaning & Sanitation",
            "type":"Services"
        }
    ],
    "sg:phone":"+61 8 8234 2400",
    "sg:postcode":"5033",
    "sg:province":"SA",
    "sg:tags":[
        "chemical",
        "pressure",
        "steam",
        "contractor"
    ],
    "wof:name":"Prime One Services",
    "wof:placetype":"venue"
},
  "geometry": {"coordinates":[138.569915772,-34.9321136475],"type":"Point"}
}