{
  "type": "Feature",
  "properties": {
    "addr:full":"Shop 4, 8 Booth Pl Balcatta WA 6021",
    "addr:housenumber":"shop;8",
    "addr:postcode":"6021",
    "addr:street":"Booth Pl",
    "iso:country":"AU",
    "sg:address":"Shop 4, 8 Booth Pl",
    "sg:city":"Balcatta",
    "sg:classifiers":[
        {
            "category":"Fast Food",
            "type":"Food & Drink"
        }
    ],
    "sg:phone":"+61 8 9345 4355",
    "sg:postcode":"6021",
    "sg:province":"WA",
    "sg:tags":[
        "away",
        "take"
    ],
    "wof:name":"Freeway Lunch Bar",
    "wof:placetype":"venue"
},
  "geometry": {"coordinates":[115.803169251,-31.8662052155],"type":"Point"}
}