{
  "type": "Feature",
  "properties": {
    "iso:country":"AU",
    "sg:address":"PO Box 8136",
    "sg:city":"Gladstone South",
    "sg:classifiers":[
        {
            "category":"Building & Trades",
            "subcategory":"Construction",
            "type":"Services"
        }
    ],
    "sg:phone":"+61 411 873 037",
    "sg:postcode":"4680",
    "sg:province":"QLD",
    "sg:tags":[
        "plasterboard",
        "plasterer",
        "fixer"
    ],
    "wof:name":"Azarry Malahoff",
    "wof:placetype":"venue"
},
  "geometry": {"coordinates":[151.26481628400001,-23.8740692139],"type":"Point"}
}