{
  "type": "Feature",
  "properties": {
    "iso:country":"AU",
    "sg:address":"83 The River Rd",
    "sg:city":"Bankstown",
    "sg:classifiers":[
        {
            "category":"Retail",
            "subcategory":"Funeral Services",
            "type":"Services"
        }
    ],
    "sg:phone":"+61 2 9792 8883",
    "sg:postcode":"2200",
    "sg:province":"NSW",
    "sg:tags":[
        "director"
    ],
    "wof:name":"Olsens Funerals",
    "wof:placetype":"venue"
},
  "geometry": {"coordinates":[151.03595000000001,-33.915886],"type":"Point"}
}