{
  "type": "Feature",
  "properties": {
    "addr:full":"2 Kate St Victoria Park WA 6100",
    "addr:housenumber":"2",
    "addr:postcode":"6100",
    "addr:street":"Kate St",
    "iso:country":"AU",
    "sg:address":"2 Kate St",
    "sg:city":"Victoria Park",
    "sg:classifiers":[
        {
            "category":"Communications",
            "type":"Services"
        }
    ],
    "sg:phone":"+61 8 9361 4089",
    "sg:postcode":"6100",
    "sg:province":"WA",
    "sg:tags":[
        "translation"
    ],
    "wof:name":"Pontre Dr Linda A.",
    "wof:placetype":"venue"
},
  "geometry": {"coordinates":[115.907897949,-31.982831955],"type":"Point"}
}