{
  "type": "Feature",
  "properties": {
    "addr:full":"24 Victor Drv Kawungan QLD 4655",
    "addr:housenumber":"24",
    "addr:postcode":"4655",
    "addr:street":"Victor Drv",
    "iso:country":"AU",
    "sg:address":"24 Victor Drv",
    "sg:city":"Kawungan",
    "sg:classifiers":[
        {
            "category":"Retail",
            "subcategory":"Repair Shop",
            "type":"Services"
        }
    ],
    "sg:phone":"+61 7 4124 0694",
    "sg:postcode":"4655",
    "sg:province":"QLD",
    "sg:tags":[
        "mending",
        "clothing",
        "alteration"
    ],
    "wof:name":"Lyn's Sewing Service",
    "wof:placetype":"venue"
},
  "geometry": {"coordinates":[152.83677700000001,-25.305914],"type":"Point"}
}