{
  "type": "Feature",
  "properties": {
    "addr:full":"Unit3 14 Midas Rd Malaga WA 6090",
    "addr:housenumber":"14",
    "addr:postcode":"6090",
    "addr:street":"Midas Rd",
    "iso:country":"AU",
    "sg:address":"Unit3 14 Midas Rd",
    "sg:city":"Malaga",
    "sg:classifiers":[
        {
            "category":"Autos & Motor Vehicles",
            "subcategory":"Automobile Sales",
            "type":"Retail Goods"
        }
    ],
    "sg:phone":"+61 8 9248 6788",
    "sg:postcode":"6090",
    "sg:province":"WA",
    "sg:tags":[
        "equipment",
        "trailer"
    ],
    "wof:name":"Design- A-Trailer",
    "wof:placetype":"venue"
},
  "geometry": {"coordinates":[115.892288208,-31.8600254059],"type":"Point"}
}