{
  "type": "Feature",
  "properties": {
    "addr:full":"1321 Malvern Rd Malvern VIC 3144",
    "addr:housenumber":"1321",
    "addr:postcode":"3144",
    "addr:street":"Malvern Rd",
    "iso:country":"AU",
    "sg:address":"1321 Malvern Rd",
    "sg:city":"Malvern",
    "sg:classifiers":[
        {
            "category":"Travel",
            "subcategory":"Hotels & Motels",
            "type":"Entertainment"
        }
    ],
    "sg:phone":"+61 3 9822 1497",
    "sg:postcode":"3144",
    "sg:province":"VIC",
    "sg:tags":[
        "pub"
    ],
    "wof:name":"Malvern Vale Hotel",
    "wof:placetype":"venue"
},
  "geometry": {"coordinates":[145.038208008,-37.8525619507],"type":"Point"}
}