{
  "type": "Feature",
  "properties": {
    "addr:full":"Shp1/ 1469 David Low Way Yaroomba QLD 4573",
    "addr:housenumber":"1469",
    "addr:postcode":"4573",
    "addr:street":"David Low Way",
    "iso:country":"AU",
    "sg:address":"Shp1/ 1469",
    "sg:city":"David Low Way Yaroomba",
    "sg:classifiers":[
        {
            "category":"Shopping",
            "subcategory":"Clothing, Apparel, & Fashions",
            "type":"Retail Goods"
        }
    ],
    "sg:phone":"+61 7 5471 7703",
    "sg:postcode":"4573",
    "sg:province":"QLD",
    "sg:tags":[
        "lady",
        "wear"
    ],
    "wof:name":"Marmilade Clothing",
    "wof:placetype":"venue"
},
  "geometry": {"coordinates":[153.09805299999999,-26.552309],"type":"Point"}
}