{
  "type": "Feature",
  "properties": {
    "addr:full":"148 Main Rd Blackwood SA 5051",
    "addr:housenumber":"148",
    "addr:postcode":"5051",
    "addr:street":"Main Rd",
    "iso:country":"AU",
    "sg:address":"148 Main Rd",
    "sg:city":"Blackwood",
    "sg:classifiers":[
        {
            "category":"Shopping",
            "subcategory":"Clothing, Apparel, & Fashions",
            "type":"Retail Goods"
        }
    ],
    "sg:phone":"+61 8 8370 0200",
    "sg:postcode":"5051",
    "sg:province":"SA",
    "sg:tags":[
        "recycled",
        "clothing"
    ],
    "wof:name":"Goodwill",
    "wof:placetype":"venue"
},
  "geometry": {"coordinates":[138.62278699999999,-35.024883],"type":"Point"}
}