{
  "type": "Feature",
  "properties": {
    "iso:country":"AU",
    "sg:address":"32 Shepherd St",
    "sg:city":"Footscray",
    "sg:classifiers":[
        {
            "category":"Food & Beverages",
            "subcategory":"Groceries & Convenience Stores",
            "type":"Retail Goods"
        }
    ],
    "sg:phone":"+61 3 9689 2422",
    "sg:postcode":"3011",
    "sg:province":"VIC",
    "wof:name":"Cakmak's Convenience Store",
    "wof:placetype":"venue"
},
  "geometry": {"coordinates":[144.890914917,-37.7948493958],"type":"Point"}
}