{
  "type": "Feature",
  "properties": {
    "addr:full":"Youngman St Kingaroy QLD 4610",
    "addr:postcode":"4610",
    "addr:street":"Youngman St",
    "iso:country":"AU",
    "sg:address":"Youngman St",
    "sg:city":"Kingaroy",
    "sg:classifiers":[
        {
            "category":"Wholesale",
            "subcategory":"Farm Supplies",
            "type":"Manufacturing & Wholesale Goods"
        }
    ],
    "sg:phone":"+61 7 4164 9000",
    "sg:postcode":"4610",
    "sg:province":"QLD",
    "sg:tags":[
        "feed",
        "supplement",
        "stock"
    ],
    "wof:name":"Kewpie Stockfeeds Pty Ltd",
    "wof:placetype":"venue"
},
  "geometry": {"coordinates":[151.83583068900001,-26.542848587],"type":"Point"}
}