{
  "type": "Feature",
  "properties": {
    "addr:full":"6 William St Brighton VIC 3186",
    "addr:housenumber":"6",
    "addr:postcode":"3186",
    "addr:street":"William St",
    "iso:country":"AU",
    "sg:address":"6 William St",
    "sg:city":"Brighton",
    "sg:classifiers":[
        {
            "category":"Professional",
            "subcategory":"Art Services",
            "type":"Services"
        }
    ],
    "sg:phone":"+61 3 9592 8188",
    "sg:postcode":"3186",
    "sg:province":"VIC",
    "sg:tags":[
        "interior",
        "decorator"
    ],
    "wof:name":"Elisabeth Garratt Interiors",
    "wof:placetype":"venue"
},
  "geometry": {"coordinates":[144.999465942,-37.907989502],"type":"Point"}
}