{
  "type": "Feature",
  "properties": {
    "iso:country":"AU",
    "sg:address":"290- 296 Argyle St",
    "sg:city":"Hobart",
    "sg:classifiers":[
        {
            "category":"Autos & Motor Vehicles",
            "subcategory":"Automobile Sales",
            "type":"Retail Goods"
        }
    ],
    "sg:phone":"+61 3 6234 8222",
    "sg:postcode":"7000",
    "sg:province":"TAS",
    "sg:tags":[
        "car",
        "used"
    ],
    "wof:name":"Colonial Motors",
    "wof:placetype":"venue"
},
  "geometry": {"coordinates":[147.317901611,-42.8723716736],"type":"Point"}
}