{
  "type": "Feature",
  "properties": {
    "addr:full":"201 Spencer St Docklands VIC 3008",
    "addr:housenumber":"201",
    "addr:postcode":"3008",
    "addr:street":"Spencer St",
    "iso:country":"AU",
    "sg:address":"201 Spencer St",
    "sg:city":"Docklands",
    "sg:classifiers":[
        {
            "category":"Shopping",
            "subcategory":"Clothing, Apparel, & Fashions",
            "type":"Retail Goods"
        }
    ],
    "sg:phone":"+61 3 8689 7525",
    "sg:postcode":"3008",
    "sg:province":"VIC",
    "sg:tags":[
        "lingerie",
        "hosiery",
        "sleepwear"
    ],
    "wof:name":"Simone Perele Factory Outlet",
    "wof:placetype":"venue"
},
  "geometry": {"coordinates":[144.95300293,-37.8168487549],"type":"Point"}
}