{
  "type": "Feature",
  "properties": {
    "iso:country":"AU",
    "sg:address":"93- 95 North Tce",
    "sg:city":"College Park",
    "sg:classifiers":[
        {
            "category":"Shopping",
            "subcategory":"Antiques",
            "type":"Retail Goods"
        }
    ],
    "sg:phone":"+61 8 8363 0233",
    "sg:postcode":"5069",
    "sg:province":"SA",
    "sg:tags":[
        "restoration",
        "reproduction"
    ],
    "wof:name":"Gilty on the Terrace",
    "wof:placetype":"venue"
},
  "geometry": {"coordinates":[138.622436523,-34.9134101868],"type":"Point"}
}