{
  "type": "Feature",
  "properties": {
    "addr:full":"Cnr Dampier & Goonan Sts Tamworth NSW 2340",
    "addr:postcode":"2340",
    "addr:street":"Cnr Dampier & Goonan Sts",
    "iso:country":"AU",
    "sg:address":"Cnr Dampier & Goonan Sts",
    "sg:city":"Tamworth",
    "sg:classifiers":[
        {
            "category":"Home & Garden",
            "subcategory":"Building Materials",
            "type":"Retail Goods"
        }
    ],
    "sg:phone":"+61 2 6762 1022",
    "sg:postcode":"2340",
    "sg:province":"NSW",
    "sg:tags":[
        "fitting",
        "door"
    ],
    "wof:name":"Tamworth Building Supplies",
    "wof:placetype":"venue"
},
  "geometry": {"coordinates":[150.89869689899999,-31.0902366638],"type":"Point"}
}