{
  "type": "Feature",
  "properties": {
    "addr:full":"25 Service St Bairnsdale VIC 3875",
    "addr:housenumber":"25",
    "addr:postcode":"3875",
    "addr:street":"Service St",
    "iso:country":"AU",
    "sg:address":"25 Service St",
    "sg:city":"Bairnsdale",
    "sg:classifiers":[
        {
            "category":"Food & Beverages",
            "subcategory":"Liquor & Beverages",
            "type":"Retail Goods"
        }
    ],
    "sg:phone":"+61 3 5152 3372",
    "sg:postcode":"3875",
    "sg:province":"VIC",
    "sg:tags":[
        "merchant",
        "spirit",
        "wine"
    ],
    "wof:name":"Tasters Wine & Foods",
    "wof:placetype":"venue"
},
  "geometry": {"coordinates":[147.62937927199999,-37.8255691528],"type":"Point"}
}