{
  "type": "Feature",
  "properties": {
    "addr:full":"Cnr Great Eastern Hwy & Lyall St Ascot WA 6104",
    "addr:postcode":"6104",
    "addr:street":"Cnr Great Eastern Hwy & Lyall St",
    "iso:country":"AU",
    "sg:address":"Cnr Great Eastern Hwy & Lyall St",
    "sg:city":"Ascot",
    "sg:classifiers":[
        {
            "category":"Fast Food",
            "type":"Food & Drink"
        }
    ],
    "sg:phone":"+61 8 9478 3480",
    "sg:postcode":"6104",
    "sg:province":"WA",
    "sg:tags":[
        "away",
        "take"
    ],
    "wof:name":"McDonald's Family Restaurants",
    "wof:placetype":"venue"
},
  "geometry": {"coordinates":[115.94390106199999,-31.930721283],"type":"Point"}
}