{
  "type": "Feature",
  "properties": {
    "addr:full":"61 James St Dunoon NSW 2480",
    "addr:housenumber":"61",
    "addr:postcode":"2480",
    "addr:street":"James St",
    "iso:country":"AU",
    "sg:address":"61 James St",
    "sg:city":"Dunoon",
    "sg:classifiers":[
        {
            "category":"Building & Trades",
            "subcategory":"Plumbing",
            "type":"Services"
        }
    ],
    "sg:phone":"+61 2 6689 5174",
    "sg:postcode":"2480",
    "sg:province":"NSW",
    "sg:tags":[
        "plumber",
        "gasfitters"
    ],
    "wof:name":"Hyde Nik",
    "wof:placetype":"venue"
},
  "geometry": {"coordinates":[153.27496337900001,-28.8161964417],"type":"Point"}
}