{
  "type": "Feature",
  "properties": {
    "iso:country":"AU",
    "sg:address":"Shop 6/ 75 Morayfield Plz",
    "sg:city":"Morayfield",
    "sg:classifiers":[
        {
            "category":"Fast Food",
            "type":"Food & Drink"
        }
    ],
    "sg:phone":"+61 7 5495 4320",
    "sg:postcode":"4506",
    "sg:province":"QLD",
    "sg:tags":[
        "away",
        "take"
    ],
    "wof:name":"Ruby Chinese Take Away",
    "wof:placetype":"venue"
},
  "geometry": {"coordinates":[152.949752808,-27.1099700928],"type":"Point"}
}