{
  "type": "Feature",
  "properties": {
    "iso:country":"AU",
    "sg:address":"87 Douglas Pde",
    "sg:city":"Williamstown",
    "sg:classifiers":[
        {
            "category":"Health Services",
            "subcategory":"Doctor",
            "type":"Services"
        }
    ],
    "sg:phone":"+61 3 9397 8133",
    "sg:postcode":"3016",
    "sg:province":"VIC",
    "sg:tags":[
        "medical",
        "practitioner"
    ],
    "wof:name":"Poon Michael Dr",
    "wof:placetype":"venue"
},
  "geometry": {"coordinates":[144.89744567899999,-37.856048584],"type":"Point"}
}