{
  "type": "Feature",
  "properties": {
    "iso:country":"AU",
    "sg:address":"52 Whiting St",
    "sg:city":"Artarmon",
    "sg:classifiers":[
        {
            "category":"Autos & Motor Vehicles",
            "subcategory":"Boat Sales",
            "type":"Retail Goods"
        }
    ],
    "sg:phone":"+61 2 9439 2333",
    "sg:postcode":"2064",
    "sg:province":"NSW",
    "sg:tags":[
        "equipment",
        "yacht"
    ],
    "wof:name":"Rubin Group",
    "wof:placetype":"venue"
},
  "geometry": {"coordinates":[151.182037353,-33.8159675598],"type":"Point"}
}