{
  "type": "Feature",
  "properties": {
    "addr:full":"148 Toorak Rd South Yarra VIC 3141",
    "addr:housenumber":"148",
    "addr:postcode":"3141",
    "addr:street":"Toorak Rd",
    "iso:country":"AU",
    "sg:address":"148 Toorak Rd",
    "sg:city":"South Yarra",
    "sg:classifiers":[
        {
            "category":"Shopping",
            "subcategory":"Jewelry",
            "type":"Retail Goods"
        }
    ],
    "sg:phone":"+61 3 9867 5858",
    "sg:postcode":"3141",
    "sg:province":"VIC",
    "sg:tags":[
        "jeweller"
    ],
    "wof:name":"Collections Fine Jewellery",
    "wof:placetype":"venue"
},
  "geometry": {"coordinates":[144.991165161,-37.839050293],"type":"Point"}
}