{
  "type": "Feature",
  "properties": {
    "addr:full":"Yarrandale Rd Dubbo NSW 2830",
    "addr:postcode":"2830",
    "addr:street":"Yarrandale Rd",
    "iso:country":"AU",
    "sg:address":"Yarrandale Rd",
    "sg:city":"Dubbo",
    "sg:phone":"+61 1800 800 626",
    "sg:postcode":"2830",
    "sg:province":"NSW",
    "wof:name":"Tankworld",
    "wof:placetype":"venue"
},
  "geometry": {"coordinates":[148.62896728499999,-32.2379760742],"type":"Point"}
}