{
  "type": "Feature",
  "properties": {
    "addr:full":"Unit 1, 5 Smith St Emu Plains NSW 2750",
    "addr:housenumber":"5",
    "addr:postcode":"2750",
    "addr:street":"Smith St",
    "iso:country":"AU",
    "sg:address":"Unit 1, 5 Smith St",
    "sg:city":"Emu Plains",
    "sg:classifiers":[
        {
            "category":"Home & Garden",
            "subcategory":"Hardware",
            "type":"Retail Goods"
        }
    ],
    "sg:phone":"+61 2 4735 5568",
    "sg:postcode":"2750",
    "sg:province":"NSW",
    "sg:tags":[
        "tarpaulin"
    ],
    "wof:name":"KH Trailers",
    "wof:placetype":"venue"
},
  "geometry": {"coordinates":[150.67071533199999,-33.7432365417],"type":"Point"}
}