{
  "type": "Feature",
  "properties": {
    "addr:full":"4 Technology Drv Warana QLD 4575",
    "addr:housenumber":"4",
    "addr:postcode":"4575",
    "addr:street":"Technology Drv",
    "iso:country":"AU",
    "sg:address":"4 Technology Drv",
    "sg:city":"Warana",
    "sg:classifiers":[
        {
            "category":"Education",
            "subcategory":"Kindergarten",
            "type":"Public Place"
        }
    ],
    "sg:phone":"+61 7 5493 7477",
    "sg:postcode":"4575",
    "sg:province":"QLD",
    "sg:tags":[
        "pre-schools"
    ],
    "wof:name":"Kindamindi Child Care Centre & Preschool",
    "wof:placetype":"venue"
},
  "geometry": {"coordinates":[153.12820400000001,-26.723322],"type":"Point"}
}