{
  "type": "Feature",
  "properties": {
    "iso:country":"AU",
    "sg:address":"762a Beaufort St",
    "sg:city":"Mt Lawley",
    "sg:classifiers":[
        {
            "category":"Shopping",
            "subcategory":"Music",
            "type":"Retail Goods"
        }
    ],
    "sg:phone":"+61 8 9371 8666",
    "sg:postcode":"6050",
    "sg:province":"WA",
    "sg:tags":[
        "instrument",
        "musical"
    ],
    "wof:name":"The Acoustic Inn",
    "wof:placetype":"venue"
},
  "geometry": {"coordinates":[115.878311157,-31.9279460907],"type":"Point"}
}