{
  "type": "Feature",
  "properties": {
    "addr:full":"53 Nihil St Alexandra VIC 3714",
    "addr:housenumber":"53",
    "addr:postcode":"3714",
    "addr:street":"Nihil St",
    "iso:country":"AU",
    "sg:address":"53 Nihil St",
    "sg:city":"Alexandra",
    "sg:classifiers":[
        {
            "category":"Shopping",
            "subcategory":"Mobile Phones",
            "type":"Retail Goods"
        }
    ],
    "sg:phone":"+61 3 5772 1292",
    "sg:postcode":"3714",
    "sg:province":"VIC",
    "sg:tags":[
        "telephone",
        "accessory"
    ],
    "wof:name":"Weeks Radio",
    "wof:placetype":"venue"
},
  "geometry": {"coordinates":[145.709381103,-37.1936340332],"type":"Point"}
}