{
  "type": "Feature",
  "properties": {
    "addr:full":"55 Robert St Surat QLD 4417",
    "addr:housenumber":"55",
    "addr:postcode":"4417",
    "addr:street":"Robert St",
    "iso:country":"AU",
    "sg:address":"55 Robert St",
    "sg:city":"Surat",
    "sg:classifiers":[
        {
            "category":"Education",
            "subcategory":"School",
            "type":"Public Place"
        }
    ],
    "sg:phone":"+61 7 4626 4333",
    "sg:postcode":"4417",
    "sg:province":"QLD",
    "sg:tags":[
        "state",
        "except",
        "nsw"
    ],
    "wof:name":"Surat Primary",
    "wof:placetype":"venue"
},
  "geometry": {"coordinates":[149.06915283199999,-27.1548252106],"type":"Point"}
}