{
  "type": "Feature",
  "properties": {
    "addr:full":"82 Mort St Toowoomba QLD 4350",
    "addr:housenumber":"82",
    "addr:postcode":"4350",
    "addr:street":"Mort St",
    "iso:country":"AU",
    "sg:address":"82 Mort St",
    "sg:city":"Toowoomba",
    "sg:classifiers":[
        {
            "category":"Building & Trades",
            "subcategory":"Construction",
            "type":"Services"
        }
    ],
    "sg:phone":"+61 7 4632 3822",
    "sg:postcode":"4350",
    "sg:province":"QLD",
    "sg:tags":[
        "monumental",
        "mason"
    ],
    "wof:name":"Ziegler R C Monumentals Pty Ltd",
    "wof:placetype":"venue"
},
  "geometry": {"coordinates":[151.95010400000001,-27.549314],"type":"Point"}
}