{
  "type": "Feature",
  "properties": {
    "iso:country":"AU",
    "sg:address":"Shop 7 Riverside Centre Maple St",
    "sg:city":"Maleny",
    "sg:classifiers":[
        {
            "category":"Fast Food",
            "type":"Food & Drink"
        }
    ],
    "sg:phone":"+61 7 5499 9444",
    "sg:postcode":"4552",
    "sg:province":"QLD",
    "sg:tags":[
        "away",
        "take"
    ],
    "wof:name":"Cappriccios Italian Licenced Restaurant",
    "wof:placetype":"venue"
},
  "geometry": {"coordinates":[152.84934997600001,-26.7581157684],"type":"Point"}
}