{
  "type": "Feature",
  "properties": {
    "addr:full":"139 Macpherson St Nhill VIC 3418",
    "addr:housenumber":"139",
    "addr:postcode":"3418",
    "addr:street":"Macpherson St",
    "iso:country":"AU",
    "sg:address":"139 Macpherson St",
    "sg:city":"Nhill",
    "sg:classifiers":[
        {
            "category":"Organizations",
            "subcategory":"Professional Association",
            "type":"Services"
        }
    ],
    "sg:phone":"+61 3 5391 1019",
    "sg:postcode":"3418",
    "sg:province":"VIC",
    "sg:tags":[
        "rural",
        "organisation",
        "production",
        "primary"
    ],
    "wof:name":"Nhill A & P Society",
    "wof:placetype":"venue"
},
  "geometry": {"coordinates":[141.649459839,-36.3347244263],"type":"Point"}
}