{
  "type": "Feature",
  "properties": {
    "iso:country":"AU",
    "sg:address":"Unit 2/ 19 Churchill St",
    "sg:city":"Narembeen",
    "sg:classifiers":[
        {
            "category":"Professional",
            "subcategory":"Secretarial Services",
            "type":"Services"
        }
    ],
    "sg:phone":"+61 8 9064 7055",
    "sg:postcode":"6369",
    "sg:province":"WA",
    "sg:tags":[
        "typing"
    ],
    "wof:name":"Narembeen Telecentre",
    "wof:placetype":"venue"
},
  "geometry": {"coordinates":[118.394569,-32.065453],"type":"Point"}
}