{
  "type": "Feature",
  "properties": {
    "iso:country":"AU",
    "sg:address":"PO Box 552",
    "sg:city":"Laverton",
    "sg:classifiers":[
        {
            "category":"Building & Trades",
            "subcategory":"Construction",
            "type":"Services"
        }
    ],
    "sg:phone":"+61 412 540 450",
    "sg:postcode":"3028",
    "sg:province":"VIC",
    "sg:tags":[
        "contractor"
    ],
    "wof:name":"M L G Builders & Sons Pty Ltd",
    "wof:placetype":"venue"
},
  "geometry": {"coordinates":[144.769699,-37.86277],"type":"Point"}
}