{
  "type": "Feature",
  "properties": {
    "iso:country":"AU",
    "sg:address":"Wembley Rd",
    "sg:city":"(cnr Benz St), Woodridge",
    "sg:classifiers":[
        {
            "category":"Health Services",
            "subcategory":"Doctor",
            "type":"Services"
        }
    ],
    "sg:phone":"+61 7 3808 1000",
    "sg:postcode":"4114",
    "sg:province":"QLD",
    "sg:tags":[
        "medical",
        "practitioner"
    ],
    "wof:name":"Woodridge Family Practice",
    "wof:placetype":"venue"
},
  "geometry": {"coordinates":[153.107254028,-27.6409168243],"type":"Point"}
}