{
  "type": "Feature",
  "properties": {
    "addr:full":"Findon Shopping Centre 303 Grange Rd Findon SA 5023",
    "addr:housenumber":"303",
    "addr:postcode":"5023",
    "addr:street":"Grange Rd",
    "iso:country":"AU",
    "sg:address":"Findon Shopping Centre 303 Grange Rd",
    "sg:city":"Findon",
    "sg:classifiers":[
        {
            "category":"Health Services",
            "subcategory":"Dentist",
            "type":"Services"
        }
    ],
    "sg:phone":"+61 8 8356 1566",
    "sg:postcode":"5023",
    "sg:province":"SA",
    "wof:name":"King P A & Plunkett R A",
    "wof:placetype":"venue"
},
  "geometry": {"coordinates":[138.531692505,-34.9053955078],"type":"Point"}
}