{
  "type": "Feature",
  "properties": {
    "iso:country":"AU",
    "sg:address":"370b Kensington Rd",
    "sg:city":"Erindale",
    "sg:classifiers":[
        {
            "category":"Shopping",
            "subcategory":"Antiques",
            "type":"Retail Goods"
        }
    ],
    "sg:phone":"+61 8 8431 4999",
    "sg:postcode":"5066",
    "sg:province":"SA",
    "wof:name":"Erindales Old & Antiques",
    "wof:placetype":"venue"
},
  "geometry": {"coordinates":[138.66317749000001,-34.9259605408],"type":"Point"}
}