{
  "type": "Feature",
  "properties": {
    "iso:country":"AU",
    "sg:address":"238 Nudgee Rd",
    "sg:city":"Hendra",
    "sg:classifiers":[
        {
            "category":"Retail",
            "subcategory":"Auto Rental",
            "type":"Services"
        }
    ],
    "sg:phone":"+61 7 3868 1500",
    "sg:postcode":"4011",
    "sg:province":"QLD",
    "sg:tags":[
        "bus",
        "truck"
    ],
    "wof:name":"A Roadway Rent A Car",
    "wof:placetype":"venue"
},
  "geometry": {"coordinates":[153.07264699999999,-27.42495],"type":"Point"}
}