{
  "type": "Feature",
  "properties": {
    "addr:full":"39 Gilbert St Adelaide SA 5000",
    "addr:housenumber":"39",
    "addr:postcode":"5000",
    "addr:street":"Gilbert St",
    "iso:country":"AU",
    "sg:address":"39 Gilbert St",
    "sg:city":"Adelaide",
    "sg:classifiers":[
        {
            "category":"Real Estate",
            "subcategory":"Real Estate Agent",
            "type":"Services"
        }
    ],
    "sg:phone":"+61 419 823 860",
    "sg:postcode":"5000",
    "sg:province":"SA",
    "sg:tags":[
        "export"
    ],
    "wof:name":"Health Connections Australia",
    "wof:placetype":"venue"
},
  "geometry": {"coordinates":[138.59965515100001,-34.9344596863],"type":"Point"}
}