{
  "type": "Feature",
  "properties": {
    "addr:full":"PO Box 6075 Kincumber NSW 2251",
    "addr:postcode":"2251",
    "iso:country":"AU",
    "sg:address":"PO Box 6075",
    "sg:city":"Kincumber",
    "sg:classifiers":[
        {
            "category":"Building & Trades",
            "subcategory":"Landscaping Services",
            "type":"Services"
        }
    ],
    "sg:phone":"+61 2 4369 2878",
    "sg:postcode":"2251",
    "sg:province":"NSW",
    "sg:tags":[
        "stump",
        "tree",
        "felling",
        "removal"
    ],
    "wof:name":"Woy Woy & Umina Tree Service",
    "wof:placetype":"venue"
},
  "geometry": {"coordinates":[151.38150024399999,-33.4676513672],"type":"Point"}
}