{
  "type": "Feature",
  "properties": {
    "iso:country":"AU",
    "sg:address":"23-27 Railway Rd",
    "sg:city":"Blackburn",
    "sg:classifiers":[
        {
            "category":"Professional",
            "subcategory":"Testing Lab",
            "type":"Services"
        }
    ],
    "sg:phone":"+61 3 9894 4222",
    "sg:postcode":"3130",
    "sg:province":"VIC",
    "sg:tags":[
        "soil",
        "investigation"
    ],
    "wof:name":"Enrik Engineering Pty Ltd",
    "wof:placetype":"venue"
},
  "geometry": {"coordinates":[145.149658203,-37.8196601868],"type":"Point"}
}