{
  "type": "Feature",
  "properties": {
    "addr:full":"167 Elizabeth St Sunbury VIC 3429",
    "addr:housenumber":"167",
    "addr:postcode":"3429",
    "addr:street":"Elizabeth St",
    "iso:country":"AU",
    "sg:address":"167 Elizabeth St",
    "sg:city":"Sunbury",
    "sg:classifiers":[
        {
            "category":"Autos & Motor Vehicles",
            "subcategory":"Auto Supplies",
            "type":"Retail Goods"
        }
    ],
    "sg:phone":"+61 3 9740 9134",
    "sg:postcode":"3429",
    "sg:province":"VIC",
    "sg:tags":[
        "equipment",
        "part",
        "truck"
    ],
    "wof:name":"Cargo Control Systems",
    "wof:placetype":"venue"
},
  "geometry": {"coordinates":[144.720993042,-37.5701789856],"type":"Point"}
}