{
  "type": "Feature",
  "properties": {
    "iso:country":"AU",
    "sg:address":"615 Rubicon St",
    "sg:city":"Sebastopol",
    "sg:classifiers":[
        {
            "category":"Home & Garden",
            "subcategory":"Kitchen Supply",
            "type":"Retail Goods"
        }
    ],
    "sg:phone":"+61 3 5336 2631",
    "sg:postcode":"3356",
    "sg:province":"VIC",
    "sg:tags":[
        "sharpening"
    ],
    "wof:name":"Kerbside Mobile Sharpening Service",
    "wof:placetype":"venue"
},
  "geometry": {"coordinates":[143.829605,-37.581059],"type":"Point"}
}