{
  "type": "Feature",
  "properties": {
    "addr:full":"18- 20 Lucca Rd Wyong North NSW 2259",
    "addr:housenumber":"20",
    "addr:postcode":"2259",
    "addr:street":"Lucca Rd",
    "iso:country":"AU",
    "sg:address":"18- 20 Lucca Rd",
    "sg:city":"Wyong North",
    "sg:classifiers":[
        {
            "category":"Manufacturing",
            "subcategory":"Building Materials",
            "type":"Manufacturing & Wholesale Goods"
        }
    ],
    "sg:phone":"+61 2 4352 2468",
    "sg:postcode":"2259",
    "sg:province":"NSW",
    "sg:tags":[
        "concrete",
        "product"
    ],
    "wof:name":"Amarcon Pty Limited",
    "wof:placetype":"venue"
},
  "geometry": {"coordinates":[151.41911315900001,-33.3097610474],"type":"Point"}
}