{
  "type": "Feature",
  "properties": {
    "addr:full":"73 Hansworth St Mulgrave VIC 3170",
    "addr:housenumber":"73",
    "addr:postcode":"3170",
    "addr:street":"Hansworth St",
    "iso:country":"AU",
    "sg:address":"73 Hansworth St",
    "sg:city":"Mulgrave",
    "sg:classifiers":[
        {
            "category":"Building & Trades",
            "subcategory":"Cleaning & Sanitation",
            "type":"Services"
        }
    ],
    "sg:phone":"+61 412 528 067",
    "sg:postcode":"3170",
    "sg:province":"VIC",
    "sg:tags":[
        "industrial",
        "commercial",
        "contractor"
    ],
    "wof:name":"Dependable Cleaning Services",
    "wof:placetype":"venue"
},
  "geometry": {"coordinates":[145.17706298799999,-37.9308776855],"type":"Point"}
}