{
  "type": "Feature",
  "properties": {
    "iso:country":"AU",
    "sg:address":"Triple Cee Shopping Centre Cnr Kingston & Wembley Rds",
    "sg:city":"Logan Central",
    "sg:classifiers":[
        {
            "category":"Food & Beverages",
            "subcategory":"Bakery",
            "type":"Retail Goods"
        }
    ],
    "sg:phone":"+61 7 3808 8233",
    "sg:postcode":"4114",
    "sg:province":"QLD",
    "sg:tags":[
        "baker"
    ],
    "wof:name":"Petro Bakery Brisbane",
    "wof:placetype":"venue"
},
  "geometry": {"coordinates":[153.11857605,-27.6407566071],"type":"Point"}
}