{
  "type": "Feature",
  "properties": {
    "addr:full":"Shop 4 & 5 / 84 Bemersyde Drv Berwick VIC 3806",
    "addr:housenumber":"shop 4 & 5 / 84",
    "addr:postcode":"3806",
    "addr:street":"Bemersyde Drv",
    "iso:country":"AU",
    "sg:address":"Shop 4 & 5 / 84 Bemersyde Drv",
    "sg:city":"Berwick",
    "sg:classifiers":[
        {
            "category":"Personal",
            "subcategory":"Beauty Salon",
            "type":"Services"
        }
    ],
    "sg:phone":"+61 3 9702 0440",
    "sg:postcode":"3806",
    "sg:province":"VIC",
    "sg:tags":[
        "hairdresser"
    ],
    "wof:name":"Funky Follicles",
    "wof:placetype":"venue"
},
  "geometry": {"coordinates":[145.34722900400001,-38.0512580872],"type":"Point"}
}