{
  "type": "Feature",
  "properties": {
    "addr:full":"8 Montague St Balmain NSW 2041",
    "addr:housenumber":"8",
    "addr:postcode":"2041",
    "addr:street":"Montague St",
    "iso:country":"AU",
    "sg:address":"8 Montague St",
    "sg:city":"Balmain",
    "sg:classifiers":[
        {
            "category":"Health Services",
            "subcategory":"Health Practitioner",
            "type":"Services"
        }
    ],
    "sg:phone":"+61 2 9818 1004",
    "sg:postcode":"2041",
    "sg:province":"NSW",
    "sg:tags":[
        "physiotherapist"
    ],
    "wof:name":"Balmain Sports Physiotherapy",
    "wof:placetype":"venue"
},
  "geometry": {"coordinates":[151.17796300000001,-33.857323],"type":"Point"}
}