{
  "type": "Feature",
  "properties": {
    "iso:country":"AU",
    "sg:address":"14 Somerton Crt",
    "sg:city":"Bacchus Marsh",
    "sg:classifiers":[
        {
            "category":"Building & Trades",
            "subcategory":"Construction",
            "type":"Services"
        }
    ],
    "sg:phone":"+61 418 589 027",
    "sg:postcode":"3340",
    "sg:province":"VIC",
    "sg:tags":[
        "concrete",
        "contractor"
    ],
    "wof:name":"Bob Stanley Concreting",
    "wof:placetype":"venue"
},
  "geometry": {"coordinates":[144.437286,-37.661556],"type":"Point"}
}