{
  "type": "Feature",
  "properties": {
    "iso:country":"AU",
    "sg:address":"270 Malabar Rd",
    "sg:city":"Maroubra",
    "sg:classifiers":[
        {
            "category":"Education",
            "subcategory":"Kindergarten",
            "type":"Public Place"
        }
    ],
    "sg:phone":"+61 2 9344 5173",
    "sg:postcode":"2035",
    "sg:province":"NSW",
    "sg:tags":[
        "pre-schools"
    ],
    "wof:name":"Maroubra Playtime Child Care Centre",
    "wof:placetype":"venue"
},
  "geometry": {"coordinates":[151.25611877399999,-33.9396972656],"type":"Point"}
}