{
  "type": "Feature",
  "properties": {
    "addr:full":"58 Henchman St Nundah QLD 4012",
    "addr:housenumber":"58",
    "addr:postcode":"4012",
    "addr:street":"Henchman St",
    "iso:country":"AU",
    "sg:address":"58 Henchman St",
    "sg:city":"Nundah",
    "sg:classifiers":[
        {
            "category":"Building & Trades",
            "subcategory":"Construction",
            "type":"Services"
        }
    ],
    "sg:phone":"+61 421 634 852",
    "sg:postcode":"4012",
    "sg:province":"QLD",
    "sg:tags":[
        "joiner",
        "carpenter"
    ],
    "wof:name":"Nicholls Carpentry Constructions",
    "wof:placetype":"venue"
},
  "geometry": {"coordinates":[153.06243896500001,-27.3985328674],"type":"Point"}
}