{
  "type": "Feature",
  "properties": {
    "iso:country":"AU",
    "sg:address":"137c Eagle St",
    "sg:city":"Longreach",
    "sg:classifiers":[
        {
            "category":"Professional",
            "subcategory":"Employment Agencies",
            "type":"Services"
        }
    ],
    "sg:phone":"+61 7 4658 1588",
    "sg:postcode":"4730",
    "sg:province":"QLD",
    "wof:name":"Golden West Emplyment Solutions",
    "wof:placetype":"venue"
},
  "geometry": {"coordinates":[144.24717699999999,-23.444176],"type":"Point"}
}