{
  "type": "Feature",
  "properties": {
    "iso:country":"AU",
    "sg:address":"Factory 1, 1 Churchill St",
    "sg:city":"Williamstown",
    "sg:classifiers":[
        {
            "category":"Wholesale",
            "subcategory":"Painting Supplies",
            "type":"Manufacturing & Wholesale Goods"
        }
    ],
    "sg:phone":"+61 3 9397 2122",
    "sg:postcode":"3016",
    "sg:province":"VIC",
    "sg:tags":[
        "product",
        "cleaning"
    ],
    "wof:name":"Curran Chemicals P/L",
    "wof:placetype":"venue"
},
  "geometry": {"coordinates":[144.86221313499999,-37.8546524048],"type":"Point"}
}