{
  "type": "Feature",
  "properties": {
    "addr:full":"341 King William St Adelaide SA 5000",
    "addr:housenumber":"341",
    "addr:postcode":"5000",
    "addr:street":"King William St",
    "iso:country":"AU",
    "sg:address":"341 King William St",
    "sg:city":"Adelaide",
    "sg:classifiers":[
        {
            "category":"Professional",
            "subcategory":"Detective & Security Services",
            "type":"Services"
        }
    ],
    "sg:phone":"+61 8 8221 6999",
    "sg:postcode":"5000",
    "sg:province":"SA",
    "sg:tags":[
        "investigator"
    ],
    "wof:name":"Quark & Associates Pty Ltd",
    "wof:placetype":"venue"
},
  "geometry": {"coordinates":[138.599975586,-34.9323654175],"type":"Point"}
}