{
  "type": "Feature",
  "properties": {
    "iso:country":"AU",
    "sg:address":"78 Main St",
    "sg:city":"Proserpine",
    "sg:classifiers":[
        {
            "category":"Shopping",
            "subcategory":"Discount & Variety Stores",
            "type":"Retail Goods"
        }
    ],
    "sg:phone":"+61 7 4945 3453",
    "sg:postcode":"4800",
    "sg:province":"QLD",
    "sg:tags":[
        "register",
        "cash"
    ],
    "wof:name":"Thedotcom",
    "wof:placetype":"venue"
},
  "geometry": {"coordinates":[148.58294677699999,-20.4018611908],"type":"Point"}
}