{
  "type": "Feature",
  "properties": {
    "addr:full":"2 Ormsby Pl Wetherill Park NSW 2164",
    "addr:housenumber":"2",
    "addr:postcode":"2164",
    "addr:street":"Ormsby Pl",
    "iso:country":"AU",
    "sg:address":"2 Ormsby Pl",
    "sg:city":"Wetherill Park",
    "sg:classifiers":[
        {
            "category":"Retail",
            "subcategory":"Auto Repair",
            "type":"Services"
        }
    ],
    "sg:phone":"+61 2 9604 3616",
    "sg:postcode":"2164",
    "sg:province":"NSW",
    "sg:tags":[
        "body",
        "builder",
        "motor"
    ],
    "wof:name":"Pacific Bodyworks",
    "wof:placetype":"venue"
},
  "geometry": {"coordinates":[150.901290894,-33.8348083496],"type":"Point"}
}