{
  "type": "Feature",
  "properties": {
    "addr:full":"Cnr Blackburn Rd & Waverley Rd Mt Waverley VIC 3149",
    "addr:postcode":"3149",
    "addr:street":"Cnr Blackburn Rd & Waverley Rd",
    "iso:country":"AU",
    "sg:address":"Cnr Blackburn Rd & Waverley Rd",
    "sg:city":"Mt Waverley",
    "sg:classifiers":[
        {
            "category":"Retail",
            "subcategory":"Car Wash",
            "type":"Services"
        }
    ],
    "sg:phone":"+61 439 369 592",
    "sg:postcode":"3149",
    "sg:province":"VIC",
    "sg:tags":[
        "truck",
        "cleaning"
    ],
    "wof:name":"Autobrite Carwash Pty Ltd",
    "wof:placetype":"venue"
},
  "geometry": {"coordinates":[145.14569091800001,-37.8867683411],"type":"Point"}
}