{
  "type": "Feature",
  "properties": {
    "addr:full":"194 Graceville Ave Graceville QLD 4075",
    "addr:housenumber":"194",
    "addr:postcode":"4075",
    "addr:street":"Graceville Ave",
    "iso:country":"AU",
    "sg:address":"194 Graceville Ave",
    "sg:city":"Graceville",
    "sg:classifiers":[
        {
            "category":"Professional",
            "subcategory":"Printing & Photocopies",
            "type":"Services"
        }
    ],
    "sg:phone":"+61 7 3379 3306",
    "sg:postcode":"4075",
    "sg:province":"QLD",
    "sg:tags":[
        "publishing",
        "desktop"
    ],
    "wof:name":"New Day Printing",
    "wof:placetype":"venue"
},
  "geometry": {"coordinates":[152.991455078,-27.5232486725],"type":"Point"}
}