{
  "type": "Feature",
  "properties": {
    "addr:full":"Shop 15, 1st Floor, Anthony Plaza, The Mall Darwin NT 0800",
    "addr:housenumber":"shop 15 1st floor",
    "addr:postcode":"nt 0800",
    "addr:street":"Anthony Plaza The Mall",
    "iso:country":"AU",
    "sg:address":"Shop 15, 1st Floor, Anthony Plaza, The Mall",
    "sg:city":"Darwin",
    "sg:classifiers":[
        {
            "category":"Shopping",
            "subcategory":"Clothing, Apparel, & Fashions",
            "type":"Retail Goods"
        }
    ],
    "sg:phone":"+61 8 8981 2830",
    "sg:postcode":"0800",
    "sg:province":"NT",
    "sg:tags":[
        "hire",
        "men's",
        "wear",
        "formal"
    ],
    "wof:name":"Just Formals",
    "wof:placetype":"venue"
},
  "geometry": {"coordinates":[130.84251403799999,-12.4638319016],"type":"Point"}
}