{
  "type": "Feature",
  "properties": {
    "iso:country":"AU",
    "sg:address":"77 Cavenagh St",
    "sg:city":"Darwin",
    "sg:classifiers":[
        {
            "category":"Retail",
            "subcategory":"Auto Rental",
            "type":"Services"
        }
    ],
    "sg:phone":"+61 8 8941 0300",
    "sg:postcode":"0800",
    "sg:province":"NT",
    "sg:tags":[
        "car",
        "hire",
        "minibus"
    ],
    "wof:name":"Europcar",
    "wof:placetype":"venue"
},
  "geometry": {"coordinates":[130.83833313,-12.4581165314],"type":"Point"}
}