{
  "type": "Feature",
  "properties": {
    "addr:full":"Level 4, 488 Bourke St Melbourne VIC 3000",
    "addr:housenumber":"488",
    "addr:postcode":"3000",
    "addr:street":"Bourke St",
    "iso:country":"AU",
    "sg:address":"Level 4, 488 Bourke St",
    "sg:city":"Melbourne",
    "sg:classifiers":[
        {
            "category":"Health Services",
            "subcategory":"Doctor",
            "type":"Services"
        }
    ],
    "sg:phone":"+61 3 9670 9385",
    "sg:postcode":"3000",
    "sg:province":"VIC",
    "sg:tags":[
        "medical",
        "practitioner"
    ],
    "wof:name":"Ramage Grant",
    "wof:placetype":"venue"
},
  "geometry": {"coordinates":[144.959182739,-37.8152656555],"type":"Point"}
}