{
  "type": "Feature",
  "properties": {
    "iso:country":"AU",
    "sg:address":"Level 7, 99 William St",
    "sg:city":"Melbourne",
    "sg:classifiers":[
        {
            "category":"Banks & Credit Unions",
            "subcategory":"Financial Services",
            "type":"Services"
        }
    ],
    "sg:phone":"+61 1300 130 775",
    "sg:postcode":"3000",
    "sg:province":"VIC",
    "sg:tags":[
        "loan",
        "finance",
        "mortgage"
    ],
    "wof:name":"Violet Home Loans Aust. Pty Ltd",
    "wof:placetype":"venue"
},
  "geometry": {"coordinates":[144.958694458,-37.8170318604],"type":"Point"}
}