{
  "type": "Feature",
  "properties": {
    "addr:full":"Suite 25, Lvl 3/ 22 Darley Rd Manly NSW 2095",
    "addr:housenumber":"/ 22",
    "addr:postcode":"2095",
    "addr:street":"Darley Rd",
    "iso:country":"AU",
    "sg:address":"Suite 25, Lvl 3/ 22 Darley Rd",
    "sg:city":"Manly",
    "sg:classifiers":[
        {
            "category":"Banks & Credit Unions",
            "subcategory":"Financial Services",
            "type":"Services"
        }
    ],
    "sg:phone":"+61 2 9976 0988",
    "sg:postcode":"2095",
    "sg:province":"NSW",
    "sg:tags":[
        "planning"
    ],
    "wof:name":"Davidson JJ",
    "wof:placetype":"venue"
},
  "geometry": {"coordinates":[151.28726196299999,-33.8000221252],"type":"Point"}
}