{
  "type": "Feature",
  "properties": {
    "addr:full":"346 Moreland Rd Brunswick West VIC 3055",
    "addr:housenumber":"346",
    "addr:postcode":"3055",
    "addr:street":"Moreland Rd",
    "iso:country":"AU",
    "sg:address":"346 Moreland Rd",
    "sg:city":"Brunswick West",
    "sg:classifiers":[
        {
            "category":"Personal",
            "subcategory":"Massage",
            "type":"Services"
        }
    ],
    "sg:phone":"+61 3 9386 8451",
    "sg:postcode":"3055",
    "sg:province":"VIC",
    "sg:tags":[
        "therapy"
    ],
    "wof:name":"Moreland Myotherapy & Acupuncture Clinic",
    "wof:placetype":"venue"
},
  "geometry": {"coordinates":[144.93801879899999,-37.7524757385],"type":"Point"}
}