{
  "type": "Feature",
  "properties": {
    "addr:full":"21 Station St Wallan VIC 3756",
    "addr:housenumber":"21",
    "addr:postcode":"3756",
    "addr:street":"Station St",
    "iso:country":"AU",
    "sg:address":"21 Station St",
    "sg:city":"Wallan",
    "sg:classifiers":[
        {
            "category":"Travel",
            "subcategory":"Hotels & Motels",
            "type":"Entertainment"
        }
    ],
    "sg:phone":"+61 3 5783 1324",
    "sg:postcode":"3756",
    "sg:province":"VIC",
    "sg:tags":[
        "accommodation"
    ],
    "wof:name":"Rattlers Hotel",
    "wof:placetype":"venue"
},
  "geometry": {"coordinates":[145.004425,-37.417686],"type":"Point"}
}