{
  "type": "Feature",
  "properties": {
    "addr:full":"Suite 201/ 39 Grafton St Coffs Harbour NSW 2450",
    "addr:housenumber":"/ 39",
    "addr:postcode":"2450",
    "addr:street":"Grafton St",
    "iso:country":"AU",
    "sg:address":"Suite 201/ 39 Grafton St",
    "sg:city":"Coffs Harbour",
    "sg:classifiers":[
        {
            "category":"Banks & Credit Unions",
            "subcategory":"Financial Services",
            "type":"Services"
        }
    ],
    "sg:phone":"+61 2 6651 5188",
    "sg:postcode":"2450",
    "sg:province":"NSW",
    "sg:tags":[
        "loan",
        "finance",
        "mortgage"
    ],
    "wof:name":"Mortgage Wisdom",
    "wof:placetype":"venue"
},
  "geometry": {"coordinates":[153.112686,-30.298246],"type":"Point"}
}