{
  "type": "Feature",
  "properties": {
    "addr:full":"44 Macquarie St Cowra NSW 2794",
    "addr:housenumber":"44",
    "addr:postcode":"2794",
    "addr:street":"Macquarie St",
    "iso:country":"AU",
    "sg:address":"44 Macquarie St",
    "sg:city":"Cowra",
    "sg:classifiers":[
        {
            "category":"Real Estate",
            "subcategory":"Real Estate Agent",
            "type":"Services"
        }
    ],
    "sg:phone":"+61 2 6342 6880",
    "sg:postcode":"2794",
    "sg:province":"NSW",
    "wof:name":"Penfolds First National",
    "wof:placetype":"venue"
},
  "geometry": {"coordinates":[148.68946838400001,-33.8313713074],"type":"Point"}
}