{
  "type": "Feature",
  "properties": {
    "addr:full":"Coles Complex Busselton WA 6280",
    "addr:postcode":"6280",
    "iso:country":"AU",
    "sg:address":"Coles Complex",
    "sg:city":"Busselton",
    "sg:classifiers":[
        {
            "category":"Food & Beverages",
            "subcategory":"Meat & Fish",
            "type":"Retail Goods"
        }
    ],
    "sg:phone":"+61 8 9754 1881",
    "sg:postcode":"6280",
    "sg:province":"WA",
    "sg:tags":[
        "seafood"
    ],
    "wof:name":"Codrocks On Kent",
    "wof:placetype":"venue"
},
  "geometry": {"coordinates":[115.344818115,-33.652141571],"type":"Point"}
}