{
  "type": "Feature",
  "properties": {
    "iso:country":"AU",
    "sg:address":"43 Docker St",
    "sg:city":"Wangaratta",
    "sg:classifiers":[
        {
            "category":"Health Services",
            "subcategory":"Doctor",
            "type":"Services"
        }
    ],
    "sg:phone":"+61 3 5721 4575",
    "sg:postcode":"3677",
    "sg:province":"VIC",
    "sg:tags":[
        "medical",
        "practitioner"
    ],
    "wof:name":"Thomas P R",
    "wof:placetype":"venue"
},
  "geometry": {"coordinates":[146.315963745,-36.3536911011],"type":"Point"}
}