{
  "type": "Feature",
  "properties": {
    "iso:country":"AU",
    "sg:address":"Unit 4, 25-27 Hocking St",
    "sg:city":"Coburg",
    "sg:classifiers":[
        {
            "category":"Professional",
            "subcategory":"Detective & Security Services",
            "type":"Services"
        }
    ],
    "sg:phone":"+61 3 9350 6077",
    "sg:postcode":"3058",
    "sg:province":"VIC",
    "sg:tags":[
        "wholesaler",
        "button",
        "mfrs",
        "buckle"
    ],
    "wof:name":"Travlon Trimmings",
    "wof:placetype":"venue"
},
  "geometry": {"coordinates":[144.95379638700001,-37.7275352478],"type":"Point"}
}