{
  "type": "Feature",
  "properties": {
    "addr:full":"PO Box 2 Vaucluse NSW 2030",
    "addr:postcode":"2030",
    "iso:country":"AU",
    "sg:address":"PO Box 2",
    "sg:city":"Vaucluse",
    "sg:classifiers":[
        {
            "category":"Utilities",
            "subcategory":"Electric",
            "type":"Services"
        }
    ],
    "sg:phone":"+61 418 645 077",
    "sg:postcode":"2030",
    "sg:province":"NSW",
    "sg:tags":[
        "electrical",
        "contractor"
    ],
    "wof:name":"J.S.B.S. Electrical Pty Ltd",
    "wof:placetype":"venue"
},
  "geometry": {"coordinates":[151.28192138700001,-33.8597106934],"type":"Point"}
}