{
  "type": "Feature",
  "properties": {
    "addr:full":"Ponds Rd Gilgai NSW 2360",
    "addr:postcode":"2360",
    "addr:street":"Ponds Rd",
    "iso:country":"AU",
    "sg:address":"Ponds Rd",
    "sg:city":"Gilgai",
    "sg:classifiers":[
        {
            "category":"Transit Center",
            "subcategory":"Freight",
            "type":"Transportation"
        }
    ],
    "sg:phone":"+61 2 6723 1350",
    "sg:postcode":"2360",
    "sg:province":"NSW",
    "sg:tags":[
        "turner",
        "wood"
    ],
    "wof:name":"New England Woodturning Supplies",
    "wof:placetype":"venue"
},
  "geometry": {"coordinates":[151.14642334000001,-29.8788528442],"type":"Point"}
}