{
  "type": "Feature",
  "properties": {
    "iso:country":"AU",
    "sg:address":"23 Clarke St",
    "sg:city":"Brunswick",
    "sg:classifiers":[
        {
            "category":"Personal",
            "subcategory":"Massage",
            "type":"Services"
        }
    ],
    "sg:phone":"+61 3 9380 8523",
    "sg:postcode":"3056",
    "sg:province":"VIC",
    "sg:tags":[
        "therapy"
    ],
    "wof:name":"McElroy Karen",
    "wof:placetype":"venue"
},
  "geometry": {"coordinates":[144.97418212900001,-37.7736625671],"type":"Point"}
}