{
  "type": "Feature",
  "properties": {
    "iso:country":"AU",
    "sg:address":"235 Barrett Rd",
    "sg:city":"Mahogany Creek",
    "sg:classifiers":[
        {
            "category":"Building & Trades",
            "subcategory":"Construction",
            "type":"Services"
        }
    ],
    "sg:phone":"+61 8 9298 8777",
    "sg:postcode":"6072",
    "sg:province":"WA",
    "sg:tags":[
        "earth",
        "excavating",
        "moving",
        "contractor"
    ],
    "wof:name":"Sheardown R S & K S",
    "wof:placetype":"venue"
},
  "geometry": {"coordinates":[116.125252,-31.902266],"type":"Point"}
}