{
  "type": "Feature",
  "properties": {
    "iso:country":"AU",
    "sg:address":"27 Playford Ave",
    "sg:city":"Whyalla Playford",
    "sg:classifiers":[
        {
            "category":"Autos & Motor Vehicles",
            "subcategory":"Auto Supplies",
            "type":"Retail Goods"
        }
    ],
    "sg:phone":"+61 8 8645 2982",
    "sg:postcode":"5600",
    "sg:province":"SA",
    "sg:tags":[
        "camper-trailers",
        "caravan",
        "equipment"
    ],
    "wof:name":"Whyalla Camping Supplies",
    "wof:placetype":"venue"
},
  "geometry": {"coordinates":[137.56346099999999,-33.034203],"type":"Point"}
}