{
  "type": "Feature",
  "properties": {
    "addr:full":"Lvl 1 Arcade Broadbeach Next to Medicare Broadbeach QLD 4218",
    "addr:postcode":"4218",
    "iso:country":"AU",
    "sg:address":"Lvl 1",
    "sg:city":"Arcade Broadbeach Next to Medicare Broadbeach",
    "sg:classifiers":[
        {
            "category":"Personal",
            "subcategory":"Beauty Salon",
            "type":"Services"
        }
    ],
    "sg:phone":"+61 7 5538 9724",
    "sg:postcode":"4218",
    "sg:province":"QLD",
    "wof:name":"Ella Bache Pacific Fair",
    "wof:placetype":"venue"
},
  "geometry": {"coordinates":[153.429397583,-28.0263690948],"type":"Point"}
}