{
  "type": "Feature",
  "properties": {
    "iso:country":"AU",
    "sg:address":"23 Tashinny Rd",
    "sg:city":"Toorak",
    "sg:classifiers":[
        {
            "category":"Food & Beverages",
            "subcategory":"Fruits & Vegetables",
            "type":"Retail Goods"
        }
    ],
    "sg:phone":"+61 3 9824 2194",
    "sg:postcode":"3142",
    "sg:province":"VIC",
    "sg:tags":[
        "consultant",
        "catering"
    ],
    "wof:name":"Natasha Carne",
    "wof:placetype":"venue"
},
  "geometry": {"coordinates":[145.006317139,-37.8445129395],"type":"Point"}
}