{
  "type": "Feature",
  "properties": {
    "addr:full":"3 Birchwood Crt Bairnsdale VIC 3875",
    "addr:housenumber":"3",
    "addr:postcode":"3875",
    "addr:street":"Birchwood Crt",
    "iso:country":"AU",
    "sg:address":"3 Birchwood Crt",
    "sg:city":"Bairnsdale",
    "sg:classifiers":[
        {
            "category":"Home & Garden",
            "subcategory":"Building Materials",
            "type":"Retail Goods"
        }
    ],
    "sg:phone":"+61 3 5153 0058",
    "sg:postcode":"3875",
    "sg:province":"VIC",
    "sg:tags":[
        "lawn",
        "cutting",
        "maintenance"
    ],
    "wof:name":"Will Garden Riviera",
    "wof:placetype":"venue"
},
  "geometry": {"coordinates":[147.600067139,-37.8203697205],"type":"Point"}
}