{
  "type": "Feature",
  "properties": {
    "iso:country":"AU",
    "sg:address":"73 Louisa Rd",
    "sg:city":"Birchgrove",
    "sg:classifiers":[
        {
            "category":"Travel",
            "subcategory":"Travel Agent",
            "type":"Entertainment"
        }
    ],
    "sg:phone":"+61 2 9555 7216",
    "sg:postcode":"2041",
    "sg:province":"NSW",
    "sg:tags":[
        "tour",
        "holiday",
        "adventure"
    ],
    "wof:name":"Sydney On The Run",
    "wof:placetype":"venue"
},
  "geometry": {"coordinates":[151.182343,-33.848129],"type":"Point"}
}