{
  "type": "Feature",
  "properties": {
    "iso:country":"AU",
    "sg:address":"58 Neridah St",
    "sg:city":"Chatswood",
    "sg:classifiers":[
        {
            "category":"Real Estate",
            "subcategory":"Real Estate Agent",
            "type":"Services"
        }
    ],
    "sg:phone":"+61 2 9413 3288",
    "sg:postcode":"2067",
    "sg:province":"NSW",
    "wof:name":"Valiant Real Estate",
    "wof:placetype":"venue"
},
  "geometry": {"coordinates":[151.187225342,-33.7961730957],"type":"Point"}
}