{
  "type": "Feature",
  "properties": {
    "addr:full":"241 Payneham Rd Joslin SA 5070",
    "addr:housenumber":"241",
    "addr:postcode":"5070",
    "addr:street":"Payneham Rd",
    "iso:country":"AU",
    "sg:address":"241 Payneham Rd",
    "sg:city":"Joslin",
    "sg:classifiers":[
        {
            "category":"Professional",
            "subcategory":"Art Services",
            "type":"Services"
        }
    ],
    "sg:phone":"+61 8 8362 8024",
    "sg:postcode":"5070",
    "sg:province":"SA",
    "sg:tags":[
        "decorator",
        "painter"
    ],
    "wof:name":"A & P Crisci Painters & Decorators",
    "wof:placetype":"venue"
},
  "geometry": {"coordinates":[138.63267517099999,-34.9036445618],"type":"Point"}
}