{
  "type": "Feature",
  "properties": {
    "addr:full":"7 Rothwell Ave Ingle Farm SA 5098",
    "addr:housenumber":"7",
    "addr:postcode":"5098",
    "addr:street":"Rothwell Ave",
    "iso:country":"AU",
    "sg:address":"7 Rothwell Ave",
    "sg:city":"Ingle Farm",
    "sg:classifiers":[
        {
            "category":"Education",
            "subcategory":"School",
            "type":"Public Place"
        }
    ],
    "sg:phone":"+61 8 8264 7498",
    "sg:postcode":"5098",
    "sg:province":"SA",
    "sg:tags":[
        "state",
        "except",
        "nsw"
    ],
    "wof:name":"North Ingle School",
    "wof:placetype":"venue"
},
  "geometry": {"coordinates":[138.645263672,-34.8181724548],"type":"Point"}
}