{
  "type": "Feature",
  "properties": {
    "addr:full":"Cradock Rd Hawker SA 5434",
    "addr:postcode":"5434",
    "addr:street":"Cradock Rd",
    "iso:country":"AU",
    "sg:address":"Cradock Rd",
    "sg:city":"Hawker",
    "sg:classifiers":[
        {
            "category":"Health Services",
            "subcategory":"Doctor",
            "type":"Services"
        }
    ],
    "sg:phone":"+61 8 8648 4172",
    "sg:postcode":"5434",
    "sg:province":"SA",
    "sg:tags":[
        "medical",
        "practitioner"
    ],
    "wof:name":"Hawker Medical Centre",
    "wof:placetype":"venue"
},
  "geometry": {"coordinates":[138.42202758799999,-31.8865623474],"type":"Point"}
}