{
  "type": "Feature",
  "properties": {
    "addr:full":"6 Greaves St Pakenham VIC 3810",
    "addr:housenumber":"6",
    "addr:postcode":"3810",
    "addr:street":"Greaves St",
    "iso:country":"AU",
    "sg:address":"6 Greaves St",
    "sg:city":"Pakenham",
    "sg:classifiers":[
        {
            "category":"Building & Trades",
            "subcategory":"Construction",
            "type":"Services"
        }
    ],
    "sg:phone":"+61 409 232 236",
    "sg:postcode":"3810",
    "sg:province":"VIC",
    "sg:tags":[
        "earth",
        "excavating",
        "moving",
        "contractor"
    ],
    "wof:name":"Pakenham Dingo Hire",
    "wof:placetype":"venue"
},
  "geometry": {"coordinates":[145.46794128400001,-38.0687408447],"type":"Point"}
}