{
  "type": "Feature",
  "properties": {
    "addr:full":"69 Belmore Rd Punchbowl NSW 2196",
    "addr:housenumber":"69",
    "addr:postcode":"2196",
    "addr:street":"Belmore Rd",
    "iso:country":"AU",
    "sg:address":"69 Belmore Rd",
    "sg:city":"Punchbowl",
    "sg:classifiers":[
        {
            "category":"Autos & Motor Vehicles",
            "subcategory":"Automobile Sales",
            "type":"Retail Goods"
        }
    ],
    "sg:phone":"+61 2 9584 9610",
    "sg:postcode":"2196",
    "sg:province":"NSW",
    "sg:tags":[
        "car",
        "used"
    ],
    "wof:name":"Sam Sead Autos",
    "wof:placetype":"venue"
},
  "geometry": {"coordinates":[151.05491599999999,-33.937111],"type":"Point"}
}