{
  "type": "Feature",
  "properties": {
    "iso:country":"AU",
    "sg:address":"Shp 5/ 62 Grafton St",
    "sg:city":"Cairns",
    "sg:classifiers":[
        {
            "category":"Manufacturing",
            "subcategory":"Jewelry",
            "type":"Manufacturing & Wholesale Goods"
        }
    ],
    "sg:phone":"+61 7 4031 1703",
    "sg:postcode":"4870",
    "sg:province":"QLD",
    "sg:tags":[
        "mfrg",
        "jeweller"
    ],
    "wof:name":"Gem Stone Creations",
    "wof:placetype":"venue"
},
  "geometry": {"coordinates":[145.77636718799999,-16.9244823456],"type":"Point"}
}