{
  "type": "Feature",
  "properties": {
    "iso:country":"AU",
    "sg:address":"154 Mary St",
    "sg:city":"Gympie",
    "sg:classifiers":[
        {
            "category":"Shopping",
            "subcategory":"Clothing, Apparel, & Fashions",
            "type":"Retail Goods"
        }
    ],
    "sg:phone":"+61 7 5483 6999",
    "sg:postcode":"4570",
    "sg:province":"QLD",
    "sg:tags":[
        "lady",
        "wear"
    ],
    "wof:name":"Katies Fashions (Aust) Pty Ltd",
    "wof:placetype":"venue"
},
  "geometry": {"coordinates":[152.661178589,-26.1897907257],"type":"Point"}
}