{
  "type": "Feature",
  "properties": {
    "addr:full":"1/ 45 Titan Drv Carrum Downs VIC 3201",
    "addr:housenumber":"/ 45",
    "addr:postcode":"3201",
    "addr:street":"Titan Drv",
    "iso:country":"AU",
    "sg:address":"1/ 45 Titan Drv",
    "sg:city":"Carrum Downs",
    "sg:classifiers":[
        {
            "category":"Shopping",
            "subcategory":"Pets & Pet Supplies",
            "type":"Retail Goods"
        }
    ],
    "sg:phone":"+61 3 9775 1334",
    "sg:postcode":"3201",
    "sg:province":"VIC",
    "sg:tags":[
        "shop",
        "supplier"
    ],
    "wof:name":"Critter Comfort",
    "wof:placetype":"venue"
},
  "geometry": {"coordinates":[145.16738899999999,-38.099159],"type":"Point"}
}