{
  "type": "Feature",
  "properties": {
    "addr:full":"91 Shoalhaven Rd Sylvania Waters NSW 2224",
    "addr:housenumber":"91",
    "addr:postcode":"2224",
    "addr:street":"Shoalhaven Rd",
    "iso:country":"AU",
    "sg:address":"91 Shoalhaven Rd",
    "sg:city":"Sylvania Waters",
    "sg:classifiers":[
        {
            "category":"Professional",
            "subcategory":"Business Services",
            "type":"Services"
        }
    ],
    "sg:phone":"+61 2 9522 2062",
    "sg:postcode":"2224",
    "sg:province":"NSW",
    "sg:tags":[
        "consultant",
        "promoter",
        "entertainment"
    ],
    "wof:name":"Triple Treat Promotions Pty Ltd",
    "wof:placetype":"venue"
},
  "geometry": {"coordinates":[151.10786438,-34.0207824707],"type":"Point"}
}