{
  "type": "Feature",
  "properties": {
    "iso:country":"AU",
    "sg:address":"245 Rawson St",
    "sg:city":"Auburn",
    "sg:classifiers":[
        {
            "category":"Wholesale",
            "subcategory":"Machinery & Supplies",
            "type":"Manufacturing & Wholesale Goods"
        }
    ],
    "sg:phone":"+61 2 9748 4533",
    "sg:postcode":"2144",
    "sg:province":"NSW",
    "sg:tags":[
        "belting",
        "mfrs"
    ],
    "wof:name":"TotalRubber Ltd",
    "wof:placetype":"venue"
},
  "geometry": {"coordinates":[151.02656555199999,-33.841129303],"type":"Point"}
}