{
  "type": "Feature",
  "properties": {
    "addr:full":"Unit 8, Monaro Court/42 Stephens Rd Queanbeyan NSW 2620",
    "addr:housenumber":"42",
    "addr:postcode":"2620",
    "addr:street":"Monaro;Stephens Rd",
    "iso:country":"AU",
    "sg:address":"Unit 8, Monaro Court/42 Stephens Rd",
    "sg:city":"Queanbeyan",
    "sg:classifiers":[
        {
            "category":"Retail",
            "subcategory":"Auto Repair",
            "type":"Services"
        }
    ],
    "sg:phone":"+61 2 6297 5701",
    "sg:postcode":"2620",
    "sg:province":"NSW",
    "sg:tags":[
        "electrical"
    ],
    "wof:name":"Monaro Auto Electrics",
    "wof:placetype":"venue"
},
  "geometry": {"coordinates":[149.20835876500001,-35.3482933044],"type":"Point"}
}