{
  "type": "Feature",
  "properties": {
    "iso:country":"AU",
    "sg:address":"Dulwich Centre 5a Stuart Rd",
    "sg:city":"Dulwich",
    "sg:classifiers":[
        {
            "category":"Personal",
            "subcategory":"Beauty Salon",
            "type":"Services"
        }
    ],
    "sg:phone":"+61 8 8331 8004",
    "sg:postcode":"5065",
    "sg:province":"SA",
    "sg:tags":[
        "hairdresser"
    ],
    "wof:name":"Stuart Road Hairdresser",
    "wof:placetype":"venue"
},
  "geometry": {"coordinates":[138.631515503,-34.9355659485],"type":"Point"}
}