{
  "type": "Feature",
  "properties": {
    "addr:full":"302 Bell St Heidelberg West VIC 3081",
    "addr:housenumber":"302",
    "addr:postcode":"3081",
    "addr:street":"Bell St",
    "iso:country":"AU",
    "sg:address":"302 Bell St",
    "sg:city":"Heidelberg West",
    "sg:classifiers":[
        {
            "category":"Home & Garden",
            "subcategory":"Carpets & Floor Coverings",
            "type":"Retail Goods"
        }
    ],
    "sg:phone":"+61 3 9457 7755",
    "sg:postcode":"3081",
    "sg:province":"VIC",
    "sg:tags":[
        "wood"
    ],
    "wof:name":"Mr Timber Floors",
    "wof:placetype":"venue"
},
  "geometry": {"coordinates":[145.04263305699999,-37.7499542236],"type":"Point"}
}