{
  "type": "Feature",
  "properties": {
    "iso:country":"AU",
    "sg:address":"28 High-Tech Drv",
    "sg:city":"Kunda Park",
    "sg:classifiers":[
        {
            "category":"Building & Trades",
            "subcategory":"Construction",
            "type":"Services"
        }
    ],
    "sg:phone":"+61 7 5445 6030",
    "sg:postcode":"4556",
    "sg:province":"QLD",
    "sg:tags":[
        "fitting",
        "line",
        "electric",
        "power"
    ],
    "wof:name":"Tenix Alliance",
    "wof:placetype":"venue"
},
  "geometry": {"coordinates":[153.038208008,-26.6630401611],"type":"Point"}
}