{
  "type": "Feature",
  "properties": {
    "iso:country":"AU",
    "sg:address":"173 Lesmurdie Rd",
    "sg:city":"Lesmurdie",
    "sg:classifiers":[
        {
            "category":"Travel",
            "subcategory":"Hostel",
            "type":"Entertainment"
        }
    ],
    "sg:phone":"+61 8 9291 6314",
    "sg:postcode":"6076",
    "sg:province":"WA",
    "sg:tags":[
        "home"
    ],
    "wof:name":"Sisters Of Mercy West Perth Congregation",
    "wof:placetype":"venue"
},
  "geometry": {"coordinates":[116.052856445,-31.9979763031],"type":"Point"}
}