{
  "type": "Feature",
  "properties": {
    "addr:full":"7 Wadell Rd Gympie QLD 4570",
    "addr:housenumber":"7",
    "addr:postcode":"4570",
    "addr:street":"Wadell Rd",
    "iso:country":"AU",
    "sg:address":"7 Wadell Rd",
    "sg:city":"Gympie",
    "sg:classifiers":[
        {
            "category":"Home & Garden",
            "subcategory":"Garden Supply",
            "type":"Retail Goods"
        }
    ],
    "sg:phone":"+61 7 5482 1911",
    "sg:postcode":"4570",
    "sg:province":"QLD",
    "sg:tags":[
        "landscape"
    ],
    "wof:name":"Gympie Sand Gravel & Landscaping Supplies",
    "wof:placetype":"venue"
},
  "geometry": {"coordinates":[152.64698791500001,-26.169675827],"type":"Point"}
}