{
  "type": "Feature",
  "properties": {
    "addr:full":"222 Tomakin Rd Mogo NSW 2536",
    "addr:housenumber":"222",
    "addr:postcode":"2536",
    "addr:street":"Tomakin Rd",
    "iso:country":"AU",
    "sg:address":"222 Tomakin Rd",
    "sg:city":"Mogo",
    "sg:classifiers":[
        {
            "category":"Communications",
            "subcategory":"News Services",
            "type":"Services"
        }
    ],
    "sg:phone":"+61 2 4474 4930",
    "sg:postcode":"2536",
    "sg:province":"NSW",
    "sg:tags":[
        "information",
        "tourist",
        "attractions"
    ],
    "wof:name":"Mogo Zoo",
    "wof:placetype":"venue"
},
  "geometry": {"coordinates":[150.15846252399999,-35.7941207886],"type":"Point"}
}