{
  "type": "Feature",
  "properties": {
    "iso:country":"AU",
    "sg:address":"\"Lewana\" McIntyre Rd",
    "sg:city":"Inverleigh",
    "sg:classifiers":[
        {
            "category":"Commercial Area",
            "type":"Public Place"
        }
    ],
    "sg:phone":"+61 3 5265 1461",
    "sg:postcode":"3321",
    "sg:province":"VIC",
    "sg:tags":[
        "heavy",
        "carrier"
    ],
    "wof:name":"Bone R E & I J",
    "wof:placetype":"venue"
},
  "geometry": {"coordinates":[143.89167800000001,-38.137218],"type":"Point"}
}