{
  "type": "Feature",
  "properties": {
    "addr:full":"Shed 2, 17 Page St Kunda Park QLD 4556",
    "addr:housenumber":"17",
    "addr:postcode":"4556",
    "addr:street":"Page St",
    "iso:country":"AU",
    "sg:address":"Shed 2, 17 Page St",
    "sg:city":"Kunda Park",
    "sg:classifiers":[
        {
            "category":"Wholesale",
            "subcategory":"Construction Materials",
            "type":"Manufacturing & Wholesale Goods"
        }
    ],
    "sg:phone":"+61 7 5450 1922",
    "sg:postcode":"4556",
    "sg:province":"QLD",
    "sg:tags":[
        "protective",
        "coating"
    ],
    "wof:name":"Coastline Distributors",
    "wof:placetype":"venue"
},
  "geometry": {"coordinates":[153.0365448,-26.6606464386],"type":"Point"}
}