{
  "type": "Feature",
  "properties": {
    "iso:country":"AU",
    "sg:address":"47 Park Rd",
    "sg:city":"Cabramatta",
    "sg:classifiers":[
        {
            "category":"Food & Beverages",
            "subcategory":"Bakery",
            "type":"Retail Goods"
        }
    ],
    "sg:phone":"+61 2 9727 4008",
    "sg:postcode":"2166",
    "sg:province":"NSW",
    "sg:tags":[
        "cake",
        "shop",
        "pastry"
    ],
    "wof:name":"Maylan Cake Shop",
    "wof:placetype":"venue"
},
  "geometry": {"coordinates":[150.93695068400001,-33.8937530518],"type":"Point"}
}