{
  "type": "Feature",
  "properties": {
    "addr:full":"163 Palmerin St Warwick QLD 4370",
    "addr:housenumber":"163",
    "addr:postcode":"4370",
    "addr:street":"Palmerin St",
    "iso:country":"AU",
    "sg:address":"163 Palmerin St",
    "sg:city":"Warwick",
    "sg:classifiers":[
        {
            "category":"Education",
            "subcategory":"School",
            "type":"Public Place"
        }
    ],
    "sg:phone":"+61 7 4661 1872",
    "sg:postcode":"4370",
    "sg:province":"QLD",
    "sg:tags":[
        "co-educational"
    ],
    "wof:name":"St Mary's Primary School",
    "wof:placetype":"venue"
},
  "geometry": {"coordinates":[152.031906128,-28.2192726135],"type":"Point"}
}