{
  "type": "Feature",
  "properties": {
    "iso:country":"AU",
    "sg:address":"B18 9 Chandler St",
    "sg:city":"Belconnen",
    "sg:classifiers":[
        {
            "category":"Education",
            "subcategory":"Special Training",
            "type":"Public Place"
        }
    ],
    "sg:phone":"+61 2 6253 3558",
    "sg:postcode":"2617",
    "sg:province":"ACT",
    "sg:tags":[
        "development"
    ],
    "wof:name":"Entertrain",
    "wof:placetype":"venue"
},
  "geometry": {"coordinates":[149.06877136200001,-35.2375068665],"type":"Point"}
}