{
  "type": "Feature",
  "properties": {
    "addr:full":"Suite G13 Paspalis Centrepoint 48-50 Smith St Mall Darwin NT 0800",
    "addr:housenumber":"48-50",
    "addr:postcode":"nt 0800",
    "addr:street":"Smith St Mall",
    "iso:country":"AU",
    "sg:address":"Suite G13 Paspalis Centrepoint 48-50 Smith St",
    "sg:city":"Mall Darwin",
    "sg:classifiers":[
        {
            "category":"Professional",
            "subcategory":"Accounting & Tax Preparation",
            "type":"Services"
        }
    ],
    "sg:phone":"+61 8 8950 3080",
    "sg:postcode":"0800",
    "sg:province":"NT",
    "sg:tags":[
        "accountant",
        "auditor"
    ],
    "wof:name":"Triple A Accounting",
    "wof:placetype":"venue"
},
  "geometry": {"coordinates":[130.84141540499999,-12.462931633],"type":"Point"}
}