{
  "type": "Feature",
  "properties": {
    "addr:full":"14 Tadema Crs Eltham VIC 3095",
    "addr:housenumber":"14",
    "addr:postcode":"3095",
    "addr:street":"Tadema Crs",
    "iso:country":"AU",
    "sg:address":"14 Tadema Crs",
    "sg:city":"Eltham",
    "sg:classifiers":[
        {
            "category":"Conference Center",
            "type":"Public Place"
        }
    ],
    "sg:phone":"+61 3 9439 6814",
    "sg:postcode":"3095",
    "sg:province":"VIC",
    "sg:tags":[
        "venue",
        "convention"
    ],
    "wof:name":"Satchels & Such",
    "wof:placetype":"venue"
},
  "geometry": {"coordinates":[145.150115967,-37.7145385742],"type":"Point"}
}