{
  "type": "Feature",
  "properties": {
    "addr:full":"357 Canterbury Rd Forest Hill VIC 3131",
    "addr:housenumber":"357",
    "addr:postcode":"3131",
    "addr:street":"Canterbury Rd",
    "iso:country":"AU",
    "sg:address":"357 Canterbury Rd",
    "sg:city":"Forest Hill",
    "sg:classifiers":[
        {
            "category":"Retail",
            "subcategory":"Veterinary Services",
            "type":"Services"
        }
    ],
    "sg:phone":"+61 3 9873 1544",
    "sg:postcode":"3131",
    "sg:province":"VIC",
    "sg:tags":[
        "surgeon"
    ],
    "wof:name":"Begg Meredith Dr",
    "wof:placetype":"venue"
},
  "geometry": {"coordinates":[145.18150329599999,-37.8356018066],"type":"Point"}
}