{
  "type": "Feature",
  "properties": {
    "iso:country":"AU",
    "sg:address":"Lvl 4/ 122 Walker St",
    "sg:city":"North Sydney",
    "sg:classifiers":[
        {
            "category":"Utilities",
            "type":"Services"
        }
    ],
    "sg:phone":"+61 2 8923 8923",
    "sg:postcode":"2060",
    "sg:province":"NSW",
    "sg:tags":[
        "management",
        "trust"
    ],
    "wof:name":"Century Funds Management Ltd",
    "wof:placetype":"venue"
},
  "geometry": {"coordinates":[151.208984375,-33.8374710083],"type":"Point"}
}