{
  "type": "Feature",
  "properties": {
    "addr:full":"39 Hillcrest Pde Highfields NSW 2289",
    "addr:housenumber":"39",
    "addr:postcode":"2289",
    "addr:street":"Hillcrest Pde",
    "iso:country":"AU",
    "sg:address":"39 Hillcrest Pde",
    "sg:city":"Highfields",
    "sg:classifiers":[
        {
            "category":"Sports & Exercise",
            "subcategory":"Gym",
            "type":"Entertainment"
        }
    ],
    "sg:phone":"+61 2 4943 4320",
    "sg:postcode":"2289",
    "sg:province":"NSW",
    "sg:tags":[
        "health",
        "fitness"
    ],
    "wof:name":"Waratah Physical Culture Club",
    "wof:placetype":"venue"
},
  "geometry": {"coordinates":[151.715866089,-32.9551925659],"type":"Point"}
}