{
  "type": "Feature",
  "properties": {
    "addr:full":"32 Henry St Hawthorn VIC 3122",
    "addr:housenumber":"32",
    "addr:postcode":"3122",
    "addr:street":"Henry St",
    "iso:country":"AU",
    "sg:address":"32 Henry St",
    "sg:city":"Hawthorn",
    "sg:classifiers":[
        {
            "category":"Education",
            "subcategory":"Music School",
            "type":"Public Place"
        }
    ],
    "sg:phone":"+61 3 9419 0316",
    "sg:postcode":"3122",
    "sg:province":"VIC",
    "sg:tags":[
        "singing",
        "teacher"
    ],
    "wof:name":"Pure Music Singing School",
    "wof:placetype":"venue"
},
  "geometry": {"coordinates":[145.04219055199999,-37.8226966858],"type":"Point"}
}