{
  "type": "Feature",
  "properties": {
    "addr:full":"131 Old Ipswich Rd Riverview QLD 4303",
    "addr:housenumber":"131",
    "addr:postcode":"4303",
    "addr:street":"Old Ipswich Rd",
    "iso:country":"AU",
    "sg:address":"131 Old Ipswich Rd",
    "sg:city":"Riverview",
    "sg:classifiers":[
        {
            "category":"Education",
            "subcategory":"School",
            "type":"Public Place"
        }
    ],
    "sg:phone":"+61 7 3816 6111",
    "sg:postcode":"4303",
    "sg:province":"QLD",
    "sg:tags":[
        "state",
        "except",
        "nsw"
    ],
    "wof:name":"Riverview Primary",
    "wof:placetype":"venue"
},
  "geometry": {"coordinates":[152.84713745100001,-27.6033344269],"type":"Point"}
}