{
  "type": "Feature",
  "properties": {
    "addr:full":"3 Slough Rd Altona VIC 3018",
    "addr:housenumber":"3",
    "addr:postcode":"3018",
    "addr:street":"Slough Rd",
    "iso:country":"AU",
    "sg:address":"3 Slough Rd",
    "sg:city":"Altona",
    "sg:classifiers":[
        {
            "category":"Shopping",
            "subcategory":"Stationery & Office Supplies",
            "type":"Retail Goods"
        }
    ],
    "sg:phone":"+61 3 9398 5611",
    "sg:postcode":"3018",
    "sg:province":"VIC",
    "sg:tags":[
        "packaging",
        "equipment",
        "sealing",
        "filling"
    ],
    "wof:name":"Webomatic",
    "wof:placetype":"venue"
},
  "geometry": {"coordinates":[144.809616089,-37.8583068848],"type":"Point"}
}