{
  "type": "Feature",
  "properties": {
    "iso:country":"AU",
    "sg:address":"179 Forest Rd",
    "sg:city":"Hurstville",
    "sg:classifiers":[
        {
            "category":"Fast Food",
            "type":"Food & Drink"
        }
    ],
    "sg:phone":"+61 2 9579 1053",
    "sg:postcode":"2220",
    "sg:province":"NSW",
    "sg:tags":[
        "away",
        "take"
    ],
    "wof:name":"Japanise Kitchen Kazuki",
    "wof:placetype":"venue"
},
  "geometry": {"coordinates":[151.10317993199999,-33.9671974182],"type":"Point"}
}