{
  "type": "Feature",
  "properties": {
    "iso:country":"AU",
    "sg:address":"15 Lawson Crs",
    "sg:city":"Coffs Harbour",
    "sg:classifiers":[
        {
            "category":"Manufacturing",
            "subcategory":"Chemicals & Compounds",
            "type":"Manufacturing & Wholesale Goods"
        }
    ],
    "sg:phone":"+61 2 6651 3577",
    "sg:postcode":"2450",
    "sg:province":"NSW",
    "sg:tags":[
        "electroplating"
    ],
    "wof:name":"Coffs Harbour Exchange Bumper Service",
    "wof:placetype":"venue"
},
  "geometry": {"coordinates":[153.115158,-30.29701],"type":"Point"}
}