{
  "type": "Feature",
  "properties": {
    "addr:full":"3270 Mt Lindesay Hwy Browns Plains QLD 4118",
    "addr:housenumber":"3270",
    "addr:postcode":"4118",
    "addr:street":"Mt Lindesay Hwy",
    "iso:country":"AU",
    "sg:address":"3270 Mt Lindesay Hwy",
    "sg:city":"Browns Plains",
    "sg:classifiers":[
        {
            "category":"Shopping",
            "subcategory":"Clothing, Apparel, & Fashions",
            "type":"Retail Goods"
        }
    ],
    "sg:phone":"+61 7 3800 8776",
    "sg:postcode":"4118",
    "sg:province":"QLD",
    "sg:tags":[
        "recycled",
        "clothing"
    ],
    "wof:name":"Lifeline Brisbane Bargain Centre",
    "wof:placetype":"venue"
},
  "geometry": {"coordinates":[153.03155517600001,-27.6784858704],"type":"Point"}
}