{
  "type": "Feature",
  "properties": {
    "iso:country":"AU",
    "sg:address":"4 Maranoa Pl",
    "sg:city":"Wahroonga",
    "sg:classifiers":[
        {
            "category":"Shopping",
            "subcategory":"Discount & Variety Stores",
            "type":"Retail Goods"
        }
    ],
    "sg:phone":"+61 2 9489 7650",
    "sg:postcode":"2076",
    "sg:province":"NSW",
    "sg:tags":[
        "information",
        "cooking",
        "class"
    ],
    "wof:name":"Cookeasy",
    "wof:placetype":"venue"
},
  "geometry": {"coordinates":[151.14187622099999,-33.7109642029],"type":"Point"}
}