{
  "type": "Feature",
  "properties": {
    "addr:full":"92 King William Rd Goodwood SA 5034",
    "addr:housenumber":"92",
    "addr:postcode":"5034",
    "addr:street":"King William Rd",
    "iso:country":"AU",
    "sg:address":"92 King William Rd",
    "sg:city":"Goodwood",
    "sg:classifiers":[
        {
            "category":"Health Services",
            "subcategory":"Optometrist",
            "type":"Services"
        }
    ],
    "sg:phone":"+61 1300 116 116",
    "sg:postcode":"5034",
    "sg:province":"SA",
    "wof:name":"Trimper Merv",
    "wof:placetype":"venue"
},
  "geometry": {"coordinates":[138.59967040999999,-34.9516716003],"type":"Point"}
}