{
  "type": "Feature",
  "properties": {
    "addr:full":"635 Ipswich Rd Annerley QLD 4103",
    "addr:housenumber":"635",
    "addr:postcode":"4103",
    "addr:street":"Ipswich Rd",
    "iso:country":"AU",
    "sg:address":"635 Ipswich Rd",
    "sg:city":"Annerley",
    "sg:classifiers":[
        {
            "category":"Travel",
            "subcategory":"Travel Agent",
            "type":"Entertainment"
        }
    ],
    "sg:phone":"+61 7 3892 1199",
    "sg:postcode":"4103",
    "sg:province":"QLD",
    "sg:tags":[
        "consultant"
    ],
    "wof:name":"TDH Travel",
    "wof:placetype":"venue"
},
  "geometry": {"coordinates":[153.02952575699999,-27.5174674988],"type":"Point"}
}