{
  "type": "Feature",
  "properties": {
    "iso:country":"AU",
    "sg:address":"Abbotsford Rd & Burrows St",
    "sg:city":"Mayne",
    "sg:classifiers":[
        {
            "category":"Autos & Motor Vehicles",
            "subcategory":"Fuel & Gas Station",
            "type":"Retail Goods"
        }
    ],
    "sg:phone":"+61 7 3252 3769",
    "sg:postcode":"4006",
    "sg:province":"QLD",
    "wof:name":"Mobil Oil Australia Pty Ltd",
    "wof:placetype":"venue"
},
  "geometry": {"coordinates":[153.0390625,-27.4408187866],"type":"Point"}
}