{
  "type": "Feature",
  "properties": {
    "addr:full":"16 High St Willunga SA 5172",
    "addr:housenumber":"16",
    "addr:postcode":"5172",
    "addr:street":"High St",
    "iso:country":"AU",
    "sg:address":"16 High St",
    "sg:city":"Willunga",
    "sg:classifiers":[
        {
            "category":"Food & Beverages",
            "subcategory":"Bakery",
            "type":"Retail Goods"
        }
    ],
    "sg:phone":"+61 8 8556 2323",
    "sg:postcode":"5172",
    "sg:province":"SA",
    "sg:tags":[
        "cake",
        "shop",
        "pastry"
    ],
    "wof:name":"Willunga Bakery",
    "wof:placetype":"venue"
},
  "geometry": {"coordinates":[138.55555725100001,-35.2727050781],"type":"Point"}
}