{
  "type": "Feature",
  "properties": {
    "iso:country":"AU",
    "sg:address":"117 Sturt St",
    "sg:city":"Southbank",
    "sg:classifiers":[
        {
            "category":"Professional",
            "subcategory":"Business Services",
            "type":"Services"
        }
    ],
    "sg:phone":"+61 3 9690 5055",
    "sg:postcode":"3006",
    "sg:province":"VIC",
    "sg:tags":[
        "consultant",
        "promoter",
        "entertainment"
    ],
    "wof:name":"Primate Entertainment Services",
    "wof:placetype":"venue"
},
  "geometry": {"coordinates":[144.966552734,-37.8266067505],"type":"Point"}
}