{
  "type": "Feature",
  "properties": {
    "iso:country":"AU",
    "sg:address":"Po Box 5142",
    "sg:city":"Highgate Hill",
    "sg:classifiers":[
        {
            "category":"Health Services",
            "subcategory":"Health Practitioner",
            "type":"Services"
        }
    ],
    "sg:phone":"+61 1300 725 334",
    "sg:postcode":"4101",
    "sg:province":"QLD",
    "sg:tags":[
        "acupuncture"
    ],
    "wof:name":"Australian Acupuncture & Chinese Medicine Association Ltd",
    "wof:placetype":"venue"
},
  "geometry": {"coordinates":[153.01754760700001,-27.4871807098],"type":"Point"}
}