{
  "type": "Feature",
  "properties": {
    "iso:country":"AU",
    "sg:address":"22 Glen Rd",
    "sg:city":"Katoomba",
    "sg:classifiers":[
        {
            "category":"Health Services",
            "subcategory":"Health Practitioner",
            "type":"Services"
        }
    ],
    "sg:phone":"+61 2 4782 7288",
    "sg:postcode":"2780",
    "sg:province":"NSW",
    "sg:tags":[
        "physiotherapist"
    ],
    "wof:name":"Kinetic Phsiotherapy & Pilates",
    "wof:placetype":"venue"
},
  "geometry": {"coordinates":[150.320022583,-33.6921691895],"type":"Point"}
}