{
  "type": "Feature",
  "properties": {
    "addr:full":"5 Rufford La Canning Vale WA 6155",
    "addr:housenumber":"5",
    "addr:postcode":"6155",
    "addr:street":"Rufford La",
    "iso:country":"AU",
    "sg:address":"5 Rufford La",
    "sg:city":"Canning Vale",
    "sg:classifiers":[
        {
            "category":"Professional",
            "subcategory":"Computer Services",
            "type":"Services"
        }
    ],
    "sg:phone":"+61 8 9456 2206",
    "sg:postcode":"6155",
    "sg:province":"WA",
    "sg:tags":[
        "consultant",
        "system"
    ],
    "wof:name":"Oldtrain Pty Ltd",
    "wof:placetype":"venue"
},
  "geometry": {"coordinates":[115.93493700000001,-32.090939],"type":"Point"}
}