{
  "type": "Feature",
  "properties": {
    "addr:full":"2 Jackson St Reservoir VIC 3073",
    "addr:housenumber":"2",
    "addr:postcode":"3073",
    "addr:street":"Jackson St",
    "iso:country":"AU",
    "sg:address":"2 Jackson St",
    "sg:city":"Reservoir",
    "sg:classifiers":[
        {
            "category":"Building & Trades",
            "subcategory":"Construction",
            "type":"Services"
        }
    ],
    "sg:phone":"+61 419 366 612",
    "sg:postcode":"3073",
    "sg:province":"VIC",
    "sg:tags":[
        "scaffolding"
    ],
    "wof:name":"Veco",
    "wof:placetype":"venue"
},
  "geometry": {"coordinates":[145.008468628,-37.7011260986],"type":"Point"}
}