{
  "type": "Feature",
  "properties": {
    "iso:country":"AU",
    "sg:address":"3/ 28 Mews Rd",
    "sg:city":"Fremantle",
    "sg:classifiers":[
        {
            "category":"Shopping",
            "subcategory":"Computers & Home Electronics",
            "type":"Retail Goods"
        }
    ],
    "sg:phone":"+61 8 9335 2716",
    "sg:postcode":"6160",
    "sg:province":"WA",
    "sg:tags":[
        "global",
        "positioning",
        "system"
    ],
    "sg:website":"http://www.maritimeelectronics.com.au",
    "wof:name":"Maritime Electronic Services",
    "wof:placetype":"venue"
},
  "geometry": {"coordinates":[115.747887,-32.060307],"type":"Point"}
}