{
  "type": "Feature",
  "properties": {
    "addr:full":"18- 20 Sherwood St Scone NSW 2337",
    "addr:housenumber":"20",
    "addr:postcode":"2337",
    "addr:street":"Sherwood St",
    "iso:country":"AU",
    "sg:address":"18- 20 Sherwood St",
    "sg:city":"Scone",
    "sg:classifiers":[
        {
            "category":"Retail",
            "subcategory":"Auto Repair",
            "type":"Services"
        }
    ],
    "sg:phone":"+61 2 6545 9100",
    "sg:postcode":"2337",
    "sg:province":"NSW",
    "sg:tags":[
        "bus",
        "truck"
    ],
    "wof:name":"Scania Australia Pty Ltd",
    "wof:placetype":"venue"
},
  "geometry": {"coordinates":[150.871582031,-32.0431098938],"type":"Point"}
}