{
  "type": "Feature",
  "properties": {
    "iso:country":"AU",
    "sg:address":"17- 27 Blue Eagle Drv",
    "sg:city":"Meadowbrook",
    "sg:classifiers":[
        {
            "category":"Structure",
            "subcategory":"Office Building",
            "type":"Public Place"
        }
    ],
    "sg:phone":"+61 7 3200 9977",
    "sg:postcode":"4131",
    "sg:province":"QLD",
    "sg:tags":[
        "fire",
        "window",
        "door"
    ],
    "wof:name":"AUSCODOORS",
    "wof:placetype":"venue"
},
  "geometry": {"coordinates":[153.134521484,-27.6643486023],"type":"Point"}
}