{
  "type": "Feature",
  "properties": {
    "addr:full":"PO Box 993 Taree NSW 2430",
    "addr:postcode":"2430",
    "iso:country":"AU",
    "sg:address":"PO Box 993",
    "sg:city":"Taree",
    "sg:classifiers":[
        {
            "category":"Communications",
            "type":"Services"
        }
    ],
    "sg:phone":"+61 2 6553 2080",
    "sg:postcode":"2430",
    "sg:province":"NSW",
    "sg:tags":[
        "equipment",
        "satellite"
    ],
    "wof:name":"Active Antenna Service",
    "wof:placetype":"venue"
},
  "geometry": {"coordinates":[152.46151699999999,-31.91313],"type":"Point"}
}