{
  "type": "Feature",
  "properties": {
    "iso:country":"AU",
    "sg:address":"23c Lusher Rd",
    "sg:city":"Croydon",
    "sg:classifiers":[
        {
            "category":"Utilities",
            "subcategory":"Electric",
            "type":"Services"
        }
    ],
    "sg:phone":"+61 417 575 261",
    "sg:postcode":"3136",
    "sg:province":"VIC",
    "sg:tags":[
        "electrical",
        "contractor"
    ],
    "wof:name":"Jim Lynch",
    "wof:placetype":"venue"
},
  "geometry": {"coordinates":[145.27871704099999,-37.802520752],"type":"Point"}
}