{
  "type": "Feature",
  "properties": {
    "addr:full":"13 Stevens Pl Kardinya WA 6163",
    "addr:housenumber":"13",
    "addr:postcode":"6163",
    "addr:street":"Stevens Pl",
    "iso:country":"AU",
    "sg:address":"13 Stevens Pl",
    "sg:city":"Kardinya",
    "sg:classifiers":[
        {
            "category":"Retail",
            "subcategory":"Driving School",
            "type":"Services"
        }
    ],
    "sg:phone":"+61 8 9337 9157",
    "sg:postcode":"6163",
    "sg:province":"WA",
    "wof:name":"Kardinya School of Motoring",
    "wof:placetype":"venue"
},
  "geometry": {"coordinates":[115.811493,-32.06955],"type":"Point"}
}