{
  "type": "Feature",
  "properties": {
    "addr:full":"Unit 1, 21- 23 Tasman Way Byron Bay NSW 2481",
    "addr:housenumber":"21 23",
    "addr:postcode":"2481",
    "addr:street":"Tasman Way",
    "iso:country":"AU",
    "sg:address":"Unit 1, 21- 23 Tasman Way",
    "sg:city":"Byron Bay",
    "sg:classifiers":[
        {
            "category":"Shopping",
            "subcategory":"Stationery & Office Supplies",
            "type":"Retail Goods"
        }
    ],
    "sg:phone":"+61 2 6680 9624",
    "sg:postcode":"2481",
    "sg:province":"NSW",
    "sg:tags":[
        "equipment",
        "display",
        "exhibition"
    ],
    "sg:website":"http://www.seesaw.com.au",
    "wof:name":"Seesaw Signs & Visual Displays",
    "wof:placetype":"venue"
},
  "geometry": {"coordinates":[153.57986450199999,-28.6349487305],"type":"Point"}
}