{
  "type": "Feature",
  "properties": {
    "addr:full":"99a King St Mascot NSW 2020",
    "addr:housenumber":"99a",
    "addr:postcode":"2020",
    "addr:street":"King St",
    "iso:country":"AU",
    "sg:address":"99a King St",
    "sg:city":"Mascot",
    "sg:classifiers":[
        {
            "category":"Travel",
            "subcategory":"Travel Agent",
            "type":"Entertainment"
        }
    ],
    "sg:phone":"+61 2 9667 0593",
    "sg:postcode":"2020",
    "sg:province":"NSW",
    "sg:tags":[
        "tour",
        "holiday",
        "adventure"
    ],
    "wof:name":"Experience Tours Australia Pty Ltd",
    "wof:placetype":"venue"
},
  "geometry": {"coordinates":[151.190307617,-33.928817749],"type":"Point"}
}