{
  "type": "Feature",
  "properties": {
    "addr:full":"6 Argyle St Narrandera NSW 2700",
    "addr:housenumber":"6",
    "addr:postcode":"2700",
    "addr:street":"Argyle St",
    "iso:country":"AU",
    "sg:address":"6 Argyle St",
    "sg:city":"Narrandera",
    "sg:classifiers":[
        {
            "category":"Retail",
            "subcategory":"Repair Shop",
            "type":"Services"
        }
    ],
    "sg:phone":"+61 2 6959 1806",
    "sg:postcode":"2700",
    "sg:province":"NSW",
    "sg:tags":[
        "machine",
        "sewing"
    ],
    "wof:name":"Bradford N M",
    "wof:placetype":"venue"
},
  "geometry": {"coordinates":[146.56123352,-34.7458381653],"type":"Point"}
}