{
  "type": "Feature",
  "properties": {
    "iso:country":"AU",
    "sg:address":"90- 106 Sydney Rd",
    "sg:city":"Brunswick",
    "sg:classifiers":[
        {
            "category":"Shopping",
            "subcategory":"Clothing, Apparel, & Fashions",
            "type":"Retail Goods"
        }
    ],
    "sg:phone":"+61 3 9388 0390",
    "sg:postcode":"3056",
    "sg:province":"VIC",
    "sg:tags":[
        "lady",
        "wear"
    ],
    "wof:name":"Central Lane",
    "wof:placetype":"venue"
},
  "geometry": {"coordinates":[144.96087646500001,-37.7754707336],"type":"Point"}
}