{
  "type": "Feature",
  "properties": {
    "iso:country":"AU",
    "sg:address":"6 Elysium St",
    "sg:city":"Carrara",
    "sg:classifiers":[
        {
            "category":"Shopping",
            "subcategory":"Crafts & Fabrics",
            "type":"Retail Goods"
        }
    ],
    "sg:phone":"+61 7 5525 3399",
    "sg:postcode":"4211",
    "sg:province":"QLD",
    "sg:tags":[
        "synthetic",
        "canvas",
        "product"
    ],
    "sg:website":"http://www.bjcanvas.com.au",
    "wof:name":"B & J Canvas",
    "wof:placetype":"venue"
},
  "geometry": {"coordinates":[153.35382080100001,-28.0331401825],"type":"Point"}
}