{
  "type": "Feature",
  "properties": {
    "addr:full":"11- 13 Erica Ave Boronia VIC 3155",
    "addr:housenumber":"13",
    "addr:postcode":"3155",
    "addr:street":"Erica Ave",
    "iso:country":"AU",
    "sg:address":"11- 13 Erica Ave",
    "sg:city":"Boronia",
    "sg:classifiers":[
        {
            "category":"Shopping",
            "subcategory":"Party Supplies",
            "type":"Retail Goods"
        }
    ],
    "sg:phone":"+61 3 9762 7134",
    "sg:postcode":"3155",
    "sg:province":"VIC",
    "wof:name":"Ace Party Hire",
    "wof:placetype":"venue"
},
  "geometry": {"coordinates":[145.283813477,-37.8614311218],"type":"Point"}
}