{
  "type": "Feature",
  "properties": {
    "addr:full":"3 Drynan St Summer Hill (Sydney) NSW 2130",
    "addr:housenumber":"3",
    "addr:postcode":"2130",
    "addr:street":"Drynan St",
    "iso:country":"AU",
    "sg:address":"3 Drynan St",
    "sg:city":"Summer Hill (Sydney)",
    "sg:classifiers":[
        {
            "category":"Social Services",
            "subcategory":"Child Care",
            "type":"Services"
        }
    ],
    "sg:phone":"+61 2 9798 4221",
    "sg:postcode":"2130",
    "sg:province":"NSW",
    "wof:name":"St Patrick's Shoosh Care Association",
    "wof:placetype":"venue"
},
  "geometry": {"coordinates":[151.13262939399999,-33.8934020996],"type":"Point"}
}