{
  "type": "Feature",
  "properties": {
    "iso:country":"AU",
    "sg:address":"5c Hamilton St",
    "sg:city":"Gisborne",
    "sg:classifiers":[
        {
            "category":"Personal",
            "subcategory":"Beauty Salon",
            "type":"Services"
        }
    ],
    "sg:phone":"+61 3 5428 1467",
    "sg:postcode":"3437",
    "sg:province":"VIC",
    "sg:tags":[
        "hairdresser"
    ],
    "wof:name":"Danny's Barber Shop",
    "wof:placetype":"venue"
},
  "geometry": {"coordinates":[144.59277343799999,-37.4883613586],"type":"Point"}
}