{
  "type": "Feature",
  "properties": {
    "addr:full":"Locked Bag 18 /117 Newtown NSW 2042",
    "addr:housenumber":"18 / 117",
    "addr:postcode":"2042",
    "iso:country":"AU",
    "sg:address":"Locked Bag 18",
    "sg:city":"/117 Newtown",
    "sg:classifiers":[
        {
            "category":"Banks & Credit Unions",
            "subcategory":"Bank",
            "type":"Services"
        }
    ],
    "sg:phone":"+61 2 9746 2877",
    "sg:postcode":"2042",
    "sg:province":"NSW",
    "sg:tags":[
        "concrete",
        "reinforcement"
    ],
    "wof:name":"Fast Fix NSW Pty Ltd",
    "wof:placetype":"venue"
},
  "geometry": {"coordinates":[151.17581200000001,-33.89859],"type":"Point"}
}