{
  "type": "Feature",
  "properties": {
    "addr:full":"798 Main Rd Hurstbridge VIC 3099",
    "addr:housenumber":"798",
    "addr:postcode":"3099",
    "addr:street":"Main Rd",
    "iso:country":"AU",
    "sg:address":"798 Main Rd",
    "sg:city":"Hurstbridge",
    "sg:classifiers":[
        {
            "category":"Food & Beverages",
            "subcategory":"Bakery",
            "type":"Retail Goods"
        }
    ],
    "sg:phone":"+61 3 9718 1128",
    "sg:postcode":"3099",
    "sg:province":"VIC",
    "sg:tags":[
        "baker"
    ],
    "wof:name":"Stoneground Bakery",
    "wof:placetype":"venue"
},
  "geometry": {"coordinates":[145.19294738799999,-37.6396751404],"type":"Point"}
}