{
  "type": "Feature",
  "properties": {
    "iso:country":"AU",
    "sg:address":"55 Brookhouse St",
    "sg:city":"Stuart",
    "sg:classifiers":[
        {
            "category":"Home & Garden",
            "subcategory":"Building Materials",
            "type":"Retail Goods"
        }
    ],
    "sg:phone":"+61 7 4799 8000",
    "sg:postcode":"4811",
    "sg:province":"QLD",
    "sg:tags":[
        "pre-mixed",
        "concrete"
    ],
    "wof:name":"Wagners",
    "wof:placetype":"venue"
},
  "geometry": {"coordinates":[146.833588,-19.340284],"type":"Point"}
}