{
  "type": "Feature",
  "properties": {
    "addr:full":"Fairview Rd Lucindale SA 5272",
    "addr:postcode":"5272",
    "addr:street":"Fairview Rd",
    "iso:country":"AU",
    "sg:address":"Fairview Rd",
    "sg:city":"Lucindale",
    "sg:classifiers":[
        {
            "category":"Building & Trades",
            "subcategory":"Landscaping Services",
            "type":"Services"
        }
    ],
    "sg:phone":"+61 8 8766 2282",
    "sg:postcode":"5272",
    "sg:province":"SA",
    "sg:tags":[
        "grazier"
    ],
    "wof:name":"Westphal Nominees Pty Ltd",
    "wof:placetype":"venue"
},
  "geometry": {"coordinates":[140.373367,-36.970493],"type":"Point"}
}