{
  "type": "Feature",
  "properties": {
    "iso:country":"AU",
    "sg:address":"Buchanan St",
    "sg:city":"Murwillumbah",
    "sg:classifiers":[
        {
            "category":"Building & Trades",
            "subcategory":"Construction",
            "type":"Services"
        }
    ],
    "sg:phone":"+61 2 6672 3922",
    "sg:postcode":"2484",
    "sg:province":"NSW",
    "sg:tags":[
        "earth",
        "excavating",
        "moving",
        "contractor"
    ],
    "wof:name":"Brims Earthmoving Pty Ltd",
    "wof:placetype":"venue"
},
  "geometry": {"coordinates":[153.40899658199999,-28.3303432465],"type":"Point"}
}