{
  "type": "Feature",
  "properties": {
    "addr:full":"20 Stark La Forest Glen QLD 4556",
    "addr:housenumber":"20",
    "addr:postcode":"4556",
    "addr:street":"Stark La",
    "iso:country":"AU",
    "sg:address":"20 Stark La",
    "sg:city":"Forest Glen",
    "sg:classifiers":[
        {
            "category":"Retail",
            "subcategory":"Auto Repair",
            "type":"Services"
        }
    ],
    "sg:phone":"+61 7 5442 2455",
    "sg:postcode":"4556",
    "sg:province":"QLD",
    "sg:tags":[
        "repairer",
        "motor",
        "engineer"
    ],
    "wof:name":"Suncoast Volvo Repairs",
    "wof:placetype":"venue"
},
  "geometry": {"coordinates":[153.00152587900001,-26.6729240417],"type":"Point"}
}