{
  "type": "Feature",
  "properties": {
    "addr:full":"Shp 3a Warnbro Fair Shopng Cntr Warnbro Ave Warnbro WA 6169",
    "addr:housenumber":"3a",
    "addr:postcode":"6169",
    "addr:street":"Warnbro Ave",
    "iso:country":"AU",
    "sg:address":"Shp 3a Warnbro Fair Shopng Cntr Warnbro Ave",
    "sg:city":"Warnbro",
    "sg:classifiers":[
        {
            "category":"Personal",
            "subcategory":"Beauty Salon",
            "type":"Services"
        }
    ],
    "sg:phone":"+61 8 9593 0267",
    "sg:postcode":"6169",
    "sg:province":"WA",
    "sg:tags":[
        "hairdresser"
    ],
    "wof:name":"Checkers Hairdressing for Men",
    "wof:placetype":"venue"
},
  "geometry": {"coordinates":[115.759407,-32.347149],"type":"Point"}
}