{
  "type": "Feature",
  "properties": {
    "addr:full":"6 Belfield Ave North Rockhampton QLD 4701",
    "addr:housenumber":"6",
    "addr:postcode":"4701",
    "addr:street":"Belfield Ave North",
    "iso:country":"AU",
    "sg:address":"6 Belfield Ave",
    "sg:city":"North Rockhampton",
    "sg:classifiers":[
        {
            "category":"Freight",
            "type":"Transportation"
        }
    ],
    "sg:phone":"+61 418 791 860",
    "sg:postcode":"4701",
    "sg:province":"QLD",
    "sg:tags":[
        "light",
        "carrier"
    ],
    "wof:name":"Koongal Carriers",
    "wof:placetype":"venue"
},
  "geometry": {"coordinates":[150.548736572,-23.3517150879],"type":"Point"}
}