{
  "type": "Feature",
  "properties": {
    "addr:full":"2 Schofield Pde Pennant Hills NSW 2120",
    "addr:housenumber":"2",
    "addr:postcode":"2120",
    "addr:street":"Schofield Pde",
    "iso:country":"AU",
    "sg:address":"2 Schofield Pde",
    "sg:city":"Pennant Hills",
    "sg:classifiers":[
        {
            "category":"Building & Trades",
            "subcategory":"Construction",
            "type":"Services"
        }
    ],
    "sg:phone":"+61 410 468 162",
    "sg:postcode":"2120",
    "sg:province":"NSW",
    "sg:tags":[
        "plasterboard",
        "plasterer",
        "fixer"
    ],
    "wof:name":"Plaster Me Nicely",
    "wof:placetype":"venue"
},
  "geometry": {"coordinates":[151.06211852999999,-33.7305107117],"type":"Point"}
}