{
  "type": "Feature",
  "properties": {
    "addr:full":"61 Bertha St Goodna QLD 4300",
    "addr:housenumber":"61",
    "addr:postcode":"4300",
    "addr:street":"Bertha St",
    "iso:country":"AU",
    "sg:address":"61 Bertha St",
    "sg:city":"Goodna",
    "sg:classifiers":[
        {
            "category":"Home & Garden",
            "subcategory":"Kitchen Supply",
            "type":"Retail Goods"
        }
    ],
    "sg:phone":"+61 7 3818 0406",
    "sg:postcode":"4300",
    "sg:province":"QLD",
    "sg:tags":[
        "traffic",
        "equipment",
        "safety",
        "road"
    ],
    "wof:name":"Xpan Pty Ltd",
    "wof:placetype":"venue"
},
  "geometry": {"coordinates":[152.90202331500001,-27.6160182953],"type":"Point"}
}