{
  "type": "Feature",
  "properties": {
    "addr:full":"PO Box 775 Sumner Park QLD 4074",
    "addr:postcode":"4074",
    "iso:country":"AU",
    "sg:address":"PO Box 775",
    "sg:city":"Sumner Park",
    "sg:classifiers":[
        {
            "category":"Home & Garden",
            "subcategory":"Carpets & Floor Coverings",
            "type":"Retail Goods"
        }
    ],
    "sg:phone":"+61 7 3376 9838",
    "sg:postcode":"4074",
    "sg:province":"QLD",
    "wof:name":"Bamboo Flooring Specialists",
    "wof:placetype":"venue"
},
  "geometry": {"coordinates":[152.93930053700001,-27.562538147],"type":"Point"}
}