{
  "type": "Feature",
  "properties": {
    "addr:full":"1st Floor 30 Hasler Rd Osborne Park WA 6017",
    "addr:housenumber":"30",
    "addr:postcode":"6017",
    "addr:street":"Hasler Rd",
    "iso:country":"AU",
    "sg:address":"1st Floor 30 Hasler Rd",
    "sg:city":"Osborne Park",
    "sg:classifiers":[
        {
            "category":"Education",
            "subcategory":"University",
            "type":"Public Place"
        }
    ],
    "sg:phone":"+61 8 9244 1987",
    "sg:postcode":"6017",
    "sg:province":"WA",
    "sg:tags":[
        "educational",
        "organisation",
        "cultural"
    ],
    "wof:name":"Science Teachers' Association Of WA Inc",
    "wof:placetype":"venue"
},
  "geometry": {"coordinates":[115.80863952599999,-31.9107151031],"type":"Point"}
}