{
  "type": "Feature",
  "properties": {
    "iso:country":"AU",
    "sg:address":"St Aubins",
    "sg:city":"Comet",
    "sg:classifiers":[
        {
            "category":"Building & Trades",
            "subcategory":"Landscaping Services",
            "type":"Services"
        }
    ],
    "sg:phone":"+61 7 4982 2068",
    "sg:postcode":"4702",
    "sg:province":"QLD",
    "sg:tags":[
        "grazier"
    ],
    "wof:name":"Morawitz C A & G",
    "wof:placetype":"venue"
},
  "geometry": {"coordinates":[148.51817321799999,-23.5977344513],"type":"Point"}
}