{
  "type": "Feature",
  "properties": {
    "iso:country":"AU",
    "sg:address":"99 Munibung Rd",
    "sg:city":"Cardiff",
    "sg:classifiers":[
        {
            "category":"Manufacturing",
            "subcategory":"Retail Goods",
            "type":"Manufacturing & Wholesale Goods"
        }
    ],
    "sg:phone":"+61 2 4954 7900",
    "sg:postcode":"2285",
    "sg:province":"NSW",
    "sg:tags":[
        "merchant",
        "pump",
        "mfrs"
    ],
    "wof:name":"Warman International",
    "wof:placetype":"venue"
},
  "geometry": {"coordinates":[151.637771606,-32.9408073425],"type":"Point"}
}