{
  "type": "Feature",
  "properties": {
    "addr:full":"Shop 10 3-5 Myahgah Rd Mosman NSW 2088",
    "addr:housenumber":"shop 10 3-5",
    "addr:postcode":"2088",
    "addr:street":"Myahgah Rd",
    "iso:country":"AU",
    "sg:address":"Shop 10 3-5 Myahgah Rd",
    "sg:city":"Mosman",
    "sg:classifiers":[
        {
            "category":"Personal",
            "subcategory":"Beauty Salon",
            "type":"Services"
        }
    ],
    "sg:phone":"+61 2 9969 3598",
    "sg:postcode":"2088",
    "sg:province":"NSW",
    "wof:name":"Vanity",
    "wof:placetype":"venue"
},
  "geometry": {"coordinates":[151.24082946799999,-33.8256416321],"type":"Point"}
}