{
  "type": "Feature",
  "properties": {
    "iso:country":"AU",
    "sg:address":"8 Walton St",
    "sg:city":"Banyo",
    "sg:classifiers":[
        {
            "category":"Communications",
            "type":"Services"
        }
    ],
    "sg:phone":"+61 7 3114 2544",
    "sg:postcode":"4014",
    "sg:province":"QLD",
    "sg:tags":[
        "antenna"
    ],
    "wof:name":"All Trades & Services",
    "wof:placetype":"venue"
},
  "geometry": {"coordinates":[153.081787109,-27.3725509644],"type":"Point"}
}