{
  "type": "Feature",
  "properties": {
    "iso:country":"AU",
    "sg:address":"25B Sheilds Crs",
    "sg:city":"Booragoon",
    "sg:classifiers":[
        {
            "category":"Building & Trades",
            "subcategory":"Construction",
            "type":"Services"
        }
    ],
    "sg:phone":"+61 407 386 255",
    "sg:postcode":"6154",
    "sg:province":"WA",
    "sg:tags":[
        "contractor"
    ],
    "wof:name":"Paintessa Homes",
    "wof:placetype":"venue"
},
  "geometry": {"coordinates":[115.832329,-32.036018],"type":"Point"}
}