{
  "type": "Feature",
  "properties": {
    "addr:full":"60- 62 Wyndham St Alexandria NSW 2015",
    "addr:housenumber":"62",
    "addr:postcode":"2015",
    "addr:street":"Wyndham St",
    "iso:country":"AU",
    "sg:address":"60- 62 Wyndham St",
    "sg:city":"Alexandria",
    "sg:classifiers":[
        {
            "category":"Retail",
            "subcategory":"Driving School",
            "type":"Services"
        }
    ],
    "sg:phone":"+61 2 9310 1166",
    "sg:postcode":"2015",
    "sg:province":"NSW",
    "wof:name":"Least Cost Taxi Centre Pty Ltd",
    "wof:placetype":"venue"
},
  "geometry": {"coordinates":[151.198562622,-33.8972015381],"type":"Point"}
}