{
  "type": "Feature",
  "properties": {
    "iso:country":"AU",
    "sg:address":"26 Michelle Crs",
    "sg:city":"Glendale",
    "sg:classifiers":[
        {
            "category":"Education",
            "subcategory":"Music School",
            "type":"Public Place"
        }
    ],
    "sg:phone":"+61 2 4954 2349",
    "sg:postcode":"2285",
    "sg:province":"NSW",
    "sg:tags":[
        "teacher"
    ],
    "wof:name":"Mee Trevor",
    "wof:placetype":"venue"
},
  "geometry": {"coordinates":[151.649734497,-32.9301300049],"type":"Point"}
}