{
  "type": "Feature",
  "properties": {
    "addr:full":"Lot 5 Vale Rd Moss Vale NSW 2577",
    "addr:postcode":"2577",
    "addr:street":"Vale Rd",
    "iso:country":"AU",
    "sg:address":"Lot 5 Vale Rd",
    "sg:city":"Moss Vale",
    "sg:classifiers":[
        {
            "category":"Retail",
            "subcategory":"Auto Repair",
            "type":"Services"
        }
    ],
    "sg:phone":"+61 2 4868 1031",
    "sg:postcode":"2577",
    "sg:province":"NSW",
    "sg:tags":[
        "beater",
        "painter",
        "panel"
    ],
    "wof:name":"Southern Highland Motor Group",
    "wof:placetype":"venue"
},
  "geometry": {"coordinates":[150.377716064,-34.5413246155],"type":"Point"}
}