{
  "type": "Feature",
  "properties": {
    "addr:full":"Lot 59 Howe St Miners Rest VIC 3352",
    "addr:postcode":"3352",
    "addr:street":"Howe St",
    "iso:country":"AU",
    "sg:address":"Lot 59 Howe St",
    "sg:city":"Miners Rest",
    "sg:classifiers":[
        {
            "category":"Building & Trades",
            "subcategory":"Construction",
            "type":"Services"
        }
    ],
    "sg:phone":"+61 3 5334 6742",
    "sg:postcode":"3352",
    "sg:province":"VIC",
    "sg:tags":[
        "contractor"
    ],
    "wof:name":"Central Highlands Building Contractors",
    "wof:placetype":"venue"
},
  "geometry": {"coordinates":[143.80548099999999,-37.499065],"type":"Point"}
}