{
  "type": "Feature",
  "properties": {
    "iso:country":"AU",
    "sg:address":"Upper Floor, 87 The Parade",
    "sg:city":"Ocean Grove",
    "sg:classifiers":[
        {
            "category":"Professional",
            "subcategory":"Business Services",
            "type":"Services"
        }
    ],
    "sg:phone":"+61 3 5255 3355",
    "sg:postcode":"3226",
    "sg:province":"VIC",
    "sg:tags":[
        "drafting"
    ],
    "wof:name":"Michael Higgins Building Design Pty Ltd",
    "wof:placetype":"venue"
},
  "geometry": {"coordinates":[144.52520799999999,-38.267235],"type":"Point"}
}