{
  "type": "Feature",
  "properties": {
    "iso:country":"AU",
    "sg:address":"9/ 401 Princes Hwy",
    "sg:city":"Noble Park",
    "sg:classifiers":[
        {
            "category":"Retail",
            "subcategory":"Auto Repair",
            "type":"Services"
        }
    ],
    "sg:phone":"+61 3 9574 0000",
    "sg:postcode":"3174",
    "sg:province":"VIC",
    "sg:tags":[
        "repairer",
        "motor",
        "engineer"
    ],
    "wof:name":"Knights Automotive",
    "wof:placetype":"venue"
},
  "geometry": {"coordinates":[145.18736267099999,-37.9611244202],"type":"Point"}
}