{
  "type": "Feature",
  "properties": {
    "addr:full":"1802 / 250 St Kilda Rd Southbank VIC 3006",
    "addr:housenumber":"1802 / 250",
    "addr:postcode":"3006",
    "addr:street":"St Kilda Rd",
    "iso:country":"AU",
    "sg:address":"1802 / 250 St Kilda Rd",
    "sg:city":"Southbank",
    "sg:classifiers":[
        {
            "category":"Real Estate",
            "subcategory":"Architect",
            "type":"Services"
        }
    ],
    "sg:phone":"+61 3 9682 2090",
    "sg:postcode":"3006",
    "sg:province":"VIC",
    "wof:name":"Castles Architecture",
    "wof:placetype":"venue"
},
  "geometry": {"coordinates":[144.97076415999999,-37.8254928589],"type":"Point"}
}