{
  "type": "Feature",
  "properties": {
    "addr:full":"10/ 3 Vaughan Drv Ormeau QLD 4208",
    "addr:housenumber":"10 / 3",
    "addr:postcode":"4208",
    "addr:street":"Vaughan Drv",
    "iso:country":"AU",
    "sg:address":"10/ 3 Vaughan Drv",
    "sg:city":"Ormeau",
    "sg:classifiers":[
        {
            "category":"Retail",
            "subcategory":"Veterinary Services",
            "type":"Services"
        }
    ],
    "sg:phone":"+61 7 5546 6205",
    "sg:postcode":"4208",
    "sg:province":"QLD",
    "sg:tags":[
        "surgeon"
    ],
    "wof:name":"Ormeau Veterinary Clinic Pty Ltd",
    "wof:placetype":"venue"
},
  "geometry": {"coordinates":[153.250534058,-27.7856864929],"type":"Point"}
}