{
  "type": "Feature",
  "properties": {
    "addr:full":"18 Paringa Ave Somerton Park SA 5044",
    "addr:housenumber":"18",
    "addr:postcode":"5044",
    "addr:street":"Paringa Ave Somerton",
    "iso:country":"AU",
    "sg:address":"18 Paringa Ave",
    "sg:city":"Somerton Park",
    "sg:classifiers":[
        {
            "category":"Autos & Motor Vehicles",
            "subcategory":"Boat Sales",
            "type":"Retail Goods"
        }
    ],
    "sg:phone":"+61 8 8350 0422",
    "sg:postcode":"5044",
    "sg:province":"SA",
    "sg:tags":[
        "yacht"
    ],
    "sg:website":"http://www.matrixmarine.com.au",
    "wof:name":"Matrix Marine SA Pty Ltd",
    "wof:placetype":"venue"
},
  "geometry": {"coordinates":[138.523788,-34.998894],"type":"Point"}
}