{
  "type": "Feature",
  "properties": {
    "iso:country":"AU",
    "sg:address":"121 Lilyfield Rd",
    "sg:city":"Lilyfield",
    "sg:classifiers":[
        {
            "category":"Arts & Performance",
            "subcategory":"Music",
            "type":"Entertainment"
        }
    ],
    "sg:phone":"+61 2 9810 2527",
    "sg:postcode":"2040",
    "sg:province":"NSW",
    "sg:tags":[
        "mobile",
        "jockey",
        "disc"
    ],
    "wof:name":"N.V. Mobile Disco",
    "wof:placetype":"venue"
},
  "geometry": {"coordinates":[151.160034,-33.874172],"type":"Point"}
}