{
  "type": "Feature",
  "properties": {
    "iso:country":"AU",
    "sg:address":"PO Box 410",
    "sg:city":"Manly",
    "sg:classifiers":[
        {
            "category":"Social Services",
            "type":"Services"
        }
    ],
    "sg:phone":"+61 409 603 346",
    "sg:postcode":"1655",
    "sg:province":"NSW",
    "sg:tags":[
        "domestic",
        "help"
    ],
    "wof:name":"Anita Koning - Personal Home Assistant",
    "wof:placetype":"venue"
},
  "geometry": {"coordinates":[151.288040161,-33.7971382141],"type":"Point"}
}