{
  "type": "Feature",
  "properties": {
    "addr:full":"Hahndorf Rd Echunga SA 5153",
    "addr:postcode":"5153",
    "addr:street":"Hahndorf Rd",
    "iso:country":"AU",
    "sg:address":"Hahndorf Rd",
    "sg:city":"Echunga",
    "sg:classifiers":[
        {
            "category":"Education",
            "subcategory":"School",
            "type":"Public Place"
        }
    ],
    "sg:phone":"+61 8 8388 8306",
    "sg:postcode":"5153",
    "sg:province":"SA",
    "sg:tags":[
        "state",
        "except",
        "nsw"
    ],
    "wof:name":"Echunga Primary",
    "wof:placetype":"venue"
},
  "geometry": {"coordinates":[138.793426514,-35.1000900269],"type":"Point"}
}