{
  "type": "Feature",
  "properties": {
    "addr:full":"Bracknell Hotel Louisa St Bracknell TAS 7302",
    "addr:postcode":"7302",
    "addr:street":"St",
    "iso:country":"AU",
    "sg:address":"Bracknell Hotel Louisa St",
    "sg:city":"Bracknell",
    "sg:classifiers":[
        {
            "category":"Food & Beverages",
            "subcategory":"Liquor & Beverages",
            "type":"Retail Goods"
        }
    ],
    "sg:phone":"+61 3 6397 3278",
    "sg:postcode":"7302",
    "sg:province":"TAS",
    "sg:tags":[
        "store"
    ],
    "wof:name":"Liquorwise",
    "wof:placetype":"venue"
},
  "geometry": {"coordinates":[146.93731689399999,-41.6501235962],"type":"Point"}
}