{
  "type": "Feature",
  "properties": {
    "addr:full":"86 Queen St St Marys NSW 2760",
    "addr:housenumber":"86",
    "addr:postcode":"2760",
    "addr:street":"Queen St",
    "iso:country":"AU",
    "sg:address":"86 Queen St St",
    "sg:city":"Marys",
    "sg:classifiers":[
        {
            "category":"Cafe",
            "type":"Food & Drink"
        }
    ],
    "sg:phone":"+61 2 9623 1462",
    "sg:postcode":"2760",
    "sg:province":"NSW",
    "wof:name":"Tarragon Cafe Carvery",
    "wof:placetype":"venue"
},
  "geometry": {"coordinates":[150.77447509800001,-33.7650108337],"type":"Point"}
}