{
  "type": "Feature",
  "properties": {
    "iso:country":"AU",
    "sg:address":"5 Anderson St",
    "sg:city":"Leongatha",
    "sg:classifiers":[
        {
            "category":"Shopping",
            "subcategory":"Stationery & Office Supplies",
            "type":"Retail Goods"
        }
    ],
    "sg:phone":"+61 3 5662 2306",
    "sg:postcode":"3953",
    "sg:province":"VIC",
    "sg:tags":[
        "equipment",
        "dairy"
    ],
    "wof:name":"De Laval & Nuplse",
    "wof:placetype":"venue"
},
  "geometry": {"coordinates":[145.94630432100001,-38.4752998352],"type":"Point"}
}