{
  "type": "Feature",
  "properties": {
    "iso:country":"AU",
    "sg:address":"7 Sargeant St",
    "sg:city":"Warragul",
    "sg:classifiers":[
        {
            "category":"Health Services",
            "subcategory":"Doctor",
            "type":"Services"
        }
    ],
    "sg:phone":"+61 3 5622 1500",
    "sg:postcode":"3820",
    "sg:province":"VIC",
    "sg:tags":[
        "medical",
        "practitioner"
    ],
    "wof:name":"Nowotny Michael Dr",
    "wof:placetype":"venue"
},
  "geometry": {"coordinates":[145.930313,-38.17329],"type":"Point"}
}