{
  "type": "Feature",
  "properties": {
    "addr:full":"Centro Kalamunda Shopng Cntr Shop 1/ 39 Railway Pde Kalamunda WA 6076",
    "addr:housenumber":"1 / 39",
    "addr:postcode":"6076",
    "addr:street":"Railway Pde",
    "iso:country":"AU",
    "sg:address":"Centro Kalamunda Shopng Cntr Shop 1/ 39 Railway Pde",
    "sg:city":"Kalamunda",
    "sg:classifiers":[
        {
            "category":"Shopping",
            "subcategory":"Jewelry",
            "type":"Retail Goods"
        }
    ],
    "sg:phone":"+61 8 9293 3977",
    "sg:postcode":"6076",
    "sg:province":"WA",
    "sg:tags":[
        "jeweller"
    ],
    "wof:name":"Adina Jewellers",
    "wof:placetype":"venue"
},
  "geometry": {"coordinates":[116.060157776,-31.9728889465],"type":"Point"}
}