{
  "type": "Feature",
  "properties": {
    "addr:full":"28- 36 New Dookie Rd Shepparton VIC 3630",
    "addr:housenumber":"36",
    "addr:postcode":"3630",
    "addr:street":"New Dookie Rd",
    "iso:country":"AU",
    "sg:address":"28- 36 New Dookie Rd",
    "sg:city":"Shepparton",
    "sg:classifiers":[
        {
            "category":"Education",
            "subcategory":"School",
            "type":"Public Place"
        }
    ],
    "sg:phone":"+61 3 5831 7228",
    "sg:postcode":"3630",
    "sg:province":"VIC",
    "sg:tags":[
        "supply"
    ],
    "wof:name":"Everyday Supplies",
    "wof:placetype":"venue"
},
  "geometry": {"coordinates":[145.41920471200001,-36.3677940369],"type":"Point"}
}