{
  "type": "Feature",
  "properties": {
    "addr:full":"Lane St Broken Hill NSW 2880",
    "addr:postcode":"2880",
    "addr:street":"Lane St",
    "iso:country":"AU",
    "sg:address":"Lane St",
    "sg:city":"Broken Hill",
    "sg:classifiers":[
        {
            "category":"Education",
            "subcategory":"School",
            "type":"Public Place"
        }
    ],
    "sg:phone":"+61 8 8087 3565",
    "sg:postcode":"2880",
    "sg:province":"NSW",
    "wof:name":"School Of The Air",
    "wof:placetype":"venue"
},
  "geometry": {"coordinates":[141.460037231,-31.9531364441],"type":"Point"}
}