{
  "type": "Feature",
  "properties": {
    "iso:country":"AU",
    "sg:address":"Level 1, UDP House 62 Walker St",
    "sg:city":"Townsville",
    "sg:classifiers":[
        {
            "category":"Professional",
            "subcategory":"Engineering",
            "type":"Services"
        }
    ],
    "sg:phone":"+61 7 4772 0666",
    "sg:postcode":"4810",
    "sg:province":"QLD",
    "sg:tags":[
        "civil",
        "engineer"
    ],
    "wof:name":"UDP Consulting Engineers",
    "wof:placetype":"venue"
},
  "geometry": {"coordinates":[146.815201,-19.2582],"type":"Point"}
}