{
  "type": "Feature",
  "properties": {
    "addr:full":"18 Treweeke St Orange NSW 2800",
    "addr:housenumber":"18",
    "addr:postcode":"2800",
    "addr:street":"Treweeke St",
    "iso:country":"AU",
    "sg:address":"18 Treweeke St",
    "sg:city":"Orange",
    "sg:classifiers":[
        {
            "category":"Education",
            "subcategory":"Music School",
            "type":"Public Place"
        }
    ],
    "sg:phone":"+61 2 6362 2334",
    "sg:postcode":"2800",
    "sg:province":"NSW",
    "sg:tags":[
        "teacher"
    ],
    "wof:name":"Fleming Carol",
    "wof:placetype":"venue"
},
  "geometry": {"coordinates":[149.120407105,-33.280544281],"type":"Point"}
}