{
  "type": "Feature",
  "properties": {
    "iso:country":"AU",
    "sg:address":"1306 Pittwater Rd",
    "sg:city":"Narrabeen",
    "sg:classifiers":[
        {
            "category":"Retail",
            "subcategory":"Funeral Services",
            "type":"Services"
        }
    ],
    "sg:phone":"+61 2 9970 5055",
    "sg:postcode":"2101",
    "sg:province":"NSW",
    "sg:tags":[
        "director"
    ],
    "wof:name":"White Lady Funerals",
    "wof:placetype":"venue"
},
  "geometry": {"coordinates":[151.29718,-33.715317],"type":"Point"}
}