{
  "type": "Feature",
  "properties": {
    "addr:full":"315 Barry Rd Campbellfield VIC 3061",
    "addr:housenumber":"315",
    "addr:postcode":"3061",
    "addr:street":"Barry Rd",
    "iso:country":"AU",
    "sg:address":"315 Barry Rd",
    "sg:city":"Campbellfield",
    "sg:classifiers":[
        {
            "category":"Deli",
            "type":"Food & Drink"
        }
    ],
    "sg:phone":"+61 3 9357 8010",
    "sg:postcode":"3061",
    "sg:province":"VIC",
    "sg:tags":[
        "delicatessen"
    ],
    "wof:name":"Hasret Gida Pazari",
    "wof:placetype":"venue"
},
  "geometry": {"coordinates":[144.94924926799999,-37.6667938232],"type":"Point"}
}