{
  "type": "Feature",
  "properties": {
    "iso:country":"AU",
    "sg:address":"103 Bacon St",
    "sg:city":"Grafton",
    "sg:classifiers":[
        {
            "category":"Utilities",
            "type":"Services"
        }
    ],
    "sg:phone":"+61 2 6643 1490",
    "sg:postcode":"2460",
    "sg:province":"NSW",
    "sg:tags":[
        "refrigeration",
        "industrial",
        "commercial",
        "retail"
    ],
    "wof:name":"Grafton Air-Conditioning & Refrigeration",
    "wof:placetype":"venue"
},
  "geometry": {"coordinates":[152.93661499000001,-29.6882324219],"type":"Point"}
}