{
  "type": "Feature",
  "properties": {
    "addr:full":"79 Union St North Sydney NSW 2060",
    "addr:housenumber":"79",
    "addr:postcode":"2060",
    "addr:street":"Union St",
    "iso:country":"AU",
    "sg:address":"79 Union St",
    "sg:city":"North Sydney",
    "sg:classifiers":[
        {
            "category":"Social Services",
            "subcategory":"Retirement Home",
            "type":"Services"
        }
    ],
    "sg:phone":"+61 2 9929 6573",
    "sg:postcode":"2060",
    "sg:province":"NSW",
    "sg:tags":[
        "environmental",
        "consultant",
        "pollution"
    ],
    "wof:name":"E.C. Sustainable Environment Consultants",
    "wof:placetype":"venue"
},
  "geometry": {"coordinates":[151.20286560100001,-33.8418502808],"type":"Point"}
}