{
  "type": "Feature",
  "properties": {
    "iso:country":"AU",
    "sg:address":"Suite 13, Wesley Way Arcade, Market St",
    "sg:city":"Fremantle",
    "sg:classifiers":[
        {
            "category":"Health Services",
            "subcategory":"Dentist",
            "type":"Services"
        }
    ],
    "sg:phone":"+61 8 9335 1993",
    "sg:postcode":"6160",
    "sg:province":"WA",
    "wof:name":"Banksia Dental Care",
    "wof:placetype":"venue"
},
  "geometry": {"coordinates":[115.746773,-32.055248],"type":"Point"}
}