{
  "type": "Feature",
  "properties": {
    "iso:country":"AU",
    "sg:address":"55 Northcote Rd",
    "sg:city":"Greenacre",
    "sg:classifiers":[
        {
            "category":"Freight",
            "type":"Transportation"
        }
    ],
    "sg:phone":"+61 2 9642 2927",
    "sg:postcode":"2190",
    "sg:province":"NSW",
    "sg:tags":[
        "light",
        "carrier"
    ],
    "wof:name":"Daly E R",
    "wof:placetype":"venue"
},
  "geometry": {"coordinates":[151.052856,-33.899868],"type":"Point"}
}