{
  "type": "Feature",
  "properties": {
    "addr:full":"1513 Logan Rd Mt Gravatt QLD 4122",
    "addr:housenumber":"1513",
    "addr:postcode":"4122",
    "addr:street":"Logan Rd",
    "iso:country":"AU",
    "sg:address":"1513 Logan Rd",
    "sg:city":"Mt Gravatt",
    "sg:classifiers":[
        {
            "category":"Retail",
            "subcategory":"Repair Shop",
            "type":"Services"
        }
    ],
    "sg:phone":"+61 7 3849 2100",
    "sg:postcode":"4122",
    "sg:province":"QLD",
    "sg:tags":[
        "windscreen"
    ],
    "wof:name":"Express Windscreens",
    "wof:placetype":"venue"
},
  "geometry": {"coordinates":[153.08135986299999,-27.541727066],"type":"Point"}
}