{
  "type": "Feature",
  "properties": {
    "addr:full":"10 Corella Crt Tewantin QLD 4565",
    "addr:housenumber":"10",
    "addr:postcode":"4565",
    "addr:street":"Corella Crt",
    "iso:country":"AU",
    "sg:address":"10 Corella Crt",
    "sg:city":"Tewantin",
    "sg:classifiers":[
        {
            "category":"Building & Trades",
            "subcategory":"Equipment Rental",
            "type":"Services"
        }
    ],
    "sg:phone":"+61 411 166 002",
    "sg:postcode":"4565",
    "sg:province":"QLD",
    "sg:tags":[
        "party",
        "hire"
    ],
    "wof:name":"Blues Karaoke",
    "wof:placetype":"venue"
},
  "geometry": {"coordinates":[153.02804565400001,-26.3807296753],"type":"Point"}
}