{
  "type": "Feature",
  "properties": {
    "addr:full":"PO Box 1353 Baulkham Hills NSW 2153",
    "addr:postcode":"2153",
    "iso:country":"AU",
    "sg:address":"PO Box 1353",
    "sg:city":"Baulkham Hills",
    "sg:classifiers":[
        {
            "category":"Social Services",
            "subcategory":"Retirement Home",
            "type":"Services"
        }
    ],
    "sg:phone":"+61 2 9686 7762",
    "sg:postcode":"2153",
    "sg:province":"NSW",
    "sg:tags":[
        "life",
        "coaching"
    ],
    "wof:name":"Exceptional Life",
    "wof:placetype":"venue"
},
  "geometry": {"coordinates":[150.989624023,-33.7578811646],"type":"Point"}
}