{
  "type": "Feature",
  "properties": {
    "addr:full":"69 Sydney St Kilmore VIC 3764",
    "addr:housenumber":"69",
    "addr:postcode":"3764",
    "addr:street":"Sydney St",
    "iso:country":"AU",
    "sg:address":"69 Sydney St",
    "sg:city":"Kilmore",
    "sg:classifiers":[
        {
            "category":"Fast Food",
            "type":"Food & Drink"
        }
    ],
    "sg:phone":"+61 3 5782 1523",
    "sg:postcode":"3764",
    "sg:province":"VIC",
    "sg:tags":[
        "away",
        "take"
    ],
    "wof:name":"Kilmore Palace Chinese Restaurant",
    "wof:placetype":"venue"
},
  "geometry": {"coordinates":[144.95048523,-37.2906532288],"type":"Point"}
}