{
  "type": "Feature",
  "properties": {
    "addr:full":"19 Foliage Crt Shailer Park QLD 4128",
    "addr:housenumber":"19",
    "addr:postcode":"4128",
    "addr:street":"Foliage Crt",
    "iso:country":"AU",
    "sg:address":"19 Foliage Crt",
    "sg:city":"Shailer Park",
    "sg:classifiers":[
        {
            "category":"Professional",
            "subcategory":"Computer Services",
            "type":"Services"
        }
    ],
    "sg:phone":"+61 7 3801 2369",
    "sg:postcode":"4128",
    "sg:province":"QLD",
    "sg:tags":[
        "package",
        "software"
    ],
    "wof:name":"Fitzsimon IT Consulting",
    "wof:placetype":"venue"
},
  "geometry": {"coordinates":[153.17956543,-27.6506118774],"type":"Point"}
}