{
  "type": "Feature",
  "properties": {
    "addr:full":"Laveas Hill Rd Simpson VIC 3266",
    "addr:postcode":"3266",
    "addr:street":"Hill Rd",
    "iso:country":"AU",
    "sg:address":"Laveas Hill Rd",
    "sg:city":"Simpson",
    "sg:classifiers":[
        {
            "category":"Fast Food",
            "type":"Food & Drink"
        }
    ],
    "sg:phone":"+61 3 5594 3255",
    "sg:postcode":"3266",
    "sg:province":"VIC",
    "sg:tags":[
        "away",
        "take"
    ],
    "wof:name":"Simpson Takeaway",
    "wof:placetype":"venue"
},
  "geometry": {"coordinates":[143.20877075199999,-38.4956512451],"type":"Point"}
}