{
  "type": "Feature",
  "properties": {
    "addr:full":"Pacific Hwy Ballina NSW 2478",
    "addr:postcode":"2478",
    "addr:street":"Pacific Hwy",
    "iso:country":"AU",
    "sg:address":"Pacific Hwy",
    "sg:city":"Ballina",
    "sg:classifiers":[
        {
            "category":"Wholesale",
            "subcategory":"Seafood",
            "type":"Manufacturing & Wholesale Goods"
        }
    ],
    "sg:phone":"+61 2 6686 2187",
    "sg:postcode":"2478",
    "sg:province":"NSW",
    "sg:tags":[
        "fish"
    ],
    "wof:name":"Northern Rivers Seafoods",
    "wof:placetype":"venue"
},
  "geometry": {"coordinates":[153.554962158,-28.8678760529],"type":"Point"}
}