{
  "type": "Feature",
  "properties": {
    "iso:country":"AU",
    "sg:address":"3 Mortimer St",
    "sg:city":"Drysdale",
    "sg:classifiers":[
        {
            "category":"Retail",
            "subcategory":"Auto Repair",
            "type":"Services"
        }
    ],
    "sg:phone":"+61 3 5253 1644",
    "sg:postcode":"3222",
    "sg:province":"VIC",
    "sg:tags":[
        "repairer",
        "motor",
        "engineer"
    ],
    "wof:name":"Bellarine Auto Service",
    "wof:placetype":"venue"
},
  "geometry": {"coordinates":[144.57557700000001,-38.173737],"type":"Point"}
}