{
  "type": "Feature",
  "properties": {
    "addr:full":"65 Smith St Naracoorte SA 5271",
    "addr:housenumber":"65",
    "addr:postcode":"5271",
    "addr:street":"Smith St",
    "iso:country":"AU",
    "sg:address":"65 Smith St",
    "sg:city":"Naracoorte",
    "sg:classifiers":[
        {
            "category":"Home & Garden",
            "subcategory":"Furniture",
            "type":"Retail Goods"
        }
    ],
    "sg:phone":"+61 8 8762 4999",
    "sg:postcode":"5271",
    "sg:province":"SA",
    "sg:tags":[
        "business"
    ],
    "wof:name":"Office National Limestone Coast",
    "wof:placetype":"venue"
},
  "geometry": {"coordinates":[140.74002100000001,-36.956501],"type":"Point"}
}