{
  "type": "Feature",
  "properties": {
    "addr:full":"Adelaide Rd Mannum SA 5238",
    "addr:postcode":"5238",
    "addr:street":"Adelaide Rd",
    "iso:country":"AU",
    "sg:address":"Adelaide Rd",
    "sg:city":"Mannum",
    "sg:classifiers":[
        {
            "category":"Retail",
            "subcategory":"Auto Repair",
            "type":"Services"
        }
    ],
    "sg:phone":"+61 8 8569 1603",
    "sg:postcode":"5238",
    "sg:province":"SA",
    "sg:tags":[
        "gas",
        "conversion",
        "natural",
        "lp",
        "vehicle"
    ],
    "wof:name":"Warhurst Neil Automotive",
    "wof:placetype":"venue"
},
  "geometry": {"coordinates":[139.30337524399999,-34.9151992798],"type":"Point"}
}