{
  "type": "Feature",
  "properties": {
    "iso:country":"AU",
    "sg:address":"Suite 304, 97 Pacific Hwy",
    "sg:city":"North Sydney",
    "sg:classifiers":[
        {
            "category":"Professional",
            "subcategory":"Computer Services",
            "type":"Services"
        }
    ],
    "sg:phone":"+61 2 9984 9025",
    "sg:postcode":"2060",
    "sg:province":"NSW",
    "sg:tags":[
        "repairs",
        "upgrade",
        "equipment"
    ],
    "wof:name":"Prolance Pty Ltd",
    "wof:placetype":"venue"
},
  "geometry": {"coordinates":[151.20877075199999,-33.8407478333],"type":"Point"}
}