{
  "type": "Feature",
  "properties": {
    "iso:country":"AU",
    "sg:address":"31 Ross St",
    "sg:city":"Glenbrook",
    "sg:classifiers":[
        {
            "category":"Fast Food",
            "type":"Food & Drink"
        }
    ],
    "sg:phone":"+61 2 4739 1837",
    "sg:postcode":"2773",
    "sg:province":"NSW",
    "sg:tags":[
        "away",
        "take"
    ],
    "wof:name":"Glenbrook Takeaway",
    "wof:placetype":"venue"
},
  "geometry": {"coordinates":[150.621627808,-33.7675666809],"type":"Point"}
}