{
  "type": "Feature",
  "properties": {
    "addr:full":"24 Bellevue Crs Preston VIC 3072",
    "addr:housenumber":"24",
    "addr:postcode":"3072",
    "addr:street":"Bellevue Crs",
    "iso:country":"AU",
    "sg:address":"24 Bellevue Crs",
    "sg:city":"Preston",
    "sg:classifiers":[
        {
            "category":"Retail",
            "subcategory":"Auto Repair",
            "type":"Services"
        }
    ],
    "sg:phone":"+61 3 9484 2222",
    "sg:postcode":"3072",
    "sg:province":"VIC",
    "sg:tags":[
        "repairer",
        "motor",
        "engineer"
    ],
    "wof:name":"Repco Authorised Service",
    "wof:placetype":"venue"
},
  "geometry": {"coordinates":[144.954055786,-37.7422828674],"type":"Point"}
}