{
  "type": "Feature",
  "properties": {
    "addr:full":"116 Brooke St Fortitude Valley QLD 4006",
    "addr:housenumber":"116",
    "addr:postcode":"4006",
    "addr:street":"Brooke St",
    "iso:country":"AU",
    "sg:address":"116 Brooke St",
    "sg:city":"Fortitude Valley",
    "sg:classifiers":[
        {
            "category":"Real Estate",
            "subcategory":"Architect",
            "type":"Services"
        }
    ],
    "sg:phone":"+61 427 704 288",
    "sg:postcode":"4006",
    "sg:province":"QLD",
    "wof:name":"James Russell Architect",
    "wof:placetype":"venue"
},
  "geometry": {"coordinates":[153.03884887699999,-27.4540042877],"type":"Point"}
}