{
  "type": "Feature",
  "properties": {
    "addr:full":"47 Pearson St Brunswick West VIC 3055",
    "addr:housenumber":"47",
    "addr:postcode":"3055",
    "addr:street":"Pearson St",
    "iso:country":"AU",
    "sg:address":"47 Pearson St",
    "sg:city":"Brunswick West",
    "sg:classifiers":[
        {
            "category":"Travel",
            "subcategory":"Hotels & Motels",
            "type":"Entertainment"
        }
    ],
    "sg:phone":"+61 3 9380 8606",
    "sg:postcode":"3055",
    "sg:province":"VIC",
    "sg:tags":[
        "accommodation"
    ],
    "wof:name":"Grandview Hotel",
    "wof:placetype":"venue"
},
  "geometry": {"coordinates":[144.948944092,-37.7663726807],"type":"Point"}
}