{
  "type": "Feature",
  "properties": {
    "iso:country":"AU",
    "sg:address":"35 Suncoast Drv",
    "sg:city":"Blackmans Bay",
    "sg:classifiers":[
        {
            "category":"Building & Trades",
            "subcategory":"Cleaning & Sanitation",
            "type":"Services"
        }
    ],
    "sg:phone":"+61 421 661 437",
    "sg:postcode":"7052",
    "sg:province":"TAS",
    "sg:tags":[
        "window"
    ],
    "wof:name":"MR Sparkle Window Cleaning",
    "wof:placetype":"venue"
},
  "geometry": {"coordinates":[147.327286,-43.010357],"type":"Point"}
}