{
  "type": "Feature",
  "properties": {
    "addr:full":"31 Dell St Woodpark NSW 2164",
    "addr:housenumber":"31",
    "addr:postcode":"2164",
    "addr:street":"Dell St",
    "iso:country":"AU",
    "sg:address":"31 Dell St",
    "sg:city":"Woodpark",
    "sg:classifiers":[
        {
            "category":"Shopping",
            "subcategory":"Party Supplies",
            "type":"Retail Goods"
        }
    ],
    "sg:phone":"+61 2 9681 4118",
    "sg:postcode":"2164",
    "sg:province":"NSW",
    "wof:name":"Ace Frozen Foods & Party Supplies",
    "wof:placetype":"venue"
},
  "geometry": {"coordinates":[150.96055602999999,-33.8417358398],"type":"Point"}
}