{
  "type": "Feature",
  "properties": {
    "iso:country":"AU",
    "sg:address":"Unit 2/ 65 Wellington St",
    "sg:city":"Riverstone",
    "sg:classifiers":[
        {
            "category":"Landmark",
            "subcategory":"Scenic View",
            "type":"Public Place"
        }
    ],
    "sg:phone":"+61 2 9627 9747",
    "sg:postcode":"2765",
    "sg:province":"NSW",
    "sg:tags":[
        "staircase",
        "handrail"
    ],
    "wof:name":"Sure Tread Stair Nosings Pty Ltd",
    "wof:placetype":"venue"
},
  "geometry": {"coordinates":[150.86309814399999,-33.6652145386],"type":"Point"}
}