{
  "type": "Feature",
  "properties": {
    "addr:full":"313 Black Forest Drv Macedon VIC 3440",
    "addr:housenumber":"313",
    "addr:postcode":"3440",
    "addr:street":"Black Forest Drv",
    "iso:country":"AU",
    "sg:address":"313 Black Forest Drv",
    "sg:city":"Macedon",
    "sg:classifiers":[
        {
            "category":"Food & Beverages",
            "subcategory":"Groceries & Convenience Stores",
            "type":"Retail Goods"
        }
    ],
    "sg:phone":"+61 3 5426 1842",
    "sg:postcode":"3440",
    "sg:province":"VIC",
    "wof:name":"Foodies",
    "wof:placetype":"venue"
},
  "geometry": {"coordinates":[144.54460144000001,-37.4143257141],"type":"Point"}
}