{
  "type": "Feature",
  "properties": {
    "addr:full":"11 Apsley Pl Seaford VIC 3198",
    "addr:housenumber":"11",
    "addr:postcode":"3198",
    "iso:country":"AU",
    "sg:address":"11 Apsley Pl",
    "sg:city":"Seaford",
    "sg:classifiers":[
        {
            "category":"Communications",
            "subcategory":"Film & Video Production",
            "type":"Services"
        }
    ],
    "sg:phone":"+61 3 9786 8373",
    "sg:postcode":"3198",
    "sg:province":"VIC",
    "sg:tags":[
        "print",
        "poster",
        "wholesale",
        "pictures"
    ],
    "wof:name":"Mirror Graphics Pty Ltd",
    "wof:placetype":"venue"
},
  "geometry": {"coordinates":[145.14244079599999,-38.1134490967],"type":"Point"}
}