{
  "type": "Feature",
  "properties": {
    "addr:full":"Brand Hwy Greenough WA 6530",
    "addr:postcode":"6530",
    "addr:street":"Brand Hwy",
    "iso:country":"AU",
    "sg:address":"Brand Hwy",
    "sg:city":"Greenough",
    "sg:classifiers":[
        {
            "category":"Wholesale",
            "subcategory":"Fruits & Vegetables",
            "type":"Manufacturing & Wholesale Goods"
        }
    ],
    "sg:phone":"+61 8 9926 1114",
    "sg:postcode":"6530",
    "sg:province":"WA",
    "sg:tags":[
        "produce",
        "grain"
    ],
    "wof:name":"Martins Mill",
    "wof:placetype":"venue"
},
  "geometry": {"coordinates":[114.615470886,-28.7873191833],"type":"Point"}
}