{
  "type": "Feature",
  "properties": {
    "iso:country":"AU",
    "sg:address":"14 St Johns Ave",
    "sg:city":"Springvale",
    "sg:classifiers":[
        {
            "category":"Health Services",
            "subcategory":"Chiropractor",
            "type":"Services"
        }
    ],
    "sg:phone":"+61 3 9546 5183",
    "sg:postcode":"3171",
    "sg:province":"VIC",
    "wof:name":"Kiss Von Soly Dr. N",
    "wof:placetype":"venue"
},
  "geometry": {"coordinates":[145.14996337900001,-37.9496078491],"type":"Point"}
}