{
  "type": "Feature",
  "properties": {
    "iso:country":"AU",
    "sg:address":"88 McIvor Rd",
    "sg:city":"Bendigo",
    "sg:classifiers":[
        {
            "category":"Health Services",
            "subcategory":"Health Practitioner",
            "type":"Services"
        }
    ],
    "sg:phone":"+61 3 5441 3770",
    "sg:postcode":"3550",
    "sg:province":"VIC",
    "sg:tags":[
        "hypnotherapy"
    ],
    "wof:name":"Margaret Biorac",
    "wof:placetype":"venue"
},
  "geometry": {"coordinates":[144.29765319800001,-36.7584877014],"type":"Point"}
}