{
  "type": "Feature",
  "properties": {
    "iso:country":"AU",
    "sg:address":"30 Tongbong St",
    "sg:city":"Rylstone",
    "sg:classifiers":[
        {
            "category":"Shopping",
            "subcategory":"Stationery & Office Supplies",
            "type":"Retail Goods"
        }
    ],
    "sg:phone":"+61 2 6379 1137",
    "sg:postcode":"2849",
    "sg:province":"NSW",
    "sg:tags":[
        "packaging",
        "material"
    ],
    "wof:name":"Escape Packaging",
    "wof:placetype":"venue"
},
  "geometry": {"coordinates":[149.975006,-32.799278],"type":"Point"}
}