{
  "type": "Feature",
  "properties": {
    "addr:full":"PO Box 385 Bribie Island QLD 4507",
    "addr:postcode":"4507",
    "iso:country":"AU",
    "sg:address":"PO Box 385",
    "sg:city":"Bribie Island",
    "sg:classifiers":[
        {
            "category":"Building & Trades",
            "subcategory":"Construction",
            "type":"Services"
        }
    ],
    "sg:phone":"+61 438 340 824",
    "sg:postcode":"4507",
    "sg:province":"QLD",
    "sg:tags":[
        "concrete",
        "contractor"
    ],
    "wof:name":"Oasis Concreting",
    "wof:placetype":"venue"
},
  "geometry": {"coordinates":[153.14137268100001,-26.9570903778],"type":"Point"}
}