{
  "type": "Feature",
  "properties": {
    "addr:full":"15 Bassett St Gladstone QLD 4680",
    "addr:housenumber":"15",
    "addr:postcode":"4680",
    "addr:street":"Bassett St",
    "iso:country":"AU",
    "sg:address":"15 Bassett St",
    "sg:city":"Gladstone",
    "sg:classifiers":[
        {
            "category":"Manufacturing",
            "subcategory":"Metals",
            "type":"Manufacturing & Wholesale Goods"
        }
    ],
    "sg:phone":"+61 7 4976 9088",
    "sg:postcode":"4680",
    "sg:province":"QLD",
    "sg:tags":[
        "wholesaler",
        "aluminium",
        "mfrs"
    ],
    "wof:name":"Atlas Speciality Metals",
    "wof:placetype":"venue"
},
  "geometry": {"coordinates":[151.23034668,-23.8515434265],"type":"Point"}
}