{
  "type": "Feature",
  "properties": {
    "addr:full":"Factory 3/ 10 Simcock St Somerville VIC 3912",
    "addr:housenumber":"/ 10",
    "addr:postcode":"3912",
    "addr:street":"Simcock St",
    "iso:country":"AU",
    "sg:address":"Factory 3/ 10 Simcock St",
    "sg:city":"Somerville",
    "sg:classifiers":[
        {
            "category":"Retail",
            "subcategory":"Auto Repair",
            "type":"Services"
        }
    ],
    "sg:phone":"+61 3 5977 7166",
    "sg:postcode":"3912",
    "sg:province":"VIC",
    "sg:tags":[
        "electrical"
    ],
    "wof:name":"Phillips Auto Spark",
    "wof:placetype":"venue"
},
  "geometry": {"coordinates":[145.176635742,-38.2211990356],"type":"Point"}
}