{
  "type": "Feature",
  "properties": {
    "addr:full":"Munns Drv Woorabinda QLD 4702",
    "addr:postcode":"4702",
    "addr:street":"Munns Drv",
    "iso:country":"AU",
    "sg:address":"Munns Drv",
    "sg:city":"Woorabinda",
    "sg:classifiers":[
        {
            "category":"Food & Beverages",
            "subcategory":"Groceries & Convenience Stores",
            "type":"Retail Goods"
        }
    ],
    "sg:phone":"+61 7 4935 0166",
    "sg:postcode":"4702",
    "sg:province":"QLD",
    "wof:name":"Woorabinda Supermarket",
    "wof:placetype":"venue"
},
  "geometry": {"coordinates":[150.06239318900001,-23.6835422516],"type":"Point"}
}