{
  "type": "Feature",
  "properties": {
    "iso:country":"AU",
    "sg:address":"Cnr Cordelia & Russell Sts",
    "sg:city":"South Brisbane",
    "sg:classifiers":[
        {
            "category":"Wholesale",
            "subcategory":"Non-durable Goods",
            "type":"Manufacturing & Wholesale Goods"
        }
    ],
    "sg:phone":"+61 7 3846 5959",
    "sg:postcode":"4101",
    "sg:province":"QLD",
    "sg:tags":[
        "wholesaler",
        "craft",
        "mfrs"
    ],
    "wof:name":"Gerrys Teddy & Craft Designs",
    "wof:placetype":"venue"
},
  "geometry": {"coordinates":[153.016113281,-27.4763736725],"type":"Point"}
}