{
  "type": "Feature",
  "properties": {
    "addr:full":"105 Normanby Drv Greenvale VIC 3059",
    "addr:housenumber":"105",
    "addr:postcode":"3059",
    "addr:street":"Normanby Drv",
    "iso:country":"AU",
    "sg:address":"105 Normanby Drv",
    "sg:city":"Greenvale",
    "sg:classifiers":[
        {
            "category":"Education",
            "subcategory":"Special Training",
            "type":"Public Place"
        }
    ],
    "sg:phone":"+61 3 9333 4392",
    "sg:postcode":"3059",
    "sg:province":"VIC",
    "sg:tags":[
        "tuition-educational"
    ],
    "wof:name":"Australian Education Academy Pty Ltd",
    "wof:placetype":"venue"
},
  "geometry": {"coordinates":[144.90257263199999,-37.6584701538],"type":"Point"}
}