{
  "type": "Feature",
  "properties": {
    "addr:full":"Level 1, King Arcade 976 High St Armadale VIC 3143",
    "addr:housenumber":"976",
    "addr:postcode":"3143",
    "addr:street":"High St",
    "iso:country":"AU",
    "sg:address":"Level 1, King Arcade 976 High St",
    "sg:city":"Armadale",
    "sg:classifiers":[
        {
            "category":"Health Services",
            "subcategory":"Health Practitioner",
            "type":"Services"
        }
    ],
    "sg:phone":"+61 3 9509 3957",
    "sg:postcode":"3143",
    "sg:province":"VIC",
    "sg:tags":[
        "acupuncture"
    ],
    "wof:name":"Kings Arcade Chinese Medicine",
    "wof:placetype":"venue"
},
  "geometry": {"coordinates":[145.020355225,-37.8555641174],"type":"Point"}
}