{
  "type": "Feature",
  "properties": {
    "addr:full":"692 Princes Hwy Bairnsdale VIC 3875",
    "addr:housenumber":"692",
    "addr:postcode":"3875",
    "addr:street":"Princes Hwy",
    "iso:country":"AU",
    "sg:address":"692 Princes Hwy",
    "sg:city":"Bairnsdale",
    "sg:classifiers":[
        {
            "category":"Shopping",
            "type":"Retail Goods"
        }
    ],
    "sg:phone":"+61 3 5152 3037",
    "sg:postcode":"3875",
    "sg:province":"VIC",
    "sg:tags":[
        "agent",
        "stock"
    ],
    "wof:name":"Elders Ltd",
    "wof:placetype":"venue"
},
  "geometry": {"coordinates":[147.60130310100001,-37.8354530334],"type":"Point"}
}