{
  "type": "Feature",
  "properties": {
    "addr:full":"23 Marriot St Cannington WA 6107",
    "addr:housenumber":"23",
    "addr:postcode":"6107",
    "addr:street":"Marriot St",
    "iso:country":"AU",
    "sg:address":"23 Marriot St",
    "sg:city":"Cannington",
    "sg:classifiers":[
        {
            "category":"Building & Trades",
            "subcategory":"Plumbing",
            "type":"Services"
        }
    ],
    "sg:phone":"+61 418 941 310",
    "sg:postcode":"6107",
    "sg:province":"WA",
    "sg:tags":[
        "plumber",
        "gasfitters"
    ],
    "wof:name":"Bruce's Plumbing Services",
    "wof:placetype":"venue"
},
  "geometry": {"coordinates":[115.9479599,-32.0222396851],"type":"Point"}
}