{
  "type": "Feature",
  "properties": {
    "addr:full":"9/ 61 Southern Cross Drv Ballina NSW 2478",
    "addr:housenumber":"/ 61",
    "addr:postcode":"2478",
    "addr:street":"Southern Cross Drv",
    "iso:country":"AU",
    "sg:address":"9/ 61 Southern Cross Drv",
    "sg:city":"Ballina",
    "sg:classifiers":[
        {
            "category":"Banks & Credit Unions",
            "subcategory":"Investment Brokerage",
            "type":"Services"
        }
    ],
    "sg:phone":"+61 2 6681 6886",
    "sg:postcode":"2478",
    "sg:province":"NSW",
    "sg:tags":[
        "shutter",
        "louvre"
    ],
    "wof:name":"Timber-Tec Blinds & Window Coverings",
    "wof:placetype":"venue"
},
  "geometry": {"coordinates":[153.553833008,-28.847858429],"type":"Point"}
}