{
  "type": "Feature",
  "properties": {
    "addr:full":"35 Dunlop St Mortlake VIC 3272",
    "addr:housenumber":"35",
    "addr:postcode":"3272",
    "addr:street":"Dunlop St",
    "iso:country":"AU",
    "sg:address":"35 Dunlop St",
    "sg:city":"Mortlake",
    "sg:classifiers":[
        {
            "category":"Retail",
            "subcategory":"Auto Rental",
            "type":"Services"
        }
    ],
    "sg:phone":"+61 3 5599 2575",
    "sg:postcode":"3272",
    "sg:province":"VIC",
    "sg:tags":[
        "bus",
        "truck"
    ],
    "wof:name":"Coles Coaches Pty Ltd",
    "wof:placetype":"venue"
},
  "geometry": {"coordinates":[142.801223755,-38.0803222656],"type":"Point"}
}