{
  "type": "Feature",
  "properties": {
    "iso:country":"AU",
    "sg:address":"Ilparpa Rd",
    "sg:city":"Alice Springs",
    "sg:classifiers":[
        {
            "category":"Building & Trades",
            "subcategory":"Landscaping Services",
            "type":"Services"
        }
    ],
    "sg:phone":"+61 8 8952 1946",
    "sg:postcode":"0870",
    "sg:province":"NT",
    "sg:tags":[
        "grazier"
    ],
    "wof:name":"Temple Bar Station",
    "wof:placetype":"venue"
},
  "geometry": {"coordinates":[133.84825134299999,-23.7506732941],"type":"Point"}
}