{
  "type": "Feature",
  "properties": {
    "iso:country":"AU",
    "sg:address":"Suite 108/ 147 King St",
    "sg:city":"Sydney",
    "sg:classifiers":[
        {
            "category":"Banks & Credit Unions",
            "subcategory":"Investment Brokerage",
            "type":"Services"
        }
    ],
    "sg:phone":"+61 410 257 765",
    "sg:postcode":"2000",
    "sg:province":"NSW",
    "sg:tags":[
        "finance",
        "broker"
    ],
    "wof:name":"International Immobiliary",
    "wof:placetype":"venue"
},
  "geometry": {"coordinates":[151.20930480999999,-33.8691215515],"type":"Point"}
}