{
  "type": "Feature",
  "properties": {
    "addr:full":"26 Mulga Rd Hawthorndene SA 5051",
    "addr:housenumber":"26",
    "addr:postcode":"5051",
    "addr:street":"Mulga Rd",
    "iso:country":"AU",
    "sg:address":"26 Mulga Rd",
    "sg:city":"Hawthorndene",
    "sg:classifiers":[
        {
            "category":"Building & Trades",
            "subcategory":"Cleaning & Sanitation",
            "type":"Services"
        }
    ],
    "sg:phone":"+61 408 831 851",
    "sg:postcode":"5051",
    "sg:province":"SA",
    "sg:tags":[
        "wall",
        "brick"
    ],
    "wof:name":"Aqua-blast Brick Cleaning",
    "wof:placetype":"venue"
},
  "geometry": {"coordinates":[138.626465,-35.019936],"type":"Point"}
}