{
  "type": "Feature",
  "properties": {
    "iso:country":"AU",
    "sg:address":"132 Blair St",
    "sg:city":"Coburg",
    "sg:classifiers":[
        {
            "category":"Professional",
            "subcategory":"Computer Services",
            "type":"Services"
        }
    ],
    "sg:phone":"+61 3 9383 1033",
    "sg:postcode":"3058",
    "sg:province":"VIC",
    "sg:tags":[
        "tele-communications",
        "consultant"
    ],
    "wof:name":"Digitech",
    "wof:placetype":"venue"
},
  "geometry": {"coordinates":[144.973846436,-37.7555847168],"type":"Point"}
}