{
  "type": "Feature",
  "properties": {
    "addr:full":"Winfields Rd Laharum North VIC 3401",
    "addr:postcode":"3401",
    "addr:street":"Winfields Rd",
    "iso:country":"AU",
    "sg:address":"Winfields Rd",
    "sg:city":"Laharum North",
    "sg:classifiers":[
        {
            "category":"Wholesale",
            "subcategory":"Plants",
            "type":"Manufacturing & Wholesale Goods"
        }
    ],
    "sg:phone":"+61 3 5383 8235",
    "sg:postcode":"3401",
    "sg:province":"VIC",
    "sg:tags":[
        "florist"
    ],
    "wof:name":"Big Spring Mount Pty Ltd",
    "wof:placetype":"venue"
},
  "geometry": {"coordinates":[142.358154297,-36.8265953064],"type":"Point"}
}