{
  "type": "Feature",
  "properties": {
    "addr:full":"1/ 251 Rothery St Corrimal NSW 2518",
    "addr:housenumber":"/ 251",
    "addr:postcode":"2518",
    "addr:street":"Rothery St",
    "iso:country":"AU",
    "sg:address":"1/ 251 Rothery St",
    "sg:city":"Corrimal",
    "sg:classifiers":[
        {
            "category":"Real Estate",
            "subcategory":"Real Estate Agent",
            "type":"Services"
        }
    ],
    "sg:phone":"+61 2 4284 2148",
    "sg:postcode":"2518",
    "sg:province":"NSW",
    "wof:name":"Blain Eric Real Estate Pty Ltd",
    "wof:placetype":"venue"
},
  "geometry": {"coordinates":[150.90501399999999,-34.367413],"type":"Point"}
}