{
  "type": "Feature",
  "properties": {
    "addr:full":"2/ 9 Bluegum Cl Tuggerah NSW 2259",
    "addr:housenumber":"/ 9",
    "addr:postcode":"2259",
    "addr:street":"Bluegum Cl",
    "iso:country":"AU",
    "sg:address":"2/ 9 Bluegum Cl",
    "sg:city":"Tuggerah",
    "sg:classifiers":[
        {
            "category":"Landmark",
            "subcategory":"Scenic View",
            "type":"Public Place"
        }
    ],
    "sg:phone":"+61 2 4351 2799",
    "sg:postcode":"2259",
    "sg:province":"NSW",
    "sg:tags":[
        "staircase",
        "handrail"
    ],
    "wof:name":"Supreme Wrought Iron",
    "wof:placetype":"venue"
},
  "geometry": {"coordinates":[151.420410156,-33.3050003052],"type":"Point"}
}