{
  "type": "Feature",
  "properties": {
    "iso:country":"AU",
    "sg:address":"53 South Circular Rd",
    "sg:city":"Tullamarine",
    "sg:classifiers":[
        {
            "category":"Utilities",
            "subcategory":"Refuse",
            "type":"Services"
        }
    ],
    "sg:phone":"+61 3 9338 2197",
    "sg:postcode":"3043",
    "sg:province":"VIC",
    "sg:tags":[
        "remover",
        "rubbish"
    ],
    "wof:name":"Russell D J",
    "wof:placetype":"venue"
},
  "geometry": {"coordinates":[144.88713073700001,-37.6903877258],"type":"Point"}
}