{
  "type": "Feature",
  "properties": {
    "addr:full":"56 Hospital Rd Bulli NSW 2516",
    "addr:housenumber":"56",
    "addr:postcode":"2516",
    "addr:street":"Hospital Rd",
    "iso:country":"AU",
    "sg:address":"56 Hospital Rd",
    "sg:city":"Bulli",
    "sg:classifiers":[
        {
            "category":"Wholesale",
            "subcategory":"Home Furnishings",
            "type":"Manufacturing & Wholesale Goods"
        }
    ],
    "sg:phone":"+61 409 656 838",
    "sg:postcode":"2516",
    "sg:province":"NSW",
    "sg:tags":[
        "wholesaler",
        "mfrs",
        "kitchenware"
    ],
    "wof:name":"Rena Ware International",
    "wof:placetype":"venue"
},
  "geometry": {"coordinates":[150.90438800000001,-34.334492],"type":"Point"}
}