{
  "type": "Feature",
  "properties": {
    "addr:full":"4 Seahorse Crt Bribie Island QLD 4507",
    "addr:housenumber":"4",
    "addr:postcode":"4507",
    "addr:street":"Seahorse Crt",
    "iso:country":"AU",
    "sg:address":"4 Seahorse Crt",
    "sg:city":"Bribie Island",
    "sg:classifiers":[
        {
            "category":"Building & Trades",
            "subcategory":"Construction",
            "type":"Services"
        }
    ],
    "sg:phone":"+61 418 712 796",
    "sg:postcode":"4507",
    "sg:province":"QLD",
    "sg:tags":[
        "contractor"
    ],
    "wof:name":"Hartmann & Cunington",
    "wof:placetype":"venue"
},
  "geometry": {"coordinates":[153.13978576700001,-27.0328502655],"type":"Point"}
}