{
  "type": "Feature",
  "properties": {
    "iso:country":"AU",
    "sg:address":"113 Queensbridge St",
    "sg:city":"Southbank",
    "sg:classifiers":[
        {
            "category":"Professional",
            "subcategory":"Accounting & Tax Preparation",
            "type":"Services"
        }
    ],
    "sg:phone":"+61 3 9686 3299",
    "sg:postcode":"3006",
    "sg:province":"VIC",
    "sg:tags":[
        "accountant",
        "auditor"
    ],
    "wof:name":"Financial Life Balance",
    "wof:placetype":"venue"
},
  "geometry": {"coordinates":[144.96051025400001,-37.825012207],"type":"Point"}
}