{
  "type": "Feature",
  "properties": {
    "addr:full":"Unit 7, 8- 10 Industrial Drv Coffs Harbour NSW 2450",
    "addr:housenumber":"8 10",
    "addr:postcode":"2450",
    "addr:street":"Industrial Drv",
    "iso:country":"AU",
    "sg:address":"Unit 7, 8- 10 Industrial Drv",
    "sg:city":"Coffs Harbour",
    "sg:classifiers":[
        {
            "category":"Building & Trades",
            "subcategory":"Construction",
            "type":"Services"
        }
    ],
    "sg:phone":"+61 2 6656 1498",
    "sg:postcode":"2450",
    "sg:province":"NSW",
    "sg:tags":[
        "scaffolding"
    ],
    "sg:website":"http://www.accessguard.com.au",
    "wof:name":"Llongos Enterprises T/A Leon Kelly Scaffolding",
    "wof:placetype":"venue"
},
  "geometry": {"coordinates":[153.087646484,-30.3137989044],"type":"Point"}
}