{
  "type": "Feature",
  "properties": {
    "addr:full":"1125 Pemberton St Albury NSW 2640",
    "addr:housenumber":"1125",
    "addr:postcode":"2640",
    "addr:street":"Pemberton St",
    "iso:country":"AU",
    "sg:address":"1125 Pemberton St",
    "sg:city":"Albury",
    "sg:classifiers":[
        {
            "category":"Health Services",
            "subcategory":"Doctor",
            "type":"Services"
        }
    ],
    "sg:phone":"+61 2 6041 1411",
    "sg:postcode":"2640",
    "sg:province":"NSW",
    "sg:tags":[
        "medical",
        "practitioner"
    ],
    "wof:name":"Albury Wodonga Private Hospital",
    "wof:placetype":"venue"
},
  "geometry": {"coordinates":[146.88211059599999,-36.0752792358],"type":"Point"}
}