{
  "type": "Feature",
  "properties": {
    "addr:full":"Wiseman Rd Bowral NSW 2576",
    "addr:postcode":"2576",
    "addr:street":"Wiseman Rd",
    "iso:country":"AU",
    "sg:address":"Wiseman Rd",
    "sg:city":"Bowral",
    "sg:classifiers":[
        {
            "category":"Building & Trades",
            "subcategory":"Landscaping Services",
            "type":"Services"
        }
    ],
    "sg:phone":"+61 2 4861 4758",
    "sg:postcode":"2576",
    "sg:province":"NSW",
    "sg:tags":[
        "designer",
        "landscape",
        "contractor"
    ],
    "wof:name":"Oxley Landscapes",
    "wof:placetype":"venue"
},
  "geometry": {"coordinates":[150.43307495100001,-34.503112793],"type":"Point"}
}