{
  "type": "Feature",
  "properties": {
    "addr:full":"10 Council St Speers Point NSW 2284",
    "addr:housenumber":"10",
    "addr:postcode":"2284",
    "addr:street":"Council St",
    "iso:country":"AU",
    "sg:address":"10 Council St",
    "sg:city":"Speers Point",
    "sg:classifiers":[
        {
            "category":"Education",
            "subcategory":"Music School",
            "type":"Public Place"
        }
    ],
    "sg:phone":"+61 2 4958 6028",
    "sg:postcode":"2284",
    "sg:province":"NSW",
    "sg:tags":[
        "teacher"
    ],
    "wof:name":"Bill Chaplin",
    "wof:placetype":"venue"
},
  "geometry": {"coordinates":[151.62513732900001,-32.9601554871],"type":"Point"}
}