{
  "type": "Feature",
  "properties": {
    "addr:full":"615 Mt Cotton Rd Sheldon QLD 4157",
    "addr:housenumber":"615",
    "addr:postcode":"4157",
    "addr:street":"Mt Cotton Rd",
    "iso:country":"AU",
    "sg:address":"615 Mt Cotton Rd",
    "sg:city":"Sheldon",
    "sg:classifiers":[
        {
            "category":"Building & Trades",
            "subcategory":"Construction",
            "type":"Services"
        }
    ],
    "sg:phone":"+61 7 3206 1008",
    "sg:postcode":"4157",
    "sg:province":"QLD",
    "sg:tags":[
        "home",
        "air conditioning"
    ],
    "wof:name":"Betta (Queensland)",
    "wof:placetype":"venue"
},
  "geometry": {"coordinates":[153.21516418499999,-27.5684986115],"type":"Point"}
}