{
  "type": "Feature",
  "properties": {
    "addr:full":"19 Fullarton Cct St Helens Park NSW 2560",
    "addr:housenumber":"19",
    "addr:postcode":"2560",
    "addr:street":"Fullarton Cct",
    "iso:country":"AU",
    "sg:address":"19 Fullarton Cct St",
    "sg:city":"Helens Park",
    "sg:classifiers":[
        {
            "category":"Education",
            "subcategory":"Music School",
            "type":"Public Place"
        }
    ],
    "sg:phone":"+61 416 087 705",
    "sg:postcode":"2560",
    "sg:province":"NSW",
    "sg:tags":[
        "choir",
        "bands",
        "orchestra"
    ],
    "wof:name":"&#034;The Simply Bushed&#034; Band",
    "wof:placetype":"venue"
},
  "geometry": {"coordinates":[150.80714416500001,-34.1051216125],"type":"Point"}
}