{
  "type": "Feature",
  "properties": {
    "addr:full":"PO Box 367 Manjimup WA 6258",
    "addr:postcode":"6258",
    "iso:country":"AU",
    "sg:address":"PO Box 367",
    "sg:city":"Manjimup",
    "sg:classifiers":[
        {
            "category":"Farming",
            "subcategory":"Vineyard",
            "type":"Manufacturing & Wholesale Goods"
        }
    ],
    "sg:phone":"+61 8 9771 2499",
    "sg:postcode":"6258",
    "sg:province":"WA",
    "sg:tags":[
        "winery"
    ],
    "wof:name":"Middlesex 31 Wines",
    "wof:placetype":"venue"
},
  "geometry": {"coordinates":[116.14914703399999,-34.2399215698],"type":"Point"}
}