{
  "type": "Feature",
  "properties": {
    "addr:full":"108 Percival Rd Smithfield NSW 2164",
    "addr:housenumber":"108",
    "addr:postcode":"2164",
    "addr:street":"Percival Rd",
    "iso:country":"AU",
    "sg:address":"108 Percival Rd",
    "sg:city":"Smithfield",
    "sg:classifiers":[
        {
            "category":"Manufacturing",
            "subcategory":"Wood Products",
            "type":"Manufacturing & Wholesale Goods"
        }
    ],
    "sg:phone":"+61 2 9609 5939",
    "sg:postcode":"2164",
    "sg:province":"NSW",
    "sg:tags":[
        "polisher",
        "french"
    ],
    "wof:name":"Nunebi Pty Ltd",
    "wof:placetype":"venue"
},
  "geometry": {"coordinates":[150.95062255900001,-33.8382492065],"type":"Point"}
}