{
  "type": "Feature",
  "properties": {
    "addr:full":"24 Thompsons Rd Geelong North VIC 3215",
    "addr:housenumber":"24",
    "addr:postcode":"3215",
    "addr:street":"Thompsons Rd",
    "iso:country":"AU",
    "sg:address":"24 Thompsons Rd",
    "sg:city":"Geelong North",
    "sg:classifiers":[
        {
            "category":"Food & Beverages",
            "subcategory":"Fruits & Vegetables",
            "type":"Retail Goods"
        }
    ],
    "sg:phone":"+61 3 5277 0600",
    "sg:postcode":"3215",
    "sg:province":"VIC",
    "sg:tags":[
        "greengrocer",
        "fruiterer"
    ],
    "wof:name":"Nardi Produce Pty Ltd",
    "wof:placetype":"venue"
},
  "geometry": {"coordinates":[144.341262817,-38.1225547791],"type":"Point"}
}