{
  "type": "Feature",
  "properties": {
    "iso:country":"AU",
    "sg:address":"4/ 10 Production Pl",
    "sg:city":"Penrith",
    "sg:classifiers":[
        {
            "category":"Professional",
            "subcategory":"Engineering",
            "type":"Services"
        }
    ],
    "sg:phone":"+61 2 4721 8836",
    "sg:postcode":"2740",
    "sg:province":"NSW",
    "sg:tags":[
        "manufacturing",
        "engineer"
    ],
    "wof:name":"Opal CNC Pty Ltd",
    "wof:placetype":"venue"
},
  "geometry": {"coordinates":[150.684525,-33.768875],"type":"Point"}
}