{
  "type": "Feature",
  "properties": {
    "addr:full":"5 Byfield St Macquarie Park NSW 2113",
    "addr:housenumber":"5",
    "addr:postcode":"2113",
    "addr:street":"Byfield St",
    "iso:country":"AU",
    "sg:address":"5 Byfield St",
    "sg:city":"Macquarie Park",
    "sg:classifiers":[
        {
            "category":"Shopping",
            "type":"Retail Goods"
        }
    ],
    "sg:phone":"+61 2 9888 6588",
    "sg:postcode":"2113",
    "sg:province":"NSW",
    "sg:tags":[
        "supply",
        "religious",
        "church"
    ],
    "wof:name":"Bible Society Bookshop",
    "wof:placetype":"venue"
},
  "geometry": {"coordinates":[151.12086486800001,-33.7807426453],"type":"Point"}
}