{
  "type": "Feature",
  "properties": {
    "addr:full":"429 Montague Rd Modbury SA 5092",
    "addr:housenumber":"429",
    "addr:postcode":"5092",
    "addr:street":"Montague Rd",
    "iso:country":"AU",
    "sg:address":"429 Montague Rd",
    "sg:city":"Modbury",
    "sg:classifiers":[
        {
            "category":"Sports & Exercise",
            "subcategory":"Gym",
            "type":"Entertainment"
        }
    ],
    "sg:phone":"+61 8 8372 6000",
    "sg:postcode":"5092",
    "sg:province":"SA",
    "sg:tags":[
        "health",
        "fitness"
    ],
    "wof:name":"InShape Womens Studio",
    "wof:placetype":"venue"
},
  "geometry": {"coordinates":[138.671417236,-34.8288612366],"type":"Point"}
}