{
  "type": "Feature",
  "properties": {
    "addr:full":"Lawyer St Maleny QLD 4552",
    "addr:postcode":"4552",
    "addr:street":"Lawyer St",
    "iso:country":"AU",
    "sg:address":"Lawyer St",
    "sg:city":"Maleny",
    "sg:classifiers":[
        {
            "category":"Retail",
            "subcategory":"Laundry & Dry Cleaning",
            "type":"Services"
        }
    ],
    "sg:phone":"+61 7 5499 9822",
    "sg:postcode":"4552",
    "sg:province":"QLD",
    "wof:name":"Hinterland Commercial Laundry",
    "wof:placetype":"venue"
},
  "geometry": {"coordinates":[152.85395813,-26.7601833344],"type":"Point"}
}