{
  "type": "Feature",
  "properties": {
    "addr:full":"9 Pembroke Drv Reynella SA 5161",
    "addr:housenumber":"9",
    "addr:postcode":"5161",
    "addr:street":"Pembroke Drv",
    "iso:country":"AU",
    "sg:address":"9 Pembroke Drv",
    "sg:city":"Reynella",
    "sg:classifiers":[
        {
            "category":"Utilities",
            "subcategory":"Electric",
            "type":"Services"
        }
    ],
    "sg:phone":"+61 8 8381 3225",
    "sg:postcode":"5161",
    "sg:province":"SA",
    "sg:tags":[
        "electrical",
        "contractor"
    ],
    "wof:name":"T.M. Electrical Pty Ltd",
    "wof:placetype":"venue"
},
  "geometry": {"coordinates":[138.52874755900001,-35.0934066772],"type":"Point"}
}