{
  "type": "Feature",
  "properties": {
    "iso:country":"AU",
    "sg:address":"8 May St",
    "sg:city":"Newdegate",
    "sg:classifiers":[
        {
            "category":"Farming",
            "subcategory":"Farm & Veterinary Services",
            "type":"Manufacturing & Wholesale Goods"
        }
    ],
    "sg:phone":"+61 427 055 900",
    "sg:postcode":"6355",
    "sg:province":"WA",
    "sg:tags":[
        "shearing",
        "contractor"
    ],
    "wof:name":"Advance Shearing WA",
    "wof:placetype":"venue"
},
  "geometry": {"coordinates":[119.02491,-33.094158],"type":"Point"}
}