{
  "type": "Feature",
  "properties": {
    "addr:full":"50 Ayr St Doncaster VIC 3108",
    "addr:housenumber":"50",
    "addr:postcode":"3108",
    "addr:street":"Ayr St",
    "iso:country":"AU",
    "sg:address":"50 Ayr St",
    "sg:city":"Doncaster",
    "sg:classifiers":[
        {
            "category":"Food & Beverages",
            "subcategory":"Fruits & Vegetables",
            "type":"Retail Goods"
        }
    ],
    "sg:phone":"+61 3 9857 5836",
    "sg:postcode":"3108",
    "sg:province":"VIC",
    "sg:tags":[
        "wholesale"
    ],
    "wof:name":"Bonadio Fresh Cut",
    "wof:placetype":"venue"
},
  "geometry": {"coordinates":[145.102859497,-37.7832832336],"type":"Point"}
}