{
  "type": "Feature",
  "properties": {
    "addr:full":"10 Mackey St Surry Hills NSW 2010",
    "addr:housenumber":"10",
    "addr:postcode":"2010",
    "addr:street":"Mackey St",
    "iso:country":"AU",
    "sg:address":"10 Mackey St",
    "sg:city":"Surry Hills",
    "sg:classifiers":[
        {
            "category":"Shopping",
            "subcategory":"Clothing, Apparel, & Fashions",
            "type":"Retail Goods"
        }
    ],
    "sg:phone":"+61 2 9282 9413",
    "sg:postcode":"2010",
    "sg:province":"NSW",
    "sg:tags":[
        "lady",
        "wear"
    ],
    "wof:name":"Kirrily Johnston Pty Ltd",
    "wof:placetype":"venue"
},
  "geometry": {"coordinates":[151.211990356,-33.8816261292],"type":"Point"}
}