{
  "type": "Feature",
  "properties": {
    "addr:full":"Gilmore Rd Emerald Creek QLD 4880",
    "addr:postcode":"4880",
    "addr:street":"Gilmore Rd",
    "iso:country":"AU",
    "sg:address":"Gilmore Rd",
    "sg:city":"Emerald Creek",
    "sg:classifiers":[
        {
            "category":"Farming",
            "subcategory":"Farm",
            "type":"Manufacturing & Wholesale Goods"
        }
    ],
    "sg:phone":"+61 7 4093 3126",
    "sg:postcode":"4880",
    "sg:province":"QLD",
    "sg:tags":[
        "farmer"
    ],
    "wof:name":"Myrteza J Q & N",
    "wof:placetype":"venue"
},
  "geometry": {"coordinates":[145.45765685999999,-16.9741153717],"type":"Point"}
}