{
  "type": "Feature",
  "properties": {
    "iso:country":"AU",
    "sg:address":"171 Wattle St",
    "sg:city":"Bankstown",
    "sg:classifiers":[
        {
            "category":"Food & Beverages",
            "subcategory":"Groceries & Convenience Stores",
            "type":"Retail Goods"
        }
    ],
    "sg:phone":"+61 2 9790 0066",
    "sg:postcode":"2200",
    "sg:province":"NSW",
    "wof:name":"Mt Lewis Convenience Store",
    "wof:placetype":"venue"
},
  "geometry": {"coordinates":[151.04748499999999,-33.91795],"type":"Point"}
}