{
  "type": "Feature",
  "properties": {
    "addr:full":"1836 Warburton Hwy Launching Place VIC 3139",
    "addr:housenumber":"1836",
    "addr:postcode":"3139",
    "addr:street":"Warburton Hwy",
    "iso:country":"AU",
    "sg:address":"1836 Warburton Hwy",
    "sg:city":"Launching Place",
    "sg:classifiers":[
        {
            "category":"Manufacturing",
            "subcategory":"Tools & Machinery",
            "type":"Manufacturing & Wholesale Goods"
        }
    ],
    "sg:phone":"+61 419 361 268",
    "sg:postcode":"3139",
    "sg:province":"VIC",
    "sg:tags":[
        "earth",
        "excavating",
        "moving",
        "equipment"
    ],
    "wof:name":"Smithy's Bobcat & Excavator Hire",
    "wof:placetype":"venue"
},
  "geometry": {"coordinates":[145.554397583,-37.7880325317],"type":"Point"}
}