{
  "type": "Feature",
  "properties": {
    "iso:country":"AU",
    "sg:address":"332 High St",
    "sg:city":"Preston",
    "sg:classifiers":[
        {
            "category":"Personal",
            "subcategory":"Beauty Salon",
            "type":"Services"
        }
    ],
    "sg:phone":"+61 3 9471 1585",
    "sg:postcode":"3072",
    "sg:province":"VIC",
    "sg:tags":[
        "hairdresser"
    ],
    "wof:name":"Nga Hairdressing",
    "wof:placetype":"venue"
},
  "geometry": {"coordinates":[145.003662109,-37.7410011292],"type":"Point"}
}