{
  "type": "Feature",
  "properties": {
    "addr:full":"38 Carwarp St Macleod VIC 3085",
    "addr:housenumber":"38",
    "addr:postcode":"3085",
    "addr:street":"Carwarp St",
    "iso:country":"AU",
    "sg:address":"38 Carwarp St",
    "sg:city":"Macleod",
    "sg:classifiers":[
        {
            "category":"Building & Trades",
            "subcategory":"Plumbing",
            "type":"Services"
        }
    ],
    "sg:phone":"+61 3 9459 4754",
    "sg:postcode":"3085",
    "sg:province":"VIC",
    "sg:tags":[
        "plumber",
        "gasfitters"
    ],
    "wof:name":"Carwarp Plumbing",
    "wof:placetype":"venue"
},
  "geometry": {"coordinates":[145.07220459000001,-37.7270965576],"type":"Point"}
}