{
  "type": "Feature",
  "properties": {
    "iso:country":"AU",
    "sg:address":"20 Juna Drv",
    "sg:city":"Malaga",
    "sg:classifiers":[
        {
            "category":"Wholesale",
            "subcategory":"Machinery & Supplies",
            "type":"Manufacturing & Wholesale Goods"
        }
    ],
    "sg:phone":"+61 8 9249 4003",
    "sg:postcode":"6090",
    "sg:province":"WA",
    "sg:tags":[
        "agricultural"
    ],
    "wof:name":"Bare- Co Pty Ltd",
    "wof:placetype":"venue"
},
  "geometry": {"coordinates":[115.90206146200001,-31.8658294678],"type":"Point"}
}