{
  "type": "Feature",
  "properties": {
    "iso:country":"AU",
    "sg:address":"Colson St",
    "sg:city":"Alice Springs",
    "sg:classifiers":[
        {
            "category":"Building & Trades",
            "subcategory":"Construction",
            "type":"Services"
        }
    ],
    "sg:phone":"+61 8 8950 4020",
    "sg:postcode":"0870",
    "sg:province":"NT",
    "sg:tags":[
        "industrial",
        "commercial",
        "air conditioning"
    ],
    "wof:name":"Murray Neck Cool Co",
    "wof:placetype":"venue"
},
  "geometry": {"coordinates":[133.87794494600001,-23.6958389282],"type":"Point"}
}