{
  "type": "Feature",
  "properties": {
    "iso:country":"AU",
    "sg:address":"110 Cummins Rd",
    "sg:city":"Camden",
    "sg:classifiers":[
        {
            "category":"Banks & Credit Unions",
            "subcategory":"Financial Services",
            "type":"Services"
        }
    ],
    "sg:phone":"+61 1800 647 236",
    "sg:postcode":"2570",
    "sg:province":"NSW",
    "sg:tags":[
        "planning"
    ],
    "wof:name":"C B P Investments",
    "wof:placetype":"venue"
},
  "geometry": {"coordinates":[150.69737243599999,-34.148563385],"type":"Point"}
}