{
  "type": "Feature",
  "properties": {
    "addr:full":"Lot 4 Mt Lindsay Hwy Park Ridge QLD 4125",
    "addr:postcode":"4125",
    "addr:street":"Lindsay Hwy",
    "iso:country":"AU",
    "sg:address":"Lot 4 Mt Lindsay Hwy",
    "sg:city":"Park Ridge",
    "sg:classifiers":[
        {
            "category":"Food & Beverages",
            "subcategory":"Fruits & Vegetables",
            "type":"Retail Goods"
        }
    ],
    "sg:phone":"+61 7 3297 0134",
    "sg:postcode":"4125",
    "sg:province":"QLD",
    "sg:tags":[
        "wholesale"
    ],
    "wof:name":"Park Ridge Fruit Market",
    "wof:placetype":"venue"
},
  "geometry": {"coordinates":[153.027420044,-27.7372913361],"type":"Point"}
}