{
  "type": "Feature",
  "properties": {
    "iso:country":"AU",
    "sg:address":"118 Old Canterbury Rd",
    "sg:city":"Lewisham",
    "sg:classifiers":[
        {
            "category":"Home & Garden",
            "subcategory":"Carpets & Floor Coverings",
            "type":"Retail Goods"
        }
    ],
    "sg:phone":"+61 2 9568 5271",
    "sg:postcode":"2049",
    "sg:province":"NSW",
    "sg:tags":[
        "mattress"
    ],
    "wof:name":"Slumberpedic Mattress Factory Pty Ltd",
    "wof:placetype":"venue"
},
  "geometry": {"coordinates":[151.144257,-33.894821],"type":"Point"}
}