{
  "type": "Feature",
  "properties": {
    "addr:full":"14 Lucas St Newcomb VIC 3219",
    "addr:housenumber":"14",
    "addr:postcode":"3219",
    "addr:street":"Lucas St",
    "iso:country":"AU",
    "sg:address":"14 Lucas St",
    "sg:city":"Newcomb",
    "sg:classifiers":[
        {
            "category":"Building & Trades",
            "subcategory":"Construction",
            "type":"Services"
        }
    ],
    "sg:phone":"+61 419 591 457",
    "sg:postcode":"3219",
    "sg:province":"VIC",
    "sg:tags":[
        "renovation",
        "alterations",
        "extension",
        "contractor"
    ],
    "wof:name":"Redi-Fix",
    "wof:placetype":"venue"
},
  "geometry": {"coordinates":[144.39488220199999,-38.1635971069],"type":"Point"}
}