{
  "type": "Feature",
  "properties": {
    "addr:full":"Shp5/ 42 Charles St Iluka NSW 2466",
    "addr:housenumber":"42",
    "addr:postcode":"2466",
    "addr:street":"Charles St",
    "iso:country":"AU",
    "sg:address":"Shp5/ 42 Charles St",
    "sg:city":"Iluka",
    "sg:classifiers":[
        {
            "category":"Personal",
            "subcategory":"Beauty Salon",
            "type":"Services"
        }
    ],
    "sg:phone":"+61 2 6646 6481",
    "sg:postcode":"2466",
    "sg:province":"NSW",
    "sg:tags":[
        "hairdresser"
    ],
    "wof:name":"Iluka Hair Design",
    "wof:placetype":"venue"
},
  "geometry": {"coordinates":[153.352493286,-29.4086208344],"type":"Point"}
}