{
  "type": "Feature",
  "properties": {
    "addr:full":"215a Macquarie St Liverpool NSW 2170",
    "addr:housenumber":"215a",
    "addr:postcode":"2170",
    "addr:street":"Macquarie St",
    "iso:country":"AU",
    "sg:address":"215a Macquarie St",
    "sg:city":"Liverpool",
    "sg:classifiers":[
        {
            "category":"Education",
            "subcategory":"Music School",
            "type":"Public Place"
        }
    ],
    "sg:phone":"+61 2 9824 1048",
    "sg:postcode":"2170",
    "sg:province":"NSW",
    "sg:tags":[
        "teacher"
    ],
    "wof:name":"School of Guitar Technology",
    "wof:placetype":"venue"
},
  "geometry": {"coordinates":[150.92350769000001,-33.9228668213],"type":"Point"}
}