{
  "type": "Feature",
  "properties": {
    "addr:full":"26A View St Beeliar WA 6164",
    "addr:housenumber":"26a",
    "addr:postcode":"6164",
    "addr:street":"View St",
    "iso:country":"AU",
    "sg:address":"26A View St",
    "sg:city":"Beeliar",
    "sg:classifiers":[
        {
            "category":"Professional",
            "type":"Services"
        }
    ],
    "sg:phone":"+61 417 982 564",
    "sg:postcode":"6164",
    "sg:province":"WA",
    "sg:tags":[
        "transport"
    ],
    "wof:name":"Captain Hook",
    "wof:placetype":"venue"
},
  "geometry": {"coordinates":[115.790024,-32.131615],"type":"Point"}
}