{
  "type": "Feature",
  "properties": {
    "addr:full":"5 Beresford Ave Beresfield NSW 2322",
    "addr:housenumber":"5",
    "addr:postcode":"2322",
    "addr:street":"Beresford Ave",
    "iso:country":"AU",
    "sg:address":"5 Beresford Ave",
    "sg:city":"Beresfield",
    "sg:classifiers":[
        {
            "category":"Personal",
            "subcategory":"Beauty Salon",
            "type":"Services"
        }
    ],
    "sg:phone":"+61 2 4966 5797",
    "sg:postcode":"2322",
    "sg:province":"NSW",
    "wof:name":"Essense-De Beaute",
    "wof:placetype":"venue"
},
  "geometry": {"coordinates":[151.65748596200001,-32.8009567261],"type":"Point"}
}