{
  "type": "Feature",
  "properties": {
    "iso:country":"AU",
    "sg:address":"19 Red Hill Rd",
    "sg:city":"Gympie",
    "sg:classifiers":[
        {
            "category":"Social Services",
            "subcategory":"Child Care",
            "type":"Services"
        }
    ],
    "sg:phone":"+61 7 5482 6099",
    "sg:postcode":"4570",
    "sg:province":"QLD",
    "wof:name":"Cooloola Family Day Care",
    "wof:placetype":"venue"
},
  "geometry": {"coordinates":[152.672805786,-26.1938648224],"type":"Point"}
}