{
  "type": "Feature",
  "properties": {
    "addr:full":"74 Glen Osmond Rd Parkside SA 5063",
    "addr:housenumber":"74",
    "addr:postcode":"5063",
    "addr:street":"Glen Osmond Rd",
    "iso:country":"AU",
    "sg:address":"74 Glen Osmond Rd",
    "sg:city":"Parkside",
    "sg:classifiers":[
        {
            "category":"Food & Beverages",
            "subcategory":"Liquor & Beverages",
            "type":"Retail Goods"
        }
    ],
    "sg:phone":"+61 8 8272 9796",
    "sg:postcode":"5063",
    "sg:province":"SA",
    "sg:tags":[
        "store"
    ],
    "wof:name":"BWS Liquor",
    "wof:placetype":"venue"
},
  "geometry": {"coordinates":[138.62014770499999,-34.9434318542],"type":"Point"}
}