{
  "type": "Feature",
  "properties": {
    "addr:full":"Unit 2 84 Swinburne St Lutwyche QLD 4030",
    "addr:housenumber":"84",
    "addr:postcode":"4030",
    "addr:street":"Swinburne St",
    "iso:country":"AU",
    "sg:address":"Unit 2 84 Swinburne St",
    "sg:city":"Lutwyche",
    "sg:classifiers":[
        {
            "category":"Professional",
            "subcategory":"Employment Agencies",
            "type":"Services"
        }
    ],
    "sg:phone":"+61 7 3857 6387",
    "sg:postcode":"4030",
    "sg:province":"QLD",
    "sg:tags":[
        "entertainer",
        "agent"
    ],
    "wof:name":"Peter Grose Comedian",
    "wof:placetype":"venue"
},
  "geometry": {"coordinates":[153.02891500000001,-27.422382],"type":"Point"}
}