{
  "type": "Feature",
  "properties": {
    "iso:country":"AU",
    "sg:address":"Unit 2 84 Swinburne St",
    "sg:city":"Lutwyche",
    "sg:classifiers":[
        {
            "category":"Professional",
            "subcategory":"Employment Agencies",
            "type":"Services"
        }
    ],
    "sg:phone":"+61 7 3857 6387",
    "sg:postcode":"4030",
    "sg:province":"QLD",
    "sg:tags":[
        "entertainer",
        "agent"
    ],
    "wof:name":"Peter Grose Comedian",
    "wof:placetype":"venue"
},
  "geometry": {"coordinates":[153.028915,-27.422382],"type":"Point"}
}