{
  "type": "Feature",
  "properties": {
    "iso:country":"AU",
    "sg:address":"189 Murray Ave",
    "sg:city":"Renmark",
    "sg:classifiers":[
        {
            "category":"Personal",
            "subcategory":"Beauty Salon",
            "type":"Services"
        }
    ],
    "sg:phone":"+61 8 8586 5010",
    "sg:postcode":"5341",
    "sg:province":"SA",
    "sg:tags":[
        "hairdresser"
    ],
    "wof:name":"Such Salon",
    "wof:placetype":"venue"
},
  "geometry": {"coordinates":[140.750289917,-34.173122406],"type":"Point"}
}