{
  "type": "Feature",
  "properties": {
    "addr:full":"30 Jordan Drv One Tree Hill SA 5114",
    "addr:housenumber":"30",
    "addr:postcode":"5114",
    "addr:street":"Jordan Drv",
    "iso:country":"AU",
    "sg:address":"30 Jordan Drv",
    "sg:city":"One Tree Hill",
    "sg:classifiers":[
        {
            "category":"Professional",
            "subcategory":"Detective & Security Services",
            "type":"Services"
        }
    ],
    "sg:phone":"+61 419 398 346",
    "sg:postcode":"5114",
    "sg:province":"SA",
    "sg:tags":[
        "consultant",
        "system"
    ],
    "wof:name":"Rob Green Security",
    "wof:placetype":"venue"
},
  "geometry": {"coordinates":[138.77085876500001,-34.7142219543],"type":"Point"}
}