{
  "type": "Feature",
  "properties": {
    "addr:full":"RMB 2220 Ourimbah NSW 2258",
    "addr:postcode":"2258",
    "iso:country":"AU",
    "sg:address":"RMB 2220",
    "sg:city":"Ourimbah",
    "sg:classifiers":[
        {
            "category":"Building & Trades",
            "subcategory":"Equipment Rental",
            "type":"Services"
        }
    ],
    "sg:phone":"+61 414 705 755",
    "sg:postcode":"2258",
    "sg:province":"NSW",
    "sg:tags":[
        "hire",
        "catering"
    ],
    "wof:name":"Cateraid",
    "wof:placetype":"venue"
},
  "geometry": {"coordinates":[151.369750977,-33.3518981934],"type":"Point"}
}