{
  "type": "Feature",
  "properties": {
    "addr:full":"PO Box 57 Kurmond NSW 2757",
    "addr:postcode":"2757",
    "iso:country":"AU",
    "sg:address":"PO Box 57",
    "sg:city":"Kurmond",
    "sg:classifiers":[
        {
            "category":"Professional",
            "subcategory":"Employment Agencies",
            "type":"Services"
        }
    ],
    "sg:phone":"+61 2 4567 8409",
    "sg:postcode":"2757",
    "sg:province":"NSW",
    "sg:tags":[
        "occupational",
        "therapist"
    ],
    "wof:name":"Liz Martin Occupational Therapist",
    "wof:placetype":"venue"
},
  "geometry": {"coordinates":[150.70112609899999,-33.5494499207],"type":"Point"}
}