{
  "type": "Feature",
  "properties": {
    "addr:full":"PO Box 57 Eagle Heights QLD 4271",
    "addr:postcode":"4271",
    "iso:country":"AU",
    "sg:address":"PO Box 57",
    "sg:city":"Eagle Heights",
    "sg:classifiers":[
        {
            "category":"Building & Trades",
            "subcategory":"Landscaping Services",
            "type":"Services"
        }
    ],
    "sg:phone":"+61 7 5545 3414",
    "sg:postcode":"4271",
    "sg:province":"QLD",
    "sg:tags":[
        "architect",
        "landscape"
    ],
    "wof:name":"The Tim Lyne Consultancy Group",
    "wof:placetype":"venue"
},
  "geometry": {"coordinates":[153.207489014,-27.9224395752],"type":"Point"}
}