{
  "type": "Feature",
  "properties": {
    "addr:full":"198 Bulban Rd Werribee VIC 3030",
    "addr:housenumber":"198",
    "addr:postcode":"3030",
    "addr:street":"Bulban Rd",
    "iso:country":"AU",
    "sg:address":"198 Bulban Rd",
    "sg:city":"Werribee",
    "sg:classifiers":[
        {
            "category":"Farming",
            "subcategory":"Poultry Farm",
            "type":"Manufacturing & Wholesale Goods"
        }
    ],
    "sg:phone":"+61 3 9741 3272",
    "sg:postcode":"3030",
    "sg:province":"VIC",
    "sg:tags":[
        "farmer"
    ],
    "wof:name":"Casaccio Egg Farm",
    "wof:placetype":"venue"
},
  "geometry": {"coordinates":[144.625854,-37.91251],"type":"Point"}
}