{
  "type": "Feature",
  "properties": {
    "iso:country":"AU",
    "sg:address":"Stuart St",
    "sg:city":"Blakehurst",
    "sg:classifiers":[
        {
            "category":"Education",
            "subcategory":"School",
            "type":"Public Place"
        }
    ],
    "sg:phone":"+61 2 9546 1565",
    "sg:postcode":"2221",
    "sg:province":"NSW",
    "sg:tags":[
        "state",
        "-",
        "nsw"
    ],
    "wof:name":"Baldface Public School",
    "wof:placetype":"venue"
},
  "geometry": {"coordinates":[151.11137390100001,-33.98802948],"type":"Point"}
}