{
  "type": "Feature",
  "properties": {
    "iso:country":"AU",
    "sg:address":"608 Peel St",
    "sg:city":"North Ballarat",
    "sg:classifiers":[
        {
            "category":"Shopping",
            "subcategory":"Party Supplies",
            "type":"Retail Goods"
        }
    ],
    "sg:phone":"+61 3 5331 8559",
    "sg:postcode":"3350",
    "sg:province":"VIC",
    "sg:tags":[
        "hire",
        "costume"
    ],
    "wof:name":"Ballarat Light Opera Company Inc.",
    "wof:placetype":"venue"
},
  "geometry": {"coordinates":[143.866455,-37.549282],"type":"Point"}
}