{
  "type": "Feature",
  "properties": {
    "addr:full":"29 Harbour Ave Shute Harbour QLD 4802",
    "addr:housenumber":"29",
    "addr:postcode":"4802",
    "addr:street":"Harbour Ave Shute",
    "iso:country":"AU",
    "sg:address":"29 Harbour Ave",
    "sg:city":"Shute Harbour",
    "sg:classifiers":[
        {
            "category":"Farming",
            "subcategory":"Fish & Marine Products",
            "type":"Manufacturing & Wholesale Goods"
        }
    ],
    "sg:phone":"+61 7 4948 1964",
    "sg:postcode":"4802",
    "sg:province":"QLD",
    "sg:tags":[
        "equipment",
        "salvage"
    ],
    "wof:name":"Engwirda Marine",
    "wof:placetype":"venue"
},
  "geometry": {"coordinates":[148.71969604500001,-20.2692394257],"type":"Point"}
}