{
  "type": "Feature",
  "properties": {
    "addr:full":"160 Marsden Rd Dundas NSW 2117",
    "addr:housenumber":"160",
    "addr:postcode":"2117",
    "addr:street":"Marsden Rd",
    "iso:country":"AU",
    "sg:address":"160 Marsden Rd",
    "sg:city":"Dundas",
    "sg:classifiers":[
        {
            "category":"Wholesale",
            "subcategory":"Machinery & Supplies",
            "type":"Manufacturing & Wholesale Goods"
        }
    ],
    "sg:phone":"+61 2 9670 5867",
    "sg:postcode":"2117",
    "sg:province":"NSW",
    "sg:tags":[
        "equipment",
        "welding"
    ],
    "wof:name":"Wear Protection Pty Ltd",
    "wof:placetype":"venue"
},
  "geometry": {"coordinates":[151.05999755900001,-33.7861289978],"type":"Point"}
}