{
  "type": "Feature",
  "properties": {
    "addr:full":"259 Carlisle St St Kilda East VIC 3183",
    "addr:housenumber":"259",
    "addr:postcode":"3183",
    "addr:street":"Carlisle St",
    "iso:country":"AU",
    "sg:address":"259 Carlisle St St",
    "sg:city":"Kilda East",
    "sg:classifiers":[
        {
            "category":"Personal",
            "subcategory":"Day Spa",
            "type":"Services"
        }
    ],
    "sg:phone":"+61 3 9527 7741",
    "sg:postcode":"3183",
    "sg:province":"VIC",
    "wof:name":"Beauty In Style",
    "wof:placetype":"venue"
},
  "geometry": {"coordinates":[144.99528503400001,-37.8690872192],"type":"Point"}
}