{
  "type": "Feature",
  "properties": {
    "addr:full":"72 Coonawarra Rd Winnellie NT 0820",
    "addr:housenumber":"72",
    "addr:postcode":"nt 0820",
    "addr:street":"Coonawarra Rd",
    "iso:country":"AU",
    "sg:address":"72 Coonawarra Rd",
    "sg:city":"Winnellie",
    "sg:classifiers":[
        {
            "category":"Professional",
            "type":"Services"
        }
    ],
    "sg:phone":"+61 8 8947 1870",
    "sg:postcode":"0820",
    "sg:province":"NT",
    "sg:tags":[
        "transport"
    ],
    "wof:name":"Japanese Engine Centre & Transport Pty Ltd",
    "wof:placetype":"venue"
},
  "geometry": {"coordinates":[130.88165283199999,-12.4305686951],"type":"Point"}
}