{
  "type": "Feature",
  "properties": {
    "addr:full":"9 Napier St Warragul VIC 3820",
    "addr:housenumber":"9",
    "addr:postcode":"3820",
    "addr:street":"Napier St",
    "iso:country":"AU",
    "sg:address":"9 Napier St",
    "sg:city":"Warragul",
    "sg:classifiers":[
        {
            "category":"Bars & Pubs",
            "subcategory":"Nightclub",
            "type":"Food & Drink"
        }
    ],
    "sg:phone":"+61 3 5622 1180",
    "sg:postcode":"3820",
    "sg:province":"VIC",
    "sg:tags":[
        "discotheque"
    ],
    "wof:name":"Buzz Bar",
    "wof:placetype":"venue"
},
  "geometry": {"coordinates":[145.929596,-38.161613],"type":"Point"}
}