{
  "type": "Feature",
  "properties": {
    "addr:full":"43 Drummond St Belmore NSW 2192",
    "addr:housenumber":"43",
    "addr:postcode":"2192",
    "addr:street":"Drummond St",
    "iso:country":"AU",
    "sg:address":"43 Drummond St",
    "sg:city":"Belmore",
    "sg:classifiers":[
        {
            "category":"Education",
            "subcategory":"Junior College",
            "type":"Public Place"
        }
    ],
    "sg:phone":"+61 2 9787 7611",
    "sg:postcode":"2192",
    "sg:province":"NSW",
    "sg:tags":[
        "wholesaler",
        "school",
        "mfrs",
        "uniform"
    ],
    "wof:name":"Luton Hats-Kangol Berets",
    "wof:placetype":"venue"
},
  "geometry": {"coordinates":[151.09191899999999,-33.922382],"type":"Point"}
}