{
  "type": "Feature",
  "properties": {
    "addr:full":"233 Castlereagh St City NSW 2000",
    "addr:housenumber":"233",
    "addr:postcode":"2000",
    "addr:street":"Castlereagh St",
    "iso:country":"AU",
    "sg:address":"233 Castlereagh St",
    "sg:city":"City",
    "sg:classifiers":[
        {
            "category":"Cafe",
            "type":"Food & Drink"
        }
    ],
    "sg:phone":"+61 2 9261 1999",
    "sg:postcode":"2000",
    "sg:province":"NSW",
    "wof:name":"Artos Espresso",
    "wof:placetype":"venue"
},
  "geometry": {"coordinates":[151.20875549300001,-33.8757247925],"type":"Point"}
}