{
  "type": "Feature",
  "properties": {
    "addr:full":"254 Park St Ballarat VIC 3350",
    "addr:housenumber":"254",
    "addr:postcode":"3350",
    "addr:street":"Park St",
    "iso:country":"AU",
    "sg:address":"254 Park St",
    "sg:city":"Ballarat",
    "sg:classifiers":[
        {
            "category":"Transit Center",
            "subcategory":"Freight",
            "type":"Transportation"
        }
    ],
    "sg:phone":"+61 3 5335 7306",
    "sg:postcode":"3350",
    "sg:province":"VIC",
    "sg:tags":[
        "equipment",
        "transport",
        "road",
        "vehicle"
    ],
    "wof:name":"Colrain Ballarat Pty Ltd",
    "wof:placetype":"venue"
},
  "geometry": {"coordinates":[143.822327,-37.570126],"type":"Point"}
}