{
  "type": "Feature",
  "properties": {
    "iso:country":"AU",
    "sg:address":"96 Ellen St",
    "sg:city":"Port Pirie",
    "sg:classifiers":[
        {
            "category":"Restaurant",
            "type":"Food & Drink"
        }
    ],
    "sg:phone":"+61 8 8632 3326",
    "sg:postcode":"5540",
    "sg:province":"SA",
    "wof:name":"Caffe Primo Port Pirie",
    "wof:placetype":"venue"
},
  "geometry": {"coordinates":[138.010055542,-33.176940918],"type":"Point"}
}