{
  "type": "Feature",
  "properties": {
    "iso:country":"AU",
    "sg:address":"Unit 4/ 8 George St",
    "sg:city":"Bunbury",
    "sg:classifiers":[
        {
            "category":"Government",
            "subcategory":"Fire Station",
            "type":"Public Place"
        }
    ],
    "sg:phone":"+61 8 9721 4770",
    "sg:postcode":"6230",
    "sg:province":"WA",
    "sg:tags":[
        "equipment",
        "protection",
        "consultant"
    ],
    "wof:name":"Protector Fire Services Pty Ltd",
    "wof:placetype":"venue"
},
  "geometry": {"coordinates":[115.64167,-33.333527],"type":"Point"}
}