{
  "type": "Feature",
  "properties": {
    "addr:full":"28 Boolimba St Narrabundah ACT 2604",
    "addr:housenumber":"28",
    "addr:postcode":"2604",
    "addr:street":"Boolimba St",
    "iso:country":"AU",
    "sg:address":"28 Boolimba St",
    "sg:city":"Narrabundah",
    "sg:classifiers":[
        {
            "category":"Professional",
            "subcategory":"Art Services",
            "type":"Services"
        }
    ],
    "sg:phone":"+61 2 6232 7435",
    "sg:postcode":"2604",
    "sg:province":"ACT",
    "sg:tags":[
        "decorator",
        "painter"
    ],
    "wof:name":"About Painting & Plaster Repairs",
    "wof:placetype":"venue"
},
  "geometry": {"coordinates":[149.151809692,-35.3319015503],"type":"Point"}
}