{
  "type": "Feature",
  "properties": {
    "addr:full":"62 Grey St Kalbarri WA 6536",
    "addr:housenumber":"62",
    "addr:postcode":"6536",
    "addr:street":"Grey St",
    "iso:country":"AU",
    "sg:address":"62 Grey St",
    "sg:city":"Kalbarri",
    "sg:classifiers":[
        {
            "category":"Airline",
            "type":"Transportation"
        }
    ],
    "sg:phone":"+61 8 9937 1130",
    "sg:postcode":"6536",
    "sg:province":"WA",
    "sg:tags":[
        "aircraft",
        "rental",
        "charter"
    ],
    "wof:name":"Kalbarri Air Charter",
    "wof:placetype":"venue"
},
  "geometry": {"coordinates":[114.16438293500001,-27.7107410431],"type":"Point"}
}