{
  "type": "Feature",
  "properties": {
    "iso:country":"AU",
    "sg:address":"53A Sheridan St",
    "sg:city":"Cairns",
    "sg:classifiers":[
        {
            "category":"Shopping",
            "subcategory":"Beauty & Cosmetics",
            "type":"Retail Goods"
        }
    ],
    "sg:phone":"+61 7 4041 6700",
    "sg:postcode":"4870",
    "sg:province":"QLD",
    "sg:tags":[
        "equipment",
        "salon",
        "supply"
    ],
    "wof:name":"Cairns Hair Beauty & Massage Supplies",
    "wof:placetype":"venue"
},
  "geometry": {"coordinates":[145.77313232399999,-16.9233131409],"type":"Point"}
}