{
  "type": "Feature",
  "properties": {
    "addr:full":"38 Sutherland St Coburg VIC 3058",
    "addr:housenumber":"38",
    "addr:postcode":"3058",
    "addr:street":"Sutherland St",
    "iso:country":"AU",
    "sg:address":"38 Sutherland St",
    "sg:city":"Coburg",
    "sg:classifiers":[
        {
            "category":"Building & Trades",
            "subcategory":"Construction",
            "type":"Services"
        }
    ],
    "sg:phone":"+61 3 8300 8008",
    "sg:postcode":"3058",
    "sg:province":"VIC",
    "sg:tags":[
        "contractor"
    ],
    "wof:name":"Professional Construction Management",
    "wof:placetype":"venue"
},
  "geometry": {"coordinates":[144.961471558,-37.7373924255],"type":"Point"}
}