{
  "type": "Feature",
  "properties": {
    "addr:full":"18 George St Granville NSW 2142",
    "addr:housenumber":"18",
    "addr:postcode":"2142",
    "addr:street":"George St",
    "iso:country":"AU",
    "sg:address":"18 George St",
    "sg:city":"Granville",
    "sg:classifiers":[
        {
            "category":"Retail",
            "subcategory":"Auto Repair",
            "type":"Services"
        }
    ],
    "sg:phone":"+61 2 9897 1378",
    "sg:postcode":"2142",
    "sg:province":"NSW",
    "sg:tags":[
        "repairer",
        "motor",
        "engineer"
    ],
    "wof:name":"Autotech Engineering Pty Ltd",
    "wof:placetype":"venue"
},
  "geometry": {"coordinates":[151.01705932600001,-33.8338279724],"type":"Point"}
}