{
  "type": "Feature",
  "properties": {
    "iso:country":"AU",
    "sg:address":"U3/ 10 Rosford Ave",
    "sg:city":"Petersham",
    "sg:classifiers":[
        {
            "category":"Building & Trades",
            "subcategory":"Cleaning & Sanitation",
            "type":"Services"
        }
    ],
    "sg:phone":"+61 2 9569 9457",
    "sg:postcode":"2049",
    "sg:province":"NSW",
    "sg:tags":[
        "cleaner",
        "repairer",
        "roof"
    ],
    "wof:name":"Roof Improvements",
    "wof:placetype":"venue"
},
  "geometry": {"coordinates":[151.153381,-33.897369],"type":"Point"}
}