{
  "type": "Feature",
  "properties": {
    "addr:full":"PO Box 909 Kununurra WA 6743",
    "addr:postcode":"6743",
    "iso:country":"AU",
    "sg:address":"PO Box 909",
    "sg:city":"Kununurra",
    "sg:classifiers":[
        {
            "category":"Communications",
            "subcategory":"News Services",
            "type":"Services"
        }
    ],
    "sg:phone":"+61 8 9169 1777",
    "sg:postcode":"6743",
    "sg:province":"WA",
    "sg:tags":[
        "information",
        "tourist",
        "attractions"
    ],
    "wof:name":"El Questro Wilderness Park",
    "wof:placetype":"venue"
},
  "geometry": {"coordinates":[128.73936462399999,-15.7726697922],"type":"Point"}
}