{
  "type": "Feature",
  "properties": {
    "addr:full":"10 O'Loughlin St North Mackay QLD 4740",
    "addr:housenumber":"10",
    "addr:postcode":"4740",
    "addr:street":"O'Loughlin St",
    "iso:country":"AU",
    "sg:address":"10 O'Loughlin St",
    "sg:city":"North Mackay",
    "sg:classifiers":[
        {
            "category":"Retail",
            "subcategory":"Auto Repair",
            "type":"Services"
        }
    ],
    "sg:phone":"+61 7 4957 7701",
    "sg:postcode":"4740",
    "sg:province":"QLD",
    "sg:tags":[
        "repairer",
        "motor",
        "engineer"
    ],
    "wof:name":"Camilleri Motors",
    "wof:placetype":"venue"
},
  "geometry": {"coordinates":[149.19430500000001,-21.118513],"type":"Point"}
}