{
  "type": "Feature",
  "properties": {
    "iso:country":"AU",
    "sg:address":"3 Adams St",
    "sg:city":"O&#039;Connor",
    "sg:classifiers":[
        {
            "category":"Building & Trades",
            "subcategory":"Construction",
            "type":"Services"
        }
    ],
    "sg:phone":"+61 8 9314 2878",
    "sg:postcode":"6163",
    "sg:province":"WA",
    "sg:tags":[
        "home",
        "air conditioning"
    ],
    "sg:website":"http://www.atozair.com.au",
    "wof:name":"A to Z Air Conditioning & Heating",
    "wof:placetype":"venue"
},
  "geometry": {"coordinates":[115.801651,-32.062202],"type":"Point"}
}