{
  "type": "Feature",
  "properties": {
    "addr:full":"23- 43 Neville Rd Stockleigh QLD 4280",
    "addr:housenumber":"43",
    "addr:postcode":"4280",
    "addr:street":"Neville Rd",
    "iso:country":"AU",
    "sg:address":"23- 43 Neville Rd",
    "sg:city":"Stockleigh",
    "sg:classifiers":[
        {
            "category":"Transit Center",
            "subcategory":"Freight",
            "type":"Transportation"
        }
    ],
    "sg:phone":"+61 1300 850 876",
    "sg:postcode":"4280",
    "sg:province":"QLD",
    "sg:tags":[
        "honey",
        "merchant"
    ],
    "wof:name":"Kirksbees Honey Pty Ltd",
    "wof:placetype":"venue"
},
  "geometry": {"coordinates":[153.03836100000001,-27.788054],"type":"Point"}
}