{
  "type": "Feature",
  "properties": {
    "addr:full":"9 Harold St Wendouree VIC 3355",
    "addr:housenumber":"9",
    "addr:postcode":"3355",
    "addr:street":"Harold St",
    "iso:country":"AU",
    "sg:address":"9 Harold St",
    "sg:city":"Wendouree",
    "sg:classifiers":[
        {
            "category":"Fast Food",
            "type":"Food & Drink"
        }
    ],
    "sg:phone":"+61 3 5339 1769",
    "sg:postcode":"3355",
    "sg:province":"VIC",
    "sg:tags":[
        "away",
        "take"
    ],
    "wof:name":"Bonanza Pizza",
    "wof:placetype":"venue"
},
  "geometry": {"coordinates":[143.83154300000001,-37.530842],"type":"Point"}
}