{
  "type": "Feature",
  "properties": {
    "addr:full":"16 Frenchs Forest Rd Frenchs Forest NSW 2086",
    "addr:housenumber":"16",
    "addr:postcode":"2086",
    "addr:street":"Frenchs Forest Rd",
    "iso:country":"AU",
    "sg:address":"16 Frenchs Forest Rd",
    "sg:city":"Frenchs Forest",
    "sg:classifiers":[
        {
            "category":"Food & Beverages",
            "subcategory":"Supermarket",
            "type":"Retail Goods"
        }
    ],
    "sg:phone":"+61 2 9451 5219",
    "sg:postcode":"2086",
    "sg:province":"NSW",
    "sg:tags":[
        "grocery",
        "store"
    ],
    "wof:name":"Welcome Mart",
    "wof:placetype":"venue"
},
  "geometry": {"coordinates":[151.24476623499999,-33.7512207031],"type":"Point"}
}