{
  "type": "Feature",
  "properties": {
    "addr:full":"Shop 1109 / Millaroo Drv Helensvale QLD 4212",
    "addr:housenumber":"1109",
    "addr:postcode":"4212",
    "addr:street":"Millaroo Drv",
    "iso:country":"AU",
    "sg:address":"Shop 1109 / Millaroo Drv",
    "sg:city":"Helensvale",
    "sg:classifiers":[
        {
            "category":"Travel",
            "subcategory":"Hotels & Motels",
            "type":"Entertainment"
        }
    ],
    "sg:phone":"+61 7 5580 0099",
    "sg:postcode":"4212",
    "sg:province":"QLD",
    "sg:tags":[
        "pub"
    ],
    "wof:name":"Options Tavern",
    "wof:placetype":"venue"
},
  "geometry": {"coordinates":[153.33462524399999,-27.9292602539],"type":"Point"}
}