{
  "type": "Feature",
  "properties": {
    "addr:full":"Level 2, 108 Flinders St Melbourne VIC 3000",
    "addr:housenumber":"108",
    "addr:postcode":"3000",
    "addr:street":"Flinders St",
    "iso:country":"AU",
    "sg:address":"Level 2, 108 Flinders St",
    "sg:city":"Melbourne",
    "sg:classifiers":[
        {
            "category":"Professional",
            "subcategory":"Computer Services",
            "type":"Services"
        }
    ],
    "sg:phone":"+61 3 9639 7622",
    "sg:postcode":"3000",
    "sg:province":"VIC",
    "sg:tags":[
        "consultant",
        "system"
    ],
    "wof:name":"Softcell Online Systems",
    "wof:placetype":"venue"
},
  "geometry": {"coordinates":[144.971313477,-37.8161811829],"type":"Point"}
}