{
  "type": "Feature",
  "properties": {
    "iso:country":"AU",
    "sg:address":"238 Charters Towers Rd",
    "sg:city":"Hermit Park",
    "sg:classifiers":[
        {
            "category":"Real Estate",
            "subcategory":"Real Estate Agent",
            "type":"Services"
        }
    ],
    "sg:phone":"+61 7 4725 2000",
    "sg:postcode":"4812",
    "sg:province":"QLD",
    "wof:name":"Edmunds First National Real Estate",
    "wof:placetype":"venue"
},
  "geometry": {"coordinates":[146.79719499999999,-19.28672],"type":"Point"}
}