{
  "type": "Feature",
  "properties": {
    "iso:country":"AU",
    "sg:address":"44a Boronia Ave",
    "sg:city":"Cheltenham",
    "sg:classifiers":[
        {
            "category":"Professional",
            "subcategory":"Computer Services",
            "type":"Services"
        }
    ],
    "sg:phone":"+61 2 9869 1068",
    "sg:postcode":"2119",
    "sg:province":"NSW",
    "sg:tags":[
        "tele-communications",
        "consultant"
    ],
    "wof:name":"Tele-Computercations Pty Ltd",
    "wof:placetype":"venue"
},
  "geometry": {"coordinates":[151.072555542,-33.7594604492],"type":"Point"}
}