{
  "type": "Feature",
  "properties": {
    "iso:country":"AU",
    "sg:address":"Suite 1 40 Station Rd",
    "sg:city":"Indooroopilly",
    "sg:classifiers":[
        {
            "category":"Health Services",
            "subcategory":"Doctor",
            "type":"Services"
        }
    ],
    "sg:phone":"+61 7 3878 4377",
    "sg:postcode":"4068",
    "sg:province":"QLD",
    "sg:tags":[
        "medical",
        "practitioner"
    ],
    "wof:name":"Andrews Esther E G",
    "wof:placetype":"venue"
},
  "geometry": {"coordinates":[152.97383117699999,-27.5020561218],"type":"Point"}
}