{
  "type": "Feature",
  "properties": {
    "addr:full":"33 Wells Rd Queanbeyan NSW 2620",
    "addr:housenumber":"33",
    "addr:postcode":"2620",
    "addr:street":"Wells Rd",
    "iso:country":"AU",
    "sg:address":"33 Wells Rd",
    "sg:city":"Queanbeyan",
    "sg:classifiers":[
        {
            "category":"Commercial Area",
            "type":"Public Place"
        }
    ],
    "sg:phone":"+61 2 6297 7425",
    "sg:postcode":"2620",
    "sg:province":"NSW",
    "sg:tags":[
        "heavy",
        "carrier"
    ],
    "sg:website":"http://www.charmanearthmoving.com.au",
    "wof:name":"Charman Earthmoving & Heavy Haulage P/L",
    "wof:placetype":"venue"
},
  "geometry": {"coordinates":[149.168533325,-35.2999687195],"type":"Point"}
}