{
  "type": "Feature",
  "properties": {
    "iso:country":"AU",
    "sg:address":"Shop 41A / 101 North Lake Rd",
    "sg:city":"South Lake",
    "sg:classifiers":[
        {
            "category":"Professional",
            "subcategory":"Accounting & Tax Preparation",
            "type":"Services"
        }
    ],
    "sg:phone":"+61 8 9414 9035",
    "sg:postcode":"6164",
    "sg:province":"WA",
    "sg:tags":[
        "consultant",
        "taxation"
    ],
    "wof:name":"G J North & Associates",
    "wof:placetype":"venue"
},
  "geometry": {"coordinates":[115.840431,-32.11742],"type":"Point"}
}