{
  "type": "Feature",
  "properties": {
    "iso:country":"AU",
    "sg:address":"PO Box 302",
    "sg:city":"Ramsgate",
    "sg:classifiers":[
        {
            "category":"Manufacturing",
            "subcategory":"Tools & Machinery",
            "type":"Manufacturing & Wholesale Goods"
        }
    ],
    "sg:phone":"+61 415 301 089",
    "sg:postcode":"2217",
    "sg:province":"NSW",
    "sg:tags":[
        "earth",
        "excavating",
        "moving",
        "equipment"
    ],
    "wof:name":"Bob Whitford Excavations",
    "wof:placetype":"venue"
},
  "geometry": {"coordinates":[151.13807700000001,-33.984421],"type":"Point"}
}