{
  "type": "Feature",
  "properties": {
    "iso:country":"AU",
    "sg:address":"291 Auburn Rd",
    "sg:city":"Hawthorn",
    "sg:classifiers":[
        {
            "category":"Travel",
            "subcategory":"Travel Agent",
            "type":"Entertainment"
        }
    ],
    "sg:phone":"+61 3 9813 5258",
    "sg:postcode":"3122",
    "sg:province":"VIC",
    "sg:tags":[
        "consultant"
    ],
    "wof:name":"Cuban Adventure Tours",
    "wof:placetype":"venue"
},
  "geometry": {"coordinates":[145.04182434099999,-37.8390235901],"type":"Point"}
}