{
  "type": "Feature",
  "properties": {
    "iso:country":"AU",
    "sg:address":"837 Beaufort St",
    "sg:city":"Inglewood",
    "sg:classifiers":[
        {
            "category":"Health Services",
            "subcategory":"Health Practitioner",
            "type":"Services"
        }
    ],
    "sg:phone":"+61 8 9371 5455",
    "sg:postcode":"6052",
    "sg:province":"WA",
    "sg:tags":[
        "psychologist"
    ],
    "wof:name":"Clinical Psychology",
    "wof:placetype":"venue"
},
  "geometry": {"coordinates":[115.88332366900001,-31.9233837128],"type":"Point"}
}