{
  "type": "Feature",
  "properties": {
    "addr:full":"27 Barnes St Tamworth NSW 2340",
    "addr:housenumber":"27",
    "addr:postcode":"2340",
    "addr:street":"Barnes St",
    "iso:country":"AU",
    "sg:address":"27 Barnes St",
    "sg:city":"Tamworth",
    "sg:classifiers":[
        {
            "category":"Professional",
            "subcategory":"Engineering",
            "type":"Services"
        }
    ],
    "sg:phone":"+61 2 6765 8311",
    "sg:postcode":"2340",
    "sg:province":"NSW",
    "sg:tags":[
        "engineer"
    ],
    "wof:name":"Douglas Industries",
    "wof:placetype":"venue"
},
  "geometry": {"coordinates":[150.914505005,-31.0896816254],"type":"Point"}
}