{
  "type": "Feature",
  "properties": {
    "iso:country":"AU",
    "sg:address":"PO Box 1356",
    "sg:city":"Moree",
    "sg:classifiers":[
        {
            "category":"Professional",
            "subcategory":"Engineering",
            "type":"Services"
        }
    ],
    "sg:phone":"+61 2 6752 5153",
    "sg:postcode":"2400",
    "sg:province":"NSW",
    "sg:tags":[
        "consulting",
        "engineer"
    ],
    "wof:name":"Bridge & General",
    "wof:placetype":"venue"
},
  "geometry": {"coordinates":[149.841598511,-29.4661998749],"type":"Point"}
}