{
  "type": "Feature",
  "properties": {
    "iso:country":"AU",
    "sg:address":"68 Cambridge St",
    "sg:city":"Cambridge Park",
    "sg:classifiers":[
        {
            "category":"Building & Trades",
            "subcategory":"Construction",
            "type":"Services"
        }
    ],
    "sg:phone":"+61 2 4721 2418",
    "sg:postcode":"2747",
    "sg:province":"NSW",
    "sg:tags":[
        "fencing",
        "contractor"
    ],
    "wof:name":"Stephen's Fencing",
    "wof:placetype":"venue"
},
  "geometry": {"coordinates":[150.723999023,-33.7514152527],"type":"Point"}
}