{
  "type": "Feature",
  "properties": {
    "addr:full":"50 Lodges Rd Narellan NSW 2567",
    "addr:housenumber":"50",
    "addr:postcode":"2567",
    "addr:street":"Lodges Rd",
    "iso:country":"AU",
    "sg:address":"50 Lodges Rd",
    "sg:city":"Narellan",
    "sg:classifiers":[
        {
            "category":"Retail",
            "subcategory":"Event Space",
            "type":"Services"
        }
    ],
    "sg:phone":"+61 2 4646 1203",
    "sg:postcode":"2567",
    "sg:province":"NSW",
    "sg:tags":[
        "venue",
        "reception",
        "wedding"
    ],
    "wof:name":"Camden Golf Club",
    "wof:placetype":"venue"
},
  "geometry": {"coordinates":[150.731658936,-34.0515289307],"type":"Point"}
}