{
  "type": "Feature",
  "properties": {
    "addr:full":"41 Mitchell St Shepparton VIC 3630",
    "addr:housenumber":"41",
    "addr:postcode":"3630",
    "addr:street":"Mitchell St",
    "iso:country":"AU",
    "sg:address":"41 Mitchell St",
    "sg:city":"Shepparton",
    "sg:classifiers":[
        {
            "category":"Shopping",
            "subcategory":"Crafts & Fabrics",
            "type":"Retail Goods"
        }
    ],
    "sg:phone":"+61 3 5831 1689",
    "sg:postcode":"3630",
    "sg:province":"VIC",
    "sg:tags":[
        "synthetic",
        "canvas",
        "product"
    ],
    "wof:name":"Tremellen Trim & Canvas",
    "wof:placetype":"venue"
},
  "geometry": {"coordinates":[145.420410156,-36.3810653687],"type":"Point"}
}