{
  "type": "Feature",
  "properties": {
    "iso:country":"AU",
    "sg:address":"4 Vista Drv",
    "sg:city":"Emerald",
    "sg:classifiers":[
        {
            "category":"Manufacturing",
            "subcategory":"Motor Vehicles & Parts",
            "type":"Manufacturing & Wholesale Goods"
        }
    ],
    "sg:phone":"+61 3 5968 3612",
    "sg:postcode":"3782",
    "sg:province":"VIC",
    "sg:tags":[
        "wholesaler",
        "cycle",
        "mfrs",
        "accessory"
    ],
    "wof:name":"Attitude Motor Cycle Engineering",
    "wof:placetype":"venue"
},
  "geometry": {"coordinates":[145.465317,-37.929306],"type":"Point"}
}