{
  "type": "Feature",
  "properties": {
    "addr:full":"5 Cherry Crt Young NSW 2594",
    "addr:housenumber":"5",
    "addr:postcode":"2594",
    "addr:street":"Cherry Crt",
    "iso:country":"AU",
    "sg:address":"5 Cherry Crt",
    "sg:city":"Young",
    "sg:classifiers":[
        {
            "category":"Professional",
            "subcategory":"Business Services",
            "type":"Services"
        }
    ],
    "sg:phone":"+61 2 6382 5975",
    "sg:postcode":"2594",
    "sg:province":"NSW",
    "sg:tags":[
        "broker"
    ],
    "wof:name":"South West Business Services",
    "wof:placetype":"venue"
},
  "geometry": {"coordinates":[148.30235290499999,-34.3022613525],"type":"Point"}
}