{
  "type": "Feature",
  "properties": {
    "iso:country":"AU",
    "sg:address":"Cnr Grandis Crs & Poinciana Ave",
    "sg:city":"Victoria Point",
    "sg:classifiers":[
        {
            "category":"Social Services",
            "subcategory":"Child Care",
            "type":"Services"
        }
    ],
    "sg:phone":"+61 7 3207 6444",
    "sg:postcode":"4165",
    "sg:province":"QLD",
    "wof:name":"Benfer Road Child Care Centre",
    "wof:placetype":"venue"
},
  "geometry": {"coordinates":[153.28811645499999,-27.5903377533],"type":"Point"}
}