{
  "type": "Feature",
  "properties": {
    "addr:full":"49 Oleander Ave Scarness QLD 4655",
    "addr:housenumber":"49",
    "addr:postcode":"4655",
    "addr:street":"Oleander Ave",
    "iso:country":"AU",
    "sg:address":"49 Oleander Ave",
    "sg:city":"Scarness",
    "sg:classifiers":[
        {
            "category":"Health Services",
            "subcategory":"Health Practitioner",
            "type":"Services"
        }
    ],
    "sg:phone":"+61 7 4124 7953",
    "sg:postcode":"4655",
    "sg:province":"QLD",
    "sg:tags":[
        "alternative"
    ],
    "wof:name":"Yul'lu Rainbow Connection Centre",
    "wof:placetype":"venue"
},
  "geometry": {"coordinates":[152.845337,-25.293056],"type":"Point"}
}