{
  "type": "Feature",
  "properties": {
    "addr:full":"58 Yoku Rd Ashgrove QLD 4060",
    "addr:housenumber":"58",
    "addr:postcode":"4060",
    "addr:street":"Yoku Rd",
    "iso:country":"AU",
    "sg:address":"58 Yoku Rd",
    "sg:city":"Ashgrove",
    "sg:classifiers":[
        {
            "category":"Building & Trades",
            "subcategory":"Construction",
            "type":"Services"
        }
    ],
    "sg:phone":"+61 7 3366 7244",
    "sg:postcode":"4060",
    "sg:province":"QLD",
    "sg:tags":[
        "contractor"
    ],
    "wof:name":"Imagine Constructions",
    "wof:placetype":"venue"
},
  "geometry": {"coordinates":[152.97601318400001,-27.44323349],"type":"Point"}
}