{
  "type": "Feature",
  "properties": {
    "iso:country":"AU",
    "sg:address":"104 Lauriston Drv",
    "sg:city":"Coldstream",
    "sg:classifiers":[
        {
            "category":"Farming",
            "subcategory":"Nursery",
            "type":"Manufacturing & Wholesale Goods"
        }
    ],
    "sg:phone":"+61 3 9739 1285",
    "sg:postcode":"3770",
    "sg:province":"VIC",
    "wof:name":"Nursery Link Pty Ltd",
    "wof:placetype":"venue"
},
  "geometry": {"coordinates":[145.384659,-37.733063],"type":"Point"}
}