{
  "type": "Feature",
  "properties": {
    "addr:full":"2/ 157 Gordon St Port Macquarie NSW 2444",
    "addr:housenumber":"/ 157",
    "addr:postcode":"2444",
    "addr:street":"Gordon St",
    "iso:country":"AU",
    "sg:address":"2/ 157 Gordon St",
    "sg:city":"Port Macquarie",
    "sg:classifiers":[
        {
            "category":"Health Services",
            "subcategory":"Health Practitioner",
            "type":"Services"
        }
    ],
    "sg:phone":"+61 2 6583 7477",
    "sg:postcode":"2444",
    "sg:province":"NSW",
    "sg:tags":[
        "physiotherapist"
    ],
    "wof:name":"Port Macquarie Physiotherapy Clinic Pty Ltd",
    "wof:placetype":"venue"
},
  "geometry": {"coordinates":[152.90136699999999,-31.434643],"type":"Point"}
}