{
  "type": "Feature",
  "properties": {
    "iso:country":"AU",
    "sg:address":"92 Victoria St",
    "sg:city":"Dubbo",
    "sg:classifiers":[
        {
            "category":"Wholesale",
            "subcategory":"Medical Equipment & Supplies",
            "type":"Manufacturing & Wholesale Goods"
        }
    ],
    "sg:phone":"+61 2 6882 9029",
    "sg:postcode":"2830",
    "sg:province":"NSW",
    "sg:tags":[
        "aid",
        "care",
        "health",
        "home"
    ],
    "wof:name":"Orana Disability Sales & Service",
    "wof:placetype":"venue"
},
  "geometry": {"coordinates":[148.59344482399999,-32.2485694885],"type":"Point"}
}