{
  "type": "Feature",
  "properties": {
    "iso:country":"AU",
    "sg:address":"89 Murray St",
    "sg:city":"Tanunda",
    "sg:classifiers":[
        {
            "category":"Cafe",
            "type":"Food & Drink"
        }
    ],
    "sg:phone":"+61 8 8563 2527",
    "sg:postcode":"5352",
    "sg:province":"SA",
    "wof:name":"La Buona Vita",
    "wof:placetype":"venue"
},
  "geometry": {"coordinates":[138.969482422,-34.5169181824],"type":"Point"}
}