{
  "type": "Feature",
  "properties": {
    "addr:full":"356 Main Rd Coromandel Valley SA 5051",
    "addr:housenumber":"356",
    "addr:postcode":"5051",
    "addr:street":"Main Rd",
    "iso:country":"AU",
    "sg:address":"356 Main Rd",
    "sg:city":"Coromandel Valley",
    "sg:classifiers":[
        {
            "category":"Home & Garden",
            "subcategory":"Building Materials",
            "type":"Retail Goods"
        }
    ],
    "sg:phone":"+61 404 021 021",
    "sg:postcode":"5051",
    "sg:province":"SA",
    "sg:tags":[
        "lawn",
        "cutting",
        "maintenance"
    ],
    "wof:name":"Maybrook Lawn & Garden Maintenance",
    "wof:placetype":"venue"
},
  "geometry": {"coordinates":[138.62472500000001,-35.042198],"type":"Point"}
}