{
  "type": "Feature",
  "properties": {
    "iso:country":"AU",
    "sg:address":"118 Beveridge St",
    "sg:city":"Swan Hill",
    "sg:classifiers":[
        {
            "category":"Government",
            "subcategory":"City Hall",
            "type":"Public Place"
        }
    ],
    "sg:phone":"+61 3 5032 9813",
    "sg:postcode":"3585",
    "sg:province":"VIC",
    "wof:name":"Masonic Halls",
    "wof:placetype":"venue"
},
  "geometry": {"coordinates":[143.558044,-35.339314],"type":"Point"}
}