{
  "type": "Feature",
  "properties": {
    "addr:full":"PO Box 1189 Canning Vale Pte Boxes WA 6970",
    "addr:postcode":"6970",
    "addr:street":"Vale",
    "iso:country":"AU",
    "sg:address":"PO Box 1189",
    "sg:city":"Canning Vale Pte Boxes",
    "sg:classifiers":[
        {
            "category":"Retail",
            "subcategory":"Auto Rental",
            "type":"Services"
        }
    ],
    "sg:phone":"+61 8 9493 2877",
    "sg:postcode":"6970",
    "sg:province":"WA",
    "sg:tags":[
        "chauffeur",
        "car",
        "hire",
        "driven",
        "limousine"
    ],
    "wof:name":"Advanced Limousines",
    "wof:placetype":"venue"
},
  "geometry": {"coordinates":[115.920921326,-32.0658683777],"type":"Point"}
}