{
  "type": "Feature",
  "properties": {
    "iso:country":"AU",
    "sg:address":"27 Tennant St",
    "sg:city":"Welshpool",
    "sg:classifiers":[
        {
            "category":"Home & Garden",
            "subcategory":"Hardware",
            "type":"Retail Goods"
        }
    ],
    "sg:phone":"+61 1300 657 756",
    "sg:postcode":"6106",
    "sg:province":"WA",
    "sg:tags":[
        "compressor",
        "air"
    ],
    "sg:website":"http://www.pneumat.com.au",
    "wof:name":"Pneumatic Engineering",
    "wof:placetype":"venue"
},
  "geometry": {"coordinates":[115.919021606,-31.9960575104],"type":"Point"}
}