{
  "type": "Feature",
  "properties": {
    "addr:full":"Cnr Merrylands Rd & Miller St Merrylands NSW 2160",
    "addr:postcode":"2160",
    "addr:street":"Cnr Merrylands Rd & Miller St",
    "iso:country":"AU",
    "sg:address":"Cnr Merrylands Rd & Miller St",
    "sg:city":"Merrylands",
    "sg:classifiers":[
        {
            "category":"Personal",
            "subcategory":"Beauty Salon",
            "type":"Services"
        }
    ],
    "sg:phone":"+61 2 9682 3559",
    "sg:postcode":"2160",
    "sg:province":"NSW",
    "sg:tags":[
        "hairdresser"
    ],
    "wof:name":"George Kosseifi",
    "wof:placetype":"venue"
},
  "geometry": {"coordinates":[150.988204956,-33.8361282349],"type":"Point"}
}