{
  "type": "Feature",
  "properties": {
    "addr:full":"45 Cordelia St South Brisbane QLD 4101",
    "addr:housenumber":"45",
    "addr:postcode":"4101",
    "addr:street":"Cordelia St",
    "iso:country":"AU",
    "sg:address":"45 Cordelia St",
    "sg:city":"South Brisbane",
    "sg:classifiers":[
        {
            "category":"Professional",
            "subcategory":"Employment Agencies",
            "type":"Services"
        }
    ],
    "sg:phone":"+61 7 3846 7730",
    "sg:postcode":"4101",
    "sg:province":"QLD",
    "wof:name":"Pure Source Recruitment",
    "wof:placetype":"venue"
},
  "geometry": {"coordinates":[153.01620483400001,-27.4767284393],"type":"Point"}
}