{
  "type": "Feature",
  "properties": {
    "iso:country":"AU",
    "sg:address":"5 Wauchope Ave",
    "sg:city":"Narre Warren",
    "sg:classifiers":[
        {
            "category":"Professional",
            "subcategory":"Engineering",
            "type":"Services"
        }
    ],
    "sg:phone":"+61 3 9796 7636",
    "sg:postcode":"3805",
    "sg:province":"VIC",
    "sg:tags":[
        "engineer"
    ],
    "wof:name":"Istvan Engineering",
    "wof:placetype":"venue"
},
  "geometry": {"coordinates":[145.313553,-38.028202],"type":"Point"}
}