{
  "type": "Feature",
  "properties": {
    "addr:full":"115 High St Avoca VIC 3467",
    "addr:housenumber":"115",
    "addr:postcode":"3467",
    "addr:street":"High St",
    "iso:country":"AU",
    "sg:address":"115 High St",
    "sg:city":"Avoca",
    "sg:classifiers":[
        {
            "category":"Travel",
            "subcategory":"Hotels & Motels",
            "type":"Entertainment"
        }
    ],
    "sg:phone":"+61 3 5465 3018",
    "sg:postcode":"3467",
    "sg:province":"VIC",
    "sg:tags":[
        "accommodation"
    ],
    "wof:name":"Avoca Hotel",
    "wof:placetype":"venue"
},
  "geometry": {"coordinates":[143.47373962399999,-37.0888824463],"type":"Point"}
}