{
  "type": "Feature",
  "properties": {
    "addr:full":"PO Box 4303 Langwarrin VIC 3910",
    "addr:postcode":"3910",
    "iso:country":"AU",
    "sg:address":"PO Box 4303",
    "sg:city":"Langwarrin",
    "sg:classifiers":[
        {
            "category":"Professional",
            "subcategory":"Business Services",
            "type":"Services"
        }
    ],
    "sg:phone":"+61 408 754 475",
    "sg:postcode":"3910",
    "sg:province":"VIC",
    "sg:tags":[
        "drafting"
    ],
    "wof:name":"Philip Harvey & Associates",
    "wof:placetype":"venue"
},
  "geometry": {"coordinates":[145.20420837399999,-38.1449012756],"type":"Point"}
}