{
  "type": "Feature",
  "properties": {
    "iso:country":"AU",
    "sg:address":"43 Heathcote Rd",
    "sg:city":"Moorebank",
    "sg:classifiers":[
        {
            "category":"Home & Garden",
            "subcategory":"Carpets & Floor Coverings",
            "type":"Retail Goods"
        }
    ],
    "sg:phone":"+61 2 9822 4166",
    "sg:postcode":"2170",
    "sg:province":"NSW",
    "sg:tags":[
        "tile",
        "wall"
    ],
    "wof:name":"Western Suburbs Tiles",
    "wof:placetype":"venue"
},
  "geometry": {"coordinates":[150.939254761,-33.9384422302],"type":"Point"}
}