{
  "type": "Feature",
  "properties": {
    "addr:full":"Blair St Harrow VIC 3317",
    "addr:postcode":"3317",
    "addr:street":"Blair St",
    "iso:country":"AU",
    "sg:address":"Blair St",
    "sg:city":"Harrow",
    "sg:classifiers":[
        {
            "category":"Cafe",
            "type":"Food & Drink"
        }
    ],
    "sg:phone":"+61 3 5588 1205",
    "sg:postcode":"3317",
    "sg:province":"VIC",
    "wof:name":"Harrow Cafe Store",
    "wof:placetype":"venue"
},
  "geometry": {"coordinates":[141.594207764,-37.1615447998],"type":"Point"}
}