{
  "type": "Feature",
  "properties": {
    "addr:full":"118 King St Buderim QLD 4556",
    "addr:housenumber":"118",
    "addr:postcode":"4556",
    "addr:street":"King St",
    "iso:country":"AU",
    "sg:address":"118 King St",
    "sg:city":"Buderim",
    "sg:classifiers":[
        {
            "category":"Health Services",
            "subcategory":"Doctor",
            "type":"Services"
        }
    ],
    "sg:phone":"+61 7 5453 4322",
    "sg:postcode":"4556",
    "sg:province":"QLD",
    "sg:tags":[
        "medical",
        "practitioner"
    ],
    "wof:name":"Schulze K R DR",
    "wof:placetype":"venue"
},
  "geometry": {"coordinates":[153.06858825699999,-26.6828327179],"type":"Point"}
}