{
  "type": "Feature",
  "properties": {
    "addr:full":"56 Bago View Drv Wauchope NSW 2446",
    "addr:housenumber":"56",
    "addr:postcode":"2446",
    "addr:street":"Bago View Drv",
    "iso:country":"AU",
    "sg:address":"56 Bago View Drv",
    "sg:city":"Wauchope",
    "sg:classifiers":[
        {
            "category":"Farming",
            "subcategory":"Livestock Farm",
            "type":"Manufacturing & Wholesale Goods"
        }
    ],
    "sg:phone":"+61 412 056 145",
    "sg:postcode":"2446",
    "sg:province":"NSW",
    "sg:tags":[
        "breeder",
        "horse",
        "stud"
    ],
    "wof:name":"Azale Arabians",
    "wof:placetype":"venue"
},
  "geometry": {"coordinates":[152.68373099999999,-31.444218],"type":"Point"}
}