{
  "type": "Feature",
  "properties": {
    "addr:full":"Marine Pde Southport QLD 4215",
    "addr:postcode":"4215",
    "addr:street":"Marine Pde",
    "iso:country":"AU",
    "sg:address":"Marine Pde",
    "sg:city":"Southport",
    "sg:classifiers":[
        {
            "category":"Shopping",
            "subcategory":"Jewelry",
            "type":"Retail Goods"
        }
    ],
    "sg:phone":"+61 7 5591 4966",
    "sg:postcode":"4215",
    "sg:province":"QLD",
    "sg:tags":[
        "jeweller"
    ],
    "wof:name":"Kleins Jewellery",
    "wof:placetype":"venue"
},
  "geometry": {"coordinates":[153.41558837900001,-27.9655361176],"type":"Point"}
}