{
  "type": "Feature",
  "properties": {
    "addr:full":"96A Murrumbeena Rd Murrumbeena VIC 3163",
    "addr:housenumber":"96a",
    "addr:postcode":"3163",
    "addr:street":"Murrumbeena Rd",
    "iso:country":"AU",
    "sg:address":"96A Murrumbeena Rd",
    "sg:city":"Murrumbeena",
    "sg:classifiers":[
        {
            "category":"Transit Center",
            "subcategory":"Passenger",
            "type":"Transportation"
        }
    ],
    "sg:phone":"+61 3 9569 0488",
    "sg:postcode":"3163",
    "sg:province":"VIC",
    "sg:tags":[
        "frozen",
        "food",
        "retail"
    ],
    "wof:name":"Katrina's Kitchen",
    "wof:placetype":"venue"
},
  "geometry": {"coordinates":[145.06642150900001,-37.8909835815],"type":"Point"}
}