{
  "type": "Feature",
  "properties": {
    "addr:full":"213 Elizabeth St Melbourne VIC 3000",
    "addr:housenumber":"213",
    "addr:postcode":"3000",
    "addr:street":"Elizabeth St",
    "iso:country":"AU",
    "sg:address":"213 Elizabeth St",
    "sg:city":"Melbourne",
    "sg:classifiers":[
        {
            "category":"Fast Food",
            "type":"Food & Drink"
        }
    ],
    "sg:phone":"+61 3 9670 3568",
    "sg:postcode":"3000",
    "sg:province":"VIC",
    "sg:tags":[
        "away",
        "take"
    ],
    "wof:name":"Tropicana Juice/Food Bar",
    "wof:placetype":"venue"
},
  "geometry": {"coordinates":[144.962646484,-37.8134498596],"type":"Point"}
}