{
  "type": "Feature",
  "properties": {
    "addr:full":"54 Miles St Mt Isa QLD 4825",
    "addr:housenumber":"54",
    "addr:postcode":"4825",
    "addr:street":"Miles St",
    "iso:country":"AU",
    "sg:address":"54 Miles St",
    "sg:city":"Mt Isa",
    "sg:classifiers":[
        {
            "category":"Retail",
            "subcategory":"Car Wash",
            "type":"Services"
        }
    ],
    "sg:phone":"+61 7 4743 2209",
    "sg:postcode":"4825",
    "sg:province":"QLD",
    "sg:tags":[
        "merchant",
        "oil",
        "refiner"
    ],
    "wof:name":"Castrol Australia Pty Limited",
    "wof:placetype":"venue"
},
  "geometry": {"coordinates":[139.492569,-20.722036],"type":"Point"}
}