{
  "type": "Feature",
  "properties": {
    "addr:full":"134 Gilles St Adelaide SA 5000",
    "addr:housenumber":"134",
    "addr:postcode":"5000",
    "addr:street":"Gilles St",
    "iso:country":"AU",
    "sg:address":"134 Gilles St",
    "sg:city":"Adelaide",
    "sg:classifiers":[
        {
            "category":"Professional",
            "subcategory":"Art Services",
            "type":"Services"
        }
    ],
    "sg:phone":"+61 8 8232 3204",
    "sg:postcode":"5000",
    "sg:province":"SA",
    "sg:tags":[
        "graphic",
        "designer"
    ],
    "wof:name":"Woodscannon",
    "wof:placetype":"venue"
},
  "geometry": {"coordinates":[138.60508727999999,-34.933921814],"type":"Point"}
}