{
  "type": "Feature",
  "properties": {
    "addr:full":"292 Mann St Armidale NSW 2350",
    "addr:housenumber":"292",
    "addr:postcode":"2350",
    "addr:street":"Mann St",
    "iso:country":"AU",
    "sg:address":"292 Mann St",
    "sg:city":"Armidale",
    "sg:classifiers":[
        {
            "category":"Utilities",
            "type":"Services"
        }
    ],
    "sg:phone":"+61 2 6772 2555",
    "sg:postcode":"2350",
    "sg:province":"NSW",
    "sg:tags":[
        "refrigeration",
        "industrial",
        "commercial",
        "retail"
    ],
    "wof:name":"Armidale Air Conditioning Pty Ltd",
    "wof:placetype":"venue"
},
  "geometry": {"coordinates":[151.641647339,-30.5144710541],"type":"Point"}
}