{
  "type": "Feature",
  "properties": {
    "addr:full":"265a Macquarie St Liverpool NSW 2170",
    "addr:housenumber":"265a",
    "addr:postcode":"2170",
    "addr:street":"Macquarie St",
    "iso:country":"AU",
    "sg:address":"265a Macquarie St",
    "sg:city":"Liverpool",
    "sg:classifiers":[
        {
            "category":"Banks & Credit Unions",
            "subcategory":"Financial Services",
            "type":"Services"
        }
    ],
    "sg:phone":"+61 1300 262 933",
    "sg:postcode":"2170",
    "sg:province":"NSW",
    "sg:tags":[
        "loan",
        "finance",
        "mortgage"
    ],
    "sg:website":"http://www.amazingloans.com.au",
    "wof:name":"Amazing Loans",
    "wof:placetype":"venue"
},
  "geometry": {"coordinates":[150.92326355,-33.9241065979],"type":"Point"}
}