{
  "type": "Feature",
  "properties": {
    "iso:country":"AU",
    "sg:address":"Suite 18/ 245 Bayview St",
    "sg:city":"Runaway Bay",
    "sg:classifiers":[
        {
            "category":"Banks & Credit Unions",
            "subcategory":"Financial Services",
            "type":"Services"
        }
    ],
    "sg:phone":"+61 1300 556 661",
    "sg:postcode":"4216",
    "sg:province":"QLD",
    "sg:tags":[
        "loan",
        "finance",
        "mortgage"
    ],
    "wof:name":"AAA Credit",
    "wof:placetype":"venue"
},
  "geometry": {"coordinates":[153.40415954599999,-27.9216747284],"type":"Point"}
}