{
  "type": "Feature",
  "properties": {
    "iso:country":"AU",
    "sg:address":"31 Inverness Ave St",
    "sg:city":"Georges",
    "sg:classifiers":[
        {
            "category":"Professional",
            "subcategory":"Advertising",
            "type":"Services"
        }
    ],
    "sg:phone":"+61 418 837 995",
    "sg:postcode":"5064",
    "sg:province":"SA",
    "sg:tags":[
        "balloon",
        "novelty"
    ],
    "wof:name":"Perfect Party The",
    "wof:placetype":"venue"
},
  "geometry": {"coordinates":[138.64938354500001,-34.9497795105],"type":"Point"}
}