{
  "type": "Feature",
  "properties": {
    "addr:full":"PO Box 274 Burpengary QLD 4505",
    "addr:postcode":"4505",
    "iso:country":"AU",
    "sg:address":"PO Box 274",
    "sg:city":"Burpengary",
    "sg:classifiers":[
        {
            "category":"Utilities",
            "subcategory":"Refuse",
            "type":"Services"
        }
    ],
    "sg:phone":"+61 417 780 247",
    "sg:postcode":"4505",
    "sg:province":"QLD",
    "sg:tags":[
        "remover",
        "rubbish"
    ],
    "wof:name":"Northside Skip bins",
    "wof:placetype":"venue"
},
  "geometry": {"coordinates":[152.9921875,-27.1472892761],"type":"Point"}
}