{
  "type": "Feature",
  "properties": {
    "addr:full":"704 Strathfieldsaye Rd Strathfieldsaye VIC 3539",
    "addr:housenumber":"704",
    "addr:postcode":"3539",
    "addr:street":"Strathfieldsaye Rd",
    "iso:country":"AU",
    "sg:address":"704 Strathfieldsaye Rd",
    "sg:city":"Strathfieldsaye",
    "sg:classifiers":[
        {
            "category":"Building & Trades",
            "subcategory":"Construction",
            "type":"Services"
        }
    ],
    "sg:phone":"+61 3 5439 5489",
    "sg:postcode":"3539",
    "sg:province":"VIC",
    "sg:tags":[
        "contractor"
    ],
    "wof:name":"Ken Young",
    "wof:placetype":"venue"
},
  "geometry": {"coordinates":[144.34187299999999,-36.796532],"type":"Point"}
}