{
  "type": "Feature",
  "properties": {
    "addr:full":"418-440 Frankston-Dandenong Rd Bangholme VIC 3175",
    "addr:housenumber":"418-440",
    "addr:postcode":"3175",
    "addr:street":"Frankston-Dandenong Rd",
    "iso:country":"AU",
    "sg:address":"418-440 Frankston-Dandenong Rd",
    "sg:city":"Bangholme",
    "sg:classifiers":[
        {
            "category":"Health Services",
            "subcategory":"Doctor",
            "type":"Services"
        }
    ],
    "sg:phone":"+61 3 9706 5168",
    "sg:postcode":"3175",
    "sg:province":"VIC",
    "sg:tags":[
        "medical",
        "practitioner"
    ],
    "wof:name":"Select Medical Group",
    "wof:placetype":"venue"
},
  "geometry": {"coordinates":[145.209381103,-38.0433120728],"type":"Point"}
}