{
  "type": "Feature",
  "properties": {
    "addr:full":"264 Lease Rd Hervey Bay QLD 4655",
    "addr:housenumber":"264",
    "addr:postcode":"4655",
    "addr:street":"Lease Rd",
    "iso:country":"AU",
    "sg:address":"264 Lease Rd",
    "sg:city":"Hervey Bay",
    "sg:classifiers":[
        {
            "category":"Building & Trades",
            "subcategory":"Construction",
            "type":"Services"
        }
    ],
    "sg:phone":"+61 7 4128 7947",
    "sg:postcode":"4655",
    "sg:province":"QLD",
    "sg:tags":[
        "earth",
        "excavating",
        "moving",
        "contractor"
    ],
    "wof:name":"CJL Transport",
    "wof:placetype":"venue"
},
  "geometry": {"coordinates":[152.763443,-25.303804],"type":"Point"}
}