{
  "type": "Feature",
  "properties": {
    "addr:full":"27 Port Stephens St Raymond Terrace NSW 2324",
    "addr:housenumber":"27",
    "addr:postcode":"2324",
    "addr:street":"Port Stephens St",
    "iso:country":"AU",
    "sg:address":"27 Port Stephens St",
    "sg:city":"Raymond Terrace",
    "sg:classifiers":[
        {
            "category":"Autos & Motor Vehicles",
            "subcategory":"Automobile Sales",
            "type":"Retail Goods"
        }
    ],
    "sg:phone":"+61 2 4987 2400",
    "sg:postcode":"2324",
    "sg:province":"NSW",
    "sg:tags":[
        "car",
        "used"
    ],
    "wof:name":"Williams River Motor Homes",
    "wof:placetype":"venue"
},
  "geometry": {"coordinates":[151.74497985799999,-32.7595367432],"type":"Point"}
}