{
  "type": "Feature",
  "properties": {
    "addr:full":"80 Sunnyholt Rd Blacktown NSW 2148",
    "addr:housenumber":"80",
    "addr:postcode":"2148",
    "addr:street":"Sunnyholt Rd",
    "iso:country":"AU",
    "sg:address":"80 Sunnyholt Rd",
    "sg:city":"Blacktown",
    "sg:classifiers":[
        {
            "category":"Autos & Motor Vehicles",
            "subcategory":"Automobile Sales",
            "type":"Retail Goods"
        }
    ],
    "sg:phone":"+61 2 9676 7840",
    "sg:postcode":"2148",
    "sg:province":"NSW",
    "sg:tags":[
        "car",
        "used"
    ],
    "wof:name":"Wayne Stewart Quality Cars",
    "wof:placetype":"venue"
},
  "geometry": {"coordinates":[150.91160583499999,-33.7713432312],"type":"Point"}
}