{
  "type": "Feature",
  "properties": {
    "addr:full":"35 Oceano St Copacabana NSW 2251",
    "addr:housenumber":"35",
    "addr:postcode":"2251",
    "addr:street":"Oceano St",
    "iso:country":"AU",
    "sg:address":"35 Oceano St",
    "sg:city":"Copacabana",
    "sg:classifiers":[
        {
            "category":"Home & Garden",
            "subcategory":"Carpets & Floor Coverings",
            "type":"Retail Goods"
        }
    ],
    "sg:phone":"+61 2 4382 3290",
    "sg:postcode":"2251",
    "sg:province":"NSW",
    "sg:tags":[
        "layer",
        "planner"
    ],
    "wof:name":"M Henwood",
    "wof:placetype":"venue"
},
  "geometry": {"coordinates":[151.440475464,-33.4902534485],"type":"Point"}
}