{
  "type": "Feature",
  "properties": {
    "addr:full":"2-4 Wakeham St Stawell VIC 3380",
    "addr:housenumber":"2-4",
    "addr:postcode":"3380",
    "addr:street":"Wakeham St",
    "iso:country":"AU",
    "sg:address":"2-4 Wakeham St",
    "sg:city":"Stawell",
    "sg:classifiers":[
        {
            "category":"Retail",
            "subcategory":"Auto Repair",
            "type":"Services"
        }
    ],
    "sg:phone":"+61 3 5358 2178",
    "sg:postcode":"3380",
    "sg:province":"VIC",
    "sg:tags":[
        "electrical"
    ],
    "wof:name":"Scott's Auto Electrics",
    "wof:placetype":"venue"
},
  "geometry": {"coordinates":[142.771575928,-37.0590782166],"type":"Point"}
}