{
  "type": "Feature",
  "properties": {
    "addr:full":"Newnham Drv Newnham TAS 7248",
    "addr:postcode":"7248",
    "addr:street":"Newnham Drv",
    "iso:country":"AU",
    "sg:address":"Newnham Drv",
    "sg:city":"Newnham",
    "sg:classifiers":[
        {
            "category":"Restaurant",
            "type":"Food & Drink"
        }
    ],
    "sg:phone":"+61 3 6324 3257",
    "sg:postcode":"7248",
    "sg:province":"TAS",
    "wof:name":"Degrees Restaurant",
    "wof:placetype":"venue"
},
  "geometry": {"coordinates":[147.12878418,-41.3990821838],"type":"Point"}
}