{
  "type": "Feature",
  "properties": {
    "addr:full":"45 Roger Pl Blacktown NSW 2148",
    "addr:housenumber":"45",
    "addr:postcode":"2148",
    "addr:street":"Roger Pl",
    "iso:country":"AU",
    "sg:address":"45 Roger Pl",
    "sg:city":"Blacktown",
    "sg:classifiers":[
        {
            "category":"Building & Trades",
            "subcategory":"Pest Control",
            "type":"Services"
        }
    ],
    "sg:phone":"+61 2 9831 5788",
    "sg:postcode":"2148",
    "sg:province":"NSW",
    "wof:name":"Wipeout Pest Control",
    "wof:placetype":"venue"
},
  "geometry": {"coordinates":[150.92182922399999,-33.785320282],"type":"Point"}
}