{
  "type": "Feature",
  "properties": {
    "addr:full":"Logan Hyperdome, cnr Bryants Rd & Pacific Hwy Loganholme QLD 4129",
    "addr:postcode":"4129",
    "addr:street":"Cnr Bryants Rd & Pacific Hwy",
    "iso:country":"AU",
    "sg:address":"Logan Hyperdome, cnr Bryants Rd & Pacific Hwy",
    "sg:city":"Loganholme",
    "sg:classifiers":[
        {
            "category":"Building & Trades",
            "subcategory":"Locksmith",
            "type":"Services"
        }
    ],
    "sg:phone":"+61 7 3801 2413",
    "sg:postcode":"4129",
    "sg:province":"QLD",
    "sg:tags":[
        "lock"
    ],
    "wof:name":"Mister Minit",
    "wof:placetype":"venue"
},
  "geometry": {"coordinates":[153.17984008799999,-27.6705970764],"type":"Point"}
}