{
  "type": "Feature",
  "properties": {
    "iso:country":"AU",
    "sg:address":"15 Martin St",
    "sg:city":"Ballina",
    "sg:classifiers":[
        {
            "category":"Health Services",
            "subcategory":"Doctor",
            "type":"Services"
        }
    ],
    "sg:phone":"+61 2 6686 3299",
    "sg:postcode":"2478",
    "sg:province":"NSW",
    "sg:tags":[
        "medical",
        "practitioner"
    ],
    "wof:name":"Family Medical Centre - Martin St",
    "wof:placetype":"venue"
},
  "geometry": {"coordinates":[153.56431579599999,-28.8704967499],"type":"Point"}
}