{
  "type": "Feature",
  "properties": {
    "addr:full":"29 Scott St Bairnsdale VIC 3875",
    "addr:housenumber":"29",
    "addr:postcode":"3875",
    "addr:street":"Scott St",
    "iso:country":"AU",
    "sg:address":"29 Scott St",
    "sg:city":"Bairnsdale",
    "sg:classifiers":[
        {
            "category":"Professional",
            "subcategory":"Art Services",
            "type":"Services"
        }
    ],
    "sg:phone":"+61 3 5152 5832",
    "sg:postcode":"3875",
    "sg:province":"VIC",
    "sg:tags":[
        "decorator",
        "painter"
    ],
    "wof:name":"Matheson G C",
    "wof:placetype":"venue"
},
  "geometry": {"coordinates":[147.612792969,-37.8182563782],"type":"Point"}
}