{
  "type": "Feature",
  "properties": {
    "addr:full":"26 Bangalow Rd Byron Bay NSW 2481",
    "addr:housenumber":"26",
    "addr:postcode":"2481",
    "addr:street":"Bangalow Rd",
    "iso:country":"AU",
    "sg:address":"26 Bangalow Rd",
    "sg:city":"Byron Bay",
    "sg:classifiers":[
        {
            "category":"Fast Food",
            "type":"Food & Drink"
        }
    ],
    "sg:phone":"+61 2 6685 5101",
    "sg:postcode":"2481",
    "sg:province":"NSW",
    "sg:tags":[
        "away",
        "take"
    ],
    "wof:name":"Mac's Homestyle Takeaways",
    "wof:placetype":"venue"
},
  "geometry": {"coordinates":[153.615524292,-28.653793335],"type":"Point"}
}