{
  "type": "Feature",
  "properties": {
    "addr:full":"Level 1, 33 -39 Rundle Mall Adelaide SA 5000",
    "addr:housenumber":"33 -39",
    "addr:postcode":"5000",
    "addr:street":"Rundle Mall",
    "iso:country":"AU",
    "sg:address":"Level 1, 33",
    "sg:city":"-39 Rundle Mall Adelaide",
    "sg:classifiers":[
        {
            "category":"Government",
            "subcategory":"Post Office",
            "type":"Public Place"
        }
    ],
    "sg:phone":"+61 13 13 18",
    "sg:postcode":"5000",
    "sg:province":"SA",
    "sg:tags":[
        "postal"
    ],
    "wof:name":"Australia Post",
    "wof:placetype":"venue"
},
  "geometry": {"coordinates":[138.60086059599999,-34.9230499268],"type":"Point"}
}