{
  "type": "Feature",
  "properties": {
    "iso:country":"AU",
    "sg:address":"Ste 21/ 96 Camberwell Rd",
    "sg:city":"Hawthorn East",
    "sg:classifiers":[
        {
            "category":"Organizations",
            "subcategory":"Professional Association",
            "type":"Services"
        }
    ],
    "sg:phone":"+61 3 9500 2033",
    "sg:postcode":"3123",
    "sg:province":"VIC",
    "sg:tags":[
        "web",
        "internet"
    ],
    "wof:name":"Bride Online Infoprobe Australia",
    "wof:placetype":"venue"
},
  "geometry": {"coordinates":[145.05174255399999,-37.8272094727],"type":"Point"}
}