{
  "type": "Feature",
  "properties": {
    "addr:full":"7 Winston Crt Traralgon VIC 3844",
    "addr:housenumber":"7",
    "addr:postcode":"3844",
    "addr:street":"Winston Crt",
    "iso:country":"AU",
    "sg:address":"7 Winston Crt",
    "sg:city":"Traralgon",
    "sg:classifiers":[
        {
            "category":"Retail",
            "subcategory":"Auto Repair",
            "type":"Services"
        }
    ],
    "sg:phone":"+61 428 598 088",
    "sg:postcode":"3844",
    "sg:province":"VIC",
    "sg:tags":[
        "electrical"
    ],
    "wof:name":"Alex Eacott",
    "wof:placetype":"venue"
},
  "geometry": {"coordinates":[146.568557739,-38.1971855164],"type":"Point"}
}