{
  "type": "Feature",
  "properties": {
    "addr:full":"52 High St Toowong QLD 4066",
    "addr:housenumber":"52",
    "addr:postcode":"4066",
    "addr:street":"High St",
    "iso:country":"AU",
    "sg:address":"52 High St",
    "sg:city":"Toowong",
    "sg:classifiers":[
        {
            "category":"Real Estate",
            "subcategory":"Real Estate Agent",
            "type":"Services"
        }
    ],
    "sg:phone":"+61 7 3870 0088",
    "sg:postcode":"4066",
    "sg:province":"QLD",
    "wof:name":"Ray White Toowong",
    "wof:placetype":"venue"
},
  "geometry": {"coordinates":[152.991577148,-27.4868392944],"type":"Point"}
}