{
  "type": "Feature",
  "properties": {
    "iso:country":"AU",
    "sg:address":"Shop 37 Waverley Gardens",
    "sg:city":"Mulgrave",
    "sg:classifiers":[
        {
            "category":"Food & Beverages",
            "subcategory":"Bakery",
            "type":"Retail Goods"
        }
    ],
    "sg:phone":"+61 3 9547 6644",
    "sg:postcode":"3170",
    "sg:province":"VIC",
    "sg:tags":[
        "cake",
        "shop",
        "pastry"
    ],
    "wof:name":"Cheesecake Heaven",
    "wof:placetype":"venue"
},
  "geometry": {"coordinates":[145.189178467,-37.92237854],"type":"Point"}
}