{
  "type": "Feature",
  "properties": {
    "addr:full":"57 Luxford Rd Mt Druitt NSW 2770",
    "addr:housenumber":"57",
    "addr:postcode":"2770",
    "addr:street":"Luxford Rd",
    "iso:country":"AU",
    "sg:address":"57 Luxford Rd",
    "sg:city":"Mt Druitt",
    "sg:classifiers":[
        {
            "category":"Health Services",
            "subcategory":"Chiropractor",
            "type":"Services"
        }
    ],
    "sg:phone":"+61 2 9832 8840",
    "sg:postcode":"2770",
    "sg:province":"NSW",
    "wof:name":"Mt Druitt Chiropractic Centre",
    "wof:placetype":"venue"
},
  "geometry": {"coordinates":[150.81451415999999,-33.7630500793],"type":"Point"}
}