{
  "type": "Feature",
  "properties": {
    "addr:full":"Cnr Warwick & Cooper Rds Willowbank QLD 4306",
    "addr:postcode":"4306",
    "addr:street":"Cnr",
    "iso:country":"AU",
    "sg:address":"Cnr Warwick & Cooper Rds",
    "sg:city":"Willowbank",
    "sg:classifiers":[
        {
            "category":"Travel",
            "subcategory":"Hotels & Motels",
            "type":"Entertainment"
        }
    ],
    "sg:phone":"+61 7 5464 3166",
    "sg:postcode":"4306",
    "sg:province":"QLD",
    "wof:name":"Willowbank Motel",
    "wof:placetype":"venue"
},
  "geometry": {"coordinates":[152.738555908,-27.6630191803],"type":"Point"}
}