{
  "type": "Feature",
  "properties": {
    "addr:full":"1175 Burke Rd Kew VIC 3101",
    "addr:housenumber":"1175",
    "addr:postcode":"3101",
    "addr:street":"Burke Rd",
    "iso:country":"AU",
    "sg:address":"1175 Burke Rd",
    "sg:city":"Kew",
    "sg:classifiers":[
        {
            "category":"Health Services",
            "subcategory":"Health Practitioner",
            "type":"Services"
        }
    ],
    "sg:phone":"+61 3 9817 7548",
    "sg:postcode":"3101",
    "sg:province":"VIC",
    "sg:tags":[
        "acupuncture"
    ],
    "wof:name":"Wu Helen",
    "wof:placetype":"venue"
},
  "geometry": {"coordinates":[145.059494019,-37.8157196045],"type":"Point"}
}