{
  "type": "Feature",
  "properties": {
    "addr:full":"Lvl 2/ 19 Pitt St Sydney NSW 2000",
    "addr:housenumber":"/ 19",
    "addr:postcode":"2000",
    "addr:street":"Pitt St",
    "iso:country":"AU",
    "sg:address":"Lvl 2/ 19 Pitt St",
    "sg:city":"Sydney",
    "sg:classifiers":[
        {
            "category":"Utilities",
            "subcategory":"Telephone",
            "type":"Services"
        }
    ],
    "sg:phone":"+61 1800 655 515",
    "sg:postcode":"2000",
    "sg:province":"NSW",
    "wof:name":"Primus Communications Pty Limited",
    "wof:placetype":"venue"
},
  "geometry": {"coordinates":[151.20901489299999,-33.8619728088],"type":"Point"}
}