{
  "type": "Feature",
  "properties": {
    "iso:country":"AU",
    "sg:address":"19 Prospect Hill Rd",
    "sg:city":"Camberwell",
    "sg:classifiers":[
        {
            "category":"Professional",
            "subcategory":"Management & Consulting",
            "type":"Services"
        }
    ],
    "sg:phone":"+61 3 9277 5555",
    "sg:postcode":"3124",
    "sg:province":"VIC",
    "sg:tags":[
        "consultant",
        "educational"
    ],
    "wof:name":"ACER LTD (Australian Council for Educational Research)",
    "wof:placetype":"venue"
},
  "geometry": {"coordinates":[145.05900573700001,-37.828212738],"type":"Point"}
}