{
  "type": "Feature",
  "properties": {
    "addr:full":"8 Jesmond Rd Croydon VIC 3136",
    "addr:housenumber":"8",
    "addr:postcode":"3136",
    "addr:street":"Jesmond Rd",
    "iso:country":"AU",
    "sg:address":"8 Jesmond Rd",
    "sg:city":"Croydon",
    "sg:classifiers":[
        {
            "category":"Professional",
            "subcategory":"Detective & Security Services",
            "type":"Services"
        }
    ],
    "sg:phone":"+61 3 9723 4145",
    "sg:postcode":"3136",
    "sg:province":"VIC",
    "sg:tags":[
        "equipment",
        "window",
        "doors"
    ],
    "wof:name":"D & K Home Security Pty Ltd",
    "wof:placetype":"venue"
},
  "geometry": {"coordinates":[145.28297424300001,-37.806350708],"type":"Point"}
}