{
  "type": "Feature",
  "properties": {
    "iso:country":"AU",
    "sg:address":"11 Sutherland Rd",
    "sg:city":"Armadale",
    "sg:classifiers":[
        {
            "category":"Utilities",
            "subcategory":"Water",
            "type":"Services"
        }
    ],
    "sg:phone":"+61 3 9500 9700",
    "sg:postcode":"3143",
    "sg:province":"VIC",
    "sg:tags":[
        "equipment",
        "treatment"
    ],
    "wof:name":"Pure Health Products",
    "wof:placetype":"venue"
},
  "geometry": {"coordinates":[145.01666259800001,-37.8596801758],"type":"Point"}
}