{
  "type": "Feature",
  "properties": {
    "addr:full":"1 Bell St Yarra Glen VIC 3775",
    "addr:housenumber":"1",
    "addr:postcode":"3775",
    "addr:street":"Bell St",
    "iso:country":"AU",
    "sg:address":"1 Bell St",
    "sg:city":"Yarra Glen",
    "sg:classifiers":[
        {
            "category":"Food & Beverages",
            "subcategory":"Supermarket",
            "type":"Retail Goods"
        }
    ],
    "sg:phone":"+61 3 9730 1241",
    "sg:postcode":"3775",
    "sg:province":"VIC",
    "sg:tags":[
        "grocery",
        "store"
    ],
    "wof:name":"IGA Everyday",
    "wof:placetype":"venue"
},
  "geometry": {"coordinates":[145.37489299999999,-37.659405],"type":"Point"}
}