{
  "type": "Feature",
  "properties": {
    "addr:full":"780 Belli Creek Rd Cooroy QLD 4563",
    "addr:housenumber":"780",
    "addr:postcode":"4563",
    "addr:street":"Belli Creek Rd",
    "iso:country":"AU",
    "sg:address":"780 Belli Creek Rd",
    "sg:city":"Cooroy",
    "sg:classifiers":[
        {
            "category":"Manufacturing",
            "subcategory":"Furniture",
            "type":"Manufacturing & Wholesale Goods"
        }
    ],
    "sg:phone":"+61 7 5447 7746",
    "sg:postcode":"4563",
    "sg:province":"QLD",
    "sg:tags":[
        "builder",
        "designer",
        "custom"
    ],
    "wof:name":"Annels Ross",
    "wof:placetype":"venue"
},
  "geometry": {"coordinates":[152.91003418,-26.419549942],"type":"Point"}
}