{
  "type": "Feature",
  "properties": {
    "iso:country":"AU",
    "sg:address":"Suite 3, Level 2, 38 President Ave",
    "sg:city":"Caringbah",
    "sg:classifiers":[
        {
            "category":"Shopping",
            "subcategory":"Computers & Home Electronics",
            "type":"Retail Goods"
        }
    ],
    "sg:phone":"+61 2 9526 6773",
    "sg:postcode":"2229",
    "sg:province":"NSW",
    "sg:tags":[
        "small",
        "equipment",
        "business"
    ],
    "wof:name":"Protype Computing Services",
    "wof:placetype":"venue"
},
  "geometry": {"coordinates":[151.12121582,-34.0430107117],"type":"Point"}
}