{
  "type": "Feature",
  "properties": {
    "iso:country":"AU",
    "sg:address":"45 Carcoar St",
    "sg:city":"Blayney",
    "sg:classifiers":[
        {
            "category":"Home & Garden",
            "subcategory":"Building Materials",
            "type":"Retail Goods"
        }
    ],
    "sg:phone":"+61 2 6368 2437",
    "sg:postcode":"2799",
    "sg:province":"NSW",
    "sg:tags":[
        "supply"
    ],
    "wof:name":"Quality Building Supplies",
    "wof:placetype":"venue"
},
  "geometry": {"coordinates":[149.249176,-33.530151],"type":"Point"}
}