{
  "type": "Feature",
  "properties": {
    "addr:full":"66 Currambene St Huskisson NSW 2540",
    "addr:housenumber":"66",
    "addr:postcode":"2540",
    "addr:street":"Currambene St",
    "iso:country":"AU",
    "sg:address":"66 Currambene St",
    "sg:city":"Huskisson",
    "sg:classifiers":[
        {
            "category":"Recreation",
            "subcategory":"Boat Charter",
            "type":"Entertainment"
        }
    ],
    "sg:phone":"+61 2 4441 6200",
    "sg:postcode":"2540",
    "sg:province":"NSW",
    "sg:tags":[
        "hire",
        "drive"
    ],
    "wof:name":"Husky-Hire-A-Boat",
    "wof:placetype":"venue"
},
  "geometry": {"coordinates":[150.66046142600001,-35.0225791931],"type":"Point"}
}