{
  "type": "Feature",
  "properties": {
    "iso:country":"AU",
    "sg:address":"466 Goodwood Rd",
    "sg:city":"Cumberland Park",
    "sg:classifiers":[
        {
            "category":"Real Estate",
            "subcategory":"Real Estate Agent",
            "type":"Services"
        }
    ],
    "sg:phone":"+61 8 8172 2000",
    "sg:postcode":"5041",
    "sg:province":"SA",
    "wof:name":"L.J. Hooker Westbourne Park",
    "wof:placetype":"venue"
},
  "geometry": {"coordinates":[138.591293,-34.974709],"type":"Point"}
}