{
  "type": "Feature",
  "properties": {
    "addr:full":"4 Gregory St Queanbeyan NSW 2620",
    "addr:housenumber":"4",
    "addr:postcode":"2620",
    "addr:street":"Gregory St",
    "iso:country":"AU",
    "sg:address":"4 Gregory St",
    "sg:city":"Queanbeyan",
    "sg:classifiers":[
        {
            "category":"Retail",
            "subcategory":"Auto Repair",
            "type":"Services"
        }
    ],
    "sg:phone":"+61 2 6297 3883",
    "sg:postcode":"2620",
    "sg:province":"NSW",
    "sg:tags":[
        "gas",
        "conversion",
        "natural",
        "lp",
        "vehicle"
    ],
    "wof:name":"Gary Shepherd Automotive Services",
    "wof:placetype":"venue"
},
  "geometry": {"coordinates":[149.209350586,-35.350643158],"type":"Point"}
}