{
  "type": "Feature",
  "properties": {
    "addr:full":"181 Richmond Rd Richmond SA 5033",
    "addr:housenumber":"181",
    "addr:postcode":"5033",
    "addr:street":"Richmond Rd",
    "iso:country":"AU",
    "sg:address":"181 Richmond Rd",
    "sg:city":"Richmond",
    "sg:classifiers":[
        {
            "category":"Professional",
            "type":"Services"
        }
    ],
    "sg:phone":"+61 8 8351 9450",
    "sg:postcode":"5033",
    "sg:province":"SA",
    "sg:tags":[
        "transport"
    ],
    "wof:name":"Lange Transport",
    "wof:placetype":"venue"
},
  "geometry": {"coordinates":[138.56393432600001,-34.942325592],"type":"Point"}
}