{
  "type": "Feature",
  "properties": {
    "iso:country":"AU",
    "sg:address":"1371 Logan Rd",
    "sg:city":"Mt Gravatt",
    "sg:classifiers":[
        {
            "category":"Shopping",
            "subcategory":"Clothing, Apparel, & Fashions",
            "type":"Retail Goods"
        }
    ],
    "sg:phone":"+61 7 3219 2711",
    "sg:postcode":"4122",
    "sg:province":"QLD",
    "sg:tags":[
        "boutique"
    ],
    "wof:name":"Treasure Trove",
    "wof:placetype":"venue"
},
  "geometry": {"coordinates":[153.07417297399999,-27.5328063965],"type":"Point"}
}