{
  "type": "Feature",
  "properties": {
    "addr:full":"20 Edward St Langwarrin VIC 3910",
    "addr:housenumber":"20",
    "addr:postcode":"3910",
    "addr:street":"Edward St",
    "iso:country":"AU",
    "sg:address":"20 Edward St",
    "sg:city":"Langwarrin",
    "sg:classifiers":[
        {
            "category":"Professional",
            "subcategory":"Art Services",
            "type":"Services"
        }
    ],
    "sg:phone":"+61 3 9776 7355",
    "sg:postcode":"3910",
    "sg:province":"VIC",
    "sg:tags":[
        "decorator",
        "painter"
    ],
    "wof:name":"R & F Maintenance & Renovations",
    "wof:placetype":"venue"
},
  "geometry": {"coordinates":[145.17364501899999,-38.1546440125],"type":"Point"}
}