{
  "type": "Feature",
  "properties": {
    "addr:full":"30 Chapman Rd Geraldton WA 6530",
    "addr:housenumber":"30",
    "addr:postcode":"6530",
    "addr:street":"Chapman Rd",
    "iso:country":"AU",
    "sg:address":"30 Chapman Rd",
    "sg:city":"Geraldton",
    "sg:classifiers":[
        {
            "category":"Retail",
            "subcategory":"Car Wash",
            "type":"Services"
        }
    ],
    "sg:phone":"+61 8 9964 2037",
    "sg:postcode":"6530",
    "sg:province":"WA",
    "sg:tags":[
        "truck",
        "cleaning"
    ],
    "wof:name":"Batavia Coast Car Care",
    "wof:placetype":"venue"
},
  "geometry": {"coordinates":[114.611778259,-28.772649765],"type":"Point"}
}