{
  "type": "Feature",
  "properties": {
    "iso:country":"AU",
    "sg:address":"Depot: 19 Downie St",
    "sg:city":"Wickham",
    "sg:classifiers":[
        {
            "category":"Freight",
            "type":"Transportation"
        }
    ],
    "sg:phone":"+61 2 4961 5260",
    "sg:postcode":"2293",
    "sg:province":"NSW",
    "sg:tags":[
        "light",
        "carrier"
    ],
    "wof:name":"Carriers Pool (Newcastle) Co-Op Ltd",
    "wof:placetype":"venue"
},
  "geometry": {"coordinates":[151.756988525,-32.9121932983],"type":"Point"}
}