{
  "type": "Feature",
  "properties": {
    "iso:country":"AU",
    "sg:address":"27 Truman Ave",
    "sg:city":"Cromer",
    "sg:classifiers":[
        {
            "category":"Shopping",
            "subcategory":"Clothing, Apparel, & Fashions",
            "type":"Retail Goods"
        }
    ],
    "sg:phone":"+61 2 9982 2839",
    "sg:postcode":"2099",
    "sg:province":"NSW",
    "sg:tags":[
        "lady",
        "wear"
    ],
    "wof:name":"Pantz & Plants Pty Ltd",
    "wof:placetype":"venue"
},
  "geometry": {"coordinates":[151.264526367,-33.7342834473],"type":"Point"}
}