{
  "type": "Feature",
  "properties": {
    "iso:country":"AU",
    "sg:address":"14 Waverley Ave",
    "sg:city":"Edwardstown",
    "sg:classifiers":[
        {
            "category":"Building & Trades",
            "subcategory":"Equipment Rental",
            "type":"Services"
        }
    ],
    "sg:phone":"+61 8 8276 1371",
    "sg:postcode":"5039",
    "sg:province":"SA",
    "sg:tags":[
        "demolition",
        "contractor"
    ],
    "wof:name":"Dia-Cut",
    "wof:placetype":"venue"
},
  "geometry": {"coordinates":[138.57081604000001,-34.9874954224],"type":"Point"}
}