{
  "type": "Feature",
  "properties": {
    "addr:full":"54 Lonus Ave Whitebridge NSW 2290",
    "addr:housenumber":"54",
    "addr:postcode":"2290",
    "addr:street":"Lonus Ave",
    "iso:country":"AU",
    "sg:address":"54 Lonus Ave",
    "sg:city":"Whitebridge",
    "sg:classifiers":[
        {
            "category":"Utilities",
            "subcategory":"Electric",
            "type":"Services"
        }
    ],
    "sg:phone":"+61 402 225 424",
    "sg:postcode":"2290",
    "sg:province":"NSW",
    "sg:tags":[
        "electrical",
        "contractor"
    ],
    "wof:name":"David Stuart Electrical",
    "wof:placetype":"venue"
},
  "geometry": {"coordinates":[151.71191406200001,-32.9744224548],"type":"Point"}
}