{
  "type": "Feature",
  "properties": {
    "addr:full":"Unit 1/ 8 Cusack Rd Malaga WA 6090",
    "addr:postcode":"6090",
    "addr:street":"Cusack Rd",
    "iso:country":"AU",
    "sg:address":"Unit 1/ 8 Cusack Rd",
    "sg:city":"Malaga",
    "sg:classifiers":[
        {
            "category":"Retail",
            "subcategory":"Auto Repair",
            "type":"Services"
        }
    ],
    "sg:phone":"+61 8 9248 1012",
    "sg:postcode":"6090",
    "sg:province":"WA",
    "sg:tags":[
        "repairer",
        "motor",
        "engineer"
    ],
    "wof:name":"T & P Autos",
    "wof:placetype":"venue"
},
  "geometry": {"coordinates":[115.886779785,-31.8639030457],"type":"Point"}
}