{
  "type": "Feature",
  "properties": {
    "addr:full":"Shp 6/ 256 Beamish St Campsie NSW 2194",
    "addr:housenumber":"/ 256",
    "addr:postcode":"2194",
    "addr:street":"Beamish St",
    "iso:country":"AU",
    "sg:address":"Shp 6/ 256 Beamish St",
    "sg:city":"Campsie",
    "sg:classifiers":[
        {
            "category":"Shopping",
            "subcategory":"Clothing, Apparel, & Fashions",
            "type":"Retail Goods"
        }
    ],
    "sg:phone":"+61 2 9718 4216",
    "sg:postcode":"2194",
    "sg:province":"NSW",
    "sg:tags":[
        "accessory"
    ],
    "wof:name":"Trendy Zone Pty Ltd",
    "wof:placetype":"venue"
},
  "geometry": {"coordinates":[151.10391200000001,-33.912956],"type":"Point"}
}