{
  "type": "Feature",
  "properties": {
    "addr:full":"110 Herbert St Ingham QLD 4850",
    "addr:housenumber":"110",
    "addr:postcode":"4850",
    "addr:street":"Herbert St",
    "iso:country":"AU",
    "sg:address":"110 Herbert St",
    "sg:city":"Ingham",
    "sg:classifiers":[
        {
            "category":"Autos & Motor Vehicles",
            "subcategory":"Fuel & Gas Station",
            "type":"Retail Goods"
        }
    ],
    "sg:phone":"+61 7 4776 1041",
    "sg:postcode":"4850",
    "sg:province":"QLD",
    "wof:name":"Shell Day Dawn",
    "wof:placetype":"venue"
},
  "geometry": {"coordinates":[146.16212463400001,-18.6463851929],"type":"Point"}
}