{
  "type": "Feature",
  "properties": {
    "iso:country":"AU",
    "sg:address":"19 Bricker St",
    "sg:city":"Cheltenham",
    "sg:classifiers":[
        {
            "category":"Building & Trades",
            "subcategory":"Locksmith",
            "type":"Services"
        }
    ],
    "sg:phone":"+61 3 9532 0855",
    "sg:postcode":"3192",
    "sg:province":"VIC",
    "sg:tags":[
        "equipment",
        "operating",
        "door",
        "gate"
    ],
    "wof:name":"Horizon Automatic Doors",
    "wof:placetype":"venue"
},
  "geometry": {"coordinates":[145.07063293499999,-37.9512825012],"type":"Point"}
}