{
  "type": "Feature",
  "properties": {
    "addr:full":"74 Davies St Kincumber NSW 2251",
    "addr:housenumber":"74",
    "addr:postcode":"2251",
    "addr:street":"Davies St",
    "iso:country":"AU",
    "sg:address":"74 Davies St",
    "sg:city":"Kincumber",
    "sg:classifiers":[
        {
            "category":"Building & Trades",
            "subcategory":"Cleaning & Sanitation",
            "type":"Services"
        }
    ],
    "sg:phone":"+61 2 4369 5577",
    "sg:postcode":"2251",
    "sg:province":"NSW",
    "sg:tags":[
        "cleaner",
        "repairer",
        "roof"
    ],
    "wof:name":"ASAP Roofing",
    "wof:placetype":"venue"
},
  "geometry": {"coordinates":[151.39044189399999,-33.4644355774],"type":"Point"}
}