{
  "type": "Feature",
  "properties": {
    "iso:country":"AU",
    "sg:address":"2 Hallow Rd",
    "sg:city":"Narellan Vale",
    "sg:classifiers":[
        {
            "category":"Retail",
            "subcategory":"Auto Repair",
            "type":"Services"
        }
    ],
    "sg:phone":"+61 2 4648 2070",
    "sg:postcode":"2567",
    "sg:province":"NSW",
    "sg:tags":[
        "repairer",
        "motor",
        "engineer"
    ],
    "wof:name":"Campbelltowns Best Under Car Centre",
    "wof:placetype":"venue"
},
  "geometry": {"coordinates":[150.747802734,-34.0431022644],"type":"Point"}
}