{
  "type": "Feature",
  "properties": {
    "addr:full":"Jackson St Monash SA 5342",
    "addr:postcode":"5342",
    "addr:street":"Jackson St",
    "iso:country":"AU",
    "sg:address":"Jackson St",
    "sg:city":"Monash",
    "sg:classifiers":[
        {
            "category":"Education",
            "subcategory":"School",
            "type":"Public Place"
        }
    ],
    "sg:phone":"+61 8 8583 5361",
    "sg:postcode":"5342",
    "sg:province":"SA",
    "sg:tags":[
        "state",
        "except",
        "nsw"
    ],
    "wof:name":"Monash Primary School",
    "wof:placetype":"venue"
},
  "geometry": {"coordinates":[140.55909729000001,-34.2368087769],"type":"Point"}
}