{
  "type": "Feature",
  "properties": {
    "iso:country":"AU",
    "sg:address":"17 Lake St",
    "sg:city":"Shepparton",
    "sg:classifiers":[
        {
            "category":"Health Services",
            "subcategory":"Health Practitioner",
            "type":"Services"
        }
    ],
    "sg:phone":"+61 3 5831 2632",
    "sg:postcode":"3630",
    "sg:province":"VIC",
    "sg:tags":[
        "pathologist",
        "speech"
    ],
    "wof:name":"Fiona Crawford Speech Therapist",
    "wof:placetype":"venue"
},
  "geometry": {"coordinates":[145.39988708499999,-36.3917732239],"type":"Point"}
}