{
  "type": "Feature",
  "properties": {
    "addr:full":"70- 72 Thomas Drv Chevron Island QLD 4217",
    "addr:housenumber":"72",
    "addr:postcode":"4217",
    "addr:street":"Thomas Drv Chevron",
    "iso:country":"AU",
    "sg:address":"70- 72 Thomas Drv",
    "sg:city":"Chevron Island",
    "sg:classifiers":[
        {
            "category":"Health Services",
            "subcategory":"Dentist",
            "type":"Services"
        }
    ],
    "sg:phone":"+61 7 5592 2866",
    "sg:postcode":"4217",
    "sg:province":"QLD",
    "wof:name":"Dr David J Simmons",
    "wof:placetype":"venue"
},
  "geometry": {"coordinates":[153.41732788100001,-27.9977779388],"type":"Point"}
}