{
  "type": "Feature",
  "properties": {
    "addr:full":"90 Goodlet St Surry Hills NSW 2010",
    "addr:housenumber":"90",
    "addr:postcode":"2010",
    "addr:street":"Goodlet St",
    "iso:country":"AU",
    "sg:address":"90 Goodlet St",
    "sg:city":"Surry Hills",
    "sg:classifiers":[
        {
            "category":"Manufacturing",
            "subcategory":"Food",
            "type":"Manufacturing & Wholesale Goods"
        }
    ],
    "sg:phone":"+61 2 9699 5500",
    "sg:postcode":"2010",
    "sg:province":"NSW",
    "sg:tags":[
        "function",
        "catering"
    ],
    "wof:name":"Brash Hospitality",
    "wof:placetype":"venue"
},
  "geometry": {"coordinates":[151.210113525,-33.8898735046],"type":"Point"}
}