{
  "type": "Feature",
  "properties": {
    "addr:full":"42 Sydney St Kilmore VIC 3764",
    "addr:housenumber":"42",
    "addr:postcode":"3764",
    "addr:street":"Sydney St",
    "iso:country":"AU",
    "sg:address":"42 Sydney St",
    "sg:city":"Kilmore",
    "sg:classifiers":[
        {
            "category":"Shopping",
            "subcategory":"Gifts & Souvenirs",
            "type":"Retail Goods"
        }
    ],
    "sg:phone":"+61 3 5782 2077",
    "sg:postcode":"3764",
    "sg:province":"VIC",
    "sg:tags":[
        "print",
        "poster",
        "pictures"
    ],
    "wof:name":"Kilmore Print And Frame",
    "wof:placetype":"venue"
},
  "geometry": {"coordinates":[144.951370239,-37.2926254272],"type":"Point"}
}