{
  "type": "Feature",
  "properties": {
    "iso:country":"AU",
    "sg:address":"32 Lamont St",
    "sg:city":"Bermagui",
    "sg:classifiers":[
        {
            "category":"Food & Beverages",
            "subcategory":"Supermarket",
            "type":"Retail Goods"
        }
    ],
    "sg:phone":"+61 2 6493 4238",
    "sg:postcode":"2546",
    "sg:province":"NSW",
    "sg:tags":[
        "grocery",
        "store"
    ],
    "wof:name":"Bermagui Village Store",
    "wof:placetype":"venue"
},
  "geometry": {"coordinates":[150.07728576700001,-36.427028656],"type":"Point"}
}