{
  "type": "Feature",
  "properties": {
    "iso:country":"AU",
    "sg:address":"97 Station Rd",
    "sg:city":"Foster",
    "sg:classifiers":[
        {
            "category":"Health Services",
            "subcategory":"Doctor",
            "type":"Services"
        }
    ],
    "sg:phone":"+61 3 5682 2088",
    "sg:postcode":"3960",
    "sg:province":"VIC",
    "sg:tags":[
        "medical",
        "practitioner"
    ],
    "wof:name":"Worboys Phillip Dr",
    "wof:placetype":"venue"
},
  "geometry": {"coordinates":[146.206787109,-38.6598396301],"type":"Point"}
}