{
  "type": "Feature",
  "properties": {
    "addr:full":"23 Wilkins Rd Gillman SA 5013",
    "addr:housenumber":"23",
    "addr:postcode":"5013",
    "addr:street":"Wilkins Rd",
    "iso:country":"AU",
    "sg:address":"23 Wilkins Rd",
    "sg:city":"Gillman",
    "sg:classifiers":[
        {
            "category":"Building & Trades",
            "subcategory":"Construction",
            "type":"Services"
        }
    ],
    "sg:phone":"+61 8 8240 0399",
    "sg:postcode":"5013",
    "sg:province":"SA",
    "sg:tags":[
        "bitumen",
        "paving",
        "asphalt"
    ],
    "wof:name":"Matson Constructions Pty Ltd",
    "wof:placetype":"venue"
},
  "geometry": {"coordinates":[138.53251648,-34.8361320496],"type":"Point"}
}