{
  "type": "Feature",
  "properties": {
    "iso:country":"AU",
    "sg:address":"17 Cattley St",
    "sg:city":"Burnie",
    "sg:classifiers":[
        {
            "category":"Banks & Credit Unions",
            "subcategory":"Financial Services",
            "type":"Services"
        }
    ],
    "sg:phone":"+61 3 6440 8440",
    "sg:postcode":"7320",
    "sg:province":"TAS",
    "sg:tags":[
        "planning"
    ],
    "wof:name":"Tasmanian Perpetual Trustees",
    "wof:placetype":"venue"
},
  "geometry": {"coordinates":[145.90669299999999,-41.052574],"type":"Point"}
}