{
  "type": "Feature",
  "properties": {
    "addr:full":"21 Paris Ave Morningside QLD 4170",
    "addr:housenumber":"21",
    "addr:postcode":"4170",
    "addr:street":"Paris Ave",
    "iso:country":"AU",
    "sg:address":"21 Paris Ave",
    "sg:city":"Morningside",
    "sg:classifiers":[
        {
            "category":"Shopping",
            "subcategory":"Musical Instruments",
            "type":"Retail Goods"
        }
    ],
    "sg:phone":"+61 7 3899 8859",
    "sg:postcode":"4170",
    "sg:province":"QLD",
    "sg:tags":[
        "musician",
        "agent"
    ],
    "wof:name":"Benjam Productions",
    "wof:placetype":"venue"
},
  "geometry": {"coordinates":[153.08387756400001,-27.4743213654],"type":"Point"}
}