{
  "type": "Feature",
  "properties": {
    "iso:country":"AU",
    "sg:address":"24 Drummond St North",
    "sg:city":"Ballarat",
    "sg:classifiers":[
        {
            "category":"Health Services",
            "subcategory":"Doctor",
            "type":"Services"
        }
    ],
    "sg:phone":"+61 3 5332 3959",
    "sg:postcode":"3350",
    "sg:province":"VIC",
    "sg:tags":[
        "medical",
        "practitioner"
    ],
    "wof:name":"Rajagopalan Mani Dr",
    "wof:placetype":"venue"
},
  "geometry": {"coordinates":[143.847855,-37.559402],"type":"Point"}
}