{
  "type": "Feature",
  "properties": {
    "iso:country":"AU",
    "sg:address":"23 William St",
    "sg:city":"Springton",
    "sg:classifiers":[
        {
            "category":"Retail",
            "subcategory":"Auto Repair",
            "type":"Services"
        }
    ],
    "sg:phone":"+61 8 8568 2153",
    "sg:postcode":"5235",
    "sg:province":"SA",
    "sg:tags":[
        "electrical"
    ],
    "wof:name":"Torrens Valley Mechanical",
    "wof:placetype":"venue"
},
  "geometry": {"coordinates":[139.09393310600001,-34.7075881958],"type":"Point"}
}