{
  "type": "Feature",
  "properties": {
    "addr:full":"Midstar Complex Melbourne Rd Shepparton South VIC 3630",
    "addr:postcode":"3630",
    "addr:street":"Melbourne Rd",
    "iso:country":"AU",
    "sg:address":"Midstar Complex Melbourne Rd",
    "sg:city":"Shepparton South",
    "sg:classifiers":[
        {
            "category":"Professional",
            "type":"Services"
        }
    ],
    "sg:phone":"+61 3 5823 2929",
    "sg:postcode":"3630",
    "sg:province":"VIC",
    "sg:tags":[
        "spray",
        "painting"
    ],
    "wof:name":"Mick Doherty Body Works",
    "wof:placetype":"venue"
},
  "geometry": {"coordinates":[145.390136719,-36.4269676208],"type":"Point"}
}