{
  "type": "Feature",
  "properties": {
    "iso:country":"AU",
    "sg:address":"Unit 5 33 Macquarie St",
    "sg:city":"Dubbo",
    "sg:classifiers":[
        {
            "category":"Insurance",
            "subcategory":"Insurance Agent",
            "type":"Services"
        }
    ],
    "sg:phone":"+61 2 6884 6744",
    "sg:postcode":"2830",
    "sg:province":"NSW",
    "sg:tags":[
        "broker"
    ],
    "wof:name":"Jardine Lloyd Thompson",
    "wof:placetype":"venue"
},
  "geometry": {"coordinates":[148.6015625,-32.2450904846],"type":"Point"}
}