{
  "type": "Feature",
  "properties": {
    "addr:full":"204-206 Gipps St Abbotsford VIC 3067",
    "addr:housenumber":"204-206",
    "addr:postcode":"3067",
    "addr:street":"Gipps St",
    "iso:country":"AU",
    "sg:address":"204-206 Gipps St",
    "sg:city":"Abbotsford",
    "sg:classifiers":[
        {
            "category":"Shopping",
            "subcategory":"Shoes",
            "type":"Retail Goods"
        }
    ],
    "sg:phone":"+61 3 8412 9800",
    "sg:postcode":"3067",
    "sg:province":"VIC",
    "sg:tags":[
        "footwear"
    ],
    "wof:name":"Aquila Shoes",
    "wof:placetype":"venue"
},
  "geometry": {"coordinates":[144.998657227,-37.8054962158],"type":"Point"}
}