{
  "type": "Feature",
  "properties": {
    "addr:full":"5 Stanton St Stawell VIC 3380",
    "addr:housenumber":"5",
    "addr:postcode":"3380",
    "addr:street":"Stanton St",
    "iso:country":"AU",
    "sg:address":"5 Stanton St",
    "sg:city":"Stawell",
    "sg:classifiers":[
        {
            "category":"Building & Trades",
            "subcategory":"Plumbing",
            "type":"Services"
        }
    ],
    "sg:phone":"+61 438 049 469",
    "sg:postcode":"3380",
    "sg:province":"VIC",
    "sg:tags":[
        "plumber",
        "gasfitters"
    ],
    "wof:name":"D & A Murley Plumbing",
    "wof:placetype":"venue"
},
  "geometry": {"coordinates":[142.77163696299999,-37.0548400879],"type":"Point"}
}