{
  "type": "Feature",
  "properties": {
    "iso:country":"AU",
    "sg:address":"14 Margaret St",
    "sg:city":"Highfield",
    "sg:classifiers":[
        {
            "category":"Building & Trades",
            "subcategory":"Landscaping Services",
            "type":"Services"
        }
    ],
    "sg:phone":"+61 2 4943 0305",
    "sg:postcode":"2485",
    "sg:province":"NSW",
    "sg:tags":[
        "designer",
        "landscape",
        "contractor"
    ],
    "wof:name":"Garden Parties Australia",
    "wof:placetype":"venue"
},
  "geometry": {"coordinates":[153.532012939,-28.185377121],"type":"Point"}
}