{
  "type": "Feature",
  "properties": {
    "iso:country":"AU",
    "sg:address":"2 Yester Ave",
    "sg:city":"Brighton",
    "sg:classifiers":[
        {
            "category":"Building & Trades",
            "subcategory":"Plumbing",
            "type":"Services"
        }
    ],
    "sg:phone":"+61 8 8298 5582",
    "sg:postcode":"5048",
    "sg:province":"SA",
    "sg:tags":[
        "plumber",
        "gasfitters"
    ],
    "wof:name":"Twigden M R",
    "wof:placetype":"venue"
},
  "geometry": {"coordinates":[138.516846,-35.015045],"type":"Point"}
}