{
  "type": "Feature",
  "properties": {
    "addr:full":"12a Lyell St Fyshwick ACT 2609",
    "addr:housenumber":"12a",
    "addr:postcode":"2609",
    "addr:street":"Lyell St",
    "iso:country":"AU",
    "sg:address":"12a Lyell St",
    "sg:city":"Fyshwick",
    "sg:classifiers":[
        {
            "category":"Professional",
            "subcategory":"Detective & Security Services",
            "type":"Services"
        }
    ],
    "sg:phone":"+61 2 6280 5829",
    "sg:postcode":"2609",
    "sg:province":"ACT",
    "sg:tags":[
        "equipment",
        "window",
        "doors"
    ],
    "wof:name":"Summers Glass",
    "wof:placetype":"venue"
},
  "geometry": {"coordinates":[149.17396545400001,-35.3283882141],"type":"Point"}
}