{
  "type": "Feature",
  "properties": {
    "iso:country":"AU",
    "sg:address":"Lot 100 Diment Rd",
    "sg:city":"Burton",
    "sg:classifiers":[
        {
            "category":"Farming",
            "subcategory":"Nursery",
            "type":"Manufacturing & Wholesale Goods"
        }
    ],
    "sg:phone":"+61 8 8280 5855",
    "sg:postcode":"5110",
    "sg:province":"SA",
    "wof:name":"Adelaide Roses",
    "wof:placetype":"venue"
},
  "geometry": {"coordinates":[138.60960388199999,-34.7298774719],"type":"Point"}
}