{
  "type": "Feature",
  "properties": {
    "iso:country":"AU",
    "sg:address":"23 Callitris Crs",
    "sg:city":"Marcus Beach",
    "sg:classifiers":[
        {
            "category":"Building & Trades",
            "subcategory":"Landscaping Services",
            "type":"Services"
        }
    ],
    "sg:phone":"+61 7 5448 2987",
    "sg:postcode":"4573",
    "sg:province":"QLD",
    "sg:tags":[
        "forestry",
        "consultant"
    ],
    "wof:name":"Sangara Agriforest Pty Ltd",
    "wof:placetype":"venue"
},
  "geometry": {"coordinates":[153.10079999999999,-26.4534],"type":"Point"}
}