{
  "type": "Feature",
  "properties": {
    "iso:country":"AU",
    "sg:address":"176 Woodward Rd",
    "sg:city":"Golden Square",
    "sg:classifiers":[
        {
            "category":"Professional",
            "subcategory":"Detective & Security Services",
            "type":"Services"
        }
    ],
    "sg:phone":"+61 3 5441 4199",
    "sg:postcode":"3555",
    "sg:province":"VIC",
    "sg:tags":[
        "consultant",
        "system"
    ],
    "wof:name":"farm Cam",
    "wof:placetype":"venue"
},
  "geometry": {"coordinates":[144.26564025900001,-36.7846069336],"type":"Point"}
}