{
  "type": "Feature",
  "properties": {
    "addr:full":"Dinyarrak Rd Serviceton VIC 3420",
    "addr:postcode":"3420",
    "addr:street":"Dinyarrak Rd",
    "iso:country":"AU",
    "sg:address":"Dinyarrak Rd",
    "sg:city":"Serviceton",
    "sg:classifiers":[
        {
            "category":"Farming",
            "subcategory":"Livestock Farm",
            "type":"Manufacturing & Wholesale Goods"
        }
    ],
    "sg:phone":"+61 3 5393 1358",
    "sg:postcode":"3420",
    "sg:province":"VIC",
    "sg:tags":[
        "breeder",
        "horse",
        "stud"
    ],
    "wof:name":"Miles M E & R B",
    "wof:placetype":"venue"
},
  "geometry": {"coordinates":[141.007568359,-36.3198280334],"type":"Point"}
}