{
  "type": "Feature",
  "properties": {
    "iso:country":"AU",
    "sg:address":"336 Carlisle St St",
    "sg:city":"Kilda East",
    "sg:classifiers":[
        {
            "category":"Health Services",
            "subcategory":"Doctor",
            "type":"Services"
        }
    ],
    "sg:phone":"+61 3 9527 2365",
    "sg:postcode":"3183",
    "sg:province":"VIC",
    "sg:tags":[
        "medical",
        "practitioner"
    ],
    "wof:name":"Rosenberg Paul M",
    "wof:placetype":"venue"
},
  "geometry": {"coordinates":[144.996459961,-37.8689689636],"type":"Point"}
}