{
  "type": "Feature",
  "properties": {
    "addr:full":"33 Lewis Ave Seven Mile Beach TAS 7170",
    "addr:housenumber":"33",
    "addr:postcode":"7170",
    "addr:street":"Lewis Ave",
    "iso:country":"AU",
    "sg:address":"33 Lewis Ave",
    "sg:city":"Seven Mile Beach",
    "sg:classifiers":[
        {
            "category":"Building & Trades",
            "subcategory":"Construction",
            "type":"Services"
        }
    ],
    "sg:phone":"+61 3 6248 7318",
    "sg:postcode":"7170",
    "sg:province":"TAS",
    "sg:tags":[
        "contractor"
    ],
    "wof:name":"Jackson Builders",
    "wof:placetype":"venue"
},
  "geometry": {"coordinates":[147.502349853,-42.8595809937],"type":"Point"}
}