{
  "type": "Feature",
  "properties": {
    "addr:full":"2/ 30 Aberdeen Rd Macleod VIC 3085",
    "addr:housenumber":"/ 30",
    "addr:postcode":"3085",
    "addr:street":"Aberdeen Rd",
    "iso:country":"AU",
    "sg:address":"2/ 30 Aberdeen Rd",
    "sg:city":"Macleod",
    "sg:classifiers":[
        {
            "category":"Professional",
            "subcategory":"Accounting & Tax Preparation",
            "type":"Services"
        }
    ],
    "sg:phone":"+61 3 9459 2833",
    "sg:postcode":"3085",
    "sg:province":"VIC",
    "sg:tags":[
        "accountant",
        "auditor"
    ],
    "wof:name":"Chris Gannon",
    "wof:placetype":"venue"
},
  "geometry": {"coordinates":[145.07020568900001,-37.7276382446],"type":"Point"}
}