{
  "type": "Feature",
  "properties": {
    "addr:full":"47 Errol St North Melbourne VIC 3051",
    "addr:housenumber":"47",
    "addr:postcode":"3051",
    "addr:street":"Errol St",
    "iso:country":"AU",
    "sg:address":"47 Errol St",
    "sg:city":"North Melbourne",
    "sg:classifiers":[
        {
            "category":"Fast Food",
            "type":"Food & Drink"
        }
    ],
    "sg:phone":"+61 3 9328 1781",
    "sg:postcode":"3051",
    "sg:province":"VIC",
    "sg:tags":[
        "away",
        "take"
    ],
    "wof:name":"Urban Burger",
    "wof:placetype":"venue"
},
  "geometry": {"coordinates":[144.94932556099999,-37.8038787842],"type":"Point"}
}