{
  "type": "Feature",
  "properties": {
    "addr:full":"84-88 Goodwood Pde Burswood WA 6100",
    "addr:housenumber":"84-88",
    "addr:postcode":"6100",
    "addr:street":"Goodwood Pde",
    "iso:country":"AU",
    "sg:address":"84-88 Goodwood Pde",
    "sg:city":"Burswood",
    "sg:classifiers":[
        {
            "category":"Professional",
            "type":"Services"
        }
    ],
    "sg:phone":"+61 8 9355 2111",
    "sg:postcode":"6100",
    "sg:province":"WA",
    "sg:tags":[
        "valuer"
    ],
    "wof:name":"Hayes Auctioneers",
    "wof:placetype":"venue"
},
  "geometry": {"coordinates":[115.89732360799999,-31.9653644562],"type":"Point"}
}