{
  "type": "Feature",
  "properties": {
    "addr:full":"Cnr Grand Prom & Walter Rd Dianella WA 6059",
    "addr:postcode":"6059",
    "addr:street":"Cnr Grand;Rd",
    "iso:country":"AU",
    "sg:address":"Cnr Grand Prom & Walter Rd",
    "sg:city":"Dianella",
    "sg:classifiers":[
        {
            "category":"Autos & Motor Vehicles",
            "subcategory":"Fuel & Gas Station",
            "type":"Retail Goods"
        }
    ],
    "sg:phone":"+61 8 9473 1213",
    "sg:postcode":"6059",
    "sg:province":"WA",
    "wof:name":"Maxi Fuel",
    "wof:placetype":"venue"
},
  "geometry": {"coordinates":[115.88259887700001,-31.9063301086],"type":"Point"}
}