{
  "type": "Feature",
  "properties": {
    "addr:full":"70 Sargent St Alice Springs NT 0870",
    "addr:housenumber":"70",
    "addr:postcode":"nt 0870",
    "addr:street":"Sargent St",
    "iso:country":"AU",
    "sg:address":"70 Sargent St",
    "sg:city":"Alice Springs",
    "sg:classifiers":[
        {
            "category":"Structure",
            "subcategory":"Office Building",
            "type":"Public Place"
        }
    ],
    "sg:phone":"+61 402 104 500",
    "sg:postcode":"0870",
    "sg:province":"NT",
    "sg:tags":[
        "tie",
        "concrete",
        "formwork",
        "form",
        "accessory"
    ],
    "wof:name":"M & M Formwork",
    "wof:placetype":"venue"
},
  "geometry": {"coordinates":[133.864776611,-23.6725444794],"type":"Point"}
}