{
  "type": "Feature",
  "properties": {
    "iso:country":"AU",
    "sg:address":"52 Paley St",
    "sg:city":"Campbelltown",
    "sg:classifiers":[
        {
            "category":"Education",
            "subcategory":"Music School",
            "type":"Public Place"
        }
    ],
    "sg:phone":"+61 2 4626 1642",
    "sg:postcode":"2560",
    "sg:province":"NSW",
    "sg:tags":[
        "teacher"
    ],
    "wof:name":"Whitmore School Of Music",
    "wof:placetype":"venue"
},
  "geometry": {"coordinates":[150.80201721200001,-34.0739784241],"type":"Point"}
}