{
  "type": "Feature",
  "properties": {
    "addr:full":"The Arcade, McAdam Square Plymouth Rd Croydon North VIC 3136",
    "addr:postcode":"3136",
    "addr:street":"Plymouth Rd",
    "iso:country":"AU",
    "sg:address":"The Arcade, McAdam Square Plymouth Rd",
    "sg:city":"Croydon North",
    "sg:classifiers":[
        {
            "category":"Shopping",
            "subcategory":"Clothing, Apparel, & Fashions",
            "type":"Retail Goods"
        }
    ],
    "sg:phone":"+61 3 9725 3793",
    "sg:postcode":"3136",
    "sg:province":"VIC",
    "sg:tags":[
        "recycled",
        "clothing"
    ],
    "wof:name":"Between Friends",
    "wof:placetype":"venue"
},
  "geometry": {"coordinates":[145.27362060600001,-37.783493042],"type":"Point"}
}