{
  "type": "Feature",
  "properties": {
    "addr:full":"289 Canberra Ave Fyshwick ACT 2609",
    "addr:housenumber":"289",
    "addr:postcode":"2609",
    "addr:street":"Canberra Ave",
    "iso:country":"AU",
    "sg:address":"289 Canberra Ave",
    "sg:city":"Fyshwick",
    "sg:classifiers":[
        {
            "category":"Wholesale",
            "subcategory":"Painting Supplies",
            "type":"Manufacturing & Wholesale Goods"
        }
    ],
    "sg:phone":"+61 2 6280 6349",
    "sg:postcode":"2609",
    "sg:province":"ACT",
    "sg:tags":[
        "painter"
    ],
    "wof:name":"Bristol",
    "wof:placetype":"venue"
},
  "geometry": {"coordinates":[149.169525147,-35.3339614868],"type":"Point"}
}