{
  "type": "Feature",
  "properties": {
    "iso:country":"AU",
    "sg:address":"8 Chapple St",
    "sg:city":"Gympie",
    "sg:classifiers":[
        {
            "category":"Home & Garden",
            "subcategory":"Hardware",
            "type":"Retail Goods"
        }
    ],
    "sg:phone":"+61 7 5482 8835",
    "sg:postcode":"4570",
    "sg:province":"QLD",
    "sg:tags":[
        "plumber",
        "supply"
    ],
    "wof:name":"Plumbing Plus",
    "wof:placetype":"venue"
},
  "geometry": {"coordinates":[152.67071533199999,-26.1864833832],"type":"Point"}
}