{
  "type": "Feature",
  "properties": {
    "addr:full":"164 Russell Rd New Lambton Heights NSW 2305",
    "addr:housenumber":"164",
    "addr:postcode":"2305",
    "addr:street":"Russell Rd",
    "iso:country":"AU",
    "sg:address":"164 Russell Rd",
    "sg:city":"New Lambton Heights",
    "sg:classifiers":[
        {
            "category":"Shopping",
            "type":"Retail Goods"
        }
    ],
    "sg:phone":"+61 2 4952 3072",
    "sg:postcode":"2305",
    "sg:province":"NSW",
    "sg:tags":[
        "supply",
        "religious",
        "church"
    ],
    "wof:name":"Heritage Stained Glass",
    "wof:placetype":"venue"
},
  "geometry": {"coordinates":[151.704285,-32.922039],"type":"Point"}
}