{
  "type": "Feature",
  "properties": {
    "iso:country":"AU",
    "sg:address":"1362 Lytton Rd",
    "sg:city":"Hemmant",
    "sg:classifiers":[
        {
            "category":"Wholesale",
            "subcategory":"Machinery & Supplies",
            "type":"Manufacturing & Wholesale Goods"
        }
    ],
    "sg:phone":"+61 7 3390 6589",
    "sg:postcode":"4174",
    "sg:province":"QLD",
    "sg:tags":[
        "rigging",
        "equipment",
        "hoisting"
    ],
    "wof:name":"Central Scaffolding & Rigging Services Pty Ltd",
    "wof:placetype":"venue"
},
  "geometry": {"coordinates":[153.12541198700001,-27.4453296661],"type":"Point"}
}