{
  "type": "Feature",
  "properties": {
    "iso:country":"AU",
    "sg:address":"24 Minimine St",
    "sg:city":"Stafford",
    "sg:classifiers":[
        {
            "category":"Organizations",
            "subcategory":"Labor Organization",
            "type":"Services"
        }
    ],
    "sg:phone":"+61 7 3356 2822",
    "sg:postcode":"4053",
    "sg:province":"QLD",
    "sg:tags":[
        "pattern",
        "clothing"
    ],
    "wof:name":"B R Patterns",
    "wof:placetype":"venue"
},
  "geometry": {"coordinates":[153.01643371599999,-27.4063911438],"type":"Point"}
}