{
  "type": "Feature",
  "properties": {
    "iso:country":"AU",
    "sg:address":"71 Hall Rd",
    "sg:city":"Carrum Downs",
    "sg:classifiers":[
        {
            "category":"Food & Beverages",
            "subcategory":"Liquor & Beverages",
            "type":"Retail Goods"
        }
    ],
    "sg:phone":"+61 3 9788 9900",
    "sg:postcode":"3201",
    "sg:province":"VIC",
    "sg:tags":[
        "store"
    ],
    "wof:name":"BWS Liquor Stores",
    "wof:placetype":"venue"
},
  "geometry": {"coordinates":[145.184113,-38.100769],"type":"Point"}
}