{
  "type": "Feature",
  "properties": {
    "iso:country":"AU",
    "sg:address":"67 Scott St",
    "sg:city":"Liverpool",
    "sg:classifiers":[
        {
            "category":"Health Services",
            "subcategory":"Health Practitioner",
            "type":"Services"
        }
    ],
    "sg:phone":"+61 2 9600 8940",
    "sg:postcode":"2170",
    "sg:province":"NSW",
    "sg:tags":[
        "naturopath"
    ],
    "wof:name":"Advanced Natural Therapy Centre",
    "wof:placetype":"venue"
},
  "geometry": {"coordinates":[150.923950195,-33.9248390198],"type":"Point"}
}