{
  "type": "Feature",
  "properties": {
    "iso:country":"AU",
    "sg:address":"199 High St",
    "sg:city":"Ashburton",
    "sg:classifiers":[
        {
            "category":"Real Estate",
            "subcategory":"Real Estate Agent",
            "type":"Services"
        }
    ],
    "sg:phone":"+61 3 9885 4466",
    "sg:postcode":"3147",
    "sg:province":"VIC",
    "wof:name":"Woodards",
    "wof:placetype":"venue"
},
  "geometry": {"coordinates":[145.076705933,-37.8629112244],"type":"Point"}
}