{
  "type": "Feature",
  "properties": {
    "iso:country":"AU",
    "sg:address":"55 Ellenborough St",
    "sg:city":"Ipswich",
    "sg:classifiers":[
        {
            "category":"Insurance",
            "subcategory":"Life Insurance",
            "type":"Services"
        }
    ],
    "sg:phone":"+61 7 3812 1744",
    "sg:postcode":"4305",
    "sg:province":"QLD",
    "wof:name":"Ipsure Insurance & Financial Services",
    "wof:placetype":"venue"
},
  "geometry": {"coordinates":[152.75697326700001,-27.6167831421],"type":"Point"}
}