{
  "type": "Feature",
  "properties": {
    "addr:full":"Fraser Rd Duntroon ACT 2600",
    "addr:postcode":"2600",
    "addr:street":"Fraser Rd",
    "iso:country":"AU",
    "sg:address":"Fraser Rd",
    "sg:city":"Duntroon",
    "sg:classifiers":[
        {
            "category":"Personal",
            "subcategory":"Barber",
            "type":"Services"
        }
    ],
    "sg:phone":"+61 2 6275 9584",
    "sg:postcode":"2600",
    "sg:province":"ACT",
    "wof:name":"Duntroon Hairdressers",
    "wof:placetype":"venue"
},
  "geometry": {"coordinates":[149.09715270999999,-35.3123931885],"type":"Point"}
}