{
  "type": "Feature",
  "properties": {
    "addr:full":"U3/ 52 Regentville Rd Penrith NSW 2750",
    "addr:postcode":"2750",
    "addr:street":"U3 / 52 Regentville Rd",
    "iso:country":"AU",
    "sg:address":"U3/ 52 Regentville Rd",
    "sg:city":"Penrith",
    "sg:classifiers":[
        {
            "category":"Manufacturing",
            "subcategory":"Wood Products",
            "type":"Manufacturing & Wholesale Goods"
        }
    ],
    "sg:phone":"+61 2 4722 3944",
    "sg:postcode":"2750",
    "sg:province":"NSW",
    "sg:tags":[
        "pallet",
        "platform"
    ],
    "wof:name":"D & S Pallets Pty Ltd",
    "wof:placetype":"venue"
},
  "geometry": {"coordinates":[150.68299865700001,-33.7659034729],"type":"Point"}
}