{
  "type": "Feature",
  "properties": {
    "addr:full":"39- 43 Sammut St Smithfield NSW 2164",
    "addr:housenumber":"43",
    "addr:postcode":"2164",
    "addr:street":"Sammut St",
    "iso:country":"AU",
    "sg:address":"39- 43 Sammut St",
    "sg:city":"Smithfield",
    "sg:classifiers":[
        {
            "category":"Wholesale",
            "subcategory":"Metals & Minerals",
            "type":"Manufacturing & Wholesale Goods"
        }
    ],
    "sg:phone":"+61 2 9604 4555",
    "sg:postcode":"2164",
    "sg:province":"NSW",
    "sg:tags":[
        "steel",
        "stainless",
        "product",
        "equipment"
    ],
    "sg:website":"http://www.stainlesssections.com.au",
    "wof:name":"Stainless Sections Pty Ltd",
    "wof:placetype":"venue"
},
  "geometry": {"coordinates":[150.93371582,-33.8397865295],"type":"Point"}
}