{
  "type": "Feature",
  "properties": {
    "addr:full":"Unit6/ 2 Liverpool St Ingleburn NSW 2565",
    "addr:housenumber":"2",
    "addr:postcode":"2565",
    "addr:street":"Liverpool St",
    "iso:country":"AU",
    "sg:address":"Unit6/ 2 Liverpool St",
    "sg:city":"Ingleburn",
    "sg:classifiers":[
        {
            "category":"Professional",
            "subcategory":"Employment Agencies",
            "type":"Services"
        }
    ],
    "sg:phone":"+61 412 994 194",
    "sg:postcode":"2565",
    "sg:province":"NSW",
    "sg:tags":[
        "entertainer",
        "agent"
    ],
    "wof:name":"WooHoo Entertainment",
    "wof:placetype":"venue"
},
  "geometry": {"coordinates":[150.86257934599999,-33.9965362549],"type":"Point"}
}