{
  "type": "Feature",
  "properties": {
    "addr:full":"89 Albert Rd Moonah TAS 7009",
    "addr:housenumber":"89",
    "addr:postcode":"7009",
    "addr:street":"Albert Rd",
    "iso:country":"AU",
    "sg:address":"89 Albert Rd",
    "sg:city":"Moonah",
    "sg:classifiers":[
        {
            "category":"Professional",
            "subcategory":"Employment Agencies",
            "type":"Services"
        }
    ],
    "sg:phone":"+61 421 509 148",
    "sg:postcode":"7009",
    "sg:province":"TAS",
    "sg:tags":[
        "model"
    ],
    "wof:name":"Euro modelling",
    "wof:placetype":"venue"
},
  "geometry": {"coordinates":[147.295455933,-42.8458518982],"type":"Point"}
}