{
  "type": "Feature",
  "properties": {
    "iso:country":"AU",
    "sg:address":"Unit 4, Sholl House, 21 Sholl St",
    "sg:city":"Mandurah",
    "sg:classifiers":[
        {
            "category":"Banks & Credit Unions",
            "subcategory":"Atm",
            "type":"Services"
        }
    ],
    "sg:phone":"+61 8 9586 8000",
    "sg:postcode":"6210",
    "sg:province":"WA",
    "sg:tags":[
        "shelf"
    ],
    "sg:website":"http://www.acndirect.com.au",
    "wof:name":"ACN Direct",
    "wof:placetype":"venue"
},
  "geometry": {"coordinates":[115.721397,-32.531876],"type":"Point"}
}