{
  "type": "Feature",
  "properties": {
    "addr:full":"106 Beamish St Campsie NSW 2194",
    "addr:housenumber":"106",
    "addr:postcode":"2194",
    "addr:street":"Beamish St",
    "iso:country":"AU",
    "sg:address":"106 Beamish St",
    "sg:city":"Campsie",
    "sg:classifiers":[
        {
            "category":"Autos & Motor Vehicles",
            "subcategory":"Auto Supplies",
            "type":"Retail Goods"
        }
    ],
    "sg:phone":"+61 2 9718 7555",
    "sg:postcode":"2194",
    "sg:province":"NSW",
    "sg:tags":[
        "tyre"
    ],
    "wof:name":"Jobsons Discount Tyre & Mechanical",
    "wof:placetype":"venue"
},
  "geometry": {"coordinates":[151.103058,-33.9077],"type":"Point"}
}