{
  "type": "Feature",
  "properties": {
    "iso:country":"AU",
    "sg:address":"Cnr The Esplanade & Main Rd",
    "sg:city":"Speers Point",
    "sg:classifiers":[
        {
            "category":"Restaurant",
            "type":"Food & Drink"
        }
    ],
    "sg:phone":"+61 2 4958 1022",
    "sg:postcode":"2284",
    "sg:province":"NSW",
    "wof:name":"Pippis At The Point",
    "wof:placetype":"venue"
},
  "geometry": {"coordinates":[151.620071411,-32.9606933594],"type":"Point"}
}