{
  "type": "Feature",
  "properties": {
    "addr:full":"14 Mitchell St Colbinabbin VIC 3559",
    "addr:housenumber":"14",
    "addr:postcode":"3559",
    "addr:street":"Mitchell St",
    "iso:country":"AU",
    "sg:address":"14 Mitchell St",
    "sg:city":"Colbinabbin",
    "sg:classifiers":[
        {
            "category":"Retail",
            "subcategory":"Auto Repair",
            "type":"Services"
        }
    ],
    "sg:phone":"+61 3 5432 9258",
    "sg:postcode":"3559",
    "sg:province":"VIC",
    "sg:tags":[
        "repairer",
        "motor",
        "engineer"
    ],
    "wof:name":"Colbinabbin Motors",
    "wof:placetype":"venue"
},
  "geometry": {"coordinates":[144.79327392600001,-36.5901374817],"type":"Point"}
}