{
  "type": "Feature",
  "properties": {
    "addr:full":"Newcastle Drv Coffs Harbour NSW 2450",
    "addr:postcode":"2450",
    "addr:street":"Newcastle Drv",
    "iso:country":"AU",
    "sg:address":"Newcastle Drv",
    "sg:city":"Coffs Harbour",
    "sg:classifiers":[
        {
            "category":"Home & Garden",
            "subcategory":"Building Materials",
            "type":"Retail Goods"
        }
    ],
    "sg:phone":"+61 2 6653 3711",
    "sg:postcode":"2450",
    "sg:province":"NSW",
    "sg:tags":[
        "pre-mixed",
        "concrete"
    ],
    "wof:name":"Pioneer Concrete",
    "wof:placetype":"venue"
},
  "geometry": {"coordinates":[153.09172100000001,-30.362101],"type":"Point"}
}