{
  "type": "Feature",
  "properties": {
    "addr:full":"33 Greenaway St Bulleen VIC 3105",
    "addr:housenumber":"33",
    "addr:postcode":"3105",
    "addr:street":"Greenaway St",
    "iso:country":"AU",
    "sg:address":"33 Greenaway St",
    "sg:city":"Bulleen",
    "sg:classifiers":[
        {
            "category":"Industrial Area",
            "type":"Public Place"
        }
    ],
    "sg:phone":"+61 3 9850 9722",
    "sg:postcode":"3105",
    "sg:province":"VIC",
    "sg:tags":[
        "consulting",
        "chemist"
    ],
    "sg:website":"http://www.sharpandhowells.com.au",
    "wof:name":"Sharp & Howells P/L",
    "wof:placetype":"venue"
},
  "geometry": {"coordinates":[145.081756592,-37.7636642456],"type":"Point"}
}