{
  "type": "Feature",
  "properties": {
    "addr:full":"Ste 101/ 621 Pacific Hwy St Leonards NSW 2065",
    "addr:housenumber":"/ 621",
    "addr:postcode":"2065",
    "addr:street":"Pacific Hwy",
    "iso:country":"AU",
    "sg:address":"Ste 101/ 621 Pacific Hwy",
    "sg:city":"St Leonards",
    "sg:classifiers":[
        {
            "category":"Professional",
            "subcategory":"Computer Services",
            "type":"Services"
        }
    ],
    "sg:phone":"+61 2 9966 4188",
    "sg:postcode":"2065",
    "sg:province":"NSW",
    "sg:tags":[
        "consultant",
        "system"
    ],
    "wof:name":"Snapdragon Consulting Pty Ltd",
    "wof:placetype":"venue"
},
  "geometry": {"coordinates":[151.19670105,-33.8233757019],"type":"Point"}
}