{
  "type": "Feature",
  "properties": {
    "addr:full":"14A Old Princes Hwy Falls Creek NSW 2540",
    "addr:housenumber":"14a",
    "addr:postcode":"2540",
    "addr:street":"Old Princes Hwy Falls",
    "iso:country":"AU",
    "sg:address":"14A Old Princes Hwy",
    "sg:city":"Falls Creek",
    "sg:classifiers":[
        {
            "category":"Home & Garden",
            "subcategory":"Building Materials",
            "type":"Retail Goods"
        }
    ],
    "sg:phone":"+61 402 469 118",
    "sg:postcode":"2540",
    "sg:province":"NSW",
    "sg:tags":[
        "retaining",
        "wall"
    ],
    "wof:name":"Dale Pickering Landscaping & Design",
    "wof:placetype":"venue"
},
  "geometry": {"coordinates":[150.594512939,-34.9721183777],"type":"Point"}
}