{
  "type": "Feature",
  "properties": {
    "addr:full":"366 Belgrave-Gembrook Rd Emerald VIC 3782",
    "addr:housenumber":"366",
    "addr:postcode":"3782",
    "addr:street":"Belgrave-Gembrook Rd",
    "iso:country":"AU",
    "sg:address":"366 Belgrave-Gembrook Rd",
    "sg:city":"Emerald",
    "sg:classifiers":[
        {
            "category":"Sports & Exercise",
            "subcategory":"Gym",
            "type":"Entertainment"
        }
    ],
    "sg:phone":"+61 3 5968 2398",
    "sg:postcode":"3782",
    "sg:province":"VIC",
    "sg:tags":[
        "health",
        "fitness"
    ],
    "wof:name":"Vibe Health & Fitness",
    "wof:placetype":"venue"
},
  "geometry": {"coordinates":[145.44212300000001,-37.931698],"type":"Point"}
}