{
  "type": "Feature",
  "properties": {
    "addr:full":"195 Abbott St Cairns QLD 4870",
    "addr:housenumber":"195",
    "addr:postcode":"4870",
    "addr:street":"Abbott St",
    "iso:country":"AU",
    "sg:address":"195 Abbott St",
    "sg:city":"Cairns",
    "sg:classifiers":[
        {
            "category":"Professional",
            "subcategory":"Accounting & Tax Preparation",
            "type":"Services"
        }
    ],
    "sg:phone":"+61 7 4044 0130",
    "sg:postcode":"4870",
    "sg:province":"QLD",
    "sg:tags":[
        "pregnancy",
        "related",
        "counselling"
    ],
    "wof:name":"Centacare Cairns",
    "wof:placetype":"venue"
},
  "geometry": {"coordinates":[145.7787323,-16.9236717224],"type":"Point"}
}