{
  "type": "Feature",
  "properties": {
    "addr:full":"10 Desmond Ave Marleston SA 5033",
    "addr:housenumber":"10",
    "addr:postcode":"5033",
    "addr:street":"Desmond Ave",
    "iso:country":"AU",
    "sg:address":"10 Desmond Ave",
    "sg:city":"Marleston",
    "sg:classifiers":[
        {
            "category":"Home & Garden",
            "subcategory":"Carpets & Floor Coverings",
            "type":"Retail Goods"
        }
    ],
    "sg:phone":"+61 8 8293 8630",
    "sg:postcode":"5033",
    "sg:province":"SA",
    "sg:tags":[
        "tile",
        "wall",
        "layer"
    ],
    "wof:name":"Bahr U K",
    "wof:placetype":"venue"
},
  "geometry": {"coordinates":[138.55575561500001,-34.9458885193],"type":"Point"}
}