{
  "type": "Feature",
  "properties": {
    "iso:country":"AU",
    "sg:address":"25 Production St",
    "sg:city":"Noosaville",
    "sg:classifiers":[
        {
            "category":"Manufacturing",
            "subcategory":"Rubber & Plastics",
            "type":"Manufacturing & Wholesale Goods"
        }
    ],
    "sg:phone":"+61 7 5442 4242",
    "sg:postcode":"4566",
    "sg:province":"QLD",
    "sg:tags":[
        "wholesaler",
        "product",
        "mfrs"
    ],
    "wof:name":"Action Tank Industries Pty Ltd",
    "wof:placetype":"venue"
},
  "geometry": {"coordinates":[153.04496765100001,-26.4178771973],"type":"Point"}
}