{
  "type": "Feature",
  "properties": {
    "addr:full":"6 Wilmette Pl Mona Vale NSW 2103",
    "addr:housenumber":"6",
    "addr:postcode":"2103",
    "addr:street":"Pl",
    "iso:country":"AU",
    "sg:address":"6 Wilmette Pl",
    "sg:city":"Mona Vale",
    "sg:classifiers":[
        {
            "category":"Banks & Credit Unions",
            "subcategory":"Investment Brokerage",
            "type":"Services"
        }
    ],
    "sg:phone":"+61 2 9979 6099",
    "sg:postcode":"2103",
    "sg:province":"NSW",
    "sg:tags":[
        "equipment",
        "spray",
        "painting",
        "supply"
    ],
    "wof:name":"Portabooth",
    "wof:placetype":"venue"
},
  "geometry": {"coordinates":[151.30494689899999,-33.6729011536],"type":"Point"}
}