{
  "type": "Feature",
  "properties": {
    "addr:full":"20 Ryan St Moonta SA 5558",
    "addr:housenumber":"20",
    "addr:postcode":"5558",
    "addr:street":"Ryan St",
    "iso:country":"AU",
    "sg:address":"20 Ryan St",
    "sg:city":"Moonta",
    "sg:classifiers":[
        {
            "category":"Travel",
            "subcategory":"Hotels & Motels",
            "type":"Entertainment"
        }
    ],
    "sg:phone":"+61 8 8825 2304",
    "sg:postcode":"5558",
    "sg:province":"SA",
    "sg:tags":[
        "pub"
    ],
    "wof:name":"Cornwall Hotel",
    "wof:placetype":"venue"
},
  "geometry": {"coordinates":[137.592407227,-34.0673408508],"type":"Point"}
}