{
  "type": "Feature",
  "properties": {
    "addr:full":"170 Pacific Hwy Broadwater NSW 2472",
    "addr:housenumber":"170",
    "addr:postcode":"2472",
    "addr:street":"Pacific Hwy",
    "iso:country":"AU",
    "sg:address":"170 Pacific Hwy",
    "sg:city":"Broadwater",
    "sg:classifiers":[
        {
            "category":"Personal",
            "subcategory":"Beauty Salon",
            "type":"Services"
        }
    ],
    "sg:phone":"+61 2 6682 8005",
    "sg:postcode":"2472",
    "sg:province":"NSW",
    "sg:tags":[
        "hairdresser"
    ],
    "wof:name":"Elenshe Hair",
    "wof:placetype":"venue"
},
  "geometry": {"coordinates":[153.435638428,-29.0106830597],"type":"Point"}
}