{
  "type": "Feature",
  "properties": {
    "addr:full":"11 Chaffer St Healesville VIC 3777",
    "addr:housenumber":"11",
    "addr:postcode":"3777",
    "addr:street":"Chaffer St",
    "iso:country":"AU",
    "sg:address":"11 Chaffer St",
    "sg:city":"Healesville",
    "sg:classifiers":[
        {
            "category":"Professional",
            "subcategory":"Engineering",
            "type":"Services"
        }
    ],
    "sg:phone":"+61 412 518 685",
    "sg:postcode":"3777",
    "sg:province":"VIC",
    "sg:tags":[
        "consulting",
        "engineer"
    ],
    "wof:name":"DJC Engineering Management Services",
    "wof:placetype":"venue"
},
  "geometry": {"coordinates":[145.49146999999999,-37.635628],"type":"Point"}
}