{
  "type": "Feature",
  "properties": {
    "iso:country":"AU",
    "sg:address":"61 Market St",
    "sg:city":"Wollongong",
    "sg:classifiers":[
        {
            "category":"Health Services",
            "subcategory":"Health Practitioner",
            "type":"Services"
        }
    ],
    "sg:phone":"+61 2 4226 3371",
    "sg:postcode":"2500",
    "sg:province":"NSW",
    "sg:tags":[
        "psychologist"
    ],
    "wof:name":"CG Psychological Services",
    "wof:placetype":"venue"
},
  "geometry": {"coordinates":[150.894836,-34.424179],"type":"Point"}
}