{
  "type": "Feature",
  "properties": {
    "addr:full":"Frith Rd Cherry Gardens SA 5157",
    "addr:postcode":"5157",
    "addr:street":"Frith Rd",
    "iso:country":"AU",
    "sg:address":"Frith Rd",
    "sg:city":"Cherry Gardens",
    "sg:classifiers":[
        {
            "category":"Wholesale",
            "subcategory":"Farm Supplies",
            "type":"Manufacturing & Wholesale Goods"
        }
    ],
    "sg:phone":"+61 8 8388 2788",
    "sg:postcode":"5157",
    "sg:province":"SA",
    "sg:tags":[
        "feed",
        "supplement",
        "stock"
    ],
    "wof:name":"Frithys Rural",
    "wof:placetype":"venue"
},
  "geometry": {"coordinates":[138.66722106899999,-35.0750160217],"type":"Point"}
}