{
  "type": "Feature",
  "properties": {
    "iso:country":"AU",
    "sg:address":"Shop C01, Bunker Rd (Cnr High St)",
    "sg:city":"Victoria Point",
    "sg:classifiers":[
        {
            "category":"Fast Food",
            "type":"Food & Drink"
        }
    ],
    "sg:phone":"+61 7 3207 7107",
    "sg:postcode":"4165",
    "sg:province":"QLD",
    "sg:tags":[
        "away",
        "take"
    ],
    "wof:name":"Big Chief Flame Grill Victoria Point",
    "wof:placetype":"venue"
},
  "geometry": {"coordinates":[153.273635864,-27.5944728851],"type":"Point"}
}