{
  "type": "Feature",
  "properties": {
    "iso:country":"AU",
    "sg:address":"Villiers Drv",
    "sg:city":"Currumbin",
    "sg:classifiers":[
        {
            "category":"Wholesale",
            "subcategory":"Construction Materials",
            "type":"Manufacturing & Wholesale Goods"
        }
    ],
    "sg:phone":"+61 7 5598 1216",
    "sg:postcode":"4223",
    "sg:province":"QLD",
    "sg:tags":[
        "wholesaler",
        "lighting",
        "mfrs",
        "accessory"
    ],
    "wof:name":"Dux Lighting Agencies",
    "wof:placetype":"venue"
},
  "geometry": {"coordinates":[153.47096252399999,-28.1504421234],"type":"Point"}
}