{
  "type": "Feature",
  "properties": {
    "addr:full":"Unit B2, 303 The Horsley Drv Fairfield NSW 2165",
    "addr:housenumber":"303",
    "addr:postcode":"2165",
    "addr:street":"The Horsley Drv",
    "iso:country":"AU",
    "sg:address":"Unit B2, 303 The Horsley Drv",
    "sg:city":"Fairfield",
    "sg:classifiers":[
        {
            "category":"Retail",
            "subcategory":"Auto Repair",
            "type":"Services"
        }
    ],
    "sg:phone":"+61 2 9726 3611",
    "sg:postcode":"2165",
    "sg:province":"NSW",
    "sg:tags":[
        "repairer",
        "motor",
        "engineer"
    ],
    "wof:name":"Midas",
    "wof:placetype":"venue"
},
  "geometry": {"coordinates":[150.95979309099999,-33.8690834045],"type":"Point"}
}