{
  "type": "Feature",
  "properties": {
    "addr:full":"164 Victoria St Mackay QLD 4740",
    "addr:housenumber":"164",
    "addr:postcode":"4740",
    "addr:street":"Victoria St",
    "iso:country":"AU",
    "sg:address":"164 Victoria St",
    "sg:city":"Mackay",
    "sg:classifiers":[
        {
            "category":"Internet Cafe",
            "subcategory":"None",
            "type":"Food & Drink"
        }
    ],
    "sg:phone":"+61 7 4957 4484",
    "sg:postcode":"4740",
    "sg:province":"QLD",
    "wof:name":"Rock N Road Internet Cafes",
    "wof:placetype":"venue"
},
  "geometry": {"coordinates":[149.184235,-21.140791],"type":"Point"}
}