{
  "type": "Feature",
  "properties": {
    "addr:full":"7- 9 Fisher St Silverwater NSW 2128",
    "addr:housenumber":"9",
    "addr:postcode":"2128",
    "addr:street":"Fisher St",
    "iso:country":"AU",
    "sg:address":"7- 9 Fisher St",
    "sg:city":"Silverwater",
    "sg:classifiers":[
        {
            "category":"Retail",
            "subcategory":"Laundry & Dry Cleaning",
            "type":"Services"
        }
    ],
    "sg:phone":"+61 2 9748 1148",
    "sg:postcode":"2128",
    "sg:province":"NSW",
    "wof:name":"About Linen Pty Ltd",
    "wof:placetype":"venue"
},
  "geometry": {"coordinates":[151.0390625,-33.8348464966],"type":"Point"}
}