{
  "type": "Feature",
  "properties": {
    "addr:full":"24 Last St West Latrobe TAS 7307",
    "addr:housenumber":"24",
    "addr:postcode":"7307",
    "addr:street":"Last St",
    "iso:country":"AU",
    "sg:address":"24 Last St West",
    "sg:city":"Latrobe",
    "sg:classifiers":[
        {
            "category":"Building & Trades",
            "subcategory":"Construction",
            "type":"Services"
        }
    ],
    "sg:phone":"+61 417 142 782",
    "sg:postcode":"7307",
    "sg:province":"TAS",
    "sg:tags":[
        "earth",
        "excavating",
        "moving",
        "contractor"
    ],
    "wof:name":"Mitch's Mini Digger",
    "wof:placetype":"venue"
},
  "geometry": {"coordinates":[146.405823,-41.232548],"type":"Point"}
}