{
  "type": "Feature",
  "properties": {
    "iso:country":"AU",
    "sg:address":"Fernhills Rd",
    "sg:city":"Tatong",
    "sg:classifiers":[
        {
            "category":"Education",
            "subcategory":"School",
            "type":"Public Place"
        }
    ],
    "sg:phone":"+61 3 5767 2222",
    "sg:postcode":"3673",
    "sg:province":"VIC",
    "sg:tags":[
        "state",
        "except",
        "nsw"
    ],
    "wof:name":"Tatong Campus Of Peranbin Primary College",
    "wof:placetype":"venue"
},
  "geometry": {"coordinates":[146.10788,-36.730381],"type":"Point"}
}