{
  "type": "Feature",
  "properties": {
    "iso:country":"AU",
    "sg:address":"276 Booker Bay Rd",
    "sg:city":"Booker Bay",
    "sg:classifiers":[
        {
            "category":"Home & Garden",
            "subcategory":"Carpets & Floor Coverings",
            "type":"Retail Goods"
        }
    ],
    "sg:phone":"+61 2 4341 2979",
    "sg:postcode":"2257",
    "sg:province":"NSW",
    "sg:tags":[
        "layer",
        "planner"
    ],
    "wof:name":"Gregory W L",
    "wof:placetype":"venue"
},
  "geometry": {"coordinates":[151.347122192,-33.5160522461],"type":"Point"}
}