{
  "type": "Feature",
  "properties": {
    "addr:full":"46 Colbee Crt Phillip ACT 2606",
    "addr:housenumber":"46",
    "addr:postcode":"2606",
    "addr:street":"Colbee Crt",
    "iso:country":"AU",
    "sg:address":"46 Colbee Crt",
    "sg:city":"Phillip",
    "sg:classifiers":[
        {
            "category":"Building & Trades",
            "subcategory":"Plumbing",
            "type":"Services"
        }
    ],
    "sg:phone":"+61 2 6285 2599",
    "sg:postcode":"2606",
    "sg:province":"ACT",
    "sg:tags":[
        "consultant"
    ],
    "wof:name":"Tennant Hydraulic Consulting Services Pty Ltd",
    "wof:placetype":"venue"
},
  "geometry": {"coordinates":[149.087356567,-35.3528709412],"type":"Point"}
}