{
  "type": "Feature",
  "properties": {
    "addr:full":"154 High St Fremantle WA 6160",
    "addr:housenumber":"154",
    "addr:postcode":"6160",
    "addr:street":"High St",
    "iso:country":"AU",
    "sg:address":"154 High St",
    "sg:city":"Fremantle",
    "sg:classifiers":[
        {
            "category":"Professional",
            "subcategory":"Computer Services",
            "type":"Services"
        }
    ],
    "sg:phone":"+61 8 9431 1999",
    "sg:postcode":"6160",
    "sg:province":"WA",
    "sg:tags":[
        "repairs",
        "upgrade",
        "equipment"
    ],
    "wof:name":"FAJ IT SERVICES",
    "wof:placetype":"venue"
},
  "geometry": {"coordinates":[115.752129,-32.052578],"type":"Point"}
}