{
  "type": "Feature",
  "properties": {
    "iso:country":"AU",
    "sg:address":"106 Elgin St",
    "sg:city":"Sale",
    "sg:classifiers":[
        {
            "category":"Building & Trades",
            "subcategory":"Construction",
            "type":"Services"
        }
    ],
    "sg:phone":"+61 3 5144 1396",
    "sg:postcode":"3850",
    "sg:province":"VIC",
    "sg:tags":[
        "renovation",
        "alterations",
        "extension",
        "contractor"
    ],
    "wof:name":"Duffell G.P.",
    "wof:placetype":"venue"
},
  "geometry": {"coordinates":[147.078292847,-38.1021957397],"type":"Point"}
}