{
  "type": "Feature",
  "properties": {
    "iso:country":"AU",
    "sg:address":"28 Bolton St",
    "sg:city":"Narrandera",
    "sg:classifiers":[
        {
            "category":"Health Services",
            "subcategory":"Optometrist",
            "type":"Services"
        }
    ],
    "sg:phone":"+61 2 6959 1401",
    "sg:postcode":"2700",
    "sg:province":"NSW",
    "wof:name":"MIA Optical Services Pty Ltd",
    "wof:placetype":"venue"
},
  "geometry": {"coordinates":[146.552825928,-34.7457695007],"type":"Point"}
}