{
  "type": "Feature",
  "properties": {
    "iso:country":"AU",
    "sg:address":"PO Box 106",
    "sg:city":"Parkes",
    "sg:classifiers":[
        {
            "category":"Building & Trades",
            "subcategory":"Pest Control",
            "type":"Services"
        }
    ],
    "sg:phone":"+61 2 6862 4558",
    "sg:postcode":"2870",
    "sg:province":"NSW",
    "wof:name":"Mid-State Pest Control",
    "wof:placetype":"venue"
},
  "geometry": {"coordinates":[148.174606,-33.136871],"type":"Point"}
}