{
  "type": "Feature",
  "properties": {
    "addr:full":"Factory 3/ 150 Cecil St Fitzroy VIC 3065",
    "addr:housenumber":"/ 150",
    "addr:postcode":"3065",
    "addr:street":"Cecil St",
    "iso:country":"AU",
    "sg:address":"Factory 3/ 150 Cecil St",
    "sg:city":"Fitzroy",
    "sg:classifiers":[
        {
            "category":"Shopping",
            "type":"Retail Goods"
        }
    ],
    "sg:phone":"+61 3 9416 0400",
    "sg:postcode":"3065",
    "sg:province":"VIC",
    "sg:tags":[
        "equipment",
        "safety",
        "accessory"
    ],
    "sg:website":"http://www.abtech.com.au",
    "wof:name":"Abtech Industrial Pty Ltd",
    "wof:placetype":"venue"
},
  "geometry": {"coordinates":[144.98316955600001,-37.7946472168],"type":"Point"}
}