{
  "type": "Feature",
  "properties": {
    "iso:country":"AU",
    "sg:address":"Factory 7-8, 181-187 Taren Point Rd",
    "sg:city":"Caringbah",
    "sg:classifiers":[
        {
            "category":"Building & Trades",
            "subcategory":"Landscaping Services",
            "type":"Services"
        }
    ],
    "sg:phone":"+61 2 9525 4811",
    "sg:postcode":"2229",
    "sg:province":"NSW",
    "sg:tags":[
        "timing",
        "equipment"
    ],
    "wof:name":"Delrico",
    "wof:placetype":"venue"
},
  "geometry": {"coordinates":[151.12005615199999,-34.0271148682],"type":"Point"}
}