{
  "type": "Feature",
  "properties": {
    "addr:full":"12 Talbot Drv Kingsley WA 6026",
    "addr:housenumber":"12",
    "addr:postcode":"6026",
    "addr:street":"Talbot Drv",
    "iso:country":"AU",
    "sg:address":"12 Talbot Drv",
    "sg:city":"Kingsley",
    "sg:classifiers":[
        {
            "category":"Travel",
            "subcategory":"Travel Agent",
            "type":"Entertainment"
        }
    ],
    "sg:phone":"+61 8 9409 9777",
    "sg:postcode":"6026",
    "sg:province":"WA",
    "sg:tags":[
        "consultant"
    ],
    "wof:name":"Wise Choice Travel Service",
    "wof:placetype":"venue"
},
  "geometry": {"coordinates":[115.80581665,-31.8095741272],"type":"Point"}
}