{
  "type": "Feature",
  "properties": {
    "addr:full":"45 Breese St Brunswick VIC 3056",
    "addr:housenumber":"45",
    "addr:postcode":"3056",
    "addr:street":"Breese St",
    "iso:country":"AU",
    "sg:address":"45 Breese St",
    "sg:city":"Brunswick",
    "sg:classifiers":[
        {
            "category":"Manufacturing",
            "subcategory":"Apparel",
            "type":"Manufacturing & Wholesale Goods"
        }
    ],
    "sg:phone":"+61 3 9386 0222",
    "sg:postcode":"3056",
    "sg:province":"VIC",
    "sg:tags":[
        "wholesaler",
        "mfrs",
        "footwear"
    ],
    "wof:name":"Paglia Shoes",
    "wof:placetype":"venue"
},
  "geometry": {"coordinates":[144.96148681599999,-37.7618331909],"type":"Point"}
}