{
  "type": "Feature",
  "properties": {
    "addr:full":"103 Tollard Drv Rokeby TAS 7019",
    "addr:housenumber":"103",
    "addr:postcode":"7019",
    "addr:street":"Tollard Drv",
    "iso:country":"AU",
    "sg:address":"103 Tollard Drv",
    "sg:city":"Rokeby",
    "sg:classifiers":[
        {
            "category":"Social Services",
            "subcategory":"Child Care",
            "type":"Services"
        }
    ],
    "sg:phone":"+61 3 6247 6543",
    "sg:postcode":"7019",
    "sg:province":"TAS",
    "wof:name":"Rokeby Child Care Centre",
    "wof:placetype":"venue"
},
  "geometry": {"coordinates":[147.43069457999999,-42.896686554],"type":"Point"}
}