{
  "type": "Feature",
  "properties": {
    "iso:country":"AU",
    "sg:address":"McDougall Building 9 Ellerslie Rd",
    "sg:city":"Battery Point",
    "sg:classifiers":[
        {
            "category":"Professional",
            "subcategory":"Accounting & Tax Preparation",
            "type":"Services"
        }
    ],
    "sg:phone":"+61 3 6224 2290",
    "sg:postcode":"7004",
    "sg:province":"TAS",
    "sg:tags":[
        "pregnancy",
        "related",
        "counselling"
    ],
    "wof:name":"Pregnancy Counselling & Support (Tasmania) Inc.",
    "wof:placetype":"venue"
},
  "geometry": {"coordinates":[147.328582764,-42.8892822266],"type":"Point"}
}