{
  "type": "Feature",
  "properties": {
    "iso:country":"AU",
    "sg:address":"PO Box 166",
    "sg:city":"Kalgoorlie",
    "sg:classifiers":[
        {
            "category":"Professional",
            "subcategory":"Art Services",
            "type":"Services"
        }
    ],
    "sg:phone":"+61 409 084 581",
    "sg:postcode":"6430",
    "sg:province":"WA",
    "sg:tags":[
        "decorator",
        "painter"
    ],
    "wof:name":"I.M. Painting & Decorating Services",
    "wof:placetype":"venue"
},
  "geometry": {"coordinates":[121.46343231199999,-30.7528495789],"type":"Point"}
}