{
  "type": "Feature",
  "properties": {
    "addr:full":"Depot 2, 1- 3 Schiller St Wagga Wagga NSW 2650",
    "addr:housenumber":"2 1 3",
    "addr:postcode":"2650",
    "addr:street":"Depot;Schiller St",
    "iso:country":"AU",
    "sg:address":"Depot 2, 1- 3 Schiller St",
    "sg:city":"Wagga Wagga",
    "sg:classifiers":[
        {
            "category":"Freight",
            "type":"Transportation"
        }
    ],
    "sg:phone":"+61 2 6926 6633",
    "sg:postcode":"2650",
    "sg:province":"NSW",
    "sg:tags":[
        "light",
        "carrier"
    ],
    "wof:name":"V & S Freight",
    "wof:placetype":"venue"
},
  "geometry": {"coordinates":[147.415939331,-35.127204895],"type":"Point"}
}