{
  "type": "Feature",
  "properties": {
    "iso:country":"AU",
    "sg:address":"170 Chapel Rd",
    "sg:city":"Bankstown",
    "sg:classifiers":[
        {
            "category":"Professional",
            "subcategory":"Accounting & Tax Preparation",
            "type":"Services"
        }
    ],
    "sg:phone":"+61 2 9709 6999",
    "sg:postcode":"2200",
    "sg:province":"NSW",
    "sg:tags":[
        "consultant",
        "taxation"
    ],
    "wof:name":"Reliable Consultancy Services Pty Ltd",
    "wof:placetype":"venue"
},
  "geometry": {"coordinates":[151.03166200000001,-33.92009],"type":"Point"}
}