{
  "type": "Feature",
  "properties": {
    "addr:full":"Shop 49 Claremont Arcade Claremont WA 6010",
    "addr:housenumber":"shop 49",
    "addr:postcode":"6010",
    "addr:street":"Claremont Arcade",
    "iso:country":"AU",
    "sg:address":"Shop 49",
    "sg:city":"Claremont Arcade Claremont",
    "sg:classifiers":[
        {
            "category":"Shopping",
            "subcategory":"Music",
            "type":"Retail Goods"
        }
    ],
    "sg:phone":"+61 8 9385 3272",
    "sg:postcode":"6010",
    "sg:province":"WA",
    "sg:tags":[
        "store"
    ],
    "wof:name":"Goodwins Records",
    "wof:placetype":"venue"
},
  "geometry": {"coordinates":[115.773887634,-31.9814968109],"type":"Point"}
}