{
  "type": "Feature",
  "properties": {
    "iso:country":"AU",
    "sg:address":"Shop 5",
    "sg:city":"Parkside Plaza Shopping Cntr Kirwan",
    "sg:classifiers":[
        {
            "category":"Food & Beverages",
            "subcategory":"Bakery",
            "type":"Retail Goods"
        }
    ],
    "sg:phone":"+61 7 4723 0111",
    "sg:postcode":"4817",
    "sg:province":"QLD",
    "sg:tags":[
        "baker"
    ],
    "wof:name":"Brumbys Bakeries",
    "wof:placetype":"venue"
},
  "geometry": {"coordinates":[146.71954299999999,-19.32214],"type":"Point"}
}