{
  "type": "Feature",
  "properties": {
    "addr:full":"9 Camelot St Tennyson QLD 4105",
    "addr:housenumber":"9",
    "addr:postcode":"4105",
    "addr:street":"Camelot St",
    "iso:country":"AU",
    "sg:address":"9 Camelot St",
    "sg:city":"Tennyson",
    "sg:classifiers":[
        {
            "category":"Building & Trades",
            "subcategory":"Pest Control",
            "type":"Services"
        }
    ],
    "sg:phone":"+61 7 3217 1610",
    "sg:postcode":"4105",
    "sg:province":"QLD",
    "sg:tags":[
        "product",
        "preservation",
        "archival"
    ],
    "wof:name":"Now&#039;n&#039;f&#039;Ever",
    "wof:placetype":"venue"
},
  "geometry": {"coordinates":[153.00038147000001,-27.5252552032],"type":"Point"}
}