{
  "type": "Feature",
  "properties": {
    "addr:full":"11 Tannery Rd Marshall VIC 3216",
    "addr:housenumber":"11",
    "addr:postcode":"3216",
    "addr:street":"Tannery Rd",
    "iso:country":"AU",
    "sg:address":"11 Tannery Rd",
    "sg:city":"Marshall",
    "sg:classifiers":[
        {
            "category":"Manufacturing",
            "subcategory":"Electronics",
            "type":"Manufacturing & Wholesale Goods"
        }
    ],
    "sg:phone":"+61 3 5243 8870",
    "sg:postcode":"3216",
    "sg:province":"VIC",
    "sg:tags":[
        "oven",
        "microwave"
    ],
    "wof:name":"Microwave Power Components Pty Ltd",
    "wof:placetype":"venue"
},
  "geometry": {"coordinates":[144.36390685999999,-38.1979026794],"type":"Point"}
}