{
  "type": "Feature",
  "properties": {
    "iso:country":"AU",
    "sg:address":"Ist Floor, 90 Broomfield St",
    "sg:city":"Cabramatta",
    "sg:classifiers":[
        {
            "category":"Professional",
            "subcategory":"Accounting & Tax Preparation",
            "type":"Services"
        }
    ],
    "sg:phone":"+61 2 9724 2300",
    "sg:postcode":"2166",
    "sg:province":"NSW",
    "sg:tags":[
        "accountant",
        "auditor"
    ],
    "wof:name":"Seang Heng",
    "wof:placetype":"venue"
},
  "geometry": {"coordinates":[150.939208984,-33.895149231],"type":"Point"}
}