{
  "type": "Feature",
  "properties": {
    "iso:country":"AU",
    "sg:address":"127 Hoare St",
    "sg:city":"Manunda",
    "sg:classifiers":[
        {
            "category":"Building & Trades",
            "subcategory":"Construction",
            "type":"Services"
        }
    ],
    "sg:phone":"+61 7 4053 2214",
    "sg:postcode":"4870",
    "sg:province":"QLD",
    "sg:tags":[
        "earth",
        "excavating",
        "moving",
        "contractor"
    ],
    "wof:name":"Allen B C",
    "wof:placetype":"venue"
},
  "geometry": {"coordinates":[145.74458313,-16.9232368469],"type":"Point"}
}