{
  "type": "Feature",
  "properties": {
    "addr:full":"224 Walker St Bundaberg QLD 4670",
    "addr:housenumber":"224",
    "addr:postcode":"4670",
    "addr:street":"Walker St",
    "iso:country":"AU",
    "sg:address":"224 Walker St",
    "sg:city":"Bundaberg",
    "sg:classifiers":[
        {
            "category":"Building & Trades",
            "subcategory":"Construction",
            "type":"Services"
        }
    ],
    "sg:phone":"+61 7 4152 3733",
    "sg:postcode":"4670",
    "sg:province":"QLD",
    "sg:tags":[
        "pool",
        "swimming"
    ],
    "wof:name":"Goodlife Pools",
    "wof:placetype":"venue"
},
  "geometry": {"coordinates":[152.33049011200001,-24.8774375916],"type":"Point"}
}