{
  "type": "Feature",
  "properties": {
    "addr:full":"20 Woorang St Milperra NSW 2214",
    "addr:housenumber":"20",
    "addr:postcode":"2214",
    "addr:street":"Woorang St",
    "iso:country":"AU",
    "sg:address":"20 Woorang St",
    "sg:city":"Milperra",
    "sg:classifiers":[
        {
            "category":"Insurance",
            "subcategory":"Hazard Insurance",
            "type":"Services"
        }
    ],
    "sg:phone":"+61 2 9774 4066",
    "sg:postcode":"2214",
    "sg:province":"NSW",
    "sg:tags":[
        "loss",
        "adjuster",
        "assessor"
    ],
    "wof:name":"Pickles Auctions Pty Ltd",
    "wof:placetype":"venue"
},
  "geometry": {"coordinates":[151.000519,-33.930996],"type":"Point"}
}