{
  "type": "Feature",
  "properties": {
    "addr:full":"2/ 250 Musgrave St North Rockhampton QLD 4701",
    "addr:housenumber":"/ 250",
    "addr:postcode":"4701",
    "addr:street":"Musgrave St North",
    "iso:country":"AU",
    "sg:address":"2/ 250 Musgrave St",
    "sg:city":"North Rockhampton",
    "sg:classifiers":[
        {
            "category":"Real Estate",
            "subcategory":"Real Estate Services",
            "type":"Services"
        }
    ],
    "sg:phone":"+61 7 4928 3900",
    "sg:postcode":"4701",
    "sg:province":"QLD",
    "sg:tags":[
        "listing"
    ],
    "wof:name":"B & P Real Estate",
    "wof:placetype":"venue"
},
  "geometry": {"coordinates":[150.523895264,-23.3571796417],"type":"Point"}
}