{
  "type": "Feature",
  "properties": {
    "addr:full":"Jackie Howe Drv Warwick QLD 4370",
    "addr:postcode":"4370",
    "addr:street":"Howe Drv",
    "iso:country":"AU",
    "sg:address":"Jackie Howe Drv",
    "sg:city":"Warwick",
    "sg:classifiers":[
        {
            "category":"Arena",
            "subcategory":"Sports Club",
            "type":"Entertainment"
        }
    ],
    "sg:phone":"+61 7 4661 4521",
    "sg:postcode":"4370",
    "sg:province":"QLD",
    "sg:tags":[
        "league",
        "rugby"
    ],
    "wof:name":"Collegians Junior Rugby League Club Inc",
    "wof:placetype":"venue"
},
  "geometry": {"coordinates":[152.03465270999999,-28.2181301117],"type":"Point"}
}