{
  "type": "Feature",
  "properties": {
    "iso:country":"AU",
    "sg:address":"7 Sylvia Ave",
    "sg:city":"Carlingford",
    "sg:classifiers":[
        {
            "category":"Health Services",
            "subcategory":"Health Practitioner",
            "type":"Services"
        }
    ],
    "sg:phone":"+61 2 9614 2161",
    "sg:postcode":"2118",
    "sg:province":"NSW",
    "sg:tags":[
        "physiotherapist"
    ],
    "wof:name":"Move Well Physiotherapy",
    "wof:placetype":"venue"
},
  "geometry": {"coordinates":[151.0390625,-33.7639732361],"type":"Point"}
}