{
  "type": "Feature",
  "properties": {
    "addr:full":"120 Penshurst St Willoughby NSW 2068",
    "addr:housenumber":"120",
    "addr:postcode":"2068",
    "addr:street":"Penshurst St",
    "iso:country":"AU",
    "sg:address":"120 Penshurst St",
    "sg:city":"Willoughby",
    "sg:classifiers":[
        {
            "category":"Retail",
            "subcategory":"Auto Repair",
            "type":"Services"
        }
    ],
    "sg:phone":"+61 2 9958 6320",
    "sg:postcode":"2068",
    "sg:province":"NSW",
    "sg:tags":[
        "repairer",
        "motor",
        "engineer"
    ],
    "wof:name":"BP Willoughby",
    "wof:placetype":"venue"
},
  "geometry": {"coordinates":[151.198532105,-33.8009223938],"type":"Point"}
}