{
  "type": "Feature",
  "properties": {
    "iso:country":"AU",
    "sg:address":"62 Main Rd",
    "sg:city":"Boolaroo",
    "sg:classifiers":[
        {
            "category":"Cinema",
            "subcategory":"Movie Theater",
            "type":"Entertainment"
        }
    ],
    "sg:phone":"+61 2 4958 5810",
    "sg:postcode":"2284",
    "sg:province":"NSW",
    "wof:name":"Lake Cinema",
    "wof:placetype":"venue"
},
  "geometry": {"coordinates":[151.622848511,-32.954208374],"type":"Point"}
}