{
  "type": "Feature",
  "properties": {
    "addr:full":"40a Church St Fitzroy North VIC 3068",
    "addr:housenumber":"40a",
    "addr:postcode":"3068",
    "addr:street":"Church St",
    "iso:country":"AU",
    "sg:address":"40a Church St",
    "sg:city":"Fitzroy North",
    "sg:classifiers":[
        {
            "category":"Building & Trades",
            "subcategory":"Landscaping Services",
            "type":"Services"
        }
    ],
    "sg:phone":"+61 414 262 108",
    "sg:postcode":"3068",
    "sg:province":"VIC",
    "sg:tags":[
        "designer",
        "landscape",
        "contractor"
    ],
    "wof:name":"Envirodesign Landscaped Gardens",
    "wof:placetype":"venue"
},
  "geometry": {"coordinates":[144.97825622600001,-37.7883872986],"type":"Point"}
}