{
  "type": "Feature",
  "properties": {
    "iso:country":"AU",
    "sg:address":"2 Antonio Crt",
    "sg:city":"Newton",
    "sg:classifiers":[
        {
            "category":"Manufacturing",
            "subcategory":"Furniture",
            "type":"Manufacturing & Wholesale Goods"
        }
    ],
    "sg:phone":"+61 8 8336 4842",
    "sg:postcode":"5074",
    "sg:province":"SA",
    "sg:tags":[
        "builder",
        "designer",
        "custom"
    ],
    "wof:name":"Reality Furniture",
    "wof:placetype":"venue"
},
  "geometry": {"coordinates":[138.68661499000001,-34.8802986145],"type":"Point"}
}