{
  "type": "Feature",
  "properties": {
    "addr:full":"PO Box 50 Inglewood SA 5133",
    "addr:postcode":"5133",
    "iso:country":"AU",
    "sg:address":"PO Box 50",
    "sg:city":"Inglewood",
    "sg:classifiers":[
        {
            "category":"Building & Trades",
            "subcategory":"Construction",
            "type":"Services"
        }
    ],
    "sg:phone":"+61 417 869 711",
    "sg:postcode":"5133",
    "sg:province":"SA",
    "sg:tags":[
        "earth",
        "excavating",
        "moving",
        "contractor"
    ],
    "wof:name":"SAR Bobcat & Tipper Hire",
    "wof:placetype":"venue"
},
  "geometry": {"coordinates":[138.791183472,-34.8022003174],"type":"Point"}
}