{
  "type": "Feature",
  "properties": {
    "iso:country":"AU",
    "sg:address":"Unit 6/ 75-85 Elm Park Drv",
    "sg:city":"Hoppers Crossing",
    "sg:classifiers":[
        {
            "category":"Shopping",
            "subcategory":"Party Supplies",
            "type":"Retail Goods"
        }
    ],
    "sg:phone":"+61 3 8742 1283",
    "sg:postcode":"3029",
    "sg:province":"VIC",
    "sg:tags":[
        "children's"
    ],
    "wof:name":"Oz Reptiles",
    "wof:placetype":"venue"
},
  "geometry": {"coordinates":[144.720306,-37.870167],"type":"Point"}
}