{
  "type": "Feature",
  "properties": {
    "addr:full":"PO Box 126 Emu Park QLD 4702",
    "addr:postcode":"4702",
    "iso:country":"AU",
    "sg:address":"PO Box 126",
    "sg:city":"Emu Park",
    "sg:classifiers":[
        {
            "category":"Real Estate",
            "subcategory":"Developer",
            "type":"Services"
        }
    ],
    "sg:phone":"+61 7 4938 8055",
    "sg:postcode":"4702",
    "sg:province":"QLD",
    "sg:tags":[
        "development"
    ],
    "wof:name":"Rescom Group",
    "wof:placetype":"venue"
},
  "geometry": {"coordinates":[150.56675720199999,-23.3882160187],"type":"Point"}
}