{
  "type": "Feature",
  "properties": {
    "iso:country":"AU",
    "sg:address":"Wark St",
    "sg:city":"Timboon",
    "sg:classifiers":[
        {
            "category":"Social Services",
            "subcategory":"Child Care",
            "type":"Services"
        }
    ],
    "sg:phone":"+61 3 5598 3410",
    "sg:postcode":"3268",
    "sg:province":"VIC",
    "sg:tags":[
        "support",
        "health"
    ],
    "wof:name":"Maternal & Child Health Centres",
    "wof:placetype":"venue"
},
  "geometry": {"coordinates":[142.9765625,-38.4856262207],"type":"Point"}
}