{
  "type": "Feature",
  "properties": {
    "addr:full":"258 Blackburn Rd Syndal VIC 3149",
    "addr:housenumber":"258",
    "addr:postcode":"3149",
    "addr:street":"Blackburn Rd",
    "iso:country":"AU",
    "sg:address":"258 Blackburn Rd",
    "sg:city":"Syndal",
    "sg:classifiers":[
        {
            "category":"Shopping",
            "subcategory":"Clothing, Apparel, & Fashions",
            "type":"Retail Goods"
        }
    ],
    "sg:phone":"+61 3 9803 8989",
    "sg:postcode":"3149",
    "sg:province":"VIC",
    "sg:tags":[
        "recycled",
        "clothing"
    ],
    "wof:name":"Second Time Around",
    "wof:placetype":"venue"
},
  "geometry": {"coordinates":[145.14805602999999,-37.8748054504],"type":"Point"}
}