{
  "type": "Feature",
  "properties": {
    "addr:full":"3/ 54 Tenth Ave Budgewoi NSW 2262",
    "addr:housenumber":"/ 54",
    "addr:postcode":"2262",
    "addr:street":"Tenth Ave",
    "iso:country":"AU",
    "sg:address":"3/ 54 Tenth Ave",
    "sg:city":"Budgewoi",
    "sg:classifiers":[
        {
            "category":"Personal",
            "subcategory":"Massage",
            "type":"Services"
        }
    ],
    "sg:phone":"+61 2 4390 0299",
    "sg:postcode":"2262",
    "sg:province":"NSW",
    "sg:tags":[
        "therapy"
    ],
    "wof:name":"Budgewoi Physiotherapy Centre",
    "wof:placetype":"venue"
},
  "geometry": {"coordinates":[151.55592300000001,-33.233826],"type":"Point"}
}