{
  "type": "Feature",
  "properties": {
    "addr:full":"Shp 2 / 168 Scarborough St Southport QLD 4215",
    "addr:housenumber":"/ 168",
    "addr:postcode":"4215",
    "addr:street":"Scarborough St",
    "iso:country":"AU",
    "sg:address":"Shp 2 / 168 Scarborough St",
    "sg:city":"Southport",
    "sg:classifiers":[
        {
            "category":"Shopping",
            "subcategory":"Bicycles & Sporting Goods",
            "type":"Retail Goods"
        }
    ],
    "sg:phone":"+61 7 5591 1983",
    "sg:postcode":"4215",
    "sg:province":"QLD",
    "sg:tags":[
        "dance",
        "accessory",
        "wear",
        "supply"
    ],
    "wof:name":"DDs Dance Shoes & Clothing",
    "wof:placetype":"venue"
},
  "geometry": {"coordinates":[153.41046142600001,-27.962469101],"type":"Point"}
}