{
  "type": "Feature",
  "properties": {
    "iso:country":"AU",
    "sg:address":"31 Lucas St",
    "sg:city":"Reynella",
    "sg:classifiers":[
        {
            "category":"Professional",
            "subcategory":"Computer Services",
            "type":"Services"
        }
    ],
    "sg:phone":"+61 8 8381 6420",
    "sg:postcode":"5161",
    "sg:province":"SA",
    "sg:tags":[
        "technical",
        "support"
    ],
    "wof:name":"Creative Information Technology Pty Ltd",
    "wof:placetype":"venue"
},
  "geometry": {"coordinates":[138.53099060100001,-35.096446991],"type":"Point"}
}