{
  "type": "Feature",
  "properties": {
    "addr:full":"Lvl 26/ 35 Collin St Melbourne VIC 3000",
    "addr:housenumber":"/ 35",
    "addr:postcode":"3000",
    "addr:street":"Collin St",
    "iso:country":"AU",
    "sg:address":"Lvl 26/ 35 Collin St",
    "sg:city":"Melbourne",
    "sg:classifiers":[
        {
            "category":"Professional",
            "subcategory":"Management & Consulting",
            "type":"Services"
        }
    ],
    "sg:phone":"+61 3 9654 8323",
    "sg:postcode":"3000",
    "sg:province":"VIC",
    "sg:tags":[
        "consultant"
    ],
    "wof:name":"International Trade Strategies Pty Ltd",
    "wof:placetype":"venue"
},
  "geometry": {"coordinates":[144.97280883799999,-37.8137741089],"type":"Point"}
}