{
  "type": "Feature",
  "properties": {
    "iso:country":"AU",
    "sg:address":"780- 786 Ingham Rd",
    "sg:city":"Bohle",
    "sg:classifiers":[
        {
            "category":"Retail",
            "subcategory":"Auto Repair",
            "type":"Services"
        }
    ],
    "sg:phone":"+61 7 4774 5452",
    "sg:postcode":"4818",
    "sg:province":"QLD",
    "sg:tags":[
        "bus",
        "truck"
    ],
    "wof:name":"Mack Trucks",
    "wof:placetype":"venue"
},
  "geometry": {"coordinates":[146.725388,-19.260853],"type":"Point"}
}