{
  "type": "Feature",
  "properties": {
    "addr:full":"1424 New Cleveland Rd Capalaba West QLD 4157",
    "addr:housenumber":"1424",
    "addr:postcode":"4157",
    "addr:street":"New Cleveland Rd",
    "iso:country":"AU",
    "sg:address":"1424 New Cleveland Rd",
    "sg:city":"Capalaba West",
    "sg:classifiers":[
        {
            "category":"Home & Garden",
            "subcategory":"Building Materials",
            "type":"Retail Goods"
        }
    ],
    "sg:phone":"+61 7 3245 2288",
    "sg:postcode":"4157",
    "sg:province":"QLD",
    "sg:tags":[
        "supply"
    ],
    "wof:name":"TRADEWARE",
    "wof:placetype":"venue"
},
  "geometry": {"coordinates":[153.17950439399999,-27.5119667053],"type":"Point"}
}