{
  "type": "Feature",
  "properties": {
    "addr:full":"17 Hesse St Waroona WA 6215",
    "addr:housenumber":"17",
    "addr:postcode":"6215",
    "addr:street":"Hesse St",
    "iso:country":"AU",
    "sg:address":"17 Hesse St",
    "sg:city":"Waroona",
    "sg:classifiers":[
        {
            "category":"Building & Trades",
            "subcategory":"Construction",
            "type":"Services"
        }
    ],
    "sg:phone":"+61 8 9733 1967",
    "sg:postcode":"6215",
    "sg:province":"WA",
    "sg:tags":[
        "joinery"
    ],
    "wof:name":"A & K Joinery",
    "wof:placetype":"venue"
},
  "geometry": {"coordinates":[115.92218800000001,-32.839516],"type":"Point"}
}