{
  "type": "Feature",
  "properties": {
    "addr:full":"Lvl 2/ 34 Collin St West Perth WA 6005",
    "addr:housenumber":"/ 34",
    "addr:postcode":"6005",
    "addr:street":"Collin St",
    "iso:country":"AU",
    "sg:address":"Lvl 2/ 34 Collin St",
    "sg:city":"West Perth",
    "sg:classifiers":[
        {
            "category":"Manufacturing",
            "subcategory":"Glass & Minerals",
            "type":"Manufacturing & Wholesale Goods"
        }
    ],
    "sg:phone":"+61 8 9264 7000",
    "sg:postcode":"6005",
    "sg:province":"WA",
    "sg:tags":[
        "exploration"
    ],
    "wof:name":"Minemakers Ltd",
    "wof:placetype":"venue"
},
  "geometry": {"coordinates":[115.839988709,-31.9501857758],"type":"Point"}
}