{
  "type": "Feature",
  "properties": {
    "addr:full":"Boathouse Drv Melbourne City Mail Rm VIC 8001",
    "addr:postcode":"8001",
    "addr:street":"Boathouse Drv",
    "iso:country":"AU",
    "sg:address":"Boathouse Drv",
    "sg:city":"Melbourne City Mail Rm",
    "sg:classifiers":[
        {
            "category":"Sports & Exercise",
            "subcategory":"Gym",
            "type":"Entertainment"
        }
    ],
    "sg:phone":"+61 3 9663 0495",
    "sg:postcode":"8001",
    "sg:province":"VIC",
    "sg:tags":[
        "health",
        "fitness"
    ],
    "wof:name":"YMCA Skatepark",
    "wof:placetype":"venue"
},
  "geometry": {"coordinates":[144.963165283,-37.814250946],"type":"Point"}
}