{
  "type": "Feature",
  "properties": {
    "addr:full":"125 Orchardleigh St Yennora NSW 2161",
    "addr:housenumber":"125",
    "addr:postcode":"2161",
    "addr:street":"Orchardleigh St",
    "iso:country":"AU",
    "sg:address":"125 Orchardleigh St",
    "sg:city":"Yennora",
    "sg:classifiers":[
        {
            "category":"Retail",
            "subcategory":"Driving School",
            "type":"Services"
        }
    ],
    "sg:phone":"+61 405 228 431",
    "sg:postcode":"2161",
    "sg:province":"NSW",
    "sg:tags":[
        "operator",
        "plant",
        "training"
    ],
    "wof:name":"F.H.V. Driver Training & Licencing",
    "wof:placetype":"venue"
},
  "geometry": {"coordinates":[150.980743408,-33.8660545349],"type":"Point"}
}