{
  "type": "Feature",
  "properties": {
    "addr:full":"16 Banksia Drv Byron Bay NSW 2481",
    "addr:housenumber":"16",
    "addr:postcode":"2481",
    "addr:street":"Banksia Drv",
    "iso:country":"AU",
    "sg:address":"16 Banksia Drv",
    "sg:city":"Byron Bay",
    "sg:classifiers":[
        {
            "category":"Retail",
            "subcategory":"Auto Repair",
            "type":"Services"
        }
    ],
    "sg:phone":"+61 2 6685 6635",
    "sg:postcode":"2481",
    "sg:province":"NSW",
    "sg:tags":[
        "electrical"
    ],
    "wof:name":"Byron Auto Electrical",
    "wof:placetype":"venue"
},
  "geometry": {"coordinates":[153.585845947,-28.6375904083],"type":"Point"}
}