{
  "type": "Feature",
  "properties": {
    "addr:full":"53 Rundle St Kent Town SA 5067",
    "addr:housenumber":"53",
    "addr:postcode":"5067",
    "addr:street":"Rundle St",
    "iso:country":"AU",
    "sg:address":"53 Rundle St",
    "sg:city":"Kent Town",
    "sg:classifiers":[
        {
            "category":"Social Services",
            "subcategory":"Job Training",
            "type":"Services"
        }
    ],
    "sg:phone":"+61 8 8130 0555",
    "sg:postcode":"5067",
    "sg:province":"SA",
    "sg:tags":[
        "hire",
        "computer",
        "leasing"
    ],
    "wof:name":"Business 2000",
    "wof:placetype":"venue"
},
  "geometry": {"coordinates":[138.617553711,-34.9207725525],"type":"Point"}
}