{
  "type": "Feature",
  "properties": {
    "addr:full":"Unit 1/ 112 Jardine St Fairy Meadow NSW 2519",
    "addr:housenumber":"/ 112",
    "addr:postcode":"2519",
    "addr:street":"Jardine St",
    "iso:country":"AU",
    "sg:address":"Unit 1/ 112 Jardine St",
    "sg:city":"Fairy Meadow",
    "sg:classifiers":[
        {
            "category":"Retail",
            "subcategory":"Auto Repair",
            "type":"Services"
        }
    ],
    "sg:phone":"+61 2 4284 8188",
    "sg:postcode":"2519",
    "sg:province":"NSW",
    "sg:tags":[
        "clutch",
        "brake"
    ],
    "wof:name":"Reliance Brakes",
    "wof:placetype":"venue"
},
  "geometry": {"coordinates":[150.89117400000001,-34.388096],"type":"Point"}
}