{
  "type": "Feature",
  "properties": {
    "iso:country":"AU",
    "sg:address":"168 Piper St",
    "sg:city":"Bathurst",
    "sg:classifiers":[
        {
            "category":"Building & Trades",
            "subcategory":"Landscaping Services",
            "type":"Services"
        }
    ],
    "sg:phone":"+61 2 6334 2255",
    "sg:postcode":"2795",
    "sg:province":"NSW",
    "sg:tags":[
        "inspection"
    ],
    "wof:name":"Acacia Pre Purchase Inspections Pty Ltd",
    "wof:placetype":"venue"
},
  "geometry": {"coordinates":[149.57369995100001,-33.4193191528],"type":"Point"}
}