{
  "type": "Feature",
  "properties": {
    "iso:country":"AU",
    "sg:address":"139- 145 Charlotte St",
    "sg:city":"Brisbane",
    "sg:classifiers":[
        {
            "category":"Sports & Exercise",
            "subcategory":"Gym",
            "type":"Entertainment"
        }
    ],
    "sg:phone":"+61 7 3256 0818",
    "sg:postcode":"4000",
    "sg:province":"QLD",
    "sg:tags":[
        "personal",
        "trainer",
        "fitness"
    ],
    "wof:name":"Always Be Fit",
    "wof:placetype":"venue"
},
  "geometry": {"coordinates":[153.027786255,-27.4705276489],"type":"Point"}
}