{
  "type": "Feature",
  "properties": {
    "addr:full":"Kalingra Rd Footscray West VIC 3012",
    "addr:postcode":"3012",
    "addr:street":"Kalingra Rd",
    "iso:country":"AU",
    "sg:address":"Kalingra Rd",
    "sg:city":"Footscray West",
    "sg:classifiers":[
        {
            "category":"Shopping",
            "subcategory":"Discount & Variety Stores",
            "type":"Retail Goods"
        }
    ],
    "sg:phone":"+61 3 9314 6397",
    "sg:postcode":"3012",
    "sg:province":"VIC",
    "sg:tags":[
        "dangerous",
        "storage"
    ],
    "wof:name":"Dove Storage",
    "wof:placetype":"venue"
},
  "geometry": {"coordinates":[144.85078430199999,-37.807964325],"type":"Point"}
}