{
  "type": "Feature",
  "properties": {
    "addr:full":"40 Dacre St Mitchell ACT 2911",
    "addr:housenumber":"40",
    "addr:postcode":"2911",
    "addr:street":"Dacre St",
    "iso:country":"AU",
    "sg:address":"40 Dacre St",
    "sg:city":"Mitchell",
    "sg:classifiers":[
        {
            "category":"Home & Garden",
            "subcategory":"Garden Supply",
            "type":"Retail Goods"
        }
    ],
    "sg:phone":"+61 2 6242 7033",
    "sg:postcode":"2911",
    "sg:province":"ACT",
    "sg:tags":[
        "equipment"
    ],
    "wof:name":"Bink Cement Products",
    "wof:placetype":"venue"
},
  "geometry": {"coordinates":[149.13409423799999,-35.2102966309],"type":"Point"}
}