{
  "type": "Feature",
  "properties": {
    "addr:full":"20 Simpson St Auburn NSW 2144",
    "addr:housenumber":"20",
    "addr:postcode":"2144",
    "addr:street":"Simpson St",
    "iso:country":"AU",
    "sg:address":"20 Simpson St",
    "sg:city":"Auburn",
    "sg:classifiers":[
        {
            "category":"Utilities",
            "subcategory":"Electric",
            "type":"Services"
        }
    ],
    "sg:phone":"+61 400 608 010",
    "sg:postcode":"2144",
    "sg:province":"NSW",
    "sg:tags":[
        "electrical",
        "contractor"
    ],
    "wof:name":"Emek Electrical Services",
    "wof:placetype":"venue"
},
  "geometry": {"coordinates":[151.038406372,-33.8460731506],"type":"Point"}
}