{
  "type": "Feature",
  "properties": {
    "iso:country":"AU",
    "sg:address":"39 Queen St",
    "sg:city":"Grafton",
    "sg:classifiers":[
        {
            "category":"Health Services",
            "subcategory":"Medical Lab",
            "type":"Services"
        }
    ],
    "sg:phone":"+61 2 6642 7420",
    "sg:postcode":"2460",
    "sg:province":"NSW",
    "sg:tags":[
        "laboratory",
        "dental"
    ],
    "wof:name":"Reliance Dental Laboratory",
    "wof:placetype":"venue"
},
  "geometry": {"coordinates":[152.932037353,-29.6882972717],"type":"Point"}
}