{
  "type": "Feature",
  "properties": {
    "addr:full":"46- 52 Townsville St Fyshwick ACT 2609",
    "addr:housenumber":"52",
    "addr:postcode":"2609",
    "addr:street":"Townsville St",
    "iso:country":"AU",
    "sg:address":"46- 52 Townsville St",
    "sg:city":"Fyshwick",
    "sg:classifiers":[
        {
            "category":"Home & Garden",
            "subcategory":"Carpets & Floor Coverings",
            "type":"Retail Goods"
        }
    ],
    "sg:phone":"+61 2 6280 6467",
    "sg:postcode":"2609",
    "sg:province":"ACT",
    "sg:tags":[
        "wood"
    ],
    "sg:website":"http://www.monarotimber.com.au",
    "wof:name":"Monaro Timber",
    "wof:placetype":"venue"
},
  "geometry": {"coordinates":[149.18321227999999,-35.3296432495],"type":"Point"}
}