{
  "type": "Feature",
  "properties": {
    "iso:country":"AU",
    "sg:address":"161 Grey St (Mantra Hotel)",
    "sg:city":"South Bank",
    "sg:classifiers":[
        {
            "category":"Personal",
            "subcategory":"Day Spa",
            "type":"Services"
        }
    ],
    "sg:phone":"+61 7 3846 5501",
    "sg:postcode":"4101",
    "sg:province":"QLD",
    "wof:name":"Glow Retreat",
    "wof:placetype":"venue"
},
  "geometry": {"coordinates":[153.02070617699999,-27.4777145386],"type":"Point"}
}