{
  "type": "Feature",
  "properties": {
    "addr:full":"2120 Mudwalls Rd Colebrook TAS 7027",
    "addr:housenumber":"2120",
    "addr:postcode":"7027",
    "addr:street":"Mudwalls Rd",
    "iso:country":"AU",
    "sg:address":"2120 Mudwalls Rd",
    "sg:city":"Colebrook",
    "sg:classifiers":[
        {
            "category":"Travel",
            "subcategory":"Hotels & Motels",
            "type":"Entertainment"
        }
    ],
    "sg:phone":"+61 3 6259 7164",
    "sg:postcode":"7027",
    "sg:province":"TAS",
    "sg:tags":[
        "pub"
    ],
    "wof:name":"Colebrook Tavern",
    "wof:placetype":"venue"
},
  "geometry": {"coordinates":[147.35870361299999,-42.5260658264],"type":"Point"}
}