{
  "type": "Feature",
  "properties": {
    "addr:full":"25 Gloucester St Highgate Hill QLD 4101",
    "addr:housenumber":"25",
    "addr:postcode":"4101",
    "addr:street":"Gloucester St",
    "iso:country":"AU",
    "sg:address":"25 Gloucester St",
    "sg:city":"Highgate Hill",
    "sg:classifiers":[
        {
            "category":"Health Services",
            "subcategory":"Health Practitioner",
            "type":"Services"
        }
    ],
    "sg:phone":"+61 7 3255 3555",
    "sg:postcode":"4101",
    "sg:province":"QLD",
    "sg:tags":[
        "osteopath"
    ],
    "wof:name":"Banks Melinda Dr.",
    "wof:placetype":"venue"
},
  "geometry": {"coordinates":[153.02067565900001,-27.4880638123],"type":"Point"}
}