{
  "type": "Feature",
  "properties": {
    "addr:full":"2 Oxford St Shoreham VIC 3916",
    "addr:housenumber":"2",
    "addr:postcode":"3916",
    "addr:street":"Oxford St",
    "iso:country":"AU",
    "sg:address":"2 Oxford St",
    "sg:city":"Shoreham",
    "sg:classifiers":[
        {
            "category":"Food & Beverages",
            "subcategory":"Fruits & Vegetables",
            "type":"Retail Goods"
        }
    ],
    "sg:phone":"+61 3 5989 8001",
    "sg:postcode":"3916",
    "sg:province":"VIC",
    "sg:tags":[
        "consultant",
        "catering"
    ],
    "wof:name":"Louise Lechte Catering & Consultants",
    "wof:placetype":"venue"
},
  "geometry": {"coordinates":[145.04351806599999,-38.4284133911],"type":"Point"}
}