{
  "type": "Feature",
  "properties": {
    "iso:country":"AU",
    "sg:address":"4 Ferrier Rd",
    "sg:city":"Narangba",
    "sg:classifiers":[
        {
            "category":"Shopping",
            "subcategory":"Stationery & Office Supplies",
            "type":"Retail Goods"
        }
    ],
    "sg:phone":"+61 7 3888 0166",
    "sg:postcode":"4504",
    "sg:province":"QLD",
    "sg:tags":[
        "packaging",
        "material"
    ],
    "sg:website":"http://www.shilohplastics.com.au",
    "wof:name":"Shiloh Plastics Pty Ltd",
    "wof:placetype":"venue"
},
  "geometry": {"coordinates":[152.976760864,-27.2073764801],"type":"Point"}
}