{
  "type": "Feature",
  "properties": {
    "addr:full":"Suite 5, Lvl 11 118 Queen Street Melbourne 3000",
    "addr:housenumber":"118",
    "addr:street":"Queen Street",
    "iso:country":"AU",
    "sg:address":"Suite 5, Lvl 11 118 Queen Street",
    "sg:city":"Melbourne",
    "sg:classifiers":[
        {
            "category":"Professional",
            "subcategory":"Computer Services",
            "type":"Services"
        }
    ],
    "sg:postcode":"3000",
    "sg:tags":[
        "bugmenot",
        "retailmenot"
    ],
    "sg:website":"http://www.statelesssystems.com/",
    "wof:name":"Stateless Systems",
    "wof:placetype":"venue"
},
  "geometry": {"coordinates":[145.08820499999999,-38.234925],"type":"Point"}
}