{
  "type": "Feature",
  "properties": {
    "addr:full":"23 Guilford Rd Riverside TAS 7250",
    "addr:housenumber":"23",
    "addr:postcode":"7250",
    "addr:street":"Guilford Rd",
    "iso:country":"AU",
    "sg:address":"23 Guilford Rd",
    "sg:city":"Riverside",
    "sg:classifiers":[
        {
            "category":"Building & Trades",
            "subcategory":"Plumbing",
            "type":"Services"
        }
    ],
    "sg:phone":"+61 418 131 175",
    "sg:postcode":"7250",
    "sg:province":"TAS",
    "sg:tags":[
        "plumber",
        "gasfitters"
    ],
    "wof:name":"Curwen Perry",
    "wof:placetype":"venue"
},
  "geometry": {"coordinates":[147.09910583499999,-41.4243545532],"type":"Point"}
}