{
  "type": "Feature",
  "properties": {
    "addr:full":"Suite 6, 409 Bong Bong St Bowral NSW 2576",
    "addr:housenumber":"409",
    "addr:postcode":"2576",
    "addr:street":"Bong Bong St",
    "iso:country":"AU",
    "sg:address":"Suite 6, 409 Bong Bong St",
    "sg:city":"Bowral",
    "sg:classifiers":[
        {
            "category":"Banks & Credit Unions",
            "subcategory":"Financial Services",
            "type":"Services"
        }
    ],
    "sg:phone":"+61 2 4861 7888",
    "sg:postcode":"2576",
    "sg:province":"NSW",
    "sg:tags":[
        "planning"
    ],
    "wof:name":"Matrix Planning Solutions Ltd",
    "wof:placetype":"venue"
},
  "geometry": {"coordinates":[150.41699218799999,-34.4822883606],"type":"Point"}
}