{
  "type": "Feature",
  "properties": {
    "addr:full":"421-423 Hammond Rd Dandenong South VIC 3164",
    "addr:housenumber":"421-423",
    "addr:postcode":"3164",
    "addr:street":"Hammond Rd",
    "iso:country":"AU",
    "sg:address":"421-423 Hammond Rd",
    "sg:city":"Dandenong South",
    "sg:classifiers":[
        {
            "category":"Commercial Area",
            "type":"Public Place"
        }
    ],
    "sg:phone":"+61 3 9792 9011",
    "sg:postcode":"3164",
    "sg:province":"VIC",
    "sg:tags":[
        "heavy",
        "carrier"
    ],
    "wof:name":"D & B Heavy Haulage Pty ltd",
    "wof:placetype":"venue"
},
  "geometry": {"coordinates":[145.20390319800001,-38.0235443115],"type":"Point"}
}