{
  "type": "Feature",
  "properties": {
    "iso:country":"AU",
    "sg:address":"40 Parry Ave",
    "sg:city":"Beverly Hills",
    "sg:classifiers":[
        {
            "category":"Retail",
            "subcategory":"Repair Shop",
            "type":"Services"
        }
    ],
    "sg:phone":"+61 408 979 819",
    "sg:postcode":"2209",
    "sg:province":"NSW",
    "sg:tags":[
        "repairing",
        "piano",
        "tuning"
    ],
    "wof:name":"Andi Hanna Piano Tuning & Service",
    "wof:placetype":"venue"
},
  "geometry": {"coordinates":[151.073563,-33.945049],"type":"Point"}
}