{
  "type": "Feature",
  "properties": {
    "addr:full":"2 Golden Grove Drv Blackmans Bay TAS 7052",
    "addr:housenumber":"2",
    "addr:postcode":"7052",
    "addr:street":"Golden Grove Drv",
    "iso:country":"AU",
    "sg:address":"2 Golden Grove Drv",
    "sg:city":"Blackmans Bay",
    "sg:classifiers":[
        {
            "category":"Professional",
            "subcategory":"Accounting & Tax Preparation",
            "type":"Services"
        }
    ],
    "sg:phone":"+61 438 131 249",
    "sg:postcode":"7052",
    "sg:province":"TAS",
    "sg:tags":[
        "accountant",
        "auditor"
    ],
    "wof:name":"Rowe P T",
    "wof:placetype":"venue"
},
  "geometry": {"coordinates":[147.30969200000001,-42.999657],"type":"Point"}
}