{
  "type": "Feature",
  "properties": {
    "iso:country":"AU",
    "sg:address":"Henry St",
    "sg:city":"Darke Peake",
    "sg:classifiers":[
        {
            "category":"Retail",
            "subcategory":"Auto Repair",
            "type":"Services"
        }
    ],
    "sg:phone":"+61 8 8620 7142",
    "sg:postcode":"5642",
    "sg:province":"SA",
    "sg:tags":[
        "repairer",
        "motor",
        "engineer"
    ],
    "wof:name":"Parkeyre Mechanical Repairs",
    "wof:placetype":"venue"
},
  "geometry": {"coordinates":[136.20054626500001,-33.4697647095],"type":"Point"}
}