{
  "type": "Feature",
  "properties": {
    "addr:full":"Unit 12, 9 Catamaran Rd Ourimbah NSW 2258",
    "addr:housenumber":"9",
    "addr:postcode":"2258",
    "addr:street":"Catamaran Rd",
    "iso:country":"AU",
    "sg:address":"Unit 12, 9 Catamaran Rd",
    "sg:city":"Ourimbah",
    "sg:classifiers":[
        {
            "category":"Home & Garden",
            "subcategory":"Building Materials",
            "type":"Retail Goods"
        }
    ],
    "sg:phone":"+61 2 4388 4545",
    "sg:postcode":"2258",
    "sg:province":"NSW",
    "sg:tags":[
        "laminate",
        "laminated",
        "panel"
    ],
    "wof:name":"Brian White",
    "wof:placetype":"venue"
},
  "geometry": {"coordinates":[151.404388428,-33.3345870972],"type":"Point"}
}