{
  "type": "Feature",
  "properties": {
    "iso:country":"AU",
    "sg:address":"39 Gunnedah Rd",
    "sg:city":"Tamworth",
    "sg:classifiers":[
        {
            "category":"Home & Garden",
            "subcategory":"Building Materials",
            "type":"Retail Goods"
        }
    ],
    "sg:phone":"+61 2 6762 0822",
    "sg:postcode":"2340",
    "sg:province":"NSW",
    "sg:tags":[
        "fitting",
        "door"
    ],
    "wof:name":"Doors Plus",
    "wof:placetype":"venue"
},
  "geometry": {"coordinates":[150.904754639,-31.0974216461],"type":"Point"}
}