{
  "type": "Feature",
  "properties": {
    "iso:country":"AU",
    "sg:address":"8b Lampton Ave",
    "sg:city":"Derwent Park",
    "sg:classifiers":[
        {
            "category":"Retail",
            "subcategory":"Auto Repair",
            "type":"Services"
        }
    ],
    "sg:phone":"+61 1300 551 600",
    "sg:postcode":"7009",
    "sg:province":"TAS",
    "sg:tags":[
        "bus",
        "truck"
    ],
    "wof:name":"Hazell Bros. Fleet Maintenance",
    "wof:placetype":"venue"
},
  "geometry": {"coordinates":[147.290771484,-42.8352279663],"type":"Point"}
}