{
  "type": "Feature",
  "properties": {
    "addr:full":"1- 3 Windebanks Rd Aberfoyle Park SA 5159",
    "addr:housenumber":"3",
    "addr:postcode":"5159",
    "addr:street":"Windebanks Rd",
    "iso:country":"AU",
    "sg:address":"1- 3 Windebanks Rd",
    "sg:city":"Aberfoyle Park",
    "sg:classifiers":[
        {
            "category":"Social Services",
            "subcategory":"Child Care",
            "type":"Services"
        }
    ],
    "sg:phone":"+61 8 8387 4511",
    "sg:postcode":"5159",
    "sg:province":"SA",
    "sg:website":"http://www.childcare.com.au",
    "wof:name":"ABC Aberfoyle Park",
    "wof:placetype":"venue"
},
  "geometry": {"coordinates":[138.60414123499999,-35.0829734802],"type":"Point"}
}