{
  "type": "Feature",
  "properties": {
    "addr:full":"32 Pentex St Salisbury QLD 4107",
    "addr:housenumber":"32",
    "addr:postcode":"4107",
    "addr:street":"Pentex St",
    "iso:country":"AU",
    "sg:address":"32 Pentex St",
    "sg:city":"Salisbury",
    "sg:classifiers":[
        {
            "category":"Sports & Exercise",
            "subcategory":"Ski Slope",
            "type":"Entertainment"
        }
    ],
    "sg:phone":"+61 7 3277 2900",
    "sg:postcode":"4107",
    "sg:province":"QLD",
    "sg:tags":[
        "equipment",
        "hire",
        "retail",
        "snow"
    ],
    "wof:name":"Snow Makers Australia",
    "wof:placetype":"venue"
},
  "geometry": {"coordinates":[153.03323364299999,-27.5441589355],"type":"Point"}
}