{
  "type": "Feature",
  "properties": {
    "addr:full":"23 Gordon St Balwyn VIC 3103",
    "addr:housenumber":"23",
    "addr:postcode":"3103",
    "addr:street":"Gordon St",
    "iso:country":"AU",
    "sg:address":"23 Gordon St",
    "sg:city":"Balwyn",
    "sg:classifiers":[
        {
            "category":"Education",
            "subcategory":"Music School",
            "type":"Public Place"
        }
    ],
    "sg:phone":"+61 3 9817 4665",
    "sg:postcode":"3103",
    "sg:province":"VIC",
    "sg:tags":[
        "teacher"
    ],
    "wof:name":"Roberts Music School",
    "wof:placetype":"venue"
},
  "geometry": {"coordinates":[145.06431579599999,-37.8070602417],"type":"Point"}
}