{
  "type": "Feature",
  "properties": {
    "addr:full":"630 Port Rd Beverley SA 5009",
    "addr:housenumber":"630",
    "addr:postcode":"5009",
    "addr:street":"Port Rd",
    "iso:country":"AU",
    "sg:address":"630 Port Rd",
    "sg:city":"Beverley",
    "sg:classifiers":[
        {
            "category":"Wholesale",
            "subcategory":"Apparel",
            "type":"Manufacturing & Wholesale Goods"
        }
    ],
    "sg:phone":"+61 8 8445 7077",
    "sg:postcode":"5009",
    "sg:province":"SA",
    "sg:tags":[
        "wholesaler",
        "mfrs",
        "sportswear",
        "women's"
    ],
    "wof:name":"Greatrex Sporting Goods",
    "wof:placetype":"venue"
},
  "geometry": {"coordinates":[138.550384522,-34.8912734985],"type":"Point"}
}