{
  "type": "Feature",
  "properties": {
    "addr:full":"43 Korong Rd Heidelberg West VIC 3081",
    "addr:housenumber":"43",
    "addr:postcode":"3081",
    "addr:street":"Korong Rd",
    "iso:country":"AU",
    "sg:address":"43 Korong Rd",
    "sg:city":"Heidelberg West",
    "sg:classifiers":[
        {
            "category":"Retail",
            "subcategory":"Auto Repair",
            "type":"Services"
        }
    ],
    "sg:phone":"+61 3 9459 5520",
    "sg:postcode":"3081",
    "sg:province":"VIC",
    "sg:tags":[
        "beater",
        "painter",
        "panel"
    ],
    "wof:name":"A Grade Plus",
    "wof:placetype":"venue"
},
  "geometry": {"coordinates":[145.04698181099999,-37.7321243286],"type":"Point"}
}