{
  "type": "Feature",
  "properties": {
    "addr:full":"15 Eastwood St Babinda QLD 4861",
    "addr:housenumber":"15",
    "addr:postcode":"4861",
    "addr:street":"Eastwood St",
    "iso:country":"AU",
    "sg:address":"15 Eastwood St",
    "sg:city":"Babinda",
    "sg:classifiers":[
        {
            "category":"Retail",
            "subcategory":"Auto Repair",
            "type":"Services"
        }
    ],
    "sg:phone":"+61 7 4067 1300",
    "sg:postcode":"4861",
    "sg:province":"QLD",
    "sg:tags":[
        "electrical"
    ],
    "wof:name":"Balbi's Auto Electrical & Airconditioning",
    "wof:placetype":"venue"
},
  "geometry": {"coordinates":[145.923629761,-17.3454723358],"type":"Point"}
}