{
  "type": "Feature",
  "properties": {
    "addr:full":"Robina Parkway Medical Centre+Suite 7/100 Cheltenh Robina QLD 4226",
    "addr:housenumber":"7 / 100",
    "addr:postcode":"4226",
    "addr:street":"Robina",
    "iso:country":"AU",
    "sg:address":"Robina Parkway Medical Centre+Suite 7/100 Cheltenh",
    "sg:city":"Robina",
    "sg:classifiers":[
        {
            "category":"Personal",
            "subcategory":"Massage",
            "type":"Services"
        }
    ],
    "sg:phone":"+61 419 024 979",
    "sg:postcode":"4226",
    "sg:province":"QLD",
    "sg:tags":[
        "therapy"
    ],
    "wof:name":"Armitage Maree",
    "wof:placetype":"venue"
},
  "geometry": {"coordinates":[153.39471435600001,-28.0681438446],"type":"Point"}
}