{
  "type": "Feature",
  "properties": {
    "addr:full":"8 Mara Pl West Lakes SA 5021",
    "addr:housenumber":"8",
    "addr:postcode":"5021",
    "addr:street":"Mara Pl",
    "iso:country":"AU",
    "sg:address":"8 Mara Pl",
    "sg:city":"West Lakes",
    "sg:classifiers":[
        {
            "category":"Professional",
            "subcategory":"Printing & Photocopies",
            "type":"Services"
        }
    ],
    "sg:phone":"+61 8 8347 0424",
    "sg:postcode":"5021",
    "sg:province":"SA",
    "sg:tags":[
        "embroidery"
    ],
    "wof:name":"Alvena Hall Whipstitch",
    "wof:placetype":"venue"
},
  "geometry": {"coordinates":[138.50108337399999,-34.8790626526],"type":"Point"}
}