{
  "type": "Feature",
  "properties": {
    "addr:full":"Oltam Rd Currabubula NSW 2342",
    "addr:postcode":"2342",
    "addr:street":"Oltam Rd",
    "iso:country":"AU",
    "sg:address":"Oltam Rd",
    "sg:city":"Currabubula",
    "sg:classifiers":[
        {
            "category":"Building & Trades",
            "subcategory":"Cleaning & Sanitation",
            "type":"Services"
        }
    ],
    "sg:phone":"+61 1800 624 913",
    "sg:postcode":"2342",
    "sg:province":"NSW",
    "sg:tags":[
        "asbestos",
        "treatment",
        "removal"
    ],
    "wof:name":"Curreng Asbestos Removal",
    "wof:placetype":"venue"
},
  "geometry": {"coordinates":[150.67596435600001,-31.2456092834],"type":"Point"}
}