{
  "type": "Feature",
  "properties": {
    "iso:country":"AU",
    "sg:address":"62 Lamb St",
    "sg:city":"Bundaberg",
    "sg:classifiers":[
        {
            "category":"Building & Trades",
            "subcategory":"Pest Control",
            "type":"Services"
        }
    ],
    "sg:phone":"+61 7 4151 0101",
    "sg:postcode":"4670",
    "sg:province":"QLD",
    "wof:name":"Wide Bay-Burnett Pest Management",
    "wof:placetype":"venue"
},
  "geometry": {"coordinates":[152.357421875,-24.8789596558],"type":"Point"}
}