{
  "type": "Feature",
  "properties": {
    "addr:full":"465a Maroondah Hwy Ringwood NSW 2646",
    "addr:housenumber":"465a",
    "addr:postcode":"2646",
    "addr:street":"Maroondah Hwy",
    "iso:country":"AU",
    "sg:address":"465a Maroondah Hwy",
    "sg:city":"Ringwood",
    "sg:classifiers":[
        {
            "category":"Autos & Motor Vehicles",
            "subcategory":"Automobile Sales",
            "type":"Retail Goods"
        }
    ],
    "sg:phone":"+61 3 9876 9955",
    "sg:postcode":"2646",
    "sg:province":"NSW",
    "sg:tags":[
        "car",
        "used"
    ],
    "wof:name":"Car Network",
    "wof:placetype":"venue"
},
  "geometry": {"coordinates":[146.19305419899999,-35.8736114502],"type":"Point"}
}