{
  "type": "Feature",
  "properties": {
    "addr:full":"5 Mill St Perth WA 6000",
    "addr:housenumber":"5",
    "addr:postcode":"6000",
    "addr:street":"Mill St",
    "iso:country":"AU",
    "sg:address":"5 Mill St",
    "sg:city":"Perth",
    "sg:classifiers":[
        {
            "category":"Health Services",
            "subcategory":"Dentist",
            "type":"Services"
        }
    ],
    "sg:phone":"+61 8 9321 7952",
    "sg:postcode":"6000",
    "sg:province":"WA",
    "wof:name":"Booker Vivian R",
    "wof:placetype":"venue"
},
  "geometry": {"coordinates":[115.852630615,-31.954957962],"type":"Point"}
}