{
  "type": "Feature",
  "properties": {
    "addr:full":"10 Marion St Leichhardt NSW 2040",
    "addr:housenumber":"10",
    "addr:postcode":"2040",
    "addr:street":"Marion St",
    "iso:country":"AU",
    "sg:address":"10 Marion St",
    "sg:city":"Leichhardt",
    "sg:classifiers":[
        {
            "category":"Health Services",
            "subcategory":"Health Practitioner",
            "type":"Services"
        }
    ],
    "sg:phone":"+61 2 9569 7092",
    "sg:postcode":"2040",
    "sg:province":"NSW",
    "sg:tags":[
        "psychologist"
    ],
    "wof:name":"Heuston Shirley",
    "wof:placetype":"venue"
},
  "geometry": {"coordinates":[151.15580700000001,-33.88401],"type":"Point"}
}