{
  "type": "Feature",
  "properties": {
    "iso:country":"AU",
    "sg:address":"Katamatite Rd",
    "sg:city":"Congupna",
    "sg:classifiers":[
        {
            "category":"Food & Beverages",
            "subcategory":"Farmers Market",
            "type":"Retail Goods"
        }
    ],
    "sg:phone":"+61 3 5829 9316",
    "sg:postcode":"3633",
    "sg:province":"VIC",
    "sg:tags":[
        "beekeeper"
    ],
    "wof:name":"Diprose M N",
    "wof:placetype":"venue"
},
  "geometry": {"coordinates":[145.47361755399999,-36.2877388],"type":"Point"}
}