{
  "type": "Feature",
  "properties": {
    "addr:full":"Unit 1/ 35 Gilbert Park Drv Knoxfield VIC 3180",
    "addr:housenumber":"35",
    "addr:postcode":"3180",
    "addr:street":"Gilbert Park Drv",
    "iso:country":"AU",
    "sg:address":"Unit 1/ 35 Gilbert Park Drv",
    "sg:city":"Knoxfield",
    "sg:classifiers":[
        {
            "category":"Manufacturing",
            "subcategory":"Metals",
            "type":"Manufacturing & Wholesale Goods"
        }
    ],
    "sg:phone":"+61 3 9763 3636",
    "sg:postcode":"3180",
    "sg:province":"VIC",
    "sg:tags":[
        "sheet",
        "worker"
    ],
    "wof:name":"A-1 Quality Sheet Metal Pty Ltd",
    "wof:placetype":"venue"
},
  "geometry": {"coordinates":[145.253417969,-37.8978767395],"type":"Point"}
}