{
  "type": "Feature",
  "properties": {
    "addr:full":"2a Hannah St Beecroft NSW 2119",
    "addr:housenumber":"2a",
    "addr:postcode":"2119",
    "addr:street":"Hannah St",
    "iso:country":"AU",
    "sg:address":"2a Hannah St",
    "sg:city":"Beecroft",
    "sg:classifiers":[
        {
            "category":"Education",
            "subcategory":"Music School",
            "type":"Public Place"
        }
    ],
    "sg:phone":"+61 2 9875 5005",
    "sg:postcode":"2119",
    "sg:province":"NSW",
    "sg:tags":[
        "teacher"
    ],
    "wof:name":"Russell's Music Australia",
    "wof:placetype":"venue"
},
  "geometry": {"coordinates":[151.06590270999999,-33.7491569519],"type":"Point"}
}