{
  "type": "Feature",
  "properties": {
    "addr:full":"43a Sydney Rd Manly NSW 2095",
    "addr:housenumber":"43a",
    "addr:postcode":"2095",
    "addr:street":"Sydney Rd",
    "iso:country":"AU",
    "sg:address":"43a Sydney Rd",
    "sg:city":"Manly",
    "sg:classifiers":[
        {
            "category":"Retail",
            "subcategory":"Laundry & Dry Cleaning",
            "type":"Services"
        }
    ],
    "sg:phone":"+61 2 9976 3311",
    "sg:postcode":"2095",
    "sg:province":"NSW",
    "sg:tags":[
        "manicurist"
    ],
    "wof:name":"Divine Nails",
    "wof:placetype":"venue"
},
  "geometry": {"coordinates":[151.285644531,-33.7971000671],"type":"Point"}
}