{
  "type": "Feature",
  "properties": {
    "iso:country":"AU",
    "sg:address":"Factory 2/ 6 Vesper Drv",
    "sg:city":"Narre Warren",
    "sg:classifiers":[
        {
            "category":"Manufacturing",
            "subcategory":"Tools & Machinery",
            "type":"Manufacturing & Wholesale Goods"
        }
    ],
    "sg:phone":"+61 3 8786 5100",
    "sg:postcode":"3805",
    "sg:province":"VIC",
    "wof:name":"Attic Industries",
    "wof:placetype":"venue"
},
  "geometry": {"coordinates":[145.296494,-38.020283],"type":"Point"}
}