{
  "type": "Feature",
  "properties": {
    "addr:full":"6 Depot Rd Dubbo West NSW 2830",
    "addr:housenumber":"6",
    "addr:postcode":"2830",
    "addr:street":"Depot Rd",
    "iso:country":"AU",
    "sg:address":"6 Depot Rd",
    "sg:city":"Dubbo West",
    "sg:classifiers":[
        {
            "category":"Retail",
            "subcategory":"Auto Repair",
            "type":"Services"
        }
    ],
    "sg:phone":"+61 2 6884 1033",
    "sg:postcode":"2830",
    "sg:province":"NSW",
    "sg:tags":[
        "body",
        "motor",
        "trimmer"
    ],
    "wof:name":"Espert Tony Upholstery & Motor Trimming Centre",
    "wof:placetype":"venue"
},
  "geometry": {"coordinates":[148.58682250999999,-32.2436141968],"type":"Point"}
}