{
  "type": "Feature",
  "properties": {
    "iso:country":"AU",
    "sg:address":"Level 9, 256 Adelaide Tce",
    "sg:city":"Perth",
    "sg:classifiers":[
        {
            "category":"Professional",
            "subcategory":"Computer Services",
            "type":"Services"
        }
    ],
    "sg:phone":"+61 1300 135 337",
    "sg:postcode":"6000",
    "sg:province":"WA",
    "sg:tags":[
        "on-line",
        "provider"
    ],
    "wof:name":"Wired City",
    "wof:placetype":"venue"
},
  "geometry": {"coordinates":[115.865730286,-31.9576511383],"type":"Point"}
}