{
  "type": "Feature",
  "properties": {
    "addr:full":"552 Reserve Rd Coomera QLD 4209",
    "addr:housenumber":"552",
    "addr:postcode":"4209",
    "addr:street":"Reserve Rd",
    "iso:country":"AU",
    "sg:address":"552 Reserve Rd",
    "sg:city":"Coomera",
    "sg:classifiers":[
        {
            "category":"Professional",
            "type":"Services"
        }
    ],
    "sg:phone":"+61 7 5573 1237",
    "sg:postcode":"4209",
    "sg:province":"QLD",
    "sg:tags":[
        "spray",
        "painting"
    ],
    "wof:name":"Commercial Fleet Refinishers",
    "wof:placetype":"venue"
},
  "geometry": {"coordinates":[153.28305053700001,-27.8933677673],"type":"Point"}
}