{
  "type": "Feature",
  "properties": {
    "iso:country":"AU",
    "sg:address":"138 Lawes St",
    "sg:city":"East Maitland",
    "sg:classifiers":[
        {
            "category":"Professional",
            "subcategory":"Accounting & Tax Preparation",
            "type":"Services"
        }
    ],
    "sg:phone":"+61 2 4933 0393",
    "sg:postcode":"2323",
    "sg:province":"NSW",
    "sg:tags":[
        "accountant",
        "auditor"
    ],
    "wof:name":"Merrick C & Company",
    "wof:placetype":"venue"
},
  "geometry": {"coordinates":[151.59065246599999,-32.7521324158],"type":"Point"}
}