{
  "type": "Feature",
  "properties": {
    "addr:full":"1/ 119 Edith St Wynnum QLD 4178",
    "addr:housenumber":"/ 119",
    "addr:postcode":"4178",
    "addr:street":"Edith St",
    "iso:country":"AU",
    "sg:address":"1/ 119 Edith St",
    "sg:city":"Wynnum",
    "sg:classifiers":[
        {
            "category":"Health Services",
            "subcategory":"Health Practitioner",
            "type":"Services"
        }
    ],
    "sg:phone":"+61 7 3396 2563",
    "sg:postcode":"4178",
    "sg:province":"QLD",
    "sg:tags":[
        "naturopath"
    ],
    "wof:name":"Pocock Loni",
    "wof:placetype":"venue"
},
  "geometry": {"coordinates":[153.173065186,-27.4450855255],"type":"Point"}
}