{
  "type": "Feature",
  "properties": {
    "addr:full":"1 Gibbens Rd Gosford West NSW 2250",
    "addr:housenumber":"1",
    "addr:postcode":"2250",
    "addr:street":"Gibbens Rd",
    "iso:country":"AU",
    "sg:address":"1 Gibbens Rd",
    "sg:city":"Gosford West",
    "sg:classifiers":[
        {
            "category":"Building & Trades",
            "subcategory":"Construction",
            "type":"Services"
        }
    ],
    "sg:phone":"+61 2 4324 5555",
    "sg:postcode":"2250",
    "sg:province":"NSW",
    "sg:tags":[
        "insulation",
        "contractor"
    ],
    "wof:name":"Bayline Roofing",
    "wof:placetype":"venue"
},
  "geometry": {"coordinates":[151.324676514,-33.4153366089],"type":"Point"}
}