{
  "type": "Feature",
  "properties": {
    "iso:country":"AU",
    "sg:address":"155 Raleigh Rd",
    "sg:city":"Maribyrnong",
    "sg:classifiers":[
        {
            "category":"Home & Garden",
            "subcategory":"Carpets & Floor Coverings",
            "type":"Retail Goods"
        }
    ],
    "sg:phone":"+61 3 9317 4888",
    "sg:postcode":"3032",
    "sg:province":"VIC",
    "sg:tags":[
        "tile",
        "wall"
    ],
    "sg:website":"http://www.middletonscentres.com.au",
    "wof:name":"Middletons Centres",
    "wof:placetype":"venue"
},
  "geometry": {"coordinates":[144.883163,-37.769585],"type":"Point"}
}