{
  "type": "Feature",
  "properties": {
    "addr:full":"380 Goonoo Goonoo Rd Tamworth NSW 2340",
    "addr:housenumber":"380",
    "addr:postcode":"2340",
    "addr:street":"Goonoo Goonoo Rd",
    "iso:country":"AU",
    "sg:address":"380 Goonoo Goonoo Rd",
    "sg:city":"Tamworth",
    "sg:classifiers":[
        {
            "category":"Farming",
            "subcategory":"Poultry Farm",
            "type":"Manufacturing & Wholesale Goods"
        }
    ],
    "sg:phone":"+61 2 6765 3626",
    "sg:postcode":"2340",
    "sg:province":"NSW",
    "sg:tags":[
        "breeder",
        "bird"
    ],
    "wof:name":"Pat Chaffey",
    "wof:placetype":"venue"
},
  "geometry": {"coordinates":[150.923950195,-31.1219062805],"type":"Point"}
}