{
  "type": "Feature",
  "properties": {
    "iso:country":"AU",
    "sg:address":"171 Currumburra Rd",
    "sg:city":"Ashmore",
    "sg:classifiers":[
        {
            "category":"Building & Trades",
            "subcategory":"Construction",
            "type":"Services"
        }
    ],
    "sg:phone":"+61 7 5597 3233",
    "sg:postcode":"4214",
    "sg:province":"QLD",
    "sg:tags":[
        "window",
        "tinting"
    ],
    "sg:website":"http://www.instinttint.com.au",
    "wof:name":"Instint Window Tinting",
    "wof:placetype":"venue"
},
  "geometry": {"coordinates":[153.38265991200001,-27.980588913],"type":"Point"}
}