{
  "type": "Feature",
  "properties": {
    "iso:country":"AU",
    "sg:address":"13 Cedar Drv",
    "sg:city":"Bathurst",
    "sg:classifiers":[
        {
            "category":"Government",
            "subcategory":"Court House",
            "type":"Public Place"
        }
    ],
    "sg:phone":"+61 1300 652 882",
    "sg:postcode":"2795",
    "sg:province":"NSW",
    "sg:tags":[
        "personal",
        "marriage",
        "family",
        "counselling"
    ],
    "wof:name":"Turning Point Telephone Counselling",
    "wof:placetype":"venue"
},
  "geometry": {"coordinates":[149.557662964,-33.3958129883],"type":"Point"}
}