{
  "type": "Feature",
  "properties": {
    "addr:full":"41 Dalton Ave Aldgate SA 5154",
    "addr:housenumber":"41",
    "addr:postcode":"5154",
    "addr:street":"Dalton Ave",
    "iso:country":"AU",
    "sg:address":"41 Dalton Ave",
    "sg:city":"Aldgate",
    "sg:classifiers":[
        {
            "category":"Professional",
            "subcategory":"Management & Consulting",
            "type":"Services"
        }
    ],
    "sg:phone":"+61 8 8370 1880",
    "sg:postcode":"5154",
    "sg:province":"SA",
    "sg:tags":[
        "consultant",
        "educational"
    ],
    "wof:name":"Webcite Pty Ltd",
    "wof:placetype":"venue"
},
  "geometry": {"coordinates":[138.751220703,-35.0253715515],"type":"Point"}
}