{
  "type": "Feature",
  "properties": {
    "addr:full":"Cnr Corrimal & Beach Sts Wollongong NSW 2500",
    "addr:postcode":"2500",
    "iso:country":"AU",
    "sg:address":"Cnr Corrimal & Beach Sts",
    "sg:city":"Wollongong",
    "sg:classifiers":[
        {
            "category":"Autos & Motor Vehicles",
            "subcategory":"Auto Supplies",
            "type":"Retail Goods"
        }
    ],
    "sg:phone":"+61 400 400 455",
    "sg:postcode":"2500",
    "sg:province":"NSW",
    "sg:tags":[
        "battery",
        "automotive"
    ],
    "wof:name":"1St Choice Auto Electrics",
    "wof:placetype":"venue"
},
  "geometry": {"coordinates":[150.900497,-34.417164],"type":"Point"}
}