{
  "type": "Feature",
  "properties": {
    "addr:full":"5 McCormack Crt Rochedale South QLD 4123",
    "addr:housenumber":"5",
    "addr:postcode":"4123",
    "addr:street":"Mccormack Crt",
    "iso:country":"AU",
    "sg:address":"5 McCormack Crt",
    "sg:city":"Rochedale South",
    "sg:classifiers":[
        {
            "category":"Wholesale",
            "subcategory":"Machinery & Supplies",
            "type":"Manufacturing & Wholesale Goods"
        }
    ],
    "sg:phone":"+61 7 3341 1217",
    "sg:postcode":"4123",
    "sg:province":"QLD",
    "sg:tags":[
        "instrument",
        "scientific"
    ],
    "wof:name":"Microscope & Optical Instrument Services",
    "wof:placetype":"venue"
},
  "geometry": {"coordinates":[153.131149292,-27.6074542999],"type":"Point"}
}