{
  "type": "Feature",
  "properties": {
    "addr:full":"Laurie St Innisfail QLD 4860",
    "addr:postcode":"4860",
    "addr:street":"Laurie St",
    "iso:country":"AU",
    "sg:address":"Laurie St",
    "sg:city":"Innisfail",
    "sg:classifiers":[
        {
            "category":"Home & Garden",
            "subcategory":"Building Materials",
            "type":"Retail Goods"
        }
    ],
    "sg:phone":"+61 7 4061 2055",
    "sg:postcode":"4860",
    "sg:province":"QLD",
    "sg:tags":[
        "pre-mixed",
        "concrete"
    ],
    "wof:name":"Readymix",
    "wof:placetype":"venue"
},
  "geometry": {"coordinates":[146.008636475,-17.5248508453],"type":"Point"}
}