{
  "type": "Feature",
  "properties": {
    "addr:full":"15 Finlayson Ave Mt Martha VIC 3934",
    "addr:housenumber":"15",
    "addr:postcode":"3934",
    "addr:street":"Finlayson Ave Mt Martha",
    "iso:country":"AU",
    "sg:address":"15 Finlayson Ave",
    "sg:city":"Mt Martha",
    "sg:classifiers":[
        {
            "category":"Professional",
            "subcategory":"Art Services",
            "type":"Services"
        }
    ],
    "sg:phone":"+61 3 5974 2357",
    "sg:postcode":"3934",
    "sg:province":"VIC",
    "sg:tags":[
        "interior",
        "designer"
    ],
    "wof:name":"Pam Shaw Interiors",
    "wof:placetype":"venue"
},
  "geometry": {"coordinates":[144.996658325,-38.2840385437],"type":"Point"}
}