{
  "type": "Feature",
  "properties": {
    "iso:country":"AU",
    "sg:address":"47 Wentworth Ave",
    "sg:city":"Sydney",
    "sg:classifiers":[
        {
            "category":"Shopping",
            "type":"Retail Goods"
        }
    ],
    "sg:phone":"+61 2 9212 7845",
    "sg:postcode":"2000",
    "sg:province":"NSW",
    "sg:tags":[
        "product",
        "plastic"
    ],
    "wof:name":"New Age Polymers",
    "wof:placetype":"venue"
},
  "geometry": {"coordinates":[151.210113525,-33.8789253235],"type":"Point"}
}