{
  "type": "Feature",
  "properties": {
    "iso:country":"AU",
    "sg:address":"22 Cedar Creek Rd",
    "sg:city":"Cedar Creek",
    "sg:classifiers":[
        {
            "category":"Manufacturing",
            "subcategory":"Tools & Machinery",
            "type":"Manufacturing & Wholesale Goods"
        }
    ],
    "sg:phone":"+61 7 5546 4566",
    "sg:postcode":"4520",
    "sg:province":"QLD",
    "sg:tags":[
        "earth",
        "excavating",
        "moving",
        "equipment"
    ],
    "wof:name":"Ty's Bobcat & Tipper Hire",
    "wof:placetype":"venue"
},
  "geometry": {"coordinates":[152.84303299999999,-27.337643],"type":"Point"}
}