{
  "type": "Feature",
  "properties": {
    "iso:country":"AU",
    "sg:address":"The University Of Wollongong B 39 Wollongong University",
    "sg:city":"Wollongong",
    "sg:classifiers":[
        {
            "category":"Manufacturing",
            "subcategory":"Electronics",
            "type":"Manufacturing & Wholesale Goods"
        }
    ],
    "sg:phone":"+61 2 4226 8823",
    "sg:postcode":"2500",
    "sg:province":"NSW",
    "sg:tags":[
        "oven",
        "microwave"
    ],
    "wof:name":"Advanced Manufacturing Technologies",
    "wof:placetype":"venue"
},
  "geometry": {"coordinates":[150.882645,-34.410782],"type":"Point"}
}