{
  "type": "Feature",
  "properties": {
    "iso:country":"AU",
    "sg:address":"Banks Rd",
    "sg:city":"Miller",
    "sg:classifiers":[
        {
            "category":"Building & Trades",
            "subcategory":"Construction",
            "type":"Services"
        }
    ],
    "sg:phone":"+61 2 9825 7473",
    "sg:postcode":"2168",
    "sg:province":"NSW",
    "sg:tags":[
        "contractor"
    ],
    "wof:name":"SWSI Tafe-Miller",
    "wof:placetype":"venue"
},
  "geometry": {"coordinates":[150.87356567399999,-33.9184188843],"type":"Point"}
}