{
  "type": "Feature",
  "properties": {
    "iso:country":"AU",
    "sg:address":"Shp 29a/ 193 Jull St",
    "sg:city":"Armadale",
    "sg:classifiers":[
        {
            "category":"Travel",
            "subcategory":"Travel Agent",
            "type":"Entertainment"
        }
    ],
    "sg:phone":"+61 8 9399 8200",
    "sg:postcode":"6112",
    "sg:province":"WA",
    "sg:tags":[
        "consultant"
    ],
    "wof:name":"Travelscene",
    "wof:placetype":"venue"
},
  "geometry": {"coordinates":[116.020591736,-32.1502342224],"type":"Point"}
}