{
  "type": "Feature",
  "properties": {
    "addr:full":"1/ 70 Pound St Grafton NSW 2460",
    "addr:housenumber":"/ 70",
    "addr:postcode":"2460",
    "addr:street":"Pound St",
    "iso:country":"AU",
    "sg:address":"1/ 70 Pound St",
    "sg:city":"Grafton",
    "sg:classifiers":[
        {
            "category":"Professional",
            "subcategory":"Employment Agencies",
            "type":"Services"
        }
    ],
    "sg:phone":"+61 2 6643 2227",
    "sg:postcode":"2460",
    "sg:province":"NSW",
    "wof:name":"Key Employment",
    "wof:placetype":"venue"
},
  "geometry": {"coordinates":[152.938034058,-29.6914024353],"type":"Point"}
}