{
  "type": "Feature",
  "properties": {
    "addr:full":"7 Akuna St Canberra City ACT 2601",
    "addr:housenumber":"7",
    "addr:postcode":"2601",
    "addr:street":"Akuna St",
    "iso:country":"AU",
    "sg:address":"7 Akuna St",
    "sg:city":"Canberra City",
    "sg:classifiers":[
        {
            "category":"Travel",
            "subcategory":"Hotels & Motels",
            "type":"Entertainment"
        }
    ],
    "sg:phone":"+61 2 6257 3999",
    "sg:postcode":"2601",
    "sg:province":"ACT",
    "sg:tags":[
        "accommodation"
    ],
    "wof:name":"Canberra City Accommodation",
    "wof:placetype":"venue"
},
  "geometry": {"coordinates":[149.13250732399999,-35.2816200256],"type":"Point"}
}