{
  "type": "Feature",
  "properties": {
    "addr:full":"14 Holland St Wembley WA 6014",
    "addr:housenumber":"14",
    "addr:postcode":"6014",
    "addr:street":"Holland St",
    "iso:country":"AU",
    "sg:address":"14 Holland St",
    "sg:city":"Wembley",
    "sg:classifiers":[
        {
            "category":"Professional",
            "subcategory":"Engineering",
            "type":"Services"
        }
    ],
    "sg:phone":"+61 8 9387 2053",
    "sg:postcode":"6014",
    "sg:province":"WA",
    "sg:tags":[
        "consultant",
        "geotechnical",
        "engineer"
    ],
    "wof:name":"A & F Geotechnical Services Pty Ltd",
    "wof:placetype":"venue"
},
  "geometry": {"coordinates":[115.81420135499999,-31.9392414093],"type":"Point"}
}