{
  "type": "Feature",
  "properties": {
    "addr:full":"Rear Level 1 257 Collins St Melbourne VIC 3000",
    "addr:housenumber":"1 257",
    "addr:postcode":"3000",
    "addr:street":"Collins St",
    "iso:country":"AU",
    "sg:address":"Rear Level 1 257 Collins St",
    "sg:city":"Melbourne",
    "sg:classifiers":[
        {
            "category":"Travel",
            "subcategory":"Hotels & Motels",
            "type":"Entertainment"
        }
    ],
    "sg:phone":"+61 3 9662 1887",
    "sg:postcode":"3000",
    "sg:province":"VIC",
    "sg:tags":[
        "accommodation"
    ],
    "wof:name":"Central Apartment Hotels",
    "wof:placetype":"venue"
},
  "geometry": {"coordinates":[144.96536254899999,-37.8159637451],"type":"Point"}
}