{
  "type": "Feature",
  "properties": {
    "addr:full":"170 Boniface St Coopers Plains QLD 4108",
    "addr:housenumber":"170",
    "addr:postcode":"4108",
    "addr:street":"Boniface St",
    "iso:country":"AU",
    "sg:address":"170 Boniface St",
    "sg:city":"Coopers Plains",
    "sg:classifiers":[
        {
            "category":"Retail",
            "subcategory":"Auto Repair",
            "type":"Services"
        }
    ],
    "sg:phone":"+61 7 3274 1808",
    "sg:postcode":"4108",
    "sg:province":"QLD",
    "sg:tags":[
        "repairer",
        "motor",
        "engineer"
    ],
    "wof:name":"Mechanics of Star Automotive",
    "wof:placetype":"venue"
},
  "geometry": {"coordinates":[153.019439697,-27.566822052],"type":"Point"}
}