{
  "type": "Feature",
  "properties": {
    "iso:country":"AU",
    "sg:address":"PO Box 3511",
    "sg:city":"Wamberal",
    "sg:classifiers":[
        {
            "category":"Professional",
            "type":"Services"
        }
    ],
    "sg:phone":"+61 2 4385 3761",
    "sg:postcode":"2260",
    "sg:province":"NSW",
    "sg:tags":[
        "shop",
        "fitting"
    ],
    "wof:name":"Classic Group Pty Ltd",
    "wof:placetype":"venue"
},
  "geometry": {"coordinates":[151.443146,-33.418209],"type":"Point"}
}