{
  "type": "Feature",
  "properties": {
    "iso:country":"AU",
    "sg:address":"PO Box 184",
    "sg:city":"Wavell Heights North",
    "sg:classifiers":[
        {
            "category":"Retail",
            "subcategory":"Auto Repair",
            "type":"Services"
        }
    ],
    "sg:phone":"+61 412 749 422",
    "sg:postcode":"4012",
    "sg:province":"QLD",
    "sg:tags":[
        "repairer",
        "motor",
        "engineer"
    ],
    "wof:name":"Quentin Phillips Mobile Auto Repairs",
    "wof:placetype":"venue"
},
  "geometry": {"coordinates":[153.04440307600001,-27.3912200928],"type":"Point"}
}