{
  "type": "Feature",
  "properties": {
    "addr:full":"Shp 7/ 1 Martin Pl Sydney NSW 2000",
    "addr:housenumber":"/ 1",
    "addr:postcode":"2000",
    "addr:street":"Pl",
    "iso:country":"AU",
    "sg:address":"Shp 7/ 1 Martin Pl",
    "sg:city":"Sydney",
    "sg:classifiers":[
        {
            "category":"Personal",
            "subcategory":"Beauty Salon",
            "type":"Services"
        }
    ],
    "sg:phone":"+61 2 9232 3124",
    "sg:postcode":"2000",
    "sg:province":"NSW",
    "sg:tags":[
        "hairdresser"
    ],
    "wof:name":"Perry Ellis Hairdressing",
    "wof:placetype":"venue"
},
  "geometry": {"coordinates":[151.207763672,-33.8676071167],"type":"Point"}
}