{
  "type": "Feature",
  "properties": {
    "iso:country":"AU",
    "sg:address":"47 Hope Valley Rd",
    "sg:city":"Naval Base",
    "sg:classifiers":[
        {
            "category":"Wholesale",
            "subcategory":"Metals & Minerals",
            "type":"Manufacturing & Wholesale Goods"
        }
    ],
    "sg:phone":"+61 8 9437 2025",
    "sg:postcode":"6165",
    "sg:province":"WA",
    "sg:tags":[
        "steel",
        "merchant"
    ],
    "wof:name":"M & J Metals",
    "wof:placetype":"venue"
},
  "geometry": {"coordinates":[115.79007,-32.192764],"type":"Point"}
}