{
  "type": "Feature",
  "properties": {
    "iso:country":"AU",
    "sg:address":"\"Summerlands\" Palmer Rd",
    "sg:city":"Kyabram",
    "sg:classifiers":[
        {
            "category":"Farming",
            "subcategory":"Orchard",
            "type":"Manufacturing & Wholesale Goods"
        }
    ],
    "sg:phone":"+61 3 5852 1162",
    "sg:postcode":"3620",
    "sg:province":"VIC",
    "sg:tags":[
        "pear",
        "apple",
        "grower"
    ],
    "wof:name":"Puckey R P & M A",
    "wof:placetype":"venue"
},
  "geometry": {"coordinates":[145.024261475,-36.2961616516],"type":"Point"}
}