{
  "type": "Feature",
  "properties": {
    "iso:country":"AU",
    "sg:address":"Unit 1/ 3 Heritage Cove",
    "sg:city":"Maylands",
    "sg:classifiers":[
        {
            "category":"Manufacturing",
            "subcategory":"Apparel",
            "type":"Manufacturing & Wholesale Goods"
        }
    ],
    "sg:phone":"+61 403 803 908",
    "sg:postcode":"6051",
    "sg:province":"WA",
    "sg:tags":[
        "makers-up",
        "clothing"
    ],
    "wof:name":"O'Brien Design Studio",
    "wof:placetype":"venue"
},
  "geometry": {"coordinates":[115.908127,-31.943056],"type":"Point"}
}