{
  "type": "Feature",
  "properties": {
    "addr:full":"27 Henty St Casterton VIC 3311",
    "addr:housenumber":"27",
    "addr:postcode":"3311",
    "addr:street":"Henty St",
    "iso:country":"AU",
    "sg:address":"27 Henty St",
    "sg:city":"Casterton",
    "sg:classifiers":[
        {
            "category":"Professional",
            "subcategory":"Accounting & Tax Preparation",
            "type":"Services"
        }
    ],
    "sg:phone":"+61 3 5581 1000",
    "sg:postcode":"3311",
    "sg:province":"VIC",
    "sg:tags":[
        "accountant",
        "auditor"
    ],
    "wof:name":"Axis Accounting Partners Pty Ltd",
    "wof:placetype":"venue"
},
  "geometry": {"coordinates":[141.40629577600001,-37.5841903687],"type":"Point"}
}