{
  "type": "Feature",
  "properties": {
    "addr:full":"Cnr Dawson Hwy & Park St Gladstone QLD 4680",
    "addr:postcode":"4680",
    "addr:street":"Cnr Dawson Hwy &;St",
    "iso:country":"AU",
    "sg:address":"Cnr Dawson Hwy & Park St",
    "sg:city":"Gladstone",
    "sg:classifiers":[
        {
            "category":"Manufacturing",
            "subcategory":"Motor Vehicles & Parts",
            "type":"Manufacturing & Wholesale Goods"
        }
    ],
    "sg:phone":"+61 7 4972 8122",
    "sg:postcode":"4680",
    "sg:province":"QLD",
    "sg:tags":[
        "replacement"
    ],
    "wof:name":"Autobarn",
    "wof:placetype":"venue"
},
  "geometry": {"coordinates":[151.24978637699999,-23.8529491425],"type":"Point"}
}