{
  "type": "Feature",
  "properties": {
    "addr:full":"17 Grandview Ave Urrbrae SA 5064",
    "addr:housenumber":"17",
    "addr:postcode":"5064",
    "addr:street":"Grandview Ave",
    "iso:country":"AU",
    "sg:address":"17 Grandview Ave",
    "sg:city":"Urrbrae",
    "sg:classifiers":[
        {
            "category":"Building & Trades",
            "subcategory":"Construction",
            "type":"Services"
        }
    ],
    "sg:phone":"+61 419 821 424",
    "sg:postcode":"5064",
    "sg:province":"SA",
    "sg:tags":[
        "renovation",
        "alterations",
        "extension",
        "contractor"
    ],
    "wof:name":"Nu-Image Homes & Improvements",
    "wof:placetype":"venue"
},
  "geometry": {"coordinates":[138.63760375999999,-34.9652404785],"type":"Point"}
}