{
  "type": "Feature",
  "properties": {
    "iso:country":"AU",
    "sg:address":"12 Eccles Rd",
    "sg:city":"Ocean Grove",
    "sg:classifiers":[
        {
            "category":"Health Services",
            "subcategory":"Chiropractor",
            "type":"Services"
        }
    ],
    "sg:phone":"+61 3 5255 4722",
    "sg:postcode":"3226",
    "sg:province":"VIC",
    "wof:name":"Ocean Grove Chiropractic",
    "wof:placetype":"venue"
},
  "geometry": {"coordinates":[144.551941,-38.263763],"type":"Point"}
}