{
  "type": "Feature",
  "properties": {
    "addr:full":"1st Floor 100 Currie St Adelaide SA 5000",
    "addr:housenumber":"100",
    "addr:postcode":"5000",
    "addr:street":"Currie St",
    "iso:country":"AU",
    "sg:address":"1st Floor 100 Currie St",
    "sg:city":"Adelaide",
    "sg:classifiers":[
        {
            "category":"Health Services",
            "subcategory":"Dentist",
            "type":"Services"
        }
    ],
    "sg:phone":"+61 8 8231 5324",
    "sg:postcode":"5000",
    "sg:province":"SA",
    "wof:name":"Choimes James",
    "wof:placetype":"venue"
},
  "geometry": {"coordinates":[138.59596252399999,-34.9243240356],"type":"Point"}
}