{
  "type": "Feature",
  "properties": {
    "addr:full":"C1.28 Abbotsford Convent, 1 St Heliers St Abbotsford VIC 3067",
    "addr:housenumber":"1",
    "addr:postcode":"3067",
    "addr:street":"St Heliers St",
    "iso:country":"AU",
    "sg:address":"C1.28 Abbotsford Convent, 1 St Heliers St",
    "sg:city":"Abbotsford",
    "sg:classifiers":[
        {
            "category":"Education",
            "subcategory":"University",
            "type":"Public Place"
        }
    ],
    "sg:phone":"+61 3 9495 6422",
    "sg:postcode":"3067",
    "sg:province":"VIC",
    "sg:tags":[
        "educational",
        "organisation",
        "cultural"
    ],
    "wof:name":"The Song Room",
    "wof:placetype":"venue"
},
  "geometry": {"coordinates":[145.00331115700001,-37.8020477295],"type":"Point"}
}