{
  "type": "Feature",
  "properties": {
    "addr:full":"212- 214 Urana St Wagga Wagga NSW 2650",
    "addr:housenumber":"212 214",
    "addr:postcode":"2650",
    "addr:street":"Urana St",
    "iso:country":"AU",
    "sg:address":"212- 214 Urana St",
    "sg:city":"Wagga Wagga",
    "sg:classifiers":[
        {
            "category":"Professional",
            "type":"Services"
        }
    ],
    "sg:phone":"+61 2 6925 5044",
    "sg:postcode":"2650",
    "sg:province":"NSW",
    "sg:tags":[
        "shop",
        "fitting"
    ],
    "wof:name":"Fosters Joinery",
    "wof:placetype":"venue"
},
  "geometry": {"coordinates":[147.34262085,-35.1250457764],"type":"Point"}
}