{
  "type": "Feature",
  "properties": {
    "addr:full":"1 Yarra Crt Dandenong North VIC 3175",
    "addr:housenumber":"1",
    "addr:postcode":"3175",
    "addr:street":"Yarra Crt",
    "iso:country":"AU",
    "sg:address":"1 Yarra Crt",
    "sg:city":"Dandenong North",
    "sg:classifiers":[
        {
            "category":"Banks & Credit Unions",
            "subcategory":"Investment Brokerage",
            "type":"Services"
        }
    ],
    "sg:phone":"+61 3 9795 6937",
    "sg:postcode":"3175",
    "sg:province":"VIC",
    "sg:tags":[
        "repairer",
        "typewriter"
    ],
    "wof:name":"E.Z. Office Machines Pty Ltd",
    "wof:placetype":"venue"
},
  "geometry": {"coordinates":[145.215942383,-37.9434547424],"type":"Point"}
}