{
  "type": "Feature",
  "properties": {
    "addr:full":"Rear 167 High Rd Willetton WA 6155",
    "addr:housenumber":"167",
    "addr:postcode":"6155",
    "addr:street":"High Rd",
    "iso:country":"AU",
    "sg:address":"Rear 167 High Rd",
    "sg:city":"Willetton",
    "sg:classifiers":[
        {
            "category":"Real Estate",
            "subcategory":"Real Estate Agent",
            "type":"Services"
        }
    ],
    "sg:phone":"+61 8 9457 8244",
    "sg:postcode":"6155",
    "sg:province":"WA",
    "sg:tags":[
        "handyman's",
        "equipment",
        "hire",
        "builders",
        "contractor"
    ],
    "wof:name":"Hire-All Machinery & Sales",
    "wof:placetype":"venue"
},
  "geometry": {"coordinates":[115.884399,-32.038864],"type":"Point"}
}