{
  "type": "Feature",
  "properties": {
    "addr:full":"Level 3, 2 Ocean St Maroochydore QLD 4558",
    "addr:housenumber":"2",
    "addr:postcode":"4558",
    "addr:street":"Ocean St",
    "iso:country":"AU",
    "sg:address":"Level 3, 2 Ocean St",
    "sg:city":"Maroochydore",
    "sg:classifiers":[
        {
            "category":"Professional",
            "subcategory":"Accounting & Tax Preparation",
            "type":"Services"
        }
    ],
    "sg:phone":"+61 7 5443 6366",
    "sg:postcode":"4558",
    "sg:province":"QLD",
    "sg:tags":[
        "accountant",
        "auditor"
    ],
    "wof:name":"Bentleys MRI",
    "wof:placetype":"venue"
},
  "geometry": {"coordinates":[153.09193420400001,-26.6517391205],"type":"Point"}
}