{
  "type": "Feature",
  "properties": {
    "addr:full":"137 Macorna St Watsonia North VIC 3087",
    "addr:housenumber":"137",
    "addr:postcode":"3087",
    "addr:street":"Macorna St",
    "iso:country":"AU",
    "sg:address":"137 Macorna St",
    "sg:city":"Watsonia North",
    "sg:classifiers":[
        {
            "category":"Utilities",
            "subcategory":"Electric",
            "type":"Services"
        }
    ],
    "sg:phone":"+61 3 9434 7074",
    "sg:postcode":"3087",
    "sg:province":"VIC",
    "sg:tags":[
        "electrical",
        "contractor"
    ],
    "wof:name":"G J K Electrical Services",
    "wof:placetype":"venue"
},
  "geometry": {"coordinates":[145.085845947,-37.6918830872],"type":"Point"}
}