{
  "type": "Feature",
  "properties": {
    "addr:full":"12 Avro St Tamworth NSW 2340",
    "addr:housenumber":"12",
    "addr:postcode":"2340",
    "addr:street":"Avro St",
    "iso:country":"AU",
    "sg:address":"12 Avro St",
    "sg:city":"Tamworth",
    "sg:classifiers":[
        {
            "category":"Building & Trades",
            "subcategory":"Construction",
            "type":"Services"
        }
    ],
    "sg:phone":"+61 2 6765 7822",
    "sg:postcode":"2340",
    "sg:province":"NSW",
    "sg:tags":[
        "contractor"
    ],
    "wof:name":"Stan Meere & Associates Pty Ltd",
    "wof:placetype":"venue"
},
  "geometry": {"coordinates":[150.91093444800001,-31.0863609314],"type":"Point"}
}