{
  "type": "Feature",
  "properties": {
    "iso:country":"AU",
    "sg:address":"145 Oxford St",
    "sg:city":"Bondi Junction",
    "sg:classifiers":[
        {
            "category":"Personal",
            "subcategory":"Massage",
            "type":"Services"
        }
    ],
    "sg:phone":"+61 2 9387 7688",
    "sg:postcode":"2022",
    "sg:province":"NSW",
    "sg:tags":[
        "therapy"
    ],
    "wof:name":"Thai Massage Therapy Centre",
    "wof:placetype":"venue"
},
  "geometry": {"coordinates":[151.247802734,-33.8919944763],"type":"Point"}
}