{
  "type": "Feature",
  "properties": {
    "addr:full":"1/ 884 Pitwater Rd Dee Why NSW 2099",
    "addr:housenumber":"/ 884",
    "addr:postcode":"2099",
    "addr:street":"Pitwater Rd",
    "iso:country":"AU",
    "sg:address":"1/ 884 Pitwater Rd",
    "sg:city":"Dee Why",
    "sg:classifiers":[
        {
            "category":"Professional",
            "subcategory":"Computer Services",
            "type":"Services"
        }
    ],
    "sg:phone":"+61 2 9972 2282",
    "sg:postcode":"2099",
    "sg:province":"NSW",
    "sg:tags":[
        "repairs",
        "upgrade",
        "equipment"
    ],
    "wof:name":"AV Computers",
    "wof:placetype":"venue"
},
  "geometry": {"coordinates":[151.28639221200001,-33.7531166077],"type":"Point"}
}