{
  "type": "Feature",
  "properties": {
    "addr:full":"358 Brunswick Rd Brunswick VIC 3056",
    "addr:housenumber":"358",
    "addr:postcode":"3056",
    "addr:street":"Brunswick Rd",
    "iso:country":"AU",
    "sg:address":"358 Brunswick Rd",
    "sg:city":"Brunswick",
    "sg:classifiers":[
        {
            "category":"Building & Trades",
            "subcategory":"Equipment Rental",
            "type":"Services"
        }
    ],
    "sg:phone":"+61 3 9380 2410",
    "sg:postcode":"3056",
    "sg:province":"VIC",
    "sg:tags":[
        "brick",
        "production",
        "supply"
    ],
    "wof:name":"JTB Machinery Brokers & Design Pty Ltd",
    "wof:placetype":"venue"
},
  "geometry": {"coordinates":[144.94900512699999,-37.7757835388],"type":"Point"}
}