{
  "type": "Feature",
  "properties": {
    "addr:full":"Unit 3/ 8 Chingford St Fairfield VIC 3078",
    "addr:housenumber":"8",
    "addr:postcode":"3078",
    "addr:street":"Chingford St",
    "iso:country":"AU",
    "sg:address":"Unit 3/ 8 Chingford St",
    "sg:city":"Fairfield",
    "sg:classifiers":[
        {
            "category":"Retail",
            "subcategory":"Auto Repair",
            "type":"Services"
        }
    ],
    "sg:phone":"+61 3 9486 8444",
    "sg:postcode":"3078",
    "sg:province":"VIC",
    "sg:tags":[
        "repairer",
        "motor",
        "engineer"
    ],
    "wof:name":"Enhanced Motor Works",
    "wof:placetype":"venue"
},
  "geometry": {"coordinates":[145.02642822300001,-37.7698898315],"type":"Point"}
}