{
  "type": "Feature",
  "properties": {
    "addr:full":"Barron Falls Rd Kuranda QLD 4872",
    "addr:postcode":"4872",
    "addr:street":"Falls Rd",
    "iso:country":"AU",
    "sg:address":"Barron Falls Rd",
    "sg:city":"Kuranda",
    "sg:classifiers":[
        {
            "category":"Building & Trades",
            "subcategory":"Construction",
            "type":"Services"
        }
    ],
    "sg:phone":"+61 414 683 244",
    "sg:postcode":"4872",
    "sg:province":"QLD",
    "sg:tags":[
        "joiner",
        "carpenter"
    ],
    "wof:name":"Carpenter & Home Maintenance Service",
    "wof:placetype":"venue"
},
  "geometry": {"coordinates":[145.54989624000001,-17.1685447693],"type":"Point"}
}