{
  "type": "Feature",
  "properties": {
    "addr:full":"5 Johnston Crt Kyneton VIC 3444",
    "addr:housenumber":"5",
    "addr:postcode":"3444",
    "addr:street":"Johnston Crt",
    "iso:country":"AU",
    "sg:address":"5 Johnston Crt",
    "sg:city":"Kyneton",
    "sg:classifiers":[
        {
            "category":"Retail",
            "subcategory":"Auto Repair",
            "type":"Services"
        }
    ],
    "sg:phone":"+61 3 5422 7290",
    "sg:postcode":"3444",
    "sg:province":"VIC",
    "sg:tags":[
        "engine",
        "reconditioning"
    ],
    "wof:name":"D.R.S. Motors",
    "wof:placetype":"venue"
},
  "geometry": {"coordinates":[144.456298828,-37.2407989502],"type":"Point"}
}