{
  "type": "Feature",
  "properties": {
    "iso:country":"AU",
    "sg:address":"256 Peel St",
    "sg:city":"Tamworth",
    "sg:classifiers":[
        {
            "category":"Personal",
            "subcategory":"Beauty Salon",
            "type":"Services"
        }
    ],
    "sg:phone":"+61 2 6766 6237",
    "sg:postcode":"2340",
    "sg:province":"NSW",
    "sg:tags":[
        "hairdresser"
    ],
    "wof:name":"Aphrodite Skin, Body and Hair Care",
    "wof:placetype":"venue"
},
  "geometry": {"coordinates":[150.92788696299999,-31.088300705],"type":"Point"}
}