{
  "type": "Feature",
  "properties": {
    "iso:country":"AU",
    "sg:address":"35 Coolangatta Ave",
    "sg:city":"Elanora Heights",
    "sg:classifiers":[
        {
            "category":"Health Services",
            "subcategory":"Health Practitioner",
            "type":"Services"
        }
    ],
    "sg:phone":"+61 2 9970 5530",
    "sg:postcode":"2101",
    "sg:province":"NSW",
    "sg:tags":[
        "acupuncture"
    ],
    "wof:name":"Martin Morrisey",
    "wof:placetype":"venue"
},
  "geometry": {"coordinates":[151.278717,-33.704735],"type":"Point"}
}