{
  "type": "Feature",
  "properties": {
    "iso:country":"AU",
    "sg:address":"4/ 7 Bourke St",
    "sg:city":"Tamworth",
    "sg:classifiers":[
        {
            "category":"Professional",
            "subcategory":"Business Services",
            "type":"Services"
        }
    ],
    "sg:phone":"+61 2 6766 6266",
    "sg:postcode":"2340",
    "sg:province":"NSW",
    "sg:tags":[
        "drafting"
    ],
    "wof:name":"arkidraft by kj",
    "wof:placetype":"venue"
},
  "geometry": {"coordinates":[150.927001953,-31.0888538361],"type":"Point"}
}