{
  "type": "Feature",
  "properties": {
    "iso:country":"AU",
    "sg:address":"63 Pigott St",
    "sg:city":"Dulwich Hill",
    "sg:classifiers":[
        {
            "category":"Shopping",
            "subcategory":"Bicycles & Sporting Goods",
            "type":"Retail Goods"
        }
    ],
    "sg:phone":"+61 2 9569 8909",
    "sg:postcode":"2203",
    "sg:province":"NSW",
    "sg:tags":[
        "dance",
        "accessory",
        "wear",
        "supply"
    ],
    "wof:name":"Bellydance Ileana",
    "wof:placetype":"venue"
},
  "geometry": {"coordinates":[151.140442,-33.900497],"type":"Point"}
}