{
  "type": "Feature",
  "properties": {
    "addr:full":"PO Box 317 Ormeau QLD 4208",
    "addr:postcode":"4208",
    "iso:country":"AU",
    "sg:address":"PO Box 317",
    "sg:city":"Ormeau",
    "sg:classifiers":[
        {
            "category":"Retail",
            "subcategory":"Driving School",
            "type":"Services"
        }
    ],
    "sg:phone":"+61 1300 551 277",
    "sg:postcode":"4208",
    "sg:province":"QLD",
    "sg:tags":[
        "equipment",
        "pile",
        "contractor"
    ],
    "wof:name":"Ausipile Contracting Pty Ltd",
    "wof:placetype":"venue"
},
  "geometry": {"coordinates":[153.244216919,-27.7652397156],"type":"Point"}
}