{
  "type": "Feature",
  "properties": {
    "addr:full":"PO Box 4047 Wyongah NSW 2259",
    "addr:postcode":"2259",
    "iso:country":"AU",
    "sg:address":"PO Box 4047",
    "sg:city":"Wyongah",
    "sg:classifiers":[
        {
            "category":"Home & Garden",
            "subcategory":"Building Materials",
            "type":"Retail Goods"
        }
    ],
    "sg:phone":"+61 2 4392 4664",
    "sg:postcode":"2259",
    "sg:province":"NSW",
    "sg:tags":[
        "lawn",
        "cutting",
        "maintenance"
    ],
    "wof:name":"Lakeside Lawns & Gardens",
    "wof:placetype":"venue"
},
  "geometry": {"coordinates":[151.48989868199999,-33.2701683044],"type":"Point"}
}