{
  "type": "Feature",
  "properties": {
    "addr:full":"418- 420 Winter St Ballarat VIC 3350",
    "addr:housenumber":"420",
    "addr:postcode":"3350",
    "addr:street":"Winter St",
    "iso:country":"AU",
    "sg:address":"418- 420 Winter St",
    "sg:city":"Ballarat",
    "sg:classifiers":[
        {
            "category":"Wholesale",
            "subcategory":"Machinery & Supplies",
            "type":"Manufacturing & Wholesale Goods"
        }
    ],
    "sg:phone":"+61 3 5334 2770",
    "sg:postcode":"3350",
    "sg:province":"VIC",
    "sg:tags":[
        "agricultural"
    ],
    "wof:name":"Munro Engineers",
    "wof:placetype":"venue"
},
  "geometry": {"coordinates":[143.813354492,-37.5680885315],"type":"Point"}
}