{
  "type": "Feature",
  "properties": {
    "addr:full":"117 Eglinton St Kew VIC 3101",
    "addr:housenumber":"117",
    "addr:postcode":"3101",
    "addr:street":"Eglinton",
    "iso:country":"AU",
    "sg:address":"117 Eglinton St",
    "sg:city":"Kew",
    "sg:classifiers":[
        {
            "category":"Retail",
            "subcategory":"Auto Rental",
            "type":"Services"
        }
    ],
    "sg:phone":"+61 402 996 697",
    "sg:postcode":"3101",
    "sg:province":"VIC",
    "sg:tags":[
        "car",
        "wedding"
    ],
    "wof:name":"C & M Wedding Cars",
    "wof:placetype":"venue"
},
  "geometry": {"coordinates":[145.041503906,-37.8005104065],"type":"Point"}
}