{
  "type": "Feature",
  "properties": {
    "addr:full":"1853 Midland Hwy Bagdad TAS 7030",
    "addr:housenumber":"1853",
    "addr:postcode":"7030",
    "addr:street":"Midland Hwy",
    "iso:country":"AU",
    "sg:address":"1853 Midland Hwy",
    "sg:city":"Bagdad",
    "sg:classifiers":[
        {
            "category":"Retail",
            "subcategory":"Auto Repair",
            "type":"Services"
        }
    ],
    "sg:phone":"+61 3 6268 6616",
    "sg:postcode":"7030",
    "sg:province":"TAS",
    "sg:tags":[
        "repairer",
        "motor",
        "engineer"
    ],
    "wof:name":"Bagdad Automotive",
    "wof:placetype":"venue"
},
  "geometry": {"coordinates":[147.22000122099999,-42.6031608582],"type":"Point"}
}