{
  "type": "Feature",
  "properties": {
    "iso:country":"AU",
    "sg:address":"Unit 2/ 77 Pickles St",
    "sg:city":"Port Melbourne",
    "sg:classifiers":[
        {
            "category":"Professional",
            "subcategory":"Management & Consulting",
            "type":"Services"
        }
    ],
    "sg:phone":"+61 3 9384 1855",
    "sg:postcode":"3207",
    "sg:province":"VIC",
    "sg:tags":[
        "consultant"
    ],
    "wof:name":"A Smart Quality Associates Pty Ltd",
    "wof:placetype":"venue"
},
  "geometry": {"coordinates":[144.945602,-37.842613],"type":"Point"}
}