{
  "type": "Feature",
  "properties": {
    "addr:full":"PO Box 270 Welshpool WA 6106",
    "addr:postcode":"6106",
    "iso:country":"AU",
    "sg:address":"PO Box 270",
    "sg:city":"Welshpool",
    "sg:classifiers":[
        {
            "category":"Manufacturing",
            "subcategory":"Retail Goods",
            "type":"Manufacturing & Wholesale Goods"
        }
    ],
    "sg:phone":"+61 1800 356 771",
    "sg:postcode":"6106",
    "sg:province":"WA",
    "sg:tags":[
        "merchant",
        "pump",
        "mfrs"
    ],
    "wof:name":"Wellmaster Hose (Australia)",
    "wof:placetype":"venue"
},
  "geometry": {"coordinates":[115.946907044,-31.9927997589],"type":"Point"}
}