{
  "type": "Feature",
  "properties": {
    "addr:full":"Shop R2, 10 D Market City 9- 13 Hay St Haymarket NSW 2000",
    "addr:housenumber":"10 d;13",
    "addr:postcode":"2000",
    "addr:street":"R2;Market City 9;Hay St",
    "iso:country":"AU",
    "sg:address":"Shop R2, 10 D Market City 9- 13 Hay St",
    "sg:city":"Haymarket",
    "sg:classifiers":[
        {
            "category":"Shopping",
            "subcategory":"Clothing, Apparel, & Fashions",
            "type":"Retail Goods"
        }
    ],
    "sg:phone":"+61 2 9281 8541",
    "sg:postcode":"2000",
    "sg:province":"NSW",
    "sg:tags":[
        "lady",
        "wear"
    ],
    "wof:name":"Sisco",
    "wof:placetype":"venue"
},
  "geometry": {"coordinates":[151.20359802199999,-33.8795166016],"type":"Point"}
}