{
  "type": "Feature",
  "properties": {
    "addr:full":"52 Arthur St Roma QLD 4455",
    "addr:housenumber":"52",
    "addr:postcode":"4455",
    "addr:street":"Arthur St",
    "iso:country":"AU",
    "sg:address":"52 Arthur St",
    "sg:city":"Roma",
    "sg:classifiers":[
        {
            "category":"Health Services",
            "subcategory":"Doctor",
            "type":"Services"
        }
    ],
    "sg:phone":"+61 7 4622 4876",
    "sg:postcode":"4455",
    "sg:province":"QLD",
    "sg:tags":[
        "nurse",
        "nursing"
    ],
    "wof:name":"Spiritus Care Services",
    "wof:placetype":"venue"
},
  "geometry": {"coordinates":[148.789993286,-26.5701503754],"type":"Point"}
}