{
  "type": "Feature",
  "properties": {
    "addr:full":"7 Darling St Abbotsbury NSW 2176",
    "addr:housenumber":"7",
    "addr:postcode":"2176",
    "addr:street":"Darling St",
    "iso:country":"AU",
    "sg:address":"7 Darling St",
    "sg:city":"Abbotsbury",
    "sg:classifiers":[
        {
            "category":"Health Services",
            "subcategory":"Health Practitioner",
            "type":"Services"
        }
    ],
    "sg:phone":"+61 2 9221 0146",
    "sg:postcode":"2176",
    "sg:province":"NSW",
    "sg:tags":[
        "psychologist"
    ],
    "wof:name":"Legg Colin",
    "wof:placetype":"venue"
},
  "geometry": {"coordinates":[150.86065673799999,-33.8709144592],"type":"Point"}
}