{
  "type": "Feature",
  "properties": {
    "addr:full":"Shop 1 43 Garfield Rd Riverstone NSW 2765",
    "addr:housenumber":"shop;43",
    "addr:postcode":"2765",
    "addr:street":"Garfield Rd",
    "iso:country":"AU",
    "sg:address":"Shop 1 43 Garfield Rd",
    "sg:city":"Riverstone",
    "sg:classifiers":[
        {
            "category":"Health Services",
            "subcategory":"Dentist",
            "type":"Services"
        }
    ],
    "sg:phone":"+61 2 9627 1002",
    "sg:postcode":"2765",
    "sg:province":"NSW",
    "wof:name":"Sundin W S",
    "wof:placetype":"venue"
},
  "geometry": {"coordinates":[150.863113403,-33.6784172058],"type":"Point"}
}