{
  "type": "Feature",
  "properties": {
    "addr:full":"57 President Rd St Albans VIC 3021",
    "addr:housenumber":"57",
    "addr:postcode":"3021",
    "addr:street":"President Rd",
    "iso:country":"AU",
    "sg:address":"57 President Rd",
    "sg:city":"St Albans",
    "sg:classifiers":[
        {
            "category":"Retail",
            "subcategory":"Auto Rental",
            "type":"Services"
        }
    ],
    "sg:phone":"+61 3 9367 4617",
    "sg:postcode":"3021",
    "sg:province":"VIC",
    "sg:tags":[
        "car",
        "wedding"
    ],
    "wof:name":"A. Las Vegas Convertibles",
    "wof:placetype":"venue"
},
  "geometry": {"coordinates":[144.77311700000001,-37.748325],"type":"Point"}
}