{
  "type": "Feature",
  "properties": {
    "addr:full":"172 Beaudesert Rd Moorooka QLD 4105",
    "addr:housenumber":"172",
    "addr:postcode":"4105",
    "addr:street":"Beaudesert Rd",
    "iso:country":"AU",
    "sg:address":"172 Beaudesert Rd",
    "sg:city":"Moorooka",
    "sg:classifiers":[
        {
            "category":"Banks & Credit Unions",
            "subcategory":"Financial Services",
            "type":"Services"
        }
    ],
    "sg:phone":"+61 7 3892 3522",
    "sg:postcode":"4105",
    "sg:province":"QLD",
    "sg:tags":[
        "annuity",
        "rollover",
        "superannuation",
        "consultant"
    ],
    "wof:name":"Dunlops Super Strategies Pty Ltd",
    "wof:placetype":"venue"
},
  "geometry": {"coordinates":[153.02470398,-27.5322933197],"type":"Point"}
}