{
  "type": "Feature",
  "properties": {
    "addr:full":"2/ 27 Hope St Ermington NSW 2115",
    "addr:housenumber":"/ 27",
    "addr:postcode":"2115",
    "addr:street":"Hope St",
    "iso:country":"AU",
    "sg:address":"2/ 27 Hope St",
    "sg:city":"Ermington",
    "sg:classifiers":[
        {
            "category":"Retail",
            "subcategory":"Auto Repair",
            "type":"Services"
        }
    ],
    "sg:phone":"+61 2 9874 7211",
    "sg:postcode":"2115",
    "sg:province":"NSW",
    "sg:tags":[
        "repairer",
        "motor",
        "engineer"
    ],
    "wof:name":"Mini Classic",
    "wof:placetype":"venue"
},
  "geometry": {"coordinates":[151.066238403,-33.8153305054],"type":"Point"}
}