{
  "type": "Feature",
  "properties": {
    "iso:country":"AU",
    "sg:address":"PO Box 308",
    "sg:city":"Sorrento",
    "sg:classifiers":[
        {
            "category":"Building & Trades",
            "subcategory":"Plumbing",
            "type":"Services"
        }
    ],
    "sg:phone":"+61 428 559 541",
    "sg:postcode":"3943",
    "sg:province":"VIC",
    "sg:tags":[
        "plumber",
        "gasfitters"
    ],
    "wof:name":"Hutchinson Steve",
    "wof:placetype":"venue"
},
  "geometry": {"coordinates":[144.742431641,-38.3386688232],"type":"Point"}
}