{
  "type": "Feature",
  "properties": {
    "addr:full":"105 Quayle Rd Wandin North VIC 3139",
    "addr:housenumber":"105",
    "addr:postcode":"3139",
    "addr:street":"Quayle Rd",
    "iso:country":"AU",
    "sg:address":"105 Quayle Rd",
    "sg:city":"Wandin North",
    "sg:classifiers":[
        {
            "category":"Cafe",
            "type":"Food & Drink"
        }
    ],
    "sg:phone":"+61 3 5964 3621",
    "sg:postcode":"3139",
    "sg:province":"VIC",
    "wof:name":"Purple Haze Cafe",
    "wof:placetype":"venue"
},
  "geometry": {"coordinates":[145.43850707999999,-37.7894058228],"type":"Point"}
}