{
  "type": "Feature",
  "properties": {
    "iso:country":"AU",
    "sg:address":"288 Wehla-Kingower Rd",
    "sg:city":"Rheola",
    "sg:classifiers":[
        {
            "category":"Farming",
            "subcategory":"Vineyard",
            "type":"Manufacturing & Wholesale Goods"
        }
    ],
    "sg:phone":"+61 3 5438 8292",
    "sg:postcode":"3517",
    "sg:province":"VIC",
    "sg:tags":[
        "winery"
    ],
    "wof:name":"Kangderaar Vineyard",
    "wof:placetype":"venue"
},
  "geometry": {"coordinates":[143.80664100000001,-36.571247],"type":"Point"}
}