{
  "type": "Feature",
  "properties": {
    "iso:country":"AU",
    "sg:address":"Unit 5/ 134 McKinnon Rd",
    "sg:city":"Berrimah",
    "sg:classifiers":[
        {
            "category":"Retail",
            "subcategory":"Auto Repair",
            "type":"Services"
        }
    ],
    "sg:phone":"+61 8 8932 4124",
    "sg:postcode":"0828",
    "sg:province":"NT",
    "sg:tags":[
        "beater",
        "painter",
        "panel"
    ],
    "wof:name":"Darwin Panel Works",
    "wof:placetype":"venue"
},
  "geometry": {"coordinates":[130.96632385300001,-12.4615049362],"type":"Point"}
}