{
  "type": "Feature",
  "properties": {
    "addr:full":"1-3 Doveton Ave Doveton VIC 3177",
    "addr:housenumber":"1-3",
    "addr:postcode":"3177",
    "addr:street":"Doveton Ave",
    "iso:country":"AU",
    "sg:address":"1-3 Doveton Ave",
    "sg:city":"Doveton",
    "sg:classifiers":[
        {
            "category":"Personal",
            "subcategory":"Massage",
            "type":"Services"
        }
    ],
    "sg:phone":"+61 412 892 009",
    "sg:postcode":"3177",
    "sg:province":"VIC",
    "sg:tags":[
        "therapy"
    ],
    "wof:name":"Mark Ladd Remedial Massage",
    "wof:placetype":"venue"
},
  "geometry": {"coordinates":[145.24942016599999,-38.002872467],"type":"Point"}
}