{
  "type": "Feature",
  "properties": {
    "iso:country":"AU",
    "sg:address":"92 Young St",
    "sg:city":"Frankston",
    "sg:classifiers":[
        {
            "category":"Manufacturing",
            "subcategory":"Jewelry",
            "type":"Manufacturing & Wholesale Goods"
        }
    ],
    "sg:phone":"+61 3 9783 6226",
    "sg:postcode":"3199",
    "sg:province":"VIC",
    "sg:tags":[
        "designer",
        "jewellery"
    ],
    "wof:name":"Anny's Manufacturing Jewellers",
    "wof:placetype":"venue"
},
  "geometry": {"coordinates":[145.12503051799999,-38.1438827515],"type":"Point"}
}