{
  "type": "Feature",
  "properties": {
    "addr:full":"381 Riley St Surry Hills NSW 2010",
    "addr:housenumber":"381",
    "addr:postcode":"2010",
    "addr:street":"Riley St",
    "iso:country":"AU",
    "sg:address":"381 Riley St",
    "sg:city":"Surry Hills",
    "sg:classifiers":[
        {
            "category":"Professional",
            "subcategory":"Engineering",
            "type":"Services"
        }
    ],
    "sg:phone":"+61 2 9310 2800",
    "sg:postcode":"2010",
    "sg:province":"NSW",
    "sg:tags":[
        "consulting",
        "engineer"
    ],
    "wof:name":"Future Engineering",
    "wof:placetype":"venue"
},
  "geometry": {"coordinates":[151.21255493199999,-33.8849945068],"type":"Point"}
}