{
  "type": "Feature",
  "properties": {
    "iso:country":"AU",
    "sg:address":"PO Box 19",
    "sg:city":"Yeoval",
    "sg:classifiers":[
        {
            "category":"Farming",
            "subcategory":"Farm & Veterinary Services",
            "type":"Manufacturing & Wholesale Goods"
        }
    ],
    "sg:phone":"+61 427 045 725",
    "sg:postcode":"2868",
    "sg:province":"NSW",
    "sg:tags":[
        "agricultural",
        "advisory"
    ],
    "wof:name":"Rural Solutions",
    "wof:placetype":"venue"
},
  "geometry": {"coordinates":[148.64845299999999,-32.753819],"type":"Point"}
}