{
  "type": "Feature",
  "properties": {
    "iso:country":"AU",
    "sg:address":"240 Smith St",
    "sg:city":"Collingwood",
    "sg:classifiers":[
        {
            "category":"Ice Cream",
            "type":"Food & Drink"
        }
    ],
    "sg:phone":"+61 3 9417 7666",
    "sg:postcode":"3066",
    "sg:province":"VIC",
    "sg:tags":[
        "specialised",
        "fitting",
        "lady",
        "wear"
    ],
    "wof:name":"Pretty Fit Fashion",
    "wof:placetype":"venue"
},
  "geometry": {"coordinates":[144.983917236,-37.8018951416],"type":"Point"}
}