{
  "type": "Feature",
  "properties": {
    "iso:country":"AU",
    "sg:address":"61 Dalkeith Rd",
    "sg:city":"Seaford Rise",
    "sg:classifiers":[
        {
            "category":"Cafe",
            "type":"Food & Drink"
        }
    ],
    "sg:phone":"+61 8 8327 1266",
    "sg:postcode":"5169",
    "sg:province":"SA",
    "wof:name":"Kia Orana Cafe",
    "wof:placetype":"venue"
},
  "geometry": {"coordinates":[138.484664917,-35.2016525269],"type":"Point"}
}