{
  "type": "Feature",
  "properties": {
    "iso:country":"AU",
    "sg:address":"43 Downard St",
    "sg:city":"Braeside",
    "sg:classifiers":[
        {
            "category":"Professional",
            "type":"Services"
        }
    ],
    "sg:phone":"+61 3 9580 5333",
    "sg:postcode":"3195",
    "sg:province":"VIC",
    "sg:tags":[
        "shop",
        "fitting"
    ],
    "wof:name":"Super Glass",
    "wof:placetype":"venue"
},
  "geometry": {"coordinates":[145.11076355,-37.9935302734],"type":"Point"}
}