{
  "type": "Feature",
  "properties": {
    "addr:full":"10 Pembury Rd Minto NSW 2566",
    "addr:housenumber":"10",
    "addr:postcode":"2566",
    "addr:street":"Pembury Rd",
    "iso:country":"AU",
    "sg:address":"10 Pembury Rd",
    "sg:city":"Minto",
    "sg:classifiers":[
        {
            "category":"Professional",
            "subcategory":"Engineering",
            "type":"Services"
        }
    ],
    "sg:phone":"+61 2 9603 9330",
    "sg:postcode":"2566",
    "sg:province":"NSW",
    "sg:tags":[
        "engineer"
    ],
    "wof:name":"C & B Engineering",
    "wof:placetype":"venue"
},
  "geometry": {"coordinates":[150.83360290499999,-34.0354118347],"type":"Point"}
}