{
  "type": "Feature",
  "properties": {
    "iso:country":"AU",
    "sg:address":"25 Hewish Rd",
    "sg:city":"Croydon",
    "sg:classifiers":[
        {
            "category":"Banks & Credit Unions",
            "subcategory":"Financial Services",
            "type":"Services"
        }
    ],
    "sg:phone":"+61 402 217 182",
    "sg:postcode":"3136",
    "sg:province":"VIC",
    "sg:tags":[
        "finance",
        "motor",
        "vehicle"
    ],
    "wof:name":"Transglobal Lending Services",
    "wof:placetype":"venue"
},
  "geometry": {"coordinates":[145.28434753400001,-37.7962341309],"type":"Point"}
}