{
  "type": "Feature",
  "properties": {
    "iso:country":"AU",
    "sg:address":"22 Darling St",
    "sg:city":"Medindie",
    "sg:classifiers":[
        {
            "category":"Professional",
            "subcategory":"Accounting & Tax Preparation",
            "type":"Services"
        }
    ],
    "sg:phone":"+61 8 8344 1890",
    "sg:postcode":"5081",
    "sg:province":"SA",
    "sg:tags":[
        "accountant",
        "auditor"
    ],
    "wof:name":"Wood D V",
    "wof:placetype":"venue"
},
  "geometry": {"coordinates":[138.601318359,-34.8974685669],"type":"Point"}
}