{
  "type": "Feature",
  "properties": {
    "iso:country":"AU",
    "sg:address":"13 Cooloongatta Rd",
    "sg:city":"Camberwell",
    "sg:classifiers":[
        {
            "category":"Professional",
            "subcategory":"Business Services",
            "type":"Services"
        }
    ],
    "sg:phone":"+61 3 9888 6522",
    "sg:postcode":"3124",
    "sg:province":"VIC",
    "sg:tags":[
        "processing",
        "word"
    ],
    "wof:name":"Save Secretarial Service",
    "wof:placetype":"venue"
},
  "geometry": {"coordinates":[145.07574462900001,-37.835521698],"type":"Point"}
}