{
  "type": "Feature",
  "properties": {
    "addr:full":"Maryland Drv Maryland NSW 2287",
    "addr:postcode":"2287",
    "addr:street":"Maryland Drv",
    "iso:country":"AU",
    "sg:address":"Maryland Drv",
    "sg:city":"Maryland",
    "sg:classifiers":[
        {
            "category":"Education",
            "subcategory":"School",
            "type":"Public Place"
        }
    ],
    "sg:phone":"+61 2 4955 6644",
    "sg:postcode":"2287",
    "sg:province":"NSW",
    "sg:tags":[
        "state",
        "-",
        "nsw"
    ],
    "wof:name":"Glendore Public School",
    "wof:placetype":"venue"
},
  "geometry": {"coordinates":[151.66253662099999,-32.8815956116],"type":"Point"}
}