{
  "type": "Feature",
  "properties": {
    "iso:country":"AU",
    "sg:address":"2/ 68 Melrose St",
    "sg:city":"Balwyn",
    "sg:classifiers":[
        {
            "category":"Building & Trades",
            "subcategory":"Cleaning & Sanitation",
            "type":"Services"
        }
    ],
    "sg:phone":"+61 411 885 594",
    "sg:postcode":"3103",
    "sg:province":"VIC",
    "sg:tags":[
        "commercial",
        "maintenance"
    ],
    "wof:name":"MFJ Painters & Decorators",
    "wof:placetype":"venue"
},
  "geometry": {"coordinates":[145.115600586,-37.8114013672],"type":"Point"}
}