{
  "type": "Feature",
  "properties": {
    "addr:full":"Cemetery La Bridgewater VIC 3516",
    "addr:postcode":"3516",
    "iso:country":"AU",
    "sg:address":"Cemetery La",
    "sg:city":"Bridgewater",
    "sg:classifiers":[
        {
            "category":"Home & Garden",
            "subcategory":"Garden Supply",
            "type":"Retail Goods"
        }
    ],
    "sg:phone":"+61 3 5437 3174",
    "sg:postcode":"3516",
    "sg:province":"VIC",
    "sg:tags":[
        "fertilizer"
    ],
    "wof:name":"Wheelhouse Group",
    "wof:placetype":"venue"
},
  "geometry": {"coordinates":[143.95161400000001,-36.609058],"type":"Point"}
}