{
  "type": "Feature",
  "properties": {
    "addr:full":"53a Glenburnie Rd Mitcham VIC 3132",
    "addr:housenumber":"53a",
    "addr:postcode":"3132",
    "addr:street":"Glenburnie Rd",
    "iso:country":"AU",
    "sg:address":"53a Glenburnie Rd",
    "sg:city":"Mitcham",
    "sg:classifiers":[
        {
            "category":"Education",
            "subcategory":"Special Training",
            "type":"Public Place"
        }
    ],
    "sg:phone":"+61 3 9872 6474",
    "sg:postcode":"3132",
    "sg:province":"VIC",
    "sg:tags":[
        "development"
    ],
    "wof:name":"Centre For Professional Coaching",
    "wof:placetype":"venue"
},
  "geometry": {"coordinates":[145.20069885300001,-37.8305664062],"type":"Point"}
}