{
  "type": "Feature",
  "properties": {
    "iso:country":"AU",
    "sg:address":"Ipswich Grande Plaza + 87 Cnr Brisbane & East Sts",
    "sg:city":"Ipswich",
    "sg:classifiers":[
        {
            "category":"Personal",
            "subcategory":"Beauty Salon",
            "type":"Services"
        }
    ],
    "sg:phone":"+61 7 3812 0774",
    "sg:postcode":"4305",
    "sg:province":"QLD",
    "sg:tags":[
        "hairdresser"
    ],
    "wof:name":"Ab Fab Hair Design",
    "wof:placetype":"venue"
},
  "geometry": {"coordinates":[152.76527404800001,-27.6164894104],"type":"Point"}
}