{
  "type": "Feature",
  "properties": {
    "addr:full":"126 Jellicoe St Toowoomba QLD 4350",
    "addr:housenumber":"126",
    "addr:postcode":"4350",
    "addr:street":"Jellicoe St",
    "iso:country":"AU",
    "sg:address":"126 Jellicoe St",
    "sg:city":"Toowoomba",
    "sg:classifiers":[
        {
            "category":"Autos & Motor Vehicles",
            "subcategory":"Auto Supplies",
            "type":"Retail Goods"
        }
    ],
    "sg:phone":"+61 7 4638 4875",
    "sg:postcode":"4350",
    "sg:province":"QLD",
    "sg:tags":[
        "part",
        "cycles",
        "accessory"
    ],
    "wof:name":"Straight N Narrow Hogs Toowoomba",
    "wof:placetype":"venue"
},
  "geometry": {"coordinates":[151.942429,-27.54434],"type":"Point"}
}