{
  "type": "Feature",
  "properties": {
    "addr:full":"Unit 2/6- 8 Wingate Rd McGraths Hill NSW 2756",
    "addr:housenumber":"8",
    "addr:postcode":"2756",
    "addr:street":"Wingate Rd",
    "iso:country":"AU",
    "sg:address":"Unit 2/6- 8 Wingate Rd",
    "sg:city":"McGraths Hill",
    "sg:classifiers":[
        {
            "category":"Home & Garden",
            "subcategory":"Garden Supply",
            "type":"Retail Goods"
        }
    ],
    "sg:phone":"+61 2 4577 4522",
    "sg:postcode":"2756",
    "sg:province":"NSW",
    "sg:tags":[
        "statuary",
        "fountains",
        "sundial"
    ],
    "sg:website":"http://www.gardenelements.com.au",
    "wof:name":"Garden Elements",
    "wof:placetype":"venue"
},
  "geometry": {"coordinates":[150.83552551299999,-33.6217041016],"type":"Point"}
}