{
  "type": "Feature",
  "properties": {
    "addr:full":"8 Boronia Rd Vermont VIC 3133",
    "addr:housenumber":"8",
    "addr:postcode":"3133",
    "addr:street":"Boronia Rd",
    "iso:country":"AU",
    "sg:address":"8 Boronia Rd",
    "sg:city":"Vermont",
    "sg:classifiers":[
        {
            "category":"Shopping",
            "subcategory":"Clothing, Apparel, & Fashions",
            "type":"Retail Goods"
        }
    ],
    "sg:phone":"+61 3 9873 4016",
    "sg:postcode":"3133",
    "sg:province":"VIC",
    "sg:tags":[
        "recycled",
        "clothing"
    ],
    "wof:name":"Vermont Opportunity Shop",
    "wof:placetype":"venue"
},
  "geometry": {"coordinates":[145.19566345199999,-37.8367271423],"type":"Point"}
}