{
  "type": "Feature",
  "properties": {
    "iso:country":"AU",
    "sg:address":"Shp 5/ 183 Beaudesert Rd",
    "sg:city":"Moorooka",
    "sg:classifiers":[
        {
            "category":"Shopping",
            "subcategory":"Discount & Variety Stores",
            "type":"Retail Goods"
        }
    ],
    "sg:phone":"+61 7 3892 7038",
    "sg:postcode":"4105",
    "sg:province":"QLD",
    "sg:tags":[
        "shop",
        "adult"
    ],
    "wof:name":"Adult Temptations",
    "wof:placetype":"venue"
},
  "geometry": {"coordinates":[153.02439880399999,-27.5325126648],"type":"Point"}
}