{
  "type": "Feature",
  "properties": {
    "addr:full":"2/ 54 Belmore St Yarrawonga VIC 3730",
    "addr:housenumber":"/ 54",
    "addr:postcode":"3730",
    "addr:street":"Belmore St",
    "iso:country":"AU",
    "sg:address":"2/ 54 Belmore St",
    "sg:city":"Yarrawonga",
    "sg:classifiers":[
        {
            "category":"Health Services",
            "subcategory":"Chiropractor",
            "type":"Services"
        }
    ],
    "sg:phone":"+61 3 5744 3848",
    "sg:postcode":"3730",
    "sg:province":"VIC",
    "wof:name":"Wheaton Chiropractic",
    "wof:placetype":"venue"
},
  "geometry": {"coordinates":[146.00424194300001,-36.0111885071],"type":"Point"}
}