{
  "type": "Feature",
  "properties": {
    "addr:full":"3/ 96 Phillip St Parramatta NSW 2150",
    "addr:housenumber":"/ 96",
    "addr:postcode":"2150",
    "addr:street":"Phillip St",
    "iso:country":"AU",
    "sg:address":"3/ 96 Phillip St",
    "sg:city":"Parramatta",
    "sg:classifiers":[
        {
            "category":"Banks & Credit Unions",
            "subcategory":"Financial Services",
            "type":"Services"
        }
    ],
    "sg:phone":"+61 2 9635 6655",
    "sg:postcode":"2150",
    "sg:province":"NSW",
    "sg:tags":[
        "planning"
    ],
    "wof:name":"Axis Financial Advisers",
    "wof:placetype":"venue"
},
  "geometry": {"coordinates":[150.96473693900001,-33.8523483276],"type":"Point"}
}