{
  "type": "Feature",
  "properties": {
    "iso:country":"AU",
    "sg:address":"Wharf St",
    "sg:city":"Port Douglas",
    "sg:classifiers":[
        {
            "category":"Recreation",
            "subcategory":"Marina",
            "type":"Entertainment"
        }
    ],
    "sg:phone":"+61 7 4099 5775",
    "sg:postcode":"4877",
    "sg:province":"QLD",
    "wof:name":"Marina Mirage",
    "wof:placetype":"venue"
},
  "geometry": {"coordinates":[145.46182250999999,-16.4836177826],"type":"Point"}
}