{
  "type": "Feature",
  "properties": {
    "addr:full":"Lot1/ Pine St Barcaldine QLD 4725",
    "addr:postcode":"4725",
    "addr:street":"Pine St",
    "iso:country":"AU",
    "sg:address":"Lot1/ Pine St",
    "sg:city":"Barcaldine",
    "sg:classifiers":[
        {
            "category":"Professional",
            "subcategory":"Engineering",
            "type":"Services"
        }
    ],
    "sg:phone":"+61 7 4651 1173",
    "sg:postcode":"4725",
    "sg:province":"QLD",
    "sg:tags":[
        "engineer"
    ],
    "wof:name":"Barcaldine Welding Works",
    "wof:placetype":"venue"
},
  "geometry": {"coordinates":[145.281723,-23.556795],"type":"Point"}
}