{
  "type": "Feature",
  "properties": {
    "iso:country":"AU",
    "sg:address":"4 Stopford Rd",
    "sg:city":"Hove",
    "sg:classifiers":[
        {
            "category":"Professional",
            "subcategory":"Accounting & Tax Preparation",
            "type":"Services"
        }
    ],
    "sg:phone":"+61 8 8377 5178",
    "sg:postcode":"5048",
    "sg:province":"SA",
    "sg:tags":[
        "bookkeeping"
    ],
    "wof:name":"Business Angel Solutions",
    "wof:placetype":"venue"
},
  "geometry": {"coordinates":[138.523453,-35.013458],"type":"Point"}
}