{
  "type": "Feature",
  "properties": {
    "iso:country":"AU",
    "sg:address":"Unit 2/ 50 Sandringham Ave",
    "sg:city":"Thornton",
    "sg:classifiers":[
        {
            "category":"Shopping",
            "subcategory":"News",
            "type":"Retail Goods"
        }
    ],
    "sg:phone":"+61 2 4966 0000",
    "sg:postcode":"2322",
    "sg:province":"NSW",
    "sg:tags":[
        "magazine",
        "periodical"
    ],
    "wof:name":"Your Hunter Valley Wedding Planner",
    "wof:placetype":"venue"
},
  "geometry": {"coordinates":[151.63375854500001,-32.7835731506],"type":"Point"}
}