{
  "type": "Feature",
  "properties": {
    "addr:full":"2/ 8 Bonnal Rd Erina NSW 2250",
    "addr:housenumber":"/ 8",
    "addr:postcode":"2250",
    "addr:street":"Bonnal Rd",
    "iso:country":"AU",
    "sg:address":"2/ 8 Bonnal Rd",
    "sg:city":"Erina",
    "sg:classifiers":[
        {
            "category":"Retail",
            "subcategory":"Auto Repair",
            "type":"Services"
        }
    ],
    "sg:phone":"+61 2 4365 6611",
    "sg:postcode":"2250",
    "sg:province":"NSW",
    "sg:tags":[
        "repairer",
        "motor",
        "engineer"
    ],
    "wof:name":"Anthony Automotives",
    "wof:placetype":"venue"
},
  "geometry": {"coordinates":[151.38388061500001,-33.4352111816],"type":"Point"}
}