{
  "type": "Feature",
  "properties": {
    "iso:country":"AU",
    "sg:address":"11 MacIntyre La",
    "sg:city":"Yering",
    "sg:classifiers":[
        {
            "category":"Farming",
            "subcategory":"Nursery",
            "type":"Manufacturing & Wholesale Goods"
        }
    ],
    "sg:phone":"+61 3 9739 1030",
    "sg:postcode":"3770",
    "sg:province":"VIC",
    "wof:name":"Vanderklift Nurseries",
    "wof:placetype":"venue"
},
  "geometry": {"coordinates":[145.36209099999999,-37.697849],"type":"Point"}
}