{
  "type": "Feature",
  "properties": {
    "iso:country":"AU",
    "sg:address":"87 Buckley St",
    "sg:city":"Essendon",
    "sg:classifiers":[
        {
            "category":"Health Services",
            "subcategory":"Health Practitioner",
            "type":"Services"
        }
    ],
    "sg:phone":"+61 3 9372 9444",
    "sg:postcode":"3040",
    "sg:province":"VIC",
    "sg:tags":[
        "hypnotherapy"
    ],
    "wof:name":"Lea Kewish",
    "wof:placetype":"venue"
},
  "geometry": {"coordinates":[144.91848754899999,-37.7573013306],"type":"Point"}
}