{
  "type": "Feature",
  "properties": {
    "addr:full":"43 Robin Ave Sorrento WA 6020",
    "addr:housenumber":"43",
    "addr:postcode":"6020",
    "addr:street":"Robin Ave",
    "iso:country":"AU",
    "sg:address":"43 Robin Ave",
    "sg:city":"Sorrento",
    "sg:classifiers":[
        {
            "category":"Building & Trades",
            "subcategory":"Construction",
            "type":"Services"
        }
    ],
    "sg:phone":"+61 8 9448 4613",
    "sg:postcode":"6020",
    "sg:province":"WA",
    "sg:tags":[
        "roof"
    ],
    "wof:name":"J A Constructions Pty Ltd",
    "wof:placetype":"venue"
},
  "geometry": {"coordinates":[115.753463745,-31.8333854675],"type":"Point"}
}