{
  "type": "Feature",
  "properties": {
    "iso:country":"AU",
    "sg:address":"Shop 31 Alexandra Hills Shopng Cntr",
    "sg:city":"Alexandra Hills",
    "sg:classifiers":[
        {
            "category":"Shopping",
            "subcategory":"Clothing, Apparel, & Fashions",
            "type":"Retail Goods"
        }
    ],
    "sg:phone":"+61 7 3820 2375",
    "sg:postcode":"4161",
    "sg:province":"QLD",
    "sg:tags":[
        "menswear"
    ],
    "wof:name":"Ed Harry Menswear",
    "wof:placetype":"venue"
},
  "geometry": {"coordinates":[153.229370117,-27.5431003571],"type":"Point"}
}