{
  "type": "Feature",
  "properties": {
    "iso:country":"AU",
    "sg:address":"22 Robert St",
    "sg:city":"Wickham",
    "sg:classifiers":[
        {
            "category":"Building & Trades",
            "subcategory":"Cleaning & Sanitation",
            "type":"Services"
        }
    ],
    "sg:phone":"+61 2 4961 0169",
    "sg:postcode":"2293",
    "sg:province":"NSW",
    "sg:tags":[
        "commercial",
        "maintenance"
    ],
    "wof:name":"Dps Property Services Pty Ltd",
    "wof:placetype":"venue"
},
  "geometry": {"coordinates":[151.756912231,-32.9173545837],"type":"Point"}
}