{
  "type": "Feature",
  "properties": {
    "addr:full":"8-10 Forrest St Collie WA 6225",
    "addr:housenumber":"8-10",
    "addr:postcode":"6225",
    "addr:street":"Forrest St",
    "iso:country":"AU",
    "sg:address":"8-10 Forrest St",
    "sg:city":"Collie",
    "sg:classifiers":[
        {
            "category":"Retail",
            "subcategory":"Auto Repair",
            "type":"Services"
        }
    ],
    "sg:phone":"+61 8 9734 1652",
    "sg:postcode":"6225",
    "sg:province":"WA",
    "sg:tags":[
        "repairer",
        "motor",
        "engineer"
    ],
    "wof:name":"Collie Auto-Tech",
    "wof:placetype":"venue"
},
  "geometry": {"coordinates":[116.157219,-33.359634],"type":"Point"}
}