{
  "type": "Feature",
  "properties": {
    "iso:country":"AU",
    "sg:address":"Taylor St",
    "sg:city":"Pialba",
    "sg:classifiers":[
        {
            "category":"Retail",
            "subcategory":"Funeral Services",
            "type":"Services"
        }
    ],
    "sg:phone":"+61 7 4124 4883",
    "sg:postcode":"4655",
    "sg:province":"QLD",
    "sg:tags":[
        "director"
    ],
    "wof:name":"Ross Leslie G Funeral Directors",
    "wof:placetype":"venue"
},
  "geometry": {"coordinates":[152.842773,-25.28705],"type":"Point"}
}