{
  "type": "Feature",
  "properties": {
    "iso:country":"AU",
    "sg:address":"Gate 5 Lowe Rd",
    "sg:city":"Hornsby",
    "sg:classifiers":[
        {
            "category":"Travel",
            "subcategory":"Hostel",
            "type":"Entertainment"
        }
    ],
    "sg:phone":"+61 2 9482 2552",
    "sg:postcode":"2077",
    "sg:province":"NSW",
    "sg:tags":[
        "home"
    ],
    "wof:name":"Masonic Towers Hostel",
    "wof:placetype":"venue"
},
  "geometry": {"coordinates":[151.114624023,-33.7010955811],"type":"Point"}
}