{
  "type": "Feature",
  "properties": {
    "addr:full":"29 Beach St Kippa-Ring QLD 4021",
    "addr:housenumber":"29",
    "addr:postcode":"4021",
    "addr:street":"Beach St",
    "iso:country":"AU",
    "sg:address":"29 Beach St",
    "sg:city":"Kippa-Ring",
    "sg:classifiers":[
        {
            "category":"Retail",
            "subcategory":"Auto Repair",
            "type":"Services"
        }
    ],
    "sg:phone":"+61 7 3284 2311",
    "sg:postcode":"4021",
    "sg:province":"QLD",
    "sg:tags":[
        "repairer",
        "motor",
        "engineer"
    ],
    "wof:name":"Brian Swain Automotives",
    "wof:placetype":"venue"
},
  "geometry": {"coordinates":[153.09120200000001,-27.224962],"type":"Point"}
}