{
  "type": "Feature",
  "properties": {
    "addr:full":"404 Windsor Rd Vineyard NSW 2765",
    "addr:housenumber":"404",
    "addr:postcode":"2765",
    "addr:street":"Windsor Rd",
    "iso:country":"AU",
    "sg:address":"404 Windsor Rd",
    "sg:city":"Vineyard",
    "sg:classifiers":[
        {
            "category":"Farming",
            "subcategory":"Nursery",
            "type":"Manufacturing & Wholesale Goods"
        }
    ],
    "sg:phone":"+61 407 906 975",
    "sg:postcode":"2765",
    "sg:province":"NSW",
    "wof:name":"Hardy And Healthy Wholesale Nursery",
    "wof:placetype":"venue"
},
  "geometry": {"coordinates":[150.86555480999999,-33.6514892578],"type":"Point"}
}