{
  "type": "Feature",
  "properties": {
    "iso:country":"AU",
    "sg:address":"Unit 2/6 Iluka St, The Laneway, Narrabundah Shops",
    "sg:city":"Narrabundah",
    "sg:classifiers":[
        {
            "category":"Arena",
            "subcategory":"Sports Club",
            "type":"Entertainment"
        }
    ],
    "sg:phone":"+61 418 622 545",
    "sg:postcode":"2604",
    "sg:province":"ACT",
    "sg:tags":[
        "defence",
        "supply",
        "self",
        "instruction",
        "martial art"
    ],
    "wof:name":"Chris Harvey Wing Chun Kung Fu",
    "wof:placetype":"venue"
},
  "geometry": {"coordinates":[149.15415954599999,-35.3325004578],"type":"Point"}
}