{
  "type": "Feature",
  "properties": {
    "iso:country":"AU",
    "sg:address":"54 Garden St",
    "sg:city":"North Narrabeen",
    "sg:classifiers":[
        {
            "category":"Fast Food",
            "type":"Food & Drink"
        }
    ],
    "sg:phone":"+61 2 9913 9211",
    "sg:postcode":"2101",
    "sg:province":"NSW",
    "sg:tags":[
        "away",
        "take"
    ],
    "wof:name":"Thai To Go",
    "wof:placetype":"venue"
},
  "geometry": {"coordinates":[151.295639,-33.702465],"type":"Point"}
}