{
  "type": "Feature",
  "properties": {
    "iso:country":"AU",
    "sg:address":"Un 7/ 7 Jetty Rd",
    "sg:city":"Bunbury",
    "sg:classifiers":[
        {
            "category":"Education",
            "subcategory":"Special Training",
            "type":"Public Place"
        }
    ],
    "sg:phone":"+61 8 9791 8714",
    "sg:postcode":"6230",
    "sg:province":"WA",
    "sg:tags":[
        "tuition-educational"
    ],
    "wof:name":"Dyslexic Diagnostic & Irlen Clinics",
    "wof:placetype":"venue"
},
  "geometry": {"coordinates":[115.639351,-33.316029],"type":"Point"}
}