{
  "type": "Feature",
  "properties": {
    "addr:full":"129a Henley Beach Rd Mile End SA 5031",
    "addr:housenumber":"129a",
    "addr:postcode":"5031",
    "addr:street":"Henley Beach Rd",
    "iso:country":"AU",
    "sg:address":"129a Henley Beach Rd",
    "sg:city":"Mile End",
    "sg:classifiers":[
        {
            "category":"Health Services",
            "subcategory":"Chiropractor",
            "type":"Services"
        }
    ],
    "sg:phone":"+61 8 8234 5812",
    "sg:postcode":"5031",
    "sg:province":"SA",
    "wof:name":"Torrensville Chiropractic Clinic",
    "wof:placetype":"venue"
},
  "geometry": {"coordinates":[138.56544494600001,-34.9241294861],"type":"Point"}
}