{
  "type": "Feature",
  "properties": {
    "addr:full":"Unit 3, 50 Derby St Silverwater NSW 2128",
    "addr:housenumber":"50",
    "addr:postcode":"2128",
    "addr:street":"Derby St",
    "iso:country":"AU",
    "sg:address":"Unit 3, 50 Derby St",
    "sg:city":"Silverwater",
    "sg:classifiers":[
        {
            "category":"Professional",
            "subcategory":"Detective & Security Services",
            "type":"Services"
        }
    ],
    "sg:phone":"+61 1300 309 920",
    "sg:postcode":"2128",
    "sg:province":"NSW",
    "sg:tags":[
        "guard",
        "patrol"
    ],
    "wof:name":"Halion Security Pty Ltd",
    "wof:placetype":"venue"
},
  "geometry": {"coordinates":[151.04826355,-33.8383636475],"type":"Point"}
}