{
  "type": "Feature",
  "properties": {
    "iso:country":"AU",
    "sg:address":"Shop 21, Erskine Park Shopping Village Swallow Drv",
    "sg:city":"Erskine Park",
    "sg:classifiers":[
        {
            "category":"Shopping",
            "subcategory":"Bicycles & Sporting Goods",
            "type":"Retail Goods"
        }
    ],
    "sg:phone":"+61 2 9834 4214",
    "sg:postcode":"2759",
    "sg:province":"NSW",
    "sg:tags":[
        "chemical",
        "equipment",
        "pool",
        "swimming"
    ],
    "wof:name":"All Purpose Pool Care",
    "wof:placetype":"venue"
},
  "geometry": {"coordinates":[150.80560302699999,-33.8038291931],"type":"Point"}
}