{
  "type": "Feature",
  "properties": {
    "iso:country":"AU",
    "sg:address":"8 Corndale St",
    "sg:city":"Loganholme",
    "sg:classifiers":[
        {
            "category":"Organizations",
            "subcategory":"Professional Association",
            "type":"Services"
        }
    ],
    "sg:phone":"+61 7 3427 0101",
    "sg:postcode":"4129",
    "sg:province":"QLD",
    "sg:tags":[
        "web",
        "internet"
    ],
    "wof:name":"WebFix Communications",
    "wof:placetype":"venue"
},
  "geometry": {"coordinates":[153.18727111800001,-27.6901950836],"type":"Point"}
}