{
  "type": "Feature",
  "properties": {
    "iso:country":"AU",
    "sg:address":"24 Odessa St",
    "sg:city":"Granville",
    "sg:classifiers":[
        {
            "category":"Food & Beverages",
            "subcategory":"Groceries & Convenience Stores",
            "type":"Retail Goods"
        }
    ],
    "sg:phone":"+61 7 4121 3571",
    "sg:postcode":"4650",
    "sg:province":"QLD",
    "wof:name":"Granville Four Square",
    "wof:placetype":"venue"
},
  "geometry": {"coordinates":[152.71719400000001,-25.540344],"type":"Point"}
}