{
  "type": "Feature",
  "properties": {
    "iso:country":"AU",
    "sg:address":"133 Mollison St",
    "sg:city":"Bendigo",
    "sg:classifiers":[
        {
            "category":"Professional",
            "subcategory":"Printing & Photocopies",
            "type":"Services"
        }
    ],
    "sg:phone":"+61 3 5442 1316",
    "sg:postcode":"3550",
    "sg:province":"VIC",
    "sg:tags":[
        "photocopying"
    ],
    "wof:name":"The Terrace",
    "wof:placetype":"venue"
},
  "geometry": {"coordinates":[144.283493042,-36.7631111145],"type":"Point"}
}