{
  "type": "Feature",
  "properties": {
    "addr:full":"25- 27 Canning St Launceston TAS 7250",
    "addr:housenumber":"27",
    "addr:postcode":"7250",
    "addr:street":"Canning St",
    "iso:country":"AU",
    "sg:address":"25- 27 Canning St",
    "sg:city":"Launceston",
    "sg:classifiers":[
        {
            "category":"Health Services",
            "subcategory":"Doctor",
            "type":"Services"
        }
    ],
    "sg:phone":"+61 3 6331 6200",
    "sg:postcode":"7250",
    "sg:province":"TAS",
    "sg:tags":[
        "medical",
        "practitioner"
    ],
    "wof:name":"Jensen R",
    "wof:placetype":"venue"
},
  "geometry": {"coordinates":[147.141845703,-41.4422187805],"type":"Point"}
}