{
  "type": "Feature",
  "properties": {
    "addr:full":"71 York St Sydney NSW 2000",
    "addr:housenumber":"71",
    "addr:postcode":"2000",
    "addr:street":"York St",
    "iso:country":"AU",
    "sg:address":"71 York St",
    "sg:city":"Sydney",
    "sg:classifiers":[
        {
            "category":"Professional",
            "subcategory":"Computer Services",
            "type":"Services"
        }
    ],
    "sg:phone":"+61 2 9223 6000",
    "sg:postcode":"2000",
    "sg:province":"NSW",
    "sg:tags":[
        "information"
    ],
    "wof:name":"IBISWorld Pty Ltd",
    "wof:placetype":"venue"
},
  "geometry": {"coordinates":[151.20585632300001,-33.8682594299],"type":"Point"}
}