{
  "type": "Feature",
  "properties": {
    "addr:full":"Gregory St Mackay QLD 4740",
    "addr:postcode":"4740",
    "addr:street":"Gregory St",
    "iso:country":"AU",
    "sg:address":"Gregory St",
    "sg:city":"Mackay",
    "sg:classifiers":[
        {
            "category":"Education",
            "subcategory":"School",
            "type":"Public Place"
        }
    ],
    "sg:phone":"+61 7 4944 7200",
    "sg:postcode":"4740",
    "sg:province":"QLD",
    "sg:tags":[
        "co-educational"
    ],
    "wof:name":"St Patricks Co-Ed College",
    "wof:placetype":"venue"
},
  "geometry": {"coordinates":[149.183853,-21.146206],"type":"Point"}
}