{
  "type": "Feature",
  "properties": {
    "addr:full":"Cnr McIlwraith & Musgrave Sts Cloncurry QLD 4824",
    "addr:postcode":"4824",
    "addr:street":"Cnr",
    "iso:country":"AU",
    "sg:address":"Cnr McIlwraith & Musgrave Sts",
    "sg:city":"Cloncurry",
    "sg:classifiers":[
        {
            "category":"Retail",
            "subcategory":"Storage",
            "type":"Services"
        }
    ],
    "sg:phone":"+61 7 4742 2499",
    "sg:postcode":"4824",
    "sg:province":"QLD",
    "wof:name":"Oldsteel Industries",
    "wof:placetype":"venue"
},
  "geometry": {"coordinates":[140.52697800000001,-20.706987],"type":"Point"}
}