{
  "type": "Feature",
  "properties": {
    "addr:full":"1362 North East Rd Tea Tree Gully SA 5091",
    "addr:housenumber":"1362",
    "addr:postcode":"5091",
    "addr:street":"North East Rd Tea Tree",
    "iso:country":"AU",
    "sg:address":"1362 North East Rd",
    "sg:city":"Tea Tree Gully",
    "sg:classifiers":[
        {
            "category":"Fast Food",
            "type":"Food & Drink"
        }
    ],
    "sg:phone":"+61 8 8395 0339",
    "sg:postcode":"5091",
    "sg:province":"SA",
    "sg:tags":[
        "away",
        "take"
    ],
    "wof:name":"Raffles Room",
    "wof:placetype":"venue"
},
  "geometry": {"coordinates":[138.72982788100001,-34.8213310242],"type":"Point"}
}