{
  "type": "Feature",
  "properties": {
    "iso:country":"AU",
    "sg:address":"10 MacTier St",
    "sg:city":"Narrabeen",
    "sg:classifiers":[
        {
            "category":"Professional",
            "subcategory":"Employment Agencies",
            "type":"Services"
        }
    ],
    "sg:phone":"+61 2 9984 8508",
    "sg:postcode":"2101",
    "sg:province":"NSW",
    "sg:tags":[
        "provider",
        "internet"
    ],
    "wof:name":"Ausdome",
    "wof:placetype":"venue"
},
  "geometry": {"coordinates":[151.29766799999999,-33.722229],"type":"Point"}
}