{
  "type": "Feature",
  "properties": {
    "addr:full":"Unit 27/ 56 Buffalo Rd Gladesville NSW 1675",
    "addr:housenumber":"/ 56",
    "addr:postcode":"1675",
    "addr:street":"Buffalo Rd",
    "iso:country":"AU",
    "sg:address":"Unit 27/ 56 Buffalo Rd",
    "sg:city":"Gladesville",
    "sg:classifiers":[
        {
            "category":"Building & Trades",
            "subcategory":"Cleaning & Sanitation",
            "type":"Services"
        }
    ],
    "sg:phone":"+61 1300 855 678",
    "sg:postcode":"1675",
    "sg:province":"NSW",
    "sg:tags":[
        "chemical",
        "pressure",
        "steam",
        "contractor"
    ],
    "wof:name":"Eclipse Housewashing & Commercial Washing",
    "wof:placetype":"venue"
},
  "geometry": {"coordinates":[151.120193481,-33.8166007996],"type":"Point"}
}