{
  "type": "Feature",
  "properties": {
    "addr:full":"Midland Hwy Creswick VIC 3363",
    "addr:postcode":"3363",
    "addr:street":"Midland Hwy",
    "iso:country":"AU",
    "sg:address":"Midland Hwy",
    "sg:city":"Creswick",
    "sg:classifiers":[
        {
            "category":"Manufacturing",
            "subcategory":"Building Materials",
            "type":"Manufacturing & Wholesale Goods"
        }
    ],
    "sg:phone":"+61 3 5345 2388",
    "sg:postcode":"3363",
    "sg:province":"VIC",
    "sg:tags":[
        "machinery",
        "secondhand"
    ],
    "wof:name":"Springmount Machinery",
    "wof:placetype":"venue"
},
  "geometry": {"coordinates":[143.90359497099999,-37.4173126221],"type":"Point"}
}