{
  "type": "Feature",
  "properties": {
    "iso:country":"AU",
    "sg:address":"1/540 Springvale Rd",
    "sg:city":"Glen Waverley",
    "sg:classifiers":[
        {
            "category":"Banks & Credit Unions",
            "subcategory":"Financial Services",
            "type":"Services"
        }
    ],
    "sg:phone":"+61 3 8888 4300",
    "sg:postcode":"3150",
    "sg:province":"VIC",
    "sg:tags":[
        "planning"
    ],
    "wof:name":"Mercer",
    "wof:placetype":"venue"
},
  "geometry": {"coordinates":[145.16213989299999,-37.9014663696],"type":"Point"}
}