{
  "type": "Feature",
  "properties": {
    "iso:country":"AU",
    "sg:address":"PO Box 4342",
    "sg:city":"Bay Village",
    "sg:classifiers":[
        {
            "category":"Building & Trades",
            "subcategory":"Plumbing",
            "type":"Services"
        }
    ],
    "sg:phone":"+61 406 427 627",
    "sg:postcode":"2261",
    "sg:province":"NSW",
    "sg:tags":[
        "plumber",
        "gasfitters"
    ],
    "wof:name":"Crystal Clear Professional Services",
    "wof:placetype":"venue"
},
  "geometry": {"coordinates":[151.47384600000001,-33.37632],"type":"Point"}
}