{
  "type": "Feature",
  "properties": {
    "addr:full":"156 Bouverie St Carlton VIC 3053",
    "addr:housenumber":"156",
    "addr:postcode":"3053",
    "addr:street":"Bouverie St",
    "iso:country":"AU",
    "sg:address":"156 Bouverie St",
    "sg:city":"Carlton",
    "sg:classifiers":[
        {
            "category":"Professional",
            "subcategory":"Management & Consulting",
            "type":"Services"
        }
    ],
    "sg:phone":"+61 3 9653 9320",
    "sg:postcode":"3053",
    "sg:province":"VIC",
    "sg:tags":[
        "consultant"
    ],
    "wof:name":"Ciptanet International Pty Ltd",
    "wof:placetype":"venue"
},
  "geometry": {"coordinates":[144.962524414,-37.8010902405],"type":"Point"}
}