{
  "type": "Feature",
  "properties": {
    "iso:country":"AU",
    "sg:address":"6 Charles St",
    "sg:city":"Gawler East",
    "sg:classifiers":[
        {
            "category":"Professional",
            "subcategory":"Art Services",
            "type":"Services"
        }
    ],
    "sg:phone":"+61 417 844 924",
    "sg:postcode":"5118",
    "sg:province":"SA",
    "sg:tags":[
        "decorator",
        "painter"
    ],
    "wof:name":"Herrmann Grant",
    "wof:placetype":"venue"
},
  "geometry": {"coordinates":[138.754425,-34.59613],"type":"Point"}
}