{
  "type": "Feature",
  "properties": {
    "addr:full":"44 Clayton St Bellevue WA 6056",
    "addr:housenumber":"44",
    "addr:postcode":"6056",
    "addr:street":"Clayton St",
    "iso:country":"AU",
    "sg:address":"44 Clayton St",
    "sg:city":"Bellevue",
    "sg:classifiers":[
        {
            "category":"Building & Trades",
            "subcategory":"Construction",
            "type":"Services"
        }
    ],
    "sg:phone":"+61 8 9274 8837",
    "sg:postcode":"6056",
    "sg:province":"WA",
    "sg:tags":[
        "pool",
        "swimming"
    ],
    "wof:name":"Equip Contractors (Australia) Pty Ltd",
    "wof:placetype":"venue"
},
  "geometry": {"coordinates":[116.022987366,-31.8997802734],"type":"Point"}
}