{
  "type": "Feature",
  "properties": {
    "iso:country":"AU",
    "sg:address":"3 Wanderer Ave",
    "sg:city":"Mermaid Waters",
    "sg:classifiers":[
        {
            "category":"Home & Garden",
            "subcategory":"Carpets & Floor Coverings",
            "type":"Retail Goods"
        }
    ],
    "sg:phone":"+61 7 5575 3233",
    "sg:postcode":"4218",
    "sg:province":"QLD",
    "wof:name":"Sea Grass & Coir Matting",
    "wof:placetype":"venue"
},
  "geometry": {"coordinates":[153.41908264200001,-28.0493984222],"type":"Point"}
}