{
  "type": "Feature",
  "properties": {
    "iso:country":"AU",
    "sg:address":"20 William St",
    "sg:city":"Condobolin",
    "sg:classifiers":[
        {
            "category":"Restaurant",
            "type":"Food & Drink"
        }
    ],
    "sg:phone":"+61 2 6895 2233",
    "sg:postcode":"2877",
    "sg:province":"NSW",
    "wof:name":"Condobolin Motor Inn",
    "wof:placetype":"venue"
},
  "geometry": {"coordinates":[147.146851,-33.090012],"type":"Point"}
}