{
  "type": "Feature",
  "properties": {
    "addr:full":"30 Dallas St Mt Waverley VIC 3149",
    "addr:housenumber":"30",
    "addr:postcode":"3149",
    "addr:street":"Dallas St Mt",
    "iso:country":"AU",
    "sg:address":"30 Dallas St",
    "sg:city":"Mt Waverley",
    "sg:classifiers":[
        {
            "category":"Professional",
            "subcategory":"Accounting & Tax Preparation",
            "type":"Services"
        }
    ],
    "sg:phone":"+61 3 9807 6655",
    "sg:postcode":"3149",
    "sg:province":"VIC",
    "sg:tags":[
        "accountant",
        "auditor"
    ],
    "wof:name":"Gordon Howlett & Co",
    "wof:placetype":"venue"
},
  "geometry": {"coordinates":[145.11965942399999,-37.8823280334],"type":"Point"}
}