{
  "type": "Feature",
  "properties": {
    "addr:full":"Shop 9/ 142 Pitt Rd North Curl Curl NSW 2099",
    "addr:housenumber":"shop 9 / 142",
    "addr:postcode":"2099",
    "addr:street":"Pitt Rd North",
    "iso:country":"AU",
    "sg:address":"Shop 9/ 142 Pitt Rd",
    "sg:city":"North Curl Curl",
    "sg:classifiers":[
        {
            "category":"Fast Food",
            "type":"Food & Drink"
        }
    ],
    "sg:phone":"+61 2 9905 5007",
    "sg:postcode":"2099",
    "sg:province":"NSW",
    "sg:tags":[
        "away",
        "take"
    ],
    "wof:name":"North Curl Curl Take Away Food",
    "wof:placetype":"venue"
},
  "geometry": {"coordinates":[151.28939819300001,-33.7626838684],"type":"Point"}
}