{
  "type": "Feature",
  "properties": {
    "iso:country":"AU",
    "sg:address":"101 Victoria Ave",
    "sg:city":"Albert Park",
    "sg:classifiers":[
        {
            "category":"Personal",
            "subcategory":"Beauty Salon",
            "type":"Services"
        }
    ],
    "sg:phone":"+61 3 9690 6227",
    "sg:postcode":"3206",
    "sg:province":"VIC",
    "sg:tags":[
        "hairdresser"
    ],
    "wof:name":"Helmut Hair Studio",
    "wof:placetype":"venue"
},
  "geometry": {"coordinates":[144.95086699999999,-37.844814],"type":"Point"}
}