{
  "type": "Feature",
  "properties": {
    "addr:full":"Dight St Jindera NSW 2642",
    "addr:postcode":"2642",
    "addr:street":"St",
    "iso:country":"AU",
    "sg:address":"Dight St",
    "sg:city":"Jindera",
    "sg:classifiers":[
        {
            "category":"Education",
            "subcategory":"School",
            "type":"Public Place"
        }
    ],
    "sg:phone":"+61 2 6026 3280",
    "sg:postcode":"2642",
    "sg:province":"NSW",
    "sg:tags":[
        "state",
        "-",
        "nsw"
    ],
    "wof:name":"Jindera Public School",
    "wof:placetype":"venue"
},
  "geometry": {"coordinates":[146.890350342,-35.9563865662],"type":"Point"}
}