{
  "type": "Feature",
  "properties": {
    "iso:country":"AU",
    "sg:address":"136 Greenhill Rd",
    "sg:city":"Unley",
    "sg:classifiers":[
        {
            "category":"Transit Center",
            "subcategory":"Freight",
            "type":"Transportation"
        }
    ],
    "sg:phone":"+61 8 8300 0000",
    "sg:postcode":"5061",
    "sg:province":"SA",
    "sg:tags":[
        "ship",
        "provedores"
    ],
    "wof:name":"Australian Ship Suppliers Association",
    "wof:placetype":"venue"
},
  "geometry": {"coordinates":[138.605636597,-34.9411811829],"type":"Point"}
}