{
  "type": "Feature",
  "properties": {
    "addr:full":"349 Scarborough Beach Rd Innaloo WA 6018",
    "addr:housenumber":"349",
    "addr:postcode":"6018",
    "addr:street":"Scarborough Beach Rd",
    "iso:country":"AU",
    "sg:address":"349 Scarborough Beach Rd",
    "sg:city":"Innaloo",
    "sg:classifiers":[
        {
            "category":"Health Services",
            "subcategory":"Dentist",
            "type":"Services"
        }
    ],
    "sg:phone":"+61 8 9446 2682",
    "sg:postcode":"6018",
    "sg:province":"WA",
    "wof:name":"Chong James T.P.",
    "wof:placetype":"venue"
},
  "geometry": {"coordinates":[115.792732239,-31.9007434845],"type":"Point"}
}