{
  "type": "Feature",
  "properties": {
    "addr:full":"1240 South Rd Clovelly Park SA 5042",
    "addr:housenumber":"1240",
    "addr:postcode":"5042",
    "addr:street":"South Rd",
    "iso:country":"AU",
    "sg:address":"1240 South Rd",
    "sg:city":"Clovelly Park",
    "sg:classifiers":[
        {
            "category":"Shopping",
            "subcategory":"Clothing, Apparel, & Fashions",
            "type":"Retail Goods"
        }
    ],
    "sg:phone":"+61 401 003 540",
    "sg:postcode":"5042",
    "sg:province":"SA",
    "sg:tags":[
        "recycled",
        "clothing"
    ],
    "wof:name":"BCS Op-Shops",
    "wof:placetype":"venue"
},
  "geometry": {"coordinates":[138.575333,-35.001633],"type":"Point"}
}