{
  "type": "Feature",
  "properties": {
    "addr:full":"9 Marina Rd Bonnells Bay NSW 2264",
    "addr:housenumber":"9",
    "addr:postcode":"2264",
    "addr:street":"Marina Rd",
    "iso:country":"AU",
    "sg:address":"9 Marina Rd",
    "sg:city":"Bonnells Bay",
    "sg:classifiers":[
        {
            "category":"Structure",
            "subcategory":"Office Building",
            "type":"Public Place"
        }
    ],
    "sg:phone":"+61 2 4970 5671",
    "sg:postcode":"2264",
    "sg:province":"NSW",
    "sg:tags":[
        "slater",
        "tiler",
        "roof"
    ],
    "wof:name":"Meyn Roofing Contractors",
    "wof:placetype":"venue"
},
  "geometry": {"coordinates":[151.539276,-33.104351],"type":"Point"}
}