{
  "type": "Feature",
  "properties": {
    "addr:full":"158 Ludstone St Hampton VIC 3188",
    "addr:housenumber":"158",
    "addr:postcode":"3188",
    "addr:street":"Ludstone St",
    "iso:country":"AU",
    "sg:address":"158 Ludstone St",
    "sg:city":"Hampton",
    "sg:classifiers":[
        {
            "category":"Social Services",
            "subcategory":"Retirement Home",
            "type":"Services"
        }
    ],
    "sg:phone":"+61 3 9598 6611",
    "sg:postcode":"3188",
    "sg:province":"VIC",
    "sg:tags":[
        "village"
    ],
    "wof:name":"Hampton House S.R.S.",
    "wof:placetype":"venue"
},
  "geometry": {"coordinates":[145.01948547399999,-37.9350852966],"type":"Point"}
}