{
  "type": "Feature",
  "properties": {
    "addr:full":"5th Flr 230 Collins St Melbourne VIC 3000",
    "addr:housenumber":"230",
    "addr:postcode":"3000",
    "addr:street":"Collins St",
    "iso:country":"AU",
    "sg:address":"5th Flr 230 Collins St",
    "sg:city":"Melbourne",
    "sg:classifiers":[
        {
            "category":"Shopping",
            "subcategory":"Jewelry",
            "type":"Retail Goods"
        }
    ],
    "sg:phone":"+61 3 9654 5100",
    "sg:postcode":"3000",
    "sg:province":"VIC",
    "sg:tags":[
        "jeweller",
        "supply"
    ],
    "wof:name":"Seivers Australia",
    "wof:placetype":"venue"
},
  "geometry": {"coordinates":[144.9662323,-37.815448761],"type":"Point"}
}