{
  "type": "Feature",
  "properties": {
    "addr:full":"1 Eastry St Norwood SA 5067",
    "addr:housenumber":"1",
    "addr:postcode":"5067",
    "addr:street":"Eastry St",
    "iso:country":"AU",
    "sg:address":"1 Eastry St",
    "sg:city":"Norwood",
    "sg:classifiers":[
        {
            "category":"Professional",
            "subcategory":"Printing & Photocopies",
            "type":"Services"
        }
    ],
    "sg:phone":"+61 8 8130 1856",
    "sg:postcode":"5067",
    "sg:province":"SA",
    "sg:tags":[
        "publishing",
        "desktop"
    ],
    "wof:name":"Thirst Communications & Design Group",
    "wof:placetype":"venue"
},
  "geometry": {"coordinates":[138.625762939,-34.9214668274],"type":"Point"}
}