{
  "type": "Feature",
  "properties": {
    "addr:full":"14a Atherton Rd Oakleigh VIC 3166",
    "addr:housenumber":"14a",
    "addr:postcode":"3166",
    "addr:street":"Atherton Rd",
    "iso:country":"AU",
    "sg:address":"14a Atherton Rd",
    "sg:city":"Oakleigh",
    "sg:classifiers":[
        {
            "category":"Personal",
            "subcategory":"Beauty Salon",
            "type":"Services"
        }
    ],
    "sg:phone":"+61 3 9530 9007",
    "sg:postcode":"3166",
    "sg:province":"VIC",
    "wof:name":"Sarzu Nails & Beauty",
    "wof:placetype":"venue"
},
  "geometry": {"coordinates":[145.08897399899999,-37.8987083435],"type":"Point"}
}