{
  "type": "Feature",
  "properties": {
    "iso:country":"AU",
    "sg:address":"49 Coleridge St",
    "sg:city":"Leichhardt",
    "sg:classifiers":[
        {
            "category":"Commercial Area",
            "type":"Public Place"
        }
    ],
    "sg:phone":"+61 2 9569 8159",
    "sg:postcode":"2040",
    "sg:province":"NSW",
    "sg:tags":[
        "heavy",
        "carrier"
    ],
    "wof:name":"Newton A E Pty Ltd",
    "wof:placetype":"venue"
},
  "geometry": {"coordinates":[151.162567,-33.881138],"type":"Point"}
}