{
  "type": "Feature",
  "properties": {
    "addr:full":"New England Hwy Via Guyra NSW 2365",
    "addr:postcode":"2365",
    "addr:street":"England Hwy Via Guyra",
    "iso:country":"AU",
    "sg:address":"New England Hwy Via",
    "sg:city":"Guyra",
    "sg:classifiers":[
        {
            "category":"Restaurant",
            "type":"Food & Drink"
        }
    ],
    "sg:phone":"+61 2 6775 0166",
    "sg:postcode":"2365",
    "sg:province":"NSW",
    "sg:tags":[
        "roadhouse"
    ],
    "wof:name":"Black Mountain Roadhouse & Motel",
    "wof:placetype":"venue"
},
  "geometry": {"coordinates":[151.673095703,-30.2176151276],"type":"Point"}
}