{
  "type": "Feature",
  "properties": {
    "addr:full":"4 Slym Crt Springvale South VIC 3172",
    "addr:housenumber":"4",
    "addr:postcode":"3172",
    "addr:street":"Slym Crt",
    "iso:country":"AU",
    "sg:address":"4 Slym Crt",
    "sg:city":"Springvale South",
    "sg:classifiers":[
        {
            "category":"Home & Garden",
            "subcategory":"Carpets & Floor Coverings",
            "type":"Retail Goods"
        }
    ],
    "sg:phone":"+61 3 9547 3292",
    "sg:postcode":"3172",
    "sg:province":"VIC",
    "sg:tags":[
        "tile",
        "wall",
        "layer"
    ],
    "wof:name":"Melatti G",
    "wof:placetype":"venue"
},
  "geometry": {"coordinates":[145.15034484899999,-37.9774589539],"type":"Point"}
}