{
  "type": "Feature",
  "properties": {
    "addr:full":"39 Scholey St Mayfield NSW 2304",
    "addr:housenumber":"39",
    "addr:postcode":"2304",
    "addr:street":"Scholey St",
    "iso:country":"AU",
    "sg:address":"39 Scholey St",
    "sg:city":"Mayfield",
    "sg:classifiers":[
        {
            "category":"Building & Trades",
            "subcategory":"Cleaning & Sanitation",
            "type":"Services"
        }
    ],
    "sg:phone":"+61 2 4967 5601",
    "sg:postcode":"2304",
    "sg:province":"NSW",
    "sg:tags":[
        "sweep",
        "chimney"
    ],
    "wof:name":"Jones Kevin",
    "wof:placetype":"venue"
},
  "geometry": {"coordinates":[151.73707580600001,-32.9063529968],"type":"Point"}
}