{
  "type": "Feature",
  "properties": {
    "iso:country":"AU",
    "sg:address":"3 Margery Rd",
    "sg:city":"High Wycombe",
    "sg:classifiers":[
        {
            "category":"Shopping",
            "subcategory":"Party Supplies",
            "type":"Retail Goods"
        }
    ],
    "sg:phone":"+61 8 9454 3319",
    "sg:postcode":"6057",
    "sg:province":"WA",
    "sg:tags":[
        "hire",
        "costume"
    ],
    "wof:name":"Helenes Fancy Dress",
    "wof:placetype":"venue"
},
  "geometry": {"coordinates":[116.000259399,-31.9369277954],"type":"Point"}
}