{
  "type": "Feature",
  "properties": {
    "addr:full":"14 Boodle St Goondiwindi QLD 4390",
    "addr:housenumber":"14",
    "addr:postcode":"4390",
    "addr:street":"Boodle St",
    "iso:country":"AU",
    "sg:address":"14 Boodle St",
    "sg:city":"Goondiwindi",
    "sg:classifiers":[
        {
            "category":"Retail",
            "subcategory":"Auto Repair",
            "type":"Services"
        }
    ],
    "sg:phone":"+61 7 4671 4222",
    "sg:postcode":"4390",
    "sg:province":"QLD",
    "sg:tags":[
        "repairer",
        "motor",
        "engineer"
    ],
    "wof:name":"Country Link Mobile Mechanical Service",
    "wof:placetype":"venue"
},
  "geometry": {"coordinates":[150.31466674800001,-28.5320072174],"type":"Point"}
}