{
  "type": "Feature",
  "properties": {
    "addr:full":"4 Jessica Pl Prestons NSW 2170",
    "addr:housenumber":"4",
    "addr:postcode":"2170",
    "addr:street":"Jessica Pl",
    "iso:country":"AU",
    "sg:address":"4 Jessica Pl",
    "sg:city":"Prestons",
    "sg:classifiers":[
        {
            "category":"Building & Trades",
            "subcategory":"Equipment Rental",
            "type":"Services"
        }
    ],
    "sg:phone":"+61 2 9607 3610",
    "sg:postcode":"2170",
    "sg:province":"NSW",
    "sg:tags":[
        "party",
        "hire"
    ],
    "wof:name":"A. Action Party Hire",
    "wof:placetype":"venue"
},
  "geometry": {"coordinates":[150.87559509299999,-33.9336051941],"type":"Point"}
}