{
  "type": "Feature",
  "properties": {
    "addr:full":"215 Doolong Rd Hervey Bay QLD 4655",
    "addr:housenumber":"215",
    "addr:postcode":"4655",
    "addr:street":"Doolong Rd",
    "iso:country":"AU",
    "sg:address":"215 Doolong Rd",
    "sg:city":"Hervey Bay",
    "sg:classifiers":[
        {
            "category":"Building & Trades",
            "subcategory":"Construction",
            "type":"Services"
        }
    ],
    "sg:phone":"+61 7 4128 6413",
    "sg:postcode":"4655",
    "sg:province":"QLD",
    "sg:tags":[
        "earth",
        "excavating",
        "moving",
        "contractor"
    ],
    "wof:name":"Sager ID & TD",
    "wof:placetype":"venue"
},
  "geometry": {"coordinates":[152.83758499999999,-25.3046],"type":"Point"}
}