{
  "type": "Feature",
  "properties": {
    "addr:full":"a 801 Pacific Hwy Marks Point NSW 2280",
    "addr:housenumber":"801",
    "addr:postcode":"2280",
    "addr:street":"A;Pacific Hwy",
    "iso:country":"AU",
    "sg:address":"a 801 Pacific Hwy",
    "sg:city":"Marks Point",
    "sg:classifiers":[
        {
            "category":"Sports & Exercise",
            "subcategory":"Golf",
            "type":"Entertainment"
        }
    ],
    "sg:phone":"+61 2 4945 2058",
    "sg:postcode":"2280",
    "sg:province":"NSW",
    "sg:tags":[
        "club"
    ],
    "wof:name":"Belmont Golf Club Ltd",
    "wof:placetype":"venue"
},
  "geometry": {"coordinates":[151.65480041500001,-33.0557861328],"type":"Point"}
}