{
  "type": "Feature",
  "properties": {
    "iso:country":"AU",
    "sg:address":"17- 19",
    "sg:city":"Oxford Cl West Leederville",
    "sg:classifiers":[
        {
            "category":"Communications",
            "subcategory":"Television Station",
            "type":"Services"
        }
    ],
    "sg:phone":"+61 8 9489 8500",
    "sg:postcode":"6007",
    "sg:province":"WA",
    "sg:tags":[
        "equipment",
        "laser"
    ],
    "wof:name":"C.R. Kennedy Total Survey Solutions",
    "wof:placetype":"venue"
},
  "geometry": {"coordinates":[115.8412323,-31.9284687042],"type":"Point"}
}