{
  "type": "Feature",
  "properties": {
    "addr:full":"The Colonnade, 1st Floor 388 Hay St Subiaco WA 6008",
    "addr:housenumber":"388",
    "addr:postcode":"6008",
    "addr:street":"Hay St",
    "iso:country":"AU",
    "sg:address":"The Colonnade, 1st Floor 388 Hay St",
    "sg:city":"Subiaco",
    "sg:classifiers":[
        {
            "category":"Personal",
            "subcategory":"Beauty Salon",
            "type":"Services"
        }
    ],
    "sg:phone":"+61 8 9388 8101",
    "sg:postcode":"6008",
    "sg:province":"WA",
    "wof:name":"Belez? International",
    "wof:placetype":"venue"
},
  "geometry": {"coordinates":[115.82582092299999,-31.9468803406],"type":"Point"}
}