{
  "type": "Feature",
  "properties": {
    "iso:country":"AU",
    "sg:address":"rear 13 Kilvington Drv",
    "sg:city":"Emerald",
    "sg:classifiers":[
        {
            "category":"Retail",
            "subcategory":"Auto Repair",
            "type":"Services"
        }
    ],
    "sg:phone":"+61 3 5968 5052",
    "sg:postcode":"3782",
    "sg:province":"VIC",
    "sg:tags":[
        "repairer",
        "motor",
        "engineer"
    ],
    "wof:name":"J L Automatic Transmissions",
    "wof:placetype":"venue"
},
  "geometry": {"coordinates":[145.440994,-37.933662],"type":"Point"}
}