{
  "type": "Feature",
  "properties": {
    "iso:country":"AU",
    "sg:address":"4/ 107 West High St",
    "sg:city":"Coffs Harbour",
    "sg:classifiers":[
        {
            "category":"Insurance",
            "subcategory":"Insurance Agent",
            "type":"Services"
        }
    ],
    "sg:phone":"+61 2 6651 7588",
    "sg:postcode":"2450",
    "sg:province":"NSW",
    "sg:tags":[
        "broker"
    ],
    "wof:name":"Insurance Advisernet Australia Pty Limited",
    "wof:placetype":"venue"
},
  "geometry": {"coordinates":[153.111313,-30.2957],"type":"Point"}
}