{
  "type": "Feature",
  "properties": {
    "iso:country":"AU",
    "sg:address":"36 Talbot Ave",
    "sg:city":"Como",
    "sg:classifiers":[
        {
            "category":"Travel",
            "subcategory":"Hostel",
            "type":"Entertainment"
        }
    ],
    "sg:phone":"+61 8 9450 2751",
    "sg:postcode":"6152",
    "sg:province":"WA",
    "sg:tags":[
        "home"
    ],
    "wof:name":"Como House",
    "wof:placetype":"venue"
},
  "geometry": {"coordinates":[115.866669,-32.003048],"type":"Point"}
}