{
  "type": "Feature",
  "properties": {
    "addr:full":"12/ 258 Canning Hwy Bicton WA 6157",
    "addr:housenumber":"12 / 258",
    "addr:postcode":"6157",
    "addr:street":"Canning Hwy",
    "iso:country":"AU",
    "sg:address":"12/ 258 Canning Hwy",
    "sg:city":"Bicton",
    "sg:classifiers":[
        {
            "category":"Communications",
            "subcategory":"Film & Video Production",
            "type":"Services"
        }
    ],
    "sg:phone":"+61 8 9339 3244",
    "sg:postcode":"6157",
    "sg:province":"WA",
    "sg:tags":[
        "dvd",
        "library"
    ],
    "wof:name":"Jumbo Video",
    "wof:placetype":"venue"
},
  "geometry": {"coordinates":[115.79280900000001,-32.034492],"type":"Point"}
}