{
  "type": "Feature",
  "properties": {
    "addr:full":"9/ 95 Research Rd Pooraka SA 5095",
    "addr:housenumber":"/ 95",
    "addr:postcode":"5095",
    "addr:street":"Research Rd",
    "iso:country":"AU",
    "sg:address":"9/ 95 Research Rd",
    "sg:city":"Pooraka",
    "sg:classifiers":[
        {
            "category":"Shopping",
            "subcategory":"Pets & Pet Supplies",
            "type":"Retail Goods"
        }
    ],
    "sg:phone":"+61 8 8349 9150",
    "sg:postcode":"5095",
    "sg:province":"SA",
    "sg:tags":[
        "equipment",
        "ceramic"
    ],
    "wof:name":"Ceramic Decor (Aust) Pty Ltd",
    "wof:placetype":"venue"
},
  "geometry": {"coordinates":[138.63284301799999,-34.8150177002],"type":"Point"}
}