{
  "type": "Feature",
  "properties": {
    "addr:full":"131 Albert Rd Moonah TAS 7009",
    "addr:housenumber":"131",
    "addr:postcode":"7009",
    "addr:street":"Albert Rd",
    "iso:country":"AU",
    "sg:address":"131 Albert Rd",
    "sg:city":"Moonah",
    "sg:classifiers":[
        {
            "category":"Farming",
            "subcategory":"Fish & Marine Products",
            "type":"Manufacturing & Wholesale Goods"
        }
    ],
    "sg:phone":"+61 3 6267 9658",
    "sg:postcode":"7009",
    "sg:province":"TAS",
    "sg:tags":[
        "production",
        "seafood",
        "processing"
    ],
    "wof:name":"Ralphs Tasmanian Seafood Pty Ltd",
    "wof:placetype":"venue"
},
  "geometry": {"coordinates":[147.31002807600001,-42.8488845825],"type":"Point"}
}