{
  "type": "Feature",
  "properties": {
    "iso:country":"AU",
    "sg:address":"152 Railway St",
    "sg:city":"Swanbourne",
    "sg:classifiers":[
        {
            "category":"Health Services",
            "subcategory":"Doctor",
            "type":"Services"
        }
    ],
    "sg:phone":"+61 8 9384 7811",
    "sg:postcode":"6010",
    "sg:province":"WA",
    "sg:tags":[
        "medical",
        "practitioner"
    ],
    "wof:name":"Graham Innes Dr",
    "wof:placetype":"venue"
},
  "geometry": {"coordinates":[115.770332336,-31.9834308624],"type":"Point"}
}