{
  "type": "Feature",
  "properties": {
    "addr:full":"28 Joachim St Holland Park QLD 4121",
    "addr:housenumber":"28",
    "addr:postcode":"4121",
    "addr:street":"Joachim St",
    "iso:country":"AU",
    "sg:address":"28 Joachim St",
    "sg:city":"Holland Park",
    "sg:classifiers":[
        {
            "category":"Health Services",
            "subcategory":"Health Practitioner",
            "type":"Services"
        }
    ],
    "sg:phone":"+61 7 3397 6544",
    "sg:postcode":"4121",
    "sg:province":"QLD",
    "sg:tags":[
        "naturopath"
    ],
    "wof:name":"Roberts Helen Naturopathic Clinic",
    "wof:placetype":"venue"
},
  "geometry": {"coordinates":[153.05674743599999,-27.5218467712],"type":"Point"}
}