{
  "type": "Feature",
  "properties": {
    "addr:full":"Shop 26 Paspaley Plaza Broome WA 6725",
    "addr:housenumber":"shop 26",
    "addr:postcode":"6725",
    "addr:street":"Paspaley Plaza",
    "iso:country":"AU",
    "sg:address":"Shop 26 Paspaley Plaza",
    "sg:city":"Broome",
    "sg:classifiers":[
        {
            "category":"Building & Trades",
            "subcategory":"Equipment Rental",
            "type":"Services"
        }
    ],
    "sg:phone":"+61 8 9193 6370",
    "sg:postcode":"6725",
    "sg:province":"WA",
    "sg:tags":[
        "fitness"
    ],
    "wof:name":"Sportspower Broome",
    "wof:placetype":"venue"
},
  "geometry": {"coordinates":[122.677589416,-18.2141704559],"type":"Point"}
}