{
  "type": "Feature",
  "properties": {
    "addr:full":"Suite 2/ 19 Atchison St Wollongong NSW 2500",
    "addr:housenumber":"19",
    "addr:postcode":"2500",
    "addr:street":"Atchison St",
    "iso:country":"AU",
    "sg:address":"Suite 2/ 19 Atchison St",
    "sg:city":"Wollongong",
    "sg:classifiers":[
        {
            "category":"Banks & Credit Unions",
            "subcategory":"Financial Services",
            "type":"Services"
        }
    ],
    "sg:phone":"+61 2 4228 1000",
    "sg:postcode":"2500",
    "sg:province":"NSW",
    "sg:tags":[
        "planning"
    ],
    "wof:name":"Lucas Financial Advisors Pty Ltd",
    "wof:placetype":"venue"
},
  "geometry": {"coordinates":[150.89068599999999,-34.427589],"type":"Point"}
}