{
  "type": "Feature",
  "properties": {
    "addr:full":"458 Fullarton Rd Myrtle Bank SA 5064",
    "addr:housenumber":"458",
    "addr:postcode":"5064",
    "addr:street":"Fullarton Rd",
    "iso:country":"AU",
    "sg:address":"458 Fullarton Rd",
    "sg:city":"Myrtle Bank",
    "sg:classifiers":[
        {
            "category":"Professional",
            "subcategory":"Accounting & Tax Preparation",
            "type":"Services"
        }
    ],
    "sg:phone":"+61 8 8338 7820",
    "sg:postcode":"5064",
    "sg:province":"SA",
    "sg:tags":[
        "accountant",
        "auditor"
    ],
    "wof:name":"Excel Bookkeeping",
    "wof:placetype":"venue"
},
  "geometry": {"coordinates":[138.62635803200001,-34.9606933594],"type":"Point"}
}