{
  "type": "Feature",
  "properties": {
    "iso:country":"AU",
    "sg:address":"441 Wondall Rd",
    "sg:city":"Tingalpa",
    "sg:classifiers":[
        {
            "category":"Professional",
            "type":"Services"
        }
    ],
    "sg:phone":"+61 7 3890 8434",
    "sg:postcode":"4173",
    "sg:province":"QLD",
    "sg:tags":[
        "transport"
    ],
    "wof:name":"Intercoast Refrigerated Transport",
    "wof:placetype":"venue"
},
  "geometry": {"coordinates":[153.15032959000001,-27.4697360992],"type":"Point"}
}