{
  "type": "Feature",
  "properties": {
    "iso:country":"AU",
    "sg:address":"9 Tumbi Creek Rd",
    "sg:city":"Tumbi Umbi",
    "sg:classifiers":[
        {
            "category":"Retail",
            "subcategory":"Auto Rental",
            "type":"Services"
        }
    ],
    "sg:phone":"+61 2 4388 1690",
    "sg:postcode":"2261",
    "sg:province":"NSW",
    "sg:tags":[
        "bus",
        "truck"
    ],
    "wof:name":"Thrifty",
    "wof:placetype":"venue"
},
  "geometry": {"coordinates":[151.444717,-33.361053],"type":"Point"}
}