{
  "type": "Feature",
  "properties": {
    "iso:country":"AU",
    "sg:address":"17- 21 Raglan St",
    "sg:city":"Preston",
    "sg:classifiers":[
        {
            "category":"Home & Garden",
            "subcategory":"Hardware",
            "type":"Retail Goods"
        }
    ],
    "sg:phone":"+61 3 9480 5066",
    "sg:postcode":"3072",
    "sg:province":"VIC",
    "sg:tags":[
        "product",
        "treatment",
        "floor"
    ],
    "wof:name":"Site Management Pty Ltd",
    "wof:placetype":"venue"
},
  "geometry": {"coordinates":[145.02888488799999,-37.7519493103],"type":"Point"}
}