{
  "type": "Feature",
  "properties": {
    "addr:full":"PO Box 42 Heywood VIC 3304",
    "addr:postcode":"3304",
    "iso:country":"AU",
    "sg:address":"PO Box 42",
    "sg:city":"Heywood",
    "sg:classifiers":[
        {
            "category":"Social Services",
            "subcategory":"Child Care",
            "type":"Services"
        }
    ],
    "sg:phone":"+61 3 5527 1851",
    "sg:postcode":"3304",
    "sg:province":"VIC",
    "sg:tags":[
        "support",
        "health"
    ],
    "wof:name":"Maternal & Child Health Centres",
    "wof:placetype":"venue"
},
  "geometry": {"coordinates":[141.62982177699999,-38.1332015991],"type":"Point"}
}