{
  "type": "Feature",
  "properties": {
    "addr:full":"5 Maberley St Geebung QLD 4034",
    "addr:housenumber":"5",
    "addr:postcode":"4034",
    "addr:street":"Maberley St",
    "iso:country":"AU",
    "sg:address":"5 Maberley St",
    "sg:city":"Geebung",
    "sg:classifiers":[
        {
            "category":"Professional",
            "subcategory":"Business Services",
            "type":"Services"
        }
    ],
    "sg:phone":"+61 413 317 690",
    "sg:postcode":"4034",
    "sg:province":"QLD",
    "sg:tags":[
        "drafting"
    ],
    "wof:name":"Alayne Williams",
    "wof:placetype":"venue"
},
  "geometry": {"coordinates":[153.036835,-27.372602],"type":"Point"}
}