{
  "type": "Feature",
  "properties": {
    "addr:full":"233 Johnston St Annandale NSW 2038",
    "addr:housenumber":"233",
    "addr:postcode":"2038",
    "addr:street":"Johnston St",
    "iso:country":"AU",
    "sg:address":"233 Johnston St",
    "sg:city":"Annandale",
    "sg:classifiers":[
        {
            "category":"Real Estate",
            "subcategory":"Architect",
            "type":"Services"
        }
    ],
    "sg:phone":"+61 2 9566 4000",
    "sg:postcode":"2038",
    "sg:province":"NSW",
    "wof:name":"Gibbon Hamor Development Planners",
    "wof:placetype":"venue"
},
  "geometry": {"coordinates":[151.17318725600001,-33.8762588501],"type":"Point"}
}