{
  "type": "Feature",
  "properties": {
    "iso:country":"AU",
    "sg:address":"Level 49, 1 Farrer Pl",
    "sg:city":"Sydney",
    "sg:classifiers":[
        {
            "category":"Professional",
            "subcategory":"Management & Consulting",
            "type":"Services"
        }
    ],
    "sg:phone":"+61 2 9251 2788",
    "sg:postcode":"2000",
    "sg:province":"NSW",
    "sg:tags":[
        "consultant"
    ],
    "wof:name":"Egon Zehnder International Pty Ltd",
    "wof:placetype":"venue"
},
  "geometry": {"coordinates":[151.21072387699999,-33.8643341064],"type":"Point"}
}