{
  "type": "Feature",
  "properties": {
    "addr:full":"8 Anstey Rd Lismore NSW 2480",
    "addr:housenumber":"8",
    "addr:postcode":"2480",
    "addr:street":"Anstey Rd",
    "iso:country":"AU",
    "sg:address":"8 Anstey Rd",
    "sg:city":"Lismore",
    "sg:classifiers":[
        {
            "category":"Building & Trades",
            "subcategory":"Plumbing",
            "type":"Services"
        }
    ],
    "sg:phone":"+61 2 6621 2487",
    "sg:postcode":"2480",
    "sg:province":"NSW",
    "sg:tags":[
        "plumber",
        "gasfitters"
    ],
    "wof:name":"T R Hensley Plumbing",
    "wof:placetype":"venue"
},
  "geometry": {"coordinates":[153.28074645999999,-28.8151874542],"type":"Point"}
}