{
  "type": "Feature",
  "properties": {
    "addr:full":"PO Box 843 Mooloolaba QLD 4557",
    "addr:postcode":"4557",
    "iso:country":"AU",
    "sg:address":"PO Box 843",
    "sg:city":"Mooloolaba",
    "sg:classifiers":[
        {
            "category":"Arts & Performance",
            "subcategory":"Music",
            "type":"Entertainment"
        }
    ],
    "sg:phone":"+61 418 248 522",
    "sg:postcode":"4557",
    "sg:province":"QLD",
    "sg:tags":[
        "mobile",
        "jockey",
        "disc"
    ],
    "wof:name":"Best Beats",
    "wof:placetype":"venue"
},
  "geometry": {"coordinates":[153.117797852,-26.6837902069],"type":"Point"}
}