{
  "type": "Feature",
  "properties": {
    "addr:full":"Lot 210, Mandalong Pl Erskine Park NSW 2759",
    "addr:postcode":"2759",
    "addr:street":"Mandalong Pl",
    "iso:country":"AU",
    "sg:address":"Lot 210, Mandalong Pl",
    "sg:city":"Erskine Park",
    "sg:classifiers":[
        {
            "category":"Building & Trades",
            "subcategory":"Equipment Rental",
            "type":"Services"
        }
    ],
    "sg:phone":"+61 412 227 110",
    "sg:postcode":"2759",
    "sg:province":"NSW",
    "sg:tags":[
        "crane",
        "hire"
    ],
    "wof:name":"Gino's Transport",
    "wof:placetype":"venue"
},
  "geometry": {"coordinates":[150.77206420900001,-33.8162956238],"type":"Point"}
}