{
  "type": "Feature",
  "properties": {
    "iso:country":"AU",
    "sg:address":"3 Elizabeth St",
    "sg:city":"Yarraville",
    "sg:classifiers":[
        {
            "category":"Retail",
            "subcategory":"Auto Repair",
            "type":"Services"
        }
    ],
    "sg:phone":"+61 402 463 948",
    "sg:postcode":"3013",
    "sg:province":"VIC",
    "sg:tags":[
        "repairer",
        "motor",
        "engineer"
    ],
    "wof:name":"AFFORDABLE AUTO REPAIRS",
    "wof:placetype":"venue"
},
  "geometry": {"coordinates":[144.884277344,-37.8161735535],"type":"Point"}
}