{
  "type": "Feature",
  "properties": {
    "iso:country":"AU",
    "sg:address":"102 William St",
    "sg:city":"Bathurst",
    "sg:classifiers":[
        {
            "category":"Real Estate",
            "subcategory":"Real Estate Agent",
            "type":"Services"
        }
    ],
    "sg:phone":"+61 2 6331 5555",
    "sg:postcode":"2795",
    "sg:province":"NSW",
    "wof:name":"Bathurst Real Estate",
    "wof:placetype":"venue"
},
  "geometry": {"coordinates":[149.581207275,-33.4167442322],"type":"Point"}
}