{
  "type": "Feature",
  "properties": {
    "addr:full":"PO Box 40 Colebrook TAS 7027",
    "addr:postcode":"7027",
    "iso:country":"AU",
    "sg:address":"PO Box 40",
    "sg:city":"Colebrook",
    "sg:classifiers":[
        {
            "category":"Building & Trades",
            "subcategory":"Cleaning & Sanitation",
            "type":"Services"
        }
    ],
    "sg:phone":"+61 3 6259 7211",
    "sg:postcode":"7027",
    "sg:province":"TAS",
    "sg:tags":[
        "sweep",
        "chimney"
    ],
    "wof:name":"Cooper & Sons W Home Heating",
    "wof:placetype":"venue"
},
  "geometry": {"coordinates":[147.363937378,-42.5341682434],"type":"Point"}
}