{
  "type": "Feature",
  "properties": {
    "addr:full":"PO Box 290 Portarlington VIC 3223",
    "addr:postcode":"3223",
    "iso:country":"AU",
    "sg:address":"PO Box 290",
    "sg:city":"Portarlington",
    "sg:classifiers":[
        {
            "category":"Building & Trades",
            "subcategory":"Plumbing",
            "type":"Services"
        }
    ],
    "sg:phone":"+61 418 524 946",
    "sg:postcode":"3223",
    "sg:province":"VIC",
    "sg:tags":[
        "plumber",
        "gasfitters"
    ],
    "wof:name":"Locke M & J",
    "wof:placetype":"venue"
},
  "geometry": {"coordinates":[144.65533400000001,-38.115292],"type":"Point"}
}