{
  "type": "Feature",
  "properties": {
    "addr:full":"18 Sam White Drv Buderim QLD 4556",
    "addr:housenumber":"18",
    "addr:postcode":"4556",
    "addr:street":"Sam White Drv",
    "iso:country":"AU",
    "sg:address":"18 Sam White Drv",
    "sg:city":"Buderim",
    "sg:classifiers":[
        {
            "category":"Manufacturing",
            "subcategory":"Furniture",
            "type":"Manufacturing & Wholesale Goods"
        }
    ],
    "sg:phone":"+61 7 5476 5639",
    "sg:postcode":"4556",
    "sg:province":"QLD",
    "sg:tags":[
        "builder",
        "designer",
        "custom"
    ],
    "wof:name":"Devine Furniture",
    "wof:placetype":"venue"
},
  "geometry": {"coordinates":[153.035720825,-26.6703796387],"type":"Point"}
}