{
  "type": "Feature",
  "properties": {
    "addr:full":"200 Walters Rd Arndell Park NSW 2148",
    "addr:housenumber":"200",
    "addr:postcode":"2148",
    "addr:street":"Walters Rd",
    "iso:country":"AU",
    "sg:address":"200 Walters Rd",
    "sg:city":"Arndell Park",
    "sg:classifiers":[
        {
            "category":"Transit Center",
            "subcategory":"Freight",
            "type":"Transportation"
        }
    ],
    "sg:phone":"+61 2 8822 8100",
    "sg:postcode":"2148",
    "sg:province":"NSW",
    "sg:tags":[
        "equipment",
        "truck",
        "transport",
        "refrigerated"
    ],
    "wof:name":"Thermo King",
    "wof:placetype":"venue"
},
  "geometry": {"coordinates":[150.89613342300001,-33.772190094],"type":"Point"}
}