{
  "type": "Feature",
  "properties": {
    "iso:country":"AU",
    "sg:address":"PO Box 7344",
    "sg:city":"Mildura East",
    "sg:classifiers":[
        {
            "category":"Building & Trades",
            "subcategory":"Cleaning & Sanitation",
            "type":"Services"
        }
    ],
    "sg:phone":"+61 428 596 248",
    "sg:postcode":"3500",
    "sg:province":"VIC",
    "sg:tags":[
        "washroom",
        "toilet",
        "equipment"
    ],
    "wof:name":"Wally Greens Hygiene Services",
    "wof:placetype":"venue"
},
  "geometry": {"coordinates":[142.19940185600001,-34.2070503235],"type":"Point"}
}