{
  "type": "Feature",
  "properties": {
    "addr:full":"Unit 13/ 35 Foundry Rd Seven Hills NSW 2147",
    "addr:housenumber":"/ 35",
    "addr:postcode":"2147",
    "addr:street":"Foundry Rd",
    "iso:country":"AU",
    "sg:address":"Unit 13/ 35 Foundry Rd",
    "sg:city":"Seven Hills",
    "sg:classifiers":[
        {
            "category":"Government",
            "subcategory":"Department Of Motor Vehicles",
            "type":"Public Place"
        }
    ],
    "sg:phone":"+61 2 9838 9681",
    "sg:postcode":"2147",
    "sg:province":"NSW",
    "sg:tags":[
        "wholesaler",
        "mfrs",
        "accessory"
    ],
    "wof:name":"Pentas International Pty Ltd",
    "wof:placetype":"venue"
},
  "geometry": {"coordinates":[150.95512390100001,-33.7702865601],"type":"Point"}
}