{
  "type": "Feature",
  "properties": {
    "iso:country":"AU",
    "sg:address":"9 Campbell St",
    "sg:city":"Ararat",
    "sg:classifiers":[
        {
            "category":"Retail",
            "subcategory":"Funeral Services",
            "type":"Services"
        }
    ],
    "sg:phone":"+61 3 5352 1047",
    "sg:postcode":"3377",
    "sg:province":"VIC",
    "sg:tags":[
        "director"
    ],
    "wof:name":"Dunn John Funeral Services Pty Ltd",
    "wof:placetype":"venue"
},
  "geometry": {"coordinates":[142.93586730999999,-37.2800827026],"type":"Point"}
}