{
  "type": "Feature",
  "properties": {
    "addr:full":"18 Albemarle St Williamstown VIC 3016",
    "addr:housenumber":"18",
    "addr:postcode":"3016",
    "addr:street":"Albemarle St",
    "iso:country":"AU",
    "sg:address":"18 Albemarle St",
    "sg:city":"Williamstown",
    "sg:classifiers":[
        {
            "category":"Personal",
            "subcategory":"Adult",
            "type":"Services"
        }
    ],
    "sg:phone":"+61 3 9399 9740",
    "sg:postcode":"3016",
    "sg:province":"VIC",
    "sg:tags":[
        "entertainment"
    ],
    "wof:name":"Sea Pearls of Melbourne",
    "wof:placetype":"venue"
},
  "geometry": {"coordinates":[144.864944458,-37.8508987427],"type":"Point"}
}