{
  "type": "Feature",
  "properties": {
    "iso:country":"AU",
    "sg:address":"272 Brunswick Rd",
    "sg:city":"Brunswick",
    "sg:classifiers":[
        {
            "category":"Retail",
            "subcategory":"Veterinary Services",
            "type":"Services"
        }
    ],
    "sg:phone":"+61 3 9387 3706",
    "sg:postcode":"3056",
    "sg:province":"VIC",
    "sg:tags":[
        "surgeon"
    ],
    "wof:name":"Australian Veterinary Association Vic Division",
    "wof:placetype":"venue"
},
  "geometry": {"coordinates":[144.95512390100001,-37.7765197754],"type":"Point"}
}