{
  "type": "Feature",
  "properties": {
    "addr:full":"785 Old Cleveland Rd Carina QLD 4152",
    "addr:housenumber":"785",
    "addr:postcode":"4152",
    "addr:street":"Old Cleveland Rd",
    "iso:country":"AU",
    "sg:address":"785 Old Cleveland Rd",
    "sg:city":"Carina",
    "sg:classifiers":[
        {
            "category":"Personal",
            "subcategory":"Barber",
            "type":"Services"
        }
    ],
    "sg:phone":"+61 433 447 171",
    "sg:postcode":"4152",
    "sg:province":"QLD",
    "wof:name":"Carina Barbers",
    "wof:placetype":"venue"
},
  "geometry": {"coordinates":[153.09007263199999,-27.4957027435],"type":"Point"}
}