{
  "type": "Feature",
  "properties": {
    "addr:full":"7 Rutherford Drv Glenning Valley NSW 2261",
    "addr:housenumber":"7",
    "addr:postcode":"2261",
    "addr:street":"Rutherford Drv",
    "iso:country":"AU",
    "sg:address":"7 Rutherford Drv",
    "sg:city":"Glenning Valley",
    "sg:classifiers":[
        {
            "category":"Utilities",
            "subcategory":"Electric",
            "type":"Services"
        }
    ],
    "sg:phone":"+61 2 4388 4402",
    "sg:postcode":"2261",
    "sg:province":"NSW",
    "sg:tags":[
        "electrical",
        "contractor"
    ],
    "wof:name":"Phillips S J",
    "wof:placetype":"venue"
},
  "geometry": {"coordinates":[151.41554300000001,-33.344852],"type":"Point"}
}