{
  "type": "Feature",
  "properties": {
    "addr:full":"11 Railway Ave Railway Estate QLD 4810",
    "addr:housenumber":"11",
    "addr:postcode":"4810",
    "addr:street":"Railway Ave Railway",
    "iso:country":"AU",
    "sg:address":"11 Railway Ave",
    "sg:city":"Railway Estate",
    "sg:classifiers":[
        {
            "category":"Autos & Motor Vehicles",
            "subcategory":"Fuel & Gas Station",
            "type":"Retail Goods"
        }
    ],
    "sg:phone":"+61 7 4771 2495",
    "sg:postcode":"4810",
    "sg:province":"QLD",
    "wof:name":"Caltex Starway",
    "wof:placetype":"venue"
},
  "geometry": {"coordinates":[146.815506,-19.272303],"type":"Point"}
}