{
  "type": "Feature",
  "properties": {
    "iso:country":"AU",
    "sg:address":"12 Leigh St",
    "sg:city":"Adelaide",
    "sg:classifiers":[
        {
            "category":"Cafe",
            "type":"Food & Drink"
        }
    ],
    "sg:phone":"+61 8 8231 3333",
    "sg:postcode":"5000",
    "sg:province":"SA",
    "wof:name":"Sarahs Cafe @ Whereinn",
    "wof:placetype":"venue"
},
  "geometry": {"coordinates":[138.59739685100001,-34.9232292175],"type":"Point"}
}