{
  "type": "Feature",
  "properties": {
    "addr:full":"7 Ling Pl Palm Beach QLD 4221",
    "addr:housenumber":"7",
    "addr:postcode":"4221",
    "addr:street":"Ling Pl",
    "iso:country":"AU",
    "sg:address":"7 Ling Pl",
    "sg:city":"Palm Beach",
    "sg:classifiers":[
        {
            "category":"Professional",
            "subcategory":"Business Services",
            "type":"Services"
        }
    ],
    "sg:phone":"+61 7 5535 4764",
    "sg:postcode":"4221",
    "sg:province":"QLD",
    "sg:tags":[
        "drafting"
    ],
    "wof:name":"Ramon Wrye Design & Dr",
    "wof:placetype":"venue"
},
  "geometry": {"coordinates":[153.44723510700001,-28.1143436432],"type":"Point"}
}