{
  "type": "Feature",
  "properties": {
    "addr:full":"1/ 2 England St Dandenong VIC 3175",
    "addr:housenumber":"/ 2",
    "addr:postcode":"3175",
    "addr:street":"England St",
    "iso:country":"AU",
    "sg:address":"1/ 2 England St",
    "sg:city":"Dandenong",
    "sg:classifiers":[
        {
            "category":"Utilities",
            "subcategory":"Refuse",
            "type":"Services"
        }
    ],
    "sg:phone":"+61 3 9706 4915",
    "sg:postcode":"3175",
    "sg:province":"VIC",
    "sg:tags":[
        "disposal",
        "reduction",
        "waste"
    ],
    "wof:name":"Quantum Shred",
    "wof:placetype":"venue"
},
  "geometry": {"coordinates":[145.218826294,-38.0322227478],"type":"Point"}
}