{
  "type": "Feature",
  "properties": {
    "addr:full":"31 Bishop St Kelvin Grove QLD 4059",
    "addr:housenumber":"31",
    "addr:postcode":"4059",
    "addr:street":"Bishop St",
    "iso:country":"AU",
    "sg:address":"31 Bishop St",
    "sg:city":"Kelvin Grove",
    "sg:classifiers":[
        {
            "category":"Building & Trades",
            "subcategory":"Construction",
            "type":"Services"
        }
    ],
    "sg:phone":"+61 7 3501 4405",
    "sg:postcode":"4059",
    "sg:province":"QLD",
    "sg:tags":[
        "concrete",
        "contractor"
    ],
    "wof:name":"Penfold Concrete Services Pty Ltd",
    "wof:placetype":"venue"
},
  "geometry": {"coordinates":[153.00909423799999,-27.4432506561],"type":"Point"}
}