{
  "type": "Feature",
  "properties": {
    "addr:full":"Suite 7 340 Kingsway Caringbah NSW 2229",
    "addr:housenumber":"340",
    "addr:postcode":"2229",
    "addr:street":"Kingsway",
    "iso:country":"AU",
    "sg:address":"Suite 7 340",
    "sg:city":"Kingsway Caringbah",
    "sg:classifiers":[
        {
            "category":"Health Services",
            "subcategory":"Health Practitioner",
            "type":"Services"
        }
    ],
    "sg:phone":"+61 2 9524 6865",
    "sg:postcode":"2229",
    "sg:province":"NSW",
    "sg:tags":[
        "psychologist"
    ],
    "wof:name":"Janice Killey",
    "wof:placetype":"venue"
},
  "geometry": {"coordinates":[151.12168884299999,-34.0419120789],"type":"Point"}
}