{
  "type": "Feature",
  "properties": {
    "addr:full":"20 King Parrot Pde Gulmarrad NSW 2463",
    "addr:housenumber":"20",
    "addr:postcode":"2463",
    "addr:street":"King Parrot Pde",
    "iso:country":"AU",
    "sg:address":"20 King Parrot Pde",
    "sg:city":"Gulmarrad",
    "sg:classifiers":[
        {
            "category":"Commercial Area",
            "type":"Public Place"
        }
    ],
    "sg:phone":"+61 2 6645 4404",
    "sg:postcode":"2463",
    "sg:province":"NSW",
    "sg:tags":[
        "heavy",
        "carrier"
    ],
    "wof:name":"Nicholson & Page Transport",
    "wof:placetype":"venue"
},
  "geometry": {"coordinates":[153.224121094,-29.4935894012],"type":"Point"}
}