{
  "type": "Feature",
  "properties": {
    "addr:full":"132 Oban Rd Ringwood North VIC 3134",
    "addr:housenumber":"132",
    "addr:postcode":"3134",
    "addr:street":"Oban Rd",
    "iso:country":"AU",
    "sg:address":"132 Oban Rd",
    "sg:city":"Ringwood North",
    "sg:classifiers":[
        {
            "category":"Health Services",
            "subcategory":"Chiropractor",
            "type":"Services"
        }
    ],
    "sg:phone":"+61 3 9876 4711",
    "sg:postcode":"3134",
    "sg:province":"VIC",
    "wof:name":"Ringwood North-Norwood Chiropractic Centre",
    "wof:placetype":"venue"
},
  "geometry": {"coordinates":[145.233718872,-37.7937355042],"type":"Point"}
}