{
  "type": "Feature",
  "properties": {
    "addr:full":"Shop 33 798 Marion Rd Marion SA 5043",
    "addr:housenumber":"shop 33 798",
    "addr:postcode":"5043",
    "addr:street":"Marion Rd",
    "iso:country":"AU",
    "sg:address":"Shop 33 798 Marion Rd",
    "sg:city":"Marion",
    "sg:classifiers":[
        {
            "category":"Professional",
            "subcategory":"Engineering",
            "type":"Services"
        }
    ],
    "sg:phone":"+61 8 8377 1871",
    "sg:postcode":"5043",
    "sg:province":"SA",
    "sg:tags":[
        "engineer"
    ],
    "wof:name":"Hammat Precision Engineering",
    "wof:placetype":"venue"
},
  "geometry": {"coordinates":[138.558075,-35.00935],"type":"Point"}
}