{
  "type": "Feature",
  "properties": {
    "iso:country":"AU",
    "sg:address":"Shop 4/ 104 Melbourne St",
    "sg:city":"South Brisbane",
    "sg:classifiers":[
        {
            "category":"Deli",
            "type":"Food & Drink"
        }
    ],
    "sg:phone":"+61 7 3844 8415",
    "sg:postcode":"4101",
    "sg:province":"QLD",
    "sg:tags":[
        "delicatessen"
    ],
    "wof:name":"Rock On Melbourne",
    "wof:placetype":"venue"
},
  "geometry": {"coordinates":[153.01756286599999,-27.4745559692],"type":"Point"}
}