{
  "type": "Feature",
  "properties": {
    "iso:country":"AU",
    "sg:address":"2 / 14 King St",
    "sg:city":"Caboolture",
    "sg:classifiers":[
        {
            "category":"Health Services",
            "subcategory":"Dentist",
            "type":"Services"
        }
    ],
    "sg:phone":"+61 7 5495 5254",
    "sg:postcode":"4510",
    "sg:province":"QLD",
    "wof:name":"Glasshouse Orthodontics",
    "wof:placetype":"venue"
},
  "geometry": {"coordinates":[152.953217,-27.084867],"type":"Point"}
}