{
  "type": "Feature",
  "properties": {
    "iso:country":"AU",
    "sg:address":"Cnr Broad St Shp 5/ Anzac St",
    "sg:city":"Sarina",
    "sg:classifiers":[
        {
            "category":"Food & Beverages",
            "subcategory":"Bakery",
            "type":"Retail Goods"
        }
    ],
    "sg:phone":"+61 7 4943 1960",
    "sg:postcode":"4737",
    "sg:province":"QLD",
    "sg:tags":[
        "baker"
    ],
    "wof:name":"Alcorns Bakery Sarina",
    "wof:placetype":"venue"
},
  "geometry": {"coordinates":[149.216522,-21.420662],"type":"Point"}
}