{
  "type": "Feature",
  "properties": {
    "addr:full":"468- 470 Burwood Rd Belmore NSW 2192",
    "addr:housenumber":"470",
    "addr:postcode":"2192",
    "addr:street":"Burwood Rd",
    "iso:country":"AU",
    "sg:address":"468- 470 Burwood Rd",
    "sg:city":"Belmore",
    "sg:classifiers":[
        {
            "category":"Shopping",
            "subcategory":"Baby Store",
            "type":"Retail Goods"
        }
    ],
    "sg:phone":"+61 2 9750 2900",
    "sg:postcode":"2192",
    "sg:province":"NSW",
    "sg:tags":[
        "children's",
        "wear"
    ],
    "wof:name":"Sweet Elegant Creations Christening, Communion Wear & Bomboniere",
    "wof:placetype":"venue"
},
  "geometry": {"coordinates":[151.089844,-33.921398],"type":"Point"}
}