{
  "type": "Feature",
  "properties": {
    "addr:full":"5/ 22 Cohn St Carlisle WA 6101",
    "addr:housenumber":"/ 22",
    "addr:postcode":"6101",
    "addr:street":"Cohn St",
    "iso:country":"AU",
    "sg:address":"5/ 22 Cohn St",
    "sg:city":"Carlisle",
    "sg:classifiers":[
        {
            "category":"Wholesale",
            "subcategory":"Machinery & Supplies",
            "type":"Manufacturing & Wholesale Goods"
        }
    ],
    "sg:phone":"+61 8 9470 2377",
    "sg:postcode":"6101",
    "sg:province":"WA",
    "sg:tags":[
        "bearing",
        "bushing"
    ],
    "wof:name":"NAK Australia Pty Ltd",
    "wof:placetype":"venue"
},
  "geometry": {"coordinates":[115.921852112,-31.9854640961],"type":"Point"}
}