{
  "type": "Feature",
  "properties": {
    "addr:full":"98 Smith St Summer Hill NSW 2130",
    "addr:housenumber":"98",
    "addr:postcode":"2130",
    "addr:street":"Smith St",
    "iso:country":"AU",
    "sg:address":"98 Smith St",
    "sg:city":"Summer Hill",
    "sg:classifiers":[
        {
            "category":"Building & Trades",
            "subcategory":"Landscaping Services",
            "type":"Services"
        }
    ],
    "sg:phone":"+61 2 9988 0437",
    "sg:postcode":"2130",
    "sg:province":"NSW",
    "sg:tags":[
        "stump",
        "tree",
        "felling",
        "removal"
    ],
    "wof:name":"Environmental Tree Services",
    "wof:placetype":"venue"
},
  "geometry": {"coordinates":[151.13909912099999,-33.8922195435],"type":"Point"}
}