{
  "type": "Feature",
  "properties": {
    "iso:country":"AU",
    "sg:address":"31 Central Drv",
    "sg:city":"Burleigh Heads",
    "sg:classifiers":[
        {
            "category":"Wholesale",
            "subcategory":"Machinery & Supplies",
            "type":"Manufacturing & Wholesale Goods"
        }
    ],
    "sg:phone":"+61 7 5593 8533",
    "sg:postcode":"4220",
    "sg:province":"QLD",
    "sg:tags":[
        "engine",
        "petrol"
    ],
    "wof:name":"Rolin Automotive Imports",
    "wof:placetype":"venue"
},
  "geometry": {"coordinates":[153.423904419,-28.1068000793],"type":"Point"}
}