{
  "type": "Feature",
  "properties": {
    "addr:full":"Fox Rd Acacia Ridge QLD 4110",
    "addr:postcode":"4110",
    "addr:street":"Fox Rd",
    "iso:country":"AU",
    "sg:address":"Fox Rd",
    "sg:city":"Acacia Ridge",
    "sg:classifiers":[
        {
            "category":"Professional",
            "type":"Services"
        }
    ],
    "sg:phone":"+61 7 3272 7543",
    "sg:postcode":"4110",
    "sg:province":"QLD",
    "sg:tags":[
        "transport"
    ],
    "wof:name":"Specialised Container Transport",
    "wof:placetype":"venue"
},
  "geometry": {"coordinates":[153.03033447300001,-27.5912837982],"type":"Point"}
}