{
  "type": "Feature",
  "properties": {
    "addr:full":"Shp 4/ 165 Mt Buller Rd Mansfield VIC 3722",
    "addr:housenumber":"/ 165",
    "addr:postcode":"3722",
    "addr:street":"Mt Buller Rd",
    "iso:country":"AU",
    "sg:address":"Shp 4/ 165 Mt Buller Rd",
    "sg:city":"Mansfield",
    "sg:classifiers":[
        {
            "category":"Autos & Motor Vehicles",
            "subcategory":"Auto Supplies",
            "type":"Retail Goods"
        }
    ],
    "sg:phone":"+61 3 5779 1711",
    "sg:postcode":"3722",
    "sg:province":"VIC",
    "sg:tags":[
        "wheel",
        "four",
        "equipment",
        "drive",
        "accessory"
    ],
    "wof:name":"North East 4x4 Supplies",
    "wof:placetype":"venue"
},
  "geometry": {"coordinates":[146.099334717,-37.0611228943],"type":"Point"}
}