{
  "type": "Feature",
  "properties": {
    "iso:country":"AU",
    "sg:address":"164 Margaret St",
    "sg:city":"(PO Box 203) Toowoomba",
    "sg:classifiers":[
        {
            "category":"Restaurant",
            "type":"Food & Drink"
        }
    ],
    "sg:phone":"+61 7 4638 0066",
    "sg:postcode":"4350",
    "sg:province":"QLD",
    "wof:name":"Bindi Spot",
    "wof:placetype":"venue"
},
  "geometry": {"coordinates":[151.95494099999999,-27.561317],"type":"Point"}
}