{
  "type": "Feature",
  "properties": {
    "iso:country":"AU",
    "sg:address":"51 Tradelink Rd",
    "sg:city":"Browns Plains",
    "sg:classifiers":[
        {
            "category":"Wholesale",
            "subcategory":"Machinery & Supplies",
            "type":"Manufacturing & Wholesale Goods"
        }
    ],
    "sg:phone":"+61 7 3800 3636",
    "sg:postcode":"4118",
    "sg:province":"QLD",
    "sg:tags":[
        "equipment",
        "hydraulic"
    ],
    "wof:name":"Hy-Performance Fluid Connectors",
    "wof:placetype":"venue"
},
  "geometry": {"coordinates":[153.03399658199999,-27.664812088],"type":"Point"}
}