{
  "type": "Feature",
  "properties": {
    "addr:full":"3 Brighton Mews Hillarys WA 6025",
    "addr:housenumber":"3",
    "addr:postcode":"6025",
    "addr:street":"Brighton Mews",
    "iso:country":"AU",
    "sg:address":"3 Brighton Mews",
    "sg:city":"Hillarys",
    "sg:classifiers":[
        {
            "category":"Professional",
            "subcategory":"Printing & Photocopies",
            "type":"Services"
        }
    ],
    "sg:phone":"+61 8 9307 4972",
    "sg:postcode":"6025",
    "sg:province":"WA",
    "sg:tags":[
        "embroidery"
    ],
    "wof:name":"A Star Embroidery",
    "wof:placetype":"venue"
},
  "geometry": {"coordinates":[115.734176636,-31.807477951],"type":"Point"}
}