{
  "type": "Feature",
  "properties": {
    "addr:full":"Head Office 55 Moore St Austinmer NSW 2515",
    "addr:housenumber":"55",
    "addr:postcode":"2515",
    "addr:street":"Moore St",
    "iso:country":"AU",
    "sg:address":"Head Office 55 Moore St",
    "sg:city":"Austinmer",
    "sg:classifiers":[
        {
            "category":"Professional",
            "subcategory":"Computer Services",
            "type":"Services"
        }
    ],
    "sg:phone":"+61 2 4268 6466",
    "sg:postcode":"2515",
    "sg:province":"NSW",
    "sg:tags":[
        "consultant",
        "system"
    ],
    "wof:name":"Proactive I.T.",
    "wof:placetype":"venue"
},
  "geometry": {"coordinates":[150.93022199999999,-34.306801],"type":"Point"}
}