{
  "type": "Feature",
  "properties": {
    "addr:full":"Factory 2/ 4 Burgess Rd Bayswater North VIC 3153",
    "addr:housenumber":"/ 4",
    "addr:postcode":"3153",
    "addr:street":"Burgess Rd",
    "iso:country":"AU",
    "sg:address":"Factory 2/ 4 Burgess Rd",
    "sg:city":"Bayswater North",
    "sg:classifiers":[
        {
            "category":"Professional",
            "subcategory":"Engineering",
            "type":"Services"
        }
    ],
    "sg:phone":"+61 3 9761 4198",
    "sg:postcode":"3153",
    "sg:province":"VIC",
    "sg:tags":[
        "engineer"
    ],
    "wof:name":"RP & M Fabrication",
    "wof:placetype":"venue"
},
  "geometry": {"coordinates":[145.28851318400001,-37.8225746155],"type":"Point"}
}