{
  "type": "Feature",
  "properties": {
    "addr:full":"14 Andrew St Mt Waverley VIC 3149",
    "addr:housenumber":"14",
    "addr:postcode":"3149",
    "addr:street":"Andrew St Mt",
    "iso:country":"AU",
    "sg:address":"14 Andrew St",
    "sg:city":"Mt Waverley",
    "sg:classifiers":[
        {
            "category":"Food & Beverages",
            "subcategory":"Liquor & Beverages",
            "type":"Retail Goods"
        }
    ],
    "sg:phone":"+61 3 9808 4105",
    "sg:postcode":"3149",
    "sg:province":"VIC",
    "sg:tags":[
        "store"
    ],
    "wof:name":"Highbury Cellars",
    "wof:placetype":"venue"
},
  "geometry": {"coordinates":[145.12359619099999,-37.8575057983],"type":"Point"}
}