{
  "type": "Feature",
  "properties": {
    "iso:country":"AU",
    "sg:address":"41 Tank St",
    "sg:city":"Gladstone",
    "sg:classifiers":[
        {
            "category":"Health Services",
            "subcategory":"Doctor",
            "type":"Services"
        }
    ],
    "sg:phone":"+61 7 4972 6470",
    "sg:postcode":"4680",
    "sg:province":"QLD",
    "sg:tags":[
        "medical",
        "practitioner"
    ],
    "wof:name":"Diefenbach Les Dr",
    "wof:placetype":"venue"
},
  "geometry": {"coordinates":[151.260131836,-23.8486537933],"type":"Point"}
}