{
  "type": "Feature",
  "properties": {
    "iso:country":"AU",
    "sg:address":"97 Church St",
    "sg:city":"Maitland",
    "sg:classifiers":[
        {
            "category":"Shopping",
            "type":"Retail Goods"
        }
    ],
    "sg:phone":"+61 2 4933 4983",
    "sg:postcode":"2320",
    "sg:province":"NSW",
    "sg:tags":[
        "agent",
        "stock"
    ],
    "wof:name":"Hicks Stewart Real Estate Pty Ltd",
    "wof:placetype":"venue"
},
  "geometry": {"coordinates":[151.55238342300001,-32.7367324829],"type":"Point"}
}