{
  "type": "Feature",
  "properties": {
    "addr:full":"21 Irvine Pde Yarrawonga VIC 3730",
    "addr:housenumber":"21",
    "addr:postcode":"3730",
    "addr:street":"Irvine Pde",
    "iso:country":"AU",
    "sg:address":"21 Irvine Pde",
    "sg:city":"Yarrawonga",
    "sg:classifiers":[
        {
            "category":"Building & Trades",
            "subcategory":"Construction",
            "type":"Services"
        }
    ],
    "sg:phone":"+61 3 5744 3768",
    "sg:postcode":"3730",
    "sg:province":"VIC",
    "sg:tags":[
        "earth",
        "excavating",
        "moving",
        "contractor"
    ],
    "wof:name":"Hilton Younger",
    "wof:placetype":"venue"
},
  "geometry": {"coordinates":[145.99935913100001,-36.0124740601],"type":"Point"}
}