{
  "type": "Feature",
  "properties": {
    "addr:full":"1220 Castlereigh Hwy Mudgee NSW 2850",
    "addr:housenumber":"1220",
    "addr:postcode":"2850",
    "addr:street":"Castlereigh Hwy",
    "iso:country":"AU",
    "sg:address":"1220 Castlereigh Hwy",
    "sg:city":"Mudgee",
    "sg:classifiers":[
        {
            "category":"Farming",
            "subcategory":"Vineyard",
            "type":"Manufacturing & Wholesale Goods"
        }
    ],
    "sg:phone":"+61 2 6373 1245",
    "sg:postcode":"2850",
    "sg:province":"NSW",
    "sg:tags":[
        "winery"
    ],
    "wof:name":"Simon Gilbert Wine Services Pty Ltd",
    "wof:placetype":"venue"
},
  "geometry": {"coordinates":[149.600098,-32.609043],"type":"Point"}
}