{
  "type": "Feature",
  "properties": {
    "addr:full":"37 Sheppard St Hume ACT 2620",
    "addr:housenumber":"37",
    "addr:postcode":"2620",
    "addr:street":"Sheppard St",
    "iso:country":"AU",
    "sg:address":"37 Sheppard St",
    "sg:city":"Hume",
    "sg:classifiers":[
        {
            "category":"Building & Trades",
            "subcategory":"Construction",
            "type":"Services"
        }
    ],
    "sg:phone":"+61 2 6260 1570",
    "sg:postcode":"2620",
    "sg:province":"ACT",
    "sg:tags":[
        "industrial",
        "commercial",
        "air conditioning"
    ],
    "wof:name":"York Australia",
    "wof:placetype":"venue"
},
  "geometry": {"coordinates":[149.17018127399999,-35.3889923096],"type":"Point"}
}