{
  "type": "Feature",
  "properties": {
    "addr:full":"38 Martinez Ave West End (Brisbane) QLD 4101",
    "addr:housenumber":"38",
    "addr:postcode":"4101",
    "addr:street":"Martinez Ave",
    "iso:country":"AU",
    "sg:address":"38 Martinez Ave",
    "sg:city":"West End (Brisbane)",
    "sg:classifiers":[
        {
            "category":"Building & Trades",
            "subcategory":"Construction",
            "type":"Services"
        }
    ],
    "sg:phone":"+61 7 4728 9568",
    "sg:postcode":"4101",
    "sg:province":"QLD",
    "sg:tags":[
        "concrete",
        "contractor"
    ],
    "wof:name":"L J & J Pepper Concreting",
    "wof:placetype":"venue"
},
  "geometry": {"coordinates":[153.012161255,-27.4802494049],"type":"Point"}
}