{
  "type": "Feature",
  "properties": {
    "addr:full":"10 Raphael Rd Winnellie NT 0820",
    "addr:housenumber":"10",
    "addr:postcode":"nt 0820",
    "addr:street":"Raphael Rd",
    "iso:country":"AU",
    "sg:address":"10 Raphael Rd",
    "sg:city":"Winnellie",
    "sg:classifiers":[
        {
            "category":"Retail",
            "subcategory":"Auto Rental",
            "type":"Services"
        }
    ],
    "sg:phone":"+61 8 8947 2467",
    "sg:postcode":"0820",
    "sg:province":"NT",
    "sg:tags":[
        "car",
        "hire",
        "minibus"
    ],
    "wof:name":"Gecko Car Rentals",
    "wof:placetype":"venue"
},
  "geometry": {"coordinates":[130.86358642600001,-12.431429863],"type":"Point"}
}