{
  "type": "Feature",
  "properties": {
    "iso:country":"AU",
    "sg:address":"628 Coronation Drv",
    "sg:city":"Toowong",
    "sg:classifiers":[
        {
            "category":"Banks & Credit Unions",
            "subcategory":"Investment Brokerage",
            "type":"Services"
        }
    ],
    "sg:phone":"+61 1300 657 509",
    "sg:postcode":"4066",
    "sg:province":"QLD",
    "wof:name":"Oakland Investments (Aus) Ltd",
    "wof:placetype":"venue"
},
  "geometry": {"coordinates":[152.99392700199999,-27.4849967957],"type":"Point"}
}