{
  "type": "Feature",
  "properties": {
    "addr:full":"3 Expansion St Molendinar QLD 4214",
    "addr:housenumber":"3",
    "addr:postcode":"4214",
    "addr:street":"Expansion St",
    "iso:country":"AU",
    "sg:address":"3 Expansion St",
    "sg:city":"Molendinar",
    "sg:classifiers":[
        {
            "category":"Shopping",
            "subcategory":"Bicycles & Sporting Goods",
            "type":"Retail Goods"
        }
    ],
    "sg:phone":"+61 7 5564 7757",
    "sg:postcode":"4214",
    "sg:province":"QLD",
    "sg:tags":[
        "chemical",
        "equipment",
        "pool",
        "swimming"
    ],
    "wof:name":"International Pool Products Pty Ltd.",
    "wof:placetype":"venue"
},
  "geometry": {"coordinates":[153.35925293,-27.9762592316],"type":"Point"}
}