{
  "type": "Feature",
  "properties": {
    "addr:full":"PO Box 266 Warburton VIC 3799",
    "addr:postcode":"3799",
    "iso:country":"AU",
    "sg:address":"PO Box 266",
    "sg:city":"Warburton",
    "sg:classifiers":[
        {
            "category":"Professional",
            "subcategory":"Engineering",
            "type":"Services"
        }
    ],
    "sg:phone":"+61 3 5966 5959",
    "sg:postcode":"3799",
    "sg:province":"VIC",
    "sg:tags":[
        "engineer"
    ],
    "wof:name":"Statewide Engineering",
    "wof:placetype":"venue"
},
  "geometry": {"coordinates":[145.707305908,-37.7111206055],"type":"Point"}
}