{
  "type": "Feature",
  "properties": {
    "addr:full":"117 Upper Heidelberg Rd Ivanhoe VIC 3079",
    "addr:housenumber":"117",
    "addr:postcode":"3079",
    "addr:street":"Upper Heidelberg Rd",
    "iso:country":"AU",
    "sg:address":"117 Upper Heidelberg Rd",
    "sg:city":"Ivanhoe",
    "sg:classifiers":[
        {
            "category":"Casinos & Gambling",
            "type":"Entertainment"
        }
    ],
    "sg:phone":"+61 3 9497 3841",
    "sg:postcode":"3079",
    "sg:province":"VIC",
    "sg:tags":[
        "lottery",
        "agent"
    ],
    "wof:name":"Centreway Lotto & Newsagency",
    "wof:placetype":"venue"
},
  "geometry": {"coordinates":[145.041946411,-37.7689476013],"type":"Point"}
}