{
  "type": "Feature",
  "properties": {
    "addr:full":"250 Rouse St Tenterfield NSW 2372",
    "addr:housenumber":"250",
    "addr:postcode":"2372",
    "addr:street":"Rouse St",
    "iso:country":"AU",
    "sg:address":"250 Rouse St",
    "sg:city":"Tenterfield",
    "sg:classifiers":[
        {
            "category":"Food & Beverages",
            "subcategory":"Fruits & Vegetables",
            "type":"Retail Goods"
        }
    ],
    "sg:phone":"+61 2 6736 2072",
    "sg:postcode":"2372",
    "sg:province":"NSW",
    "sg:tags":[
        "greengrocer",
        "fruiterer"
    ],
    "wof:name":"Cumquats Nursery & Fruit Market",
    "wof:placetype":"venue"
},
  "geometry": {"coordinates":[152.018844605,-29.0542583466],"type":"Point"}
}