{
  "type": "Feature",
  "properties": {
    "iso:country":"AU",
    "sg:address":"7 Gary Crt",
    "sg:city":"Carrara",
    "sg:classifiers":[
        {
            "category":"Professional",
            "type":"Services"
        }
    ],
    "sg:phone":"+61 413 871 886",
    "sg:postcode":"4211",
    "sg:province":"QLD",
    "sg:tags":[
        "courier"
    ],
    "wof:name":"Pony Express Courier Services",
    "wof:placetype":"venue"
},
  "geometry": {"coordinates":[153.36415100100001,-28.021112442],"type":"Point"}
}