{
  "type": "Feature",
  "properties": {
    "addr:full":"111 Northgate Drv Thomastown VIC 3074",
    "addr:housenumber":"111",
    "addr:postcode":"3074",
    "addr:street":"Northgate Drv",
    "iso:country":"AU",
    "sg:address":"111 Northgate Drv",
    "sg:city":"Thomastown",
    "sg:classifiers":[
        {
            "category":"Utilities",
            "subcategory":"Telephone",
            "type":"Services"
        }
    ],
    "sg:phone":"+61 3 9464 3901",
    "sg:postcode":"3074",
    "sg:province":"VIC",
    "sg:tags":[
        "equipment",
        "system"
    ],
    "wof:name":"Voiceweb-Voipnow Pty Ltd",
    "wof:placetype":"venue"
},
  "geometry": {"coordinates":[145.029953003,-37.6888237],"type":"Point"}
}