{
  "type": "Feature",
  "properties": {
    "iso:country":"AU",
    "sg:address":"Shop 3/ 192 George St",
    "sg:city":"Windsor",
    "sg:classifiers":[
        {
            "category":"Airline",
            "type":"Transportation"
        }
    ],
    "sg:phone":"+61 2 4577 4766",
    "sg:postcode":"2756",
    "sg:province":"NSW",
    "sg:tags":[
        "agent"
    ],
    "wof:name":"Hawkesbury Travel",
    "wof:placetype":"venue"
},
  "geometry": {"coordinates":[150.81704711899999,-33.6092720032],"type":"Point"}
}