{
  "type": "Feature",
  "properties": {
    "addr:full":"242 George St Windsor NSW 2756",
    "addr:housenumber":"242",
    "addr:postcode":"2756",
    "addr:street":"George St",
    "iso:country":"AU",
    "sg:address":"242 George St",
    "sg:city":"Windsor",
    "sg:classifiers":[
        {
            "category":"Shopping",
            "subcategory":"Mobile Phones",
            "type":"Retail Goods"
        }
    ],
    "sg:phone":"+61 2 4577 2544",
    "sg:postcode":"2756",
    "sg:province":"NSW",
    "sg:tags":[
        "telephone",
        "accessory"
    ],
    "wof:name":"Brian Keegans Electrical",
    "wof:placetype":"venue"
},
  "geometry": {"coordinates":[150.81721496599999,-33.6091537476],"type":"Point"}
}