{
  "type": "Feature",
  "properties": {
    "addr:full":"14 Provident Av Glynde SA 5070",
    "addr:housenumber":"14",
    "addr:postcode":"5070",
    "addr:street":"Provident Av",
    "iso:country":"AU",
    "sg:address":"14 Provident Av",
    "sg:city":"Glynde",
    "sg:classifiers":[
        {
            "category":"Retail",
            "subcategory":"Auto Repair",
            "type":"Services"
        }
    ],
    "sg:phone":"+61 8 8365 5100",
    "sg:postcode":"5070",
    "sg:province":"SA",
    "sg:tags":[
        "repairer",
        "motor",
        "engineer"
    ],
    "wof:name":"Peter & Rick's Auto Workshop",
    "wof:placetype":"venue"
},
  "geometry": {"coordinates":[138.65315246599999,-34.8947753906],"type":"Point"}
}