{
  "type": "Feature",
  "properties": {
    "addr:full":"9 Cook St Forestville NSW 2087",
    "addr:housenumber":"9",
    "addr:postcode":"2087",
    "addr:street":"Cook St",
    "iso:country":"AU",
    "sg:address":"9 Cook St",
    "sg:city":"Forestville",
    "sg:classifiers":[
        {
            "category":"Building & Trades",
            "subcategory":"Construction",
            "type":"Services"
        }
    ],
    "sg:phone":"+61 2 9975 6561",
    "sg:postcode":"2087",
    "sg:province":"NSW",
    "sg:tags":[
        "concrete",
        "contractor"
    ],
    "wof:name":"CTI Sydney Pty Ltd",
    "wof:placetype":"venue"
},
  "geometry": {"coordinates":[151.219116211,-33.7604904175],"type":"Point"}
}