{
  "type": "Feature",
  "properties": {
    "addr:full":"136 Elizabeth Drv Liverpool NSW 2170",
    "addr:housenumber":"136",
    "addr:postcode":"2170",
    "addr:street":"Elizabeth Drv",
    "iso:country":"AU",
    "sg:address":"136 Elizabeth Drv",
    "sg:city":"Liverpool",
    "sg:classifiers":[
        {
            "category":"Autos & Motor Vehicles",
            "subcategory":"Automobile Sales",
            "type":"Retail Goods"
        }
    ],
    "sg:phone":"+61 2 9602 3442",
    "sg:postcode":"2170",
    "sg:province":"NSW",
    "sg:tags":[
        "car",
        "used"
    ],
    "wof:name":"Elizabeth Drive Auto Centre",
    "wof:placetype":"venue"
},
  "geometry": {"coordinates":[150.910400391,-33.9160728455],"type":"Point"}
}