{
  "type": "Feature",
  "properties": {
    "iso:country":"AU",
    "sg:address":"355 Arina Rd",
    "sg:city":"Bargo",
    "sg:classifiers":[
        {
            "category":"Government",
            "subcategory":"Department Of Motor Vehicles",
            "type":"Public Place"
        }
    ],
    "sg:phone":"+61 2 4684 3080",
    "sg:postcode":"2574",
    "sg:province":"NSW",
    "sg:tags":[
        "tank",
        "cleaning"
    ],
    "wof:name":"Smith's Water & Maintenance Services",
    "wof:placetype":"venue"
},
  "geometry": {"coordinates":[150.60989379899999,-34.2815551758],"type":"Point"}
}