{
  "type": "Feature",
  "properties": {
    "iso:country":"AU",
    "sg:address":"8 Kemp St",
    "sg:city":"Wallsend",
    "sg:classifiers":[
        {
            "category":"Retail",
            "subcategory":"Veterinary Services",
            "type":"Services"
        }
    ],
    "sg:phone":"+61 2 4951 4222",
    "sg:postcode":"2287",
    "sg:province":"NSW",
    "sg:tags":[
        "surgeon"
    ],
    "wof:name":"Vetcare Hospitals",
    "wof:placetype":"venue"
},
  "geometry": {"coordinates":[151.670852661,-32.9019126892],"type":"Point"}
}