{
  "type": "Feature",
  "properties": {
    "addr:full":"5 Hospital Rd Emerald QLD 4720",
    "addr:housenumber":"5",
    "addr:postcode":"4720",
    "addr:street":"Hospital Rd",
    "iso:country":"AU",
    "sg:address":"5 Hospital Rd",
    "sg:city":"Emerald",
    "sg:classifiers":[
        {
            "category":"Wholesale",
            "subcategory":"Painting Supplies",
            "type":"Manufacturing & Wholesale Goods"
        }
    ],
    "sg:phone":"+61 7 4982 4466",
    "sg:postcode":"4720",
    "sg:province":"QLD",
    "sg:tags":[
        "equipment",
        "spraying"
    ],
    "wof:name":"Earle's Paint Place",
    "wof:placetype":"venue"
},
  "geometry": {"coordinates":[148.157836914,-23.5231761932],"type":"Point"}
}