{
  "type": "Feature",
  "properties": {
    "addr:full":"The Rear of 281 Elizabeth St Melbourne VIC 3000",
    "addr:housenumber":"281",
    "addr:postcode":"3000",
    "addr:street":"Elizabeth St",
    "iso:country":"AU",
    "sg:address":"The Rear of 281 Elizabeth St",
    "sg:city":"Melbourne",
    "sg:classifiers":[
        {
            "category":"Shopping",
            "subcategory":"Discount & Variety Stores",
            "type":"Retail Goods"
        }
    ],
    "sg:phone":"+61 3 9600 0234",
    "sg:postcode":"3000",
    "sg:province":"VIC",
    "sg:tags":[
        "shop",
        "adult"
    ],
    "wof:name":"Erotica Plus Book Shop",
    "wof:placetype":"venue"
},
  "geometry": {"coordinates":[144.96200561500001,-37.8120689392],"type":"Point"}
}