{
  "type": "Feature",
  "properties": {
    "addr:full":"23 Encounter St Callala Bay NSW 2540",
    "addr:housenumber":"23",
    "addr:postcode":"2540",
    "addr:street":"Encounter St",
    "iso:country":"AU",
    "sg:address":"23 Encounter St",
    "sg:city":"Callala Bay",
    "sg:classifiers":[
        {
            "category":"Building & Trades",
            "subcategory":"Plumbing",
            "type":"Services"
        }
    ],
    "sg:phone":"+61 2 4446 5712",
    "sg:postcode":"2540",
    "sg:province":"NSW",
    "sg:tags":[
        "plumber",
        "gasfitters"
    ],
    "wof:name":"St Johns Plumbing Service",
    "wof:placetype":"venue"
},
  "geometry": {"coordinates":[150.725631714,-34.9911804199],"type":"Point"}
}