{
  "type": "Feature",
  "properties": {
    "iso:country":"AU",
    "sg:address":"28 Browns Plains Rd",
    "sg:city":"Browns Plains",
    "sg:classifiers":[
        {
            "category":"Real Estate",
            "subcategory":"Real Estate Agent",
            "type":"Services"
        }
    ],
    "sg:phone":"+61 7 3800 8606",
    "sg:postcode":"4118",
    "sg:province":"QLD",
    "wof:name":"First National Real Estate Group",
    "wof:placetype":"venue"
},
  "geometry": {"coordinates":[153.047332764,-27.6620559692],"type":"Point"}
}