{
  "type": "Feature",
  "properties": {
    "iso:country":"AU",
    "sg:address":"Teusner Rd",
    "sg:city":"Concordia",
    "sg:classifiers":[
        {
            "category":"Farming",
            "subcategory":"Farm",
            "type":"Manufacturing & Wholesale Goods"
        }
    ],
    "sg:phone":"+61 8 8522 6993",
    "sg:postcode":"5118",
    "sg:province":"SA",
    "sg:tags":[
        "farmer"
    ],
    "wof:name":"Teusner F H & Sons",
    "wof:placetype":"venue"
},
  "geometry": {"coordinates":[138.800583,-34.585758],"type":"Point"}
}