{
  "type": "Feature",
  "properties": {
    "addr:full":"47 Gulfview Rd Christies Beach SA 5165",
    "addr:housenumber":"47",
    "addr:postcode":"5165",
    "addr:street":"Gulfview Rd",
    "iso:country":"AU",
    "sg:address":"47 Gulfview Rd",
    "sg:city":"Christies Beach",
    "sg:classifiers":[
        {
            "category":"Retail",
            "subcategory":"Self-service Laundry",
            "type":"Services"
        }
    ],
    "sg:phone":"+61 8 8382 4126",
    "sg:postcode":"5165",
    "sg:province":"SA",
    "wof:name":"Laundry Centre Christies Beach",
    "wof:placetype":"venue"
},
  "geometry": {"coordinates":[138.47671508799999,-35.1307487488],"type":"Point"}
}