{
  "type": "Feature",
  "properties": {
    "iso:country":"AU",
    "sg:address":"U2 / 5 Jaggs Way",
    "sg:city":"Kardinya",
    "sg:classifiers":[
        {
            "category":"Professional",
            "subcategory":"Detective & Security Services",
            "type":"Services"
        }
    ],
    "sg:phone":"+61 8 9314 1711",
    "sg:postcode":"6163",
    "sg:province":"WA",
    "sg:tags":[
        "consultant",
        "system"
    ],
    "wof:name":"Satellite Security Services Pty Ltd",
    "wof:placetype":"venue"
},
  "geometry": {"coordinates":[115.804382,-32.059837],"type":"Point"}
}