{
  "type": "Feature",
  "properties": {
    "addr:full":"4 Nelson Rd Box Hill VIC 3128",
    "addr:housenumber":"4",
    "addr:postcode":"3128",
    "addr:street":"Nelson Rd",
    "iso:country":"AU",
    "sg:address":"4 Nelson Rd",
    "sg:city":"Box Hill",
    "sg:classifiers":[
        {
            "category":"Banks & Credit Unions",
            "subcategory":"Investment Brokerage",
            "type":"Services"
        }
    ],
    "sg:phone":"+61 3 9895 0257",
    "sg:postcode":"3128",
    "sg:province":"VIC",
    "sg:tags":[
        "repairer",
        "typewriter"
    ],
    "wof:name":"Capital Business Machines",
    "wof:placetype":"venue"
},
  "geometry": {"coordinates":[145.119537353,-37.8170776367],"type":"Point"}
}