{
  "type": "Feature",
  "properties": {
    "addr:full":"18 Houston St Epping VIC 3076",
    "addr:housenumber":"18",
    "addr:postcode":"3076",
    "addr:street":"Houston St",
    "iso:country":"AU",
    "sg:address":"18 Houston St",
    "sg:city":"Epping",
    "sg:classifiers":[
        {
            "category":"Retail",
            "subcategory":"Storage",
            "type":"Services"
        }
    ],
    "sg:phone":"+61 414 075 639",
    "sg:postcode":"3076",
    "sg:province":"VIC",
    "sg:tags":[
        "removal",
        "furniture"
    ],
    "wof:name":"Wayne Evans",
    "wof:placetype":"venue"
},
  "geometry": {"coordinates":[145.09121704099999,-37.9827957153],"type":"Point"}
}