{
  "type": "Feature",
  "properties": {
    "addr:full":"129 Smart Rd Modbury SA 5092",
    "addr:housenumber":"129",
    "addr:postcode":"5092",
    "addr:street":"Smart Rd",
    "iso:country":"AU",
    "sg:address":"129 Smart Rd",
    "sg:city":"Modbury",
    "sg:classifiers":[
        {
            "category":"Shopping",
            "subcategory":"Computers & Home Electronics",
            "type":"Retail Goods"
        }
    ],
    "sg:phone":"+61 8 8265 1003",
    "sg:postcode":"5092",
    "sg:province":"SA",
    "sg:tags":[
        "hardware",
        "equipment"
    ],
    "wof:name":"Command Computer Services",
    "wof:placetype":"venue"
},
  "geometry": {"coordinates":[138.69793701200001,-34.8329925537],"type":"Point"}
}