{
  "type": "Feature",
  "properties": {
    "addr:full":"2 Derriton St Ferndale WA 6148",
    "addr:housenumber":"2",
    "addr:postcode":"6148",
    "addr:street":"Derriton St",
    "iso:country":"AU",
    "sg:address":"2 Derriton St",
    "sg:city":"Ferndale",
    "sg:classifiers":[
        {
            "category":"Building & Trades",
            "subcategory":"Construction",
            "type":"Services"
        }
    ],
    "sg:phone":"+61 8 9451 4249",
    "sg:postcode":"6148",
    "sg:province":"WA",
    "sg:tags":[
        "welding"
    ],
    "wof:name":"Auski Engineers Pty Ltd",
    "wof:placetype":"venue"
},
  "geometry": {"coordinates":[115.921288,-32.026871],"type":"Point"}
}