{
  "type": "Feature",
  "properties": {
    "iso:country":"AU",
    "sg:address":"216 Conadilly St",
    "sg:city":"Gunnedah",
    "sg:classifiers":[
        {
            "category":"Shopping",
            "subcategory":"Clothing, Apparel, & Fashions",
            "type":"Retail Goods"
        }
    ],
    "sg:phone":"+61 2 6742 1954",
    "sg:postcode":"2380",
    "sg:province":"NSW",
    "sg:tags":[
        "jean"
    ],
    "wof:name":"Blue Denim Jeanery",
    "wof:placetype":"venue"
},
  "geometry": {"coordinates":[150.25309753400001,-30.9772911072],"type":"Point"}
}