{
  "type": "Feature",
  "properties": {
    "iso:country":"AU",
    "sg:address":"Unit 2/ 13 Bishop St",
    "sg:city":"Stuart Park",
    "sg:classifiers":[
        {
            "category":"Building & Trades",
            "subcategory":"Construction",
            "type":"Services"
        }
    ],
    "sg:phone":"+61 8 8947 0004",
    "sg:postcode":"0820",
    "sg:province":"NT",
    "sg:tags":[
        "waterproofing",
        "contractor"
    ],
    "wof:name":"RST Tiling Pty Ltd",
    "wof:placetype":"venue"
},
  "geometry": {"coordinates":[130.851638794,-12.433347702],"type":"Point"}
}