{
  "type": "Feature",
  "properties": {
    "iso:country":"AU",
    "sg:address":"157 Briens Rd",
    "sg:city":"Northmead",
    "sg:classifiers":[
        {
            "category":"Home & Garden",
            "subcategory":"Building Materials",
            "type":"Retail Goods"
        }
    ],
    "sg:phone":"+61 2 9630 5622",
    "sg:postcode":"2152",
    "sg:province":"NSW",
    "sg:tags":[
        "fitting",
        "door"
    ],
    "sg:website":"http://www.finewood.com.au",
    "wof:name":"Finewood Products Pty Ltd",
    "wof:placetype":"venue"
},
  "geometry": {"coordinates":[150.98472595199999,-33.7976951599],"type":"Point"}
}