{
  "type": "Feature",
  "properties": {
    "iso:country":"AU",
    "sg:address":"219 Mount St",
    "sg:city":"Fernmount",
    "sg:classifiers":[
        {
            "category":"Real Estate",
            "subcategory":"Architect",
            "type":"Services"
        }
    ],
    "sg:phone":"+61 2 6655 0641",
    "sg:postcode":"2454",
    "sg:province":"NSW",
    "wof:name":"Christian Fisher Design",
    "wof:placetype":"venue"
},
  "geometry": {"coordinates":[152.94975299999999,-30.478485],"type":"Point"}
}