{
  "type": "Feature",
  "properties": {
    "addr:full":"26 Mills St Cheltenham VIC 3192",
    "addr:housenumber":"26",
    "addr:postcode":"3192",
    "addr:street":"Mills St",
    "iso:country":"AU",
    "sg:address":"26 Mills St",
    "sg:city":"Cheltenham",
    "sg:classifiers":[
        {
            "category":"Personal",
            "subcategory":"Skin Care",
            "type":"Services"
        }
    ],
    "sg:phone":"+61 3 9584 3326",
    "sg:postcode":"3192",
    "sg:province":"VIC",
    "sg:tags":[
        "hair",
        "product"
    ],
    "wof:name":"Sprayset Products",
    "wof:placetype":"venue"
},
  "geometry": {"coordinates":[145.074783325,-37.9564857483],"type":"Point"}
}