{
  "type": "Feature",
  "properties": {
    "iso:country":"AU",
    "sg:address":"43-51 Queen St",
    "sg:city":"Melbourne",
    "sg:classifiers":[
        {
            "category":"Personal",
            "type":"Services"
        }
    ],
    "sg:phone":"+61 3 9614 4556",
    "sg:postcode":"3000",
    "sg:province":"VIC",
    "sg:tags":[
        "introduction",
        "social"
    ],
    "sg:website":"http://www.itsjustlunch.com",
    "wof:name":"It's Just Lunch Melbourne",
    "wof:placetype":"venue"
},
  "geometry": {"coordinates":[144.961791992,-37.8176345825],"type":"Point"}
}