{
  "type": "Feature",
  "properties": {
    "addr:full":"377 Sheridan St Cairns North QLD 4870",
    "addr:housenumber":"377",
    "addr:postcode":"4870",
    "addr:street":"Sheridan St",
    "iso:country":"AU",
    "sg:address":"377 Sheridan St",
    "sg:city":"Cairns North",
    "sg:classifiers":[
        {
            "category":"Health Services",
            "subcategory":"Doctor",
            "type":"Services"
        }
    ],
    "sg:phone":"+61 7 4051 6299",
    "sg:postcode":"4870",
    "sg:province":"QLD",
    "sg:tags":[
        "medical",
        "practitioner"
    ],
    "wof:name":"McAuliffe Michael",
    "wof:placetype":"venue"
},
  "geometry": {"coordinates":[145.757156372,-16.9030723572],"type":"Point"}
}