{
  "type": "Feature",
  "properties": {
    "iso:country":"AU",
    "sg:address":"Suite 1/ 16 Hannah St",
    "sg:city":"Beecroft",
    "sg:classifiers":[
        {
            "category":"Banks & Credit Unions",
            "subcategory":"Bank",
            "type":"Services"
        }
    ],
    "sg:phone":"+61 2 9980 2788",
    "sg:postcode":"2119",
    "sg:province":"NSW",
    "sg:tags":[
        "broker",
        "mortgage"
    ],
    "wof:name":"Mark Berry Actuary Financial Planner & Mortgage Brokers",
    "wof:placetype":"venue"
},
  "geometry": {"coordinates":[151.06524658199999,-33.7492752075],"type":"Point"}
}