{
  "type": "Feature",
  "properties": {
    "addr:full":"7 Farzana Pl Underwood QLD 4119",
    "addr:housenumber":"7",
    "addr:postcode":"4119",
    "addr:street":"Farzana Pl",
    "iso:country":"AU",
    "sg:address":"7 Farzana Pl",
    "sg:city":"Underwood",
    "sg:classifiers":[
        {
            "category":"Organizations",
            "subcategory":"Professional Association",
            "type":"Services"
        }
    ],
    "sg:phone":"+61 407 282 800",
    "sg:postcode":"4119",
    "sg:province":"QLD",
    "sg:tags":[
        "web",
        "internet"
    ],
    "wof:name":"Limebox Hosting Solutions",
    "wof:placetype":"venue"
},
  "geometry": {"coordinates":[153.105224609,-27.6154785156],"type":"Point"}
}