{
  "type": "Feature",
  "properties": {
    "iso:country":"AU",
    "sg:address":"317 Princess Hwy",
    "sg:city":"Werribee",
    "sg:classifiers":[
        {
            "category":"Retail",
            "subcategory":"Auto Rental",
            "type":"Services"
        }
    ],
    "sg:phone":"+61 3 9742 7490",
    "sg:postcode":"3030",
    "sg:province":"VIC",
    "sg:tags":[
        "car",
        "hire",
        "minibus"
    ],
    "wof:name":"General Car & Truck Rentals",
    "wof:placetype":"venue"
},
  "geometry": {"coordinates":[144.698654,-37.884987],"type":"Point"}
}