{
  "type": "Feature",
  "properties": {
    "addr:full":"36 Lorne Pde Surrey Hills VIC 3127",
    "addr:housenumber":"36",
    "addr:postcode":"3127",
    "addr:street":"Lorne Pde",
    "iso:country":"AU",
    "sg:address":"36 Lorne Pde",
    "sg:city":"Surrey Hills",
    "sg:classifiers":[
        {
            "category":"Professional",
            "subcategory":"Computer Services",
            "type":"Services"
        }
    ],
    "sg:phone":"+61 3 9849 0270",
    "sg:postcode":"3127",
    "sg:province":"VIC",
    "sg:tags":[
        "package",
        "software"
    ],
    "wof:name":"B & M Business Systems Pty Ltd",
    "wof:placetype":"venue"
},
  "geometry": {"coordinates":[145.103393555,-37.8213920593],"type":"Point"}
}