{
  "type": "Feature",
  "properties": {
    "addr:full":"U3/ 39 Colin Jamieson Drv Welshpool WA 6106",
    "addr:housenumber":"39",
    "addr:postcode":"6106",
    "addr:street":"U3 /;Jamieson Drv",
    "iso:country":"AU",
    "sg:address":"U3/ 39 Colin Jamieson Drv",
    "sg:city":"Welshpool",
    "sg:classifiers":[
        {
            "category":"Professional",
            "type":"Services"
        }
    ],
    "sg:phone":"+61 8 9358 1622",
    "sg:postcode":"6106",
    "sg:province":"WA",
    "sg:tags":[
        "courier"
    ],
    "wof:name":"P & P Distribution Pty Ltd",
    "wof:placetype":"venue"
},
  "geometry": {"coordinates":[115.937301636,-31.9939537048],"type":"Point"}
}