{
  "type": "Feature",
  "properties": {
    "addr:full":"13a Tandarra Pl Wembley Downs WA 6019",
    "addr:housenumber":"13a",
    "addr:postcode":"6019",
    "addr:street":"Pl Wembley Downs",
    "iso:country":"AU",
    "sg:address":"13a Tandarra Pl",
    "sg:city":"Wembley Downs",
    "sg:classifiers":[
        {
            "category":"Real Estate",
            "subcategory":"Developer",
            "type":"Services"
        }
    ],
    "sg:phone":"+61 8 9245 1688",
    "sg:postcode":"6019",
    "sg:province":"WA",
    "sg:tags":[
        "development"
    ],
    "wof:name":"Saruman Holdings Pty Ltd",
    "wof:placetype":"venue"
},
  "geometry": {"coordinates":[115.767906189,-31.9173622131],"type":"Point"}
}