{
  "type": "Feature",
  "properties": {
    "addr:full":"Shp 79 Main St Blacktown NSW 2148",
    "addr:housenumber":"79",
    "addr:postcode":"2148",
    "addr:street":"Main St",
    "iso:country":"AU",
    "sg:address":"Shp 79 Main St",
    "sg:city":"Blacktown",
    "sg:classifiers":[
        {
            "category":"Health Services",
            "subcategory":"Optometrist",
            "type":"Services"
        }
    ],
    "sg:phone":"+61 2 9831 1438",
    "sg:postcode":"2148",
    "sg:province":"NSW",
    "wof:name":"George Mala",
    "wof:placetype":"venue"
},
  "geometry": {"coordinates":[150.90968322800001,-33.7702636719],"type":"Point"}
}