{
  "type": "Feature",
  "properties": {
    "iso:country":"AU",
    "sg:address":"Shp 2 69 Maitland St",
    "sg:city":"Narrabri",
    "sg:classifiers":[
        {
            "category":"Professional",
            "subcategory":"Accounting & Tax Preparation",
            "type":"Services"
        }
    ],
    "sg:phone":"+61 2 6792 2800",
    "sg:postcode":"2390",
    "sg:province":"NSW",
    "sg:tags":[
        "accountant",
        "auditor"
    ],
    "wof:name":"Calvin Skues Pty Ltd",
    "wof:placetype":"venue"
},
  "geometry": {"coordinates":[149.78401184099999,-30.3271274567],"type":"Point"}
}