{
  "type": "Feature",
  "properties": {
    "addr:full":"160 Churchill Rd Cavan SA 5094",
    "addr:housenumber":"160",
    "addr:postcode":"5094",
    "addr:street":"Churchill Rd",
    "iso:country":"AU",
    "sg:address":"160 Churchill Rd",
    "sg:city":"Cavan",
    "sg:classifiers":[
        {
            "category":"Wholesale",
            "subcategory":"Metals & Minerals",
            "type":"Manufacturing & Wholesale Goods"
        }
    ],
    "sg:phone":"+61 8 8260 5577",
    "sg:postcode":"5094",
    "sg:province":"SA",
    "sg:tags":[
        "steel",
        "merchant"
    ],
    "wof:name":"Senturion Steel Supplies",
    "wof:placetype":"venue"
},
  "geometry": {"coordinates":[138.59770202600001,-34.8378448486],"type":"Point"}
}