{
  "type": "Feature",
  "properties": {
    "addr:full":"16 Foley St Balcatta WA 6021",
    "addr:housenumber":"16",
    "addr:postcode":"6021",
    "addr:street":"Foley St",
    "iso:country":"AU",
    "sg:address":"16 Foley St",
    "sg:city":"Balcatta",
    "sg:classifiers":[
        {
            "category":"Home & Garden",
            "subcategory":"Hardware",
            "type":"Retail Goods"
        }
    ],
    "sg:phone":"+61 1300 668 620",
    "sg:postcode":"6021",
    "sg:province":"WA",
    "sg:tags":[
        "product",
        "treatment",
        "floor"
    ],
    "wof:name":"Global Safe Technologies",
    "wof:placetype":"venue"
},
  "geometry": {"coordinates":[115.824157715,-31.863243103],"type":"Point"}
}