{
  "type": "Feature",
  "properties": {
    "addr:full":"76- 80 Clarence St Sydney NSW 2000",
    "addr:housenumber":"80",
    "addr:postcode":"2000",
    "addr:street":"Clarence St",
    "iso:country":"AU",
    "sg:address":"76- 80 Clarence St",
    "sg:city":"Sydney",
    "sg:classifiers":[
        {
            "category":"Travel",
            "subcategory":"Travel Agent",
            "type":"Entertainment"
        }
    ],
    "sg:phone":"+61 2 9249 6060",
    "sg:postcode":"2000",
    "sg:province":"NSW",
    "sg:tags":[
        "consultant"
    ],
    "wof:name":"travel.com.au/cruise",
    "wof:placetype":"venue"
},
  "geometry": {"coordinates":[151.20530700699999,-33.8673553467],"type":"Point"}
}