{
  "type": "Feature",
  "properties": {
    "addr:full":"515 Robinson Rd Aspley QLD 4034",
    "addr:housenumber":"515",
    "addr:postcode":"4034",
    "addr:street":"Robinson Rd",
    "iso:country":"AU",
    "sg:address":"515 Robinson Rd",
    "sg:city":"Aspley",
    "sg:classifiers":[
        {
            "category":"Professional",
            "subcategory":"Art Services",
            "type":"Services"
        }
    ],
    "sg:phone":"+61 7 3263 5838",
    "sg:postcode":"4034",
    "sg:province":"QLD",
    "sg:tags":[
        "decorator",
        "painter"
    ],
    "wof:name":"Zanchetta G",
    "wof:placetype":"venue"
},
  "geometry": {"coordinates":[153.031677,-27.365898],"type":"Point"}
}