{
  "type": "Feature",
  "properties": {
    "addr:full":"69 Gurwood St Wagga Wagga NSW 2650",
    "addr:housenumber":"69",
    "addr:postcode":"2650",
    "addr:street":"Gurwood St",
    "iso:country":"AU",
    "sg:address":"69 Gurwood St",
    "sg:city":"Wagga Wagga",
    "sg:classifiers":[
        {
            "category":"Travel",
            "subcategory":"Hotels & Motels",
            "type":"Entertainment"
        }
    ],
    "sg:phone":"+61 2 6923 7000",
    "sg:postcode":"2650",
    "sg:province":"NSW",
    "wof:name":"Quest Wagga Wagga Serviced Apartments",
    "wof:placetype":"venue"
},
  "geometry": {"coordinates":[147.35272216800001,-35.1110458374],"type":"Point"}
}