{
  "type": "Feature",
  "properties": {
    "addr:full":"14 Amy St Campsie NSW 2194",
    "addr:housenumber":"14",
    "addr:postcode":"2194",
    "addr:street":"Amy St",
    "iso:country":"AU",
    "sg:address":"14 Amy St",
    "sg:city":"Campsie",
    "sg:classifiers":[
        {
            "category":"Fast Food",
            "type":"Food & Drink"
        }
    ],
    "sg:phone":"+61 2 9787 3090",
    "sg:postcode":"2194",
    "sg:province":"NSW",
    "sg:tags":[
        "away",
        "take"
    ],
    "wof:name":"Oz Turko",
    "wof:placetype":"venue"
},
  "geometry": {"coordinates":[151.09780900000001,-33.910915],"type":"Point"}
}