{
  "type": "Feature",
  "properties": {
    "addr:full":"Factory 2 / 74 - 80 Melverton Drv Hallam VIC 3803",
    "addr:housenumber":"/;80",
    "addr:postcode":"3803",
    "addr:street":"74;Melverton Drv",
    "iso:country":"AU",
    "sg:address":"Factory 2 / 74 - 80 Melverton Drv",
    "sg:city":"Hallam",
    "sg:classifiers":[
        {
            "category":"Utilities",
            "subcategory":"Mobile Phone",
            "type":"Services"
        }
    ],
    "sg:phone":"+61 1300 086 772",
    "sg:postcode":"3803",
    "sg:province":"VIC",
    "sg:tags":[
        "repair",
        "telephone"
    ],
    "sg:website":"http://www.expertinstalls.com.au",
    "wof:name":"Expert Installs Pty Ltd",
    "wof:placetype":"venue"
},
  "geometry": {"coordinates":[145.27365112300001,-38.0119552612],"type":"Point"}
}