{
  "type": "Feature",
  "properties": {
    "addr:full":"137 Ellison Rd Geebung QLD 4034",
    "addr:housenumber":"137",
    "addr:postcode":"4034",
    "addr:street":"Ellison Rd",
    "iso:country":"AU",
    "sg:address":"137 Ellison Rd",
    "sg:city":"Geebung",
    "sg:classifiers":[
        {
            "category":"Professional",
            "subcategory":"Computer Services",
            "type":"Services"
        }
    ],
    "sg:phone":"+61 413 837 085",
    "sg:postcode":"4034",
    "sg:province":"QLD",
    "sg:tags":[
        "consultant",
        "system"
    ],
    "wof:name":"Stark Consulting Pty Ltd",
    "wof:placetype":"venue"
},
  "geometry": {"coordinates":[153.04806500000001,-27.375957],"type":"Point"}
}