{
  "type": "Feature",
  "properties": {
    "addr:full":"Unit 10/ 8 Gosport St Cronulla NSW 2230",
    "addr:housenumber":"/ 8",
    "addr:postcode":"2230",
    "addr:street":"Gosport St",
    "iso:country":"AU",
    "sg:address":"Unit 10/ 8 Gosport St",
    "sg:city":"Cronulla",
    "sg:classifiers":[
        {
            "category":"Professional",
            "subcategory":"Accounting & Tax Preparation",
            "type":"Services"
        }
    ],
    "sg:phone":"+61 417 651 949",
    "sg:postcode":"2230",
    "sg:province":"NSW",
    "sg:tags":[
        "bookkeeping"
    ],
    "wof:name":"Books By Lara",
    "wof:placetype":"venue"
},
  "geometry": {"coordinates":[151.15153503400001,-34.0485687256],"type":"Point"}
}