{
  "type": "Feature",
  "properties": {
    "addr:full":"12 Olive St Newstead TAS 7250",
    "addr:housenumber":"12",
    "addr:postcode":"7250",
    "addr:street":"Olive St",
    "iso:country":"AU",
    "sg:address":"12 Olive St",
    "sg:city":"Newstead",
    "sg:classifiers":[
        {
            "category":"Building & Trades",
            "subcategory":"Construction",
            "type":"Services"
        }
    ],
    "sg:phone":"+61 439 800 874",
    "sg:postcode":"7250",
    "sg:province":"TAS",
    "sg:tags":[
        "stonework",
        "stone",
        "mason"
    ],
    "wof:name":"Stonewall Constructions",
    "wof:placetype":"venue"
},
  "geometry": {"coordinates":[147.15776062,-41.435874939],"type":"Point"}
}