{
  "type": "Feature",
  "properties": {
    "addr:full":"Unit 6/ 29 The Broadway Burringbar NSW 2483",
    "addr:housenumber":"29",
    "addr:postcode":"2483",
    "addr:street":"The Broadway",
    "iso:country":"AU",
    "sg:address":"Unit 6/ 29",
    "sg:city":"The Broadway Burringbar",
    "sg:classifiers":[
        {
            "category":"Real Estate",
            "subcategory":"Developer",
            "type":"Services"
        }
    ],
    "sg:phone":"+61 2 6677 1010",
    "sg:postcode":"2483",
    "sg:province":"NSW",
    "sg:tags":[
        "development"
    ],
    "wof:name":"Dostar Pty Ltd",
    "wof:placetype":"venue"
},
  "geometry": {"coordinates":[153.457931519,-28.4234790802],"type":"Point"}
}