{
  "type": "Feature",
  "properties": {
    "addr:full":"387 Churchill Rd Kilburn SA 5084",
    "addr:housenumber":"387",
    "addr:postcode":"5084",
    "addr:street":"Churchill Rd",
    "iso:country":"AU",
    "sg:address":"387 Churchill Rd",
    "sg:city":"Kilburn",
    "sg:classifiers":[
        {
            "category":"Wholesale",
            "subcategory":"Auto Parts",
            "type":"Manufacturing & Wholesale Goods"
        }
    ],
    "sg:phone":"+61 13 17 40",
    "sg:postcode":"5084",
    "sg:province":"SA",
    "sg:tags":[
        "recyclers"
    ],
    "wof:name":"A.D.A. Hotline 40",
    "wof:placetype":"venue"
},
  "geometry": {"coordinates":[138.583526611,-34.8636665344],"type":"Point"}
}