{
  "type": "Feature",
  "properties": {
    "addr:full":"65 Church St Morwell VIC 3840",
    "addr:housenumber":"65",
    "addr:postcode":"3840",
    "addr:street":"Church St",
    "iso:country":"AU",
    "sg:address":"65 Church St",
    "sg:city":"Morwell",
    "sg:classifiers":[
        {
            "category":"Government",
            "subcategory":"Court House",
            "type":"Public Place"
        }
    ],
    "sg:phone":"+61 3 5133 9998",
    "sg:postcode":"3840",
    "sg:province":"VIC",
    "sg:tags":[
        "personal",
        "marriage",
        "family",
        "counselling"
    ],
    "wof:name":"BreakEven Problem Gambling Counselling",
    "wof:placetype":"venue"
},
  "geometry": {"coordinates":[146.39958190900001,-38.234413147],"type":"Point"}
}