{
  "type": "Feature",
  "properties": {
    "iso:country":"AU",
    "sg:address":"227 West St",
    "sg:city":"Umina",
    "sg:classifiers":[
        {
            "category":"Manufacturing",
            "subcategory":"Motor Vehicles & Parts",
            "type":"Manufacturing & Wholesale Goods"
        }
    ],
    "sg:phone":"+61 2 4342 1788",
    "sg:postcode":"2257",
    "sg:province":"NSW",
    "sg:tags":[
        "replacement"
    ],
    "wof:name":"Ocean Beach Spares",
    "wof:placetype":"venue"
},
  "geometry": {"coordinates":[151.32237243599999,-33.5217170715],"type":"Point"}
}