{
  "type": "Feature",
  "properties": {
    "addr:full":"16 Bean Ave Parkhurst QLD 4702",
    "addr:housenumber":"16",
    "addr:postcode":"4702",
    "addr:street":"Bean Ave",
    "iso:country":"AU",
    "sg:address":"16 Bean Ave",
    "sg:city":"Parkhurst",
    "sg:classifiers":[
        {
            "category":"Education",
            "subcategory":"Kindergarten",
            "type":"Public Place"
        }
    ],
    "sg:phone":"+61 7 4936 2216",
    "sg:postcode":"4702",
    "sg:province":"QLD",
    "sg:tags":[
        "pre-schools"
    ],
    "wof:name":"Parkhurst Early Learning Centre",
    "wof:placetype":"venue"
},
  "geometry": {"coordinates":[150.514602661,-23.3035182953],"type":"Point"}
}