{
  "type": "Feature",
  "properties": {
    "addr:full":"34 Binney St Euroa VIC 3666",
    "addr:housenumber":"34",
    "addr:postcode":"3666",
    "addr:street":"Binney St",
    "iso:country":"AU",
    "sg:address":"34 Binney St",
    "sg:city":"Euroa",
    "sg:classifiers":[
        {
            "category":"Shopping",
            "subcategory":"Shoes",
            "type":"Retail Goods"
        }
    ],
    "sg:phone":"+61 3 5795 1122",
    "sg:postcode":"3666",
    "sg:province":"VIC",
    "sg:tags":[
        "footwear"
    ],
    "wof:name":"Fashion Footwear",
    "wof:placetype":"venue"
},
  "geometry": {"coordinates":[145.569702148,-36.7497596741],"type":"Point"}
}