{
  "type": "Feature",
  "properties": {
    "addr:full":"6 Warren Rd Gilgandra NSW 2827",
    "addr:housenumber":"6",
    "addr:postcode":"2827",
    "addr:street":"Warren Rd",
    "iso:country":"AU",
    "sg:address":"6 Warren Rd",
    "sg:city":"Gilgandra",
    "sg:classifiers":[
        {
            "category":"Wholesale",
            "subcategory":"Farm Supplies",
            "type":"Manufacturing & Wholesale Goods"
        }
    ],
    "sg:phone":"+61 2 6847 2411",
    "sg:postcode":"2827",
    "sg:province":"NSW",
    "sg:tags":[
        "equipment"
    ],
    "wof:name":"Rohr G K & L H Rural Supplies",
    "wof:placetype":"venue"
},
  "geometry": {"coordinates":[148.66531372099999,-31.7130699158],"type":"Point"}
}