{
  "type": "Feature",
  "properties": {
    "addr:full":"Ksk14/ 459 Pittwater Rd Brookvale NSW 2100",
    "addr:housenumber":"459",
    "addr:postcode":"2100",
    "addr:street":"Pittwater Rd",
    "iso:country":"AU",
    "sg:address":"Ksk14/ 459 Pittwater Rd",
    "sg:city":"Brookvale",
    "sg:classifiers":[
        {
            "category":"Cafe",
            "type":"Food & Drink"
        }
    ],
    "sg:phone":"+61 2 9939 8324",
    "sg:postcode":"2100",
    "sg:province":"NSW",
    "wof:name":"D&#039;Ough Espresso",
    "wof:placetype":"venue"
},
  "geometry": {"coordinates":[151.27093505900001,-33.7644309998],"type":"Point"}
}