{
  "type": "Feature",
  "properties": {
    "addr:full":"Lot 8 Lucas Crt Maryborough QLD 4650",
    "addr:postcode":"4650",
    "addr:street":"Lucas Crt",
    "iso:country":"AU",
    "sg:address":"Lot 8 Lucas Crt",
    "sg:city":"Maryborough",
    "sg:classifiers":[
        {
            "category":"Retail",
            "subcategory":"Repair Shop",
            "type":"Services"
        }
    ],
    "sg:phone":"+61 7 4123 6134",
    "sg:postcode":"4650",
    "sg:province":"QLD",
    "sg:tags":[
        "upholsterer"
    ],
    "wof:name":"Saltwater Sails & Upholstery",
    "wof:placetype":"venue"
},
  "geometry": {"coordinates":[152.71040300000001,-25.486057],"type":"Point"}
}