{
  "type": "Feature",
  "properties": {
    "iso:country":"AU",
    "sg:address":"PO Box 636",
    "sg:city":"Exmouth",
    "sg:classifiers":[
        {
            "category":"Building & Trades",
            "subcategory":"Construction",
            "type":"Services"
        }
    ],
    "sg:phone":"+61 417 922 830",
    "sg:postcode":"6707",
    "sg:province":"WA",
    "sg:tags":[
        "contractor"
    ],
    "wof:name":"Temar Building Company",
    "wof:placetype":"venue"
},
  "geometry": {"coordinates":[114.133277893,-21.9462604523],"type":"Point"}
}