{
  "type": "Feature",
  "properties": {
    "iso:country":"AU",
    "sg:address":"9- 10 Shores Drv",
    "sg:city":"Yamba",
    "sg:classifiers":[
        {
            "category":"Education",
            "subcategory":"Kindergarten",
            "type":"Public Place"
        }
    ],
    "sg:phone":"+61 2 6646 8168",
    "sg:postcode":"2464",
    "sg:province":"NSW",
    "sg:tags":[
        "pre-schools"
    ],
    "wof:name":"Willy Wagtail Kindergarten",
    "wof:placetype":"venue"
},
  "geometry": {"coordinates":[153.336227417,-29.4286422729],"type":"Point"}
}