{
  "type": "Feature",
  "properties": {
    "addr:full":"Level 1, Suite 8/ 12 North Lakes Drv North Lakes QLD 4509",
    "addr:postcode":"4509",
    "addr:street":"North Lakes Drv",
    "iso:country":"AU",
    "sg:address":"Level 1, Suite 8/ 12 North Lakes Drv",
    "sg:city":"North Lakes",
    "sg:classifiers":[
        {
            "category":"Personal",
            "subcategory":"Hair Removal",
            "type":"Services"
        }
    ],
    "sg:phone":"+61 7 3482 2999",
    "sg:postcode":"4509",
    "sg:province":"QLD",
    "wof:name":"North Lakes Beauty & Skin Care Clinic",
    "wof:placetype":"venue"
},
  "geometry": {"coordinates":[153.01356506400001,-27.2402191162],"type":"Point"}
}