{
  "type": "Feature",
  "properties": {
    "iso:country":"AU",
    "sg:address":"41 Craig Rd",
    "sg:city":"Cranbourne",
    "sg:classifiers":[
        {
            "category":"Health Services",
            "subcategory":"Doctor",
            "type":"Services"
        }
    ],
    "sg:phone":"+61 419 561 642",
    "sg:postcode":"3977",
    "sg:province":"VIC",
    "sg:tags":[
        "medical",
        "practitioner"
    ],
    "wof:name":"Smith Damien Dr",
    "wof:placetype":"venue"
},
  "geometry": {"coordinates":[145.29400634800001,-38.1379013062],"type":"Point"}
}