{
  "type": "Feature",
  "properties": {
    "addr:full":"158 Lemon Ave Mildura VIC 3500",
    "addr:housenumber":"158",
    "addr:postcode":"3500",
    "addr:street":"Lemon Ave",
    "iso:country":"AU",
    "sg:address":"158 Lemon Ave",
    "sg:city":"Mildura",
    "sg:classifiers":[
        {
            "category":"Manufacturing",
            "subcategory":"Motor Vehicles & Parts",
            "type":"Manufacturing & Wholesale Goods"
        }
    ],
    "sg:phone":"+61 409 532 042",
    "sg:postcode":"3500",
    "sg:province":"VIC",
    "sg:tags":[
        "engine",
        "equipment",
        "diesel"
    ],
    "wof:name":"Bruce Manly",
    "wof:placetype":"venue"
},
  "geometry": {"coordinates":[142.160766602,-34.1920166016],"type":"Point"}
}