{
  "type": "Feature",
  "properties": {
    "iso:country":"AU",
    "sg:address":"13 Hume Rd",
    "sg:city":"Smithfield",
    "sg:phone":"+61 2 9725 9000",
    "sg:postcode":"2164",
    "sg:province":"NSW",
    "wof:name":"Liquip International",
    "wof:placetype":"venue"
},
  "geometry": {"coordinates":[150.93099975600001,-33.837310791],"type":"Point"}
}