{
  "type": "Feature",
  "properties": {
    "addr:full":"138b Waterloo Rd Greenacre NSW 2190",
    "addr:housenumber":"138b",
    "addr:postcode":"2190",
    "addr:street":"Waterloo Rd",
    "iso:country":"AU",
    "sg:address":"138b Waterloo Rd",
    "sg:city":"Greenacre",
    "sg:classifiers":[
        {
            "category":"Food & Beverages",
            "subcategory":"Fruits & Vegetables",
            "type":"Retail Goods"
        }
    ],
    "sg:phone":"+61 2 9759 4146",
    "sg:postcode":"2190",
    "sg:province":"NSW",
    "sg:tags":[
        "greengrocer",
        "fruiterer"
    ],
    "wof:name":"Greenacre Milk Bar Fruit & Vegetables",
    "wof:placetype":"venue"
},
  "geometry": {"coordinates":[151.05819700000001,-33.901997],"type":"Point"}
}