{
  "type": "Feature",
  "properties": {
    "iso:country":"AU",
    "sg:address":"7 Druitt Crt",
    "sg:city":"Finley",
    "sg:classifiers":[
        {
            "category":"Building & Trades",
            "subcategory":"Construction",
            "type":"Services"
        }
    ],
    "sg:phone":"+61 3 5883 1836",
    "sg:postcode":"2713",
    "sg:province":"NSW",
    "sg:tags":[
        "contractor"
    ],
    "wof:name":"Polkinghorne G A & M",
    "wof:placetype":"venue"
},
  "geometry": {"coordinates":[145.56968689000001,-35.6485099792],"type":"Point"}
}