{
  "type": "Feature",
  "properties": {
    "addr:full":"18 O&#039;Brien Ave Salisbury Downs SA 5108",
    "addr:housenumber":"18",
    "addr:postcode":"5108",
    "addr:street":"O &;Brien Ave",
    "iso:country":"AU",
    "sg:address":"18 O&#039;Brien Ave",
    "sg:city":"Salisbury Downs",
    "sg:classifiers":[
        {
            "category":"Retail",
            "subcategory":"Auto Repair",
            "type":"Services"
        }
    ],
    "sg:phone":"+61 8 8281 2660",
    "sg:postcode":"5108",
    "sg:province":"SA",
    "sg:tags":[
        "body",
        "motor",
        "trimmer"
    ],
    "wof:name":"P.B.A. Trimming",
    "wof:placetype":"venue"
},
  "geometry": {"coordinates":[138.62739563,-34.7732505798],"type":"Point"}
}