{
  "type": "Feature",
  "properties": {
    "addr:full":"Unit 6/ 6 Casua Drv Varsity Lakes QLD 4227",
    "addr:housenumber":"6",
    "addr:postcode":"4227",
    "addr:street":"Casua Drv",
    "iso:country":"AU",
    "sg:address":"Unit 6/ 6 Casua Drv",
    "sg:city":"Varsity Lakes",
    "sg:classifiers":[
        {
            "category":"Building & Trades",
            "subcategory":"Plumbing",
            "type":"Services"
        }
    ],
    "sg:phone":"+61 7 5502 0620",
    "sg:postcode":"4227",
    "sg:province":"QLD",
    "sg:tags":[
        "pump",
        "repairer"
    ],
    "wof:name":"Crystal Clear Chlorinators",
    "wof:placetype":"venue"
},
  "geometry": {"coordinates":[153.40699768100001,-28.1020183563],"type":"Point"}
}