{
  "type": "Feature",
  "properties": {
    "addr:full":"2 Johnston St Stirling SA 5152",
    "addr:housenumber":"2",
    "addr:postcode":"5152",
    "addr:street":"Johnston St",
    "iso:country":"AU",
    "sg:address":"2 Johnston St",
    "sg:city":"Stirling",
    "sg:classifiers":[
        {
            "category":"Health Services",
            "subcategory":"Doctor",
            "type":"Services"
        }
    ],
    "sg:phone":"+61 8 8339 4344",
    "sg:postcode":"5152",
    "sg:province":"SA",
    "sg:tags":[
        "medical",
        "practitioner"
    ],
    "wof:name":"Bridgewater Surgery",
    "wof:placetype":"venue"
},
  "geometry": {"coordinates":[138.71711730999999,-35.0070304871],"type":"Point"}
}