{
  "type": "Feature",
  "properties": {
    "iso:country":"AU",
    "sg:address":"Lvl 4/ 141 Osborne St",
    "sg:city":"South Yarra",
    "sg:classifiers":[
        {
            "category":"Utilities",
            "subcategory":"Fuel Oil & Lpg",
            "type":"Services"
        }
    ],
    "sg:phone":"+61 3 9279 3941",
    "sg:postcode":"3141",
    "sg:province":"VIC",
    "sg:tags":[
        "merchant"
    ],
    "wof:name":"Gaseng",
    "wof:placetype":"venue"
},
  "geometry": {"coordinates":[144.99137878400001,-37.8395042419],"type":"Point"}
}