{
  "type": "Feature",
  "properties": {
    "iso:country":"AU",
    "sg:address":"9/96 Kurraba Rd",
    "sg:city":"Neutral Bay",
    "sg:classifiers":[
        {
            "category":"Professional",
            "subcategory":"Engineering",
            "type":"Services"
        }
    ],
    "sg:phone":"+61 2 9953 4237",
    "sg:postcode":"2089",
    "sg:province":"NSW",
    "sg:tags":[
        "consulting",
        "engineer"
    ],
    "wof:name":"White Resources",
    "wof:placetype":"venue"
},
  "geometry": {"coordinates":[151.219284058,-33.8397636414],"type":"Point"}
}