{
  "type": "Feature",
  "properties": {
    "iso:country":"AU",
    "sg:address":"Unit 10/ Lot 13 Brian Rd",
    "sg:city":"Lonsdale",
    "sg:classifiers":[
        {
            "category":"Home & Garden",
            "subcategory":"Garden Supply",
            "type":"Retail Goods"
        }
    ],
    "sg:phone":"+61 8 8322 3583",
    "sg:postcode":"5160",
    "sg:province":"SA",
    "sg:tags":[
        "equipment"
    ],
    "wof:name":"Adelaide Statues",
    "wof:placetype":"venue"
},
  "geometry": {"coordinates":[138.50674438499999,-35.1002120972],"type":"Point"}
}