{
  "type": "Feature",
  "properties": {
    "addr:full":"41 Bradford Rd Burpengary QLD 4505",
    "addr:housenumber":"41",
    "addr:postcode":"4505",
    "addr:street":"Bradford Rd",
    "iso:country":"AU",
    "sg:address":"41 Bradford Rd",
    "sg:city":"Burpengary",
    "sg:classifiers":[
        {
            "category":"Military Area",
            "subcategory":"Army Base",
            "type":"Public Place"
        }
    ],
    "sg:phone":"+61 418 150 878",
    "sg:postcode":"4505",
    "sg:province":"QLD",
    "sg:tags":[
        "concrete",
        "slab",
        "floor"
    ],
    "wof:name":"B S M Concreting",
    "wof:placetype":"venue"
},
  "geometry": {"coordinates":[153.007125855,-27.1364154816],"type":"Point"}
}