{
  "type": "Feature",
  "properties": {
    "iso:country":"AU",
    "sg:address":"23 Addison Rd",
    "sg:city":"Marrickville",
    "sg:classifiers":[
        {
            "category":"Banks & Credit Unions",
            "subcategory":"Bank",
            "type":"Services"
        }
    ],
    "sg:phone":"+61 2 9565 2730",
    "sg:postcode":"2204",
    "sg:province":"NSW",
    "sg:tags":[
        "leather",
        "cutting",
        "fabric",
        "plastic"
    ],
    "wof:name":"Contour Cutting Pty Ltd",
    "wof:placetype":"venue"
},
  "geometry": {"coordinates":[151.167587,-33.903687],"type":"Point"}
}