{
  "type": "Feature",
  "properties": {
    "addr:full":"Shop 28 16 Lower Dandenong Rd Mentone VIC 3194",
    "addr:housenumber":"shop 28 16",
    "addr:postcode":"3194",
    "addr:street":"Lower Dandenong Rd",
    "iso:country":"AU",
    "sg:address":"Shop 28 16 Lower Dandenong Rd",
    "sg:city":"Mentone",
    "sg:classifiers":[
        {
            "category":"Professional",
            "subcategory":"Computer Services",
            "type":"Services"
        }
    ],
    "sg:phone":"+61 3 9585 5633",
    "sg:postcode":"3194",
    "sg:province":"VIC",
    "sg:tags":[
        "equipment",
        "networking",
        "installation"
    ],
    "wof:name":"JSN Computers Pty ltd",
    "wof:placetype":"venue"
},
  "geometry": {"coordinates":[145.07673645,-37.9827194214],"type":"Point"}
}