{
  "type": "Feature",
  "properties": {
    "iso:country":"AU",
    "sg:address":"3a Tennyson Rd",
    "sg:city":"Cromer",
    "sg:classifiers":[
        {
            "category":"Building & Trades",
            "subcategory":"Plumbing",
            "type":"Services"
        }
    ],
    "sg:phone":"+61 2 9971 9063",
    "sg:postcode":"2099",
    "sg:province":"NSW",
    "sg:tags":[
        "plumber",
        "gasfitters"
    ],
    "wof:name":"Permanent Plumbing Services",
    "wof:placetype":"venue"
},
  "geometry": {"coordinates":[151.28378295900001,-33.7435150146],"type":"Point"}
}