{
  "type": "Feature",
  "properties": {
    "iso:country":"AU",
    "sg:address":"Cnr Industrial Drv & Avon St",
    "sg:city":"Mayfield",
    "sg:classifiers":[
        {
            "category":"Organizations",
            "subcategory":"Community Association",
            "type":"Services"
        }
    ],
    "sg:phone":"+61 2 4968 2511",
    "sg:postcode":"2304",
    "sg:province":"NSW",
    "sg:tags":[
        "organisation",
        "family",
        "welfare"
    ],
    "wof:name":"Hunter Women's Centre",
    "wof:placetype":"venue"
},
  "geometry": {"coordinates":[151.740966797,-32.894493103],"type":"Point"}
}