{
  "type": "Feature",
  "properties": {
    "addr:full":"PO Box 2053 Redcliffe QLD 4020",
    "addr:postcode":"4020",
    "iso:country":"AU",
    "sg:address":"PO Box 2053",
    "sg:city":"Redcliffe",
    "sg:classifiers":[
        {
            "category":"Utilities",
            "subcategory":"Water",
            "type":"Services"
        }
    ],
    "sg:phone":"+61 415 718 331",
    "sg:postcode":"4020",
    "sg:province":"QLD",
    "sg:tags":[
        "equipment",
        "treatment"
    ],
    "wof:name":"Hydrotreat",
    "wof:placetype":"venue"
},
  "geometry": {"coordinates":[153.107224,-27.22217],"type":"Point"}
}