{
  "type": "Feature",
  "properties": {
    "addr:full":"18 Monomeeth Drv Mitcham VIC 3132",
    "addr:housenumber":"18",
    "addr:postcode":"3132",
    "addr:street":"Monomeeth Drv",
    "iso:country":"AU",
    "sg:address":"18 Monomeeth Drv",
    "sg:city":"Mitcham",
    "sg:classifiers":[
        {
            "category":"Banks & Credit Unions",
            "subcategory":"Bureau De Change",
            "type":"Services"
        }
    ],
    "sg:phone":"+61 3 9874 1733",
    "sg:postcode":"3132",
    "sg:province":"VIC",
    "sg:tags":[
        "equipment",
        "heat",
        "exchange"
    ],
    "wof:name":"Hendy Coils Pty Ltd",
    "wof:placetype":"venue"
},
  "geometry": {"coordinates":[145.20460510300001,-37.8168830872],"type":"Point"}
}