{
  "type": "Feature",
  "properties": {
    "addr:full":"Beaumaris St Enfield NSW 2136",
    "addr:postcode":"2136",
    "addr:street":"Beaumaris St",
    "iso:country":"AU",
    "sg:address":"Beaumaris St",
    "sg:city":"Enfield",
    "sg:classifiers":[
        {
            "category":"Education",
            "subcategory":"School",
            "type":"Public Place"
        }
    ],
    "sg:phone":"+61 2 9747 3514",
    "sg:postcode":"2136",
    "sg:province":"NSW",
    "sg:tags":[
        "state",
        "-",
        "nsw"
    ],
    "wof:name":"Enfield Public School",
    "wof:placetype":"venue"
},
  "geometry": {"coordinates":[151.09408569300001,-33.887840271],"type":"Point"}
}