{
  "type": "Feature",
  "properties": {
    "iso:country":"AU",
    "sg:address":"63 Frederick St",
    "sg:city":"Wellington Point",
    "sg:classifiers":[
        {
            "category":"Utilities",
            "subcategory":"Electric",
            "type":"Services"
        }
    ],
    "sg:phone":"+61 7 3822 1663",
    "sg:postcode":"4160",
    "sg:province":"QLD",
    "sg:tags":[
        "electrical",
        "contractor"
    ],
    "wof:name":"Brighter Eletrical Pty Ltd",
    "wof:placetype":"venue"
},
  "geometry": {"coordinates":[153.24331665,-27.498752594],"type":"Point"}
}