{
  "type": "Feature",
  "properties": {
    "addr:full":"8 Elster Ave Elsternwick VIC 3185",
    "addr:housenumber":"8",
    "addr:postcode":"3185",
    "addr:street":"Elster Ave",
    "iso:country":"AU",
    "sg:address":"8 Elster Ave",
    "sg:city":"Elsternwick",
    "sg:classifiers":[
        {
            "category":"Real Estate",
            "subcategory":"Architect",
            "type":"Services"
        }
    ],
    "sg:phone":"+61 3 9596 8577",
    "sg:postcode":"3185",
    "sg:province":"VIC",
    "wof:name":"Braunstein Jack",
    "wof:placetype":"venue"
},
  "geometry": {"coordinates":[145.01075744600001,-37.8963775635],"type":"Point"}
}