{
  "type": "Feature",
  "properties": {
    "addr:full":"Ste303A/ 22 St Kilda Rd St Kilda VIC 3182",
    "addr:housenumber":"22",
    "addr:postcode":"3182",
    "addr:street":"St Kilda Rd",
    "iso:country":"AU",
    "sg:address":"Ste303A/ 22 St Kilda Rd",
    "sg:city":"St Kilda",
    "sg:classifiers":[
        {
            "category":"Banks & Credit Unions",
            "subcategory":"Financial Services",
            "type":"Services"
        }
    ],
    "sg:phone":"+61 3 9510 7003",
    "sg:postcode":"3182",
    "sg:province":"VIC",
    "sg:tags":[
        "planning"
    ],
    "wof:name":"Icg Financial Planning Pty Ltd",
    "wof:placetype":"venue"
},
  "geometry": {"coordinates":[144.98339843799999,-37.8569564819],"type":"Point"}
}