{
  "type": "Feature",
  "properties": {
    "addr:full":"50 Fenton St Ascot Vale VIC 3032",
    "addr:housenumber":"50",
    "addr:postcode":"3032",
    "addr:street":"Fenton St",
    "iso:country":"AU",
    "sg:address":"50 Fenton St",
    "sg:city":"Ascot Vale",
    "sg:classifiers":[
        {
            "category":"Retail",
            "subcategory":"Event Space",
            "type":"Services"
        }
    ],
    "sg:phone":"+61 3 9370 8717",
    "sg:postcode":"3032",
    "sg:province":"VIC",
    "sg:tags":[
        "venue",
        "reception",
        "wedding"
    ],
    "wof:name":"Ascot House Receptions",
    "wof:placetype":"venue"
},
  "geometry": {"coordinates":[144.93171699999999,-37.77494],"type":"Point"}
}