{
  "type": "Feature",
  "properties": {
    "addr:full":"22 Windsor St Richmond NSW 2753",
    "addr:housenumber":"22",
    "addr:postcode":"2753",
    "addr:street":"Windsor St",
    "iso:country":"AU",
    "sg:address":"22 Windsor St",
    "sg:city":"Richmond",
    "sg:classifiers":[
        {
            "category":"Farming",
            "subcategory":"Livestock Farm",
            "type":"Manufacturing & Wholesale Goods"
        }
    ],
    "sg:phone":"+61 2 4578 2477",
    "sg:postcode":"2753",
    "sg:province":"NSW",
    "sg:tags":[
        "breeder",
        "horse",
        "stud"
    ],
    "wof:name":"Charlton Horse Stud Saddlery",
    "wof:placetype":"venue"
},
  "geometry": {"coordinates":[150.75352477999999,-33.5979957581],"type":"Point"}
}