{
  "type": "Feature",
  "properties": {
    "iso:country":"AU",
    "sg:address":"26 Notar Drv",
    "sg:city":"Ormeau",
    "sg:classifiers":[
        {
            "category":"Wholesale",
            "subcategory":"Durable Goods & Equipment",
            "type":"Manufacturing & Wholesale Goods"
        }
    ],
    "sg:phone":"+61 7 5549 3666",
    "sg:postcode":"4208",
    "sg:province":"QLD",
    "sg:tags":[
        "degreasing"
    ],
    "wof:name":"Ardelve Equipment",
    "wof:placetype":"venue"
},
  "geometry": {"coordinates":[153.24919128400001,-27.7594051361],"type":"Point"}
}