{
  "type": "Feature",
  "properties": {
    "addr:full":"Shop 107-108 Centre Plz Mildura VIC 3500",
    "addr:housenumber":"107-108",
    "addr:postcode":"3500",
    "addr:street":"Centre Plz",
    "iso:country":"AU",
    "sg:address":"Shop 107-108 Centre Plz",
    "sg:city":"Mildura",
    "sg:classifiers":[
        {
            "category":"Shopping",
            "subcategory":"Clothing, Apparel, & Fashions",
            "type":"Retail Goods"
        }
    ],
    "sg:phone":"+61 3 5022 2128",
    "sg:postcode":"3500",
    "sg:province":"VIC",
    "sg:tags":[
        "lady",
        "wear"
    ],
    "wof:name":"Katies Fashions Aust Pty Ltd",
    "wof:placetype":"venue"
},
  "geometry": {"coordinates":[142.154098511,-34.2107391357],"type":"Point"}
}