{
  "type": "Feature",
  "properties": {
    "iso:country":"AU",
    "sg:address":"43 Railway Pde",
    "sg:city":"Lakemba",
    "sg:classifiers":[
        {
            "category":"Shopping",
            "subcategory":"Pawn Shop",
            "type":"Retail Goods"
        }
    ],
    "sg:phone":"+61 2 9740 6680",
    "sg:postcode":"2195",
    "sg:province":"NSW",
    "sg:tags":[
        "pawnbroker"
    ],
    "wof:name":"Trajs Loan Office",
    "wof:placetype":"venue"
},
  "geometry": {"coordinates":[151.076096,-33.919601],"type":"Point"}
}