{
  "type": "Feature",
  "properties": {
    "addr:full":"Shop 6 & 9 McKinnon Arc Echuca VIC 3564",
    "addr:housenumber":"shop 6 & 9",
    "addr:postcode":"3564",
    "addr:street":"Mckinnon Arc",
    "iso:country":"AU",
    "sg:address":"Shop 6 & 9 McKinnon Arc",
    "sg:city":"Echuca",
    "sg:classifiers":[
        {
            "category":"Shopping",
            "subcategory":"Party Supplies",
            "type":"Retail Goods"
        }
    ],
    "sg:phone":"+61 3 5482 1262",
    "sg:postcode":"3564",
    "sg:province":"VIC",
    "wof:name":"Party & Paper",
    "wof:placetype":"venue"
},
  "geometry": {"coordinates":[144.75718689000001,-36.1118545532],"type":"Point"}
}