{
  "type": "Feature",
  "properties": {
    "addr:full":"Unit 2 / 79 Allenby Rd Hillside (Sydenham) VIC 3037",
    "addr:housenumber":"79",
    "addr:postcode":"3037",
    "addr:street":"Allenby Rd",
    "iso:country":"AU",
    "sg:address":"Unit 2 / 79 Allenby Rd",
    "sg:city":"Hillside (Sydenham)",
    "sg:classifiers":[
        {
            "category":"Professional",
            "subcategory":"Art Services",
            "type":"Services"
        }
    ],
    "sg:phone":"+61 405 542 638",
    "sg:postcode":"3037",
    "sg:province":"VIC",
    "sg:tags":[
        "decorator",
        "painter"
    ],
    "wof:name":"F.A.Painting",
    "wof:placetype":"venue"
},
  "geometry": {"coordinates":[144.74601699999999,-37.702839],"type":"Point"}
}