{
  "type": "Feature",
  "properties": {
    "addr:full":"16 Boyne St Stuart QLD 4811",
    "addr:housenumber":"16",
    "addr:postcode":"4811",
    "addr:street":"Boyne St",
    "iso:country":"AU",
    "sg:address":"16 Boyne St",
    "sg:city":"Stuart",
    "sg:classifiers":[
        {
            "category":"Professional",
            "type":"Services"
        }
    ],
    "sg:phone":"+61 417 649 964",
    "sg:postcode":"4811",
    "sg:province":"QLD",
    "sg:tags":[
        "courier"
    ],
    "wof:name":"Prestige Metro Courier Service",
    "wof:placetype":"venue"
},
  "geometry": {"coordinates":[146.820786,-19.326389],"type":"Point"}
}