{
  "type": "Feature",
  "properties": {
    "addr:full":"44 Lawson View Pde Wentworth Falls NSW 2782",
    "addr:housenumber":"44",
    "addr:postcode":"2782",
    "addr:street":"Lawson View Pde",
    "iso:country":"AU",
    "sg:address":"44 Lawson View Pde",
    "sg:city":"Wentworth Falls",
    "sg:classifiers":[
        {
            "category":"Health Services",
            "subcategory":"Health Practitioner",
            "type":"Services"
        }
    ],
    "sg:phone":"+61 2 4757 1853",
    "sg:postcode":"2782",
    "sg:province":"NSW",
    "sg:tags":[
        "acupuncture"
    ],
    "wof:name":"Hawkesbury Natural Health Acupuncture Centre",
    "wof:placetype":"venue"
},
  "geometry": {"coordinates":[150.388473511,-33.7030487061],"type":"Point"}
}