{
  "type": "Feature",
  "properties": {
    "iso:country":"AU",
    "sg:address":"2 Bullo Crt",
    "sg:city":"Leanyer",
    "sg:classifiers":[
        {
            "category":"Building & Trades",
            "subcategory":"Construction",
            "type":"Services"
        }
    ],
    "sg:phone":"+61 8 8927 4648",
    "sg:postcode":"0812",
    "sg:province":"NT",
    "sg:tags":[
        "repair",
        "maintenance",
        "contractor"
    ],
    "wof:name":"Datec",
    "wof:placetype":"venue"
},
  "geometry": {"coordinates":[130.89962800000001,-12.370365],"type":"Point"}
}