{
  "type": "Feature",
  "properties": {
    "iso:country":"AU",
    "sg:address":"56 Wingewarra St",
    "sg:city":"Dubbo",
    "sg:classifiers":[
        {
            "category":"Banks & Credit Unions",
            "subcategory":"Investment Brokerage",
            "type":"Services"
        }
    ],
    "sg:phone":"+61 1800 247 499",
    "sg:postcode":"2830",
    "sg:province":"NSW",
    "sg:tags":[
        "finance",
        "broker"
    ],
    "wof:name":"Daryl Coxon Financial Services",
    "wof:placetype":"venue"
},
  "geometry": {"coordinates":[148.60150146500001,-32.2453727722],"type":"Point"}
}