{
  "type": "Feature",
  "properties": {
    "iso:country":"AU",
    "sg:address":"89 Vimiera Rd",
    "sg:city":"Eastwood",
    "sg:classifiers":[
        {
            "category":"Professional",
            "subcategory":"Business Services",
            "type":"Services"
        }
    ],
    "sg:phone":"+61 2 9868 7737",
    "sg:postcode":"2122",
    "sg:province":"NSW",
    "sg:tags":[
        "broker"
    ],
    "wof:name":"Action International",
    "wof:placetype":"venue"
},
  "geometry": {"coordinates":[151.09297180199999,-33.7813873291],"type":"Point"}
}