{
  "type": "Feature",
  "properties": {
    "iso:country":"AU",
    "sg:address":"34 Norton St",
    "sg:city":"Leichhardt",
    "sg:classifiers":[
        {
            "category":"Health Services",
            "subcategory":"Health Practitioner",
            "type":"Services"
        }
    ],
    "sg:phone":"+61 2 9560 6519",
    "sg:postcode":"2040",
    "sg:province":"NSW",
    "sg:tags":[
        "alternative"
    ],
    "wof:name":"Feldenkrais Method",
    "wof:placetype":"venue"
},
  "geometry": {"coordinates":[151.157318,-33.886803],"type":"Point"}
}