{
  "type": "Feature",
  "properties": {
    "addr:full":"32 Taylor Rd Burpengary QLD 4505",
    "addr:housenumber":"32",
    "addr:postcode":"4505",
    "addr:street":"Taylor Rd",
    "iso:country":"AU",
    "sg:address":"32 Taylor Rd",
    "sg:city":"Burpengary",
    "sg:classifiers":[
        {
            "category":"Building & Trades",
            "subcategory":"Construction",
            "type":"Services"
        }
    ],
    "sg:phone":"+61 404 940 175",
    "sg:postcode":"4505",
    "sg:province":"QLD",
    "sg:tags":[
        "scaffolding"
    ],
    "wof:name":"Williams Scaffolding",
    "wof:placetype":"venue"
},
  "geometry": {"coordinates":[152.997879028,-27.1530284882],"type":"Point"}
}