{
  "type": "Feature",
  "properties": {
    "addr:full":"44 John St Rosewood QLD 4340",
    "addr:housenumber":"44",
    "addr:postcode":"4340",
    "addr:street":"John St",
    "iso:country":"AU",
    "sg:address":"44 John St",
    "sg:city":"Rosewood",
    "sg:classifiers":[
        {
            "category":"Food & Beverages",
            "subcategory":"Supermarket",
            "type":"Retail Goods"
        }
    ],
    "sg:phone":"+61 7 5464 1416",
    "sg:postcode":"4340",
    "sg:province":"QLD",
    "sg:tags":[
        "grocery",
        "store"
    ],
    "wof:name":"Rosewood IGA Everyday",
    "wof:placetype":"venue"
},
  "geometry": {"coordinates":[152.59071350100001,-27.6357765198],"type":"Point"}
}