{
  "type": "Feature",
  "properties": {
    "addr:full":"11 Scott St Cairns QLD 4870",
    "addr:housenumber":"11",
    "addr:postcode":"4870",
    "addr:street":"Scott St",
    "iso:country":"AU",
    "sg:address":"11 Scott St",
    "sg:city":"Cairns",
    "sg:classifiers":[
        {
            "category":"Retail",
            "subcategory":"Auto Repair",
            "type":"Services"
        }
    ],
    "sg:phone":"+61 7 4041 5551",
    "sg:postcode":"4870",
    "sg:province":"QLD",
    "sg:tags":[
        "testing",
        "inspection",
        "motor",
        "vehicle"
    ],
    "wof:name":"Aardvark Auto's",
    "wof:placetype":"venue"
},
  "geometry": {"coordinates":[145.76991272000001,-16.9264221191],"type":"Point"}
}