{
  "type": "Feature",
  "properties": {
    "iso:country":"AU",
    "sg:address":"Lot10/ Broughton Rd",
    "sg:city":"Broughton",
    "sg:classifiers":[
        {
            "category":"Mining & Drilling",
            "type":"Manufacturing & Wholesale Goods"
        }
    ],
    "sg:phone":"+61 7 4787 8746",
    "sg:postcode":"4820",
    "sg:province":"QLD",
    "sg:tags":[
        "boring",
        "contractor"
    ],
    "wof:name":"OME Drilling Pty Ltd",
    "wof:placetype":"venue"
},
  "geometry": {"coordinates":[146.292297,-20.087389],"type":"Point"}
}