{
  "type": "Feature",
  "properties": {
    "addr:full":"Shop G 3 18 Ross Ave Rosny Park TAS 7018",
    "addr:housenumber":"3 18",
    "addr:postcode":"7018",
    "addr:street":"G;Ross Ave",
    "iso:country":"AU",
    "sg:address":"Shop G 3 18 Ross Ave",
    "sg:city":"Rosny Park",
    "sg:classifiers":[
        {
            "category":"Banks & Credit Unions",
            "subcategory":"Bank",
            "type":"Services"
        }
    ],
    "sg:phone":"+61 3 6244 4077",
    "sg:postcode":"7018",
    "sg:province":"TAS",
    "sg:tags":[
        "broker",
        "mortgage"
    ],
    "wof:name":"Wizard Home Loans",
    "wof:placetype":"venue"
},
  "geometry": {"coordinates":[147.37037658700001,-42.8653068542],"type":"Point"}
}