{
  "type": "Feature",
  "properties": {
    "addr:full":"Factory 7 11 Havelock Rd Bayswater VIC 3153",
    "addr:housenumber":"11",
    "addr:postcode":"3153",
    "addr:street":"Havelock Rd",
    "iso:country":"AU",
    "sg:address":"Factory 7 11 Havelock Rd",
    "sg:city":"Bayswater",
    "sg:classifiers":[
        {
            "category":"Shopping",
            "subcategory":"Computers & Home Electronics",
            "type":"Retail Goods"
        }
    ],
    "sg:phone":"+61 3 9729 8222",
    "sg:postcode":"3153",
    "sg:province":"VIC",
    "sg:tags":[
        "wholesaler",
        "equipment",
        "electronic",
        "mfrs"
    ],
    "wof:name":"Vema International Pty Ltd",
    "wof:placetype":"venue"
},
  "geometry": {"coordinates":[145.244216919,-37.8439407349],"type":"Point"}
}