{
  "type": "Feature",
  "properties": {
    "addr:full":"PO Box 6026 Hammondville NSW 2170",
    "addr:postcode":"2170",
    "iso:country":"AU",
    "sg:address":"PO Box 6026",
    "sg:city":"Hammondville",
    "sg:classifiers":[
        {
            "category":"Building & Trades",
            "subcategory":"Pest Control",
            "type":"Services"
        }
    ],
    "sg:phone":"+61 422 704 020",
    "sg:postcode":"2170",
    "sg:province":"NSW",
    "wof:name":"A.A.A.A. Pest Control",
    "wof:placetype":"venue"
},
  "geometry": {"coordinates":[150.95053100600001,-33.948890686],"type":"Point"}
}