{
  "type": "Feature",
  "properties": {
    "addr:full":"151 Dawson Ave Forrestfield WA 6058",
    "addr:housenumber":"151",
    "addr:postcode":"6058",
    "addr:street":"Dawson Ave",
    "iso:country":"AU",
    "sg:address":"151 Dawson Ave",
    "sg:city":"Forrestfield",
    "sg:classifiers":[
        {
            "category":"Professional",
            "subcategory":"Accounting & Tax Preparation",
            "type":"Services"
        }
    ],
    "sg:phone":"+61 8 9276 6863",
    "sg:postcode":"6058",
    "sg:province":"WA",
    "sg:tags":[
        "accountant",
        "auditor"
    ],
    "wof:name":"Abbott Cooper & Co. M.F.",
    "wof:placetype":"venue"
},
  "geometry": {"coordinates":[115.99546814,-31.9817790985],"type":"Point"}
}