{
  "type": "Feature",
  "properties": {
    "iso:country":"AU",
    "sg:address":"2 Industrial Ave",
    "sg:city":"Hoppers Crossing",
    "sg:classifiers":[
        {
            "category":"Food & Beverages",
            "subcategory":"Bakery",
            "type":"Retail Goods"
        }
    ],
    "sg:phone":"+61 3 9369 6071",
    "sg:postcode":"3029",
    "sg:province":"VIC",
    "sg:tags":[
        "baker"
    ],
    "wof:name":"Outback Bakeries",
    "wof:placetype":"venue"
},
  "geometry": {"coordinates":[144.724762,-37.870003],"type":"Point"}
}