{
  "type": "Feature",
  "properties": {
    "addr:full":"Suite 2/ 22 Spit Rd Mosman NSW 2088",
    "addr:housenumber":"22",
    "addr:postcode":"2088",
    "addr:street":"Spit Rd",
    "iso:country":"AU",
    "sg:address":"Suite 2/ 22 Spit Rd",
    "sg:city":"Mosman",
    "sg:classifiers":[
        {
            "category":"Personal",
            "subcategory":"Massage",
            "type":"Services"
        }
    ],
    "sg:phone":"+61 2 9960 3422",
    "sg:postcode":"2088",
    "sg:province":"NSW",
    "sg:tags":[
        "therapy"
    ],
    "wof:name":"Renew Therapies",
    "wof:placetype":"venue"
},
  "geometry": {"coordinates":[151.24127197300001,-33.8240966797],"type":"Point"}
}