{
  "type": "Feature",
  "properties": {
    "addr:full":"43 Kethel Rd Cheltenham NSW 2119",
    "addr:housenumber":"43",
    "addr:postcode":"2119",
    "addr:street":"Kethel Rd",
    "iso:country":"AU",
    "sg:address":"43 Kethel Rd",
    "sg:city":"Cheltenham",
    "sg:classifiers":[
        {
            "category":"Professional",
            "subcategory":"Computer Services",
            "type":"Services"
        }
    ],
    "sg:phone":"+61 2 9484 4832",
    "sg:postcode":"2119",
    "sg:province":"NSW",
    "sg:tags":[
        "consultant",
        "system"
    ],
    "wof:name":"Cad Outsource Group",
    "wof:placetype":"venue"
},
  "geometry": {"coordinates":[151.077194214,-33.7514305115],"type":"Point"}
}