{
  "type": "Feature",
  "properties": {
    "addr:full":"704 Station St Box Hill VIC 3128",
    "addr:housenumber":"704",
    "addr:postcode":"3128",
    "addr:street":"Station St",
    "iso:country":"AU",
    "sg:address":"704 Station St",
    "sg:city":"Box Hill",
    "sg:classifiers":[
        {
            "category":"Retail",
            "subcategory":"Self-service Laundry",
            "type":"Services"
        }
    ],
    "sg:phone":"+61 3 9898 2677",
    "sg:postcode":"3128",
    "sg:province":"VIC",
    "wof:name":"Box Hill Laundrette",
    "wof:placetype":"venue"
},
  "geometry": {"coordinates":[145.124237061,-37.8172912598],"type":"Point"}
}