{
  "type": "Feature",
  "properties": {
    "addr:full":"66 Lantana Drv Narre Warren VIC 3805",
    "addr:housenumber":"66",
    "addr:postcode":"3805",
    "addr:street":"Lantana Drv",
    "iso:country":"AU",
    "sg:address":"66 Lantana Drv",
    "sg:city":"Narre Warren",
    "sg:classifiers":[
        {
            "category":"Utilities",
            "subcategory":"Electric",
            "type":"Services"
        }
    ],
    "sg:phone":"+61 3 9705 2870",
    "sg:postcode":"3805",
    "sg:province":"VIC",
    "sg:tags":[
        "electrical",
        "contractor"
    ],
    "wof:name":"Main Guy Electrical",
    "wof:placetype":"venue"
},
  "geometry": {"coordinates":[145.31987000000001,-38.039074],"type":"Point"}
}