{
  "type": "Feature",
  "properties": {
    "addr:full":"2 Bertram St Glen Iris VIC 3146",
    "addr:housenumber":"2",
    "addr:postcode":"3146",
    "addr:street":"Bertram St",
    "iso:country":"AU",
    "sg:address":"2 Bertram St",
    "sg:city":"Glen Iris",
    "sg:classifiers":[
        {
            "category":"Professional",
            "subcategory":"Employment Agencies",
            "type":"Services"
        }
    ],
    "sg:phone":"+61 438 370 103",
    "sg:postcode":"3146",
    "sg:province":"VIC",
    "sg:tags":[
        "entertainer",
        "agent"
    ],
    "wof:name":"Andrew Dyson",
    "wof:placetype":"venue"
},
  "geometry": {"coordinates":[145.08180236800001,-37.8529090881],"type":"Point"}
}