{
  "type": "Feature",
  "properties": {
    "iso:country":"AU",
    "sg:address":"131 Bunya Rd",
    "sg:city":"Arana Hills",
    "sg:classifiers":[
        {
            "category":"Building & Trades",
            "subcategory":"Construction",
            "type":"Services"
        }
    ],
    "sg:phone":"+61 7 3851 0200",
    "sg:postcode":"4054",
    "sg:province":"QLD",
    "sg:tags":[
        "contractor"
    ],
    "wof:name":"Bang A Bundy",
    "wof:placetype":"venue"
},
  "geometry": {"coordinates":[152.962036133,-27.3875541687],"type":"Point"}
}