{
  "type": "Feature",
  "properties": {
    "addr:full":"111 Juliette St Greenslopes QLD 4120",
    "addr:housenumber":"111",
    "addr:postcode":"4120",
    "addr:street":"Juliette St",
    "iso:country":"AU",
    "sg:address":"111 Juliette St",
    "sg:city":"Greenslopes",
    "sg:classifiers":[
        {
            "category":"Building & Trades",
            "subcategory":"Construction",
            "type":"Services"
        }
    ],
    "sg:phone":"+61 407 619 561",
    "sg:postcode":"4120",
    "sg:province":"QLD",
    "sg:tags":[
        "window",
        "aluminium"
    ],
    "wof:name":"System Ex Australia",
    "wof:placetype":"venue"
},
  "geometry": {"coordinates":[153.041183472,-27.5045204163],"type":"Point"}
}