{
  "type": "Feature",
  "properties": {
    "addr:full":"18 Morley Ave Kingswood NSW 2747",
    "addr:housenumber":"18",
    "addr:postcode":"2747",
    "addr:street":"Morley Ave",
    "iso:country":"AU",
    "sg:address":"18 Morley Ave",
    "sg:city":"Kingswood",
    "sg:classifiers":[
        {
            "category":"Shopping",
            "subcategory":"Clothing, Apparel, & Fashions",
            "type":"Retail Goods"
        }
    ],
    "sg:phone":"+61 2 4736 1558",
    "sg:postcode":"2747",
    "sg:province":"NSW",
    "sg:tags":[
        "lady",
        "wear"
    ],
    "wof:name":"Spyros Cutting Service",
    "wof:placetype":"venue"
},
  "geometry": {"coordinates":[150.72836303700001,-33.7593727112],"type":"Point"}
}