{
  "type": "Feature",
  "properties": {
    "iso:country":"AU",
    "sg:address":"27 Herbert Rd",
    "sg:city":"Bunbury",
    "sg:classifiers":[
        {
            "category":"Building & Trades",
            "subcategory":"Construction",
            "type":"Services"
        }
    ],
    "sg:phone":"+61 8 9721 2012",
    "sg:postcode":"6230",
    "sg:province":"WA",
    "sg:tags":[
        "earth",
        "excavating",
        "moving",
        "contractor"
    ],
    "wof:name":"Country Bobcat & Truck Hire",
    "wof:placetype":"venue"
},
  "geometry": {"coordinates":[115.652138,-33.332581],"type":"Point"}
}