{
  "type": "Feature",
  "properties": {
    "addr:full":"320 Bay St Brighton North VIC 3186",
    "addr:housenumber":"320",
    "addr:postcode":"3186",
    "addr:street":"Bay St",
    "iso:country":"AU",
    "sg:address":"320 Bay St",
    "sg:city":"Brighton North",
    "sg:classifiers":[
        {
            "category":"Farming",
            "subcategory":"Fish & Marine Products",
            "type":"Manufacturing & Wholesale Goods"
        }
    ],
    "sg:phone":"+61 3 9596 9035",
    "sg:postcode":"3186",
    "sg:province":"VIC",
    "sg:tags":[
        "organic"
    ],
    "wof:name":"Wholefoods Food Store",
    "wof:placetype":"venue"
},
  "geometry": {"coordinates":[145.00311279300001,-37.9057235718],"type":"Point"}
}