{
  "type": "Feature",
  "properties": {
    "addr:full":"Lv 1/ 215 Main St Osborne Park WA 6017",
    "addr:housenumber":"215",
    "addr:postcode":"6017",
    "addr:street":"Main St",
    "iso:country":"AU",
    "sg:address":"Lv 1/ 215 Main St",
    "sg:city":"Osborne Park",
    "sg:classifiers":[
        {
            "category":"Shopping",
            "subcategory":"Clothing, Apparel, & Fashions",
            "type":"Retail Goods"
        }
    ],
    "sg:phone":"+61 8 9349 1119",
    "sg:postcode":"6017",
    "sg:province":"WA",
    "sg:tags":[
        "lady",
        "wear"
    ],
    "wof:name":"Skirtz",
    "wof:placetype":"venue"
},
  "geometry": {"coordinates":[115.828102112,-31.8970756531],"type":"Point"}
}