{
  "type": "Feature",
  "properties": {
    "addr:full":"94 Woonona Ave Wahroonga NSW 2076",
    "addr:housenumber":"94",
    "addr:postcode":"2076",
    "addr:street":"Woonona Ave",
    "iso:country":"AU",
    "sg:address":"94 Woonona Ave",
    "sg:city":"Wahroonga",
    "sg:classifiers":[
        {
            "category":"Real Estate",
            "subcategory":"Architect",
            "type":"Services"
        }
    ],
    "sg:phone":"+61 2 9489 2131",
    "sg:postcode":"2076",
    "sg:province":"NSW",
    "wof:name":"GDM Design Architects",
    "wof:placetype":"venue"
},
  "geometry": {"coordinates":[151.11558532699999,-33.7071266174],"type":"Point"}
}