{
  "type": "Feature",
  "properties": {
    "addr:full":"4/84 Bells Line of Road North Richmond NSW 2754",
    "addr:housenumber":"/ 84",
    "addr:postcode":"2754",
    "addr:street":"Bells Line Of Road",
    "iso:country":"AU",
    "sg:address":"4/84 Bells Line of Road",
    "sg:city":"North Richmond",
    "sg:classifiers":[
        {
            "category":"Home & Garden",
            "subcategory":"Furniture",
            "type":"Retail Goods"
        }
    ],
    "sg:phone":"+61 2 4571 4877",
    "sg:postcode":"2754",
    "sg:province":"NSW",
    "sg:tags":[
        "repair",
        "restoration"
    ],
    "wof:name":"Harry Howard Fine Furniture",
    "wof:placetype":"venue"
},
  "geometry": {"coordinates":[150.71777343799999,-33.5778236389],"type":"Point"}
}