{
  "type": "Feature",
  "properties": {
    "addr:full":"174 Long Gully Rd Indigo Valley NSW 3685",
    "addr:housenumber":"174",
    "addr:postcode":"3685",
    "addr:street":"Long Gully Rd",
    "iso:country":"AU",
    "sg:address":"174 Long Gully Rd",
    "sg:city":"Indigo Valley",
    "sg:classifiers":[
        {
            "category":"Utilities",
            "subcategory":"Water",
            "type":"Services"
        }
    ],
    "sg:phone":"+61 2 6026 9238",
    "sg:postcode":"3685",
    "sg:province":"NSW",
    "sg:tags":[
        "cartage"
    ],
    "wof:name":"Whippet Transport",
    "wof:placetype":"venue"
},
  "geometry": {"coordinates":[146.45783996599999,-36.058921814],"type":"Point"}
}