{
  "type": "Feature",
  "properties": {
    "addr:full":"Level 5, 96 Albert St Brisbane QLD 4000",
    "addr:housenumber":"96",
    "addr:postcode":"4000",
    "addr:street":"Albert St",
    "iso:country":"AU",
    "sg:address":"Level 5, 96 Albert St",
    "sg:city":"Brisbane",
    "sg:classifiers":[
        {
            "category":"Organizations",
            "subcategory":"Labor Organization",
            "type":"Services"
        }
    ],
    "sg:phone":"+61 1300 137 636",
    "sg:postcode":"4000",
    "sg:province":"QLD",
    "sg:tags":[
        "union"
    ],
    "wof:name":"Community and Public Sector Union (CPSU)",
    "wof:placetype":"venue"
},
  "geometry": {"coordinates":[153.027252197,-27.4718589783],"type":"Point"}
}