{
  "type": "Feature",
  "properties": {
    "iso:country":"AU",
    "sg:address":"Learmonth St",
    "sg:city":"Ballarat",
    "sg:classifiers":[
        {
            "category":"Personal",
            "type":"Services"
        }
    ],
    "sg:phone":"+61 1300 130 245",
    "sg:postcode":"3350",
    "sg:province":"VIC",
    "sg:tags":[
        "counselling",
        "alcohol",
        "drug"
    ],
    "wof:name":"Driver Training Academy",
    "wof:placetype":"venue"
},
  "geometry": {"coordinates":[143.810654,-37.568817],"type":"Point"}
}