{
  "type": "Feature",
  "properties": {
    "iso:country":"AU",
    "sg:address":"10 Lamont St",
    "sg:city":"Bermagui",
    "sg:classifiers":[
        {
            "category":"Travel",
            "subcategory":"Hotels & Motels",
            "type":"Entertainment"
        }
    ],
    "sg:phone":"+61 2 6493 4206",
    "sg:postcode":"2546",
    "sg:province":"NSW",
    "wof:name":"Bermagui Beach Hotel",
    "wof:placetype":"venue"
},
  "geometry": {"coordinates":[150.07882690400001,-36.4261474609],"type":"Point"}
}