{
  "type": "Feature",
  "properties": {
    "addr:full":"PO Box 125 Brunswick Junction WA 6224",
    "addr:postcode":"6224",
    "iso:country":"AU",
    "sg:address":"PO Box 125",
    "sg:city":"Brunswick Junction",
    "sg:classifiers":[
        {
            "category":"Professional",
            "subcategory":"Business Services",
            "type":"Services"
        }
    ],
    "sg:phone":"+61 8 9726 9069",
    "sg:postcode":"6224",
    "sg:province":"WA",
    "sg:tags":[
        "drafting"
    ],
    "wof:name":"Southern Cross Architectural Drafting",
    "wof:placetype":"venue"
},
  "geometry": {"coordinates":[115.839691,-33.252102],"type":"Point"}
}