{
  "type": "Feature",
  "properties": {
    "addr:full":"Suite 1/ 81 Brisbane St Ipswich QLD 4305",
    "addr:housenumber":"81",
    "addr:postcode":"4305",
    "addr:street":"Brisbane St",
    "iso:country":"AU",
    "sg:address":"Suite 1/ 81 Brisbane St",
    "sg:city":"Ipswich",
    "sg:classifiers":[
        {
            "category":"Professional",
            "subcategory":"Accounting & Tax Preparation",
            "type":"Services"
        }
    ],
    "sg:phone":"+61 7 3281 4559",
    "sg:postcode":"4305",
    "sg:province":"QLD",
    "sg:tags":[
        "consultant",
        "taxation"
    ],
    "wof:name":"Wayne Page & Associates",
    "wof:placetype":"venue"
},
  "geometry": {"coordinates":[152.761352539,-27.614522934],"type":"Point"}
}