{
  "type": "Feature",
  "properties": {
    "addr:full":"94 Lear Jet Dr Caboolture QLD 4510",
    "addr:housenumber":"94",
    "addr:postcode":"4510",
    "addr:street":"Lear Jet Dr",
    "iso:country":"AU",
    "sg:address":"94 Lear Jet Dr",
    "sg:city":"Caboolture",
    "sg:classifiers":[
        {
            "category":"Professional",
            "subcategory":"Detective & Security Services",
            "type":"Services"
        }
    ],
    "sg:phone":"+61 7 5499 0904",
    "sg:postcode":"4510",
    "sg:province":"QLD",
    "sg:tags":[
        "protective",
        "rustproofing"
    ],
    "wof:name":"Tint Mart Window Tinting",
    "wof:placetype":"venue"
},
  "geometry": {"coordinates":[152.97839400000001,-27.08407],"type":"Point"}
}