{
  "type": "Feature",
  "properties": {
    "addr:full":"64 Lahrs Rd Ormeau QLD 4208",
    "addr:housenumber":"64",
    "addr:postcode":"4208",
    "addr:street":"Lahrs Rd",
    "iso:country":"AU",
    "sg:address":"64 Lahrs Rd",
    "sg:city":"Ormeau",
    "sg:classifiers":[
        {
            "category":"Freight",
            "type":"Transportation"
        }
    ],
    "sg:phone":"+61 7 5547 1200",
    "sg:postcode":"4208",
    "sg:province":"QLD",
    "sg:tags":[
        "transport",
        "refrigerated"
    ],
    "wof:name":"Australian Meat Carriers",
    "wof:placetype":"venue"
},
  "geometry": {"coordinates":[153.24888610799999,-27.7610664368],"type":"Point"}
}