{
  "type": "Feature",
  "properties": {
    "iso:country":"AU",
    "sg:address":"26 Craighill Drv",
    "sg:city":"Wheelers Hill",
    "sg:classifiers":[
        {
            "category":"Manufacturing",
            "subcategory":"Buildings",
            "type":"Manufacturing & Wholesale Goods"
        }
    ],
    "sg:phone":"+61 3 9561 5700",
    "sg:postcode":"3150",
    "sg:province":"VIC",
    "sg:tags":[
        "transportable",
        "domestic",
        "relocatable"
    ],
    "wof:name":"Better House Removers Pty Ltd",
    "wof:placetype":"venue"
},
  "geometry": {"coordinates":[145.19404602,-37.913192749],"type":"Point"}
}