{
  "type": "Feature",
  "properties": {
    "addr:full":"107 Ballandella Rd Toongabbie NSW 2146",
    "addr:housenumber":"107",
    "addr:postcode":"2146",
    "addr:street":"Ballandella Rd",
    "iso:country":"AU",
    "sg:address":"107 Ballandella Rd",
    "sg:city":"Toongabbie",
    "sg:classifiers":[
        {
            "category":"Banks & Credit Unions",
            "subcategory":"Bureau De Change",
            "type":"Services"
        }
    ],
    "sg:phone":"+61 402 417 791",
    "sg:postcode":"2146",
    "sg:province":"NSW",
    "sg:tags":[
        "repairs",
        "part",
        "appliance",
        "electrical"
    ],
    "wof:name":"New Service Appliance Repairs",
    "wof:placetype":"venue"
},
  "geometry": {"coordinates":[150.95591735799999,-33.7953681946],"type":"Point"}
}