{
  "type": "Feature",
  "properties": {
    "addr:full":"336 Kent St Maryborough QLD 4650",
    "addr:housenumber":"336",
    "addr:postcode":"4650",
    "addr:street":"Kent St",
    "iso:country":"AU",
    "sg:address":"336 Kent St",
    "sg:city":"Maryborough",
    "sg:classifiers":[
        {
            "category":"Travel",
            "subcategory":"Hotels & Motels",
            "type":"Entertainment"
        }
    ],
    "sg:phone":"+61 7 4121 6225",
    "sg:postcode":"4650",
    "sg:province":"QLD",
    "sg:tags":[
        "accommodation"
    ],
    "wof:name":"Royal Hotel",
    "wof:placetype":"venue"
},
  "geometry": {"coordinates":[152.69906599999999,-25.535395],"type":"Point"}
}