{
  "type": "Feature",
  "properties": {
    "iso:country":"AU",
    "sg:address":"15 Laidley St",
    "sg:city":"Lithgow",
    "sg:classifiers":[
        {
            "category":"Manufacturing",
            "subcategory":"Tools & Machinery",
            "type":"Manufacturing & Wholesale Goods"
        }
    ],
    "sg:phone":"+61 2 6351 2647",
    "sg:postcode":"2790",
    "sg:province":"NSW",
    "sg:tags":[
        "earth",
        "excavating",
        "moving",
        "equipment"
    ],
    "wof:name":"Kemdar Pty. Ltd.",
    "wof:placetype":"venue"
},
  "geometry": {"coordinates":[150.16958618199999,-33.4710655212],"type":"Point"}
}