{
  "type": "Feature",
  "properties": {
    "addr:full":"164 Abbotsford Rd Bowen Hills QLD 4006",
    "addr:housenumber":"164",
    "addr:postcode":"4006",
    "addr:street":"Abbotsford Rd",
    "iso:country":"AU",
    "sg:address":"164 Abbotsford Rd",
    "sg:city":"Bowen Hills",
    "sg:classifiers":[
        {
            "category":"Utilities",
            "subcategory":"Electric",
            "type":"Services"
        }
    ],
    "sg:phone":"+61 7 3252 4257",
    "sg:postcode":"4006",
    "sg:province":"QLD",
    "sg:tags":[
        "element"
    ],
    "wof:name":"Cynebar",
    "wof:placetype":"venue"
},
  "geometry": {"coordinates":[153.04066467300001,-27.4381637573],"type":"Point"}
}