{
  "type": "Feature",
  "properties": {
    "addr:full":"207 Regency Rd Croydon Park SA 5008",
    "addr:housenumber":"207",
    "addr:postcode":"5008",
    "addr:street":"Regency Rd",
    "iso:country":"AU",
    "sg:address":"207 Regency Rd",
    "sg:city":"Croydon Park",
    "sg:classifiers":[
        {
            "category":"Industrial Area",
            "type":"Public Place"
        }
    ],
    "sg:phone":"+61 8 8346 6899",
    "sg:postcode":"5008",
    "sg:province":"SA",
    "sg:tags":[
        "protective",
        "clothing"
    ],
    "wof:name":"Romac Trading Co Pty Ltd",
    "wof:placetype":"venue"
},
  "geometry": {"coordinates":[138.57260099999999,-34.875164],"type":"Point"}
}