{
  "type": "Feature",
  "properties": {
    "iso:country":"AU",
    "sg:address":"600- 604 Geelong Rd",
    "sg:city":"Brooklyn",
    "sg:classifiers":[
        {
            "category":"Real Estate",
            "subcategory":"Developer",
            "type":"Services"
        }
    ],
    "sg:phone":"+61 3 9315 2266",
    "sg:postcode":"3025",
    "sg:province":"VIC",
    "sg:tags":[
        "development"
    ],
    "wof:name":"Coopersmith Holdings Pty Ltd",
    "wof:placetype":"venue"
},
  "geometry": {"coordinates":[144.837585,-37.819733],"type":"Point"}
}