{
  "type": "Feature",
  "properties": {
    "iso:country":"AU",
    "sg:address":"2 Wangee Rd",
    "sg:city":"Lakemba",
    "sg:classifiers":[
        {
            "category":"Health Services",
            "subcategory":"Doctor",
            "type":"Services"
        }
    ],
    "sg:phone":"+61 2 9740 8652",
    "sg:postcode":"2195",
    "sg:province":"NSW",
    "sg:tags":[
        "medical",
        "practitioner"
    ],
    "wof:name":"Dr P Barea Alameddin",
    "wof:placetype":"venue"
},
  "geometry": {"coordinates":[151.076416,-33.917538],"type":"Point"}
}