{
  "type": "Feature",
  "properties": {
    "iso:country":"AU",
    "sg:address":"128 Parramatta Rd",
    "sg:city":"Camperdown",
    "sg:classifiers":[
        {
            "category":"Cinema",
            "subcategory":"Movie Theater",
            "type":"Entertainment"
        }
    ],
    "sg:phone":"+61 2 9519 4606",
    "sg:postcode":"2050",
    "sg:province":"NSW",
    "wof:name":"Genesian Theatre Company",
    "wof:placetype":"venue"
},
  "geometry": {"coordinates":[151.177887,-33.886341],"type":"Point"}
}