{
  "type": "Feature",
  "properties": {
    "addr:full":"186 King St Clontarf QLD 4019",
    "addr:housenumber":"186",
    "addr:postcode":"4019",
    "addr:street":"King St",
    "iso:country":"AU",
    "sg:address":"186 King St",
    "sg:city":"Clontarf",
    "sg:classifiers":[
        {
            "category":"Building & Trades",
            "subcategory":"Plumbing",
            "type":"Services"
        }
    ],
    "sg:phone":"+61 7 3283 4529",
    "sg:postcode":"4019",
    "sg:province":"QLD",
    "sg:tags":[
        "plumber",
        "gasfitters"
    ],
    "wof:name":"Paul Fitzpatrick",
    "wof:placetype":"venue"
},
  "geometry": {"coordinates":[153.09164428700001,-27.2484321594],"type":"Point"}
}