{
  "type": "Feature",
  "properties": {
    "iso:country":"AU",
    "sg:address":"11 Buckley St",
    "sg:city":"Marrickville",
    "sg:classifiers":[
        {
            "category":"Wholesale",
            "subcategory":"Home Furnishings",
            "type":"Manufacturing & Wholesale Goods"
        }
    ],
    "sg:phone":"+61 2 9557 4998",
    "sg:postcode":"2204",
    "sg:province":"NSW",
    "wof:name":"Macaluso Upholstery",
    "wof:placetype":"venue"
},
  "geometry": {"coordinates":[151.165176,-33.912952],"type":"Point"}
}