{
  "type": "Feature",
  "properties": {
    "addr:full":"Unit 21 83- 89 Brighton Rd Elwood VIC 3184",
    "addr:housenumber":"83 89",
    "addr:postcode":"3184",
    "addr:street":"Brighton Rd",
    "iso:country":"AU",
    "sg:address":"Unit 21 83- 89 Brighton Rd",
    "sg:city":"Elwood",
    "sg:classifiers":[
        {
            "category":"Professional",
            "type":"Services"
        }
    ],
    "sg:phone":"+61 3 9525 7922",
    "sg:postcode":"3184",
    "sg:province":"VIC",
    "sg:tags":[
        "forwarding",
        "agent",
        "transport"
    ],
    "wof:name":"B.C.R. Freight (Victoria) Pty Ltd",
    "wof:placetype":"venue"
},
  "geometry": {"coordinates":[144.98982238799999,-37.8730659485],"type":"Point"}
}