{
  "type": "Feature",
  "properties": {
    "addr:full":"12 Allambee Pl Valentine NSW 2280",
    "addr:housenumber":"12",
    "addr:postcode":"2280",
    "addr:street":"Allambee Pl",
    "iso:country":"AU",
    "sg:address":"12 Allambee Pl",
    "sg:city":"Valentine",
    "sg:classifiers":[
        {
            "category":"Food & Beverages",
            "subcategory":"Groceries & Convenience Stores",
            "type":"Retail Goods"
        }
    ],
    "sg:phone":"+61 2 4946 7630",
    "sg:postcode":"2280",
    "sg:province":"NSW",
    "wof:name":"K.J.'s Mini Mart",
    "wof:placetype":"venue"
},
  "geometry": {"coordinates":[151.634277344,-33.0102539062],"type":"Point"}
}