{
  "type": "Feature",
  "properties": {
    "addr:full":"6 Harley Crt Finley NSW 2713",
    "addr:housenumber":"6",
    "addr:postcode":"2713",
    "addr:street":"Harley Crt",
    "iso:country":"AU",
    "sg:address":"6 Harley Crt",
    "sg:city":"Finley",
    "sg:classifiers":[
        {
            "category":"Wholesale",
            "subcategory":"Machinery & Supplies",
            "type":"Manufacturing & Wholesale Goods"
        }
    ],
    "sg:phone":"+61 3 5883 4560",
    "sg:postcode":"2713",
    "sg:province":"NSW",
    "sg:tags":[
        "agricultural"
    ],
    "wof:name":"Agtrade Machinery Pty Ltd",
    "wof:placetype":"venue"
},
  "geometry": {"coordinates":[145.58108520499999,-35.629989624],"type":"Point"}
}