{
  "type": "Feature",
  "properties": {
    "addr:full":"Shop 2/ 823 Pittwater Rd (Cnr South Creek Rd) Dee Why NSW 2099",
    "addr:housenumber":"shop 2 / 823",
    "addr:postcode":"2099",
    "addr:street":"Pittwater Rd Cnr South Creek Rd",
    "iso:country":"AU",
    "sg:address":"Shop 2/ 823 Pittwater Rd (Cnr South Creek Rd)",
    "sg:city":"Dee Why",
    "sg:classifiers":[
        {
            "category":"Health Services",
            "subcategory":"Chiropractor",
            "type":"Services"
        }
    ],
    "sg:phone":"+61 2 9984 0999",
    "sg:postcode":"2099",
    "sg:province":"NSW",
    "wof:name":"Chirosports DEE WHY",
    "wof:placetype":"venue"
},
  "geometry": {"coordinates":[151.29302978499999,-33.7453536987],"type":"Point"}
}