{
  "type": "Feature",
  "properties": {
    "addr:full":"512 Crescent Head Rd Kempsey NSW 2440",
    "addr:housenumber":"512",
    "addr:postcode":"2440",
    "addr:street":"Crescent Head Rd",
    "iso:country":"AU",
    "sg:address":"512 Crescent Head Rd",
    "sg:city":"Kempsey",
    "sg:classifiers":[
        {
            "category":"Professional",
            "subcategory":"Art Services",
            "type":"Services"
        }
    ],
    "sg:phone":"+61 2 6563 1449",
    "sg:postcode":"2440",
    "sg:province":"NSW",
    "sg:tags":[
        "picture",
        "frame",
        "framing"
    ],
    "wof:name":"Billy Goat Hill Picture Framing",
    "wof:placetype":"venue"
},
  "geometry": {"coordinates":[152.872604,-31.12077],"type":"Point"}
}