{
  "type": "Feature",
  "properties": {
    "addr:full":"74 Ahearne St Hermit Park QLD 4812",
    "addr:housenumber":"74",
    "addr:postcode":"4812",
    "addr:street":"Ahearne St",
    "iso:country":"AU",
    "sg:address":"74 Ahearne St",
    "sg:city":"Hermit Park",
    "sg:classifiers":[
        {
            "category":"Shopping",
            "subcategory":"Computers & Home Electronics",
            "type":"Retail Goods"
        }
    ],
    "sg:phone":"+61 7 4724 4033",
    "sg:postcode":"4812",
    "sg:province":"QLD",
    "sg:tags":[
        "hardware",
        "equipment"
    ],
    "wof:name":"John Grantham Computers",
    "wof:placetype":"venue"
},
  "geometry": {"coordinates":[146.807785,-19.281431],"type":"Point"}
}