{
  "type": "Feature",
  "properties": {
    "iso:country":"AU",
    "sg:address":"111 Beach Rd",
    "sg:city":"Pialba",
    "sg:classifiers":[
        {
            "category":"Wholesale",
            "subcategory":"Machinery & Supplies",
            "type":"Manufacturing & Wholesale Goods"
        }
    ],
    "sg:phone":"+61 7 4124 0999",
    "sg:postcode":"4655",
    "sg:province":"QLD",
    "sg:tags":[
        "bearing",
        "bushing"
    ],
    "wof:name":"Bearing Service Centre",
    "wof:placetype":"venue"
},
  "geometry": {"coordinates":[152.831024,-25.287935],"type":"Point"}
}