{
  "type": "Feature",
  "properties": {
    "addr:full":"Piazza on the Boulevarde 3221 Surfers Paradise Blv Surfers Paradise QLD 4217",
    "addr:postcode":"3221;4217",
    "addr:street":"Piazza;Boulevarde;Surfers Paradise Blv",
    "iso:country":"AU",
    "sg:address":"Piazza on the Boulevarde 3221 Surfers Paradise Blv",
    "sg:city":"Surfers Paradise",
    "sg:classifiers":[
        {
            "category":"Health Services",
            "subcategory":"Doctor",
            "type":"Services"
        }
    ],
    "sg:phone":"+61 7 5592 2299",
    "sg:postcode":"4217",
    "sg:province":"QLD",
    "sg:tags":[
        "medical",
        "practitioner"
    ],
    "wof:name":"Surfers Paradise Day & Night Medical Centre",
    "wof:placetype":"venue"
},
  "geometry": {"coordinates":[153.428787231,-28.0038166046],"type":"Point"}
}