{
  "type": "Feature",
  "properties": {
    "iso:country":"AU",
    "sg:address":"Phillip Island Tourist Rd",
    "sg:city":"Cowes",
    "sg:classifiers":[
        {
            "category":"Communications",
            "subcategory":"News Services",
            "type":"Services"
        }
    ],
    "sg:phone":"+61 3 5952 1307",
    "sg:postcode":"3922",
    "sg:province":"VIC",
    "sg:tags":[
        "information",
        "tourist",
        "attractions"
    ],
    "wof:name":"Koala Conservation Centre",
    "wof:placetype":"venue"
},
  "geometry": {"coordinates":[145.21678161599999,-38.4578094482],"type":"Point"}
}