{
  "type": "Feature",
  "properties": {
    "iso:country":"AU",
    "sg:address":"136 Furner Ave",
    "sg:city":"Geelong North",
    "sg:phone":"+61 3 5278 7888",
    "sg:postcode":"3215",
    "sg:province":"VIC",
    "wof:name":"Williams & Jackson Pty Ltd",
    "wof:placetype":"venue"
},
  "geometry": {"coordinates":[144.344360352,-38.1046333313],"type":"Point"}
}