{
  "type": "Feature",
  "properties": {
    "iso:country":"AU",
    "sg:address":"346 Pacific Hwy",
    "sg:city":"Lindfield",
    "sg:classifiers":[
        {
            "category":"Health Services",
            "subcategory":"Health Practitioner",
            "type":"Services"
        }
    ],
    "sg:phone":"+61 2 9416 2259",
    "sg:postcode":"2070",
    "sg:province":"NSW",
    "sg:tags":[
        "homoeopath"
    ],
    "wof:name":"Goodman Nick Dr",
    "wof:placetype":"venue"
},
  "geometry": {"coordinates":[151.16839599599999,-33.7749557495],"type":"Point"}
}