{
  "type": "Feature",
  "properties": {
    "addr:full":"127 Adelaide Rd Murray Bridge SA 5253",
    "addr:housenumber":"127",
    "addr:postcode":"5253",
    "addr:street":"Adelaide Rd",
    "iso:country":"AU",
    "sg:address":"127 Adelaide Rd",
    "sg:city":"Murray Bridge",
    "sg:classifiers":[
        {
            "category":"Autos & Motor Vehicles",
            "subcategory":"Auto Supplies",
            "type":"Retail Goods"
        }
    ],
    "sg:phone":"+61 8 8532 3255",
    "sg:postcode":"5253",
    "sg:province":"SA",
    "sg:tags":[
        "tyre"
    ],
    "wof:name":"Bridge Tyre Service",
    "wof:placetype":"venue"
},
  "geometry": {"coordinates":[139.26802063,-35.1222610474],"type":"Point"}
}