{
  "type": "Feature",
  "properties": {
    "addr:full":"55 Downey St Alexandra VIC 3714",
    "addr:housenumber":"55",
    "addr:postcode":"3714",
    "addr:street":"Downey St",
    "iso:country":"AU",
    "sg:address":"55 Downey St",
    "sg:city":"Alexandra",
    "sg:classifiers":[
        {
            "category":"Shopping",
            "subcategory":"Bicycles & Sporting Goods",
            "type":"Retail Goods"
        }
    ],
    "sg:phone":"+61 3 5772 0400",
    "sg:postcode":"3714",
    "sg:province":"VIC",
    "sg:tags":[
        "chemical",
        "equipment",
        "pool",
        "swimming"
    ],
    "wof:name":"Alexandra Pools & Spas",
    "wof:placetype":"venue"
},
  "geometry": {"coordinates":[145.706787109,-37.1921386719],"type":"Point"}
}