{
  "type": "Feature",
  "properties": {
    "iso:country":"AU",
    "sg:address":"18 Pickworth Drv",
    "sg:city":"Mill Park",
    "sg:classifiers":[
        {
            "category":"Building & Trades",
            "subcategory":"Construction",
            "type":"Services"
        }
    ],
    "sg:phone":"+61 418 587 627",
    "sg:postcode":"3082",
    "sg:province":"VIC",
    "sg:tags":[
        "joiner",
        "carpenter"
    ],
    "wof:name":"F.J.B.' s Carpentry & General Maintenance",
    "wof:placetype":"venue"
},
  "geometry": {"coordinates":[145.04414367699999,-37.6598510742],"type":"Point"}
}