{
  "type": "Feature",
  "properties": {
    "addr:full":"Ampol Service Stat 700 Victoria Rd Ermington NSW 2115",
    "addr:housenumber":"700",
    "addr:postcode":"2115",
    "addr:street":"Victoria Rd",
    "iso:country":"AU",
    "sg:address":"Ampol Service Stat 700 Victoria Rd",
    "sg:city":"Ermington",
    "sg:classifiers":[
        {
            "category":"Retail",
            "subcategory":"Car Wash",
            "type":"Services"
        }
    ],
    "sg:phone":"+61 2 9874 1888",
    "sg:postcode":"2115",
    "sg:province":"NSW",
    "sg:tags":[
        "truck",
        "cleaning"
    ],
    "wof:name":"Uncle Mick's Car Wash",
    "wof:placetype":"venue"
},
  "geometry": {"coordinates":[151.05642700199999,-33.7996406555],"type":"Point"}
}