{
  "type": "Feature",
  "properties": {
    "iso:country":"AU",
    "sg:address":"80- 84 Shamrock St",
    "sg:city":"Blackall",
    "sg:classifiers":[
        {
            "category":"Autos & Motor Vehicles",
            "subcategory":"Auto Supplies",
            "type":"Retail Goods"
        }
    ],
    "sg:phone":"+61 7 4657 4277",
    "sg:postcode":"4472",
    "sg:province":"QLD",
    "sg:tags":[
        "accessory"
    ],
    "wof:name":"Autopro",
    "wof:placetype":"venue"
},
  "geometry": {"coordinates":[145.46649169899999,-24.4248828888],"type":"Point"}
}