{
  "type": "Feature",
  "properties": {
    "addr:full":"129 Melbourne St North Adelaide SA 5006",
    "addr:housenumber":"129",
    "addr:postcode":"5006",
    "addr:street":"Melbourne St",
    "iso:country":"AU",
    "sg:address":"129 Melbourne St",
    "sg:city":"North Adelaide",
    "sg:classifiers":[
        {
            "category":"Personal",
            "subcategory":"Adult",
            "type":"Services"
        }
    ],
    "sg:phone":"+61 8 8267 2023",
    "sg:postcode":"5006",
    "sg:province":"SA",
    "sg:tags":[
        "product"
    ],
    "wof:name":"Whisper Shop The",
    "wof:placetype":"venue"
},
  "geometry": {"coordinates":[138.60707092300001,-34.9073486328],"type":"Point"}
}