{
  "type": "Feature",
  "properties": {
    "addr:full":"453 The Entrance Rd Long Jetty NSW 2261",
    "addr:housenumber":"453",
    "addr:postcode":"2261",
    "addr:street":"The Entrance Rd",
    "iso:country":"AU",
    "sg:address":"453 The Entrance Rd",
    "sg:city":"Long Jetty",
    "sg:classifiers":[
        {
            "category":"Real Estate",
            "subcategory":"Real Estate Agent",
            "type":"Services"
        }
    ],
    "sg:phone":"+61 2 4332 1155",
    "sg:postcode":"2261",
    "sg:province":"NSW",
    "sg:website":"http://www.mclachlanpts.com.au",
    "wof:name":"McLachlan Partners Real Estate",
    "wof:placetype":"venue"
},
  "geometry": {"coordinates":[151.48147599999999,-33.361591],"type":"Point"}
}