{
  "type": "Feature",
  "properties": {
    "addr:full":"9 Campbell St Cobar NSW 2835",
    "addr:housenumber":"9",
    "addr:postcode":"2835",
    "addr:street":"Campbell St",
    "iso:country":"AU",
    "sg:address":"9 Campbell St",
    "sg:city":"Cobar",
    "sg:classifiers":[
        {
            "category":"Mining & Drilling",
            "type":"Manufacturing & Wholesale Goods"
        }
    ],
    "sg:phone":"+61 2 6836 4309",
    "sg:postcode":"2835",
    "sg:province":"NSW",
    "sg:tags":[
        "boring",
        "contractor"
    ],
    "wof:name":"G.O.S. Drilling",
    "wof:placetype":"venue"
},
  "geometry": {"coordinates":[145.84948700000001,-31.498045],"type":"Point"}
}