{
  "type": "Feature",
  "properties": {
    "iso:country":"AU",
    "sg:address":"Marrickville Metro 34 Victoria Rd",
    "sg:city":"Marrickville",
    "sg:classifiers":[
        {
            "category":"Shopping",
            "subcategory":"Music",
            "type":"Retail Goods"
        }
    ],
    "sg:phone":"+61 2 9519 0910",
    "sg:postcode":"2204",
    "sg:province":"NSW",
    "sg:tags":[
        "store"
    ],
    "wof:name":"Sanity",
    "wof:placetype":"venue"
},
  "geometry": {"coordinates":[151.172028,-33.906013],"type":"Point"}
}