{
  "type": "Feature",
  "properties": {
    "iso:country":"AU",
    "sg:address":"20 McCartins La",
    "sg:city":"Mirboo North",
    "sg:classifiers":[
        {
            "category":"Farming",
            "subcategory":"Dairy Farm",
            "type":"Manufacturing & Wholesale Goods"
        }
    ],
    "sg:phone":"+61 3 5668 1357",
    "sg:postcode":"3871",
    "sg:province":"VIC",
    "wof:name":"McCartin M & L",
    "wof:placetype":"venue"
},
  "geometry": {"coordinates":[146.14801025400001,-38.4222335815],"type":"Point"}
}