{
  "type": "Feature",
  "properties": {
    "addr:full":"PO Box 58 Casula NSW 2170",
    "addr:postcode":"2170",
    "iso:country":"AU",
    "sg:address":"PO Box 58",
    "sg:city":"Casula",
    "sg:classifiers":[
        {
            "category":"Building & Trades",
            "subcategory":"Construction",
            "type":"Services"
        }
    ],
    "sg:phone":"+61 2 9601 6711",
    "sg:postcode":"2170",
    "sg:province":"NSW",
    "sg:tags":[
        "contractor"
    ],
    "wof:name":"Full Brick Homes Pty Ltd",
    "wof:placetype":"venue"
},
  "geometry": {"coordinates":[150.90397644000001,-33.9497909546],"type":"Point"}
}