{
  "type": "Feature",
  "properties": {
    "iso:country":"AU",
    "sg:address":"20 Glenbarry Rd",
    "sg:city":"Campbellfield",
    "sg:classifiers":[
        {
            "category":"Retail",
            "subcategory":"Auto Repair",
            "type":"Services"
        }
    ],
    "sg:phone":"+61 3 9357 7111",
    "sg:postcode":"3061",
    "sg:province":"VIC",
    "sg:tags":[
        "beater",
        "painter",
        "panel"
    ],
    "wof:name":"Malas Smash Repairs",
    "wof:placetype":"venue"
},
  "geometry": {"coordinates":[144.96234130900001,-37.663608551],"type":"Point"}
}