{
  "type": "Feature",
  "properties": {
    "iso:country":"AU",
    "sg:address":"951 Mountain Hwy",
    "sg:city":"Boronia",
    "sg:classifiers":[
        {
            "category":"Fast Food",
            "type":"Food & Drink"
        }
    ],
    "sg:phone":"+61 3 9720 2500",
    "sg:postcode":"3155",
    "sg:province":"VIC",
    "sg:tags":[
        "away",
        "take"
    ],
    "wof:name":"Dots Diner",
    "wof:placetype":"venue"
},
  "geometry": {"coordinates":[145.287307739,-37.8374176025],"type":"Point"}
}