{
  "type": "Feature",
  "properties": {
    "addr:full":"8 Kitson Pl Maddington WA 6109",
    "addr:housenumber":"8",
    "addr:postcode":"6109",
    "addr:street":"Kitson Pl",
    "iso:country":"AU",
    "sg:address":"8 Kitson Pl",
    "sg:city":"Maddington",
    "sg:classifiers":[
        {
            "category":"Home & Garden",
            "subcategory":"Building Materials",
            "type":"Retail Goods"
        }
    ],
    "sg:phone":"+61 8 9493 0188",
    "sg:postcode":"6109",
    "sg:province":"WA",
    "sg:tags":[
        "gate"
    ],
    "wof:name":"Lattice Makers W.A.",
    "wof:placetype":"venue"
},
  "geometry": {"coordinates":[115.983879089,-32.047000885],"type":"Point"}
}