{
  "type": "Feature",
  "properties": {
    "addr:full":"Unit 9/ 37 Borec Rd Penrith NSW 2750",
    "addr:postcode":"2750",
    "addr:street":"37 Borec Rd",
    "iso:country":"AU",
    "sg:address":"Unit 9/ 37 Borec Rd",
    "sg:city":"Penrith",
    "sg:classifiers":[
        {
            "category":"Personal",
            "subcategory":"Beauty Salon",
            "type":"Services"
        }
    ],
    "sg:phone":"+61 2 4731 3250",
    "sg:postcode":"2750",
    "sg:province":"NSW",
    "sg:tags":[
        "hairdresser"
    ],
    "wof:name":"Uptown Cuts",
    "wof:placetype":"venue"
},
  "geometry": {"coordinates":[150.89732360799999,-33.7458610535],"type":"Point"}
}