{
  "type": "Feature",
  "properties": {
    "addr:full":"10a Torpy Ave Snug TAS 7054",
    "addr:housenumber":"10a",
    "addr:postcode":"7054",
    "addr:street":"Torpy Ave",
    "iso:country":"AU",
    "sg:address":"10a Torpy Ave",
    "sg:city":"Snug",
    "sg:classifiers":[
        {
            "category":"Travel",
            "subcategory":"Hostel",
            "type":"Entertainment"
        }
    ],
    "sg:phone":"+61 3 6267 9966",
    "sg:postcode":"7054",
    "sg:province":"TAS",
    "sg:tags":[
        "home"
    ],
    "wof:name":"Snug Village Aged Care Home",
    "wof:placetype":"venue"
},
  "geometry": {"coordinates":[147.257645,-43.066776],"type":"Point"}
}