{
  "type": "Feature",
  "properties": {
    "addr:full":"115 Seaford Pl Seaford VIC 3198",
    "addr:housenumber":"115",
    "addr:postcode":"3198",
    "addr:street":"Seaford Pl",
    "iso:country":"AU",
    "sg:address":"115 Seaford Pl",
    "sg:city":"Seaford",
    "sg:classifiers":[
        {
            "category":"Arena",
            "subcategory":"Sports Club",
            "type":"Entertainment"
        }
    ],
    "sg:phone":"+61 3 9782 3077",
    "sg:postcode":"3198",
    "sg:province":"VIC",
    "sg:tags":[
        "defence",
        "supply",
        "self",
        "instruction",
        "martial art"
    ],
    "wof:name":"Martial Sports Aust Pty Ltd.",
    "wof:placetype":"venue"
},
  "geometry": {"coordinates":[145.141311645,-38.1107902527],"type":"Point"}
}