{
  "type": "Feature",
  "properties": {
    "addr:full":"No 8 505 Pittwater Rd Brookvale NSW 2100",
    "addr:housenumber":"505",
    "addr:postcode":"2100",
    "addr:street":"Pittwater Rd",
    "iso:country":"AU",
    "sg:address":"No 8 505 Pittwater Rd",
    "sg:city":"Brookvale",
    "sg:classifiers":[
        {
            "category":"Personal",
            "subcategory":"Massage",
            "type":"Services"
        }
    ],
    "sg:phone":"+61 2 9938 5718",
    "sg:postcode":"2100",
    "sg:province":"NSW",
    "sg:tags":[
        "therapy"
    ],
    "wof:name":"Aromas Parisenne International",
    "wof:placetype":"venue"
},
  "geometry": {"coordinates":[151.27127075199999,-33.7639007568],"type":"Point"}
}