{
  "type": "Feature",
  "properties": {
    "addr:full":"11 Bokissa Drv Frankston VIC 3199",
    "addr:housenumber":"11",
    "addr:postcode":"3199",
    "addr:street":"Bokissa Drv",
    "iso:country":"AU",
    "sg:address":"11 Bokissa Drv",
    "sg:city":"Frankston",
    "sg:classifiers":[
        {
            "category":"Building & Trades",
            "subcategory":"Construction",
            "type":"Services"
        }
    ],
    "sg:phone":"+61 3 9770 0977",
    "sg:postcode":"3199",
    "sg:province":"VIC",
    "sg:tags":[
        "contractor"
    ],
    "wof:name":"Sage Homes",
    "wof:placetype":"venue"
},
  "geometry": {"coordinates":[145.14831543,-38.1355552673],"type":"Point"}
}