{
  "type": "Feature",
  "properties": {
    "addr:full":"118 Maroondah Hwy Ringwood VIC 3134",
    "addr:housenumber":"118",
    "addr:postcode":"3134",
    "addr:street":"Maroondah Hwy",
    "iso:country":"AU",
    "sg:address":"118 Maroondah Hwy",
    "sg:city":"Ringwood",
    "sg:classifiers":[
        {
            "category":"Real Estate",
            "subcategory":"Real Estate Agent",
            "type":"Services"
        }
    ],
    "sg:phone":"+61 3 9870 0111",
    "sg:postcode":"3134",
    "sg:province":"VIC",
    "wof:name":"AA Michael Nardella Real Estate Pty Ltd",
    "wof:placetype":"venue"
},
  "geometry": {"coordinates":[145.22825622600001,-37.8156433105],"type":"Point"}
}