{
  "type": "Feature",
  "properties": {
    "addr:full":"Shed 1 11 Aldinga St Brendale QLD 4500",
    "addr:housenumber":"11",
    "addr:postcode":"4500",
    "addr:street":"Aldinga St",
    "iso:country":"AU",
    "sg:address":"Shed 1 11 Aldinga St",
    "sg:city":"Brendale",
    "sg:classifiers":[
        {
            "category":"Farming",
            "subcategory":"Fish & Marine Products",
            "type":"Manufacturing & Wholesale Goods"
        }
    ],
    "sg:phone":"+61 414 606 201",
    "sg:postcode":"4500",
    "sg:province":"QLD",
    "sg:tags":[
        "organic"
    ],
    "wof:name":"Bell K J & J Mushrooms",
    "wof:placetype":"venue"
},
  "geometry": {"coordinates":[152.97940063499999,-27.3190917969],"type":"Point"}
}