{
  "type": "Feature",
  "properties": {
    "iso:country":"AU",
    "sg:address":"3/ 51 High St",
    "sg:city":"Wallan",
    "sg:classifiers":[
        {
            "category":"Real Estate",
            "subcategory":"Real Estate Agent",
            "type":"Services"
        }
    ],
    "sg:phone":"+61 3 5783 1268",
    "sg:postcode":"3756",
    "sg:province":"VIC",
    "wof:name":"Raine & Horne",
    "wof:placetype":"venue"
},
  "geometry": {"coordinates":[144.979034,-37.415504],"type":"Point"}
}