{
  "type": "Feature",
  "properties": {
    "addr:full":"55 High St Ararat VIC 3377",
    "addr:housenumber":"55",
    "addr:postcode":"3377",
    "addr:street":"High St",
    "iso:country":"AU",
    "sg:address":"55 High St",
    "sg:city":"Ararat",
    "sg:classifiers":[
        {
            "category":"Health Services",
            "subcategory":"Doctor",
            "type":"Services"
        }
    ],
    "sg:phone":"+61 3 5352 2311",
    "sg:postcode":"3377",
    "sg:province":"VIC",
    "sg:tags":[
        "medical",
        "practitioner"
    ],
    "wof:name":"Ararat Medical Centre",
    "wof:placetype":"venue"
},
  "geometry": {"coordinates":[142.92828369099999,-37.2830162048],"type":"Point"}
}