{
  "type": "Feature",
  "properties": {
    "addr:full":"29 King St Lismore NSW 2480",
    "addr:housenumber":"29",
    "addr:postcode":"2480",
    "addr:street":"King St",
    "iso:country":"AU",
    "sg:address":"29 King St",
    "sg:city":"Lismore",
    "sg:classifiers":[
        {
            "category":"Home & Garden",
            "subcategory":"Carpets & Floor Coverings",
            "type":"Retail Goods"
        }
    ],
    "sg:phone":"+61 2 6622 3576",
    "sg:postcode":"2480",
    "sg:province":"NSW",
    "sg:tags":[
        "tile",
        "wall"
    ],
    "wof:name":"SHM Design",
    "wof:placetype":"venue"
},
  "geometry": {"coordinates":[153.28024292000001,-28.8084831238],"type":"Point"}
}