{
  "type": "Feature",
  "properties": {
    "addr:full":"690 Woodville Rd Villawood NSW 2163",
    "addr:housenumber":"690",
    "addr:postcode":"2163",
    "addr:street":"Woodville Rd",
    "iso:country":"AU",
    "sg:address":"690 Woodville Rd",
    "sg:city":"Villawood",
    "sg:classifiers":[
        {
            "category":"Retail",
            "subcategory":"Auto Repair",
            "type":"Services"
        }
    ],
    "sg:phone":"+61 2 9728 2907",
    "sg:postcode":"2163",
    "sg:province":"NSW",
    "sg:tags":[
        "body",
        "builder",
        "motor"
    ],
    "wof:name":"H T A Body Repairs",
    "wof:placetype":"venue"
},
  "geometry": {"coordinates":[150.973480225,-33.8886489868],"type":"Point"}
}