{
  "type": "Feature",
  "properties": {
    "addr:full":"133 Wandal Rd Rockhampton QLD 4700",
    "addr:housenumber":"133",
    "addr:postcode":"4700",
    "addr:street":"Wandal Rd",
    "iso:country":"AU",
    "sg:address":"133 Wandal Rd",
    "sg:city":"Rockhampton",
    "sg:classifiers":[
        {
            "category":"Food & Beverages",
            "subcategory":"Groceries & Convenience Stores",
            "type":"Retail Goods"
        }
    ],
    "sg:phone":"+61 7 4922 5494",
    "sg:postcode":"4700",
    "sg:province":"QLD",
    "wof:name":"Whites Store",
    "wof:placetype":"venue"
},
  "geometry": {"coordinates":[150.48907470699999,-23.3676681519],"type":"Point"}
}