{
  "type": "Feature",
  "properties": {
    "addr:full":"50B Angove St North Perth WA 6006",
    "addr:housenumber":"50b",
    "addr:postcode":"6006",
    "addr:street":"Angove St",
    "iso:country":"AU",
    "sg:address":"50B Angove St",
    "sg:city":"North Perth",
    "sg:classifiers":[
        {
            "category":"Wholesale",
            "subcategory":"Photographic Equipment",
            "type":"Manufacturing & Wholesale Goods"
        }
    ],
    "sg:phone":"+61 8 9228 4855",
    "sg:postcode":"6006",
    "sg:province":"WA",
    "sg:tags":[
        "wholesaler",
        "mfrs",
        "supply"
    ],
    "wof:name":"UR1 International",
    "wof:placetype":"venue"
},
  "geometry": {"coordinates":[115.857292175,-31.9296531677],"type":"Point"}
}