{
  "type": "Feature",
  "properties": {
    "iso:country":"AU",
    "sg:address":"Level 9, 20 Collins St",
    "sg:city":"Melbourne",
    "sg:classifiers":[
        {
            "category":"Health Services",
            "subcategory":"Health Practitioner",
            "type":"Services"
        }
    ],
    "sg:phone":"+61 3 9654 8918",
    "sg:postcode":"3000",
    "sg:province":"VIC",
    "sg:tags":[
        "physiotherapist"
    ],
    "wof:name":"David Zuker Oam Fasmf",
    "wof:placetype":"venue"
},
  "geometry": {"coordinates":[144.973190308,-37.8134040833],"type":"Point"}
}