{
  "type": "Feature",
  "properties": {
    "addr:full":"38 Carlyle St Ashwood VIC 3147",
    "addr:housenumber":"38",
    "addr:postcode":"3147",
    "addr:street":"Carlyle St",
    "iso:country":"AU",
    "sg:address":"38 Carlyle St",
    "sg:city":"Ashwood",
    "sg:classifiers":[
        {
            "category":"Professional",
            "subcategory":"Computer Services",
            "type":"Services"
        }
    ],
    "sg:phone":"+61 3 9885 7565",
    "sg:postcode":"3147",
    "sg:province":"VIC",
    "sg:tags":[
        "consultant",
        "system"
    ],
    "wof:name":"Intech Aust Pty Ltd",
    "wof:placetype":"venue"
},
  "geometry": {"coordinates":[145.09771728499999,-37.8613853455],"type":"Point"}
}