{
  "type": "Feature",
  "properties": {
    "addr:full":"240 Smith St Collingwood VIC 3066",
    "addr:housenumber":"240",
    "addr:postcode":"3066",
    "addr:street":"Smith St",
    "iso:country":"AU",
    "sg:address":"240 Smith St",
    "sg:city":"Collingwood",
    "sg:classifiers":[
        {
            "category":"Food & Beverages",
            "subcategory":"Supermarket",
            "type":"Retail Goods"
        }
    ],
    "sg:phone":"+61 3 9416 0413",
    "sg:postcode":"3066",
    "sg:province":"VIC",
    "sg:tags":[
        "grocery",
        "store"
    ],
    "wof:name":"My Quang Chinese Groceries",
    "wof:placetype":"venue"
},
  "geometry": {"coordinates":[144.983917236,-37.8018951416],"type":"Point"}
}