{
  "type": "Feature",
  "properties": {
    "addr:full":"254- 256 Parramatta Rd Stanmore NSW 2048",
    "addr:housenumber":"256",
    "addr:postcode":"2048",
    "addr:street":"Parramatta Rd",
    "iso:country":"AU",
    "sg:address":"254- 256 Parramatta Rd",
    "sg:city":"Stanmore",
    "sg:classifiers":[
        {
            "category":"Shopping",
            "subcategory":"Antiques",
            "type":"Retail Goods"
        }
    ],
    "sg:phone":"+61 2 9564 1256",
    "sg:postcode":"2048",
    "sg:province":"NSW",
    "sg:tags":[
        "restoration",
        "reproduction"
    ],
    "wof:name":"Annie-Boyd Antiques",
    "wof:placetype":"venue"
},
  "geometry": {"coordinates":[151.165268,-33.888248],"type":"Point"}
}