{
  "type": "Feature",
  "properties": {
    "addr:full":"Suite 507, 737 Burwood Rd Hawthorn VIC 3122",
    "addr:housenumber":"737",
    "addr:postcode":"3122",
    "addr:street":"Burwood Rd",
    "iso:country":"AU",
    "sg:address":"Suite 507, 737 Burwood Rd",
    "sg:city":"Hawthorn",
    "sg:classifiers":[
        {
            "category":"Building & Trades",
            "subcategory":"Construction",
            "type":"Services"
        }
    ],
    "sg:phone":"+61 3 8862 6322",
    "sg:postcode":"3122",
    "sg:province":"VIC",
    "sg:tags":[
        "contractor"
    ],
    "wof:name":"Latrobe Building Service Pty Ltd",
    "wof:placetype":"venue"
},
  "geometry": {"coordinates":[145.049194336,-37.8241119385],"type":"Point"}
}