{
  "type": "Feature",
  "properties": {
    "iso:country":"AU",
    "sg:address":"Cnr Ellen & Jessie Sts",
    "sg:city":"Penola",
    "sg:classifiers":[
        {
            "category":"Home & Garden",
            "subcategory":"Garden Supply",
            "type":"Retail Goods"
        }
    ],
    "sg:phone":"+61 8 8737 3266",
    "sg:postcode":"5277",
    "sg:province":"SA",
    "sg:tags":[
        "landscape"
    ],
    "wof:name":"Gem Building & Landscape Supplies",
    "wof:placetype":"venue"
},
  "geometry": {"coordinates":[140.837372,-37.367886],"type":"Point"}
}