{
  "type": "Feature",
  "properties": {
    "addr:full":"112-116 San Fernando Drv Worongary QLD 4213",
    "addr:postcode":"112-116;4213",
    "addr:street":"San Fernando Drv",
    "iso:country":"AU",
    "sg:address":"112-116 San Fernando Drv",
    "sg:city":"Worongary",
    "sg:classifiers":[
        {
            "category":"Building & Trades",
            "subcategory":"Equipment Rental",
            "type":"Services"
        }
    ],
    "sg:phone":"+61 413 130 033",
    "sg:postcode":"4213",
    "sg:province":"QLD",
    "sg:tags":[
        "crane",
        "hire"
    ],
    "wof:name":"Affordable Cranes",
    "wof:placetype":"venue"
},
  "geometry": {"coordinates":[153.34323120100001,-28.0324993134],"type":"Point"}
}