{
  "type": "Feature",
  "properties": {
    "iso:country":"AU",
    "sg:address":"34 Baynes St",
    "sg:city":"Margate",
    "sg:classifiers":[
        {
            "category":"Food & Beverages",
            "subcategory":"Bakery",
            "type":"Retail Goods"
        }
    ],
    "sg:phone":"+61 7 3284 7521",
    "sg:postcode":"4019",
    "sg:province":"QLD",
    "sg:tags":[
        "cake",
        "shop",
        "pastry"
    ],
    "wof:name":"Marles Cake Shops",
    "wof:placetype":"venue"
},
  "geometry": {"coordinates":[153.10838317899999,-27.2438430786],"type":"Point"}
}