{
  "type": "Feature",
  "properties": {
    "addr:full":"9 Doulton Rd Blackburn VIC 3130",
    "addr:housenumber":"9",
    "addr:postcode":"3130",
    "addr:street":"Doulton Rd",
    "iso:country":"AU",
    "sg:address":"9 Doulton Rd",
    "sg:city":"Blackburn",
    "sg:classifiers":[
        {
            "category":"Professional",
            "subcategory":"Art Services",
            "type":"Services"
        }
    ],
    "sg:phone":"+61 419 322 824",
    "sg:postcode":"3130",
    "sg:province":"VIC",
    "sg:tags":[
        "decorator",
        "painter"
    ],
    "wof:name":"Fad Painting & Decorating",
    "wof:placetype":"venue"
},
  "geometry": {"coordinates":[145.141967773,-37.8104286194],"type":"Point"}
}