{
  "type": "Feature",
  "properties": {
    "addr:full":"Turvey Crt St George QLD 4487",
    "addr:postcode":"4487",
    "addr:street":"Turvey Crt",
    "iso:country":"AU",
    "sg:address":"Turvey Crt St",
    "sg:city":"George",
    "sg:classifiers":[
        {
            "category":"Building & Trades",
            "subcategory":"Construction",
            "type":"Services"
        }
    ],
    "sg:phone":"+61 7 4625 3621",
    "sg:postcode":"4487",
    "sg:province":"QLD",
    "sg:tags":[
        "contractor"
    ],
    "wof:name":"Turvey G T & H G",
    "wof:placetype":"venue"
},
  "geometry": {"coordinates":[148.59707641599999,-28.0303840637],"type":"Point"}
}