{
  "type": "Feature",
  "properties": {
    "iso:country":"AU",
    "sg:address":"108 Maling Rd",
    "sg:city":"Canterbury",
    "sg:classifiers":[
        {
            "category":"Food & Beverages",
            "subcategory":"Fruits & Vegetables",
            "type":"Retail Goods"
        }
    ],
    "sg:phone":"+61 3 9836 4703",
    "sg:postcode":"3126",
    "sg:province":"VIC",
    "sg:tags":[
        "greengrocer",
        "fruiterer"
    ],
    "wof:name":"A&M Petroro",
    "wof:placetype":"venue"
},
  "geometry": {"coordinates":[145.08241272000001,-37.8246612549],"type":"Point"}
}