{
  "type": "Feature",
  "properties": {
    "addr:full":"Blackwood Ave Augusta WA 6290",
    "addr:postcode":"6290",
    "addr:street":"Blackwood Ave",
    "iso:country":"AU",
    "sg:address":"Blackwood Ave",
    "sg:city":"Augusta",
    "sg:classifiers":[
        {
            "category":"Deli",
            "type":"Food & Drink"
        }
    ],
    "sg:phone":"+61 8 9758 1400",
    "sg:postcode":"6290",
    "sg:province":"WA",
    "sg:tags":[
        "delicatessen"
    ],
    "wof:name":"Leewin Light Deli",
    "wof:placetype":"venue"
},
  "geometry": {"coordinates":[115.158638001,-34.3022537231],"type":"Point"}
}