{
  "type": "Feature",
  "properties": {
    "addr:full":"Shop 3, 129 Mooloolaba Esp Mooloolaba QLD 4557",
    "addr:housenumber":"shop 3",
    "addr:postcode":"129;4557",
    "iso:country":"AU",
    "sg:address":"Shop 3, 129",
    "sg:city":"Mooloolaba Esp Mooloolaba",
    "sg:classifiers":[
        {
            "category":"Shopping",
            "subcategory":"Clothing, Apparel, & Fashions",
            "type":"Retail Goods"
        }
    ],
    "sg:phone":"+61 7 5478 1525",
    "sg:postcode":"4557",
    "sg:province":"QLD",
    "sg:tags":[
        "lady",
        "wear"
    ],
    "wof:name":"Jebejay Boutique",
    "wof:placetype":"venue"
},
  "geometry": {"coordinates":[153.11991882300001,-26.679807663],"type":"Point"}
}