{
  "type": "Feature",
  "properties": {
    "iso:country":"AU",
    "sg:address":"150 Francisco St",
    "sg:city":"Belmont",
    "sg:classifiers":[
        {
            "category":"Shopping",
            "subcategory":"Clothing, Apparel, & Fashions",
            "type":"Retail Goods"
        }
    ],
    "sg:phone":"+61 8 9277 5555",
    "sg:postcode":"6104",
    "sg:province":"WA",
    "sg:tags":[
        "uniform"
    ],
    "wof:name":"Stewart & Heaton Clothing Co Pty Ltd",
    "wof:placetype":"venue"
},
  "geometry": {"coordinates":[115.92384338399999,-31.9535331726],"type":"Point"}
}