{
  "type": "Feature",
  "properties": {
    "addr:full":"425 Canterbury Rd Vermont VIC 3133",
    "addr:housenumber":"425",
    "addr:postcode":"3133",
    "addr:street":"Canterbury Rd",
    "iso:country":"AU",
    "sg:address":"425 Canterbury Rd",
    "sg:city":"Vermont",
    "sg:classifiers":[
        {
            "category":"Education",
            "subcategory":"Kindergarten",
            "type":"Public Place"
        }
    ],
    "sg:phone":"+61 3 9873 8400",
    "sg:postcode":"3133",
    "sg:province":"VIC",
    "sg:tags":[
        "pre-schools"
    ],
    "wof:name":"Vermont Child Care & Kindergarten-\"Top Kids\"",
    "wof:placetype":"venue"
},
  "geometry": {"coordinates":[145.189453125,-37.8365898132],"type":"Point"}
}