{
  "type": "Feature",
  "properties": {
    "addr:full":"Ferntree Gully Rd Scoresby VIC 3179",
    "addr:postcode":"3179",
    "addr:street":"Ferntree Gully Rd",
    "iso:country":"AU",
    "sg:address":"Ferntree Gully Rd",
    "sg:city":"Scoresby",
    "sg:classifiers":[
        {
            "category":"Manufacturing",
            "subcategory":"Glass & Minerals",
            "type":"Manufacturing & Wholesale Goods"
        }
    ],
    "sg:phone":"+61 3 9763 7233",
    "sg:postcode":"3179",
    "sg:province":"VIC",
    "sg:tags":[
        "repair",
        "fibreglass",
        "product"
    ],
    "wof:name":"Caribbean Boats",
    "wof:placetype":"venue"
},
  "geometry": {"coordinates":[145.21788024899999,-37.9017333984],"type":"Point"}
}