{
  "type": "Feature",
  "properties": {
    "iso:country":"AU",
    "sg:address":"4/ 1 Cook Drv",
    "sg:city":"Coffs Harbour",
    "sg:classifiers":[
        {
            "category":"Retail",
            "subcategory":"Repair Shop",
            "type":"Services"
        }
    ],
    "sg:phone":"+61 2 6652 6340",
    "sg:postcode":"2450",
    "sg:province":"NSW",
    "sg:tags":[
        "upholsterer"
    ],
    "wof:name":"Sutherland's Upholstery",
    "wof:placetype":"venue"
},
  "geometry": {"coordinates":[153.09672499999999,-30.313881],"type":"Point"}
}