{
  "type": "Feature",
  "properties": {
    "addr:full":"2 Law St Mt Gambier SA 5290",
    "addr:housenumber":"2",
    "addr:postcode":"5290",
    "addr:street":"Law St",
    "iso:country":"AU",
    "sg:address":"2 Law St",
    "sg:city":"Mt Gambier",
    "sg:classifiers":[
        {
            "category":"Building & Trades",
            "subcategory":"Locksmith",
            "type":"Services"
        }
    ],
    "sg:phone":"+61 8 8725 4546",
    "sg:postcode":"5290",
    "sg:province":"SA",
    "sg:tags":[
        "strongroom",
        "safe",
        "door"
    ],
    "wof:name":"Gambier Shooting Supplies Pty Ltd",
    "wof:placetype":"venue"
},
  "geometry": {"coordinates":[140.78831500000001,-37.816166],"type":"Point"}
}