{
  "type": "Feature",
  "properties": {
    "iso:country":"AU",
    "sg:address":"268 Queens Rd",
    "sg:city":"Wandin",
    "sg:classifiers":[
        {
            "category":"Farming",
            "subcategory":"Berry Farm",
            "type":"Manufacturing & Wholesale Goods"
        }
    ],
    "sg:phone":"+61 3 5964 4238",
    "sg:postcode":"3139",
    "sg:province":"VIC",
    "sg:tags":[
        "fruit",
        "grower"
    ],
    "wof:name":"Moon R B",
    "wof:placetype":"venue"
},
  "geometry": {"coordinates":[145.45484924300001,-37.7961273193],"type":"Point"}
}