{
  "type": "Feature",
  "properties": {
    "iso:country":"AU",
    "sg:address":"12 Trade St",
    "sg:city":"Lytton",
    "sg:classifiers":[
        {
            "category":"Building & Trades",
            "subcategory":"Plumbing",
            "type":"Services"
        }
    ],
    "sg:phone":"+61 7 3906 7600",
    "sg:postcode":"4178",
    "sg:province":"QLD",
    "sg:tags":[
        "pipe",
        "line",
        "contractor"
    ],
    "wof:name":"Delco Australia Pty Ltd",
    "wof:placetype":"venue"
},
  "geometry": {"coordinates":[153.145721436,-27.4286842346],"type":"Point"}
}