{
  "type": "Feature",
  "properties": {
    "addr:full":"177 Bourbong St Bundaberg QLD 4670",
    "addr:housenumber":"177",
    "addr:postcode":"4670",
    "addr:street":"Bourbong St",
    "iso:country":"AU",
    "sg:address":"177 Bourbong St",
    "sg:city":"Bundaberg",
    "sg:classifiers":[
        {
            "category":"Arts & Performance",
            "subcategory":"Theater",
            "type":"Entertainment"
        }
    ],
    "sg:phone":"+61 7 4192 1072",
    "sg:postcode":"4670",
    "sg:province":"QLD",
    "sg:tags":[
        "theatre"
    ],
    "wof:name":"Moncrieff Theatre",
    "wof:placetype":"venue"
},
  "geometry": {"coordinates":[152.34739685100001,-24.8662967682],"type":"Point"}
}