{
  "type": "Feature",
  "properties": {
    "addr:full":"37 Karome St Pacific Paradise QLD 4564",
    "addr:housenumber":"37",
    "addr:postcode":"4564",
    "addr:street":"Karome St",
    "iso:country":"AU",
    "sg:address":"37 Karome St",
    "sg:city":"Pacific Paradise",
    "sg:classifiers":[
        {
            "category":"Building & Trades",
            "subcategory":"Landscaping Services",
            "type":"Services"
        }
    ],
    "sg:phone":"+61 7 5448 8503",
    "sg:postcode":"4564",
    "sg:province":"QLD",
    "sg:tags":[
        "inspection"
    ],
    "wof:name":"Bill Finnerty",
    "wof:placetype":"venue"
},
  "geometry": {"coordinates":[153.07655334500001,-26.6165351868],"type":"Point"}
}