{
  "type": "Feature",
  "properties": {
    "addr:full":"125 Vincent St Cessnock NSW 2325",
    "addr:housenumber":"125",
    "addr:postcode":"2325",
    "addr:street":"Vincent St",
    "iso:country":"AU",
    "sg:address":"125 Vincent St",
    "sg:city":"Cessnock",
    "sg:classifiers":[
        {
            "category":"Professional",
            "subcategory":"Advertising",
            "type":"Services"
        }
    ],
    "sg:phone":"+61 2 4991 7199",
    "sg:postcode":"2325",
    "sg:province":"NSW",
    "sg:tags":[
        "balloon",
        "novelty"
    ],
    "wof:name":"Cessnock Floral Affects",
    "wof:placetype":"venue"
},
  "geometry": {"coordinates":[151.355957031,-32.8359909058],"type":"Point"}
}