{
  "type": "Feature",
  "properties": {
    "addr:full":"Suite 3 Level 1 486 Station St Box Hill VIC 3128",
    "addr:housenumber":"486",
    "addr:postcode":"3128",
    "addr:street":"Station St",
    "iso:country":"AU",
    "sg:address":"Suite 3 Level 1 486 Station St",
    "sg:city":"Box Hill",
    "sg:classifiers":[
        {
            "category":"Shopping",
            "subcategory":"Clothing, Apparel, & Fashions",
            "type":"Retail Goods"
        }
    ],
    "sg:phone":"+61 3 9896 1100",
    "sg:postcode":"3128",
    "sg:province":"VIC",
    "sg:tags":[
        "jean"
    ],
    "wof:name":"Giordano (Australia) Pty Ltd",
    "wof:placetype":"venue"
},
  "geometry": {"coordinates":[145.12278747600001,-37.8246841431],"type":"Point"}
}