{
  "type": "Feature",
  "properties": {
    "addr:full":"28 Watt St Cornubia QLD 4130",
    "addr:housenumber":"28",
    "addr:postcode":"4130",
    "addr:street":"Watt St",
    "iso:country":"AU",
    "sg:address":"28 Watt St",
    "sg:city":"Cornubia",
    "sg:classifiers":[
        {
            "category":"Building & Trades",
            "subcategory":"Construction",
            "type":"Services"
        }
    ],
    "sg:phone":"+61 417 664 446",
    "sg:postcode":"4130",
    "sg:province":"QLD",
    "sg:tags":[
        "concrete",
        "treatment",
        "repair"
    ],
    "wof:name":"Orpin John",
    "wof:placetype":"venue"
},
  "geometry": {"coordinates":[153.20103454599999,-27.6739273071],"type":"Point"}
}