{
  "type": "Feature",
  "properties": {
    "addr:full":"Suite 1/ 10 Kimberley Ave Modbury North SA 5092",
    "addr:housenumber":"10",
    "addr:postcode":"5092",
    "addr:street":"Kimberley Ave",
    "iso:country":"AU",
    "sg:address":"Suite 1/ 10 Kimberley Ave",
    "sg:city":"Modbury North",
    "sg:classifiers":[
        {
            "category":"Banks & Credit Unions",
            "subcategory":"Investment Brokerage",
            "type":"Services"
        }
    ],
    "sg:phone":"+61 411 627 772",
    "sg:postcode":"5092",
    "sg:province":"SA",
    "sg:tags":[
        "management",
        "property"
    ],
    "wof:name":"E-Financial Information Services Australasia",
    "wof:placetype":"venue"
},
  "geometry": {"coordinates":[138.684783936,-34.8186416626],"type":"Point"}
}