{
  "type": "Feature",
  "properties": {
    "iso:country":"AU",
    "sg:address":"58A Cleary St",
    "sg:city":"Hamilton",
    "sg:classifiers":[
        {
            "category":"Health Services",
            "subcategory":"Doctor",
            "type":"Services"
        }
    ],
    "sg:phone":"+61 2 4969 2739",
    "sg:postcode":"2303",
    "sg:province":"NSW",
    "sg:tags":[
        "medical",
        "practitioner"
    ],
    "wof:name":"Hamilton Eye Centre",
    "wof:placetype":"venue"
},
  "geometry": {"coordinates":[151.746826,-32.920582],"type":"Point"}
}