{
  "type": "Feature",
  "properties": {
    "addr:full":"49 MacBarry Pl Rocklea QLD 4106",
    "addr:housenumber":"49",
    "addr:postcode":"4106",
    "addr:street":"Macbarry Pl",
    "iso:country":"AU",
    "sg:address":"49 MacBarry Pl",
    "sg:city":"Rocklea",
    "sg:classifiers":[
        {
            "category":"Autos & Motor Vehicles",
            "subcategory":"Automobile Sales",
            "type":"Retail Goods"
        }
    ],
    "sg:phone":"+61 7 3277 3944",
    "sg:postcode":"4106",
    "sg:province":"QLD",
    "sg:tags":[
        "equipment",
        "trailer"
    ],
    "wof:name":"Trailer Industries",
    "wof:placetype":"venue"
},
  "geometry": {"coordinates":[153.00192260700001,-27.5495128632],"type":"Point"}
}