{
  "type": "Feature",
  "properties": {
    "iso:country":"AU",
    "sg:address":"162 Boundary Rd",
    "sg:city":"West End (Brisbane)",
    "sg:classifiers":[
        {
            "category":"Utilities",
            "subcategory":"Telephone",
            "type":"Services"
        }
    ],
    "sg:phone":"+61 1300 882 985",
    "sg:postcode":"4101",
    "sg:province":"QLD",
    "sg:tags":[
        "installation",
        "system",
        "maintenance"
    ],
    "wof:name":"Voip 4 U",
    "wof:placetype":"venue"
},
  "geometry": {"coordinates":[153.01205444300001,-27.4815502167],"type":"Point"}
}