{
  "type": "Feature",
  "properties": {
    "addr:full":"Shop 1 Queen Victoria Building Sydney NSW 2000",
    "addr:housenumber":"shop 1",
    "addr:postcode":"2000",
    "addr:street":"Queen",
    "iso:country":"AU",
    "sg:address":"Shop 1 Queen Victoria Building",
    "sg:city":"Sydney",
    "sg:classifiers":[
        {
            "category":"Shopping",
            "subcategory":"Clothing, Apparel, & Fashions",
            "type":"Retail Goods"
        }
    ],
    "sg:phone":"+61 2 9261 2034",
    "sg:postcode":"2000",
    "sg:province":"NSW",
    "sg:tags":[
        "lady",
        "wear"
    ],
    "wof:name":"Portmans",
    "wof:placetype":"venue"
},
  "geometry": {"coordinates":[151.159423828,-33.8509368896],"type":"Point"}
}