{
  "type": "Feature",
  "properties": {
    "iso:country":"AU",
    "sg:address":"195 Brunswick St",
    "sg:city":"Fitzroy",
    "sg:classifiers":[
        {
            "category":"Shopping",
            "subcategory":"Clothing, Apparel, & Fashions",
            "type":"Retail Goods"
        }
    ],
    "sg:phone":"+61 3 8415 0102",
    "sg:postcode":"3065",
    "sg:province":"VIC",
    "sg:tags":[
        "boutique"
    ],
    "wof:name":"Gizelle Pty Ltd",
    "wof:placetype":"venue"
},
  "geometry": {"coordinates":[144.97770690900001,-37.8016967773],"type":"Point"}
}