{
  "type": "Feature",
  "properties": {
    "addr:full":"48 Timbertop Drv Rowville VIC 3178",
    "addr:housenumber":"48",
    "addr:postcode":"3178",
    "addr:street":"Timbertop Drv",
    "iso:country":"AU",
    "sg:address":"48 Timbertop Drv",
    "sg:city":"Rowville",
    "sg:classifiers":[
        {
            "category":"Organizations",
            "subcategory":"Professional Association",
            "type":"Services"
        }
    ],
    "sg:phone":"+61 3 9790 1217",
    "sg:postcode":"3178",
    "sg:province":"VIC",
    "sg:tags":[
        "organisation",
        "business"
    ],
    "wof:name":"United Retailers Association",
    "wof:placetype":"venue"
},
  "geometry": {"coordinates":[145.225906372,-37.9328918457],"type":"Point"}
}