{
  "type": "Feature",
  "properties": {
    "addr:full":"PO Box 287 Beerwah QLD 4519",
    "addr:postcode":"4519",
    "iso:country":"AU",
    "sg:address":"PO Box 287",
    "sg:city":"Beerwah",
    "sg:classifiers":[
        {
            "category":"Manufacturing",
            "subcategory":"Buildings",
            "type":"Manufacturing & Wholesale Goods"
        }
    ],
    "sg:phone":"+61 7 5494 9666",
    "sg:postcode":"4519",
    "sg:province":"QLD",
    "sg:tags":[
        "house",
        "gazebo",
        "shade"
    ],
    "wof:name":"ClassicPavilions",
    "wof:placetype":"venue"
},
  "geometry": {"coordinates":[152.95784,-26.85771],"type":"Point"}
}