{
  "type": "Feature",
  "properties": {
    "iso:country":"AU",
    "sg:address":"Factory 1, 71 Northgate Dr",
    "sg:city":"Thomastown",
    "sg:classifiers":[
        {
            "category":"Retail",
            "subcategory":"Repair Shop",
            "type":"Services"
        }
    ],
    "sg:phone":"+61 1800 886 010",
    "sg:postcode":"3074",
    "sg:province":"VIC",
    "sg:tags":[
        "stove",
        "part",
        "range"
    ],
    "wof:name":"B A C Appliance Parts",
    "wof:placetype":"venue"
},
  "geometry": {"coordinates":[145.035232544,-37.6887702942],"type":"Point"}
}