{
  "type": "Feature",
  "properties": {
    "addr:full":"36 Lawrence Rd Point Lonsdale VIC 3225",
    "addr:housenumber":"36",
    "addr:postcode":"3225",
    "addr:street":"Lawrence Rd",
    "iso:country":"AU",
    "sg:address":"36 Lawrence Rd",
    "sg:city":"Point Lonsdale",
    "sg:classifiers":[
        {
            "category":"Home & Garden",
            "subcategory":"Building Materials",
            "type":"Retail Goods"
        }
    ],
    "sg:phone":"+61 3 5258 1417",
    "sg:postcode":"3225",
    "sg:province":"VIC",
    "sg:tags":[
        "lawn",
        "cutting",
        "maintenance"
    ],
    "wof:name":"Moonah Gardens",
    "wof:placetype":"venue"
},
  "geometry": {"coordinates":[144.61532600000001,-38.273033],"type":"Point"}
}