{
  "type": "Feature",
  "properties": {
    "iso:country":"AU",
    "sg:address":"569 Karrinyup Rd",
    "sg:city":"Stirling",
    "sg:classifiers":[
        {
            "category":"Health Services",
            "subcategory":"Chiropractor",
            "type":"Services"
        }
    ],
    "sg:phone":"+61 8 9446 8322",
    "sg:postcode":"6021",
    "sg:province":"WA",
    "wof:name":"Grant Brendan J",
    "wof:placetype":"venue"
},
  "geometry": {"coordinates":[115.809791565,-31.8861865997],"type":"Point"}
}