{
  "type": "Feature",
  "properties": {
    "addr:full":"31 Cummins St Rapid Creek NT 0810",
    "addr:housenumber":"31",
    "addr:postcode":"nt 0810",
    "addr:street":"Cummins St",
    "iso:country":"AU",
    "sg:address":"31 Cummins St",
    "sg:city":"Rapid Creek",
    "sg:classifiers":[
        {
            "category":"Education",
            "subcategory":"Kindergarten",
            "type":"Public Place"
        }
    ],
    "sg:phone":"+61 8 8985 3861",
    "sg:postcode":"0810",
    "sg:province":"NT",
    "sg:tags":[
        "pre-schools"
    ],
    "wof:name":"Essington Early Childhood Centre",
    "wof:placetype":"venue"
},
  "geometry": {"coordinates":[130.85894775400001,-12.3848953247],"type":"Point"}
}