{
  "type": "Feature",
  "properties": {
    "iso:country":"AU",
    "sg:address":"PO Box 24",
    "sg:city":"Euroa",
    "sg:classifiers":[
        {
            "category":"Building & Trades",
            "subcategory":"Construction",
            "type":"Services"
        }
    ],
    "sg:phone":"+61 409 384 074",
    "sg:postcode":"3666",
    "sg:province":"VIC",
    "sg:tags":[
        "earth",
        "excavating",
        "moving",
        "contractor"
    ],
    "wof:name":"North Eastern Trenching",
    "wof:placetype":"venue"
},
  "geometry": {"coordinates":[145.58433532699999,-36.7453804016],"type":"Point"}
}