{
  "type": "Feature",
  "properties": {
    "addr:full":"217 Evans St Penrith South NSW 2750",
    "addr:housenumber":"217",
    "addr:postcode":"2750",
    "addr:street":"Evans St",
    "iso:country":"AU",
    "sg:address":"217 Evans St",
    "sg:city":"Penrith South",
    "sg:classifiers":[
        {
            "category":"Education",
            "subcategory":"Kindergarten",
            "type":"Public Place"
        }
    ],
    "sg:phone":"+61 2 4732 3190",
    "sg:postcode":"2750",
    "sg:province":"NSW",
    "sg:tags":[
        "pre-schools"
    ],
    "wof:name":"Tandara Pre-School",
    "wof:placetype":"venue"
},
  "geometry": {"coordinates":[150.69786071799999,-33.7730293274],"type":"Point"}
}