{
  "type": "Feature",
  "properties": {
    "addr:full":"PO Box 484 Beerwah QLD 4519",
    "addr:postcode":"4519",
    "iso:country":"AU",
    "sg:address":"PO Box 484",
    "sg:city":"Beerwah",
    "sg:classifiers":[
        {
            "category":"Professional",
            "subcategory":"Accounting & Tax Preparation",
            "type":"Services"
        }
    ],
    "sg:phone":"+61 7 5494 9786",
    "sg:postcode":"4519",
    "sg:province":"QLD",
    "sg:tags":[
        "bookkeeping"
    ],
    "wof:name":"Fortune Bookkeeping",
    "wof:placetype":"venue"
},
  "geometry": {"coordinates":[152.95784,-26.85771],"type":"Point"}
}