{
  "type": "Feature",
  "properties": {
    "addr:full":"Lvl 1, 97a York St Launceston TAS 7250",
    "addr:postcode":"7250",
    "addr:street":"York St",
    "iso:country":"AU",
    "sg:address":"Lvl 1, 97a York St",
    "sg:city":"Launceston",
    "sg:classifiers":[
        {
            "category":"Education",
            "subcategory":"Junior College",
            "type":"Public Place"
        }
    ],
    "sg:phone":"+61 3 6331 4535",
    "sg:postcode":"7250",
    "sg:province":"TAS",
    "sg:tags":[
        "wholesaler",
        "school",
        "mfrs",
        "uniform"
    ],
    "wof:name":"Tasmanian Uniform Specialists",
    "wof:placetype":"venue"
},
  "geometry": {"coordinates":[147.139068603,-41.4391059875],"type":"Point"}
}