{
  "type": "Feature",
  "properties": {
    "addr:full":"Kelly Drv Busselton WA 6280",
    "addr:postcode":"6280",
    "addr:street":"Kelly Drv",
    "iso:country":"AU",
    "sg:address":"Kelly Drv",
    "sg:city":"Busselton",
    "sg:classifiers":[
        {
            "category":"Education",
            "subcategory":"School",
            "type":"Public Place"
        }
    ],
    "sg:phone":"+61 8 9752 1800",
    "sg:postcode":"6280",
    "sg:province":"WA",
    "wof:name":"St Joseph's School",
    "wof:placetype":"venue"
},
  "geometry": {"coordinates":[115.328430176,-33.6635437012],"type":"Point"}
}