{
  "type": "Feature",
  "properties": {
    "addr:full":"13 Moonah Rd Alfords Point NSW 2234",
    "addr:housenumber":"13",
    "addr:postcode":"2234",
    "addr:street":"Moonah Rd",
    "iso:country":"AU",
    "sg:address":"13 Moonah Rd",
    "sg:city":"Alfords Point",
    "sg:classifiers":[
        {
            "category":"Professional",
            "subcategory":"Management & Consulting",
            "type":"Services"
        }
    ],
    "sg:phone":"+61 2 9532 0418",
    "sg:postcode":"2234",
    "sg:province":"NSW",
    "sg:tags":[
        "consultant"
    ],
    "wof:name":"B Seth & Associates",
    "wof:placetype":"venue"
},
  "geometry": {"coordinates":[151.018676758,-33.9831581116],"type":"Point"}
}