{
  "type": "Feature",
  "properties": {
    "iso:country":"AU",
    "sg:address":"52A Willsmere Rd",
    "sg:city":"Kew",
    "sg:classifiers":[
        {
            "category":"Personal",
            "subcategory":"Beauty Salon",
            "type":"Services"
        }
    ],
    "sg:phone":"+61 3 9853 8959",
    "sg:postcode":"3101",
    "sg:province":"VIC",
    "sg:tags":[
        "hairdresser"
    ],
    "wof:name":"Lestat Hair",
    "wof:placetype":"venue"
},
  "geometry": {"coordinates":[145.03515625,-37.7966995239],"type":"Point"}
}