{
  "type": "Feature",
  "properties": {
    "addr:full":"359 Gympie Rd Kedron QLD 4031",
    "addr:housenumber":"359",
    "addr:postcode":"4031",
    "addr:street":"Gympie Rd",
    "iso:country":"AU",
    "sg:address":"359 Gympie Rd",
    "sg:city":"Kedron",
    "sg:classifiers":[
        {
            "category":"Professional",
            "subcategory":"Accounting & Tax Preparation",
            "type":"Services"
        }
    ],
    "sg:phone":"+61 7 3359 3377",
    "sg:postcode":"4031",
    "sg:province":"QLD",
    "sg:tags":[
        "accountant",
        "auditor"
    ],
    "wof:name":"Schoenmaker & Associates",
    "wof:placetype":"venue"
},
  "geometry": {"coordinates":[153.03211999999999,-27.404261],"type":"Point"}
}