{
  "type": "Feature",
  "properties": {
    "iso:country":"AU",
    "sg:address":"Shp4/ 69 Mitchell St",
    "sg:city":"Darwin",
    "sg:classifiers":[
        {
            "category":"Restaurant",
            "type":"Food & Drink"
        }
    ],
    "sg:phone":"+61 8 8942 2500",
    "sg:postcode":"0800",
    "sg:province":"NT",
    "wof:name":"Cafe Uno On Mitchell",
    "wof:placetype":"venue"
},
  "geometry": {"coordinates":[130.83895874000001,-12.4623985291],"type":"Point"}
}