{
  "type": "Feature",
  "properties": {
    "addr:full":"17 MacDonald St Killcare NSW 2257",
    "addr:housenumber":"17",
    "addr:postcode":"2257",
    "addr:street":"Macdonald St",
    "iso:country":"AU",
    "sg:address":"17 MacDonald St",
    "sg:city":"Killcare",
    "sg:classifiers":[
        {
            "category":"Professional",
            "subcategory":"Art Services",
            "type":"Services"
        }
    ],
    "sg:phone":"+61 2 4360 1625",
    "sg:postcode":"2257",
    "sg:province":"NSW",
    "sg:tags":[
        "decorator",
        "painter"
    ],
    "wof:name":"Mick Sloman",
    "wof:placetype":"venue"
},
  "geometry": {"coordinates":[151.37167358400001,-33.5241279602],"type":"Point"}
}