{
  "type": "Feature",
  "properties": {
    "addr:full":"2365 Point Nepean Rd Rye VIC 3941",
    "addr:housenumber":"2365",
    "addr:postcode":"3941",
    "addr:street":"Point Nepean Rd",
    "iso:country":"AU",
    "sg:address":"2365 Point Nepean Rd",
    "sg:city":"Rye",
    "sg:classifiers":[
        {
            "category":"Communications",
            "subcategory":"Film & Video Production",
            "type":"Services"
        }
    ],
    "sg:phone":"+61 3 5985 5017",
    "sg:postcode":"3941",
    "sg:province":"VIC",
    "sg:tags":[
        "dvd",
        "library"
    ],
    "wof:name":"Palm Video",
    "wof:placetype":"venue"
},
  "geometry": {"coordinates":[144.82313537600001,-38.3705024719],"type":"Point"}
}