{
  "type": "Feature",
  "properties": {
    "iso:country":"AU",
    "sg:address":"180 Fairfield Rd",
    "sg:city":"Fairfield",
    "sg:classifiers":[
        {
            "category":"Utilities",
            "subcategory":"Fuel Oil & Lpg",
            "type":"Services"
        }
    ],
    "sg:phone":"+61 7 3844 2195",
    "sg:postcode":"4103",
    "sg:province":"QLD",
    "sg:tags":[
        "merchant"
    ],
    "wof:name":"Independent Fuel Supplies",
    "wof:placetype":"venue"
},
  "geometry": {"coordinates":[153.02468872099999,-27.5088291168],"type":"Point"}
}