{
  "type": "Feature",
  "properties": {
    "addr:full":"318 Wilsons Rd Hodgson Vale QLD 4352",
    "addr:housenumber":"318",
    "addr:postcode":"4352",
    "addr:street":"Wilsons Rd",
    "iso:country":"AU",
    "sg:address":"318 Wilsons Rd",
    "sg:city":"Hodgson Vale",
    "sg:classifiers":[
        {
            "category":"Building & Trades",
            "subcategory":"Construction",
            "type":"Services"
        }
    ],
    "sg:phone":"+61 7 4630 9095",
    "sg:postcode":"4352",
    "sg:province":"QLD",
    "sg:tags":[
        "contractor"
    ],
    "wof:name":"Housen Constructions",
    "wof:placetype":"venue"
},
  "geometry": {"coordinates":[151.98895300000001,-27.684977],"type":"Point"}
}