{
  "type": "Feature",
  "properties": {
    "iso:country":"AU",
    "sg:address":"92 La Spezia Drv",
    "sg:city":"Secret Harbour",
    "sg:classifiers":[
        {
            "category":"Banks & Credit Unions",
            "subcategory":"Bank",
            "type":"Services"
        }
    ],
    "sg:phone":"+61 8 9524 8516",
    "sg:postcode":"6173",
    "sg:province":"WA",
    "sg:tags":[
        "broker",
        "mortgage"
    ],
    "wof:name":"Mortgage Gallery The",
    "wof:placetype":"venue"
},
  "geometry": {"coordinates":[115.75608800000001,-32.397198],"type":"Point"}
}