{
  "type": "Feature",
  "properties": {
    "addr:full":"18 Turner Pl Kelmscott WA 6111",
    "addr:housenumber":"18",
    "addr:postcode":"6111",
    "addr:street":"Turner Pl",
    "iso:country":"AU",
    "sg:address":"18 Turner Pl",
    "sg:city":"Kelmscott",
    "sg:classifiers":[
        {
            "category":"Home & Garden",
            "subcategory":"Hardware",
            "type":"Retail Goods"
        }
    ],
    "sg:phone":"+61 8 9495 1388",
    "sg:postcode":"6111",
    "sg:province":"WA",
    "sg:tags":[
        "product",
        "treatment",
        "floor"
    ],
    "wof:name":"Concrete Floor Sealing Systems WA",
    "wof:placetype":"venue"
},
  "geometry": {"coordinates":[116.01355743400001,-32.1079444885],"type":"Point"}
}