{
  "type": "Feature",
  "properties": {
    "addr:full":"8 Sunset Ave Olinda VIC 3788",
    "addr:housenumber":"8",
    "addr:postcode":"3788",
    "addr:street":"Sunset Ave",
    "iso:country":"AU",
    "sg:address":"8 Sunset Ave",
    "sg:city":"Olinda",
    "sg:classifiers":[
        {
            "category":"Food & Beverages",
            "subcategory":"Fruits & Vegetables",
            "type":"Retail Goods"
        }
    ],
    "sg:phone":"+61 3 9751 0525",
    "sg:postcode":"3788",
    "sg:province":"VIC",
    "sg:tags":[
        "greengrocer",
        "fruiterer"
    ],
    "wof:name":"Pellegrino's Fresh Fruits",
    "wof:placetype":"venue"
},
  "geometry": {"coordinates":[145.35983300000001,-37.848171],"type":"Point"}
}