{
  "type": "Feature",
  "properties": {
    "addr:full":"147 Gilston Rd Nerang QLD 4211",
    "addr:housenumber":"147",
    "addr:postcode":"4211",
    "addr:street":"Gilston Rd",
    "iso:country":"AU",
    "sg:address":"147 Gilston Rd",
    "sg:city":"Nerang",
    "sg:classifiers":[
        {
            "category":"Home & Garden",
            "subcategory":"Carpets & Floor Coverings",
            "type":"Retail Goods"
        }
    ],
    "sg:phone":"+61 7 5527 2799",
    "sg:postcode":"4211",
    "sg:province":"QLD",
    "sg:tags":[
        "tile",
        "wall",
        "layer"
    ],
    "wof:name":"Clarke Tiling",
    "wof:placetype":"venue"
},
  "geometry": {"coordinates":[153.33071899399999,-28.0019207001],"type":"Point"}
}