{
  "type": "Feature",
  "properties": {
    "addr:full":"214 Sussex St Sydney NSW 2000",
    "addr:housenumber":"214",
    "addr:postcode":"2000",
    "addr:street":"Sussex St",
    "iso:country":"AU",
    "sg:address":"214 Sussex St",
    "sg:city":"Sydney",
    "sg:classifiers":[
        {
            "category":"Personal",
            "subcategory":"Beauty Salon",
            "type":"Services"
        }
    ],
    "sg:phone":"+61 2 9211 4010",
    "sg:postcode":"2000",
    "sg:province":"NSW",
    "wof:name":"Real Beauty",
    "wof:placetype":"venue"
},
  "geometry": {"coordinates":[151.20413207999999,-33.8717308044],"type":"Point"}
}