{
  "type": "Feature",
  "properties": {
    "addr:full":"129 Smiths Hill St White Cliffs NSW 2836",
    "addr:housenumber":"129",
    "addr:postcode":"2836",
    "addr:street":"Smiths Hill St",
    "iso:country":"AU",
    "sg:address":"129 Smiths Hill St",
    "sg:city":"White Cliffs",
    "sg:classifiers":[
        {
            "category":"Travel",
            "subcategory":"Hotels & Motels",
            "type":"Entertainment"
        }
    ],
    "sg:phone":"+61 8 8091 6677",
    "sg:postcode":"2836",
    "sg:province":"NSW",
    "wof:name":"White Cliffs Underground Motel",
    "wof:placetype":"venue"
},
  "geometry": {"coordinates":[143.08067321799999,-30.8453903198],"type":"Point"}
}