{
  "type": "Feature",
  "properties": {
    "addr:full":"PO Box 398 Drummoyne NSW 1470",
    "addr:postcode":"1470",
    "iso:country":"AU",
    "sg:address":"PO Box 398",
    "sg:city":"Drummoyne",
    "sg:classifiers":[
        {
            "category":"Education",
            "subcategory":"Special Training",
            "type":"Public Place"
        }
    ],
    "sg:phone":"+61 1300 137 038",
    "sg:postcode":"1470",
    "sg:province":"NSW",
    "sg:tags":[
        "development"
    ],
    "wof:name":"Australian Centre For Corporate Advancement",
    "wof:placetype":"venue"
},
  "geometry": {"coordinates":[151.14894104000001,-33.8445739746],"type":"Point"}
}