{
  "type": "Feature",
  "properties": {
    "addr:full":"34 Wyndham St Roma QLD 4455",
    "addr:housenumber":"34",
    "addr:postcode":"4455",
    "addr:street":"Wyndham St",
    "iso:country":"AU",
    "sg:address":"34 Wyndham St",
    "sg:city":"Roma",
    "sg:classifiers":[
        {
            "category":"Shopping",
            "subcategory":"Luggage & Leather Goods",
            "type":"Retail Goods"
        }
    ],
    "sg:phone":"+61 7 4622 4004",
    "sg:postcode":"4455",
    "sg:province":"QLD",
    "wof:name":"Roma Saddlery",
    "wof:placetype":"venue"
},
  "geometry": {"coordinates":[148.79133605999999,-26.5702190399],"type":"Point"}
}