{
  "type": "Feature",
  "properties": {
    "addr:full":"498 Barrenjoey Rd Avalon NSW 2107",
    "addr:housenumber":"498",
    "addr:postcode":"2107",
    "addr:street":"Barrenjoey Rd",
    "iso:country":"AU",
    "sg:address":"498 Barrenjoey Rd",
    "sg:city":"Avalon",
    "sg:classifiers":[
        {
            "category":"Utilities",
            "subcategory":"Electric",
            "type":"Services"
        }
    ],
    "sg:phone":"+61 2 9973 1105",
    "sg:postcode":"2107",
    "sg:province":"NSW",
    "sg:tags":[
        "electrical",
        "contractor"
    ],
    "wof:name":"Illuminating Experience",
    "wof:placetype":"venue"
},
  "geometry": {"coordinates":[151.33151245100001,-33.6419906616],"type":"Point"}
}