{
  "type": "Feature",
  "properties": {
    "addr:full":"493 Mtt Alexander Rd Moonee Ponds VIC 3039",
    "addr:housenumber":"493",
    "addr:postcode":"3039",
    "addr:street":"Mtt Alexander Rd",
    "iso:country":"AU",
    "sg:address":"493 Mtt Alexander Rd",
    "sg:city":"Moonee Ponds",
    "sg:classifiers":[
        {
            "category":"Shopping",
            "subcategory":"Musical Instruments",
            "type":"Retail Goods"
        }
    ],
    "sg:phone":"+61 419 109 924",
    "sg:postcode":"3039",
    "sg:province":"VIC",
    "sg:tags":[
        "piano",
        "organ"
    ],
    "wof:name":"Darnum Musical Village",
    "wof:placetype":"venue"
},
  "geometry": {"coordinates":[144.92639199999999,-37.771748],"type":"Point"}
}