{
  "type": "Feature",
  "properties": {
    "iso:country":"AU",
    "sg:address":"Shop 6/ 3 Railway St",
    "sg:city":"Corrimal",
    "sg:classifiers":[
        {
            "category":"Food & Beverages",
            "subcategory":"Supermarket",
            "type":"Retail Goods"
        }
    ],
    "sg:phone":"+61 2 4284 5605",
    "sg:postcode":"2518",
    "sg:province":"NSW",
    "sg:tags":[
        "grocery",
        "store"
    ],
    "wof:name":"Prosperity General Trading Company",
    "wof:placetype":"venue"
},
  "geometry": {"coordinates":[150.90850800000001,-34.374771],"type":"Point"}
}