{
  "type": "Feature",
  "properties": {
    "iso:country":"AU",
    "sg:address":"Shop 35, Unley Shopping Centre 204 Unley Rd",
    "sg:city":"Unley",
    "sg:classifiers":[
        {
            "category":"Shopping",
            "subcategory":"Baby Store",
            "type":"Retail Goods"
        }
    ],
    "sg:phone":"+61 8 8271 9351",
    "sg:postcode":"5061",
    "sg:province":"SA",
    "sg:tags":[
        "children's",
        "wear"
    ],
    "wof:name":"Kids Shack The",
    "wof:placetype":"venue"
},
  "geometry": {"coordinates":[138.607330322,-34.9514045715],"type":"Point"}
}