{
  "type": "Feature",
  "properties": {
    "addr:full":"344 Unley Rd Hyde Park SA 5061",
    "addr:housenumber":"344",
    "addr:postcode":"5061",
    "addr:street":"Unley Rd",
    "iso:country":"AU",
    "sg:address":"344 Unley Rd",
    "sg:city":"Hyde Park",
    "sg:classifiers":[
        {
            "category":"Education",
            "subcategory":"Kindergarten",
            "type":"Public Place"
        }
    ],
    "sg:phone":"+61 8 8373 4599",
    "sg:postcode":"5061",
    "sg:province":"SA",
    "sg:tags":[
        "pre-schools"
    ],
    "wof:name":"Cedars Montessori Preschool The",
    "wof:placetype":"venue"
},
  "geometry": {"coordinates":[138.60797119099999,-34.9582748413],"type":"Point"}
}