{
  "type": "Feature",
  "properties": {
    "addr:full":"First Flr, Headland Business P 84 Wises Rd Maroochydore QLD 4558",
    "addr:housenumber":"84",
    "addr:postcode":"4558",
    "addr:street":"Wises Rd",
    "iso:country":"AU",
    "sg:address":"First Flr, Headland Business P 84 Wises Rd",
    "sg:city":"Maroochydore",
    "sg:classifiers":[
        {
            "category":"Professional",
            "subcategory":"Employment Agencies",
            "type":"Services"
        }
    ],
    "sg:phone":"+61 7 5475 9600",
    "sg:postcode":"4558",
    "sg:province":"QLD",
    "wof:name":"Manpower",
    "wof:placetype":"venue"
},
  "geometry": {"coordinates":[153.09762573200001,-26.6586055756],"type":"Point"}
}