{
  "type": "Feature",
  "properties": {
    "addr:full":"Upstairs 6 Barker St Griffith ACT 2603",
    "addr:housenumber":"6",
    "addr:postcode":"2603",
    "addr:street":"Barker St",
    "iso:country":"AU",
    "sg:address":"Upstairs 6 Barker St",
    "sg:city":"Griffith",
    "sg:classifiers":[
        {
            "category":"Health Services",
            "subcategory":"Health Practitioner",
            "type":"Services"
        }
    ],
    "sg:phone":"+61 2 6295 6939",
    "sg:postcode":"2603",
    "sg:province":"ACT",
    "sg:tags":[
        "naturopath"
    ],
    "wof:name":"Hierophant The",
    "wof:placetype":"venue"
},
  "geometry": {"coordinates":[149.14268493599999,-35.3282470703],"type":"Point"}
}