{
  "type": "Feature",
  "properties": {
    "addr:full":"1st Floor, 355 Sussex Street Sydney NSW 2000",
    "addr:housenumber":"355",
    "addr:postcode":"2000",
    "addr:street":"Sussex Street",
    "iso:country":"AU",
    "sg:address":"1st Floor, 355 Sussex Street",
    "sg:city":"Sydney",
    "sg:classifiers":[
        {
            "category":"Sports & Exercise",
            "subcategory":"Gym",
            "type":"Entertainment"
        }
    ],
    "sg:phone":"+61 2 9264 9947",
    "sg:postcode":"2000",
    "sg:province":"NSW",
    "sg:tags":[
        "health",
        "fitness"
    ],
    "wof:name":"Grand Master Jim Fungs Wing Chun Academy",
    "wof:placetype":"venue"
},
  "geometry": {"coordinates":[151.20440673799999,-33.8763656616],"type":"Point"}
}