{
  "type": "Feature",
  "properties": {
    "addr:full":"98 Lawes St East Maitland NSW 2323",
    "addr:housenumber":"98",
    "addr:postcode":"2323",
    "addr:street":"Lawes St",
    "iso:country":"AU",
    "sg:address":"98 Lawes St",
    "sg:city":"East Maitland",
    "sg:classifiers":[
        {
            "category":"Banks & Credit Unions",
            "subcategory":"Bank",
            "type":"Services"
        }
    ],
    "sg:phone":"+61 2 4933 7344",
    "sg:postcode":"2323",
    "sg:province":"NSW",
    "wof:name":"National Australia Bank Limited",
    "wof:placetype":"venue"
},
  "geometry": {"coordinates":[151.589767456,-32.7505989075],"type":"Point"}
}