{
  "type": "Feature",
  "properties": {
    "iso:country":"AU",
    "sg:address":"PO Box 685",
    "sg:city":"Kogarah",
    "sg:classifiers":[
        {
            "category":"Banks & Credit Unions",
            "subcategory":"Financial Services",
            "type":"Services"
        }
    ],
    "sg:phone":"+61 1300 782 264",
    "sg:postcode":"1485",
    "sg:province":"NSW",
    "sg:tags":[
        "financier"
    ],
    "wof:name":"Sydney Auto Hock",
    "wof:placetype":"venue"
},
  "geometry": {"coordinates":[151.13345336899999,-33.9631118774],"type":"Point"}
}