{
  "type": "Feature",
  "properties": {
    "addr:full":"Caplethorns Rd Langkoop VIC 3312",
    "addr:postcode":"3312",
    "addr:street":"Caplethorns Rd",
    "iso:country":"AU",
    "sg:address":"Caplethorns Rd",
    "sg:city":"Langkoop",
    "sg:classifiers":[
        {
            "category":"Building & Trades",
            "subcategory":"Landscaping Services",
            "type":"Services"
        }
    ],
    "sg:phone":"+61 3 5586 4283",
    "sg:postcode":"3312",
    "sg:province":"VIC",
    "sg:tags":[
        "grazier"
    ],
    "wof:name":"Mutooroo Pastoral Co Pty Ltd",
    "wof:placetype":"venue"
},
  "geometry": {"coordinates":[141.301223755,-37.4890708923],"type":"Point"}
}