{
  "type": "Feature",
  "properties": {
    "iso:country":"AU",
    "sg:address":"4 17 Raymond Ave",
    "sg:city":"Bayswater",
    "sg:classifiers":[
        {
            "category":"Professional",
            "subcategory":"Engineering",
            "type":"Services"
        }
    ],
    "sg:phone":"+61 8 9271 1401",
    "sg:postcode":"6053",
    "sg:province":"WA",
    "sg:tags":[
        "manufacturing",
        "engineer"
    ],
    "wof:name":"SAF Engineering Pty Ltd",
    "wof:placetype":"venue"
},
  "geometry": {"coordinates":[115.918067932,-31.9080886841],"type":"Point"}
}