{
  "type": "Feature",
  "properties": {
    "addr:full":"Suite 22 33 Southbank Blv Southbank VIC 3006",
    "addr:housenumber":"33",
    "addr:postcode":"3006",
    "addr:street":"Southbank Blv",
    "iso:country":"AU",
    "sg:address":"Suite 22 33 Southbank Blv",
    "sg:city":"Southbank",
    "sg:classifiers":[
        {
            "category":"Professional",
            "subcategory":"Accounting & Tax Preparation",
            "type":"Services"
        }
    ],
    "sg:phone":"+61 3 9645 7087",
    "sg:postcode":"3006",
    "sg:province":"VIC",
    "sg:tags":[
        "accountant",
        "auditor"
    ],
    "wof:name":"Ritzer Bernd W",
    "wof:placetype":"venue"
},
  "geometry": {"coordinates":[144.96397399899999,-37.8222503662],"type":"Point"}
}