{
  "type": "Feature",
  "properties": {
    "addr:full":"88 Fielding Rd Fernvale QLD 4306",
    "addr:housenumber":"88",
    "addr:postcode":"4306",
    "addr:street":"Fielding Rd",
    "iso:country":"AU",
    "sg:address":"88 Fielding Rd",
    "sg:city":"Fernvale",
    "sg:classifiers":[
        {
            "category":"Farming",
            "subcategory":"Nursery",
            "type":"Manufacturing & Wholesale Goods"
        }
    ],
    "sg:phone":"+61 7 5426 7127",
    "sg:postcode":"4306",
    "sg:province":"QLD",
    "wof:name":"Larsens Warm Climate Bulbs",
    "wof:placetype":"venue"
},
  "geometry": {"coordinates":[152.631225586,-27.448802948],"type":"Point"}
}