{
  "type": "Feature",
  "properties": {
    "addr:full":"Allenstown Plaza Upper Dawson Rd Rockhampton QLD 4700",
    "addr:postcode":"4700",
    "addr:street":"Upper Dawson Rd",
    "iso:country":"AU",
    "sg:address":"Allenstown Plaza Upper Dawson Rd",
    "sg:city":"Rockhampton",
    "sg:classifiers":[
        {
            "category":"Food & Beverages",
            "subcategory":"Supermarket",
            "type":"Retail Goods"
        }
    ],
    "sg:phone":"+61 7 4927 1511",
    "sg:postcode":"4700",
    "sg:province":"QLD",
    "sg:tags":[
        "grocery",
        "store"
    ],
    "wof:name":"Woolworths Limited",
    "wof:placetype":"venue"
},
  "geometry": {"coordinates":[150.499923706,-23.4071331024],"type":"Point"}
}