{
  "type": "Feature",
  "properties": {
    "addr:full":"Companies House 74- 76 Campbell St Sydney NSW 2000",
    "addr:housenumber":"74 76",
    "addr:postcode":"2000",
    "addr:street":"Campbell St",
    "iso:country":"AU",
    "sg:address":"Companies House 74- 76 Campbell St",
    "sg:city":"Sydney",
    "sg:classifiers":[
        {
            "category":"Banks & Credit Unions",
            "subcategory":"Atm",
            "type":"Services"
        }
    ],
    "sg:phone":"+61 1800 257 123",
    "sg:postcode":"2000",
    "sg:province":"NSW",
    "sg:tags":[
        "shelf"
    ],
    "wof:name":"Australian Formation Services Pty Ltd",
    "wof:placetype":"venue"
},
  "geometry": {"coordinates":[151.20976257300001,-33.8799438477],"type":"Point"}
}