{
  "type": "Feature",
  "properties": {
    "addr:full":"57 Winbourne Rd Brookvale NSW 2100",
    "addr:housenumber":"57",
    "addr:postcode":"2100",
    "addr:street":"Winbourne Rd",
    "iso:country":"AU",
    "sg:address":"57 Winbourne Rd",
    "sg:city":"Brookvale",
    "sg:classifiers":[
        {
            "category":"Home & Garden",
            "subcategory":"Carpets & Floor Coverings",
            "type":"Retail Goods"
        }
    ],
    "sg:phone":"+61 2 9938 2577",
    "sg:postcode":"2100",
    "sg:province":"NSW",
    "sg:tags":[
        "layer",
        "planner"
    ],
    "wof:name":"Monobond Aust Pty Ltd",
    "wof:placetype":"venue"
},
  "geometry": {"coordinates":[151.27520751899999,-33.7624702454],"type":"Point"}
}