{
  "type": "Feature",
  "properties": {
    "addr:full":"349 Victoria Rd Malaga WA 6090",
    "addr:housenumber":"349",
    "addr:postcode":"6090",
    "addr:street":"Victoria Rd",
    "iso:country":"AU",
    "sg:address":"349 Victoria Rd",
    "sg:city":"Malaga",
    "sg:classifiers":[
        {
            "category":"Home & Garden",
            "subcategory":"Hardware",
            "type":"Retail Goods"
        }
    ],
    "sg:phone":"+61 8 9249 3322",
    "sg:postcode":"6090",
    "sg:province":"WA",
    "sg:tags":[
        "plumber",
        "supply"
    ],
    "wof:name":"Regal Cement & Sales Pty Ltd",
    "wof:placetype":"venue"
},
  "geometry": {"coordinates":[115.89176940900001,-31.8614044189],"type":"Point"}
}