{
  "type": "Feature",
  "properties": {
    "iso:country":"AU",
    "sg:address":"6 Dellvale Crt",
    "sg:city":"Flagstaff Hill",
    "sg:classifiers":[
        {
            "category":"Professional",
            "subcategory":"Art Services",
            "type":"Services"
        }
    ],
    "sg:phone":"+61 8 8370 6733",
    "sg:postcode":"5159",
    "sg:province":"SA",
    "sg:tags":[
        "decorator",
        "painter"
    ],
    "wof:name":"A.A. Ashton Pty Ltd",
    "wof:placetype":"venue"
},
  "geometry": {"coordinates":[138.58857727,-35.065486908],"type":"Point"}
}