{
  "type": "Feature",
  "properties": {
    "addr:full":"136 Castlereagh St Sydney NSW 2000",
    "addr:housenumber":"136",
    "addr:postcode":"2000",
    "addr:street":"Castlereagh St",
    "iso:country":"AU",
    "sg:address":"136 Castlereagh St",
    "sg:city":"Sydney",
    "sg:classifiers":[
        {
            "category":"Banks & Credit Unions",
            "subcategory":"Bank",
            "type":"Services"
        }
    ],
    "sg:phone":"+61 2 8255 6580",
    "sg:postcode":"2000",
    "sg:province":"NSW",
    "wof:name":"Bank Of Queensland",
    "wof:placetype":"venue"
},
  "geometry": {"coordinates":[151.20953369099999,-33.8715629578],"type":"Point"}
}