{
  "type": "Feature",
  "properties": {
    "addr:full":"10 Ranfurley Rd Double Bay NSW 2028",
    "addr:housenumber":"10",
    "addr:postcode":"2028",
    "addr:street":"Ranfurley Rd",
    "iso:country":"AU",
    "sg:address":"10 Ranfurley Rd",
    "sg:city":"Double Bay",
    "sg:classifiers":[
        {
            "category":"Health Services",
            "subcategory":"Health Practitioner",
            "type":"Services"
        }
    ],
    "sg:phone":"+61 2 9328 2257",
    "sg:postcode":"2028",
    "sg:province":"NSW",
    "sg:tags":[
        "physiotherapist"
    ],
    "wof:name":"Felsher S Physiotherapy",
    "wof:placetype":"venue"
},
  "geometry": {"coordinates":[151.249069214,-33.884262085],"type":"Point"}
}