{
  "type": "Feature",
  "properties": {
    "addr:full":"47 Shoplands Rd Annangrove NSW 2156",
    "addr:housenumber":"47",
    "addr:postcode":"2156",
    "addr:street":"Shoplands Rd",
    "iso:country":"AU",
    "sg:address":"47 Shoplands Rd",
    "sg:city":"Annangrove",
    "sg:classifiers":[
        {
            "category":"Utilities",
            "subcategory":"Fuel Oil & Lpg",
            "type":"Services"
        }
    ],
    "sg:phone":"+61 2 9679 2488",
    "sg:postcode":"2156",
    "sg:province":"NSW",
    "sg:tags":[
        "combustion",
        "engineer"
    ],
    "wof:name":"Complete Combustion Services Pty Ltd",
    "wof:placetype":"venue"
},
  "geometry": {"coordinates":[150.93864440900001,-33.6414260864],"type":"Point"}
}