{
  "type": "Feature",
  "properties": {
    "addr:full":"Showground Shopping Centre, 157 Mulgrave Rd Westcourt QLD 4870",
    "addr:housenumber":"157",
    "addr:postcode":"4870",
    "addr:street":"Mulgrave Rd",
    "iso:country":"AU",
    "sg:address":"Showground Shopping Centre, 157 Mulgrave Rd",
    "sg:city":"Westcourt",
    "sg:classifiers":[
        {
            "category":"Shopping",
            "subcategory":"Party Supplies",
            "type":"Retail Goods"
        }
    ],
    "sg:phone":"+61 7 4051 0486",
    "sg:postcode":"4870",
    "sg:province":"QLD",
    "wof:name":"Confectionery & Party Shop The",
    "wof:placetype":"venue"
},
  "geometry": {"coordinates":[145.753738403,-16.9356613159],"type":"Point"}
}