{
  "type": "Feature",
  "properties": {
    "addr:full":"Doyle St Goodooga NSW 2831",
    "addr:postcode":"2831",
    "addr:street":"Doyle St",
    "iso:country":"AU",
    "sg:address":"Doyle St",
    "sg:city":"Goodooga",
    "sg:classifiers":[
        {
            "category":"Health Services",
            "subcategory":"Doctor",
            "type":"Services"
        }
    ],
    "sg:phone":"+61 2 6829 6268",
    "sg:postcode":"2831",
    "sg:province":"NSW",
    "sg:tags":[
        "medical",
        "practitioner"
    ],
    "wof:name":"Benjamin V A",
    "wof:placetype":"venue"
},
  "geometry": {"coordinates":[147.455200195,-29.1131839752],"type":"Point"}
}