{
  "type": "Feature",
  "properties": {
    "iso:country":"AU",
    "sg:address":"190 Jindy Andy La",
    "sg:city":"Numbaa",
    "sg:classifiers":[
        {
            "category":"Farming",
            "subcategory":"Farm",
            "type":"Manufacturing & Wholesale Goods"
        }
    ],
    "sg:phone":"+61 2 4447 1344",
    "sg:postcode":"2540",
    "sg:province":"NSW",
    "sg:tags":[
        "farmer"
    ],
    "wof:name":"L R Anderson & Sons",
    "wof:placetype":"venue"
},
  "geometry": {"coordinates":[150.67619323700001,-34.8847122192],"type":"Point"}
}