{
  "type": "Feature",
  "properties": {
    "iso:country":"AU",
    "sg:address":"South Town Walk, 40 Baylis Street",
    "sg:city":"Wagga Wagga",
    "sg:classifiers":[
        {
            "category":"Education",
            "subcategory":"Special Training",
            "type":"Public Place"
        }
    ],
    "sg:phone":"+61 2 6921 3468",
    "sg:postcode":"2650",
    "sg:province":"NSW",
    "sg:tags":[
        "tuition-educational"
    ],
    "wof:name":"Gateway Book Shop",
    "wof:placetype":"venue"
},
  "geometry": {"coordinates":[147.36924743599999,-35.1174545288],"type":"Point"}
}