{
  "type": "Feature",
  "properties": {
    "iso:country":"AU",
    "sg:address":"110 Malbon St",
    "sg:city":"Bungendore",
    "sg:classifiers":[
        {
            "category":"Building & Trades",
            "subcategory":"Construction",
            "type":"Services"
        }
    ],
    "sg:phone":"+61 2 6238 0113",
    "sg:postcode":"2621",
    "sg:province":"NSW",
    "sg:tags":[
        "earth",
        "excavating",
        "moving",
        "contractor"
    ],
    "wof:name":"JKM EXCAVATIONS",
    "wof:placetype":"venue"
},
  "geometry": {"coordinates":[149.44105529800001,-35.2563018799],"type":"Point"}
}