{
  "type": "Feature",
  "properties": {
    "iso:country":"AU",
    "sg:address":"Banksia Rd",
    "sg:city":"Stuarts Point",
    "sg:classifiers":[
        {
            "category":"Education",
            "subcategory":"School",
            "type":"Public Place"
        }
    ],
    "sg:phone":"+61 2 6569 0627",
    "sg:postcode":"2441",
    "sg:province":"NSW",
    "sg:tags":[
        "state",
        "-",
        "nsw"
    ],
    "wof:name":"Stuarts Point Public School",
    "wof:placetype":"venue"
},
  "geometry": {"coordinates":[152.99281300000001,-30.819849],"type":"Point"}
}