{
  "type": "Feature",
  "properties": {
    "addr:full":"3 William Pl St Kilda East VIC 3183",
    "addr:housenumber":"3",
    "addr:postcode":"3183",
    "addr:street":"William Pl",
    "iso:country":"AU",
    "sg:address":"3 William Pl",
    "sg:city":"St Kilda East",
    "sg:classifiers":[
        {
            "category":"Retail",
            "subcategory":"Event Space",
            "type":"Services"
        }
    ],
    "sg:phone":"+61 3 9527 6846",
    "sg:postcode":"3183",
    "sg:province":"VIC",
    "sg:tags":[
        "venue",
        "reception",
        "wedding"
    ],
    "wof:name":"A AAARed Scooter",
    "wof:placetype":"venue"
},
  "geometry": {"coordinates":[144.993896484,-37.8703956604],"type":"Point"}
}