{
  "type": "Feature",
  "properties": {
    "addr:full":"411 Hunsley Rd Kenilworth QLD 4574",
    "addr:housenumber":"411",
    "addr:postcode":"4574",
    "addr:street":"Hunsley Rd",
    "iso:country":"AU",
    "sg:address":"411 Hunsley Rd",
    "sg:city":"Kenilworth",
    "sg:classifiers":[
        {
            "category":"Utilities",
            "subcategory":"Electric",
            "type":"Services"
        }
    ],
    "sg:phone":"+61 7 5446 0367",
    "sg:postcode":"4574",
    "sg:province":"QLD",
    "sg:tags":[
        "electrical",
        "contractor"
    ],
    "wof:name":"Kupiak R J",
    "wof:placetype":"venue"
},
  "geometry": {"coordinates":[152.784775,-26.632919],"type":"Point"}
}