{
  "type": "Feature",
  "properties": {
    "iso:country":"AU",
    "sg:address":"52 Freda St",
    "sg:city":"Upper Mt Gravatt",
    "sg:classifiers":[
        {
            "category":"Building & Trades",
            "subcategory":"Equipment Rental",
            "type":"Services"
        }
    ],
    "sg:phone":"+61 1300 101 888",
    "sg:postcode":"4122",
    "sg:province":"QLD",
    "sg:tags":[
        "supply",
        "catering"
    ],
    "wof:name":"Santoshi India House",
    "wof:placetype":"venue"
},
  "geometry": {"coordinates":[153.08299255399999,-27.5583724976],"type":"Point"}
}