{
  "type": "Feature",
  "properties": {
    "iso:country":"AU",
    "sg:address":"6 Ailema Pl",
    "sg:city":"Kingston",
    "sg:classifiers":[
        {
            "category":"Professional",
            "subcategory":"Management & Consulting",
            "type":"Services"
        }
    ],
    "sg:phone":"+61 417 484 224",
    "sg:postcode":"7050",
    "sg:province":"TAS",
    "sg:tags":[
        "consultant"
    ],
    "wof:name":"M Worsley",
    "wof:placetype":"venue"
},
  "geometry": {"coordinates":[147.301346,-42.968266],"type":"Point"}
}