{
  "type": "Feature",
  "properties": {
    "addr:full":"181 Phillip Hwy Elizabeth SA 5112",
    "addr:housenumber":"181",
    "addr:postcode":"5112",
    "addr:street":"Phillip Hwy",
    "iso:country":"AU",
    "sg:address":"181 Phillip Hwy",
    "sg:city":"Elizabeth",
    "sg:classifiers":[
        {
            "category":"Building & Trades",
            "subcategory":"Construction",
            "type":"Services"
        }
    ],
    "sg:phone":"+61 8 8287 6489",
    "sg:postcode":"5112",
    "sg:province":"SA",
    "sg:tags":[
        "welding"
    ],
    "wof:name":"Williams Metal Fabrication Pty Ltd",
    "wof:placetype":"venue"
},
  "geometry": {"coordinates":[138.66311645499999,-34.731590271],"type":"Point"}
}