{
  "type": "Feature",
  "properties": {
    "iso:country":"AU",
    "sg:address":"Cnr Marmian & Warburton Aves",
    "sg:city":"Padbury",
    "sg:classifiers":[
        {
            "category":"Retail",
            "subcategory":"Auto Repair",
            "type":"Services"
        }
    ],
    "sg:phone":"+61 8 9401 3765",
    "sg:postcode":"6025",
    "sg:province":"WA",
    "sg:tags":[
        "repairer",
        "motor",
        "engineer"
    ],
    "wof:name":"BP Padbury Auto Care",
    "wof:placetype":"venue"
},
  "geometry": {"coordinates":[115.758827209,-31.8136825562],"type":"Point"}
}