{
  "type": "Feature",
  "properties": {
    "addr:full":"1208 Lytton Rd Hemmant QLD 4174",
    "addr:housenumber":"1208",
    "addr:postcode":"4174",
    "addr:street":"Lytton Rd",
    "iso:country":"AU",
    "sg:address":"1208 Lytton Rd",
    "sg:city":"Hemmant",
    "sg:classifiers":[
        {
            "category":"Fast Food",
            "type":"Food & Drink"
        }
    ],
    "sg:phone":"+61 7 3390 7097",
    "sg:postcode":"4174",
    "sg:province":"QLD",
    "sg:tags":[
        "away",
        "take"
    ],
    "wof:name":"Roadside Snacks",
    "wof:placetype":"venue"
},
  "geometry": {"coordinates":[153.11911010700001,-27.4443588257],"type":"Point"}
}