{
  "type": "Feature",
  "properties": {
    "addr:full":"Fact 2, 11 Laser Drv Rowville VIC 3178",
    "addr:housenumber":"2 11",
    "addr:postcode":"3178",
    "addr:street":"Fact;Laser Drv",
    "iso:country":"AU",
    "sg:address":"Fact 2, 11 Laser Drv",
    "sg:city":"Rowville",
    "sg:classifiers":[
        {
            "category":"Wholesale",
            "subcategory":"Machinery & Supplies",
            "type":"Manufacturing & Wholesale Goods"
        }
    ],
    "sg:phone":"+61 3 9764 9222",
    "sg:postcode":"3178",
    "sg:province":"VIC",
    "sg:tags":[
        "equipment",
        "welding"
    ],
    "wof:name":"Victorian Welding Supplies",
    "wof:placetype":"venue"
},
  "geometry": {"coordinates":[145.24412536599999,-37.911151886],"type":"Point"}
}