{
  "type": "Feature",
  "properties": {
    "iso:country":"AU",
    "sg:address":"124 Welshpool Rd",
    "sg:city":"Welshpool",
    "sg:classifiers":[
        {
            "category":"Building & Trades",
            "subcategory":"Equipment Rental",
            "type":"Services"
        }
    ],
    "sg:phone":"+61 8 9490 5556",
    "sg:postcode":"6106",
    "sg:province":"WA",
    "sg:tags":[
        "party",
        "hire"
    ],
    "wof:name":"ABC Amusements",
    "wof:placetype":"venue"
},
  "geometry": {"coordinates":[115.931472778,-31.9948253632],"type":"Point"}
}