{
  "type": "Feature",
  "properties": {
    "addr:full":"Golf Ave Mollymook NSW 2539",
    "addr:postcode":"2539",
    "addr:street":"Golf;Mollymook",
    "iso:country":"AU",
    "sg:address":"Golf Ave",
    "sg:city":"Mollymook",
    "sg:classifiers":[
        {
            "category":"Sports & Exercise",
            "subcategory":"Golf",
            "type":"Entertainment"
        }
    ],
    "sg:phone":"+61 2 4455 1911",
    "sg:postcode":"2539",
    "sg:province":"NSW",
    "sg:tags":[
        "club"
    ],
    "wof:name":"Mollymook Golf Club Ltd",
    "wof:placetype":"venue"
},
  "geometry": {"coordinates":[150.47383117699999,-35.3413238525],"type":"Point"}
}