{
  "type": "Feature",
  "properties": {
    "addr:full":"PO Box 515 Avalon NSW 2107",
    "addr:postcode":"2107",
    "iso:country":"AU",
    "sg:address":"PO Box 515",
    "sg:city":"Avalon",
    "sg:classifiers":[
        {
            "category":"Professional",
            "subcategory":"Art Services",
            "type":"Services"
        }
    ],
    "sg:phone":"+61 418 479 717",
    "sg:postcode":"2107",
    "sg:province":"NSW",
    "sg:tags":[
        "arranger",
        "music",
        "composer"
    ],
    "wof:name":"Frost Garry",
    "wof:placetype":"venue"
},
  "geometry": {"coordinates":[151.33171081500001,-33.6286201477],"type":"Point"}
}