{
  "type": "Feature",
  "properties": {
    "iso:country":"AU",
    "sg:address":"113 Kambalda Crs",
    "sg:city":"Fisher",
    "sg:classifiers":[
        {
            "category":"Personal",
            "subcategory":"Beauty Salon",
            "type":"Services"
        }
    ],
    "sg:phone":"+61 2 6287 5957",
    "sg:postcode":"2611",
    "sg:province":"ACT",
    "wof:name":"Rosi Barkemeyer",
    "wof:placetype":"venue"
},
  "geometry": {"coordinates":[149.05584716800001,-35.3615684509],"type":"Point"}
}