{
  "type": "Feature",
  "properties": {
    "addr:full":"Barcom St Merrylands NSW 2160",
    "addr:postcode":"2160",
    "addr:street":"St",
    "iso:country":"AU",
    "sg:address":"Barcom St",
    "sg:city":"Merrylands",
    "sg:classifiers":[
        {
            "category":"Social Services",
            "subcategory":"Retirement Home",
            "type":"Services"
        }
    ],
    "sg:phone":"+61 2 9632 3144",
    "sg:postcode":"2160",
    "sg:province":"NSW",
    "sg:tags":[
        "village"
    ],
    "wof:name":"Cardinal Gilroy Village",
    "wof:placetype":"venue"
},
  "geometry": {"coordinates":[150.97445678700001,-33.8395042419],"type":"Point"}
}