{
  "type": "Feature",
  "properties": {
    "addr:full":"97 Upton St Bundall QLD 4217",
    "addr:housenumber":"97",
    "addr:postcode":"4217",
    "addr:street":"Upton St",
    "iso:country":"AU",
    "sg:address":"97 Upton St",
    "sg:city":"Bundall",
    "sg:classifiers":[
        {
            "category":"Professional",
            "subcategory":"Computer Services",
            "type":"Services"
        }
    ],
    "sg:phone":"+61 7 5574 0616",
    "sg:postcode":"4217",
    "sg:province":"QLD",
    "sg:tags":[
        "consultant",
        "system"
    ],
    "wof:name":"Apprima Computer Service",
    "wof:placetype":"venue"
},
  "geometry": {"coordinates":[153.411865234,-28.0013542175],"type":"Point"}
}