{
  "type": "Feature",
  "properties": {
    "iso:country":"AU",
    "sg:address":"187 Days Rd",
    "sg:city":"Grange",
    "sg:classifiers":[
        {
            "category":"Organizations",
            "subcategory":"Membership Organization",
            "type":"Services"
        }
    ],
    "sg:phone":"+61 7 3356 3325",
    "sg:postcode":"4051",
    "sg:province":"QLD",
    "sg:tags":[
        "support",
        "health",
        "organisation"
    ],
    "wof:name":"Diabetic Care Centre",
    "wof:placetype":"venue"
},
  "geometry": {"coordinates":[153.01475524899999,-27.4258365631],"type":"Point"}
}