{
  "type": "Feature",
  "properties": {
    "addr:full":"Unit 5, 13 Rocla Crt Wilsonton QLD 4350",
    "addr:housenumber":"13",
    "addr:postcode":"4350",
    "addr:street":"Rocla Crt",
    "iso:country":"AU",
    "sg:address":"Unit 5, 13 Rocla Crt",
    "sg:city":"Wilsonton",
    "sg:classifiers":[
        {
            "category":"Professional",
            "type":"Services"
        }
    ],
    "sg:phone":"+61 7 4633 5079",
    "sg:postcode":"4350",
    "sg:province":"QLD",
    "sg:tags":[
        "spray",
        "painting"
    ],
    "wof:name":"D & K Elliott",
    "wof:placetype":"venue"
},
  "geometry": {"coordinates":[151.91021699999999,-27.553934],"type":"Point"}
}