{
  "type": "Feature",
  "properties": {
    "addr:full":"Wells House 35 Hay St Subiaco WA 6008",
    "addr:housenumber":"35",
    "addr:postcode":"6008",
    "addr:street":"Hay St",
    "iso:country":"AU",
    "sg:address":"Wells House 35 Hay St",
    "sg:city":"Subiaco",
    "sg:classifiers":[
        {
            "category":"Real Estate",
            "subcategory":"Real Estate Agent",
            "type":"Services"
        }
    ],
    "sg:phone":"+61 8 9380 4111",
    "sg:postcode":"6008",
    "sg:province":"WA",
    "wof:name":"Perth Commercial Realty",
    "wof:placetype":"venue"
},
  "geometry": {"coordinates":[115.83641815199999,-31.9472312927],"type":"Point"}
}