{
  "type": "Feature",
  "properties": {
    "addr:full":"32 Telopea St Redfern NSW 2016",
    "addr:housenumber":"32",
    "addr:postcode":"2016",
    "addr:street":"Telopea St",
    "iso:country":"AU",
    "sg:address":"32 Telopea St",
    "sg:city":"Redfern",
    "sg:classifiers":[
        {
            "category":"Utilities",
            "subcategory":"Water",
            "type":"Services"
        }
    ],
    "sg:phone":"+61 2 9337 1009",
    "sg:postcode":"2016",
    "sg:province":"NSW",
    "sg:tags":[
        "hot",
        "system"
    ],
    "wof:name":"Best Hot Water Services",
    "wof:placetype":"venue"
},
  "geometry": {"coordinates":[151.212356567,-33.8942909241],"type":"Point"}
}