{
  "type": "Feature",
  "properties": {
    "addr:full":"27 Ben Nevis St Beaconsfield QLD 4740",
    "addr:housenumber":"27",
    "addr:postcode":"4740",
    "addr:street":"Ben Nevis St",
    "iso:country":"AU",
    "sg:address":"27 Ben Nevis St",
    "sg:city":"Beaconsfield",
    "sg:classifiers":[
        {
            "category":"Real Estate",
            "subcategory":"Real Estate Services",
            "type":"Services"
        }
    ],
    "sg:phone":"+61 7 4955 1633",
    "sg:postcode":"4740",
    "sg:province":"QLD",
    "sg:tags":[
        "valuer"
    ],
    "wof:name":"Cronin & Associates",
    "wof:placetype":"venue"
},
  "geometry": {"coordinates":[149.171753,-21.08596],"type":"Point"}
}