{
  "type": "Feature",
  "properties": {
    "iso:country":"AU",
    "sg:address":"14- 28 Montague St",
    "sg:city":"South Melbourne",
    "sg:classifiers":[
        {
            "category":"Wholesale",
            "subcategory":"Apparel",
            "type":"Manufacturing & Wholesale Goods"
        }
    ],
    "sg:phone":"+61 3 9646 8755",
    "sg:postcode":"3205",
    "sg:province":"VIC",
    "sg:tags":[
        "wholesaler",
        "mfrs",
        "menswear"
    ],
    "wof:name":"R J N Australia Pty Ltd",
    "wof:placetype":"venue"
},
  "geometry": {"coordinates":[144.94721999999999,-37.827877],"type":"Point"}
}