{
  "type": "Feature",
  "properties": {
    "iso:country":"AU",
    "sg:address":"333 Mulwaree Drv",
    "sg:city":"Tallong",
    "sg:classifiers":[
        {
            "category":"Retail",
            "subcategory":"Car Wash",
            "type":"Services"
        }
    ],
    "sg:phone":"+61 414 891 601",
    "sg:postcode":"2579",
    "sg:province":"NSW",
    "sg:tags":[
        "truck",
        "cleaning"
    ],
    "wof:name":"D&H Mobile Car Detailing",
    "wof:placetype":"venue"
},
  "geometry": {"coordinates":[150.10017395,-34.6994972229],"type":"Point"}
}