{
  "type": "Feature",
  "properties": {
    "iso:country":"AU",
    "sg:address":"30 Kensington Rd",
    "sg:city":"Rose Park",
    "sg:classifiers":[
        {
            "category":"Health Services",
            "subcategory":"Health Practitioner",
            "type":"Services"
        }
    ],
    "sg:phone":"+61 8 8333 0940",
    "sg:postcode":"5067",
    "sg:province":"SA",
    "sg:tags":[
        "psychologist"
    ],
    "wof:name":"Chataway Joan",
    "wof:placetype":"venue"
},
  "geometry": {"coordinates":[138.62608337399999,-34.9276275635],"type":"Point"}
}