{
  "type": "Feature",
  "properties": {
    "iso:country":"AU",
    "sg:address":"Lot 31 Tuberosa Rd",
    "sg:city":"Armidale",
    "sg:classifiers":[
        {
            "category":"Building & Trades",
            "subcategory":"Plumbing",
            "type":"Services"
        }
    ],
    "sg:phone":"+61 2 6775 3168",
    "sg:postcode":"2350",
    "sg:province":"NSW",
    "sg:tags":[
        "plumber",
        "gasfitters"
    ],
    "wof:name":"RMX Plumbing",
    "wof:placetype":"venue"
},
  "geometry": {"coordinates":[151.58290100100001,-30.5614204407],"type":"Point"}
}