{
  "type": "Feature",
  "properties": {
    "addr:full":"15a Randor St Campbellfield VIC 3061",
    "addr:housenumber":"15a",
    "addr:postcode":"3061",
    "addr:street":"Randor St",
    "iso:country":"AU",
    "sg:address":"15a Randor St",
    "sg:city":"Campbellfield",
    "sg:classifiers":[
        {
            "category":"Building & Trades",
            "subcategory":"Plumbing",
            "type":"Services"
        }
    ],
    "sg:phone":"+61 3 9357 6555",
    "sg:postcode":"3061",
    "sg:province":"VIC",
    "sg:tags":[
        "equipment",
        "valves"
    ],
    "wof:name":"Valflo Australia",
    "wof:placetype":"venue"
},
  "geometry": {"coordinates":[144.9659729,-37.665435791],"type":"Point"}
}