{
  "type": "Feature",
  "properties": {
    "addr:full":"414 Milne Rd Redwood Park SA 5097",
    "addr:housenumber":"414",
    "addr:postcode":"5097",
    "addr:street":"Milne Rd",
    "iso:country":"AU",
    "sg:address":"414 Milne Rd",
    "sg:city":"Redwood Park",
    "sg:classifiers":[
        {
            "category":"Food & Beverages",
            "subcategory":"Supermarket",
            "type":"Retail Goods"
        }
    ],
    "sg:phone":"+61 8 8263 6500",
    "sg:postcode":"5097",
    "sg:province":"SA",
    "sg:tags":[
        "grocery",
        "store"
    ],
    "wof:name":"IGA Food Stores",
    "wof:placetype":"venue"
},
  "geometry": {"coordinates":[138.705612183,-34.8167686462],"type":"Point"}
}