{
  "type": "Feature",
  "properties": {
    "iso:country":"AU",
    "sg:address":"Arnhem Hwy",
    "sg:city":"Humpty Doo",
    "sg:classifiers":[
        {
            "category":"Government",
            "subcategory":"Post Office",
            "type":"Public Place"
        }
    ],
    "sg:phone":"+61 8 8988 1047",
    "sg:postcode":"0836",
    "sg:province":"NT",
    "sg:tags":[
        "postal"
    ],
    "wof:name":"Australia Post",
    "wof:placetype":"venue"
},
  "geometry": {"coordinates":[131.109894,-12.57359],"type":"Point"}
}