{
  "type": "Feature",
  "properties": {
    "addr:full":"179 Jensen St Edge Hill QLD 4870",
    "addr:housenumber":"179",
    "addr:postcode":"4870",
    "addr:street":"Jensen St",
    "iso:country":"AU",
    "sg:address":"179 Jensen St",
    "sg:city":"Edge Hill",
    "sg:classifiers":[
        {
            "category":"Health Services",
            "subcategory":"Health Practitioner",
            "type":"Services"
        }
    ],
    "sg:phone":"+61 7 4053 6222",
    "sg:postcode":"4870",
    "sg:province":"QLD",
    "sg:tags":[
        "physiotherapist"
    ],
    "wof:name":"Julie Smith",
    "wof:placetype":"venue"
},
  "geometry": {"coordinates":[145.73449707,-16.8980445862],"type":"Point"}
}