{
  "type": "Feature",
  "properties": {
    "iso:country":"AU",
    "sg:address":"46 Hector St",
    "sg:city":"Osborne Park",
    "sg:classifiers":[
        {
            "category":"Home & Garden",
            "subcategory":"Carpets & Floor Coverings",
            "type":"Retail Goods"
        }
    ],
    "sg:phone":"+61 8 9446 6000",
    "sg:postcode":"6017",
    "sg:province":"WA",
    "sg:tags":[
        "tile",
        "wall"
    ],
    "sg:website":"http://www.crosbytiles.com.au",
    "wof:name":"Crosby Tiles",
    "wof:placetype":"venue"
},
  "geometry": {"coordinates":[115.822570801,-31.9043045044],"type":"Point"}
}