{
  "type": "Feature",
  "properties": {
    "addr:full":"83 Railway St Corrimal NSW 2518",
    "addr:housenumber":"83",
    "addr:postcode":"2518",
    "addr:street":"Railway St",
    "iso:country":"AU",
    "sg:address":"83 Railway St",
    "sg:city":"Corrimal",
    "sg:classifiers":[
        {
            "category":"Manufacturing",
            "subcategory":"Jewelry",
            "type":"Manufacturing & Wholesale Goods"
        }
    ],
    "sg:phone":"+61 2 4284 7412",
    "sg:postcode":"2518",
    "sg:province":"NSW",
    "sg:tags":[
        "mfrg",
        "jeweller"
    ],
    "wof:name":"Camaruti & Co",
    "wof:placetype":"venue"
},
  "geometry": {"coordinates":[150.89999399999999,-34.373348],"type":"Point"}
}