{
  "type": "Feature",
  "properties": {
    "addr:full":"305 Old Warburton Rd Woori Yallock VIC 3139",
    "addr:housenumber":"305",
    "addr:postcode":"3139",
    "addr:street":"Old Warburton Rd",
    "iso:country":"AU",
    "sg:address":"305 Old Warburton Rd",
    "sg:city":"Woori Yallock",
    "sg:classifiers":[
        {
            "category":"Travel",
            "subcategory":"Hotels & Motels",
            "type":"Entertainment"
        }
    ],
    "sg:phone":"+61 3 5964 7201",
    "sg:postcode":"3139",
    "sg:province":"VIC",
    "sg:tags":[
        "accommodation"
    ],
    "wof:name":"Woori Yallock Hotel",
    "wof:placetype":"venue"
},
  "geometry": {"coordinates":[145.46270751899999,-37.771812439],"type":"Point"}
}