{
  "type": "Feature",
  "properties": {
    "iso:country":"AU",
    "sg:address":"2 Birdwood Ave",
    "sg:city":"Moonah",
    "sg:classifiers":[
        {
            "category":"Health Services",
            "subcategory":"Doctor",
            "type":"Services"
        }
    ],
    "sg:phone":"+61 3 6273 3000",
    "sg:postcode":"7009",
    "sg:province":"TAS",
    "sg:tags":[
        "nurse",
        "nursing"
    ],
    "wof:name":"The District Nurses",
    "wof:placetype":"venue"
},
  "geometry": {"coordinates":[147.292434692,-42.8428344727],"type":"Point"}
}