{
  "type": "Feature",
  "properties": {
    "iso:country":"AU",
    "sg:address":"33B Briggs Rd",
    "sg:city":"Raceview",
    "sg:classifiers":[
        {
            "category":"Building & Trades",
            "subcategory":"Landscaping Services",
            "type":"Services"
        }
    ],
    "sg:phone":"+61 7 3281 1640",
    "sg:postcode":"4305",
    "sg:province":"QLD",
    "sg:tags":[
        "designer",
        "landscape",
        "contractor"
    ],
    "wof:name":"Raceview Sand & Gravel",
    "wof:placetype":"venue"
},
  "geometry": {"coordinates":[152.763504028,-27.6349716187],"type":"Point"}
}