{
  "type": "Feature",
  "properties": {
    "iso:country":"AU",
    "sg:address":"206 Adelaide St",
    "sg:city":"Brisbane",
    "sg:classifiers":[
        {
            "category":"Shopping",
            "subcategory":"Jewelry",
            "type":"Retail Goods"
        }
    ],
    "sg:phone":"+61 7 3221 7516",
    "sg:postcode":"4000",
    "sg:province":"QLD",
    "sg:tags":[
        "jeweller"
    ],
    "wof:name":"Penfold Jewellers",
    "wof:placetype":"venue"
},
  "geometry": {"coordinates":[153.02745056099999,-27.4663658142],"type":"Point"}
}