{
  "type": "Feature",
  "properties": {
    "addr:full":"10 Renda Crt Narre Warren North VIC 3804",
    "addr:housenumber":"10",
    "addr:postcode":"3804",
    "addr:street":"Renda Crt",
    "iso:country":"AU",
    "sg:address":"10 Renda Crt",
    "sg:city":"Narre Warren North",
    "sg:classifiers":[
        {
            "category":"Building & Trades",
            "subcategory":"Construction",
            "type":"Services"
        }
    ],
    "sg:phone":"+61 3 9796 9663",
    "sg:postcode":"3804",
    "sg:province":"VIC",
    "sg:tags":[
        "concrete",
        "contractor"
    ],
    "wof:name":"N & F Concreting",
    "wof:placetype":"venue"
},
  "geometry": {"coordinates":[145.31585693400001,-37.9968948364],"type":"Point"}
}