{
  "type": "Feature",
  "properties": {
    "iso:country":"AU",
    "sg:address":"Jamison Rd",
    "sg:city":"Penrith",
    "sg:classifiers":[
        {
            "category":"Professional",
            "subcategory":"Accounting & Tax Preparation",
            "type":"Services"
        }
    ],
    "sg:phone":"+61 2 4727 1325",
    "sg:postcode":"2750",
    "sg:province":"NSW",
    "sg:tags":[
        "bookkeeping"
    ],
    "wof:name":"CAS Secretarial & Bookkeeping Services",
    "wof:placetype":"venue"
},
  "geometry": {"coordinates":[150.676345825,-33.7596931458],"type":"Point"}
}