{
  "type": "Feature",
  "properties": {
    "iso:country":"AU",
    "sg:address":"464 Napier St",
    "sg:city":"White Hills",
    "sg:classifiers":[
        {
            "category":"Home & Garden",
            "subcategory":"Furniture",
            "type":"Retail Goods"
        }
    ],
    "sg:phone":"+61 3 5442 2282",
    "sg:postcode":"3550",
    "sg:province":"VIC",
    "sg:tags":[
        "repair",
        "restoration"
    ],
    "wof:name":"Sandhurst Upholstery",
    "wof:placetype":"venue"
},
  "geometry": {"coordinates":[144.30337524399999,-36.733631134],"type":"Point"}
}