{
  "type": "Feature",
  "properties": {
    "addr:full":"44 Nicholson St Fitzroy VIC 3065",
    "addr:housenumber":"44",
    "addr:postcode":"3065",
    "addr:street":"Nicholson St",
    "iso:country":"AU",
    "sg:address":"44 Nicholson St",
    "sg:city":"Fitzroy",
    "sg:classifiers":[
        {
            "category":"Manufacturing",
            "subcategory":"Food",
            "type":"Manufacturing & Wholesale Goods"
        }
    ],
    "sg:phone":"+61 3 9417 4542",
    "sg:postcode":"3065",
    "sg:province":"VIC",
    "sg:tags":[
        "function",
        "catering"
    ],
    "sg:website":"http://www.catering-co.com.au",
    "wof:name":"The Catering Company",
    "wof:placetype":"venue"
},
  "geometry": {"coordinates":[144.97381591800001,-37.8057518005],"type":"Point"}
}