{
  "type": "Feature",
  "properties": {
    "iso:country":"AU",
    "sg:address":"1173 Kingsford Smith Drv",
    "sg:city":"Pinkenba",
    "sg:classifiers":[
        {
            "category":"Food & Beverages",
            "subcategory":"Fruits & Vegetables",
            "type":"Retail Goods"
        }
    ],
    "sg:phone":"+61 7 3260 2000",
    "sg:postcode":"4008",
    "sg:province":"QLD",
    "sg:tags":[
        "wholesale"
    ],
    "wof:name":"Gambaros Wholesale Seafood",
    "wof:placetype":"venue"
},
  "geometry": {"coordinates":[153.10426330600001,-27.4294757843],"type":"Point"}
}