{
  "type": "Feature",
  "properties": {
    "iso:country":"AU",
    "sg:address":"15/ 151 Hartley Rd",
    "sg:city":"Smeaton Grange",
    "sg:classifiers":[
        {
            "category":"Utilities",
            "subcategory":"Telephone",
            "type":"Services"
        }
    ],
    "sg:phone":"+61 2 4647 6653",
    "sg:postcode":"2567",
    "sg:province":"NSW",
    "sg:tags":[
        "installation",
        "system",
        "maintenance"
    ],
    "sg:website":"http://www.gmcable.com.au",
    "wof:name":"GM Cabling Solutions",
    "wof:placetype":"venue"
},
  "geometry": {"coordinates":[150.75637817399999,-34.0390548706],"type":"Point"}
}