{
  "type": "Feature",
  "properties": {
    "addr:full":"223 Canterbury Rd Canterbury VIC 3126",
    "addr:housenumber":"223",
    "addr:postcode":"3126",
    "addr:street":"Canterbury Rd",
    "iso:country":"AU",
    "sg:address":"223 Canterbury Rd",
    "sg:city":"Canterbury",
    "sg:classifiers":[
        {
            "category":"Sports & Exercise",
            "subcategory":"Gym",
            "type":"Entertainment"
        }
    ],
    "sg:phone":"+61 3 9880 7022",
    "sg:postcode":"3126",
    "sg:province":"VIC",
    "sg:tags":[
        "personal",
        "trainer",
        "fitness"
    ],
    "wof:name":"New Level Personal Training",
    "wof:placetype":"venue"
},
  "geometry": {"coordinates":[145.08091735799999,-37.823841095],"type":"Point"}
}