{
  "type": "Feature",
  "properties": {
    "addr:full":"Radke Rd Bethania QLD 4205",
    "addr:postcode":"4205",
    "addr:street":"Radke Rd",
    "iso:country":"AU",
    "sg:address":"Radke Rd",
    "sg:city":"Bethania",
    "sg:classifiers":[
        {
            "category":"Farming",
            "subcategory":"Livestock Farm",
            "type":"Manufacturing & Wholesale Goods"
        }
    ],
    "sg:phone":"+61 7 3299 7328",
    "sg:postcode":"4205",
    "sg:province":"QLD",
    "sg:tags":[
        "breeder",
        "horse",
        "stud"
    ],
    "wof:name":"Chazar Equine Services",
    "wof:placetype":"venue"
},
  "geometry": {"coordinates":[153.15614318900001,-27.6833343506],"type":"Point"}
}