{
  "type": "Feature",
  "properties": {
    "iso:country":"AU",
    "sg:address":"13 Ivanhoe Crt",
    "sg:city":"Thomastown",
    "sg:classifiers":[
        {
            "category":"Building & Trades",
            "subcategory":"Construction",
            "type":"Services"
        }
    ],
    "sg:phone":"+61 411 110 629",
    "sg:postcode":"3074",
    "sg:province":"VIC",
    "sg:tags":[
        "concrete",
        "contractor"
    ],
    "wof:name":"Home Grind",
    "wof:placetype":"venue"
},
  "geometry": {"coordinates":[145.02702331500001,-37.6853141785],"type":"Point"}
}