{
  "type": "Feature",
  "properties": {
    "iso:country":"AU",
    "sg:address":"116 Military Rd",
    "sg:city":"Neutral Bay",
    "sg:classifiers":[
        {
            "category":"Real Estate",
            "subcategory":"Surveying",
            "type":"Services"
        }
    ],
    "sg:phone":"+61 2 9465 5855",
    "sg:postcode":"2089",
    "sg:province":"NSW",
    "sg:tags":[
        "building",
        "surveyor"
    ],
    "wof:name":"Colwell Larcombe Rein",
    "wof:placetype":"venue"
},
  "geometry": {"coordinates":[151.219314575,-33.830242157],"type":"Point"}
}