{
  "type": "Feature",
  "properties": {
    "addr:full":"Jacobs St Whyalla Norrie SA 5608",
    "addr:postcode":"5608",
    "addr:street":"Jacobs St",
    "iso:country":"AU",
    "sg:address":"Jacobs St",
    "sg:city":"Whyalla Norrie",
    "sg:classifiers":[
        {
            "category":"Wholesale",
            "subcategory":"Machinery & Supplies",
            "type":"Manufacturing & Wholesale Goods"
        }
    ],
    "sg:phone":"+61 8 8645 7033",
    "sg:postcode":"5608",
    "sg:province":"SA",
    "sg:tags":[
        "equipment",
        "welding"
    ],
    "wof:name":"Avid Engineering Pty Ltd",
    "wof:placetype":"venue"
},
  "geometry": {"coordinates":[137.54440299999999,-33.040665],"type":"Point"}
}