{
  "type": "Feature",
  "properties": {
    "addr:full":"6 Balaclava Rd St Kilda East VIC 3183",
    "addr:housenumber":"6",
    "addr:postcode":"3183",
    "addr:street":"Balaclava Rd",
    "iso:country":"AU",
    "sg:address":"6 Balaclava Rd",
    "sg:city":"St Kilda East",
    "sg:classifiers":[
        {
            "category":"Education",
            "subcategory":"University",
            "type":"Public Place"
        }
    ],
    "sg:phone":"+61 3 9522 8222",
    "sg:postcode":"3183",
    "sg:province":"VIC",
    "sg:tags":[
        "college",
        "tertiary"
    ],
    "wof:name":"Ohel Chana College",
    "wof:placetype":"venue"
},
  "geometry": {"coordinates":[144.99996948200001,-37.8694381714],"type":"Point"}
}