{
  "type": "Feature",
  "properties": {
    "addr:full":"28 Bank St West End QLD 4810",
    "addr:housenumber":"28",
    "addr:postcode":"4810",
    "addr:street":"Bank St",
    "iso:country":"AU",
    "sg:address":"28 Bank St",
    "sg:city":"West End",
    "sg:classifiers":[
        {
            "category":"Real Estate",
            "subcategory":"Surveying",
            "type":"Services"
        }
    ],
    "sg:phone":"+61 7 5570 3814",
    "sg:postcode":"4810",
    "sg:province":"QLD",
    "sg:tags":[
        "surveyor",
        "quantity"
    ],
    "wof:name":"Butler Wright & Partners",
    "wof:placetype":"venue"
},
  "geometry": {"coordinates":[146.81300400000001,-19.321175],"type":"Point"}
}