{
  "type": "Feature",
  "properties": {
    "iso:country":"AU",
    "sg:address":"23- 29 Main North Rd",
    "sg:city":"Smithfield",
    "sg:classifiers":[
        {
            "category":"Food & Beverages",
            "subcategory":"Bakery",
            "type":"Retail Goods"
        }
    ],
    "sg:phone":"+61 8 8254 8694",
    "sg:postcode":"5114",
    "sg:province":"SA",
    "sg:tags":[
        "baker"
    ],
    "wof:name":"Brumby's Bakeries",
    "wof:placetype":"venue"
},
  "geometry": {"coordinates":[138.69136047399999,-34.6862792969],"type":"Point"}
}