{
  "type": "Feature",
  "properties": {
    "addr:full":"460 Archerfield Rd Inala QLD 4077",
    "addr:housenumber":"460",
    "addr:postcode":"4077",
    "addr:street":"Archerfield Rd",
    "iso:country":"AU",
    "sg:address":"460 Archerfield Rd",
    "sg:city":"Inala",
    "sg:classifiers":[
        {
            "category":"Food & Beverages",
            "subcategory":"Fruits & Vegetables",
            "type":"Retail Goods"
        }
    ],
    "sg:phone":"+61 7 3879 1199",
    "sg:postcode":"4077",
    "sg:province":"QLD",
    "sg:tags":[
        "greengrocer",
        "fruiterer"
    ],
    "wof:name":"Archerfield Rd Fruit Barn",
    "wof:placetype":"venue"
},
  "geometry": {"coordinates":[152.95968627900001,-27.5944328308],"type":"Point"}
}