{
  "type": "Feature",
  "properties": {
    "addr:full":"PO Box 240 Thornleigh NSW 2120",
    "addr:postcode":"2120",
    "iso:country":"AU",
    "sg:address":"PO Box 240",
    "sg:city":"Thornleigh",
    "sg:classifiers":[
        {
            "category":"Shopping",
            "subcategory":"Computers & Home Electronics",
            "type":"Retail Goods"
        }
    ],
    "sg:phone":"+61 2 9481 7522",
    "sg:postcode":"2120",
    "sg:province":"NSW",
    "sg:tags":[
        "equipment",
        "multimedia"
    ],
    "wof:name":"Media Forge",
    "wof:placetype":"venue"
},
  "geometry": {"coordinates":[151.08340454099999,-33.7282104492],"type":"Point"}
}