{
  "type": "Feature",
  "properties": {
    "iso:country":"AU",
    "sg:address":"25 Redfern St",
    "sg:city":"Wetherill Park",
    "sg:classifiers":[
        {
            "category":"Shopping",
            "subcategory":"Stationery & Office Supplies",
            "type":"Retail Goods"
        }
    ],
    "sg:phone":"+61 2 9604 5202",
    "sg:postcode":"2164",
    "sg:province":"NSW",
    "sg:tags":[
        "packaging",
        "material"
    ],
    "wof:name":"IWD Strapping Sales Pty Ltd",
    "wof:placetype":"venue"
},
  "geometry": {"coordinates":[150.91184997600001,-33.8437309265],"type":"Point"}
}