{
  "type": "Feature",
  "properties": {
    "addr:full":"3156 Beaudesert Rd Calamvale QLD 4116",
    "addr:housenumber":"3156",
    "addr:postcode":"4116",
    "addr:street":"Beaudesert Rd",
    "iso:country":"AU",
    "sg:address":"3156 Beaudesert Rd",
    "sg:city":"Calamvale",
    "sg:classifiers":[
        {
            "category":"Farming",
            "subcategory":"Nursery",
            "type":"Manufacturing & Wholesale Goods"
        }
    ],
    "sg:phone":"+61 7 3800 0266",
    "sg:postcode":"4116",
    "sg:province":"QLD",
    "wof:name":"Tetra & Associates Pty Ltd",
    "wof:placetype":"venue"
},
  "geometry": {"coordinates":[153.04127502399999,-27.6489524841],"type":"Point"}
}