{
  "type": "Feature",
  "properties": {
    "addr:full":"Mater Medical Centre 21- 37 Fulham Rd Pimlico QLD 4812",
    "addr:housenumber":"21 37",
    "addr:postcode":"4812",
    "addr:street":"Fulham Rd",
    "iso:country":"AU",
    "sg:address":"Mater Medical Centre 21- 37 Fulham Rd",
    "sg:city":"Pimlico",
    "sg:classifiers":[
        {
            "category":"Health Services",
            "subcategory":"Health Practitioner",
            "type":"Services"
        }
    ],
    "sg:phone":"+61 7 4728 9999",
    "sg:postcode":"4812",
    "sg:province":"QLD",
    "sg:tags":[
        "physiotherapist"
    ],
    "wof:name":"Waters Rebecca",
    "wof:placetype":"venue"
},
  "geometry": {"coordinates":[146.78637699999999,-19.289091],"type":"Point"}
}