{
  "type": "Feature",
  "properties": {
    "addr:full":"87 Starbush Crs Ellenbrook WA 6069",
    "addr:housenumber":"87",
    "addr:postcode":"6069",
    "addr:street":"Starbush Crs",
    "iso:country":"AU",
    "sg:address":"87 Starbush Crs",
    "sg:city":"Ellenbrook",
    "sg:classifiers":[
        {
            "category":"Farming",
            "subcategory":"Farm & Veterinary Services",
            "type":"Manufacturing & Wholesale Goods"
        }
    ],
    "sg:phone":"+61 408 453 411",
    "sg:postcode":"6069",
    "sg:province":"WA",
    "sg:tags":[
        "irrigation",
        "reticulation",
        "system"
    ],
    "wof:name":"Unique Landscaping",
    "wof:placetype":"venue"
},
  "geometry": {"coordinates":[115.97013855,-31.7888202667],"type":"Point"}
}