{
  "type": "Feature",
  "properties": {
    "addr:full":"19 Careela St Mooloolaba QLD 4557",
    "addr:housenumber":"19",
    "addr:postcode":"4557",
    "addr:street":"Careela St",
    "iso:country":"AU",
    "sg:address":"19 Careela St",
    "sg:city":"Mooloolaba",
    "sg:classifiers":[
        {
            "category":"Food & Beverages",
            "subcategory":"Groceries & Convenience Stores",
            "type":"Retail Goods"
        }
    ],
    "sg:phone":"+61 7 5444 3627",
    "sg:postcode":"4557",
    "sg:province":"QLD",
    "wof:name":"Mooloolaba Convenience Store",
    "wof:placetype":"venue"
},
  "geometry": {"coordinates":[153.11041259800001,-26.6780605316],"type":"Point"}
}