{
  "type": "Feature",
  "properties": {
    "iso:country":"AU",
    "sg:address":"29 Fisher Drv",
    "sg:city":"Mt Isa",
    "sg:classifiers":[
        {
            "category":"Mining & Drilling",
            "type":"Manufacturing & Wholesale Goods"
        }
    ],
    "sg:phone":"+61 7 4743 9403",
    "sg:postcode":"4825",
    "sg:province":"QLD",
    "sg:tags":[
        "equipment",
        "quarrying",
        "supply"
    ],
    "wof:name":"Elphinstone Caterpillar Pty Ltd",
    "wof:placetype":"venue"
},
  "geometry": {"coordinates":[139.485825,-20.727293],"type":"Point"}
}