{
  "type": "Feature",
  "properties": {
    "addr:full":"24 Egan Rd Dandenong VIC 3175",
    "addr:housenumber":"24",
    "addr:postcode":"3175",
    "addr:street":"Egan Rd",
    "iso:country":"AU",
    "sg:address":"24 Egan Rd",
    "sg:city":"Dandenong",
    "sg:classifiers":[
        {
            "category":"Manufacturing",
            "subcategory":"Tools & Machinery",
            "type":"Manufacturing & Wholesale Goods"
        }
    ],
    "sg:phone":"+61 3 9791 8645",
    "sg:postcode":"3175",
    "sg:province":"VIC",
    "sg:tags":[
        "toolmaker"
    ],
    "wof:name":"High Precision Tooling Pty Ltd",
    "wof:placetype":"venue"
},
  "geometry": {"coordinates":[145.19433593799999,-37.9936904907],"type":"Point"}
}