{
  "type": "Feature",
  "properties": {
    "iso:country":"AU",
    "sg:address":"U1/ 10 Clavering Rd",
    "sg:city":"Bayswater",
    "sg:classifiers":[
        {
            "category":"Retail",
            "subcategory":"Auto Repair",
            "type":"Services"
        }
    ],
    "sg:phone":"+61 8 9370 5441",
    "sg:postcode":"6053",
    "sg:province":"WA",
    "sg:tags":[
        "beater",
        "painter",
        "panel"
    ],
    "wof:name":"Pacer Panel & Paint",
    "wof:placetype":"venue"
},
  "geometry": {"coordinates":[115.92224883999999,-31.9179897308],"type":"Point"}
}