{
  "type": "Feature",
  "properties": {
    "iso:country":"AU",
    "sg:address":"Shop 3 Tourist Building Doyle St",
    "sg:city":"Narrabri",
    "sg:classifiers":[
        {
            "category":"Health Services",
            "subcategory":"Doctor",
            "type":"Services"
        }
    ],
    "sg:phone":"+61 2 6792 2949",
    "sg:postcode":"2390",
    "sg:province":"NSW",
    "sg:tags":[
        "medical",
        "practitioner"
    ],
    "wof:name":"Ling Michael",
    "wof:placetype":"venue"
},
  "geometry": {"coordinates":[149.782470703,-30.3249950409],"type":"Point"}
}