{
  "type": "Feature",
  "properties": {
    "addr:full":"182 Parramatta Rd Camperdown NSW 2050",
    "addr:housenumber":"182",
    "addr:postcode":"2050",
    "addr:street":"Parramatta Rd",
    "iso:country":"AU",
    "sg:address":"182 Parramatta Rd",
    "sg:city":"Camperdown",
    "sg:classifiers":[
        {
            "category":"Home & Garden",
            "subcategory":"Carpets & Floor Coverings",
            "type":"Retail Goods"
        }
    ],
    "sg:phone":"+61 2 9550 5205",
    "sg:postcode":"2050",
    "sg:province":"NSW",
    "sg:tags":[
        "tile",
        "wall"
    ],
    "wof:name":"Reproduction Tiles",
    "wof:placetype":"venue"
},
  "geometry": {"coordinates":[151.17524700000001,-33.886959],"type":"Point"}
}