{
  "type": "Feature",
  "properties": {
    "addr:full":"Waddell Rd Richmond QLD 4822",
    "addr:postcode":"4822",
    "addr:street":"Waddell Rd",
    "iso:country":"AU",
    "sg:address":"Waddell Rd",
    "sg:city":"Richmond",
    "sg:classifiers":[
        {
            "category":"Building & Trades",
            "subcategory":"Landscaping Services",
            "type":"Services"
        }
    ],
    "sg:phone":"+61 7 4942 2886",
    "sg:postcode":"4822",
    "sg:province":"QLD",
    "sg:tags":[
        "grazier"
    ],
    "wof:name":"Hasker W E S & J M",
    "wof:placetype":"venue"
},
  "geometry": {"coordinates":[143.14309700000001,-20.73255],"type":"Point"}
}