{
  "type": "Feature",
  "properties": {
    "addr:full":"715 Springvale Rd Glen Waverley VIC 3150",
    "addr:housenumber":"715",
    "addr:postcode":"3150",
    "addr:street":"Springvale Rd",
    "iso:country":"AU",
    "sg:address":"715 Springvale Rd",
    "sg:city":"Glen Waverley",
    "sg:classifiers":[
        {
            "category":"Autos & Motor Vehicles",
            "subcategory":"Automobile Sales",
            "type":"Retail Goods"
        }
    ],
    "sg:phone":"+61 3 8562 5586",
    "sg:postcode":"3150",
    "sg:province":"VIC",
    "sg:tags":[
        "car",
        "new"
    ],
    "wof:name":"Garry & Warren Smith",
    "wof:placetype":"venue"
},
  "geometry": {"coordinates":[145.15858459500001,-37.9170227051],"type":"Point"}
}