{
  "type": "Feature",
  "properties": {
    "addr:full":"Taplin St Raukkan SA 5259",
    "addr:postcode":"5259",
    "addr:street":"Taplin St",
    "iso:country":"AU",
    "sg:address":"Taplin St",
    "sg:city":"Raukkan",
    "sg:classifiers":[
        {
            "category":"Education",
            "subcategory":"School",
            "type":"Public Place"
        }
    ],
    "sg:phone":"+61 8 8574 0042",
    "sg:postcode":"5259",
    "sg:province":"SA",
    "sg:tags":[
        "state",
        "except",
        "nsw"
    ],
    "wof:name":"Raukkan Aboriginal School",
    "wof:placetype":"venue"
},
  "geometry": {"coordinates":[139.37124633799999,-35.414680481],"type":"Point"}
}