{
  "type": "Feature",
  "properties": {
    "iso:country":"AU",
    "sg:address":"9a Beresford Ave",
    "sg:city":"Beresfield",
    "sg:classifiers":[
        {
            "category":"Health Services",
            "subcategory":"Doctor",
            "type":"Services"
        }
    ],
    "sg:phone":"+61 2 4966 4766",
    "sg:postcode":"2322",
    "sg:province":"NSW",
    "sg:tags":[
        "medical",
        "practitioner"
    ],
    "wof:name":"Mellows H A",
    "wof:placetype":"venue"
},
  "geometry": {"coordinates":[151.65719604500001,-32.8008460999],"type":"Point"}
}