{
  "type": "Feature",
  "properties": {
    "iso:country":"AU",
    "sg:address":"1686 Princes Hwy",
    "sg:city":"Oakleigh",
    "sg:classifiers":[
        {
            "category":"Home & Garden",
            "subcategory":"Carpets & Floor Coverings",
            "type":"Retail Goods"
        }
    ],
    "sg:phone":"+61 3 9543 8843",
    "sg:postcode":"3166",
    "sg:province":"VIC",
    "sg:tags":[
        "wood"
    ],
    "wof:name":"Bamboo & Timber Select",
    "wof:placetype":"venue"
},
  "geometry": {"coordinates":[145.10372924800001,-37.8991737366],"type":"Point"}
}