{
  "type": "Feature",
  "properties": {
    "iso:country":"AU",
    "sg:address":"10 Michel St",
    "sg:city":"Lowood",
    "sg:classifiers":[
        {
            "category":"Building & Trades",
            "subcategory":"Construction",
            "type":"Services"
        }
    ],
    "sg:phone":"+61 7 5426 1207",
    "sg:postcode":"4311",
    "sg:province":"QLD",
    "sg:tags":[
        "contractor"
    ],
    "wof:name":"Lubke N",
    "wof:placetype":"venue"
},
  "geometry": {"coordinates":[152.57972717300001,-27.4633750916],"type":"Point"}
}