{
  "type": "Feature",
  "properties": {
    "addr:full":"414 Somerville Rd Tottenham VIC 3012",
    "addr:housenumber":"414",
    "addr:postcode":"3012",
    "addr:street":"Somerville Rd",
    "iso:country":"AU",
    "sg:address":"414 Somerville Rd",
    "sg:city":"Tottenham",
    "sg:classifiers":[
        {
            "category":"Home & Garden",
            "subcategory":"Building Materials",
            "type":"Retail Goods"
        }
    ],
    "sg:phone":"+61 3 9362 6500",
    "sg:postcode":"3012",
    "sg:province":"VIC",
    "sg:tags":[
        "roofing"
    ],
    "wof:name":"VM ZINC - Umicore Aust",
    "wof:placetype":"venue"
},
  "geometry": {"coordinates":[144.858078003,-37.8097419739],"type":"Point"}
}