{
  "type": "Feature",
  "properties": {
    "addr:full":"Unit 5/ 141 George Rd Salamander Bay NSW 2317",
    "addr:housenumber":"/ 141",
    "addr:postcode":"2317",
    "addr:street":"George Rd",
    "iso:country":"AU",
    "sg:address":"Unit 5/ 141 George Rd",
    "sg:city":"Salamander Bay",
    "sg:classifiers":[
        {
            "category":"Autos & Motor Vehicles",
            "subcategory":"Boat Sales",
            "type":"Retail Goods"
        }
    ],
    "sg:phone":"+61 2 4982 0055",
    "sg:postcode":"2317",
    "sg:province":"NSW",
    "sg:tags":[
        "builder",
        "yacht",
        "repairer"
    ],
    "wof:name":"Fairfit Marine",
    "wof:placetype":"venue"
},
  "geometry": {"coordinates":[152.07841500000001,-32.72628],"type":"Point"}
}