{
  "type": "Feature",
  "properties": {
    "addr:full":"GPO Box 2936 Brisbane QLD 4001",
    "addr:postcode":"4001",
    "iso:country":"AU",
    "sg:address":"GPO Box 2936",
    "sg:city":"Brisbane",
    "sg:classifiers":[
        {
            "category":"Autos & Motor Vehicles",
            "subcategory":"Automobile Sales",
            "type":"Retail Goods"
        }
    ],
    "sg:phone":"+61 7 3807 5083",
    "sg:postcode":"4001",
    "sg:province":"QLD",
    "sg:tags":[
        "equipment",
        "trailer"
    ],
    "wof:name":"XPT Power Industries",
    "wof:placetype":"venue"
},
  "geometry": {"coordinates":[153.02789306599999,-27.4675807953],"type":"Point"}
}