{
  "type": "Feature",
  "properties": {
    "addr:full":"Shop M3, Elizabeth Shopping Centre, 50 Elizabeth Way Elizabeth SA 5112",
    "addr:housenumber":"50",
    "addr:postcode":"5112",
    "addr:street":"Elizabeth Way",
    "iso:country":"AU",
    "sg:address":"Shop M3, Elizabeth Shopping Centre, 50 Elizabeth Way",
    "sg:city":"Elizabeth",
    "sg:classifiers":[
        {
            "category":"Shopping",
            "subcategory":"Computers & Home Electronics",
            "type":"Retail Goods"
        }
    ],
    "sg:phone":"+61 8 8252 6840",
    "sg:postcode":"5112",
    "sg:province":"SA",
    "sg:tags":[
        "small",
        "equipment",
        "business"
    ],
    "wof:name":"Dick Smith Electronics",
    "wof:placetype":"venue"
},
  "geometry": {"coordinates":[138.66700744600001,-34.7156982422],"type":"Point"}
}