{
  "type": "Feature",
  "properties": {
    "addr:full":"10/ 12 Tasman Way Byron Bay NSW 2481",
    "addr:housenumber":"10 / 12",
    "addr:postcode":"2481",
    "addr:street":"Tasman Way",
    "iso:country":"AU",
    "sg:address":"10/ 12",
    "sg:city":"Tasman Way Byron Bay",
    "sg:classifiers":[
        {
            "category":"Social Services",
            "subcategory":"Retirement Home",
            "type":"Services"
        }
    ],
    "sg:phone":"+61 2 6680 9704",
    "sg:postcode":"2481",
    "sg:province":"NSW",
    "sg:tags":[
        "environmental",
        "consultant",
        "pollution"
    ],
    "wof:name":"WSP Environmental Pty Ltd",
    "wof:placetype":"venue"
},
  "geometry": {"coordinates":[153.579956055,-28.6355228424],"type":"Point"}
}