{
  "type": "Feature",
  "properties": {
    "addr:full":"16 Adelaide Rd Gawler SA 5118",
    "addr:housenumber":"16",
    "addr:postcode":"5118",
    "addr:street":"Adelaide Rd",
    "iso:country":"AU",
    "sg:address":"16 Adelaide Rd",
    "sg:city":"Gawler",
    "sg:classifiers":[
        {
            "category":"Professional",
            "subcategory":"Accounting & Tax Preparation",
            "type":"Services"
        }
    ],
    "sg:phone":"+61 8 8522 3964",
    "sg:postcode":"5118",
    "sg:province":"SA",
    "sg:tags":[
        "consultant",
        "taxation"
    ],
    "wof:name":"Clayton Hentschke Accountants",
    "wof:placetype":"venue"
},
  "geometry": {"coordinates":[138.74612400000001,-34.604965],"type":"Point"}
}