{
  "type": "Feature",
  "properties": {
    "addr:full":"Corner Norma Rd & Marmion St Booragoon WA 6154",
    "addr:postcode":"6154",
    "addr:street":"Norma Rd & Marmion St",
    "iso:country":"AU",
    "sg:address":"Corner Norma Rd & Marmion St",
    "sg:city":"Booragoon",
    "sg:classifiers":[
        {
            "category":"Building & Trades",
            "subcategory":"Equipment Rental",
            "type":"Services"
        }
    ],
    "sg:phone":"+61 1300 134 213",
    "sg:postcode":"6154",
    "sg:province":"WA",
    "sg:tags":[
        "fitness"
    ],
    "wof:name":"Orbit Health & Fitness Solutions",
    "wof:placetype":"venue"
},
  "geometry": {"coordinates":[115.822273,-32.03529],"type":"Point"}
}