{
  "type": "Feature",
  "properties": {
    "iso:country":"AU",
    "sg:address":"370 Ingham Rd",
    "sg:city":"Garbutt",
    "sg:classifiers":[
        {
            "category":"Professional",
            "subcategory":"Art Services",
            "type":"Services"
        }
    ],
    "sg:phone":"+61 7 4779 0957",
    "sg:postcode":"4814",
    "sg:province":"QLD",
    "sg:tags":[
        "medical",
        "industrial",
        "gas"
    ],
    "wof:name":"Boc Ltd",
    "wof:placetype":"venue"
},
  "geometry": {"coordinates":[146.767914,-19.263641],"type":"Point"}
}