{
  "type": "Feature",
  "properties": {
    "iso:country":"AU",
    "sg:address":"61-63 Murradoc Rd",
    "sg:city":"Drysdale",
    "sg:classifiers":[
        {
            "category":"Shopping",
            "subcategory":"Crafts & Fabrics",
            "type":"Retail Goods"
        }
    ],
    "sg:phone":"+61 3 5253 2569",
    "sg:postcode":"3222",
    "sg:province":"VIC",
    "sg:tags":[
        "synthetic",
        "canvas",
        "product"
    ],
    "wof:name":"Concept Campers",
    "wof:placetype":"venue"
},
  "geometry": {"coordinates":[144.576553,-38.173496],"type":"Point"}
}