{
  "type": "Feature",
  "properties": {
    "iso:country":"AU",
    "sg:address":"15 Ridgeway Rd",
    "sg:city":"Elizabeth West",
    "sg:classifiers":[
        {
            "category":"Farming",
            "subcategory":"Farm & Veterinary Services",
            "type":"Manufacturing & Wholesale Goods"
        }
    ],
    "sg:phone":"+61 8 8444 7600",
    "sg:postcode":"5113",
    "sg:province":"SA",
    "sg:tags":[
        "poultry",
        "processing",
        "supply"
    ],
    "wof:name":"Manos Poultry Industries",
    "wof:placetype":"venue"
},
  "geometry": {"coordinates":[138.657104492,-34.7066955566],"type":"Point"}
}