{
  "type": "Feature",
  "properties": {
    "addr:full":"Pepper Tree House,Doctors Hill Goomalling Rd Northam WA 6401",
    "addr:postcode":"6401",
    "addr:street":"Goomalling Rd",
    "iso:country":"AU",
    "sg:address":"Pepper Tree House,Doctors Hill Goomalling Rd",
    "sg:city":"Northam",
    "sg:classifiers":[
        {
            "category":"Health Services",
            "subcategory":"Health Practitioner",
            "type":"Services"
        }
    ],
    "sg:phone":"+61 8 9622 3427",
    "sg:postcode":"6401",
    "sg:province":"WA",
    "sg:tags":[
        "naturopath"
    ],
    "wof:name":"Radiant Health",
    "wof:placetype":"venue"
},
  "geometry": {"coordinates":[116.677139282,-31.6452598572],"type":"Point"}
}