{
  "type": "Feature",
  "properties": {
    "addr:full":"341 Payneham Rd Marden SA 5070",
    "addr:housenumber":"341",
    "addr:postcode":"5070",
    "addr:street":"Payneham Rd",
    "iso:country":"AU",
    "sg:address":"341 Payneham Rd",
    "sg:city":"Marden",
    "sg:classifiers":[
        {
            "category":"Health Services",
            "subcategory":"Health Practitioner",
            "type":"Services"
        }
    ],
    "sg:phone":"+61 8 8363 9336",
    "sg:postcode":"5070",
    "sg:province":"SA",
    "sg:tags":[
        "naturopath"
    ],
    "wof:name":"Ultrahealth Energy Medicine",
    "wof:placetype":"venue"
},
  "geometry": {"coordinates":[138.63848876899999,-34.8968925476],"type":"Point"}
}