{
  "type": "Feature",
  "properties": {
    "addr:full":"Factory 3/ 29 Gibbs St Labrador QLD 4215",
    "addr:housenumber":"/ 29",
    "addr:postcode":"4215",
    "addr:street":"Gibbs St",
    "iso:country":"AU",
    "sg:address":"Factory 3/ 29 Gibbs St",
    "sg:city":"Labrador",
    "sg:classifiers":[
        {
            "category":"Landmark",
            "subcategory":"Scenic View",
            "type":"Public Place"
        }
    ],
    "sg:phone":"+61 7 5528 9200",
    "sg:postcode":"4215",
    "sg:province":"QLD",
    "sg:tags":[
        "staircase",
        "handrail"
    ],
    "wof:name":"Slattery & Acquroff Holdings Pty Ltd",
    "wof:placetype":"venue"
},
  "geometry": {"coordinates":[153.38278198200001,-27.9368877411],"type":"Point"}
}