{
  "type": "Feature",
  "properties": {
    "iso:country":"AU",
    "sg:address":"11 Bishop St",
    "sg:city":"Stuart Park",
    "sg:classifiers":[
        {
            "category":"Home & Garden",
            "subcategory":"Carpets & Floor Coverings",
            "type":"Retail Goods"
        }
    ],
    "sg:phone":"+61 1300 134 752",
    "sg:postcode":"0820",
    "sg:province":"NT",
    "sg:tags":[
        "mat",
        "matting"
    ],
    "wof:name":"Ensign Services (Aust) Pty Ltd",
    "wof:placetype":"venue"
},
  "geometry": {"coordinates":[130.851364136,-12.4334688187],"type":"Point"}
}