{
  "type": "Feature",
  "properties": {
    "iso:country":"AU",
    "sg:address":"36 High St",
    "sg:city":"Glen Iris",
    "sg:classifiers":[
        {
            "category":"Government",
            "subcategory":"Court House",
            "type":"Public Place"
        }
    ],
    "sg:phone":"+61 3 9885 9033",
    "sg:postcode":"3146",
    "sg:province":"VIC",
    "sg:tags":[
        "personal",
        "marriage",
        "family",
        "counselling"
    ],
    "wof:name":"Talk Therapy",
    "wof:placetype":"venue"
},
  "geometry": {"coordinates":[145.065643311,-37.8618736267],"type":"Point"}
}