{
  "type": "Feature",
  "properties": {
    "addr:full":"18 Bulletin Place Sydney 2000",
    "addr:housenumber":"18",
    "addr:postcode":"2000",
    "addr:street":"Bulletin Place",
    "iso:country":"AU",
    "sg:address":"18 Bulletin Place",
    "sg:city":"Sydney",
    "sg:classifiers":[
        {
            "category":"Professional",
            "subcategory":"Advertising",
            "type":"Services"
        }
    ],
    "sg:postcode":"2000",
    "sg:tags":[
        "video",
        "metrics",
        "analytics",
        "social-networks"
    ],
    "sg:website":"http://www.vquence.com.au/",
    "wof:name":"Vquence",
    "wof:placetype":"venue"
},
  "geometry": {"coordinates":[151.20971,-33.862686],"type":"Point"}
}