{
  "type": "Feature",
  "properties": {
    "iso:country":"AU",
    "sg:address":"2/ 2 Spinnaker Drv",
    "sg:city":"Mt Coolum",
    "sg:classifiers":[
        {
            "category":"Health Services",
            "subcategory":"Health Practitioner",
            "type":"Services"
        }
    ],
    "sg:phone":"+61 7 5446 3436",
    "sg:postcode":"4573",
    "sg:province":"QLD",
    "sg:tags":[
        "acupuncture"
    ],
    "wof:name":"Smith, Michael William",
    "wof:placetype":"venue"
},
  "geometry": {"coordinates":[153.09339900000001,-26.564718],"type":"Point"}
}