{
  "type": "Feature",
  "properties": {
    "addr:full":"24 Northview Pl Mt Colah NSW 2079",
    "addr:housenumber":"24",
    "addr:postcode":"2079",
    "addr:street":"Northview Pl Mt Colah",
    "iso:country":"AU",
    "sg:address":"24 Northview Pl",
    "sg:city":"Mt Colah",
    "sg:classifiers":[
        {
            "category":"Education",
            "subcategory":"Special Training",
            "type":"Public Place"
        }
    ],
    "sg:phone":"+61 2 9477 1793",
    "sg:postcode":"2079",
    "sg:province":"NSW",
    "sg:tags":[
        "tuition-educational"
    ],
    "wof:name":"Computer Camp Learning Centre",
    "wof:placetype":"venue"
},
  "geometry": {"coordinates":[151.10873413100001,-33.670539856],"type":"Point"}
}