{
  "type": "Feature",
  "properties": {
    "addr:full":"Cnr Nash & Monkland Sts Gympie QLD 4570",
    "addr:housenumber":"cnr",
    "addr:postcode":"4570",
    "addr:street":"Nash & Monkland Sts",
    "iso:country":"AU",
    "sg:address":"Cnr Nash & Monkland Sts",
    "sg:city":"Gympie",
    "sg:classifiers":[
        {
            "category":"Shopping",
            "subcategory":"Baby Store",
            "type":"Retail Goods"
        }
    ],
    "sg:phone":"+61 7 5482 7820",
    "sg:postcode":"4570",
    "sg:province":"QLD",
    "sg:tags":[
        "wear"
    ],
    "wof:name":"Baby Days",
    "wof:placetype":"venue"
},
  "geometry": {"coordinates":[152.65852355999999,-26.1916275024],"type":"Point"}
}