{
  "type": "Feature",
  "properties": {
    "addr:full":"331 Liverpool St (cnr Molle St) Hobart TAS 7000",
    "addr:housenumber":"331",
    "addr:postcode":"7000",
    "addr:street":"Liverpool St Cnr Molle St",
    "iso:country":"AU",
    "sg:address":"331 Liverpool St (cnr Molle St)",
    "sg:city":"Hobart",
    "sg:classifiers":[
        {
            "category":"Communications",
            "subcategory":"Film & Video Production",
            "type":"Services"
        }
    ],
    "sg:phone":"+61 3 6234 3939",
    "sg:postcode":"7000",
    "sg:province":"TAS",
    "sg:tags":[
        "mirror"
    ],
    "wof:name":"Taylor Framing Mirrors",
    "wof:placetype":"venue"
},
  "geometry": {"coordinates":[147.32063293499999,-42.8871078491],"type":"Point"}
}