{
  "type": "Feature",
  "properties": {
    "iso:country":"AU",
    "sg:address":"Lvl3/ 22 Bridge Rd",
    "sg:city":"Glebe",
    "sg:classifiers":[
        {
            "category":"Manufacturing",
            "subcategory":"Tools & Machinery",
            "type":"Manufacturing & Wholesale Goods"
        }
    ],
    "sg:phone":"+61 2 8356 9988",
    "sg:postcode":"2037",
    "sg:province":"NSW",
    "sg:tags":[
        "wholesaler",
        "lingerie",
        "mfrs",
        "sleepwear"
    ],
    "wof:name":"Julianne",
    "wof:placetype":"venue"
},
  "geometry": {"coordinates":[151.188034058,-33.8769416809],"type":"Point"}
}