{
  "type": "Feature",
  "properties": {
    "iso:country":"AU",
    "sg:address":"52 Bushnall Rd",
    "sg:city":"Nanango",
    "sg:classifiers":[
        {
            "category":"Utilities",
            "subcategory":"Electric",
            "type":"Services"
        }
    ],
    "sg:phone":"+61 7 4163 2376",
    "sg:postcode":"4615",
    "sg:province":"QLD",
    "sg:tags":[
        "electrical",
        "contractor"
    ],
    "wof:name":"Bellert G E & J",
    "wof:placetype":"venue"
},
  "geometry": {"coordinates":[151.97178649899999,-26.6660804749],"type":"Point"}
}