{
  "type": "Feature",
  "properties": {
    "addr:full":"First Floor / 21- 29 Global Drv Tullamarine VIC 3043",
    "addr:housenumber":"first floor / 21 29",
    "addr:postcode":"3043",
    "addr:street":"Global Drv",
    "iso:country":"AU",
    "sg:address":"First Floor / 21- 29 Global Drv",
    "sg:city":"Tullamarine",
    "sg:classifiers":[
        {
            "category":"Professional",
            "type":"Services"
        }
    ],
    "sg:phone":"+61 3 9335 3311",
    "sg:postcode":"3043",
    "sg:province":"VIC",
    "sg:tags":[
        "forwarding",
        "agent",
        "transport"
    ],
    "wof:name":"Dacotrans Australia Pty Ltd",
    "wof:placetype":"venue"
},
  "geometry": {"coordinates":[144.877685547,-37.6835479736],"type":"Point"}
}