{
  "type": "Feature",
  "properties": {
    "addr:full":"22 Wingadee St Coonamble NSW 2829",
    "addr:housenumber":"22",
    "addr:postcode":"2829",
    "addr:street":"Wingadee St",
    "iso:country":"AU",
    "sg:address":"22 Wingadee St",
    "sg:city":"Coonamble",
    "sg:classifiers":[
        {
            "category":"Food & Beverages",
            "subcategory":"Groceries & Convenience Stores",
            "type":"Retail Goods"
        }
    ],
    "sg:phone":"+61 2 6822 1608",
    "sg:postcode":"2829",
    "sg:province":"NSW",
    "wof:name":"McKeown M & H",
    "wof:placetype":"venue"
},
  "geometry": {"coordinates":[148.37985229500001,-30.9499530792],"type":"Point"}
}