{
  "type": "Feature",
  "properties": {
    "addr:full":"120 Fullarton Rd Norwood SA 5067",
    "addr:housenumber":"120",
    "addr:postcode":"5067",
    "addr:street":"Fullarton Rd",
    "iso:country":"AU",
    "sg:address":"120 Fullarton Rd",
    "sg:city":"Norwood",
    "sg:classifiers":[
        {
            "category":"School Buses",
            "type":"Transportation"
        }
    ],
    "sg:phone":"+61 8 8364 3077",
    "sg:postcode":"5067",
    "sg:province":"SA",
    "sg:tags":[
        "nanny"
    ],
    "wof:name":"Yourkids",
    "wof:placetype":"venue"
},
  "geometry": {"coordinates":[138.623703003,-34.9265594482],"type":"Point"}
}