{
  "type": "Feature",
  "properties": {
    "iso:country":"AU",
    "sg:address":"187 Princes Hwy",
    "sg:city":"Drouin",
    "sg:classifiers":[
        {
            "category":"Retail",
            "subcategory":"Auto Repair",
            "type":"Services"
        }
    ],
    "sg:phone":"+61 3 5625 2047",
    "sg:postcode":"3818",
    "sg:province":"VIC",
    "sg:tags":[
        "beater",
        "painter",
        "panel"
    ],
    "wof:name":"Franklin John",
    "wof:placetype":"venue"
},
  "geometry": {"coordinates":[145.882294,-38.136951],"type":"Point"}
}