{
  "type": "Feature",
  "properties": {
    "addr:full":"Unit 1/ 135 Norton Prm Dalyellup WA 6230",
    "addr:housenumber":"/ 135",
    "addr:postcode":"6230",
    "addr:street":"Norton Prm",
    "iso:country":"AU",
    "sg:address":"Unit 1/ 135 Norton Prm",
    "sg:city":"Dalyellup",
    "sg:classifiers":[
        {
            "category":"Health Services",
            "subcategory":"Doctor",
            "type":"Services"
        }
    ],
    "sg:phone":"+61 8 9795 6422",
    "sg:postcode":"6230",
    "sg:province":"WA",
    "sg:tags":[
        "podiatrist"
    ],
    "wof:name":"Dalyellup Podiatry",
    "wof:placetype":"venue"
},
  "geometry": {"coordinates":[115.62560999999999,-33.399422],"type":"Point"}
}