{
  "type": "Feature",
  "properties": {
    "addr:full":"43 High St Oatlands TAS 7120",
    "addr:housenumber":"43",
    "addr:postcode":"7120",
    "addr:street":"High St",
    "iso:country":"AU",
    "sg:address":"43 High St",
    "sg:city":"Oatlands",
    "sg:classifiers":[
        {
            "category":"Retail",
            "subcategory":"Auto Repair",
            "type":"Services"
        }
    ],
    "sg:phone":"+61 3 6254 1211",
    "sg:postcode":"7120",
    "sg:province":"TAS",
    "sg:tags":[
        "repairer",
        "motor",
        "engineer"
    ],
    "wof:name":"Wards Service Station",
    "wof:placetype":"venue"
},
  "geometry": {"coordinates":[147.368484497,-42.3020553589],"type":"Point"}
}