{
  "type": "Feature",
  "properties": {
    "iso:country":"AU",
    "sg:address":"Level 2, 85 Smith St",
    "sg:city":"Wollongong",
    "sg:classifiers":[
        {
            "category":"Real Estate",
            "subcategory":"Real Estate Services",
            "type":"Services"
        }
    ],
    "sg:phone":"+61 411 324 555",
    "sg:postcode":"2500",
    "sg:province":"NSW",
    "sg:tags":[
        "valuer"
    ],
    "wof:name":"Tony Varayiannis",
    "wof:placetype":"venue"
},
  "geometry": {"coordinates":[150.891296,-34.421291],"type":"Point"}
}