{
  "type": "Feature",
  "properties": {
    "addr:full":"33- 59 William St Moffat Beach QLD 4551",
    "addr:housenumber":"59",
    "addr:postcode":"4551",
    "addr:street":"William St",
    "iso:country":"AU",
    "sg:address":"33- 59 William St",
    "sg:city":"Moffat Beach",
    "sg:classifiers":[
        {
            "category":"Retail",
            "subcategory":"Laundry & Dry Cleaning",
            "type":"Services"
        }
    ],
    "sg:phone":"+61 416 008 167",
    "sg:postcode":"4551",
    "sg:province":"QLD",
    "sg:tags":[
        "truck",
        "tip",
        "contractor"
    ],
    "wof:name":"Gibson Sand & Gravel",
    "wof:placetype":"venue"
},
  "geometry": {"coordinates":[153.13865661599999,-26.7936935425],"type":"Point"}
}