{
  "type": "Feature",
  "properties": {
    "iso:country":"AU",
    "sg:address":"Factory 4/ 50 Camp Rd",
    "sg:city":"Broadmeadows",
    "sg:classifiers":[
        {
            "category":"Retail",
            "subcategory":"Auto Repair",
            "type":"Services"
        }
    ],
    "sg:phone":"+61 3 9359 1999",
    "sg:postcode":"3047",
    "sg:province":"VIC",
    "sg:tags":[
        "repairer",
        "motor",
        "engineer"
    ],
    "wof:name":"Choice One Motors",
    "wof:placetype":"venue"
},
  "geometry": {"coordinates":[144.926605225,-37.6862106323],"type":"Point"}
}