{
  "type": "Feature",
  "properties": {
    "addr:full":"103- 107 Potassium St Narangba QLD 4504",
    "addr:housenumber":"103 107",
    "addr:postcode":"4504",
    "addr:street":"Potassium St",
    "iso:country":"AU",
    "sg:address":"103- 107 Potassium St",
    "sg:city":"Narangba",
    "sg:classifiers":[
        {
            "category":"Utilities",
            "subcategory":"Water",
            "type":"Services"
        }
    ],
    "sg:phone":"+61 7 3204 7772",
    "sg:postcode":"4504",
    "sg:province":"QLD",
    "sg:tags":[
        "equipment",
        "treatment"
    ],
    "wof:name":"Drew Australia Pty ltd",
    "wof:placetype":"venue"
},
  "geometry": {"coordinates":[152.998535156,-27.1972637177],"type":"Point"}
}