{
  "type": "Feature",
  "properties": {
    "addr:full":"23 Kemmis St Randwick NSW 2031",
    "addr:housenumber":"23",
    "addr:postcode":"2031",
    "addr:street":"Kemmis St",
    "iso:country":"AU",
    "sg:address":"23 Kemmis St",
    "sg:city":"Randwick",
    "sg:classifiers":[
        {
            "category":"Sports & Exercise",
            "subcategory":"Gym",
            "type":"Entertainment"
        }
    ],
    "sg:phone":"+61 419 822 321",
    "sg:postcode":"2031",
    "sg:province":"NSW",
    "sg:tags":[
        "health",
        "fitness"
    ],
    "wof:name":"Fit Together",
    "wof:placetype":"venue"
},
  "geometry": {"coordinates":[151.24902343799999,-33.9087791443],"type":"Point"}
}