{
  "type": "Feature",
  "properties": {
    "addr:full":"12/ 1 Waverley Rd Lara VIC 3212",
    "addr:housenumber":"12 / 1",
    "addr:postcode":"3212",
    "addr:street":"Waverley Rd",
    "iso:country":"AU",
    "sg:address":"12/ 1 Waverley Rd",
    "sg:city":"Lara",
    "sg:classifiers":[
        {
            "category":"Shopping",
            "subcategory":"Party Supplies",
            "type":"Retail Goods"
        }
    ],
    "sg:phone":"+61 3 5282 5920",
    "sg:postcode":"3212",
    "sg:province":"VIC",
    "sg:tags":[
        "children's"
    ],
    "wof:name":"Down Under Fancy Dress Hire",
    "wof:placetype":"venue"
},
  "geometry": {"coordinates":[144.40835571299999,-38.0236587524],"type":"Point"}
}