{
  "type": "Feature",
  "properties": {
    "addr:full":"Windmill Centre 216 Phillip St Gladstone QLD 4680",
    "addr:housenumber":"216",
    "addr:postcode":"4680",
    "addr:street":"Phillip St",
    "iso:country":"AU",
    "sg:address":"Windmill Centre 216 Phillip St",
    "sg:city":"Gladstone",
    "sg:classifiers":[
        {
            "category":"Health Services",
            "subcategory":"Dentist",
            "type":"Services"
        }
    ],
    "sg:phone":"+61 7 4978 1122",
    "sg:postcode":"4680",
    "sg:province":"QLD",
    "wof:name":"Malcolm Bruce",
    "wof:placetype":"venue"
},
  "geometry": {"coordinates":[151.37464904800001,-23.9533576965],"type":"Point"}
}