{
  "type": "Feature",
  "properties": {
    "addr:full":"1774- 1794 Mt Cotton Rd Carbrook QLD 4130",
    "addr:housenumber":"1774 1794",
    "addr:postcode":"4130",
    "addr:street":"Mt Cotton Rd",
    "iso:country":"AU",
    "sg:address":"1774- 1794 Mt Cotton Rd",
    "sg:city":"Carbrook",
    "sg:classifiers":[
        {
            "category":"Retail",
            "subcategory":"Funeral Services",
            "type":"Services"
        }
    ],
    "sg:phone":"+61 7 3829 9999",
    "sg:postcode":"4130",
    "sg:province":"QLD",
    "sg:tags":[
        "director"
    ],
    "wof:name":"Great Southern Garden Of Remembrance",
    "wof:placetype":"venue"
},
  "geometry": {"coordinates":[153.23776245100001,-27.6530952454],"type":"Point"}
}