{
  "type": "Feature",
  "properties": {
    "addr:full":"U 14/ 12 Yatala Rd Mt Kuring-gai NSW 2080",
    "addr:housenumber":"14 / 12",
    "addr:postcode":"2080",
    "addr:street":"Yatala Rd",
    "iso:country":"AU",
    "sg:address":"U 14/ 12 Yatala Rd",
    "sg:city":"Mt Kuring-gai",
    "sg:classifiers":[
        {
            "category":"Shopping",
            "subcategory":"Computers & Home Electronics",
            "type":"Retail Goods"
        }
    ],
    "sg:phone":"+61 2 9457 6011",
    "sg:postcode":"2080",
    "sg:province":"NSW",
    "sg:tags":[
        "wholesaler",
        "mfrs",
        "part",
        "electronic"
    ],
    "wof:name":"ICP Electronics Australia Pty Ltd",
    "wof:placetype":"venue"
},
  "geometry": {"coordinates":[151.13238525400001,-33.6448059082],"type":"Point"}
}