{
  "type": "Feature",
  "properties": {
    "iso:country":"AU",
    "sg:address":"239 Great Eastern Hwy",
    "sg:city":"Belmont",
    "sg:classifiers":[
        {
            "category":"Retail",
            "subcategory":"Auto Rental",
            "type":"Services"
        }
    ],
    "sg:phone":"+61 8 9475 0600",
    "sg:postcode":"6104",
    "sg:province":"WA",
    "sg:tags":[
        "car",
        "hire",
        "minibus"
    ],
    "wof:name":"M 2000 Car Rental",
    "wof:placetype":"venue"
},
  "geometry": {"coordinates":[115.925598145,-31.9420375824],"type":"Point"}
}