{
  "type": "Feature",
  "properties": {
    "iso:country":"AU",
    "sg:address":"1611 Botany Rd",
    "sg:city":"Botany",
    "sg:classifiers":[
        {
            "category":"Retail",
            "subcategory":"Repair Shop",
            "type":"Services"
        }
    ],
    "sg:phone":"+61 2 9666 3573",
    "sg:postcode":"2019",
    "sg:province":"NSW",
    "sg:tags":[
        "upholsterer"
    ],
    "wof:name":"Sydney Recover Company",
    "wof:placetype":"venue"
},
  "geometry": {"coordinates":[151.203125,-33.9536972046],"type":"Point"}
}