{
  "type": "Feature",
  "properties": {
    "iso:country":"AU",
    "sg:address":"6 Avocado Pl",
    "sg:city":"Ewingsdale",
    "sg:classifiers":[
        {
            "category":"Professional",
            "subcategory":"Management & Consulting",
            "type":"Services"
        }
    ],
    "sg:phone":"+61 2 6684 7318",
    "sg:postcode":"2481",
    "sg:province":"NSW",
    "sg:tags":[
        "consultant",
        "migration"
    ],
    "wof:name":"Lindsay Wooten Solicitors",
    "wof:placetype":"venue"
},
  "geometry": {"coordinates":[153.55479431099999,-28.6422386169],"type":"Point"}
}