{
  "type": "Feature",
  "properties": {
    "addr:full":"26 Korong Rd Heidelberg West VIC 3081",
    "addr:housenumber":"26",
    "addr:postcode":"3081",
    "addr:street":"Korong Rd",
    "iso:country":"AU",
    "sg:address":"26 Korong Rd",
    "sg:city":"Heidelberg West",
    "sg:classifiers":[
        {
            "category":"Utilities",
            "subcategory":"Electric",
            "type":"Services"
        }
    ],
    "sg:phone":"+61 3 9458 1177",
    "sg:postcode":"3081",
    "sg:province":"VIC",
    "sg:tags":[
        "transformer"
    ],
    "wof:name":"BWM Electrical Engineering Pty Ltd",
    "wof:placetype":"venue"
},
  "geometry": {"coordinates":[145.04702758799999,-37.7337913513],"type":"Point"}
}