{
  "type": "Feature",
  "properties": {
    "iso:country":"AU",
    "sg:address":"21 Henty St",
    "sg:city":"Brighton East",
    "sg:classifiers":[
        {
            "category":"Professional",
            "subcategory":"Management & Consulting",
            "type":"Services"
        }
    ],
    "sg:phone":"+61 3 9593 1998",
    "sg:postcode":"3187",
    "sg:province":"VIC",
    "sg:tags":[
        "consultant"
    ],
    "wof:name":"Peter A Hill & Associates Pty Ltd",
    "wof:placetype":"venue"
},
  "geometry": {"coordinates":[145.00941467300001,-37.9210128784],"type":"Point"}
}