{
  "type": "Feature",
  "properties": {
    "addr:full":"12 Arunga Drv Beresfield NSW 2322",
    "addr:housenumber":"12",
    "addr:postcode":"2322",
    "addr:street":"Arunga Drv",
    "iso:country":"AU",
    "sg:address":"12 Arunga Drv",
    "sg:city":"Beresfield",
    "sg:classifiers":[
        {
            "category":"Autos & Motor Vehicles",
            "subcategory":"Auto Supplies",
            "type":"Retail Goods"
        }
    ],
    "sg:phone":"+61 2 4966 0091",
    "sg:postcode":"2322",
    "sg:province":"NSW",
    "sg:tags":[
        "tyre"
    ],
    "wof:name":"Toyo Tyre & Rubber Aust. Ltd.",
    "wof:placetype":"venue"
},
  "geometry": {"coordinates":[151.64047241200001,-32.8085021973],"type":"Point"}
}