{
  "type": "Feature",
  "properties": {
    "addr:full":"Shop 16, High St (Cnr Meibusch St) Rangeville QLD 4350",
    "addr:housenumber":"shop 16",
    "addr:postcode":"4350",
    "addr:street":"High St Cnr Meibusch St",
    "iso:country":"AU",
    "sg:address":"Shop 16, High St",
    "sg:city":"(Cnr Meibusch St) Rangeville",
    "sg:classifiers":[
        {
            "category":"Fast Food",
            "type":"Food & Drink"
        }
    ],
    "sg:phone":"+61 7 4635 3355",
    "sg:postcode":"4350",
    "sg:province":"QLD",
    "sg:tags":[
        "away",
        "take"
    ],
    "wof:name":"High Street Carvery & Takeaway",
    "wof:placetype":"venue"
},
  "geometry": {"coordinates":[151.97891200000001,-27.580112],"type":"Point"}
}