{
  "type": "Feature",
  "properties": {
    "addr:full":"Lvl1/ 88 Hanbury St Mayfield NSW 2304",
    "addr:housenumber":"88",
    "addr:postcode":"2304",
    "addr:street":"Hanbury St",
    "iso:country":"AU",
    "sg:address":"Lvl1/ 88 Hanbury St",
    "sg:city":"Mayfield",
    "sg:classifiers":[
        {
            "category":"Organizations",
            "subcategory":"Membership Organization",
            "type":"Services"
        }
    ],
    "sg:phone":"+61 2 4960 2667",
    "sg:postcode":"2304",
    "sg:province":"NSW",
    "sg:tags":[
        "support",
        "health",
        "organisation"
    ],
    "wof:name":"Kaiya Enterprises",
    "wof:placetype":"venue"
},
  "geometry": {"coordinates":[151.735839844,-32.8977546692],"type":"Point"}
}