{
  "type": "Feature",
  "properties": {
    "addr:full":"Level 2, 75 - 77 Clarence St Port Macquarie NSW 2444",
    "addr:housenumber":"75 77",
    "addr:postcode":"2444",
    "addr:street":"Clarence St",
    "iso:country":"AU",
    "sg:address":"Level 2, 75 - 77 Clarence St",
    "sg:city":"Port Macquarie",
    "sg:classifiers":[
        {
            "category":"Professional",
            "subcategory":"Accounting & Tax Preparation",
            "type":"Services"
        }
    ],
    "sg:phone":"+61 2 6580 0400",
    "sg:postcode":"2444",
    "sg:province":"NSW",
    "sg:tags":[
        "accountant",
        "auditor"
    ],
    "wof:name":"PPB",
    "wof:placetype":"venue"
},
  "geometry": {"coordinates":[152.906113,-31.429157],"type":"Point"}
}