{
  "type": "Feature",
  "properties": {
    "iso:country":"AU",
    "sg:address":"44 Agnes St",
    "sg:city":"Birkdale",
    "sg:classifiers":[
        {
            "category":"Mining & Drilling",
            "type":"Manufacturing & Wholesale Goods"
        }
    ],
    "sg:phone":"+61 407 029 853",
    "sg:postcode":"4159",
    "sg:province":"QLD",
    "sg:tags":[
        "concrete",
        "breaking",
        "grinding",
        "sawing"
    ],
    "wof:name":"All States Concrete Cutting",
    "wof:placetype":"venue"
},
  "geometry": {"coordinates":[153.214599609,-27.4866867065],"type":"Point"}
}