{
  "type": "Feature",
  "properties": {
    "addr:full":"237 Oxford St Bondi Junction NSW 2022",
    "addr:housenumber":"237",
    "addr:postcode":"2022",
    "addr:street":"Oxford St",
    "iso:country":"AU",
    "sg:address":"237 Oxford St",
    "sg:city":"Bondi Junction",
    "sg:classifiers":[
        {
            "category":"Health Services",
            "subcategory":"Optometrist",
            "type":"Services"
        }
    ],
    "sg:phone":"+61 2 9387 2334",
    "sg:postcode":"2022",
    "sg:province":"NSW",
    "wof:name":"Scott Michael",
    "wof:placetype":"venue"
},
  "geometry": {"coordinates":[151.25144958499999,-33.891960144],"type":"Point"}
}