{
  "type": "Feature",
  "properties": {
    "addr:full":"3 Tara Rd Broadmeadow NSW 2292",
    "addr:housenumber":"3",
    "addr:postcode":"2292",
    "addr:street":"Tara Rd",
    "iso:country":"AU",
    "sg:address":"3 Tara Rd",
    "sg:city":"Broadmeadow",
    "sg:classifiers":[
        {
            "category":"Professional",
            "subcategory":"Detective & Security Services",
            "type":"Services"
        }
    ],
    "sg:phone":"+61 2 4961 2405",
    "sg:postcode":"2292",
    "sg:province":"NSW",
    "sg:tags":[
        "protective",
        "rustproofing"
    ],
    "wof:name":"D & D Body Repairs (Newcastle)",
    "wof:placetype":"venue"
},
  "geometry": {"coordinates":[151.73008727999999,-32.9253845215],"type":"Point"}
}