{
  "type": "Feature",
  "properties": {
    "addr:full":"Hinkler Ave Bundaberg QLD 4670",
    "addr:postcode":"4670",
    "addr:street":"Hinkler Ave",
    "iso:country":"AU",
    "sg:address":"Hinkler Ave",
    "sg:city":"Bundaberg",
    "sg:classifiers":[
        {
            "category":"Organizations",
            "subcategory":"Non-profit Organization",
            "type":"Services"
        }
    ],
    "sg:phone":"+61 7 4151 3510",
    "sg:postcode":"4670",
    "sg:province":"QLD",
    "sg:tags":[
        "support",
        "disability",
        "organisation"
    ],
    "wof:name":"Carinbundi",
    "wof:placetype":"venue"
},
  "geometry": {"coordinates":[152.340606689,-24.8603553772],"type":"Point"}
}