{
  "type": "Feature",
  "properties": {
    "addr:full":"Ste 19/ 20 Bay St Double Bay NSW 2028",
    "addr:housenumber":"/ 20",
    "addr:postcode":"2028",
    "addr:street":"Bay St",
    "iso:country":"AU",
    "sg:address":"Ste 19/ 20 Bay St",
    "sg:city":"Double Bay",
    "sg:classifiers":[
        {
            "category":"Health Services",
            "subcategory":"Health Practitioner",
            "type":"Services"
        }
    ],
    "sg:phone":"+61 2 9363 0490",
    "sg:postcode":"2028",
    "sg:province":"NSW",
    "sg:tags":[
        "physiotherapist"
    ],
    "wof:name":"Viner Alison",
    "wof:placetype":"venue"
},
  "geometry": {"coordinates":[151.241363525,-33.877620697],"type":"Point"}
}