{
  "type": "Feature",
  "properties": {
    "addr:full":"Unit 9/11- 13 Potter Cl Wetherill Park NSW 2164",
    "addr:housenumber":"13",
    "addr:postcode":"2164",
    "addr:street":"Potter Cl",
    "iso:country":"AU",
    "sg:address":"Unit 9/11- 13 Potter Cl",
    "sg:city":"Wetherill Park",
    "sg:classifiers":[
        {
            "category":"Manufacturing",
            "subcategory":"Tools & Machinery",
            "type":"Manufacturing & Wholesale Goods"
        }
    ],
    "sg:phone":"+61 2 9609 2940",
    "sg:postcode":"2164",
    "sg:province":"NSW",
    "sg:tags":[
        "fastener",
        "industrial"
    ],
    "wof:name":"Warex Industrial Fasteners Pty Ltd",
    "wof:placetype":"venue"
},
  "geometry": {"coordinates":[150.90489196799999,-33.8546104431],"type":"Point"}
}