{
  "type": "Feature",
  "properties": {
    "addr:full":"10A Princes Hwy Berry NSW 2535",
    "addr:housenumber":"10a",
    "addr:postcode":"2535",
    "addr:street":"Princes Hwy",
    "iso:country":"AU",
    "sg:address":"10A Princes Hwy",
    "sg:city":"Berry",
    "sg:classifiers":[
        {
            "category":"Travel",
            "subcategory":"Hotels & Motels",
            "type":"Entertainment"
        }
    ],
    "sg:phone":"+61 2 4464 1305",
    "sg:postcode":"2535",
    "sg:province":"NSW",
    "wof:name":"Bangalee Motel",
    "wof:placetype":"venue"
},
  "geometry": {"coordinates":[150.70457458499999,-34.7745361328],"type":"Point"}
}