{
  "type": "Feature",
  "properties": {
    "addr:full":"Fortesque Pl Ellenbrook WA 6069",
    "addr:postcode":"6069",
    "addr:street":"Fortesque Pl",
    "iso:country":"AU",
    "sg:address":"Fortesque Pl",
    "sg:city":"Ellenbrook",
    "sg:classifiers":[
        {
            "category":"Education",
            "subcategory":"Kindergarten",
            "type":"Public Place"
        }
    ],
    "sg:phone":"+61 8 9296 7077",
    "sg:postcode":"6069",
    "sg:province":"WA",
    "sg:tags":[
        "pre-schools"
    ],
    "wof:name":"Catholic Church",
    "wof:placetype":"venue"
},
  "geometry": {"coordinates":[115.976631165,-31.7912101746],"type":"Point"}
}