{
  "type": "Feature",
  "properties": {
    "iso:country":"AU",
    "sg:address":"Ground Floor 22 Marine Pde",
    "sg:city":"Southport",
    "sg:classifiers":[
        {
            "category":"Banks & Credit Unions",
            "subcategory":"Bank",
            "type":"Services"
        }
    ],
    "sg:phone":"+61 13 13 33",
    "sg:postcode":"4215",
    "sg:province":"QLD",
    "sg:tags":[
        "broker",
        "mortgage"
    ],
    "wof:name":"Aussie",
    "wof:placetype":"venue"
},
  "geometry": {"coordinates":[153.41702270499999,-27.969581604],"type":"Point"}
}