{
  "type": "Feature",
  "properties": {
    "addr:full":"Shop 2, 142 Barton St Kurri Kurri NSW 2327",
    "addr:housenumber":"shop 2 142",
    "addr:postcode":"2327",
    "addr:street":"Barton St",
    "iso:country":"AU",
    "sg:address":"Shop 2, 142 Barton St",
    "sg:city":"Kurri Kurri",
    "sg:classifiers":[
        {
            "category":"Fast Food",
            "type":"Food & Drink"
        }
    ],
    "sg:phone":"+61 2 4936 2554",
    "sg:postcode":"2327",
    "sg:province":"NSW",
    "sg:tags":[
        "away",
        "take"
    ],
    "wof:name":"Eagle Boys Pizza - Kurri Kurri",
    "wof:placetype":"venue"
},
  "geometry": {"coordinates":[151.480911255,-32.8195610046],"type":"Point"}
}