{
  "type": "Feature",
  "properties": {
    "addr:full":"67 Farrall Rd Midvale WA 6056",
    "addr:housenumber":"67",
    "addr:postcode":"6056",
    "addr:street":"Farrall Rd",
    "iso:country":"AU",
    "sg:address":"67 Farrall Rd",
    "sg:city":"Midvale",
    "sg:classifiers":[
        {
            "category":"Retail",
            "subcategory":"Auto Repair",
            "type":"Services"
        }
    ],
    "sg:phone":"+61 8 9250 2104",
    "sg:postcode":"6056",
    "sg:province":"WA",
    "sg:tags":[
        "beater",
        "painter",
        "panel"
    ],
    "wof:name":"Phipps Mark Smash Repairs",
    "wof:placetype":"venue"
},
  "geometry": {"coordinates":[116.03324890099999,-31.889005661],"type":"Point"}
}