{
  "type": "Feature",
  "properties": {
    "addr:full":"57 King St Sydney NSW 2000",
    "addr:housenumber":"57",
    "addr:postcode":"2000",
    "addr:street":"King St",
    "iso:country":"AU",
    "sg:address":"57 King St",
    "sg:city":"Sydney",
    "sg:classifiers":[
        {
            "category":"Travel",
            "subcategory":"Hotels & Motels",
            "type":"Entertainment"
        }
    ],
    "sg:phone":"+61 2 9290 1811",
    "sg:postcode":"2000",
    "sg:province":"NSW",
    "sg:tags":[
        "pub"
    ],
    "wof:name":"P J O&#039;Briens Irish Pub",
    "wof:placetype":"venue"
},
  "geometry": {"coordinates":[151.20538330100001,-33.8688201904],"type":"Point"}
}