{
  "type": "Feature",
  "properties": {
    "addr:full":"PO Box 1150 Narre Warren VIC 3805",
    "addr:postcode":"3805",
    "iso:country":"AU",
    "sg:address":"PO Box 1150",
    "sg:city":"Narre Warren",
    "sg:classifiers":[
        {
            "category":"Real Estate",
            "subcategory":"Developer",
            "type":"Services"
        }
    ],
    "sg:phone":"+61 3 8794 9412",
    "sg:postcode":"3805",
    "sg:province":"VIC",
    "sg:tags":[
        "development"
    ],
    "wof:name":"Dan-E Investments",
    "wof:placetype":"venue"
},
  "geometry": {"coordinates":[145.305588,-38.02042],"type":"Point"}
}