{
  "type": "Feature",
  "properties": {
    "addr:full":"34 Diamond Bay Rd Vaucluse NSW 2030",
    "addr:housenumber":"34",
    "addr:postcode":"2030",
    "addr:street":"Diamond Bay Rd",
    "iso:country":"AU",
    "sg:address":"34 Diamond Bay Rd",
    "sg:city":"Vaucluse",
    "sg:classifiers":[
        {
            "category":"Professional",
            "subcategory":"Business Services",
            "type":"Services"
        }
    ],
    "sg:phone":"+61 2 9388 7661",
    "sg:postcode":"2030",
    "sg:province":"NSW",
    "sg:tags":[
        "consultant",
        "promoter",
        "entertainment"
    ],
    "wof:name":"Sunbiz Promotions",
    "wof:placetype":"venue"
},
  "geometry": {"coordinates":[151.28109741200001,-33.8610725403],"type":"Point"}
}