{
  "type": "Feature",
  "properties": {
    "iso:country":"AU",
    "sg:address":"63 Deans St",
    "sg:city":"Margate",
    "sg:classifiers":[
        {
            "category":"Food & Beverages",
            "subcategory":"Farmers Market",
            "type":"Retail Goods"
        }
    ],
    "sg:phone":"+61 7 3284 8416",
    "sg:postcode":"4019",
    "sg:province":"QLD",
    "sg:tags":[
        "beekeeper"
    ],
    "wof:name":"Croydon Gold Apiary",
    "wof:placetype":"venue"
},
  "geometry": {"coordinates":[153.09678649899999,-27.2481803894],"type":"Point"}
}