{
  "type": "Feature",
  "properties": {
    "addr:full":"2 Marlborough St Bentleigh East VIC 3165",
    "addr:housenumber":"2",
    "addr:postcode":"3165",
    "addr:street":"Marlborough St",
    "iso:country":"AU",
    "sg:address":"2 Marlborough St",
    "sg:city":"Bentleigh East",
    "sg:classifiers":[
        {
            "category":"Health Services",
            "subcategory":"Health Practitioner",
            "type":"Services"
        }
    ],
    "sg:phone":"+61 3 9579 7227",
    "sg:postcode":"3165",
    "sg:province":"VIC",
    "sg:tags":[
        "naturopath"
    ],
    "wof:name":"Penny Di Pasquale-Marinelli",
    "wof:placetype":"venue"
},
  "geometry": {"coordinates":[145.06692504899999,-37.9181976318],"type":"Point"}
}