{
  "type": "Feature",
  "properties": {
    "iso:country":"AU",
    "sg:address":"The Pines Shopng Cntr",
    "sg:city":"Doncaster East",
    "sg:classifiers":[
        {
            "category":"Personal",
            "subcategory":"Beauty Salon",
            "type":"Services"
        }
    ],
    "sg:phone":"+61 3 9842 2222",
    "sg:postcode":"3109",
    "sg:province":"VIC",
    "sg:tags":[
        "hairdresser"
    ],
    "wof:name":"Sharde Salon",
    "wof:placetype":"venue"
},
  "geometry": {"coordinates":[145.167800903,-37.7634353638],"type":"Point"}
}