{
  "type": "Feature",
  "properties": {
    "addr:full":"Shepparton Private Hospital Fitzgerald St Shepparton VIC 3630",
    "addr:postcode":"3630",
    "addr:street":"St",
    "iso:country":"AU",
    "sg:address":"Shepparton Private Hospital Fitzgerald St",
    "sg:city":"Shepparton",
    "sg:classifiers":[
        {
            "category":"Health Services",
            "subcategory":"Doctor",
            "type":"Services"
        }
    ],
    "sg:phone":"+61 3 5832 1312",
    "sg:postcode":"3630",
    "sg:province":"VIC",
    "sg:tags":[
        "medical",
        "practitioner"
    ],
    "wof:name":"Nanayakkara N Dr",
    "wof:placetype":"venue"
},
  "geometry": {"coordinates":[145.41163635300001,-36.3617172241],"type":"Point"}
}