{
  "type": "Feature",
  "properties": {
    "addr:full":"47 Essington Ave Gray NT 0830",
    "addr:housenumber":"47",
    "addr:postcode":"nt 0830",
    "addr:street":"Essington Ave",
    "iso:country":"AU",
    "sg:address":"47 Essington Ave",
    "sg:city":"Gray",
    "sg:classifiers":[
        {
            "category":"Utilities",
            "subcategory":"Electric",
            "type":"Services"
        }
    ],
    "sg:phone":"+61 8 8932 3777",
    "sg:postcode":"0830",
    "sg:province":"NT",
    "sg:tags":[
        "electrical",
        "contractor"
    ],
    "wof:name":"Falcon Electrical Services",
    "wof:placetype":"venue"
},
  "geometry": {"coordinates":[130.982224,-12.490094],"type":"Point"}
}