{
  "type": "Feature",
  "properties": {
    "iso:country":"AU",
    "sg:address":"8 Phillimore St",
    "sg:city":"Fremantle",
    "sg:classifiers":[
        {
            "category":"Education",
            "subcategory":"University",
            "type":"Public Place"
        }
    ],
    "sg:phone":"+61 8 9335 8366",
    "sg:postcode":"6160",
    "sg:province":"WA",
    "sg:tags":[
        "educational",
        "organisation",
        "cultural"
    ],
    "wof:name":"Artists Foundation Of WA",
    "wof:placetype":"venue"
},
  "geometry": {"coordinates":[115.74252300000001,-32.054653],"type":"Point"}
}