{
  "type": "Feature",
  "properties": {
    "addr:full":"Railway Rd West Wyalong NSW 2671",
    "addr:postcode":"2671",
    "addr:street":"Railway Rd",
    "iso:country":"AU",
    "sg:address":"Railway Rd",
    "sg:city":"West Wyalong",
    "sg:classifiers":[
        {
            "category":"Wholesale",
            "subcategory":"Machinery & Supplies",
            "type":"Manufacturing & Wholesale Goods"
        }
    ],
    "sg:phone":"+61 2 6972 2699",
    "sg:postcode":"2671",
    "sg:province":"NSW",
    "sg:tags":[
        "agricultural"
    ],
    "wof:name":"V & L Machinery",
    "wof:placetype":"venue"
},
  "geometry": {"coordinates":[147.20506286599999,-33.9274406433],"type":"Point"}
}