{
  "type": "Feature",
  "properties": {
    "addr:full":"7 Crowley St Port Kennedy Warnbro WA 6169",
    "addr:housenumber":"7",
    "addr:postcode":"6169",
    "addr:street":"Crowley St",
    "iso:country":"AU",
    "sg:address":"7 Crowley St Port Kennedy",
    "sg:city":"Warnbro",
    "sg:classifiers":[
        {
            "category":"Home & Garden",
            "subcategory":"Building Materials",
            "type":"Retail Goods"
        }
    ],
    "sg:phone":"+61 8 9524 6575",
    "sg:postcode":"6169",
    "sg:province":"WA",
    "sg:tags":[
        "fitting",
        "door"
    ],
    "wof:name":"Albany Nomafa",
    "wof:placetype":"venue"
},
  "geometry": {"coordinates":[115.75865899999999,-32.366531],"type":"Point"}
}