{
  "type": "Feature",
  "properties": {
    "iso:country":"AU",
    "sg:address":"71 Kensington Rd",
    "sg:city":"Norwood",
    "sg:classifiers":[
        {
            "category":"Professional",
            "subcategory":"Accounting & Tax Preparation",
            "type":"Services"
        }
    ],
    "sg:phone":"+61 8 8332 2150",
    "sg:postcode":"5067",
    "sg:province":"SA",
    "sg:tags":[
        "accountant",
        "auditor"
    ],
    "wof:name":"Inglis Donald J",
    "wof:placetype":"venue"
},
  "geometry": {"coordinates":[138.63203430199999,-34.927532196],"type":"Point"}
}