{
  "type": "Feature",
  "properties": {
    "addr:full":"Shauna Downs Centre Shop 3 - 18 Wynne St Sunnybank Hills QLD 4109",
    "addr:housenumber":"shop 3 18",
    "addr:postcode":"4109",
    "addr:street":"Wynne St",
    "iso:country":"AU",
    "sg:address":"Shauna Downs Centre Shop 3 - 18 Wynne St",
    "sg:city":"Sunnybank Hills",
    "sg:classifiers":[
        {
            "category":"Food & Beverages",
            "subcategory":"Liquor & Beverages",
            "type":"Retail Goods"
        }
    ],
    "sg:phone":"+61 7 3344 7495",
    "sg:postcode":"4109",
    "sg:province":"QLD",
    "sg:tags":[
        "store"
    ],
    "wof:name":"Liquor King",
    "wof:placetype":"venue"
},
  "geometry": {"coordinates":[153.05726623499999,-27.5866069794],"type":"Point"}
}