{
  "type": "Feature",
  "properties": {
    "iso:country":"AU",
    "sg:address":"180 Ruthven St",
    "sg:city":"Toowoomba",
    "sg:classifiers":[
        {
            "category":"Professional",
            "subcategory":"Employment Agencies",
            "type":"Services"
        }
    ],
    "sg:phone":"+61 7 4659 9777",
    "sg:postcode":"4350",
    "sg:province":"QLD",
    "sg:tags":[
        "provider",
        "internet"
    ],
    "wof:name":"I.T. Works",
    "wof:placetype":"venue"
},
  "geometry": {"coordinates":[151.95190400000001,-27.569506],"type":"Point"}
}