{
  "type": "Feature",
  "properties": {
    "addr:full":"60 Warburton St North Ward QLD 4810",
    "addr:housenumber":"60",
    "addr:postcode":"4810",
    "addr:street":"Warburton St",
    "iso:country":"AU",
    "sg:address":"60 Warburton St",
    "sg:city":"North Ward",
    "sg:classifiers":[
        {
            "category":"Professional",
            "subcategory":"Research",
            "type":"Services"
        }
    ],
    "sg:phone":"+61 7 4772 5226",
    "sg:postcode":"4810",
    "sg:province":"QLD",
    "sg:tags":[
        "market"
    ],
    "wof:name":"North Queensland Consultancy",
    "wof:placetype":"venue"
},
  "geometry": {"coordinates":[146.80879200000001,-19.249193],"type":"Point"}
}