{
  "type": "Feature",
  "properties": {
    "addr:full":"40- 42 Rowan St Wangaratta VIC 3677",
    "addr:housenumber":"42",
    "addr:postcode":"3677",
    "addr:street":"Rowan St",
    "iso:country":"AU",
    "sg:address":"40- 42 Rowan St",
    "sg:city":"Wangaratta",
    "sg:classifiers":[
        {
            "category":"Professional",
            "subcategory":"Employment Agencies",
            "type":"Services"
        }
    ],
    "sg:phone":"+61 3 5722 8000",
    "sg:postcode":"3677",
    "sg:province":"VIC",
    "wof:name":"Hume Employment Service Limited",
    "wof:placetype":"venue"
},
  "geometry": {"coordinates":[146.321166992,-36.3523445129],"type":"Point"}
}