{
  "type": "Feature",
  "properties": {
    "iso:country":"AU",
    "sg:address":"589 Military Rd",
    "sg:city":"Mosman",
    "sg:classifiers":[
        {
            "category":"Shopping",
            "subcategory":"Music",
            "type":"Retail Goods"
        }
    ],
    "sg:phone":"+61 2 9969 8736",
    "sg:postcode":"2088",
    "sg:province":"NSW",
    "sg:tags":[
        "store"
    ],
    "wof:name":"Leading Edge Music",
    "wof:placetype":"venue"
},
  "geometry": {"coordinates":[151.24176025400001,-33.8250350952],"type":"Point"}
}