{
  "type": "Feature",
  "properties": {
    "iso:country":"AU",
    "sg:address":"610 Darling St",
    "sg:city":"Balmain",
    "sg:classifiers":[
        {
            "category":"Real Estate",
            "subcategory":"Real Estate Agent",
            "type":"Services"
        }
    ],
    "sg:phone":"+61 2 9810 3422",
    "sg:postcode":"2041",
    "sg:province":"NSW",
    "wof:name":"Ray White Commercial Inner West",
    "wof:placetype":"venue"
},
  "geometry": {"coordinates":[151.171402,-33.861851],"type":"Point"}
}