{
  "type": "Feature",
  "properties": {
    "addr:full":"139 Princes Hwy Unanderra NSW 2526",
    "addr:housenumber":"139",
    "addr:postcode":"2526",
    "addr:street":"Princes Hwy",
    "iso:country":"AU",
    "sg:address":"139 Princes Hwy",
    "sg:city":"Unanderra",
    "sg:classifiers":[
        {
            "category":"Retail",
            "subcategory":"Laundry & Dry Cleaning",
            "type":"Services"
        }
    ],
    "sg:phone":"+61 2 4272 1031",
    "sg:postcode":"2526",
    "sg:province":"NSW",
    "sg:tags":[
        "manicurist"
    ],
    "wof:name":"Sweet Serenity Beauty",
    "wof:placetype":"venue"
},
  "geometry": {"coordinates":[150.84442138700001,-34.4555740356],"type":"Point"}
}