{
  "type": "Feature",
  "properties": {
    "addr:full":"51 Yeo St Neutral Bay NSW 2089",
    "addr:housenumber":"51",
    "addr:postcode":"2089",
    "addr:street":"Yeo St",
    "iso:country":"AU",
    "sg:address":"51 Yeo St",
    "sg:city":"Neutral Bay",
    "sg:classifiers":[
        {
            "category":"Health Services",
            "subcategory":"Health Practitioner",
            "type":"Services"
        }
    ],
    "sg:phone":"+61 2 9953 2903",
    "sg:postcode":"2089",
    "sg:province":"NSW",
    "sg:tags":[
        "physiotherapist"
    ],
    "wof:name":"North Shore Pelvic Floor Centre",
    "wof:placetype":"venue"
},
  "geometry": {"coordinates":[151.221603394,-33.8323287964],"type":"Point"}
}