{
  "type": "Feature",
  "properties": {
    "addr:full":"Old Maitland Rd Mardi NSW 2259",
    "addr:postcode":"2259",
    "addr:street":"Maitland Rd",
    "iso:country":"AU",
    "sg:address":"Old Maitland Rd",
    "sg:city":"Mardi",
    "sg:classifiers":[
        {
            "category":"Building & Trades",
            "subcategory":"Construction",
            "type":"Services"
        }
    ],
    "sg:phone":"+61 414 767 642",
    "sg:postcode":"2259",
    "sg:province":"NSW",
    "sg:tags":[
        "contractor"
    ],
    "wof:name":"Parkinson Constructions Pty Ltd",
    "wof:placetype":"venue"
},
  "geometry": {"coordinates":[151.39938354500001,-33.3064880371],"type":"Point"}
}