{
  "type": "Feature",
  "properties": {
    "addr:full":"Great Eastern Hwy Carrabin WA 6423",
    "addr:postcode":"6423",
    "addr:street":"Eastern Hwy",
    "iso:country":"AU",
    "sg:address":"Great Eastern Hwy",
    "sg:city":"Carrabin",
    "sg:classifiers":[
        {
            "category":"Travel",
            "subcategory":"Hotels & Motels",
            "type":"Entertainment"
        }
    ],
    "sg:phone":"+61 8 9046 7162",
    "sg:postcode":"6423",
    "sg:province":"WA",
    "wof:name":"Carrabin Roadhouse Motel",
    "wof:placetype":"venue"
},
  "geometry": {"coordinates":[118.678192,-31.378407],"type":"Point"}
}