{
  "type": "Feature",
  "properties": {
    "addr:full":"Mitchell Rd Alexandria NSW 2015",
    "addr:postcode":"2015",
    "addr:street":"Mitchell Rd",
    "iso:country":"AU",
    "sg:address":"Mitchell Rd",
    "sg:city":"Alexandria",
    "sg:classifiers":[
        {
            "category":"Education",
            "subcategory":"School",
            "type":"Public Place"
        }
    ],
    "sg:phone":"+61 2 9557 1101",
    "sg:postcode":"2015",
    "sg:province":"NSW",
    "sg:tags":[
        "state",
        "-",
        "nsw"
    ],
    "wof:name":"Alexandria Public School",
    "wof:placetype":"venue"
},
  "geometry": {"coordinates":[151.18728637699999,-33.9075546265],"type":"Point"}
}