{
  "type": "Feature",
  "properties": {
    "iso:country":"AU",
    "sg:address":"175-177 Pakington St",
    "sg:city":"Geelong West",
    "sg:classifiers":[
        {
            "category":"Wholesale",
            "subcategory":"Medical Equipment & Supplies",
            "type":"Manufacturing & Wholesale Goods"
        }
    ],
    "sg:phone":"+61 3 5229 1058",
    "sg:postcode":"3218",
    "sg:province":"VIC",
    "sg:tags":[
        "aid",
        "care",
        "health",
        "home"
    ],
    "wof:name":"Geelong West Pharmacy",
    "wof:placetype":"venue"
},
  "geometry": {"coordinates":[144.34788513199999,-38.1420516968],"type":"Point"}
}