{
  "type": "Feature",
  "properties": {
    "addr:full":"4 Hodson Ave Wagga Wagga NSW 2650",
    "addr:housenumber":"4",
    "addr:postcode":"2650",
    "addr:street":"Hodson Ave",
    "iso:country":"AU",
    "sg:address":"4 Hodson Ave",
    "sg:city":"Wagga Wagga",
    "sg:classifiers":[
        {
            "category":"Professional",
            "subcategory":"Management & Consulting",
            "type":"Services"
        }
    ],
    "sg:phone":"+61 402 107 790",
    "sg:postcode":"2650",
    "sg:province":"NSW",
    "sg:tags":[
        "consultant",
        "energy"
    ],
    "wof:name":"Residential Energy Ratings Mark Nye",
    "wof:placetype":"venue"
},
  "geometry": {"coordinates":[147.352783203,-35.0700149536],"type":"Point"}
}