{
  "type": "Feature",
  "properties": {
    "addr:full":"30 Redfern St North Perth WA 6006",
    "addr:housenumber":"30",
    "addr:postcode":"6006",
    "addr:street":"Redfern St",
    "iso:country":"AU",
    "sg:address":"30 Redfern St",
    "sg:city":"North Perth",
    "sg:classifiers":[
        {
            "category":"Social Services",
            "subcategory":"Adult Care",
            "type":"Services"
        }
    ],
    "sg:phone":"+61 8 9444 9806",
    "sg:postcode":"6006",
    "sg:province":"WA",
    "sg:tags":[
        "aged"
    ],
    "wof:name":"Box&#039;n&#039;Dice Activity Resources",
    "wof:placetype":"venue"
},
  "geometry": {"coordinates":[115.85562133800001,-31.9223251343],"type":"Point"}
}