{
  "type": "Feature",
  "properties": {
    "addr:full":"Seaforth Medical Centre, 602 Sydney Rd Seaforth NSW 2092",
    "addr:housenumber":"602",
    "addr:postcode":"2092",
    "addr:street":"Sydney Rd",
    "iso:country":"AU",
    "sg:address":"Seaforth Medical Centre, 602 Sydney Rd",
    "sg:city":"Seaforth",
    "sg:classifiers":[
        {
            "category":"Health Services",
            "subcategory":"Dentist",
            "type":"Services"
        }
    ],
    "sg:phone":"+61 2 9948 2881",
    "sg:postcode":"2092",
    "sg:province":"NSW",
    "wof:name":"Morrow Peter F",
    "wof:placetype":"venue"
},
  "geometry": {"coordinates":[151.24928283700001,-33.7976570129],"type":"Point"}
}