{
  "type": "Feature",
  "properties": {
    "iso:country":"AU",
    "sg:address":"Lot 1 Dowerin Kalannie Rd",
    "sg:city":"Burakin",
    "sg:classifiers":[
        {
            "category":"Farming",
            "subcategory":"Livestock Farm",
            "type":"Manufacturing & Wholesale Goods"
        }
    ],
    "sg:phone":"+61 8 9675 1048",
    "sg:postcode":"6467",
    "sg:province":"WA",
    "sg:tags":[
        "feedlot"
    ],
    "wof:name":"Westbeef",
    "wof:placetype":"venue"
},
  "geometry": {"coordinates":[117.159851074,-30.4546604156],"type":"Point"}
}