{
  "type": "Feature",
  "properties": {
    "addr:full":"High St Parachilna SA 5730",
    "addr:postcode":"5730",
    "addr:street":"High St",
    "iso:country":"AU",
    "sg:address":"High St",
    "sg:city":"Parachilna",
    "sg:classifiers":[
        {
            "category":"Travel",
            "subcategory":"Hotels & Motels",
            "type":"Entertainment"
        }
    ],
    "sg:phone":"+61 8 8648 4844",
    "sg:postcode":"5730",
    "sg:province":"SA",
    "wof:name":"Prairie Hotel",
    "wof:placetype":"venue"
},
  "geometry": {"coordinates":[138.396194458,-31.13331604],"type":"Point"}
}