{
  "type": "Feature",
  "properties": {
    "iso:country":"AU",
    "sg:address":"8 Short St",
    "sg:city":"Bundamba",
    "sg:classifiers":[
        {
            "category":"Autos & Motor Vehicles",
            "subcategory":"Auto Supplies",
            "type":"Retail Goods"
        }
    ],
    "sg:phone":"+61 7 3282 6111",
    "sg:postcode":"4304",
    "sg:province":"QLD",
    "sg:tags":[
        "accessory"
    ],
    "wof:name":"FBI Spoilers & Kits",
    "wof:placetype":"venue"
},
  "geometry": {"coordinates":[152.80824279800001,-27.6085186005],"type":"Point"}
}