{
  "type": "Feature",
  "properties": {
    "addr:full":"Unit 3 22 Johnstone St Guildford NSW 2161",
    "addr:housenumber":"22",
    "addr:postcode":"2161",
    "addr:street":"Johnstone St",
    "iso:country":"AU",
    "sg:address":"Unit 3 22 Johnstone St",
    "sg:city":"Guildford",
    "sg:classifiers":[
        {
            "category":"Building & Trades",
            "subcategory":"Construction",
            "type":"Services"
        }
    ],
    "sg:phone":"+61 2 9632 3578",
    "sg:postcode":"2161",
    "sg:province":"NSW",
    "sg:tags":[
        "polishing",
        "sanding",
        "floor"
    ],
    "wof:name":"Murray's Floorsanding",
    "wof:placetype":"venue"
},
  "geometry": {"coordinates":[150.968353272,-33.8532333374],"type":"Point"}
}