{
  "type": "Feature",
  "properties": {
    "iso:country":"AU",
    "sg:address":"1/ 126 Best St",
    "sg:city":"Devonport",
    "sg:classifiers":[
        {
            "category":"Personal",
            "subcategory":"Beauty Salon",
            "type":"Services"
        }
    ],
    "sg:phone":"+61 3 6424 1088",
    "sg:postcode":"7310",
    "sg:province":"TAS",
    "sg:tags":[
        "hairdresser"
    ],
    "wof:name":"Barber Shop The",
    "wof:placetype":"venue"
},
  "geometry": {"coordinates":[146.35069274899999,-41.1768379211],"type":"Point"}
}