{
  "type": "Feature",
  "properties": {
    "addr:full":"84 Perouse Rd Randwick NSW 2031",
    "addr:housenumber":"84",
    "addr:postcode":"2031",
    "addr:street":"Perouse Rd",
    "iso:country":"AU",
    "sg:address":"84 Perouse Rd",
    "sg:city":"Randwick",
    "sg:classifiers":[
        {
            "category":"Education",
            "subcategory":"Kindergarten",
            "type":"Public Place"
        }
    ],
    "sg:phone":"+61 2 9399 8265",
    "sg:postcode":"2031",
    "sg:province":"NSW",
    "sg:tags":[
        "pre-schools"
    ],
    "wof:name":"Spot Pre-School",
    "wof:placetype":"venue"
},
  "geometry": {"coordinates":[151.24296569800001,-33.9215087891],"type":"Point"}
}