{
  "type": "Feature",
  "properties": {
    "iso:country":"AU",
    "sg:address":"Bridges Reserve Bell St",
    "sg:city":"Coburg",
    "sg:classifiers":[
        {
            "category":"Sports & Exercise",
            "subcategory":"Gym",
            "type":"Entertainment"
        }
    ],
    "sg:phone":"+61 3 9354 3504",
    "sg:postcode":"3058",
    "sg:province":"VIC",
    "sg:tags":[
        "health",
        "fitness"
    ],
    "wof:name":"Coburg Leisure Centre",
    "wof:placetype":"venue"
},
  "geometry": {"coordinates":[144.96759033199999,-37.7414207458],"type":"Point"}
}