{
  "type": "Feature",
  "properties": {
    "addr:full":"20 Fyfes Rd Bears Lagoon VIC 3517",
    "addr:housenumber":"20",
    "addr:postcode":"3517",
    "addr:street":"Fyfes Rd",
    "iso:country":"AU",
    "sg:address":"20 Fyfes Rd",
    "sg:city":"Bears Lagoon",
    "sg:classifiers":[
        {
            "category":"Retail",
            "subcategory":"Auto Repair",
            "type":"Services"
        }
    ],
    "sg:phone":"+61 3 5437 9248",
    "sg:postcode":"3517",
    "sg:province":"VIC",
    "sg:tags":[
        "repairer",
        "motor",
        "engineer"
    ],
    "wof:name":"Bears Lagoon Garage",
    "wof:placetype":"venue"
},
  "geometry": {"coordinates":[143.96719400000001,-36.328754],"type":"Point"}
}