{
  "type": "Feature",
  "properties": {
    "addr:full":"2/51 Antram Ave Warilla NSW 2528",
    "addr:housenumber":"/ 51",
    "addr:postcode":"2528",
    "addr:street":"Antram Ave",
    "iso:country":"AU",
    "sg:address":"2/51 Antram Ave",
    "sg:city":"Warilla",
    "sg:classifiers":[
        {
            "category":"Utilities",
            "subcategory":"Water",
            "type":"Services"
        }
    ],
    "sg:phone":"+61 423 343 281",
    "sg:postcode":"2528",
    "sg:province":"NSW",
    "sg:tags":[
        "hot",
        "system"
    ],
    "wof:name":"I E Electrical",
    "wof:placetype":"venue"
},
  "geometry": {"coordinates":[150.85792541500001,-34.5572891235],"type":"Point"}
}