{
  "type": "Feature",
  "properties": {
    "addr:full":"232 Robinson Rd East Geebung QLD 4034",
    "addr:housenumber":"232",
    "addr:postcode":"4034",
    "addr:street":"Robinson Rd East",
    "iso:country":"AU",
    "sg:address":"232 Robinson Rd East",
    "sg:city":"Geebung",
    "sg:classifiers":[
        {
            "category":"Shopping",
            "type":"Retail Goods"
        }
    ],
    "sg:phone":"+61 7 3265 1277",
    "sg:postcode":"4034",
    "sg:province":"QLD",
    "sg:tags":[
        "product",
        "plastic"
    ],
    "wof:name":"APS",
    "wof:placetype":"venue"
},
  "geometry": {"coordinates":[153.05229199999999,-27.365145],"type":"Point"}
}