{
  "type": "Feature",
  "properties": {
    "addr:full":"Atticus St Woree QLD 4868",
    "addr:postcode":"4868",
    "addr:street":"St",
    "iso:country":"AU",
    "sg:address":"Atticus St",
    "sg:city":"Woree",
    "sg:classifiers":[
        {
            "category":"Manufacturing",
            "subcategory":"Tools & Machinery",
            "type":"Manufacturing & Wholesale Goods"
        }
    ],
    "sg:phone":"+61 1300 763 881",
    "sg:postcode":"4868",
    "sg:province":"QLD",
    "sg:tags":[
        "earth",
        "excavating",
        "moving",
        "equipment"
    ],
    "wof:name":"Lift And Shift Machinery Sales",
    "wof:placetype":"venue"
},
  "geometry": {"coordinates":[145.74888610799999,-16.9552650452],"type":"Point"}
}