{
  "type": "Feature",
  "properties": {
    "addr:full":"Highway Palms Shopping Centre Yamba Rd North Rockhampton QLD 4701",
    "addr:postcode":"4701",
    "addr:street":"Highway;Yamba Rd North",
    "iso:country":"AU",
    "sg:address":"Highway Palms Shopping Centre Yamba Rd",
    "sg:city":"North Rockhampton",
    "sg:classifiers":[
        {
            "category":"Fast Food",
            "type":"Food & Drink"
        }
    ],
    "sg:phone":"+61 7 4926 6188",
    "sg:postcode":"4701",
    "sg:province":"QLD",
    "sg:tags":[
        "away",
        "take"
    ],
    "wof:name":"Express Subs and Sushi",
    "wof:placetype":"venue"
},
  "geometry": {"coordinates":[150.54896545400001,-23.3510398865],"type":"Point"}
}