{
  "type": "Feature",
  "properties": {
    "addr:full":"62 Gray St Hamilton VIC 3300",
    "addr:housenumber":"62",
    "addr:postcode":"3300",
    "addr:street":"Gray St",
    "iso:country":"AU",
    "sg:address":"62 Gray St",
    "sg:city":"Hamilton",
    "sg:classifiers":[
        {
            "category":"Professional",
            "subcategory":"Accounting & Tax Preparation",
            "type":"Services"
        }
    ],
    "sg:phone":"+61 3 5571 9182",
    "sg:postcode":"3300",
    "sg:province":"VIC",
    "sg:tags":[
        "bookkeeping"
    ],
    "wof:name":"Get Smart IT",
    "wof:placetype":"venue"
},
  "geometry": {"coordinates":[142.02206420900001,-37.7445144653],"type":"Point"}
}