{
  "type": "Feature",
  "properties": {
    "addr:full":"Shop 12b, 120 Birkdale Rd Birkdale QLD 4159",
    "addr:housenumber":"12b",
    "addr:postcode":"120;4159",
    "addr:street":"Shop;Birkdale Rd",
    "iso:country":"AU",
    "sg:address":"Shop 12b, 120 Birkdale Rd",
    "sg:city":"Birkdale",
    "sg:classifiers":[
        {
            "category":"Personal",
            "subcategory":"Beauty Salon",
            "type":"Services"
        }
    ],
    "sg:phone":"+61 7 3822 2893",
    "sg:postcode":"4159",
    "sg:province":"QLD",
    "sg:tags":[
        "hairdresser"
    ],
    "wof:name":"I.C Stylz",
    "wof:placetype":"venue"
},
  "geometry": {"coordinates":[153.21072387699999,-27.5007686615],"type":"Point"}
}