{
  "type": "Feature",
  "properties": {
    "addr:full":"5/ 9 Armitage St Bongaree QLD 4507",
    "addr:housenumber":"/ 9",
    "addr:postcode":"4507",
    "addr:street":"Armitage St",
    "iso:country":"AU",
    "sg:address":"5/ 9 Armitage St",
    "sg:city":"Bongaree",
    "sg:classifiers":[
        {
            "category":"Farming",
            "subcategory":"Fish & Marine Products",
            "type":"Manufacturing & Wholesale Goods"
        }
    ],
    "sg:phone":"+61 7 3408 2844",
    "sg:postcode":"4507",
    "sg:province":"QLD",
    "sg:tags":[
        "supplier",
        "oyster",
        "farmer"
    ],
    "wof:name":"Toorbul Point Rock Oysters Pty Ltd",
    "wof:placetype":"venue"
},
  "geometry": {"coordinates":[153.18046569800001,-27.0773391724],"type":"Point"}
}