{
  "type": "Feature",
  "properties": {
    "iso:country":"AU",
    "sg:address":"44 Lucerne Crs",
    "sg:city":"Frankston",
    "sg:classifiers":[
        {
            "category":"Retail",
            "subcategory":"Driving School",
            "type":"Services"
        }
    ],
    "sg:phone":"+61 3 5975 2715",
    "sg:postcode":"3199",
    "sg:province":"VIC",
    "wof:name":"The Rover School Of Motoring",
    "wof:placetype":"venue"
},
  "geometry": {"coordinates":[145.12179565400001,-38.1415710449],"type":"Point"}
}