{
  "type": "Feature",
  "properties": {
    "iso:country":"AU",
    "sg:address":"Ferguson St",
    "sg:city":"Canowindra",
    "sg:classifiers":[
        {
            "category":"Education",
            "subcategory":"Kindergarten",
            "type":"Public Place"
        }
    ],
    "sg:phone":"+61 2 6344 1261",
    "sg:postcode":"2804",
    "sg:province":"NSW",
    "sg:tags":[
        "pre-schools"
    ],
    "wof:name":"Canowindra Pre-School Kindergarten",
    "wof:placetype":"venue"
},
  "geometry": {"coordinates":[148.66522216800001,-33.5622215271],"type":"Point"}
}