{
  "type": "Feature",
  "properties": {
    "iso:country":"AU",
    "sg:address":"13 Kennion Crt",
    "sg:city":"Wynn Vale",
    "sg:classifiers":[
        {
            "category":"Utilities",
            "subcategory":"Telephone",
            "type":"Services"
        }
    ],
    "sg:phone":"+61 8 8289 4109",
    "sg:postcode":"5127",
    "sg:province":"SA",
    "sg:tags":[
        "installation",
        "system",
        "maintenance"
    ],
    "wof:name":"G D Communications",
    "wof:placetype":"venue"
},
  "geometry": {"coordinates":[138.68516540499999,-34.7943916321],"type":"Point"}
}