{
  "type": "Feature",
  "properties": {
    "addr:full":"170 Peachey Rd Davoren Park SA 5113",
    "addr:housenumber":"170",
    "addr:postcode":"5113",
    "addr:street":"Peachey Rd",
    "iso:country":"AU",
    "sg:address":"170 Peachey Rd",
    "sg:city":"Davoren Park",
    "sg:classifiers":[
        {
            "category":"Professional",
            "subcategory":"Art Services",
            "type":"Services"
        }
    ],
    "sg:phone":"+61 8 8254 8489",
    "sg:postcode":"5113",
    "sg:province":"SA",
    "sg:tags":[
        "decorator",
        "painter"
    ],
    "wof:name":"Park John",
    "wof:placetype":"venue"
},
  "geometry": {"coordinates":[138.66746520999999,-34.6935653687],"type":"Point"}
}