{
  "type": "Feature",
  "properties": {
    "addr:full":"12 Alfred St Gympie QLD 4570",
    "addr:housenumber":"12",
    "addr:postcode":"4570",
    "addr:street":"Alfred St",
    "iso:country":"AU",
    "sg:address":"12 Alfred St",
    "sg:city":"Gympie",
    "sg:classifiers":[
        {
            "category":"Organizations",
            "subcategory":"Non-profit Organization",
            "type":"Services"
        }
    ],
    "sg:phone":"+61 7 5482 5336",
    "sg:postcode":"4570",
    "sg:province":"QLD",
    "sg:tags":[
        "support",
        "disability",
        "organisation"
    ],
    "wof:name":"Bravo Disability Support Network",
    "wof:placetype":"venue"
},
  "geometry": {"coordinates":[152.66722106899999,-26.1963195801],"type":"Point"}
}