{
  "type": "Feature",
  "properties": {
    "addr:full":"189 East St Rockhampton QLD 4700",
    "addr:housenumber":"189",
    "addr:postcode":"4700",
    "addr:street":"East St",
    "iso:country":"AU",
    "sg:address":"189 East St",
    "sg:city":"Rockhampton",
    "sg:classifiers":[
        {
            "category":"Bars & Pubs",
            "subcategory":"Nightclub",
            "type":"Food & Drink"
        }
    ],
    "sg:phone":"+61 7 4922 5344",
    "sg:postcode":"4700",
    "sg:province":"QLD",
    "sg:tags":[
        "discotheque"
    ],
    "wof:name":"East Street Entertainment Centre",
    "wof:placetype":"venue"
},
  "geometry": {"coordinates":[150.52162170400001,-23.3895931244],"type":"Point"}
}