{
  "type": "Feature",
  "properties": {
    "addr:full":"450 C Fitzgerald St North Perth WA 6006",
    "addr:housenumber":"450",
    "addr:postcode":"6006",
    "addr:street":"C Fitzgerald St",
    "iso:country":"AU",
    "sg:address":"450 C Fitzgerald St",
    "sg:city":"North Perth",
    "sg:classifiers":[
        {
            "category":"Food & Beverages",
            "subcategory":"Specialty",
            "type":"Retail Goods"
        }
    ],
    "sg:phone":"+61 8 9328 2812",
    "sg:postcode":"6006",
    "sg:province":"WA",
    "sg:tags":[
        "delicacy"
    ],
    "wof:name":"Chilli & Spice & All Things Nice",
    "wof:placetype":"venue"
},
  "geometry": {"coordinates":[115.85925293,-31.9247207642],"type":"Point"}
}