{
  "type": "Feature",
  "properties": {
    "addr:full":"313 Bay St Brighton-le-Sands NSW 2216",
    "addr:housenumber":"313",
    "addr:postcode":"2216",
    "addr:street":"Bay St",
    "iso:country":"AU",
    "sg:address":"313 Bay St",
    "sg:city":"Brighton-le-Sands",
    "sg:classifiers":[
        {
            "category":"Education",
            "subcategory":"Vocational School",
            "type":"Public Place"
        }
    ],
    "sg:phone":"+61 2 9597 7080",
    "sg:postcode":"2216",
    "sg:province":"NSW",
    "sg:tags":[
        "cake",
        "decorating",
        "decorator"
    ],
    "wof:name":"Nicks Cake Shop Pty Ltd",
    "wof:placetype":"venue"
},
  "geometry": {"coordinates":[151.15426635700001,-33.9601860046],"type":"Point"}
}