{
  "type": "Feature",
  "properties": {
    "iso:country":"AU",
    "sg:address":"2 Glouster St",
    "sg:city":"Ormiston",
    "sg:classifiers":[
        {
            "category":"Professional",
            "subcategory":"Employment Agencies",
            "type":"Services"
        }
    ],
    "sg:phone":"+61 7 3286 3712",
    "sg:postcode":"4160",
    "sg:province":"QLD",
    "sg:tags":[
        "entertainer",
        "agent"
    ],
    "wof:name":"Cat & The Fiddle",
    "wof:placetype":"venue"
},
  "geometry": {"coordinates":[153.253051758,-27.5016918182],"type":"Point"}
}