{
  "type": "Feature",
  "properties": {
    "addr:full":"7 Hornby Rd Goodwood TAS 7010",
    "addr:housenumber":"7",
    "addr:postcode":"7010",
    "addr:street":"Hornby Rd",
    "iso:country":"AU",
    "sg:address":"7 Hornby Rd",
    "sg:city":"Goodwood",
    "sg:classifiers":[
        {
            "category":"Utilities",
            "subcategory":"Sewage",
            "type":"Services"
        }
    ],
    "sg:phone":"+61 3 6273 0755",
    "sg:postcode":"7010",
    "sg:province":"TAS",
    "sg:tags":[
        "water",
        "waste",
        "treatment"
    ],
    "sg:website":"http://www.envirocycle.com.au",
    "wof:name":"Envirocycle",
    "wof:placetype":"venue"
},
  "geometry": {"coordinates":[147.29800415,-42.8270301819],"type":"Point"}
}