{
  "type": "Feature",
  "properties": {
    "iso:country":"AU",
    "sg:address":"35 Augustus St",
    "sg:city":"Kingston",
    "sg:classifiers":[
        {
            "category":"Utilities",
            "subcategory":"Electric",
            "type":"Services"
        }
    ],
    "sg:phone":"+61 7 3209 4538",
    "sg:postcode":"4114",
    "sg:province":"QLD",
    "sg:tags":[
        "electrical",
        "contractor"
    ],
    "wof:name":"J & N McLean",
    "wof:placetype":"venue"
},
  "geometry": {"coordinates":[153.119308472,-27.6521263123],"type":"Point"}
}