{
  "type": "Feature",
  "properties": {
    "addr:full":"Shop 1, Victoria Cross Building 60 Miller St North Sydney NSW 2060",
    "addr:housenumber":"shop 1;60",
    "addr:postcode":"2060",
    "addr:street":"Miller St",
    "iso:country":"AU",
    "sg:address":"Shop 1, Victoria Cross Building 60 Miller St",
    "sg:city":"North Sydney",
    "sg:classifiers":[
        {
            "category":"Cafe",
            "type":"Food & Drink"
        }
    ],
    "sg:phone":"+61 2 9954 6697",
    "sg:postcode":"2060",
    "sg:province":"NSW",
    "wof:name":"Starbucks Coffee Company (Australia) Pty Ltd",
    "wof:placetype":"venue"
},
  "geometry": {"coordinates":[151.206665039,-33.839176178],"type":"Point"}
}