{
  "type": "Feature",
  "properties": {
    "addr:full":"Racecourse Rd Deagon QLD 4017",
    "addr:postcode":"4017",
    "addr:street":"Racecourse Rd",
    "iso:country":"AU",
    "sg:address":"Racecourse Rd",
    "sg:city":"Deagon",
    "sg:classifiers":[
        {
            "category":"Arena",
            "subcategory":"Sports Club",
            "type":"Entertainment"
        }
    ],
    "sg:phone":"+61 7 3869 0499",
    "sg:postcode":"4017",
    "sg:province":"QLD",
    "sg:tags":[
        "hunt",
        "racing"
    ],
    "wof:name":"QLD Owners & Breeders",
    "wof:placetype":"venue"
},
  "geometry": {"coordinates":[153.05801391599999,-27.3217258453],"type":"Point"}
}