{
  "type": "Feature",
  "properties": {
    "iso:country":"AU",
    "sg:address":"23 Belmore St",
    "sg:city":"Arncliffe",
    "sg:classifiers":[
        {
            "category":"Food & Beverages",
            "subcategory":"Fruits & Vegetables",
            "type":"Retail Goods"
        }
    ],
    "sg:phone":"+61 2 9567 1005",
    "sg:postcode":"2205",
    "sg:province":"NSW",
    "sg:tags":[
        "greengrocer",
        "fruiterer"
    ],
    "wof:name":"Arncliffe Fruit Market",
    "wof:placetype":"venue"
},
  "geometry": {"coordinates":[151.14584400000001,-33.935764],"type":"Point"}
}