{
  "type": "Feature",
  "properties": {
    "iso:country":"AU",
    "sg:address":"4 Sunnyside Rd",
    "sg:city":"Lindisfarne",
    "sg:classifiers":[
        {
            "category":"Professional",
            "subcategory":"Printing & Photocopies",
            "type":"Services"
        }
    ],
    "sg:phone":"+61 3 6243 6253",
    "sg:postcode":"7015",
    "sg:province":"TAS",
    "sg:tags":[
        "screen",
        "printer"
    ],
    "wof:name":"O.D. Prints",
    "wof:placetype":"venue"
},
  "geometry": {"coordinates":[147.358718872,-42.8532714844],"type":"Point"}
}