{
  "type": "Feature",
  "properties": {
    "addr:full":"21 Jackman St Greenock SA 5360",
    "addr:housenumber":"21",
    "addr:postcode":"5360",
    "addr:street":"Jackman St Greenock",
    "iso:country":"AU",
    "sg:address":"21 Jackman St",
    "sg:city":"Greenock",
    "sg:classifiers":[
        {
            "category":"Building & Trades",
            "subcategory":"Landscaping Services",
            "type":"Services"
        }
    ],
    "sg:phone":"+61 417 771 916",
    "sg:postcode":"5360",
    "sg:province":"SA",
    "sg:tags":[
        "designer",
        "landscape",
        "contractor"
    ],
    "wof:name":"T & P Bobcat Hire",
    "wof:placetype":"venue"
},
  "geometry": {"coordinates":[138.89671325699999,-34.4674491882],"type":"Point"}
}