{
  "type": "Feature",
  "properties": {
    "addr:full":"Shop 10 Kings Langley Town Centre Ravenhill St Kings Langley NSW 2147",
    "addr:housenumber":"shop 10",
    "addr:postcode":"2147",
    "addr:street":"Ravenhill St",
    "iso:country":"AU",
    "sg:address":"Shop 10 Kings Langley Town Centre Ravenhill St",
    "sg:city":"Kings Langley",
    "sg:classifiers":[
        {
            "category":"Banks & Credit Unions",
            "subcategory":"Bank",
            "type":"Services"
        }
    ],
    "sg:phone":"+61 2 9674 3400",
    "sg:postcode":"2147",
    "sg:province":"NSW",
    "wof:name":"Colonial",
    "wof:placetype":"venue"
},
  "geometry": {"coordinates":[150.922485352,-33.7427444458],"type":"Point"}
}