{
  "type": "Feature",
  "properties": {
    "addr:full":"47 Westerfield Drv Notting Hill VIC 3168",
    "addr:housenumber":"47",
    "addr:postcode":"3168",
    "addr:street":"Westerfield Drv",
    "iso:country":"AU",
    "sg:address":"47 Westerfield Drv",
    "sg:city":"Notting Hill",
    "sg:classifiers":[
        {
            "category":"Building & Trades",
            "subcategory":"Plumbing",
            "type":"Services"
        }
    ],
    "sg:phone":"+61 3 9545 3366",
    "sg:postcode":"3168",
    "sg:province":"VIC",
    "sg:tags":[
        "plumber",
        "gasfitters"
    ],
    "wof:name":"Lethlean Andrew",
    "wof:placetype":"venue"
},
  "geometry": {"coordinates":[145.14894104000001,-37.9066963196],"type":"Point"}
}