{
  "type": "Feature",
  "properties": {
    "addr:full":"419 Surf Edge Drv Golden Beach VIC 3851",
    "addr:housenumber":"419",
    "addr:postcode":"3851",
    "addr:street":"Surf Edge Drv",
    "iso:country":"AU",
    "sg:address":"419 Surf Edge Drv",
    "sg:city":"Golden Beach",
    "sg:classifiers":[
        {
            "category":"Real Estate",
            "subcategory":"Real Estate Agent",
            "type":"Services"
        }
    ],
    "sg:phone":"+61 3 5146 3473",
    "sg:postcode":"3851",
    "sg:province":"VIC",
    "wof:name":"90 Mile Beach Real Estate Pty Ltd",
    "wof:placetype":"venue"
},
  "geometry": {"coordinates":[147.403564453,-38.2091789246],"type":"Point"}
}