{
  "type": "Feature",
  "properties": {
    "iso:country":"AU",
    "sg:address":"Shop 12G 184 King St",
    "sg:city":"Melbourne",
    "sg:classifiers":[
        {
            "category":"Fast Food",
            "type":"Food & Drink"
        }
    ],
    "sg:phone":"+61 3 9642 4414",
    "sg:postcode":"3000",
    "sg:province":"VIC",
    "sg:tags":[
        "away",
        "take"
    ],
    "wof:name":"BBNT (Burgers, Burritos, Nachos & Tacos) King Street",
    "wof:placetype":"venue"
},
  "geometry": {"coordinates":[144.9556427,-37.815776825],"type":"Point"}
}