{
  "type": "Feature",
  "properties": {
    "addr:full":"10 Vincent St Marrickville NSW 2204",
    "addr:housenumber":"10",
    "addr:postcode":"2204",
    "addr:street":"Vincent St",
    "iso:country":"AU",
    "sg:address":"10 Vincent St",
    "sg:city":"Marrickville",
    "sg:classifiers":[
        {
            "category":"Wholesale",
            "subcategory":"Home Furnishings",
            "type":"Manufacturing & Wholesale Goods"
        }
    ],
    "sg:phone":"+61 2 8594 0700",
    "sg:postcode":"2204",
    "sg:province":"NSW",
    "sg:tags":[
        "wholesaler",
        "curtain",
        "mfrs"
    ],
    "wof:name":"Turner Bros Furnishings P/L",
    "wof:placetype":"venue"
},
  "geometry": {"coordinates":[151.163208,-33.911018],"type":"Point"}
}