{
  "type": "Feature",
  "properties": {
    "iso:country":"AU",
    "sg:address":"2a Wedge St",
    "sg:city":"Werribee",
    "sg:classifiers":[
        {
            "category":"Insurance",
            "subcategory":"Insurance Agent",
            "type":"Services"
        }
    ],
    "sg:phone":"+61 3 9974 9000",
    "sg:postcode":"3030",
    "sg:province":"VIC",
    "sg:tags":[
        "broker"
    ],
    "sg:website":"http://www.roderick.com.au",
    "wof:name":"Roderick Insurance Brokers Pty Ltd",
    "wof:placetype":"venue"
},
  "geometry": {"coordinates":[144.658096,-37.903519],"type":"Point"}
}