{
  "type": "Feature",
  "properties": {
    "addr:full":"930 Ipswich Rd Moorooka QLD 4105",
    "addr:housenumber":"930",
    "addr:postcode":"4105",
    "addr:street":"Ipswich Rd",
    "iso:country":"AU",
    "sg:address":"930 Ipswich Rd",
    "sg:city":"Moorooka",
    "sg:classifiers":[
        {
            "category":"Autos & Motor Vehicles",
            "subcategory":"Automobile Sales",
            "type":"Retail Goods"
        }
    ],
    "sg:phone":"+61 7 3848 7444",
    "sg:postcode":"4105",
    "sg:province":"QLD",
    "sg:tags":[
        "car",
        "used"
    ],
    "wof:name":"Nolan Car Centre",
    "wof:placetype":"venue"
},
  "geometry": {"coordinates":[153.02090454099999,-27.5275554657],"type":"Point"}
}