{
  "type": "Feature",
  "properties": {
    "addr:full":"10 Brannigan St Tully QLD 4854",
    "addr:housenumber":"10",
    "addr:postcode":"4854",
    "addr:street":"Brannigan St",
    "iso:country":"AU",
    "sg:address":"10 Brannigan St",
    "sg:city":"Tully",
    "sg:classifiers":[
        {
            "category":"Health Services",
            "subcategory":"Doctor",
            "type":"Services"
        }
    ],
    "sg:phone":"+61 7 4068 3666",
    "sg:postcode":"4854",
    "sg:province":"QLD",
    "sg:tags":[
        "medical",
        "practitioner"
    ],
    "wof:name":"Ken Stark Medical",
    "wof:placetype":"venue"
},
  "geometry": {"coordinates":[145.920944214,-17.932762146],"type":"Point"}
}