{
  "type": "Feature",
  "properties": {
    "addr:full":"67 Inkerman St St Kilda VIC 3182",
    "addr:housenumber":"67",
    "addr:postcode":"3182",
    "addr:street":"Inkerman St",
    "iso:country":"AU",
    "sg:address":"67 Inkerman St",
    "sg:city":"St Kilda",
    "sg:classifiers":[
        {
            "category":"Professional",
            "subcategory":"Computer Services",
            "type":"Services"
        }
    ],
    "sg:phone":"+61 3 9593 8311",
    "sg:postcode":"3182",
    "sg:province":"VIC",
    "sg:tags":[
        "repairs",
        "upgrade",
        "equipment"
    ],
    "wof:name":"D G L Mobile Computer Services",
    "wof:placetype":"venue"
},
  "geometry": {"coordinates":[144.984466553,-37.8645782471],"type":"Point"}
}