{
  "type": "Feature",
  "properties": {
    "addr:full":"124 Barry Pde Fortitude Valley QLD 4006",
    "addr:housenumber":"124",
    "addr:postcode":"4006",
    "addr:street":"Barry Pde",
    "iso:country":"AU",
    "sg:address":"124 Barry Pde",
    "sg:city":"Fortitude Valley",
    "sg:classifiers":[
        {
            "category":"Cafe",
            "type":"Food & Drink"
        }
    ],
    "sg:phone":"+61 7 3831 8281",
    "sg:postcode":"4006",
    "sg:province":"QLD",
    "wof:name":"Rosy Cafe",
    "wof:placetype":"venue"
},
  "geometry": {"coordinates":[153.03067016599999,-27.4595870972],"type":"Point"}
}