{
  "type": "Feature",
  "properties": {
    "iso:country":"AU",
    "sg:address":"114 Tambourine Bay Rd",
    "sg:city":"Lane Cove",
    "sg:classifiers":[
        {
            "category":"Building & Trades",
            "subcategory":"Construction",
            "type":"Services"
        }
    ],
    "sg:phone":"+61 2 9428 4505",
    "sg:postcode":"2066",
    "sg:province":"NSW",
    "sg:tags":[
        "contractor"
    ],
    "wof:name":"McNally T I Pty Ltd",
    "wof:placetype":"venue"
},
  "geometry": {"coordinates":[151.16021728499999,-33.8250961304],"type":"Point"}
}