{
  "type": "Feature",
  "properties": {
    "addr:full":"229 High St Kew VIC 3101",
    "addr:housenumber":"229",
    "addr:postcode":"3101",
    "addr:street":"High St",
    "iso:country":"AU",
    "sg:address":"229 High St",
    "sg:city":"Kew",
    "sg:classifiers":[
        {
            "category":"Restaurant",
            "type":"Food & Drink"
        }
    ],
    "sg:phone":"+61 3 9852 7788",
    "sg:postcode":"3101",
    "sg:province":"VIC",
    "wof:name":"Baraka",
    "wof:placetype":"venue"
},
  "geometry": {"coordinates":[145.03512573200001,-37.8050918579],"type":"Point"}
}