{
  "type": "Feature",
  "properties": {
    "addr:full":"1/ 7 Jannali Ave Jannali NSW 2226",
    "addr:housenumber":"/ 7",
    "addr:postcode":"2226",
    "addr:street":"Jannali Ave",
    "iso:country":"AU",
    "sg:address":"1/ 7 Jannali Ave",
    "sg:city":"Jannali",
    "sg:classifiers":[
        {
            "category":"Personal",
            "type":"Services"
        }
    ],
    "sg:phone":"+61 2 9589 4920",
    "sg:postcode":"2226",
    "sg:province":"NSW",
    "sg:tags":[
        "dressmaker"
    ],
    "wof:name":"A Magnolia Rose",
    "wof:placetype":"venue"
},
  "geometry": {"coordinates":[151.064178467,-34.0162734985],"type":"Point"}
}