{
  "type": "Feature",
  "properties": {
    "iso:country":"AU",
    "sg:address":"C/o Coles Express, 61- 65 Bryants Rd",
    "sg:city":"Loganholme",
    "sg:classifiers":[
        {
            "category":"Autos & Motor Vehicles",
            "subcategory":"Auto Supplies",
            "type":"Retail Goods"
        }
    ],
    "sg:phone":"+61 7 3209 6777",
    "sg:postcode":"4129",
    "sg:province":"QLD",
    "sg:tags":[
        "tyre"
    ],
    "wof:name":"Kmart Tyre & Auto Service",
    "wof:placetype":"venue"
},
  "geometry": {"coordinates":[153.17729187,-27.6631507874],"type":"Point"}
}