{
  "type": "Feature",
  "properties": {
    "addr:full":"Albion St Oberon NSW 2787",
    "addr:postcode":"2787",
    "addr:street":"Albion St",
    "iso:country":"AU",
    "sg:address":"Albion St",
    "sg:city":"Oberon",
    "sg:classifiers":[
        {
            "category":"Travel",
            "subcategory":"Hotels & Motels",
            "type":"Entertainment"
        }
    ],
    "sg:phone":"+61 411 955 616",
    "sg:postcode":"2787",
    "sg:province":"NSW",
    "wof:name":"Oberon Caravan Park",
    "wof:placetype":"venue"
},
  "geometry": {"coordinates":[149.868682861,-33.7002677917],"type":"Point"}
}