{
  "type": "Feature",
  "properties": {
    "iso:country":"AU",
    "sg:address":"22 Ridge St",
    "sg:city":"Nambucca Heads",
    "sg:classifiers":[
        {
            "category":"Health Services",
            "subcategory":"Doctor",
            "type":"Services"
        }
    ],
    "sg:phone":"+61 2 6568 7377",
    "sg:postcode":"2448",
    "sg:province":"NSW",
    "sg:tags":[
        "medical",
        "practitioner"
    ],
    "wof:name":"Warrier A & I",
    "wof:placetype":"venue"
},
  "geometry": {"coordinates":[153.003174,-30.64213],"type":"Point"}
}