{
  "type": "Feature",
  "properties": {
    "addr:full":"48 Emma St Cunnamulla QLD 4490",
    "addr:housenumber":"48",
    "addr:postcode":"4490",
    "addr:street":"Emma St",
    "iso:country":"AU",
    "sg:address":"48 Emma St",
    "sg:city":"Cunnamulla",
    "sg:classifiers":[
        {
            "category":"Retail",
            "subcategory":"Auto Repair",
            "type":"Services"
        }
    ],
    "sg:phone":"+61 7 4655 1476",
    "sg:postcode":"4490",
    "sg:province":"QLD",
    "sg:tags":[
        "beater",
        "painter",
        "panel"
    ],
    "wof:name":"Higgins Bros (Cunnamulla) Pty Ltd",
    "wof:placetype":"venue"
},
  "geometry": {"coordinates":[145.69142150900001,-28.0694656372],"type":"Point"}
}