{
  "type": "Feature",
  "properties": {
    "addr:full":"3 Thompson St Wallaroo SA 5556",
    "addr:housenumber":"3",
    "addr:postcode":"5556",
    "addr:street":"Thompson St",
    "iso:country":"AU",
    "sg:address":"3 Thompson St",
    "sg:city":"Wallaroo",
    "sg:classifiers":[
        {
            "category":"Communications",
            "subcategory":"Television Station",
            "type":"Services"
        }
    ],
    "sg:phone":"+61 8 8823 3175",
    "sg:postcode":"5556",
    "sg:province":"SA",
    "sg:tags":[
        "mfrs",
        "tank",
        "installation",
        "septic"
    ],
    "wof:name":"R A Grillett Plumbing Services",
    "wof:placetype":"venue"
},
  "geometry": {"coordinates":[137.642044067,-33.9363899231],"type":"Point"}
}