{
  "type": "Feature",
  "properties": {
    "iso:country":"AU",
    "sg:address":"150 Edgecliff Rd",
    "sg:city":"Woollahra",
    "sg:classifiers":[
        {
            "category":"Professional",
            "subcategory":"Art Services",
            "type":"Services"
        }
    ],
    "sg:phone":"+61 2 9389 9399",
    "sg:postcode":"2025",
    "sg:province":"NSW",
    "sg:tags":[
        "picture",
        "frame",
        "framing"
    ],
    "wof:name":"Graphis Art & Framing",
    "wof:placetype":"venue"
},
  "geometry": {"coordinates":[151.24203491200001,-33.8848152161],"type":"Point"}
}