{
  "type": "Feature",
  "properties": {
    "addr:full":"13 Wittenoom St Bunbury WA 6230",
    "addr:housenumber":"13",
    "addr:postcode":"6230",
    "addr:street":"Wittenoom St",
    "iso:country":"AU",
    "sg:address":"13 Wittenoom St",
    "sg:city":"Bunbury",
    "sg:classifiers":[
        {
            "category":"Professional",
            "subcategory":"Engineering",
            "type":"Services"
        }
    ],
    "sg:phone":"+61 8 9791 1834",
    "sg:postcode":"6230",
    "sg:province":"WA",
    "sg:tags":[
        "consulting",
        "engineer"
    ],
    "wof:name":"Civil & Structural Engineers",
    "wof:placetype":"venue"
},
  "geometry": {"coordinates":[115.635689,-33.321308],"type":"Point"}
}