{
  "type": "Feature",
  "properties": {
    "addr:full":"King William St Adelaide SA 5000",
    "addr:postcode":"5000",
    "addr:street":"King William St",
    "iso:country":"AU",
    "sg:address":"King William St",
    "sg:city":"Adelaide",
    "sg:classifiers":[
        {
            "category":"Sports & Exercise",
            "subcategory":"Gym",
            "type":"Entertainment"
        }
    ],
    "sg:phone":"+61 409 288 489",
    "sg:postcode":"5000",
    "sg:province":"SA",
    "sg:tags":[
        "health",
        "fitness"
    ],
    "wof:name":"EFM Health Clubs",
    "wof:placetype":"venue"
},
  "geometry": {"coordinates":[138.59982299800001,-34.9253387451],"type":"Point"}
}