{
  "type": "Feature",
  "properties": {
    "addr:full":"Shop 3 200 Bay St Port Melbourne VIC 3207",
    "addr:housenumber":"shop 3 200",
    "addr:postcode":"3207",
    "addr:street":"Bay St",
    "iso:country":"AU",
    "sg:address":"Shop 3 200 Bay St",
    "sg:city":"Port Melbourne",
    "sg:classifiers":[
        {
            "category":"Travel",
            "subcategory":"Travel Agent",
            "type":"Entertainment"
        }
    ],
    "sg:phone":"+61 13 18 66",
    "sg:postcode":"3207",
    "sg:province":"VIC",
    "sg:tags":[
        "consultant"
    ],
    "wof:name":"Flight Centre",
    "wof:placetype":"venue"
},
  "geometry": {"coordinates":[144.94198600000001,-37.839169],"type":"Point"}
}