{
  "type": "Feature",
  "properties": {
    "iso:country":"AU",
    "sg:address":"13 Sandra Pl",
    "sg:city":"Welshpool",
    "sg:classifiers":[
        {
            "category":"Building & Trades",
            "subcategory":"Plumbing",
            "type":"Services"
        }
    ],
    "sg:phone":"+61 8 9362 1022",
    "sg:postcode":"6106",
    "sg:province":"WA",
    "sg:tags":[
        "plumber",
        "gasfitters"
    ],
    "wof:name":"U.N. Plumbing",
    "wof:placetype":"venue"
},
  "geometry": {"coordinates":[115.9296875,-31.9830341339],"type":"Point"}
}