{
  "type": "Feature",
  "properties": {
    "addr:full":"2/ 10 Finlay St Frankston VIC 3199",
    "addr:housenumber":"/ 10",
    "addr:postcode":"3199",
    "addr:street":"Finlay St",
    "iso:country":"AU",
    "sg:address":"2/ 10 Finlay St",
    "sg:city":"Frankston",
    "sg:classifiers":[
        {
            "category":"Wholesale",
            "subcategory":"Medical Equipment & Supplies",
            "type":"Manufacturing & Wholesale Goods"
        }
    ],
    "sg:phone":"+61 3 9770 2307",
    "sg:postcode":"3199",
    "sg:province":"VIC",
    "sg:tags":[
        "aid",
        "care",
        "health",
        "home"
    ],
    "wof:name":"Better Health Victoria",
    "wof:placetype":"venue"
},
  "geometry": {"coordinates":[144.955932617,-37.84324646],"type":"Point"}
}