{
  "type": "Feature",
  "properties": {
    "addr:full":"15 Duffy St Epping VIC 3076",
    "addr:housenumber":"15",
    "addr:postcode":"3076",
    "addr:street":"Duffy St",
    "iso:country":"AU",
    "sg:address":"15 Duffy St",
    "sg:city":"Epping",
    "sg:classifiers":[
        {
            "category":"Building & Trades",
            "subcategory":"Construction",
            "type":"Services"
        }
    ],
    "sg:phone":"+61 3 9408 6095",
    "sg:postcode":"3076",
    "sg:province":"VIC",
    "sg:tags":[
        "earth",
        "excavating",
        "moving",
        "contractor"
    ],
    "wof:name":"Phiroma Excavations",
    "wof:placetype":"venue"
},
  "geometry": {"coordinates":[144.90060424800001,-37.7388267517],"type":"Point"}
}