{
  "type": "Feature",
  "properties": {
    "iso:country":"AU",
    "sg:address":"661 North Rd",
    "sg:city":"Ormond",
    "sg:classifiers":[
        {
            "category":"Food & Beverages",
            "subcategory":"Bakery",
            "type":"Retail Goods"
        }
    ],
    "sg:phone":"+61 3 9578 0881",
    "sg:postcode":"3204",
    "sg:province":"VIC",
    "sg:tags":[
        "cake",
        "shop",
        "pastry"
    ],
    "wof:name":"Cottage Cakes",
    "wof:placetype":"venue"
},
  "geometry": {"coordinates":[145.05299400000001,-37.905403],"type":"Point"}
}