{
  "type": "Feature",
  "properties": {
    "iso:country":"AU",
    "sg:address":"74 Goondoon St",
    "sg:city":"Gladstone",
    "sg:classifiers":[
        {
            "category":"Banks & Credit Unions",
            "subcategory":"Financial Services",
            "type":"Services"
        }
    ],
    "sg:phone":"+61 7 4972 4355",
    "sg:postcode":"4680",
    "sg:province":"QLD",
    "sg:tags":[
        "building",
        "society"
    ],
    "wof:name":"Bendigo Bank",
    "wof:placetype":"venue"
},
  "geometry": {"coordinates":[151.25498962399999,-23.8416690826],"type":"Point"}
}