{
  "type": "Feature",
  "properties": {
    "addr:full":"PO Box 531 Wahroonga NSW 2076",
    "addr:postcode":"2076",
    "iso:country":"AU",
    "sg:address":"PO Box 531",
    "sg:city":"Wahroonga",
    "sg:classifiers":[
        {
            "category":"Building & Trades",
            "subcategory":"Construction",
            "type":"Services"
        }
    ],
    "sg:phone":"+61 2 9489 2326",
    "sg:postcode":"2076",
    "sg:province":"NSW",
    "sg:tags":[
        "contractor"
    ],
    "wof:name":"Kirby Constructions",
    "wof:placetype":"venue"
},
  "geometry": {"coordinates":[151.12272644000001,-33.7176551819],"type":"Point"}
}