{
  "type": "Feature",
  "properties": {
    "iso:country":"AU",
    "sg:address":"22 Fennell St",
    "sg:city":"North Parramatta",
    "sg:classifiers":[
        {
            "category":"Professional",
            "subcategory":"Printing & Photocopies",
            "type":"Services"
        }
    ],
    "sg:phone":"+61 2 9630 2006",
    "sg:postcode":"2151",
    "sg:province":"NSW",
    "sg:tags":[
        "publishing",
        "desktop"
    ],
    "wof:name":"MACAXIS Computer Imaging",
    "wof:placetype":"venue"
},
  "geometry": {"coordinates":[151.00865173299999,-33.8058509827],"type":"Point"}
}