{
  "type": "Feature",
  "properties": {
    "addr:full":"48 Sharp St Cooma NSW 2630",
    "addr:housenumber":"48",
    "addr:postcode":"2630",
    "addr:street":"Sharp St",
    "iso:country":"AU",
    "sg:address":"48 Sharp St",
    "sg:city":"Cooma",
    "sg:classifiers":[
        {
            "category":"Retail",
            "subcategory":"Car Wash",
            "type":"Services"
        }
    ],
    "sg:phone":"+61 2 6452 4376",
    "sg:postcode":"2630",
    "sg:province":"NSW",
    "sg:tags":[
        "truck",
        "cleaning"
    ],
    "wof:name":"Alpine Car Detailing",
    "wof:placetype":"venue"
},
  "geometry": {"coordinates":[149.13409423799999,-36.2313766479],"type":"Point"}
}