{
  "type": "Feature",
  "properties": {
    "iso:country":"AU",
    "sg:address":"7 Cobram St",
    "sg:city":"Berrigan",
    "sg:classifiers":[
        {
            "category":"Government",
            "subcategory":"Fire Station",
            "type":"Public Place"
        }
    ],
    "sg:phone":"+61 3 5885 2107",
    "sg:postcode":"2712",
    "sg:province":"VIC",
    "sg:tags":[
        "brigade"
    ],
    "wof:name":"Berrigan Fire Brigade",
    "wof:placetype":"venue"
},
  "geometry": {"coordinates":[145.80870056099999,-35.6615257263],"type":"Point"}
}