{
  "type": "Feature",
  "properties": {
    "addr:full":"Shop 71 Tea Tree Plaza Modbury SA 5092",
    "addr:housenumber":"shop 71",
    "addr:postcode":"5092",
    "addr:street":"Tea Tree Plaza",
    "iso:country":"AU",
    "sg:address":"Shop 71 Tea Tree Plaza",
    "sg:city":"Modbury",
    "sg:classifiers":[
        {
            "category":"Ice Cream",
            "type":"Food & Drink"
        }
    ],
    "sg:phone":"+61 8 8395 5366",
    "sg:postcode":"5092",
    "sg:province":"SA",
    "sg:tags":[
        "specialised",
        "fitting",
        "lady",
        "wear"
    ],
    "wof:name":"1626",
    "wof:placetype":"venue"
},
  "geometry": {"coordinates":[138.69236755399999,-34.8331794739],"type":"Point"}
}