{
  "type": "Feature",
  "properties": {
    "addr:full":"92 Aerodrome Rd Maroochydore QLD 4558",
    "addr:housenumber":"92",
    "addr:postcode":"4558",
    "addr:street":"Aerodrome Rd",
    "iso:country":"AU",
    "sg:address":"92 Aerodrome Rd",
    "sg:city":"Maroochydore",
    "sg:classifiers":[
        {
            "category":"Retail",
            "subcategory":"Auto Rental",
            "type":"Services"
        }
    ],
    "sg:phone":"+61 7 5443 4318",
    "sg:postcode":"4558",
    "sg:province":"QLD",
    "sg:tags":[
        "car",
        "hire",
        "minibus"
    ],
    "sg:website":"http://www.networkrentals.com.au",
    "wof:name":"Network Car & Truck Rentals",
    "wof:placetype":"venue"
},
  "geometry": {"coordinates":[153.09614563,-26.6587600708],"type":"Point"}
}