{
  "type": "Feature",
  "properties": {
    "addr:full":"29 Broadway St Nedlands WA 6009",
    "addr:housenumber":"29",
    "addr:postcode":"6009",
    "addr:street":"Broadway St",
    "iso:country":"AU",
    "sg:address":"29 Broadway St",
    "sg:city":"Nedlands",
    "sg:classifiers":[
        {
            "category":"Deli",
            "type":"Food & Drink"
        }
    ],
    "sg:phone":"+61 8 9386 5016",
    "sg:postcode":"6009",
    "sg:province":"WA",
    "sg:tags":[
        "delicatessen"
    ],
    "wof:name":"Taste Bubbs At Kitchen Korner",
    "wof:placetype":"venue"
},
  "geometry": {"coordinates":[115.813957,-31.978203],"type":"Point"}
}