{
  "type": "Feature",
  "properties": {
    "addr:full":"Lvl 4/ 225 St Georges Tce Perth WA 6000",
    "addr:housenumber":"/ 225",
    "addr:postcode":"6000",
    "addr:street":"St Georges Tce",
    "iso:country":"AU",
    "sg:address":"Lvl 4/ 225 St",
    "sg:city":"Georges Tce Perth",
    "sg:classifiers":[
        {
            "category":"Professional",
            "subcategory":"Art Services",
            "type":"Services"
        }
    ],
    "sg:phone":"+61 8 9226 3566",
    "sg:postcode":"6000",
    "sg:province":"WA",
    "sg:tags":[
        "interior",
        "designer"
    ],
    "wof:name":"Anitma Design Group",
    "wof:placetype":"venue"
},
  "geometry": {"coordinates":[115.8516922,-31.9532432556],"type":"Point"}
}