{
  "type": "Feature",
  "properties": {
    "addr:full":"Cnr Joynton Ave & Epsom Rd Waterloo NSW 2017",
    "addr:postcode":"2017",
    "addr:street":"Cnr Joynton Ave & Epsom Rd",
    "iso:country":"AU",
    "sg:address":"Cnr Joynton Ave & Epsom Rd",
    "sg:city":"Waterloo",
    "sg:classifiers":[
        {
            "category":"Autos & Motor Vehicles",
            "subcategory":"Fuel & Gas Station",
            "type":"Retail Goods"
        }
    ],
    "sg:phone":"+61 2 9663 2020",
    "sg:postcode":"2017",
    "sg:province":"NSW",
    "wof:name":"Ampol",
    "wof:placetype":"venue"
},
  "geometry": {"coordinates":[151.20957946799999,-33.9038963318],"type":"Point"}
}