{
  "type": "Feature",
  "properties": {
    "addr:full":"96 High St Northcote VIC 3070",
    "addr:housenumber":"96",
    "addr:postcode":"3070",
    "addr:street":"High St",
    "iso:country":"AU",
    "sg:address":"96 High St",
    "sg:city":"Northcote",
    "sg:classifiers":[
        {
            "category":"Personal",
            "subcategory":"Massage",
            "type":"Services"
        }
    ],
    "sg:phone":"+61 418 548 026",
    "sg:postcode":"3070",
    "sg:province":"VIC",
    "sg:tags":[
        "therapy"
    ],
    "wof:name":"Aalive Natural Therapy",
    "wof:placetype":"venue"
},
  "geometry": {"coordinates":[144.99707000000001,-37.779846],"type":"Point"}
}