{
  "type": "Feature",
  "properties": {
    "addr:full":"73 Mackie Rd Mulgrave VIC 3170",
    "addr:housenumber":"73",
    "addr:postcode":"3170",
    "addr:street":"Mackie Rd",
    "iso:country":"AU",
    "sg:address":"73 Mackie Rd",
    "sg:city":"Mulgrave",
    "sg:classifiers":[
        {
            "category":"Arts & Performance",
            "subcategory":"Art Gallery",
            "type":"Entertainment"
        }
    ],
    "sg:phone":"+61 3 9561 7111",
    "sg:postcode":"3170",
    "sg:province":"VIC",
    "wof:name":"Mulgrave Art Gallery",
    "wof:placetype":"venue"
},
  "geometry": {"coordinates":[145.15834045400001,-37.925403595],"type":"Point"}
}