{
  "type": "Feature",
  "properties": {
    "iso:country":"AU",
    "sg:address":"83 Ware St",
    "sg:city":"Fairfield",
    "sg:classifiers":[
        {
            "category":"Shopping",
            "subcategory":"Clothing, Apparel, & Fashions",
            "type":"Retail Goods"
        }
    ],
    "sg:phone":"+61 2 9723 8058",
    "sg:postcode":"2165",
    "sg:province":"NSW",
    "sg:tags":[
        "recycled",
        "clothing"
    ],
    "wof:name":"Hot Vintage",
    "wof:placetype":"venue"
},
  "geometry": {"coordinates":[150.954467773,-33.8703384399],"type":"Point"}
}