{
  "type": "Feature",
  "properties": {
    "addr:full":"Cnr Flinders & Pulteney Sts Adelaide SA 5000",
    "addr:postcode":"5000",
    "addr:street":"Cnr Flinders &;Sts",
    "iso:country":"AU",
    "sg:address":"Cnr Flinders & Pulteney Sts",
    "sg:city":"Adelaide",
    "sg:classifiers":[
        {
            "category":"Autos & Motor Vehicles",
            "subcategory":"Auto Supplies",
            "type":"Retail Goods"
        }
    ],
    "sg:phone":"+61 8 8223 7388",
    "sg:postcode":"5000",
    "sg:province":"SA",
    "sg:tags":[
        "battery",
        "automotive"
    ],
    "wof:name":"Bob Jane T-Marts",
    "wof:placetype":"venue"
},
  "geometry": {"coordinates":[138.60093689000001,-34.9271087646],"type":"Point"}
}