{
  "type": "Feature",
  "properties": {
    "iso:country":"AU",
    "sg:address":"26 Sinclair Rd",
    "sg:city":"Bayswater",
    "sg:classifiers":[
        {
            "category":"Building & Trades",
            "subcategory":"Construction",
            "type":"Services"
        }
    ],
    "sg:phone":"+61 3 9720 8780",
    "sg:postcode":"3153",
    "sg:province":"VIC",
    "sg:tags":[
        "polishing",
        "sanding",
        "floor"
    ],
    "wof:name":"Carefree Floors",
    "wof:placetype":"venue"
},
  "geometry": {"coordinates":[145.27226257300001,-37.8508605957],"type":"Point"}
}