{
  "type": "Feature",
  "properties": {
    "iso:country":"AU",
    "sg:address":"65 Sidney Pl",
    "sg:city":"Caroline Springs",
    "sg:classifiers":[
        {
            "category":"Banks & Credit Unions",
            "subcategory":"Financial Services",
            "type":"Services"
        }
    ],
    "sg:phone":"+61 3 9363 8899",
    "sg:postcode":"3023",
    "sg:province":"VIC",
    "sg:tags":[
        "loan",
        "finance",
        "mortgage"
    ],
    "wof:name":"Home Loans Service Centre",
    "wof:placetype":"venue"
},
  "geometry": {"coordinates":[144.74144000000001,-37.754398],"type":"Point"}
}