{
  "type": "Feature",
  "properties": {
    "iso:country":"AU",
    "sg:address":"Shp18t/ 44 Pelican Waters Blv",
    "sg:city":"Pelican Waters",
    "sg:classifiers":[
        {
            "category":"Fast Food",
            "type":"Food & Drink"
        }
    ],
    "sg:phone":"+61 7 5439 7891",
    "sg:postcode":"4551",
    "sg:province":"QLD",
    "sg:tags":[
        "away",
        "take"
    ],
    "wof:name":"Pelican Waters Seafood",
    "wof:placetype":"venue"
},
  "geometry": {"coordinates":[153.10740661599999,-26.8328857422],"type":"Point"}
}