{
  "type": "Feature",
  "properties": {
    "addr:full":"102 Enterprise St Kunda Park QLD 4556",
    "addr:housenumber":"102",
    "addr:postcode":"4556",
    "addr:street":"Enterprise St",
    "iso:country":"AU",
    "sg:address":"102 Enterprise St",
    "sg:city":"Kunda Park",
    "sg:classifiers":[
        {
            "category":"Professional",
            "subcategory":"Engineering",
            "type":"Services"
        }
    ],
    "sg:phone":"+61 7 5456 1682",
    "sg:postcode":"4556",
    "sg:province":"QLD",
    "sg:tags":[
        "engineer",
        "toolmaker",
        "plastic"
    ],
    "wof:name":"Ashgrove Industries",
    "wof:placetype":"venue"
},
  "geometry": {"coordinates":[153.02964782699999,-26.666765213],"type":"Point"}
}