{
  "type": "Feature",
  "properties": {
    "addr:full":"Shp 2, 26 Baynes St Margate Beach QLD 4019",
    "addr:housenumber":"26",
    "addr:postcode":"4019",
    "addr:street":"Baynes St",
    "iso:country":"AU",
    "sg:address":"Shp 2, 26 Baynes St",
    "sg:city":"Margate Beach",
    "sg:classifiers":[
        {
            "category":"Shopping",
            "subcategory":"Clothing, Apparel, & Fashions",
            "type":"Retail Goods"
        }
    ],
    "sg:phone":"+61 7 3284 8666",
    "sg:postcode":"4019",
    "sg:province":"QLD",
    "sg:tags":[
        "recycled",
        "clothing"
    ],
    "wof:name":"Lifeline Clothing Shops",
    "wof:placetype":"venue"
},
  "geometry": {"coordinates":[153.108154297,-27.243812561],"type":"Point"}
}