{
  "type": "Feature",
  "properties": {
    "addr:full":"351 South Station Rd Ipswich QLD 4305",
    "addr:housenumber":"351",
    "addr:postcode":"4305",
    "addr:street":"South Station Rd",
    "iso:country":"AU",
    "sg:address":"351 South Station Rd",
    "sg:city":"Ipswich",
    "sg:classifiers":[
        {
            "category":"Building & Trades",
            "subcategory":"Cleaning & Sanitation",
            "type":"Services"
        }
    ],
    "sg:phone":"+61 416 190 827",
    "sg:postcode":"4305",
    "sg:province":"QLD",
    "sg:tags":[
        "chemical",
        "pressure",
        "steam",
        "contractor"
    ],
    "wof:name":"Ipswich High Pressure Cleaning",
    "wof:placetype":"venue"
},
  "geometry": {"coordinates":[152.788131714,-27.6188678741],"type":"Point"}
}