{
  "type": "Feature",
  "properties": {
    "addr:full":"20-30 Beauchamp St St Kyneton VIC 3444",
    "addr:housenumber":"20-30",
    "addr:postcode":"3444",
    "addr:street":"Beauchamp St St",
    "iso:country":"AU",
    "sg:address":"20-30 Beauchamp St St",
    "sg:city":"Kyneton",
    "sg:classifiers":[
        {
            "category":"Real Estate",
            "subcategory":"Real Estate Agent",
            "type":"Services"
        }
    ],
    "sg:phone":"+61 3 5422 1200",
    "sg:postcode":"3444",
    "sg:province":"VIC",
    "sg:tags":[
        "steel",
        "foundry",
        "iron"
    ],
    "wof:name":"Alan Beckwith Macbro Pty Ltd",
    "wof:placetype":"venue"
},
  "geometry": {"coordinates":[144.454147339,-37.242603302],"type":"Point"}
}