{
  "type": "Feature",
  "properties": {
    "iso:country":"AU",
    "sg:address":"Borilla St",
    "sg:city":"Emerald",
    "sg:classifiers":[
        {
            "category":"Airline",
            "type":"Transportation"
        }
    ],
    "sg:phone":"+61 7 4982 1133",
    "sg:postcode":"4720",
    "sg:province":"QLD",
    "sg:tags":[
        "agent"
    ],
    "wof:name":"Flight West Airlines",
    "wof:placetype":"venue"
},
  "geometry": {"coordinates":[148.161224,-23.526552],"type":"Point"}
}