{
  "type": "Feature",
  "properties": {
    "iso:country":"AU",
    "sg:address":"6 Sandra Crt",
    "sg:city":"Wheelers Hill",
    "sg:classifiers":[
        {
            "category":"Professional",
            "subcategory":"Credit Reporting & Collection",
            "type":"Services"
        }
    ],
    "sg:phone":"+61 3 9574 8860",
    "sg:postcode":"3150",
    "sg:province":"VIC",
    "sg:tags":[
        "management"
    ],
    "wof:name":"Pacific Business Information Services",
    "wof:placetype":"venue"
},
  "geometry": {"coordinates":[145.168502808,-37.9094963074],"type":"Point"}
}