{
  "type": "Feature",
  "properties": {
    "iso:country":"AU",
    "sg:address":"Shp12/ 1 William St",
    "sg:city":"Port Macquarie",
    "sg:classifiers":[
        {
            "category":"Real Estate",
            "subcategory":"Real Estate Agent",
            "type":"Services"
        }
    ],
    "sg:phone":"+61 2 6583 7308",
    "sg:postcode":"2444",
    "sg:province":"NSW",
    "wof:name":"Cool Change Realty",
    "wof:placetype":"venue"
},
  "geometry": {"coordinates":[152.904663,-31.431238],"type":"Point"}
}