{
  "type": "Feature",
  "properties": {
    "iso:country":"AU",
    "sg:address":"Flat AGW 63 Jackson Rd",
    "sg:city":"Karawara",
    "sg:classifiers":[
        {
            "category":"Education",
            "subcategory":"University",
            "type":"Public Place"
        }
    ],
    "sg:phone":"+61 8 9313 2015",
    "sg:postcode":"6152",
    "sg:province":"WA",
    "sg:tags":[
        "college",
        "tertiary"
    ],
    "wof:name":"Curtin Student Guild Housing",
    "wof:placetype":"venue"
},
  "geometry": {"coordinates":[115.876152,-32.005135],"type":"Point"}
}