{
  "type": "Feature",
  "properties": {
    "addr:full":"57 Brisbane St St Marys NSW 2760",
    "addr:housenumber":"57",
    "addr:postcode":"2760",
    "addr:street":"Brisbane St",
    "iso:country":"AU",
    "sg:address":"57 Brisbane St",
    "sg:city":"St Marys",
    "sg:classifiers":[
        {
            "category":"Education",
            "subcategory":"Kindergarten",
            "type":"Public Place"
        }
    ],
    "sg:phone":"+61 2 9623 4519",
    "sg:postcode":"2760",
    "sg:province":"NSW",
    "sg:tags":[
        "pre-schools"
    ],
    "wof:name":"Uniting Church Child Care Centres & Pre-School Kindergartens",
    "wof:placetype":"venue"
},
  "geometry": {"coordinates":[150.79255676299999,-33.7679367065],"type":"Point"}
}