{
  "type": "Feature",
  "properties": {
    "addr:full":"35 High St Glen Iris VIC 3146",
    "addr:housenumber":"35",
    "addr:postcode":"3146",
    "addr:street":"High St",
    "iso:country":"AU",
    "sg:address":"35 High St",
    "sg:city":"Glen Iris",
    "sg:classifiers":[
        {
            "category":"Organizations",
            "subcategory":"Non-profit Organization",
            "type":"Services"
        }
    ],
    "sg:phone":"+61 3 9885 0533",
    "sg:postcode":"3146",
    "sg:province":"VIC",
    "sg:tags":[
        "support",
        "disability",
        "organisation"
    ],
    "wof:name":"Autism Victoria",
    "wof:placetype":"venue"
},
  "geometry": {"coordinates":[145.06549072300001,-37.8616027832],"type":"Point"}
}