{
  "type": "Feature",
  "properties": {
    "iso:country":"AU",
    "sg:address":"9 Dawson St",
    "sg:city":"Bundaberg",
    "sg:classifiers":[
        {
            "category":"Utilities",
            "subcategory":"Electric",
            "type":"Services"
        }
    ],
    "sg:phone":"+61 7 4152 9833",
    "sg:postcode":"4670",
    "sg:province":"QLD",
    "sg:tags":[
        "electrical",
        "contractor"
    ],
    "wof:name":"Jorgensen Jeff",
    "wof:placetype":"venue"
},
  "geometry": {"coordinates":[152.375366211,-24.8585090637],"type":"Point"}
}