{
  "type": "Feature",
  "properties": {
    "iso:country":"AU",
    "sg:address":"17 Fleming St",
    "sg:city":"Brunswick West",
    "sg:classifiers":[
        {
            "category":"Social Services",
            "subcategory":"Retirement Home",
            "type":"Services"
        }
    ],
    "sg:phone":"+61 500 599 777",
    "sg:postcode":"3055",
    "sg:province":"VIC",
    "sg:tags":[
        "life",
        "coaching"
    ],
    "wof:name":"Mentors and Business Coaches International Pty Ltd",
    "wof:placetype":"venue"
},
  "geometry": {"coordinates":[144.94569397000001,-37.772567749],"type":"Point"}
}