{
  "type": "Feature",
  "properties": {
    "iso:country":"AU",
    "sg:address":"621 Ballarat Rd",
    "sg:city":"Albion",
    "sg:classifiers":[
        {
            "category":"Wholesale",
            "subcategory":"Metals & Minerals",
            "type":"Manufacturing & Wholesale Goods"
        }
    ],
    "sg:phone":"+61 3 9311 8333",
    "sg:postcode":"3020",
    "sg:province":"VIC",
    "sg:tags":[
        "steel",
        "merchant"
    ],
    "wof:name":"Ferrous Forgings Pty Ltd",
    "wof:placetype":"venue"
},
  "geometry": {"coordinates":[144.811646,-37.77528],"type":"Point"}
}