{
  "type": "Feature",
  "properties": {
    "addr:full":"PO Box 7162 Karingal Central 3199 Karingal Centre VIC 3199",
    "addr:housenumber":"3199",
    "addr:postcode":"3199",
    "addr:street":"Central",
    "iso:country":"AU",
    "sg:address":"PO Box 7162 Karingal Central 3199",
    "sg:city":"Karingal Centre",
    "sg:classifiers":[
        {
            "category":"Professional",
            "subcategory":"Computer Services",
            "type":"Services"
        }
    ],
    "sg:phone":"+61 3 9776 7573",
    "sg:postcode":"3199",
    "sg:province":"VIC",
    "sg:tags":[
        "equipment",
        "networking",
        "installation"
    ],
    "wof:name":"Aabicon Computing Solutions Pty Ltd",
    "wof:placetype":"venue"
},
  "geometry": {"coordinates":[145.16229248100001,-38.1541557312],"type":"Point"}
}