{
  "type": "Feature",
  "properties": {
    "iso:country":"AU",
    "sg:address":"124 Coogee Bay Rd",
    "sg:city":"Coogee",
    "sg:classifiers":[
        {
            "category":"Personal",
            "subcategory":"Beauty Salon",
            "type":"Services"
        }
    ],
    "sg:phone":"+61 2 9664 1115",
    "sg:postcode":"2034",
    "sg:province":"NSW",
    "sg:tags":[
        "hairdresser"
    ],
    "wof:name":"Looking Even Better",
    "wof:placetype":"venue"
},
  "geometry": {"coordinates":[151.250488281,-33.919757843],"type":"Point"}
}