{
  "type": "Feature",
  "properties": {
    "iso:country":"AU",
    "sg:address":"Warburton Hwy",
    "sg:city":"Yarra Junction",
    "sg:classifiers":[
        {
            "category":"Sports & Exercise",
            "subcategory":"Gym",
            "type":"Entertainment"
        }
    ],
    "sg:phone":"+61 3 5967 1675",
    "sg:postcode":"3797",
    "sg:province":"VIC",
    "sg:tags":[
        "health",
        "fitness"
    ],
    "wof:name":"Yarra Recreation Centre",
    "wof:placetype":"venue"
},
  "geometry": {"coordinates":[145.612426758,-37.7815589905],"type":"Point"}
}