{
  "type": "Feature",
  "properties": {
    "iso:country":"AU",
    "sg:address":"111- 113 William Angliss Drv",
    "sg:city":"Laverton North",
    "sg:classifiers":[
        {
            "category":"Professional",
            "type":"Services"
        }
    ],
    "sg:phone":"+61 1300 306 830",
    "sg:postcode":"3026",
    "sg:province":"VIC",
    "sg:tags":[
        "control",
        "equipment",
        "traffic"
    ],
    "wof:name":"Workforce International",
    "wof:placetype":"venue"
},
  "geometry": {"coordinates":[144.781158,-37.816753],"type":"Point"}
}