{
  "type": "Feature",
  "properties": {
    "addr:full":"GPO Box 191 Shoreham VIC 3916",
    "addr:postcode":"3916",
    "iso:country":"AU",
    "sg:address":"GPO Box 191",
    "sg:city":"Shoreham",
    "sg:classifiers":[
        {
            "category":"Building & Trades",
            "subcategory":"Construction",
            "type":"Services"
        }
    ],
    "sg:phone":"+61 412 537 540",
    "sg:postcode":"3916",
    "sg:province":"VIC",
    "sg:tags":[
        "contractor"
    ],
    "wof:name":"Shoreham Building Services",
    "wof:placetype":"venue"
},
  "geometry": {"coordinates":[145.04161071799999,-38.4311103821],"type":"Point"}
}