{
  "type": "Feature",
  "properties": {
    "addr:full":"24 Harrington St Cabramatta NSW 2166",
    "addr:housenumber":"24",
    "addr:postcode":"2166",
    "addr:street":"Harrington St",
    "iso:country":"AU",
    "sg:address":"24 Harrington St",
    "sg:city":"Cabramatta",
    "sg:classifiers":[
        {
            "category":"Personal",
            "type":"Services"
        }
    ],
    "sg:phone":"+61 2 9725 3661",
    "sg:postcode":"2166",
    "sg:province":"NSW",
    "sg:tags":[
        "introduction",
        "social"
    ],
    "wof:name":"La Casa Matrimonial Agency",
    "wof:placetype":"venue"
},
  "geometry": {"coordinates":[150.91009521500001,-33.8885765076],"type":"Point"}
}