{
  "type": "Feature",
  "properties": {
    "iso:country":"AU",
    "sg:address":"Ladywood Clinic 184 Ladywood Rd",
    "sg:city":"Modbury Heights",
    "sg:classifiers":[
        {
            "category":"Health Services",
            "subcategory":"Doctor",
            "type":"Services"
        }
    ],
    "sg:phone":"+61 8 8263 6521",
    "sg:postcode":"5092",
    "sg:province":"SA",
    "sg:tags":[
        "medical",
        "practitioner"
    ],
    "wof:name":"Wakefield Inge Dr",
    "wof:placetype":"venue"
},
  "geometry": {"coordinates":[138.68597412099999,-34.8088645935],"type":"Point"}
}