{
  "type": "Feature",
  "properties": {
    "addr:full":"Kington St Minchinbury NSW 2770",
    "addr:postcode":"2770",
    "addr:street":"St",
    "iso:country":"AU",
    "sg:address":"Kington St",
    "sg:city":"Minchinbury",
    "sg:classifiers":[
        {
            "category":"Retail",
            "subcategory":"Funeral Services",
            "type":"Services"
        }
    ],
    "sg:phone":"+61 2 9625 8066",
    "sg:postcode":"2770",
    "sg:province":"NSW",
    "sg:tags":[
        "director"
    ],
    "wof:name":"Pinegrove Memorial Park",
    "wof:placetype":"venue"
},
  "geometry": {"coordinates":[150.84806823700001,-33.7878608704],"type":"Point"}
}