{
  "type": "Feature",
  "properties": {
    "addr:full":"11 Mason St Newport VIC 3015",
    "addr:housenumber":"11",
    "addr:postcode":"3015",
    "addr:street":"Mason St",
    "iso:country":"AU",
    "sg:address":"11 Mason St",
    "sg:city":"Newport",
    "sg:classifiers":[
        {
            "category":"Social Services",
            "subcategory":"Child Care",
            "type":"Services"
        }
    ],
    "sg:phone":"+61 3 9932 2070",
    "sg:postcode":"3015",
    "sg:province":"VIC",
    "sg:tags":[
        "support",
        "health"
    ],
    "wof:name":"Maternal & Child Health Centres",
    "wof:placetype":"venue"
},
  "geometry": {"coordinates":[144.881622314,-37.8425521851],"type":"Point"}
}