{
  "type": "Feature",
  "properties": {
    "iso:country":"AU",
    "sg:address":"710 Inkerman Rd",
    "sg:city":"Caulfield North",
    "sg:classifiers":[
        {
            "category":"Government",
            "subcategory":"Court House",
            "type":"Public Place"
        }
    ],
    "sg:phone":"+61 3 9576 0881",
    "sg:postcode":"3161",
    "sg:province":"VIC",
    "sg:tags":[
        "personal",
        "marriage",
        "family",
        "counselling"
    ],
    "wof:name":"Posen Les",
    "wof:placetype":"venue"
},
  "geometry": {"coordinates":[145.026412964,-37.8695755005],"type":"Point"}
}