{
  "type": "Feature",
  "properties": {
    "addr:full":"116 Eagle St Longreach QLD 4730",
    "addr:housenumber":"116",
    "addr:postcode":"4730",
    "addr:street":"Eagle St",
    "iso:country":"AU",
    "sg:address":"116 Eagle St",
    "sg:city":"Longreach",
    "sg:classifiers":[
        {
            "category":"Real Estate",
            "subcategory":"Real Estate Agent",
            "type":"Services"
        }
    ],
    "sg:phone":"+61 7 4658 0000",
    "sg:postcode":"4730",
    "sg:province":"QLD",
    "wof:name":"Ray White Rural Longreach",
    "wof:placetype":"venue"
},
  "geometry": {"coordinates":[144.24890099999999,-23.442532],"type":"Point"}
}