{
  "type": "Feature",
  "properties": {
    "addr:full":"Inchiquin Rd Clare SA 5453",
    "addr:postcode":"5453",
    "addr:street":"Inchiquin Rd",
    "iso:country":"AU",
    "sg:address":"Inchiquin Rd",
    "sg:city":"Clare",
    "sg:classifiers":[
        {
            "category":"Social Services",
            "subcategory":"Child Care",
            "type":"Services"
        }
    ],
    "sg:phone":"+61 8 8842 3551",
    "sg:postcode":"5453",
    "sg:province":"SA",
    "wof:name":"Family Day Care",
    "wof:placetype":"venue"
},
  "geometry": {"coordinates":[138.61077900000001,-33.83239],"type":"Point"}
}