{
  "type": "Feature",
  "properties": {
    "addr:full":"233 Berwick St Victoria Park WA 6100",
    "addr:housenumber":"233",
    "addr:postcode":"6100",
    "addr:street":"Berwick St",
    "iso:country":"AU",
    "sg:address":"233 Berwick St",
    "sg:city":"Victoria Park",
    "sg:classifiers":[
        {
            "category":"Communications",
            "type":"Services"
        }
    ],
    "sg:phone":"+61 8 9355 1638",
    "sg:postcode":"6100",
    "sg:province":"WA",
    "sg:tags":[
        "equipment",
        "radio"
    ],
    "wof:name":"Maxwell Electronics",
    "wof:placetype":"venue"
},
  "geometry": {"coordinates":[115.89437866199999,-31.9838619232],"type":"Point"}
}