{
  "type": "Feature",
  "properties": {
    "addr:full":"34 Goodhope St Paddington NSW 2021",
    "addr:housenumber":"34",
    "addr:postcode":"2021",
    "addr:street":"Goodhope St",
    "iso:country":"AU",
    "sg:address":"34 Goodhope St",
    "sg:city":"Paddington",
    "sg:classifiers":[
        {
            "category":"Real Estate",
            "subcategory":"Architect",
            "type":"Services"
        }
    ],
    "sg:phone":"+61 2 9361 0515",
    "sg:postcode":"2021",
    "sg:province":"NSW",
    "wof:name":"Robertson Ward Associates",
    "wof:placetype":"venue"
},
  "geometry": {"coordinates":[151.22830200199999,-33.8813819885],"type":"Point"}
}