{
  "type": "Feature",
  "properties": {
    "iso:country":"AU",
    "sg:address":"108 Acland St",
    "sg:city":"St Kilda South",
    "sg:classifiers":[
        {
            "category":"Banks & Credit Unions",
            "subcategory":"Bank",
            "type":"Services"
        }
    ],
    "sg:phone":"+61 13 25 75",
    "sg:postcode":"3182",
    "sg:province":"VIC",
    "wof:name":"Bank Of Melbourne",
    "wof:placetype":"venue"
},
  "geometry": {"coordinates":[144.97958374000001,-37.8681716919],"type":"Point"}
}