{
  "type": "Feature",
  "properties": {
    "addr:full":"Level 3, 504 Pacific Hwy St Leonards NSW 2065",
    "addr:housenumber":"504",
    "addr:postcode":"2065",
    "addr:street":"Pacific Hwy",
    "iso:country":"AU",
    "sg:address":"Level 3, 504 Pacific Hwy",
    "sg:city":"St Leonards",
    "sg:classifiers":[
        {
            "category":"Real Estate",
            "subcategory":"Real Estate Operator",
            "type":"Services"
        }
    ],
    "sg:phone":"+61 1800 666 113",
    "sg:postcode":"2065",
    "sg:province":"NSW",
    "sg:tags":[
        "building",
        "consultant",
        "management"
    ],
    "wof:name":"Sodexho Total Support Services",
    "wof:placetype":"venue"
},
  "geometry": {"coordinates":[151.19691467300001,-33.8237495422],"type":"Point"}
}