{
  "type": "Feature",
  "properties": {
    "addr:full":"538 Chapel St South Yarra VIC 3141",
    "addr:housenumber":"538",
    "addr:postcode":"3141",
    "addr:street":"Chapel St",
    "iso:country":"AU",
    "sg:address":"538 Chapel St",
    "sg:city":"South Yarra",
    "sg:classifiers":[
        {
            "category":"Shopping",
            "subcategory":"Clothing, Apparel, & Fashions",
            "type":"Retail Goods"
        }
    ],
    "sg:phone":"+61 3 9824 2937",
    "sg:postcode":"3141",
    "sg:province":"VIC",
    "sg:tags":[
        "menswear"
    ],
    "wof:name":"Saba- Men",
    "wof:placetype":"venue"
},
  "geometry": {"coordinates":[144.995437622,-37.8412971497],"type":"Point"}
}