{
  "type": "Feature",
  "properties": {
    "addr:full":"384 Beach Rd Batemans Bay NSW 2536",
    "addr:housenumber":"384",
    "addr:postcode":"2536",
    "addr:street":"Beach Rd",
    "iso:country":"AU",
    "sg:address":"384 Beach Rd",
    "sg:city":"Batemans Bay",
    "sg:classifiers":[
        {
            "category":"Travel",
            "subcategory":"Hotels & Motels",
            "type":"Entertainment"
        }
    ],
    "sg:phone":"+61 2 4472 4381",
    "sg:postcode":"2536",
    "sg:province":"NSW",
    "wof:name":"Edge Water Gardens",
    "wof:placetype":"venue"
},
  "geometry": {"coordinates":[150.20237731899999,-35.7324676514],"type":"Point"}
}