{
  "type": "Feature",
  "properties": {
    "addr:full":"37 Ackland Ave Christies Beach SA 5165",
    "addr:housenumber":"37",
    "addr:postcode":"5165",
    "addr:street":"Ackland Ave",
    "iso:country":"AU",
    "sg:address":"37 Ackland Ave",
    "sg:city":"Christies Beach",
    "sg:classifiers":[
        {
            "category":"Coffee & Tea",
            "type":"Food & Drink"
        }
    ],
    "sg:phone":"+61 8 8382 0037",
    "sg:postcode":"5165",
    "sg:province":"SA",
    "sg:tags":[
        "kayak",
        "canoe"
    ],
    "wof:name":"Marathon Canoe Club (SA) Incorporated",
    "wof:placetype":"venue"
},
  "geometry": {"coordinates":[138.473312378,-35.1290626526],"type":"Point"}
}