{
  "type": "Feature",
  "properties": {
    "addr:full":"92 Sheridan St Gundagai NSW 2722",
    "addr:housenumber":"92",
    "addr:postcode":"2722",
    "addr:street":"Sheridan St",
    "iso:country":"AU",
    "sg:address":"92 Sheridan St",
    "sg:city":"Gundagai",
    "sg:classifiers":[
        {
            "category":"Retail",
            "subcategory":"Veterinary Services",
            "type":"Services"
        }
    ],
    "sg:phone":"+61 2 6944 1725",
    "sg:postcode":"2722",
    "sg:province":"NSW",
    "sg:tags":[
        "surgeon"
    ],
    "wof:name":"Gundagai Veterinary Clinic",
    "wof:placetype":"venue"
},
  "geometry": {"coordinates":[148.106461,-35.065205],"type":"Point"}
}