{
  "type": "Feature",
  "properties": {
    "addr:full":"11 Maple St Greystanes NSW 2145",
    "addr:housenumber":"11",
    "addr:postcode":"2145",
    "addr:street":"Maple St",
    "iso:country":"AU",
    "sg:address":"11 Maple St",
    "sg:city":"Greystanes",
    "sg:classifiers":[
        {
            "category":"Building & Trades",
            "subcategory":"Plumbing",
            "type":"Services"
        }
    ],
    "sg:phone":"+61 417 048 966",
    "sg:postcode":"2145",
    "sg:province":"NSW",
    "sg:tags":[
        "plumber",
        "gasfitters"
    ],
    "wof:name":"Aaloda Plumbing",
    "wof:placetype":"venue"
},
  "geometry": {"coordinates":[150.95677185100001,-33.8162612915],"type":"Point"}
}