{
  "type": "Feature",
  "properties": {
    "iso:country":"AU",
    "sg:address":"165 Gilbert St",
    "sg:city":"Latrobe",
    "sg:classifiers":[
        {
            "category":"Autos & Motor Vehicles",
            "subcategory":"Fuel & Gas Station",
            "type":"Retail Goods"
        }
    ],
    "sg:phone":"+61 3 6426 1586",
    "sg:postcode":"7307",
    "sg:province":"TAS",
    "wof:name":"Shell Australia Limited",
    "wof:placetype":"venue"
},
  "geometry": {"coordinates":[146.41540499999999,-41.235973],"type":"Point"}
}