{
  "type": "Feature",
  "properties": {
    "addr:full":"50-56 Stawell St West Melbourne VIC 3003",
    "addr:housenumber":"50-56",
    "addr:postcode":"3003",
    "addr:street":"Stawell St",
    "iso:country":"AU",
    "sg:address":"50-56 Stawell St",
    "sg:city":"West Melbourne",
    "sg:classifiers":[
        {
            "category":"Manufacturing",
            "subcategory":"Motor Vehicles & Parts",
            "type":"Manufacturing & Wholesale Goods"
        }
    ],
    "sg:phone":"+61 3 9329 5766",
    "sg:postcode":"3003",
    "sg:province":"VIC",
    "sg:tags":[
        "replacement"
    ],
    "wof:name":"JRA Parts",
    "wof:placetype":"venue"
},
  "geometry": {"coordinates":[144.94276428200001,-37.8047676086],"type":"Point"}
}