{
  "type": "Feature",
  "properties": {
    "addr:full":"Windermere Rd Alexandra Hills QLD 4161",
    "addr:postcode":"4161",
    "addr:street":"Windermere Rd",
    "iso:country":"AU",
    "sg:address":"Windermere Rd",
    "sg:city":"Alexandra Hills",
    "sg:classifiers":[
        {
            "category":"Building & Trades",
            "subcategory":"Construction",
            "type":"Services"
        }
    ],
    "sg:phone":"+61 7 3820 2207",
    "sg:postcode":"4161",
    "sg:province":"QLD",
    "sg:tags":[
        "earth",
        "excavating",
        "moving",
        "contractor"
    ],
    "wof:name":"Herb's Bobcat Hire",
    "wof:placetype":"venue"
},
  "geometry": {"coordinates":[153.2134552,-27.5327720642],"type":"Point"}
}