{
  "type": "Feature",
  "properties": {
    "addr:full":"Shp9a/ 147 Marshalltown Rd Grovedale VIC 3216",
    "addr:housenumber":"147",
    "addr:postcode":"3216",
    "addr:street":"Marshalltown Rd",
    "iso:country":"AU",
    "sg:address":"Shp9a/ 147 Marshalltown Rd",
    "sg:city":"Grovedale",
    "sg:classifiers":[
        {
            "category":"Building & Trades",
            "subcategory":"Construction",
            "type":"Services"
        }
    ],
    "sg:phone":"+61 3 5241 3363",
    "sg:postcode":"3216",
    "sg:province":"VIC",
    "sg:tags":[
        "contractor"
    ],
    "wof:name":"Big Contractors",
    "wof:placetype":"venue"
},
  "geometry": {"coordinates":[144.34501648,-38.1957817078],"type":"Point"}
}