{
  "type": "Feature",
  "properties": {
    "addr:full":"158 Mary St Richmond VIC 3121",
    "addr:housenumber":"158",
    "addr:postcode":"3121",
    "addr:street":"Mary St",
    "iso:country":"AU",
    "sg:address":"158 Mary St",
    "sg:city":"Richmond",
    "sg:classifiers":[
        {
            "category":"Health Services",
            "subcategory":"Health Practitioner",
            "type":"Services"
        }
    ],
    "sg:phone":"+61 3 9429 3980",
    "sg:postcode":"3121",
    "sg:province":"VIC",
    "sg:tags":[
        "psychologist"
    ],
    "wof:name":"McCrossin Peter",
    "wof:placetype":"venue"
},
  "geometry": {"coordinates":[145.00114440900001,-37.8245506287],"type":"Point"}
}