{
  "type": "Feature",
  "properties": {
    "addr:full":"Grip Rd Toora VIC 3962",
    "addr:postcode":"3962",
    "addr:street":"Grip Rd",
    "iso:country":"AU",
    "sg:address":"Grip Rd",
    "sg:city":"Toora",
    "sg:classifiers":[
        {
            "category":"Wholesale",
            "subcategory":"Meat",
            "type":"Manufacturing & Wholesale Goods"
        }
    ],
    "sg:phone":"+61 428 520 177",
    "sg:postcode":"3962",
    "sg:province":"VIC",
    "sg:tags":[
        "abattoir"
    ],
    "wof:name":"Toora Stock Removers",
    "wof:placetype":"venue"
},
  "geometry": {"coordinates":[146.31944274899999,-38.6625099182],"type":"Point"}
}