{
  "type": "Feature",
  "properties": {
    "addr:full":"41 Elizabeth St Gympie QLD 4570",
    "addr:housenumber":"41",
    "addr:postcode":"4570",
    "addr:street":"Elizabeth St",
    "iso:country":"AU",
    "sg:address":"41 Elizabeth St",
    "sg:city":"Gympie",
    "sg:classifiers":[
        {
            "category":"Education",
            "subcategory":"Music School",
            "type":"Public Place"
        }
    ],
    "sg:phone":"+61 7 5482 4163",
    "sg:postcode":"4570",
    "sg:province":"QLD",
    "sg:tags":[
        "teacher"
    ],
    "wof:name":"B & M Music",
    "wof:placetype":"venue"
},
  "geometry": {"coordinates":[152.676544189,-26.1958045959],"type":"Point"}
}