{
  "type": "Feature",
  "properties": {
    "addr:full":"1/ 1933 Logan Rd Upper Mt Gravatt QLD 4122",
    "addr:housenumber":"/ 1933",
    "addr:postcode":"4122",
    "addr:street":"Logan Rd Upper",
    "iso:country":"AU",
    "sg:address":"1/ 1933 Logan Rd",
    "sg:city":"Upper Mt Gravatt",
    "sg:classifiers":[
        {
            "category":"Banks & Credit Unions",
            "subcategory":"Bank",
            "type":"Services"
        }
    ],
    "sg:phone":"+61 7 3349 9044",
    "sg:postcode":"4122",
    "sg:province":"QLD",
    "sg:tags":[
        "broker",
        "mortgage"
    ],
    "wof:name":"City Pacific Finance",
    "wof:placetype":"venue"
},
  "geometry": {"coordinates":[153.079986572,-27.5573596954],"type":"Point"}
}