{
  "type": "Feature",
  "properties": {
    "iso:country":"AU",
    "sg:address":"Shop 3, Furneaux St",
    "sg:city":"Manuka",
    "sg:classifiers":[
        {
            "category":"Personal",
            "subcategory":"Beauty Salon",
            "type":"Services"
        }
    ],
    "sg:phone":"+61 2 6295 0828",
    "sg:postcode":"2603",
    "sg:province":"ACT",
    "sg:tags":[
        "hairdresser"
    ],
    "wof:name":"Bizarre Of Canberra",
    "wof:placetype":"venue"
},
  "geometry": {"coordinates":[149.13279724099999,-35.3194236755],"type":"Point"}
}