{
  "type": "Feature",
  "properties": {
    "addr:full":"284 Unley Rd Unley SA 5061",
    "addr:housenumber":"284",
    "addr:postcode":"5061",
    "addr:street":"Unley Rd",
    "iso:country":"AU",
    "sg:address":"284 Unley Rd",
    "sg:city":"Unley",
    "sg:classifiers":[
        {
            "category":"Autos & Motor Vehicles",
            "subcategory":"Automobile Sales",
            "type":"Retail Goods"
        }
    ],
    "sg:phone":"+61 8 8306 7777",
    "sg:postcode":"5061",
    "sg:province":"SA",
    "sg:tags":[
        "car",
        "new"
    ],
    "wof:name":"Nissan Unley",
    "wof:placetype":"venue"
},
  "geometry": {"coordinates":[138.60775756800001,-34.9556388855],"type":"Point"}
}