{
  "type": "Feature",
  "properties": {
    "addr:full":"627 Canning St Carlton North VIC 3054",
    "addr:housenumber":"627",
    "addr:postcode":"3054",
    "addr:street":"Canning St",
    "iso:country":"AU",
    "sg:address":"627 Canning St",
    "sg:city":"Carlton North",
    "sg:classifiers":[
        {
            "category":"Professional",
            "subcategory":"Management & Consulting",
            "type":"Services"
        }
    ],
    "sg:phone":"+61 3 9381 2364",
    "sg:postcode":"3054",
    "sg:province":"VIC",
    "sg:tags":[
        "consultant"
    ],
    "wof:name":"Knowledge Teams International",
    "wof:placetype":"venue"
},
  "geometry": {"coordinates":[144.97543335,-37.7812461853],"type":"Point"}
}