{
  "type": "Feature",
  "properties": {
    "iso:country":"AU",
    "sg:address":"Rushall Crs",
    "sg:city":"Elizabeth Vale",
    "sg:classifiers":[
        {
            "category":"Personal",
            "type":"Services"
        }
    ],
    "sg:phone":"+61 8 8411 0027",
    "sg:postcode":"5112",
    "sg:province":"SA",
    "sg:tags":[
        "reducing",
        "treatment",
        "weight"
    ],
    "wof:name":"Herbalife Australasia Pty Ltd",
    "wof:placetype":"venue"
},
  "geometry": {"coordinates":[138.66709899899999,-34.7487602234],"type":"Point"}
}