{
  "type": "Feature",
  "properties": {
    "iso:country":"AU",
    "sg:address":"27 Atchison St",
    "sg:city":"Wollongong",
    "sg:classifiers":[
        {
            "category":"Organizations",
            "subcategory":"Community Association",
            "type":"Services"
        }
    ],
    "sg:phone":"+61 2 4254 0512",
    "sg:postcode":"2500",
    "sg:province":"NSW",
    "sg:tags":[
        "organisation",
        "family",
        "welfare"
    ],
    "wof:name":"Wollongong City Mission-Family Support Centre",
    "wof:placetype":"venue"
},
  "geometry": {"coordinates":[150.890564,-34.428169],"type":"Point"}
}