{
  "type": "Feature",
  "properties": {
    "addr:full":"158 Weddell Rd Geelong North VIC 3215",
    "addr:housenumber":"158",
    "addr:postcode":"3215",
    "addr:street":"Weddell Rd",
    "iso:country":"AU",
    "sg:address":"158 Weddell Rd",
    "sg:city":"Geelong North",
    "sg:classifiers":[
        {
            "category":"Insurance",
            "subcategory":"Insurance Agent",
            "type":"Services"
        }
    ],
    "sg:phone":"+61 3 9360 9177",
    "sg:postcode":"3215",
    "sg:province":"VIC",
    "sg:tags":[
        "wool",
        "broker"
    ],
    "wof:name":"Techwool Trading",
    "wof:placetype":"venue"
},
  "geometry": {"coordinates":[144.34715270999999,-38.1226463318],"type":"Point"}
}