{
  "type": "Feature",
  "properties": {
    "iso:country":"AU",
    "sg:address":"51 St Vincent Pl",
    "sg:city":"(South) Albert Park",
    "sg:classifiers":[
        {
            "category":"Health Services",
            "subcategory":"Doctor",
            "type":"Services"
        }
    ],
    "sg:phone":"+61 3 9699 8044",
    "sg:postcode":"3206",
    "sg:province":"VIC",
    "sg:tags":[
        "medical",
        "practitioner"
    ],
    "wof:name":"St Vincent Place Medical Centre",
    "wof:placetype":"venue"
},
  "geometry": {"coordinates":[144.955383,-37.839588],"type":"Point"}
}