{
  "type": "Feature",
  "properties": {
    "addr:full":"Shop 3a Alice St Merimbula NSW 2548",
    "addr:housenumber":"shop 3a",
    "addr:postcode":"2548",
    "addr:street":"Alice St",
    "iso:country":"AU",
    "sg:address":"Shop 3a Alice St",
    "sg:city":"Merimbula",
    "sg:classifiers":[
        {
            "category":"Fast Food",
            "type":"Food & Drink"
        }
    ],
    "sg:phone":"+61 2 6495 3677",
    "sg:postcode":"2548",
    "sg:province":"NSW",
    "sg:tags":[
        "away",
        "take"
    ],
    "wof:name":"The Merimbula Flower Rain",
    "wof:placetype":"venue"
},
  "geometry": {"coordinates":[149.9112854,-36.8882369995],"type":"Point"}
}