{
  "type": "Feature",
  "properties": {
    "addr:full":"Glenarty Rd Karridale WA 6288",
    "addr:postcode":"6288",
    "addr:street":"Glenarty Rd",
    "iso:country":"AU",
    "sg:address":"Glenarty Rd",
    "sg:city":"Karridale",
    "sg:classifiers":[
        {
            "category":"Building & Trades",
            "subcategory":"Construction",
            "type":"Services"
        }
    ],
    "sg:phone":"+61 427 582 211",
    "sg:postcode":"6288",
    "sg:province":"WA",
    "sg:tags":[
        "earth",
        "excavating",
        "moving",
        "contractor"
    ],
    "wof:name":"Karridale Contractors Pty Ltd",
    "wof:placetype":"venue"
},
  "geometry": {"coordinates":[115.162971497,-34.2017822266],"type":"Point"}
}