{
  "type": "Feature",
  "properties": {
    "addr:full":"15 James Paterson St Anna Bay NSW 2316",
    "addr:housenumber":"15",
    "addr:postcode":"2316",
    "addr:street":"James Paterson St",
    "iso:country":"AU",
    "sg:address":"15 James Paterson St",
    "sg:city":"Anna Bay",
    "sg:classifiers":[
        {
            "category":"Cafe",
            "type":"Food & Drink"
        }
    ],
    "sg:phone":"+61 439 380 729",
    "sg:postcode":"2316",
    "sg:province":"NSW",
    "wof:name":"Blue Juice Beach Cafe",
    "wof:placetype":"venue"
},
  "geometry": {"coordinates":[152.079803,-32.781586],"type":"Point"}
}