{
  "type": "Feature",
  "properties": {
    "addr:full":"8/24 Garnett Rd Green Hills NSW 2323",
    "addr:housenumber":"/ 24",
    "addr:postcode":"2323",
    "addr:street":"Garnett Rd",
    "iso:country":"AU",
    "sg:address":"8/24 Garnett Rd",
    "sg:city":"Green Hills",
    "sg:classifiers":[
        {
            "category":"Professional",
            "subcategory":"Employment Agencies",
            "type":"Services"
        }
    ],
    "sg:phone":"+61 2 4934 4700",
    "sg:postcode":"2323",
    "sg:province":"NSW",
    "wof:name":"J Rennie Labour Pty Ltd",
    "wof:placetype":"venue"
},
  "geometry": {"coordinates":[151.59829711899999,-32.7531166077],"type":"Point"}
}