{
  "type": "Feature",
  "properties": {
    "addr:full":"1212 Old Port Rd Royal Park SA 5014",
    "addr:housenumber":"1212",
    "addr:postcode":"5014",
    "addr:street":"Old Port Rd",
    "iso:country":"AU",
    "sg:address":"1212 Old Port Rd",
    "sg:city":"Royal Park",
    "sg:classifiers":[
        {
            "category":"Manufacturing",
            "subcategory":"Watercraft",
            "type":"Manufacturing & Wholesale Goods"
        }
    ],
    "sg:phone":"+61 1800 810 880",
    "sg:postcode":"5014",
    "sg:province":"SA",
    "sg:tags":[
        "sail",
        "marine",
        "maker"
    ],
    "wof:name":"Alegayter Sails",
    "wof:placetype":"venue"
},
  "geometry": {"coordinates":[138.50477600100001,-34.8609313965],"type":"Point"}
}