{
  "type": "Feature",
  "properties": {
    "addr:full":"Shop 3/ 69 Manning Rd Como WA 6152",
    "addr:housenumber":"shop 3 / 69",
    "addr:postcode":"6152",
    "addr:street":"Manning Rd",
    "iso:country":"AU",
    "sg:address":"Shop 3/ 69 Manning Rd",
    "sg:city":"Como",
    "sg:classifiers":[
        {
            "category":"Personal",
            "subcategory":"Tanning Parlor",
            "type":"Services"
        }
    ],
    "sg:phone":"+61 8 9313 2233",
    "sg:postcode":"6152",
    "sg:province":"WA",
    "sg:tags":[
        "solarium"
    ],
    "wof:name":"Como Total Body Salon",
    "wof:placetype":"venue"
},
  "geometry": {"coordinates":[115.86367799999999,-32.012356],"type":"Point"}
}