{
  "type": "Feature",
  "properties": {
    "addr:full":"Shop 2/ 3 Scarborough Beach Rd Scarborough WA 6019",
    "addr:housenumber":"shop 2 / 3",
    "addr:postcode":"6019",
    "addr:street":"Scarborough Beach Rd",
    "iso:country":"AU",
    "sg:address":"Shop 2/ 3 Scarborough Beach Rd",
    "sg:city":"Scarborough",
    "sg:classifiers":[
        {
            "category":"Professional",
            "subcategory":"Computer Services",
            "type":"Services"
        }
    ],
    "sg:phone":"+61 400 442 888",
    "sg:postcode":"6019",
    "sg:province":"WA",
    "sg:tags":[
        "equipment",
        "networking",
        "installation"
    ],
    "wof:name":"Jjorg Conmputer Solutions",
    "wof:placetype":"venue"
},
  "geometry": {"coordinates":[115.75700378400001,-31.8945159912],"type":"Point"}
}