{
  "type": "Feature",
  "properties": {
    "addr:full":"PO Box 7019 Toowoomba Mail Centre QLD 4352",
    "addr:postcode":"4352",
    "iso:country":"AU",
    "sg:address":"PO Box 7019",
    "sg:city":"Toowoomba Mail Centre",
    "sg:classifiers":[
        {
            "category":"Home & Garden",
            "subcategory":"Building Materials",
            "type":"Retail Goods"
        }
    ],
    "sg:phone":"+61 408 649 318",
    "sg:postcode":"4352",
    "sg:province":"QLD",
    "sg:tags":[
        "lawn",
        "cutting",
        "maintenance"
    ],
    "wof:name":"Gold Star Lawn And Garden Care",
    "wof:placetype":"venue"
},
  "geometry": {"coordinates":[151.59376499999999,-28.363979],"type":"Point"}
}