{
  "type": "Feature",
  "properties": {
    "addr:full":"1 Noonan Pl Ingleburn NSW 2565",
    "addr:housenumber":"1",
    "addr:postcode":"2565",
    "addr:street":"Noonan Pl",
    "iso:country":"AU",
    "sg:address":"1 Noonan Pl",
    "sg:city":"Ingleburn",
    "sg:classifiers":[
        {
            "category":"Professional",
            "type":"Services"
        }
    ],
    "sg:phone":"+61 2 9618 3026",
    "sg:postcode":"2565",
    "sg:province":"NSW",
    "sg:tags":[
        "shop",
        "fitting"
    ],
    "wof:name":"N & J Joinery Pty Ltd",
    "wof:placetype":"venue"
},
  "geometry": {"coordinates":[150.86264038100001,-33.9877548218],"type":"Point"}
}