{
  "type": "Feature",
  "properties": {
    "addr:full":"257 Woolgoolga Creek Rd Woolgoolga NSW 2456",
    "addr:housenumber":"257",
    "addr:postcode":"2456",
    "addr:street":"Woolgoolga Creek Rd",
    "iso:country":"AU",
    "sg:address":"257 Woolgoolga Creek Rd",
    "sg:city":"Woolgoolga",
    "sg:classifiers":[
        {
            "category":"Manufacturing",
            "subcategory":"Glass & Minerals",
            "type":"Manufacturing & Wholesale Goods"
        }
    ],
    "sg:phone":"+61 421 033 153",
    "sg:postcode":"2456",
    "sg:province":"NSW",
    "sg:tags":[
        "repair",
        "fibreglass",
        "product"
    ],
    "wof:name":"Pete's Fibreglass Repairs",
    "wof:placetype":"venue"
},
  "geometry": {"coordinates":[153.162735,-30.117062],"type":"Point"}
}