{
  "type": "Feature",
  "properties": {
    "addr:full":"PO Box 100 Cundletown NSW 2430",
    "addr:postcode":"2430",
    "iso:country":"AU",
    "sg:address":"PO Box 100",
    "sg:city":"Cundletown",
    "sg:classifiers":[
        {
            "category":"Recreation",
            "type":"Entertainment"
        }
    ],
    "sg:phone":"+61 2 6553 8240",
    "sg:postcode":"2430",
    "sg:province":"NSW",
    "sg:tags":[
        "recreational",
        "diver"
    ],
    "wof:name":"Cundle Divers",
    "wof:placetype":"venue"
},
  "geometry": {"coordinates":[152.51597599999999,-31.897129],"type":"Point"}
}