{
  "type": "Feature",
  "properties": {
    "addr:full":"29 Hoepper St Toowoomba QLD 4350",
    "addr:housenumber":"29",
    "addr:postcode":"4350",
    "addr:street":"Hoepper St",
    "iso:country":"AU",
    "sg:address":"29 Hoepper St",
    "sg:city":"Toowoomba",
    "sg:classifiers":[
        {
            "category":"Home & Garden",
            "subcategory":"Building Materials",
            "type":"Retail Goods"
        }
    ],
    "sg:phone":"+61 7 4635 6742",
    "sg:postcode":"4350",
    "sg:province":"QLD",
    "sg:tags":[
        "shutter",
        "roller",
        "grille"
    ],
    "wof:name":"Duncan's Doors",
    "wof:placetype":"venue"
},
  "geometry": {"coordinates":[151.94148300000001,-27.587431],"type":"Point"}
}