{
  "type": "Feature",
  "properties": {
    "addr:full":"Fcty12/ 32 Mills Rd Dandenong VIC 3175",
    "addr:postcode":"3175",
    "addr:street":"Mills Rd",
    "iso:country":"AU",
    "sg:address":"Fcty12/ 32 Mills Rd",
    "sg:city":"Dandenong",
    "sg:classifiers":[
        {
            "category":"Retail",
            "subcategory":"Auto Repair",
            "type":"Services"
        }
    ],
    "sg:phone":"+61 3 9794 8559",
    "sg:postcode":"3175",
    "sg:province":"VIC",
    "sg:tags":[
        "beater",
        "painter",
        "panel"
    ],
    "wof:name":"Oc Panels",
    "wof:placetype":"venue"
},
  "geometry": {"coordinates":[145.194946289,-37.9904022217],"type":"Point"}
}