{
  "type": "Feature",
  "properties": {
    "addr:full":"66- 68 Bedford St Gillman SA 5013",
    "addr:housenumber":"68",
    "addr:postcode":"5013",
    "addr:street":"Bedford St",
    "iso:country":"AU",
    "sg:address":"66- 68 Bedford St",
    "sg:city":"Gillman",
    "sg:classifiers":[
        {
            "category":"Freight",
            "type":"Transportation"
        }
    ],
    "sg:phone":"+61 8 8563 3259",
    "sg:postcode":"5013",
    "sg:province":"SA",
    "sg:tags":[
        "light",
        "carrier"
    ],
    "wof:name":"Barossa Express",
    "wof:placetype":"venue"
},
  "geometry": {"coordinates":[138.527267456,-34.8410644531],"type":"Point"}
}