{
  "type": "Feature",
  "properties": {
    "iso:country":"AU",
    "sg:address":"2a Booth St",
    "sg:city":"Balmain",
    "sg:classifiers":[
        {
            "category":"Government",
            "subcategory":"Court House",
            "type":"Public Place"
        }
    ],
    "sg:phone":"+61 418 226 231",
    "sg:postcode":"2041",
    "sg:province":"NSW",
    "sg:tags":[
        "personal",
        "marriage",
        "family",
        "counselling"
    ],
    "wof:name":"Susan Meyer",
    "wof:placetype":"venue"
},
  "geometry": {"coordinates":[151.182312,-33.859692],"type":"Point"}
}