{
  "type": "Feature",
  "properties": {
    "iso:country":"AU",
    "sg:address":"PO Box 67",
    "sg:city":"Injune",
    "sg:classifiers":[
        {
            "category":"Professional",
            "type":"Services"
        }
    ],
    "sg:phone":"+61 428 150 983",
    "sg:postcode":"4454",
    "sg:province":"QLD",
    "sg:tags":[
        "transport"
    ],
    "wof:name":"Injune Daily Express",
    "wof:placetype":"venue"
},
  "geometry": {"coordinates":[148.56715393100001,-25.8402309418],"type":"Point"}
}