{
  "type": "Feature",
  "properties": {
    "iso:country":"AU",
    "sg:address":"92b Main Rd",
    "sg:city":"Penguin",
    "sg:classifiers":[
        {
            "category":"Personal",
            "subcategory":"Beauty Salon",
            "type":"Services"
        }
    ],
    "sg:phone":"+61 3 6437 1202",
    "sg:postcode":"7316",
    "sg:province":"TAS",
    "sg:tags":[
        "hairdresser"
    ],
    "wof:name":"Coast Hairdressing",
    "wof:placetype":"venue"
},
  "geometry": {"coordinates":[146.07427978499999,-41.1148414612],"type":"Point"}
}