{
  "type": "Feature",
  "properties": {
    "iso:country":"AU",
    "sg:address":"11 Sunderland Drv",
    "sg:city":"Bray Park",
    "sg:classifiers":[
        {
            "category":"Building & Trades",
            "subcategory":"Construction",
            "type":"Services"
        }
    ],
    "sg:phone":"+61 414 867 055",
    "sg:postcode":"4500",
    "sg:province":"QLD",
    "sg:tags":[
        "equipment",
        "balancing"
    ],
    "wof:name":"Northside Balancing Pty Ltd",
    "wof:placetype":"venue"
},
  "geometry": {"coordinates":[152.95713806099999,-27.2856712341],"type":"Point"}
}