{
  "type": "Feature",
  "properties": {
    "addr:full":"98 Catherine St Leichhardt NSW 2040",
    "addr:housenumber":"98",
    "addr:postcode":"2040",
    "addr:street":"Catherine St",
    "iso:country":"AU",
    "sg:address":"98 Catherine St",
    "sg:city":"Leichhardt",
    "sg:classifiers":[
        {
            "category":"Education",
            "subcategory":"School",
            "type":"Public Place"
        }
    ],
    "sg:phone":"+61 2 9560 2225",
    "sg:postcode":"2040",
    "sg:province":"NSW",
    "wof:name":"St Fiacre's School",
    "wof:placetype":"venue"
},
  "geometry": {"coordinates":[151.162125,-33.884773],"type":"Point"}
}