{
  "type": "Feature",
  "properties": {
    "iso:country":"AU",
    "sg:address":"70 Frederick St",
    "sg:city":"Albany",
    "sg:classifiers":[
        {
            "category":"Farming",
            "subcategory":"Farm & Veterinary Services",
            "type":"Manufacturing & Wholesale Goods"
        }
    ],
    "sg:phone":"+61 8 9842 1949",
    "sg:postcode":"6330",
    "sg:province":"WA",
    "sg:tags":[
        "agricultural",
        "advisory"
    ],
    "wof:name":"Smith Wayne",
    "wof:placetype":"venue"
},
  "geometry": {"coordinates":[117.885719299,-35.0259056091],"type":"Point"}
}