{
  "type": "Feature",
  "properties": {
    "iso:country":"AU",
    "sg:address":"627 Canterbury Rd",
    "sg:city":"Belmore",
    "sg:classifiers":[
        {
            "category":"Professional",
            "subcategory":"Detective & Security Services",
            "type":"Services"
        }
    ],
    "sg:phone":"+61 2 9718 7111",
    "sg:postcode":"2192",
    "sg:province":"NSW",
    "sg:tags":[
        "equipment",
        "window",
        "doors"
    ],
    "wof:name":"Southern Security Doors",
    "wof:placetype":"venue"
},
  "geometry": {"coordinates":[151.095032,-33.921989],"type":"Point"}
}