{
  "type": "Feature",
  "properties": {
    "addr:full":"477 Raglan Pde Warrnambool VIC 3280",
    "addr:housenumber":"477",
    "addr:postcode":"3280",
    "addr:street":"Raglan Pde",
    "iso:country":"AU",
    "sg:address":"477 Raglan Pde",
    "sg:city":"Warrnambool",
    "sg:classifiers":[
        {
            "category":"Home & Garden",
            "subcategory":"Furniture",
            "type":"Retail Goods"
        }
    ],
    "sg:phone":"+61 3 5561 3900",
    "sg:postcode":"3280",
    "sg:province":"VIC",
    "sg:tags":[
        "outdoor"
    ],
    "wof:name":"Barbeques Galore Warrnambool",
    "wof:placetype":"venue"
},
  "geometry": {"coordinates":[142.49067688,-38.3832168579],"type":"Point"}
}