{
  "type": "Feature",
  "properties": {
    "addr:full":"200 Bourke St Glen Innes NSW 2370",
    "addr:housenumber":"200",
    "addr:postcode":"2370",
    "addr:street":"Bourke St",
    "iso:country":"AU",
    "sg:address":"200 Bourke St",
    "sg:city":"Glen Innes",
    "sg:classifiers":[
        {
            "category":"Shopping",
            "subcategory":"Crafts & Fabrics",
            "type":"Retail Goods"
        }
    ],
    "sg:phone":"+61 2 6732 5599",
    "sg:postcode":"2370",
    "sg:province":"NSW",
    "sg:tags":[
        "florist",
        "supply"
    ],
    "wof:name":"Glensprings Wholesale Flowers Pty Ltd",
    "wof:placetype":"venue"
},
  "geometry": {"coordinates":[151.73748779300001,-29.7391853333],"type":"Point"}
}