{
  "type": "Feature",
  "properties": {
    "addr:full":"1A Salisbury Hwy Salisbury SA 5108",
    "addr:housenumber":"1a",
    "addr:postcode":"5108",
    "addr:street":"Salisbury Hwy",
    "iso:country":"AU",
    "sg:address":"1A Salisbury Hwy",
    "sg:city":"Salisbury",
    "sg:classifiers":[
        {
            "category":"Home & Garden",
            "subcategory":"Carpets & Floor Coverings",
            "type":"Retail Goods"
        }
    ],
    "sg:phone":"+61 8 8283 2244",
    "sg:postcode":"5108",
    "sg:province":"SA",
    "wof:name":"Solomons Flooring",
    "wof:placetype":"venue"
},
  "geometry": {"coordinates":[138.64878845199999,-34.7537918091],"type":"Point"}
}