{
  "type": "Feature",
  "properties": {
    "iso:country":"AU",
    "sg:address":"4/ 28 Woodlark St",
    "sg:city":"Lismore",
    "sg:classifiers":[
        {
            "category":"Real Estate",
            "subcategory":"Real Estate Agent",
            "type":"Services"
        }
    ],
    "sg:phone":"+61 2 6622 6800",
    "sg:postcode":"2480",
    "sg:province":"NSW",
    "wof:name":"Clayton James",
    "wof:placetype":"venue"
},
  "geometry": {"coordinates":[153.27792358400001,-28.8068695068],"type":"Point"}
}