{
  "type": "Feature",
  "properties": {
    "iso:country":"AU",
    "sg:address":"102 Elliott St",
    "sg:city":"Balmain",
    "sg:classifiers":[
        {
            "category":"Shopping",
            "subcategory":"Party Supplies",
            "type":"Retail Goods"
        }
    ],
    "sg:phone":"+61 2 9818 9011",
    "sg:postcode":"2041",
    "sg:province":"NSW",
    "sg:tags":[
        "selling",
        "plan"
    ],
    "wof:name":"Nutrimetics",
    "wof:placetype":"venue"
},
  "geometry": {"coordinates":[151.169815,-33.855659],"type":"Point"}
}