{
  "type": "Feature",
  "properties": {
    "addr:full":"8 Stevenson St Dandenong VIC 3175",
    "addr:housenumber":"8",
    "addr:postcode":"3175",
    "addr:street":"Stevenson St",
    "iso:country":"AU",
    "sg:address":"8 Stevenson St",
    "sg:city":"Dandenong",
    "sg:classifiers":[
        {
            "category":"Retail",
            "subcategory":"Driving School",
            "type":"Services"
        }
    ],
    "sg:phone":"+61 3 9792 0202",
    "sg:postcode":"3175",
    "sg:province":"VIC",
    "wof:name":"Montgomery K D",
    "wof:placetype":"venue"
},
  "geometry": {"coordinates":[145.19827270499999,-37.9666938782],"type":"Point"}
}