{
  "type": "Feature",
  "properties": {
    "addr:full":"Marlin St Balgal Beach QLD 4816",
    "addr:postcode":"4816",
    "addr:street":"Marlin St",
    "iso:country":"AU",
    "sg:address":"Marlin St",
    "sg:city":"Balgal Beach",
    "sg:classifiers":[
        {
            "category":"Fast Food",
            "type":"Food & Drink"
        }
    ],
    "sg:phone":"+61 7 4770 7227",
    "sg:postcode":"4816",
    "sg:province":"QLD",
    "sg:tags":[
        "away",
        "take"
    ],
    "wof:name":"Fisherman's Landing Kiosk",
    "wof:placetype":"venue"
},
  "geometry": {"coordinates":[146.408005,-19.017427],"type":"Point"}
}