{
  "type": "Feature",
  "properties": {
    "addr:full":"99 Glebe Point Rd Glebe NSW 2037",
    "addr:housenumber":"99",
    "addr:postcode":"2037",
    "addr:street":"Glebe Point Rd",
    "iso:country":"AU",
    "sg:address":"99 Glebe Point Rd",
    "sg:city":"Glebe",
    "sg:classifiers":[
        {
            "category":"Restaurant",
            "type":"Food & Drink"
        }
    ],
    "sg:phone":"+61 2 9660 4999",
    "sg:postcode":"2037",
    "sg:province":"NSW",
    "wof:name":"a&#039;Mews",
    "wof:placetype":"venue"
},
  "geometry": {"coordinates":[151.190216064,-33.8823013306],"type":"Point"}
}