{
  "type": "Feature",
  "properties": {
    "addr:full":"U 2/ 175 Hastings Pde Bondi NSW 2026",
    "addr:housenumber":"/ 175",
    "addr:postcode":"2026",
    "addr:street":"Hastings Pde",
    "iso:country":"AU",
    "sg:address":"U 2/ 175 Hastings Pde",
    "sg:city":"Bondi",
    "sg:classifiers":[
        {
            "category":"Education",
            "subcategory":"Special Training",
            "type":"Public Place"
        }
    ],
    "sg:phone":"+61 2 9365 0612",
    "sg:postcode":"2026",
    "sg:province":"NSW",
    "sg:tags":[
        "wine"
    ],
    "wof:name":"Stephen Harris Wine Consultancy",
    "wof:placetype":"venue"
},
  "geometry": {"coordinates":[151.284759522,-33.8910255432],"type":"Point"}
}