{
  "type": "Feature",
  "properties": {
    "addr:full":"107 Walker St Casino NSW 2470",
    "addr:housenumber":"107",
    "addr:postcode":"2470",
    "addr:street":"Walker St",
    "iso:country":"AU",
    "sg:address":"107 Walker St",
    "sg:city":"Casino",
    "sg:classifiers":[
        {
            "category":"Retail",
            "subcategory":"Funeral Services",
            "type":"Services"
        }
    ],
    "sg:phone":"+61 1800 809 336",
    "sg:postcode":"2470",
    "sg:province":"NSW",
    "sg:tags":[
        "director"
    ],
    "wof:name":"Parkview Funeral Home",
    "wof:placetype":"venue"
},
  "geometry": {"coordinates":[153.04856872600001,-28.8627948761],"type":"Point"}
}