{
  "type": "Feature",
  "properties": {
    "addr:full":"36 Dodd St Wembley WA 6014",
    "addr:housenumber":"36",
    "addr:postcode":"6014",
    "addr:street":"Dodd St",
    "iso:country":"AU",
    "sg:address":"36 Dodd St",
    "sg:city":"Wembley",
    "sg:classifiers":[
        {
            "category":"Wholesale",
            "subcategory":"Medical Equipment & Supplies",
            "type":"Manufacturing & Wholesale Goods"
        }
    ],
    "sg:phone":"+61 432 948 758",
    "sg:postcode":"6014",
    "sg:province":"WA",
    "sg:tags":[
        "aids",
        "hearing"
    ],
    "wof:name":"Come Hear Centre",
    "wof:placetype":"venue"
},
  "geometry": {"coordinates":[115.824890137,-31.924156189],"type":"Point"}
}