{
  "type": "Feature",
  "properties": {
    "addr:full":"11 Armiger Crt Holden Hill SA 5088",
    "addr:housenumber":"11",
    "addr:postcode":"5088",
    "addr:street":"Armiger Crt",
    "iso:country":"AU",
    "sg:address":"11 Armiger Crt",
    "sg:city":"Holden Hill",
    "sg:classifiers":[
        {
            "category":"Retail",
            "subcategory":"Auto Repair",
            "type":"Services"
        }
    ],
    "sg:phone":"+61 8 8396 2088",
    "sg:postcode":"5088",
    "sg:province":"SA",
    "sg:tags":[
        "beater",
        "painter",
        "panel"
    ],
    "wof:name":"Highlander Crash Repairs Pty Ltd",
    "wof:placetype":"venue"
},
  "geometry": {"coordinates":[138.67871093799999,-34.8469810486],"type":"Point"}
}