{
  "type": "Feature",
  "properties": {
    "addr:full":"167 Oxford St Darlinghurst NSW 2010",
    "addr:housenumber":"167",
    "addr:postcode":"2010",
    "addr:street":"Oxford St",
    "iso:country":"AU",
    "sg:address":"167 Oxford St",
    "sg:city":"Darlinghurst",
    "sg:classifiers":[
        {
            "category":"Personal",
            "subcategory":"Beauty Salon",
            "type":"Services"
        }
    ],
    "sg:phone":"+61 2 9331 5240",
    "sg:postcode":"2010",
    "sg:province":"NSW",
    "sg:tags":[
        "wig",
        "hairpiece"
    ],
    "wof:name":"Glamour Wigs",
    "wof:placetype":"venue"
},
  "geometry": {"coordinates":[151.216262817,-33.8803024292],"type":"Point"}
}