{
  "type": "Feature",
  "properties": {
    "iso:country":"AU",
    "sg:address":"22 Block C, 661 Newcastle St",
    "sg:city":"Leederville",
    "sg:classifiers":[
        {
            "category":"Banks & Credit Unions",
            "subcategory":"Financial Services",
            "type":"Services"
        }
    ],
    "sg:phone":"+61 8 9228 7111",
    "sg:postcode":"6007",
    "sg:province":"WA",
    "sg:tags":[
        "franchising"
    ],
    "wof:name":"Bear City Make Your Own",
    "wof:placetype":"venue"
},
  "geometry": {"coordinates":[115.842323303,-31.9377975464],"type":"Point"}
}