{
  "type": "Feature",
  "properties": {
    "addr:full":"33 Henry St Stepney SA 5069",
    "addr:housenumber":"33",
    "addr:postcode":"5069",
    "addr:street":"Henry St",
    "iso:country":"AU",
    "sg:address":"33 Henry St",
    "sg:city":"Stepney",
    "sg:classifiers":[
        {
            "category":"Home & Garden",
            "subcategory":"Carpets & Floor Coverings",
            "type":"Retail Goods"
        }
    ],
    "sg:phone":"+61 8 8363 2828",
    "sg:postcode":"5069",
    "sg:province":"SA",
    "sg:tags":[
        "mat",
        "matting"
    ],
    "wof:name":"Sisal Floorco",
    "wof:placetype":"venue"
},
  "geometry": {"coordinates":[138.626556397,-34.9140777588],"type":"Point"}
}