{
  "type": "Feature",
  "properties": {
    "addr:full":"26 Norman St Peakhurst NSW 2210",
    "addr:housenumber":"26",
    "addr:postcode":"2210",
    "addr:street":"Norman St",
    "iso:country":"AU",
    "sg:address":"26 Norman St",
    "sg:city":"Peakhurst",
    "sg:classifiers":[
        {
            "category":"Shopping",
            "subcategory":"Stationery & Office Supplies",
            "type":"Retail Goods"
        }
    ],
    "sg:phone":"+61 2 9533 4477",
    "sg:postcode":"2210",
    "sg:province":"NSW",
    "sg:tags":[
        "equipment",
        "display",
        "exhibition"
    ],
    "wof:name":"A.E. Displays & Sales Pty Ltd",
    "wof:placetype":"venue"
},
  "geometry": {"coordinates":[151.06437700000001,-33.964466],"type":"Point"}
}