{
  "type": "Feature",
  "properties": {
    "addr:full":"52 Barrett Drv Lennox Head NSW 2478",
    "addr:housenumber":"52",
    "addr:postcode":"2478",
    "addr:street":"Barrett Drv",
    "iso:country":"AU",
    "sg:address":"52 Barrett Drv",
    "sg:city":"Lennox Head",
    "sg:classifiers":[
        {
            "category":"Building & Trades",
            "subcategory":"Construction",
            "type":"Services"
        }
    ],
    "sg:phone":"+61 2 6687 5404",
    "sg:postcode":"2478",
    "sg:province":"NSW",
    "sg:tags":[
        "earth",
        "excavating",
        "moving",
        "contractor"
    ],
    "wof:name":"Geoff Wightman",
    "wof:placetype":"venue"
},
  "geometry": {"coordinates":[153.58934020999999,-28.786113739],"type":"Point"}
}