{
  "type": "Feature",
  "properties": {
    "addr:full":"91 Greenwich Rd Greenwich NSW 2065",
    "addr:housenumber":"91",
    "addr:postcode":"2065",
    "addr:street":"Greenwich Rd",
    "iso:country":"AU",
    "sg:address":"91 Greenwich Rd",
    "sg:city":"Greenwich",
    "sg:classifiers":[
        {
            "category":"Food & Beverages",
            "subcategory":"Liquor & Beverages",
            "type":"Retail Goods"
        }
    ],
    "sg:phone":"+61 2 9436 0240",
    "sg:postcode":"2065",
    "sg:province":"NSW",
    "sg:tags":[
        "store"
    ],
    "wof:name":"Greenwich Road Cellars",
    "wof:placetype":"venue"
},
  "geometry": {"coordinates":[151.18635559099999,-33.8313713074],"type":"Point"}
}