{
  "type": "Feature",
  "properties": {
    "addr:full":"Lvl 3, 17 Raglan St South Melbourne VIC 3205",
    "addr:housenumber":"17",
    "addr:postcode":"3205",
    "addr:street":"Raglan St",
    "iso:country":"AU",
    "sg:address":"Lvl 3, 17 Raglan St",
    "sg:city":"South Melbourne",
    "sg:classifiers":[
        {
            "category":"Banks & Credit Unions",
            "subcategory":"Investment Brokerage",
            "type":"Services"
        }
    ],
    "sg:phone":"+61 3 9626 5555",
    "sg:postcode":"3205",
    "sg:province":"VIC",
    "sg:tags":[
        "debt",
        "collection"
    ],
    "wof:name":"icollect.com.au",
    "wof:placetype":"venue"
},
  "geometry": {"coordinates":[144.966049,-37.836578],"type":"Point"}
}