{
  "type": "Feature",
  "properties": {
    "iso:country":"AU",
    "sg:address":"Unit 2 Lot 15 Industrial Rd",
    "sg:city":"Gatton",
    "sg:classifiers":[
        {
            "category":"Wholesale",
            "subcategory":"Chemicals & Plastics",
            "type":"Manufacturing & Wholesale Goods"
        }
    ],
    "sg:phone":"+61 7 5462 1822",
    "sg:postcode":"4343",
    "sg:province":"QLD",
    "sg:tags":[
        "repair"
    ],
    "wof:name":"Grahams Budget Exhaust",
    "wof:placetype":"venue"
},
  "geometry": {"coordinates":[152.277267456,-27.5753421783],"type":"Point"}
}