{
  "type": "Feature",
  "properties": {
    "iso:country":"AU",
    "sg:address":"PO Box 376",
    "sg:city":"Kurri Kurri",
    "sg:classifiers":[
        {
            "category":"Building & Trades",
            "subcategory":"Construction",
            "type":"Services"
        }
    ],
    "sg:phone":"+61 400 362 499",
    "sg:postcode":"2327",
    "sg:province":"NSW",
    "sg:tags":[
        "earth",
        "excavating",
        "moving",
        "contractor"
    ],
    "wof:name":"Cheals Excavation",
    "wof:placetype":"venue"
},
  "geometry": {"coordinates":[151.481124878,-32.8189888],"type":"Point"}
}