{
  "type": "Feature",
  "properties": {
    "iso:country":"AU",
    "sg:address":"Level 3, 141 York St",
    "sg:city":"Sydney",
    "sg:classifiers":[
        {
            "category":"Professional",
            "subcategory":"Management & Consulting",
            "type":"Services"
        }
    ],
    "sg:phone":"+61 2 9264 3626",
    "sg:postcode":"2000",
    "sg:province":"NSW",
    "sg:tags":[
        "consultant"
    ],
    "wof:name":"PM Group",
    "wof:placetype":"venue"
},
  "geometry": {"coordinates":[151.20631408700001,-33.8723373413],"type":"Point"}
}