{
  "type": "Feature",
  "properties": {
    "addr:full":"105-107 Bronte Rd Bondi Junction NSW 2022",
    "addr:housenumber":"105-107",
    "addr:postcode":"2022",
    "addr:street":"Bronte Rd",
    "iso:country":"AU",
    "sg:address":"105-107 Bronte Rd",
    "sg:city":"Bondi Junction",
    "sg:classifiers":[
        {
            "category":"Building & Trades",
            "subcategory":"Construction",
            "type":"Services"
        }
    ],
    "sg:phone":"+61 2 9389 0066",
    "sg:postcode":"2022",
    "sg:province":"NSW",
    "sg:tags":[
        "renovation",
        "alterations",
        "extension",
        "contractor"
    ],
    "sg:website":"http://www.barryskitchens-bathrooms.com.au",
    "wof:name":"Barry's Kitchens & Bathrooms",
    "wof:placetype":"venue"
},
  "geometry": {"coordinates":[151.25062560999999,-33.895488739],"type":"Point"}
}