{
  "type": "Feature",
  "properties": {
    "addr:full":"4/ 401 Gympie Rd Strathpine QLD 4500",
    "addr:housenumber":"/ 401",
    "addr:postcode":"4500",
    "addr:street":"Gympie Rd",
    "iso:country":"AU",
    "sg:address":"4/ 401 Gympie Rd",
    "sg:city":"Strathpine",
    "sg:classifiers":[
        {
            "category":"Personal",
            "subcategory":"Hair Removal",
            "type":"Services"
        }
    ],
    "sg:phone":"+61 7 3205 8824",
    "sg:postcode":"4500",
    "sg:province":"QLD",
    "wof:name":"Hairfree Centre",
    "wof:placetype":"venue"
},
  "geometry": {"coordinates":[153.00668335,-27.317150116],"type":"Point"}
}