{
  "type": "Feature",
  "properties": {
    "iso:country":"AU",
    "sg:address":"PO Box 1637",
    "sg:city":"Surfers Paradise",
    "sg:classifiers":[
        {
            "category":"Real Estate",
            "subcategory":"Surveying",
            "type":"Services"
        }
    ],
    "sg:phone":"+61 7 5504 5662",
    "sg:postcode":"4217",
    "sg:province":"QLD",
    "sg:tags":[
        "surveyor",
        "quantity"
    ],
    "wof:name":"Gold Coast Property Depreciation Services.",
    "wof:placetype":"venue"
},
  "geometry": {"coordinates":[153.42675781200001,-27.9907436371],"type":"Point"}
}