{
  "type": "Feature",
  "properties": {
    "iso:country":"AU",
    "sg:address":"384 Tamborine Oxenford Rd",
    "sg:city":"Upper Coomera",
    "sg:classifiers":[
        {
            "category":"Professional",
            "subcategory":"Art Services",
            "type":"Services"
        }
    ],
    "sg:phone":"+61 7 5502 6509",
    "sg:postcode":"4209",
    "sg:province":"QLD",
    "sg:tags":[
        "decorator",
        "painter"
    ],
    "wof:name":"Garbe's Painting Services Pty Ltd",
    "wof:placetype":"venue"
},
  "geometry": {"coordinates":[153.27993774399999,-27.8980693817],"type":"Point"}
}