{
  "type": "Feature",
  "properties": {
    "iso:country":"AU",
    "sg:address":"14 Kendall Rd",
    "sg:city":"Lancelin",
    "sg:classifiers":[
        {
            "category":"Autos & Motor Vehicles",
            "subcategory":"Boat Sales",
            "type":"Retail Goods"
        }
    ],
    "sg:phone":"+61 8 9655 1276",
    "sg:postcode":"6044",
    "sg:province":"WA",
    "sg:tags":[
        "builder",
        "yacht",
        "repairer"
    ],
    "wof:name":"Lancelin Fabrication & Aluminium Boat Builders",
    "wof:placetype":"venue"
},
  "geometry": {"coordinates":[115.339912415,-31.0210494995],"type":"Point"}
}