{
  "type": "Feature",
  "properties": {
    "iso:country":"AU",
    "sg:address":"8 Lily Pl",
    "sg:city":"Queanbeyan",
    "sg:classifiers":[
        {
            "category":"Autos & Motor Vehicles",
            "subcategory":"Fuel & Gas Station",
            "type":"Retail Goods"
        }
    ],
    "sg:phone":"+61 2 6297 7285",
    "sg:postcode":"2620",
    "sg:province":"NSW",
    "sg:tags":[
        "injection",
        "diesel"
    ],
    "wof:name":"Capital Diesel Service",
    "wof:placetype":"venue"
},
  "geometry": {"coordinates":[149.231002808,-35.3665313721],"type":"Point"}
}