{
  "type": "Feature",
  "properties": {
    "iso:country":"AU",
    "sg:address":"237 Point Nepean Rd",
    "sg:city":"Dromana",
    "sg:classifiers":[
        {
            "category":"Shopping",
            "subcategory":"Clothing, Apparel, & Fashions",
            "type":"Retail Goods"
        }
    ],
    "sg:phone":"+61 3 5987 2084",
    "sg:postcode":"3936",
    "sg:province":"VIC",
    "sg:tags":[
        "menswear"
    ],
    "wof:name":"Buchanan C & Y Menswear",
    "wof:placetype":"venue"
},
  "geometry": {"coordinates":[144.964767456,-38.3328666687],"type":"Point"}
}