{
  "type": "Feature",
  "properties": {
    "iso:country":"AU",
    "sg:address":"Thomson St",
    "sg:city":"Forbes",
    "sg:classifiers":[
        {
            "category":"Education",
            "subcategory":"School",
            "type":"Public Place"
        }
    ],
    "sg:phone":"+61 2 6852 2187",
    "sg:postcode":"2871",
    "sg:province":"NSW",
    "sg:tags":[
        "state",
        "-",
        "nsw"
    ],
    "wof:name":"Forbes North Public School",
    "wof:placetype":"venue"
},
  "geometry": {"coordinates":[148.007706,-33.371887],"type":"Point"}
}