{
  "type": "Feature",
  "properties": {
    "addr:full":"4 Garland Pl Spence ACT 2615",
    "addr:housenumber":"4",
    "addr:postcode":"2615",
    "addr:street":"Garland Pl",
    "iso:country":"AU",
    "sg:address":"4 Garland Pl",
    "sg:city":"Spence",
    "sg:classifiers":[
        {
            "category":"Health Services",
            "subcategory":"Health Practitioner",
            "type":"Services"
        }
    ],
    "sg:phone":"+61 2 6259 1821",
    "sg:postcode":"2615",
    "sg:province":"ACT",
    "sg:tags":[
        "psychologist"
    ],
    "wof:name":"Chandra S Dr & Associates",
    "wof:placetype":"venue"
},
  "geometry": {"coordinates":[149.06358337399999,-35.2040672302],"type":"Point"}
}