{
  "type": "Feature",
  "properties": {
    "iso:country":"AU",
    "sg:address":"Shop 40 Pembroke St",
    "sg:city":"Minto",
    "sg:classifiers":[
        {
            "category":"Shopping",
            "subcategory":"Shoes",
            "type":"Retail Goods"
        }
    ],
    "sg:phone":"+61 2 9603 9105",
    "sg:postcode":"2566",
    "sg:province":"NSW",
    "sg:tags":[
        "footwear"
    ],
    "wof:name":"Kwik Key Cutting & Engraving Pty Ltd",
    "wof:placetype":"venue"
},
  "geometry": {"coordinates":[150.85140991200001,-34.021648407],"type":"Point"}
}