{
  "type": "Feature",
  "properties": {
    "addr:full":"3 Holder Pl Holder ACT 2611",
    "addr:housenumber":"3",
    "addr:postcode":"2611",
    "addr:street":"Holder Pl",
    "iso:country":"AU",
    "sg:address":"3 Holder Pl",
    "sg:city":"Holder",
    "sg:classifiers":[
        {
            "category":"Food & Beverages",
            "subcategory":"Supermarket",
            "type":"Retail Goods"
        }
    ],
    "sg:phone":"+61 2 6288 2577",
    "sg:postcode":"2611",
    "sg:province":"ACT",
    "sg:tags":[
        "grocery",
        "store"
    ],
    "wof:name":"Holder Food Works",
    "wof:placetype":"venue"
},
  "geometry": {"coordinates":[149.12757873499999,-35.2670707703],"type":"Point"}
}