{
  "type": "Feature",
  "properties": {
    "addr:full":"\"Central Park\" 19 Central Rd Port Macquarie NSW 2444",
    "addr:housenumber":"19",
    "addr:postcode":"2444",
    "addr:street":"Central Rd",
    "iso:country":"AU",
    "sg:address":"\"Central Park\" 19 Central Rd",
    "sg:city":"Port Macquarie",
    "sg:classifiers":[
        {
            "category":"Shopping",
            "subcategory":"Antiques",
            "type":"Retail Goods"
        }
    ],
    "sg:phone":"+61 2 6581 1644",
    "sg:postcode":"2444",
    "sg:province":"NSW",
    "wof:name":"Habitat Antiques",
    "wof:placetype":"venue"
},
  "geometry": {"coordinates":[152.89355499999999,-31.446276],"type":"Point"}
}