{
  "type": "Feature",
  "properties": {
    "iso:country":"AU",
    "sg:address":"\"Central Park\" 19 Central Rd",
    "sg:city":"Port Macquarie",
    "sg:classifiers":[
        {
            "category":"Shopping",
            "subcategory":"Antiques",
            "type":"Retail Goods"
        }
    ],
    "sg:phone":"+61 2 6581 1644",
    "sg:postcode":"2444",
    "sg:province":"NSW",
    "wof:name":"Habitat Antiques",
    "wof:placetype":"venue"
},
  "geometry": {"coordinates":[152.893555,-31.446276],"type":"Point"}
}