{
  "type": "Feature",
  "properties": {
    "iso:country":"AU",
    "sg:address":"6 Mitchell Rd",
    "sg:city":"Moorebank",
    "sg:classifiers":[
        {
            "category":"Home & Garden",
            "subcategory":"Hardware",
            "type":"Retail Goods"
        }
    ],
    "sg:phone":"+61 2 9601 1233",
    "sg:postcode":"2170",
    "sg:province":"NSW",
    "sg:tags":[
        "pipe",
        "fitting",
        "plastic"
    ],
    "wof:name":"Milnes Pty Ltd",
    "wof:placetype":"venue"
},
  "geometry": {"coordinates":[150.93772888199999,-33.9360313416],"type":"Point"}
}