{
  "type": "Feature",
  "properties": {
    "addr:full":"Unit A 30- 34 Hilly St Mortlake NSW 2137",
    "addr:housenumber":"34",
    "addr:postcode":"2137",
    "addr:street":"Hilly St",
    "iso:country":"AU",
    "sg:address":"Unit A 30- 34 Hilly St",
    "sg:city":"Mortlake",
    "sg:classifiers":[
        {
            "category":"Shopping",
            "subcategory":"Computers & Home Electronics",
            "type":"Retail Goods"
        }
    ],
    "sg:phone":"+61 2 9311 3255",
    "sg:postcode":"2137",
    "sg:province":"NSW",
    "sg:tags":[
        "wholesaler",
        "mfrs",
        "part",
        "electronic"
    ],
    "wof:name":"Associated Controls (Australia) Pty Ltd",
    "wof:placetype":"venue"
},
  "geometry": {"coordinates":[151.10499572800001,-33.8369255066],"type":"Point"}
}