{
  "type": "Feature",
  "properties": {
    "addr:full":"Unit 1 / 240 Stirling Hwy Claremont WA 6010",
    "addr:housenumber":"/ 240",
    "addr:postcode":"6010",
    "addr:street":"Stirling Hwy",
    "iso:country":"AU",
    "sg:address":"Unit 1 / 240 Stirling Hwy",
    "sg:city":"Claremont",
    "sg:classifiers":[
        {
            "category":"Health Services",
            "subcategory":"Dentist",
            "type":"Services"
        }
    ],
    "sg:phone":"+61 1300 483 384",
    "sg:postcode":"6010",
    "sg:province":"WA",
    "wof:name":"DB Dental",
    "wof:placetype":"venue"
},
  "geometry": {"coordinates":[115.780097961,-31.9835319519],"type":"Point"}
}