{
  "type": "Feature",
  "properties": {
    "addr:full":"7 Singer Pl Ingleburn NSW 2565",
    "addr:housenumber":"7",
    "addr:postcode":"2565",
    "addr:street":"Singer Pl",
    "iso:country":"AU",
    "sg:address":"7 Singer Pl",
    "sg:city":"Ingleburn",
    "sg:classifiers":[
        {
            "category":"Home & Garden",
            "subcategory":"Building Materials",
            "type":"Retail Goods"
        }
    ],
    "sg:phone":"+61 2 9829 7212",
    "sg:postcode":"2565",
    "sg:province":"NSW",
    "sg:tags":[
        "lawn",
        "cutting",
        "maintenance"
    ],
    "wof:name":"TMG Cleaning & Lawn Mowing Services",
    "wof:placetype":"venue"
},
  "geometry": {"coordinates":[150.88148498499999,-34.0032043457],"type":"Point"}
}