{
  "type": "Feature",
  "properties": {
    "addr:full":"Cnr Manningtree & Glenferrie Rds Hawthorn VIC 3122",
    "addr:postcode":"3122",
    "addr:street":"Cnr",
    "iso:country":"AU",
    "sg:address":"Cnr Manningtree & Glenferrie Rds",
    "sg:city":"Hawthorn",
    "sg:classifiers":[
        {
            "category":"Food & Beverages",
            "subcategory":"Groceries & Convenience Stores",
            "type":"Retail Goods"
        }
    ],
    "sg:phone":"+61 3 9818 2014",
    "sg:postcode":"3122",
    "sg:province":"VIC",
    "wof:name":"7-Eleven Stores Pty Ltd",
    "wof:placetype":"venue"
},
  "geometry": {"coordinates":[145.031494141,-37.823600769],"type":"Point"}
}