{
  "type": "Feature",
  "properties": {
    "addr:full":"174 Glenwood Park Drv Glenwood NSW 2768",
    "addr:housenumber":"174",
    "addr:postcode":"2768",
    "addr:street":"Glenwood Park Drv",
    "iso:country":"AU",
    "sg:address":"174 Glenwood Park Drv",
    "sg:city":"Glenwood",
    "sg:classifiers":[
        {
            "category":"Health Services",
            "subcategory":"Doctor",
            "type":"Services"
        }
    ],
    "sg:phone":"+61 2 9629 1777",
    "sg:postcode":"2768",
    "sg:province":"NSW",
    "sg:tags":[
        "medical",
        "practitioner"
    ],
    "wof:name":"Lie Lucia Dr",
    "wof:placetype":"venue"
},
  "geometry": {"coordinates":[150.93142700000001,-33.726982],"type":"Point"}
}