{
  "type": "Feature",
  "properties": {
    "iso:country":"AU",
    "sg:address":"Suite 2/ 2A Booth St",
    "sg:city":"Balmain",
    "sg:classifiers":[
        {
            "category":"Health Services",
            "subcategory":"Health Practitioner",
            "type":"Services"
        }
    ],
    "sg:phone":"+61 2 9555 7055",
    "sg:postcode":"2041",
    "sg:province":"NSW",
    "sg:tags":[
        "acupuncture"
    ],
    "wof:name":"Ogden Lisa",
    "wof:placetype":"venue"
},
  "geometry": {"coordinates":[151.182312,-33.859692],"type":"Point"}
}