{
  "type": "Feature",
  "properties": {
    "iso:country":"AU",
    "sg:address":"13 Collard Rd",
    "sg:city":"Point Clare",
    "sg:classifiers":[
        {
            "category":"Building & Trades",
            "subcategory":"Landscaping Services",
            "type":"Services"
        }
    ],
    "sg:phone":"+61 2 4362 3395",
    "sg:postcode":"2250",
    "sg:province":"NSW",
    "sg:tags":[
        "stump",
        "tree",
        "felling",
        "removal"
    ],
    "wof:name":"Hofman Peter",
    "wof:placetype":"venue"
},
  "geometry": {"coordinates":[151.328582764,-33.4380683899],"type":"Point"}
}