{
  "type": "Feature",
  "properties": {
    "iso:country":"AU",
    "sg:address":"67 Rokeby Rd",
    "sg:city":"Subiaco",
    "sg:classifiers":[
        {
            "category":"Restaurant",
            "type":"Food & Drink"
        }
    ],
    "sg:phone":"+61 8 9381 2099",
    "sg:postcode":"6008",
    "sg:province":"WA",
    "wof:name":"Chutney Mary's Indian Restaurant",
    "wof:placetype":"venue"
},
  "geometry": {"coordinates":[115.82383728000001,-31.9471473694],"type":"Point"}
}