{
  "type": "Feature",
  "properties": {
    "iso:country":"AU",
    "sg:address":"280 Edgar St",
    "sg:city":"Condell Park",
    "sg:classifiers":[
        {
            "category":"Professional",
            "type":"Services"
        }
    ],
    "sg:phone":"+61 2 9790 5004",
    "sg:postcode":"2200",
    "sg:province":"NSW",
    "sg:tags":[
        "courier"
    ],
    "wof:name":"Performance Plus Couriers",
    "wof:placetype":"venue"
},
  "geometry": {"coordinates":[151.012115,-33.926895],"type":"Point"}
}