{
  "type": "Feature",
  "properties": {
    "addr:full":"717 Rathdowne St Carlton North VIC 3054",
    "addr:housenumber":"717",
    "addr:postcode":"3054",
    "addr:street":"Rathdowne St",
    "iso:country":"AU",
    "sg:address":"717 Rathdowne St",
    "sg:city":"Carlton North",
    "sg:classifiers":[
        {
            "category":"Cafe",
            "type":"Food & Drink"
        }
    ],
    "sg:phone":"+61 3 9348 1276",
    "sg:postcode":"3054",
    "sg:province":"VIC",
    "wof:name":"North Cafeteria",
    "wof:placetype":"venue"
},
  "geometry": {"coordinates":[144.971893311,-37.7881126404],"type":"Point"}
}