{
  "type": "Feature",
  "properties": {
    "addr:full":"Martin Rd Green Fields SA 5107",
    "addr:postcode":"5107",
    "addr:street":"Martin Rd",
    "iso:country":"AU",
    "sg:address":"Martin Rd",
    "sg:city":"Green Fields",
    "sg:classifiers":[
        {
            "category":"Building & Trades",
            "subcategory":"Construction",
            "type":"Services"
        }
    ],
    "sg:phone":"+61 8 8250 6301",
    "sg:postcode":"5107",
    "sg:province":"SA",
    "sg:tags":[
        "ceiling"
    ],
    "wof:name":"Bivone Bros Ceilings Pty Ltd",
    "wof:placetype":"venue"
},
  "geometry": {"coordinates":[138.59991455100001,-34.7910079956],"type":"Point"}
}