{
  "type": "Feature",
  "properties": {
    "iso:country":"AU",
    "sg:address":"18 Collaroy St",
    "sg:city":"Collaroy Beach",
    "sg:classifiers":[
        {
            "category":"Real Estate",
            "subcategory":"Architect",
            "type":"Services"
        }
    ],
    "sg:phone":"+61 2 9971 6442",
    "sg:postcode":"2097",
    "sg:province":"NSW",
    "sg:tags":[
        "building",
        "designer"
    ],
    "wof:name":"Phantom Design Architecture",
    "wof:placetype":"venue"
},
  "geometry": {"coordinates":[151.299484253,-33.7319602966],"type":"Point"}
}