{
  "type": "Feature",
  "properties": {
    "addr:full":"Unit 20a Louise Ave Ingleburn NSW 2565",
    "addr:housenumber":"unit 20a",
    "addr:postcode":"2565",
    "addr:street":"Louise Ave",
    "iso:country":"AU",
    "sg:address":"Unit 20a Louise Ave",
    "sg:city":"Ingleburn",
    "sg:classifiers":[
        {
            "category":"Autos & Motor Vehicles",
            "subcategory":"Auto Supplies",
            "type":"Retail Goods"
        }
    ],
    "sg:phone":"+61 2 9829 3445",
    "sg:postcode":"2565",
    "sg:province":"NSW",
    "sg:tags":[
        "transmission",
        "equipment",
        "power"
    ],
    "wof:name":"Bearings & Drives",
    "wof:placetype":"venue"
},
  "geometry": {"coordinates":[150.86579895,-33.9951972961],"type":"Point"}
}