{
  "type": "Feature",
  "properties": {
    "iso:country":"AU",
    "sg:address":"210 Oxford St",
    "sg:city":"Paddington",
    "sg:classifiers":[
        {
            "category":"Cafe",
            "type":"Food & Drink"
        }
    ],
    "sg:phone":"+61 2 9331 7907",
    "sg:postcode":"2021",
    "sg:province":"NSW",
    "wof:name":"Cafe Kaz",
    "wof:placetype":"venue"
},
  "geometry": {"coordinates":[151.22523498499999,-33.8847541809],"type":"Point"}
}