{
  "type": "Feature",
  "properties": {
    "addr:full":"95 Barker St Casino NSW 2470",
    "addr:housenumber":"95",
    "addr:postcode":"2470",
    "addr:street":"Barker St",
    "iso:country":"AU",
    "sg:address":"95 Barker St",
    "sg:city":"Casino",
    "sg:classifiers":[
        {
            "category":"Real Estate",
            "subcategory":"Surveying",
            "type":"Services"
        }
    ],
    "sg:phone":"+61 2 6662 1888",
    "sg:postcode":"2470",
    "sg:province":"NSW",
    "sg:tags":[
        "surveyor",
        "land"
    ],
    "wof:name":"Envirolink Consulting",
    "wof:placetype":"venue"
},
  "geometry": {"coordinates":[153.04710388199999,-28.8649196625],"type":"Point"}
}