{
  "type": "Feature",
  "properties": {
    "addr:full":"5/ 89 Main St Osborne Park WA 6017",
    "addr:housenumber":"/ 89",
    "addr:postcode":"6017",
    "addr:street":"Main St",
    "iso:country":"AU",
    "sg:address":"5/ 89 Main St",
    "sg:city":"Osborne Park",
    "sg:classifiers":[
        {
            "category":"Professional",
            "subcategory":"Art Services",
            "type":"Services"
        }
    ],
    "sg:phone":"+61 8 9444 3251",
    "sg:postcode":"6017",
    "sg:province":"WA",
    "sg:tags":[
        "picture",
        "frame",
        "framing"
    ],
    "wof:name":"Art Forum",
    "wof:placetype":"venue"
},
  "geometry": {"coordinates":[115.82569122300001,-31.9072551727],"type":"Point"}
}