{
  "type": "Feature",
  "properties": {
    "iso:country":"AU",
    "sg:address":"60 Belmont Ave",
    "sg:city":"Belmont",
    "sg:classifiers":[
        {
            "category":"Building & Trades",
            "subcategory":"Construction",
            "type":"Services"
        }
    ],
    "sg:phone":"+61 1300 657 896",
    "sg:postcode":"6104",
    "sg:province":"WA",
    "sg:tags":[
        "window",
        "aluminium"
    ],
    "sg:website":"http://www.doorscape.com.au",
    "wof:name":"Dowell",
    "wof:placetype":"venue"
},
  "geometry": {"coordinates":[115.922042847,-31.956205368],"type":"Point"}
}