{
  "type": "Feature",
  "properties": {
    "addr:full":"595 Grand Junction Rd Gepps Cross SA 5094",
    "addr:housenumber":"595",
    "addr:postcode":"5094",
    "addr:street":"Grand Junction Rd",
    "iso:country":"AU",
    "sg:address":"595 Grand Junction Rd",
    "sg:city":"Gepps Cross",
    "sg:classifiers":[
        {
            "category":"Organizations",
            "subcategory":"Non-profit Organization",
            "type":"Services"
        }
    ],
    "sg:phone":"+61 8 8260 5455",
    "sg:postcode":"5094",
    "sg:province":"SA",
    "sg:tags":[
        "support",
        "disability",
        "organisation"
    ],
    "wof:name":"Phoenix Society Incorporated",
    "wof:placetype":"venue"
},
  "geometry": {"coordinates":[138.59892273,-34.8479728699],"type":"Point"}
}