{
  "type": "Feature",
  "properties": {
    "addr:full":"63 Queen St Adelaide SA 5000",
    "addr:housenumber":"63",
    "addr:postcode":"5000",
    "addr:street":"Queen St",
    "iso:country":"AU",
    "sg:address":"63 Queen St",
    "sg:city":"Adelaide",
    "sg:classifiers":[
        {
            "category":"Health Services",
            "subcategory":"Clinic",
            "type":"Services"
        }
    ],
    "sg:phone":"+61 8 8223 2099",
    "sg:postcode":"5000",
    "sg:province":"SA",
    "sg:tags":[
        "aromatherapy"
    ],
    "wof:name":"Gumleaf Aromatics",
    "wof:placetype":"venue"
},
  "geometry": {"coordinates":[138.60435485799999,-34.9322242737],"type":"Point"}
}