{
  "type": "Feature",
  "properties": {
    "addr:full":"134 Burke Rd Malvern East VIC 3145",
    "addr:housenumber":"134",
    "addr:postcode":"3145",
    "addr:street":"Burke Rd",
    "iso:country":"AU",
    "sg:address":"134 Burke Rd",
    "sg:city":"Malvern East",
    "sg:classifiers":[
        {
            "category":"Restaurant",
            "type":"Food & Drink"
        }
    ],
    "sg:phone":"+61 3 9886 0458",
    "sg:postcode":"3145",
    "sg:province":"VIC",
    "sg:website":"http://www.neillsoncentralpark.com.au",
    "wof:name":"Neill's On Central Park",
    "wof:placetype":"venue"
},
  "geometry": {"coordinates":[145.05030822800001,-37.8656044006],"type":"Point"}
}