{
  "type": "Feature",
  "properties": {
    "iso:country":"AU",
    "sg:address":"34 Vicars St",
    "sg:city":"Mitchell",
    "sg:phone":"+61 2 6213 3700",
    "sg:postcode":"2911",
    "sg:province":"ACT",
    "wof:name":"FAW Building & Rural Supplies",
    "wof:placetype":"venue"
},
  "geometry": {"coordinates":[149.145385742,-35.2117958069],"type":"Point"}
}