{
  "type": "Feature",
  "properties": {
    "addr:full":"PO Box 2231 Noosa Heads QLD 4567",
    "addr:postcode":"4567",
    "iso:country":"AU",
    "sg:address":"PO Box 2231",
    "sg:city":"Noosa Heads",
    "sg:classifiers":[
        {
            "category":"Home & Garden",
            "subcategory":"Building Materials",
            "type":"Retail Goods"
        }
    ],
    "sg:phone":"+61 431 415 475",
    "sg:postcode":"4567",
    "sg:province":"QLD",
    "sg:tags":[
        "lawn",
        "cutting",
        "maintenance"
    ],
    "wof:name":"Green Goat Complete Lawn & Garden Service",
    "wof:placetype":"venue"
},
  "geometry": {"coordinates":[153.086105347,-26.3990192413],"type":"Point"}
}