{
  "type": "Feature",
  "properties": {
    "addr:full":"53 Cameron St Cranbourne VIC 3977",
    "addr:housenumber":"53",
    "addr:postcode":"3977",
    "addr:street":"Cameron St",
    "iso:country":"AU",
    "sg:address":"53 Cameron St",
    "sg:city":"Cranbourne",
    "sg:phone":"+61 3 5995 1595",
    "sg:postcode":"3977",
    "sg:province":"VIC",
    "wof:name":"Casey Cab & Frame",
    "wof:placetype":"venue"
},
  "geometry": {"coordinates":[145.289352417,-38.1153717041],"type":"Point"}
}