{
  "type": "Feature",
  "properties": {
    "addr:full":"North St Nowra NSW 2541",
    "addr:postcode":"2541",
    "addr:street":"North St",
    "iso:country":"AU",
    "sg:address":"North St",
    "sg:city":"Nowra",
    "sg:classifiers":[
        {
            "category":"Retail",
            "subcategory":"Auto Repair",
            "type":"Services"
        }
    ],
    "sg:phone":"+61 2 4421 4544",
    "sg:postcode":"2541",
    "sg:province":"NSW",
    "sg:tags":[
        "electrical"
    ],
    "wof:name":"Charlies Auto Electrical",
    "wof:placetype":"venue"
},
  "geometry": {"coordinates":[150.59507751500001,-34.8714637756],"type":"Point"}
}