{
  "type": "Feature",
  "properties": {
    "addr:full":"104 Hampden Rd Artarmon NSW 2064",
    "addr:housenumber":"104",
    "addr:postcode":"2064",
    "addr:street":"Hampden Rd",
    "iso:country":"AU",
    "sg:address":"104 Hampden Rd",
    "sg:city":"Artarmon",
    "sg:classifiers":[
        {
            "category":"Personal",
            "subcategory":"Beauty Salon",
            "type":"Services"
        }
    ],
    "sg:phone":"+61 2 9413 1017",
    "sg:postcode":"2064",
    "sg:province":"NSW",
    "sg:tags":[
        "hairdresser"
    ],
    "wof:name":"Black & White Hair & Beauty Studio",
    "wof:placetype":"venue"
},
  "geometry": {"coordinates":[151.18417358400001,-33.8086700439],"type":"Point"}
}