{
  "type": "Feature",
  "properties": {
    "addr:full":"4/ 22 Babdoyle St Loganholme QLD 4129",
    "addr:housenumber":"/ 22",
    "addr:postcode":"4129",
    "addr:street":"Babdoyle St",
    "iso:country":"AU",
    "sg:address":"4/ 22 Babdoyle St",
    "sg:city":"Loganholme",
    "sg:classifiers":[
        {
            "category":"Retail",
            "subcategory":"Auto Repair",
            "type":"Services"
        }
    ],
    "sg:phone":"+61 7 3801 4152",
    "sg:postcode":"4129",
    "sg:province":"QLD",
    "sg:tags":[
        "electrical"
    ],
    "wof:name":"Jasper Auto Electrical",
    "wof:placetype":"venue"
},
  "geometry": {"coordinates":[153.19288635300001,-27.680721283],"type":"Point"}
}