{
  "type": "Feature",
  "properties": {
    "iso:country":"AU",
    "sg:address":"773 Toorak Rd",
    "sg:city":"Hawthorn East",
    "sg:classifiers":[
        {
            "category":"Building & Trades",
            "subcategory":"Landscaping Services",
            "type":"Services"
        }
    ],
    "sg:phone":"+61 3 9625 3093",
    "sg:postcode":"3123",
    "sg:province":"VIC",
    "sg:tags":[
        "designer",
        "landscape",
        "contractor"
    ],
    "wof:name":"Botanic Hispanic Creative Landscape Design",
    "wof:placetype":"venue"
},
  "geometry": {"coordinates":[145.04284668,-37.8450088501],"type":"Point"}
}