{
  "type": "Feature",
  "properties": {
    "addr:full":"Gympie St North Landsborough QLD 4550",
    "addr:postcode":"4550",
    "addr:street":"Gympie St North",
    "iso:country":"AU",
    "sg:address":"Gympie St",
    "sg:city":"North Landsborough",
    "sg:classifiers":[
        {
            "category":"Education",
            "subcategory":"School",
            "type":"Public Place"
        }
    ],
    "sg:phone":"+61 7 5494 1525",
    "sg:postcode":"4550",
    "sg:province":"QLD",
    "sg:tags":[
        "state",
        "except",
        "nsw"
    ],
    "wof:name":"Landsborough Preschool",
    "wof:placetype":"venue"
},
  "geometry": {"coordinates":[152.96386718799999,-26.8046112061],"type":"Point"}
}