{
  "type": "Feature",
  "properties": {
    "iso:country":"AU",
    "sg:address":"Factory 1, 16- 18 Fleet St",
    "sg:city":"Somerton",
    "sg:classifiers":[
        {
            "category":"Retail",
            "subcategory":"Auto Repair",
            "type":"Services"
        }
    ],
    "sg:phone":"+61 3 9303 7388",
    "sg:postcode":"3062",
    "sg:province":"VIC",
    "sg:tags":[
        "camper-trailers",
        "caravan",
        "servicing"
    ],
    "wof:name":"Retrovan",
    "wof:placetype":"venue"
},
  "geometry": {"coordinates":[144.961868286,-37.6429786682],"type":"Point"}
}