{
  "type": "Feature",
  "properties": {
    "addr:full":"Cnr Melaluka Rd & Barrabool Crs Leopold VIC 3224",
    "addr:postcode":"3224",
    "addr:street":"Cnr Melaluka Rd & Barrabool Crs Leopold",
    "iso:country":"AU",
    "sg:address":"Cnr Melaluka Rd & Barrabool Crs",
    "sg:city":"Leopold",
    "sg:classifiers":[
        {
            "category":"Social Services",
            "subcategory":"Child Care",
            "type":"Services"
        }
    ],
    "sg:phone":"+61 3 5250 1161",
    "sg:postcode":"3224",
    "sg:province":"VIC",
    "wof:name":"Melaluka Child Care & Kindergarten Centre",
    "wof:placetype":"venue"
},
  "geometry": {"coordinates":[144.453781128,-38.1954040527],"type":"Point"}
}