{
  "type": "Feature",
  "properties": {
    "iso:country":"AU",
    "sg:address":"4 Airds Rd",
    "sg:city":"Minto",
    "sg:classifiers":[
        {
            "category":"Professional",
            "subcategory":"Engineering",
            "type":"Services"
        }
    ],
    "sg:phone":"+61 2 9603 1355",
    "sg:postcode":"2566",
    "sg:province":"NSW",
    "sg:tags":[
        "engineer"
    ],
    "wof:name":"Gradon General Engineering",
    "wof:placetype":"venue"
},
  "geometry": {"coordinates":[150.84147644000001,-34.0214805603],"type":"Point"}
}