{
  "type": "Feature",
  "properties": {
    "addr:full":"32 Currie St Nambour QLD 4560",
    "addr:housenumber":"32",
    "addr:postcode":"4560",
    "addr:street":"Currie St",
    "iso:country":"AU",
    "sg:address":"32 Currie St",
    "sg:city":"Nambour",
    "sg:classifiers":[
        {
            "category":"Health Services",
            "subcategory":"Dentist",
            "type":"Services"
        }
    ],
    "sg:phone":"+61 7 5441 1166",
    "sg:postcode":"4560",
    "sg:province":"QLD",
    "wof:name":"Dr Marieta Hovey",
    "wof:placetype":"venue"
},
  "geometry": {"coordinates":[152.958908081,-26.6251277924],"type":"Point"}
}