{
  "type": "Feature",
  "properties": {
    "addr:full":"Morgan St Gladstone QLD 4680",
    "addr:postcode":"4680",
    "addr:street":"Morgan St",
    "iso:country":"AU",
    "sg:address":"Morgan St",
    "sg:city":"Gladstone",
    "sg:classifiers":[
        {
            "category":"Home & Garden",
            "subcategory":"Building Materials",
            "type":"Retail Goods"
        }
    ],
    "sg:phone":"+61 7 4972 3033",
    "sg:postcode":"4680",
    "sg:province":"QLD",
    "sg:tags":[
        "pre-mixed",
        "concrete"
    ],
    "wof:name":"Readymix",
    "wof:placetype":"venue"
},
  "geometry": {"coordinates":[151.24778747600001,-23.8392391205],"type":"Point"}
}