{
  "type": "Feature",
  "properties": {
    "addr:full":"Lot 14 Bruce Rock Rd Merredin WA 6415",
    "addr:housenumber":"14",
    "addr:postcode":"6415",
    "addr:street":"Bruce Rock Rd",
    "iso:country":"AU",
    "sg:address":"Lot 14 Bruce Rock Rd",
    "sg:city":"Merredin",
    "sg:classifiers":[
        {
            "category":"Building & Trades",
            "subcategory":"Plumbing",
            "type":"Services"
        }
    ],
    "sg:phone":"+61 8 9041 1005",
    "sg:postcode":"6415",
    "sg:province":"WA",
    "sg:tags":[
        "plumber",
        "gasfitters"
    ],
    "wof:name":"Eddie Hombergen Plumbing & Building",
    "wof:placetype":"venue"
},
  "geometry": {"coordinates":[118.273292541,-31.4829692841],"type":"Point"}
}