{
  "type": "Feature",
  "properties": {
    "addr:full":"3 Jason Pl Melton West VIC 3337",
    "addr:housenumber":"3",
    "addr:postcode":"3337",
    "addr:street":"Jason Pl",
    "iso:country":"AU",
    "sg:address":"3 Jason Pl",
    "sg:city":"Melton West",
    "sg:classifiers":[
        {
            "category":"Retail",
            "subcategory":"Driving School",
            "type":"Services"
        }
    ],
    "sg:phone":"+61 3 9743 4565",
    "sg:postcode":"3337",
    "sg:province":"VIC",
    "wof:name":"Better Learning Driving School",
    "wof:placetype":"venue"
},
  "geometry": {"coordinates":[144.554047,-37.673531],"type":"Point"}
}