{
  "type": "Feature",
  "properties": {
    "iso:country":"AU",
    "sg:address":"755 Doncaster Rd",
    "sg:city":"Doncaster",
    "sg:classifiers":[
        {
            "category":"Personal",
            "subcategory":"Tanning Parlor",
            "type":"Services"
        }
    ],
    "sg:phone":"+61 3 9855 9199",
    "sg:postcode":"3108",
    "sg:province":"VIC",
    "sg:tags":[
        "solarium"
    ],
    "wof:name":"Brazilian Sun Beauty & Tanning Studio",
    "wof:placetype":"venue"
},
  "geometry": {"coordinates":[145.13470459000001,-37.786655426],"type":"Point"}
}