{
  "type": "Feature",
  "properties": {
    "addr:full":"472 Goodwood Rd Cumberland Park SA 5041",
    "addr:housenumber":"472",
    "addr:postcode":"5041",
    "addr:street":"Goodwood Rd",
    "iso:country":"AU",
    "sg:address":"472 Goodwood Rd",
    "sg:city":"Cumberland Park",
    "sg:classifiers":[
        {
            "category":"Food & Beverages",
            "subcategory":"Liquor & Beverages",
            "type":"Retail Goods"
        }
    ],
    "sg:phone":"+61 8 8272 9600",
    "sg:postcode":"5041",
    "sg:province":"SA",
    "sg:tags":[
        "store"
    ],
    "wof:name":"Baily & Baily Liquor Stores",
    "wof:placetype":"venue"
},
  "geometry": {"coordinates":[138.59132399999999,-34.975155],"type":"Point"}
}