{
  "type": "Feature",
  "properties": {
    "addr:full":"PO Box 8046 Dunoon NSW 2480",
    "addr:postcode":"2480",
    "iso:country":"AU",
    "sg:address":"PO Box 8046",
    "sg:city":"Dunoon",
    "sg:classifiers":[
        {
            "category":"Manufacturing",
            "subcategory":"Motor Vehicles & Parts",
            "type":"Manufacturing & Wholesale Goods"
        }
    ],
    "sg:phone":"+61 2 6689 5977",
    "sg:postcode":"2480",
    "sg:province":"NSW",
    "sg:tags":[
        "replacement"
    ],
    "wof:name":"Wanxiang Australia Pty Ltd",
    "wof:placetype":"venue"
},
  "geometry": {"coordinates":[153.31552124000001,-28.6843605042],"type":"Point"}
}