{
  "type": "Feature",
  "properties": {
    "iso:country":"AU",
    "sg:address":"104 Dougharty Rd",
    "sg:city":"Heidelberg West",
    "sg:classifiers":[
        {
            "category":"Wholesale",
            "subcategory":"Non-durable Goods",
            "type":"Manufacturing & Wholesale Goods"
        }
    ],
    "sg:phone":"+61 3 9450 8900",
    "sg:postcode":"3081",
    "sg:province":"VIC",
    "sg:tags":[
        "textile"
    ],
    "wof:name":"Birch E.C. Pty Ltd",
    "wof:placetype":"venue"
},
  "geometry": {"coordinates":[145.05157470699999,-37.7345695496],"type":"Point"}
}