{
  "type": "Feature",
  "properties": {
    "addr:full":"10 Bridge St Gunnedah NSW 2380",
    "addr:housenumber":"10",
    "addr:postcode":"2380",
    "addr:street":"Bridge St",
    "iso:country":"AU",
    "sg:address":"10 Bridge St",
    "sg:city":"Gunnedah",
    "sg:classifiers":[
        {
            "category":"Food & Beverages",
            "subcategory":"Groceries & Convenience Stores",
            "type":"Retail Goods"
        }
    ],
    "sg:phone":"+61 2 6742 4174",
    "sg:postcode":"2380",
    "sg:province":"NSW",
    "wof:name":"Wilko's Corner Store",
    "wof:placetype":"venue"
},
  "geometry": {"coordinates":[150.250289917,-30.9890632629],"type":"Point"}
}