{
  "type": "Feature",
  "properties": {
    "addr:full":"39 Drayton St Nanango QLD 4615",
    "addr:housenumber":"39",
    "addr:postcode":"4615",
    "addr:street":"Drayton St",
    "iso:country":"AU",
    "sg:address":"39 Drayton St",
    "sg:city":"Nanango",
    "sg:classifiers":[
        {
            "category":"Education",
            "subcategory":"School",
            "type":"Public Place"
        }
    ],
    "sg:phone":"+61 7 4171 6200",
    "sg:postcode":"4615",
    "sg:province":"QLD",
    "sg:tags":[
        "state",
        "except",
        "nsw"
    ],
    "wof:name":"Nanango Primary",
    "wof:placetype":"venue"
},
  "geometry": {"coordinates":[152.001586914,-26.671245575],"type":"Point"}
}