{
  "type": "Feature",
  "properties": {
    "addr:full":"U1/ 125 Magowar Rd Girraween NSW 2145",
    "addr:housenumber":"125",
    "addr:postcode":"2145",
    "addr:street":"U1 /;Magowar Rd",
    "iso:country":"AU",
    "sg:address":"U1/ 125 Magowar Rd",
    "sg:city":"Girraween",
    "sg:classifiers":[
        {
            "category":"Arts & Performance",
            "subcategory":"Dance",
            "type":"Entertainment"
        }
    ],
    "sg:phone":"+61 2 9896 5559",
    "sg:postcode":"2145",
    "sg:province":"NSW",
    "sg:tags":[
        "theatrical",
        "ballet",
        "tuition"
    ],
    "wof:name":"Performance Studio The",
    "wof:placetype":"venue"
},
  "geometry": {"coordinates":[150.94378662099999,-33.8012771606],"type":"Point"}
}