{
  "type": "Feature",
  "properties": {
    "iso:country":"AU",
    "sg:address":"13- 19 Leslie St",
    "sg:city":"Brunswick",
    "sg:classifiers":[
        {
            "category":"Wholesale",
            "subcategory":"Metals & Minerals",
            "type":"Manufacturing & Wholesale Goods"
        }
    ],
    "sg:phone":"+61 3 9380 1955",
    "sg:postcode":"3056",
    "sg:province":"VIC",
    "sg:tags":[
        "steel",
        "stainless",
        "product",
        "equipment"
    ],
    "wof:name":"Fairmont Stainless Steel",
    "wof:placetype":"venue"
},
  "geometry": {"coordinates":[144.95843505900001,-37.7676429749],"type":"Point"}
}