{
  "type": "Feature",
  "properties": {
    "addr:full":"146 Morgan St Broken Hill NSW 2880",
    "addr:housenumber":"146",
    "addr:postcode":"2880",
    "addr:street":"Morgan St",
    "iso:country":"AU",
    "sg:address":"146 Morgan St",
    "sg:city":"Broken Hill",
    "sg:classifiers":[
        {
            "category":"Utilities",
            "subcategory":"Electric",
            "type":"Services"
        }
    ],
    "sg:phone":"+61 8 8087 7988",
    "sg:postcode":"2880",
    "sg:province":"NSW",
    "sg:tags":[
        "electrical",
        "contractor"
    ],
    "wof:name":"Bevan B W",
    "wof:placetype":"venue"
},
  "geometry": {"coordinates":[141.45118713400001,-31.9482479095],"type":"Point"}
}