{
  "type": "Feature",
  "properties": {
    "addr:full":"GPO Box 2792 Darwin NT 0800",
    "addr:postcode":"nt 0800",
    "iso:country":"AU",
    "sg:address":"GPO Box 2792",
    "sg:city":"Darwin",
    "sg:classifiers":[
        {
            "category":"Wholesale",
            "subcategory":"Machinery & Supplies",
            "type":"Manufacturing & Wholesale Goods"
        }
    ],
    "sg:phone":"+61 8 8927 7708",
    "sg:postcode":"0800",
    "sg:province":"NT",
    "sg:tags":[
        "equipment",
        "pneumatic"
    ],
    "wof:name":"Compressed Air Australia Pty Ltd",
    "wof:placetype":"venue"
},
  "geometry": {"coordinates":[130.84231567399999,-12.4620399475],"type":"Point"}
}