{
  "type": "Feature",
  "properties": {
    "addr:full":"13 Garfield Rd Glenorchy TAS 7010",
    "addr:housenumber":"13",
    "addr:postcode":"7010",
    "addr:street":"Garfield Rd",
    "iso:country":"AU",
    "sg:address":"13 Garfield Rd",
    "sg:city":"Glenorchy",
    "sg:classifiers":[
        {
            "category":"Building & Trades",
            "subcategory":"Cleaning & Sanitation",
            "type":"Services"
        }
    ],
    "sg:phone":"+61 419 520 316",
    "sg:postcode":"7010",
    "sg:province":"TAS",
    "sg:tags":[
        "window"
    ],
    "wof:name":"D & L Cleaning Service",
    "wof:placetype":"venue"
},
  "geometry": {"coordinates":[147.25332641599999,-42.8325691223],"type":"Point"}
}