{
  "type": "Feature",
  "properties": {
    "iso:country":"AU",
    "sg:address":"111 Lennox St",
    "sg:city":"Newtown",
    "sg:classifiers":[
        {
            "category":"Professional",
            "subcategory":"Art Services",
            "type":"Services"
        }
    ],
    "sg:phone":"+61 411 800 588",
    "sg:postcode":"2042",
    "sg:province":"NSW",
    "sg:tags":[
        "picture",
        "frame",
        "framing"
    ],
    "wof:name":"Mobile Framing Service",
    "wof:placetype":"venue"
},
  "geometry": {"coordinates":[151.177567,-33.896267],"type":"Point"}
}