{
  "type": "Feature",
  "properties": {
    "addr:full":"31 Flinders St Queenscliff VIC 3225",
    "addr:housenumber":"31",
    "addr:postcode":"3225",
    "addr:street":"Flinders St",
    "iso:country":"AU",
    "sg:address":"31 Flinders St",
    "sg:city":"Queenscliff",
    "sg:classifiers":[
        {
            "category":"Travel",
            "subcategory":"Hotels & Motels",
            "type":"Entertainment"
        }
    ],
    "sg:phone":"+61 3 5258 1675",
    "sg:postcode":"3225",
    "sg:province":"VIC",
    "wof:name":"Britton I E",
    "wof:placetype":"venue"
},
  "geometry": {"coordinates":[144.65022300000001,-38.270615],"type":"Point"}
}