{
  "type": "Feature",
  "properties": {
    "addr:full":"3 Darsham Ave Lismore NSW 2480",
    "addr:housenumber":"3",
    "addr:postcode":"2480",
    "addr:street":"Darsham Ave",
    "iso:country":"AU",
    "sg:address":"3 Darsham Ave",
    "sg:city":"Lismore",
    "sg:classifiers":[
        {
            "category":"Professional",
            "subcategory":"Art Services",
            "type":"Services"
        }
    ],
    "sg:phone":"+61 2 6622 3941",
    "sg:postcode":"2480",
    "sg:province":"NSW",
    "sg:tags":[
        "decorator",
        "painter"
    ],
    "wof:name":"Hopping R S & L A",
    "wof:placetype":"venue"
},
  "geometry": {"coordinates":[153.27386474599999,-28.8166294098],"type":"Point"}
}