{
  "type": "Feature",
  "properties": {
    "addr:full":"Unit 1/ 31 Innes Rd Greenwich NSW 2065",
    "addr:housenumber":"31",
    "addr:postcode":"2065",
    "addr:street":"Innes Rd",
    "iso:country":"AU",
    "sg:address":"Unit 1/ 31 Innes Rd",
    "sg:city":"Greenwich",
    "sg:classifiers":[
        {
            "category":"Professional",
            "subcategory":"Art Services",
            "type":"Services"
        }
    ],
    "sg:phone":"+61 2 9439 6953",
    "sg:postcode":"2065",
    "sg:province":"NSW",
    "sg:tags":[
        "decorator",
        "painter"
    ],
    "wof:name":"A Better Finish",
    "wof:placetype":"venue"
},
  "geometry": {"coordinates":[151.181762695,-33.822517395],"type":"Point"}
}