{
  "type": "Feature",
  "properties": {
    "addr:full":"PO Box 1 Katoomba NSW 2780",
    "addr:postcode":"2780",
    "iso:country":"AU",
    "sg:address":"PO Box 1",
    "sg:city":"Katoomba",
    "sg:classifiers":[
        {
            "category":"Education",
            "subcategory":"Dance Studio",
            "type":"Public Place"
        }
    ],
    "sg:phone":"+61 2 4784 1534",
    "sg:postcode":"2780",
    "sg:province":"NSW",
    "sg:tags":[
        "venue",
        "tuition"
    ],
    "wof:name":"TM Dance Studios",
    "wof:placetype":"venue"
},
  "geometry": {"coordinates":[150.31053161599999,-33.7118186951],"type":"Point"}
}