{
  "type": "Feature",
  "properties": {
    "addr:full":"Wey St Blackwater QLD 4717",
    "addr:postcode":"4717",
    "addr:street":"Wey St",
    "iso:country":"AU",
    "sg:address":"Wey St",
    "sg:city":"Blackwater",
    "sg:classifiers":[
        {
            "category":"Organizations",
            "subcategory":"Community Association",
            "type":"Services"
        }
    ],
    "sg:phone":"+61 7 4982 6535",
    "sg:postcode":"4717",
    "sg:province":"QLD",
    "sg:tags":[
        "organisation",
        "family",
        "welfare"
    ],
    "wof:name":"Anglicare Central Queensland",
    "wof:placetype":"venue"
},
  "geometry": {"coordinates":[148.87796,-23.58334],"type":"Point"}
}