{
  "type": "Feature",
  "properties": {
    "addr:full":"295 Pacific Hwy Charlestown NSW 2290",
    "addr:housenumber":"295",
    "addr:postcode":"2290",
    "addr:street":"Pacific Hwy",
    "iso:country":"AU",
    "sg:address":"295 Pacific Hwy",
    "sg:city":"Charlestown",
    "sg:classifiers":[
        {
            "category":"Building & Trades",
            "subcategory":"Construction",
            "type":"Services"
        }
    ],
    "sg:phone":"+61 2 4943 9891",
    "sg:postcode":"2290",
    "sg:province":"NSW",
    "sg:tags":[
        "concrete",
        "contractor"
    ],
    "wof:name":"Greg Chapman Concrete",
    "wof:placetype":"venue"
},
  "geometry": {"coordinates":[151.70429992699999,-32.9563560486],"type":"Point"}
}