{
  "type": "Feature",
  "properties": {
    "addr:full":"2 Mitchell Rd Brookvale NSW 2100",
    "addr:housenumber":"2",
    "addr:postcode":"2100",
    "addr:street":"Mitchell Rd",
    "iso:country":"AU",
    "sg:address":"2 Mitchell Rd",
    "sg:city":"Brookvale",
    "sg:classifiers":[
        {
            "category":"Professional",
            "subcategory":"Art Services",
            "type":"Services"
        }
    ],
    "sg:phone":"+61 2 9939 4299",
    "sg:postcode":"2100",
    "sg:province":"NSW",
    "sg:tags":[
        "graphic",
        "designer"
    ],
    "wof:name":"Artopian Pty Ltd",
    "wof:placetype":"venue"
},
  "geometry": {"coordinates":[151.274536133,-33.7622108459],"type":"Point"}
}