{
  "type": "Feature",
  "properties": {
    "addr:full":"PO Box 1506 Rockhampton QLD 4700",
    "addr:postcode":"4700",
    "iso:country":"AU",
    "sg:address":"PO Box 1506",
    "sg:city":"Rockhampton",
    "sg:classifiers":[
        {
            "category":"Education",
            "subcategory":"Special Training",
            "type":"Public Place"
        }
    ],
    "sg:phone":"+61 411 442 688",
    "sg:postcode":"4700",
    "sg:province":"QLD",
    "sg:tags":[
        "development"
    ],
    "wof:name":"Ability Plus Training Services",
    "wof:placetype":"venue"
},
  "geometry": {"coordinates":[150.50942993199999,-23.4106502533],"type":"Point"}
}