{
  "type": "Feature",
  "properties": {
    "addr:full":"70 High St South Gippsland Hwy Woodside VIC 3874",
    "addr:housenumber":"70",
    "addr:postcode":"3874",
    "addr:street":"High St South;Hwy",
    "iso:country":"AU",
    "sg:address":"70 High St South Gippsland Hwy",
    "sg:city":"Woodside",
    "sg:classifiers":[
        {
            "category":"Travel",
            "subcategory":"Hotels & Motels",
            "type":"Entertainment"
        }
    ],
    "sg:phone":"+61 3 5187 1391",
    "sg:postcode":"3874",
    "sg:province":"VIC",
    "wof:name":"Summerbreeze",
    "wof:placetype":"venue"
},
  "geometry": {"coordinates":[146.87448120100001,-38.523651123],"type":"Point"}
}