{
  "type": "Feature",
  "properties": {
    "addr:full":"19 Wray Ave Fremantle WA 6160",
    "addr:housenumber":"19",
    "addr:postcode":"6160",
    "addr:street":"Wray Ave",
    "iso:country":"AU",
    "sg:address":"19 Wray Ave",
    "sg:city":"Fremantle",
    "sg:classifiers":[
        {
            "category":"Food & Beverages",
            "subcategory":"Specialty",
            "type":"Retail Goods"
        }
    ],
    "sg:phone":"+61 8 9335 6157",
    "sg:postcode":"6160",
    "sg:province":"WA",
    "sg:tags":[
        "delicacy"
    ],
    "wof:name":"Galati A & Sons",
    "wof:placetype":"venue"
},
  "geometry": {"coordinates":[115.752876,-32.060287],"type":"Point"}
}