{
  "type": "Feature",
  "properties": {
    "addr:full":"1/ 10 Laurence Rd Walliston WA 6076",
    "addr:housenumber":"/ 10",
    "addr:postcode":"6076",
    "addr:street":"Laurence Rd",
    "iso:country":"AU",
    "sg:address":"1/ 10 Laurence Rd",
    "sg:city":"Walliston",
    "sg:classifiers":[
        {
            "category":"Wholesale",
            "subcategory":"Machinery & Supplies",
            "type":"Manufacturing & Wholesale Goods"
        }
    ],
    "sg:phone":"+61 8 9257 1541",
    "sg:postcode":"6076",
    "sg:province":"WA",
    "sg:tags":[
        "equipment",
        "welding"
    ],
    "wof:name":"Studweld International",
    "wof:placetype":"venue"
},
  "geometry": {"coordinates":[116.0729599,-31.9947032928],"type":"Point"}
}