{
  "type": "Feature",
  "properties": {
    "iso:country":"AU",
    "sg:address":"Napoli St",
    "sg:city":"Padstow",
    "sg:classifiers":[
        {
            "category":"Education",
            "subcategory":"School",
            "type":"Public Place"
        }
    ],
    "sg:phone":"+61 2 9709 4661",
    "sg:postcode":"2211",
    "sg:province":"NSW",
    "sg:tags":[
        "state",
        "-",
        "nsw"
    ],
    "wof:name":"Caroline Chisholm Special School",
    "wof:placetype":"venue"
},
  "geometry": {"coordinates":[151.025436,-33.936733],"type":"Point"}
}