{
  "type": "Feature",
  "properties": {
    "iso:country":"AU",
    "sg:address":"109 Liberty Ave",
    "sg:city":"Rowville",
    "sg:classifiers":[
        {
            "category":"Shopping",
            "subcategory":"Bicycles & Sporting Goods",
            "type":"Retail Goods"
        }
    ],
    "sg:phone":"+61 3 9755 5960",
    "sg:postcode":"3178",
    "sg:province":"VIC",
    "sg:tags":[
        "chemical",
        "equipment",
        "pool",
        "swimming"
    ],
    "wof:name":"Victorian Pool & Spa Services",
    "wof:placetype":"venue"
},
  "geometry": {"coordinates":[145.240692139,-37.9351768494],"type":"Point"}
}