{
  "type": "Feature",
  "properties": {
    "addr:full":"107 Bridge Rd Richmond VIC 3121",
    "addr:housenumber":"107",
    "addr:postcode":"3121",
    "addr:street":"Bridge Rd",
    "iso:country":"AU",
    "sg:address":"107 Bridge Rd",
    "sg:city":"Richmond",
    "sg:classifiers":[
        {
            "category":"Shopping",
            "subcategory":"Clothing, Apparel, & Fashions",
            "type":"Retail Goods"
        }
    ],
    "sg:phone":"+61 3 9429 7508",
    "sg:postcode":"3121",
    "sg:province":"VIC",
    "sg:tags":[
        "lady",
        "wear"
    ],
    "wof:name":"Review Stores",
    "wof:placetype":"venue"
},
  "geometry": {"coordinates":[144.993286133,-37.8177757263],"type":"Point"}
}