{
  "type": "Feature",
  "properties": {
    "addr:full":"440 Shute Harbour Rd Airlie Beach QLD 4802",
    "addr:housenumber":"440",
    "addr:postcode":"4802",
    "addr:street":"Shute Harbour Rd",
    "iso:country":"AU",
    "sg:address":"440 Shute Harbour Rd",
    "sg:city":"Airlie Beach",
    "sg:classifiers":[
        {
            "category":"Travel",
            "subcategory":"Hotels & Motels",
            "type":"Entertainment"
        }
    ],
    "sg:phone":"+61 7 4948 4948",
    "sg:postcode":"4802",
    "sg:province":"QLD",
    "wof:name":"Boathaven Spa Resort",
    "wof:placetype":"venue"
},
  "geometry": {"coordinates":[148.722824097,-20.2727375031],"type":"Point"}
}