{
  "type": "Feature",
  "properties": {
    "addr:full":"1 Lillian St Geelong North VIC 3215",
    "addr:housenumber":"1",
    "addr:postcode":"3215",
    "addr:street":"Lillian St",
    "iso:country":"AU",
    "sg:address":"1 Lillian St",
    "sg:city":"Geelong North",
    "sg:classifiers":[
        {
            "category":"Banks & Credit Unions",
            "subcategory":"Bureau De Change",
            "type":"Services"
        }
    ],
    "sg:phone":"+61 3 5272 2722",
    "sg:postcode":"3215",
    "sg:province":"VIC",
    "sg:tags":[
        "gas",
        "natural",
        "lp",
        "equipment"
    ],
    "wof:name":"Auto Gas Supplies",
    "wof:placetype":"venue"
},
  "geometry": {"coordinates":[144.34677124000001,-38.1006240845],"type":"Point"}
}