{
  "type": "Feature",
  "properties": {
    "addr:full":"Lakes Plaza 371 The Esplanade Lakes Entrance VIC 3909",
    "addr:housenumber":"371",
    "addr:postcode":"3909",
    "addr:street":"The Esplanade",
    "iso:country":"AU",
    "sg:address":"Lakes Plaza 371",
    "sg:city":"The Esplanade Lakes Entrance",
    "sg:classifiers":[
        {
            "category":"Autos & Motor Vehicles",
            "subcategory":"Fuel & Gas Station",
            "type":"Retail Goods"
        }
    ],
    "sg:phone":"+61 3 5155 5194",
    "sg:postcode":"3909",
    "sg:province":"VIC",
    "wof:name":"Safeway + Plus Petrol",
    "wof:placetype":"venue"
},
  "geometry": {"coordinates":[147.98458862300001,-37.8790855408],"type":"Point"}
}