{
  "type": "Feature",
  "properties": {
    "addr:full":"599 The Entrance Rd Bateau Bay NSW 2261",
    "addr:housenumber":"599",
    "addr:postcode":"2261",
    "addr:street":"The Entrance Rd",
    "iso:country":"AU",
    "sg:address":"599 The Entrance Rd",
    "sg:city":"Bateau Bay",
    "sg:classifiers":[
        {
            "category":"Health Services",
            "subcategory":"Doctor",
            "type":"Services"
        }
    ],
    "sg:phone":"+61 2 4332 6411",
    "sg:postcode":"2261",
    "sg:province":"NSW",
    "sg:tags":[
        "medical",
        "practitioner"
    ],
    "wof:name":"Bateau Bay Medical Centre",
    "wof:placetype":"venue"
},
  "geometry": {"coordinates":[151.47273300000001,-33.388298],"type":"Point"}
}