{
  "type": "Feature",
  "properties": {
    "iso:country":"AU",
    "sg:address":"19-21 Loyalty Rd",
    "sg:city":"North Rocks",
    "sg:classifiers":[
        {
            "category":"Wholesale",
            "subcategory":"Electrical",
            "type":"Manufacturing & Wholesale Goods"
        }
    ],
    "sg:phone":"+61 2 8839 9000",
    "sg:postcode":"2151",
    "sg:province":"NSW",
    "sg:tags":[
        "wholesaler"
    ],
    "wof:name":"M M Electrical Merchandising",
    "wof:placetype":"venue"
},
  "geometry": {"coordinates":[151.00796508799999,-33.7748756409],"type":"Point"}
}