{
  "type": "Feature",
  "properties": {
    "iso:country":"AU",
    "sg:address":"310 Spence St",
    "sg:city":"Cairns",
    "sg:classifiers":[
        {
            "category":"Retail",
            "subcategory":"Storage",
            "type":"Services"
        }
    ],
    "sg:phone":"+61 7 4052 1977",
    "sg:postcode":"4870",
    "sg:province":"QLD",
    "wof:name":"Big Blue Self Storage Central",
    "wof:placetype":"venue"
},
  "geometry": {"coordinates":[145.754592895,-16.9412155151],"type":"Point"}
}