{
  "type": "Feature",
  "properties": {
    "addr:full":"197 Norris Creek Rd Munruben QLD 4125",
    "addr:housenumber":"197",
    "addr:postcode":"4125",
    "addr:street":"Norris Creek Rd",
    "iso:country":"AU",
    "sg:address":"197 Norris Creek Rd",
    "sg:city":"Munruben",
    "sg:classifiers":[
        {
            "category":"Building & Trades",
            "subcategory":"Construction",
            "type":"Services"
        }
    ],
    "sg:phone":"+61 7 3802 1334",
    "sg:postcode":"4125",
    "sg:province":"QLD",
    "sg:tags":[
        "waterproofing",
        "contractor"
    ],
    "wof:name":"Mainline Waterproofing (Qld) Pty Ltd",
    "wof:placetype":"venue"
},
  "geometry": {"coordinates":[153.03497314399999,-27.7475776672],"type":"Point"}
}