{
  "type": "Feature",
  "properties": {
    "addr:full":"Shed 1, Shell Truck Stop, Lilbili St Alice Springs NT 0870",
    "addr:housenumber":"1",
    "addr:postcode":"nt 0870",
    "addr:street":"St",
    "iso:country":"AU",
    "sg:address":"Shed 1, Shell Truck Stop, Lilbili St",
    "sg:city":"Alice Springs",
    "sg:classifiers":[
        {
            "category":"Autos & Motor Vehicles",
            "subcategory":"Automobile Sales",
            "type":"Retail Goods"
        }
    ],
    "sg:phone":"+61 8 8953 0031",
    "sg:postcode":"0870",
    "sg:province":"NT",
    "sg:tags":[
        "equipment",
        "trailer"
    ],
    "wof:name":"Aust. Advanced Trailer Sales & Service",
    "wof:placetype":"venue"
},
  "geometry": {"coordinates":[133.86485290499999,-23.6671047211],"type":"Point"}
}