{
  "type": "Feature",
  "properties": {
    "iso:country":"AU",
    "sg:address":"12 Malvern Ave",
    "sg:city":"Chatswood",
    "sg:classifiers":[
        {
            "category":"Health Services",
            "subcategory":"Doctor",
            "type":"Services"
        }
    ],
    "sg:phone":"+61 2 9411 7767",
    "sg:postcode":"2067",
    "sg:province":"NSW",
    "sg:tags":[
        "medical",
        "practitioner"
    ],
    "wof:name":"Chatswood Grove Eye Clinic Pty Ltd",
    "wof:placetype":"venue"
},
  "geometry": {"coordinates":[151.18580627399999,-33.7930221558],"type":"Point"}
}