{
  "type": "Feature",
  "properties": {
    "iso:country":"AU",
    "sg:address":"Unit 3, 71 Stuart St",
    "sg:city":"Bulimba",
    "sg:classifiers":[
        {
            "category":"Manufacturing",
            "subcategory":"Chemicals & Compounds",
            "type":"Manufacturing & Wholesale Goods"
        }
    ],
    "sg:phone":"+61 7 3899 8003",
    "sg:postcode":"4171",
    "sg:province":"QLD",
    "sg:tags":[
        "oil",
        "recovery",
        "dispersal",
        "spill"
    ],
    "wof:name":"Fasteners Direct",
    "wof:placetype":"venue"
},
  "geometry": {"coordinates":[153.05775451700001,-27.4539260864],"type":"Point"}
}