{
  "type": "Feature",
  "properties": {
    "addr:full":"Shop 1 Peter Lalor Mall Lalor VIC 3075",
    "addr:housenumber":"shop 1;lalor",
    "addr:postcode":"3075",
    "iso:country":"AU",
    "sg:address":"Shop 1",
    "sg:city":"Peter Lalor Mall Lalor",
    "sg:classifiers":[
        {
            "category":"Wholesale",
            "subcategory":"Painting Supplies",
            "type":"Manufacturing & Wholesale Goods"
        }
    ],
    "sg:phone":"+61 3 9465 4457",
    "sg:postcode":"3075",
    "sg:province":"VIC",
    "sg:tags":[
        "painter"
    ],
    "wof:name":"Paint Spot",
    "wof:placetype":"venue"
},
  "geometry": {"coordinates":[145.01715087900001,-37.6733055115],"type":"Point"}
}