{
  "type": "Feature",
  "properties": {
    "iso:country":"AU",
    "sg:address":"53 Jersey St",
    "sg:city":"Hornsby",
    "sg:classifiers":[
        {
            "category":"Industrial Area",
            "type":"Public Place"
        }
    ],
    "sg:phone":"+61 2 9482 7553",
    "sg:postcode":"2077",
    "sg:province":"NSW",
    "sg:tags":[
        "rural",
        "shed"
    ],
    "wof:name":"Award Garages & Sheds",
    "wof:placetype":"venue"
},
  "geometry": {"coordinates":[151.09890747099999,-33.6982154846],"type":"Point"}
}