{
  "type": "Feature",
  "properties": {
    "iso:country":"AU",
    "sg:address":"29 Bell St",
    "sg:city":"Preston",
    "sg:classifiers":[
        {
            "category":"Shopping",
            "subcategory":"Stationery & Office Supplies",
            "type":"Retail Goods"
        }
    ],
    "sg:phone":"+61 3 9487 3811",
    "sg:postcode":"3072",
    "sg:province":"VIC",
    "sg:tags":[
        "packaging",
        "material"
    ],
    "wof:name":"Amcor- Flexibles Australasia",
    "wof:placetype":"venue"
},
  "geometry": {"coordinates":[145.02764892600001,-37.7482070923],"type":"Point"}
}