{
  "type": "Feature",
  "properties": {
    "addr:full":"138 Tanti Ave Mornington VIC 3931",
    "addr:housenumber":"138",
    "addr:postcode":"3931",
    "addr:street":"Tanti Ave",
    "iso:country":"AU",
    "sg:address":"138 Tanti Ave",
    "sg:city":"Mornington",
    "sg:classifiers":[
        {
            "category":"Personal",
            "subcategory":"Massage",
            "type":"Services"
        }
    ],
    "sg:phone":"+61 3 5973 6886",
    "sg:postcode":"3931",
    "sg:province":"VIC",
    "sg:tags":[
        "therapy"
    ],
    "wof:name":"Mornington Complementary Medicine",
    "wof:placetype":"venue"
},
  "geometry": {"coordinates":[145.04795837399999,-38.2253723145],"type":"Point"}
}