{
  "type": "Feature",
  "properties": {
    "iso:country":"AU",
    "sg:address":"17 Gairloch St",
    "sg:city":"Applecross",
    "sg:classifiers":[
        {
            "category":"Social Services",
            "subcategory":"Retirement Home",
            "type":"Services"
        }
    ],
    "sg:phone":"+61 8 9316 4646",
    "sg:postcode":"6153",
    "sg:province":"WA",
    "sg:tags":[
        "environmental",
        "consultant",
        "pollution"
    ],
    "wof:name":"John Consulting Services",
    "wof:placetype":"venue"
},
  "geometry": {"coordinates":[115.837059,-32.011539],"type":"Point"}
}