{
  "type": "Feature",
  "properties": {
    "addr:full":"Woodville Rd Granville NSW 2142",
    "addr:postcode":"2142",
    "addr:street":"Woodville Rd",
    "iso:country":"AU",
    "sg:address":"Woodville Rd",
    "sg:city":"Granville",
    "sg:classifiers":[
        {
            "category":"Travel",
            "subcategory":"Hotels & Motels",
            "type":"Entertainment"
        }
    ],
    "sg:phone":"+61 2 9637 2289",
    "sg:postcode":"2142",
    "sg:province":"NSW",
    "sg:tags":[
        "accommodation"
    ],
    "wof:name":"VauxHall Inn",
    "wof:placetype":"venue"
},
  "geometry": {"coordinates":[151.003295898,-33.8317337036],"type":"Point"}
}