{
  "type": "Feature",
  "properties": {
    "addr:full":"5 Howard St Paddington QLD 4064",
    "addr:housenumber":"5",
    "addr:postcode":"4064",
    "addr:street":"Howard St",
    "iso:country":"AU",
    "sg:address":"5 Howard St",
    "sg:city":"Paddington",
    "sg:classifiers":[
        {
            "category":"Health Services",
            "subcategory":"Doctor",
            "type":"Services"
        }
    ],
    "sg:phone":"+61 7 3369 5433",
    "sg:postcode":"4064",
    "sg:province":"QLD",
    "sg:tags":[
        "medical",
        "practitioner"
    ],
    "wof:name":"Brown David",
    "wof:placetype":"venue"
},
  "geometry": {"coordinates":[152.998138428,-27.4671916962],"type":"Point"}
}