{
  "type": "Feature",
  "properties": {
    "addr:full":"1/ 21 Stirling Hwy Nedlands WA 6009",
    "addr:housenumber":"/ 21",
    "addr:postcode":"6009",
    "addr:street":"Stirling Hwy",
    "iso:country":"AU",
    "sg:address":"1/ 21 Stirling Hwy",
    "sg:city":"Nedlands",
    "sg:classifiers":[
        {
            "category":"Health Services",
            "subcategory":"Doctor",
            "type":"Services"
        }
    ],
    "sg:phone":"+61 8 9389 6000",
    "sg:postcode":"6009",
    "sg:province":"WA",
    "sg:tags":[
        "medical",
        "practitioner"
    ],
    "wof:name":"Martinick Jennifer Dr",
    "wof:placetype":"venue"
},
  "geometry": {"coordinates":[115.811638,-31.977598],"type":"Point"}
}