{
  "type": "Feature",
  "properties": {
    "iso:country":"AU",
    "sg:address":"14 Seville Ave",
    "sg:city":"Gulfview Heights",
    "sg:classifiers":[
        {
            "category":"Building & Trades",
            "subcategory":"Construction",
            "type":"Services"
        }
    ],
    "sg:phone":"+61 8 8182 4959",
    "sg:postcode":"5096",
    "sg:province":"SA",
    "sg:tags":[
        "contractor"
    ],
    "wof:name":"City Builders",
    "wof:placetype":"venue"
},
  "geometry": {"coordinates":[138.66232299800001,-34.7980690002],"type":"Point"}
}