{
  "type": "Feature",
  "properties": {
    "addr:full":"483 Hunter St Newcastle NSW 2300",
    "addr:housenumber":"483",
    "addr:postcode":"2300",
    "addr:street":"Hunter St",
    "iso:country":"AU",
    "sg:address":"483 Hunter St",
    "sg:city":"Newcastle",
    "sg:classifiers":[
        {
            "category":"Retail",
            "subcategory":"Repair Shop",
            "type":"Services"
        }
    ],
    "sg:phone":"+61 2 4929 4456",
    "sg:postcode":"2300",
    "sg:province":"NSW",
    "sg:tags":[
        "machine",
        "sewing"
    ],
    "sg:website":"http://www.thorpeandco.com.au",
    "wof:name":"NH Thorpe & Co",
    "wof:placetype":"venue"
},
  "geometry": {"coordinates":[151.76885999999999,-32.927429],"type":"Point"}
}