{
  "type": "Feature",
  "properties": {
    "addr:full":"Cnr Pacific Hwy & Jersey St Mt Colah NSW 2079",
    "addr:postcode":"2079",
    "addr:street":"Cnr Pacific Hwy & Jersey St Mt Colah",
    "iso:country":"AU",
    "sg:address":"Cnr Pacific Hwy & Jersey St",
    "sg:city":"Mt Colah",
    "sg:classifiers":[
        {
            "category":"Fast Food",
            "type":"Food & Drink"
        }
    ],
    "sg:phone":"+61 2 9476 3322",
    "sg:postcode":"2079",
    "sg:province":"NSW",
    "sg:tags":[
        "away",
        "take"
    ],
    "wof:name":"La Porchetta Mt Colah",
    "wof:placetype":"venue"
},
  "geometry": {"coordinates":[151.11697387699999,-33.6694717407],"type":"Point"}
}