{
  "type": "Feature",
  "properties": {
    "iso:country":"AU",
    "sg:address":"Queens Wharf Rd",
    "sg:city":"North Quay",
    "sg:classifiers":[
        {
            "category":"Retail",
            "subcategory":"Event Space",
            "type":"Services"
        }
    ],
    "sg:phone":"+61 7 3262 7422",
    "sg:postcode":"4002",
    "sg:province":"QLD",
    "sg:tags":[
        "venue",
        "reception",
        "wedding"
    ],
    "wof:name":"Brisbane Paddlewheeler",
    "wof:placetype":"venue"
},
  "geometry": {"coordinates":[153.02789306599999,-27.4675807953],"type":"Point"}
}