{
  "type": "Feature",
  "properties": {
    "iso:country":"AU",
    "sg:address":"Shop 1/ 276 Invermay Rd",
    "sg:city":"Mowbray",
    "sg:classifiers":[
        {
            "category":"Cafe",
            "type":"Food & Drink"
        }
    ],
    "sg:phone":"+61 3 6326 2510",
    "sg:postcode":"7248",
    "sg:province":"TAS",
    "wof:name":"Top Of The Hill Cafe",
    "wof:placetype":"venue"
},
  "geometry": {"coordinates":[147.13250732399999,-41.4049110413],"type":"Point"}
}