{
  "type": "Feature",
  "properties": {
    "addr:full":"21 Mayfield St Greensborough VIC 3088",
    "addr:housenumber":"21",
    "addr:postcode":"3088",
    "addr:street":"Mayfield St",
    "iso:country":"AU",
    "sg:address":"21 Mayfield St",
    "sg:city":"Greensborough",
    "sg:classifiers":[
        {
            "category":"Building & Trades",
            "subcategory":"Plumbing",
            "type":"Services"
        }
    ],
    "sg:phone":"+61 418 359 936",
    "sg:postcode":"3088",
    "sg:province":"VIC",
    "sg:tags":[
        "plumber",
        "gasfitters"
    ],
    "wof:name":"R & R Hall Plumbing",
    "wof:placetype":"venue"
},
  "geometry": {"coordinates":[145.09669494600001,-37.7005653381],"type":"Point"}
}