{
  "type": "Feature",
  "properties": {
    "addr:full":"Level 1, 104 Little Malop St Geelong VIC 3220",
    "addr:housenumber":"104",
    "addr:postcode":"3220",
    "addr:street":"Little Malop St",
    "iso:country":"AU",
    "sg:address":"Level 1, 104 Little Malop St",
    "sg:city":"Geelong",
    "sg:classifiers":[
        {
            "category":"Shopping",
            "subcategory":"Computers & Home Electronics",
            "type":"Retail Goods"
        }
    ],
    "sg:phone":"+61 3 5221 6382",
    "sg:postcode":"3220",
    "sg:province":"VIC",
    "sg:tags":[
        "equipment",
        "multimedia"
    ],
    "wof:name":"Getpixel Multimedia",
    "wof:placetype":"venue"
},
  "geometry": {"coordinates":[144.36085499999999,-38.148571],"type":"Point"}
}