{
  "type": "Feature",
  "properties": {
    "addr:full":"13 Maywood Rd Cranbourne South VIC 3977",
    "addr:housenumber":"13",
    "addr:postcode":"3977",
    "addr:street":"Maywood Rd",
    "iso:country":"AU",
    "sg:address":"13 Maywood Rd",
    "sg:city":"Cranbourne South",
    "sg:classifiers":[
        {
            "category":"Building & Trades",
            "subcategory":"Construction",
            "type":"Services"
        }
    ],
    "sg:phone":"+61 418 525 079",
    "sg:postcode":"3977",
    "sg:province":"VIC",
    "sg:tags":[
        "earth",
        "excavating",
        "moving",
        "contractor"
    ],
    "wof:name":"Pearcedale Excavation",
    "wof:placetype":"venue"
},
  "geometry": {"coordinates":[145.251098633,-38.1663780212],"type":"Point"}
}