{
  "type": "Feature",
  "properties": {
    "addr:full":"45 Wellington Rd Bittern VIC 3918",
    "addr:housenumber":"45",
    "addr:postcode":"3918",
    "addr:street":"Wellington Rd",
    "iso:country":"AU",
    "sg:address":"45 Wellington Rd",
    "sg:city":"Bittern",
    "sg:classifiers":[
        {
            "category":"Recreation",
            "subcategory":"Boat Charter",
            "type":"Entertainment"
        }
    ],
    "sg:phone":"+61 3 5983 8087",
    "sg:postcode":"3918",
    "sg:province":"VIC",
    "sg:tags":[
        "canopy",
        "motor"
    ],
    "wof:name":"Bronco Canopies",
    "wof:placetype":"venue"
},
  "geometry": {"coordinates":[145.15614318900001,-38.3580436707],"type":"Point"}
}