{
  "type": "Feature",
  "properties": {
    "iso:country":"AU",
    "sg:address":"1 Susan St",
    "sg:city":"Hindmarsh",
    "sg:classifiers":[
        {
            "category":"Professional",
            "subcategory":"Accounting & Tax Preparation",
            "type":"Services"
        }
    ],
    "sg:phone":"+61 8 8340 8177",
    "sg:postcode":"5007",
    "sg:province":"SA",
    "sg:tags":[
        "bookkeeping"
    ],
    "wof:name":"Ledger Bookeeping",
    "wof:placetype":"venue"
},
  "geometry": {"coordinates":[138.56767273,-34.9079360962],"type":"Point"}
}