{
  "type": "Feature",
  "properties": {
    "addr:full":"Rear 120A, John St Singleton NSW 2330",
    "addr:housenumber":"120a",
    "addr:postcode":"2330",
    "addr:street":"John St",
    "iso:country":"AU",
    "sg:address":"Rear 120A, John St",
    "sg:city":"Singleton",
    "sg:classifiers":[
        {
            "category":"Education",
            "subcategory":"Special Training",
            "type":"Public Place"
        }
    ],
    "sg:phone":"+61 2 6571 1101",
    "sg:postcode":"2330",
    "sg:province":"NSW",
    "sg:tags":[
        "tuition-educational"
    ],
    "wof:name":"Kip McGrath Education Centres",
    "wof:placetype":"venue"
},
  "geometry": {"coordinates":[151.167023,-32.565193],"type":"Point"}
}