{
  "type": "Feature",
  "properties": {
    "iso:country":"AU",
    "sg:address":"92 Park Beach Rd",
    "sg:city":"Coffs Harbour",
    "sg:classifiers":[
        {
            "category":"Restaurant",
            "type":"Food & Drink"
        }
    ],
    "sg:phone":"+61 2 6651 4777",
    "sg:postcode":"2450",
    "sg:province":"NSW",
    "wof:name":"Granma's Restaurant",
    "wof:placetype":"venue"
},
  "geometry": {"coordinates":[153.132416,-30.285742],"type":"Point"}
}