{
  "type": "Feature",
  "properties": {
    "iso:country":"AU",
    "sg:address":"48 Darling Rd",
    "sg:city":"Malvern East",
    "sg:classifiers":[
        {
            "category":"Retail",
            "subcategory":"Storage",
            "type":"Services"
        }
    ],
    "sg:phone":"+61 3 9572 2206",
    "sg:postcode":"3145",
    "sg:province":"VIC",
    "sg:tags":[
        "removal",
        "furniture"
    ],
    "wof:name":"Olympic Furniture Removalist",
    "wof:placetype":"venue"
},
  "geometry": {"coordinates":[145.05897522000001,-37.8798751831],"type":"Point"}
}