{
  "type": "Feature",
  "properties": {
    "addr:full":"80 B Cabbage Tree Rd Bayview NSW 2104",
    "addr:housenumber":"80 b",
    "addr:postcode":"2104",
    "addr:street":"Cabbage Tree Rd",
    "iso:country":"AU",
    "sg:address":"80 B Cabbage Tree Rd",
    "sg:city":"Bayview",
    "sg:classifiers":[
        {
            "category":"Building & Trades",
            "subcategory":"Construction",
            "type":"Services"
        }
    ],
    "sg:phone":"+61 419 691 204",
    "sg:postcode":"2104",
    "sg:province":"NSW",
    "sg:tags":[
        "contractor"
    ],
    "wof:name":"Rojo Construction Group",
    "wof:placetype":"venue"
},
  "geometry": {"coordinates":[151.292236,-33.668594],"type":"Point"}
}