{
  "type": "Feature",
  "properties": {
    "iso:country":"AU",
    "sg:address":"Cnr Australis Ave & Village Way",
    "sg:city":"Wattle Grove",
    "sg:classifiers":[
        {
            "category":"Travel",
            "subcategory":"Hotels & Motels",
            "type":"Entertainment"
        }
    ],
    "sg:phone":"+61 2 9731 1023",
    "sg:postcode":"2173",
    "sg:province":"NSW",
    "sg:tags":[
        "pub"
    ],
    "wof:name":"Wattle Grove Club Hotel",
    "wof:placetype":"venue"
},
  "geometry": {"coordinates":[150.94252014200001,-33.9550209045],"type":"Point"}
}