{
  "type": "Feature",
  "properties": {
    "iso:country":"AU",
    "sg:address":"1/ 21 Park St",
    "sg:city":"Glenbrook",
    "sg:classifiers":[
        {
            "category":"Health Services",
            "subcategory":"Chiropractor",
            "type":"Services"
        }
    ],
    "sg:phone":"+61 2 4753 6380",
    "sg:postcode":"2773",
    "sg:province":"NSW",
    "wof:name":"Bridle Ross",
    "wof:placetype":"venue"
},
  "geometry": {"coordinates":[150.62112426799999,-33.766658783],"type":"Point"}
}