{
  "type": "Feature",
  "properties": {
    "addr:full":"Unit 1/32- 60 Alice St Newtown NSW 2042",
    "addr:housenumber":"60",
    "addr:postcode":"2042",
    "addr:street":"Alice St",
    "iso:country":"AU",
    "sg:address":"Unit 1/32- 60 Alice St",
    "sg:city":"Newtown",
    "sg:classifiers":[
        {
            "category":"Banks & Credit Unions",
            "subcategory":"Bank",
            "type":"Services"
        }
    ],
    "sg:phone":"+61 2 9565 2685",
    "sg:postcode":"2042",
    "sg:province":"NSW",
    "sg:tags":[
        "leather",
        "cutting",
        "fabric",
        "plastic"
    ],
    "wof:name":"Roberto El Fashions Pty Ltd",
    "wof:placetype":"venue"
},
  "geometry": {"coordinates":[151.177628,-33.903648],"type":"Point"}
}