{
  "type": "Feature",
  "properties": {
    "addr:full":"12 Bosworth Rd Woolgoolga NSW 2456",
    "addr:housenumber":"12",
    "addr:postcode":"2456",
    "addr:street":"Bosworth Rd",
    "iso:country":"AU",
    "sg:address":"12 Bosworth Rd",
    "sg:city":"Woolgoolga",
    "sg:phone":"+61 2 6654 1888",
    "sg:postcode":"2456",
    "sg:province":"NSW",
    "wof:name":"Coffs Harbour Septic Tanks",
    "wof:placetype":"venue"
},
  "geometry": {"coordinates":[153.19366500000001,-30.125216],"type":"Point"}
}