{
  "type": "Feature",
  "properties": {
    "addr:full":"352 Swansea Rd Lilydale VIC 3140",
    "addr:housenumber":"352",
    "addr:postcode":"3140",
    "addr:street":"Swansea Rd",
    "iso:country":"AU",
    "sg:address":"352 Swansea Rd",
    "sg:city":"Lilydale",
    "sg:classifiers":[
        {
            "category":"Utilities",
            "subcategory":"Refuse",
            "type":"Services"
        }
    ],
    "sg:phone":"+61 3 9739 4749",
    "sg:postcode":"3140",
    "sg:province":"VIC",
    "sg:tags":[
        "remover",
        "rubbish"
    ],
    "wof:name":"T-Rex Bin Hire",
    "wof:placetype":"venue"
},
  "geometry": {"coordinates":[145.363372803,-37.7746276855],"type":"Point"}
}