{
  "type": "Feature",
  "properties": {
    "addr:full":"Shop 10a, (Union Square Pharmacy) 190-196 Union St Brunswick West VIC 3055",
    "addr:housenumber":"10a;190-196",
    "addr:postcode":"3055",
    "addr:street":"Union St",
    "iso:country":"AU",
    "sg:address":"Shop 10a, (Union Square Pharmacy) 190-196 Union St",
    "sg:city":"Brunswick West",
    "sg:classifiers":[
        {
            "category":"Health Services",
            "subcategory":"Optometrist",
            "type":"Services"
        }
    ],
    "sg:phone":"+61 3 9380 9535",
    "sg:postcode":"3055",
    "sg:province":"VIC",
    "wof:name":"Plus Optics",
    "wof:placetype":"venue"
},
  "geometry": {"coordinates":[144.947143555,-37.7724075317],"type":"Point"}
}