{
  "type": "Feature",
  "properties": {
    "addr:full":"9 Left Bank Rd Mullumbimby NSW 2482",
    "addr:housenumber":"9",
    "addr:postcode":"2482",
    "addr:street":"Left Bank Rd",
    "iso:country":"AU",
    "sg:address":"9 Left Bank Rd",
    "sg:city":"Mullumbimby",
    "sg:classifiers":[
        {
            "category":"Landmark",
            "subcategory":"City Walls",
            "type":"Public Place"
        }
    ],
    "sg:phone":"+61 2 6684 1053",
    "sg:postcode":"2482",
    "sg:province":"NSW",
    "sg:tags":[
        "finish"
    ],
    "wof:name":"A C & H M East",
    "wof:placetype":"venue"
},
  "geometry": {"coordinates":[153.49993896500001,-28.5531997681],"type":"Point"}
}