{
  "type": "Feature",
  "properties": {
    "iso:country":"AU",
    "sg:address":"79 Cecil Ave",
    "sg:city":"Castle Hill",
    "sg:classifiers":[
        {
            "category":"Health Services",
            "subcategory":"Dentist",
            "type":"Services"
        }
    ],
    "sg:phone":"+61 2 9659 1200",
    "sg:postcode":"2154",
    "sg:province":"NSW",
    "wof:name":"Hawkins G. Dr",
    "wof:placetype":"venue"
},
  "geometry": {"coordinates":[151.00169372600001,-33.7342185974],"type":"Point"}
}