{
  "type": "Feature",
  "properties": {
    "addr:full":"39 Mccracken Ave Northcote VIC 3070",
    "addr:housenumber":"39",
    "addr:postcode":"3070",
    "addr:street":"Mccracken Ave",
    "iso:country":"AU",
    "sg:address":"39 Mccracken Ave",
    "sg:city":"Northcote",
    "sg:classifiers":[
        {
            "category":"Building & Trades",
            "subcategory":"Plumbing",
            "type":"Services"
        }
    ],
    "sg:phone":"+61 3 9481 1603",
    "sg:postcode":"3070",
    "sg:province":"VIC",
    "sg:tags":[
        "plumber",
        "gasfitters"
    ],
    "wof:name":"Westgarth Plumbing Service",
    "wof:placetype":"venue"
},
  "geometry": {"coordinates":[144.99461400000001,-37.769802],"type":"Point"}
}