{
  "type": "Feature",
  "properties": {
    "iso:country":"AU",
    "sg:address":"2 Cahill Crt",
    "sg:city":"Yarrawonga",
    "sg:classifiers":[
        {
            "category":"Utilities",
            "subcategory":"Electric",
            "type":"Services"
        }
    ],
    "sg:phone":"+61 3 5744 1355",
    "sg:postcode":"3730",
    "sg:province":"VIC",
    "sg:tags":[
        "electrical",
        "contractor"
    ],
    "wof:name":"Nicholson P & D M",
    "wof:placetype":"venue"
},
  "geometry": {"coordinates":[146.006759644,-36.0222434998],"type":"Point"}
}