{
  "type": "Feature",
  "properties": {
    "addr:full":"30 Second St Orroroo SA 5431",
    "addr:housenumber":"30",
    "addr:postcode":"5431",
    "addr:street":"Second St",
    "iso:country":"AU",
    "sg:address":"30 Second St",
    "sg:city":"Orroroo",
    "sg:classifiers":[
        {
            "category":"Travel",
            "subcategory":"Hotels & Motels",
            "type":"Entertainment"
        }
    ],
    "sg:phone":"+61 8 8658 1272",
    "sg:postcode":"5431",
    "sg:province":"SA",
    "sg:tags":[
        "accommodation"
    ],
    "wof:name":"Orroroo Commercial Hotel",
    "wof:placetype":"venue"
},
  "geometry": {"coordinates":[138.61593627900001,-32.7354927063],"type":"Point"}
}