{
  "type": "Feature",
  "properties": {
    "addr:full":"128 Cross St Footscray West VIC 3012",
    "addr:housenumber":"128",
    "addr:postcode":"3012",
    "addr:street":"Cross St",
    "iso:country":"AU",
    "sg:address":"128 Cross St",
    "sg:city":"Footscray West",
    "sg:classifiers":[
        {
            "category":"Professional",
            "subcategory":"Art Services",
            "type":"Services"
        }
    ],
    "sg:phone":"+61 414 374 724",
    "sg:postcode":"3012",
    "sg:province":"VIC",
    "sg:tags":[
        "decorator",
        "painter"
    ],
    "wof:name":"Decorative Colors Painting & Decorating",
    "wof:placetype":"venue"
},
  "geometry": {"coordinates":[144.87640380900001,-37.8000411987],"type":"Point"}
}