{
  "type": "Feature",
  "properties": {
    "addr:full":"27 Wellington St North Hobart TAS 7000",
    "addr:housenumber":"27",
    "addr:postcode":"7000",
    "addr:street":"Wellington St",
    "iso:country":"AU",
    "sg:address":"27 Wellington St",
    "sg:city":"North Hobart",
    "sg:classifiers":[
        {
            "category":"Manufacturing",
            "subcategory":"Furniture",
            "type":"Manufacturing & Wholesale Goods"
        }
    ],
    "sg:phone":"+61 3 6231 0363",
    "sg:postcode":"7000",
    "sg:province":"TAS",
    "sg:tags":[
        "builder",
        "designer",
        "custom"
    ],
    "wof:name":"Chris St. Hill",
    "wof:placetype":"venue"
},
  "geometry": {"coordinates":[147.31907653799999,-42.8707542419],"type":"Point"}
}