{
  "type": "Feature",
  "properties": {
    "addr:full":"4 Edwards St Ayr QLD 4807",
    "addr:housenumber":"4",
    "addr:postcode":"4807",
    "addr:street":"Edwards St",
    "iso:country":"AU",
    "sg:address":"4 Edwards St",
    "sg:city":"Ayr",
    "sg:classifiers":[
        {
            "category":"Travel",
            "subcategory":"Hotels & Motels",
            "type":"Entertainment"
        }
    ],
    "sg:phone":"+61 7 4783 2033",
    "sg:postcode":"4807",
    "sg:province":"QLD",
    "wof:name":"Ayr Max Motel",
    "wof:placetype":"venue"
},
  "geometry": {"coordinates":[147.394897461,-19.5647010803],"type":"Point"}
}