{
  "type": "Feature",
  "properties": {
    "addr:full":"Farm 102 Petersham Rd Leeton NSW 2705",
    "addr:housenumber":"102",
    "addr:postcode":"2705",
    "addr:street":"Petersham Rd",
    "iso:country":"AU",
    "sg:address":"Farm 102 Petersham Rd",
    "sg:city":"Leeton",
    "sg:classifiers":[
        {
            "category":"Building & Trades",
            "subcategory":"Construction",
            "type":"Services"
        }
    ],
    "sg:phone":"+61 2 6953 4445",
    "sg:postcode":"2705",
    "sg:province":"NSW",
    "sg:tags":[
        "earth",
        "excavating",
        "moving",
        "contractor"
    ],
    "wof:name":"P & G Digger Pty Ltd",
    "wof:placetype":"venue"
},
  "geometry": {"coordinates":[146.415359497,-34.5621528625],"type":"Point"}
}