{
  "type": "Feature",
  "properties": {
    "addr:full":"Suite 2, 1st Floor, 50- 54 Madden Ave Mildura VIC 3500",
    "addr:housenumber":"50 54",
    "addr:postcode":"3500",
    "addr:street":"Madden Ave",
    "iso:country":"AU",
    "sg:address":"Suite 2, 1st Floor, 50- 54 Madden Ave",
    "sg:city":"Mildura",
    "sg:classifiers":[
        {
            "category":"Professional",
            "subcategory":"Engineering",
            "type":"Services"
        }
    ],
    "sg:phone":"+61 3 5021 2424",
    "sg:postcode":"3500",
    "sg:province":"VIC",
    "sg:tags":[
        "consulting",
        "engineer"
    ],
    "wof:name":"Inland Consultants",
    "wof:placetype":"venue"
},
  "geometry": {"coordinates":[142.16351318400001,-34.1864128113],"type":"Point"}
}