{
  "type": "Feature",
  "properties": {
    "iso:country":"AU",
    "sg:address":"50- 60 Harper St",
    "sg:city":"Ashmore",
    "sg:classifiers":[
        {
            "category":"Utilities",
            "subcategory":"Refuse",
            "type":"Services"
        }
    ],
    "sg:phone":"+61 7 5593 5766",
    "sg:postcode":"4214",
    "sg:province":"QLD",
    "sg:tags":[
        "remover",
        "rubbish"
    ],
    "wof:name":"Miniskips",
    "wof:placetype":"venue"
},
  "geometry": {"coordinates":[153.359817505,-27.9846878052],"type":"Point"}
}