{
  "type": "Feature",
  "properties": {
    "addr:full":"10 Bay Rd Sandringham VIC 3191",
    "addr:housenumber":"10",
    "addr:postcode":"3191",
    "addr:street":"Bay Rd",
    "iso:country":"AU",
    "sg:address":"10 Bay Rd",
    "sg:city":"Sandringham",
    "sg:classifiers":[
        {
            "category":"Real Estate",
            "subcategory":"Real Estate Agent",
            "type":"Services"
        }
    ],
    "sg:phone":"+61 3 9598 9444",
    "sg:postcode":"3191",
    "sg:province":"VIC",
    "wof:name":"Peter Gordon Real Estate",
    "wof:placetype":"venue"
},
  "geometry": {"coordinates":[145.004196167,-37.951839447],"type":"Point"}
}