{
  "type": "Feature",
  "properties": {
    "addr:full":"10 College Rd Gooseberry Hill WA 6076",
    "addr:housenumber":"10",
    "addr:postcode":"6076",
    "addr:street":"College Rd",
    "iso:country":"AU",
    "sg:address":"10 College Rd",
    "sg:city":"Gooseberry Hill",
    "sg:classifiers":[
        {
            "category":"Real Estate",
            "subcategory":"Architect",
            "type":"Services"
        }
    ],
    "sg:phone":"+61 8 6293 1301",
    "sg:postcode":"6076",
    "sg:province":"WA",
    "wof:name":"Hardman W",
    "wof:placetype":"venue"
},
  "geometry": {"coordinates":[116.04863739,-31.9627475739],"type":"Point"}
}