{
  "type": "Feature",
  "properties": {
    "addr:full":"Level 1, Suite 3, 98 Cambridge St West Leederville WA 6007",
    "addr:housenumber":"98",
    "addr:postcode":"6007",
    "addr:street":"Cambridge St West",
    "iso:country":"AU",
    "sg:address":"Level 1, Suite 3, 98 Cambridge St",
    "sg:city":"West Leederville",
    "sg:classifiers":[
        {
            "category":"Health Services",
            "subcategory":"Dentist",
            "type":"Services"
        }
    ],
    "sg:phone":"+61 8 9382 8266",
    "sg:postcode":"6007",
    "sg:province":"WA",
    "sg:website":"http://www.ccdental.com.au",
    "wof:name":"Cambridge City Dental",
    "wof:placetype":"venue"
},
  "geometry": {"coordinates":[115.835533142,-31.9405441284],"type":"Point"}
}