{
  "type": "Feature",
  "properties": {
    "addr:full":"146 - 148 Glebe Point Rd Glebe NSW 2037",
    "addr:housenumber":"148",
    "addr:postcode":"2037",
    "addr:street":"Glebe Point Rd",
    "iso:country":"AU",
    "sg:address":"146 - 148 Glebe Point Rd",
    "sg:city":"Glebe",
    "sg:classifiers":[
        {
            "category":"Travel",
            "subcategory":"Hotels & Motels",
            "type":"Entertainment"
        }
    ],
    "sg:phone":"+61 2 9660 7711",
    "sg:postcode":"2037",
    "sg:province":"NSW",
    "sg:website":"http://www.rooftoptravellerslodge.com",
    "wof:name":"Rooftop Travellers Lodge",
    "wof:placetype":"venue"
},
  "geometry": {"coordinates":[151.186676025,-33.8795776367],"type":"Point"}
}