{
  "type": "Feature",
  "properties": {
    "addr:full":"Goulburn St Broadmeadows VIC 3047",
    "addr:postcode":"3047",
    "addr:street":"Goulburn St",
    "iso:country":"AU",
    "sg:address":"Goulburn St",
    "sg:city":"Broadmeadows",
    "sg:classifiers":[
        {
            "category":"Education",
            "subcategory":"School",
            "type":"Public Place"
        }
    ],
    "sg:phone":"+61 3 9309 0388",
    "sg:postcode":"3047",
    "sg:province":"VIC",
    "sg:tags":[
        "co-educational"
    ],
    "wof:name":"Isik College",
    "wof:placetype":"venue"
},
  "geometry": {"coordinates":[144.93487548799999,-37.6847000122],"type":"Point"}
}