{
  "type": "Feature",
  "properties": {
    "iso:country":"AU",
    "sg:address":"28 Halloran St",
    "sg:city":"Lilyfield",
    "sg:classifiers":[
        {
            "category":"Autos & Motor Vehicles",
            "subcategory":"Automobile Sales",
            "type":"Retail Goods"
        }
    ],
    "sg:phone":"+61 2 8755 2000",
    "sg:postcode":"2040",
    "sg:province":"NSW",
    "sg:tags":[
        "car",
        "new"
    ],
    "wof:name":"Sydney City Subaru",
    "wof:placetype":"venue"
},
  "geometry": {"coordinates":[151.165054,-33.872192],"type":"Point"}
}