{
  "type": "Feature",
  "properties": {
    "addr:full":"127 Catherderal St Woolloomooloo NSW 2011",
    "addr:housenumber":"127",
    "addr:postcode":"2011",
    "addr:street":"Catherderal St",
    "iso:country":"AU",
    "sg:address":"127 Catherderal St",
    "sg:city":"Woolloomooloo",
    "sg:classifiers":[
        {
            "category":"Professional",
            "subcategory":"Art Services",
            "type":"Services"
        }
    ],
    "sg:phone":"+61 2 9368 0140",
    "sg:postcode":"2011",
    "sg:province":"NSW",
    "sg:tags":[
        "interior",
        "designer"
    ],
    "wof:name":"Greg de Montfort Project Management",
    "wof:placetype":"venue"
},
  "geometry": {"coordinates":[151.217453003,-33.8725891113],"type":"Point"}
}