{
  "type": "Feature",
  "properties": {
    "iso:country":"AU",
    "sg:address":"Hannaford Rd",
    "sg:city":"Blackwood",
    "sg:classifiers":[
        {
            "category":"Government",
            "subcategory":"City Hall",
            "type":"Public Place"
        }
    ],
    "sg:phone":"+61 8 8278 4554",
    "sg:postcode":"5051",
    "sg:province":"SA",
    "wof:name":"Blackwood Wittunga Guide Hall",
    "wof:placetype":"venue"
},
  "geometry": {"coordinates":[138.609528,-35.013687],"type":"Point"}
}