{
  "type": "Feature",
  "properties": {
    "addr:full":"4 Bentley St Wetherill Park NSW 2164",
    "addr:housenumber":"4",
    "addr:postcode":"2164",
    "addr:street":"Bentley St",
    "iso:country":"AU",
    "sg:address":"4 Bentley St",
    "sg:city":"Wetherill Park",
    "sg:classifiers":[
        {
            "category":"Home & Garden",
            "subcategory":"Furniture",
            "type":"Retail Goods"
        }
    ],
    "sg:phone":"+61 2 9756 4988",
    "sg:postcode":"2164",
    "sg:province":"NSW",
    "sg:tags":[
        "business"
    ],
    "wof:name":"Acoustics & Felts Pty Ltd",
    "wof:placetype":"venue"
},
  "geometry": {"coordinates":[150.883056641,-33.8479804993],"type":"Point"}
}