{
  "type": "Feature",
  "properties": {
    "iso:country":"AU",
    "sg:address":"Unit 2 17 Powdrill Rd",
    "sg:city":"Hoxton Park",
    "sg:classifiers":[
        {
            "category":"Home & Garden",
            "subcategory":"Carpets & Floor Coverings",
            "type":"Retail Goods"
        }
    ],
    "sg:phone":"+61 2 9607 3472",
    "sg:postcode":"2171",
    "sg:province":"NSW",
    "sg:tags":[
        "mat",
        "matting"
    ],
    "wof:name":"A D K Enterprises",
    "wof:placetype":"venue"
},
  "geometry": {"coordinates":[150.84803772000001,-33.9280090332],"type":"Point"}
}