{
  "type": "Feature",
  "properties": {
    "addr:full":"88 Rosedale Ave Greenacre NSW 2190",
    "addr:housenumber":"88",
    "addr:postcode":"2190",
    "addr:street":"Rosedale Ave",
    "iso:country":"AU",
    "sg:address":"88 Rosedale Ave",
    "sg:city":"Greenacre",
    "sg:phone":"+61 2 9796 8105",
    "sg:postcode":"2190",
    "sg:province":"NSW",
    "wof:name":"Treloar Bowcock Manufacturing Pty Ltd",
    "wof:placetype":"venue"
},
  "geometry": {"coordinates":[151.04104599999999,-33.901283],"type":"Point"}
}