{
  "type": "Feature",
  "properties": {
    "iso:country":"AU",
    "sg:address":"Suite 5, 596 North Rd",
    "sg:city":"Ormond",
    "sg:classifiers":[
        {
            "category":"Farming",
            "subcategory":"Crops",
            "type":"Manufacturing & Wholesale Goods"
        }
    ],
    "sg:phone":"+61 3 9274 6777",
    "sg:postcode":"3204",
    "sg:province":"VIC",
    "sg:tags":[
        "warehousing"
    ],
    "wof:name":"Active Fulfilment",
    "wof:placetype":"venue"
},
  "geometry": {"coordinates":[145.04167200000001,-37.90427],"type":"Point"}
}