{
  "type": "Feature",
  "properties": {
    "addr:full":"Union Bridge Rd Mole Creek TAS 7304",
    "addr:postcode":"7304",
    "addr:street":"Union Bridge Rd Mole",
    "iso:country":"AU",
    "sg:address":"Union Bridge Rd",
    "sg:city":"Mole Creek",
    "sg:classifiers":[
        {
            "category":"Building & Trades",
            "subcategory":"Construction",
            "type":"Services"
        }
    ],
    "sg:phone":"+61 3 6363 1127",
    "sg:postcode":"7304",
    "sg:province":"TAS",
    "sg:tags":[
        "contractor"
    ],
    "wof:name":"Green A G",
    "wof:placetype":"venue"
},
  "geometry": {"coordinates":[146.36019899999999,-41.552162],"type":"Point"}
}