{
  "type": "Feature",
  "properties": {
    "addr:full":"Shop 3, 11 The Mall Alice Springs NT 0871",
    "addr:housenumber":"shop;11",
    "addr:postcode":"nt 0871",
    "addr:street":"The Mall",
    "iso:country":"AU",
    "sg:address":"Shop 3, 11 The Mall",
    "sg:city":"Alice Springs",
    "sg:classifiers":[
        {
            "category":"Travel",
            "subcategory":"Travel Agent",
            "type":"Entertainment"
        }
    ],
    "sg:phone":"+61 8 8953 4081",
    "sg:postcode":"0871",
    "sg:province":"NT",
    "sg:tags":[
        "consultant"
    ],
    "wof:name":"Flight Centre",
    "wof:placetype":"venue"
},
  "geometry": {"coordinates":[133.88088989299999,-23.7003593445],"type":"Point"}
}