{
  "type": "Feature",
  "properties": {
    "addr:full":"Suite 4, 307 The Kingsway Caringbah NSW 2229",
    "addr:housenumber":"307",
    "addr:postcode":"2229",
    "addr:street":"The Kingsway",
    "iso:country":"AU",
    "sg:address":"Suite 4, 307 The Kingsway",
    "sg:city":"Caringbah",
    "sg:classifiers":[
        {
            "category":"Professional",
            "subcategory":"Employment Agencies",
            "type":"Services"
        }
    ],
    "sg:phone":"+61 2 9548 2651",
    "sg:postcode":"2229",
    "sg:province":"NSW",
    "wof:name":"Neildon Australia Pty Ltd",
    "wof:placetype":"venue"
},
  "geometry": {"coordinates":[151.12420654300001,-34.0129547119],"type":"Point"}
}