{
  "type": "Feature",
  "properties": {
    "iso:country":"AU",
    "sg:address":"22/ 20A Lawson Cres",
    "sg:city":"Coffs Harbour",
    "sg:classifiers":[
        {
            "category":"Utilities",
            "subcategory":"Water",
            "type":"Services"
        }
    ],
    "sg:phone":"+61 2 6652 7990",
    "sg:postcode":"2450",
    "sg:province":"NSW",
    "sg:tags":[
        "hot",
        "system"
    ],
    "wof:name":"Coffs Coast Plumbing",
    "wof:placetype":"venue"
},
  "geometry": {"coordinates":[153.127838,-30.290117],"type":"Point"}
}