{
  "type": "Feature",
  "properties": {
    "iso:country":"AU",
    "sg:address":"333 Railway Rd",
    "sg:city":"Shenton Park",
    "sg:classifiers":[
        {
            "category":"Wholesale",
            "subcategory":"Apparel",
            "type":"Manufacturing & Wholesale Goods"
        }
    ],
    "sg:phone":"+61 8 9381 3868",
    "sg:postcode":"6008",
    "sg:province":"WA",
    "sg:tags":[
        "wholesaler",
        "mfrs",
        "uniform"
    ],
    "wof:name":"Shuttle Apparel Australia Pty Ltd",
    "wof:placetype":"venue"
},
  "geometry": {"coordinates":[115.806907654,-31.9581871033],"type":"Point"}
}