{
  "type": "Feature",
  "properties": {
    "addr:full":"60 Riverside Pl Morningside QLD 4170",
    "addr:housenumber":"60",
    "addr:postcode":"4170",
    "addr:street":"Riverside Pl",
    "iso:country":"AU",
    "sg:address":"60 Riverside Pl",
    "sg:city":"Morningside",
    "sg:classifiers":[
        {
            "category":"Retail",
            "subcategory":"Auto Repair",
            "type":"Services"
        }
    ],
    "sg:phone":"+61 7 3399 5795",
    "sg:postcode":"4170",
    "sg:province":"QLD",
    "sg:tags":[
        "repairer",
        "motor",
        "engineer"
    ],
    "wof:name":"Colin Grace Automotive",
    "wof:placetype":"venue"
},
  "geometry": {"coordinates":[153.07887268100001,-27.4529628754],"type":"Point"}
}