{
  "type": "Feature",
  "properties": {
    "addr:full":"PO Box 14066 Melbourne City Mail Rm VIC 8001",
    "addr:postcode":"8001",
    "iso:country":"AU",
    "sg:address":"PO Box 14066",
    "sg:city":"Melbourne City Mail Rm",
    "sg:classifiers":[
        {
            "category":"Professional",
            "type":"Services"
        }
    ],
    "sg:phone":"+61 3 9376 0788",
    "sg:postcode":"8001",
    "sg:province":"VIC",
    "sg:tags":[
        "shop",
        "fitting"
    ],
    "wof:name":"D M Interiors Pty Ltd",
    "wof:placetype":"venue"
},
  "geometry": {"coordinates":[144.963165283,-37.814250946],"type":"Point"}
}