{
  "type": "Feature",
  "properties": {
    "addr:full":"147 Greville St Prahran VIC 3181",
    "addr:housenumber":"147",
    "addr:postcode":"3181",
    "addr:street":"Greville St",
    "iso:country":"AU",
    "sg:address":"147 Greville St",
    "sg:city":"Prahran",
    "sg:classifiers":[
        {
            "category":"Shopping",
            "subcategory":"Clothing, Apparel, & Fashions",
            "type":"Retail Goods"
        }
    ],
    "sg:phone":"+61 3 9521 3330",
    "sg:postcode":"3181",
    "sg:province":"VIC",
    "sg:tags":[
        "menswear"
    ],
    "wof:name":"MLDENIM",
    "wof:placetype":"venue"
},
  "geometry": {"coordinates":[144.99171447800001,-37.8491706848],"type":"Point"}
}