{
  "type": "Feature",
  "properties": {
    "addr:full":"591 Elizabeth St Redfern NSW 2016",
    "addr:housenumber":"591",
    "addr:postcode":"2016",
    "addr:street":"Elizabeth St",
    "iso:country":"AU",
    "sg:address":"591 Elizabeth St",
    "sg:city":"Redfern",
    "sg:classifiers":[
        {
            "category":"Autos & Motor Vehicles",
            "subcategory":"Auto Supplies",
            "type":"Retail Goods"
        }
    ],
    "sg:phone":"+61 2 9568 8801",
    "sg:postcode":"2016",
    "sg:province":"NSW",
    "sg:tags":[
        "car",
        "alarm"
    ],
    "wof:name":"Cobra Car Alarms",
    "wof:placetype":"venue"
},
  "geometry": {"coordinates":[151.207595825,-33.8908538818],"type":"Point"}
}