{
  "type": "Feature",
  "properties": {
    "addr:full":"446 Bunnerong Rd Matraville NSW 2036",
    "addr:housenumber":"446",
    "addr:postcode":"2036",
    "addr:street":"Bunnerong Rd",
    "iso:country":"AU",
    "sg:address":"446 Bunnerong Rd",
    "sg:city":"Matraville",
    "sg:classifiers":[
        {
            "category":"Home & Garden",
            "subcategory":"Carpets & Floor Coverings",
            "type":"Retail Goods"
        }
    ],
    "sg:phone":"+61 2 9311 1776",
    "sg:postcode":"2036",
    "sg:province":"NSW",
    "sg:tags":[
        "mattress"
    ],
    "wof:name":"Kingsford Furnishing Centre",
    "wof:placetype":"venue"
},
  "geometry": {"coordinates":[151.23130798299999,-33.9580726624],"type":"Point"}
}