{
  "type": "Feature",
  "properties": {
    "addr:full":"65 Commercial Rd Port Augusta SA 5700",
    "addr:housenumber":"65",
    "addr:postcode":"5700",
    "addr:street":"Commercial Rd",
    "iso:country":"AU",
    "sg:address":"65 Commercial Rd",
    "sg:city":"Port Augusta",
    "sg:classifiers":[
        {
            "category":"Building & Trades",
            "subcategory":"Equipment Rental",
            "type":"Services"
        }
    ],
    "sg:phone":"+61 8 8642 4358",
    "sg:postcode":"5700",
    "sg:province":"SA",
    "sg:tags":[
        "fitness"
    ],
    "wof:name":"Sportspower",
    "wof:placetype":"venue"
},
  "geometry": {"coordinates":[137.76268005399999,-32.4924507141],"type":"Point"}
}