{
  "type": "Feature",
  "properties": {
    "addr:full":"22 Tovey St Reservoir VIC 3073",
    "addr:housenumber":"22",
    "addr:postcode":"3073",
    "addr:street":"Tovey St",
    "iso:country":"AU",
    "sg:address":"22 Tovey St",
    "sg:city":"Reservoir",
    "sg:classifiers":[
        {
            "category":"Building & Trades",
            "subcategory":"Cleaning & Sanitation",
            "type":"Services"
        }
    ],
    "sg:phone":"+61 413 765 406",
    "sg:postcode":"3073",
    "sg:province":"VIC",
    "sg:tags":[
        "commercial",
        "maintenance"
    ],
    "wof:name":"DCM Coatings",
    "wof:placetype":"venue"
},
  "geometry": {"coordinates":[144.99925231899999,-37.7006568909],"type":"Point"}
}