{
  "type": "Feature",
  "properties": {
    "iso:country":"AU",
    "sg:address":"Mail Service 149",
    "sg:city":"Tenthill Upper",
    "sg:classifiers":[
        {
            "category":"Farming",
            "subcategory":"Farm",
            "type":"Manufacturing & Wholesale Goods"
        }
    ],
    "sg:phone":"+61 7 5462 7256",
    "sg:postcode":"4343",
    "sg:province":"QLD",
    "sg:tags":[
        "farmer"
    ],
    "wof:name":"Logan A A",
    "wof:placetype":"venue"
},
  "geometry": {"coordinates":[152.23402404800001,-27.5911502838],"type":"Point"}
}