{
  "type": "Feature",
  "properties": {
    "iso:country":"AU",
    "sg:address":"Cnr Forest Rd & Prince Hwy",
    "sg:city":"Arncliffe",
    "sg:classifiers":[
        {
            "category":"Food & Beverages",
            "subcategory":"Liquor & Beverages",
            "type":"Retail Goods"
        }
    ],
    "sg:phone":"+61 2 9567 2294",
    "sg:postcode":"2205",
    "sg:province":"NSW",
    "sg:tags":[
        "store"
    ],
    "wof:name":"Pubmart",
    "wof:placetype":"venue"
},
  "geometry": {"coordinates":[151.14686599999999,-33.939171],"type":"Point"}
}