{
  "type": "Feature",
  "properties": {
    "addr:full":"16 Blackwood Rd Woodridge QLD 4114",
    "addr:housenumber":"16",
    "addr:postcode":"4114",
    "addr:street":"Blackwood Rd",
    "iso:country":"AU",
    "sg:address":"16 Blackwood Rd",
    "sg:city":"Woodridge",
    "sg:classifiers":[
        {
            "category":"Freight",
            "type":"Transportation"
        }
    ],
    "sg:phone":"+61 13 17 70",
    "sg:postcode":"4114",
    "sg:province":"QLD",
    "sg:tags":[
        "light",
        "carrier"
    ],
    "wof:name":"Yellow Couriers",
    "wof:placetype":"venue"
},
  "geometry": {"coordinates":[153.106323242,-27.6380596161],"type":"Point"}
}