{
  "type": "Feature",
  "properties": {
    "iso:country":"AU",
    "sg:address":"5 Hicky Drv",
    "sg:city":"Moama",
    "sg:classifiers":[
        {
            "category":"Retail",
            "subcategory":"Auto Rental",
            "type":"Services"
        }
    ],
    "sg:phone":"+61 3 5480 2802",
    "sg:postcode":"2731",
    "sg:province":"NSW",
    "sg:tags":[
        "bus",
        "truck"
    ],
    "wof:name":"Echuca Rent-A-Car",
    "wof:placetype":"venue"
},
  "geometry": {"coordinates":[144.772202,-36.109035],"type":"Point"}
}