{
  "type": "Feature",
  "properties": {
    "iso:country":"AU",
    "sg:address":"5/ 151 Beauchamp Rd",
    "sg:city":"Matraville",
    "sg:classifiers":[
        {
            "category":"Retail",
            "subcategory":"Auto Rental",
            "type":"Services"
        }
    ],
    "sg:phone":"+61 2 9666 6622",
    "sg:postcode":"2036",
    "sg:province":"NSW",
    "sg:tags":[
        "car",
        "hire",
        "minibus"
    ],
    "wof:name":"Abus Rental",
    "wof:placetype":"venue"
},
  "geometry": {"coordinates":[151.226028442,-33.956489563],"type":"Point"}
}