{
  "type": "Feature",
  "properties": {
    "iso:country":"AU",
    "sg:address":"4 Walsh Ave",
    "sg:city":"Castle Hill",
    "sg:classifiers":[
        {
            "category":"Building & Trades",
            "subcategory":"Construction",
            "type":"Services"
        }
    ],
    "sg:phone":"+61 418 971 166",
    "sg:postcode":"2154",
    "sg:province":"NSW",
    "sg:tags":[
        "contractor"
    ],
    "wof:name":"XDC Consulting",
    "wof:placetype":"venue"
},
  "geometry": {"coordinates":[151.013275147,-33.7405509949],"type":"Point"}
}