{
  "type": "Feature",
  "properties": {
    "addr:full":"317 Gosport St Moree NSW 2400",
    "addr:housenumber":"317",
    "addr:postcode":"2400",
    "addr:street":"Gosport St",
    "iso:country":"AU",
    "sg:address":"317 Gosport St",
    "sg:city":"Moree",
    "sg:classifiers":[
        {
            "category":"Building & Trades",
            "subcategory":"Plumbing",
            "type":"Services"
        }
    ],
    "sg:phone":"+61 2 6752 4637",
    "sg:postcode":"2400",
    "sg:province":"NSW",
    "sg:tags":[
        "plumber",
        "gasfitters"
    ],
    "wof:name":"Leeder John P Pty Ltd",
    "wof:placetype":"venue"
},
  "geometry": {"coordinates":[149.84710693400001,-29.4722099304],"type":"Point"}
}