{
  "type": "Feature",
  "properties": {
    "iso:country":"AU",
    "sg:address":"Sutton St",
    "sg:city":"Ballarat",
    "sg:classifiers":[
        {
            "category":"Home & Garden",
            "subcategory":"Building Materials",
            "type":"Retail Goods"
        }
    ],
    "sg:phone":"+61 1800 666 437",
    "sg:postcode":"3350",
    "sg:province":"VIC",
    "sg:tags":[
        "roofing"
    ],
    "wof:name":"Monier Wunderlich",
    "wof:placetype":"venue"
},
  "geometry": {"coordinates":[143.827911,-37.577271],"type":"Point"}
}