{
  "type": "Feature",
  "properties": {
    "iso:country":"AU",
    "sg:address":"42 Adderley St East",
    "sg:city":"Lidcombe",
    "sg:classifiers":[
        {
            "category":"Government",
            "subcategory":"Fire Station",
            "type":"Public Place"
        }
    ],
    "sg:phone":"+61 2 9648 0133",
    "sg:postcode":"2141",
    "sg:province":"NSW",
    "sg:tags":[
        "equipment",
        "protection",
        "consultant"
    ],
    "wof:name":"Rassco Services Pty Ltd",
    "wof:placetype":"venue"
},
  "geometry": {"coordinates":[151.04507446299999,-33.8442077637],"type":"Point"}
}