{
  "type": "Feature",
  "properties": {
    "addr:full":"69 Queen St Warragul VIC 3820",
    "addr:housenumber":"69",
    "addr:postcode":"3820",
    "addr:street":"Queen St",
    "iso:country":"AU",
    "sg:address":"69 Queen St",
    "sg:city":"Warragul",
    "sg:classifiers":[
        {
            "category":"Real Estate",
            "subcategory":"Real Estate Agent",
            "type":"Services"
        }
    ],
    "sg:phone":"+61 3 5622 0822",
    "sg:postcode":"3820",
    "sg:province":"VIC",
    "wof:name":"Fairweather Realty",
    "wof:placetype":"venue"
},
  "geometry": {"coordinates":[145.938614,-38.143978],"type":"Point"}
}