{
  "type": "Feature",
  "properties": {
    "addr:full":"21 Whitley St Mt Gravatt East QLD 4122",
    "addr:housenumber":"21",
    "addr:postcode":"4122",
    "addr:street":"Whitley St",
    "iso:country":"AU",
    "sg:address":"21 Whitley St",
    "sg:city":"Mt Gravatt East",
    "sg:classifiers":[
        {
            "category":"Organizations",
            "subcategory":"Non-profit Organization",
            "type":"Services"
        }
    ],
    "sg:phone":"+61 7 3347 7200",
    "sg:postcode":"4122",
    "sg:province":"QLD",
    "sg:tags":[
        "support",
        "disability",
        "organisation"
    ],
    "wof:name":"Cerebral Palsy League of Queensland",
    "wof:placetype":"venue"
},
  "geometry": {"coordinates":[153.08306884800001,-27.5409946442],"type":"Point"}
}