{
  "type": "Feature",
  "properties": {
    "iso:country":"AU",
    "sg:address":"Level 3, 70 Pitt Street",
    "sg:city":"Sydney",
    "sg:classifiers":[
        {
            "category":"Organizations",
            "subcategory":"Professional Association",
            "type":"Services"
        }
    ],
    "sg:phone":"+61 2 8227 6405",
    "sg:postcode":"2000",
    "sg:province":"NSW",
    "sg:tags":[
        "call"
    ],
    "wof:name":"Intero Sales Integration",
    "wof:placetype":"venue"
},
  "geometry": {"coordinates":[151.208786011,-33.8659362793],"type":"Point"}
}