{
  "type": "Feature",
  "properties": {
    "addr:full":"23 MacCarthy Crs Armidale NSW 2350",
    "addr:housenumber":"23",
    "addr:postcode":"2350",
    "addr:street":"Maccarthy Crs",
    "iso:country":"AU",
    "sg:address":"23 MacCarthy Crs",
    "sg:city":"Armidale",
    "sg:classifiers":[
        {
            "category":"Wholesale",
            "subcategory":"Machinery & Supplies",
            "type":"Manufacturing & Wholesale Goods"
        }
    ],
    "sg:phone":"+61 2 6772 6770",
    "sg:postcode":"2350",
    "sg:province":"NSW",
    "sg:tags":[
        "instrument",
        "scientific"
    ],
    "wof:name":"ICT International Pty Ltd",
    "wof:placetype":"venue"
},
  "geometry": {"coordinates":[151.74203491200001,-30.6037902832],"type":"Point"}
}