{
  "type": "Feature",
  "properties": {
    "addr:full":"461 Alice St Maryborough QLD 4650",
    "addr:housenumber":"461",
    "addr:postcode":"4650",
    "addr:street":"Alice St",
    "iso:country":"AU",
    "sg:address":"461 Alice St",
    "sg:city":"Maryborough",
    "sg:classifiers":[
        {
            "category":"Shopping",
            "subcategory":"Shoes",
            "type":"Retail Goods"
        }
    ],
    "sg:phone":"+61 7 4123 1666",
    "sg:postcode":"4650",
    "sg:province":"QLD",
    "sg:tags":[
        "footwear"
    ],
    "wof:name":"Blundstone Trading",
    "wof:placetype":"venue"
},
  "geometry": {"coordinates":[152.68446399999999,-25.530258],"type":"Point"}
}