{
  "type": "Feature",
  "properties": {
    "addr:full":"Crn Beresford Ave & Landor St Beresfield NSW 2322",
    "addr:postcode":"2322",
    "addr:street":"Crn Beresford Ave & Landor St",
    "iso:country":"AU",
    "sg:address":"Crn Beresford Ave & Landor St",
    "sg:city":"Beresfield",
    "sg:classifiers":[
        {
            "category":"Professional",
            "subcategory":"Computer Services",
            "type":"Services"
        }
    ],
    "sg:phone":"+61 2 4966 1768",
    "sg:postcode":"2322",
    "sg:province":"NSW",
    "sg:tags":[
        "training"
    ],
    "wof:name":"Beresfield Computer Services",
    "wof:placetype":"venue"
},
  "geometry": {"coordinates":[151.64703369099999,-32.7995262146],"type":"Point"}
}