{
  "type": "Feature",
  "properties": {
    "iso:country":"AU",
    "sg:address":"U 4 6",
    "sg:city":"Edison Cct Rockingham",
    "sg:classifiers":[
        {
            "category":"Building & Trades",
            "subcategory":"Plumbing",
            "type":"Services"
        }
    ],
    "sg:phone":"+61 8 9591 2700",
    "sg:postcode":"6168",
    "sg:province":"WA",
    "sg:tags":[
        "plumber",
        "gasfitters"
    ],
    "wof:name":"Commercial Drainage Co Pty Ltd",
    "wof:placetype":"venue"
},
  "geometry": {"coordinates":[115.774834,-32.276024],"type":"Point"}
}