{
  "type": "Feature",
  "properties": {
    "addr:full":"14 Maggs St Wavell Heights QLD 4012",
    "addr:housenumber":"14",
    "addr:postcode":"4012",
    "addr:street":"Maggs St",
    "iso:country":"AU",
    "sg:address":"14 Maggs St",
    "sg:city":"Wavell Heights",
    "sg:classifiers":[
        {
            "category":"Utilities",
            "subcategory":"Electric",
            "type":"Services"
        }
    ],
    "sg:phone":"+61 7 3861 5777",
    "sg:postcode":"4012",
    "sg:province":"QLD",
    "sg:tags":[
        "electrical",
        "contractor"
    ],
    "wof:name":"Brad Turner Electrician",
    "wof:placetype":"venue"
},
  "geometry": {"coordinates":[153.03613281200001,-27.3961677551],"type":"Point"}
}