{
  "type": "Feature",
  "properties": {
    "iso:country":"AU",
    "sg:address":"Shop 23 & 24 Waurn Ponds Town & Country Shopping World, 173-199 Pioneer Rd",
    "sg:city":"Waurn Ponds",
    "sg:classifiers":[
        {
            "category":"Utilities",
            "subcategory":"Telephone",
            "type":"Services"
        }
    ],
    "sg:phone":"+61 3 5244 4222",
    "sg:postcode":"3216",
    "sg:province":"VIC",
    "sg:tags":[
        "equipment",
        "system"
    ],
    "wof:name":"Telstra Shop",
    "wof:placetype":"venue"
},
  "geometry": {"coordinates":[144.30209350600001,-38.2035293579],"type":"Point"}
}