{
  "type": "Feature",
  "properties": {
    "iso:country":"AU",
    "sg:address":"4 Cocker Pl",
    "sg:city":"Devonport East",
    "sg:classifiers":[
        {
            "category":"Wholesale",
            "subcategory":"Non-durable Goods",
            "type":"Manufacturing & Wholesale Goods"
        }
    ],
    "sg:phone":"+61 3 6423 2025",
    "sg:postcode":"7310",
    "sg:province":"TAS",
    "sg:tags":[
        "wholesaler",
        "mfrs",
        "cosmetic"
    ],
    "wof:name":"Sharlex",
    "wof:placetype":"venue"
},
  "geometry": {"coordinates":[146.344482422,-41.177482605],"type":"Point"}
}