{
  "type": "Feature",
  "properties": {
    "addr:full":"9 Harper St Abbotsford VIC 3067",
    "addr:housenumber":"9",
    "addr:postcode":"3067",
    "addr:street":"Harper St",
    "iso:country":"AU",
    "sg:address":"9 Harper St",
    "sg:city":"Abbotsford",
    "sg:classifiers":[
        {
            "category":"Wholesale",
            "subcategory":"Non-durable Goods",
            "type":"Manufacturing & Wholesale Goods"
        }
    ],
    "sg:phone":"+61 1300 307 214",
    "sg:postcode":"3067",
    "sg:province":"VIC",
    "sg:tags":[
        "textile"
    ],
    "wof:name":"Stern's Textiles",
    "wof:placetype":"venue"
},
  "geometry": {"coordinates":[144.99801635700001,-37.8040161133],"type":"Point"}
}