{
  "type": "Feature",
  "properties": {
    "addr:full":"138 Railway Pde Kogarah NSW 2217",
    "addr:housenumber":"138",
    "addr:postcode":"2217",
    "addr:street":"Railway Pde",
    "iso:country":"AU",
    "sg:address":"138 Railway Pde",
    "sg:city":"Kogarah",
    "sg:classifiers":[
        {
            "category":"Travel",
            "subcategory":"Travel Agent",
            "type":"Entertainment"
        }
    ],
    "sg:phone":"+61 2 9588 1666",
    "sg:postcode":"2217",
    "sg:province":"NSW",
    "sg:tags":[
        "consultant"
    ],
    "wof:name":"Kogarah Travel Service",
    "wof:placetype":"venue"
},
  "geometry": {"coordinates":[151.132294,-33.964676],"type":"Point"}
}