{
  "type": "Feature",
  "properties": {
    "addr:full":"Fcty 1/ 33 Sir Laurence Drv Seaford VIC 3198",
    "addr:housenumber":"/ 33",
    "addr:postcode":"3198",
    "addr:street":"Sir Laurence Drv",
    "iso:country":"AU",
    "sg:address":"Fcty 1/ 33 Sir Laurence Drv",
    "sg:city":"Seaford",
    "sg:classifiers":[
        {
            "category":"Professional",
            "subcategory":"Art Services",
            "type":"Services"
        }
    ],
    "sg:phone":"+61 3 9786 0157",
    "sg:postcode":"3198",
    "sg:province":"VIC",
    "sg:tags":[
        "picture",
        "frame",
        "framing"
    ],
    "wof:name":"GRS Marketing",
    "wof:placetype":"venue"
},
  "geometry": {"coordinates":[145.13653564399999,-38.1128234863],"type":"Point"}
}