{
  "type": "Feature",
  "properties": {
    "addr:full":"1441 Burwood Hwy Upwey VIC 3158",
    "addr:housenumber":"1441",
    "addr:postcode":"3158",
    "addr:street":"Burwood Hwy",
    "iso:country":"AU",
    "sg:address":"1441 Burwood Hwy",
    "sg:city":"Upwey",
    "sg:classifiers":[
        {
            "category":"Autos & Motor Vehicles",
            "subcategory":"Fuel & Gas Station",
            "type":"Retail Goods"
        }
    ],
    "sg:phone":"+61 3 9754 3073",
    "sg:postcode":"3158",
    "sg:province":"VIC",
    "wof:name":"Quix Food Stores",
    "wof:placetype":"venue"
},
  "geometry": {"coordinates":[145.33009338400001,-37.9019737244],"type":"Point"}
}