{
  "type": "Feature",
  "properties": {
    "addr:full":"531 Middleborough Rd Box Hill North VIC 3129",
    "addr:housenumber":"531",
    "addr:postcode":"3129",
    "addr:street":"Middleborough Rd",
    "iso:country":"AU",
    "sg:address":"531 Middleborough Rd",
    "sg:city":"Box Hill North",
    "sg:classifiers":[
        {
            "category":"Food & Beverages",
            "subcategory":"Fruits & Vegetables",
            "type":"Retail Goods"
        }
    ],
    "sg:phone":"+61 3 9890 9739",
    "sg:postcode":"3129",
    "sg:province":"VIC",
    "sg:tags":[
        "greengrocer",
        "fruiterer"
    ],
    "wof:name":"Marangos P",
    "wof:placetype":"venue"
},
  "geometry": {"coordinates":[145.14028930699999,-37.8084411621],"type":"Point"}
}