{
  "type": "Feature",
  "properties": {
    "addr:full":"PO Box 927 Sutherland NSW 1499",
    "addr:postcode":"1499",
    "iso:country":"AU",
    "sg:address":"PO Box 927",
    "sg:city":"Sutherland",
    "sg:classifiers":[
        {
            "category":"Food & Beverages",
            "subcategory":"Specialty",
            "type":"Retail Goods"
        }
    ],
    "sg:phone":"+61 2 9545 3611",
    "sg:postcode":"1499",
    "sg:province":"NSW",
    "sg:tags":[
        "product",
        "health"
    ],
    "wof:name":"Herb &#034;a&#034; Cell Nutrition",
    "wof:placetype":"venue"
},
  "geometry": {"coordinates":[151.057953,-34.031429],"type":"Point"}
}