{
  "type": "Feature",
  "properties": {
    "addr:full":"46 Winston Ave Clarence Gardens SA 5039",
    "addr:housenumber":"46",
    "addr:postcode":"5039",
    "addr:street":"Winston Ave",
    "iso:country":"AU",
    "sg:address":"46 Winston Ave",
    "sg:city":"Clarence Gardens",
    "sg:classifiers":[
        {
            "category":"Building & Trades",
            "subcategory":"Landscaping Services",
            "type":"Services"
        }
    ],
    "sg:phone":"+61 8 8351 3331",
    "sg:postcode":"5039",
    "sg:province":"SA",
    "sg:tags":[
        "designer",
        "landscape",
        "contractor"
    ],
    "wof:name":"Living Colour Garden Design & Art",
    "wof:placetype":"venue"
},
  "geometry": {"coordinates":[138.58224487300001,-34.9750213623],"type":"Point"}
}