{
  "type": "Feature",
  "properties": {
    "iso:country":"AU",
    "sg:address":"Level 28, 1 Spring St",
    "sg:city":"Melbourne",
    "sg:classifiers":[
        {
            "category":"Banks & Credit Unions",
            "subcategory":"Investment Brokerage",
            "type":"Services"
        }
    ],
    "sg:phone":"+61 1800 008 494",
    "sg:postcode":"3000",
    "sg:province":"VIC",
    "wof:name":"SAITeysmcmahon",
    "wof:placetype":"venue"
},
  "geometry": {"coordinates":[144.974685669,-37.8152275085],"type":"Point"}
}