{
  "type": "Feature",
  "properties": {
    "iso:country":"AU",
    "sg:address":"14 Tambo Upper Rd",
    "sg:city":"Bruthen",
    "sg:classifiers":[
        {
            "category":"Travel",
            "subcategory":"Hotels & Motels",
            "type":"Entertainment"
        }
    ],
    "sg:phone":"+61 3 5157 5201",
    "sg:postcode":"3885",
    "sg:province":"VIC",
    "sg:tags":[
        "accommodation"
    ],
    "wof:name":"Bruthen Inn Hotel",
    "wof:placetype":"venue"
},
  "geometry": {"coordinates":[147.848266602,-37.7301025391],"type":"Point"}
}