{
  "type": "Feature",
  "properties": {
    "iso:country":"AU",
    "sg:address":"420 Sydney Rd",
    "sg:city":"Coburg",
    "sg:classifiers":[
        {
            "category":"Organizations",
            "subcategory":"Professional Association",
            "type":"Services"
        }
    ],
    "sg:phone":"+61 3 9350 5737",
    "sg:postcode":"3058",
    "sg:province":"VIC",
    "sg:tags":[
        "organisation",
        "business"
    ],
    "wof:name":"The Coburg Traders Association",
    "wof:placetype":"venue"
},
  "geometry": {"coordinates":[144.96635437,-37.7435340881],"type":"Point"}
}