{
  "type": "Feature",
  "properties": {
    "iso:country":"AU",
    "sg:address":"58 Neurum Rd",
    "sg:city":"Yaroomba",
    "sg:classifiers":[
        {
            "category":"Building & Trades",
            "subcategory":"Landscaping Services",
            "type":"Services"
        }
    ],
    "sg:phone":"+61 417 633 776",
    "sg:postcode":"4573",
    "sg:province":"QLD",
    "sg:tags":[
        "designer",
        "landscape",
        "contractor"
    ],
    "wof:name":"Anthony Waring",
    "wof:placetype":"venue"
},
  "geometry": {"coordinates":[153.095993,-26.547398],"type":"Point"}
}