{
  "type": "Feature",
  "properties": {
    "addr:full":"Shed 1 / 50 Elliott St Lismore NSW 2480",
    "addr:housenumber":"1 / 50",
    "addr:postcode":"2480",
    "addr:street":"Elliott St",
    "iso:country":"AU",
    "sg:address":"Shed 1 / 50 Elliott St",
    "sg:city":"Lismore",
    "sg:classifiers":[
        {
            "category":"Retail",
            "subcategory":"Auto Repair",
            "type":"Services"
        }
    ],
    "sg:phone":"+61 2 6622 1220",
    "sg:postcode":"2480",
    "sg:province":"NSW",
    "sg:tags":[
        "electrical"
    ],
    "wof:name":"B.O.W. Auto Electrical",
    "wof:placetype":"venue"
},
  "geometry": {"coordinates":[153.264938355,-28.8123931885],"type":"Point"}
}