{
  "type": "Feature",
  "properties": {
    "iso:country":"AU",
    "sg:address":"128 Blue Bell Drv",
    "sg:city":"Wamberal",
    "sg:classifiers":[
        {
            "category":"Utilities",
            "subcategory":"Water",
            "type":"Services"
        }
    ],
    "sg:phone":"+61 409 741 693",
    "sg:postcode":"2260",
    "sg:province":"NSW",
    "sg:tags":[
        "hot",
        "system"
    ],
    "wof:name":"Greg Clayton",
    "wof:placetype":"venue"
},
  "geometry": {"coordinates":[151.448074,-33.421417],"type":"Point"}
}