{
  "type": "Feature",
  "properties": {
    "iso:country":"AU",
    "sg:address":"Pier 1 International Marina, Coffs Harbour Jetty",
    "sg:city":"Coffs Harbour",
    "sg:classifiers":[
        {
            "category":"Recreation",
            "subcategory":"Boat Charter",
            "type":"Entertainment"
        }
    ],
    "sg:phone":"+61 2 6650 0155",
    "sg:postcode":"2450",
    "sg:province":"NSW",
    "wof:name":"Spirit of Coffs Harbour Cruises",
    "wof:placetype":"venue"
},
  "geometry": {"coordinates":[153.138565,-30.303198],"type":"Point"}
}