{
  "type": "Feature",
  "properties": {
    "iso:country":"AU",
    "sg:address":"Cnr Oaklands & Morphett Rds",
    "sg:city":"Warradale",
    "sg:classifiers":[
        {
            "category":"Organizations",
            "subcategory":"Community Association",
            "type":"Services"
        }
    ],
    "sg:phone":"+61 8 8295 7984",
    "sg:postcode":"5046",
    "sg:province":"SA",
    "sg:tags":[
        "organisation",
        "family",
        "welfare"
    ],
    "wof:name":"Meals On Wheels (S.A.) Incorporated",
    "wof:placetype":"venue"
},
  "geometry": {"coordinates":[138.534836,-34.996456],"type":"Point"}
}