{
  "type": "Feature",
  "properties": {
    "iso:country":"AU",
    "sg:address":"16 Pin Oak Crs",
    "sg:city":"Newmarket",
    "sg:classifiers":[
        {
            "category":"Personal",
            "subcategory":"Beauty Salon",
            "type":"Services"
        }
    ],
    "sg:phone":"+61 3 9376 0333",
    "sg:postcode":"3031",
    "sg:province":"VIC",
    "sg:tags":[
        "hairdresser"
    ],
    "wof:name":"Beverley Hills Hair Centre",
    "wof:placetype":"venue"
},
  "geometry": {"coordinates":[144.926743,-37.787155],"type":"Point"}
}