{
  "type": "Feature",
  "properties": {
    "iso:country":"AU",
    "sg:address":"32 Taylor St",
    "sg:city":"Moonee Ponds",
    "sg:classifiers":[
        {
            "category":"Professional",
            "subcategory":"Accounting & Tax Preparation",
            "type":"Services"
        }
    ],
    "sg:phone":"+61 3 9326 1244",
    "sg:postcode":"3039",
    "sg:province":"VIC",
    "sg:tags":[
        "accountant",
        "auditor"
    ],
    "wof:name":"Tolevsky Partners",
    "wof:placetype":"venue"
},
  "geometry": {"coordinates":[144.92056299999999,-37.763802],"type":"Point"}
}