{
  "type": "Feature",
  "properties": {
    "addr:full":"32 Casuarina Crs Jurien Bay WA 6516",
    "addr:housenumber":"32",
    "addr:postcode":"6516",
    "addr:street":"Casuarina Crs",
    "iso:country":"AU",
    "sg:address":"32 Casuarina Crs",
    "sg:city":"Jurien Bay",
    "sg:classifiers":[
        {
            "category":"Farming",
            "subcategory":"Fish & Marine Products",
            "type":"Manufacturing & Wholesale Goods"
        }
    ],
    "sg:phone":"+61 8 9652 1173",
    "sg:postcode":"6516",
    "sg:province":"WA",
    "sg:tags":[
        "fisherman"
    ],
    "wof:name":"Simmonds B & J",
    "wof:placetype":"venue"
},
  "geometry": {"coordinates":[115.043266,-30.302891],"type":"Point"}
}