{
  "type": "Feature",
  "properties": {
    "addr:full":"292 Rokeby Rd Subiaco WA 6008",
    "addr:housenumber":"292",
    "addr:postcode":"6008",
    "addr:street":"Rokeby Rd",
    "iso:country":"AU",
    "sg:address":"292 Rokeby Rd",
    "sg:city":"Subiaco",
    "sg:classifiers":[
        {
            "category":"Professional",
            "subcategory":"Accounting & Tax Preparation",
            "type":"Services"
        }
    ],
    "sg:phone":"+61 8 9388 2735",
    "sg:postcode":"6008",
    "sg:province":"WA",
    "sg:tags":[
        "accountant",
        "auditor"
    ],
    "wof:name":"Marpik Accountants Pty Ltd",
    "wof:placetype":"venue"
},
  "geometry": {"coordinates":[115.82408905,-31.9534511566],"type":"Point"}
}