{
  "type": "Feature",
  "properties": {
    "iso:country":"AU",
    "sg:address":"57 Hastings River Drv",
    "sg:city":"Port Macquarie",
    "sg:classifiers":[
        {
            "category":"Shopping",
            "subcategory":"Bicycles & Sporting Goods",
            "type":"Retail Goods"
        }
    ],
    "sg:phone":"+61 2 6583 6335",
    "sg:postcode":"2444",
    "sg:province":"NSW",
    "sg:tags":[
        "chemical",
        "equipment",
        "pool",
        "swimming"
    ],
    "wof:name":"AAA Cascade Pool & Spa Centre",
    "wof:placetype":"venue"
},
  "geometry": {"coordinates":[152.891647,-31.432198],"type":"Point"}
}