{
  "type": "Feature",
  "properties": {
    "addr:full":"171 Curtin Ave Cottesloe WA 6011",
    "addr:housenumber":"171",
    "addr:postcode":"6011",
    "addr:street":"Curtin Ave",
    "iso:country":"AU",
    "sg:address":"171 Curtin Ave",
    "sg:city":"Cottesloe",
    "sg:classifiers":[
        {
            "category":"Arena",
            "subcategory":"Sports Club",
            "type":"Entertainment"
        }
    ],
    "sg:phone":"+61 8 9384 2397",
    "sg:postcode":"6011",
    "sg:province":"WA",
    "sg:tags":[
        "australian",
        "football",
        "rule"
    ],
    "wof:name":"St Kilda Football Club - Western Saints",
    "wof:placetype":"venue"
},
  "geometry": {"coordinates":[115.75965118400001,-31.998872757],"type":"Point"}
}