{
  "type": "Feature",
  "properties": {
    "addr:full":"10 Davey Duke Drv Wendouree VIC 3355",
    "addr:housenumber":"10",
    "addr:postcode":"3355",
    "addr:street":"Davey Duke Drv",
    "iso:country":"AU",
    "sg:address":"10 Davey Duke Drv",
    "sg:city":"Wendouree",
    "sg:classifiers":[
        {
            "category":"Transit Center",
            "subcategory":"Freight",
            "type":"Transportation"
        }
    ],
    "sg:phone":"+61 3 5339 3002",
    "sg:postcode":"3355",
    "sg:province":"VIC",
    "sg:tags":[
        "forklift",
        "truck"
    ],
    "wof:name":"Allforks",
    "wof:placetype":"venue"
},
  "geometry": {"coordinates":[143.80587800000001,-37.512039],"type":"Point"}
}