{
  "type": "Feature",
  "properties": {
    "addr:full":"62 Meier St Camira QLD 4300",
    "addr:housenumber":"62",
    "addr:postcode":"4300",
    "addr:street":"Meier St",
    "iso:country":"AU",
    "sg:address":"62 Meier St",
    "sg:city":"Camira",
    "sg:classifiers":[
        {
            "category":"Professional",
            "type":"Services"
        }
    ],
    "sg:phone":"+61 7 3818 0880",
    "sg:postcode":"4300",
    "sg:province":"QLD",
    "sg:tags":[
        "courier"
    ],
    "wof:name":"RKC Installations (Qld) Pty Ltd",
    "wof:placetype":"venue"
},
  "geometry": {"coordinates":[152.915405273,-27.6391143799],"type":"Point"}
}