{
  "type": "Feature",
  "properties": {
    "addr:full":"104 Faunce St West Gosford NSW 2250",
    "addr:housenumber":"104",
    "addr:postcode":"2250",
    "addr:street":"Faunce St West",
    "iso:country":"AU",
    "sg:address":"104 Faunce St West",
    "sg:city":"Gosford",
    "sg:classifiers":[
        {
            "category":"Health Services",
            "subcategory":"Health Practitioner",
            "type":"Services"
        }
    ],
    "sg:phone":"+61 2 4324 4779",
    "sg:postcode":"2250",
    "sg:province":"NSW",
    "sg:tags":[
        "psychologist"
    ],
    "wof:name":"Tiffen Kathryn",
    "wof:placetype":"venue"
},
  "geometry": {"coordinates":[151.34274292000001,-33.423122406],"type":"Point"}
}