{
  "type": "Feature",
  "properties": {
    "addr:full":"PO Box 407 Hampton Park VIC 3976",
    "addr:postcode":"3976",
    "iso:country":"AU",
    "sg:address":"PO Box 407",
    "sg:city":"Hampton Park",
    "sg:classifiers":[
        {
            "category":"Home & Garden",
            "subcategory":"Kitchen Supply",
            "type":"Retail Goods"
        }
    ],
    "sg:phone":"+61 3 9705 2350",
    "sg:postcode":"3976",
    "sg:province":"VIC",
    "sg:tags":[
        "traffic",
        "equipment",
        "safety",
        "road"
    ],
    "wof:name":"Able Traffic Management Pty Ltd",
    "wof:placetype":"venue"
},
  "geometry": {"coordinates":[145.26762390100001,-38.0422897339],"type":"Point"}
}