{
  "type": "Feature",
  "properties": {
    "iso:country":"AU",
    "sg:address":"16 Edith St",
    "sg:city":"North Haven",
    "sg:classifiers":[
        {
            "category":"Building & Trades",
            "subcategory":"Construction",
            "type":"Services"
        }
    ],
    "sg:phone":"+61 418 869 763",
    "sg:postcode":"2443",
    "sg:province":"NSW",
    "sg:tags":[
        "waterproofing",
        "contractor"
    ],
    "wof:name":"Wayne Ross Waterproof & Shower Repair Specialists",
    "wof:placetype":"venue"
},
  "geometry": {"coordinates":[152.826187,-31.634682],"type":"Point"}
}