{
  "type": "Feature",
  "properties": {
    "addr:full":"17 Machinery Drv Tweed Heads South NSW 2486",
    "addr:postcode":"2486",
    "addr:street":"Machinery Drv",
    "iso:country":"AU",
    "sg:address":"17 Machinery Drv",
    "sg:city":"Tweed Heads South",
    "sg:classifiers":[
        {
            "category":"Home & Garden",
            "subcategory":"Garden Supply",
            "type":"Retail Goods"
        }
    ],
    "sg:phone":"+61 7 5524 5444",
    "sg:postcode":"2486",
    "sg:province":"NSW",
    "sg:tags":[
        "nursery"
    ],
    "wof:name":"Agricultural Plastics",
    "wof:placetype":"venue"
},
  "geometry": {"coordinates":[153.539962769,-28.2034664154],"type":"Point"}
}