{
  "type": "Feature",
  "properties": {
    "addr:full":"30 Glen Ave Randwick NSW 2031",
    "addr:housenumber":"30",
    "addr:postcode":"2031",
    "addr:street":"Glen Ave",
    "iso:country":"AU",
    "sg:address":"30 Glen Ave",
    "sg:city":"Randwick",
    "sg:classifiers":[
        {
            "category":"Health Services",
            "subcategory":"Doctor",
            "type":"Services"
        }
    ],
    "sg:phone":"+61 2 9398 5406",
    "sg:postcode":"2031",
    "sg:province":"NSW",
    "sg:tags":[
        "medical",
        "practitioner"
    ],
    "wof:name":"Polon Melvyn",
    "wof:placetype":"venue"
},
  "geometry": {"coordinates":[151.24839782699999,-33.9126968384],"type":"Point"}
}