{
  "type": "Feature",
  "properties": {
    "iso:country":"AU",
    "sg:address":"9 Freeman St",
    "sg:city":"Yeppoon",
    "sg:classifiers":[
        {
            "category":"Utilities",
            "subcategory":"Electric",
            "type":"Services"
        }
    ],
    "sg:phone":"+61 7 4939 1042",
    "sg:postcode":"4703",
    "sg:province":"QLD",
    "sg:tags":[
        "electrical",
        "contractor"
    ],
    "wof:name":"Koro's Electrical",
    "wof:placetype":"venue"
},
  "geometry": {"coordinates":[150.74710082999999,-23.12550354],"type":"Point"}
}