{
  "type": "Feature",
  "properties": {
    "iso:country":"AU",
    "sg:address":"21- 35 Wallace St",
    "sg:city":"Swansea",
    "sg:classifiers":[
        {
            "category":"Travel",
            "subcategory":"Hostel",
            "type":"Entertainment"
        }
    ],
    "sg:phone":"+61 2 4971 3611",
    "sg:postcode":"2281",
    "sg:province":"NSW",
    "sg:tags":[
        "home"
    ],
    "wof:name":"The Village Swansea",
    "wof:placetype":"venue"
},
  "geometry": {"coordinates":[151.63409423799999,-33.0925941467],"type":"Point"}
}