{
  "type": "Feature",
  "properties": {
    "iso:country":"AU",
    "sg:address":"New England Hwy",
    "sg:city":"Guyra",
    "sg:classifiers":[
        {
            "category":"Manufacturing",
            "subcategory":"Petroleum Products",
            "type":"Manufacturing & Wholesale Goods"
        }
    ],
    "sg:phone":"+61 2 6779 1599",
    "sg:postcode":"2365",
    "sg:province":"NSW",
    "sg:tags":[
        "lubricant"
    ],
    "wof:name":"Castrol Australia Pty Ltd",
    "wof:placetype":"venue"
},
  "geometry": {"coordinates":[151.673095703,-30.2176151276],"type":"Point"}
}