{
  "type": "Feature",
  "properties": {
    "iso:country":"AU",
    "sg:address":"1 Tradewinds Crt",
    "sg:city":"Toowoomba",
    "sg:classifiers":[
        {
            "category":"Retail",
            "subcategory":"Auto Repair",
            "type":"Services"
        }
    ],
    "sg:phone":"+61 7 4634 2733",
    "sg:postcode":"4350",
    "sg:province":"QLD",
    "sg:tags":[
        "beater",
        "painter",
        "panel"
    ],
    "wof:name":"Toowoomba Rod And Custom Shop",
    "wof:placetype":"venue"
},
  "geometry": {"coordinates":[151.90838600000001,-27.555183],"type":"Point"}
}