{
  "type": "Feature",
  "properties": {
    "addr:full":"15 Railway St Toowoomba QLD 4350",
    "addr:housenumber":"15",
    "addr:postcode":"4350",
    "addr:street":"Railway St",
    "iso:country":"AU",
    "sg:address":"15 Railway St",
    "sg:city":"Toowoomba",
    "sg:classifiers":[
        {
            "category":"Education",
            "subcategory":"Dance Studio",
            "type":"Public Place"
        }
    ],
    "sg:phone":"+61 7 4637 2660",
    "sg:postcode":"4350",
    "sg:province":"QLD",
    "sg:tags":[
        "venue",
        "tuition"
    ],
    "wof:name":"Dance Connection",
    "wof:placetype":"venue"
},
  "geometry": {"coordinates":[151.950974,-27.55789],"type":"Point"}
}