{
  "type": "Feature",
  "properties": {
    "iso:country":"AU",
    "sg:address":"101 Lockyer Ave",
    "sg:city":"Albany",
    "sg:classifiers":[
        {
            "category":"Banks & Credit Unions",
            "subcategory":"Bureau De Change",
            "type":"Services"
        }
    ],
    "sg:phone":"+61 8 9841 6024",
    "sg:postcode":"6330",
    "sg:province":"WA",
    "sg:tags":[
        "supply",
        "equipment",
        "beating",
        "panel"
    ],
    "wof:name":"Paint &#034;N&#034; Quip",
    "wof:placetype":"venue"
},
  "geometry": {"coordinates":[117.88439178500001,-35.0165214539],"type":"Point"}
}