{
  "type": "Feature",
  "properties": {
    "addr:full":"67 Herbert St Goondiwindi QLD 4390",
    "addr:housenumber":"67",
    "addr:postcode":"4390",
    "addr:street":"Herbert St",
    "iso:country":"AU",
    "sg:address":"67 Herbert St",
    "sg:city":"Goondiwindi",
    "sg:classifiers":[
        {
            "category":"Retail",
            "subcategory":"Auto Repair",
            "type":"Services"
        }
    ],
    "sg:phone":"+61 7 4671 1674",
    "sg:postcode":"4390",
    "sg:province":"QLD",
    "sg:tags":[
        "repairer",
        "motor",
        "engineer"
    ],
    "wof:name":"McCosker's Mechanical Centre",
    "wof:placetype":"venue"
},
  "geometry": {"coordinates":[150.30648803700001,-28.539434433],"type":"Point"}
}