{
  "type": "Feature",
  "properties": {
    "iso:country":"AU",
    "sg:address":"57 Palmer St",
    "sg:city":"South Townsville",
    "sg:classifiers":[
        {
            "category":"Personal",
            "subcategory":"Beauty Salon",
            "type":"Services"
        }
    ],
    "sg:phone":"+61 404 146 178",
    "sg:postcode":"4810",
    "sg:province":"QLD",
    "sg:tags":[
        "supply",
        "artist",
        "make-up"
    ],
    "wof:name":"Jade Gleeson",
    "wof:placetype":"venue"
},
  "geometry": {"coordinates":[146.823822,-19.259529],"type":"Point"}
}