{
  "type": "Feature",
  "properties": {
    "iso:country":"AU",
    "sg:address":"21 Alexander Ave",
    "sg:city":"Bateau Bay",
    "sg:classifiers":[
        {
            "category":"Building & Trades",
            "subcategory":"Construction",
            "type":"Services"
        }
    ],
    "sg:phone":"+61 2 4332 0852",
    "sg:postcode":"2261",
    "sg:province":"NSW",
    "sg:tags":[
        "contractor"
    ],
    "wof:name":"Truewood Constructions",
    "wof:placetype":"venue"
},
  "geometry": {"coordinates":[151.461288,-33.389805],"type":"Point"}
}