{
  "type": "Feature",
  "properties": {
    "addr:full":"1368 Mount Mee Rd Mt Mee QLD 4521",
    "addr:housenumber":"1368",
    "addr:postcode":"4521",
    "addr:street":"Mount Mee Rd Mt Mee",
    "iso:country":"AU",
    "sg:address":"1368 Mount Mee Rd",
    "sg:city":"Mt Mee",
    "sg:classifiers":[
        {
            "category":"Education",
            "subcategory":"School",
            "type":"Public Place"
        }
    ],
    "sg:phone":"+61 7 5498 2228",
    "sg:postcode":"4521",
    "sg:province":"QLD",
    "sg:tags":[
        "state",
        "except",
        "nsw"
    ],
    "wof:name":"Mt Mee Primary School",
    "wof:placetype":"venue"
},
  "geometry": {"coordinates":[152.764465,-27.081207],"type":"Point"}
}