{
  "type": "Feature",
  "properties": {
    "iso:country":"AU",
    "sg:address":"178- 184 Boundary Rd",
    "sg:city":"Braeside",
    "sg:classifiers":[
        {
            "category":"Professional",
            "subcategory":"Accounting & Tax Preparation",
            "type":"Services"
        }
    ],
    "sg:phone":"+61 3 9586 6466",
    "sg:postcode":"3195",
    "sg:province":"VIC",
    "sg:tags":[
        "jukebox"
    ],
    "wof:name":"Pioneer Electronics",
    "wof:placetype":"venue"
},
  "geometry": {"coordinates":[145.10581970199999,-37.9994354248],"type":"Point"}
}