{
  "type": "Feature",
  "properties": {
    "iso:country":"AU",
    "sg:address":"361 Hume Hwy",
    "sg:city":"Bankstown",
    "sg:classifiers":[
        {
            "category":"Professional",
            "subcategory":"Detective & Security Services",
            "type":"Services"
        }
    ],
    "sg:phone":"+61 2 9790 1544",
    "sg:postcode":"2200",
    "sg:province":"NSW",
    "sg:tags":[
        "consultant",
        "system"
    ],
    "wof:name":"Easy Living Systems",
    "wof:placetype":"venue"
},
  "geometry": {"coordinates":[151.03362999999999,-33.90741],"type":"Point"}
}