{
  "type": "Feature",
  "properties": {
    "iso:country":"AU",
    "sg:address":"59 Military Rd",
    "sg:city":"Dover Heights",
    "sg:classifiers":[
        {
            "category":"Manufacturing",
            "subcategory":"Textiles",
            "type":"Manufacturing & Wholesale Goods"
        }
    ],
    "sg:phone":"+61 2 9371 5425",
    "sg:postcode":"2030",
    "sg:province":"NSW",
    "sg:tags":[
        "wholesaler",
        "knitwear",
        "mfrs"
    ],
    "wof:name":"Esterhazy Francoise Design",
    "wof:placetype":"venue"
},
  "geometry": {"coordinates":[151.28027343799999,-33.8793144226],"type":"Point"}
}