{
  "type": "Feature",
  "properties": {
    "addr:full":"4 Devon St Box Hill VIC 3128",
    "addr:housenumber":"4",
    "addr:postcode":"3128",
    "addr:street":"Devon St",
    "iso:country":"AU",
    "sg:address":"4 Devon St",
    "sg:city":"Box Hill",
    "sg:classifiers":[
        {
            "category":"Professional",
            "subcategory":"Accounting & Tax Preparation",
            "type":"Services"
        }
    ],
    "sg:phone":"+61 412 459 411",
    "sg:postcode":"3128",
    "sg:province":"VIC",
    "sg:tags":[
        "accountant",
        "auditor"
    ],
    "wof:name":"George & Partners",
    "wof:placetype":"venue"
},
  "geometry": {"coordinates":[145.121337891,-37.8340339661],"type":"Point"}
}