{
  "type": "Feature",
  "properties": {
    "addr:full":"U10/ 6 Vanessa Blv Springwood QLD 4127",
    "addr:housenumber":"6",
    "addr:postcode":"4127",
    "addr:street":"/;Vanessa Blv",
    "iso:country":"AU",
    "sg:address":"U10/ 6",
    "sg:city":"Vanessa Blv Springwood",
    "sg:classifiers":[
        {
            "category":"Real Estate",
            "subcategory":"Developer",
            "type":"Services"
        }
    ],
    "sg:phone":"+61 7 3808 6477",
    "sg:postcode":"4127",
    "sg:province":"QLD",
    "sg:tags":[
        "development"
    ],
    "wof:name":"Indacom Commercial Pty Ltd",
    "wof:placetype":"venue"
},
  "geometry": {"coordinates":[153.12538147000001,-27.6159439087],"type":"Point"}
}