{
  "type": "Feature",
  "properties": {
    "addr:full":"2/10- 12 Hamilton St Allawah NSW 2218",
    "addr:housenumber":"/;12",
    "addr:postcode":"2218",
    "addr:street":"10;Hamilton St",
    "iso:country":"AU",
    "sg:address":"2/10- 12 Hamilton St",
    "sg:city":"Allawah",
    "sg:classifiers":[
        {
            "category":"Shopping",
            "subcategory":"Computers & Home Electronics",
            "type":"Retail Goods"
        }
    ],
    "sg:phone":"+61 2 9587 1380",
    "sg:postcode":"2218",
    "sg:province":"NSW",
    "sg:tags":[
        "equipment",
        "supply"
    ],
    "wof:name":"Tycon Technology",
    "wof:placetype":"venue"
},
  "geometry": {"coordinates":[151.118942,-33.970654],"type":"Point"}
}