{
  "type": "Feature",
  "properties": {
    "addr:full":"Middle Rd Dunolly VIC 3472",
    "addr:postcode":"3472",
    "addr:street":"Middle Rd",
    "iso:country":"AU",
    "sg:address":"Middle Rd",
    "sg:city":"Dunolly",
    "sg:classifiers":[
        {
            "category":"Taxi",
            "type":"Transportation"
        }
    ],
    "sg:phone":"+61 3 5468 1999",
    "sg:postcode":"3472",
    "sg:province":"VIC",
    "sg:tags":[
        "cab"
    ],
    "wof:name":"Dunolly Taxi Service",
    "wof:placetype":"venue"
},
  "geometry": {"coordinates":[143.753219605,-36.8750419617],"type":"Point"}
}