{
  "type": "Feature",
  "properties": {
    "addr:full":"32 Boulder Rd Kalgoorlie WA 6430",
    "addr:housenumber":"32",
    "addr:postcode":"6430",
    "addr:street":"Boulder Rd",
    "iso:country":"AU",
    "sg:address":"32 Boulder Rd",
    "sg:city":"Kalgoorlie",
    "sg:classifiers":[
        {
            "category":"Communications",
            "subcategory":"Film & Video Production",
            "type":"Services"
        }
    ],
    "sg:phone":"+61 8 9021 6369",
    "sg:postcode":"6430",
    "sg:province":"WA",
    "sg:tags":[
        "dvd",
        "library"
    ],
    "wof:name":"Civic Video",
    "wof:placetype":"venue"
},
  "geometry": {"coordinates":[121.476173401,-30.7479476929],"type":"Point"}
}