{
  "type": "Feature",
  "properties": {
    "iso:country":"AU",
    "sg:address":"26 Tortice Drv",
    "sg:city":"Ringwood North",
    "sg:classifiers":[
        {
            "category":"Food & Beverages",
            "subcategory":"Groceries & Convenience Stores",
            "type":"Retail Goods"
        }
    ],
    "sg:phone":"+61 3 9879 0317",
    "sg:postcode":"3134",
    "sg:province":"VIC",
    "wof:name":"Parkwood Convenience Store",
    "wof:placetype":"venue"
},
  "geometry": {"coordinates":[145.239868164,-37.7861328125],"type":"Point"}
}