{
  "type": "Feature",
  "properties": {
    "addr:full":"604 Bruce Hwy Cairns QLD 4870",
    "addr:housenumber":"604",
    "addr:postcode":"4870",
    "addr:street":"Bruce Hwy",
    "iso:country":"AU",
    "sg:address":"604 Bruce Hwy",
    "sg:city":"Cairns",
    "sg:classifiers":[
        {
            "category":"Retail",
            "subcategory":"Funeral Services",
            "type":"Services"
        }
    ],
    "sg:phone":"+61 7 4054 5400",
    "sg:postcode":"4870",
    "sg:province":"QLD",
    "sg:tags":[
        "director"
    ],
    "wof:name":"Burkin Funerals",
    "wof:placetype":"venue"
},
  "geometry": {"coordinates":[145.74342346200001,-17.0010871887],"type":"Point"}
}