{
  "type": "Feature",
  "properties": {
    "addr:full":"280 Henry Lawson Drv Mudgee NSW 2850",
    "addr:housenumber":"280",
    "addr:postcode":"2850",
    "addr:street":"Henry Lawson Drv",
    "iso:country":"AU",
    "sg:address":"280 Henry Lawson Drv",
    "sg:city":"Mudgee",
    "sg:classifiers":[
        {
            "category":"Farming",
            "subcategory":"Vineyard",
            "type":"Manufacturing & Wholesale Goods"
        }
    ],
    "sg:phone":"+61 2 6372 2258",
    "sg:postcode":"2850",
    "sg:province":"NSW",
    "sg:tags":[
        "winery"
    ],
    "wof:name":"Mudgee Wines Pty Ltd",
    "wof:placetype":"venue"
},
  "geometry": {"coordinates":[149.60870399999999,-32.552219],"type":"Point"}
}