{
  "type": "Feature",
  "properties": {
    "addr:full":"126 Junction St Nowra NSW 2541",
    "addr:housenumber":"126",
    "addr:postcode":"2541",
    "addr:street":"Junction St",
    "iso:country":"AU",
    "sg:address":"126 Junction St",
    "sg:city":"Nowra",
    "sg:classifiers":[
        {
            "category":"Shopping",
            "subcategory":"Clothing, Apparel, & Fashions",
            "type":"Retail Goods"
        }
    ],
    "sg:phone":"+61 2 4421 0967",
    "sg:postcode":"2541",
    "sg:province":"NSW",
    "sg:tags":[
        "lady",
        "wear"
    ],
    "wof:name":"Snellings Pty Ltd",
    "wof:placetype":"venue"
},
  "geometry": {"coordinates":[150.60253906200001,-34.874671936],"type":"Point"}
}