{
  "type": "Feature",
  "properties": {
    "addr:full":"16 Asquith Crt Greenwood WA 6024",
    "addr:housenumber":"16",
    "addr:postcode":"6024",
    "addr:street":"Asquith Crt",
    "iso:country":"AU",
    "sg:address":"16 Asquith Crt",
    "sg:city":"Greenwood",
    "sg:classifiers":[
        {
            "category":"Professional",
            "subcategory":"Computer Services",
            "type":"Services"
        }
    ],
    "sg:phone":"+61 8 9448 7820",
    "sg:postcode":"6024",
    "sg:province":"WA",
    "sg:tags":[
        "repairs",
        "upgrade",
        "equipment"
    ],
    "wof:name":"Microtechnics",
    "wof:placetype":"venue"
},
  "geometry": {"coordinates":[115.787742615,-31.8198986053],"type":"Point"}
}