{
  "type": "Feature",
  "properties": {
    "iso:country":"AU",
    "sg:address":"Shop B4 Stockland Corrimal Crt",
    "sg:city":"Corrimal",
    "sg:classifiers":[
        {
            "category":"Manufacturing",
            "subcategory":"Jewelry",
            "type":"Manufacturing & Wholesale Goods"
        }
    ],
    "sg:phone":"+61 2 4285 3395",
    "sg:postcode":"2518",
    "sg:province":"NSW",
    "sg:tags":[
        "mfrg",
        "jeweller"
    ],
    "wof:name":"Dennis Jewellers",
    "wof:placetype":"venue"
},
  "geometry": {"coordinates":[150.88652,-34.375858],"type":"Point"}
}