{
  "type": "Feature",
  "properties": {
    "addr:full":"Unit 8, 2 Kipling St St Kilda VIC 3182",
    "addr:housenumber":"2",
    "addr:postcode":"3182",
    "addr:street":"Kipling St",
    "iso:country":"AU",
    "sg:address":"Unit 8, 2 Kipling St",
    "sg:city":"St Kilda",
    "sg:classifiers":[
        {
            "category":"Professional",
            "subcategory":"Computer Services",
            "type":"Services"
        }
    ],
    "sg:phone":"+61 3 9537 2742",
    "sg:postcode":"3182",
    "sg:province":"VIC",
    "sg:tags":[
        "equipment",
        "networking",
        "installation"
    ],
    "wof:name":"Computer Doctor",
    "wof:placetype":"venue"
},
  "geometry": {"coordinates":[144.99095153799999,-37.8640861511],"type":"Point"}
}