{
  "type": "Feature",
  "properties": {
    "addr:full":"28 Wolseley Rd Blackwood SA 5051",
    "addr:housenumber":"28",
    "addr:postcode":"5051",
    "addr:street":"Wolseley Rd",
    "iso:country":"AU",
    "sg:address":"28 Wolseley Rd",
    "sg:city":"Blackwood",
    "sg:classifiers":[
        {
            "category":"Utilities",
            "subcategory":"Electric",
            "type":"Services"
        }
    ],
    "sg:phone":"+61 8 8278 1144",
    "sg:postcode":"5051",
    "sg:province":"SA",
    "sg:tags":[
        "electrical",
        "contractor"
    ],
    "wof:name":"Willoughby R Electrical",
    "wof:placetype":"venue"
},
  "geometry": {"coordinates":[138.61689799999999,-35.030331],"type":"Point"}
}