{
  "type": "Feature",
  "properties": {
    "addr:full":"U1/ 2 Shelly Rd Moruya NSW 2537",
    "addr:housenumber":"2",
    "addr:postcode":"2537",
    "addr:street":"U1 /;Shelly Rd",
    "iso:country":"AU",
    "sg:address":"U1/ 2 Shelly Rd",
    "sg:city":"Moruya",
    "sg:classifiers":[
        {
            "category":"Autos & Motor Vehicles",
            "subcategory":"Auto Supplies",
            "type":"Retail Goods"
        }
    ],
    "sg:phone":"+61 2 4474 5845",
    "sg:postcode":"2537",
    "sg:province":"NSW",
    "sg:tags":[
        "part",
        "cycles",
        "accessory"
    ],
    "wof:name":"Motorcycle Parts New & Used",
    "wof:placetype":"venue"
},
  "geometry": {"coordinates":[150.0887146,-35.8777160645],"type":"Point"}
}