{
  "type": "Feature",
  "properties": {
    "addr:full":"30 Paxton St Malvern East VIC 3145",
    "addr:housenumber":"30",
    "addr:postcode":"3145",
    "addr:street":"Paxton St",
    "iso:country":"AU",
    "sg:address":"30 Paxton St",
    "sg:city":"Malvern East",
    "sg:classifiers":[
        {
            "category":"Social Services",
            "subcategory":"Child Care",
            "type":"Services"
        }
    ],
    "sg:phone":"+61 3 9885 9491",
    "sg:postcode":"3145",
    "sg:province":"VIC",
    "sg:tags":[
        "baby",
        "sitter"
    ],
    "wof:name":"&#034;NANNY&#034; Baby-Sitting Service",
    "wof:placetype":"venue"
},
  "geometry": {"coordinates":[145.05305480999999,-37.8707199097],"type":"Point"}
}