{
  "type": "Feature",
  "properties": {
    "iso:country":"AU",
    "sg:address":"186- 196 Nathan St",
    "sg:city":"Aitkenvale",
    "sg:classifiers":[
        {
            "category":"Communications",
            "subcategory":"Film & Video Production",
            "type":"Services"
        }
    ],
    "sg:phone":"+61 7 4728 1011",
    "sg:postcode":"4814",
    "sg:province":"QLD",
    "sg:tags":[
        "dvd",
        "library"
    ],
    "wof:name":"Blockbuster Video Australia",
    "wof:placetype":"venue"
},
  "geometry": {"coordinates":[146.761337,-19.301659],"type":"Point"}
}