{
  "type": "Feature",
  "properties": {
    "addr:full":"Level 10 MLC Centre Martin Pl Sydney NSW 2000",
    "addr:postcode":"2000",
    "addr:street":"Martin Pl",
    "iso:country":"AU",
    "sg:address":"Level 10 MLC Centre Martin Pl",
    "sg:city":"Sydney",
    "sg:classifiers":[
        {
            "category":"Health Services",
            "subcategory":"Health Practitioner",
            "type":"Services"
        }
    ],
    "sg:phone":"+61 2 9223 1575",
    "sg:postcode":"2000",
    "sg:province":"NSW",
    "sg:tags":[
        "physiotherapist"
    ],
    "wof:name":"A Khallouf",
    "wof:placetype":"venue"
},
  "geometry": {"coordinates":[151.21018981899999,-33.8676948547],"type":"Point"}
}