{
  "type": "Feature",
  "properties": {
    "iso:country":"AU",
    "sg:address":"Homesglen TAFE, Batesford & Waverley Rds",
    "sg:city":"Chadstone",
    "sg:classifiers":[
        {
            "category":"Sports & Exercise",
            "subcategory":"Gym",
            "type":"Entertainment"
        }
    ],
    "sg:phone":"+61 1300 557 799",
    "sg:postcode":"3148",
    "sg:province":"VIC",
    "sg:tags":[
        "health",
        "fitness"
    ],
    "wof:name":"Fitness First Chadstone TAFE",
    "wof:placetype":"venue"
},
  "geometry": {"coordinates":[145.09750366200001,-37.8758392334],"type":"Point"}
}