{
  "type": "Feature",
  "properties": {
    "addr:full":"Bay 6 13 Johnson St Tuggerah NSW 2259",
    "addr:housenumber":"13",
    "addr:postcode":"2259",
    "addr:street":"Johnson St",
    "iso:country":"AU",
    "sg:address":"Bay 6 13 Johnson St",
    "sg:city":"Tuggerah",
    "sg:classifiers":[
        {
            "category":"Retail",
            "subcategory":"Auto Repair",
            "type":"Services"
        }
    ],
    "sg:phone":"+61 2 4351 2355",
    "sg:postcode":"2259",
    "sg:province":"NSW",
    "sg:tags":[
        "repairer",
        "motor",
        "engineer"
    ],
    "wof:name":"Gaff Automotive Repairs",
    "wof:placetype":"venue"
},
  "geometry": {"coordinates":[151.41969299300001,-33.2943725586],"type":"Point"}
}