{
  "type": "Feature",
  "properties": {
    "iso:country":"AU",
    "sg:address":"Walkerston Shopping Centre, Dutton Rd",
    "sg:city":"Walkerston",
    "sg:classifiers":[
        {
            "category":"Fast Food",
            "type":"Food & Drink"
        }
    ],
    "sg:phone":"+61 7 4959 3588",
    "sg:postcode":"4751",
    "sg:province":"QLD",
    "sg:tags":[
        "away",
        "take"
    ],
    "wof:name":"Eagle Boys Pizza",
    "wof:placetype":"venue"
},
  "geometry": {"coordinates":[149.06546,-21.160376],"type":"Point"}
}