{
  "type": "Feature",
  "properties": {
    "iso:country":"AU",
    "sg:address":"697- 701 Botany Rd",
    "sg:city":"Rosebery",
    "sg:classifiers":[
        {
            "category":"Professional",
            "type":"Services"
        }
    ],
    "sg:phone":"+61 2 9667 1033",
    "sg:postcode":"2018",
    "sg:province":"NSW",
    "sg:tags":[
        "auctioneer"
    ],
    "wof:name":"Geoff K Gray Auctions",
    "wof:placetype":"venue"
},
  "geometry": {"coordinates":[151.20150756800001,-33.9132080078],"type":"Point"}
}