{
  "type": "Feature",
  "properties": {
    "iso:country":"AU",
    "sg:address":"41 High St",
    "sg:city":"Wauchope",
    "sg:classifiers":[
        {
            "category":"Personal",
            "subcategory":"Beauty Salon",
            "type":"Services"
        }
    ],
    "sg:phone":"+61 2 6585 3168",
    "sg:postcode":"2446",
    "sg:province":"NSW",
    "sg:tags":[
        "hairdresser"
    ],
    "wof:name":"Hair Affair-Beautician",
    "wof:placetype":"venue"
},
  "geometry": {"coordinates":[152.73262,-31.457191],"type":"Point"}
}