{
  "type": "Feature",
  "properties": {
    "addr:full":"311 Main St Bairnsdale VIC 3875",
    "addr:housenumber":"311",
    "addr:postcode":"3875",
    "addr:street":"Main St",
    "iso:country":"AU",
    "sg:address":"311 Main St",
    "sg:city":"Bairnsdale",
    "sg:classifiers":[
        {
            "category":"Health Services",
            "subcategory":"Doctor",
            "type":"Services"
        }
    ],
    "sg:phone":"+61 3 5152 1940",
    "sg:postcode":"3875",
    "sg:province":"VIC",
    "sg:tags":[
        "reflexology"
    ],
    "wof:name":"Ralph Wall Massage",
    "wof:placetype":"venue"
},
  "geometry": {"coordinates":[147.827224731,-37.7086296082],"type":"Point"}
}