{
  "type": "Feature",
  "properties": {
    "iso:country":"AU",
    "sg:address":"St",
    "sg:city":"Georges Basin",
    "sg:classifiers":[
        {
            "category":"Retail",
            "subcategory":"Auto Rental",
            "type":"Services"
        }
    ],
    "sg:phone":"+61 2 4443 5557",
    "sg:postcode":"2540",
    "sg:province":"NSW",
    "sg:tags":[
        "car",
        "wedding"
    ],
    "wof:name":"Shoalhaven Prestige Wedding Cars",
    "wof:placetype":"venue"
},
  "geometry": {"coordinates":[150.598114014,-35.0891685486],"type":"Point"}
}