{
  "type": "Feature",
  "properties": {
    "addr:full":"Shop 7, 60 MacGregor Tce Bardon QLD 4065",
    "addr:housenumber":"shop;60",
    "addr:postcode":"4065",
    "addr:street":"Macgregor Tce Bardon",
    "iso:country":"AU",
    "sg:address":"Shop 7, 60 MacGregor Tce",
    "sg:city":"Bardon",
    "sg:classifiers":[
        {
            "category":"Food & Beverages",
            "subcategory":"Bakery",
            "type":"Retail Goods"
        }
    ],
    "sg:phone":"+61 7 3217 6437",
    "sg:postcode":"4065",
    "sg:province":"QLD",
    "sg:tags":[
        "baker"
    ],
    "wof:name":"Brumby's Bakeries",
    "wof:placetype":"venue"
},
  "geometry": {"coordinates":[152.987670898,-27.4583778381],"type":"Point"}
}