{
  "type": "Feature",
  "properties": {
    "addr:full":"29 High St Glen Iris VIC 3146",
    "addr:housenumber":"29",
    "addr:postcode":"3146",
    "addr:street":"High St",
    "iso:country":"AU",
    "sg:address":"29 High St",
    "sg:city":"Glen Iris",
    "sg:classifiers":[
        {
            "category":"Building & Trades",
            "subcategory":"Construction",
            "type":"Services"
        }
    ],
    "sg:phone":"+61 3 9885 2011",
    "sg:postcode":"3146",
    "sg:province":"VIC",
    "sg:tags":[
        "contractor"
    ],
    "wof:name":"Nicholson Wright P/L",
    "wof:placetype":"venue"
},
  "geometry": {"coordinates":[145.06532287600001,-37.8615913391],"type":"Point"}
}