{
  "type": "Feature",
  "properties": {
    "iso:country":"AU",
    "sg:address":"Shop 1/ 121 Richmond Tce",
    "sg:city":"Coraki",
    "sg:classifiers":[
        {
            "category":"Health Services",
            "subcategory":"Doctor",
            "type":"Services"
        }
    ],
    "sg:phone":"+61 2 6683 2888",
    "sg:postcode":"2471",
    "sg:province":"NSW",
    "sg:tags":[
        "medical",
        "practitioner"
    ],
    "wof:name":"Coraki Medical Centre",
    "wof:placetype":"venue"
},
  "geometry": {"coordinates":[153.28669738799999,-28.9844837189],"type":"Point"}
}