{
  "type": "Feature",
  "properties": {
    "iso:country":"AU",
    "sg:address":"94 McNaughton Ave",
    "sg:city":"Maryland",
    "sg:classifiers":[
        {
            "category":"Building & Trades",
            "subcategory":"Construction",
            "type":"Services"
        }
    ],
    "sg:phone":"+61 2 4951 6945",
    "sg:postcode":"2287",
    "sg:province":"NSW",
    "sg:tags":[
        "earth",
        "excavating",
        "moving",
        "contractor"
    ],
    "wof:name":"E McTaggart Excavator Hire",
    "wof:placetype":"venue"
},
  "geometry": {"coordinates":[151.66279602,-32.8842010498],"type":"Point"}
}