{
  "type": "Feature",
  "properties": {
    "addr:full":"10/ 82 Stanley St Darlinghurst NSW 2010",
    "addr:housenumber":"10 / 82",
    "addr:postcode":"2010",
    "addr:street":"Stanley St",
    "iso:country":"AU",
    "sg:address":"10/ 82 Stanley St",
    "sg:city":"Darlinghurst",
    "sg:classifiers":[
        {
            "category":"Manufacturing",
            "subcategory":"Food",
            "type":"Manufacturing & Wholesale Goods"
        }
    ],
    "sg:phone":"+61 2 9360 0774",
    "sg:postcode":"2010",
    "sg:province":"NSW",
    "sg:tags":[
        "function",
        "catering"
    ],
    "sg:website":"http://www.budgetbites.com.au",
    "wof:name":"Budget Bites",
    "wof:placetype":"venue"
},
  "geometry": {"coordinates":[151.21580505399999,-33.8744277954],"type":"Point"}
}