{
  "type": "Feature",
  "properties": {
    "addr:full":"10 Crane St Ballina NSW 2478",
    "addr:housenumber":"10",
    "addr:postcode":"2478",
    "addr:street":"Crane St",
    "iso:country":"AU",
    "sg:address":"10 Crane St",
    "sg:city":"Ballina",
    "sg:classifiers":[
        {
            "category":"Wholesale",
            "subcategory":"Home Furnishings",
            "type":"Manufacturing & Wholesale Goods"
        }
    ],
    "sg:phone":"+61 2 6686 2214",
    "sg:postcode":"2478",
    "sg:province":"NSW",
    "sg:tags":[
        "wholesaler",
        "curtain",
        "mfrs"
    ],
    "wof:name":"Colleen Steel",
    "wof:placetype":"venue"
},
  "geometry": {"coordinates":[153.56800842300001,-28.8709106445],"type":"Point"}
}