{
  "type": "Feature",
  "properties": {
    "iso:country":"AU",
    "sg:address":"12th Floor 333 Adelaide St",
    "sg:city":"Brisbane",
    "sg:classifiers":[
        {
            "category":"Organizations",
            "subcategory":"Labor Organization",
            "type":"Services"
        }
    ],
    "sg:phone":"+61 7 3221 8855",
    "sg:postcode":"4000",
    "sg:province":"QLD",
    "sg:tags":[
        "union"
    ],
    "wof:name":"Australian Workers&#039; Union",
    "wof:placetype":"venue"
},
  "geometry": {"coordinates":[153.02952575699999,-27.4651126862],"type":"Point"}
}