{
  "type": "Feature",
  "properties": {
    "addr:full":"88 Clara St Ulverstone TAS 7315",
    "addr:housenumber":"88",
    "addr:postcode":"7315",
    "addr:street":"Clara St",
    "iso:country":"AU",
    "sg:address":"88 Clara St",
    "sg:city":"Ulverstone",
    "sg:classifiers":[
        {
            "category":"Building & Trades",
            "subcategory":"Cleaning & Sanitation",
            "type":"Services"
        }
    ],
    "sg:phone":"+61 421 073 499",
    "sg:postcode":"7315",
    "sg:province":"TAS",
    "sg:tags":[
        "cleaner",
        "repairer",
        "roof"
    ],
    "wof:name":"B.U.D. Roofing",
    "wof:placetype":"venue"
},
  "geometry": {"coordinates":[146.15473938,-41.1513290405],"type":"Point"}
}