{
  "type": "Feature",
  "properties": {
    "addr:full":"Ste 15, 50- 52 Urunga Pde Miranda NSW 2228",
    "addr:housenumber":"50 52",
    "addr:postcode":"2228",
    "addr:street":"Urunga Pde Miranda",
    "iso:country":"AU",
    "sg:address":"Ste 15, 50- 52 Urunga Pde",
    "sg:city":"Miranda",
    "sg:classifiers":[
        {
            "category":"Health Services",
            "subcategory":"Health Practitioner",
            "type":"Services"
        }
    ],
    "sg:phone":"+61 2 9524 7709",
    "sg:postcode":"2228",
    "sg:province":"NSW",
    "sg:tags":[
        "psychologist"
    ],
    "wof:name":"Mather Fiona",
    "wof:placetype":"venue"
},
  "geometry": {"coordinates":[151.10215759299999,-34.0357933044],"type":"Point"}
}