{
  "type": "Feature",
  "properties": {
    "addr:full":"450 Forrest Rd Bexley NSW 2207",
    "addr:housenumber":"450",
    "addr:postcode":"2207",
    "addr:street":"Forrest Rd",
    "iso:country":"AU",
    "sg:address":"450 Forrest Rd",
    "sg:city":"Bexley",
    "sg:classifiers":[
        {
            "category":"Communications",
            "subcategory":"Film & Video Production",
            "type":"Services"
        }
    ],
    "sg:phone":"+61 2 9556 2211",
    "sg:postcode":"2207",
    "sg:province":"NSW",
    "sg:tags":[
        "dvd",
        "library"
    ],
    "wof:name":"Movies 4 U",
    "wof:placetype":"venue"
},
  "geometry": {"coordinates":[151.12408447300001,-33.9518699646],"type":"Point"}
}