{
  "type": "Feature",
  "properties": {
    "iso:country":"AU",
    "sg:address":"55- 57 Main Rd",
    "sg:city":"Romsey",
    "sg:classifiers":[
        {
            "category":"Manufacturing",
            "subcategory":"Retail Goods",
            "type":"Manufacturing & Wholesale Goods"
        }
    ],
    "sg:phone":"+61 3 5429 6977",
    "sg:postcode":"3434",
    "sg:province":"VIC",
    "sg:tags":[
        "merchant",
        "pump",
        "mfrs"
    ],
    "wof:name":"Romsey Mowers",
    "wof:placetype":"venue"
},
  "geometry": {"coordinates":[144.743041992,-37.353679657],"type":"Point"}
}