{
  "type": "Feature",
  "properties": {
    "addr:full":"15 Chetwynd St Loganholme QLD 4129",
    "addr:housenumber":"15",
    "addr:postcode":"4129",
    "addr:street":"Chetwynd St",
    "iso:country":"AU",
    "sg:address":"15 Chetwynd St",
    "sg:city":"Loganholme",
    "sg:classifiers":[
        {
            "category":"Manufacturing",
            "subcategory":"Printing",
            "type":"Manufacturing & Wholesale Goods"
        }
    ],
    "sg:phone":"+61 7 3806 2955",
    "sg:postcode":"4129",
    "sg:province":"QLD",
    "sg:tags":[
        "wholesaler",
        "mfrs",
        "greeting",
        "card"
    ],
    "wof:name":"All Australian Greetings",
    "wof:placetype":"venue"
},
  "geometry": {"coordinates":[153.18841552699999,-27.6788387299],"type":"Point"}
}