{
  "type": "Feature",
  "properties": {
    "addr:full":"186 Warnervale Rd Hamlyn Terrace NSW 2259",
    "addr:housenumber":"186",
    "addr:postcode":"2259",
    "addr:street":"Warnervale Rd",
    "iso:country":"AU",
    "sg:address":"186 Warnervale Rd",
    "sg:city":"Hamlyn Terrace",
    "sg:classifiers":[
        {
            "category":"Professional",
            "subcategory":"Computer Services",
            "type":"Services"
        }
    ],
    "sg:phone":"+61 2 4392 7025",
    "sg:postcode":"2259",
    "sg:province":"NSW",
    "sg:tags":[
        "technical",
        "support"
    ],
    "wof:name":"Cornerstone Computer Connections",
    "wof:placetype":"venue"
},
  "geometry": {"coordinates":[151.472732544,-33.2507019043],"type":"Point"}
}