{
  "type": "Feature",
  "properties": {
    "addr:full":"Weld St Beaconsfield TAS 7270",
    "addr:postcode":"7270",
    "addr:street":"Weld St",
    "iso:country":"AU",
    "sg:address":"Weld St",
    "sg:city":"Beaconsfield",
    "sg:classifiers":[
        {
            "category":"Food & Beverages",
            "subcategory":"Supermarket",
            "type":"Retail Goods"
        }
    ],
    "sg:phone":"+61 3 6383 1171",
    "sg:postcode":"7270",
    "sg:province":"TAS",
    "sg:tags":[
        "grocery",
        "store"
    ],
    "wof:name":"Festival IGA Stores",
    "wof:placetype":"venue"
},
  "geometry": {"coordinates":[146.81593322800001,-41.1999397278],"type":"Point"}
}