{
  "type": "Feature",
  "properties": {
    "addr:full":"Ste24/ 22b Horwood Pl Parramatta NSW 2150",
    "addr:housenumber":"22b",
    "addr:postcode":"2150",
    "addr:street":"/",
    "iso:country":"AU",
    "sg:address":"Ste24/ 22b Horwood Pl",
    "sg:city":"Parramatta",
    "sg:classifiers":[
        {
            "category":"Social Services",
            "subcategory":"Retirement Home",
            "type":"Services"
        }
    ],
    "sg:phone":"+61 2 9721 2121",
    "sg:postcode":"2150",
    "sg:province":"NSW",
    "sg:tags":[
        "life",
        "coaching"
    ],
    "wof:name":"Coaching For Excellence",
    "wof:placetype":"venue"
},
  "geometry": {"coordinates":[150.921600342,-33.7408447266],"type":"Point"}
}