{
  "type": "Feature",
  "properties": {
    "addr:full":"13 Hovell St Wodonga VIC 3690",
    "addr:housenumber":"13",
    "addr:postcode":"3690",
    "addr:street":"Hovell St",
    "iso:country":"AU",
    "sg:address":"13 Hovell St",
    "sg:city":"Wodonga",
    "sg:classifiers":[
        {
            "category":"Manufacturing",
            "subcategory":"Metals",
            "type":"Manufacturing & Wholesale Goods"
        }
    ],
    "sg:phone":"+61 2 6056 3477",
    "sg:postcode":"3690",
    "sg:province":"VIC",
    "sg:tags":[
        "steel",
        "tube"
    ],
    "wof:name":"Surdex Steel Pty Ltd",
    "wof:placetype":"venue"
},
  "geometry": {"coordinates":[146.89421081500001,-36.1156158447],"type":"Point"}
}