{
  "type": "Feature",
  "properties": {
    "iso:country":"AU",
    "sg:address":"Alexandra St",
    "sg:city":"Kurri Kurri",
    "sg:classifiers":[
        {
            "category":"Industrial Area",
            "type":"Public Place"
        }
    ],
    "sg:phone":"+61 2 4936 1107",
    "sg:postcode":"2327",
    "sg:province":"NSW",
    "sg:tags":[
        "rural",
        "shed"
    ],
    "wof:name":"Coast To Coast Garages",
    "wof:placetype":"venue"
},
  "geometry": {"coordinates":[151.47653198200001,-32.8205299377],"type":"Point"}
}