{
  "type": "Feature",
  "properties": {
    "iso:country":"AU",
    "sg:address":"Level 1, 98 Victoria St",
    "sg:city":"Bunbury",
    "sg:classifiers":[
        {
            "category":"Professional",
            "subcategory":"Employment Agencies",
            "type":"Services"
        }
    ],
    "sg:phone":"+61 1300 309 500",
    "sg:postcode":"6230",
    "sg:province":"WA",
    "sg:tags":[
        "provider",
        "internet"
    ],
    "wof:name":"Gateway Internet Services",
    "wof:placetype":"venue"
},
  "geometry": {"coordinates":[115.637169,-33.325012],"type":"Point"}
}