{
  "type": "Feature",
  "properties": {
    "iso:country":"AU",
    "sg:address":"Level 1, 36 Roger St",
    "sg:city":"Brookvale",
    "sg:classifiers":[
        {
            "category":"Banks & Credit Unions",
            "subcategory":"Investment Brokerage",
            "type":"Services"
        }
    ],
    "sg:phone":"+61 2 9907 1968",
    "sg:postcode":"2100",
    "sg:province":"NSW",
    "sg:tags":[
        "shutter",
        "louvre"
    ],
    "sg:website":"http://www.fairliteblinds.com.au",
    "wof:name":"Fairlite Blinds Pty Ltd",
    "wof:placetype":"venue"
},
  "geometry": {"coordinates":[151.26249694800001,-33.7639503479],"type":"Point"}
}