{
  "type": "Feature",
  "properties": {
    "addr:full":"Shop C24, Harbour Town Outlet Centre, 9, Gateway Drive Biggera Waters QLD 4216",
    "addr:housenumber":"c24;9",
    "addr:postcode":"4216",
    "addr:street":"Gateway Drive",
    "iso:country":"AU",
    "sg:address":"Shop C24, Harbour Town Outlet Centre, 9, Gateway Drive",
    "sg:city":"Biggera Waters",
    "sg:classifiers":[
        {
            "category":"Shopping",
            "subcategory":"Clothing, Apparel, & Fashions",
            "type":"Retail Goods"
        }
    ],
    "sg:phone":"+61 7 5537 5415",
    "sg:postcode":"4216",
    "sg:province":"QLD",
    "sg:tags":[
        "lady",
        "wear"
    ],
    "wof:name":"The Designer Room",
    "wof:placetype":"venue"
},
  "geometry": {"coordinates":[153.38572692899999,-27.9329986572],"type":"Point"}
}