{
  "type": "Feature",
  "properties": {
    "addr:full":"Murray St (cnr James St) Pinjarra WA 6208",
    "addr:postcode":"6208",
    "addr:street":"Murray St Cnr James St",
    "iso:country":"AU",
    "sg:address":"Murray St (cnr James St)",
    "sg:city":"Pinjarra",
    "sg:classifiers":[
        {
            "category":"Professional",
            "subcategory":"Employment Agencies",
            "type":"Services"
        }
    ],
    "sg:phone":"+61 8 9531 3833",
    "sg:postcode":"6208",
    "sg:province":"WA",
    "wof:name":"Community First Inc",
    "wof:placetype":"venue"
},
  "geometry": {"coordinates":[115.874458,-32.626823],"type":"Point"}
}