{
  "type": "Feature",
  "properties": {
    "addr:full":"36 Haynes Ave Eleebana NSW 2282",
    "addr:housenumber":"36",
    "addr:postcode":"2282",
    "addr:street":"Haynes Ave",
    "iso:country":"AU",
    "sg:address":"36 Haynes Ave",
    "sg:city":"Eleebana",
    "sg:classifiers":[
        {
            "category":"Health Services",
            "subcategory":"Health Practitioner",
            "type":"Services"
        }
    ],
    "sg:phone":"+61 408 113 861",
    "sg:postcode":"2282",
    "sg:province":"NSW",
    "sg:tags":[
        "bowen",
        "therapy"
    ],
    "wof:name":"Webster Jennifer Dip in BT",
    "wof:placetype":"venue"
},
  "geometry": {"coordinates":[151.643966675,-32.9879798889],"type":"Point"}
}