{
  "type": "Feature",
  "properties": {
    "iso:country":"AU",
    "sg:address":"Factory 2 / 60 Dixon St",
    "sg:city":"Inverloch",
    "sg:classifiers":[
        {
            "category":"Wholesale",
            "subcategory":"Toys & Hobbies",
            "type":"Manufacturing & Wholesale Goods"
        }
    ],
    "sg:phone":"+61 3 5674 6085",
    "sg:postcode":"3996",
    "sg:province":"VIC",
    "sg:tags":[
        "mfrs"
    ],
    "wof:name":"Jambolli",
    "wof:placetype":"venue"
},
  "geometry": {"coordinates":[145.717682,-38.631535],"type":"Point"}
}