{
  "type": "Feature",
  "properties": {
    "addr:full":"Westfield Innaloo Shop 1028 Cannington WA 6107",
    "addr:housenumber":"1028",
    "addr:postcode":"6107",
    "iso:country":"AU",
    "sg:address":"Westfield Innaloo Shop 1028",
    "sg:city":"Cannington",
    "sg:classifiers":[
        {
            "category":"Professional",
            "subcategory":"Art Services",
            "type":"Services"
        }
    ],
    "sg:phone":"+61 8 9446 4930",
    "sg:postcode":"6107",
    "sg:province":"WA",
    "sg:tags":[
        "picture",
        "frame",
        "framing"
    ],
    "wof:name":"Framers Mill",
    "wof:placetype":"venue"
},
  "geometry": {"coordinates":[115.990013123,-32.0448036194],"type":"Point"}
}