{
  "type": "Feature",
  "properties": {
    "iso:country":"AU",
    "sg:address":"5264 Pacific Hwy",
    "sg:city":"Kew",
    "sg:classifiers":[
        {
            "category":"Wholesale",
            "subcategory":"Farm Supplies",
            "type":"Manufacturing & Wholesale Goods"
        }
    ],
    "sg:phone":"+61 2 6585 7123",
    "sg:postcode":"2439",
    "sg:province":"NSW",
    "sg:tags":[
        "equipment"
    ],
    "wof:name":"Beattie's Tractors & Implements",
    "wof:placetype":"venue"
},
  "geometry": {"coordinates":[152.72357199999999,-31.634142],"type":"Point"}
}