{
  "type": "Feature",
  "properties": {
    "addr:full":"34 Eastern Ave Bilinga QLD 4225",
    "addr:housenumber":"34",
    "addr:postcode":"4225",
    "addr:street":"Eastern Ave",
    "iso:country":"AU",
    "sg:address":"34 Eastern Ave",
    "sg:city":"Bilinga",
    "sg:classifiers":[
        {
            "category":"Education",
            "subcategory":"Special Training",
            "type":"Public Place"
        }
    ],
    "sg:phone":"+61 7 5536 2822",
    "sg:postcode":"4225",
    "sg:province":"QLD",
    "sg:tags":[
        "school",
        "flying"
    ],
    "wof:name":"Air Gold Coast Pty Ltd",
    "wof:placetype":"venue"
},
  "geometry": {"coordinates":[153.510375977,-28.161190033],"type":"Point"}
}