{
  "type": "Feature",
  "properties": {
    "addr:full":"424b Station St Box Hill VIC 3128",
    "addr:housenumber":"424b",
    "addr:postcode":"3128",
    "addr:street":"Station St",
    "iso:country":"AU",
    "sg:address":"424b Station St",
    "sg:city":"Box Hill",
    "sg:classifiers":[
        {
            "category":"Sports & Exercise",
            "subcategory":"Gym",
            "type":"Entertainment"
        }
    ],
    "sg:phone":"+61 3 9897 3000",
    "sg:postcode":"3128",
    "sg:province":"VIC",
    "sg:tags":[
        "health",
        "fitness"
    ],
    "wof:name":"Oze-Yoga & Love Me, Love Me Not Holistic Centre",
    "wof:placetype":"venue"
},
  "geometry": {"coordinates":[145.12213134800001,-37.8280601501],"type":"Point"}
}