{
  "type": "Feature",
  "properties": {
    "addr:full":"Shp24b/ 219 Hampton Rd South Fremantle WA 6162",
    "addr:housenumber":"219",
    "addr:postcode":"6162",
    "addr:street":"Hampton Rd",
    "iso:country":"AU",
    "sg:address":"Shp24b/ 219 Hampton Rd",
    "sg:city":"South Fremantle",
    "sg:classifiers":[
        {
            "category":"Personal",
            "subcategory":"Barber",
            "type":"Services"
        }
    ],
    "sg:phone":"+61 8 9431 7531",
    "sg:postcode":"6162",
    "sg:province":"WA",
    "wof:name":"Sunset Barbers",
    "wof:placetype":"venue"
},
  "geometry": {"coordinates":[115.760132,-32.074459],"type":"Point"}
}