{
  "type": "Feature",
  "properties": {
    "addr:full":"9 Elgin St Maitland NSW 2320",
    "addr:housenumber":"9",
    "addr:postcode":"2320",
    "addr:street":"Elgin St",
    "iso:country":"AU",
    "sg:address":"9 Elgin St",
    "sg:city":"Maitland",
    "sg:classifiers":[
        {
            "category":"Manufacturing",
            "subcategory":"Textiles",
            "type":"Manufacturing & Wholesale Goods"
        }
    ],
    "sg:phone":"+61 2 4933 4266",
    "sg:postcode":"2320",
    "sg:province":"NSW",
    "sg:tags":[
        "knitted",
        "woven",
        "fabric"
    ],
    "wof:name":"Bargain Box Fabrics",
    "wof:placetype":"venue"
},
  "geometry": {"coordinates":[151.55473327600001,-32.732460022],"type":"Point"}
}