{
  "type": "Feature",
  "properties": {
    "addr:full":"Shop 303a Kawana Shopping World Buddina QLD 4575",
    "addr:housenumber":"303a",
    "addr:postcode":"4575",
    "iso:country":"AU",
    "sg:address":"Shop 303a Kawana Shopping World",
    "sg:city":"Buddina",
    "sg:classifiers":[
        {
            "category":"Wholesale",
            "subcategory":"Music Publishers",
            "type":"Manufacturing & Wholesale Goods"
        }
    ],
    "sg:phone":"+61 7 5444 8497",
    "sg:postcode":"4575",
    "sg:province":"QLD",
    "sg:tags":[
        "wholesaler",
        "dvd",
        "mfrs",
        "cd"
    ],
    "wof:name":"Sanity",
    "wof:placetype":"venue"
},
  "geometry": {"coordinates":[153.129639,-26.700609],"type":"Point"}
}