{
  "type": "Feature",
  "properties": {
    "iso:country":"AU",
    "sg:address":"14 Sand St",
    "sg:city":"Coffs Harbour",
    "sg:classifiers":[
        {
            "category":"Building & Trades",
            "subcategory":"Construction",
            "type":"Services"
        }
    ],
    "sg:phone":"+61 409 700 352",
    "sg:postcode":"2450",
    "sg:province":"NSW",
    "sg:tags":[
        "window",
        "tinting"
    ],
    "wof:name":"Bullet Proof Window Tinting",
    "wof:placetype":"venue"
},
  "geometry": {"coordinates":[153.09759500000001,-30.30769],"type":"Point"}
}