{
  "type": "Feature",
  "properties": {
    "iso:country":"AU",
    "sg:address":"10/ 9 Inkerman St St",
    "sg:city":"Kilda",
    "sg:classifiers":[
        {
            "category":"Professional",
            "subcategory":"Art Services",
            "type":"Services"
        }
    ],
    "sg:phone":"+61 3 9593 6677",
    "sg:postcode":"3182",
    "sg:province":"VIC",
    "sg:tags":[
        "graphic",
        "designer"
    ],
    "wof:name":"Caramel Creative",
    "wof:placetype":"venue"
},
  "geometry": {"coordinates":[144.982345581,-37.8643074036],"type":"Point"}
}