{
  "type": "Feature",
  "properties": {
    "addr:full":"42 Huntingdale Rd Noarlunga Downs SA 5168",
    "addr:housenumber":"42",
    "addr:postcode":"5168",
    "addr:street":"Huntingdale Rd",
    "iso:country":"AU",
    "sg:address":"42 Huntingdale Rd",
    "sg:city":"Noarlunga Downs",
    "sg:classifiers":[
        {
            "category":"Government",
            "subcategory":"Fire Station",
            "type":"Public Place"
        }
    ],
    "sg:phone":"+61 8 8326 5511",
    "sg:postcode":"5168",
    "sg:province":"SA",
    "sg:tags":[
        "equipment",
        "protection",
        "consultant"
    ],
    "wof:name":"Country Safety & Fire Equipment",
    "wof:placetype":"venue"
},
  "geometry": {"coordinates":[138.499923706,-35.1563873291],"type":"Point"}
}