{
  "type": "Feature",
  "properties": {
    "iso:country":"AU",
    "sg:address":"Shop 1A, Cranbrook Rd",
    "sg:city":"Batemans Bay",
    "sg:classifiers":[
        {
            "category":"Building & Trades",
            "subcategory":"Equipment Rental",
            "type":"Services"
        }
    ],
    "sg:phone":"+61 2 4472 8333",
    "sg:postcode":"2536",
    "sg:province":"NSW",
    "sg:tags":[
        "hire",
        "catering"
    ],
    "wof:name":"Hire N Hire Batemans Bay",
    "wof:placetype":"venue"
},
  "geometry": {"coordinates":[150.175247192,-35.7203903198],"type":"Point"}
}