{
  "type": "Feature",
  "properties": {
    "iso:country":"AU",
    "sg:address":"293 High St",
    "sg:city":"Preston",
    "sg:classifiers":[
        {
            "category":"Professional",
            "subcategory":"Employment Agencies",
            "type":"Services"
        }
    ],
    "sg:phone":"+61 3 9484 8511",
    "sg:postcode":"3072",
    "sg:province":"VIC",
    "wof:name":"MAXNetWork Employment",
    "wof:placetype":"venue"
},
  "geometry": {"coordinates":[145.00372314399999,-37.7406845093],"type":"Point"}
}