{
  "type": "Feature",
  "properties": {
    "iso:country":"AU",
    "sg:address":"1393 Botany Rd",
    "sg:city":"Botany",
    "sg:classifiers":[
        {
            "category":"Personal",
            "subcategory":"Beauty Salon",
            "type":"Services"
        }
    ],
    "sg:phone":"+61 2 9316 8519",
    "sg:postcode":"2019",
    "sg:province":"NSW",
    "sg:tags":[
        "hairdresser"
    ],
    "wof:name":"Peters Hairdressing For Men",
    "wof:placetype":"venue"
},
  "geometry": {"coordinates":[151.19627380399999,-33.9439697266],"type":"Point"}
}