{
  "type": "Feature",
  "properties": {
    "addr:full":"26 Mitchell St Darwin NT 0800",
    "addr:housenumber":"26",
    "addr:postcode":"nt 0800",
    "addr:street":"Mitchell St",
    "iso:country":"AU",
    "sg:address":"26 Mitchell St",
    "sg:city":"Darwin",
    "sg:classifiers":[
        {
            "category":"Health Services",
            "subcategory":"Dentist",
            "type":"Services"
        }
    ],
    "sg:phone":"+61 8 8941 1717",
    "sg:postcode":"0800",
    "sg:province":"NT",
    "wof:name":"Central Darwin Dental Surgery",
    "wof:placetype":"venue"
},
  "geometry": {"coordinates":[130.841888428,-12.4648275375],"type":"Point"}
}