{
  "type": "Feature",
  "properties": {
    "addr:full":"Stawell Rd Horsham VIC 3400",
    "addr:postcode":"3400",
    "addr:street":"Stawell Rd",
    "iso:country":"AU",
    "sg:address":"Stawell Rd",
    "sg:city":"Horsham",
    "sg:classifiers":[
        {
            "category":"Autos & Motor Vehicles",
            "subcategory":"Fuel & Gas Station",
            "type":"Retail Goods"
        }
    ],
    "sg:phone":"+61 3 5382 6948",
    "sg:postcode":"3400",
    "sg:province":"VIC",
    "wof:name":"Caltex 24 Hour Roadhouse",
    "wof:placetype":"venue"
},
  "geometry": {"coordinates":[142.204833984,-36.7234687805],"type":"Point"}
}