{
  "type": "Feature",
  "properties": {
    "addr:full":"Unit 5/ 58 Pritchard Rd Virginia QLD 4014",
    "addr:housenumber":"58",
    "addr:postcode":"4014",
    "addr:street":"Pritchard Rd",
    "iso:country":"AU",
    "sg:address":"Unit 5/ 58 Pritchard Rd",
    "sg:city":"Virginia",
    "sg:classifiers":[
        {
            "category":"Professional",
            "subcategory":"Accounting & Tax Preparation",
            "type":"Services"
        }
    ],
    "sg:phone":"+61 7 3265 7760",
    "sg:postcode":"4014",
    "sg:province":"QLD",
    "sg:tags":[
        "accountant",
        "auditor"
    ],
    "wof:name":"Precision Knives (Aust)",
    "wof:placetype":"venue"
},
  "geometry": {"coordinates":[153.05862426799999,-27.3741130829],"type":"Point"}
}