{
  "type": "Feature",
  "properties": {
    "addr:full":"1415 Logan Rd Mt Gravatt QLD 4122",
    "addr:housenumber":"1415",
    "addr:postcode":"4122",
    "addr:street":"Logan Rd",
    "iso:country":"AU",
    "sg:address":"1415 Logan Rd",
    "sg:city":"Mt Gravatt",
    "sg:classifiers":[
        {
            "category":"Health Services",
            "subcategory":"Health Practitioner",
            "type":"Services"
        }
    ],
    "sg:phone":"+61 7 3219 2011",
    "sg:postcode":"4122",
    "sg:province":"QLD",
    "sg:tags":[
        "physiotherapist"
    ],
    "wof:name":"Advanced Physiotherapy",
    "wof:placetype":"venue"
},
  "geometry": {"coordinates":[153.07853698700001,-27.5369625092],"type":"Point"}
}