{
  "type": "Feature",
  "properties": {
    "addr:full":"\"Harlow Park\" Gostwyck Rd Uralla NSW 2358",
    "addr:postcode":"2358",
    "addr:street":"Gostwyck Rd",
    "iso:country":"AU",
    "sg:address":"\"Harlow Park\" Gostwyck Rd",
    "sg:city":"Uralla",
    "sg:classifiers":[
        {
            "category":"Travel",
            "subcategory":"Travel Agent",
            "type":"Entertainment"
        }
    ],
    "sg:phone":"+61 2 6778 4631",
    "sg:postcode":"2358",
    "sg:province":"NSW",
    "sg:tags":[
        "tour",
        "holiday",
        "adventure"
    ],
    "wof:name":"Harlow Park Horse Riding",
    "wof:placetype":"venue"
},
  "geometry": {"coordinates":[151.50749206500001,-30.6487865448],"type":"Point"}
}