{
  "type": "Feature",
  "properties": {
    "addr:full":"2 Fiani Crt Kingston TAS 7050",
    "addr:housenumber":"2",
    "addr:postcode":"7050",
    "addr:street":"Fiani Crt",
    "iso:country":"AU",
    "sg:address":"2 Fiani Crt",
    "sg:city":"Kingston",
    "sg:classifiers":[
        {
            "category":"Building & Trades",
            "subcategory":"Plumbing",
            "type":"Services"
        }
    ],
    "sg:phone":"+61 418 399 189",
    "sg:postcode":"7050",
    "sg:province":"TAS",
    "sg:tags":[
        "plumber",
        "gasfitters"
    ],
    "wof:name":"Vince Plumbing ND & LL",
    "wof:placetype":"venue"
},
  "geometry": {"coordinates":[147.299881,-42.968761],"type":"Point"}
}