{
  "type": "Feature",
  "properties": {
    "addr:full":"42 Shakespeare St Traralgon VIC 3844",
    "addr:housenumber":"42",
    "addr:postcode":"3844",
    "addr:street":"Shakespeare St",
    "iso:country":"AU",
    "sg:address":"42 Shakespeare St",
    "sg:city":"Traralgon",
    "sg:classifiers":[
        {
            "category":"Building & Trades",
            "subcategory":"Landscaping Services",
            "type":"Services"
        }
    ],
    "sg:phone":"+61 412 953 922",
    "sg:postcode":"3844",
    "sg:province":"VIC",
    "sg:tags":[
        "gardener"
    ],
    "wof:name":"S & K Oxley Landscaping",
    "wof:placetype":"venue"
},
  "geometry": {"coordinates":[146.53808593799999,-38.2007141113],"type":"Point"}
}