{
  "type": "Feature",
  "properties": {
    "iso:country":"AU",
    "sg:address":"406 Bilsen Rd",
    "sg:city":"Geebung",
    "sg:classifiers":[
        {
            "category":"Home & Garden",
            "subcategory":"Carpets & Floor Coverings",
            "type":"Retail Goods"
        }
    ],
    "sg:phone":"+61 1300 788 625",
    "sg:postcode":"4034",
    "sg:province":"QLD",
    "sg:tags":[
        "wood"
    ],
    "wof:name":"Bamboo Wood Flooring",
    "wof:placetype":"venue"
},
  "geometry": {"coordinates":[153.05575561500001,-27.3717937469],"type":"Point"}
}