{
  "type": "Feature",
  "properties": {
    "addr:full":"24 Pittwater Rd Gladesville NSW 2111",
    "addr:housenumber":"24",
    "addr:postcode":"2111",
    "addr:street":"Pittwater Rd",
    "iso:country":"AU",
    "sg:address":"24 Pittwater Rd",
    "sg:city":"Gladesville",
    "sg:classifiers":[
        {
            "category":"Professional",
            "subcategory":"Printing & Photocopies",
            "type":"Services"
        }
    ],
    "sg:phone":"+61 2 9879 7313",
    "sg:postcode":"2111",
    "sg:province":"NSW",
    "sg:tags":[
        "trophy"
    ],
    "wof:name":"Gladesville Trophies",
    "wof:placetype":"venue"
},
  "geometry": {"coordinates":[151.128982544,-33.8286094666],"type":"Point"}
}