{
  "type": "Feature",
  "properties": {
    "addr:full":"Adelaide St Brisbane QLD 4000",
    "addr:postcode":"4000",
    "addr:street":"Adelaide St",
    "iso:country":"AU",
    "sg:address":"Adelaide St",
    "sg:city":"Brisbane",
    "sg:classifiers":[
        {
            "category":"Personal",
            "subcategory":"Beauty Salon",
            "type":"Services"
        }
    ],
    "sg:phone":"+61 7 3221 0377",
    "sg:postcode":"4000",
    "sg:province":"QLD",
    "sg:tags":[
        "hairdresser"
    ],
    "wof:name":"Impact Hair Care",
    "wof:placetype":"venue"
},
  "geometry": {"coordinates":[153.027175903,-27.4674472809],"type":"Point"}
}