{
  "type": "Feature",
  "properties": {
    "addr:full":"1619a Botany Rd Botany NSW 2019",
    "addr:housenumber":"1619a",
    "addr:postcode":"2019",
    "addr:street":"Botany Rd",
    "iso:country":"AU",
    "sg:address":"1619a Botany Rd",
    "sg:city":"Botany",
    "sg:classifiers":[
        {
            "category":"Banks & Credit Unions",
            "subcategory":"Investment Brokerage",
            "type":"Services"
        }
    ],
    "sg:phone":"+61 2 9316 4921",
    "sg:postcode":"2019",
    "sg:province":"NSW",
    "sg:tags":[
        "shutter",
        "louvre"
    ],
    "sg:website":"http://www.atpplantationshutters.com.au",
    "wof:name":"ATP Plantation Shutters Pty Ltd",
    "wof:placetype":"venue"
},
  "geometry": {"coordinates":[151.20370483400001,-33.9539337158],"type":"Point"}
}