{
  "type": "Feature",
  "properties": {
    "iso:country":"AU",
    "sg:address":"99 Glengala Rd",
    "sg:city":"Sunshine West",
    "sg:classifiers":[
        {
            "category":"Food & Beverages",
            "subcategory":"Supermarket",
            "type":"Retail Goods"
        }
    ],
    "sg:phone":"+61 3 9364 7685",
    "sg:postcode":"3020",
    "sg:province":"VIC",
    "sg:tags":[
        "grocery",
        "store"
    ],
    "wof:name":"Kim Dung Milk Bar & Asian Grocery",
    "wof:placetype":"venue"
},
  "geometry": {"coordinates":[144.816849,-37.790443],"type":"Point"}
}