{
  "type": "Feature",
  "properties": {
    "addr:full":"157 Riverpark Drv Annandale QLD 4814",
    "addr:housenumber":"157",
    "addr:postcode":"4814",
    "addr:street":"Riverpark Drv",
    "iso:country":"AU",
    "sg:address":"157 Riverpark Drv",
    "sg:city":"Annandale",
    "sg:classifiers":[
        {
            "category":"Building & Trades",
            "subcategory":"Construction",
            "type":"Services"
        }
    ],
    "sg:phone":"+61 7 4725 1523",
    "sg:postcode":"4814",
    "sg:province":"QLD",
    "sg:tags":[
        "pool",
        "swimming"
    ],
    "wof:name":"Kookaburra Pools",
    "wof:placetype":"venue"
},
  "geometry": {"coordinates":[146.785324,-19.312973],"type":"Point"}
}