{
  "type": "Feature",
  "properties": {
    "addr:full":"Shop 2, 524 Lutwyche Rd Lutwyche QLD 4030",
    "addr:housenumber":"shop 2 524",
    "addr:postcode":"4030",
    "addr:street":"Lutwyche Rd",
    "iso:country":"AU",
    "sg:address":"Shop 2, 524 Lutwyche Rd",
    "sg:city":"Lutwyche",
    "sg:classifiers":[
        {
            "category":"Professional",
            "subcategory":"Computer Services",
            "type":"Services"
        }
    ],
    "sg:phone":"+61 7 3857 1822",
    "sg:postcode":"4030",
    "sg:province":"QLD",
    "sg:tags":[
        "training"
    ],
    "wof:name":"The Fourth R (Brisbane NE) Pty Ltd",
    "wof:placetype":"venue"
},
  "geometry": {"coordinates":[153.033615,-27.422216],"type":"Point"}
}