{
  "type": "Feature",
  "properties": {
    "addr:full":"159 Holloway Rd Croydon North VIC 3136",
    "addr:housenumber":"159",
    "addr:postcode":"3136",
    "addr:street":"Holloway Rd",
    "iso:country":"AU",
    "sg:address":"159 Holloway Rd",
    "sg:city":"Croydon North",
    "sg:classifiers":[
        {
            "category":"Building & Trades",
            "subcategory":"Construction",
            "type":"Services"
        }
    ],
    "sg:phone":"+61 408 322 782",
    "sg:postcode":"3136",
    "sg:province":"VIC",
    "sg:tags":[
        "earth",
        "excavating",
        "moving",
        "contractor"
    ],
    "wof:name":"Ontrax Constructions",
    "wof:placetype":"venue"
},
  "geometry": {"coordinates":[145.273040772,-37.7629814148],"type":"Point"}
}