{
  "type": "Feature",
  "properties": {
    "addr:full":"Suite 4/ 15 Pandanus St Mudjimba QLD 4564",
    "addr:housenumber":"15",
    "addr:postcode":"4564",
    "addr:street":"Pandanus St",
    "iso:country":"AU",
    "sg:address":"Suite 4/ 15 Pandanus St",
    "sg:city":"Mudjimba",
    "sg:classifiers":[
        {
            "category":"Health Services",
            "subcategory":"Dentist",
            "type":"Services"
        }
    ],
    "sg:phone":"+61 7 5448 7837",
    "sg:postcode":"4564",
    "sg:province":"QLD",
    "wof:name":"Aussie Dental Tours",
    "wof:placetype":"venue"
},
  "geometry": {"coordinates":[153.09817504899999,-26.6146583557],"type":"Point"}
}