{
  "type": "Feature",
  "properties": {
    "addr:full":"PO Box 158 Oakey QLD 4401",
    "addr:postcode":"4401",
    "iso:country":"AU",
    "sg:address":"PO Box 158",
    "sg:city":"Oakey",
    "sg:classifiers":[
        {
            "category":"Airport",
            "subcategory":"General Aviation",
            "type":"Transportation"
        }
    ],
    "sg:phone":"+61 7 4691 4450",
    "sg:postcode":"4401",
    "sg:province":"QLD",
    "sg:tags":[
        "helicopter"
    ],
    "wof:name":"Bristow Defence Industries",
    "wof:placetype":"venue"
},
  "geometry": {"coordinates":[151.66009521500001,-27.4057693481],"type":"Point"}
}