{
  "type": "Feature",
  "properties": {
    "iso:country":"AU",
    "sg:address":"13 Sandridge Rd",
    "sg:city":"Bunbury",
    "sg:classifiers":[
        {
            "category":"Home & Garden",
            "subcategory":"Furniture",
            "type":"Retail Goods"
        }
    ],
    "sg:phone":"+61 8 9721 6677",
    "sg:postcode":"6230",
    "sg:province":"WA",
    "sg:tags":[
        "outdoor"
    ],
    "wof:name":"Vogue Furniture",
    "wof:placetype":"venue"
},
  "geometry": {"coordinates":[115.653877,-33.340385],"type":"Point"}
}