{
  "type": "Feature",
  "properties": {
    "iso:country":"AU",
    "sg:address":"251 Canning St",
    "sg:city":"Carlton North",
    "sg:classifiers":[
        {
            "category":"Professional",
            "subcategory":"Management & Consulting",
            "type":"Services"
        }
    ],
    "sg:phone":"+61 3 9348 2351",
    "sg:postcode":"3054",
    "sg:province":"VIC",
    "sg:tags":[
        "consultant"
    ],
    "wof:name":"Canterbury Consulting Group",
    "wof:placetype":"venue"
},
  "geometry": {"coordinates":[144.97363281200001,-37.7920036316],"type":"Point"}
}