{
  "type": "Feature",
  "properties": {
    "addr:full":"2 Martha St Melrose Park SA 5039",
    "addr:housenumber":"2",
    "addr:postcode":"5039",
    "addr:street":"Martha St",
    "iso:country":"AU",
    "sg:address":"2 Martha St",
    "sg:city":"Melrose Park",
    "sg:classifiers":[
        {
            "category":"Building & Trades",
            "subcategory":"Plumbing",
            "type":"Services"
        }
    ],
    "sg:phone":"+61 8 8374 4100",
    "sg:postcode":"5039",
    "sg:province":"SA",
    "sg:tags":[
        "plumber",
        "gasfitters"
    ],
    "wof:name":"Warren Plumbing Services",
    "wof:placetype":"venue"
},
  "geometry": {"coordinates":[138.575241089,-34.9808692932],"type":"Point"}
}