{
  "type": "Feature",
  "properties": {
    "iso:country":"AU",
    "sg:address":"43 Limestone St",
    "sg:city":"Ipswich",
    "sg:classifiers":[
        {
            "category":"Personal",
            "subcategory":"Shoe Repair & Shine",
            "type":"Services"
        }
    ],
    "sg:phone":"+61 7 3812 4355",
    "sg:postcode":"4305",
    "sg:province":"QLD",
    "sg:tags":[
        "footwear"
    ],
    "wof:name":"The Shoe Repairer",
    "wof:placetype":"venue"
},
  "geometry": {"coordinates":[152.76043701200001,-27.6153125763],"type":"Point"}
}