{
  "type": "Feature",
  "properties": {
    "iso:country":"AU",
    "sg:address":"505 Wyndham St",
    "sg:city":"Shepparton",
    "sg:classifiers":[
        {
            "category":"Travel",
            "subcategory":"Hotels & Motels",
            "type":"Entertainment"
        }
    ],
    "sg:phone":"+61 3 5821 3355",
    "sg:postcode":"3630",
    "sg:province":"VIC",
    "wof:name":"The Carrington Manor",
    "wof:placetype":"venue"
},
  "geometry": {"coordinates":[145.39796447800001,-36.3886947632],"type":"Point"}
}