{
  "type": "Feature",
  "properties": {
    "addr:full":"44 Margaret St Mayfield East NSW 2304",
    "addr:housenumber":"44",
    "addr:postcode":"2304",
    "addr:street":"Margaret St",
    "iso:country":"AU",
    "sg:address":"44 Margaret St",
    "sg:city":"Mayfield East",
    "sg:classifiers":[
        {
            "category":"Health Services",
            "subcategory":"Health Practitioner",
            "type":"Services"
        }
    ],
    "sg:phone":"+61 2 4968 9664",
    "sg:postcode":"2304",
    "sg:province":"NSW",
    "sg:tags":[
        "osteopath"
    ],
    "wof:name":"Andrew Farthing",
    "wof:placetype":"venue"
},
  "geometry": {"coordinates":[151.74911499000001,-32.9002494812],"type":"Point"}
}