{
  "type": "Feature",
  "properties": {
    "iso:country":"AU",
    "sg:address":"32 Water St",
    "sg:city":"Toowoomba",
    "sg:classifiers":[
        {
            "category":"Autos & Motor Vehicles",
            "subcategory":"Auto Supplies",
            "type":"Retail Goods"
        }
    ],
    "sg:phone":"+61 13 61 30",
    "sg:postcode":"4350",
    "sg:province":"QLD",
    "sg:tags":[
        "battery",
        "automotive"
    ],
    "wof:name":"Marshall Batteries",
    "wof:placetype":"venue"
},
  "geometry": {"coordinates":[151.949387,-27.566877],"type":"Point"}
}