{
  "type": "Feature",
  "properties": {
    "addr:full":"3 1 Outram Street, Level 3 West Perth WA 6005",
    "addr:housenumber":"1",
    "addr:postcode":"6005",
    "addr:street":"Outram Street",
    "iso:country":"AU",
    "sg:address":"3",
    "sg:city":"1 Outram Street, Level 3 West Perth",
    "sg:classifiers":[
        {
            "category":"Health Services",
            "subcategory":"Health Practitioner",
            "type":"Services"
        }
    ],
    "sg:phone":"+61 8 9481 0003",
    "sg:postcode":"6005",
    "sg:province":"WA",
    "sg:tags":[
        "physiotherapist"
    ],
    "wof:name":"Verity John",
    "wof:placetype":"venue"
},
  "geometry": {"coordinates":[115.83910369900001,-31.9495334625],"type":"Point"}
}