{
  "type": "Feature",
  "properties": {
    "addr:full":"9 Yarrabin Rd Kenthurst NSW 2156",
    "addr:housenumber":"9",
    "addr:postcode":"2156",
    "addr:street":"Yarrabin Rd",
    "iso:country":"AU",
    "sg:address":"9 Yarrabin Rd",
    "sg:city":"Kenthurst",
    "sg:classifiers":[
        {
            "category":"Retail",
            "subcategory":"Auto Rental",
            "type":"Services"
        }
    ],
    "sg:phone":"+61 2 9654 2776",
    "sg:postcode":"2156",
    "sg:province":"NSW",
    "sg:tags":[
        "chauffeur",
        "car",
        "hire",
        "driven",
        "limousine"
    ],
    "wof:name":"Elegant Journeys",
    "wof:placetype":"venue"
},
  "geometry": {"coordinates":[150.98973083499999,-33.6770629883],"type":"Point"}
}