{
  "type": "Feature",
  "properties": {
    "addr:full":"1 Castlereigh St Sydney NSW 2000",
    "addr:housenumber":"1",
    "addr:postcode":"2000",
    "addr:street":"Castlereigh St",
    "iso:country":"AU",
    "sg:address":"1 Castlereigh St",
    "sg:city":"Sydney",
    "sg:classifiers":[
        {
            "category":"Travel",
            "subcategory":"Travel Agent",
            "type":"Entertainment"
        }
    ],
    "sg:phone":"+61 1300 735 865",
    "sg:postcode":"2000",
    "sg:province":"NSW",
    "sg:tags":[
        "consultant"
    ],
    "wof:name":"Escape Travel",
    "wof:placetype":"venue"
},
  "geometry": {"coordinates":[151.20985412600001,-33.8663482666],"type":"Point"}
}