{
  "type": "Feature",
  "properties": {
    "addr:full":"70 Tiral St Charlestown NSW 2290",
    "addr:housenumber":"70",
    "addr:postcode":"2290",
    "addr:street":"Tiral St",
    "iso:country":"AU",
    "sg:address":"70 Tiral St",
    "sg:city":"Charlestown",
    "sg:classifiers":[
        {
            "category":"Building & Trades",
            "subcategory":"Construction",
            "type":"Services"
        }
    ],
    "sg:phone":"+61 408 689 199",
    "sg:postcode":"2290",
    "sg:province":"NSW",
    "sg:tags":[
        "contractor"
    ],
    "wof:name":"Bootland Building",
    "wof:placetype":"venue"
},
  "geometry": {"coordinates":[151.70248413100001,-32.9715423584],"type":"Point"}
}