{
  "type": "Feature",
  "properties": {
    "addr:full":"53 Windermere St Bundaberg QLD 4670",
    "addr:housenumber":"53",
    "addr:postcode":"4670",
    "addr:street":"Windermere St",
    "iso:country":"AU",
    "sg:address":"53 Windermere St",
    "sg:city":"Bundaberg",
    "sg:classifiers":[
        {
            "category":"Building & Trades",
            "subcategory":"Plumbing",
            "type":"Services"
        }
    ],
    "sg:phone":"+61 418 796 469",
    "sg:postcode":"4670",
    "sg:province":"QLD",
    "sg:tags":[
        "plumber",
        "gasfitters"
    ],
    "wof:name":"A J Read Plumbing",
    "wof:placetype":"venue"
},
  "geometry": {"coordinates":[152.358917236,-24.8749637604],"type":"Point"}
}