{
  "type": "Feature",
  "properties": {
    "addr:full":"1071 Wildwood Rd Yallingup WA 6282",
    "addr:housenumber":"1071",
    "addr:postcode":"6282",
    "addr:street":"Wildwood Rd",
    "iso:country":"AU",
    "sg:address":"1071 Wildwood Rd",
    "sg:city":"Yallingup",
    "sg:classifiers":[
        {
            "category":"Farming",
            "subcategory":"Vineyard",
            "type":"Manufacturing & Wholesale Goods"
        }
    ],
    "sg:phone":"+61 8 9755 2121",
    "sg:postcode":"6282",
    "sg:province":"WA",
    "sg:tags":[
        "winery"
    ],
    "wof:name":"The Growers Pty Ltd",
    "wof:placetype":"venue"
},
  "geometry": {"coordinates":[115.09342956499999,-33.698802948],"type":"Point"}
}