{
  "type": "Feature",
  "properties": {
    "addr:full":"2- 4 Leda Drv Loganholme QLD 4129",
    "addr:housenumber":"4",
    "addr:postcode":"4129",
    "addr:street":"Leda Drv",
    "iso:country":"AU",
    "sg:address":"2- 4 Leda Drv",
    "sg:city":"Loganholme",
    "sg:classifiers":[
        {
            "category":"Fast Food",
            "type":"Food & Drink"
        }
    ],
    "sg:phone":"+61 7 3801 4744",
    "sg:postcode":"4129",
    "sg:province":"QLD",
    "sg:tags":[
        "away",
        "take"
    ],
    "wof:name":"Red Rooster",
    "wof:placetype":"venue"
},
  "geometry": {"coordinates":[153.16903686500001,-27.6590747833],"type":"Point"}
}