{
  "type": "Feature",
  "properties": {
    "addr:full":"79 Oxford St Bondi Junction NSW 2022",
    "addr:housenumber":"79",
    "addr:postcode":"2022",
    "addr:street":"Oxford St",
    "iso:country":"AU",
    "sg:address":"79 Oxford St",
    "sg:city":"Bondi Junction",
    "sg:classifiers":[
        {
            "category":"Professional",
            "subcategory":"Accounting & Tax Preparation",
            "type":"Services"
        }
    ],
    "sg:phone":"+61 2 9369 5718",
    "sg:postcode":"2022",
    "sg:province":"NSW",
    "sg:tags":[
        "accountant",
        "auditor"
    ],
    "wof:name":"Conrick E T Chartered Accountant",
    "wof:placetype":"venue"
},
  "geometry": {"coordinates":[151.24615478499999,-33.8915214539],"type":"Point"}
}