{
  "type": "Feature",
  "properties": {
    "addr:full":"John Lund Drv Hope Island QLD 4212",
    "addr:postcode":"4212",
    "addr:street":"Lund Drv",
    "iso:country":"AU",
    "sg:address":"John Lund Drv",
    "sg:city":"Hope Island",
    "sg:classifiers":[
        {
            "category":"Autos & Motor Vehicles",
            "subcategory":"Boat Sales",
            "type":"Retail Goods"
        }
    ],
    "sg:phone":"+61 7 5530 1411",
    "sg:postcode":"4212",
    "sg:province":"QLD",
    "sg:tags":[
        "yacht"
    ],
    "wof:name":"Fish Marine Brokerage",
    "wof:placetype":"venue"
},
  "geometry": {"coordinates":[153.374389648,-27.8697471619],"type":"Point"}
}