{
  "type": "Feature",
  "properties": {
    "addr:full":"Shop 6 57- 63 Shore St Cleveland QLD 4163",
    "addr:housenumber":"shop;57 63",
    "addr:postcode":"4163",
    "addr:street":"Shore St",
    "iso:country":"AU",
    "sg:address":"Shop 6 57- 63 Shore St",
    "sg:city":"Cleveland",
    "sg:classifiers":[
        {
            "category":"Home & Garden",
            "subcategory":"Furniture",
            "type":"Retail Goods"
        }
    ],
    "sg:phone":"+61 7 3821 2188",
    "sg:postcode":"4163",
    "sg:province":"QLD",
    "sg:tags":[
        "repair",
        "restoration"
    ],
    "wof:name":"Bayside Quality Furniture Restorations",
    "wof:placetype":"venue"
},
  "geometry": {"coordinates":[153.25868225100001,-27.5244369507],"type":"Point"}
}