{
  "type": "Feature",
  "properties": {
    "addr:full":"15 Filmer St Clontarf QLD 4019",
    "addr:housenumber":"15",
    "addr:postcode":"4019",
    "addr:street":"Filmer St",
    "iso:country":"AU",
    "sg:address":"15 Filmer St",
    "sg:city":"Clontarf",
    "sg:classifiers":[
        {
            "category":"Retail",
            "subcategory":"Auto Repair",
            "type":"Services"
        }
    ],
    "sg:phone":"+61 7 3284 6508",
    "sg:postcode":"4019",
    "sg:province":"QLD",
    "sg:tags":[
        "repairer",
        "motor",
        "engineer"
    ],
    "wof:name":"B & W Mechanical",
    "wof:placetype":"venue"
},
  "geometry": {"coordinates":[153.083053589,-27.2346858978],"type":"Point"}
}