{
  "type": "Feature",
  "properties": {
    "addr:full":"67 Barry Ave Mortdale NSW 2223",
    "addr:housenumber":"67",
    "addr:postcode":"2223",
    "addr:street":"Barry Ave",
    "iso:country":"AU",
    "sg:address":"67 Barry Ave",
    "sg:city":"Mortdale",
    "sg:classifiers":[
        {
            "category":"Retail",
            "subcategory":"Car Wash",
            "type":"Services"
        }
    ],
    "sg:phone":"+61 2 9534 6844",
    "sg:postcode":"2223",
    "sg:province":"NSW",
    "sg:tags":[
        "wholesaler",
        "screw",
        "mfrs"
    ],
    "wof:name":"Industrial Fasteners Pty Ltd",
    "wof:placetype":"venue"
},
  "geometry": {"coordinates":[151.06692504899999,-33.9664840698],"type":"Point"}
}