{
  "type": "Feature",
  "properties": {
    "iso:country":"AU",
    "sg:address":"Suite 1, Level 5 80 Mount St",
    "sg:city":"North Sydney",
    "sg:classifiers":[
        {
            "category":"Professional",
            "subcategory":"Computer Services",
            "type":"Services"
        }
    ],
    "sg:phone":"+61 2 9922 6555",
    "sg:postcode":"2060",
    "sg:province":"NSW",
    "sg:tags":[
        "package",
        "software"
    ],
    "wof:name":"MRI (Management Reports International Pty Ltd) - An Intuit Company",
    "wof:placetype":"venue"
},
  "geometry": {"coordinates":[151.20817565900001,-33.8388671875],"type":"Point"}
}