{
  "type": "Feature",
  "properties": {
    "iso:country":"AU",
    "sg:address":"7 Warwick Farm Rd",
    "sg:city":"Olinda",
    "sg:classifiers":[
        {
            "category":"Real Estate",
            "subcategory":"Developer",
            "type":"Services"
        }
    ],
    "sg:phone":"+61 3 9755 2322",
    "sg:postcode":"3788",
    "sg:province":"VIC",
    "sg:tags":[
        "development"
    ],
    "wof:name":"Bokkar Nominees Pty Ltd",
    "wof:placetype":"venue"
},
  "geometry": {"coordinates":[145.366409,-37.866898],"type":"Point"}
}