{
  "type": "Feature",
  "properties": {
    "iso:country":"AU",
    "sg:address":"1 Scarborough Beach Rd",
    "sg:city":"North Perth",
    "sg:classifiers":[
        {
            "category":"Personal",
            "subcategory":"Beauty Salon",
            "type":"Services"
        }
    ],
    "sg:phone":"+61 8 9201 2911",
    "sg:postcode":"6006",
    "sg:province":"WA",
    "sg:tags":[
        "hairdresser"
    ],
    "wof:name":"Intercoiffer",
    "wof:placetype":"venue"
},
  "geometry": {"coordinates":[115.852020264,-31.9272632599],"type":"Point"}
}