{
  "type": "Feature",
  "properties": {
    "iso:country":"AU",
    "sg:address":"PO Box 4099 St",
    "sg:city":"Lucia South",
    "sg:classifiers":[
        {
            "category":"Professional",
            "subcategory":"Management & Consulting",
            "type":"Services"
        }
    ],
    "sg:phone":"+61 7 3876 1216",
    "sg:postcode":"4067",
    "sg:province":"QLD",
    "sg:tags":[
        "consultant",
        "relocation"
    ],
    "wof:name":"Relocations Australia",
    "wof:placetype":"venue"
},
  "geometry": {"coordinates":[153.00567626899999,-27.5024299622],"type":"Point"}
}