{
  "type": "Feature",
  "properties": {
    "addr:full":"Shop 29/30 The Hills Shopping Centre Seven Hills NSW 2147",
    "addr:housenumber":"shop 29 / 30",
    "addr:postcode":"2147",
    "addr:street":"The Hills",
    "iso:country":"AU",
    "sg:address":"Shop 29/30 The Hills Shopping Centre",
    "sg:city":"Seven Hills",
    "sg:classifiers":[
        {
            "category":"Shopping",
            "subcategory":"Clothing, Apparel, & Fashions",
            "type":"Retail Goods"
        }
    ],
    "sg:phone":"+61 2 9831 1684",
    "sg:postcode":"2147",
    "sg:province":"NSW",
    "sg:tags":[
        "lady",
        "wear"
    ],
    "wof:name":"Suzanne Grae",
    "wof:placetype":"venue"
},
  "geometry": {"coordinates":[150.933883667,-33.775970459],"type":"Point"}
}