{
  "type": "Feature",
  "properties": {
    "addr:full":"U 4/ 299 Brisbane Water Drv Gosford West NSW 2250",
    "addr:housenumber":"/ 299",
    "addr:postcode":"2250",
    "addr:street":"Brisbane Water Drv",
    "iso:country":"AU",
    "sg:address":"U 4/ 299 Brisbane Water Drv",
    "sg:city":"Gosford West",
    "sg:classifiers":[
        {
            "category":"Professional",
            "subcategory":"Accounting & Tax Preparation",
            "type":"Services"
        }
    ],
    "sg:phone":"+61 2 4323 1170",
    "sg:postcode":"2250",
    "sg:province":"NSW",
    "sg:tags":[
        "accountant",
        "auditor"
    ],
    "wof:name":"Susan Drew Taxtime Pty Ltd",
    "wof:placetype":"venue"
},
  "geometry": {"coordinates":[151.316696167,-33.4278297424],"type":"Point"}
}