{
  "type": "Feature",
  "properties": {
    "addr:full":"21 Crosbie Rd Murrumbeena VIC 3163",
    "addr:housenumber":"21",
    "addr:postcode":"3163",
    "addr:street":"Crosbie Rd",
    "iso:country":"AU",
    "sg:address":"21 Crosbie Rd",
    "sg:city":"Murrumbeena",
    "sg:classifiers":[
        {
            "category":"Social Services",
            "subcategory":"Retirement Home",
            "type":"Services"
        }
    ],
    "sg:phone":"+61 3 9570 7262",
    "sg:postcode":"3163",
    "sg:province":"VIC",
    "sg:tags":[
        "accommodation",
        "special"
    ],
    "wof:name":"Crosbie House S R S",
    "wof:placetype":"venue"
},
  "geometry": {"coordinates":[145.065872192,-37.9056854248],"type":"Point"}
}