{
  "type": "Feature",
  "properties": {
    "iso:country":"AU",
    "sg:address":"85 Enterprise St",
    "sg:city":"Kunda Park",
    "sg:classifiers":[
        {
            "category":"Autos & Motor Vehicles",
            "subcategory":"Automobile Sales",
            "type":"Retail Goods"
        }
    ],
    "sg:phone":"+61 7 5476 5833",
    "sg:postcode":"4556",
    "sg:province":"QLD",
    "sg:tags":[
        "equipment",
        "trailer"
    ],
    "wof:name":"Bushtracker Australia Pty Ltd",
    "wof:placetype":"venue"
},
  "geometry": {"coordinates":[153.02992248499999,-26.6669044495],"type":"Point"}
}