{
  "type": "Feature",
  "properties": {
    "addr:full":"Cnr Gymea Bay & Forest Rds Gymea Bay NSW 2227",
    "addr:postcode":"2227",
    "addr:street":"Cnr Gymea",
    "iso:country":"AU",
    "sg:address":"Cnr Gymea Bay & Forest Rds",
    "sg:city":"Gymea Bay",
    "sg:classifiers":[
        {
            "category":"Retail",
            "subcategory":"Auto Repair",
            "type":"Services"
        }
    ],
    "sg:phone":"+61 2 9524 7602",
    "sg:postcode":"2227",
    "sg:province":"NSW",
    "sg:tags":[
        "repairer",
        "motor",
        "engineer"
    ],
    "wof:name":"Auto Care (Shell)",
    "wof:placetype":"venue"
},
  "geometry": {"coordinates":[151.08357238799999,-34.0421791077],"type":"Point"}
}