{
  "type": "Feature",
  "properties": {
    "addr:full":"Shp 12, Pelican Plz Cnr Main North East & Golden Grove Rds Ridgehaven SA 5097",
    "addr:housenumber":"12",
    "addr:postcode":"5097",
    "addr:street":"Pelican Plz Cnr Main North East & Golden;Rds",
    "iso:country":"AU",
    "sg:address":"Shp 12, Pelican Plz Cnr Main North East & Golden Grove Rds",
    "sg:city":"Ridgehaven",
    "sg:classifiers":[
        {
            "category":"Retail",
            "subcategory":"Repair Shop",
            "type":"Services"
        }
    ],
    "sg:phone":"+61 8 8396 2999",
    "sg:postcode":"5097",
    "sg:province":"SA",
    "sg:tags":[
        "cleaner",
        "part",
        "vacuum"
    ],
    "wof:name":"Godfreys",
    "wof:placetype":"venue"
},
  "geometry": {"coordinates":[138.71014404300001,-34.8235282898],"type":"Point"}
}