{
  "type": "Feature",
  "properties": {
    "addr:full":"2148 Logan Rd Upper Mt Gravatt QLD 4122",
    "addr:housenumber":"2148",
    "addr:postcode":"4122",
    "addr:street":"Logan Rd Upper",
    "iso:country":"AU",
    "sg:address":"2148 Logan Rd",
    "sg:city":"Upper Mt Gravatt",
    "sg:classifiers":[
        {
            "category":"Travel",
            "subcategory":"Hotels & Motels",
            "type":"Entertainment"
        }
    ],
    "sg:phone":"+61 7 3343 3655",
    "sg:postcode":"4122",
    "sg:province":"QLD",
    "wof:name":"Garden City Motor Inn Upper Mt Gravatt",
    "wof:placetype":"venue"
},
  "geometry": {"coordinates":[153.08515930199999,-27.5623054504],"type":"Point"}
}