{
  "type": "Feature",
  "properties": {
    "addr:full":"15 Swadling Ave Glenlee QLD 4711",
    "addr:housenumber":"15",
    "addr:postcode":"4711",
    "addr:street":"Swadling Ave Glenlee",
    "iso:country":"AU",
    "sg:address":"15 Swadling Ave",
    "sg:city":"Glenlee",
    "sg:classifiers":[
        {
            "category":"Education",
            "subcategory":"Special Training",
            "type":"Public Place"
        }
    ],
    "sg:phone":"+61 7 4936 1824",
    "sg:postcode":"4711",
    "sg:province":"QLD",
    "sg:tags":[
        "development"
    ],
    "wof:name":"Fire Equipment & Training",
    "wof:placetype":"venue"
},
  "geometry": {"coordinates":[150.50071716299999,-23.2661991119],"type":"Point"}
}