{
  "type": "Feature",
  "properties": {
    "iso:country":"AU",
    "sg:address":"Level 7/ 35 York St",
    "sg:city":"Sydney",
    "sg:classifiers":[
        {
            "category":"Professional",
            "subcategory":"Management & Consulting",
            "type":"Services"
        }
    ],
    "sg:phone":"+61 2 9262 1336",
    "sg:postcode":"2000",
    "sg:province":"NSW",
    "sg:tags":[
        "consultant"
    ],
    "wof:name":"W.T. Australian Secretarial & Accounting Practice",
    "wof:placetype":"venue"
},
  "geometry": {"coordinates":[151.20567321799999,-33.8667373657],"type":"Point"}
}