{
  "type": "Feature",
  "properties": {
    "iso:country":"AU",
    "sg:address":"Clearendon on York Business Centre Office 7 / 68 - 72 York St",
    "sg:city":"South Melbourne",
    "sg:classifiers":[
        {
            "category":"Professional",
            "subcategory":"Business Services",
            "type":"Services"
        }
    ],
    "sg:phone":"+61 3 9674 0377",
    "sg:postcode":"3205",
    "sg:province":"VIC",
    "sg:tags":[
        "drafting"
    ],
    "wof:name":"A Australia Wide Contracting",
    "wof:placetype":"venue"
},
  "geometry": {"coordinates":[144.959885,-37.830547],"type":"Point"}
}