{
  "type": "Feature",
  "properties": {
    "addr:full":"342 Blackburn Rd Burwood East VIC 3151",
    "addr:housenumber":"342",
    "addr:postcode":"3151",
    "addr:street":"Blackburn Rd",
    "iso:country":"AU",
    "sg:address":"342 Blackburn Rd",
    "sg:city":"Burwood East",
    "sg:classifiers":[
        {
            "category":"Health Services",
            "subcategory":"Health Practitioner",
            "type":"Services"
        }
    ],
    "sg:phone":"+61 3 9802 9383",
    "sg:postcode":"3151",
    "sg:province":"VIC",
    "sg:tags":[
        "acupuncture"
    ],
    "wof:name":"Life Care Chinese Medicine",
    "wof:placetype":"venue"
},
  "geometry": {"coordinates":[145.15199279800001,-37.851474762],"type":"Point"}
}