{
  "type": "Feature",
  "properties": {
    "iso:country":"AU",
    "sg:address":"Yass Rd",
    "sg:city":"Cootamundra",
    "sg:classifiers":[
        {
            "category":"Farming",
            "subcategory":"Vineyard",
            "type":"Manufacturing & Wholesale Goods"
        }
    ],
    "sg:phone":"+61 2 6942 2784",
    "sg:postcode":"2590",
    "sg:province":"NSW",
    "sg:tags":[
        "saleyards"
    ],
    "wof:name":"Municipal Saleyards",
    "wof:placetype":"venue"
},
  "geometry": {"coordinates":[148.02609252900001,-34.6400413513],"type":"Point"}
}