{
  "type": "Feature",
  "properties": {
    "iso:country":"AU",
    "sg:address":"12- 15 Bass Hwy",
    "sg:city":"Round Hill",
    "sg:classifiers":[
        {
            "category":"Commercial Area",
            "type":"Public Place"
        }
    ],
    "sg:phone":"+61 3 6431 9233",
    "sg:postcode":"7320",
    "sg:province":"TAS",
    "sg:tags":[
        "heavy",
        "carrier"
    ],
    "wof:name":"Holloway L.G. Quarries And Transport Pty Ltd",
    "wof:placetype":"venue"
},
  "geometry": {"coordinates":[145.94892899999999,-41.066517],"type":"Point"}
}