{
  "type": "Feature",
  "properties": {
    "addr:full":"1 Moreland Rd Essendon VIC 3040",
    "addr:housenumber":"1",
    "addr:postcode":"3040",
    "addr:street":"Moreland Rd",
    "iso:country":"AU",
    "sg:address":"1 Moreland Rd",
    "sg:city":"Essendon",
    "sg:classifiers":[
        {
            "category":"Social Services",
            "subcategory":"Retirement Home",
            "type":"Services"
        }
    ],
    "sg:phone":"+61 3 9370 4511",
    "sg:postcode":"3040",
    "sg:province":"VIC",
    "sg:tags":[
        "village"
    ],
    "wof:name":"Lionsville Incorporated",
    "wof:placetype":"venue"
},
  "geometry": {"coordinates":[144.92658996599999,-37.7508773804],"type":"Point"}
}