{
  "type": "Feature",
  "properties": {
    "addr:full":"8 Hospital Rd Bulli NSW 2516",
    "addr:housenumber":"8",
    "addr:postcode":"2516",
    "addr:street":"Hospital Rd",
    "iso:country":"AU",
    "sg:address":"8 Hospital Rd",
    "sg:city":"Bulli",
    "sg:classifiers":[
        {
            "category":"Organizations",
            "subcategory":"Community Association",
            "type":"Services"
        }
    ],
    "sg:phone":"+61 2 4285 4888",
    "sg:postcode":"2516",
    "sg:province":"NSW",
    "sg:tags":[
        "club",
        "senior",
        "citizen"
    ],
    "wof:name":"Bulli Senior Citizens Centre",
    "wof:placetype":"venue"
},
  "geometry": {"coordinates":[150.90982099999999,-34.336681],"type":"Point"}
}