{
  "type": "Feature",
  "properties": {
    "addr:full":"142 Howes Crs Dianella WA 6059",
    "addr:housenumber":"142",
    "addr:postcode":"6059",
    "addr:street":"Howes Crs",
    "iso:country":"AU",
    "sg:address":"142 Howes Crs",
    "sg:city":"Dianella",
    "sg:classifiers":[
        {
            "category":"Professional",
            "subcategory":"Art Services",
            "type":"Services"
        }
    ],
    "sg:phone":"+61 8 9375 7771",
    "sg:postcode":"6059",
    "sg:province":"WA",
    "sg:tags":[
        "decorator",
        "painter"
    ],
    "wof:name":"Bryan Cooper Painters",
    "wof:placetype":"venue"
},
  "geometry": {"coordinates":[115.871528626,-31.8887805939],"type":"Point"}
}