{
  "type": "Feature",
  "properties": {
    "addr:full":"1 Fishermans Wharf Rd Geraldton WA 6530",
    "addr:housenumber":"1",
    "addr:postcode":"6530",
    "addr:street":"Fishermans Wharf Rd",
    "iso:country":"AU",
    "sg:address":"1 Fishermans Wharf Rd",
    "sg:city":"Geraldton",
    "sg:classifiers":[
        {
            "category":"Wholesale",
            "subcategory":"Metals & Minerals",
            "type":"Manufacturing & Wholesale Goods"
        }
    ],
    "sg:phone":"+61 8 9964 3642",
    "sg:postcode":"6530",
    "sg:province":"WA",
    "sg:tags":[
        "steel",
        "stainless",
        "product",
        "equipment"
    ],
    "wof:name":"Max Marine",
    "wof:placetype":"venue"
},
  "geometry": {"coordinates":[114.64060974100001,-28.7494506836],"type":"Point"}
}