{
  "type": "Feature",
  "properties": {
    "iso:country":"AU",
    "sg:address":"97 Yarra St",
    "sg:city":"Geelong",
    "sg:classifiers":[
        {
            "category":"Banks & Credit Unions",
            "subcategory":"Bureau De Change",
            "type":"Services"
        }
    ],
    "sg:phone":"+61 3 5224 2269",
    "sg:postcode":"3220",
    "sg:province":"VIC",
    "sg:tags":[
        "reporting"
    ],
    "wof:name":"Prushka Fast Credit Reports",
    "wof:placetype":"venue"
},
  "geometry": {"coordinates":[144.36218299999999,-38.150681],"type":"Point"}
}