{
  "type": "Feature",
  "properties": {
    "addr:full":"Level 1 9 Harper St Abbotsford VIC 3067",
    "addr:housenumber":"9",
    "addr:postcode":"3067",
    "addr:street":"Harper St",
    "iso:country":"AU",
    "sg:address":"Level 1 9 Harper St",
    "sg:city":"Abbotsford",
    "sg:classifiers":[
        {
            "category":"Shopping",
            "subcategory":"Computers & Home Electronics",
            "type":"Retail Goods"
        }
    ],
    "sg:phone":"+61 3 9251 3111",
    "sg:postcode":"3067",
    "sg:province":"VIC",
    "sg:tags":[
        "hardware",
        "equipment"
    ],
    "wof:name":"Computer Hardware of Australia Pty Ltd",
    "wof:placetype":"venue"
},
  "geometry": {"coordinates":[144.99801635700001,-37.8040161133],"type":"Point"}
}