{
  "type": "Feature",
  "properties": {
    "iso:country":"AU",
    "sg:address":"345 Windsor St",
    "sg:city":"Richmond",
    "sg:classifiers":[
        {
            "category":"Health Services",
            "subcategory":"Chiropractor",
            "type":"Services"
        }
    ],
    "sg:phone":"+61 2 4578 2348",
    "sg:postcode":"2753",
    "sg:province":"NSW",
    "wof:name":"Lyell Anne, Lyell Andrew & Mison Matthew",
    "wof:placetype":"venue"
},
  "geometry": {"coordinates":[150.742874145,-33.5929107666],"type":"Point"}
}