{
  "type": "Feature",
  "properties": {
    "addr:full":"13 Herbert St Goondiwindi QLD 4390",
    "addr:housenumber":"13",
    "addr:postcode":"4390",
    "addr:street":"Herbert St",
    "iso:country":"AU",
    "sg:address":"13 Herbert St",
    "sg:city":"Goondiwindi",
    "sg:classifiers":[
        {
            "category":"Communications",
            "subcategory":"Film & Video Production",
            "type":"Services"
        }
    ],
    "sg:phone":"+61 7 4671 5262",
    "sg:postcode":"4390",
    "sg:province":"QLD",
    "sg:tags":[
        "dvd",
        "library"
    ],
    "wof:name":"Video Ezy",
    "wof:placetype":"venue"
},
  "geometry": {"coordinates":[150.30523681599999,-28.5457134247],"type":"Point"}
}