{
  "type": "Feature",
  "properties": {
    "addr:full":"Main St Tarampa QLD 4311",
    "addr:postcode":"4311",
    "addr:street":"Main St",
    "iso:country":"AU",
    "sg:address":"Main St",
    "sg:city":"Tarampa",
    "sg:classifiers":[
        {
            "category":"Autos & Motor Vehicles",
            "subcategory":"Fuel & Gas Station",
            "type":"Retail Goods"
        }
    ],
    "sg:phone":"+61 7 5426 1399",
    "sg:postcode":"4311",
    "sg:province":"QLD",
    "wof:name":"BP Australia Limited",
    "wof:placetype":"venue"
},
  "geometry": {"coordinates":[152.57882690400001,-27.4731216431],"type":"Point"}
}