{
  "type": "Feature",
  "properties": {
    "addr:full":"PO Box 7094 Wattle Park VIC 3128",
    "addr:postcode":"3128",
    "iso:country":"AU",
    "sg:address":"PO Box 7094",
    "sg:city":"Wattle Park",
    "sg:classifiers":[
        {
            "category":"Bars & Pubs",
            "subcategory":"Nightclub",
            "type":"Food & Drink"
        }
    ],
    "sg:phone":"+61 3 9898 0044",
    "sg:postcode":"3128",
    "sg:province":"VIC",
    "sg:tags":[
        "karaoke"
    ],
    "wof:name":"Mworx",
    "wof:placetype":"venue"
},
  "geometry": {"coordinates":[145.11491394000001,-37.8409805298],"type":"Point"}
}