{
  "type": "Feature",
  "properties": {
    "addr:full":"1st Floor 163 Lambton Rd Broadmeadow NSW 2292",
    "addr:housenumber":"163",
    "addr:postcode":"2292",
    "addr:street":"Lambton Rd",
    "iso:country":"AU",
    "sg:address":"1st Floor 163 Lambton Rd",
    "sg:city":"Broadmeadow",
    "sg:classifiers":[
        {
            "category":"Building & Trades",
            "subcategory":"Construction",
            "type":"Services"
        }
    ],
    "sg:phone":"+61 2 4965 5956",
    "sg:postcode":"2292",
    "sg:province":"NSW",
    "sg:tags":[
        "contractor"
    ],
    "wof:name":"Newcastle Quality Constructions Pty Ltd",
    "wof:placetype":"venue"
},
  "geometry": {"coordinates":[151.722946167,-32.923374176],"type":"Point"}
}