{
  "type": "Feature",
  "properties": {
    "addr:full":"Orrong Rd Kewdale WA 6105",
    "addr:postcode":"6105",
    "addr:street":"Orrong Rd",
    "iso:country":"AU",
    "sg:address":"Orrong Rd",
    "sg:city":"Kewdale",
    "sg:classifiers":[
        {
            "category":"Education",
            "subcategory":"School",
            "type":"Public Place"
        }
    ],
    "sg:phone":"+61 8 9470 1321",
    "sg:postcode":"6105",
    "sg:province":"WA",
    "sg:tags":[
        "state",
        "except",
        "nsw"
    ],
    "wof:name":"Carlisle Pre-Primary School-2",
    "wof:placetype":"venue"
},
  "geometry": {"coordinates":[115.92640686,-31.9781665802],"type":"Point"}
}