{
  "type": "Feature",
  "properties": {
    "addr:full":"Unit 2/ 109 Riverside Pl Morningside QLD 4170",
    "addr:housenumber":"/ 109",
    "addr:postcode":"4170",
    "addr:street":"Riverside Pl",
    "iso:country":"AU",
    "sg:address":"Unit 2/ 109 Riverside Pl",
    "sg:city":"Morningside",
    "sg:classifiers":[
        {
            "category":"Social Services",
            "subcategory":"Retirement Home",
            "type":"Services"
        }
    ],
    "sg:phone":"+61 7 3899 2311",
    "sg:postcode":"4170",
    "sg:province":"QLD",
    "sg:tags":[
        "environmental",
        "consultant",
        "pollution"
    ],
    "wof:name":"Leeder Consulting Pty Ltd",
    "wof:placetype":"venue"
},
  "geometry": {"coordinates":[153.08076477,-27.4499397278],"type":"Point"}
}