{
  "type": "Feature",
  "properties": {
    "addr:full":"PO Box 259236 Loganholme QLD 4129",
    "addr:postcode":"4129",
    "iso:country":"AU",
    "sg:address":"PO Box 259236",
    "sg:city":"Loganholme",
    "sg:classifiers":[
        {
            "category":"Arena",
            "subcategory":"Sports Club",
            "type":"Entertainment"
        }
    ],
    "sg:phone":"+61 431 056 423",
    "sg:postcode":"4129",
    "sg:province":"QLD",
    "sg:tags":[
        "defence",
        "supply",
        "self",
        "instruction",
        "martial art"
    ],
    "wof:name":"Wing Chun Kung Fu",
    "wof:placetype":"venue"
},
  "geometry": {"coordinates":[153.185791016,-27.6725502014],"type":"Point"}
}