{
  "type": "Feature",
  "properties": {
    "iso:country":"AU",
    "sg:address":"76a Hermitage Rd",
    "sg:city":"West Ryde",
    "sg:classifiers":[
        {
            "category":"Building & Trades",
            "subcategory":"Construction",
            "type":"Services"
        }
    ],
    "sg:phone":"+61 2 9809 5214",
    "sg:postcode":"2114",
    "sg:province":"NSW",
    "sg:tags":[
        "window",
        "aluminium"
    ],
    "wof:name":"The Joinery Company Pty Ltd",
    "wof:placetype":"venue"
},
  "geometry": {"coordinates":[151.09248352,-33.809803009],"type":"Point"}
}