{
  "type": "Feature",
  "properties": {
    "iso:country":"AU",
    "sg:address":"Level 1, 83- 85 Foveaux St",
    "sg:city":"Surry Hills",
    "sg:classifiers":[
        {
            "category":"Professional",
            "subcategory":"Business Services",
            "type":"Services"
        }
    ],
    "sg:phone":"+61 2 9211 3666",
    "sg:postcode":"2010",
    "sg:province":"NSW",
    "sg:tags":[
        "fashion",
        "agent"
    ],
    "wof:name":"Lappin Philip Agencies",
    "wof:placetype":"venue"
},
  "geometry": {"coordinates":[151.21116638199999,-33.8846931458],"type":"Point"}
}