{
  "type": "Feature",
  "properties": {
    "addr:full":"21 Murray Valley Hwy Echuca VIC 3564",
    "addr:housenumber":"21",
    "addr:postcode":"3564",
    "addr:street":"Murray Valley Hwy",
    "iso:country":"AU",
    "sg:address":"21 Murray Valley Hwy",
    "sg:city":"Echuca",
    "sg:classifiers":[
        {
            "category":"Retail",
            "subcategory":"Auto Repair",
            "type":"Services"
        }
    ],
    "sg:phone":"+61 3 5482 6309",
    "sg:postcode":"3564",
    "sg:province":"VIC",
    "sg:tags":[
        "electrical"
    ],
    "wof:name":"Westside Auto Electrics",
    "wof:placetype":"venue"
},
  "geometry": {"coordinates":[144.75157165499999,-36.140499115],"type":"Point"}
}