{
  "type": "Feature",
  "properties": {
    "iso:country":"AU",
    "sg:address":"76a Main St",
    "sg:city":"Penguin",
    "sg:classifiers":[
        {
            "category":"Fast Food",
            "type":"Food & Drink"
        }
    ],
    "sg:phone":"+61 3 6437 2265",
    "sg:postcode":"7316",
    "sg:province":"TAS",
    "sg:tags":[
        "away",
        "take"
    ],
    "wof:name":"Penguin Food Bar",
    "wof:placetype":"venue"
},
  "geometry": {"coordinates":[146.072341919,-41.113483429],"type":"Point"}
}