{
  "type": "Feature",
  "properties": {
    "addr:full":"14 Bell St Yarra Glen VIC 3775",
    "addr:housenumber":"14",
    "addr:postcode":"3775",
    "addr:street":"Bell St",
    "iso:country":"AU",
    "sg:address":"14 Bell St",
    "sg:city":"Yarra Glen",
    "sg:classifiers":[
        {
            "category":"Food & Beverages",
            "subcategory":"Groceries & Convenience Stores",
            "type":"Retail Goods"
        }
    ],
    "sg:phone":"+61 3 9730 1908",
    "sg:postcode":"3775",
    "sg:province":"VIC",
    "wof:name":"Yarra Flats General Store",
    "wof:placetype":"venue"
},
  "geometry": {"coordinates":[145.374863,-37.658909],"type":"Point"}
}