{
  "type": "Feature",
  "properties": {
    "addr:full":"34 Olive St Fairfield NSW 2165",
    "addr:housenumber":"34",
    "addr:postcode":"2165",
    "addr:street":"Olive St",
    "iso:country":"AU",
    "sg:address":"34 Olive St",
    "sg:city":"Fairfield",
    "sg:classifiers":[
        {
            "category":"Home & Garden",
            "subcategory":"Building Materials",
            "type":"Retail Goods"
        }
    ],
    "sg:phone":"+61 414 640 631",
    "sg:postcode":"2165",
    "sg:province":"NSW",
    "sg:tags":[
        "lawn",
        "cutting",
        "maintenance"
    ],
    "wof:name":"Taty's Lawnmowing Service",
    "wof:placetype":"venue"
},
  "geometry": {"coordinates":[150.95057678200001,-33.8772583008],"type":"Point"}
}