{
  "type": "Feature",
  "properties": {
    "addr:full":"33 Vine St Hurstville NSW 2220",
    "addr:housenumber":"33",
    "addr:postcode":"2220",
    "addr:street":"Vine St",
    "iso:country":"AU",
    "sg:address":"33 Vine St",
    "sg:city":"Hurstville",
    "sg:classifiers":[
        {
            "category":"Social Services",
            "subcategory":"Child Care",
            "type":"Services"
        }
    ],
    "sg:phone":"+61 2 9553 6006",
    "sg:postcode":"2220",
    "sg:province":"NSW",
    "wof:name":"Teddy Bear Early Learning Centre",
    "wof:placetype":"venue"
},
  "geometry": {"coordinates":[151.10867309599999,-33.9616470337],"type":"Point"}
}