{
  "type": "Feature",
  "properties": {
    "addr:full":"Lot 46 Patriarch Drv Huntingfield TAS 7055",
    "addr:postcode":"7055",
    "addr:street":"Patriarch Drv",
    "iso:country":"AU",
    "sg:address":"Lot 46 Patriarch Drv",
    "sg:city":"Huntingfield",
    "sg:classifiers":[
        {
            "category":"Retail",
            "subcategory":"Storage",
            "type":"Services"
        }
    ],
    "sg:phone":"+61 407 728 720",
    "sg:postcode":"7055",
    "sg:province":"TAS",
    "wof:name":"Extra-Space Storage",
    "wof:placetype":"venue"
},
  "geometry": {"coordinates":[147.29115300000001,-42.993111],"type":"Point"}
}