{
  "type": "Feature",
  "properties": {
    "addr:full":"Ste48/ 98 Railway Pde West Perth WA 6005",
    "addr:housenumber":"98",
    "addr:postcode":"6005",
    "addr:street":"Railway Pde",
    "iso:country":"AU",
    "sg:address":"Ste48/ 98 Railway Pde",
    "sg:city":"West Perth",
    "sg:classifiers":[
        {
            "category":"Professional",
            "subcategory":"Business Services",
            "type":"Services"
        }
    ],
    "sg:phone":"+61 8 9486 8877",
    "sg:postcode":"6005",
    "sg:province":"WA",
    "sg:tags":[
        "fashion",
        "agent"
    ],
    "wof:name":"Mick Ryan Fashion Agents",
    "wof:placetype":"venue"
},
  "geometry": {"coordinates":[115.841667175,-31.943271637],"type":"Point"}
}