{
  "type": "Feature",
  "properties": {
    "addr:full":"123 Fifth Ave Royston Park SA 5070",
    "addr:housenumber":"123",
    "addr:postcode":"5070",
    "addr:street":"Fifth Ave Royston",
    "iso:country":"AU",
    "sg:address":"123 Fifth Ave",
    "sg:city":"Royston Park",
    "sg:classifiers":[
        {
            "category":"Professional",
            "subcategory":"Accounting & Tax Preparation",
            "type":"Services"
        }
    ],
    "sg:phone":"+61 8 8132 0250",
    "sg:postcode":"5070",
    "sg:province":"SA",
    "sg:tags":[
        "bookkeeping"
    ],
    "wof:name":"B.S.A. Business Services",
    "wof:placetype":"venue"
},
  "geometry": {"coordinates":[138.630935669,-34.8972625732],"type":"Point"}
}