{
  "type": "Feature",
  "properties": {
    "addr:full":"61 Michael St Fitzroy North VIC 3068",
    "addr:housenumber":"61",
    "addr:postcode":"3068",
    "addr:street":"Michael St",
    "iso:country":"AU",
    "sg:address":"61 Michael St",
    "sg:city":"Fitzroy North",
    "sg:classifiers":[
        {
            "category":"Cinema",
            "subcategory":"Movie Theater",
            "type":"Entertainment"
        }
    ],
    "sg:phone":"+61 3 9481 2626",
    "sg:postcode":"3068",
    "sg:province":"VIC",
    "wof:name":"Soul Theatre Inc",
    "wof:placetype":"venue"
},
  "geometry": {"coordinates":[144.98928832999999,-37.78647995],"type":"Point"}
}