{
  "type": "Feature",
  "properties": {
    "addr:full":"323 Keira St Wollongong NSW 2500",
    "addr:housenumber":"323",
    "addr:postcode":"2500",
    "addr:street":"Keira St",
    "iso:country":"AU",
    "sg:address":"323 Keira St",
    "sg:city":"Wollongong",
    "sg:classifiers":[
        {
            "category":"Organizations",
            "subcategory":"Membership Organization",
            "type":"Services"
        }
    ],
    "sg:phone":"+61 2 4253 5566",
    "sg:postcode":"2500",
    "sg:province":"NSW",
    "sg:tags":[
        "equipment",
        "inter-communication",
        "system"
    ],
    "wof:name":"N.E.C. Telephone Systems",
    "wof:placetype":"venue"
},
  "geometry": {"coordinates":[150.89259300000001,-34.432133],"type":"Point"}
}