{
  "type": "Feature",
  "properties": {
    "addr:full":"PO Box 421 Jindabyne NSW 2627",
    "addr:postcode":"2627",
    "iso:country":"AU",
    "sg:address":"PO Box 421",
    "sg:city":"Jindabyne",
    "sg:classifiers":[
        {
            "category":"Building & Trades",
            "subcategory":"Cleaning & Sanitation",
            "type":"Services"
        }
    ],
    "sg:phone":"+61 2 6457 2337",
    "sg:postcode":"2627",
    "sg:province":"NSW",
    "sg:tags":[
        "industrial",
        "commercial",
        "contractor"
    ],
    "wof:name":"Mountain Maid Cleaning",
    "wof:placetype":"venue"
},
  "geometry": {"coordinates":[148.60859680199999,-36.4327316284],"type":"Point"}
}