{
  "type": "Feature",
  "properties": {
    "addr:full":"121 Royal St East Perth WA 6004",
    "addr:housenumber":"121",
    "addr:postcode":"6004",
    "addr:street":"Royal St East",
    "iso:country":"AU",
    "sg:address":"121 Royal St",
    "sg:city":"East Perth",
    "sg:classifiers":[
        {
            "category":"Organizations",
            "subcategory":"Labor Organization",
            "type":"Services"
        }
    ],
    "sg:phone":"+61 8 9223 0800",
    "sg:postcode":"6004",
    "sg:province":"WA",
    "sg:tags":[
        "union"
    ],
    "wof:name":"Australian Manufacturing Workers Union",
    "wof:placetype":"venue"
},
  "geometry": {"coordinates":[115.874740601,-31.9529151917],"type":"Point"}
}