{
  "type": "Feature",
  "properties": {
    "addr:full":"Great Sandy Straights Marina Buccaneer Ave Urangan QLD 4655",
    "addr:postcode":"4655",
    "addr:street":"Great;Buccaneer Ave",
    "iso:country":"AU",
    "sg:address":"Great Sandy Straights Marina Buccaneer Ave",
    "sg:city":"Urangan",
    "sg:classifiers":[
        {
            "category":"Recreation",
            "subcategory":"Boat Charter",
            "type":"Entertainment"
        }
    ],
    "sg:phone":"+61 7 4124 9540",
    "sg:postcode":"4655",
    "sg:province":"QLD",
    "wof:name":"Arthur Mackie",
    "wof:placetype":"venue"
},
  "geometry": {"coordinates":[152.908646,-25.293362],"type":"Point"}
}