{
  "type": "Feature",
  "properties": {
    "iso:country":"AU",
    "sg:address":"98 King St",
    "sg:city":"Newcastle",
    "sg:classifiers":[
        {
            "category":"Health Services",
            "subcategory":"Health Practitioner",
            "type":"Services"
        }
    ],
    "sg:phone":"+61 2 4926 1318",
    "sg:postcode":"2300",
    "sg:province":"NSW",
    "sg:tags":[
        "osteopath"
    ],
    "wof:name":"Kylie Read",
    "wof:placetype":"venue"
},
  "geometry": {"coordinates":[151.780167,-32.927704],"type":"Point"}
}