{
  "type": "Feature",
  "properties": {
    "addr:full":"578 Waverley Rd Glen Waverley VIC 3150",
    "addr:housenumber":"578",
    "addr:postcode":"3150",
    "addr:street":"Waverley Rd",
    "iso:country":"AU",
    "sg:address":"578 Waverley Rd",
    "sg:city":"Glen Waverley",
    "sg:classifiers":[
        {
            "category":"Professional",
            "subcategory":"Business Services",
            "type":"Services"
        }
    ],
    "sg:phone":"+61 3 9802 2514",
    "sg:postcode":"3150",
    "sg:province":"VIC",
    "sg:tags":[
        "drafting"
    ],
    "wof:name":"Griggs R D",
    "wof:placetype":"venue"
},
  "geometry": {"coordinates":[145.149124145,-37.8872489929],"type":"Point"}
}