{
  "type": "Feature",
  "properties": {
    "addr:full":"5b Claremont St South Yarra VIC 3141",
    "addr:housenumber":"5b",
    "addr:postcode":"3141",
    "addr:street":"Claremont St",
    "iso:country":"AU",
    "sg:address":"5b Claremont St",
    "sg:city":"South Yarra",
    "sg:classifiers":[
        {
            "category":"Professional",
            "subcategory":"Computer Services",
            "type":"Services"
        }
    ],
    "sg:phone":"+61 3 9415 8477",
    "sg:postcode":"3141",
    "sg:province":"VIC",
    "sg:tags":[
        "package",
        "software"
    ],
    "wof:name":"X.I Consulting Group",
    "wof:placetype":"venue"
},
  "geometry": {"coordinates":[144.99351501500001,-37.8384437561],"type":"Point"}
}