{
  "type": "Feature",
  "properties": {
    "iso:country":"AU",
    "sg:address":"7 The Hermitate Lake Rd",
    "sg:city":"Port Macquarie",
    "sg:classifiers":[
        {
            "category":"Health Services",
            "subcategory":"Health Practitioner",
            "type":"Services"
        }
    ],
    "sg:phone":"+61 2 6583 4243",
    "sg:postcode":"2444",
    "sg:province":"NSW",
    "sg:tags":[
        "physiotherapist"
    ],
    "wof:name":"Hastings Sports Injury & Physiotherapy Centre",
    "wof:placetype":"venue"
},
  "geometry": {"coordinates":[152.911469,-31.434656],"type":"Point"}
}