{
  "type": "Feature",
  "properties": {
    "addr:full":"William Murray Drv Airlie Beach QLD 4802",
    "addr:postcode":"4802",
    "addr:street":"Murray Drv",
    "iso:country":"AU",
    "sg:address":"William Murray Drv",
    "sg:city":"Airlie Beach",
    "sg:classifiers":[
        {
            "category":"Professional",
            "subcategory":"Testing Lab",
            "type":"Services"
        }
    ],
    "sg:phone":"+61 7 4946 7566",
    "sg:postcode":"4802",
    "sg:province":"QLD",
    "sg:tags":[
        "inspection"
    ],
    "wof:name":"Roadtest",
    "wof:placetype":"venue"
},
  "geometry": {"coordinates":[148.68153381400001,-20.2840118408],"type":"Point"}
}