{
  "type": "Feature",
  "properties": {
    "iso:country":"AU",
    "sg:address":"PO Box 439",
    "sg:city":"Newport Beach",
    "sg:classifiers":[
        {
            "category":"Utilities",
            "subcategory":"Electric",
            "type":"Services"
        }
    ],
    "sg:phone":"+61 1300 856 465",
    "sg:postcode":"2106",
    "sg:province":"NSW",
    "sg:tags":[
        "electrical",
        "contractor"
    ],
    "wof:name":"Synergy Intergrated Systems Pty Ltd",
    "wof:placetype":"venue"
},
  "geometry": {"coordinates":[151.32278442399999,-33.6524810791],"type":"Point"}
}