{
  "type": "Feature",
  "properties": {
    "addr:full":"Shop 3-4/ 6-10 Kippax St Greystanes NSW 2145",
    "addr:housenumber":"shop 3-4 / 6-10",
    "addr:postcode":"2145",
    "addr:street":"Kippax St",
    "iso:country":"AU",
    "sg:address":"Shop 3-4/ 6-10 Kippax St",
    "sg:city":"Greystanes",
    "sg:classifiers":[
        {
            "category":"Home & Garden",
            "subcategory":"Home Furnishings",
            "type":"Retail Goods"
        }
    ],
    "sg:phone":"+61 2 9636 2352",
    "sg:postcode":"2145",
    "sg:province":"NSW",
    "sg:tags":[
        "candle"
    ],
    "wof:name":"Whiff The Scented Candle Experience",
    "wof:placetype":"venue"
},
  "geometry": {"coordinates":[150.938156128,-33.8276023865],"type":"Point"}
}