{
  "type": "Feature",
  "properties": {
    "addr:full":"Welsford St Shepparton VIC 3630",
    "addr:postcode":"3630",
    "addr:street":"Welsford St",
    "iso:country":"AU",
    "sg:address":"Welsford St",
    "sg:city":"Shepparton",
    "sg:classifiers":[
        {
            "category":"Organizations",
            "subcategory":"Community Association",
            "type":"Services"
        }
    ],
    "sg:phone":"+61 3 5821 4384",
    "sg:postcode":"3630",
    "sg:province":"VIC",
    "sg:tags":[
        "club",
        "senior",
        "citizen"
    ],
    "wof:name":"Shepparton Senior Citizens Centre",
    "wof:placetype":"venue"
},
  "geometry": {"coordinates":[145.39691162099999,-36.3854064941],"type":"Point"}
}