{
  "type": "Feature",
  "properties": {
    "addr:full":"5 Van Moolenbroeks Rd Pleystowe QLD 4741",
    "addr:housenumber":"5",
    "addr:postcode":"4741",
    "addr:street":"Van Moolenbroeks Rd",
    "iso:country":"AU",
    "sg:address":"5 Van Moolenbroeks Rd",
    "sg:city":"Pleystowe",
    "sg:classifiers":[
        {
            "category":"Mining & Drilling",
            "type":"Manufacturing & Wholesale Goods"
        }
    ],
    "sg:phone":"+61 7 4954 0760",
    "sg:postcode":"4741",
    "sg:province":"QLD",
    "sg:tags":[
        "boring",
        "contractor"
    ],
    "wof:name":"Mackay Directional Boring",
    "wof:placetype":"venue"
},
  "geometry": {"coordinates":[149.02598599999999,-21.143169],"type":"Point"}
}