{
  "type": "Feature",
  "properties": {
    "iso:country":"AU",
    "sg:address":"Suite4/ 1298 Hay St",
    "sg:city":"Perth",
    "sg:classifiers":[
        {
            "category":"Professional",
            "subcategory":"Computer Services",
            "type":"Services"
        }
    ],
    "sg:phone":"+61 8 9322 7881",
    "sg:postcode":"6000",
    "sg:province":"WA",
    "sg:tags":[
        "package",
        "software"
    ],
    "wof:name":"Epiction Pty Ltd",
    "wof:placetype":"venue"
},
  "geometry": {"coordinates":[115.839546204,-31.9477119446],"type":"Point"}
}