{
  "type": "Feature",
  "properties": {
    "iso:country":"AU",
    "sg:address":"Pacific Hwy",
    "sg:city":"Burringbar",
    "sg:classifiers":[
        {
            "category":"Autos & Motor Vehicles",
            "subcategory":"Fuel & Gas Station",
            "type":"Retail Goods"
        }
    ],
    "sg:phone":"+61 2 6677 1474",
    "sg:postcode":"2483",
    "sg:province":"NSW",
    "wof:name":"Burringbar Service Station",
    "wof:placetype":"venue"
},
  "geometry": {"coordinates":[153.50279235799999,-28.4427337646],"type":"Point"}
}