{
  "type": "Feature",
  "properties": {
    "iso:country":"AU",
    "sg:address":"127 Duke Rd",
    "sg:city":"Doonan",
    "sg:classifiers":[
        {
            "category":"Real Estate",
            "subcategory":"Architect",
            "type":"Services"
        }
    ],
    "sg:phone":"+61 7 5471 0455",
    "sg:postcode":"4562",
    "sg:province":"QLD",
    "wof:name":"Robinson Architects",
    "wof:placetype":"venue"
},
  "geometry": {"coordinates":[152.999237061,-26.4526786804],"type":"Point"}
}