{
  "type": "Feature",
  "properties": {
    "addr:full":"81 Glenvale Rd Donvale VIC 3111",
    "addr:housenumber":"81",
    "addr:postcode":"3111",
    "addr:street":"Glenvale Rd",
    "iso:country":"AU",
    "sg:address":"81 Glenvale Rd",
    "sg:city":"Donvale",
    "sg:classifiers":[
        {
            "category":"Utilities",
            "subcategory":"Electric",
            "type":"Services"
        }
    ],
    "sg:phone":"+61 414 480 836",
    "sg:postcode":"3111",
    "sg:province":"VIC",
    "sg:tags":[
        "electrical",
        "contractor"
    ],
    "wof:name":"Plumridge P E",
    "wof:placetype":"venue"
},
  "geometry": {"coordinates":[145.21478271500001,-37.8041572571],"type":"Point"}
}