{
  "type": "Feature",
  "properties": {
    "iso:country":"AU",
    "sg:address":"22 Sandpiper Pde",
    "sg:city":"Australind",
    "sg:classifiers":[
        {
            "category":"Professional",
            "subcategory":"Art Services",
            "type":"Services"
        }
    ],
    "sg:phone":"+61 418 923 249",
    "sg:postcode":"6233",
    "sg:province":"WA",
    "sg:tags":[
        "decorator",
        "painter"
    ],
    "wof:name":"Ray Venner & Co",
    "wof:placetype":"venue"
},
  "geometry": {"coordinates":[115.72556299999999,-33.280396],"type":"Point"}
}