{
  "type": "Feature",
  "properties": {
    "iso:country":"AU",
    "sg:address":"170 Mary St",
    "sg:city":"Gympie",
    "sg:classifiers":[
        {
            "category":"Travel",
            "subcategory":"Hotels & Motels",
            "type":"Entertainment"
        }
    ],
    "sg:phone":"+61 7 5482 1506",
    "sg:postcode":"4570",
    "sg:province":"QLD",
    "sg:tags":[
        "accommodation"
    ],
    "wof:name":"Billys Hotel",
    "wof:placetype":"venue"
},
  "geometry": {"coordinates":[152.660766602,-26.1896438599],"type":"Point"}
}