{
  "type": "Feature",
  "properties": {
    "addr:full":"163 William St Beverley SA 5009",
    "addr:housenumber":"163",
    "addr:postcode":"5009",
    "addr:street":"William St",
    "iso:country":"AU",
    "sg:address":"163 William St",
    "sg:city":"Beverley",
    "sg:classifiers":[
        {
            "category":"Building & Trades",
            "subcategory":"Construction",
            "type":"Services"
        }
    ],
    "sg:phone":"+61 8 8347 3999",
    "sg:postcode":"5009",
    "sg:province":"SA",
    "sg:tags":[
        "roof"
    ],
    "wof:name":"Cladding & Roofing Contractors Pty Ltd",
    "wof:placetype":"venue"
},
  "geometry": {"coordinates":[138.547775269,-34.9027633667],"type":"Point"}
}