{
  "type": "Feature",
  "properties": {
    "iso:country":"AU",
    "sg:address":"160 Garnet Rd",
    "sg:city":"Kirrawee",
    "sg:classifiers":[
        {
            "category":"Building & Trades",
            "subcategory":"Construction",
            "type":"Services"
        }
    ],
    "sg:phone":"+61 2 9521 3754",
    "sg:postcode":"2232",
    "sg:province":"NSW",
    "sg:tags":[
        "window",
        "aluminium"
    ],
    "sg:website":"http://www.trubluwindows.com.au",
    "wof:name":"Tru-Blu Windows Pty Ltd",
    "wof:placetype":"venue"
},
  "geometry": {"coordinates":[151.07916259800001,-34.0222434998],"type":"Point"}
}