{
  "type": "Feature",
  "properties": {
    "addr:full":"Suite 1, 17 Gurwood St Wagga Wagga NSW 2650",
    "addr:housenumber":"17",
    "addr:postcode":"2650",
    "addr:street":"Gurwood St",
    "iso:country":"AU",
    "sg:address":"Suite 1, 17 Gurwood St",
    "sg:city":"Wagga Wagga",
    "sg:classifiers":[
        {
            "category":"Insurance",
            "subcategory":"Life Insurance",
            "type":"Services"
        }
    ],
    "sg:phone":"+61 2 6921 1999",
    "sg:postcode":"2650",
    "sg:province":"NSW",
    "wof:name":"Flynn Sprake Financial Services",
    "wof:placetype":"venue"
},
  "geometry": {"coordinates":[147.35301208499999,-35.11095047],"type":"Point"}
}