{
  "type": "Feature",
  "properties": {
    "addr:full":"Capalaba Park Shopng Cntr Capalaba QLD 4157",
    "addr:postcode":"4157",
    "iso:country":"AU",
    "sg:address":"Capalaba Park Shopng Cntr",
    "sg:city":"Capalaba",
    "sg:classifiers":[
        {
            "category":"Shopping",
            "subcategory":"Clothing, Apparel, & Fashions",
            "type":"Retail Goods"
        }
    ],
    "sg:phone":"+61 7 3245 6899",
    "sg:postcode":"4157",
    "sg:province":"QLD",
    "sg:tags":[
        "menswear"
    ],
    "wof:name":"Lowes",
    "wof:placetype":"venue"
},
  "geometry": {"coordinates":[153.19229125999999,-27.5437927246],"type":"Point"}
}