{
  "type": "Feature",
  "properties": {
    "addr:full":"65 Watton St Werribee VIC 3030",
    "addr:housenumber":"65",
    "addr:postcode":"3030",
    "addr:street":"Watton St",
    "iso:country":"AU",
    "sg:address":"65 Watton St",
    "sg:city":"Werribee",
    "sg:classifiers":[
        {
            "category":"Real Estate",
            "subcategory":"Real Estate Agent",
            "type":"Services"
        }
    ],
    "sg:phone":"+61 3 9731 7766",
    "sg:postcode":"3030",
    "sg:province":"VIC",
    "wof:name":"Campbell Moore Real Estate",
    "wof:placetype":"venue"
},
  "geometry": {"coordinates":[144.66171299999999,-37.901222],"type":"Point"}
}