{
  "type": "Feature",
  "properties": {
    "iso:country":"AU",
    "sg:address":"Shop 1314",
    "sg:city":", Lower Ground Level Central Plz Adelaide",
    "sg:classifiers":[
        {
            "category":"Shopping",
            "subcategory":"Discount & Variety Stores",
            "type":"Retail Goods"
        }
    ],
    "sg:phone":"+61 8 8232 4122",
    "sg:postcode":"5000",
    "sg:province":"SA",
    "sg:tags":[
        "information",
        "cooking",
        "class"
    ],
    "wof:name":"Pete &#039;N&#039; Peppa",
    "wof:placetype":"venue"
},
  "geometry": {"coordinates":[138.60076904300001,-34.9256401062],"type":"Point"}
}