{
  "type": "Feature",
  "properties": {
    "iso:country":"AU",
    "sg:address":"3 Hewittson Rd",
    "sg:city":"Elizabeth West",
    "sg:classifiers":[
        {
            "category":"Real Estate",
            "subcategory":"Real Estate Agent",
            "type":"Services"
        }
    ],
    "sg:phone":"+61 8 8252 1666",
    "sg:postcode":"5113",
    "sg:province":"SA",
    "sg:tags":[
        "steel",
        "foundry",
        "iron"
    ],
    "wof:name":"Dinning Foundries Pty Ltd",
    "wof:placetype":"venue"
},
  "geometry": {"coordinates":[138.65602111800001,-34.7037811279],"type":"Point"}
}