{
  "type": "Feature",
  "properties": {
    "iso:country":"AU",
    "sg:address":"14 Sydenham Rd",
    "sg:city":"Norwood",
    "sg:classifiers":[
        {
            "category":"Farming",
            "subcategory":"Vineyard",
            "type":"Manufacturing & Wholesale Goods"
        }
    ],
    "sg:phone":"+61 8 8363 5800",
    "sg:postcode":"5067",
    "sg:province":"SA",
    "sg:tags":[
        "winery"
    ],
    "wof:name":"Tidswell Wines",
    "wof:placetype":"venue"
},
  "geometry": {"coordinates":[138.623504639,-34.9236068726],"type":"Point"}
}