{
  "type": "Feature",
  "properties": {
    "iso:country":"AU",
    "sg:address":"5-7 Drabsch St",
    "sg:city":"Loxton",
    "sg:classifiers":[
        {
            "category":"Food & Beverages",
            "subcategory":"Bakery",
            "type":"Retail Goods"
        }
    ],
    "sg:phone":"+61 8 8584 5966",
    "sg:postcode":"5333",
    "sg:province":"SA",
    "sg:tags":[
        "baker"
    ],
    "wof:name":"Prices Loxton Bakery",
    "wof:placetype":"venue"
},
  "geometry": {"coordinates":[140.56971740700001,-34.4513816833],"type":"Point"}
}