{
  "type": "Feature",
  "properties": {
    "addr:full":"7 Neon St Sumner Park QLD 4074",
    "addr:housenumber":"7",
    "addr:postcode":"4074",
    "addr:street":"Neon St",
    "iso:country":"AU",
    "sg:address":"7 Neon St",
    "sg:city":"Sumner Park",
    "sg:classifiers":[
        {
            "category":"Home & Garden",
            "subcategory":"Hardware",
            "type":"Retail Goods"
        }
    ],
    "sg:phone":"+61 7 3279 3300",
    "sg:postcode":"4074",
    "sg:province":"QLD",
    "sg:tags":[
        "generating",
        "set",
        "generator"
    ],
    "wof:name":"Allclass Power",
    "wof:placetype":"venue"
},
  "geometry": {"coordinates":[152.936767578,-27.5666770935],"type":"Point"}
}