{
  "type": "Feature",
  "properties": {
    "iso:country":"AU",
    "sg:address":"Level One Commonwealth Bank Building 1356 Gympie R",
    "sg:city":"Aspley",
    "sg:classifiers":[
        {
            "category":"Banks & Credit Unions",
            "subcategory":"Investment Brokerage",
            "type":"Services"
        }
    ],
    "sg:phone":"+61 7 3263 7166",
    "sg:postcode":"4034",
    "sg:province":"QLD",
    "wof:name":"Dollar Logic",
    "wof:placetype":"venue"
},
  "geometry": {"coordinates":[153.01686100000001,-27.363651],"type":"Point"}
}