{
  "type": "Feature",
  "properties": {
    "addr:full":"Suite 7/ 140 Elizabeth Drv Liverpool NSW 2170",
    "addr:housenumber":"/ 140",
    "addr:postcode":"2170",
    "addr:street":"Elizabeth Drv",
    "iso:country":"AU",
    "sg:address":"Suite 7/ 140 Elizabeth Drv",
    "sg:city":"Liverpool",
    "sg:classifiers":[
        {
            "category":"Health Services",
            "subcategory":"Health Practitioner",
            "type":"Services"
        }
    ],
    "sg:phone":"+61 2 9600 8242",
    "sg:postcode":"2170",
    "sg:province":"NSW",
    "sg:tags":[
        "pathologist",
        "speech"
    ],
    "wof:name":"Liverpool Speech Pathology Sevices",
    "wof:placetype":"venue"
},
  "geometry": {"coordinates":[150.89822387699999,-33.9058837891],"type":"Point"}
}