{
  "type": "Feature",
  "properties": {
    "iso:country":"AU",
    "sg:address":"Shop 71 Burnside Village Shopping Centre",
    "sg:city":"Glenside",
    "sg:classifiers":[
        {
            "category":"Shopping",
            "subcategory":"Clothing, Apparel, & Fashions",
            "type":"Retail Goods"
        }
    ],
    "sg:phone":"+61 8 8338 3771",
    "sg:postcode":"5065",
    "sg:province":"SA",
    "sg:tags":[
        "textile",
        "designer"
    ],
    "wof:name":"Annie Lantz Pty Ltd",
    "wof:placetype":"venue"
},
  "geometry": {"coordinates":[138.642654419,-34.9418182373],"type":"Point"}
}