{
  "type": "Feature",
  "properties": {
    "addr:full":"164 Gympie Rd Kedron QLD 4031",
    "addr:housenumber":"164",
    "addr:postcode":"4031",
    "addr:street":"Gympie Rd",
    "iso:country":"AU",
    "sg:address":"164 Gympie Rd",
    "sg:city":"Kedron",
    "sg:classifiers":[
        {
            "category":"Retail",
            "subcategory":"Auto Rental",
            "type":"Services"
        }
    ],
    "sg:phone":"+61 7 3863 7022",
    "sg:postcode":"4031",
    "sg:province":"QLD",
    "sg:tags":[
        "car",
        "hire",
        "minibus"
    ],
    "wof:name":"Thrifty Car Rental",
    "wof:placetype":"venue"
},
  "geometry": {"coordinates":[153.03276099999999,-27.410448],"type":"Point"}
}