{
  "type": "Feature",
  "properties": {
    "addr:full":"75 Hastings River Dr Port Macquarie NSW 2444",
    "addr:housenumber":"75",
    "addr:postcode":"2444",
    "addr:street":"Hastings River Dr",
    "iso:country":"AU",
    "sg:address":"75 Hastings River Dr",
    "sg:city":"Port Macquarie",
    "sg:classifiers":[
        {
            "category":"Autos & Motor Vehicles",
            "subcategory":"Boat Sales",
            "type":"Retail Goods"
        }
    ],
    "sg:phone":"+61 2 6583 1492",
    "sg:postcode":"2444",
    "sg:province":"NSW",
    "sg:tags":[
        "yacht"
    ],
    "sg:website":"http://www.mcm.tsn.cc",
    "wof:name":"Mid Coast Marine",
    "wof:placetype":"venue"
},
  "geometry": {"coordinates":[152.88928200000001,-31.431273],"type":"Point"}
}