{
  "type": "Feature",
  "properties": {
    "addr:full":"38 Warrigo St Rolleston QLD 4702",
    "addr:housenumber":"38",
    "addr:postcode":"4702",
    "addr:street":"Warrigo St",
    "iso:country":"AU",
    "sg:address":"38 Warrigo St",
    "sg:city":"Rolleston",
    "sg:classifiers":[
        {
            "category":"Cafe",
            "type":"Food & Drink"
        }
    ],
    "sg:phone":"+61 7 4984 3030",
    "sg:postcode":"4702",
    "sg:province":"QLD",
    "wof:name":"Rolleston Cafe",
    "wof:placetype":"venue"
},
  "geometry": {"coordinates":[148.624145508,-24.4630699158],"type":"Point"}
}