{
  "type": "Feature",
  "properties": {
    "addr:full":"12 Richards St Mitcham VIC 3132",
    "addr:housenumber":"12",
    "addr:postcode":"3132",
    "addr:street":"Richards St",
    "iso:country":"AU",
    "sg:address":"12 Richards St",
    "sg:city":"Mitcham",
    "sg:classifiers":[
        {
            "category":"Building & Trades",
            "subcategory":"Plumbing",
            "type":"Services"
        }
    ],
    "sg:phone":"+61 3 9874 7670",
    "sg:postcode":"3132",
    "sg:province":"VIC",
    "sg:tags":[
        "plumber",
        "gasfitters"
    ],
    "wof:name":"Lightning Solutions Pty Ltd",
    "wof:placetype":"venue"
},
  "geometry": {"coordinates":[145.18736267099999,-37.8182487488],"type":"Point"}
}