{
  "type": "Feature",
  "properties": {
    "addr:full":"Suite 512, Dulhunty Arcade, 65 Horton St Port Macquarie NSW 2444",
    "addr:housenumber":"65",
    "addr:postcode":"2444",
    "addr:street":"Horton St",
    "iso:country":"AU",
    "sg:address":"Suite 512, Dulhunty Arcade, 65 Horton St",
    "sg:city":"Port Macquarie",
    "sg:classifiers":[
        {
            "category":"Banks & Credit Unions",
            "subcategory":"Bank",
            "type":"Services"
        }
    ],
    "sg:phone":"+61 2 6582 7910",
    "sg:postcode":"2444",
    "sg:province":"NSW",
    "sg:tags":[
        "broker",
        "mortgage"
    ],
    "wof:name":"Mortgages And More Pty Ltd",
    "wof:placetype":"venue"
},
  "geometry": {"coordinates":[152.908096,-31.430391],"type":"Point"}
}