{
  "type": "Feature",
  "properties": {
    "iso:country":"AU",
    "sg:address":"12 Serrata Crt",
    "sg:city":"Tuncurry",
    "sg:classifiers":[
        {
            "category":"Building & Trades",
            "subcategory":"Plumbing",
            "type":"Services"
        }
    ],
    "sg:phone":"+61 2 6554 6396",
    "sg:postcode":"2428",
    "sg:province":"NSW",
    "sg:tags":[
        "plumber",
        "gasfitters"
    ],
    "wof:name":"Unger I C",
    "wof:placetype":"venue"
},
  "geometry": {"coordinates":[152.49002100000001,-32.159275],"type":"Point"}
}