{
  "type": "Feature",
  "properties": {
    "addr:full":"Lot 2 Reservoir Rd Landsborough QLD 4550",
    "addr:housenumber":"2",
    "addr:postcode":"4550",
    "addr:street":"Reservoir Rd",
    "iso:country":"AU",
    "sg:address":"Lot 2 Reservoir Rd",
    "sg:city":"Landsborough",
    "sg:classifiers":[
        {
            "category":"Professional",
            "subcategory":"Art Services",
            "type":"Services"
        }
    ],
    "sg:phone":"+61 419 706 237",
    "sg:postcode":"4550",
    "sg:province":"QLD",
    "sg:tags":[
        "decorator",
        "painter"
    ],
    "wof:name":"Godfrey R J",
    "wof:placetype":"venue"
},
  "geometry": {"coordinates":[152.95350647000001,-26.8013877869],"type":"Point"}
}