{
  "type": "Feature",
  "properties": {
    "addr:full":"32 Lower Terrace Crs Noble Park North VIC 3174",
    "addr:housenumber":"32",
    "addr:postcode":"3174",
    "addr:street":"Lower Terrace Crs",
    "iso:country":"AU",
    "sg:address":"32 Lower Terrace Crs",
    "sg:city":"Noble Park North",
    "sg:classifiers":[
        {
            "category":"Building & Trades",
            "subcategory":"Construction",
            "type":"Services"
        }
    ],
    "sg:phone":"+61 412 538 701",
    "sg:postcode":"3174",
    "sg:province":"VIC",
    "sg:tags":[
        "joiner",
        "carpenter"
    ],
    "wof:name":"Advanced Carpentry",
    "wof:placetype":"venue"
},
  "geometry": {"coordinates":[145.19183349599999,-37.947479248],"type":"Point"}
}