{
  "type": "Feature",
  "properties": {
    "iso:country":"AU",
    "sg:address":"30 Station St",
    "sg:city":"Bayswater",
    "sg:classifiers":[
        {
            "category":"Fast Food",
            "type":"Food & Drink"
        }
    ],
    "sg:phone":"+61 3 9720 6710",
    "sg:postcode":"3153",
    "sg:province":"VIC",
    "sg:tags":[
        "away",
        "take"
    ],
    "wof:name":"Fish Connection The",
    "wof:placetype":"venue"
},
  "geometry": {"coordinates":[145.266387939,-37.8411407471],"type":"Point"}
}