{
  "type": "Feature",
  "properties": {
    "addr:full":"1024 Beaudesert Rd Coopers Plains QLD 4108",
    "addr:postcode":"1024;4108",
    "addr:street":"Beaudesert Rd",
    "iso:country":"AU",
    "sg:address":"1024 Beaudesert Rd",
    "sg:city":"Coopers Plains",
    "sg:classifiers":[
        {
            "category":"Transit Center",
            "subcategory":"Freight",
            "type":"Transportation"
        }
    ],
    "sg:phone":"+61 7 3277 6900",
    "sg:postcode":"4108",
    "sg:province":"QLD",
    "sg:tags":[
        "forklift",
        "truck"
    ],
    "sg:website":"http://www.scotties.com.au",
    "wof:name":"Scotties Forklift Hire",
    "wof:placetype":"venue"
},
  "geometry": {"coordinates":[153.02459716800001,-27.5695457458],"type":"Point"}
}