{
  "type": "Feature",
  "properties": {
    "addr:full":"2 Arapala Crt Carseldine QLD 4034",
    "addr:housenumber":"2",
    "addr:postcode":"4034",
    "addr:street":"Arapala Crt",
    "iso:country":"AU",
    "sg:address":"2 Arapala Crt",
    "sg:city":"Carseldine",
    "sg:classifiers":[
        {
            "category":"Building & Trades",
            "subcategory":"Landscaping Services",
            "type":"Services"
        }
    ],
    "sg:phone":"+61 7 3263 8557",
    "sg:postcode":"4034",
    "sg:province":"QLD",
    "sg:tags":[
        "inspection"
    ],
    "wof:name":"A.A.A. Building Inspections",
    "wof:placetype":"venue"
},
  "geometry": {"coordinates":[153.023911,-27.343845],"type":"Point"}
}