{
  "type": "Feature",
  "properties": {
    "iso:country":"AU",
    "sg:address":"475 Warrigal Range Rd",
    "sg:city":"Brogo",
    "sg:classifiers":[
        {
            "category":"Food & Beverages",
            "subcategory":"Bakery",
            "type":"Retail Goods"
        }
    ],
    "sg:phone":"+61 2 6492 7225",
    "sg:postcode":"2550",
    "sg:province":"NSW",
    "sg:tags":[
        "baker"
    ],
    "wof:name":"Brogo River Bakery",
    "wof:placetype":"venue"
},
  "geometry": {"coordinates":[149.790115356,-36.5403785706],"type":"Point"}
}