{
  "type": "Feature",
  "properties": {
    "iso:country":"AU",
    "sg:address":"181 Langridge St",
    "sg:city":"Abbotsford",
    "sg:classifiers":[
        {
            "category":"Travel",
            "subcategory":"Hotels & Motels",
            "type":"Entertainment"
        }
    ],
    "sg:phone":"+61 3 9417 2316",
    "sg:postcode":"3067",
    "sg:province":"VIC",
    "wof:name":"City Edge Motel",
    "wof:placetype":"venue"
},
  "geometry": {"coordinates":[144.9921875,-37.8073043823],"type":"Point"}
}