{
  "type": "Feature",
  "properties": {
    "addr:full":"Level 2, 1/ 972 Main Rd Eltham VIC 3095",
    "addr:housenumber":"1 / 972",
    "addr:postcode":"3095",
    "addr:street":"Main Rd",
    "iso:country":"AU",
    "sg:address":"Level 2, 1/ 972 Main Rd",
    "sg:city":"Eltham",
    "sg:classifiers":[
        {
            "category":"Utilities",
            "subcategory":"Electric",
            "type":"Services"
        }
    ],
    "sg:phone":"+61 3 9431 3990",
    "sg:postcode":"3095",
    "sg:province":"VIC",
    "sg:tags":[
        "electrical",
        "contractor"
    ],
    "wof:name":"Laser Electrical",
    "wof:placetype":"venue"
},
  "geometry": {"coordinates":[145.14878845199999,-37.7137413025],"type":"Point"}
}