{
  "type": "Feature",
  "properties": {
    "addr:full":"13 Wallace St Balaklava SA 5461",
    "addr:housenumber":"13",
    "addr:postcode":"5461",
    "addr:street":"Wallace St",
    "iso:country":"AU",
    "sg:address":"13 Wallace St",
    "sg:city":"Balaklava",
    "sg:classifiers":[
        {
            "category":"Food & Beverages",
            "subcategory":"Supermarket",
            "type":"Retail Goods"
        }
    ],
    "sg:phone":"+61 8 8862 1571",
    "sg:postcode":"5461",
    "sg:province":"SA",
    "sg:tags":[
        "grocery",
        "store"
    ],
    "wof:name":"Foodland Balaklava",
    "wof:placetype":"venue"
},
  "geometry": {"coordinates":[138.41514599999999,-34.14661],"type":"Point"}
}