{
  "type": "Feature",
  "properties": {
    "iso:country":"AU",
    "sg:address":"63 Castlereagh St",
    "sg:city":"Sydney",
    "sg:classifiers":[
        {
            "category":"Shopping",
            "subcategory":"Clothing, Apparel, & Fashions",
            "type":"Retail Goods"
        }
    ],
    "sg:phone":"+61 1300 883 880",
    "sg:postcode":"2000",
    "sg:province":"NSW",
    "sg:tags":[
        "boutique"
    ],
    "wof:name":"Louis Vuitton Australia Pty Ltd",
    "wof:placetype":"venue"
},
  "geometry": {"coordinates":[151.20954895,-33.8688659668],"type":"Point"}
}