{
  "type": "Feature",
  "properties": {
    "addr:full":"2 Commercial Ave Bundaberg QLD 4670",
    "addr:housenumber":"2",
    "addr:postcode":"4670",
    "addr:street":"Commercial Ave",
    "iso:country":"AU",
    "sg:address":"2 Commercial Ave",
    "sg:city":"Bundaberg",
    "sg:classifiers":[
        {
            "category":"Building & Trades",
            "subcategory":"Construction",
            "type":"Services"
        }
    ],
    "sg:phone":"+61 7 4151 2190",
    "sg:postcode":"4670",
    "sg:province":"QLD",
    "sg:tags":[
        "welding"
    ],
    "wof:name":"Bundaberg Customised Welding",
    "wof:placetype":"venue"
},
  "geometry": {"coordinates":[152.333816528,-24.8923625946],"type":"Point"}
}