{
  "type": "Feature",
  "properties": {
    "addr:full":"6 Birdwood Crt Lara VIC 3212",
    "addr:housenumber":"6",
    "addr:postcode":"3212",
    "addr:street":"Birdwood Crt",
    "iso:country":"AU",
    "sg:address":"6 Birdwood Crt",
    "sg:city":"Lara",
    "sg:classifiers":[
        {
            "category":"Shopping",
            "subcategory":"Mobile Phones",
            "type":"Retail Goods"
        }
    ],
    "sg:phone":"+61 3 5282 3229",
    "sg:postcode":"3212",
    "sg:province":"VIC",
    "sg:tags":[
        "telephone",
        "accessory"
    ],
    "wof:name":"Mobile Installation Group",
    "wof:placetype":"venue"
},
  "geometry": {"coordinates":[144.39225769000001,-38.0312728882],"type":"Point"}
}