{
  "type": "Feature",
  "properties": {
    "addr:full":"503 Victoria St Brunswick VIC 3056",
    "addr:housenumber":"503",
    "addr:postcode":"3056",
    "addr:street":"Victoria St",
    "iso:country":"AU",
    "sg:address":"503 Victoria St",
    "sg:city":"Brunswick",
    "sg:classifiers":[
        {
            "category":"Personal",
            "subcategory":"Beauty Salon",
            "type":"Services"
        }
    ],
    "sg:phone":"+61 3 9380 5669",
    "sg:postcode":"3056",
    "sg:province":"VIC",
    "sg:tags":[
        "hairdresser"
    ],
    "wof:name":"Cutz 503",
    "wof:placetype":"venue"
},
  "geometry": {"coordinates":[144.94557189899999,-37.7648582458],"type":"Point"}
}