{
  "type": "Feature",
  "properties": {
    "addr:full":"87 Palm Ave Leeton NSW 2705",
    "addr:housenumber":"87",
    "addr:postcode":"2705",
    "addr:street":"Palm Ave",
    "iso:country":"AU",
    "sg:address":"87 Palm Ave",
    "sg:city":"Leeton",
    "sg:classifiers":[
        {
            "category":"Building & Trades",
            "subcategory":"Cleaning & Sanitation",
            "type":"Services"
        }
    ],
    "sg:phone":"+61 2 6953 4231",
    "sg:postcode":"2705",
    "sg:province":"NSW",
    "sg:tags":[
        "industrial",
        "commercial",
        "contractor"
    ],
    "wof:name":"Leeton Cleaning Service",
    "wof:placetype":"venue"
},
  "geometry": {"coordinates":[146.40620422399999,-34.5520401001],"type":"Point"}
}