{
  "type": "Feature",
  "properties": {
    "addr:full":"154 North Rd Brighton VIC 3186",
    "addr:housenumber":"154",
    "addr:postcode":"3186",
    "addr:street":"North Rd",
    "iso:country":"AU",
    "sg:address":"154 North Rd",
    "sg:city":"Brighton",
    "sg:classifiers":[
        {
            "category":"Building & Trades",
            "subcategory":"Landscaping Services",
            "type":"Services"
        }
    ],
    "sg:phone":"+61 3 9530 8021",
    "sg:postcode":"3186",
    "sg:province":"VIC",
    "sg:tags":[
        "designer",
        "landscape",
        "contractor"
    ],
    "sg:website":"http://www.sml.com.au",
    "wof:name":"Simon McCurdy Landscapes Pty Ltd",
    "wof:placetype":"venue"
},
  "geometry": {"coordinates":[145.00523376500001,-37.8997955322],"type":"Point"}
}