{
  "type": "Feature",
  "properties": {
    "addr:full":"9b Olsen Pl Broadmeadows VIC 3047",
    "addr:housenumber":"9b",
    "addr:postcode":"3047",
    "addr:street":"Olsen Pl",
    "iso:country":"AU",
    "sg:address":"9b Olsen Pl",
    "sg:city":"Broadmeadows",
    "sg:classifiers":[
        {
            "category":"Food & Beverages",
            "subcategory":"Specialty",
            "type":"Retail Goods"
        }
    ],
    "sg:phone":"+61 3 9302 3350",
    "sg:postcode":"3047",
    "sg:province":"VIC",
    "sg:tags":[
        "delicacy"
    ],
    "wof:name":"Arbee Lankasian Foods",
    "wof:placetype":"venue"
},
  "geometry": {"coordinates":[144.92684936500001,-37.6898117065],"type":"Point"}
}