{
  "type": "Feature",
  "properties": {
    "addr:full":"44 Aitken St Gisborne VIC 3437",
    "addr:housenumber":"44",
    "addr:postcode":"3437",
    "addr:street":"Aitken St",
    "iso:country":"AU",
    "sg:address":"44 Aitken St",
    "sg:city":"Gisborne",
    "sg:classifiers":[
        {
            "category":"Building & Trades",
            "subcategory":"Locksmith",
            "type":"Services"
        }
    ],
    "sg:phone":"+61 3 9740 9929",
    "sg:postcode":"3437",
    "sg:province":"VIC",
    "sg:tags":[
        "lock"
    ],
    "wof:name":"Hume Locksmiths",
    "wof:placetype":"venue"
},
  "geometry": {"coordinates":[144.59092712399999,-37.4883537292],"type":"Point"}
}