{
  "type": "Feature",
  "properties": {
    "iso:country":"AU",
    "sg:address":"94 Frankland St",
    "sg:city":"Launceston",
    "sg:classifiers":[
        {
            "category":"Professional",
            "subcategory":"Engineering",
            "type":"Services"
        }
    ],
    "sg:phone":"+61 3 6331 7430",
    "sg:postcode":"7250",
    "sg:province":"TAS",
    "sg:tags":[
        "electrical",
        "engineer"
    ],
    "wof:name":"Hill R J & Associates",
    "wof:placetype":"venue"
},
  "geometry": {"coordinates":[147.13786315900001,-41.4474220276],"type":"Point"}
}