{
  "type": "Feature",
  "properties": {
    "addr:full":"13 Wilkinson St Hoppers Crossing VIC 3029",
    "addr:housenumber":"13",
    "addr:postcode":"3029",
    "addr:street":"Wilkinson St",
    "iso:country":"AU",
    "sg:address":"13 Wilkinson St",
    "sg:city":"Hoppers Crossing",
    "sg:classifiers":[
        {
            "category":"Professional",
            "subcategory":"Testing Lab",
            "type":"Services"
        }
    ],
    "sg:phone":"+61 3 9749 4265",
    "sg:postcode":"3029",
    "sg:province":"VIC",
    "sg:tags":[
        "inspection"
    ],
    "wof:name":"Australia Wide Inspection Services Pty Ltd",
    "wof:placetype":"venue"
},
  "geometry": {"coordinates":[144.68498199999999,-37.872864],"type":"Point"}
}