{
  "type": "Feature",
  "properties": {
    "iso:country":"AU",
    "sg:address":"4/50 Peachtree Rd",
    "sg:city":"Penrith",
    "sg:classifiers":[
        {
            "category":"Building & Trades",
            "subcategory":"Locksmith",
            "type":"Services"
        }
    ],
    "sg:phone":"+61 2 4731 6622",
    "sg:postcode":"2750",
    "sg:province":"NSW",
    "sg:tags":[
        "strongroom",
        "safe",
        "door"
    ],
    "wof:name":"Olympic Locksmiths Pty Ltd",
    "wof:placetype":"venue"
},
  "geometry": {"coordinates":[150.97596740700001,-33.7895431519],"type":"Point"}
}