{
  "type": "Feature",
  "properties": {
    "iso:country":"AU",
    "sg:address":"326 Millers Rd",
    "sg:city":"Underwood",
    "sg:classifiers":[
        {
            "category":"Professional",
            "subcategory":"Computer Services",
            "type":"Services"
        }
    ],
    "sg:phone":"+61 7 3841 5722",
    "sg:postcode":"4119",
    "sg:province":"QLD",
    "sg:tags":[
        "repairs",
        "upgrade",
        "equipment"
    ],
    "wof:name":"Brian Dillon",
    "wof:placetype":"venue"
},
  "geometry": {"coordinates":[153.103912353,-27.6045684814],"type":"Point"}
}