{
  "type": "Feature",
  "properties": {
    "iso:country":"AU",
    "sg:address":"2 Donald St",
    "sg:city":"Highett",
    "sg:classifiers":[
        {
            "category":"Manufacturing",
            "subcategory":"Textiles",
            "type":"Manufacturing & Wholesale Goods"
        }
    ],
    "sg:phone":"+61 3 9555 2091",
    "sg:postcode":"3190",
    "sg:province":"VIC",
    "sg:tags":[
        "agent"
    ],
    "wof:name":"Sorati Clausen & Co",
    "wof:placetype":"venue"
},
  "geometry": {"coordinates":[145.038009644,-37.9522438049],"type":"Point"}
}