{
  "type": "Feature",
  "properties": {
    "addr:full":"20 Ann St Salisbury SA 5108",
    "addr:housenumber":"20",
    "addr:postcode":"5108",
    "addr:street":"Ann St",
    "iso:country":"AU",
    "sg:address":"20 Ann St",
    "sg:city":"Salisbury",
    "sg:classifiers":[
        {
            "category":"Health Services",
            "subcategory":"Health Practitioner",
            "type":"Services"
        }
    ],
    "sg:phone":"+61 8 8258 8877",
    "sg:postcode":"5108",
    "sg:province":"SA",
    "sg:tags":[
        "hypnotherapy"
    ],
    "wof:name":"Primiana Fernandes",
    "wof:placetype":"venue"
},
  "geometry": {"coordinates":[138.64854431099999,-34.7642211914],"type":"Point"}
}