{
  "type": "Feature",
  "properties": {
    "addr:full":"Shop 2, 33 Ardross St, Applecross Village Applecross WA 6153",
    "addr:housenumber":"shop;33",
    "addr:postcode":"6153",
    "addr:street":"Ardross St",
    "iso:country":"AU",
    "sg:address":"Shop 2, 33 Ardross St, Applecross Village",
    "sg:city":"Applecross",
    "sg:classifiers":[
        {
            "category":"Personal",
            "subcategory":"Beauty Salon",
            "type":"Services"
        }
    ],
    "sg:phone":"+61 8 9364 6414",
    "sg:postcode":"6153",
    "sg:province":"WA",
    "wof:name":"Elements On Ardross",
    "wof:placetype":"venue"
},
  "geometry": {"coordinates":[115.83442700000001,-32.009995],"type":"Point"}
}