{
  "type": "Feature",
  "properties": {
    "addr:full":"7 McLean St Coffs Harbour NSW 2450",
    "addr:housenumber":"7",
    "addr:postcode":"2450",
    "addr:street":"Mclean St",
    "iso:country":"AU",
    "sg:address":"7 McLean St",
    "sg:city":"Coffs Harbour",
    "sg:classifiers":[
        {
            "category":"Organizations",
            "subcategory":"Community Association",
            "type":"Services"
        }
    ],
    "sg:phone":"+61 2 6651 3367",
    "sg:postcode":"2450",
    "sg:province":"NSW",
    "sg:tags":[
        "organisation",
        "family",
        "welfare"
    ],
    "wof:name":"Burnside Hire Intensity Fostering Service",
    "wof:placetype":"venue"
},
  "geometry": {"coordinates":[153.11068700000001,-30.298042],"type":"Point"}
}