{
  "type": "Feature",
  "properties": {
    "iso:country":"AU",
    "sg:address":"Lot 1 Dover St",
    "sg:city":"Boonah",
    "sg:classifiers":[
        {
            "category":"Wholesale",
            "subcategory":"Machinery & Supplies",
            "type":"Manufacturing & Wholesale Goods"
        }
    ],
    "sg:phone":"+61 7 5463 4303",
    "sg:postcode":"4310",
    "sg:province":"QLD",
    "sg:tags":[
        "agricultural"
    ],
    "wof:name":"Gee's Machinery",
    "wof:placetype":"venue"
},
  "geometry": {"coordinates":[152.69128418,-27.9982738495],"type":"Point"}
}