{
  "type": "Feature",
  "properties": {
    "addr:full":"403 Bronte Rd Bronte NSW 2024",
    "addr:housenumber":"403",
    "addr:postcode":"2024",
    "addr:street":"Bronte Rd",
    "iso:country":"AU",
    "sg:address":"403 Bronte Rd",
    "sg:city":"Bronte",
    "sg:classifiers":[
        {
            "category":"Professional",
            "subcategory":"Art Services",
            "type":"Services"
        }
    ],
    "sg:phone":"+61 2 9369 5252",
    "sg:postcode":"2024",
    "sg:province":"NSW",
    "sg:tags":[
        "arranger",
        "music",
        "composer"
    ],
    "wof:name":"Rafael May Music",
    "wof:placetype":"venue"
},
  "geometry": {"coordinates":[151.26353454599999,-33.9025611877],"type":"Point"}
}