{
  "type": "Feature",
  "properties": {
    "addr:full":"111 Musgrave St North Rockhampton QLD 4701",
    "addr:housenumber":"111",
    "addr:postcode":"4701",
    "addr:street":"Musgrave St North",
    "iso:country":"AU",
    "sg:address":"111 Musgrave St",
    "sg:city":"North Rockhampton",
    "sg:classifiers":[
        {
            "category":"Professional",
            "subcategory":"Accounting & Tax Preparation",
            "type":"Services"
        }
    ],
    "sg:phone":"+61 7 4922 6128",
    "sg:postcode":"4701",
    "sg:province":"QLD",
    "sg:tags":[
        "accountant",
        "auditor"
    ],
    "wof:name":"The Business Centre",
    "wof:placetype":"venue"
},
  "geometry": {"coordinates":[150.52192688,-23.3657855988],"type":"Point"}
}