{
  "type": "Feature",
  "properties": {
    "addr:full":"82 Forsyth St Wagga Wagga NSW 2650",
    "addr:housenumber":"82",
    "addr:postcode":"2650",
    "addr:street":"Forsyth St",
    "iso:country":"AU",
    "sg:address":"82 Forsyth St",
    "sg:city":"Wagga Wagga",
    "sg:classifiers":[
        {
            "category":"Personal",
            "subcategory":"Beauty Salon",
            "type":"Services"
        }
    ],
    "sg:phone":"+61 2 6971 9060",
    "sg:postcode":"2650",
    "sg:province":"NSW",
    "wof:name":"Irvin Day Hair & Beauty Excellence",
    "wof:placetype":"venue"
},
  "geometry": {"coordinates":[147.368606567,-35.1139373779],"type":"Point"}
}