{
  "type": "Feature",
  "properties": {
    "iso:country":"AU",
    "sg:address":"2 Nambour Rd",
    "sg:city":"Bli Bli",
    "sg:classifiers":[
        {
            "category":"Real Estate",
            "subcategory":"Real Estate Agent",
            "type":"Services"
        }
    ],
    "sg:phone":"+61 7 5448 4008",
    "sg:postcode":"4560",
    "sg:province":"QLD",
    "wof:name":"L J Hooker",
    "wof:placetype":"venue"
},
  "geometry": {"coordinates":[152.98306274399999,-26.6161994934],"type":"Point"}
}