{
  "type": "Feature",
  "properties": {
    "addr:full":"Gloucester Ave Devonport TAS 7310",
    "addr:postcode":"7310",
    "addr:street":"Gloucester Ave",
    "iso:country":"AU",
    "sg:address":"Gloucester Ave",
    "sg:city":"Devonport",
    "sg:classifiers":[
        {
            "category":"Museum",
            "type":"Entertainment"
        }
    ],
    "sg:phone":"+61 3 6424 7100",
    "sg:postcode":"7310",
    "sg:province":"TAS",
    "wof:name":"Devonport Maritime Museum",
    "wof:placetype":"venue"
},
  "geometry": {"coordinates":[146.36203002900001,-41.1667938232],"type":"Point"}
}