{
  "type": "Feature",
  "properties": {
    "addr:full":"Shop T95A Erina Fair Shopping Centre Erina NSW 2250",
    "addr:postcode":"2250",
    "iso:country":"AU",
    "sg:address":"Shop T95A Erina Fair Shopping Centre",
    "sg:city":"Erina",
    "sg:classifiers":[
        {
            "category":"Professional",
            "subcategory":"Art Services",
            "type":"Services"
        }
    ],
    "sg:phone":"+61 2 4365 4493",
    "sg:postcode":"2250",
    "sg:province":"NSW",
    "sg:tags":[
        "picture",
        "frame",
        "framing"
    ],
    "wof:name":"Rabbit Photo",
    "wof:placetype":"venue"
},
  "geometry": {"coordinates":[151.39523315400001,-33.4345855713],"type":"Point"}
}