{
  "type": "Feature",
  "properties": {
    "addr:full":"Shop 9, 103 Currie St Nambour QLD 4560",
    "addr:housenumber":"shop 9 103",
    "addr:postcode":"4560",
    "addr:street":"Currie St",
    "iso:country":"AU",
    "sg:address":"Shop 9, 103 Currie St",
    "sg:city":"Nambour",
    "sg:classifiers":[
        {
            "category":"Fast Food",
            "type":"Food & Drink"
        }
    ],
    "sg:phone":"+61 7 5441 1647",
    "sg:postcode":"4560",
    "sg:province":"QLD",
    "sg:tags":[
        "away",
        "take"
    ],
    "wof:name":"Nambour Kebabs",
    "wof:placetype":"venue"
},
  "geometry": {"coordinates":[152.959274292,-26.6266956329],"type":"Point"}
}