{
  "type": "Feature",
  "properties": {
    "addr:full":"28 Sophia Jane Ave Woodberry NSW 2322",
    "addr:housenumber":"28",
    "addr:postcode":"2322",
    "addr:street":"Sophia Jane Ave",
    "iso:country":"AU",
    "sg:address":"28 Sophia Jane Ave",
    "sg:city":"Woodberry",
    "sg:classifiers":[
        {
            "category":"Building & Trades",
            "subcategory":"Construction",
            "type":"Services"
        }
    ],
    "sg:phone":"+61 416 089 696",
    "sg:postcode":"2322",
    "sg:province":"NSW",
    "sg:tags":[
        "spouting",
        "guttering"
    ],
    "wof:name":"Brendan Missen Spouting",
    "wof:placetype":"venue"
},
  "geometry": {"coordinates":[151.66911315900001,-32.7910766602],"type":"Point"}
}