{
  "type": "Feature",
  "properties": {
    "iso:country":"AU",
    "sg:address":"Level 2/ 29 Crossley St",
    "sg:city":"Melbourne",
    "sg:classifiers":[
        {
            "category":"Real Estate",
            "subcategory":"Architect",
            "type":"Services"
        }
    ],
    "sg:phone":"+61 3 9663 0733",
    "sg:postcode":"3000",
    "sg:province":"VIC",
    "wof:name":"Herbert Mason Architecture",
    "wof:placetype":"venue"
},
  "geometry": {"coordinates":[144.97088623100001,-37.8112487793],"type":"Point"}
}