{
  "type": "Feature",
  "properties": {
    "addr:full":"25 Kennealy St Surrey Hills VIC 3127",
    "addr:housenumber":"25",
    "addr:postcode":"3127",
    "addr:street":"Kennealy St",
    "iso:country":"AU",
    "sg:address":"25 Kennealy St",
    "sg:city":"Surrey Hills",
    "sg:classifiers":[
        {
            "category":"Health Services",
            "subcategory":"Medical Lab",
            "type":"Services"
        }
    ],
    "sg:phone":"+61 3 9836 1762",
    "sg:postcode":"3127",
    "sg:province":"VIC",
    "sg:tags":[
        "laboratory",
        "dental"
    ],
    "wof:name":"Deko Dental Laboratories",
    "wof:placetype":"venue"
},
  "geometry": {"coordinates":[145.088821411,-37.8274230957],"type":"Point"}
}