{
  "type": "Feature",
  "properties": {
    "iso:country":"AU",
    "sg:address":"Bindoo Rd",
    "sg:city":"Yuna East",
    "sg:classifiers":[
        {
            "category":"Farming",
            "subcategory":"Farm",
            "type":"Manufacturing & Wholesale Goods"
        }
    ],
    "sg:phone":"+61 8 9931 1017",
    "sg:postcode":"6532",
    "sg:province":"WA",
    "sg:tags":[
        "farmer"
    ],
    "wof:name":"Wilton B R",
    "wof:placetype":"venue"
},
  "geometry": {"coordinates":[115.02613067599999,-28.3689956665],"type":"Point"}
}