{
  "type": "Feature",
  "properties": {
    "addr:full":"Warwick Grove Shopng Cntr Beach Rd Warwick WA 6024",
    "addr:postcode":"6024",
    "addr:street":"Warwick Grove Shopng Cntr Beach Rd",
    "iso:country":"AU",
    "sg:address":"Warwick Grove Shopng Cntr Beach Rd",
    "sg:city":"Warwick",
    "sg:classifiers":[
        {
            "category":"Food & Beverages",
            "subcategory":"Bakery",
            "type":"Retail Goods"
        }
    ],
    "sg:phone":"+61 8 9246 5445",
    "sg:postcode":"6024",
    "sg:province":"WA",
    "sg:tags":[
        "baker"
    ],
    "wof:name":"Bakers Delight",
    "wof:placetype":"venue"
},
  "geometry": {"coordinates":[115.80857849100001,-31.8337993622],"type":"Point"}
}