{
  "type": "Feature",
  "properties": {
    "iso:country":"AU",
    "sg:address":"117 Cedar Park Rd",
    "sg:city":"Kuranda",
    "sg:classifiers":[
        {
            "category":"Sports & Exercise",
            "subcategory":"Gym",
            "type":"Entertainment"
        }
    ],
    "sg:phone":"+61 7 4093 7989",
    "sg:postcode":"4872",
    "sg:province":"QLD",
    "sg:tags":[
        "health",
        "fitness"
    ],
    "wof:name":"Clohesy River Health Farm",
    "wof:placetype":"venue"
},
  "geometry": {"coordinates":[145.581542969,-17.2701511383],"type":"Point"}
}