{
  "type": "Feature",
  "properties": {
    "addr:full":"Unit 3 221-223 O&#039;Riordan St Mascot NSW 2020",
    "addr:postcode":"221-223;2020",
    "addr:street":"O &;Riordan St",
    "iso:country":"AU",
    "sg:address":"Unit 3 221-223 O&#039;Riordan St",
    "sg:city":"Mascot",
    "sg:classifiers":[
        {
            "category":"Professional",
            "type":"Services"
        }
    ],
    "sg:phone":"+61 2 9700 7411",
    "sg:postcode":"2020",
    "sg:province":"NSW",
    "sg:tags":[
        "mail",
        "contractor"
    ],
    "wof:name":"DHL Globalmail",
    "wof:placetype":"venue"
},
  "geometry": {"coordinates":[151.18719482399999,-33.9288215637],"type":"Point"}
}