{
  "type": "Feature",
  "properties": {
    "addr:full":"Shop 1B Kings Langley Shopping Cntr James Cook Drv Kings Langley NSW 2147",
    "addr:housenumber":"shop 1b",
    "addr:postcode":"2147",
    "addr:street":"Cook Drv",
    "iso:country":"AU",
    "sg:address":"Shop 1B Kings Langley Shopping Cntr James Cook Drv",
    "sg:city":"Kings Langley",
    "sg:classifiers":[
        {
            "category":"Shopping",
            "subcategory":"Optical Goods",
            "type":"Retail Goods"
        }
    ],
    "sg:phone":"+61 2 9624 7255",
    "sg:postcode":"2147",
    "sg:province":"NSW",
    "sg:tags":[
        "dispenser",
        "prescription"
    ],
    "wof:name":"All About Eyes",
    "wof:placetype":"venue"
},
  "geometry": {"coordinates":[150.924850464,-33.7430839539],"type":"Point"}
}