{
  "type": "Feature",
  "properties": {
    "iso:country":"AU",
    "sg:address":"107 Dandenong Rd",
    "sg:city":"Mt Ommaney",
    "sg:classifiers":[
        {
            "category":"Real Estate",
            "subcategory":"Real Estate Agent",
            "type":"Services"
        }
    ],
    "sg:phone":"+61 7 3376 5222",
    "sg:postcode":"4074",
    "sg:province":"QLD",
    "wof:name":"Barry Truss Real Estate",
    "wof:placetype":"venue"
},
  "geometry": {"coordinates":[152.93597412099999,-27.5507774353],"type":"Point"}
}