{
  "type": "Feature",
  "properties": {
    "iso:country":"AU",
    "sg:address":"21 Lanaglen Drv",
    "sg:city":"Birkdale",
    "sg:classifiers":[
        {
            "category":"Home & Garden",
            "subcategory":"Carpets & Floor Coverings",
            "type":"Retail Goods"
        }
    ],
    "sg:phone":"+61 7 3822 8953",
    "sg:postcode":"4159",
    "sg:province":"QLD",
    "sg:tags":[
        "tile",
        "wall"
    ],
    "wof:name":"Black Rock Tiling",
    "wof:placetype":"venue"
},
  "geometry": {"coordinates":[153.20050048799999,-27.4958744049],"type":"Point"}
}