{
  "type": "Feature",
  "properties": {
    "iso:country":"AU",
    "sg:address":"1400 Mt Cotton Rd",
    "sg:city":"Burbank",
    "sg:classifiers":[
        {
            "category":"Farming",
            "subcategory":"Nursery",
            "type":"Manufacturing & Wholesale Goods"
        }
    ],
    "sg:phone":"+61 7 3349 8696",
    "sg:postcode":"4156",
    "sg:province":"QLD",
    "wof:name":"Ibrox Park Nursery",
    "wof:placetype":"venue"
},
  "geometry": {"coordinates":[153.18949890100001,-27.5254459381],"type":"Point"}
}