{
  "type": "Feature",
  "properties": {
    "addr:full":"12 Cutts Rd Don TAS 7310",
    "addr:housenumber":"12",
    "addr:postcode":"7310",
    "addr:street":"Cutts Rd",
    "iso:country":"AU",
    "sg:address":"12 Cutts Rd",
    "sg:city":"Don",
    "sg:classifiers":[
        {
            "category":"Building & Trades",
            "subcategory":"Plumbing",
            "type":"Services"
        }
    ],
    "sg:phone":"+61 3 6424 5751",
    "sg:postcode":"7310",
    "sg:province":"TAS",
    "sg:tags":[
        "plumber",
        "gasfitters"
    ],
    "wof:name":"Gleeson C J & M J Plumbing Pty Ltd",
    "wof:placetype":"venue"
},
  "geometry": {"coordinates":[146.319381714,-41.1749534607],"type":"Point"}
}