{
  "type": "Feature",
  "properties": {
    "iso:country":"AU",
    "sg:address":"65 Mair St East",
    "sg:city":"Ballarat",
    "sg:classifiers":[
        {
            "category":"Retail",
            "subcategory":"Repair Shop",
            "type":"Services"
        }
    ],
    "sg:phone":"+61 3 5333 2877",
    "sg:postcode":"3350",
    "sg:province":"VIC",
    "sg:tags":[
        "machine",
        "sewing"
    ],
    "wof:name":"Statewide Sewing Centres",
    "wof:placetype":"venue"
},
  "geometry": {"coordinates":[143.865128,-37.560421],"type":"Point"}
}