{
  "type": "Feature",
  "properties": {
    "iso:country":"AU",
    "sg:address":"183 Moorabool St",
    "sg:city":"Geelong",
    "sg:classifiers":[
        {
            "category":"Professional",
            "subcategory":"Art Services",
            "type":"Services"
        }
    ],
    "sg:phone":"+61 3 5229 9892",
    "sg:postcode":"3220",
    "sg:province":"VIC",
    "sg:tags":[
        "picture",
        "frame",
        "framing"
    ],
    "wof:name":"Mahoneys Galleries",
    "wof:placetype":"venue"
},
  "geometry": {"coordinates":[144.35966500000001,-38.149967],"type":"Point"}
}