{
  "type": "Feature",
  "properties": {
    "addr:full":"34 Main St Minlaton SA 5575",
    "addr:housenumber":"34",
    "addr:postcode":"5575",
    "addr:street":"Main St",
    "iso:country":"AU",
    "sg:address":"34 Main St",
    "sg:city":"Minlaton",
    "sg:classifiers":[
        {
            "category":"Professional",
            "subcategory":"Printing & Photocopies",
            "type":"Services"
        }
    ],
    "sg:phone":"+61 8 8853 2047",
    "sg:postcode":"5575",
    "sg:province":"SA",
    "sg:tags":[
        "trophy"
    ],
    "wof:name":"Minlaton Sports Store",
    "wof:placetype":"venue"
},
  "geometry": {"coordinates":[137.59539794899999,-34.7720069885],"type":"Point"}
}