{
  "type": "Feature",
  "properties": {
    "addr:full":"610 Oxley Ave Scarborough QLD 4020",
    "addr:housenumber":"610",
    "addr:postcode":"4020",
    "addr:street":"Oxley Ave",
    "iso:country":"AU",
    "sg:address":"610 Oxley Ave",
    "sg:city":"Scarborough",
    "sg:classifiers":[
        {
            "category":"Personal",
            "subcategory":"Beauty Salon",
            "type":"Services"
        }
    ],
    "sg:phone":"+61 7 3203 6749",
    "sg:postcode":"4020",
    "sg:province":"QLD",
    "wof:name":"Essential Beauty Studio The",
    "wof:placetype":"venue"
},
  "geometry": {"coordinates":[153.11378500000001,-27.206676],"type":"Point"}
}