{
  "type": "Feature",
  "properties": {
    "addr:full":"100 Commercial St West Mt Gambier SA 5290",
    "addr:housenumber":"100",
    "addr:postcode":"5290",
    "addr:street":"Commercial St West",
    "iso:country":"AU",
    "sg:address":"100 Commercial St",
    "sg:city":"West Mt Gambier",
    "sg:classifiers":[
        {
            "category":"Autos & Motor Vehicles",
            "subcategory":"Fuel & Gas Station",
            "type":"Retail Goods"
        }
    ],
    "sg:phone":"+61 8 8725 5037",
    "sg:postcode":"5290",
    "sg:province":"SA",
    "wof:name":"Shell Blue Lake Service Station",
    "wof:placetype":"venue"
},
  "geometry": {"coordinates":[140.774902,-37.826378],"type":"Point"}
}