{
  "type": "Feature",
  "properties": {
    "addr:full":"63 Swanport Rd Murray Bridge SA 5253",
    "addr:housenumber":"63",
    "addr:postcode":"5253",
    "addr:street":"Swanport Rd",
    "iso:country":"AU",
    "sg:address":"63 Swanport Rd",
    "sg:city":"Murray Bridge",
    "sg:classifiers":[
        {
            "category":"Retail",
            "subcategory":"Funeral Services",
            "type":"Services"
        }
    ],
    "sg:phone":"+61 8 8531 1111",
    "sg:postcode":"5253",
    "sg:province":"SA",
    "sg:tags":[
        "director"
    ],
    "wof:name":"Minge Funerals",
    "wof:placetype":"venue"
},
  "geometry": {"coordinates":[139.280639648,-35.1319770813],"type":"Point"}
}