{
  "type": "Feature",
  "properties": {
    "addr:full":"Bay Rd Victor Harbor SA 5211",
    "addr:postcode":"5211",
    "addr:street":"Bay Rd",
    "iso:country":"AU",
    "sg:address":"Bay Rd",
    "sg:city":"Victor Harbor",
    "sg:classifiers":[
        {
            "category":"Arena",
            "subcategory":"Sports Club",
            "type":"Entertainment"
        }
    ],
    "sg:phone":"+61 8 8552 1949",
    "sg:postcode":"5211",
    "sg:province":"SA",
    "sg:tags":[
        "tour",
        "holiday"
    ],
    "sg:website":"http://www.victorharborholiday.com.au",
    "wof:name":"Victor Harbor Holiday & Cabin Park",
    "wof:placetype":"venue"
},
  "geometry": {"coordinates":[138.611495972,-35.5574913025],"type":"Point"}
}