{
  "type": "Feature",
  "properties": {
    "addr:full":"PO Box 4145 Winmalee NSW 2777",
    "addr:postcode":"2777",
    "iso:country":"AU",
    "sg:address":"PO Box 4145",
    "sg:city":"Winmalee",
    "sg:classifiers":[
        {
            "category":"Building & Trades",
            "subcategory":"Construction",
            "type":"Services"
        }
    ],
    "sg:phone":"+61 2 4754 2241",
    "sg:postcode":"2777",
    "sg:province":"NSW",
    "sg:tags":[
        "contractor"
    ],
    "wof:name":"Trevane Building Services Pty Ltd",
    "wof:placetype":"venue"
},
  "geometry": {"coordinates":[150.60635375999999,-33.6747589111],"type":"Point"}
}