{
  "type": "Feature",
  "properties": {
    "iso:country":"AU",
    "sg:address":"1339 Main Rd",
    "sg:city":"Eltham",
    "sg:classifiers":[
        {
            "category":"Travel",
            "subcategory":"Hotels & Motels",
            "type":"Entertainment"
        }
    ],
    "sg:phone":"+61 3 9431 1666",
    "sg:postcode":"3095",
    "sg:province":"VIC",
    "wof:name":"Eltham Gateway Hotel & Conference Centre",
    "wof:placetype":"venue"
},
  "geometry": {"coordinates":[145.16542053200001,-37.7024002075],"type":"Point"}
}