{
  "type": "Feature",
  "properties": {
    "addr:full":"1029 Ridley St Wedgefield WA 6724",
    "addr:housenumber":"1029",
    "addr:postcode":"6724",
    "addr:street":"Ridley St",
    "iso:country":"AU",
    "sg:address":"1029 Ridley St",
    "sg:city":"Wedgefield",
    "sg:classifiers":[
        {
            "category":"Retail",
            "subcategory":"Repair Shop",
            "type":"Services"
        }
    ],
    "sg:phone":"+61 8 9172 2610",
    "sg:postcode":"6724",
    "sg:province":"WA",
    "sg:tags":[
        "windscreen"
    ],
    "wof:name":"Robs Panel & Paint",
    "wof:placetype":"venue"
},
  "geometry": {"coordinates":[118.59757232699999,-20.3809604645],"type":"Point"}
}