{
  "type": "Feature",
  "properties": {
    "addr:full":"58 Lionel St Kalgoorlie WA 6430",
    "addr:housenumber":"58",
    "addr:postcode":"6430",
    "addr:street":"Lionel St",
    "iso:country":"AU",
    "sg:address":"58 Lionel St",
    "sg:city":"Kalgoorlie",
    "sg:classifiers":[
        {
            "category":"Food & Beverages",
            "subcategory":"Liquor & Beverages",
            "type":"Retail Goods"
        }
    ],
    "sg:phone":"+61 8 9021 2583",
    "sg:postcode":"6430",
    "sg:province":"WA",
    "sg:tags":[
        "store"
    ],
    "wof:name":"Cellarbrations",
    "wof:placetype":"venue"
},
  "geometry": {"coordinates":[121.484039307,-30.7719459534],"type":"Point"}
}