{
  "type": "Feature",
  "properties": {
    "addr:full":"3 Brewer Rd Brighton East VIC 3187",
    "addr:housenumber":"3",
    "addr:postcode":"3187",
    "addr:street":"Brewer Rd",
    "iso:country":"AU",
    "sg:address":"3 Brewer Rd",
    "sg:city":"Brighton East",
    "sg:classifiers":[
        {
            "category":"Health Services",
            "subcategory":"Health Practitioner",
            "type":"Services"
        }
    ],
    "sg:phone":"+61 3 9599 2266",
    "sg:postcode":"3187",
    "sg:province":"VIC",
    "sg:tags":[
        "physiotherapist"
    ],
    "wof:name":"Club Classic Physiotherapy",
    "wof:placetype":"venue"
},
  "geometry": {"coordinates":[145.024734497,-37.9204711914],"type":"Point"}
}