{
  "type": "Feature",
  "properties": {
    "addr:full":"270 Grand Junction Rd Athol Park SA 5012",
    "addr:housenumber":"270",
    "addr:postcode":"5012",
    "addr:street":"Grand Junction Rd",
    "iso:country":"AU",
    "sg:address":"270 Grand Junction Rd",
    "sg:city":"Athol Park",
    "sg:classifiers":[
        {
            "category":"Wholesale",
            "subcategory":"Furniture",
            "type":"Manufacturing & Wholesale Goods"
        }
    ],
    "sg:phone":"+61 8 8240 4677",
    "sg:postcode":"5012",
    "sg:province":"SA",
    "sg:tags":[
        "wholesaler",
        "mfrs"
    ],
    "wof:name":"Inspire Home Furniture",
    "wof:placetype":"venue"
},
  "geometry": {"coordinates":[138.54391479500001,-34.8509063721],"type":"Point"}
}