{
  "type": "Feature",
  "properties": {
    "addr:full":"6 Napier St Paddington NSW 2021",
    "addr:housenumber":"6",
    "addr:postcode":"2021",
    "addr:street":"Napier St",
    "iso:country":"AU",
    "sg:address":"6 Napier St",
    "sg:city":"Paddington",
    "sg:classifiers":[
        {
            "category":"Arts & Performance",
            "subcategory":"Art Gallery",
            "type":"Entertainment"
        }
    ],
    "sg:phone":"+61 2 9326 0034",
    "sg:postcode":"2021",
    "sg:province":"NSW",
    "wof:name":"Kudos Gallery",
    "wof:placetype":"venue"
},
  "geometry": {"coordinates":[151.219146728,-33.8830795288],"type":"Point"}
}