{
  "type": "Feature",
  "properties": {
    "iso:country":"AU",
    "sg:address":"130 City Rd",
    "sg:city":"Southbank",
    "sg:classifiers":[
        {
            "category":"Autos & Motor Vehicles",
            "subcategory":"Auto Supplies",
            "type":"Retail Goods"
        }
    ],
    "sg:phone":"+61 3 9686 1999",
    "sg:postcode":"3006",
    "sg:province":"VIC",
    "sg:tags":[
        "part",
        "cycles",
        "accessory"
    ],
    "sg:website":"http://www.bmwsouthbank.com.au",
    "wof:name":"Southbank Motorcycles",
    "wof:placetype":"venue"
},
  "geometry": {"coordinates":[144.96340942399999,-37.8229293823],"type":"Point"}
}