{
  "type": "Feature",
  "properties": {
    "addr:full":"193 Esplanade St Aldinga Beach SA 5173",
    "addr:housenumber":"193",
    "addr:postcode":"5173",
    "addr:street":"Esplanade St",
    "iso:country":"AU",
    "sg:address":"193 Esplanade St",
    "sg:city":"Aldinga Beach",
    "sg:classifiers":[
        {
            "category":"Personal",
            "subcategory":"Beauty Salon",
            "type":"Services"
        }
    ],
    "sg:phone":"+61 8 8556 5342",
    "sg:postcode":"5173",
    "sg:province":"SA",
    "sg:tags":[
        "hairdresser"
    ],
    "wof:name":"Beth's Hair Boutique",
    "wof:placetype":"venue"
},
  "geometry": {"coordinates":[138.446166992,-35.2708091736],"type":"Point"}
}