{
  "type": "Feature",
  "properties": {
    "iso:country":"AU",
    "sg:address":"17 Torrens Rd",
    "sg:city":"Riverton",
    "sg:classifiers":[
        {
            "category":"Fast Food",
            "type":"Food & Drink"
        }
    ],
    "sg:phone":"+61 8 8847 2006",
    "sg:postcode":"5412",
    "sg:province":"SA",
    "sg:tags":[
        "away",
        "take"
    ],
    "wof:name":"Riverton Diner",
    "wof:placetype":"venue"
},
  "geometry": {"coordinates":[138.747879028,-34.1555023193],"type":"Point"}
}