{
  "type": "Feature",
  "properties": {
    "addr:full":"Shop 13, Singleton Plaza John Street Singleton 2330 N.S.W Singleton NSW 2330",
    "addr:housenumber":"shop 13 singleton plaza",
    "addr:postcode":"2330;2330",
    "addr:street":"John Street",
    "iso:country":"AU",
    "sg:address":"Shop 13, Singleton Plaza John Street Singleton 2330 N.S.W",
    "sg:city":"Singleton",
    "sg:classifiers":[
        {
            "category":"Retail",
            "subcategory":"Repair Shop",
            "type":"Services"
        }
    ],
    "sg:phone":"+61 2 6572 4844",
    "sg:postcode":"2330",
    "sg:province":"NSW",
    "sg:tags":[
        "handbag"
    ],
    "wof:name":"P.D. Bags",
    "wof:placetype":"venue"
},
  "geometry": {"coordinates":[151.16395600000001,-32.567196],"type":"Point"}
}