{
  "type": "Feature",
  "properties": {
    "addr:full":"Cnr Kline & Wesley Sts Ballarat East VIC 3350",
    "addr:postcode":"3350",
    "addr:street":"Cnr Kline;Sts",
    "iso:country":"AU",
    "sg:address":"Cnr Kline & Wesley Sts",
    "sg:city":"Ballarat East",
    "sg:classifiers":[
        {
            "category":"Personal",
            "subcategory":"Beauty Salon",
            "type":"Services"
        }
    ],
    "sg:phone":"+61 3 5331 1227",
    "sg:postcode":"3350",
    "sg:province":"VIC",
    "sg:tags":[
        "hairdresser"
    ],
    "wof:name":"Studio Six Hairdressing",
    "wof:placetype":"venue"
},
  "geometry": {"coordinates":[143.886078,-37.566685],"type":"Point"}
}