{
  "type": "Feature",
  "properties": {
    "addr:full":"359 Vardys Rd Kings Park NSW 2148",
    "addr:housenumber":"359",
    "addr:postcode":"2148",
    "addr:street":"Vardys Rd",
    "iso:country":"AU",
    "sg:address":"359 Vardys Rd",
    "sg:city":"Kings Park",
    "sg:classifiers":[
        {
            "category":"Building & Trades",
            "subcategory":"Equipment Rental",
            "type":"Services"
        }
    ],
    "sg:phone":"+61 2 9831 5044",
    "sg:postcode":"2148",
    "sg:province":"NSW",
    "sg:tags":[
        "saw"
    ],
    "wof:name":"Gabbett Machinery Pty Ltd",
    "wof:placetype":"venue"
},
  "geometry": {"coordinates":[150.907592773,-33.7463874817],"type":"Point"}
}