{
  "type": "Feature",
  "properties": {
    "addr:full":"10 Beach St Tuncurry NSW 2428",
    "addr:housenumber":"10",
    "addr:postcode":"2428",
    "addr:street":"Beach St",
    "iso:country":"AU",
    "sg:address":"10 Beach St",
    "sg:city":"Tuncurry",
    "sg:classifiers":[
        {
            "category":"Health Services",
            "subcategory":"Optometrist",
            "type":"Services"
        }
    ],
    "sg:phone":"+61 2 6557 2020",
    "sg:postcode":"2428",
    "sg:province":"NSW",
    "wof:name":"Fealy Chris Optometrist",
    "wof:placetype":"venue"
},
  "geometry": {"coordinates":[152.500168,-32.174427],"type":"Point"}
}