{
  "type": "Feature",
  "properties": {
    "addr:full":"140 Carrington St Narara NSW 2250",
    "addr:housenumber":"140",
    "addr:postcode":"2250",
    "addr:street":"Carrington St",
    "iso:country":"AU",
    "sg:address":"140 Carrington St",
    "sg:city":"Narara",
    "sg:classifiers":[
        {
            "category":"Personal",
            "subcategory":"Massage",
            "type":"Services"
        }
    ],
    "sg:phone":"+61 2 4328 2818",
    "sg:postcode":"2250",
    "sg:province":"NSW",
    "sg:tags":[
        "therapy"
    ],
    "wof:name":"Hewett Vicki",
    "wof:placetype":"venue"
},
  "geometry": {"coordinates":[151.34072875999999,-33.4009208679],"type":"Point"}
}