{
  "type": "Feature",
  "properties": {
    "addr:full":"1, 33 Maddox St Alexandria NSW 2015",
    "addr:housenumber":"33",
    "addr:postcode":"2015",
    "addr:street":"1;Maddox St",
    "iso:country":"AU",
    "sg:address":"1, 33 Maddox St",
    "sg:city":"Alexandria",
    "sg:classifiers":[
        {
            "category":"Manufacturing",
            "subcategory":"Tobacco Products",
            "type":"Manufacturing & Wholesale Goods"
        }
    ],
    "sg:phone":"+61 2 9690 2488",
    "sg:postcode":"2015",
    "sg:province":"NSW",
    "sg:tags":[
        "car",
        "truck",
        "cleaning",
        "equipment"
    ],
    "sg:website":"http://www.carkleen.com.au",
    "wof:name":"Car Kleen Australia Pty Ltd",
    "wof:placetype":"venue"
},
  "geometry": {"coordinates":[151.19444274899999,-33.9079284668],"type":"Point"}
}