{
  "type": "Feature",
  "properties": {
    "addr:full":"7 Lampton Ave Derwent Park TAS 7009",
    "addr:housenumber":"7",
    "addr:postcode":"7009",
    "addr:street":"Lampton Ave",
    "iso:country":"AU",
    "sg:address":"7 Lampton Ave",
    "sg:city":"Derwent Park",
    "sg:classifiers":[
        {
            "category":"Government",
            "subcategory":"Fire Station",
            "type":"Public Place"
        }
    ],
    "sg:phone":"+61 3 6272 4155",
    "sg:postcode":"7009",
    "sg:province":"TAS",
    "sg:tags":[
        "spring",
        "shock",
        "absorbers",
        "suspension"
    ],
    "wof:name":"Tasmanian Suspension & Exhaust Services",
    "wof:placetype":"venue"
},
  "geometry": {"coordinates":[147.288330078,-42.835483551],"type":"Point"}
}