{
  "type": "Feature",
  "properties": {
    "iso:country":"AU",
    "sg:address":"Shop 1, 216 Main St",
    "sg:city":"Mornington",
    "sg:classifiers":[
        {
            "category":"Shopping",
            "subcategory":"Jewelry",
            "type":"Retail Goods"
        }
    ],
    "sg:phone":"+61 3 5975 5906",
    "sg:postcode":"3931",
    "sg:province":"VIC",
    "sg:tags":[
        "jeweller"
    ],
    "wof:name":"Mornington Jewellers",
    "wof:placetype":"venue"
},
  "geometry": {"coordinates":[145.04054260300001,-38.2222747803],"type":"Point"}
}