{
  "type": "Feature",
  "properties": {
    "addr:full":"740 Murdering Point Rd Kurrimine Beach QLD 4871",
    "addr:housenumber":"740",
    "addr:postcode":"4871",
    "addr:street":"Murdering Point Rd",
    "iso:country":"AU",
    "sg:address":"740 Murdering Point Rd",
    "sg:city":"Kurrimine Beach",
    "sg:classifiers":[
        {
            "category":"Building & Trades",
            "subcategory":"Construction",
            "type":"Services"
        }
    ],
    "sg:phone":"+61 7 4065 6341",
    "sg:postcode":"4871",
    "sg:province":"QLD",
    "sg:tags":[
        "earth",
        "excavating",
        "moving",
        "contractor"
    ],
    "wof:name":"Azzopardi M J & C M",
    "wof:placetype":"venue"
},
  "geometry": {"coordinates":[146.053100586,-17.7549781799],"type":"Point"}
}