{
  "type": "Feature",
  "properties": {
    "addr:full":"Level 1 10 Station St Cottesloe WA 6011",
    "addr:housenumber":"10",
    "addr:postcode":"6011",
    "addr:street":"Station St",
    "iso:country":"AU",
    "sg:address":"Level 1 10 Station St",
    "sg:city":"Cottesloe",
    "sg:classifiers":[
        {
            "category":"Personal",
            "subcategory":"Beauty Salon",
            "type":"Services"
        }
    ],
    "sg:phone":"+61 8 9384 7528",
    "sg:postcode":"6011",
    "sg:province":"WA",
    "sg:tags":[
        "hairdresser"
    ],
    "wof:name":"Osh Posh Hairdressers",
    "wof:placetype":"venue"
},
  "geometry": {"coordinates":[115.76222991900001,-31.9969558716],"type":"Point"}
}