{
  "type": "Feature",
  "properties": {
    "addr:full":"PO Box 43 Virginia Store Via Winnellie Private Bags NT 0822",
    "addr:postcode":"nt 0822",
    "addr:street":"Via Winnellie Private",
    "iso:country":"AU",
    "sg:address":"PO Box 43",
    "sg:city":"Virginia Store Via Winnellie Private Bags",
    "sg:classifiers":[
        {
            "category":"Building & Trades",
            "subcategory":"Landscaping Services",
            "type":"Services"
        }
    ],
    "sg:phone":"+61 417 801 318",
    "sg:postcode":"0822",
    "sg:province":"NT",
    "sg:tags":[
        "designer",
        "landscape",
        "contractor"
    ],
    "wof:name":"Fence Masters Landscaping",
    "wof:placetype":"venue"
},
  "geometry": {"coordinates":[130.892426,-12.426623],"type":"Point"}
}