{
  "type": "Feature",
  "properties": {
    "iso:country":"AU",
    "sg:address":"Bridge Inn Rd",
    "sg:city":"Wollert",
    "sg:classifiers":[
        {
            "category":"Utilities",
            "subcategory":"Refuse",
            "type":"Services"
        }
    ],
    "sg:phone":"+61 3 9408 1299",
    "sg:postcode":"3750",
    "sg:province":"VIC",
    "sg:tags":[
        "disposal",
        "reduction",
        "waste"
    ],
    "wof:name":"Wollert Landfill",
    "wof:placetype":"venue"
},
  "geometry": {"coordinates":[145.037933,-37.594334],"type":"Point"}
}