{
  "type": "Feature",
  "properties": {
    "addr:full":"10 Hillsborough Rd Charlestown NSW 2290",
    "addr:housenumber":"10",
    "addr:postcode":"2290",
    "addr:street":"Hillsborough Rd",
    "iso:country":"AU",
    "sg:address":"10 Hillsborough Rd",
    "sg:city":"Charlestown",
    "sg:classifiers":[
        {
            "category":"Health Services",
            "subcategory":"Doctor",
            "type":"Services"
        }
    ],
    "sg:phone":"+61 2 4943 9404",
    "sg:postcode":"2290",
    "sg:province":"NSW",
    "sg:tags":[
        "medical",
        "practitioner"
    ],
    "wof:name":"Walsh Bernard A",
    "wof:placetype":"venue"
},
  "geometry": {"coordinates":[151.685256958,-32.9568939209],"type":"Point"}
}