{
  "type": "Feature",
  "properties": {
    "iso:country":"AU",
    "sg:address":"Unit 6/ 226",
    "sg:city":"The Boulevarde Punchbowl",
    "sg:classifiers":[
        {
            "category":"Building & Trades",
            "subcategory":"Construction",
            "type":"Services"
        }
    ],
    "sg:phone":"+61 2 9750 5960",
    "sg:postcode":"2196",
    "sg:province":"NSW",
    "sg:tags":[
        "contractor"
    ],
    "wof:name":"ACM Construction & Maintenance Pty Ltd",
    "wof:placetype":"venue"
},
  "geometry": {"coordinates":[151.05639600000001,-33.92588],"type":"Point"}
}