{
  "type": "Feature",
  "properties": {
    "iso:country":"AU",
    "sg:address":"15 Borg Crs",
    "sg:city":"Scoresby",
    "sg:classifiers":[
        {
            "category":"Structure",
            "subcategory":"Office Building",
            "type":"Public Place"
        }
    ],
    "sg:phone":"+61 3 9763 9401",
    "sg:postcode":"3179",
    "sg:province":"VIC",
    "sg:tags":[
        "slater",
        "tiler",
        "roof"
    ],
    "wof:name":"Gilbert J W",
    "wof:placetype":"venue"
},
  "geometry": {"coordinates":[145.21795654300001,-37.9017715454],"type":"Point"}
}