{
  "type": "Feature",
  "properties": {
    "addr:full":"PO Box 293 Hillarys Private Boxes WA 6923",
    "addr:postcode":"6923",
    "addr:street":"Hillarys",
    "iso:country":"AU",
    "sg:address":"PO Box 293",
    "sg:city":"Hillarys Private Boxes",
    "sg:classifiers":[
        {
            "category":"Professional",
            "subcategory":"Detective & Security Services",
            "type":"Services"
        }
    ],
    "sg:phone":"+61 8 9328 2928",
    "sg:postcode":"6923",
    "sg:province":"WA",
    "sg:tags":[
        "domestic",
        "alarm",
        "commercial",
        "burglar"
    ],
    "wof:name":"Custom Alarm Systems",
    "wof:placetype":"venue"
},
  "geometry": {"coordinates":[115.741539002,-31.809419632],"type":"Point"}
}