{
  "type": "Feature",
  "properties": {
    "addr:full":"83 Melville St Hobart TAS 7000",
    "addr:housenumber":"83",
    "addr:postcode":"7000",
    "addr:street":"Melville St",
    "iso:country":"AU",
    "sg:address":"83 Melville St",
    "sg:city":"Hobart",
    "sg:classifiers":[
        {
            "category":"Building & Trades",
            "subcategory":"Landscaping Services",
            "type":"Services"
        }
    ],
    "sg:phone":"+61 3 6233 7640",
    "sg:postcode":"7000",
    "sg:province":"TAS",
    "sg:tags":[
        "forestry",
        "consultant"
    ],
    "wof:name":"Private Forests Tasmania",
    "wof:placetype":"venue"
},
  "geometry": {"coordinates":[147.31973266599999,-42.8801498413],"type":"Point"}
}