{
  "type": "Feature",
  "properties": {
    "addr:full":"286 Whitehorse Rd Nunawading VIC 3131",
    "addr:housenumber":"286",
    "addr:postcode":"3131",
    "addr:street":"Whitehorse Rd",
    "iso:country":"AU",
    "sg:address":"286 Whitehorse Rd",
    "sg:city":"Nunawading",
    "sg:classifiers":[
        {
            "category":"Shopping",
            "subcategory":"Shoes",
            "type":"Retail Goods"
        }
    ],
    "sg:phone":"+61 3 9894 0811",
    "sg:postcode":"3131",
    "sg:province":"VIC",
    "sg:tags":[
        "footwear"
    ],
    "wof:name":"Brand Smart Outlet Mall",
    "wof:placetype":"venue"
},
  "geometry": {"coordinates":[145.171707153,-37.8186531067],"type":"Point"}
}