{
  "type": "Feature",
  "properties": {
    "iso:country":"AU",
    "sg:address":"14 Bates Crt",
    "sg:city":"Batesford",
    "sg:classifiers":[
        {
            "category":"Personal",
            "subcategory":"Beauty Salon",
            "type":"Services"
        }
    ],
    "sg:phone":"+61 3 5276 1039",
    "sg:postcode":"3221",
    "sg:province":"VIC",
    "sg:tags":[
        "hairdresser"
    ],
    "wof:name":"Anna Ferguson's Hair & Beauty",
    "wof:placetype":"venue"
},
  "geometry": {"coordinates":[144.254059,-38.083645],"type":"Point"}
}