{
  "type": "Feature",
  "properties": {
    "addr:full":"Bexhill Rd Lismore NSW 2480",
    "addr:postcode":"2480",
    "addr:street":"Bexhill Rd",
    "iso:country":"AU",
    "sg:address":"Bexhill Rd",
    "sg:city":"Lismore",
    "sg:classifiers":[
        {
            "category":"Food & Beverages",
            "subcategory":"Fruits & Vegetables",
            "type":"Retail Goods"
        }
    ],
    "sg:phone":"+61 2 6621 6857",
    "sg:postcode":"2480",
    "sg:province":"NSW",
    "sg:tags":[
        "wholesale"
    ],
    "wof:name":"Conte E",
    "wof:placetype":"venue"
},
  "geometry": {"coordinates":[153.27818298299999,-28.8139896393],"type":"Point"}
}