{
  "type": "Feature",
  "properties": {
    "iso:country":"AU",
    "sg:address":"62 Meier Rd",
    "sg:city":"Camira",
    "sg:classifiers":[
        {
            "category":"Utilities",
            "subcategory":"Electric",
            "type":"Services"
        }
    ],
    "sg:phone":"+61 437 765 656",
    "sg:postcode":"4300",
    "sg:province":"QLD",
    "sg:tags":[
        "electrical",
        "contractor"
    ],
    "wof:name":"AAC RKC & Sons Electrical Pty Ltd",
    "wof:placetype":"venue"
},
  "geometry": {"coordinates":[152.915405273,-27.6391143799],"type":"Point"}
}