{
  "type": "Feature",
  "properties": {
    "iso:country":"AU",
    "sg:address":"80 Hume Hwy",
    "sg:city":"Somerton",
    "sg:classifiers":[
        {
            "category":"Wholesale",
            "subcategory":"Machinery & Supplies",
            "type":"Manufacturing & Wholesale Goods"
        }
    ],
    "sg:phone":"+61 3 9308 0055",
    "sg:postcode":"3062",
    "sg:province":"VIC",
    "sg:tags":[
        "bearing",
        "bushing"
    ],
    "wof:name":"Northern Bearing Supplies",
    "wof:placetype":"venue"
},
  "geometry": {"coordinates":[144.950897217,-37.6367797852],"type":"Point"}
}