{
  "type": "Feature",
  "properties": {
    "iso:country":"AU",
    "sg:address":"48 Albert St",
    "sg:city":"Brunswick East",
    "sg:classifiers":[
        {
            "category":"Shopping",
            "subcategory":"Clothing, Apparel, & Fashions",
            "type":"Retail Goods"
        }
    ],
    "sg:phone":"+61 3 9388 2276",
    "sg:postcode":"3057",
    "sg:province":"VIC",
    "sg:tags":[
        "menswear"
    ],
    "wof:name":"Sires Suits & Menswear",
    "wof:placetype":"venue"
},
  "geometry": {"coordinates":[144.97689819300001,-37.7705612183],"type":"Point"}
}