{
  "type": "Feature",
  "properties": {
    "addr:full":"224 Balwyn Rd Balwyn North VIC 3104",
    "addr:housenumber":"224",
    "addr:postcode":"3104",
    "addr:street":"Balwyn Rd",
    "iso:country":"AU",
    "sg:address":"224 Balwyn Rd",
    "sg:city":"Balwyn North",
    "sg:classifiers":[
        {
            "category":"Professional",
            "subcategory":"Employment Agencies",
            "type":"Services"
        }
    ],
    "sg:phone":"+61 3 9857 5713",
    "sg:postcode":"3104",
    "sg:province":"VIC",
    "sg:tags":[
        "entertainer",
        "agent"
    ],
    "wof:name":"Belmore Events",
    "wof:placetype":"venue"
},
  "geometry": {"coordinates":[145.08636474599999,-37.7878227234],"type":"Point"}
}