{
  "type": "Feature",
  "properties": {
    "addr:full":"520 Samford Rd Mitchelton QLD 4053",
    "addr:housenumber":"520",
    "addr:postcode":"4053",
    "addr:street":"Samford Rd",
    "iso:country":"AU",
    "sg:address":"520 Samford Rd",
    "sg:city":"Mitchelton",
    "sg:classifiers":[
        {
            "category":"Retail",
            "subcategory":"Repair Shop",
            "type":"Services"
        }
    ],
    "sg:phone":"+61 7 3355 1774",
    "sg:postcode":"4053",
    "sg:province":"QLD",
    "sg:tags":[
        "mending",
        "clothing",
        "alteration"
    ],
    "wof:name":"Mitchelton Quality Dry Cleaners",
    "wof:placetype":"venue"
},
  "geometry": {"coordinates":[152.97816467300001,-27.4155540466],"type":"Point"}
}