{
  "type": "Feature",
  "properties": {
    "iso:country":"AU",
    "sg:address":"16 Cowell St",
    "sg:city":"Gladesville",
    "sg:classifiers":[
        {
            "category":"Health Services",
            "subcategory":"Doctor",
            "type":"Services"
        }
    ],
    "sg:phone":"+61 2 9879 4722",
    "sg:postcode":"2111",
    "sg:province":"NSW",
    "sg:tags":[
        "medical",
        "practitioner"
    ],
    "wof:name":"Rodley Stephanie",
    "wof:placetype":"venue"
},
  "geometry": {"coordinates":[151.12869262699999,-33.8315505981],"type":"Point"}
}