{
  "type": "Feature",
  "properties": {
    "addr:full":"PO Box 7957 Cairns QLD 4870",
    "addr:postcode":"4870",
    "iso:country":"AU",
    "sg:address":"PO Box 7957",
    "sg:city":"Cairns",
    "sg:classifiers":[
        {
            "category":"Banks & Credit Unions",
            "subcategory":"Investment Brokerage",
            "type":"Services"
        }
    ],
    "sg:phone":"+61 411 274 731",
    "sg:postcode":"4870",
    "sg:province":"QLD",
    "sg:tags":[
        "debt",
        "collection"
    ],
    "wof:name":"Cairns Business Credit Consultants",
    "wof:placetype":"venue"
},
  "geometry": {"coordinates":[145.66958618199999,-17.0185699463],"type":"Point"}
}