{
  "type": "Feature",
  "properties": {
    "iso:country":"AU",
    "sg:address":"10 Raynes St",
    "sg:city":"Caulfield South",
    "sg:classifiers":[
        {
            "category":"Professional",
            "subcategory":"Accounting & Tax Preparation",
            "type":"Services"
        }
    ],
    "sg:phone":"+61 3 9596 2240",
    "sg:postcode":"3162",
    "sg:province":"VIC",
    "sg:tags":[
        "accountant",
        "auditor"
    ],
    "wof:name":"J & F Malter FPA",
    "wof:placetype":"venue"
},
  "geometry": {"coordinates":[145.01918029800001,-37.8962478638],"type":"Point"}
}