{
  "type": "Feature",
  "properties": {
    "addr:full":"U 1/ 52 Hopetoun Ave Canterbury VIC 3126",
    "addr:housenumber":"52",
    "addr:postcode":"3126",
    "addr:street":"Hopetoun Ave",
    "iso:country":"AU",
    "sg:address":"U 1/ 52 Hopetoun Ave",
    "sg:city":"Canterbury",
    "sg:classifiers":[
        {
            "category":"Home & Garden",
            "subcategory":"Furniture",
            "type":"Retail Goods"
        }
    ],
    "sg:phone":"+61 3 9830 4059",
    "sg:postcode":"3126",
    "sg:province":"VIC",
    "sg:tags":[
        "business"
    ],
    "wof:name":"Contract Furnishing Services",
    "wof:placetype":"venue"
},
  "geometry": {"coordinates":[145.07749939000001,-37.8182296753],"type":"Point"}
}