{
  "type": "Feature",
  "properties": {
    "iso:country":"AU",
    "sg:address":"47 Hardey Rd",
    "sg:city":"Wattle Grove",
    "sg:classifiers":[
        {
            "category":"Utilities",
            "subcategory":"Refuse",
            "type":"Services"
        }
    ],
    "sg:phone":"+61 8 9359 2200",
    "sg:postcode":"6107",
    "sg:province":"WA",
    "sg:tags":[
        "remover",
        "rubbish"
    ],
    "wof:name":"Bandicoot Bins",
    "wof:placetype":"venue"
},
  "geometry": {"coordinates":[115.988952637,-31.9929199219],"type":"Point"}
}