{
  "type": "Feature",
  "properties": {
    "addr:full":"543 Lutwyche Rd Lutwyche QLD 4030",
    "addr:housenumber":"543",
    "addr:postcode":"4030",
    "addr:street":"Lutwyche Rd",
    "iso:country":"AU",
    "sg:address":"543 Lutwyche Rd",
    "sg:city":"Lutwyche",
    "sg:classifiers":[
        {
            "category":"Education",
            "subcategory":"Special Training",
            "type":"Public Place"
        }
    ],
    "sg:phone":"+61 7 3857 3311",
    "sg:postcode":"4030",
    "sg:province":"QLD",
    "sg:tags":[
        "development"
    ],
    "wof:name":"Career Guidance Institute Of Australia",
    "wof:placetype":"venue"
},
  "geometry": {"coordinates":[153.03413399999999,-27.421741],"type":"Point"}
}