{
  "type": "Feature",
  "properties": {
    "iso:country":"AU",
    "sg:address":"Shp2/ 86 Central Ave",
    "sg:city":"Oak Flats",
    "sg:classifiers":[
        {
            "category":"Shopping",
            "subcategory":"Bicycles & Sporting Goods",
            "type":"Retail Goods"
        }
    ],
    "sg:phone":"+61 2 4257 3879",
    "sg:postcode":"2529",
    "sg:province":"NSW",
    "sg:tags":[
        "dance",
        "accessory",
        "wear",
        "supply"
    ],
    "wof:name":"Advanced Dance Supplies",
    "wof:placetype":"venue"
},
  "geometry": {"coordinates":[150.81915283199999,-34.5623054504],"type":"Point"}
}