{
  "type": "Feature",
  "properties": {
    "iso:country":"AU",
    "sg:address":"Gateway Plaza Raglan Pde",
    "sg:city":"Warrnambool",
    "sg:classifiers":[
        {
            "category":"Shopping",
            "subcategory":"Jewelry",
            "type":"Retail Goods"
        }
    ],
    "sg:phone":"+61 3 5562 0024",
    "sg:postcode":"3280",
    "sg:province":"VIC",
    "sg:tags":[
        "jeweller"
    ],
    "wof:name":"Kleins",
    "wof:placetype":"venue"
},
  "geometry": {"coordinates":[142.48599243199999,-38.3809890747],"type":"Point"}
}