{
  "type": "Feature",
  "properties": {
    "iso:country":"AU",
    "sg:address":"200- 204 Waldron Rd",
    "sg:city":"Chester Hill",
    "sg:classifiers":[
        {
            "category":"Food & Beverages",
            "subcategory":"Bakery",
            "type":"Retail Goods"
        }
    ],
    "sg:phone":"+61 2 9743 9399",
    "sg:postcode":"2162",
    "sg:province":"NSW",
    "sg:tags":[
        "cake",
        "shop",
        "pastry"
    ],
    "wof:name":"Simply Devine Continental Cakes & Gateauxs Wholesale & Retail Pty Ltd",
    "wof:placetype":"venue"
},
  "geometry": {"coordinates":[150.99893188499999,-33.8826675415],"type":"Point"}
}