{
  "type": "Feature",
  "properties": {
    "iso:country":"AU",
    "sg:address":"3096 Moe-Rawson Rd",
    "sg:city":"Tanjil South",
    "sg:classifiers":[
        {
            "category":"Farming",
            "subcategory":"Farm & Veterinary Services",
            "type":"Manufacturing & Wholesale Goods"
        }
    ],
    "sg:phone":"+61 3 5160 1455",
    "sg:postcode":"3825",
    "sg:province":"VIC",
    "sg:tags":[
        "deer",
        "farmer"
    ],
    "wof:name":"Sinyat Deer Farm",
    "wof:placetype":"venue"
},
  "geometry": {"coordinates":[146.256912,-38.213585],"type":"Point"}
}