{
  "type": "Feature",
  "properties": {
    "addr:full":"13 Godfrey St Walliston WA 6076",
    "addr:housenumber":"13",
    "addr:postcode":"6076",
    "addr:street":"Godfrey St",
    "iso:country":"AU",
    "sg:address":"13 Godfrey St",
    "sg:city":"Walliston",
    "sg:classifiers":[
        {
            "category":"Building & Trades",
            "subcategory":"Plumbing",
            "type":"Services"
        }
    ],
    "sg:phone":"+61 8 9291 6000",
    "sg:postcode":"6076",
    "sg:province":"WA",
    "sg:tags":[
        "plumber",
        "gasfitters"
    ],
    "wof:name":"Jones Plumbing Service",
    "wof:placetype":"venue"
},
  "geometry": {"coordinates":[116.07128906200001,-31.9949989319],"type":"Point"}
}