{
  "type": "Feature",
  "properties": {
    "addr:full":"PO Box 2444 Tuggeranong ACT 2901",
    "addr:postcode":"2901",
    "iso:country":"AU",
    "sg:address":"PO Box 2444",
    "sg:city":"Tuggeranong",
    "sg:classifiers":[
        {
            "category":"Utilities",
            "subcategory":"Electric",
            "type":"Services"
        }
    ],
    "sg:phone":"+61 423 309 833",
    "sg:postcode":"2901",
    "sg:province":"ACT",
    "sg:tags":[
        "electrical",
        "contractor"
    ],
    "wof:name":"Everloch Electrical",
    "wof:placetype":"venue"
},
  "geometry": {"coordinates":[149.05650329599999,-35.4157295227],"type":"Point"}
}