{
  "type": "Feature",
  "properties": {
    "addr:full":"4 King William Rd Wayville SA 5034",
    "addr:housenumber":"4",
    "addr:postcode":"5034",
    "addr:street":"King William Rd",
    "iso:country":"AU",
    "sg:address":"4 King William Rd",
    "sg:city":"Wayville",
    "sg:classifiers":[
        {
            "category":"Health Services",
            "subcategory":"Dentist",
            "type":"Services"
        }
    ],
    "sg:phone":"+61 8 8272 7399",
    "sg:postcode":"5034",
    "sg:province":"SA",
    "wof:name":"Jaunay Tom Dr",
    "wof:placetype":"venue"
},
  "geometry": {"coordinates":[138.59913635300001,-34.9444122314],"type":"Point"}
}