{
  "type": "Feature",
  "properties": {
    "iso:country":"AU",
    "sg:address":"Mayurra Rd",
    "sg:city":"Millicent",
    "sg:classifiers":[
        {
            "category":"Building & Trades",
            "subcategory":"Landscaping Services",
            "type":"Services"
        }
    ],
    "sg:phone":"+61 8 8733 4912",
    "sg:postcode":"5280",
    "sg:province":"SA",
    "sg:tags":[
        "forestry",
        "consultant"
    ],
    "wof:name":"Auspine Limited",
    "wof:placetype":"venue"
},
  "geometry": {"coordinates":[140.31633,-37.609451],"type":"Point"}
}