{
  "type": "Feature",
  "properties": {
    "iso:country":"AU",
    "sg:address":"Kiosk 2, Northcote Plaza, Separation St",
    "sg:city":"Northcote",
    "sg:classifiers":[
        {
            "category":"Shopping",
            "subcategory":"Mobile Phones",
            "type":"Retail Goods"
        }
    ],
    "sg:phone":"+61 13 19 30",
    "sg:postcode":"3070",
    "sg:province":"VIC",
    "sg:tags":[
        "telephone",
        "accessory"
    ],
    "wof:name":"TeleChoice",
    "wof:placetype":"venue"
},
  "geometry": {"coordinates":[145.00198399999999,-37.76963],"type":"Point"}
}