{
  "type": "Feature",
  "properties": {
    "addr:full":"Shop 24 Capalaba Central Shopng Cntr, Moreton Bay Capalaba QLD 4157",
    "addr:housenumber":"shop 24",
    "addr:postcode":"4157",
    "iso:country":"AU",
    "sg:address":"Shop 24 Capalaba Central Shopng Cntr, Moreton Bay",
    "sg:city":"Capalaba",
    "sg:classifiers":[
        {
            "category":"Travel",
            "subcategory":"Travel Agent",
            "type":"Entertainment"
        }
    ],
    "sg:phone":"+61 13 18 66",
    "sg:postcode":"4157",
    "sg:province":"QLD",
    "sg:tags":[
        "consultant"
    ],
    "wof:name":"Flight Centre",
    "wof:placetype":"venue"
},
  "geometry": {"coordinates":[153.199981689,-27.5226707458],"type":"Point"}
}