{
  "type": "Feature",
  "properties": {
    "addr:full":"Shop 2049 Westfield Carindale QLD 4152",
    "addr:housenumber":"2049",
    "addr:postcode":"4152",
    "addr:street":"Westfield",
    "iso:country":"AU",
    "sg:address":"Shop 2049",
    "sg:city":"Westfield Carindale",
    "sg:classifiers":[
        {
            "category":"Health Services",
            "subcategory":"Optometrist",
            "type":"Services"
        }
    ],
    "sg:phone":"+61 7 3395 4900",
    "sg:postcode":"4152",
    "sg:province":"QLD",
    "wof:name":"Premier Optique",
    "wof:placetype":"venue"
},
  "geometry": {"coordinates":[153.10316467300001,-27.5040683746],"type":"Point"}
}