{
  "type": "Feature",
  "properties": {
    "addr:full":"86 Maple Dr Andergrove QLD 4740",
    "addr:housenumber":"86",
    "addr:postcode":"4740",
    "addr:street":"Maple Dr",
    "iso:country":"AU",
    "sg:address":"86 Maple Dr",
    "sg:city":"Andergrove",
    "sg:classifiers":[
        {
            "category":"Building & Trades",
            "subcategory":"Pest Control",
            "type":"Services"
        }
    ],
    "sg:phone":"+61 417 734 102",
    "sg:postcode":"4740",
    "sg:province":"QLD",
    "wof:name":"White Ants",
    "wof:placetype":"venue"
},
  "geometry": {"coordinates":[149.18810999999999,-21.089535],"type":"Point"}
}