{
  "type": "Feature",
  "properties": {
    "addr:full":"\"Park Village\" Horizon Drv Middle Park QLD 4074",
    "addr:postcode":"4074",
    "addr:street":"Horizon Drv",
    "iso:country":"AU",
    "sg:address":"\"Park Village\" Horizon Drv",
    "sg:city":"Middle Park",
    "sg:classifiers":[
        {
            "category":"Health Services",
            "subcategory":"Dentist",
            "type":"Services"
        }
    ],
    "sg:phone":"+61 7 3210 1418",
    "sg:postcode":"4074",
    "sg:province":"QLD",
    "sg:tags":[
        "qld",
        "orthodontist"
    ],
    "wof:name":"Kulig Martha",
    "wof:placetype":"venue"
},
  "geometry": {"coordinates":[152.928466797,-27.5555896759],"type":"Point"}
}