{
  "type": "Feature",
  "properties": {
    "addr:full":"Shop 38 Westfield Carousel Shoppingtown Cannington WA 6107",
    "addr:housenumber":"shop 38;shoppingtown",
    "addr:postcode":"6107",
    "addr:street":"Westfield Carousel",
    "iso:country":"AU",
    "sg:address":"Shop 38",
    "sg:city":"Westfield Carousel Shoppingtown Cannington",
    "sg:classifiers":[
        {
            "category":"Shopping",
            "subcategory":"Clothing, Apparel, & Fashions",
            "type":"Retail Goods"
        }
    ],
    "sg:phone":"+61 8 9356 2408",
    "sg:postcode":"6107",
    "sg:province":"WA",
    "sg:tags":[
        "lingerie",
        "hosiery",
        "sleepwear"
    ],
    "wof:name":"Bras &#039;N&#039; Things",
    "wof:placetype":"venue"
},
  "geometry": {"coordinates":[115.994178772,-32.0480461121],"type":"Point"}
}