{
  "type": "Feature",
  "properties": {
    "addr:full":"232 Burwood Rd Croydon Park NSW 2133",
    "addr:housenumber":"232",
    "addr:postcode":"2133",
    "addr:street":"Burwood Rd",
    "iso:country":"AU",
    "sg:address":"232 Burwood Rd",
    "sg:city":"Croydon Park",
    "sg:classifiers":[
        {
            "category":"Shopping",
            "subcategory":"Clothing, Apparel, & Fashions",
            "type":"Retail Goods"
        }
    ],
    "sg:phone":"+61 2 9744 3429",
    "sg:postcode":"2133",
    "sg:province":"NSW",
    "sg:tags":[
        "recycled",
        "clothing"
    ],
    "wof:name":"After-a-Fashion",
    "wof:placetype":"venue"
},
  "geometry": {"coordinates":[151.09959411599999,-33.9017181396],"type":"Point"}
}