{
  "type": "Feature",
  "properties": {
    "addr:full":"PO Box 356 Joondalup DC WA 6919",
    "addr:postcode":"6919",
    "iso:country":"AU",
    "sg:address":"PO Box 356",
    "sg:city":"Joondalup DC",
    "sg:classifiers":[
        {
            "category":"Professional",
            "subcategory":"Business Services",
            "type":"Services"
        }
    ],
    "sg:phone":"+61 8 9305 3338",
    "sg:postcode":"6919",
    "sg:province":"WA",
    "sg:tags":[
        "management",
        "event"
    ],
    "wof:name":"Jolin Events Management",
    "wof:placetype":"venue"
},
  "geometry": {"coordinates":[115.769889831,-31.7465190887],"type":"Point"}
}