{
  "type": "Feature",
  "properties": {
    "addr:full":"19 Grant St Bacchus Marsh VIC 3340",
    "addr:housenumber":"19",
    "addr:postcode":"3340",
    "addr:street":"Grant St",
    "iso:country":"AU",
    "sg:address":"19 Grant St",
    "sg:city":"Bacchus Marsh",
    "sg:classifiers":[
        {
            "category":"Professional",
            "subcategory":"Accounting & Tax Preparation",
            "type":"Services"
        }
    ],
    "sg:phone":"+61 3 5367 3063",
    "sg:postcode":"3340",
    "sg:province":"VIC",
    "sg:tags":[
        "accountant",
        "auditor"
    ],
    "wof:name":"Daniel M Watson & Co",
    "wof:placetype":"venue"
},
  "geometry": {"coordinates":[144.43490600000001,-37.677006],"type":"Point"}
}