{
  "type": "Feature",
  "properties": {
    "addr:full":"Shop 8/ 142 Hub Drv Aberfoyle Park SA 5159",
    "addr:housenumber":"shop 8 / 142",
    "addr:postcode":"5159",
    "addr:street":"Hub Drv",
    "iso:country":"AU",
    "sg:address":"Shop 8/ 142 Hub Drv",
    "sg:city":"Aberfoyle Park",
    "sg:classifiers":[
        {
            "category":"Fast Food",
            "type":"Food & Drink"
        }
    ],
    "sg:phone":"+61 8 8270 7333",
    "sg:postcode":"5159",
    "sg:province":"SA",
    "sg:tags":[
        "away",
        "take"
    ],
    "wof:name":"Marcellina Pizza Bar Restaurant",
    "wof:placetype":"venue"
},
  "geometry": {"coordinates":[138.595611572,-35.0758171082],"type":"Point"}
}