{
  "type": "Feature",
  "properties": {
    "iso:country":"AU",
    "sg:address":"1st Floor 333 King William St",
    "sg:city":"Adelaide",
    "sg:classifiers":[
        {
            "category":"Home & Garden",
            "subcategory":"Household Appliances",
            "type":"Retail Goods"
        }
    ],
    "sg:phone":"+61 8 8212 7000",
    "sg:postcode":"5000",
    "sg:province":"SA",
    "sg:tags":[
        "heating",
        "system"
    ],
    "wof:name":"Cannon Gas Log Heaters",
    "wof:placetype":"venue"
},
  "geometry": {"coordinates":[138.59996032699999,-34.9320755005],"type":"Point"}
}