{
  "type": "Feature",
  "properties": {
    "addr:full":"PO Box 930 Buderim QLD 4556",
    "addr:postcode":"4556",
    "iso:country":"AU",
    "sg:address":"PO Box 930",
    "sg:city":"Buderim",
    "sg:classifiers":[
        {
            "category":"Building & Trades",
            "subcategory":"Construction",
            "type":"Services"
        }
    ],
    "sg:phone":"+61 7 5452 5745",
    "sg:postcode":"4556",
    "sg:province":"QLD",
    "sg:tags":[
        "plasterboard",
        "plasterer",
        "fixer"
    ],
    "wof:name":"St George Interior Linings",
    "wof:placetype":"venue"
},
  "geometry": {"coordinates":[153.09310913100001,-26.6773891449],"type":"Point"}
}