{
  "type": "Feature",
  "properties": {
    "addr:full":"Shop 2040, Westfield Southland Shoppingtown, 1239- Cheltenham VIC 3192",
    "addr:housenumber":"2040;1239",
    "addr:postcode":"shoppingtown;3192",
    "iso:country":"AU",
    "sg:address":"Shop 2040, Westfield Southland Shoppingtown, 1239-",
    "sg:city":"Cheltenham",
    "sg:classifiers":[
        {
            "category":"Shopping",
            "subcategory":"Jewelry",
            "type":"Retail Goods"
        }
    ],
    "sg:phone":"+61 3 9583 0200",
    "sg:postcode":"3192",
    "sg:province":"VIC",
    "sg:tags":[
        "jeweller"
    ],
    "wof:name":"Zamels",
    "wof:placetype":"venue"
},
  "geometry": {"coordinates":[145.052810669,-37.9579963684],"type":"Point"}
}