{
  "type": "Feature",
  "properties": {
    "addr:full":"PO Box 405 Henley Beach SA 5022",
    "addr:postcode":"5022",
    "iso:country":"AU",
    "sg:address":"PO Box 405",
    "sg:city":"Henley Beach",
    "sg:classifiers":[
        {
            "category":"Arena",
            "subcategory":"Sports Club",
            "type":"Entertainment"
        }
    ],
    "sg:phone":"+61 418 845 334",
    "sg:postcode":"5022",
    "sg:province":"SA",
    "sg:tags":[
        "defence",
        "supply",
        "self",
        "instruction",
        "martial art"
    ],
    "wof:name":"Doc Pares",
    "wof:placetype":"venue"
},
  "geometry": {"coordinates":[138.49435424800001,-34.9197387695],"type":"Point"}
}