{
  "type": "Feature",
  "properties": {
    "addr:full":"41 Mount Barker Rd Stirling SA 5152",
    "addr:housenumber":"41",
    "addr:postcode":"5152",
    "addr:street":"Mount Barker Rd",
    "iso:country":"AU",
    "sg:address":"41 Mount Barker Rd",
    "sg:city":"Stirling",
    "sg:classifiers":[
        {
            "category":"Banks & Credit Unions",
            "subcategory":"Bank",
            "type":"Services"
        }
    ],
    "sg:phone":"+61 13 20 32",
    "sg:postcode":"5152",
    "sg:province":"SA",
    "wof:name":"Westpac",
    "wof:placetype":"venue"
},
  "geometry": {"coordinates":[138.72184753400001,-35.007900238],"type":"Point"}
}