{
  "type": "Feature",
  "properties": {
    "iso:country":"AU",
    "sg:address":"362 High St",
    "sg:city":"Templestowe Lower",
    "sg:classifiers":[
        {
            "category":"Health Services",
            "subcategory":"Dentist",
            "type":"Services"
        }
    ],
    "sg:phone":"+61 3 9850 3589",
    "sg:postcode":"3107",
    "sg:province":"VIC",
    "wof:name":"Darrer J R",
    "wof:placetype":"venue"
},
  "geometry": {"coordinates":[145.118865967,-37.7599182129],"type":"Point"}
}