{
  "type": "Feature",
  "properties": {
    "addr:full":"9 Rees St O'Connor WA 6163",
    "addr:housenumber":"9",
    "addr:postcode":"6163",
    "addr:street":"Rees St",
    "iso:country":"AU",
    "sg:address":"9 Rees St",
    "sg:city":"O'Connor",
    "sg:classifiers":[
        {
            "category":"Professional",
            "subcategory":"Research",
            "type":"Services"
        }
    ],
    "sg:phone":"+61 8 9337 7370",
    "sg:postcode":"6163",
    "sg:province":"WA",
    "sg:tags":[
        "pearler"
    ],
    "wof:name":"Pearling Technologies",
    "wof:placetype":"venue"
},
  "geometry": {"coordinates":[115.79270200000001,-32.061695],"type":"Point"}
}