{
  "type": "Feature",
  "properties": {
    "addr:full":"Ste6/15-17 Forest Rd Hurstville NSW 2220",
    "addr:housenumber":"15-17",
    "addr:postcode":"2220",
    "addr:street":"Forest Rd",
    "iso:country":"AU",
    "sg:address":"Ste6/15-17 Forest Rd",
    "sg:city":"Hurstville",
    "sg:classifiers":[
        {
            "category":"Banks & Credit Unions",
            "subcategory":"Investment Brokerage",
            "type":"Services"
        }
    ],
    "sg:phone":"+61 2 9588 6383",
    "sg:postcode":"2220",
    "sg:province":"NSW",
    "wof:name":"Australian Investment Strategies Pty Ltd",
    "wof:placetype":"venue"
},
  "geometry": {"coordinates":[151.104812622,-33.9676818848],"type":"Point"}
}