{
  "type": "Feature",
  "properties": {
    "addr:full":"64 Regent St Redfern NSW 2016",
    "addr:housenumber":"64",
    "addr:postcode":"2016",
    "addr:street":"Regent St",
    "iso:country":"AU",
    "sg:address":"64 Regent St",
    "sg:city":"Redfern",
    "sg:classifiers":[
        {
            "category":"Professional",
            "subcategory":"Employment Agencies",
            "type":"Services"
        }
    ],
    "sg:phone":"+61 2 8399 0888",
    "sg:postcode":"2016",
    "sg:province":"NSW",
    "wof:name":"Waverley Action For Youth Services (WAYS)",
    "wof:placetype":"venue"
},
  "geometry": {"coordinates":[151.200241089,-33.8926086426],"type":"Point"}
}