{
  "type": "Feature",
  "properties": {
    "iso:country":"AU",
    "sg:address":"10 Bridge St",
    "sg:city":"Eltham",
    "sg:classifiers":[
        {
            "category":"Structure",
            "subcategory":"Bridge",
            "type":"Public Place"
        }
    ],
    "sg:phone":"+61 3 9431 4444",
    "sg:postcode":"3095",
    "sg:province":"VIC",
    "sg:tags":[
        "chainsaw",
        "brushcutters"
    ],
    "wof:name":"Eltham Hire",
    "wof:placetype":"venue"
},
  "geometry": {"coordinates":[145.139160156,-37.7182998657],"type":"Point"}
}