{
  "type": "Feature",
  "properties": {
    "addr:full":"3 Wilkinson Rd Para Hills SA 5096",
    "addr:housenumber":"3",
    "addr:postcode":"5096",
    "addr:street":"Wilkinson Rd Para",
    "iso:country":"AU",
    "sg:address":"3 Wilkinson Rd",
    "sg:city":"Para Hills",
    "sg:classifiers":[
        {
            "category":"Banks & Credit Unions",
            "subcategory":"Bank",
            "type":"Services"
        }
    ],
    "sg:phone":"+61 8 8264 7011",
    "sg:postcode":"5096",
    "sg:province":"SA",
    "wof:name":"Commonwealth Bank Of Australia",
    "wof:placetype":"venue"
},
  "geometry": {"coordinates":[138.652832031,-34.8095626831],"type":"Point"}
}