{
  "type": "Feature",
  "properties": {
    "addr:full":"24 Philip St Hawthorne QLD 4171",
    "addr:housenumber":"24",
    "addr:postcode":"4171",
    "addr:street":"Philip St",
    "iso:country":"AU",
    "sg:address":"24 Philip St",
    "sg:city":"Hawthorne",
    "sg:classifiers":[
        {
            "category":"Professional",
            "subcategory":"Employment Agencies",
            "type":"Services"
        }
    ],
    "sg:phone":"+61 7 3395 8300",
    "sg:postcode":"4171",
    "sg:province":"QLD",
    "sg:tags":[
        "provider",
        "internet"
    ],
    "wof:name":"S & A E 1 Media",
    "wof:placetype":"venue"
},
  "geometry": {"coordinates":[153.05986023,-27.4708900452],"type":"Point"}
}