{
  "type": "Feature",
  "properties": {
    "addr:full":"122 Yala Rd Bangor NSW 2234",
    "addr:housenumber":"122",
    "addr:postcode":"2234",
    "addr:street":"Yala Rd",
    "iso:country":"AU",
    "sg:address":"122 Yala Rd",
    "sg:city":"Bangor",
    "sg:classifiers":[
        {
            "category":"Building & Trades",
            "subcategory":"Construction",
            "type":"Services"
        }
    ],
    "sg:phone":"+61 2 9543 2629",
    "sg:postcode":"2234",
    "sg:province":"NSW",
    "sg:tags":[
        "installation",
        "air conditioning"
    ],
    "wof:name":"A Mark Air",
    "wof:placetype":"venue"
},
  "geometry": {"coordinates":[151.03143310600001,-34.0171890259],"type":"Point"}
}