{
  "type": "Feature",
  "properties": {
    "addr:full":"32 Inglis St Boyup Brook WA 6244",
    "addr:housenumber":"32",
    "addr:postcode":"6244",
    "addr:street":"Inglis St",
    "iso:country":"AU",
    "sg:address":"32 Inglis St",
    "sg:city":"Boyup Brook",
    "sg:classifiers":[
        {
            "category":"Commercial Area",
            "type":"Public Place"
        }
    ],
    "sg:phone":"+61 8 9765 1116",
    "sg:postcode":"6244",
    "sg:province":"WA",
    "sg:tags":[
        "heavy",
        "carrier"
    ],
    "wof:name":"Atherton T M & Co",
    "wof:placetype":"venue"
},
  "geometry": {"coordinates":[116.38709258999999,-33.8354110718],"type":"Point"}
}