{
  "type": "Feature",
  "properties": {
    "iso:country":"AU",
    "sg:address":"16 Railway St",
    "sg:city":"Southport",
    "sg:classifiers":[
        {
            "category":"Organizations",
            "subcategory":"Non-profit Organization",
            "type":"Services"
        }
    ],
    "sg:phone":"+61 7 5564 0655",
    "sg:postcode":"4215",
    "sg:province":"QLD",
    "sg:tags":[
        "support",
        "disability",
        "organisation"
    ],
    "wof:name":"Gold Coast Family Support Group",
    "wof:placetype":"venue"
},
  "geometry": {"coordinates":[153.41192626899999,-27.9629592896],"type":"Point"}
}