{
  "type": "Feature",
  "properties": {
    "addr:full":"Suite 1, Forum Centre, 242 Pacific Hwy Charlestown NSW 2290",
    "addr:housenumber":"242",
    "addr:postcode":"2290",
    "addr:street":"Pacific Hwy",
    "iso:country":"AU",
    "sg:address":"Suite 1, Forum Centre, 242 Pacific Hwy",
    "sg:city":"Charlestown",
    "sg:classifiers":[
        {
            "category":"Banks & Credit Unions",
            "subcategory":"Financial Services",
            "type":"Services"
        }
    ],
    "sg:phone":"+61 1800 025 241",
    "sg:postcode":"2290",
    "sg:province":"NSW",
    "sg:tags":[
        "annuity",
        "rollover",
        "superannuation",
        "consultant"
    ],
    "wof:name":"Nationwide Superannuation Fund",
    "wof:placetype":"venue"
},
  "geometry": {"coordinates":[151.69879150400001,-32.9593963623],"type":"Point"}
}