{
  "type": "Feature",
  "properties": {
    "addr:full":"8 Jones Rd Capalaba QLD 4157",
    "addr:housenumber":"8",
    "addr:postcode":"4157",
    "addr:street":"Jones Rd",
    "iso:country":"AU",
    "sg:address":"8 Jones Rd",
    "sg:city":"Capalaba",
    "sg:classifiers":[
        {
            "category":"Building & Trades",
            "subcategory":"Equipment Rental",
            "type":"Services"
        }
    ],
    "sg:phone":"+61 7 3823 3504",
    "sg:postcode":"4157",
    "sg:province":"QLD",
    "sg:tags":[
        "demolition",
        "contractor"
    ],
    "wof:name":"Terrapins Pty Ltd",
    "wof:placetype":"venue"
},
  "geometry": {"coordinates":[153.20323181099999,-27.5145721436],"type":"Point"}
}