{
  "type": "Feature",
  "properties": {
    "addr:full":"Sippy Creek Rd Tanawha QLD 4556",
    "addr:postcode":"4556",
    "addr:street":"Creek Rd",
    "iso:country":"AU",
    "sg:address":"Sippy Creek Rd",
    "sg:city":"Tanawha",
    "sg:classifiers":[
        {
            "category":"Building & Trades",
            "subcategory":"Cleaning & Sanitation",
            "type":"Services"
        }
    ],
    "sg:phone":"+61 7 5439 6491",
    "sg:postcode":"4556",
    "sg:province":"QLD",
    "sg:tags":[
        "tank",
        "septic"
    ],
    "wof:name":"Mann Waste Management Pty Ltd",
    "wof:placetype":"venue"
},
  "geometry": {"coordinates":[153.04258727999999,-26.7218494415],"type":"Point"}
}