{
  "type": "Feature",
  "properties": {
    "addr:full":"PO Box 72 Terranora NSW 2486",
    "addr:postcode":"2486",
    "iso:country":"AU",
    "sg:address":"PO Box 72",
    "sg:city":"Terranora",
    "sg:classifiers":[
        {
            "category":"Professional",
            "subcategory":"Business Services",
            "type":"Services"
        }
    ],
    "sg:phone":"+61 409 527 735",
    "sg:postcode":"2486",
    "sg:province":"NSW",
    "sg:tags":[
        "management",
        "event"
    ],
    "wof:name":"Exceptional Events Pty Ltd",
    "wof:placetype":"venue"
},
  "geometry": {"coordinates":[153.504364014,-28.2403507233],"type":"Point"}
}