{
  "type": "Feature",
  "properties": {
    "addr:full":"20 Groveland Crt Isabella Plains ACT 2905",
    "addr:housenumber":"20",
    "addr:postcode":"2905",
    "addr:street":"Groveland Crt Isabella",
    "iso:country":"AU",
    "sg:address":"20 Groveland Crt",
    "sg:city":"Isabella Plains",
    "sg:classifiers":[
        {
            "category":"Home & Garden",
            "subcategory":"Carpets & Floor Coverings",
            "type":"Retail Goods"
        }
    ],
    "sg:phone":"+61 402 790 086",
    "sg:postcode":"2905",
    "sg:province":"ACT",
    "sg:tags":[
        "tile",
        "wall",
        "layer"
    ],
    "wof:name":"Can-Tile",
    "wof:placetype":"venue"
},
  "geometry": {"coordinates":[149.09919738799999,-35.4301795959],"type":"Point"}
}