{
  "type": "Feature",
  "properties": {
    "addr:full":"Princess Mary St St Marys NSW 2760",
    "addr:postcode":"2760",
    "addr:street":"Mary St",
    "iso:country":"AU",
    "sg:address":"Princess Mary St St",
    "sg:city":"Marys",
    "sg:classifiers":[
        {
            "category":"Education",
            "subcategory":"School",
            "type":"Public Place"
        }
    ],
    "sg:phone":"+61 2 9623 1968",
    "sg:postcode":"2760",
    "sg:province":"NSW",
    "sg:tags":[
        "state",
        "-",
        "nsw"
    ],
    "wof:name":"St Marys Primary School",
    "wof:placetype":"venue"
},
  "geometry": {"coordinates":[150.77024841299999,-33.7690505981],"type":"Point"}
}