{
  "type": "Feature",
  "properties": {
    "addr:full":"Suite 6/Level 2 32a Oxford St Darlinghurst NSW 2010",
    "addr:postcode":"2010",
    "addr:street":"Oxford St",
    "iso:country":"AU",
    "sg:address":"Suite 6/Level 2 32a Oxford St",
    "sg:city":"Darlinghurst",
    "sg:classifiers":[
        {
            "category":"Professional",
            "subcategory":"Computer Services",
            "type":"Services"
        }
    ],
    "sg:phone":"+61 2 9339 8200",
    "sg:postcode":"2010",
    "sg:province":"NSW",
    "sg:tags":[
        "information"
    ],
    "wof:name":"Australian Property Monitors",
    "wof:placetype":"venue"
},
  "geometry": {"coordinates":[151.213623047,-33.8776168823],"type":"Point"}
}