{
  "type": "Feature",
  "properties": {
    "addr:full":"4 Booralie Rd Terrey Hills NSW 2084",
    "addr:housenumber":"4",
    "addr:postcode":"2084",
    "addr:street":"Booralie Rd",
    "iso:country":"AU",
    "sg:address":"4 Booralie Rd",
    "sg:city":"Terrey Hills",
    "sg:classifiers":[
        {
            "category":"Food & Beverages",
            "subcategory":"Supermarket",
            "type":"Retail Goods"
        }
    ],
    "sg:phone":"+61 2 9450 1747",
    "sg:postcode":"2084",
    "sg:province":"NSW",
    "sg:tags":[
        "grocery",
        "store"
    ],
    "wof:name":"Terrey Hills Supermarket",
    "wof:placetype":"venue"
},
  "geometry": {"coordinates":[151.22833251899999,-33.6832695007],"type":"Point"}
}