{
  "type": "Feature",
  "properties": {
    "addr:full":"455 Bluff Rd Hampton VIC 3188",
    "addr:housenumber":"455",
    "addr:postcode":"3188",
    "addr:street":"Bluff Rd",
    "iso:country":"AU",
    "sg:address":"455 Bluff Rd",
    "sg:city":"Hampton",
    "sg:classifiers":[
        {
            "category":"Social Services",
            "subcategory":"Retirement Home",
            "type":"Services"
        }
    ],
    "sg:phone":"+61 1300 655 748",
    "sg:postcode":"3188",
    "sg:province":"VIC",
    "sg:tags":[
        "village"
    ],
    "wof:name":"Premier Assisted Living",
    "wof:placetype":"venue"
},
  "geometry": {"coordinates":[145.02366638199999,-37.9374313354],"type":"Point"}
}