{
  "type": "Feature",
  "properties": {
    "addr:full":"388 Queen St Brisbane QLD 4000",
    "addr:housenumber":"388",
    "addr:postcode":"4000",
    "addr:street":"Queen St",
    "iso:country":"AU",
    "sg:address":"388 Queen St",
    "sg:city":"Brisbane",
    "sg:classifiers":[
        {
            "category":"Banks & Credit Unions",
            "subcategory":"Financial Services",
            "type":"Services"
        }
    ],
    "sg:phone":"+61 7 3221 7399",
    "sg:postcode":"4000",
    "sg:province":"QLD",
    "sg:tags":[
        "loan",
        "finance",
        "mortgage"
    ],
    "wof:name":"RESI Mortgage Corporation",
    "wof:placetype":"venue"
},
  "geometry": {"coordinates":[153.03038024899999,-27.4654502869],"type":"Point"}
}