{
  "type": "Feature",
  "properties": {
    "addr:full":"C/- 29 Adelong Crt Morayfield QLD 4506",
    "addr:housenumber":"29",
    "addr:postcode":"4506",
    "addr:street":"C /;Adelong Crt",
    "iso:country":"AU",
    "sg:address":"C/- 29 Adelong Crt",
    "sg:city":"Morayfield",
    "sg:classifiers":[
        {
            "category":"Education",
            "subcategory":"Dance Studio",
            "type":"Public Place"
        }
    ],
    "sg:phone":"+61 412 427 933",
    "sg:postcode":"4506",
    "sg:province":"QLD",
    "sg:tags":[
        "venue",
        "tuition"
    ],
    "wof:name":"B.J.P. Physical Culture Association",
    "wof:placetype":"venue"
},
  "geometry": {"coordinates":[152.919433594,-27.130027771],"type":"Point"}
}