{
  "type": "Feature",
  "properties": {
    "addr:full":"Ste8/ 857 Doncaster Rd Doncaster VIC 3108",
    "addr:housenumber":"857",
    "addr:postcode":"3108",
    "addr:street":"Doncaster Rd",
    "iso:country":"AU",
    "sg:address":"Ste8/ 857 Doncaster Rd",
    "sg:city":"Doncaster",
    "sg:classifiers":[
        {
            "category":"Building & Trades",
            "subcategory":"Construction",
            "type":"Services"
        }
    ],
    "sg:phone":"+61 3 9848 9377",
    "sg:postcode":"3108",
    "sg:province":"VIC",
    "sg:tags":[
        "contractor"
    ],
    "wof:name":"Technique Construction Group Ltd",
    "wof:placetype":"venue"
},
  "geometry": {"coordinates":[145.14389038100001,-37.787197113],"type":"Point"}
}