{
  "type": "Feature",
  "properties": {
    "addr:full":"135 Keys Rd Moorabbin VIC 3189",
    "addr:housenumber":"135",
    "addr:postcode":"3189",
    "addr:street":"Keys Rd",
    "iso:country":"AU",
    "sg:address":"135 Keys Rd",
    "sg:city":"Moorabbin",
    "sg:classifiers":[
        {
            "category":"Shopping",
            "subcategory":"Gifts & Souvenirs",
            "type":"Retail Goods"
        }
    ],
    "sg:phone":"+61 3 9555 9706",
    "sg:postcode":"3189",
    "sg:province":"VIC",
    "sg:tags":[
        "shop",
        "supply"
    ],
    "wof:name":"Wendy Importer & Exporter Company",
    "wof:placetype":"venue"
},
  "geometry": {"coordinates":[145.07351684599999,-37.9492263794],"type":"Point"}
}