{
  "type": "Feature",
  "properties": {
    "iso:country":"AU",
    "sg:address":"40 Kings Rd",
    "sg:city":"St Albans",
    "sg:classifiers":[
        {
            "category":"Home & Garden",
            "subcategory":"Garden Supply",
            "type":"Retail Goods"
        }
    ],
    "sg:phone":"+61 3 9310 8378",
    "sg:postcode":"3021",
    "sg:province":"VIC",
    "sg:tags":[
        "statuary",
        "fountains",
        "sundial"
    ],
    "wof:name":"Along the Garden Path Garden Ornaments",
    "wof:placetype":"venue"
},
  "geometry": {"coordinates":[144.780365,-37.738266],"type":"Point"}
}