{
  "type": "Feature",
  "properties": {
    "addr:full":"1853 Lytton Rd Lytton QLD 4178",
    "addr:housenumber":"1853",
    "addr:postcode":"4178",
    "addr:street":"Lytton Rd",
    "iso:country":"AU",
    "sg:address":"1853 Lytton Rd",
    "sg:city":"Lytton",
    "sg:classifiers":[
        {
            "category":"Autos & Motor Vehicles",
            "subcategory":"Boat Sales",
            "type":"Retail Goods"
        }
    ],
    "sg:phone":"+61 7 3893 4215",
    "sg:postcode":"4178",
    "sg:province":"QLD",
    "sg:tags":[
        "builder",
        "yacht",
        "repairer"
    ],
    "wof:name":"Bayside Boats & Spars",
    "wof:placetype":"venue"
},
  "geometry": {"coordinates":[153.14680480999999,-27.4236087799],"type":"Point"}
}