{
  "type": "Feature",
  "properties": {
    "addr:full":"11 Johnston St Alexandra VIC 3714",
    "addr:housenumber":"11",
    "addr:postcode":"3714",
    "addr:street":"Johnston St",
    "iso:country":"AU",
    "sg:address":"11 Johnston St",
    "sg:city":"Alexandra",
    "sg:classifiers":[
        {
            "category":"Building & Trades",
            "subcategory":"Plumbing",
            "type":"Services"
        }
    ],
    "sg:phone":"+61 3 5772 1738",
    "sg:postcode":"3714",
    "sg:province":"VIC",
    "sg:tags":[
        "plumber",
        "gasfitters"
    ],
    "wof:name":"Richards M J",
    "wof:placetype":"venue"
},
  "geometry": {"coordinates":[145.706939697,-37.1869697571],"type":"Point"}
}