{
  "type": "Feature",
  "properties": {
    "addr:full":"701 Majura La Pialligo ACT 2609",
    "addr:housenumber":"701",
    "addr:postcode":"2609",
    "addr:street":"Majura La",
    "iso:country":"AU",
    "sg:address":"701 Majura La",
    "sg:city":"Pialligo",
    "sg:classifiers":[
        {
            "category":"Social Services",
            "subcategory":"Adult Care",
            "type":"Services"
        }
    ],
    "sg:phone":"+61 412 486 757",
    "sg:postcode":"2609",
    "sg:province":"ACT",
    "sg:tags":[
        "towing"
    ],
    "wof:name":"Quickeze Towing",
    "wof:placetype":"venue"
},
  "geometry": {"coordinates":[149.183151245,-35.2987861633],"type":"Point"}
}