{
  "type": "Feature",
  "properties": {
    "addr:full":"Lvl3/ 77 William St East Sydney NSW 2010",
    "addr:housenumber":"77",
    "addr:postcode":"2010",
    "addr:street":"William St East",
    "iso:country":"AU",
    "sg:address":"Lvl3/ 77 William St",
    "sg:city":"East Sydney",
    "sg:classifiers":[
        {
            "category":"Professional",
            "subcategory":"Art Services",
            "type":"Services"
        }
    ],
    "sg:phone":"+61 2 9357 1751",
    "sg:postcode":"2010",
    "sg:province":"NSW",
    "sg:tags":[
        "graphic",
        "designer"
    ],
    "wof:name":"Design Animals",
    "wof:placetype":"venue"
},
  "geometry": {"coordinates":[151.215576172,-33.8743972778],"type":"Point"}
}