{
  "type": "Feature",
  "properties": {
    "addr:full":"shop5 23 Gordon St Mandurah WA 6210",
    "addr:housenumber":"23",
    "addr:postcode":"6210",
    "addr:street":"Gordon St",
    "iso:country":"AU",
    "sg:address":"shop5 23 Gordon St",
    "sg:city":"Mandurah",
    "sg:classifiers":[
        {
            "category":"Sports & Exercise",
            "subcategory":"Gym",
            "type":"Entertainment"
        }
    ],
    "sg:phone":"+61 8 9581 8077",
    "sg:postcode":"6210",
    "sg:province":"WA",
    "sg:tags":[
        "health",
        "fitness"
    ],
    "wof:name":"Healthy Inspirations",
    "wof:placetype":"venue"
},
  "geometry": {"coordinates":[115.743156,-32.51115],"type":"Point"}
}