{
  "type": "Feature",
  "properties": {
    "addr:full":"PO Box 1142 Wangaratta VIC 3677",
    "addr:postcode":"3677",
    "iso:country":"AU",
    "sg:address":"PO Box 1142",
    "sg:city":"Wangaratta",
    "sg:classifiers":[
        {
            "category":"Banks & Credit Unions",
            "subcategory":"Bank",
            "type":"Services"
        }
    ],
    "sg:phone":"+61 1300 133 820",
    "sg:postcode":"3677",
    "sg:province":"VIC",
    "sg:tags":[
        "broker",
        "mortgage"
    ],
    "wof:name":"Fraser Jeffrey Finance Pty Ltd",
    "wof:placetype":"venue"
},
  "geometry": {"coordinates":[146.318527222,-36.3704109192],"type":"Point"}
}