{
  "type": "Feature",
  "properties": {
    "iso:country":"AU",
    "sg:address":"Shop 10 Robertson Village 17 Barrett St",
    "sg:city":"Robertson",
    "sg:classifiers":[
        {
            "category":"Health Services",
            "subcategory":"Health Practitioner",
            "type":"Services"
        }
    ],
    "sg:phone":"+61 7 3274 2974",
    "sg:postcode":"4109",
    "sg:province":"QLD",
    "sg:tags":[
        "naturopath"
    ],
    "wof:name":"Akins Judith",
    "wof:placetype":"venue"
},
  "geometry": {"coordinates":[153.05140685999999,-27.5608005524],"type":"Point"}
}