{
  "type": "Feature",
  "properties": {
    "iso:country":"AU",
    "sg:address":"187 Geldart Rd",
    "sg:city":"Chandler",
    "sg:classifiers":[
        {
            "category":"Professional",
            "subcategory":"Engineering",
            "type":"Services"
        }
    ],
    "sg:phone":"+61 7 3823 2488",
    "sg:postcode":"4155",
    "sg:province":"QLD",
    "sg:tags":[
        "electrical",
        "engineer"
    ],
    "wof:name":"Precis One Pty Ltd",
    "wof:placetype":"venue"
},
  "geometry": {"coordinates":[153.157745361,-27.5190372467],"type":"Point"}
}