{
  "type": "Feature",
  "properties": {
    "addr:full":"139 Puckle St Moonee Ponds VIC 3039",
    "addr:housenumber":"139",
    "addr:postcode":"3039",
    "addr:street":"Puckle St",
    "iso:country":"AU",
    "sg:address":"139 Puckle St",
    "sg:city":"Moonee Ponds",
    "sg:classifiers":[
        {
            "category":"Personal",
            "subcategory":"Beauty Salon",
            "type":"Services"
        }
    ],
    "sg:phone":"+61 3 9370 5216",
    "sg:postcode":"3039",
    "sg:province":"VIC",
    "sg:tags":[
        "hairdresser"
    ],
    "wof:name":"Romero Hair And Beauty Establishment",
    "wof:placetype":"venue"
},
  "geometry": {"coordinates":[144.91984600000001,-37.766712],"type":"Point"}
}