{
  "type": "Feature",
  "properties": {
    "iso:country":"AU",
    "sg:address":"Cnr Talbragar & Macquarie Sts",
    "sg:city":"Dubbo",
    "sg:classifiers":[
        {
            "category":"Professional",
            "subcategory":"Engineering",
            "type":"Services"
        }
    ],
    "sg:phone":"+61 2 6882 8900",
    "sg:postcode":"2830",
    "sg:province":"NSW",
    "sg:tags":[
        "consulting",
        "engineer"
    ],
    "wof:name":"Cook J & M",
    "wof:placetype":"venue"
},
  "geometry": {"coordinates":[148.601852417,-32.2448692322],"type":"Point"}
}