{
  "type": "Feature",
  "properties": {
    "addr:full":"22 Callister St Shepparton VIC 3630",
    "addr:housenumber":"22",
    "addr:postcode":"3630",
    "addr:street":"Callister St",
    "iso:country":"AU",
    "sg:address":"22 Callister St",
    "sg:city":"Shepparton",
    "sg:classifiers":[
        {
            "category":"Home & Garden",
            "subcategory":"Building Materials",
            "type":"Retail Goods"
        }
    ],
    "sg:phone":"+61 3 5821 5211",
    "sg:postcode":"3630",
    "sg:province":"VIC",
    "sg:tags":[
        "merchant",
        "glass",
        "glazier"
    ],
    "wof:name":"Yencken-Gale Glass & Glazing Pty Ltd",
    "wof:placetype":"venue"
},
  "geometry": {"coordinates":[145.415084839,-36.3861694336],"type":"Point"}
}