{
  "type": "Feature",
  "properties": {
    "addr:full":"5 Meaka Crt Warrandyte VIC 3113",
    "addr:housenumber":"5",
    "addr:postcode":"3113",
    "addr:street":"Meaka Crt",
    "iso:country":"AU",
    "sg:address":"5 Meaka Crt",
    "sg:city":"Warrandyte",
    "sg:classifiers":[
        {
            "category":"Building & Trades",
            "subcategory":"Construction",
            "type":"Services"
        }
    ],
    "sg:phone":"+61 414 728 261",
    "sg:postcode":"3113",
    "sg:province":"VIC",
    "sg:tags":[
        "excavation",
        "foundation"
    ],
    "wof:name":"All Dirtwork Excavations",
    "wof:placetype":"venue"
},
  "geometry": {"coordinates":[145.18801879899999,-37.7551460266],"type":"Point"}
}