{
  "type": "Feature",
  "properties": {
    "addr:full":"46 Webster St Alexandra VIC 3714",
    "addr:housenumber":"46",
    "addr:postcode":"3714",
    "addr:street":"Webster St",
    "iso:country":"AU",
    "sg:address":"46 Webster St",
    "sg:city":"Alexandra",
    "sg:classifiers":[
        {
            "category":"Utilities",
            "subcategory":"Refuse",
            "type":"Services"
        }
    ],
    "sg:phone":"+61 409 997 632",
    "sg:postcode":"3714",
    "sg:province":"VIC",
    "sg:tags":[
        "disposal",
        "reduction",
        "waste"
    ],
    "wof:name":"Alexandra Skip Bins",
    "wof:placetype":"venue"
},
  "geometry": {"coordinates":[145.71255493199999,-37.1958084106],"type":"Point"}
}