{
  "type": "Feature",
  "properties": {
    "addr:full":"419 Macquarie St Liverpool NSW 2170",
    "addr:housenumber":"419",
    "addr:postcode":"2170",
    "addr:street":"Macquarie St",
    "iso:country":"AU",
    "sg:address":"419 Macquarie St",
    "sg:city":"Liverpool",
    "sg:classifiers":[
        {
            "category":"Government",
            "subcategory":"Fire Station",
            "type":"Public Place"
        }
    ],
    "sg:phone":"+61 2 9601 2777",
    "sg:postcode":"2170",
    "sg:province":"NSW",
    "sg:tags":[
        "spring",
        "shock",
        "absorbers",
        "suspension"
    ],
    "wof:name":"A.A. Australian Made-K-Mac",
    "wof:placetype":"venue"
},
  "geometry": {"coordinates":[150.91900634800001,-33.9276542664],"type":"Point"}
}