{
  "type": "Feature",
  "properties": {
    "addr:full":"Singapore Plaza Shop 6/76-80 John St Cabramatta NSW 2166",
    "addr:housenumber":"shop 6 / 76-80",
    "addr:postcode":"2166",
    "addr:street":"John St",
    "iso:country":"AU",
    "sg:address":"Singapore Plaza Shop 6/76-80 John St",
    "sg:city":"Cabramatta",
    "sg:classifiers":[
        {
            "category":"Health Services",
            "subcategory":"Dentist",
            "type":"Services"
        }
    ],
    "sg:phone":"+61 2 9724 0466",
    "sg:postcode":"2166",
    "sg:province":"NSW",
    "wof:name":"Bill Trung Binh Ta & Associates Dental Centre",
    "wof:placetype":"venue"
},
  "geometry": {"coordinates":[150.93431091299999,-33.8949661255],"type":"Point"}
}