{
  "type": "Feature",
  "properties": {
    "iso:country":"AU",
    "sg:address":"PO Box 465",
    "sg:city":"Dickson",
    "sg:classifiers":[
        {
            "category":"Organizations",
            "subcategory":"Community Association",
            "type":"Services"
        }
    ],
    "sg:phone":"+61 2 6248 6333",
    "sg:postcode":"2602",
    "sg:province":"ACT",
    "sg:tags":[
        "organisation",
        "family",
        "welfare"
    ],
    "wof:name":"Parents Without Partners (ACT) Inc.",
    "wof:placetype":"venue"
},
  "geometry": {"coordinates":[149.142944336,-35.2521018982],"type":"Point"}
}