{
  "type": "Feature",
  "properties": {
    "addr:full":"Shop 2, 70 Chamberlain St Campbelltown NSW 2560",
    "addr:housenumber":"shop;70",
    "addr:postcode":"2560",
    "addr:street":"Chamberlain St",
    "iso:country":"AU",
    "sg:address":"Shop 2, 70 Chamberlain St",
    "sg:city":"Campbelltown",
    "sg:classifiers":[
        {
            "category":"Food & Beverages",
            "subcategory":"Fruits & Vegetables",
            "type":"Retail Goods"
        }
    ],
    "sg:phone":"+61 2 4627 8199",
    "sg:postcode":"2560",
    "sg:province":"NSW",
    "sg:tags":[
        "greengrocer",
        "fruiterer"
    ],
    "wof:name":"Chamberlain Street Fruit & Flower Shop",
    "wof:placetype":"venue"
},
  "geometry": {"coordinates":[150.825241089,-34.065990448],"type":"Point"}
}