{
  "type": "Feature",
  "properties": {
    "addr:full":"425 High St Northcote VIC 3070",
    "addr:housenumber":"425",
    "addr:postcode":"3070",
    "addr:street":"High St",
    "iso:country":"AU",
    "sg:address":"425 High St",
    "sg:city":"Northcote",
    "sg:classifiers":[
        {
            "category":"Building & Trades",
            "subcategory":"Construction",
            "type":"Services"
        }
    ],
    "sg:phone":"+61 3 9482 3335",
    "sg:postcode":"3070",
    "sg:province":"VIC",
    "sg:tags":[
        "contractor"
    ],
    "wof:name":"Kaito Developments Pty Ltd",
    "wof:placetype":"venue"
},
  "geometry": {"coordinates":[144.99902299999999,-37.767876],"type":"Point"}
}