{
  "type": "Feature",
  "properties": {
    "addr:full":"28 Pompadour St Sunnybank Hills QLD 4109",
    "addr:housenumber":"28",
    "addr:postcode":"4109",
    "addr:street":"Pompadour St",
    "iso:country":"AU",
    "sg:address":"28 Pompadour St",
    "sg:city":"Sunnybank Hills",
    "sg:classifiers":[
        {
            "category":"Professional",
            "subcategory":"Art Services",
            "type":"Services"
        }
    ],
    "sg:phone":"+61 401 206 461",
    "sg:postcode":"4109",
    "sg:province":"QLD",
    "sg:tags":[
        "picture",
        "frame",
        "framing"
    ],
    "wof:name":"Southside Picture Framing",
    "wof:placetype":"venue"
},
  "geometry": {"coordinates":[153.059356689,-27.6061306],"type":"Point"}
}