{
  "type": "Feature",
  "properties": {
    "addr:full":"PO Box 211 Alexandria NSW 1435",
    "addr:postcode":"1435",
    "iso:country":"AU",
    "sg:address":"PO Box 211",
    "sg:city":"Alexandria",
    "sg:classifiers":[
        {
            "category":"Shopping",
            "subcategory":"News",
            "type":"Retail Goods"
        }
    ],
    "sg:phone":"+61 2 9516 2127",
    "sg:postcode":"1435",
    "sg:province":"NSW",
    "sg:tags":[
        "magazine",
        "periodical"
    ],
    "wof:name":"Crema Magazine",
    "wof:placetype":"venue"
},
  "geometry": {"coordinates":[151.19557189899999,-33.8975715637],"type":"Point"}
}