{
  "type": "Feature",
  "properties": {
    "addr:full":"Unit 1/ 557 Lower Dandenong Rd Dingley VIC 3172",
    "addr:housenumber":"/ 557",
    "addr:postcode":"3172",
    "addr:street":"Lower Dandenong Rd",
    "iso:country":"AU",
    "sg:address":"Unit 1/ 557 Lower Dandenong Rd",
    "sg:city":"Dingley",
    "sg:classifiers":[
        {
            "category":"Real Estate",
            "subcategory":"Architect",
            "type":"Services"
        }
    ],
    "sg:phone":"+61 414 563 817",
    "sg:postcode":"3172",
    "sg:province":"VIC",
    "sg:tags":[
        "building",
        "designer"
    ],
    "wof:name":"Norm Robinson Design Services",
    "wof:placetype":"venue"
},
  "geometry": {"coordinates":[145.13221740700001,-37.9890937805],"type":"Point"}
}