{
  "type": "Feature",
  "properties": {
    "iso:country":"AU",
    "sg:address":"Level 4/ 7 Help St",
    "sg:city":"Chatswood",
    "sg:classifiers":[
        {
            "category":"Professional",
            "subcategory":"Business Services",
            "type":"Services"
        }
    ],
    "sg:phone":"+61 1300 650 058",
    "sg:postcode":"2057",
    "sg:province":"NSW",
    "sg:tags":[
        "small",
        "advisory"
    ],
    "wof:name":"NSW Government Business Advisory Services",
    "wof:placetype":"venue"
},
  "geometry": {"coordinates":[151.18071,-33.795414],"type":"Point"}
}