{
  "type": "Feature",
  "properties": {
    "addr:full":"127 Chandler Rd Noble Park VIC 3174",
    "addr:housenumber":"127",
    "addr:postcode":"3174",
    "addr:street":"Chandler Rd",
    "iso:country":"AU",
    "sg:address":"127 Chandler Rd",
    "sg:city":"Noble Park",
    "sg:classifiers":[
        {
            "category":"Health Services",
            "subcategory":"Doctor",
            "type":"Services"
        }
    ],
    "sg:phone":"+61 3 9791 1122",
    "sg:postcode":"3174",
    "sg:province":"VIC",
    "sg:tags":[
        "medical",
        "practitioner"
    ],
    "wof:name":"Saaroni Gideon",
    "wof:placetype":"venue"
},
  "geometry": {"coordinates":[145.18576049800001,-37.9748916626],"type":"Point"}
}