{
  "type": "Feature",
  "properties": {
    "iso:country":"AU",
    "sg:address":"11- 15 Chickerell St",
    "sg:city":"Morwell",
    "sg:classifiers":[
        {
            "category":"Professional",
            "subcategory":"Detective & Security Services",
            "type":"Services"
        }
    ],
    "sg:phone":"+61 3 5134 6572",
    "sg:postcode":"3840",
    "sg:province":"VIC",
    "sg:tags":[
        "equipment",
        "window",
        "doors"
    ],
    "wof:name":"Morwell Shopfitters Pty Ltd",
    "wof:placetype":"venue"
},
  "geometry": {"coordinates":[146.43392944300001,-38.2325134277],"type":"Point"}
}