{
  "type": "Feature",
  "properties": {
    "addr:full":"29 Park St Brighton VIC 3186",
    "addr:housenumber":"29",
    "addr:postcode":"3186",
    "addr:street":"Park St",
    "iso:country":"AU",
    "sg:address":"29 Park St",
    "sg:city":"Brighton",
    "sg:classifiers":[
        {
            "category":"Professional",
            "subcategory":"Management & Consulting",
            "type":"Services"
        }
    ],
    "sg:phone":"+61 417 384 037",
    "sg:postcode":"3186",
    "sg:province":"VIC",
    "sg:tags":[
        "consultant",
        "business"
    ],
    "wof:name":"Mentor International Pty Ltd",
    "wof:placetype":"venue"
},
  "geometry": {"coordinates":[144.99029540999999,-37.9128570557],"type":"Point"}
}