{
  "type": "Feature",
  "properties": {
    "addr:full":"10 Devon St Lonsdale SA 5160",
    "addr:housenumber":"10",
    "addr:postcode":"5160",
    "addr:street":"Devon St",
    "iso:country":"AU",
    "sg:address":"10 Devon St",
    "sg:city":"Lonsdale",
    "sg:classifiers":[
        {
            "category":"Park",
            "subcategory":"County",
            "type":"Public Place"
        }
    ],
    "sg:phone":"+61 8 8382 3522",
    "sg:postcode":"5160",
    "sg:province":"SA",
    "sg:tags":[
        "box",
        "fibre",
        "carton",
        "secondhand",
        "cardboard"
    ],
    "wof:name":"Grunert C",
    "wof:placetype":"venue"
},
  "geometry": {"coordinates":[138.50100707999999,-35.1163482666],"type":"Point"}
}