{
  "type": "Feature",
  "properties": {
    "iso:country":"AU",
    "sg:address":"101 Queen St",
    "sg:city":"Woollahra",
    "sg:classifiers":[
        {
            "category":"Food & Beverages",
            "subcategory":"Meat & Fish",
            "type":"Retail Goods"
        }
    ],
    "sg:phone":"+61 2 9328 7120",
    "sg:postcode":"2025",
    "sg:province":"NSW",
    "sg:tags":[
        "seafood"
    ],
    "wof:name":"Simply Seafood Woollahra",
    "wof:placetype":"venue"
},
  "geometry": {"coordinates":[151.23733520499999,-33.8885192871],"type":"Point"}
}