{
  "type": "Feature",
  "properties": {
    "addr:full":"3 Park St Coffs Harbour NSW 2450",
    "addr:housenumber":"3",
    "addr:postcode":"2450",
    "addr:street":"Park St",
    "iso:country":"AU",
    "sg:address":"3 Park St",
    "sg:city":"Coffs Harbour",
    "sg:classifiers":[
        {
            "category":"Shopping",
            "subcategory":"Stationery & Office Supplies",
            "type":"Retail Goods"
        }
    ],
    "sg:phone":"+61 416 075 777",
    "sg:postcode":"2450",
    "sg:province":"NSW",
    "sg:tags":[
        "equipment",
        "display",
        "exhibition"
    ],
    "wof:name":"Display Power",
    "wof:placetype":"venue"
},
  "geometry": {"coordinates":[153.10223400000001,-30.373756],"type":"Point"}
}