{
  "type": "Feature",
  "properties": {
    "addr:full":"Shp SO53, Elizabeth Shopng Cntr Elizabeth SA 5112",
    "addr:postcode":"5112",
    "addr:street":"Elizabeth",
    "iso:country":"AU",
    "sg:address":"Shp SO53, Elizabeth Shopng Cntr",
    "sg:city":"Elizabeth",
    "sg:classifiers":[
        {
            "category":"Professional",
            "subcategory":"Accounting & Tax Preparation",
            "type":"Services"
        }
    ],
    "sg:phone":"+61 8 8255 4856",
    "sg:postcode":"5112",
    "sg:province":"SA",
    "sg:tags":[
        "accountant",
        "auditor"
    ],
    "wof:name":"H&R Block",
    "wof:placetype":"venue"
},
  "geometry": {"coordinates":[138.66700744600001,-34.7156982422],"type":"Point"}
}