{
  "type": "Feature",
  "properties": {
    "iso:country":"AU",
    "sg:address":"269 Ingham Rd",
    "sg:city":"Townsville",
    "sg:classifiers":[
        {
            "category":"Wholesale",
            "subcategory":"Machinery & Supplies",
            "type":"Manufacturing & Wholesale Goods"
        }
    ],
    "sg:phone":"+61 7 4779 8355",
    "sg:postcode":"4810",
    "sg:province":"QLD",
    "sg:tags":[
        "engineer"
    ],
    "wof:name":"Bakers",
    "wof:placetype":"venue"
},
  "geometry": {"coordinates":[146.776978,-19.265488],"type":"Point"}
}