{
  "type": "Feature",
  "properties": {
    "iso:country":"AU",
    "sg:address":"224- 226 Scott St",
    "sg:city":"Cairns",
    "sg:classifiers":[
        {
            "category":"Conference Center",
            "type":"Public Place"
        }
    ],
    "sg:phone":"+61 7 4033 7577",
    "sg:postcode":"4870",
    "sg:province":"QLD",
    "sg:tags":[
        "dryer",
        "electric",
        "hand"
    ],
    "wof:name":"James & More Pty Ltd",
    "wof:placetype":"venue"
},
  "geometry": {"coordinates":[145.75083923299999,-16.9411582947],"type":"Point"}
}