{
  "type": "Feature",
  "properties": {
    "iso:country":"AU",
    "sg:address":"PO Box 609",
    "sg:city":"Clare",
    "sg:classifiers":[
        {
            "category":"Building & Trades",
            "subcategory":"Construction",
            "type":"Services"
        }
    ],
    "sg:phone":"+61 8 8842 2407",
    "sg:postcode":"5453",
    "sg:province":"SA",
    "sg:tags":[
        "fencing",
        "contractor"
    ],
    "wof:name":"Regional Fencing & Trellising",
    "wof:placetype":"venue"
},
  "geometry": {"coordinates":[138.61077900000001,-33.83239],"type":"Point"}
}