{
  "type": "Feature",
  "properties": {
    "iso:country":"AU",
    "sg:address":"2 Windsor Rd",
    "sg:city":"Red Hill",
    "sg:classifiers":[
        {
            "category":"Government",
            "subcategory":"Post Office",
            "type":"Public Place"
        }
    ],
    "sg:phone":"+61 7 3369 2157",
    "sg:postcode":"4059",
    "sg:province":"QLD",
    "sg:tags":[
        "postal"
    ],
    "wof:name":"Red Hill Post Office",
    "wof:placetype":"venue"
},
  "geometry": {"coordinates":[153.00665283199999,-27.4545516968],"type":"Point"}
}