{
  "type": "Feature",
  "properties": {
    "addr:full":"22 Brownlie Crt Beenleigh QLD 4207",
    "addr:housenumber":"22",
    "addr:postcode":"4207",
    "addr:street":"Brownlie Crt",
    "iso:country":"AU",
    "sg:address":"22 Brownlie Crt",
    "sg:city":"Beenleigh",
    "sg:classifiers":[
        {
            "category":"Home & Garden",
            "subcategory":"Carpets & Floor Coverings",
            "type":"Retail Goods"
        }
    ],
    "sg:phone":"+61 7 3382 6373",
    "sg:postcode":"4207",
    "sg:province":"QLD",
    "sg:tags":[
        "layer",
        "planner"
    ],
    "wof:name":"McArthur Alex",
    "wof:placetype":"venue"
},
  "geometry": {"coordinates":[153.18272399899999,-27.7234344482],"type":"Point"}
}