{
  "type": "Feature",
  "properties": {
    "iso:country":"AU",
    "sg:address":"13 Frenshams Drv",
    "sg:city":"Woodcroft",
    "sg:classifiers":[
        {
            "category":"Building & Trades",
            "subcategory":"Construction",
            "type":"Services"
        }
    ],
    "sg:phone":"+61 412 371 745",
    "sg:postcode":"5162",
    "sg:province":"SA",
    "sg:tags":[
        "joiner",
        "carpenter"
    ],
    "wof:name":"Creation Carpentry",
    "wof:placetype":"venue"
},
  "geometry": {"coordinates":[138.55192565900001,-35.0961074829],"type":"Point"}
}