{
  "type": "Feature",
  "properties": {
    "iso:country":"AU",
    "sg:address":"Unit 3 264 Kalamunda Rd",
    "sg:city":"Kalamunda",
    "sg:classifiers":[
        {
            "category":"Utilities",
            "subcategory":"Electric",
            "type":"Services"
        }
    ],
    "sg:phone":"+61 8 9352 8166",
    "sg:postcode":"6076",
    "sg:province":"WA",
    "sg:tags":[
        "electrical",
        "contractor"
    ],
    "wof:name":"Sparkies Electrical Contractors Pty Ltd",
    "wof:placetype":"venue"
},
  "geometry": {"coordinates":[116.03563690199999,-31.9598388672],"type":"Point"}
}