{
  "type": "Feature",
  "properties": {
    "addr:full":"28 Monterey Rd Bilgola NSW 2107",
    "addr:housenumber":"28",
    "addr:postcode":"2107",
    "addr:street":"Monterey Rd",
    "iso:country":"AU",
    "sg:address":"28 Monterey Rd",
    "sg:city":"Bilgola",
    "sg:classifiers":[
        {
            "category":"Professional",
            "subcategory":"Management & Consulting",
            "type":"Services"
        }
    ],
    "sg:phone":"+61 2 9918 4277",
    "sg:postcode":"2107",
    "sg:province":"NSW",
    "sg:tags":[
        "consultant",
        "business"
    ],
    "wof:name":"Breden Butter Pty Ltd",
    "wof:placetype":"venue"
},
  "geometry": {"coordinates":[151.3175354,-33.646030426],"type":"Point"}
}