{
  "type": "Feature",
  "properties": {
    "iso:country":"AU",
    "sg:address":"71 Old Maryborough Rd",
    "sg:city":"Pialba",
    "sg:classifiers":[
        {
            "category":"Autos & Motor Vehicles",
            "subcategory":"Auto Supplies",
            "type":"Retail Goods"
        }
    ],
    "sg:phone":"+61 7 4128 2868",
    "sg:postcode":"4655",
    "sg:province":"QLD",
    "sg:tags":[
        "camper-trailers",
        "caravan",
        "equipment"
    ],
    "wof:name":"Coastline Caravans Hervey Bay",
    "wof:placetype":"venue"
},
  "geometry": {"coordinates":[152.826889,-25.282785],"type":"Point"}
}