{
  "type": "Feature",
  "properties": {
    "iso:country":"AU",
    "sg:address":"Shp2/ 1390 Anzac Ave",
    "sg:city":"Kallangur",
    "sg:classifiers":[
        {
            "category":"Cafe",
            "type":"Food & Drink"
        }
    ],
    "sg:phone":"+61 7 3482 2051",
    "sg:postcode":"4503",
    "sg:province":"QLD",
    "wof:name":"Buwarri Cafe",
    "wof:placetype":"venue"
},
  "geometry": {"coordinates":[152.99273681599999,-27.2505092621],"type":"Point"}
}