{
  "type": "Feature",
  "properties": {
    "addr:full":"PO Box 455 Somerton VIC 3062",
    "addr:postcode":"3062",
    "iso:country":"AU",
    "sg:address":"PO Box 455",
    "sg:city":"Somerton",
    "sg:classifiers":[
        {
            "category":"Building & Trades",
            "subcategory":"Plumbing",
            "type":"Services"
        }
    ],
    "sg:phone":"+61 409 231 968",
    "sg:postcode":"3062",
    "sg:province":"VIC",
    "sg:tags":[
        "plumber",
        "gasfitters"
    ],
    "wof:name":"Helms Plumbing Services",
    "wof:placetype":"venue"
},
  "geometry": {"coordinates":[144.954055786,-37.6336288452],"type":"Point"}
}