{
  "type": "Feature",
  "properties": {
    "addr:full":"8 Laurie St Innisfail QLD 4860",
    "addr:housenumber":"8",
    "addr:postcode":"4860",
    "addr:street":"Laurie St",
    "iso:country":"AU",
    "sg:address":"8 Laurie St",
    "sg:city":"Innisfail",
    "sg:classifiers":[
        {
            "category":"Home & Garden",
            "subcategory":"Garden Supply",
            "type":"Retail Goods"
        }
    ],
    "sg:phone":"+61 7 4061 1066",
    "sg:postcode":"4860",
    "sg:province":"QLD",
    "sg:tags":[
        "fertilizer"
    ],
    "wof:name":"Grow Force Australia Ltd",
    "wof:placetype":"venue"
},
  "geometry": {"coordinates":[146.00877380399999,-17.5249958038],"type":"Point"}
}