{
  "type": "Feature",
  "properties": {
    "addr:full":"615 Bagnoo Rd Bagnoo NSW 2446",
    "addr:housenumber":"615",
    "addr:postcode":"2446",
    "addr:street":"Bagnoo Rd",
    "iso:country":"AU",
    "sg:address":"615 Bagnoo Rd",
    "sg:city":"Bagnoo",
    "sg:classifiers":[
        {
            "category":"Manufacturing",
            "subcategory":"Metals",
            "type":"Manufacturing & Wholesale Goods"
        }
    ],
    "sg:phone":"+61 2 6587 1176",
    "sg:postcode":"2446",
    "sg:province":"NSW",
    "sg:tags":[
        "polisher"
    ],
    "wof:name":"Port Maquarie Metal Finishers & Polishers",
    "wof:placetype":"venue"
},
  "geometry": {"coordinates":[152.72854599999999,-31.485729],"type":"Point"}
}