{
  "type": "Feature",
  "properties": {
    "addr:full":"122 Dynon Rd West Melbourne VIC 3003",
    "addr:housenumber":"122",
    "addr:postcode":"3003",
    "addr:street":"Dynon Rd",
    "iso:country":"AU",
    "sg:address":"122 Dynon Rd",
    "sg:city":"West Melbourne",
    "sg:classifiers":[
        {
            "category":"Taxi",
            "type":"Transportation"
        }
    ],
    "sg:phone":"+61 3 9372 1844",
    "sg:postcode":"3003",
    "sg:province":"VIC",
    "sg:tags":[
        "truck"
    ],
    "wof:name":"Macs Transport Services",
    "wof:placetype":"venue"
},
  "geometry": {"coordinates":[144.93159484899999,-37.8033638],"type":"Point"}
}