{
  "type": "Feature",
  "properties": {
    "addr:full":"60 Young Rd Cowra NSW 2794",
    "addr:housenumber":"60",
    "addr:postcode":"2794",
    "addr:street":"Young Rd",
    "iso:country":"AU",
    "sg:address":"60 Young Rd",
    "sg:city":"Cowra",
    "sg:classifiers":[
        {
            "category":"Autos & Motor Vehicles",
            "subcategory":"Fuel & Gas Station",
            "type":"Retail Goods"
        }
    ],
    "sg:phone":"+61 2 6341 4743",
    "sg:postcode":"2794",
    "sg:province":"NSW",
    "wof:name":"Save On Fuel",
    "wof:placetype":"venue"
},
  "geometry": {"coordinates":[148.69056701700001,-33.8345909119],"type":"Point"}
}