{
  "type": "Feature",
  "properties": {
    "addr:full":"51b Hitchcock Ave Barwon Heads VIC 3227",
    "addr:housenumber":"51b",
    "addr:postcode":"3227",
    "addr:street":"Hitchcock Ave",
    "iso:country":"AU",
    "sg:address":"51b Hitchcock Ave",
    "sg:city":"Barwon Heads",
    "sg:classifiers":[
        {
            "category":"Building & Trades",
            "subcategory":"Landscaping Services",
            "type":"Services"
        }
    ],
    "sg:phone":"+61 3 5254 3216",
    "sg:postcode":"3227",
    "sg:province":"VIC",
    "sg:tags":[
        "consultant"
    ],
    "wof:name":"Just Building Surveying Solutions",
    "wof:placetype":"venue"
},
  "geometry": {"coordinates":[144.49025,-38.266445],"type":"Point"}
}