{
  "type": "Feature",
  "properties": {
    "iso:country":"AU",
    "sg:address":"84 Eastern Rd",
    "sg:city":"Traralgon",
    "sg:classifiers":[
        {
            "category":"Utilities",
            "type":"Services"
        }
    ],
    "sg:phone":"+61 3 5174 2548",
    "sg:postcode":"3844",
    "sg:province":"VIC",
    "sg:tags":[
        "refrigeration",
        "industrial",
        "commercial",
        "retail"
    ],
    "wof:name":"Graham Hobson Refrigeration",
    "wof:placetype":"venue"
},
  "geometry": {"coordinates":[146.56576538100001,-38.1794052124],"type":"Point"}
}