{
  "type": "Feature",
  "properties": {
    "addr:full":"33 Brisbane St Launceston TAS 7250",
    "addr:housenumber":"33",
    "addr:postcode":"7250",
    "addr:street":"Brisbane St",
    "iso:country":"AU",
    "sg:address":"33 Brisbane St",
    "sg:city":"Launceston",
    "sg:classifiers":[
        {
            "category":"Health Services",
            "subcategory":"Doctor",
            "type":"Services"
        }
    ],
    "sg:phone":"+61 3 6331 2355",
    "sg:postcode":"7250",
    "sg:province":"TAS",
    "sg:tags":[
        "medical",
        "practitioner"
    ],
    "wof:name":"Thomson A Dr",
    "wof:placetype":"venue"
},
  "geometry": {"coordinates":[147.14251709000001,-41.4347610474],"type":"Point"}
}