{
  "type": "Feature",
  "properties": {
    "iso:country":"AU",
    "sg:address":"193 Stawell St",
    "sg:city":"Sale",
    "sg:classifiers":[
        {
            "category":"Personal",
            "subcategory":"Massage",
            "type":"Services"
        }
    ],
    "sg:phone":"+61 3 5144 7190",
    "sg:postcode":"3850",
    "sg:province":"VIC",
    "sg:tags":[
        "therapy"
    ],
    "wof:name":"Glenn Sclater Massage Clinic",
    "wof:placetype":"venue"
},
  "geometry": {"coordinates":[147.064331055,-38.1089134216],"type":"Point"}
}