{
  "type": "Feature",
  "properties": {
    "iso:country":"AU",
    "sg:address":"4 Bickell Rd",
    "sg:city":"Mosman",
    "sg:classifiers":[
        {
            "category":"Sports & Exercise",
            "subcategory":"Sports Center",
            "type":"Entertainment"
        }
    ],
    "sg:phone":"+61 2 9968 1888",
    "sg:postcode":"2088",
    "sg:province":"NSW",
    "sg:tags":[
        "ground"
    ],
    "wof:name":"Mosman Tennis Centre",
    "wof:placetype":"venue"
},
  "geometry": {"coordinates":[151.24205017099999,-33.8171463013],"type":"Point"}
}