{
  "type": "Feature",
  "properties": {
    "addr:full":"Morell St Glenroy VIC 3046",
    "addr:postcode":"3046",
    "addr:street":"Morell St",
    "iso:country":"AU",
    "sg:address":"Morell St",
    "sg:city":"Glenroy",
    "sg:classifiers":[
        {
            "category":"Education",
            "subcategory":"School",
            "type":"Public Place"
        }
    ],
    "sg:phone":"+61 3 9306 7900",
    "sg:postcode":"3046",
    "sg:province":"VIC",
    "sg:tags":[
        "state",
        "except",
        "nsw"
    ],
    "wof:name":"Belle Vue Park Primary",
    "wof:placetype":"venue"
},
  "geometry": {"coordinates":[144.939056397,-37.6981735229],"type":"Point"}
}