{
  "type": "Feature",
  "properties": {
    "addr:full":"29 Amherst Rd West Midland WA 6056",
    "addr:housenumber":"29",
    "addr:postcode":"6056",
    "addr:street":"Amherst Rd West",
    "iso:country":"AU",
    "sg:address":"29 Amherst Rd",
    "sg:city":"West Midland",
    "sg:classifiers":[
        {
            "category":"Health Services",
            "subcategory":"Health Practitioner",
            "type":"Services"
        }
    ],
    "sg:phone":"+61 8 9274 6118",
    "sg:postcode":"6056",
    "sg:province":"WA",
    "sg:tags":[
        "psychologist"
    ],
    "wof:name":"Aggett Maggie.",
    "wof:placetype":"venue"
},
  "geometry": {"coordinates":[116.051147461,-31.892244339],"type":"Point"}
}