{
  "type": "Feature",
  "properties": {
    "addr:full":"83 Sorrell St North Parramatta NSW 2151",
    "addr:housenumber":"83",
    "addr:postcode":"2151",
    "addr:street":"Sorrell St",
    "iso:country":"AU",
    "sg:address":"83 Sorrell St",
    "sg:city":"North Parramatta",
    "sg:classifiers":[
        {
            "category":"Utilities",
            "subcategory":"Telephone",
            "type":"Services"
        }
    ],
    "sg:phone":"+61 2 9683 5201",
    "sg:postcode":"2151",
    "sg:province":"NSW",
    "sg:tags":[
        "equipment",
        "system"
    ],
    "wof:name":"Emcorp Solutions Pty Ltd",
    "wof:placetype":"venue"
},
  "geometry": {"coordinates":[151.008255005,-33.8013916016],"type":"Point"}
}