{
  "type": "Feature",
  "properties": {
    "addr:full":"143 Canterbury Rd Toorak VIC 3142",
    "addr:housenumber":"143",
    "addr:postcode":"3142",
    "addr:street":"Canterbury Rd",
    "iso:country":"AU",
    "sg:address":"143 Canterbury Rd",
    "sg:city":"Toorak",
    "sg:classifiers":[
        {
            "category":"Shopping",
            "subcategory":"Clothing, Apparel, & Fashions",
            "type":"Retail Goods"
        }
    ],
    "sg:phone":"+61 3 9827 3172",
    "sg:postcode":"3142",
    "sg:province":"VIC",
    "sg:tags":[
        "recycled",
        "clothing"
    ],
    "wof:name":"Toorak Opportunity Shop",
    "wof:placetype":"venue"
},
  "geometry": {"coordinates":[145.010375977,-37.8422927856],"type":"Point"}
}