{
  "type": "Feature",
  "properties": {
    "addr:full":"72 Gladstone Rd Greensborough VIC 3088",
    "addr:housenumber":"72",
    "addr:postcode":"3088",
    "addr:street":"Gladstone Rd",
    "iso:country":"AU",
    "sg:address":"72 Gladstone Rd",
    "sg:city":"Greensborough",
    "sg:classifiers":[
        {
            "category":"Building & Trades",
            "subcategory":"Construction",
            "type":"Services"
        }
    ],
    "sg:phone":"+61 3 9434 5348",
    "sg:postcode":"3088",
    "sg:province":"VIC",
    "sg:tags":[
        "joiner",
        "carpenter"
    ],
    "wof:name":"Bowman Leigh",
    "wof:placetype":"venue"
},
  "geometry": {"coordinates":[145.11236572300001,-37.7068939209],"type":"Point"}
}