{
  "type": "Feature",
  "properties": {
    "iso:country":"AU",
    "sg:address":"80 Main St",
    "sg:city":"Hervey Bay",
    "sg:classifiers":[
        {
            "category":"Professional",
            "subcategory":"Employment Agencies",
            "type":"Services"
        }
    ],
    "sg:phone":"+61 7 4124 7492",
    "sg:postcode":"4655",
    "sg:province":"QLD",
    "wof:name":"Queensland Apprenticeship Services Pty Ltd",
    "wof:placetype":"venue"
},
  "geometry": {"coordinates":[152.83839399999999,-25.287622],"type":"Point"}
}