{
  "type": "Feature",
  "properties": {
    "addr:full":"580 Mcauleys Rd North Tumbulgum NSW 2490",
    "addr:housenumber":"580",
    "addr:postcode":"2490",
    "addr:street":"Mcauleys Rd",
    "iso:country":"AU",
    "sg:address":"580 Mcauleys Rd",
    "sg:city":"North Tumbulgum",
    "sg:classifiers":[
        {
            "category":"Real Estate",
            "subcategory":"Architect",
            "type":"Services"
        }
    ],
    "sg:phone":"+61 7 5590 5116",
    "sg:postcode":"2490",
    "sg:province":"NSW",
    "sg:tags":[
        "building",
        "designer"
    ],
    "wof:name":"J H Building & Landscape Designs Pty Ltd",
    "wof:placetype":"venue"
},
  "geometry": {"coordinates":[153.47039794899999,-28.2702960968],"type":"Point"}
}