{
  "type": "Feature",
  "properties": {
    "iso:country":"AU",
    "sg:address":"445 Whitehorse Rd",
    "sg:city":"Balwyn",
    "sg:classifiers":[
        {
            "category":"Food & Beverages",
            "subcategory":"Supermarket",
            "type":"Retail Goods"
        }
    ],
    "sg:phone":"+61 3 9830 5177",
    "sg:postcode":"3103",
    "sg:province":"VIC",
    "sg:tags":[
        "grocery",
        "store"
    ],
    "wof:name":"IGA Everyday",
    "wof:placetype":"venue"
},
  "geometry": {"coordinates":[145.08558654800001,-37.8132095337],"type":"Point"}
}