{
  "type": "Feature",
  "properties": {
    "addr:full":"83 Old Gosford Rd Wamberal NSW 2260",
    "addr:housenumber":"83",
    "addr:postcode":"2260",
    "addr:street":"Old Gosford Rd",
    "iso:country":"AU",
    "sg:address":"83 Old Gosford Rd",
    "sg:city":"Wamberal",
    "sg:classifiers":[
        {
            "category":"Building & Trades",
            "subcategory":"Construction",
            "type":"Services"
        }
    ],
    "sg:phone":"+61 412 698 926",
    "sg:postcode":"2260",
    "sg:province":"NSW",
    "sg:tags":[
        "ceiling"
    ],
    "wof:name":"J, Tarasenko",
    "wof:placetype":"venue"
},
  "geometry": {"coordinates":[151.43424999999999,-33.424767],"type":"Point"}
}