{
  "type": "Feature",
  "properties": {
    "addr:full":"94 Melbourne St Moora WA 6510",
    "addr:housenumber":"94",
    "addr:postcode":"6510",
    "addr:street":"Melbourne St",
    "iso:country":"AU",
    "sg:address":"94 Melbourne St",
    "sg:city":"Moora",
    "sg:classifiers":[
        {
            "category":"Farming",
            "subcategory":"Farm & Veterinary Services",
            "type":"Manufacturing & Wholesale Goods"
        }
    ],
    "sg:phone":"+61 8 9651 1245",
    "sg:postcode":"6510",
    "sg:province":"WA",
    "sg:tags":[
        "shearing",
        "contractor"
    ],
    "wof:name":"Wilson T S & Co",
    "wof:placetype":"venue"
},
  "geometry": {"coordinates":[116.011009,-30.640413],"type":"Point"}
}