{
  "type": "Feature",
  "properties": {
    "addr:full":"326 Serpentine Creek Rd Redland Bay QLD 4165",
    "addr:housenumber":"326",
    "addr:postcode":"4165",
    "addr:street":"Serpentine Creek Rd",
    "iso:country":"AU",
    "sg:address":"326 Serpentine Creek Rd",
    "sg:city":"Redland Bay",
    "sg:classifiers":[
        {
            "category":"Farming",
            "subcategory":"Nursery",
            "type":"Manufacturing & Wholesale Goods"
        }
    ],
    "sg:phone":"+61 7 3829 0144",
    "sg:postcode":"4165",
    "sg:province":"QLD",
    "wof:name":"Raward's Nursery",
    "wof:placetype":"venue"
},
  "geometry": {"coordinates":[153.30279540999999,-27.6617412567],"type":"Point"}
}