{
  "type": "Feature",
  "properties": {
    "iso:country":"AU",
    "sg:address":"8 Brown St",
    "sg:city":"Ashfield",
    "sg:classifiers":[
        {
            "category":"Health Services",
            "subcategory":"Doctor",
            "type":"Services"
        }
    ],
    "sg:phone":"+61 2 9798 6310",
    "sg:postcode":"2131",
    "sg:province":"NSW",
    "sg:tags":[
        "podiatrist"
    ],
    "wof:name":"Feet First Podiatry Services",
    "wof:placetype":"venue"
},
  "geometry": {"coordinates":[151.125366211,-33.8876228333],"type":"Point"}
}