{
  "type": "Feature",
  "properties": {
    "iso:country":"AU",
    "sg:address":"24 Jersey St",
    "sg:city":"Morningside",
    "sg:classifiers":[
        {
            "category":"Utilities",
            "subcategory":"Electric",
            "type":"Services"
        }
    ],
    "sg:phone":"+61 7 3399 6605",
    "sg:postcode":"4170",
    "sg:province":"QLD",
    "sg:tags":[
        "electrical",
        "contractor"
    ],
    "wof:name":"Morningside Electrical Service",
    "wof:placetype":"venue"
},
  "geometry": {"coordinates":[153.075683594,-27.4701843262],"type":"Point"}
}