{
  "type": "Feature",
  "properties": {
    "iso:country":"AU",
    "sg:address":"8 Ballinger Crs",
    "sg:city":"Buderim",
    "sg:classifiers":[
        {
            "category":"Health Services",
            "subcategory":"Doctor",
            "type":"Services"
        }
    ],
    "sg:phone":"+61 7 5445 1406",
    "sg:postcode":"4556",
    "sg:province":"QLD",
    "sg:tags":[
        "medical",
        "practitioner"
    ],
    "wof:name":"Ballinger Family Medical Practice",
    "wof:placetype":"venue"
},
  "geometry": {"coordinates":[153.051513672,-26.6865119934],"type":"Point"}
}