{
  "type": "Feature",
  "properties": {
    "addr:full":"85 Rivette St Hackett ACT 2602",
    "addr:housenumber":"85",
    "addr:postcode":"2602",
    "addr:street":"Rivette St",
    "iso:country":"AU",
    "sg:address":"85 Rivette St",
    "sg:city":"Hackett",
    "sg:classifiers":[
        {
            "category":"Utilities",
            "subcategory":"Electric",
            "type":"Services"
        }
    ],
    "sg:phone":"+61 419 291 900",
    "sg:postcode":"2602",
    "sg:province":"ACT",
    "sg:tags":[
        "electrical",
        "contractor"
    ],
    "wof:name":"Cummins M J & W A",
    "wof:placetype":"venue"
},
  "geometry": {"coordinates":[149.166946411,-35.2454185486],"type":"Point"}
}