{
  "type": "Feature",
  "properties": {
    "iso:country":"AU",
    "sg:address":"1 Silverbirch Pl",
    "sg:city":"Mawson Lakes",
    "sg:classifiers":[
        {
            "category":"Building & Trades",
            "subcategory":"Construction",
            "type":"Services"
        }
    ],
    "sg:phone":"+61 8 8349 4620",
    "sg:postcode":"5095",
    "sg:province":"SA",
    "sg:tags":[
        "decking",
        "contractor"
    ],
    "wof:name":"Progola",
    "wof:placetype":"venue"
},
  "geometry": {"coordinates":[138.61294555699999,-34.8244743347],"type":"Point"}
}