{
  "type": "Feature",
  "properties": {
    "iso:country":"AU",
    "sg:address":"63 Turrella St",
    "sg:city":"Turrella",
    "sg:classifiers":[
        {
            "category":"Manufacturing",
            "subcategory":"Textiles",
            "type":"Manufacturing & Wholesale Goods"
        }
    ],
    "sg:phone":"+61 2 9597 6644",
    "sg:postcode":"2205",
    "sg:province":"NSW",
    "sg:tags":[
        "mill"
    ],
    "wof:name":"Sellers Fabrics Pty Ltd",
    "wof:placetype":"venue"
},
  "geometry": {"coordinates":[151.146561,-33.928631],"type":"Point"}
}