{
  "type": "Feature",
  "properties": {
    "addr:full":"4/ 125 Magowar Rd Girraween NSW 2145",
    "addr:housenumber":"/ 125",
    "addr:postcode":"2145",
    "addr:street":"Magowar Rd",
    "iso:country":"AU",
    "sg:address":"4/ 125 Magowar Rd",
    "sg:city":"Girraween",
    "sg:classifiers":[
        {
            "category":"Manufacturing",
            "subcategory":"Metals",
            "type":"Manufacturing & Wholesale Goods"
        }
    ],
    "sg:phone":"+61 2 9896 6000",
    "sg:postcode":"2145",
    "sg:province":"NSW",
    "sg:tags":[
        "sheet",
        "worker"
    ],
    "wof:name":"Muscat Sheet Metal & Engineering",
    "wof:placetype":"venue"
},
  "geometry": {"coordinates":[150.94378662099999,-33.8012771606],"type":"Point"}
}