{
  "type": "Feature",
  "properties": {
    "addr:full":"14 Playford Crs Salisbury North SA 5108",
    "addr:housenumber":"14",
    "addr:postcode":"5108",
    "addr:street":"Playford Crs",
    "iso:country":"AU",
    "sg:address":"14 Playford Crs",
    "sg:city":"Salisbury North",
    "sg:classifiers":[
        {
            "category":"Education",
            "subcategory":"Music School",
            "type":"Public Place"
        }
    ],
    "sg:phone":"+61 8 8285 9722",
    "sg:postcode":"5108",
    "sg:province":"SA",
    "sg:tags":[
        "hi-fi",
        "equipment",
        "wholesaler",
        "mfrs"
    ],
    "wof:name":"Sonique Audio Pty Ltd",
    "wof:placetype":"venue"
},
  "geometry": {"coordinates":[138.62971496599999,-34.7420501709],"type":"Point"}
}