{
  "type": "Feature",
  "properties": {
    "addr:full":"286 Bay St Port Melbourne VIC 3207",
    "addr:housenumber":"286",
    "addr:postcode":"3207",
    "addr:street":"Bay St",
    "iso:country":"AU",
    "sg:address":"286 Bay St",
    "sg:city":"Port Melbourne",
    "sg:classifiers":[
        {
            "category":"Banks & Credit Unions",
            "subcategory":"Bureau De Change",
            "type":"Services"
        }
    ],
    "sg:phone":"+61 3 9646 7205",
    "sg:postcode":"3207",
    "sg:province":"VIC",
    "sg:tags":[
        "preparation",
        "processing",
        "data"
    ],
    "wof:name":"Creative Data Services P/L",
    "wof:placetype":"venue"
},
  "geometry": {"coordinates":[144.94349700000001,-37.837528],"type":"Point"}
}