{
  "type": "Feature",
  "properties": {
    "addr:full":"PO Box 323 Red Cliffs VIC 3496",
    "addr:postcode":"3496",
    "iso:country":"AU",
    "sg:address":"PO Box 323",
    "sg:city":"Red Cliffs",
    "sg:classifiers":[
        {
            "category":"Building & Trades",
            "subcategory":"Construction",
            "type":"Services"
        }
    ],
    "sg:phone":"+61 428 147 134",
    "sg:postcode":"3496",
    "sg:province":"VIC",
    "sg:tags":[
        "welding"
    ],
    "wof:name":"Sunset Welding Pty Ltd",
    "wof:placetype":"venue"
},
  "geometry": {"coordinates":[142.18652343799999,-34.3077087402],"type":"Point"}
}