{
  "type": "Feature",
  "properties": {
    "addr:full":"15 Para Rd Tanunda SA 5352",
    "addr:housenumber":"15",
    "addr:postcode":"5352",
    "addr:street":"Para Rd",
    "iso:country":"AU",
    "sg:address":"15 Para Rd",
    "sg:city":"Tanunda",
    "sg:classifiers":[
        {
            "category":"Building & Trades",
            "subcategory":"Construction",
            "type":"Services"
        }
    ],
    "sg:phone":"+61 418 821 755",
    "sg:postcode":"5352",
    "sg:province":"SA",
    "sg:tags":[
        "concrete",
        "contractor"
    ],
    "wof:name":"Straight Edge Concrete",
    "wof:placetype":"venue"
},
  "geometry": {"coordinates":[138.97029113799999,-34.5103302002],"type":"Point"}
}