{
  "type": "Feature",
  "properties": {
    "iso:country":"AU",
    "sg:address":"138 Norton St",
    "sg:city":"Leichhardt",
    "sg:classifiers":[
        {
            "category":"Restaurant",
            "type":"Food & Drink"
        }
    ],
    "sg:phone":"+61 2 9564 6490",
    "sg:postcode":"2040",
    "sg:province":"NSW",
    "wof:name":"Bar Galante",
    "wof:placetype":"venue"
},
  "geometry": {"coordinates":[151.156754,-33.882572],"type":"Point"}
}