{
  "type": "Feature",
  "properties": {
    "iso:country":"AU",
    "sg:address":"13 Charles St",
    "sg:city":"Orford",
    "sg:classifiers":[
        {
            "category":"Real Estate",
            "subcategory":"Real Estate Agent",
            "type":"Services"
        }
    ],
    "sg:phone":"+61 3 6257 1199",
    "sg:postcode":"7190",
    "sg:province":"TAS",
    "wof:name":"Roberts Real Estate",
    "wof:placetype":"venue"
},
  "geometry": {"coordinates":[147.872345,-42.560368],"type":"Point"}
}