{
  "type": "Feature",
  "properties": {
    "iso:country":"AU",
    "sg:address":"53 Manchester St",
    "sg:city":"Tinonee",
    "sg:classifiers":[
        {
            "category":"Building & Trades",
            "subcategory":"Construction",
            "type":"Services"
        }
    ],
    "sg:phone":"+61 2 6551 2973",
    "sg:postcode":"2430",
    "sg:province":"NSW",
    "sg:tags":[
        "contractor"
    ],
    "wof:name":"P & D Garage Doors",
    "wof:placetype":"venue"
},
  "geometry": {"coordinates":[152.413605,-31.939671],"type":"Point"}
}