{
  "type": "Feature",
  "properties": {
    "addr:full":"56 Medcalf St Warners Bay NSW 2282",
    "addr:housenumber":"56",
    "addr:postcode":"2282",
    "addr:street":"Medcalf St",
    "iso:country":"AU",
    "sg:address":"56 Medcalf St",
    "sg:city":"Warners Bay",
    "sg:classifiers":[
        {
            "category":"Structure",
            "subcategory":"Bridge",
            "type":"Public Place"
        }
    ],
    "sg:phone":"+61 2 4954 5258",
    "sg:postcode":"2282",
    "sg:province":"NSW",
    "sg:tags":[
        "chainsaw",
        "brushcutters"
    ],
    "wof:name":"Warners Bay Mowers & Chainsaws",
    "wof:placetype":"venue"
},
  "geometry": {"coordinates":[151.64718627900001,-32.9660758972],"type":"Point"}
}