{
  "type": "Feature",
  "properties": {
    "iso:country":"AU",
    "sg:address":"Cnr Dyson & Alderhoven Rds",
    "sg:city":"Lonsdale",
    "sg:classifiers":[
        {
            "category":"Building & Trades",
            "subcategory":"Plumbing",
            "type":"Services"
        }
    ],
    "sg:phone":"+61 8 8186 6000",
    "sg:postcode":"5160",
    "sg:province":"SA",
    "sg:tags":[
        "plumber",
        "gasfitters"
    ],
    "wof:name":"Sola Edwards Adelaide",
    "wof:placetype":"venue"
},
  "geometry": {"coordinates":[138.498947144,-35.1067886353],"type":"Point"}
}