{
  "type": "Feature",
  "properties": {
    "addr:full":"66 Allara St Canberra ACT 2600",
    "addr:housenumber":"66",
    "addr:postcode":"2600",
    "addr:street":"Allara St",
    "iso:country":"AU",
    "sg:address":"66 Allara St",
    "sg:city":"Canberra",
    "sg:classifiers":[
        {
            "category":"Personal",
            "subcategory":"Beauty Salon",
            "type":"Services"
        }
    ],
    "sg:phone":"+61 405 618 490",
    "sg:postcode":"2600",
    "sg:province":"ACT",
    "sg:tags":[
        "supply",
        "artist",
        "make-up"
    ],
    "wof:name":"Melody McCabe",
    "wof:placetype":"venue"
},
  "geometry": {"coordinates":[149.131317139,-35.2861061096],"type":"Point"}
}