{
  "type": "Feature",
  "properties": {
    "iso:country":"AU",
    "sg:address":"70 Research-Warrandyte Rd",
    "sg:city":"Research",
    "sg:classifiers":[
        {
            "category":"Farming",
            "subcategory":"Farm & Veterinary Services",
            "type":"Manufacturing & Wholesale Goods"
        }
    ],
    "sg:phone":"+61 408 107 735",
    "sg:postcode":"3095",
    "sg:province":"VIC",
    "sg:tags":[
        "contracting"
    ],
    "wof:name":"Joslyn Geoffrey W",
    "wof:placetype":"venue"
},
  "geometry": {"coordinates":[145.19361877399999,-37.7100257874],"type":"Point"}
}