{
  "type": "Feature",
  "properties": {
    "iso:country":"AU",
    "sg:address":"2 Staughton Pl",
    "sg:city":"Hoppers Crossing",
    "sg:classifiers":[
        {
            "category":"Retail",
            "subcategory":"Storage",
            "type":"Services"
        }
    ],
    "sg:phone":"+61 423 772 019",
    "sg:postcode":"3029",
    "sg:province":"VIC",
    "sg:tags":[
        "removal",
        "furniture"
    ],
    "wof:name":"Mulholland James",
    "wof:placetype":"venue"
},
  "geometry": {"coordinates":[144.68167099999999,-37.872044],"type":"Point"}
}