{
  "type": "Feature",
  "properties": {
    "addr:full":"66 Noosa Drv Noosa Heads QLD 4567",
    "addr:housenumber":"66",
    "addr:postcode":"4567",
    "addr:street":"Noosa Drv",
    "iso:country":"AU",
    "sg:address":"66 Noosa Drv",
    "sg:city":"Noosa Heads",
    "sg:classifiers":[
        {
            "category":"Autos & Motor Vehicles",
            "subcategory":"Fuel & Gas Station",
            "type":"Retail Goods"
        }
    ],
    "sg:phone":"+61 7 5474 8800",
    "sg:postcode":"4567",
    "sg:province":"QLD",
    "wof:name":"Mobil Oil Australia Pty Ltd",
    "wof:placetype":"venue"
},
  "geometry": {"coordinates":[153.088912964,-26.3962402344],"type":"Point"}
}