{
  "type": "Feature",
  "properties": {
    "addr:full":"Suite 6/ 139 Alexander St Crows Nest NSW 2065",
    "addr:housenumber":"/ 139",
    "addr:postcode":"2065",
    "addr:street":"Alexander St",
    "iso:country":"AU",
    "sg:address":"Suite 6/ 139 Alexander St",
    "sg:city":"Crows Nest",
    "sg:classifiers":[
        {
            "category":"Building & Trades",
            "subcategory":"Construction",
            "type":"Services"
        }
    ],
    "sg:phone":"+61 2 9460 9687",
    "sg:postcode":"2065",
    "sg:province":"NSW",
    "sg:tags":[
        "brick",
        "paving"
    ],
    "wof:name":"Grand Paving Pty Ltd",
    "wof:placetype":"venue"
},
  "geometry": {"coordinates":[151.20291137699999,-33.8240013123],"type":"Point"}
}