{
  "type": "Feature",
  "properties": {
    "addr:full":"30 Clement Rd Athelstone SA 5076",
    "addr:housenumber":"30",
    "addr:postcode":"5076",
    "addr:street":"Clement Rd",
    "iso:country":"AU",
    "sg:address":"30 Clement Rd",
    "sg:city":"Athelstone",
    "sg:classifiers":[
        {
            "category":"Utilities",
            "subcategory":"Natural Gas",
            "type":"Services"
        }
    ],
    "sg:phone":"+61 8 8336 6385",
    "sg:postcode":"5076",
    "sg:province":"SA",
    "sg:tags":[
        "solid",
        "plasterer"
    ],
    "wof:name":"Fine Line Plastering Contractors",
    "wof:placetype":"venue"
},
  "geometry": {"coordinates":[138.71762085,-34.8666687012],"type":"Point"}
}