{
  "type": "Feature",
  "properties": {
    "addr:full":"9 Hays St Goolwa SA 5214",
    "addr:housenumber":"9",
    "addr:postcode":"5214",
    "addr:street":"Hays St",
    "iso:country":"AU",
    "sg:address":"9 Hays St",
    "sg:city":"Goolwa",
    "sg:classifiers":[
        {
            "category":"Building & Trades",
            "subcategory":"Construction",
            "type":"Services"
        }
    ],
    "sg:phone":"+61 8 8555 1534",
    "sg:postcode":"5214",
    "sg:province":"SA",
    "sg:tags":[
        "equipment",
        "system",
        "automation"
    ],
    "wof:name":"Up-Link Communications",
    "wof:placetype":"venue"
},
  "geometry": {"coordinates":[138.78343200699999,-35.5048522949],"type":"Point"}
}