{
  "type": "Feature",
  "properties": {
    "addr:full":"Banks St Yarralumla ACT 2600",
    "addr:postcode":"2600",
    "addr:street":"Banks St",
    "iso:country":"AU",
    "sg:address":"Banks St",
    "sg:city":"Yarralumla",
    "sg:classifiers":[
        {
            "category":"Metro Station",
            "type":"Transportation"
        }
    ],
    "sg:phone":"+61 2 6281 8450",
    "sg:postcode":"2600",
    "sg:province":"ACT",
    "sg:tags":[
        "consultant",
        "marine"
    ],
    "wof:name":"Australian Marine Science & Technology Ltd",
    "wof:placetype":"venue"
},
  "geometry": {"coordinates":[149.09556579599999,-35.3059654236],"type":"Point"}
}