{
  "type": "Feature",
  "properties": {
    "addr:full":"Shop 9, The Mark Building, Orchid Ave Surfers Paradise QLD 4217",
    "addr:housenumber":"shop 9",
    "addr:postcode":"4217",
    "addr:street":"The;Orchid Ave",
    "iso:country":"AU",
    "sg:address":"Shop 9, The Mark Building, Orchid Ave",
    "sg:city":"Surfers Paradise",
    "sg:classifiers":[
        {
            "category":"Recreation",
            "type":"Entertainment"
        }
    ],
    "sg:phone":"+61 7 5592 2817",
    "sg:postcode":"4217",
    "sg:province":"QLD",
    "sg:tags":[
        "hire",
        "tour",
        "motor",
        "cycle"
    ],
    "wof:name":"Eagle Motorcycle Tours Pty Ltd",
    "wof:placetype":"venue"
},
  "geometry": {"coordinates":[153.429595947,-28.00050354],"type":"Point"}
}