{
  "type": "Feature",
  "properties": {
    "addr:full":"50 Liston Rd Lonsdale SA 5160",
    "addr:housenumber":"50",
    "addr:postcode":"5160",
    "addr:street":"Liston Rd",
    "iso:country":"AU",
    "sg:address":"50 Liston Rd",
    "sg:city":"Lonsdale",
    "sg:classifiers":[
        {
            "category":"Military Area",
            "subcategory":"Air Force Base",
            "type":"Public Place"
        }
    ],
    "sg:phone":"+61 8 8387 4221",
    "sg:postcode":"5160",
    "sg:province":"SA",
    "sg:tags":[
        "conditioner",
        "treatment",
        "soil"
    ],
    "wof:name":"S.A. Composters",
    "wof:placetype":"venue"
},
  "geometry": {"coordinates":[138.50831604000001,-35.1007843018],"type":"Point"}
}