{
  "type": "Feature",
  "properties": {
    "addr:full":"Heinjus Rd Strathalbyn SA 5255",
    "addr:postcode":"5255",
    "addr:street":"Heinjus Rd",
    "iso:country":"AU",
    "sg:address":"Heinjus Rd",
    "sg:city":"Strathalbyn",
    "sg:classifiers":[
        {
            "category":"Farming",
            "subcategory":"Nursery",
            "type":"Manufacturing & Wholesale Goods"
        }
    ],
    "sg:phone":"+61 412 391 989",
    "sg:postcode":"5255",
    "sg:province":"SA",
    "wof:name":"Burian Tom Orchids",
    "wof:placetype":"venue"
},
  "geometry": {"coordinates":[138.938232422,-35.2247276306],"type":"Point"}
}