{
  "type": "Feature",
  "properties": {
    "iso:country":"AU",
    "sg:address":"55 Peisley St",
    "sg:city":"Orange",
    "sg:classifiers":[
        {
            "category":"Retail",
            "subcategory":"Auto Repair",
            "type":"Services"
        }
    ],
    "sg:phone":"+61 2 6362 7511",
    "sg:postcode":"2800",
    "sg:province":"NSW",
    "sg:tags":[
        "repairer",
        "motor",
        "engineer"
    ],
    "wof:name":"Eslick's Mechanical Repairs",
    "wof:placetype":"venue"
},
  "geometry": {"coordinates":[149.10353088400001,-33.2838134766],"type":"Point"}
}