{
  "type": "Feature",
  "properties": {
    "addr:full":"George Campbell Drv Mudgee NSW 2850",
    "addr:postcode":"2850",
    "addr:street":"Campbell Drv",
    "iso:country":"AU",
    "sg:address":"George Campbell Drv",
    "sg:city":"Mudgee",
    "sg:classifiers":[
        {
            "category":"Restaurant",
            "type":"Food & Drink"
        }
    ],
    "sg:phone":"+61 2 6372 6816",
    "sg:postcode":"2850",
    "sg:province":"NSW",
    "wof:name":"Augustine Food House",
    "wof:placetype":"venue"
},
  "geometry": {"coordinates":[149.61677599999999,-32.565758],"type":"Point"}
}