{
  "type": "Feature",
  "properties": {
    "addr:full":"3 Central Park Rd Malvern East VIC 3145",
    "addr:housenumber":"3",
    "addr:postcode":"3145",
    "addr:street":"Central Park Rd",
    "iso:country":"AU",
    "sg:address":"3 Central Park Rd",
    "sg:city":"Malvern East",
    "sg:classifiers":[
        {
            "category":"Health Services",
            "subcategory":"Health Practitioner",
            "type":"Services"
        }
    ],
    "sg:phone":"+61 3 9509 7376",
    "sg:postcode":"3145",
    "sg:province":"VIC",
    "sg:tags":[
        "naturopath"
    ],
    "wof:name":"Natural Medicine & Weight Management Clinic",
    "wof:placetype":"venue"
},
  "geometry": {"coordinates":[145.04029846200001,-37.8677024841],"type":"Point"}
}