{
  "type": "Feature",
  "properties": {
    "iso:country":"AU",
    "sg:address":"3 jannah Crt",
    "sg:city":"Mornington",
    "sg:classifiers":[
        {
            "category":"Building & Trades",
            "subcategory":"Construction",
            "type":"Services"
        }
    ],
    "sg:phone":"+61 438 446 323",
    "sg:postcode":"7018",
    "sg:province":"TAS",
    "sg:tags":[
        "welding"
    ],
    "wof:name":"JT WEIR",
    "wof:placetype":"venue"
},
  "geometry": {"coordinates":[147.40037536599999,-42.8623352051],"type":"Point"}
}