{
  "type": "Feature",
  "properties": {
    "addr:full":"Mt Nathan Rd Nerang QLD 4211",
    "addr:postcode":"4211",
    "addr:street":"Nathan Rd",
    "iso:country":"AU",
    "sg:address":"Mt Nathan Rd",
    "sg:city":"Nerang",
    "sg:classifiers":[
        {
            "category":"Farming",
            "subcategory":"Nursery",
            "type":"Manufacturing & Wholesale Goods"
        }
    ],
    "sg:phone":"+61 7 5533 7266",
    "sg:postcode":"4211",
    "sg:province":"QLD",
    "wof:name":"Country Gardens Nursery",
    "wof:placetype":"venue"
},
  "geometry": {"coordinates":[153.30056762699999,-28.0004062653],"type":"Point"}
}