{
  "type": "Feature",
  "properties": {
    "addr:full":"Shop1-6 Pearson St Bunyip VIC 3815",
    "addr:postcode":"3815",
    "addr:street":"Pearson St",
    "iso:country":"AU",
    "sg:address":"Shop1-6 Pearson St",
    "sg:city":"Bunyip",
    "sg:classifiers":[
        {
            "category":"Personal",
            "subcategory":"Beauty Salon",
            "type":"Services"
        }
    ],
    "sg:phone":"+61 3 5629 5107",
    "sg:postcode":"3815",
    "sg:province":"VIC",
    "wof:name":"Mermaid Beauty Therapy",
    "wof:placetype":"venue"
},
  "geometry": {"coordinates":[145.717758,-38.097469],"type":"Point"}
}