{
  "type": "Feature",
  "properties": {
    "iso:country":"AU",
    "sg:address":"Poseidon Rd",
    "sg:city":"Heathridge",
    "sg:classifiers":[
        {
            "category":"Education",
            "subcategory":"School",
            "type":"Public Place"
        }
    ],
    "sg:phone":"+61 8 9307 2356",
    "sg:postcode":"6027",
    "sg:province":"WA",
    "sg:tags":[
        "state",
        "except",
        "nsw"
    ],
    "wof:name":"Poseidon Primary School",
    "wof:placetype":"venue"
},
  "geometry": {"coordinates":[115.75521850600001,-31.7642364502],"type":"Point"}
}