{
  "type": "Feature",
  "properties": {
    "addr:full":"20 Bay St Tweed Heads NSW 2485",
    "addr:housenumber":"20",
    "addr:postcode":"2485",
    "addr:street":"Bay St",
    "iso:country":"AU",
    "sg:address":"20 Bay St",
    "sg:city":"Tweed Heads",
    "sg:classifiers":[
        {
            "category":"Banks & Credit Unions",
            "subcategory":"Financial Services",
            "type":"Services"
        }
    ],
    "sg:phone":"+61 7 5599 3355",
    "sg:postcode":"2485",
    "sg:province":"NSW",
    "sg:tags":[
        "annuity",
        "rollover",
        "superannuation",
        "consultant"
    ],
    "wof:name":"AMP - Wendy Scarlett",
    "wof:placetype":"venue"
},
  "geometry": {"coordinates":[153.542114258,-28.1710605621],"type":"Point"}
}