{
  "type": "Feature",
  "properties": {
    "addr:full":"3 McKern St Wentworthville NSW 2145",
    "addr:housenumber":"3",
    "addr:postcode":"2145",
    "addr:street":"Mckern St",
    "iso:country":"AU",
    "sg:address":"3 McKern St",
    "sg:city":"Wentworthville",
    "sg:classifiers":[
        {
            "category":"Social Services",
            "subcategory":"Child Care",
            "type":"Services"
        }
    ],
    "sg:phone":"+61 2 9631 8258",
    "sg:postcode":"2145",
    "sg:province":"NSW",
    "sg:tags":[
        "support",
        "health"
    ],
    "wof:name":"Early Childhood Health Centres",
    "wof:placetype":"venue"
},
  "geometry": {"coordinates":[150.97134399399999,-33.809753418],"type":"Point"}
}