{
  "type": "Feature",
  "properties": {
    "iso:country":"AU",
    "sg:address":"Creswick Rd",
    "sg:city":"Ballarat",
    "sg:classifiers":[
        {
            "category":"Food & Beverages",
            "subcategory":"Liquor & Beverages",
            "type":"Retail Goods"
        }
    ],
    "sg:phone":"+61 3 5331 1308",
    "sg:postcode":"3350",
    "sg:province":"VIC",
    "sg:tags":[
        "store"
    ],
    "wof:name":"Harrys Liquor",
    "wof:placetype":"venue"
},
  "geometry": {"coordinates":[143.855026,-37.557148],"type":"Point"}
}