{
  "type": "Feature",
  "properties": {
    "iso:country":"AU",
    "sg:address":"25A Marks St",
    "sg:city":"Naremburn",
    "sg:classifiers":[
        {
            "category":"Retail",
            "subcategory":"Storage",
            "type":"Services"
        }
    ],
    "sg:phone":"+61 2 9439 7512",
    "sg:postcode":"2065",
    "sg:province":"NSW",
    "sg:tags":[
        "removal",
        "furniture"
    ],
    "wof:name":"AAARRIVEONTIME REMOVALS",
    "wof:placetype":"venue"
},
  "geometry": {"coordinates":[151.20645141599999,-33.8188362122],"type":"Point"}
}