{
  "type": "Feature",
  "properties": {
    "addr:full":"59 Chetwind St North Melbourne VIC 3051",
    "addr:housenumber":"59",
    "addr:postcode":"3051",
    "addr:street":"Chetwind St",
    "iso:country":"AU",
    "sg:address":"59 Chetwind St",
    "sg:city":"North Melbourne",
    "sg:classifiers":[
        {
            "category":"Health Services",
            "subcategory":"Doctor",
            "type":"Services"
        }
    ],
    "sg:phone":"+61 3 9348 9103",
    "sg:postcode":"3051",
    "sg:province":"VIC",
    "sg:tags":[
        "occupational",
        "safety"
    ],
    "wof:name":"Nosa Limited Australia",
    "wof:placetype":"venue"
},
  "geometry": {"coordinates":[144.95216369600001,-37.8047218323],"type":"Point"}
}