{
  "type": "Feature",
  "properties": {
    "addr:full":"213 Church St Parramatta NSW 2150",
    "addr:housenumber":"213",
    "addr:postcode":"2150",
    "addr:street":"Church St",
    "iso:country":"AU",
    "sg:address":"213 Church St",
    "sg:city":"Parramatta",
    "sg:classifiers":[
        {
            "category":"Wholesale",
            "subcategory":"Apparel",
            "type":"Manufacturing & Wholesale Goods"
        }
    ],
    "sg:phone":"+61 2 9635 4300",
    "sg:postcode":"2150",
    "sg:province":"NSW",
    "sg:tags":[
        "wholesaler",
        "men's",
        "mfrs",
        "sportswear"
    ],
    "wof:name":"Champion Sportswear",
    "wof:placetype":"venue"
},
  "geometry": {"coordinates":[151.00296020499999,-33.8144989014],"type":"Point"}
}