{
  "type": "Feature",
  "properties": {
    "addr:full":"Shop 11b Walsend Plz Cowper St Wallsend NSW 2287",
    "addr:housenumber":"11b",
    "addr:postcode":"2287",
    "addr:street":"Shop;Walsend Plz Cowper St",
    "iso:country":"AU",
    "sg:address":"Shop 11b Walsend Plz Cowper St",
    "sg:city":"Wallsend",
    "sg:classifiers":[
        {
            "category":"Banks & Credit Unions",
            "subcategory":"Financial Services",
            "type":"Services"
        }
    ],
    "sg:phone":"+61 2 4955 5744",
    "sg:postcode":"2287",
    "sg:province":"NSW",
    "sg:tags":[
        "financier"
    ],
    "wof:name":"GE Finance and Insurance",
    "wof:placetype":"venue"
},
  "geometry": {"coordinates":[151.66819763199999,-32.9037399292],"type":"Point"}
}