{
  "type": "Feature",
  "properties": {
    "iso:country":"AU",
    "sg:address":"Shp2 46 Garden City Shopng Cntr Cnr Park Ave & Nor",
    "sg:city":"Kotara",
    "sg:classifiers":[
        {
            "category":"Retail",
            "subcategory":"Repair Shop",
            "type":"Services"
        }
    ],
    "sg:phone":"+61 2 4957 7017",
    "sg:postcode":"2289",
    "sg:province":"NSW",
    "sg:tags":[
        "handbag"
    ],
    "wof:name":"Kays Bag Stores (NSW) Pty Ltd",
    "wof:placetype":"venue"
},
  "geometry": {"coordinates":[151.710693359,-32.9406433105],"type":"Point"}
}