{
  "type": "Feature",
  "properties": {
    "addr:full":"10 Gardiner St Gisborne VIC 3437",
    "addr:housenumber":"10",
    "addr:postcode":"3437",
    "addr:street":"Gardiner St",
    "iso:country":"AU",
    "sg:address":"10 Gardiner St",
    "sg:city":"Gisborne",
    "sg:classifiers":[
        {
            "category":"Building & Trades",
            "subcategory":"Landscaping Services",
            "type":"Services"
        }
    ],
    "sg:phone":"+61 3 5428 8878",
    "sg:postcode":"3437",
    "sg:province":"VIC",
    "sg:tags":[
        "stump",
        "tree",
        "felling",
        "removal"
    ],
    "wof:name":"Tarboree Tree Services",
    "wof:placetype":"venue"
},
  "geometry": {"coordinates":[144.60047912600001,-37.4952888489],"type":"Point"}
}