{
  "type": "Feature",
  "properties": {
    "addr:full":"4 Hawthorn Pl Orange NSW 2800",
    "addr:housenumber":"4",
    "addr:postcode":"2800",
    "addr:street":"Hawthorn Pl",
    "iso:country":"AU",
    "sg:address":"4 Hawthorn Pl",
    "sg:city":"Orange",
    "sg:classifiers":[
        {
            "category":"Building & Trades",
            "subcategory":"Construction",
            "type":"Services"
        }
    ],
    "sg:phone":"+61 400 658 506",
    "sg:postcode":"2800",
    "sg:province":"NSW",
    "sg:tags":[
        "fencing",
        "contractor"
    ],
    "wof:name":"Skeltech Fabrication",
    "wof:placetype":"venue"
},
  "geometry": {"coordinates":[149.111785889,-33.3093757629],"type":"Point"}
}