{
  "type": "Feature",
  "properties": {
    "iso:country":"AU",
    "sg:address":"37 Kinghorne St",
    "sg:city":"Goulburn",
    "sg:classifiers":[
        {
            "category":"Utilities",
            "subcategory":"Water",
            "type":"Services"
        }
    ],
    "sg:phone":"+61 419 437 502",
    "sg:postcode":"2580",
    "sg:province":"NSW",
    "sg:tags":[
        "hot",
        "system"
    ],
    "wof:name":"David Alt Electrical",
    "wof:placetype":"venue"
},
  "geometry": {"coordinates":[149.72633361800001,-34.7427215576],"type":"Point"}
}