{
  "type": "Feature",
  "properties": {
    "addr:full":"11 Mount Barker Rd Mt Barker SA 5251",
    "addr:housenumber":"11",
    "addr:postcode":"5251",
    "addr:street":"Mount Barker Rd",
    "iso:country":"AU",
    "sg:address":"11 Mount Barker Rd",
    "sg:city":"Mt Barker",
    "sg:classifiers":[
        {
            "category":"Farming",
            "subcategory":"Farm & Veterinary Services",
            "type":"Manufacturing & Wholesale Goods"
        }
    ],
    "sg:phone":"+61 8 8391 5722",
    "sg:postcode":"5251",
    "sg:province":"SA",
    "sg:tags":[
        "irrigation",
        "reticulation",
        "system"
    ],
    "wof:name":"Irrigation Pumps&#039;N&#039;More",
    "wof:placetype":"venue"
},
  "geometry": {"coordinates":[138.84877014200001,-35.0535736084],"type":"Point"}
}