{
  "type": "Feature",
  "properties": {
    "addr:full":"PO Box 1009 Murwillumbah NSW 2484",
    "addr:postcode":"2484",
    "iso:country":"AU",
    "sg:address":"PO Box 1009",
    "sg:city":"Murwillumbah",
    "sg:classifiers":[
        {
            "category":"Manufacturing",
            "subcategory":"Jewelry",
            "type":"Manufacturing & Wholesale Goods"
        }
    ],
    "sg:phone":"+61 2 6677 9585",
    "sg:postcode":"2484",
    "sg:province":"NSW",
    "sg:tags":[
        "mfrg",
        "jeweller"
    ],
    "wof:name":"Local Talent Jewels",
    "wof:placetype":"venue"
},
  "geometry": {"coordinates":[153.39169311500001,-28.3299503326],"type":"Point"}
}