{
  "type": "Feature",
  "properties": {
    "addr:full":"Level 1, 1 Collins St Melbourne VIC 3000",
    "addr:housenumber":"1",
    "addr:postcode":"3000",
    "addr:street":"Collins St",
    "iso:country":"AU",
    "sg:address":"Level 1, 1 Collins St",
    "sg:city":"Melbourne",
    "sg:classifiers":[
        {
            "category":"Professional",
            "subcategory":"Computer Services",
            "type":"Services"
        }
    ],
    "sg:phone":"+61 3 9631 7900",
    "sg:postcode":"3000",
    "sg:province":"VIC",
    "sg:tags":[
        "package",
        "software"
    ],
    "wof:name":"Information Builders Pty Ltd",
    "wof:placetype":"venue"
},
  "geometry": {"coordinates":[144.97392273,-37.8134498596],"type":"Point"}
}