{
  "type": "Feature",
  "properties": {
    "addr:full":"134 Bailey Rd Mt Evelyn VIC 3796",
    "addr:housenumber":"134",
    "addr:postcode":"3796",
    "addr:street":"Bailey Rd",
    "iso:country":"AU",
    "sg:address":"134 Bailey Rd",
    "sg:city":"Mt Evelyn",
    "sg:classifiers":[
        {
            "category":"Manufacturing",
            "subcategory":"Textiles",
            "type":"Manufacturing & Wholesale Goods"
        }
    ],
    "sg:phone":"+61 407 370 913",
    "sg:postcode":"3796",
    "sg:province":"VIC",
    "sg:tags":[
        "agent"
    ],
    "wof:name":"Australian Textile Marketing Pty Ltd",
    "wof:placetype":"venue"
},
  "geometry": {"coordinates":[145.395263672,-37.7815322876],"type":"Point"}
}