{
  "type": "Feature",
  "properties": {
    "addr:full":"9 Corporation Pl Orange NSW 2800",
    "addr:housenumber":"9",
    "addr:postcode":"2800",
    "addr:street":"Corporation Pl",
    "iso:country":"AU",
    "sg:address":"9 Corporation Pl",
    "sg:city":"Orange",
    "sg:classifiers":[
        {
            "category":"Professional",
            "type":"Services"
        }
    ],
    "sg:phone":"+61 2 6362 9687",
    "sg:postcode":"2800",
    "sg:province":"NSW",
    "sg:tags":[
        "transport"
    ],
    "wof:name":"Harvey Transport",
    "wof:placetype":"venue"
},
  "geometry": {"coordinates":[149.10765075699999,-33.313117981],"type":"Point"}
}