{
  "type": "Feature",
  "properties": {
    "addr:full":"422 Albion St Brunswick West VIC 3055",
    "addr:housenumber":"422",
    "addr:postcode":"3055",
    "addr:street":"Albion St",
    "iso:country":"AU",
    "sg:address":"422 Albion St",
    "sg:city":"Brunswick West",
    "sg:classifiers":[
        {
            "category":"Professional",
            "subcategory":"Lawyer & Legal Services",
            "type":"Services"
        }
    ],
    "sg:phone":"+61 3 9386 3548",
    "sg:postcode":"3055",
    "sg:province":"VIC",
    "sg:tags":[
        "process",
        "server"
    ],
    "wof:name":"J.J.R. Australia Pty Ltd",
    "wof:placetype":"venue"
},
  "geometry": {"coordinates":[144.94134521500001,-37.7583694458],"type":"Point"}
}