{
  "type": "Feature",
  "properties": {
    "iso:country":"AU",
    "sg:address":"Ingham Rd",
    "sg:city":"Bohle",
    "sg:classifiers":[
        {
            "category":"Professional",
            "subcategory":"Testing Lab",
            "type":"Services"
        }
    ],
    "sg:phone":"+61 7 4774 8045",
    "sg:postcode":"4818",
    "sg:province":"QLD",
    "sg:tags":[
        "inspection"
    ],
    "wof:name":"Readymix",
    "wof:placetype":"venue"
},
  "geometry": {"coordinates":[146.711548,-19.26277],"type":"Point"}
}