{
  "type": "Feature",
  "properties": {
    "addr:full":"PO Box 360 Roseville NSW 2069",
    "addr:postcode":"2069",
    "iso:country":"AU",
    "sg:address":"PO Box 360",
    "sg:city":"Roseville",
    "sg:classifiers":[
        {
            "category":"Shopping",
            "subcategory":"Stationery & Office Supplies",
            "type":"Retail Goods"
        }
    ],
    "sg:phone":"+61 2 8901 4621",
    "sg:postcode":"2069",
    "sg:province":"NSW",
    "sg:tags":[
        "partition"
    ],
    "wof:name":"CMC Interiors Pty Ltd",
    "wof:placetype":"venue"
},
  "geometry": {"coordinates":[151.17579650900001,-33.7836799622],"type":"Point"}
}