{
  "type": "Feature",
  "properties": {
    "addr:full":"27- 29 Whitehorse St Garbutt QLD 4814",
    "addr:housenumber":"29",
    "addr:postcode":"4814",
    "addr:street":"Whitehorse St",
    "iso:country":"AU",
    "sg:address":"27- 29 Whitehorse St",
    "sg:city":"Garbutt",
    "sg:classifiers":[
        {
            "category":"Professional",
            "type":"Services"
        }
    ],
    "sg:phone":"+61 13 14 06",
    "sg:postcode":"4814",
    "sg:province":"QLD",
    "sg:tags":[
        "courier"
    ],
    "wof:name":"DHL",
    "wof:placetype":"venue"
},
  "geometry": {"coordinates":[146.75509600000001,-19.269106],"type":"Point"}
}