{
  "type": "Feature",
  "properties": {
    "iso:country":"AU",
    "sg:address":"7 Blackwood Crt",
    "sg:city":"Drouin",
    "sg:classifiers":[
        {
            "category":"Retail",
            "subcategory":"Repair Shop",
            "type":"Services"
        }
    ],
    "sg:phone":"+61 3 5625 2365",
    "sg:postcode":"3818",
    "sg:province":"VIC",
    "sg:tags":[
        "upholsterer"
    ],
    "wof:name":"West Gippsland Upholstery",
    "wof:placetype":"venue"
},
  "geometry": {"coordinates":[145.845078,-38.133537],"type":"Point"}
}