{
  "type": "Feature",
  "properties": {
    "addr:full":"14 Deacon Ave Richmond SA 5033",
    "addr:housenumber":"14",
    "addr:postcode":"5033",
    "addr:street":"Deacon Ave",
    "iso:country":"AU",
    "sg:address":"14 Deacon Ave",
    "sg:city":"Richmond",
    "sg:classifiers":[
        {
            "category":"Food & Beverages",
            "subcategory":"Bakery",
            "type":"Retail Goods"
        }
    ],
    "sg:phone":"+61 8 8234 0766",
    "sg:postcode":"5033",
    "sg:province":"SA",
    "sg:tags":[
        "baker"
    ],
    "wof:name":"Unique Homestyle Foods",
    "wof:placetype":"venue"
},
  "geometry": {"coordinates":[138.56869506800001,-34.9399604797],"type":"Point"}
}