{
  "type": "Feature",
  "properties": {
    "addr:full":"75 Orange Ave Mildura VIC 3500",
    "addr:housenumber":"75",
    "addr:postcode":"3500",
    "addr:street":"Orange Ave",
    "iso:country":"AU",
    "sg:address":"75 Orange Ave",
    "sg:city":"Mildura",
    "sg:classifiers":[
        {
            "category":"Education",
            "subcategory":"Special Training",
            "type":"Public Place"
        }
    ],
    "sg:phone":"+61 3 5022 2900",
    "sg:postcode":"3500",
    "sg:province":"VIC",
    "sg:tags":[
        "development"
    ],
    "wof:name":"ANI Pty Ltd",
    "wof:placetype":"venue"
},
  "geometry": {"coordinates":[142.163131714,-34.1879425049],"type":"Point"}
}