{
  "type": "Feature",
  "properties": {
    "addr:full":"6 Thompson St Long Jetty NSW 2261",
    "addr:housenumber":"6",
    "addr:postcode":"2261",
    "addr:street":"Thompson St",
    "iso:country":"AU",
    "sg:address":"6 Thompson St",
    "sg:city":"Long Jetty",
    "sg:classifiers":[
        {
            "category":"Organizations",
            "subcategory":"Community Association",
            "type":"Services"
        }
    ],
    "sg:phone":"+61 2 4332 5522",
    "sg:postcode":"2261",
    "sg:province":"NSW",
    "sg:tags":[
        "club",
        "senior",
        "citizen"
    ],
    "wof:name":"Long Jetty Senior Citizens Centre Inc",
    "wof:placetype":"venue"
},
  "geometry": {"coordinates":[151.484116,-33.357098],"type":"Point"}
}