{
  "type": "Feature",
  "properties": {
    "iso:country":"AU",
    "sg:address":"PO Box 193",
    "sg:city":"Sans Souci",
    "sg:classifiers":[
        {
            "category":"Government",
            "subcategory":"Fire Station",
            "type":"Public Place"
        }
    ],
    "sg:phone":"+61 2 9529 9950",
    "sg:postcode":"2219",
    "sg:province":"NSW",
    "sg:tags":[
        "equipment",
        "protection",
        "consultant"
    ],
    "wof:name":"National Fire & Safety Pty Ltd",
    "wof:placetype":"venue"
},
  "geometry": {"coordinates":[151.132172,-33.992779],"type":"Point"}
}