{
  "type": "Feature",
  "properties": {
    "addr:full":"74 Macleod St Bairnsdale VIC 3875",
    "addr:housenumber":"74",
    "addr:postcode":"3875",
    "addr:street":"Macleod St",
    "iso:country":"AU",
    "sg:address":"74 Macleod St",
    "sg:city":"Bairnsdale",
    "sg:classifiers":[
        {
            "category":"Shopping",
            "subcategory":"Bicycles & Sporting Goods",
            "type":"Retail Goods"
        }
    ],
    "sg:phone":"+61 3 5152 4687",
    "sg:postcode":"3875",
    "sg:province":"VIC",
    "sg:tags":[
        "water",
        "equipment",
        "skiing"
    ],
    "wof:name":"Riviera Jet Ski",
    "wof:placetype":"venue"
},
  "geometry": {"coordinates":[147.631759644,-37.8270950317],"type":"Point"}
}