{
  "type": "Feature",
  "properties": {
    "addr:full":"9 Coolberry Rd Huntingdale WA 6110",
    "addr:housenumber":"9",
    "addr:postcode":"6110",
    "addr:street":"Coolberry Rd",
    "iso:country":"AU",
    "sg:address":"9 Coolberry Rd",
    "sg:city":"Huntingdale",
    "sg:classifiers":[
        {
            "category":"Building & Trades",
            "subcategory":"Construction",
            "type":"Services"
        }
    ],
    "sg:phone":"+61 8 9490 5962",
    "sg:postcode":"6110",
    "sg:province":"WA",
    "sg:tags":[
        "fencing",
        "contractor"
    ],
    "wof:name":"Wescombe W R & Kemp A",
    "wof:placetype":"venue"
},
  "geometry": {"coordinates":[115.962219238,-32.0833396912],"type":"Point"}
}