{
  "type": "Feature",
  "properties": {
    "addr:full":"The Pines Shopping Centre K.P. McGrath Drv Elanora QLD 4221",
    "addr:postcode":"4221",
    "addr:street":"K.P. Mcgrath Drv",
    "iso:country":"AU",
    "sg:address":"The Pines Shopping Centre K.P. McGrath Drv",
    "sg:city":"Elanora",
    "sg:classifiers":[
        {
            "category":"Health Services",
            "subcategory":"Dentist",
            "type":"Services"
        }
    ],
    "sg:phone":"+61 7 5521 0877",
    "sg:postcode":"4221",
    "sg:province":"QLD",
    "wof:name":"McNab Melissa",
    "wof:placetype":"venue"
},
  "geometry": {"coordinates":[153.46051025400001,-28.1234436035],"type":"Point"}
}