{
  "type": "Feature",
  "properties": {
    "addr:full":"Unit 1 239 Beechboro Rd Bayswater WA 6053",
    "addr:housenumber":"239",
    "addr:postcode":"6053",
    "addr:street":"Beechboro Rd",
    "iso:country":"AU",
    "sg:address":"Unit 1 239 Beechboro Rd",
    "sg:city":"Bayswater",
    "sg:classifiers":[
        {
            "category":"Retail",
            "subcategory":"Auto Repair",
            "type":"Services"
        }
    ],
    "sg:phone":"+61 414 344 863",
    "sg:postcode":"6053",
    "sg:province":"WA",
    "sg:tags":[
        "electrical"
    ],
    "wof:name":"Nationwide Auto Electrical",
    "wof:placetype":"venue"
},
  "geometry": {"coordinates":[115.923240662,-31.8957748413],"type":"Point"}
}