{
  "type": "Feature",
  "properties": {
    "addr:full":"35 Lydia St Tamworth NSW 2340",
    "addr:housenumber":"35",
    "addr:postcode":"2340",
    "addr:street":"Lydia St",
    "iso:country":"AU",
    "sg:address":"35 Lydia St",
    "sg:city":"Tamworth",
    "sg:classifiers":[
        {
            "category":"Retail",
            "subcategory":"Storage",
            "type":"Services"
        }
    ],
    "sg:phone":"+61 2 6765 7978",
    "sg:postcode":"2340",
    "sg:province":"NSW",
    "sg:tags":[
        "shelving",
        "system"
    ],
    "wof:name":"Whitham's Warehouse",
    "wof:placetype":"venue"
},
  "geometry": {"coordinates":[150.91958618199999,-31.1093044281],"type":"Point"}
}