{
  "type": "Feature",
  "properties": {
    "iso:country":"AU",
    "sg:address":"15 Robinson Ave",
    "sg:city":"Northbridge",
    "sg:classifiers":[
        {
            "category":"Travel",
            "subcategory":"Hotels & Motels",
            "type":"Entertainment"
        }
    ],
    "sg:phone":"+61 8 9328 0000",
    "sg:postcode":"6003",
    "sg:province":"WA",
    "sg:tags":[
        "accommodation"
    ],
    "wof:name":"Acacia Hotel",
    "wof:placetype":"venue"
},
  "geometry": {"coordinates":[115.863639831,-31.9444007874],"type":"Point"}
}