{
  "type": "Feature",
  "properties": {
    "addr:full":"118 Wynnum North Rd Wynnum QLD 4178",
    "addr:housenumber":"118",
    "addr:postcode":"4178",
    "addr:street":"Wynnum North Rd",
    "iso:country":"AU",
    "sg:address":"118 Wynnum North Rd",
    "sg:city":"Wynnum",
    "sg:classifiers":[
        {
            "category":"Building & Trades",
            "subcategory":"Construction",
            "type":"Services"
        }
    ],
    "sg:phone":"+61 7 3901 0166",
    "sg:postcode":"4178",
    "sg:province":"QLD",
    "sg:tags":[
        "home",
        "air conditioning"
    ],
    "wof:name":"Effective Heating & Cooling",
    "wof:placetype":"venue"
},
  "geometry": {"coordinates":[153.157714844,-27.4383544922],"type":"Point"}
}