{
  "type": "Feature",
  "properties": {
    "addr:full":"138 South St Toowoomba QLD 4350",
    "addr:housenumber":"138",
    "addr:postcode":"4350",
    "addr:street":"South St",
    "iso:country":"AU",
    "sg:address":"138 South St",
    "sg:city":"Toowoomba",
    "sg:classifiers":[
        {
            "category":"Manufacturing",
            "subcategory":"Food",
            "type":"Manufacturing & Wholesale Goods"
        }
    ],
    "sg:phone":"+61 7 4635 1568",
    "sg:postcode":"4350",
    "sg:province":"QLD",
    "sg:tags":[
        "function",
        "catering"
    ],
    "wof:name":"Gray's Modern Meat Mart",
    "wof:placetype":"venue"
},
  "geometry": {"coordinates":[151.90742499999999,-27.571968],"type":"Point"}
}