{
  "type": "Feature",
  "properties": {
    "addr:full":"2 Jubaea Crt Canning Vale WA 6155",
    "addr:housenumber":"2",
    "addr:postcode":"6155",
    "addr:street":"Jubaea Crt",
    "iso:country":"AU",
    "sg:address":"2 Jubaea Crt",
    "sg:city":"Canning Vale",
    "sg:classifiers":[
        {
            "category":"Building & Trades",
            "subcategory":"Construction",
            "type":"Services"
        }
    ],
    "sg:phone":"+61 418 945 183",
    "sg:postcode":"6155",
    "sg:province":"WA",
    "sg:tags":[
        "contractor"
    ],
    "wof:name":"Livingston Construction",
    "wof:placetype":"venue"
},
  "geometry": {"coordinates":[115.917084,-32.072933],"type":"Point"}
}