{
  "type": "Feature",
  "properties": {
    "iso:country":"AU",
    "sg:address":"Unit 1b/ 7 Enniss Ave",
    "sg:city":"Cooloongup",
    "sg:classifiers":[
        {
            "category":"Personal",
            "subcategory":"Beauty Salon",
            "type":"Services"
        }
    ],
    "sg:phone":"+61 8 9528 6778",
    "sg:postcode":"6168",
    "sg:province":"WA",
    "sg:tags":[
        "hairdresser"
    ],
    "wof:name":"Hot Rods Hairdressing",
    "wof:placetype":"venue"
},
  "geometry": {"coordinates":[115.763496,-32.2953],"type":"Point"}
}