{
  "type": "Feature",
  "properties": {
    "iso:country":"AU",
    "sg:address":"12 Marcia St",
    "sg:city":"Coffs Harbour",
    "sg:classifiers":[
        {
            "category":"Building & Trades",
            "subcategory":"Construction",
            "type":"Services"
        }
    ],
    "sg:phone":"+61 2 6652 4966",
    "sg:postcode":"2450",
    "sg:province":"NSW",
    "sg:tags":[
        "ceiling"
    ],
    "wof:name":"Plastamasta Centre",
    "wof:placetype":"venue"
},
  "geometry": {"coordinates":[153.116287,-30.289358],"type":"Point"}
}