{
  "type": "Feature",
  "properties": {
    "addr:full":"Unit 1, 13 Carnaby St Maroochydore QLD 4558",
    "addr:housenumber":"13",
    "addr:postcode":"4558",
    "addr:street":"Carnaby St",
    "iso:country":"AU",
    "sg:address":"Unit 1, 13 Carnaby St",
    "sg:city":"Maroochydore",
    "sg:classifiers":[
        {
            "category":"Professional",
            "subcategory":"Accounting & Tax Preparation",
            "type":"Services"
        }
    ],
    "sg:phone":"+61 7 5479 0060",
    "sg:postcode":"4558",
    "sg:province":"QLD",
    "sg:tags":[
        "accountant",
        "auditor"
    ],
    "wof:name":"Thomson Green Pty Ltd",
    "wof:placetype":"venue"
},
  "geometry": {"coordinates":[153.08682250999999,-26.6576461792],"type":"Point"}
}