{
  "type": "Feature",
  "properties": {
    "addr:full":"18 Sandra Pl Welshpool WA 6106",
    "addr:housenumber":"18",
    "addr:postcode":"6106",
    "addr:street":"Sandra Pl",
    "iso:country":"AU",
    "sg:address":"18 Sandra Pl",
    "sg:city":"Welshpool",
    "sg:classifiers":[
        {
            "category":"Autos & Motor Vehicles",
            "subcategory":"Automobile Sales",
            "type":"Retail Goods"
        }
    ],
    "sg:phone":"+61 8 9362 6955",
    "sg:postcode":"6106",
    "sg:province":"WA",
    "sg:tags":[
        "car",
        "used"
    ],
    "wof:name":"Wheels Cars & Commercials",
    "wof:placetype":"venue"
},
  "geometry": {"coordinates":[115.929580688,-31.9829406738],"type":"Point"}
}