{
  "type": "Feature",
  "properties": {
    "addr:full":"8 Shannon Crt Dingley VIC 3172",
    "addr:housenumber":"8",
    "addr:postcode":"3172",
    "addr:street":"Shannon Crt",
    "iso:country":"AU",
    "sg:address":"8 Shannon Crt",
    "sg:city":"Dingley",
    "sg:classifiers":[
        {
            "category":"Manufacturing",
            "subcategory":"Retail Goods",
            "type":"Manufacturing & Wholesale Goods"
        }
    ],
    "sg:phone":"+61 1800 775 511",
    "sg:postcode":"3172",
    "sg:province":"VIC",
    "sg:tags":[
        "merchant",
        "pump",
        "mfrs"
    ],
    "wof:name":"Fire Pumps Australia",
    "wof:placetype":"venue"
},
  "geometry": {"coordinates":[145.12005615199999,-37.9743728638],"type":"Point"}
}