{
  "type": "Feature",
  "properties": {
    "addr:full":"274 Church St Richmond VIC 3121",
    "addr:housenumber":"274",
    "addr:postcode":"3121",
    "addr:street":"Church St",
    "iso:country":"AU",
    "sg:address":"274 Church St",
    "sg:city":"Richmond",
    "sg:classifiers":[
        {
            "category":"Shopping",
            "subcategory":"Clothing, Apparel, & Fashions",
            "type":"Retail Goods"
        }
    ],
    "sg:phone":"+61 3 9428 3988",
    "sg:postcode":"3121",
    "sg:province":"VIC",
    "sg:tags":[
        "maternity",
        "wear"
    ],
    "sg:website":"http://www.mother2b.com.au",
    "wof:name":"Mother 2B",
    "wof:placetype":"venue"
},
  "geometry": {"coordinates":[144.99882507300001,-37.8195457458],"type":"Point"}
}