{
  "type": "Feature",
  "properties": {
    "addr:full":"226 Headland Rd Dee Why NSW 2099",
    "addr:housenumber":"226",
    "addr:postcode":"2099",
    "addr:street":"Headland Rd",
    "iso:country":"AU",
    "sg:address":"226 Headland Rd",
    "sg:city":"Dee Why",
    "sg:classifiers":[
        {
            "category":"Manufacturing",
            "subcategory":"Rubber & Plastics",
            "type":"Manufacturing & Wholesale Goods"
        }
    ],
    "sg:phone":"+61 2 9905 6433",
    "sg:postcode":"2099",
    "sg:province":"NSW",
    "sg:tags":[
        "wholesaler",
        "product",
        "mfrs"
    ],
    "wof:name":"Popular Home Products",
    "wof:placetype":"venue"
},
  "geometry": {"coordinates":[151.281814575,-33.7600288391],"type":"Point"}
}