{
  "type": "Feature",
  "properties": {
    "addr:full":"Unit 2/ 4 Textile Ave Warana QLD 4575",
    "addr:housenumber":"4",
    "addr:postcode":"4575",
    "addr:street":"Textile Ave",
    "iso:country":"AU",
    "sg:address":"Unit 2/ 4 Textile Ave",
    "sg:city":"Warana",
    "sg:classifiers":[
        {
            "category":"Professional",
            "subcategory":"Testing Lab",
            "type":"Services"
        }
    ],
    "sg:phone":"+61 7 5436 9199",
    "sg:postcode":"4575",
    "sg:province":"QLD",
    "sg:tags":[
        "soil",
        "investigation"
    ],
    "wof:name":"Engineering & Building Investigation Services",
    "wof:placetype":"venue"
},
  "geometry": {"coordinates":[153.12411499999999,-26.727795],"type":"Point"}
}