{
  "type": "Feature",
  "properties": {
    "addr:full":"Napper Rd Arundel QLD 4214",
    "addr:postcode":"4214",
    "addr:street":"Napper Rd",
    "iso:country":"AU",
    "sg:address":"Napper Rd",
    "sg:city":"Arundel",
    "sg:classifiers":[
        {
            "category":"Health Services",
            "subcategory":"Doctor",
            "type":"Services"
        }
    ],
    "sg:phone":"+61 7 5574 5144",
    "sg:postcode":"4214",
    "sg:province":"QLD",
    "sg:tags":[
        "medical",
        "practitioner"
    ],
    "wof:name":"Ward James Dr",
    "wof:placetype":"venue"
},
  "geometry": {"coordinates":[153.3800354,-27.9506473541],"type":"Point"}
}