{
  "type": "Feature",
  "properties": {
    "addr:full":"25 Cowie St Geelong North VIC 3215",
    "addr:housenumber":"25",
    "addr:postcode":"3215",
    "addr:street":"Cowie St",
    "iso:country":"AU",
    "sg:address":"25 Cowie St",
    "sg:city":"Geelong North",
    "sg:classifiers":[
        {
            "category":"Building & Trades",
            "subcategory":"Construction",
            "type":"Services"
        }
    ],
    "sg:phone":"+61 3 5278 5235",
    "sg:postcode":"3215",
    "sg:province":"VIC",
    "sg:tags":[
        "joinery"
    ],
    "wof:name":"Linro Joinery Pty Ltd",
    "wof:placetype":"venue"
},
  "geometry": {"coordinates":[144.34996032699999,-38.1059570312],"type":"Point"}
}