{
  "type": "Feature",
  "properties": {
    "addr:full":"205 Melbourne Road Wodonga VIC 3690",
    "addr:housenumber":"205",
    "addr:postcode":"3690",
    "addr:street":"Melbourne Road",
    "iso:country":"AU",
    "sg:address":"205 Melbourne Road",
    "sg:city":"Wodonga",
    "sg:classifiers":[
        {
            "category":"Shopping",
            "subcategory":"Bicycles & Sporting Goods",
            "type":"Retail Goods"
        }
    ],
    "sg:phone":"+61 2 6056 4495",
    "sg:postcode":"3690",
    "sg:province":"VIC",
    "sg:tags":[
        "chemical",
        "equipment",
        "pool",
        "swimming"
    ],
    "wof:name":"The Drive In Pool Shop",
    "wof:placetype":"venue"
},
  "geometry": {"coordinates":[146.86436462399999,-36.1122779846],"type":"Point"}
}