{
  "type": "Feature",
  "properties": {
    "addr:full":"16 Eucalypt St Whyalla Stuart SA 5608",
    "addr:housenumber":"16",
    "addr:postcode":"5608",
    "addr:street":"Eucalypt St",
    "iso:country":"AU",
    "sg:address":"16 Eucalypt St",
    "sg:city":"Whyalla Stuart",
    "sg:classifiers":[
        {
            "category":"Health Services",
            "subcategory":"Dentist",
            "type":"Services"
        }
    ],
    "sg:phone":"+61 8 8645 0837",
    "sg:postcode":"5608",
    "sg:province":"SA",
    "sg:tags":[
        "equipment",
        "dental",
        "repair"
    ],
    "wof:name":"Davidson Dental Services",
    "wof:placetype":"venue"
},
  "geometry": {"coordinates":[137.52586400000001,-33.035969],"type":"Point"}
}