{
  "type": "Feature",
  "properties": {
    "addr:full":"41 Gill St Rosewater SA 5013",
    "addr:housenumber":"41",
    "addr:postcode":"5013",
    "addr:street":"Gill St",
    "iso:country":"AU",
    "sg:address":"41 Gill St",
    "sg:city":"Rosewater",
    "sg:classifiers":[
        {
            "category":"Retail",
            "subcategory":"Repair Shop",
            "type":"Services"
        }
    ],
    "sg:phone":"+61 432 834 614",
    "sg:postcode":"5013",
    "sg:province":"SA",
    "sg:tags":[
        "mending",
        "clothing",
        "alteration"
    ],
    "wof:name":"Ann Potocnik",
    "wof:placetype":"venue"
},
  "geometry": {"coordinates":[138.527954102,-34.8544006348],"type":"Point"}
}