{
  "type": "Feature",
  "properties": {
    "addr:full":"CBT Clinical Psychology Cntr,+ 28 Harrow Rd Stanmore NSW 2048",
    "addr:housenumber":"28",
    "addr:postcode":"2048",
    "addr:street":"Harrow Rd",
    "iso:country":"AU",
    "sg:address":"CBT Clinical Psychology Cntr,+ 28 Harrow Rd",
    "sg:city":"Stanmore",
    "sg:classifiers":[
        {
            "category":"Health Services",
            "subcategory":"Health Practitioner",
            "type":"Services"
        }
    ],
    "sg:phone":"+61 2 9557 7420",
    "sg:postcode":"2048",
    "sg:province":"NSW",
    "sg:tags":[
        "psychologist"
    ],
    "wof:name":"Hendy Julie & Roberts Corinne",
    "wof:placetype":"venue"
},
  "geometry": {"coordinates":[151.169434,-33.895622],"type":"Point"}
}