{
  "type": "Feature",
  "properties": {
    "addr:full":"Stargate Shopping Centre Shop 2 /129 Lyndon Blvd Atwell WA 6164",
    "addr:housenumber":"shop 2 / 129",
    "addr:postcode":"6164",
    "addr:street":"Lyndon Blvd",
    "iso:country":"AU",
    "sg:address":"Stargate Shopping Centre Shop 2",
    "sg:city":"/129 Lyndon Blvd Atwell",
    "sg:classifiers":[
        {
            "category":"Real Estate",
            "subcategory":"Real Estate Agent",
            "type":"Services"
        }
    ],
    "sg:phone":"+61 8 9498 5022",
    "sg:postcode":"6164",
    "sg:province":"WA",
    "wof:name":"L J Hooker",
    "wof:placetype":"venue"
},
  "geometry": {"coordinates":[115.86720275899999,-32.1363296509],"type":"Point"}
}