{
  "type": "Feature",
  "properties": {
    "iso:country":"AU",
    "sg:address":"Unit 3 802 Boundry Rd",
    "sg:city":"Coopers Plains",
    "sg:classifiers":[
        {
            "category":"Autos & Motor Vehicles",
            "subcategory":"Auto Supplies",
            "type":"Retail Goods"
        }
    ],
    "sg:phone":"+61 412 296 439",
    "sg:postcode":"4108",
    "sg:province":"QLD",
    "sg:tags":[
        "camper-trailers",
        "caravan",
        "equipment"
    ],
    "wof:name":"Gary Wheater",
    "wof:placetype":"venue"
},
  "geometry": {"coordinates":[153.02903747600001,-27.569026947],"type":"Point"}
}