{
  "type": "Feature",
  "properties": {
    "addr:full":"219 Windsor St Richmond NSW 2753",
    "addr:housenumber":"219",
    "addr:postcode":"2753",
    "addr:street":"Windsor St",
    "iso:country":"AU",
    "sg:address":"219 Windsor St",
    "sg:city":"Richmond",
    "sg:classifiers":[
        {
            "category":"Cafe",
            "type":"Food & Drink"
        }
    ],
    "sg:phone":"+61 2 4578 2696",
    "sg:postcode":"2753",
    "sg:province":"NSW",
    "wof:name":"Right Bite The",
    "wof:placetype":"venue"
},
  "geometry": {"coordinates":[150.75111389200001,-33.5967521667],"type":"Point"}
}