{
  "type": "Feature",
  "properties": {
    "iso:country":"AU",
    "sg:address":"5 Weber St",
    "sg:city":"Brighton East",
    "sg:classifiers":[
        {
            "category":"Personal",
            "subcategory":"Massage",
            "type":"Services"
        }
    ],
    "sg:phone":"+61 3 9578 5117",
    "sg:postcode":"3187",
    "sg:province":"VIC",
    "sg:tags":[
        "therapy"
    ],
    "wof:name":"Balint George",
    "wof:placetype":"venue"
},
  "geometry": {"coordinates":[145.02079773,-37.9037399292],"type":"Point"}
}