{
  "type": "Feature",
  "properties": {
    "iso:country":"AU",
    "sg:address":"11 Charlotte St",
    "sg:city":"Smithfield",
    "sg:classifiers":[
        {
            "category":"Retail",
            "subcategory":"Auto Repair",
            "type":"Services"
        }
    ],
    "sg:phone":"+61 8 8254 1033",
    "sg:postcode":"5114",
    "sg:province":"SA",
    "sg:tags":[
        "repairer",
        "motor",
        "engineer"
    ],
    "wof:name":"C & M Engine Services",
    "wof:placetype":"venue"
},
  "geometry": {"coordinates":[138.689544678,-34.6815032959],"type":"Point"}
}