{
  "type": "Feature",
  "properties": {
    "addr:full":"Unit 2/ 100 Redland Bay Rd Capalaba QLD 4157",
    "addr:housenumber":"/ 100",
    "addr:postcode":"4157",
    "addr:street":"Redland Bay Rd",
    "iso:country":"AU",
    "sg:address":"Unit 2/ 100 Redland Bay Rd",
    "sg:city":"Capalaba",
    "sg:classifiers":[
        {
            "category":"Autos & Motor Vehicles",
            "subcategory":"Auto Supplies",
            "type":"Retail Goods"
        }
    ],
    "sg:phone":"+61 7 3823 2244",
    "sg:postcode":"4157",
    "sg:province":"QLD",
    "sg:tags":[
        "part",
        "cycles",
        "accessory"
    ],
    "wof:name":"MX World",
    "wof:placetype":"venue"
},
  "geometry": {"coordinates":[153.19593810999999,-27.5284080505],"type":"Point"}
}