{
  "type": "Feature",
  "properties": {
    "iso:country":"AU",
    "sg:address":"Unit 24 A 33-37 Colledge St",
    "sg:city":"Gladesville",
    "sg:classifiers":[
        {
            "category":"Social Services",
            "subcategory":"Adult Care",
            "type":"Services"
        }
    ],
    "sg:phone":"+61 414 373 171",
    "sg:postcode":"2111",
    "sg:province":"NSW",
    "sg:tags":[
        "towing"
    ],
    "wof:name":"Twin Towing Australia",
    "wof:placetype":"venue"
},
  "geometry": {"coordinates":[151.12176513700001,-33.8203773499],"type":"Point"}
}