{
  "type": "Feature",
  "properties": {
    "addr:full":"Suite 1, 9 Station St Fairfield NSW 2165",
    "addr:housenumber":"9",
    "addr:postcode":"2165",
    "addr:street":"Station St",
    "iso:country":"AU",
    "sg:address":"Suite 1, 9 Station St",
    "sg:city":"Fairfield",
    "sg:classifiers":[
        {
            "category":"Health Services",
            "subcategory":"Dentist",
            "type":"Services"
        }
    ],
    "sg:phone":"+61 2 9728 3111",
    "sg:postcode":"2165",
    "sg:province":"NSW",
    "wof:name":"Fairfield Dental Healthcare Clinic",
    "wof:placetype":"venue"
},
  "geometry": {"coordinates":[150.94479370100001,-33.8659248352],"type":"Point"}
}