{
  "type": "Feature",
  "properties": {
    "addr:full":"34 Western Rd Cohuna VIC 3568",
    "addr:housenumber":"34",
    "addr:postcode":"3568",
    "addr:street":"Western Rd",
    "iso:country":"AU",
    "sg:address":"34 Western Rd",
    "sg:city":"Cohuna",
    "sg:classifiers":[
        {
            "category":"Building & Trades",
            "subcategory":"Electrical",
            "type":"Services"
        }
    ],
    "sg:phone":"+61 3 5456 2575",
    "sg:postcode":"3568",
    "sg:province":"VIC",
    "sg:tags":[
        "repair",
        "generator",
        "electric",
        "motor"
    ],
    "wof:name":"Cohuna Rewinds & Pump Service",
    "wof:placetype":"venue"
},
  "geometry": {"coordinates":[144.209884644,-35.8046646118],"type":"Point"}
}