{
  "type": "Feature",
  "properties": {
    "addr:full":"12 Cambage Rd Northgate QLD 4013",
    "addr:housenumber":"12",
    "addr:postcode":"4013",
    "addr:street":"Cambage Rd",
    "iso:country":"AU",
    "sg:address":"12 Cambage Rd",
    "sg:city":"Northgate",
    "sg:classifiers":[
        {
            "category":"Building & Trades",
            "subcategory":"Plumbing",
            "type":"Services"
        }
    ],
    "sg:phone":"+61 7 3260 6109",
    "sg:postcode":"4013",
    "sg:province":"QLD",
    "sg:tags":[
        "plumber",
        "gasfitters"
    ],
    "wof:name":"Whitehead R W & Y J",
    "wof:placetype":"venue"
},
  "geometry": {"coordinates":[153.07264709500001,-27.3964138031],"type":"Point"}
}