{
  "type": "Feature",
  "properties": {
    "iso:country":"AU",
    "sg:address":"2/ 66 Lee Holm Rd",
    "sg:city":"St Marys",
    "sg:classifiers":[
        {
            "category":"Wholesale",
            "subcategory":"Machinery & Supplies",
            "type":"Manufacturing & Wholesale Goods"
        }
    ],
    "sg:phone":"+61 2 9833 9399",
    "sg:postcode":"2760",
    "sg:province":"NSW",
    "sg:tags":[
        "equipment",
        "hydraulic"
    ],
    "wof:name":"Western Hydraulics",
    "wof:placetype":"venue"
},
  "geometry": {"coordinates":[150.770294189,-33.7536659241],"type":"Point"}
}