{
  "type": "Feature",
  "properties": {
    "iso:country":"AU",
    "sg:address":"Lvl8/ 56 Pitt St",
    "sg:city":"Sydney",
    "sg:classifiers":[
        {
            "category":"Banks & Credit Unions",
            "subcategory":"Financial Services",
            "type":"Services"
        }
    ],
    "sg:phone":"+61 2 9276 1000",
    "sg:postcode":"2000",
    "sg:province":"NSW",
    "sg:tags":[
        "planning"
    ],
    "wof:name":"Alpine Asset Management Pty Ltd",
    "wof:placetype":"venue"
},
  "geometry": {"coordinates":[151.20904540999999,-33.8638038635],"type":"Point"}
}