{
  "type": "Feature",
  "properties": {
    "addr:full":"Shop 1/ 2 Snowy River Ave Jindabyne NSW 2627",
    "addr:housenumber":"shop 1 / 2",
    "addr:postcode":"2627",
    "addr:street":"Snowy River Ave",
    "iso:country":"AU",
    "sg:address":"Shop 1/ 2 Snowy River Ave",
    "sg:city":"Jindabyne",
    "sg:classifiers":[
        {
            "category":"Restaurant",
            "type":"Food & Drink"
        }
    ],
    "sg:phone":"+61 2 6457 1029",
    "sg:postcode":"2627",
    "sg:province":"NSW",
    "wof:name":"Curry&#039;d Away",
    "wof:placetype":"venue"
},
  "geometry": {"coordinates":[148.619873047,-36.4159469604],"type":"Point"}
}