{
  "type": "Feature",
  "properties": {
    "iso:country":"AU",
    "sg:address":"Pandanus Pde",
    "sg:city":"Cabarita Beach",
    "sg:classifiers":[
        {
            "category":"Arena",
            "subcategory":"Sports Club",
            "type":"Entertainment"
        }
    ],
    "sg:phone":"+61 2 6676 1551",
    "sg:postcode":"2488",
    "sg:province":"NSW",
    "sg:tags":[
        "life",
        "surfing",
        "saving"
    ],
    "wof:name":"Cabarita Beach Surf Life Saving Club",
    "wof:placetype":"venue"
},
  "geometry": {"coordinates":[153.570465,-28.331919],"type":"Point"}
}