{
  "type": "Feature",
  "properties": {
    "addr:full":"10 McDonald St Ulverstone TAS 7315",
    "addr:housenumber":"10",
    "addr:postcode":"7315",
    "addr:street":"Mcdonald St",
    "iso:country":"AU",
    "sg:address":"10 McDonald St",
    "sg:city":"Ulverstone",
    "sg:classifiers":[
        {
            "category":"Professional",
            "subcategory":"Art Services",
            "type":"Services"
        }
    ],
    "sg:phone":"+61 417 149 495",
    "sg:postcode":"7315",
    "sg:province":"TAS",
    "sg:tags":[
        "decorator",
        "painter"
    ],
    "wof:name":"Troy Brooks",
    "wof:placetype":"venue"
},
  "geometry": {"coordinates":[146.18940734899999,-41.1580543518],"type":"Point"}
}