{
  "type": "Feature",
  "properties": {
    "iso:country":"AU",
    "sg:address":"37 Warwick Rd",
    "sg:city":"Dundas",
    "sg:classifiers":[
        {
            "category":"Utilities",
            "subcategory":"Electric",
            "type":"Services"
        }
    ],
    "sg:phone":"+61 2 9873 4900",
    "sg:postcode":"2117",
    "sg:province":"NSW",
    "sg:tags":[
        "electrical",
        "contractor"
    ],
    "wof:name":"Bateup Electrical Pty Ltd",
    "wof:placetype":"venue"
},
  "geometry": {"coordinates":[151.05653381400001,-33.7860031128],"type":"Point"}
}