{
  "type": "Feature",
  "properties": {
    "addr:full":"PO Box 4083 Patterson VIC 3204",
    "addr:postcode":"3204",
    "iso:country":"AU",
    "sg:address":"PO Box 4083",
    "sg:city":"Patterson",
    "sg:classifiers":[
        {
            "category":"Banks & Credit Unions",
            "subcategory":"Financial Services",
            "type":"Services"
        }
    ],
    "sg:phone":"+61 1300 308 966",
    "sg:postcode":"3204",
    "sg:province":"VIC",
    "sg:tags":[
        "financier"
    ],
    "wof:name":"Freedom Money Lending (Aust) Pty Ltd",
    "wof:placetype":"venue"
},
  "geometry": {"coordinates":[145.03857400000001,-37.915771],"type":"Point"}
}