{
  "type": "Feature",
  "properties": {
    "addr:full":"1 Bruce St Eudunda SA 5374",
    "addr:housenumber":"1",
    "addr:postcode":"5374",
    "addr:street":"Bruce St",
    "iso:country":"AU",
    "sg:address":"1 Bruce St",
    "sg:city":"Eudunda",
    "sg:classifiers":[
        {
            "category":"Travel",
            "subcategory":"Hotels & Motels",
            "type":"Entertainment"
        }
    ],
    "sg:phone":"+61 8 8581 1188",
    "sg:postcode":"5374",
    "sg:province":"SA",
    "sg:tags":[
        "accommodation"
    ],
    "wof:name":"Light Hotel",
    "wof:placetype":"venue"
},
  "geometry": {"coordinates":[139.08476257300001,-34.1723365784],"type":"Point"}
}