{
  "type": "Feature",
  "properties": {
    "iso:country":"AU",
    "sg:address":"6 Chataway St",
    "sg:city":"West Mackay",
    "sg:classifiers":[
        {
            "category":"Professional",
            "subcategory":"Computer Services",
            "type":"Services"
        }
    ],
    "sg:phone":"+61 418 735 310",
    "sg:postcode":"4740",
    "sg:province":"QLD",
    "sg:tags":[
        "consultant",
        "system"
    ],
    "wof:name":"Houston Electronic Services",
    "wof:placetype":"venue"
},
  "geometry": {"coordinates":[149.15834000000001,-21.152601],"type":"Point"}
}