{
  "type": "Feature",
  "properties": {
    "addr:full":"Shop 5 699 Sherwood Rd Sherwood QLD 4075",
    "addr:housenumber":"shop 5 699",
    "addr:postcode":"4075",
    "addr:street":"Sherwood Rd",
    "iso:country":"AU",
    "sg:address":"Shop 5 699 Sherwood Rd",
    "sg:city":"Sherwood",
    "sg:classifiers":[
        {
            "category":"Government",
            "subcategory":"Post Office",
            "type":"Public Place"
        }
    ],
    "sg:phone":"+61 7 3379 2640",
    "sg:postcode":"4075",
    "sg:province":"QLD",
    "sg:tags":[
        "postal"
    ],
    "wof:name":"Sherwood Post Office",
    "wof:placetype":"venue"
},
  "geometry": {"coordinates":[152.982025147,-27.5321369171],"type":"Point"}
}