{
  "type": "Feature",
  "properties": {
    "addr:full":"369 Centre Rd Bentleigh VIC 3204",
    "addr:housenumber":"369",
    "addr:postcode":"3204",
    "addr:street":"Centre Rd",
    "iso:country":"AU",
    "sg:address":"369 Centre Rd",
    "sg:city":"Bentleigh",
    "sg:classifiers":[
        {
            "category":"Banks & Credit Unions",
            "subcategory":"Financial Services",
            "type":"Services"
        }
    ],
    "sg:phone":"+61 3 9557 8248",
    "sg:postcode":"3204",
    "sg:province":"VIC",
    "sg:tags":[
        "annuity",
        "rollover",
        "superannuation",
        "consultant"
    ],
    "wof:name":"Vin Haughton Insurance Agency Pty Ltd",
    "wof:placetype":"venue"
},
  "geometry": {"coordinates":[145.03706399999999,-37.918098],"type":"Point"}
}