{
  "type": "Feature",
  "properties": {
    "addr:full":"17 Darly Ave Kanahooka NSW 2530",
    "addr:housenumber":"17",
    "addr:postcode":"2530",
    "addr:street":"Darly Ave",
    "iso:country":"AU",
    "sg:address":"17 Darly Ave",
    "sg:city":"Kanahooka",
    "sg:classifiers":[
        {
            "category":"Structure",
            "subcategory":"Office Building",
            "type":"Public Place"
        }
    ],
    "sg:phone":"+61 418 298 743",
    "sg:postcode":"2530",
    "sg:province":"NSW",
    "sg:tags":[
        "slater",
        "tiler",
        "roof"
    ],
    "wof:name":"D & J Professional Roofing Pty Ltd",
    "wof:placetype":"venue"
},
  "geometry": {"coordinates":[150.809051514,-34.489490509],"type":"Point"}
}