{
  "type": "Feature",
  "properties": {
    "iso:country":"AU",
    "sg:address":"2 Australia Ave, Sydney Olympic Park",
    "sg:city":"Homebush Bay",
    "sg:classifiers":[
        {
            "category":"Train Station",
            "subcategory":"Light Rail",
            "type":"Transportation"
        }
    ],
    "sg:phone":"+61 1800 802 762",
    "sg:postcode":"2127",
    "sg:province":"NSW",
    "sg:tags":[
        "equipment",
        "energy",
        "solar"
    ],
    "sg:website":"http://www.bpsolar.com.au",
    "wof:name":"BP Solar Pty Ltd",
    "wof:placetype":"venue"
},
  "geometry": {"coordinates":[151.07211303700001,-33.8466835022],"type":"Point"}
}