{
  "type": "Feature",
  "properties": {
    "addr:full":"586 Kangaroo Ground-St Andrews Rd Panton Hill VIC 3759",
    "addr:housenumber":"586",
    "addr:postcode":"3759",
    "addr:street":"Kangaroo Ground-St Andrews Rd",
    "iso:country":"AU",
    "sg:address":"586 Kangaroo Ground-St Andrews Rd",
    "sg:city":"Panton Hill",
    "sg:classifiers":[
        {
            "category":"Food & Beverages",
            "subcategory":"Groceries & Convenience Stores",
            "type":"Retail Goods"
        }
    ],
    "sg:phone":"+61 3 9719 7771",
    "sg:postcode":"3759",
    "sg:province":"VIC",
    "wof:name":"Panton Hill General Store",
    "wof:placetype":"venue"
},
  "geometry": {"coordinates":[145.23561100000001,-37.644028],"type":"Point"}
}