{
  "type": "Feature",
  "properties": {
    "addr:full":"32 Freemantle Rd Noarlunga SA 5168",
    "addr:housenumber":"32",
    "addr:postcode":"5168",
    "addr:street":"Freemantle Rd",
    "iso:country":"AU",
    "sg:address":"32 Freemantle Rd",
    "sg:city":"Noarlunga",
    "sg:classifiers":[
        {
            "category":"Building & Trades",
            "subcategory":"Construction",
            "type":"Services"
        }
    ],
    "sg:phone":"+61 419 646 286",
    "sg:postcode":"5168",
    "sg:province":"SA",
    "sg:tags":[
        "earth",
        "excavating",
        "moving",
        "contractor"
    ],
    "wof:name":"Southern Cross Earthmovers",
    "wof:placetype":"venue"
},
  "geometry": {"coordinates":[138.47494506800001,-35.1694869995],"type":"Point"}
}