{
  "type": "Feature",
  "properties": {
    "addr:full":"PO Box 482 Kingaroy QLD 4610",
    "addr:postcode":"4610",
    "iso:country":"AU",
    "sg:address":"PO Box 482",
    "sg:city":"Kingaroy",
    "sg:classifiers":[
        {
            "category":"Real Estate",
            "subcategory":"Real Estate Services",
            "type":"Services"
        }
    ],
    "sg:phone":"+61 7 4162 7822",
    "sg:postcode":"4610",
    "sg:province":"QLD",
    "sg:tags":[
        "valuer"
    ],
    "wof:name":"John Logan & Associates",
    "wof:placetype":"venue"
},
  "geometry": {"coordinates":[151.835845947,-26.5428390503],"type":"Point"}
}