{
  "type": "Feature",
  "properties": {
    "addr:full":"37 Bryant St Padstow NSW 2211",
    "addr:housenumber":"37",
    "addr:postcode":"2211",
    "addr:street":"Bryant St",
    "iso:country":"AU",
    "sg:address":"37 Bryant St",
    "sg:city":"Padstow",
    "sg:classifiers":[
        {
            "category":"Building & Trades",
            "subcategory":"Construction",
            "type":"Services"
        }
    ],
    "sg:phone":"+61 2 9772 4977",
    "sg:postcode":"2211",
    "sg:province":"NSW",
    "sg:tags":[
        "contractor"
    ],
    "wof:name":"Metropolitan Civil Contractors Pty Ltd",
    "wof:placetype":"venue"
},
  "geometry": {"coordinates":[151.03268399999999,-33.941143],"type":"Point"}
}