{
  "type": "Feature",
  "properties": {
    "iso:country":"AU",
    "sg:address":"9 Harley St",
    "sg:city":"Labrador",
    "sg:classifiers":[
        {
            "category":"Retail",
            "subcategory":"Repair Shop",
            "type":"Services"
        }
    ],
    "sg:phone":"+61 7 5537 5877",
    "sg:postcode":"4215",
    "sg:province":"QLD",
    "sg:tags":[
        "windscreen"
    ],
    "wof:name":"All Modern Parts",
    "wof:placetype":"venue"
},
  "geometry": {"coordinates":[153.398834228,-27.9364891052],"type":"Point"}
}