{
  "type": "Feature",
  "properties": {
    "addr:full":"47 Station St Porepunkah VIC 3740",
    "addr:housenumber":"47",
    "addr:postcode":"3740",
    "addr:street":"Station St",
    "iso:country":"AU",
    "sg:address":"47 Station St",
    "sg:city":"Porepunkah",
    "sg:classifiers":[
        {
            "category":"Utilities",
            "subcategory":"Fuel Oil & Lpg",
            "type":"Services"
        }
    ],
    "sg:phone":"+61 3 5756 2686",
    "sg:postcode":"3740",
    "sg:province":"VIC",
    "sg:tags":[
        "merchant"
    ],
    "wof:name":"Alpine Firewood Supplies",
    "wof:placetype":"venue"
},
  "geometry": {"coordinates":[146.915314,-36.696953],"type":"Point"}
}