{
  "type": "Feature",
  "properties": {
    "addr:full":"9 Carnavon St Hawthorn VIC 3122",
    "addr:housenumber":"9",
    "addr:postcode":"3122",
    "addr:street":"Carnavon St",
    "iso:country":"AU",
    "sg:address":"9 Carnavon St",
    "sg:city":"Hawthorn",
    "sg:classifiers":[
        {
            "category":"Shopping",
            "subcategory":"Antiques",
            "type":"Retail Goods"
        }
    ],
    "sg:phone":"+61 418 368 109",
    "sg:postcode":"3122",
    "sg:province":"VIC",
    "wof:name":"Beeches & Rale",
    "wof:placetype":"venue"
},
  "geometry": {"coordinates":[145.04765319800001,-37.8293151855],"type":"Point"}
}