{
  "type": "Feature",
  "properties": {
    "addr:full":"101 Blues Point Rd McMahons Point NSW 2060",
    "addr:housenumber":"101",
    "addr:postcode":"2060",
    "addr:street":"Blues Point Rd",
    "iso:country":"AU",
    "sg:address":"101 Blues Point Rd",
    "sg:city":"McMahons Point",
    "sg:classifiers":[
        {
            "category":"Health Services",
            "subcategory":"Health Practitioner",
            "type":"Services"
        }
    ],
    "sg:phone":"+61 2 9957 4101",
    "sg:postcode":"2060",
    "sg:province":"NSW",
    "sg:tags":[
        "naturopath"
    ],
    "wof:name":"Center 101",
    "wof:placetype":"venue"
},
  "geometry": {"coordinates":[151.20429992699999,-33.8452796936],"type":"Point"}
}