{
  "type": "Feature",
  "properties": {
    "addr:full":"Lot 6 Cable Sands Rd Busselton WA 6280",
    "addr:housenumber":"6",
    "addr:postcode":"6280",
    "addr:street":"Cable Sands Rd",
    "iso:country":"AU",
    "sg:address":"Lot 6 Cable Sands Rd",
    "sg:city":"Busselton",
    "sg:classifiers":[
        {
            "category":"Building & Trades",
            "subcategory":"Equipment Rental",
            "type":"Services"
        }
    ],
    "sg:phone":"+61 8 9752 1000",
    "sg:postcode":"6280",
    "sg:province":"WA",
    "sg:tags":[
        "crane",
        "hire"
    ],
    "wof:name":"Busselton Crane & Plant Hire",
    "wof:placetype":"venue"
},
  "geometry": {"coordinates":[115.399291992,-33.6558036804],"type":"Point"}
}