{
  "type": "Feature",
  "properties": {
    "iso:country":"AU",
    "sg:address":"Suite 803, 229- 231 Macquarie St",
    "sg:city":"Sydney",
    "sg:classifiers":[
        {
            "category":"Health Services",
            "subcategory":"Dentist",
            "type":"Services"
        }
    ],
    "sg:phone":"+61 2 9232 6172",
    "sg:postcode":"2000",
    "sg:province":"NSW",
    "wof:name":"Pistolese Anthony",
    "wof:placetype":"venue"
},
  "geometry": {"coordinates":[151.21191406200001,-33.8690872192],"type":"Point"}
}