{
  "type": "Feature",
  "properties": {
    "addr:full":"Unit 2/ 4 Queen St Wodonga VIC 3690",
    "addr:housenumber":"4",
    "addr:postcode":"3690",
    "addr:street":"Queen St",
    "iso:country":"AU",
    "sg:address":"Unit 2/ 4 Queen St",
    "sg:city":"Wodonga",
    "sg:classifiers":[
        {
            "category":"Building & Trades",
            "subcategory":"Cleaning & Sanitation",
            "type":"Services"
        }
    ],
    "sg:phone":"+61 408 572 931",
    "sg:postcode":"3690",
    "sg:province":"VIC",
    "sg:tags":[
        "cleaner",
        "repairer",
        "roof"
    ],
    "wof:name":"Ryan T R & S E",
    "wof:placetype":"venue"
},
  "geometry": {"coordinates":[146.89732360799999,-36.118270874],"type":"Point"}
}