{
  "type": "Feature",
  "properties": {
    "iso:country":"AU",
    "sg:address":"19 Casey St",
    "sg:city":"Aitkenvale",
    "sg:classifiers":[
        {
            "category":"Building & Trades",
            "subcategory":"Construction",
            "type":"Services"
        }
    ],
    "sg:phone":"+61 7 4779 1600",
    "sg:postcode":"4814",
    "sg:province":"QLD",
    "sg:tags":[
        "welding"
    ],
    "wof:name":"K G Engineering Pty Ltd",
    "wof:placetype":"venue"
},
  "geometry": {"coordinates":[146.769104,-19.294491],"type":"Point"}
}