{
  "type": "Feature",
  "properties": {
    "iso:country":"AU",
    "sg:address":"Promenade Level 108 Cockle Bay Whf",
    "sg:city":"Darling Harbour",
    "sg:classifiers":[
        {
            "category":"Restaurant",
            "type":"Food & Drink"
        }
    ],
    "sg:phone":"+61 2 9283 3393",
    "sg:postcode":"2000",
    "sg:province":"NSW",
    "wof:name":"CMC Citi Marina Cafe",
    "wof:placetype":"venue"
},
  "geometry": {"coordinates":[151.19822692899999,-33.8725891113],"type":"Point"}
}