{
  "type": "Feature",
  "properties": {
    "iso:country":"AU",
    "sg:address":"1525 Eumundi-Noosa Rd",
    "sg:city":"Eumundi",
    "sg:classifiers":[
        {
            "category":"Education",
            "subcategory":"School",
            "type":"Public Place"
        }
    ],
    "sg:phone":"+61 7 5472 6333",
    "sg:postcode":"4562",
    "sg:province":"QLD",
    "sg:tags":[
        "state",
        "except",
        "nsw"
    ],
    "wof:name":"Eumundi Primary School",
    "wof:placetype":"venue"
},
  "geometry": {"coordinates":[152.95181274399999,-26.4729671478],"type":"Point"}
}