{
  "type": "Feature",
  "properties": {
    "addr:full":"Colston St Ryde NSW 2112",
    "addr:postcode":"2112",
    "addr:street":"Colston St",
    "iso:country":"AU",
    "sg:address":"Colston St",
    "sg:city":"Ryde",
    "sg:classifiers":[
        {
            "category":"Professional",
            "subcategory":"Computer Services",
            "type":"Services"
        }
    ],
    "sg:phone":"+61 2 9809 2318",
    "sg:postcode":"2112",
    "sg:province":"NSW",
    "sg:tags":[
        "consultant",
        "system"
    ],
    "wof:name":"Osmosys Consulting",
    "wof:placetype":"venue"
},
  "geometry": {"coordinates":[151.102752686,-33.8094711304],"type":"Point"}
}