{
  "type": "Feature",
  "properties": {
    "addr:full":"1263 Howitt St Wendouree VIC 3355",
    "addr:housenumber":"1263",
    "addr:postcode":"3355",
    "addr:street":"Howitt St",
    "iso:country":"AU",
    "sg:address":"1263 Howitt St",
    "sg:city":"Wendouree",
    "sg:classifiers":[
        {
            "category":"Retail",
            "subcategory":"Car Wash",
            "type":"Services"
        }
    ],
    "sg:phone":"+61 3 5339 4400",
    "sg:postcode":"3355",
    "sg:province":"VIC",
    "sg:tags":[
        "truck",
        "cleaning"
    ],
    "wof:name":"JJ's Waterwise Carwash",
    "wof:placetype":"venue"
},
  "geometry": {"coordinates":[143.824814,-37.539585],"type":"Point"}
}