{
  "type": "Feature",
  "properties": {
    "iso:country":"AU",
    "sg:address":"Naracoorte Rd",
    "sg:city":"Bordertown",
    "sg:classifiers":[
        {
            "category":"Building & Trades",
            "subcategory":"Construction",
            "type":"Services"
        }
    ],
    "sg:phone":"+61 8 8752 1863",
    "sg:postcode":"5268",
    "sg:province":"SA",
    "sg:tags":[
        "earth",
        "excavating",
        "moving",
        "contractor"
    ],
    "wof:name":"Murch P J & L E",
    "wof:placetype":"venue"
},
  "geometry": {"coordinates":[140.771423,-36.31395],"type":"Point"}
}