{
  "type": "Feature",
  "properties": {
    "iso:country":"AU",
    "sg:address":"Shop 1, Balnarring Shopng Cntr",
    "sg:city":"Balnarring",
    "sg:classifiers":[
        {
            "category":"Fast Food",
            "type":"Food & Drink"
        }
    ],
    "sg:phone":"+61 3 5983 1457",
    "sg:postcode":"3926",
    "sg:province":"VIC",
    "sg:tags":[
        "away",
        "take"
    ],
    "wof:name":"Hoolies Inn",
    "wof:placetype":"venue"
},
  "geometry": {"coordinates":[145.12693786599999,-38.3735809326],"type":"Point"}
}