{
  "type": "Feature",
  "properties": {
    "addr:full":"Unit 2/ 9 Postle St Coopers Plains QLD 4108",
    "addr:postcode":"4108",
    "addr:street":"Postle St",
    "iso:country":"AU",
    "sg:address":"Unit 2/ 9 Postle St",
    "sg:city":"Coopers Plains",
    "sg:classifiers":[
        {
            "category":"Manufacturing",
            "subcategory":"Tools & Machinery",
            "type":"Manufacturing & Wholesale Goods"
        }
    ],
    "sg:phone":"+61 7 3216 6866",
    "sg:postcode":"4108",
    "sg:province":"QLD",
    "sg:tags":[
        "fastener",
        "industrial"
    ],
    "wof:name":"EDL Fasteners Pty Ltd",
    "wof:placetype":"venue"
},
  "geometry": {"coordinates":[153.025466919,-27.5690765381],"type":"Point"}
}