{
  "type": "Feature",
  "properties": {
    "iso:country":"AU",
    "sg:address":"4 Wickham Crs",
    "sg:city":"Red Hill",
    "sg:classifiers":[
        {
            "category":"Building & Trades",
            "subcategory":"Construction",
            "type":"Services"
        }
    ],
    "sg:phone":"+61 2 6295 1013",
    "sg:postcode":"2603",
    "sg:province":"ACT",
    "sg:tags":[
        "contractor"
    ],
    "wof:name":"Waldren C J",
    "wof:placetype":"venue"
},
  "geometry": {"coordinates":[149.12684631400001,-35.3397903442],"type":"Point"}
}