{
  "type": "Feature",
  "properties": {
    "addr:full":"404 Balwyn Rd Balwyn North VIC 3104",
    "addr:housenumber":"404",
    "addr:postcode":"3104",
    "addr:street":"Balwyn Rd",
    "iso:country":"AU",
    "sg:address":"404 Balwyn Rd",
    "sg:city":"Balwyn North",
    "sg:classifiers":[
        {
            "category":"Professional",
            "subcategory":"Accounting & Tax Preparation",
            "type":"Services"
        }
    ],
    "sg:phone":"+61 3 9816 3733",
    "sg:postcode":"3104",
    "sg:province":"VIC",
    "sg:tags":[
        "accountant",
        "auditor"
    ],
    "wof:name":"S P B F Solutions Pty Ltd",
    "wof:placetype":"venue"
},
  "geometry": {"coordinates":[145.08651733400001,-37.7870063782],"type":"Point"}
}