{
  "type": "Feature",
  "properties": {
    "iso:country":"AU",
    "sg:address":"35 Maude St",
    "sg:city":"Dunolly",
    "sg:classifiers":[
        {
            "category":"Professional",
            "subcategory":"Art Services",
            "type":"Services"
        }
    ],
    "sg:phone":"+61 3 5468 1079",
    "sg:postcode":"3472",
    "sg:province":"VIC",
    "sg:tags":[
        "graphic",
        "designer"
    ],
    "wof:name":"Effigy Press",
    "wof:placetype":"venue"
},
  "geometry": {"coordinates":[143.73452758799999,-36.8665161133],"type":"Point"}
}