{
  "type": "Feature",
  "properties": {
    "iso:country":"AU",
    "sg:address":"30 Stymie St",
    "sg:city":"Kingsbury",
    "sg:classifiers":[
        {
            "category":"Home & Garden",
            "subcategory":"Carpets & Floor Coverings",
            "type":"Retail Goods"
        }
    ],
    "sg:phone":"+61 411 530 828",
    "sg:postcode":"3083",
    "sg:province":"VIC",
    "sg:tags":[
        "wholesaler",
        "tie",
        "mfrs",
        "scarf"
    ],
    "wof:name":"J. L. Neck Wear",
    "wof:placetype":"venue"
},
  "geometry": {"coordinates":[145.029785156,-37.7156333923],"type":"Point"}
}