{
  "type": "Feature",
  "properties": {
    "addr:full":"26 Camelot Crt Carlingford NSW 2118",
    "addr:housenumber":"26",
    "addr:postcode":"2118",
    "addr:street":"Camelot Crt",
    "iso:country":"AU",
    "sg:address":"26 Camelot Crt",
    "sg:city":"Carlingford",
    "sg:classifiers":[
        {
            "category":"Health Services",
            "subcategory":"Doctor",
            "type":"Services"
        }
    ],
    "sg:phone":"+61 2 9630 1454",
    "sg:postcode":"2118",
    "sg:province":"NSW",
    "sg:tags":[
        "medical",
        "practitioner"
    ],
    "wof:name":"Donohoo C M",
    "wof:placetype":"venue"
},
  "geometry": {"coordinates":[151.02395629899999,-33.7828521729],"type":"Point"}
}