{
  "type": "Feature",
  "properties": {
    "addr:full":"57 Miners Hut Rd Haddon VIC 3351",
    "addr:housenumber":"57",
    "addr:postcode":"3351",
    "addr:street":"Miners Hut Rd",
    "iso:country":"AU",
    "sg:address":"57 Miners Hut Rd",
    "sg:city":"Haddon",
    "sg:classifiers":[
        {
            "category":"Retail",
            "subcategory":"Repair Shop",
            "type":"Services"
        }
    ],
    "sg:phone":"+61 3 5342 4581",
    "sg:postcode":"3351",
    "sg:province":"VIC",
    "sg:tags":[
        "repairing",
        "piano",
        "tuning"
    ],
    "wof:name":"Cockerill P W & E H",
    "wof:placetype":"venue"
},
  "geometry": {"coordinates":[143.662384,-37.608036],"type":"Point"}
}