{
  "type": "Feature",
  "properties": {
    "addr:full":"Shop 27 Worongary Shopping Village 1 Mudgeeraba Rd Mudgeeraba QLD 4213",
    "addr:housenumber":"shop 27",
    "addr:postcode":"4213",
    "addr:street":"Worongary;Mudgeeraba Rd",
    "iso:country":"AU",
    "sg:address":"Shop 27 Worongary Shopping Village 1 Mudgeeraba Rd",
    "sg:city":"Mudgeeraba",
    "sg:classifiers":[
        {
            "category":"Personal",
            "subcategory":"Massage",
            "type":"Services"
        }
    ],
    "sg:phone":"+61 7 5530 3166",
    "sg:postcode":"4213",
    "sg:province":"QLD",
    "sg:tags":[
        "therapy"
    ],
    "wof:name":"Zen Health Centre",
    "wof:placetype":"venue"
},
  "geometry": {"coordinates":[153.35496520999999,-28.0528259277],"type":"Point"}
}