{
  "type": "Feature",
  "properties": {
    "iso:country":"AU",
    "sg:address":"191 Parramatta Rd",
    "sg:city":"Annandale",
    "sg:classifiers":[
        {
            "category":"Communications",
            "subcategory":"Film & Video Production",
            "type":"Services"
        }
    ],
    "sg:phone":"+61 2 9560 2506",
    "sg:postcode":"2038",
    "sg:province":"NSW",
    "sg:tags":[
        "linen",
        "good"
    ],
    "wof:name":"House of Lombard",
    "wof:placetype":"venue"
},
  "geometry": {"coordinates":[151.16453552199999,-33.8880500793],"type":"Point"}
}