{
  "type": "Feature",
  "properties": {
    "addr:full":"Suite 2 Calvary Clinic Haydon Drive Belconnen ACT 2617",
    "addr:postcode":"2617",
    "addr:street":"Haydon Drive",
    "iso:country":"AU",
    "sg:address":"Suite 2 Calvary Clinic Haydon Drive",
    "sg:city":"Belconnen",
    "sg:classifiers":[
        {
            "category":"Health Services",
            "subcategory":"Health Practitioner",
            "type":"Services"
        }
    ],
    "sg:phone":"+61 2 6253 0177",
    "sg:postcode":"2617",
    "sg:province":"ACT",
    "sg:tags":[
        "dietitian"
    ],
    "wof:name":"Judith Williams APD",
    "wof:placetype":"venue"
},
  "geometry": {"coordinates":[149.09005737300001,-35.2409095764],"type":"Point"}
}