{
  "type": "Feature",
  "properties": {
    "addr:full":"3/ 42 Moonee St Coffs Harbour NSW 2450",
    "addr:housenumber":"/ 42",
    "addr:postcode":"2450",
    "addr:street":"Moonee St",
    "iso:country":"AU",
    "sg:address":"3/ 42 Moonee St",
    "sg:city":"Coffs Harbour",
    "sg:classifiers":[
        {
            "category":"Banks & Credit Unions",
            "subcategory":"Financial Services",
            "type":"Services"
        }
    ],
    "sg:phone":"+61 2 6651 5554",
    "sg:postcode":"2450",
    "sg:province":"NSW",
    "sg:tags":[
        "loan",
        "finance",
        "mortgage"
    ],
    "wof:name":"AREA Home Loans",
    "wof:placetype":"venue"
},
  "geometry": {"coordinates":[153.11274700000001,-30.296265],"type":"Point"}
}