{
  "type": "Feature",
  "properties": {
    "addr:full":"4 Gibbon Crt St Albans VIC 3021",
    "addr:housenumber":"4",
    "addr:postcode":"3021",
    "addr:street":"Gibbon Crt",
    "iso:country":"AU",
    "sg:address":"4 Gibbon Crt St",
    "sg:city":"Albans",
    "sg:classifiers":[
        {
            "category":"Real Estate",
            "subcategory":"Real Estate Operator",
            "type":"Services"
        }
    ],
    "sg:phone":"+61 3 9323 0958",
    "sg:postcode":"3021",
    "sg:province":"VIC",
    "sg:tags":[
        "concrete",
        "pumping"
    ],
    "wof:name":"L&J Concrete Pumping Services",
    "wof:placetype":"venue"
},
  "geometry": {"coordinates":[144.78407300000001,-37.729622],"type":"Point"}
}