{
  "type": "Feature",
  "properties": {
    "addr:full":"34 Adelaide Rd Gawler SA 5118",
    "addr:housenumber":"34",
    "addr:postcode":"5118",
    "addr:street":"Adelaide Rd",
    "iso:country":"AU",
    "sg:address":"34 Adelaide Rd",
    "sg:city":"Gawler",
    "sg:classifiers":[
        {
            "category":"Manufacturing",
            "subcategory":"Motor Vehicles & Parts",
            "type":"Manufacturing & Wholesale Goods"
        }
    ],
    "sg:phone":"+61 8 8523 4144",
    "sg:postcode":"5118",
    "sg:province":"SA",
    "sg:tags":[
        "replacement"
    ],
    "wof:name":"Sprint Auto Parts & Accessories",
    "wof:placetype":"venue"
},
  "geometry": {"coordinates":[138.74508700000001,-34.606236],"type":"Point"}
}