{
  "type": "Feature",
  "properties": {
    "addr:full":"3 Betula Pl Loftus NSW 2232",
    "addr:housenumber":"3",
    "addr:postcode":"2232",
    "addr:street":"Betula Pl",
    "iso:country":"AU",
    "sg:address":"3 Betula Pl",
    "sg:city":"Loftus",
    "sg:classifiers":[
        {
            "category":"Professional",
            "subcategory":"Art Services",
            "type":"Services"
        }
    ],
    "sg:phone":"+61 2 9545 6216",
    "sg:postcode":"2232",
    "sg:province":"NSW",
    "sg:tags":[
        "decorator",
        "painter"
    ],
    "wof:name":"Darrin Currey Painting Service",
    "wof:placetype":"venue"
},
  "geometry": {"coordinates":[151.04139709500001,-34.0499038696],"type":"Point"}
}