{
  "type": "Feature",
  "properties": {
    "addr:full":"The Vault, 257 Collins St Melbourne VIC 3000",
    "addr:housenumber":"257",
    "addr:postcode":"3000",
    "addr:street":"Collins St",
    "iso:country":"AU",
    "sg:address":"The Vault, 257 Collins St",
    "sg:city":"Melbourne",
    "sg:classifiers":[
        {
            "category":"Social Services",
            "subcategory":"Retirement Home",
            "type":"Services"
        }
    ],
    "sg:phone":"+61 3 9543 1788",
    "sg:postcode":"3000",
    "sg:province":"VIC",
    "sg:tags":[
        "environmental",
        "consultant",
        "pollution"
    ],
    "wof:name":"Remedi 8 P/L",
    "wof:placetype":"venue"
},
  "geometry": {"coordinates":[144.96536254899999,-37.8159637451],"type":"Point"}
}