{
  "type": "Feature",
  "properties": {
    "addr:full":"Lot 2 Tews Crt Toowoomba QLD 4350",
    "addr:postcode":"4350",
    "iso:country":"AU",
    "sg:address":"Lot 2 Tews Crt",
    "sg:city":"Toowoomba",
    "sg:classifiers":[
        {
            "category":"Commercial Area",
            "type":"Public Place"
        }
    ],
    "sg:phone":"+61 7 4634 8868",
    "sg:postcode":"4350",
    "sg:province":"QLD",
    "sg:tags":[
        "heavy",
        "carrier"
    ],
    "wof:name":"Statewide General Transport",
    "wof:placetype":"venue"
},
  "geometry": {"coordinates":[151.910751,-27.548697],"type":"Point"}
}