{
  "type": "Feature",
  "properties": {
    "iso:country":"AU",
    "sg:address":"146 William St",
    "sg:city":"Bathurst",
    "sg:classifiers":[
        {
            "category":"Social Services",
            "subcategory":"Adult Care",
            "type":"Services"
        }
    ],
    "sg:phone":"+61 439 529 944",
    "sg:postcode":"2795",
    "sg:province":"NSW",
    "sg:tags":[
        "towing"
    ],
    "wof:name":"A1 Towing Bathurst",
    "wof:placetype":"venue"
},
  "geometry": {"coordinates":[149.55354309099999,-33.5437316895],"type":"Point"}
}