{
  "type": "Feature",
  "properties": {
    "addr:full":"50 Caramut Rd Warrnambool VIC 3280",
    "addr:housenumber":"50",
    "addr:postcode":"3280",
    "addr:street":"Caramut Rd",
    "iso:country":"AU",
    "sg:address":"50 Caramut Rd",
    "sg:city":"Warrnambool",
    "sg:classifiers":[
        {
            "category":"Wholesale",
            "subcategory":"Farm Supplies",
            "type":"Manufacturing & Wholesale Goods"
        }
    ],
    "sg:phone":"+61 3 5561 3252",
    "sg:postcode":"3280",
    "sg:province":"VIC",
    "sg:tags":[
        "equipment"
    ],
    "wof:name":"Total Dairy Service",
    "wof:placetype":"venue"
},
  "geometry": {"coordinates":[142.46081543,-38.3584098816],"type":"Point"}
}