{
  "type": "Feature",
  "properties": {
    "iso:country":"AU",
    "sg:address":"2/ 14 Parkinson La",
    "sg:city":"Kardinya",
    "sg:classifiers":[
        {
            "category":"Shopping",
            "subcategory":"Bicycles & Sporting Goods",
            "type":"Retail Goods"
        }
    ],
    "sg:phone":"+61 1300 361 955",
    "sg:postcode":"6163",
    "sg:province":"WA",
    "sg:tags":[
        "chemical",
        "equipment",
        "pool",
        "swimming"
    ],
    "wof:name":"Solapool Covers",
    "wof:placetype":"venue"
},
  "geometry": {"coordinates":[115.804062,-32.060669],"type":"Point"}
}