{
  "type": "Feature",
  "properties": {
    "iso:country":"AU",
    "sg:address":"Shop 4/ 16 Miyal Pl",
    "sg:city":"Engadine",
    "sg:classifiers":[
        {
            "category":"Personal",
            "subcategory":"Beauty Salon",
            "type":"Services"
        }
    ],
    "sg:phone":"+61 2 9548 3200",
    "sg:postcode":"2233",
    "sg:province":"NSW",
    "sg:tags":[
        "hairdresser"
    ],
    "wof:name":"Serenity Hair Nail & Beauty",
    "wof:placetype":"venue"
},
  "geometry": {"coordinates":[151.01167297399999,-34.0646209717],"type":"Point"}
}