{
  "type": "Feature",
  "properties": {
    "addr:full":"999 Nepean Hwy Moorabbin VIC 3189",
    "addr:housenumber":"999",
    "addr:postcode":"3189",
    "addr:street":"Nepean Hwy",
    "iso:country":"AU",
    "sg:address":"999 Nepean Hwy",
    "sg:city":"Moorabbin",
    "sg:classifiers":[
        {
            "category":"Professional",
            "subcategory":"Management & Consulting",
            "type":"Services"
        }
    ],
    "sg:phone":"+61 3 9532 2066",
    "sg:postcode":"3189",
    "sg:province":"VIC",
    "sg:tags":[
        "consultant",
        "business"
    ],
    "wof:name":"Beyond 19",
    "wof:placetype":"venue"
},
  "geometry": {"coordinates":[145.03631591800001,-37.9345703125],"type":"Point"}
}