{
  "type": "Feature",
  "properties": {
    "iso:country":"AU",
    "sg:address":"8 Comley St",
    "sg:city":"Sunshine North",
    "sg:classifiers":[
        {
            "category":"Retail",
            "subcategory":"Auto Repair",
            "type":"Services"
        }
    ],
    "sg:phone":"+61 3 9312 7333",
    "sg:postcode":"3020",
    "sg:province":"VIC",
    "sg:tags":[
        "repairer",
        "motor",
        "engineer"
    ],
    "wof:name":"Mechanical Clinic",
    "wof:placetype":"venue"
},
  "geometry": {"coordinates":[144.82968099999999,-37.767273],"type":"Point"}
}