{
  "type": "Feature",
  "properties": {
    "addr:full":"416 Shakespeare St Mackay QLD 4740",
    "addr:housenumber":"416",
    "addr:postcode":"4740",
    "addr:street":"Shakespeare St",
    "iso:country":"AU",
    "sg:address":"416 Shakespeare St",
    "sg:city":"Mackay",
    "sg:classifiers":[
        {
            "category":"Education",
            "subcategory":"Kindergarten",
            "type":"Public Place"
        }
    ],
    "sg:phone":"+61 7 4957 4589",
    "sg:postcode":"4740",
    "sg:province":"QLD",
    "sg:tags":[
        "pre-schools"
    ],
    "wof:name":"Mackay Kindergarten & Pre-School Assoc Inc",
    "wof:placetype":"venue"
},
  "geometry": {"coordinates":[149.169464,-21.145214],"type":"Point"}
}