{
  "type": "Feature",
  "properties": {
    "iso:country":"AU",
    "sg:address":"3/ 40 Park St",
    "sg:city":"Narrabeen",
    "sg:classifiers":[
        {
            "category":"Professional",
            "subcategory":"Printing & Photocopies",
            "type":"Services"
        }
    ],
    "sg:phone":"+61 412 230 108",
    "sg:postcode":"2101",
    "sg:province":"NSW",
    "sg:tags":[
        "screen",
        "printer"
    ],
    "wof:name":"HOS Screenprinting",
    "wof:placetype":"venue"
},
  "geometry": {"coordinates":[151.29594399999999,-33.723858],"type":"Point"}
}