{
  "type": "Feature",
  "properties": {
    "iso:country":"AU",
    "sg:address":"Drouin Rd",
    "sg:city":"Longwarry",
    "sg:classifiers":[
        {
            "category":"Wholesale",
            "subcategory":"Toys & Hobbies",
            "type":"Manufacturing & Wholesale Goods"
        }
    ],
    "sg:phone":"+61 3 5629 9378",
    "sg:postcode":"3816",
    "sg:province":"VIC",
    "sg:tags":[
        "mfrs"
    ],
    "wof:name":"Proposch Toys",
    "wof:placetype":"venue"
},
  "geometry": {"coordinates":[145.771774,-38.11087],"type":"Point"}
}