{
  "type": "Feature",
  "properties": {
    "addr:full":"83 Princess St Morpeth NSW 2321",
    "addr:housenumber":"83",
    "addr:postcode":"2321",
    "addr:street":"Princess St",
    "iso:country":"AU",
    "sg:address":"83 Princess St",
    "sg:city":"Morpeth",
    "sg:classifiers":[
        {
            "category":"Government",
            "subcategory":"Court House",
            "type":"Public Place"
        }
    ],
    "sg:phone":"+61 2 4933 5766",
    "sg:postcode":"2321",
    "sg:province":"NSW",
    "sg:tags":[
        "personal",
        "marriage",
        "family",
        "counselling"
    ],
    "wof:name":"Joan Wiseman",
    "wof:placetype":"venue"
},
  "geometry": {"coordinates":[151.62893676799999,-32.7269668579],"type":"Point"}
}