{
  "type": "Feature",
  "properties": {
    "addr:full":"155 Wickham St Fortitude Valley QLD 4006",
    "addr:housenumber":"155",
    "addr:postcode":"4006",
    "addr:street":"Wickham St",
    "iso:country":"AU",
    "sg:address":"155 Wickham St",
    "sg:city":"Fortitude Valley",
    "sg:classifiers":[
        {
            "category":"Food & Beverages",
            "subcategory":"Supermarket",
            "type":"Retail Goods"
        }
    ],
    "sg:phone":"+61 7 3852 1283",
    "sg:postcode":"4006",
    "sg:province":"QLD",
    "sg:tags":[
        "grocery",
        "store"
    ],
    "wof:name":"Yuen's Market Trading Co",
    "wof:placetype":"venue"
},
  "geometry": {"coordinates":[153.032669067,-27.458650589],"type":"Point"}
}