{
  "type": "Feature",
  "properties": {
    "iso:country":"AU",
    "sg:address":"32 Boolagi Drv",
    "sg:city":"Wurtulla",
    "sg:classifiers":[
        {
            "category":"Building & Trades",
            "subcategory":"Construction",
            "type":"Services"
        }
    ],
    "sg:phone":"+61 7 5437 6705",
    "sg:postcode":"4575",
    "sg:province":"QLD",
    "sg:tags":[
        "concrete",
        "contractor"
    ],
    "wof:name":"Beerwah Concreting",
    "wof:placetype":"venue"
},
  "geometry": {"coordinates":[153.11994899999999,-26.762295],"type":"Point"}
}