{
  "type": "Feature",
  "properties": {
    "addr:full":"Ocean Drv Port Macquarie NSW 2444",
    "addr:postcode":"2444",
    "addr:street":"Ocean Drv",
    "iso:country":"AU",
    "sg:address":"Ocean Drv",
    "sg:city":"Port Macquarie",
    "sg:classifiers":[
        {
            "category":"Retail",
            "subcategory":"Event Space",
            "type":"Services"
        }
    ],
    "sg:phone":"+61 2 6583 6996",
    "sg:postcode":"2444",
    "sg:province":"NSW",
    "sg:tags":[
        "venue",
        "reception",
        "wedding"
    ],
    "wof:name":"Marian Hospitality Centre",
    "wof:placetype":"venue"
},
  "geometry": {"coordinates":[152.90147400000001,-31.448679],"type":"Point"}
}