{
  "type": "Feature",
  "properties": {
    "iso:country":"AU",
    "sg:address":"75 Yandilla St",
    "sg:city":"Pittsworth",
    "sg:classifiers":[
        {
            "category":"Banks & Credit Unions",
            "subcategory":"Bank",
            "type":"Services"
        }
    ],
    "sg:phone":"+61 7 4693 1300",
    "sg:postcode":"4356",
    "sg:province":"QLD",
    "wof:name":"National Australia Bank Ltd",
    "wof:placetype":"venue"
},
  "geometry": {"coordinates":[151.634491,-27.715731],"type":"Point"}
}