{
  "type": "Feature",
  "properties": {
    "iso:country":"AU",
    "sg:address":"18 Lakeside Drv",
    "sg:city":"Sapphire Beach",
    "sg:classifiers":[
        {
            "category":"Professional",
            "subcategory":"Accounting & Tax Preparation",
            "type":"Services"
        }
    ],
    "sg:phone":"+61 2 6653 6062",
    "sg:postcode":"2450",
    "sg:province":"NSW",
    "sg:tags":[
        "accountant",
        "auditor"
    ],
    "wof:name":"Neal D L & A G",
    "wof:placetype":"venue"
},
  "geometry": {"coordinates":[153.152771,-30.231174],"type":"Point"}
}