{
  "type": "Feature",
  "properties": {
    "iso:country":"AU",
    "sg:address":"90 Cheltenham Rd",
    "sg:city":"Dandenong",
    "sg:classifiers":[
        {
            "category":"Home & Garden",
            "subcategory":"Hardware",
            "type":"Retail Goods"
        }
    ],
    "sg:phone":"+61 3 9794 0844",
    "sg:postcode":"3175",
    "sg:province":"VIC",
    "sg:tags":[
        "plumber",
        "supply"
    ],
    "wof:name":"Living Wise Rainwater Tanks",
    "wof:placetype":"venue"
},
  "geometry": {"coordinates":[145.19917297399999,-37.9910507202],"type":"Point"}
}