{
  "type": "Feature",
  "properties": {
    "addr:full":"9 Ferguson St Underwood QLD 4119",
    "addr:housenumber":"9",
    "addr:postcode":"4119",
    "addr:street":"Ferguson St",
    "iso:country":"AU",
    "sg:address":"9 Ferguson St",
    "sg:city":"Underwood",
    "sg:classifiers":[
        {
            "category":"Home & Garden",
            "subcategory":"Carpets & Floor Coverings",
            "type":"Retail Goods"
        }
    ],
    "sg:phone":"+61 7 3341 6799",
    "sg:postcode":"4119",
    "sg:province":"QLD",
    "sg:tags":[
        "tile",
        "wall"
    ],
    "wof:name":"Underwood Tile Centre",
    "wof:placetype":"venue"
},
  "geometry": {"coordinates":[153.113723755,-27.6116294861],"type":"Point"}
}