{
  "type": "Feature",
  "properties": {
    "addr:full":"Suite 201 60 Archer St Chatswood NSW 2067",
    "addr:housenumber":"60",
    "addr:postcode":"2067",
    "addr:street":"Archer St",
    "iso:country":"AU",
    "sg:address":"Suite 201 60 Archer St",
    "sg:city":"Chatswood",
    "sg:classifiers":[
        {
            "category":"Professional",
            "subcategory":"Computer Services",
            "type":"Services"
        }
    ],
    "sg:phone":"+61 2 9553 7760",
    "sg:postcode":"2067",
    "sg:province":"NSW",
    "sg:tags":[
        "consultant",
        "system"
    ],
    "wof:name":"St George Consultancy Services",
    "wof:placetype":"venue"
},
  "geometry": {"coordinates":[151.185836792,-33.7969894409],"type":"Point"}
}