{
  "type": "Feature",
  "properties": {
    "addr:full":"PO Box 120 Tamborine QLD 4270",
    "addr:postcode":"4270",
    "iso:country":"AU",
    "sg:address":"PO Box 120",
    "sg:city":"Tamborine",
    "sg:classifiers":[
        {
            "category":"Building & Trades",
            "subcategory":"Plumbing",
            "type":"Services"
        }
    ],
    "sg:phone":"+61 7 5543 6070",
    "sg:postcode":"4270",
    "sg:province":"QLD",
    "sg:tags":[
        "plumber",
        "gasfitters"
    ],
    "wof:name":"Hutchinson RP & LJ Plumbing",
    "wof:placetype":"venue"
},
  "geometry": {"coordinates":[153.13044738799999,-27.8806591034],"type":"Point"}
}