{
  "type": "Feature",
  "properties": {
    "addr:full":"39 Tingira St Portsmith QLD 4870",
    "addr:housenumber":"39",
    "addr:postcode":"4870",
    "addr:street":"Tingira St Portsmith",
    "iso:country":"AU",
    "sg:address":"39 Tingira St",
    "sg:city":"Portsmith",
    "sg:classifiers":[
        {
            "category":"Wholesale",
            "subcategory":"Seafood",
            "type":"Manufacturing & Wholesale Goods"
        }
    ],
    "sg:phone":"+61 7 4035 1951",
    "sg:postcode":"4870",
    "sg:province":"QLD",
    "sg:tags":[
        "fish"
    ],
    "wof:name":"GNM Seafoods",
    "wof:placetype":"venue"
},
  "geometry": {"coordinates":[145.771606445,-16.9462471008],"type":"Point"}
}