{
  "type": "Feature",
  "properties": {
    "addr:full":"10 Warrawong St Chapel Hill QLD 4069",
    "addr:housenumber":"10",
    "addr:postcode":"4069",
    "addr:street":"Warrawong St",
    "iso:country":"AU",
    "sg:address":"10 Warrawong St",
    "sg:city":"Chapel Hill",
    "sg:classifiers":[
        {
            "category":"Banks & Credit Unions",
            "subcategory":"Investment Brokerage",
            "type":"Services"
        }
    ],
    "sg:phone":"+61 7 3720 1085",
    "sg:postcode":"4069",
    "sg:province":"QLD",
    "sg:tags":[
        "finance",
        "broker"
    ],
    "wof:name":"Equity Express Pty Ltd",
    "wof:placetype":"venue"
},
  "geometry": {"coordinates":[152.960083008,-27.49933815],"type":"Point"}
}