{
  "type": "Feature",
  "properties": {
    "iso:country":"AU",
    "sg:address":"24 Telford Drv",
    "sg:city":"Shepparton",
    "sg:classifiers":[
        {
            "category":"Farming",
            "subcategory":"Farm & Veterinary Services",
            "type":"Manufacturing & Wholesale Goods"
        }
    ],
    "sg:phone":"+61 3 5831 2176",
    "sg:postcode":"3630",
    "sg:province":"VIC",
    "sg:tags":[
        "agricultural",
        "advisory"
    ],
    "wof:name":"Animal Mineral Solutions",
    "wof:placetype":"venue"
},
  "geometry": {"coordinates":[145.42869567899999,-36.3764953613],"type":"Point"}
}