{
  "type": "Feature",
  "properties": {
    "addr:full":"PO Box 820 South Melbourne VIC 3205",
    "addr:postcode":"3205",
    "iso:country":"AU",
    "sg:address":"PO Box 820",
    "sg:city":"South Melbourne",
    "sg:classifiers":[
        {
            "category":"Manufacturing",
            "subcategory":"Food",
            "type":"Manufacturing & Wholesale Goods"
        }
    ],
    "sg:phone":"+61 3 5422 2411",
    "sg:postcode":"3205",
    "sg:province":"VIC",
    "sg:tags":[
        "wholesaler",
        "mfrs",
        "yarn"
    ],
    "wof:name":"Fitzgerald V.A & Sons Pty Ltd",
    "wof:placetype":"venue"
},
  "geometry": {"coordinates":[144.95585600000001,-37.833881],"type":"Point"}
}