{
  "type": "Feature",
  "properties": {
    "iso:country":"AU",
    "sg:address":"49 Simpsons Rd",
    "sg:city":"Eaglehawk",
    "sg:classifiers":[
        {
            "category":"Farming",
            "subcategory":"Farm & Veterinary Services",
            "type":"Manufacturing & Wholesale Goods"
        }
    ],
    "sg:phone":"+61 400 669 058",
    "sg:postcode":"3556",
    "sg:province":"VIC",
    "sg:tags":[
        "shearing",
        "contractor"
    ],
    "wof:name":"Bendigo Shearing Services",
    "wof:placetype":"venue"
},
  "geometry": {"coordinates":[144.255859375,-36.7121887207],"type":"Point"}
}