{
  "type": "Feature",
  "properties": {
    "addr:full":"139 Buckley St Essendon VIC 3040",
    "addr:housenumber":"139",
    "addr:postcode":"3040",
    "addr:street":"Buckley St",
    "iso:country":"AU",
    "sg:address":"139 Buckley St",
    "sg:city":"Essendon",
    "sg:classifiers":[
        {
            "category":"Education",
            "subcategory":"School",
            "type":"Public Place"
        }
    ],
    "sg:phone":"+61 3 9337 5311",
    "sg:postcode":"3040",
    "sg:province":"VIC",
    "sg:tags":[
        "girl"
    ],
    "wof:name":"St Columba's College",
    "wof:placetype":"venue"
},
  "geometry": {"coordinates":[144.914230347,-37.7568244934],"type":"Point"}
}