{
  "type": "Feature",
  "properties": {
    "addr:full":"176 Maquarie St Hobart TAS 7000",
    "addr:housenumber":"176",
    "addr:postcode":"7000",
    "addr:street":"Maquarie St",
    "iso:country":"AU",
    "sg:address":"176 Maquarie St",
    "sg:city":"Hobart",
    "sg:classifiers":[
        {
            "category":"Health Services",
            "subcategory":"Health Practitioner",
            "type":"Services"
        }
    ],
    "sg:phone":"+61 3 6224 4900",
    "sg:postcode":"7000",
    "sg:province":"TAS",
    "sg:tags":[
        "physiotherapist"
    ],
    "wof:name":"Marshall Rebecca",
    "wof:placetype":"venue"
},
  "geometry": {"coordinates":[147.325973511,-42.8861999512],"type":"Point"}
}