{
  "type": "Feature",
  "properties": {
    "iso:country":"AU",
    "sg:address":"62 Treeview Drv",
    "sg:city":"Burleigh Waters",
    "sg:classifiers":[
        {
            "category":"Shopping",
            "subcategory":"Hobbies, Toys, & Games",
            "type":"Retail Goods"
        }
    ],
    "sg:phone":"+61 500 555 656",
    "sg:postcode":"4220",
    "sg:province":"QLD",
    "sg:tags":[
        "bag",
        "sack"
    ],
    "wof:name":"Tunbrood Pty Ltd",
    "wof:placetype":"venue"
},
  "geometry": {"coordinates":[153.426147461,-28.0924892426],"type":"Point"}
}