{
  "type": "Feature",
  "properties": {
    "addr:full":"28 Felstead Crs Hamersley WA 6022",
    "addr:housenumber":"28",
    "addr:postcode":"6022",
    "addr:street":"Felstead Crs",
    "iso:country":"AU",
    "sg:address":"28 Felstead Crs",
    "sg:city":"Hamersley",
    "sg:classifiers":[
        {
            "category":"Real Estate",
            "subcategory":"Surveying",
            "type":"Services"
        }
    ],
    "sg:phone":"+61 8 9448 2987",
    "sg:postcode":"6022",
    "sg:province":"WA",
    "sg:tags":[
        "surveyor",
        "land"
    ],
    "wof:name":"Bartlett K D",
    "wof:placetype":"venue"
},
  "geometry": {"coordinates":[115.811462402,-31.8507709503],"type":"Point"}
}