{
  "type": "Feature",
  "properties": {
    "iso:country":"AU",
    "sg:address":"23 Bayview Rd",
    "sg:city":"Mornington",
    "sg:classifiers":[
        {
            "category":"Real Estate",
            "subcategory":"Real Estate Operator",
            "type":"Services"
        }
    ],
    "sg:phone":"+61 409 748 596",
    "sg:postcode":"3931",
    "sg:province":"VIC",
    "sg:tags":[
        "building",
        "consultant",
        "management"
    ],
    "wof:name":"Vogel B",
    "wof:placetype":"venue"
},
  "geometry": {"coordinates":[145.041549683,-38.2345619202],"type":"Point"}
}