{
  "type": "Feature",
  "properties": {
    "addr:full":"U9/ 34 East St Five Dock NSW 2046",
    "addr:housenumber":"34",
    "addr:postcode":"2046",
    "addr:street":"U9 /;East St",
    "iso:country":"AU",
    "sg:address":"U9/ 34 East St",
    "sg:city":"Five Dock",
    "sg:classifiers":[
        {
            "category":"Personal",
            "subcategory":"Massage",
            "type":"Services"
        }
    ],
    "sg:phone":"+61 2 9713 9378",
    "sg:postcode":"2046",
    "sg:province":"NSW",
    "sg:tags":[
        "therapy"
    ],
    "wof:name":"Asian Darling",
    "wof:placetype":"venue"
},
  "geometry": {"coordinates":[151.129425,-33.866081],"type":"Point"}
}