{
  "type": "Feature",
  "properties": {
    "iso:country":"AU",
    "sg:address":"PO Box 1065",
    "sg:city":"Reservoir",
    "sg:classifiers":[
        {
            "category":"Professional",
            "subcategory":"Computer Services",
            "type":"Services"
        }
    ],
    "sg:phone":"+61 3 9402 0875",
    "sg:postcode":"3073",
    "sg:province":"VIC",
    "sg:tags":[
        "consultant",
        "system"
    ],
    "wof:name":"Wesnet Computer Services",
    "wof:placetype":"venue"
},
  "geometry": {"coordinates":[145.005569458,-37.7123413086],"type":"Point"}
}