{
  "type": "Feature",
  "properties": {
    "iso:country":"AU",
    "sg:address":"242 Invermay Rd",
    "sg:city":"Mowbray",
    "sg:classifiers":[
        {
            "category":"Health Services",
            "subcategory":"Health Practitioner",
            "type":"Services"
        }
    ],
    "sg:phone":"+61 3 6326 6070",
    "sg:postcode":"7248",
    "sg:province":"TAS",
    "sg:tags":[
        "reiki"
    ],
    "wof:name":"Joan Marshall",
    "wof:placetype":"venue"
},
  "geometry": {"coordinates":[147.133544922,-41.4074668884],"type":"Point"}
}