{
  "type": "Feature",
  "properties": {
    "addr:full":"PO Box 294 Ulladulla NSW 2539",
    "addr:postcode":"2539",
    "iso:country":"AU",
    "sg:address":"PO Box 294",
    "sg:city":"Ulladulla",
    "sg:classifiers":[
        {
            "category":"Retail",
            "subcategory":"Repair Shop",
            "type":"Services"
        }
    ],
    "sg:phone":"+61 2 4455 5812",
    "sg:postcode":"2539",
    "sg:province":"NSW",
    "sg:tags":[
        "machine",
        "repairs",
        "part",
        "dryer",
        "washing"
    ],
    "wof:name":"Ulladulla Washing Machine Service Repairs",
    "wof:placetype":"venue"
},
  "geometry": {"coordinates":[150.475631714,-35.3509788513],"type":"Point"}
}