{
  "type": "Feature",
  "properties": {
    "addr:full":"1/ 6 Alma Rd New Lambton NSW 2305",
    "addr:housenumber":"/ 6",
    "addr:postcode":"2305",
    "addr:street":"Alma Rd",
    "iso:country":"AU",
    "sg:address":"1/ 6 Alma Rd",
    "sg:city":"New Lambton",
    "sg:classifiers":[
        {
            "category":"Health Services",
            "subcategory":"Doctor",
            "type":"Services"
        }
    ],
    "sg:phone":"+61 2 4957 4455",
    "sg:postcode":"2305",
    "sg:province":"NSW",
    "sg:tags":[
        "podiatrist"
    ],
    "wof:name":"A Quality Podiatry Service",
    "wof:placetype":"venue"
},
  "geometry": {"coordinates":[151.71456900000001,-32.922062],"type":"Point"}
}