{
  "type": "Feature",
  "properties": {
    "addr:full":"35 Habib Drv South Lismore NSW 2480",
    "addr:housenumber":"35",
    "addr:postcode":"2480",
    "addr:street":"Habib Drv South",
    "iso:country":"AU",
    "sg:address":"35 Habib Drv",
    "sg:city":"South Lismore",
    "sg:classifiers":[
        {
            "category":"Wholesale",
            "subcategory":"Metals & Minerals",
            "type":"Manufacturing & Wholesale Goods"
        }
    ],
    "sg:phone":"+61 2 6621 8185",
    "sg:postcode":"2480",
    "sg:province":"NSW",
    "sg:tags":[
        "steel",
        "stainless",
        "product",
        "equipment"
    ],
    "wof:name":"Attard Sheet Metal Pty Ltd",
    "wof:placetype":"venue"
},
  "geometry": {"coordinates":[153.26278686500001,-28.824798584],"type":"Point"}
}