{
  "type": "Feature",
  "properties": {
    "iso:country":"AU",
    "sg:address":"7 Alexandria Pde",
    "sg:city":"Waitara",
    "sg:classifiers":[
        {
            "category":"Real Estate",
            "subcategory":"Real Estate Agent",
            "type":"Services"
        }
    ],
    "sg:phone":"+61 2 9477 5898",
    "sg:postcode":"2077",
    "sg:province":"NSW",
    "wof:name":"Hilton Real Estate",
    "wof:placetype":"venue"
},
  "geometry": {"coordinates":[151.104370117,-33.7095108032],"type":"Point"}
}