{
  "type": "Feature",
  "properties": {
    "addr:full":"145 King St Sydney NSW 2000",
    "addr:housenumber":"145",
    "addr:postcode":"2000",
    "addr:street":"King St",
    "iso:country":"AU",
    "sg:address":"145 King St",
    "sg:city":"Sydney",
    "sg:classifiers":[
        {
            "category":"Shopping",
            "subcategory":"Clothing, Apparel, & Fashions",
            "type":"Retail Goods"
        }
    ],
    "sg:phone":"+61 2 9221 4994",
    "sg:postcode":"2000",
    "sg:province":"NSW",
    "sg:tags":[
        "menswear"
    ],
    "wof:name":"Gant",
    "wof:placetype":"venue"
},
  "geometry": {"coordinates":[151.20924377399999,-33.8691139221],"type":"Point"}
}