{
  "type": "Feature",
  "properties": {
    "addr:full":"Prince St Railway Station Mullumbimby NSW 2482",
    "addr:postcode":"2482",
    "addr:street":"Prince St",
    "iso:country":"AU",
    "sg:address":"Prince St Railway Station",
    "sg:city":"Mullumbimby",
    "sg:classifiers":[
        {
            "category":"Education",
            "subcategory":"University",
            "type":"Public Place"
        }
    ],
    "sg:phone":"+61 2 6684 3374",
    "sg:postcode":"2482",
    "sg:province":"NSW",
    "sg:tags":[
        "educational",
        "organisation",
        "cultural"
    ],
    "wof:name":"Adult & Community Education Centres",
    "wof:placetype":"venue"
},
  "geometry": {"coordinates":[153.50338745100001,-28.5536785126],"type":"Point"}
}