{
  "type": "Feature",
  "properties": {
    "iso:country":"AU",
    "sg:address":"183 Fitzmaurice St",
    "sg:city":"Wagga Wagga",
    "sg:classifiers":[
        {
            "category":"Retail",
            "subcategory":"Laundry & Dry Cleaning",
            "type":"Services"
        }
    ],
    "sg:phone":"+61 2 6921 2747",
    "sg:postcode":"2650",
    "sg:province":"NSW",
    "wof:name":"Earsmans American Dry Cleaning & Laundry Co.",
    "wof:placetype":"venue"
},
  "geometry": {"coordinates":[147.36807250999999,-35.1019897461],"type":"Point"}
}