{
  "type": "Feature",
  "properties": {
    "iso:country":"AU",
    "sg:address":"Suite 6 255 Whitehorse Rd",
    "sg:city":"Balwyn",
    "sg:classifiers":[
        {
            "category":"Professional",
            "subcategory":"Management & Consulting",
            "type":"Services"
        }
    ],
    "sg:phone":"+61 3 9862 3222",
    "sg:postcode":"3103",
    "sg:province":"VIC",
    "sg:tags":[
        "consultant",
        "economic"
    ],
    "wof:name":"Martec Automotive Consulting Pty Ltd",
    "wof:placetype":"venue"
},
  "geometry": {"coordinates":[145.07701110799999,-37.812171936],"type":"Point"}
}