{
  "type": "Feature",
  "properties": {
    "iso:country":"AU",
    "sg:address":"Shop 3, Shumack St",
    "sg:city":"Weetangera",
    "sg:classifiers":[
        {
            "category":"Personal",
            "subcategory":"Beauty Salon",
            "type":"Services"
        }
    ],
    "sg:phone":"+61 2 6254 4636",
    "sg:postcode":"2614",
    "sg:province":"ACT",
    "sg:tags":[
        "hairdresser"
    ],
    "wof:name":"The Strand Hair Studio",
    "wof:placetype":"venue"
},
  "geometry": {"coordinates":[149.05091857900001,-35.2440948486],"type":"Point"}
}