{
  "type": "Feature",
  "properties": {
    "addr:full":"5 Silo Rd Pinnaroo SA 5304",
    "addr:housenumber":"5",
    "addr:postcode":"5304",
    "addr:street":"Silo Rd",
    "iso:country":"AU",
    "sg:address":"5 Silo Rd",
    "sg:city":"Pinnaroo",
    "sg:classifiers":[
        {
            "category":"Home & Garden",
            "subcategory":"Garden Supply",
            "type":"Retail Goods"
        }
    ],
    "sg:phone":"+61 8 8577 8101",
    "sg:postcode":"5304",
    "sg:province":"SA",
    "sg:tags":[
        "fertilizer"
    ],
    "wof:name":"Pinnaroo Fertilizer Depot",
    "wof:placetype":"venue"
},
  "geometry": {"coordinates":[140.90196227999999,-35.2605361938],"type":"Point"}
}