{
  "type": "Feature",
  "properties": {
    "addr:full":"208 Allan St Kyabram VIC 3620",
    "addr:housenumber":"208",
    "addr:postcode":"3620",
    "addr:street":"Allan St",
    "iso:country":"AU",
    "sg:address":"208 Allan St",
    "sg:city":"Kyabram",
    "sg:classifiers":[
        {
            "category":"Shopping",
            "subcategory":"Shoes",
            "type":"Retail Goods"
        }
    ],
    "sg:phone":"+61 3 5853 1333",
    "sg:postcode":"3620",
    "sg:province":"VIC",
    "sg:tags":[
        "footwear"
    ],
    "wof:name":"All About Shoes",
    "wof:placetype":"venue"
},
  "geometry": {"coordinates":[145.04718017600001,-36.3135795593],"type":"Point"}
}