{
  "type": "Feature",
  "properties": {
    "iso:country":"AU",
    "sg:address":"Shop L13, Altona Gate Shopping Centre, 124 Millers Rd",
    "sg:city":"Altona North",
    "sg:classifiers":[
        {
            "category":"Deli",
            "type":"Food & Drink"
        }
    ],
    "sg:phone":"+61 3 9315 1446",
    "sg:postcode":"3025",
    "sg:province":"VIC",
    "sg:tags":[
        "delicatessen"
    ],
    "wof:name":"Kings Carvery",
    "wof:placetype":"venue"
},
  "geometry": {"coordinates":[144.848495,-37.828789],"type":"Point"}
}