{
  "type": "Feature",
  "properties": {
    "iso:country":"AU",
    "sg:address":"6 McEwan Ave",
    "sg:city":"Oaks Estate",
    "sg:classifiers":[
        {
            "category":"Utilities",
            "type":"Services"
        }
    ],
    "sg:phone":"+61 2 6299 7559",
    "sg:postcode":"2620",
    "sg:province":"ACT",
    "sg:tags":[
        "refrigeration",
        "industrial",
        "commercial",
        "retail"
    ],
    "wof:name":"Capital Stainless Steel",
    "wof:placetype":"venue"
},
  "geometry": {"coordinates":[149.22132873499999,-35.3411827087],"type":"Point"}
}