{
  "type": "Feature",
  "properties": {
    "addr:full":"6 Swanston St Preston VIC 3072",
    "addr:housenumber":"6",
    "addr:postcode":"3072",
    "addr:street":"Swanston St",
    "iso:country":"AU",
    "sg:address":"6 Swanston St",
    "sg:city":"Preston",
    "sg:classifiers":[
        {
            "category":"Manufacturing",
            "subcategory":"Tools & Machinery",
            "type":"Manufacturing & Wholesale Goods"
        }
    ],
    "sg:phone":"+61 3 9480 5899",
    "sg:postcode":"3072",
    "sg:province":"VIC",
    "sg:tags":[
        "earth",
        "excavating",
        "moving",
        "equipment"
    ],
    "wof:name":"Ciplack Vehicle Repair Pty Ltd",
    "wof:placetype":"venue"
},
  "geometry": {"coordinates":[145.03321838400001,-37.7479095459],"type":"Point"}
}