{
  "type": "Feature",
  "properties": {
    "addr:full":"198 Denison St Bondi Junction NSW 2022",
    "addr:housenumber":"198",
    "addr:postcode":"2022",
    "addr:street":"Denison St",
    "iso:country":"AU",
    "sg:address":"198 Denison St",
    "sg:city":"Bondi Junction",
    "sg:classifiers":[
        {
            "category":"Autos & Motor Vehicles",
            "subcategory":"Fuel & Gas Station",
            "type":"Retail Goods"
        }
    ],
    "sg:phone":"+61 2 9387 1979",
    "sg:postcode":"2022",
    "sg:province":"NSW",
    "wof:name":"Caltex Ampol Service Station",
    "wof:placetype":"venue"
},
  "geometry": {"coordinates":[151.243743897,-33.8970375061],"type":"Point"}
}