{
  "type": "Feature",
  "properties": {
    "addr:full":"U3/ 71 Western Ave Tullamarine VIC 3043",
    "addr:housenumber":"71",
    "addr:postcode":"3043",
    "addr:street":"U3 /;Western Ave",
    "iso:country":"AU",
    "sg:address":"U3/ 71 Western Ave",
    "sg:city":"Tullamarine",
    "sg:classifiers":[
        {
            "category":"Professional",
            "subcategory":"Employment Agencies",
            "type":"Services"
        }
    ],
    "sg:phone":"+61 3 9338 7555",
    "sg:postcode":"3043",
    "sg:province":"VIC",
    "sg:tags":[
        "broker",
        "custom"
    ],
    "wof:name":"APC Logistics Pty Ltd",
    "wof:placetype":"venue"
},
  "geometry": {"coordinates":[144.87727355999999,-37.6838035583],"type":"Point"}
}