{
  "type": "Feature",
  "properties": {
    "addr:full":"69 Rowe St Brighton TAS 7030",
    "addr:housenumber":"69",
    "addr:postcode":"7030",
    "addr:street":"Rowe St",
    "iso:country":"AU",
    "sg:address":"69 Rowe St",
    "sg:city":"Brighton",
    "sg:classifiers":[
        {
            "category":"Building & Trades",
            "subcategory":"Construction",
            "type":"Services"
        }
    ],
    "sg:phone":"+61 417 978 257",
    "sg:postcode":"7030",
    "sg:province":"TAS",
    "sg:tags":[
        "earth",
        "excavating",
        "moving",
        "contractor"
    ],
    "wof:name":"Doubles Machinery Operating Services",
    "wof:placetype":"venue"
},
  "geometry": {"coordinates":[147.23312377900001,-42.6867866516],"type":"Point"}
}