{
  "type": "Feature",
  "properties": {
    "addr:full":"146 O'Riordan St Mascot NSW 2020",
    "addr:housenumber":"146",
    "addr:postcode":"2020",
    "addr:street":"O'Riordan St",
    "iso:country":"AU",
    "sg:address":"146 O'Riordan St",
    "sg:city":"Mascot",
    "sg:classifiers":[
        {
            "category":"Utilities",
            "subcategory":"Telephone",
            "type":"Services"
        }
    ],
    "sg:phone":"+61 1300 303 475",
    "sg:postcode":"2020",
    "sg:province":"NSW",
    "sg:tags":[
        "equipment",
        "system"
    ],
    "wof:name":"IPL Group",
    "wof:placetype":"venue"
},
  "geometry": {"coordinates":[151.18719482399999,-33.9288215637],"type":"Point"}
}