{
  "type": "Feature",
  "properties": {
    "addr:full":"226 Glenmore Rd Paddington NSW 2021",
    "addr:housenumber":"226",
    "addr:postcode":"2021",
    "addr:street":"Glenmore Rd",
    "iso:country":"AU",
    "sg:address":"226 Glenmore Rd",
    "sg:city":"Paddington",
    "sg:classifiers":[
        {
            "category":"Manufacturing",
            "subcategory":"Food",
            "type":"Manufacturing & Wholesale Goods"
        }
    ],
    "sg:phone":"+61 2 9361 6131",
    "sg:postcode":"2021",
    "sg:province":"NSW",
    "sg:tags":[
        "function",
        "catering"
    ],
    "wof:name":"and the dish ran away with the spoon",
    "wof:placetype":"venue"
},
  "geometry": {"coordinates":[151.228057861,-33.8821182251],"type":"Point"}
}