{
  "type": "Feature",
  "properties": {
    "addr:full":"4 Cross St Double Bay NSW 2028",
    "addr:housenumber":"4",
    "addr:postcode":"2028",
    "addr:street":"Cross St",
    "iso:country":"AU",
    "sg:address":"4 Cross St",
    "sg:city":"Double Bay",
    "sg:classifiers":[
        {
            "category":"Shopping",
            "subcategory":"Clothing, Apparel, & Fashions",
            "type":"Retail Goods"
        }
    ],
    "sg:phone":"+61 2 9327 3513",
    "sg:postcode":"2028",
    "sg:province":"NSW",
    "sg:tags":[
        "lady",
        "wear"
    ],
    "wof:name":"Eleni Boutique",
    "wof:placetype":"venue"
},
  "geometry": {"coordinates":[151.244262695,-33.8766746521],"type":"Point"}
}