{
  "type": "Feature",
  "properties": {
    "iso:country":"AU",
    "sg:address":"46 Whiting St",
    "sg:city":"Artarmon",
    "sg:classifiers":[
        {
            "category":"Retail",
            "subcategory":"Auto Repair",
            "type":"Services"
        }
    ],
    "sg:phone":"+61 2 9966 0077",
    "sg:postcode":"2064",
    "sg:province":"NSW",
    "sg:tags":[
        "beater",
        "painter",
        "panel"
    ],
    "wof:name":"Anva Auto Body",
    "wof:placetype":"venue"
},
  "geometry": {"coordinates":[151.182373047,-33.815788269],"type":"Point"}
}