{
  "type": "Feature",
  "properties": {
    "addr:full":"16 Marin Pl Glendenning NSW 2761",
    "addr:housenumber":"16",
    "addr:postcode":"2761",
    "addr:street":"Marin Pl",
    "iso:country":"AU",
    "sg:address":"16 Marin Pl",
    "sg:city":"Glendenning",
    "sg:classifiers":[
        {
            "category":"Utilities",
            "subcategory":"Electric",
            "type":"Services"
        }
    ],
    "sg:phone":"+61 2 9677 0562",
    "sg:postcode":"2761",
    "sg:province":"NSW",
    "sg:tags":[
        "electrical",
        "contractor"
    ],
    "wof:name":"Same Call Electrical Service",
    "wof:placetype":"venue"
},
  "geometry": {"coordinates":[150.852295,-33.745327],"type":"Point"}
}