{
  "type": "Feature",
  "properties": {
    "addr:full":"PO Box 57 Calingiri WA 6569",
    "addr:postcode":"6569",
    "iso:country":"AU",
    "sg:address":"PO Box 57",
    "sg:city":"Calingiri",
    "sg:classifiers":[
        {
            "category":"Health Services",
            "subcategory":"Health Practitioner",
            "type":"Services"
        }
    ],
    "sg:phone":"+61 8 9628 7042",
    "sg:postcode":"6569",
    "sg:province":"WA",
    "sg:tags":[
        "herbalist"
    ],
    "wof:name":"Herb Growers Network Of WA",
    "wof:placetype":"venue"
},
  "geometry": {"coordinates":[116.45004299999999,-31.08831],"type":"Point"}
}