{
  "type": "Feature",
  "properties": {
    "addr:full":"40 Regency Drv Regents Park QLD 4118",
    "addr:housenumber":"40",
    "addr:postcode":"4118",
    "addr:street":"Regency Drv",
    "iso:country":"AU",
    "sg:address":"40 Regency Drv",
    "sg:city":"Regents Park",
    "sg:classifiers":[
        {
            "category":"Professional",
            "subcategory":"Art Services",
            "type":"Services"
        }
    ],
    "sg:phone":"+61 412 014 474",
    "sg:postcode":"4118",
    "sg:province":"QLD",
    "sg:tags":[
        "decorator",
        "painter"
    ],
    "wof:name":"Bill Shabanay Painter",
    "wof:placetype":"venue"
},
  "geometry": {"coordinates":[153.047531128,-27.6718902588],"type":"Point"}
}