{
  "type": "Feature",
  "properties": {
    "addr:full":"Lvl2/ 381 Port Hacking Rd Caringbah NSW 2229",
    "addr:housenumber":"381",
    "addr:postcode":"2229",
    "addr:street":"Port Hacking Rd",
    "iso:country":"AU",
    "sg:address":"Lvl2/ 381 Port Hacking Rd",
    "sg:city":"Caringbah",
    "sg:classifiers":[
        {
            "category":"Insurance",
            "subcategory":"Insurance Agent",
            "type":"Services"
        }
    ],
    "sg:phone":"+61 2 9541 3317",
    "sg:postcode":"2229",
    "sg:province":"NSW",
    "wof:name":"Pearl Insurance Group",
    "wof:placetype":"venue"
},
  "geometry": {"coordinates":[151.12309265100001,-34.0450744629],"type":"Point"}
}