{
  "type": "Feature",
  "properties": {
    "addr:full":"Shop 7 2892 Logan Rd Underwood QLD 4119",
    "addr:housenumber":"shop 7 2892",
    "addr:postcode":"4119",
    "addr:street":"Logan Rd",
    "iso:country":"AU",
    "sg:address":"Shop 7 2892 Logan Rd",
    "sg:city":"Underwood",
    "sg:classifiers":[
        {
            "category":"Travel",
            "subcategory":"Travel Agent",
            "type":"Entertainment"
        }
    ],
    "sg:phone":"+61 7 3841 4433",
    "sg:postcode":"4119",
    "sg:province":"QLD",
    "sg:tags":[
        "consultant"
    ],
    "wof:name":"Gold Club Tours & Travel",
    "wof:placetype":"venue"
},
  "geometry": {"coordinates":[153.11575317399999,-27.6111450195],"type":"Point"}
}