{
  "type": "Feature",
  "properties": {
    "addr:full":"1st Floor 210 Lower Heidelberg Rd Ivanhoe East VIC 3079",
    "addr:housenumber":"210",
    "addr:postcode":"3079",
    "addr:street":"Lower Heidelberg Rd",
    "iso:country":"AU",
    "sg:address":"1st Floor 210 Lower Heidelberg Rd",
    "sg:city":"Ivanhoe East",
    "sg:classifiers":[
        {
            "category":"Banks & Credit Unions",
            "subcategory":"Investment Brokerage",
            "type":"Services"
        }
    ],
    "sg:phone":"+61 3 9499 5177",
    "sg:postcode":"3079",
    "sg:province":"VIC",
    "wof:name":"Bernet & Associates Pty Ltd",
    "wof:placetype":"venue"
},
  "geometry": {"coordinates":[145.057373047,-37.7726669312],"type":"Point"}
}