{
  "type": "Feature",
  "properties": {
    "addr:full":"106 Caldarra Ave Engadine NSW 2233",
    "addr:housenumber":"106",
    "addr:postcode":"2233",
    "addr:street":"Caldarra Ave",
    "iso:country":"AU",
    "sg:address":"106 Caldarra Ave",
    "sg:city":"Engadine",
    "sg:classifiers":[
        {
            "category":"Health Services",
            "subcategory":"Doctor",
            "type":"Services"
        }
    ],
    "sg:phone":"+61 2 9520 8610",
    "sg:postcode":"2233",
    "sg:province":"NSW",
    "sg:tags":[
        "medical",
        "practitioner"
    ],
    "wof:name":"Tran Manh Dr",
    "wof:placetype":"venue"
},
  "geometry": {"coordinates":[151.01530456500001,-34.063659668],"type":"Point"}
}