{
  "type": "Feature",
  "properties": {
    "addr:full":"4 Miller St O'Connor ACT 2602",
    "addr:housenumber":"4",
    "addr:postcode":"2602",
    "addr:street":"Miller St",
    "iso:country":"AU",
    "sg:address":"4 Miller St",
    "sg:city":"O'Connor",
    "sg:classifiers":[
        {
            "category":"Professional",
            "subcategory":"Art Services",
            "type":"Services"
        }
    ],
    "sg:phone":"+61 412 045 203",
    "sg:postcode":"2602",
    "sg:province":"ACT",
    "sg:tags":[
        "sculptor"
    ],
    "wof:name":"Harding Matthew",
    "wof:placetype":"venue"
},
  "geometry": {"coordinates":[149.11453247099999,-35.2680702209],"type":"Point"}
}