{
  "type": "Feature",
  "properties": {
    "iso:country":"AU",
    "sg:address":"32 Gardere Ave",
    "sg:city":"Harbord",
    "sg:classifiers":[
        {
            "category":"Social Services",
            "subcategory":"Retirement Home",
            "type":"Services"
        }
    ],
    "sg:phone":"+61 2 9939 7294",
    "sg:postcode":"2096",
    "sg:province":"NSW",
    "sg:tags":[
        "environmental",
        "consultant",
        "pollution"
    ],
    "wof:name":"Alan Stewart & Associates",
    "wof:placetype":"venue"
},
  "geometry": {"coordinates":[151.29156494099999,-33.771232605],"type":"Point"}
}