{
  "type": "Feature",
  "properties": {
    "addr:full":"Cnr Portofino Drv & Narre Warren-Cranbourne Rd Cranbourne North VIC 3977",
    "addr:postcode":"3977",
    "addr:street":"Cnr Portofino Drv &;Warren-Cranbourne Rd",
    "iso:country":"AU",
    "sg:address":"Cnr Portofino Drv & Narre Warren-Cranbourne Rd",
    "sg:city":"Cranbourne North",
    "sg:classifiers":[
        {
            "category":"Health Services",
            "subcategory":"Doctor",
            "type":"Services"
        }
    ],
    "sg:phone":"+61 3 5995 8888",
    "sg:postcode":"3977",
    "sg:province":"VIC",
    "sg:tags":[
        "medical",
        "practitioner"
    ],
    "wof:name":"Casey Health Care",
    "wof:placetype":"venue"
},
  "geometry": {"coordinates":[145.29661560100001,-38.0781402588],"type":"Point"}
}