{
  "type": "Feature",
  "properties": {
    "addr:full":"45 McNamara Ave Airport West VIC 3042",
    "addr:housenumber":"45",
    "addr:postcode":"3042",
    "addr:street":"Mcnamara Ave",
    "iso:country":"AU",
    "sg:address":"45 McNamara Ave",
    "sg:city":"Airport West",
    "sg:classifiers":[
        {
            "category":"Wholesale",
            "subcategory":"Home Furnishings",
            "type":"Manufacturing & Wholesale Goods"
        }
    ],
    "sg:phone":"+61 418 176 672",
    "sg:postcode":"3042",
    "sg:province":"VIC",
    "sg:tags":[
        "wholesaler",
        "bedding",
        "mfrs",
        "bed"
    ],
    "wof:name":"Supafurn Pty Ltd",
    "wof:placetype":"venue"
},
  "geometry": {"coordinates":[144.88108825699999,-37.7260360718],"type":"Point"}
}