{
  "type": "Feature",
  "properties": {
    "addr:full":"18- 20 Railway Ave Ringwood East VIC 3135",
    "addr:housenumber":"20",
    "addr:postcode":"3135",
    "addr:street":"Railway Ave",
    "iso:country":"AU",
    "sg:address":"18- 20 Railway Ave",
    "sg:city":"Ringwood East",
    "sg:classifiers":[
        {
            "category":"Shopping",
            "subcategory":"Bridal",
            "type":"Retail Goods"
        }
    ],
    "sg:phone":"+61 3 9870 2665",
    "sg:postcode":"3135",
    "sg:province":"VIC",
    "sg:tags":[
        "hire",
        "wear"
    ],
    "wof:name":"Melanies Bridal Couture",
    "wof:placetype":"venue"
},
  "geometry": {"coordinates":[145.25201415999999,-37.8116912842],"type":"Point"}
}