{
  "type": "Feature",
  "properties": {
    "addr:full":"3/ 36 Mertonvale Cct Kingston TAS 7050",
    "addr:housenumber":"/ 36",
    "addr:postcode":"7050",
    "addr:street":"Mertonvale Cct",
    "iso:country":"AU",
    "sg:address":"3/ 36 Mertonvale Cct",
    "sg:city":"Kingston",
    "sg:classifiers":[
        {
            "category":"Wholesale",
            "subcategory":"Painting Supplies",
            "type":"Manufacturing & Wholesale Goods"
        }
    ],
    "sg:phone":"+61 3 6229 6540",
    "sg:postcode":"7050",
    "sg:province":"TAS",
    "sg:tags":[
        "product",
        "cleaning"
    ],
    "wof:name":"Supply Services Australia",
    "wof:placetype":"venue"
},
  "geometry": {"coordinates":[147.29414399999999,-42.982086],"type":"Point"}
}