{
  "type": "Feature",
  "properties": {
    "iso:country":"AU",
    "sg:address":"355 Bunnerong Rd",
    "sg:city":"Maroubra",
    "sg:classifiers":[
        {
            "category":"Building & Trades",
            "subcategory":"Cleaning & Sanitation",
            "type":"Services"
        }
    ],
    "sg:phone":"+61 419 524 157",
    "sg:postcode":"2035",
    "sg:province":"NSW",
    "sg:tags":[
        "cleaner",
        "repairer",
        "roof"
    ],
    "wof:name":"Mark Scanlon",
    "wof:placetype":"venue"
},
  "geometry": {"coordinates":[151.22735595699999,-33.9432640076],"type":"Point"}
}