{
  "type": "Feature",
  "properties": {
    "addr:full":"Shp 78 Werribee Plz, Cnr Heath & Dermut Rds Werribee VIC 3030",
    "addr:housenumber":"78",
    "addr:postcode":"3030",
    "addr:street":"Werribee Plz Cnr Heath & Dermut Rds",
    "iso:country":"AU",
    "sg:address":"Shp 78 Werribee Plz, Cnr Heath & Dermut Rds",
    "sg:city":"Werribee",
    "sg:classifiers":[
        {
            "category":"Wholesale",
            "subcategory":"Medical Equipment & Supplies",
            "type":"Manufacturing & Wholesale Goods"
        }
    ],
    "sg:phone":"+61 1800 057 220",
    "sg:postcode":"3030",
    "sg:province":"VIC",
    "sg:tags":[
        "aids",
        "hearing"
    ],
    "wof:name":"AudioClinic",
    "wof:placetype":"venue"
},
  "geometry": {"coordinates":[144.659637,-37.903702],"type":"Point"}
}