{
  "type": "Feature",
  "properties": {
    "iso:country":"AU",
    "sg:address":"Community Pl Off Banksia Rd",
    "sg:city":"Greenacre",
    "sg:classifiers":[
        {
            "category":"Education",
            "subcategory":"Kindergarten",
            "type":"Public Place"
        }
    ],
    "sg:phone":"+61 2 9759 9354",
    "sg:postcode":"2190",
    "sg:province":"NSW",
    "sg:tags":[
        "pre-schools"
    ],
    "wof:name":"KU Childrens Services",
    "wof:placetype":"venue"
},
  "geometry": {"coordinates":[151.056686,-33.908703],"type":"Point"}
}