{
  "type": "Feature",
  "properties": {
    "addr:full":"Sh 28a, Pacific Fair Shopng Cntr, Hooker Blvd Broadbeach QLD 4218",
    "addr:postcode":"4218",
    "addr:street":"Sh 28A Pacific;Blvd",
    "iso:country":"AU",
    "sg:address":"Sh 28a, Pacific Fair Shopng Cntr, Hooker Blvd",
    "sg:city":"Broadbeach",
    "sg:classifiers":[
        {
            "category":"Food & Beverages",
            "subcategory":"Liquor & Beverages",
            "type":"Retail Goods"
        }
    ],
    "sg:phone":"+61 7 5561 0900",
    "sg:postcode":"4218",
    "sg:province":"QLD",
    "sg:tags":[
        "store"
    ],
    "wof:name":"BWS Liquor Stores",
    "wof:placetype":"venue"
},
  "geometry": {"coordinates":[153.43081665,-28.034198761],"type":"Point"}
}