{
  "type": "Feature",
  "properties": {
    "iso:country":"AU",
    "sg:address":"29 Tennant St",
    "sg:city":"Fyshwick",
    "sg:classifiers":[
        {
            "category":"Banks & Credit Unions",
            "subcategory":"Bank",
            "type":"Services"
        }
    ],
    "sg:phone":"+61 2 6211 3000",
    "sg:postcode":"2609",
    "sg:province":"ACT",
    "sg:tags":[
        "concrete",
        "reinforcement"
    ],
    "wof:name":"Smorgon Steel",
    "wof:placetype":"venue"
},
  "geometry": {"coordinates":[149.18385314899999,-35.3321838379],"type":"Point"}
}