{
  "type": "Feature",
  "properties": {
    "addr:full":"Level 17, 60 Albert Rd South Melbourne VIC 3205",
    "addr:housenumber":"60",
    "addr:postcode":"3205",
    "addr:street":"Albert Rd",
    "iso:country":"AU",
    "sg:address":"Level 17, 60 Albert Rd",
    "sg:city":"South Melbourne",
    "sg:classifiers":[
        {
            "category":"Professional",
            "subcategory":"Computer Services",
            "type":"Services"
        }
    ],
    "sg:phone":"+61 3 8646 3333",
    "sg:postcode":"3205",
    "sg:province":"VIC",
    "sg:tags":[
        "consultant",
        "system"
    ],
    "wof:name":"WorldGroup Consulting",
    "wof:placetype":"venue"
},
  "geometry": {"coordinates":[144.971146,-37.834568],"type":"Point"}
}