{
  "type": "Feature",
  "properties": {
    "addr:full":"54 Giles St Kingston ACT 2604",
    "addr:housenumber":"54",
    "addr:postcode":"2604",
    "addr:street":"Giles St",
    "iso:country":"AU",
    "sg:address":"54 Giles St",
    "sg:city":"Kingston",
    "sg:classifiers":[
        {
            "category":"Fast Food",
            "type":"Food & Drink"
        }
    ],
    "sg:phone":"+61 2 6295 0318",
    "sg:postcode":"2604",
    "sg:province":"ACT",
    "sg:tags":[
        "away",
        "take"
    ],
    "wof:name":"Hoang Hau Restaurant",
    "wof:placetype":"venue"
},
  "geometry": {"coordinates":[149.14057922399999,-35.3154296875],"type":"Point"}
}