{
  "type": "Feature",
  "properties": {
    "addr:full":"135 a/b Swan St Morpeth NSW 2321",
    "addr:housenumber":"135 a / b",
    "addr:postcode":"2321",
    "addr:street":"Swan St",
    "iso:country":"AU",
    "sg:address":"135 a/b Swan St",
    "sg:city":"Morpeth",
    "sg:classifiers":[
        {
            "category":"Retail",
            "subcategory":"Laundry & Dry Cleaning",
            "type":"Services"
        }
    ],
    "sg:phone":"+61 2 4933 5787",
    "sg:postcode":"2321",
    "sg:province":"NSW",
    "sg:tags":[
        "breeder",
        "alpaca",
        "llama"
    ],
    "wof:name":"Australian Alpaca Barn",
    "wof:placetype":"venue"
},
  "geometry": {"coordinates":[151.627075195,-32.7248573303],"type":"Point"}
}