{
  "type": "Feature",
  "properties": {
    "iso:country":"AU",
    "sg:address":"Activities Centre Lincoln St",
    "sg:city":"Lindisfarne",
    "sg:classifiers":[
        {
            "category":"Education",
            "subcategory":"Dance Studio",
            "type":"Public Place"
        }
    ],
    "sg:phone":"+61 418 545 156",
    "sg:postcode":"7015",
    "sg:province":"TAS",
    "sg:tags":[
        "venue",
        "tuition"
    ],
    "wof:name":"Leaps Ahead Dance Studio",
    "wof:placetype":"venue"
},
  "geometry": {"coordinates":[147.35845947300001,-42.8460159302],"type":"Point"}
}