{
  "type": "Feature",
  "properties": {
    "addr:full":"Cnr Sunshine Blv & Karbunya St Mermaid Waters QLD 4218",
    "addr:postcode":"4218",
    "addr:street":"Cnr Sunshine Blv & Karbunya St",
    "iso:country":"AU",
    "sg:address":"Cnr Sunshine Blv & Karbunya St",
    "sg:city":"Mermaid Waters",
    "sg:classifiers":[
        {
            "category":"Health Services",
            "subcategory":"Health Practitioner",
            "type":"Services"
        }
    ],
    "sg:phone":"+61 7 5572 5166",
    "sg:postcode":"4218",
    "sg:province":"QLD",
    "sg:tags":[
        "physiotherapist"
    ],
    "wof:name":"Waterways Chiropractic",
    "wof:placetype":"venue"
},
  "geometry": {"coordinates":[153.42874145499999,-28.0586299896],"type":"Point"}
}