{
  "type": "Feature",
  "properties": {
    "addr:full":"3/ 493 Riversdale Rd Camberwell VIC 3124",
    "addr:housenumber":"/ 493",
    "addr:postcode":"3124",
    "addr:street":"Riversdale Rd",
    "iso:country":"AU",
    "sg:address":"3/ 493 Riversdale Rd",
    "sg:city":"Camberwell",
    "sg:classifiers":[
        {
            "category":"Sports & Exercise",
            "subcategory":"Gym",
            "type":"Entertainment"
        }
    ],
    "sg:phone":"+61 3 9815 1991",
    "sg:postcode":"3124",
    "sg:province":"VIC",
    "sg:tags":[
        "meditation"
    ],
    "wof:name":"Maine Rowena",
    "wof:placetype":"venue"
},
  "geometry": {"coordinates":[145.056884766,-37.8312301636],"type":"Point"}
}