{
  "type": "Feature",
  "properties": {
    "addr:full":"32 Rowland St Slacks Creek QLD 4127",
    "addr:housenumber":"32",
    "addr:postcode":"4127",
    "addr:street":"Rowland St",
    "iso:country":"AU",
    "sg:address":"32 Rowland St",
    "sg:city":"Slacks Creek",
    "sg:classifiers":[
        {
            "category":"Retail",
            "subcategory":"Veterinary Services",
            "type":"Services"
        }
    ],
    "sg:phone":"+61 7 3387 9797",
    "sg:postcode":"4127",
    "sg:province":"QLD",
    "sg:tags":[
        "surgeon"
    ],
    "wof:name":"Mason Kenneth",
    "wof:placetype":"venue"
},
  "geometry": {"coordinates":[153.126296997,-27.6301784515],"type":"Point"}
}