{
  "type": "Feature",
  "properties": {
    "addr:full":"657 Pittwater Rd Dee Why NSW 2099",
    "addr:housenumber":"657",
    "addr:postcode":"2099",
    "addr:street":"Pittwater Rd",
    "iso:country":"AU",
    "sg:address":"657 Pittwater Rd",
    "sg:city":"Dee Why",
    "sg:classifiers":[
        {
            "category":"Shopping",
            "subcategory":"Computers & Home Electronics",
            "type":"Retail Goods"
        }
    ],
    "sg:phone":"+61 2 9982 7500",
    "sg:postcode":"2099",
    "sg:province":"NSW",
    "sg:tags":[
        "hi-fi",
        "equipment"
    ],
    "wof:name":"Ryall Dave Electronics",
    "wof:placetype":"venue"
},
  "geometry": {"coordinates":[151.28416442899999,-33.7541770935],"type":"Point"}
}