{
  "type": "Feature",
  "properties": {
    "iso:country":"AU",
    "sg:address":"212 Arnold St",
    "sg:city":"Bendigo",
    "sg:classifiers":[
        {
            "category":"Real Estate",
            "subcategory":"Architect",
            "type":"Services"
        }
    ],
    "sg:phone":"+61 3 5444 5268",
    "sg:postcode":"3550",
    "sg:province":"VIC",
    "sg:tags":[
        "building",
        "designer"
    ],
    "wof:name":"Narell Peacock Design",
    "wof:placetype":"venue"
},
  "geometry": {"coordinates":[144.28590393100001,-36.7518005371],"type":"Point"}
}