{
  "type": "Feature",
  "properties": {
    "addr:full":"Suite 2, 17-23 Merriwa St Gordon NSW 2072",
    "addr:housenumber":"17-23",
    "addr:postcode":"2072",
    "addr:street":"Merriwa St",
    "iso:country":"AU",
    "sg:address":"Suite 2, 17-23 Merriwa St",
    "sg:city":"Gordon",
    "sg:classifiers":[
        {
            "category":"Professional",
            "subcategory":"Detective & Security Services",
            "type":"Services"
        }
    ],
    "sg:phone":"+61 2 9499 2144",
    "sg:postcode":"2072",
    "sg:province":"NSW",
    "sg:tags":[
        "consultant",
        "system"
    ],
    "wof:name":"Paramax Integrated Systems",
    "wof:placetype":"venue"
},
  "geometry": {"coordinates":[151.14729309099999,-33.752910614],"type":"Point"}
}