{
  "type": "Feature",
  "properties": {
    "addr:full":"Conway Rd Proserpine QLD 4800",
    "addr:postcode":"4800",
    "addr:street":"Conway Rd",
    "iso:country":"AU",
    "sg:address":"Conway Rd",
    "sg:city":"Proserpine",
    "sg:classifiers":[
        {
            "category":"Farming",
            "subcategory":"Crops",
            "type":"Manufacturing & Wholesale Goods"
        }
    ],
    "sg:phone":"+61 7 4947 3142",
    "sg:postcode":"4800",
    "sg:province":"QLD",
    "sg:tags":[
        "sugarcane",
        "mill",
        "grower"
    ],
    "wof:name":"Penhallurick J E & M A",
    "wof:placetype":"venue"
},
  "geometry": {"coordinates":[148.62742614699999,-20.375617981],"type":"Point"}
}