{
  "type": "Feature",
  "properties": {
    "addr:full":"Shop 1/ 69 Holbeche Rd Arndell Park NSW 2148",
    "addr:housenumber":"shop 1 / 69",
    "addr:postcode":"2148",
    "addr:street":"Holbeche Rd",
    "iso:country":"AU",
    "sg:address":"Shop 1/ 69 Holbeche Rd",
    "sg:city":"Arndell Park",
    "sg:classifiers":[
        {
            "category":"Fast Food",
            "type":"Food & Drink"
        }
    ],
    "sg:phone":"+61 2 9622 4093",
    "sg:postcode":"2148",
    "sg:province":"NSW",
    "sg:tags":[
        "away",
        "take"
    ],
    "wof:name":"Taste Of Paradise",
    "wof:placetype":"venue"
},
  "geometry": {"coordinates":[150.88182067899999,-33.7884178162],"type":"Point"}
}