{
  "type": "Feature",
  "properties": {
    "addr:full":"22 Monomeith St Rye VIC 3941",
    "addr:housenumber":"22",
    "addr:postcode":"3941",
    "addr:street":"Monomeith St",
    "iso:country":"AU",
    "sg:address":"22 Monomeith St",
    "sg:city":"Rye",
    "sg:classifiers":[
        {
            "category":"Building & Trades",
            "subcategory":"Construction",
            "type":"Services"
        }
    ],
    "sg:phone":"+61 3 5985 2501",
    "sg:postcode":"3941",
    "sg:province":"VIC",
    "sg:tags":[
        "concrete",
        "contractor"
    ],
    "wof:name":"ARTCO",
    "wof:placetype":"venue"
},
  "geometry": {"coordinates":[144.82369995100001,-38.3862686157],"type":"Point"}
}