{
  "type": "Feature",
  "properties": {
    "addr:full":"233 Edgars Rd Thomastown VIC 3074",
    "addr:housenumber":"233",
    "addr:postcode":"3074",
    "addr:street":"Edgars Rd",
    "iso:country":"AU",
    "sg:address":"233 Edgars Rd",
    "sg:city":"Thomastown",
    "sg:classifiers":[
        {
            "category":"Health Services",
            "subcategory":"Dentist",
            "type":"Services"
        }
    ],
    "sg:phone":"+61 3 9466 2501",
    "sg:postcode":"3074",
    "sg:province":"VIC",
    "wof:name":"Lambrineas Jim",
    "wof:placetype":"venue"
},
  "geometry": {"coordinates":[145.001190186,-37.6731452942],"type":"Point"}
}