{
  "type": "Feature",
  "properties": {
    "iso:country":"AU",
    "sg:address":"Shop 252, Chadstone Shopping Centre, 1341 Dandenong Rd",
    "sg:city":"Chadstone",
    "sg:classifiers":[
        {
            "category":"Food & Beverages",
            "subcategory":"Bakery",
            "type":"Retail Goods"
        }
    ],
    "sg:phone":"+61 3 9568 7339",
    "sg:postcode":"3148",
    "sg:province":"VIC",
    "sg:tags":[
        "baker"
    ],
    "wof:name":"Bakers Delight Ltd",
    "wof:placetype":"venue"
},
  "geometry": {"coordinates":[145.08218383799999,-37.8900718689],"type":"Point"}
}