{
  "type": "Feature",
  "properties": {
    "addr:full":"84 McDowall St Roma QLD 4455",
    "addr:housenumber":"84",
    "addr:postcode":"4455",
    "addr:street":"Mcdowall St",
    "iso:country":"AU",
    "sg:address":"84 McDowall St",
    "sg:city":"Roma",
    "sg:classifiers":[
        {
            "category":"Wholesale",
            "subcategory":"Medical Equipment & Supplies",
            "type":"Manufacturing & Wholesale Goods"
        }
    ],
    "sg:phone":"+61 1800 653 336",
    "sg:postcode":"4455",
    "sg:province":"QLD",
    "sg:tags":[
        "aids",
        "hearing"
    ],
    "wof:name":"King Hearing Centres",
    "wof:placetype":"venue"
},
  "geometry": {"coordinates":[148.78863525400001,-26.5716342926],"type":"Point"}
}