{
  "type": "Feature",
  "properties": {
    "iso:country":"AU",
    "sg:address":"Tylden Rd",
    "sg:city":"Woodend",
    "sg:classifiers":[
        {
            "category":"Building & Trades",
            "subcategory":"Landscaping Services",
            "type":"Services"
        }
    ],
    "sg:phone":"+61 3 5427 1540",
    "sg:postcode":"3442",
    "sg:province":"VIC",
    "sg:tags":[
        "grazier"
    ],
    "wof:name":"Rhoden P E & P T & P H",
    "wof:placetype":"venue"
},
  "geometry": {"coordinates":[144.53222656200001,-37.3525390625],"type":"Point"}
}