{
  "type": "Feature",
  "properties": {
    "iso:country":"AU",
    "sg:address":"Lot 200 Lui St",
    "sg:city":"Bamaga",
    "sg:classifiers":[
        {
            "category":"Retail",
            "subcategory":"Auto Repair",
            "type":"Services"
        }
    ],
    "sg:phone":"+61 7 4069 3507",
    "sg:postcode":"4876",
    "sg:province":"QLD",
    "sg:tags":[
        "repairer",
        "motor",
        "engineer"
    ],
    "wof:name":"Cape York Spares & Repairs",
    "wof:placetype":"venue"
},
  "geometry": {"coordinates":[142.39251709000001,-10.8925237656],"type":"Point"}
}