{
  "type": "Feature",
  "properties": {
    "iso:country":"AU",
    "sg:address":"Locked Bag 1999",
    "sg:city":"Sydney Olympic Park",
    "sg:classifiers":[
        {
            "category":"Retail",
            "subcategory":"Event Space",
            "type":"Services"
        }
    ],
    "sg:phone":"+61 2 8765 2000",
    "sg:postcode":"2127",
    "sg:province":"NSW",
    "sg:tags":[
        "function",
        "organiser"
    ],
    "wof:name":"Telstra Stadium",
    "wof:placetype":"venue"
},
  "geometry": {"coordinates":[151.06936645499999,-33.8435287476],"type":"Point"}
}