{
  "type": "Feature",
  "properties": {
    "addr:full":"10 Hogans Rd Hoppers Crossing VIC 3029",
    "addr:housenumber":"10",
    "addr:postcode":"3029",
    "addr:street":"Hogans Rd",
    "iso:country":"AU",
    "sg:address":"10 Hogans Rd",
    "sg:city":"Hoppers Crossing",
    "sg:classifiers":[
        {
            "category":"Shopping",
            "type":"Retail Goods"
        }
    ],
    "sg:phone":"+61 3 9749 3996",
    "sg:postcode":"3029",
    "sg:province":"VIC",
    "sg:tags":[
        "equipment",
        "safety",
        "accessory"
    ],
    "wof:name":"European Building Innovations",
    "wof:placetype":"venue"
},
  "geometry": {"coordinates":[144.70211800000001,-37.86451],"type":"Point"}
}