{
  "type": "Feature",
  "properties": {
    "addr:full":"17 Minilya Rd Broome WA 6725",
    "addr:housenumber":"17",
    "addr:postcode":"6725",
    "addr:street":"Minilya Rd",
    "iso:country":"AU",
    "sg:address":"17 Minilya Rd",
    "sg:city":"Broome",
    "sg:classifiers":[
        {
            "category":"Autos & Motor Vehicles",
            "subcategory":"Auto Supplies",
            "type":"Retail Goods"
        }
    ],
    "sg:phone":"+61 8 9192 5551",
    "sg:postcode":"6725",
    "sg:province":"WA",
    "sg:tags":[
        "accessory"
    ],
    "wof:name":"Broome Automotive Spares",
    "wof:placetype":"venue"
},
  "geometry": {"coordinates":[122.240600586,-17.9234752655],"type":"Point"}
}