{
  "type": "Feature",
  "properties": {
    "iso:country":"AU",
    "sg:address":"Ground Flr 2",
    "sg:city":"A Waverley Mall Bondi Junction",
    "sg:classifiers":[
        {
            "category":"Professional",
            "subcategory":"Computer Services",
            "type":"Services"
        }
    ],
    "sg:phone":"+61 2 9369 3784",
    "sg:postcode":"2022",
    "sg:province":"NSW",
    "sg:tags":[
        "training"
    ],
    "wof:name":"Futurekids Computer Learning Centres",
    "wof:placetype":"venue"
},
  "geometry": {"coordinates":[151.252029419,-33.8924865723],"type":"Point"}
}