{
  "type": "Feature",
  "properties": {
    "iso:country":"AU",
    "sg:address":"Milleara Shopping Centre Cnr Milleara Rd & Buckley St",
    "sg:city":"Keilor East",
    "sg:classifiers":[
        {
            "category":"Health Services",
            "subcategory":"Dentist",
            "type":"Services"
        }
    ],
    "sg:phone":"+61 3 9331 0091",
    "sg:postcode":"3033",
    "sg:province":"VIC",
    "wof:name":"Milleara Mall Dental Group",
    "wof:placetype":"venue"
},
  "geometry": {"coordinates":[144.864349,-37.737251],"type":"Point"}
}