{
  "type": "Feature",
  "properties": {
    "iso:country":"AU",
    "sg:address":"21/ 35 Oceans St",
    "sg:city":"Bondi",
    "sg:classifiers":[
        {
            "category":"Utilities",
            "subcategory":"Electric",
            "type":"Services"
        }
    ],
    "sg:phone":"+61 414 652 118",
    "sg:postcode":"2026",
    "sg:province":"NSW",
    "sg:tags":[
        "electrical",
        "contractor"
    ],
    "wof:name":"V.& V. Electrics",
    "wof:placetype":"venue"
},
  "geometry": {"coordinates":[151.262573242,-33.8922996521],"type":"Point"}
}