{
  "type": "Feature",
  "properties": {
    "addr:full":"Cnr Toombul & St Vincents Rds Virginia QLD 4014",
    "addr:postcode":"4014",
    "addr:street":"Cnr",
    "iso:country":"AU",
    "sg:address":"Cnr Toombul & St Vincents Rds",
    "sg:city":"Virginia",
    "sg:classifiers":[
        {
            "category":"Building & Trades",
            "subcategory":"Equipment Rental",
            "type":"Services"
        }
    ],
    "sg:phone":"+61 7 3260 6088",
    "sg:postcode":"4014",
    "sg:province":"QLD",
    "sg:tags":[
        "renting",
        "trailer"
    ],
    "wof:name":"Kennards Trailer Hire",
    "wof:placetype":"venue"
},
  "geometry": {"coordinates":[153.064056397,-27.3818836212],"type":"Point"}
}