{
  "type": "Feature",
  "properties": {
    "iso:country":"AU",
    "sg:address":"183 Old Hume Hwy",
    "sg:city":"Mittagong",
    "sg:classifiers":[
        {
            "category":"Industrial Area",
            "type":"Public Place"
        }
    ],
    "sg:phone":"+61 2 4872 1819",
    "sg:postcode":"2575",
    "sg:province":"NSW",
    "sg:tags":[
        "rural",
        "shed"
    ],
    "wof:name":"Highland Garages",
    "wof:placetype":"venue"
},
  "geometry": {"coordinates":[150.43827819800001,-34.4478874207],"type":"Point"}
}