{
  "type": "Feature",
  "properties": {
    "iso:country":"AU",
    "sg:address":"Shop 2, Ravenhill St",
    "sg:city":"Kings Langley",
    "sg:classifiers":[
        {
            "category":"Real Estate",
            "subcategory":"Real Estate Agent",
            "type":"Services"
        }
    ],
    "sg:phone":"+61 2 9674 4000",
    "sg:postcode":"2147",
    "sg:province":"NSW",
    "wof:name":"Richardson & Wrench Kings Langley",
    "wof:placetype":"venue"
},
  "geometry": {"coordinates":[150.922531128,-33.7422332764],"type":"Point"}
}