{
  "type": "Feature",
  "properties": {
    "addr:full":"112 Maroondah Hwy Ringwood VIC 3134",
    "addr:housenumber":"112",
    "addr:postcode":"3134",
    "addr:street":"Maroondah Hwy",
    "iso:country":"AU",
    "sg:address":"112 Maroondah Hwy",
    "sg:city":"Ringwood",
    "sg:classifiers":[
        {
            "category":"Shopping",
            "subcategory":"Antiques",
            "type":"Retail Goods"
        }
    ],
    "sg:phone":"+61 3 9870 3841",
    "sg:postcode":"3134",
    "sg:province":"VIC",
    "sg:tags":[
        "collectable",
        "memorabilia"
    ],
    "wof:name":"Comics &#039;R&#039; Us",
    "wof:placetype":"venue"
},
  "geometry": {"coordinates":[145.22796630900001,-37.815776825],"type":"Point"}
}