{
  "type": "Feature",
  "properties": {
    "addr:full":"140 East St Rockhampton QLD 4700",
    "addr:housenumber":"140",
    "addr:postcode":"4700",
    "addr:street":"East St",
    "iso:country":"AU",
    "sg:address":"140 East St",
    "sg:city":"Rockhampton",
    "sg:classifiers":[
        {
            "category":"Real Estate",
            "subcategory":"Real Estate Agent",
            "type":"Services"
        }
    ],
    "sg:phone":"+61 7 4927 7133",
    "sg:postcode":"4700",
    "sg:province":"QLD",
    "wof:name":"Frank Brady",
    "wof:placetype":"venue"
},
  "geometry": {"coordinates":[150.521392822,-23.3892631531],"type":"Point"}
}