{
  "type": "Feature",
  "properties": {
    "iso:country":"AU",
    "sg:address":"2b Turon St",
    "sg:city":"Morley",
    "sg:classifiers":[
        {
            "category":"Deli",
            "type":"Food & Drink"
        }
    ],
    "sg:phone":"+61 8 9279 4340",
    "sg:postcode":"6062",
    "sg:province":"WA",
    "sg:tags":[
        "delicatessen"
    ],
    "wof:name":"Somerset Deli & Take-Away",
    "wof:placetype":"venue"
},
  "geometry": {"coordinates":[115.924766541,-31.8854446411],"type":"Point"}
}