{
  "type": "Feature",
  "properties": {
    "iso:country":"AU",
    "sg:address":"28 Lincoln St",
    "sg:city":"Laverton North",
    "sg:classifiers":[
        {
            "category":"Personal",
            "subcategory":"Skin Care",
            "type":"Services"
        }
    ],
    "sg:phone":"+61 3 9369 7767",
    "sg:postcode":"3026",
    "sg:province":"VIC",
    "sg:tags":[
        "merchant",
        "hide"
    ],
    "wof:name":"Cost Price Sheepskin Co Pty Ltd",
    "wof:placetype":"venue"
},
  "geometry": {"coordinates":[144.81517,-37.822113],"type":"Point"}
}