{
  "type": "Feature",
  "properties": {
    "addr:full":"48a McCartin St Leongatha VIC 3953",
    "addr:housenumber":"48a",
    "addr:postcode":"3953",
    "addr:street":"Mccartin St",
    "iso:country":"AU",
    "sg:address":"48a McCartin St",
    "sg:city":"Leongatha",
    "sg:classifiers":[
        {
            "category":"Fast Food",
            "type":"Food & Drink"
        }
    ],
    "sg:phone":"+61 3 5662 5515",
    "sg:postcode":"3953",
    "sg:province":"VIC",
    "sg:tags":[
        "away",
        "take"
    ],
    "wof:name":"K & F Olcorn Pty Ltd",
    "wof:placetype":"venue"
},
  "geometry": {"coordinates":[145.94430542000001,-38.4773406982],"type":"Point"}
}