{
  "type": "Feature",
  "properties": {
    "iso:country":"AU",
    "sg:address":"Shop 2 29 Hospital Rd",
    "sg:city":"Emerald",
    "sg:classifiers":[
        {
            "category":"Personal",
            "subcategory":"Beauty Salon",
            "type":"Services"
        }
    ],
    "sg:phone":"+61 7 4982 2454",
    "sg:postcode":"4720",
    "sg:province":"QLD",
    "sg:tags":[
        "hairdresser"
    ],
    "wof:name":"Hair Hut",
    "wof:placetype":"venue"
},
  "geometry": {"coordinates":[148.15715,-23.520758],"type":"Point"}
}