{
  "type": "Feature",
  "properties": {
    "iso:country":"AU",
    "sg:address":"Hillsborough & Macquarie Rd",
    "sg:city":"Warners Bay",
    "sg:classifiers":[
        {
            "category":"Building & Trades",
            "subcategory":"Equipment Rental",
            "type":"Services"
        }
    ],
    "sg:phone":"+61 2 4954 6774",
    "sg:postcode":"2282",
    "sg:province":"NSW",
    "sg:tags":[
        "renting",
        "trailer"
    ],
    "wof:name":"Mobil Service Stations",
    "wof:placetype":"venue"
},
  "geometry": {"coordinates":[151.653900147,-32.9664230347],"type":"Point"}
}