{
  "type": "Feature",
  "properties": {
    "iso:country":"AU",
    "sg:address":"Level 29, 264 George St",
    "sg:city":"Sydney",
    "sg:classifiers":[
        {
            "category":"Professional",
            "subcategory":"Accounting & Tax Preparation",
            "type":"Services"
        }
    ],
    "sg:phone":"+61 2 9251 4600",
    "sg:postcode":"2000",
    "sg:province":"NSW",
    "sg:tags":[
        "accountant",
        "auditor"
    ],
    "wof:name":"Hillman N",
    "wof:placetype":"venue"
},
  "geometry": {"coordinates":[151.207519531,-33.8647346497],"type":"Point"}
}