{
  "type": "Feature",
  "properties": {
    "addr:full":"103 Abbott St Cairns QLD 4870",
    "addr:housenumber":"103",
    "addr:postcode":"4870",
    "addr:street":"Abbott St",
    "iso:country":"AU",
    "sg:address":"103 Abbott St",
    "sg:city":"Cairns",
    "sg:classifiers":[
        {
            "category":"Food & Beverages",
            "subcategory":"Supermarket",
            "type":"Retail Goods"
        }
    ],
    "sg:phone":"+61 7 4051 2015",
    "sg:postcode":"4870",
    "sg:province":"QLD",
    "sg:tags":[
        "grocery",
        "store"
    ],
    "wof:name":"Woolworths Limited",
    "wof:placetype":"venue"
},
  "geometry": {"coordinates":[145.77879333499999,-16.9237518311],"type":"Point"}
}