{
  "type": "Feature",
  "properties": {
    "addr:full":"70- 72 Yass Rd Queanbeyan NSW 2620",
    "addr:housenumber":"72",
    "addr:postcode":"2620",
    "addr:street":"Yass Rd",
    "iso:country":"AU",
    "sg:address":"70- 72 Yass Rd",
    "sg:city":"Queanbeyan",
    "sg:classifiers":[
        {
            "category":"Social Services",
            "subcategory":"Adult Care",
            "type":"Services"
        }
    ],
    "sg:phone":"+61 2 6299 3977",
    "sg:postcode":"2620",
    "sg:province":"NSW",
    "sg:tags":[
        "towing"
    ],
    "wof:name":"David Smash Repairs",
    "wof:placetype":"venue"
},
  "geometry": {"coordinates":[149.24354553200001,-35.3397026062],"type":"Point"}
}