{
  "type": "Feature",
  "properties": {
    "addr:full":"Shop 208 Wallsend Plaza Wallsend NSW 2287",
    "addr:housenumber":"208",
    "addr:postcode":"2287",
    "addr:street":"Wallsend Plaza",
    "iso:country":"AU",
    "sg:address":"Shop 208",
    "sg:city":"Wallsend Plaza Wallsend",
    "sg:classifiers":[
        {
            "category":"Shopping",
            "subcategory":"Jewelry",
            "type":"Retail Goods"
        }
    ],
    "sg:phone":"+61 2 4965 6211",
    "sg:postcode":"2287",
    "sg:province":"NSW",
    "sg:tags":[
        "jeweller"
    ],
    "wof:name":"Hourglass Jewellers",
    "wof:placetype":"venue"
},
  "geometry": {"coordinates":[151.66819763199999,-32.9037284851],"type":"Point"}
}