{
  "type": "Feature",
  "properties": {
    "addr:full":"310a Botany Rd Alexandria NSW 2015",
    "addr:housenumber":"310a",
    "addr:postcode":"2015",
    "addr:street":"Botany Rd",
    "iso:country":"AU",
    "sg:address":"310a Botany Rd",
    "sg:city":"Alexandria",
    "sg:classifiers":[
        {
            "category":"Manufacturing",
            "subcategory":"Furniture",
            "type":"Manufacturing & Wholesale Goods"
        }
    ],
    "sg:phone":"+61 2 9319 4600",
    "sg:postcode":"2015",
    "sg:province":"NSW",
    "sg:tags":[
        "builder",
        "designer",
        "custom"
    ],
    "wof:name":"Sears Decor",
    "wof:placetype":"venue"
},
  "geometry": {"coordinates":[151.20269775400001,-33.9054412842],"type":"Point"}
}