{
  "type": "Feature",
  "properties": {
    "addr:full":"20 Lepena Crs Hallett Cove SA 5158",
    "addr:housenumber":"20",
    "addr:postcode":"5158",
    "addr:street":"Lepena Crs",
    "iso:country":"AU",
    "sg:address":"20 Lepena Crs",
    "sg:city":"Hallett Cove",
    "sg:classifiers":[
        {
            "category":"Building & Trades",
            "subcategory":"Pest Control",
            "type":"Services"
        }
    ],
    "sg:phone":"+61 8 8381 2596",
    "sg:postcode":"5158",
    "sg:province":"SA",
    "wof:name":"Universal Pest Control Pty Ltd",
    "wof:placetype":"venue"
},
  "geometry": {"coordinates":[138.512741089,-35.0668983459],"type":"Point"}
}