{
  "type": "Feature",
  "properties": {
    "addr:full":"27 Gordon St Mt Morgan QLD 4714",
    "addr:housenumber":"27",
    "addr:postcode":"4714",
    "addr:street":"Gordon St",
    "iso:country":"AU",
    "sg:address":"27 Gordon St",
    "sg:city":"Mt Morgan",
    "sg:classifiers":[
        {
            "category":"Building & Trades",
            "subcategory":"Construction",
            "type":"Services"
        }
    ],
    "sg:phone":"+61 7 4938 1229",
    "sg:postcode":"4714",
    "sg:province":"QLD",
    "sg:tags":[
        "earth",
        "excavating",
        "moving",
        "contractor"
    ],
    "wof:name":"Mt Morgan Truck & Crane Hire",
    "wof:placetype":"venue"
},
  "geometry": {"coordinates":[150.38340759299999,-23.6470394135],"type":"Point"}
}