{
  "type": "Feature",
  "properties": {
    "addr:full":"118 Hudson Rd Spotswood VIC 3015",
    "addr:housenumber":"118",
    "addr:postcode":"3015",
    "addr:street":"Hudson Rd",
    "iso:country":"AU",
    "sg:address":"118 Hudson Rd",
    "sg:city":"Spotswood",
    "sg:classifiers":[
        {
            "category":"Professional",
            "subcategory":"Engineering",
            "type":"Services"
        }
    ],
    "sg:phone":"+61 3 9391 3920",
    "sg:postcode":"3015",
    "sg:province":"VIC",
    "sg:tags":[
        "engineer"
    ],
    "wof:name":"Servac Engineering Pty Ltd",
    "wof:placetype":"venue"
},
  "geometry": {"coordinates":[144.88302612300001,-37.8292884827],"type":"Point"}
}