{
  "type": "Feature",
  "properties": {
    "iso:country":"AU",
    "sg:address":"9 Westmarket St",
    "sg:city":"Richmond",
    "sg:classifiers":[
        {
            "category":"Building & Trades",
            "subcategory":"Construction",
            "type":"Services"
        }
    ],
    "sg:phone":"+61 2 4578 4399",
    "sg:postcode":"2753",
    "sg:province":"NSW",
    "sg:tags":[
        "home",
        "air conditioning"
    ],
    "wof:name":"Richmond Retravision",
    "wof:placetype":"venue"
},
  "geometry": {"coordinates":[150.752410889,-33.5984802246],"type":"Point"}
}