{
  "type": "Feature",
  "properties": {
    "addr:full":"Rear Entrance 97B Henry St Penrith NSW 2750",
    "addr:housenumber":"97b",
    "addr:postcode":"2750",
    "addr:street":"Entrance;Henry St",
    "iso:country":"AU",
    "sg:address":"Rear Entrance 97B Henry St",
    "sg:city":"Penrith",
    "sg:classifiers":[
        {
            "category":"Shopping",
            "subcategory":"Crafts & Fabrics",
            "type":"Retail Goods"
        }
    ],
    "sg:phone":"+61 2 4721 1213",
    "sg:postcode":"2750",
    "sg:province":"NSW",
    "sg:tags":[
        "supply"
    ],
    "wof:name":"Penrith Patchwork Folklore",
    "wof:placetype":"venue"
},
  "geometry": {"coordinates":[150.982055664,-33.8592300415],"type":"Point"}
}