{
  "type": "Feature",
  "properties": {
    "addr:full":"37 Church St Brighton VIC 3186",
    "addr:housenumber":"37",
    "addr:postcode":"3186",
    "addr:street":"Church St",
    "iso:country":"AU",
    "sg:address":"37 Church St",
    "sg:city":"Brighton",
    "sg:classifiers":[
        {
            "category":"Health Services",
            "subcategory":"Optometrist",
            "type":"Services"
        }
    ],
    "sg:phone":"+61 3 9592 4800",
    "sg:postcode":"3186",
    "sg:province":"VIC",
    "wof:name":"Bastiaan J N",
    "wof:placetype":"venue"
},
  "geometry": {"coordinates":[144.99391174300001,-37.9132347107],"type":"Point"}
}