{
  "type": "Feature",
  "properties": {
    "addr:full":"59 Cadbury Rd Claremont TAS 7011",
    "addr:housenumber":"59",
    "addr:postcode":"7011",
    "addr:street":"Cadbury Rd",
    "iso:country":"AU",
    "sg:address":"59 Cadbury Rd",
    "sg:city":"Claremont",
    "sg:classifiers":[
        {
            "category":"Organizations",
            "subcategory":"Non-profit Organization",
            "type":"Services"
        }
    ],
    "sg:phone":"+61 3 6249 5144",
    "sg:postcode":"7011",
    "sg:province":"TAS",
    "sg:tags":[
        "support",
        "disability",
        "organisation"
    ],
    "wof:name":"Tasmanian Deaf Society Inc",
    "wof:placetype":"venue"
},
  "geometry": {"coordinates":[147.260253906,-42.7895355225],"type":"Point"}
}