{
  "type": "Feature",
  "properties": {
    "iso:country":"AU",
    "sg:address":"Loganholme Shopping Village Bryants Road",
    "sg:city":"Loganholme",
    "sg:classifiers":[
        {
            "category":"Real Estate",
            "subcategory":"Real Estate Agent",
            "type":"Services"
        }
    ],
    "sg:phone":"+61 7 3801 2020",
    "sg:postcode":"4129",
    "sg:province":"QLD",
    "wof:name":"Shailer Park First National",
    "wof:placetype":"venue"
},
  "geometry": {"coordinates":[153.18995666500001,-27.6680431366],"type":"Point"}
}