{
  "type": "Feature",
  "properties": {
    "iso:country":"AU",
    "sg:address":"7012 Gwydir Hwy",
    "sg:city":"Inverell",
    "sg:classifiers":[
        {
            "category":"Personal",
            "type":"Services"
        }
    ],
    "sg:phone":"+61 2 6722 5885",
    "sg:postcode":"2360",
    "sg:province":"NSW",
    "sg:tags":[
        "wallpapering",
        "wallcovering"
    ],
    "wof:name":"Jeffries Mark",
    "wof:placetype":"venue"
},
  "geometry": {"coordinates":[151.11361694300001,-29.7762546539],"type":"Point"}
}