{
  "type": "Feature",
  "properties": {
    "addr:full":"Suite 1, 173- 179 Bigge St Liverpool NSW 2170",
    "addr:housenumber":"173 179",
    "addr:postcode":"2170",
    "addr:street":"Bigge St",
    "iso:country":"AU",
    "sg:address":"Suite 1, 173- 179 Bigge St",
    "sg:city":"Liverpool",
    "sg:classifiers":[
        {
            "category":"Real Estate",
            "subcategory":"Real Estate Agent",
            "type":"Services"
        }
    ],
    "sg:phone":"+61 2 9822 4111",
    "sg:postcode":"2170",
    "sg:province":"NSW",
    "wof:name":"L J Hooker",
    "wof:placetype":"venue"
},
  "geometry": {"coordinates":[150.92686462399999,-33.9220924377],"type":"Point"}
}