{
  "type": "Feature",
  "properties": {
    "addr:full":"1 Richmond St Cronulla NSW 2230",
    "addr:housenumber":"1",
    "addr:postcode":"2230",
    "addr:street":"Richmond St",
    "iso:country":"AU",
    "sg:address":"1 Richmond St",
    "sg:city":"Cronulla",
    "sg:classifiers":[
        {
            "category":"Health Services",
            "subcategory":"Dentist",
            "type":"Services"
        }
    ],
    "sg:phone":"+61 2 9523 0241",
    "sg:postcode":"2230",
    "sg:province":"NSW",
    "sg:tags":[
        "dental",
        "prosthetist"
    ],
    "wof:name":"Hayes R D",
    "wof:placetype":"venue"
},
  "geometry": {"coordinates":[151.15245056099999,-34.0625648499],"type":"Point"}
}