{
  "type": "Feature",
  "properties": {
    "iso:country":"AU",
    "sg:address":"Shop 66 The Corso",
    "sg:city":"Manly",
    "sg:classifiers":[
        {
            "category":"Shopping",
            "subcategory":"Clothing, Apparel, & Fashions",
            "type":"Retail Goods"
        }
    ],
    "sg:phone":"+61 2 9977 1970",
    "sg:postcode":"2095",
    "sg:province":"NSW",
    "sg:tags":[
        "lady",
        "wear"
    ],
    "wof:name":"Sussan",
    "wof:placetype":"venue"
},
  "geometry": {"coordinates":[151.286743164,-33.798084259],"type":"Point"}
}