{
  "type": "Feature",
  "properties": {
    "addr:full":"1a Eileen St Booval QLD 4304",
    "addr:housenumber":"1a",
    "addr:postcode":"4304",
    "addr:street":"Eileen St",
    "iso:country":"AU",
    "sg:address":"1a Eileen St",
    "sg:city":"Booval",
    "sg:classifiers":[
        {
            "category":"Health Services",
            "subcategory":"Dentist",
            "type":"Services"
        }
    ],
    "sg:phone":"+61 7 3281 1319",
    "sg:postcode":"4304",
    "sg:province":"QLD",
    "wof:name":"Wong Andrew Dr",
    "wof:placetype":"venue"
},
  "geometry": {"coordinates":[152.7862854,-27.614200592],"type":"Point"}
}