{
  "type": "Feature",
  "properties": {
    "iso:country":"AU",
    "sg:address":"PO Box 230",
    "sg:city":"Beverly Hills",
    "sg:classifiers":[
        {
            "category":"Building & Trades",
            "subcategory":"Construction",
            "type":"Services"
        }
    ],
    "sg:phone":"+61 414 522 455",
    "sg:postcode":"2209",
    "sg:province":"NSW",
    "sg:tags":[
        "earth",
        "excavating",
        "moving",
        "contractor"
    ],
    "wof:name":"Magnum Demolitions",
    "wof:placetype":"venue"
},
  "geometry": {"coordinates":[151.079666,-33.947041],"type":"Point"}
}