{
  "type": "Feature",
  "properties": {
    "addr:full":"Shop 8, 147- 151 Foster St Dandenong VIC 3175",
    "addr:housenumber":"shop 8;151",
    "addr:postcode":"147;3175",
    "addr:street":"Foster St",
    "iso:country":"AU",
    "sg:address":"Shop 8, 147- 151 Foster St",
    "sg:city":"Dandenong",
    "sg:classifiers":[
        {
            "category":"Real Estate",
            "subcategory":"Real Estate Agent",
            "type":"Services"
        }
    ],
    "sg:phone":"+61 3 9213 3000",
    "sg:postcode":"3175",
    "sg:province":"VIC",
    "wof:name":"RE/MAX Property Specialist",
    "wof:placetype":"venue"
},
  "geometry": {"coordinates":[145.21644592300001,-37.989402771],"type":"Point"}
}