{
  "type": "Feature",
  "properties": {
    "iso:country":"AU",
    "sg:address":"7a Bartlett St",
    "sg:city":"Summer Hill (Sydney)",
    "sg:classifiers":[
        {
            "category":"Professional",
            "subcategory":"Business Services",
            "type":"Services"
        }
    ],
    "sg:phone":"+61 2 9798 3533",
    "sg:postcode":"2130",
    "sg:province":"NSW",
    "sg:tags":[
        "broker"
    ],
    "wof:name":"Cec Phillips Pty Ltd",
    "wof:placetype":"venue"
},
  "geometry": {"coordinates":[151.135696411,-33.8928794861],"type":"Point"}
}