{
  "type": "Feature",
  "properties": {
    "addr:full":"12 Wirra Crt Salisbury SA 5108",
    "addr:housenumber":"12",
    "addr:postcode":"5108",
    "addr:street":"Wirra Crt",
    "iso:country":"AU",
    "sg:address":"12 Wirra Crt",
    "sg:city":"Salisbury",
    "sg:classifiers":[
        {
            "category":"Farming",
            "subcategory":"Farm & Veterinary Services",
            "type":"Manufacturing & Wholesale Goods"
        }
    ],
    "sg:phone":"+61 8 8250 8219",
    "sg:postcode":"5108",
    "sg:province":"SA",
    "sg:tags":[
        "irrigation",
        "reticulation",
        "system"
    ],
    "wof:name":"Irrigation System Manufacturing",
    "wof:placetype":"venue"
},
  "geometry": {"coordinates":[138.61796569800001,-34.7366065979],"type":"Point"}
}