{
  "type": "Feature",
  "properties": {
    "addr:full":"Suite 11, 28- 32 Arnold St Box Hill VIC 3128",
    "addr:housenumber":"28 32",
    "addr:postcode":"3128",
    "addr:street":"Arnold St",
    "iso:country":"AU",
    "sg:address":"Suite 11, 28- 32 Arnold St",
    "sg:city":"Box Hill",
    "sg:classifiers":[
        {
            "category":"Health Services",
            "subcategory":"Dentist",
            "type":"Services"
        }
    ],
    "sg:phone":"+61 3 9898 1877",
    "sg:postcode":"3128",
    "sg:province":"VIC",
    "wof:name":"Ferguson John W Dr",
    "wof:placetype":"venue"
},
  "geometry": {"coordinates":[145.11929321299999,-37.8174324036],"type":"Point"}
}