{
  "type": "Feature",
  "properties": {
    "addr:full":"2- 58 Newmarket St Flemington VIC 3031",
    "addr:housenumber":"58",
    "addr:postcode":"3031",
    "addr:street":"2;Newmarket St",
    "iso:country":"AU",
    "sg:address":"2- 58 Newmarket St",
    "sg:city":"Flemington",
    "sg:classifiers":[
        {
            "category":"Health Services",
            "subcategory":"Nursing And Care Facility",
            "type":"Services"
        }
    ],
    "sg:phone":"+61 3 9376 9966",
    "sg:postcode":"3031",
    "sg:province":"VIC",
    "sg:tags":[
        "home"
    ],
    "wof:name":"Gregory Lodge Nursing Home",
    "wof:placetype":"venue"
},
  "geometry": {"coordinates":[144.92700199999999,-37.786579],"type":"Point"}
}