{
  "type": "Feature",
  "properties": {
    "addr:full":"E111 Northview St Mermaid Beach QLD 4218",
    "addr:housenumber":"e111",
    "addr:postcode":"4218",
    "addr:street":"Northview St",
    "iso:country":"AU",
    "sg:address":"E111 Northview St",
    "sg:city":"Mermaid Beach",
    "sg:classifiers":[
        {
            "category":"Retail",
            "subcategory":"Auto Rental",
            "type":"Services"
        }
    ],
    "sg:phone":"+61 7 5575 5400",
    "sg:postcode":"4218",
    "sg:province":"QLD",
    "sg:tags":[
        "car",
        "hire",
        "minibus"
    ],
    "wof:name":"5 Star Car Rentals",
    "wof:placetype":"venue"
},
  "geometry": {"coordinates":[153.43182373100001,-28.0402889252],"type":"Point"}
}