{
  "type": "Feature",
  "properties": {
    "iso:country":"AU",
    "sg:address":"93 Tabilban St",
    "sg:city":"Burleigh Heads",
    "sg:classifiers":[
        {
            "category":"Professional",
            "subcategory":"Computer Services",
            "type":"Services"
        }
    ],
    "sg:phone":"+61 7 5535 3740",
    "sg:postcode":"4220",
    "sg:province":"QLD",
    "sg:tags":[
        "tele-communications",
        "consultant"
    ],
    "wof:name":"Boat House Cabling",
    "wof:placetype":"venue"
},
  "geometry": {"coordinates":[153.44461059599999,-28.0966300964],"type":"Point"}
}