{
  "type": "Feature",
  "properties": {
    "addr:full":"16 Herbert St Goondiwindi QLD 4390",
    "addr:housenumber":"16",
    "addr:postcode":"4390",
    "addr:street":"Herbert St",
    "iso:country":"AU",
    "sg:address":"16 Herbert St",
    "sg:city":"Goondiwindi",
    "sg:classifiers":[
        {
            "category":"Health Services",
            "subcategory":"Chiropractor",
            "type":"Services"
        }
    ],
    "sg:phone":"+61 7 4671 3609",
    "sg:postcode":"4390",
    "sg:province":"QLD",
    "wof:name":"Barham Chiropractic",
    "wof:placetype":"venue"
},
  "geometry": {"coordinates":[150.305511475,-28.5458698273],"type":"Point"}
}