{
  "type": "Feature",
  "properties": {
    "addr:full":"Knutsford St Fremantle WA 6160",
    "addr:postcode":"6160",
    "addr:street":"Knutsford St",
    "iso:country":"AU",
    "sg:address":"Knutsford St",
    "sg:city":"Fremantle",
    "sg:classifiers":[
        {
            "category":"Utilities",
            "subcategory":"Refuse",
            "type":"Services"
        }
    ],
    "sg:phone":"+61 8 9432 9612",
    "sg:postcode":"6160",
    "sg:province":"WA",
    "sg:tags":[
        "disposal",
        "reduction",
        "waste"
    ],
    "wof:name":"City of Fremantle Waste Management",
    "wof:placetype":"venue"
},
  "geometry": {"coordinates":[115.756439,-32.053467],"type":"Point"}
}