{
  "type": "Feature",
  "properties": {
    "addr:full":"7 Gow Ave Port Hacking NSW 2229",
    "addr:housenumber":"7",
    "addr:postcode":"2229",
    "addr:street":"Gow Ave Port",
    "iso:country":"AU",
    "sg:address":"7 Gow Ave",
    "sg:city":"Port Hacking",
    "sg:classifiers":[
        {
            "category":"Communications",
            "subcategory":"Film & Video Production",
            "type":"Services"
        }
    ],
    "sg:phone":"+61 2 9542 8121",
    "sg:postcode":"2229",
    "sg:province":"NSW",
    "sg:tags":[
        "trestle",
        "ladders",
        "steps",
        "accessory"
    ],
    "wof:name":"Lilly Pilly Ladders",
    "wof:placetype":"venue"
},
  "geometry": {"coordinates":[151.125656128,-34.068321228],"type":"Point"}
}