{
  "type": "Feature",
  "properties": {
    "addr:full":"151 Victoria Ave Chatswood NSW 2067",
    "addr:housenumber":"151",
    "addr:postcode":"2067",
    "addr:street":"Victoria Ave",
    "iso:country":"AU",
    "sg:address":"151 Victoria Ave",
    "sg:city":"Chatswood",
    "sg:classifiers":[
        {
            "category":"Sports & Exercise",
            "subcategory":"Gym",
            "type":"Entertainment"
        }
    ],
    "sg:phone":"+61 2 9419 4077",
    "sg:postcode":"2067",
    "sg:province":"NSW",
    "sg:tags":[
        "health",
        "fitness"
    ],
    "wof:name":"Shape Toning Studio",
    "wof:placetype":"venue"
},
  "geometry": {"coordinates":[151.19476318400001,-33.7925262451],"type":"Point"}
}