{
  "type": "Feature",
  "properties": {
    "addr:full":"43 Hertford St Upper Mt Gravatt QLD 4122",
    "addr:housenumber":"43",
    "addr:postcode":"4122",
    "addr:street":"Hertford St",
    "iso:country":"AU",
    "sg:address":"43 Hertford St",
    "sg:city":"Upper Mt Gravatt",
    "sg:classifiers":[
        {
            "category":"Health Services",
            "subcategory":"Health Practitioner",
            "type":"Services"
        }
    ],
    "sg:phone":"+61 7 3422 1782",
    "sg:postcode":"4122",
    "sg:province":"QLD",
    "sg:tags":[
        "psychologist"
    ],
    "wof:name":"New Directions Clinic",
    "wof:placetype":"venue"
},
  "geometry": {"coordinates":[153.08172607399999,-27.5514965057],"type":"Point"}
}