{
  "type": "Feature",
  "properties": {
    "iso:country":"AU",
    "sg:address":"10 Main St",
    "sg:city":"Crafers",
    "sg:classifiers":[
        {
            "category":"Food & Beverages",
            "subcategory":"Liquor & Beverages",
            "type":"Retail Goods"
        }
    ],
    "sg:phone":"+61 8 8339 2050",
    "sg:postcode":"5152",
    "sg:province":"SA",
    "sg:tags":[
        "store"
    ],
    "wof:name":"Liquorsmart Pty Ltd",
    "wof:placetype":"venue"
},
  "geometry": {"coordinates":[138.70460510300001,-34.9976997375],"type":"Point"}
}