{
  "type": "Feature",
  "properties": {
    "addr:full":"Thompson St Normanton QLD 4890",
    "addr:postcode":"4890",
    "addr:street":"Thompson St",
    "iso:country":"AU",
    "sg:address":"Thompson St",
    "sg:city":"Normanton",
    "sg:classifiers":[
        {
            "category":"Education",
            "subcategory":"School",
            "type":"Public Place"
        }
    ],
    "sg:phone":"+61 7 4745 1383",
    "sg:postcode":"4890",
    "sg:province":"QLD",
    "sg:tags":[
        "state",
        "except",
        "nsw"
    ],
    "wof:name":"Normanton Preschool",
    "wof:placetype":"venue"
},
  "geometry": {"coordinates":[141.08076477,-17.6715526581],"type":"Point"}
}