{
  "type": "Feature",
  "properties": {
    "addr:full":"285 New St Brighton VIC 3186",
    "addr:housenumber":"285",
    "addr:postcode":"3186",
    "addr:street":"New St",
    "iso:country":"AU",
    "sg:address":"285 New St",
    "sg:city":"Brighton",
    "sg:classifiers":[
        {
            "category":"Arts & Performance",
            "subcategory":"Art Gallery",
            "type":"Entertainment"
        }
    ],
    "sg:phone":"+61 3 9592 1252",
    "sg:postcode":"3186",
    "sg:province":"VIC",
    "wof:name":"Luba Bilu Gallery",
    "wof:placetype":"venue"
},
  "geometry": {"coordinates":[144.992385864,-37.9075279236],"type":"Point"}
}