{
  "type": "Feature",
  "properties": {
    "addr:full":"33 Nott St Port Melbourne VIC 3207",
    "addr:housenumber":"33",
    "addr:postcode":"3207",
    "addr:street":"Nott St",
    "iso:country":"AU",
    "sg:address":"33 Nott St",
    "sg:city":"Port Melbourne",
    "sg:classifiers":[
        {
            "category":"Mining & Drilling",
            "type":"Manufacturing & Wholesale Goods"
        }
    ],
    "sg:phone":"+61 3 9646 7500",
    "sg:postcode":"3207",
    "sg:province":"VIC",
    "sg:tags":[
        "boring",
        "contractor"
    ],
    "wof:name":"Wagstaff Piling",
    "wof:placetype":"venue"
},
  "geometry": {"coordinates":[144.944199,-37.831394],"type":"Point"}
}