{
  "type": "Feature",
  "properties": {
    "addr:full":"46 Kolora Rd Heidelberg West VIC 3081",
    "addr:housenumber":"46",
    "addr:postcode":"3081",
    "addr:street":"Kolora Rd",
    "iso:country":"AU",
    "sg:address":"46 Kolora Rd",
    "sg:city":"Heidelberg West",
    "sg:classifiers":[
        {
            "category":"Building & Trades",
            "subcategory":"Construction",
            "type":"Services"
        }
    ],
    "sg:phone":"+61 3 9455 1510",
    "sg:postcode":"3081",
    "sg:province":"VIC",
    "sg:tags":[
        "mural"
    ],
    "wof:name":"Melbourne Mural Studio Pty Ltd",
    "wof:placetype":"venue"
},
  "geometry": {"coordinates":[145.04592895499999,-37.7331314087],"type":"Point"}
}