{
  "type": "Feature",
  "properties": {
    "iso:country":"AU",
    "sg:address":"535 Toolamba Rd",
    "sg:city":"Mooroopna",
    "sg:classifiers":[
        {
            "category":"Shopping",
            "subcategory":"Stationery & Office Supplies",
            "type":"Retail Goods"
        }
    ],
    "sg:phone":"+61 3 5825 2589",
    "sg:postcode":"3629",
    "sg:province":"VIC",
    "sg:tags":[
        "packaging",
        "equipment",
        "sealing",
        "filling"
    ],
    "wof:name":"Custom Conveyors",
    "wof:placetype":"venue"
},
  "geometry": {"coordinates":[145.33171081500001,-36.438873291],"type":"Point"}
}