{
  "type": "Feature",
  "properties": {
    "addr:full":"153 Beaufort St Perth WA 6000",
    "addr:housenumber":"153",
    "addr:postcode":"6000",
    "addr:street":"Beaufort St",
    "iso:country":"AU",
    "sg:address":"153 Beaufort St",
    "sg:city":"Perth",
    "sg:classifiers":[
        {
            "category":"Retail",
            "subcategory":"Repair Shop",
            "type":"Services"
        }
    ],
    "sg:phone":"+61 8 9328 7804",
    "sg:postcode":"6000",
    "sg:province":"WA",
    "sg:tags":[
        "leadlights"
    ],
    "wof:name":"Mainstone Glass & Leadlights",
    "wof:placetype":"venue"
},
  "geometry": {"coordinates":[115.865196228,-31.9452075958],"type":"Point"}
}