{
  "type": "Feature",
  "properties": {
    "addr:full":"110 Temora St Cootamundra NSW 2590",
    "addr:housenumber":"110",
    "addr:postcode":"2590",
    "addr:street":"Temora St",
    "iso:country":"AU",
    "sg:address":"110 Temora St",
    "sg:city":"Cootamundra",
    "sg:classifiers":[
        {
            "category":"Autos & Motor Vehicles",
            "subcategory":"Auto Supplies",
            "type":"Retail Goods"
        }
    ],
    "sg:phone":"+61 2 6942 3488",
    "sg:postcode":"2590",
    "sg:province":"NSW",
    "sg:tags":[
        "battery",
        "automotive"
    ],
    "wof:name":"Country Batteries",
    "wof:placetype":"venue"
},
  "geometry": {"coordinates":[148.026412964,-34.6302642822],"type":"Point"}
}