{
  "type": "Feature",
  "properties": {
    "iso:country":"AU",
    "sg:address":"Unit 10,4 Garling Rd",
    "sg:city":"Kings Park",
    "sg:classifiers":[
        {
            "category":"Landmark",
            "subcategory":"Fountain",
            "type":"Public Place"
        }
    ],
    "sg:phone":"+61 2 9622 4264",
    "sg:postcode":"2148",
    "sg:province":"NSW",
    "sg:tags":[
        "wholesaler",
        "spring",
        "mfrs"
    ],
    "wof:name":"Specific Springs Pty Ltd",
    "wof:placetype":"venue"
},
  "geometry": {"coordinates":[150.91566467300001,-33.745880127],"type":"Point"}
}