{
  "type": "Feature",
  "properties": {
    "addr:full":"U1/ 25 Dale St Brookvale NSW 2100",
    "addr:housenumber":"25",
    "addr:postcode":"2100",
    "addr:street":"U1 /;Dale St",
    "iso:country":"AU",
    "sg:address":"U1/ 25 Dale St",
    "sg:city":"Brookvale",
    "sg:classifiers":[
        {
            "category":"Retail",
            "subcategory":"Auto Repair",
            "type":"Services"
        }
    ],
    "sg:phone":"+61 2 9905 1122",
    "sg:postcode":"2100",
    "sg:province":"NSW",
    "sg:tags":[
        "repairer",
        "motor",
        "engineer"
    ],
    "wof:name":"Peter Kramer Automotive",
    "wof:placetype":"venue"
},
  "geometry": {"coordinates":[151.26856994600001,-33.7651023865],"type":"Point"}
}