{
  "type": "Feature",
  "properties": {
    "addr:full":"92 Lincoln St Oxley QLD 4075",
    "addr:housenumber":"92",
    "addr:postcode":"4075",
    "addr:street":"Lincoln St",
    "iso:country":"AU",
    "sg:address":"92 Lincoln St",
    "sg:city":"Oxley",
    "sg:classifiers":[
        {
            "category":"Professional",
            "subcategory":"Employment Agencies",
            "type":"Services"
        }
    ],
    "sg:phone":"+61 7 3379 8932",
    "sg:postcode":"4075",
    "sg:province":"QLD",
    "wof:name":"Mission Australia",
    "wof:placetype":"venue"
},
  "geometry": {"coordinates":[152.97538757300001,-27.5530967712],"type":"Point"}
}