{
  "type": "Feature",
  "properties": {
    "addr:full":"157 Springvale Rd Nunawading VIC 3131",
    "addr:housenumber":"157",
    "addr:postcode":"3131",
    "addr:street":"Springvale Rd",
    "iso:country":"AU",
    "sg:address":"157 Springvale Rd",
    "sg:city":"Nunawading",
    "sg:classifiers":[
        {
            "category":"Building & Trades",
            "subcategory":"Locksmith",
            "type":"Services"
        }
    ],
    "sg:phone":"+61 3 9894 4053",
    "sg:postcode":"3131",
    "sg:province":"VIC",
    "sg:tags":[
        "lock"
    ],
    "wof:name":"Larners Blackburn Station Locksmith",
    "wof:placetype":"venue"
},
  "geometry": {"coordinates":[145.17604064899999,-37.8197479248],"type":"Point"}
}