{
  "type": "Feature",
  "properties": {
    "iso:country":"AU",
    "sg:address":"U2/ 28 Gympie Way",
    "sg:city":"Willetton",
    "sg:classifiers":[
        {
            "category":"Retail",
            "subcategory":"Repair Shop",
            "type":"Services"
        }
    ],
    "sg:phone":"+61 8 9354 4524",
    "sg:postcode":"6155",
    "sg:province":"WA",
    "sg:tags":[
        "upholsterer"
    ],
    "wof:name":"Southside Upholstery",
    "wof:placetype":"venue"
},
  "geometry": {"coordinates":[115.883461,-32.041264],"type":"Point"}
}