{
  "type": "Feature",
  "properties": {
    "addr:full":"Suite 3, 27- 29 Oxford Rd Ingleburn NSW 2565",
    "addr:housenumber":"27 29",
    "addr:postcode":"2565",
    "addr:street":"Oxford Rd",
    "iso:country":"AU",
    "sg:address":"Suite 3, 27- 29 Oxford Rd",
    "sg:city":"Ingleburn",
    "sg:classifiers":[
        {
            "category":"Professional",
            "subcategory":"Accounting & Tax Preparation",
            "type":"Services"
        }
    ],
    "sg:phone":"+61 2 9605 4777",
    "sg:postcode":"2565",
    "sg:province":"NSW",
    "sg:tags":[
        "accountant",
        "auditor"
    ],
    "wof:name":"A Schwartz & Co",
    "wof:placetype":"venue"
},
  "geometry": {"coordinates":[150.86685180699999,-33.9992675781],"type":"Point"}
}