{
  "type": "Feature",
  "properties": {
    "addr:full":"4 Delander Crs Moree NSW 2400",
    "addr:housenumber":"4",
    "addr:postcode":"2400",
    "addr:street":"Delander Crs",
    "iso:country":"AU",
    "sg:address":"4 Delander Crs",
    "sg:city":"Moree",
    "sg:classifiers":[
        {
            "category":"Building & Trades",
            "subcategory":"Landscaping Services",
            "type":"Services"
        }
    ],
    "sg:phone":"+61 2 6752 3051",
    "sg:postcode":"2400",
    "sg:province":"NSW",
    "sg:tags":[
        "fertilizer",
        "spreading",
        "insecticide"
    ],
    "wof:name":"W & T Bruce Growndstray Contractors",
    "wof:placetype":"venue"
},
  "geometry": {"coordinates":[149.841598511,-29.4661998749],"type":"Point"}
}