{
  "type": "Feature",
  "properties": {
    "iso:country":"AU",
    "sg:address":"25 Garner Pl",
    "sg:city":"Ingleba",
    "sg:classifiers":[
        {
            "category":"Transit Center",
            "subcategory":"Freight",
            "type":"Transportation"
        }
    ],
    "sg:phone":"+61 2 9618 6099",
    "sg:postcode":"2354",
    "sg:province":"NSW",
    "sg:tags":[
        "forklift",
        "truck"
    ],
    "wof:name":"A.W.D Equipment Sales",
    "wof:placetype":"venue"
},
  "geometry": {"coordinates":[151.44218444800001,-31.1732597351],"type":"Point"}
}