{
  "type": "Feature",
  "properties": {
    "addr:full":"Shop 4, Mountain Gate Shopping Centre Mo Ferntree Gully VIC 3156",
    "addr:housenumber":"shop 4",
    "addr:postcode":"3156",
    "addr:street":"Mountain Gate",
    "iso:country":"AU",
    "sg:address":"Shop 4, Mountain Gate Shopping Centre Mo",
    "sg:city":"Ferntree Gully",
    "sg:classifiers":[
        {
            "category":"Shopping",
            "subcategory":"Computers & Home Electronics",
            "type":"Retail Goods"
        }
    ],
    "sg:phone":"+61 3 9753 6882",
    "sg:postcode":"3156",
    "sg:province":"VIC",
    "sg:tags":[
        "hardware",
        "equipment"
    ],
    "wof:name":"Pacific Computers Pty Ltd",
    "wof:placetype":"venue"
},
  "geometry": {"coordinates":[145.27574157699999,-37.8847503662],"type":"Point"}
}