{
  "type": "Feature",
  "properties": {
    "addr:full":"40 Bunyala St Blakehurst NSW 2221",
    "addr:housenumber":"40",
    "addr:postcode":"2221",
    "addr:street":"Bunyala St",
    "iso:country":"AU",
    "sg:address":"40 Bunyala St",
    "sg:city":"Blakehurst",
    "sg:classifiers":[
        {
            "category":"Social Services",
            "subcategory":"Retirement Home",
            "type":"Services"
        }
    ],
    "sg:phone":"+61 2 9546 2897",
    "sg:postcode":"2221",
    "sg:province":"NSW",
    "sg:tags":[
        "village"
    ],
    "wof:name":"Bayside Park Retirement",
    "wof:placetype":"venue"
},
  "geometry": {"coordinates":[151.11349487300001,-33.9900627136],"type":"Point"}
}