{
  "type": "Feature",
  "properties": {
    "addr:full":"210 Kolara Boundary Rd Kolora VIC 3265",
    "addr:housenumber":"210",
    "addr:postcode":"3265",
    "addr:street":"Kolara Boundary Rd",
    "iso:country":"AU",
    "sg:address":"210 Kolara Boundary Rd",
    "sg:city":"Kolora",
    "sg:classifiers":[
        {
            "category":"Park",
            "subcategory":"County",
            "type":"Public Place"
        }
    ],
    "sg:phone":"+61 3 5592 7254",
    "sg:postcode":"3265",
    "sg:province":"VIC",
    "sg:tags":[
        "sanctuary",
        "zoos",
        "animal"
    ],
    "wof:name":"Veal K",
    "wof:placetype":"venue"
},
  "geometry": {"coordinates":[142.81304931599999,-38.0828666687],"type":"Point"}
}