{
  "type": "Feature",
  "properties": {
    "iso:country":"AU",
    "sg:address":"33 Louth Park Rd",
    "sg:city":"South Maitland",
    "sg:classifiers":[
        {
            "category":"Food & Beverages",
            "subcategory":"Supermarket",
            "type":"Retail Goods"
        }
    ],
    "sg:phone":"+61 2 4934 4122",
    "sg:postcode":"2320",
    "sg:province":"NSW",
    "sg:tags":[
        "grocery",
        "store"
    ],
    "wof:name":"Louth Park Corner Store",
    "wof:placetype":"venue"
},
  "geometry": {"coordinates":[151.56019592300001,-32.7432441711],"type":"Point"}
}