{
  "type": "Feature",
  "properties": {
    "addr:full":"102 Windmill St Tarragindi QLD 4121",
    "addr:housenumber":"102",
    "addr:postcode":"4121",
    "addr:street":"Windmill St",
    "iso:country":"AU",
    "sg:address":"102 Windmill St",
    "sg:city":"Tarragindi",
    "sg:classifiers":[
        {
            "category":"Food & Beverages",
            "subcategory":"Supermarket",
            "type":"Retail Goods"
        }
    ],
    "sg:phone":"+61 7 3848 7923",
    "sg:postcode":"4121",
    "sg:province":"QLD",
    "sg:tags":[
        "grocery",
        "store"
    ],
    "wof:name":"Four Square Stores (Qld) Ltd",
    "wof:placetype":"venue"
},
  "geometry": {"coordinates":[153.04216003400001,-27.5307216644],"type":"Point"}
}