{
  "type": "Feature",
  "properties": {
    "addr:full":"Lvl 5/ 340 Collins St Melbourne VIC 3000",
    "addr:housenumber":"/ 340",
    "addr:postcode":"3000",
    "addr:street":"Collins St",
    "iso:country":"AU",
    "sg:address":"Lvl 5/ 340 Collins St",
    "sg:city":"Melbourne",
    "sg:classifiers":[
        {
            "category":"Professional",
            "subcategory":"Detective & Security Services",
            "type":"Services"
        }
    ],
    "sg:phone":"+61 3 9670 5858",
    "sg:postcode":"3000",
    "sg:province":"VIC",
    "sg:tags":[
        "investigator"
    ],
    "wof:name":"A Charles Aaron Consultancy",
    "wof:placetype":"venue"
},
  "geometry": {"coordinates":[144.963088989,-37.8163528442],"type":"Point"}
}