{
  "type": "Feature",
  "properties": {
    "addr:full":"Level 3/ 5 Belmore Burwood NSW 2134",
    "addr:housenumber":"/ 5 belmore",
    "addr:postcode":"2134",
    "iso:country":"AU",
    "sg:address":"Level 3/ 5 Belmore",
    "sg:city":"Burwood",
    "sg:classifiers":[
        {
            "category":"Travel",
            "subcategory":"Travel Agent",
            "type":"Entertainment"
        }
    ],
    "sg:phone":"+61 2 9744 8344",
    "sg:postcode":"2134",
    "sg:province":"NSW",
    "sg:tags":[
        "consultant"
    ],
    "wof:name":"Burwood International Travel",
    "wof:placetype":"venue"
},
  "geometry": {"coordinates":[151.105957031,-33.8791046143],"type":"Point"}
}