{
  "type": "Feature",
  "properties": {
    "addr:full":"4 Conara Rd Kunda Park QLD 4556",
    "addr:housenumber":"4",
    "addr:postcode":"4556",
    "addr:street":"Conara Rd",
    "iso:country":"AU",
    "sg:address":"4 Conara Rd",
    "sg:city":"Kunda Park",
    "sg:classifiers":[
        {
            "category":"Structure",
            "subcategory":"Tunnel",
            "type":"Public Place"
        }
    ],
    "sg:phone":"+61 7 5477 1511",
    "sg:postcode":"4556",
    "sg:province":"QLD",
    "sg:tags":[
        "cleaner",
        "industrial",
        "vacuum"
    ],
    "wof:name":"Tensens Cleaning Equipment",
    "wof:placetype":"venue"
},
  "geometry": {"coordinates":[153.04142761200001,-26.6631889343],"type":"Point"}
}