{
  "type": "Feature",
  "properties": {
    "addr:full":"Shop 4 Griffin Plaza Griffith NSW 2680",
    "addr:housenumber":"shop 4",
    "addr:postcode":"2680",
    "addr:street":"Griffin Plaza",
    "iso:country":"AU",
    "sg:address":"Shop 4 Griffin Plaza",
    "sg:city":"Griffith",
    "sg:classifiers":[
        {
            "category":"Shopping",
            "subcategory":"Clothing, Apparel, & Fashions",
            "type":"Retail Goods"
        }
    ],
    "sg:phone":"+61 2 6964 5406",
    "sg:postcode":"2680",
    "sg:province":"NSW",
    "sg:tags":[
        "jean"
    ],
    "wof:name":"JeansWest",
    "wof:placetype":"venue"
},
  "geometry": {"coordinates":[146.03324900000001,-34.286346],"type":"Point"}
}