{
  "type": "Feature",
  "properties": {
    "addr:full":"384 Carrington St Hamilton Hill WA 6163",
    "addr:housenumber":"384",
    "addr:postcode":"6163",
    "addr:street":"Carrington St",
    "iso:country":"AU",
    "sg:address":"384 Carrington St",
    "sg:city":"Hamilton Hill",
    "sg:classifiers":[
        {
            "category":"Health Services",
            "subcategory":"Nursing And Care Facility",
            "type":"Services"
        }
    ],
    "sg:phone":"+61 8 9337 5994",
    "sg:postcode":"6163",
    "sg:province":"WA",
    "sg:tags":[
        "home"
    ],
    "wof:name":"Carrington Lodge",
    "wof:placetype":"venue"
},
  "geometry": {"coordinates":[115.776901,-32.085308],"type":"Point"}
}