{
  "type": "Feature",
  "properties": {
    "iso:country":"AU",
    "sg:address":"PO Box 104",
    "sg:city":"Belrose West",
    "sg:classifiers":[
        {
            "category":"Shopping",
            "subcategory":"Party Supplies",
            "type":"Retail Goods"
        }
    ],
    "sg:phone":"+61 2 8901 0434",
    "sg:postcode":"2085",
    "sg:province":"NSW",
    "sg:tags":[
        "children's"
    ],
    "wof:name":"Kids Party Stuff",
    "wof:placetype":"venue"
},
  "geometry": {"coordinates":[151.20327758799999,-33.7364196777],"type":"Point"}
}