{
  "type": "Feature",
  "properties": {
    "addr:full":"Ste1/ 210 Lower Heidelberg Rd Ivanhoe East VIC 3079",
    "addr:housenumber":"210",
    "addr:postcode":"3079",
    "addr:street":"Lower Heidelberg Rd",
    "iso:country":"AU",
    "sg:address":"Ste1/ 210 Lower Heidelberg Rd",
    "sg:city":"Ivanhoe East",
    "sg:classifiers":[
        {
            "category":"Personal",
            "subcategory":"Beauty Salon",
            "type":"Services"
        }
    ],
    "sg:phone":"+61 3 9499 1888",
    "sg:postcode":"3079",
    "sg:province":"VIC",
    "sg:tags":[
        "hairdresser"
    ],
    "wof:name":"Mary R Hair Design",
    "wof:placetype":"venue"
},
  "geometry": {"coordinates":[145.056884766,-37.7723617554],"type":"Point"}
}