{
  "type": "Feature",
  "properties": {
    "addr:full":"Brebner Drv West Lakes SA 5021",
    "addr:postcode":"5021",
    "addr:street":"Brebner Drv",
    "iso:country":"AU",
    "sg:address":"Brebner Drv",
    "sg:city":"West Lakes",
    "sg:classifiers":[
        {
            "category":"Government",
            "subcategory":"City Hall",
            "type":"Public Place"
        }
    ],
    "sg:phone":"+61 8 8408 1144",
    "sg:postcode":"5021",
    "sg:province":"SA",
    "wof:name":"West Lake Community Centre",
    "wof:placetype":"venue"
},
  "geometry": {"coordinates":[138.491744995,-34.8766365051],"type":"Point"}
}