{
  "type": "Feature",
  "properties": {
    "addr:full":"24a Marcus Rd Frankston South VIC 3199",
    "addr:housenumber":"24a",
    "addr:postcode":"3199",
    "addr:street":"Marcus Rd",
    "iso:country":"AU",
    "sg:address":"24a Marcus Rd",
    "sg:city":"Frankston South",
    "sg:classifiers":[
        {
            "category":"Professional",
            "subcategory":"Art Services",
            "type":"Services"
        }
    ],
    "sg:phone":"+61 3 9787 0635",
    "sg:postcode":"3199",
    "sg:province":"VIC",
    "sg:tags":[
        "graphic",
        "designer"
    ],
    "wof:name":"Doggone Productions",
    "wof:placetype":"venue"
},
  "geometry": {"coordinates":[145.117263794,-38.1665458679],"type":"Point"}
}