{
  "type": "Feature",
  "properties": {
    "iso:country":"AU",
    "sg:address":"27 Crompton Rd",
    "sg:city":"Rockingham",
    "sg:classifiers":[
        {
            "category":"Real Estate",
            "subcategory":"Real Estate Agent",
            "type":"Services"
        }
    ],
    "sg:phone":"+61 8 9528 5595",
    "sg:postcode":"6168",
    "sg:province":"WA",
    "sg:tags":[
        "handyman's",
        "equipment",
        "hire",
        "builders",
        "contractor"
    ],
    "wof:name":"Fab Quip Hire",
    "wof:placetype":"venue"
},
  "geometry": {"coordinates":[115.766968,-32.274837],"type":"Point"}
}