{
  "type": "Feature",
  "properties": {
    "addr:full":"Level 2, 552 Lonsdale St Melbourne VIC 3000",
    "addr:housenumber":"552",
    "addr:postcode":"3000",
    "addr:street":"Lonsdale St",
    "iso:country":"AU",
    "sg:address":"Level 2, 552 Lonsdale St",
    "sg:city":"Melbourne",
    "sg:classifiers":[
        {
            "category":"Banks & Credit Unions",
            "subcategory":"Financial Services",
            "type":"Services"
        }
    ],
    "sg:phone":"+61 3 9642 1266",
    "sg:postcode":"3000",
    "sg:province":"VIC",
    "sg:tags":[
        "advisory",
        "planning",
        "retirement"
    ],
    "sg:website":"http://www.investwellfp.com.au",
    "wof:name":"Investwell Financial Planning",
    "wof:placetype":"venue"
},
  "geometry": {"coordinates":[144.95587158199999,-37.8139877319],"type":"Point"}
}