{
  "type": "Feature",
  "properties": {
    "iso:country":"AU",
    "sg:address":"Unit 4 17 Railway Tce",
    "sg:city":"Wingfield",
    "sg:classifiers":[
        {
            "category":"Retail",
            "subcategory":"Auto Repair",
            "type":"Services"
        }
    ],
    "sg:phone":"+61 412 717 866",
    "sg:postcode":"5013",
    "sg:province":"SA",
    "sg:tags":[
        "car",
        "restoration",
        "supply"
    ],
    "wof:name":"S Gosti & Son Vehicle Restoration",
    "wof:placetype":"venue"
},
  "geometry": {"coordinates":[138.546951294,-34.840461731],"type":"Point"}
}