{
  "type": "Feature",
  "properties": {
    "addr:full":"Riverside Shopping Centre Maple St Maleny QLD 4552",
    "addr:postcode":"4552",
    "addr:street":"Maple St",
    "iso:country":"AU",
    "sg:address":"Riverside Shopping Centre Maple St",
    "sg:city":"Maleny",
    "sg:classifiers":[
        {
            "category":"Insurance",
            "subcategory":"Hazard Insurance",
            "type":"Services"
        }
    ],
    "sg:phone":"+61 13 11 75",
    "sg:postcode":"4552",
    "sg:province":"QLD",
    "sg:tags":[
        "fire",
        "accident",
        "marine"
    ],
    "wof:name":"Suncorp",
    "wof:placetype":"venue"
},
  "geometry": {"coordinates":[152.84934997600001,-26.7581157684],"type":"Point"}
}