{
  "type": "Feature",
  "properties": {
    "iso:country":"AU",
    "sg:address":"5 Malabar Crt",
    "sg:city":"Keysborough",
    "sg:classifiers":[
        {
            "category":"Education",
            "subcategory":"Dance Studio",
            "type":"Public Place"
        }
    ],
    "sg:phone":"+61 3 9798 7171",
    "sg:postcode":"3173",
    "sg:province":"VIC",
    "sg:tags":[
        "venue",
        "tuition"
    ],
    "wof:name":"Hesketh Russ",
    "wof:placetype":"venue"
},
  "geometry": {"coordinates":[145.16741943400001,-37.9880523682],"type":"Point"}
}