{
  "type": "Feature",
  "properties": {
    "iso:country":"AU",
    "sg:address":"25 Stockton Ave",
    "sg:city":"Moorebank",
    "sg:classifiers":[
        {
            "category":"Health Services",
            "subcategory":"Chiropractor",
            "type":"Services"
        }
    ],
    "sg:phone":"+61 2 9601 2714",
    "sg:postcode":"2170",
    "sg:province":"NSW",
    "wof:name":"Ruttle Corey",
    "wof:placetype":"venue"
},
  "geometry": {"coordinates":[150.948486328,-33.9318733215],"type":"Point"}
}