{
  "type": "Feature",
  "properties": {
    "addr:full":"Gateway Professional Suites 716 Main Rd Eltham VIC 3095",
    "addr:housenumber":"716",
    "addr:postcode":"3095",
    "addr:street":"Main Rd",
    "iso:country":"AU",
    "sg:address":"Gateway Professional Suites 716 Main Rd",
    "sg:city":"Eltham",
    "sg:classifiers":[
        {
            "category":"Personal",
            "subcategory":"Massage",
            "type":"Services"
        }
    ],
    "sg:phone":"+61 3 9431 2755",
    "sg:postcode":"3095",
    "sg:province":"VIC",
    "sg:tags":[
        "therapy"
    ],
    "wof:name":"Devenish Colin",
    "wof:placetype":"venue"
},
  "geometry": {"coordinates":[145.14588928200001,-37.7231636047],"type":"Point"}
}