{
  "type": "Feature",
  "properties": {
    "addr:full":"194 George St Quirindi NSW 2343",
    "addr:housenumber":"194",
    "addr:postcode":"2343",
    "addr:street":"George St",
    "iso:country":"AU",
    "sg:address":"194 George St",
    "sg:city":"Quirindi",
    "sg:classifiers":[
        {
            "category":"Shopping",
            "subcategory":"Department Store",
            "type":"Retail Goods"
        }
    ],
    "sg:phone":"+61 2 6746 1388",
    "sg:postcode":"2343",
    "sg:province":"NSW",
    "wof:name":"Rowntree Pty Ltd",
    "wof:placetype":"venue"
},
  "geometry": {"coordinates":[150.67904663100001,-31.5118217468],"type":"Point"}
}