{
  "type": "Feature",
  "properties": {
    "addr:full":"Unit 2, 3 Kitawah St Lonsdale SA 5160",
    "addr:housenumber":"3",
    "addr:postcode":"5160",
    "addr:street":"Kitawah St",
    "iso:country":"AU",
    "sg:address":"Unit 2, 3 Kitawah St",
    "sg:city":"Lonsdale",
    "sg:classifiers":[
        {
            "category":"Retail",
            "subcategory":"Auto Repair",
            "type":"Services"
        }
    ],
    "sg:phone":"+61 8 8384 8238",
    "sg:postcode":"5160",
    "sg:province":"SA",
    "sg:tags":[
        "camper-trailers",
        "caravan",
        "servicing"
    ],
    "wof:name":"12 Volt Powerhouse",
    "wof:placetype":"venue"
},
  "geometry": {"coordinates":[138.49705505399999,-35.1107788086],"type":"Point"}
}