{
  "type": "Feature",
  "properties": {
    "addr:full":"46a Brady Rd Dandenong North VIC 3175",
    "addr:housenumber":"46a",
    "addr:postcode":"3175",
    "addr:street":"Brady Rd",
    "iso:country":"AU",
    "sg:address":"46a Brady Rd",
    "sg:city":"Dandenong North",
    "sg:classifiers":[
        {
            "category":"Fast Food",
            "type":"Food & Drink"
        }
    ],
    "sg:phone":"+61 3 9795 0080",
    "sg:postcode":"3175",
    "sg:province":"VIC",
    "sg:tags":[
        "away",
        "take"
    ],
    "wof:name":"Brady Road Pizza",
    "wof:placetype":"venue"
},
  "geometry": {"coordinates":[145.212768555,-37.9541511536],"type":"Point"}
}