{
  "type": "Feature",
  "properties": {
    "addr:full":"6 Boyle St Sutherland NSW 2232",
    "addr:housenumber":"6",
    "addr:postcode":"2232",
    "addr:street":"Boyle St",
    "iso:country":"AU",
    "sg:address":"6 Boyle St",
    "sg:city":"Sutherland",
    "sg:classifiers":[
        {
            "category":"Shopping",
            "subcategory":"Pawn Shop",
            "type":"Retail Goods"
        }
    ],
    "sg:phone":"+61 2 9542 1096",
    "sg:postcode":"2232",
    "sg:province":"NSW",
    "sg:tags":[
        "pawnbroker"
    ],
    "wof:name":"Sutherland Loan Office",
    "wof:placetype":"venue"
},
  "geometry": {"coordinates":[151.05784606899999,-34.0329284668],"type":"Point"}
}