{
  "type": "Feature",
  "properties": {
    "addr:full":"Industrial Estate 4/ 21 Wanya Rd Tea Gardens NSW 2324",
    "addr:housenumber":"4 / 21",
    "addr:postcode":"2324",
    "addr:street":"Wanya Rd Tea Gardens",
    "iso:country":"AU",
    "sg:address":"Industrial Estate 4/ 21 Wanya Rd",
    "sg:city":"Tea Gardens",
    "sg:classifiers":[
        {
            "category":"Utilities",
            "subcategory":"Natural Gas",
            "type":"Services"
        }
    ],
    "sg:phone":"+61 418 499 750",
    "sg:postcode":"2324",
    "sg:province":"NSW",
    "sg:tags":[
        "supplier"
    ],
    "wof:name":"Tea Gardens Gas",
    "wof:placetype":"venue"
},
  "geometry": {"coordinates":[152.14468383799999,-32.6466217041],"type":"Point"}
}