{
  "type": "Feature",
  "properties": {
    "iso:country":"AU",
    "sg:address":"29 Whiting St",
    "sg:city":"Artarmon",
    "sg:classifiers":[
        {
            "category":"Wholesale",
            "subcategory":"Machinery & Supplies",
            "type":"Manufacturing & Wholesale Goods"
        }
    ],
    "sg:phone":"+61 2 9438 2311",
    "sg:postcode":"2064",
    "sg:province":"NSW",
    "sg:tags":[
        "bearing",
        "bushing"
    ],
    "wof:name":"CBC Australia (NSW) Pty Ltd",
    "wof:placetype":"venue"
},
  "geometry": {"coordinates":[151.18362426799999,-33.8148651123],"type":"Point"}
}