{
  "type": "Feature",
  "properties": {
    "iso:country":"AU",
    "sg:address":"Unit 3/ 17 Cavendish St",
    "sg:city":"Mittagong",
    "sg:classifiers":[
        {
            "category":"Health Services",
            "subcategory":"Doctor",
            "type":"Services"
        }
    ],
    "sg:phone":"+61 2 4872 4900",
    "sg:postcode":"2575",
    "sg:province":"NSW",
    "sg:tags":[
        "occupational",
        "safety"
    ],
    "wof:name":"Boots 'n All Workwear",
    "wof:placetype":"venue"
},
  "geometry": {"coordinates":[150.433670044,-34.4502372742],"type":"Point"}
}