{
  "type": "Feature",
  "properties": {
    "addr:full":"64 Kenneally Rd Mareeba QLD 4880",
    "addr:housenumber":"64",
    "addr:postcode":"4880",
    "addr:street":"Kenneally Rd",
    "iso:country":"AU",
    "sg:address":"64 Kenneally Rd",
    "sg:city":"Mareeba",
    "sg:classifiers":[
        {
            "category":"Building & Trades",
            "subcategory":"Construction",
            "type":"Services"
        }
    ],
    "sg:phone":"+61 7 4092 2781",
    "sg:postcode":"4880",
    "sg:province":"QLD",
    "sg:tags":[
        "earth",
        "excavating",
        "moving",
        "contractor"
    ],
    "wof:name":"Rains Joe & Co",
    "wof:placetype":"venue"
},
  "geometry": {"coordinates":[145.43179321299999,-17.015542984],"type":"Point"}
}