{
  "type": "Feature",
  "properties": {
    "addr:full":"25 Sale St Orange NSW 2800",
    "addr:housenumber":"25",
    "addr:postcode":"2800",
    "addr:street":"Sale St",
    "iso:country":"AU",
    "sg:address":"25 Sale St",
    "sg:city":"Orange",
    "sg:classifiers":[
        {
            "category":"Real Estate",
            "subcategory":"Real Estate Agent",
            "type":"Services"
        }
    ],
    "sg:phone":"+61 2 6362 1144",
    "sg:postcode":"2800",
    "sg:province":"NSW",
    "wof:name":"Fisher Peter & Co",
    "wof:placetype":"venue"
},
  "geometry": {"coordinates":[149.09576415999999,-33.28465271],"type":"Point"}
}