{
  "type": "Feature",
  "properties": {
    "iso:country":"AU",
    "sg:address":"Shop 9 Westfield Park Shopng Cntr",
    "sg:city":"Westfield",
    "sg:classifiers":[
        {
            "category":"Deli",
            "type":"Food & Drink"
        }
    ],
    "sg:phone":"+61 8 9390 7950",
    "sg:postcode":"6111",
    "sg:province":"WA",
    "sg:tags":[
        "delicatessen"
    ],
    "wof:name":"Joe's Westfield Deli",
    "wof:placetype":"venue"
},
  "geometry": {"coordinates":[116.01206970200001,-32.1104049683],"type":"Point"}
}