{
  "type": "Feature",
  "properties": {
    "addr:full":"426 William St West Melbourne VIC 3003",
    "addr:housenumber":"426",
    "addr:postcode":"3003",
    "addr:street":"William St",
    "iso:country":"AU",
    "sg:address":"426 William St",
    "sg:city":"West Melbourne",
    "sg:classifiers":[
        {
            "category":"Food & Beverages",
            "subcategory":"Liquor & Beverages",
            "type":"Retail Goods"
        }
    ],
    "sg:phone":"+61 3 9326 4985",
    "sg:postcode":"3003",
    "sg:province":"VIC",
    "sg:tags":[
        "store"
    ],
    "wof:name":"Flagstaff Cellars",
    "wof:placetype":"venue"
},
  "geometry": {"coordinates":[144.95481872600001,-37.8079299927],"type":"Point"}
}