{
  "type": "Feature",
  "properties": {
    "iso:country":"AU",
    "sg:address":"18 Glen St",
    "sg:city":"Eastwood",
    "sg:classifiers":[
        {
            "category":"Professional",
            "subcategory":"Printing & Photocopies",
            "type":"Services"
        }
    ],
    "sg:phone":"+61 2 9874 2212",
    "sg:postcode":"2122",
    "sg:province":"NSW",
    "sg:tags":[
        "photocopying"
    ],
    "wof:name":"Snap Printing",
    "wof:placetype":"venue"
},
  "geometry": {"coordinates":[151.07716369600001,-33.7910118103],"type":"Point"}
}