{
  "type": "Feature",
  "properties": {
    "iso:country":"AU",
    "sg:address":"43 Douglas Mawson Rd",
    "sg:city":"Dubbo",
    "sg:classifiers":[
        {
            "category":"Manufacturing",
            "subcategory":"Metals",
            "type":"Manufacturing & Wholesale Goods"
        }
    ],
    "sg:phone":"+61 2 6884 3007",
    "sg:postcode":"2830",
    "sg:province":"NSW",
    "sg:tags":[
        "sheet",
        "worker"
    ],
    "wof:name":"Ivers Air Conditioning",
    "wof:placetype":"venue"
},
  "geometry": {"coordinates":[148.63362121599999,-32.2473602295],"type":"Point"}
}