{
  "type": "Feature",
  "properties": {
    "addr:full":"2 Park St Mona Vale NSW 2103",
    "addr:housenumber":"2",
    "addr:postcode":"2103",
    "addr:street":"Park St",
    "iso:country":"AU",
    "sg:address":"2 Park St",
    "sg:city":"Mona Vale",
    "sg:classifiers":[
        {
            "category":"Food & Beverages",
            "subcategory":"Liquor & Beverages",
            "type":"Retail Goods"
        }
    ],
    "sg:phone":"+61 2 9999 4214",
    "sg:postcode":"2103",
    "sg:province":"NSW",
    "sg:tags":[
        "store"
    ],
    "wof:name":"Liquor Stax Australia Pty Ltd",
    "wof:placetype":"venue"
},
  "geometry": {"coordinates":[151.30569457999999,-33.6767196655],"type":"Point"}
}