{
  "type": "Feature",
  "properties": {
    "addr:full":"81 Hampton St Bridgetown WA 6255",
    "addr:housenumber":"81",
    "addr:postcode":"6255",
    "addr:street":"Hampton St",
    "iso:country":"AU",
    "sg:address":"81 Hampton St",
    "sg:city":"Bridgetown",
    "sg:classifiers":[
        {
            "category":"Communications",
            "subcategory":"News Services",
            "type":"Services"
        }
    ],
    "sg:phone":"+61 8 9761 1038",
    "sg:postcode":"6255",
    "sg:province":"WA",
    "sg:tags":[
        "information",
        "tourist",
        "attractions"
    ],
    "wof:name":"Bridgetown Pottery-Restaurant",
    "wof:placetype":"venue"
},
  "geometry": {"coordinates":[116.13703918500001,-33.9577980042],"type":"Point"}
}