{
  "type": "Feature",
  "properties": {
    "iso:country":"AU",
    "sg:address":"25 Iron St",
    "sg:city":"North Parramatta",
    "sg:classifiers":[
        {
            "category":"Health Services",
            "subcategory":"Doctor",
            "type":"Services"
        }
    ],
    "sg:phone":"+61 2 9630 2695",
    "sg:postcode":"2151",
    "sg:province":"NSW",
    "sg:tags":[
        "medical",
        "practitioner"
    ],
    "wof:name":"Loe Gary T T",
    "wof:placetype":"venue"
},
  "geometry": {"coordinates":[151.004837036,-33.7970809937],"type":"Point"}
}