{
  "type": "Feature",
  "properties": {
    "addr:full":"104 Alexander St Crows Nest NSW 2065",
    "addr:housenumber":"104",
    "addr:postcode":"2065",
    "addr:street":"Alexander St",
    "iso:country":"AU",
    "sg:address":"104 Alexander St",
    "sg:city":"Crows Nest",
    "sg:classifiers":[
        {
            "category":"Professional",
            "subcategory":"Computer Services",
            "type":"Services"
        }
    ],
    "sg:phone":"+61 2 9436 1702",
    "sg:postcode":"2065",
    "sg:province":"NSW",
    "sg:tags":[
        "training"
    ],
    "wof:name":"Knowledge Path",
    "wof:placetype":"venue"
},
  "geometry": {"coordinates":[151.202468872,-33.8246612549],"type":"Point"}
}