{
  "type": "Feature",
  "properties": {
    "addr:full":"41-43 Conness St Chiltern VIC 3683",
    "addr:housenumber":"41-43",
    "addr:postcode":"3683",
    "addr:street":"Conness St",
    "iso:country":"AU",
    "sg:address":"41-43 Conness St",
    "sg:city":"Chiltern",
    "sg:classifiers":[
        {
            "category":"Cafe",
            "type":"Food & Drink"
        }
    ],
    "sg:phone":"+61 3 5726 1540",
    "sg:postcode":"3683",
    "sg:province":"VIC",
    "wof:name":"Chiltern Cafe",
    "wof:placetype":"venue"
},
  "geometry": {"coordinates":[146.60876500000001,-36.151089],"type":"Point"}
}