{
  "type": "Feature",
  "properties": {
    "addr:full":"Shp 70 Hollywood Plz Shopng Cntr Salisbury Downs SA 5108",
    "addr:housenumber":"70",
    "addr:postcode":"5108",
    "addr:street":"Hollywood Plz Shopng Cntr",
    "iso:country":"AU",
    "sg:address":"Shp 70",
    "sg:city":"Hollywood Plz Shopng Cntr Salisbury Downs",
    "sg:classifiers":[
        {
            "category":"Travel",
            "subcategory":"Travel Agent",
            "type":"Entertainment"
        }
    ],
    "sg:phone":"+61 8 8285 2255",
    "sg:postcode":"5108",
    "sg:province":"SA",
    "sg:tags":[
        "consultant"
    ],
    "wof:name":"Harvey World Travel",
    "wof:placetype":"venue"
},
  "geometry": {"coordinates":[138.61895751899999,-34.7697105408],"type":"Point"}
}