{
  "type": "Feature",
  "properties": {
    "addr:full":"113 Connaught St Sandgate QLD 4017",
    "addr:housenumber":"113",
    "addr:postcode":"4017",
    "addr:street":"Connaught St",
    "iso:country":"AU",
    "sg:address":"113 Connaught St",
    "sg:city":"Sandgate",
    "sg:classifiers":[
        {
            "category":"Retail",
            "subcategory":"Auto Repair",
            "type":"Services"
        }
    ],
    "sg:phone":"+61 7 3269 3158",
    "sg:postcode":"4017",
    "sg:province":"QLD",
    "sg:tags":[
        "fuel",
        "petrol",
        "injection"
    ],
    "wof:name":"Todd McArthur",
    "wof:placetype":"venue"
},
  "geometry": {"coordinates":[153.05763244600001,-27.3185024261],"type":"Point"}
}