{
  "type": "Feature",
  "properties": {
    "addr:full":"Factory 2, 24- 26 Carride Drv Tullamarine VIC 3043",
    "addr:housenumber":"24 26",
    "addr:postcode":"3043",
    "addr:street":"Carride Drv",
    "iso:country":"AU",
    "sg:address":"Factory 2, 24- 26 Carride Drv",
    "sg:city":"Tullamarine",
    "sg:classifiers":[
        {
            "category":"Retail",
            "subcategory":"Auto Repair",
            "type":"Services"
        }
    ],
    "sg:phone":"+61 3 9338 0144",
    "sg:postcode":"3043",
    "sg:province":"VIC",
    "sg:tags":[
        "muffler",
        "exhaust",
        "system"
    ],
    "wof:name":"Metro Muffla Fit",
    "wof:placetype":"venue"
},
  "geometry": {"coordinates":[144.86845398,-37.7137413025],"type":"Point"}
}