{
  "type": "Feature",
  "properties": {
    "addr:full":"16 Grimshaw St Greensborough VIC 3088",
    "addr:housenumber":"16",
    "addr:postcode":"3088",
    "addr:street":"Grimshaw St",
    "iso:country":"AU",
    "sg:address":"16 Grimshaw St",
    "sg:city":"Greensborough",
    "sg:classifiers":[
        {
            "category":"Professional",
            "subcategory":"Accounting & Tax Preparation",
            "type":"Services"
        }
    ],
    "sg:phone":"+61 3 9432 9611",
    "sg:postcode":"3088",
    "sg:province":"VIC",
    "sg:tags":[
        "consultant",
        "taxation"
    ],
    "wof:name":"Forces Financial Services",
    "wof:placetype":"venue"
},
  "geometry": {"coordinates":[145.10708618199999,-37.7049407959],"type":"Point"}
}