{
  "type": "Feature",
  "properties": {
    "iso:country":"AU",
    "sg:address":"108 Arthur St",
    "sg:city":"Fairfield",
    "sg:classifiers":[
        {
            "category":"Building & Trades",
            "subcategory":"Construction",
            "type":"Services"
        }
    ],
    "sg:phone":"+61 418 322 905",
    "sg:postcode":"3078",
    "sg:province":"VIC",
    "sg:tags":[
        "joiner",
        "carpenter"
    ],
    "wof:name":"Sharpline Carpentry",
    "wof:placetype":"venue"
},
  "geometry": {"coordinates":[145.01954650900001,-37.776424408],"type":"Point"}
}