{
  "type": "Feature",
  "properties": {
    "addr:full":"U2/ 133 Keilor Rd Essendon VIC 3040",
    "addr:housenumber":"133",
    "addr:postcode":"3040",
    "addr:street":"U2 /;Keilor Rd",
    "iso:country":"AU",
    "sg:address":"U2/ 133 Keilor Rd",
    "sg:city":"Essendon",
    "sg:classifiers":[
        {
            "category":"Banks & Credit Unions",
            "subcategory":"Financial Services",
            "type":"Services"
        }
    ],
    "sg:phone":"+61 3 9374 8989",
    "sg:postcode":"3040",
    "sg:province":"VIC",
    "sg:tags":[
        "planning"
    ],
    "wof:name":"P.K. Chin Financial Services Pty Ltd",
    "wof:placetype":"venue"
},
  "geometry": {"coordinates":[144.901977539,-37.7410392761],"type":"Point"}
}