{
  "type": "Feature",
  "properties": {
    "iso:country":"AU",
    "sg:address":"Dolphin Drv",
    "sg:city":"Mandurah",
    "sg:classifiers":[
        {
            "category":"Recreation",
            "subcategory":"Boat Charter",
            "type":"Entertainment"
        }
    ],
    "sg:phone":"+61 8 9535 5399",
    "sg:postcode":"6210",
    "sg:province":"WA",
    "sg:tags":[
        "hire",
        "drive"
    ],
    "wof:name":"Blue Manna Boat Hire",
    "wof:placetype":"venue"
},
  "geometry": {"coordinates":[115.721619,-32.52285],"type":"Point"}
}