{
  "type": "Feature",
  "properties": {
    "addr:full":"Cnr Mulgrave Rd & Barr St Earlville QLD 4870",
    "addr:postcode":"4870",
    "addr:street":"Cnr Mulgrave Rd & Barr St",
    "iso:country":"AU",
    "sg:address":"Cnr Mulgrave Rd & Barr St",
    "sg:city":"Earlville",
    "sg:classifiers":[
        {
            "category":"Fast Food",
            "type":"Food & Drink"
        }
    ],
    "sg:phone":"+61 7 4033 1149",
    "sg:postcode":"4870",
    "sg:province":"QLD",
    "sg:tags":[
        "away",
        "take"
    ],
    "wof:name":"KFC",
    "wof:placetype":"venue"
},
  "geometry": {"coordinates":[145.73794555699999,-16.9455127716],"type":"Point"}
}