{
  "type": "Feature",
  "properties": {
    "iso:country":"AU",
    "sg:address":"29 Wests Rd",
    "sg:city":"Maribyrnong",
    "sg:classifiers":[
        {
            "category":"Health Services",
            "subcategory":"Chiropractor",
            "type":"Services"
        }
    ],
    "sg:phone":"+61 3 9318 7758",
    "sg:postcode":"3032",
    "sg:province":"VIC",
    "wof:name":"Malone Daniel Dr",
    "wof:placetype":"venue"
},
  "geometry": {"coordinates":[144.881348,-37.773083],"type":"Point"}
}