{
  "type": "Feature",
  "properties": {
    "addr:full":"Morgan Ave Seaview Downs SA 5049",
    "addr:postcode":"5049",
    "addr:street":"Morgan Ave",
    "iso:country":"AU",
    "sg:address":"Morgan Ave",
    "sg:city":"Seaview Downs",
    "sg:classifiers":[
        {
            "category":"Health Services",
            "subcategory":"Health Practitioner",
            "type":"Services"
        }
    ],
    "sg:phone":"+61 405 972 911",
    "sg:postcode":"5049",
    "sg:province":"SA",
    "sg:tags":[
        "alternative"
    ],
    "wof:name":"Leanne Hall Acupuncturist",
    "wof:placetype":"venue"
},
  "geometry": {"coordinates":[138.53727699999999,-35.036575],"type":"Point"}
}