{
  "type": "Feature",
  "properties": {
    "addr:full":"1108 Botany Rd Botany NSW 2019",
    "addr:housenumber":"1108",
    "addr:postcode":"2019",
    "addr:street":"Botany Rd",
    "iso:country":"AU",
    "sg:address":"1108 Botany Rd",
    "sg:city":"Botany",
    "sg:classifiers":[
        {
            "category":"Fast Food",
            "type":"Food & Drink"
        }
    ],
    "sg:phone":"+61 2 9316 5366",
    "sg:postcode":"2019",
    "sg:province":"NSW",
    "sg:tags":[
        "away",
        "take"
    ],
    "wof:name":"Botany Cantonese Take Away",
    "wof:placetype":"venue"
},
  "geometry": {"coordinates":[151.19606018100001,-33.9441833496],"type":"Point"}
}