{
  "type": "Feature",
  "properties": {
    "addr:full":"458 Pacific Hwy Wyong North NSW 2259",
    "addr:housenumber":"458",
    "addr:postcode":"2259",
    "addr:street":"Pacific Hwy",
    "iso:country":"AU",
    "sg:address":"458 Pacific Hwy",
    "sg:city":"Wyong North",
    "sg:classifiers":[
        {
            "category":"Shopping",
            "subcategory":"Discount & Variety Stores",
            "type":"Retail Goods"
        }
    ],
    "sg:phone":"+61 2 4351 5688",
    "sg:postcode":"2259",
    "sg:province":"NSW",
    "sg:tags":[
        "dangerous",
        "storage"
    ],
    "wof:name":"Storage Constructions Pty Ltd",
    "wof:placetype":"venue"
},
  "geometry": {"coordinates":[151.46051025400001,-33.2622489929],"type":"Point"}
}