{
  "type": "Feature",
  "properties": {
    "iso:country":"AU",
    "sg:address":"90 Aerodrome Rd",
    "sg:city":"Maroochydore",
    "sg:classifiers":[
        {
            "category":"Retail",
            "subcategory":"Auto Rental",
            "type":"Services"
        }
    ],
    "sg:phone":"+61 1800 063 743",
    "sg:postcode":"4558",
    "sg:province":"QLD",
    "sg:tags":[
        "car",
        "hire",
        "minibus"
    ],
    "sg:website":"http://www.car-rent.com.au",
    "wof:name":"? Price Car Rentals",
    "wof:placetype":"venue"
},
  "geometry": {"coordinates":[153.09645080600001,-26.6589202881],"type":"Point"}
}