{
  "type": "Feature",
  "properties": {
    "addr:full":"2 Yorkminster Ave Wantirna VIC 3152",
    "addr:housenumber":"2",
    "addr:postcode":"3152",
    "addr:street":"Yorkminster Ave",
    "iso:country":"AU",
    "sg:address":"2 Yorkminster Ave",
    "sg:city":"Wantirna",
    "sg:classifiers":[
        {
            "category":"Health Services",
            "subcategory":"Doctor",
            "type":"Services"
        }
    ],
    "sg:phone":"+61 3 9801 2846",
    "sg:postcode":"3152",
    "sg:province":"VIC",
    "sg:tags":[
        "medical",
        "practitioner"
    ],
    "wof:name":"Clark J V T",
    "wof:placetype":"venue"
},
  "geometry": {"coordinates":[145.23379516599999,-37.8498840332],"type":"Point"}
}