{
  "type": "Feature",
  "properties": {
    "iso:country":"AU",
    "sg:address":"Shop 4, 338 Camden Valley Hwy",
    "sg:city":"Narellan",
    "sg:classifiers":[
        {
            "category":"Shopping",
            "subcategory":"Clothing, Apparel, & Fashions",
            "type":"Retail Goods"
        }
    ],
    "sg:phone":"+61 2 4647 5977",
    "sg:postcode":"2567",
    "sg:province":"NSW",
    "sg:tags":[
        "hire",
        "men's",
        "wear",
        "formal"
    ],
    "wof:name":"Spurling Bridal & Formalwear",
    "wof:placetype":"venue"
},
  "geometry": {"coordinates":[150.73765564000001,-34.0401344299],"type":"Point"}
}