{
  "type": "Feature",
  "properties": {
    "iso:country":"AU",
    "sg:address":"Factory 5/ 40 Edina Rd",
    "sg:city":"Ferntree Gully",
    "sg:classifiers":[
        {
            "category":"Retail",
            "subcategory":"Auto Repair",
            "type":"Services"
        }
    ],
    "sg:phone":"+61 3 9752 2446",
    "sg:postcode":"3156",
    "sg:province":"VIC",
    "sg:tags":[
        "repairer",
        "motor",
        "engineer"
    ],
    "wof:name":"L.S.C. Motor Repairers Pty Ltd",
    "wof:placetype":"venue"
},
  "geometry": {"coordinates":[145.28070068400001,-37.8748588562],"type":"Point"}
}