{
  "type": "Feature",
  "properties": {
    "addr:full":"59 Potts Rd Langwarrin VIC 3910",
    "addr:housenumber":"59",
    "addr:postcode":"3910",
    "addr:street":"Potts Rd",
    "iso:country":"AU",
    "sg:address":"59 Potts Rd",
    "sg:city":"Langwarrin",
    "sg:classifiers":[
        {
            "category":"Home & Garden",
            "subcategory":"Carpets & Floor Coverings",
            "type":"Retail Goods"
        }
    ],
    "sg:phone":"+61 3 9775 8653",
    "sg:postcode":"3910",
    "sg:province":"VIC",
    "sg:tags":[
        "tile",
        "wall",
        "layer"
    ],
    "wof:name":"G.D. & P.A. Moran Tiling",
    "wof:placetype":"venue"
},
  "geometry": {"coordinates":[145.210006714,-38.1368942261],"type":"Point"}
}