{
  "type": "Feature",
  "properties": {
    "iso:country":"AU",
    "sg:address":"9 Hardware St",
    "sg:city":"Melbourne",
    "sg:classifiers":[
        {
            "category":"Shopping",
            "subcategory":"Bicycles & Sporting Goods",
            "type":"Retail Goods"
        }
    ],
    "sg:phone":"+61 3 9670 1767",
    "sg:postcode":"3000",
    "sg:province":"VIC",
    "sg:tags":[
        "water",
        "equipment",
        "skiing"
    ],
    "wof:name":"Auski Sales Pty Ltd",
    "wof:placetype":"venue"
},
  "geometry": {"coordinates":[144.96058654800001,-37.812210083],"type":"Point"}
}