{
  "type": "Feature",
  "properties": {
    "iso:country":"AU",
    "sg:address":"K10 Morayfield Shopping Centre, 171 Morayfield Road",
    "sg:city":"Morayfield",
    "sg:classifiers":[
        {
            "category":"Shopping",
            "subcategory":"Mobile Phones",
            "type":"Retail Goods"
        }
    ],
    "sg:phone":"+61 7 5498 9555",
    "sg:postcode":"4506",
    "sg:province":"QLD",
    "sg:tags":[
        "telephone",
        "accessory"
    ],
    "wof:name":"Allphones",
    "wof:placetype":"venue"
},
  "geometry": {"coordinates":[152.95074462900001,-27.111328125],"type":"Point"}
}