{
  "type": "Feature",
  "properties": {
    "addr:full":"51a Copeland Rd Beecroft NSW 2119",
    "addr:housenumber":"51a",
    "addr:postcode":"2119",
    "addr:street":"Copeland Rd",
    "iso:country":"AU",
    "sg:address":"51a Copeland Rd",
    "sg:city":"Beecroft",
    "sg:classifiers":[
        {
            "category":"Professional",
            "subcategory":"Computer Services",
            "type":"Services"
        }
    ],
    "sg:phone":"+61 2 9484 3668",
    "sg:postcode":"2119",
    "sg:province":"NSW",
    "sg:tags":[
        "repairs",
        "upgrade",
        "equipment"
    ],
    "wof:name":"Mystar Computers",
    "wof:placetype":"venue"
},
  "geometry": {"coordinates":[151.05323791500001,-33.7529830933],"type":"Point"}
}