{
  "type": "Feature",
  "properties": {
    "addr:full":"3/ 106 Aerodrome Rd Maroochydore QLD 4558",
    "addr:housenumber":"/ 106",
    "addr:postcode":"4558",
    "addr:street":"Aerodrome Rd",
    "iso:country":"AU",
    "sg:address":"3/ 106 Aerodrome Rd",
    "sg:city":"Maroochydore",
    "sg:classifiers":[
        {
            "category":"Retail",
            "subcategory":"Auto Repair",
            "type":"Services"
        }
    ],
    "sg:phone":"+61 7 5452 7666",
    "sg:postcode":"4558",
    "sg:province":"QLD",
    "sg:tags":[
        "repairer",
        "motor",
        "engineer"
    ],
    "wof:name":"National Automotive Electrical & Mechanical",
    "wof:placetype":"venue"
},
  "geometry": {"coordinates":[153.09515380900001,-26.6582012177],"type":"Point"}
}