{
  "type": "Feature",
  "properties": {
    "iso:country":"AU",
    "sg:address":"448 Burwood Hwy",
    "sg:city":"Wantirna South",
    "sg:classifiers":[
        {
            "category":"Personal",
            "subcategory":"Beauty Salon",
            "type":"Services"
        }
    ],
    "sg:phone":"+61 3 9801 6757",
    "sg:postcode":"3152",
    "sg:province":"VIC",
    "sg:tags":[
        "hairdresser"
    ],
    "wof:name":"Scruples Hair & Beauty",
    "wof:placetype":"venue"
},
  "geometry": {"coordinates":[145.23887634299999,-37.8705062866],"type":"Point"}
}