{
  "type": "Feature",
  "properties": {
    "iso:country":"AU",
    "sg:address":"13- 15",
    "sg:city":"Carrington Cct Leumeah",
    "sg:classifiers":[
        {
            "category":"Social Services",
            "subcategory":"Child Care",
            "type":"Services"
        }
    ],
    "sg:phone":"+61 2 4625 9940",
    "sg:postcode":"2560",
    "sg:province":"NSW",
    "wof:name":"Leumeah Pre-School Kindergarten",
    "wof:placetype":"venue"
},
  "geometry": {"coordinates":[150.83691406200001,-34.0580291748],"type":"Point"}
}