{
  "type": "Feature",
  "properties": {
    "addr:full":"62 Dawson St Brunswick VIC 3056",
    "addr:housenumber":"62",
    "addr:postcode":"3056",
    "addr:street":"Dawson St",
    "iso:country":"AU",
    "sg:address":"62 Dawson St",
    "sg:city":"Brunswick",
    "sg:classifiers":[
        {
            "category":"Manufacturing",
            "subcategory":"Paper Products",
            "type":"Manufacturing & Wholesale Goods"
        }
    ],
    "sg:phone":"+61 3 9380 9867",
    "sg:postcode":"3056",
    "sg:province":"VIC",
    "sg:tags":[
        "box",
        "fibre",
        "carton",
        "cardboard"
    ],
    "wof:name":"Litho Superpak Pty Ltd",
    "wof:placetype":"venue"
},
  "geometry": {"coordinates":[144.957199097,-37.7699623108],"type":"Point"}
}