{
  "type": "Feature",
  "properties": {
    "iso:country":"AU",
    "sg:address":"100 Pearson Rd",
    "sg:city":"Yatala",
    "sg:classifiers":[
        {
            "category":"Autos & Motor Vehicles",
            "subcategory":"Automobile Sales",
            "type":"Retail Goods"
        }
    ],
    "sg:phone":"+61 7 3807 6311",
    "sg:postcode":"4207",
    "sg:province":"QLD",
    "sg:tags":[
        "equipment",
        "trailer"
    ],
    "wof:name":"Mate Transport Equipment",
    "wof:placetype":"venue"
},
  "geometry": {"coordinates":[153.19435119600001,-27.7119293213],"type":"Point"}
}