{
  "type": "Feature",
  "properties": {
    "iso:country":"AU",
    "sg:address":"6491 Lyell Higway Hwy",
    "sg:city":"Ouse",
    "sg:classifiers":[
        {
            "category":"Food & Beverages",
            "subcategory":"Supermarket",
            "type":"Retail Goods"
        }
    ],
    "sg:phone":"+61 3 6287 1205",
    "sg:postcode":"7140",
    "sg:province":"TAS",
    "sg:tags":[
        "grocery",
        "store"
    ],
    "wof:name":"Ouse Value Plus",
    "wof:placetype":"venue"
},
  "geometry": {"coordinates":[146.666595,-42.443531],"type":"Point"}
}