{
  "type": "Feature",
  "properties": {
    "iso:country":"AU",
    "sg:address":"35 Lusher Rd",
    "sg:city":"Croydon",
    "sg:classifiers":[
        {
            "category":"Retail",
            "subcategory":"Storage",
            "type":"Services"
        }
    ],
    "sg:phone":"+61 3 9723 0000",
    "sg:postcode":"3136",
    "sg:province":"VIC",
    "sg:tags":[
        "removal",
        "furniture"
    ],
    "wof:name":"AAA Rock Self Storage",
    "wof:placetype":"venue"
},
  "geometry": {"coordinates":[145.278533936,-37.8034248352],"type":"Point"}
}