{
  "type": "Feature",
  "properties": {
    "addr:full":"10 Railway La Cowra NSW 2794",
    "addr:housenumber":"10",
    "addr:postcode":"2794",
    "addr:street":"Railway La",
    "iso:country":"AU",
    "sg:address":"10 Railway La",
    "sg:city":"Cowra",
    "sg:classifiers":[
        {
            "category":"Food & Beverages",
            "subcategory":"Liquor & Beverages",
            "type":"Retail Goods"
        }
    ],
    "sg:phone":"+61 2 6341 1925",
    "sg:postcode":"2794",
    "sg:province":"NSW",
    "sg:tags":[
        "store"
    ],
    "wof:name":"Cellarbrations",
    "wof:placetype":"venue"
},
  "geometry": {"coordinates":[148.69140625,-33.8355712891],"type":"Point"}
}