{
  "type": "Feature",
  "properties": {
    "iso:country":"AU",
    "sg:address":"107 Regent St",
    "sg:city":"Preston West",
    "sg:classifiers":[
        {
            "category":"Health Services",
            "subcategory":"Doctor",
            "type":"Services"
        }
    ],
    "sg:phone":"+61 3 9470 2493",
    "sg:postcode":"3072",
    "sg:province":"VIC",
    "sg:tags":[
        "medical",
        "practitioner"
    ],
    "wof:name":"Regent Medical Group",
    "wof:placetype":"venue"
},
  "geometry": {"coordinates":[144.99380493199999,-37.7296905518],"type":"Point"}
}