{
  "type": "Feature",
  "properties": {
    "addr:full":"Shop 1 / 50 - 52 Spit Rd Mosman NSW 2088",
    "addr:housenumber":"shop 1 / 50 52",
    "addr:postcode":"2088",
    "addr:street":"Spit Rd",
    "iso:country":"AU",
    "sg:address":"Shop 1 / 50 - 52 Spit Rd",
    "sg:city":"Mosman",
    "sg:classifiers":[
        {
            "category":"Personal",
            "subcategory":"Beauty Salon",
            "type":"Services"
        }
    ],
    "sg:phone":"+61 2 9960 4994",
    "sg:postcode":"2088",
    "sg:province":"NSW",
    "sg:tags":[
        "hairdresser"
    ],
    "sg:website":"http://www.hairfidelity.com.au",
    "wof:name":"Hair Fidelity",
    "wof:placetype":"venue"
},
  "geometry": {"coordinates":[151.24217224099999,-33.8234977722],"type":"Point"}
}