{
  "type": "Feature",
  "properties": {
    "addr:full":"17 Woolley St Dickson ACT 2602",
    "addr:housenumber":"17",
    "addr:postcode":"2602",
    "addr:street":"Woolley St",
    "iso:country":"AU",
    "sg:address":"17 Woolley St",
    "sg:city":"Dickson",
    "sg:classifiers":[
        {
            "category":"Education",
            "subcategory":"Special Training",
            "type":"Public Place"
        }
    ],
    "sg:phone":"+61 2 6249 1099",
    "sg:postcode":"2602",
    "sg:province":"ACT",
    "sg:tags":[
        "development"
    ],
    "wof:name":"Workwatch Training Centre",
    "wof:placetype":"venue"
},
  "geometry": {"coordinates":[149.136428833,-35.2507133484],"type":"Point"}
}