{
  "type": "Feature",
  "properties": {
    "addr:full":"2 Wattle Crt Epsom VIC 3551",
    "addr:housenumber":"2",
    "addr:postcode":"3551",
    "addr:street":"Wattle Crt",
    "iso:country":"AU",
    "sg:address":"2 Wattle Crt",
    "sg:city":"Epsom",
    "sg:classifiers":[
        {
            "category":"Education",
            "subcategory":"Special Training",
            "type":"Public Place"
        }
    ],
    "sg:phone":"+61 3 5448 3166",
    "sg:postcode":"3551",
    "sg:province":"VIC",
    "sg:tags":[
        "drama",
        "tuition"
    ],
    "wof:name":"Drama Academy, Helen O'Grady Childrens",
    "wof:placetype":"venue"
},
  "geometry": {"coordinates":[144.308303833,-36.7057418823],"type":"Point"}
}