{
  "type": "Feature",
  "properties": {
    "iso:country":"AU",
    "sg:address":"26 Park St",
    "sg:city":"West Wyalong",
    "sg:classifiers":[
        {
            "category":"Professional",
            "subcategory":"Accounting & Tax Preparation",
            "type":"Services"
        }
    ],
    "sg:phone":"+61 2 6972 1006",
    "sg:postcode":"2671",
    "sg:province":"NSW",
    "sg:tags":[
        "bookkeeping"
    ],
    "wof:name":"Kwality Business Services",
    "wof:placetype":"venue"
},
  "geometry": {"coordinates":[147.19973754899999,-33.9212112427],"type":"Point"}
}