{
  "type": "Feature",
  "properties": {
    "addr:full":"Banksia St Bellfield VIC 3081",
    "addr:postcode":"3081",
    "addr:street":"St",
    "iso:country":"AU",
    "sg:address":"Banksia St",
    "sg:city":"Bellfield",
    "sg:classifiers":[
        {
            "category":"Education",
            "subcategory":"School",
            "type":"Public Place"
        }
    ],
    "sg:phone":"+61 3 9499 5172",
    "sg:postcode":"3081",
    "sg:province":"VIC",
    "sg:tags":[
        "state",
        "except",
        "nsw"
    ],
    "wof:name":"Banksia La Trobe Secondary College Deaf Facility",
    "wof:placetype":"venue"
},
  "geometry": {"coordinates":[145.03709411599999,-37.7562942505],"type":"Point"}
}