{
  "type": "Feature",
  "properties": {
    "iso:country":"AU",
    "sg:address":"10/ 838 Old Princes Hwy",
    "sg:city":"Sutherland",
    "sg:classifiers":[
        {
            "category":"Real Estate",
            "subcategory":"Real Estate Services",
            "type":"Services"
        }
    ],
    "sg:phone":"+61 2 9521 4644",
    "sg:postcode":"2232",
    "sg:province":"NSW",
    "sg:tags":[
        "valuer"
    ],
    "wof:name":"Watkins Mick",
    "wof:placetype":"venue"
},
  "geometry": {"coordinates":[151.05659484899999,-34.0335006714],"type":"Point"}
}