{
  "type": "Feature",
  "properties": {
    "addr:full":"17 Rex Rd Georges Hall NSW 2198",
    "addr:housenumber":"17",
    "addr:postcode":"2198",
    "addr:street":"Rex Rd Georges Hall",
    "iso:country":"AU",
    "sg:address":"17 Rex Rd",
    "sg:city":"Georges Hall",
    "sg:classifiers":[
        {
            "category":"Building & Trades",
            "subcategory":"Construction",
            "type":"Services"
        }
    ],
    "sg:phone":"+61 2 9644 1440",
    "sg:postcode":"2198",
    "sg:province":"NSW",
    "sg:tags":[
        "contractor"
    ],
    "wof:name":"Robertson T J",
    "wof:placetype":"venue"
},
  "geometry": {"coordinates":[150.98599200000001,-33.910194],"type":"Point"}
}