{
  "type": "Feature",
  "properties": {
    "addr:full":"78-82 Macleod St Bairnsdale VIC 3875",
    "addr:housenumber":"78-82",
    "addr:postcode":"3875",
    "addr:street":"Macleod St",
    "iso:country":"AU",
    "sg:address":"78-82 Macleod St",
    "sg:city":"Bairnsdale",
    "sg:classifiers":[
        {
            "category":"Home & Garden",
            "subcategory":"Garden Supply",
            "type":"Retail Goods"
        }
    ],
    "sg:phone":"+61 3 5152 3833",
    "sg:postcode":"3875",
    "sg:province":"VIC",
    "sg:tags":[
        "equipment"
    ],
    "wof:name":"Schmidt's Mower & Chainsaw Service",
    "wof:placetype":"venue"
},
  "geometry": {"coordinates":[147.631134033,-37.8272361755],"type":"Point"}
}