{
  "type": "Feature",
  "properties": {
    "iso:country":"AU",
    "sg:address":"Shp18a/ 33 Hutchinson St",
    "sg:city":"Lilydale",
    "sg:classifiers":[
        {
            "category":"Shopping",
            "subcategory":"Clothing, Apparel, & Fashions",
            "type":"Retail Goods"
        }
    ],
    "sg:phone":"+61 3 9735 1988",
    "sg:postcode":"3140",
    "sg:province":"VIC",
    "sg:tags":[
        "lady",
        "wear"
    ],
    "wof:name":"Lilydale Carisma Boutique",
    "wof:placetype":"venue"
},
  "geometry": {"coordinates":[145.347579956,-37.7595787048],"type":"Point"}
}