{
  "type": "Feature",
  "properties": {
    "addr:full":"126 St Kilda Rd St Kilda VIC 3182",
    "addr:housenumber":"126",
    "addr:postcode":"3182",
    "addr:street":"St Kilda Rd",
    "iso:country":"AU",
    "sg:address":"126 St Kilda Rd",
    "sg:city":"St Kilda",
    "sg:classifiers":[
        {
            "category":"Shopping",
            "subcategory":"Mobile Phones",
            "type":"Retail Goods"
        }
    ],
    "sg:phone":"+61 3 9525 3828",
    "sg:postcode":"3182",
    "sg:province":"VIC",
    "sg:tags":[
        "telephone",
        "accessory"
    ],
    "wof:name":"Optus World St.Kilda",
    "wof:placetype":"venue"
},
  "geometry": {"coordinates":[144.98440551799999,-37.8597259521],"type":"Point"}
}