{
  "type": "Feature",
  "properties": {
    "addr:full":"Cnr Warrandyte & Loughnan Rds Ringwood VIC 3134",
    "addr:postcode":"3134",
    "addr:street":"Cnr",
    "iso:country":"AU",
    "sg:address":"Cnr Warrandyte & Loughnan Rds",
    "sg:city":"Ringwood",
    "sg:classifiers":[
        {
            "category":"Food & Beverages",
            "subcategory":"Supermarket",
            "type":"Retail Goods"
        }
    ],
    "sg:phone":"+61 3 9879 5522",
    "sg:postcode":"3134",
    "sg:province":"VIC",
    "sg:tags":[
        "grocery",
        "store"
    ],
    "wof:name":"Quix Food Stores",
    "wof:placetype":"venue"
},
  "geometry": {"coordinates":[145.23088073700001,-37.8144378662],"type":"Point"}
}