{
  "type": "Feature",
  "properties": {
    "addr:full":"3 A, 81 Saints Rd Salisbury Plain SA 5109",
    "addr:housenumber":"3 a 81",
    "addr:postcode":"5109",
    "addr:street":"Saints Rd",
    "iso:country":"AU",
    "sg:address":"3 A, 81 Saints Rd",
    "sg:city":"Salisbury Plain",
    "sg:classifiers":[
        {
            "category":"Professional",
            "subcategory":"Detective & Security Services",
            "type":"Services"
        }
    ],
    "sg:phone":"+61 8 8285 1000",
    "sg:postcode":"5109",
    "sg:province":"SA",
    "sg:tags":[
        "equipment",
        "window",
        "doors"
    ],
    "wof:name":"Aluminium Plus",
    "wof:placetype":"venue"
},
  "geometry": {"coordinates":[138.667114258,-34.764919281],"type":"Point"}
}