{
  "type": "Feature",
  "properties": {
    "addr:full":"52 Smith St Warragul VIC 3820",
    "addr:housenumber":"52",
    "addr:postcode":"3820",
    "addr:street":"Smith St",
    "iso:country":"AU",
    "sg:address":"52 Smith St",
    "sg:city":"Warragul",
    "sg:classifiers":[
        {
            "category":"Shopping",
            "subcategory":"Jewelry",
            "type":"Retail Goods"
        }
    ],
    "sg:phone":"+61 3 5623 2741",
    "sg:postcode":"3820",
    "sg:province":"VIC",
    "sg:tags":[
        "jeweller"
    ],
    "wof:name":"Showcase Jewellers",
    "wof:placetype":"venue"
},
  "geometry": {"coordinates":[145.931625,-38.162033],"type":"Point"}
}