{
  "type": "Feature",
  "properties": {
    "addr:full":"72 Oatley Crt Belconnen ACT 2617",
    "addr:housenumber":"72",
    "addr:postcode":"2617",
    "addr:street":"Oatley Crt",
    "iso:country":"AU",
    "sg:address":"72 Oatley Crt",
    "sg:city":"Belconnen",
    "sg:classifiers":[
        {
            "category":"Sports & Exercise",
            "subcategory":"Ski Slope",
            "type":"Entertainment"
        }
    ],
    "sg:phone":"+61 2 6253 1178",
    "sg:postcode":"2617",
    "sg:province":"ACT",
    "sg:tags":[
        "equipment",
        "hire",
        "retail",
        "snow"
    ],
    "wof:name":"Phat Ski & Board",
    "wof:placetype":"venue"
},
  "geometry": {"coordinates":[149.058395386,-35.2424507141],"type":"Point"}
}