{
  "type": "Feature",
  "properties": {
    "iso:country":"AU",
    "sg:address":"17 Clanalpine St",
    "sg:city":"Mosman",
    "sg:classifiers":[
        {
            "category":"Health Services",
            "subcategory":"Nursing And Care Facility",
            "type":"Services"
        }
    ],
    "sg:phone":"+61 2 9960 7555",
    "sg:postcode":"2088",
    "sg:province":"NSW",
    "sg:tags":[
        "home"
    ],
    "wof:name":"Villiers Nursing Home",
    "wof:placetype":"venue"
},
  "geometry": {"coordinates":[151.23733520499999,-33.8377838135],"type":"Point"}
}