{
  "type": "Feature",
  "properties": {
    "addr:full":"ANA Hotel Cumberland St The Rocks NSW 2000",
    "addr:postcode":"2000",
    "addr:street":"Cumberland St",
    "iso:country":"AU",
    "sg:address":"ANA Hotel Cumberland St",
    "sg:city":"The Rocks",
    "sg:classifiers":[
        {
            "category":"Personal",
            "subcategory":"Massage",
            "type":"Services"
        }
    ],
    "sg:phone":"+61 2 9250 6033",
    "sg:postcode":"2000",
    "sg:province":"NSW",
    "sg:tags":[
        "therapy"
    ],
    "wof:name":"Hands Oz Therapeutic Bodywork",
    "wof:placetype":"venue"
},
  "geometry": {"coordinates":[151.20780944800001,-33.8574371338],"type":"Point"}
}