{
  "type": "Feature",
  "properties": {
    "iso:country":"AU",
    "sg:address":"31 Union St",
    "sg:city":"Cooks Hill",
    "sg:classifiers":[
        {
            "category":"Food & Beverages",
            "subcategory":"Bakery",
            "type":"Retail Goods"
        }
    ],
    "sg:phone":"+61 2 4929 3544",
    "sg:postcode":"2300",
    "sg:province":"NSW",
    "sg:tags":[
        "cake",
        "shop",
        "pastry"
    ],
    "wof:name":"T & P's Firestation Pie Shop",
    "wof:placetype":"venue"
},
  "geometry": {"coordinates":[151.766846,-32.929646],"type":"Point"}
}