{
  "type": "Feature",
  "properties": {
    "iso:country":"AU",
    "sg:address":"45 Scott St",
    "sg:city":"Ballarat",
    "sg:classifiers":[
        {
            "category":"Professional",
            "subcategory":"Art Services",
            "type":"Services"
        }
    ],
    "sg:phone":"+61 3 5331 1577",
    "sg:postcode":"3350",
    "sg:province":"VIC",
    "sg:tags":[
        "interior",
        "decorator"
    ],
    "wof:name":"Cindy Jones Interiors",
    "wof:placetype":"venue"
},
  "geometry": {"coordinates":[143.849411,-37.559078],"type":"Point"}
}