{
  "type": "Feature",
  "properties": {
    "addr:full":"16/ 486 Waterworks Rd Ashgrove QLD 4060",
    "addr:housenumber":"16 / 486",
    "addr:postcode":"4060",
    "addr:street":"Waterworks Rd",
    "iso:country":"AU",
    "sg:address":"16/ 486 Waterworks Rd",
    "sg:city":"Ashgrove",
    "sg:classifiers":[
        {
            "category":"Personal",
            "subcategory":"Massage",
            "type":"Services"
        }
    ],
    "sg:phone":"+61 7 3366 5899",
    "sg:postcode":"4060",
    "sg:province":"QLD",
    "sg:tags":[
        "therapy"
    ],
    "wof:name":"Sports Injuries-Ashgrove",
    "wof:placetype":"venue"
},
  "geometry": {"coordinates":[152.97793579099999,-27.4492511749],"type":"Point"}
}