{
  "type": "Feature",
  "properties": {
    "addr:full":"Lvl 1/ 382 Queens Pde Clifton Hill VIC 3068",
    "addr:housenumber":"/ 382",
    "addr:postcode":"3068",
    "addr:street":"Queens Pde",
    "iso:country":"AU",
    "sg:address":"Lvl 1/ 382 Queens Pde",
    "sg:city":"Clifton Hill",
    "sg:classifiers":[
        {
            "category":"Real Estate",
            "subcategory":"Architect",
            "type":"Services"
        }
    ],
    "sg:phone":"+61 3 9481 4744",
    "sg:postcode":"3068",
    "sg:province":"VIC",
    "wof:name":"Archiforma",
    "wof:placetype":"venue"
},
  "geometry": {"coordinates":[144.99197387699999,-37.7877006531],"type":"Point"}
}