{
  "type": "Feature",
  "properties": {
    "addr:full":"3/ 75 Boundary Rd Peakhurst NSW 2210",
    "addr:housenumber":"/ 75",
    "addr:postcode":"2210",
    "addr:street":"Boundary Rd",
    "iso:country":"AU",
    "sg:address":"3/ 75 Boundary Rd",
    "sg:city":"Peakhurst",
    "sg:classifiers":[
        {
            "category":"Retail",
            "subcategory":"Auto Repair",
            "type":"Services"
        }
    ],
    "sg:phone":"+61 2 9584 2220",
    "sg:postcode":"2210",
    "sg:province":"NSW",
    "sg:tags":[
        "electrical"
    ],
    "wof:name":"Hi-Quality Auto Electrics",
    "wof:placetype":"venue"
},
  "geometry": {"coordinates":[151.06849700000001,-33.964417],"type":"Point"}
}