{
  "type": "Feature",
  "properties": {
    "iso:country":"AU",
    "sg:address":"16 Avocet Drv",
    "sg:city":"Wagga Wagga",
    "sg:classifiers":[
        {
            "category":"Building & Trades",
            "subcategory":"Construction",
            "type":"Services"
        }
    ],
    "sg:phone":"+61 423 576 972",
    "sg:postcode":"2650",
    "sg:province":"NSW",
    "sg:tags":[
        "contractor"
    ],
    "wof:name":"AS & MA Waken",
    "wof:placetype":"venue"
},
  "geometry": {"coordinates":[147.35369873100001,-35.0747146606],"type":"Point"}
}