{
  "type": "Feature",
  "properties": {
    "iso:country":"AU",
    "sg:address":"U1/ 443 Albany Hwy",
    "sg:city":"Victoria Park",
    "sg:classifiers":[
        {
            "category":"Professional",
            "subcategory":"Art Services",
            "type":"Services"
        }
    ],
    "sg:phone":"+61 8 9361 2263",
    "sg:postcode":"6100",
    "sg:province":"WA",
    "sg:tags":[
        "interior",
        "designer"
    ],
    "wof:name":"Urbani Leyton Design",
    "wof:placetype":"venue"
},
  "geometry": {"coordinates":[115.897819519,-31.9756965637],"type":"Point"}
}