{
  "type": "Feature",
  "properties": {
    "iso:country":"AU",
    "sg:address":"2 Mercato Crt",
    "sg:city":"Kewdale",
    "sg:classifiers":[
        {
            "category":"Real Estate",
            "subcategory":"Developer",
            "type":"Services"
        }
    ],
    "sg:phone":"+61 8 9277 7202",
    "sg:postcode":"6105",
    "sg:province":"WA",
    "sg:tags":[
        "development"
    ],
    "wof:name":"Strata Title Consultancy Services",
    "wof:placetype":"venue"
},
  "geometry": {"coordinates":[115.931549072,-31.9715442657],"type":"Point"}
}