{
  "type": "Feature",
  "properties": {
    "addr:full":"27 Church St Traralgon VIC 3844",
    "addr:housenumber":"27",
    "addr:postcode":"3844",
    "addr:street":"Church St",
    "iso:country":"AU",
    "sg:address":"27 Church St",
    "sg:city":"Traralgon",
    "sg:classifiers":[
        {
            "category":"Professional",
            "subcategory":"Computer Services",
            "type":"Services"
        }
    ],
    "sg:phone":"+61 3 5174 6888",
    "sg:postcode":"3844",
    "sg:province":"VIC",
    "sg:tags":[
        "repairs",
        "upgrade",
        "equipment"
    ],
    "wof:name":"Pro-Tek Computers",
    "wof:placetype":"venue"
},
  "geometry": {"coordinates":[146.53509521500001,-38.1967124939],"type":"Point"}
}