{
  "type": "Feature",
  "properties": {
    "iso:country":"AU",
    "sg:address":"Donneleys Castle Rd",
    "sg:city":"Pozieres",
    "sg:classifiers":[
        {
            "category":"Farming",
            "subcategory":"Farm",
            "type":"Manufacturing & Wholesale Goods"
        }
    ],
    "sg:phone":"+61 7 4685 3360",
    "sg:postcode":"4352",
    "sg:province":"QLD",
    "sg:tags":[
        "farmer"
    ],
    "wof:name":"Abraham Dudley B",
    "wof:placetype":"venue"
},
  "geometry": {"coordinates":[152.01597599999999,-27.438499],"type":"Point"}
}