{
  "type": "Feature",
  "properties": {
    "addr:full":"354 High St Preston VIC 3072",
    "addr:housenumber":"354",
    "addr:postcode":"3072",
    "addr:street":"High St",
    "iso:country":"AU",
    "sg:address":"354 High St",
    "sg:city":"Preston",
    "sg:classifiers":[
        {
            "category":"Health Services",
            "subcategory":"Optometrist",
            "type":"Services"
        }
    ],
    "sg:phone":"+61 3 9478 0480",
    "sg:postcode":"3072",
    "sg:province":"VIC",
    "wof:name":"De Felice Michael",
    "wof:placetype":"venue"
},
  "geometry": {"coordinates":[145.00384521500001,-37.7400588989],"type":"Point"}
}