{
  "type": "Feature",
  "properties": {
    "addr:full":"Suite 3 89 Dora St Morisset NSW 2264",
    "addr:housenumber":"89",
    "addr:postcode":"2264",
    "addr:street":"Dora St",
    "iso:country":"AU",
    "sg:address":"Suite 3 89 Dora St",
    "sg:city":"Morisset",
    "sg:classifiers":[
        {
            "category":"Health Services",
            "subcategory":"Doctor",
            "type":"Services"
        }
    ],
    "sg:phone":"+61 2 4973 5755",
    "sg:postcode":"2264",
    "sg:province":"NSW",
    "sg:tags":[
        "medical",
        "practitioner"
    ],
    "wof:name":"Wright Tim Dr",
    "wof:placetype":"venue"
},
  "geometry": {"coordinates":[151.48684700000001,-33.108864],"type":"Point"}
}