{
  "type": "Feature",
  "properties": {
    "addr:full":"90 Walker St Maryborough QLD 4650",
    "addr:housenumber":"90",
    "addr:postcode":"4650",
    "addr:street":"Walker St",
    "iso:country":"AU",
    "sg:address":"90 Walker St",
    "sg:city":"Maryborough",
    "sg:classifiers":[
        {
            "category":"Autos & Motor Vehicles",
            "subcategory":"Automobile Sales",
            "type":"Retail Goods"
        }
    ],
    "sg:phone":"+61 7 4121 0642",
    "sg:postcode":"4650",
    "sg:province":"QLD",
    "sg:tags":[
        "car",
        "used"
    ],
    "wof:name":"Kent & Co Used Cars",
    "wof:placetype":"venue"
},
  "geometry": {"coordinates":[152.692047,-25.525003],"type":"Point"}
}