{
  "type": "Feature",
  "properties": {
    "addr:full":"Cnr Milperra Rd & Violet St Bankstown NSW 2200",
    "addr:postcode":"2200",
    "addr:street":"Cnr Milperra Rd & Violet St",
    "iso:country":"AU",
    "sg:address":"Cnr Milperra Rd & Violet St",
    "sg:city":"Bankstown",
    "sg:classifiers":[
        {
            "category":"Retail",
            "subcategory":"Auto Rental",
            "type":"Services"
        }
    ],
    "sg:phone":"+61 2 9772 2888",
    "sg:postcode":"2200",
    "sg:province":"NSW",
    "sg:tags":[
        "car",
        "hire",
        "minibus"
    ],
    "wof:name":"Thrifty Car Rental",
    "wof:placetype":"venue"
},
  "geometry": {"coordinates":[151.00636299999999,-33.934563],"type":"Point"}
}