{
  "type": "Feature",
  "properties": {
    "addr:full":"Coolbellup Shopping Centre, Coolbellup Ave Coolbellup WA 6163",
    "addr:postcode":"6163",
    "addr:street":"Coolbellup Ave",
    "iso:country":"AU",
    "sg:address":"Coolbellup Shopping Centre, Coolbellup Ave",
    "sg:city":"Coolbellup",
    "sg:classifiers":[
        {
            "category":"Fast Food",
            "type":"Food & Drink"
        }
    ],
    "sg:phone":"+61 8 9314 7405",
    "sg:postcode":"6163",
    "sg:province":"WA",
    "sg:tags":[
        "away",
        "take"
    ],
    "wof:name":"Chooks Fresh and Tasty",
    "wof:placetype":"venue"
},
  "geometry": {"coordinates":[115.80677799999999,-32.082279],"type":"Point"}
}