{
  "type": "Feature",
  "properties": {
    "addr:full":"116 Buckley St Footscray VIC 3011",
    "addr:housenumber":"116",
    "addr:postcode":"3011",
    "addr:street":"Buckley St",
    "iso:country":"AU",
    "sg:address":"116 Buckley St",
    "sg:city":"Footscray",
    "sg:classifiers":[
        {
            "category":"Retail",
            "subcategory":"Auto Repair",
            "type":"Services"
        }
    ],
    "sg:phone":"+61 3 9689 8522",
    "sg:postcode":"3011",
    "sg:province":"VIC",
    "sg:tags":[
        "wheel",
        "balancing",
        "alignment"
    ],
    "wof:name":"Pedders Suspension",
    "wof:placetype":"venue"
},
  "geometry": {"coordinates":[144.89300537099999,-37.8032722473],"type":"Point"}
}