{
  "type": "Feature",
  "properties": {
    "iso:country":"AU",
    "sg:address":"30 Bourton Rd",
    "sg:city":"Merrimac",
    "sg:classifiers":[
        {
            "category":"Professional",
            "subcategory":"Employment Agencies",
            "type":"Services"
        }
    ],
    "sg:phone":"+61 7 5522 7293",
    "sg:postcode":"4226",
    "sg:province":"QLD",
    "sg:tags":[
        "entertainer",
        "agent"
    ],
    "wof:name":"Trix Circus",
    "wof:placetype":"venue"
},
  "geometry": {"coordinates":[153.36026000999999,-28.0500144958],"type":"Point"}
}