{
  "type": "Feature",
  "properties": {
    "addr:full":"2 Lilli Pilli Pl Springvale NSW 2650",
    "addr:housenumber":"2",
    "addr:postcode":"2650",
    "addr:street":"Lilli Pilli Pl",
    "iso:country":"AU",
    "sg:address":"2 Lilli Pilli Pl",
    "sg:city":"Springvale",
    "sg:classifiers":[
        {
            "category":"Recreation",
            "subcategory":"Fishing",
            "type":"Entertainment"
        }
    ],
    "sg:phone":"+61 2 6931 3990",
    "sg:postcode":"2650",
    "sg:province":"NSW",
    "sg:tags":[
        "tackle"
    ],
    "wof:name":"Oar-Gee Lures",
    "wof:placetype":"venue"
},
  "geometry": {"coordinates":[147.321868897,-35.1787910461],"type":"Point"}
}