{
  "type": "Feature",
  "properties": {
    "addr:full":"146 Arlunya Ave Cloverdale WA 6105",
    "addr:housenumber":"146",
    "addr:postcode":"6105",
    "addr:street":"Arlunya Ave",
    "iso:country":"AU",
    "sg:address":"146 Arlunya Ave",
    "sg:city":"Cloverdale",
    "sg:classifiers":[
        {
            "category":"Food & Beverages",
            "subcategory":"Specialty",
            "type":"Retail Goods"
        }
    ],
    "sg:phone":"+61 8 9277 3233",
    "sg:postcode":"6105",
    "sg:province":"WA",
    "sg:tags":[
        "product",
        "health"
    ],
    "wof:name":"Rawleigh Products",
    "wof:placetype":"venue"
},
  "geometry": {"coordinates":[115.94400024399999,-31.9619903564],"type":"Point"}
}