{
  "type": "Feature",
  "properties": {
    "iso:country":"AU",
    "sg:address":"11 Donald Crt",
    "sg:city":"Maryborough",
    "sg:classifiers":[
        {
            "category":"Retail",
            "subcategory":"Driving School",
            "type":"Services"
        }
    ],
    "sg:phone":"+61 427 222 650",
    "sg:postcode":"4650",
    "sg:province":"QLD",
    "sg:tags":[
        "defensive",
        "advanced"
    ],
    "wof:name":"DEFENSIVE DRIVING SCHOOLS MARYBOROUGH & HERVEY BAY",
    "wof:placetype":"venue"
},
  "geometry": {"coordinates":[152.680725,-25.543896],"type":"Point"}
}