{
  "type": "Feature",
  "properties": {
    "addr:full":"Unit 1/ 13 Adventure Pl Taren Point NSW 2229",
    "addr:housenumber":"13",
    "addr:postcode":"2229",
    "addr:street":"Adventure Pl",
    "iso:country":"AU",
    "sg:address":"Unit 1/ 13 Adventure Pl",
    "sg:city":"Taren Point",
    "sg:classifiers":[
        {
            "category":"Home & Garden",
            "subcategory":"Furniture",
            "type":"Retail Goods"
        }
    ],
    "sg:phone":"+61 411 745 268",
    "sg:postcode":"2229",
    "sg:province":"NSW",
    "sg:tags":[
        "business"
    ],
    "wof:name":"GAPCOMM Interiors",
    "wof:placetype":"venue"
},
  "geometry": {"coordinates":[151.12994384800001,-34.0292053223],"type":"Point"}
}