{
  "type": "Feature",
  "properties": {
    "iso:country":"AU",
    "sg:address":"1/ 5 Burgess Rd",
    "sg:city":"Bayswater North",
    "sg:classifiers":[
        {
            "category":"Building & Trades",
            "subcategory":"Construction",
            "type":"Services"
        }
    ],
    "sg:phone":"+61 1300 763 666",
    "sg:postcode":"3153",
    "sg:province":"VIC",
    "sg:tags":[
        "concrete",
        "treatment",
        "repair"
    ],
    "wof:name":"Pro Grind Pty Ltd",
    "wof:placetype":"venue"
},
  "geometry": {"coordinates":[145.28825378400001,-37.8222885132],"type":"Point"}
}