{
  "type": "Feature",
  "properties": {
    "addr:full":"3 Kembla St Balgownie NSW 2519",
    "addr:housenumber":"3",
    "addr:postcode":"2519",
    "addr:street":"Kembla St",
    "iso:country":"AU",
    "sg:address":"3 Kembla St",
    "sg:city":"Balgownie",
    "sg:classifiers":[
        {
            "category":"Professional",
            "subcategory":"Detective & Security Services",
            "type":"Services"
        }
    ],
    "sg:phone":"+61 1300 305 568",
    "sg:postcode":"2519",
    "sg:province":"NSW",
    "sg:tags":[
        "consultant",
        "system"
    ],
    "wof:name":"Specialist Security Services",
    "wof:placetype":"venue"
},
  "geometry": {"coordinates":[150.87759399999999,-34.389076],"type":"Point"}
}