{
  "type": "Feature",
  "properties": {
    "addr:full":"333 Lords Pl Orange NSW 2800",
    "addr:housenumber":"333",
    "addr:postcode":"2800",
    "addr:street":"Lords Pl",
    "iso:country":"AU",
    "sg:address":"333 Lords Pl",
    "sg:city":"Orange",
    "sg:classifiers":[
        {
            "category":"Home & Garden",
            "subcategory":"Building Materials",
            "type":"Retail Goods"
        }
    ],
    "sg:phone":"+61 2 6360 2094",
    "sg:postcode":"2800",
    "sg:province":"NSW",
    "sg:tags":[
        "lawn",
        "cutting",
        "maintenance"
    ],
    "wof:name":"Fardell Lawn & Garden Maintenance",
    "wof:placetype":"venue"
},
  "geometry": {"coordinates":[149.10134887699999,-33.2821350098],"type":"Point"}
}