{
  "type": "Feature",
  "properties": {
    "iso:country":"AU",
    "sg:address":"Factory 3/ 654 Waterdale Rd",
    "sg:city":"Heidelberg West",
    "sg:classifiers":[
        {
            "category":"Professional",
            "subcategory":"Printing & Photocopies",
            "type":"Services"
        }
    ],
    "sg:phone":"+61 3 9455 0345",
    "sg:postcode":"3081",
    "sg:province":"VIC",
    "sg:tags":[
        "laminating"
    ],
    "wof:name":"Aztec Laminating Pty Ltd",
    "wof:placetype":"venue"
},
  "geometry": {"coordinates":[145.05015564000001,-37.7294960022],"type":"Point"}
}