{
  "type": "Feature",
  "properties": {
    "addr:full":"Unit 3/ 19 Reliance Drv Tuggerah NSW 2259",
    "addr:housenumber":"19",
    "addr:postcode":"2259",
    "addr:street":"Reliance Drv",
    "iso:country":"AU",
    "sg:address":"Unit 3/ 19 Reliance Drv",
    "sg:city":"Tuggerah",
    "sg:classifiers":[
        {
            "category":"Organizations",
            "subcategory":"Professional Association",
            "type":"Services"
        }
    ],
    "sg:phone":"+61 2 4353 0763",
    "sg:postcode":"2259",
    "sg:province":"NSW",
    "sg:tags":[
        "organisation",
        "business"
    ],
    "wof:name":"Australian Business Limited",
    "wof:placetype":"venue"
},
  "geometry": {"coordinates":[151.42494201700001,-33.3204612732],"type":"Point"}
}