{
  "type": "Feature",
  "properties": {
    "addr:full":"Cnr Nepean Hwy & Hampton St Brighton VIC 3186",
    "addr:postcode":"3186",
    "addr:street":"Cnr Nepean Hwy & Hampton St",
    "iso:country":"AU",
    "sg:address":"Cnr Nepean Hwy & Hampton St",
    "sg:city":"Brighton",
    "sg:classifiers":[
        {
            "category":"Shopping",
            "subcategory":"Optical Goods",
            "type":"Retail Goods"
        }
    ],
    "sg:phone":"+61 3 9596 1433",
    "sg:postcode":"3186",
    "sg:province":"VIC",
    "sg:tags":[
        "dispenser",
        "prescription"
    ],
    "wof:name":"Brighton Optika",
    "wof:placetype":"venue"
},
  "geometry": {"coordinates":[145.00852966299999,-37.9065895081],"type":"Point"}
}