{
  "type": "Feature",
  "properties": {
    "addr:full":"38 Reynolds St Pymble NSW 2073",
    "addr:housenumber":"38",
    "addr:postcode":"2073",
    "addr:street":"Reynolds St",
    "iso:country":"AU",
    "sg:address":"38 Reynolds St",
    "sg:city":"Pymble",
    "sg:classifiers":[
        {
            "category":"Building & Trades",
            "subcategory":"Construction",
            "type":"Services"
        }
    ],
    "sg:phone":"+61 2 9449 4535",
    "sg:postcode":"2073",
    "sg:province":"NSW",
    "sg:tags":[
        "earth",
        "excavating",
        "moving",
        "contractor"
    ],
    "wof:name":"Eco Excavations Pty Ltd",
    "wof:placetype":"venue"
},
  "geometry": {"coordinates":[151.145584106,-33.7332382202],"type":"Point"}
}