{
  "type": "Feature",
  "properties": {
    "iso:country":"AU",
    "sg:address":"206a Albert St",
    "sg:city":"Sebastopol",
    "sg:classifiers":[
        {
            "category":"Travel",
            "subcategory":"Travel Agent",
            "type":"Entertainment"
        }
    ],
    "sg:phone":"+61 3 5336 0260",
    "sg:postcode":"3356",
    "sg:province":"VIC",
    "sg:tags":[
        "consultant"
    ],
    "wof:name":"Travel Options",
    "wof:placetype":"venue"
},
  "geometry": {"coordinates":[143.840897,-37.59906],"type":"Point"}
}