{
  "type": "Feature",
  "properties": {
    "addr:full":"206a Albert St Sebastopol VIC 3356",
    "addr:housenumber":"206a",
    "addr:postcode":"3356",
    "addr:street":"Albert St",
    "iso:country":"AU",
    "sg:address":"206a Albert St",
    "sg:city":"Sebastopol",
    "sg:classifiers":[
        {
            "category":"Travel",
            "subcategory":"Travel Agent",
            "type":"Entertainment"
        }
    ],
    "sg:phone":"+61 3 5336 0260",
    "sg:postcode":"3356",
    "sg:province":"VIC",
    "sg:tags":[
        "consultant"
    ],
    "wof:name":"Travel Options",
    "wof:placetype":"venue"
},
  "geometry": {"coordinates":[143.84089700000001,-37.59906],"type":"Point"}
}