{
  "type": "Feature",
  "properties": {
    "iso:country":"AU",
    "sg:address":"PO Box 1378",
    "sg:city":"Noosaville",
    "sg:classifiers":[
        {
            "category":"Home & Garden",
            "subcategory":"Building Materials",
            "type":"Retail Goods"
        }
    ],
    "sg:phone":"+61 418 980 211",
    "sg:postcode":"4566",
    "sg:province":"QLD",
    "sg:tags":[
        "retaining",
        "wall"
    ],
    "wof:name":"Granite Boulder Supplies",
    "wof:placetype":"venue"
},
  "geometry": {"coordinates":[153.05047607399999,-26.4029693604],"type":"Point"}
}