{
  "type": "Feature",
  "properties": {
    "iso:country":"AU",
    "sg:address":"874 Ballarat Rd",
    "sg:city":"Deer Park",
    "sg:classifiers":[
        {
            "category":"Utilities",
            "subcategory":"Electric",
            "type":"Services"
        }
    ],
    "sg:phone":"+61 3 9360 4300",
    "sg:postcode":"3023",
    "sg:province":"VIC",
    "sg:tags":[
        "electrical",
        "contractor"
    ],
    "wof:name":"C.L. Electrics",
    "wof:placetype":"venue"
},
  "geometry": {"coordinates":[144.76355000000001,-37.765926],"type":"Point"}
}