{
  "type": "Feature",
  "properties": {
    "iso:country":"AU",
    "sg:address":"Midland Hwy",
    "sg:city":"Mooroopna",
    "sg:classifiers":[
        {
            "category":"Retail",
            "subcategory":"Auto Repair",
            "type":"Services"
        }
    ],
    "sg:phone":"+61 3 5825 1550",
    "sg:postcode":"3629",
    "sg:province":"VIC",
    "sg:tags":[
        "beater",
        "painter",
        "panel"
    ],
    "wof:name":"Heenan Panel Works",
    "wof:placetype":"venue"
},
  "geometry": {"coordinates":[145.36723327600001,-36.3912353516],"type":"Point"}
}