{
  "type": "Feature",
  "properties": {
    "iso:country":"AU",
    "sg:address":"130 Camlet St",
    "sg:city":"Mt Gravatt",
    "sg:classifiers":[
        {
            "category":"Social Services",
            "subcategory":"Adult Care",
            "type":"Services"
        }
    ],
    "sg:phone":"+61 7 3849 4038",
    "sg:postcode":"4122",
    "sg:province":"QLD",
    "sg:tags":[
        "disadvantaged",
        "aid",
        "organisation",
        "group"
    ],
    "wof:name":"Nathanael House Youth Shelter",
    "wof:placetype":"venue"
},
  "geometry": {"coordinates":[153.08393859899999,-27.5311431885],"type":"Point"}
}