{
  "type": "Feature",
  "properties": {
    "addr:full":"Wivenhoe Somerset Dam Rd Fernvale QLD 4306",
    "addr:postcode":"4306",
    "addr:street":"Dam Rd",
    "iso:country":"AU",
    "sg:address":"Wivenhoe Somerset Dam Rd",
    "sg:city":"Fernvale",
    "sg:classifiers":[
        {
            "category":"Farming",
            "subcategory":"Farm",
            "type":"Manufacturing & Wholesale Goods"
        }
    ],
    "sg:phone":"+61 7 5426 7168",
    "sg:postcode":"4306",
    "sg:province":"QLD",
    "sg:tags":[
        "farmer"
    ],
    "wof:name":"Varley V",
    "wof:placetype":"venue"
},
  "geometry": {"coordinates":[152.646575928,-27.3997097015],"type":"Point"}
}