{
  "type": "Feature",
  "properties": {
    "iso:country":"AU",
    "sg:address":"32 Nindavale Ave",
    "sg:city":"Nindaroo",
    "sg:classifiers":[
        {
            "category":"Health Services",
            "subcategory":"Doctor",
            "type":"Services"
        }
    ],
    "sg:phone":"+61 7 4942 0240",
    "sg:postcode":"4740",
    "sg:province":"QLD",
    "sg:tags":[
        "occupational",
        "safety"
    ],
    "wof:name":"Hygiene Technologies Pty Ltd",
    "wof:placetype":"venue"
},
  "geometry": {"coordinates":[149.132568,-21.068007],"type":"Point"}
}