{
  "type": "Feature",
  "properties": {
    "addr:full":"Shop 2, 2A Cross St Hurstville NSW 2220",
    "addr:housenumber":"shop 2 2a",
    "addr:postcode":"2220",
    "addr:street":"Cross St",
    "iso:country":"AU",
    "sg:address":"Shop 2, 2A Cross St",
    "sg:city":"Hurstville",
    "sg:classifiers":[
        {
            "category":"Shopping",
            "subcategory":"Computers & Home Electronics",
            "type":"Retail Goods"
        }
    ],
    "sg:phone":"+61 2 9586 1117",
    "sg:postcode":"2220",
    "sg:province":"NSW",
    "sg:tags":[
        "equipment",
        "supply"
    ],
    "wof:name":"Cartridge World",
    "wof:placetype":"venue"
},
  "geometry": {"coordinates":[151.104568481,-33.9655532837],"type":"Point"}
}