{
  "type": "Feature",
  "properties": {
    "iso:country":"AU",
    "sg:address":"2/ 289 Whitehorse Rd",
    "sg:city":"Balwyn",
    "sg:classifiers":[
        {
            "category":"Real Estate",
            "subcategory":"Architect",
            "type":"Services"
        }
    ],
    "sg:phone":"+61 3 9830 2465",
    "sg:postcode":"3103",
    "sg:province":"VIC",
    "wof:name":"Nigel Hume Architect",
    "wof:placetype":"venue"
},
  "geometry": {"coordinates":[145.07875060999999,-37.8123779297],"type":"Point"}
}