{
  "type": "Feature",
  "properties": {
    "addr:full":"56- 60 Princes Hwy Sylvania NSW 2224",
    "addr:housenumber":"60",
    "addr:postcode":"2224",
    "addr:street":"Princes Hwy",
    "iso:country":"AU",
    "sg:address":"56- 60 Princes Hwy",
    "sg:city":"Sylvania",
    "sg:classifiers":[
        {
            "category":"Education",
            "subcategory":"Kindergarten",
            "type":"Public Place"
        }
    ],
    "sg:phone":"+61 2 9522 6261",
    "sg:postcode":"2224",
    "sg:province":"NSW",
    "sg:tags":[
        "pre-schools"
    ],
    "wof:name":"Orange Emu Kindergarten",
    "wof:placetype":"venue"
},
  "geometry": {"coordinates":[151.10992431599999,-34.0091972351],"type":"Point"}
}