{
  "type": "Feature",
  "properties": {
    "iso:country":"AU",
    "sg:address":"36 Hubert St",
    "sg:city":"Leichhardt",
    "sg:classifiers":[
        {
            "category":"Retail",
            "subcategory":"Auto Rental",
            "type":"Services"
        }
    ],
    "sg:phone":"+61 414 744 933",
    "sg:postcode":"2040",
    "sg:province":"NSW",
    "sg:tags":[
        "chauffeur",
        "car",
        "hire",
        "driven",
        "limousine"
    ],
    "wof:name":"Limousines in Sydney",
    "wof:placetype":"venue"
},
  "geometry": {"coordinates":[151.15332,-33.8764],"type":"Point"}
}