{
  "type": "Feature",
  "properties": {
    "iso:country":"AU",
    "sg:address":"Shop 19A Nuggets Crossing",
    "sg:city":"Jindabyne",
    "sg:classifiers":[
        {
            "category":"Real Estate",
            "subcategory":"Real Estate Agent",
            "type":"Services"
        }
    ],
    "sg:phone":"+61 2 6451 2007",
    "sg:postcode":"2627",
    "sg:province":"NSW",
    "wof:name":"L J Hooker Jindabyne",
    "wof:placetype":"venue"
},
  "geometry": {"coordinates":[148.60859680199999,-36.4327316284],"type":"Point"}
}