{
  "type": "Feature",
  "properties": {
    "addr:full":"Unit 6/ 1 Bell St Preston VIC 3072",
    "addr:housenumber":"1",
    "addr:postcode":"3072",
    "addr:street":"Bell St",
    "iso:country":"AU",
    "sg:address":"Unit 6/ 1 Bell St",
    "sg:city":"Preston",
    "sg:classifiers":[
        {
            "category":"Communications",
            "subcategory":"Film & Video Production",
            "type":"Services"
        }
    ],
    "sg:phone":"+61 3 9484 8579",
    "sg:postcode":"3072",
    "sg:province":"VIC",
    "sg:tags":[
        "television",
        "system",
        "circuit",
        "closed"
    ],
    "wof:name":"Allstate Security",
    "wof:placetype":"venue"
},
  "geometry": {"coordinates":[145.030807495,-37.7485809326],"type":"Point"}
}