{
  "type": "Feature",
  "properties": {
    "iso:country":"AU",
    "sg:address":"179a Fairy St",
    "sg:city":"Warrnambool",
    "sg:classifiers":[
        {
            "category":"Utilities",
            "subcategory":"Natural Gas",
            "type":"Services"
        }
    ],
    "sg:phone":"+61 3 5562 1685",
    "sg:postcode":"3280",
    "sg:province":"VIC",
    "sg:tags":[
        "cylinder",
        "testing"
    ],
    "wof:name":"Warrnambool Diving Services",
    "wof:placetype":"venue"
},
  "geometry": {"coordinates":[142.480758667,-38.3790664673],"type":"Point"}
}