{
  "type": "Feature",
  "properties": {
    "addr:full":"5 Somers St Mitcham VIC 3132",
    "addr:housenumber":"5",
    "addr:postcode":"3132",
    "addr:street":"Somers St",
    "iso:country":"AU",
    "sg:address":"5 Somers St",
    "sg:city":"Mitcham",
    "sg:classifiers":[
        {
            "category":"Professional",
            "subcategory":"Secretarial Services",
            "type":"Services"
        }
    ],
    "sg:phone":"+61 3 9873 7740",
    "sg:postcode":"3132",
    "sg:province":"VIC",
    "sg:tags":[
        "typing"
    ],
    "wof:name":"Helen Boettcher - Business Support",
    "wof:placetype":"venue"
},
  "geometry": {"coordinates":[145.20355224599999,-37.8236846924],"type":"Point"}
}