{
  "type": "Feature",
  "properties": {
    "iso:country":"AU",
    "sg:address":"15 Newmarch Pl",
    "sg:city":"Bligh Park",
    "sg:classifiers":[
        {
            "category":"Home & Garden",
            "subcategory":"Carpets & Floor Coverings",
            "type":"Retail Goods"
        }
    ],
    "sg:phone":"+61 2 4572 6206",
    "sg:postcode":"2756",
    "sg:province":"NSW",
    "sg:tags":[
        "club",
        "boat",
        "motor"
    ],
    "wof:name":"Yamato Outboard Racing Club",
    "wof:placetype":"venue"
},
  "geometry": {"coordinates":[150.79124450699999,-33.6392173767],"type":"Point"}
}