{
  "type": "Feature",
  "properties": {
    "addr:full":"Unit 6 / 12 Peacock Rd Para Hills West SA 5096",
    "addr:housenumber":"12",
    "addr:postcode":"5096",
    "addr:street":"Peacock Rd Para Hills West",
    "iso:country":"AU",
    "sg:address":"Unit 6 / 12 Peacock Rd",
    "sg:city":"Para Hills West",
    "sg:classifiers":[
        {
            "category":"Building & Trades",
            "subcategory":"Equipment Rental",
            "type":"Services"
        }
    ],
    "sg:phone":"+61 8 8263 1581",
    "sg:postcode":"5096",
    "sg:province":"SA",
    "sg:tags":[
        "crane",
        "hire"
    ],
    "wof:name":"AGL & Son Crane Hire",
    "wof:placetype":"venue"
},
  "geometry": {"coordinates":[138.64935302699999,-34.7936706543],"type":"Point"}
}