{
  "type": "Feature",
  "properties": {
    "addr:full":"176 Stoney Rise Rd Devonport TAS 7310",
    "addr:housenumber":"176",
    "addr:postcode":"7310",
    "addr:street":"Stoney Rise Rd",
    "iso:country":"AU",
    "sg:address":"176 Stoney Rise Rd",
    "sg:city":"Devonport",
    "sg:classifiers":[
        {
            "category":"Transit Center",
            "subcategory":"Freight",
            "type":"Transportation"
        }
    ],
    "sg:phone":"+61 3 6424 9855",
    "sg:postcode":"7310",
    "sg:province":"TAS",
    "sg:tags":[
        "forklift",
        "truck"
    ],
    "wof:name":"FRM Materials Handling Pty Ltd",
    "wof:placetype":"venue"
},
  "geometry": {"coordinates":[146.32403564399999,-41.1865463257],"type":"Point"}
}