{
  "type": "Feature",
  "properties": {
    "iso:country":"AU",
    "sg:address":"17 Princess St",
    "sg:city":"Lidcombe",
    "sg:classifiers":[
        {
            "category":"Retail",
            "subcategory":"Auto Repair",
            "type":"Services"
        }
    ],
    "sg:phone":"+61 2 9649 8293",
    "sg:postcode":"2141",
    "sg:province":"NSW",
    "sg:tags":[
        "beater",
        "painter",
        "panel"
    ],
    "wof:name":"Etheridge R & Sons",
    "wof:placetype":"venue"
},
  "geometry": {"coordinates":[151.05361938499999,-33.8598442078],"type":"Point"}
}