{
  "type": "Feature",
  "properties": {
    "iso:country":"AU",
    "sg:address":"48 Chandos St St",
    "sg:city":"Leonards",
    "sg:classifiers":[
        {
            "category":"Wholesale",
            "subcategory":"Construction Materials",
            "type":"Manufacturing & Wholesale Goods"
        }
    ],
    "sg:phone":"+61 2 9437 0577",
    "sg:postcode":"2065",
    "sg:province":"NSW",
    "sg:tags":[
        "lift"
    ],
    "wof:name":"Campbell Jim & Associates",
    "wof:placetype":"venue"
},
  "geometry": {"coordinates":[151.19720459000001,-33.8218841553],"type":"Point"}
}