{
  "type": "Feature",
  "properties": {
    "iso:country":"AU",
    "sg:address":"Studio 13 Lvl5/ 35 Buckingham St",
    "sg:city":"Surry Hills",
    "sg:classifiers":[
        {
            "category":"Professional",
            "subcategory":"Management & Consulting",
            "type":"Services"
        }
    ],
    "sg:phone":"+61 2 8399 2999",
    "sg:postcode":"2010",
    "sg:province":"NSW",
    "sg:tags":[
        "consultant"
    ],
    "wof:name":"Wade Maher & Asssociates Pty Ltd",
    "wof:placetype":"venue"
},
  "geometry": {"coordinates":[151.20562744099999,-33.8968391418],"type":"Point"}
}