{
  "type": "Feature",
  "properties": {
    "iso:country":"AU",
    "sg:address":"20 Wharton St",
    "sg:city":"Surrey Hills",
    "sg:classifiers":[
        {
            "category":"Professional",
            "subcategory":"Management & Consulting",
            "type":"Services"
        }
    ],
    "sg:phone":"+61 3 9830 1384",
    "sg:postcode":"3127",
    "sg:province":"VIC",
    "sg:tags":[
        "consultant",
        "business"
    ],
    "wof:name":"Riverans & Associates",
    "wof:placetype":"venue"
},
  "geometry": {"coordinates":[145.09062194800001,-37.8158416748],"type":"Point"}
}