{
  "type": "Feature",
  "properties": {
    "iso:country":"AU",
    "sg:address":"Shp 9a 1 Opal Drv",
    "sg:city":"Blackmans Bay",
    "sg:classifiers":[
        {
            "category":"Fast Food",
            "type":"Food & Drink"
        }
    ],
    "sg:phone":"+61 3 6229 7633",
    "sg:postcode":"7052",
    "sg:province":"TAS",
    "sg:tags":[
        "away",
        "take"
    ],
    "wof:name":"Dom's Asian Teahouse",
    "wof:placetype":"venue"
},
  "geometry": {"coordinates":[147.317947,-42.998211],"type":"Point"}
}