{
  "type": "Feature",
  "properties": {
    "iso:country":"AU",
    "sg:address":"27 Callington Rd",
    "sg:city":"Strathalbyn",
    "sg:classifiers":[
        {
            "category":"Home & Garden",
            "subcategory":"Garden Supply",
            "type":"Retail Goods"
        }
    ],
    "sg:phone":"+61 8 8536 3877",
    "sg:postcode":"5255",
    "sg:province":"SA",
    "sg:tags":[
        "equipment"
    ],
    "wof:name":"P & K Statues",
    "wof:placetype":"venue"
},
  "geometry": {"coordinates":[138.904006958,-35.256061554],"type":"Point"}
}