{
  "type": "Feature",
  "properties": {
    "addr:full":"35 Fullerton St Birkdale QLD 4159",
    "addr:housenumber":"35",
    "addr:postcode":"4159",
    "addr:street":"Fullerton St",
    "iso:country":"AU",
    "sg:address":"35 Fullerton St",
    "sg:city":"Birkdale",
    "sg:classifiers":[
        {
            "category":"Professional",
            "subcategory":"Accounting & Tax Preparation",
            "type":"Services"
        }
    ],
    "sg:phone":"+61 7 3824 2889",
    "sg:postcode":"4159",
    "sg:province":"QLD",
    "sg:tags":[
        "bookkeeping"
    ],
    "wof:name":"Busy Bookkeeping Pty Ltd",
    "wof:placetype":"venue"
},
  "geometry": {"coordinates":[153.21661376899999,-27.5128440857],"type":"Point"}
}