{
  "type": "Feature",
  "properties": {
    "addr:full":"160- 162 Gaffney St Coburg VIC 3058",
    "addr:housenumber":"160 162",
    "addr:postcode":"3058",
    "addr:street":"Gaffney St",
    "iso:country":"AU",
    "sg:address":"160- 162 Gaffney St",
    "sg:city":"Coburg",
    "sg:classifiers":[
        {
            "category":"Home & Garden",
            "subcategory":"Building Materials",
            "type":"Retail Goods"
        }
    ],
    "sg:phone":"+61 3 9350 4140",
    "sg:postcode":"3058",
    "sg:province":"VIC",
    "sg:tags":[
        "tile",
        "roofing"
    ],
    "wof:name":"North Suburban Roof Tiles",
    "wof:placetype":"venue"
},
  "geometry": {"coordinates":[144.952194214,-37.7326087952],"type":"Point"}
}