{
  "type": "Feature",
  "properties": {
    "addr:full":"90 Victoria St Richmond North VIC 3121",
    "addr:housenumber":"90",
    "addr:postcode":"3121",
    "addr:street":"Victoria St",
    "iso:country":"AU",
    "sg:address":"90 Victoria St",
    "sg:city":"Richmond North",
    "sg:classifiers":[
        {
            "category":"Shopping",
            "subcategory":"Jewelry",
            "type":"Retail Goods"
        }
    ],
    "sg:phone":"+61 3 9428 7206",
    "sg:postcode":"3121",
    "sg:province":"VIC",
    "sg:tags":[
        "jeweller"
    ],
    "wof:name":"Kim Ngoc Jewellery",
    "wof:placetype":"venue"
},
  "geometry": {"coordinates":[144.99465942399999,-37.8100547791],"type":"Point"}
}