{
  "type": "Feature",
  "properties": {
    "iso:country":"AU",
    "sg:address":"2/ 36 Machinery Drv",
    "sg:city":"Tweed Heads South",
    "sg:classifiers":[
        {
            "category":"Banks & Credit Unions",
            "subcategory":"Bank",
            "type":"Services"
        }
    ],
    "sg:phone":"+61 7 5524 7581",
    "sg:postcode":"2486",
    "sg:province":"NSW",
    "sg:tags":[
        "equipment",
        "sale",
        "point"
    ],
    "wof:name":"Harris Data",
    "wof:placetype":"venue"
},
  "geometry": {"coordinates":[153.540740967,-28.2041816711],"type":"Point"}
}