{
  "type": "Feature",
  "properties": {
    "iso:country":"AU",
    "sg:address":"PO Box 3389",
    "sg:city":"Tamarama",
    "sg:classifiers":[
        {
            "category":"Professional",
            "subcategory":"Detective & Security Services",
            "type":"Services"
        }
    ],
    "sg:phone":"+61 414 673 883",
    "sg:postcode":"2026",
    "sg:province":"NSW",
    "sg:tags":[
        "consultant",
        "system"
    ],
    "wof:name":"Rival Protective Services",
    "wof:placetype":"venue"
},
  "geometry": {"coordinates":[151.27003479000001,-33.899559021],"type":"Point"}
}