{
  "type": "Feature",
  "properties": {
    "addr:full":"10 Commercial St Marleston SA 5033",
    "addr:housenumber":"10",
    "addr:postcode":"5033",
    "addr:street":"Commercial St",
    "iso:country":"AU",
    "sg:address":"10 Commercial St",
    "sg:city":"Marleston",
    "sg:classifiers":[
        {
            "category":"Building & Trades",
            "subcategory":"Equipment Rental",
            "type":"Services"
        }
    ],
    "sg:phone":"+61 8 8293 5657",
    "sg:postcode":"5033",
    "sg:province":"SA",
    "sg:tags":[
        "demolition",
        "contractor"
    ],
    "wof:name":"A-1 Adelaide Roof Tile Recyclers",
    "wof:placetype":"venue"
},
  "geometry": {"coordinates":[138.56387329099999,-34.9445381165],"type":"Point"}
}