{
  "type": "Feature",
  "properties": {
    "addr:full":"152 Waterworth Drv Mt Annan NSW 2567",
    "addr:housenumber":"152",
    "addr:postcode":"2567",
    "addr:street":"Waterworth Drv",
    "iso:country":"AU",
    "sg:address":"152 Waterworth Drv",
    "sg:city":"Mt Annan",
    "sg:classifiers":[
        {
            "category":"Education",
            "subcategory":"Kindergarten",
            "type":"Public Place"
        }
    ],
    "sg:phone":"+61 2 4647 2054",
    "sg:postcode":"2567",
    "sg:province":"NSW",
    "sg:tags":[
        "pre-schools"
    ],
    "wof:name":"Miss Lizzie's Kindergarten",
    "wof:placetype":"venue"
},
  "geometry": {"coordinates":[150.758178711,-34.0505981445],"type":"Point"}
}