{
  "type": "Feature",
  "properties": {
    "addr:full":"Level 3 Shop 3055 Westfield Shoppingtown Parramatta NSW 2150",
    "addr:housenumber":"shop 3055;shoppingtown",
    "addr:postcode":"2150",
    "addr:street":"Westfield",
    "iso:country":"AU",
    "sg:address":"Level 3 Shop 3055 Westfield Shoppingtown",
    "sg:city":"Parramatta",
    "sg:classifiers":[
        {
            "category":"Personal",
            "subcategory":"Shoe Repair & Shine",
            "type":"Services"
        }
    ],
    "sg:phone":"+61 2 9891 9010",
    "sg:postcode":"2150",
    "sg:province":"NSW",
    "sg:tags":[
        "footwear"
    ],
    "wof:name":"Kumfs Naturally",
    "wof:placetype":"venue"
},
  "geometry": {"coordinates":[151.00227355999999,-33.8176116943],"type":"Point"}
}