{
  "type": "Feature",
  "properties": {
    "addr:full":"PO Box 570 Willunga SA 5172",
    "addr:postcode":"5172",
    "iso:country":"AU",
    "sg:address":"PO Box 570",
    "sg:city":"Willunga",
    "sg:classifiers":[
        {
            "category":"Manufacturing",
            "subcategory":"Musical Instruments",
            "type":"Manufacturing & Wholesale Goods"
        }
    ],
    "sg:phone":"+61 414 441 688",
    "sg:postcode":"5172",
    "sg:province":"SA",
    "sg:tags":[
        "repair",
        "maker"
    ],
    "wof:name":"Sizer Neil R",
    "wof:placetype":"venue"
},
  "geometry": {"coordinates":[138.57168579099999,-35.2866897583],"type":"Point"}
}