{
  "type": "Feature",
  "properties": {
    "addr:full":"Thomas St Ultimo NSW 2007",
    "addr:postcode":"2007",
    "addr:street":"Thomas St",
    "iso:country":"AU",
    "sg:address":"Thomas St",
    "sg:city":"Ultimo",
    "sg:classifiers":[
        {
            "category":"Social Services",
            "subcategory":"Child Care",
            "type":"Services"
        }
    ],
    "sg:phone":"+61 2 9514 1456",
    "sg:postcode":"2007",
    "sg:province":"NSW",
    "wof:name":"Magic Pudding Child Care Centre",
    "wof:placetype":"venue"
},
  "geometry": {"coordinates":[151.19880676299999,-33.8832588196],"type":"Point"}
}