{
  "type": "Feature",
  "properties": {
    "addr:full":"Shop 7, 82 Canterbury Rd Canterbury VIC 3126",
    "addr:housenumber":"shop;82",
    "addr:postcode":"3126",
    "addr:street":"Canterbury Rd",
    "iso:country":"AU",
    "sg:address":"Shop 7, 82 Canterbury Rd",
    "sg:city":"Canterbury",
    "sg:classifiers":[
        {
            "category":"Fast Food",
            "type":"Food & Drink"
        }
    ],
    "sg:phone":"+61 3 9830 1288",
    "sg:postcode":"3126",
    "sg:province":"VIC",
    "sg:tags":[
        "away",
        "take"
    ],
    "wof:name":"Tio Pepe",
    "wof:placetype":"venue"
},
  "geometry": {"coordinates":[145.06933593799999,-37.822769165],"type":"Point"}
}