{
  "type": "Feature",
  "properties": {
    "addr:full":"Lot 3 Kingswood Rd Albany WA 6330",
    "addr:postcode":"6330",
    "addr:street":"Kingswood Rd",
    "iso:country":"AU",
    "sg:address":"Lot 3 Kingswood Rd",
    "sg:city":"Albany",
    "sg:classifiers":[
        {
            "category":"Recreation",
            "subcategory":"Boat Charter",
            "type":"Entertainment"
        }
    ],
    "sg:phone":"+61 409 107 180",
    "sg:postcode":"6330",
    "sg:province":"WA",
    "wof:name":"Albany Whale Tours",
    "wof:placetype":"venue"
},
  "geometry": {"coordinates":[117.897041321,-34.934337616],"type":"Point"}
}