{
  "type": "Feature",
  "properties": {
    "addr:full":"8 King St Airport West VIC 3042",
    "addr:housenumber":"8",
    "addr:postcode":"3042",
    "addr:street":"King St",
    "iso:country":"AU",
    "sg:address":"8 King St",
    "sg:city":"Airport West",
    "sg:classifiers":[
        {
            "category":"Retail",
            "subcategory":"Storage",
            "type":"Services"
        }
    ],
    "sg:phone":"+61 411 817 207",
    "sg:postcode":"3042",
    "sg:province":"VIC",
    "sg:tags":[
        "removal",
        "furniture"
    ],
    "wof:name":"Faddoul Removalists",
    "wof:placetype":"venue"
},
  "geometry": {"coordinates":[144.89030456500001,-37.7233924866],"type":"Point"}
}