{
  "type": "Feature",
  "properties": {
    "addr:full":"4 Hibiscus Ave Carlingford NSW 2118",
    "addr:housenumber":"4",
    "addr:postcode":"2118",
    "addr:street":"Hibiscus Ave",
    "iso:country":"AU",
    "sg:address":"4 Hibiscus Ave",
    "sg:city":"Carlingford",
    "sg:classifiers":[
        {
            "category":"Education",
            "subcategory":"Junior College",
            "type":"Public Place"
        }
    ],
    "sg:phone":"+61 402 305 345",
    "sg:postcode":"2118",
    "sg:province":"NSW",
    "sg:tags":[
        "wholesaler",
        "school",
        "mfrs",
        "uniform"
    ],
    "wof:name":"School & Sports Hair Accessories",
    "wof:placetype":"venue"
},
  "geometry": {"coordinates":[151.03143310600001,-33.773475647],"type":"Point"}
}