{
  "type": "Feature",
  "properties": {
    "addr:full":"66 Collingwood St Osborne Park WA 6017",
    "addr:housenumber":"66",
    "addr:postcode":"6017",
    "addr:street":"Collingwood St",
    "iso:country":"AU",
    "sg:address":"66 Collingwood St",
    "sg:city":"Osborne Park",
    "sg:classifiers":[
        {
            "category":"Government",
            "subcategory":"Fire Station",
            "type":"Public Place"
        }
    ],
    "sg:phone":"+61 8 9244 3553",
    "sg:postcode":"6017",
    "sg:province":"WA",
    "sg:tags":[
        "spring",
        "shock",
        "absorbers",
        "suspension"
    ],
    "wof:name":"Old Man Emu",
    "wof:placetype":"venue"
},
  "geometry": {"coordinates":[115.81738281200001,-31.9049758911],"type":"Point"}
}