{
  "type": "Feature",
  "properties": {
    "addr:full":"316 Colchester Rd Kilsyth South VIC 3137",
    "addr:housenumber":"316",
    "addr:postcode":"3137",
    "addr:street":"Colchester Rd",
    "iso:country":"AU",
    "sg:address":"316 Colchester Rd",
    "sg:city":"Kilsyth South",
    "sg:classifiers":[
        {
            "category":"Social Services",
            "subcategory":"Child Care",
            "type":"Services"
        }
    ],
    "sg:phone":"+61 3 9720 4133",
    "sg:postcode":"3137",
    "sg:province":"VIC",
    "wof:name":"ABC Developmental Learning Centres Pty Ltd",
    "wof:placetype":"venue"
},
  "geometry": {"coordinates":[145.30221557600001,-37.8314704895],"type":"Point"}
}