{
  "type": "Feature",
  "properties": {
    "iso:country":"AU",
    "sg:address":"15 Yulong Ave",
    "sg:city":"Terrey Hills",
    "sg:classifiers":[
        {
            "category":"Personal",
            "subcategory":"Massage",
            "type":"Services"
        }
    ],
    "sg:phone":"+61 2 9486 3973",
    "sg:postcode":"2084",
    "sg:province":"NSW",
    "sg:tags":[
        "therapy"
    ],
    "wof:name":"Suzanne Bailey",
    "wof:placetype":"venue"
},
  "geometry": {"coordinates":[151.228424072,-33.6824264526],"type":"Point"}
}