{
  "type": "Feature",
  "properties": {
    "iso:country":"AU",
    "sg:address":"66 McCaughey St",
    "sg:city":"Turner",
    "sg:classifiers":[
        {
            "category":"Education",
            "subcategory":"Special Training",
            "type":"Public Place"
        }
    ],
    "sg:phone":"+61 2 6247 5027",
    "sg:postcode":"2612",
    "sg:province":"ACT",
    "sg:tags":[
        "tuition-educational"
    ],
    "sg:website":"http://www.afcanberra.com.au",
    "wof:name":"Alliance Francaise",
    "wof:placetype":"venue"
},
  "geometry": {"coordinates":[149.123123169,-35.2658538818],"type":"Point"}
}