{
  "type": "Feature",
  "properties": {
    "addr:full":"5 Warida Ave Malvern East VIC 3145",
    "addr:housenumber":"5",
    "addr:postcode":"3145",
    "addr:street":"Warida Ave",
    "iso:country":"AU",
    "sg:address":"5 Warida Ave",
    "sg:city":"Malvern East",
    "sg:classifiers":[
        {
            "category":"Building & Trades",
            "subcategory":"Construction",
            "type":"Services"
        }
    ],
    "sg:phone":"+61 425 770 605",
    "sg:postcode":"3145",
    "sg:province":"VIC",
    "sg:tags":[
        "polishing",
        "sanding",
        "floor"
    ],
    "wof:name":"Ednie G",
    "wof:placetype":"venue"
},
  "geometry": {"coordinates":[145.06614685100001,-37.87915802],"type":"Point"}
}