{
  "type": "Feature",
  "properties": {
    "iso:country":"AU",
    "sg:address":"17 Bayview St",
    "sg:city":"McMahons Point",
    "sg:classifiers":[
        {
            "category":"Professional",
            "subcategory":"Art Services",
            "type":"Services"
        }
    ],
    "sg:phone":"+61 2 9460 0012",
    "sg:postcode":"2060",
    "sg:province":"NSW",
    "sg:tags":[
        "interior",
        "decorator"
    ],
    "wof:name":"Kathy Abbott Interiors",
    "wof:placetype":"venue"
},
  "geometry": {"coordinates":[151.2059021,-33.8455696106],"type":"Point"}
}