{
  "type": "Feature",
  "properties": {
    "addr:full":"164 Maroondah Hwy Ringwood VIC 3134",
    "addr:housenumber":"164",
    "addr:postcode":"3134",
    "addr:street":"Maroondah Hwy",
    "iso:country":"AU",
    "sg:address":"164 Maroondah Hwy",
    "sg:city":"Ringwood",
    "sg:classifiers":[
        {
            "category":"Building & Trades",
            "subcategory":"Construction",
            "type":"Services"
        }
    ],
    "sg:phone":"+61 3 9870 4305",
    "sg:postcode":"3134",
    "sg:province":"VIC",
    "sg:tags":[
        "polishing",
        "sanding",
        "floor"
    ],
    "wof:name":"Complete Floor Service",
    "wof:placetype":"venue"
},
  "geometry": {"coordinates":[145.23492431599999,-37.8130073547],"type":"Point"}
}