{
  "type": "Feature",
  "properties": {
    "addr:full":"60 Stud Rd Dandenong VIC 3175",
    "addr:housenumber":"60",
    "addr:postcode":"3175",
    "addr:street":"Stud Rd",
    "iso:country":"AU",
    "sg:address":"60 Stud Rd",
    "sg:city":"Dandenong",
    "sg:classifiers":[
        {
            "category":"Health Services",
            "subcategory":"Health Practitioner",
            "type":"Services"
        }
    ],
    "sg:phone":"+61 3 9791 5344",
    "sg:postcode":"3175",
    "sg:province":"VIC",
    "sg:tags":[
        "homoeopath"
    ],
    "wof:name":"Paszkiewicz Jolanta Dr",
    "wof:placetype":"venue"
},
  "geometry": {"coordinates":[145.22198486299999,-37.9795188904],"type":"Point"}
}