{
  "type": "Feature",
  "properties": {
    "addr:full":"Brisbane Valley Hwy Toogoolawah QLD 4313",
    "addr:postcode":"4313",
    "addr:street":"Valley Hwy",
    "iso:country":"AU",
    "sg:address":"Brisbane Valley Hwy",
    "sg:city":"Toogoolawah",
    "sg:classifiers":[
        {
            "category":"Building & Trades",
            "subcategory":"Construction",
            "type":"Services"
        }
    ],
    "sg:phone":"+61 7 5423 5121",
    "sg:postcode":"4313",
    "sg:province":"QLD",
    "sg:tags":[
        "contractor"
    ],
    "wof:name":"Tones L G & G C",
    "wof:placetype":"venue"
},
  "geometry": {"coordinates":[152.38087463400001,-27.0906124115],"type":"Point"}
}