{
  "type": "Feature",
  "properties": {
    "addr:full":"101 Cobra St Dubbo NSW 2830",
    "addr:housenumber":"101",
    "addr:postcode":"2830",
    "addr:street":"Cobra St",
    "iso:country":"AU",
    "sg:address":"101 Cobra St",
    "sg:city":"Dubbo",
    "sg:classifiers":[
        {
            "category":"Travel",
            "subcategory":"Hotels & Motels",
            "type":"Entertainment"
        }
    ],
    "sg:phone":"+61 2 6882 4944",
    "sg:postcode":"2830",
    "sg:province":"NSW",
    "wof:name":"Homestead Motel Dubbo",
    "wof:placetype":"venue"
},
  "geometry": {"coordinates":[148.60043335,-32.2529983521],"type":"Point"}
}