{
  "type": "Feature",
  "properties": {
    "iso:country":"AU",
    "sg:address":"D&#039;Aguilar Hwy",
    "sg:city":"Yarraman",
    "sg:classifiers":[
        {
            "category":"Food & Beverages",
            "subcategory":"Groceries & Convenience Stores",
            "type":"Retail Goods"
        }
    ],
    "sg:phone":"+61 7 4163 8447",
    "sg:postcode":"4614",
    "sg:province":"QLD",
    "wof:name":"Herberts Food & Fuel",
    "wof:placetype":"venue"
},
  "geometry": {"coordinates":[151.98326110799999,-26.8468475342],"type":"Point"}
}