{
  "type": "Feature",
  "properties": {
    "iso:country":"AU",
    "sg:address":"Shed 1, Reservoir St",
    "sg:city":"Beenleigh",
    "sg:classifiers":[
        {
            "category":"Retail",
            "subcategory":"Auto Repair",
            "type":"Services"
        }
    ],
    "sg:phone":"+61 7 3807 3840",
    "sg:postcode":"4207",
    "sg:province":"QLD",
    "sg:tags":[
        "electrical"
    ],
    "wof:name":"Beenleigh Batteries",
    "wof:placetype":"venue"
},
  "geometry": {"coordinates":[153.197631836,-27.7181587219],"type":"Point"}
}