{
  "type": "Feature",
  "properties": {
    "addr:full":"PO Box 5 Roseworthy SA 5371",
    "addr:postcode":"5371",
    "iso:country":"AU",
    "sg:address":"PO Box 5",
    "sg:city":"Roseworthy",
    "sg:classifiers":[
        {
            "category":"Utilities",
            "subcategory":"Natural Gas",
            "type":"Services"
        }
    ],
    "sg:phone":"+61 8 8524 8078",
    "sg:postcode":"5371",
    "sg:province":"SA",
    "sg:tags":[
        "solid",
        "plasterer"
    ],
    "wof:name":"D J R Plasterers",
    "wof:placetype":"venue"
},
  "geometry": {"coordinates":[138.74957275400001,-34.5343704224],"type":"Point"}
}