{
  "type": "Feature",
  "properties": {
    "addr:full":"Suite 11, 456 St Kilda Rd South Yarra VIC 3141",
    "addr:housenumber":"456",
    "addr:postcode":"3141",
    "addr:street":"St Kilda Rd",
    "iso:country":"AU",
    "sg:address":"Suite 11, 456 St Kilda Rd",
    "sg:city":"South Yarra",
    "sg:classifiers":[
        {
            "category":"Health Services",
            "subcategory":"Optometrist",
            "type":"Services"
        }
    ],
    "sg:phone":"+61 3 9866 1702",
    "sg:postcode":"3141",
    "sg:province":"VIC",
    "wof:name":"Nathan & Slack Optometrists",
    "wof:placetype":"venue"
},
  "geometry": {"coordinates":[144.976364136,-37.8395652771],"type":"Point"}
}