{
  "type": "Feature",
  "properties": {
    "iso:country":"AU",
    "sg:address":"15 Aldridge Crt",
    "sg:city":"Hampton Park",
    "sg:classifiers":[
        {
            "category":"Building & Trades",
            "subcategory":"Landscaping Services",
            "type":"Services"
        }
    ],
    "sg:phone":"+61 419 582 461",
    "sg:postcode":"3976",
    "sg:province":"VIC",
    "sg:tags":[
        "designer",
        "landscape",
        "contractor"
    ],
    "wof:name":"B.A.S. Garden Care",
    "wof:placetype":"venue"
},
  "geometry": {"coordinates":[145.28062439000001,-38.0321311951],"type":"Point"}
}