{
  "type": "Feature",
  "properties": {
    "addr:full":"U3/ 1601 Main Rd Research VIC 3095",
    "addr:housenumber":"1601",
    "addr:postcode":"3095",
    "addr:street":"U3 /;Main Rd",
    "iso:country":"AU",
    "sg:address":"U3/ 1601 Main Rd",
    "sg:city":"Research",
    "sg:classifiers":[
        {
            "category":"Professional",
            "subcategory":"Employment Agencies",
            "type":"Services"
        }
    ],
    "sg:phone":"+61 3 9437 1433",
    "sg:postcode":"3095",
    "sg:province":"VIC",
    "wof:name":"Aplus Childcare Personnel",
    "wof:placetype":"venue"
},
  "geometry": {"coordinates":[145.185836792,-37.7011642456],"type":"Point"}
}