{
  "type": "Feature",
  "properties": {
    "addr:full":"296 Grange Rd Flinders Park SA 5025",
    "addr:housenumber":"296",
    "addr:postcode":"5025",
    "addr:street":"Grange Rd",
    "iso:country":"AU",
    "sg:address":"296 Grange Rd",
    "sg:city":"Flinders Park",
    "sg:classifiers":[
        {
            "category":"Professional",
            "type":"Services"
        }
    ],
    "sg:phone":"+61 8 8234 8970",
    "sg:postcode":"5025",
    "sg:province":"SA",
    "sg:tags":[
        "overlocking",
        "rug",
        "carpet"
    ],
    "wof:name":"Carpet Mart",
    "wof:placetype":"venue"
},
  "geometry": {"coordinates":[138.53352355999999,-34.9055709839],"type":"Point"}
}