{
  "type": "Feature",
  "properties": {
    "addr:full":"Blackwood Rd Ballan VIC 3342",
    "addr:postcode":"3342",
    "addr:street":"Blackwood Rd",
    "iso:country":"AU",
    "sg:address":"Blackwood Rd",
    "sg:city":"Ballan",
    "sg:classifiers":[
        {
            "category":"Sports & Exercise",
            "subcategory":"Gym",
            "type":"Entertainment"
        }
    ],
    "sg:phone":"+61 3 5368 1265",
    "sg:postcode":"3342",
    "sg:province":"VIC",
    "sg:tags":[
        "health",
        "fitness"
    ],
    "wof:name":"Ballan Outdoor Pool",
    "wof:placetype":"venue"
},
  "geometry": {"coordinates":[144.23085,-37.598305],"type":"Point"}
}