{
  "type": "Feature",
  "properties": {
    "iso:country":"AU",
    "sg:address":"145D Rockingham Rd",
    "sg:city":"Hamilton Hill",
    "sg:classifiers":[
        {
            "category":"Professional",
            "subcategory":"Accounting & Tax Preparation",
            "type":"Services"
        }
    ],
    "sg:phone":"+61 8 9418 2255",
    "sg:postcode":"6163",
    "sg:province":"WA",
    "sg:tags":[
        "accountant",
        "auditor"
    ],
    "wof:name":"Beaver Vos",
    "wof:placetype":"venue"
},
  "geometry": {"coordinates":[115.77851099999999,-32.087177],"type":"Point"}
}