{
  "type": "Feature",
  "properties": {
    "addr:full":"Fact 8, 65 Canterbury Rd Kilsyth VIC 3137",
    "addr:housenumber":"8 65",
    "addr:postcode":"3137",
    "addr:street":"Fact;Canterbury Rd",
    "iso:country":"AU",
    "sg:address":"Fact 8, 65 Canterbury Rd",
    "sg:city":"Kilsyth",
    "sg:classifiers":[
        {
            "category":"Building & Trades",
            "subcategory":"Pest Control",
            "type":"Services"
        }
    ],
    "sg:phone":"+61 433 291 250",
    "sg:postcode":"3137",
    "sg:province":"VIC",
    "wof:name":"First Choice Pest Control",
    "wof:placetype":"venue"
},
  "geometry": {"coordinates":[145.32728576700001,-37.8151245117],"type":"Point"}
}