{
  "type": "Feature",
  "properties": {
    "addr:full":"34a Seventh St East Mildura VIC 3500",
    "addr:housenumber":"34a",
    "addr:postcode":"3500",
    "addr:street":"Seventh St East",
    "iso:country":"AU",
    "sg:address":"34a Seventh St East",
    "sg:city":"Mildura",
    "sg:classifiers":[
        {
            "category":"Farming",
            "subcategory":"Vineyard",
            "type":"Manufacturing & Wholesale Goods"
        }
    ],
    "sg:phone":"+61 3 5022 7255",
    "sg:postcode":"3500",
    "sg:province":"VIC",
    "sg:tags":[
        "winery"
    ],
    "wof:name":"Tall Poppy Wines",
    "wof:placetype":"venue"
},
  "geometry": {"coordinates":[142.154098511,-34.2107391357],"type":"Point"}
}