{
  "type": "Feature",
  "properties": {
    "addr:full":"7 Fran Crs Rosanna VIC 3084",
    "addr:housenumber":"7",
    "addr:postcode":"3084",
    "addr:street":"Fran Crs",
    "iso:country":"AU",
    "sg:address":"7 Fran Crs",
    "sg:city":"Rosanna",
    "sg:classifiers":[
        {
            "category":"Wholesale",
            "subcategory":"Durable Goods & Equipment",
            "type":"Manufacturing & Wholesale Goods"
        }
    ],
    "sg:phone":"+61 3 9457 6452",
    "sg:postcode":"3084",
    "sg:province":"VIC",
    "sg:tags":[
        "degreasing"
    ],
    "wof:name":"Waldhaus Pty Ltd",
    "wof:placetype":"venue"
},
  "geometry": {"coordinates":[145.106765747,-37.75623703],"type":"Point"}
}