{
  "type": "Feature",
  "properties": {
    "addr:full":"Shop T381A Erina Fair Shopng Cntr, Terrigal Drv Erina NSW 2250",
    "addr:postcode":"2250",
    "addr:street":"Terrigal Drv",
    "iso:country":"AU",
    "sg:address":"Shop T381A Erina Fair Shopng Cntr, Terrigal Drv",
    "sg:city":"Erina",
    "sg:classifiers":[
        {
            "category":"Travel",
            "subcategory":"Travel Agent",
            "type":"Entertainment"
        }
    ],
    "sg:phone":"+61 13 18 66",
    "sg:postcode":"2250",
    "sg:province":"NSW",
    "sg:tags":[
        "consultant"
    ],
    "wof:name":"Flight Centre",
    "wof:placetype":"venue"
},
  "geometry": {"coordinates":[151.39523315400001,-33.4345855713],"type":"Point"}
}