{
  "type": "Feature",
  "properties": {
    "addr:full":"Suite 300/ 45 Glenferrie Rd Malvern VIC 3144",
    "addr:housenumber":"300 / 45",
    "addr:postcode":"3144",
    "addr:street":"Glenferrie Rd",
    "iso:country":"AU",
    "sg:address":"Suite 300/ 45 Glenferrie Rd",
    "sg:city":"Malvern",
    "sg:classifiers":[
        {
            "category":"Social Services",
            "type":"Services"
        }
    ],
    "sg:phone":"+61 1300 301 828",
    "sg:postcode":"3144",
    "sg:province":"VIC",
    "sg:tags":[
        "domestic",
        "help"
    ],
    "wof:name":"Professional Home Sitters",
    "wof:placetype":"venue"
},
  "geometry": {"coordinates":[145.02792358400001,-37.8638496399],"type":"Point"}
}