{
  "type": "Feature",
  "properties": {
    "addr:full":"239 Sackville St Fairfield NSW 2165",
    "addr:housenumber":"239",
    "addr:postcode":"2165",
    "addr:street":"Sackville St",
    "iso:country":"AU",
    "sg:address":"239 Sackville St",
    "sg:city":"Fairfield",
    "sg:classifiers":[
        {
            "category":"Education",
            "subcategory":"Special Training",
            "type":"Public Place"
        }
    ],
    "sg:phone":"+61 2 9727 9199",
    "sg:postcode":"2165",
    "sg:province":"NSW",
    "sg:tags":[
        "development"
    ],
    "wof:name":"Fairfield Training Centre",
    "wof:placetype":"venue"
},
  "geometry": {"coordinates":[150.949020386,-33.8674583435],"type":"Point"}
}