{
  "type": "Feature",
  "properties": {
    "addr:full":"47 Stenhouse Drv Cameron Park NSW 2285",
    "addr:housenumber":"47",
    "addr:postcode":"2285",
    "addr:street":"Stenhouse Drv",
    "iso:country":"AU",
    "sg:address":"47 Stenhouse Drv",
    "sg:city":"Cameron Park",
    "sg:classifiers":[
        {
            "category":"Industrial Area",
            "type":"Public Place"
        }
    ],
    "sg:phone":"+61 2 4955 1600",
    "sg:postcode":"2285",
    "sg:province":"NSW",
    "sg:tags":[
        "rural",
        "shed"
    ],
    "wof:name":"Compass Sheds & Garages",
    "wof:placetype":"venue"
},
  "geometry": {"coordinates":[151.60310363799999,-32.8950462341],"type":"Point"}
}