{
  "type": "Feature",
  "properties": {
    "addr:full":"Shop 6 Wapengo St Bermagui NSW 2546",
    "addr:housenumber":"shop 6",
    "addr:postcode":"2546",
    "addr:street":"Wapengo St",
    "iso:country":"AU",
    "sg:address":"Shop 6 Wapengo St",
    "sg:city":"Bermagui",
    "sg:classifiers":[
        {
            "category":"Health Services",
            "subcategory":"Doctor",
            "type":"Services"
        }
    ],
    "sg:phone":"+61 2 6493 4233",
    "sg:postcode":"2546",
    "sg:province":"NSW",
    "sg:tags":[
        "medical",
        "practitioner"
    ],
    "wof:name":"Wapengo Street Surgery",
    "wof:placetype":"venue"
},
  "geometry": {"coordinates":[150.06546020499999,-36.4223403931],"type":"Point"}
}