{
  "type": "Feature",
  "properties": {
    "addr:full":"7 Alma St Gympie QLD 4570",
    "addr:housenumber":"7",
    "addr:postcode":"4570",
    "addr:street":"Alma St",
    "iso:country":"AU",
    "sg:address":"7 Alma St",
    "sg:city":"Gympie",
    "sg:classifiers":[
        {
            "category":"Government",
            "subcategory":"Post Office",
            "type":"Public Place"
        }
    ],
    "sg:phone":"+61 7 5482 6263",
    "sg:postcode":"4570",
    "sg:province":"QLD",
    "sg:tags":[
        "yoga"
    ],
    "wof:name":"Gympie Yoga & Relaxation Centre",
    "wof:placetype":"venue"
},
  "geometry": {"coordinates":[152.66682434099999,-26.1898479462],"type":"Point"}
}