{
  "type": "Feature",
  "properties": {
    "iso:country":"AU",
    "sg:address":"21 Clyde St",
    "sg:city":"Ferntree Gully",
    "sg:classifiers":[
        {
            "category":"Building & Trades",
            "subcategory":"Equipment Rental",
            "type":"Services"
        }
    ],
    "sg:phone":"+61 3 9752 3488",
    "sg:postcode":"3156",
    "sg:province":"VIC",
    "sg:tags":[
        "repairing",
        "changing",
        "retreading",
        "tyre"
    ],
    "wof:name":"Tyrequip",
    "wof:placetype":"venue"
},
  "geometry": {"coordinates":[145.26832580600001,-37.8818511963],"type":"Point"}
}