{
  "type": "Feature",
  "properties": {
    "addr:full":"223 Victoria Rd Gladesville NSW 2111",
    "addr:housenumber":"223",
    "addr:postcode":"2111",
    "addr:street":"Victoria Rd",
    "iso:country":"AU",
    "sg:address":"223 Victoria Rd",
    "sg:city":"Gladesville",
    "sg:classifiers":[
        {
            "category":"Real Estate",
            "subcategory":"Real Estate Agent",
            "type":"Services"
        }
    ],
    "sg:phone":"+61 2 9817 6688",
    "sg:postcode":"2111",
    "sg:province":"NSW",
    "wof:name":"Raine & Horne Gladesville",
    "wof:placetype":"venue"
},
  "geometry": {"coordinates":[151.127075195,-33.8319816589],"type":"Point"}
}