{
  "type": "Feature",
  "properties": {
    "addr:full":"Ellem Crt Diddillibah QLD 4559",
    "addr:postcode":"4559",
    "addr:street":"Ellem",
    "iso:country":"AU",
    "sg:address":"Ellem Crt",
    "sg:city":"Diddillibah",
    "sg:classifiers":[
        {
            "category":"Building & Trades",
            "subcategory":"Cleaning & Sanitation",
            "type":"Services"
        }
    ],
    "sg:phone":"+61 7 5450 8166",
    "sg:postcode":"4559",
    "sg:province":"QLD",
    "sg:tags":[
        "industrial",
        "commercial",
        "contractor"
    ],
    "wof:name":"Pearlman Cleaning Services Pty Ltd",
    "wof:placetype":"venue"
},
  "geometry": {"coordinates":[153.0209198,-26.6488933563],"type":"Point"}
}