{
  "type": "Feature",
  "properties": {
    "addr:full":"Level 4, 100 Harbour Esp Docklands VIC 3008",
    "addr:housenumber":"100",
    "addr:postcode":"3008",
    "addr:street":"Harbour Esp",
    "iso:country":"AU",
    "sg:address":"Level 4, 100",
    "sg:city":"Harbour Esp Docklands",
    "sg:classifiers":[
        {
            "category":"Health Services",
            "subcategory":"Health Practitioner",
            "type":"Services"
        }
    ],
    "sg:phone":"+61 3 8615 9644",
    "sg:postcode":"3008",
    "sg:province":"VIC",
    "sg:tags":[
        "physiotherapist"
    ],
    "wof:name":"Melbourne Myotherapy",
    "wof:placetype":"venue"
},
  "geometry": {"coordinates":[144.94499206500001,-37.8152694702],"type":"Point"}
}