{
  "type": "Feature",
  "properties": {
    "addr:full":"Francis St Injinoo via Bamaga Injinoo QLD 4876",
    "addr:postcode":"4876",
    "addr:street":"Francis St Injinoo Via Bamaga",
    "iso:country":"AU",
    "sg:address":"Francis St",
    "sg:city":"Injinoo via Bamaga Injinoo",
    "sg:classifiers":[
        {
            "category":"Education",
            "subcategory":"School",
            "type":"Public Place"
        }
    ],
    "sg:phone":"+61 7 4069 3131",
    "sg:postcode":"4876",
    "sg:province":"QLD",
    "sg:tags":[
        "state",
        "except",
        "nsw"
    ],
    "wof:name":"Northern Peninsula Area State College Preschool",
    "wof:placetype":"venue"
},
  "geometry": {"coordinates":[142.33592224099999,-10.8995666504],"type":"Point"}
}