{
  "type": "Feature",
  "properties": {
    "iso:country":"AU",
    "sg:address":"PO Box 1886",
    "sg:city":"Toowoomba",
    "sg:classifiers":[
        {
            "category":"Utilities",
            "subcategory":"Refuse",
            "type":"Services"
        }
    ],
    "sg:phone":"+61 427 063 201",
    "sg:postcode":"4352",
    "sg:province":"QLD",
    "sg:tags":[
        "disposal",
        "reduction",
        "waste"
    ],
    "wof:name":"Smart Skip",
    "wof:placetype":"venue"
},
  "geometry": {"coordinates":[151.953293,-27.561449],"type":"Point"}
}