{
  "type": "Feature",
  "properties": {
    "addr:full":"11- 17 Leveson St North Melbourne VIC 3051",
    "addr:housenumber":"17",
    "addr:postcode":"3051",
    "addr:street":"Leveson St",
    "iso:country":"AU",
    "sg:address":"11- 17 Leveson St",
    "sg:city":"North Melbourne",
    "sg:classifiers":[
        {
            "category":"Professional",
            "type":"Services"
        }
    ],
    "sg:phone":"+61 3 9321 7000",
    "sg:postcode":"3051",
    "sg:province":"VIC",
    "sg:tags":[
        "courier"
    ],
    "wof:name":"Cash Couriers",
    "wof:placetype":"venue"
},
  "geometry": {"coordinates":[144.95069885300001,-37.8045768738],"type":"Point"}
}