{
  "type": "Feature",
  "properties": {
    "addr:full":"34 Edols St North Geelong VIC 3215",
    "addr:housenumber":"34",
    "addr:postcode":"3215",
    "addr:street":"Edols St",
    "iso:country":"AU",
    "sg:address":"34 Edols St",
    "sg:city":"North Geelong",
    "sg:classifiers":[
        {
            "category":"Utilities",
            "subcategory":"Refuse",
            "type":"Services"
        }
    ],
    "sg:phone":"+61 1300 308 172",
    "sg:postcode":"3215",
    "sg:province":"VIC",
    "sg:tags":[
        "disposal",
        "reduction",
        "waste"
    ],
    "wof:name":"QEST Environmental",
    "wof:placetype":"venue"
},
  "geometry": {"coordinates":[144.344406128,-38.1131019592],"type":"Point"}
}