{
  "type": "Feature",
  "properties": {
    "iso:country":"AU",
    "sg:address":"29 Patterson Rd",
    "sg:city":"Bentleigh",
    "sg:classifiers":[
        {
            "category":"Wholesale",
            "subcategory":"Medical Equipment & Supplies",
            "type":"Manufacturing & Wholesale Goods"
        }
    ],
    "sg:phone":"+61 3 9563 9466",
    "sg:postcode":"3204",
    "sg:province":"VIC",
    "sg:tags":[
        "dental"
    ],
    "wof:name":"Bourke Dental Supply",
    "wof:placetype":"venue"
},
  "geometry": {"coordinates":[145.033752,-37.925297],"type":"Point"}
}