{
  "type": "Feature",
  "properties": {
    "addr:full":"Suite 4, Level 5 424 St Kilda Rd Melbourne VIC 3000",
    "addr:housenumber":"424",
    "addr:postcode":"3000",
    "addr:street":"St Kilda Rd",
    "iso:country":"AU",
    "sg:address":"Suite 4, Level 5 424 St Kilda Rd",
    "sg:city":"Melbourne",
    "sg:classifiers":[
        {
            "category":"Banks & Credit Unions",
            "subcategory":"Investment Brokerage",
            "type":"Services"
        }
    ],
    "sg:phone":"+61 3 9866 6627",
    "sg:postcode":"3000",
    "sg:province":"VIC",
    "sg:tags":[
        "debt",
        "collection"
    ],
    "wof:name":"Repcol-Austwide (Vic) Pty Ltd",
    "wof:placetype":"venue"
},
  "geometry": {"coordinates":[144.97528076200001,-37.8365516663],"type":"Point"}
}