{
  "type": "Feature",
  "properties": {
    "iso:country":"AU",
    "sg:address":"Unit 2 184 Pier St",
    "sg:city":"Perth",
    "sg:classifiers":[
        {
            "category":"Retail",
            "subcategory":"Laundry & Dry Cleaning",
            "type":"Services"
        }
    ],
    "sg:phone":"+61 1300 555 776",
    "sg:postcode":"6000",
    "sg:province":"WA",
    "wof:name":"Ecoclean",
    "wof:placetype":"venue"
},
  "geometry": {"coordinates":[115.864646912,-31.951385498],"type":"Point"}
}