{
  "type": "Feature",
  "properties": {
    "iso:country":"AU",
    "sg:address":"843 Creswick Rd",
    "sg:city":"Wendouree",
    "sg:classifiers":[
        {
            "category":"Retail",
            "subcategory":"Auto Rental",
            "type":"Services"
        }
    ],
    "sg:phone":"+61 3 5338 1883",
    "sg:postcode":"3355",
    "sg:province":"VIC",
    "sg:tags":[
        "car",
        "hire",
        "minibus"
    ],
    "wof:name":"Budget Truck Rentals",
    "wof:placetype":"venue"
},
  "geometry": {"coordinates":[143.84487899999999,-37.523193],"type":"Point"}
}