{
  "type": "Feature",
  "properties": {
    "addr:full":"53 Wairoa Ave North Bondi NSW 2026",
    "addr:housenumber":"53",
    "addr:postcode":"2026",
    "addr:street":"Wairoa Ave",
    "iso:country":"AU",
    "sg:address":"53 Wairoa Ave",
    "sg:city":"North Bondi",
    "sg:classifiers":[
        {
            "category":"Health Services",
            "subcategory":"Doctor",
            "type":"Services"
        }
    ],
    "sg:phone":"+61 2 9130 8176",
    "sg:postcode":"2026",
    "sg:province":"NSW",
    "sg:tags":[
        "medical",
        "practitioner"
    ],
    "wof:name":"Springer T",
    "wof:placetype":"venue"
},
  "geometry": {"coordinates":[151.28016662600001,-33.8860664368],"type":"Point"}
}