{
  "type": "Feature",
  "properties": {
    "addr:full":"Grigg Rd Koondrook VIC 3580",
    "addr:postcode":"3580",
    "addr:street":"Grigg Rd",
    "iso:country":"AU",
    "sg:address":"Grigg Rd",
    "sg:city":"Koondrook",
    "sg:classifiers":[
        {
            "category":"Parking",
            "subcategory":"Lot",
            "type":"Transportation"
        }
    ],
    "sg:phone":"+61 3 5453 2523",
    "sg:postcode":"3580",
    "sg:province":"VIC",
    "sg:tags":[
        "vegetable",
        "packing",
        "fruit",
        "pack"
    ],
    "wof:name":"Border Packers Pty Ltd",
    "wof:placetype":"venue"
},
  "geometry": {"coordinates":[144.12448120100001,-35.6311454773],"type":"Point"}
}