{
  "type": "Feature",
  "properties": {
    "addr:full":"15 Antill Rd Mt Pritchard NSW 2170",
    "addr:housenumber":"15",
    "addr:postcode":"2170",
    "addr:street":"Antill Rd;Pritchard",
    "iso:country":"AU",
    "sg:address":"15 Antill Rd",
    "sg:city":"Mt Pritchard",
    "sg:classifiers":[
        {
            "category":"Professional",
            "type":"Services"
        }
    ],
    "sg:phone":"+61 414 999 353",
    "sg:postcode":"2170",
    "sg:province":"NSW",
    "sg:tags":[
        "transport"
    ],
    "wof:name":"Ecko Transport",
    "wof:placetype":"venue"
},
  "geometry": {"coordinates":[150.907592773,-33.8987121582],"type":"Point"}
}