{
  "type": "Feature",
  "properties": {
    "addr:full":"PO Box 6160 Kincumber NSW 2251",
    "addr:postcode":"2251",
    "iso:country":"AU",
    "sg:address":"PO Box 6160",
    "sg:city":"Kincumber",
    "sg:classifiers":[
        {
            "category":"Organizations",
            "subcategory":"Professional Association",
            "type":"Services"
        }
    ],
    "sg:phone":"+61 1300 303 769",
    "sg:postcode":"2251",
    "sg:province":"NSW",
    "sg:tags":[
        "web",
        "internet"
    ],
    "wof:name":"Virtual Property Developments Pty Ltd",
    "wof:placetype":"venue"
},
  "geometry": {"coordinates":[151.38150024399999,-33.4676513672],"type":"Point"}
}