{
  "type": "Feature",
  "properties": {
    "addr:full":"2- 46 Catalano Rd Canning Vale WA 6155",
    "addr:housenumber":"46",
    "addr:postcode":"6155",
    "addr:street":"2;Catalano Rd",
    "iso:country":"AU",
    "sg:address":"2- 46 Catalano Rd",
    "sg:city":"Canning Vale",
    "sg:classifiers":[
        {
            "category":"Wholesale",
            "subcategory":"Office Equipment",
            "type":"Manufacturing & Wholesale Goods"
        }
    ],
    "sg:phone":"+61 8 9256 3522",
    "sg:postcode":"6155",
    "sg:province":"WA",
    "sg:tags":[
        "staple",
        "stapling"
    ],
    "wof:name":"Jamieson Fasteners",
    "wof:placetype":"venue"
},
  "geometry": {"coordinates":[115.902428,-32.06081],"type":"Point"}
}