{
  "type": "Feature",
  "properties": {
    "addr:full":"60 Mockridge Rd Rokeby TAS 7019",
    "addr:housenumber":"60",
    "addr:postcode":"7019",
    "addr:street":"Mockridge Rd",
    "iso:country":"AU",
    "sg:address":"60 Mockridge Rd",
    "sg:city":"Rokeby",
    "sg:classifiers":[
        {
            "category":"Manufacturing",
            "subcategory":"Tools & Machinery",
            "type":"Manufacturing & Wholesale Goods"
        }
    ],
    "sg:phone":"+61 437 399 260",
    "sg:postcode":"7019",
    "sg:province":"TAS",
    "sg:tags":[
        "earth",
        "excavating",
        "moving",
        "equipment"
    ],
    "wof:name":"Cap Excavations &Tipper Hire",
    "wof:placetype":"venue"
},
  "geometry": {"coordinates":[147.44125366200001,-42.8893241882],"type":"Point"}
}