{
  "type": "Feature",
  "properties": {
    "addr:full":"2/ 35 Priest St Alice Springs NT 0870",
    "addr:housenumber":"/ 35",
    "addr:postcode":"nt 0870",
    "addr:street":"Priest St",
    "iso:country":"AU",
    "sg:address":"2/ 35 Priest St",
    "sg:city":"Alice Springs",
    "sg:classifiers":[
        {
            "category":"Building & Trades",
            "subcategory":"Landscaping Services",
            "type":"Services"
        }
    ],
    "sg:phone":"+61 8 8952 3389",
    "sg:postcode":"0870",
    "sg:province":"NT",
    "sg:tags":[
        "consultant"
    ],
    "wof:name":"Warla Building Consultants",
    "wof:placetype":"venue"
},
  "geometry": {"coordinates":[133.87135314899999,-23.6897773743],"type":"Point"}
}