{
  "type": "Feature",
  "properties": {
    "iso:country":"AU",
    "sg:address":"30 Gymea Bay Rd",
    "sg:city":"Gymea",
    "sg:classifiers":[
        {
            "category":"Food & Beverages",
            "subcategory":"Meat & Fish",
            "type":"Retail Goods"
        }
    ],
    "sg:phone":"+61 2 9524 6888",
    "sg:postcode":"2227",
    "sg:province":"NSW",
    "sg:tags":[
        "seafood"
    ],
    "wof:name":"Gourmet King Seafood Grill",
    "wof:placetype":"venue"
},
  "geometry": {"coordinates":[151.08538818400001,-34.0339927673],"type":"Point"}
}