{
  "type": "Feature",
  "properties": {
    "iso:country":"AU",
    "sg:address":"7 Dino Crt",
    "sg:city":"Junortoun",
    "sg:classifiers":[
        {
            "category":"Professional",
            "type":"Services"
        }
    ],
    "sg:phone":"+61 3 5449 3835",
    "sg:postcode":"3551",
    "sg:province":"VIC",
    "sg:tags":[
        "transport"
    ],
    "wof:name":"Ivermac Holdings Pty Ltd",
    "wof:placetype":"venue"
},
  "geometry": {"coordinates":[144.386550903,-36.7693710327],"type":"Point"}
}