{
  "type": "Feature",
  "properties": {
    "addr:full":"16A Scarba St Coffs Harbour NSW 2450",
    "addr:housenumber":"16a",
    "addr:postcode":"2450",
    "addr:street":"Scarba St",
    "iso:country":"AU",
    "sg:address":"16A Scarba St",
    "sg:city":"Coffs Harbour",
    "sg:classifiers":[
        {
            "category":"Health Services",
            "subcategory":"Doctor",
            "type":"Services"
        }
    ],
    "sg:phone":"+61 2 6651 2827",
    "sg:postcode":"2450",
    "sg:province":"NSW",
    "sg:tags":[
        "medical",
        "practitioner"
    ],
    "wof:name":"Morrissey Mark J Dr",
    "wof:placetype":"venue"
},
  "geometry": {"coordinates":[153.11502100000001,-30.300259],"type":"Point"}
}