{
  "type": "Feature",
  "properties": {
    "iso:country":"AU",
    "sg:address":"McLoughlin St",
    "sg:city":"Scone",
    "sg:classifiers":[
        {
            "category":"Home & Garden",
            "subcategory":"Garden Supply",
            "type":"Retail Goods"
        }
    ],
    "sg:phone":"+61 427 262 181",
    "sg:postcode":"2337",
    "sg:province":"NSW",
    "sg:tags":[
        "landscape"
    ],
    "wof:name":"Scone Landscape Supplies",
    "wof:placetype":"venue"
},
  "geometry": {"coordinates":[150.869064331,-32.0406227112],"type":"Point"}
}