{
  "type": "Feature",
  "properties": {
    "addr:full":"73 Gordon St Brighton-le-Sands NSW 2216",
    "addr:housenumber":"73",
    "addr:postcode":"2216",
    "addr:street":"Gordon St",
    "iso:country":"AU",
    "sg:address":"73 Gordon St",
    "sg:city":"Brighton-le-Sands",
    "sg:classifiers":[
        {
            "category":"Building & Trades",
            "subcategory":"Landscaping Services",
            "type":"Services"
        }
    ],
    "sg:phone":"+61 404 806 067",
    "sg:postcode":"2216",
    "sg:province":"NSW",
    "sg:tags":[
        "consultant"
    ],
    "wof:name":"Resolve Building Consultancy Services",
    "wof:placetype":"venue"
},
  "geometry": {"coordinates":[151.15267900000001,-33.957394],"type":"Point"}
}