{
  "type": "Feature",
  "properties": {
    "addr:full":"334 Victoria Rd Gladesville NSW 2111",
    "addr:housenumber":"334",
    "addr:postcode":"2111",
    "addr:street":"Victoria Rd",
    "iso:country":"AU",
    "sg:address":"334 Victoria Rd",
    "sg:city":"Gladesville",
    "sg:classifiers":[
        {
            "category":"Manufacturing",
            "subcategory":"Furniture",
            "type":"Manufacturing & Wholesale Goods"
        }
    ],
    "sg:phone":"+61 2 9817 6999",
    "sg:postcode":"2111",
    "sg:province":"NSW",
    "sg:tags":[
        "builder",
        "designer",
        "custom"
    ],
    "wof:name":"Wildwood Designs",
    "wof:placetype":"venue"
},
  "geometry": {"coordinates":[151.126052856,-33.826335907],"type":"Point"}
}