{
  "type": "Feature",
  "properties": {
    "iso:country":"AU",
    "sg:address":"315 Wharf Rd",
    "sg:city":"Newcastle",
    "sg:classifiers":[
        {
            "category":"Government",
            "subcategory":"Court House",
            "type":"Public Place"
        }
    ],
    "sg:phone":"+61 2 4927 1888",
    "sg:postcode":"2300",
    "sg:province":"NSW",
    "sg:tags":[
        "personal",
        "marriage",
        "family",
        "counselling"
    ],
    "wof:name":"Newcastle City Church",
    "wof:placetype":"venue"
},
  "geometry": {"coordinates":[151.774246,-32.92548],"type":"Point"}
}