{
  "type": "Feature",
  "properties": {
    "iso:country":"AU",
    "sg:address":"Unit 1/ 1868- 1874 Marmion Ave",
    "sg:city":"Clarkson",
    "sg:classifiers":[
        {
            "category":"Real Estate",
            "subcategory":"Real Estate Agent",
            "type":"Services"
        }
    ],
    "sg:phone":"+61 8 9407 7211",
    "sg:postcode":"6030",
    "sg:province":"WA",
    "wof:name":"CENTURY 21 Gold Key Realty",
    "wof:placetype":"venue"
},
  "geometry": {"coordinates":[115.715240478,-31.6904964447],"type":"Point"}
}