{
  "type": "Feature",
  "properties": {
    "iso:country":"AU",
    "sg:address":"3 Main St",
    "sg:city":"Beenleigh",
    "sg:classifiers":[
        {
            "category":"Banks & Credit Unions",
            "subcategory":"Financial Services",
            "type":"Services"
        }
    ],
    "sg:phone":"+61 7 3807 1187",
    "sg:postcode":"4207",
    "sg:province":"QLD",
    "sg:tags":[
        "financier"
    ],
    "wof:name":"Fast Access Finance Beenleigh",
    "wof:placetype":"venue"
},
  "geometry": {"coordinates":[153.202392578,-27.7163963318],"type":"Point"}
}