{
  "type": "Feature",
  "properties": {
    "addr:full":"49 Furnace Rd Welshpool WA 6106",
    "addr:housenumber":"49",
    "addr:postcode":"6106",
    "addr:street":"Furnace Rd",
    "iso:country":"AU",
    "sg:address":"49 Furnace Rd",
    "sg:city":"Welshpool",
    "sg:classifiers":[
        {
            "category":"Retail",
            "subcategory":"Storage",
            "type":"Services"
        }
    ],
    "sg:phone":"+61 8 9258 5277",
    "sg:postcode":"6106",
    "sg:province":"WA",
    "sg:tags":[
        "shelving",
        "system"
    ],
    "wof:name":"Allwest Racking Solutions",
    "wof:placetype":"venue"
},
  "geometry": {"coordinates":[115.952003479,-31.9956512451],"type":"Point"}
}