{
  "type": "Feature",
  "properties": {
    "addr:full":"Cnr Wharf & Boyd Sts Tweed Heads NSW 2485",
    "addr:postcode":"2485",
    "addr:street":"Cnr;Sts",
    "iso:country":"AU",
    "sg:address":"Cnr Wharf & Boyd Sts",
    "sg:city":"Tweed Heads",
    "sg:classifiers":[
        {
            "category":"Autos & Motor Vehicles",
            "subcategory":"Automobile Sales",
            "type":"Retail Goods"
        }
    ],
    "sg:phone":"+61 7 5523 7400",
    "sg:postcode":"2485",
    "sg:province":"NSW",
    "sg:tags":[
        "car",
        "new"
    ],
    "wof:name":"Von Bibra Kia",
    "wof:placetype":"venue"
},
  "geometry": {"coordinates":[153.54066467300001,-28.179693222],"type":"Point"}
}