{
  "type": "Feature",
  "properties": {
    "iso:country":"AU",
    "sg:address":"Shop 12A Westfield S/C Cnr Aird & Marsden St",
    "sg:city":"Parramatta",
    "sg:classifiers":[
        {
            "category":"Personal",
            "type":"Services"
        }
    ],
    "sg:phone":"+61 2 9806 0202",
    "sg:postcode":"2150",
    "sg:province":"NSW",
    "sg:tags":[
        "reducing",
        "treatment",
        "weight"
    ],
    "wof:name":"Fernwood Slimplicity",
    "wof:placetype":"venue"
},
  "geometry": {"coordinates":[151.000854492,-33.8173675537],"type":"Point"}
}