{
  "type": "Feature",
  "properties": {
    "addr:full":"2 Monaco St Doncaster VIC 3108",
    "addr:housenumber":"2",
    "addr:postcode":"3108",
    "addr:street":"Monaco St",
    "iso:country":"AU",
    "sg:address":"2 Monaco St",
    "sg:city":"Doncaster",
    "sg:classifiers":[
        {
            "category":"Retail",
            "subcategory":"Driving School",
            "type":"Services"
        }
    ],
    "sg:phone":"+61 3 9857 6418",
    "sg:postcode":"3108",
    "sg:province":"VIC",
    "wof:name":"Bert Chapman Driving School",
    "wof:placetype":"venue"
},
  "geometry": {"coordinates":[145.11109924300001,-37.7809410095],"type":"Point"}
}