{
  "type": "Feature",
  "properties": {
    "addr:full":"5 Davis Rd Wetherill Park NSW 2164",
    "addr:housenumber":"5",
    "addr:postcode":"2164",
    "addr:street":"Davis Rd",
    "iso:country":"AU",
    "sg:address":"5 Davis Rd",
    "sg:city":"Wetherill Park",
    "sg:classifiers":[
        {
            "category":"Wholesale",
            "subcategory":"Chemicals & Plastics",
            "type":"Manufacturing & Wholesale Goods"
        }
    ],
    "sg:phone":"+61 2 9756 1900",
    "sg:postcode":"2164",
    "sg:province":"NSW",
    "sg:tags":[
        "bag"
    ],
    "wof:name":"Amadon Pty. Ltd.",
    "wof:placetype":"venue"
},
  "geometry": {"coordinates":[150.91255188,-33.8368721008],"type":"Point"}
}