{
  "type": "Feature",
  "properties": {
    "addr:full":"Piccadilly Rd Crafers SA 5152",
    "addr:postcode":"5152",
    "addr:street":"Piccadilly Rd",
    "iso:country":"AU",
    "sg:address":"Piccadilly Rd",
    "sg:city":"Crafers",
    "sg:classifiers":[
        {
            "category":"Education",
            "subcategory":"School",
            "type":"Public Place"
        }
    ],
    "sg:phone":"+61 8 8339 1073",
    "sg:postcode":"5152",
    "sg:province":"SA",
    "sg:tags":[
        "state",
        "except",
        "nsw"
    ],
    "wof:name":"Crafers Primary",
    "wof:placetype":"venue"
},
  "geometry": {"coordinates":[138.70588684099999,-34.9973945618],"type":"Point"}
}