{
  "type": "Feature",
  "properties": {
    "addr:full":"5 Melball St Bentleigh East VIC 3165",
    "addr:housenumber":"5",
    "addr:postcode":"3165",
    "addr:street":"Melball St",
    "iso:country":"AU",
    "sg:address":"5 Melball St",
    "sg:city":"Bentleigh East",
    "sg:classifiers":[
        {
            "category":"Shopping",
            "subcategory":"Clothing, Apparel, & Fashions",
            "type":"Retail Goods"
        }
    ],
    "sg:phone":"+61 3 9503 8225",
    "sg:postcode":"3165",
    "sg:province":"VIC",
    "sg:tags":[
        "sportswear"
    ],
    "wof:name":"Divida Spirit Sportswear",
    "wof:placetype":"venue"
},
  "geometry": {"coordinates":[145.05303955100001,-37.9311218262],"type":"Point"}
}