{
  "type": "Feature",
  "properties": {
    "addr:full":"21 Macquarie St Windsor NSW 2756",
    "addr:housenumber":"21",
    "addr:postcode":"2756",
    "addr:street":"Macquarie St",
    "iso:country":"AU",
    "sg:address":"21 Macquarie St",
    "sg:city":"Windsor",
    "sg:classifiers":[
        {
            "category":"Retail",
            "subcategory":"Auto Repair",
            "type":"Services"
        }
    ],
    "sg:phone":"+61 2 4577 5225",
    "sg:postcode":"2756",
    "sg:province":"NSW",
    "sg:tags":[
        "electrical"
    ],
    "wof:name":"Mark Hayes Auto Electrical",
    "wof:placetype":"venue"
},
  "geometry": {"coordinates":[150.822799683,-33.6061439514],"type":"Point"}
}