{
  "type": "Feature",
  "properties": {
    "addr:full":"Lot 31 Old Mill Crt McLaren Vale SA 5171",
    "addr:postcode":"5171",
    "addr:street":"Old Mill Crt",
    "iso:country":"AU",
    "sg:address":"Lot 31 Old Mill Crt",
    "sg:city":"McLaren Vale",
    "sg:classifiers":[
        {
            "category":"Retail",
            "subcategory":"Storage",
            "type":"Services"
        }
    ],
    "sg:phone":"+61 8 8323 9069",
    "sg:postcode":"5171",
    "sg:province":"SA",
    "wof:name":"McLaren Vale Self Storage",
    "wof:placetype":"venue"
},
  "geometry": {"coordinates":[138.535614014,-35.2097740173],"type":"Point"}
}