{
  "type": "Feature",
  "properties": {
    "iso:country":"AU",
    "sg:address":"Shop 5, Rovera Plaza, Cnr King St & Cotton Tree Pde",
    "sg:city":"Cotton Tree",
    "sg:classifiers":[
        {
            "category":"Manufacturing",
            "subcategory":"Jewelry",
            "type":"Manufacturing & Wholesale Goods"
        }
    ],
    "sg:phone":"+61 7 5443 1955",
    "sg:postcode":"4558",
    "sg:province":"QLD",
    "sg:tags":[
        "designer",
        "jewellery"
    ],
    "wof:name":"Paul New Jeweller",
    "wof:placetype":"venue"
},
  "geometry": {"coordinates":[153.100708008,-26.6547050476],"type":"Point"}
}