{
  "type": "Feature",
  "properties": {
    "addr:full":"Level 1 288 Sydney Rd Coburg VIC 3058",
    "addr:housenumber":"288",
    "addr:postcode":"3058",
    "addr:street":"Sydney Rd",
    "iso:country":"AU",
    "sg:address":"Level 1 288 Sydney Rd",
    "sg:city":"Coburg",
    "sg:classifiers":[
        {
            "category":"Professional",
            "subcategory":"Accounting & Tax Preparation",
            "type":"Services"
        }
    ],
    "sg:phone":"+61 3 9384 2211",
    "sg:postcode":"3058",
    "sg:province":"VIC",
    "sg:tags":[
        "consultant",
        "taxation"
    ],
    "wof:name":"Failla Sam & Associates",
    "wof:placetype":"venue"
},
  "geometry": {"coordinates":[144.96568298299999,-37.7474555969],"type":"Point"}
}