{
  "type": "Feature",
  "properties": {
    "addr:full":"Main St Bayles VIC 3981",
    "addr:postcode":"3981",
    "addr:street":"Main St",
    "iso:country":"AU",
    "sg:address":"Main St",
    "sg:city":"Bayles",
    "sg:classifiers":[
        {
            "category":"Food & Beverages",
            "subcategory":"Groceries & Convenience Stores",
            "type":"Retail Goods"
        }
    ],
    "sg:phone":"+61 3 5997 7203",
    "sg:postcode":"3981",
    "sg:province":"VIC",
    "wof:name":"Bayles General Store",
    "wof:placetype":"venue"
},
  "geometry": {"coordinates":[145.570755005,-38.1776618958],"type":"Point"}
}