{
  "type": "Feature",
  "properties": {
    "iso:country":"AU",
    "sg:address":"Kremzow Rd",
    "sg:city":"Strathpine",
    "sg:classifiers":[
        {
            "category":"School Buses",
            "type":"Transportation"
        }
    ],
    "sg:phone":"+61 7 3881 2977",
    "sg:postcode":"4500",
    "sg:province":"QLD",
    "sg:tags":[
        "brick"
    ],
    "wof:name":"Homescape",
    "wof:placetype":"venue"
},
  "geometry": {"coordinates":[152.99511718799999,-27.3150901794],"type":"Point"}
}