{
  "type": "Feature",
  "properties": {
    "iso:country":"AU",
    "sg:address":"38 James St",
    "sg:city":"Burleigh Heads",
    "sg:classifiers":[
        {
            "category":"Banks & Credit Unions",
            "subcategory":"Investment Brokerage",
            "type":"Services"
        }
    ],
    "sg:phone":"+61 7 5576 4633",
    "sg:postcode":"4220",
    "sg:province":"QLD",
    "sg:tags":[
        "finance",
        "broker"
    ],
    "wof:name":"Money Power & Finance Pty Ltd",
    "wof:placetype":"venue"
},
  "geometry": {"coordinates":[153.45018005399999,-28.0893383026],"type":"Point"}
}