{
  "type": "Feature",
  "properties": {
    "iso:country":"AU",
    "sg:address":"Lot 2 17 Welsford St",
    "sg:city":"Meeniyan",
    "sg:classifiers":[
        {
            "category":"Building & Trades",
            "subcategory":"Construction",
            "type":"Services"
        }
    ],
    "sg:phone":"+61 3 5664 7473",
    "sg:postcode":"3956",
    "sg:province":"VIC",
    "sg:tags":[
        "contractor"
    ],
    "wof:name":"Wilson D J & T L",
    "wof:placetype":"venue"
},
  "geometry": {"coordinates":[146.01580810600001,-38.5817146301],"type":"Point"}
}