{
  "type": "Feature",
  "properties": {
    "addr:full":"35 Burwood Rd Burwood NSW 2134",
    "addr:housenumber":"35",
    "addr:postcode":"2134",
    "addr:street":"Burwood Rd",
    "iso:country":"AU",
    "sg:address":"35 Burwood Rd",
    "sg:city":"Burwood",
    "sg:classifiers":[
        {
            "category":"Taxi",
            "type":"Transportation"
        }
    ],
    "sg:phone":"+61 418 462 528",
    "sg:postcode":"2134",
    "sg:province":"NSW",
    "sg:tags":[
        "cab"
    ],
    "wof:name":"Gambri Pty Ltd",
    "wof:placetype":"venue"
},
  "geometry": {"coordinates":[151.104125977,-33.8743362427],"type":"Point"}
}