{
  "type": "Feature",
  "properties": {
    "iso:country":"AU",
    "sg:address":"85 Long Gully Rd",
    "sg:city":"Greendale",
    "sg:classifiers":[
        {
            "category":"Professional",
            "subcategory":"Accounting & Tax Preparation",
            "type":"Services"
        }
    ],
    "sg:phone":"+61 3 5368 2918",
    "sg:postcode":"3341",
    "sg:province":"VIC",
    "sg:tags":[
        "bookkeeping"
    ],
    "wof:name":"Award Bookkeeping Company (Melton Bacchus Marsh)",
    "wof:placetype":"venue"
},
  "geometry": {"coordinates":[144.31190490700001,-37.5506477356],"type":"Point"}
}