{
  "type": "Feature",
  "properties": {
    "addr:full":"2 Market St Burra SA 5417",
    "addr:housenumber":"2",
    "addr:postcode":"5417",
    "addr:street":"Market St",
    "iso:country":"AU",
    "sg:address":"2 Market St",
    "sg:city":"Burra",
    "sg:classifiers":[
        {
            "category":"Food & Beverages",
            "subcategory":"Meat & Fish",
            "type":"Retail Goods"
        }
    ],
    "sg:phone":"+61 8 8892 2009",
    "sg:postcode":"5417",
    "sg:province":"SA",
    "sg:tags":[
        "seafood"
    ],
    "wof:name":"McPhee's Butchers",
    "wof:placetype":"venue"
},
  "geometry": {"coordinates":[138.93307495100001,-33.6778450012],"type":"Point"}
}