{
  "type": "Feature",
  "properties": {
    "addr:full":"38- 40 Marble Drv Kingston QLD 4114",
    "addr:housenumber":"40",
    "addr:postcode":"4114",
    "addr:street":"Marble Drv",
    "iso:country":"AU",
    "sg:address":"38- 40 Marble Drv",
    "sg:city":"Kingston",
    "sg:classifiers":[
        {
            "category":"Wholesale",
            "subcategory":"Metals & Minerals",
            "type":"Manufacturing & Wholesale Goods"
        }
    ],
    "sg:phone":"+61 7 3386 0638",
    "sg:postcode":"4114",
    "sg:province":"QLD",
    "sg:tags":[
        "steel",
        "merchant"
    ],
    "wof:name":"Steelcast",
    "wof:placetype":"venue"
},
  "geometry": {"coordinates":[153.113449097,-27.6658000946],"type":"Point"}
}