{
  "type": "Feature",
  "properties": {
    "iso:country":"AU",
    "sg:address":"5 Parksville Drv",
    "sg:city":"Gladstone",
    "sg:classifiers":[
        {
            "category":"Manufacturing",
            "subcategory":"Tools & Machinery",
            "type":"Manufacturing & Wholesale Goods"
        }
    ],
    "sg:phone":"+61 7 4978 2707",
    "sg:postcode":"4680",
    "sg:province":"QLD",
    "sg:tags":[
        "earth",
        "excavating",
        "moving",
        "equipment"
    ],
    "wof:name":"Boyle Plant Hire",
    "wof:placetype":"venue"
},
  "geometry": {"coordinates":[151.242843628,-23.8893527985],"type":"Point"}
}