{
  "type": "Feature",
  "properties": {
    "addr:full":"Lvl 1/ 681 Pittwater Rd Dee Why NSW 2099",
    "addr:housenumber":"/ 681",
    "addr:postcode":"2099",
    "addr:street":"Pittwater Rd",
    "iso:country":"AU",
    "sg:address":"Lvl 1/ 681 Pittwater Rd",
    "sg:city":"Dee Why",
    "sg:classifiers":[
        {
            "category":"Travel",
            "subcategory":"Travel Agent",
            "type":"Entertainment"
        }
    ],
    "sg:phone":"+61 2 9971 4922",
    "sg:postcode":"2099",
    "sg:province":"NSW",
    "sg:tags":[
        "consultant"
    ],
    "wof:name":"Mystery Flights",
    "wof:placetype":"venue"
},
  "geometry": {"coordinates":[151.28521728499999,-33.75340271],"type":"Point"}
}