{
  "type": "Feature",
  "properties": {
    "addr:full":"80 Station St (cnr Station St) Bowral NSW 2576",
    "addr:housenumber":"80",
    "addr:postcode":"2576",
    "addr:street":"Station St Cnr Station St",
    "iso:country":"AU",
    "sg:address":"80 Station St (cnr Station St)",
    "sg:city":"Bowral",
    "sg:classifiers":[
        {
            "category":"Autos & Motor Vehicles",
            "subcategory":"Auto Supplies",
            "type":"Retail Goods"
        }
    ],
    "sg:phone":"+61 2 4861 1102",
    "sg:postcode":"2576",
    "sg:province":"NSW",
    "sg:tags":[
        "tyre"
    ],
    "wof:name":"Reekie's Tyres & More",
    "wof:placetype":"venue"
},
  "geometry": {"coordinates":[150.41365051299999,-34.4841804504],"type":"Point"}
}