{
  "type": "Feature",
  "properties": {
    "iso:country":"AU",
    "sg:address":"9 Naroma Crt",
    "sg:city":"Coolum Beach",
    "sg:classifiers":[
        {
            "category":"Social Services",
            "subcategory":"Job Training",
            "type":"Services"
        }
    ],
    "sg:phone":"+61 402 158 860",
    "sg:postcode":"4573",
    "sg:province":"QLD",
    "sg:tags":[
        "sport"
    ],
    "wof:name":"Clasby I G",
    "wof:placetype":"venue"
},
  "geometry": {"coordinates":[153.086197,-26.521725],"type":"Point"}
}