{
  "type": "Feature",
  "properties": {
    "addr:full":"Shp 4/ 28 Kent St Nambucca Heads NSW 2448",
    "addr:housenumber":"/ 28",
    "addr:postcode":"2448",
    "addr:street":"Kent St",
    "iso:country":"AU",
    "sg:address":"Shp 4/ 28 Kent St",
    "sg:city":"Nambucca Heads",
    "sg:classifiers":[
        {
            "category":"Food & Beverages",
            "subcategory":"Fruits & Vegetables",
            "type":"Retail Goods"
        }
    ],
    "sg:phone":"+61 2 6568 6892",
    "sg:postcode":"2448",
    "sg:province":"NSW",
    "sg:tags":[
        "greengrocer",
        "fruiterer"
    ],
    "wof:name":"Nambucca Fresh Fruit & Vegetables",
    "wof:placetype":"venue"
},
  "geometry": {"coordinates":[153.00100699999999,-30.642582],"type":"Point"}
}