{
  "type": "Feature",
  "properties": {
    "iso:country":"AU",
    "sg:address":"2 Nicosia Crt",
    "sg:city":"Williamstown",
    "sg:classifiers":[
        {
            "category":"Building & Trades",
            "subcategory":"Construction",
            "type":"Services"
        }
    ],
    "sg:phone":"+61 433 264 711",
    "sg:postcode":"3016",
    "sg:province":"VIC",
    "sg:tags":[
        "contractor"
    ],
    "wof:name":"George's Building Group",
    "wof:placetype":"venue"
},
  "geometry": {"coordinates":[144.87223815900001,-37.8533706665],"type":"Point"}
}