{
  "type": "Feature",
  "properties": {
    "iso:country":"AU",
    "sg:address":"16 Acland St St",
    "sg:city":"Kilda",
    "sg:classifiers":[
        {
            "category":"Professional",
            "subcategory":"Art Services",
            "type":"Services"
        }
    ],
    "sg:phone":"+61 3 9534 2858",
    "sg:postcode":"3182",
    "sg:province":"VIC",
    "sg:tags":[
        "product",
        "industrial",
        "designer"
    ],
    "wof:name":"Phillip Meyer",
    "wof:placetype":"venue"
},
  "geometry": {"coordinates":[144.97454834000001,-37.8627815247],"type":"Point"}
}