{
  "type": "Feature",
  "properties": {
    "iso:country":"AU",
    "sg:address":"29 Chester St",
    "sg:city":"Epping",
    "sg:classifiers":[
        {
            "category":"Health Services",
            "subcategory":"Chiropractor",
            "type":"Services"
        }
    ],
    "sg:phone":"+61 2 9877 0764",
    "sg:postcode":"2121",
    "sg:province":"NSW",
    "wof:name":"Dolman Wei",
    "wof:placetype":"venue"
},
  "geometry": {"coordinates":[151.08732605,-33.769077301],"type":"Point"}
}