{
  "type": "Feature",
  "properties": {
    "iso:country":"AU",
    "sg:address":"Grnd Flr/ 115 Grenfell St",
    "sg:city":"Adelaide",
    "sg:classifiers":[
        {
            "category":"Health Services",
            "subcategory":"Dentist",
            "type":"Services"
        }
    ],
    "sg:phone":"+61 8 8232 6177",
    "sg:postcode":"5000",
    "sg:province":"SA",
    "wof:name":"Grenfell Street Dental",
    "wof:placetype":"venue"
},
  "geometry": {"coordinates":[138.60395813,-34.9243736267],"type":"Point"}
}