{
  "type": "Feature",
  "properties": {
    "addr:full":"108 Warrane Rd Willoughby NSW 2068",
    "addr:housenumber":"108",
    "addr:postcode":"2068",
    "addr:street":"Warrane Rd",
    "iso:country":"AU",
    "sg:address":"108 Warrane Rd",
    "sg:city":"Willoughby",
    "sg:classifiers":[
        {
            "category":"Communications",
            "type":"Services"
        }
    ],
    "sg:phone":"+61 2 9417 4588",
    "sg:postcode":"2068",
    "sg:province":"NSW",
    "sg:tags":[
        "public",
        "system",
        "address"
    ],
    "wof:name":"Sontec (NSW) Pty Ltd",
    "wof:placetype":"venue"
},
  "geometry": {"coordinates":[151.202835083,-33.7901382446],"type":"Point"}
}