{
  "type": "Feature",
  "properties": {
    "addr:full":"12 Thomas St Murray Bridge SA 5253",
    "addr:housenumber":"12",
    "addr:postcode":"5253",
    "addr:street":"Thomas St",
    "iso:country":"AU",
    "sg:address":"12 Thomas St",
    "sg:city":"Murray Bridge",
    "sg:classifiers":[
        {
            "category":"Communications",
            "subcategory":"News Services",
            "type":"Services"
        }
    ],
    "sg:phone":"+61 8 8531 0049",
    "sg:postcode":"5253",
    "sg:province":"SA",
    "sg:tags":[
        "information",
        "tourist",
        "attractions"
    ],
    "wof:name":"Captains Cottage Museum",
    "wof:placetype":"venue"
},
  "geometry": {"coordinates":[139.26448059099999,-35.1249885559],"type":"Point"}
}