{
  "type": "Feature",
  "properties": {
    "addr:full":"22 Bourke Rd Alexandria NSW 2015",
    "addr:housenumber":"22",
    "addr:postcode":"2015",
    "addr:street":"Bourke Rd",
    "iso:country":"AU",
    "sg:address":"22 Bourke Rd",
    "sg:city":"Alexandria",
    "sg:classifiers":[
        {
            "category":"Retail",
            "subcategory":"Auto Repair",
            "type":"Services"
        }
    ],
    "sg:phone":"+61 2 9310 4140",
    "sg:postcode":"2015",
    "sg:province":"NSW",
    "sg:tags":[
        "repairer",
        "motor",
        "engineer"
    ],
    "wof:name":"Savvas Automotive Services",
    "wof:placetype":"venue"
},
  "geometry": {"coordinates":[151.19996643100001,-33.9063339233],"type":"Point"}
}