{
  "type": "Feature",
  "properties": {
    "iso:country":"AU",
    "sg:address":"4 Rosedean Rd",
    "sg:city":"Caveside",
    "sg:classifiers":[
        {
            "category":"Professional",
            "subcategory":"Art Services",
            "type":"Services"
        }
    ],
    "sg:phone":"+61 3 6367 8137",
    "sg:postcode":"7304",
    "sg:province":"TAS",
    "sg:tags":[
        "decorator",
        "painter"
    ],
    "wof:name":"Neil Doyle Painting",
    "wof:placetype":"venue"
},
  "geometry": {"coordinates":[146.458359,-41.607655],"type":"Point"}
}