{
  "type": "Feature",
  "properties": {
    "iso:country":"AU",
    "sg:address":"Balbarrup Rd",
    "sg:city":"Manjimup",
    "sg:classifiers":[
        {
            "category":"Sports & Exercise",
            "subcategory":"Golf",
            "type":"Entertainment"
        }
    ],
    "sg:phone":"+61 8 9771 1032",
    "sg:postcode":"6258",
    "sg:province":"WA",
    "sg:tags":[
        "club"
    ],
    "wof:name":"Manjimup Country Club",
    "wof:placetype":"venue"
},
  "geometry": {"coordinates":[116.188110352,-34.2019386292],"type":"Point"}
}