{
  "type": "Feature",
  "properties": {
    "addr:full":"105- 109 Mayne Rd Bowen Hills QLD 4006",
    "addr:housenumber":"105 109",
    "addr:postcode":"4006",
    "addr:street":"Mayne Rd",
    "iso:country":"AU",
    "sg:address":"105- 109 Mayne Rd",
    "sg:city":"Bowen Hills",
    "sg:classifiers":[
        {
            "category":"Banks & Credit Unions",
            "subcategory":"Financial Services",
            "type":"Services"
        }
    ],
    "sg:phone":"+61 7 3252 7911",
    "sg:postcode":"4006",
    "sg:province":"QLD",
    "sg:tags":[
        "equipment",
        "chain"
    ],
    "wof:name":"Serafini Chains Pty Ltd",
    "wof:placetype":"venue"
},
  "geometry": {"coordinates":[153.03828430199999,-27.4429016113],"type":"Point"}
}