{
  "type": "Feature",
  "properties": {
    "addr:full":"538 Malvern Rd Prahran VIC 3181",
    "addr:housenumber":"538",
    "addr:postcode":"3181",
    "addr:street":"Malvern Rd",
    "iso:country":"AU",
    "sg:address":"538 Malvern Rd",
    "sg:city":"Prahran",
    "sg:classifiers":[
        {
            "category":"Health Services",
            "subcategory":"Optometrist",
            "type":"Services"
        }
    ],
    "sg:phone":"+61 3 9533 2000",
    "sg:postcode":"3181",
    "sg:province":"VIC",
    "wof:name":"Sacho, Colin & Beverley",
    "wof:placetype":"venue"
},
  "geometry": {"coordinates":[145.00424194300001,-37.8483467102],"type":"Point"}
}