{
  "type": "Feature",
  "properties": {
    "addr:full":"35 Coonara Ave West Pennant Hills NSW 2125",
    "addr:housenumber":"35",
    "addr:postcode":"2125",
    "addr:street":"Coonara Ave",
    "iso:country":"AU",
    "sg:address":"35 Coonara Ave",
    "sg:city":"West Pennant Hills",
    "sg:classifiers":[
        {
            "category":"Health Services",
            "subcategory":"Dentist",
            "type":"Services"
        }
    ],
    "sg:phone":"+61 2 9894 4999",
    "sg:postcode":"2125",
    "sg:province":"NSW",
    "sg:tags":[
        "dental",
        "emergency"
    ],
    "wof:name":"Smart Dental",
    "wof:placetype":"venue"
},
  "geometry": {"coordinates":[151.02993774399999,-33.744846344],"type":"Point"}
}