{
  "type": "Feature",
  "properties": {
    "addr:full":"Bldg C/ 115 Sherriff St Underdale SA 5032",
    "addr:housenumber":"115",
    "addr:postcode":"5032",
    "addr:street":"C /;Sherriff St",
    "iso:country":"AU",
    "sg:address":"Bldg C/ 115 Sherriff St",
    "sg:city":"Underdale",
    "sg:classifiers":[
        {
            "category":"Wholesale",
            "subcategory":"Drugs",
            "type":"Manufacturing & Wholesale Goods"
        }
    ],
    "sg:phone":"+61 8 8408 3000",
    "sg:postcode":"5032",
    "sg:province":"SA",
    "sg:tags":[
        "wholesaler",
        "pharmaceutical",
        "product",
        "mfrs"
    ],
    "wof:name":"Faulding F H & Co Limited",
    "wof:placetype":"venue"
},
  "geometry": {"coordinates":[138.551177978,-34.9159202576],"type":"Point"}
}