{
  "type": "Feature",
  "properties": {
    "addr:full":"23 Warraba Rd North Narrabeen NSW 2101",
    "addr:housenumber":"23",
    "addr:postcode":"2101",
    "addr:street":"Warraba Rd",
    "iso:country":"AU",
    "sg:address":"23 Warraba Rd",
    "sg:city":"North Narrabeen",
    "sg:classifiers":[
        {
            "category":"Sports & Exercise",
            "subcategory":"Gym",
            "type":"Entertainment"
        }
    ],
    "sg:phone":"+61 2 9913 8600",
    "sg:postcode":"2101",
    "sg:province":"NSW",
    "sg:tags":[
        "personal",
        "trainer",
        "fitness"
    ],
    "wof:name":"Fastrak Performance Pty Ltd",
    "wof:placetype":"venue"
},
  "geometry": {"coordinates":[151.294006,-33.700825],"type":"Point"}
}