{
  "type": "Feature",
  "properties": {
    "addr:full":"201 Longueville Rd Lane Cove NSW 2066",
    "addr:housenumber":"201",
    "addr:postcode":"2066",
    "addr:street":"Longueville Rd",
    "iso:country":"AU",
    "sg:address":"201 Longueville Rd",
    "sg:city":"Lane Cove",
    "sg:classifiers":[
        {
            "category":"Wholesale",
            "subcategory":"Apparel",
            "type":"Manufacturing & Wholesale Goods"
        }
    ],
    "sg:phone":"+61 2 9428 3500",
    "sg:postcode":"2066",
    "sg:province":"NSW",
    "sg:tags":[
        "wholesaler",
        "mfrs",
        "cap",
        "hat"
    ],
    "wof:name":"Pascall Principal The",
    "wof:placetype":"venue"
},
  "geometry": {"coordinates":[151.17013549800001,-33.820526123],"type":"Point"}
}