{
  "type": "Feature",
  "properties": {
    "iso:country":"AU",
    "sg:address":"Factory 6 3 Woodbine Crt",
    "sg:city":"Wantirna South",
    "sg:classifiers":[
        {
            "category":"Shopping",
            "subcategory":"Optical Goods",
            "type":"Retail Goods"
        }
    ],
    "sg:phone":"+61 3 9801 5992",
    "sg:postcode":"3152",
    "sg:province":"VIC",
    "sg:tags":[
        "supply"
    ],
    "wof:name":"Groiss Herbert A & Co",
    "wof:placetype":"venue"
},
  "geometry": {"coordinates":[145.25050354000001,-37.8699035645],"type":"Point"}
}