{
  "type": "Feature",
  "properties": {
    "iso:country":"AU",
    "sg:address":"1 Hume Rd",
    "sg:city":"Laverton North",
    "sg:classifiers":[
        {
            "category":"Professional",
            "type":"Services"
        }
    ],
    "sg:phone":"+61 3 8369 8100",
    "sg:postcode":"3026",
    "sg:province":"VIC",
    "sg:tags":[
        "transport"
    ],
    "wof:name":"Toll Refrigerated",
    "wof:placetype":"venue"
},
  "geometry": {"coordinates":[144.796494,-37.828777],"type":"Point"}
}