{
  "type": "Feature",
  "properties": {
    "iso:country":"AU",
    "sg:address":"46 Domitia Ave",
    "sg:city":"Seven Hills",
    "sg:classifiers":[
        {
            "category":"Building & Trades",
            "subcategory":"Construction",
            "type":"Services"
        }
    ],
    "sg:phone":"+61 7 3399 8003",
    "sg:postcode":"4170",
    "sg:province":"QLD",
    "sg:tags":[
        "concrete",
        "contractor"
    ],
    "wof:name":"Blake Peter",
    "wof:placetype":"venue"
},
  "geometry": {"coordinates":[153.07398986800001,-27.4801273346],"type":"Point"}
}