{
  "type": "Feature",
  "properties": {
    "addr:full":"5 Hurst St Bridgewater TAS 7030",
    "addr:housenumber":"5",
    "addr:postcode":"7030",
    "addr:street":"Hurst St",
    "iso:country":"AU",
    "sg:address":"5 Hurst St",
    "sg:city":"Bridgewater",
    "sg:classifiers":[
        {
            "category":"Shopping",
            "subcategory":"Clothing, Apparel, & Fashions",
            "type":"Retail Goods"
        }
    ],
    "sg:phone":"+61 3 6263 5737",
    "sg:postcode":"7030",
    "sg:province":"TAS",
    "sg:tags":[
        "recycled",
        "clothing"
    ],
    "wof:name":"St Vincent De Paul Society",
    "wof:placetype":"venue"
},
  "geometry": {"coordinates":[147.244430542,-42.7354469299],"type":"Point"}
}