{
  "type": "Feature",
  "properties": {
    "iso:country":"AU",
    "sg:address":"1/ 122 Morrison Rd",
    "sg:city":"Gladesville",
    "sg:classifiers":[
        {
            "category":"Health Services",
            "subcategory":"Doctor",
            "type":"Services"
        }
    ],
    "sg:phone":"+61 2 4736 6900",
    "sg:postcode":"2111",
    "sg:province":"NSW",
    "sg:tags":[
        "medical",
        "practitioner"
    ],
    "wof:name":"Muthukrishnan R S Dr",
    "wof:placetype":"venue"
},
  "geometry": {"coordinates":[151.11643981899999,-33.8272514343],"type":"Point"}
}