{
  "type": "Feature",
  "properties": {
    "iso:country":"AU",
    "sg:address":"129 Russell St",
    "sg:city":"Toowoomba",
    "sg:classifiers":[
        {
            "category":"Health Services",
            "subcategory":"Doctor",
            "type":"Services"
        }
    ],
    "sg:phone":"+61 7 4632 2029",
    "sg:postcode":"4350",
    "sg:province":"QLD",
    "sg:tags":[
        "medical",
        "practitioner"
    ],
    "wof:name":"West Andrew",
    "wof:placetype":"venue"
},
  "geometry": {"coordinates":[151.948456,-27.55818],"type":"Point"}
}