{
  "type": "Feature",
  "properties": {
    "addr:full":"PO Box 370 Babinda QLD 4861",
    "addr:postcode":"4861",
    "iso:country":"AU",
    "sg:address":"PO Box 370",
    "sg:city":"Babinda",
    "sg:classifiers":[
        {
            "category":"Farming",
            "subcategory":"Nursery",
            "type":"Manufacturing & Wholesale Goods"
        }
    ],
    "sg:phone":"+61 7 4067 1733",
    "sg:postcode":"4861",
    "sg:province":"QLD",
    "wof:name":"Russell River Plantation",
    "wof:placetype":"venue"
},
  "geometry": {"coordinates":[145.92481994600001,-17.3449401855],"type":"Point"}
}