{
  "type": "Feature",
  "properties": {
    "iso:country":"AU",
    "sg:address":"469 Princes Hwy",
    "sg:city":"Rockdale",
    "sg:classifiers":[
        {
            "category":"Shopping",
            "subcategory":"Pawn Shop",
            "type":"Retail Goods"
        }
    ],
    "sg:phone":"+61 2 9556 2489",
    "sg:postcode":"2216",
    "sg:province":"NSW",
    "sg:tags":[
        "pawnbroker"
    ],
    "wof:name":"Cash Converters",
    "wof:placetype":"venue"
},
  "geometry": {"coordinates":[151.138153,-33.951363],"type":"Point"}
}