{
  "type": "Feature",
  "properties": {
    "iso:country":"AU",
    "sg:address":"145 The Entrance Rd",
    "sg:city":"The Entrance",
    "sg:classifiers":[
        {
            "category":"Real Estate",
            "subcategory":"Real Estate Agent",
            "type":"Services"
        }
    ],
    "sg:phone":"+61 2 4332 2266",
    "sg:postcode":"2261",
    "sg:province":"NSW",
    "wof:name":"Peter Brand Real Estate",
    "wof:placetype":"venue"
},
  "geometry": {"coordinates":[151.494629,-33.34589],"type":"Point"}
}