{
  "type": "Feature",
  "properties": {
    "addr:full":"2/70 Wadhurst Drv Boronia VIC 3155",
    "addr:housenumber":"/ 70",
    "addr:postcode":"3155",
    "addr:street":"Wadhurst Drv",
    "iso:country":"AU",
    "sg:address":"2/70 Wadhurst Drv",
    "sg:city":"Boronia",
    "sg:classifiers":[
        {
            "category":"Manufacturing",
            "subcategory":"Motor Vehicles & Parts",
            "type":"Manufacturing & Wholesale Goods"
        }
    ],
    "sg:phone":"+61 3 9887 4115",
    "sg:postcode":"3155",
    "sg:province":"VIC",
    "sg:tags":[
        "press",
        "knife",
        "dy"
    ],
    "wof:name":"R Short & Sons Pty Ltd",
    "wof:placetype":"venue"
},
  "geometry": {"coordinates":[145.25405883799999,-37.8679351807],"type":"Point"}
}