{
  "type": "Feature",
  "properties": {
    "iso:country":"AU",
    "sg:address":"34-36 Glenferrie Rd",
    "sg:city":"Robina East Quay Robina",
    "sg:classifiers":[
        {
            "category":"Health Services",
            "subcategory":"Health Practitioner",
            "type":"Services"
        }
    ],
    "sg:phone":"+61 427 943 384",
    "sg:postcode":"4226",
    "sg:province":"QLD",
    "sg:tags":[
        "psychologist"
    ],
    "wof:name":"Natalie Turvey",
    "wof:placetype":"venue"
},
  "geometry": {"coordinates":[153.40196227999999,-28.064289093],"type":"Point"}
}