{
  "type": "Feature",
  "properties": {
    "iso:country":"AU",
    "sg:address":"Cnr Oswald St & Scarborough Beach Rd",
    "sg:city":"Innaloo",
    "sg:classifiers":[
        {
            "category":"Food & Beverages",
            "subcategory":"Meat & Fish",
            "type":"Retail Goods"
        }
    ],
    "sg:phone":"+61 8 9445 2451",
    "sg:postcode":"6018",
    "sg:province":"WA",
    "sg:tags":[
        "seafood"
    ],
    "wof:name":"Innaloo Seafresh Fish Markets",
    "wof:placetype":"venue"
},
  "geometry": {"coordinates":[115.78749084499999,-31.8992271423],"type":"Point"}
}