{
  "type": "Feature",
  "properties": {
    "addr:full":"179 Springvale Rd Nunawading VIC 3131",
    "addr:housenumber":"179",
    "addr:postcode":"3131",
    "addr:street":"Springvale Rd",
    "iso:country":"AU",
    "sg:address":"179 Springvale Rd",
    "sg:city":"Nunawading",
    "sg:classifiers":[
        {
            "category":"Building & Trades",
            "subcategory":"Construction",
            "type":"Services"
        }
    ],
    "sg:phone":"+61 3 9878 0588",
    "sg:postcode":"3131",
    "sg:province":"VIC",
    "sg:tags":[
        "contractor"
    ],
    "wof:name":"Betta Extensions Pty Ltd",
    "wof:placetype":"venue"
},
  "geometry": {"coordinates":[145.17582702600001,-37.820854187],"type":"Point"}
}