{
  "type": "Feature",
  "properties": {
    "addr:full":"U6/ 10-12 Opala St Regency Park SA 5010",
    "addr:housenumber":"10-12",
    "addr:postcode":"5010",
    "addr:street":"U6 /;Opala St",
    "iso:country":"AU",
    "sg:address":"U6/ 10-12 Opala St",
    "sg:city":"Regency Park",
    "sg:classifiers":[
        {
            "category":"Professional",
            "subcategory":"Testing Lab",
            "type":"Services"
        }
    ],
    "sg:phone":"+61 8 8244 3055",
    "sg:postcode":"5010",
    "sg:province":"SA",
    "sg:tags":[
        "inspection"
    ],
    "wof:name":"Adelec Emergency Lighting & Battery Services",
    "wof:placetype":"venue"
},
  "geometry": {"coordinates":[138.56735229500001,-34.8507575989],"type":"Point"}
}