{
  "type": "Feature",
  "properties": {
    "addr:full":"20 Nyah Rd Swan Hill VIC 3585",
    "addr:housenumber":"20",
    "addr:postcode":"3585",
    "addr:street":"Nyah Rd",
    "iso:country":"AU",
    "sg:address":"20 Nyah Rd",
    "sg:city":"Swan Hill",
    "sg:classifiers":[
        {
            "category":"Home & Garden",
            "subcategory":"Garden Supply",
            "type":"Retail Goods"
        }
    ],
    "sg:phone":"+61 3 5032 9255",
    "sg:postcode":"3585",
    "sg:province":"VIC",
    "sg:tags":[
        "fertilizer"
    ],
    "wof:name":"Swan Hill Chemicals Pty Ltd",
    "wof:placetype":"venue"
},
  "geometry": {"coordinates":[143.55380199999999,-35.329205],"type":"Point"}
}