{
  "type": "Feature",
  "properties": {
    "addr:full":"1244 Pittwater Rd Narrabeen NSW 2101",
    "addr:housenumber":"1244",
    "addr:postcode":"2101",
    "addr:street":"Pittwater Rd",
    "iso:country":"AU",
    "sg:address":"1244 Pittwater Rd",
    "sg:city":"Narrabeen",
    "sg:classifiers":[
        {
            "category":"Banks & Credit Unions",
            "subcategory":"Investment Brokerage",
            "type":"Services"
        }
    ],
    "sg:phone":"+61 2 9913 1344",
    "sg:postcode":"2101",
    "sg:province":"NSW",
    "sg:tags":[
        "management",
        "property"
    ],
    "wof:name":"Hooker L J Collaroy",
    "wof:placetype":"venue"
},
  "geometry": {"coordinates":[151.29818700000001,-33.71933],"type":"Point"}
}