{
  "type": "Feature",
  "properties": {
    "addr:full":"451 Albany Hwy Albany WA 6330",
    "addr:housenumber":"451",
    "addr:postcode":"6330",
    "addr:street":"Albany Hwy",
    "iso:country":"AU",
    "sg:address":"451 Albany Hwy",
    "sg:city":"Albany",
    "sg:classifiers":[
        {
            "category":"Cinema",
            "subcategory":"Movie Theater",
            "type":"Entertainment"
        }
    ],
    "sg:phone":"+61 8 9842 2210",
    "sg:postcode":"6330",
    "sg:province":"WA",
    "wof:name":"Albany Cinemas",
    "wof:placetype":"venue"
},
  "geometry": {"coordinates":[117.839019775,-34.977104187],"type":"Point"}
}