{
  "type": "Feature",
  "properties": {
    "addr:full":"PO Box 5548 West End (Brisbane) QLD 4101",
    "addr:postcode":"4101",
    "iso:country":"AU",
    "sg:address":"PO Box 5548",
    "sg:city":"West End (Brisbane)",
    "sg:classifiers":[
        {
            "category":"Building & Trades",
            "subcategory":"Construction",
            "type":"Services"
        }
    ],
    "sg:phone":"+61 7 3848 9143",
    "sg:postcode":"4101",
    "sg:province":"QLD",
    "sg:tags":[
        "renovation",
        "alterations",
        "extension",
        "contractor"
    ],
    "wof:name":"Crocker Builders",
    "wof:placetype":"venue"
},
  "geometry": {"coordinates":[153.012161255,-27.4802494049],"type":"Point"}
}