{
  "type": "Feature",
  "properties": {
    "addr:full":"Kiosk 17, Shellharbour Square, Lake Entrance Road Shellharbour NSW 2529",
    "addr:postcode":"2529",
    "addr:street":"Shellharbour Square Lake Entrance Road",
    "iso:country":"AU",
    "sg:address":"Kiosk 17, Shellharbour Square, Lake Entrance Road",
    "sg:city":"Shellharbour",
    "sg:classifiers":[
        {
            "category":"Shopping",
            "subcategory":"Mobile Phones",
            "type":"Retail Goods"
        }
    ],
    "sg:phone":"+61 2 4295 3244",
    "sg:postcode":"2529",
    "sg:province":"NSW",
    "sg:tags":[
        "telephone",
        "accessory"
    ],
    "wof:name":"Allphones",
    "wof:placetype":"venue"
},
  "geometry": {"coordinates":[150.82241821299999,-34.5697593689],"type":"Point"}
}