{
  "type": "Feature",
  "properties": {
    "addr:full":"Ambrose St Broadmeadows VIC 3047",
    "addr:postcode":"3047",
    "addr:street":"Ambrose St",
    "iso:country":"AU",
    "sg:address":"Ambrose St",
    "sg:city":"Broadmeadows",
    "sg:classifiers":[
        {
            "category":"Education",
            "subcategory":"School",
            "type":"Public Place"
        }
    ],
    "sg:phone":"+61 3 9359 1966",
    "sg:postcode":"3047",
    "sg:province":"VIC",
    "sg:tags":[
        "state",
        "except",
        "nsw"
    ],
    "wof:name":"Upfield Primary",
    "wof:placetype":"venue"
},
  "geometry": {"coordinates":[144.94392395,-37.668926239],"type":"Point"}
}