{
  "type": "Feature",
  "properties": {
    "addr:full":"PO Box 22 Fulham Gardens SA 5024",
    "addr:postcode":"5024",
    "iso:country":"AU",
    "sg:address":"PO Box 22",
    "sg:city":"Fulham Gardens",
    "sg:classifiers":[
        {
            "category":"Professional",
            "subcategory":"Employment Agencies",
            "type":"Services"
        }
    ],
    "sg:phone":"+61 8 8355 5588",
    "sg:postcode":"5024",
    "sg:province":"SA",
    "sg:tags":[
        "theatrical",
        "managers",
        "agent",
        "producer"
    ],
    "wof:name":"Fanfare Artist Management Pty Ltd",
    "wof:placetype":"venue"
},
  "geometry": {"coordinates":[138.51495361299999,-34.9204788208],"type":"Point"}
}