{
  "type": "Feature",
  "properties": {
    "addr:full":"8 Beech St Marcoola QLD 4564",
    "addr:housenumber":"8",
    "addr:postcode":"4564",
    "addr:street":"Beech St",
    "iso:country":"AU",
    "sg:address":"8 Beech St",
    "sg:city":"Marcoola",
    "sg:classifiers":[
        {
            "category":"Retail",
            "subcategory":"Event Space",
            "type":"Services"
        }
    ],
    "sg:phone":"+61 7 5448 9500",
    "sg:postcode":"4564",
    "sg:province":"QLD",
    "sg:tags":[
        "function",
        "organiser"
    ],
    "wof:name":"The Theming Company",
    "wof:placetype":"venue"
},
  "geometry": {"coordinates":[153.08399963400001,-26.6085338593],"type":"Point"}
}