{
  "type": "Feature",
  "properties": {
    "iso:country":"AU",
    "sg:address":"14- 16 Harvard Way",
    "sg:city":"Canning Vale",
    "sg:classifiers":[
        {
            "category":"Shopping",
            "subcategory":"Gifts & Souvenirs",
            "type":"Retail Goods"
        }
    ],
    "sg:phone":"+61 8 9455 1615",
    "sg:postcode":"6155",
    "sg:province":"WA",
    "sg:tags":[
        "greeting",
        "card"
    ],
    "wof:name":"Cardland",
    "wof:placetype":"venue"
},
  "geometry": {"coordinates":[115.924171,-32.06366],"type":"Point"}
}