{
  "type": "Feature",
  "properties": {
    "iso:country":"AU",
    "sg:address":"6 Sinclair Drv",
    "sg:city":"Wangaratta",
    "sg:classifiers":[
        {
            "category":"Building & Trades",
            "subcategory":"Cleaning & Sanitation",
            "type":"Services"
        }
    ],
    "sg:phone":"+61 3 5721 5756",
    "sg:postcode":"3677",
    "sg:province":"VIC",
    "sg:tags":[
        "cleaner",
        "repairer",
        "roof"
    ],
    "wof:name":"Golding Plumbing Services",
    "wof:placetype":"venue"
},
  "geometry": {"coordinates":[146.294067383,-36.3639678955],"type":"Point"}
}