{
  "type": "Feature",
  "properties": {
    "addr:full":"49 Larapinta Drv Alice Springs NT 0871",
    "addr:housenumber":"49",
    "addr:postcode":"nt 0871",
    "addr:street":"Larapinta Drv",
    "iso:country":"AU",
    "sg:address":"49 Larapinta Drv",
    "sg:city":"Alice Springs",
    "sg:classifiers":[
        {
            "category":"Building & Trades",
            "subcategory":"Construction",
            "type":"Services"
        }
    ],
    "sg:phone":"+61 414 522 438",
    "sg:postcode":"0871",
    "sg:province":"NT",
    "sg:tags":[
        "fencing",
        "contractor"
    ],
    "wof:name":"PGC Pty Ltd",
    "wof:placetype":"venue"
},
  "geometry": {"coordinates":[133.866165161,-23.7005786896],"type":"Point"}
}