{
  "type": "Feature",
  "properties": {
    "addr:full":"1 Dane Hill Crt Ballarat VIC 3350",
    "addr:housenumber":"1",
    "addr:postcode":"3350",
    "addr:street":"Dane Hill Crt",
    "iso:country":"AU",
    "sg:address":"1 Dane Hill Crt",
    "sg:city":"Ballarat",
    "sg:classifiers":[
        {
            "category":"Education",
            "subcategory":"Dance Studio",
            "type":"Public Place"
        }
    ],
    "sg:phone":"+61 438 567 209",
    "sg:postcode":"3350",
    "sg:province":"VIC",
    "sg:tags":[
        "training",
        "video",
        "film"
    ],
    "wof:name":"Wide Eyed Digital Media",
    "wof:placetype":"venue"
},
  "geometry": {"coordinates":[143.85716199999999,-37.522705],"type":"Point"}
}