{
  "type": "Feature",
  "properties": {
    "addr:full":"727 Glenferrie Rd Hawthorn VIC 3122",
    "addr:housenumber":"727",
    "addr:postcode":"3122",
    "addr:street":"Glenferrie Rd",
    "iso:country":"AU",
    "sg:address":"727 Glenferrie Rd",
    "sg:city":"Hawthorn",
    "sg:classifiers":[
        {
            "category":"Cafe",
            "type":"Food & Drink"
        }
    ],
    "sg:phone":"+61 3 9818 3141",
    "sg:postcode":"3122",
    "sg:province":"VIC",
    "wof:name":"Cafe Vamp",
    "wof:placetype":"venue"
},
  "geometry": {"coordinates":[145.035842895,-37.8190307617],"type":"Point"}
}