{
  "type": "Feature",
  "properties": {
    "addr:full":"43 Second Ave Forestville SA 5035",
    "addr:housenumber":"43",
    "addr:postcode":"5035",
    "addr:street":"Second Ave",
    "iso:country":"AU",
    "sg:address":"43 Second Ave",
    "sg:city":"Forestville",
    "sg:classifiers":[
        {
            "category":"Building & Trades",
            "subcategory":"Construction",
            "type":"Services"
        }
    ],
    "sg:phone":"+61 8 8293 4048",
    "sg:postcode":"5035",
    "sg:province":"SA",
    "sg:tags":[
        "mural"
    ],
    "wof:name":"Set The Scene",
    "wof:placetype":"venue"
},
  "geometry": {"coordinates":[138.579147339,-34.9525909424],"type":"Point"}
}