{
  "type": "Feature",
  "properties": {
    "iso:country":"AU",
    "sg:address":"47 Eve Rd",
    "sg:city":"Bellevue Heights",
    "sg:classifiers":[
        {
            "category":"Travel",
            "subcategory":"Hostel",
            "type":"Entertainment"
        }
    ],
    "sg:phone":"+61 8 8278 8588",
    "sg:postcode":"5050",
    "sg:province":"SA",
    "sg:tags":[
        "home"
    ],
    "wof:name":"Resthaven",
    "wof:placetype":"venue"
},
  "geometry": {"coordinates":[138.588638,-35.032555],"type":"Point"}
}