{
  "type": "Feature",
  "properties": {
    "addr:full":"2452 Gold Coast Hwy Mermaid Beach QLD 4218",
    "addr:housenumber":"2452",
    "addr:postcode":"4218",
    "addr:street":"Gold Coast Hwy",
    "iso:country":"AU",
    "sg:address":"2452 Gold Coast Hwy",
    "sg:city":"Mermaid Beach",
    "sg:classifiers":[
        {
            "category":"Building & Trades",
            "subcategory":"Construction",
            "type":"Services"
        }
    ],
    "sg:phone":"+61 438 461 122",
    "sg:postcode":"4218",
    "sg:province":"QLD",
    "sg:tags":[
        "pool",
        "swimming"
    ],
    "wof:name":"Mermaid Pools & Spas",
    "wof:placetype":"venue"
},
  "geometry": {"coordinates":[153.43484497099999,-28.0454292297],"type":"Point"}
}