{
  "type": "Feature",
  "properties": {
    "addr:full":"Siems Rd Euroa VIC 3666",
    "addr:postcode":"3666",
    "addr:street":"Siems Rd",
    "iso:country":"AU",
    "sg:address":"Siems Rd",
    "sg:city":"Euroa",
    "sg:classifiers":[
        {
            "category":"Farming",
            "subcategory":"Farm",
            "type":"Manufacturing & Wholesale Goods"
        }
    ],
    "sg:phone":"+61 3 5795 2618",
    "sg:postcode":"3666",
    "sg:province":"VIC",
    "sg:tags":[
        "farmer"
    ],
    "wof:name":"Siems W L & P",
    "wof:placetype":"venue"
},
  "geometry": {"coordinates":[145.55755615199999,-36.7434883118],"type":"Point"}
}