{
  "type": "Feature",
  "properties": {
    "addr:full":"11 Dega Ave Bentleigh East VIC 3165",
    "addr:housenumber":"11",
    "addr:postcode":"3165",
    "addr:street":"Dega Ave",
    "iso:country":"AU",
    "sg:address":"11 Dega Ave",
    "sg:city":"Bentleigh East",
    "sg:classifiers":[
        {
            "category":"Health Services",
            "subcategory":"Health Practitioner",
            "type":"Services"
        }
    ],
    "sg:phone":"+61 3 9576 5955",
    "sg:postcode":"3165",
    "sg:province":"VIC",
    "sg:tags":[
        "naturopath"
    ],
    "wof:name":"Botanica Naturopathy",
    "wof:placetype":"venue"
},
  "geometry": {"coordinates":[145.050857544,-37.929725647],"type":"Point"}
}