{
  "type": "Feature",
  "properties": {
    "addr:full":"Unit 2, 827 Old Northern Rd Dural NSW 2158",
    "addr:housenumber":"827",
    "addr:postcode":"2158",
    "addr:street":"Old Northern Rd",
    "iso:country":"AU",
    "sg:address":"Unit 2, 827 Old Northern Rd",
    "sg:city":"Dural",
    "sg:classifiers":[
        {
            "category":"Professional",
            "subcategory":"Art Services",
            "type":"Services"
        }
    ],
    "sg:phone":"+61 2 9659 7444",
    "sg:postcode":"2158",
    "sg:province":"NSW",
    "sg:tags":[
        "interior",
        "decorator"
    ],
    "wof:name":"Lounge Manufacturers",
    "wof:placetype":"venue"
},
  "geometry": {"coordinates":[151.03147888199999,-33.6949882507],"type":"Point"}
}