{
  "type": "Feature",
  "properties": {
    "addr:full":"2/ 320 Curtin Ave Eagle Farm QLD 4009",
    "addr:housenumber":"/ 320",
    "addr:postcode":"4009",
    "addr:street":"Curtin Ave",
    "iso:country":"AU",
    "sg:address":"2/ 320 Curtin Ave",
    "sg:city":"Eagle Farm",
    "sg:classifiers":[
        {
            "category":"Building & Trades",
            "subcategory":"Cleaning & Sanitation",
            "type":"Services"
        }
    ],
    "sg:phone":"+61 7 3868 2411",
    "sg:postcode":"4009",
    "sg:province":"QLD",
    "sg:tags":[
        "washroom",
        "toilet",
        "equipment"
    ],
    "wof:name":"Initial Healthcare",
    "wof:placetype":"venue"
},
  "geometry": {"coordinates":[153.088180542,-27.439458847],"type":"Point"}
}