{
  "type": "Feature",
  "properties": {
    "addr:full":"PO Box 550 Lobethal SA 5241",
    "addr:postcode":"5241",
    "iso:country":"AU",
    "sg:address":"PO Box 550",
    "sg:city":"Lobethal",
    "sg:classifiers":[
        {
            "category":"Building & Trades",
            "subcategory":"Cleaning & Sanitation",
            "type":"Services"
        }
    ],
    "sg:phone":"+61 8 8389 5440",
    "sg:postcode":"5241",
    "sg:province":"SA",
    "sg:tags":[
        "cleaner",
        "repairer",
        "roof"
    ],
    "wof:name":"Adelaide Property Restoration Services",
    "wof:placetype":"venue"
},
  "geometry": {"coordinates":[138.87628173799999,-34.9008102417],"type":"Point"}
}