{
  "type": "Feature",
  "properties": {
    "iso:country":"AU",
    "sg:address":"Shop 13, 204 Warrandyte Rd",
    "sg:city":"Ringwood North",
    "sg:classifiers":[
        {
            "category":"Real Estate",
            "subcategory":"Real Estate Agent",
            "type":"Services"
        }
    ],
    "sg:phone":"+61 3 9876 1466",
    "sg:postcode":"3134",
    "sg:province":"VIC",
    "wof:name":"Ray White (Victoria) Pty Ltd",
    "wof:placetype":"venue"
},
  "geometry": {"coordinates":[145.23631286599999,-37.7889900208],"type":"Point"}
}