{
  "type": "Feature",
  "properties": {
    "addr:full":"2 Hibiscus Haven Burleigh Heads QLD 4220",
    "addr:housenumber":"2",
    "addr:postcode":"4220",
    "addr:street":"Hibiscus Haven",
    "iso:country":"AU",
    "sg:address":"2 Hibiscus Haven",
    "sg:city":"Burleigh Heads",
    "sg:classifiers":[
        {
            "category":"Autos & Motor Vehicles",
            "subcategory":"Automobile Sales",
            "type":"Retail Goods"
        }
    ],
    "sg:phone":"+61 7 5576 5855",
    "sg:postcode":"4220",
    "sg:province":"QLD",
    "sg:tags":[
        "car",
        "used"
    ],
    "wof:name":"Fraser Wholesale",
    "wof:placetype":"venue"
},
  "geometry": {"coordinates":[153.43096923799999,-28.1023406982],"type":"Point"}
}