{
  "type": "Feature",
  "properties": {
    "addr:full":"Unit 3 36 Turbo Drv Woolloongabba QLD 4102",
    "addr:housenumber":"36",
    "addr:postcode":"4102",
    "addr:street":"Turbo Drv",
    "iso:country":"AU",
    "sg:address":"Unit 3 36 Turbo Drv",
    "sg:city":"Woolloongabba",
    "sg:classifiers":[
        {
            "category":"Wholesale",
            "subcategory":"Painting Supplies",
            "type":"Manufacturing & Wholesale Goods"
        }
    ],
    "sg:phone":"+61 7 3891 2422",
    "sg:postcode":"4102",
    "sg:province":"QLD",
    "sg:tags":[
        "product",
        "cleaning"
    ],
    "wof:name":"Oates Clean",
    "wof:placetype":"venue"
},
  "geometry": {"coordinates":[153.04914855999999,-27.492433548],"type":"Point"}
}