{
  "type": "Feature",
  "properties": {
    "iso:country":"AU",
    "sg:address":"305 Glen Huntly Rd",
    "sg:city":"Elsternwick",
    "sg:classifiers":[
        {
            "category":"Real Estate",
            "subcategory":"Real Estate Agent",
            "type":"Services"
        }
    ],
    "sg:phone":"+61 3 9533 0999",
    "sg:postcode":"3185",
    "sg:province":"VIC",
    "wof:name":"LJ Hooker Elsternwick",
    "wof:placetype":"venue"
},
  "geometry": {"coordinates":[145.00209045400001,-37.8842887878],"type":"Point"}
}