{
  "type": "Feature",
  "properties": {
    "addr:full":"25 La Mascotte Ave Concord NSW 2137",
    "addr:housenumber":"25",
    "addr:postcode":"2137",
    "addr:street":"La Mascotte Ave",
    "iso:country":"AU",
    "sg:address":"25 La Mascotte Ave",
    "sg:city":"Concord",
    "sg:classifiers":[
        {
            "category":"Shopping",
            "subcategory":"Computers & Home Electronics",
            "type":"Retail Goods"
        }
    ],
    "sg:phone":"+61 2 9747 4969",
    "sg:postcode":"2137",
    "sg:province":"NSW",
    "sg:tags":[
        "plate",
        "name"
    ],
    "wof:name":"Active Signs",
    "wof:placetype":"venue"
},
  "geometry": {"coordinates":[151.11021423299999,-33.8595237732],"type":"Point"}
}