{
  "type": "Feature",
  "properties": {
    "iso:country":"AU",
    "sg:address":"1 Ann St",
    "sg:city":"Bulahdelah",
    "sg:classifiers":[
        {
            "category":"Museum",
            "type":"Entertainment"
        }
    ],
    "sg:phone":"+61 2 4987 9274",
    "sg:postcode":"2423",
    "sg:province":"NSW",
    "wof:name":"Bulladelah & District Historical Society",
    "wof:placetype":"venue"
},
  "geometry": {"coordinates":[152.208847,-32.414356],"type":"Point"}
}