{
  "type": "Feature",
  "properties": {
    "iso:country":"AU",
    "sg:address":"30 Sutherland Pl",
    "sg:city":"Golden Grove",
    "sg:classifiers":[
        {
            "category":"Building & Trades",
            "subcategory":"Landscaping Services",
            "type":"Services"
        }
    ],
    "sg:phone":"+61 8 8251 3352",
    "sg:postcode":"5125",
    "sg:province":"SA",
    "sg:tags":[
        "stump",
        "tree",
        "felling",
        "removal"
    ],
    "wof:name":"Get Stumped & More",
    "wof:placetype":"venue"
},
  "geometry": {"coordinates":[138.701706,-34.790245],"type":"Point"}
}