{
  "type": "Feature",
  "properties": {
    "addr:full":"50 Walder Rd Hammondville NSW 2170",
    "addr:housenumber":"50",
    "addr:postcode":"2170",
    "addr:street":"Walder Rd",
    "iso:country":"AU",
    "sg:address":"50 Walder Rd",
    "sg:city":"Hammondville",
    "sg:classifiers":[
        {
            "category":"Food & Beverages",
            "subcategory":"Bakery",
            "type":"Retail Goods"
        }
    ],
    "sg:phone":"+61 2 9825 4187",
    "sg:postcode":"2170",
    "sg:province":"NSW",
    "sg:tags":[
        "baker"
    ],
    "wof:name":"Hammondville Bakery",
    "wof:placetype":"venue"
},
  "geometry": {"coordinates":[150.95463562,-33.9483108521],"type":"Point"}
}