{
  "type": "Feature",
  "properties": {
    "addr:full":"140 Mollison St Kyneton VIC 3444",
    "addr:housenumber":"140",
    "addr:postcode":"3444",
    "addr:street":"Mollison St",
    "iso:country":"AU",
    "sg:address":"140 Mollison St",
    "sg:city":"Kyneton",
    "sg:classifiers":[
        {
            "category":"Shopping",
            "type":"Retail Goods"
        }
    ],
    "sg:phone":"+61 3 5422 1122",
    "sg:postcode":"3444",
    "sg:province":"VIC",
    "sg:tags":[
        "agent",
        "stock"
    ],
    "wof:name":"Dalgety Dwyer",
    "wof:placetype":"venue"
},
  "geometry": {"coordinates":[144.45379638700001,-37.2468948364],"type":"Point"}
}