{
  "type": "Feature",
  "properties": {
    "addr:full":"4 Bradbury La Horsham VIC 3400",
    "addr:housenumber":"4",
    "addr:postcode":"3400",
    "addr:street":"Bradbury La",
    "iso:country":"AU",
    "sg:address":"4 Bradbury La",
    "sg:city":"Horsham",
    "sg:classifiers":[
        {
            "category":"Personal",
            "subcategory":"Adult",
            "type":"Services"
        }
    ],
    "sg:phone":"+61 1300 304 340",
    "sg:postcode":"3400",
    "sg:province":"VIC",
    "sg:tags":[
        "product"
    ],
    "wof:name":"Murrays Adult World",
    "wof:placetype":"venue"
},
  "geometry": {"coordinates":[142.199417114,-36.7138442993],"type":"Point"}
}