{
  "type": "Feature",
  "properties": {
    "iso:country":"AU",
    "sg:address":"40 Yeoman Ave",
    "sg:city":"Metford",
    "sg:classifiers":[
        {
            "category":"Home & Garden",
            "subcategory":"Carpets & Floor Coverings",
            "type":"Retail Goods"
        }
    ],
    "sg:phone":"+61 2 4933 9215",
    "sg:postcode":"2323",
    "sg:province":"NSW",
    "sg:tags":[
        "tile",
        "wall",
        "layer"
    ],
    "wof:name":"Williams Robert",
    "wof:placetype":"venue"
},
  "geometry": {"coordinates":[151.610061645,-32.7702064514],"type":"Point"}
}