{
  "type": "Feature",
  "properties": {
    "iso:country":"AU",
    "sg:address":"Aldinga Beach Rd, Cnr How Rd",
    "sg:city":"Aldinga Beach",
    "sg:classifiers":[
        {
            "category":"Communications",
            "subcategory":"Film & Video Production",
            "type":"Services"
        }
    ],
    "sg:phone":"+61 8 8557 7294",
    "sg:postcode":"5173",
    "sg:province":"SA",
    "sg:tags":[
        "dvd",
        "library"
    ],
    "wof:name":"Aldinga Central Video",
    "wof:placetype":"venue"
},
  "geometry": {"coordinates":[138.470947266,-35.2745056152],"type":"Point"}
}