{
  "type": "Feature",
  "properties": {
    "iso:country":"AU",
    "sg:address":"75 Miller St",
    "sg:city":"North Sydney",
    "sg:classifiers":[
        {
            "category":"Professional",
            "subcategory":"Printing & Photocopies",
            "type":"Services"
        }
    ],
    "sg:phone":"+61 2 9929 5500",
    "sg:postcode":"2060",
    "sg:province":"NSW",
    "sg:tags":[
        "photocopying"
    ],
    "wof:name":"North Sydney Copy Centre",
    "wof:placetype":"venue"
},
  "geometry": {"coordinates":[151.206741333,-33.8401870728],"type":"Point"}
}