{
  "type": "Feature",
  "properties": {
    "iso:country":"AU",
    "sg:address":"2/ 17 Anzac Rd",
    "sg:city":"Tuggerah",
    "sg:classifiers":[
        {
            "category":"Health Services",
            "subcategory":"Doctor",
            "type":"Services"
        }
    ],
    "sg:phone":"+61 2 4351 8777",
    "sg:postcode":"2259",
    "sg:province":"NSW",
    "sg:tags":[
        "medical",
        "practitioner"
    ],
    "wof:name":"Central Coast Family Medicine",
    "wof:placetype":"venue"
},
  "geometry": {"coordinates":[151.41766357399999,-33.3067970276],"type":"Point"}
}