{
  "type": "Feature",
  "properties": {
    "addr:full":"PO Box 5011 Canning Vale WA 6155",
    "addr:postcode":"6155",
    "iso:country":"AU",
    "sg:address":"PO Box 5011",
    "sg:city":"Canning Vale",
    "sg:classifiers":[
        {
            "category":"Building & Trades",
            "subcategory":"Landscaping Services",
            "type":"Services"
        }
    ],
    "sg:phone":"+61 8 9313 8668",
    "sg:postcode":"6155",
    "sg:province":"WA",
    "sg:tags":[
        "inspection"
    ],
    "wof:name":"Aztech House Inspections",
    "wof:placetype":"venue"
},
  "geometry": {"coordinates":[115.92858099999999,-32.080261],"type":"Point"}
}