{
  "type": "Feature",
  "properties": {
    "addr:full":"49 Lodges Rd Narellan NSW 2567",
    "addr:housenumber":"49",
    "addr:postcode":"2567",
    "addr:street":"Lodges Rd",
    "iso:country":"AU",
    "sg:address":"49 Lodges Rd",
    "sg:city":"Narellan",
    "sg:classifiers":[
        {
            "category":"Social Services",
            "subcategory":"Adult Care",
            "type":"Services"
        }
    ],
    "sg:phone":"+61 2 4658 1040",
    "sg:postcode":"2567",
    "sg:province":"NSW",
    "sg:tags":[
        "aged"
    ],
    "wof:name":"Narellan Congregational Community Services",
    "wof:placetype":"venue"
},
  "geometry": {"coordinates":[150.731658936,-34.0515289307],"type":"Point"}
}