{
  "type": "Feature",
  "properties": {
    "iso:country":"AU",
    "sg:address":"406 Canning Hwy",
    "sg:city":"Bicton",
    "sg:classifiers":[
        {
            "category":"Sports & Exercise",
            "subcategory":"Gym",
            "type":"Entertainment"
        }
    ],
    "sg:phone":"+61 8 9339 7555",
    "sg:postcode":"6157",
    "sg:province":"WA",
    "sg:tags":[
        "personal",
        "trainer",
        "fitness"
    ],
    "wof:name":"Mind Body & Soul Fitness Studio",
    "wof:placetype":"venue"
},
  "geometry": {"coordinates":[115.783592,-32.036621],"type":"Point"}
}