{
  "type": "Feature",
  "properties": {
    "addr:full":"175 Howick St Bathurst NSW 2795",
    "addr:housenumber":"175",
    "addr:postcode":"2795",
    "addr:street":"Howick St",
    "iso:country":"AU",
    "sg:address":"175 Howick St",
    "sg:city":"Bathurst",
    "sg:classifiers":[
        {
            "category":"Health Services",
            "subcategory":"Optometrist",
            "type":"Services"
        }
    ],
    "sg:phone":"+61 2 6334 2000",
    "sg:postcode":"2795",
    "sg:province":"NSW",
    "wof:name":"Hansen Sean",
    "wof:placetype":"venue"
},
  "geometry": {"coordinates":[149.581130981,-33.4166679382],"type":"Point"}
}