{
  "type": "Feature",
  "properties": {
    "iso:country":"AU",
    "sg:address":"Unit 17/ 8 Booth Pl",
    "sg:city":"Balcatta",
    "sg:classifiers":[
        {
            "category":"Wholesale",
            "subcategory":"Machinery & Supplies",
            "type":"Manufacturing & Wholesale Goods"
        }
    ],
    "sg:phone":"+61 8 9240 1229",
    "sg:postcode":"6021",
    "sg:province":"WA",
    "sg:tags":[
        "equipment",
        "laboratory"
    ],
    "wof:name":"Applied Electronics Pty Ltd",
    "wof:placetype":"venue"
},
  "geometry": {"coordinates":[115.803169251,-31.8662052155],"type":"Point"}
}