{
  "type": "Feature",
  "properties": {
    "addr:full":"Stockland Super Centre Lake Rd Glendale NSW 2285",
    "addr:postcode":"2285",
    "addr:street":"Lake Rd",
    "iso:country":"AU",
    "sg:address":"Stockland Super Centre Lake Rd",
    "sg:city":"Glendale",
    "sg:classifiers":[
        {
            "category":"Cinema",
            "subcategory":"Movie Theater",
            "type":"Entertainment"
        }
    ],
    "sg:phone":"+61 2 4956 9331",
    "sg:postcode":"2285",
    "sg:province":"NSW",
    "wof:name":"The Greater Union Tower Cinemas",
    "wof:placetype":"venue"
},
  "geometry": {"coordinates":[151.64448547399999,-32.933506012],"type":"Point"}
}