{
  "type": "Feature",
  "properties": {
    "addr:full":"85 Franklin St Traralgon VIC 3844",
    "addr:housenumber":"85",
    "addr:postcode":"3844",
    "addr:street":"Franklin St",
    "iso:country":"AU",
    "sg:address":"85 Franklin St",
    "sg:city":"Traralgon",
    "sg:classifiers":[
        {
            "category":"Shopping",
            "subcategory":"Clothing, Apparel, & Fashions",
            "type":"Retail Goods"
        }
    ],
    "sg:phone":"+61 3 5174 1394",
    "sg:postcode":"3844",
    "sg:province":"VIC",
    "sg:tags":[
        "menswear"
    ],
    "wof:name":"Mensland",
    "wof:placetype":"venue"
},
  "geometry": {"coordinates":[146.53811645499999,-38.1965255737],"type":"Point"}
}