{
  "type": "Feature",
  "properties": {
    "iso:country":"AU",
    "sg:address":"100 Parr Pde",
    "sg:city":"Narraweena",
    "sg:classifiers":[
        {
            "category":"Education",
            "subcategory":"Music School",
            "type":"Public Place"
        }
    ],
    "sg:phone":"+61 2 9981 1668",
    "sg:postcode":"2099",
    "sg:province":"NSW",
    "sg:tags":[
        "teacher"
    ],
    "wof:name":"Teacher On Tap",
    "wof:placetype":"venue"
},
  "geometry": {"coordinates":[151.27020263700001,-33.7470855713],"type":"Point"}
}