{
  "type": "Feature",
  "properties": {
    "addr:full":"49 Cattai Ridge Rd Glenorie NSW 2157",
    "addr:housenumber":"49",
    "addr:postcode":"2157",
    "addr:street":"Cattai Ridge Rd",
    "iso:country":"AU",
    "sg:address":"49 Cattai Ridge Rd",
    "sg:city":"Glenorie",
    "sg:classifiers":[
        {
            "category":"Shopping",
            "subcategory":"Computers & Home Electronics",
            "type":"Retail Goods"
        }
    ],
    "sg:phone":"+61 2 9652 0525",
    "sg:postcode":"2157",
    "sg:province":"NSW",
    "sg:tags":[
        "equipment",
        "multimedia"
    ],
    "wof:name":"Cyber Interchange Australia",
    "wof:placetype":"venue"
},
  "geometry": {"coordinates":[151.00117492699999,-33.6175613403],"type":"Point"}
}