{
  "type": "Feature",
  "properties": {
    "addr:full":"2/ 12 Zenith St Dandenong VIC 3175",
    "addr:housenumber":"/ 12",
    "addr:postcode":"3175",
    "addr:street":"Zenith St",
    "iso:country":"AU",
    "sg:address":"2/ 12 Zenith St",
    "sg:city":"Dandenong",
    "sg:classifiers":[
        {
            "category":"Wholesale",
            "subcategory":"Furniture",
            "type":"Manufacturing & Wholesale Goods"
        }
    ],
    "sg:phone":"+61 3 9706 9225",
    "sg:postcode":"3175",
    "sg:province":"VIC",
    "sg:tags":[
        "wholesaler",
        "mfrs"
    ],
    "wof:name":"Officer Furniture Fair Pty Ltd",
    "wof:placetype":"venue"
},
  "geometry": {"coordinates":[145.220535278,-38.0201072693],"type":"Point"}
}