{
  "type": "Feature",
  "properties": {
    "iso:country":"AU",
    "sg:address":"1/ 156 Great Eastern Hwy",
    "sg:city":"Midland",
    "sg:classifiers":[
        {
            "category":"Autos & Motor Vehicles",
            "subcategory":"Auto Supplies",
            "type":"Retail Goods"
        }
    ],
    "sg:phone":"+61 8 9250 2866",
    "sg:postcode":"6056",
    "sg:province":"WA",
    "sg:tags":[
        "battery",
        "automotive"
    ],
    "wof:name":"Auto One Parts & Accessories",
    "wof:placetype":"venue"
},
  "geometry": {"coordinates":[116.00958252,-31.8909702301],"type":"Point"}
}