{
  "type": "Feature",
  "properties": {
    "iso:country":"AU",
    "sg:address":"255 Cressy St",
    "sg:city":"Deniliquin",
    "sg:classifiers":[
        {
            "category":"Shopping",
            "subcategory":"Clothing, Apparel, & Fashions",
            "type":"Retail Goods"
        }
    ],
    "sg:phone":"+61 3 5881 7237",
    "sg:postcode":"2710",
    "sg:province":"NSW",
    "sg:tags":[
        "lady",
        "wear"
    ],
    "wof:name":"Rockmans Stores Ltd",
    "wof:placetype":"venue"
},
  "geometry": {"coordinates":[144.96177673299999,-35.5278739929],"type":"Point"}
}