{
  "type": "Feature",
  "properties": {
    "addr:full":"Suite 2/ 319a Neerim Rd Carnegie VIC 3163",
    "addr:housenumber":"319a",
    "addr:postcode":"3163",
    "addr:street":"Neerim Rd",
    "iso:country":"AU",
    "sg:address":"Suite 2/ 319a Neerim Rd",
    "sg:city":"Carnegie",
    "sg:classifiers":[
        {
            "category":"Building & Trades",
            "subcategory":"Construction",
            "type":"Services"
        }
    ],
    "sg:phone":"+61 3 9569 8100",
    "sg:postcode":"3163",
    "sg:province":"VIC",
    "sg:tags":[
        "contractor"
    ],
    "wof:name":"Highland Properties Pty Ltd",
    "wof:placetype":"venue"
},
  "geometry": {"coordinates":[145.057662964,-37.889377594],"type":"Point"}
}