{
  "type": "Feature",
  "properties": {
    "addr:full":"157 Merriang Rd Myrtleford VIC 3737",
    "addr:housenumber":"157",
    "addr:postcode":"3737",
    "addr:street":"Merriang Rd",
    "iso:country":"AU",
    "sg:address":"157 Merriang Rd",
    "sg:city":"Myrtleford",
    "sg:classifiers":[
        {
            "category":"Building & Trades",
            "subcategory":"Construction",
            "type":"Services"
        }
    ],
    "sg:phone":"+61 3 5752 2097",
    "sg:postcode":"3737",
    "sg:province":"VIC",
    "sg:tags":[
        "road",
        "contractor"
    ],
    "wof:name":"Crameri Enterprise Pty Ltd",
    "wof:placetype":"venue"
},
  "geometry": {"coordinates":[146.699829102,-36.5633392334],"type":"Point"}
}