{
  "type": "Feature",
  "properties": {
    "addr:full":"56 Rudd St Toowoomba QLD 4350",
    "addr:housenumber":"56",
    "addr:postcode":"4350",
    "addr:street":"Rudd St",
    "iso:country":"AU",
    "sg:address":"56 Rudd St",
    "sg:city":"Toowoomba",
    "sg:classifiers":[
        {
            "category":"Professional",
            "subcategory":"Accounting & Tax Preparation",
            "type":"Services"
        }
    ],
    "sg:phone":"+61 7 4630 2309",
    "sg:postcode":"4350",
    "sg:province":"QLD",
    "sg:tags":[
        "bookkeeping"
    ],
    "wof:name":"Robynlea Briskey Bookkeeping",
    "wof:placetype":"venue"
},
  "geometry": {"coordinates":[151.91177400000001,-27.60273],"type":"Point"}
}