{
  "type": "Feature",
  "properties": {
    "addr:full":"54 Ross St Newstead QLD 4006",
    "addr:housenumber":"54",
    "addr:postcode":"4006",
    "addr:street":"Ross St",
    "iso:country":"AU",
    "sg:address":"54 Ross St",
    "sg:city":"Newstead",
    "sg:classifiers":[
        {
            "category":"Autos & Motor Vehicles",
            "subcategory":"Auto Supplies",
            "type":"Retail Goods"
        }
    ],
    "sg:phone":"+61 7 3252 5691",
    "sg:postcode":"4006",
    "sg:province":"QLD",
    "sg:tags":[
        "part",
        "cycles",
        "accessory"
    ],
    "wof:name":"Buell",
    "wof:placetype":"venue"
},
  "geometry": {"coordinates":[153.043334961,-27.4419078827],"type":"Point"}
}