{
  "type": "Feature",
  "properties": {
    "addr:full":"5 Henry St Emu Park QLD 4710",
    "addr:housenumber":"5",
    "addr:postcode":"4710",
    "addr:street":"Henry St",
    "iso:country":"AU",
    "sg:address":"5 Henry St",
    "sg:city":"Emu Park",
    "sg:classifiers":[
        {
            "category":"Retail",
            "subcategory":"Auto Repair",
            "type":"Services"
        }
    ],
    "sg:phone":"+61 7 4939 6343",
    "sg:postcode":"4710",
    "sg:province":"QLD",
    "sg:tags":[
        "repairer",
        "motor",
        "engineer"
    ],
    "wof:name":"Zilzie Workshop",
    "wof:placetype":"venue"
},
  "geometry": {"coordinates":[150.81308000000001,-23.255016],"type":"Point"}
}