{
  "type": "Feature",
  "properties": {
    "addr:full":"15 First Ave Sawtell NSW 2452",
    "addr:housenumber":"15",
    "addr:postcode":"2452",
    "addr:street":"First Ave",
    "iso:country":"AU",
    "sg:address":"15 First Ave",
    "sg:city":"Sawtell",
    "sg:classifiers":[
        {
            "category":"Shopping",
            "subcategory":"Jewelry",
            "type":"Retail Goods"
        }
    ],
    "sg:phone":"+61 2 6658 4877",
    "sg:postcode":"2452",
    "sg:province":"NSW",
    "sg:tags":[
        "jeweller"
    ],
    "wof:name":"Lisbeth E Jewellery",
    "wof:placetype":"venue"
},
  "geometry": {"coordinates":[153.090576,-30.35095],"type":"Point"}
}