{
  "type": "Feature",
  "properties": {
    "addr:full":"Suite 2, 9- 11 Knox St Double Bay NSW 2028",
    "addr:housenumber":"9 11",
    "addr:postcode":"2028",
    "addr:street":"Knox St",
    "iso:country":"AU",
    "sg:address":"Suite 2, 9- 11 Knox St",
    "sg:city":"Double Bay",
    "sg:classifiers":[
        {
            "category":"Health Services",
            "subcategory":"Doctor",
            "type":"Services"
        }
    ],
    "sg:phone":"+61 2 9380 4507",
    "sg:postcode":"2028",
    "sg:province":"NSW",
    "sg:tags":[
        "medical",
        "practitioner"
    ],
    "wof:name":"Epstein Julie Dr",
    "wof:placetype":"venue"
},
  "geometry": {"coordinates":[151.24285888700001,-33.8769836426],"type":"Point"}
}