{
  "type": "Feature",
  "properties": {
    "iso:country":"AU",
    "sg:address":"Penney St",
    "sg:city":"Goolgowi",
    "sg:classifiers":[
        {
            "category":"Education",
            "subcategory":"School",
            "type":"Public Place"
        }
    ],
    "sg:phone":"+61 2 6965 1207",
    "sg:postcode":"2652",
    "sg:province":"NSW",
    "sg:tags":[
        "state",
        "-",
        "nsw"
    ],
    "wof:name":"Goolgowi Public School",
    "wof:placetype":"venue"
},
  "geometry": {"coordinates":[145.71424865700001,-33.9754905701],"type":"Point"}
}