{
  "type": "Feature",
  "properties": {
    "addr:full":"6 Terminalia St Redlynch QLD 4870",
    "addr:housenumber":"6",
    "addr:postcode":"4870",
    "addr:street":"Terminalia St",
    "iso:country":"AU",
    "sg:address":"6 Terminalia St",
    "sg:city":"Redlynch",
    "sg:classifiers":[
        {
            "category":"Communications",
            "subcategory":"News Services",
            "type":"Services"
        }
    ],
    "sg:phone":"+61 7 4039 0315",
    "sg:postcode":"4870",
    "sg:province":"QLD",
    "sg:tags":[
        "information",
        "tourist",
        "attractions"
    ],
    "wof:name":"Skywalker Tours",
    "wof:placetype":"venue"
},
  "geometry": {"coordinates":[145.68980407699999,-16.8902835846],"type":"Point"}
}