{
  "type": "Feature",
  "properties": {
    "iso:country":"AU",
    "sg:address":"47 Barnes St",
    "sg:city":"Tamworth",
    "sg:classifiers":[
        {
            "category":"Manufacturing",
            "subcategory":"Motor Vehicles & Parts",
            "type":"Manufacturing & Wholesale Goods"
        }
    ],
    "sg:phone":"+61 2 6765 7600",
    "sg:postcode":"2340",
    "sg:province":"NSW",
    "sg:tags":[
        "engine",
        "equipment",
        "diesel"
    ],
    "wof:name":"A Transpacific Industries Group Company",
    "wof:placetype":"venue"
},
  "geometry": {"coordinates":[150.91261291500001,-31.0908527374],"type":"Point"}
}