{
  "type": "Feature",
  "properties": {
    "iso:country":"AU",
    "sg:address":"PO Box 693",
    "sg:city":"Bega",
    "sg:classifiers":[
        {
            "category":"Wholesale",
            "subcategory":"Machinery & Supplies",
            "type":"Manufacturing & Wholesale Goods"
        }
    ],
    "sg:phone":"+61 408 489 579",
    "sg:postcode":"2550",
    "sg:province":"NSW",
    "sg:tags":[
        "equipment",
        "hydraulic"
    ],
    "wof:name":"Sapphire Coast Hydraulics",
    "wof:placetype":"venue"
},
  "geometry": {"coordinates":[149.84138488799999,-36.6739883423],"type":"Point"}
}