{
  "type": "Feature",
  "properties": {
    "addr:full":"PO Box 492 Willetton Private Box WA 6955",
    "addr:postcode":"6955",
    "iso:country":"AU",
    "sg:address":"PO Box 492",
    "sg:city":"Willetton Private Box",
    "sg:classifiers":[
        {
            "category":"Home & Garden",
            "subcategory":"Carpets & Floor Coverings",
            "type":"Retail Goods"
        }
    ],
    "sg:phone":"+61 413 806 494",
    "sg:postcode":"6955",
    "sg:province":"WA",
    "wof:name":"Broom Zoom Cleaning Services",
    "wof:placetype":"venue"
},
  "geometry": {"coordinates":[115.881530762,-32.053150177],"type":"Point"}
}