{
  "type": "Feature",
  "properties": {
    "addr:full":"Unit 1 54- 58 Wellington Rd South Granville NSW 2142",
    "addr:housenumber":"54 58",
    "addr:postcode":"2142",
    "addr:street":"Wellington Rd",
    "iso:country":"AU",
    "sg:address":"Unit 1 54- 58 Wellington Rd",
    "sg:city":"South Granville",
    "sg:classifiers":[
        {
            "category":"Home & Garden",
            "subcategory":"Carpets & Floor Coverings",
            "type":"Retail Goods"
        }
    ],
    "sg:phone":"+61 2 9632 8387",
    "sg:postcode":"2142",
    "sg:province":"NSW",
    "sg:tags":[
        "tile",
        "wall"
    ],
    "wof:name":"Berry Tiles",
    "wof:placetype":"venue"
},
  "geometry": {"coordinates":[151.010055542,-33.8627586365],"type":"Point"}
}