{
  "type": "Feature",
  "properties": {
    "addr:full":"Sd7/ 84 Ingleston Rd Wakerley QLD 4154",
    "addr:housenumber":"sd7 / 84",
    "addr:postcode":"4154",
    "addr:street":"Ingleston Rd",
    "iso:country":"AU",
    "sg:address":"Sd7/ 84 Ingleston Rd",
    "sg:city":"Wakerley",
    "sg:classifiers":[
        {
            "category":"Professional",
            "type":"Services"
        }
    ],
    "sg:phone":"+61 7 3890 1119",
    "sg:postcode":"4154",
    "sg:province":"QLD",
    "sg:tags":[
        "transport"
    ],
    "wof:name":"Jmb Haulage Pty Ltd",
    "wof:placetype":"venue"
},
  "geometry": {"coordinates":[153.142669678,-27.4816169739],"type":"Point"}
}