{
  "type": "Feature",
  "properties": {
    "iso:country":"AU",
    "sg:address":"148 Newton Rd",
    "sg:city":"Wetherill Park",
    "sg:classifiers":[
        {
            "category":"Professional",
            "type":"Services"
        }
    ],
    "sg:phone":"+61 2 9756 5611",
    "sg:postcode":"2164",
    "sg:province":"NSW",
    "sg:tags":[
        "forwarding",
        "agent",
        "transport"
    ],
    "wof:name":"NSW Freight Management Services",
    "wof:placetype":"venue"
},
  "geometry": {"coordinates":[150.88946533199999,-33.8388938904],"type":"Point"}
}