{
  "type": "Feature",
  "properties": {
    "iso:country":"AU",
    "sg:address":"Unit 1, 30 Yarranabbe Rd",
    "sg:city":"Darling Point",
    "sg:classifiers":[
        {
            "category":"Sports & Exercise",
            "subcategory":"Gym",
            "type":"Entertainment"
        }
    ],
    "sg:phone":"+61 2 9328 1973",
    "sg:postcode":"2027",
    "sg:province":"NSW",
    "sg:tags":[
        "meditation"
    ],
    "wof:name":"Well Awareness",
    "wof:placetype":"venue"
},
  "geometry": {"coordinates":[151.236862183,-33.8715171814],"type":"Point"}
}