{
  "type": "Feature",
  "properties": {
    "addr:full":"Your Health Manly 15 South Steyne St Manly NSW 2095",
    "addr:housenumber":"15",
    "addr:postcode":"2095",
    "addr:street":"South Steyne St",
    "iso:country":"AU",
    "sg:address":"Your Health Manly 15 South Steyne St",
    "sg:city":"Manly",
    "sg:classifiers":[
        {
            "category":"Health Services",
            "subcategory":"Doctor",
            "type":"Services"
        }
    ],
    "sg:phone":"+61 2 9977 7888",
    "sg:postcode":"2095",
    "sg:province":"NSW",
    "sg:tags":[
        "medical",
        "practitioner"
    ],
    "wof:name":"Varipatis Emmanuel Dr",
    "wof:placetype":"venue"
},
  "geometry": {"coordinates":[151.28981018100001,-33.799659729],"type":"Point"}
}