{
  "type": "Feature",
  "properties": {
    "addr:full":"Park Village Shopping Centre 27 Riverhills Rd Middle Park QLD 4074",
    "addr:housenumber":"27",
    "addr:postcode":"4074",
    "addr:street":"Riverhills Rd",
    "iso:country":"AU",
    "sg:address":"Park Village Shopping Centre 27 Riverhills Rd",
    "sg:city":"Middle Park",
    "sg:classifiers":[
        {
            "category":"Real Estate",
            "subcategory":"Real Estate Agent",
            "type":"Services"
        }
    ],
    "sg:phone":"+61 7 3279 4777",
    "sg:postcode":"4074",
    "sg:province":"QLD",
    "wof:name":"Lowthian Heathcote Realty",
    "wof:placetype":"venue"
},
  "geometry": {"coordinates":[152.92228698700001,-27.5562858582],"type":"Point"}
}