{
  "type": "Feature",
  "properties": {
    "addr:full":"154- 162 Cavendish Rd Coorparoo QLD 4151",
    "addr:housenumber":"162",
    "addr:postcode":"4151",
    "addr:street":"Cavendish Rd",
    "iso:country":"AU",
    "sg:address":"154- 162 Cavendish Rd",
    "sg:city":"Coorparoo",
    "sg:classifiers":[
        {
            "category":"Banks & Credit Unions",
            "subcategory":"Bank",
            "type":"Services"
        }
    ],
    "sg:phone":"+61 13 20 32",
    "sg:postcode":"4151",
    "sg:province":"QLD",
    "wof:name":"Westpac",
    "wof:placetype":"venue"
},
  "geometry": {"coordinates":[153.058792114,-27.4935760498],"type":"Point"}
}