{
  "type": "Feature",
  "properties": {
    "iso:country":"AU",
    "sg:address":"Shp 4 26 Kalamunda Rd",
    "sg:city":"South Guildford",
    "sg:classifiers":[
        {
            "category":"Fast Food",
            "type":"Food & Drink"
        }
    ],
    "sg:phone":"+61 8 9377 1888",
    "sg:postcode":"6055",
    "sg:province":"WA",
    "sg:tags":[
        "away",
        "take"
    ],
    "wof:name":"South Guildford Lunchbox",
    "wof:placetype":"venue"
},
  "geometry": {"coordinates":[115.969017,-31.911757],"type":"Point"}
}