{
  "type": "Feature",
  "properties": {
    "addr:full":"217 High St Shepparton VIC 3630",
    "addr:housenumber":"217",
    "addr:postcode":"3630",
    "addr:street":"High St",
    "iso:country":"AU",
    "sg:address":"217 High St",
    "sg:city":"Shepparton",
    "sg:classifiers":[
        {
            "category":"Shopping",
            "subcategory":"Music",
            "type":"Retail Goods"
        }
    ],
    "sg:phone":"+61 3 5831 1787",
    "sg:postcode":"3630",
    "sg:province":"VIC",
    "sg:tags":[
        "instrument",
        "musical"
    ],
    "wof:name":"Schier Music",
    "wof:placetype":"venue"
},
  "geometry": {"coordinates":[145.40577697800001,-36.3817901611],"type":"Point"}
}