{
  "type": "Feature",
  "properties": {
    "iso:country":"AU",
    "sg:address":"45 Gordon Rd (East)",
    "sg:city":"Osborne Park",
    "sg:classifiers":[
        {
            "category":"Building & Trades",
            "subcategory":"Construction",
            "type":"Services"
        }
    ],
    "sg:phone":"+61 411 494 860",
    "sg:postcode":"6017",
    "sg:province":"WA",
    "sg:tags":[
        "renovation",
        "alterations",
        "extension",
        "contractor"
    ],
    "wof:name":"Moschilla Builders",
    "wof:placetype":"venue"
},
  "geometry": {"coordinates":[115.823036194,-31.9067554474],"type":"Point"}
}