{
  "type": "Feature",
  "properties": {
    "iso:country":"AU",
    "sg:address":"Unit 2, 7 St James Ave",
    "sg:city":"Mont Albert",
    "sg:classifiers":[
        {
            "category":"Shopping",
            "subcategory":"Pets & Pet Supplies",
            "type":"Retail Goods"
        }
    ],
    "sg:phone":"+61 3 9898 2372",
    "sg:postcode":"3127",
    "sg:province":"VIC",
    "sg:tags":[
        "equipment",
        "ceramic"
    ],
    "wof:name":"Ceramcal",
    "wof:placetype":"venue"
},
  "geometry": {"coordinates":[145.108551025,-37.8233795166],"type":"Point"}
}