{
  "type": "Feature",
  "properties": {
    "iso:country":"AU",
    "sg:address":"Glen Orme Ave",
    "sg:city":"Ormond",
    "sg:classifiers":[
        {
            "category":"Education",
            "subcategory":"School",
            "type":"Public Place"
        }
    ],
    "sg:phone":"+61 3 9578 1182",
    "sg:postcode":"3204",
    "sg:province":"VIC",
    "sg:tags":[
        "co-educational"
    ],
    "wof:name":"St Kevin's Primary",
    "wof:placetype":"venue"
},
  "geometry": {"coordinates":[145.03825399999999,-37.904793],"type":"Point"}
}