{
  "type": "Feature",
  "properties": {
    "addr:full":"66 Arcadia Drv Mermaid Waters QLD 4218",
    "addr:housenumber":"66",
    "addr:postcode":"4218",
    "addr:street":"Arcadia Drv",
    "iso:country":"AU",
    "sg:address":"66 Arcadia Drv",
    "sg:city":"Mermaid Waters",
    "sg:classifiers":[
        {
            "category":"Structure",
            "subcategory":"Office Building",
            "type":"Public Place"
        }
    ],
    "sg:phone":"+61 7 5572 0909",
    "sg:postcode":"4218",
    "sg:province":"QLD",
    "sg:tags":[
        "slater",
        "tiler",
        "roof"
    ],
    "wof:name":"A Abandon Roof Tile Problems",
    "wof:placetype":"venue"
},
  "geometry": {"coordinates":[153.426879883,-28.0494995117],"type":"Point"}
}