{
  "type": "Feature",
  "properties": {
    "addr:full":"9 Killara Rd Campbellfield VIC 3061",
    "addr:housenumber":"9",
    "addr:postcode":"3061",
    "addr:street":"Killara Rd",
    "iso:country":"AU",
    "sg:address":"9 Killara Rd",
    "sg:city":"Campbellfield",
    "sg:classifiers":[
        {
            "category":"Retail",
            "subcategory":"Auto Repair",
            "type":"Services"
        }
    ],
    "sg:phone":"+61 3 9357 0795",
    "sg:postcode":"3061",
    "sg:province":"VIC",
    "sg:tags":[
        "repairer",
        "motor",
        "engineer"
    ],
    "wof:name":"Riolos Automotive",
    "wof:placetype":"venue"
},
  "geometry": {"coordinates":[144.963790894,-37.6676139832],"type":"Point"}
}