{
  "type": "Feature",
  "properties": {
    "iso:country":"AU",
    "sg:address":"Shp5/ 11",
    "sg:city":"Minorca Cl Toormina",
    "sg:classifiers":[
        {
            "category":"Cafe",
            "type":"Food & Drink"
        }
    ],
    "sg:phone":"+61 2 6658 1480",
    "sg:postcode":"2452",
    "sg:province":"NSW",
    "wof:name":"Rock&#039;n & Cruz&#039;n Cafe",
    "wof:placetype":"venue"
},
  "geometry": {"coordinates":[153.090729,-30.352793],"type":"Point"}
}