{
  "type": "Feature",
  "properties": {
    "addr:full":"12 Riverleigh Drv North Mackay QLD 4740",
    "addr:housenumber":"12",
    "addr:postcode":"4740",
    "addr:street":"Riverleigh Drv",
    "iso:country":"AU",
    "sg:address":"12 Riverleigh Drv",
    "sg:city":"North Mackay",
    "sg:classifiers":[
        {
            "category":"Building & Trades",
            "subcategory":"Construction",
            "type":"Services"
        }
    ],
    "sg:phone":"+61 7 4942 6898",
    "sg:postcode":"4740",
    "sg:province":"QLD",
    "sg:tags":[
        "contractor"
    ],
    "wof:name":"Hotondo Building Services",
    "wof:placetype":"venue"
},
  "geometry": {"coordinates":[149.168915,-21.129557],"type":"Point"}
}