{
  "type": "Feature",
  "properties": {
    "addr:full":"2450 Gold Coast Hwy Mermaid Beach QLD 4218",
    "addr:housenumber":"2450",
    "addr:postcode":"4218",
    "addr:street":"Gold Coast Hwy",
    "iso:country":"AU",
    "sg:address":"2450 Gold Coast Hwy",
    "sg:city":"Mermaid Beach",
    "sg:classifiers":[
        {
            "category":"Building & Trades",
            "subcategory":"Construction",
            "type":"Services"
        }
    ],
    "sg:phone":"+61 7 5526 1122",
    "sg:postcode":"4218",
    "sg:province":"QLD",
    "sg:tags":[
        "pool",
        "swimming"
    ],
    "wof:name":"Pool Warehouse Gold Coast",
    "wof:placetype":"venue"
},
  "geometry": {"coordinates":[153.434814453,-28.0456008911],"type":"Point"}
}