{
  "type": "Feature",
  "properties": {
    "addr:full":"227 Autumn St Geelong West VIC 3218",
    "addr:housenumber":"227",
    "addr:postcode":"3218",
    "addr:street":"Autumn St",
    "iso:country":"AU",
    "sg:address":"227 Autumn St",
    "sg:city":"Geelong West",
    "sg:classifiers":[
        {
            "category":"Personal",
            "type":"Services"
        }
    ],
    "sg:phone":"+61 1300 550 976",
    "sg:postcode":"3218",
    "sg:province":"VIC",
    "sg:tags":[
        "gift"
    ],
    "wof:name":"The Australian Wedding Company",
    "wof:placetype":"venue"
},
  "geometry": {"coordinates":[144.336334228,-38.1417541504],"type":"Point"}
}