{
  "type": "Feature",
  "properties": {
    "addr:full":"31 Richard St Maryborough QLD 4650",
    "addr:housenumber":"31",
    "addr:postcode":"4650",
    "addr:street":"Richard St",
    "iso:country":"AU",
    "sg:address":"31 Richard St",
    "sg:city":"Maryborough",
    "sg:classifiers":[
        {
            "category":"Personal",
            "type":"Services"
        }
    ],
    "sg:phone":"+61 7 4121 7299",
    "sg:postcode":"4650",
    "sg:province":"QLD",
    "sg:tags":[
        "dressmaker"
    ],
    "wof:name":"Jeannette Russell",
    "wof:placetype":"venue"
},
  "geometry": {"coordinates":[152.678406,-25.527315],"type":"Point"}
}