{
  "type": "Feature",
  "properties": {
    "iso:country":"AU",
    "sg:address":"243 Peel St",
    "sg:city":"North Melbourne",
    "sg:classifiers":[
        {
            "category":"Wholesale",
            "subcategory":"Seafood",
            "type":"Manufacturing & Wholesale Goods"
        }
    ],
    "sg:phone":"+61 3 9348 9452",
    "sg:postcode":"3051",
    "sg:province":"VIC",
    "sg:tags":[
        "fish"
    ],
    "wof:name":"Allseas International",
    "wof:placetype":"venue"
},
  "geometry": {"coordinates":[144.956466675,-37.8015518188],"type":"Point"}
}