{
  "type": "Feature",
  "properties": {
    "iso:country":"AU",
    "sg:address":"Shop 4, 264- 266 Pinjarra Rd",
    "sg:city":"Mandurah",
    "sg:classifiers":[
        {
            "category":"Shopping",
            "subcategory":"Bicycles & Sporting Goods",
            "type":"Retail Goods"
        }
    ],
    "sg:phone":"+61 8 9535 1529",
    "sg:postcode":"6210",
    "sg:province":"WA",
    "sg:tags":[
        "chemical",
        "equipment",
        "pool",
        "swimming"
    ],
    "wof:name":"Mandurah Pools & Spas",
    "wof:placetype":"venue"
},
  "geometry": {"coordinates":[115.781464,-32.554134],"type":"Point"}
}