{
  "type": "Feature",
  "properties": {
    "iso:country":"AU",
    "sg:address":"Units 5 393 Crown St",
    "sg:city":"Wollongong",
    "sg:classifiers":[
        {
            "category":"Health Services",
            "subcategory":"Medical Lab",
            "type":"Services"
        }
    ],
    "sg:phone":"+61 2 4228 1333",
    "sg:postcode":"2500",
    "sg:province":"NSW",
    "sg:tags":[
        "laboratory",
        "pathology"
    ],
    "wof:name":"General Clinical Laboratories-Pathology",
    "wof:placetype":"venue"
},
  "geometry": {"coordinates":[150.876892,-34.425823],"type":"Point"}
}