{
  "type": "Feature",
  "properties": {
    "addr:full":"36 Crinan St Hurlstone Park NSW 2193",
    "addr:housenumber":"36",
    "addr:postcode":"2193",
    "addr:street":"Crinan St",
    "iso:country":"AU",
    "sg:address":"36 Crinan St",
    "sg:city":"Hurlstone Park",
    "sg:classifiers":[
        {
            "category":"Organizations",
            "subcategory":"Professional Association",
            "type":"Services"
        }
    ],
    "sg:phone":"+61 2 9559 2629",
    "sg:postcode":"2193",
    "sg:province":"NSW",
    "sg:tags":[
        "web",
        "internet"
    ],
    "wof:name":"Mort Bay Communications Pty Ltd",
    "wof:placetype":"venue"
},
  "geometry": {"coordinates":[151.13125600000001,-33.909351],"type":"Point"}
}