{
  "type": "Feature",
  "properties": {
    "iso:country":"AU",
    "sg:address":"170 Grange Rd",
    "sg:city":"Fairfield",
    "sg:classifiers":[
        {
            "category":"Autos & Motor Vehicles",
            "subcategory":"Auto Supplies",
            "type":"Retail Goods"
        }
    ],
    "sg:phone":"+61 3 9499 7522",
    "sg:postcode":"3078",
    "sg:province":"VIC",
    "sg:tags":[
        "tyre"
    ],
    "wof:name":"Darebin Tyre & Service Centre",
    "wof:placetype":"venue"
},
  "geometry": {"coordinates":[145.026977539,-37.7695960999],"type":"Point"}
}