{
  "type": "Feature",
  "properties": {
    "addr:full":"165-173 Annesley St Echuca VIC 3564",
    "addr:housenumber":"165-173",
    "addr:postcode":"3564",
    "addr:street":"Annesley St",
    "iso:country":"AU",
    "sg:address":"165-173 Annesley St",
    "sg:city":"Echuca",
    "sg:classifiers":[
        {
            "category":"Retail",
            "subcategory":"Event Space",
            "type":"Services"
        }
    ],
    "sg:phone":"+61 3 5482 3140",
    "sg:postcode":"3564",
    "sg:province":"VIC",
    "sg:tags":[
        "venue",
        "reception",
        "wedding"
    ],
    "wof:name":"Echuca Workers & Services Club",
    "wof:placetype":"venue"
},
  "geometry": {"coordinates":[144.75157165499999,-36.127166748],"type":"Point"}
}