{
  "type": "Feature",
  "properties": {
    "addr:full":"747 Marion Rd Ascot Park SA 5043",
    "addr:housenumber":"747",
    "addr:postcode":"5043",
    "addr:street":"Marion Rd",
    "iso:country":"AU",
    "sg:address":"747 Marion Rd",
    "sg:city":"Ascot Park",
    "sg:classifiers":[
        {
            "category":"Autos & Motor Vehicles",
            "subcategory":"Automobile Sales",
            "type":"Retail Goods"
        }
    ],
    "sg:phone":"+61 8 8299 0288",
    "sg:postcode":"5043",
    "sg:province":"SA",
    "sg:tags":[
        "car",
        "used"
    ],
    "wof:name":"Peter's Used Car Company",
    "wof:placetype":"venue"
},
  "geometry": {"coordinates":[138.557053,-34.991989],"type":"Point"}
}