{
  "type": "Feature",
  "properties": {
    "iso:country":"AU",
    "sg:address":"65 York St",
    "sg:city":"Sydney",
    "sg:classifiers":[
        {
            "category":"Social Services",
            "subcategory":"Retirement Home",
            "type":"Services"
        }
    ],
    "sg:phone":"+61 2 9299 3615",
    "sg:postcode":"2000",
    "sg:province":"NSW",
    "sg:tags":[
        "environmental",
        "consultant",
        "pollution"
    ],
    "wof:name":"Building Healthcare Services",
    "wof:placetype":"venue"
},
  "geometry": {"coordinates":[151.20579528799999,-33.8678817749],"type":"Point"}
}