{
  "type": "Feature",
  "properties": {
    "iso:country":"AU",
    "sg:address":"PO Box 42",
    "sg:city":"Preston",
    "sg:classifiers":[
        {
            "category":"Professional",
            "subcategory":"Detective & Security Services",
            "type":"Services"
        }
    ],
    "sg:phone":"+61 3 9466 3000",
    "sg:postcode":"3072",
    "sg:province":"VIC",
    "sg:tags":[
        "consultant",
        "system"
    ],
    "wof:name":"Dateline Security Service P/L",
    "wof:placetype":"venue"
},
  "geometry": {"coordinates":[145.00909423799999,-37.7416496277],"type":"Point"}
}