{
  "type": "Feature",
  "properties": {
    "addr:full":"98 Best St Wagga Wagga NSW 2650",
    "addr:housenumber":"98",
    "addr:postcode":"2650",
    "addr:street":"Best St",
    "iso:country":"AU",
    "sg:address":"98 Best St",
    "sg:city":"Wagga Wagga",
    "sg:classifiers":[
        {
            "category":"Health Services",
            "subcategory":"Doctor",
            "type":"Services"
        }
    ],
    "sg:phone":"+61 2 6931 8511",
    "sg:postcode":"2650",
    "sg:province":"NSW",
    "sg:tags":[
        "medical",
        "practitioner"
    ],
    "wof:name":"Sharma A K Dr",
    "wof:placetype":"venue"
},
  "geometry": {"coordinates":[147.36677551299999,-35.1126785278],"type":"Point"}
}