{
  "type": "Feature",
  "properties": {
    "addr:full":"Cnr Abbott & Minnie Sts Cairns QLD 4870",
    "addr:housenumber":"cnr",
    "addr:postcode":"4870",
    "addr:street":"Abbott &;Sts",
    "iso:country":"AU",
    "sg:address":"Cnr Abbott & Minnie Sts",
    "sg:city":"Cairns",
    "sg:classifiers":[
        {
            "category":"Health Services",
            "subcategory":"Optometrist",
            "type":"Services"
        }
    ],
    "sg:phone":"+61 7 4051 6795",
    "sg:postcode":"4870",
    "sg:province":"QLD",
    "wof:name":"Bruce Mellick Optometry",
    "wof:placetype":"venue"
},
  "geometry": {"coordinates":[145.761627197,-16.9246749878],"type":"Point"}
}