{
  "type": "Feature",
  "properties": {
    "addr:full":"12 Anderson St Yarraville VIC 3013",
    "addr:housenumber":"12",
    "addr:postcode":"3013",
    "addr:street":"Anderson St",
    "iso:country":"AU",
    "sg:address":"12 Anderson St",
    "sg:city":"Yarraville",
    "sg:classifiers":[
        {
            "category":"Food & Beverages",
            "subcategory":"Supermarket",
            "type":"Retail Goods"
        }
    ],
    "sg:phone":"+61 3 9687 2113",
    "sg:postcode":"3013",
    "sg:province":"VIC",
    "sg:tags":[
        "grocery",
        "store"
    ],
    "wof:name":"Foodtown",
    "wof:placetype":"venue"
},
  "geometry": {"coordinates":[144.89149475100001,-37.8165969849],"type":"Point"}
}