{
  "type": "Feature",
  "properties": {
    "iso:country":"AU",
    "sg:address":"445 Belgrave/Gembrook Rd",
    "sg:city":"Avonsleigh",
    "sg:classifiers":[
        {
            "category":"Fast Food",
            "type":"Food & Drink"
        }
    ],
    "sg:phone":"+61 3 5968 4455",
    "sg:postcode":"3782",
    "sg:province":"VIC",
    "sg:tags":[
        "away",
        "take"
    ],
    "wof:name":"Si Si Pizza",
    "wof:placetype":"venue"
},
  "geometry": {"coordinates":[145.468887,-37.921707],"type":"Point"}
}