{
  "type": "Feature",
  "properties": {
    "addr:full":"582 Heidelberg Rd Fairfield VIC 3078",
    "addr:housenumber":"582",
    "addr:postcode":"3078",
    "addr:street":"Heidelberg Rd",
    "iso:country":"AU",
    "sg:address":"582 Heidelberg Rd",
    "sg:city":"Fairfield",
    "sg:classifiers":[
        {
            "category":"Health Services",
            "subcategory":"Medical Lab",
            "type":"Services"
        }
    ],
    "sg:phone":"+61 3 9882 9940",
    "sg:postcode":"3078",
    "sg:province":"VIC",
    "sg:tags":[
        "laboratory",
        "pathology"
    ],
    "wof:name":"Skin And Cancer Pathology",
    "wof:placetype":"venue"
},
  "geometry": {"coordinates":[145.02456665,-37.7820663452],"type":"Point"}
}