{
  "type": "Feature",
  "properties": {
    "iso:country":"AU",
    "sg:address":"15- 17 Intrepid St",
    "sg:city":"Jamboree Heights",
    "sg:classifiers":[
        {
            "category":"Social Services",
            "subcategory":"Child Care",
            "type":"Services"
        }
    ],
    "sg:phone":"+61 7 3279 1575",
    "sg:postcode":"4074",
    "sg:province":"QLD",
    "wof:name":"Kiah Occasional Early Childhood Centre",
    "wof:placetype":"venue"
},
  "geometry": {"coordinates":[152.93638610799999,-27.5593147278],"type":"Point"}
}