{
  "type": "Feature",
  "properties": {
    "addr:full":"11 Hazel Smith Crs Oxley ACT 2903",
    "addr:housenumber":"11",
    "addr:postcode":"2903",
    "addr:street":"Hazel Smith Crs",
    "iso:country":"AU",
    "sg:address":"11 Hazel Smith Crs",
    "sg:city":"Oxley",
    "sg:classifiers":[
        {
            "category":"Building & Trades",
            "subcategory":"Landscaping Services",
            "type":"Services"
        }
    ],
    "sg:phone":"+61 2 6296 7704",
    "sg:postcode":"2903",
    "sg:province":"ACT",
    "sg:tags":[
        "consultant"
    ],
    "wof:name":"Independant Building Solutions",
    "wof:placetype":"venue"
},
  "geometry": {"coordinates":[149.082305908,-35.4088287354],"type":"Point"}
}