{
  "type": "Feature",
  "properties": {
    "addr:full":"95 Breakfast Creek Rd Newstead QLD 4006",
    "addr:housenumber":"95",
    "addr:postcode":"4006",
    "addr:street":"Breakfast Creek Rd",
    "iso:country":"AU",
    "sg:address":"95 Breakfast Creek Rd",
    "sg:city":"Newstead",
    "sg:classifiers":[
        {
            "category":"Autos & Motor Vehicles",
            "subcategory":"Automobile Sales",
            "type":"Retail Goods"
        }
    ],
    "sg:phone":"+61 7 3364 1199",
    "sg:postcode":"4006",
    "sg:province":"QLD",
    "sg:tags":[
        "car",
        "used"
    ],
    "sg:website":"http://www.eagers.com.au",
    "wof:name":"Eagers Holden",
    "wof:placetype":"venue"
},
  "geometry": {"coordinates":[153.042236328,-27.4467067719],"type":"Point"}
}