{
  "type": "Feature",
  "properties": {
    "addr:full":"14 Burford St Elizabeth Downs SA 5113",
    "addr:housenumber":"14",
    "addr:postcode":"5113",
    "addr:street":"Burford St",
    "iso:country":"AU",
    "sg:address":"14 Burford St",
    "sg:city":"Elizabeth Downs",
    "sg:classifiers":[
        {
            "category":"Building & Trades",
            "subcategory":"Construction",
            "type":"Services"
        }
    ],
    "sg:phone":"+61 8 8252 4931",
    "sg:postcode":"5113",
    "sg:province":"SA",
    "sg:tags":[
        "concrete",
        "contractor"
    ],
    "wof:name":"Puro Foundations",
    "wof:placetype":"venue"
},
  "geometry": {"coordinates":[138.70065307600001,-34.6981697083],"type":"Point"}
}