{
  "type": "Feature",
  "properties": {
    "addr:full":"Goulburn St Abermain NSW 2326",
    "addr:postcode":"2326",
    "addr:street":"Goulburn St",
    "iso:country":"AU",
    "sg:address":"Goulburn St",
    "sg:city":"Abermain",
    "sg:classifiers":[
        {
            "category":"Education",
            "subcategory":"School",
            "type":"Public Place"
        }
    ],
    "sg:phone":"+61 2 4930 4210",
    "sg:postcode":"2326",
    "sg:province":"NSW",
    "sg:tags":[
        "state",
        "-",
        "nsw"
    ],
    "wof:name":"Abermain Public School",
    "wof:placetype":"venue"
},
  "geometry": {"coordinates":[151.42640685999999,-32.8110618591],"type":"Point"}
}