{
  "type": "Feature",
  "properties": {
    "iso:country":"AU",
    "sg:address":"2/ 40 Technology Drv",
    "sg:city":"Warana",
    "sg:classifiers":[
        {
            "category":"Building & Trades",
            "subcategory":"Plumbing",
            "type":"Services"
        }
    ],
    "sg:phone":"+61 7 5437 7660",
    "sg:postcode":"4575",
    "sg:province":"QLD",
    "sg:tags":[
        "consultant"
    ],
    "wof:name":"Lees Keith",
    "wof:placetype":"venue"
},
  "geometry": {"coordinates":[153.127502,-26.724867],"type":"Point"}
}