{
  "type": "Feature",
  "properties": {
    "addr:full":"Shp8/ Waldhorn Drv Grindelwald TAS 7277",
    "addr:postcode":"7277",
    "addr:street":"Waldhorn Drv",
    "iso:country":"AU",
    "sg:address":"Shp8/ Waldhorn Drv",
    "sg:city":"Grindelwald",
    "sg:classifiers":[
        {
            "category":"Cafe",
            "type":"Food & Drink"
        }
    ],
    "sg:phone":"+61 3 6330 2090",
    "sg:postcode":"7277",
    "sg:province":"TAS",
    "wof:name":"Grindelwald Bakery & Coffee Shop",
    "wof:placetype":"venue"
},
  "geometry": {"coordinates":[147.00126648,-41.3507232666],"type":"Point"}
}