{
  "type": "Feature",
  "properties": {
    "addr:full":"35 Donovan Ave Maroubra NSW 2035",
    "addr:housenumber":"35",
    "addr:postcode":"2035",
    "addr:street":"Donovan Ave",
    "iso:country":"AU",
    "sg:address":"35 Donovan Ave",
    "sg:city":"Maroubra",
    "sg:classifiers":[
        {
            "category":"Education",
            "subcategory":"School",
            "type":"Public Place"
        }
    ],
    "sg:phone":"+61 2 9349 7333",
    "sg:postcode":"2035",
    "sg:province":"NSW",
    "sg:tags":[
        "boy"
    ],
    "wof:name":"Marist College Pagewood",
    "wof:placetype":"venue"
},
  "geometry": {"coordinates":[151.23020935100001,-33.9466629028],"type":"Point"}
}