{
  "type": "Feature",
  "properties": {
    "iso:country":"AU",
    "sg:address":"19 Chesterton St",
    "sg:city":"Spearwood",
    "sg:classifiers":[
        {
            "category":"Utilities",
            "subcategory":"Electric",
            "type":"Services"
        }
    ],
    "sg:phone":"+61 412 775 015",
    "sg:postcode":"6163",
    "sg:province":"WA",
    "sg:tags":[
        "electrical",
        "contractor"
    ],
    "wof:name":"APV Odyssey Electrical Contractors",
    "wof:placetype":"venue"
},
  "geometry": {"coordinates":[115.790421,-32.115685],"type":"Point"}
}