{
  "type": "Feature",
  "properties": {
    "addr:full":"Suite 4 Dalton Pl Maroochydore QLD 4558",
    "addr:postcode":"4558",
    "addr:street":"Pl",
    "iso:country":"AU",
    "sg:address":"Suite 4 Dalton Pl",
    "sg:city":"Maroochydore",
    "sg:classifiers":[
        {
            "category":"Health Services",
            "subcategory":"Health Practitioner",
            "type":"Services"
        }
    ],
    "sg:phone":"+61 1800 072 050",
    "sg:postcode":"4558",
    "sg:province":"QLD",
    "sg:tags":[
        "naturopath"
    ],
    "wof:name":"Queensland Institute of Natural Science",
    "wof:placetype":"venue"
},
  "geometry": {"coordinates":[153.091064453,-26.6671009064],"type":"Point"}
}