{
  "type": "Feature",
  "properties": {
    "addr:full":"105 Merimbula Drv Merimbula NSW 2548",
    "addr:housenumber":"105",
    "addr:postcode":"2548",
    "addr:street":"Merimbula Drv",
    "iso:country":"AU",
    "sg:address":"105 Merimbula Drv",
    "sg:city":"Merimbula",
    "sg:classifiers":[
        {
            "category":"Travel",
            "subcategory":"Hotels & Motels",
            "type":"Entertainment"
        }
    ],
    "sg:phone":"+61 2 6495 1595",
    "sg:postcode":"2548",
    "sg:province":"NSW",
    "wof:name":"Kingfisher Motel",
    "wof:placetype":"venue"
},
  "geometry": {"coordinates":[149.89796447800001,-36.8889541626],"type":"Point"}
}