{
  "type": "Feature",
  "properties": {
    "addr:full":"129 Vincent St Cessnock NSW 2325",
    "addr:housenumber":"129",
    "addr:postcode":"2325",
    "addr:street":"Vincent St",
    "iso:country":"AU",
    "sg:address":"129 Vincent St",
    "sg:city":"Cessnock",
    "sg:classifiers":[
        {
            "category":"Personal",
            "subcategory":"Beauty Salon",
            "type":"Services"
        }
    ],
    "sg:phone":"+61 2 4991 2350",
    "sg:postcode":"2325",
    "sg:province":"NSW",
    "sg:tags":[
        "hairdresser"
    ],
    "wof:name":"Black Cat Hair",
    "wof:placetype":"venue"
},
  "geometry": {"coordinates":[151.355926514,-32.8361206055],"type":"Point"}
}