{
  "type": "Feature",
  "properties": {
    "addr:full":"Cnr Ruthven & Archibald Sts Toowoomba QLD 4350",
    "addr:housenumber":"cnr",
    "addr:postcode":"4350",
    "iso:country":"AU",
    "sg:address":"Cnr Ruthven & Archibald Sts",
    "sg:city":"Toowoomba",
    "sg:classifiers":[
        {
            "category":"Building & Trades",
            "subcategory":"Construction",
            "type":"Services"
        }
    ],
    "sg:phone":"+61 13 16 16",
    "sg:postcode":"4350",
    "sg:province":"QLD",
    "sg:tags":[
        "repairing",
        "window"
    ],
    "wof:name":"O&#039;Brien",
    "wof:placetype":"venue"
},
  "geometry": {"coordinates":[151.95190400000001,-27.569506],"type":"Point"}
}