{
  "type": "Feature",
  "properties": {
    "iso:country":"AU",
    "sg:address":"3 Caves Rd",
    "sg:city":"Busselton",
    "sg:classifiers":[
        {
            "category":"Food & Beverages",
            "subcategory":"Liquor & Beverages",
            "type":"Retail Goods"
        }
    ],
    "sg:phone":"+61 8 9755 4821",
    "sg:postcode":"6280",
    "sg:province":"WA",
    "sg:tags":[
        "store"
    ],
    "wof:name":"Liquor Barons",
    "wof:placetype":"venue"
},
  "geometry": {"coordinates":[115.183387756,-33.6446037292],"type":"Point"}
}