{
  "type": "Feature",
  "properties": {
    "addr:full":"10 Sherman St Canning Vale WA 6155",
    "addr:housenumber":"10",
    "addr:postcode":"6155",
    "addr:street":"Sherman St",
    "iso:country":"AU",
    "sg:address":"10 Sherman St",
    "sg:city":"Canning Vale",
    "sg:classifiers":[
        {
            "category":"Bus Stop",
            "subcategory":"None",
            "type":"Transportation"
        }
    ],
    "sg:phone":"+61 8 9455 1713",
    "sg:postcode":"6155",
    "sg:province":"WA",
    "sg:tags":[
        "galvanising",
        "tinning"
    ],
    "sg:website":"http://www.hartway.com.au",
    "wof:name":"Hartway Galvanizers",
    "wof:placetype":"venue"
},
  "geometry": {"coordinates":[115.91114,-32.056713],"type":"Point"}
}