{
  "type": "Feature",
  "properties": {
    "addr:full":"56 Brucedale Drv Baulkham Hills NSW 2153",
    "addr:housenumber":"56",
    "addr:postcode":"2153",
    "addr:street":"Brucedale Drv",
    "iso:country":"AU",
    "sg:address":"56 Brucedale Drv",
    "sg:city":"Baulkham Hills",
    "sg:classifiers":[
        {
            "category":"Home & Garden",
            "subcategory":"Carpets & Floor Coverings",
            "type":"Retail Goods"
        }
    ],
    "sg:phone":"+61 2 9686 4026",
    "sg:postcode":"2153",
    "sg:province":"NSW",
    "sg:tags":[
        "tile",
        "wall",
        "layer"
    ],
    "wof:name":"Wigley P E Tiling & Plastering",
    "wof:placetype":"venue"
},
  "geometry": {"coordinates":[150.985961914,-33.7449073792],"type":"Point"}
}