{
  "type": "Feature",
  "properties": {
    "iso:country":"AU",
    "sg:address":"264 Whitehorse Rd",
    "sg:city":"Balwyn",
    "sg:classifiers":[
        {
            "category":"Personal",
            "subcategory":"Beauty Salon",
            "type":"Services"
        }
    ],
    "sg:phone":"+61 3 9836 9663",
    "sg:postcode":"3103",
    "sg:province":"VIC",
    "sg:tags":[
        "hairdresser"
    ],
    "wof:name":"Latif Hair & Beauty Clinic",
    "wof:placetype":"venue"
},
  "geometry": {"coordinates":[145.08229064899999,-37.8130569458],"type":"Point"}
}