{
  "type": "Feature",
  "properties": {
    "addr:full":"2 Bourne Rd Glen Iris VIC 3146",
    "addr:housenumber":"2",
    "addr:postcode":"3146",
    "addr:street":"Bourne Rd",
    "iso:country":"AU",
    "sg:address":"2 Bourne Rd",
    "sg:city":"Glen Iris",
    "sg:classifiers":[
        {
            "category":"Professional",
            "subcategory":"Engineering",
            "type":"Services"
        }
    ],
    "sg:phone":"+61 418 396 980",
    "sg:postcode":"3146",
    "sg:province":"VIC",
    "sg:tags":[
        "electronic",
        "engineer"
    ],
    "wof:name":"Cher Electrics Pty Ltd",
    "wof:placetype":"venue"
},
  "geometry": {"coordinates":[145.06643676799999,-37.8571968079],"type":"Point"}
}