{
  "type": "Feature",
  "properties": {
    "iso:country":"AU",
    "sg:address":"202 Logan St",
    "sg:city":"Tenterfield",
    "sg:classifiers":[
        {
            "category":"Health Services",
            "subcategory":"Chiropractor",
            "type":"Services"
        }
    ],
    "sg:phone":"+61 2 6736 2636",
    "sg:postcode":"2372",
    "sg:province":"NSW",
    "wof:name":"Hoffmann Narelle",
    "wof:placetype":"venue"
},
  "geometry": {"coordinates":[152.02296447800001,-29.0461292267],"type":"Point"}
}