{
  "type": "Feature",
  "properties": {
    "addr:full":"6 Mackillop Crs St Helens Park NSW 2560",
    "addr:housenumber":"6",
    "addr:postcode":"2560",
    "addr:street":"Mackillop Crs",
    "iso:country":"AU",
    "sg:address":"6 Mackillop Crs",
    "sg:city":"St Helens Park",
    "sg:classifiers":[
        {
            "category":"Professional",
            "subcategory":"Art Services",
            "type":"Services"
        }
    ],
    "sg:phone":"+61 404 069 815",
    "sg:postcode":"2560",
    "sg:province":"NSW",
    "sg:tags":[
        "decorator",
        "painter"
    ],
    "wof:name":"MacArthur Painting Professionals",
    "wof:placetype":"venue"
},
  "geometry": {"coordinates":[150.80714416500001,-34.1051216125],"type":"Point"}
}