{
  "type": "Feature",
  "properties": {
    "iso:country":"AU",
    "sg:address":"15 Tribute St",
    "sg:city":"Shelley",
    "sg:classifiers":[
        {
            "category":"Food & Beverages",
            "subcategory":"Liquor & Beverages",
            "type":"Retail Goods"
        }
    ],
    "sg:phone":"+61 8 9457 4668",
    "sg:postcode":"6148",
    "sg:province":"WA",
    "sg:tags":[
        "store"
    ],
    "wof:name":"Harvest Liquor",
    "wof:placetype":"venue"
},
  "geometry": {"coordinates":[115.884567,-32.030727],"type":"Point"}
}