{
  "type": "Feature",
  "properties": {
    "iso:country":"AU",
    "sg:address":"PO Box 220",
    "sg:city":"Exeter",
    "sg:classifiers":[
        {
            "category":"Professional",
            "subcategory":"Art Services",
            "type":"Services"
        }
    ],
    "sg:phone":"+61 2 4883 4186",
    "sg:postcode":"2579",
    "sg:province":"NSW",
    "sg:tags":[
        "graphic",
        "designer"
    ],
    "wof:name":"Inscript Publishing",
    "wof:placetype":"venue"
},
  "geometry": {"coordinates":[150.31590270999999,-34.6156387329],"type":"Point"}
}