{
  "type": "Feature",
  "properties": {
    "addr:full":"26 Vidler St Falls Creek NSW 2540",
    "addr:housenumber":"26",
    "addr:postcode":"2540",
    "addr:street":"Vidler St Falls",
    "iso:country":"AU",
    "sg:address":"26 Vidler St",
    "sg:city":"Falls Creek",
    "sg:classifiers":[
        {
            "category":"Education",
            "subcategory":"School",
            "type":"Public Place"
        }
    ],
    "sg:phone":"+61 2 4447 8243",
    "sg:postcode":"2540",
    "sg:province":"NSW",
    "sg:tags":[
        "state",
        "-",
        "nsw"
    ],
    "wof:name":"Falls Creek Public School",
    "wof:placetype":"venue"
},
  "geometry": {"coordinates":[150.594116211,-34.9665641785],"type":"Point"}
}