{
  "type": "Feature",
  "properties": {
    "iso:country":"AU",
    "sg:address":"College St",
    "sg:city":"Darlinghurst",
    "sg:classifiers":[
        {
            "category":"Education",
            "subcategory":"School",
            "type":"Public Place"
        }
    ],
    "sg:phone":"+61 2 9332 5800",
    "sg:postcode":"2010",
    "sg:province":"NSW",
    "sg:tags":[
        "boy"
    ],
    "wof:name":"Sydney Grammar School",
    "wof:placetype":"venue"
},
  "geometry": {"coordinates":[151.21214294399999,-33.8768043518],"type":"Point"}
}