{
  "type": "Feature",
  "properties": {
    "addr:full":"Level 2, Unisys Building, 147 Coronation Drv Milton QLD 4064",
    "addr:housenumber":"147",
    "addr:postcode":"4064",
    "addr:street":"Coronation Drv",
    "iso:country":"AU",
    "sg:address":"Level 2, Unisys Building, 147 Coronation Drv",
    "sg:city":"Milton",
    "sg:classifiers":[
        {
            "category":"Banks & Credit Unions",
            "subcategory":"Financial Services",
            "type":"Services"
        }
    ],
    "sg:phone":"+61 7 3318 9270",
    "sg:postcode":"4064",
    "sg:province":"QLD",
    "sg:tags":[
        "financier"
    ],
    "wof:name":"Lease Choice Pty Ltd",
    "wof:placetype":"venue"
},
  "geometry": {"coordinates":[153.0052948,-27.4685897827],"type":"Point"}
}