{
  "type": "Feature",
  "properties": {
    "addr:full":"Lot 5 Dickson Rd Innisfail QLD 4860",
    "addr:housenumber":"5",
    "addr:postcode":"4860",
    "addr:street":"Dickson Rd",
    "iso:country":"AU",
    "sg:address":"Lot 5 Dickson Rd",
    "sg:city":"Innisfail",
    "sg:classifiers":[
        {
            "category":"Utilities",
            "subcategory":"Refuse",
            "type":"Services"
        }
    ],
    "sg:phone":"+61 7 4061 7450",
    "sg:postcode":"4860",
    "sg:province":"QLD",
    "sg:tags":[
        "disposal",
        "reduction",
        "waste"
    ],
    "wof:name":"Subloo's Recycling",
    "wof:placetype":"venue"
},
  "geometry": {"coordinates":[146.00843810999999,-17.512966156],"type":"Point"}
}