{
  "type": "Feature",
  "properties": {
    "addr:full":"491 Pennant Hills Rd West Pennant Hills NSW 2125",
    "addr:housenumber":"491",
    "addr:postcode":"2125",
    "addr:street":"Pennant Hills Rd",
    "iso:country":"AU",
    "sg:address":"491 Pennant Hills Rd",
    "sg:city":"West Pennant Hills",
    "sg:classifiers":[
        {
            "category":"Building & Trades",
            "subcategory":"Construction",
            "type":"Services"
        }
    ],
    "sg:phone":"+61 416 072 803",
    "sg:postcode":"2125",
    "sg:province":"NSW",
    "sg:tags":[
        "contractor"
    ],
    "wof:name":"K.B. Jeppesen, Design & Construction",
    "wof:placetype":"venue"
},
  "geometry": {"coordinates":[151.05331420900001,-33.7450027466],"type":"Point"}
}