{
  "type": "Feature",
  "properties": {
    "iso:country":"AU",
    "sg:address":"Level 1 / 221 Queen St",
    "sg:city":"Melbourne",
    "sg:classifiers":[
        {
            "category":"Professional",
            "subcategory":"Management & Consulting",
            "type":"Services"
        }
    ],
    "sg:phone":"+61 3 9670 7978",
    "sg:postcode":"3000",
    "sg:province":"VIC",
    "sg:tags":[
        "consultant",
        "migration"
    ],
    "wof:name":"Aust-China Migration Services",
    "wof:placetype":"venue"
},
  "geometry": {"coordinates":[144.95985412600001,-37.813457489],"type":"Point"}
}