{
  "type": "Feature",
  "properties": {
    "iso:country":"AU",
    "sg:address":"55 Bay St",
    "sg:city":"Double Bay",
    "sg:classifiers":[
        {
            "category":"Restaurant",
            "type":"Food & Drink"
        }
    ],
    "sg:phone":"+61 2 9363 5510",
    "sg:postcode":"2028",
    "sg:province":"NSW",
    "wof:name":"Bukhara Indian Restaurant of Double Bay",
    "wof:placetype":"venue"
},
  "geometry": {"coordinates":[151.24205017099999,-33.8760032654],"type":"Point"}
}