{
  "type": "Feature",
  "properties": {
    "addr:full":"317 Rouse St Tenterfield NSW 2372",
    "addr:housenumber":"317",
    "addr:postcode":"2372",
    "addr:street":"Rouse St",
    "iso:country":"AU",
    "sg:address":"317 Rouse St",
    "sg:city":"Tenterfield",
    "sg:classifiers":[
        {
            "category":"Fast Food",
            "type":"Food & Drink"
        }
    ],
    "sg:phone":"+61 2 6736 1544",
    "sg:postcode":"2372",
    "sg:province":"NSW",
    "sg:tags":[
        "away",
        "take"
    ],
    "wof:name":"Food And Water Canteen",
    "wof:placetype":"venue"
},
  "geometry": {"coordinates":[152.019622803,-29.0517520905],"type":"Point"}
}