{
  "type": "Feature",
  "properties": {
    "addr:full":"27 Crossman Drv Croydon Hills VIC 3136",
    "addr:housenumber":"27",
    "addr:postcode":"3136",
    "addr:street":"Crossman Drv",
    "iso:country":"AU",
    "sg:address":"27 Crossman Drv",
    "sg:city":"Croydon Hills",
    "sg:classifiers":[
        {
            "category":"Retail",
            "subcategory":"Repair Shop",
            "type":"Services"
        }
    ],
    "sg:phone":"+61 418 397 367",
    "sg:postcode":"3136",
    "sg:province":"VIC",
    "sg:tags":[
        "maintenance",
        "pool",
        "swimming"
    ],
    "wof:name":"Pool Paint",
    "wof:placetype":"venue"
},
  "geometry": {"coordinates":[145.259567261,-37.7780342102],"type":"Point"}
}