{
  "type": "Feature",
  "properties": {
    "addr:full":"1 Cromwell Pde West Footscray VIC 3012",
    "addr:housenumber":"1",
    "addr:postcode":"3012",
    "addr:street":"Cromwell Pde",
    "iso:country":"AU",
    "sg:address":"1 Cromwell Pde",
    "sg:city":"West Footscray",
    "sg:classifiers":[
        {
            "category":"Professional",
            "subcategory":"Art Services",
            "type":"Services"
        }
    ],
    "sg:phone":"+61 3 9315 1156",
    "sg:postcode":"3012",
    "sg:province":"VIC",
    "sg:tags":[
        "work",
        "metal"
    ],
    "wof:name":"Fundere Bronze Art Foundry",
    "wof:placetype":"venue"
},
  "geometry": {"coordinates":[144.862457275,-37.8126564026],"type":"Point"}
}