{
  "type": "Feature",
  "properties": {
    "addr:full":"13 Mason Drv Braeside VIC 3195",
    "addr:housenumber":"13",
    "addr:postcode":"3195",
    "addr:street":"Mason Drv",
    "iso:country":"AU",
    "sg:address":"13 Mason Drv",
    "sg:city":"Braeside",
    "sg:classifiers":[
        {
            "category":"Building & Trades",
            "subcategory":"Construction",
            "type":"Services"
        }
    ],
    "sg:phone":"+61 3 9587 2358",
    "sg:postcode":"3195",
    "sg:province":"VIC",
    "sg:tags":[
        "window",
        "aluminium"
    ],
    "wof:name":"Higgins & Cooper",
    "wof:placetype":"venue"
},
  "geometry": {"coordinates":[145.11062622099999,-37.9992103577],"type":"Point"}
}