{
  "type": "Feature",
  "properties": {
    "addr:full":"35 Mt Barker Central Shopping Cntr Mt Barker SA 5251",
    "addr:housenumber":"35",
    "addr:postcode":"5251",
    "addr:street":"Mt Barker Central Shopping Cntr Mt",
    "iso:country":"AU",
    "sg:address":"35 Mt Barker Central Shopping Cntr",
    "sg:city":"Mt Barker",
    "sg:classifiers":[
        {
            "category":"Shopping",
            "subcategory":"Computers & Home Electronics",
            "type":"Retail Goods"
        }
    ],
    "sg:phone":"+61 8 8391 3699",
    "sg:postcode":"5251",
    "sg:province":"SA",
    "sg:tags":[
        "equipment",
        "supply"
    ],
    "wof:name":"Leading Edge Computers Mt Barker",
    "wof:placetype":"venue"
},
  "geometry": {"coordinates":[138.84681701700001,-35.0531845093],"type":"Point"}
}