{
  "type": "Feature",
  "properties": {
    "addr:full":"11 Moira Park Rd Morisset NSW 2264",
    "addr:housenumber":"11",
    "addr:postcode":"2264",
    "addr:street":"Moira Park Rd",
    "iso:country":"AU",
    "sg:address":"11 Moira Park Rd",
    "sg:city":"Morisset",
    "sg:classifiers":[
        {
            "category":"Sports & Exercise",
            "subcategory":"Sports Center",
            "type":"Entertainment"
        }
    ],
    "sg:phone":"+61 2 4970 5764",
    "sg:postcode":"2264",
    "sg:province":"NSW",
    "sg:tags":[
        "coach",
        "tennis"
    ],
    "wof:name":"O&#039;Neils School Of Tennis",
    "wof:placetype":"venue"
},
  "geometry": {"coordinates":[151.49707000000001,-33.10107],"type":"Point"}
}