{
  "type": "Feature",
  "properties": {
    "iso:country":"AU",
    "sg:address":"Shop 1, 188 Balcatta Rd",
    "sg:city":"Balcatta",
    "sg:classifiers":[
        {
            "category":"Home & Garden",
            "subcategory":"Carpets & Floor Coverings",
            "type":"Retail Goods"
        }
    ],
    "sg:phone":"+61 8 9345 4777",
    "sg:postcode":"6021",
    "sg:province":"WA",
    "wof:name":"Town & Country Floor Coverings",
    "wof:placetype":"venue"
},
  "geometry": {"coordinates":[115.816932678,-31.8623943329],"type":"Point"}
}