{
  "type": "Feature",
  "properties": {
    "iso:country":"AU",
    "sg:address":"12 Pamela St",
    "sg:city":"Mt Isa",
    "sg:classifiers":[
        {
            "category":"Wholesale",
            "subcategory":"Painting Supplies",
            "type":"Manufacturing & Wholesale Goods"
        }
    ],
    "sg:phone":"+61 7 4749 1872",
    "sg:postcode":"4825",
    "sg:province":"QLD",
    "sg:tags":[
        "painter"
    ],
    "wof:name":"Wattyl Pascol Trade Paint Centre",
    "wof:placetype":"venue"
},
  "geometry": {"coordinates":[139.497253,-20.73007],"type":"Point"}
}