{
  "type": "Feature",
  "properties": {
    "iso:country":"AU",
    "sg:address":"8 Rural Drv",
    "sg:city":"Sandgate",
    "sg:classifiers":[
        {
            "category":"Professional",
            "type":"Services"
        }
    ],
    "sg:phone":"+61 1300 305 880",
    "sg:postcode":"2304",
    "sg:province":"NSW",
    "sg:tags":[
        "forwarding",
        "agent",
        "transport"
    ],
    "wof:name":"AirRoad Distribution Pty Ltd",
    "wof:placetype":"venue"
},
  "geometry": {"coordinates":[151.70806884800001,-32.8736114502],"type":"Point"}
}