{
  "type": "Feature",
  "properties": {
    "iso:country":"AU",
    "sg:address":"11 Inverallan Ave",
    "sg:city":"West Pymble",
    "sg:classifiers":[
        {
            "category":"Arts & Performance",
            "subcategory":"Dance",
            "type":"Entertainment"
        }
    ],
    "sg:phone":"+61 2 9498 1569",
    "sg:postcode":"2073",
    "sg:province":"NSW",
    "sg:tags":[
        "theatrical",
        "ballet",
        "tuition"
    ],
    "wof:name":"Ku-Ring-Gai School Of Dance",
    "wof:placetype":"venue"
},
  "geometry": {"coordinates":[151.134475708,-33.7602615356],"type":"Point"}
}