{
  "type": "Feature",
  "properties": {
    "addr:full":"2 Kurrewa La Coomera QLD 4209",
    "addr:housenumber":"2",
    "addr:postcode":"4209",
    "addr:street":"Kurrewa La",
    "iso:country":"AU",
    "sg:address":"2 Kurrewa La",
    "sg:city":"Coomera",
    "sg:classifiers":[
        {
            "category":"Banks & Credit Unions",
            "subcategory":"Investment Brokerage",
            "type":"Services"
        }
    ],
    "sg:phone":"+61 7 5529 9914",
    "sg:postcode":"4209",
    "sg:province":"QLD",
    "sg:tags":[
        "finance",
        "broker"
    ],
    "wof:name":"Pilot Financial Services",
    "wof:placetype":"venue"
},
  "geometry": {"coordinates":[153.36398315400001,-27.839963913],"type":"Point"}
}