{
  "type": "Feature",
  "properties": {
    "addr:full":"\"Tarban\" 122 Miles Tenterfield NSW 2372",
    "addr:housenumber":"122",
    "addr:postcode":"2372",
    "addr:street":"Miles",
    "iso:country":"AU",
    "sg:address":"\"Tarban\" 122 Miles",
    "sg:city":"Tenterfield",
    "sg:classifiers":[
        {
            "category":"Building & Trades",
            "subcategory":"Landscaping Services",
            "type":"Services"
        }
    ],
    "sg:phone":"+61 2 6736 1396",
    "sg:postcode":"2372",
    "sg:province":"NSW",
    "sg:tags":[
        "grazier"
    ],
    "wof:name":"Schroder L M",
    "wof:placetype":"venue"
},
  "geometry": {"coordinates":[152.02232360799999,-29.0578193665],"type":"Point"}
}