{
  "type": "Feature",
  "properties": {
    "addr:full":"34 Belmore Rd Randwick NSW 2031",
    "addr:housenumber":"34",
    "addr:postcode":"2031",
    "addr:street":"Belmore Rd",
    "iso:country":"AU",
    "sg:address":"34 Belmore Rd",
    "sg:city":"Randwick",
    "sg:classifiers":[
        {
            "category":"Cafe",
            "type":"Food & Drink"
        }
    ],
    "sg:phone":"+61 2 9399 8771",
    "sg:postcode":"2031",
    "sg:province":"NSW",
    "wof:name":"Zellini's Cafe",
    "wof:placetype":"venue"
},
  "geometry": {"coordinates":[151.23973083499999,-33.9138946533],"type":"Point"}
}