{
  "type": "Feature",
  "properties": {
    "addr:full":"11 Windorah St Stafford QLD 4053",
    "addr:housenumber":"11",
    "addr:postcode":"4053",
    "addr:street":"Windorah St",
    "iso:country":"AU",
    "sg:address":"11 Windorah St",
    "sg:city":"Stafford",
    "sg:classifiers":[
        {
            "category":"Retail",
            "subcategory":"Auto Repair",
            "type":"Services"
        }
    ],
    "sg:phone":"+61 7 3856 0999",
    "sg:postcode":"4053",
    "sg:province":"QLD",
    "sg:tags":[
        "beater",
        "painter",
        "panel"
    ],
    "wof:name":"Workshop",
    "wof:placetype":"venue"
},
  "geometry": {"coordinates":[153.01104736299999,-27.4103450775],"type":"Point"}
}