{
  "type": "Feature",
  "properties": {
    "iso:country":"AU",
    "sg:address":"Roadside Mail Box 8310",
    "sg:city":"Bethanga",
    "sg:classifiers":[
        {
            "category":"Retail",
            "subcategory":"Animal Services",
            "type":"Services"
        }
    ],
    "sg:phone":"+61 2 6026 4282",
    "sg:postcode":"3691",
    "sg:province":"VIC",
    "sg:tags":[
        "breeder",
        "sheep",
        "stud",
        "cattle"
    ],
    "wof:name":"Elliott Margaret M",
    "wof:placetype":"venue"
},
  "geometry": {"coordinates":[147.100006,-36.12455],"type":"Point"}
}