{
  "type": "Feature",
  "properties": {
    "iso:country":"AU",
    "sg:address":"1010 Coolawanyah Rd",
    "sg:city":"Karratha",
    "sg:classifiers":[
        {
            "category":"Home & Garden",
            "subcategory":"Hardware",
            "type":"Retail Goods"
        }
    ],
    "sg:phone":"+61 8 9185 5088",
    "sg:postcode":"6714",
    "sg:province":"WA",
    "sg:tags":[
        "plumber",
        "supply"
    ],
    "wof:name":"Tradelink Plumbing Centres",
    "wof:placetype":"venue"
},
  "geometry": {"coordinates":[116.86666870099999,-20.7689933777],"type":"Point"}
}