{
  "type": "Feature",
  "properties": {
    "addr:full":"20 Northcott Ave Kingsgrove NSW 2208",
    "addr:housenumber":"20",
    "addr:postcode":"2208",
    "addr:street":"Northcott Ave",
    "iso:country":"AU",
    "sg:address":"20 Northcott Ave",
    "sg:city":"Kingsgrove",
    "sg:classifiers":[
        {
            "category":"Building & Trades",
            "subcategory":"Pest Control",
            "type":"Services"
        }
    ],
    "sg:phone":"+61 2 9825 6360",
    "sg:postcode":"2208",
    "sg:province":"NSW",
    "wof:name":"St George Pest Control Services",
    "wof:placetype":"venue"
},
  "geometry": {"coordinates":[151.09896900000001,-33.941929],"type":"Point"}
}