{
  "type": "Feature",
  "properties": {
    "iso:country":"AU",
    "sg:address":"24 Meadow Ave",
    "sg:city":"Coopers Plains",
    "sg:classifiers":[
        {
            "category":"Wholesale",
            "subcategory":"Machinery & Supplies",
            "type":"Manufacturing & Wholesale Goods"
        }
    ],
    "sg:phone":"+61 7 3277 0190",
    "sg:postcode":"4108",
    "sg:province":"QLD",
    "sg:tags":[
        "engineer"
    ],
    "wof:name":"A.E. Baker & Co.",
    "wof:placetype":"venue"
},
  "geometry": {"coordinates":[153.02470398,-27.5655918121],"type":"Point"}
}