{
  "type": "Feature",
  "properties": {
    "addr:full":"Collingwood Secondary College Entry Via Cromwell St Collingwood VIC 3066",
    "addr:postcode":"3066",
    "addr:street":"Via Cromwell St",
    "iso:country":"AU",
    "sg:address":"Collingwood Secondary College Entry Via Cromwell St",
    "sg:city":"Collingwood",
    "sg:classifiers":[
        {
            "category":"Education",
            "subcategory":"Dance Studio",
            "type":"Public Place"
        }
    ],
    "sg:phone":"+61 3 9417 6134",
    "sg:postcode":"3066",
    "sg:province":"VIC",
    "sg:tags":[
        "instruction",
        "language"
    ],
    "wof:name":"AMES Education",
    "wof:placetype":"venue"
},
  "geometry": {"coordinates":[144.99034118599999,-37.8041152954],"type":"Point"}
}