{
  "type": "Feature",
  "properties": {
    "addr:full":"Shop 1g1 Supa Centa Moore Park NSW 2021",
    "addr:housenumber":"1g1",
    "addr:postcode":"2021",
    "addr:street":"Shop",
    "iso:country":"AU",
    "sg:address":"Shop 1g1 Supa Centa",
    "sg:city":"Moore Park",
    "sg:classifiers":[
        {
            "category":"Cafe",
            "type":"Food & Drink"
        }
    ],
    "sg:phone":"+61 2 9663 0535",
    "sg:postcode":"2021",
    "sg:province":"NSW",
    "wof:name":"Cafe 101",
    "wof:placetype":"venue"
},
  "geometry": {"coordinates":[151.22596740700001,-33.8964805603],"type":"Point"}
}