{
  "type": "Feature",
  "properties": {
    "addr:full":"Unit 3/ 39 Union Rd North Albury NSW 2640",
    "addr:postcode":"2640",
    "addr:street":"Union Rd",
    "iso:country":"AU",
    "sg:address":"Unit 3/ 39 Union Rd",
    "sg:city":"North Albury",
    "sg:classifiers":[
        {
            "category":"Building & Trades",
            "subcategory":"Construction",
            "type":"Services"
        }
    ],
    "sg:phone":"+61 2 6025 1866",
    "sg:postcode":"2640",
    "sg:province":"NSW",
    "sg:tags":[
        "industrial",
        "commercial",
        "air conditioning"
    ],
    "wof:name":"Ideal Rayson",
    "wof:placetype":"venue"
},
  "geometry": {"coordinates":[146.93507385300001,-36.0525512695],"type":"Point"}
}