{
  "type": "Feature",
  "properties": {
    "addr:full":"2 Glen-Ard Mohr Rd Exeter TAS 7275",
    "addr:housenumber":"2",
    "addr:postcode":"7275",
    "addr:street":"Glen-Ard Mohr Rd",
    "iso:country":"AU",
    "sg:address":"2 Glen-Ard Mohr Rd",
    "sg:city":"Exeter",
    "sg:classifiers":[
        {
            "category":"Education",
            "subcategory":"Music School",
            "type":"Public Place"
        }
    ],
    "sg:phone":"+61 3 6394 4758",
    "sg:postcode":"7275",
    "sg:province":"TAS",
    "sg:tags":[
        "choir",
        "bands",
        "orchestra"
    ],
    "wof:name":"West Tamar Municipal Band",
    "wof:placetype":"venue"
},
  "geometry": {"coordinates":[146.95509338400001,-41.3003692627],"type":"Point"}
}