{
  "type": "Feature",
  "properties": {
    "addr:full":"PO Box 107 Ulverstone TAS 7315",
    "addr:postcode":"7315",
    "iso:country":"AU",
    "sg:address":"PO Box 107",
    "sg:city":"Ulverstone",
    "sg:classifiers":[
        {
            "category":"Arena",
            "subcategory":"Bull Ring",
            "type":"Entertainment"
        }
    ],
    "sg:phone":"+61 3 6423 2844",
    "sg:postcode":"7315",
    "sg:province":"TAS",
    "sg:tags":[
        "club",
        "bushwalking"
    ],
    "wof:name":"North West Walking Club",
    "wof:placetype":"venue"
},
  "geometry": {"coordinates":[146.18096923799999,-41.1590881348],"type":"Point"}
}