{
  "type": "Feature",
  "properties": {
    "iso:country":"AU",
    "sg:address":"71 Springwood Rd",
    "sg:city":"Springwood",
    "sg:classifiers":[
        {
            "category":"Health Services",
            "subcategory":"Doctor",
            "type":"Services"
        }
    ],
    "sg:phone":"+61 7 3341 2040",
    "sg:postcode":"4127",
    "sg:province":"QLD",
    "sg:tags":[
        "medical",
        "practitioner"
    ],
    "wof:name":"Kastrissios John",
    "wof:placetype":"venue"
},
  "geometry": {"coordinates":[153.12550354000001,-27.6097393036],"type":"Point"}
}