{
  "type": "Feature",
  "properties": {
    "addr:full":"2 Attunga Drv Torquay VIC 3228",
    "addr:housenumber":"2",
    "addr:postcode":"3228",
    "addr:street":"Attunga Drv",
    "iso:country":"AU",
    "sg:address":"2 Attunga Drv",
    "sg:city":"Torquay",
    "sg:classifiers":[
        {
            "category":"Personal",
            "subcategory":"Massage",
            "type":"Services"
        }
    ],
    "sg:phone":"+61 438 668 878",
    "sg:postcode":"3228",
    "sg:province":"VIC",
    "sg:tags":[
        "therapy"
    ],
    "wof:name":"Surfcoast Massage",
    "wof:placetype":"venue"
},
  "geometry": {"coordinates":[144.314224,-38.325565],"type":"Point"}
}