{
  "type": "Feature",
  "properties": {
    "addr:full":"West Rd Waikerie SA 5330",
    "addr:postcode":"5330",
    "addr:street":"West Rd",
    "iso:country":"AU",
    "sg:address":"West Rd",
    "sg:city":"Waikerie",
    "sg:classifiers":[
        {
            "category":"Farming",
            "subcategory":"Orchard",
            "type":"Manufacturing & Wholesale Goods"
        }
    ],
    "sg:phone":"+61 8 8541 2091",
    "sg:postcode":"5330",
    "sg:province":"SA",
    "sg:tags":[
        "citrus",
        "fruit",
        "grower"
    ],
    "wof:name":"Arnold M G",
    "wof:placetype":"venue"
},
  "geometry": {"coordinates":[139.97921752900001,-34.1807556152],"type":"Point"}
}