{
  "type": "Feature",
  "properties": {
    "addr:full":"108 Anakie Rd Bell Park VIC 3215",
    "addr:housenumber":"108",
    "addr:postcode":"3215",
    "addr:street":"Anakie Rd",
    "iso:country":"AU",
    "sg:address":"108 Anakie Rd",
    "sg:city":"Bell Park",
    "sg:classifiers":[
        {
            "category":"Health Services",
            "subcategory":"Doctor",
            "type":"Services"
        }
    ],
    "sg:phone":"+61 3 5272 1662",
    "sg:postcode":"3215",
    "sg:province":"VIC",
    "sg:tags":[
        "medical",
        "practitioner"
    ],
    "wof:name":"Bogacki W A Dr",
    "wof:placetype":"venue"
},
  "geometry": {"coordinates":[144.332473755,-38.1068305969],"type":"Point"}
}