{
  "type": "Feature",
  "properties": {
    "addr:full":"Westfield Shoppingtown Moggill Rd Indooroopilly QLD 4068",
    "addr:postcode":"4068",
    "addr:street":"Moggill Rd",
    "iso:country":"AU",
    "sg:address":"Westfield Shoppingtown Moggill Rd",
    "sg:city":"Indooroopilly",
    "sg:classifiers":[
        {
            "category":"Food & Beverages",
            "subcategory":"Supermarket",
            "type":"Retail Goods"
        }
    ],
    "sg:phone":"+61 7 3378 8294",
    "sg:postcode":"4068",
    "sg:province":"QLD",
    "sg:tags":[
        "grocery",
        "store"
    ],
    "wof:name":"Franklins",
    "wof:placetype":"venue"
},
  "geometry": {"coordinates":[152.974487305,-27.4973583221],"type":"Point"}
}