{
  "type": "Feature",
  "properties": {
    "addr:full":"34 Seaview St Tweed Heads South NSW 2486",
    "addr:housenumber":"34",
    "addr:postcode":"2486",
    "addr:street":"Seaview St",
    "iso:country":"AU",
    "sg:address":"34 Seaview St",
    "sg:city":"Tweed Heads South",
    "sg:classifiers":[
        {
            "category":"Personal",
            "subcategory":"Massage",
            "type":"Services"
        }
    ],
    "sg:phone":"+61 7 5523 0029",
    "sg:postcode":"2486",
    "sg:province":"NSW",
    "sg:tags":[
        "therapy"
    ],
    "wof:name":"Dragana Vekic",
    "wof:placetype":"venue"
},
  "geometry": {"coordinates":[153.51885986299999,-28.2056388855],"type":"Point"}
}