{
  "type": "Feature",
  "properties": {
    "addr:full":"Rubyanna Rd Kalkie QLD 4670",
    "addr:postcode":"4670",
    "addr:street":"Rubyanna Rd",
    "iso:country":"AU",
    "sg:address":"Rubyanna Rd",
    "sg:city":"Kalkie",
    "sg:classifiers":[
        {
            "category":"Professional",
            "subcategory":"Detective & Security Services",
            "type":"Services"
        }
    ],
    "sg:phone":"+61 7 4155 6199",
    "sg:postcode":"4670",
    "sg:province":"QLD",
    "sg:tags":[
        "consultant",
        "laser"
    ],
    "wof:name":"Forsyth G L & M J",
    "wof:placetype":"venue"
},
  "geometry": {"coordinates":[152.39845275900001,-24.8322086334],"type":"Point"}
}