{
  "type": "Feature",
  "properties": {
    "addr:full":"Unit 1/ 8 - 10 Deadman Rd Moorebank NSW 2170",
    "addr:housenumber":"10",
    "addr:postcode":"2170",
    "addr:street":"Deadman Rd",
    "iso:country":"AU",
    "sg:address":"Unit 1/ 8 - 10 Deadman Rd",
    "sg:city":"Moorebank",
    "sg:classifiers":[
        {
            "category":"Building & Trades",
            "subcategory":"Pest Control",
            "type":"Services"
        }
    ],
    "sg:phone":"+61 1300 306 760",
    "sg:postcode":"2170",
    "sg:province":"NSW",
    "sg:website":"http://www.sherlockpest.com.au",
    "wof:name":"Sherlock Pest Control",
    "wof:placetype":"venue"
},
  "geometry": {"coordinates":[150.936157227,-33.9325752258],"type":"Point"}
}