{
  "type": "Feature",
  "properties": {
    "addr:full":"PO Box 510 Rosny TAS 7018",
    "addr:postcode":"7018",
    "iso:country":"AU",
    "sg:address":"PO Box 510",
    "sg:city":"Rosny",
    "sg:classifiers":[
        {
            "category":"Professional",
            "subcategory":"Detective & Security Services",
            "type":"Services"
        }
    ],
    "sg:phone":"+61 407 727 378",
    "sg:postcode":"7018",
    "sg:province":"TAS",
    "sg:tags":[
        "consultant",
        "system"
    ],
    "wof:name":"Tassat Communications",
    "wof:placetype":"venue"
},
  "geometry": {"coordinates":[147.355545044,-42.8691101074],"type":"Point"}
}