{
  "type": "Feature",
  "properties": {
    "addr:full":"335 Oxley Ave Redcliffe QLD 4020",
    "addr:housenumber":"335",
    "addr:postcode":"4020",
    "addr:street":"Oxley Ave",
    "iso:country":"AU",
    "sg:address":"335 Oxley Ave",
    "sg:city":"Redcliffe",
    "sg:classifiers":[
        {
            "category":"Retail",
            "subcategory":"Funeral Services",
            "type":"Services"
        }
    ],
    "sg:phone":"+61 7 3883 3983",
    "sg:postcode":"4020",
    "sg:province":"QLD",
    "sg:tags":[
        "director"
    ],
    "wof:name":"Skinners Funerals",
    "wof:placetype":"venue"
},
  "geometry": {"coordinates":[153.10791,-27.237471],"type":"Point"}
}