{
  "type": "Feature",
  "properties": {
    "iso:country":"AU",
    "sg:address":"Fairfield Waters Drv",
    "sg:city":"Idalia",
    "sg:classifiers":[
        {
            "category":"Education",
            "subcategory":"School",
            "type":"Public Place"
        }
    ],
    "sg:phone":"+61 7 4799 8333",
    "sg:postcode":"4811",
    "sg:province":"QLD",
    "sg:tags":[
        "state",
        "except",
        "nsw"
    ],
    "wof:name":"Oonoonba Primary",
    "wof:placetype":"venue"
},
  "geometry": {"coordinates":[146.812057,-19.304438],"type":"Point"}
}