{
  "type": "Feature",
  "properties": {
    "addr:full":"Kerford St Tatura VIC 3616",
    "addr:postcode":"3616",
    "addr:street":"St",
    "iso:country":"AU",
    "sg:address":"Kerford St",
    "sg:city":"Tatura",
    "sg:classifiers":[
        {
            "category":"Social Services",
            "subcategory":"Child Care",
            "type":"Services"
        }
    ],
    "sg:phone":"+61 3 5824 1294",
    "sg:postcode":"3616",
    "sg:province":"VIC",
    "sg:tags":[
        "support",
        "health"
    ],
    "wof:name":"Maternal & Child Health Centres",
    "wof:placetype":"venue"
},
  "geometry": {"coordinates":[145.22906494099999,-36.442440033],"type":"Point"}
}