{
  "type": "Feature",
  "properties": {
    "addr:full":"725 Glenferrie Rd Hawthorn VIC 3122",
    "addr:housenumber":"725",
    "addr:postcode":"3122",
    "addr:street":"Glenferrie Rd",
    "iso:country":"AU",
    "sg:address":"725 Glenferrie Rd",
    "sg:city":"Hawthorn",
    "sg:classifiers":[
        {
            "category":"Shopping",
            "subcategory":"Clothing, Apparel, & Fashions",
            "type":"Retail Goods"
        }
    ],
    "sg:phone":"+61 3 9819 3376",
    "sg:postcode":"3122",
    "sg:province":"VIC",
    "sg:tags":[
        "lingerie",
        "hosiery",
        "sleepwear"
    ],
    "wof:name":"Betty McDowell",
    "wof:placetype":"venue"
},
  "geometry": {"coordinates":[145.035842895,-37.8190803528],"type":"Point"}
}