{
  "type": "Feature",
  "properties": {
    "addr:full":"25- 47 Horne St Sunbury VIC 3429",
    "addr:housenumber":"47",
    "addr:postcode":"3429",
    "addr:street":"Horne St",
    "iso:country":"AU",
    "sg:address":"25- 47 Horne St",
    "sg:city":"Sunbury",
    "sg:classifiers":[
        {
            "category":"Food & Beverages",
            "subcategory":"Liquor & Beverages",
            "type":"Retail Goods"
        }
    ],
    "sg:phone":"+61 3 9744 4133",
    "sg:postcode":"3429",
    "sg:province":"VIC",
    "sg:tags":[
        "store"
    ],
    "wof:name":"Safeway Liquor",
    "wof:placetype":"venue"
},
  "geometry": {"coordinates":[144.725906372,-37.5797958374],"type":"Point"}
}