{
  "type": "Feature",
  "properties": {
    "iso:country":"AU",
    "sg:address":"PO Box 5129 Studfield 3152",
    "sg:city":"Wantirna",
    "sg:classifiers":[
        {
            "category":"Utilities",
            "subcategory":"Electric",
            "type":"Services"
        }
    ],
    "sg:phone":"+61 3 9762 1234",
    "sg:postcode":"3152",
    "sg:province":"VIC",
    "sg:tags":[
        "electrical",
        "contractor"
    ],
    "wof:name":"LLoyds Electrical",
    "wof:placetype":"venue"
},
  "geometry": {"coordinates":[145.227096558,-37.8489570618],"type":"Point"}
}