{
  "type": "Feature",
  "properties": {
    "iso:country":"AU",
    "sg:address":"163 Jellicoe St",
    "sg:city":"Toowoomba",
    "sg:classifiers":[
        {
            "category":"Home & Garden",
            "subcategory":"Furniture",
            "type":"Retail Goods"
        }
    ],
    "sg:phone":"+61 7 4632 7069",
    "sg:postcode":"4350",
    "sg:province":"QLD",
    "sg:tags":[
        "business"
    ],
    "wof:name":"Fiveways New & Used Furniture Sales",
    "wof:placetype":"venue"
},
  "geometry": {"coordinates":[151.942245,-27.544323],"type":"Point"}
}