{
  "type": "Feature",
  "properties": {
    "iso:country":"AU",
    "sg:address":"GMF Health Building 7/130 Egan St",
    "sg:city":"Kalgoorlie",
    "sg:classifiers":[
        {
            "category":"Health Services",
            "subcategory":"Dentist",
            "type":"Services"
        }
    ],
    "sg:phone":"+61 8 9091 4000",
    "sg:postcode":"6430",
    "sg:province":"WA",
    "wof:name":"GMF Dental Centre",
    "wof:placetype":"venue"
},
  "geometry": {"coordinates":[121.470397949,-30.7510604858],"type":"Point"}
}