{
  "type": "Feature",
  "properties": {
    "addr:full":"PO Box 7302 Garbutt Business Centre QLD 4814",
    "addr:postcode":"4814",
    "iso:country":"AU",
    "sg:address":"PO Box 7302",
    "sg:city":"Garbutt Business Centre",
    "sg:classifiers":[
        {
            "category":"Retail",
            "subcategory":"Auto Repair",
            "type":"Services"
        }
    ],
    "sg:phone":"+61 438 287 900",
    "sg:postcode":"4814",
    "sg:province":"QLD",
    "sg:tags":[
        "repairer",
        "motor",
        "engineer"
    ],
    "wof:name":"Barrys Transmissions",
    "wof:placetype":"venue"
},
  "geometry": {"coordinates":[146.76252700000001,-19.292179],"type":"Point"}
}