{
  "type": "Feature",
  "properties": {
    "addr:full":"59- 65 Gaines Rd Dandenong South VIC 3175",
    "addr:housenumber":"65",
    "addr:postcode":"3175",
    "addr:street":"Gaines Rd",
    "iso:country":"AU",
    "sg:address":"59- 65 Gaines Rd",
    "sg:city":"Dandenong South",
    "sg:classifiers":[
        {
            "category":"Home & Garden",
            "subcategory":"Garden Supply",
            "type":"Retail Goods"
        }
    ],
    "sg:phone":"+61 3 9702 7788",
    "sg:postcode":"3175",
    "sg:province":"VIC",
    "sg:tags":[
        "equipment"
    ],
    "wof:name":"Serano Timber & Hardware",
    "wof:placetype":"venue"
},
  "geometry": {"coordinates":[145.241500855,-38.0350990295],"type":"Point"}
}