{
  "type": "Feature",
  "properties": {
    "addr:full":"22 Piction St Broken Hill NSW 2880",
    "addr:housenumber":"22",
    "addr:postcode":"2880",
    "addr:street":"Piction St",
    "iso:country":"AU",
    "sg:address":"22 Piction St",
    "sg:city":"Broken Hill",
    "sg:classifiers":[
        {
            "category":"Shopping",
            "subcategory":"Computers & Home Electronics",
            "type":"Retail Goods"
        }
    ],
    "sg:phone":"+61 2 6836 2900",
    "sg:postcode":"2880",
    "sg:province":"NSW",
    "sg:tags":[
        "hardware",
        "equipment"
    ],
    "wof:name":"Copper City Stationery",
    "wof:placetype":"venue"
},
  "geometry": {"coordinates":[141.46548461899999,-31.9583301544],"type":"Point"}
}