{
  "type": "Feature",
  "properties": {
    "addr:full":"Building 3.4 Dairy Rd Fyshwick ACT 2609",
    "addr:postcode":"2609",
    "addr:street":"Dairy Rd",
    "iso:country":"AU",
    "sg:address":"Building 3.4 Dairy Rd",
    "sg:city":"Fyshwick",
    "sg:classifiers":[
        {
            "category":"Retail",
            "subcategory":"Auto Repair",
            "type":"Services"
        }
    ],
    "sg:phone":"+61 2 6202 5378",
    "sg:postcode":"2609",
    "sg:province":"ACT",
    "sg:tags":[
        "repairer",
        "motor",
        "engineer"
    ],
    "wof:name":"Dasfleet Auto Service",
    "wof:placetype":"venue"
},
  "geometry": {"coordinates":[149.166015625,-35.3212966919],"type":"Point"}
}