{
  "type": "Feature",
  "properties": {
    "iso:country":"AU",
    "sg:address":"200 Timor St",
    "sg:city":"Warrnambool",
    "sg:classifiers":[
        {
            "category":"Professional",
            "subcategory":"Computer Services",
            "type":"Services"
        }
    ],
    "sg:phone":"+61 3 5561 7280",
    "sg:postcode":"3280",
    "sg:province":"VIC",
    "sg:tags":[
        "training"
    ],
    "wof:name":"Multimedia Warrnambool",
    "wof:placetype":"venue"
},
  "geometry": {"coordinates":[142.48077392600001,-38.3845787048],"type":"Point"}
}