{
  "type": "Feature",
  "properties": {
    "addr:full":"18 Carbine Crt Kelso QLD 4815",
    "addr:housenumber":"18",
    "addr:postcode":"4815",
    "addr:street":"Carbine Crt",
    "iso:country":"AU",
    "sg:address":"18 Carbine Crt",
    "sg:city":"Kelso",
    "sg:classifiers":[
        {
            "category":"Government",
            "subcategory":"Post Office",
            "type":"Public Place"
        }
    ],
    "sg:phone":"+61 407 166 315",
    "sg:postcode":"4815",
    "sg:province":"QLD",
    "sg:tags":[
        "equipment",
        "hole",
        "contractor"
    ],
    "wof:name":"A W Morelli",
    "wof:placetype":"venue"
},
  "geometry": {"coordinates":[146.72813400000001,-19.409811],"type":"Point"}
}