{
  "type": "Feature",
  "properties": {
    "iso:country":"AU",
    "sg:address":"70 Scotts Rd",
    "sg:city":"Risdon Vale",
    "sg:classifiers":[
        {
            "category":"Building & Trades",
            "subcategory":"Construction",
            "type":"Services"
        }
    ],
    "sg:phone":"+61 3 6243 0711",
    "sg:postcode":"7016",
    "sg:province":"TAS",
    "sg:tags":[
        "rigging",
        "erection",
        "contractor"
    ],
    "wof:name":"Highrig Crane Hire",
    "wof:placetype":"venue"
},
  "geometry": {"coordinates":[147.35049438499999,-42.8047103882],"type":"Point"}
}