{
  "type": "Feature",
  "properties": {
    "addr:full":"365 Macquarie St South Hobart TAS 7004",
    "addr:housenumber":"365",
    "addr:postcode":"7004",
    "addr:street":"Macquarie St",
    "iso:country":"AU",
    "sg:address":"365 Macquarie St",
    "sg:city":"South Hobart",
    "sg:classifiers":[
        {
            "category":"Building & Trades",
            "subcategory":"Construction",
            "type":"Services"
        }
    ],
    "sg:phone":"+61 3 6223 5887",
    "sg:postcode":"7004",
    "sg:province":"TAS",
    "sg:tags":[
        "earth",
        "excavating",
        "moving",
        "contractor"
    ],
    "wof:name":"C A Long Pty Ltd",
    "wof:placetype":"venue"
},
  "geometry": {"coordinates":[147.31585693400001,-42.8925247192],"type":"Point"}
}