{
  "type": "Feature",
  "properties": {
    "addr:full":"Cnr Lydia & Moore Sts Ravenshoe QLD 4872",
    "addr:postcode":"4872",
    "iso:country":"AU",
    "sg:address":"Cnr Lydia & Moore Sts",
    "sg:city":"Ravenshoe",
    "sg:classifiers":[
        {
            "category":"Health Services",
            "subcategory":"Dentist",
            "type":"Services"
        }
    ],
    "sg:phone":"+61 7 4097 6404",
    "sg:postcode":"4872",
    "sg:province":"QLD",
    "wof:name":"Jacob John",
    "wof:placetype":"venue"
},
  "geometry": {"coordinates":[145.686309814,-16.8261585236],"type":"Point"}
}