{
  "type": "Feature",
  "properties": {
    "addr:full":"301 Bay St Brighton North VIC 3186",
    "addr:housenumber":"301",
    "addr:postcode":"3186",
    "addr:street":"Bay St",
    "iso:country":"AU",
    "sg:address":"301 Bay St",
    "sg:city":"Brighton North",
    "sg:classifiers":[
        {
            "category":"Professional",
            "subcategory":"Printing & Photocopies",
            "type":"Services"
        }
    ],
    "sg:phone":"+61 3 9596 3311",
    "sg:postcode":"3186",
    "sg:province":"VIC",
    "sg:tags":[
        "laminating"
    ],
    "wof:name":"Bottomley Fine Framing",
    "wof:placetype":"venue"
},
  "geometry": {"coordinates":[145.002151489,-37.9053382874],"type":"Point"}
}