{
  "type": "Feature",
  "properties": {
    "addr:full":"36 Caldermeade Rd Corio VIC 3214",
    "addr:housenumber":"36",
    "addr:postcode":"3214",
    "addr:street":"Caldermeade Rd",
    "iso:country":"AU",
    "sg:address":"36 Caldermeade Rd",
    "sg:city":"Corio",
    "sg:classifiers":[
        {
            "category":"Building & Trades",
            "subcategory":"Construction",
            "type":"Services"
        }
    ],
    "sg:phone":"+61 412 032 187",
    "sg:postcode":"3214",
    "sg:province":"VIC",
    "sg:tags":[
        "brick",
        "paving"
    ],
    "wof:name":"Olde Geelong Paving Company",
    "wof:placetype":"venue"
},
  "geometry": {"coordinates":[144.341796875,-38.0688705444],"type":"Point"}
}