{
  "type": "Feature",
  "properties": {
    "iso:country":"AU",
    "sg:address":"Mill Rd",
    "sg:city":"Edmonton",
    "sg:classifiers":[
        {
            "category":"Farming",
            "subcategory":"Farm",
            "type":"Manufacturing & Wholesale Goods"
        }
    ],
    "sg:phone":"+61 7 4055 4219",
    "sg:postcode":"4869",
    "sg:province":"QLD",
    "sg:tags":[
        "farmer"
    ],
    "wof:name":"Mann G G & N E",
    "wof:placetype":"venue"
},
  "geometry": {"coordinates":[145.73402404800001,-17.0210590363],"type":"Point"}
}