{
  "type": "Feature",
  "properties": {
    "addr:full":"7 Cuthbert Drv Mt Warrigal NSW 2528",
    "addr:housenumber":"7",
    "addr:postcode":"2528",
    "addr:street":"Cuthbert Drv",
    "iso:country":"AU",
    "sg:address":"7 Cuthbert Drv",
    "sg:city":"Mt Warrigal",
    "sg:classifiers":[
        {
            "category":"Building & Trades",
            "subcategory":"Construction",
            "type":"Services"
        }
    ],
    "sg:phone":"+61 2 4296 6671",
    "sg:postcode":"2528",
    "sg:province":"NSW",
    "sg:tags":[
        "joiner",
        "carpenter"
    ],
    "wof:name":"Mifsud Paul",
    "wof:placetype":"venue"
},
  "geometry": {"coordinates":[150.847732544,-34.5486717224],"type":"Point"}
}