{
  "type": "Feature",
  "properties": {
    "iso:country":"AU",
    "sg:address":"2/ 41 Deakin St",
    "sg:city":"Brendale",
    "sg:classifiers":[
        {
            "category":"Professional",
            "subcategory":"Printing & Photocopies",
            "type":"Services"
        }
    ],
    "sg:phone":"+61 7 3881 2339",
    "sg:postcode":"4500",
    "sg:province":"QLD",
    "sg:tags":[
        "photocopying"
    ],
    "wof:name":"Snap Printing",
    "wof:placetype":"venue"
},
  "geometry": {"coordinates":[152.989624023,-27.3251857758],"type":"Point"}
}