{
  "type": "Feature",
  "properties": {
    "iso:country":"AU",
    "sg:address":"23 Barvas St",
    "sg:city":"Ferny Grove",
    "sg:classifiers":[
        {
            "category":"Building & Trades",
            "subcategory":"Construction",
            "type":"Services"
        }
    ],
    "sg:phone":"+61 7 3351 4642",
    "sg:postcode":"4055",
    "sg:province":"QLD",
    "sg:tags":[
        "contractor"
    ],
    "wof:name":"Custom Carpentry",
    "wof:placetype":"venue"
},
  "geometry": {"coordinates":[152.930877686,-27.3984203339],"type":"Point"}
}