{
  "type": "Feature",
  "properties": {
    "addr:full":"36 Murrumbeena Crs Murrumbeena VIC 3163",
    "addr:housenumber":"36",
    "addr:postcode":"3163",
    "addr:street":"Murrumbeena Crs",
    "iso:country":"AU",
    "sg:address":"36 Murrumbeena Crs",
    "sg:city":"Murrumbeena",
    "sg:classifiers":[
        {
            "category":"Building & Trades",
            "subcategory":"Cleaning & Sanitation",
            "type":"Services"
        }
    ],
    "sg:phone":"+61 3 9568 7804",
    "sg:postcode":"3163",
    "sg:province":"VIC",
    "sg:tags":[
        "industrial",
        "commercial",
        "contractor"
    ],
    "wof:name":"Fine Floors",
    "wof:placetype":"venue"
},
  "geometry": {"coordinates":[145.067092895,-37.8876266479],"type":"Point"}
}