{
  "type": "Feature",
  "properties": {
    "iso:country":"AU",
    "sg:address":"2062 Fourteenth St",
    "sg:city":"Mildura",
    "sg:classifiers":[
        {
            "category":"Personal",
            "subcategory":"Massage",
            "type":"Services"
        }
    ],
    "sg:phone":"+61 402 297 494",
    "sg:postcode":"3500",
    "sg:province":"VIC",
    "sg:tags":[
        "therapy"
    ],
    "wof:name":"Una Harding",
    "wof:placetype":"venue"
},
  "geometry": {"coordinates":[142.17285156200001,-34.2200012207],"type":"Point"}
}