{
  "type": "Feature",
  "properties": {
    "addr:full":"257 Main St Lithgow NSW 2790",
    "addr:housenumber":"257",
    "addr:postcode":"2790",
    "addr:street":"Main St",
    "iso:country":"AU",
    "sg:address":"257 Main St",
    "sg:city":"Lithgow",
    "sg:classifiers":[
        {
            "category":"Professional",
            "subcategory":"Accounting & Tax Preparation",
            "type":"Services"
        }
    ],
    "sg:phone":"+61 2 6351 2940",
    "sg:postcode":"2790",
    "sg:province":"NSW",
    "sg:tags":[
        "accountant",
        "auditor"
    ],
    "wof:name":"Buckley John",
    "wof:placetype":"venue"
},
  "geometry": {"coordinates":[150.14845275900001,-33.4831161499],"type":"Point"}
}