{
  "type": "Feature",
  "properties": {
    "addr:full":"12 Garnett Rd East Maitland NSW 2323",
    "addr:housenumber":"12",
    "addr:postcode":"2323",
    "addr:street":"Garnett Rd",
    "iso:country":"AU",
    "sg:address":"12 Garnett Rd",
    "sg:city":"East Maitland",
    "sg:classifiers":[
        {
            "category":"Professional",
            "subcategory":"Computer Services",
            "type":"Services"
        }
    ],
    "sg:phone":"+61 2 4934 4330",
    "sg:postcode":"2323",
    "sg:province":"NSW",
    "sg:tags":[
        "package",
        "software"
    ],
    "wof:name":"Geodata Information Systems Pty Ltd",
    "wof:placetype":"venue"
},
  "geometry": {"coordinates":[151.58888244600001,-32.7600517273],"type":"Point"}
}