{
  "type": "Feature",
  "properties": {
    "iso:country":"AU",
    "sg:address":"344 Settlement Rd",
    "sg:city":"Thomastown",
    "sg:classifiers":[
        {
            "category":"Wholesale",
            "subcategory":"Auto Parts",
            "type":"Manufacturing & Wholesale Goods"
        }
    ],
    "sg:phone":"+61 3 9465 8088",
    "sg:postcode":"3074",
    "sg:province":"VIC",
    "sg:tags":[
        "recyclers"
    ],
    "wof:name":"A ABC Epping Auto Salvage",
    "wof:placetype":"venue"
},
  "geometry": {"coordinates":[145.02093505900001,-37.6885948181],"type":"Point"}
}