{
  "type": "Feature",
  "properties": {
    "iso:country":"AU",
    "sg:address":"Unit 5 / 1341 Albany Hwy",
    "sg:city":"Cannington",
    "sg:classifiers":[
        {
            "category":"Health Services",
            "subcategory":"Dentist",
            "type":"Services"
        }
    ],
    "sg:phone":"+61 8 9458 8646",
    "sg:postcode":"6107",
    "sg:province":"WA",
    "wof:name":"Gasiorowski John",
    "wof:placetype":"venue"
},
  "geometry": {"coordinates":[115.933692932,-32.0175209045],"type":"Point"}
}