{
  "type": "Feature",
  "properties": {
    "iso:country":"AU",
    "sg:address":"33b Berrigan Rd",
    "sg:city":"Devonport",
    "sg:classifiers":[
        {
            "category":"Personal",
            "subcategory":"Piercing",
            "type":"Services"
        }
    ],
    "sg:phone":"+61 3 6424 7554",
    "sg:postcode":"7310",
    "sg:province":"TAS",
    "sg:tags":[
        "body",
        "ear"
    ],
    "wof:name":"Salon 32",
    "wof:placetype":"venue"
},
  "geometry": {"coordinates":[146.355194092,-41.1956214905],"type":"Point"}
}