{
  "type": "Feature",
  "properties": {
    "addr:full":"Unit 10 - 101 Jijaws St Sumner Park QLD 4074",
    "addr:housenumber":"101",
    "addr:postcode":"4074",
    "addr:street":"Jijaws St",
    "iso:country":"AU",
    "sg:address":"Unit 10 - 101 Jijaws St",
    "sg:city":"Sumner Park",
    "sg:classifiers":[
        {
            "category":"Utilities",
            "subcategory":"Electric",
            "type":"Services"
        }
    ],
    "sg:phone":"+61 7 3279 0000",
    "sg:postcode":"4074",
    "sg:province":"QLD",
    "sg:tags":[
        "electrical",
        "contractor"
    ],
    "wof:name":"R. Jay Electrical Services",
    "wof:placetype":"venue"
},
  "geometry": {"coordinates":[152.94023132300001,-27.5651493073],"type":"Point"}
}