{
  "type": "Feature",
  "properties": {
    "addr:full":"Unit 5, Paxbury House 91 Landsborough Ave Scarborough QLD 4020",
    "addr:housenumber":"91",
    "addr:postcode":"4020",
    "addr:street":"Landsborough Ave",
    "iso:country":"AU",
    "sg:address":"Unit 5, Paxbury House 91 Landsborough Ave",
    "sg:city":"Scarborough",
    "sg:classifiers":[
        {
            "category":"Professional",
            "subcategory":"Testing Lab",
            "type":"Services"
        }
    ],
    "sg:phone":"+61 7 3203 8699",
    "sg:postcode":"4020",
    "sg:province":"QLD",
    "sg:tags":[
        "soil",
        "investigation"
    ],
    "wof:name":"Brisbane North Geotech Consultants",
    "wof:placetype":"venue"
},
  "geometry": {"coordinates":[153.11436499999999,-27.204266],"type":"Point"}
}