{
  "type": "Feature",
  "properties": {
    "addr:full":"28 Kalang Rd Camberwell VIC 3124",
    "addr:housenumber":"28",
    "addr:postcode":"3124",
    "addr:street":"Kalang Rd",
    "iso:country":"AU",
    "sg:address":"28 Kalang Rd",
    "sg:city":"Camberwell",
    "sg:classifiers":[
        {
            "category":"Building & Trades",
            "subcategory":"Landscaping Services",
            "type":"Services"
        }
    ],
    "sg:phone":"+61 3 9889 1417",
    "sg:postcode":"3124",
    "sg:province":"VIC",
    "sg:tags":[
        "gardener"
    ],
    "wof:name":"Franipeni Garden Management",
    "wof:placetype":"venue"
},
  "geometry": {"coordinates":[145.08114624000001,-37.8444099426],"type":"Point"}
}