{
  "type": "Feature",
  "properties": {
    "addr:full":"RMB 520 Goonoo Goonoo Rd Tamworth NSW 2340",
    "addr:postcode":"2340",
    "addr:street":"Goonoo Goonoo Rd",
    "iso:country":"AU",
    "sg:address":"RMB 520 Goonoo Goonoo Rd",
    "sg:city":"Tamworth",
    "sg:classifiers":[
        {
            "category":"Utilities",
            "subcategory":"Water",
            "type":"Services"
        }
    ],
    "sg:phone":"+61 2 6767 0273",
    "sg:postcode":"2340",
    "sg:province":"NSW",
    "sg:tags":[
        "cartage"
    ],
    "wof:name":"Tamworth Water Delivery",
    "wof:placetype":"venue"
},
  "geometry": {"coordinates":[150.92288207999999,-31.0920314789],"type":"Point"}
}