{
  "type": "Feature",
  "properties": {
    "iso:country":"AU",
    "sg:address":"Cnr Sturgeon & Wellington Sts",
    "sg:city":"Ormiston",
    "sg:classifiers":[
        {
            "category":"Health Services",
            "subcategory":"Doctor",
            "type":"Services"
        }
    ],
    "sg:phone":"+61 7 3286 5333",
    "sg:postcode":"4160",
    "sg:province":"QLD",
    "sg:tags":[
        "medical",
        "practitioner"
    ],
    "wof:name":"Dudgeon Alan",
    "wof:placetype":"venue"
},
  "geometry": {"coordinates":[153.25291442899999,-27.511844635],"type":"Point"}
}