{
  "type": "Feature",
  "properties": {
    "addr:full":"1/ 3 Mount St Burnie TAS 7320",
    "addr:housenumber":"/ 3",
    "addr:postcode":"7320",
    "addr:street":"Mount St",
    "iso:country":"AU",
    "sg:address":"1/ 3 Mount St",
    "sg:city":"Burnie",
    "sg:classifiers":[
        {
            "category":"Autos & Motor Vehicles",
            "subcategory":"Fuel & Gas Station",
            "type":"Retail Goods"
        }
    ],
    "sg:phone":"+61 3 6431 5317",
    "sg:postcode":"7320",
    "sg:province":"TAS",
    "wof:name":"Caltex West Beach Service Station",
    "wof:placetype":"venue"
},
  "geometry": {"coordinates":[145.905655,-41.049992],"type":"Point"}
}