{
  "type": "Feature",
  "properties": {
    "addr:full":"126-128 Ryrie St Geelong VIC 3220",
    "addr:housenumber":"126-128",
    "addr:postcode":"3220",
    "addr:street":"Ryrie St",
    "iso:country":"AU",
    "sg:address":"126-128 Ryrie St",
    "sg:city":"Geelong",
    "sg:classifiers":[
        {
            "category":"Education",
            "subcategory":"Dance Studio",
            "type":"Public Place"
        }
    ],
    "sg:phone":"+61 3 5266 1465",
    "sg:postcode":"3220",
    "sg:province":"VIC",
    "sg:tags":[
        "venue",
        "tuition"
    ],
    "wof:name":"Geelong Ballet Centre",
    "wof:placetype":"venue"
},
  "geometry": {"coordinates":[144.35871900000001,-38.149178],"type":"Point"}
}