{
  "type": "Feature",
  "properties": {
    "addr:full":"15 Ferrington Crs Liverpool NSW 2170",
    "addr:housenumber":"15",
    "addr:postcode":"2170",
    "addr:street":"Ferrington Crs",
    "iso:country":"AU",
    "sg:address":"15 Ferrington Crs",
    "sg:city":"Liverpool",
    "sg:classifiers":[
        {
            "category":"Utilities",
            "subcategory":"Electric",
            "type":"Services"
        }
    ],
    "sg:phone":"+61 2 9601 8601",
    "sg:postcode":"2170",
    "sg:province":"NSW",
    "sg:tags":[
        "electrical",
        "contractor"
    ],
    "wof:name":"N & J Electrical Air Conditioning",
    "wof:placetype":"venue"
},
  "geometry": {"coordinates":[150.910766602,-33.916683197],"type":"Point"}
}