{
  "type": "Feature",
  "properties": {
    "iso:country":"AU",
    "sg:address":"Cnr Charlestown & Myall Rds",
    "sg:city":"Charlestown",
    "sg:classifiers":[
        {
            "category":"Home & Garden",
            "subcategory":"Carpets & Floor Coverings",
            "type":"Retail Goods"
        }
    ],
    "sg:phone":"+61 2 4942 1311",
    "sg:postcode":"2290",
    "sg:province":"NSW",
    "sg:tags":[
        "tile",
        "wall"
    ],
    "wof:name":"Amber",
    "wof:placetype":"venue"
},
  "geometry": {"coordinates":[151.68814086899999,-32.9578399658],"type":"Point"}
}