{
  "type": "Feature",
  "properties": {
    "addr:full":"166 Great North Rd Five Dock NSW 2046",
    "addr:housenumber":"166",
    "addr:postcode":"2046",
    "addr:street":"Great North Rd",
    "iso:country":"AU",
    "sg:address":"166 Great North Rd",
    "sg:city":"Five Dock",
    "sg:classifiers":[
        {
            "category":"Military Area",
            "subcategory":"Air Force Base",
            "type":"Public Place"
        }
    ],
    "sg:phone":"+61 2 9713 1603",
    "sg:postcode":"2046",
    "sg:province":"NSW",
    "sg:tags":[
        "men's",
        "tailor"
    ],
    "wof:name":"Tornatore A",
    "wof:placetype":"venue"
},
  "geometry": {"coordinates":[151.13046299999999,-33.864868],"type":"Point"}
}