{
  "type": "Feature",
  "properties": {
    "addr:full":"16 Davis Drv Jindera NSW 2642",
    "addr:housenumber":"16",
    "addr:postcode":"2642",
    "addr:street":"Davis Drv",
    "iso:country":"AU",
    "sg:address":"16 Davis Drv",
    "sg:city":"Jindera",
    "sg:classifiers":[
        {
            "category":"Professional",
            "subcategory":"Engineering",
            "type":"Services"
        }
    ],
    "sg:phone":"+61 2 6026 3944",
    "sg:postcode":"2642",
    "sg:province":"NSW",
    "sg:tags":[
        "manufacturing",
        "engineer"
    ],
    "wof:name":"VDS Engineers Pty Ltd",
    "wof:placetype":"venue"
},
  "geometry": {"coordinates":[146.88897705100001,-35.9545898438],"type":"Point"}
}