{
  "type": "Feature",
  "properties": {
    "addr:full":"273 Albert St Balcatta WA 6021",
    "addr:housenumber":"273",
    "addr:postcode":"6021",
    "addr:street":"Albert St",
    "iso:country":"AU",
    "sg:address":"273 Albert St",
    "sg:city":"Balcatta",
    "sg:classifiers":[
        {
            "category":"Sports & Exercise",
            "subcategory":"Sports Center",
            "type":"Entertainment"
        }
    ],
    "sg:phone":"+61 8 9344 2215",
    "sg:postcode":"6021",
    "sg:province":"WA",
    "sg:tags":[
        "ground"
    ],
    "wof:name":"Macedonian Park",
    "wof:placetype":"venue"
},
  "geometry": {"coordinates":[115.826828003,-31.8796024323],"type":"Point"}
}