{
  "type": "Feature",
  "properties": {
    "addr:full":"7 Lincoln St Richmond VIC 3121",
    "addr:housenumber":"7",
    "addr:postcode":"3121",
    "addr:street":"Lincoln St",
    "iso:country":"AU",
    "sg:address":"7 Lincoln St",
    "sg:city":"Richmond",
    "sg:classifiers":[
        {
            "category":"Shopping",
            "type":"Retail Goods"
        }
    ],
    "sg:phone":"+61 3 9420 3744",
    "sg:postcode":"3121",
    "sg:province":"VIC",
    "sg:tags":[
        "equipment",
        "safety",
        "accessory"
    ],
    "wof:name":"FES Safety Shop",
    "wof:placetype":"venue"
},
  "geometry": {"coordinates":[145.00038147000001,-37.8128395081],"type":"Point"}
}