{
  "type": "Feature",
  "properties": {
    "addr:full":"Unit 5/ 14 Cressall Rd Balcatta WA 6021",
    "addr:postcode":"6021",
    "addr:street":"14 Cressall Rd",
    "iso:country":"AU",
    "sg:address":"Unit 5/ 14 Cressall Rd",
    "sg:city":"Balcatta",
    "sg:classifiers":[
        {
            "category":"Home & Garden",
            "subcategory":"Building Materials",
            "type":"Retail Goods"
        }
    ],
    "sg:phone":"+61 8 9240 8311",
    "sg:postcode":"6021",
    "sg:province":"WA",
    "sg:tags":[
        "merchant",
        "glass",
        "glazier"
    ],
    "wof:name":"Glasscraft Pty Ltd",
    "wof:placetype":"venue"
},
  "geometry": {"coordinates":[115.812301636,-31.8612480164],"type":"Point"}
}