{
  "type": "Feature",
  "properties": {
    "addr:full":"Suite 5b, 1 Swann Rd Taringa QLD 4068",
    "addr:housenumber":"suite 5b 1",
    "addr:postcode":"4068",
    "addr:street":"Swann Rd",
    "iso:country":"AU",
    "sg:address":"Suite 5b, 1 Swann Rd",
    "sg:city":"Taringa",
    "sg:classifiers":[
        {
            "category":"Utilities",
            "subcategory":"Natural Gas",
            "type":"Services"
        }
    ],
    "sg:phone":"+61 7 3217 8772",
    "sg:postcode":"4068",
    "sg:province":"QLD",
    "sg:tags":[
        "consultant",
        "resource"
    ],
    "wof:name":"AustralAsian Resource Consultants",
    "wof:placetype":"venue"
},
  "geometry": {"coordinates":[152.97767639200001,-27.4936313629],"type":"Point"}
}