{
  "type": "Feature",
  "properties": {
    "iso:country":"AU",
    "sg:address":"11 Hendy Ave",
    "sg:city":"Collaroy",
    "sg:classifiers":[
        {
            "category":"Health Services",
            "subcategory":"Chiropractor",
            "type":"Services"
        }
    ],
    "sg:phone":"+61 2 9971 7159",
    "sg:postcode":"2097",
    "sg:province":"NSW",
    "wof:name":"Huggett Peter",
    "wof:placetype":"venue"
},
  "geometry": {"coordinates":[151.296218872,-33.7368545532],"type":"Point"}
}