{
  "type": "Feature",
  "properties": {
    "iso:country":"AU",
    "sg:address":"Strathpine Specialist Cntr 32 Dixon",
    "sg:city":"Strathpine",
    "sg:classifiers":[
        {
            "category":"Health Services",
            "subcategory":"Dentist",
            "type":"Services"
        }
    ],
    "sg:phone":"+61 7 3881 0165",
    "sg:postcode":"4500",
    "sg:province":"QLD",
    "wof:name":"Ferguson Peter D",
    "wof:placetype":"venue"
},
  "geometry": {"coordinates":[152.99530029300001,-27.3083190918],"type":"Point"}
}