{
  "type": "Feature",
  "properties": {
    "addr:full":"82- 84 Glen Innes Rd Armidale NSW 2350",
    "addr:housenumber":"84",
    "addr:postcode":"2350",
    "addr:street":"Glen Innes Rd",
    "iso:country":"AU",
    "sg:address":"82- 84 Glen Innes Rd",
    "sg:city":"Armidale",
    "sg:classifiers":[
        {
            "category":"Social Services",
            "subcategory":"Retirement Home",
            "type":"Services"
        }
    ],
    "sg:phone":"+61 2 6771 4864",
    "sg:postcode":"2350",
    "sg:province":"NSW",
    "sg:tags":[
        "environmental",
        "consultant",
        "pollution"
    ],
    "wof:name":"E.A. Systems",
    "wof:placetype":"venue"
},
  "geometry": {"coordinates":[151.67103576700001,-30.4916343689],"type":"Point"}
}