{
  "type": "Feature",
  "properties": {
    "addr:full":"Cnr Carlton St & Price Ave North Rockhampton QLD 4701",
    "addr:postcode":"4701",
    "addr:street":"Cnr Carlton St & Price Ave North",
    "iso:country":"AU",
    "sg:address":"Cnr Carlton St & Price Ave",
    "sg:city":"North Rockhampton",
    "sg:classifiers":[
        {
            "category":"Home & Garden",
            "subcategory":"Building Materials",
            "type":"Retail Goods"
        }
    ],
    "sg:phone":"+61 7 4936 2088",
    "sg:postcode":"4701",
    "sg:province":"QLD",
    "sg:tags":[
        "fencing"
    ],
    "wof:name":"Fence Place The",
    "wof:placetype":"venue"
},
  "geometry": {"coordinates":[150.51690673799999,-23.3280334473],"type":"Point"}
}