{
  "type": "Feature",
  "properties": {
    "addr:full":"140 Corrigan Rd Noble Park VIC 3174",
    "addr:housenumber":"140",
    "addr:postcode":"3174",
    "addr:street":"Corrigan Rd",
    "iso:country":"AU",
    "sg:address":"140 Corrigan Rd",
    "sg:city":"Noble Park",
    "sg:classifiers":[
        {
            "category":"Building & Trades",
            "subcategory":"Plumbing",
            "type":"Services"
        }
    ],
    "sg:phone":"+61 419 377 332",
    "sg:postcode":"3174",
    "sg:province":"VIC",
    "sg:tags":[
        "plumber",
        "gasfitters"
    ],
    "wof:name":"Plumbcare",
    "wof:placetype":"venue"
},
  "geometry": {"coordinates":[145.16796875,-37.9663467407],"type":"Point"}
}