{
  "type": "Feature",
  "properties": {
    "addr:full":"114 Quarantine Rd Norwood TAS 7250",
    "addr:housenumber":"114",
    "addr:postcode":"7250",
    "addr:street":"Quarantine Rd",
    "iso:country":"AU",
    "sg:address":"114 Quarantine Rd",
    "sg:city":"Norwood",
    "sg:classifiers":[
        {
            "category":"Building & Trades",
            "subcategory":"Construction",
            "type":"Services"
        }
    ],
    "sg:phone":"+61 418 380 833",
    "sg:postcode":"7250",
    "sg:province":"TAS",
    "sg:tags":[
        "joinery"
    ],
    "wof:name":"Brett Stephens",
    "wof:placetype":"venue"
},
  "geometry": {"coordinates":[147.17619323700001,-41.4700202942],"type":"Point"}
}