{
  "type": "Feature",
  "properties": {
    "addr:full":"Ste 2/ 154 Henderson Rd Alexandria NSW 2015",
    "addr:housenumber":"/ 154",
    "addr:postcode":"2015",
    "addr:street":"Henderson Rd",
    "iso:country":"AU",
    "sg:address":"Ste 2/ 154 Henderson Rd",
    "sg:city":"Alexandria",
    "sg:classifiers":[
        {
            "category":"Shopping",
            "subcategory":"Clothing, Apparel, & Fashions",
            "type":"Retail Goods"
        }
    ],
    "sg:phone":"+61 2 9557 8242",
    "sg:postcode":"2015",
    "sg:province":"NSW",
    "sg:tags":[
        "lady",
        "wear"
    ],
    "wof:name":"Ru Mu Pty Ltd",
    "wof:placetype":"venue"
},
  "geometry": {"coordinates":[151.1925354,-33.8977928162],"type":"Point"}
}