{
  "type": "Feature",
  "properties": {
    "addr:full":"92 Pittwater Rd Manly NSW 2095",
    "addr:housenumber":"92",
    "addr:postcode":"2095",
    "addr:street":"Pittwater Rd",
    "iso:country":"AU",
    "sg:address":"92 Pittwater Rd",
    "sg:city":"Manly",
    "sg:classifiers":[
        {
            "category":"Professional",
            "subcategory":"Art Services",
            "type":"Services"
        }
    ],
    "sg:phone":"+61 2 9977 7372",
    "sg:postcode":"2095",
    "sg:province":"NSW",
    "sg:tags":[
        "graphic",
        "designer"
    ],
    "wof:name":"35ONE",
    "wof:placetype":"venue"
},
  "geometry": {"coordinates":[151.28570556599999,-33.7923927307],"type":"Point"}
}