{
  "type": "Feature",
  "properties": {
    "iso:country":"AU",
    "sg:address":"7 Addolorata Crt",
    "sg:city":"Highbury",
    "sg:classifiers":[
        {
            "category":"Building & Trades",
            "subcategory":"Construction",
            "type":"Services"
        }
    ],
    "sg:phone":"+61 417 882 815",
    "sg:postcode":"5089",
    "sg:province":"SA",
    "sg:tags":[
        "tennis court",
        "repair"
    ],
    "wof:name":"MBM Sports Surfacing",
    "wof:placetype":"venue"
},
  "geometry": {"coordinates":[138.701660156,-34.8504943848],"type":"Point"}
}