{
  "type": "Feature",
  "properties": {
    "addr:full":"143 Rokeby Rd Subiaco WA 6008",
    "addr:housenumber":"143",
    "addr:postcode":"6008",
    "addr:street":"Rokeby Rd",
    "iso:country":"AU",
    "sg:address":"143 Rokeby Rd",
    "sg:city":"Subiaco",
    "sg:classifiers":[
        {
            "category":"Shopping",
            "subcategory":"Jewelry",
            "type":"Retail Goods"
        }
    ],
    "sg:phone":"+61 8 9382 3222",
    "sg:postcode":"6008",
    "sg:province":"WA",
    "sg:tags":[
        "jeweller"
    ],
    "wof:name":"SMALES",
    "wof:placetype":"venue"
},
  "geometry": {"coordinates":[115.823822022,-31.9490890503],"type":"Point"}
}