{
  "type": "Feature",
  "properties": {
    "addr:full":"7 Wargundy Ave Rye VIC 3941",
    "addr:housenumber":"7",
    "addr:postcode":"3941",
    "addr:street":"Wargundy Ave",
    "iso:country":"AU",
    "sg:address":"7 Wargundy Ave",
    "sg:city":"Rye",
    "sg:classifiers":[
        {
            "category":"Building & Trades",
            "subcategory":"Construction",
            "type":"Services"
        }
    ],
    "sg:phone":"+61 417 709 366",
    "sg:postcode":"3941",
    "sg:province":"VIC",
    "sg:tags":[
        "fencing",
        "contractor"
    ],
    "wof:name":"Peninsula Feature Fencing",
    "wof:placetype":"venue"
},
  "geometry": {"coordinates":[144.82293701200001,-38.3853721619],"type":"Point"}
}