{
  "type": "Feature",
  "properties": {
    "addr:full":"7 Oborn St Whyalla Norrie SA 5608",
    "addr:housenumber":"7",
    "addr:postcode":"5608",
    "addr:street":"Oborn St",
    "iso:country":"AU",
    "sg:address":"7 Oborn St",
    "sg:city":"Whyalla Norrie",
    "sg:classifiers":[
        {
            "category":"Retail",
            "subcategory":"Car Wash",
            "type":"Services"
        }
    ],
    "sg:phone":"+61 8 8645 5599",
    "sg:postcode":"5608",
    "sg:province":"SA",
    "sg:tags":[
        "truck",
        "cleaning"
    ],
    "wof:name":"Whyalla Car Detailing",
    "wof:placetype":"venue"
},
  "geometry": {"coordinates":[137.54437300000001,-33.037189],"type":"Point"}
}