{
  "type": "Feature",
  "properties": {
    "iso:country":"AU",
    "sg:address":"35 Stephenson St",
    "sg:city":"Oxley",
    "sg:classifiers":[
        {
            "category":"Personal",
            "subcategory":"Nail Salon",
            "type":"Services"
        }
    ],
    "sg:phone":"+61 412 008 460",
    "sg:postcode":"4075",
    "sg:province":"QLD",
    "sg:tags":[
        "artificial"
    ],
    "wof:name":"Lee McKay",
    "wof:placetype":"venue"
},
  "geometry": {"coordinates":[152.97154235799999,-27.5607509613],"type":"Point"}
}