{
  "type": "Feature",
  "properties": {
    "iso:country":"AU",
    "sg:address":"U43, 51 Leighton Pl",
    "sg:city":"Hornsby",
    "sg:classifiers":[
        {
            "category":"Home & Garden",
            "subcategory":"Furniture",
            "type":"Retail Goods"
        }
    ],
    "sg:phone":"+61 2 9477 7755",
    "sg:postcode":"2077",
    "sg:province":"NSW",
    "sg:tags":[
        "business"
    ],
    "wof:name":"Northside Office Furniture Pty Ltd",
    "wof:placetype":"venue"
},
  "geometry": {"coordinates":[151.11749267600001,-33.694278717],"type":"Point"}
}