{
  "type": "Feature",
  "properties": {
    "addr:full":"Shop 23, Raymond Terrace Market Place, William St Raymond Terrace NSW 2324",
    "addr:housenumber":"shop 23",
    "addr:postcode":"2324",
    "addr:street":"Raymond Terrace Market Place William St",
    "iso:country":"AU",
    "sg:address":"Shop 23, Raymond Terrace Market Place, William St",
    "sg:city":"Raymond Terrace",
    "sg:classifiers":[
        {
            "category":"Shopping",
            "subcategory":"Shoes",
            "type":"Retail Goods"
        }
    ],
    "sg:phone":"+61 2 4983 1808",
    "sg:postcode":"2324",
    "sg:province":"NSW",
    "sg:tags":[
        "footwear"
    ],
    "wof:name":"Payless Shoes",
    "wof:placetype":"venue"
},
  "geometry": {"coordinates":[151.74574279800001,-32.7644882202],"type":"Point"}
}