{
  "type": "Feature",
  "properties": {
    "iso:country":"AU",
    "sg:address":"8 Electra St",
    "sg:city":"Bundaberg",
    "sg:classifiers":[
        {
            "category":"Shopping",
            "subcategory":"Luggage & Leather Goods",
            "type":"Retail Goods"
        }
    ],
    "sg:phone":"+61 7 4153 3326",
    "sg:postcode":"4670",
    "sg:province":"QLD",
    "wof:name":"R K Saddleworld & Country Clothing",
    "wof:placetype":"venue"
},
  "geometry": {"coordinates":[152.348876953,-24.8663959503],"type":"Point"}
}