{
  "type": "Feature",
  "properties": {
    "iso:country":"AU",
    "sg:address":"18 Foster St",
    "sg:city":"Railton",
    "sg:classifiers":[
        {
            "category":"Military Area",
            "subcategory":"Air Force Base",
            "type":"Public Place"
        }
    ],
    "sg:phone":"+61 417 556 700",
    "sg:postcode":"7305",
    "sg:province":"TAS",
    "sg:tags":[
        "fibre",
        "optic"
    ],
    "wof:name":"Looking Glass Cottage",
    "wof:placetype":"venue"
},
  "geometry": {"coordinates":[146.422684,-41.346134],"type":"Point"}
}