{
  "type": "Feature",
  "properties": {
    "addr:full":"Unit 4/ 16 Sweetenham Rd Minto NSW 2566",
    "addr:postcode":"2566",
    "addr:street":"16 Sweetenham Rd",
    "iso:country":"AU",
    "sg:address":"Unit 4/ 16 Sweetenham Rd",
    "sg:city":"Minto",
    "sg:classifiers":[
        {
            "category":"Food & Beverages",
            "subcategory":"Liquor & Beverages",
            "type":"Retail Goods"
        }
    ],
    "sg:phone":"+61 2 9820 1555",
    "sg:postcode":"2566",
    "sg:province":"NSW",
    "sg:tags":[
        "store"
    ],
    "wof:name":"Liquorstop",
    "wof:placetype":"venue"
},
  "geometry": {"coordinates":[150.83180236800001,-34.0294952393],"type":"Point"}
}