{
  "type": "Feature",
  "properties": {
    "iso:country":"AU",
    "sg:address":"6 Joyce St",
    "sg:city":"Branxholm",
    "sg:classifiers":[
        {
            "category":"Building & Trades",
            "subcategory":"Construction",
            "type":"Services"
        }
    ],
    "sg:phone":"+61 429 783 837",
    "sg:postcode":"7261",
    "sg:province":"TAS",
    "sg:tags":[
        "earth",
        "excavating",
        "moving",
        "contractor"
    ],
    "wof:name":"S Phillips Earthmoving",
    "wof:placetype":"venue"
},
  "geometry": {"coordinates":[147.740479,-41.168625],"type":"Point"}
}