{
  "type": "Feature",
  "properties": {
    "addr:full":"Second Ave Injune QLD 4454",
    "addr:postcode":"4454",
    "addr:street":"Second Ave",
    "iso:country":"AU",
    "sg:address":"Second Ave",
    "sg:city":"Injune",
    "sg:classifiers":[
        {
            "category":"Health Services",
            "subcategory":"Doctor",
            "type":"Services"
        }
    ],
    "sg:phone":"+61 7 4626 1343",
    "sg:postcode":"4454",
    "sg:province":"QLD",
    "sg:tags":[
        "nurse",
        "nursing"
    ],
    "wof:name":"Blue Nursing Service",
    "wof:placetype":"venue"
},
  "geometry": {"coordinates":[148.56556701700001,-25.8429203033],"type":"Point"}
}