{
  "type": "Feature",
  "properties": {
    "addr:full":"3 O'Keefe Crt Garbutt QLD 4814",
    "addr:housenumber":"3",
    "addr:postcode":"4814",
    "addr:street":"O'Keefe Crt",
    "iso:country":"AU",
    "sg:address":"3 O'Keefe Crt",
    "sg:city":"Garbutt",
    "sg:classifiers":[
        {
            "category":"Shopping",
            "subcategory":"Computers & Home Electronics",
            "type":"Retail Goods"
        }
    ],
    "sg:phone":"+61 7 4725 6490",
    "sg:postcode":"4814",
    "sg:province":"QLD",
    "sg:tags":[
        "hardware",
        "equipment"
    ],
    "wof:name":"Rosh-Tech Townsville Pty Ltd",
    "wof:placetype":"venue"
},
  "geometry": {"coordinates":[146.76315299999999,-19.27743],"type":"Point"}
}