{
  "type": "Feature",
  "properties": {
    "iso:country":"AU",
    "sg:address":"11 Nyora Ave",
    "sg:city":"Smithfield",
    "sg:classifiers":[
        {
            "category":"Health Services",
            "subcategory":"Nursing And Care Facility",
            "type":"Services"
        }
    ],
    "sg:phone":"+61 2 9755 7333",
    "sg:postcode":"2164",
    "sg:province":"NSW",
    "sg:tags":[
        "home"
    ],
    "wof:name":"Nyora Gardens Nursing Home",
    "wof:placetype":"venue"
},
  "geometry": {"coordinates":[150.94535827600001,-33.8607711792],"type":"Point"}
}