{
  "type": "Feature",
  "properties": {
    "addr:full":"214 Wellington St Launceston TAS 7250",
    "addr:housenumber":"214",
    "addr:postcode":"7250",
    "addr:street":"Wellington St",
    "iso:country":"AU",
    "sg:address":"214 Wellington St",
    "sg:city":"Launceston",
    "sg:classifiers":[
        {
            "category":"Utilities",
            "subcategory":"Electric",
            "type":"Services"
        }
    ],
    "sg:phone":"+61 3 6343 2747",
    "sg:postcode":"7250",
    "sg:province":"TAS",
    "sg:tags":[
        "electrical",
        "contractor"
    ],
    "wof:name":"Tag & Test Gas/Electric",
    "wof:placetype":"venue"
},
  "geometry": {"coordinates":[147.14201355,-41.4512863159],"type":"Point"}
}