{
  "type": "Feature",
  "properties": {
    "addr:full":"207 Old Veteran Rd Gympie QLD 4570",
    "addr:housenumber":"207",
    "addr:postcode":"4570",
    "addr:street":"Old Veteran Rd",
    "iso:country":"AU",
    "sg:address":"207 Old Veteran Rd",
    "sg:city":"Gympie",
    "sg:classifiers":[
        {
            "category":"Building & Trades",
            "subcategory":"Landscaping Services",
            "type":"Services"
        }
    ],
    "sg:phone":"+61 7 5482 9256",
    "sg:postcode":"4570",
    "sg:province":"QLD",
    "sg:tags":[
        "forestry",
        "consultant"
    ],
    "wof:name":"Land Regeneration (Qld)",
    "wof:placetype":"venue"
},
  "geometry": {"coordinates":[152.70669555699999,-26.1562652588],"type":"Point"}
}