{
  "type": "Feature",
  "properties": {
    "iso:country":"AU",
    "sg:address":"Princes Hwy",
    "sg:city":"Narre Warren",
    "sg:classifiers":[
        {
            "category":"Shopping",
            "subcategory":"Mobile Phones",
            "type":"Retail Goods"
        }
    ],
    "sg:phone":"+61 3 9705 1233",
    "sg:postcode":"3805",
    "sg:province":"VIC",
    "sg:tags":[
        "telephone",
        "accessory"
    ],
    "wof:name":"Vodafone",
    "wof:placetype":"venue"
},
  "geometry": {"coordinates":[145.30183400000001,-38.02269],"type":"Point"}
}