{
  "type": "Feature",
  "properties": {
    "addr:full":"Unit 6 112 Benaroon Rd Belmore NSW 2192",
    "addr:housenumber":"112",
    "addr:postcode":"2192",
    "addr:street":"Benaroon Rd",
    "iso:country":"AU",
    "sg:address":"Unit 6 112 Benaroon Rd",
    "sg:city":"Belmore",
    "sg:classifiers":[
        {
            "category":"Education",
            "subcategory":"Music School",
            "type":"Public Place"
        }
    ],
    "sg:phone":"+61 2 9750 0544",
    "sg:postcode":"2192",
    "sg:province":"NSW",
    "sg:tags":[
        "hi-fi",
        "equipment",
        "wholesaler",
        "mfrs"
    ],
    "wof:name":"Soundring Pty Ltd",
    "wof:placetype":"venue"
},
  "geometry": {"coordinates":[151.07716400000001,-33.909012],"type":"Point"}
}