{
  "type": "Feature",
  "properties": {
    "addr:full":"4 Kitcherner Rd Melville WA 6156",
    "addr:housenumber":"4",
    "addr:postcode":"6156",
    "addr:street":"Kitcherner Rd",
    "iso:country":"AU",
    "sg:address":"4 Kitcherner Rd",
    "sg:city":"Melville",
    "sg:classifiers":[
        {
            "category":"Social Services",
            "subcategory":"Retirement Home",
            "type":"Services"
        }
    ],
    "sg:phone":"+61 8 9330 0100",
    "sg:postcode":"6156",
    "sg:province":"WA",
    "sg:tags":[
        "village"
    ],
    "wof:name":"Craigville Gardens",
    "wof:placetype":"venue"
},
  "geometry": {"coordinates":[115.79444100000001,-32.036633],"type":"Point"}
}