{
  "type": "Feature",
  "properties": {
    "iso:country":"AU",
    "sg:address":"26 Safety Bay Rd",
    "sg:city":"Rockingham",
    "sg:classifiers":[
        {
            "category":"Professional",
            "subcategory":"Secretarial Services",
            "type":"Services"
        }
    ],
    "sg:phone":"+61 8 9528 7133",
    "sg:postcode":"6168",
    "sg:province":"WA",
    "sg:tags":[
        "typing"
    ],
    "wof:name":"Sound Medical & Secretarial Typing Services",
    "wof:placetype":"venue"
},
  "geometry": {"coordinates":[115.711212,-32.281132],"type":"Point"}
}