{
  "type": "Feature",
  "properties": {
    "addr:full":"Cnr Princess & Oxford Sts Bulimba QLD 4171",
    "addr:postcode":"4171",
    "iso:country":"AU",
    "sg:address":"Cnr Princess & Oxford Sts",
    "sg:city":"Bulimba",
    "sg:classifiers":[
        {
            "category":"Food & Beverages",
            "subcategory":"Bakery",
            "type":"Retail Goods"
        }
    ],
    "sg:phone":"+61 7 3399 6701",
    "sg:postcode":"4171",
    "sg:province":"QLD",
    "sg:tags":[
        "baker"
    ],
    "wof:name":"Brumby's Bakeries",
    "wof:placetype":"venue"
},
  "geometry": {"coordinates":[153.059249878,-27.4513397217],"type":"Point"}
}