{
  "type": "Feature",
  "properties": {
    "iso:country":"AU",
    "sg:address":"Factory 5, 395- 397 Old Geelong Rd",
    "sg:city":"Hoppers Crossing",
    "sg:classifiers":[
        {
            "category":"Retail",
            "subcategory":"Auto Repair",
            "type":"Services"
        }
    ],
    "sg:phone":"+61 3 9360 9221",
    "sg:postcode":"3029",
    "sg:province":"VIC",
    "sg:tags":[
        "transmission",
        "automotive",
        "car"
    ],
    "wof:name":"Tectrans Automatic Transmission Specialists",
    "wof:placetype":"venue"
},
  "geometry": {"coordinates":[144.72908000000001,-37.869705],"type":"Point"}
}