{
  "type": "Feature",
  "properties": {
    "addr:full":"86 Bedford Rd Andergrove QLD 4740",
    "addr:housenumber":"86",
    "addr:postcode":"4740",
    "addr:street":"Bedford Rd",
    "iso:country":"AU",
    "sg:address":"86 Bedford Rd",
    "sg:city":"Andergrove",
    "sg:classifiers":[
        {
            "category":"Personal",
            "subcategory":"Beauty Salon",
            "type":"Services"
        }
    ],
    "sg:phone":"+61 407 826 497",
    "sg:postcode":"4740",
    "sg:province":"QLD",
    "wof:name":"Kelly Koolstra-Alplin Make-Up Artist/Photographer",
    "wof:placetype":"venue"
},
  "geometry": {"coordinates":[149.18194600000001,-21.107048],"type":"Point"}
}