{
  "type": "Feature",
  "properties": {
    "iso:country":"AU",
    "sg:address":"Lot 17 South West Hwy",
    "sg:city":"Boyanup",
    "sg:classifiers":[
        {
            "category":"Food & Beverages",
            "subcategory":"Liquor & Beverages",
            "type":"Retail Goods"
        }
    ],
    "sg:phone":"+61 8 9731 5781",
    "sg:postcode":"6237",
    "sg:province":"WA",
    "sg:tags":[
        "store"
    ],
    "wof:name":"Western Cellars",
    "wof:placetype":"venue"
},
  "geometry": {"coordinates":[115.558739,-33.554203],"type":"Point"}
}