{
  "type": "Feature",
  "properties": {
    "iso:country":"AU",
    "sg:address":"63 Milchester Rd",
    "sg:city":"Charters Towers",
    "sg:classifiers":[
        {
            "category":"Communications",
            "subcategory":"Film & Video Production",
            "type":"Services"
        }
    ],
    "sg:phone":"+61 7 4787 8330",
    "sg:postcode":"4820",
    "sg:province":"QLD",
    "sg:tags":[
        "buyer",
        "refiner",
        "gold"
    ],
    "wof:name":"Gold City Gold Services Pty Ltd",
    "wof:placetype":"venue"
},
  "geometry": {"coordinates":[146.263153,-20.0774],"type":"Point"}
}