{
  "type": "Feature",
  "properties": {
    "iso:country":"AU",
    "sg:address":"Ste10/ 3 Packard Ave",
    "sg:city":"Castle Hill",
    "sg:classifiers":[
        {
            "category":"Wholesale",
            "subcategory":"Non-durable Goods",
            "type":"Manufacturing & Wholesale Goods"
        }
    ],
    "sg:phone":"+61 2 8850 0048",
    "sg:postcode":"2154",
    "sg:province":"NSW",
    "sg:tags":[
        "wholesaler",
        "mfrs",
        "cosmetic"
    ],
    "wof:name":"Orbis Australasia Pty Ltd - (DU&#039;IT)",
    "wof:placetype":"venue"
},
  "geometry": {"coordinates":[150.982025147,-33.7349853516],"type":"Point"}
}