{
  "type": "Feature",
  "properties": {
    "iso:country":"AU",
    "sg:address":"269 The Pde",
    "sg:city":"Beulah Park",
    "sg:classifiers":[
        {
            "category":"Professional",
            "subcategory":"Accounting & Tax Preparation",
            "type":"Services"
        }
    ],
    "sg:phone":"+61 8 8364 0233",
    "sg:postcode":"5067",
    "sg:province":"SA",
    "sg:tags":[
        "consultant",
        "taxation"
    ],
    "wof:name":"Costanzo Rocco",
    "wof:placetype":"venue"
},
  "geometry": {"coordinates":[138.64486694300001,-34.9206771851],"type":"Point"}
}