{
  "type": "Feature",
  "properties": {
    "addr:full":"Golf Links Rd Pemberton WA 6260",
    "addr:postcode":"6260",
    "addr:street":"Golf Links Rd",
    "iso:country":"AU",
    "sg:address":"Golf Links Rd",
    "sg:city":"Pemberton",
    "sg:classifiers":[
        {
            "category":"Farming",
            "subcategory":"Farm",
            "type":"Manufacturing & Wholesale Goods"
        }
    ],
    "sg:phone":"+61 8 9776 1267",
    "sg:postcode":"6260",
    "sg:province":"WA",
    "sg:tags":[
        "farmer"
    ],
    "wof:name":"Bendotti John & Christine",
    "wof:placetype":"venue"
},
  "geometry": {"coordinates":[116.036247253,-34.4411621094],"type":"Point"}
}