{
  "type": "Feature",
  "properties": {
    "iso:country":"AU",
    "sg:address":"Unit 1, 18 Bentham St",
    "sg:city":"Yarralumla",
    "sg:classifiers":[
        {
            "category":"Health Services",
            "subcategory":"Doctor",
            "type":"Services"
        }
    ],
    "sg:phone":"+61 2 6282 3899",
    "sg:postcode":"2600",
    "sg:province":"ACT",
    "sg:tags":[
        "medical",
        "practitioner"
    ],
    "wof:name":"Yarralumla Surgery",
    "wof:placetype":"venue"
},
  "geometry": {"coordinates":[149.097290039,-35.307800293],"type":"Point"}
}