{
  "type": "Feature",
  "properties": {
    "addr:full":"1st Floor, 22 Queen St Fremantle WA 6160",
    "addr:housenumber":"22",
    "addr:postcode":"6160",
    "addr:street":"Queen St",
    "iso:country":"AU",
    "sg:address":"1st Floor, 22 Queen St",
    "sg:city":"Fremantle",
    "sg:classifiers":[
        {
            "category":"Professional",
            "subcategory":"Employment Agencies",
            "type":"Services"
        }
    ],
    "sg:phone":"+61 8 9431 6900",
    "sg:postcode":"6160",
    "sg:province":"WA",
    "wof:name":"Mercy Employment",
    "wof:placetype":"venue"
},
  "geometry": {"coordinates":[115.74839,-32.053131],"type":"Point"}
}