{
  "type": "Feature",
  "properties": {
    "addr:full":"Lot 16 Darragh Rd Pambula South NSW 2549",
    "addr:postcode":"2549",
    "addr:street":"Darragh Rd",
    "iso:country":"AU",
    "sg:address":"Lot 16 Darragh Rd",
    "sg:city":"Pambula South",
    "sg:classifiers":[
        {
            "category":"Retail",
            "subcategory":"Auto Repair",
            "type":"Services"
        }
    ],
    "sg:phone":"+61 2 6495 6279",
    "sg:postcode":"2549",
    "sg:province":"NSW",
    "sg:tags":[
        "body",
        "builder",
        "motor"
    ],
    "wof:name":"Hammond Conversions",
    "wof:placetype":"venue"
},
  "geometry": {"coordinates":[149.87188720699999,-36.9241790771],"type":"Point"}
}