{
  "type": "Feature",
  "properties": {
    "iso:country":"AU",
    "sg:address":"11 Carlotta St",
    "sg:city":"Greenwich",
    "sg:classifiers":[
        {
            "category":"Professional",
            "subcategory":"Art Services",
            "type":"Services"
        }
    ],
    "sg:phone":"+61 411 291 176",
    "sg:postcode":"2065",
    "sg:province":"NSW",
    "sg:tags":[
        "interior",
        "designer"
    ],
    "wof:name":"Beesley Boyd Colour & Design Consultants",
    "wof:placetype":"venue"
},
  "geometry": {"coordinates":[151.18646240199999,-33.82970047],"type":"Point"}
}