{
  "type": "Feature",
  "properties": {
    "addr:full":"55 Hunter St Hornsby NSW 2077",
    "addr:housenumber":"55",
    "addr:postcode":"2077",
    "addr:street":"Hunter St",
    "iso:country":"AU",
    "sg:address":"55 Hunter St",
    "sg:city":"Hornsby",
    "sg:classifiers":[
        {
            "category":"Home & Garden",
            "subcategory":"Hardware",
            "type":"Retail Goods"
        }
    ],
    "sg:phone":"+61 2 9477 1555",
    "sg:postcode":"2077",
    "sg:province":"NSW",
    "sg:tags":[
        "generating",
        "set",
        "generator"
    ],
    "sg:website":"http://www.australianpowerequipment.com.au",
    "wof:name":"Australian Power Equipment",
    "wof:placetype":"venue"
},
  "geometry": {"coordinates":[151.100875855,-33.7017326355],"type":"Point"}
}