{
  "type": "Feature",
  "properties": {
    "addr:full":"6 Curlew Crs Woodberry NSW 2322",
    "addr:housenumber":"6",
    "addr:postcode":"2322",
    "addr:street":"Curlew Crs",
    "iso:country":"AU",
    "sg:address":"6 Curlew Crs",
    "sg:city":"Woodberry",
    "sg:classifiers":[
        {
            "category":"Education",
            "subcategory":"Dance Studio",
            "type":"Public Place"
        }
    ],
    "sg:phone":"+61 419 482 665",
    "sg:postcode":"2322",
    "sg:province":"NSW",
    "sg:tags":[
        "venue",
        "tuition"
    ],
    "wof:name":"M & J's All that Jazz",
    "wof:placetype":"venue"
},
  "geometry": {"coordinates":[151.67132568400001,-32.7913017273],"type":"Point"}
}