{
  "type": "Feature",
  "properties": {
    "addr:full":"104 Elizabeth Drv Liverpool NSW 2170",
    "addr:housenumber":"104",
    "addr:postcode":"2170",
    "addr:street":"Elizabeth Drv",
    "iso:country":"AU",
    "sg:address":"104 Elizabeth Drv",
    "sg:city":"Liverpool",
    "sg:classifiers":[
        {
            "category":"Retail",
            "subcategory":"Auto Repair",
            "type":"Services"
        }
    ],
    "sg:phone":"+61 2 9602 3913",
    "sg:postcode":"2170",
    "sg:province":"NSW",
    "sg:tags":[
        "beater",
        "painter",
        "panel"
    ],
    "wof:name":"Elizabeth Drive Smash Repairs Pty Ltd",
    "wof:placetype":"venue"
},
  "geometry": {"coordinates":[150.91317749000001,-33.9182014465],"type":"Point"}
}