{
  "type": "Feature",
  "properties": {
    "addr:full":"104 Edney Rd High Wycombe WA 6057",
    "addr:housenumber":"104",
    "addr:postcode":"6057",
    "addr:street":"Edney Rd",
    "iso:country":"AU",
    "sg:address":"104 Edney Rd",
    "sg:city":"High Wycombe",
    "sg:classifiers":[
        {
            "category":"Social Services",
            "subcategory":"Child Care",
            "type":"Services"
        }
    ],
    "sg:phone":"+61 8 9454 8090",
    "sg:postcode":"6057",
    "sg:province":"WA",
    "wof:name":"High Wycombe Out Of School Care Centre Incorporated",
    "wof:placetype":"venue"
},
  "geometry": {"coordinates":[116.008743286,-31.9473190308],"type":"Point"}
}