{
  "type": "Feature",
  "properties": {
    "addr:full":"Suite 8 / 134 King St Newtown NSW 2042",
    "addr:housenumber":"/ 134",
    "addr:postcode":"2042",
    "addr:street":"King St",
    "iso:country":"AU",
    "sg:address":"Suite 8 / 134 King St",
    "sg:city":"Newtown",
    "sg:classifiers":[
        {
            "category":"Health Services",
            "subcategory":"Health Practitioner",
            "type":"Services"
        }
    ],
    "sg:phone":"+61 2 9516 4399",
    "sg:postcode":"2042",
    "sg:province":"NSW",
    "sg:tags":[
        "homoeopath"
    ],
    "wof:name":"Baruch Vivian",
    "wof:placetype":"venue"
},
  "geometry": {"coordinates":[151.18377699999999,-33.893501],"type":"Point"}
}