{
  "type": "Feature",
  "properties": {
    "iso:country":"AU",
    "sg:address":"PO Box 34",
    "sg:city":"Peakhurst",
    "sg:classifiers":[
        {
            "category":"Building & Trades",
            "subcategory":"Landscaping Services",
            "type":"Services"
        }
    ],
    "sg:phone":"+61 2 9596 1611",
    "sg:postcode":"2210",
    "sg:province":"NSW",
    "sg:tags":[
        "gardener"
    ],
    "wof:name":"Gold Medal Lawn & Garden Landscape Specialists",
    "wof:placetype":"venue"
},
  "geometry": {"coordinates":[151.05807495100001,-33.9625396729],"type":"Point"}
}