{
  "type": "Feature",
  "properties": {
    "addr:full":"104 Crown St Woolloomooloo NSW 2011",
    "addr:housenumber":"104",
    "addr:postcode":"2011",
    "addr:street":"Crown St",
    "iso:country":"AU",
    "sg:address":"104 Crown St",
    "sg:city":"Woolloomooloo",
    "sg:classifiers":[
        {
            "category":"Personal",
            "subcategory":"Adult",
            "type":"Services"
        }
    ],
    "sg:phone":"+61 2 9360 3366",
    "sg:postcode":"2011",
    "sg:province":"NSW",
    "sg:tags":[
        "vic",
        "except",
        "state",
        "escort",
        "social",
        "qld"
    ],
    "wof:name":"Bliss Erotic Massage",
    "wof:placetype":"venue"
},
  "geometry": {"coordinates":[151.21661376899999,-33.8736953735],"type":"Point"}
}