{
  "type": "Feature",
  "properties": {
    "iso:country":"AU",
    "sg:address":"16 Vivian St",
    "sg:city":"Boulder",
    "sg:classifiers":[
        {
            "category":"Manufacturing",
            "subcategory":"Metals",
            "type":"Manufacturing & Wholesale Goods"
        }
    ],
    "sg:phone":"+61 8 9093 3800",
    "sg:postcode":"6432",
    "sg:province":"WA",
    "sg:tags":[
        "steel",
        "fabricator",
        "mfrs"
    ],
    "wof:name":"Goldfields Metal Industries",
    "wof:placetype":"venue"
},
  "geometry": {"coordinates":[121.497947693,-30.7905540466],"type":"Point"}
}