{
  "type": "Feature",
  "properties": {
    "addr:full":"2 Milner Rd Alice Springs NT 0870",
    "addr:housenumber":"2",
    "addr:postcode":"nt 0870",
    "addr:street":"Milner Rd",
    "iso:country":"AU",
    "sg:address":"2 Milner Rd",
    "sg:city":"Alice Springs",
    "sg:classifiers":[
        {
            "category":"Commercial Area",
            "type":"Public Place"
        }
    ],
    "sg:phone":"+61 418 380 684",
    "sg:postcode":"0870",
    "sg:province":"NT",
    "sg:tags":[
        "heavy",
        "carrier"
    ],
    "wof:name":"Talbots",
    "wof:placetype":"venue"
},
  "geometry": {"coordinates":[133.86895751899999,-23.6998634338],"type":"Point"}
}