{
  "type": "Feature",
  "properties": {
    "addr:full":"292a Bridge Rd Richmond VIC 3121",
    "addr:housenumber":"292a",
    "addr:postcode":"3121",
    "addr:street":"Bridge Rd",
    "iso:country":"AU",
    "sg:address":"292a Bridge Rd",
    "sg:city":"Richmond",
    "sg:classifiers":[
        {
            "category":"Personal",
            "subcategory":"Beauty Salon",
            "type":"Services"
        }
    ],
    "sg:phone":"+61 3 9421 3100",
    "sg:postcode":"3121",
    "sg:province":"VIC",
    "sg:tags":[
        "hairdresser"
    ],
    "wof:name":"Frisk Hair Cutters",
    "wof:placetype":"venue"
},
  "geometry": {"coordinates":[145.00097656200001,-37.8188591003],"type":"Point"}
}