{
  "type": "Feature",
  "properties": {
    "addr:full":"Shop 3 108 Royal St East Perth WA 6004",
    "addr:housenumber":"shop 3 108",
    "addr:postcode":"6004",
    "addr:street":"Royal St East",
    "iso:country":"AU",
    "sg:address":"Shop 3 108 Royal St",
    "sg:city":"East Perth",
    "sg:classifiers":[
        {
            "category":"Real Estate",
            "subcategory":"Real Estate Agent",
            "type":"Services"
        }
    ],
    "sg:phone":"+61 8 9325 3555",
    "sg:postcode":"6004",
    "sg:province":"WA",
    "wof:name":"Centrepoint Realty",
    "wof:placetype":"venue"
},
  "geometry": {"coordinates":[115.87551116900001,-31.9529037476],"type":"Point"}
}