{
  "type": "Feature",
  "properties": {
    "iso:country":"AU",
    "sg:address":"19 Exeter St",
    "sg:city":"Torquay",
    "sg:classifiers":[
        {
            "category":"Health Services",
            "subcategory":"Health Practitioner",
            "type":"Services"
        }
    ],
    "sg:phone":"+61 7 4125 1231",
    "sg:postcode":"4655",
    "sg:province":"QLD",
    "sg:tags":[
        "homoeopath"
    ],
    "sg:website":"http://www.atms.com.au",
    "wof:name":"Health Solutions",
    "wof:placetype":"venue"
},
  "geometry": {"coordinates":[152.861176,-25.293346],"type":"Point"}
}