{
  "type": "Feature",
  "properties": {
    "addr:full":"PO Box 226 Narangba QLD 4504",
    "addr:postcode":"4504",
    "iso:country":"AU",
    "sg:address":"PO Box 226",
    "sg:city":"Narangba",
    "sg:classifiers":[
        {
            "category":"Building & Trades",
            "subcategory":"Construction",
            "type":"Services"
        }
    ],
    "sg:phone":"+61 414 572 382",
    "sg:postcode":"4504",
    "sg:province":"QLD",
    "sg:tags":[
        "contractor"
    ],
    "wof:name":"Komodo Construction",
    "wof:placetype":"venue"
},
  "geometry": {"coordinates":[152.92854309099999,-27.1869602203],"type":"Point"}
}