{
  "type": "Feature",
  "properties": {
    "iso:country":"AU",
    "sg:address":"PO Box 3313",
    "sg:city":"Bracken Ridge",
    "sg:classifiers":[
        {
            "category":"Building & Trades",
            "subcategory":"Pest Control",
            "type":"Services"
        }
    ],
    "sg:phone":"+61 7 3269 4939",
    "sg:postcode":"4017",
    "sg:province":"QLD",
    "wof:name":"Complete Pest Control",
    "wof:placetype":"venue"
},
  "geometry": {"coordinates":[153.035614014,-27.3143539429],"type":"Point"}
}