{
  "type": "Feature",
  "properties": {
    "addr:full":"2 Greenhills Drv Melton VIC 3337",
    "addr:housenumber":"2",
    "addr:postcode":"3337",
    "addr:street":"Greenhills Drv",
    "iso:country":"AU",
    "sg:address":"2 Greenhills Drv",
    "sg:city":"Melton",
    "sg:classifiers":[
        {
            "category":"Personal",
            "subcategory":"Beauty Salon",
            "type":"Services"
        }
    ],
    "sg:phone":"+61 3 9743 7809",
    "sg:postcode":"3337",
    "sg:province":"VIC",
    "sg:tags":[
        "hairdresser"
    ],
    "wof:name":"ANA Styles",
    "wof:placetype":"venue"
},
  "geometry": {"coordinates":[144.57531700000001,-37.672516],"type":"Point"}
}