{
  "type": "Feature",
  "properties": {
    "iso:country":"AU",
    "sg:address":"Pt Kembla Coal Terminal North Admin Bldg Inner Harbour, Port Kembla Rd",
    "sg:city":"Wollongong",
    "sg:classifiers":[
        {
            "category":"Transit Center",
            "subcategory":"Freight",
            "type":"Transportation"
        }
    ],
    "sg:phone":"+61 2 4225 9884",
    "sg:postcode":"2500",
    "sg:province":"NSW",
    "sg:tags":[
        "agent",
        "shipping"
    ],
    "wof:name":"Adsteam Agency Pty Limited",
    "wof:placetype":"venue"
},
  "geometry": {"coordinates":[150.896805,-34.437881],"type":"Point"}
}