{
  "type": "Feature",
  "properties": {
    "iso:country":"AU",
    "sg:address":"131 Bridge Rd",
    "sg:city":"Eastwood",
    "sg:classifiers":[
        {
            "category":"Home & Garden",
            "subcategory":"Carpets & Floor Coverings",
            "type":"Retail Goods"
        }
    ],
    "sg:phone":"+61 2 9888 2133",
    "sg:postcode":"2122",
    "sg:province":"NSW",
    "sg:tags":[
        "tile",
        "wall",
        "layer"
    ],
    "wof:name":"Mirenzi G",
    "wof:placetype":"venue"
},
  "geometry": {"coordinates":[151.10455322300001,-33.7902145386],"type":"Point"}
}