{
  "type": "Feature",
  "properties": {
    "iso:country":"AU",
    "sg:address":"28 Queen St",
    "sg:city":"Bellerive",
    "sg:classifiers":[
        {
            "category":"Utilities",
            "subcategory":"Electric",
            "type":"Services"
        }
    ],
    "sg:phone":"+61 3 6244 5051",
    "sg:postcode":"7018",
    "sg:province":"TAS",
    "sg:tags":[
        "electrical",
        "contractor"
    ],
    "wof:name":"Bryce Electrical",
    "wof:placetype":"venue"
},
  "geometry": {"coordinates":[147.36915588400001,-42.8768196106],"type":"Point"}
}