{
  "type": "Feature",
  "properties": {
    "addr:full":"236 Clarence St Sydney NSW 2000",
    "addr:housenumber":"236",
    "addr:postcode":"2000",
    "addr:street":"Clarence St",
    "iso:country":"AU",
    "sg:address":"236 Clarence St",
    "sg:city":"Sydney",
    "sg:classifiers":[
        {
            "category":"Professional",
            "subcategory":"Employment Agencies",
            "type":"Services"
        }
    ],
    "sg:phone":"+61 2 9261 5666",
    "sg:postcode":"2000",
    "sg:province":"NSW",
    "sg:tags":[
        "provider",
        "internet"
    ],
    "wof:name":"Webdesigning.com.au",
    "wof:placetype":"venue"
},
  "geometry": {"coordinates":[151.20587158199999,-33.8726844788],"type":"Point"}
}