{
  "type": "Feature",
  "properties": {
    "addr:full":"Shop 151, Crown St Mall Next to National Bank Wollongong NSW 2500",
    "addr:housenumber":"151",
    "addr:postcode":"2500",
    "addr:street":"Crown St Mall Next",
    "iso:country":"AU",
    "sg:address":"Shop 151, Crown St",
    "sg:city":"Mall Next to National Bank Wollongong",
    "sg:classifiers":[
        {
            "category":"Food & Beverages",
            "subcategory":"Specialty",
            "type":"Retail Goods"
        }
    ],
    "sg:phone":"+61 2 4229 1142",
    "sg:postcode":"2500",
    "sg:province":"NSW",
    "sg:tags":[
        "product",
        "health"
    ],
    "wof:name":"HSC Health & Sports Centre",
    "wof:placetype":"venue"
},
  "geometry": {"coordinates":[150.89527899999999,-34.425335],"type":"Point"}
}