{
  "type": "Feature",
  "properties": {
    "addr:full":"PO Box 136 Ashgrove QLD 4060",
    "addr:postcode":"4060",
    "iso:country":"AU",
    "sg:address":"PO Box 136",
    "sg:city":"Ashgrove",
    "sg:classifiers":[
        {
            "category":"Mining & Drilling",
            "type":"Manufacturing & Wholesale Goods"
        }
    ],
    "sg:phone":"+61 410 268 703",
    "sg:postcode":"4060",
    "sg:province":"QLD",
    "sg:tags":[
        "concrete",
        "breaking",
        "grinding",
        "sawing"
    ],
    "wof:name":"Prompt Concrete Cutting & Core Drilling",
    "wof:placetype":"venue"
},
  "geometry": {"coordinates":[152.99197387699999,-27.4456806183],"type":"Point"}
}