{
  "type": "Feature",
  "properties": {
    "addr:full":"27 Second Ave Maroochydore QLD 4558",
    "addr:housenumber":"27",
    "addr:postcode":"4558",
    "addr:street":"Second Ave",
    "iso:country":"AU",
    "sg:address":"27 Second Ave",
    "sg:city":"Maroochydore",
    "sg:classifiers":[
        {
            "category":"Health Services",
            "subcategory":"Dentist",
            "type":"Services"
        }
    ],
    "sg:phone":"+61 7 5479 5522",
    "sg:postcode":"4558",
    "sg:province":"QLD",
    "wof:name":"Ellis Callum",
    "wof:placetype":"venue"
},
  "geometry": {"coordinates":[153.09552001899999,-26.6570014954],"type":"Point"}
}