{
  "type": "Feature",
  "properties": {
    "addr:full":"U6/ 55 Collinsvale St Rocklea QLD 4106",
    "addr:postcode":"4106",
    "addr:street":"U6 / 55 Collinsvale St",
    "iso:country":"AU",
    "sg:address":"U6/ 55 Collinsvale St",
    "sg:city":"Rocklea",
    "sg:classifiers":[
        {
            "category":"Building & Trades",
            "subcategory":"Plumbing",
            "type":"Services"
        }
    ],
    "sg:phone":"+61 7 3255 6910",
    "sg:postcode":"4106",
    "sg:province":"QLD",
    "sg:tags":[
        "equipment",
        "valves"
    ],
    "wof:name":"DB Valve & Industrial Pty Ltd",
    "wof:placetype":"venue"
},
  "geometry": {"coordinates":[152.994903564,-27.5594100952],"type":"Point"}
}