{
  "type": "Feature",
  "properties": {
    "addr:full":"Lvl 1/ 43-51 Cowper Wharf Rd Woolloomooloo NSW 2011",
    "addr:housenumber":"/ 43-51",
    "addr:postcode":"2011",
    "addr:street":"Cowper Wharf Rd",
    "iso:country":"AU",
    "sg:address":"Lvl 1/ 43-51 Cowper Wharf Rd",
    "sg:city":"Woolloomooloo",
    "sg:classifiers":[
        {
            "category":"Education",
            "subcategory":"University",
            "type":"Public Place"
        }
    ],
    "sg:phone":"+61 2 9368 1900",
    "sg:postcode":"2011",
    "sg:province":"NSW",
    "sg:tags":[
        "educational",
        "organisation",
        "cultural"
    ],
    "wof:name":"National Association For The Visual Arts(NAVA)",
    "wof:placetype":"venue"
},
  "geometry": {"coordinates":[151.21868896500001,-33.8686294556],"type":"Point"}
}