{
  "type": "Feature",
  "properties": {
    "addr:full":"1364 Gympie Rd Aspley QLD 4034",
    "addr:housenumber":"1364",
    "addr:postcode":"4034",
    "addr:street":"Gympie Rd",
    "iso:country":"AU",
    "sg:address":"1364 Gympie Rd",
    "sg:city":"Aspley",
    "sg:classifiers":[
        {
            "category":"Fast Food",
            "type":"Food & Drink"
        }
    ],
    "sg:phone":"+61 7 3862 7733",
    "sg:postcode":"4034",
    "sg:province":"QLD",
    "sg:tags":[
        "away",
        "take"
    ],
    "wof:name":"McDonald's Family Restaurants",
    "wof:placetype":"venue"
},
  "geometry": {"coordinates":[153.016876,-27.362814],"type":"Point"}
}