{
  "type": "Feature",
  "properties": {
    "addr:full":"Shop 5 & 6 Fountain Plaza, Nish St Echuca VIC 3564",
    "addr:housenumber":"shop 5 & 6",
    "addr:postcode":"3564",
    "addr:street":"Fountain Plaza Nish St",
    "iso:country":"AU",
    "sg:address":"Shop 5 & 6 Fountain Plaza, Nish St",
    "sg:city":"Echuca",
    "sg:classifiers":[
        {
            "category":"Ice Cream",
            "type":"Food & Drink"
        }
    ],
    "sg:phone":"+61 3 5482 1261",
    "sg:postcode":"3564",
    "sg:province":"VIC",
    "sg:tags":[
        "specialised",
        "fitting",
        "lady",
        "wear"
    ],
    "wof:name":"Supa Gals Fashions",
    "wof:placetype":"venue"
},
  "geometry": {"coordinates":[144.751052856,-36.1292190552],"type":"Point"}
}