{
  "type": "Feature",
  "properties": {
    "addr:full":"1/ 24 Artisan Rd Seven Hills NSW 2147",
    "addr:housenumber":"/ 24",
    "addr:postcode":"2147",
    "addr:street":"Artisan Rd",
    "iso:country":"AU",
    "sg:address":"1/ 24 Artisan Rd",
    "sg:city":"Seven Hills",
    "sg:classifiers":[
        {
            "category":"Home & Garden",
            "subcategory":"Building Materials",
            "type":"Retail Goods"
        }
    ],
    "sg:phone":"+61 2 8916 6407",
    "sg:postcode":"2147",
    "sg:province":"NSW",
    "sg:tags":[
        "balustrading"
    ],
    "sg:website":"http://www.stainlesssteeldesigns.com",
    "wof:name":"Stainless Steel Designs",
    "wof:placetype":"venue"
},
  "geometry": {"coordinates":[150.960494995,-33.7753295898],"type":"Point"}
}