{
  "type": "Feature",
  "properties": {
    "addr:full":"279 Hunter St Newcastle NSW 2300",
    "addr:housenumber":"279",
    "addr:postcode":"2300",
    "addr:street":"Hunter St",
    "iso:country":"AU",
    "sg:address":"279 Hunter St",
    "sg:city":"Newcastle",
    "sg:classifiers":[
        {
            "category":"Shopping",
            "subcategory":"Clothing, Apparel, & Fashions",
            "type":"Retail Goods"
        }
    ],
    "sg:phone":"+61 2 4927 1117",
    "sg:postcode":"2300",
    "sg:province":"NSW",
    "sg:tags":[
        "lady",
        "wear"
    ],
    "wof:name":"Captain Saucy",
    "wof:placetype":"venue"
},
  "geometry": {"coordinates":[151.77600100000001,-32.926704],"type":"Point"}
}