{
  "type": "Feature",
  "properties": {
    "addr:full":"Unit 31/ 47 Crompton Rd Rockingham WA 6168",
    "addr:housenumber":"/ 47",
    "addr:postcode":"6168",
    "addr:street":"Crompton Rd",
    "iso:country":"AU",
    "sg:address":"Unit 31/ 47 Crompton Rd",
    "sg:city":"Rockingham",
    "sg:classifiers":[
        {
            "category":"Building & Trades",
            "subcategory":"Construction",
            "type":"Services"
        }
    ],
    "sg:phone":"+61 414 548 998",
    "sg:postcode":"6168",
    "sg:province":"WA",
    "sg:tags":[
        "monumental",
        "mason"
    ],
    "wof:name":"Asuns The Masons",
    "wof:placetype":"venue"
},
  "geometry": {"coordinates":[115.76641100000001,-32.274837],"type":"Point"}
}