{
  "type": "Feature",
  "properties": {
    "iso:country":"AU",
    "sg:address":"55 Lavender St",
    "sg:city":"Milsons Point",
    "sg:classifiers":[
        {
            "category":"Banks & Credit Unions",
            "subcategory":"Financial Services",
            "type":"Services"
        }
    ],
    "sg:phone":"+61 2 9934 1234",
    "sg:postcode":"2061",
    "sg:province":"NSW",
    "sg:tags":[
        "financier"
    ],
    "wof:name":"Hino Financial Services",
    "wof:placetype":"venue"
},
  "geometry": {"coordinates":[151.20970153799999,-33.8435440063],"type":"Point"}
}