{
  "type": "Feature",
  "properties": {
    "iso:country":"AU",
    "sg:address":"91 Rostrevor Pde",
    "sg:city":"Box Hill North",
    "sg:classifiers":[
        {
            "category":"Professional",
            "subcategory":"Secretarial Services",
            "type":"Services"
        }
    ],
    "sg:phone":"+61 419 570 753",
    "sg:postcode":"3129",
    "sg:province":"VIC",
    "sg:tags":[
        "typing"
    ],
    "wof:name":"E H M Secretarial Services",
    "wof:placetype":"venue"
},
  "geometry": {"coordinates":[145.10760498100001,-37.8043289185],"type":"Point"}
}