{
  "type": "Feature",
  "properties": {
    "iso:country":"AU",
    "sg:address":"35- 37 Lakeside Drv",
    "sg:city":"Broadmeadows",
    "sg:classifiers":[
        {
            "category":"Building & Trades",
            "subcategory":"Construction",
            "type":"Services"
        }
    ],
    "sg:phone":"+61 3 9357 2515",
    "sg:postcode":"3047",
    "sg:province":"VIC",
    "sg:tags":[
        "roof"
    ],
    "wof:name":"Cruise-Pro Group Pty Ltd",
    "wof:placetype":"venue"
},
  "geometry": {"coordinates":[144.94757080100001,-37.6863098145],"type":"Point"}
}