{
  "type": "Feature",
  "properties": {
    "addr:full":"PO Box 7098 Toowoomba Mail Centre QLD 4352",
    "addr:postcode":"4352",
    "iso:country":"AU",
    "sg:address":"PO Box 7098",
    "sg:city":"Toowoomba Mail Centre",
    "sg:classifiers":[
        {
            "category":"Professional",
            "type":"Services"
        }
    ],
    "sg:phone":"+61 7 4634 8925",
    "sg:postcode":"4352",
    "sg:province":"QLD",
    "sg:tags":[
        "coating",
        "powder"
    ],
    "wof:name":"Garden City Powdercoating & Sandblasting",
    "wof:placetype":"venue"
},
  "geometry": {"coordinates":[151.59376499999999,-28.363979],"type":"Point"}
}