{
  "type": "Feature",
  "properties": {
    "iso:country":"AU",
    "sg:address":"935 Stanley St",
    "sg:city":"East Brisbane",
    "sg:classifiers":[
        {
            "category":"Shopping",
            "subcategory":"Shoes",
            "type":"Retail Goods"
        }
    ],
    "sg:phone":"+61 7 3891 2466",
    "sg:postcode":"4169",
    "sg:province":"QLD",
    "sg:tags":[
        "footwear"
    ],
    "wof:name":"Aries The Sheepskin Specialist",
    "wof:placetype":"venue"
},
  "geometry": {"coordinates":[153.04425048799999,-27.4879512787],"type":"Point"}
}