{
  "type": "Feature",
  "properties": {
    "addr:full":"168 Wharf St Spring Hill QLD 4000",
    "addr:housenumber":"168",
    "addr:postcode":"4000",
    "addr:street":"Wharf St",
    "iso:country":"AU",
    "sg:address":"168 Wharf St",
    "sg:city":"Spring Hill",
    "sg:classifiers":[
        {
            "category":"Sports & Exercise",
            "subcategory":"Gym",
            "type":"Entertainment"
        }
    ],
    "sg:phone":"+61 7 3839 5522",
    "sg:postcode":"4000",
    "sg:province":"QLD",
    "sg:tags":[
        "personal",
        "trainer",
        "fitness"
    ],
    "wof:name":"Next Generation Express Fitness",
    "wof:placetype":"venue"
},
  "geometry": {"coordinates":[153.027053833,-27.4625587463],"type":"Point"}
}