{
  "type": "Feature",
  "properties": {
    "addr:full":"Lvl 8, 16 Rundle St Adelaide SA 5000",
    "addr:housenumber":"16",
    "addr:postcode":"5000",
    "addr:street":"Rundle St",
    "iso:country":"AU",
    "sg:address":"Lvl 8, 16 Rundle St",
    "sg:city":"Adelaide",
    "sg:classifiers":[
        {
            "category":"Utilities",
            "subcategory":"Telephone",
            "type":"Services"
        }
    ],
    "sg:phone":"+61 1300 650 238",
    "sg:postcode":"5000",
    "sg:province":"SA",
    "wof:name":"Green Communications Ltd",
    "wof:placetype":"venue"
},
  "geometry": {"coordinates":[138.60980224599999,-34.922328949],"type":"Point"}
}