{
  "type": "Feature",
  "properties": {
    "addr:full":"PO Box 166 Scarborough QLD 4020",
    "addr:postcode":"4020",
    "iso:country":"AU",
    "sg:address":"PO Box 166",
    "sg:city":"Scarborough",
    "sg:classifiers":[
        {
            "category":"Recreation",
            "subcategory":"Fishing",
            "type":"Entertainment"
        }
    ],
    "sg:phone":"+61 7 3880 3312",
    "sg:postcode":"4020",
    "sg:province":"QLD",
    "sg:tags":[
        "trip"
    ],
    "wof:name":"Bribie Island Charters",
    "wof:placetype":"venue"
},
  "geometry": {"coordinates":[153.114014,-27.20532],"type":"Point"}
}