{
  "type": "Feature",
  "properties": {
    "addr:full":"2 Snapper Rocks Rd Coolangatta QLD 4225",
    "addr:housenumber":"2",
    "addr:postcode":"4225",
    "addr:street":"Snapper Rocks Rd",
    "iso:country":"AU",
    "sg:address":"2 Snapper Rocks Rd",
    "sg:city":"Coolangatta",
    "sg:classifiers":[
        {
            "category":"Retail",
            "subcategory":"Event Space",
            "type":"Services"
        }
    ],
    "sg:phone":"+61 7 5599 4866",
    "sg:postcode":"4225",
    "sg:province":"QLD",
    "sg:tags":[
        "function",
        "organiser"
    ],
    "wof:name":"Rainbow On The Beach",
    "wof:placetype":"venue"
},
  "geometry": {"coordinates":[153.548736572,-28.1631946564],"type":"Point"}
}