{
  "type": "Feature",
  "properties": {
    "addr:full":"44 Beaumont St Hamilton NSW 2303",
    "addr:housenumber":"44",
    "addr:postcode":"2303",
    "addr:street":"Beaumont St",
    "iso:country":"AU",
    "sg:address":"44 Beaumont St",
    "sg:city":"Hamilton",
    "sg:classifiers":[
        {
            "category":"Cafe",
            "type":"Food & Drink"
        }
    ],
    "sg:phone":"+61 2 4969 8900",
    "sg:postcode":"2303",
    "sg:province":"NSW",
    "wof:name":"Caffe Giannotti",
    "wof:placetype":"venue"
},
  "geometry": {"coordinates":[151.74728400000001,-32.921364],"type":"Point"}
}