{
  "type": "Feature",
  "properties": {
    "iso:country":"AU",
    "sg:address":"637 Fifteenth St",
    "sg:city":"Mildura",
    "sg:classifiers":[
        {
            "category":"Wholesale",
            "subcategory":"Machinery & Supplies",
            "type":"Manufacturing & Wholesale Goods"
        }
    ],
    "sg:phone":"+61 3 5022 2840",
    "sg:postcode":"3500",
    "sg:province":"VIC",
    "sg:tags":[
        "engine",
        "petrol"
    ],
    "wof:name":"Stihl Shop Mildura",
    "wof:placetype":"venue"
},
  "geometry": {"coordinates":[142.1512146,-34.2186393738],"type":"Point"}
}