{
  "type": "Feature",
  "properties": {
    "iso:country":"AU",
    "sg:address":"Mary Mackillop Centre, Avoca Drv",
    "sg:city":"Kincumber",
    "sg:classifiers":[
        {
            "category":"Health Services",
            "subcategory":"Doctor",
            "type":"Services"
        }
    ],
    "sg:phone":"+61 2 4369 4485",
    "sg:postcode":"2251",
    "sg:province":"NSW",
    "sg:tags":[
        "medical",
        "practitioner"
    ],
    "wof:name":"Mayne Laverty Pathology Collection Centres",
    "wof:placetype":"venue"
},
  "geometry": {"coordinates":[151.381515503,-33.4676437378],"type":"Point"}
}