{
  "type": "Feature",
  "properties": {
    "addr:full":"Millstream Rd Karratha WA 6714",
    "addr:postcode":"6714",
    "addr:street":"Millstream Rd",
    "iso:country":"AU",
    "sg:address":"Millstream Rd",
    "sg:city":"Karratha",
    "sg:classifiers":[
        {
            "category":"Travel",
            "subcategory":"Hotels & Motels",
            "type":"Entertainment"
        }
    ],
    "sg:phone":"+61 8 9185 3111",
    "sg:postcode":"6714",
    "sg:province":"WA",
    "wof:name":"Karratha International Hotel",
    "wof:placetype":"venue"
},
  "geometry": {"coordinates":[116.84954834,-20.7377128601],"type":"Point"}
}