{
  "type": "Feature",
  "properties": {
    "iso:country":"AU",
    "sg:address":"18 Denham St",
    "sg:city":"Annerley",
    "sg:classifiers":[
        {
            "category":"Government",
            "subcategory":"Post Office",
            "type":"Public Place"
        }
    ],
    "sg:phone":"+61 7 3895 8395",
    "sg:postcode":"4103",
    "sg:province":"QLD",
    "sg:tags":[
        "yoga"
    ],
    "wof:name":"Annerley Yoga and Health Practices",
    "wof:placetype":"venue"
},
  "geometry": {"coordinates":[153.03106689399999,-27.5064983368],"type":"Point"}
}