{
  "type": "Feature",
  "properties": {
    "addr:full":"10 Jerilderie St Jerilderie NSW 2716",
    "addr:housenumber":"10",
    "addr:postcode":"2716",
    "addr:street":"Jerilderie St",
    "iso:country":"AU",
    "sg:address":"10 Jerilderie St",
    "sg:city":"Jerilderie",
    "sg:classifiers":[
        {
            "category":"Retail",
            "subcategory":"Repair Shop",
            "type":"Services"
        }
    ],
    "sg:phone":"+61 3 5886 1750",
    "sg:postcode":"2716",
    "sg:province":"NSW",
    "sg:tags":[
        "upholsterer"
    ],
    "wof:name":"Sneddon Ian Canvas & Upholstery",
    "wof:placetype":"venue"
},
  "geometry": {"coordinates":[145.74464416500001,-35.3600158691],"type":"Point"}
}