{
  "type": "Feature",
  "properties": {
    "addr:full":"198 Hartley St Cairns QLD 4870",
    "addr:housenumber":"198",
    "addr:postcode":"4870",
    "addr:street":"Hartley St",
    "iso:country":"AU",
    "sg:address":"198 Hartley St",
    "sg:city":"Cairns",
    "sg:classifiers":[
        {
            "category":"Home & Garden",
            "subcategory":"Hardware",
            "type":"Retail Goods"
        }
    ],
    "sg:phone":"+61 7 4035 2746",
    "sg:postcode":"4870",
    "sg:province":"QLD",
    "sg:tags":[
        "generating",
        "set",
        "generator"
    ],
    "wof:name":"KAC Generation & Mechanical Pty Ltd",
    "wof:placetype":"venue"
},
  "geometry": {"coordinates":[145.76223754899999,-16.9390926361],"type":"Point"}
}