{
  "type": "Feature",
  "properties": {
    "addr:full":"76 Deccan St Goulburn NSW 2580",
    "addr:housenumber":"76",
    "addr:postcode":"2580",
    "addr:street":"Deccan St",
    "iso:country":"AU",
    "sg:address":"76 Deccan St",
    "sg:city":"Goulburn",
    "sg:classifiers":[
        {
            "category":"Banks & Credit Unions",
            "subcategory":"Bank",
            "type":"Services"
        }
    ],
    "sg:phone":"+61 2 4822 7835",
    "sg:postcode":"2580",
    "sg:province":"NSW",
    "sg:tags":[
        "broker",
        "mortgage"
    ],
    "wof:name":"ProMortgage",
    "wof:placetype":"venue"
},
  "geometry": {"coordinates":[149.70724487300001,-34.7493476868],"type":"Point"}
}