{
  "type": "Feature",
  "properties": {
    "addr:full":"367 Horsley Rd Milperra NSW 2214",
    "addr:housenumber":"367",
    "addr:postcode":"2214",
    "addr:street":"Horsley Rd",
    "iso:country":"AU",
    "sg:address":"367 Horsley Rd",
    "sg:city":"Milperra",
    "sg:classifiers":[
        {
            "category":"Shopping",
            "subcategory":"Crafts & Fabrics",
            "type":"Retail Goods"
        }
    ],
    "sg:phone":"+61 2 9792 7859",
    "sg:postcode":"2214",
    "sg:province":"NSW",
    "sg:tags":[
        "supply"
    ],
    "wof:name":"Pots Plus",
    "wof:placetype":"venue"
},
  "geometry": {"coordinates":[150.99453700000001,-33.938721],"type":"Point"}
}