{
  "type": "Feature",
  "properties": {
    "addr:full":"5/ 134 Le Souef Drv Kardinya WA 6163",
    "addr:housenumber":"/ 134",
    "addr:postcode":"6163",
    "addr:street":"Le Souef Drv",
    "iso:country":"AU",
    "sg:address":"5/ 134 Le Souef Drv",
    "sg:city":"Kardinya",
    "sg:classifiers":[
        {
            "category":"Real Estate",
            "subcategory":"Real Estate Agent",
            "type":"Services"
        }
    ],
    "sg:phone":"+61 8 9337 6484",
    "sg:postcode":"6163",
    "sg:province":"WA",
    "wof:name":"Roy Weston First Choice Kardinya",
    "wof:placetype":"venue"
},
  "geometry": {"coordinates":[115.811279,-32.060146],"type":"Point"}
}