{
  "type": "Feature",
  "properties": {
    "addr:full":"217 Chapel St Prahran VIC 3181",
    "addr:housenumber":"217",
    "addr:postcode":"3181",
    "addr:street":"Chapel St",
    "iso:country":"AU",
    "sg:address":"217 Chapel St",
    "sg:city":"Prahran",
    "sg:classifiers":[
        {
            "category":"Shopping",
            "subcategory":"Shoes",
            "type":"Retail Goods"
        }
    ],
    "sg:phone":"+61 3 9510 2258",
    "sg:postcode":"3181",
    "sg:province":"VIC",
    "sg:tags":[
        "footwear"
    ],
    "wof:name":"Papucci",
    "wof:placetype":"venue"
},
  "geometry": {"coordinates":[144.99336242699999,-37.8507614136],"type":"Point"}
}