{
  "type": "Feature",
  "properties": {
    "addr:full":"22 Asher Crt null QLD 4210",
    "addr:housenumber":"22",
    "addr:postcode":"4210",
    "addr:street":"Asher Crt",
    "iso:country":"AU",
    "sg:address":"22 Asher Crt",
    "sg:city":"null",
    "sg:classifiers":[
        {
            "category":"Home & Garden",
            "subcategory":"Building Materials",
            "type":"Retail Goods"
        }
    ],
    "sg:phone":"+61 7 5573 1100",
    "sg:postcode":"4210",
    "sg:province":"QLD",
    "sg:tags":[
        "merchant",
        "glass",
        "glazier"
    ],
    "wof:name":"I & H Contract-Fixing",
    "wof:placetype":"venue"
},
  "geometry": {"coordinates":[153.267089844,-27.9027233124],"type":"Point"}
}