{
  "type": "Feature",
  "properties": {
    "addr:full":"117 Durham Rd Sunshine VIC 3020",
    "addr:housenumber":"117",
    "addr:postcode":"3020",
    "addr:street":"Durham Rd",
    "iso:country":"AU",
    "sg:address":"117 Durham Rd",
    "sg:city":"Sunshine",
    "sg:classifiers":[
        {
            "category":"Health Services",
            "subcategory":"Doctor",
            "type":"Services"
        }
    ],
    "sg:phone":"+61 3 9312 3711",
    "sg:postcode":"3020",
    "sg:province":"VIC",
    "sg:tags":[
        "medical",
        "practitioner"
    ],
    "wof:name":"Sunshine Diagnostic Centre & Scanning Clinic",
    "wof:placetype":"venue"
},
  "geometry": {"coordinates":[144.83033800000001,-37.788445],"type":"Point"}
}