{
  "type": "Feature",
  "properties": {
    "addr:full":"379 Blaxland Rd Ryde NSW 2112",
    "addr:housenumber":"379",
    "addr:postcode":"2112",
    "addr:street":"Blaxland Rd",
    "iso:country":"AU",
    "sg:address":"379 Blaxland Rd",
    "sg:city":"Ryde",
    "sg:classifiers":[
        {
            "category":"Building & Trades",
            "subcategory":"Construction",
            "type":"Services"
        }
    ],
    "sg:phone":"+61 2 9807 4029",
    "sg:postcode":"2112",
    "sg:province":"NSW",
    "sg:tags":[
        "contractor"
    ],
    "wof:name":"Joe Zaouk",
    "wof:placetype":"venue"
},
  "geometry": {"coordinates":[151.10049438499999,-33.8014221191],"type":"Point"}
}