{
  "type": "Feature",
  "properties": {
    "iso:country":"AU",
    "sg:address":"8 Mt Erin Rd",
    "sg:city":"Ferny Creek",
    "sg:classifiers":[
        {
            "category":"Education",
            "subcategory":"Special Training",
            "type":"Public Place"
        }
    ],
    "sg:phone":"+61 3 9755 3801",
    "sg:postcode":"3786",
    "sg:province":"VIC",
    "sg:tags":[
        "development"
    ],
    "wof:name":"IDP Asia-Pacific Pty Ltd",
    "wof:placetype":"venue"
},
  "geometry": {"coordinates":[145.32402,-37.873974],"type":"Point"}
}