{
  "type": "Feature",
  "properties": {
    "iso:country":"AU",
    "sg:address":"U16/ 459",
    "sg:city":"The Blv Kirrawee",
    "sg:classifiers":[
        {
            "category":"Professional",
            "type":"Services"
        }
    ],
    "sg:phone":"+61 2 9545 4745",
    "sg:postcode":"2232",
    "sg:province":"NSW",
    "sg:tags":[
        "spray",
        "painting"
    ],
    "wof:name":"Dna Custom Painting",
    "wof:placetype":"venue"
},
  "geometry": {"coordinates":[151.073532105,-34.0122947693],"type":"Point"}
}