{
  "type": "Feature",
  "properties": {
    "addr:full":"5 Hunter St Sydney NSW 2000",
    "addr:housenumber":"5",
    "addr:postcode":"2000",
    "addr:street":"Hunter St",
    "iso:country":"AU",
    "sg:address":"5 Hunter St",
    "sg:city":"Sydney",
    "sg:classifiers":[
        {
            "category":"Health Services",
            "subcategory":"Optometrist",
            "type":"Services"
        }
    ],
    "sg:phone":"+61 2 9233 2083",
    "sg:postcode":"2000",
    "sg:province":"NSW",
    "wof:name":"Wood Colin, Bell Kenneth",
    "wof:placetype":"venue"
},
  "geometry": {"coordinates":[151.20753479000001,-33.865650177],"type":"Point"}
}