{
  "type": "Feature",
  "properties": {
    "iso:country":"AU",
    "sg:address":"125 Aphrasia St",
    "sg:city":"Newtown",
    "sg:classifiers":[
        {
            "category":"Health Services",
            "subcategory":"Health Practitioner",
            "type":"Services"
        }
    ],
    "sg:phone":"+61 3 5229 9580",
    "sg:postcode":"3220",
    "sg:province":"VIC",
    "sg:tags":[
        "physiotherapist"
    ],
    "wof:name":"Helen Purnell Physiotherapy",
    "wof:placetype":"venue"
},
  "geometry": {"coordinates":[144.333389,-38.149757],"type":"Point"}
}