{
  "type": "Feature",
  "properties": {
    "iso:country":"AU",
    "sg:address":"Shop 3, 200 Old Cleaveland Rd",
    "sg:city":"Coorparoo",
    "sg:classifiers":[
        {
            "category":"Fast Food",
            "type":"Food & Drink"
        }
    ],
    "sg:phone":"+61 7 3847 3358",
    "sg:postcode":"4151",
    "sg:province":"QLD",
    "sg:tags":[
        "away",
        "take"
    ],
    "wof:name":"Fins N Chips - Coorparoo",
    "wof:placetype":"venue"
},
  "geometry": {"coordinates":[153.05447387699999,-27.4968662262],"type":"Point"}
}