{
  "type": "Feature",
  "properties": {
    "addr:full":"302 Macarthur St Soldiers Hill VIC 3350",
    "addr:housenumber":"302",
    "addr:postcode":"3350",
    "addr:street":"Macarthur St",
    "iso:country":"AU",
    "sg:address":"302 Macarthur St",
    "sg:city":"Soldiers Hill",
    "sg:classifiers":[
        {
            "category":"Fast Food",
            "type":"Food & Drink"
        }
    ],
    "sg:phone":"+61 3 5332 1203",
    "sg:postcode":"3350",
    "sg:province":"VIC",
    "sg:tags":[
        "away",
        "take"
    ],
    "wof:name":"Lydiard Fish Haul",
    "wof:placetype":"venue"
},
  "geometry": {"coordinates":[143.85682700000001,-37.565678],"type":"Point"}
}