{
  "type": "Feature",
  "properties": {
    "iso:country":"AU",
    "sg:address":"50 Boyles Rd",
    "sg:city":"Mepunga",
    "sg:classifiers":[
        {
            "category":"Professional",
            "subcategory":"Testing Lab",
            "type":"Services"
        }
    ],
    "sg:phone":"+61 427 323 759",
    "sg:postcode":"3277",
    "sg:province":"VIC",
    "sg:tags":[
        "inspection"
    ],
    "wof:name":"Warrnambool Appliance Testing & Tagging",
    "wof:placetype":"venue"
},
  "geometry": {"coordinates":[142.656646728,-38.4213867188],"type":"Point"}
}