{
  "type": "Feature",
  "properties": {
    "iso:country":"AU",
    "sg:address":"31 Clifton Springs Rd",
    "sg:city":"Drysdale",
    "sg:classifiers":[
        {
            "category":"Building & Trades",
            "subcategory":"Plumbing",
            "type":"Services"
        }
    ],
    "sg:phone":"+61 418 532 316",
    "sg:postcode":"3222",
    "sg:province":"VIC",
    "sg:tags":[
        "plumber",
        "gasfitters"
    ],
    "wof:name":"Soupy's Plumbing Service",
    "wof:placetype":"venue"
},
  "geometry": {"coordinates":[144.573486,-38.159431],"type":"Point"}
}