{
  "type": "Feature",
  "properties": {
    "addr:full":"113- 123 Dalrymple Rd Garbutt QLD 4814",
    "addr:housenumber":"113 123",
    "addr:postcode":"4814",
    "addr:street":"Dalrymple Rd",
    "iso:country":"AU",
    "sg:address":"113- 123 Dalrymple Rd",
    "sg:city":"Garbutt",
    "sg:classifiers":[
        {
            "category":"Professional",
            "subcategory":"Computer Services",
            "type":"Services"
        }
    ],
    "sg:phone":"+61 7 4727 9012",
    "sg:postcode":"4814",
    "sg:province":"QLD",
    "sg:tags":[
        "training"
    ],
    "wof:name":"The Learning Centre",
    "wof:placetype":"venue"
},
  "geometry": {"coordinates":[146.772446,-19.271147],"type":"Point"}
}