{
  "type": "Feature",
  "properties": {
    "addr:full":"Bradfield St Downer ACT 2602",
    "addr:postcode":"2602",
    "addr:street":"St",
    "iso:country":"AU",
    "sg:address":"Bradfield St",
    "sg:city":"Downer",
    "sg:classifiers":[
        {
            "category":"Education",
            "subcategory":"Special Training",
            "type":"Public Place"
        }
    ],
    "sg:phone":"+61 2 6241 6836",
    "sg:postcode":"2602",
    "sg:province":"ACT",
    "sg:tags":[
        "development"
    ],
    "wof:name":"Tourism Training ACT & Region",
    "wof:placetype":"venue"
},
  "geometry": {"coordinates":[149.144607544,-35.2433586121],"type":"Point"}
}