{
  "type": "Feature",
  "properties": {
    "addr:full":"115 Ashleigh Ave Karingal VIC 3199",
    "addr:housenumber":"115",
    "addr:postcode":"3199",
    "addr:street":"Ashleigh Ave",
    "iso:country":"AU",
    "sg:address":"115 Ashleigh Ave",
    "sg:city":"Karingal",
    "sg:classifiers":[
        {
            "category":"Education",
            "subcategory":"Kindergarten",
            "type":"Public Place"
        }
    ],
    "sg:phone":"+61 3 9789 0225",
    "sg:postcode":"3199",
    "sg:province":"VIC",
    "sg:tags":[
        "pre-schools"
    ],
    "wof:name":"Karingal Kindergarten",
    "wof:placetype":"venue"
},
  "geometry": {"coordinates":[145.15255737300001,-38.138923645],"type":"Point"}
}