{
  "type": "Feature",
  "properties": {
    "addr:full":"Shed 1 / 104 Main St Elliminyt VIC 3249",
    "addr:housenumber":"1 / 104",
    "addr:postcode":"3249",
    "addr:street":"Main St",
    "iso:country":"AU",
    "sg:address":"Shed 1 / 104 Main St",
    "sg:city":"Elliminyt",
    "sg:classifiers":[
        {
            "category":"Professional",
            "subcategory":"Engineering",
            "type":"Services"
        }
    ],
    "sg:phone":"+61 3 5232 2249",
    "sg:postcode":"3249",
    "sg:province":"VIC",
    "sg:tags":[
        "engineer"
    ],
    "wof:name":"Tyrer Engineering",
    "wof:placetype":"venue"
},
  "geometry": {"coordinates":[143.58340454099999,-38.3555030823],"type":"Point"}
}