{
  "type": "Feature",
  "properties": {
    "iso:country":"AU",
    "sg:address":"Level 9 410 Queen St",
    "sg:city":"Brisbane",
    "sg:classifiers":[
        {
            "category":"Transit Center",
            "subcategory":"Freight",
            "type":"Transportation"
        }
    ],
    "sg:phone":"+61 7 3007 2104",
    "sg:postcode":"4000",
    "sg:province":"QLD",
    "sg:tags":[
        "agent",
        "shipping"
    ],
    "wof:name":"Mitsui OSK Lines (Australia) Pty Ltd",
    "wof:placetype":"venue"
},
  "geometry": {"coordinates":[153.03074645999999,-27.4651298523],"type":"Point"}
}