{
  "type": "Feature",
  "properties": {
    "addr:full":"23- 25 Sefton Rd Thornleigh NSW 2120",
    "addr:housenumber":"25",
    "addr:postcode":"2120",
    "addr:street":"Sefton Rd",
    "iso:country":"AU",
    "sg:address":"23- 25 Sefton Rd",
    "sg:city":"Thornleigh",
    "sg:classifiers":[
        {
            "category":"Professional",
            "type":"Services"
        }
    ],
    "sg:phone":"+61 2 9980 8666",
    "sg:postcode":"2120",
    "sg:province":"NSW",
    "sg:tags":[
        "packaging",
        "filling",
        "assembling"
    ],
    "wof:name":"DFC Thompson",
    "wof:placetype":"venue"
},
  "geometry": {"coordinates":[151.08708190900001,-33.7220916748],"type":"Point"}
}