{
  "type": "Feature",
  "properties": {
    "addr:full":"13 Corinth Rd Heathcote NSW 2233",
    "addr:housenumber":"13",
    "addr:postcode":"2233",
    "addr:street":"Corinth Rd",
    "iso:country":"AU",
    "sg:address":"13 Corinth Rd",
    "sg:city":"Heathcote",
    "sg:classifiers":[
        {
            "category":"Professional",
            "subcategory":"Computer Services",
            "type":"Services"
        }
    ],
    "sg:phone":"+61 2 9548 6200",
    "sg:postcode":"2233",
    "sg:province":"NSW",
    "sg:tags":[
        "tele-communications",
        "consultant"
    ],
    "wof:name":"Dwesa Pty Ltd",
    "wof:placetype":"venue"
},
  "geometry": {"coordinates":[151.005737305,-34.0795021057],"type":"Point"}
}