{
  "type": "Feature",
  "properties": {
    "addr:full":"26 Huntriss St Torrensville SA 5031",
    "addr:housenumber":"26",
    "addr:postcode":"5031",
    "addr:street":"Huntriss St",
    "iso:country":"AU",
    "sg:address":"26 Huntriss St",
    "sg:city":"Torrensville",
    "sg:classifiers":[
        {
            "category":"Personal",
            "subcategory":"Massage",
            "type":"Services"
        }
    ],
    "sg:phone":"+61 8 8354 2006",
    "sg:postcode":"5031",
    "sg:province":"SA",
    "sg:tags":[
        "therapy"
    ],
    "wof:name":"Blend Body Care",
    "wof:placetype":"venue"
},
  "geometry": {"coordinates":[138.56489563,-34.9221382141],"type":"Point"}
}