{
  "type": "Feature",
  "properties": {
    "iso:country":"AU",
    "sg:address":"543 Coronation Drv",
    "sg:city":"Toowong",
    "sg:classifiers":[
        {
            "category":"Restaurant",
            "type":"Food & Drink"
        }
    ],
    "sg:phone":"+61 7 3871 9595",
    "sg:postcode":"4066",
    "sg:province":"QLD",
    "sg:website":"http://www.regattahotel.com.au",
    "wof:name":"Regatta Hotel",
    "wof:placetype":"venue"
},
  "geometry": {"coordinates":[152.99635314899999,-27.4826011658],"type":"Point"}
}