{
  "type": "Feature",
  "properties": {
    "iso:country":"AU",
    "sg:address":"Level 1, 90 Phillip St",
    "sg:city":"Parramatta",
    "sg:classifiers":[
        {
            "category":"Banks & Credit Unions",
            "subcategory":"Financial Services",
            "type":"Services"
        }
    ],
    "sg:phone":"+61 2 8895 2355",
    "sg:postcode":"2150",
    "sg:province":"NSW",
    "sg:tags":[
        "planning"
    ],
    "wof:name":"State Super Financial Services Australia Limited",
    "wof:placetype":"venue"
},
  "geometry": {"coordinates":[150.96473693900001,-33.8522949219],"type":"Point"}
}