{
  "type": "Feature",
  "properties": {
    "addr:full":"Level 1/ 1A Hannah St Beecroft NSW 2119",
    "addr:housenumber":"/ 1a",
    "addr:postcode":"2119",
    "addr:street":"Hannah St",
    "iso:country":"AU",
    "sg:address":"Level 1/ 1A Hannah St",
    "sg:city":"Beecroft",
    "sg:classifiers":[
        {
            "category":"Health Services",
            "subcategory":"Doctor",
            "type":"Services"
        }
    ],
    "sg:phone":"+61 2 9484 6470",
    "sg:postcode":"2119",
    "sg:province":"NSW",
    "sg:tags":[
        "medical",
        "practitioner"
    ],
    "wof:name":"Motbey Dr. Josephine",
    "wof:placetype":"venue"
},
  "geometry": {"coordinates":[151.06568908700001,-33.7494544983],"type":"Point"}
}