{
  "type": "Feature",
  "properties": {
    "iso:country":"AU",
    "sg:address":"164 Km Peg Brand Hwy",
    "sg:city":"Dandaragan West",
    "sg:classifiers":[
        {
            "category":"Autos & Motor Vehicles",
            "subcategory":"Fuel & Gas Station",
            "type":"Retail Goods"
        }
    ],
    "sg:phone":"+61 8 9651 2024",
    "sg:postcode":"6507",
    "sg:province":"WA",
    "wof:name":"Ampol Roadhouse Cataby",
    "wof:placetype":"venue"
},
  "geometry": {"coordinates":[115.553551,-30.742691],"type":"Point"}
}