{
  "type": "Feature",
  "properties": {
    "addr:full":"414 Frome St Moree NSW 2400",
    "addr:housenumber":"414",
    "addr:postcode":"2400",
    "addr:street":"Frome St",
    "iso:country":"AU",
    "sg:address":"414 Frome St",
    "sg:city":"Moree",
    "sg:classifiers":[
        {
            "category":"Retail",
            "subcategory":"Auto Repair",
            "type":"Services"
        }
    ],
    "sg:phone":"+61 2 6752 3299",
    "sg:postcode":"2400",
    "sg:province":"NSW",
    "sg:tags":[
        "electrical"
    ],
    "wof:name":"A 1 Auto Electrics",
    "wof:placetype":"venue"
},
  "geometry": {"coordinates":[149.843185425,-29.4776077271],"type":"Point"}
}