{
  "type": "Feature",
  "properties": {
    "addr:full":"Unit 12/ 28 Pendlebury Rd Cardiff NSW 2285",
    "addr:housenumber":"/ 28",
    "addr:postcode":"2285",
    "addr:street":"Pendlebury Rd",
    "iso:country":"AU",
    "sg:address":"Unit 12/ 28 Pendlebury Rd",
    "sg:city":"Cardiff",
    "sg:classifiers":[
        {
            "category":"Utilities",
            "subcategory":"Electric",
            "type":"Services"
        }
    ],
    "sg:phone":"+61 411 536 204",
    "sg:postcode":"2285",
    "sg:province":"NSW",
    "sg:tags":[
        "electrical",
        "contractor"
    ],
    "wof:name":"Impact Air",
    "wof:placetype":"venue"
},
  "geometry": {"coordinates":[151.65365600600001,-32.9462661743],"type":"Point"}
}