{
  "type": "Feature",
  "properties": {
    "addr:full":"235 Maude St Mall Shepparton VIC 3630",
    "addr:housenumber":"235",
    "addr:postcode":"3630",
    "addr:street":"Maude St Mall",
    "iso:country":"AU",
    "sg:address":"235 Maude St Mall",
    "sg:city":"Shepparton",
    "sg:classifiers":[
        {
            "category":"Cafe",
            "type":"Food & Drink"
        }
    ],
    "sg:phone":"+61 3 5821 8832",
    "sg:postcode":"3630",
    "sg:province":"VIC",
    "wof:name":"Healthy & Delicious",
    "wof:placetype":"venue"
},
  "geometry": {"coordinates":[145.4009552,-36.3811035156],"type":"Point"}
}