{
  "type": "Feature",
  "properties": {
    "addr:full":"Ksk 5/ 330 Mcdonalds Rd South Morang VIC 3752",
    "addr:housenumber":"/ 330",
    "addr:postcode":"3752",
    "addr:street":"Mcdonalds Rd",
    "iso:country":"AU",
    "sg:address":"Ksk 5/ 330 Mcdonalds Rd",
    "sg:city":"South Morang",
    "sg:classifiers":[
        {
            "category":"Casinos & Gambling",
            "type":"Entertainment"
        }
    ],
    "sg:phone":"+61 3 9436 0000",
    "sg:postcode":"3752",
    "sg:province":"VIC",
    "sg:tags":[
        "lottery",
        "agent"
    ],
    "wof:name":"Plenty Valley Lotto",
    "wof:placetype":"venue"
},
  "geometry": {"coordinates":[145.07449299999999,-37.649811],"type":"Point"}
}