{
  "type": "Feature",
  "properties": {
    "addr:full":"High St Woodend VIC 3442",
    "addr:postcode":"3442",
    "addr:street":"High St",
    "iso:country":"AU",
    "sg:address":"High St",
    "sg:city":"Woodend",
    "sg:classifiers":[
        {
            "category":"Food & Beverages",
            "subcategory":"Groceries & Convenience Stores",
            "type":"Retail Goods"
        }
    ],
    "sg:phone":"+61 3 5427 2248",
    "sg:postcode":"3442",
    "sg:province":"VIC",
    "wof:name":"&#034;C&#034; Store",
    "wof:placetype":"venue"
},
  "geometry": {"coordinates":[144.53224182100001,-37.3525466919],"type":"Point"}
}