{
  "type": "Feature",
  "properties": {
    "iso:country":"AU",
    "sg:address":"9 Birdwood Ave",
    "sg:city":"Brighton",
    "sg:classifiers":[
        {
            "category":"Health Services",
            "subcategory":"Doctor",
            "type":"Services"
        }
    ],
    "sg:phone":"+61 411 465 235",
    "sg:postcode":"3186",
    "sg:province":"VIC",
    "sg:tags":[
        "medical",
        "practitioner"
    ],
    "wof:name":"Freedman Mark Dr",
    "wof:placetype":"venue"
},
  "geometry": {"coordinates":[144.98817443900001,-37.8944625854],"type":"Point"}
}