{
  "type": "Feature",
  "properties": {
    "addr:full":"277 Hampton St Hampton VIC 3188",
    "addr:housenumber":"277",
    "addr:postcode":"3188",
    "addr:street":"Hampton St",
    "iso:country":"AU",
    "sg:address":"277 Hampton St",
    "sg:city":"Hampton",
    "sg:classifiers":[
        {
            "category":"Fast Food",
            "type":"Food & Drink"
        }
    ],
    "sg:phone":"+61 3 9598 4444",
    "sg:postcode":"3188",
    "sg:province":"VIC",
    "sg:tags":[
        "away",
        "take"
    ],
    "wof:name":"Indian Express",
    "wof:placetype":"venue"
},
  "geometry": {"coordinates":[145.001953125,-37.9396781921],"type":"Point"}
}