{
  "type": "Feature",
  "properties": {
    "addr:full":"115 Mullens St Balmain NSW 2041",
    "addr:housenumber":"115",
    "addr:postcode":"2041",
    "addr:street":"Mullens St",
    "iso:country":"AU",
    "sg:address":"115 Mullens St",
    "sg:city":"Balmain",
    "sg:classifiers":[
        {
            "category":"Professional",
            "subcategory":"Engineering",
            "type":"Services"
        }
    ],
    "sg:phone":"+61 2 9555 1166",
    "sg:postcode":"2041",
    "sg:province":"NSW",
    "sg:tags":[
        "engineer",
        "designing"
    ],
    "wof:name":"Design + Industry",
    "wof:placetype":"venue"
},
  "geometry": {"coordinates":[151.176254,-33.86261],"type":"Point"}
}