{
  "type": "Feature",
  "properties": {
    "addr:full":"129 Hotham Rd Sorrento VIC 3943",
    "addr:housenumber":"129",
    "addr:postcode":"3943",
    "addr:street":"Hotham Rd",
    "iso:country":"AU",
    "sg:address":"129 Hotham Rd",
    "sg:city":"Sorrento",
    "sg:classifiers":[
        {
            "category":"Manufacturing",
            "subcategory":"Motor Vehicles & Parts",
            "type":"Manufacturing & Wholesale Goods"
        }
    ],
    "sg:phone":"+61 3 5984 4333",
    "sg:postcode":"3943",
    "sg:province":"VIC",
    "sg:tags":[
        "engine",
        "equipment",
        "diesel"
    ],
    "wof:name":"Wooden Boat Shop",
    "wof:placetype":"venue"
},
  "geometry": {"coordinates":[144.72966003400001,-38.3343811035],"type":"Point"}
}