{
  "type": "Feature",
  "properties": {
    "iso:country":"AU",
    "sg:address":"Boyup Rd",
    "sg:city":"Kendenup",
    "sg:classifiers":[
        {
            "category":"Farming",
            "subcategory":"Farm",
            "type":"Manufacturing & Wholesale Goods"
        }
    ],
    "sg:phone":"+61 8 9851 4147",
    "sg:postcode":"6323",
    "sg:province":"WA",
    "sg:tags":[
        "farmer"
    ],
    "wof:name":"Howard J R",
    "wof:placetype":"venue"
},
  "geometry": {"coordinates":[117.49720764200001,-34.4960594177],"type":"Point"}
}