{
  "type": "Feature",
  "properties": {
    "iso:country":"AU",
    "sg:address":"11 Bayldon Rd",
    "sg:city":"Queanbeyan",
    "sg:classifiers":[
        {
            "category":"Utilities",
            "subcategory":"Electric",
            "type":"Services"
        }
    ],
    "sg:phone":"+61 2 6299 6233",
    "sg:postcode":"2620",
    "sg:province":"NSW",
    "sg:tags":[
        "electrical",
        "contractor"
    ],
    "wof:name":"Control & Electric Pty Ltd",
    "wof:placetype":"venue"
},
  "geometry": {"coordinates":[149.20687866200001,-35.3519325256],"type":"Point"}
}