{
  "type": "Feature",
  "properties": {
    "addr:full":"Corner Ballarat Road & Evan Street Braybrook VIC 3019",
    "addr:postcode":"3019",
    "addr:street":"Ballarat Road & Evan Street",
    "iso:country":"AU",
    "sg:address":"Corner Ballarat Road",
    "sg:city":"& Evan Street Braybrook",
    "sg:classifiers":[
        {
            "category":"Retail",
            "subcategory":"Auto Repair",
            "type":"Services"
        }
    ],
    "sg:phone":"+61 3 9317 8222",
    "sg:postcode":"3019",
    "sg:province":"VIC",
    "sg:tags":[
        "hire",
        "go-kart"
    ],
    "wof:name":"Fun City Entertainment Complex",
    "wof:placetype":"venue"
},
  "geometry": {"coordinates":[144.855300903,-37.7800369263],"type":"Point"}
}