{
  "type": "Feature",
  "properties": {
    "addr:full":"13 Success Crs Salter Point WA 6152",
    "addr:housenumber":"13",
    "addr:postcode":"6152",
    "addr:street":"Success Crs",
    "iso:country":"AU",
    "sg:address":"13 Success Crs",
    "sg:city":"Salter Point",
    "sg:classifiers":[
        {
            "category":"Banks & Credit Unions",
            "subcategory":"Financial Services",
            "type":"Services"
        }
    ],
    "sg:phone":"+61 8 9450 8800",
    "sg:postcode":"6152",
    "sg:province":"WA",
    "sg:tags":[
        "settlement",
        "nt",
        "agent",
        "wa"
    ],
    "wof:name":"PR Settlements",
    "wof:placetype":"venue"
},
  "geometry": {"coordinates":[115.862793,-32.020641],"type":"Point"}
}