{
  "type": "Feature",
  "properties": {
    "addr:full":"18 Elsie Mews Brunswick East VIC 3057",
    "addr:housenumber":"18",
    "addr:postcode":"3057",
    "addr:street":"Elsie Mews",
    "iso:country":"AU",
    "sg:address":"18 Elsie Mews",
    "sg:city":"Brunswick East",
    "sg:classifiers":[
        {
            "category":"Building & Trades",
            "subcategory":"Plumbing",
            "type":"Services"
        }
    ],
    "sg:phone":"+61 3 9381 4314",
    "sg:postcode":"3057",
    "sg:province":"VIC",
    "sg:tags":[
        "plumber",
        "gasfitters"
    ],
    "wof:name":"Inner City Plumbing",
    "wof:placetype":"venue"
},
  "geometry": {"coordinates":[144.977905273,-37.7681617737],"type":"Point"}
}