{
  "type": "Feature",
  "properties": {
    "addr:full":"89 Monfarville St St Marys NSW 2760",
    "addr:housenumber":"89",
    "addr:postcode":"2760",
    "addr:street":"Monfarville St",
    "iso:country":"AU",
    "sg:address":"89 Monfarville St",
    "sg:city":"St Marys",
    "sg:classifiers":[
        {
            "category":"Food & Beverages",
            "subcategory":"Groceries & Convenience Stores",
            "type":"Retail Goods"
        }
    ],
    "sg:phone":"+61 2 9623 5030",
    "sg:postcode":"2760",
    "sg:province":"NSW",
    "wof:name":"Andrews Corner Store",
    "wof:placetype":"venue"
},
  "geometry": {"coordinates":[150.775482178,-33.7786407471],"type":"Point"}
}