{
  "type": "Feature",
  "properties": {
    "iso:country":"AU",
    "sg:address":"146 Murphy St",
    "sg:city":"Bendigo",
    "sg:classifiers":[
        {
            "category":"Autos & Motor Vehicles",
            "subcategory":"Boat Sales",
            "type":"Retail Goods"
        }
    ],
    "sg:phone":"+61 3 5441 4488",
    "sg:postcode":"3550",
    "sg:province":"VIC",
    "sg:tags":[
        "yacht"
    ],
    "wof:name":"Bendigo Ski Boat Centre",
    "wof:placetype":"venue"
},
  "geometry": {"coordinates":[144.303665161,-36.7481384277],"type":"Point"}
}