{
  "type": "Feature",
  "properties": {
    "addr:full":"132 Johnston St Collingwood VIC 3066",
    "addr:housenumber":"132",
    "addr:postcode":"3066",
    "addr:street":"Johnston St",
    "iso:country":"AU",
    "sg:address":"132 Johnston St",
    "sg:city":"Collingwood",
    "sg:classifiers":[
        {
            "category":"Government",
            "subcategory":"Post Office",
            "type":"Public Place"
        }
    ],
    "sg:phone":"+61 3 9419 1818",
    "sg:postcode":"3066",
    "sg:province":"VIC",
    "sg:tags":[
        "postage",
        "meter"
    ],
    "wof:name":"Advanced Office Systems",
    "wof:placetype":"venue"
},
  "geometry": {"coordinates":[144.98945617699999,-37.7993507385],"type":"Point"}
}