{
  "type": "Feature",
  "properties": {
    "addr:full":"57 Northcote St Kurri Kurri NSW 2327",
    "addr:housenumber":"57",
    "addr:postcode":"2327",
    "addr:street":"Northcote St",
    "iso:country":"AU",
    "sg:address":"57 Northcote St",
    "sg:city":"Kurri Kurri",
    "sg:classifiers":[
        {
            "category":"Home & Garden",
            "subcategory":"Garden Supply",
            "type":"Retail Goods"
        }
    ],
    "sg:phone":"+61 2 4937 3220",
    "sg:postcode":"2327",
    "sg:province":"NSW",
    "sg:tags":[
        "landscape"
    ],
    "wof:name":"Kurri Kurri Sand, Soil & Landscape Supplies",
    "wof:placetype":"venue"
},
  "geometry": {"coordinates":[151.47845459000001,-32.8116455078],"type":"Point"}
}