{
  "type": "Feature",
  "properties": {
    "addr:full":"17 West St Five Dock NSW 2046",
    "addr:housenumber":"17",
    "addr:postcode":"2046",
    "addr:street":"West St",
    "iso:country":"AU",
    "sg:address":"17 West St",
    "sg:city":"Five Dock",
    "sg:classifiers":[
        {
            "category":"Professional",
            "subcategory":"Computer Services",
            "type":"Services"
        }
    ],
    "sg:phone":"+61 2 9713 1700",
    "sg:postcode":"2046",
    "sg:province":"NSW",
    "sg:tags":[
        "consultant",
        "system"
    ],
    "wof:name":"Tech Care Computer Services",
    "wof:placetype":"venue"
},
  "geometry": {"coordinates":[151.128479,-33.865253],"type":"Point"}
}