{
  "type": "Feature",
  "properties": {
    "addr:full":"Shop 151 Gladstone Pk Shp Gladstone Park Drv Tullamarine VIC 3043",
    "addr:housenumber":"151",
    "addr:postcode":"3043",
    "addr:street":"Gladstone Pk;Gladstone Park Drv",
    "iso:country":"AU",
    "sg:address":"Shop 151 Gladstone Pk Shp Gladstone Park Drv",
    "sg:city":"Tullamarine",
    "sg:classifiers":[
        {
            "category":"Health Services",
            "subcategory":"Health Practitioner",
            "type":"Services"
        }
    ],
    "sg:phone":"+61 3 9338 2585",
    "sg:postcode":"3043",
    "sg:province":"VIC",
    "sg:tags":[
        "osteopath"
    ],
    "wof:name":"Hume Osteopathic Clinic",
    "wof:placetype":"venue"
},
  "geometry": {"coordinates":[144.88247680699999,-37.6881065369],"type":"Point"}
}