{
  "type": "Feature",
  "properties": {
    "addr:full":"26 Edmonstone Rd Bowen Hills QLD 4006",
    "addr:housenumber":"26",
    "addr:postcode":"4006",
    "addr:street":"Edmonstone Rd",
    "iso:country":"AU",
    "sg:address":"26 Edmonstone Rd",
    "sg:city":"Bowen Hills",
    "sg:classifiers":[
        {
            "category":"Professional",
            "subcategory":"Computer Services",
            "type":"Services"
        }
    ],
    "sg:phone":"+61 1300 792 844",
    "sg:postcode":"4006",
    "sg:province":"QLD",
    "sg:tags":[
        "repairs",
        "upgrade",
        "equipment"
    ],
    "sg:website":"http://www.qldbusinessmachines.com.au",
    "wof:name":"Printer Repair Company",
    "wof:placetype":"venue"
},
  "geometry": {"coordinates":[153.04057312,-27.4424743652],"type":"Point"}
}