{
  "type": "Feature",
  "properties": {
    "iso:country":"AU",
    "sg:address":"3/21 Lionel Rd",
    "sg:city":"Mt Waverley",
    "sg:classifiers":[
        {
            "category":"Building & Trades",
            "subcategory":"Electrical",
            "type":"Services"
        }
    ],
    "sg:phone":"+61 3 9535 2000",
    "sg:postcode":"3149",
    "sg:province":"VIC",
    "sg:tags":[
        "wholesaler",
        "mfrs",
        "appliance"
    ],
    "wof:name":"Franke Australia Pty Ltd",
    "wof:placetype":"venue"
},
  "geometry": {"coordinates":[145.13955688499999,-37.898399353],"type":"Point"}
}