{
  "type": "Feature",
  "properties": {
    "addr:full":"33 Sway St Coopers Plains QLD 4108",
    "addr:housenumber":"33",
    "addr:postcode":"4108",
    "addr:street":"Sway St",
    "iso:country":"AU",
    "sg:address":"33 Sway St",
    "sg:city":"Coopers Plains",
    "sg:classifiers":[
        {
            "category":"Real Estate",
            "subcategory":"Real Estate Agent",
            "type":"Services"
        }
    ],
    "sg:phone":"+61 7 3274 4044",
    "sg:postcode":"4108",
    "sg:province":"QLD",
    "sg:tags":[
        "steel",
        "foundry",
        "iron"
    ],
    "wof:name":"Wear Tech Foundry",
    "wof:placetype":"venue"
},
  "geometry": {"coordinates":[153.02798461899999,-27.5595035553],"type":"Point"}
}