{
  "type": "Feature",
  "properties": {
    "addr:full":"12a Ryelane St Maddington WA 6109",
    "addr:housenumber":"12a",
    "addr:postcode":"6109",
    "addr:street":"Ryelane St",
    "iso:country":"AU",
    "sg:address":"12a Ryelane St",
    "sg:city":"Maddington",
    "sg:classifiers":[
        {
            "category":"Home & Garden",
            "subcategory":"Building Materials",
            "type":"Retail Goods"
        }
    ],
    "sg:phone":"+61 8 9459 4020",
    "sg:postcode":"6109",
    "sg:province":"WA",
    "sg:tags":[
        "fencing"
    ],
    "wof:name":"Fencing Products Australia",
    "wof:placetype":"venue"
},
  "geometry": {"coordinates":[115.98925781200001,-32.0424499512],"type":"Point"}
}