{
  "type": "Feature",
  "properties": {
    "addr:full":"43 Greenhill Rd Wayville SA 5034",
    "addr:housenumber":"43",
    "addr:postcode":"5034",
    "addr:street":"Greenhill Rd",
    "iso:country":"AU",
    "sg:address":"43 Greenhill Rd",
    "sg:city":"Wayville",
    "sg:classifiers":[
        {
            "category":"Professional",
            "subcategory":"Employment Agencies",
            "type":"Services"
        }
    ],
    "sg:phone":"+61 8 8272 8885",
    "sg:postcode":"5034",
    "sg:province":"SA",
    "sg:tags":[
        "provider",
        "internet"
    ],
    "wof:name":"TX Communications Pty Ltd",
    "wof:placetype":"venue"
},
  "geometry": {"coordinates":[138.59042358400001,-34.9420013428],"type":"Point"}
}