{
  "type": "Feature",
  "properties": {
    "iso:country":"AU",
    "sg:address":"36 Epsom Ave",
    "sg:city":"Belmont",
    "sg:classifiers":[
        {
            "category":"Retail",
            "subcategory":"Auto Repair",
            "type":"Services"
        }
    ],
    "sg:phone":"+61 8 9479 4741",
    "sg:postcode":"6104",
    "sg:province":"WA",
    "sg:tags":[
        "beater",
        "painter",
        "panel"
    ],
    "wof:name":"Ascot Smash Repair",
    "wof:placetype":"venue"
},
  "geometry": {"coordinates":[115.93106079099999,-31.9352722168],"type":"Point"}
}