{
  "type": "Feature",
  "properties": {
    "addr:full":"Shop 122 Marina Mirage Main Beach QLD 4217",
    "addr:housenumber":"122",
    "addr:postcode":"4217",
    "iso:country":"AU",
    "sg:address":"Shop 122 Marina Mirage",
    "sg:city":"Main Beach",
    "sg:classifiers":[
        {
            "category":"Shopping",
            "subcategory":"Clothing, Apparel, & Fashions",
            "type":"Retail Goods"
        }
    ],
    "sg:phone":"+61 7 5532 9055",
    "sg:postcode":"4217",
    "sg:province":"QLD",
    "sg:tags":[
        "lingerie",
        "hosiery",
        "sleepwear"
    ],
    "wof:name":"I.M. Designer Bodywear",
    "wof:placetype":"venue"
},
  "geometry": {"coordinates":[153.429153442,-27.982339859],"type":"Point"}
}