{
  "type": "Feature",
  "properties": {
    "iso:country":"AU",
    "sg:address":"31 Ivanhoe Pde",
    "sg:city":"Ivanhoe",
    "sg:classifiers":[
        {
            "category":"Shopping",
            "subcategory":"Computers & Home Electronics",
            "type":"Retail Goods"
        }
    ],
    "sg:phone":"+61 3 9499 6838",
    "sg:postcode":"3079",
    "sg:province":"VIC",
    "sg:tags":[
        "hardware",
        "equipment"
    ],
    "wof:name":"C N Z Computers",
    "wof:placetype":"venue"
},
  "geometry": {"coordinates":[145.04454040499999,-37.7662315369],"type":"Point"}
}