{
  "type": "Feature",
  "properties": {
    "addr:full":"569 Merrylands Rd Merrylands NSW 2160",
    "addr:housenumber":"569",
    "addr:postcode":"2160",
    "addr:street":"Merrylands Rd",
    "iso:country":"AU",
    "sg:address":"569 Merrylands Rd",
    "sg:city":"Merrylands",
    "sg:classifiers":[
        {
            "category":"Mining & Drilling",
            "type":"Manufacturing & Wholesale Goods"
        }
    ],
    "sg:phone":"+61 2 9636 1963",
    "sg:postcode":"2160",
    "sg:province":"NSW",
    "sg:tags":[
        "concrete",
        "breaking",
        "grinding",
        "sawing"
    ],
    "wof:name":"Fitzgerald G M",
    "wof:placetype":"venue"
},
  "geometry": {"coordinates":[150.96403503400001,-33.8308677673],"type":"Point"}
}