{
  "type": "Feature",
  "properties": {
    "addr:full":"Six Mile Rd Boyup Brook WA 6244",
    "addr:postcode":"6244",
    "addr:street":"Six Mile Rd",
    "iso:country":"AU",
    "sg:address":"Six Mile Rd",
    "sg:city":"Boyup Brook",
    "sg:classifiers":[
        {
            "category":"Farming",
            "subcategory":"Farm",
            "type":"Manufacturing & Wholesale Goods"
        }
    ],
    "sg:phone":"+61 8 9765 1020",
    "sg:postcode":"6244",
    "sg:province":"WA",
    "sg:tags":[
        "farmer"
    ],
    "wof:name":"Gibbs B J & A J",
    "wof:placetype":"venue"
},
  "geometry": {"coordinates":[116.451042175,-33.8813514709],"type":"Point"}
}