{
  "type": "Feature",
  "properties": {
    "addr:full":"PO Box 1016 Browns Plains QLD 4118",
    "addr:postcode":"4118",
    "iso:country":"AU",
    "sg:address":"PO Box 1016",
    "sg:city":"Browns Plains",
    "sg:classifiers":[
        {
            "category":"Social Services",
            "subcategory":"Retirement Home",
            "type":"Services"
        }
    ],
    "sg:phone":"+61 7 3808 3177",
    "sg:postcode":"4118",
    "sg:province":"QLD",
    "sg:tags":[
        "environmental",
        "consultant",
        "pollution"
    ],
    "wof:name":"Huson & Associates",
    "wof:placetype":"venue"
},
  "geometry": {"coordinates":[153.05284118599999,-27.6627407074],"type":"Point"}
}