{
  "type": "Feature",
  "properties": {
    "addr:full":"2 Hillview Crs Bahrs Scrub QLD 4207",
    "addr:housenumber":"2",
    "addr:postcode":"4207",
    "addr:street":"Hillview Crs",
    "iso:country":"AU",
    "sg:address":"2 Hillview Crs",
    "sg:city":"Bahrs Scrub",
    "sg:classifiers":[
        {
            "category":"Building & Trades",
            "subcategory":"Plumbing",
            "type":"Services"
        }
    ],
    "sg:phone":"+61 411 555 886",
    "sg:postcode":"4207",
    "sg:province":"QLD",
    "sg:tags":[
        "plumber",
        "gasfitters"
    ],
    "wof:name":"Smith Graham Plumbing Contractors",
    "wof:placetype":"venue"
},
  "geometry": {"coordinates":[153.18716430699999,-27.7437705994],"type":"Point"}
}