{
  "type": "Feature",
  "properties": {
    "iso:country":"AU",
    "sg:address":"Unit 3/4 32- 36 Hampton St",
    "sg:city":"East Brisbane",
    "sg:classifiers":[
        {
            "category":"Wholesale",
            "subcategory":"Electrical",
            "type":"Manufacturing & Wholesale Goods"
        }
    ],
    "sg:phone":"+61 7 3891 6450",
    "sg:postcode":"4169",
    "sg:province":"QLD",
    "sg:tags":[
        "wholesaler"
    ],
    "wof:name":"ABK Electrical Wholesale Pty Ltd",
    "wof:placetype":"venue"
},
  "geometry": {"coordinates":[153.040557861,-27.4894580841],"type":"Point"}
}