{
  "type": "Feature",
  "properties": {
    "addr:full":"Shop 24 North Adelaide Village Shopping Centre O&# North Adelaide SA 5006",
    "addr:housenumber":"shop 24",
    "addr:postcode":"5006",
    "iso:country":"AU",
    "sg:address":"Shop 24 North Adelaide Village Shopping Centre O&#",
    "sg:city":"North Adelaide",
    "sg:classifiers":[
        {
            "category":"Personal",
            "subcategory":"Beauty Salon",
            "type":"Services"
        }
    ],
    "sg:phone":"+61 8 8267 5646",
    "sg:postcode":"5006",
    "sg:province":"SA",
    "sg:tags":[
        "hairdresser"
    ],
    "wof:name":"YS Salon",
    "wof:placetype":"venue"
},
  "geometry": {"coordinates":[138.59637451200001,-34.9079818726],"type":"Point"}
}