{
  "type": "Feature",
  "properties": {
    "addr:full":"23- 25 Swift Way Dandenong VIC 3175",
    "addr:housenumber":"25",
    "addr:postcode":"3175",
    "addr:street":"Swift Way",
    "iso:country":"AU",
    "sg:address":"23- 25",
    "sg:city":"Swift Way Dandenong",
    "sg:classifiers":[
        {
            "category":"Professional",
            "subcategory":"Testing Lab",
            "type":"Services"
        }
    ],
    "sg:phone":"+61 3 9768 2872",
    "sg:postcode":"3175",
    "sg:province":"VIC",
    "sg:tags":[
        "soil",
        "investigation"
    ],
    "wof:name":"Bowler Geotechnical",
    "wof:placetype":"venue"
},
  "geometry": {"coordinates":[145.20608520499999,-38.0343437195],"type":"Point"}
}