{
  "type": "Feature",
  "properties": {
    "iso:country":"AU",
    "sg:address":"21 Renwick Rd",
    "sg:city":"Ferntree Gully",
    "sg:classifiers":[
        {
            "category":"Building & Trades",
            "subcategory":"Construction",
            "type":"Services"
        }
    ],
    "sg:phone":"+61 3 9758 5376",
    "sg:postcode":"3156",
    "sg:province":"VIC",
    "sg:tags":[
        "window",
        "aluminium"
    ],
    "wof:name":"Victorian Window Replacements",
    "wof:placetype":"venue"
},
  "geometry": {"coordinates":[145.26557922399999,-37.8822364807],"type":"Point"}
}