{
  "type": "Feature",
  "properties": {
    "iso:country":"AU",
    "sg:address":"41 Violet St",
    "sg:city":"Eagle Farm",
    "sg:classifiers":[
        {
            "category":"Home & Garden",
            "subcategory":"Carpets & Floor Coverings",
            "type":"Retail Goods"
        }
    ],
    "sg:phone":"+61 1300 300 953",
    "sg:postcode":"4009",
    "sg:province":"QLD",
    "sg:tags":[
        "mat",
        "matting"
    ],
    "wof:name":"Alsco Pty Ltd",
    "wof:placetype":"venue"
},
  "geometry": {"coordinates":[153.08442688,-27.4312839508],"type":"Point"}
}