{
  "type": "Feature",
  "properties": {
    "addr:full":"55 Patrick St Stawell VIC 3380",
    "addr:housenumber":"55",
    "addr:postcode":"3380",
    "addr:street":"Patrick St",
    "iso:country":"AU",
    "sg:address":"55 Patrick St",
    "sg:city":"Stawell",
    "sg:classifiers":[
        {
            "category":"Education",
            "subcategory":"School",
            "type":"Public Place"
        }
    ],
    "sg:phone":"+61 3 5358 2493",
    "sg:postcode":"3380",
    "sg:province":"VIC",
    "wof:name":"St Patricks School",
    "wof:placetype":"venue"
},
  "geometry": {"coordinates":[142.78713989299999,-37.0594062805],"type":"Point"}
}