{
  "type": "Feature",
  "properties": {
    "addr:full":"5 McLaren St North Sydney NSW 2060",
    "addr:housenumber":"5",
    "addr:postcode":"2060",
    "addr:street":"Mclaren St",
    "iso:country":"AU",
    "sg:address":"5 McLaren St",
    "sg:city":"North Sydney",
    "sg:classifiers":[
        {
            "category":"Real Estate",
            "subcategory":"Developer",
            "type":"Services"
        }
    ],
    "sg:phone":"+61 2 9959 5446",
    "sg:postcode":"2060",
    "sg:province":"NSW",
    "sg:tags":[
        "development"
    ],
    "wof:name":"Waromar Pty Ltd",
    "wof:placetype":"venue"
},
  "geometry": {"coordinates":[151.205810547,-33.8346366882],"type":"Point"}
}