{
  "type": "Feature",
  "properties": {
    "addr:full":"PO Box 408 Hastings VIC 3915",
    "addr:postcode":"3915",
    "iso:country":"AU",
    "sg:address":"PO Box 408",
    "sg:city":"Hastings",
    "sg:classifiers":[
        {
            "category":"Building & Trades",
            "subcategory":"Construction",
            "type":"Services"
        }
    ],
    "sg:phone":"+61 417 898 818",
    "sg:postcode":"3915",
    "sg:province":"VIC",
    "sg:tags":[
        "concrete",
        "contractor"
    ],
    "wof:name":"Crete Force",
    "wof:placetype":"venue"
},
  "geometry": {"coordinates":[145.19129943900001,-38.3077011108],"type":"Point"}
}