{
  "type": "Feature",
  "properties": {
    "addr:full":"22/ 1 Short St Chatswood NSW 2067",
    "addr:housenumber":"22 / 1",
    "addr:postcode":"2067",
    "addr:street":"Short St",
    "iso:country":"AU",
    "sg:address":"22/ 1 Short St",
    "sg:city":"Chatswood",
    "sg:classifiers":[
        {
            "category":"Professional",
            "subcategory":"Printing & Photocopies",
            "type":"Services"
        }
    ],
    "sg:phone":"+61 2 9882 2111",
    "sg:postcode":"2067",
    "sg:province":"NSW",
    "sg:tags":[
        "embroidery"
    ],
    "sg:website":"http://www.northsideembroidery.com",
    "wof:name":"Northside Embroidery",
    "wof:placetype":"venue"
},
  "geometry": {"coordinates":[151.19781494099999,-33.7858695984],"type":"Point"}
}