{
  "type": "Feature",
  "properties": {
    "iso:country":"AU",
    "sg:address":"436 Wanneroo Rd (cnr Main St)",
    "sg:city":"Balcatta",
    "sg:classifiers":[
        {
            "category":"Retail",
            "subcategory":"Auto Rental",
            "type":"Services"
        }
    ],
    "sg:phone":"+61 8 9345 5855",
    "sg:postcode":"6021",
    "sg:province":"WA",
    "sg:tags":[
        "bus",
        "truck"
    ],
    "wof:name":"Northside Rentals",
    "wof:placetype":"venue"
},
  "geometry": {"coordinates":[115.829490662,-31.8672294617],"type":"Point"}
}