{
  "type": "Feature",
  "properties": {
    "addr:full":"Lvl 4/ 450 St Kilda Rd Melbourne VIC 3000",
    "addr:housenumber":"/ 450",
    "addr:postcode":"3000",
    "addr:street":"St Kilda Rd",
    "iso:country":"AU",
    "sg:address":"Lvl 4/ 450 St Kilda Rd",
    "sg:city":"Melbourne",
    "sg:classifiers":[
        {
            "category":"Professional",
            "subcategory":"Employment Agencies",
            "type":"Services"
        }
    ],
    "sg:phone":"+61 3 9820 5805",
    "sg:postcode":"3000",
    "sg:province":"VIC",
    "sg:tags":[
        "broker",
        "custom"
    ],
    "wof:name":"ENK Logistics",
    "wof:placetype":"venue"
},
  "geometry": {"coordinates":[144.976119995,-37.8387718201],"type":"Point"}
}