{
  "type": "Feature",
  "properties": {
    "addr:full":"40 Balcombe Rd Mentone VIC 3194",
    "addr:housenumber":"40",
    "addr:postcode":"3194",
    "addr:street":"Balcombe Rd",
    "iso:country":"AU",
    "sg:address":"40 Balcombe Rd",
    "sg:city":"Mentone",
    "sg:classifiers":[
        {
            "category":"Banks & Credit Unions",
            "subcategory":"Bureau De Change",
            "type":"Services"
        }
    ],
    "sg:phone":"+61 1300 656 474",
    "sg:postcode":"3194",
    "sg:province":"VIC",
    "sg:tags":[
        "bin",
        "ash",
        "tray"
    ],
    "wof:name":"Smoke Zone - Managing Smokers",
    "wof:placetype":"venue"
},
  "geometry": {"coordinates":[145.068161011,-37.9814872742],"type":"Point"}
}