{
  "type": "Feature",
  "properties": {
    "addr:full":"15a Conochie Crs Manning WA 6152",
    "addr:housenumber":"15a",
    "addr:postcode":"6152",
    "addr:street":"Conochie Crs",
    "iso:country":"AU",
    "sg:address":"15a Conochie Crs",
    "sg:city":"Manning",
    "sg:classifiers":[
        {
            "category":"Utilities",
            "subcategory":"Mobile Phone",
            "type":"Services"
        }
    ],
    "sg:phone":"+61 8 9450 1629",
    "sg:postcode":"6152",
    "sg:province":"WA",
    "sg:tags":[
        "aviation",
        "consultant"
    ],
    "wof:name":"Avtek Pty Ltd",
    "wof:placetype":"venue"
},
  "geometry": {"coordinates":[115.868973,-32.015171],"type":"Point"}
}