{
  "type": "Feature",
  "properties": {
    "addr:full":"75 Rees Ave Coorparoo QLD 4151",
    "addr:housenumber":"75",
    "addr:postcode":"4151",
    "addr:street":"Rees Ave",
    "iso:country":"AU",
    "sg:address":"75 Rees Ave",
    "sg:city":"Coorparoo",
    "sg:classifiers":[
        {
            "category":"Professional",
            "subcategory":"Art Services",
            "type":"Services"
        }
    ],
    "sg:phone":"+61 7 3397 5690",
    "sg:postcode":"4151",
    "sg:province":"QLD",
    "sg:tags":[
        "interior",
        "designer"
    ],
    "wof:name":"KDW Commercial Design",
    "wof:placetype":"venue"
},
  "geometry": {"coordinates":[153.05723571799999,-27.5012054443],"type":"Point"}
}