{
  "type": "Feature",
  "properties": {
    "iso:country":"AU",
    "sg:address":"392 Seaview Rd",
    "sg:city":"Henley Beach",
    "sg:classifiers":[
        {
            "category":"Manufacturing",
            "subcategory":"Tools & Machinery",
            "type":"Manufacturing & Wholesale Goods"
        }
    ],
    "sg:phone":"+61 1300 768 038",
    "sg:postcode":"5022",
    "sg:province":"SA",
    "sg:tags":[
        "equipment",
        "scale",
        "weighing"
    ],
    "wof:name":"Micro-strain Technology P/L",
    "wof:placetype":"venue"
},
  "geometry": {"coordinates":[138.495193481,-34.9220352173],"type":"Point"}
}