{
  "type": "Feature",
  "properties": {
    "iso:country":"AU",
    "sg:address":"24- 26 Brown St",
    "sg:city":"East Perth",
    "sg:classifiers":[
        {
            "category":"Retail",
            "subcategory":"Auto Repair",
            "type":"Services"
        }
    ],
    "sg:phone":"+61 8 9325 4686",
    "sg:postcode":"6004",
    "sg:province":"WA",
    "sg:tags":[
        "beater",
        "painter",
        "panel"
    ],
    "wof:name":"A Nova Smash Repairs",
    "wof:placetype":"venue"
},
  "geometry": {"coordinates":[115.877403259,-31.9508419037],"type":"Point"}
}