{
  "type": "Feature",
  "properties": {
    "addr:full":"Shop 10 Dampier Arcade Dampier WA 6713",
    "addr:housenumber":"shop 10",
    "addr:postcode":"6713",
    "addr:street":"Dampier Arcade",
    "iso:country":"AU",
    "sg:address":"Shop 10 Dampier Arcade",
    "sg:city":"Dampier",
    "sg:classifiers":[
        {
            "category":"Professional",
            "subcategory":"Secretarial Services",
            "type":"Services"
        }
    ],
    "sg:phone":"+61 8 9183 1858",
    "sg:postcode":"6713",
    "sg:province":"WA",
    "sg:tags":[
        "typing"
    ],
    "wof:name":"Secretarial & Administrative Support Systems",
    "wof:placetype":"venue"
},
  "geometry": {"coordinates":[116.711601257,-20.6621799469],"type":"Point"}
}