{
  "type": "Feature",
  "properties": {
    "addr:full":"1485 Goodwood Rd Childers QLD 4660",
    "addr:housenumber":"1485",
    "addr:postcode":"4660",
    "addr:street":"Goodwood Rd",
    "iso:country":"AU",
    "sg:address":"1485 Goodwood Rd",
    "sg:city":"Childers",
    "sg:classifiers":[
        {
            "category":"Home & Garden",
            "subcategory":"Garden Supply",
            "type":"Retail Goods"
        }
    ],
    "sg:phone":"+61 7 4126 8233",
    "sg:postcode":"4660",
    "sg:province":"QLD",
    "sg:tags":[
        "landscape"
    ],
    "wof:name":"Paverock Quarries",
    "wof:placetype":"venue"
},
  "geometry": {"coordinates":[152.37345886200001,-25.1591777802],"type":"Point"}
}