{
  "type": "Feature",
  "properties": {
    "addr:full":"2814- 2818 Logan Rd Underwood QLD 4119",
    "addr:housenumber":"2814 2818",
    "addr:postcode":"4119",
    "addr:street":"Logan Rd",
    "iso:country":"AU",
    "sg:address":"2814- 2818 Logan Rd",
    "sg:city":"Underwood",
    "sg:classifiers":[
        {
            "category":"Retail",
            "subcategory":"Car Wash",
            "type":"Services"
        }
    ],
    "sg:phone":"+61 1300 227 927",
    "sg:postcode":"4119",
    "sg:province":"QLD",
    "sg:tags":[
        "truck",
        "cleaning"
    ],
    "wof:name":"Carlovers Car Wash",
    "wof:placetype":"venue"
},
  "geometry": {"coordinates":[153.115722656,-27.6111278534],"type":"Point"}
}