{
  "type": "Feature",
  "properties": {
    "addr:full":"160 Pacific Hwy North Sydney NSW 2060",
    "addr:housenumber":"160",
    "addr:postcode":"2060",
    "addr:street":"Pacific Hwy",
    "iso:country":"AU",
    "sg:address":"160 Pacific Hwy",
    "sg:city":"North Sydney",
    "sg:classifiers":[
        {
            "category":"Real Estate",
            "subcategory":"Real Estate Agent",
            "type":"Services"
        }
    ],
    "sg:phone":"+61 2 9929 7575",
    "sg:postcode":"2060",
    "sg:province":"NSW",
    "wof:name":"Raine & Horne Country Lifestyle",
    "wof:placetype":"venue"
},
  "geometry": {"coordinates":[151.20542907699999,-33.8361816406],"type":"Point"}
}