{
  "type": "Feature",
  "properties": {
    "addr:full":"2/ 3 Wirth Tce Nerang QLD 4211",
    "addr:housenumber":"/ 3",
    "addr:postcode":"4211",
    "addr:street":"Wirth Tce",
    "iso:country":"AU",
    "sg:address":"2/ 3 Wirth Tce",
    "sg:city":"Nerang",
    "sg:classifiers":[
        {
            "category":"Personal",
            "type":"Services"
        }
    ],
    "sg:phone":"+61 7 5574 9597",
    "sg:postcode":"4211",
    "sg:province":"QLD",
    "sg:tags":[
        "dressmaker"
    ],
    "wof:name":"Heligr-Pyke Jessica",
    "wof:placetype":"venue"
},
  "geometry": {"coordinates":[153.34111023,-28.0144081116],"type":"Point"}
}