{
  "type": "Feature",
  "properties": {
    "addr:full":"29 Frederick St Valentine NSW 2280",
    "addr:housenumber":"29",
    "addr:postcode":"2280",
    "addr:street":"Frederick St",
    "iso:country":"AU",
    "sg:address":"29 Frederick St",
    "sg:city":"Valentine",
    "sg:classifiers":[
        {
            "category":"Real Estate",
            "subcategory":"Architect",
            "type":"Services"
        }
    ],
    "sg:phone":"+61 2 4942 7780",
    "sg:postcode":"2280",
    "sg:province":"NSW",
    "sg:tags":[
        "building",
        "designer"
    ],
    "wof:name":"Cook Russell",
    "wof:placetype":"venue"
},
  "geometry": {"coordinates":[151.63154602,-33.0136680603],"type":"Point"}
}