{
  "type": "Feature",
  "properties": {
    "iso:country":"AU",
    "sg:address":"89 Victoria Ave",
    "sg:city":"Albert Park",
    "sg:classifiers":[
        {
            "category":"Professional",
            "subcategory":"Art Services",
            "type":"Services"
        }
    ],
    "sg:phone":"+61 3 9693 2500",
    "sg:postcode":"3206",
    "sg:province":"VIC",
    "sg:tags":[
        "interior",
        "designer"
    ],
    "sg:website":"http://www.redretail.com.au",
    "wof:name":"Red Retail Environment Design",
    "wof:placetype":"venue"
},
  "geometry": {"coordinates":[144.95115699999999,-37.844463],"type":"Point"}
}