{
  "type": "Feature",
  "properties": {
    "iso:country":"AU",
    "sg:address":"2/61 Basedow Rd",
    "sg:city":"Tanunda",
    "sg:classifiers":[
        {
            "category":"Wholesale",
            "subcategory":"Electrical",
            "type":"Manufacturing & Wholesale Goods"
        }
    ],
    "sg:phone":"+61 8 8563 0644",
    "sg:postcode":"5352",
    "sg:province":"SA",
    "sg:tags":[
        "wholesaler"
    ],
    "wof:name":"M M Electrical Merchandising",
    "wof:placetype":"venue"
},
  "geometry": {"coordinates":[138.967407227,-34.5263214111],"type":"Point"}
}