{
  "type": "Feature",
  "properties": {
    "iso:country":"AU",
    "sg:address":"88 Hawken Drv",
    "sg:city":"St Lucia",
    "sg:classifiers":[
        {
            "category":"Organizations",
            "subcategory":"Professional Association",
            "type":"Services"
        }
    ],
    "sg:phone":"+61 1300 857 345",
    "sg:postcode":"4067",
    "sg:province":"QLD",
    "sg:tags":[
        "web",
        "internet"
    ],
    "wof:name":"Dot Zero",
    "wof:placetype":"venue"
},
  "geometry": {"coordinates":[153.004516602,-27.4940605164],"type":"Point"}
}