{
  "type": "Feature",
  "properties": {
    "iso:country":"AU",
    "sg:address":"521 Anzac Hwy",
    "sg:city":"Glenelg North",
    "sg:classifiers":[
        {
            "category":"Retail",
            "subcategory":"Event Space",
            "type":"Services"
        }
    ],
    "sg:phone":"+61 8 8294 2155",
    "sg:postcode":"5045",
    "sg:province":"SA",
    "sg:tags":[
        "venue",
        "reception",
        "wedding"
    ],
    "wof:name":"Adelaide International Motel",
    "wof:placetype":"venue"
},
  "geometry": {"coordinates":[138.519608,-34.976112],"type":"Point"}
}