{
  "type": "Feature",
  "properties": {
    "iso:country":"AU",
    "sg:address":"Albert Rd",
    "sg:city":"South Melbourne",
    "sg:classifiers":[
        {
            "category":"Organizations",
            "subcategory":"Labor Organization",
            "type":"Services"
        }
    ],
    "sg:phone":"+61 3 9699 4200",
    "sg:postcode":"3205",
    "sg:province":"VIC",
    "sg:tags":[
        "union"
    ],
    "wof:name":"Australian Federation Of Air Pilots",
    "wof:placetype":"venue"
},
  "geometry": {"coordinates":[144.963547,-37.838436],"type":"Point"}
}