{
  "type": "Feature",
  "properties": {
    "addr:full":"122 Stuart La Sunbury VIC 3429",
    "addr:housenumber":"122",
    "addr:postcode":"3429",
    "addr:street":"Stuart La Sunbury",
    "iso:country":"AU",
    "sg:address":"122 Stuart La",
    "sg:city":"Sunbury",
    "sg:classifiers":[
        {
            "category":"Building & Trades",
            "subcategory":"Landscaping Services",
            "type":"Services"
        }
    ],
    "sg:phone":"+61 419 552 257",
    "sg:postcode":"3429",
    "sg:province":"VIC",
    "sg:tags":[
        "designer",
        "landscape",
        "contractor"
    ],
    "wof:name":"McLandscapes",
    "wof:placetype":"venue"
},
  "geometry": {"coordinates":[144.71675109899999,-37.5809936523],"type":"Point"}
}