{
  "type": "Feature",
  "properties": {
    "iso:country":"AU",
    "sg:address":"45 McCormack St",
    "sg:city":"Curtin",
    "sg:classifiers":[
        {
            "category":"Insurance",
            "subcategory":"Insurance Agent",
            "type":"Services"
        }
    ],
    "sg:phone":"+61 2 6282 5576",
    "sg:postcode":"2605",
    "sg:province":"ACT",
    "sg:tags":[
        "broker"
    ],
    "wof:name":"Insurance Advisernet Australia Pty Limited",
    "wof:placetype":"venue"
},
  "geometry": {"coordinates":[149.07374572800001,-35.3301963806],"type":"Point"}
}