{
  "type": "Feature",
  "properties": {
    "addr:full":"Main Rd Huonville TAS 7109",
    "addr:postcode":"7109",
    "addr:street":"Main Rd",
    "iso:country":"AU",
    "sg:address":"Main Rd",
    "sg:city":"Huonville",
    "sg:classifiers":[
        {
            "category":"Home & Garden",
            "subcategory":"Building Materials",
            "type":"Retail Goods"
        }
    ],
    "sg:phone":"+61 3 6264 1255",
    "sg:postcode":"7109",
    "sg:province":"TAS",
    "sg:tags":[
        "fencing"
    ],
    "wof:name":"Clennetts Mitre 10",
    "wof:placetype":"venue"
},
  "geometry": {"coordinates":[147.04820251500001,-43.0312271118],"type":"Point"}
}