{
  "type": "Feature",
  "properties": {
    "addr:full":"4/ 3 Sunblest Crs Mt Druitt NSW 2770",
    "addr:housenumber":"/ 3",
    "addr:postcode":"2770",
    "addr:street":"Sunblest Crs Mt",
    "iso:country":"AU",
    "sg:address":"4/ 3 Sunblest Crs",
    "sg:city":"Mt Druitt",
    "sg:classifiers":[
        {
            "category":"Manufacturing",
            "subcategory":"Petroleum Products",
            "type":"Manufacturing & Wholesale Goods"
        }
    ],
    "sg:phone":"+61 2 9625 6868",
    "sg:postcode":"2770",
    "sg:province":"NSW",
    "sg:tags":[
        "lubricant"
    ],
    "wof:name":"Emarat Lubricants Australia & New Zealand",
    "wof:placetype":"venue"
},
  "geometry": {"coordinates":[150.81727600100001,-33.7652893066],"type":"Point"}
}