{
  "type": "Feature",
  "properties": {
    "addr:full":"PO Box 244 Essendon VIC 3040",
    "addr:postcode":"3040",
    "iso:country":"AU",
    "sg:address":"PO Box 244",
    "sg:city":"Essendon",
    "sg:classifiers":[
        {
            "category":"Manufacturing",
            "subcategory":"Food",
            "type":"Manufacturing & Wholesale Goods"
        }
    ],
    "sg:phone":"+61 1300 889 664",
    "sg:postcode":"3040",
    "sg:province":"VIC",
    "sg:tags":[
        "function",
        "catering"
    ],
    "wof:name":"MY SHOUT BEVERAGE CATERING",
    "wof:placetype":"venue"
},
  "geometry": {"coordinates":[144.90951538100001,-37.7515411377],"type":"Point"}
}