{
  "type": "Feature",
  "properties": {
    "addr:full":"Ruskin St Byron Bay NSW 2481",
    "addr:postcode":"2481",
    "addr:street":"Ruskin St",
    "iso:country":"AU",
    "sg:address":"Ruskin St",
    "sg:city":"Byron Bay",
    "sg:classifiers":[
        {
            "category":"Education",
            "subcategory":"School",
            "type":"Public Place"
        }
    ],
    "sg:phone":"+61 2 6685 6342",
    "sg:postcode":"2481",
    "sg:province":"NSW",
    "wof:name":"St Finbarr's Primary School",
    "wof:placetype":"venue"
},
  "geometry": {"coordinates":[153.613372803,-28.6490154266],"type":"Point"}
}