{
  "type": "Feature",
  "properties": {
    "iso:country":"AU",
    "sg:address":"17 Railway Rd",
    "sg:city":"Fairfield",
    "sg:classifiers":[
        {
            "category":"Farming",
            "subcategory":"Farm & Veterinary Services",
            "type":"Manufacturing & Wholesale Goods"
        }
    ],
    "sg:phone":"+61 7 3848 5290",
    "sg:postcode":"4103",
    "sg:province":"QLD",
    "sg:tags":[
        "agricultural",
        "advisory"
    ],
    "wof:name":"Pastoral & Feedlot Systems Australasia Pty Ltd",
    "wof:placetype":"venue"
},
  "geometry": {"coordinates":[153.02259826700001,-27.5120658875],"type":"Point"}
}