{
  "type": "Feature",
  "properties": {
    "iso:country":"AU",
    "sg:address":"359 Lang St",
    "sg:city":"Hay",
    "sg:classifiers":[
        {
            "category":"Health Services",
            "subcategory":"Health Practitioner",
            "type":"Services"
        }
    ],
    "sg:phone":"+61 2 6993 1957",
    "sg:postcode":"2711",
    "sg:province":"NSW",
    "sg:tags":[
        "naturopath"
    ],
    "wof:name":"Aldred Kerry H R",
    "wof:placetype":"venue"
},
  "geometry": {"coordinates":[144.845825195,-34.518081665],"type":"Point"}
}