{
  "type": "Feature",
  "properties": {
    "iso:country":"AU",
    "sg:address":"12 Apollo Crt",
    "sg:city":"Blackburn",
    "sg:classifiers":[
        {
            "category":"Utilities",
            "subcategory":"Sewage",
            "type":"Services"
        }
    ],
    "sg:phone":"+61 3 9894 2399",
    "sg:postcode":"3130",
    "sg:province":"VIC",
    "sg:tags":[
        "water",
        "waste",
        "treatment"
    ],
    "wof:name":"Ecotech Pty Ltd",
    "wof:placetype":"venue"
},
  "geometry": {"coordinates":[145.16207885700001,-37.8199882507],"type":"Point"}
}