{
  "type": "Feature",
  "properties": {
    "iso:country":"AU",
    "sg:address":"Mandurah Eye Centre, Suite 3, Doctors Consulting Suites, Peel Health Campus 110 Lakes Rd",
    "sg:city":"Mandurah",
    "sg:classifiers":[
        {
            "category":"Health Services",
            "subcategory":"Doctor",
            "type":"Services"
        }
    ],
    "sg:phone":"+61 8 9535 1300",
    "sg:postcode":"6210",
    "sg:province":"WA",
    "sg:tags":[
        "medical",
        "practitioner"
    ],
    "wof:name":"Taylor Graeme",
    "wof:placetype":"venue"
},
  "geometry": {"coordinates":[115.731133,-32.527493],"type":"Point"}
}