{
  "type": "Feature",
  "properties": {
    "iso:country":"AU",
    "sg:address":"Bailey centre 150 Pacific Hwy",
    "sg:city":"Coffs Harbour",
    "sg:classifiers":[
        {
            "category":"Communications",
            "subcategory":"Film & Video Production",
            "type":"Services"
        }
    ],
    "sg:phone":"+61 2 6652 7177",
    "sg:postcode":"2450",
    "sg:province":"NSW",
    "sg:tags":[
        "dvd",
        "library"
    ],
    "wof:name":"Video Ezy",
    "wof:placetype":"venue"
},
  "geometry": {"coordinates":[153.09053,-30.318281],"type":"Point"}
}