{
  "type": "Feature",
  "properties": {
    "addr:full":"17 Sylvaterre Crt Samford QLD 4520",
    "addr:housenumber":"17",
    "addr:postcode":"4520",
    "addr:street":"Sylvaterre Crt",
    "iso:country":"AU",
    "sg:address":"17 Sylvaterre Crt",
    "sg:city":"Samford",
    "sg:classifiers":[
        {
            "category":"Building & Trades",
            "subcategory":"Construction",
            "type":"Services"
        }
    ],
    "sg:phone":"+61 407 706 615",
    "sg:postcode":"4520",
    "sg:province":"QLD",
    "sg:tags":[
        "installation",
        "air conditioning"
    ],
    "wof:name":"Acme Air Conditioning",
    "wof:placetype":"venue"
},
  "geometry": {"coordinates":[152.90052800000001,-27.367252],"type":"Point"}
}