{
  "type": "Feature",
  "properties": {
    "addr:full":"60 Elizabeth St Melbourne VIC 3000",
    "addr:housenumber":"60",
    "addr:postcode":"3000",
    "addr:street":"Elizabeth St",
    "iso:country":"AU",
    "sg:address":"60 Elizabeth St",
    "sg:city":"Melbourne",
    "sg:classifiers":[
        {
            "category":"Manufacturing",
            "subcategory":"Textiles",
            "type":"Manufacturing & Wholesale Goods"
        }
    ],
    "sg:phone":"+61 3 9654 7677",
    "sg:postcode":"3000",
    "sg:province":"VIC",
    "sg:tags":[
        "knitted",
        "woven",
        "fabric"
    ],
    "wof:name":"Clegs Fabrics",
    "wof:placetype":"venue"
},
  "geometry": {"coordinates":[144.96446227999999,-37.8166885376],"type":"Point"}
}