{
  "type": "Feature",
  "properties": {
    "addr:full":"848 Ann St Fortitude Valley QLD 4006",
    "addr:housenumber":"848",
    "addr:postcode":"4006",
    "addr:street":"Ann St",
    "iso:country":"AU",
    "sg:address":"848 Ann St",
    "sg:city":"Fortitude Valley",
    "sg:classifiers":[
        {
            "category":"Building & Trades",
            "subcategory":"Locksmith",
            "type":"Services"
        }
    ],
    "sg:phone":"+61 7 3854 1154",
    "sg:postcode":"4006",
    "sg:province":"QLD",
    "sg:tags":[
        "lock"
    ],
    "wof:name":"Locksmiths H.A. Reed",
    "wof:placetype":"venue"
},
  "geometry": {"coordinates":[153.037872314,-27.4553775787],"type":"Point"}
}