{
  "type": "Feature",
  "properties": {
    "addr:full":"Shop 94 Macquarie Shopping Cntr North Ryde NSW 2113",
    "addr:housenumber":"shop 94",
    "addr:postcode":"2113",
    "addr:street":"Macquarie Shopping Cntr",
    "iso:country":"AU",
    "sg:address":"Shop 94 Macquarie Shopping Cntr",
    "sg:city":"North Ryde",
    "sg:classifiers":[
        {
            "category":"Fast Food",
            "type":"Food & Drink"
        }
    ],
    "sg:phone":"+61 2 9878 5848",
    "sg:postcode":"2113",
    "sg:province":"NSW",
    "sg:tags":[
        "away",
        "take"
    ],
    "wof:name":"KFC",
    "wof:placetype":"venue"
},
  "geometry": {"coordinates":[151.11436462399999,-33.7759208679],"type":"Point"}
}