{
  "type": "Feature",
  "properties": {
    "addr:full":"22 Hustler St Dianella WA 6059",
    "addr:housenumber":"22",
    "addr:postcode":"6059",
    "addr:street":"Hustler St",
    "iso:country":"AU",
    "sg:address":"22 Hustler St",
    "sg:city":"Dianella",
    "sg:classifiers":[
        {
            "category":"Professional",
            "subcategory":"Computer Services",
            "type":"Services"
        }
    ],
    "sg:phone":"+61 8 9276 6362",
    "sg:postcode":"6059",
    "sg:province":"WA",
    "sg:tags":[
        "repairs",
        "upgrade",
        "equipment"
    ],
    "wof:name":"Computer Bugs",
    "wof:placetype":"venue"
},
  "geometry": {"coordinates":[115.866828919,-31.8874015808],"type":"Point"}
}