{
  "type": "Feature",
  "properties": {
    "addr:full":"Lot 6 Somer St Dalby QLD 4405",
    "addr:postcode":"4405",
    "addr:street":"Somer St",
    "iso:country":"AU",
    "sg:address":"Lot 6 Somer St",
    "sg:city":"Dalby",
    "sg:classifiers":[
        {
            "category":"Farming",
            "subcategory":"Crops",
            "type":"Manufacturing & Wholesale Goods"
        }
    ],
    "sg:phone":"+61 7 4662 6033",
    "sg:postcode":"4405",
    "sg:province":"QLD",
    "sg:tags":[
        "warehousing"
    ],
    "wof:name":"Dunavant Warehousing Pty Ltd",
    "wof:placetype":"venue"
},
  "geometry": {"coordinates":[151.25738525400001,-27.1699829102],"type":"Point"}
}