{
  "type": "Feature",
  "properties": {
    "addr:full":"13 Fitzroy St Newtown NSW 2042",
    "addr:housenumber":"13",
    "addr:postcode":"2042",
    "addr:street":"Fitzroy St",
    "iso:country":"AU",
    "sg:address":"13 Fitzroy St",
    "sg:city":"Newtown",
    "sg:classifiers":[
        {
            "category":"Real Estate",
            "subcategory":"Real Estate Agent",
            "type":"Services"
        }
    ],
    "sg:phone":"+61 2 9519 6466",
    "sg:postcode":"2042",
    "sg:province":"NSW",
    "sg:tags":[
        "export"
    ],
    "wof:name":"Australian Marketing Channels Pty Ltd",
    "wof:placetype":"venue"
},
  "geometry": {"coordinates":[151.185959,-33.893562],"type":"Point"}
}