{
  "type": "Feature",
  "properties": {
    "addr:full":"Unit 1, 252 Sydney Rd Balgowlah NSW 2093",
    "addr:housenumber":"252",
    "addr:postcode":"2093",
    "addr:street":"Sydney Rd",
    "iso:country":"AU",
    "sg:address":"Unit 1, 252 Sydney Rd",
    "sg:city":"Balgowlah",
    "sg:classifiers":[
        {
            "category":"Shopping",
            "subcategory":"Baby Store",
            "type":"Retail Goods"
        }
    ],
    "sg:phone":"+61 2 9948 0640",
    "sg:postcode":"2093",
    "sg:province":"NSW",
    "sg:tags":[
        "wear"
    ],
    "wof:name":"Hill St Baby",
    "wof:placetype":"venue"
},
  "geometry": {"coordinates":[151.265533447,-33.7945518494],"type":"Point"}
}