{
  "type": "Feature",
  "properties": {
    "addr:full":"Shop 6 185 Military Rd Neutral Bay NSW 2089",
    "addr:housenumber":"shop 6 185",
    "addr:postcode":"2089",
    "addr:street":"Military Rd",
    "iso:country":"AU",
    "sg:address":"Shop 6 185 Military Rd",
    "sg:city":"Neutral Bay",
    "sg:classifiers":[
        {
            "category":"Travel",
            "subcategory":"Travel Agent",
            "type":"Entertainment"
        }
    ],
    "sg:phone":"+61 13 18 66",
    "sg:postcode":"2089",
    "sg:province":"NSW",
    "sg:tags":[
        "consultant"
    ],
    "wof:name":"Flight Centre",
    "wof:placetype":"venue"
},
  "geometry": {"coordinates":[151.22286987300001,-33.8316841125],"type":"Point"}
}