{
  "type": "Feature",
  "properties": {
    "addr:full":"2 Fisher St Silverwater NSW 2128",
    "addr:housenumber":"2",
    "addr:postcode":"2128",
    "addr:street":"Fisher St",
    "iso:country":"AU",
    "sg:address":"2 Fisher St",
    "sg:city":"Silverwater",
    "sg:classifiers":[
        {
            "category":"Wholesale",
            "subcategory":"Furniture",
            "type":"Manufacturing & Wholesale Goods"
        }
    ],
    "sg:phone":"+61 2 9737 9025",
    "sg:postcode":"2128",
    "sg:province":"NSW",
    "sg:tags":[
        "wholesaler",
        "mfrs"
    ],
    "wof:name":"Sac Furniture Pty Ltd",
    "wof:placetype":"venue"
},
  "geometry": {"coordinates":[151.03956604000001,-33.8353881836],"type":"Point"}
}