{
  "type": "Feature",
  "properties": {
    "iso:country":"AU",
    "sg:address":"60 Collingwood St",
    "sg:city":"Paddington",
    "sg:classifiers":[
        {
            "category":"Museum",
            "subcategory":"Art Museum",
            "type":"Entertainment"
        }
    ],
    "sg:phone":"+61 7 3368 3371",
    "sg:postcode":"4064",
    "sg:province":"QLD",
    "sg:tags":[
        "antique",
        "fine",
        "valuer"
    ],
    "wof:name":"Christine Tilley (Valuer-Books)",
    "wof:placetype":"venue"
},
  "geometry": {"coordinates":[152.99501037600001,-27.4556427002],"type":"Point"}
}