{
  "type": "Feature",
  "properties": {
    "iso:country":"AU",
    "sg:address":"59 Goodwood Rd",
    "sg:city":"Wayville",
    "sg:classifiers":[
        {
            "category":"Shopping",
            "subcategory":"Stationery & Office Supplies",
            "type":"Retail Goods"
        }
    ],
    "sg:phone":"+61 8 8272 0866",
    "sg:postcode":"5034",
    "sg:province":"SA",
    "sg:tags":[
        "equipment",
        "display",
        "exhibition"
    ],
    "wof:name":"Projection Graphics Signs & Displays Pty Ltd",
    "wof:placetype":"venue"
},
  "geometry": {"coordinates":[138.589553833,-34.9472389221],"type":"Point"}
}