{
  "type": "Feature",
  "properties": {
    "iso:country":"AU",
    "sg:address":"3 Council St",
    "sg:city":"Willoughby",
    "sg:classifiers":[
        {
            "category":"Professional",
            "subcategory":"Computer Services",
            "type":"Services"
        }
    ],
    "sg:phone":"+61 2 9967 4073",
    "sg:postcode":"2068",
    "sg:province":"NSW",
    "sg:tags":[
        "consultant",
        "system"
    ],
    "wof:name":"Software Project Assist Pty Ltd",
    "wof:placetype":"venue"
},
  "geometry": {"coordinates":[151.201004028,-33.7973670959],"type":"Point"}
}