{
  "type": "Feature",
  "properties": {
    "iso:country":"AU",
    "sg:address":"PO Box 111",
    "sg:city":"Belmore",
    "sg:classifiers":[
        {
            "category":"Building & Trades",
            "subcategory":"Pest Control",
            "type":"Services"
        }
    ],
    "sg:phone":"+61 2 9703 2667",
    "sg:postcode":"2192",
    "sg:province":"NSW",
    "wof:name":"Knock Down Pest Control",
    "wof:placetype":"venue"
},
  "geometry": {"coordinates":[151.08824200000001,-33.91946],"type":"Point"}
}