{
  "type": "Feature",
  "properties": {
    "iso:country":"AU",
    "sg:address":"PO Box 733",
    "sg:city":"Gymea",
    "sg:classifiers":[
        {
            "category":"Shopping",
            "subcategory":"Pets & Pet Supplies",
            "type":"Retail Goods"
        }
    ],
    "sg:phone":"+61 1300 735 135",
    "sg:postcode":"2227",
    "sg:province":"NSW",
    "sg:tags":[
        "food"
    ],
    "wof:name":"Central Bark",
    "wof:placetype":"venue"
},
  "geometry": {"coordinates":[151.08496093799999,-34.0353317261],"type":"Point"}
}