{
  "type": "Feature",
  "properties": {
    "addr:full":"25 Acacia St Eagle Farm QLD 4009",
    "addr:housenumber":"25",
    "addr:postcode":"4009",
    "addr:street":"Acacia St",
    "iso:country":"AU",
    "sg:address":"25 Acacia St",
    "sg:city":"Eagle Farm",
    "sg:classifiers":[
        {
            "category":"Retail",
            "subcategory":"Auto Repair",
            "type":"Services"
        }
    ],
    "sg:phone":"+61 7 3268 4188",
    "sg:postcode":"4009",
    "sg:province":"QLD",
    "sg:tags":[
        "wheel",
        "balancing",
        "alignment"
    ],
    "wof:name":"Big Wheels Truck Alignment Nth Brisbane",
    "wof:placetype":"venue"
},
  "geometry": {"coordinates":[153.08355712900001,-27.4305076599],"type":"Point"}
}