{
  "type": "Feature",
  "properties": {
    "addr:full":"9 Barellan St Caves Beach NSW 2281",
    "addr:housenumber":"9",
    "addr:postcode":"2281",
    "addr:street":"Barellan St",
    "iso:country":"AU",
    "sg:address":"9 Barellan St",
    "sg:city":"Caves Beach",
    "sg:classifiers":[
        {
            "category":"Retail",
            "subcategory":"Photofinishing",
            "type":"Services"
        }
    ],
    "sg:phone":"+61 407 906 607",
    "sg:postcode":"2281",
    "sg:province":"NSW",
    "sg:tags":[
        "refractory"
    ],
    "wof:name":"Nothrop Refractories Management",
    "wof:placetype":"venue"
},
  "geometry": {"coordinates":[151.644287109,-33.1117401123],"type":"Point"}
}