{
  "type": "Feature",
  "properties": {
    "addr:full":"244a Canning Hwy Como WA 6152",
    "addr:housenumber":"244a",
    "addr:postcode":"6152",
    "addr:street":"Canning Hwy",
    "iso:country":"AU",
    "sg:address":"244a Canning Hwy",
    "sg:city":"Como",
    "sg:classifiers":[
        {
            "category":"Building & Trades",
            "subcategory":"Cleaning & Sanitation",
            "type":"Services"
        }
    ],
    "sg:phone":"+61 1300 130 021",
    "sg:postcode":"6152",
    "sg:province":"WA",
    "sg:tags":[
        "industrial",
        "commercial",
        "contractor"
    ],
    "wof:name":"Mrs Mop",
    "wof:placetype":"venue"
},
  "geometry": {"coordinates":[115.870712,-31.988613],"type":"Point"}
}