{
  "type": "Feature",
  "properties": {
    "addr:full":"Cnr North & Railway Sts Gatton QLD 4343",
    "addr:postcode":"4343",
    "addr:street":"Cnr",
    "iso:country":"AU",
    "sg:address":"Cnr North & Railway Sts",
    "sg:city":"Gatton",
    "sg:classifiers":[
        {
            "category":"Banks & Credit Unions",
            "subcategory":"Financial Services",
            "type":"Services"
        }
    ],
    "sg:phone":"+61 7 5462 1211",
    "sg:postcode":"4343",
    "sg:province":"QLD",
    "sg:tags":[
        "financier"
    ],
    "wof:name":"CBFC Limited",
    "wof:placetype":"venue"
},
  "geometry": {"coordinates":[152.271392822,-27.5677967072],"type":"Point"}
}