{
  "type": "Feature",
  "properties": {
    "iso:country":"AU",
    "sg:address":"Shops 4 & 5 Centro Springwood Shopping Centre, Cnr Fitzgerlad Ave & Rochedale Rd",
    "sg:city":"Springwood",
    "sg:classifiers":[
        {
            "category":"Fast Food",
            "type":"Food & Drink"
        }
    ],
    "sg:phone":"+61 7 3451 6744",
    "sg:postcode":"4127",
    "sg:province":"QLD",
    "sg:tags":[
        "away",
        "take"
    ],
    "wof:name":"Domino's Pizza",
    "wof:placetype":"venue"
},
  "geometry": {"coordinates":[153.12535095199999,-27.613035202],"type":"Point"}
}