{
  "type": "Feature",
  "properties": {
    "addr:full":"Old Melbourne Rd Dunnstown VIC 3352",
    "addr:postcode":"3352",
    "addr:street":"Old Melbourne Rd",
    "iso:country":"AU",
    "sg:address":"Old Melbourne Rd",
    "sg:city":"Dunnstown",
    "sg:classifiers":[
        {
            "category":"Utilities",
            "subcategory":"Electric",
            "type":"Services"
        }
    ],
    "sg:phone":"+61 407 847 456",
    "sg:postcode":"3352",
    "sg:province":"VIC",
    "sg:tags":[
        "electrical",
        "contractor"
    ],
    "wof:name":"Dash John Electrical Contractor",
    "wof:placetype":"venue"
},
  "geometry": {"coordinates":[143.96867399999999,-37.591003],"type":"Point"}
}