{
  "type": "Feature",
  "properties": {
    "addr:full":"Broughton Drv Belmont VIC 3216",
    "addr:postcode":"3216",
    "addr:street":"Broughton Drv",
    "iso:country":"AU",
    "sg:address":"Broughton Drv",
    "sg:city":"Belmont",
    "sg:classifiers":[
        {
            "category":"Education",
            "subcategory":"Kindergarten",
            "type":"Public Place"
        }
    ],
    "sg:phone":"+61 3 5241 1565",
    "sg:postcode":"3216",
    "sg:province":"VIC",
    "sg:tags":[
        "pre-schools"
    ],
    "wof:name":"Williams House Kindergarten",
    "wof:placetype":"venue"
},
  "geometry": {"coordinates":[144.32469177199999,-38.1899604797],"type":"Point"}
}