{
  "type": "Feature",
  "properties": {
    "addr:full":"72 Melbourne St Riverstone NSW 2765",
    "addr:housenumber":"72",
    "addr:postcode":"2765",
    "addr:street":"Melbourne St",
    "iso:country":"AU",
    "sg:address":"72 Melbourne St",
    "sg:city":"Riverstone",
    "sg:classifiers":[
        {
            "category":"Professional",
            "subcategory":"Engineering",
            "type":"Services"
        }
    ],
    "sg:phone":"+61 2 9627 5004",
    "sg:postcode":"2765",
    "sg:province":"NSW",
    "sg:tags":[
        "manufacturing",
        "engineer"
    ],
    "wof:name":"H & B Plant Repairs Pty Ltd",
    "wof:placetype":"venue"
},
  "geometry": {"coordinates":[150.86044311500001,-33.6620445251],"type":"Point"}
}