{
  "type": "Feature",
  "properties": {
    "iso:country":"AU",
    "sg:address":"PO Box 480",
    "sg:city":"Castle Hill",
    "sg:classifiers":[
        {
            "category":"Health Services",
            "subcategory":"Doctor",
            "type":"Services"
        }
    ],
    "sg:phone":"+61 2 9369 9836",
    "sg:postcode":"1765",
    "sg:province":"NSW",
    "sg:tags":[
        "nurse",
        "nursing"
    ],
    "wof:name":"ABC Medisafe Australia",
    "wof:placetype":"venue"
},
  "geometry": {"coordinates":[151.01724200000001,-33.730858],"type":"Point"}
}