{
  "type": "Feature",
  "properties": {
    "iso:country":"AU",
    "sg:address":"Mc Dermott Ave",
    "sg:city":"Mooroolbark",
    "sg:classifiers":[
        {
            "category":"Sports & Exercise",
            "subcategory":"Sports Center",
            "type":"Entertainment"
        }
    ],
    "sg:phone":"+61 3 9726 4939",
    "sg:postcode":"3138",
    "sg:province":"VIC",
    "sg:tags":[
        "ground"
    ],
    "wof:name":"Mooroolbark Netball Centre",
    "wof:placetype":"venue"
},
  "geometry": {"coordinates":[145.31617736800001,-37.7770652771],"type":"Point"}
}