{
  "type": "Feature",
  "properties": {
    "addr:full":"Shop G085 Bayside Shopping Centre, 28 Beach Frankston VIC 3199",
    "addr:housenumber":"g085;28",
    "addr:postcode":"3199",
    "addr:street":"Beach",
    "iso:country":"AU",
    "sg:address":"Shop G085 Bayside Shopping Centre, 28",
    "sg:city":"Beach Frankston",
    "sg:classifiers":[
        {
            "category":"Shopping",
            "subcategory":"Computers & Home Electronics",
            "type":"Retail Goods"
        }
    ],
    "sg:phone":"+61 3 9770 6604",
    "sg:postcode":"3199",
    "sg:province":"VIC",
    "sg:tags":[
        "equipment",
        "part",
        "electronic"
    ],
    "wof:name":"Tandy",
    "wof:placetype":"venue"
},
  "geometry": {"coordinates":[145.08114624000001,-38.0043640137],"type":"Point"}
}