{
  "type": "Feature",
  "properties": {
    "addr:full":"25 Manchester Rd Taringa QLD 4068",
    "addr:housenumber":"25",
    "addr:postcode":"4068",
    "addr:street":"Manchester Rd",
    "iso:country":"AU",
    "sg:address":"25 Manchester Rd",
    "sg:city":"Taringa",
    "sg:classifiers":[
        {
            "category":"Professional",
            "subcategory":"Art Services",
            "type":"Services"
        }
    ],
    "sg:phone":"+61 7 3720 9280",
    "sg:postcode":"4068",
    "sg:province":"QLD",
    "sg:tags":[
        "decorator",
        "painter"
    ],
    "wof:name":"Boriss Painting Service",
    "wof:placetype":"venue"
},
  "geometry": {"coordinates":[152.97512817399999,-27.4932479858],"type":"Point"}
}