{
  "type": "Feature",
  "properties": {
    "iso:country":"AU",
    "sg:address":"Vittoria Rd",
    "sg:city":"Picton",
    "sg:classifiers":[
        {
            "category":"Education",
            "subcategory":"School",
            "type":"Public Place"
        }
    ],
    "sg:phone":"+61 8 9725 6308",
    "sg:postcode":"6229",
    "sg:province":"WA",
    "wof:name":"Bunbury Community School",
    "wof:placetype":"venue"
},
  "geometry": {"coordinates":[115.680412,-33.3451],"type":"Point"}
}