{
  "type": "Feature",
  "properties": {
    "addr:full":"7 Nicholas Rd Wanneroo WA 6065",
    "addr:housenumber":"7",
    "addr:postcode":"6065",
    "addr:street":"Nicholas Rd",
    "iso:country":"AU",
    "sg:address":"7 Nicholas Rd",
    "sg:city":"Wanneroo",
    "sg:classifiers":[
        {
            "category":"Health Services",
            "subcategory":"Health Practitioner",
            "type":"Services"
        }
    ],
    "sg:phone":"+61 8 9405 1214",
    "sg:postcode":"6065",
    "sg:province":"WA",
    "sg:tags":[
        "naturopath"
    ],
    "wof:name":"Magnetic Health Clinics",
    "wof:placetype":"venue"
},
  "geometry": {"coordinates":[115.836952209,-31.7699642181],"type":"Point"}
}