{
  "type": "Feature",
  "properties": {
    "iso:country":"AU",
    "sg:address":"Unit 1, 16 Common Rd",
    "sg:city":"Muswellbrook",
    "sg:phone":"+61 2 6543 3688",
    "sg:postcode":"2333",
    "sg:province":"NSW",
    "wof:name":"Hunter Valley Filter Sales Pty Ltd",
    "wof:placetype":"venue"
},
  "geometry": {"coordinates":[150.905029297,-32.263874054],"type":"Point"}
}