{
  "type": "Feature",
  "properties": {
    "iso:country":"AU",
    "sg:address":"5 Yarral Ave",
    "sg:city":"Tamworth",
    "sg:classifiers":[
        {
            "category":"Farming",
            "subcategory":"Farm & Veterinary Services",
            "type":"Manufacturing & Wholesale Goods"
        }
    ],
    "sg:phone":"+61 2 6766 3196",
    "sg:postcode":"2340",
    "sg:province":"NSW",
    "sg:tags":[
        "agricultural",
        "advisory"
    ],
    "wof:name":"Hely W B",
    "wof:placetype":"venue"
},
  "geometry": {"coordinates":[150.94192504899999,-31.0855808258],"type":"Point"}
}