{
  "type": "Feature",
  "properties": {
    "addr:full":"Lvl 1, 188 Edward St Brisbane QLD 4000",
    "addr:housenumber":"188",
    "addr:postcode":"4000",
    "addr:street":"Edward St",
    "iso:country":"AU",
    "sg:address":"Lvl 1, 188 Edward St",
    "sg:city":"Brisbane",
    "sg:classifiers":[
        {
            "category":"Personal",
            "subcategory":"Beauty Salon",
            "type":"Services"
        }
    ],
    "sg:phone":"+61 7 3210 1727",
    "sg:postcode":"4000",
    "sg:province":"QLD",
    "sg:tags":[
        "hairdresser"
    ],
    "wof:name":"Toni & Guy Hairdressing",
    "wof:placetype":"venue"
},
  "geometry": {"coordinates":[153.02734375,-27.4689483643],"type":"Point"}
}