{
  "type": "Feature",
  "properties": {
    "addr:full":"Johnny Chi La Broome WA 6725",
    "addr:postcode":"6725",
    "iso:country":"AU",
    "sg:address":"Johnny Chi La",
    "sg:city":"Broome",
    "sg:classifiers":[
        {
            "category":"Cafe",
            "type":"Food & Drink"
        }
    ],
    "sg:phone":"+61 8 9192 2060",
    "sg:postcode":"6725",
    "sg:province":"WA",
    "wof:name":"Shady Lane Cafe",
    "wof:placetype":"venue"
},
  "geometry": {"coordinates":[122.677589416,-18.2141704559],"type":"Point"}
}