{
  "type": "Feature",
  "properties": {
    "addr:full":"4- 6 Isa Way Boronia VIC 3155",
    "addr:housenumber":"6",
    "addr:postcode":"3155",
    "addr:street":"Isa Way",
    "iso:country":"AU",
    "sg:address":"4- 6",
    "sg:city":"Isa Way Boronia",
    "sg:classifiers":[
        {
            "category":"Government",
            "subcategory":"Department Of Motor Vehicles",
            "type":"Public Place"
        }
    ],
    "sg:phone":"+61 3 9720 5533",
    "sg:postcode":"3155",
    "sg:province":"VIC",
    "sg:tags":[
        "wholesaler",
        "mfrs",
        "accessory"
    ],
    "wof:name":"Autosafe Industries",
    "wof:placetype":"venue"
},
  "geometry": {"coordinates":[145.295654297,-37.8372154236],"type":"Point"}
}