{
  "type": "Feature",
  "properties": {
    "iso:country":"AU",
    "sg:address":"12 Boyd St",
    "sg:city":"Geraldton",
    "sg:classifiers":[
        {
            "category":"Home & Garden",
            "subcategory":"Building Materials",
            "type":"Retail Goods"
        }
    ],
    "sg:phone":"+61 8 9921 6411",
    "sg:postcode":"6530",
    "sg:province":"WA",
    "sg:tags":[
        "merchant",
        "glass",
        "glazier"
    ],
    "wof:name":"Wright-Way Glass & Mirrors",
    "wof:placetype":"venue"
},
  "geometry": {"coordinates":[114.63156890899999,-28.7529239655],"type":"Point"}
}