{
  "type": "Feature",
  "properties": {
    "iso:country":"AU",
    "sg:address":"14 Boree Pl",
    "sg:city":"Jerrabomberra",
    "sg:classifiers":[
        {
            "category":"Building & Trades",
            "subcategory":"Construction",
            "type":"Services"
        }
    ],
    "sg:phone":"+61 417 668 835",
    "sg:postcode":"2619",
    "sg:province":"NSW",
    "sg:tags":[
        "renovation",
        "alterations",
        "extension",
        "contractor"
    ],
    "wof:name":"Brumec Building Services",
    "wof:placetype":"venue"
},
  "geometry": {"coordinates":[149.20924377399999,-35.379360199],"type":"Point"}
}