{
  "type": "Feature",
  "properties": {
    "addr:full":"25 Oakmont Crs Albany Creek QLD 4035",
    "addr:housenumber":"25",
    "addr:postcode":"4035",
    "addr:street":"Oakmont Crs",
    "iso:country":"AU",
    "sg:address":"25 Oakmont Crs",
    "sg:city":"Albany Creek",
    "sg:classifiers":[
        {
            "category":"Home & Garden",
            "subcategory":"Building Materials",
            "type":"Retail Goods"
        }
    ],
    "sg:phone":"+61 418 726 097",
    "sg:postcode":"4035",
    "sg:province":"QLD",
    "sg:tags":[
        "lawn",
        "cutting",
        "maintenance"
    ],
    "wof:name":"A Jason Milton Landscape Care",
    "wof:placetype":"venue"
},
  "geometry": {"coordinates":[152.96537799999999,-27.34589],"type":"Point"}
}