{
  "type": "Feature",
  "properties": {
    "iso:country":"AU",
    "sg:address":"37- 39 Aster Ave",
    "sg:city":"Carrum Downs",
    "sg:classifiers":[
        {
            "category":"Manufacturing",
            "subcategory":"Building Materials",
            "type":"Manufacturing & Wholesale Goods"
        }
    ],
    "sg:phone":"+61 3 9775 0500",
    "sg:postcode":"3201",
    "sg:province":"VIC",
    "sg:tags":[
        "adhesive",
        "tape"
    ],
    "wof:name":"Berbec Pty Ltd",
    "wof:placetype":"venue"
},
  "geometry": {"coordinates":[145.165604,-38.100956],"type":"Point"}
}