{
  "type": "Feature",
  "properties": {
    "addr:full":"53 Barkly St Mornington VIC 3931",
    "addr:housenumber":"53",
    "addr:postcode":"3931",
    "addr:street":"Barkly St",
    "iso:country":"AU",
    "sg:address":"53 Barkly St",
    "sg:city":"Mornington",
    "sg:classifiers":[
        {
            "category":"Retail",
            "subcategory":"Event Space",
            "type":"Services"
        }
    ],
    "sg:phone":"+61 3 5975 9955",
    "sg:postcode":"3931",
    "sg:province":"VIC",
    "sg:tags":[
        "venue",
        "reception",
        "wedding"
    ],
    "wof:name":"The Church On Barkly",
    "wof:placetype":"venue"
},
  "geometry": {"coordinates":[145.038406372,-38.2215003967],"type":"Point"}
}