{
  "type": "Feature",
  "properties": {
    "addr:full":"Unit 4, 83 Lysaght St Mitchell ACT 2911",
    "addr:housenumber":"83",
    "addr:postcode":"2911",
    "addr:street":"Lysaght St",
    "iso:country":"AU",
    "sg:address":"Unit 4, 83 Lysaght St",
    "sg:city":"Mitchell",
    "sg:classifiers":[
        {
            "category":"Home & Garden",
            "subcategory":"Carpets & Floor Coverings",
            "type":"Retail Goods"
        }
    ],
    "sg:phone":"+61 2 6255 7789",
    "sg:postcode":"2911",
    "sg:province":"ACT",
    "sg:tags":[
        "wood"
    ],
    "wof:name":"Kinxon Timber Floor",
    "wof:placetype":"venue"
},
  "geometry": {"coordinates":[149.14137268100001,-35.2156219482],"type":"Point"}
}