{
  "type": "Feature",
  "properties": {
    "addr:full":"10 Beddingfield St Bunbury WA 6230",
    "addr:housenumber":"10",
    "addr:postcode":"6230",
    "addr:street":"Beddingfield St",
    "iso:country":"AU",
    "sg:address":"10 Beddingfield St",
    "sg:city":"Bunbury",
    "sg:classifiers":[
        {
            "category":"Home & Garden",
            "subcategory":"Building Materials",
            "type":"Retail Goods"
        }
    ],
    "sg:phone":"+61 8 9725 7700",
    "sg:postcode":"6230",
    "sg:province":"WA",
    "sg:tags":[
        "skylight"
    ],
    "wof:name":"Bunbury Home Improvements",
    "wof:placetype":"venue"
},
  "geometry": {"coordinates":[115.67910000000001,-33.355293],"type":"Point"}
}