{
  "type": "Feature",
  "properties": {
    "addr:full":"Access Medical Cntr,Knox Towerpoint, 1 Rezes Wantirna South VIC 3152",
    "addr:housenumber":"1",
    "addr:postcode":"3152",
    "addr:street":"Towerpoint",
    "iso:country":"AU",
    "sg:address":"Access Medical Cntr,Knox Towerpoint, 1 Rezes",
    "sg:city":"Wantirna South",
    "sg:classifiers":[
        {
            "category":"Health Services",
            "subcategory":"Health Practitioner",
            "type":"Services"
        }
    ],
    "sg:phone":"+61 3 9887 0211",
    "sg:postcode":"3152",
    "sg:province":"VIC",
    "sg:tags":[
        "physiotherapist"
    ],
    "wof:name":"Lakewood Sports & Spinal Physiotherapy",
    "wof:placetype":"venue"
},
  "geometry": {"coordinates":[145.24333190900001,-37.8709220886],"type":"Point"}
}