{
  "type": "Feature",
  "properties": {
    "addr:full":"Unit 2, 60- 70 Mahoneys Rd Thomastown VIC 3074",
    "addr:housenumber":"60 70",
    "addr:postcode":"3074",
    "addr:street":"Mahoneys Rd",
    "iso:country":"AU",
    "sg:address":"Unit 2, 60- 70 Mahoneys Rd",
    "sg:city":"Thomastown",
    "sg:classifiers":[
        {
            "category":"Industrial Area",
            "type":"Public Place"
        }
    ],
    "sg:phone":"+61 3 9460 5811",
    "sg:postcode":"3074",
    "sg:province":"VIC",
    "sg:tags":[
        "protective",
        "clothing"
    ],
    "wof:name":"Stylecorp Corporate Wear",
    "wof:placetype":"venue"
},
  "geometry": {"coordinates":[145.00265502900001,-37.6937217712],"type":"Point"}
}