{
  "type": "Feature",
  "properties": {
    "iso:country":"AU",
    "sg:address":"180 Main St",
    "sg:city":"Bairnsdale",
    "sg:classifiers":[
        {
            "category":"Real Estate",
            "subcategory":"Real Estate Services",
            "type":"Services"
        }
    ],
    "sg:phone":"+61 3 5153 2929",
    "sg:postcode":"3875",
    "sg:province":"VIC",
    "sg:tags":[
        "listing"
    ],
    "wof:name":"John Hansen Real Estate",
    "wof:placetype":"venue"
},
  "geometry": {"coordinates":[147.827224731,-37.7086296082],"type":"Point"}
}