{
  "type": "Feature",
  "properties": {
    "iso:country":"AU",
    "sg:address":"Unit 2/ 1 London St",
    "sg:city":"Enmore",
    "sg:classifiers":[
        {
            "category":"Shopping",
            "subcategory":"Musical Instruments",
            "type":"Retail Goods"
        }
    ],
    "sg:phone":"+61 2 9550 5042",
    "sg:postcode":"2042",
    "sg:province":"NSW",
    "sg:tags":[
        "musician",
        "agent"
    ],
    "wof:name":"Cin Cin Entertainment",
    "wof:placetype":"venue"
},
  "geometry": {"coordinates":[151.172089,-33.898434],"type":"Point"}
}