{
  "type": "Feature",
  "properties": {
    "iso:country":"AU",
    "sg:address":"204 West Fyans St",
    "sg:city":"Newtown",
    "sg:classifiers":[
        {
            "category":"Education",
            "subcategory":"Kindergarten",
            "type":"Public Place"
        }
    ],
    "sg:phone":"+61 3 5221 4630",
    "sg:postcode":"3220",
    "sg:province":"VIC",
    "sg:tags":[
        "pre-schools"
    ],
    "wof:name":"Fyans Park Kindergarten",
    "wof:placetype":"venue"
},
  "geometry": {"coordinates":[144.32676699999999,-38.157272],"type":"Point"}
}