{
  "type": "Feature",
  "properties": {
    "addr:full":"39 William Drv Busselton WA 6280",
    "addr:housenumber":"39",
    "addr:postcode":"6280",
    "addr:street":"William Drv",
    "iso:country":"AU",
    "sg:address":"39 William Drv",
    "sg:city":"Busselton",
    "sg:classifiers":[
        {
            "category":"Personal",
            "subcategory":"Beauty Salon",
            "type":"Services"
        }
    ],
    "sg:phone":"+61 8 9752 4991",
    "sg:postcode":"6280",
    "sg:province":"WA",
    "wof:name":"Beauty & Soul",
    "wof:placetype":"venue"
},
  "geometry": {"coordinates":[115.292762756,-33.6580085754],"type":"Point"}
}