{
  "type": "Feature",
  "properties": {
    "iso:country":"AU",
    "sg:address":"19 Stinton Ave",
    "sg:city":"Newtown",
    "sg:classifiers":[
        {
            "category":"Food & Beverages",
            "subcategory":"Supermarket",
            "type":"Retail Goods"
        }
    ],
    "sg:phone":"+61 3 5221 1628",
    "sg:postcode":"3220",
    "sg:province":"VIC",
    "sg:tags":[
        "grocery",
        "store"
    ],
    "wof:name":"Newtown Licensed Grocery",
    "wof:placetype":"venue"
},
  "geometry": {"coordinates":[144.33609,-38.155571],"type":"Point"}
}