{
  "type": "Feature",
  "properties": {
    "addr:full":"Unit 3 25 MacMillan St Labrador QLD 4215",
    "addr:housenumber":"25",
    "addr:postcode":"4215",
    "addr:street":"Macmillan St",
    "iso:country":"AU",
    "sg:address":"Unit 3 25 MacMillan St",
    "sg:city":"Labrador",
    "sg:classifiers":[
        {
            "category":"Autos & Motor Vehicles",
            "subcategory":"Auto Supplies",
            "type":"Retail Goods"
        }
    ],
    "sg:phone":"+61 401 560 781",
    "sg:postcode":"4215",
    "sg:province":"QLD",
    "sg:tags":[
        "automotive",
        "stereo",
        "radio"
    ],
    "wof:name":"Cris Mobile",
    "wof:placetype":"venue"
},
  "geometry": {"coordinates":[153.38937377900001,-27.9483375549],"type":"Point"}
}