{
  "type": "Feature",
  "properties": {
    "addr:full":"171 Military Rd Guildford NSW 2161",
    "addr:housenumber":"171",
    "addr:postcode":"2161",
    "addr:street":"Military Rd",
    "iso:country":"AU",
    "sg:address":"171 Military Rd",
    "sg:city":"Guildford",
    "sg:classifiers":[
        {
            "category":"Autos & Motor Vehicles",
            "subcategory":"Auto Supplies",
            "type":"Retail Goods"
        }
    ],
    "sg:phone":"+61 2 9681 3211",
    "sg:postcode":"2161",
    "sg:province":"NSW",
    "sg:tags":[
        "equipment",
        "part",
        "truck"
    ],
    "wof:name":"I Know Parts & Wrecking Pty Ltd",
    "wof:placetype":"venue"
},
  "geometry": {"coordinates":[150.97915649399999,-33.8597793579],"type":"Point"}
}