{
  "type": "Feature",
  "properties": {
    "addr:full":"361 Wentworth Ave Pendle Hill NSW 2145",
    "addr:housenumber":"361",
    "addr:postcode":"2145",
    "addr:street":"Wentworth Ave",
    "iso:country":"AU",
    "sg:address":"361 Wentworth Ave",
    "sg:city":"Pendle Hill",
    "sg:classifiers":[
        {
            "category":"Autos & Motor Vehicles",
            "subcategory":"Auto Supplies",
            "type":"Retail Goods"
        }
    ],
    "sg:phone":"+61 2 9896 3550",
    "sg:postcode":"2145",
    "sg:province":"NSW",
    "sg:tags":[
        "camper-trailers",
        "caravan",
        "equipment"
    ],
    "wof:name":"Cub Campers Pty Ltd",
    "wof:placetype":"venue"
},
  "geometry": {"coordinates":[150.95315551799999,-33.7961730957],"type":"Point"}
}