{
  "type": "Feature",
  "properties": {
    "iso:country":"AU",
    "sg:address":"44 Napoleon St",
    "sg:city":"Port Lincoln",
    "sg:classifiers":[
        {
            "category":"Autos & Motor Vehicles",
            "subcategory":"Automobile Sales",
            "type":"Retail Goods"
        }
    ],
    "sg:phone":"+61 8 8682 2988",
    "sg:postcode":"5606",
    "sg:province":"SA",
    "sg:tags":[
        "car",
        "new"
    ],
    "wof:name":"Mike Raleigh Motors Pty Ltd",
    "wof:placetype":"venue"
},
  "geometry": {"coordinates":[135.861526,-34.724224],"type":"Point"}
}