{
  "type": "Feature",
  "properties": {
    "addr:full":"10 Aldyth St New Lambton NSW 2305",
    "addr:housenumber":"10",
    "addr:postcode":"2305",
    "addr:street":"Aldyth St",
    "iso:country":"AU",
    "sg:address":"10 Aldyth St",
    "sg:city":"New Lambton",
    "sg:classifiers":[
        {
            "category":"Government",
            "subcategory":"Customs House",
            "type":"Public Place"
        }
    ],
    "sg:phone":"+61 2 4957 2722",
    "sg:postcode":"2305",
    "sg:province":"NSW",
    "sg:tags":[
        "title",
        "management",
        "stratum"
    ],
    "wof:name":"Alton Bowen",
    "wof:placetype":"venue"
},
  "geometry": {"coordinates":[151.706085,-32.930424],"type":"Point"}
}