{
  "type": "Feature",
  "properties": {
    "iso:country":"AU",
    "sg:address":"Unit 3/ 47 Lear Jet Drv",
    "sg:city":"Caboolture",
    "sg:classifiers":[
        {
            "category":"Building & Trades",
            "subcategory":"Construction",
            "type":"Services"
        }
    ],
    "sg:phone":"+61 7 5428 1212",
    "sg:postcode":"4510",
    "sg:province":"QLD",
    "sg:tags":[
        "pool",
        "swimming"
    ],
    "wof:name":"Leisure Pools Sunshine Coast",
    "wof:placetype":"venue"
},
  "geometry": {"coordinates":[152.979492,-27.079998],"type":"Point"}
}