{
  "type": "Feature",
  "properties": {
    "addr:full":"24 Alexandra Pl Bentley WA 6102",
    "addr:housenumber":"24",
    "addr:postcode":"6102",
    "addr:street":"Alexandra Pl",
    "iso:country":"AU",
    "sg:address":"24 Alexandra Pl",
    "sg:city":"Bentley",
    "sg:classifiers":[
        {
            "category":"Education",
            "subcategory":"Music School",
            "type":"Public Place"
        }
    ],
    "sg:phone":"+61 8 9458 2543",
    "sg:postcode":"6102",
    "sg:province":"WA",
    "sg:tags":[
        "teacher"
    ],
    "wof:name":"Joseph Mitchell",
    "wof:placetype":"venue"
},
  "geometry": {"coordinates":[115.924858093,-32.0040855408],"type":"Point"}
}