{
  "type": "Feature",
  "properties": {
    "iso:country":"AU",
    "sg:address":"77 Kingsclere Ave",
    "sg:city":"Keysborough",
    "sg:classifiers":[
        {
            "category":"Food & Beverages",
            "subcategory":"Groceries & Convenience Stores",
            "type":"Retail Goods"
        }
    ],
    "sg:phone":"+61 3 9706 3640",
    "sg:postcode":"3173",
    "sg:province":"VIC",
    "wof:name":"Noble Milk Bar",
    "wof:placetype":"venue"
},
  "geometry": {"coordinates":[145.169830322,-37.9871788025],"type":"Point"}
}