{
  "type": "Feature",
  "properties": {
    "iso:country":"AU",
    "sg:address":"13 Rogers Ave",
    "sg:city":"Haberfield",
    "sg:classifiers":[
        {
            "category":"Professional",
            "subcategory":"Management & Consulting",
            "type":"Services"
        }
    ],
    "sg:phone":"+61 2 9716 6632",
    "sg:postcode":"2045",
    "sg:province":"NSW",
    "sg:tags":[
        "consultant",
        "business"
    ],
    "wof:name":"Dundee Pty Ltd",
    "wof:placetype":"venue"
},
  "geometry": {"coordinates":[151.13575700000001,-33.882736],"type":"Point"}
}