{
  "type": "Feature",
  "properties": {
    "addr:full":"327 Bell St Pascoe Vale South VIC 3044",
    "addr:housenumber":"327",
    "addr:postcode":"3044",
    "addr:street":"Bell St",
    "iso:country":"AU",
    "sg:address":"327 Bell St",
    "sg:city":"Pascoe Vale South",
    "sg:classifiers":[
        {
            "category":"Real Estate",
            "subcategory":"Real Estate Agent",
            "type":"Services"
        }
    ],
    "sg:phone":"+61 3 9354 4999",
    "sg:postcode":"3044",
    "sg:province":"VIC",
    "wof:name":"Barry Plant Doherty",
    "wof:placetype":"venue"
},
  "geometry": {"coordinates":[144.94635009800001,-37.7393875122],"type":"Point"}
}