{
  "type": "Feature",
  "properties": {
    "addr:full":"60 Maryland St Stanthorpe QLD 4380",
    "addr:housenumber":"60",
    "addr:postcode":"4380",
    "addr:street":"Maryland St",
    "iso:country":"AU",
    "sg:address":"60 Maryland St",
    "sg:city":"Stanthorpe",
    "sg:classifiers":[
        {
            "category":"Communications",
            "subcategory":"Film & Video Production",
            "type":"Services"
        }
    ],
    "sg:phone":"+61 7 4681 2485",
    "sg:postcode":"4380",
    "sg:province":"QLD",
    "sg:tags":[
        "dvd",
        "library"
    ],
    "wof:name":"Video Ezy",
    "wof:placetype":"venue"
},
  "geometry": {"coordinates":[151.93365499999999,-28.656261],"type":"Point"}
}