{
  "type": "Feature",
  "properties": {
    "addr:full":"400 Cleveland St Surry Hills NSW 2010",
    "addr:housenumber":"400",
    "addr:postcode":"2010",
    "addr:street":"Cleveland St",
    "iso:country":"AU",
    "sg:address":"400 Cleveland St",
    "sg:city":"Surry Hills",
    "sg:classifiers":[
        {
            "category":"Personal",
            "subcategory":"Adult",
            "type":"Services"
        }
    ],
    "sg:phone":"+61 2 9319 5177",
    "sg:postcode":"2010",
    "sg:province":"NSW",
    "sg:tags":[
        "vic",
        "except",
        "state",
        "escort",
        "social",
        "qld"
    ],
    "wof:name":"Vamps International",
    "wof:placetype":"venue"
},
  "geometry": {"coordinates":[151.21124267600001,-33.8910636902],"type":"Point"}
}