{
  "type": "Feature",
  "properties": {
    "addr:full":"Level 1 , North Tce Hackney SA 5069",
    "addr:postcode":"5069",
    "addr:street":"North Tce",
    "iso:country":"AU",
    "sg:address":"Level 1",
    "sg:city":", North Tce Hackney",
    "sg:classifiers":[
        {
            "category":"Banks & Credit Unions",
            "subcategory":"Bank",
            "type":"Services"
        }
    ],
    "sg:phone":"+61 1300 655 627",
    "sg:postcode":"5069",
    "sg:province":"SA",
    "wof:name":"Cashcard Australia Limited",
    "wof:placetype":"venue"
},
  "geometry": {"coordinates":[138.61369323700001,-34.9100418091],"type":"Point"}
}