{
  "type": "Feature",
  "properties": {
    "addr:full":"52 Elphin Rd Launceston TAS 7250",
    "addr:housenumber":"52",
    "addr:postcode":"7250",
    "addr:street":"Elphin Rd",
    "iso:country":"AU",
    "sg:address":"52 Elphin Rd",
    "sg:city":"Launceston",
    "sg:classifiers":[
        {
            "category":"Health Services",
            "subcategory":"Dentist",
            "type":"Services"
        }
    ],
    "sg:phone":"+61 3 6331 7240",
    "sg:postcode":"7250",
    "sg:province":"TAS",
    "sg:tags":[
        "dental",
        "prosthetist"
    ],
    "wof:name":"Oral Armour Mouthguard",
    "wof:placetype":"venue"
},
  "geometry": {"coordinates":[147.150878906,-41.4328651428],"type":"Point"}
}