{
  "type": "Feature",
  "properties": {
    "iso:country":"AU",
    "sg:address":"4 Gordon Rd",
    "sg:city":"West Osborne Park",
    "sg:classifiers":[
        {
            "category":"Shopping",
            "subcategory":"Pets & Pet Supplies",
            "type":"Retail Goods"
        }
    ],
    "sg:phone":"+61 8 9444 8822",
    "sg:postcode":"6017",
    "sg:province":"WA",
    "sg:tags":[
        "sheep",
        "equipment",
        "shearing"
    ],
    "wof:name":"Westline Clothing Company",
    "wof:placetype":"venue"
},
  "geometry": {"coordinates":[115.819877624,-31.9070053101],"type":"Point"}
}