{
  "type": "Feature",
  "properties": {
    "addr:full":"A 20 Llewellyn St Oatley NSW 2223",
    "addr:housenumber":"20",
    "addr:postcode":"2223",
    "addr:street":"A;Llewellyn St",
    "iso:country":"AU",
    "sg:address":"A 20 Llewellyn St",
    "sg:city":"Oatley",
    "sg:classifiers":[
        {
            "category":"Real Estate",
            "subcategory":"Architect",
            "type":"Services"
        }
    ],
    "sg:phone":"+61 2 9570 9445",
    "sg:postcode":"2223",
    "sg:province":"NSW",
    "sg:tags":[
        "building",
        "designer"
    ],
    "wof:name":"Creative Architecture Pty Ltd",
    "wof:placetype":"venue"
},
  "geometry": {"coordinates":[151.073684692,-33.9867897034],"type":"Point"}
}