{
  "type": "Feature",
  "properties": {
    "addr:full":"96 Station St Fairfield VIC 3078",
    "addr:housenumber":"96",
    "addr:postcode":"3078",
    "addr:street":"Station St",
    "iso:country":"AU",
    "sg:address":"96 Station St",
    "sg:city":"Fairfield",
    "sg:classifiers":[
        {
            "category":"Food & Beverages",
            "subcategory":"Supermarket",
            "type":"Retail Goods"
        }
    ],
    "sg:phone":"+61 3 9481 3571",
    "sg:postcode":"3078",
    "sg:province":"VIC",
    "sg:tags":[
        "grocery",
        "store"
    ],
    "wof:name":"IGA Everyday",
    "wof:placetype":"venue"
},
  "geometry": {"coordinates":[145.01838684099999,-37.7784347534],"type":"Point"}
}