{
  "type": "Feature",
  "properties": {
    "addr:full":"4/ 1 Ferguson La Chatswood NSW 2067",
    "addr:housenumber":"/ 1",
    "addr:postcode":"2067",
    "addr:street":"Ferguson La",
    "iso:country":"AU",
    "sg:address":"4/ 1 Ferguson La",
    "sg:city":"Chatswood",
    "sg:classifiers":[
        {
            "category":"Health Services",
            "subcategory":"Optometrist",
            "type":"Services"
        }
    ],
    "sg:phone":"+61 2 9413 1800",
    "sg:postcode":"2067",
    "sg:province":"NSW",
    "wof:name":"Edgar Paul F",
    "wof:placetype":"venue"
},
  "geometry": {"coordinates":[151.18328857399999,-33.7951850891],"type":"Point"}
}