{
  "type": "Feature",
  "properties": {
    "addr:full":"1 Brockman Hwy Karridale WA 6288",
    "addr:housenumber":"1",
    "addr:postcode":"6288",
    "addr:street":"Brockman Hwy",
    "iso:country":"AU",
    "sg:address":"1 Brockman Hwy",
    "sg:city":"Karridale",
    "sg:classifiers":[
        {
            "category":"Farming",
            "subcategory":"Vineyard",
            "type":"Manufacturing & Wholesale Goods"
        }
    ],
    "sg:phone":"+61 8 9758 2332",
    "sg:postcode":"6288",
    "sg:province":"WA",
    "sg:tags":[
        "winery"
    ],
    "wof:name":"Blackwood Meadery",
    "wof:placetype":"venue"
},
  "geometry": {"coordinates":[115.13835143999999,-34.1904983521],"type":"Point"}
}