{
  "type": "Feature",
  "properties": {
    "iso:country":"AU",
    "sg:address":"PO Box 8091",
    "sg:city":"Mt Pleasant",
    "sg:classifiers":[
        {
            "category":"Professional",
            "subcategory":"Accounting & Tax Preparation",
            "type":"Services"
        }
    ],
    "sg:phone":"+61 418 960 085",
    "sg:postcode":"4740",
    "sg:province":"QLD",
    "sg:tags":[
        "bookkeeping"
    ],
    "wof:name":"AAA Bookkeeping Services",
    "wof:placetype":"venue"
},
  "geometry": {"coordinates":[149.15718100000001,-21.11883],"type":"Point"}
}