{
  "type": "Feature",
  "properties": {
    "addr:full":"315 Harfleur St Deniliquin NSW 2710",
    "addr:housenumber":"315",
    "addr:postcode":"2710",
    "addr:street":"Harfleur St",
    "iso:country":"AU",
    "sg:address":"315 Harfleur St",
    "sg:city":"Deniliquin",
    "sg:classifiers":[
        {
            "category":"Taxi",
            "type":"Transportation"
        }
    ],
    "sg:phone":"+61 3 5881 2129",
    "sg:postcode":"2710",
    "sg:province":"NSW",
    "sg:tags":[
        "cab"
    ],
    "wof:name":"Black & White Taxis",
    "wof:placetype":"venue"
},
  "geometry": {"coordinates":[144.95448303200001,-35.5268821716],"type":"Point"}
}