{
  "type": "Feature",
  "properties": {
    "iso:country":"AU",
    "sg:address":"Unit 3/ 355 Samford Rd",
    "sg:city":"Samford",
    "sg:classifiers":[
        {
            "category":"Professional",
            "subcategory":"Computer Services",
            "type":"Services"
        }
    ],
    "sg:phone":"+61 7 3289 5656",
    "sg:postcode":"4520",
    "sg:province":"QLD",
    "sg:tags":[
        "on-line",
        "provider"
    ],
    "wof:name":"Samford Net",
    "wof:placetype":"venue"
},
  "geometry": {"coordinates":[152.88664199999999,-27.373665],"type":"Point"}
}