{
  "type": "Feature",
  "properties": {
    "iso:country":"AU",
    "sg:address":"332 Sturt St",
    "sg:city":"Ballarat Central",
    "sg:classifiers":[
        {
            "category":"Shopping",
            "subcategory":"Clothing, Apparel, & Fashions",
            "type":"Retail Goods"
        }
    ],
    "sg:phone":"+61 3 5331 9950",
    "sg:postcode":"3350",
    "sg:province":"VIC",
    "sg:tags":[
        "lady",
        "wear"
    ],
    "wof:name":"Peppa Women",
    "wof:placetype":"venue"
},
  "geometry": {"coordinates":[143.855057,-37.56134],"type":"Point"}
}