{
  "type": "Feature",
  "properties": {
    "addr:full":"260 Sunshine Rd Tottenham VIC 3012",
    "addr:housenumber":"260",
    "addr:postcode":"3012",
    "addr:street":"Sunshine Rd",
    "iso:country":"AU",
    "sg:address":"260 Sunshine Rd",
    "sg:city":"Tottenham",
    "sg:classifiers":[
        {
            "category":"Professional",
            "type":"Services"
        }
    ],
    "sg:phone":"+61 3 9364 7377",
    "sg:postcode":"3012",
    "sg:province":"VIC",
    "sg:tags":[
        "transport"
    ],
    "wof:name":"Foster Haulage",
    "wof:placetype":"venue"
},
  "geometry": {"coordinates":[144.84262085,-37.7971763611],"type":"Point"}
}