{
  "type": "Feature",
  "properties": {
    "addr:full":"38 Lake Placid Rd Lake Placid QLD 4878",
    "addr:housenumber":"38",
    "addr:postcode":"4878",
    "addr:street":"Lake Placid Rd",
    "iso:country":"AU",
    "sg:address":"38 Lake Placid Rd",
    "sg:city":"Lake Placid",
    "sg:classifiers":[
        {
            "category":"Food & Beverages",
            "subcategory":"Supermarket",
            "type":"Retail Goods"
        }
    ],
    "sg:phone":"+61 7 4039 2558",
    "sg:postcode":"4878",
    "sg:province":"QLD",
    "sg:tags":[
        "grocery",
        "store"
    ],
    "wof:name":"Lake Placid General Store",
    "wof:placetype":"venue"
},
  "geometry": {"coordinates":[145.67552185100001,-16.8699054718],"type":"Point"}
}