{
  "type": "Feature",
  "properties": {
    "addr:full":"Level 1 195 Adelaide Tce Perth WA 6000",
    "addr:housenumber":"195",
    "addr:postcode":"6000",
    "addr:street":"Adelaide Tce",
    "iso:country":"AU",
    "sg:address":"Level 1 195",
    "sg:city":"Adelaide Tce Perth",
    "sg:classifiers":[
        {
            "category":"Professional",
            "subcategory":"Employment Agencies",
            "type":"Services"
        }
    ],
    "sg:phone":"+61 8 9221 6966",
    "sg:postcode":"6000",
    "sg:province":"WA",
    "sg:tags":[
        "provider",
        "internet"
    ],
    "wof:name":"Quik Internet",
    "wof:placetype":"venue"
},
  "geometry": {"coordinates":[115.869300842,-31.9590892792],"type":"Point"}
}