{
  "type": "Feature",
  "properties": {
    "iso:country":"AU",
    "sg:address":"16 Sutcliffe St",
    "sg:city":"Dalkeith",
    "sg:classifiers":[
        {
            "category":"Professional",
            "subcategory":"Detective & Security Services",
            "type":"Services"
        }
    ],
    "sg:phone":"+61 8 9386 2669",
    "sg:postcode":"6009",
    "sg:province":"WA",
    "sg:tags":[
        "consultant",
        "system"
    ],
    "wof:name":"Nedlands Security Systems & Services",
    "wof:placetype":"venue"
},
  "geometry": {"coordinates":[115.800041,-31.990644],"type":"Point"}
}