{
  "type": "Feature",
  "properties": {
    "addr:full":"20 Wellington St Baradine NSW 2396",
    "addr:housenumber":"20",
    "addr:postcode":"2396",
    "addr:street":"Wellington St",
    "iso:country":"AU",
    "sg:address":"20 Wellington St",
    "sg:city":"Baradine",
    "sg:classifiers":[
        {
            "category":"Cafe",
            "type":"Food & Drink"
        }
    ],
    "sg:phone":"+61 2 6843 1781",
    "sg:postcode":"2396",
    "sg:province":"NSW",
    "wof:name":"Emmy Lou's Eatery",
    "wof:placetype":"venue"
},
  "geometry": {"coordinates":[149.06800842300001,-30.9498996735],"type":"Point"}
}