{
  "type": "Feature",
  "properties": {
    "addr:full":"7 Dixon St Dalby QLD 4405",
    "addr:housenumber":"7",
    "addr:postcode":"4405",
    "addr:street":"Dixon St",
    "iso:country":"AU",
    "sg:address":"7 Dixon St",
    "sg:city":"Dalby",
    "sg:classifiers":[
        {
            "category":"Manufacturing",
            "subcategory":"Retail Goods",
            "type":"Manufacturing & Wholesale Goods"
        }
    ],
    "sg:phone":"+61 7 4662 4542",
    "sg:postcode":"4405",
    "sg:province":"QLD",
    "sg:tags":[
        "merchant",
        "pump",
        "mfrs"
    ],
    "wof:name":"Burton's Water Drilling Pty Ltd",
    "wof:placetype":"venue"
},
  "geometry": {"coordinates":[151.24288940400001,-27.1839294434],"type":"Point"}
}