{
  "type": "Feature",
  "properties": {
    "addr:full":"Shop1/ 145 Lake St Cairns QLD 4870",
    "addr:housenumber":"145",
    "addr:postcode":"4870",
    "addr:street":"Lake St",
    "iso:country":"AU",
    "sg:address":"Shop1/ 145 Lake St",
    "sg:city":"Cairns",
    "sg:classifiers":[
        {
            "category":"Recreation",
            "type":"Entertainment"
        }
    ],
    "sg:phone":"+61 7 4041 5088",
    "sg:postcode":"4870",
    "sg:province":"QLD",
    "sg:tags":[
        "hire",
        "tour",
        "motor",
        "cycle"
    ],
    "wof:name":"AJs Mototours",
    "wof:placetype":"venue"
},
  "geometry": {"coordinates":[145.77357482900001,-16.9196987152],"type":"Point"}
}