{
  "type": "Feature",
  "properties": {
    "addr:full":"1 Funda Pl Brookvale NSW 2100",
    "addr:housenumber":"1",
    "addr:postcode":"2100",
    "addr:street":"Funda Pl",
    "iso:country":"AU",
    "sg:address":"1 Funda Pl",
    "sg:city":"Brookvale",
    "sg:classifiers":[
        {
            "category":"Building & Trades",
            "subcategory":"Landscaping Services",
            "type":"Services"
        }
    ],
    "sg:phone":"+61 413 861 351",
    "sg:postcode":"2100",
    "sg:province":"NSW",
    "sg:tags":[
        "architect",
        "landscape"
    ],
    "wof:name":"R.L. Frew Landscape Architectural Services",
    "wof:placetype":"venue"
},
  "geometry": {"coordinates":[151.265426636,-33.7629013062],"type":"Point"}
}