{
  "type": "Feature",
  "properties": {
    "iso:country":"AU",
    "sg:address":"675 South Pine Rd",
    "sg:city":"Everton Park",
    "sg:classifiers":[
        {
            "category":"Retail",
            "subcategory":"Auto Repair",
            "type":"Services"
        }
    ],
    "sg:phone":"+61 7 3855 1600",
    "sg:postcode":"4053",
    "sg:province":"QLD",
    "sg:tags":[
        "repairer",
        "motor",
        "engineer"
    ],
    "wof:name":"Matilda Everton Park - Work Shop",
    "wof:placetype":"venue"
},
  "geometry": {"coordinates":[152.986984253,-27.4012145996],"type":"Point"}
}