{
  "type": "Feature",
  "properties": {
    "addr:full":"175 Cranebrook Rd Cranebrook NSW 2749",
    "addr:housenumber":"175",
    "addr:postcode":"2749",
    "addr:street":"Cranebrook Rd",
    "iso:country":"AU",
    "sg:address":"175 Cranebrook Rd",
    "sg:city":"Cranebrook",
    "sg:classifiers":[
        {
            "category":"Social Services",
            "subcategory":"Retirement Home",
            "type":"Services"
        }
    ],
    "sg:phone":"+61 2 4777 0111",
    "sg:postcode":"2749",
    "sg:province":"NSW",
    "sg:tags":[
        "environmental",
        "consultant",
        "pollution"
    ],
    "wof:name":"Australian Wetlands Pty Ltd",
    "wof:placetype":"venue"
},
  "geometry": {"coordinates":[150.69786071799999,-33.7138442993],"type":"Point"}
}