{
  "type": "Feature",
  "properties": {
    "addr:full":"331 Settlement Rd Thomastown VIC 3074",
    "addr:housenumber":"331",
    "addr:postcode":"3074",
    "addr:street":"Settlement Rd",
    "iso:country":"AU",
    "sg:address":"331 Settlement Rd",
    "sg:city":"Thomastown",
    "sg:classifiers":[
        {
            "category":"Shopping",
            "subcategory":"Clothing, Apparel, & Fashions",
            "type":"Retail Goods"
        }
    ],
    "sg:phone":"+61 1800 885 239",
    "sg:postcode":"3074",
    "sg:province":"VIC",
    "sg:tags":[
        "lingerie",
        "hosiery",
        "sleepwear"
    ],
    "wof:name":"Sexyland Adult Department Store",
    "wof:placetype":"venue"
},
  "geometry": {"coordinates":[145.022827148,-37.6890335083],"type":"Point"}
}