{
  "type": "Feature",
  "properties": {
    "addr:full":"Ranfurlie Crs Glen Iris VIC 3146",
    "addr:postcode":"3146",
    "addr:street":"Ranfurlie Crs",
    "iso:country":"AU",
    "sg:address":"Ranfurlie Crs",
    "sg:city":"Glen Iris",
    "sg:classifiers":[
        {
            "category":"Education",
            "subcategory":"School",
            "type":"Public Place"
        }
    ],
    "sg:phone":"+61 3 9885 0336",
    "sg:postcode":"3146",
    "sg:province":"VIC",
    "wof:name":"Korowa Anglican Girls' School",
    "wof:placetype":"venue"
},
  "geometry": {"coordinates":[145.067626953,-37.8564682007],"type":"Point"}
}