{
  "type": "Feature",
  "properties": {
    "addr:full":"Cnr Charnwood Pl & Loktsky St Charnwood ACT 2615",
    "addr:postcode":"2615",
    "addr:street":"St",
    "iso:country":"AU",
    "sg:address":"Cnr Charnwood Pl & Loktsky St",
    "sg:city":"Charnwood",
    "sg:classifiers":[
        {
            "category":"Fast Food",
            "type":"Food & Drink"
        }
    ],
    "sg:phone":"+61 2 6259 9199",
    "sg:postcode":"2615",
    "sg:province":"ACT",
    "sg:tags":[
        "away",
        "take"
    ],
    "wof:name":"McDonald's Family Restaurants",
    "wof:placetype":"venue"
},
  "geometry": {"coordinates":[149.03257751500001,-35.2047195435],"type":"Point"}
}