{
  "type": "Feature",
  "properties": {
    "addr:full":"3 Crouch Crt Doncaster VIC 3108",
    "addr:housenumber":"3",
    "addr:postcode":"3108",
    "addr:street":"Crouch Crt",
    "iso:country":"AU",
    "sg:address":"3 Crouch Crt",
    "sg:city":"Doncaster",
    "sg:classifiers":[
        {
            "category":"Professional",
            "subcategory":"Management & Consulting",
            "type":"Services"
        }
    ],
    "sg:phone":"+61 3 9848 7100",
    "sg:postcode":"3108",
    "sg:province":"VIC",
    "sg:tags":[
        "consultant"
    ],
    "wof:name":"Decision Dynamics Pty Ltd",
    "wof:placetype":"venue"
},
  "geometry": {"coordinates":[145.13250732399999,-37.774394989],"type":"Point"}
}