{
  "type": "Feature",
  "properties": {
    "addr:full":"9 Lochlarney St Beenleigh QLD 4207",
    "addr:housenumber":"9",
    "addr:postcode":"4207",
    "addr:street":"Lochlarney St",
    "iso:country":"AU",
    "sg:address":"9 Lochlarney St",
    "sg:city":"Beenleigh",
    "sg:classifiers":[
        {
            "category":"Manufacturing",
            "subcategory":"Metals",
            "type":"Manufacturing & Wholesale Goods"
        }
    ],
    "sg:phone":"+61 7 3804 7585",
    "sg:postcode":"4207",
    "sg:province":"QLD",
    "sg:tags":[
        "steel",
        "fabricator",
        "mfrs"
    ],
    "wof:name":"NBC Welding & Fabrications",
    "wof:placetype":"venue"
},
  "geometry": {"coordinates":[153.18354797399999,-27.7124557495],"type":"Point"}
}