{
  "type": "Feature",
  "properties": {
    "addr:full":"Anne St Moree NSW 2400",
    "addr:postcode":"2400",
    "addr:street":"Anne St",
    "iso:country":"AU",
    "sg:address":"Anne St",
    "sg:city":"Moree",
    "sg:classifiers":[
        {
            "category":"Social Services",
            "subcategory":"Child Care",
            "type":"Services"
        }
    ],
    "sg:phone":"+61 2 6752 8011",
    "sg:postcode":"2400",
    "sg:province":"NSW",
    "wof:name":"Kiah Pre-School",
    "wof:placetype":"venue"
},
  "geometry": {"coordinates":[149.84127807600001,-29.4737148285],"type":"Point"}
}