{
  "type": "Feature",
  "properties": {
    "addr:full":"111 Trafalgar St Stanmore NSW 2048",
    "addr:housenumber":"111",
    "addr:postcode":"2048",
    "addr:street":"Trafalgar St",
    "iso:country":"AU",
    "sg:address":"111 Trafalgar St",
    "sg:city":"Stanmore",
    "sg:classifiers":[
        {
            "category":"Professional",
            "subcategory":"Art Services",
            "type":"Services"
        }
    ],
    "sg:phone":"+61 402 116 210",
    "sg:postcode":"2048",
    "sg:province":"NSW",
    "sg:tags":[
        "graphic",
        "designer"
    ],
    "wof:name":"Brazil Design",
    "wof:placetype":"venue"
},
  "geometry": {"coordinates":[151.16351299999999,-33.894943],"type":"Point"}
}