{
  "type": "Feature",
  "properties": {
    "iso:country":"AU",
    "sg:address":"Bellingen Rd",
    "sg:city":"Bowraville",
    "sg:classifiers":[
        {
            "category":"Education",
            "subcategory":"School",
            "type":"Public Place"
        }
    ],
    "sg:phone":"+61 2 6564 7619",
    "sg:postcode":"2449",
    "sg:province":"NSW",
    "wof:name":"Tallowood School",
    "wof:placetype":"venue"
},
  "geometry": {"coordinates":[152.85952800000001,-30.638567],"type":"Point"}
}