{
  "type": "Feature",
  "properties": {
    "iso:country":"AU",
    "sg:address":"2 Beltana St",
    "sg:city":"Grovedale",
    "sg:classifiers":[
        {
            "category":"Arena",
            "subcategory":"Sports Club",
            "type":"Entertainment"
        }
    ],
    "sg:phone":"+61 3 5243 1277",
    "sg:postcode":"3216",
    "sg:province":"VIC",
    "sg:tags":[
        "hunt",
        "racing"
    ],
    "wof:name":"Australian Bowhunters Association",
    "wof:placetype":"venue"
},
  "geometry": {"coordinates":[144.33303832999999,-38.2053718567],"type":"Point"}
}