{
  "type": "Feature",
  "properties": {
    "iso:country":"AU",
    "sg:address":"86- 88 Melbourne St",
    "sg:city":"North Adelaide",
    "sg:classifiers":[
        {
            "category":"Professional",
            "subcategory":"Employment Agencies",
            "type":"Services"
        }
    ],
    "sg:phone":"+61 8 8267 4744",
    "sg:postcode":"5006",
    "sg:province":"SA",
    "sg:tags":[
        "consultant",
        "corrosion"
    ],
    "wof:name":"Incospec & Associates",
    "wof:placetype":"venue"
},
  "geometry": {"coordinates":[138.60806274399999,-34.90650177],"type":"Point"}
}