{
  "type": "Feature",
  "properties": {
    "addr:full":"76 Churchill Rd Prospect SA 5082",
    "addr:housenumber":"76",
    "addr:postcode":"5082",
    "addr:street":"Churchill Rd",
    "iso:country":"AU",
    "sg:address":"76 Churchill Rd",
    "sg:city":"Prospect",
    "sg:classifiers":[
        {
            "category":"Sports & Exercise",
            "subcategory":"Gym",
            "type":"Entertainment"
        }
    ],
    "sg:phone":"+61 8 8269 5323",
    "sg:postcode":"5082",
    "sg:province":"SA",
    "sg:tags":[
        "health",
        "fitness"
    ],
    "wof:name":"Powerhouse Gym & Fitness Centre",
    "wof:placetype":"venue"
},
  "geometry": {"coordinates":[138.58515930199999,-34.8919639587],"type":"Point"}
}