{
  "type": "Feature",
  "properties": {
    "addr:full":"556 Tarragindi Rd Salisbury QLD 4107",
    "addr:housenumber":"556",
    "addr:postcode":"4107",
    "addr:street":"Tarragindi Rd",
    "iso:country":"AU",
    "sg:address":"556 Tarragindi Rd",
    "sg:city":"Salisbury",
    "sg:classifiers":[
        {
            "category":"Wholesale",
            "subcategory":"Machinery & Supplies",
            "type":"Manufacturing & Wholesale Goods"
        }
    ],
    "sg:phone":"+61 7 3719 3400",
    "sg:postcode":"4107",
    "sg:province":"QLD",
    "sg:tags":[
        "instrument",
        "scientific"
    ],
    "wof:name":"Seismic Asia Pacific",
    "wof:placetype":"venue"
},
  "geometry": {"coordinates":[153.03166198700001,-27.543422699],"type":"Point"}
}