{
  "type": "Feature",
  "properties": {
    "iso:country":"AU",
    "sg:address":"112 Majors Bay Rd",
    "sg:city":"Concord",
    "sg:classifiers":[
        {
            "category":"Health Services",
            "subcategory":"Health Practitioner",
            "type":"Services"
        }
    ],
    "sg:phone":"+61 2 9322 1208",
    "sg:postcode":"2137",
    "sg:province":"NSW",
    "sg:tags":[
        "physiotherapist"
    ],
    "wof:name":"Manipulative Physiotherapy Association of Australia",
    "wof:placetype":"venue"
},
  "geometry": {"coordinates":[151.10301208499999,-33.8554573059],"type":"Point"}
}