{
  "type": "Feature",
  "properties": {
    "addr:full":"190 Pacific Hwy North Sydney NSW 2060",
    "addr:housenumber":"190",
    "addr:postcode":"2060",
    "addr:street":"Pacific Hwy",
    "iso:country":"AU",
    "sg:address":"190 Pacific Hwy",
    "sg:city":"North Sydney",
    "sg:classifiers":[
        {
            "category":"Education",
            "subcategory":"Special Training",
            "type":"Public Place"
        }
    ],
    "sg:phone":"+61 2 9955 6777",
    "sg:postcode":"2060",
    "sg:province":"NSW",
    "sg:tags":[
        "development"
    ],
    "wof:name":"H & H Accredited Training Australasia Inc",
    "wof:placetype":"venue"
},
  "geometry": {"coordinates":[151.20419311500001,-33.8327293396],"type":"Point"}
}