{
  "type": "Feature",
  "properties": {
    "iso:country":"AU",
    "sg:address":"112 Vincent St",
    "sg:city":"Cessnock",
    "sg:classifiers":[
        {
            "category":"Shopping",
            "subcategory":"Clothing, Apparel, & Fashions",
            "type":"Retail Goods"
        }
    ],
    "sg:phone":"+61 2 4990 7625",
    "sg:postcode":"2325",
    "sg:province":"NSW",
    "sg:tags":[
        "recycled",
        "clothing"
    ],
    "wof:name":"Samaritans",
    "wof:placetype":"venue"
},
  "geometry": {"coordinates":[151.35617065400001,-32.8364334106],"type":"Point"}
}