{
  "type": "Feature",
  "properties": {
    "addr:full":"PO Box 115 Berowra NSW 2081",
    "addr:postcode":"2081",
    "iso:country":"AU",
    "sg:address":"PO Box 115",
    "sg:city":"Berowra",
    "sg:classifiers":[
        {
            "category":"Social Services",
            "subcategory":"Retirement Home",
            "type":"Services"
        }
    ],
    "sg:phone":"+61 2 9294 4560",
    "sg:postcode":"2081",
    "sg:province":"NSW",
    "sg:tags":[
        "environmental",
        "consultant",
        "pollution"
    ],
    "wof:name":"Ecotone Ecological Consultants Pty Ltd",
    "wof:placetype":"venue"
},
  "geometry": {"coordinates":[151.150390625,-33.6227493286],"type":"Point"}
}