{
  "type": "Feature",
  "properties": {
    "addr:full":"77 Laburnum St Blackburn VIC 3130",
    "addr:housenumber":"77",
    "addr:postcode":"3130",
    "addr:street":"Laburnum St",
    "iso:country":"AU",
    "sg:address":"77 Laburnum St",
    "sg:city":"Blackburn",
    "sg:classifiers":[
        {
            "category":"Health Services",
            "subcategory":"Doctor",
            "type":"Services"
        }
    ],
    "sg:phone":"+61 3 9894 4739",
    "sg:postcode":"3130",
    "sg:province":"VIC",
    "sg:tags":[
        "medical",
        "practitioner"
    ],
    "wof:name":"Kefford R.S",
    "wof:placetype":"venue"
},
  "geometry": {"coordinates":[145.149734497,-37.8214302063],"type":"Point"}
}