{
  "type": "Feature",
  "properties": {
    "addr:full":"Level 1/ 1 Cobden St South Melbourne VIC 3205",
    "addr:housenumber":"/ 1",
    "addr:postcode":"3205",
    "addr:street":"Cobden St",
    "iso:country":"AU",
    "sg:address":"Level 1/ 1 Cobden St",
    "sg:city":"South Melbourne",
    "sg:classifiers":[
        {
            "category":"Arena",
            "subcategory":"Sports Club",
            "type":"Entertainment"
        }
    ],
    "sg:phone":"+61 3 9696 2344",
    "sg:postcode":"3205",
    "sg:province":"VIC",
    "sg:tags":[
        "organisation",
        "sporting"
    ],
    "wof:name":"Ski & Snowboard Australia",
    "wof:placetype":"venue"
},
  "geometry": {"coordinates":[144.96942100000001,-37.833961],"type":"Point"}
}