{
  "type": "Feature",
  "properties": {
    "addr:full":"122 Rooty Hill Rd North Rooty Hill NSW 2766",
    "addr:housenumber":"122",
    "addr:postcode":"2766",
    "addr:street":"Rooty Hill Rd North Rooty",
    "iso:country":"AU",
    "sg:address":"122 Rooty Hill Rd North",
    "sg:city":"Rooty Hill",
    "sg:classifiers":[
        {
            "category":"Professional",
            "subcategory":"Employment Agencies",
            "type":"Services"
        }
    ],
    "sg:phone":"+61 2 9625 6289",
    "sg:postcode":"2766",
    "sg:province":"NSW",
    "sg:tags":[
        "entertainer",
        "agent"
    ],
    "wof:name":"Philippine Entertainment Network",
    "wof:placetype":"venue"
},
  "geometry": {"coordinates":[150.839447022,-33.76537323],"type":"Point"}
}