{
  "type": "Feature",
  "properties": {
    "iso:country":"AU",
    "sg:address":"65 Crawford Rd",
    "sg:city":"Cooranbong",
    "sg:classifiers":[
        {
            "category":"Personal",
            "subcategory":"Massage",
            "type":"Services"
        }
    ],
    "sg:phone":"+61 2 4977 2026",
    "sg:postcode":"2265",
    "sg:province":"NSW",
    "sg:tags":[
        "therapy"
    ],
    "wof:name":"Bless Terri",
    "wof:placetype":"venue"
},
  "geometry": {"coordinates":[151.457809,-33.100819],"type":"Point"}
}