{
  "type": "Feature",
  "properties": {
    "addr:full":"296 Main Rd Cardiff NSW 2285",
    "addr:housenumber":"296",
    "addr:postcode":"2285",
    "addr:street":"Main Rd",
    "iso:country":"AU",
    "sg:address":"296 Main Rd",
    "sg:city":"Cardiff",
    "sg:classifiers":[
        {
            "category":"Banks & Credit Unions",
            "subcategory":"Financial Services",
            "type":"Services"
        }
    ],
    "sg:phone":"+61 2 4921 9905",
    "sg:postcode":"2285",
    "sg:province":"NSW",
    "sg:tags":[
        "building",
        "society"
    ],
    "wof:name":"Greater Building Society Ltd",
    "wof:placetype":"venue"
},
  "geometry": {"coordinates":[151.659545898,-32.9398612976],"type":"Point"}
}