{
  "type": "Feature",
  "properties": {
    "addr:full":"PO Box 284 Hillarys WA 6025",
    "addr:postcode":"6025",
    "iso:country":"AU",
    "sg:address":"PO Box 284",
    "sg:city":"Hillarys",
    "sg:classifiers":[
        {
            "category":"Military Area",
            "subcategory":"Air Force Base",
            "type":"Public Place"
        }
    ],
    "sg:phone":"+61 412 911 368",
    "sg:postcode":"6025",
    "sg:province":"WA",
    "sg:tags":[
        "wholesaler",
        "bag",
        "mfrs",
        "sack"
    ],
    "wof:name":"Calico Imports",
    "wof:placetype":"venue"
},
  "geometry": {"coordinates":[115.74561309800001,-31.8076992035],"type":"Point"}
}