{
  "type": "Feature",
  "properties": {
    "addr:full":"54 Balmoral Rd Warrnambool VIC 3280",
    "addr:housenumber":"54",
    "addr:postcode":"3280",
    "addr:street":"Balmoral Rd",
    "iso:country":"AU",
    "sg:address":"54 Balmoral Rd",
    "sg:city":"Warrnambool",
    "sg:classifiers":[
        {
            "category":"Building & Trades",
            "subcategory":"Construction",
            "type":"Services"
        }
    ],
    "sg:phone":"+61 3 5562 7388",
    "sg:postcode":"3280",
    "sg:province":"VIC",
    "sg:tags":[
        "joiner",
        "carpenter"
    ],
    "wof:name":"McCarthy Kevin",
    "wof:placetype":"venue"
},
  "geometry": {"coordinates":[142.50502014200001,-38.3629417419],"type":"Point"}
}