{
  "type": "Feature",
  "properties": {
    "addr:full":"1180 Centre Rd Clayton South VIC 3169",
    "addr:housenumber":"1180",
    "addr:postcode":"3169",
    "addr:street":"Centre Rd",
    "iso:country":"AU",
    "sg:address":"1180 Centre Rd",
    "sg:city":"Clayton South",
    "sg:classifiers":[
        {
            "category":"Health Services",
            "subcategory":"Doctor",
            "type":"Services"
        }
    ],
    "sg:phone":"+61 3 9562 7119",
    "sg:postcode":"3169",
    "sg:province":"VIC",
    "sg:tags":[
        "medical",
        "practitioner"
    ],
    "wof:name":"Milonas P Dr",
    "wof:placetype":"venue"
},
  "geometry": {"coordinates":[145.10426330600001,-37.9268188477],"type":"Point"}
}