{
  "type": "Feature",
  "properties": {
    "addr:full":"28 O'Shanesy St Gracemere QLD 4702",
    "addr:housenumber":"28",
    "addr:postcode":"4702",
    "addr:street":"O'Shanesy St",
    "iso:country":"AU",
    "sg:address":"28 O'Shanesy St",
    "sg:city":"Gracemere",
    "sg:classifiers":[
        {
            "category":"Wholesale",
            "subcategory":"Machinery & Supplies",
            "type":"Manufacturing & Wholesale Goods"
        }
    ],
    "sg:phone":"+61 7 4933 4500",
    "sg:postcode":"4702",
    "sg:province":"QLD",
    "sg:tags":[
        "agricultural"
    ],
    "wof:name":"Tractor Central",
    "wof:placetype":"venue"
},
  "geometry": {"coordinates":[150.452194214,-23.4334201813],"type":"Point"}
}