{
  "type": "Feature",
  "properties": {
    "addr:full":"59 Middle Boambee Rd Coffs Harbour NSW 2450",
    "addr:housenumber":"59",
    "addr:postcode":"2450",
    "addr:street":"Middle Boambee Rd",
    "iso:country":"AU",
    "sg:address":"59 Middle Boambee Rd",
    "sg:city":"Coffs Harbour",
    "sg:classifiers":[
        {
            "category":"Utilities",
            "subcategory":"Telephone",
            "type":"Services"
        }
    ],
    "sg:phone":"+61 2 6653 3396",
    "sg:postcode":"2450",
    "sg:province":"NSW",
    "sg:tags":[
        "installation",
        "system",
        "maintenance"
    ],
    "wof:name":"Avid Communications",
    "wof:placetype":"venue"
},
  "geometry": {"coordinates":[153.063354,-30.33473],"type":"Point"}
}