{
  "type": "Feature",
  "properties": {
    "addr:full":"Shop 14, Rockingham City Read St Rockingham WA 6168",
    "addr:housenumber":"shop 14",
    "addr:postcode":"6168",
    "addr:street":"Read St",
    "iso:country":"AU",
    "sg:address":"Shop 14, Rockingham City Read St",
    "sg:city":"Rockingham",
    "sg:classifiers":[
        {
            "category":"Personal",
            "subcategory":"Skin Care",
            "type":"Services"
        }
    ],
    "sg:phone":"+61 8 9527 6787",
    "sg:postcode":"6168",
    "sg:province":"WA",
    "sg:tags":[
        "hair",
        "product"
    ],
    "wof:name":"Price Attack",
    "wof:placetype":"venue"
},
  "geometry": {"coordinates":[115.736557,-32.280621],"type":"Point"}
}