{
  "type": "Feature",
  "properties": {
    "addr:full":"32 Princes Hwy Stratford VIC 3862",
    "addr:housenumber":"32",
    "addr:postcode":"3862",
    "addr:street":"Princes Hwy",
    "iso:country":"AU",
    "sg:address":"32 Princes Hwy",
    "sg:city":"Stratford",
    "sg:classifiers":[
        {
            "category":"Building & Trades",
            "subcategory":"Construction",
            "type":"Services"
        }
    ],
    "sg:phone":"+61 3 5145 6181",
    "sg:postcode":"3862",
    "sg:province":"VIC",
    "sg:tags":[
        "earth",
        "excavating",
        "moving",
        "contractor"
    ],
    "wof:name":"H & H Contracting Pty Ltd",
    "wof:placetype":"venue"
},
  "geometry": {"coordinates":[147.069625855,-38.090763092],"type":"Point"}
}