{
  "type": "Feature",
  "properties": {
    "addr:full":"McFarlane Drv Minchinbury NSW 2770",
    "addr:postcode":"2770",
    "addr:street":"Mcfarlane Drv",
    "iso:country":"AU",
    "sg:address":"McFarlane Drv",
    "sg:city":"Minchinbury",
    "sg:classifiers":[
        {
            "category":"Utilities",
            "subcategory":"Electric",
            "type":"Services"
        }
    ],
    "sg:phone":"+61 419 109 901",
    "sg:postcode":"2770",
    "sg:province":"NSW",
    "sg:tags":[
        "electrical",
        "contractor"
    ],
    "wof:name":"Barnstable Ray",
    "wof:placetype":"venue"
},
  "geometry": {"coordinates":[150.82659912099999,-33.7832946777],"type":"Point"}
}