{
  "type": "Feature",
  "properties": {
    "iso:country":"AU",
    "sg:address":"64 Kosciusko Rd",
    "sg:city":"Thurgoona",
    "sg:classifiers":[
        {
            "category":"Building & Trades",
            "subcategory":"Cleaning & Sanitation",
            "type":"Services"
        }
    ],
    "sg:phone":"+61 412 431 147",
    "sg:postcode":"2640",
    "sg:province":"NSW",
    "sg:tags":[
        "window"
    ],
    "wof:name":"All Round & Thurgoona Contractors",
    "wof:placetype":"venue"
},
  "geometry": {"coordinates":[146.99012756400001,-36.0492668152],"type":"Point"}
}