{
  "type": "Feature",
  "properties": {
    "iso:country":"AU",
    "sg:address":"Cnr Dawson Hwy & Park St",
    "sg:city":"Gladstone",
    "sg:classifiers":[
        {
            "category":"Health Services",
            "subcategory":"Doctor",
            "type":"Services"
        }
    ],
    "sg:phone":"+61 13 10 55",
    "sg:postcode":"4680",
    "sg:province":"QLD",
    "sg:tags":[
        "medical",
        "practitioner"
    ],
    "wof:name":"Medihelp General Practice",
    "wof:placetype":"venue"
},
  "geometry": {"coordinates":[151.24978637699999,-23.8529491425],"type":"Point"}
}