{
  "type": "Feature",
  "properties": {
    "addr:full":"21 Port Stephens St Raymond Terrace NSW 2324",
    "addr:housenumber":"21",
    "addr:postcode":"2324",
    "addr:street":"Port Stephens St",
    "iso:country":"AU",
    "sg:address":"21 Port Stephens St",
    "sg:city":"Raymond Terrace",
    "sg:classifiers":[
        {
            "category":"Structure",
            "subcategory":"Bridge",
            "type":"Public Place"
        }
    ],
    "sg:phone":"+61 2 4987 3355",
    "sg:postcode":"2324",
    "sg:province":"NSW",
    "sg:tags":[
        "chainsaw",
        "brushcutters"
    ],
    "wof:name":"Terrace Mowers",
    "wof:placetype":"venue"
},
  "geometry": {"coordinates":[151.74525451700001,-32.7593345642],"type":"Point"}
}