{
  "type": "Feature",
  "properties": {
    "iso:country":"AU",
    "sg:address":"Oak St",
    "sg:city":"Drouin",
    "sg:classifiers":[
        {
            "category":"Education",
            "subcategory":"Kindergarten",
            "type":"Public Place"
        }
    ],
    "sg:phone":"+61 3 5625 1520",
    "sg:postcode":"3818",
    "sg:province":"VIC",
    "sg:tags":[
        "pre-schools"
    ],
    "wof:name":"Drouin Oak Street Kindergarten",
    "wof:placetype":"venue"
},
  "geometry": {"coordinates":[145.85560599999999,-38.13718],"type":"Point"}
}