{
  "type": "Feature",
  "properties": {
    "addr:full":"U2/ 98 Old Pittwater Rd Brookvale NSW 2100",
    "addr:housenumber":"98",
    "addr:postcode":"2100",
    "addr:street":"U2 /;Old Pittwater Rd",
    "iso:country":"AU",
    "sg:address":"U2/ 98 Old Pittwater Rd",
    "sg:city":"Brookvale",
    "sg:classifiers":[
        {
            "category":"Utilities",
            "subcategory":"Cable",
            "type":"Services"
        }
    ],
    "sg:phone":"+61 2 9905 1591",
    "sg:postcode":"2100",
    "sg:province":"NSW",
    "sg:tags":[
        "synthetic",
        "rope",
        "fitting",
        "wire"
    ],
    "wof:name":"Sydney Lifting Equipment Pty Ltd",
    "wof:placetype":"venue"
},
  "geometry": {"coordinates":[151.26356506400001,-33.7635498047],"type":"Point"}
}