{
  "type": "Feature",
  "properties": {
    "addr:full":"62 Butler St Tully QLD 4854",
    "addr:housenumber":"62",
    "addr:postcode":"4854",
    "addr:street":"Butler St",
    "iso:country":"AU",
    "sg:address":"62 Butler St",
    "sg:city":"Tully",
    "sg:classifiers":[
        {
            "category":"Banks & Credit Unions",
            "subcategory":"Bureau De Change",
            "type":"Services"
        }
    ],
    "sg:phone":"+61 7 4068 1440",
    "sg:postcode":"4854",
    "sg:province":"QLD",
    "sg:tags":[
        "repairs",
        "part",
        "appliance",
        "electrical"
    ],
    "wof:name":"Tully Electronics",
    "wof:placetype":"venue"
},
  "geometry": {"coordinates":[145.926437378,-17.9339046478],"type":"Point"}
}