{
  "type": "Feature",
  "properties": {
    "addr:full":"24 Bemersyde Drv Berwick VIC 3806",
    "addr:housenumber":"24",
    "addr:postcode":"3806",
    "addr:street":"Bemersyde Drv",
    "iso:country":"AU",
    "sg:address":"24 Bemersyde Drv",
    "sg:city":"Berwick",
    "sg:classifiers":[
        {
            "category":"Food & Beverages",
            "subcategory":"Groceries & Convenience Stores",
            "type":"Retail Goods"
        }
    ],
    "sg:phone":"+61 3 9702 1060",
    "sg:postcode":"3806",
    "sg:province":"VIC",
    "wof:name":"Brentwood Mini Mart",
    "wof:placetype":"venue"
},
  "geometry": {"coordinates":[145.34695434599999,-38.0509529114],"type":"Point"}
}