{
  "type": "Feature",
  "properties": {
    "iso:country":"AU",
    "sg:address":"37 Courageous Crt",
    "sg:city":"Scarborough",
    "sg:classifiers":[
        {
            "category":"Utilities",
            "subcategory":"Electric",
            "type":"Services"
        }
    ],
    "sg:phone":"+61 7 3880 1481",
    "sg:postcode":"4020",
    "sg:province":"QLD",
    "sg:tags":[
        "electrical",
        "contractor"
    ],
    "wof:name":"Pirie Electrical",
    "wof:placetype":"venue"
},
  "geometry": {"coordinates":[153.096405,-27.208305],"type":"Point"}
}