{
  "type": "Feature",
  "properties": {
    "addr:full":"Shop 4, 99 Kedron Brook Rd Wilston QLD 4051",
    "addr:housenumber":"shop;99",
    "addr:postcode":"4051",
    "addr:street":"Kedron Brook Rd",
    "iso:country":"AU",
    "sg:address":"Shop 4, 99 Kedron Brook Rd",
    "sg:city":"Wilston",
    "sg:classifiers":[
        {
            "category":"Cafe",
            "type":"Food & Drink"
        }
    ],
    "sg:phone":"+61 7 3356 5988",
    "sg:postcode":"4051",
    "sg:province":"QLD",
    "wof:name":"Coffee Club The",
    "wof:placetype":"venue"
},
  "geometry": {"coordinates":[153.01971435600001,-27.4320545197],"type":"Point"}
}