{
  "type": "Feature",
  "properties": {
    "iso:country":"AU",
    "sg:address":"44 Uduc Rd",
    "sg:city":"Harvey",
    "sg:classifiers":[
        {
            "category":"Health Services",
            "subcategory":"Doctor",
            "type":"Services"
        }
    ],
    "sg:phone":"+61 8 9729 1600",
    "sg:postcode":"6220",
    "sg:province":"WA",
    "sg:tags":[
        "medical",
        "practitioner"
    ],
    "wof:name":"Wu H L",
    "wof:placetype":"venue"
},
  "geometry": {"coordinates":[115.89971199999999,-33.080936],"type":"Point"}
}