{
  "type": "Feature",
  "properties": {
    "addr:full":"U4/ 51 Chard Rd Brookvale NSW 2100",
    "addr:housenumber":"51",
    "addr:postcode":"2100",
    "addr:street":"U4 /;Chard Rd",
    "iso:country":"AU",
    "sg:address":"U4/ 51 Chard Rd",
    "sg:city":"Brookvale",
    "sg:classifiers":[
        {
            "category":"Wholesale",
            "subcategory":"Home Furnishings",
            "type":"Manufacturing & Wholesale Goods"
        }
    ],
    "sg:phone":"+61 2 9907 1641",
    "sg:postcode":"2100",
    "sg:province":"NSW",
    "sg:tags":[
        "wholesaler",
        "mfrs",
        "manchester"
    ],
    "wof:name":"Bas Phillips Pty Ltd",
    "wof:placetype":"venue"
},
  "geometry": {"coordinates":[151.27525329599999,-33.7635803223],"type":"Point"}
}