{
  "type": "Feature",
  "properties": {
    "iso:country":"AU",
    "sg:address":"421 Victoria St",
    "sg:city":"Brunswick",
    "sg:classifiers":[
        {
            "category":"Wholesale",
            "subcategory":"Electrical",
            "type":"Manufacturing & Wholesale Goods"
        }
    ],
    "sg:phone":"+61 1300 656 090",
    "sg:postcode":"3056",
    "sg:province":"VIC",
    "sg:tags":[
        "control",
        "equipment",
        "switch"
    ],
    "wof:name":"Crompton Instruments",
    "wof:placetype":"venue"
},
  "geometry": {"coordinates":[144.953292847,-37.7658233643],"type":"Point"}
}