{
  "type": "Feature",
  "properties": {
    "addr:full":"159 Walter Rd West Dianella WA 6059",
    "addr:housenumber":"159",
    "addr:postcode":"6059",
    "addr:street":"Walter Rd West",
    "iso:country":"AU",
    "sg:address":"159 Walter Rd West",
    "sg:city":"Dianella",
    "sg:classifiers":[
        {
            "category":"Personal",
            "subcategory":"Beauty Salon",
            "type":"Services"
        }
    ],
    "sg:phone":"+61 8 9275 4419",
    "sg:postcode":"6059",
    "sg:province":"WA",
    "wof:name":"New York Nails",
    "wof:placetype":"venue"
},
  "geometry": {"coordinates":[115.888961792,-31.8996829987],"type":"Point"}
}