{
  "type": "Feature",
  "properties": {
    "addr:full":"1232 Burwood Hwy Ferntree Gully VIC 3156",
    "addr:housenumber":"1232",
    "addr:postcode":"3156",
    "addr:street":"Burwood Hwy",
    "iso:country":"AU",
    "sg:address":"1232 Burwood Hwy",
    "sg:city":"Ferntree Gully",
    "sg:classifiers":[
        {
            "category":"Social Services",
            "type":"Services"
        }
    ],
    "sg:phone":"+61 404 097 541",
    "sg:postcode":"3156",
    "sg:province":"VIC",
    "sg:tags":[
        "kinesiology"
    ],
    "wof:name":"Kim McNeill",
    "wof:placetype":"venue"
},
  "geometry": {"coordinates":[145.31098938,-37.893737793],"type":"Point"}
}