{
  "type": "Feature",
  "properties": {
    "addr:full":"149- 153 Epping Rd Marsfield NSW 2122",
    "addr:housenumber":"153",
    "addr:postcode":"2122",
    "addr:street":"Epping Rd",
    "iso:country":"AU",
    "sg:address":"149- 153 Epping Rd",
    "sg:city":"Marsfield",
    "sg:classifiers":[
        {
            "category":"Social Services",
            "subcategory":"Retirement Home",
            "type":"Services"
        }
    ],
    "sg:phone":"+61 2 9346 1340",
    "sg:postcode":"2122",
    "sg:province":"NSW",
    "sg:tags":[
        "village"
    ],
    "wof:name":"BCS Willandra Village",
    "wof:placetype":"venue"
},
  "geometry": {"coordinates":[151.09846496599999,-33.7708702087],"type":"Point"}
}