{
  "type": "Feature",
  "properties": {
    "addr:full":"Hangar 5 / 2 First Street Moorabbin Airport VIC 3194",
    "addr:housenumber":"2",
    "addr:postcode":"3194",
    "addr:street":"First Street",
    "iso:country":"AU",
    "sg:address":"Hangar 5 / 2",
    "sg:city":"First Street Moorabbin Airport",
    "sg:classifiers":[
        {
            "category":"Airline",
            "type":"Transportation"
        }
    ],
    "sg:phone":"+61 418 311 686",
    "sg:postcode":"3194",
    "sg:province":"VIC",
    "sg:tags":[
        "aircraft",
        "rental",
        "charter"
    ],
    "wof:name":"Warbird Flights",
    "wof:placetype":"venue"
},
  "geometry": {"coordinates":[145.09268188499999,-37.9750671387],"type":"Point"}
}