{
  "type": "Feature",
  "properties": {
    "iso:country":"AU",
    "sg:address":"331 Wynnum North Rd",
    "sg:city":"Wynnum North",
    "sg:classifiers":[
        {
            "category":"Professional",
            "subcategory":"Accounting & Tax Preparation",
            "type":"Services"
        }
    ],
    "sg:phone":"+61 7 3396 1747",
    "sg:postcode":"4178",
    "sg:province":"QLD",
    "sg:tags":[
        "accountant",
        "auditor"
    ],
    "wof:name":"Baz Accounting",
    "wof:placetype":"venue"
},
  "geometry": {"coordinates":[153.16279602,-27.4293022156],"type":"Point"}
}