{
  "type": "Feature",
  "properties": {
    "addr:full":"7 Boyer Rd Beacon Hill NSW 2100",
    "addr:housenumber":"7",
    "addr:postcode":"2100",
    "addr:street":"Boyer Rd",
    "iso:country":"AU",
    "sg:address":"7 Boyer Rd",
    "sg:city":"Beacon Hill",
    "sg:classifiers":[
        {
            "category":"Education",
            "subcategory":"Kindergarten",
            "type":"Public Place"
        }
    ],
    "sg:phone":"+61 2 9975 1888",
    "sg:postcode":"2100",
    "sg:province":"NSW",
    "sg:tags":[
        "pre-schools"
    ],
    "wof:name":"Holy Trinity Kindergarten",
    "wof:placetype":"venue"
},
  "geometry": {"coordinates":[151.25349426299999,-33.7494239807],"type":"Point"}
}