{
  "type": "Feature",
  "properties": {
    "iso:country":"AU",
    "sg:address":"PO Box 508",
    "sg:city":"Pascoe Vale",
    "sg:classifiers":[
        {
            "category":"Building & Trades",
            "subcategory":"Construction",
            "type":"Services"
        }
    ],
    "sg:phone":"+61 3 9304 2777",
    "sg:postcode":"3044",
    "sg:province":"VIC",
    "sg:tags":[
        "earth",
        "excavating",
        "moving",
        "contractor"
    ],
    "wof:name":"CDC Products",
    "wof:placetype":"venue"
},
  "geometry": {"coordinates":[144.93971252399999,-37.7242393494],"type":"Point"}
}