{
  "type": "Feature",
  "properties": {
    "addr:full":"Ground Floor, 184 Parry St Newcastle West NSW 2302",
    "addr:housenumber":"184",
    "addr:postcode":"2302",
    "addr:street":"Parry St",
    "iso:country":"AU",
    "sg:address":"Ground Floor, 184 Parry St",
    "sg:city":"Newcastle West",
    "sg:classifiers":[
        {
            "category":"Professional",
            "subcategory":"Accounting & Tax Preparation",
            "type":"Services"
        }
    ],
    "sg:phone":"+61 2 4969 5777",
    "sg:postcode":"2302",
    "sg:province":"NSW",
    "sg:tags":[
        "accountant",
        "auditor"
    ],
    "wof:name":"Maher Ebrill McLean",
    "wof:placetype":"venue"
},
  "geometry": {"coordinates":[151.760254,-32.92836],"type":"Point"}
}