{
  "type": "Feature",
  "properties": {
    "addr:full":"15 Jordan Crt Aberfoyle Park SA 5159",
    "addr:housenumber":"15",
    "addr:postcode":"5159",
    "addr:street":"Jordan Crt",
    "iso:country":"AU",
    "sg:address":"15 Jordan Crt",
    "sg:city":"Aberfoyle Park",
    "sg:classifiers":[
        {
            "category":"Home & Garden",
            "subcategory":"Household Appliances",
            "type":"Retail Goods"
        }
    ],
    "sg:phone":"+61 418 831 280",
    "sg:postcode":"5159",
    "sg:province":"SA",
    "sg:tags":[
        "equipment",
        "gas"
    ],
    "wof:name":"Instant Gas & Plumbing Services Pty Ltd",
    "wof:placetype":"venue"
},
  "geometry": {"coordinates":[138.604125977,-35.0715675354],"type":"Point"}
}