{
  "type": "Feature",
  "properties": {
    "iso:country":"AU",
    "sg:address":"308 Malven Rd",
    "sg:city":"Prahran",
    "sg:classifiers":[
        {
            "category":"Health Services",
            "subcategory":"Doctor",
            "type":"Services"
        }
    ],
    "sg:phone":"+61 3 9328 5222",
    "sg:postcode":"3181",
    "sg:province":"VIC",
    "sg:tags":[
        "medical",
        "practitioner"
    ],
    "wof:name":"O&#039;Sullivan Mark",
    "wof:placetype":"venue"
},
  "geometry": {"coordinates":[144.997116089,-37.8473739624],"type":"Point"}
}