{
  "type": "Feature",
  "properties": {
    "iso:country":"AU",
    "sg:address":"105 Vernon St",
    "sg:city":"Nundah",
    "sg:classifiers":[
        {
            "category":"Professional",
            "subcategory":"Art Services",
            "type":"Services"
        }
    ],
    "sg:phone":"+61 7 3266 5547",
    "sg:postcode":"4012",
    "sg:province":"QLD",
    "sg:tags":[
        "artist"
    ],
    "wof:name":"Maria Cosgrove",
    "wof:placetype":"venue"
},
  "geometry": {"coordinates":[153.070602417,-27.4022464752],"type":"Point"}
}