{
  "type": "Feature",
  "properties": {
    "addr:full":"Shop 16, Lower Ground Walk, 455 George St Sydney NSW 2000",
    "addr:housenumber":"shop 16;455",
    "addr:postcode":"2000",
    "addr:street":"Ground Walk;George St",
    "iso:country":"AU",
    "sg:address":"Shop 16, Lower Ground Walk, 455 George St",
    "sg:city":"Sydney",
    "sg:classifiers":[
        {
            "category":"Shopping",
            "subcategory":"Beauty & Cosmetics",
            "type":"Retail Goods"
        }
    ],
    "sg:phone":"+61 2 8198 8203",
    "sg:postcode":"2000",
    "sg:province":"NSW",
    "wof:name":"Aveda Experience Centre",
    "wof:placetype":"venue"
},
  "geometry": {"coordinates":[151.206863403,-33.8719215393],"type":"Point"}
}