{
  "type": "Feature",
  "properties": {
    "iso:country":"AU",
    "sg:address":"PO Box 288",
    "sg:city":"Enmore",
    "sg:classifiers":[
        {
            "category":"Professional",
            "subcategory":"Art Services",
            "type":"Services"
        }
    ],
    "sg:phone":"+61 415 433 107",
    "sg:postcode":"2042",
    "sg:province":"NSW",
    "sg:tags":[
        "decorator",
        "painter"
    ],
    "wof:name":"1st Class Painting & Decorating Services",
    "wof:placetype":"venue"
},
  "geometry": {"coordinates":[151.171173,-33.899288],"type":"Point"}
}