{
  "type": "Feature",
  "properties": {
    "addr:full":"Cnr Mclean & Callandoon Sts Goondiwindi QLD 4390",
    "addr:postcode":"4390",
    "addr:street":"Cnr",
    "iso:country":"AU",
    "sg:address":"Cnr Mclean & Callandoon Sts",
    "sg:city":"Goondiwindi",
    "sg:classifiers":[
        {
            "category":"Autos & Motor Vehicles",
            "subcategory":"Automobile Sales",
            "type":"Retail Goods"
        }
    ],
    "sg:phone":"+61 7 4671 3044",
    "sg:postcode":"4390",
    "sg:province":"QLD",
    "sg:tags":[
        "car",
        "new"
    ],
    "wof:name":"Rod Gibson Ford",
    "wof:placetype":"venue"
},
  "geometry": {"coordinates":[150.307495117,-28.5473709106],"type":"Point"}
}