{
  "type": "Feature",
  "properties": {
    "iso:country":"AU",
    "sg:address":"Unit 1/ 305 Manns Rd",
    "sg:city":"Gosford West",
    "sg:classifiers":[
        {
            "category":"Home & Garden",
            "subcategory":"Building Materials",
            "type":"Retail Goods"
        }
    ],
    "sg:phone":"+61 2 4324 8800",
    "sg:postcode":"2250",
    "sg:province":"NSW",
    "sg:tags":[
        "insect",
        "screen"
    ],
    "wof:name":"Danzara Pty Ltd",
    "wof:placetype":"venue"
},
  "geometry": {"coordinates":[151.319381714,-33.424571991],"type":"Point"}
}