{
  "type": "Feature",
  "properties": {
    "addr:full":"294- 298 Swan St Richmond VIC 3121",
    "addr:housenumber":"298",
    "addr:postcode":"3121",
    "addr:street":"Swan St",
    "iso:country":"AU",
    "sg:address":"294- 298 Swan St",
    "sg:city":"Richmond",
    "sg:classifiers":[
        {
            "category":"Communications",
            "subcategory":"Film & Video Production",
            "type":"Services"
        }
    ],
    "sg:phone":"+61 3 9427 0706",
    "sg:postcode":"3121",
    "sg:province":"VIC",
    "sg:tags":[
        "dvd",
        "library"
    ],
    "wof:name":"Blockbuster",
    "wof:placetype":"venue"
},
  "geometry": {"coordinates":[145.00071716299999,-37.8261146545],"type":"Point"}
}