{
  "type": "Feature",
  "properties": {
    "addr:full":"Conness St Chiltern VIC 3683",
    "addr:postcode":"3683",
    "addr:street":"St",
    "iso:country":"AU",
    "sg:address":"Conness St",
    "sg:city":"Chiltern",
    "sg:classifiers":[
        {
            "category":"Travel",
            "subcategory":"Hotels & Motels",
            "type":"Entertainment"
        }
    ],
    "sg:phone":"+61 3 5726 1470",
    "sg:postcode":"3683",
    "sg:province":"VIC",
    "sg:tags":[
        "accommodation"
    ],
    "wof:name":"Chiltern Telegraph Hotel",
    "wof:placetype":"venue"
},
  "geometry": {"coordinates":[146.60772700000001,-36.151257],"type":"Point"}
}