{
  "type": "Feature",
  "properties": {
    "addr:full":"Lot 2 Mortensen Rd Nerang QLD 4211",
    "addr:postcode":"4211",
    "addr:street":"Mortensen Rd",
    "iso:country":"AU",
    "sg:address":"Lot 2 Mortensen Rd",
    "sg:city":"Nerang",
    "sg:classifiers":[
        {
            "category":"Communications",
            "subcategory":"Film & Video Production",
            "type":"Services"
        }
    ],
    "sg:phone":"+61 7 5578 3855",
    "sg:postcode":"4211",
    "sg:province":"QLD",
    "sg:tags":[
        "dvd",
        "library"
    ],
    "wof:name":"Video Ezy",
    "wof:placetype":"venue"
},
  "geometry": {"coordinates":[153.33799743599999,-28.0057449341],"type":"Point"}
}