{
  "type": "Feature",
  "properties": {
    "addr:full":"Shop 3, 37-39 Main Rd Wivenhoe TAS 7320",
    "addr:housenumber":"shop 3 37-39",
    "addr:postcode":"7320",
    "addr:street":"Main Rd",
    "iso:country":"AU",
    "sg:address":"Shop 3, 37-39 Main Rd",
    "sg:city":"Wivenhoe",
    "sg:classifiers":[
        {
            "category":"Deli",
            "type":"Food & Drink"
        }
    ],
    "sg:phone":"+61 3 6431 2211",
    "sg:postcode":"7320",
    "sg:province":"TAS",
    "sg:tags":[
        "delicatessen"
    ],
    "wof:name":"Delish Fine Foods",
    "wof:placetype":"venue"
},
  "geometry": {"coordinates":[145.93620300000001,-41.068062],"type":"Point"}
}