{
  "type": "Feature",
  "properties": {
    "iso:country":"AU",
    "sg:address":"PO Box 780",
    "sg:city":"Blackwood",
    "sg:classifiers":[
        {
            "category":"Education",
            "subcategory":"Music School",
            "type":"Public Place"
        }
    ],
    "sg:phone":"+61 8 8358 6781",
    "sg:postcode":"5051",
    "sg:province":"SA",
    "sg:tags":[
        "teacher"
    ],
    "wof:name":"Doctor Rhythm",
    "wof:placetype":"venue"
},
  "geometry": {"coordinates":[138.611435,-35.020821],"type":"Point"}
}