{
  "type": "Feature",
  "properties": {
    "iso:country":"AU",
    "sg:address":"Barrina St",
    "sg:city":"Blackburn South",
    "sg:classifiers":[
        {
            "category":"Social Services",
            "subcategory":"Retirement Home",
            "type":"Services"
        }
    ],
    "sg:phone":"+61 3 9899 4150",
    "sg:postcode":"3130",
    "sg:province":"VIC",
    "sg:tags":[
        "village"
    ],
    "wof:name":"Barrina Gardens Retirement Community",
    "wof:placetype":"venue"
},
  "geometry": {"coordinates":[145.141082764,-37.835521698],"type":"Point"}
}