{
  "type": "Feature",
  "properties": {
    "addr:full":"62 McLahlan Ave Rushcutters Bay NSW 2011",
    "addr:housenumber":"62",
    "addr:postcode":"2011",
    "addr:street":"Mclahlan Ave",
    "iso:country":"AU",
    "sg:address":"62 McLahlan Ave",
    "sg:city":"Rushcutters Bay",
    "sg:classifiers":[
        {
            "category":"Manufacturing",
            "subcategory":"Motor Vehicles & Parts",
            "type":"Manufacturing & Wholesale Goods"
        }
    ],
    "sg:phone":"+61 2 9332 4477",
    "sg:postcode":"2011",
    "sg:province":"NSW",
    "sg:tags":[
        "replacement"
    ],
    "wof:name":"Sanderson's Eastern Suburbs Pty Ltd",
    "wof:placetype":"venue"
},
  "geometry": {"coordinates":[151.228607178,-33.8764648438],"type":"Point"}
}