{
  "type": "Feature",
  "properties": {
    "addr:full":"1046 Jensen Rd Griffith NSW 2680",
    "addr:housenumber":"1046",
    "addr:postcode":"2680",
    "addr:street":"Jensen Rd",
    "iso:country":"AU",
    "sg:address":"1046 Jensen Rd",
    "sg:city":"Griffith",
    "sg:classifiers":[
        {
            "category":"Manufacturing",
            "subcategory":"Building Materials",
            "type":"Manufacturing & Wholesale Goods"
        }
    ],
    "sg:phone":"+61 2 6964 4554",
    "sg:postcode":"2680",
    "sg:province":"NSW",
    "sg:tags":[
        "aggregate",
        "concrete"
    ],
    "wof:name":"J J Stevenson",
    "wof:placetype":"venue"
},
  "geometry": {"coordinates":[146.05656400000001,-34.29591],"type":"Point"}
}