{
  "type": "Feature",
  "properties": {
    "iso:country":"AU",
    "sg:address":"125b Falcon St",
    "sg:city":"Crows Nest",
    "sg:classifiers":[
        {
            "category":"Retail",
            "subcategory":"Auto Repair",
            "type":"Services"
        }
    ],
    "sg:phone":"+61 2 9955 5153",
    "sg:postcode":"2065",
    "sg:province":"NSW",
    "sg:tags":[
        "repairer",
        "motor",
        "engineer"
    ],
    "wof:name":"Germania Motors",
    "wof:placetype":"venue"
},
  "geometry": {"coordinates":[151.206665039,-33.8286857605],"type":"Point"}
}