{
  "type": "Feature",
  "properties": {
    "addr:full":"645 Arthurs Creek Rd Arthurs Creek VIC 3099",
    "addr:housenumber":"645",
    "addr:postcode":"3099",
    "addr:street":"Arthurs Creek Rd",
    "iso:country":"AU",
    "sg:address":"645 Arthurs Creek Rd",
    "sg:city":"Arthurs Creek",
    "sg:classifiers":[
        {
            "category":"Utilities",
            "subcategory":"Water",
            "type":"Services"
        }
    ],
    "sg:phone":"+61 3 9714 8217",
    "sg:postcode":"3099",
    "sg:province":"VIC",
    "sg:tags":[
        "cartage"
    ],
    "wof:name":"A C Water Cartage",
    "wof:placetype":"venue"
},
  "geometry": {"coordinates":[145.199676514,-37.5790481567],"type":"Point"}
}