{
  "type": "Feature",
  "properties": {
    "addr:full":"Lot 101 Kirby's Rd Montville QLD 4560",
    "addr:postcode":"4560",
    "addr:street":"Kirby'S Rd",
    "iso:country":"AU",
    "sg:address":"Lot 101 Kirby's Rd",
    "sg:city":"Montville",
    "sg:classifiers":[
        {
            "category":"Building & Trades",
            "subcategory":"Construction",
            "type":"Services"
        }
    ],
    "sg:phone":"+61 7 5445 9819",
    "sg:postcode":"4560",
    "sg:province":"QLD",
    "sg:tags":[
        "renovation",
        "alterations",
        "extension",
        "contractor"
    ],
    "wof:name":"Van de Vorst L",
    "wof:placetype":"venue"
},
  "geometry": {"coordinates":[153.03419494600001,-26.6149291992],"type":"Point"}
}