{
  "type": "Feature",
  "properties": {
    "addr:full":"38 Sorbonne Crs Canning Vale WA 6155",
    "addr:housenumber":"38",
    "addr:postcode":"6155",
    "addr:street":"Sorbonne Crs",
    "iso:country":"AU",
    "sg:address":"38 Sorbonne Crs",
    "sg:city":"Canning Vale",
    "sg:classifiers":[
        {
            "category":"Structure",
            "subcategory":"Building",
            "type":"Public Place"
        }
    ],
    "sg:phone":"+61 8 9456 0996",
    "sg:postcode":"6155",
    "sg:province":"WA",
    "sg:tags":[
        "sail",
        "shade"
    ],
    "sg:website":"http://www.shadexperience.com",
    "wof:name":"Shade Experience",
    "wof:placetype":"venue"
},
  "geometry": {"coordinates":[115.911362,-32.07708],"type":"Point"}
}