{
  "type": "Feature",
  "properties": {
    "addr:full":"Shop 236 Australia Fair Shopping Centre Southport QLD 4215",
    "addr:housenumber":"236",
    "addr:postcode":"4215",
    "iso:country":"AU",
    "sg:address":"Shop 236 Australia Fair Shopping Centre",
    "sg:city":"Southport",
    "sg:classifiers":[
        {
            "category":"Shopping",
            "subcategory":"Clothing, Apparel, & Fashions",
            "type":"Retail Goods"
        }
    ],
    "sg:phone":"+61 7 5532 4192",
    "sg:postcode":"4215",
    "sg:province":"QLD",
    "sg:tags":[
        "lady",
        "wear"
    ],
    "wof:name":"Suzanne Grae",
    "wof:placetype":"venue"
},
  "geometry": {"coordinates":[153.415557861,-27.9655303955],"type":"Point"}
}