{
  "type": "Feature",
  "properties": {
    "addr:full":"Carillon Arcade 680 Hay Perth WA 6000",
    "addr:housenumber":"680",
    "addr:postcode":"6000",
    "addr:street":"Hay",
    "iso:country":"AU",
    "sg:address":"Carillon Arcade 680 Hay",
    "sg:city":"Perth",
    "sg:classifiers":[
        {
            "category":"Fast Food",
            "type":"Food & Drink"
        }
    ],
    "sg:phone":"+61 8 9322 2733",
    "sg:postcode":"6000",
    "sg:province":"WA",
    "sg:tags":[
        "away",
        "take"
    ],
    "wof:name":"Ole Mexican Restaurant",
    "wof:placetype":"venue"
},
  "geometry": {"coordinates":[115.85514831499999,-31.953086853],"type":"Point"}
}