{
  "type": "Feature",
  "properties": {
    "iso:country":"AU",
    "sg:address":"Suite 4a, Level 4 43 Horton St",
    "sg:city":"Port Macquarie",
    "sg:classifiers":[
        {
            "category":"Professional",
            "subcategory":"Art Services",
            "type":"Services"
        }
    ],
    "sg:phone":"+61 2 6588 0083",
    "sg:postcode":"2444",
    "sg:province":"NSW",
    "sg:tags":[
        "graphic",
        "designer"
    ],
    "wof:name":"Gillespie Media",
    "wof:placetype":"venue"
},
  "geometry": {"coordinates":[152.908173,-31.4296],"type":"Point"}
}