{
  "type": "Feature",
  "properties": {
    "addr:full":"28 Blackburn Rd Mooroolbark VIC 3138",
    "addr:housenumber":"28",
    "addr:postcode":"3138",
    "addr:street":"Blackburn Rd",
    "iso:country":"AU",
    "sg:address":"28 Blackburn Rd",
    "sg:city":"Mooroolbark",
    "sg:classifiers":[
        {
            "category":"Building & Trades",
            "subcategory":"Cleaning & Sanitation",
            "type":"Services"
        }
    ],
    "sg:phone":"+61 3 9726 4858",
    "sg:postcode":"3138",
    "sg:province":"VIC",
    "sg:tags":[
        "window"
    ],
    "wof:name":"Hi Glaze Window Cleaning (AUST) PTY LTD",
    "wof:placetype":"venue"
},
  "geometry": {"coordinates":[145.33265685999999,-37.7829551697],"type":"Point"}
}