{
  "type": "Feature",
  "properties": {
    "addr:full":"Shop 10 Main Arcade Junction St Nowra NSW 2541",
    "addr:housenumber":"shop 10",
    "addr:postcode":"2541",
    "addr:street":"Main Arcade Junction St",
    "iso:country":"AU",
    "sg:address":"Shop 10 Main Arcade Junction St",
    "sg:city":"Nowra",
    "sg:classifiers":[
        {
            "category":"Fast Food",
            "type":"Food & Drink"
        }
    ],
    "sg:phone":"+61 2 4421 5505",
    "sg:postcode":"2541",
    "sg:province":"NSW",
    "sg:tags":[
        "away",
        "take"
    ],
    "wof:name":"Oh La La Lunch Bar",
    "wof:placetype":"venue"
},
  "geometry": {"coordinates":[150.59463500999999,-34.8734321594],"type":"Point"}
}