{
  "type": "Feature",
  "properties": {
    "addr:full":"Shop 6 Stirlings Centre Sanford St Geraldton WA 6530",
    "addr:housenumber":"shop 6",
    "addr:postcode":"6530",
    "addr:street":"Stirlings Centre Sanford St",
    "iso:country":"AU",
    "sg:address":"Shop 6 Stirlings Centre Sanford St",
    "sg:city":"Geraldton",
    "sg:classifiers":[
        {
            "category":"Health Services",
            "subcategory":"Optometrist",
            "type":"Services"
        }
    ],
    "sg:phone":"+61 8 9921 3445",
    "sg:postcode":"6530",
    "sg:province":"WA",
    "wof:name":"Midwest Optical",
    "wof:placetype":"venue"
},
  "geometry": {"coordinates":[114.614936829,-28.7718486786],"type":"Point"}
}