{
  "type": "Feature",
  "properties": {
    "addr:full":"35 Strickland St Denmark WA 6333",
    "addr:housenumber":"35",
    "addr:postcode":"6333",
    "addr:street":"Strickland St",
    "iso:country":"AU",
    "sg:address":"35 Strickland St",
    "sg:city":"Denmark",
    "sg:classifiers":[
        {
            "category":"Health Services",
            "subcategory":"Dentist",
            "type":"Services"
        }
    ],
    "sg:phone":"+61 8 9848 1143",
    "sg:postcode":"6333",
    "sg:province":"WA",
    "wof:name":"Heady Robert G",
    "wof:placetype":"venue"
},
  "geometry": {"coordinates":[117.355461121,-34.9605140686],"type":"Point"}
}