{
  "type": "Feature",
  "properties": {
    "addr:full":"257 Barkly St Ararat VIC 3377",
    "addr:housenumber":"257",
    "addr:postcode":"3377",
    "addr:street":"Barkly St",
    "iso:country":"AU",
    "sg:address":"257 Barkly St",
    "sg:city":"Ararat",
    "sg:classifiers":[
        {
            "category":"Travel",
            "subcategory":"Hotels & Motels",
            "type":"Entertainment"
        }
    ],
    "sg:phone":"+61 3 5352 1177",
    "sg:postcode":"3377",
    "sg:province":"VIC",
    "sg:tags":[
        "accommodation"
    ],
    "wof:name":"Blue Duck Hotel",
    "wof:placetype":"venue"
},
  "geometry": {"coordinates":[142.93544006400001,-37.2839508057],"type":"Point"}
}