{
  "type": "Feature",
  "properties": {
    "iso:country":"AU",
    "sg:address":"1a/ 19 Lang Pde",
    "sg:city":"Auchenflower",
    "sg:classifiers":[
        {
            "category":"Building & Trades",
            "subcategory":"Cleaning & Sanitation",
            "type":"Services"
        }
    ],
    "sg:phone":"+61 7 3870 9966",
    "sg:postcode":"4066",
    "sg:province":"QLD",
    "sg:tags":[
        "industrial",
        "commercial",
        "contractor"
    ],
    "wof:name":"Jani-King (Australia) Pty Ltd",
    "wof:placetype":"venue"
},
  "geometry": {"coordinates":[153.001754761,-27.4740123749],"type":"Point"}
}