{
  "type": "Feature",
  "properties": {
    "addr:full":"Unit 1 23 Anthony St West End QLD 4101",
    "addr:housenumber":"23",
    "addr:postcode":"4101",
    "addr:street":"Anthony St",
    "iso:country":"AU",
    "sg:address":"Unit 1 23 Anthony St",
    "sg:city":"West End",
    "sg:classifiers":[
        {
            "category":"Professional",
            "subcategory":"Business Services",
            "type":"Services"
        }
    ],
    "sg:phone":"+61 7 3844 1768",
    "sg:postcode":"4101",
    "sg:province":"QLD",
    "sg:tags":[
        "fashion",
        "agent"
    ],
    "wof:name":"Beitz & Nolan Fashion Agents Pty Ltd",
    "wof:placetype":"venue"
},
  "geometry": {"coordinates":[153.007568359,-27.4767093658],"type":"Point"}
}