{
  "type": "Feature",
  "properties": {
    "iso:country":"AU",
    "sg:address":"PO Box 759",
    "sg:city":"Mornington",
    "sg:classifiers":[
        {
            "category":"Personal",
            "subcategory":"Day Spa",
            "type":"Services"
        }
    ],
    "sg:phone":"+61 1300 737 330",
    "sg:postcode":"3931",
    "sg:province":"VIC",
    "wof:name":"endota spa",
    "wof:placetype":"venue"
},
  "geometry": {"coordinates":[145.06236267099999,-38.2280197144],"type":"Point"}
}