{
  "type": "Feature",
  "properties": {
    "iso:country":"AU",
    "sg:address":"70 Ross River Rd",
    "sg:city":"Mundingburra",
    "sg:classifiers":[
        {
            "category":"Organizations",
            "subcategory":"Non-profit Organization",
            "type":"Services"
        }
    ],
    "sg:phone":"+61 7 4721 2850",
    "sg:postcode":"4812",
    "sg:province":"QLD",
    "sg:tags":[
        "support",
        "disability",
        "organisation"
    ],
    "wof:name":"Supported Options In Lifestyle & Access Services Inc",
    "wof:placetype":"venue"
},
  "geometry": {"coordinates":[146.78938299999999,-19.295071],"type":"Point"}
}