{
  "type": "Feature",
  "properties": {
    "addr:full":"Suite 637 Manly National Bldg 22 Central Ave Manly NSW 2095",
    "addr:housenumber":"22",
    "addr:postcode":"2095",
    "addr:street":"Central Ave",
    "iso:country":"AU",
    "sg:address":"Suite 637 Manly National Bldg 22 Central Ave",
    "sg:city":"Manly",
    "sg:classifiers":[
        {
            "category":"Arts & Performance",
            "subcategory":"Theater",
            "type":"Entertainment"
        }
    ],
    "sg:phone":"+61 2 9977 6239",
    "sg:postcode":"2095",
    "sg:province":"NSW",
    "sg:tags":[
        "agency",
        "booking",
        "theatre"
    ],
    "wof:name":"MacDonee Incorparated Theatre Company-Theatrical Agents",
    "wof:placetype":"venue"
},
  "geometry": {"coordinates":[151.28666687,-33.7968025208],"type":"Point"}
}