{
  "type": "Feature",
  "properties": {
    "addr:full":"1 Park Rd Milton QLD 4064",
    "addr:housenumber":"1",
    "addr:postcode":"4064",
    "addr:street":"Park Rd",
    "iso:country":"AU",
    "sg:address":"1 Park Rd",
    "sg:city":"Milton",
    "sg:classifiers":[
        {
            "category":"Autos & Motor Vehicles",
            "subcategory":"Boat Sales",
            "type":"Retail Goods"
        }
    ],
    "sg:phone":"+61 1800 222 822",
    "sg:postcode":"4064",
    "sg:province":"QLD",
    "sg:tags":[
        "dictating",
        "machine"
    ],
    "wof:name":"Lanier Voice",
    "wof:placetype":"venue"
},
  "geometry": {"coordinates":[153.00378418,-27.4693546295],"type":"Point"}
}