{
  "type": "Feature",
  "properties": {
    "addr:full":"19 Fitzgerald St Windsor NSW 2756",
    "addr:housenumber":"19",
    "addr:postcode":"2756",
    "addr:street":"Fitzgerald St",
    "iso:country":"AU",
    "sg:address":"19 Fitzgerald St",
    "sg:city":"Windsor",
    "sg:classifiers":[
        {
            "category":"Government",
            "subcategory":"Fire Station",
            "type":"Public Place"
        }
    ],
    "sg:phone":"+61 2 4577 3182",
    "sg:postcode":"2756",
    "sg:province":"NSW",
    "sg:tags":[
        "brigade"
    ],
    "wof:name":"Fire Brigades-NSW",
    "wof:placetype":"venue"
},
  "geometry": {"coordinates":[150.82005310100001,-33.6064300537],"type":"Point"}
}