{
  "type": "Feature",
  "properties": {
    "iso:country":"AU",
    "sg:address":"2 William St",
    "sg:city":"Orange",
    "sg:classifiers":[
        {
            "category":"Professional",
            "subcategory":"Detective & Security Services",
            "type":"Services"
        }
    ],
    "sg:phone":"+61 2 6361 8425",
    "sg:postcode":"2800",
    "sg:province":"NSW",
    "sg:tags":[
        "consultant",
        "system"
    ],
    "wof:name":"N & N Security Concepts",
    "wof:placetype":"venue"
},
  "geometry": {"coordinates":[149.10569763199999,-33.2848548889],"type":"Point"}
}