{
  "type": "Feature",
  "properties": {
    "addr:full":"20 Napoleon St Cottesloe WA 6011",
    "addr:housenumber":"20",
    "addr:postcode":"6011",
    "addr:street":"Napoleon St",
    "iso:country":"AU",
    "sg:address":"20 Napoleon St",
    "sg:city":"Cottesloe",
    "sg:classifiers":[
        {
            "category":"Food & Beverages",
            "subcategory":"Specialty",
            "type":"Retail Goods"
        }
    ],
    "sg:phone":"+61 8 9384 8900",
    "sg:postcode":"6011",
    "sg:province":"WA",
    "sg:tags":[
        "product",
        "health"
    ],
    "wof:name":"Good Life Health Stores",
    "wof:placetype":"venue"
},
  "geometry": {"coordinates":[115.761901855,-31.9977741241],"type":"Point"}
}