{
  "type": "Feature",
  "properties": {
    "addr:full":"PO Box 2277 Byron Bay NSW 2481",
    "addr:postcode":"2481",
    "iso:country":"AU",
    "sg:address":"PO Box 2277",
    "sg:city":"Byron Bay",
    "sg:classifiers":[
        {
            "category":"Retail",
            "subcategory":"Car Wash",
            "type":"Services"
        }
    ],
    "sg:phone":"+61 419 025 481",
    "sg:postcode":"2481",
    "sg:province":"NSW",
    "sg:tags":[
        "truck",
        "cleaning"
    ],
    "wof:name":"Elite Auto Detailing",
    "wof:placetype":"venue"
},
  "geometry": {"coordinates":[153.612823486,-28.6468906403],"type":"Point"}
}