{
  "type": "Feature",
  "properties": {
    "addr:full":"6 Barnett Pl Ernest QLD 4214",
    "addr:housenumber":"6",
    "addr:postcode":"4214",
    "addr:street":"Barnett Pl Ernest",
    "iso:country":"AU",
    "sg:address":"6 Barnett Pl",
    "sg:city":"Ernest",
    "sg:classifiers":[
        {
            "category":"Utilities",
            "subcategory":"Recycling",
            "type":"Services"
        }
    ],
    "sg:phone":"+61 7 5530 8571",
    "sg:postcode":"4214",
    "sg:province":"QLD",
    "wof:name":"Australian Foam Recycling",
    "wof:placetype":"venue"
},
  "geometry": {"coordinates":[153.36064148,-27.9655475616],"type":"Point"}
}