{
  "type": "Feature",
  "properties": {
    "addr:full":"54 Charles St Aitkenvale QLD 4814",
    "addr:housenumber":"54",
    "addr:postcode":"4814",
    "addr:street":"Charles St",
    "iso:country":"AU",
    "sg:address":"54 Charles St",
    "sg:city":"Aitkenvale",
    "sg:classifiers":[
        {
            "category":"Farming",
            "subcategory":"Farm & Veterinary Services",
            "type":"Manufacturing & Wholesale Goods"
        }
    ],
    "sg:phone":"+61 7 4779 1172",
    "sg:postcode":"4814",
    "sg:province":"QLD",
    "sg:tags":[
        "irrigation",
        "reticulation",
        "system"
    ],
    "sg:website":"http://www.wetworld.com.au",
    "wof:name":"Wetworld",
    "wof:placetype":"venue"
},
  "geometry": {"coordinates":[146.76895099999999,-19.291147],"type":"Point"}
}