{
  "type": "Feature",
  "properties": {
    "addr:full":"Stark Ave Boonah QLD 4310",
    "addr:postcode":"4310",
    "addr:street":"Stark Ave Boonah",
    "iso:country":"AU",
    "sg:address":"Stark Ave",
    "sg:city":"Boonah",
    "sg:classifiers":[
        {
            "category":"Travel",
            "subcategory":"Hostel",
            "type":"Entertainment"
        }
    ],
    "sg:phone":"+61 7 5463 1355",
    "sg:postcode":"4310",
    "sg:province":"QLD",
    "sg:tags":[
        "home"
    ],
    "wof:name":"Churches Of Christ Care",
    "wof:placetype":"venue"
},
  "geometry": {"coordinates":[152.68232727,-27.9942798615],"type":"Point"}
}