{
  "type": "Feature",
  "properties": {
    "addr:full":"1169- 1175 Beaudesert Acacia Ridge QLD 4110",
    "addr:housenumber":"1169 1175",
    "addr:postcode":"4110",
    "addr:street":"Beaudesert",
    "iso:country":"AU",
    "sg:address":"1169- 1175 Beaudesert",
    "sg:city":"Acacia Ridge",
    "sg:classifiers":[
        {
            "category":"Autos & Motor Vehicles",
            "subcategory":"Automobile Sales",
            "type":"Retail Goods"
        }
    ],
    "sg:phone":"+61 7 3272 7368",
    "sg:postcode":"4110",
    "sg:province":"QLD",
    "sg:tags":[
        "bus",
        "used",
        "truck"
    ],
    "wof:name":"East Coast Commercial Vehicle Disposals & Four Wheel Drive Sales",
    "wof:placetype":"venue"
},
  "geometry": {"coordinates":[153.02928161599999,-27.5916042328],"type":"Point"}
}