{
  "type": "Feature",
  "properties": {
    "iso:country":"AU",
    "sg:address":"13 Diagonal St",
    "sg:city":"Toowoomba",
    "sg:classifiers":[
        {
            "category":"Bars & Pubs",
            "subcategory":"Lounge",
            "type":"Food & Drink"
        }
    ],
    "sg:phone":"+61 1300 887 303",
    "sg:postcode":"4350",
    "sg:province":"QLD",
    "sg:tags":[
        "water",
        "filter",
        "drinking"
    ],
    "wof:name":"Water Magic International Pty Ltd",
    "wof:placetype":"venue"
},
  "geometry": {"coordinates":[151.944214,-27.572363],"type":"Point"}
}