{
  "type": "Feature",
  "properties": {
    "addr:full":"Ulladulla Campus Green St Ulladulla NSW 2539",
    "addr:postcode":"2539",
    "addr:street":"Green St",
    "iso:country":"AU",
    "sg:address":"Ulladulla Campus Green St",
    "sg:city":"Ulladulla",
    "sg:classifiers":[
        {
            "category":"Education",
            "subcategory":"Vocational School",
            "type":"Public Place"
        }
    ],
    "sg:phone":"+61 2 4455 3866",
    "sg:postcode":"2539",
    "sg:province":"NSW",
    "sg:tags":[
        "technical",
        "college",
        "trade"
    ],
    "wof:name":"Illawarra Institute Of Technology",
    "wof:placetype":"venue"
},
  "geometry": {"coordinates":[150.47366332999999,-35.3569717407],"type":"Point"}
}