{
  "type": "Feature",
  "properties": {
    "addr:full":"18 Narrabundah St Mudgeeraba QLD 4213",
    "addr:housenumber":"18",
    "addr:postcode":"4213",
    "addr:street":"Narrabundah St",
    "iso:country":"AU",
    "sg:address":"18 Narrabundah St",
    "sg:city":"Mudgeeraba",
    "sg:classifiers":[
        {
            "category":"Manufacturing",
            "subcategory":"Tools & Machinery",
            "type":"Manufacturing & Wholesale Goods"
        }
    ],
    "sg:phone":"+61 7 5530 5654",
    "sg:postcode":"4213",
    "sg:province":"QLD",
    "sg:tags":[
        "toolmaker"
    ],
    "wof:name":"D S. Precision Products",
    "wof:placetype":"venue"
},
  "geometry": {"coordinates":[153.35874939000001,-28.0677547455],"type":"Point"}
}