{
  "type": "Feature",
  "properties": {
    "addr:full":"Proteus House 9- 11 Prosper Crs Burleigh Heads QLD 4220",
    "addr:housenumber":"9 11",
    "addr:postcode":"4220",
    "addr:street":"Prosper Crs",
    "iso:country":"AU",
    "sg:address":"Proteus House 9- 11 Prosper Crs",
    "sg:city":"Burleigh Heads",
    "sg:classifiers":[
        {
            "category":"Professional",
            "subcategory":"Computer Services",
            "type":"Services"
        }
    ],
    "sg:phone":"+61 7 5576 6700",
    "sg:postcode":"4220",
    "sg:province":"QLD",
    "sg:tags":[
        "package",
        "software"
    ],
    "wof:name":"Proteus Corporation Pty Ltd",
    "wof:placetype":"venue"
},
  "geometry": {"coordinates":[153.449752808,-28.0879096985],"type":"Point"}
}