{
  "type": "Feature",
  "properties": {
    "addr:full":"Silverdell Pl Surf Beach NSW 2536",
    "addr:postcode":"2536",
    "addr:street":"Silverdell Pl",
    "iso:country":"AU",
    "sg:address":"Silverdell Pl",
    "sg:city":"Surf Beach",
    "sg:classifiers":[
        {
            "category":"Building & Trades",
            "subcategory":"Construction",
            "type":"Services"
        }
    ],
    "sg:phone":"+61 2 4471 3369",
    "sg:postcode":"2536",
    "sg:province":"NSW",
    "sg:tags":[
        "contractor"
    ],
    "wof:name":"AC & EA Findlay Constructions",
    "wof:placetype":"venue"
},
  "geometry": {"coordinates":[150.20050048799999,-35.7550964355],"type":"Point"}
}