{
  "type": "Feature",
  "properties": {
    "addr:full":"16 Gordon St Beaumaris VIC 3193",
    "addr:housenumber":"16",
    "addr:postcode":"3193",
    "addr:street":"Gordon St",
    "iso:country":"AU",
    "sg:address":"16 Gordon St",
    "sg:city":"Beaumaris",
    "sg:classifiers":[
        {
            "category":"Building & Trades",
            "subcategory":"Construction",
            "type":"Services"
        }
    ],
    "sg:phone":"+61 3 9583 4226",
    "sg:postcode":"3193",
    "sg:province":"VIC",
    "sg:tags":[
        "polishing",
        "sanding",
        "floor"
    ],
    "wof:name":"Astute Sanding & Polishing (ASAP)",
    "wof:placetype":"venue"
},
  "geometry": {"coordinates":[145.05267334000001,-37.9741973877],"type":"Point"}
}