{
  "type": "Feature",
  "properties": {
    "iso:country":"AU",
    "sg:address":"3 Miles St",
    "sg:city":"Inverell",
    "sg:classifiers":[
        {
            "category":"Arts & Performance",
            "subcategory":"Dance",
            "type":"Entertainment"
        }
    ],
    "sg:phone":"+61 439 458 624",
    "sg:postcode":"2360",
    "sg:province":"NSW",
    "sg:tags":[
        "theatrical",
        "ballet",
        "tuition"
    ],
    "wof:name":"Craze Dance Academy",
    "wof:placetype":"venue"
},
  "geometry": {"coordinates":[151.092453003,-29.7736873627],"type":"Point"}
}