{
  "type": "Feature",
  "properties": {
    "iso:country":"AU",
    "sg:address":"Hoadley Pl",
    "sg:city":"Arndell Park",
    "sg:classifiers":[
        {
            "category":"Professional",
            "type":"Services"
        }
    ],
    "sg:phone":"+61 2 9672 7000",
    "sg:postcode":"2148",
    "sg:province":"NSW",
    "sg:tags":[
        "transport"
    ],
    "wof:name":"Lindsay Transport",
    "wof:placetype":"venue"
},
  "geometry": {"coordinates":[150.883834839,-33.7922172546],"type":"Point"}
}