{
  "type": "Feature",
  "properties": {
    "iso:country":"AU",
    "sg:address":"100 Rokeby St",
    "sg:city":"Collingwood",
    "sg:classifiers":[
        {
            "category":"Retail",
            "subcategory":"Auto Rental",
            "type":"Services"
        }
    ],
    "sg:phone":"+61 1800 818 816",
    "sg:postcode":"3066",
    "sg:province":"VIC",
    "sg:tags":[
        "car",
        "wedding"
    ],
    "wof:name":"Buses + 4WD Hire Pty Ltd",
    "wof:placetype":"venue"
},
  "geometry": {"coordinates":[144.99130249000001,-37.8055458069],"type":"Point"}
}