{
  "type": "Feature",
  "properties": {
    "iso:country":"AU",
    "sg:address":"Lot 43 Isaac St",
    "sg:city":"Busselton",
    "sg:classifiers":[
        {
            "category":"Wholesale",
            "subcategory":"Machinery & Supplies",
            "type":"Manufacturing & Wholesale Goods"
        }
    ],
    "sg:phone":"+61 8 9754 4185",
    "sg:postcode":"6280",
    "sg:province":"WA",
    "sg:tags":[
        "agricultural"
    ],
    "wof:name":"Innovative Machinery",
    "wof:placetype":"venue"
},
  "geometry": {"coordinates":[115.351463318,-33.659614563],"type":"Point"}
}