{
  "type": "Feature",
  "properties": {
    "iso:country":"AU",
    "sg:address":"Surfside Arcade,Shop 3,355-357 Barrenjoey Rd",
    "sg:city":"Newport",
    "sg:classifiers":[
        {
            "category":"Deli",
            "type":"Food & Drink"
        }
    ],
    "sg:phone":"+61 2 9979 7441",
    "sg:postcode":"2106",
    "sg:province":"NSW",
    "sg:tags":[
        "delicatessen"
    ],
    "wof:name":"Chapmans Fine Foods",
    "wof:placetype":"venue"
},
  "geometry": {"coordinates":[151.32046508799999,-33.654800415],"type":"Point"}
}