{
  "type": "Feature",
  "properties": {
    "addr:full":"415 Argyle St Moss Vale NSW 2577",
    "addr:housenumber":"415",
    "addr:postcode":"2577",
    "addr:street":"Argyle St",
    "iso:country":"AU",
    "sg:address":"415 Argyle St",
    "sg:city":"Moss Vale",
    "sg:classifiers":[
        {
            "category":"Retail",
            "subcategory":"Funeral Services",
            "type":"Services"
        }
    ],
    "sg:phone":"+61 2 4869 2888",
    "sg:postcode":"2577",
    "sg:province":"NSW",
    "sg:tags":[
        "director"
    ],
    "wof:name":"Southern Highlands Funerals",
    "wof:placetype":"venue"
},
  "geometry": {"coordinates":[150.371185303,-34.5501174927],"type":"Point"}
}