{
  "type": "Feature",
  "properties": {
    "iso:country":"AU",
    "sg:address":"Cnr Rob & Tor Sts",
    "sg:city":"Toowoomba",
    "sg:classifiers":[
        {
            "category":"Shopping",
            "subcategory":"Party Supplies",
            "type":"Retail Goods"
        }
    ],
    "sg:phone":"+61 7 4634 9699",
    "sg:postcode":"4350",
    "sg:province":"QLD",
    "sg:tags":[
        "hire",
        "costume"
    ],
    "wof:name":"Teiki Costume Hire & Sales",
    "wof:placetype":"venue"
},
  "geometry": {"coordinates":[151.92735300000001,-27.564123],"type":"Point"}
}