{
  "type": "Feature",
  "properties": {
    "iso:country":"AU",
    "sg:address":"281 Henry Parry Drv",
    "sg:city":"Wyoming",
    "sg:classifiers":[
        {
            "category":"Social Services",
            "subcategory":"Child Care",
            "type":"Services"
        }
    ],
    "sg:phone":"+61 2 4325 3924",
    "sg:postcode":"2250",
    "sg:province":"NSW",
    "wof:name":"Koala Kindy",
    "wof:placetype":"venue"
},
  "geometry": {"coordinates":[151.35002136200001,-33.4118843079],"type":"Point"}
}