{
  "type": "Feature",
  "properties": {
    "addr:full":"Shop 15/ The Conservatory, Abbott St Cairns QLD 4870",
    "addr:housenumber":"shop 15 /",
    "addr:postcode":"4870",
    "addr:street":"Abbott St",
    "iso:country":"AU",
    "sg:address":"Shop 15/ The Conservatory, Abbott St",
    "sg:city":"Cairns",
    "sg:classifiers":[
        {
            "category":"Shopping",
            "subcategory":"Clothing, Apparel, & Fashions",
            "type":"Retail Goods"
        }
    ],
    "sg:phone":"+61 7 4031 6377",
    "sg:postcode":"4870",
    "sg:province":"QLD",
    "sg:tags":[
        "lady",
        "wear"
    ],
    "wof:name":"Elizabeth Shepherd Fashions",
    "wof:placetype":"venue"
},
  "geometry": {"coordinates":[145.77940368599999,-16.9243106842],"type":"Point"}
}