{
  "type": "Feature",
  "properties": {
    "addr:full":"222 Dowling St Dungog NSW 2420",
    "addr:housenumber":"222",
    "addr:postcode":"2420",
    "addr:street":"Dowling St",
    "iso:country":"AU",
    "sg:address":"222 Dowling St",
    "sg:city":"Dungog",
    "sg:classifiers":[
        {
            "category":"Personal",
            "subcategory":"Beauty Salon",
            "type":"Services"
        }
    ],
    "sg:phone":"+61 2 4992 1597",
    "sg:postcode":"2420",
    "sg:province":"NSW",
    "sg:tags":[
        "hairdresser"
    ],
    "wof:name":"Dungog Hair We Do",
    "wof:placetype":"venue"
},
  "geometry": {"coordinates":[151.75787399999999,-32.401272],"type":"Point"}
}