{
  "type": "Feature",
  "properties": {
    "iso:country":"AU",
    "sg:address":"2/ 12 Panama St",
    "sg:city":"Canning Vale",
    "sg:classifiers":[
        {
            "category":"Utilities",
            "subcategory":"Electric",
            "type":"Services"
        }
    ],
    "sg:phone":"+61 8 9456 1888",
    "sg:postcode":"6155",
    "sg:province":"WA",
    "sg:tags":[
        "electrical",
        "contractor"
    ],
    "wof:name":"Elder Electric",
    "wof:placetype":"venue"
},
  "geometry": {"coordinates":[115.932487,-32.064388],"type":"Point"}
}