{
  "type": "Feature",
  "properties": {
    "addr:full":"Fry St Ringarooma TAS 7263",
    "addr:postcode":"7263",
    "addr:street":"Fry St",
    "iso:country":"AU",
    "sg:address":"Fry St",
    "sg:city":"Ringarooma",
    "sg:classifiers":[
        {
            "category":"Professional",
            "subcategory":"Employment Agencies",
            "type":"Services"
        }
    ],
    "sg:phone":"+61 3 6353 1095",
    "sg:postcode":"7263",
    "sg:province":"TAS",
    "sg:tags":[
        "provider",
        "internet"
    ],
    "wof:name":"Online Access Centres",
    "wof:placetype":"venue"
},
  "geometry": {"coordinates":[147.733124,-41.242992],"type":"Point"}
}