{
  "type": "Feature",
  "properties": {
    "iso:country":"AU",
    "sg:address":"130 Longlear La",
    "sg:city":"Kurmond",
    "sg:classifiers":[
        {
            "category":"Farming",
            "subcategory":"Nursery",
            "type":"Manufacturing & Wholesale Goods"
        }
    ],
    "sg:phone":"+61 2 4573 1708",
    "sg:postcode":"2757",
    "sg:province":"NSW",
    "wof:name":"Springrove Wholesale Nursery",
    "wof:placetype":"venue"
},
  "geometry": {"coordinates":[150.68190002399999,-33.5594406128],"type":"Point"}
}