{
  "type": "Feature",
  "properties": {
    "addr:full":"22 Nimbin Rd Koolewong NSW 2256",
    "addr:housenumber":"22",
    "addr:postcode":"2256",
    "addr:street":"Nimbin Rd",
    "iso:country":"AU",
    "sg:address":"22 Nimbin Rd",
    "sg:city":"Koolewong",
    "sg:classifiers":[
        {
            "category":"Building & Trades",
            "subcategory":"Construction",
            "type":"Services"
        }
    ],
    "sg:phone":"+61 416 179 789",
    "sg:postcode":"2256",
    "sg:province":"NSW",
    "sg:tags":[
        "mural"
    ],
    "wof:name":"Painted Visions",
    "wof:placetype":"venue"
},
  "geometry": {"coordinates":[151.31661987300001,-33.4664154053],"type":"Point"}
}