{
  "type": "Feature",
  "properties": {
    "iso:country":"AU",
    "sg:address":"Great Alpine Rd",
    "sg:city":"Everton",
    "sg:classifiers":[
        {
            "category":"Education",
            "subcategory":"School",
            "type":"Public Place"
        }
    ],
    "sg:phone":"+61 3 5727 0222",
    "sg:postcode":"3678",
    "sg:province":"VIC",
    "sg:tags":[
        "state",
        "except",
        "nsw"
    ],
    "wof:name":"Everton Primary School",
    "wof:placetype":"venue"
},
  "geometry": {"coordinates":[146.54292297399999,-36.4339790344],"type":"Point"}
}