{
  "type": "Feature",
  "properties": {
    "iso:country":"AU",
    "sg:address":"8 Froma La",
    "sg:city":"Katoomba",
    "sg:classifiers":[
        {
            "category":"Professional",
            "subcategory":"Business Services",
            "type":"Services"
        }
    ],
    "sg:phone":"+61 2 4782 2750",
    "sg:postcode":"2780",
    "sg:province":"NSW",
    "sg:tags":[
        "drafting"
    ],
    "wof:name":"Edwards T Drafting",
    "wof:placetype":"venue"
},
  "geometry": {"coordinates":[150.311203003,-33.7139778137],"type":"Point"}
}