{
  "type": "Feature",
  "properties": {
    "iso:country":"AU",
    "sg:address":"Unit 2/ 46 Williams St",
    "sg:city":"Frankston",
    "sg:classifiers":[
        {
            "category":"Professional",
            "subcategory":"Computer Services",
            "type":"Services"
        }
    ],
    "sg:phone":"+61 3 9770 6673",
    "sg:postcode":"3199",
    "sg:province":"VIC",
    "sg:tags":[
        "consultant",
        "system"
    ],
    "wof:name":"SRP IT",
    "wof:placetype":"venue"
},
  "geometry": {"coordinates":[144.97518920900001,-38.3319892883],"type":"Point"}
}