{
  "type": "Feature",
  "properties": {
    "addr:full":"52 Palawan Ave Kings Park NSW 2148",
    "addr:housenumber":"52",
    "addr:postcode":"2148",
    "addr:street":"Palawan Ave",
    "iso:country":"AU",
    "sg:address":"52 Palawan Ave",
    "sg:city":"Kings Park",
    "sg:classifiers":[
        {
            "category":"Education",
            "subcategory":"Music School",
            "type":"Public Place"
        }
    ],
    "sg:phone":"+61 438 437 213",
    "sg:postcode":"2148",
    "sg:province":"NSW",
    "sg:tags":[
        "teacher"
    ],
    "wof:name":"Norwest Guitar Tuition",
    "wof:placetype":"venue"
},
  "geometry": {"coordinates":[150.914337158,-33.741985321],"type":"Point"}
}