{
  "type": "Feature",
  "properties": {
    "iso:country":"AU",
    "sg:address":"16 Jukes Way",
    "sg:city":"Wembley",
    "sg:classifiers":[
        {
            "category":"Professional",
            "subcategory":"Art Services",
            "type":"Services"
        }
    ],
    "sg:phone":"+61 411 442 002",
    "sg:postcode":"6014",
    "sg:province":"WA",
    "sg:tags":[
        "interior",
        "decorator"
    ],
    "sg:website":"http://www.amazingmakeovers.com.au",
    "wof:name":"Amazing Makeovers",
    "wof:placetype":"venue"
},
  "geometry": {"coordinates":[115.81844329800001,-31.9239273071],"type":"Point"}
}