{
  "type": "Feature",
  "properties": {
    "iso:country":"AU",
    "sg:address":"Oxley Hwy",
    "sg:city":"Warren",
    "sg:classifiers":[
        {
            "category":"Travel",
            "subcategory":"Hotels & Motels",
            "type":"Entertainment"
        }
    ],
    "sg:phone":"+61 2 6847 4396",
    "sg:postcode":"2824",
    "sg:province":"NSW",
    "wof:name":"Macquarie Valley Motor Inn",
    "wof:placetype":"venue"
},
  "geometry": {"coordinates":[147.835662842,-31.7004318237],"type":"Point"}
}