{
  "type": "Feature",
  "properties": {
    "addr:full":"Unit 2/ 49 Sterling Rd Minchinbury NSW 2770",
    "addr:housenumber":"49",
    "addr:postcode":"2770",
    "addr:street":"Sterling Rd",
    "iso:country":"AU",
    "sg:address":"Unit 2/ 49 Sterling Rd",
    "sg:city":"Minchinbury",
    "sg:classifiers":[
        {
            "category":"Wholesale",
            "subcategory":"Toys & Hobbies",
            "type":"Manufacturing & Wholesale Goods"
        }
    ],
    "sg:phone":"+61 2 9832 4660",
    "sg:postcode":"2770",
    "sg:province":"NSW",
    "wof:name":"Cheapa Toy & Gift Imports",
    "wof:placetype":"venue"
},
  "geometry": {"coordinates":[150.815475464,-33.7821350098],"type":"Point"}
}