{
  "type": "Feature",
  "properties": {
    "addr:full":"PO Box 1067 Auburn NSW 2144",
    "addr:postcode":"2144",
    "iso:country":"AU",
    "sg:address":"PO Box 1067",
    "sg:city":"Auburn",
    "sg:classifiers":[
        {
            "category":"Retail",
            "subcategory":"Auto Rental",
            "type":"Services"
        }
    ],
    "sg:phone":"+61 413 504 571",
    "sg:postcode":"2144",
    "sg:province":"NSW",
    "sg:tags":[
        "chauffeur",
        "car",
        "hire",
        "driven",
        "limousine"
    ],
    "wof:name":"Taxis Limousinous",
    "wof:placetype":"venue"
},
  "geometry": {"coordinates":[151.02838134800001,-33.8578300476],"type":"Point"}
}