{
  "type": "Feature",
  "properties": {
    "iso:country":"AU",
    "sg:address":"15 Horatio St",
    "sg:city":"Mudgee",
    "sg:classifiers":[
        {
            "category":"Travel",
            "subcategory":"Hotels & Motels",
            "type":"Entertainment"
        }
    ],
    "sg:phone":"+61 2 6372 7727",
    "sg:postcode":"2850",
    "sg:province":"NSW",
    "wof:name":"Golden Chain Horatio Motor Inn",
    "wof:placetype":"venue"
},
  "geometry": {"coordinates":[149.59515380900001,-32.6004142761],"type":"Point"}
}