{
  "type": "Feature",
  "properties": {
    "addr:full":"5 Kyeamba St Merimbula NSW 2548",
    "addr:housenumber":"5",
    "addr:postcode":"2548",
    "addr:street":"Kyeamba St",
    "iso:country":"AU",
    "sg:address":"5 Kyeamba St",
    "sg:city":"Merimbula",
    "sg:classifiers":[
        {
            "category":"Social Services",
            "subcategory":"Child Care",
            "type":"Services"
        }
    ],
    "sg:phone":"+61 2 6495 4155",
    "sg:postcode":"2548",
    "sg:province":"NSW",
    "wof:name":"ABC Learning Centres",
    "wof:placetype":"venue"
},
  "geometry": {"coordinates":[149.908126831,-36.8897705078],"type":"Point"}
}