{
  "type": "Feature",
  "properties": {
    "iso:country":"AU",
    "sg:address":"3/ 45 Southern Cross Drv",
    "sg:city":"Ballina",
    "sg:classifiers":[
        {
            "category":"Utilities",
            "type":"Services"
        }
    ],
    "sg:phone":"+61 2 6687 1360",
    "sg:postcode":"2478",
    "sg:province":"NSW",
    "sg:tags":[
        "refrigeration",
        "industrial",
        "commercial",
        "retail"
    ],
    "wof:name":"Shore Cool",
    "wof:placetype":"venue"
},
  "geometry": {"coordinates":[153.55436706500001,-28.8482570648],"type":"Point"}
}