{
  "type": "Feature",
  "properties": {
    "addr:full":"1 Alfred St Marrickville NSW 2204",
    "addr:housenumber":"1",
    "addr:postcode":"2204",
    "addr:street":"Alfred St",
    "iso:country":"AU",
    "sg:address":"1 Alfred St",
    "sg:city":"Marrickville",
    "sg:classifiers":[
        {
            "category":"Building & Trades",
            "subcategory":"Construction",
            "type":"Services"
        }
    ],
    "sg:phone":"+61 2 9558 7185",
    "sg:postcode":"2204",
    "sg:province":"NSW",
    "sg:tags":[
        "contractor"
    ],
    "wof:name":"Sydwide Constructions Pty Ltd",
    "wof:placetype":"venue"
},
  "geometry": {"coordinates":[151.14231899999999,-33.916195],"type":"Point"}
}