{
  "type": "Feature",
  "properties": {
    "iso:country":"AU",
    "sg:address":"Suite 20, 34 Dominions Rd",
    "sg:city":"Ashmore",
    "sg:classifiers":[
        {
            "category":"Personal",
            "subcategory":"Massage",
            "type":"Services"
        }
    ],
    "sg:phone":"+61 1800 198 888",
    "sg:postcode":"4214",
    "sg:province":"QLD",
    "sg:tags":[
        "therapy"
    ],
    "wof:name":"Marquerite Tarman",
    "wof:placetype":"venue"
},
  "geometry": {"coordinates":[153.38392639200001,-27.9806404114],"type":"Point"}
}