{
  "type": "Feature",
  "properties": {
    "iso:country":"AU",
    "sg:address":"45 Whitaker Ave",
    "sg:city":"Reynella",
    "sg:classifiers":[
        {
            "category":"Building & Trades",
            "subcategory":"Construction",
            "type":"Services"
        }
    ],
    "sg:phone":"+61 8 8387 1874",
    "sg:postcode":"5161",
    "sg:province":"SA",
    "sg:tags":[
        "concrete",
        "contractor"
    ],
    "wof:name":"Lui Pinos",
    "wof:placetype":"venue"
},
  "geometry": {"coordinates":[138.54354858400001,-35.1029663086],"type":"Point"}
}