{
  "type": "Feature",
  "properties": {
    "addr:full":"Level 2 541 Blackburn Rd Mt Waverley VIC 3149",
    "addr:housenumber":"541",
    "addr:postcode":"3149",
    "addr:street":"Blackburn Rd",
    "iso:country":"AU",
    "sg:address":"Level 2 541 Blackburn Rd",
    "sg:city":"Mt Waverley",
    "sg:classifiers":[
        {
            "category":"Professional",
            "subcategory":"Accounting & Tax Preparation",
            "type":"Services"
        }
    ],
    "sg:phone":"+61 3 9550 0892",
    "sg:postcode":"3149",
    "sg:province":"VIC",
    "sg:tags":[
        "accountant",
        "auditor"
    ],
    "wof:name":"Gottliebsens Pty Ltd",
    "wof:placetype":"venue"
},
  "geometry": {"coordinates":[145.14315795900001,-37.899055481],"type":"Point"}
}