{
  "type": "Feature",
  "properties": {
    "iso:country":"AU",
    "sg:address":"41-43 Rudall Ave",
    "sg:city":"Whyalla Playford",
    "sg:classifiers":[
        {
            "category":"Autos & Motor Vehicles",
            "subcategory":"Auto Supplies",
            "type":"Retail Goods"
        }
    ],
    "sg:phone":"+61 8 8645 7911",
    "sg:postcode":"5600",
    "sg:province":"SA",
    "sg:tags":[
        "part",
        "cycles",
        "accessory"
    ],
    "wof:name":"Bikes &#039;n&#039; Gear",
    "wof:placetype":"venue"
},
  "geometry": {"coordinates":[137.566437,-33.0247],"type":"Point"}
}