{
  "type": "Feature",
  "properties": {
    "addr:full":"23 Wellington St Geelong West VIC 3218",
    "addr:housenumber":"23",
    "addr:postcode":"3218",
    "addr:street":"Wellington St",
    "iso:country":"AU",
    "sg:address":"23 Wellington St",
    "sg:city":"Geelong West",
    "sg:classifiers":[
        {
            "category":"Real Estate",
            "subcategory":"Surveying",
            "type":"Services"
        }
    ],
    "sg:phone":"+61 3 5221 3449",
    "sg:postcode":"3218",
    "sg:province":"VIC",
    "sg:tags":[
        "map",
        "mapping"
    ],
    "wof:name":"CartDeco Cartographics",
    "wof:placetype":"venue"
},
  "geometry": {"coordinates":[144.35166931099999,-38.1385269165],"type":"Point"}
}