{
  "type": "Feature",
  "properties": {
    "addr:full":"PO Box 1176 Canning Vale DC WA 6155",
    "addr:postcode":"6155",
    "iso:country":"AU",
    "sg:address":"PO Box 1176",
    "sg:city":"Canning Vale DC",
    "sg:classifiers":[
        {
            "category":"Building & Trades",
            "subcategory":"Construction",
            "type":"Services"
        }
    ],
    "sg:phone":"+61 8 9456 0352",
    "sg:postcode":"6155",
    "sg:province":"WA",
    "sg:tags":[
        "welding"
    ],
    "wof:name":"West Weld Fabrications",
    "wof:placetype":"venue"
},
  "geometry": {"coordinates":[115.91941799999999,-32.05872],"type":"Point"}
}