{
  "type": "Feature",
  "properties": {
    "addr:full":"Shop 3 Bellmere Shopping Centre Bellmere QLD 4510",
    "addr:housenumber":"shop 3",
    "addr:postcode":"4510",
    "addr:street":"Bellmere",
    "iso:country":"AU",
    "sg:address":"Shop 3 Bellmere Shopping Centre",
    "sg:city":"Bellmere",
    "sg:classifiers":[
        {
            "category":"Fast Food",
            "type":"Food & Drink"
        }
    ],
    "sg:phone":"+61 7 5499 0422",
    "sg:postcode":"4510",
    "sg:province":"QLD",
    "sg:tags":[
        "away",
        "take"
    ],
    "wof:name":"The Burger Shack",
    "wof:placetype":"venue"
},
  "geometry": {"coordinates":[152.934494,-27.08169],"type":"Point"}
}