{
  "type": "Feature",
  "properties": {
    "addr:full":"28 Morrisett St Queanbeyan NSW 2620",
    "addr:housenumber":"28",
    "addr:postcode":"2620",
    "addr:street":"Morrisett St",
    "iso:country":"AU",
    "sg:address":"28 Morrisett St",
    "sg:city":"Queanbeyan",
    "sg:classifiers":[
        {
            "category":"Fast Food",
            "type":"Food & Drink"
        }
    ],
    "sg:phone":"+61 2 6299 6670",
    "sg:postcode":"2620",
    "sg:province":"NSW",
    "sg:tags":[
        "away",
        "take"
    ],
    "wof:name":"Spicy Inn",
    "wof:placetype":"venue"
},
  "geometry": {"coordinates":[149.233612061,-35.3509941101],"type":"Point"}
}