{
  "type": "Feature",
  "properties": {
    "iso:country":"AU",
    "sg:address":"PO Box 3375",
    "sg:city":"Victoria Point West",
    "sg:classifiers":[
        {
            "category":"Education",
            "subcategory":"Special Training",
            "type":"Public Place"
        }
    ],
    "sg:phone":"+61 1800 180 599",
    "sg:postcode":"4165",
    "sg:province":"QLD",
    "sg:tags":[
        "development"
    ],
    "wof:name":"Global Dynamics Pty Ltd",
    "wof:placetype":"venue"
},
  "geometry": {"coordinates":[153.28187560999999,-27.5851898193],"type":"Point"}
}