{
  "type": "Feature",
  "properties": {
    "addr:full":"504 Old South Head Rd Rose Bay NSW 2029",
    "addr:housenumber":"504",
    "addr:postcode":"2029",
    "addr:street":"Old South Head Rd",
    "iso:country":"AU",
    "sg:address":"504 Old South Head Rd",
    "sg:city":"Rose Bay",
    "sg:classifiers":[
        {
            "category":"Education",
            "subcategory":"University",
            "type":"Public Place"
        }
    ],
    "sg:phone":"+61 2 9371 3382",
    "sg:postcode":"2029",
    "sg:province":"NSW",
    "sg:tags":[
        "educational",
        "organisation",
        "cultural"
    ],
    "wof:name":"BNEI Baruch Inc",
    "wof:placetype":"venue"
},
  "geometry": {"coordinates":[151.272994995,-33.8740921021],"type":"Point"}
}