{
  "type": "Feature",
  "properties": {
    "iso:country":"AU",
    "sg:address":"13 Rowan St",
    "sg:city":"Bendigo",
    "sg:classifiers":[
        {
            "category":"Health Services",
            "subcategory":"Health Practitioner",
            "type":"Services"
        }
    ],
    "sg:phone":"+61 3 5442 5800",
    "sg:postcode":"3550",
    "sg:province":"VIC",
    "sg:tags":[
        "consultant",
        "conservation",
        "hearing"
    ],
    "wof:name":"Bendigo Hearing Clinic",
    "wof:placetype":"venue"
},
  "geometry": {"coordinates":[144.27450561500001,-36.757648468],"type":"Point"}
}