{
  "type": "Feature",
  "properties": {
    "iso:country":"AU",
    "sg:address":"Stoney Creek Rd",
    "sg:city":"Beaconsfield Upper",
    "sg:classifiers":[
        {
            "category":"Education",
            "subcategory":"Kindergarten",
            "type":"Public Place"
        }
    ],
    "sg:phone":"+61 3 5944 3822",
    "sg:postcode":"3808",
    "sg:province":"VIC",
    "sg:tags":[
        "pre-schools"
    ],
    "wof:name":"Upper Beaconsfield Kindergarten",
    "wof:placetype":"venue"
},
  "geometry": {"coordinates":[145.414536,-37.989769],"type":"Point"}
}