{
  "type": "Feature",
  "properties": {
    "addr:full":"Unit 20, 7/9 Activity Crs Molendinar QLD 4214",
    "addr:housenumber":"7 / 9",
    "addr:postcode":"4214",
    "addr:street":"Activity Crs",
    "iso:country":"AU",
    "sg:address":"Unit 20, 7/9 Activity Crs",
    "sg:city":"Molendinar",
    "sg:classifiers":[
        {
            "category":"Home & Garden",
            "subcategory":"Building Materials",
            "type":"Retail Goods"
        }
    ],
    "sg:phone":"+61 408 702 629",
    "sg:postcode":"4214",
    "sg:province":"QLD",
    "sg:tags":[
        "merchant",
        "glass",
        "glazier"
    ],
    "wof:name":"Action Glass & Aluminium",
    "wof:placetype":"venue"
},
  "geometry": {"coordinates":[153.36187744099999,-27.9781703949],"type":"Point"}
}