{
  "type": "Feature",
  "properties": {
    "addr:full":"158 Oak Rd Kirrawee NSW 2232",
    "addr:housenumber":"158",
    "addr:postcode":"2232",
    "addr:street":"Oak Rd",
    "iso:country":"AU",
    "sg:address":"158 Oak Rd",
    "sg:city":"Kirrawee",
    "sg:classifiers":[
        {
            "category":"Health Services",
            "subcategory":"Doctor",
            "type":"Services"
        }
    ],
    "sg:phone":"+61 2 9521 2007",
    "sg:postcode":"2232",
    "sg:province":"NSW",
    "sg:tags":[
        "medical",
        "practitioner"
    ],
    "wof:name":"Edmondson-Jones Dr John",
    "wof:placetype":"venue"
},
  "geometry": {"coordinates":[151.07115173299999,-34.0347251892],"type":"Point"}
}