{
  "type": "Feature",
  "properties": {
    "iso:country":"AU",
    "sg:address":"Garden City Shpng Cntr 125 Riseley St",
    "sg:city":"Booragoon",
    "sg:classifiers":[
        {
            "category":"Shopping",
            "subcategory":"Department Store",
            "type":"Retail Goods"
        }
    ],
    "sg:phone":"+61 8 9314 9100",
    "sg:postcode":"6154",
    "sg:province":"WA",
    "wof:name":"Myer Pty Ltd",
    "wof:placetype":"venue"
},
  "geometry": {"coordinates":[115.83802,-32.032337],"type":"Point"}
}