{
  "type": "Feature",
  "properties": {
    "addr:full":"16 Panorama Dr Thornlands QLD 4164",
    "addr:housenumber":"16",
    "addr:postcode":"4164",
    "addr:street":"Panorama Dr",
    "iso:country":"AU",
    "sg:address":"16 Panorama Dr",
    "sg:city":"Thornlands",
    "sg:classifiers":[
        {
            "category":"Building & Trades",
            "subcategory":"Construction",
            "type":"Services"
        }
    ],
    "sg:phone":"+61 7 3821 1811",
    "sg:postcode":"4164",
    "sg:province":"QLD",
    "sg:tags":[
        "contractor"
    ],
    "wof:name":"K D Building Services Consulting Pty Ltd",
    "wof:placetype":"venue"
},
  "geometry": {"coordinates":[153.26397705100001,-27.5493545532],"type":"Point"}
}