{
  "type": "Feature",
  "properties": {
    "addr:full":"19 Strickland Pl Erskine Park NSW 2759",
    "addr:housenumber":"19",
    "addr:postcode":"2759",
    "addr:street":"Pl",
    "iso:country":"AU",
    "sg:address":"19 Strickland Pl",
    "sg:city":"Erskine Park",
    "sg:classifiers":[
        {
            "category":"Banks & Credit Unions",
            "subcategory":"Financial Services",
            "type":"Services"
        }
    ],
    "sg:phone":"+61 2 9834 6463",
    "sg:postcode":"2759",
    "sg:province":"NSW",
    "sg:tags":[
        "loan",
        "finance",
        "mortgage"
    ],
    "wof:name":"A Plus Finance & Property Pty Ltd",
    "wof:placetype":"venue"
},
  "geometry": {"coordinates":[150.797698975,-33.8045120239],"type":"Point"}
}