{
  "type": "Feature",
  "properties": {
    "addr:full":"Shop 1/ 809 New South Head Rd Rose Bay NSW 2029",
    "addr:housenumber":"shop 1 / 809",
    "addr:postcode":"2029",
    "addr:street":"New South Head Rd",
    "iso:country":"AU",
    "sg:address":"Shop 1/ 809 New South Head Rd",
    "sg:city":"Rose Bay",
    "sg:classifiers":[
        {
            "category":"Cafe",
            "type":"Food & Drink"
        }
    ],
    "sg:phone":"+61 2 9371 5041",
    "sg:postcode":"2029",
    "sg:province":"NSW",
    "wof:name":"Espresso on Dover",
    "wof:placetype":"venue"
},
  "geometry": {"coordinates":[151.269973755,-33.8696784973],"type":"Point"}
}