{
  "type": "Feature",
  "properties": {
    "addr:full":"Level 4 55 Phillip St Parramatta NSW 2150",
    "addr:housenumber":"55",
    "addr:postcode":"2150",
    "addr:street":"Phillip St",
    "iso:country":"AU",
    "sg:address":"Level 4 55 Phillip St",
    "sg:city":"Parramatta",
    "sg:classifiers":[
        {
            "category":"Banks & Credit Unions",
            "subcategory":"Financial Services",
            "type":"Services"
        }
    ],
    "sg:phone":"+61 2 9633 5255",
    "sg:postcode":"2150",
    "sg:province":"NSW",
    "sg:tags":[
        "planning"
    ],
    "wof:name":"Caranth Pty Ltd",
    "wof:placetype":"venue"
},
  "geometry": {"coordinates":[150.964553833,-33.8517341614],"type":"Point"}
}