{
  "type": "Feature",
  "properties": {
    "addr:full":"Suite 94/ 350 Kingsway Caringbah NSW 2229",
    "addr:housenumber":"94 / 350",
    "addr:postcode":"2229",
    "addr:street":"Kingsway",
    "iso:country":"AU",
    "sg:address":"Suite 94/ 350",
    "sg:city":"Kingsway Caringbah",
    "sg:classifiers":[
        {
            "category":"Recreation",
            "subcategory":"Boat Charter",
            "type":"Entertainment"
        }
    ],
    "sg:phone":"+61 2 9544 1400",
    "sg:postcode":"2229",
    "sg:province":"NSW",
    "wof:name":"Cronulla Cruises",
    "wof:placetype":"venue"
},
  "geometry": {"coordinates":[151.12159729000001,-34.041809082],"type":"Point"}
}