{
  "type": "Feature",
  "properties": {
    "addr:full":"Level 1, 12 Waters Rd Neutral Bay NSW 2089",
    "addr:housenumber":"12",
    "addr:postcode":"2089",
    "addr:street":"Waters Rd",
    "iso:country":"AU",
    "sg:address":"Level 1, 12 Waters Rd",
    "sg:city":"Neutral Bay",
    "sg:classifiers":[
        {
            "category":"Professional",
            "subcategory":"Accounting & Tax Preparation",
            "type":"Services"
        }
    ],
    "sg:phone":"+61 2 8969 8600",
    "sg:postcode":"2089",
    "sg:province":"NSW",
    "sg:tags":[
        "consultant",
        "taxation"
    ],
    "wof:name":"Aitken Wayne and Partners",
    "wof:placetype":"venue"
},
  "geometry": {"coordinates":[151.223480225,-33.830783844],"type":"Point"}
}