{
  "type": "Feature",
  "properties": {
    "addr:full":"Level 5, 280 Thomas St Dandenong VIC 3175",
    "addr:housenumber":"280",
    "addr:postcode":"3175",
    "addr:street":"Thomas St",
    "iso:country":"AU",
    "sg:address":"Level 5, 280 Thomas St",
    "sg:city":"Dandenong",
    "sg:classifiers":[
        {
            "category":"Professional",
            "subcategory":"Employment Agencies",
            "type":"Services"
        }
    ],
    "sg:phone":"+61 3 8791 2400",
    "sg:postcode":"3175",
    "sg:province":"VIC",
    "wof:name":"AMES Employment",
    "wof:placetype":"venue"
},
  "geometry": {"coordinates":[145.212646484,-37.9859237671],"type":"Point"}
}