{
  "type": "Feature",
  "properties": {
    "iso:country":"AU",
    "sg:address":"68- 72 Parramatta Rd",
    "sg:city":"Stanmore",
    "sg:classifiers":[
        {
            "category":"Wholesale",
            "subcategory":"Furniture",
            "type":"Manufacturing & Wholesale Goods"
        }
    ],
    "sg:phone":"+61 1300 558 481",
    "sg:postcode":"2048",
    "sg:province":"NSW",
    "sg:tags":[
        "wholesaler",
        "mfrs"
    ],
    "sg:website":"http://www.naturallytimber.com.au",
    "wof:name":"Naturally Timber",
    "wof:placetype":"venue"
},
  "geometry": {"coordinates":[151.169937,-33.887875],"type":"Point"}
}