{
  "type": "Feature",
  "properties": {
    "iso:country":"AU",
    "sg:address":"47 Unwins Bridge Rd",
    "sg:city":"Sydenham",
    "sg:classifiers":[
        {
            "category":"Shopping",
            "subcategory":"Clothing, Apparel, & Fashions",
            "type":"Retail Goods"
        }
    ],
    "sg:phone":"+61 2 9519 5299",
    "sg:postcode":"2044",
    "sg:province":"NSW",
    "sg:tags":[
        "lady",
        "wear"
    ],
    "wof:name":"Clothing Clearance Warehouse",
    "wof:placetype":"venue"
},
  "geometry": {"coordinates":[151.166336,-33.916412],"type":"Point"}
}