{
  "type": "Feature",
  "properties": {
    "iso:country":"AU",
    "sg:address":"7 Victoria St",
    "sg:city":"Loch",
    "sg:classifiers":[
        {
            "category":"Wholesale",
            "subcategory":"Farm Supplies",
            "type":"Manufacturing & Wholesale Goods"
        }
    ],
    "sg:phone":"+61 3 5659 4277",
    "sg:postcode":"3945",
    "sg:province":"VIC",
    "sg:tags":[
        "feed",
        "supplement",
        "stock"
    ],
    "wof:name":"Loch Stock & Bales",
    "wof:placetype":"venue"
},
  "geometry": {"coordinates":[145.70698547399999,-38.3687782288],"type":"Point"}
}