{
  "type": "Feature",
  "properties": {
    "addr:full":"Shop 454 Castle Towers Castle Hill NSW 2154",
    "addr:housenumber":"454",
    "addr:postcode":"2154",
    "addr:street":"Castle Towers",
    "iso:country":"AU",
    "sg:address":"Shop 454 Castle Towers",
    "sg:city":"Castle Hill",
    "sg:classifiers":[
        {
            "category":"Cafe",
            "type":"Food & Drink"
        }
    ],
    "sg:phone":"+61 2 9899 4174",
    "sg:postcode":"2154",
    "sg:province":"NSW",
    "wof:name":"Cafe Bar Q",
    "wof:placetype":"venue"
},
  "geometry": {"coordinates":[151.003814697,-33.7317695618],"type":"Point"}
}