{
  "type": "Feature",
  "properties": {
    "iso:country":"AU",
    "sg:address":"22 South Gippsland Hwy",
    "sg:city":"Tooradin",
    "sg:classifiers":[
        {
            "category":"Autos & Motor Vehicles",
            "subcategory":"Fuel & Gas Station",
            "type":"Retail Goods"
        }
    ],
    "sg:phone":"+61 3 5998 3332",
    "sg:postcode":"3980",
    "sg:province":"VIC",
    "wof:name":"Tooradin Fuel Stop",
    "wof:placetype":"venue"
},
  "geometry": {"coordinates":[145.38011169399999,-38.2136383057],"type":"Point"}
}