{
  "type": "Feature",
  "properties": {
    "addr:full":"7 Ovens Pl Rowville VIC 3178",
    "addr:housenumber":"7",
    "addr:postcode":"3178",
    "addr:street":"Ovens Pl",
    "iso:country":"AU",
    "sg:address":"7 Ovens Pl",
    "sg:city":"Rowville",
    "sg:classifiers":[
        {
            "category":"Social Services",
            "subcategory":"Retirement Home",
            "type":"Services"
        }
    ],
    "sg:phone":"+61 3 9763 3268",
    "sg:postcode":"3178",
    "sg:province":"VIC",
    "sg:tags":[
        "environmental",
        "consultant",
        "pollution"
    ],
    "wof:name":"PE Consulting Services Pty Ltd",
    "wof:placetype":"venue"
},
  "geometry": {"coordinates":[145.24763488799999,-37.9194526672],"type":"Point"}
}