{
  "type": "Feature",
  "properties": {
    "addr:full":"Shop 8, Village Arcade, 269- 271 Darling St Balmain NSW 2041",
    "addr:housenumber":"shop 8;269 271",
    "addr:postcode":"2041",
    "addr:street":"Village Arcade;Darling St",
    "iso:country":"AU",
    "sg:address":"Shop 8, Village Arcade, 269- 271 Darling St",
    "sg:city":"Balmain",
    "sg:classifiers":[
        {
            "category":"Health Services",
            "subcategory":"Doctor",
            "type":"Services"
        }
    ],
    "sg:phone":"+61 2 9555 1043",
    "sg:postcode":"2041",
    "sg:province":"NSW",
    "sg:tags":[
        "medical",
        "practitioner"
    ],
    "wof:name":"Douglass Hanly Moir Pathology",
    "wof:placetype":"venue"
},
  "geometry": {"coordinates":[151.18150299999999,-33.857479],"type":"Point"}
}