{
  "type": "Feature",
  "properties": {
    "addr:full":"10 Buttons Ave Ulverstone TAS 7315",
    "addr:housenumber":"10",
    "addr:postcode":"7315",
    "addr:street":"Buttons Ave",
    "iso:country":"AU",
    "sg:address":"10 Buttons Ave",
    "sg:city":"Ulverstone",
    "sg:classifiers":[
        {
            "category":"Building & Trades",
            "subcategory":"Construction",
            "type":"Services"
        }
    ],
    "sg:phone":"+61 3 6425 1876",
    "sg:postcode":"7315",
    "sg:province":"TAS",
    "sg:tags":[
        "contractor"
    ],
    "wof:name":"Clark B J & B E",
    "wof:placetype":"venue"
},
  "geometry": {"coordinates":[146.187774658,-41.1568222046],"type":"Point"}
}