{
  "type": "Feature",
  "properties": {
    "addr:full":"Pacific Hwy Coopernook NSW 2426",
    "addr:postcode":"2426",
    "addr:street":"Pacific Hwy",
    "iso:country":"AU",
    "sg:address":"Pacific Hwy",
    "sg:city":"Coopernook",
    "sg:classifiers":[
        {
            "category":"Travel",
            "subcategory":"Hotels & Motels",
            "type":"Entertainment"
        }
    ],
    "sg:phone":"+61 2 6556 3150",
    "sg:postcode":"2426",
    "sg:province":"NSW",
    "sg:tags":[
        "accommodation"
    ],
    "wof:name":"Coopernook Hotel",
    "wof:placetype":"venue"
},
  "geometry": {"coordinates":[152.61587499999999,-31.824137],"type":"Point"}
}