{
  "type": "Feature",
  "properties": {
    "addr:full":"146 King St Melbourne VIC 3000",
    "addr:housenumber":"146",
    "addr:postcode":"3000",
    "addr:street":"King St",
    "iso:country":"AU",
    "sg:address":"146 King St",
    "sg:city":"Melbourne",
    "sg:classifiers":[
        {
            "category":"Shopping",
            "subcategory":"Clothing, Apparel, & Fashions",
            "type":"Retail Goods"
        }
    ],
    "sg:phone":"+61 3 9621 1521",
    "sg:postcode":"3000",
    "sg:province":"VIC",
    "sg:tags":[
        "menswear"
    ],
    "wof:name":"Ludlow Retailers Pty Ltd",
    "wof:placetype":"venue"
},
  "geometry": {"coordinates":[144.95605468799999,-37.8166542053],"type":"Point"}
}