{
  "type": "Feature",
  "properties": {
    "iso:country":"AU",
    "sg:address":"Shp2/ 245 Fletcher Rd",
    "sg:city":"Largs North",
    "sg:classifiers":[
        {
            "category":"Home & Garden",
            "subcategory":"Garden Supply",
            "type":"Retail Goods"
        }
    ],
    "sg:phone":"+61 8 8242 3788",
    "sg:postcode":"5016",
    "sg:province":"SA",
    "sg:tags":[
        "equipment"
    ],
    "wof:name":"Largs Bay Garden Supplies",
    "wof:placetype":"venue"
},
  "geometry": {"coordinates":[138.49411010700001,-34.8208694458],"type":"Point"}
}