{
  "type": "Feature",
  "properties": {
    "addr:full":"133 Dalgetty Rd Beaumaris VIC 3193",
    "addr:housenumber":"133",
    "addr:postcode":"3193",
    "addr:street":"Dalgetty Rd",
    "iso:country":"AU",
    "sg:address":"133 Dalgetty Rd",
    "sg:city":"Beaumaris",
    "sg:classifiers":[
        {
            "category":"Building & Trades",
            "subcategory":"Construction",
            "type":"Services"
        }
    ],
    "sg:phone":"+61 418 537 000",
    "sg:postcode":"3193",
    "sg:province":"VIC",
    "sg:tags":[
        "contractor"
    ],
    "wof:name":"Prime Construction Management Pty Ltd",
    "wof:placetype":"venue"
},
  "geometry": {"coordinates":[145.03843689000001,-37.9818115234],"type":"Point"}
}