{
  "type": "Feature",
  "properties": {
    "iso:country":"AU",
    "sg:address":"35 Edward St",
    "sg:city":"Morpeth",
    "sg:classifiers":[
        {
            "category":"Building & Trades",
            "subcategory":"Construction",
            "type":"Services"
        }
    ],
    "sg:phone":"+61 2 4933 4434",
    "sg:postcode":"2321",
    "sg:province":"NSW",
    "sg:tags":[
        "renovation",
        "alterations",
        "extension",
        "contractor"
    ],
    "wof:name":"Burg J K Constructions",
    "wof:placetype":"venue"
},
  "geometry": {"coordinates":[151.636322022,-32.725566864],"type":"Point"}
}