{
  "type": "Feature",
  "properties": {
    "iso:country":"AU",
    "sg:address":"53 Queen St",
    "sg:city":"Woollahra",
    "sg:classifiers":[
        {
            "category":"Personal",
            "subcategory":"Beauty Salon",
            "type":"Services"
        }
    ],
    "sg:phone":"+61 2 9362 1039",
    "sg:postcode":"2025",
    "sg:province":"NSW",
    "sg:tags":[
        "hairdresser"
    ],
    "wof:name":"Giancarlo Hair Art Gallery",
    "wof:placetype":"venue"
},
  "geometry": {"coordinates":[151.23516845699999,-33.8889274597],"type":"Point"}
}