{
  "type": "Feature",
  "properties": {
    "iso:country":"AU",
    "sg:address":"310 Bong Bong St",
    "sg:city":"Bowral",
    "sg:classifiers":[
        {
            "category":"Health Services",
            "subcategory":"Optometrist",
            "type":"Services"
        }
    ],
    "sg:phone":"+61 2 4861 4369",
    "sg:postcode":"2576",
    "sg:province":"NSW",
    "wof:name":"Hannaford Eyewear",
    "wof:placetype":"venue"
},
  "geometry": {"coordinates":[150.41793823200001,-34.4792938232],"type":"Point"}
}