{
  "type": "Feature",
  "properties": {
    "addr:full":"14 Harley Crt Finley NSW 2713",
    "addr:housenumber":"14",
    "addr:postcode":"2713",
    "addr:street":"Harley Crt",
    "iso:country":"AU",
    "sg:address":"14 Harley Crt",
    "sg:city":"Finley",
    "sg:classifiers":[
        {
            "category":"Social Services",
            "subcategory":"Adult Care",
            "type":"Services"
        }
    ],
    "sg:phone":"+61 3 5883 1702",
    "sg:postcode":"2713",
    "sg:province":"NSW",
    "sg:tags":[
        "towing"
    ],
    "wof:name":"Dundon Panel Works",
    "wof:placetype":"venue"
},
  "geometry": {"coordinates":[145.58128356899999,-35.6287155151],"type":"Point"}
}