{
  "type": "Feature",
  "properties": {
    "addr:full":"308 Darling St Balmain NSW 2041",
    "addr:housenumber":"308",
    "addr:postcode":"2041",
    "addr:street":"Darling St",
    "iso:country":"AU",
    "sg:address":"308 Darling St",
    "sg:city":"Balmain",
    "sg:classifiers":[
        {
            "category":"Health Services",
            "subcategory":"Dentist",
            "type":"Services"
        }
    ],
    "sg:phone":"+61 2 9810 3867",
    "sg:postcode":"2041",
    "sg:province":"NSW",
    "wof:name":"Sebel Robert Dr",
    "wof:placetype":"venue"
},
  "geometry": {"coordinates":[151.180283,-33.857311],"type":"Point"}
}