{
  "type": "Feature",
  "properties": {
    "addr:full":"119 Craythorne Rd Rosevears TAS 7277",
    "addr:housenumber":"119",
    "addr:postcode":"7277",
    "addr:street":"Craythorne Rd",
    "iso:country":"AU",
    "sg:address":"119 Craythorne Rd",
    "sg:city":"Rosevears",
    "sg:classifiers":[
        {
            "category":"Building & Trades",
            "subcategory":"Landscaping Services",
            "type":"Services"
        }
    ],
    "sg:phone":"+61 3 6330 2464",
    "sg:postcode":"7277",
    "sg:province":"TAS",
    "sg:tags":[
        "designer",
        "landscape",
        "contractor"
    ],
    "wof:name":"Denouden M & I",
    "wof:placetype":"venue"
},
  "geometry": {"coordinates":[147.006103516,-41.3315124512],"type":"Point"}
}