{
  "type": "Feature",
  "properties": {
    "addr:full":"Level7, Unit 2, 18 Queen St Melbourne VIC 3000",
    "addr:housenumber":"18",
    "addr:postcode":"3000",
    "addr:street":"Queen St",
    "iso:country":"AU",
    "sg:address":"Level7, Unit 2, 18 Queen St",
    "sg:city":"Melbourne",
    "sg:classifiers":[
        {
            "category":"Social Services",
            "subcategory":"Retirement Home",
            "type":"Services"
        }
    ],
    "sg:phone":"+61 3 9629 7776",
    "sg:postcode":"3000",
    "sg:province":"VIC",
    "sg:tags":[
        "life",
        "coaching"
    ],
    "wof:name":"Ability Clinic",
    "wof:placetype":"venue"
},
  "geometry": {"coordinates":[144.962432861,-37.8183021545],"type":"Point"}
}