{
  "type": "Feature",
  "properties": {
    "addr:full":"116a Sandy Bay Rd Sandy Bay TAS 7005",
    "addr:housenumber":"116a",
    "addr:postcode":"7005",
    "addr:street":"Sandy Bay Rd",
    "iso:country":"AU",
    "sg:address":"116a Sandy Bay Rd",
    "sg:city":"Sandy Bay",
    "sg:classifiers":[
        {
            "category":"Real Estate",
            "subcategory":"Architect",
            "type":"Services"
        }
    ],
    "sg:phone":"+61 3 6223 2166",
    "sg:postcode":"7005",
    "sg:province":"TAS",
    "wof:name":"Drury Mark",
    "wof:placetype":"venue"
},
  "geometry": {"coordinates":[147.32621765100001,-42.8924026489],"type":"Point"}
}