{
  "type": "Feature",
  "properties": {
    "addr:full":"25- 27 Wellington St North Hobart TAS 7000",
    "addr:housenumber":"27",
    "addr:postcode":"7000",
    "addr:street":"Wellington St",
    "iso:country":"AU",
    "sg:address":"25- 27 Wellington St",
    "sg:city":"North Hobart",
    "sg:classifiers":[
        {
            "category":"Professional",
            "subcategory":"Computer Services",
            "type":"Services"
        }
    ],
    "sg:phone":"+61 3 6231 2349",
    "sg:postcode":"7000",
    "sg:province":"TAS",
    "sg:tags":[
        "repairs",
        "upgrade",
        "equipment"
    ],
    "wof:name":"P C Service & Support",
    "wof:placetype":"venue"
},
  "geometry": {"coordinates":[147.31907653799999,-42.8707542419],"type":"Point"}
}