{
  "type": "Feature",
  "properties": {
    "addr:full":"Lot 26 McLeans Rd Samford QLD 4520",
    "addr:postcode":"4520",
    "addr:street":"Mcleans Rd",
    "iso:country":"AU",
    "sg:address":"Lot 26 McLeans Rd",
    "sg:city":"Samford",
    "sg:classifiers":[
        {
            "category":"Government",
            "subcategory":"Department Of Motor Vehicles",
            "type":"Public Place"
        }
    ],
    "sg:phone":"+61 7 3289 2284",
    "sg:postcode":"4520",
    "sg:province":"QLD",
    "sg:tags":[
        "tank",
        "cleaning"
    ],
    "wof:name":"A 1 Water Tank Services",
    "wof:placetype":"venue"
},
  "geometry": {"coordinates":[152.897446,-27.399429],"type":"Point"}
}