{
  "type": "Feature",
  "properties": {
    "addr:full":"31 Mount Barker Rd Stirling SA 5152",
    "addr:housenumber":"31",
    "addr:postcode":"5152",
    "addr:street":"Mount Barker Rd",
    "iso:country":"AU",
    "sg:address":"31 Mount Barker Rd",
    "sg:city":"Stirling",
    "sg:classifiers":[
        {
            "category":"Shopping",
            "subcategory":"Clothing, Apparel, & Fashions",
            "type":"Retail Goods"
        }
    ],
    "sg:phone":"+61 8 8370 8313",
    "sg:postcode":"5152",
    "sg:province":"SA",
    "sg:tags":[
        "lady",
        "wear"
    ],
    "wof:name":"Judells",
    "wof:placetype":"venue"
},
  "geometry": {"coordinates":[138.72291564899999,-35.0080375671],"type":"Point"}
}