{
  "type": "Feature",
  "properties": {
    "addr:full":"192 Brandon Park Drv Wheelers Hill VIC 3150",
    "addr:housenumber":"192",
    "addr:postcode":"3150",
    "addr:street":"Brandon Park Drv",
    "iso:country":"AU",
    "sg:address":"192 Brandon Park Drv",
    "sg:city":"Wheelers Hill",
    "sg:classifiers":[
        {
            "category":"Personal",
            "subcategory":"Beauty Salon",
            "type":"Services"
        }
    ],
    "sg:phone":"+61 3 9561 1022",
    "sg:postcode":"3150",
    "sg:province":"VIC",
    "sg:tags":[
        "hairdresser"
    ],
    "wof:name":"Heads For Hair",
    "wof:placetype":"venue"
},
  "geometry": {"coordinates":[145.176437378,-37.9170913696],"type":"Point"}
}