{
  "type": "Feature",
  "properties": {
    "addr:full":"5 Vickers St Edmonton QLD 4869",
    "addr:housenumber":"5",
    "addr:postcode":"4869",
    "addr:street":"Vickers St",
    "iso:country":"AU",
    "sg:address":"5 Vickers St",
    "sg:city":"Edmonton",
    "sg:classifiers":[
        {
            "category":"Building & Trades",
            "subcategory":"Construction",
            "type":"Services"
        }
    ],
    "sg:phone":"+61 7 4045 5998",
    "sg:postcode":"4869",
    "sg:province":"QLD",
    "sg:tags":[
        "management"
    ],
    "wof:name":"Metrobuild Constructions Pty Ltd",
    "wof:placetype":"venue"
},
  "geometry": {"coordinates":[145.74597168,-17.0002288818],"type":"Point"}
}