{
  "type": "Feature",
  "properties": {
    "addr:full":"131 Ferry Rd Southport QLD 4215",
    "addr:housenumber":"131",
    "addr:postcode":"4215",
    "addr:street":"Ferry Rd",
    "iso:country":"AU",
    "sg:address":"131 Ferry Rd",
    "sg:city":"Southport",
    "sg:classifiers":[
        {
            "category":"Home & Garden",
            "subcategory":"Furniture",
            "type":"Retail Goods"
        }
    ],
    "sg:phone":"+61 7 5528 4483",
    "sg:postcode":"4215",
    "sg:province":"QLD",
    "sg:tags":[
        "business"
    ],
    "wof:name":"Pure Comfort",
    "wof:placetype":"venue"
},
  "geometry": {"coordinates":[153.41038513199999,-27.9812374115],"type":"Point"}
}