{
  "type": "Feature",
  "properties": {
    "addr:full":"Level 1, 136 Main St Osborne Park WA 6017",
    "addr:housenumber":"136",
    "addr:postcode":"6017",
    "addr:street":"Main St",
    "iso:country":"AU",
    "sg:address":"Level 1, 136 Main St",
    "sg:city":"Osborne Park",
    "sg:classifiers":[
        {
            "category":"Building & Trades",
            "subcategory":"Construction",
            "type":"Services"
        }
    ],
    "sg:phone":"+61 8 9340 9888",
    "sg:postcode":"6017",
    "sg:province":"WA",
    "sg:tags":[
        "contractor"
    ],
    "wof:name":"Pyramid Constructions (Wa) Pty Ltd",
    "wof:placetype":"venue"
},
  "geometry": {"coordinates":[115.828392029,-31.9016265869],"type":"Point"}
}