{
  "type": "Feature",
  "properties": {
    "addr:full":"Lot 82 Lilydale Rd Gidgegannup WA 6083",
    "addr:postcode":"6083",
    "addr:street":"Lilydale Rd",
    "iso:country":"AU",
    "sg:address":"Lot 82 Lilydale Rd",
    "sg:city":"Gidgegannup",
    "sg:classifiers":[
        {
            "category":"Farming",
            "subcategory":"Fish & Marine Products",
            "type":"Manufacturing & Wholesale Goods"
        }
    ],
    "sg:phone":"+61 8 9574 6493",
    "sg:postcode":"6083",
    "sg:province":"WA",
    "sg:tags":[
        "emu",
        "farmer"
    ],
    "wof:name":"Emu Breeders WA",
    "wof:placetype":"venue"
},
  "geometry": {"coordinates":[116.245277405,-31.7985992432],"type":"Point"}
}