{
  "type": "Feature",
  "properties": {
    "addr:full":"RMB 6380 Coragulac VIC 3249",
    "addr:postcode":"3249",
    "iso:country":"AU",
    "sg:address":"RMB 6380",
    "sg:city":"Coragulac",
    "sg:classifiers":[
        {
            "category":"Real Estate",
            "subcategory":"Surveying",
            "type":"Services"
        }
    ],
    "sg:phone":"+61 3 5233 1559",
    "sg:postcode":"3249",
    "sg:province":"VIC",
    "sg:tags":[
        "surveyor",
        "land"
    ],
    "wof:name":"Reed & Reed",
    "wof:placetype":"venue"
},
  "geometry": {"coordinates":[143.52618408199999,-38.2639007568],"type":"Point"}
}