{
  "type": "Feature",
  "properties": {
    "addr:full":"6/ 384 Oxford St Bondi Junction NSW 2022",
    "addr:housenumber":"/ 384",
    "addr:postcode":"2022",
    "addr:street":"Oxford St",
    "iso:country":"AU",
    "sg:address":"6/ 384 Oxford St",
    "sg:city":"Bondi Junction",
    "sg:classifiers":[
        {
            "category":"Health Services",
            "subcategory":"Doctor",
            "type":"Services"
        }
    ],
    "sg:phone":"+61 2 9387 1545",
    "sg:postcode":"2022",
    "sg:province":"NSW",
    "sg:tags":[
        "podiatrist"
    ],
    "wof:name":"Barry Georgina",
    "wof:placetype":"venue"
},
  "geometry": {"coordinates":[151.24700927699999,-33.8915061951],"type":"Point"}
}