{
  "type": "Feature",
  "properties": {
    "addr:full":"237 Woodham Ave Mildura VIC 3500",
    "addr:housenumber":"237",
    "addr:postcode":"3500",
    "addr:street":"Woodham Ave",
    "iso:country":"AU",
    "sg:address":"237 Woodham Ave",
    "sg:city":"Mildura",
    "sg:classifiers":[
        {
            "category":"Building & Trades",
            "subcategory":"Landscaping Services",
            "type":"Services"
        }
    ],
    "sg:phone":"+61 3 5023 6327",
    "sg:postcode":"3500",
    "sg:province":"VIC",
    "sg:tags":[
        "stump",
        "tree",
        "felling",
        "removal"
    ],
    "wof:name":"O&#039;Rourke Danny",
    "wof:placetype":"venue"
},
  "geometry": {"coordinates":[142.15269470199999,-34.1949577332],"type":"Point"}
}