{
  "type": "Feature",
  "properties": {
    "addr:full":"21 Highs Rd West Pennant Hills NSW 2125",
    "addr:housenumber":"21",
    "addr:postcode":"2125",
    "addr:street":"Highs Rd",
    "iso:country":"AU",
    "sg:address":"21 Highs Rd",
    "sg:city":"West Pennant Hills",
    "sg:classifiers":[
        {
            "category":"Manufacturing",
            "subcategory":"Tools & Machinery",
            "type":"Manufacturing & Wholesale Goods"
        }
    ],
    "sg:phone":"+61 2 9899 1178",
    "sg:postcode":"2125",
    "sg:province":"NSW",
    "sg:tags":[
        "wholesaler",
        "lingerie",
        "mfrs",
        "sleepwear"
    ],
    "wof:name":"Silkway Pty Ltd",
    "wof:placetype":"venue"
},
  "geometry": {"coordinates":[151.024658203,-33.7354278564],"type":"Point"}
}