{
  "type": "Feature",
  "properties": {
    "addr:full":"4 Post Office Pl Glenroy VIC 3046",
    "addr:housenumber":"4",
    "addr:postcode":"3046",
    "addr:street":"Post Office Pl",
    "iso:country":"AU",
    "sg:address":"4 Post Office Pl",
    "sg:city":"Glenroy",
    "sg:classifiers":[
        {
            "category":"Communications",
            "subcategory":"Film & Video Production",
            "type":"Services"
        }
    ],
    "sg:phone":"+61 3 9300 3811",
    "sg:postcode":"3046",
    "sg:province":"VIC",
    "sg:tags":[
        "dvd",
        "library"
    ],
    "wof:name":"Video Busters",
    "wof:placetype":"venue"
},
  "geometry": {"coordinates":[144.916503906,-37.7042922974],"type":"Point"}
}