{
  "type": "Feature",
  "properties": {
    "iso:country":"AU",
    "sg:address":"PO Box 626",
    "sg:city":"Inverell",
    "sg:classifiers":[
        {
            "category":"Social Services",
            "subcategory":"Retirement Home",
            "type":"Services"
        }
    ],
    "sg:phone":"+61 408 224 997",
    "sg:postcode":"2360",
    "sg:province":"NSW",
    "sg:tags":[
        "environmental",
        "consultant",
        "pollution"
    ],
    "wof:name":"The Envirofactor",
    "wof:placetype":"venue"
},
  "geometry": {"coordinates":[151.113555908,-29.776309967],"type":"Point"}
}