{
  "type": "Feature",
  "properties": {
    "iso:country":"AU",
    "sg:address":"210 George Rd",
    "sg:city":"Geraldton",
    "sg:classifiers":[
        {
            "category":"Farming",
            "subcategory":"Farm",
            "type":"Manufacturing & Wholesale Goods"
        }
    ],
    "sg:phone":"+61 8 9921 3274",
    "sg:postcode":"6530",
    "sg:province":"WA",
    "sg:tags":[
        "farmer"
    ],
    "wof:name":"Mills P J & C A",
    "wof:placetype":"venue"
},
  "geometry": {"coordinates":[114.619537353,-28.756778717],"type":"Point"}
}