{
  "type": "Feature",
  "properties": {
    "addr:full":"65 Deakin St Silverwater NSW 2128",
    "addr:housenumber":"65",
    "addr:postcode":"2128",
    "addr:street":"Deakin St",
    "iso:country":"AU",
    "sg:address":"65 Deakin St",
    "sg:city":"Silverwater",
    "sg:classifiers":[
        {
            "category":"Utilities",
            "subcategory":"Refuse",
            "type":"Services"
        }
    ],
    "sg:phone":"+61 2 9748 1848",
    "sg:postcode":"2128",
    "sg:province":"NSW",
    "sg:tags":[
        "remover",
        "rubbish"
    ],
    "wof:name":"Trailer Skips",
    "wof:placetype":"venue"
},
  "geometry": {"coordinates":[151.039260864,-33.83959198],"type":"Point"}
}