{
  "type": "Feature",
  "properties": {
    "addr:full":"10 Cunneen St Mulgrave NSW 2756",
    "addr:housenumber":"10",
    "addr:postcode":"2756",
    "addr:street":"Cunneen St",
    "iso:country":"AU",
    "sg:address":"10 Cunneen St",
    "sg:city":"Mulgrave",
    "sg:classifiers":[
        {
            "category":"Manufacturing",
            "subcategory":"Tools & Machinery",
            "type":"Manufacturing & Wholesale Goods"
        }
    ],
    "sg:phone":"+61 2 4577 3733",
    "sg:postcode":"2756",
    "sg:province":"NSW",
    "sg:tags":[
        "earth",
        "excavating",
        "moving",
        "equipment"
    ],
    "sg:website":"http://www.skidsteertoyota.com.au",
    "wof:name":"Skid Steer Toyota",
    "wof:placetype":"venue"
},
  "geometry": {"coordinates":[150.83375549300001,-33.6223106384],"type":"Point"}
}