{
  "type": "Feature",
  "properties": {
    "iso:country":"AU",
    "sg:address":"PO Box 3478",
    "sg:city":"Success",
    "sg:classifiers":[
        {
            "category":"Wholesale",
            "subcategory":"Seafood",
            "type":"Manufacturing & Wholesale Goods"
        }
    ],
    "sg:phone":"+61 8 9498 7109",
    "sg:postcode":"6964",
    "sg:province":"WA",
    "sg:tags":[
        "fish"
    ],
    "wof:name":"Adriatic Seafood",
    "wof:placetype":"venue"
},
  "geometry": {"coordinates":[115.846428,-32.15659],"type":"Point"}
}