{
  "type": "Feature",
  "properties": {
    "addr:full":"Cnr Commercial Rd & Freeman St Lalor Park NSW 2147",
    "addr:postcode":"2147",
    "addr:street":"Commercial Rd & Freeman St",
    "iso:country":"AU",
    "sg:address":"Cnr Commercial Rd & Freeman St",
    "sg:city":"Lalor Park",
    "sg:classifiers":[
        {
            "category":"Autos & Motor Vehicles",
            "subcategory":"Fuel & Gas Station",
            "type":"Retail Goods"
        }
    ],
    "sg:phone":"+61 2 9624 5550",
    "sg:postcode":"2147",
    "sg:province":"NSW",
    "wof:name":"Ampol",
    "wof:placetype":"venue"
},
  "geometry": {"coordinates":[150.930343628,-33.7625656128],"type":"Point"}
}