{
  "type": "Feature",
  "properties": {
    "addr:full":"1 Carlita Pl Raceview QLD 4305",
    "addr:housenumber":"1",
    "addr:postcode":"4305",
    "addr:street":"Carlita Pl",
    "iso:country":"AU",
    "sg:address":"1 Carlita Pl",
    "sg:city":"Raceview",
    "sg:classifiers":[
        {
            "category":"Building & Trades",
            "subcategory":"Construction",
            "type":"Services"
        }
    ],
    "sg:phone":"+61 7 3288 8671",
    "sg:postcode":"4305",
    "sg:province":"QLD",
    "sg:tags":[
        "contractor"
    ],
    "wof:name":"Glode D B",
    "wof:placetype":"venue"
},
  "geometry": {"coordinates":[152.77491760300001,-27.6356887817],"type":"Point"}
}