{
  "type": "Feature",
  "properties": {
    "addr:full":"Unit 2/ 18 Vale Rd Bathurst NSW 2795",
    "addr:housenumber":"18",
    "addr:postcode":"2795",
    "addr:street":"Vale Rd",
    "iso:country":"AU",
    "sg:address":"Unit 2/ 18 Vale Rd",
    "sg:city":"Bathurst",
    "sg:classifiers":[
        {
            "category":"Freight",
            "type":"Transportation"
        }
    ],
    "sg:phone":"+61 2 6331 8184",
    "sg:postcode":"2795",
    "sg:province":"NSW",
    "sg:tags":[
        "light",
        "carrier"
    ],
    "wof:name":"IPEC",
    "wof:placetype":"venue"
},
  "geometry": {"coordinates":[149.56953430199999,-33.4664382935],"type":"Point"}
}