{
  "type": "Feature",
  "properties": {
    "addr:full":"64 Dun Bay Rd Dunsborough WA 6281",
    "addr:housenumber":"64",
    "addr:postcode":"6281",
    "addr:street":"Dun Bay Rd",
    "iso:country":"AU",
    "sg:address":"64 Dun Bay Rd",
    "sg:city":"Dunsborough",
    "sg:classifiers":[
        {
            "category":"Real Estate",
            "subcategory":"Real Estate Services",
            "type":"Services"
        }
    ],
    "sg:phone":"+61 8 9754 1555",
    "sg:postcode":"6281",
    "sg:province":"WA",
    "sg:tags":[
        "valuer"
    ],
    "wof:name":"Valuation Partners WA Pty Ltd",
    "wof:placetype":"venue"
},
  "geometry": {"coordinates":[115.10247039799999,-33.6168327332],"type":"Point"}
}