{
  "type": "Feature",
  "properties": {
    "addr:full":"Level 1, 1000 Whitehorse Rd Box Hill VIC 3128",
    "addr:housenumber":"1000",
    "addr:postcode":"3128",
    "addr:street":"Whitehorse Rd",
    "iso:country":"AU",
    "sg:address":"Level 1, 1000 Whitehorse Rd",
    "sg:city":"Box Hill",
    "sg:classifiers":[
        {
            "category":"Wholesale",
            "subcategory":"Painting Supplies",
            "type":"Manufacturing & Wholesale Goods"
        }
    ],
    "sg:phone":"+61 3 9286 9629",
    "sg:postcode":"3128",
    "sg:province":"VIC",
    "sg:tags":[
        "equipment",
        "drawing",
        "drafting"
    ],
    "wof:name":"Box Hill Institute Art & Bookshop",
    "wof:placetype":"venue"
},
  "geometry": {"coordinates":[145.12567138700001,-37.8186073303],"type":"Point"}
}