{
  "type": "Feature",
  "properties": {
    "addr:full":"423 Frome St (Newell Hwy) Moree NSW 2400",
    "addr:housenumber":"423",
    "addr:postcode":"2400",
    "addr:street":"Frome St Newell Hwy",
    "iso:country":"AU",
    "sg:address":"423 Frome St (Newell Hwy)",
    "sg:city":"Moree",
    "sg:classifiers":[
        {
            "category":"Utilities",
            "subcategory":"Fuel Oil & Lpg",
            "type":"Services"
        }
    ],
    "sg:phone":"+61 2 6752 6200",
    "sg:postcode":"2400",
    "sg:province":"NSW",
    "sg:tags":[
        "merchant"
    ],
    "wof:name":"BP Oil",
    "wof:placetype":"venue"
},
  "geometry": {"coordinates":[149.842697144,-29.4699363708],"type":"Point"}
}