{
  "type": "Feature",
  "properties": {
    "addr:full":"13/ 343 Melton Rd Northgate QLD 4013",
    "addr:housenumber":"13 / 343",
    "addr:postcode":"4013",
    "addr:street":"Melton Rd",
    "iso:country":"AU",
    "sg:address":"13/ 343 Melton Rd",
    "sg:city":"Northgate",
    "sg:classifiers":[
        {
            "category":"Home & Garden",
            "subcategory":"Furniture",
            "type":"Retail Goods"
        }
    ],
    "sg:phone":"+61 7 3266 3277",
    "sg:postcode":"4013",
    "sg:province":"QLD",
    "sg:tags":[
        "outdoor"
    ],
    "wof:name":"Metal Art Design",
    "wof:placetype":"venue"
},
  "geometry": {"coordinates":[153.07098388700001,-27.3938045502],"type":"Point"}
}