{
  "type": "Feature",
  "properties": {
    "addr:full":"U3/ 185 Ramsgate Rd Ramsgate Beach NSW 2217",
    "addr:housenumber":"185",
    "addr:postcode":"2217",
    "addr:street":"U3 /;Ramsgate Rd",
    "iso:country":"AU",
    "sg:address":"U3/ 185 Ramsgate Rd",
    "sg:city":"Ramsgate Beach",
    "sg:classifiers":[
        {
            "category":"Utilities",
            "subcategory":"Electric",
            "type":"Services"
        }
    ],
    "sg:phone":"+61 2 9529 7966",
    "sg:postcode":"2217",
    "sg:province":"NSW",
    "sg:tags":[
        "electrical",
        "contractor"
    ],
    "wof:name":"Bevia Services",
    "wof:placetype":"venue"
},
  "geometry": {"coordinates":[151.143936,-33.985733],"type":"Point"}
}