{
  "type": "Feature",
  "properties": {
    "addr:full":"21 Falls Rd Serpentine WA 6125",
    "addr:housenumber":"21",
    "addr:postcode":"6125",
    "addr:street":"Falls Rd",
    "iso:country":"AU",
    "sg:address":"21 Falls Rd",
    "sg:city":"Serpentine",
    "sg:classifiers":[
        {
            "category":"Shopping",
            "subcategory":"Crafts & Fabrics",
            "type":"Retail Goods"
        }
    ],
    "sg:phone":"+61 8 9525 2638",
    "sg:postcode":"6125",
    "sg:province":"WA",
    "sg:tags":[
        "supply"
    ],
    "wof:name":"Jarrah Joint The",
    "wof:placetype":"venue"
},
  "geometry": {"coordinates":[116.000389099,-32.3686256409],"type":"Point"}
}