{
  "type": "Feature",
  "properties": {
    "iso:country":"AU",
    "sg:address":"1910 Beach Rd",
    "sg:city":"Malaga",
    "sg:classifiers":[
        {
            "category":"Landmark",
            "subcategory":"City Walls",
            "type":"Public Place"
        }
    ],
    "sg:phone":"+61 13 23 77",
    "sg:postcode":"6090",
    "sg:province":"WA",
    "sg:tags":[
        "finish"
    ],
    "wof:name":"Dulux",
    "wof:placetype":"venue"
},
  "geometry": {"coordinates":[115.88723754900001,-31.8555831909],"type":"Point"}
}