{
  "type": "Feature",
  "properties": {
    "addr:full":"Shop 2/ 246 Hay St (Corner of Bennett St) East Perth WA 6004",
    "addr:housenumber":"shop 2 / 246",
    "addr:postcode":"6004",
    "addr:street":"Hay St Corner Of Bennett St East",
    "iso:country":"AU",
    "sg:address":"Shop 2/ 246 Hay St (Corner of Bennett St)",
    "sg:city":"East Perth",
    "sg:classifiers":[
        {
            "category":"Personal",
            "subcategory":"Beauty Salon",
            "type":"Services"
        }
    ],
    "sg:phone":"+61 8 9225 5030",
    "sg:postcode":"6004",
    "sg:province":"WA",
    "sg:tags":[
        "hairdresser"
    ],
    "wof:name":"Angelique Q Hair Salon",
    "wof:placetype":"venue"
},
  "geometry": {"coordinates":[115.870620727,-31.9578723907],"type":"Point"}
}