{
  "type": "Feature",
  "properties": {
    "addr:full":"7A Gurr St Geelong East VIC 3219",
    "addr:housenumber":"7a",
    "addr:postcode":"3219",
    "addr:street":"Gurr St",
    "iso:country":"AU",
    "sg:address":"7A Gurr St",
    "sg:city":"Geelong East",
    "sg:classifiers":[
        {
            "category":"Professional",
            "subcategory":"Business Services",
            "type":"Services"
        }
    ],
    "sg:phone":"+61 3 5223 2779",
    "sg:postcode":"3219",
    "sg:province":"VIC",
    "sg:tags":[
        "drafting"
    ],
    "wof:name":"Adams Chris",
    "wof:placetype":"venue"
},
  "geometry": {"coordinates":[144.375457764,-38.1570968628],"type":"Point"}
}