{
  "type": "Feature",
  "properties": {
    "iso:country":"AU",
    "sg:address":"Edgell La",
    "sg:city":"Mudgee",
    "sg:classifiers":[
        {
            "category":"Farming",
            "subcategory":"Vineyard",
            "type":"Manufacturing & Wholesale Goods"
        }
    ],
    "sg:phone":"+61 2 6372 2408",
    "sg:postcode":"2850",
    "sg:province":"NSW",
    "sg:tags":[
        "winery"
    ],
    "wof:name":"Tallara Wines - Frog Rock",
    "wof:placetype":"venue"
},
  "geometry": {"coordinates":[149.615982,-32.571018],"type":"Point"}
}