{
  "type": "Feature",
  "properties": {
    "addr:full":"PO Box 92 Glengarry WA 6023",
    "addr:postcode":"6023",
    "iso:country":"AU",
    "sg:address":"PO Box 92",
    "sg:city":"Glengarry",
    "sg:classifiers":[
        {
            "category":"Professional",
            "subcategory":"Computer Services",
            "type":"Services"
        }
    ],
    "sg:phone":"+61 8 9345 1269",
    "sg:postcode":"6023",
    "sg:province":"WA",
    "sg:tags":[
        "repairs",
        "upgrade",
        "equipment"
    ],
    "wof:name":"Mach Solutions IT",
    "wof:placetype":"venue"
},
  "geometry": {"coordinates":[115.78256225600001,-31.8317890167],"type":"Point"}
}