{
  "type": "Feature",
  "properties": {
    "addr:full":"37 Bendigo St Richmond VIC 3121",
    "addr:housenumber":"37",
    "addr:postcode":"3121",
    "addr:street":"Bendigo St",
    "iso:country":"AU",
    "sg:address":"37 Bendigo St",
    "sg:city":"Richmond",
    "sg:classifiers":[
        {
            "category":"Fast Food",
            "type":"Food & Drink"
        }
    ],
    "sg:phone":"+61 3 9428 4196",
    "sg:postcode":"3121",
    "sg:province":"VIC",
    "sg:tags":[
        "away",
        "take"
    ],
    "wof:name":"Nine Stars Milk Bar",
    "wof:placetype":"venue"
},
  "geometry": {"coordinates":[145.012176514,-37.8248062134],"type":"Point"}
}