{
  "type": "Feature",
  "properties": {
    "addr:full":"69 St Pauls Rd Sorrento VIC 3943",
    "addr:housenumber":"69",
    "addr:postcode":"3943",
    "addr:street":"St Pauls Rd",
    "iso:country":"AU",
    "sg:address":"69 St Pauls Rd",
    "sg:city":"Sorrento",
    "sg:classifiers":[
        {
            "category":"Food & Beverages",
            "subcategory":"Groceries & Convenience Stores",
            "type":"Retail Goods"
        }
    ],
    "sg:phone":"+61 3 5984 1708",
    "sg:postcode":"3943",
    "sg:province":"VIC",
    "wof:name":"St Pauls Road General Store",
    "wof:placetype":"venue"
},
  "geometry": {"coordinates":[144.74296569800001,-38.3472976685],"type":"Point"}
}