{
  "type": "Feature",
  "properties": {
    "addr:full":"Douglas Rd Quakers Hill NSW 2763",
    "addr:postcode":"2763",
    "addr:street":"Douglas Rd",
    "iso:country":"AU",
    "sg:address":"Douglas Rd",
    "sg:city":"Quakers Hill",
    "sg:classifiers":[
        {
            "category":"Fast Food",
            "type":"Food & Drink"
        }
    ],
    "sg:phone":"+61 2 9626 3419",
    "sg:postcode":"2763",
    "sg:province":"NSW",
    "sg:tags":[
        "away",
        "take"
    ],
    "wof:name":"Chiotellis A & I",
    "wof:placetype":"venue"
},
  "geometry": {"coordinates":[150.88461303700001,-33.7268257141],"type":"Point"}
}