{
  "type": "Feature",
  "properties": {
    "addr:full":"560 Metcalfe Rd Ferndale WA 6148",
    "addr:housenumber":"560",
    "addr:postcode":"6148",
    "addr:street":"Metcalfe Rd",
    "iso:country":"AU",
    "sg:address":"560 Metcalfe Rd",
    "sg:city":"Ferndale",
    "sg:classifiers":[
        {
            "category":"Personal",
            "subcategory":"Beauty Salon",
            "type":"Services"
        }
    ],
    "sg:phone":"+61 8 9350 5858",
    "sg:postcode":"6148",
    "sg:province":"WA",
    "sg:tags":[
        "hairdresser"
    ],
    "wof:name":"Paradee Hair Studio",
    "wof:placetype":"venue"
},
  "geometry": {"coordinates":[115.925667,-32.035683],"type":"Point"}
}