{
  "type": "Feature",
  "properties": {
    "addr:full":"Shop T258 Sunshine Plaza Horton Pde Maroochydore QLD 4558",
    "addr:housenumber":"t258",
    "addr:postcode":"4558",
    "addr:street":"Horton Pde",
    "iso:country":"AU",
    "sg:address":"Shop T258 Sunshine Plaza Horton Pde",
    "sg:city":"Maroochydore",
    "sg:classifiers":[
        {
            "category":"Shopping",
            "subcategory":"Clothing, Apparel, & Fashions",
            "type":"Retail Goods"
        }
    ],
    "sg:phone":"+61 7 5443 7466",
    "sg:postcode":"4558",
    "sg:province":"QLD",
    "sg:tags":[
        "lady",
        "wear"
    ],
    "wof:name":"Miller's Fashion Club",
    "wof:placetype":"venue"
},
  "geometry": {"coordinates":[153.089675903,-26.6531066895],"type":"Point"}
}