{
  "type": "Feature",
  "properties": {
    "iso:country":"AU",
    "sg:address":"112 Woorarra Ave",
    "sg:city":"Elanora Heights",
    "sg:classifiers":[
        {
            "category":"Building & Trades",
            "subcategory":"Construction",
            "type":"Services"
        }
    ],
    "sg:phone":"+61 2 9944 6200",
    "sg:postcode":"2101",
    "sg:province":"NSW",
    "sg:tags":[
        "contractor"
    ],
    "wof:name":"W.E. Knight Pty Ltd",
    "wof:placetype":"venue"
},
  "geometry": {"coordinates":[151.28715500000001,-33.706764],"type":"Point"}
}