{
  "type": "Feature",
  "properties": {
    "iso:country":"AU",
    "sg:address":"Unit 2/ 14 York Rd",
    "sg:city":"Ingleburn",
    "sg:classifiers":[
        {
            "category":"Retail",
            "subcategory":"Storage",
            "type":"Services"
        }
    ],
    "sg:phone":"+61 2 9605 7646",
    "sg:postcode":"2565",
    "sg:province":"NSW",
    "sg:tags":[
        "shelving",
        "system"
    ],
    "wof:name":"Structured Warehouse Solutions",
    "wof:placetype":"venue"
},
  "geometry": {"coordinates":[150.861862183,-33.9916229248],"type":"Point"}
}