{
  "type": "Feature",
  "properties": {
    "addr:full":"Woodcroft Medical Centre 1 Sir James Hardy Way Woodcroft SA 5162",
    "addr:housenumber":"1",
    "addr:postcode":"5162",
    "addr:street":"Sir James Hardy Way",
    "iso:country":"AU",
    "sg:address":"Woodcroft Medical Centre 1",
    "sg:city":"Sir James Hardy Way Woodcroft",
    "sg:classifiers":[
        {
            "category":"Government",
            "subcategory":"Court House",
            "type":"Public Place"
        }
    ],
    "sg:phone":"+61 419 821 988",
    "sg:postcode":"5162",
    "sg:province":"SA",
    "sg:tags":[
        "personal",
        "marriage",
        "family",
        "counselling"
    ],
    "wof:name":"Burnett Kerry",
    "wof:placetype":"venue"
},
  "geometry": {"coordinates":[138.55752563499999,-35.0939559937],"type":"Point"}
}