{
  "type": "Feature",
  "properties": {
    "addr:full":"741 Glen Huntly Rd Caulfield South VIC 3162",
    "addr:housenumber":"741",
    "addr:postcode":"3162",
    "addr:street":"Glen Huntly Rd",
    "iso:country":"AU",
    "sg:address":"741 Glen Huntly Rd",
    "sg:city":"Caulfield South",
    "sg:classifiers":[
        {
            "category":"Cafe",
            "type":"Food & Drink"
        }
    ],
    "sg:phone":"+61 3 9532 7988",
    "sg:postcode":"3162",
    "sg:province":"VIC",
    "wof:name":"Signatures",
    "wof:placetype":"venue"
},
  "geometry": {"coordinates":[145.02041625999999,-37.886554718],"type":"Point"}
}