{
  "type": "Feature",
  "properties": {
    "addr:full":"St Ives Cct Forest Lake QLD 4078",
    "addr:postcode":"4078",
    "iso:country":"AU",
    "sg:address":"St",
    "sg:city":"Ives Cct Forest Lake",
    "sg:classifiers":[
        {
            "category":"Building & Trades",
            "subcategory":"Construction",
            "type":"Services"
        }
    ],
    "sg:phone":"+61 7 3879 7766",
    "sg:postcode":"4078",
    "sg:province":"QLD",
    "sg:tags":[
        "contractor"
    ],
    "wof:name":"Adenbrook Homes",
    "wof:placetype":"venue"
},
  "geometry": {"coordinates":[152.97117614699999,-27.6286220551],"type":"Point"}
}