{
  "type": "Feature",
  "properties": {
    "iso:country":"AU",
    "sg:address":"66 Leila Rd",
    "sg:city":"Ormond",
    "sg:classifiers":[
        {
            "category":"Health Services",
            "subcategory":"Health Practitioner",
            "type":"Services"
        }
    ],
    "sg:phone":"+61 3 9578 8522",
    "sg:postcode":"3204",
    "sg:province":"VIC",
    "sg:tags":[
        "psychologist"
    ],
    "wof:name":"Forbes Simon",
    "wof:placetype":"venue"
},
  "geometry": {"coordinates":[145.050842,-37.901112],"type":"Point"}
}