{
  "type": "Feature",
  "properties": {
    "addr:full":"17 Hartington Drv Wantirna VIC 3152",
    "addr:housenumber":"17",
    "addr:postcode":"3152",
    "addr:street":"Hartington Drv",
    "iso:country":"AU",
    "sg:address":"17 Hartington Drv",
    "sg:city":"Wantirna",
    "sg:classifiers":[
        {
            "category":"Home & Garden",
            "subcategory":"Household Appliances",
            "type":"Retail Goods"
        }
    ],
    "sg:phone":"+61 3 9801 7161",
    "sg:postcode":"3152",
    "sg:province":"VIC",
    "sg:tags":[
        "heating",
        "system"
    ],
    "wof:name":"Aqua Therm",
    "wof:placetype":"venue"
},
  "geometry": {"coordinates":[145.231231689,-37.8653297424],"type":"Point"}
}