{
  "type": "Feature",
  "properties": {
    "iso:country":"AU",
    "sg:address":"8 Sackett St",
    "sg:city":"Brighton",
    "sg:classifiers":[
        {
            "category":"Building & Trades",
            "subcategory":"Construction",
            "type":"Services"
        }
    ],
    "sg:phone":"+61 411 472 086",
    "sg:postcode":"4017",
    "sg:province":"QLD",
    "sg:tags":[
        "concrete",
        "paving"
    ],
    "wof:name":"Innovations in Paving & Landscaping",
    "wof:placetype":"venue"
},
  "geometry": {"coordinates":[153.05389404300001,-27.2912502289],"type":"Point"}
}