{
  "type": "Feature",
  "properties": {
    "addr:full":"51 Quarry St Fremantle WA 6160",
    "addr:housenumber":"51",
    "addr:postcode":"6160",
    "addr:street":"Quarry St",
    "iso:country":"AU",
    "sg:address":"51 Quarry St",
    "sg:city":"Fremantle",
    "sg:classifiers":[
        {
            "category":"Health Services",
            "subcategory":"Doctor",
            "type":"Services"
        }
    ],
    "sg:phone":"+61 8 9336 1884",
    "sg:postcode":"6160",
    "sg:province":"WA",
    "sg:tags":[
        "medical",
        "practitioner"
    ],
    "wof:name":"Mole Check",
    "wof:placetype":"venue"
},
  "geometry": {"coordinates":[115.752731,-32.046761],"type":"Point"}
}