{
  "type": "Feature",
  "properties": {
    "addr:full":"55 Macleod St Bairnsdale VIC 3875",
    "addr:housenumber":"55",
    "addr:postcode":"3875",
    "addr:street":"Macleod St",
    "iso:country":"AU",
    "sg:address":"55 Macleod St",
    "sg:city":"Bairnsdale",
    "sg:classifiers":[
        {
            "category":"Home & Garden",
            "subcategory":"Building Materials",
            "type":"Retail Goods"
        }
    ],
    "sg:phone":"+61 3 5153 1700",
    "sg:postcode":"3875",
    "sg:province":"VIC",
    "sg:tags":[
        "secondhand"
    ],
    "wof:name":"Bairnsdale Buy & Sell Bazaar",
    "wof:placetype":"venue"
},
  "geometry": {"coordinates":[147.63351440400001,-37.8269805908],"type":"Point"}
}