{
  "type": "Feature",
  "properties": {
    "addr:full":"Level 1 360 Brunswick St Fitzroy VIC 3065",
    "addr:housenumber":"360",
    "addr:postcode":"3065",
    "addr:street":"Brunswick St",
    "iso:country":"AU",
    "sg:address":"Level 1 360 Brunswick St",
    "sg:city":"Fitzroy",
    "sg:classifiers":[
        {
            "category":"Personal",
            "subcategory":"Beauty Salon",
            "type":"Services"
        }
    ],
    "sg:phone":"+61 3 9419 6143",
    "sg:postcode":"3065",
    "sg:province":"VIC",
    "sg:tags":[
        "hairdresser"
    ],
    "wof:name":"Sogo Hair Body Image",
    "wof:placetype":"venue"
},
  "geometry": {"coordinates":[144.97889709500001,-37.7965507507],"type":"Point"}
}