{
  "type": "Feature",
  "properties": {
    "addr:full":"57 Braeside Rd Stirling SA 5152",
    "addr:housenumber":"57",
    "addr:postcode":"5152",
    "addr:street":"Braeside Rd",
    "iso:country":"AU",
    "sg:address":"57 Braeside Rd",
    "sg:city":"Stirling",
    "sg:classifiers":[
        {
            "category":"Ferry Terminal",
            "type":"Transportation"
        }
    ],
    "sg:phone":"+61 8 8339 4886",
    "sg:postcode":"5152",
    "sg:province":"SA",
    "sg:tags":[
        "raised",
        "floor"
    ],
    "wof:name":"Microfloor Systems Pty Ltd",
    "wof:placetype":"venue"
},
  "geometry": {"coordinates":[138.73431396500001,-35.003074646],"type":"Point"}
}