{
  "type": "Feature",
  "properties": {
    "addr:full":"867 South Western Hwy Byford WA 6122",
    "addr:housenumber":"867",
    "addr:postcode":"6122",
    "addr:street":"South Western Hwy",
    "iso:country":"AU",
    "sg:address":"867 South Western Hwy",
    "sg:city":"Byford",
    "sg:classifiers":[
        {
            "category":"Food & Beverages",
            "subcategory":"Supermarket",
            "type":"Retail Goods"
        }
    ],
    "sg:phone":"+61 8 9525 1500",
    "sg:postcode":"6122",
    "sg:province":"WA",
    "sg:tags":[
        "grocery",
        "store"
    ],
    "wof:name":"IGA Supermarkets",
    "wof:placetype":"venue"
},
  "geometry": {"coordinates":[116.008537292,-32.2220306396],"type":"Point"}
}