{
  "type": "Feature",
  "properties": {
    "iso:country":"AU",
    "sg:address":"161 Racecourse Rd",
    "sg:city":"Ascot",
    "sg:classifiers":[
        {
            "category":"Fast Food",
            "type":"Food & Drink"
        }
    ],
    "sg:phone":"+61 7 3268 4008",
    "sg:postcode":"4007",
    "sg:province":"QLD",
    "sg:tags":[
        "away",
        "take"
    ],
    "wof:name":"Cafe Restaurant Sebastien",
    "wof:placetype":"venue"
},
  "geometry": {"coordinates":[153.06559799999999,-27.432047],"type":"Point"}
}