{
  "type": "Feature",
  "properties": {
    "addr:full":"Unit 5, 83- 87 Wellington St St Kilda VIC 3182",
    "addr:housenumber":"83 87",
    "addr:postcode":"3182",
    "addr:street":"Wellington St",
    "iso:country":"AU",
    "sg:address":"Unit 5, 83- 87 Wellington St",
    "sg:city":"St Kilda",
    "sg:classifiers":[
        {
            "category":"Wholesale",
            "subcategory":"Apparel",
            "type":"Manufacturing & Wholesale Goods"
        }
    ],
    "sg:phone":"+61 3 9533 8544",
    "sg:postcode":"3182",
    "sg:province":"VIC",
    "sg:tags":[
        "wholesaler",
        "mfrs",
        "cap",
        "hat"
    ],
    "wof:name":"Australian Corporate Essentials",
    "wof:placetype":"venue"
},
  "geometry": {"coordinates":[144.98806762699999,-37.8568992615],"type":"Point"}
}