{
  "type": "Feature",
  "properties": {
    "iso:country":"AU",
    "sg:address":"45 Stephen St",
    "sg:city":"Bunbury",
    "sg:classifiers":[
        {
            "category":"Shopping",
            "subcategory":"Computers & Home Electronics",
            "type":"Retail Goods"
        }
    ],
    "sg:phone":"+61 8 9721 6222",
    "sg:postcode":"6230",
    "sg:province":"WA",
    "sg:tags":[
        "equipment",
        "part",
        "electronic"
    ],
    "wof:name":"Leading Edge Telecoms & Audio (W.A.)",
    "wof:placetype":"venue"
},
  "geometry": {"coordinates":[115.638763,-33.326294],"type":"Point"}
}