{
  "type": "Feature",
  "properties": {
    "addr:full":"Haly St Kingaroy QLD 4610",
    "addr:postcode":"4610",
    "addr:street":"Haly St",
    "iso:country":"AU",
    "sg:address":"Haly St",
    "sg:city":"Kingaroy",
    "sg:classifiers":[
        {
            "category":"Manufacturing",
            "subcategory":"Food",
            "type":"Manufacturing & Wholesale Goods"
        }
    ],
    "sg:phone":"+61 7 4162 6311",
    "sg:postcode":"4610",
    "sg:province":"QLD",
    "sg:tags":[
        "product",
        "nut",
        "edible"
    ],
    "wof:name":"Peanut Company Of Australia Limited",
    "wof:placetype":"venue"
},
  "geometry": {"coordinates":[151.83888244600001,-26.5392513275],"type":"Point"}
}