{
  "type": "Feature",
  "properties": {
    "addr:full":"224- 228 Murray St Hobart TAS 7000",
    "addr:housenumber":"228",
    "addr:postcode":"7000",
    "addr:street":"Murray St",
    "iso:country":"AU",
    "sg:address":"224- 228 Murray St",
    "sg:city":"Hobart",
    "sg:classifiers":[
        {
            "category":"Real Estate",
            "subcategory":"Architect",
            "type":"Services"
        }
    ],
    "sg:phone":"+61 3 6234 3307",
    "sg:postcode":"7000",
    "sg:province":"TAS",
    "wof:name":"David Menzies Architects Pty Ltd",
    "wof:placetype":"venue"
},
  "geometry": {"coordinates":[147.320236206,-42.880027771],"type":"Point"}
}