{
  "type": "Feature",
  "properties": {
    "iso:country":"AU",
    "sg:address":"112 Carthage St",
    "sg:city":"Tamworth",
    "sg:classifiers":[
        {
            "category":"Organizations",
            "subcategory":"Non-profit Organization",
            "type":"Services"
        }
    ],
    "sg:phone":"+61 2 6762 4902",
    "sg:postcode":"2340",
    "sg:province":"NSW",
    "sg:tags":[
        "support",
        "disability",
        "organisation"
    ],
    "wof:name":"Northcott Society The",
    "wof:placetype":"venue"
},
  "geometry": {"coordinates":[150.93522644000001,-31.0893688202],"type":"Point"}
}