{
  "type": "Feature",
  "properties": {
    "addr:full":"70 Stud Rd Dandenong VIC 3175",
    "addr:housenumber":"70",
    "addr:postcode":"3175",
    "addr:street":"Stud Rd",
    "iso:country":"AU",
    "sg:address":"70 Stud Rd",
    "sg:city":"Dandenong",
    "sg:classifiers":[
        {
            "category":"Health Services",
            "subcategory":"Dentist",
            "type":"Services"
        }
    ],
    "sg:phone":"+61 3 9791 9440",
    "sg:postcode":"3175",
    "sg:province":"VIC",
    "wof:name":"Ferguson Iain Dr",
    "wof:placetype":"venue"
},
  "geometry": {"coordinates":[145.22215270999999,-37.9785346985],"type":"Point"}
}