{
  "type": "Feature",
  "properties": {
    "addr:full":"563 The Scenic Rd MacMasters Beach NSW 2251",
    "addr:housenumber":"563",
    "addr:postcode":"2251",
    "addr:street":"The Scenic Rd",
    "iso:country":"AU",
    "sg:address":"563 The Scenic Rd",
    "sg:city":"MacMasters Beach",
    "sg:classifiers":[
        {
            "category":"Building & Trades",
            "subcategory":"Plumbing",
            "type":"Services"
        }
    ],
    "sg:phone":"+61 2 4368 1166",
    "sg:postcode":"2251",
    "sg:province":"NSW",
    "sg:tags":[
        "plumber",
        "gasfitters"
    ],
    "wof:name":"Bellchambers W E & B",
    "wof:placetype":"venue"
},
  "geometry": {"coordinates":[151.421707153,-33.494972229],"type":"Point"}
}