{
  "type": "Feature",
  "properties": {
    "iso:country":"AU",
    "sg:address":"54 Mclean St",
    "sg:city":"Ingleside",
    "sg:classifiers":[
        {
            "category":"Health Services",
            "subcategory":"Doctor",
            "type":"Services"
        }
    ],
    "sg:phone":"+61 2 9913 3033",
    "sg:postcode":"2101",
    "sg:province":"NSW",
    "sg:tags":[
        "podiatrist"
    ],
    "wof:name":"Australian Pedorthic Footwear Services",
    "wof:placetype":"venue"
},
  "geometry": {"coordinates":[151.27967799999999,-33.701031],"type":"Point"}
}