{
  "type": "Feature",
  "properties": {
    "addr:full":"11 Moss Rd Wingfield SA 5013",
    "addr:housenumber":"11",
    "addr:postcode":"5013",
    "addr:street":"Moss Rd",
    "iso:country":"AU",
    "sg:address":"11 Moss Rd",
    "sg:city":"Wingfield",
    "sg:classifiers":[
        {
            "category":"Building & Trades",
            "subcategory":"Construction",
            "type":"Services"
        }
    ],
    "sg:phone":"+61 8 8349 4011",
    "sg:postcode":"5013",
    "sg:province":"SA",
    "sg:tags":[
        "window",
        "timber"
    ],
    "wof:name":"Gordon M F & Co Pty Ltd",
    "wof:placetype":"venue"
},
  "geometry": {"coordinates":[138.58062744099999,-34.8410072327],"type":"Point"}
}