{
  "type": "Feature",
  "properties": {
    "iso:country":"AU",
    "sg:address":"Maranoa Rd",
    "sg:city":"Kingston",
    "sg:classifiers":[
        {
            "category":"Health Services",
            "subcategory":"Doctor",
            "type":"Services"
        }
    ],
    "sg:phone":"+61 409 219 650",
    "sg:postcode":"7050",
    "sg:province":"TAS",
    "sg:tags":[
        "medical",
        "practitioner"
    ],
    "wof:name":"Prasad R",
    "wof:placetype":"venue"
},
  "geometry": {"coordinates":[147.307175,-42.976063],"type":"Point"}
}