{
  "type": "Feature",
  "properties": {
    "iso:country":"AU",
    "sg:address":"Tenancy 1, Escada Bldg 18-26 Main St",
    "sg:city":"Mawson Lakes",
    "sg:classifiers":[
        {
            "category":"Banks & Credit Unions",
            "subcategory":"Bank",
            "type":"Services"
        }
    ],
    "sg:phone":"+61 13 20 32",
    "sg:postcode":"5095",
    "sg:province":"SA",
    "wof:name":"Westpac",
    "wof:placetype":"venue"
},
  "geometry": {"coordinates":[138.617111206,-34.8083992004],"type":"Point"}
}