{
  "type": "Feature",
  "properties": {
    "addr:full":"PO Box 803 Dalby QLD 4405",
    "addr:postcode":"4405",
    "iso:country":"AU",
    "sg:address":"PO Box 803",
    "sg:city":"Dalby",
    "sg:classifiers":[
        {
            "category":"Banks & Credit Unions",
            "subcategory":"Investment Brokerage",
            "type":"Services"
        }
    ],
    "sg:phone":"+61 1300 769 775",
    "sg:postcode":"4405",
    "sg:province":"QLD",
    "sg:tags":[
        "debt",
        "collection"
    ],
    "wof:name":"This is Your Office - Debt Collection Division",
    "wof:placetype":"venue"
},
  "geometry": {"coordinates":[151.257415772,-27.1783504486],"type":"Point"}
}