{
  "type": "Feature",
  "properties": {
    "addr:full":"12 French St Wynnum QLD 4178",
    "addr:housenumber":"12",
    "addr:postcode":"4178",
    "addr:street":"French St",
    "iso:country":"AU",
    "sg:address":"12 French St",
    "sg:city":"Wynnum",
    "sg:classifiers":[
        {
            "category":"Utilities",
            "subcategory":"Refuse",
            "type":"Services"
        }
    ],
    "sg:phone":"+61 7 3396 8187",
    "sg:postcode":"4178",
    "sg:province":"QLD",
    "sg:tags":[
        "remover",
        "rubbish"
    ],
    "wof:name":"North Coast Garden Sacks",
    "wof:placetype":"venue"
},
  "geometry": {"coordinates":[153.1612854,-27.438911438],"type":"Point"}
}