{
  "type": "Feature",
  "properties": {
    "addr:full":"PO Box 808 Cotton Tree QLD 4558",
    "addr:postcode":"4558",
    "iso:country":"AU",
    "sg:address":"PO Box 808",
    "sg:city":"Cotton Tree",
    "sg:classifiers":[
        {
            "category":"Professional",
            "subcategory":"Management & Consulting",
            "type":"Services"
        }
    ],
    "sg:phone":"+61 413 441 017",
    "sg:postcode":"4558",
    "sg:province":"QLD",
    "sg:tags":[
        "consultant",
        "business"
    ],
    "wof:name":"Andrew Priestley",
    "wof:placetype":"venue"
},
  "geometry": {"coordinates":[153.098754883,-26.6551895142],"type":"Point"}
}