{
  "type": "Feature",
  "properties": {
    "iso:country":"AU",
    "sg:address":"91 East St",
    "sg:city":"Mt Isa",
    "sg:classifiers":[
        {
            "category":"Professional",
            "subcategory":"Business Services",
            "type":"Services"
        }
    ],
    "sg:phone":"+61 407 024 346",
    "sg:postcode":"4825",
    "sg:province":"QLD",
    "sg:tags":[
        "livestock",
        "transport"
    ],
    "wof:name":"Abdys Stock Haulage",
    "wof:placetype":"venue"
},
  "geometry": {"coordinates":[139.501846,-20.728346],"type":"Point"}
}