{
  "type": "Feature",
  "properties": {
    "addr:full":"305 View St Bendigo VIC 3550",
    "addr:housenumber":"305",
    "addr:postcode":"3550",
    "addr:street":"View St",
    "iso:country":"AU",
    "sg:address":"305 View St",
    "sg:city":"Bendigo",
    "sg:classifiers":[
        {
            "category":"Food & Beverages",
            "subcategory":"Groceries & Convenience Stores",
            "type":"Retail Goods"
        }
    ],
    "sg:phone":"+61 3 5443 2116",
    "sg:postcode":"3550",
    "sg:province":"VIC",
    "wof:name":"View Street Milk Bar",
    "wof:placetype":"venue"
},
  "geometry": {"coordinates":[144.27098083499999,-36.7515716553],"type":"Point"}
}