{
  "type": "Feature",
  "properties": {
    "addr:full":"26 Parkside Ave Box Hill VIC 3128",
    "addr:housenumber":"26",
    "addr:postcode":"3128",
    "addr:street":"Parkside Ave",
    "iso:country":"AU",
    "sg:address":"26 Parkside Ave",
    "sg:city":"Box Hill",
    "sg:classifiers":[
        {
            "category":"Building & Trades",
            "subcategory":"Landscaping Services",
            "type":"Services"
        }
    ],
    "sg:phone":"+61 3 9899 4922",
    "sg:postcode":"3128",
    "sg:province":"VIC",
    "sg:tags":[
        "gardener"
    ],
    "wof:name":"Stewart's James Horticultural Service",
    "wof:placetype":"venue"
},
  "geometry": {"coordinates":[145.11924743599999,-37.8258895874],"type":"Point"}
}