{
  "type": "Feature",
  "properties": {
    "addr:full":"The Bakehouse Quarter, 1 George St North Strathfield NSW 2137",
    "addr:housenumber":"1",
    "addr:postcode":"2137",
    "addr:street":"George St",
    "iso:country":"AU",
    "sg:address":"The Bakehouse Quarter, 1 George St",
    "sg:city":"North Strathfield",
    "sg:classifiers":[
        {
            "category":"Shopping",
            "subcategory":"Party Supplies",
            "type":"Retail Goods"
        }
    ],
    "sg:phone":"+61 2 9746 5255",
    "sg:postcode":"2137",
    "sg:province":"NSW",
    "sg:tags":[
        "children's"
    ],
    "wof:name":"Lollipop's Playland & Cafe",
    "wof:placetype":"venue"
},
  "geometry": {"coordinates":[151.08840942399999,-33.8641586304],"type":"Point"}
}