{
  "type": "Feature",
  "properties": {
    "addr:full":"38 Activity St Warwick QLD 4370",
    "addr:housenumber":"38",
    "addr:postcode":"4370",
    "addr:street":"Activity St",
    "iso:country":"AU",
    "sg:address":"38 Activity St",
    "sg:city":"Warwick",
    "sg:classifiers":[
        {
            "category":"Building & Trades",
            "subcategory":"Construction",
            "type":"Services"
        }
    ],
    "sg:phone":"+61 7 4661 8963",
    "sg:postcode":"4370",
    "sg:province":"QLD",
    "sg:tags":[
        "welding"
    ],
    "wof:name":"Inka Industries",
    "wof:placetype":"venue"
},
  "geometry": {"coordinates":[152.03919982900001,-28.2381896973],"type":"Point"}
}