{
  "type": "Feature",
  "properties": {
    "iso:country":"AU",
    "sg:address":"26 Len Shield St",
    "sg:city":"Paget",
    "sg:classifiers":[
        {
            "category":"Professional",
            "subcategory":"Testing Lab",
            "type":"Services"
        }
    ],
    "sg:phone":"+61 7 4952 6826",
    "sg:postcode":"4740",
    "sg:province":"QLD",
    "sg:tags":[
        "soil",
        "investigation"
    ],
    "sg:website":"http://www.iesa.com.au",
    "wof:name":"IESA Pty Ltd",
    "wof:placetype":"venue"
},
  "geometry": {"coordinates":[149.164185,-21.177717],"type":"Point"}
}