{
  "type": "Feature",
  "properties": {
    "addr:full":"Factory B/ 195 Port Hacking Rd Miranda NSW 2228",
    "addr:housenumber":"195",
    "addr:postcode":"2228",
    "addr:street":"Port Hacking Rd",
    "iso:country":"AU",
    "sg:address":"Factory B/ 195 Port Hacking Rd",
    "sg:city":"Miranda",
    "sg:classifiers":[
        {
            "category":"Retail",
            "subcategory":"Storage",
            "type":"Services"
        }
    ],
    "sg:phone":"+61 2 9544 9673",
    "sg:postcode":"2228",
    "sg:province":"NSW",
    "sg:tags":[
        "shelving",
        "system"
    ],
    "wof:name":"Adkent Pty Ltd",
    "wof:placetype":"venue"
},
  "geometry": {"coordinates":[151.10650634800001,-34.0251808167],"type":"Point"}
}