{
  "type": "Feature",
  "properties": {
    "addr:full":"1 Hillside St Springvale VIC 3171",
    "addr:housenumber":"1",
    "addr:postcode":"3171",
    "addr:street":"Hillside St",
    "iso:country":"AU",
    "sg:address":"1 Hillside St",
    "sg:city":"Springvale",
    "sg:classifiers":[
        {
            "category":"Retail",
            "subcategory":"Auto Repair",
            "type":"Services"
        }
    ],
    "sg:phone":"+61 3 9546 9784",
    "sg:postcode":"3171",
    "sg:province":"VIC",
    "sg:tags":[
        "beater",
        "painter",
        "panel"
    ],
    "wof:name":"P B Body Works Pty Ltd",
    "wof:placetype":"venue"
},
  "geometry": {"coordinates":[145.16560363799999,-37.9405975342],"type":"Point"}
}