{
  "type": "Feature",
  "properties": {
    "addr:full":"168 Princes Hwy Arncliffe NSW 2205",
    "addr:housenumber":"168",
    "addr:postcode":"2205",
    "addr:street":"Princes Hwy",
    "iso:country":"AU",
    "sg:address":"168 Princes Hwy",
    "sg:city":"Arncliffe",
    "sg:classifiers":[
        {
            "category":"Education",
            "subcategory":"School",
            "type":"Public Place"
        }
    ],
    "sg:phone":"+61 2 9567 5060",
    "sg:postcode":"2205",
    "sg:province":"NSW",
    "sg:tags":[
        "state",
        "-",
        "nsw"
    ],
    "wof:name":"Arncliffe Public School",
    "wof:placetype":"venue"
},
  "geometry": {"coordinates":[151.14683500000001,-33.940369],"type":"Point"}
}