{
  "type": "Feature",
  "properties": {
    "addr:full":"24 Alice St Caringbah NSW 2229",
    "addr:housenumber":"24",
    "addr:postcode":"2229",
    "addr:street":"Alice St",
    "iso:country":"AU",
    "sg:address":"24 Alice St",
    "sg:city":"Caringbah",
    "sg:classifiers":[
        {
            "category":"Building & Trades",
            "subcategory":"Construction",
            "type":"Services"
        }
    ],
    "sg:phone":"+61 416 230 550",
    "sg:postcode":"2229",
    "sg:province":"NSW",
    "sg:tags":[
        "plasterboard",
        "plasterer",
        "fixer"
    ],
    "wof:name":"Ascent Interiors",
    "wof:placetype":"venue"
},
  "geometry": {"coordinates":[151.118240356,-34.0600891113],"type":"Point"}
}