{
  "type": "Feature",
  "properties": {
    "iso:country":"AU",
    "sg:address":"125 Rockingham Rd",
    "sg:city":"Hamilton Hill",
    "sg:classifiers":[
        {
            "category":"Retail",
            "subcategory":"Auto Repair",
            "type":"Services"
        }
    ],
    "sg:phone":"+61 8 9434 4456",
    "sg:postcode":"6163",
    "sg:province":"WA",
    "sg:tags":[
        "repairer",
        "motor",
        "engineer"
    ],
    "wof:name":"Terry Favazzo Auto Repairs",
    "wof:placetype":"venue"
},
  "geometry": {"coordinates":[115.777496,-32.086662],"type":"Point"}
}