{
  "type": "Feature",
  "properties": {
    "addr:full":"10 Torquay Rd East Devonport TAS 7310",
    "addr:housenumber":"10",
    "addr:postcode":"7310",
    "addr:street":"Torquay Rd",
    "iso:country":"AU",
    "sg:address":"10 Torquay Rd",
    "sg:city":"East Devonport",
    "sg:classifiers":[
        {
            "category":"Retail",
            "subcategory":"Auto Repair",
            "type":"Services"
        }
    ],
    "sg:phone":"+61 3 6427 7122",
    "sg:postcode":"7310",
    "sg:province":"TAS",
    "sg:tags":[
        "body",
        "builder",
        "motor"
    ],
    "wof:name":"Rick's Smash Repairs",
    "wof:placetype":"venue"
},
  "geometry": {"coordinates":[146.37094116200001,-41.1870956421],"type":"Point"}
}