{
  "type": "Feature",
  "properties": {
    "addr:full":"Shop 53- 57 Elizabeth Way Elizabeth SA 5112",
    "addr:housenumber":"shop 53 57",
    "addr:postcode":"5112",
    "addr:street":"Elizabeth Way",
    "iso:country":"AU",
    "sg:address":"Shop 53- 57 Elizabeth Way",
    "sg:city":"Elizabeth",
    "sg:classifiers":[
        {
            "category":"Food & Beverages",
            "subcategory":"Bakery",
            "type":"Retail Goods"
        }
    ],
    "sg:phone":"+61 8 8287 5355",
    "sg:postcode":"5112",
    "sg:province":"SA",
    "sg:tags":[
        "cake",
        "shop",
        "pastry"
    ],
    "wof:name":"Cheesecake Shop The",
    "wof:placetype":"venue"
},
  "geometry": {"coordinates":[138.66494750999999,-34.7187423706],"type":"Point"}
}