{
  "type": "Feature",
  "properties": {
    "addr:full":"5-7 Temple Drv Thomastown VIC 3074",
    "addr:housenumber":"5-7",
    "addr:postcode":"3074",
    "addr:street":"Temple Drv",
    "iso:country":"AU",
    "sg:address":"5-7 Temple Drv",
    "sg:city":"Thomastown",
    "sg:classifiers":[
        {
            "category":"Organizations",
            "subcategory":"Labor Organization",
            "type":"Services"
        }
    ],
    "sg:phone":"+61 3 9466 1666",
    "sg:postcode":"3074",
    "sg:province":"VIC",
    "sg:tags":[
        "dust",
        "fume",
        "control",
        "equipment"
    ],
    "wof:name":"HNS Fume & Dust Control Pty Ltd",
    "wof:placetype":"venue"
},
  "geometry": {"coordinates":[145.019699097,-37.6893882751],"type":"Point"}
}