{
  "type": "Feature",
  "properties": {
    "addr:full":"Shop 1 Melba Crt Melba ACT 2615",
    "addr:housenumber":"shop 1",
    "addr:postcode":"2615",
    "addr:street":"Melba Crt",
    "iso:country":"AU",
    "sg:address":"Shop 1 Melba Crt",
    "sg:city":"Melba",
    "sg:classifiers":[
        {
            "category":"Personal",
            "subcategory":"Beauty Salon",
            "type":"Services"
        }
    ],
    "sg:phone":"+61 2 6258 0303",
    "sg:postcode":"2615",
    "sg:province":"ACT",
    "sg:tags":[
        "hairdresser"
    ],
    "wof:name":"Beyond The Cutting Line",
    "wof:placetype":"venue"
},
  "geometry": {"coordinates":[149.048919678,-35.2080726624],"type":"Point"}
}