{
  "type": "Feature",
  "properties": {
    "addr:full":"1/ 31- 33 Dover Drv Burleigh Heads QLD 4220",
    "addr:housenumber":"/;33",
    "addr:postcode":"4220",
    "addr:street":"31;Dover Drv",
    "iso:country":"AU",
    "sg:address":"1/ 31- 33 Dover Drv",
    "sg:city":"Burleigh Heads",
    "sg:classifiers":[
        {
            "category":"Building & Trades",
            "subcategory":"Plumbing",
            "type":"Services"
        }
    ],
    "sg:phone":"+61 7 5520 3219",
    "sg:postcode":"4220",
    "sg:province":"QLD",
    "sg:tags":[
        "pump",
        "repairer"
    ],
    "wof:name":"Complete Pump & Chlorinator Repairs",
    "wof:placetype":"venue"
},
  "geometry": {"coordinates":[153.42675781200001,-28.1041812897],"type":"Point"}
}