{
  "type": "Feature",
  "properties": {
    "iso:country":"AU",
    "sg:address":"12 Crofts Crs",
    "sg:city":"Spence",
    "sg:classifiers":[
        {
            "category":"Building & Trades",
            "subcategory":"Landscaping Services",
            "type":"Services"
        }
    ],
    "sg:phone":"+61 2 6294 3939",
    "sg:postcode":"2615",
    "sg:province":"ACT",
    "sg:tags":[
        "designer",
        "landscape",
        "contractor"
    ],
    "wof:name":"Unique Landscaping",
    "wof:placetype":"venue"
},
  "geometry": {"coordinates":[149.06117248499999,-35.1970100403],"type":"Point"}
}