{
  "type": "Feature",
  "properties": {
    "addr:full":"663 Pemberton St Albury NSW 2640",
    "addr:housenumber":"663",
    "addr:postcode":"2640",
    "addr:street":"Pemberton St",
    "iso:country":"AU",
    "sg:address":"663 Pemberton St",
    "sg:city":"Albury",
    "sg:classifiers":[
        {
            "category":"Health Services",
            "subcategory":"Dentist",
            "type":"Services"
        }
    ],
    "sg:phone":"+61 2 6021 3777",
    "sg:postcode":"2640",
    "sg:province":"NSW",
    "wof:name":"Dr Geoff Ross",
    "wof:placetype":"venue"
},
  "geometry": {"coordinates":[146.889694214,-36.0733261108],"type":"Point"}
}