{
  "type": "Feature",
  "properties": {
    "addr:full":"21 Alexander St Manly NSW 2095",
    "addr:housenumber":"21",
    "addr:postcode":"2095",
    "addr:street":"Alexander St",
    "iso:country":"AU",
    "sg:address":"21 Alexander St",
    "sg:city":"Manly",
    "sg:classifiers":[
        {
            "category":"Organizations",
            "subcategory":"Professional Association",
            "type":"Services"
        }
    ],
    "sg:phone":"+61 2 9977 7494",
    "sg:postcode":"2095",
    "sg:province":"NSW",
    "sg:tags":[
        "web",
        "internet"
    ],
    "wof:name":"Web Mechanic",
    "wof:placetype":"venue"
},
  "geometry": {"coordinates":[151.28279113799999,-33.7889671326],"type":"Point"}
}