{
  "type": "Feature",
  "properties": {
    "addr:full":"409 Bong Bong St Bowral NSW 2576",
    "addr:housenumber":"409",
    "addr:postcode":"2576",
    "addr:street":"Bong Bong St",
    "iso:country":"AU",
    "sg:address":"409 Bong Bong St",
    "sg:city":"Bowral",
    "sg:classifiers":[
        {
            "category":"Building & Trades",
            "subcategory":"Pest Control",
            "type":"Services"
        }
    ],
    "sg:phone":"+61 2 4861 2422",
    "sg:postcode":"2576",
    "sg:province":"NSW",
    "wof:name":"Southern Highlands Pest Control",
    "wof:placetype":"venue"
},
  "geometry": {"coordinates":[150.41699218799999,-34.4822883606],"type":"Point"}
}