{
  "type": "Feature",
  "properties": {
    "addr:full":"62 Churchill Rd North Dry Creek SA 5094",
    "addr:housenumber":"62",
    "addr:postcode":"5094",
    "addr:street":"Churchill Rd North Dry",
    "iso:country":"AU",
    "sg:address":"62 Churchill Rd North",
    "sg:city":"Dry Creek",
    "sg:classifiers":[
        {
            "category":"Building & Trades",
            "subcategory":"Construction",
            "type":"Services"
        }
    ],
    "sg:phone":"+61 8 8260 5002",
    "sg:postcode":"5094",
    "sg:province":"SA",
    "sg:tags":[
        "earth",
        "excavating",
        "moving",
        "contractor"
    ],
    "wof:name":"Mollison & Co. Pty Ltd",
    "wof:placetype":"venue"
},
  "geometry": {"coordinates":[138.588256836,-34.8364295959],"type":"Point"}
}