{
  "type": "Feature",
  "properties": {
    "iso:country":"AU",
    "sg:address":"53 Reserve Drv",
    "sg:city":"Mandurah",
    "sg:classifiers":[
        {
            "category":"Home & Garden",
            "subcategory":"Building Materials",
            "type":"Retail Goods"
        }
    ],
    "sg:phone":"+61 8 9581 7611",
    "sg:postcode":"6210",
    "sg:province":"WA",
    "sg:tags":[
        "retaining",
        "wall"
    ],
    "wof:name":"Archistone",
    "wof:placetype":"venue"
},
  "geometry": {"coordinates":[115.742027,-32.514465],"type":"Point"}
}