{
  "type": "Feature",
  "properties": {
    "addr:full":"Lot 1 Southgate Industrial Estate Pacific Highway C NSW 2450",
    "addr:postcode":"2450",
    "addr:street":"Pacific Highway C",
    "iso:country":"AU",
    "sg:address":"Lot 1",
    "sg:city":"Southgate Industrial Estate Pacific Highway C",
    "sg:classifiers":[
        {
            "category":"Wholesale",
            "subcategory":"Scrap",
            "type":"Manufacturing & Wholesale Goods"
        }
    ],
    "sg:phone":"+61 2 6652 1709",
    "sg:postcode":"2450",
    "sg:province":"NSW",
    "sg:tags":[
        "merchant",
        "metal"
    ],
    "wof:name":"Smorgonsteel Recycling",
    "wof:placetype":"venue"
},
  "geometry": {"coordinates":[153.114304,-30.295885],"type":"Point"}
}