{
  "type": "Feature",
  "properties": {
    "addr:full":"Cnr Frederick Rd & Wilson St Royal Park SA 5014",
    "addr:postcode":"5014",
    "addr:street":"Cnr Frederick Rd & Wilson St",
    "iso:country":"AU",
    "sg:address":"Cnr Frederick Rd & Wilson St",
    "sg:city":"Royal Park",
    "sg:classifiers":[
        {
            "category":"Home & Garden",
            "subcategory":"Hardware",
            "type":"Retail Goods"
        }
    ],
    "sg:phone":"+61 8 8341 0008",
    "sg:postcode":"5014",
    "sg:province":"SA",
    "sg:tags":[
        "pipe",
        "fitting",
        "plastic"
    ],
    "wof:name":"H-R Poly Fittings",
    "wof:placetype":"venue"
},
  "geometry": {"coordinates":[138.502883911,-34.8685913086],"type":"Point"}
}