{
  "type": "Feature",
  "properties": {
    "iso:country":"AU",
    "sg:address":"44 Atherton Rd",
    "sg:city":"Oakleigh",
    "sg:classifiers":[
        {
            "category":"Banks & Credit Unions",
            "subcategory":"Bank",
            "type":"Services"
        }
    ],
    "sg:phone":"+61 13 25 75",
    "sg:postcode":"3166",
    "sg:province":"VIC",
    "wof:name":"Bank Of Melbourne",
    "wof:placetype":"venue"
},
  "geometry": {"coordinates":[145.09158325199999,-37.8990287781],"type":"Point"}
}