{
  "type": "Feature",
  "properties": {
    "iso:country":"AU",
    "sg:address":"1338 Etiwanda Ave",
    "sg:city":"Mildura",
    "sg:classifiers":[
        {
            "category":"Home & Garden",
            "subcategory":"Building Materials",
            "type":"Retail Goods"
        }
    ],
    "sg:phone":"+61 418 303 863",
    "sg:postcode":"3500",
    "sg:province":"VIC",
    "sg:tags":[
        "lawn",
        "cutting",
        "maintenance"
    ],
    "wof:name":"Brents Lawn Mowing & Gardening Services",
    "wof:placetype":"venue"
},
  "geometry": {"coordinates":[142.16067504899999,-34.2033615112],"type":"Point"}
}