{
  "type": "Feature",
  "properties": {
    "iso:country":"AU",
    "sg:address":"Level 1, 16 Edmondstone St",
    "sg:city":"Newmarket",
    "sg:classifiers":[
        {
            "category":"Professional",
            "subcategory":"Computer Services",
            "type":"Services"
        }
    ],
    "sg:phone":"+61 7 3356 4377",
    "sg:postcode":"4051",
    "sg:province":"QLD",
    "sg:tags":[
        "consultant",
        "system"
    ],
    "wof:name":"Qtech Business Systems",
    "wof:placetype":"venue"
},
  "geometry": {"coordinates":[153.008346558,-27.4378318787],"type":"Point"}
}