{
  "type": "Feature",
  "properties": {
    "addr:full":"765 Princes Hwy Tempe NSW 2044",
    "addr:housenumber":"765",
    "addr:postcode":"2044",
    "addr:street":"Princes Hwy",
    "iso:country":"AU",
    "sg:address":"765 Princes Hwy",
    "sg:city":"Tempe",
    "sg:classifiers":[
        {
            "category":"Train Station",
            "subcategory":"Light Rail",
            "type":"Transportation"
        }
    ],
    "sg:phone":"+61 2 9557 6657",
    "sg:postcode":"2044",
    "sg:province":"NSW",
    "sg:tags":[
        "equipment",
        "energy",
        "solar"
    ],
    "wof:name":"PV Solar Tiles",
    "wof:placetype":"venue"
},
  "geometry": {"coordinates":[151.160416,-33.924896],"type":"Point"}
}