{
  "type": "Feature",
  "properties": {
    "iso:country":"AU",
    "sg:address":"Fcty8/ 43 Vinter Ave",
    "sg:city":"Croydon",
    "sg:classifiers":[
        {
            "category":"Building & Trades",
            "subcategory":"Construction",
            "type":"Services"
        }
    ],
    "sg:phone":"+61 3 9725 8999",
    "sg:postcode":"3136",
    "sg:province":"VIC",
    "sg:tags":[
        "spouting",
        "guttering"
    ],
    "wof:name":"The Leaf Man",
    "wof:placetype":"venue"
},
  "geometry": {"coordinates":[145.27821350100001,-37.8058280945],"type":"Point"}
}