{
  "type": "Feature",
  "properties": {
    "iso:country":"AU",
    "sg:address":"Shp1/ 175 Hume Hwy",
    "sg:city":"Lansvale",
    "sg:classifiers":[
        {
            "category":"Home & Garden",
            "subcategory":"Household Appliances",
            "type":"Retail Goods"
        }
    ],
    "sg:phone":"+61 2 9727 3997",
    "sg:postcode":"2166",
    "sg:province":"NSW",
    "sg:tags":[
        "wholesale",
        "mfrs",
        "air conditioning"
    ],
    "wof:name":"Integral Electrical Wholesalers",
    "wof:placetype":"venue"
},
  "geometry": {"coordinates":[150.95549011200001,-33.8953552246],"type":"Point"}
}