{
  "type": "Feature",
  "properties": {
    "addr:full":"140 Raglan St Preston VIC 3072",
    "addr:housenumber":"140",
    "addr:postcode":"3072",
    "addr:street":"Raglan St",
    "iso:country":"AU",
    "sg:address":"140 Raglan St",
    "sg:city":"Preston",
    "sg:classifiers":[
        {
            "category":"Retail",
            "subcategory":"Laundry & Dry Cleaning",
            "type":"Services"
        }
    ],
    "sg:phone":"+61 3 9484 3378",
    "sg:postcode":"3072",
    "sg:province":"VIC",
    "sg:tags":[
        "ironing"
    ],
    "wof:name":"G Y Fashions",
    "wof:placetype":"venue"
},
  "geometry": {"coordinates":[145.01461792000001,-37.7500915527],"type":"Point"}
}