{
  "type": "Feature",
  "properties": {
    "iso:country":"AU",
    "sg:address":"Suite 207b/ 414 Gardeners Rd",
    "sg:city":"Rosebery",
    "sg:classifiers":[
        {
            "category":"Transit Center",
            "subcategory":"Freight",
            "type":"Transportation"
        }
    ],
    "sg:phone":"+61 2 9667 3365",
    "sg:postcode":"2018",
    "sg:province":"NSW",
    "sg:tags":[
        "agent",
        "shipping"
    ],
    "wof:name":"Keenway International Pty Ltd",
    "wof:placetype":"venue"
},
  "geometry": {"coordinates":[151.19926452600001,-33.9217033386],"type":"Point"}
}