{
  "type": "Feature",
  "properties": {
    "addr:full":"Suite 1/ 139 Alexander St Crows Nest NSW 2065",
    "addr:housenumber":"/ 139",
    "addr:postcode":"2065",
    "addr:street":"Alexander St",
    "iso:country":"AU",
    "sg:address":"Suite 1/ 139 Alexander St",
    "sg:city":"Crows Nest",
    "sg:classifiers":[
        {
            "category":"Personal",
            "subcategory":"Beauty Salon",
            "type":"Services"
        }
    ],
    "sg:phone":"+61 2 9436 0478",
    "sg:postcode":"2065",
    "sg:province":"NSW",
    "wof:name":"A Touch Of Natural Beauty Clinic Specialising in Ageing Treatments",
    "wof:placetype":"venue"
},
  "geometry": {"coordinates":[151.20291137699999,-33.8240013123],"type":"Point"}
}