{
  "type": "Feature",
  "properties": {
    "addr:full":"290- 292 Maroondah Hwy Ringwood VIC 3134",
    "addr:housenumber":"292",
    "addr:postcode":"3134",
    "addr:street":"Maroondah Hwy",
    "iso:country":"AU",
    "sg:address":"290- 292 Maroondah Hwy",
    "sg:city":"Ringwood",
    "sg:classifiers":[
        {
            "category":"Social Services",
            "subcategory":"Child Care",
            "type":"Services"
        }
    ],
    "sg:phone":"+61 3 9870 0660",
    "sg:postcode":"3134",
    "sg:province":"VIC",
    "wof:name":"ABC Learning Centres",
    "wof:placetype":"venue"
},
  "geometry": {"coordinates":[145.24020385700001,-37.8090820312],"type":"Point"}
}