{
  "type": "Feature",
  "properties": {
    "iso:country":"AU",
    "sg:address":"14 Leeds St",
    "sg:city":"Rocklea",
    "sg:classifiers":[
        {
            "category":"Professional",
            "subcategory":"Engineering",
            "type":"Services"
        }
    ],
    "sg:phone":"+61 7 3277 4199",
    "sg:postcode":"4106",
    "sg:province":"QLD",
    "sg:tags":[
        "refrigeration",
        "engineer"
    ],
    "wof:name":"Dewar Bruce",
    "wof:placetype":"venue"
},
  "geometry": {"coordinates":[153.01660156200001,-27.5484790802],"type":"Point"}
}