{
  "type": "Feature",
  "properties": {
    "addr:full":"13 - 19 Goldsmith St Goulburn NSW 2580",
    "addr:housenumber":"19",
    "addr:postcode":"2580",
    "addr:street":"Goldsmith St",
    "iso:country":"AU",
    "sg:address":"13 - 19 Goldsmith St",
    "sg:city":"Goulburn",
    "sg:classifiers":[
        {
            "category":"Autos & Motor Vehicles",
            "subcategory":"Auto Supplies",
            "type":"Retail Goods"
        }
    ],
    "sg:phone":"+61 13 61 30",
    "sg:postcode":"2580",
    "sg:province":"NSW",
    "sg:tags":[
        "battery",
        "automotive"
    ],
    "wof:name":"Marshall Batteries",
    "wof:placetype":"venue"
},
  "geometry": {"coordinates":[149.718139648,-34.7586708069],"type":"Point"}
}