{
  "type": "Feature",
  "properties": {
    "addr:full":"199 Campbell St Hobart TAS 7000",
    "addr:housenumber":"199",
    "addr:postcode":"7000",
    "addr:street":"Campbell St",
    "iso:country":"AU",
    "sg:address":"199 Campbell St",
    "sg:city":"Hobart",
    "sg:classifiers":[
        {
            "category":"Shopping",
            "subcategory":"Computers & Home Electronics",
            "type":"Retail Goods"
        }
    ],
    "sg:phone":"+61 3 6231 5173",
    "sg:postcode":"7000",
    "sg:province":"TAS",
    "sg:tags":[
        "hardware",
        "equipment"
    ],
    "wof:name":"Micro-Tech",
    "wof:placetype":"venue"
},
  "geometry": {"coordinates":[147.323486328,-42.8742980957],"type":"Point"}
}