{
  "type": "Feature",
  "properties": {
    "iso:country":"AU",
    "sg:address":"66 Newton Rd",
    "sg:city":"Strathfield",
    "sg:classifiers":[
        {
            "category":"Real Estate",
            "subcategory":"Real Estate Services",
            "type":"Services"
        }
    ],
    "sg:phone":"+61 2 9746 8100",
    "sg:postcode":"2135",
    "sg:province":"NSW",
    "sg:tags":[
        "valuer"
    ],
    "wof:name":"Austin P.J. Valuation",
    "wof:placetype":"venue"
},
  "geometry": {"coordinates":[151.07322692899999,-33.8778572083],"type":"Point"}
}