{
  "type": "Feature",
  "properties": {
    "addr:full":"40 Elizabeth Ave South Golden Beach NSW 2483",
    "addr:housenumber":"40",
    "addr:postcode":"2483",
    "addr:street":"Elizabeth Ave South",
    "iso:country":"AU",
    "sg:address":"40 Elizabeth Ave",
    "sg:city":"South Golden Beach",
    "sg:classifiers":[
        {
            "category":"Banks & Credit Unions",
            "subcategory":"Bureau De Change",
            "type":"Services"
        }
    ],
    "sg:phone":"+61 2 6680 4944",
    "sg:postcode":"2483",
    "sg:province":"NSW",
    "sg:tags":[
        "archaeology"
    ],
    "wof:name":"Dan Tuck Archaeologist",
    "wof:placetype":"venue"
},
  "geometry": {"coordinates":[153.54408264200001,-28.4945983887],"type":"Point"}
}