{
  "type": "Feature",
  "properties": {
    "iso:country":"AU",
    "sg:address":"Lot 58, Macaulay Rd",
    "sg:city":"Emerald",
    "sg:classifiers":[
        {
            "category":"Building & Trades",
            "subcategory":"Construction",
            "type":"Services"
        }
    ],
    "sg:phone":"+61 7 4987 5744",
    "sg:postcode":"4720",
    "sg:province":"QLD",
    "sg:tags":[
        "earth",
        "excavating",
        "moving",
        "contractor"
    ],
    "wof:name":"Jonker",
    "wof:placetype":"venue"
},
  "geometry": {"coordinates":[148.154465,-23.505688],"type":"Point"}
}