{
  "type": "Feature",
  "properties": {
    "addr:full":"40 Sydney Rd Coburg VIC 3058",
    "addr:housenumber":"40",
    "addr:postcode":"3058",
    "addr:street":"Sydney Rd",
    "iso:country":"AU",
    "sg:address":"40 Sydney Rd",
    "sg:city":"Coburg",
    "sg:classifiers":[
        {
            "category":"Personal",
            "subcategory":"Beauty Salon",
            "type":"Services"
        }
    ],
    "sg:phone":"+61 3 9386 6750",
    "sg:postcode":"3058",
    "sg:province":"VIC",
    "sg:tags":[
        "hairdresser"
    ],
    "wof:name":"Meo Hairdressing",
    "wof:placetype":"venue"
},
  "geometry": {"coordinates":[144.96449279800001,-37.7542495728],"type":"Point"}
}