{
  "type": "Feature",
  "properties": {
    "addr:full":"P.O. Box 92 Bentleigh VIC 3204",
    "addr:postcode":"3204",
    "iso:country":"AU",
    "sg:address":"P.O. Box 92",
    "sg:city":"Bentleigh",
    "sg:classifiers":[
        {
            "category":"Shopping",
            "subcategory":"Optical Goods",
            "type":"Retail Goods"
        }
    ],
    "sg:phone":"+61 3 9557 7664",
    "sg:postcode":"3204",
    "sg:province":"VIC",
    "sg:tags":[
        "supply"
    ],
    "wof:name":"Astronomy &#034;ALIVE&#034;",
    "wof:placetype":"venue"
},
  "geometry": {"coordinates":[145.026962,-37.91193],"type":"Point"}
}