{
  "type": "Feature",
  "properties": {
    "iso:country":"AU",
    "sg:address":"Golf Links Rd",
    "sg:city":"Barwon Heads",
    "sg:classifiers":[
        {
            "category":"Sports & Exercise",
            "subcategory":"Golf",
            "type":"Entertainment"
        }
    ],
    "sg:phone":"+61 3 5254 2321",
    "sg:postcode":"3227",
    "sg:province":"VIC",
    "sg:tags":[
        "club"
    ],
    "wof:name":"Barwon Heads Golf Club Pro Shop",
    "wof:placetype":"venue"
},
  "geometry": {"coordinates":[144.487137,-38.282108],"type":"Point"}
}