{
  "type": "Feature",
  "properties": {
    "addr:full":"Golf Links Rd Barwon Heads VIC 3227",
    "addr:postcode":"3227",
    "addr:street":"Golf Links Rd",
    "iso:country":"AU",
    "sg:address":"Golf Links Rd",
    "sg:city":"Barwon Heads",
    "sg:classifiers":[
        {
            "category":"Sports & Exercise",
            "subcategory":"Golf",
            "type":"Entertainment"
        }
    ],
    "sg:phone":"+61 3 5254 2321",
    "sg:postcode":"3227",
    "sg:province":"VIC",
    "sg:tags":[
        "club"
    ],
    "wof:name":"Barwon Heads Golf Club Pro Shop",
    "wof:placetype":"venue"
},
  "geometry": {"coordinates":[144.48713699999999,-38.282108],"type":"Point"}
}