{
  "type": "Feature",
  "properties": {
    "addr:full":"316 Little Collins St Melbourne VIC 3000",
    "addr:housenumber":"316",
    "addr:postcode":"3000",
    "addr:street":"Little Collins St",
    "iso:country":"AU",
    "sg:address":"316 Little Collins St",
    "sg:city":"Melbourne",
    "sg:classifiers":[
        {
            "category":"Shopping",
            "subcategory":"Clothing, Apparel, & Fashions",
            "type":"Retail Goods"
        }
    ],
    "sg:phone":"+61 3 9650 1461",
    "sg:postcode":"3000",
    "sg:province":"VIC",
    "sg:tags":[
        "menswear"
    ],
    "wof:name":"Suit Box The",
    "wof:placetype":"venue"
},
  "geometry": {"coordinates":[144.964233398,-37.8149108887],"type":"Point"}
}