{
  "type": "Feature",
  "properties": {
    "iso:country":"AU",
    "sg:address":"36 William St",
    "sg:city":"Condobolin",
    "sg:classifiers":[
        {
            "category":"Farming",
            "subcategory":"Fish & Marine Products",
            "type":"Manufacturing & Wholesale Goods"
        }
    ],
    "sg:phone":"+61 2 6895 2288",
    "sg:postcode":"2877",
    "sg:province":"NSW",
    "sg:tags":[
        "chemical",
        "supplier"
    ],
    "wof:name":"Cooney Frank & Son Pty Ltd",
    "wof:placetype":"venue"
},
  "geometry": {"coordinates":[147.148483,-33.082413],"type":"Point"}
}