{
  "type": "Feature",
  "properties": {
    "addr:full":"4 Sirius St Oberon NSW 2787",
    "addr:housenumber":"4",
    "addr:postcode":"2787",
    "addr:street":"Sirius St",
    "iso:country":"AU",
    "sg:address":"4 Sirius St",
    "sg:city":"Oberon",
    "sg:classifiers":[
        {
            "category":"Professional",
            "subcategory":"Engineering",
            "type":"Services"
        }
    ],
    "sg:phone":"+61 2 6336 0810",
    "sg:postcode":"2787",
    "sg:province":"NSW",
    "sg:tags":[
        "engineer"
    ],
    "wof:name":"M.C.F. Engineering Pty Ltd",
    "wof:placetype":"venue"
},
  "geometry": {"coordinates":[149.86247253400001,-33.6988830566],"type":"Point"}
}