{
  "type": "Feature",
  "properties": {
    "iso:country":"AU",
    "sg:address":"100 Mallett St",
    "sg:city":"Newtown",
    "sg:classifiers":[
        {
            "category":"Health Services",
            "subcategory":"Doctor",
            "type":"Services"
        }
    ],
    "sg:phone":"+61 2 9972 9000",
    "sg:postcode":"2042",
    "sg:province":"NSW",
    "sg:tags":[
        "medical",
        "practitioner"
    ],
    "wof:name":"Frith J A Dr",
    "wof:placetype":"venue"
},
  "geometry": {"coordinates":[151.177673,-33.889069],"type":"Point"}
}