{
  "type": "Feature",
  "properties": {
    "addr:full":"Lot 3 Fifty One Rd Cowaramup WA 6284",
    "addr:postcode":"6284",
    "addr:street":"Rd",
    "iso:country":"AU",
    "sg:address":"Lot 3 Fifty One Rd",
    "sg:city":"Cowaramup",
    "sg:classifiers":[
        {
            "category":"Farming",
            "subcategory":"Vineyard",
            "type":"Manufacturing & Wholesale Goods"
        }
    ],
    "sg:phone":"+61 8 9755 5669",
    "sg:postcode":"6284",
    "sg:province":"WA",
    "sg:tags":[
        "winery"
    ],
    "wof:name":"Cape Grace Wines",
    "wof:placetype":"venue"
},
  "geometry": {"coordinates":[115.053871155,-33.8460235596],"type":"Point"}
}