{
  "type": "Feature",
  "properties": {
    "addr:full":"PO Box 54 Ormeau QLD 4208",
    "addr:postcode":"4208",
    "iso:country":"AU",
    "sg:address":"PO Box 54",
    "sg:city":"Ormeau",
    "sg:classifiers":[
        {
            "category":"Shopping",
            "subcategory":"Computers & Home Electronics",
            "type":"Retail Goods"
        }
    ],
    "sg:phone":"+61 407 388 453",
    "sg:postcode":"4208",
    "sg:province":"QLD",
    "sg:tags":[
        "hardware",
        "equipment"
    ],
    "wof:name":"Virtutech",
    "wof:placetype":"venue"
},
  "geometry": {"coordinates":[153.244216919,-27.7652397156],"type":"Point"}
}