{
  "type": "Feature",
  "properties": {
    "addr:full":"Suite 20, Pacific Centre (AAPT) Block A, 223 Calam Road Calam Rd Sunnybank Hills QLD 4109",
    "addr:housenumber":"block a 223",
    "addr:postcode":"4109",
    "addr:street":"Calam Road Calam Rd",
    "iso:country":"AU",
    "sg:address":"Suite 20, Pacific Centre (AAPT) Block A, 223 Calam Road Calam Rd",
    "sg:city":"Sunnybank Hills",
    "sg:classifiers":[
        {
            "category":"Health Services",
            "subcategory":"Dentist",
            "type":"Services"
        }
    ],
    "sg:phone":"+61 7 3276 1066",
    "sg:postcode":"4109",
    "sg:province":"QLD",
    "wof:name":"Dr P.Y. Lai Dental",
    "wof:placetype":"venue"
},
  "geometry": {"coordinates":[153.054397583,-27.609708786],"type":"Point"}
}