{
  "type": "Feature",
  "properties": {
    "addr:full":"42 Grey St Belgrave VIC 3160",
    "addr:housenumber":"42",
    "addr:postcode":"3160",
    "addr:street":"Grey St",
    "iso:country":"AU",
    "sg:address":"42 Grey St",
    "sg:city":"Belgrave",
    "sg:classifiers":[
        {
            "category":"Professional",
            "subcategory":"Detective & Security Services",
            "type":"Services"
        }
    ],
    "sg:phone":"+61 3 9752 6867",
    "sg:postcode":"3160",
    "sg:province":"VIC",
    "sg:tags":[
        "equipment",
        "window",
        "doors"
    ],
    "wof:name":"Fast Mobile Screens & Doors",
    "wof:placetype":"venue"
},
  "geometry": {"coordinates":[145.347930908,-37.9125976562],"type":"Point"}
}