{
  "type": "Feature",
  "properties": {
    "addr:full":"193 Bourke St Melbourne VIC 3000",
    "addr:housenumber":"193",
    "addr:postcode":"3000",
    "addr:street":"Bourke St",
    "iso:country":"AU",
    "sg:address":"193 Bourke St",
    "sg:city":"Melbourne",
    "sg:classifiers":[
        {
            "category":"Shopping",
            "subcategory":"Optical Goods",
            "type":"Retail Goods"
        }
    ],
    "sg:phone":"+61 1800 683 325",
    "sg:postcode":"3000",
    "sg:province":"VIC",
    "sg:tags":[
        "dispenser",
        "prescription"
    ],
    "wof:name":"Nudeal Contact Lens",
    "wof:placetype":"venue"
},
  "geometry": {"coordinates":[144.96763610799999,-37.8130722046],"type":"Point"}
}