{
  "type": "Feature",
  "properties": {
    "addr:full":"42 Sixth Ave Chelsea Heights VIC 3196",
    "addr:housenumber":"42",
    "addr:postcode":"3196",
    "addr:street":"Sixth Ave",
    "iso:country":"AU",
    "sg:address":"42 Sixth Ave",
    "sg:city":"Chelsea Heights",
    "sg:classifiers":[
        {
            "category":"Building & Trades",
            "subcategory":"Construction",
            "type":"Services"
        }
    ],
    "sg:phone":"+61 3 9773 1925",
    "sg:postcode":"3196",
    "sg:province":"VIC",
    "sg:tags":[
        "earth",
        "excavating",
        "moving",
        "contractor"
    ],
    "wof:name":"Chelsea Excavations",
    "wof:placetype":"venue"
},
  "geometry": {"coordinates":[145.136260986,-38.0416069031],"type":"Point"}
}