{
  "type": "Feature",
  "properties": {
    "addr:full":"414 Sydney Rd Balgowlah NSW 2093",
    "addr:housenumber":"414",
    "addr:postcode":"2093",
    "addr:street":"Sydney Rd",
    "iso:country":"AU",
    "sg:address":"414 Sydney Rd",
    "sg:city":"Balgowlah",
    "sg:classifiers":[
        {
            "category":"Health Services",
            "subcategory":"Dentist",
            "type":"Services"
        }
    ],
    "sg:phone":"+61 2 9948 8643",
    "sg:postcode":"2093",
    "sg:province":"NSW",
    "wof:name":"Wholistic Dentalhealth Care",
    "wof:placetype":"venue"
},
  "geometry": {"coordinates":[151.26185607900001,-33.7938232422],"type":"Point"}
}