{
  "type": "Feature",
  "properties": {
    "addr:full":"56- 58 Power St St Marys NSW 2760",
    "addr:housenumber":"58",
    "addr:postcode":"2760",
    "addr:street":"Power St",
    "iso:country":"AU",
    "sg:address":"56- 58 Power St",
    "sg:city":"St Marys",
    "sg:classifiers":[
        {
            "category":"Manufacturing",
            "subcategory":"Building Materials",
            "type":"Manufacturing & Wholesale Goods"
        }
    ],
    "sg:phone":"+61 1800 643 911",
    "sg:postcode":"2760",
    "sg:province":"NSW",
    "sg:tags":[
        "equipment",
        "handling"
    ],
    "wof:name":"Cevol Industries Pty Ltd",
    "wof:placetype":"venue"
},
  "geometry": {"coordinates":[150.77340698200001,-33.7554283142],"type":"Point"}
}