{
  "type": "Feature",
  "properties": {
    "addr:full":"74 Cressbrook Drv Albany Creek QLD 4035",
    "addr:housenumber":"74",
    "addr:postcode":"4035",
    "addr:street":"Cressbrook Drv",
    "iso:country":"AU",
    "sg:address":"74 Cressbrook Drv",
    "sg:city":"Albany Creek",
    "sg:classifiers":[
        {
            "category":"Building & Trades",
            "subcategory":"Construction",
            "type":"Services"
        }
    ],
    "sg:phone":"+61 7 3325 2690",
    "sg:postcode":"4035",
    "sg:province":"QLD",
    "sg:tags":[
        "contractor"
    ],
    "wof:name":"Proper Homes Pty Ltd",
    "wof:placetype":"venue"
},
  "geometry": {"coordinates":[152.95230100000001,-27.353188],"type":"Point"}
}