{
  "type": "Feature",
  "properties": {
    "addr:full":"91 Koloona Ave Mt Keira NSW 2500",
    "addr:housenumber":"91",
    "addr:postcode":"2500",
    "addr:street":"Koloona Ave",
    "iso:country":"AU",
    "sg:address":"91 Koloona Ave",
    "sg:city":"Mt Keira",
    "sg:classifiers":[
        {
            "category":"Building & Trades",
            "subcategory":"Construction",
            "type":"Services"
        }
    ],
    "sg:phone":"+61 2 4226 2973",
    "sg:postcode":"2500",
    "sg:province":"NSW",
    "sg:tags":[
        "contractor"
    ],
    "wof:name":"Charman Constructions",
    "wof:placetype":"venue"
},
  "geometry": {"coordinates":[150.85562100000001,-34.417442],"type":"Point"}
}