{
  "type": "Feature",
  "properties": {
    "iso:country":"AU",
    "sg:address":"PO Box 369",
    "sg:city":"Seaford",
    "sg:classifiers":[
        {
            "category":"Military Area",
            "subcategory":"Air Force Base",
            "type":"Public Place"
        }
    ],
    "sg:phone":"+61 3 9775 3223",
    "sg:postcode":"3198",
    "sg:province":"VIC",
    "sg:tags":[
        "adjuster",
        "compass"
    ],
    "wof:name":"Compass Adjuster",
    "wof:placetype":"venue"
},
  "geometry": {"coordinates":[145.14215087900001,-38.1062583923],"type":"Point"}
}