{
  "type": "Feature",
  "properties": {
    "addr:full":"Cnr Newbridge Rd & Journeyman Cl Berkeley Vale NSW 2261",
    "addr:postcode":"2261",
    "addr:street":"Cnr Newbridge Rd & Journeyman Cl",
    "iso:country":"AU",
    "sg:address":"Cnr Newbridge Rd & Journeyman Cl",
    "sg:city":"Berkeley Vale",
    "sg:classifiers":[
        {
            "category":"Professional",
            "subcategory":"Engineering",
            "type":"Services"
        }
    ],
    "sg:phone":"+61 2 4389 1314",
    "sg:postcode":"2261",
    "sg:province":"NSW",
    "sg:tags":[
        "manufacturing",
        "engineer"
    ],
    "wof:name":"Christensen Engineering Australia Pty Ltd",
    "wof:placetype":"venue"
},
  "geometry": {"coordinates":[151.424316,-33.324512],"type":"Point"}
}