{
  "type": "Feature",
  "properties": {
    "addr:full":"11 Martin St Ballina NSW 2478",
    "addr:housenumber":"11",
    "addr:postcode":"2478",
    "addr:street":"Martin St",
    "iso:country":"AU",
    "sg:address":"11 Martin St",
    "sg:city":"Ballina",
    "sg:classifiers":[
        {
            "category":"Health Services",
            "subcategory":"Health Practitioner",
            "type":"Services"
        }
    ],
    "sg:phone":"+61 2 6686 4555",
    "sg:postcode":"2478",
    "sg:province":"NSW",
    "sg:tags":[
        "physiotherapist"
    ],
    "wof:name":"Ballina Pacific Sports & Spinal Physiotherapy Pty Ltd",
    "wof:placetype":"venue"
},
  "geometry": {"coordinates":[153.564056397,-28.8709812164],"type":"Point"}
}