{
  "type": "Feature",
  "properties": {
    "addr:full":"2 Domain Drv Berwick VIC 3806",
    "addr:housenumber":"2",
    "addr:postcode":"3806",
    "addr:street":"Domain Drv",
    "iso:country":"AU",
    "sg:address":"2 Domain Drv",
    "sg:city":"Berwick",
    "sg:classifiers":[
        {
            "category":"Professional",
            "type":"Services"
        }
    ],
    "sg:phone":"+61 418 545 598",
    "sg:postcode":"3806",
    "sg:province":"VIC",
    "sg:tags":[
        "transport"
    ],
    "wof:name":"G & Y Rowley Transport",
    "wof:placetype":"venue"
},
  "geometry": {"coordinates":[145.32986450199999,-38.0553436279],"type":"Point"}
}