{
  "type": "Feature",
  "properties": {
    "addr:full":"105 Riversdale Rd Hawthorn VIC 3122",
    "addr:housenumber":"105",
    "addr:postcode":"3122",
    "addr:street":"Riversdale Rd",
    "iso:country":"AU",
    "sg:address":"105 Riversdale Rd",
    "sg:city":"Hawthorn",
    "sg:classifiers":[
        {
            "category":"Health Services",
            "subcategory":"Doctor",
            "type":"Services"
        }
    ],
    "sg:phone":"+61 3 9818 3233",
    "sg:postcode":"3122",
    "sg:province":"VIC",
    "sg:tags":[
        "occupational",
        "safety"
    ],
    "wof:name":"Company Medical Services",
    "wof:placetype":"venue"
},
  "geometry": {"coordinates":[145.03489685100001,-37.8286476135],"type":"Point"}
}