{
  "type": "Feature",
  "properties": {
    "addr:full":"Cnr Belmont Ave & Kenwick Rd Kenwick WA 6107",
    "addr:postcode":"6107",
    "addr:street":"Cnr Belmont Ave & Kenwick Rd",
    "iso:country":"AU",
    "sg:address":"Cnr Belmont Ave & Kenwick Rd",
    "sg:city":"Kenwick",
    "sg:classifiers":[
        {
            "category":"Fast Food",
            "type":"Food & Drink"
        }
    ],
    "sg:phone":"+61 8 9493 6063",
    "sg:postcode":"6107",
    "sg:province":"WA",
    "sg:tags":[
        "away",
        "take"
    ],
    "wof:name":"Kenwick Village Fish & Chips",
    "wof:placetype":"venue"
},
  "geometry": {"coordinates":[115.973243713,-32.0352058411],"type":"Point"}
}