{
  "type": "Feature",
  "properties": {
    "iso:country":"AU",
    "sg:address":"86 George St",
    "sg:city":"Redfern",
    "sg:classifiers":[
        {
            "category":"Arts & Performance",
            "subcategory":"Art Gallery",
            "type":"Entertainment"
        }
    ],
    "sg:phone":"+61 2 9699 9033",
    "sg:postcode":"2016",
    "sg:province":"NSW",
    "wof:name":"GrantPirrie",
    "wof:placetype":"venue"
},
  "geometry": {"coordinates":[151.20216369600001,-33.8917694092],"type":"Point"}
}