{
  "type": "Feature",
  "properties": {
    "addr:full":"17 Park Drv Sunshine North VIC 3020",
    "addr:housenumber":"17",
    "addr:postcode":"3020",
    "addr:street":"Park Drv",
    "iso:country":"AU",
    "sg:address":"17 Park Drv",
    "sg:city":"Sunshine North",
    "sg:classifiers":[
        {
            "category":"Travel",
            "subcategory":"Hostel",
            "type":"Entertainment"
        }
    ],
    "sg:phone":"+61 3 9310 1000",
    "sg:postcode":"3020",
    "sg:province":"VIC",
    "sg:tags":[
        "home"
    ],
    "wof:name":"St Bernadette's Aged Care Facility",
    "wof:placetype":"venue"
},
  "geometry": {"coordinates":[144.825684,-37.759632],"type":"Point"}
}