{
  "type": "Feature",
  "properties": {
    "addr:full":"Jaffrays Rd Wallacedale VIC 3303",
    "addr:postcode":"3303",
    "addr:street":"Jaffrays Rd",
    "iso:country":"AU",
    "sg:address":"Jaffrays Rd",
    "sg:city":"Wallacedale",
    "sg:classifiers":[
        {
            "category":"Building & Trades",
            "subcategory":"Construction",
            "type":"Services"
        }
    ],
    "sg:phone":"+61 417 355 962",
    "sg:postcode":"3303",
    "sg:province":"VIC",
    "sg:tags":[
        "fencing",
        "contractor"
    ],
    "wof:name":"Charcdale Fencing Contractors",
    "wof:placetype":"venue"
},
  "geometry": {"coordinates":[141.79804992699999,-37.932975769],"type":"Point"}
}