{
  "type": "Feature",
  "properties": {
    "addr:full":"8 Hawley Pl Marangaroo WA 6064",
    "addr:housenumber":"8",
    "addr:postcode":"6064",
    "addr:street":"Hawley Pl Marangaroo",
    "iso:country":"AU",
    "sg:address":"8 Hawley Pl",
    "sg:city":"Marangaroo",
    "sg:classifiers":[
        {
            "category":"Building & Trades",
            "subcategory":"Construction",
            "type":"Services"
        }
    ],
    "sg:phone":"+61 407 199 855",
    "sg:postcode":"6064",
    "sg:province":"WA",
    "sg:tags":[
        "concrete",
        "contractor"
    ],
    "wof:name":"Advanced Concreting & Waterproofing Services",
    "wof:placetype":"venue"
},
  "geometry": {"coordinates":[115.824890137,-31.8332653046],"type":"Point"}
}