{
  "type": "Feature",
  "properties": {
    "addr:full":"50 Commercial St East Mt Gambier SA 5290",
    "addr:housenumber":"50",
    "addr:postcode":"5290",
    "addr:street":"Commercial St East Mt",
    "iso:country":"AU",
    "sg:address":"50 Commercial St East",
    "sg:city":"Mt Gambier",
    "sg:classifiers":[
        {
            "category":"Shopping",
            "subcategory":"Clothing, Apparel, & Fashions",
            "type":"Retail Goods"
        }
    ],
    "sg:phone":"+61 8 8725 5952",
    "sg:postcode":"5290",
    "sg:province":"SA",
    "sg:tags":[
        "lady",
        "wear"
    ],
    "wof:name":"Josephine Lingerie & Fashions",
    "wof:placetype":"venue"
},
  "geometry": {"coordinates":[140.78242499999999,-37.829098],"type":"Point"}
}