{
  "type": "Feature",
  "properties": {
    "addr:full":"Unit 7/ 26 Wotton St Bayswater WA 6053",
    "addr:housenumber":"26",
    "addr:postcode":"6053",
    "addr:street":"Wotton St",
    "iso:country":"AU",
    "sg:address":"Unit 7/ 26 Wotton St",
    "sg:city":"Bayswater",
    "sg:classifiers":[
        {
            "category":"Manufacturing",
            "subcategory":"Glass & Minerals",
            "type":"Manufacturing & Wholesale Goods"
        }
    ],
    "sg:phone":"+61 8 9371 9722",
    "sg:postcode":"6053",
    "sg:province":"WA",
    "sg:tags":[
        "merchant",
        "granite",
        "marble"
    ],
    "wof:name":"Casa Stoneworks",
    "wof:placetype":"venue"
},
  "geometry": {"coordinates":[115.91642761200001,-31.90924263],"type":"Point"}
}