{
  "type": "Feature",
  "properties": {
    "iso:country":"AU",
    "sg:address":"Shop 29, Edgecliff Cntr New South Head Rd",
    "sg:city":"Edgecliff",
    "sg:classifiers":[
        {
            "category":"Banks & Credit Unions",
            "subcategory":"Bank",
            "type":"Services"
        }
    ],
    "sg:phone":"+61 13 33 30",
    "sg:postcode":"2027",
    "sg:province":"NSW",
    "wof:name":"St.George Bank Limited",
    "wof:placetype":"venue"
},
  "geometry": {"coordinates":[151.23907470699999,-33.8790206909],"type":"Point"}
}