{
  "type": "Feature",
  "properties": {
    "iso:country":"AU",
    "sg:address":"Carnegie Pl",
    "sg:city":"Mandurah",
    "sg:classifiers":[
        {
            "category":"Social Services",
            "subcategory":"Retirement Home",
            "type":"Services"
        }
    ],
    "sg:phone":"+61 8 9582 8790",
    "sg:postcode":"6210",
    "sg:province":"WA",
    "sg:tags":[
        "village"
    ],
    "wof:name":"St Ives Mandurah",
    "wof:placetype":"venue"
},
  "geometry": {"coordinates":[115.770973,-32.5378],"type":"Point"}
}