{
  "type": "Feature",
  "properties": {
    "iso:country":"AU",
    "sg:address":"9 Village St",
    "sg:city":"Balnarring",
    "sg:classifiers":[
        {
            "category":"Professional",
            "subcategory":"Art Services",
            "type":"Services"
        }
    ],
    "sg:phone":"+61 3 5983 1822",
    "sg:postcode":"3926",
    "sg:province":"VIC",
    "sg:tags":[
        "decorator",
        "painter"
    ],
    "wof:name":"Underwood D",
    "wof:placetype":"venue"
},
  "geometry": {"coordinates":[145.123046875,-38.3715744019],"type":"Point"}
}