{
  "type": "Feature",
  "properties": {
    "addr:full":"251 Hoskins St Temora NSW 2666",
    "addr:housenumber":"251",
    "addr:postcode":"2666",
    "addr:street":"Hoskins St",
    "iso:country":"AU",
    "sg:address":"251 Hoskins St",
    "sg:city":"Temora",
    "sg:classifiers":[
        {
            "category":"Retail",
            "subcategory":"Laundry & Dry Cleaning",
            "type":"Services"
        }
    ],
    "sg:phone":"+61 2 6977 1595",
    "sg:postcode":"2666",
    "sg:province":"NSW",
    "wof:name":"Temora Coin Laundry",
    "wof:placetype":"venue"
},
  "geometry": {"coordinates":[147.53515625,-34.4504623413],"type":"Point"}
}