{
  "type": "Feature",
  "properties": {
    "iso:country":"AU",
    "sg:address":"P O Box 19 Ashburton VIC 3147",
    "sg:city":"Ashburton",
    "sg:classifiers":[
        {
            "category":"Arena",
            "subcategory":"Sports Club",
            "type":"Entertainment"
        }
    ],
    "sg:phone":"+61 3 9885 7728",
    "sg:postcode":"3147",
    "sg:province":"VIC",
    "sg:tags":[
        "defence",
        "supply",
        "self",
        "instruction",
        "martial art"
    ],
    "wof:name":"Womens Self Defence Academy",
    "wof:placetype":"venue"
},
  "geometry": {"coordinates":[145.07417297399999,-37.8595848083],"type":"Point"}
}