{
  "type": "Feature",
  "properties": {
    "addr:full":"10 Burke St Wynnum QLD 4178",
    "addr:housenumber":"10",
    "addr:postcode":"4178",
    "addr:street":"Burke St",
    "iso:country":"AU",
    "sg:address":"10 Burke St",
    "sg:city":"Wynnum",
    "sg:classifiers":[
        {
            "category":"Retail",
            "subcategory":"Auto Repair",
            "type":"Services"
        }
    ],
    "sg:phone":"+61 7 3396 5022",
    "sg:postcode":"4178",
    "sg:province":"QLD",
    "sg:tags":[
        "repairer",
        "motor",
        "engineer"
    ],
    "wof:name":"Ron Carroll Motors",
    "wof:placetype":"venue"
},
  "geometry": {"coordinates":[153.16700744600001,-27.4411449432],"type":"Point"}
}