{
  "type": "Feature",
  "properties": {
    "iso:country":"AU",
    "sg:address":"4 Excelsior Drv",
    "sg:city":"Canning Vale",
    "sg:classifiers":[
        {
            "category":"Building & Trades",
            "subcategory":"Landscaping Services",
            "type":"Services"
        }
    ],
    "sg:phone":"+61 403 248 594",
    "sg:postcode":"6155",
    "sg:province":"WA",
    "sg:tags":[
        "designer",
        "landscape",
        "contractor"
    ],
    "wof:name":"All To Plan Landscapes & Gardens",
    "wof:placetype":"venue"
},
  "geometry": {"coordinates":[115.948349,-32.079971],"type":"Point"}
}