{
  "type": "Feature",
  "properties": {
    "addr:full":"1/ 589 Collins St Melbourne VIC 3000",
    "addr:housenumber":"/ 589",
    "addr:postcode":"3000",
    "addr:street":"Collins St",
    "iso:country":"AU",
    "sg:address":"1/ 589 Collins St",
    "sg:city":"Melbourne",
    "sg:classifiers":[
        {
            "category":"Professional",
            "type":"Services"
        }
    ],
    "sg:phone":"+61 3 9619 1106",
    "sg:postcode":"3000",
    "sg:province":"VIC",
    "sg:tags":[
        "transport"
    ],
    "wof:name":"Pacific National",
    "wof:placetype":"venue"
},
  "geometry": {"coordinates":[144.95542907699999,-37.8188438416],"type":"Point"}
}