{
  "type": "Feature",
  "properties": {
    "iso:country":"AU",
    "sg:address":"Unit 7 / 34 Old Pacific Hwy",
    "sg:city":"Yatala",
    "sg:classifiers":[
        {
            "category":"Manufacturing",
            "subcategory":"Wood Products",
            "type":"Manufacturing & Wholesale Goods"
        }
    ],
    "sg:phone":"+61 500 500 207",
    "sg:postcode":"4207",
    "sg:province":"QLD",
    "sg:tags":[
        "chippers"
    ],
    "sg:website":"http://www.tubgrinders.com.au",
    "wof:name":"Tubgrinders Australia Pty Ltd",
    "wof:placetype":"venue"
},
  "geometry": {"coordinates":[153.22425842300001,-27.7336044312],"type":"Point"}
}