{
  "type": "Feature",
  "properties": {
    "addr:full":"460 Galston Rd Dural NSW 2158",
    "addr:housenumber":"460",
    "addr:postcode":"2158",
    "addr:street":"Galston Rd",
    "iso:country":"AU",
    "sg:address":"460 Galston Rd",
    "sg:city":"Dural",
    "sg:classifiers":[
        {
            "category":"Building & Trades",
            "subcategory":"Equipment Rental",
            "type":"Services"
        }
    ],
    "sg:phone":"+61 2 9651 3183",
    "sg:postcode":"2158",
    "sg:province":"NSW",
    "sg:tags":[
        "party",
        "hire"
    ],
    "wof:name":"Jubilee Amusements Pty Ltd",
    "wof:placetype":"venue"
},
  "geometry": {"coordinates":[151.03660583499999,-33.6704368591],"type":"Point"}
}