{
  "type": "Feature",
  "properties": {
    "iso:country":"AU",
    "sg:address":"11- 17 Derwent Park Rd",
    "sg:city":"Derwent Park",
    "sg:classifiers":[
        {
            "category":"Building & Trades",
            "subcategory":"Construction",
            "type":"Services"
        }
    ],
    "sg:phone":"+61 3 6273 2521",
    "sg:postcode":"7009",
    "sg:province":"TAS",
    "sg:tags":[
        "plasterboard",
        "plasterer",
        "fixer"
    ],
    "wof:name":"Hobart Plaster",
    "wof:placetype":"venue"
},
  "geometry": {"coordinates":[147.292694092,-42.8392868042],"type":"Point"}
}