{
  "type": "Feature",
  "properties": {
    "iso:country":"AU",
    "sg:address":"Level 6 172-192 Flinders St",
    "sg:city":"Melbourne",
    "sg:classifiers":[
        {
            "category":"Real Estate",
            "subcategory":"Real Estate Agent",
            "type":"Services"
        }
    ],
    "sg:phone":"+61 3 9654 8666",
    "sg:postcode":"3000",
    "sg:province":"VIC",
    "wof:name":"Gross Waddell Pty Ltd",
    "wof:placetype":"venue"
},
  "geometry": {"coordinates":[144.96833801299999,-37.8170547485],"type":"Point"}
}