{
  "type": "Feature",
  "properties": {
    "addr:full":"PO Box 3037 Rouse Hill NSW 2155",
    "addr:postcode":"2155",
    "iso:country":"AU",
    "sg:address":"PO Box 3037",
    "sg:city":"Rouse Hill",
    "sg:classifiers":[
        {
            "category":"Utilities",
            "subcategory":"Electric",
            "type":"Services"
        }
    ],
    "sg:phone":"+61 419 617 975",
    "sg:postcode":"2155",
    "sg:province":"NSW",
    "sg:tags":[
        "electrical",
        "contractor"
    ],
    "wof:name":"DJN Electrical Services Pty Ltd",
    "wof:placetype":"venue"
},
  "geometry": {"coordinates":[150.92202758799999,-33.6771697998],"type":"Point"}
}