{
  "type": "Feature",
  "properties": {
    "addr:full":"Hamel Rd Mt Pritchard NSW 2170",
    "addr:postcode":"2170",
    "addr:street":"Hamel Rd;Pritchard",
    "iso:country":"AU",
    "sg:address":"Hamel Rd",
    "sg:city":"Mt Pritchard",
    "sg:classifiers":[
        {
            "category":"Food & Beverages",
            "subcategory":"Supermarket",
            "type":"Retail Goods"
        }
    ],
    "sg:phone":"+61 2 9608 3687",
    "sg:postcode":"2170",
    "sg:province":"NSW",
    "sg:tags":[
        "grocery",
        "store"
    ],
    "wof:name":"Welcome Mart",
    "wof:placetype":"venue"
},
  "geometry": {"coordinates":[150.89544677699999,-33.9032058716],"type":"Point"}
}