{
  "type": "Feature",
  "properties": {
    "addr:full":"6/ 28 Bonthon St Windsor QLD 4030",
    "addr:housenumber":"/ 28",
    "addr:postcode":"4030",
    "addr:street":"Bonthon St",
    "iso:country":"AU",
    "sg:address":"6/ 28 Bonthon St",
    "sg:city":"Windsor",
    "sg:classifiers":[
        {
            "category":"Communications",
            "subcategory":"Film & Video Production",
            "type":"Services"
        }
    ],
    "sg:phone":"+61 1300 487 638",
    "sg:postcode":"4030",
    "sg:province":"QLD",
    "sg:tags":[
        "television",
        "system",
        "circuit",
        "closed"
    ],
    "wof:name":"Independent Technology Solutions",
    "wof:placetype":"venue"
},
  "geometry": {"coordinates":[153.033356,-27.431076],"type":"Point"}
}