{
  "type": "Feature",
  "properties": {
    "addr:full":"295 Maitland Rd Mayfield West NSW 2304",
    "addr:housenumber":"295",
    "addr:postcode":"2304",
    "addr:street":"Maitland Rd",
    "iso:country":"AU",
    "sg:address":"295 Maitland Rd",
    "sg:city":"Mayfield West",
    "sg:classifiers":[
        {
            "category":"Travel",
            "subcategory":"Hotels & Motels",
            "type":"Entertainment"
        }
    ],
    "sg:phone":"+61 2 4968 1394",
    "sg:postcode":"2304",
    "sg:province":"NSW",
    "sg:website":"http://www.tmv.com.au",
    "wof:name":"Travellers Motor Village",
    "wof:placetype":"venue"
},
  "geometry": {"coordinates":[151.72921752900001,-32.8916358948],"type":"Point"}
}