{
  "type": "Feature",
  "properties": {
    "addr:full":"72 Main St Mornington VIC 3931",
    "addr:housenumber":"72",
    "addr:postcode":"3931",
    "addr:street":"Main St",
    "iso:country":"AU",
    "sg:address":"72 Main St",
    "sg:city":"Mornington",
    "sg:classifiers":[
        {
            "category":"Health Services",
            "subcategory":"Health Practitioner",
            "type":"Services"
        }
    ],
    "sg:phone":"+61 413 068 121",
    "sg:postcode":"3931",
    "sg:province":"VIC",
    "sg:tags":[
        "psychotherapist"
    ],
    "wof:name":"Keith A. Wray (MAPS)#",
    "wof:placetype":"venue"
},
  "geometry": {"coordinates":[145.03808593799999,-38.2185974121],"type":"Point"}
}