{
  "type": "Feature",
  "properties": {
    "iso:country":"AU",
    "sg:address":"\"Winbourne\" Yarrandi Rd",
    "sg:city":"Scone",
    "sg:classifiers":[
        {
            "category":"Farming",
            "subcategory":"Vineyard",
            "type":"Manufacturing & Wholesale Goods"
        }
    ],
    "sg:phone":"+61 2 6545 1699",
    "sg:postcode":"2337",
    "sg:province":"NSW",
    "sg:tags":[
        "winery"
    ],
    "wof:name":"St Albans Scone Pty Ltd",
    "wof:placetype":"venue"
},
  "geometry": {"coordinates":[150.86297607399999,-31.9798545837],"type":"Point"}
}