{
  "type": "Feature",
  "properties": {
    "iso:country":"AU",
    "sg:address":"366 Kensington Rd",
    "sg:city":"Erindale",
    "sg:classifiers":[
        {
            "category":"Personal",
            "subcategory":"Beauty Salon",
            "type":"Services"
        }
    ],
    "sg:phone":"+61 8 8431 5446",
    "sg:postcode":"5066",
    "sg:province":"SA",
    "sg:tags":[
        "hairdresser"
    ],
    "wof:name":"Headway Of Erindale",
    "wof:placetype":"venue"
},
  "geometry": {"coordinates":[138.66288757300001,-34.9259681702],"type":"Point"}
}