{
  "type": "Feature",
  "properties": {
    "addr:full":"PO Box 561 Buderim QLD 4556",
    "addr:postcode":"4556",
    "iso:country":"AU",
    "sg:address":"PO Box 561",
    "sg:city":"Buderim",
    "sg:classifiers":[
        {
            "category":"Structure",
            "subcategory":"Building",
            "type":"Public Place"
        }
    ],
    "sg:phone":"+61 428 394 512",
    "sg:postcode":"4556",
    "sg:province":"QLD",
    "sg:tags":[
        "sail",
        "shade"
    ],
    "wof:name":"All Of Shade",
    "wof:placetype":"venue"
},
  "geometry": {"coordinates":[153.09310913100001,-26.6773891449],"type":"Point"}
}