{
  "type": "Feature",
  "properties": {
    "addr:full":"17 Hunts Rd Bittern VIC 3918",
    "addr:housenumber":"17",
    "addr:postcode":"3918",
    "addr:street":"Hunts Rd",
    "iso:country":"AU",
    "sg:address":"17 Hunts Rd",
    "sg:city":"Bittern",
    "sg:classifiers":[
        {
            "category":"Retail",
            "subcategory":"Event Space",
            "type":"Services"
        }
    ],
    "sg:phone":"+61 3 5983 6700",
    "sg:postcode":"3918",
    "sg:province":"VIC",
    "sg:tags":[
        "venue",
        "reception",
        "wedding"
    ],
    "wof:name":"Summerfields Country House",
    "wof:placetype":"venue"
},
  "geometry": {"coordinates":[145.14906310999999,-38.3242149353],"type":"Point"}
}