{
  "type": "Feature",
  "properties": {
    "addr:full":"Suite 25/ Lvl 1 MVB Bldg 90 Mona Vale Rd Mona Vale NSW 2103",
    "addr:housenumber":"25;90",
    "addr:postcode":"2103",
    "addr:street":"/;Mona Vale Rd",
    "iso:country":"AU",
    "sg:address":"Suite 25/ Lvl 1 MVB Bldg 90 Mona Vale Rd",
    "sg:city":"Mona Vale",
    "sg:classifiers":[
        {
            "category":"Real Estate",
            "subcategory":"Architect",
            "type":"Services"
        }
    ],
    "sg:phone":"+61 2 9979 4966",
    "sg:postcode":"2103",
    "sg:province":"NSW",
    "wof:name":"Planpac International Pty Ltd",
    "wof:placetype":"venue"
},
  "geometry": {"coordinates":[151.28941345199999,-33.6761665344],"type":"Point"}
}