{
  "type": "Feature",
  "properties": {
    "iso:country":"AU",
    "sg:address":"223 Gympie Rd",
    "sg:city":"Strathpine",
    "sg:classifiers":[
        {
            "category":"Autos & Motor Vehicles",
            "subcategory":"Fuel & Gas Station",
            "type":"Retail Goods"
        }
    ],
    "sg:phone":"+61 7 3881 0244",
    "sg:postcode":"4500",
    "sg:province":"QLD",
    "wof:name":"Shell",
    "wof:placetype":"venue"
},
  "geometry": {"coordinates":[152.988845825,-27.3024196625],"type":"Point"}
}