{
  "type": "Feature",
  "properties": {
    "addr:full":"Shop 131 Westfield Shoppingtown 151 Bunnerong Rd Eastgardens NSW 2036",
    "addr:housenumber":"131;151",
    "addr:postcode":"2036",
    "addr:street":"Westfield Shoppingtown;Bunnerong Rd",
    "iso:country":"AU",
    "sg:address":"Shop 131 Westfield Shoppingtown 151 Bunnerong Rd",
    "sg:city":"Eastgardens",
    "sg:classifiers":[
        {
            "category":"Health Services",
            "subcategory":"Doctor",
            "type":"Services"
        }
    ],
    "sg:phone":"+61 2 9315 5343",
    "sg:postcode":"2036",
    "sg:province":"NSW",
    "sg:tags":[
        "medical",
        "practitioner"
    ],
    "wof:name":"SDS Pathology",
    "wof:placetype":"venue"
},
  "geometry": {"coordinates":[151.22450256400001,-33.9438209534],"type":"Point"}
}