{
  "type": "Feature",
  "properties": {
    "addr:full":"2 / 39 Bartlett St Ermington NSW 2115",
    "addr:housenumber":"/ 39",
    "addr:postcode":"2115",
    "addr:street":"Bartlett St",
    "iso:country":"AU",
    "sg:address":"2 / 39 Bartlett St",
    "sg:city":"Ermington",
    "sg:classifiers":[
        {
            "category":"Professional",
            "type":"Services"
        }
    ],
    "sg:phone":"+61 2 9638 0795",
    "sg:postcode":"2115",
    "sg:province":"NSW",
    "sg:tags":[
        "industrial",
        "commercial",
        "catering"
    ],
    "wof:name":"Polly's Pantry",
    "wof:placetype":"venue"
},
  "geometry": {"coordinates":[151.05557250999999,-33.804813385],"type":"Point"}
}