{
  "type": "Feature",
  "properties": {
    "iso:country":"AU",
    "sg:address":"Shp2/ 57 First Ave",
    "sg:city":"Sawtell",
    "sg:classifiers":[
        {
            "category":"Shopping",
            "subcategory":"Clothing, Apparel, & Fashions",
            "type":"Retail Goods"
        }
    ],
    "sg:phone":"+61 2 6658 9936",
    "sg:postcode":"2452",
    "sg:province":"NSW",
    "sg:tags":[
        "accessory"
    ],
    "wof:name":"Sapa Surprise",
    "wof:placetype":"venue"
},
  "geometry": {"coordinates":[153.10064700000001,-30.368008],"type":"Point"}
}