{
  "type": "Feature",
  "properties": {
    "addr:full":"56 Day St Tara QLD 4421",
    "addr:housenumber":"56",
    "addr:postcode":"4421",
    "addr:street":"Day St",
    "iso:country":"AU",
    "sg:address":"56 Day St",
    "sg:city":"Tara",
    "sg:classifiers":[
        {
            "category":"Utilities",
            "subcategory":"Electric",
            "type":"Services"
        }
    ],
    "sg:phone":"+61 7 4665 3450",
    "sg:postcode":"4421",
    "sg:province":"QLD",
    "sg:tags":[
        "electrical",
        "contractor"
    ],
    "wof:name":"Tara Electrical Co",
    "wof:placetype":"venue"
},
  "geometry": {"coordinates":[150.45758056599999,-27.2769184113],"type":"Point"}
}