{
  "type": "Feature",
  "properties": {
    "addr:full":"2/ 302 Burns Bay Rd Lane Cove NSW 2066",
    "addr:housenumber":"/ 302",
    "addr:postcode":"2066",
    "addr:street":"Burns Bay Rd",
    "iso:country":"AU",
    "sg:address":"2/ 302 Burns Bay Rd",
    "sg:city":"Lane Cove",
    "sg:classifiers":[
        {
            "category":"Building & Trades",
            "subcategory":"Landscaping Services",
            "type":"Services"
        }
    ],
    "sg:phone":"+61 2 9420 4414",
    "sg:postcode":"2066",
    "sg:province":"NSW",
    "sg:tags":[
        "consultant"
    ],
    "wof:name":"Building Sustainability BASIX & NatHERS Assessors",
    "wof:placetype":"venue"
},
  "geometry": {"coordinates":[151.15040588400001,-33.8203620911],"type":"Point"}
}