{
  "type": "Feature",
  "properties": {
    "addr:full":"PO Box 4437 Gosford East NSW 2250",
    "addr:postcode":"2250",
    "iso:country":"AU",
    "sg:address":"PO Box 4437",
    "sg:city":"Gosford East",
    "sg:classifiers":[
        {
            "category":"Building & Trades",
            "subcategory":"Cleaning & Sanitation",
            "type":"Services"
        }
    ],
    "sg:phone":"+61 421 530 728",
    "sg:postcode":"2250",
    "sg:province":"NSW",
    "sg:tags":[
        "cleaner",
        "repairer",
        "roof"
    ],
    "wof:name":"Dans Gutter Cleaning",
    "wof:placetype":"venue"
},
  "geometry": {"coordinates":[151.355392456,-33.4287757874],"type":"Point"}
}