{
  "type": "Feature",
  "properties": {
    "iso:country":"AU",
    "sg:address":"PO Box 150",
    "sg:city":"Virginia",
    "sg:classifiers":[
        {
            "category":"Real Estate",
            "subcategory":"Architect",
            "type":"Services"
        }
    ],
    "sg:phone":"+61 8 8983 2812",
    "sg:postcode":"0835",
    "sg:province":"NT",
    "sg:tags":[
        "building",
        "designer"
    ],
    "wof:name":"C&J Production Enterprises",
    "wof:placetype":"venue"
},
  "geometry": {"coordinates":[131.02928199999999,-12.52754],"type":"Point"}
}