{
  "type": "Feature",
  "properties": {
    "iso:country":"AU",
    "sg:address":"521 Bridge Rd",
    "sg:city":"Richmond",
    "sg:classifiers":[
        {
            "category":"Building & Trades",
            "subcategory":"Equipment Rental",
            "type":"Services"
        }
    ],
    "sg:phone":"+61 3 9428 8900",
    "sg:postcode":"3121",
    "sg:province":"VIC",
    "sg:tags":[
        "fitness"
    ],
    "wof:name":"Just Fitness Richmond",
    "wof:placetype":"venue"
},
  "geometry": {"coordinates":[145.00802612300001,-37.8193283081],"type":"Point"}
}