{
  "type": "Feature",
  "properties": {
    "iso:country":"AU",
    "sg:address":"313 Fry St",
    "sg:city":"Grafton",
    "sg:classifiers":[
        {
            "category":"Fast Food",
            "type":"Food & Drink"
        }
    ],
    "sg:phone":"+61 2 6643 5889",
    "sg:postcode":"2460",
    "sg:province":"NSW",
    "sg:tags":[
        "away",
        "take"
    ],
    "wof:name":"Brownies Corner Store",
    "wof:placetype":"venue"
},
  "geometry": {"coordinates":[152.92393493599999,-29.6754550934],"type":"Point"}
}