{
  "type": "Feature",
  "properties": {
    "iso:country":"AU",
    "sg:address":"Lawrence St",
    "sg:city":"Morphett Vale",
    "sg:classifiers":[
        {
            "category":"Education",
            "subcategory":"School",
            "type":"Public Place"
        }
    ],
    "sg:phone":"+61 8 8382 5111",
    "sg:postcode":"5162",
    "sg:province":"SA",
    "sg:tags":[
        "state",
        "except",
        "nsw"
    ],
    "wof:name":"Morphett Vale High",
    "wof:placetype":"venue"
},
  "geometry": {"coordinates":[138.516555786,-35.1093330383],"type":"Point"}
}