{
  "type": "Feature",
  "properties": {
    "addr:full":"12 Hawkesburry Pl Dubbo NSW 2830",
    "addr:housenumber":"12",
    "addr:postcode":"2830",
    "addr:street":"Hawkesburry Pl",
    "iso:country":"AU",
    "sg:address":"12 Hawkesburry Pl",
    "sg:city":"Dubbo",
    "sg:classifiers":[
        {
            "category":"Professional",
            "subcategory":"Accounting & Tax Preparation",
            "type":"Services"
        }
    ],
    "sg:phone":"+61 418 592 442",
    "sg:postcode":"2830",
    "sg:province":"NSW",
    "sg:tags":[
        "bookkeeping"
    ],
    "wof:name":"Bowendarra Business Management Resources",
    "wof:placetype":"venue"
},
  "geometry": {"coordinates":[148.65065002399999,-32.2568626404],"type":"Point"}
}