{
  "type": "Feature",
  "properties": {
    "iso:country":"AU",
    "sg:address":"29 Abercrombie St",
    "sg:city":"Deepdene",
    "sg:classifiers":[
        {
            "category":"Banks & Credit Unions",
            "subcategory":"Atm",
            "type":"Services"
        }
    ],
    "sg:phone":"+61 3 9817 2710",
    "sg:postcode":"3103",
    "sg:province":"VIC",
    "sg:tags":[
        "reconditioners",
        "drum",
        "manufacturers"
    ],
    "wof:name":"D.C. Closures",
    "wof:placetype":"venue"
},
  "geometry": {"coordinates":[145.06463623100001,-37.8080215454],"type":"Point"}
}