{
  "type": "Feature",
  "properties": {
    "iso:country":"AU",
    "sg:address":"1 Lincoln Rd",
    "sg:city":"Georges Hall",
    "sg:classifiers":[
        {
            "category":"Health Services",
            "subcategory":"Health Practitioner",
            "type":"Services"
        }
    ],
    "sg:phone":"+61 2 9709 5490",
    "sg:postcode":"2198",
    "sg:province":"NSW",
    "sg:tags":[
        "physiotherapist"
    ],
    "wof:name":"Gilbert Sandra",
    "wof:placetype":"venue"
},
  "geometry": {"coordinates":[150.99968,-33.914898],"type":"Point"}
}