{
  "type": "Feature",
  "properties": {
    "addr:full":"45 Dumaresq St Campbelltown NSW 2560",
    "addr:housenumber":"45",
    "addr:postcode":"2560",
    "addr:street":"Dumaresq St",
    "iso:country":"AU",
    "sg:address":"45 Dumaresq St",
    "sg:city":"Campbelltown",
    "sg:classifiers":[
        {
            "category":"Shopping",
            "subcategory":"Computers & Home Electronics",
            "type":"Retail Goods"
        }
    ],
    "sg:phone":"+61 2 4628 6777",
    "sg:postcode":"2560",
    "sg:province":"NSW",
    "sg:tags":[
        "equipment",
        "supply"
    ],
    "wof:name":"Zip Computers",
    "wof:placetype":"venue"
},
  "geometry": {"coordinates":[150.81248474099999,-34.0675888062],"type":"Point"}
}