{
  "type": "Feature",
  "properties": {
    "iso:country":"AU",
    "sg:address":"1756 Ipswich Rd",
    "sg:city":"Rocklea",
    "sg:classifiers":[
        {
            "category":"Building & Trades",
            "subcategory":"Construction",
            "type":"Services"
        }
    ],
    "sg:phone":"+61 7 3255 5355",
    "sg:postcode":"4106",
    "sg:province":"QLD",
    "sg:tags":[
        "earth",
        "excavating",
        "moving",
        "contractor"
    ],
    "wof:name":"Donpra Hire",
    "wof:placetype":"venue"
},
  "geometry": {"coordinates":[152.99920654300001,-27.5606555939],"type":"Point"}
}