{
  "type": "Feature",
  "properties": {
    "addr:full":"341 Francis St Yarraville VIC 3013",
    "addr:housenumber":"341",
    "addr:postcode":"3013",
    "addr:street":"Francis St",
    "iso:country":"AU",
    "sg:address":"341 Francis St",
    "sg:city":"Yarraville",
    "sg:classifiers":[
        {
            "category":"Manufacturing",
            "subcategory":"Textiles",
            "type":"Manufacturing & Wholesale Goods"
        }
    ],
    "sg:phone":"+61 3 9244 3488",
    "sg:postcode":"3013",
    "sg:province":"VIC",
    "sg:tags":[
        "mill"
    ],
    "wof:name":"Flamesafe Fabric Specialists",
    "wof:placetype":"venue"
},
  "geometry": {"coordinates":[144.86761474599999,-37.8187141418],"type":"Point"}
}