{
  "type": "Feature",
  "properties": {
    "iso:country":"AU",
    "sg:address":"113 Fairford Rd",
    "sg:city":"Padstow",
    "sg:classifiers":[
        {
            "category":"Building & Trades",
            "subcategory":"Cleaning & Sanitation",
            "type":"Services"
        }
    ],
    "sg:phone":"+61 2 9773 4333",
    "sg:postcode":"2211",
    "sg:province":"NSW",
    "sg:tags":[
        "sweeping",
        "machine"
    ],
    "wof:name":"Action Scrubbing Services",
    "wof:placetype":"venue"
},
  "geometry": {"coordinates":[151.03500399999999,-33.941898],"type":"Point"}
}