{
  "type": "Feature",
  "properties": {
    "addr:full":"Unit 3, 6 Barnett Crt Morley WA 6062",
    "addr:housenumber":"6",
    "addr:postcode":"6062",
    "addr:street":"Barnett Crt",
    "iso:country":"AU",
    "sg:address":"Unit 3, 6 Barnett Crt",
    "sg:city":"Morley",
    "sg:classifiers":[
        {
            "category":"Professional",
            "subcategory":"Printing & Photocopies",
            "type":"Services"
        }
    ],
    "sg:phone":"+61 8 9371 0909",
    "sg:postcode":"6062",
    "sg:province":"WA",
    "sg:tags":[
        "publishing",
        "desktop"
    ],
    "wof:name":"Proto-Type Graphics",
    "wof:placetype":"venue"
},
  "geometry": {"coordinates":[115.902542114,-31.9019184113],"type":"Point"}
}