{
  "type": "Feature",
  "properties": {
    "iso:country":"AU",
    "sg:address":"24 Tydeman Rd",
    "sg:city":"Fremantle",
    "sg:classifiers":[
        {
            "category":"Restaurant",
            "type":"Food & Drink"
        }
    ],
    "sg:phone":"+61 8 9430 8468",
    "sg:postcode":"6160",
    "sg:province":"WA",
    "sg:website":"http://www.thenewbridges.com.au",
    "wof:name":"The New Bridges Restaurant",
    "wof:placetype":"venue"
},
  "geometry": {"coordinates":[115.753929,-32.036602],"type":"Point"}
}