{
  "type": "Feature",
  "properties": {
    "iso:country":"AU",
    "sg:address":"245 Malop St",
    "sg:city":"Geelong",
    "sg:classifiers":[
        {
            "category":"Food & Beverages",
            "subcategory":"Groceries & Convenience Stores",
            "type":"Retail Goods"
        }
    ],
    "sg:phone":"+61 3 5229 5295",
    "sg:postcode":"3220",
    "sg:province":"VIC",
    "wof:name":"Fan's Milkbar",
    "wof:placetype":"venue"
},
  "geometry": {"coordinates":[144.368561,-38.149315],"type":"Point"}
}