{
  "type": "Feature",
  "properties": {
    "addr:full":"PO Box 575 Floreat Forum WA 6014",
    "addr:postcode":"6014",
    "iso:country":"AU",
    "sg:address":"PO Box 575",
    "sg:city":"Floreat Forum",
    "sg:classifiers":[
        {
            "category":"Shopping",
            "subcategory":"Musical Instruments",
            "type":"Retail Goods"
        }
    ],
    "sg:phone":"+61 8 9387 6282",
    "sg:postcode":"6014",
    "sg:province":"WA",
    "sg:tags":[
        "musician",
        "agent"
    ],
    "wof:name":"Solo To Symphony",
    "wof:placetype":"venue"
},
  "geometry": {"coordinates":[115.792800903,-31.9380493164],"type":"Point"}
}