{
  "type": "Feature",
  "properties": {
    "iso:country":"AU",
    "sg:address":"SHOP 15 (Rear) Forster Tower Wallis St",
    "sg:city":"Forster",
    "sg:classifiers":[
        {
            "category":"Manufacturing",
            "subcategory":"Electronics",
            "type":"Manufacturing & Wholesale Goods"
        }
    ],
    "sg:phone":"+61 2 6554 5352",
    "sg:postcode":"2428",
    "sg:province":"NSW",
    "sg:tags":[
        "oven",
        "microwave"
    ],
    "wof:name":"Forster Electronic Services",
    "wof:placetype":"venue"
},
  "geometry": {"coordinates":[152.517242,-32.181564],"type":"Point"}
}