{
  "type": "Feature",
  "properties": {
    "addr:full":"30 Griffiths Ave West Ryde NSW 2114",
    "addr:housenumber":"30",
    "addr:postcode":"2114",
    "addr:street":"Griffiths Ave",
    "iso:country":"AU",
    "sg:address":"30 Griffiths Ave",
    "sg:city":"West Ryde",
    "sg:classifiers":[
        {
            "category":"Real Estate",
            "subcategory":"Real Estate Services",
            "type":"Services"
        }
    ],
    "sg:phone":"+61 2 9809 4055",
    "sg:postcode":"2114",
    "sg:province":"NSW",
    "sg:tags":[
        "consultant",
        "property"
    ],
    "wof:name":"Bluwol & Associates Conveyancers",
    "wof:placetype":"venue"
},
  "geometry": {"coordinates":[151.098144531,-33.8106536865],"type":"Point"}
}