{
  "type": "Feature",
  "properties": {
    "addr:full":"154 Boronia Rd Boronia VIC 3155",
    "addr:housenumber":"154",
    "addr:postcode":"3155",
    "addr:street":"Boronia Rd",
    "iso:country":"AU",
    "sg:address":"154 Boronia Rd",
    "sg:city":"Boronia",
    "sg:classifiers":[
        {
            "category":"Health Services",
            "subcategory":"Doctor",
            "type":"Services"
        }
    ],
    "sg:phone":"+61 3 9762 6978",
    "sg:postcode":"3155",
    "sg:province":"VIC",
    "sg:tags":[
        "medical",
        "practitioner"
    ],
    "wof:name":"Hattotuwa Melanie Dr",
    "wof:placetype":"venue"
},
  "geometry": {"coordinates":[145.28242492699999,-37.8625335693],"type":"Point"}
}