{
  "type": "Feature",
  "properties": {
    "addr:full":"Austin Ave Terang VIC 3264",
    "addr:postcode":"3264",
    "addr:street":"Austin Ave",
    "iso:country":"AU",
    "sg:address":"Austin Ave",
    "sg:city":"Terang",
    "sg:classifiers":[
        {
            "category":"Health Services",
            "subcategory":"Nursing And Care Facility",
            "type":"Services"
        }
    ],
    "sg:phone":"+61 3 5592 0222",
    "sg:postcode":"3264",
    "sg:province":"VIC",
    "sg:tags":[
        "home"
    ],
    "wof:name":"Terang & Mortlake Health Service",
    "wof:placetype":"venue"
},
  "geometry": {"coordinates":[142.90257263199999,-38.2400550842],"type":"Point"}
}