{
  "type": "Feature",
  "properties": {
    "iso:country":"AU",
    "sg:address":"3 Drysdale St",
    "sg:city":"Malvern",
    "sg:classifiers":[
        {
            "category":"Personal",
            "subcategory":"Beauty Salon",
            "type":"Services"
        }
    ],
    "sg:phone":"+61 3 9500 0033",
    "sg:postcode":"3144",
    "sg:province":"VIC",
    "wof:name":"Nice One Nails And Spa",
    "wof:placetype":"venue"
},
  "geometry": {"coordinates":[145.029373169,-37.8621902466],"type":"Point"}
}