{
  "type": "Feature",
  "properties": {
    "addr:full":"607 Parramatta Rd Leichhardt NSW 2040",
    "addr:housenumber":"607",
    "addr:postcode":"2040",
    "addr:street":"Parramatta Rd",
    "iso:country":"AU",
    "sg:address":"607 Parramatta Rd",
    "sg:city":"Leichhardt",
    "sg:classifiers":[
        {
            "category":"Retail",
            "subcategory":"Auto Repair",
            "type":"Services"
        }
    ],
    "sg:phone":"+61 2 9569 3330",
    "sg:postcode":"2040",
    "sg:province":"NSW",
    "sg:tags":[
        "hire",
        "go-kart"
    ],
    "wof:name":"Merlin Racing Australia",
    "wof:placetype":"venue"
},
  "geometry": {"coordinates":[151.15007,-33.8895],"type":"Point"}
}