{
  "type": "Feature",
  "properties": {
    "addr:full":"2 Phelps St Surry Hills NSW 2010",
    "addr:housenumber":"2",
    "addr:postcode":"2010",
    "addr:street":"Phelps St",
    "iso:country":"AU",
    "sg:address":"2 Phelps St",
    "sg:city":"Surry Hills",
    "sg:classifiers":[
        {
            "category":"Education",
            "subcategory":"Kindergarten",
            "type":"Public Place"
        }
    ],
    "sg:phone":"+61 2 9360 4921",
    "sg:postcode":"2010",
    "sg:province":"NSW",
    "sg:tags":[
        "pre-schools"
    ],
    "wof:name":"KU Children's Services",
    "wof:placetype":"venue"
},
  "geometry": {"coordinates":[151.21458435100001,-33.8869743347],"type":"Point"}
}