{
  "type": "Feature",
  "properties": {
    "addr:full":"Slaughter House Rd Clare SA 5453",
    "addr:postcode":"5453",
    "addr:street":"House Rd",
    "iso:country":"AU",
    "sg:address":"Slaughter House Rd",
    "sg:city":"Clare",
    "sg:classifiers":[
        {
            "category":"Farming",
            "subcategory":"Vineyard",
            "type":"Manufacturing & Wholesale Goods"
        }
    ],
    "sg:phone":"+61 8 8842 1799",
    "sg:postcode":"5453",
    "sg:province":"SA",
    "sg:tags":[
        "winery"
    ],
    "wof:name":"Tullymore Vineyard",
    "wof:placetype":"venue"
},
  "geometry": {"coordinates":[138.62510700000001,-33.826523],"type":"Point"}
}