{
  "type": "Feature",
  "properties": {
    "addr:full":"Shop T03 Plenty Valley Shopping Plenty Valley Rd Mill Park VIC 3082",
    "addr:postcode":"3082",
    "addr:street":"Valley Rd",
    "iso:country":"AU",
    "sg:address":"Shop T03 Plenty Valley Shopping Plenty Valley Rd",
    "sg:city":"Mill Park",
    "sg:classifiers":[
        {
            "category":"Real Estate",
            "subcategory":"Real Estate Agent",
            "type":"Services"
        }
    ],
    "sg:phone":"+61 3 9437 9000",
    "sg:postcode":"3082",
    "sg:province":"VIC",
    "wof:name":"L J Hooker",
    "wof:placetype":"venue"
},
  "geometry": {"coordinates":[145.072433472,-37.6628112793],"type":"Point"}
}