{
  "type": "Feature",
  "properties": {
    "iso:country":"AU",
    "sg:address":"21b Montview Pde",
    "sg:city":"Hornsby Heights",
    "sg:classifiers":[
        {
            "category":"Retail",
            "subcategory":"Auto Repair",
            "type":"Services"
        }
    ],
    "sg:phone":"+61 2 9477 2069",
    "sg:postcode":"2077",
    "sg:province":"NSW",
    "sg:tags":[
        "car",
        "restoration",
        "supply"
    ],
    "wof:name":"Vintage Speed Shop",
    "wof:placetype":"venue"
},
  "geometry": {"coordinates":[151.09387207,-33.6649894714],"type":"Point"}
}