{
  "type": "Feature",
  "properties": {
    "addr:full":"Clarence St Moss Vale NSW 2577",
    "addr:postcode":"2577",
    "addr:street":"Clarence St",
    "iso:country":"AU",
    "sg:address":"Clarence St",
    "sg:city":"Moss Vale",
    "sg:classifiers":[
        {
            "category":"Home & Garden",
            "subcategory":"Furniture",
            "type":"Retail Goods"
        }
    ],
    "sg:phone":"+61 2 4868 1274",
    "sg:postcode":"2577",
    "sg:province":"NSW",
    "sg:tags":[
        "business"
    ],
    "wof:name":"Moss Vale Newsagency",
    "wof:placetype":"venue"
},
  "geometry": {"coordinates":[150.373413086,-34.5485496521],"type":"Point"}
}