{
  "type": "Feature",
  "properties": {
    "addr:full":"Unit 4/7 Lindsay Rd Lonsdale SA 5160",
    "addr:housenumber":"7",
    "addr:postcode":"5160",
    "addr:street":"Lindsay Rd",
    "iso:country":"AU",
    "sg:address":"Unit 4/7 Lindsay Rd",
    "sg:city":"Lonsdale",
    "sg:classifiers":[
        {
            "category":"Military Area",
            "subcategory":"Air Force Base",
            "type":"Public Place"
        }
    ],
    "sg:phone":"+61 8 8322 4811",
    "sg:postcode":"5160",
    "sg:province":"SA",
    "sg:tags":[
        "box",
        "case",
        "wood"
    ],
    "wof:name":"Jones Timber Products",
    "wof:placetype":"venue"
},
  "geometry": {"coordinates":[138.500930786,-35.1052742004],"type":"Point"}
}