{
  "type": "Feature",
  "properties": {
    "addr:full":"151 Station St Aspendale VIC 3195",
    "addr:housenumber":"151",
    "addr:postcode":"3195",
    "addr:street":"Station St",
    "iso:country":"AU",
    "sg:address":"151 Station St",
    "sg:city":"Aspendale",
    "sg:classifiers":[
        {
            "category":"Education",
            "subcategory":"Kindergarten",
            "type":"Public Place"
        }
    ],
    "sg:phone":"+61 3 9580 1549",
    "sg:postcode":"3195",
    "sg:province":"VIC",
    "sg:tags":[
        "pre-schools"
    ],
    "wof:name":"Nola Barber Kindergarten",
    "wof:placetype":"venue"
},
  "geometry": {"coordinates":[145.103317261,-38.0285644531],"type":"Point"}
}