{
  "type": "Feature",
  "properties": {
    "addr:full":"Unit 1/ 183 Canterbury Rd Bayswater VIC 3153",
    "addr:housenumber":"/ 183",
    "addr:postcode":"3153",
    "addr:street":"Canterbury Rd",
    "iso:country":"AU",
    "sg:address":"Unit 1/ 183 Canterbury Rd",
    "sg:city":"Bayswater",
    "sg:classifiers":[
        {
            "category":"Building & Trades",
            "subcategory":"Construction",
            "type":"Services"
        }
    ],
    "sg:phone":"+61 3 9738 2322",
    "sg:postcode":"3153",
    "sg:province":"VIC",
    "sg:tags":[
        "pool",
        "swimming"
    ],
    "wof:name":"Clark Pools & Spas",
    "wof:placetype":"venue"
},
  "geometry": {"coordinates":[145.277053833,-37.8297042847],"type":"Point"}
}