{
  "type": "Feature",
  "properties": {
    "addr:full":"10 Shoreham Rd Shoreham VIC 3916",
    "addr:housenumber":"10",
    "addr:postcode":"3916",
    "addr:street":"Shoreham Rd",
    "iso:country":"AU",
    "sg:address":"10 Shoreham Rd",
    "sg:city":"Shoreham",
    "sg:classifiers":[
        {
            "category":"Farming",
            "subcategory":"Vineyard",
            "type":"Manufacturing & Wholesale Goods"
        }
    ],
    "sg:phone":"+61 3 5989 8848",
    "sg:postcode":"3916",
    "sg:province":"VIC",
    "sg:tags":[
        "winery"
    ],
    "wof:name":"Pier 10",
    "wof:placetype":"venue"
},
  "geometry": {"coordinates":[145.04225158700001,-38.4182090759],"type":"Point"}
}