{
  "type": "Feature",
  "properties": {
    "iso:country":"AU",
    "sg:address":"60 Corporate Drv",
    "sg:city":"Moorabbin",
    "sg:classifiers":[
        {
            "category":"Professional",
            "subcategory":"Management & Consulting",
            "type":"Services"
        }
    ],
    "sg:phone":"+61 3 9558 3200",
    "sg:postcode":"3189",
    "sg:province":"VIC",
    "sg:tags":[
        "consultant"
    ],
    "wof:name":"James Rynn & Associates",
    "wof:placetype":"venue"
},
  "geometry": {"coordinates":[145.07745361299999,-37.9498443604],"type":"Point"}
}