{
  "type": "Feature",
  "properties": {
    "addr:full":"113 Hogan St Tatura VIC 3616",
    "addr:housenumber":"113",
    "addr:postcode":"3616",
    "addr:street":"Hogan St",
    "iso:country":"AU",
    "sg:address":"113 Hogan St",
    "sg:city":"Tatura",
    "sg:classifiers":[
        {
            "category":"Real Estate",
            "subcategory":"Real Estate Agent",
            "type":"Services"
        }
    ],
    "sg:phone":"+61 3 5824 2900",
    "sg:postcode":"3616",
    "sg:province":"VIC",
    "wof:name":"Tatura Real Estate",
    "wof:placetype":"venue"
},
  "geometry": {"coordinates":[145.226806641,-36.4399757385],"type":"Point"}
}