{
  "type": "Feature",
  "properties": {
    "iso:country":"AU",
    "sg:address":"66 Wuduru Rd",
    "sg:city":"Cornubia",
    "sg:classifiers":[
        {
            "category":"Professional",
            "subcategory":"Engineering",
            "type":"Services"
        }
    ],
    "sg:phone":"+61 412 771 162",
    "sg:postcode":"4130",
    "sg:province":"QLD",
    "sg:tags":[
        "consulting",
        "engineer"
    ],
    "wof:name":"McCarthy Mathews Civil Engineers",
    "wof:placetype":"venue"
},
  "geometry": {"coordinates":[153.228912353,-27.6573448181],"type":"Point"}
}