{
  "type": "Feature",
  "properties": {
    "addr:full":"86 High St Wodonga VIC 3690",
    "addr:housenumber":"86",
    "addr:postcode":"3690",
    "addr:street":"High St",
    "iso:country":"AU",
    "sg:address":"86 High St",
    "sg:city":"Wodonga",
    "sg:classifiers":[
        {
            "category":"Travel",
            "subcategory":"Travel Agent",
            "type":"Entertainment"
        }
    ],
    "sg:phone":"+61 2 6024 3422",
    "sg:postcode":"3690",
    "sg:province":"VIC",
    "sg:tags":[
        "consultant"
    ],
    "wof:name":"Wodonga Travel",
    "wof:placetype":"venue"
},
  "geometry": {"coordinates":[146.88938903799999,-36.1188201904],"type":"Point"}
}