{
  "type": "Feature",
  "properties": {
    "addr:full":"134B Great Western Hwy Blaxland NSW 2774",
    "addr:housenumber":"134b",
    "addr:postcode":"2774",
    "addr:street":"Great Western Hwy",
    "iso:country":"AU",
    "sg:address":"134B Great Western Hwy",
    "sg:city":"Blaxland",
    "sg:classifiers":[
        {
            "category":"Health Services",
            "subcategory":"Doctor",
            "type":"Services"
        }
    ],
    "sg:phone":"+61 2 4739 1555",
    "sg:postcode":"2774",
    "sg:province":"NSW",
    "sg:tags":[
        "medical",
        "practitioner"
    ],
    "wof:name":"Stewart Heather Dr",
    "wof:placetype":"venue"
},
  "geometry": {"coordinates":[150.61070251500001,-33.744884491],"type":"Point"}
}