{
  "type": "Feature",
  "properties": {
    "addr:full":"302 Forest Rd Bexley NSW 2207",
    "addr:housenumber":"302",
    "addr:postcode":"2207",
    "addr:street":"Forest Rd",
    "iso:country":"AU",
    "sg:address":"302 Forest Rd",
    "sg:city":"Bexley",
    "sg:classifiers":[
        {
            "category":"Home & Garden",
            "subcategory":"Carpets & Floor Coverings",
            "type":"Retail Goods"
        }
    ],
    "sg:phone":"+61 2 9599 8999",
    "sg:postcode":"2207",
    "sg:province":"NSW",
    "sg:tags":[
        "tile",
        "wall"
    ],
    "wof:name":"Riza Tiles",
    "wof:placetype":"venue"
},
  "geometry": {"coordinates":[151.124695,-33.95155],"type":"Point"}
}