{
  "type": "Feature",
  "properties": {
    "iso:country":"AU",
    "sg:address":"102 Kenny St",
    "sg:city":"Portsmith",
    "sg:classifiers":[
        {
            "category":"Retail",
            "subcategory":"Auto Repair",
            "type":"Services"
        }
    ],
    "sg:phone":"+61 7 4035 4114",
    "sg:postcode":"4870",
    "sg:province":"QLD",
    "sg:tags":[
        "repairer",
        "motor",
        "engineer"
    ],
    "wof:name":"R K Motors",
    "wof:placetype":"venue"
},
  "geometry": {"coordinates":[145.76983642600001,-16.9355201721],"type":"Point"}
}