{
  "type": "Feature",
  "properties": {
    "addr:full":"17 Owen St Innisfail QLD 4860",
    "addr:housenumber":"17",
    "addr:postcode":"4860",
    "addr:street":"Owen St",
    "iso:country":"AU",
    "sg:address":"17 Owen St",
    "sg:city":"Innisfail",
    "sg:classifiers":[
        {
            "category":"Personal",
            "subcategory":"Beauty Salon",
            "type":"Services"
        }
    ],
    "sg:phone":"+61 7 4061 7266",
    "sg:postcode":"4860",
    "sg:province":"QLD",
    "sg:tags":[
        "hairdresser"
    ],
    "wof:name":"Innisfail Gentz Barber",
    "wof:placetype":"venue"
},
  "geometry": {"coordinates":[146.02951049800001,-17.5246734619],"type":"Point"}
}