{
  "type": "Feature",
  "properties": {
    "iso:country":"AU",
    "sg:address":"Wharf St",
    "sg:city":"Marrickville",
    "sg:classifiers":[
        {
            "category":"Sports & Exercise",
            "subcategory":"Golf",
            "type":"Entertainment"
        }
    ],
    "sg:phone":"+61 2 9558 1876",
    "sg:postcode":"2204",
    "sg:province":"NSW",
    "sg:tags":[
        "club"
    ],
    "wof:name":"Marrickville Golf Club Ltd",
    "wof:placetype":"venue"
},
  "geometry": {"coordinates":[151.1427,-33.921165],"type":"Point"}
}