{
  "type": "Feature",
  "properties": {
    "addr:full":"39 Malop St Geelong VIC 3220",
    "addr:housenumber":"39",
    "addr:postcode":"3220",
    "addr:street":"Malop St",
    "iso:country":"AU",
    "sg:address":"39 Malop St",
    "sg:city":"Geelong",
    "sg:classifiers":[
        {
            "category":"Shopping",
            "subcategory":"Shoes",
            "type":"Retail Goods"
        }
    ],
    "sg:phone":"+61 3 5224 2362",
    "sg:postcode":"3220",
    "sg:province":"VIC",
    "sg:tags":[
        "footwear"
    ],
    "wof:name":"One Two Buckle My Shoe",
    "wof:placetype":"venue"
},
  "geometry": {"coordinates":[144.36013800000001,-38.146919],"type":"Point"}
}