{
  "type": "Feature",
  "properties": {
    "iso:country":"AU",
    "sg:address":"Westport Shop 17 30 Charles St",
    "sg:city":"Parramatta",
    "sg:classifiers":[
        {
            "category":"Banks & Credit Unions",
            "subcategory":"Financial Services",
            "type":"Services"
        }
    ],
    "sg:phone":"+61 1300 782 572",
    "sg:postcode":"2150",
    "sg:province":"NSW",
    "sg:tags":[
        "loan",
        "finance",
        "mortgage"
    ],
    "wof:name":"Home Equity Mate Pty Ltd",
    "wof:placetype":"venue"
},
  "geometry": {"coordinates":[151.01153564399999,-33.8423423767],"type":"Point"}
}