{
  "type": "Feature",
  "properties": {
    "addr:full":"7 Plante Crt Strathdale VIC 3550",
    "addr:housenumber":"7",
    "addr:postcode":"3550",
    "addr:street":"Plante Crt",
    "iso:country":"AU",
    "sg:address":"7 Plante Crt",
    "sg:city":"Strathdale",
    "sg:classifiers":[
        {
            "category":"Health Services",
            "subcategory":"Health Practitioner",
            "type":"Services"
        }
    ],
    "sg:phone":"+61 3 5443 7857",
    "sg:postcode":"3550",
    "sg:province":"VIC",
    "sg:tags":[
        "dietitian"
    ],
    "wof:name":"Hicks N F",
    "wof:placetype":"venue"
},
  "geometry": {"coordinates":[144.31214904800001,-36.7740898132],"type":"Point"}
}