{
  "type": "Feature",
  "properties": {
    "addr:full":"PO Box 716 Chester Hill NSW 2162",
    "addr:postcode":"2162",
    "iso:country":"AU",
    "sg:address":"PO Box 716",
    "sg:city":"Chester Hill",
    "sg:classifiers":[
        {
            "category":"Retail",
            "subcategory":"Auto Repair",
            "type":"Services"
        }
    ],
    "sg:phone":"+61 412 642 165",
    "sg:postcode":"2162",
    "sg:province":"NSW",
    "sg:tags":[
        "repairer",
        "motor",
        "engineer"
    ],
    "wof:name":"David's Mobile Lubes",
    "wof:placetype":"venue"
},
  "geometry": {"coordinates":[151.00013732900001,-33.8829994202],"type":"Point"}
}