{
  "type": "Feature",
  "properties": {
    "addr:full":"Cnr Sherwood Rd & Jephson St Toowong QLD 4066",
    "addr:postcode":"4066",
    "addr:street":"Cnr Sherwood Rd & Jephson St",
    "iso:country":"AU",
    "sg:address":"Cnr Sherwood Rd & Jephson St",
    "sg:city":"Toowong",
    "sg:classifiers":[
        {
            "category":"Health Services",
            "subcategory":"Dentist",
            "type":"Services"
        }
    ],
    "sg:phone":"+61 7 3870 7617",
    "sg:postcode":"4066",
    "sg:province":"QLD",
    "wof:name":"Toowong Dental Group",
    "wof:placetype":"venue"
},
  "geometry": {"coordinates":[152.98452758799999,-27.4843597412],"type":"Point"}
}