{
  "type": "Feature",
  "properties": {
    "iso:country":"AU",
    "sg:address":"161 Spencer St",
    "sg:city":"Bunbury",
    "sg:classifiers":[
        {
            "category":"Health Services",
            "subcategory":"Dentist",
            "type":"Services"
        }
    ],
    "sg:phone":"+61 8 9721 5727",
    "sg:postcode":"6230",
    "sg:province":"WA",
    "wof:name":"Cary Dry",
    "wof:placetype":"venue"
},
  "geometry": {"coordinates":[115.64151,-33.346283],"type":"Point"}
}