{
  "type": "Feature",
  "properties": {
    "addr:full":"Wishart Square 296 Newnham (cnr Wishart Rd) Rd Upper Mt Gravatt QLD 4122",
    "addr:housenumber":"296",
    "addr:postcode":"4122",
    "addr:street":"Newnham Cnr Wishart Rd Rd",
    "iso:country":"AU",
    "sg:address":"Wishart Square 296 Newnham (cnr Wishart Rd) Rd",
    "sg:city":"Upper Mt Gravatt",
    "sg:classifiers":[
        {
            "category":"Real Estate",
            "subcategory":"Real Estate Agent",
            "type":"Services"
        }
    ],
    "sg:phone":"+61 7 3349 5333",
    "sg:postcode":"4122",
    "sg:province":"QLD",
    "wof:name":"Raine & Horne (Qld) Pty Ltd",
    "wof:placetype":"venue"
},
  "geometry": {"coordinates":[153.09190368599999,-27.5470333099],"type":"Point"}
}