{
  "type": "Feature",
  "properties": {
    "addr:full":"20 Clarendon St Frankston VIC 3199",
    "addr:housenumber":"20",
    "addr:postcode":"3199",
    "addr:street":"Clarendon St",
    "iso:country":"AU",
    "sg:address":"20 Clarendon St",
    "sg:city":"Frankston",
    "sg:classifiers":[
        {
            "category":"Health Services",
            "subcategory":"Doctor",
            "type":"Services"
        }
    ],
    "sg:phone":"+61 3 9770 0522",
    "sg:postcode":"3199",
    "sg:province":"VIC",
    "sg:tags":[
        "medical",
        "practitioner"
    ],
    "wof:name":"Taverner M G Dr",
    "wof:placetype":"venue"
},
  "geometry": {"coordinates":[145.274734497,-38.1046905518],"type":"Point"}
}