{
  "type": "Feature",
  "properties": {
    "iso:country":"AU",
    "sg:address":"PO Box 1499",
    "sg:city":"Mona Vale",
    "sg:classifiers":[
        {
            "category":"Building & Trades",
            "subcategory":"Construction",
            "type":"Services"
        }
    ],
    "sg:phone":"+61 2 9999 2134",
    "sg:postcode":"2103",
    "sg:province":"NSW",
    "sg:tags":[
        "home",
        "air conditioning"
    ],
    "wof:name":"Barrenjoey Air Conditioning",
    "wof:placetype":"venue"
},
  "geometry": {"coordinates":[151.300323486,-33.6770706177],"type":"Point"}
}