{
  "type": "Feature",
  "properties": {
    "iso:country":"AU",
    "sg:address":"Suite 7/ 69 The Esplanade, Balmoral Beach",
    "sg:city":"Balmoral",
    "sg:classifiers":[
        {
            "category":"Shopping",
            "subcategory":"Computers & Home Electronics",
            "type":"Retail Goods"
        }
    ],
    "sg:phone":"+61 2 9969 7441",
    "sg:postcode":"2088",
    "sg:province":"NSW",
    "sg:tags":[
        "equipment",
        "multimedia"
    ],
    "wof:name":"Premium Media",
    "wof:placetype":"venue"
},
  "geometry": {"coordinates":[151.25018310600001,-33.8217926025],"type":"Point"}
}