{
  "type": "Feature",
  "properties": {
    "iso:country":"AU",
    "sg:address":"24 Rawson Ave",
    "sg:city":"Bexley",
    "sg:classifiers":[
        {
            "category":"Building & Trades",
            "subcategory":"Construction",
            "type":"Services"
        }
    ],
    "sg:phone":"+61 419 440 013",
    "sg:postcode":"2207",
    "sg:province":"NSW",
    "sg:tags":[
        "earth",
        "excavating",
        "moving",
        "contractor"
    ],
    "wof:name":"Cane Excavation",
    "wof:placetype":"venue"
},
  "geometry": {"coordinates":[151.12167400000001,-33.959007],"type":"Point"}
}