{
  "type": "Feature",
  "properties": {
    "addr:full":"71 High St Prahran VIC 3181",
    "addr:housenumber":"71",
    "addr:postcode":"3181",
    "addr:street":"High St",
    "iso:country":"AU",
    "sg:address":"71 High St",
    "sg:city":"Prahran",
    "sg:classifiers":[
        {
            "category":"Fast Food",
            "type":"Food & Drink"
        }
    ],
    "sg:phone":"+61 3 9510 8988",
    "sg:postcode":"3181",
    "sg:province":"VIC",
    "sg:tags":[
        "away",
        "take"
    ],
    "wof:name":"Prahran Takeaway",
    "wof:placetype":"venue"
},
  "geometry": {"coordinates":[144.98822021500001,-37.8510246277],"type":"Point"}
}