{
  "type": "Feature",
  "properties": {
    "addr:full":"164 Witty Rd Moggill QLD 4070",
    "addr:housenumber":"164",
    "addr:postcode":"4070",
    "addr:street":"Witty Rd",
    "iso:country":"AU",
    "sg:address":"164 Witty Rd",
    "sg:city":"Moggill",
    "sg:classifiers":[
        {
            "category":"Farming",
            "subcategory":"Nursery",
            "type":"Manufacturing & Wholesale Goods"
        }
    ],
    "sg:phone":"+61 7 3202 6905",
    "sg:postcode":"4070",
    "sg:province":"QLD",
    "wof:name":"Ian Bullens Nursery",
    "wof:placetype":"venue"
},
  "geometry": {"coordinates":[152.859619141,-27.568031311],"type":"Point"}
}