{
  "type": "Feature",
  "properties": {
    "addr:full":"3/ 24 Breed St Traralgon VIC 3844",
    "addr:housenumber":"/ 24",
    "addr:postcode":"3844",
    "addr:street":"Breed St",
    "iso:country":"AU",
    "sg:address":"3/ 24 Breed St",
    "sg:city":"Traralgon",
    "sg:classifiers":[
        {
            "category":"Professional",
            "subcategory":"Employment Agencies",
            "type":"Services"
        }
    ],
    "sg:phone":"+61 3 5174 5632",
    "sg:postcode":"3844",
    "sg:province":"VIC",
    "wof:name":"Workways Association Inc. Employment Services",
    "wof:placetype":"venue"
},
  "geometry": {"coordinates":[146.53326415999999,-38.1971969604],"type":"Point"}
}