{
  "type": "Feature",
  "properties": {
    "addr:full":"265 Walter Rd Morley WA 6062",
    "addr:housenumber":"265",
    "addr:postcode":"6062",
    "addr:street":"Walter Rd",
    "iso:country":"AU",
    "sg:address":"265 Walter Rd",
    "sg:city":"Morley",
    "sg:classifiers":[
        {
            "category":"Deli",
            "type":"Food & Drink"
        }
    ],
    "sg:phone":"+61 8 9276 1151",
    "sg:postcode":"6062",
    "sg:province":"WA",
    "sg:tags":[
        "delicatessen"
    ],
    "wof:name":"Morley Delicatessen",
    "wof:placetype":"venue"
},
  "geometry": {"coordinates":[115.897743225,-31.8945217133],"type":"Point"}
}