{
  "type": "Feature",
  "properties": {
    "addr:full":"41 Machinery Drv Tweed Heads NSW 2485",
    "addr:postcode":"2485",
    "addr:street":"Machinery Drv",
    "iso:country":"AU",
    "sg:address":"41 Machinery Drv",
    "sg:city":"Tweed Heads",
    "sg:classifiers":[
        {
            "category":"Wholesale",
            "subcategory":"Electrical",
            "type":"Manufacturing & Wholesale Goods"
        }
    ],
    "sg:phone":"+61 7 5524 4488",
    "sg:postcode":"2485",
    "sg:province":"NSW",
    "sg:tags":[
        "wholesaler"
    ],
    "wof:name":"Haymans Electrical",
    "wof:placetype":"venue"
},
  "geometry": {"coordinates":[153.54278564399999,-28.2030124664],"type":"Point"}
}