{
  "type": "Feature",
  "properties": {
    "addr:full":"Lot 5 Bucholz Rd Kabra QLD 4702",
    "addr:postcode":"4702",
    "addr:street":"Bucholz Rd",
    "iso:country":"AU",
    "sg:address":"Lot 5 Bucholz Rd",
    "sg:city":"Kabra",
    "sg:classifiers":[
        {
            "category":"Building & Trades",
            "subcategory":"Construction",
            "type":"Services"
        }
    ],
    "sg:phone":"+61 7 4933 2591",
    "sg:postcode":"4702",
    "sg:province":"QLD",
    "sg:tags":[
        "earth",
        "excavating",
        "moving",
        "contractor"
    ],
    "wof:name":"Titmarsh Trevor",
    "wof:placetype":"venue"
},
  "geometry": {"coordinates":[150.390335083,-23.4742164612],"type":"Point"}
}