{
  "type": "Feature",
  "properties": {
    "addr:full":"Riordonvale Rd Airlie Beach QLD 4802",
    "addr:postcode":"4802",
    "addr:street":"Riordonvale Rd",
    "iso:country":"AU",
    "sg:address":"Riordonvale Rd",
    "sg:city":"Airlie Beach",
    "sg:classifiers":[
        {
            "category":"Wholesale",
            "subcategory":"Painting Supplies",
            "type":"Manufacturing & Wholesale Goods"
        }
    ],
    "sg:phone":"+61 7 4946 1312",
    "sg:postcode":"4802",
    "sg:province":"QLD",
    "sg:tags":[
        "product",
        "cleaning"
    ],
    "wof:name":"Amway of Australia Distributors",
    "wof:placetype":"venue"
},
  "geometry": {"coordinates":[148.66110229500001,-20.3004894257],"type":"Point"}
}