{
  "type": "Feature",
  "properties": {
    "iso:country":"AU",
    "sg:address":"PO Box 106",
    "sg:city":"Kingston",
    "sg:classifiers":[
        {
            "category":"Home & Garden",
            "subcategory":"Building Materials",
            "type":"Retail Goods"
        }
    ],
    "sg:phone":"+61 7 5541 2327",
    "sg:postcode":"4114",
    "sg:province":"QLD",
    "sg:tags":[
        "pre-mixed",
        "concrete"
    ],
    "wof:name":"Sunmix Concrete Pty Ltd",
    "wof:placetype":"venue"
},
  "geometry": {"coordinates":[153.11424255399999,-27.6566905975],"type":"Point"}
}