{
  "type": "Feature",
  "properties": {
    "addr:full":"121 Belmore St Yarrawonga VIC 3730",
    "addr:housenumber":"121",
    "addr:postcode":"3730",
    "addr:street":"Belmore St",
    "iso:country":"AU",
    "sg:address":"121 Belmore St",
    "sg:city":"Yarrawonga",
    "sg:classifiers":[
        {
            "category":"Personal",
            "subcategory":"Beauty Salon",
            "type":"Services"
        }
    ],
    "sg:phone":"+61 3 5743 2602",
    "sg:postcode":"3730",
    "sg:province":"VIC",
    "sg:tags":[
        "hairdresser"
    ],
    "wof:name":"Salon 121",
    "wof:placetype":"venue"
},
  "geometry": {"coordinates":[146.00421142600001,-36.0136146545],"type":"Point"}
}