{
  "type": "Feature",
  "properties": {
    "addr:full":"47 Lexton Rd Box Hill VIC 3128",
    "addr:housenumber":"47",
    "addr:postcode":"3128",
    "addr:street":"Lexton Rd",
    "iso:country":"AU",
    "sg:address":"47 Lexton Rd",
    "sg:city":"Box Hill",
    "sg:classifiers":[
        {
            "category":"Building & Trades",
            "subcategory":"Cleaning & Sanitation",
            "type":"Services"
        }
    ],
    "sg:phone":"+61 3 9897 1688",
    "sg:postcode":"3128",
    "sg:province":"VIC",
    "sg:tags":[
        "cleaner",
        "repairer",
        "roof"
    ],
    "wof:name":"Roofshield Melbourne",
    "wof:placetype":"venue"
},
  "geometry": {"coordinates":[145.13638305699999,-37.811958313],"type":"Point"}
}