{
  "type": "Feature",
  "properties": {
    "iso:country":"AU",
    "sg:address":"Peachey Rd",
    "sg:city":"Elizabeth",
    "sg:classifiers":[
        {
            "category":"Manufacturing",
            "subcategory":"Building Materials",
            "type":"Manufacturing & Wholesale Goods"
        }
    ],
    "sg:phone":"+61 8 8255 3777",
    "sg:postcode":"5112",
    "sg:province":"SA",
    "sg:tags":[
        "adhesive",
        "tape"
    ],
    "wof:name":"Gardiner Australia Pty Ltd",
    "wof:placetype":"venue"
},
  "geometry": {"coordinates":[138.66166687,-34.7102928162],"type":"Point"}
}