{
  "type": "Feature",
  "properties": {
    "addr:full":"222 Safety Bay Rd Safety Bay WA 6169",
    "addr:postcode":"6169",
    "addr:street":"Safety Bay Rd",
    "iso:country":"AU",
    "sg:address":"222 Safety Bay Rd",
    "sg:city":"Safety Bay",
    "sg:classifiers":[
        {
            "category":"Professional",
            "subcategory":"Art Services",
            "type":"Services"
        }
    ],
    "sg:phone":"+61 8 9592 6922",
    "sg:postcode":"6169",
    "sg:province":"WA",
    "sg:tags":[
        "picture",
        "frame",
        "framing"
    ],
    "wof:name":"Tall Poppy Art Framers",
    "wof:placetype":"venue"
},
  "geometry": {"coordinates":[115.711349,-32.302944],"type":"Point"}
}