{
  "type": "Feature",
  "properties": {
    "iso:country":"AU",
    "sg:address":"26 Dodgin St",
    "sg:city":"Wynyard",
    "sg:classifiers":[
        {
            "category":"Building & Trades",
            "subcategory":"Construction",
            "type":"Services"
        }
    ],
    "sg:phone":"+61 400 108 694",
    "sg:postcode":"7325",
    "sg:province":"TAS",
    "sg:tags":[
        "joiner",
        "carpenter"
    ],
    "wof:name":"Steve Marijic Building & Carpentry Services",
    "wof:placetype":"venue"
},
  "geometry": {"coordinates":[145.732193,-40.99012],"type":"Point"}
}