{
  "type": "Feature",
  "properties": {
    "addr:full":"Preston Rd Collie WA 6225",
    "addr:postcode":"6225",
    "addr:street":"Preston Rd",
    "iso:country":"AU",
    "sg:address":"Preston Rd",
    "sg:city":"Collie",
    "sg:classifiers":[
        {
            "category":"Farming",
            "subcategory":"Farm",
            "type":"Manufacturing & Wholesale Goods"
        }
    ],
    "sg:phone":"+61 8 9734 5680",
    "sg:postcode":"6225",
    "sg:province":"WA",
    "sg:tags":[
        "farmer"
    ],
    "wof:name":"Hoddell T W & A L",
    "wof:placetype":"venue"
},
  "geometry": {"coordinates":[116.154037,-33.366085],"type":"Point"}
}