{
  "type": "Feature",
  "properties": {
    "iso:country":"AU",
    "sg:address":"6 Australia St",
    "sg:city":"Camperdown",
    "sg:classifiers":[
        {
            "category":"Food & Beverages",
            "subcategory":"Liquor & Beverages",
            "type":"Retail Goods"
        }
    ],
    "sg:phone":"+61 2 9550 5480",
    "sg:postcode":"2050",
    "sg:province":"NSW",
    "sg:tags":[
        "merchant",
        "spirit",
        "wine"
    ],
    "wof:name":"Winebond",
    "wof:placetype":"venue"
},
  "geometry": {"coordinates":[151.174896,-33.888275],"type":"Point"}
}