{
  "type": "Feature",
  "properties": {
    "addr:full":"25 Northpoint St North Sydney NSW 2060",
    "addr:housenumber":"25",
    "addr:postcode":"2060",
    "addr:street":"Northpoint St",
    "iso:country":"AU",
    "sg:address":"25 Northpoint St",
    "sg:city":"North Sydney",
    "sg:classifiers":[
        {
            "category":"Personal",
            "subcategory":"Shoe Repair & Shine",
            "type":"Services"
        }
    ],
    "sg:phone":"+61 2 9922 7763",
    "sg:postcode":"2060",
    "sg:province":"NSW",
    "sg:tags":[
        "footwear"
    ],
    "wof:name":"T.J Shoe Repairs",
    "wof:placetype":"venue"
},
  "geometry": {"coordinates":[151.198028564,-33.8181915283],"type":"Point"}
}