{
  "type": "Feature",
  "properties": {
    "iso:country":"AU",
    "sg:address":"PO Box 345",
    "sg:city":"Windsor",
    "sg:classifiers":[
        {
            "category":"Professional",
            "subcategory":"Testing Lab",
            "type":"Services"
        }
    ],
    "sg:phone":"+61 2 4578 4588",
    "sg:postcode":"2756",
    "sg:province":"NSW",
    "sg:tags":[
        "soil",
        "investigation"
    ],
    "wof:name":"Naturelink Environmental Services Pty Ltd",
    "wof:placetype":"venue"
},
  "geometry": {"coordinates":[150.81382751500001,-33.6134490967],"type":"Point"}
}