{
  "type": "Feature",
  "properties": {
    "addr:full":"26 Sydney St Mackay QLD 4740",
    "addr:housenumber":"26",
    "addr:postcode":"4740",
    "addr:street":"Sydney St",
    "iso:country":"AU",
    "sg:address":"26 Sydney St",
    "sg:city":"Mackay",
    "sg:classifiers":[
        {
            "category":"Wholesale",
            "subcategory":"Machinery & Supplies",
            "type":"Manufacturing & Wholesale Goods"
        }
    ],
    "sg:phone":"+61 7 4953 0466",
    "sg:postcode":"4740",
    "sg:province":"QLD",
    "sg:tags":[
        "process",
        "instrument",
        "control"
    ],
    "wof:name":"Comtech Mackay Pty Ltd",
    "wof:placetype":"venue"
},
  "geometry": {"coordinates":[149.18602000000001,-21.149691],"type":"Point"}
}