{
  "type": "Feature",
  "properties": {
    "iso:country":"AU",
    "sg:address":"40 The Drv",
    "sg:city":"Bardon",
    "sg:classifiers":[
        {
            "category":"Government",
            "subcategory":"Post Office",
            "type":"Public Place"
        }
    ],
    "sg:phone":"+61 7 3220 0911",
    "sg:postcode":"4065",
    "sg:province":"QLD",
    "sg:tags":[
        "yoga"
    ],
    "wof:name":"Alexis Burns",
    "wof:placetype":"venue"
},
  "geometry": {"coordinates":[152.980667114,-27.4592723846],"type":"Point"}
}