{
  "type": "Feature",
  "properties": {
    "addr:full":"Shop 6 Village Cntr Rouse Hill NSW 2155",
    "addr:housenumber":"shop 6",
    "addr:postcode":"2155",
    "addr:street":"Village Cntr",
    "iso:country":"AU",
    "sg:address":"Shop 6 Village Cntr",
    "sg:city":"Rouse Hill",
    "sg:classifiers":[
        {
            "category":"Food & Beverages",
            "subcategory":"Fruits & Vegetables",
            "type":"Retail Goods"
        }
    ],
    "sg:phone":"+61 2 8824 9311",
    "sg:postcode":"2155",
    "sg:province":"NSW",
    "sg:tags":[
        "greengrocer",
        "fruiterer"
    ],
    "wof:name":"Franklins Family Supermarket",
    "wof:placetype":"venue"
},
  "geometry": {"coordinates":[150.92202758799999,-33.6771697998],"type":"Point"}
}