{
  "type": "Feature",
  "properties": {
    "iso:country":"AU",
    "sg:address":"2 Emslie St",
    "sg:city":"Charlestown",
    "sg:classifiers":[
        {
            "category":"Professional",
            "subcategory":"Accounting & Tax Preparation",
            "type":"Services"
        }
    ],
    "sg:phone":"+61 2 4923 4000",
    "sg:postcode":"2290",
    "sg:province":"NSW",
    "sg:tags":[
        "accountant",
        "auditor"
    ],
    "wof:name":"Kilpatrick Owen",
    "wof:placetype":"venue"
},
  "geometry": {"coordinates":[151.70111084000001,-32.9621772766],"type":"Point"}
}