{
  "type": "Feature",
  "properties": {
    "iso:country":"AU",
    "sg:address":"Lvl 17/ 201 Miller St",
    "sg:city":"North Sydney",
    "sg:classifiers":[
        {
            "category":"Organizations",
            "subcategory":"Membership Organization",
            "type":"Services"
        }
    ],
    "sg:phone":"+61 1800 015 458",
    "sg:postcode":"2059",
    "sg:province":"NSW",
    "sg:tags":[
        "recording",
        "system",
        "time"
    ],
    "wof:name":"Peoplekey",
    "wof:placetype":"venue"
},
  "geometry": {"coordinates":[151.207443,-33.836639],"type":"Point"}
}