{
  "type": "Feature",
  "properties": {
    "addr:full":"45 Beach St Kippa-Ring QLD 4021",
    "addr:housenumber":"45",
    "addr:postcode":"4021",
    "addr:street":"Beach St",
    "iso:country":"AU",
    "sg:address":"45 Beach St",
    "sg:city":"Kippa-Ring",
    "sg:classifiers":[
        {
            "category":"Wholesale",
            "subcategory":"Metals & Minerals",
            "type":"Manufacturing & Wholesale Goods"
        }
    ],
    "sg:phone":"+61 7 3284 5100",
    "sg:postcode":"4021",
    "sg:province":"QLD",
    "sg:tags":[
        "steel",
        "stainless",
        "product",
        "equipment"
    ],
    "wof:name":"Kaima Engineering",
    "wof:placetype":"venue"
},
  "geometry": {"coordinates":[153.09072900000001,-27.224907],"type":"Point"}
}