{
  "type": "Feature",
  "properties": {
    "addr:full":"237 Vincent St Cessnock NSW 2325",
    "addr:housenumber":"237",
    "addr:postcode":"2325",
    "addr:street":"Vincent St",
    "iso:country":"AU",
    "sg:address":"237 Vincent St",
    "sg:city":"Cessnock",
    "sg:classifiers":[
        {
            "category":"Manufacturing",
            "subcategory":"Motor Vehicles & Parts",
            "type":"Manufacturing & Wholesale Goods"
        }
    ],
    "sg:phone":"+61 2 4990 1177",
    "sg:postcode":"2325",
    "sg:province":"NSW",
    "sg:tags":[
        "engine",
        "equipment",
        "diesel"
    ],
    "wof:name":"Cessnock Diesel Service Pty Ltd",
    "wof:placetype":"venue"
},
  "geometry": {"coordinates":[151.35505676299999,-32.8406105042],"type":"Point"}
}