{
  "type": "Feature",
  "properties": {
    "addr:full":"340 Bong Bong St Bowral NSW 2576",
    "addr:housenumber":"340",
    "addr:postcode":"2576",
    "addr:street":"Bong Bong St",
    "iso:country":"AU",
    "sg:address":"340 Bong Bong St",
    "sg:city":"Bowral",
    "sg:classifiers":[
        {
            "category":"Shopping",
            "subcategory":"Clothing, Apparel, & Fashions",
            "type":"Retail Goods"
        }
    ],
    "sg:phone":"+61 2 4861 3613",
    "sg:postcode":"2576",
    "sg:province":"NSW",
    "sg:tags":[
        "menswear"
    ],
    "wof:name":"Brafel Mens Wear",
    "wof:placetype":"venue"
},
  "geometry": {"coordinates":[150.41778564399999,-34.4800338745],"type":"Point"}
}