{
  "type": "Feature",
  "properties": {
    "iso:country":"AU",
    "sg:address":"390 Brooker Ave",
    "sg:city":"Moonah",
    "sg:classifiers":[
        {
            "category":"Train Station",
            "subcategory":"Rail",
            "type":"Transportation"
        }
    ],
    "sg:phone":"+61 3 6273 2679",
    "sg:postcode":"7009",
    "sg:province":"TAS",
    "sg:tags":[
        "wallboard"
    ],
    "wof:name":"Foster Plastering",
    "wof:placetype":"venue"
},
  "geometry": {"coordinates":[147.304397583,-42.8399429321],"type":"Point"}
}