{
  "type": "Feature",
  "properties": {
    "addr:full":"51 Lower Jordan Hill Rd West Hobart TAS 7000",
    "addr:housenumber":"51",
    "addr:postcode":"7000",
    "addr:street":"Lower Jordan Hill Rd",
    "iso:country":"AU",
    "sg:address":"51 Lower Jordan Hill Rd",
    "sg:city":"West Hobart",
    "sg:classifiers":[
        {
            "category":"Manufacturing",
            "subcategory":"Food",
            "type":"Manufacturing & Wholesale Goods"
        }
    ],
    "sg:phone":"+61 439 973 078",
    "sg:postcode":"7000",
    "sg:province":"TAS",
    "sg:tags":[
        "function",
        "catering"
    ],
    "wof:name":"Salamanca Catering",
    "wof:placetype":"venue"
},
  "geometry": {"coordinates":[147.30772399899999,-42.874710083],"type":"Point"}
}