{
  "type": "Feature",
  "properties": {
    "addr:full":"6 Fleet St Laverton North VIC 3026",
    "addr:housenumber":"6",
    "addr:postcode":"3026",
    "addr:street":"Fleet St",
    "iso:country":"AU",
    "sg:address":"6 Fleet St",
    "sg:city":"Laverton North",
    "sg:classifiers":[
        {
            "category":"Home & Garden",
            "subcategory":"Building Materials",
            "type":"Retail Goods"
        }
    ],
    "sg:phone":"+61 3 9369 5522",
    "sg:postcode":"3026",
    "sg:province":"VIC",
    "sg:tags":[
        "fencing"
    ],
    "wof:name":"Dunn & Farrugia Fencing & Gates",
    "wof:placetype":"venue"
},
  "geometry": {"coordinates":[144.78384399999999,-37.842773],"type":"Point"}
}