{
  "type": "Feature",
  "properties": {
    "iso:country":"AU",
    "sg:address":"19 Hall St",
    "sg:city":"Newport",
    "sg:classifiers":[
        {
            "category":"Organizations",
            "subcategory":"Non-profit Organization",
            "type":"Services"
        }
    ],
    "sg:phone":"+61 3 9398 0846",
    "sg:postcode":"3015",
    "sg:province":"VIC",
    "sg:tags":[
        "support",
        "disability",
        "organisation"
    ],
    "wof:name":"Citizen Advocacy Western",
    "wof:placetype":"venue"
},
  "geometry": {"coordinates":[144.88395690900001,-37.8430290222],"type":"Point"}
}