{
  "type": "Feature",
  "properties": {
    "iso:country":"AU",
    "sg:address":"Factory 1 51 Reserve Rd",
    "sg:city":"Melton",
    "sg:classifiers":[
        {
            "category":"Arena",
            "subcategory":"Sports Club",
            "type":"Entertainment"
        }
    ],
    "sg:phone":"+61 3 9743 3686",
    "sg:postcode":"3337",
    "sg:province":"VIC",
    "sg:tags":[
        "defence",
        "supply",
        "self",
        "instruction",
        "martial art"
    ],
    "wof:name":"Melton Martial Arts Academy",
    "wof:placetype":"venue"
},
  "geometry": {"coordinates":[144.591003,-37.686642],"type":"Point"}
}