{
  "type": "Feature",
  "properties": {
    "addr:full":"Shop 7 Safeway Complex Sebastopol VIC 3356",
    "addr:housenumber":"shop 7",
    "addr:postcode":"3356",
    "iso:country":"AU",
    "sg:address":"Shop 7 Safeway Complex",
    "sg:city":"Sebastopol",
    "sg:classifiers":[
        {
            "category":"Food & Beverages",
            "subcategory":"Bakery",
            "type":"Retail Goods"
        }
    ],
    "sg:phone":"+61 3 5335 7988",
    "sg:postcode":"3356",
    "sg:province":"VIC",
    "sg:tags":[
        "baker"
    ],
    "wof:name":"Ballarat Bakery",
    "wof:placetype":"venue"
},
  "geometry": {"coordinates":[143.84077500000001,-37.598759],"type":"Point"}
}