{
  "type": "Feature",
  "properties": {
    "iso:country":"AU",
    "sg:address":"Mulgoa Rd ( Cnr Fairlight Rd)",
    "sg:city":"Mulgoa",
    "sg:classifiers":[
        {
            "category":"Health Services",
            "subcategory":"Doctor",
            "type":"Services"
        }
    ],
    "sg:phone":"+61 2 4773 8525",
    "sg:postcode":"2745",
    "sg:province":"NSW",
    "sg:tags":[
        "medical",
        "practitioner"
    ],
    "wof:name":"Mulgoa Medical Centre",
    "wof:placetype":"venue"
},
  "geometry": {"coordinates":[150.64923095699999,-33.8417854309],"type":"Point"}
}