{
  "type": "Feature",
  "properties": {
    "iso:country":"AU",
    "sg:address":"4 Itawara Pl",
    "sg:city":"Bridgewater",
    "sg:classifiers":[
        {
            "category":"Wholesale",
            "subcategory":"Apparel",
            "type":"Manufacturing & Wholesale Goods"
        }
    ],
    "sg:phone":"+61 1300 556 113",
    "sg:postcode":"5155",
    "sg:province":"SA",
    "sg:tags":[
        "wholesaler",
        "mfrs",
        "silo"
    ],
    "wof:name":"Silo Safe",
    "wof:placetype":"venue"
},
  "geometry": {"coordinates":[138.76937866200001,-35.0097885132],"type":"Point"}
}