{
  "type": "Feature",
  "properties": {
    "addr:full":"179 Port Rd Hindmarsh SA 5007",
    "addr:housenumber":"179",
    "addr:postcode":"5007",
    "addr:street":"Port Rd",
    "iso:country":"AU",
    "sg:address":"179 Port Rd",
    "sg:city":"Hindmarsh",
    "sg:classifiers":[
        {
            "category":"Home & Garden",
            "subcategory":"Furniture",
            "type":"Retail Goods"
        }
    ],
    "sg:phone":"+61 8 8340 2499",
    "sg:postcode":"5007",
    "sg:province":"SA",
    "sg:tags":[
        "business"
    ],
    "wof:name":"Hindmarsh Disposals",
    "wof:placetype":"venue"
},
  "geometry": {"coordinates":[138.57148742699999,-34.9044494629],"type":"Point"}
}