{
  "type": "Feature",
  "properties": {
    "addr:full":"Shop 6 Port Home Zone Centre Port Macquarie NSW 2444",
    "addr:housenumber":"shop 6",
    "addr:postcode":"2444",
    "addr:street":"Port Home Zone Centre",
    "iso:country":"AU",
    "sg:address":"Shop 6",
    "sg:city":"Port Home Zone Centre Port Macquarie",
    "sg:classifiers":[
        {
            "category":"Manufacturing",
            "subcategory":"Motor Vehicles & Parts",
            "type":"Manufacturing & Wholesale Goods"
        }
    ],
    "sg:phone":"+61 2 6584 9100",
    "sg:postcode":"2444",
    "sg:province":"NSW",
    "sg:tags":[
        "replacement"
    ],
    "wof:name":"Autobarn",
    "wof:placetype":"venue"
},
  "geometry": {"coordinates":[152.90817300000001,-31.4296],"type":"Point"}
}