{
  "type": "Feature",
  "properties": {
    "addr:full":"47 Ben Lomond St Aspley QLD 4034",
    "addr:housenumber":"47",
    "addr:postcode":"4034",
    "addr:street":"Ben Lomond St",
    "iso:country":"AU",
    "sg:address":"47 Ben Lomond St",
    "sg:city":"Aspley",
    "sg:classifiers":[
        {
            "category":"Professional",
            "subcategory":"Computer Services",
            "type":"Services"
        }
    ],
    "sg:phone":"+61 7 3862 9677",
    "sg:postcode":"4034",
    "sg:province":"QLD",
    "sg:tags":[
        "consultant",
        "system"
    ],
    "wof:name":"Triple J Vendors",
    "wof:placetype":"venue"
},
  "geometry": {"coordinates":[153.01161200000001,-27.366255],"type":"Point"}
}