{
  "type": "Feature",
  "properties": {
    "addr:full":"15 Maddox Crs Melville WA 6156",
    "addr:housenumber":"15",
    "addr:postcode":"6156",
    "addr:street":"Maddox Crs",
    "iso:country":"AU",
    "sg:address":"15 Maddox Crs",
    "sg:city":"Melville",
    "sg:classifiers":[
        {
            "category":"Health Services",
            "subcategory":"Health Practitioner",
            "type":"Services"
        }
    ],
    "sg:phone":"+61 8 9330 6317",
    "sg:postcode":"6156",
    "sg:province":"WA",
    "sg:tags":[
        "physiotherapist"
    ],
    "wof:name":"Lee Norma",
    "wof:placetype":"venue"
},
  "geometry": {"coordinates":[115.80201,-32.042488],"type":"Point"}
}