{
  "type": "Feature",
  "properties": {
    "addr:full":"1st Floor 10 Bayfield St Rosny Park TAS 7018",
    "addr:housenumber":"10",
    "addr:postcode":"7018",
    "addr:street":"Bayfield St",
    "iso:country":"AU",
    "sg:address":"1st Floor 10 Bayfield St",
    "sg:city":"Rosny Park",
    "sg:classifiers":[
        {
            "category":"Professional",
            "subcategory":"Accounting & Tax Preparation",
            "type":"Services"
        }
    ],
    "sg:phone":"+61 3 6244 5888",
    "sg:postcode":"7018",
    "sg:province":"TAS",
    "sg:tags":[
        "consultant",
        "taxation"
    ],
    "wof:name":"Wiaczek Richard",
    "wof:placetype":"venue"
},
  "geometry": {"coordinates":[147.370529175,-42.8664245605],"type":"Point"}
}