{
  "type": "Feature",
  "properties": {
    "addr:full":"43 Dandenong St Dandenong VIC 3175",
    "addr:housenumber":"43",
    "addr:postcode":"3175",
    "addr:street":"Dandenong St",
    "iso:country":"AU",
    "sg:address":"43 Dandenong St",
    "sg:city":"Dandenong",
    "sg:classifiers":[
        {
            "category":"Building & Trades",
            "subcategory":"Equipment Rental",
            "type":"Services"
        }
    ],
    "sg:phone":"+61 3 9793 2533",
    "sg:postcode":"3175",
    "sg:province":"VIC",
    "sg:tags":[
        "hire",
        "catering"
    ],
    "wof:name":"Pride Events Pty Ltd",
    "wof:placetype":"venue"
},
  "geometry": {"coordinates":[145.199615478,-37.9942207336],"type":"Point"}
}