{
  "type": "Feature",
  "properties": {
    "addr:full":"40 Macquarie St Parramatta NSW 2150",
    "addr:housenumber":"40",
    "addr:postcode":"2150",
    "addr:street":"Macquarie St",
    "iso:country":"AU",
    "sg:address":"40 Macquarie St",
    "sg:city":"Parramatta",
    "sg:classifiers":[
        {
            "category":"Education",
            "subcategory":"Junior College",
            "type":"Public Place"
        }
    ],
    "sg:phone":"+61 2 9635 4077",
    "sg:postcode":"2150",
    "sg:province":"NSW",
    "sg:tags":[
        "business"
    ],
    "wof:name":"Academy of Learning",
    "wof:placetype":"venue"
},
  "geometry": {"coordinates":[150.9425354,-33.8705253601],"type":"Point"}
}