{
  "type": "Feature",
  "properties": {
    "iso:country":"AU",
    "sg:address":"65 Spurway St",
    "sg:city":"Ermington",
    "sg:classifiers":[
        {
            "category":"Social Services",
            "subcategory":"Child Care",
            "type":"Services"
        }
    ],
    "sg:phone":"+61 2 9638 2262",
    "sg:postcode":"2115",
    "sg:province":"NSW",
    "sg:tags":[
        "support",
        "health"
    ],
    "wof:name":"Early Childhood Health Centres",
    "wof:placetype":"venue"
},
  "geometry": {"coordinates":[151.05531310999999,-33.8100242615],"type":"Point"}
}