{
  "type": "Feature",
  "properties": {
    "addr:full":"47 Diamond Ave Kallangur QLD 4503",
    "addr:housenumber":"47",
    "addr:postcode":"4503",
    "addr:street":"Diamond Ave",
    "iso:country":"AU",
    "sg:address":"47 Diamond Ave",
    "sg:city":"Kallangur",
    "sg:classifiers":[
        {
            "category":"Manufacturing",
            "subcategory":"Tools & Machinery",
            "type":"Manufacturing & Wholesale Goods"
        }
    ],
    "sg:phone":"+61 416 026 687",
    "sg:postcode":"4503",
    "sg:province":"QLD",
    "wof:name":"Tools Direct",
    "wof:placetype":"venue"
},
  "geometry": {"coordinates":[153.00581359899999,-27.2483215332],"type":"Point"}
}