{
  "type": "Feature",
  "properties": {
    "addr:full":"U13/ 633-634 Mitcham Rd Vermont VIC 3133",
    "addr:housenumber":"/ 633-634",
    "addr:postcode":"3133",
    "addr:street":"Mitcham Rd",
    "iso:country":"AU",
    "sg:address":"U13/ 633-634 Mitcham Rd",
    "sg:city":"Vermont",
    "sg:classifiers":[
        {
            "category":"Organizations",
            "subcategory":"Membership Organization",
            "type":"Services"
        }
    ],
    "sg:phone":"+61 3 9874 8057",
    "sg:postcode":"3133",
    "sg:province":"VIC",
    "sg:tags":[
        "support",
        "health",
        "organisation"
    ],
    "wof:name":"Nurse Assist Post Acute Care Services",
    "wof:placetype":"venue"
},
  "geometry": {"coordinates":[145.19483947800001,-37.8323249817],"type":"Point"}
}