{
  "type": "Feature",
  "properties": {
    "iso:country":"AU",
    "sg:address":"Central 3/ 254 Canterbury Rd",
    "sg:city":"Bayswater",
    "sg:classifiers":[
        {
            "category":"Landmark",
            "subcategory":"Scenic View",
            "type":"Public Place"
        }
    ],
    "sg:phone":"+61 3 9729 0485",
    "sg:postcode":"3153",
    "sg:province":"VIC",
    "sg:tags":[
        "staircase",
        "handrail"
    ],
    "wof:name":"Kingco Engineering Pty Ltd",
    "wof:placetype":"venue"
},
  "geometry": {"coordinates":[145.27476501500001,-37.8301429749],"type":"Point"}
}