{
  "type": "Feature",
  "properties": {
    "iso:country":"AU",
    "sg:address":"621 Whitehorse Rd",
    "sg:city":"Mitcham",
    "sg:classifiers":[
        {
            "category":"Wholesale",
            "subcategory":"Metals & Minerals",
            "type":"Manufacturing & Wholesale Goods"
        }
    ],
    "sg:phone":"+61 3 9874 1122",
    "sg:postcode":"3132",
    "sg:province":"VIC",
    "sg:tags":[
        "steel",
        "merchant"
    ],
    "wof:name":"Danks Steel",
    "wof:placetype":"venue"
},
  "geometry": {"coordinates":[145.2059021,-37.8161468506],"type":"Point"}
}