{
  "type": "Feature",
  "properties": {
    "iso:country":"AU",
    "sg:address":"Shop 1046/ 28 Eenie Creek Rd",
    "sg:city":"Noosaville",
    "sg:classifiers":[
        {
            "category":"Shopping",
            "subcategory":"Clothing, Apparel, & Fashions",
            "type":"Retail Goods"
        }
    ],
    "sg:phone":"+61 7 5473 0705",
    "sg:postcode":"4566",
    "sg:province":"QLD",
    "sg:tags":[
        "menswear"
    ],
    "wof:name":"Tom Browns Menswear Pty Ltd",
    "wof:placetype":"venue"
},
  "geometry": {"coordinates":[153.047485352,-26.4120159149],"type":"Point"}
}