{
  "type": "Feature",
  "properties": {
    "iso:country":"AU",
    "sg:address":"Level 7/ 157 Ann St",
    "sg:city":"Brisbane",
    "sg:classifiers":[
        {
            "category":"Parking",
            "type":"Transportation"
        }
    ],
    "sg:phone":"+61 7 3229 1860",
    "sg:postcode":"4000",
    "sg:province":"QLD",
    "wof:name":"Secure Parking",
    "wof:placetype":"venue"
},
  "geometry": {"coordinates":[153.02479553200001,-27.4675636292],"type":"Point"}
}