{
  "type": "Feature",
  "properties": {
    "iso:country":"AU",
    "sg:address":"Suite 1/ 210 Homer St",
    "sg:city":"Earlwood",
    "sg:classifiers":[
        {
            "category":"Professional",
            "subcategory":"Business Services",
            "type":"Services"
        }
    ],
    "sg:phone":"+61 2 9558 8944",
    "sg:postcode":"2206",
    "sg:province":"NSW",
    "sg:tags":[
        "drafting"
    ],
    "wof:name":"Design Studio 407",
    "wof:placetype":"venue"
},
  "geometry": {"coordinates":[151.123367,-33.928036],"type":"Point"}
}