{
  "type": "Feature",
  "properties": {
    "addr:full":"72 Stranraeer Drv St Andrews NSW 2566",
    "addr:housenumber":"72",
    "addr:postcode":"2566",
    "addr:street":"Stranraeer Drv",
    "iso:country":"AU",
    "sg:address":"72 Stranraeer Drv St",
    "sg:city":"Andrews",
    "sg:classifiers":[
        {
            "category":"Autos & Motor Vehicles",
            "subcategory":"Fuel & Gas Station",
            "type":"Retail Goods"
        }
    ],
    "sg:phone":"+61 2 9603 7500",
    "sg:postcode":"2566",
    "sg:province":"NSW",
    "wof:name":"Joe & Tonys Service Centre Pty Ltd",
    "wof:placetype":"venue"
},
  "geometry": {"coordinates":[150.827667236,-34.0289001465],"type":"Point"}
}