{
  "type": "Feature",
  "properties": {
    "iso:country":"AU",
    "sg:address":"10 Geel St",
    "sg:city":"Bentleigh",
    "sg:classifiers":[
        {
            "category":"Education",
            "subcategory":"Music School",
            "type":"Public Place"
        }
    ],
    "sg:phone":"+61 3 9557 1561",
    "sg:postcode":"3204",
    "sg:province":"VIC",
    "sg:tags":[
        "choir",
        "bands",
        "orchestra"
    ],
    "wof:name":"Concertino Trio",
    "wof:placetype":"venue"
},
  "geometry": {"coordinates":[145.044724,-37.925812],"type":"Point"}
}