{
  "type": "Feature",
  "properties": {
    "addr:full":"420 Hargreaves St Bendigo VIC 3550",
    "addr:housenumber":"420",
    "addr:postcode":"3550",
    "addr:street":"Hargreaves St",
    "iso:country":"AU",
    "sg:address":"420 Hargreaves St",
    "sg:city":"Bendigo",
    "sg:classifiers":[
        {
            "category":"Organizations",
            "subcategory":"Non-profit Organization",
            "type":"Services"
        }
    ],
    "sg:phone":"+61 3 5444 0777",
    "sg:postcode":"3550",
    "sg:province":"VIC",
    "sg:tags":[
        "environmental",
        "organisation",
        "conservation"
    ],
    "wof:name":"Conservation Volunteers Australia",
    "wof:placetype":"venue"
},
  "geometry": {"coordinates":[144.27670288100001,-36.7624168396],"type":"Point"}
}