{
  "type": "Feature",
  "properties": {
    "addr:full":"80 Dixon St Lambton NSW 2299",
    "addr:housenumber":"80",
    "addr:postcode":"2299",
    "addr:street":"Dixon St",
    "iso:country":"AU",
    "sg:address":"80 Dixon St",
    "sg:city":"Lambton",
    "sg:classifiers":[
        {
            "category":"Home & Garden",
            "subcategory":"Building Materials",
            "type":"Retail Goods"
        }
    ],
    "sg:phone":"+61 2 4952 4719",
    "sg:postcode":"2299",
    "sg:province":"NSW",
    "sg:tags":[
        "lawn",
        "cutting",
        "maintenance"
    ],
    "wof:name":"Kennaway Bob",
    "wof:placetype":"venue"
},
  "geometry": {"coordinates":[151.705154419,-32.9101905823],"type":"Point"}
}