{
  "type": "Feature",
  "properties": {
    "addr:full":"Lewis St Cherry Gardens SA 5157",
    "addr:postcode":"5157",
    "addr:street":"Lewis St Cherry Gardens",
    "iso:country":"AU",
    "sg:address":"Lewis St",
    "sg:city":"Cherry Gardens",
    "sg:classifiers":[
        {
            "category":"Building & Trades",
            "subcategory":"Plumbing",
            "type":"Services"
        }
    ],
    "sg:phone":"+61 8 8370 7184",
    "sg:postcode":"5157",
    "sg:province":"SA",
    "sg:tags":[
        "repair",
        "appliance",
        "system",
        "heating"
    ],
    "wof:name":"Watson Heating & Cooling Installations",
    "wof:placetype":"venue"
},
  "geometry": {"coordinates":[138.64588928200001,-35.0757331848],"type":"Point"}
}