{
  "type": "Feature",
  "properties": {
    "addr:full":"52 Pyrmont Bridge Rd Camperdown NSW 2050",
    "addr:housenumber":"52",
    "addr:postcode":"2050",
    "addr:street":"Pyrmont Bridge Rd",
    "iso:country":"AU",
    "sg:address":"52 Pyrmont Bridge Rd",
    "sg:city":"Camperdown",
    "sg:classifiers":[
        {
            "category":"Home & Garden",
            "subcategory":"Home Furnishings",
            "type":"Retail Goods"
        }
    ],
    "sg:phone":"+61 2 9660 7557",
    "sg:postcode":"2050",
    "sg:province":"NSW",
    "sg:tags":[
        "shower",
        "screen"
    ],
    "wof:name":"Renovation Boys",
    "wof:placetype":"venue"
},
  "geometry": {"coordinates":[151.17588799999999,-33.885433],"type":"Point"}
}