{
  "type": "Feature",
  "properties": {
    "iso:country":"AU",
    "sg:address":"U 7/ 90 Heathcote Rd",
    "sg:city":"Moorebank",
    "sg:classifiers":[
        {
            "category":"Building & Trades",
            "subcategory":"Construction",
            "type":"Services"
        }
    ],
    "sg:phone":"+61 2 9601 6563",
    "sg:postcode":"2170",
    "sg:province":"NSW",
    "sg:tags":[
        "window",
        "aluminium"
    ],
    "wof:name":"Imperial Windows Pty Ltd",
    "wof:placetype":"venue"
},
  "geometry": {"coordinates":[150.93746948200001,-33.9371948242],"type":"Point"}
}