{
  "type": "Feature",
  "properties": {
    "addr:full":"Crn Plenty & Greenhills Rds Bundoora VIC 3083",
    "addr:postcode":"3083",
    "addr:street":"Crn",
    "iso:country":"AU",
    "sg:address":"Crn Plenty & Greenhills Rds",
    "sg:city":"Bundoora",
    "sg:classifiers":[
        {
            "category":"Health Services",
            "subcategory":"Doctor",
            "type":"Services"
        }
    ],
    "sg:phone":"+61 3 9467 1937",
    "sg:postcode":"3083",
    "sg:province":"VIC",
    "sg:tags":[
        "medical",
        "practitioner"
    ],
    "wof:name":"Zahirovic Avdo Mr",
    "wof:placetype":"venue"
},
  "geometry": {"coordinates":[145.058761597,-37.6987876892],"type":"Point"}
}