{
  "type": "Feature",
  "properties": {
    "iso:country":"AU",
    "sg:address":"PO Box 219",
    "sg:city":"Mandurah",
    "sg:classifiers":[
        {
            "category":"Arena",
            "subcategory":"Indoor Arena",
            "type":"Entertainment"
        }
    ],
    "sg:phone":"+61 8 9535 6251",
    "sg:postcode":"6210",
    "sg:province":"WA",
    "sg:tags":[
        "club",
        "angling"
    ],
    "wof:name":"Mandurah Offshore Fishing And Sailing Club Inc",
    "wof:placetype":"venue"
},
  "geometry": {"coordinates":[115.784737,-32.509258],"type":"Point"}
}