{
  "type": "Feature",
  "properties": {
    "iso:country":"AU",
    "sg:address":"Cannon Park Complex High Range Drv",
    "sg:city":"Thuringowa Central",
    "sg:classifiers":[
        {
            "category":"Food & Beverages",
            "subcategory":"Bakery",
            "type":"Retail Goods"
        }
    ],
    "sg:phone":"+61 7 4723 1750",
    "sg:postcode":"4817",
    "sg:province":"QLD",
    "sg:tags":[
        "cake",
        "shop",
        "pastry"
    ],
    "wof:name":"Cold Rock Ice Creamery",
    "wof:placetype":"venue"
},
  "geometry": {"coordinates":[146.724823,-19.319843],"type":"Point"}
}