{
  "type": "Feature",
  "properties": {
    "iso:country":"AU",
    "sg:address":"4/ 226 Watkins Rd",
    "sg:city":"Wangi Wangi",
    "sg:classifiers":[
        {
            "category":"Personal",
            "subcategory":"Beauty Salon",
            "type":"Services"
        }
    ],
    "sg:phone":"+61 2 4975 5122",
    "sg:postcode":"2267",
    "sg:province":"NSW",
    "sg:tags":[
        "hairdresser"
    ],
    "wof:name":"The Hair Retreat Of Wangi",
    "wof:placetype":"venue"
},
  "geometry": {"coordinates":[151.588593,-33.069572],"type":"Point"}
}