{
  "type": "Feature",
  "properties": {
    "addr:full":"219 Morris Rd Rothwell QLD 4022",
    "addr:housenumber":"219",
    "addr:postcode":"4022",
    "addr:street":"Morris Rd",
    "iso:country":"AU",
    "sg:address":"219 Morris Rd",
    "sg:city":"Rothwell",
    "sg:classifiers":[
        {
            "category":"Building & Trades",
            "subcategory":"Construction",
            "type":"Services"
        }
    ],
    "sg:phone":"+61 7 3204 0006",
    "sg:postcode":"4022",
    "sg:province":"QLD",
    "sg:tags":[
        "contractor"
    ],
    "wof:name":"Brett Morris Homes Pty Ltd",
    "wof:placetype":"venue"
},
  "geometry": {"coordinates":[153.059067,-27.212015],"type":"Point"}
}