{
  "type": "Feature",
  "properties": {
    "iso:country":"AU",
    "sg:address":"6 Willunga St",
    "sg:city":"Eden Hills",
    "sg:classifiers":[
        {
            "category":"Building & Trades",
            "subcategory":"Construction",
            "type":"Services"
        }
    ],
    "sg:phone":"+61 8 8278 6930",
    "sg:postcode":"5050",
    "sg:province":"SA",
    "sg:tags":[
        "earth",
        "excavating",
        "moving",
        "contractor"
    ],
    "wof:name":"Neil Philbey",
    "wof:placetype":"venue"
},
  "geometry": {"coordinates":[138.60093699999999,-35.026005],"type":"Point"}
}