{
  "type": "Feature",
  "properties": {
    "iso:country":"AU",
    "sg:address":"6 Allen Pl",
    "sg:city":"Wetherill Park",
    "sg:classifiers":[
        {
            "category":"Home & Garden",
            "subcategory":"Kitchen Supply",
            "type":"Retail Goods"
        }
    ],
    "sg:phone":"+61 2 9756 3900",
    "sg:postcode":"2164",
    "sg:province":"NSW",
    "sg:tags":[
        "sharpening"
    ],
    "wof:name":"Toolco Australia Pty Ltd",
    "wof:placetype":"venue"
},
  "geometry": {"coordinates":[150.89941406200001,-33.8480796814],"type":"Point"}
}