{
  "type": "Feature",
  "properties": {
    "addr:full":"240a Hume Hwy Lansvale NSW 2166",
    "addr:housenumber":"240a",
    "addr:postcode":"2166",
    "addr:street":"Hume Hwy",
    "iso:country":"AU",
    "sg:address":"240a Hume Hwy",
    "sg:city":"Lansvale",
    "sg:classifiers":[
        {
            "category":"Autos & Motor Vehicles",
            "subcategory":"Automobile Sales",
            "type":"Retail Goods"
        }
    ],
    "sg:phone":"+61 2 9727 4222",
    "sg:postcode":"2166",
    "sg:province":"NSW",
    "sg:tags":[
        "car",
        "used"
    ],
    "wof:name":"Budget Autos",
    "wof:placetype":"venue"
},
  "geometry": {"coordinates":[150.95225524899999,-33.8978996277],"type":"Point"}
}