{
  "type": "Feature",
  "properties": {
    "iso:country":"AU",
    "sg:address":"George St",
    "sg:city":"Windsor",
    "sg:classifiers":[
        {
            "category":"Retail",
            "subcategory":"Storage",
            "type":"Services"
        }
    ],
    "sg:phone":"+61 429 149 993",
    "sg:postcode":"2756",
    "sg:province":"NSW",
    "sg:tags":[
        "removal",
        "furniture"
    ],
    "wof:name":"A.A Abway Removals",
    "wof:placetype":"venue"
},
  "geometry": {"coordinates":[150.81301879899999,-33.6125946045],"type":"Point"}
}