{
  "type": "Feature",
  "properties": {
    "iso:country":"AU",
    "sg:address":"2/ 28 Burley Cl",
    "sg:city":"Illawong",
    "sg:classifiers":[
        {
            "category":"Fast Food",
            "type":"Food & Drink"
        }
    ],
    "sg:phone":"+61 2 9543 2188",
    "sg:postcode":"2234",
    "sg:province":"NSW",
    "sg:tags":[
        "away",
        "take"
    ],
    "wof:name":"PGE Gourmet",
    "wof:placetype":"venue"
},
  "geometry": {"coordinates":[151.03378295900001,-33.9555435181],"type":"Point"}
}