{
  "type": "Feature",
  "properties": {
    "iso:country":"AU",
    "sg:address":"Shop 5/ 40 Simpson St",
    "sg:city":"Beerwah",
    "sg:classifiers":[
        {
            "category":"Cafe",
            "type":"Food & Drink"
        }
    ],
    "sg:phone":"+61 7 5494 0722",
    "sg:postcode":"4519",
    "sg:province":"QLD",
    "wof:name":"Garden Terrace Coffee Lounge",
    "wof:placetype":"venue"
},
  "geometry": {"coordinates":[152.958557,-26.853155],"type":"Point"}
}