{
  "type": "Feature",
  "properties": {
    "iso:country":"AU",
    "sg:address":"1 Shepherd Rd",
    "sg:city":"Swan Hill",
    "sg:classifiers":[
        {
            "category":"Real Estate",
            "subcategory":"Surveying",
            "type":"Services"
        }
    ],
    "sg:phone":"+61 3 5033 2344",
    "sg:postcode":"3585",
    "sg:province":"VIC",
    "sg:tags":[
        "map",
        "mapping"
    ],
    "wof:name":"Mapmaster Australia",
    "wof:placetype":"venue"
},
  "geometry": {"coordinates":[143.539536,-35.32753],"type":"Point"}
}