{
  "type": "Feature",
  "properties": {
    "addr:full":"18 Burns Rd Heathcote NSW 2233",
    "addr:housenumber":"18",
    "addr:postcode":"2233",
    "addr:street":"Burns Rd",
    "iso:country":"AU",
    "sg:address":"18 Burns Rd",
    "sg:city":"Heathcote",
    "sg:classifiers":[
        {
            "category":"Manufacturing",
            "subcategory":"Furniture",
            "type":"Manufacturing & Wholesale Goods"
        }
    ],
    "sg:phone":"+61 2 9548 4888",
    "sg:postcode":"2233",
    "sg:province":"NSW",
    "sg:tags":[
        "mfrs",
        "supply"
    ],
    "wof:name":"Furnware Trading Co",
    "wof:placetype":"venue"
},
  "geometry": {"coordinates":[150.99615478499999,-34.0974731445],"type":"Point"}
}