{
  "type": "Feature",
  "properties": {
    "iso:country":"AU",
    "sg:address":"36 Railway Pde",
    "sg:city":"Bayswater",
    "sg:classifiers":[
        {
            "category":"Professional",
            "type":"Services"
        }
    ],
    "sg:phone":"+61 8 9370 2898",
    "sg:postcode":"6053",
    "sg:province":"WA",
    "sg:tags":[
        "spray",
        "painting"
    ],
    "wof:name":"One Stop Autos",
    "wof:placetype":"venue"
},
  "geometry": {"coordinates":[115.912216187,-31.9177417755],"type":"Point"}
}