{
  "type": "Feature",
  "properties": {
    "addr:full":"Cnr Evans & Macedon Sts Sunbury VIC 3429",
    "addr:postcode":"3429",
    "addr:street":"Cnr",
    "iso:country":"AU",
    "sg:address":"Cnr Evans & Macedon Sts",
    "sg:city":"Sunbury",
    "sg:classifiers":[
        {
            "category":"Food & Beverages",
            "subcategory":"Liquor & Beverages",
            "type":"Retail Goods"
        }
    ],
    "sg:phone":"+61 3 9744 2508",
    "sg:postcode":"3429",
    "sg:province":"VIC",
    "sg:tags":[
        "store"
    ],
    "wof:name":"Liquorland",
    "wof:placetype":"venue"
},
  "geometry": {"coordinates":[144.73263549800001,-37.5778999329],"type":"Point"}
}