{
  "type": "Feature",
  "properties": {
    "addr:full":"7/ 112 Millswyn St South Yarra VIC 3141",
    "addr:housenumber":"/ 112",
    "addr:postcode":"3141",
    "addr:street":"Millswyn St",
    "iso:country":"AU",
    "sg:address":"7/ 112 Millswyn St",
    "sg:city":"South Yarra",
    "sg:classifiers":[
        {
            "category":"Manufacturing",
            "subcategory":"Printing",
            "type":"Manufacturing & Wholesale Goods"
        }
    ],
    "sg:phone":"+61 3 9867 3692",
    "sg:postcode":"3141",
    "sg:province":"VIC",
    "sg:tags":[
        "wholesaler",
        "mfrs",
        "greeting",
        "card"
    ],
    "wof:name":"Veritas Productions Australia",
    "wof:placetype":"venue"
},
  "geometry": {"coordinates":[144.980743408,-37.8346405029],"type":"Point"}
}