{
  "type": "Feature",
  "properties": {
    "iso:country":"AU",
    "sg:address":"101 Wombeyan Caves Rd",
    "sg:city":"Mittagong",
    "sg:classifiers":[
        {
            "category":"Professional",
            "subcategory":"Engineering",
            "type":"Services"
        }
    ],
    "sg:phone":"+61 2 4878 5361",
    "sg:postcode":"2575",
    "sg:province":"NSW",
    "sg:tags":[
        "engineer"
    ],
    "wof:name":"Counterpart Engineering",
    "wof:placetype":"venue"
},
  "geometry": {"coordinates":[150.433395386,-34.4518966675],"type":"Point"}
}