{
  "type": "Feature",
  "properties": {
    "addr:full":"363 Pitt St Sydney NSW 2000",
    "addr:housenumber":"363",
    "addr:postcode":"2000",
    "addr:street":"Pitt St",
    "iso:country":"AU",
    "sg:address":"363 Pitt St",
    "sg:city":"Sydney",
    "sg:classifiers":[
        {
            "category":"Real Estate",
            "subcategory":"Surveying",
            "type":"Services"
        }
    ],
    "sg:phone":"+61 2 9267 9728",
    "sg:postcode":"2000",
    "sg:province":"NSW",
    "sg:tags":[
        "surveyor",
        "land"
    ],
    "wof:name":"Association Of Consulting Surveyors New South Wales Inc",
    "wof:placetype":"venue"
},
  "geometry": {"coordinates":[151.20773315400001,-33.8758850098],"type":"Point"}
}