{
  "type": "Feature",
  "properties": {
    "iso:country":"AU",
    "sg:address":"Level 1/ 175 Pitt St",
    "sg:city":"Sydney",
    "sg:classifiers":[
        {
            "category":"Cafe",
            "type":"Food & Drink"
        }
    ],
    "sg:phone":"+61 2 9221 1644",
    "sg:postcode":"2000",
    "sg:province":"NSW",
    "wof:name":"GG Espresso",
    "wof:placetype":"venue"
},
  "geometry": {"coordinates":[151.20814514200001,-33.8687782288],"type":"Point"}
}