{
  "type": "Feature",
  "properties": {
    "addr:full":"2 Anne Marie Pl Carlingford NSW 2118",
    "addr:housenumber":"2",
    "addr:postcode":"2118",
    "addr:street":"Anne Marie Pl",
    "iso:country":"AU",
    "sg:address":"2 Anne Marie Pl",
    "sg:city":"Carlingford",
    "sg:classifiers":[
        {
            "category":"Real Estate",
            "subcategory":"Real Estate Services",
            "type":"Services"
        }
    ],
    "sg:phone":"+61 2 9873 2506",
    "sg:postcode":"2118",
    "sg:province":"NSW",
    "sg:tags":[
        "valuer"
    ],
    "wof:name":"Demographic Analysis & Property Services",
    "wof:placetype":"venue"
},
  "geometry": {"coordinates":[151.03802490199999,-33.768787384],"type":"Point"}
}