{
  "type": "Feature",
  "properties": {
    "addr:full":"30-34 Strezlecki Ave Sunshine VIC 3020",
    "addr:housenumber":"30-34",
    "addr:postcode":"3020",
    "addr:street":"Strezlecki Ave",
    "iso:country":"AU",
    "sg:address":"30-34 Strezlecki Ave",
    "sg:city":"Sunshine",
    "sg:classifiers":[
        {
            "category":"Wholesale",
            "subcategory":"Meat",
            "type":"Manufacturing & Wholesale Goods"
        }
    ],
    "sg:phone":"+61 3 9310 2726",
    "sg:postcode":"3020",
    "sg:province":"VIC",
    "sg:tags":[
        "packing",
        "exporting"
    ],
    "wof:name":"Australian Lamb Co Pty Ltd",
    "wof:placetype":"venue"
},
  "geometry": {"coordinates":[144.827057,-37.80872],"type":"Point"}
}