{
  "type": "Feature",
  "properties": {
    "iso:country":"AU",
    "sg:address":"33 Bouvardia Crs",
    "sg:city":"Frankston North",
    "sg:classifiers":[
        {
            "category":"Professional",
            "subcategory":"Art Services",
            "type":"Services"
        }
    ],
    "sg:phone":"+61 3 9766 4354",
    "sg:postcode":"3200",
    "sg:province":"VIC",
    "sg:tags":[
        "graphic",
        "designer"
    ],
    "wof:name":"Centaur Graphix",
    "wof:placetype":"venue"
},
  "geometry": {"coordinates":[145.159378,-38.118],"type":"Point"}
}