{
  "type": "Feature",
  "properties": {
    "addr:full":"56 Hulbert St Hove SA 5048",
    "addr:housenumber":"56",
    "addr:postcode":"5048",
    "addr:street":"Hulbert St",
    "iso:country":"AU",
    "sg:address":"56 Hulbert St",
    "sg:city":"Hove",
    "sg:classifiers":[
        {
            "category":"Building & Trades",
            "subcategory":"Construction",
            "type":"Services"
        }
    ],
    "sg:phone":"+61 8 8298 5835",
    "sg:postcode":"5048",
    "sg:province":"SA",
    "sg:tags":[
        "contractor"
    ],
    "wof:name":"Blazon Constructions Pty Ltd",
    "wof:placetype":"venue"
},
  "geometry": {"coordinates":[138.518463,-35.009655],"type":"Point"}
}