{
  "type": "Feature",
  "properties": {
    "addr:full":"33 Robertson Rd Bacchus Marsh VIC 3340",
    "addr:housenumber":"33",
    "addr:postcode":"3340",
    "addr:street":"Robertson Rd",
    "iso:country":"AU",
    "sg:address":"33 Robertson Rd",
    "sg:city":"Bacchus Marsh",
    "sg:classifiers":[
        {
            "category":"Banks & Credit Unions",
            "subcategory":"Bank",
            "type":"Services"
        }
    ],
    "sg:phone":"+61 419 517 897",
    "sg:postcode":"3340",
    "sg:province":"VIC",
    "sg:tags":[
        "line",
        "marking",
        "road"
    ],
    "wof:name":"M & M Line Marking",
    "wof:placetype":"venue"
},
  "geometry": {"coordinates":[144.43135100000001,-37.642784],"type":"Point"}
}