{
  "type": "Feature",
  "properties": {
    "addr:full":"1355 High St Malvern VIC 3144",
    "addr:housenumber":"1355",
    "addr:postcode":"3144",
    "addr:street":"High St",
    "iso:country":"AU",
    "sg:address":"1355 High St",
    "sg:city":"Malvern",
    "sg:classifiers":[
        {
            "category":"Health Services",
            "subcategory":"Doctor",
            "type":"Services"
        }
    ],
    "sg:phone":"+61 3 9804 6100",
    "sg:postcode":"3144",
    "sg:province":"VIC",
    "sg:tags":[
        "medical",
        "practitioner"
    ],
    "wof:name":"East Melbourne Radiology",
    "wof:placetype":"venue"
},
  "geometry": {"coordinates":[145.039916992,-37.8578567505],"type":"Point"}
}