{
  "type": "Feature",
  "properties": {
    "addr:full":"19d Collins St Morwell VIC 3840",
    "addr:housenumber":"19d",
    "addr:postcode":"3840",
    "addr:street":"Collins St",
    "iso:country":"AU",
    "sg:address":"19d Collins St",
    "sg:city":"Morwell",
    "sg:classifiers":[
        {
            "category":"Organizations",
            "subcategory":"Non-profit Organization",
            "type":"Services"
        }
    ],
    "sg:phone":"+61 3 5133 9440",
    "sg:postcode":"3840",
    "sg:province":"VIC",
    "sg:tags":[
        "support",
        "disability",
        "organisation"
    ],
    "wof:name":"Gippsland Citizen Advocacy",
    "wof:placetype":"venue"
},
  "geometry": {"coordinates":[146.39700317399999,-38.2349395752],"type":"Point"}
}