{
  "type": "Feature",
  "properties": {
    "iso:country":"AU",
    "sg:address":"Shp4/ 79 Church St",
    "sg:city":"Mudgee",
    "sg:classifiers":[
        {
            "category":"Fast Food",
            "type":"Food & Drink"
        }
    ],
    "sg:phone":"+61 2 6372 3768",
    "sg:postcode":"2850",
    "sg:province":"NSW",
    "sg:tags":[
        "away",
        "take"
    ],
    "wof:name":"Country Noodles",
    "wof:placetype":"venue"
},
  "geometry": {"coordinates":[149.58526599999999,-32.606995],"type":"Point"}
}