{
  "type": "Feature",
  "properties": {
    "iso:country":"AU",
    "sg:address":"357 Gold Creek Rd",
    "sg:city":"Brookfield",
    "sg:classifiers":[
        {
            "category":"Building & Trades",
            "subcategory":"Construction",
            "type":"Services"
        }
    ],
    "sg:phone":"+61 407 969 515",
    "sg:postcode":"4069",
    "sg:province":"QLD",
    "sg:tags":[
        "joiner",
        "carpenter"
    ],
    "wof:name":"Dunns Building",
    "wof:placetype":"venue"
},
  "geometry": {"coordinates":[152.906738281,-27.4704589844],"type":"Point"}
}