{
  "type": "Feature",
  "properties": {
    "addr:full":"Shop 10, 2 Surf Rd Cronulla NSW 2230",
    "addr:housenumber":"shop 10 2",
    "addr:postcode":"2230",
    "addr:street":"Surf Rd",
    "iso:country":"AU",
    "sg:address":"Shop 10, 2 Surf Rd",
    "sg:city":"Cronulla",
    "sg:classifiers":[
        {
            "category":"Arts & Performance",
            "subcategory":"Art Gallery",
            "type":"Entertainment"
        }
    ],
    "sg:phone":"+61 2 9523 6169",
    "sg:postcode":"2230",
    "sg:province":"NSW",
    "wof:name":"Cronulla Gallery",
    "wof:placetype":"venue"
},
  "geometry": {"coordinates":[151.153106689,-34.0547599792],"type":"Point"}
}