{
  "type": "Feature",
  "properties": {
    "iso:country":"AU",
    "sg:address":"2 Fison Ave",
    "sg:city":"Eagle Farm",
    "sg:classifiers":[
        {
            "category":"Retail",
            "subcategory":"Auto Repair",
            "type":"Services"
        }
    ],
    "sg:phone":"+61 7 3268 2326",
    "sg:postcode":"4009",
    "sg:province":"QLD",
    "sg:tags":[
        "repairer",
        "motor",
        "engineer"
    ],
    "wof:name":"Burgess Motors",
    "wof:placetype":"venue"
},
  "geometry": {"coordinates":[153.08558654800001,-27.4357433319],"type":"Point"}
}