{
  "type": "Feature",
  "properties": {
    "iso:country":"AU",
    "sg:address":"Westminster Junior Primary School 22 Ungaroo Rd",
    "sg:city":"Westminster",
    "sg:classifiers":[
        {
            "category":"Education",
            "subcategory":"School",
            "type":"Public Place"
        }
    ],
    "sg:phone":"+61 8 9349 4290",
    "sg:postcode":"6061",
    "sg:province":"WA",
    "sg:tags":[
        "state",
        "except",
        "nsw"
    ],
    "wof:name":"Schools Government (Public)",
    "wof:placetype":"venue"
},
  "geometry": {"coordinates":[115.837753296,-31.8716144562],"type":"Point"}
}