{
  "type": "Feature",
  "properties": {
    "addr:full":"PO Box 196 Bull Creek WA 6149",
    "addr:postcode":"6149",
    "iso:country":"AU",
    "sg:address":"PO Box 196",
    "sg:city":"Bull Creek",
    "sg:classifiers":[
        {
            "category":"Wholesale",
            "subcategory":"Medical Equipment & Supplies",
            "type":"Manufacturing & Wholesale Goods"
        }
    ],
    "sg:phone":"+61 8 9332 7271",
    "sg:postcode":"6149",
    "sg:province":"WA",
    "sg:tags":[
        "aid",
        "care",
        "health",
        "home"
    ],
    "wof:name":"Personal Delivery Services",
    "wof:placetype":"venue"
},
  "geometry": {"coordinates":[115.86541,-32.056782],"type":"Point"}
}