{
  "type": "Feature",
  "properties": {
    "addr:full":"1 Grange Rd Kalorama VIC 3766",
    "addr:housenumber":"1",
    "addr:postcode":"3766",
    "addr:street":"Grange Rd",
    "iso:country":"AU",
    "sg:address":"1 Grange Rd",
    "sg:city":"Kalorama",
    "sg:classifiers":[
        {
            "category":"Building & Trades",
            "subcategory":"Construction",
            "type":"Services"
        }
    ],
    "sg:phone":"+61 3 9728 6516",
    "sg:postcode":"3766",
    "sg:province":"VIC",
    "sg:tags":[
        "stonework",
        "stone",
        "mason"
    ],
    "wof:name":"Junkaris Garry",
    "wof:placetype":"venue"
},
  "geometry": {"coordinates":[145.37811279300001,-37.8172683716],"type":"Point"}
}