{
  "type": "Feature",
  "properties": {
    "addr:full":"Eton St Sutherland NSW 2232",
    "addr:postcode":"2232",
    "addr:street":"Eton St",
    "iso:country":"AU",
    "sg:address":"Eton St",
    "sg:city":"Sutherland",
    "sg:classifiers":[
        {
            "category":"Food & Beverages",
            "subcategory":"Fruits & Vegetables",
            "type":"Retail Goods"
        }
    ],
    "sg:phone":"+61 2 9545 0378",
    "sg:postcode":"2232",
    "sg:province":"NSW",
    "sg:tags":[
        "greengrocer",
        "fruiterer"
    ],
    "wof:name":"Best Fresh Farm Markets",
    "wof:placetype":"venue"
},
  "geometry": {"coordinates":[151.05743408199999,-34.0387153625],"type":"Point"}
}