{
  "type": "Feature",
  "properties": {
    "iso:country":"AU",
    "sg:address":"16 Sydney St",
    "sg:city":"Kilmore",
    "sg:classifiers":[
        {
            "category":"Restaurant",
            "type":"Food & Drink"
        }
    ],
    "sg:phone":"+61 3 5782 1991",
    "sg:postcode":"3764",
    "sg:province":"VIC",
    "wof:name":"Kilmore Town Hall",
    "wof:placetype":"venue"
},
  "geometry": {"coordinates":[144.951828003,-37.2942619324],"type":"Point"}
}