{
  "type": "Feature",
  "properties": {
    "addr:full":"PO Box 2104 Carrum Downs VIC 3201",
    "addr:postcode":"3201",
    "iso:country":"AU",
    "sg:address":"PO Box 2104",
    "sg:city":"Carrum Downs",
    "sg:classifiers":[
        {
            "category":"Health Services",
            "subcategory":"Doctor",
            "type":"Services"
        }
    ],
    "sg:phone":"+61 419 580 805",
    "sg:postcode":"3201",
    "sg:province":"VIC",
    "sg:tags":[
        "occupational",
        "safety"
    ],
    "wof:name":"Business Unlimited",
    "wof:placetype":"venue"
},
  "geometry": {"coordinates":[145.17598000000001,-38.09708],"type":"Point"}
}