{
  "type": "Feature",
  "properties": {
    "addr:full":"Vaughan St Gosford NSW 2250",
    "addr:postcode":"2250",
    "addr:street":"Vaughan St",
    "iso:country":"AU",
    "sg:address":"Vaughan St",
    "sg:city":"Gosford",
    "sg:classifiers":[
        {
            "category":"Social Services",
            "subcategory":"Child Care",
            "type":"Services"
        }
    ],
    "sg:phone":"+61 2 4324 5675",
    "sg:postcode":"2250",
    "sg:province":"NSW",
    "wof:name":"Gosford & District Vacation Care",
    "wof:placetype":"venue"
},
  "geometry": {"coordinates":[151.34071350100001,-33.4306259155],"type":"Point"}
}