{
  "type": "Feature",
  "properties": {
    "addr:full":"4 - 6 Great Western Hwy Parramatta NSW 2150",
    "addr:housenumber":"6",
    "addr:postcode":"2150",
    "addr:street":"Great Western Hwy",
    "iso:country":"AU",
    "sg:address":"4 - 6 Great Western Hwy",
    "sg:city":"Parramatta",
    "sg:classifiers":[
        {
            "category":"Retail",
            "subcategory":"Auto Repair",
            "type":"Services"
        }
    ],
    "sg:phone":"+61 2 9689 2277",
    "sg:postcode":"2150",
    "sg:province":"NSW",
    "sg:tags":[
        "repairer",
        "motor",
        "engineer"
    ],
    "wof:name":"Midas",
    "wof:placetype":"venue"
},
  "geometry": {"coordinates":[150.99220275900001,-33.8186302185],"type":"Point"}
}