{
  "type": "Feature",
  "properties": {
    "addr:full":"Maitland Rd Muswellbrook NSW 2333",
    "addr:postcode":"2333",
    "addr:street":"Maitland Rd",
    "iso:country":"AU",
    "sg:address":"Maitland Rd",
    "sg:city":"Muswellbrook",
    "sg:classifiers":[
        {
            "category":"Shopping",
            "subcategory":"Computers & Home Electronics",
            "type":"Retail Goods"
        }
    ],
    "sg:phone":"+61 2 6543 4483",
    "sg:postcode":"2333",
    "sg:province":"NSW",
    "sg:tags":[
        "hardware",
        "equipment"
    ],
    "wof:name":"Zanatos Enterprises",
    "wof:placetype":"venue"
},
  "geometry": {"coordinates":[150.88752746599999,-32.268901825],"type":"Point"}
}